Workbook

Sheet README
A1: 南電（8046.TW）收支與估值模型 v0.1（AI 半導體 Project：載板與 PCB 次產業） 2026-10-25
A2: 版本：v0.1（初版）。樣板：unimicron/。AI 加速器載板的每顆金額、Ibiden 份額與非 NVIDIA 權重讀 ibiden/dist，欣興份額讀 unimicron/dist（本專案權威）；三家份額合計在 Units 頁檢查。
A3: 模型命題：南電的 ABF 載板營收＝MIN（需求, 產能）；需求以網通交換器載板為主（隨 markets/network 的交換晶片與交換器市場），加上 AI 加速器顆數 × 每顆載板金額（與 Ibiden、欣興同口徑）× 南電份額（個位數）與非 AI ABF；產能 2026–28 年靠去瓶頸與昆山廠爬坡，新廠約 2029 年。BT 載板（約三成營收）以漲價為主。資本支出低（2026 年約 40 億）、折舊約 70 億。
A4: 核心問題：2026 年下半年的漲價與交換器載板需求，能不能讓毛利率從 FY2026 約 27% 再升、EPS 在 FY2027–28 倍增；約 1,265 元的股價隱含什麼路徑。
A6: 會計年度＝日曆年，FY(t)＝CY(t)，不平移。預測期 FY2027–FY2029 由驅動因子推導；FY2030 起為收斂法，非驅動因子推導（延伸到 FY2032；PL 頁灰底）。金額：十億新台幣；EPS：新台幣（基本、歸屬母公司）。3Q26 財報約 10 月底公布，本版只納入 3Q26 營收實績。
A8: 驅動因子 → 推導量（全部唯讀上游，不修改）
A9: 加速器載板：markets/network 的 NVIDIA 與非 NVIDIA 顆數 × tsmc 同字母情境係數 × 每顆 NVIDIA 載板金額（Ibiden 模型 US$215 × 面積層數 +18%／年 × Ibiden 溢價指數）× 南電份額（NVIDIA 2%→4%、非 NVIDIA 金額 5%→7%，Assumed）× 漲價年度化 1.15。
A10: 其他 AI 載板（交換器為主）＝FY2026 AI 載板（ABF × 65%）− 加速器載板（校準殘差），之後 × 交換晶片與交換器市場成長 ^ 0.5 × 情境係數 × 溢價 × 漲價年度化；非 AI ABF +3%。ABF 產能指數 1.20／1.35／1.60（Assumed）× 組合 +5%／年。BT 年增依情境（A 30%／10%／5%、B 25%／5%／3%、C 15%／0%／0%），PCB 持平。
A11: 毛利＝FY2026 錨點＋ABF 現金毛利增量（50%）＋其他產品現金毛利增量（40%）＋漲價溢價營收 − 折舊增量；折舊＝前一年 ×（1 − 1／8 年）＋前一年資本支出 ÷ 8 年；資本支出 140／180／120 億（三情境相同）。營業費用彈性 0.6；業外每年 6 億；稅率 21%；股數持平 6.46 億股。
A12: 校準：FY2026 ＝ 1Q26、2Q26 財報實績（EPS 2.03、3.50）＋3Q26 營收實績 163.8 億＋3Q26 毛利率 30%、4Q26 營收季增 10%、毛利率 32.5%（Assumed）。不用券商數字（只在 Recon 對帳）。
A13: 估值：Val 第 0 節目標價＝0.5 × DCF 目標價（股東現金流＝每股（淨利＋折舊－資本支出），FY2027–32 明確期＋永續，r 10%、g 4%，三情境權重 0.3／0.5／0.2，負值取 0）＋0.5 × Comparable 目標價（欣興、景碩、Ibiden、三星電機、AT&S 前瞻 P/E 中位數 × 12 個月後前瞻 EPS；無 A 股）；另列 Comparable 單獨目標價、市場共識目標價與差距拆解。十年 P/E 規則值 × FY2027 EPS 保留為參考（不是目標價）。本版未做先驗，無 Andy 合理 P/E 對照。
A14: 情境與行業一致：A／B／C 讀 tsmc 同字母顆數係數（＝markets/memory SCEN_UNITS，建置時核對）；交換器市場讀 markets/network（單一路徑 × 同字母係數）；公司特有變數只有 BT 年增隨情境，A 最有利、C 最不利。
... A17: 已知限制：(1) 加速器、交換器與 CPU 載板的拆分公司未揭露，其他 AI 載板為校準殘差；(2) 份額、產能指數、漲價年度化皆為 Assumed，與 Ibiden、欣興合計只做上限檢查；(3) 毛利用現金流通率近似，未建分廠稼動率；(4) AMD 伺服器 CPU 認證（美銀：成功則 2027 年逾兩成營收）未建入；(5) 新廠資本支出未定，DCF 現金流可能偏高；(6) 十年 P/E 2016–2018 年虧損不計，其餘與盈餘反向；(7) FactSet 共識為 2026-06；(8) 3Q26 財報（約 10 月底）後更新錨點。

Sheet In
A1: In — 輸入（藍字；基準欄 E，低 D、高 F）。金額：十億新台幣（NT$B）；顆數：百萬顆；比例：%。每個輸入附兩個來源（找不到者寫「未找到」）；公司原文算一個
A2: 標記：Verified／Interested-party／Analogy／Assumed／Derived；Analogy、Assumed 給低／高區間，不當點估計（放情境或 Sens）。SemiAnalysis 未使用。公司數字經資料商（stockanalysis）與媒體轉載；公司說法為 Interested-party；券商、媒體、資料商為 Interested-party
A3: 鍵 | B3: 項目 | C3: 單位 | D3: 低 | E3: 基準 | F3: 高 | G3: 標記 | H3: 來源1 | I3: 來源2／說明
A4: A. AI 加速器顆數、AI IT 資本支出與交換器市場（讀 markets/network、tsmc 成品；唯讀，不自行重估）
A5: u_bw_26 | B5: NVIDIA Blackwell（B200／B300） 顆數 2026 | C5: 百萬顆 | E5: 5.4 | G5: Derived | H5: markets/network/dist/20261023_AI網通市場模型_v0.2.2.xlsx｜In!E5 | I5: 唯讀上游；與 Ibiden、欣興、台積電模型同一份顆數
A6: u_bw_27 | B6: NVIDIA Blackwell（B200／B300） 顆數 2027 | C6: 百萬顆 | E6: 2.4 | G6: Derived | H6: markets/network/dist/20261023_AI網通市場模型_v0.2.2.xlsx｜In!E6 | I6: 唯讀上游；與 Ibiden、欣興、台積電模型同一份顆數
A7: u_bw_28 | B7: NVIDIA Blackwell（B200／B300） 顆數 2028 | C7: 百萬顆 | E7: 0.5 | G7: Derived | H7: markets/network/dist/20261023_AI網通市場模型_v0.2.2.xlsx｜In!E7 | I7: 唯讀上游；與 Ibiden、欣興、台積電模型同一份顆數
A8: g29_bw | B8: NVIDIA Blackwell（B200／B300） 2029 顆數成長 | C8: % | E8: -0.5 | G8: Derived | H8: markets/network/dist/20261023_AI網通市場模型_v0.2.2.xlsx｜In!E8 | I8: 同上
A9: u_rb_26 | B9: NVIDIA Rubin 顆數 2026 | C9: 百萬顆 | E9: 1.7 | G9: Derived | H9: markets/network/dist/20261023_AI網通市場模型_v0.2.2.xlsx｜In!E9 | I9: 唯讀上游；與 Ibiden、欣興、台積電模型同一份顆數
A10: u_rb_27 | B10: NVIDIA Rubin 顆數 2027 | C10: 百萬顆 | E10: 7 | G10: Derived | H10: markets/network/dist/20261023_AI網通市場模型_v0.2.2.xlsx｜In!E10 | I10: 唯讀上游；與 Ibiden、欣興、台積電模型同一份顆數
A11: u_rb_28 | B11: NVIDIA Rubin 顆數 2028 | C11: 百萬顆 | E11: 7 | G11: Derived | H11: markets/network/dist/20261023_AI網通市場模型_v0.2.2.xlsx｜In!E11 | I11: 唯讀上游；與 Ibiden、欣興、台積電模型同一份顆數
A12: g29_rb | B12: NVIDIA Rubin 2029 顆數成長 | C12: % | E12: 0.15 | G12: Derived | H12: markets/network/dist/20261023_AI網通市場模型_v0.2.2.xlsx｜In!E12 | I12: 同上
A13: u_ru_26 | B13: NVIDIA Rubin Ultra 顆數 2026 | C13: 百萬顆 | E13: 0 | G13: Derived | H13: markets/network/dist/20261023_AI網通市場模型_v0.2.2.xlsx｜In!E13 | I13: 唯讀上游；與 Ibiden、欣興、台積電模型同一份顆數
A14: u_ru_27 | B14: NVIDIA Rubin Ultra 顆數 2027 | C14: 百萬顆 | E14: 0.3 | G14: Derived | H14: markets/network/dist/20261023_AI網通市場模型_v0.2.2.xlsx｜In!E14 | I14: 唯讀上游；與 Ibiden、欣興、台積電模型同一份顆數
A15: u_ru_28 | B15: NVIDIA Rubin Ultra 顆數 2028 | C15: 百萬顆 | E15: 2 | G15: Derived | H15: markets/network/dist/20261023_AI網通市場模型_v0.2.2.xlsx｜In!E15 | I15: 唯讀上游；與 Ibiden、欣興、台積電模型同一份顆數
A16: g29_ru | B16: NVIDIA Rubin Ultra 2029 顆數成長 | C16: % | E16: 0.15 | G16: Derived | H16: markets/network/dist/20261023_AI網通市場模型_v0.2.2.xlsx｜In!E16 | I16: 同上
... A50: um29_C | B50: 情境 C：2029 顆數 ÷ 基準 | C50: x | E50: 0.6 | G50: Assumed | H50: tsmc/dist/20261025_台積電模型_v0.3.xlsx｜In!E42 | I50: 同上
A51: B. 每顆加速器載板金額與份額（口徑與 Ibiden、欣興一致；兩者數字唯讀取自各自 dist）
A52: v26 | B52: FY2026 每顆 NVIDIA 加速器載板金額（全市場；Ibiden 模型校準） | C52: US$ | E52: 215.3086 | G52: Derived | H52: ibiden/dist/20261025_Ibiden模型_v0.2.xlsx｜Units!C8 | I52: Ibiden 模型：Ibiden 每顆營收 ÷ 份額 70%（BofA，Interested-party）
A53: g_asp | B53: 每顆載板金額年增（面積、層數；Ibiden 模型） | C53: % | D53: 0.1 | E53: 0.18 | F53: 0.22 | G53: Analogy | H53: ibiden/dist/20261025_Ibiden模型_v0.2.xlsx｜In!E50 | I53: Ibiden 路線圖 2026 年 90×90 mm → 2028 年 110×110 mm（經 Ibiden 模型）
A54: ibpp_27 | B54: ABF 價格溢價指數 2027（FY2026＝1；Ibiden 模型） | C54: x | D54: 0.95 | E54: 1 | F54: 1.05 | G54: Assumed | H54: ibiden/dist/20261025_Ibiden模型_v0.2.xlsx｜In!E55 | I54: 全市場短缺溢價；新產能到位後回落（Ibiden 模型；欣興模型同值）
A55: ibrel_27 | B55: Ibiden NVIDIA 份額 2027 ÷ 2026（Ibiden 模型） | C55: x | E55: 0.95 | G55: Assumed | H55: ibiden/dist/20261025_Ibiden模型_v0.2.xlsx｜In!E51 | I55: Units 頁份額合計檢查用
A56: ibpp_28 | B56: ABF 價格溢價指數 2028（FY2026＝1；Ibiden 模型） | C56: x | D56: 0.85 | E56: 0.95 | F56: 1.05 | G56: Assumed | H56: ibiden/dist/20261025_Ibiden模型_v0.2.xlsx｜In!E56 | I56: 同上
A57: ibrel_28 | B57: Ibiden NVIDIA 份額 2028 ÷ 2026（Ibiden 模型） | C57: x | E57: 0.88 | G57: Assumed | H57: ibiden/dist/20261025_Ibiden模型_v0.2.xlsx｜In!E52 | I57: Units 頁份額合計檢查用
A58: ibpp_29 | B58: ABF 價格溢價指數 2029（FY2026＝1；Ibiden 模型） | C58: x | D58: 0.75 | E58: 0.9 | F58: 1 | G58: Assumed | H58: ibiden/dist/20261025_Ibiden模型_v0.2.xlsx｜In!E57 | I58: 同上
A59: ibrel_29 | B59: Ibiden NVIDIA 份額 2029 ÷ 2026（Ibiden 模型） | C59: x | E59: 0.85 | G59: Assumed | H59: ibiden/dist/20261025_Ibiden模型_v0.2.xlsx｜In!E53 | I59: Units 頁份額合計檢查用
A60: ib_sh26 | B60: Ibiden 占 NVIDIA 加速器載板 FY2026（Ibiden 模型假設） | C60: % | D60: 0.7 | E60: 0.7 | F60: 0.8 | G60: Interested-party | H60: ibiden/dist/20261025_Ibiden模型_v0.2.xlsx｜Units!C8（列標籤：假設 FY2026 份額 70%） | I60: BofA：Ibiden 70–80%
A61: ib_w_ot | B61: Ibiden 非 NVIDIA 權重（份額 × 每顆金額，相對 NVIDIA；Ibiden 模型） | C61: x | D61: 0.2 | E61: 0.4 | F61: 0.6 | G61: Assumed | H61: ibiden/dist/20261025_Ibiden模型_v0.2.xlsx｜In!E48 | I61: Units 頁：÷ v_ot 即 Ibiden 非 NVIDIA 份額
A62: v_ot | B62: 非 NVIDIA 加速器每顆載板金額 ÷ NVIDIA（欣興模型同值） | C62: x | D62: 0.6 | E62: 0.8 | F62: 1 | G62: Assumed | H62: TPU、Trainium、MI 系列封裝面積接近 GPU；量化：未找到 | I62: 與欣興模型 v_ot 相同
A63: un_nv_26 | B63: 欣興占 NVIDIA 加速器載板 2026（欣興模型） | C63: % | E63: 0.25 | G63: Assumed | H63: unimicron/dist/20261025_欣興模型_v0.1.xlsx｜In!E59 | I63: Units 頁份額合計檢查用
A64: un_ot_26 | B64: 欣興占非 NVIDIA 加速器載板（金額）2026（欣興模型） | C64: % | E64: 0.3 | G64: Assumed | H64: unimicron/dist/20261025_欣興模型_v0.1.xlsx｜In!E63 | I64: 同上
A65: un_nv_27 | B65: 欣興占 NVIDIA 加速器載板 2027（欣興模型） | C65: % | E65: 0.27 | G65: Assumed | H65: unimicron/dist/20261025_欣興模型_v0.1.xlsx｜In!E60 | I65: Units 頁份額合計檢查用
A66: un_ot_27 | B66: 欣興占非 NVIDIA 加速器載板（金額）2027（欣興模型） | C66: % | E66: 0.31 | G66: Assumed | H66: unimicron/dist/20261025_欣興模型_v0.1.xlsx｜In!E64 | I66: 同上
A67: un_nv_28 | B67: 欣興占 NVIDIA 加速器載板 2028（欣興模型） | C67: % | E67: 0.29 | G67: Assumed | H67: unimicron/dist/20261025_欣興模型_v0.1.xlsx｜In!E61 | I67: Units 頁份額合計檢查用
A68: un_ot_28 | B68: 欣興占非 NVIDIA 加速器載板（金額）2028（欣興模型） | C68: % | E68: 0.32 | G68: Assumed | H68: unimicron/dist/20261025_欣興模型_v0.1.xlsx｜In!E65 | I68: 同上
A69: un_nv_29 | B69: 欣興占 NVIDIA 加速器載板 2029（欣興模型） | C69: % | E69: 0.3 | G69: Assumed | H69: unimicron/dist/20261025_欣興模型_v0.1.xlsx｜In!E62 | I69: Units 頁份額合計檢查用
A70: un_ot_29 | B70: 欣興占非 NVIDIA 加速器載板（金額）2029（欣興模型） | C70: % | E70: 0.33 | G70: Assumed | H70: unimicron/dist/20261025_欣興模型_v0.1.xlsx｜In!E66 | I70: 同上
A71: sh_nv_26 | B71: 南電占 NVIDIA 加速器載板 2026 | C71: % | D71: 0.01 | E71: 0.02 | F71: 0.03 | G71: Assumed | H71: 凱基 PCB 產業報告 2026-07-20（Interested-party）：客戶含博通、輝達、超微、蘋果（份額未揭露） | I71: 南電 AI 載板以網通交換器為主，GPU 載板份額小（brodoginvestment 南電深度分析（引述券商報告；Interested-party））；量化：未找到
A72: sh_nv_27 | B72: 南電占 NVIDIA 加速器載板 2027 | C72: % | D72: 0.01 | E72: 0.03 | F72: 0.05 | G72: Assumed | H72: Ibiden、欣興合計 95%→約 90%，其餘由南電、三星電機分食（Units 頁） | I72: —
A73: sh_nv_28 | B73: 南電占 NVIDIA 加速器載板 2028 | C73: % | D73: 0.01 | E73: 0.04 | F73: 0.06 | G73: Assumed | H73: Ibiden、欣興合計 95%→約 90%，其餘由南電、三星電機分食（Units 頁） | I73: —
A74: sh_nv_29 | B74: 南電占 NVIDIA 加速器載板 2029 | C74: % | D74: 0.01 | E74: 0.04 | F74: 0.06 | G74: Assumed | H74: Ibiden、欣興合計 95%→約 90%，其餘由南電、三星電機分食（Units 頁） | I74: —
A75: sh_ot_26 | B75: 南電占非 NVIDIA 加速器載板（金額）2026 | C75: % | D75: 0.03 | E75: 0.05 | F75: 0.08 | G75: Assumed | H75: TechNews 2026-10-02（美銀報告）：調配昆山廠產能支應博通需求（ASIC） | I75: 合計檢查：Ibiden 50%＋欣興 30%＋南電 5%＝85%，其餘為三星電機、景碩、AT&S（Units 頁）
A76: sh_ot_27 | B76: 南電占非 NVIDIA 加速器載板（金額）2027 | C76: % | D76: 0.03 | E76: 0.06 | F76: 0.09 | G76: Assumed | H76: 同上 | I76: —
A77: sh_ot_28 | B77: 南電占非 NVIDIA 加速器載板（金額）2028 | C77: % | D77: 0.03 | E77: 0.07 | F77: 0.1 | G77: Assumed | H77: 同上 | I77: —
A78: sh_ot_29 | B78: 南電占非 NVIDIA 加速器載板（金額）2029 | C78: % | D78: 0.03 | E78: 0.07 | F78: 0.1 | G78: Assumed | H78: 同上 | I78: —
A79: C. FY2026 產品組合與 AI 占比（公司未按季揭露；券商與法說摘要推全年）
A80: mx_abf | B80: FY2026 ABF 載板 ÷ 營收 | C80: % | D80: 0.53 | E80: 0.58 | F80: 0.62 | G80: Interested-party | H80: 凱基 PCB 產業報告 2026-07-20（Interested-party）：1Q26 ABF 約 55–60%、BT 約 30–35% | I80: vocus 4Q25 法說摘要（2026-03-17）：2025 年 ABF 50–55%、BT 約 30%、PCB 10–15%
A81: mx_bt | B81: FY2026 BT 載板 ÷ 營收（其餘為 PCB） | C81: % | D81: 0.28 | E81: 0.32 | F81: 0.35 | G81: Interested-party | H81: 凱基 PCB 產業報告 2026-07-20（Interested-party） | I81: brodoginvestment 南電深度分析（引述券商報告；Interested-party）：ABF 約 60%、BT 約 30%
A82: ai_abf | B82: FY2026 AI 與資料中心 ÷ ABF 營收 | C82: % | D82: 0.55 | E82: 0.65 | F82: 0.75 | G82: Interested-party | H82: 凱基 PCB 產業報告 2026-07-20（Interested-party）：AI 與資料中心（800G 交換器）約占 ABF 營收 60% | I82: 富果 1Q26 法說摘要（2026-06-12，AI 摘要）：1Q26 應用別網通 49%、AI 與 HPC 16%（全公司）
A83: D. 需求與產能（FY2027 起）
A84: el_o | B84: 其他 AI 載板（交換器、伺服器 CPU、網通 ASIC）對交換晶片與交換器市場的彈性 | C84: x | D84: 0.3 | E84: 0.5 | F84: 0.8 | G84: Assumed | H84: 其他 AI 載板＝FY2026 AI 載板 − 加速器載板（校準殘差）；隨交換器市場成長但低於等比例（單價已由溢價另計） | I84: 研究報告 A：南電占高階 800G／1.6T 交換晶片 ABF 逾 70%（brodoginvestment 南電深度分析（引述券商報告；Interested-party））
A85: g_nai | B85: 非 AI ABF（PC、一般伺服器、車用）年增 | C85: % | D85: -0.02 | E85: 0.03 | F85: 0.06 | G85: Assumed | H85: 富果 1Q26 法說摘要（2026-06-12，AI 摘要）：電腦 17%（零組件缺貨限制）、車用 6%（需求弱） | I85: —
A86: cap_27 | B86: ABF 產能指數 2027（FY2026 平均＝1） | C86: x | D86: 1.1 | E86: 1.2 | F86: 1.3 | G86: Assumed | H86: 凱基 PCB 產業報告 2026-07-20（Interested-party）：新產能 2029 年到位，2026–28 年主要靠產能升級；1H26 ABF 稼動率約 80–85% | I86: 三立 2026-07-27（2Q26 營收、法人預估、產能）：錦興、樹林滿載，昆山稼動率約 50%，以去瓶頸擴產
A87: cap_28 | B87: ABF 產能指數 2028（FY2026 平均＝1） | C87: x | D87: 1.2 | E87: 1.35 | F87: 1.5 | G87: Assumed | H87: 同上 | I87: 公司：持續擴充 ABF，含新建廠，時程待董事會（富果 1Q26 法說摘要（2026-06-12，AI 摘要））
A88: cap_29 | B88: ABF 產能指數 2029（FY2026 平均＝1） | C88: x | D88: 1.35 | E88: 1.6 | F88: 1.85 | G88: Assumed | H88: 同上 | I88: —
A89: g_mix | B89: 每單位產能營收年增（層數、尺寸組合） | C89: % | D89: 0 | E89: 0.05 | F89: 0.08 | G89: Assumed | H89: 公司：產品朝 140 mm 以上大尺寸、30 層以上（2028 年後）發展（vocus 4Q25 法說摘要（2026-03-17）） | I89: 與欣興模型同值
A90: carry | B90: 南電漲價年度化（CY2026 基期含上半年低價；FY2027 起 ×(1＋此值)） | C90: % | D90: 0.08 | E90: 0.15 | F90: 0.22 | G90: Assumed | H90: FY2026 毛利率由 1Q26 15.8% 升到 4Q26 約 32%（美銀估），季營收由 111.8 億升到約 180 億；4Q26 年化 ÷ FY2026 營收約 1.22（Q 頁，Derived；含量增） | I90: 研究報告：ABF 每平方呎單價 2026 +35%、2027 +57%（brodoginvestment 南電深度分析（引述券商報告；Interested-party），Interested-party）
A91: g_bt27_A | B91: BT 載板年增 FY2027（情境 A；公司特有，A 最有利） | C91: % | E91: 0.3 | G91: Assumed | H91: TechNews 2026-10-02（美銀報告）：BT 4Q26 漲價個位數、1Q27 再漲 20% 以上 | I91: TechNews 2026-10-05（大和報告；8 月自結獲利）：BT 1Q27 季增最高 20%；台、韓部分廠商縮減 BT 產能（凱基 PCB 產業報告 2026-07-20（Interested-party））
A92: g_bt28_A | B92: BT 載板年增 FY2028（情境 A；公司特有，A 最有利） | C92: % | E92: 0.1 | G92: Assumed | H92: 同上 | I92: —
A93: g_bt29_A | B93: BT 載板年增 FY2029（情境 A；公司特有，A 最有利） | C93: % | E93: 0.05 | G93: Assumed | H93: 同上 | I93: —
A94: g_bt27_B | B94: BT 載板年增 FY2027（情境 B；公司特有，A 最有利） | C94: % | E94: 0.25 | G94: Assumed | H94: 同上 | I94: —
A95: g_bt28_B | B95: BT 載板年增 FY2028（情境 B；公司特有，A 最有利） | C95: % | E95: 0.05 | G95: Assumed | H95: 同上 | I95: —
A96: g_bt29_B | B96: BT 載板年增 FY2029（情境 B；公司特有，A 最有利） | C96: % | E96: 0.03 | G96: Assumed | H96: 同上 | I96: —
A97: g_bt27_C | B97: BT 載板年增 FY2027（情境 C；公司特有，A 最有利） | C97: % | E97: 0.15 | G97: Assumed | H97: 同上 | I97: —
A98: g_bt28_C | B98: BT 載板年增 FY2028（情境 C；公司特有，A 最有利） | C98: % | E98: 0 | G98: Assumed | H98: 同上 | I98: —
A99: g_bt29_C | B99: BT 載板年增 FY2029（情境 C；公司特有，A 最有利） | C99: % | E99: 0 | G99: Assumed | H99: 同上 | I99: —
A100: g_pcb | B100: PCB（一般電路板）年增 | C100: % | D100: -0.05 | E100: 0 | F100: 0.03 | G100: Assumed | H100: 凱基 PCB 產業報告 2026-07-20（Interested-party）：PCB 以消費型為主且虧損，公司計畫產能轉向 BT | I100: —
A101: E. 毛利、折舊、費用與淨利（FY2027 起）
A102: ft_abf | B102: ABF 營收增量的現金毛利率（扣除漲價溢價後） | C102: % | D102: 0.4 | E102: 0.5 | F102: 0.6 | G102: Assumed | H102: TechNews 2026-10-02（美銀報告）：2027 年 ABF 毛利率約 50% | I102: 與欣興模型同值
A103: ft_oth | B103: 其他產品（BT、PCB）營收增量的現金毛利率 | C103: % | D103: 0.25 | E103: 0.4 | F103: 0.55 | G103: Assumed | H103: BT 成長以漲價為主（漲價幾乎全數落在毛利）；PCB 虧損 | I103: —
A104: cx27 | B104: 資本支出 FY2027（三情境相同；公司特有） | C104: NT$B | D104: 6 | E104: 14 | F104: 20 | G104: Assumed | H104: 凱基 PCB 產業報告 2026-07-20（Interested-party）：2025–28 年資本支出約 US$12.8 億（約 416 億新台幣；七家載板廠第六） | I104: 公司：2026 年約 40 億，新廠待董事會決議（富果 1Q26 法說摘要（2026-06-12，AI 摘要））
A105: cx28 | B105: 資本支出 FY2028（三情境相同；公司特有） | C105: NT$B | D105: 6 | E105: 18 | F105: 24 | G105: Assumed | H105: 同上 | I105: —
A106: cx29 | B106: 資本支出 FY2029（三情境相同；公司特有） | C106: NT$B | D106: 6 | E106: 12 | F106: 20 | G106: Assumed | H106: 同上 | I106: —
A107: capex26 | B107: FY2026 資本支出（公司計畫） | C107: NT$B | E107: 4 | G107: Interested-party | H107: 富果 1Q26 法說摘要（2026-06-12，AI 摘要）：2026 年約 40 億 | I107: TTM 至 2026-06：19.3 億（stockanalysis 現金流量表）
A108: da26 | B108: FY2026 折舊攤提 | C108: NT$B | E108: 7.1 | G108: Interested-party | H108: stockanalysis 現金流量表：TTM 至 2026-06 71.0 億 | I108: 研究報告 C：2026 年 71 億、2028 年 58 億（brodoginvestment 南電深度分析（引述券商報告；Interested-party））
A109: life | B109: 新增資產平均折舊年限 | C109: 年 | D109: 6 | E109: 8 | F109: 10 | G109: Assumed | H109: 載板設備與廠房混合；與欣興模型同值 | I109: 會計年限：未找到
A110: phi | B110: 營業費用成長對營收成長的彈性 | C110: x | D110: 0.3 | E110: 0.6 | F110: 1 | G110: Assumed | H110: 1Q26 營業費用 4.19 億、2Q26 4.61 億（營收季增 21%；Q 頁推得） | I110: —
A111: nonop27 | B111: 營業外淨額 FY2027 | C111: NT$B | D111: 0 | E111: 0.6 | F111: 1.2 | G111: Assumed | H111: 1Q26 2.5 億、2Q26 0.8 億（stockanalysis 推得；含匯兌） | I111: 利息收入（現金部位）（Assumed）
A112: nonop28 | B112: 營業外淨額 FY2028 | C112: NT$B | D112: 0 | E112: 0.6 | F112: 1.2 | G112: Assumed | H112: 同上 | I112: —
A113: nonop29 | B113: 營業外淨額 FY2029 | C113: NT$B | D113: 0 | E113: 0.6 | F113: 1.2 | G113: Assumed | H113: 同上 | I113: —
A114: tax | B114: 所得稅 ÷ 稅前利益 | C114: % | D114: 0.18 | E114: 0.21 | F114: 0.24 | G114: Derived | H114: 1H26：稅前 45.7、淨利 35.7 億 → 21.9%（stockanalysis 推得） | I114: 2Q26 24.0%、1Q26 18.1%；營所稅 20%
A115: sh_g | B115: 股數年變動 | C115: % | D115: 0 | E115: 0 | F115: 0.01 | G115: Assumed | H115: 流通股數 6.4617 億股（stockanalysis） | I115: 無可轉債資訊：未找到
A116: F. FY2026 錨點（1H26 實績＋3Q26 營收實績＋假設）
A117: q3_rev | B117: 3Q26 營收（月營收實績加總） | C117: NT$B | E117: 16.379 | G117: Verified | H117: TechNews 2026-10-03（9 月營收、前 9 月累計）：前 9 月 411.31 億 − 1H26 247.52 億 | I117: winvest 2026-08（7 月營收、1Q26 EPS）：7 月 54.40 億；TechNews 2026-10-05（大和報告；8 月自結獲利）：8 月 53.53 億；9 月 55.86 億
A118: q3_gm | B118: 3Q26 毛利率 | C118: % | D118: 0.28 | E118: 0.3 | F118: 0.315 | G118: Assumed | H118: TechNews 2026-10-05（大和報告；8 月自結獲利）：8 月自結稅前淨利率 27.8%、毛利率推算約 30–31% | I118: 三立 2026-07-27（2Q26 營收、法人預估、產能）：法人估 28.1%
A119: q3_opx | B119: 3Q26 營業費用 | C119: NT$B | D119: 0.46 | E119: 0.5 | F119: 0.55 | G119: Assumed | H119: 1Q26 0.419、2Q26 0.461（Q 頁推得） | I119: —
A120: q4_g | B120: 4Q26 營收季增 | C120: % | D120: 0.03 | E120: 0.1 | F120: 0.15 | G120: Assumed | H120: TechNews 2026-10-02（美銀報告）：4Q26 季增約 10% | I120: TechNews 2026-10-05（大和報告；8 月自結獲利）：法人估 4Q26 184.1 億（季增 12%）
A121: q4_gm | B121: 4Q26 毛利率 | C121: % | D121: 0.29 | E121: 0.325 | F121: 0.34 | G121: Assumed | H121: TechNews 2026-10-02（美銀報告）：4Q26 毛利率 32–33% | I121: —
A122: q4_opx | B122: 4Q26 營業費用 | C122: NT$B | D122: 0.48 | E122: 0.52 | F122: 0.58 | G122: Assumed | H122: 同上 | I122: —
A123: q_nonop | B123: 3Q、4Q26 營業外淨額（每季） | C123: NT$B | D123: 0 | E123: 0.15 | F123: 0.4 | G123: Assumed | H123: 1Q26 0.246、2Q26 0.077（stockanalysis 推得） | I123: 3Q26 財報約 10 月底（stockanalysis 估 2026-11-03）
A124: q_sh | B124: 3Q、4Q26 加權股數 | C124: 十億股 | E124: 0.64617 | G124: Interested-party | H124: stockanalysis.com（8046）：流通股數 646.17M | I124: 凱基 PCB 產業報告 2026-07-20（Interested-party）：約 6.46 億股
A125: G. 共識與券商（只作 Recon 與 Val 對照，不作校準）
A126: cons_eps26 | B126: 共識 EPS FY2026（FactSet 平均，2026-06） | C126: NT$ | D126: 8.56 | E126: 13.19 | F126: 20.48 | G126: Interested-party | H126: 鉅亨 2026-06-24（FactSet 14 位分析師） | I126: 中位數 12.57；凱基 2026-07：17.27；美銀 2026-10：18.44
A127: cons_eps27 | B127: 共識 EPS FY2027（FactSet 平均，2026-06） | C127: NT$ | D127: 21.66 | E127: 32.12 | F127: 52.88 | G127: Interested-party | H127: 鉅亨 2026-06-24（FactSet 14 位分析師） | I127: 中位數 28.9；凱基 38.88；美銀 43.80
A128: cons_eps28 | B128: 共識 EPS FY2028（FactSet 平均，2026-06） | C128: NT$ | D128: 42.03 | E128: 59.21 | F128: 80.8 | G128: Interested-party | H128: 鉅亨 2026-06-24（FactSet 14 位分析師） | I128: 中位數 54.25；凱基 61.35；美銀 70.09
A129: cons_rev27 | B129: 共識營收 FY2027（FactSet 平均，2026-06） | C129: NT$B | D129: 69.31 | E129: 90.26 | F129: 127.93 | G129: Interested-party | H129: 鉅亨 2026-06-24（FactSet 14 位分析師） | I129: 美銀 90.33；凱基 88.41
A130: cons_rev28 | B130: 共識營收 FY2028（FactSet 平均，2026-06） | C130: NT$B | D130: 109.36 | E130: 133.54 | F130: 178.55 | G130: Interested-party | H130: 鉅亨 2026-06-24（FactSet 14 位分析師） | I130: 美銀 120.65；凱基 123.31
A131: bk_eps27 | B131: 券商 EPS FY2027（美銀 2026-10 43.80、凱基 2026-07 38.88 平均） | C131: NT$ | D131: 38.88 | E131: 41.34 | F131: 43.8 | G131: Interested-party | H131: TechNews 2026-10-02（美銀報告） | I131: 凱基 PCB 產業報告 2026-07-20（Interested-party）
A132: bk_eps28 | B132: 券商 EPS FY2028（美銀 70.09、凱基 61.35 平均） | C132: NT$ | D132: 61.35 | E132: 65.72 | F132: 70.09 | G132: Interested-party | H132: TechNews 2026-10-02（美銀報告） | I132: 凱基 PCB 產業報告 2026-07-20（Interested-party）
A133: H. 價格與市場資料
...

Sheet Q
A1: Q — FY2025 實績、1Q26／2Q26 實績、3Q26 營收實績與 FY2026 錨點（十億新台幣；EPS 新台幣、基本；股數十億股）。藍字＝輸入；黑字＝公式
A2: FY2026 錨點＝1Q、2Q26 財報實績＋3Q26 營收實績（月營收）與 3Q26 毛利率、費用假設＋4Q26 假設。3Q26 財報約 10 月底公布，屆時以實績取代 E 欄（毛利率、費用、業外、淨利）
A3: 項目 | B3: FY2025A | C3: 1Q26（實績） | D3: 2Q26（實績） | E3: 3Q26（營收實績） | F3: 4Q26（模型） | G3: FY2026 錨點 | H3: 標記 | I3: 來源1（公司） | J3: 來源2／說明
A4: 營收 | B4: 40.173 | C4: 11.177 | D4: 13.575 | E4: =q3_rev -> 16.379 | F4: =E4*(1+q4_g) -> 18.0169 | G4: =SUM(C4:F4) -> 59.1479 | H4: Verified／Assumed（4Q） | I4: stockanalysis 年度與季損益表（公司財報轉載） | J4: FY2025 401.73 億（vocus 4Q25 法說、FactSet 同）；1Q26 111.77 億（富果同）；2Q26 135.75 億（大和、三立同）
A5: 毛利 | B5: 3.647 | C5: 1.771 | D5: 3.36 | E5: =E4*q3_gm -> 4.9137 | F5: =F4*q4_gm -> 5.8554925 | G5: =SUM(C5:F5) -> 15.900192 | H5: Verified／Assumed | I5: stockanalysis 年度與季損益表（公司財報轉載） | J5: 1Q26 毛利率 15.8%（三立同；富果摘要 16.8% 與此不符，不採用）
A6: 毛利率 | B6: =B5/B4 -> 0.090782366 | C6: =C5/C4 -> 0.15845039 | D6: =D5/D4 -> 0.24751381 | E6: =E5/E4 -> 0.3 | F6: =F5/F4 -> 0.325 | G6: =G5/G4 -> 0.26882091 | H6: Derived | I6: — | J6: FY2025 9.08%（凱基、美銀 9.1%）
A7: 營業費用 | B7: =B5-B8 -> 1.665 | C7: =C5-C8 -> 0.419 | D7: =D5-D8 -> 0.461 | E7: =q3_opx -> 0.5 | F7: =q4_opx -> 0.52 | G7: =SUM(C7:F7) -> 1.9 | H7: Derived／Assumed | I7: 毛利 − 營業利益 | J7: —
A8: 營業利益 | B8: 1.982 | C8: 1.352 | D8: 2.899 | E8: =E5-E7 -> 4.4137 | F8: =F5-F7 -> 5.3354925 | G8: =SUM(C8:F8) -> 14.000193 | H8: Verified／Derived | I8: stockanalysis 年度與季損益表（公司財報轉載） | J8: FY2025 19.82 億（vocus 同）；1Q26 13.52 億（富果同）
A9: 營業外淨額 | B9: 0.364 | C9: 0.246 | D9: 0.077 | E9: =q_nonop -> 0.15 | F9: =q_nonop -> 0.15 | G9: =SUM(C9:F9) -> 0.623 | H9: Derived／Assumed | I9: stockanalysis 年度與季損益表（公司財報轉載） | J9: 稅前利益 − 營業利益；稅前利益由 stockanalysis 稅前利益率 × 營收推得（近似）
A10: 稅前利益 | B10: =B8+B9 -> 2.346 | C10: =C8+C9 -> 1.598 | D10: =D8+D9 -> 2.976 | E10: =E8+E9 -> 4.5637 | F10: =F8+F9 -> 5.4854925 | G10: =SUM(C10:F10) -> 14.623193 | H10: Derived | I10: —
A11: 歸屬母公司淨利 | B11: 1.947 | C11: 1.309 | D11: 2.262 | E11: =E10*(1-tax) -> 3.605323 | F11: =F10*(1-tax) -> 4.3335391 | G11: =SUM(C11:F11) -> 11.509862 | H11: Verified／Derived | I11: stockanalysis 年度與季損益表（公司財報轉載） | J11: FY2025 19.47 億（FactSet 表同）；2Q26 22.61 億（大和同）
A12: 所得稅 | B12: =B10-B11 -> 0.399 | C12: =C10-C11 -> 0.289 | D12: =D10-D11 -> 0.714 | E12: =E10-E11 -> 0.958377 | F12: =F10-F11 -> 1.1519534 | G12: =SUM(C12:F12) -> 3.1133304 | H12: Derived | I12: — | J12: —
A13: 加權股數（十億股） | B13: =B11/B14 -> 0.64684385 | C13: =C11/C14 -> 0.64482759 | D13: =D11/D14 -> 0.64628571 | E13: =q_sh -> 0.64617 | F13: =q_sh -> 0.64617 | G13: =AVERAGE(C13:F13) -> 0.64586333 | H13: Derived | I13: 淨利 ÷ EPS | J13: —
A14: EPS（基本） | B14: 3.01 | C14: 2.03 | D14: 3.5 | E14: =E11/E13 -> 5.5795271 | F14: =F11/F13 -> 6.7065 | G14: =G11/G13 -> 17.820894 | H14: Verified／Derived | I14: stockanalysis 年度與季損益表（公司財報轉載） | J14: FY2025 3.01（wantgoo 同）；1Q26 2.03（winvest 同）；2Q26 3.50（大和、HiStock 同）
A15: 折舊攤提（年度） | B15: 6.894 | G15: =da26 -> 7.1 | H15: Verified／Interested-party | I15: stockanalysis 現金流量表 | J15: FY2026：TTM 至 2026-06 71.0 億
A16: 資本支出（年度） | B16: 2.422 | G16: =capex26 -> 4 | H16: Verified／Interested-party | I16: FY2025：stockanalysis 現金流量表；FY2026：公司計畫約 40 億 | J16: 富果摘要稱 2025 年實際 43.14 億（口徑可能含預付設備款；不採用）
A18: FY2026 產品別（錨點營收 × In 頁 C 節占比）
A19: ABF 載板 | G19: =G4*mx_abf -> 34.305782 | H19: Derived
A20: BT 載板 | G20: =G4*mx_bt -> 18.927328 | H20: Derived
A21: PCB（一般電路板） | G21: =G4*(1-mx_abf-mx_bt) -> 5.91479 | H21: Derived
A23: 檢查（參考；校準未使用券商數字）
A24: 1H26 營收 自算 − 前 9 月累計 41.131 + 3Q26（應為 0） | B24: =C4+D4-(41.131-q3_rev) -> 0
A25: FY2026 營收年增 | B25: =G4/B4-1 -> 0.47232967
A26: FY2025→FY2026 現金毛利增量 ÷ 營收增量（含漲價；In 頁 ft_abf、ft_oth 的對照） | B26: =((G5+G15)-(B5+B15))/(G4-B4) -> 0.6566144
A27: FY2026 EPS ÷ 凱基 17.27 − 1 | B27: =G14/17.27-1 -> 0.03189892
A28: 3Q26 EPS ÷ 大和估 5.62 − 1 | B28: =E14/5.62-1 -> -0.0072015908
A29: 4Q26 營收年化 ÷ FY2026 營收（漲價年度化 carry 的對照） | B29: =F4*4/G4 -> 1.2184304

Sheet Units
A1: Units — 南電在 AI 加速器載板的份額與每顆金額（口徑與 Ibiden、欣興模型一致；情境 A）。份額合計＝Ibiden（ibiden/dist）＋欣興（unimicron/dist）＋南電，其餘為三星電機、景碩、AT&S 等
A3: 項目 | B3: 單位 | C3: CY2026 | D3: CY2027 | E3: CY2028 | F3: CY2029 | G3: 說明
A4: NVIDIA 加速器顆數 | B4: 百萬顆 | C4: =PL!D63 -> 7.6 | D4: =PL!E63 -> 9.7 | E4: =PL!F63 -> 9.5 | F4: =PL!G63 -> 10.6 | G4: markets/network
A5: 非 NVIDIA 加速器顆數 | B5: 百萬顆 | C5: =PL!D64 -> 7.6 | D5: =PL!E64 -> 14 | E5: =PL!F64 -> 17 | F5: =PL!G64 -> 19.55
A6: 每顆 NVIDIA 加速器載板金額（全市場） | B6: US$ | C6: =PL!D68 -> 215.3086 | D6: =PL!E68 -> 254.06414 | E6: =PL!F68 -> 284.8059 | F6: =PL!G68 -> 318.38302 | G6: Ibiden 模型 Units 頁同值（FY2026 校準 × 面積層數 × 溢價）
A7: 南電份額：NVIDIA | B7: % | C7: =PL!D69 -> 0.02 | D7: =PL!E69 -> 0.03 | E7: =PL!F69 -> 0.04 | F7: =PL!G69 -> 0.04 | G7: Assumed
A8: Ibiden 份額：NVIDIA（70% × Ibiden 份額相對值） | B8: % | C8: =ib_sh26*1 -> 0.7 | D8: =ib_sh26*ibrel_27 -> 0.665 | E8: =ib_sh26*ibrel_28 -> 0.616 | F8: =ib_sh26*ibrel_29 -> 0.595 | G8: Ibiden 模型
A9: 欣興份額：NVIDIA | B9: % | C9: =un_nv_26 -> 0.25 | D9: =un_nv_27 -> 0.27 | E9: =un_nv_28 -> 0.29 | F9: =un_nv_29 -> 0.3 | G9: 欣興模型
A10: 合計：Ibiden＋欣興＋南電（NVIDIA） | B10: % | C10: =C7+C8+C9 -> 0.97 | D10: =D7+D8+D9 -> 0.965 | E10: =E7+E8+E9 -> 0.946 | F10: =F7+F8+F9 -> 0.935 | G10: 應 ≤ 100%；其餘為三星電機等
A11: 南電份額：非 NVIDIA（金額） | B11: % | C11: =PL!D70 -> 0.05 | D11: =PL!E70 -> 0.06 | E11: =PL!F70 -> 0.07 | F11: =PL!G70 -> 0.07 | G11: Assumed
A12: Ibiden 份額：非 NVIDIA（Ibiden 權重 × 份額相對值 ÷ v_ot） | B12: % | C12: =ib_w_ot*1/v_ot -> 0.5 | D12: =ib_w_ot*ibrel_27/v_ot -> 0.475 | E12: =ib_w_ot*ibrel_28/v_ot -> 0.44 | F12: =ib_w_ot*ibrel_29/v_ot -> 0.425 | G12: 與欣興模型同算法
A13: 欣興份額：非 NVIDIA（金額） | B13: % | C13: =un_ot_26 -> 0.3 | D13: =un_ot_27 -> 0.31 | E13: =un_ot_28 -> 0.32 | F13: =un_ot_29 -> 0.33 | G13: 欣興模型
A14: 合計：Ibiden＋欣興＋南電（非 NVIDIA） | B14: % | C14: =C11+C12+C13 -> 0.85 | D14: =D11+D12+D13 -> 0.845 | E14: =E11+E12+E13 -> 0.83 | F14: =F11+F12+F13 -> 0.825 | G14: 應 ≤ 100%；其餘為三星電機、景碩、AT&S
A15: 每顆 NVIDIA 加速器的南電營收 | B15: US$ | C15: =PL!D68*PL!D69*PL!D67 -> 4.3061719 | D15: =PL!E68*PL!E69*PL!E67 -> 8.7652129 | E15: =PL!F68*PL!F69*PL!F67 -> 13.101072 | F15: =PL!G68*PL!G69*PL!G67 -> 14.645619 | G15: Ibiden、欣興對照值見各自 dist Units 頁
A16: 南電加速器載板營收 | B16: US$M | C16: =PL!D71 -> 98.18072 | D16: =PL!E71 -> 281.36334 | E16: =PL!F71 -> 436.26568 | F16: =PL!G71 -> 556.09415
A17: 南電 AI 載板營收（含交換器等其他 AI） | B17: NT$B | C17: =PL!D81 -> 22.298758 | D17: =PL!E81 -> 37.942577 | E17: =PL!F81 -> 43.600329 | F17: =PL!G81 -> 49.818301
A18: 南電 AI 載板營收 ÷ AI IT 資本支出 | B18: % | C18: =PL!D81/fx/itc_26 -> 0.00087752834 | D18: =PL!E81/fx/itc_27 -> 0.00074581653 | E18: =PL!F81/fx/itc_28 -> 0.00067609383 | F18: =PL!G81/fx/itc_29 -> 0.00067814431 | G18: × 每 GW IT capex 即每 GW 營收
A19: 每 GW 南電 AI 載板營收（VR200 每 GW IT capex 37.59B） | B19: US$M | C19: =PL!D81/fx/itc_26*37.59*1000 -> 32.98629 | D19: =PL!E81/fx/itc_27*37.59*1000 -> 28.035243 | E19: =PL!F81/fx/itc_28*37.59*1000 -> 25.414367 | F19: =PL!G81/fx/itc_29*37.59*1000 -> 25.491445 | G19: Tokenomics IF_CapexIT（VR200 基準，經橋接表；與 Ibiden、欣興模型相同係數）
A21: 讀法：南電在 GPU、ASIC 加速器載板的份額小（個位數），AI 載板以網通交換器（800G／1.6T 交換晶片）為主；加速器載板只占南電 AI 載板一小部分，其餘為校準殘差（公司未揭露）。三家合計留給三星電機、景碩、AT&S。

Sheet PL
A1: PL — 南電損益（十億新台幣；EPS 新台幣、基本；歸屬母公司）。FY2025A 實績、FY2026 錨點（1H26 實績＋3Q26 營收實績＋假設；三情境相同），FY2027–FY2029 由驅動因子推導，FY2030 起為收斂法。三情境各一個完整推導區塊（本頁下方），頂端為摘要
A2: 灰底＝FY2030–FY2032 收斂法（上游顆數只到 2029）：營收年增線性收斂到 fade_g、淨利率線性收斂到 fade_m（In 頁 I 節），非驅動因子推導
A3: 情境／項目 | B3: 單位 | C3: FY2025A | D3: FY2026（錨點） | E3: FY2027 | F3: FY2028 | G3: FY2029 | H3: FY2030（收斂） | I3: FY2031（收斂） | J3: FY2032（收斂） | K3: 說明
A4: 情境 A
A5: 營收 | B5: NT$B | C5: =C86 -> 40.173 | D5: =D86 -> 59.1479 | E5: =E86 -> 80.229395 | F5: =F86 -> 88.763775 | G5: =G86 -> 97.272873 | H5: =H86 -> 105.43486 | I5: =I86 -> 113.02133 | J5: =J86 -> 119.80261
A6: 營收年增 | B6: % | D6: =D87 -> 0.47232967 | E6: =E87 -> 0.35642 | F6: =F87 -> 0.10637474 | G6: =G87 -> 0.095862283 | H6: =H87 -> 0.083908189 | I6: =I87 -> 0.071954094 | J6: =J87 -> 0.06
A7: ABF 載板 | B7: NT$B | D7: =D79 -> 34.305782 | E7: =E79 -> 49.709078 | F7: =F79 -> 55.782906 | G7: =G79 -> 62.9387
A8: AI 載板 | B8: NT$B | D8: =D81 -> 22.298758 | E8: =E81 -> 37.942577 | F8: =F81 -> 43.600329 | G8: =G81 -> 49.818301
A9: ABF 需求滿足率 | B9: % | D9: =D80 -> 1 | E9: =E80 -> 0.95142541 | F9: =F80 -> 0.95637753 | G9: =G80 -> 1
A10: 毛利率 | B10: % | C10: =C96 -> 0.090782366 | D10: =D96 -> 0.26882091 | E10: =E96 -> 0.35816219 | F10: =F96 -> 0.35168173 | G10: =G96 -> 0.33961477
A11: 折舊攤提 | B11: NT$B | C11: =C92 -> 6.894 | D11: =D92 -> 7.1 | E11: =E92 -> 6.7125 | F11: =F92 -> 7.6234375 | G11: =G92 -> 8.9205078 | H11: =H92 -> 9.6690115 | I11: =I92 -> 10.364736 | J11: =J92 -> 10.986621
A12: 營業利益率 | B12: % | C12: =C99 -> 0.049336619 | D12: =D99 -> 0.23669805 | E12: =E99 -> 0.32941564 | F12: =F99 -> 0.32404073 | G12: =G99 -> 0.31294095
A13: 歸屬母公司淨利 | B13: NT$B | C13: =C103 -> 1.947 | D13: =D103 -> 11.509862 | E13: =E103 -> 21.352765 | F13: =F103 -> 23.196832 | G13: =G103 -> 24.522125 | H13: =H103 -> 26.579733 | I13: =I103 -> 28.492253 | J13: =J103 -> 30.201788
A14: 淨利率 | B14: % | C14: =C107 -> 0.048465387 | D14: =D107 -> 0.1945946 | E14: =E107 -> 0.26614641 | F14: =F107 -> 0.2613322 | G14: =G107 -> 0.25209624 | H14: =H107 -> 0.25209624 | I14: =I107 -> 0.25209624 | J14: =J107 -> 0.25209624
A15: EPS | B15: NT$ | C15: =C105 -> 3.01 | D15: =D105 -> 17.820894 | E15: =E105 -> 33.04512 | F15: =F105 -> 35.898962 | G15: =G105 -> 37.94996 | H15: =H105 -> 41.134272 | I15: =I105 -> 44.094051 | J15: =J105 -> 46.739694
A16: EPS 年增 | B16: % | D16: =D106 -> 4.9205629 | E16: =E106 -> 0.8542908 | F16: =F106 -> 0.086361964 | G16: =G106 -> 0.057132507 | H16: =H106 -> 0.083908189 | I16: =I106 -> 0.071954094 | J16: =J106 -> 0.06
A18: 情境 B
A19: 營收 | B19: NT$B | C19: =C139 -> 40.173 | D19: =D139 -> 59.1479 | E19: =E139 -> 79.283028 | F19: =F139 -> 79.966387 | G19: =G139 -> 86.968127 | H19: =H139 -> 93.204236 | I19: =I139 -> 98.409957 | J19: =J139 -> 102.34636
A20: 營收年增 | B20: % | D20: =D140 -> 0.47232967 | E20: =E140 -> 0.34042 | F20: =F140 -> 0.0086192381 | G20: =G140 -> 0.087558528 | H20: =H140 -> 0.071705686 | I20: =I140 -> 0.055852843 | J20: =J140 -> 0.04
A21: ABF 載板 | B21: NT$B | D21: =D132 -> 34.305782 | E21: =E132 -> 49.709078 | F21: =F132 -> 49.209479 | G21: =G132 -> 55.465955
A22: AI 載板 | B22: NT$B | D22: =D134 -> 22.298758 | E22: =E134 -> 37.942577 | F22: =F134 -> 36.471228 | G22: =G134 -> 42.345556
A23: ABF 需求滿足率 | B23: % | D23: =D133 -> 1 | E23: =E133 -> 0.95142541 | F23: =F133 -> 1 | G23: =G133 -> 1
A24: 毛利率 | B24: % | C24: =C149 -> 0.090782366 | D24: =D149 -> 0.26882091 | E24: =E149 -> 0.35766279 | F24: =F149 -> 0.33437169 | G24: =G149 -> 0.32241445
A25: 折舊攤提 | B25: NT$B | C25: =C145 -> 6.894 | D25: =D145 -> 7.1 | E25: =E145 -> 6.7125 | F25: =F145 -> 7.6234375 | G25: =G145 -> 8.9205078 | H25: =H145 -> 9.5601589 | I25: =I145 -> 10.094121 | J25: =J145 -> 10.497886
A26: 營業利益率 | B26: % | C26: =C152 -> 0.049336619 | D26: =D152 -> 0.23669805 | E26: =E152 -> 0.32880316 | F26: =F152 -> 0.30561071 | G26: =G152 -> 0.29457968
A27: 歸屬母公司淨利 | B27: NT$B | C27: =C156 -> 1.947 | D27: =D156 -> 11.509862 | E27: =E156 -> 21.068123 | F27: =F156 -> 19.780482 | G27: =G156 -> 20.713044 | H27: =H156 -> 21.458344 | I27: =I156 -> 21.875582 | J27: =J156 -> 21.938084
A28: 淨利率 | B28: % | C28: =C160 -> 0.048465387 | D28: =D160 -> 0.1945946 | E28: =E160 -> 0.26573308 | F28: =F160 -> 0.24735995 | G28: =G160 -> 0.23816822 | H28: =H160 -> 0.23022928 | I28: =I160 -> 0.22229033 | J28: =J160 -> 0.21435139
A29: EPS | B29: NT$ | C29: =C158 -> 3.01 | D29: =D158 -> 17.820894 | E29: =E158 -> 32.604614 | F29: =F158 -> 30.611885 | G29: =G158 -> 32.055099 | H29: =H158 -> 33.208511 | I29: =I158 -> 33.854222 | J29: =J158 -> 33.950948
A30: EPS 年增 | B30: % | D30: =D159 -> 4.9205629 | E30: =E159 -> 0.82957225 | F30: =F159 -> -0.061117998 | G30: =G159 -> 0.047145556 | H30: =H159 -> 0.035982163 | I30: =I159 -> 0.019444124 | J30: =J159 -> 0.0028571429
A32: 情境 C
A33: 營收 | B33: NT$B | C33: =C192 -> 40.173 | D33: =D192 -> 59.1479 | E33: =E192 -> 77.390295 | F33: =F192 -> 67.77289 | G33: =G192 -> 70.692597 | H33: =H192 -> 73.194208 | I33: =I192 -> 75.221218 | J33: =J192 -> 76.725642
A34: 營收年增 | B34: % | D34: =D193 -> 0.47232967 | E34: =E193 -> 0.30842 | F34: =F193 -> -0.12427147 | G34: =G193 -> 0.043080756 | H34: =H193 -> 0.035387171 | I34: =I193 -> 0.027693585 | J34: =J193 -> 0.02
A35: ABF 載板 | B35: NT$B | D35: =D185 -> 34.305782 | E35: =E185 -> 49.709078 | F35: =F185 -> 40.091672 | G35: =G185 -> 43.01138
A36: AI 載板 | B36: NT$B | D36: =D187 -> 22.298758 | E36: =E187 -> 37.942577 | F36: =F187 -> 27.353421 | G36: =G187 -> 29.890981
A37: ABF 需求滿足率 | B37: % | D37: =D186 -> 1 | E37: =E186 -> 0.95142541 | F37: =F186 -> 1 | G37: =G186 -> 1
A38: 毛利率 | B38: % | C38: =C202 -> 0.090782366 | D38: =D202 -> 0.26882091 | E38: =E202 -> 0.35662735 | F38: =F202 -> 0.30341516 | G38: =G202 -> 0.28395514
A39: 折舊攤提 | B39: NT$B | C39: =C198 -> 6.894 | D39: =D198 -> 7.1 | E39: =E198 -> 6.7125 | F39: =F198 -> 7.6234375 | G39: =G198 -> 8.9205078 | H39: =H198 -> 9.2361793 | I39: =I198 -> 9.4919623 | J39: =J198 -> 9.6818015
A40: 營業利益率 | B40: % | C40: =C205 -> 0.049336619 | D40: =D205 -> 0.23669805 | E40: =E205 -> 0.32753328 | F40: =F205 -> 0.27266964 | G40: =G205 -> 0.25371755
A41: 歸屬母公司淨利 | B41: NT$B | C41: =C209 -> 1.947 | D41: =D209 -> 11.509862 | E41: =E209 -> 20.498839 | F41: =F209 -> 15.072891 | G41: =G209 -> 14.643402 | H41: =H209 -> 14.150818 | I41: =I209 -> 13.503941 | J41: =J209 -> 12.714479
A42: 淨利率 | B42: % | C42: =C213 -> 0.048465387 | D42: =D213 -> 0.1945946 | E42: =E213 -> 0.26487609 | F42: =F213 -> 0.22240296 | G42: =G213 -> 0.20714195 | H42: =H213 -> 0.19333249 | I42: =I213 -> 0.17952302 | J42: =J213 -> 0.16571356
A43: EPS | B43: NT$ | C43: =C211 -> 3.01 | D43: =D211 -> 17.820894 | E43: =E211 -> 31.7236 | F43: =F211 -> 23.32651 | G43: =G211 -> 22.661842 | H43: =H211 -> 21.899528 | I43: =I211 -> 20.898433 | J43: =J211 -> 19.676679
A44: EPS 年增 | B44: % | D44: =D212 -> 4.9205629 | E44: =E212 -> 0.78013515 | F44: =F212 -> -0.26469537 | G44: =G212 -> -0.028494122 | H44: =H212 -> -0.033638641 | I44: =I212 -> -0.045713099 | J44: =J212 -> -0.058461538
A46: 核對（應為 0）：FY2026 模型 − 錨點
A47: 三情境：營收差（NT$B） | D47: =ABS(D86-a26_rev)+ABS(D139-a26_rev)+ABS(D192-a26_rev) -> 0
A48: 三情境：EPS 差（NT$） | D48: =ABS(D105-a26_eps)+ABS(D158-a26_eps)+ABS(D211-a26_eps) -> 0
A49: 情境 A：其他 AI 載板 FY2026 應 > 0（1＝是） | D49: =IF(D75>0,0,1) -> 0
A60: 情境 A（順利）：tsmc 顆數係數 A（基準）；BT 年增 30%／10%／5%
A61: 項目 | B61: 單位 | C61: FY2025A | D61: FY2026（錨點） | E61: FY2027 | F61: FY2028 | G61: FY2029 | H61: FY2030（收斂） | I61: FY2031（收斂） | J61: FY2032（收斂） | K61: 說明
A62: A. AI 加速器載板（口徑與 Ibiden、欣興一致；D 欄＝FY2026 校準年）
A63: NVIDIA 加速器顆數 × 情境係數 | B63: 百萬顆 | D63: =(u_bw_26+u_rb_26+u_ru_26+u_hp_26)*1 -> 7.6 | E63: =(u_bw_27+u_rb_27+u_ru_27+u_hp_27)*1*1 -> 9.7 | F63: =(u_bw_28+u_rb_28+u_ru_28+u_hp_28)*um28_A*1 -> 9.5 | G63: =(u_bw_28*(1+g29_bw)+u_rb_28*(1+g29_rb)+u_ru_28*(1+g29_ru)+u_hp_28*(1+g29_hp))*um29_A*1 -> 10.6 | K63: markets/network In：Blackwell、Rubin、Rubin Ultra、Hopper
A64: 非 NVIDIA 加速器顆數 × 情境係數 | B64: 百萬顆 | D64: =(u_amd_26+u_tpu_26+u_trn_26+u_oth_26)*1 -> 7.6 | E64: =(u_amd_27+u_tpu_27+u_trn_27+u_oth_27)*1*1 -> 14 | F64: =(u_amd_28+u_tpu_28+u_trn_28+u_oth_28)*um28_A*1 -> 17 | G64: =(u_amd_28*(1+g29_amd)+u_tpu_28*(1+g29_tpu)+u_trn_28*(1+g29_trn)+u_oth_28*(1+g29_oth))*um29_A*1 -> 19.55 | K64: AMD、TPU、Trainium、其他 ASIC
A65: 每顆載板面積與層數指數（FY2026＝1） | B65: x | D65: =1 -> 1 | E65: =D65*(1+g_asp) -> 1.18 | F65: =E65*(1+g_asp) -> 1.3924 | G65: =F65*(1+g_asp) -> 1.643032 | K65: Ibiden 模型 g_asp（Analogy）
A66: ABF 價格溢價指數（全市場；FY2026＝1） | B66: x | D66: =1 -> 1 | E66: =ibpp_27 -> 1 | F66: =ibpp_28 -> 0.95 | G66: =ibpp_29 -> 0.9 | K66: Ibiden 模型 pp（Assumed）
A67: 南電漲價年度化（CY2026 基期；FY2026＝1） | B67: x | D67: =1 -> 1 | E67: =1+carry -> 1.15 | F67: =1+carry -> 1.15 | G67: =1+carry -> 1.15 | K67: In 頁 carry（Assumed）
A68: 每顆 NVIDIA 加速器載板金額（全市場）＝ FY2026 金額 × 面積層數 × 溢價 | B68: US$／顆 | D68: =v26*D65*D66 -> 215.3086 | E68: =v26*E65*E66 -> 254.06414 | F68: =v26*F65*F66 -> 284.8059 | G68: =v26*G65*G66 -> 318.38302 | K68: FY2026 金額取自 Ibiden 模型 Units 頁（權威）
A69: 南電份額：NVIDIA 加速器載板 | B69: % | D69: =sh_nv_26 -> 0.02 | E69: =sh_nv_27 -> 0.03 | F69: =sh_nv_28 -> 0.04 | G69: =sh_nv_29 -> 0.04
A70: 南電份額：非 NVIDIA 加速器載板（金額） | B70: % | D70: =sh_ot_26 -> 0.05 | E70: =sh_ot_27 -> 0.06 | F70: =sh_ot_28 -> 0.07 | G70: =sh_ot_29 -> 0.07
A71: 南電加速器載板營收 ＝（NVIDIA × 金額 × 份額 ＋ 非 NVIDIA × 金額 × v_ot × 份額）× 漲價年度化 | B71: US$M | D71: =(D63*D68*D69+D64*D68*v_ot*D70)*D67 -> 98.18072 | E71: =(E63*E68*E69+E64*E68*v_ot*E70)*E67 -> 281.36334 | F71: =(F63*F68*F69+F64*F68*v_ot*F70)*F67 -> 436.26568 | G71: =(G63*G68*G69+G64*G68*v_ot*G70)*G67 -> 556.09415
A72: 南電加速器載板營收（新台幣） | B72: NT$B | D72: =D71*fx/1000 -> 3.1908734 | E72: =E71*fx/1000 -> 9.1443084 | F72: =F71*fx/1000 -> 14.178635 | G72: =G71*fx/1000 -> 18.07306
A73: B. ABF 需求與產能（營收＝MIN（需求, 產能））
A74: AI 載板需求（FY2026＝ABF × AI 占比） | B74: NT$B | D74: =a26_abf*ai_abf -> 22.298758 | K74: 凱基：AI 與資料中心（800G 交換器）約占 ABF 60%
A75: 其他 AI 載板需求（交換器為主，另含伺服器 CPU、網通 ASIC） | B75: NT$B | D75: =D74-D72 -> 19.107885 | E75: =$D75*(swm_27/swm_26)^el_o*1*1*E66*E67 -> 30.735409 | F75: =$D75*(swm_28/swm_26)^el_o*um28_A*1*F66*F67 -> 31.4104 | G75: =$D75*(swm_29/swm_26)^el_o*um29_A*1*G66*G67 -> 31.745241 | K75: FY2026＝校準殘差（Derived）；之後 × 交換晶片與交換器市場成長 ^ 彈性 × 情境係數 × 溢價
A76: 非 AI ABF 需求（PC、一般伺服器、車用） | B76: NT$B | D76: =a26_abf-D74 -> 12.007024 | E76: =D76*(1+g_nai) -> 12.367234 | F76: =E76*(1+g_nai) -> 12.738251 | G76: =F76*(1+g_nai) -> 13.120399
A77: ABF 需求合計 | B77: NT$B | D77: =D72+D75+D76 -> 34.305782 | E77: =E72+E75+E76 -> 52.246952 | F77: =F72+F75+F76 -> 58.327286 | G77: =G72+G75+G76 -> 62.9387
A78: ABF 產能上限（FY2026 營收 × 產能指數 × 組合 × 溢價） | B78: NT$B | D78: =a26_abf -> 34.305782 | E78: =$D77*cap_27*(1+g_mix)^1*E66*E67 -> 49.709078 | F78: =$D77*cap_28*(1+g_mix)^2*F66*F67 -> 55.782906 | G78: =$D77*cap_29*(1+g_mix)^3*G66*G67 -> 65.76511 | K78: 1H26 ABF 稼動率約 80–85%（昆山約 50%），以 FY2026 營收為產能基準
A79: ABF 載板營收 ＝ MIN（需求, 產能） | B79: NT$B | D79: =a26_abf -> 34.305782 | E79: =MIN(E77,E78) -> 49.709078 | F79: =MIN(F77,F78) -> 55.782906 | G79: =MIN(G77,G78) -> 62.9387
A80: 需求滿足率（營收 ÷ 需求；< 100% 表示產能受限） | B80: % | D80: =D79/D77 -> 1 | E80: =E79/E77 -> 0.95142541 | F80: =F79/F77 -> 0.95637753 | G80: =G79/G77 -> 1
A81: AI 載板營收（加速器＋其他 AI，乘滿足率） | B81: NT$B | D81: =(D72+D75)*D80 -> 22.298758 | E81: =(E72+E75)*E80 -> 37.942577 | F81: =(F72+F75)*F80 -> 43.600329 | G81: =(G72+G75)*G80 -> 49.818301
A82: 加速器載板 ÷ AI 載板 | B82: % | D82: =D72/(D72+D75) -> 0.14309646 | E82: =E72/(E72+E75) -> 0.22929722 | F82: =F72/(F72+F75) -> 0.31100976 | G82: =G72/(G72+G75) -> 0.36277953
A83: C. 其他產品與合計
A84: BT 載板（情境別年增；公司特有） | B84: NT$B | D84: =a26_bt -> 18.927328 | E84: =D84*(1+g_bt27_A) -> 24.605526 | F84: =E84*(1+g_bt28_A) -> 27.066079 | G84: =F84*(1+g_bt29_A) -> 28.419383 | K84: BT 成長以漲價為主
A85: PCB（一般電路板） | B85: NT$B | D85: =a26_pcb -> 5.91479 | E85: =D85*(1+g_pcb) -> 5.91479 | F85: =E85*(1+g_pcb) -> 5.91479 | G85: =F85*(1+g_pcb) -> 5.91479
A86: 營收 | B86: NT$B | C86: =a25_rev -> 40.173 | D86: =D79+D84+D85 -> 59.1479 | E86: =E79+E84+E85 -> 80.229395 | F86: =F79+F84+F85 -> 88.763775 | G86: =G79+G84+G85 -> 97.272873 | H86: =G86*(1+H87) -> 105.43486 | I86: =H86*(1+I87) -> 113.02133 | J86: =I86*(1+J87) -> 119.80261 | K86: FY2030 起為收斂法：營收年增由 FY2029 線性收斂到 fade_g、淨利率收斂到 fade_m（FY2032 達到），非驅動因子推導
A87: 營收年增 | B87: % | D87: =D86/C86-1 -> 0.47232967 | E87: =E86/D86-1 -> 0.35642 | F87: =F86/E86-1 -> 0.10637474 | G87: =G86/F86-1 -> 0.095862283 | H87: =$G87+(fade_gA-$G87)*1/3 -> 0.083908189 | I87: =$G87+(fade_gA-$G87)*2/3 -> 0.071954094 | J87: =$G87+(fade_gA-$G87)*3/3 -> 0.06
A88: ABF ÷ 營收 | B88: % | D88: =D79/D86 -> 0.58 | E88: =E79/E86 -> 0.61958685 | F88: =F79/F86 -> 0.62844224 | G88: =G79/G86 -> 0.6470324
A89: AI 載板 ÷ 營收 | B89: % | D89: =D81/D86 -> 0.377 | E89: =E81/E86 -> 0.47292613 | F89: =F81/F86 -> 0.49119507 | G89: =G81/G86 -> 0.51214999 | K89: 公司：1Q26 網通 49%、AI 與 HPC 16%（應用別口徑不同）
A90: D. 折舊、毛利與損益
A91: 資本支出 | B91: NT$B | C91: =a25_cx -> 2.422 | D91: =capex26 -> 4 | E91: =cx27 -> 14 | F91: =cx28 -> 18 | G91: =cx29 -> 12 | H91: =H86*H108 -> 12.441724 | I91: =I86*I108 -> 12.731116 | J91: =J86*J108 -> 12.852792
A92: 折舊攤提 ＝ 前一年 ×（1 − 1／年限）＋ 前一年資本支出 ÷ 年限 | B92: NT$B | C92: =a25_da -> 6.894 | D92: =da26 -> 7.1 | E92: =D92*(1-1/life)+D91/life -> 6.7125 | F92: =E92*(1-1/life)+E91/life -> 7.6234375 | G92: =F92*(1-1/life)+F91/life -> 8.9205078 | H92: =H86*H93 -> 9.6690115 | I92: =I86*I93 -> 10.364736 | J92: =J86*J93 -> 10.986621 | K92: 新產能前一年投入、當年開始折舊（近似）
A93: 折舊 ÷ 營收 | B93: % | C93: =C92/C86 -> 0.1716078 | D93: =D92/D86 -> 0.12003807 | E93: =E92/E86 -> 0.083666342 | F93: =F92/F86 -> 0.085884557 | G93: =G92/G86 -> 0.091706017 | H93: =$G93 -> 0.091706017 | I93: =$G93 -> 0.091706017 | J93: =$G93 -> 0.091706017
A94: 漲價溢價營收（相對 FY2026 價格；全數落在毛利） | B94: NT$B | E94: =E81*(1-1/(E66*E67)) -> 4.9490318 | F94: =F81*(1-1/(F66*F67)) -> 3.691561 | G94: =G81*(1-1/(G66*G67)) -> 1.6846769 | K94: AI 載板營收 ×（1 − 1／價格指數）
A95: 毛利 ＝ FY2026 ＋ ABF 現金毛利增量 ＋ 其他產品現金毛利增量 ＋ 溢價 − 折舊增量 | B95: NT$B | C95: =a25_gp -> 3.647 | D95: =a26_gp -> 15.900192 | E95: =$D95+ft_abf*(E79-E94-$D79)+ft_oth*((E86-E79)-($D86-$D79))+E94-(E92-$D92) -> 28.735136 | F95: =$D95+ft_abf*(F79-F94-$D79)+ft_oth*((F86-F79)-($D86-$D79))+F94-(F92-$D92) -> 31.216598 | G95: =$D95+ft_abf*(G79-G94-$D79)+ft_oth*((G86-G79)-($D86-$D79))+G94-(G92-$D92) -> 33.035304 | K95: 流通率為現金毛利口徑；折舊另計
A96: 毛利率 | B96: % | C96: =C95/C86 -> 0.090782366 | D96: =D95/D86 -> 0.26882091 | E96: =E95/E86 -> 0.35816219 | F96: =F95/F86 -> 0.35168173 | G96: =G95/G86 -> 0.33961477
A97: 營業費用 | B97: NT$B | C97: =a25_opx -> 1.665 | D97: =a26_opx -> 1.9 | E97: =D97*(1+phi*E87) -> 2.3063188 | F97: =E97*(1+phi*F87) -> 2.4535192 | G97: =F97*(1+phi*G87) -> 2.5946392
A98: 營業利益 | B98: NT$B | C98: =C95-C97 -> 1.982 | D98: =D95-D97 -> 14.000193 | E98: =E95-E97 -> 26.428817 | F98: =F95-F97 -> 28.763079 | G98: =G95-G97 -> 30.440665
A99: 營業利益率 | B99: % | C99: =C98/C86 -> 0.049336619 | D99: =D98/D86 -> 0.23669805 | E99: =E98/E86 -> 0.32941564 | F99: =F98/F86 -> 0.32404073 | G99: =G98/G86 -> 0.31294095
A100: 營業外淨額 | B100: NT$B | C100: =a25_nonop -> 0.364 | D100: =a26_nonop -> 0.623 | E100: =nonop27 -> 0.6 | F100: =nonop28 -> 0.6 | G100: =nonop29 -> 0.6
A101: 稅前利益 | B101: NT$B | C101: =C98+C100 -> 2.346 | D101: =D98+D100 -> 14.623193 | E101: =E98+E100 -> 27.028817 | F101: =F98+F100 -> 29.363079 | G101: =G98+G100 -> 31.040665
A102: 所得稅 | B102: NT$B | E102: =E101*tax -> 5.6760516 | F102: =F101*tax -> 6.1662465 | G102: =G101*tax -> 6.5185397
A103: 歸屬母公司淨利 | B103: NT$B | C103: =a25_ni -> 1.947 | D103: =a26_ni -> 11.509862 | E103: =E101-E102 -> 21.352765 | F103: =F101-F102 -> 23.196832 | G103: =G101-G102 -> 24.522125 | H103: =H86*H107 -> 26.579733 | I103: =I86*I107 -> 28.492253 | J103: =J86*J107 -> 30.201788
A104: 加權股數 | B104: 十億股 | C104: =a25_sh -> 0.64684385 | D104: =a26_sh -> 0.64586333 | E104: =a26_shend*(1+sh_g) -> 0.64617 | F104: =E104*(1+sh_g) -> 0.64617 | G104: =F104*(1+sh_g) -> 0.64617 | H104: =G104*(1+sh_g) -> 0.64617 | I104: =H104*(1+sh_g) -> 0.64617 | J104: =I104*(1+sh_g) -> 0.64617
A105: EPS（基本） | B105: NT$ | C105: =C103/C104 -> 3.01 | D105: =D103/D104 -> 17.820894 | E105: =E103/E104 -> 33.04512 | F105: =F103/F104 -> 35.898962 | G105: =G103/G104 -> 37.94996 | H105: =H103/H104 -> 41.134272 | I105: =I103/I104 -> 44.094051 | J105: =J103/J104 -> 46.739694
A106: EPS 年增 | B106: % | D106: =D105/C105-1 -> 4.9205629 | E106: =E105/D105-1 -> 0.8542908 | F106: =F105/E105-1 -> 0.086361964 | G106: =G105/F105-1 -> 0.057132507 | H106: =H105/G105-1 -> 0.083908189 | I106: =I105/H105-1 -> 0.071954094 | J106: =J105/I105-1 -> 0.06
A107: 淨利率（歸屬母公司淨利 ÷ 營收） | B107: % | C107: =C103/C86 -> 0.048465387 | D107: =D103/D86 -> 0.1945946 | E107: =E103/E86 -> 0.26614641 | F107: =F103/F86 -> 0.2613322 | G107: =G103/G86 -> 0.25209624 | H107: =$G107+(fade_mA-$G107)*1/3 -> 0.25209624 | I107: =$G107+(fade_mA-$G107)*2/3 -> 0.25209624 | J107: =$G107+(fade_mA-$G107)*3/3 -> 0.25209624
A108: 資本支出 ÷ 營收 | B108: % | C108: =C91/C86 -> 0.060289249 | D108: =D91/D86 -> 0.067627084 | E108: =E91/E86 -> 0.17449963 | F108: =F91/F86 -> 0.20278543 | G108: =G91/G86 -> 0.1233643 | H108: =$G108+($G93*(1+tp_g)^(life/2)-$G108)*1/3 -> 0.11800389 | I108: =$G108+($G93*(1+tp_g)^(life/2)-$G108)*2/3 -> 0.11264348 | J108: =$G108+($G93*(1+tp_g)^(life/2)-$G108)*3/3 -> 0.10728307 | K108: FY2030 起：資本支出率由 FY2029 線性收斂到 折舊率 ×（1＋tp_g）^（年限／2）（穩態更新）；折舊率維持 FY2029
A109: 股東現金流 ＝ 淨利 ＋ 折舊 − 資本支出 | B109: NT$B | E109: =E103+E92-E91 -> 14.065265 | F109: =F103+F92-F91 -> 12.82027 | G109: =G103+G92-G91 -> 21.442633 | H109: =H103+H92-H91 -> 23.80702 | I109: =I103+I92-I91 -> 26.125873 | J109: =J103+J92-J91 -> 28.335617 | K109: 不含營運資金變動
A110: 每股股東現金流 | B110: NT$ | E110: =E109/E104 -> 21.767129 | F110: =F109/F104 -> 19.840398 | G110: =G109/G104 -> 33.184198 | H110: =H109/H104 -> 36.843276 | I110: =I109/I104 -> 40.431888 | J110: =J109/J104 -> 43.851644
A113: 情境 B（平平）：tsmc 顆數係數 B（CY2028 ×0.8、CY2029 ×0.85）；BT 年增 25%／5%／3%
A114: 項目 | B114: 單位 | C114: FY2025A | D114: FY2026（錨點） | E114: FY2027 | F114: FY2028 | G114: FY2029 | H114: FY2030（收斂） | I114: FY2031（收斂） | J114: FY2032（收斂） | K114: 說明
A115: A. AI 加速器載板（口徑與 Ibiden、欣興一致；D 欄＝FY2026 校準年）
...

Sheet Val
A1: Val — P/E 估值（新台幣）。結論用「現價 ÷ FY2027、FY2028 EPS（模型）」；目標價＝DCF 與 Comparable 加權（第 0 節）；十年 P/E 規則值（第 3 節，年底落後 P/E）只作參考
A2: 循環位置：南電不是設備股，不套設備市場見頂年；以本模型營收最高的會計年度為見頂年（比照 Ibiden、欣興；FY(t)＝CY(t)）。營收到 FY2029 仍在增加時，見頂年未知，判為中段
A4: 0. 目標價
A5: 0.1 DCF（股東權益現金流，FY2027–FY2032 明確期＋FY2032 後永續）
A6: 項目 | B6: A（順利） | C6: B（平平） | D6: C（不如預期） | E6: 說明
A7: 情境 EPS（FY2027–FY2032） | E7: PL 頁各情境；FY2030 起為收斂法
A8: FY2027 | B8: =PL!E15 -> 33.04512 | C8: =PL!E29 -> 32.604614 | D8: =PL!E43 -> 31.7236
A9: FY2028 | B9: =PL!F15 -> 35.898962 | C9: =PL!F29 -> 30.611885 | D9: =PL!F43 -> 23.32651
A10: FY2029 | B10: =PL!G15 -> 37.94996 | C10: =PL!G29 -> 32.055099 | D10: =PL!G43 -> 22.661842
A11: FY2030 | B11: =PL!H15 -> 41.134272 | C11: =PL!H29 -> 33.208511 | D11: =PL!H43 -> 21.899528
A12: FY2031 | B12: =PL!I15 -> 44.094051 | C12: =PL!I29 -> 33.854222 | D12: =PL!I43 -> 20.898433
A13: FY2032 | B13: =PL!J15 -> 46.739694 | C13: =PL!J29 -> 33.950948 | D13: =PL!J43 -> 19.676679
A14: 股東現金流＝EPS ×（1 − tp_g ÷ tp_roe） | E14: 方法：南電模型有資本支出與折舊，改用每股（淨利＋折舊－資本支出）（PL 頁「每股股東現金流」；FY2030 起資本支出率收斂到穩態更新）
A15: 參考：再投資率（tp_g ÷ tp_roe，上限 0.8） | B15: =MIN(tp_g/tp_roe,0.8) -> 0.74349442 | E15: ROE 為近三年平均（In 頁 tp_roe）；本模型不採用，只作對照（第 25 列）
A16: FY2027 | B16: =PL!E110 -> 21.767129 | C16: =PL!E163 -> 21.326622 | D16: =PL!E216 -> 20.445609
A17: FY2028 | B17: =PL!F110 -> 19.840398 | C17: =PL!F163 -> 14.553321 | D17: =PL!F216 -> 7.2679461
A18: FY2029 | B18: =PL!G110 -> 33.184198 | C18: =PL!G163 -> 27.289338 | D18: =PL!G216 -> 17.89608
A19: FY2030 | B19: =PL!H110 -> 36.843276 | C19: =PL!H163 -> 28.965823 | D19: =PL!H216 -> 17.800619
A20: FY2031 | B20: =PL!I110 -> 40.431888 | C20: =PL!I163 -> 30.287675 | D20: =PL!I216 -> 17.544646
A21: FY2032 | B21: =PL!J110 -> 43.851644 | C21: =PL!J163 -> 31.191371 | D21: =PL!J216 -> 17.131626
A22: DCF 情境每股價值（折現率 tp_r） | B22: =MAX(0,SUMPRODUCT(B16:B21,1/(1+tp_r)^{1;2;3;4;5;6})+B21*(1+tp_g)/(tp_r-tp_g)/(1+tp_r)^6) -> 565.19359 | C22: =MAX(0,SUMPRODUCT(C16:C21,1/(1+tp_r)^{1;2;3;4;5;6})+C21*(1+tp_g)/(tp_r-tp_g)/(1+tp_r)^6) -> 413.29836 | D22: =MAX(0,SUMPRODUCT(D16:D21,1/(1+tp_r)^{1;2;3;4;5;6})+D21*(1+tp_g)/(tp_r-tp_g)/(1+tp_r)^6) -> 238.38084 | E22: Σ 明確期現金流 ÷ (1＋r)^t ＋ 永續價值 ÷ (1＋r)^6；永續價值＝FY2032 現金流 ×(1＋g)÷(r−g)；基準日 2026 年底；< 0 時取 0（股東有限責任）
A23: DCF 情境價值推到 12 個月後（×(1＋tp_r)） | B23: =B22*(1+tp_r) -> 621.71295 | C23: =C22*(1+tp_r) -> 454.62819 | D23: =D22*(1+tp_r) -> 262.21893
A24: DCF 目標價（情境加權） | B24: =tp_wA*B23+tp_wB*C23+tp_wC*D23 -> 466.27177 | E24: Σ 權重 × 情境價值 ×(1＋r)；權重見 In 頁
A25: 參考：EPS ×（1 − g／ROE）法的 DCF 目標價（情境加權） | B25: =(tp_wA*MAX(0,SUMPRODUCT(B8:B13,1/(1+tp_r)^{1;2;3;4;5;6})+B13*(1+tp_g)/(tp_r-tp_g)/(1+tp_r)^6)+tp_wB*MAX(0,SUMPRODUCT(C8:C13,1/(1+tp_r)^{1;2;3;4;5;6})+C13*(1+tp_g)/(tp_r-tp_g)/(1+tp_r)^6)+tp_wC*MAX(0,SUMPRODUCT(D8:D13,1/(1+tp_r)^{1;2;3;4;5;6})+D13*(1+tp_g)/(tp_r-tp_g)/(1+tp_r)^6))*(1-B15)*(1+tp_r) -> 136.73149 | E25: 近三年 ROE 約 5%（2024 年接近 0）→ 再投資率約 74%；不進目標價
A26: 0.2 Comparable（市場主流同業前瞻 P/E）
A27: 同業與前瞻 P/E | B27: 代號 | C27: 前瞻 12 月 P/E | D27: 日期 | E27: 來源 | F27: 標記
A28: 欣興（Unimicron） | B28: 3037.TW | C28: 42.28 | D28: 2026-10-22 | E28: stockanalysis.com forward PE（分析師共識；價格日期如左；與欣興、Ibiden 模型同一組數字） | F28: Interested-party
A29: 景碩（Kinsus） | B29: 3189.TW | C29: 44.7 | D29: 2026-10-22 | E29: stockanalysis.com forward PE（分析師共識；價格日期如左；與欣興、Ibiden 模型同一組數字） | F29: Interested-party
A30: Ibiden（揖斐電） | B30: 4062.T | C30: 53.97 | D30: 2026-10-16 | E30: stockanalysis.com forward PE（分析師共識；價格日期如左；與欣興、Ibiden 模型同一組數字） | F30: Interested-party
A31: 三星電機（Samsung Electro-Mechanics） | B31: 009150.KS | C31: 43.4 | D31: 2026-08-28 | E31: stockanalysis.com forward PE（分析師共識；價格日期如左；與欣興、Ibiden 模型同一組數字） | F31: Interested-party
A32: AT&S | B32: ATS.VI | C32: 14.91 | D32: 2026-10-23 | E32: stockanalysis.com forward PE（分析師共識；價格日期如左；與欣興、Ibiden 模型同一組數字） | F32: Interested-party
A33: 同業前瞻 P/E 中位數 | B33: =MEDIAN(C28:C32) -> 43.4 | E33: ABF 載板同業：欣興、景碩、Ibiden、三星電機、AT&S（無中國 A 股）；三星電機價格日期較舊
A34: 12 個月後的前瞻 EPS（情境加權） | B34: =tp_wA*(2/12*B8+10/12*B9)+tp_wB*(2/12*C8+10/12*C9)+tp_wC*(2/12*D8+10/12*D9) -> 31.044205 | E34: 約 2027-10 時的未來 12 月 EPS ≈ 2／12 × FY2027＋10／12 × FY2028（會計年度＝日曆年）
A35: Comparable 目標價 | B35: =B33*B34 -> 1347.3185 | E35: 同業中位數 × 前瞻 EPS
A37: 0.3 結論
A38: 項目 | B38: 數值 | E38: 說明
A39: 目標價（DCF 與 Comparable 加權） | B39: =tp_w_dcf*B24+(1-tp_w_dcf)*B35 -> 906.79513 | E39: tp_w_dcf × DCF＋（1 − tp_w_dcf）× Comparable；tp_w_dcf 見 In 頁（0.5）
A40: Comparable 目標價（市場主流同業法） | B40: =B35 -> 1347.3185
A41: 市場共識目標價 | B41: =cons_tp -> 1651.31 | E41: stockanalysis：14 位分析師平均 1,651.31（頁面價格日期 2026-09-07）；10 月美銀 2,000、大和 2,460
A42: 上檔空間：加權目標價 | B42: =B39/px-1 -> -0.28316591 | E42: 現價＝In 頁 px（2026-10-22 收盤）
A43: 上檔空間：Comparable 目標價 | B43: =B40/px-1 -> 0.065073904
A44: 與市場共識目標價的差距：EPS 因素 | B44: =B34/cons_feps-1 -> -0.002741878 | E44: 本模型前瞻 EPS ÷ 共識前瞻 EPS − 1；共識前瞻 EPS＝頁面價格 ÷ 前瞻 P/E（In 頁 cons_feps）
A45: 與市場共識目標價的差距：倍數因素 | B45: =(cons_tp/cons_feps)/B33-1 -> 0.22226654 | E45: ="共識目標價隱含 "&TEXT(cons_tp/cons_feps,"0.0")&"x，同業中位數 "&TEXT(B33,"0.0")&"x" -> 共識目標價隱含 53.0x，同業中位數 43.4x
A46: 價格帶（DCF 不如預期～順利） | B46: =TEXT(D23,"#,##0")&"～"&TEXT(B23,"#,##0") -> 262～622 | E46: C 情境價值～A 情境價值（推到 12 個月後）
A47: 歷史倍數檢查：現價隱含 P/E 的十年分位（A／B／C） | B47: =IF(px/B9>=MAX($B$86:$B$95),1,IF(px/B9<=MIN($B$86:$B$95),0,PERCENTRANK($B$86:$B$95,px/B9))) -> 0.501 | C47: =IF(px/C9>=MAX($B$86:$B$95),1,IF(px/C9<=MIN($B$86:$B$95),0,PERCENTRANK($B$86:$B$95,px/C9))) -> 0.524 | D47: =IF(px/D9>=MAX($B$86:$B$95),1,IF(px/D9<=MIN($B$86:$B$95),0,PERCENTRANK($B$86:$B$95,px/D9))) -> 0.571 | E47: 現價 ÷ 各情境 FY2028 EPS 在 2019–2025 年底 P/E（第 5 節兩來源平均，2016–2018 虧損不計）的分位（超出區間時記 0% 或 100%）；只作檢查，不進目標價
A48: 目標價方法 | B48: DCF：股東現金流＝每股（淨利＋折舊－資本支出），r＝10%、g＝4%，FY2027–32 明確期＋永續，情境價值 < 0 取 0；南電資本支出低（2026 年約 40 億）、折舊約 70 億，現金流高於淨利；新廠資本支出未定，若擴產加速，現金流偏高估；ABF 溢價沿用 Ibiden 模型（2027 持平、之後回落），比券商保守。Comparable：欣興、景碩、Ibiden、三星電機、AT&S 前瞻 P/E 中位數（無 A 股）；同業同處 ABF 短缺溢價期，倍數偏高。情境對應：A＝順利（顆數基準）、B＝平平（顆數 ×0.8／0.85）、C＝不如預期（顆數 ×0.6），皆讀 tsmc 同字母係數；BT 年增 A 最高、C 最低
A51: 1. 價格與市場隱含倍數
A52: 項目 | B52: A | C52: B | D52: C | E52: 說明
A53: 現價（2026-10-22 收盤） | B53: =px -> 1265
A54: 現價 ÷ FY2026 EPS（錨點） | B54: =px/PL!D15 -> 70.984092 | C54: =px/PL!D29 -> 70.984092 | D54: =px/PL!D43 -> 70.984092 | E54: FY2026 三情境相同（錨點）
A55: 現價 ÷ FY2027 EPS（模型） | B55: =px/PL!E15 -> 38.280992 | C55: =px/PL!E29 -> 38.79819 | D55: =px/PL!E43 -> 39.875676 | E55: FY2027 情境差只來自 BT 年增（顆數係數從 CY2028 開始）
A56: 現價 ÷ FY2028 EPS（模型） | B56: =px/PL!F15 -> 35.237788 | C56: =px/PL!F29 -> 41.323819 | D56: =px/PL!F43 -> 54.230143
A57: 現價 ÷ FY2029 EPS（模型） | B57: =px/PL!G15 -> 33.333369 | C57: =px/PL!G29 -> 39.4633 | D57: =px/PL!G43 -> 55.820705
A58: 未來 12 月 EPS（模型 B）≈ 0.2 × FY2026＋0.8 × FY2027 | B58: =0.2*PL!D29+0.8*PL!E29 -> 29.64787
A59: 現價 ÷ 未來 12 月 EPS（模型 B） | B59: =px/B58 -> 42.667484
A60: 近 12 月 P/E（財報狗，10-22） | B60: =pe_ttm -> 148.7
A61: 前瞻 P/E（stockanalysis，價格日期 09-07） | B61: =fpe -> 33.73
A63: 2. 循環位置（本模型營收最高年；FY(t)＝CY(t)）
A64: 情境 | B64: 營收最高年（FY2026–FY2029） | C64: FY2027 判定 | D64: 規則倍數（P/E） | E64: 見頂年是否未知 | F64: 說明
A65: A | B65: =INDEX({2026,2027,2028,2029},MATCH(MAX(PL!D86:G86),PL!D86:G86,0)) -> 2029 | C65: =IF(B65=2029,"中段",IF(2027<B65,"中段",IF(2027=B65,"見頂","谷底"))) -> 中段 | D65: =IF(C65="見頂",pe_peak,IF(C65="谷底",pe_trough,pe_mid)) -> 34.93 | E65: =IF(B65=2029,"是：營收到觀測期末仍在增加","否") -> 是：營收到觀測期末仍在增加 | F65: tools/cycle_position.py excel_rule；營收最高年取代設備市場見頂年
A66: B | B66: =INDEX({2026,2027,2028,2029},MATCH(MAX(PL!D139:G139),PL!D139:G139,0)) -> 2029 | C66: =IF(B66=2029,"中段",IF(2027<B66,"中段",IF(2027=B66,"見頂","谷底"))) -> 中段 | D66: =IF(C66="見頂",pe_peak,IF(C66="谷底",pe_trough,pe_mid)) -> 34.93 | E66: =IF(B66=2029,"是：營收到觀測期末仍在增加","否") -> 是：營收到觀測期末仍在增加 | F66: 同上
A67: C | B67: =INDEX({2026,2027,2028,2029},MATCH(MAX(PL!D192:G192),PL!D192:G192,0)) -> 2027 | C67: =IF(B67=2029,"中段",IF(2027<B67,"中段",IF(2027=B67,"見頂","谷底"))) -> 見頂 | D67: =IF(C67="見頂",pe_peak,IF(C67="谷底",pe_trough,pe_mid)) -> 28.98 | E67: =IF(B67=2029,"是：營收到觀測期末仍在增加","否") -> 否 | F67: 同上
A69: 3. 規則值隱含股價（新台幣；約 FY2027 年底，未折現）＝ FY2027 EPS × 規則倍數
A70: 情境 | B70: FY2027 EPS | C70: （同左） | D70: 規則倍數 | E70: 隱含股價 | F70: 相對現價 | G70: 現價 ÷ FY2027 EPS
A71: A | B71: =PL!E15 -> 33.04512 | C71: =B71 -> 33.04512 | D71: =D65 -> 34.93 | E71: =C71*D71 -> 1154.2661 | F71: =E71/px-1 -> -0.087536715 | G71: =px/C71 -> 38.280992
A72: B | B72: =PL!E29 -> 32.604614 | C72: =B72 -> 32.604614 | D72: =D66 -> 34.93 | E72: =C72*D72 -> 1138.8792 | F72: =E72/px-1 -> -0.099700271 | G72: =px/C72 -> 38.79819
A73: C | B73: =PL!E43 -> 31.7236 | C73: =B73 -> 31.7236 | D73: =D67 -> 28.98 | E73: =C73*D73 -> 919.34994 | F73: =E73/px-1 -> -0.27324115 | G73: =px/C73 -> 39.875676
A75: 4. What must be true：FY2027 年底價 ＝ 現價 ×（1＋報酬）所需的倍數（FY2028 EPS；約 2027 年底的價格看下一年 EPS）
A76: FY2027 年底價 ÷ 現價 | B76: 所需倍數（÷ FY2028 EPS，A） | C76: 所需倍數（÷ FY2028 EPS，B） | D76: 所需倍數（÷ FY2028 EPS，C） | E76: 對照：十年中位數
A77: 0.75 | B77: =px*A77/PL!F15 -> 26.428341 | C77: =px*A77/PL!F29 -> 30.992864 | D77: =px*A77/PL!F43 -> 40.672607 | E77: =pe_mid -> 34.93
A78: 1 | B78: =px*A78/PL!F15 -> 35.237788 | C78: =px*A78/PL!F29 -> 41.323819 | D78: =px*A78/PL!F43 -> 54.230143 | E78: =pe_mid -> 34.93
A79: 1.1 | B79: =px*A79/PL!F15 -> 38.761567 | C79: =px*A79/PL!F29 -> 45.456201 | D79: =px*A79/PL!F43 -> 59.653158 | E79: =pe_mid -> 34.93
A80: 1.21 | B80: =px*A80/PL!F15 -> 42.637723 | C80: =px*A80/PL!F29 -> 50.001821 | D80: =px*A80/PL!F43 -> 65.618473 | E80: =pe_mid -> 34.93
A81: 1.5 | B81: =px*A81/PL!F15 -> 52.856682 | C81: =px*A81/PL!F29 -> 61.985729 | D81: =px*A81/PL!F43 -> 81.345215 | E81: =pe_mid -> 34.93
A82: 讀法：1.00＝價格不變、1.21＝一年約 21%。所需倍數愈高，現價愈依賴「ABF、BT 漲價延續、交換器載板份額守住」。本版未做先驗，無 Andy 合理 P/E 對照。
A84: 5. 十年 P/E（2016–2025 年底；兩來源平均，分位排名用；2016–2018 年 EPS 為負，P/E 無意義，不計）
A85: 年底 | B85: 兩來源平均 P/E | C85: stockanalysis | D85: 自算
A86: 2016 | E86: 不計（EPS 為負，P/E 無意義）
A87: 2017 | E87: 不計（EPS 為負，P/E 無意義）
A88: 2018 | E88: 不計（EPS 為負，P/E 無意義）
A89: 2019 | B89: =AVERAGE(C89:D89) -> 95.729167 | C89: =IF(ISNUMBER(B108),B108,"") | D89: =IF(ISNUMBER(C108),C108,"") -> 95.729167
A90: 2020 | B90: =AVERAGE(C90:D90) -> 32.098765 | C90: =IF(ISNUMBER(B109),B109,"") | D90: =IF(ISNUMBER(C109),C109,"") -> 32.098765
A91: 2021 | B91: =AVERAGE(C91:D91) -> 34.925317 | C91: =IF(ISNUMBER(B110),B110,"") -> 34.93 | D91: =IF(ISNUMBER(C110),C110,"") -> 34.920635
A92: 2022 | B92: =AVERAGE(C92:D92) -> 7.5570383 | C92: =IF(ISNUMBER(B111),B111,"") -> 7.56 | D92: =IF(ISNUMBER(C111),C111,"") -> 7.5540765
A93: 2023 | B93: =AVERAGE(C93:D93) -> 27.942222 | C93: =IF(ISNUMBER(B112),B112,"") -> 27.94 | D93: =IF(ISNUMBER(C112),C112,"") -> 27.944444
A94: 2024 | B94: =AVERAGE(C94:D94) -> 410.86125 | C94: =IF(ISNUMBER(B113),B113,"") -> 413.91 | D94: =IF(ISNUMBER(C113),C113,"") -> 407.8125
A95: 2025 | B95: =AVERAGE(C95:D95) -> 80.028223 | C95: =IF(ISNUMBER(B114),B114,"") -> 79.99 | D95: =IF(ISNUMBER(C114),C114,"") -> 80.066445
A96: 年數 | B96: =COUNT($B$86:$B$95) -> 7
A100: 6. 十年倍數與規則值（2016–2025 年底；見頂年 25 分位、中段中位數、谷底 75 分位）
A101: 規則（Andy 2026-10-13）：合理倍數＝2016–2025 年底 P/E 依循環位置取分位，兩個來源分別取分位再平均。南電的落後 P/E 與盈餘反向：盈餘低谷年（2019、2024）P/E 96–414x，高峰年（2022）約 8x；2016–2018 年虧損不計，十年多為 AI 載板需求前的循環，套用在 FY2027 EPS 時偏誤方向不明確。
A103: P/E：十年歷史倍數
A104: 年底 | B104: stockanalysis（年度 P/E） | C104: 自算（digrin 12 月未調整股價 ÷ 年度 EPS） | D104: 標記／說明
A105: 2016 | D105: stockanalysis（年度 P/E）：Interested-party（資料商；只有 2021–2025 共 5 年）；自算（digrin 12 月未調整股價 ÷ 年度 EPS）：Derived（價格為月資料的 12 月值；EPS 取自 wantgoo 歷年股利表；2016–2018 EPS 為負不計，2019–2025 共 7 年）
A106: 2017
A107: 2018
A108: 2019 | C108: =45.95/0.48 -> 95.729167
A109: 2020 | C109: =182/5.67 -> 32.098765
A110: 2021 | B110: 34.93 | C110: =572/16.38 -> 34.920635
A111: 2022 | B111: 7.56 | C111: =227/30.05 -> 7.5540765
A112: 2023 | B112: 27.94 | C112: =251.5/9 -> 27.944444
...

Sheet Recon
A1: Recon — 本模型 vs 券商、共識與市場口徑。只作事後對照，不為對上數字而調參數。FactSet 共識為 2026-06（2Q26 財報前），10 月券商數字只取得美銀一家完整年度預估
A3: 項目 | B3: 對照值 | C3: 模型 A | D3: 差距 A | E3: 模型 B | F3: 差距 B | G3: 模型 C | H3: 差距 C | I3: 對照來源 | J3: 說明
A4: A. EPS 與營收 vs 共識、券商
A5: FY2026 EPS vs 美銀 18.44（2026-10-02） | B5: 18.44 | C5: =PL!D105 -> 17.820894 | D5: =C5/B5-1 -> -0.03357406 | E5: =PL!D158 -> 17.820894 | F5: =E5/B5-1 -> -0.03357406 | G5: =PL!D211 -> 17.820894 | H5: =G5/B5-1 -> -0.03357406 | I5: TechNews（美銀） | J5: FactSet 2026-06 平均 13.19 為 2Q26 財報之前
A6: FY2026 EPS vs 凱基 17.27（2026-07-20） | B6: 17.27 | C6: =PL!D105 -> 17.820894 | D6: =C6/B6-1 -> 0.03189892 | E6: =PL!D158 -> 17.820894 | F6: =E6/B6-1 -> 0.03189892 | G6: =PL!D211 -> 17.820894 | H6: =G6/B6-1 -> 0.03189892 | I6: 凱基
A7: FY2027 EPS vs 券商平均（美銀 43.80、凱基 38.88） | B7: =bk_eps27 -> 41.34 | C7: =PL!E105 -> 33.04512 | D7: =C7/B7-1 -> -0.20065021 | E7: =PL!E158 -> 32.604614 | F7: =E7/B7-1 -> -0.21130591 | G7: =PL!E211 -> 31.7236 | H7: =G7/B7-1 -> -0.23261731 | I7: TechNews（美銀）、凱基 | J7: 差距超過 30% 的原因見 README
A8: FY2027 EPS vs FactSet 平均 32.12（2026-06） | B8: =cons_eps27 -> 32.12 | C8: =PL!E105 -> 33.04512 | D8: =C8/B8-1 -> 0.028802005 | E8: =PL!E158 -> 32.604614 | F8: =E8/B8-1 -> 0.015087601 | G8: =PL!E211 -> 31.7236 | H8: =G8/B8-1 -> -0.012341207 | I8: 鉅亨（FactSet 14 位）
A9: FY2028 EPS vs FactSet 平均 59.21（2026-06） | B9: =cons_eps28 -> 59.21 | C9: =PL!F105 -> 35.898962 | D9: =C9/B9-1 -> -0.39370103 | E9: =PL!F158 -> 30.611885 | F9: =E9/B9-1 -> -0.48299468 | G9: =PL!F211 -> 23.32651 | H9: =G9/B9-1 -> -0.60603766 | I9: 鉅亨（FactSet）
A10: FY2028 EPS vs 券商平均（美銀 70.09、凱基 61.35） | B10: =bk_eps28 -> 65.72 | C10: =PL!F105 -> 35.898962 | D10: =C10/B10-1 -> -0.45375895 | E10: =PL!F158 -> 30.611885 | F10: =E10/B10-1 -> -0.53420747 | G10: =PL!F211 -> 23.32651 | H10: =G10/B10-1 -> -0.64506223 | I10: TechNews（美銀）、凱基
A11: FY2027 營收 vs FactSet 平均（2026-06） | B11: =cons_rev27 -> 90.26 | C11: =PL!E86 -> 80.229395 | D11: =C11/B11-1 -> -0.11113013 | E11: =PL!E139 -> 79.283028 | F11: =E11/B11-1 -> -0.12161502 | G11: =PL!E192 -> 77.390295 | H11: =G11/B11-1 -> -0.14258481 | I11: 鉅亨（FactSet） | J11: 美銀 90.33
A12: FY2028 營收 vs FactSet 平均（2026-06） | B12: =cons_rev28 -> 133.54 | C12: =PL!F86 -> 88.763775 | D12: =C12/B12-1 -> -0.33530197 | E12: =PL!F139 -> 79.966387 | F12: =E12/B12-1 -> -0.40118026 | G12: =PL!F192 -> 67.77289 | H12: =G12/B12-1 -> -0.49248997 | I12: 鉅亨（FactSet） | J12: 美銀 120.65
A13: 模型前瞻 12 月 EPS（0.2 × FY2026＋0.8 × FY2027）vs 頁面價格 ÷ 前瞻 P/E | B13: =cons_feps -> 31.129558 | C13: =0.2*PL!D105+0.8*PL!E105 -> 30.000275 | D13: =C13/B13-1 -> -0.036276875 | E13: =0.2*PL!D158+0.8*PL!E158 -> 29.64787 | F13: =E13/B13-1 -> -0.047597476 | G13: =0.2*PL!D211+0.8*PL!E211 -> 28.943059 | H13: =G13/B13-1 -> -0.070238679 | I13: stockanalysis（推導） | J13: 口徑不同，只作量級比較
A14: B. 錨點與毛利率
A15: 3Q26 毛利率（假設）vs 法人估 28.1%（百分點） | B15: 0.281 | C15: =Q!E6 -> 0.3 | D15: =C15-B15 -> 0.019 | E15: =Q!E6 -> 0.3 | F15: =E15-B15 -> 0.019 | G15: =Q!E6 -> 0.3 | H15: =G15-B15 -> 0.019 | I15: 三立 2026-07-27（法人） | J15: 3Q26 財報約 10 月底
A16: 3Q26 EPS（模型）vs 大和估 5.62 | B16: 5.62 | C16: =Q!E14 -> 5.5795271 | D16: =C16/B16-1 -> -0.0072015908 | E16: =Q!E14 -> 5.5795271 | F16: =E16/B16-1 -> -0.0072015908 | G16: =Q!E14 -> 5.5795271 | H16: =G16/B16-1 -> -0.0072015908 | I16: TechNews（大和）
A17: 4Q26 毛利率（假設）vs 美銀估 32.5%（百分點） | B17: 0.325 | C17: =Q!F6 -> 0.325 | D17: =C17-B17 -> 0 | E17: =Q!F6 -> 0.325 | F17: =E17-B17 -> 0 | G17: =Q!F6 -> 0.325 | H17: =G17-B17 -> 0 | I17: TechNews（美銀）：32–33%
A18: FY2027 毛利率 vs 美銀 39.9%（百分點） | B18: 0.399 | C18: =PL!E96 -> 0.35816219 | D18: =C18-B18 -> -0.040837808 | E18: =PL!E149 -> 0.35766279 | F18: =E18-B18 -> -0.041337207 | G18: =PL!E202 -> 0.35662735 | H18: =G18-B18 -> -0.042372647 | I18: TechNews（美銀） | J18: 凱基 37.4%
A19: FY2028 毛利率 vs 美銀 46.6%（百分點） | B19: 0.466 | C19: =PL!F96 -> 0.35168173 | D19: =C19-B19 -> -0.11431827 | E19: =PL!F149 -> 0.33437169 | F19: =E19-B19 -> -0.13162831 | G19: =PL!F202 -> 0.30341516 | H19: =G19-B19 -> -0.16258484 | I19: TechNews（美銀） | J19: 凱基 42.1%
A20: C. 產能、份額與 AI 口徑
A21: FY2027 ABF 需求滿足率（< 100%＝產能受限） | C21: =PL!E80 -> 0.95142541 | E21: =PL!E133 -> 0.95142541 | G21: =PL!E186 -> 0.95142541 | I21: PL 頁 | J21: 凱基：ABF 供需缺口 2027 年 22%、2028 年 29%
A22: FY2028 ABF 需求滿足率 | C22: =PL!F80 -> 0.95637753 | E22: =PL!F133 -> 1 | G22: =PL!F186 -> 1 | I22: PL 頁
A23: FY2026 AI 載板占營收 | C23: =PL!D89 -> 0.377 | E23: =PL!D142 -> 0.377 | G23: =PL!D195 -> 0.377 | I23: PL 頁 | J23: 公司應用別：網通 49%、AI 與 HPC 16%（1Q26）
A24: FY2027 份額合計：Ibiden＋欣興＋南電（NVIDIA） | C24: =Units!D10 -> 0.965 | E24: =Units!D10 -> 0.965 | G24: =Units!D10 -> 0.965 | I24: Units 頁 | J24: 應 ≤ 100%
A25: FY2027 份額合計：Ibiden＋欣興＋南電（非 NVIDIA） | C25: =Units!D14 -> 0.845 | E25: =Units!D14 -> 0.845 | G25: =Units!D14 -> 0.845 | I25: Units 頁 | J25: 應 ≤ 100%
A26: FY2027 每顆 NVIDIA 加速器的南電營收（US$） | C26: =Units!D15 -> 8.7652129 | E26: =Units!D15 -> 8.7652129 | G26: =Units!D15 -> 8.7652129 | I26: Units 頁 | J26: Ibiden 同期約 169（ibiden/dist Units 頁）
A27: FY2027 每 GW 南電 AI 載板營收（US$M） | C27: =Units!D19 -> 28.035243 | E27: =Units!D19 -> 28.035243 | G27: =Units!D19 -> 28.035243 | I27: Units 頁 | J27: Ibiden 同期約 62（只含加速器載板）
A28: D. 資本支出
A29: FY2027＋FY2028 資本支出 vs 凱基 2025–28 合計約 416 億扣除 2025–26（約 64 億） | B29: 35.2 | C29: =PL!E91+PL!F91 -> 32 | D29: =C29/B29-1 -> -0.090909091 | E29: =PL!E144+PL!F144 -> 32 | F29: =E29/B29-1 -> -0.090909091 | G29: =PL!E197+PL!F197 -> 32 | H29: =G29/B29-1 -> -0.090909091 | I29: 凱基（US$12.8 億 × 32.5）

Sheet Sens
A1: Sens — 一次動一個輸入（情境 A；FY2026 恆等於錨點，其他 AI 載板在每個案例內重新校準）：對 FY2027、FY2028 營收、毛利率與 EPS 的影響。每個案例是一個完整推導區塊（本頁下方）
A3: 案例 | B3: 設定 | C3: FY2027 營收 | D3: FY2027 毛利率 | E3: FY2027 EPS | F3: FY2027 EPS 相對基準 | G3: FY2028 營收 | H3: FY2028 毛利率 | I3: FY2028 EPS | J3: FY2028 EPS 相對基準
A4: 基準（情境 A） | B4: PL 區塊 A | C4: =PL!E86 -> 80.229395 | D4: =PL!E96 -> 0.35816219 | E4: =PL!E105 -> 33.04512 | F4: =E4/E$4-1 -> 0 | G4: =PL!F86 -> 88.763775 | H4: =PL!F96 -> 0.35168173 | I4: =PL!F105 -> 35.898962 | J4: =I4/I$4-1 -> 0
A5: AI 部署 ×0.8 | B5: FY2027 起顆數與其他 AI ×0.8 | C5: =E76 -> 74.791325 | D5: =E86 -> 0.3425834 | E5: =E95 -> 29.367504 | F5: =E5/E$4-1 -> -0.11129077 | G5: =F76 -> 82.190348 | H5: =F86 -> 0.33614751 | I5: =F95 -> 31.660027 | J5: =I5/I$4-1 -> -0.1180796
A6: AI 部署 ×1.2 | B6: ×1.2 | C6: =E129 -> 80.229395 | D6: =E139 -> 0.35942896 | E6: =E148 -> 33.169375 | F6: =E6/E$4-1 -> 0.0037601413 | G6: =F129 -> 88.763775 | H6: =F139 -> 0.35246721 | I6: =F148 -> 35.984203 | J6: =I6/I$4-1 -> 0.0023744767
A7: ABF 產能 低 | B7: 產能指數 1.10／1.20／1.35 | C7: =E182 -> 76.086971 | D7: =E192 -> 0.3477299 | E7: =E201 -> 30.358383 | F7: =E7/E$4-1 -> -0.081305125 | G7: =F182 -> 82.565674 | H7: =F192 -> 0.33806374 | I7: =F201 -> 31.997871 | J7: =I7/I$4-1 -> -0.10866864
A8: ABF 產能 高 | B8: 1.30／1.50／1.85 | C8: =E235 -> 82.767269 | D8: =E245 -> 0.36403772 | E8: =E254 -> 34.691162 | F8: =E8/E$4-1 -> 0.049811951 | G8: =F235 -> 91.308155 | H8: =F245 -> 0.35673679 | I8: =F254 -> 37.499137 | J8: =I8/I$4-1 -> 0.044574421
A9: ABF 溢價 低（Ibiden 低值） | B9: 0.95／0.85／0.75 | C9: =E288 -> 77.743941 | D9: =E298 -> 0.34118502 | E9: =E307 -> 30.401683 | F9: =E9/E$4-1 -> -0.079994779 | G9: =F288 -> 82.89189 | H9: =F298 -> 0.31362716 | I9: =F307 -> 29.646556 | J9: =I9/I$4-1 -> -0.17416677
A10: ABF 溢價 高（Ibiden 高值） | B10: 1.05／1.05／1.00 | C10: =E341 -> 82.714848 | D10: =E351 -> 0.37436388 | E10: =E360 -> 35.713312 | F10: =E10/E$4-1 -> 0.080743878 | G10: =F341 -> 94.63566 | H10: =F351 -> 0.38606213 | I10: =F360 -> 42.27399 | J10: =I10/I$4-1 -> 0.17758251
A11: 漲價年度化 8% | B11: 基準 15% | C11: =E394 -> 77.203625 | D11: =E404 -> 0.33738746 | E11: =E413 -> 29.830589 | F11: =E11/E$4-1 -> -0.097277026 | G11: =F394 -> 85.368294 | H11: =F404 -> 0.3301536 | I11: =F413 -> 32.269008 | J11: =I11/I$4-1 -> -0.10111585
A12: 漲價年度化 22% | C12: =E447 -> 83.255164 | D12: =E457 -> 0.37778755 | E12: =E466 -> 36.296364 | F12: =E12/E$4-1 -> 0.098388003 | G12: =F447 -> 92.159256 | H12: =F457 -> 0.3719818 | I12: =F466 -> 39.569311 | J12: =I12/I$4-1 -> 0.10224109
A13: ABF 現金毛利率 40% | B13: 基準 50% | C13: =E500 -> 80.229395 | D13: =E510 -> 0.34513173 | E13: =E519 -> 31.766994 | F13: =E13/E$4-1 -> -0.038678216 | G13: =F500 -> 88.763775 | H13: =F510 -> 0.33164477 | I13: =F519 -> 33.724519 | J13: =I13/I$4-1 -> -0.060571179
A14: ABF 現金毛利率 60% | C14: =E553 -> 80.229395 | D14: =E563 -> 0.37119266 | E14: =E572 -> 34.323247 | F14: =E14/E$4-1 -> 0.038678216 | G14: =F553 -> 88.763775 | H14: =F563 -> 0.37171869 | I14: =F572 -> 38.073404 | J14: =I14/I$4-1 -> 0.060571179
A15: 其他產品現金毛利率 25% | B15: 基準 40% | C15: =E606 -> 80.229395 | D15: =E616 -> 0.34754601 | E15: =E625 -> 32.003805 | F15: =E15/E$4-1 -> -0.031511914 | G15: =F606 -> 88.763775 | H15: =F616 -> 0.33792823 | I15: =F625 -> 34.40641 | J15: =I15/I$4-1 -> -0.041576453
A16: 其他產品現金毛利率 55% | C16: =E659 -> 80.229395 | D16: =E669 -> 0.36877837 | E16: =E678 -> 34.086435 | F16: =E16/E$4-1 -> 0.031511914 | G16: =F659 -> 88.763775 | H16: =F669 -> 0.36543523 | I16: =F678 -> 37.391513 | J16: =I16/I$4-1 -> 0.041576453
A17: BT 年增 走 C 路徑 | B17: 15%／0%／0% | C17: =E712 -> 77.390295 | D17: =E722 -> 0.35662735 | E17: =E731 -> 31.7236 | F17: =E17/E$4-1 -> -0.03999138 | G17: =F712 -> 83.464123 | H17: =F722 -> 0.3486137 | I17: =F731 -> 33.424482 | J17: =I17/I$4-1 -> -0.068929003
A18: 折舊年限 6 年 | B18: 基準 8 年 | C18: =E765 -> 80.229395 | D18: =E775 -> 0.35977216 | E18: =E784 -> 33.203038 | F18: =E18/E$4-1 -> 0.0047788502 | G18: =F765 -> 88.763775 | H18: =F775 -> 0.34947354 | I18: =F784 -> 35.659326 | J18: =I18/I$4-1 -> -0.0066752859
A19: 折舊年限 10 年 | C19: =E818 -> 80.229395 | D19: =E828 -> 0.35719621 | E19: =E837 -> 32.95037 | F19: =E19/E$4-1 -> -0.0028673101 | G19: =F818 -> 88.763775 | H19: =F828 -> 0.35294843 | I19: =F837 -> 36.036427 | J19: =I19/I$4-1 -> 0.0038292136
A20: 資本支出 低 | B20: 每年 60 億 | C20: =E871 -> 80.229395 | D20: =E881 -> 0.35816219 | E20: =E890 -> 33.04512 | F20: =E20/E$4-1 -> 0 | G20: =F871 -> 88.763775 | H20: =F881 -> 0.36294759 | I20: =F890 -> 37.12155 | J20: =I20/I$4-1 -> 0.034056374
A21: 資本支出 高 | B21: 200／240／200 億 | C21: =E924 -> 80.229395 | D21: =E934 -> 0.35816219 | E21: =E943 -> 33.04512 | F21: =E21/E$4-1 -> 0 | G21: =F924 -> 88.763775 | H21: =F934 -> 0.34323234 | I21: =F943 -> 34.982021 | J21: =I21/I$4-1 -> -0.025542281
A22: 南電 NVIDIA 份額 低 | B22: 1% | C22: =E977 -> 80.229395 | D22: =E987 -> 0.35797808 | E22: =E996 -> 33.027061 | F22: =E22/E$4-1 -> -0.0005465116 | G22: =F977 -> 88.763775 | H22: =F987 -> 0.35145834 | I22: =F996 -> 35.874719 | J22: =I22/I$4-1 -> -0.0006752954
A23: 南電 NVIDIA 份額 高 | B23: 3%→6% | C23: =E1030 -> 80.229395 | D23: =E1040 -> 0.35833948 | E23: =E1049 -> 33.06251 | F23: =E23/E$4-1 -> 0.00052625162 | G23: =F1030 -> 88.763775 | H23: =F1040 -> 0.3517939 | I23: =F1049 -> 35.911135 | J23: =I23/I$4-1 -> 0.00033910179
A24: 南電 ASIC 份額 低 | B24: 3% | C24: =E1083 -> 80.229395 | D24: =E1093 -> 0.35781662 | E24: =E1102 -> 33.011224 | F24: =E24/E$4-1 -> -0.0010257682 | G24: =F1083 -> 86.916229 | H24: =F1093 -> 0.34735845 | I24: =F1102 -> 34.684143 | J24: =I24/I$4-1 -> -0.033839946
A25: 南電 ASIC 份額 高 | B25: 8%→10% | C25: =E1136 -> 80.229395 | D25: =E1146 -> 0.358366 | E25: =E1155 -> 33.065111 | F25: =E25/E$4-1 -> 0.00060495349 | G25: =F1136 -> 88.763775 | H25: =F1146 -> 0.35189706 | I25: =F1155 -> 35.92233 | J25: =I25/I$4-1 -> 0.00065095175
A26: 交換器載板彈性 0.3 | B26: 基準 0.5 | C26: =E1189 -> 78.906804 | D26: =E1199 -> 0.35419514 | E26: =E1208 -> 32.11444 | F26: =E26/E$4-1 -> -0.028163942 | G26: =F1189 -> 86.572342 | H26: =F1199 -> 0.34658396 | I26: =F1208 -> 34.465763 | J26: =I26/I$4-1 -> -0.039923128
A27: 交換器載板彈性 0.8 | C27: =E1242 -> 80.229395 | D27: =E1252 -> 0.35927157 | E27: =E1261 -> 33.153936 | F27: =E27/E$4-1 -> 0.003292948 | G27: =F1242 -> 88.763775 | H27: =F1252 -> 0.35243784 | I27: =F1261 -> 35.981016 | J27: =I27/I$4-1 -> 0.0022856925
A28: 營業費用彈性 1.0 | B28: 基準 0.6 | C28: =E1295 -> 80.229395 | D28: =E1305 -> 0.35816219 | E28: =E1314 -> 32.713947 | F28: =E28/E$4-1 -> -0.010021867 | G28: =F1295 -> 88.763775 | H28: =F1305 -> 0.35168173 | I28: =F1314 -> 35.412583 | J28: =I28/I$4-1 -> -0.013548563
A29: 稅率 24% | B29: 基準 21% | C29: =E1348 -> 80.229395 | D29: =E1358 -> 0.35816219 | E29: =E1367 -> 31.790242 | F29: =E29/E$4-1 -> -0.037974684 | G29: =F1348 -> 88.763775 | H29: =F1358 -> 0.35168173 | I29: =F1367 -> 34.53571 | J29: =I29/I$4-1 -> -0.037974684
A30: 業外 0 | B30: 每年 0（基準 6 億） | C30: =E1401 -> 80.229395 | D30: =E1411 -> 0.35816219 | E30: =E1420 -> 32.311567 | F30: =E30/E$4-1 -> -0.02219853 | G30: =F1401 -> 88.763775 | H30: =F1411 -> 0.35168173 | I30: =F1420 -> 35.165409 | J30: =I30/I$4-1 -> -0.020433825
A31: 情境 B | B31: tsmc 顆數係數 B；BT 年增較低 | C31: =PL!E139 -> 79.283028 | D31: =PL!E149 -> 0.35766279 | E31: =PL!E158 -> 32.604614 | F31: =E31/E$4-1 -> -0.01333046 | G31: =PL!F139 -> 79.966387 | H31: =PL!F149 -> 0.33437169 | I31: =PL!F158 -> 30.611885 | J31: =I31/I$4-1 -> -0.1472766
A32: 情境 C | B32: tsmc 顆數係數 C；BT 年增最低 | C32: =PL!E192 -> 77.390295 | D32: =PL!E202 -> 0.35662735 | E32: =PL!E211 -> 31.7236 | F32: =E32/E$4-1 -> -0.03999138 | G32: =PL!F192 -> 67.77289 | H32: =PL!F202 -> 0.30341516 | I32: =PL!F211 -> 23.32651 | J32: =I32/I$4-1 -> -0.35021769
A34: 讀法：漲價年度化與 ABF 溢價直接決定毛利（溢價全數落在毛利）；ABF 產能受限時，份額與部署的上修只部分轉成營收；南電加速器份額小，NVIDIA／ASIC 份額的影響有限；FY2027 情境差只來自 BT 年增。
A36: 目標價參數（只改 DCF 參數；PL 收斂法的 fade_g 與資本支出率路徑不隨 tp_g 變動）
A37: 案例 | B37: 設定 | C37: DCF 目標價 | D37: Comparable 目標價 | E37: 加權目標價 | F37: 相對基準
A38: 基準 | B38: r 10%、g 4%、DCF 權重 0.5 | C38: =(tp_wA*MAX(0,SUMPRODUCT(Val!B16:B21,1/(1+tp_r)^{1;2;3;4;5;6})+Val!B21*(1+tp_g)/(tp_r-tp_g)/(1+tp_r)^6)+tp_wB*MAX(0,SUMPRODUCT(Val!C16:C21,1/(1+tp_r)^{1;2;3;4;5;6})+Val!C21*(1+tp_g)/(tp_r-tp_g)/(1+tp_r)^6)+tp_wC*MAX(0,SUMPRODUCT(Val!D16:D21,1/(1+tp_r)^{1;2;3;4;5;6})+Val!D21*(1+tp_g)/(tp_r-tp_g)/(1+tp_r)^6))*(1+tp_r) -> 466.27177 | D38: =Val!B35 -> 1347.3185 | E38: =tp_w_dcf*C38+(1-tp_w_dcf)*D38 -> 906.79513 | F38: =E38/E$38-1 -> 0
A39: 折現率 +1pt | B39: r 11% | C39: =(tp_wA*MAX(0,SUMPRODUCT(Val!B16:B21,1/(1+(tp_r+0.01))^{1;2;3;4;5;6})+Val!B21*(1+tp_g)/((tp_r+0.01)-tp_g)/(1+(tp_r+0.01))^6)+tp_wB*MAX(0,SUMPRODUCT(Val!C16:C21,1/(1+(tp_r+0.01))^{1;2;3;4;5;6})+Val!C21*(1+tp_g)/((tp_r+0.01)-tp_g)/(1+(tp_r+0.01))^6)+tp_wC*MAX(0,SUMPRODUCT(Val!D16:D21,1/(1+(tp_r+0.01))^{1;2;3;4;5;6})+Val!D21*(1+tp_g)/((tp_r+0.01)-tp_g)/(1+(tp_r+0.01))^6))*(1+(tp_r+0.01)) -> 400.92572 | D39: =Val!B35 -> 1347.3185 | E39: =tp_w_dcf*C39+(1-tp_w_dcf)*D39 -> 874.1221 | F39: =E39/E$38-1 -> -0.036031319
A40: 折現率 −1pt | B40: r 9% | C40: =(tp_wA*MAX(0,SUMPRODUCT(Val!B16:B21,1/(1+(tp_r-0.01))^{1;2;3;4;5;6})+Val!B21*(1+tp_g)/((tp_r-0.01)-tp_g)/(1+(tp_r-0.01))^6)+tp_wB*MAX(0,SUMPRODUCT(Val!C16:C21,1/(1+(tp_r-0.01))^{1;2;3;4;5;6})+Val!C21*(1+tp_g)/((tp_r-0.01)-tp_g)/(1+(tp_r-0.01))^6)+tp_wC*MAX(0,SUMPRODUCT(Val!D16:D21,1/(1+(tp_r-0.01))^{1;2;3;4;5;6})+Val!D21*(1+tp_g)/((tp_r-0.01)-tp_g)/(1+(tp_r-0.01))^6))*(1+(tp_r-0.01)) -> 557.81032 | D40: =Val!B35 -> 1347.3185 | E40: =tp_w_dcf*C40+(1-tp_w_dcf)*D40 -> 952.5644 | F40: =E40/E$38-1 -> 0.050473669
A41: 長期成長 +1pt | B41: g 5% | C41: =(tp_wA*MAX(0,SUMPRODUCT(Val!B16:B21,1/(1+tp_r)^{1;2;3;4;5;6})+Val!B21*(1+(tp_g+0.01))/(tp_r-(tp_g+0.01))/(1+tp_r)^6)+tp_wB*MAX(0,SUMPRODUCT(Val!C16:C21,1/(1+tp_r)^{1;2;3;4;5;6})+Val!C21*(1+(tp_g+0.01))/(tp_r-(tp_g+0.01))/(1+tp_r)^6)+tp_wC*MAX(0,SUMPRODUCT(Val!D16:D21,1/(1+tp_r)^{1;2;3;4;5;6})+Val!D21*(1+(tp_g+0.01))/(tp_r-(tp_g+0.01))/(1+tp_r)^6))*(1+tp_r) -> 539.53066 | D41: =Val!B35 -> 1347.3185 | E41: =tp_w_dcf*C41+(1-tp_w_dcf)*D41 -> 943.42457 | F41: =E41/E$38-1 -> 0.040394402
A42: 長期成長 −1pt | B42: g 3% | C42: =(tp_wA*MAX(0,SUMPRODUCT(Val!B16:B21,1/(1+tp_r)^{1;2;3;4;5;6})+Val!B21*(1+(tp_g-0.01))/(tp_r-(tp_g-0.01))/(1+tp_r)^6)+tp_wB*MAX(0,SUMPRODUCT(Val!C16:C21,1/(1+tp_r)^{1;2;3;4;5;6})+Val!C21*(1+(tp_g-0.01))/(tp_r-(tp_g-0.01))/(1+tp_r)^6)+tp_wC*MAX(0,SUMPRODUCT(Val!D16:D21,1/(1+tp_r)^{1;2;3;4;5;6})+Val!D21*(1+(tp_g-0.01))/(tp_r-(tp_g-0.01))/(1+tp_r)^6))*(1+tp_r) -> 413.94399 | D42: =Val!B35 -> 1347.3185 | E42: =tp_w_dcf*C42+(1-tp_w_dcf)*D42 -> 880.63124 | F42: =E42/E$38-1 -> -0.028853144
A43: DCF 權重 0.3 | C43: =(tp_wA*MAX(0,SUMPRODUCT(Val!B16:B21,1/(1+tp_r)^{1;2;3;4;5;6})+Val!B21*(1+tp_g)/(tp_r-tp_g)/(1+tp_r)^6)+tp_wB*MAX(0,SUMPRODUCT(Val!C16:C21,1/(1+tp_r)^{1;2;3;4;5;6})+Val!C21*(1+tp_g)/(tp_r-tp_g)/(1+tp_r)^6)+tp_wC*MAX(0,SUMPRODUCT(Val!D16:D21,1/(1+tp_r)^{1;2;3;4;5;6})+Val!D21*(1+tp_g)/(tp_r-tp_g)/(1+tp_r)^6))*(1+tp_r) -> 466.27177 | D43: =Val!B35 -> 1347.3185 | E43: =0.3*C43+(1-0.3)*D43 -> 1083.0045 | F43: =E43/E$38-1 -> 0.19432101
A44: DCF 權重 0.7 | C44: =(tp_wA*MAX(0,SUMPRODUCT(Val!B16:B21,1/(1+tp_r)^{1;2;3;4;5;6})+Val!B21*(1+tp_g)/(tp_r-tp_g)/(1+tp_r)^6)+tp_wB*MAX(0,SUMPRODUCT(Val!C16:C21,1/(1+tp_r)^{1;2;3;4;5;6})+Val!C21*(1+tp_g)/(tp_r-tp_g)/(1+tp_r)^6)+tp_wC*MAX(0,SUMPRODUCT(Val!D16:D21,1/(1+tp_r)^{1;2;3;4;5;6})+Val!D21*(1+tp_g)/(tp_r-tp_g)/(1+tp_r)^6))*(1+tp_r) -> 466.27177 | D44: =Val!B35 -> 1347.3185 | E44: =0.7*C44+(1-0.7)*D44 -> 730.58578 | F44: =E44/E$38-1 -> -0.19432101
A50: 案例區塊：AI 部署 ×0.8（情境 A）
A51: 項目 | B51: 單位 | C51: FY2025A | D51: FY2026（錨點） | E51: FY2027 | F51: FY2028 | G51: FY2029 | H51: FY2030（收斂） | I51: FY2031（收斂） | J51: FY2032（收斂） | K51: 說明
A52: A. AI 加速器載板（口徑與 Ibiden、欣興一致；D 欄＝FY2026 校準年）
A53: NVIDIA 加速器顆數 × 情境係數 | B53: 百萬顆 | D53: =(u_bw_26+u_rb_26+u_ru_26+u_hp_26)*1 -> 7.6 | E53: =(u_bw_27+u_rb_27+u_ru_27+u_hp_27)*1*0.8 -> 7.76 | F53: =(u_bw_28+u_rb_28+u_ru_28+u_hp_28)*um28_A*0.8 -> 7.6 | G53: =(u_bw_28*(1+g29_bw)+u_rb_28*(1+g29_rb)+u_ru_28*(1+g29_ru)+u_hp_28*(1+g29_hp))*um29_A*0.8 -> 8.48 | K53: markets/network In：Blackwell、Rubin、Rubin Ultra、Hopper
A54: 非 NVIDIA 加速器顆數 × 情境係數 | B54: 百萬顆 | D54: =(u_amd_26+u_tpu_26+u_trn_26+u_oth_26)*1 -> 7.6 | E54: =(u_amd_27+u_tpu_27+u_trn_27+u_oth_27)*1*0.8 -> 11.2 | F54: =(u_amd_28+u_tpu_28+u_trn_28+u_oth_28)*um28_A*0.8 -> 13.6 | G54: =(u_amd_28*(1+g29_amd)+u_tpu_28*(1+g29_tpu)+u_trn_28*(1+g29_trn)+u_oth_28*(1+g29_oth))*um29_A*0.8 -> 15.64 | K54: AMD、TPU、Trainium、其他 ASIC
A55: 每顆載板面積與層數指數（FY2026＝1） | B55: x | D55: =1 -> 1 | E55: =D55*(1+g_asp) -> 1.18 | F55: =E55*(1+g_asp) -> 1.3924 | G55: =F55*(1+g_asp) -> 1.643032 | K55: Ibiden 模型 g_asp（Analogy）
A56: ABF 價格溢價指數（全市場；FY2026＝1） | B56: x | D56: =1 -> 1 | E56: =ibpp_27 -> 1 | F56: =ibpp_28 -> 0.95 | G56: =ibpp_29 -> 0.9 | K56: Ibiden 模型 pp（Assumed）
A57: 南電漲價年度化（CY2026 基期；FY2026＝1） | B57: x | D57: =1 -> 1 | E57: =1+carry -> 1.15 | F57: =1+carry -> 1.15 | G57: =1+carry -> 1.15 | K57: In 頁 carry（Assumed）
A58: 每顆 NVIDIA 加速器載板金額（全市場）＝ FY2026 金額 × 面積層數 × 溢價 | B58: US$／顆 | D58: =v26*D55*D56 -> 215.3086 | E58: =v26*E55*E56 -> 254.06414 | F58: =v26*F55*F56 -> 284.8059 | G58: =v26*G55*G56 -> 318.38302 | K58: FY2026 金額取自 Ibiden 模型 Units 頁（權威）
A59: 南電份額：NVIDIA 加速器載板 | B59: % | D59: =sh_nv_26 -> 0.02 | E59: =sh_nv_27 -> 0.03 | F59: =sh_nv_28 -> 0.04 | G59: =sh_nv_29 -> 0.04
A60: 南電份額：非 NVIDIA 加速器載板（金額） | B60: % | D60: =sh_ot_26 -> 0.05 | E60: =sh_ot_27 -> 0.06 | F60: =sh_ot_28 -> 0.07 | G60: =sh_ot_29 -> 0.07
A61: 南電加速器載板營收 ＝（NVIDIA × 金額 × 份額 ＋ 非 NVIDIA × 金額 × v_ot × 份額）× 漲價年度化 | B61: US$M | D61: =(D53*D58*D59+D54*D58*v_ot*D60)*D57 -> 98.18072 | E61: =(E53*E58*E59+E54*E58*v_ot*E60)*E57 -> 225.09067 | F61: =(F53*F58*F59+F54*F58*v_ot*F60)*F57 -> 349.01255 | G61: =(G53*G58*G59+G54*G58*v_ot*G60)*G57 -> 444.87532
A62: 南電加速器載板營收（新台幣） | B62: NT$B | D62: =D61*fx/1000 -> 3.1908734 | E62: =E61*fx/1000 -> 7.3154467 | F62: =F61*fx/1000 -> 11.342908 | G62: =G61*fx/1000 -> 14.458448
A63: B. ABF 需求與產能（營收＝MIN（需求, 產能））
A64: AI 載板需求（FY2026＝ABF × AI 占比） | B64: NT$B | D64: =a26_abf*ai_abf -> 22.298758 | K64: 凱基：AI 與資料中心（800G 交換器）約占 ABF 60%
A65: 其他 AI 載板需求（交換器為主，另含伺服器 CPU、網通 ASIC） | B65: NT$B | D65: =D64-D62 -> 19.107885 | E65: =$D65*(swm_27/swm_26)^el_o*1*0.8*E56*E57 -> 24.588328 | F65: =$D65*(swm_28/swm_26)^el_o*um28_A*0.8*F56*F57 -> 25.12832 | G65: =$D65*(swm_29/swm_26)^el_o*um29_A*0.8*G56*G57 -> 25.396193 | K65: FY2026＝校準殘差（Derived）；之後 × 交換晶片與交換器市場成長 ^ 彈性 × 情境係數 × 溢價
A66: 非 AI ABF 需求（PC、一般伺服器、車用） | B66: NT$B | D66: =a26_abf-D64 -> 12.007024 | E66: =D66*(1+g_nai) -> 12.367234 | F66: =E66*(1+g_nai) -> 12.738251 | G66: =F66*(1+g_nai) -> 13.120399
A67: ABF 需求合計 | B67: NT$B | D67: =D62+D65+D66 -> 34.305782 | E67: =E62+E65+E66 -> 44.271009 | F67: =F62+F65+F66 -> 49.209479 | G67: =G62+G65+G66 -> 52.97504
A68: ABF 產能上限（FY2026 營收 × 產能指數 × 組合 × 溢價） | B68: NT$B | D68: =a26_abf -> 34.305782 | E68: =$D67*cap_27*(1+g_mix)^1*E56*E57 -> 49.709078 | F68: =$D67*cap_28*(1+g_mix)^2*F56*F57 -> 55.782906 | G68: =$D67*cap_29*(1+g_mix)^3*G56*G57 -> 65.76511 | K68: 1H26 ABF 稼動率約 80–85%（昆山約 50%），以 FY2026 營收為產能基準
A69: ABF 載板營收 ＝ MIN（需求, 產能） | B69: NT$B | D69: =a26_abf -> 34.305782 | E69: =MIN(E67,E68) -> 44.271009 | F69: =MIN(F67,F68) -> 49.209479 | G69: =MIN(G67,G68) -> 52.97504
A70: 需求滿足率（營收 ÷ 需求；< 100% 表示產能受限） | B70: % | D70: =D69/D67 -> 1 | E70: =E69/E67 -> 1 | F70: =F69/F67 -> 1 | G70: =G69/G67 -> 1
A71: AI 載板營收（加速器＋其他 AI，乘滿足率） | B71: NT$B | D71: =(D62+D65)*D70 -> 22.298758 | E71: =(E62+E65)*E70 -> 31.903774 | F71: =(F62+F65)*F70 -> 36.471228 | G71: =(G62+G65)*G70 -> 39.854641
A72: 加速器載板 ÷ AI 載板 | B72: % | D72: =D62/(D62+D65) -> 0.14309646 | E72: =E62/(E62+E65) -> 0.22929722 | F72: =F62/(F62+F65) -> 0.31100976 | G72: =G62/(G62+G65) -> 0.36277953
A73: C. 其他產品與合計
A74: BT 載板（情境別年增；公司特有） | B74: NT$B | D74: =a26_bt -> 18.927328 | E74: =D74*(1+g_bt27_A) -> 24.605526 | F74: =E74*(1+g_bt28_A) -> 27.066079 | G74: =F74*(1+g_bt29_A) -> 28.419383 | K74: BT 成長以漲價為主
A75: PCB（一般電路板） | B75: NT$B | D75: =a26_pcb -> 5.91479 | E75: =D75*(1+g_pcb) -> 5.91479 | F75: =E75*(1+g_pcb) -> 5.91479 | G75: =F75*(1+g_pcb) -> 5.91479
A76: 營收 | B76: NT$B | C76: =a25_rev -> 40.173 | D76: =D69+D74+D75 -> 59.1479 | E76: =E69+E74+E75 -> 74.791325 | F76: =F69+F74+F75 -> 82.190348 | G76: =G69+G74+G75 -> 87.309213 | H76: =G76*(1+H77) -> 92.680511 | I76: =H76*(1+I77) -> 98.311797 | J76: =I76*(1+J77) -> 104.21051 | K76: FY2030 起為收斂法：營收年增由 FY2029 線性收斂到 fade_g、淨利率收斂到 fade_m（FY2032 達到），非驅動因子推導
A77: 營收年增 | B77: % | D77: =D76/C76-1 -> 0.47232967 | E77: =E76/D76-1 -> 0.26447981 | F77: =F76/E76-1 -> 0.098928897 | G77: =G76/F76-1 -> 0.062280604 | H77: =$G77+(fade_gA-$G77)*1/3 -> 0.061520403 | I77: =$G77+(fade_gA-$G77)*2/3 -> 0.060760201 | J77: =$G77+(fade_gA-$G77)*3/3 -> 0.06
A78: ABF ÷ 營收 | B78: % | D78: =D69/D76 -> 0.58 | E78: =E69/E76 -> 0.59192705 | F78: =F69/F76 -> 0.59872577 | G78: =G69/G76 -> 0.606752
A79: AI 載板 ÷ 營收 | B79: % | D79: =D71/D76 -> 0.377 | E79: =E71/E76 -> 0.42657052 | F79: =F71/F76 -> 0.44374101 | G79: =G71/G76 -> 0.45647692 | K79: 公司：1Q26 網通 49%、AI 與 HPC 16%（應用別口徑不同）
A80: D. 折舊、毛利與損益
A81: 資本支出 | B81: NT$B | C81: =a25_cx -> 2.422 | D81: =capex26 -> 4 | E81: =cx27 -> 14 | F81: =cx28 -> 18 | G81: =cx29 -> 12 | H81: =H76*H98 -> 12.184744 | I81: =I76*I98 -> 12.33796 | J81: =J76*J98 -> 12.455878
A82: 折舊攤提 ＝ 前一年 ×（1 − 1／年限）＋ 前一年資本支出 ÷ 年限 | B82: NT$B | C82: =a25_da -> 6.894 | D82: =da26 -> 7.1 | E82: =D82*(1-1/life)+D81/life -> 6.7125 | F82: =E82*(1-1/life)+E81/life -> 7.6234375 | G82: =F82*(1-1/life)+F81/life -> 8.9205078 | H82: =H76*H83 -> 9.469301 | I82: =I76*I83 -> 10.044658 | J82: =J76*J83 -> 10.647337 | K82: 新產能前一年投入、當年開始折舊（近似）
A83: 折舊 ÷ 營收 | B83: % | C83: =C82/C76 -> 0.1716078 | D83: =D82/D76 -> 0.12003807 | E83: =E82/E76 -> 0.089749713 | F83: =F82/F76 -> 0.092753439 | G83: =G82/G76 -> 0.10217144 | H83: =$G83 -> 0.10217144 | I83: =$G83 -> 0.10217144 | J83: =$G83 -> 0.10217144
A84: 漲價溢價營收（相對 FY2026 價格；全數落在毛利） | B84: NT$B | E84: =E71*(1-1/(E56*E57)) -> 4.1613619 | F84: =F71*(1-1/(F56*F57)) -> 3.0879529 | G84: =G71*(1-1/(G56*G57)) -> 1.3477415 | K84: AI 載板營收 ×（1 − 1／價格指數）
A85: 毛利 ＝ FY2026 ＋ ABF 現金毛利增量 ＋ 其他產品現金毛利增量 ＋ 溢價 − 折舊增量 | B85: NT$B | C85: =a25_gp -> 3.647 | D85: =a26_gp -> 15.900192 | E85: =$D85+ft_abf*(E69-E84-$D69)+ft_oth*((E76-E69)-($D76-$D69))+E84-(E82-$D82) -> 25.622266 | F85: =$D85+ft_abf*(F69-F84-$D69)+ft_oth*((F76-F69)-($D76-$D69))+F84-(F82-$D82) -> 27.628081 | G85: =$D85+ft_abf*(G69-G84-$D69)+ft_oth*((G76-G69)-($D76-$D69))+G84-(G82-$D82) -> 27.885006 | K85: 流通率為現金毛利口徑；折舊另計
A86: 毛利率 | B86: % | C86: =C85/C76 -> 0.090782366 | D86: =D85/D76 -> 0.26882091 | E86: =E85/E76 -> 0.3425834 | F86: =F85/F76 -> 0.33614751 | G86: =G85/G76 -> 0.31938218
A87: 營業費用 | B87: NT$B | C87: =a25_opx -> 1.665 | D87: =a26_opx -> 1.9 | E87: =D87*(1+phi*E77) -> 2.201507 | F87: =E87*(1+phi*F77) -> 2.3321826 | G87: =F87*(1+phi*G77) -> 2.4193324
A88: 營業利益 | B88: NT$B | C88: =C85-C87 -> 1.982 | D88: =D85-D87 -> 14.000193 | E88: =E85-E87 -> 23.420759 | F88: =F85-F87 -> 25.295898 | G88: =G85-G87 -> 25.465674
A89: 營業利益率 | B89: % | C89: =C88/C76 -> 0.049336619 | D89: =D88/D76 -> 0.23669805 | E89: =E88/E76 -> 0.31314807 | F89: =F88/F76 -> 0.30777212 | G89: =G88/G76 -> 0.29167224
A90: 營業外淨額 | B90: NT$B | C90: =a25_nonop -> 0.364 | D90: =a26_nonop -> 0.623 | E90: =nonop27 -> 0.6 | F90: =nonop28 -> 0.6 | G90: =nonop29 -> 0.6
A91: 稅前利益 | B91: NT$B | C91: =C88+C90 -> 2.346 | D91: =D88+D90 -> 14.623193 | E91: =E88+E90 -> 24.020759 | F91: =F88+F90 -> 25.895898 | G91: =G88+G90 -> 26.065674
A92: 所得稅 | B92: NT$B | E92: =E91*tax -> 5.0443594 | F92: =F91*tax -> 5.4381386 | G92: =G91*tax -> 5.4737915
A93: 歸屬母公司淨利 | B93: NT$B | C93: =a25_ni -> 1.947 | D93: =a26_ni -> 11.509862 | E93: =E91-E92 -> 18.9764 | F93: =F91-F92 -> 20.457759 | G93: =G91-G92 -> 20.591882 | H93: =H76*H97 -> 22.360605 | I93: =I76*I97 -> 24.251637 | J93: =J76*J97 -> 26.271076
A94: 加權股數 | B94: 十億股 | C94: =a25_sh -> 0.64684385 | D94: =a26_sh -> 0.64586333 | E94: =a26_shend*(1+sh_g) -> 0.64617 | F94: =E94*(1+sh_g) -> 0.64617 | G94: =F94*(1+sh_g) -> 0.64617 | H94: =G94*(1+sh_g) -> 0.64617 | I94: =H94*(1+sh_g) -> 0.64617 | J94: =I94*(1+sh_g) -> 0.64617
A95: EPS（基本） | B95: NT$ | C95: =C93/C94 -> 3.01 | D95: =D93/D94 -> 17.820894 | E95: =E93/E94 -> 29.367504 | F95: =F93/F94 -> 31.660027 | G95: =G93/G94 -> 31.867593 | H95: =H93/H94 -> 34.604833 | I95: =I93/I94 -> 37.531357 | J95: =J93/J94 -> 40.656602
A96: EPS 年增 | B96: % | D96: =D95/C95-1 -> 4.9205629 | E96: =E95/D95-1 -> 0.64792535 | F96: =F95/E95-1 -> 0.078063263 | G96: =G95/F95-1 -> 0.006556096 | H96: =H95/G95-1 -> 0.085894162 | I96: =I95/H95-1 -> 0.084569809 | J96: =J95/I95-1 -> 0.083270225
A97: 淨利率（歸屬母公司淨利 ÷ 營收） | B97: % | C97: =C93/C76 -> 0.048465387 | D97: =D93/D76 -> 0.1945946 | E97: =E93/E76 -> 0.25372461 | F97: =F93/F76 -> 0.24890708 | G97: =G93/G76 -> 0.23585005 | H97: =$G97+(fade_mA-$G97)*1/3 -> 0.24126545 | I97: =$G97+(fade_mA-$G97)*2/3 -> 0.24668084 | J97: =$G97+(fade_mA-$G97)*3/3 -> 0.25209624
A98: 資本支出 ÷ 營收 | B98: % | C98: =C81/C76 -> 0.060289249 | D98: =D81/D76 -> 0.067627084 | E98: =E81/E76 -> 0.18718748 | F98: =F81/F76 -> 0.21900382 | G98: =G81/G76 -> 0.13744254 | H98: =$G98+($G83*(1+tp_g)^(life/2)-$G98)*1/3 -> 0.1314704 | I98: =$G98+($G83*(1+tp_g)^(life/2)-$G98)*2/3 -> 0.12549827 | J98: =$G98+($G83*(1+tp_g)^(life/2)-$G98)*3/3 -> 0.11952613 | K98: FY2030 起：資本支出率由 FY2029 線性收斂到 折舊率 ×（1＋tp_g）^（年限／2）（穩態更新）；折舊率維持 FY2029
A99: 股東現金流 ＝ 淨利 ＋ 折舊 − 資本支出 | B99: NT$B | E99: =E93+E82-E81 -> 11.6889 | F99: =F93+F82-F81 -> 10.081197 | G99: =G93+G82-G81 -> 17.51239 | H99: =H93+H82-H81 -> 19.645162 | I99: =I93+I82-I81 -> 21.958334 | J99: =J93+J82-J81 -> 24.462535 | K99: 不含營運資金變動
A100: 每股股東現金流 | B100: NT$ | E100: =E99/E94 -> 18.089512 | F100: =F99/F94 -> 15.601462 | G100: =G99/G94 -> 27.101831 | H100: =H99/H94 -> 30.402467 | I100: =I99/I94 -> 33.982287 | J100: =J99/J94 -> 37.857739
A103: 案例區塊：AI 部署 ×1.2（情境 A）
A104: 項目 | B104: 單位 | C104: FY2025A | D104: FY2026（錨點） | E104: FY2027 | F104: FY2028 | G104: FY2029 | H104: FY2030（收斂） | I104: FY2031（收斂） | J104: FY2032（收斂） | K104: 說明
A105: A. AI 加速器載板（口徑與 Ibiden、欣興一致；D 欄＝FY2026 校準年）
A106: NVIDIA 加速器顆數 × 情境係數 | B106: 百萬顆 | D106: =(u_bw_26+u_rb_26+u_ru_26+u_hp_26)*1 -> 7.6 | E106: =(u_bw_27+u_rb_27+u_ru_27+u_hp_27)*1*1.2 -> 11.64 | F106: =(u_bw_28+u_rb_28+u_ru_28+u_hp_28)*um28_A*1.2 -> 11.4 | G106: =(u_bw_28*(1+g29_bw)+u_rb_28*(1+g29_rb)+u_ru_28*(1+g29_ru)+u_hp_28*(1+g29_hp))*um29_A*1.2 -> 12.72 | K106: markets/network In：Blackwell、Rubin、Rubin Ultra、Hopper
A107: 非 NVIDIA 加速器顆數 × 情境係數 | B107: 百萬顆 | D107: =(u_amd_26+u_tpu_26+u_trn_26+u_oth_26)*1 -> 7.6 | E107: =(u_amd_27+u_tpu_27+u_trn_27+u_oth_27)*1*1.2 -> 16.8 | F107: =(u_amd_28+u_tpu_28+u_trn_28+u_oth_28)*um28_A*1.2 -> 20.4 | G107: =(u_amd_28*(1+g29_amd)+u_tpu_28*(1+g29_tpu)+u_trn_28*(1+g29_trn)+u_oth_28*(1+g29_oth))*um29_A*1.2 -> 23.46 | K107: AMD、TPU、Trainium、其他 ASIC
A108: 每顆載板面積與層數指數（FY2026＝1） | B108: x | D108: =1 -> 1 | E108: =D108*(1+g_asp) -> 1.18 | F108: =E108*(1+g_asp) -> 1.3924 | G108: =F108*(1+g_asp) -> 1.643032 | K108: Ibiden 模型 g_asp（Analogy）
A109: ABF 價格溢價指數（全市場；FY2026＝1） | B109: x | D109: =1 -> 1 | E109: =ibpp_27 -> 1 | F109: =ibpp_28 -> 0.95 | G109: =ibpp_29 -> 0.9 | K109: Ibiden 模型 pp（Assumed）
A110: 南電漲價年度化（CY2026 基期；FY2026＝1） | B110: x | D110: =1 -> 1 | E110: =1+carry -> 1.15 | F110: =1+carry -> 1.15 | G110: =1+carry -> 1.15 | K110: In 頁 carry（Assumed）
...

Sheet Sources
A1: 來源（公司財報經資料商與媒體轉載；法說內容經媒體摘要；券商與資料商皆為 Interested-party）
A2: 資料商：stockanalysis（現價、股數、前瞻與近 12 月 P/E、目標價、FY2021–25 與季損益、現金流、ROE、年度 P/E） | B2: https://stockanalysis.com/quote/tpe/8046/
A3: 資料商：stockanalysis 歷史價格（2026-10-22 收盤 1,265） | B3: https://stockanalysis.com/quote/tpe/8046/history/
A4: 資料商：財報狗（10-22 收盤、近 12 月 P/E、近 4 季 ROE） | B4: https://statementdog.com/analysis/8046
A5: 資料商：HiStock（現價核對、2Q26 EPS） | B5: https://histock.tw/stock/8046
A6: 公司（摘要）：富果 1Q26 法說摘要（應用別、資本支出、擴產） | B6: https://blog.fugle.tw/post/earnings-call-8046-2026-06-12
A7: 公司（摘要）：vocus 4Q25 法說摘要（FY2025、產品別 2025） | B7: https://vocus.cc/article/6a12e069fd897800013a5f84
A8: 媒體：TechNews 2026-10-03（9 月營收、前 9 月累計） | B8: https://finance.technews.tw/2026/10/03/n-p-c-8046-202609-financial-report/
A9: 媒體：winvest（7 月營收、1Q26 EPS） | B9: https://winvest.tw/News/Detail/90850
A10: 券商（媒體）：三立 2026-07-27（2Q26 營收、法人 3Q26 預估、產能） | B10: https://www.mirrormedia.mg/external/setn_1879204
A11: 券商（媒體）：TechNews 2026-10-02 美銀（目標價 2,000、EPS 2026–28、毛利率、BT 漲價、AMD／博通） | B11: https://finance.technews.tw/2026/10/02/bank-of-america-gives-nanyang-power-a-buy-rating-with-a-target-price-of-nt2000/
A12: 券商（媒體）：TechNews 2026-10-05 大和（目標價 2,460、8 月自結獲利、3Q／4Q26 預估） | B12: https://finance.technews.tw/2026/10/05/daiwa-securities-strongly-supports-nan-ya-powers-target-price-of-nt2460/
A13: 券商：凱基 PCB 產業報告 2026-07-20（EPS、營收、毛利率、產品組合、產能、資本支出、ABF 缺口、同業 P/E） | B13: https://www.kgi.com.hk/zh-cn/-/media/files/kgishk/research-reports/tw-reports/pcb-sector_20260720e.pdf
... A21: SemiAnalysis | B21: 未使用
