Workbook

Sheet README
A1: 聯發科（2454.TW）收支與估值模型 v0.1.2（AI 半導體 Project：運算層，手機 SoC＋AI ASIC） 2026-10-25
A2: 版本：v0.1（初版）。ASIC 每顆規格（核心售價、HBM 代購）讀 Broadcom 模型（本專案權威），份額與 Broadcom、Marvell 合計不超過 100%；手機、智慧邊緣平台、電源 IC 用簡化成長率。本版未做先驗。
A3: 模型命題：聯發科的 AI ASIC 營收＝Google TPU 顆數（市場層）× 聯發科份額 × 每顆營收（Broadcom 模型規格）；FY2026 只有約 20 億美元，賣方卻估 FY2028 達 500 億美元。在 Broadcom 占 TPU 75%、Marvell 5% 的份額口徑下，聯發科最多拿到兩成 TPU，推得出多少 ASIC 營收與 EPS？
A4: 核心問題：以市場層 TPU 顆數與份額上限往前推，聯發科 FY2027–28 的 ASIC 營收與 EPS 離公司目標、賣方估計有多遠；差距要靠顆數、份額還是單價補上，現價約 39 倍前瞻 P/E 隱含哪一條路徑。
A6: 會計年度＝日曆年，FY(t)＝CY(t)，不平移。FY2025A 實績、FY2026 錨點、FY2027–FY2029 驅動因子推導、FY2030–FY2032 收斂法。金額：十億新台幣；EPS：新台幣（基本）。口徑：歸屬母公司淨利（TIFRS）。3Q26 財報約 10 月底公布，本版只納入 3Q26 營收實績。
A8: 驅動因子 → 推導量（全部唯讀上游，不修改）
A9: AI ASIC：tsmc 成品的 Google TPU 顆數 × 情境係數（CY2028–29）× 聯發科份額（Assumed；CY2026 5%、CY2027 15%、CY2028 起 18%，高值以 1 − Broadcom − Marvell 份額為上限）×（核心售價 8K × 第二顆 ASIC 單價係數＋代購比例 0.6 × HBM 金額）× k_x（FY2026 以公司「超過 20 億美元」校準）× 匯率 32。
A10: 非 ASIC：手機、智慧邊緣平台（不含 ASIC）、電源 IC 由 FY2026 錨點依情境成長率推（A 順利／B 平平／C 不如預期）。
A11: 毛利：ASIC 核心毛利率 45%（Assumed）、代購 HBM 10%（Broadcom 模型）；非 ASIC 毛利率為 FY2026 殘差（Derived）後沿用。營業費用彈性 0.3（ASIC 營業費用低）、年增下限 6%；營業外 18、稅率 14%、股數持平。
A12: 校準：FY2026 ＝ 1H26 實績＋3Q26 營收實績（月營收）＋3Q26 指引（毛利率 46%、費用 48.5）＋4Q26 假設（手機 −5%、智慧邊緣 −5%、ASIC 約 17 億美元量產）。不用券商數字（只在 Recon 對帳）。
A13: 估值：Val 第 0 節目標價＝0.5 × DCF 目標價（股東現金流＝EPS ×（1 − g／ROE），FY2027–32 明確期＋永續，r 10%、g 4%，三情境權重 0.3／0.5／0.2）＋0.5 × Comparable 目標價（高通、博通、邁威爾、世芯、創意前瞻 P/E 中位數 × 12 個月後前瞻 EPS；不含 A 股）；另列 Comparable 單獨目標價、市場共識目標價與差距拆解。十年 P/E 規則值 × FY2027 EPS 保留為參考（不是目標價）。本版未做先驗，無 Andy 合理 P/E 對照。
A14: 預估期間：FY2027–FY2029 由驅動因子推導；FY2030 起為收斂法，非驅動因子推導（營收年增由 FY2029 線性收斂到 fade_g、淨利率收斂到 fade_m，FY2032 達到；PL 頁灰底）。十年平均淨利率未找到，B、C 依工作單以 FY2029 × 0.8 代替。
... A18: v0.1.1（2026-10-25）：補上檔空間級距、投資建議、重點觀察（數值不變）。Val 頁末新增「上檔空間級距」「投資建議」兩列（Andy 2026-10-25 14:00、14:17 固定規則），README 頁末新增投資建議與重點觀察三點；既有儲存格位置與數值不變。
A19: ="投資建議："&Val!B135&"（依上檔空間固定規則）" -> 投資建議：放空（依上檔空間固定規則）
A20: 重點觀察 1：目標價 NT$2,057（DCF 1,846、Comparable 2,268 各半），比現價 4,010（2026-10-22）低 48.7%，級距 −25%～−50%；Comparable 單獨為 −43.4%。主因是倍數不是 EPS：本模型 12 個月後前瞻 EPS 119.49 比共識前瞻 EPS 103.48 高 15.5%，但同業（高通、博通、邁威爾、世芯、創意）前瞻 P/E 中位數 19.0 倍，現價隱含 38.8 倍、共識目標價 6,067 隱含 58.6 倍（比同業高 208.9%）；市場給聯發科的 AI ASIC 成長溢價，Comparable 未計入。
A21: 重點觀察 2：情境分歧大：FY2028 EPS A／B／C 為 149.3／119.5／85.3，DCF 價格帶 1,012～2,466；C 情境（顆數 ×0.6、手機 −8%）FY2028 EPS 低於 FY2027 的 100.1。即使 A 情境 DCF 2,466 也比現價低 38.5%。
A22: 重點觀察 3：TPU 份額是最敏感變數：聯發科占 TPU −5pt 時 FY2027 EPS −13.2%、取上限 20% 時 +13.2%；營業費用彈性 0.6 時 −12.7%（Sens 頁）。下一個檢驗點是 3Q26 財報與法說（約 2026-10 底）的 ASIC 營收與客戶進度。
A23: v0.1.2（2026-10-28）：分部原則重建（數值不變）。Q 頁最後追加核對列「檢查：分部合計 − 合併營收」；官方分部與子列宣告見 segments.json。

Sheet In
A1: In — 輸入（藍字；基準欄 E，低 D、高 F）。金額：十億新台幣（NT$B）；ASIC 每顆價格：千美元（US$K）；顆數：百萬顆；匯率：新台幣／美元。每個輸入附兩個來源（找不到者寫「未找到」）；公司原文算一個
A2: 標記：Verified／Interested-party／Analogy／Assumed／Derived；Analogy、Assumed 給低／高區間，不當點估計（放情境或 Sens）。SemiAnalysis 未使用。公司原文＝聯發科法說營運報告、新聞稿、法說逐字稿與講稿（mediatek.com）；公司指引與目標為 Interested-party；券商、資料商、媒體為 Interested-party
A3: 鍵 | B3: 項目 | C3: 單位 | D3: 低 | E3: 基準 | F3: 高 | G3: 標記 | H3: 來源1 | I3: 來源2／說明
A4: A. AI 加速器顆數（tsmc 成品；與 HBM、台積電、Broadcom、Marvell 模型同一份；情境係數讀台積電模型，不另訂）
A5: u_tpu_26 | B5: Google TPU 顆數 CY2026 | C5: 百萬顆 | E5: 3.85 | G5: Interested-party | H5: tsmc/dist/20261028_台積電個股模型_v0.4.xlsx｜In!E25 | I5: avgo 成品同值（建置時檢查）
A6: u_tpu_27 | B6: Google TPU 顆數 CY2027 | C6: 百萬顆 | E6: 5.5 | G6: Interested-party | H6: tsmc/dist/20261028_台積電個股模型_v0.4.xlsx｜In!E26 | I6: 同上
A7: u_tpu_28 | B7: Google TPU 顆數 CY2028 | C7: 百萬顆 | E7: 7 | G7: Interested-party | H7: tsmc/dist/20261028_台積電個股模型_v0.4.xlsx｜In!E27 | I7: 同上
A8: g29_tpu | B8: Google TPU CY2029 顆數成長 | C8: % | E8: 0.15 | G8: Assumed | H8: tsmc/dist/20261028_台積電個股模型_v0.4.xlsx｜In!E28 | I8: markets/memory 無 2029；沿用台積電模型
A9: u_oth_26 | B9: 其他 ASIC（MTIA、Maia、Ascend 等） 顆數 CY2026 | C9: 百萬顆 | E9: 1 | G9: Derived／Assumed | H9: tsmc/dist/20261028_台積電個股模型_v0.4.xlsx｜In!E33 | I9: avgo 成品同值（建置時檢查）
A10: u_oth_27 | B10: 其他 ASIC（MTIA、Maia、Ascend 等） 顆數 CY2027 | C10: 百萬顆 | E10: 4.5 | G10: Derived／Assumed | H10: tsmc/dist/20261028_台積電個股模型_v0.4.xlsx｜In!E34 | I10: 同上
A11: u_oth_28 | B11: 其他 ASIC（MTIA、Maia、Ascend 等） 顆數 CY2028 | C11: 百萬顆 | E11: 5 | G11: Derived／Assumed | H11: tsmc/dist/20261028_台積電個股模型_v0.4.xlsx｜In!E35 | I11: 同上
A12: g29_oth | B12: 其他 ASIC（MTIA、Maia、Ascend 等） CY2029 顆數成長 | C12: % | E12: 0.15 | G12: Assumed | H12: tsmc/dist/20261028_台積電個股模型_v0.4.xlsx｜In!E36 | I12: markets/memory 無 2029；沿用台積電模型
A13: um28_A | B13: 情境 A：CY2028 顆數 ÷ 基準 | C13: x | E13: 1 | G13: Assumed | H13: tsmc/dist/20261028_台積電個股模型_v0.4.xlsx｜In!E37 | I13: A＝基準；B＝AI 資本支出消化；C＝明顯下修（與台積電、Broadcom、Marvell 模型相同）
A14: um29_A | B14: 情境 A：CY2029 顆數 ÷ 基準 | C14: x | E14: 1 | G14: Assumed | H14: tsmc/dist/20261028_台積電個股模型_v0.4.xlsx｜In!E38 | I14: 同上
A15: um28_B | B15: 情境 B：CY2028 顆數 ÷ 基準 | C15: x | E15: 0.8 | G15: Assumed | H15: tsmc/dist/20261028_台積電個股模型_v0.4.xlsx｜In!E39 | I15: 同上
A16: um29_B | B16: 情境 B：CY2029 顆數 ÷ 基準 | C16: x | E16: 0.85 | G16: Assumed | H16: tsmc/dist/20261028_台積電個股模型_v0.4.xlsx｜In!E40 | I16: 同上
... A18: um29_C | B18: 情境 C：CY2029 顆數 ÷ 基準 | C18: x | E18: 0.6 | G18: Assumed | H18: tsmc/dist/20261028_台積電個股模型_v0.4.xlsx｜In!E42 | I18: 同上
A19: B. ASIC 每顆規格（權威在 Broadcom 模型 In 頁，唯讀；本模型只加聯發科份額）與份額
A20: core_tpu | B20: TPU 每顆核心售價（不含 HBM） | C20: US$K | D20: 6 | E20: 8 | F20: 11 | G20: Assumed | H20: avgo/dist/20261028_Broadcom個股模型_v0.3.xlsx｜In!E56 | I20: Broadcom 模型的 ASIC 每顆規格（本專案權威）；本模型不另訂；聯發科負責的世代與 Broadcom 是否同價：未找到
A21: core_oth | B21: 其他 ASIC 每顆核心售價（不含 HBM） | C21: US$K | D21: 4 | E21: 6 | F21: 9 | G21: Assumed | H21: avgo/dist/20261028_Broadcom個股模型_v0.3.xlsx｜In!E57 | I21: Broadcom 模型的 ASIC 每顆規格（本專案權威）；本模型不另訂；聯發科負責的世代與 Broadcom 是否同價：未找到
A22: f_hbm | B22: HBM 由 ASIC 設計夥伴代購並計入營收的比例 | C22: x | D22: 0.3 | E22: 0.6 | F22: 1 | G22: Assumed | H22: avgo/dist/20261028_Broadcom個股模型_v0.3.xlsx｜In!E58 | I22: 沿用 Broadcom 模型；聯發科客戶是否自購 HBM：未找到（1Q26 法說未回答）
A23: m_hbm | B23: 代購 HBM 的毛利率 | C23: x | D23: 0 | E23: 0.1 | F23: 0.2 | G23: Assumed | H23: avgo/dist/20261028_Broadcom個股模型_v0.3.xlsx｜In!E59 | I23: 沿用 Broadcom 模型
A24: gb_tpu_26 | B24: Google TPU 每顆 HBM CY2026 | C24: GB | E24: 192 | G24: Derived／Assumed | H24: avgo/dist/20261028_Broadcom個股模型_v0.3.xlsx｜In!E43 | I24: markets/memory UNITS；CY2029 沿用 CY2028
A25: gb_tpu_27 | B25: Google TPU 每顆 HBM CY2027 | C25: GB | E25: 250 | G25: Derived／Assumed | H25: avgo/dist/20261028_Broadcom個股模型_v0.3.xlsx｜In!E44 | I25: 同上
A26: gb_tpu_28 | B26: Google TPU 每顆 HBM CY2028 | C26: GB | E26: 288 | G26: Derived／Assumed | H26: avgo/dist/20261028_Broadcom個股模型_v0.3.xlsx｜In!E45 | I26: 同上
A27: gb_oth_26 | B27: 其他 ASIC（MTIA、Maia、Ascend 等） 每顆 HBM CY2026 | C27: GB | E27: 150 | G27: Derived／Assumed | H27: avgo/dist/20261028_Broadcom個股模型_v0.3.xlsx｜In!E46 | I27: markets/memory UNITS；CY2029 沿用 CY2028
A28: gb_oth_27 | B28: 其他 ASIC（MTIA、Maia、Ascend 等） 每顆 HBM CY2027 | C28: GB | E28: 200 | G28: Derived／Assumed | H28: avgo/dist/20261028_Broadcom個股模型_v0.3.xlsx｜In!E47 | I28: 同上
A29: gb_oth_28 | B29: 其他 ASIC（MTIA、Maia、Ascend 等） 每顆 HBM CY2028 | C29: GB | E29: 250 | G29: Derived／Assumed | H29: avgo/dist/20261028_Broadcom個股模型_v0.3.xlsx｜In!E48 | I29: 同上
A30: av_tpu_26 | B30: Broadcom 占 Google TPU 顆數 CY2026（份額加總檢查用） | C30: % | E30: 0.9 | G30: Assumed | H30: avgo/dist/20261028_Broadcom個股模型_v0.3.xlsx｜In!E50 | I30: Broadcom 模型；Broadcom＋Marvell＋聯發科（高）≤ 100%（建置時檢查）
A31: mv_tpu_26 | B31: Marvell 占 Google TPU 顆數 CY2026（份額加總檢查用） | C31: % | E31: 0 | G31: Assumed | H31: mrvl/dist/20261028_邁威爾個股模型_v0.2.3.xlsx｜In!E51 | I31: Marvell 模型
A32: av_tpu_27 | B32: Broadcom 占 Google TPU 顆數 CY2027（份額加總檢查用） | C32: % | E32: 0.8 | G32: Assumed | H32: avgo/dist/20261028_Broadcom個股模型_v0.3.xlsx｜In!E51 | I32: Broadcom 模型；Broadcom＋Marvell＋聯發科（高）≤ 100%（建置時檢查）
A33: mv_tpu_27 | B33: Marvell 占 Google TPU 顆數 CY2027（份額加總檢查用） | C33: % | E33: 0 | G33: Assumed | H33: mrvl/dist/20261028_邁威爾個股模型_v0.2.3.xlsx｜In!E52 | I33: Marvell 模型
A34: av_tpu_28 | B34: Broadcom 占 Google TPU 顆數 CY2028（份額加總檢查用） | C34: % | E34: 0.75 | G34: Assumed | H34: avgo/dist/20261028_Broadcom個股模型_v0.3.xlsx｜In!E52 | I34: Broadcom 模型；Broadcom＋Marvell＋聯發科（高）≤ 100%（建置時檢查）
A35: mv_tpu_28 | B35: Marvell 占 Google TPU 顆數 CY2028（份額加總檢查用） | C35: % | E35: 0.05 | G35: Assumed | H35: mrvl/dist/20261028_邁威爾個股模型_v0.2.3.xlsx｜In!E53 | I35: Marvell 模型
... A41: mv_oth_28 | B41: Marvell 占 其他 ASIC（MTIA、Maia、Ascend 等） 顆數 CY2028（份額加總檢查用） | C41: % | E41: 0.15 | G41: Assumed | H41: mrvl/dist/20261028_邁威爾個股模型_v0.2.3.xlsx｜In!E50 | I41: Marvell 模型
A42: mtk_tpu_26 | B42: 聯發科占 Google TPU 顆數 CY2026 | C42: % | D42: 0.03 | E42: 0.05 | F42: 0.1 | G42: Assumed | H42: 公司：與一家美國大型雲端客戶合作的第一顆 AI 加速器 ASIC 於 4Q26 量產；第二顆 2028 年量產（2Q26 講稿）；客戶名稱公司未揭露 | I42: 凱基 2026-07-23：v8x Zebrafish（4Q26 起）、v9 Humufish（4Q27 起）為 Google TPU（Interested-party）；高值受 avgo、mrvl 份額限制（1 − Broadcom − Marvell 基準）
A43: mtk_tpu_27 | B43: 聯發科占 Google TPU 顆數 CY2027 | C43: % | D43: 0.08 | E43: 0.15 | F43: 0.2 | G43: Assumed | H43: 同上 | I43: —
A44: mtk_tpu_28 | B44: 聯發科占 Google TPU 顆數 CY2028（CY2029 沿用） | C44: % | D44: 0.1 | E44: 0.18 | F44: 0.2 | G44: Assumed | H44: 同上 | I44: —
A45: mtk_oth_26 | B45: 聯發科占 其他 ASIC（MTIA、Maia、Ascend 等） 顆數 CY2026 | C45: % | D45: 0 | E45: 0 | F45: 0.02 | G45: Assumed | H45: 公司：與其他多家客戶接觸中、資料中心有望取得更多設計案（2Q26 講稿） | I45: 第二客戶與量產時點：未找到；基準 0，只放 Sens
A46: mtk_oth_27 | B46: 聯發科占 其他 ASIC（MTIA、Maia、Ascend 等） 顆數 CY2027 | C46: % | D46: 0 | E46: 0 | F46: 0.03 | G46: Assumed | H46: 同上 | I46: —
A47: mtk_oth_28 | B47: 聯發科占 其他 ASIC（MTIA、Maia、Ascend 等） 顆數 CY2028（CY2029 沿用） | C47: % | D47: 0 | E47: 0 | F47: 0.05 | G47: Assumed | H47: 同上 | I47: —
A48: pfc | B48: CY2028 起 ASIC 核心售價係數（第二顆 ASIC；Sens 用；基準 1） | C48: x | D48: 0.8 | E48: 1 | F48: 2 | G48: Assumed | H48: 經濟日報 2026-05-03 轉述高盛：下一代 ASIC 平均單價為現行數倍（Interested-party）；凱基：v9 單價至少 +200% | I48: 基準沿用 Broadcom 模型規格（不另訂）；高值 2.0 只放 Sens
A49: uf | B49: 聯發科 ASIC 顆數係數（Sens 用；CY2027 起） | C49: x | D49: 0.8 | E49: 1 | F49: 1.2 | G49: Assumed | H49: 無 | I49: ±20%
A50: m_core | B50: ASIC 核心（不含代購 HBM）毛利率 | C50: x | D50: 0.35 | E50: 0.45 | F50: 0.55 | G50: Assumed | H50: 公司：ASIC 放量將使營業利益率上升（營業費用低；4Q25 法說）；ASIC 毛利率未揭露 | I50: 第二來源：未找到
A51: hf26 | B51: CY2026 TPU 每顆營收中代購 HBM 的比例（Q 頁第四季毛利用） | C51: x | E51: =f_hbm*gb_tpu_26*hbm_A_26/1000/(core_tpu+f_hbm*gb_tpu_26*hbm_A_26/1000) -> 0.17371761 | G51: Derived | H51: In 頁 B、C 節 | I51: —
A52: C. 記憶體價格路徑（讀 Broadcom 模型成品，其來源為 skhynix 成品；唯讀；情境別）
A53: hbm_A_26 | B53: HBM 混合單價 CY2026（A） | C53: US$/GB | E53: 14.6 | G53: Derived | H53: avgo/dist/20261028_Broadcom個股模型_v0.3.xlsx｜In!E62 | I53: markets/memory：2026 BofA $14.6/GB；2027 +80%
A54: hbm_A_27 | B54: HBM 混合單價 CY2027（A） | C54: US$/GB | E54: 26.28 | G54: Derived | H54: avgo/dist/20261028_Broadcom個股模型_v0.3.xlsx｜In!E63 | I54: 同上
A55: hbm_A_28 | B55: HBM 混合單價 CY2028（A） | C55: US$/GB | E55: 28.908 | G55: Derived | H55: avgo/dist/20261028_Broadcom個股模型_v0.3.xlsx｜In!E64 | I55: 同上
A56: hbm_A_29 | B56: HBM 混合單價 CY2029（A） | C56: US$/GB | E56: 27.4626 | G56: Derived | H56: avgo/dist/20261028_Broadcom個股模型_v0.3.xlsx｜In!E65 | I56: 同上
A57: hbm_B_26 | B57: HBM 混合單價 CY2026（B） | C57: US$/GB | E57: 14.6 | G57: Derived | H57: avgo/dist/20261028_Broadcom個股模型_v0.3.xlsx｜In!E66 | I57: 同上
A58: hbm_B_27 | B58: HBM 混合單價 CY2027（B） | C58: US$/GB | E58: 26.28 | G58: Derived | H58: avgo/dist/20261028_Broadcom個股模型_v0.3.xlsx｜In!E67 | I58: 同上
A59: hbm_B_28 | B59: HBM 混合單價 CY2028（B） | C59: US$/GB | E59: 19.71 | G59: Derived | H59: avgo/dist/20261028_Broadcom個股模型_v0.3.xlsx｜In!E68 | I59: 同上
A60: hbm_B_29 | B60: HBM 混合單價 CY2029（B） | C60: US$/GB | E60: 19.71 | G60: Derived | H60: avgo/dist/20261028_Broadcom個股模型_v0.3.xlsx｜In!E69 | I60: 同上
A61: hbm_C_26 | B61: HBM 混合單價 CY2026（C） | C61: US$/GB | E61: 14.6 | G61: Derived | H61: avgo/dist/20261028_Broadcom個股模型_v0.3.xlsx｜In!E70 | I61: 同上
A62: hbm_C_27 | B62: HBM 混合單價 CY2027（C） | C62: US$/GB | E62: 26.28 | G62: Derived | H62: avgo/dist/20261028_Broadcom個股模型_v0.3.xlsx｜In!E71 | I62: 同上
A63: hbm_C_28 | B63: HBM 混合單價 CY2028（C） | C63: US$/GB | E63: 15.768 | G63: Derived | H63: avgo/dist/20261028_Broadcom個股模型_v0.3.xlsx｜In!E72 | I63: 同上
A64: hbm_C_29 | B64: HBM 混合單價 CY2029（C） | C64: US$/GB | E64: 16.5564 | G64: Derived | H64: avgo/dist/20261028_Broadcom個股模型_v0.3.xlsx｜In!E73 | I64: 同上
A65: D. 手機、智慧邊緣平台（不含 ASIC）、電源 IC：簡化成長率（FY2027 起；情境別）
A66: g_mob27_A | B66: 手機年增 FY2027（情境 A） | C66: % | D66: -0.12 | E66: 0.05 | F66: 0.08 | G66: Assumed | H66: 公司：2026 年全球智慧型手機出貨約 −15%（記憶體成本）、2027 年持續擴大旗艦市占（2Q26 講稿） | I66: FY2026 錨點手機約 −17%（Q 頁）；C＝記憶體成本續壓、市占流失
A67: g_mobL_A | B67: 手機年增 FY2028–29（情境 A） | C67: % | D67: -0.12 | E67: 0.04 | F67: 0.08 | G67: Assumed | H67: 同上 | I67: —
A68: g_mob27_B | B68: 手機年增 FY2027（情境 B） | C68: % | D68: -0.12 | E68: 0 | F68: 0.08 | G68: Assumed | H68: 同上 | I68: —
A69: g_mobL_B | B69: 手機年增 FY2028–29（情境 B） | C69: % | D69: -0.12 | E69: 0.02 | F69: 0.08 | G69: Assumed | H69: 同上 | I69: —
A70: g_mob27_C | B70: 手機年增 FY2027（情境 C） | C70: % | D70: -0.12 | E70: -0.08 | F70: 0.08 | G70: Assumed | H70: 同上 | I70: —
A71: g_mobL_C | B71: 手機年增 FY2028–29（情境 C） | C71: % | D71: -0.12 | E71: -0.03 | F71: 0.08 | G71: Assumed | H71: 同上 | I71: —
A72: g_sep27_A | B72: 智慧邊緣平台（不含 ASIC）年增 FY2027（情境 A） | C72: % | D72: -0.06 | E72: 0.08 | F72: 0.12 | G72: Assumed | H72: 公司：連網、電視 SoC（含 DRAM 內容）、車用、運算市占提升；2Q26 年增 26%（2Q26 講稿） | I72: FY2026 錨點約 +26%（含記憶體轉嫁，偏高基期）
A73: g_sepL_A | B73: 智慧邊緣平台（不含 ASIC）年增 FY2028–29（情境 A） | C73: % | D73: -0.06 | E73: 0.07 | F73: 0.12 | G73: Assumed | H73: 同上 | I73: —
A74: g_sep27_B | B74: 智慧邊緣平台（不含 ASIC）年增 FY2027（情境 B） | C74: % | D74: -0.06 | E74: 0.04 | F74: 0.12 | G74: Assumed | H74: 同上 | I74: —
A75: g_sepL_B | B75: 智慧邊緣平台（不含 ASIC）年增 FY2028–29（情境 B） | C75: % | D75: -0.06 | E75: 0.04 | F75: 0.12 | G75: Assumed | H75: 同上 | I75: —
A76: g_sep27_C | B76: 智慧邊緣平台（不含 ASIC）年增 FY2027（情境 C） | C76: % | D76: -0.06 | E76: -0.03 | F76: 0.12 | G76: Assumed | H76: 同上 | I76: —
A77: g_sepL_C | B77: 智慧邊緣平台（不含 ASIC）年增 FY2028–29（情境 C） | C77: % | D77: -0.06 | E77: 0.01 | F77: 0.12 | G77: Assumed | H77: 同上 | I77: —
... A84: gmadj | B84: 非 ASIC 毛利率調整（Sens 用；基準 0） | C84: pt | D84: -0.02 | E84: 0 | F84: 0.02 | G84: Assumed | H84: 無 | I84: 非 ASIC 毛利率為 FY2026 殘差（Derived），之後沿用
A85: E. FY2026 錨點（1H26 實績＋3Q26 營收實績＋3Q26 指引＋4Q26 假設）
A86: dc26 | B86: 公司 FY2026 資料中心（AI ASIC 為主）營收 | C86: US$B | D86: 2 | E86: 2 | F86: 2.5 | G86: Interested-party | H86: 公司 2Q26 法說講稿：超過 20 億美元（2Q26 講稿） | I86: 經濟日報 2026-08-03 轉述高盛約 22 億美元；4Q25 法說為「超過 10 億美元」（一年內上修）
A87: asic13 | B87: 其中 1–3Q26（量產前：NRE、樣品等；Q 頁全數放在 3Q） | C87: US$B | D87: 0.1 | E87: 0.3 | F87: 0.6 | G87: Assumed | H87: 公司：第一顆 ASIC 於 4Q26 量產（2Q26 講稿） | I87: 1Q26 逐字稿：「第四季約 20 億美元」說法與年度說法不易區分（原文含糊）
A88: fx_q1 | B88: 1Q26 匯率（公司指引假設） | C88: NT$/US$ | E88: 31.2 | G88: Interested-party | H88: 公司 4Q25 法說逐字稿：1Q26 指引匯率 31.2 | I88: 實際平均匯率：未找到
A89: fx_q2 | B89: 2Q26 平均匯率 | C89: NT$/US$ | E89: 31.6 | G89: Verified | H89: 公司 2Q26 法說講稿 | I89: 風傳媒同值
A90: fx26 | B90: 3Q、4Q26 匯率（公司 3Q26 指引假設；FY2026 ASIC 換算用） | C90: NT$/US$ | D90: 30.5 | E90: 32 | F90: 33 | G90: Interested-party | H90: 公司 2Q26 法說講稿：3Q26 指引匯率 32 | I90: 實際平均匯率：未找到
A91: q3_rev | B91: 3Q26 營收（月營收實績；7–9 月合計） | C91: NT$B | E91: =469.391-301.334 -> 168.057 | G91: Verified | H91: 科技新報（9 月營收，2026-10-08）：前 9 月 4,693.91 億；1H26 3,013.34 億（公司） | I91: 財報狗（3Q26 營收，2026-10）：3Q26 1,680.58 億，高於財測上緣 1,598 億
A92: q3_mob | B92: 3Q26 手機季增（公司指引：持平至中個位數下滑） | C92: % | D92: -0.06 | E92: -0.03 | F92: 0 | G92: Interested-party | H92: 公司 2Q26 法說講稿 | I92: 只用來拆分 3Q 營收（等比例放大到實績）
A93: q3_sep | B93: 3Q26 智慧邊緣平台季增（公司指引：中至高個位數） | C93: % | D93: 0.04 | E93: 0.07 | F93: 0.09 | G93: Interested-party | H93: 公司 2Q26 法說講稿 | I93: 同上
A94: q3_pic | B94: 3Q26 電源 IC 季增（公司指引：約持平） | C94: % | D94: -0.02 | E94: 0 | F94: 0.02 | G94: Interested-party | H94: 公司 2Q26 法說講稿 | I94: 同上
A95: q3_gm | B95: 3Q26 毛利率（指引 46% ± 1.5pt 中點） | C95: % | D95: 0.445 | E95: 0.46 | F95: 0.475 | G95: Interested-party | H95: 公司 2Q26 法說講稿 | I95: 3Q26 財報約 10 月底公布（確切日期未找到）
A96: q3_opx | B96: 3Q26 營業費用（指引費用率 31% × 營收指引中點） | C96: NT$B | D96: 46 | E96: 48.5 | F96: 51 | G96: Interested-party | H96: 公司 2Q26 法說講稿：費用率 31% ± 2pt、營收 1,522–1,598 億 | I96: 2Q26 47.44（公司）
A97: q4_mob | B97: 4Q26 手機季增 | C97: % | D97: -0.12 | E97: -0.05 | F97: 0.03 | G97: Assumed | H97: 公司：旗艦新機帶動 4Q 出貨（財報狗轉述） | I97: 供應鏈：11 月起手機需求轉弱（財報狗，Interested-party）
A98: q4_sepx | B98: 4Q26 智慧邊緣平台（不含 ASIC）季增 | C98: % | D98: -0.1 | E98: -0.05 | F98: 0 | G98: Assumed | H98: 3Q 為消費性旺季（電視、連網）；4Q 季節性下滑 | I98: —
A99: q4_pic | B99: 4Q26 電源 IC 季增 | C99: % | D99: -0.08 | E99: -0.03 | F99: 0.03 | G99: Assumed | H99: 無 | I99: —
A100: q4_gmx | B100: 4Q26 非 ASIC 毛利率 | C100: % | D100: 0.445 | E100: 0.46 | F100: 0.47 | G100: Assumed | H100: 公司：全年毛利率維持在 3Q 指引區間（2Q26 講稿） | I100: 1Q26 46.3%、2Q26 46.2%（公司）
A101: q4_opx | B101: 4Q26 營業費用 | C101: NT$B | D101: 48 | E101: 50 | F101: 53 | G101: Assumed | H101: 研發費用逐季增加（1Q 38.3、2Q 39.4；公司） | I101: —
A102: q_nonop | B102: 3Q、4Q26 營業外淨額（每季） | C102: NT$B | D102: 3.5 | E102: 4.8 | F102: 5.5 | G102: Assumed | H102: 1Q26 4.13、2Q26 5.09（公司） | I102: US$5B 融資額度若動用，利息收入下降（Assumed）
A103: q_tax | B103: 3Q、4Q26 有效稅率 | C103: % | D103: 0.1 | E103: 0.13 | F103: 0.16 | G103: Assumed | H103: 1Q26 9.8%、2Q26 12.0%、FY2025 15.0%（公司） | I103: —
A104: q_nci | B104: 3Q、4Q26 非控制權益（每季） | C104: NT$B | E104: 0.25 | G104: Derived | H104: 1Q26 0.222、2Q26 0.270（公司） | I104: —
A105: q_sh | B105: 3Q、4Q26 加權股數 | C105: 十億股 | E105: =24.335/15.28 -> 1.5926047 | G105: Derived | H105: 2Q26 歸屬母公司淨利 ÷ EPS（公司） | I105: stockanalysis：流通股數 1.60B
A106: F. FY2027 起：營業費用、營業外、稅、股數、匯率
A107: phi | B107: 營業費用成長對營收成長的彈性 | C107: x | D107: 0.2 | E107: 0.3 | F107: 0.6 | G107: Assumed | H107: ASIC 營收放量所需營業費用低（公司 4Q25 法說：營業利益率上升）；FY2025 營業費用 +11.6%、營收 +12.3%（公司） | I107: 高盛 2027 營業利益率 22%、2028 33%（Interested-party，經濟日報）
A108: g_opx_min | B108: 營業費用年增下限 | C108: % | D108: 0.03 | E108: 0.06 | F108: 0.1 | G108: Assumed | H108: 研發費用年增 FY2025 +12.4%（公司） | I108: —
A109: opx_adj | B109: 營業費用額外占營收比（Sens 用；基準 0） | C109: pt | D109: -0.02 | E109: 0 | F109: 0.02 | G109: Assumed | H109: 無 | I109: Sens 用 +2 個百分點
A110: nonop_f | B110: 營業外淨額（每年） | C110: NT$B | D110: 10 | E110: 18 | F110: 24 | G110: Assumed | H110: FY2025 21.4、1H26 9.2（公司） | I110: 現金與流動金融資產 2Q26 198.4（公司）；US$5B 融資額度（2Q26 講稿）
A111: tax | B111: 有效稅率（FY2027 起） | C111: % | D111: 0.12 | E111: 0.14 | F111: 0.17 | G111: Assumed | H111: FY2024 10.4%、FY2025 15.0%、1H26 10.9%（公司） | I111: —
A112: nci | B112: 非控制權益（每年） | C112: NT$B | E112: 1 | G112: Derived | H112: FY2025 0.80、1H26 0.49（公司） | I112: —
...

Sheet Q
A1: Q — 實績與 FY2026 錨點（十億新台幣；EPS 為新台幣、基本；股數為十億股）。藍字＝輸入（公司營運報告）；黑字＝公式。產品線金額＝公司公布占比 × 營收（Derived）
A2: FY2026 錨點＝1Q、2Q26 實績＋3Q26 營收實績（月營收）與指引（毛利率、費用）＋4Q26 假設；AI ASIC（資料中心）全年取公司「超過 20 億美元」，1–3Q 部分全數放在 3Q 欄（簡化）。3Q26 財報約 10 月底公布，屆時以實績取代 E 欄
A3: 項目 | B3: FY2025A | C3: 1Q26（實績） | D3: 2Q26（實績） | E3: 3Q26（營收實績＋指引） | F3: 4Q26（模型） | G3: FY2026 錨點 | H3: 標記 | I3: 來源1（公司） | J3: 來源2／說明
A4: 營收 | B4: 595.966 | C4: 149.151 | D4: 152.183 | E4: =q3_rev -> 168.057 | F4: =SUM(F5:F7) -> 205.13094 | G4: =SUM(C4:F4) -> 674.52194 | H4: Verified／Assumed（4Q） | I4: FY2025：4Q25 營運報告；1Q26、2Q26：2Q26 營運報告（公司） | J4: 3Q26：月營收實績（科技新報、財報狗）
A5: 手機 | B5: =B4*0.53 -> 315.86198 | C5: =C4*0.49 -> 73.08399 | D5: =D4*0.41 -> 62.39503 | E5: =D5*(1+q3_mob)*q3_rev/(D5*(1+q3_mob)+D6*(1+q3_sep)+D7*(1+q3_pic)) -> 65.218842 | F5: =E5*(1+q4_mob) -> 61.9579 | G5: =SUM(C5:F5) -> 262.65576 | H5: Derived（占比 × 營收）／Assumed | I5: FY2025：4Q25 營運報告；1Q26、2Q26：2Q26 營運報告（公司） | J5: 占比：1Q26 49%、2Q26 41%（公司）；FY2025 約 53%（公司：手機超過 100 億美元 ÷ 191 億美元；占比未揭露，Derived）
A6: 智慧邊緣平台（含 AI ASIC） | B6: =B4*0.415 -> 247.32589 | C6: =C4*0.46 -> 68.60946 | D6: =D4*0.53 -> 80.65699 | E6: =D6*(1+q3_sep)*q3_rev/(D5*(1+q3_mob)+D6*(1+q3_sep)+D7*(1+q3_pic)) -> 92.998756 | F6: =(E6-E8)*(1+q4_sepx)+F8 -> 133.62882 | G6: =SUM(C6:F6) -> 375.89402 | H6: Derived／Assumed | I6: FY2025：4Q25 營運報告；1Q26、2Q26：2Q26 營運報告（公司） | J6: 占比：1Q26 46%、2Q26 53%（公司）；FY2025 約 41.5%（Derived；公司僅揭露美元年增 21%）
A7: 電源 IC | B7: =B4*0.055 -> 32.77813 | C7: =C4*0.05 -> 7.45755 | D7: =D4*0.06 -> 9.13098 | E7: =D7*(1+q3_pic)*q3_rev/(D5*(1+q3_mob)+D6*(1+q3_sep)+D7*(1+q3_pic)) -> 9.8394028 | F7: =E7*(1+q4_pic) -> 9.5442207 | G7: =SUM(C7:F7) -> 35.972154 | H7: Derived／Assumed | I7: FY2025：4Q25 營運報告；1Q26、2Q26：2Q26 營運報告（公司） | J7: 占比：1Q26 5%、2Q26 6%、4Q25 5%（公司）
A8: 其中 AI ASIC（資料中心） | B8: 0 | C8: 0 | D8: 0 | E8: =asic13*fx26 -> 9.6 | F8: =(dc26-asic13)*fx26 -> 54.4 | G8: =SUM(C8:F8) -> 64 | H8: Interested-party／Assumed | I8: 2Q26 講稿：FY2026 資料中心超過 20 億美元、4Q26 量產 | J8: FY2025 視為 0（量產自 4Q26）；1–3Q 部分放在 3Q 欄
A9: 智慧邊緣平台（不含 AI ASIC） | B9: =B6-B8 -> 247.32589 | C9: =C6-C8 -> 68.60946 | D9: =D6-D8 -> 80.65699 | E9: =E6-E8 -> 83.398756 | F9: =F6-F8 -> 79.228818 | G9: =SUM(C9:F9) -> 311.89402 | H9: Derived | I9: — | J9: —
A10: 毛利 | B10: 283.08 | C10: 69.055 | D10: 70.308 | E10: =E4*q3_gm -> 77.30622 | F10: =q4_gmx*(F5+F9+F7)+F8*(m_core*(1-hf26)+m_hbm*hf26) -> 90.508648 | G10: =SUM(C10:F10) -> 307.17787 | H10: Verified／Interested-party（3Q）／Assumed（4Q） | I10: FY2025：4Q25 營運報告；1Q26、2Q26：2Q26 營運報告（公司） | J10: 4Q：非 ASIC × 毛利率＋ASIC（核心 m_core、代購 HBM m_hbm）
A11: 毛利率 | B11: =B10/B4 -> 0.47499354 | C11: =C10/C4 -> 0.46298717 | D11: =D10/D4 -> 0.46199641 | E11: =E10/E4 -> 0.46 | F11: =F10/F4 -> 0.44122378 | G11: =G10/G4 -> 0.45540086 | H11: Derived | I11: — | J11: 公司：FY2025 47.5%、1Q26 46.3%、2Q26 46.2%
A12: 營業費用（推銷＋管理＋研發） | B12: 179.61 | C12: 46.165 | D12: 47.44 | E12: =q3_opx -> 48.5 | F12: =q4_opx -> 50 | G12: =SUM(C12:F12) -> 192.105 | H12: Verified／Interested-party／Assumed | I12: FY2025：4Q25 營運報告；1Q26、2Q26：2Q26 營運報告（公司） | J12: —
A13: 營業利益 | B13: =B10-B12 -> 103.47 | C13: =C10-C12 -> 22.89 | D13: =D10-D12 -> 22.868 | E13: =E10-E12 -> 28.80622 | F13: =F10-F12 -> 40.508648 | G13: =SUM(C13:F13) -> 115.07287 | H13: Derived | I13: FY2025：4Q25 營運報告；1Q26、2Q26：2Q26 營運報告（公司） | J13: 公司：FY2025 103.470、1Q26 22.891、2Q26 22.868（核對見下方）
A14: 營業外淨額 | B14: 21.418 | C14: 4.129 | D14: 5.094 | E14: =q_nonop -> 4.8 | F14: =q_nonop -> 4.8 | G14: =SUM(C14:F14) -> 18.823 | H14: Verified／Assumed | I14: FY2025：4Q25 營運報告；1Q26、2Q26：2Q26 營運報告（公司） | J14: —
A15: 稅前利益 | B15: =B13+B14 -> 124.888 | C15: =C13+C14 -> 27.019 | D15: =D13+D14 -> 27.962 | E15: =E13+E14 -> 33.60622 | F15: =F13+F14 -> 45.308648 | G15: =SUM(C15:F15) -> 133.89587 | H15: Derived | I15: — | J15: —
A16: 所得稅 | B16: 18.77 | C16: 2.643 | D16: 3.357 | E16: =E15*q_tax -> 4.3688086 | F16: =F15*q_tax -> 5.8901243 | G16: =SUM(C16:F16) -> 16.258933 | H16: Verified／Assumed | I16: FY2025：4Q25 營運報告；1Q26、2Q26：2Q26 營運報告（公司） | J16: —
A17: 非控制權益 | B17: 0.798 | C17: 0.222 | D17: 0.27 | E17: =q_nci -> 0.25 | F17: =q_nci -> 0.25 | G17: =SUM(C17:F17) -> 0.992 | H17: Verified／Derived | I17: FY2025：4Q25 營運報告；1Q26、2Q26：2Q26 營運報告（公司） | J17: —
A18: 歸屬母公司淨利 | B18: =B15-B16-B17 -> 105.32 | C18: =C15-C16-C17 -> 24.154 | D18: =D15-D16-D17 -> 24.335 | E18: =E15-E16-E17 -> 28.987411 | F18: =F15-F16-F17 -> 39.168524 | G18: =SUM(C18:F18) -> 116.64494 | H18: Derived | I18: FY2025：4Q25 營運報告；1Q26、2Q26：2Q26 營運報告（公司） | J18: 公司：FY2025 105.319、1Q26 24.154、2Q26 24.335
A19: 公司揭露歸屬母公司淨利 | B19: 105.319 | C19: 24.154 | D19: 24.335 | H19: Verified | I19: FY2025：4Q25 營運報告；1Q26、2Q26：2Q26 營運報告（公司） | J19: —
A20: 加權股數（十億股） | B20: =105.319/66.16 -> 1.5918833 | C20: =24.154/15.17 -> 1.5922215 | D20: =24.335/15.28 -> 1.5926047 | E20: =q_sh -> 1.5926047 | F20: =q_sh -> 1.5926047 | G20: =AVERAGE(C20:F20) -> 1.5925089 | H20: Derived | I20: 淨利 ÷ EPS（公司） | J20: —
A21: EPS（基本） | B21: =B18/B20 -> 66.160628 | C21: =C18/C20 -> 15.17 | D21: =D18/D20 -> 15.28 | E21: =E18/E20 -> 18.201259 | F21: =F18/F20 -> 24.594002 | G21: =G18/G20 -> 73.246018 | H21: Derived | I21: 淨利 ÷ 股數 | J21: —
A22: 公司揭露 EPS | B22: 66.16 | C22: 15.17 | D22: 15.28 | H22: Verified | I22: FY2025：4Q25 營運報告；1Q26、2Q26：2Q26 營運報告（公司） | J22: —
A24: FY2026 錨點的檢查（參考；校準未使用券商數字）
A25: FY2026 營收年增 | B25: =G4/B4-1 -> 0.13181278
A26: FY2026 美元營收年增（各季營收 ÷ 匯率；對照公司高個位數） | B26: =(C4/fx_q1+D4/fx_q2+(E4+F4)/fx26)/co_usd25-1 -> 0.1130116
A27: FY2026 手機年增 | B27: =G5/B5-1 -> -0.16844768
A28: FY2026 智慧邊緣平台（不含 ASIC）年增 | B28: =G9/B9-1 -> 0.261065
A29: 3Q26 營收 ÷ 指引上緣 159.8 − 1 | B29: =E4/159.8-1 -> 0.051670839
A30: 4Q26 營收季增 | B30: =F4/E4-1 -> 0.22060336
A31: 檢查：FY2025 營業利益 自算 − 公司 103.470（應約為 0） | B31: =B13-103.47 -> 0
A32: 檢查：1H26 歸屬淨利 自算 − 公司 48.489（應約為 0） | B32: =C18+D18-48.489 -> 0
A33: 檢查：FY2025 歸屬淨利 自算 − 公司（應約為 0） | B33: =B18-B19 -> 0.001
A35: 檢查：分部合計 − 合併營收 | B35: =ROUND(B5+B6+B7-B4,3) -> 0 | C35: =ROUND(C5+C6+C7-C4,3) -> 0 | D35: =ROUND(D5+D6+D7-D4,3) -> 0 | E35: =ROUND(E5+E6+E7-E4,3) -> 0 | F35: =ROUND(F5+F6+F7-F4,3) -> 0 | G35: =ROUND(G5+G6+G7-G4,3) -> 0
A36: 分部原則第 3 條（2026-10-28 追加）：產品線別營收；分部宣告見 segments.json

Sheet Units
A1: Units — 聯發科 AI ASIC 規格（情境 A）。ASIC 核心售價、HBM 代購比例取自 Broadcom 模型（本專案權威，唯讀）；顆數：百萬顆（日曆年；與 HBM、台積電、Broadcom、Marvell 模型同一份）；每顆價：US$K
A3: 項目 | B3: 單位 | C3: CY2026 | D3: CY2027 | E3: CY2028 | F3: CY2029 | G3: 說明
A4: 1. Google TPU（情境 A；聯發科營收口徑＝核心售價＋代購 HBM，乘 k_x）
A5: Google TPU 市場顆數 | B5: 百萬顆 | C5: =PL!D63 -> 3.85 | D5: =PL!E63 -> 5.5 | E5: =PL!F63 -> 7 | F5: =PL!G63 -> 8.05 | G5: tsmc 成品 In 頁
A6: 聯發科份額：Google TPU | B6: % | C6: =PL!D65 -> 0.05 | D6: =PL!E65 -> 0.15 | E6: =PL!F65 -> 0.18 | F6: =PL!G65 -> 0.18 | G6: In 頁 B 節（Assumed）
A7: 聯發科顆數：Google TPU | B7: 百萬顆 | C7: =PL!D67 -> 0.1925 | D7: =PL!E67 -> 0.825 | E7: =PL!F67 -> 1.26 | F7: =PL!G67 -> 1.449 | G7: 市場層顆數 × 份額
A8: 每顆 HBM 金額：Google TPU | B8: US$K | C8: =PL!D74 -> 2.8032 | D8: =PL!E74 -> 6.57 | E8: =PL!F74 -> 8.325504 | F8: =PL!G74 -> 7.9092288 | G8: 容量 × HBM 單價（情境 A）
A9: 每顆聯發科營收（校準後）：Google TPU | B9: US$K | C9: =PL!D76*PL!$D$79 -> 10.38961 | D9: =PL!E76*PL!$D$79 -> 12.814889 | E9: =PL!F76*PL!$D$79 -> 13.945181 | F9: =PL!G76*PL!$D$79 -> 13.67716 | G9: （核心＋代購比例 × HBM）× k_x
A10: 聯發科 AI ASIC 營收（美元） | B10: US$B | C10: =PL!D80 -> 2 | D10: =PL!E80 -> 10.572283 | E10: =PL!F80 -> 17.570928 | F10: =PL!G80 -> 19.818204 | G10: 含其他 ASIC（基準份額 0）
A12: 2. 份額加總檢查（Broadcom＋Marvell＋聯發科 ≤ 100%；Broadcom、Marvell 份額讀各自成品 In 頁）
A13: Broadcom＋Marvell＋聯發科：Google TPU | B13: % | C13: =av_tpu_26+mv_tpu_26+PL!D65 -> 0.95 | D13: =av_tpu_27+mv_tpu_27+PL!E65 -> 0.95 | E13: =av_tpu_28+mv_tpu_28+PL!F65 -> 0.98 | F13: =av_tpu_28+mv_tpu_28+PL!G65 -> 0.98 | G13: 其餘為世芯、創意、華為等
A14: Broadcom＋Marvell＋聯發科：其他 ASIC（MTIA、Maia、Ascend 等） | B14: % | C14: =av_oth_26+mv_oth_26+PL!D66 -> 0.4 | D14: =av_oth_27+mv_oth_27+PL!E66 -> 0.61 | E14: =av_oth_28+mv_oth_28+PL!F66 -> 0.7 | F14: =av_oth_28+mv_oth_28+PL!G66 -> 0.7 | G14: 其餘為世芯、創意、華為等
A15: 聯發科 TPU 份額上限（1 − Broadcom − Marvell 基準） | B15: % | C15: =1-av_tpu_26-mv_tpu_26 -> 0.1 | D15: =1-av_tpu_27-mv_tpu_27 -> 0.2 | E15: =1-av_tpu_28-mv_tpu_28 -> 0.2 | F15: =1-av_tpu_28-mv_tpu_28 -> 0.2 | G15: In 頁份額高值受此上限限制
A17: 3. 校準值（只用 FY2026 已發生的實績、當季指引與公司全年資料中心說法；不用共識、不用 FY2027 起的目標）
A18: ASIC 校準係數 k_x | C18: =PL!D79 -> 1.073094 | G18: 公司 FY2026 資料中心營收 ÷ 未校準由下而上
A19: 非 ASIC 毛利率（FY2026 殘差） | C19: =PL!D98 -> 0.4623407 | G19: 讓 FY2026 毛利等於錨點
A20: FY2026 資料中心營收（公司） | C20: =dc26 -> 2 | G20: US$B
A22: 讀法：聯發科 ASIC 營收受市場層 TPU 顆數與 Broadcom、Marvell 份額共同限制；CY2028 份額上限 20%（1 − 75% − 5%）。賣方 FY2028 約 500 億美元的 ASIC 營收需要的顆數或單價遠高於此口徑（Recon 第 B 節）。

Sheet PL
A1: PL — 聯發科損益（十億新台幣；EPS 新台幣、基本；歸屬母公司）。FY2025A 實績、FY2026 錨點（三情境相同），FY2027–FY2029 由驅動因子推導，FY2030–FY2032 為收斂法。FY(t)＝CY(t)。三情境各一個完整推導區塊（本頁下方），頂端為摘要
A2: 灰底＝FY2030–FY2032 收斂法（上游顆數只到 CY2029）：營收年增線性收斂到 fade_g、淨利率線性收斂到 fade_m（In 頁 I 節），非驅動因子推導
A3: 情境／項目 | B3: 單位 | C3: FY2025A | D3: FY2026（錨點） | E3: FY2027 | F3: FY2028 | G3: FY2029 | H3: FY2030（收斂） | I3: FY2031（收斂） | J3: FY2032（收斂） | K3: 說明
A4: 情境 A
A5: 營收 | B5: NT$B | C5: =C92 -> 595.966 | D5: =D92 -> 674.52194 | E5: =E92 -> 989.79708 | F5: =F92 -> 1251.4725 | G5: =G92 -> 1363.4445 | H5: =H92 -> 1472.0403 | I5: =I92 -> 1574.8241 | J5: =J92 -> 1669.3136
A6: 營收年增 | B6: % | D6: =D93 -> 0.13181278 | E6: =E93 -> 0.46740532 | F6: =F93 -> 0.26437274 | G6: =G93 -> 0.08947221 | H6: =H93 -> 0.07964814 | I6: =I93 -> 0.06982407 | J6: =J93 -> 0.06
A7: AI ASIC | B7: NT$B | C7: =C82 -> 0 | D7: =D82 -> 64 | E7: =E82 -> 338.31306 | F7: =F82 -> 562.26971 | G7: =G82 -> 634.18254
A8: 手機 | B8: NT$B | C8: =C88 -> 315.86198 | D8: =D88 -> 262.65576 | E8: =E88 -> 275.78855 | F8: =F88 -> 286.82009 | G8: =G88 -> 298.29289
A9: 智慧邊緣平台（不含 ASIC） | B9: NT$B | C9: =C89 -> 247.32589 | D9: =D89 -> 311.89402 | E9: =E89 -> 336.84555 | F9: =F89 -> 360.42473 | G9: =G89 -> 385.65446
A10: 電源 IC | B10: NT$B | C10: =C90 -> 32.77813 | D10: =D90 -> 35.972154 | E10: =E90 -> 38.849926 | F10: =F90 -> 41.95792 | G10: =G90 -> 45.314553
A11: 毛利率 | B11: % | C11: =C100 -> 0.47499354 | D11: =D100 -> 0.45540086 | E11: =E100 -> 0.41863328 | F11: =F100 -> 0.39635029 | G11: =G100 -> 0.39598675
A12: 營業利益率 | B12: % | C12: =C103 -> 0.17361729 | D12: =D103 -> 0.17059915 | E12: =E103 -> 0.1973331 | F12: =F103 -> 0.20744089 | G12: =G103 -> 0.2121877
A13: 歸屬母公司淨利 | B13: NT$B | C13: =C108 -> 105.32 | D13: =D108 -> 116.64494 | E13: =E108 -> 182.45496 | F13: =F108 -> 237.74164 | G13: =G108 -> 263.28328 | H13: =H108 -> 284.2533 | I13: =I108 -> 304.10103 | J13: =J108 -> 322.34709
A14: 淨利率 | B14: % | C14: =C112 -> 0.17672149 | D14: =D112 -> 0.17292979 | E14: =E112 -> 0.18433573 | F14: =F112 -> 0.18996954 | G14: =G112 -> 0.19310158 | H14: =H112 -> 0.19310158 | I14: =I112 -> 0.19310158 | J14: =J112 -> 0.19310158
A15: EPS | B15: NT$ | C15: =C110 -> 66.160628 | D15: =D110 -> 73.246018 | E15: =E110 -> 114.57077 | F15: =F110 -> 149.28748 | G15: =G110 -> 165.3261 | H15: =H110 -> 178.49401 | I15: =I110 -> 190.95719 | J15: =J110 -> 202.41462
A16: EPS 年增 | B16: % | D16: =D111 -> 0.10709374 | E16: =E111 -> 0.56419106 | F16: =F111 -> 0.30301548 | G16: =G111 -> 0.10743442 | H16: =H111 -> 0.07964814 | I16: =I111 -> 0.06982407 | J16: =J111 -> 0.06
A18: 情境 B
A19: 營收 | B19: NT$B | C19: =C147 -> 595.966 | D19: =D147 -> 674.52194 | E19: =E147 -> 962.74965 | F19: =F147 -> 1038.9612 | G19: =G147 -> 1146.9657 | H19: =H147 -> 1241.7467 | I19: =I147 -> 1317.8882 | J19: =J147 -> 1370.6038
A20: 營收年增 | B20: % | D20: =D148 -> 0.13181278 | E20: =E148 -> 0.42730665 | F20: =F148 -> 0.079160253 | G20: =G148 -> 0.10395438 | H20: =H148 -> 0.082636251 | I20: =I148 -> 0.061318125 | J20: =J148 -> 0.04
A21: AI ASIC | B21: NT$B | C21: =C137 -> 0 | D21: =D137 -> 64 | E21: =E137 -> 338.31306 | F21: =F137 -> 394.80022 | G21: =G137 -> 482.39652
A22: 手機 | B22: NT$B | C22: =C143 -> 315.86198 | D22: =D143 -> 262.65576 | E22: =E143 -> 262.65576 | F22: =F143 -> 267.90888 | G22: =G143 -> 273.26705
A23: 智慧邊緣平台（不含 ASIC） | B23: NT$B | C23: =C144 -> 247.32589 | D23: =D144 -> 311.89402 | E23: =E144 -> 324.36978 | F23: =F144 -> 337.34458 | G23: =G144 -> 350.83836
A24: 電源 IC | B24: NT$B | C24: =C145 -> 32.77813 | D24: =D145 -> 35.972154 | E24: =E145 -> 37.41104 | F24: =F145 -> 38.907481 | G24: =G145 -> 40.463781
A25: 毛利率 | B25: % | C25: =C155 -> 0.47499354 | D25: =D155 -> 0.45540086 | E25: =E155 -> 0.41740536 | F25: =F155 -> 0.41793695 | G25: =G155 -> 0.4131939
A26: 營業利益率 | B26: % | C26: =C158 -> 0.17361729 | D26: =D158 -> 0.17059915 | E26: =E158 -> 0.19228835 | F26: =F158 -> 0.19681685 | G26: =G158 -> 0.20087777
A27: 歸屬母公司淨利 | B27: NT$B | C27: =C163 -> 105.32 | D27: =D163 -> 116.64494 | E27: =E163 -> 173.68797 | F27: =F163 -> 190.33715 | G27: =G163 -> 212.62393 | H27: =H163 -> 222.52123 | I27: =I163 -> 228.02216 | J27: =J163 -> 228.67365
A28: 淨利率 | B28: % | C28: =C167 -> 0.17672149 | D28: =D167 -> 0.17292979 | E28: =E167 -> 0.18040824 | F28: =F167 -> 0.18319949 | G28: =G167 -> 0.1853795 | H28: =H167 -> 0.17920018 | I28: =I167 -> 0.17302087 | J28: =J167 -> 0.16684155
A29: EPS | B29: NT$ | C29: =C165 -> 66.160628 | D29: =D165 -> 73.246018 | E29: =E165 -> 109.06562 | F29: =F165 -> 119.5203 | G29: =G165 -> 133.51506 | H29: =H165 -> 139.72997 | I29: =I165 -> 143.18423 | J29: =J165 -> 143.59333
A30: EPS 年增 | B30: % | D30: =D166 -> 0.10709374 | E30: =E166 -> 0.48903136 | F30: =F166 -> 0.09585685 | G30: =G166 -> 0.11709107 | H30: =H166 -> 0.046548376 | I30: =I166 -> 0.024720949 | J30: =J166 -> 0.0028571429
A32: 情境 C
A33: 營收 | B33: NT$B | C33: =C202 -> 595.966 | D33: =D202 -> 674.52194 | E33: =E202 -> 918.46572 | F33: =F202 -> 854.34533 | G33: =G202 -> 896.19884 | H33: =H202 -> 931.44275 | I33: =I202 -> 959.07214 | J33: =J202 -> 978.25358
A34: 營收年增 | B34: % | D34: =D203 -> 0.13181278 | E34: =E203 -> 0.36165433 | F34: =F203 -> -0.069812505 | G34: =G203 -> 0.048988991 | H34: =H203 -> 0.039325994 | I34: =I203 -> 0.029662997 | J34: =J203 -> 0.02
A35: AI ASIC | B35: NT$B | C35: =C192 -> 0 | D35: =D192 -> 64 | E35: =E192 -> 338.31306 | F35: =F192 -> 278.4166 | G35: =G192 -> 324.24631
A36: 手機 | B36: NT$B | C36: =C198 -> 315.86198 | D36: =D198 -> 262.65576 | E36: =E198 -> 241.6433 | F36: =F198 -> 234.394 | G36: =G198 -> 227.36218
A37: 智慧邊緣平台（不含 ASIC） | B37: NT$B | C37: =C199 -> 247.32589 | D37: =D199 -> 311.89402 | E37: =E199 -> 302.5372 | F37: =F199 -> 305.56257 | G37: =G199 -> 308.6182
A38: 電源 IC | B38: NT$B | C38: =C200 -> 32.77813 | D38: =D200 -> 35.972154 | E38: =E200 -> 35.972154 | F38: =F200 -> 35.972154 | G38: =G200 -> 35.972154
A39: 毛利率 | B39: % | C39: =C210 -> 0.47499354 | D39: =D210 -> 0.45540086 | E39: =E210 -> 0.4152388 | F39: =F210 -> 0.42934134 | G39: =G210 -> 0.4245193
A40: 營業利益率 | B40: % | C40: =C213 -> 0.17361729 | D40: =D213 -> 0.17059915 | E40: =E213 -> 0.18338727 | F40: =F213 -> 0.16513372 | G40: =G213 -> 0.15753835
A41: 歸屬母公司淨利 | B41: NT$B | C41: =C218 -> 105.32 | D41: =D218 -> 116.64494 | E41: =E218 -> 159.33403 | F41: =F218 -> 135.80985 | G41: =G218 -> 135.89969 | H41: =H218 -> 131.82781 | I41: =I218 -> 126.04263 | J41: =J218 -> 118.67399
A42: 淨利率 | B42: % | C42: =C222 -> 0.17672149 | D42: =D222 -> 0.17292979 | E42: =E222 -> 0.17347848 | F42: =F222 -> 0.15896365 | G42: =G222 -> 0.15164011 | H42: =H222 -> 0.14153077 | I42: =I222 -> 0.13142143 | J42: =J222 -> 0.12131209
A43: EPS | B43: NT$ | C43: =C220 -> 66.160628 | D43: =D220 -> 73.246018 | E43: =E220 -> 100.05221 | F43: =F220 -> 85.280435 | G43: =G220 -> 85.336849 | H43: =H220 -> 82.779952 | I43: =I220 -> 79.147207 | J43: =J220 -> 74.520139
A44: EPS 年增 | B44: % | D44: =D221 -> 0.10709374 | E44: =E221 -> 0.36597472 | F44: =F221 -> -0.14764065 | G44: =G221 -> 0.00066150575 | H44: =H221 -> -0.029962405 | I44: =I221 -> -0.04388436 | J44: =J221 -> -0.058461538
A46: 核對（應為 0）：FY2026 模型 − 錨點
A47: 三情境：營收差（NT$B） | D47: =ABS(D92-a26_rev)+ABS(D147-a26_rev)+ABS(D202-a26_rev) -> 0
A48: 三情境：EPS 差（NT$） | D48: =ABS(D110-a26_eps)+ABS(D165-a26_eps)+ABS(D220-a26_eps) -> 0
A49: 情境 A：ASIC 由下而上 − Q 頁 ASIC（NT$B） | D49: =D82-a26_asic -> 0
A60: 情境 A（順利）：顆數基準；手機 FY2027 +5%、之後 +4%；智慧邊緣 +8%／+7%；電源 IC +8%
A61: 項目 | B61: 單位 | C61: FY2025A | D61: FY2026（錨點） | E61: FY2027 | F61: FY2028 | G61: FY2029 | H61: FY2030（收斂） | I61: FY2031（收斂） | J61: FY2032（收斂） | K61: 說明
A62: A. AI ASIC（由下而上；D 欄＝FY2026 校準年；FY(t)＝CY(t)）
A63: Google TPU 市場顆數（含情境係數） | B63: 百萬顆 | D63: =u_tpu_26 -> 3.85 | E63: =u_tpu_27 -> 5.5 | F63: =u_tpu_28*um28_A -> 7 | G63: =u_tpu_28*(1+g29_tpu)*um29_A -> 8.05
A64: 其他 ASIC（MTIA、Maia、Ascend 等） 市場顆數（含情境係數） | B64: 百萬顆 | D64: =u_oth_26 -> 1 | E64: =u_oth_27 -> 4.5 | F64: =u_oth_28*um28_A -> 5 | G64: =u_oth_28*(1+g29_oth)*um29_A -> 5.75
A65: 聯發科份額：Google TPU | B65: % | D65: =mtk_tpu_26 -> 0.05 | E65: =MIN(1,MAX(0,mtk_tpu_27+0)) -> 0.15 | F65: =MIN(1,MAX(0,mtk_tpu_28+0)) -> 0.18 | G65: =MIN(1,MAX(0,mtk_tpu_28+0)) -> 0.18
A66: 聯發科份額：其他 ASIC（MTIA、Maia、Ascend 等） | B66: % | D66: =mtk_oth_26 -> 0 | E66: =MIN(1,MAX(0,mtk_oth_27+0)) -> 0 | F66: =MIN(1,MAX(0,mtk_oth_28+0)) -> 0 | G66: =MIN(1,MAX(0,mtk_oth_28+0)) -> 0
A67: 聯發科顆數：Google TPU | B67: 百萬顆 | D67: =D63*D65 -> 0.1925 | E67: =E63*E65*1 -> 0.825 | F67: =F63*F65*1 -> 1.26 | G67: =G63*G65*1 -> 1.449
A68: 聯發科顆數：其他 ASIC（MTIA、Maia、Ascend 等） | B68: 百萬顆 | D68: =D64*D66 -> 0 | E68: =E64*E66*1 -> 0 | F68: =F64*F66*1 -> 0 | G68: =G64*G66*1 -> 0
A69: 每顆 HBM：Google TPU | B69: GB | D69: =gb_tpu_26 -> 192 | E69: =gb_tpu_27 -> 250 | F69: =gb_tpu_28 -> 288 | G69: =gb_tpu_28 -> 288
A70: 每顆 HBM：其他 ASIC（MTIA、Maia、Ascend 等） | B70: GB | D70: =gb_oth_26 -> 150 | E70: =gb_oth_27 -> 200 | F70: =gb_oth_28 -> 250 | G70: =gb_oth_28 -> 250
A71: HBM 單價 | B71: US$/GB | D71: =hbm_A_26 -> 14.6 | E71: =hbm_A_27 -> 26.28 | F71: =hbm_A_28 -> 28.908 | G71: =hbm_A_29 -> 27.4626
A72: 每顆核心售價：Google TPU | B72: US$K | D72: =core_tpu -> 8 | E72: =core_tpu -> 8 | F72: =core_tpu*1 -> 8 | G72: =core_tpu*1 -> 8
A73: 每顆核心售價：其他 ASIC（MTIA、Maia、Ascend 等） | B73: US$K | D73: =core_oth -> 6 | E73: =core_oth -> 6 | F73: =core_oth*1 -> 6 | G73: =core_oth*1 -> 6
A74: 每顆 HBM 金額（全部）：Google TPU | B74: US$K | D74: =D69*D71/1000 -> 2.8032 | E74: =E69*E71/1000 -> 6.57 | F74: =F69*F71/1000 -> 8.325504 | G74: =G69*G71/1000 -> 7.9092288
A75: 每顆 HBM 金額（全部）：其他 ASIC（MTIA、Maia、Ascend 等） | B75: US$K | D75: =D70*D71/1000 -> 2.19 | E75: =E70*E71/1000 -> 5.256 | F75: =F70*F71/1000 -> 7.227 | G75: =G70*G71/1000 -> 6.86565
A76: 每顆聯發科營收（核心＋代購 HBM）：Google TPU | B76: US$K | D76: =D72+f_hbm*D74 -> 9.68192 | E76: =E72+f_hbm*E74 -> 11.942 | F76: =F72+f_hbm*F74 -> 12.995302 | G76: =G72+f_hbm*G74 -> 12.745537 | K76: 核心售價 ＋ 代購比例 × HBM 金額（未乘 k_x）
A77: 每顆聯發科營收（核心＋代購 HBM）：其他 ASIC（MTIA、Maia、Ascend 等） | B77: US$K | D77: =D73+f_hbm*D75 -> 7.314 | E77: =E73+f_hbm*E75 -> 9.1536 | F77: =F73+f_hbm*F75 -> 10.3362 | G77: =G73+f_hbm*G75 -> 10.11939
A78: AI ASIC 營收（未校準） | B78: US$B | D78: =D67*D76+D68*D77 -> 1.8637696 | E78: =E67*E76+E68*E77 -> 9.85215 | F78: =F67*F76+F68*F77 -> 16.374081 | G78: =G67*G76+G68*G77 -> 18.468284
A79: ASIC 校準係數 k_x ＝ FY2026 公司資料中心營收 ÷ 未校準 | B79: x | D79: =dc26/D78 -> 1.073094 | K79: Derived：以公司 FY2026「超過 20 億美元」校準；FY2027 起沿用。顆數、份額、單價的合併係數
A80: AI ASIC 營收（美元） | B80: US$B | D80: =D78*$D$79 -> 2 | E80: =E78*$D$79 -> 10.572283 | F80: =F78*$D$79 -> 17.570928 | G80: =G78*$D$79 -> 19.818204
A81: 匯率 | B81: NT$/US$ | D81: =fx26 -> 32 | E81: =fx -> 32 | F81: =fx -> 32 | G81: =fx -> 32
A82: AI ASIC 營收 | B82: NT$B | C82: =a25_asic -> 0 | D82: =D80*D81 -> 64 | E82: =E80*E81 -> 338.31306 | F82: =F80*F81 -> 562.26971 | G82: =G80*G81 -> 634.18254
A83: 其中代購 HBM | B83: NT$B | D83: =$D$79*f_hbm*(D67*D74+D68*D75)*D81 -> 11.117927 | E83: =$D$79*f_hbm*(E67*E74+E68*E75)*E81 -> 111.67561 | F83: =$D$79*f_hbm*(F67*F74+F68*F75)*F81 -> 216.1325 | G83: =$D$79*f_hbm*(G67*G74+G68*G75)*G81 -> 236.12476
A84: 其中核心（設計＋晶片＋封裝） | B84: NT$B | D84: =D82-D83 -> 52.882073 | E84: =E82-E83 -> 226.63746 | F84: =F82-F83 -> 346.1372 | G84: =G82-G83 -> 398.05779
A85: 聯發科 ASIC 顆數合計 | B85: 百萬顆 | D85: =D67+D68 -> 0.1925 | E85: =E67+E68 -> 0.825 | F85: =F67+F68 -> 1.26 | G85: =G67+G68 -> 1.449
A86: 每顆聯發科 ASIC 營收（校準後） | B86: US$K | D86: =IF(D85>0,D80/D85,0) -> 10.38961 | E86: =IF(E85>0,E80/E85,0) -> 12.814889 | F86: =IF(F85>0,F80/F85,0) -> 13.945181 | G86: =IF(G85>0,G80/G85,0) -> 13.67716
A87: B. 手機、智慧邊緣平台（不含 ASIC）、電源 IC（FY2027 起簡化成長率）
A88: 手機 | B88: NT$B | C88: =a25_mob -> 315.86198 | D88: =a26_mob -> 262.65576 | E88: =D88*(1+g_mob27_A) -> 275.78855 | F88: =E88*(1+g_mobL_A) -> 286.82009 | G88: =F88*(1+g_mobL_A) -> 298.29289
A89: 智慧邊緣平台（不含 ASIC） | B89: NT$B | C89: =a25_sepx -> 247.32589 | D89: =a26_sepx -> 311.89402 | E89: =D89*(1+g_sep27_A) -> 336.84555 | F89: =E89*(1+g_sepL_A) -> 360.42473 | G89: =F89*(1+g_sepL_A) -> 385.65446
A90: 電源 IC | B90: NT$B | C90: =a25_pic -> 32.77813 | D90: =a26_pic -> 35.972154 | E90: =D90*(1+g_pic27_A) -> 38.849926 | F90: =E90*(1+g_picL_A) -> 41.95792 | G90: =F90*(1+g_picL_A) -> 45.314553
A91: 非 ASIC 合計 | B91: NT$B | C91: =C88+C89+C90 -> 595.966 | D91: =D88+D89+D90 -> 610.52194 | E91: =E88+E89+E90 -> 651.48402 | F91: =F88+F89+F90 -> 689.20274 | G91: =G88+G89+G90 -> 729.26191
A92: 營收 | B92: NT$B | C92: =C91+C82 -> 595.966 | D92: =D91+D82 -> 674.52194 | E92: =E91+E82 -> 989.79708 | F92: =F91+F82 -> 1251.4725 | G92: =G91+G82 -> 1363.4445 | H92: =G92*(1+H93) -> 1472.0403 | I92: =H92*(1+I93) -> 1574.8241 | J92: =I92*(1+J93) -> 1669.3136 | K92: FY2030 起為收斂法：營收年增由 FY2029 線性收斂到 fade_g、淨利率收斂到 fade_m（FY2032 達到），非驅動因子推導
A93: 營收年增 | B93: % | D93: =D92/C92-1 -> 0.13181278 | E93: =E92/D92-1 -> 0.46740532 | F93: =F92/E92-1 -> 0.26437274 | G93: =G92/F92-1 -> 0.08947221 | H93: =$G93+(fade_gA-$G93)*1/3 -> 0.07964814 | I93: =$G93+(fade_gA-$G93)*2/3 -> 0.06982407 | J93: =$G93+(fade_gA-$G93)*3/3 -> 0.06
A94: AI ASIC ÷ 營收 | B94: % | C94: =C82/C92 -> 0 | D94: =D82/D92 -> 0.094882014 | E94: =E82/E92 -> 0.34180042 | F94: =F82/F92 -> 0.44928652 | G94: =G82/G92 -> 0.46513266
A95: 手機 ÷ 營收 | B95: % | C95: =C88/C92 -> 0.53 | D95: =D88/D92 -> 0.38939543 | E95: =E88/E92 -> 0.2786314 | F95: =F88/F92 -> 0.2291861 | G95: =G88/G92 -> 0.21877891
A96: C. 毛利與損益
A97: AI ASIC 毛利 ＝ m_core × 核心 ＋ m_hbm × 代購 HBM | B97: NT$B | D97: =m_core*D84+m_hbm*D83 -> 24.908726 | E97: =m_core*E84+m_hbm*E83 -> 113.15442 | F97: =m_core*F84+m_hbm*F83 -> 177.37499 | G97: =m_core*G84+m_hbm*G83 -> 202.73848
A98: 非 ASIC 毛利率（FY2026 殘差，之後沿用＋調整） | B98: % | C98: =a25_gp/C91 -> 0.47499354 | D98: =(a26_gp-D97)/D91 -> 0.4623407 | E98: =$D98+0 -> 0.4623407 | F98: =$D98+0 -> 0.4623407 | G98: =$D98+0 -> 0.4623407 | K98: Derived：讓 FY2026 毛利等於錨點
A99: 毛利 | B99: NT$B | C99: =a25_gp -> 283.08 | D99: =a26_gp -> 307.17787 | E99: =E98*E91+E97 -> 414.362 | F99: =F98*F91+F97 -> 496.02147 | G99: =G98*G91+G97 -> 539.90595
A100: 毛利率 | B100: % | C100: =C99/C92 -> 0.47499354 | D100: =D99/D92 -> 0.45540086 | E100: =E99/E92 -> 0.41863328 | F100: =F99/F92 -> 0.39635029 | G100: =G99/G92 -> 0.39598675
A101: 營業費用 | B101: NT$B | C101: =a25_opx -> 179.61 | D101: =a26_opx -> 192.105 | E101: =D101*(1+MAX(g_opx_min,phi*E93))+0*E92 -> 219.04227 | F101: =E101*(1+MAX(g_opx_min,phi*F93))+0*F92 -> 236.41491 | G101: =F101*(1+MAX(g_opx_min,phi*G93))+0*G92 -> 250.59981
A102: 營業利益 | B102: NT$B | C102: =C99-C101 -> 103.47 | D102: =D99-D101 -> 115.07287 | E102: =E99-E101 -> 195.31973 | F102: =F99-F101 -> 259.60656 | G102: =G99-G101 -> 289.30614
A103: 營業利益率 | B103: % | C103: =C102/C92 -> 0.17361729 | D103: =D102/D92 -> 0.17059915 | E103: =E102/E92 -> 0.1973331 | F103: =F102/F92 -> 0.20744089 | G103: =G102/G92 -> 0.2121877
A104: 營業外淨額 | B104: NT$B | C104: =a25_nonop -> 21.418 | D104: =a26_nonop -> 18.823 | E104: =nonop_f -> 18 | F104: =nonop_f -> 18 | G104: =nonop_f -> 18
A105: 稅前利益 | B105: NT$B | C105: =C102+C104 -> 124.888 | D105: =D102+D104 -> 133.89587 | E105: =E102+E104 -> 213.31973 | F105: =F102+F104 -> 277.60656 | G105: =G102+G104 -> 307.30614
A106: 所得稅 | B106: NT$B | C106: =a25_tax -> 18.77 | D106: =a26_tax -> 16.258933 | E106: =E105*tax -> 29.864762 | F106: =F105*tax -> 38.864919 | G106: =G105*tax -> 43.02286
A107: 非控制權益 | B107: NT$B | C107: =a25_nci -> 0.798 | D107: =a26_nci -> 0.992 | E107: =nci -> 1 | F107: =nci -> 1 | G107: =nci -> 1
A108: 歸屬母公司淨利 | B108: NT$B | C108: =C105-C106-C107 -> 105.32 | D108: =D105-D106-D107 -> 116.64494 | E108: =E105-E106-E107 -> 182.45496 | F108: =F105-F106-F107 -> 237.74164 | G108: =G105-G106-G107 -> 263.28328 | H108: =H92*H112 -> 284.2533 | I108: =I92*I112 -> 304.10103 | J108: =J92*J112 -> 322.34709
A109: 加權股數 | B109: 十億股 | C109: =a25_sh -> 1.5918833 | D109: =a26_sh -> 1.5925089 | E109: =D109*(1+sh_g) -> 1.5925089 | F109: =E109*(1+sh_g) -> 1.5925089 | G109: =F109*(1+sh_g) -> 1.5925089 | H109: =G109*(1+sh_g) -> 1.5925089 | I109: =H109*(1+sh_g) -> 1.5925089 | J109: =I109*(1+sh_g) -> 1.5925089
A110: EPS（基本） | B110: NT$ | C110: =C108/C109 -> 66.160628 | D110: =D108/D109 -> 73.246018 | E110: =E108/E109 -> 114.57077 | F110: =F108/F109 -> 149.28748 | G110: =G108/G109 -> 165.3261 | H110: =H108/H109 -> 178.49401 | I110: =I108/I109 -> 190.95719 | J110: =J108/J109 -> 202.41462
A111: EPS 年增 | B111: % | D111: =D110/C110-1 -> 0.10709374 | E111: =E110/D110-1 -> 0.56419106 | F111: =F110/E110-1 -> 0.30301548 | G111: =G110/F110-1 -> 0.10743442 | H111: =H110/G110-1 -> 0.07964814 | I111: =I110/H110-1 -> 0.06982407 | J111: =J110/I110-1 -> 0.06
A112: 淨利率（歸屬母公司淨利 ÷ 營收） | B112: % | C112: =C108/C92 -> 0.17672149 | D112: =D108/D92 -> 0.17292979 | E112: =E108/E92 -> 0.18433573 | F112: =F108/F92 -> 0.18996954 | G112: =G108/G92 -> 0.19310158 | H112: =$G112+(fade_mA-$G112)*1/3 -> 0.19310158 | I112: =$G112+(fade_mA-$G112)*2/3 -> 0.19310158 | J112: =$G112+(fade_mA-$G112)*3/3 -> 0.19310158
A115: 情境 B（平平）：CY2028 顆數 ×0.8、CY2029 ×0.85；手機 0%／+2%；智慧邊緣 +4%；電源 IC +4%
...

Sheet Val
A1: Val — P/E 估值（新台幣）。結論用「現價 ÷ FY2027、FY2028 EPS（模型）」；目標價＝DCF 與 Comparable 加權（第 0 節）；十年 P/E 規則值（第 3 節，年底落後 P/E）只作參考
A2: 循環位置：聯發科不是設備股，不套設備市場見頂年；以本模型營收最高的會計年度為見頂年（比照 Amkor、廣達；FY(t)＝CY(t)）。營收到 FY2029 仍在增加時，見頂年未知，判為中段
A4: 0. 目標價
A5: 0.1 DCF（股東權益現金流，FY2027–FY2032 明確期＋FY2032 後永續）
A6: 項目 | B6: A（順利） | C6: B（平平） | D6: C（不如預期） | E6: 說明
A7: 情境 EPS（FY2027–FY2032） | E7: PL 頁各情境；FY2030 起為收斂法
A8: FY2027 | B8: =PL!E15 -> 114.57077 | C8: =PL!E29 -> 109.06562 | D8: =PL!E43 -> 100.05221
A9: FY2028 | B9: =PL!F15 -> 149.28748 | C9: =PL!F29 -> 119.5203 | D9: =PL!F43 -> 85.280435
A10: FY2029 | B10: =PL!G15 -> 165.3261 | C10: =PL!G29 -> 133.51506 | D10: =PL!G43 -> 85.336849
A11: FY2030 | B11: =PL!H15 -> 178.49401 | C11: =PL!H29 -> 139.72997 | D11: =PL!H43 -> 82.779952
A12: FY2031 | B12: =PL!I15 -> 190.95719 | C12: =PL!I29 -> 143.18423 | D12: =PL!I43 -> 79.147207
A13: FY2032 | B13: =PL!J15 -> 202.41462 | C13: =PL!J29 -> 143.59333 | D13: =PL!J43 -> 74.520139
A14: 股東現金流＝EPS ×（1 − tp_g ÷ tp_roe）
A15: 再投資率（tp_g ÷ tp_roe，上限 0.8） | B15: =MIN(tp_g/tp_roe,0.8) -> 0.16563147 | E15: ROE 為近三年平均（In 頁 tp_roe）
A16: FY2027 | B16: =B8*(1-$B$15) -> 95.594241 | C16: =C8*(1-$B$15) -> 91.000919 | D16: =D8*(1-$B$15) -> 83.480414
A17: FY2028 | B17: =B9*(1-$B$15) -> 124.56078 | C17: =C9*(1-$B$15) -> 99.72398 | D17: =D9*(1-$B$15) -> 71.155312
A18: FY2029 | B18: =B10*(1-$B$15) -> 137.94289 | C18: =C10*(1-$B$15) -> 111.40077 | D18: =D10*(1-$B$15) -> 71.202381
A19: FY2030 | B19: =B11*(1-$B$15) -> 148.92979 | C19: =C11*(1-$B$15) -> 116.58629 | D19: =D11*(1-$B$15) -> 69.068987
A20: FY2031 | B20: =B12*(1-$B$15) -> 159.32867 | C20: =C12*(1-$B$15) -> 119.46842 | D20: =D12*(1-$B$15) -> 66.037938
A21: FY2032 | B21: =B13*(1-$B$15) -> 168.88839 | C21: =C13*(1-$B$15) -> 119.80975 | D21: =D13*(1-$B$15) -> 62.177259
A22: DCF 情境每股價值（折現率 tp_r） | B22: =SUMPRODUCT(B16:B21,1/(1+tp_r)^{1;2;3;4;5;6})+B21*(1+tp_g)/(tp_r-tp_g)/(1+tp_r)^6 -> 2241.9102 | C22: =SUMPRODUCT(C16:C21,1/(1+tp_r)^{1;2;3;4;5;6})+C21*(1+tp_g)/(tp_r-tp_g)/(1+tp_r)^6 -> 1642.526 | D22: =SUMPRODUCT(D16:D21,1/(1+tp_r)^{1;2;3;4;5;6})+D21*(1+tp_g)/(tp_r-tp_g)/(1+tp_r)^6 -> 919.82524 | E22: Σ 明確期現金流 ÷ (1＋r)^t ＋ 永續價值 ÷ (1＋r)^6；永續價值＝FY2032 現金流 ×(1＋g)÷(r−g)；基準日 2026 年底
A23: DCF 情境價值推到 12 個月後（×(1＋tp_r)） | B23: =B22*(1+tp_r) -> 2466.1012 | C23: =C22*(1+tp_r) -> 1806.7786 | D23: =D22*(1+tp_r) -> 1011.8078
A24: DCF 目標價（情境加權） | B24: =tp_wA*B23+tp_wB*C23+tp_wC*D23 -> 1845.5812 | E24: Σ 權重 × 情境價值 ×(1＋r)；權重見 In 頁
A26: 0.2 Comparable（市場主流同業前瞻 P/E）
A27: 同業與前瞻 P/E | B27: 代號 | C27: 前瞻 12 月 P/E | D27: 日期 | E27: 來源 | F27: 標記
A28: 高通（Qualcomm） | B28: QCOM | C28: 18.98 | D28: 2026-10-23 | E28: stockanalysis.com forward PE（分析師共識；價格日期如左） | F28: Interested-party
A29: 博通（Broadcom） | B29: AVGO | C29: 18.52 | D29: 2026-10-23 | E29: stockanalysis.com forward PE（分析師共識；價格日期如左） | F29: Interested-party
A30: 邁威爾（Marvell） | B30: MRVL | C30: 40.44 | D30: 2026-10-23 | E30: stockanalysis.com forward PE（分析師共識；價格日期如左） | F30: Interested-party
A31: 世芯-KY（Alchip） | B31: 3661.TW | C31: 17.15 | D31: 2026-10-22 | E31: stockanalysis.com forward PE（分析師共識；價格日期如左） | F31: Interested-party
A32: 創意（GUC） | B32: 3443.TW | C32: 102.85 | D32: 2026-10-08 | E32: stockanalysis.com forward PE（分析師共識；價格日期如左） | F32: Interested-party
A33: 同業前瞻 P/E 中位數 | B33: =MEDIAN(C28:C32) -> 18.98 | E33: 手機 SoC（高通）＋ASIC 設計（博通、邁威爾、世芯、創意）；不含 A 股（非 A 股公司，Andy 2026-10-25 11:53）
A34: 12 個月後的前瞻 EPS（情境加權） | B34: =tp_wA*(2/12*B8+10/12*B9)+tp_wB*(2/12*C8+10/12*C9)+tp_wC*(2/12*D8+10/12*D9) -> 119.48782 | E34: 約 2027-10 時的未來 12 月 EPS ≈ 2／12 × FY2027＋10／12 × FY2028（會計年度＝日曆年）
A35: Comparable 目標價 | B35: =B33*B34 -> 2267.8788 | E35: 同業中位數 × 前瞻 EPS
A37: 0.3 結論
A38: 項目 | B38: 數值 | E38: 說明
A39: 目標價（DCF 與 Comparable 加權） | B39: =tp_w_dcf*B24+(1-tp_w_dcf)*B35 -> 2056.73 | E39: tp_w_dcf × DCF＋（1 − tp_w_dcf）× Comparable；tp_w_dcf 見 In 頁
A40: Comparable 目標價（市場主流同業法） | B40: =B35 -> 2267.8788
A41: 市場共識目標價 | B41: =cons_tp -> 6067 | E41: stockanalysis：28 位分析師平均 6,067（中位數 5,861），2026-10-23 擷取
A42: 上檔空間：加權目標價 | B42: =B39/px-1 -> -0.48709975 | E42: 現價＝In 頁 px（2026-10-22 收盤）
A43: 上檔空間：Comparable 目標價 | B43: =B40/px-1 -> -0.4344442
A44: 與市場共識目標價的差距：EPS 因素 | B44: =B34/cons_feps-1 -> 0.15465159 | E44: 本模型前瞻 EPS ÷ 共識前瞻 EPS − 1；共識前瞻 EPS＝現價 ÷ 前瞻 P/E（In 頁 cons_feps）
A45: 與市場共識目標價的差距：倍數因素 | B45: =(cons_tp/cons_feps)/B33-1 -> 2.088909 | E45: ="共識目標價隱含 "&TEXT(cons_tp/cons_feps,"0.0")&"x，同業中位數 "&TEXT(B33,"0.0")&"x" -> 共識目標價隱含 58.6x，同業中位數 19.0x
A46: 價格帶（DCF 不如預期～順利） | B46: =TEXT(D23,"#,##0")&"～"&TEXT(B23,"#,##0") -> 1,012～2,466 | E46: C 情境價值～A 情境價值（推到 12 個月後）
A47: 歷史倍數檢查：現價隱含 P/E 的十年分位（A／B／C） | B47: =IF(px/B9>=MAX($B$86:$B$95),1,IF(px/B9<=MIN($B$86:$B$95),0,PERCENTRANK($B$86:$B$95,px/B9))) -> 1 | C47: =IF(px/C9>=MAX($B$86:$B$95),1,IF(px/C9<=MIN($B$86:$B$95),0,PERCENTRANK($B$86:$B$95,px/C9))) -> 1 | D47: =IF(px/D9>=MAX($B$86:$B$95),1,IF(px/D9<=MIN($B$86:$B$95),0,PERCENTRANK($B$86:$B$95,px/D9))) -> 1 | E47: 現價 ÷ 各情境 FY2028 EPS 在 2016–2025 年底 P/E（第 5 節兩來源平均）的分位；高於十年最大值記為 100%；只作檢查，不進目標價
A48: 目標價方法 | B48: DCF：股東現金流＝EPS ×（1 − g／ROE），r＝10%、g＝4%、ROE 為近三年平均約 24%（再投資率約 17%），FY2027–32 明確期＋永續；聯發科為輕資產 IC 設計，不改用淨利＋折舊－資本支出。FY2030 起為收斂法，ASIC 第二、第三顆的成長未在明確期展開，DCF 偏低估的方向。Comparable：高通、博通、邁威爾、世芯、創意前瞻 P/E 中位數（高通 19x、博通 18.5x 落在中間；創意 103x 為極端值，中位數不受影響）。主要偏誤：ASIC 營收受市場層 TPU 顆數與 Broadcom 份額限制，遠低於賣方（Recon 第 B 節），本模型 EPS 與目標價都偏向低估賣方路徑。情境對應：A＝順利（顆數基準）、B＝平平（顆數 ×0.8／0.85）、C＝不如預期（顆數 ×0.6、手機下滑）
A51: 1. 價格與市場隱含倍數
A52: 項目 | B52: A | C52: B | D52: C | E52: 說明
A53: 現價（2026-10-22 收盤） | B53: =px -> 4010
A54: 現價 ÷ FY2026 EPS（錨點） | B54: =px/PL!D15 -> 54.747004 | C54: =px/PL!D29 -> 54.747004 | D54: =px/PL!D43 -> 54.747004 | E54: FY2026 三情境相同（錨點）
A55: 現價 ÷ FY2027 EPS（模型） | B55: =px/PL!E15 -> 35.000203 | C55: =px/PL!E29 -> 36.766857 | D55: =px/PL!E43 -> 40.079075 | E55: FY2027 三情境只差非 ASIC 成長率（顆數情境係數從 CY2028 開始）
A56: 現價 ÷ FY2028 EPS（模型） | B56: =px/PL!F15 -> 26.860926 | C56: =px/PL!F29 -> 33.550785 | D56: =px/PL!F43 -> 47.021336
A57: 現價 ÷ FY2029 EPS（模型） | B57: =px/PL!G15 -> 24.255094 | C57: =px/PL!G29 -> 30.034064 | D57: =px/PL!G43 -> 46.990252
A58: 未來 12 月 EPS（模型 B）≈ 0.2 × FY2026＋0.8 × FY2027 | B58: =0.2*PL!D29+0.8*PL!E29 -> 101.9017
A59: 現價 ÷ 未來 12 月 EPS（模型 B） | B59: =px/B58 -> 39.351651
A60: 近 12 月 P/E（stockanalysis） | B60: =pe_ttm -> 66.23
A61: 前瞻 P/E（stockanalysis） | B61: =fpe -> 38.75
A63: 2. 循環位置（本模型營收最高年；FY(t)＝CY(t)）
A64: 情境 | B64: 營收最高年（FY2026–FY2029） | C64: FY2027 判定 | D64: 規則倍數（P/E） | E64: 見頂年是否未知 | F64: 說明
A65: A | B65: =INDEX({2026,2027,2028,2029},MATCH(MAX(PL!D92:G92),PL!D92:G92,0)) -> 2029 | C65: =IF(B65=2029,"中段",IF(2027<B65,"中段",IF(2027=B65,"見頂","谷底"))) -> 中段 | D65: =IF(C65="見頂",pe_peak,IF(C65="谷底",pe_trough,pe_mid)) -> 18.44 | E65: =IF(B65=2029,"是：營收到觀測期末仍在增加","否") -> 是：營收到觀測期末仍在增加 | F65: tools/cycle_position.py excel_rule；營收最高年取代設備市場見頂年
A66: B | B66: =INDEX({2026,2027,2028,2029},MATCH(MAX(PL!D147:G147),PL!D147:G147,0)) -> 2029 | C66: =IF(B66=2029,"中段",IF(2027<B66,"中段",IF(2027=B66,"見頂","谷底"))) -> 中段 | D66: =IF(C66="見頂",pe_peak,IF(C66="谷底",pe_trough,pe_mid)) -> 18.44 | E66: =IF(B66=2029,"是：營收到觀測期末仍在增加","否") -> 是：營收到觀測期末仍在增加 | F66: 同上
A67: C | B67: =INDEX({2026,2027,2028,2029},MATCH(MAX(PL!D202:G202),PL!D202:G202,0)) -> 2027 | C67: =IF(B67=2029,"中段",IF(2027<B67,"中段",IF(2027=B67,"見頂","谷底"))) -> 見頂 | D67: =IF(C67="見頂",pe_peak,IF(C67="谷底",pe_trough,pe_mid)) -> 14.54 | E67: =IF(B67=2029,"是：營收到觀測期末仍在增加","否") -> 否 | F67: 同上
A69: 3. 規則值隱含股價（新台幣；約 FY2027 年底，未折現）＝ FY2027 EPS × 規則倍數
A70: 情境 | B70: FY2027 EPS | C70: （同左） | D70: 規則倍數 | E70: 隱含股價 | F70: 相對現價 | G70: 現價 ÷ FY2027 EPS
A71: A | B71: =PL!E15 -> 114.57077 | C71: =B71 -> 114.57077 | D71: =D65 -> 18.44 | E71: =C71*D71 -> 2112.6849 | F71: =E71/px-1 -> -0.47314591 | G71: =px/C71 -> 35.000203
A72: B | B72: =PL!E29 -> 109.06562 | C72: =B72 -> 109.06562 | D72: =D66 -> 18.44 | E72: =C72*D72 -> 2011.17 | F72: =E72/px-1 -> -0.49846135 | G72: =px/C72 -> 36.766857
A73: C | B73: =PL!E43 -> 100.05221 | C73: =B73 -> 100.05221 | D73: =D67 -> 14.54 | E73: =C73*D73 -> 1454.7591 | F73: =E73/px-1 -> -0.63721718 | G73: =px/C73 -> 40.079075
A75: 4. What must be true：FY2027 年底價 ＝ 現價 ×（1＋報酬）所需的倍數（FY2028 EPS；約 2027 年底的價格看下一年 EPS）
A76: FY2027 年底價 ÷ 現價 | B76: 所需倍數（÷ FY2028 EPS，A） | C76: 所需倍數（÷ FY2028 EPS，B） | D76: 所需倍數（÷ FY2028 EPS，C） | E76: 對照：十年中位數
A77: 1 | B77: =px*A77/PL!F15 -> 26.860926 | C77: =px*A77/PL!F29 -> 33.550785 | D77: =px*A77/PL!F43 -> 47.021336 | E77: =pe_mid -> 18.44
A78: 1.1 | B78: =px*A78/PL!F15 -> 29.547019 | C78: =px*A78/PL!F29 -> 36.905863 | D78: =px*A78/PL!F43 -> 51.723469 | E78: =pe_mid -> 18.44
A79: 1.21 | B79: =px*A79/PL!F15 -> 32.50172 | C79: =px*A79/PL!F29 -> 40.59645 | D79: =px*A79/PL!F43 -> 56.895816 | E79: =pe_mid -> 18.44
A80: 1.5 | B80: =px*A80/PL!F15 -> 40.291389 | C80: =px*A80/PL!F29 -> 50.326177 | D80: =px*A80/PL!F43 -> 70.532004 | E80: =pe_mid -> 18.44
A81: 2 | B81: =px*A81/PL!F15 -> 53.721852 | C81: =px*A81/PL!F29 -> 67.10157 | D81: =px*A81/PL!F43 -> 94.042672 | E81: =pe_mid -> 18.44
A82: 讀法：1.00＝價格不變、1.21＝一年約 21%。所需倍數低於歷史中位數時，現價相對便宜；倍數是否合理，另看前瞻 P/E 歷史（Bloomberg）。本版未做先驗，無 Andy 合理 P/E 對照。
A84: 5. 十年 P/E（2016–2025 年底；兩來源平均，分位排名用；無負值或 >200 需剔除）
A85: 年底 | B85: 兩來源平均 P/E | C85: companiesmarketcap | D85: 自算
A86: 2016 | B86: =AVERAGE(C86:D86) -> 9.22 | C86: =B105 -> 9.22 | D86: =IF(C105="","",C105)
A87: 2017 | B87: =AVERAGE(C87:D87) -> 15.747301 | C87: =B106 -> 12.6 | D87: =IF(C106="","",C106) -> 18.894602
A88: 2018 | B88: =AVERAGE(C88:D88) -> 14.403846 | C88: =B107 -> 11.5 | D88: =IF(C107="","",C107) -> 17.307692
A89: 2019 | B89: =AVERAGE(C89:D89) -> 25.895303 | C89: =B108 -> 21.6 | D89: =IF(C108="","",C108) -> 30.190606
A90: 2020 | B90: =AVERAGE(C90:D90) -> 24.709862 | C90: =B109 -> 20.7 | D90: =IF(C109="","",C109) -> 28.719723
A91: 2021 | B91: =AVERAGE(C91:D91) -> 14.78254 | C91: =B110 -> 12.7 | D91: =IF(C110="","",C110) -> 16.865079
A92: 2022 | B92: =AVERAGE(C92:D92) -> 7.6545696 | C92: =B111 -> 6.93 | D92: =IF(C111="","",C111) -> 8.3791393
A93: 2023 | B93: =AVERAGE(C93:D93) -> 20.06176 | C93: =B112 -> 19.2 | D93: =IF(C112="","",C112) -> 20.923521
A94: 2024 | B94: =AVERAGE(C94:D94) -> 20.772325 | C94: =B113 -> 20.4 | D94: =IF(C113="","",C113) -> 21.14465
A95: 2025 | B95: =AVERAGE(C95:D95) -> 21.557134 | C95: =B114 -> 21.5 | D95: =IF(C114="","",C114) -> 21.614268
A96: 年數 | B96: =COUNT($B$86:$B$95) -> 10
A100: 6. 十年倍數與規則值（2016–2025 年底；見頂年 25 分位、中段中位數、谷底 75 分位）
A101: 規則（Andy 2026-10-13）：合理倍數＝2016–2025 年底 P/E 依循環位置取分位，兩個來源分別取分位再平均。stockanalysis 2021–2025 年底 P/E（16.99、8.42、20.99、21.20、21.67）與自算相同，只作核對。聯發科為高配息公司，companiesmarketcap 早年倍數偏低（疑為除息調整價格）；十年皆為手機 SoC 期，未含 AI ASIC 放量後的成長溢價，套用在 FY2027 EPS 時偏向低估。
A103: P/E：十年歷史倍數
A104: 年底 | B104: companiesmarketcap（年底 P/E） | C104: 自算（digrin 12 月未調整股價 ÷ 公司 EPS） | D104: 標記／說明
A105: 2016 | B105: 9.22 | D105: companiesmarketcap（年底 P/E）：Interested-party（資料商；2016–2025 共 10 年；早年價格疑為除息調整後，倍數偏低）；自算（digrin 12 月未調整股價 ÷ 公司 EPS）：Derived（價格為月資料的 12 月值；EPS：2017 科技新報、2018–2025 HiStock 與公司；2016 EPS 未找到）
A106: 2017 | B106: 12.6 | C106: =294/15.56 -> 18.894602
A107: 2018 | B107: 11.5 | C107: =229.5/13.26 -> 17.307692
A108: 2019 | B108: 21.6 | C108: =443.5/14.69 -> 30.190606
A109: 2020 | B109: 20.7 | C109: =747/26.01 -> 28.719723
A110: 2021 | B110: 12.7 | C110: =1190/70.56 -> 16.865079
A111: 2022 | B111: 6.93 | C111: =625/74.59 -> 8.3791393
A112: 2023 | B112: 19.2 | C112: =1015/48.51 -> 20.923521
A113: 2024 | B113: 20.4 | C113: =1415/66.92 -> 21.14465
...

Sheet Recon
A1: Recon — 本模型 vs 公司指引與目標、共識、券商。只作事後對照，不為對上數字而調參數。公司 FY2027 SAM 份額目標與券商 FY2027–28 估計為 Interested-party，不用於校準
A3: 項目 | B3: 對照值 | C3: 模型 A | D3: 差距 A | E3: 模型 B | F3: 差距 B | G3: 模型 C | H3: 差距 C | I3: 對照來源 | J3: 說明
A4: A. FY2026 錨點 vs 公司展望與共識
A5: FY2026 營收 vs 共識 | B5: =cons_rev26 -> 662.3 | C5: =PL!D92 -> 674.52194 | D5: =C5/B5-1 -> 0.018453779 | E5: =PL!D147 -> 674.52194 | F5: =E5/B5-1 -> 0.018453779 | G5: =PL!D202 -> 674.52194 | H5: =G5/B5-1 -> 0.018453779 | I5: stockanalysis（25 位） | J5: 凱基 678.0；3Q26 營收已超過指引上緣 5%
A6: FY2026 EPS vs 共識 | B6: =cons_eps26 -> 68.27 | C6: =PL!D110 -> 73.246018 | D6: =C6/B6-1 -> 0.072887323 | E6: =PL!D165 -> 73.246018 | F6: =E6/B6-1 -> 0.072887323 | G6: =PL!D220 -> 73.246018 | H6: =G6/B6-1 -> 0.072887323 | I6: stockanalysis（25 位） | J6: 共識區間 58.48–73.35
A7: FY2026 美元營收年增 vs 公司高個位數（百分點） | B7: =co_g26 -> 0.09 | C7: =Q!B26 -> 0.1130116 | D7: =C7-B7 -> 0.0230116 | E7: =Q!B26 -> 0.1130116 | F7: =E7-B7 -> 0.0230116 | G7: =Q!B26 -> 0.1130116 | H7: =G7-B7 -> 0.0230116 | I7: 2Q26 講稿 | J7: 3Q26 營收超出指引、4Q26 ASIC 量產
A8: B. AI ASIC vs 公司目標與賣方（市場層顆數 × 份額口徑）
A9: FY2027 ASIC（美元）vs 公司 SAM × 份額目標中點（80 × 17.5%） | B9: =co_sam27*co_sh27 -> 14 | C9: =PL!E80 -> 10.572283 | D9: =C9/B9-1 -> -0.24483692 | E9: =PL!E135 -> 10.572283 | F9: =E9/B9-1 -> -0.24483692 | G9: =PL!E190 -> 10.572283 | H9: =G9/B9-1 -> -0.24483692 | I9: 2Q26 講稿 | J9: 目標區間 12–16（US$B）；份額目標的分母為 SAM，不是 TPU 顆數
A10: FY2027 ASIC（美元）vs 高盛 120–160 億美元中點 | B10: =ss_asic27 -> 14 | C10: =PL!E80 -> 10.572283 | D10: =C10/B10-1 -> -0.24483692 | E10: =PL!E135 -> 10.572283 | F10: =E10/B10-1 -> -0.24483692 | G10: =PL!E190 -> 10.572283 | H10: =G10/B10-1 -> -0.24483692 | I10: 經濟日報 2026-08-03
A11: FY2027 ASIC ÷ 營收 vs 公司「20% 可能」（百分點） | B11: =co_dc27sh -> 0.2 | C11: =PL!E94 -> 0.34180042 | D11: =C11-B11 -> 0.14180042 | E11: =PL!E149 -> 0.35140295 | F11: =E11-B11 -> 0.15140295 | G11: =PL!E204 -> 0.36834588 | H11: =G11-B11 -> 0.16834588 | I11: 4Q25 法說
A12: FY2028 ASIC（美元）vs 凱基 500 億美元 | B12: =ss_asic28 -> 50 | C12: =PL!F80 -> 17.570928 | D12: =C12/B12-1 -> -0.64858143 | E12: =PL!F135 -> 12.337507 | F12: =E12/B12-1 -> -0.75324986 | G12: =PL!F190 -> 8.7005186 | H12: =G12/B12-1 -> -0.82598963 | I12: 凱基 2026-07-23 | J12: 差距為本模型最大的口徑問題（見下兩列）
A13: FY2028：達到凱基 ASIC 所需聯發科顆數（＝500 億 ÷ 模型每顆營收） | C13: =ss_asic28/PL!F86 -> 3.5854679 | E13: =ss_asic28/PL!F141 -> 4.0851041 | G13: =ss_asic28/PL!F196 -> 4.3445686 | I13: 推導 | J13: 百萬顆；凱基假設 v9 Humufish 400 萬顆
A14: FY2028：所需顆數 ÷ 市場層 TPU 顆數 | C14: =ss_asic28/PL!F86/PL!F63 -> 0.5122097 | E14: =ss_asic28/PL!F141/PL!F118 -> 0.72948288 | G14: =ss_asic28/PL!F196/PL!F173 -> 1.0344211 | I14: 推導 | J14: >（1 − Broadcom 75% − Marvell 5%）＝ 20% 即與 avgo 份額口徑衝突
A15: FY2028：凱基顆數下所需每顆營收（＝500 億 ÷ 400 萬顆）÷ 模型每顆營收 | C15: =ss_asic28/ss_hu28/PL!F86 -> 0.89636698 | E15: =ss_asic28/ss_hu28/PL!F141 -> 1.021276 | G15: =ss_asic28/ss_hu28/PL!F196 -> 1.0861421 | I15: 推導 | J15: 倍數；凱基稱 v9 單價至少 +200%
A16: C. EPS vs 券商（校準未使用）
A17: FY2027 EPS vs 凱基 | B17: =kgi_eps27 -> 112.6 | C17: =PL!E110 -> 114.57077 | D17: =C17/B17-1 -> 0.017502359 | E17: =PL!E165 -> 109.06562 | F17: =E17/B17-1 -> -0.031388834 | G17: =PL!E220 -> 100.05221 | H17: =G17/B17-1 -> -0.11143687 | I17: 凱基 2026-07-23
A18: FY2027 EPS vs Citi | B18: =citi_eps27 -> 133.87 | C18: =PL!E110 -> 114.57077 | D18: =C18/B18-1 -> -0.144164 | E18: =PL!E165 -> 109.06562 | F18: =E18/B18-1 -> -0.18528709 | G18: =PL!E220 -> 100.05221 | H18: =G18/B18-1 -> -0.25261666 | I18: 經濟日報 2026-08-03
A19: FY2028 EPS vs 凱基 | B19: =kgi_eps28 -> 246.6 | C19: =PL!F110 -> 149.28748 | D19: =C19/B19-1 -> -0.39461686 | E19: =PL!F165 -> 119.5203 | F19: =E19/B19-1 -> -0.51532724 | G19: =PL!F220 -> 85.280435 | H19: =G19/B19-1 -> -0.65417504 | I19: 凱基 2026-07-23 | J19: 差距 >30%：見 README
A20: FY2028 EPS vs Citi | B20: =citi_eps28 -> 260.38 | C20: =PL!F110 -> 149.28748 | D20: =C20/B20-1 -> -0.42665534 | E20: =PL!F165 -> 119.5203 | F20: =E20/B20-1 -> -0.5409774 | G20: =PL!F220 -> 85.280435 | H20: =G20/B20-1 -> -0.67247701 | I20: 經濟日報 2026-08-03
A21: FY2027 營收 vs 凱基 | B21: =kgi_rev27 -> 1110.805 | C21: =PL!E92 -> 989.79708 | D21: =C21/B21-1 -> -0.10893714 | E21: =PL!E147 -> 962.74965 | F21: =E21/B21-1 -> -0.13328654 | G21: =PL!E202 -> 918.46572 | H21: =G21/B21-1 -> -0.17315306 | I21: 凱基 2026-07-23
A22: 共識前瞻 12 月 EPS vs 模型（情境加權 2／12 × FY2027＋10／12 × FY2028） | B22: =cons_feps -> 103.48387 | C22: =Val!B34 -> 119.48782 | D22: =C22/B22-1 -> 0.15465159 | E22: =Val!B34 -> 119.48782 | F22: =E22/B22-1 -> 0.15465159 | G22: =Val!B34 -> 119.48782 | H22: =G22/B22-1 -> 0.15465159 | I22: stockanalysis 前瞻 P/E 推得 | J22: 三欄同值（情境加權）
A23: D. 校準與份額
A24: k_x（ASIC 校準係數） | C24: =PL!D79 -> 1.073094 | E24: =PL!D134 -> 1.073094 | G24: =PL!D189 -> 1.073094 | I24: 公司 FY2026 資料中心 ÷ 未校準 | J24: 接近 1＝市場層 TPU 顆數 × 5% × Broadcom 模型單價與公司說法一致
A25: 非 ASIC 毛利率（FY2026 殘差） | C25: =PL!D98 -> 0.4623407 | E25: =PL!D153 -> 0.4623407 | G25: =PL!D208 -> 0.4623407 | I25: FY2026 毛利殘差 | J25: FY2025 47.5%（全部非 ASIC）
A26: CY2028 Broadcom＋Marvell＋聯發科 TPU 份額 | B26: 1 | C26: =Units!E13 -> 0.98 | D26: =C26-B26 -> -0.02 | E26: =Units!E13 -> 0.98 | F26: =E26-B26 -> -0.02 | G26: =Units!E13 -> 0.98 | H26: =G26-B26 -> -0.02 | I26: avgo、mrvl 成品 | J26: 應 ≤ 100%
A27: FY2027 營業利益率 vs 高盛 22%（百分點） | B27: 0.22 | C27: =PL!E103 -> 0.1973331 | D27: =C27-B27 -> -0.0226669 | E27: =PL!E158 -> 0.19228835 | F27: =E27-B27 -> -0.027711648 | G27: =PL!E213 -> 0.18338727 | H27: =G27-B27 -> -0.036612729 | I27: 經濟日報 2026-05-03
A28: FY2028 營業利益率 vs 高盛 33%（百分點） | B28: 0.33 | C28: =PL!F103 -> 0.20744089 | D28: =C28-B28 -> -0.12255911 | E28: =PL!F158 -> 0.19681685 | F28: =E28-B28 -> -0.13318315 | G28: =PL!F213 -> 0.16513372 | H28: =G28-B28 -> -0.16486628 | I28: 經濟日報 2026-05-03
A29: E. 預留
A30: R4 產業部署路徑（markets/deploy_path/，尚未建立）：上線後以聯發科 ASIC 營收 ÷ 部署 GW 對照 Tokenomics 非 NVIDIA 加速器比例 | J30: 預留列：本版無數值

Sheet Sens
A1: Sens — 一次動一個輸入（情境 A；FY2026 恆等於錨點，k_x 與非 ASIC 毛利率在每個案例內重算）：對 FY2027、FY2028 營收、毛利率與 EPS 的影響。每個案例是一個完整推導區塊（本頁下方）
A3: 案例 | B3: 設定 | C3: FY2027 營收 | D3: FY2027 毛利率 | E3: FY2027 EPS | F3: FY2027 EPS 相對基準 | G3: FY2028 營收 | H3: FY2028 毛利率 | I3: FY2028 EPS | J3: FY2028 EPS 相對基準
A4: 基準（情境 A） | B4: PL 區塊 A | C4: =PL!E92 -> 989.79708 | D4: =PL!E100 -> 0.41863328 | E4: =PL!E110 -> 114.57077 | F4: =E4/E$4-1 -> 0 | G4: =PL!F92 -> 1251.4725 | H4: =PL!F100 -> 0.39635029 | I4: =PL!F110 -> 149.28748 | J4: =I4/I$4-1 -> 0
A5: TPU 份額 −5pt | B5: CY2027 起聯發科占 TPU −5 個百分點 | C5: =E72 -> 877.02606 | D5: =E80 -> 0.42945572 | E5: =E90 -> 99.405189 | F5: =E5/E$4-1 -> -0.13236864 | G5: =F72 -> 1095.2864 | H5: =F80 -> 0.40788476 | I5: =F90 -> 128.82195 | J5: =I5/I$4-1 -> -0.13708809
A6: TPU 份額取高值（上限） | B6: CY2027 20%、CY2028 起 20% | C6: =E127 -> 1102.5681 | D6: =E135 -> 0.41002468 | E6: =E145 -> 129.73634 | F6: =E6/E$4-1 -> 0.13236864 | G6: =F127 -> 1313.9469 | H6: =F135 -> 0.39250431 | I6: =F145 -> 156.69943 | J6: =I6/I$4-1 -> 0.049648835
A7: ASIC 顆數 ×0.8 | B7: CY2027 起聯發科顆數 ×0.8 | C7: =E182 -> 922.13447 | D7: =E190 -> 0.4248091 | E7: =E200 -> 105.47142 | F7: =E7/E$4-1 -> -0.079421183 | G7: =F182 -> 1139.0185 | H7: =F190 -> 0.40433625 | I7: =F200 -> 134.50755 | J7: =I7/I$4-1 -> -0.099003123
A8: ASIC 顆數 ×1.2 | B8: ×1.2（超出份額上限，僅示意） | C8: =E237 -> 1057.4597 | D8: =E245 -> 0.41324779 | E8: =E255 -> 123.67011 | F8: =E8/E$4-1 -> 0.079421183 | G8: =F237 -> 1363.9264 | H8: =F245 -> 0.3896812 | I8: =F255 -> 164.14875 | J8: =I8/I$4-1 -> 0.099547971
A9: 第二顆 ASIC 單價 ×2 | B9: CY2028 起核心售價 ×2（賣方：新世代單價數倍） | C9: =E292 -> 989.79708 | D9: =E300 -> 0.41863328 | E9: =E310 -> 114.57077 | F9: =E9/E$4-1 -> 0 | G9: =F292 -> 1597.6097 | H9: =F300 -> 0.40797401 | I9: =F310 -> 220.99335 | J9: =I9/I$4-1 -> 0.48032073
A10: 核心售價 ×0.8 | B10: CY2028 起 ×0.8 | C10: =E347 -> 989.79708 | D10: =E355 -> 0.41863328 | E10: =E365 -> 114.57077 | F10: =E10/E$4-1 -> 0 | G10: =F347 -> 1182.245 | H10: =F355 -> 0.39320879 | I10: =F365 -> 134.74871 | J10: =I10/I$4-1 -> -0.097387772
A11: 其他 ASIC 份額 +5pt | B11: CY2027 起第二客戶（基準 0） | C11: =E402 -> 1060.5203 | D11: =E410 -> 0.41268375 | E11: =E420 -> 123.88889 | F11: =E11/E$4-1 -> 0.081330717 | G11: =F402 -> 1340.2062 | H11: =F410 -> 0.39018088 | I11: =F420 -> 160.31659 | J11: =I11/I$4-1 -> 0.073878316
A12: HBM 代購比例 低 | B12: 代購比例取低值（k_x 重算） | C12: =E457 -> 960.82858 | D12: =E465 -> 0.43413753 | E12: =E475 -> 117.40312 | F12: =E12/E$4-1 -> 0.02472146 | G12: =F457 -> 1186.6104 | H12: =F465 -> 0.42058582 | I12: =F475 -> 153.40825 | J12: =I12/I$4-1 -> 0.027602922
A13: HBM 代購比例 高 | B13: 代購比例取高值 | C13: =E512 -> 1021.4062 | D13: =E520 -> 0.40271911 | E13: =E530 -> 111.48023 | F13: =E13/E$4-1 -> -0.026974901 | G13: =F512 -> 1322.2468 | H13: =F520 -> 0.37261832 | I13: =F530 -> 144.83252 | J13: =I13/I$4-1 -> -0.029841499
A14: ASIC 核心毛利率 35% | B14: 基準 45% | C14: =E567 -> 989.79708 | D14: =E575 -> 0.40143709 | E14: =E585 -> 105.37909 | F14: =E14/E$4-1 -> -0.08022709 | G14: =F567 -> 1251.4725 | H14: =F575 -> 0.37346206 | I14: =F585 -> 133.81891 | J14: =I14/I$4-1 -> -0.103616
A15: ASIC 核心毛利率 55% | C15: =E622 -> 989.79708 | D15: =E630 -> 0.43582946 | E15: =E640 -> 123.76244 | F15: =E15/E$4-1 -> 0.08022709 | G15: =F622 -> 1251.4725 | H15: =F630 -> 0.41923853 | I15: =F640 -> 164.75605 | J15: =I15/I$4-1 -> 0.103616
A16: 手機 情境 C 路徑 | B16: FY2027 −8%、之後 −3% | C16: =E677 -> 955.65183 | D16: =E685 -> 0.41707162 | E16: =E695 -> 107.62095 | F16: =E16/E$4-1 -> -0.060659581 | G16: =F677 -> 1199.0464 | H16: =F685 -> 0.39346499 | I16: =F695 -> 138.23736 | J16: =I16/I$4-1 -> -0.074019068
A17: 智慧邊緣 情境 C 路徑 | B17: FY2027 −3%、之後 +1% | C17: =E732 -> 955.48874 | D17: =E740 -> 0.41706389 | E17: =E750 -> 107.58776 | F17: =E17/E$4-1 -> -0.06094932 | G17: =F732 -> 1196.6103 | H17: =F740 -> 0.39332477 | I17: =F750 -> 137.719 | J17: =I17/I$4-1 -> -0.077491323
A18: 非 ASIC 毛利率 −2pt | B18: FY2027 起 | C18: =E787 -> 989.79708 | D18: =E795 -> 0.40546929 | E18: =E805 -> 107.53437 | F18: =E18/E$4-1 -> -0.061415293 | G18: =F787 -> 1251.4725 | H18: =F795 -> 0.38533603 | I18: =F805 -> 141.8437 | J18: =I18/I$4-1 -> -0.049862056
A19: 營業費用彈性 0.6 | B19: 基準 0.3 | C19: =E842 -> 989.79708 | D19: =E850 -> 0.41863328 | E19: =E860 -> 100.02388 | F19: =E19/E$4-1 -> -0.1269686 | G19: =F842 -> 1251.4725 | H19: =F850 -> 0.39635029 | I19: =F860 -> 123.05139 | J19: =I19/I$4-1 -> -0.17574207
A20: 營業費用率 +2pt | B20: 營業費用額外 +2% × 營收 | C20: =E897 -> 989.79708 | D20: =E905 -> 0.41863328 | E20: =E915 -> 103.8804 | F20: =E20/E$4-1 -> -0.093308011 | G20: =F897 -> 1251.4725 | H20: =F905 -> 0.39635029 | I20: =F915 -> 124.23263 | J20: =I20/I$4-1 -> -0.16782958
A21: 匯率 30 | B21: 基準 32（ASIC 美元營收換算） | C21: =E952 -> 968.65252 | D21: =E960 -> 0.42047054 | E21: =E970 -> 111.72722 | F21: =E21/E$4-1 -> -0.02481912 | G21: =F952 -> 1216.3306 | H21: =F960 -> 0.39868728 | I21: =F970 -> 144.65922 | J21: =I21/I$4-1 -> -0.031002371
A22: 稅率 17% | B22: 基準 14% | C22: =E1007 -> 989.79708 | D22: =E1015 -> 0.41863328 | E22: =E1025 -> 110.55221 | F22: =E22/E$4-1 -> -0.035074912 | G22: =F1007 -> 1251.4725 | H22: =F1015 -> 0.39635029 | I22: =F1025 -> 144.05787 | J22: =I22/I$4-1 -> -0.03503045
A23: 營業外 10 | B23: 基準 18 | C23: =E1062 -> 989.79708 | D23: =E1070 -> 0.41863328 | E23: =E1080 -> 110.25054 | F23: =E23/E$4-1 -> -0.037707935 | G23: =F1062 -> 1251.4725 | H23: =F1070 -> 0.39635029 | I23: =F1080 -> 144.96725 | J23: =I23/I$4-1 -> -0.028938977
A24: 情境 B | B24: CY2028 顆數 ×0.8、CY2029 ×0.85；非 ASIC 成長較低 | C24: =PL!E147 -> 962.74965 | D24: =PL!E155 -> 0.41740536 | E24: =PL!E165 -> 109.06562 | F24: =E24/E$4-1 -> -0.048050201 | G24: =PL!F147 -> 1038.9612 | H24: =PL!F155 -> 0.41793695 | I24: =PL!F165 -> 119.5203 | J24: =I24/I$4-1 -> -0.199395
A25: 情境 C | B25: CY2028–29 顆數 ×0.6；手機 −8% | C25: =PL!E202 -> 918.46572 | D25: =PL!E210 -> 0.4152388 | E25: =PL!E220 -> 100.05221 | F25: =E25/E$4-1 -> -0.12672131 | G25: =PL!F202 -> 854.34533 | H25: =PL!F210 -> 0.42934134 | I25: =PL!F220 -> 85.280435 | J25: =I25/I$4-1 -> -0.42875026
A27: 讀法：FY2027 三情境只差非 ASIC 成長率；顆數情境 B、C 的差異從 FY2028 起。TPU 份額高值受 Broadcom、Marvell 份額上限限制；第二顆 ASIC 單價 ×2 是賣方路徑的主要差異來源。
A29: 目標價參數（只改 DCF 參數；PL 收斂法的 fade_g 不隨 tp_g 變動）
A30: 案例 | B30: 設定 | C30: DCF 目標價 | D30: Comparable 目標價 | E30: 加權目標價 | F30: 相對基準
A31: 基準 | B31: r 10%、g 4%、DCF 權重 0.5 | C31: =(tp_wA*(Val!B8*(1-MIN(tp_g/tp_roe,0.8))/(1+tp_r)^1+Val!B9*(1-MIN(tp_g/tp_roe,0.8))/(1+tp_r)^2+Val!B10*(1-MIN(tp_g/tp_roe,0.8))/(1+tp_r)^3+Val!B11*(1-MIN(tp_g/tp_roe,0.8))/(1+tp_r)^4+Val!B12*(1-MIN(tp_g/tp_roe,0.8))/(1+tp_r)^5+Val!B13*(1-MIN(tp_g/tp_roe,0.8))/(1+tp_r)^6+Val!B13*(1-MIN(tp_g/tp_roe,0.8))*(1+tp_g)/(tp_r-tp_g)/(1+tp_r)^6)+tp_wB*(Val!C8*(1-MIN(tp_g/tp_roe,0.8))/(1+tp_r)^1+Val!C9*(1-MIN(tp_g/tp_roe,0.8))/(1+tp_r)^2+Val!C10*(1-MIN(tp_g/tp_roe,0.8))/(1+tp_r)^3+Val!C11*(1-MIN(tp_g/tp_roe,0.8))/(1+tp_r)^4+Val!C12*(1-MIN(tp_g/tp_roe,0.8))/(1+tp_r)^5+Val!C13*(1-MIN(tp_g/tp_roe,0.8))/(1+tp_r)^6+Val!C13*(1-MIN(tp_g/tp_roe,0.8))*(1+tp_g)/(tp_r-tp_g)/(1+tp_r)^6)+tp_wC*(Val!D8*(1-MIN(tp_g/tp_roe,0.8))/(1+tp_r)^1+Val!D9*(1-MIN(tp_g/tp_roe,0.8))/(1+tp_r)^2+Val!D10*(1-MIN(tp_g/tp_roe,0.8))/(1+tp_r)^3+Val!D11*(1-MIN(tp_g/tp_roe,0.8))/(1+tp_r)^4+Val!D12*(1-MIN(tp_g/tp_roe,0.8))/(1+tp_r)^5+Val!D13*(1-MIN(tp_g/tp_roe,0.8))/(1+tp_r)^6+Val!D13*(1-MIN(tp_g/tp_roe,0.8))*(1+tp_g)/(tp_r-tp_g)/(1+tp_r)^6))*(1+tp_r) -> 1845.5812 | D31: =Val!B35 -> 2267.8788 | E31: =tp_w_dcf*C31+(1-tp_w_dcf)*D31 -> 2056.73 | F31: =E31/E$31-1 -> 0
A32: 折現率 +1pt | B32: r 11% | C32: =(tp_wA*(Val!B8*(1-MIN(tp_g/tp_roe,0.8))/(1+(tp_r+0.01))^1+Val!B9*(1-MIN(tp_g/tp_roe,0.8))/(1+(tp_r+0.01))^2+Val!B10*(1-MIN(tp_g/tp_roe,0.8))/(1+(tp_r+0.01))^3+Val!B11*(1-MIN(tp_g/tp_roe,0.8))/(1+(tp_r+0.01))^4+Val!B12*(1-MIN(tp_g/tp_roe,0.8))/(1+(tp_r+0.01))^5+Val!B13*(1-MIN(tp_g/tp_roe,0.8))/(1+(tp_r+0.01))^6+Val!B13*(1-MIN(tp_g/tp_roe,0.8))*(1+tp_g)/((tp_r+0.01)-tp_g)/(1+(tp_r+0.01))^6)+tp_wB*(Val!C8*(1-MIN(tp_g/tp_roe,0.8))/(1+(tp_r+0.01))^1+Val!C9*(1-MIN(tp_g/tp_roe,0.8))/(1+(tp_r+0.01))^2+Val!C10*(1-MIN(tp_g/tp_roe,0.8))/(1+(tp_r+0.01))^3+Val!C11*(1-MIN(tp_g/tp_roe,0.8))/(1+(tp_r+0.01))^4+Val!C12*(1-MIN(tp_g/tp_roe,0.8))/(1+(tp_r+0.01))^5+Val!C13*(1-MIN(tp_g/tp_roe,0.8))/(1+(tp_r+0.01))^6+Val!C13*(1-MIN(tp_g/tp_roe,0.8))*(1+tp_g)/((tp_r+0.01)-tp_g)/(1+(tp_r+0.01))^6)+tp_wC*(Val!D8*(1-MIN(tp_g/tp_roe,0.8))/(1+(tp_r+0.01))^1+Val!D9*(1-MIN(tp_g/tp_roe,0.8))/(1+(tp_r+0.01))^2+Val!D10*(1-MIN(tp_g/tp_roe,0.8))/(1+(tp_r+0.01))^3+Val!D11*(1-MIN(tp_g/tp_roe,0.8))/(1+(tp_r+0.01))^4+Val!D12*(1-MIN(tp_g/tp_roe,0.8))/(1+(tp_r+0.01))^5+Val!D13*(1-MIN(tp_g/tp_roe,0.8))/(1+(tp_r+0.01))^6+Val!D13*(1-MIN(tp_g/tp_roe,0.8))*(1+tp_g)/((tp_r+0.01)-tp_g)/(1+(tp_r+0.01))^6))*(1+(tp_r+0.01)) -> 1595.1113 | D32: =Val!B35 -> 2267.8788 | E32: =tp_w_dcf*C32+(1-tp_w_dcf)*D32 -> 1931.495 | F32: =E32/E$31-1 -> -0.060890319
A33: 折現率 −1pt | B33: r 9% | C33: =(tp_wA*(Val!B8*(1-MIN(tp_g/tp_roe,0.8))/(1+(tp_r-0.01))^1+Val!B9*(1-MIN(tp_g/tp_roe,0.8))/(1+(tp_r-0.01))^2+Val!B10*(1-MIN(tp_g/tp_roe,0.8))/(1+(tp_r-0.01))^3+Val!B11*(1-MIN(tp_g/tp_roe,0.8))/(1+(tp_r-0.01))^4+Val!B12*(1-MIN(tp_g/tp_roe,0.8))/(1+(tp_r-0.01))^5+Val!B13*(1-MIN(tp_g/tp_roe,0.8))/(1+(tp_r-0.01))^6+Val!B13*(1-MIN(tp_g/tp_roe,0.8))*(1+tp_g)/((tp_r-0.01)-tp_g)/(1+(tp_r-0.01))^6)+tp_wB*(Val!C8*(1-MIN(tp_g/tp_roe,0.8))/(1+(tp_r-0.01))^1+Val!C9*(1-MIN(tp_g/tp_roe,0.8))/(1+(tp_r-0.01))^2+Val!C10*(1-MIN(tp_g/tp_roe,0.8))/(1+(tp_r-0.01))^3+Val!C11*(1-MIN(tp_g/tp_roe,0.8))/(1+(tp_r-0.01))^4+Val!C12*(1-MIN(tp_g/tp_roe,0.8))/(1+(tp_r-0.01))^5+Val!C13*(1-MIN(tp_g/tp_roe,0.8))/(1+(tp_r-0.01))^6+Val!C13*(1-MIN(tp_g/tp_roe,0.8))*(1+tp_g)/((tp_r-0.01)-tp_g)/(1+(tp_r-0.01))^6)+tp_wC*(Val!D8*(1-MIN(tp_g/tp_roe,0.8))/(1+(tp_r-0.01))^1+Val!D9*(1-MIN(tp_g/tp_roe,0.8))/(1+(tp_r-0.01))^2+Val!D10*(1-MIN(tp_g/tp_roe,0.8))/(1+(tp_r-0.01))^3+Val!D11*(1-MIN(tp_g/tp_roe,0.8))/(1+(tp_r-0.01))^4+Val!D12*(1-MIN(tp_g/tp_roe,0.8))/(1+(tp_r-0.01))^5+Val!D13*(1-MIN(tp_g/tp_roe,0.8))/(1+(tp_r-0.01))^6+Val!D13*(1-MIN(tp_g/tp_roe,0.8))*(1+tp_g)/((tp_r-0.01)-tp_g)/(1+(tp_r-0.01))^6))*(1+(tp_r-0.01)) -> 2196.1962 | D33: =Val!B35 -> 2267.8788 | E33: =tp_w_dcf*C33+(1-tp_w_dcf)*D33 -> 2232.0375 | F33: =E33/E$31-1 -> 0.085236027
A34: 長期成長 +1pt | B34: g 5% | C34: =(tp_wA*(Val!B8*(1-MIN((tp_g+0.01)/tp_roe,0.8))/(1+tp_r)^1+Val!B9*(1-MIN((tp_g+0.01)/tp_roe,0.8))/(1+tp_r)^2+Val!B10*(1-MIN((tp_g+0.01)/tp_roe,0.8))/(1+tp_r)^3+Val!B11*(1-MIN((tp_g+0.01)/tp_roe,0.8))/(1+tp_r)^4+Val!B12*(1-MIN((tp_g+0.01)/tp_roe,0.8))/(1+tp_r)^5+Val!B13*(1-MIN((tp_g+0.01)/tp_roe,0.8))/(1+tp_r)^6+Val!B13*(1-MIN((tp_g+0.01)/tp_roe,0.8))*(1+(tp_g+0.01))/(tp_r-(tp_g+0.01))/(1+tp_r)^6)+tp_wB*(Val!C8*(1-MIN((tp_g+0.01)/tp_roe,0.8))/(1+tp_r)^1+Val!C9*(1-MIN((tp_g+0.01)/tp_roe,0.8))/(1+tp_r)^2+Val!C10*(1-MIN((tp_g+0.01)/tp_roe,0.8))/(1+tp_r)^3+Val!C11*(1-MIN((tp_g+0.01)/tp_roe,0.8))/(1+tp_r)^4+Val!C12*(1-MIN((tp_g+0.01)/tp_roe,0.8))/(1+tp_r)^5+Val!C13*(1-MIN((tp_g+0.01)/tp_roe,0.8))/(1+tp_r)^6+Val!C13*(1-MIN((tp_g+0.01)/tp_roe,0.8))*(1+(tp_g+0.01))/(tp_r-(tp_g+0.01))/(1+tp_r)^6)+tp_wC*(Val!D8*(1-MIN((tp_g+0.01)/tp_roe,0.8))/(1+tp_r)^1+Val!D9*(1-MIN((tp_g+0.01)/tp_roe,0.8))/(1+tp_r)^2+Val!D10*(1-MIN((tp_g+0.01)/tp_roe,0.8))/(1+tp_r)^3+Val!D11*(1-MIN((tp_g+0.01)/tp_roe,0.8))/(1+tp_r)^4+Val!D12*(1-MIN((tp_g+0.01)/tp_roe,0.8))/(1+tp_r)^5+Val!D13*(1-MIN((tp_g+0.01)/tp_roe,0.8))/(1+tp_r)^6+Val!D13*(1-MIN((tp_g+0.01)/tp_roe,0.8))*(1+(tp_g+0.01))/(tp_r-(tp_g+0.01))/(1+tp_r)^6))*(1+tp_r) -> 2020.1419 | D34: =Val!B35 -> 2267.8788 | E34: =tp_w_dcf*C34+(1-tp_w_dcf)*D34 -> 2144.0103 | F34: =E34/E$31-1 -> 0.042436457
A35: 長期成長 −1pt | B35: g 3% | C35: =(tp_wA*(Val!B8*(1-MIN((tp_g-0.01)/tp_roe,0.8))/(1+tp_r)^1+Val!B9*(1-MIN((tp_g-0.01)/tp_roe,0.8))/(1+tp_r)^2+Val!B10*(1-MIN((tp_g-0.01)/tp_roe,0.8))/(1+tp_r)^3+Val!B11*(1-MIN((tp_g-0.01)/tp_roe,0.8))/(1+tp_r)^4+Val!B12*(1-MIN((tp_g-0.01)/tp_roe,0.8))/(1+tp_r)^5+Val!B13*(1-MIN((tp_g-0.01)/tp_roe,0.8))/(1+tp_r)^6+Val!B13*(1-MIN((tp_g-0.01)/tp_roe,0.8))*(1+(tp_g-0.01))/(tp_r-(tp_g-0.01))/(1+tp_r)^6)+tp_wB*(Val!C8*(1-MIN((tp_g-0.01)/tp_roe,0.8))/(1+tp_r)^1+Val!C9*(1-MIN((tp_g-0.01)/tp_roe,0.8))/(1+tp_r)^2+Val!C10*(1-MIN((tp_g-0.01)/tp_roe,0.8))/(1+tp_r)^3+Val!C11*(1-MIN((tp_g-0.01)/tp_roe,0.8))/(1+tp_r)^4+Val!C12*(1-MIN((tp_g-0.01)/tp_roe,0.8))/(1+tp_r)^5+Val!C13*(1-MIN((tp_g-0.01)/tp_roe,0.8))/(1+tp_r)^6+Val!C13*(1-MIN((tp_g-0.01)/tp_roe,0.8))*(1+(tp_g-0.01))/(tp_r-(tp_g-0.01))/(1+tp_r)^6)+tp_wC*(Val!D8*(1-MIN((tp_g-0.01)/tp_roe,0.8))/(1+tp_r)^1+Val!D9*(1-MIN((tp_g-0.01)/tp_roe,0.8))/(1+tp_r)^2+Val!D10*(1-MIN((tp_g-0.01)/tp_roe,0.8))/(1+tp_r)^3+Val!D11*(1-MIN((tp_g-0.01)/tp_roe,0.8))/(1+tp_r)^4+Val!D12*(1-MIN((tp_g-0.01)/tp_roe,0.8))/(1+tp_r)^5+Val!D13*(1-MIN((tp_g-0.01)/tp_roe,0.8))/(1+tp_r)^6+Val!D13*(1-MIN((tp_g-0.01)/tp_roe,0.8))*(1+(tp_g-0.01))/(tp_r-(tp_g-0.01))/(1+tp_r)^6))*(1+tp_r) -> 1727.2095 | D35: =Val!B35 -> 2267.8788 | E35: =tp_w_dcf*C35+(1-tp_w_dcf)*D35 -> 1997.5441 | F35: =E35/E$31-1 -> -0.028776688
A36: DCF 權重 0.3 | C36: =(tp_wA*(Val!B8*(1-MIN(tp_g/tp_roe,0.8))/(1+tp_r)^1+Val!B9*(1-MIN(tp_g/tp_roe,0.8))/(1+tp_r)^2+Val!B10*(1-MIN(tp_g/tp_roe,0.8))/(1+tp_r)^3+Val!B11*(1-MIN(tp_g/tp_roe,0.8))/(1+tp_r)^4+Val!B12*(1-MIN(tp_g/tp_roe,0.8))/(1+tp_r)^5+Val!B13*(1-MIN(tp_g/tp_roe,0.8))/(1+tp_r)^6+Val!B13*(1-MIN(tp_g/tp_roe,0.8))*(1+tp_g)/(tp_r-tp_g)/(1+tp_r)^6)+tp_wB*(Val!C8*(1-MIN(tp_g/tp_roe,0.8))/(1+tp_r)^1+Val!C9*(1-MIN(tp_g/tp_roe,0.8))/(1+tp_r)^2+Val!C10*(1-MIN(tp_g/tp_roe,0.8))/(1+tp_r)^3+Val!C11*(1-MIN(tp_g/tp_roe,0.8))/(1+tp_r)^4+Val!C12*(1-MIN(tp_g/tp_roe,0.8))/(1+tp_r)^5+Val!C13*(1-MIN(tp_g/tp_roe,0.8))/(1+tp_r)^6+Val!C13*(1-MIN(tp_g/tp_roe,0.8))*(1+tp_g)/(tp_r-tp_g)/(1+tp_r)^6)+tp_wC*(Val!D8*(1-MIN(tp_g/tp_roe,0.8))/(1+tp_r)^1+Val!D9*(1-MIN(tp_g/tp_roe,0.8))/(1+tp_r)^2+Val!D10*(1-MIN(tp_g/tp_roe,0.8))/(1+tp_r)^3+Val!D11*(1-MIN(tp_g/tp_roe,0.8))/(1+tp_r)^4+Val!D12*(1-MIN(tp_g/tp_roe,0.8))/(1+tp_r)^5+Val!D13*(1-MIN(tp_g/tp_roe,0.8))/(1+tp_r)^6+Val!D13*(1-MIN(tp_g/tp_roe,0.8))*(1+tp_g)/(tp_r-tp_g)/(1+tp_r)^6))*(1+tp_r) -> 1845.5812 | D36: =Val!B35 -> 2267.8788 | E36: =0.3*C36+(1-0.3)*D36 -> 2141.1895 | F36: =E36/E$31-1 -> 0.041064946
A37: DCF 權重 0.7 | C37: =(tp_wA*(Val!B8*(1-MIN(tp_g/tp_roe,0.8))/(1+tp_r)^1+Val!B9*(1-MIN(tp_g/tp_roe,0.8))/(1+tp_r)^2+Val!B10*(1-MIN(tp_g/tp_roe,0.8))/(1+tp_r)^3+Val!B11*(1-MIN(tp_g/tp_roe,0.8))/(1+tp_r)^4+Val!B12*(1-MIN(tp_g/tp_roe,0.8))/(1+tp_r)^5+Val!B13*(1-MIN(tp_g/tp_roe,0.8))/(1+tp_r)^6+Val!B13*(1-MIN(tp_g/tp_roe,0.8))*(1+tp_g)/(tp_r-tp_g)/(1+tp_r)^6)+tp_wB*(Val!C8*(1-MIN(tp_g/tp_roe,0.8))/(1+tp_r)^1+Val!C9*(1-MIN(tp_g/tp_roe,0.8))/(1+tp_r)^2+Val!C10*(1-MIN(tp_g/tp_roe,0.8))/(1+tp_r)^3+Val!C11*(1-MIN(tp_g/tp_roe,0.8))/(1+tp_r)^4+Val!C12*(1-MIN(tp_g/tp_roe,0.8))/(1+tp_r)^5+Val!C13*(1-MIN(tp_g/tp_roe,0.8))/(1+tp_r)^6+Val!C13*(1-MIN(tp_g/tp_roe,0.8))*(1+tp_g)/(tp_r-tp_g)/(1+tp_r)^6)+tp_wC*(Val!D8*(1-MIN(tp_g/tp_roe,0.8))/(1+tp_r)^1+Val!D9*(1-MIN(tp_g/tp_roe,0.8))/(1+tp_r)^2+Val!D10*(1-MIN(tp_g/tp_roe,0.8))/(1+tp_r)^3+Val!D11*(1-MIN(tp_g/tp_roe,0.8))/(1+tp_r)^4+Val!D12*(1-MIN(tp_g/tp_roe,0.8))/(1+tp_r)^5+Val!D13*(1-MIN(tp_g/tp_roe,0.8))/(1+tp_r)^6+Val!D13*(1-MIN(tp_g/tp_roe,0.8))*(1+tp_g)/(tp_r-tp_g)/(1+tp_r)^6))*(1+tp_r) -> 1845.5812 | D37: =Val!B35 -> 2267.8788 | E37: =0.7*C37+(1-0.7)*D37 -> 1972.2705 | F37: =E37/E$31-1 -> -0.041064946
A40: 案例區塊：TPU 份額 −5pt（情境 A）
A41: 項目 | B41: 單位 | C41: FY2025A | D41: FY2026（錨點） | E41: FY2027 | F41: FY2028 | G41: FY2029 | H41: FY2030（收斂） | I41: FY2031（收斂） | J41: FY2032（收斂） | K41: 說明
A42: A. AI ASIC（由下而上；D 欄＝FY2026 校準年；FY(t)＝CY(t)）
A43: Google TPU 市場顆數（含情境係數） | B43: 百萬顆 | D43: =u_tpu_26 -> 3.85 | E43: =u_tpu_27 -> 5.5 | F43: =u_tpu_28*um28_A -> 7 | G43: =u_tpu_28*(1+g29_tpu)*um29_A -> 8.05
A44: 其他 ASIC（MTIA、Maia、Ascend 等） 市場顆數（含情境係數） | B44: 百萬顆 | D44: =u_oth_26 -> 1 | E44: =u_oth_27 -> 4.5 | F44: =u_oth_28*um28_A -> 5 | G44: =u_oth_28*(1+g29_oth)*um29_A -> 5.75
A45: 聯發科份額：Google TPU | B45: % | D45: =mtk_tpu_26 -> 0.05 | E45: =MIN(1,MAX(0,mtk_tpu_27+(-0.05))) -> 0.1 | F45: =MIN(1,MAX(0,mtk_tpu_28+(-0.05))) -> 0.13 | G45: =MIN(1,MAX(0,mtk_tpu_28+(-0.05))) -> 0.13
A46: 聯發科份額：其他 ASIC（MTIA、Maia、Ascend 等） | B46: % | D46: =mtk_oth_26 -> 0 | E46: =MIN(1,MAX(0,mtk_oth_27+0)) -> 0 | F46: =MIN(1,MAX(0,mtk_oth_28+0)) -> 0 | G46: =MIN(1,MAX(0,mtk_oth_28+0)) -> 0
A47: 聯發科顆數：Google TPU | B47: 百萬顆 | D47: =D43*D45 -> 0.1925 | E47: =E43*E45*1 -> 0.55 | F47: =F43*F45*1 -> 0.91 | G47: =G43*G45*1 -> 1.0465
A48: 聯發科顆數：其他 ASIC（MTIA、Maia、Ascend 等） | B48: 百萬顆 | D48: =D44*D46 -> 0 | E48: =E44*E46*1 -> 0 | F48: =F44*F46*1 -> 0 | G48: =G44*G46*1 -> 0
A49: 每顆 HBM：Google TPU | B49: GB | D49: =gb_tpu_26 -> 192 | E49: =gb_tpu_27 -> 250 | F49: =gb_tpu_28 -> 288 | G49: =gb_tpu_28 -> 288
A50: 每顆 HBM：其他 ASIC（MTIA、Maia、Ascend 等） | B50: GB | D50: =gb_oth_26 -> 150 | E50: =gb_oth_27 -> 200 | F50: =gb_oth_28 -> 250 | G50: =gb_oth_28 -> 250
A51: HBM 單價 | B51: US$/GB | D51: =hbm_A_26 -> 14.6 | E51: =hbm_A_27 -> 26.28 | F51: =hbm_A_28 -> 28.908 | G51: =hbm_A_29 -> 27.4626
A52: 每顆核心售價：Google TPU | B52: US$K | D52: =core_tpu -> 8 | E52: =core_tpu -> 8 | F52: =core_tpu*1 -> 8 | G52: =core_tpu*1 -> 8
A53: 每顆核心售價：其他 ASIC（MTIA、Maia、Ascend 等） | B53: US$K | D53: =core_oth -> 6 | E53: =core_oth -> 6 | F53: =core_oth*1 -> 6 | G53: =core_oth*1 -> 6
A54: 每顆 HBM 金額（全部）：Google TPU | B54: US$K | D54: =D49*D51/1000 -> 2.8032 | E54: =E49*E51/1000 -> 6.57 | F54: =F49*F51/1000 -> 8.325504 | G54: =G49*G51/1000 -> 7.9092288
A55: 每顆 HBM 金額（全部）：其他 ASIC（MTIA、Maia、Ascend 等） | B55: US$K | D55: =D50*D51/1000 -> 2.19 | E55: =E50*E51/1000 -> 5.256 | F55: =F50*F51/1000 -> 7.227 | G55: =G50*G51/1000 -> 6.86565
A56: 每顆聯發科營收（核心＋代購 HBM）：Google TPU | B56: US$K | D56: =D52+f_hbm*D54 -> 9.68192 | E56: =E52+f_hbm*E54 -> 11.942 | F56: =F52+f_hbm*F54 -> 12.995302 | G56: =G52+f_hbm*G54 -> 12.745537 | K56: 核心售價 ＋ 代購比例 × HBM 金額（未乘 k_x）
A57: 每顆聯發科營收（核心＋代購 HBM）：其他 ASIC（MTIA、Maia、Ascend 等） | B57: US$K | D57: =D53+f_hbm*D55 -> 7.314 | E57: =E53+f_hbm*E55 -> 9.1536 | F57: =F53+f_hbm*F55 -> 10.3362 | G57: =G53+f_hbm*G55 -> 10.11939
A58: AI ASIC 營收（未校準） | B58: US$B | D58: =D47*D56+D48*D57 -> 1.8637696 | E58: =E47*E56+E48*E57 -> 6.5681 | F58: =F47*F56+F48*F57 -> 11.825725 | G58: =G47*G56+G48*G57 -> 13.338205
A59: ASIC 校準係數 k_x ＝ FY2026 公司資料中心營收 ÷ 未校準 | B59: x | D59: =dc26/D58 -> 1.073094 | K59: Derived：以公司 FY2026「超過 20 億美元」校準；FY2027 起沿用。顆數、份額、單價的合併係數
A60: AI ASIC 營收（美元） | B60: US$B | D60: =D58*$D$59 -> 2 | E60: =E58*$D$59 -> 7.0481888 | F60: =F58*$D$59 -> 12.690115 | G60: =G58*$D$59 -> 14.313148
A61: 匯率 | B61: NT$/US$ | D61: =fx26 -> 32 | E61: =fx -> 32 | F61: =fx -> 32 | G61: =fx -> 32
A62: AI ASIC 營收 | B62: NT$B | C62: =a25_asic -> 0 | D62: =D60*D61 -> 64 | E62: =E60*E61 -> 225.54204 | F62: =F60*F61 -> 406.08368 | G62: =G60*G61 -> 458.02073
A63: 其中代購 HBM | B63: NT$B | D63: =$D$59*f_hbm*(D47*D54+D48*D55)*D61 -> 11.117927 | E63: =$D$59*f_hbm*(E47*E54+E48*E55)*E61 -> 74.450404 | F63: =$D$59*f_hbm*(F47*F54+F48*F55)*F61 -> 156.0957 | G63: =$D$59*f_hbm*(G47*G54+G48*G55)*G61 -> 170.53455
A64: 其中核心（設計＋晶片＋封裝） | B64: NT$B | D64: =D62-D63 -> 52.882073 | E64: =E62-E63 -> 151.09164 | F64: =F62-F63 -> 249.98798 | G64: =G62-G63 -> 287.48618
A65: 聯發科 ASIC 顆數合計 | B65: 百萬顆 | D65: =D47+D48 -> 0.1925 | E65: =E47+E48 -> 0.55 | F65: =F47+F48 -> 0.91 | G65: =G47+G48 -> 1.0465
A66: 每顆聯發科 ASIC 營收（校準後） | B66: US$K | D66: =IF(D65>0,D60/D65,0) -> 10.38961 | E66: =IF(E65>0,E60/E65,0) -> 12.814889 | F66: =IF(F65>0,F60/F65,0) -> 13.945181 | G66: =IF(G65>0,G60/G65,0) -> 13.67716
A67: B. 手機、智慧邊緣平台（不含 ASIC）、電源 IC（FY2027 起簡化成長率）
A68: 手機 | B68: NT$B | C68: =a25_mob -> 315.86198 | D68: =a26_mob -> 262.65576 | E68: =D68*(1+g_mob27_A) -> 275.78855 | F68: =E68*(1+g_mobL_A) -> 286.82009 | G68: =F68*(1+g_mobL_A) -> 298.29289
A69: 智慧邊緣平台（不含 ASIC） | B69: NT$B | C69: =a25_sepx -> 247.32589 | D69: =a26_sepx -> 311.89402 | E69: =D69*(1+g_sep27_A) -> 336.84555 | F69: =E69*(1+g_sepL_A) -> 360.42473 | G69: =F69*(1+g_sepL_A) -> 385.65446
A70: 電源 IC | B70: NT$B | C70: =a25_pic -> 32.77813 | D70: =a26_pic -> 35.972154 | E70: =D70*(1+g_pic27_A) -> 38.849926 | F70: =E70*(1+g_picL_A) -> 41.95792 | G70: =F70*(1+g_picL_A) -> 45.314553
A71: 非 ASIC 合計 | B71: NT$B | C71: =C68+C69+C70 -> 595.966 | D71: =D68+D69+D70 -> 610.52194 | E71: =E68+E69+E70 -> 651.48402 | F71: =F68+F69+F70 -> 689.20274 | G71: =G68+G69+G70 -> 729.26191
A72: 營收 | B72: NT$B | C72: =C71+C62 -> 595.966 | D72: =D71+D62 -> 674.52194 | E72: =E71+E62 -> 877.02606 | F72: =F71+F62 -> 1095.2864 | G72: =G71+G62 -> 1187.2826 | H72: =G72*(1+H73) -> 1277.5105 | I72: =H72*(1+I73) -> 1364.3781 | J72: =I72*(1+J73) -> 1446.2408 | K72: FY2030 起為收斂法：營收年增由 FY2029 線性收斂到 fade_g、淨利率收斂到 fade_m（FY2032 達到），非驅動因子推導
A73: 營收年增 | B73: % | D73: =D72/C72-1 -> 0.13181278 | E73: =E72/D72-1 -> 0.30021874 | F73: =F72/E72-1 -> 0.24886417 | G73: =G72/F72-1 -> 0.08399284 | H73: =$G73+(fade_gA-$G73)*1/3 -> 0.075995227 | I73: =$G73+(fade_gA-$G73)*2/3 -> 0.067997613 | J73: =$G73+(fade_gA-$G73)*3/3 -> 0.06
A74: AI ASIC ÷ 營收 | B74: % | C74: =C62/C72 -> 0 | D74: =D62/D72 -> 0.094882014 | E74: =E62/E72 -> 0.25716686 | F74: =F62/F72 -> 0.37075569 | G74: =G62/G72 -> 0.38577228
A75: 手機 ÷ 營收 | B75: % | C75: =C68/C72 -> 0.53 | D75: =D68/D72 -> 0.38939543 | E75: =E68/E72 -> 0.31445878 | F75: =F68/F72 -> 0.26186766 | G75: =G68/G72 -> 0.25124
A76: C. 毛利與損益
A77: AI ASIC 毛利 ＝ m_core × 核心 ＋ m_hbm × 代購 HBM | B77: NT$B | D77: =m_core*D64+m_hbm*D63 -> 24.908726 | E77: =m_core*E64+m_hbm*E63 -> 75.436277 | F77: =m_core*F64+m_hbm*F63 -> 128.10416 | G77: =m_core*G64+m_hbm*G63 -> 146.42224
A78: 非 ASIC 毛利率（FY2026 殘差，之後沿用＋調整） | B78: % | C78: =a25_gp/C71 -> 0.47499354 | D78: =(a26_gp-D77)/D71 -> 0.4623407 | E78: =$D78+0 -> 0.4623407 | F78: =$D78+0 -> 0.4623407 | G78: =$D78+0 -> 0.4623407 | K78: Derived：讓 FY2026 毛利等於錨點
A79: 毛利 | B79: NT$B | C79: =a25_gp -> 283.08 | D79: =a26_gp -> 307.17787 | E79: =E78*E71+E77 -> 376.64386 | F79: =F78*F71+F77 -> 446.75064 | G79: =G78*G71+G77 -> 483.5897
A80: 毛利率 | B80: % | C80: =C79/C72 -> 0.47499354 | D80: =D79/D72 -> 0.45540086 | E80: =E79/E72 -> 0.42945572 | F80: =F79/F72 -> 0.40788476 | G80: =G79/G72 -> 0.40730799
A81: 營業費用 | B81: NT$B | C81: =a25_opx -> 179.61 | D81: =a26_opx -> 192.105 | E81: =D81*(1+MAX(g_opx_min,phi*E73))+0*E72 -> 209.40706 | F81: =E81*(1+MAX(g_opx_min,phi*F73))+0*F72 -> 225.04123 | G81: =F81*(1+MAX(g_opx_min,phi*G73))+0*G72 -> 238.5437
A82: 營業利益 | B82: NT$B | C82: =C79-C81 -> 103.47 | D82: =D79-D81 -> 115.07287 | E82: =E79-E81 -> 167.2368 | F82: =F79-F81 -> 221.70941 | G82: =G79-G81 -> 245.046
A83: 營業利益率 | B83: % | C83: =C82/C72 -> 0.17361729 | D83: =D82/D72 -> 0.17059915 | E83: =E82/E72 -> 0.19068624 | F83: =F82/F72 -> 0.2024214 | G83: =G82/G72 -> 0.2063923
A84: 營業外淨額 | B84: NT$B | C84: =a25_nonop -> 21.418 | D84: =a26_nonop -> 18.823 | E84: =nonop_f -> 18 | F84: =nonop_f -> 18 | G84: =nonop_f -> 18
A85: 稅前利益 | B85: NT$B | C85: =C82+C84 -> 124.888 | D85: =D82+D84 -> 133.89587 | E85: =E82+E84 -> 185.2368 | F85: =F82+F84 -> 239.70941 | G85: =G82+G84 -> 263.046
A86: 所得稅 | B86: NT$B | C86: =a25_tax -> 18.77 | D86: =a26_tax -> 16.258933 | E86: =E85*tax -> 25.933152 | F86: =F85*tax -> 33.559318 | G86: =G85*tax -> 36.82644
A87: 非控制權益 | B87: NT$B | C87: =a25_nci -> 0.798 | D87: =a26_nci -> 0.992 | E87: =nci -> 1 | F87: =nci -> 1 | G87: =nci -> 1
A88: 歸屬母公司淨利 | B88: NT$B | C88: =C85-C86-C87 -> 105.32 | D88: =D85-D86-D87 -> 116.64494 | E88: =E85-E86-E87 -> 158.30365 | F88: =F85-F86-F87 -> 205.1501 | G88: =G85-G86-G87 -> 225.21956 | H88: =H72*H92 -> 243.78654 | I88: =I72*I92 -> 261.91351 | J88: =J72*J92 -> 279.27138
A89: 加權股數 | B89: 十億股 | C89: =a25_sh -> 1.5918833 | D89: =a26_sh -> 1.5925089 | E89: =D89*(1+sh_g) -> 1.5925089 | F89: =E89*(1+sh_g) -> 1.5925089 | G89: =F89*(1+sh_g) -> 1.5925089 | H89: =G89*(1+sh_g) -> 1.5925089 | I89: =H89*(1+sh_g) -> 1.5925089 | J89: =I89*(1+sh_g) -> 1.5925089
A90: EPS（基本） | B90: NT$ | C90: =C88/C89 -> 66.160628 | D90: =D88/D89 -> 73.246018 | E90: =E88/E89 -> 99.405189 | F90: =F88/F89 -> 128.82195 | G90: =G88/G89 -> 141.42436 | H90: =H88/H89 -> 153.08331 | I90: =I88/I89 -> 164.46596 | J90: =J88/J89 -> 175.36567
A91: EPS 年增 | B91: % | D91: =D90/C90-1 -> 0.10709374 | E91: =E90/D90-1 -> 0.35714122 | F91: =F90/E90-1 -> 0.29592777 | G91: =G90/F90-1 -> 0.09782819 | H91: =H90/G90-1 -> 0.082439484 | I91: =I90/H90-1 -> 0.074355892 | J91: =J90/I90-1 -> 0.066273317
A92: 淨利率（歸屬母公司淨利 ÷ 營收） | B92: % | C92: =C88/C72 -> 0.17672149 | D92: =D88/D72 -> 0.17292979 | E92: =E88/E72 -> 0.18050051 | F92: =F88/F72 -> 0.18730269 | G92: =G88/G72 -> 0.1896933 | H92: =$G92+(fade_mA-$G92)*1/3 -> 0.19082939 | I92: =$G92+(fade_mA-$G92)*2/3 -> 0.19196549 | J92: =$G92+(fade_mA-$G92)*3/3 -> 0.19310158
A95: 案例區塊：TPU 份額取高值（上限）（情境 A）
A96: 項目 | B96: 單位 | C96: FY2025A | D96: FY2026（錨點） | E96: FY2027 | F96: FY2028 | G96: FY2029 | H96: FY2030（收斂） | I96: FY2031（收斂） | J96: FY2032（收斂） | K96: 說明
A97: A. AI ASIC（由下而上；D 欄＝FY2026 校準年；FY(t)＝CY(t)）
A98: Google TPU 市場顆數（含情境係數） | B98: 百萬顆 | D98: =u_tpu_26 -> 3.85 | E98: =u_tpu_27 -> 5.5 | F98: =u_tpu_28*um28_A -> 7 | G98: =u_tpu_28*(1+g29_tpu)*um29_A -> 8.05
A99: 其他 ASIC（MTIA、Maia、Ascend 等） 市場顆數（含情境係數） | B99: 百萬顆 | D99: =u_oth_26 -> 1 | E99: =u_oth_27 -> 4.5 | F99: =u_oth_28*um28_A -> 5 | G99: =u_oth_28*(1+g29_oth)*um29_A -> 5.75
A100: 聯發科份額：Google TPU | B100: % | D100: =mtk_tpu_26 -> 0.05 | E100: =MIN(1,MAX(0,mtk_tpu_27_hi+0)) -> 0.2 | F100: =MIN(1,MAX(0,mtk_tpu_28_hi+0)) -> 0.2 | G100: =MIN(1,MAX(0,mtk_tpu_28_hi+0)) -> 0.2
A101: 聯發科份額：其他 ASIC（MTIA、Maia、Ascend 等） | B101: % | D101: =mtk_oth_26 -> 0 | E101: =MIN(1,MAX(0,mtk_oth_27+0)) -> 0 | F101: =MIN(1,MAX(0,mtk_oth_28+0)) -> 0 | G101: =MIN(1,MAX(0,mtk_oth_28+0)) -> 0
A102: 聯發科顆數：Google TPU | B102: 百萬顆 | D102: =D98*D100 -> 0.1925 | E102: =E98*E100*1 -> 1.1 | F102: =F98*F100*1 -> 1.4 | G102: =G98*G100*1 -> 1.61
A103: 聯發科顆數：其他 ASIC（MTIA、Maia、Ascend 等） | B103: 百萬顆 | D103: =D99*D101 -> 0 | E103: =E99*E101*1 -> 0 | F103: =F99*F101*1 -> 0 | G103: =G99*G101*1 -> 0
A104: 每顆 HBM：Google TPU | B104: GB | D104: =gb_tpu_26 -> 192 | E104: =gb_tpu_27 -> 250 | F104: =gb_tpu_28 -> 288 | G104: =gb_tpu_28 -> 288
A105: 每顆 HBM：其他 ASIC（MTIA、Maia、Ascend 等） | B105: GB | D105: =gb_oth_26 -> 150 | E105: =gb_oth_27 -> 200 | F105: =gb_oth_28 -> 250 | G105: =gb_oth_28 -> 250
A106: HBM 單價 | B106: US$/GB | D106: =hbm_A_26 -> 14.6 | E106: =hbm_A_27 -> 26.28 | F106: =hbm_A_28 -> 28.908 | G106: =hbm_A_29 -> 27.4626
A107: 每顆核心售價：Google TPU | B107: US$K | D107: =core_tpu -> 8 | E107: =core_tpu -> 8 | F107: =core_tpu*1 -> 8 | G107: =core_tpu*1 -> 8
...

Sheet Sources
A1: 來源（公司原文＝聯發科法說資料；券商、資料商、媒體皆為 Interested-party）
A2: 公司：2Q26 營運報告（1Q26、2Q26 損益表、資產負債） | B2: https://www.mediatek.com/hubfs/MediaTek%20Assets/Pdfs/Quarterly%20Earnings%20Release/2026/Quarterly%20Earnings%20Release-2026Q2/%5B%E6%B3%95%E8%AA%AA%E6%9C%83%E8%B3%87%E6%96%99%5DQ2%E7%87%9F%E9%81%8B%E5%A0%B1%E5%91%8A.pdf
A3: 公司：2Q26 法說講稿（3Q26 指引、資料中心超過 20 億美元、SAM 800 億美元、份額 15–20%、第二顆 ASIC 2028） | B3: https://www.mediatek.com/hubfs/MediaTek%20Assets/Pdfs/Quarterly%20Earnings%20Release/2026/Quarterly%20Earnings%20Release-2026Q2/Prepared%20remarks.pdf
A4: 公司：1Q26 法說逐字稿（ASIC 數十億美元、SAM 700–800 億美元、份額 10–15%） | B4: https://www.mediatek.com/hubfs/MediaTek%20Assets/Pdfs/Quarterly%20Earnings%20Release/2026/Quarterly%20Earnings%20Release-2026Q1/%E8%AA%AA%E6%98%8E%E6%9C%83%E9%80%90%E5%AD%97%E7%A8%BF.pdf
A5: 公司：4Q25 營運報告（FY2025、4Q25、3Q25 損益表） | B5: https://www.mediatek.com/hubfs/MediaTek%20Assets/Pdfs/Quarterly%20Earnings%20Release/2025/Quarterly%20Earnings%20Release-2025Q4/%5B%E6%B3%95%E8%AA%AA%E6%9C%83%E8%B3%87%E6%96%99%5DQ4%E7%87%9F%E9%81%8B%E5%A0%B1%E5%91%8A.pdf
A6: 公司：4Q25 法說逐字稿（FY2025 美元營收 191 億、資料中心 2026 超過 10 億美元、2027 占營收 20%） | B6: https://www.mediatek.com/hubfs/MediaTek%20Assets/Pdfs/Quarterly%20Earnings%20Release/2025/Quarterly%20Earnings%20Release-2025Q4/%E8%AA%AA%E6%98%8E%E6%9C%83%E9%80%90%E5%AD%97%E7%A8%BF.pdf
A7: 媒體：科技新報（9 月營收、前 9 月累計） | B7: https://finance.technews.tw/2026/10/08/mtk-2454-202609-financial-report/
A8: 媒體：財報狗（3Q26 營收 1,680.58 億、4Q 展望） | B8: https://statementdog.com/news/17861
A9: 媒體：風傳媒（2Q26 法說摘要） | B9: https://www.storm.mg/article/11153222
A10: 券商：凱基 2026-07-23（FY2026–28 預估、v8x／v9／v10 TPU、FY2028 ASIC 500 億美元、目標價 6,150） | B10: https://www.kgi.com.hk/zh-cn/-/media/files/kgishk/research-reports/tw-reports/mediatek-2454-tt_20260723_en.pdf
A11: 媒體：經濟日報 2026-08-03（高盛、Citi 目標價與 EPS、ASIC 2026–28） | B11: https://udn.com/news/story/7252/9668107
A12: 媒體：經濟日報 2026-05-03（高盛 EPS、ASIC 單價數倍、25x P/E） | B12: https://money.udn.com/money/amp/story/5607/9479348
A13: 資料商：stockanalysis（現價 10-22、近 12 月與前瞻 P/E、ROE、FY2021–25 財務） | B13: https://stockanalysis.com/quote/tpe/2454/
... A23: SemiAnalysis | B23: 未使用
