Workbook

Sheet README
A1: Anthropic 收支模型 v0.1.3（v0.1.3-B；2026-10-22）
A2: 命題（與 OpenAI v0.6 同一句）：Anthropic 每 VR 等值 GW 的年營收能否覆蓋每 GW 年全成本；若不能，缺口要多少外部資金、由誰以什麼條件提供。FY2025–FY2030，曆年制，2025 為實際校準年。
A4: 本版範圍 | B4: v0.1.3-B：SRC_ANT、TK_Link（含 NonNV 讀表）、OAI_Link、Inputs、Demand（需求與 token 量）、Revenue（訂閱方案別、API 層級別、通路分成、淨額、容量上限）、Compute（加速器族、逐合約供給 GW、η、推論與研發 GW、容量上限、VR 等值）、Cost（逐合約實付、自建資本支出、供應商持有成本、非算力成本、股權報酬、命題表；A4 補逐家對帳與敏感度）、Bridge（逐層對照，唯讀）、EtaDiag（η 診斷，唯讀）、Funding（命題 2）、Reverse（管理層目標反解，只作對照）、Checks。
A5: v0.1.3 A 段更新 | B5: 採納外部驗收報告（v0.1.2）：①TK 快照改 v19.0（103 個值與 v18.0 相同）；②U2 新法（Inputs u2_method）：Nscale、Lambda 供給 GW 取揭露 MW（460／350），付款路徑不變（『最高 86』按 MW 比例分攤的年付款，Cost 第二十二節；隱含每 GW 年付款對照列）；③資金三層（Funding 第十節：①營運自由現金流自給、②加已到位股權＝基準、③再加條件式）；④持續擴張情境（Cost 第二十三節、Funding 第十一節；只作情境，基準不追加）；⑤HTML 結論改條件式。新列皆附加在頁尾，既有列編號不變。
A6: v0.1.3 B 段更新 | B6: ①Bridge 頁（Cost 之後；唯讀）：需求 → token → GW → 成本逐層對照（公式來源、單位、2025–2030、2030 敏感度包絡、標記），最後一節與 Tokenomics 同口徑量對照；②EtaDiag 頁（唯讀）：η（2025）拆成計價口徑 × 利用率 × 工作負載組合 × 未解釋殘差（只作診斷，η 的值不變），並列 TK L1_Gap*（OpenAI 口徑，Analogy）；③TK_Link 尾端新增 22 個對照名稱（IF_UtilActual、L1_TokGW_PaidCap_VR200、L1_Gap* 各含低／高）；④公開 S-1 或經審計資料出現時的替換程序見 CLAUDE.md 第 8 節。兩頁不被任何計算頁引用（Checks e1_iso）。
A7: v0.1.2 更新 | B7: Tokenomics 快照 v5.26 → v18.0（master 868e2cc）：TK_Link 以同一份名稱清單重讀；公式不變。η（2025 校準）吸收 IF_TokGW_* 的整體上升；TK 值變動的名稱逐一在報告「語意核對」列出；Cost 第二十節、Checks 尾端加 L1_RevGW_PQ_VR200 對照列（只對照，不回饋計算）。
A8: v0.1.1 更新 | B8: 依 WSJ 轉述的草擬 S-1（2026-10-20）與 Q3 投資人簡報（2026-10-14）：新增 SRC_ANT_380–409；U1 2026 營收基準＝上半年實際＋Q3 實際＋Q4（Q3 持平）；U2 Nscale＋Lambda 兩約合計錨定『最高 86』；U3 逐家與三口徑承諾對照；U4 2026 算力支出對照（不校準）；U5 D22 加 Q3 11%；U6 談判中 $150B 情境（Cost 第十九節、Funding S8）；U7 上半年非現金費用列示。Inputs 回歸開關 u1_switch、u2_switch＝0 可還原 v0.1。
A9: Compute | B9: 加速器族 × 世代（NVIDIA Hopper／GB200／GB300／VR200；TPU v6e／v7；Trainium2／3；AMD MI455X）每 GW 年產能＝TK IF_TokGW_* ×（NonNV 產出比）；供給 GW 只由算力合約加總（D10 r1；機房租約只列對照）；η＝2025 token 換算推論 GW ÷ 2025 推論支出換算 GW（D8）；研發 GW＝供給 ×（1 − 閒置）− 推論（D12）；容量上限 2025、2026 固定 1；VR 等值＝各族 Sol 產能比。
A10: Cost | B10: 算力成本（現金）＝逐合約實付＋自建資本支出（D10、D11）；供應商持有成本＝GW × TK IF_HoldEcon × 持有比、雲端毛利；非算力成本 2025＝說明書營業費用 − 算力 − 平台抽成（D13、D5 r1），之後人數 × 每人成本；股權報酬單列；命題表：每 VR 等值 GW 營收淨額、算力、非算力、全成本（含／不含股權報酬）、差額、覆蓋率。
A11: Funding | B11: 自由現金流＝營收淨額（截頂後）− 算力成本（現金）− 非算力成本（不含股權報酬）；來源順序（D16 r1）：2025 年底現金 → 2026 已交割股權（Series G 30、Amazon G 5、Series H 65）→ 外部資金（補足至最低現金＝次年非算力 6 個月，D17）；條件式（Amazon 15、Google 30、NVIDIA 10、AMD 5）與 IPO 約 100 只列情境；或有負債只列示；情境 S1–S7（IPO、條件式、逐家錨定招股書、機房租金、D22、合併）；回流對照（D18）。
A12: Reverse | B12: 管理層營收目標（2026 18、2027 55、2028 70、2029 148；2030 無目標取正向）→ 只靠 API／只靠訂閱／兩線等比例的所需倍數 → 反向資金（同一支出）；只被 Checks 引用（D19）。
A13: Excel 為唯一計算引擎 | B13: 藍字＝輸入（Excel 擁有，重建時保留已改過的值）；黑字＝公式；綠字＝跨頁連結。builder 只產生結構（data/*.yaml → SRC_ANT／Inputs；Tokenomics → TK_Link；OpenAI → OAI_Link）。
A14: SRC_ANT | B14: 409 列：公司財務原始數據（A1 蒐集 376 列＋A2 新增 3 列供 Derived 列公式化＋v0.1.1 新增 30 列〔草擬 S-1 經 WSJ 轉述、Q3 投資人簡報〕）。標記 Derived 的 14 列：13 列改為公式、1 列（Reuters 自行計算後公布的通路費）保留報導值。
A15: TK_Link | B15: Tokenomics v19.0（20261022_Tokenomics_v19.0.xlsx），master 提交 1916a06；104 個具名範圍（OpenAI v0.6 同一組 63 名＋A2 新增任務 token 5 名＋v0.1.2 新增 v18.0 對照名稱 14 個，只對照）＋ 讀表（非具名）21 格：NonNV 18 格（規格 D6）與 PUE 3 格（A3；Tokenomics Inputs 頁）。
... A23: 分層 | B23: 公司財務原始數據→SRC_ANT；AI 技術與算力→TK_Link（取自 Tokenomics）；假設→Inputs；OpenAI 對照→OAI_Link（不進計算）。

Sheet SRC_ANT
A1: SRC_ANT — 第 0 層 Source：Anthropic 公司財務原始數據（營收、價格、用戶、合約、成本、融資、管理層目標）
A2: 只存已取得的原始訊息（非計算、非假設）。藍字＝原始值，由本活頁簿擁有。標記 Derived 的列：值欄改為公式（由其他 SRC_ANT 列推得），處理狀態欄說明；AI 技術與算力原始數據不在此登錄（取自 TK_Link）。
A3: 來源等級（1 一手／2 二手已讀或轉載／未評）、立場、立場說明、一手／二手：依 builder/source_rules.py 的機械規則由 CC 初評（AB 欄）；利害方與誘因欄為 A1 逐列登錄。
A4: SRC_ID | B4: key | C4: 分組 | D4: 項目 | E4: 值 | F4: 低 | G4: 高 | H4: 單位 | I4: 期間 | J4: 日期（序列值） | K4: 口徑 | L4: 來源 | M4: 網址 | N4: 文件日期 | O4: 擷取日 | P4: 標記 | Q4: 利害方與誘因 | R4: 來源等級 | S4: 立場 | T4: 立場說明 | U4: 一手／二手 | V4: 處理狀態 | W4: 備註 | X4: 缺值（公式） | Y4: 缺出處（公式） | Z4: 區間順序異常（公式） | AA4: Derived 未處理（公式） | AB4: 四欄標註
A5: SRC_ANT_001 | B5: rev_2025_recognized | C5: A | D5: 2025 年認列營收 | E5: 4.6 | H5: $B/年 | I5: 2025 | K5: 總額 | L5: Reuters〈Anthropic's IPO prospectus shows sweeping AI vision, surging costs〉（經 Fortune 轉述） | M5: https://fortune.com/2026/09/29/anthropic-leaked-ipo-prospectus-losses-growth-ai-end-humanity/ | N5: 2026-09-29 | O5: 2026-10-08 | P5: Interested-party | Q5: Anthropic（外流機密招股書草稿；IPO 募資誘因） | R5: 2 | S5: 利害關係方 | T5: Anthropic（外流機密招股書草稿；IPO 募資誘因） | U5: 二手 | V5: 觀測 | W5: 原文：'bringing in $4.6 billion in revenue'；'Revenue rose 1,088% in 2025'。雲端市集銷售以總額認列（見 rev_recognition_gross） | X5: =IF(AND(COUNT($E5:$G5)=0,LEFT($H5,2)<>"定性",LEFT($H5,2)<>"文字",LEFT($H5,2)<>"日期"),1,0) -> 0 | Y5: =IF(OR($L5="",$M5=""),1,0) -> 0 | Z5: =IF(AND(ISNUMBER($E5),ISNUMBER($F5)),IF($F5>$E5,1,0),0)+IF(AND(ISNUMBER($E5),ISNUMBER($G5)),IF($E5>$G5,1,0),0)+IF(AND(ISNUMBER($F5),ISNUMBER($G5)),IF($F5>$G5,1,0),0) -> 0 | AA5: =IF(AND($P5="Derived",$V5="觀測"),1,0) -> 0 | AB5: CC 初評
A6: SRC_ANT_002 | B6: rev_2025_recognized_b | C6: A | D6: 2025 年認列營收 | E6: 4.59 | H6: $B/年 | I6: 2025 | K6: 總額 | L6: KuCoin 快訊〈Anthropic fiscal year 2025 revenue surges 1,088% to $4.59 billion〉 | M6: https://www.kucoin.com/news/flash/anthropic-2025-fiscal-year-revenue-surges-1088-to-4-59-billion | N6: 2026-09-29 | O6: 2026-10-08 | P6: Interested-party | Q6: Anthropic（外流招股書；IPO 募資誘因） | R6: 2 | S6: 利害關係方 | T6: Anthropic（外流招股書；IPO 募資誘因） | U6: 二手 | V6: 觀測 | W6: 標題：'revenue surges 1,088% to $4.59 billion'。與 4.6（Reuters 'nearly $4.6 billion'）一致，為更精確值；僅見標題 | X6: =IF(AND(COUNT($E6:$G6)=0,LEFT($H6,2)<>"定性",LEFT($H6,2)<>"文字",LEFT($H6,2)<>"日期"),1,0) -> 0 | Y6: =IF(OR($L6="",$M6=""),1,0) -> 0 | Z6: =IF(AND(ISNUMBER($E6),ISNUMBER($F6)),IF($F6>$E6,1,0),0)+IF(AND(ISNUMBER($E6),ISNUMBER($G6)),IF($E6>$G6,1,0),0)+IF(AND(ISNUMBER($F6),ISNUMBER($G6)),IF($F6>$G6,1,0),0) -> 0 | AA6: =IF(AND($P6="Derived",$V6="觀測"),1,0) -> 0 | AB6: CC 初評
A7: SRC_ANT_003 | B7: rev_2024_recognized_derived | C7: A | D7: 2024 年認列營收（由 2025 年成長率反推） | E7: =SRC_ANT_002/(1+SRC_ANT_377) -> 0.38636364 | H7: $B/年 | I7: 2024 | K7: 總額 | L7: 由 rev_2025_recognized（$4.59B、+1,088%）推算 | M7: https://www.kucoin.com/news/flash/anthropic-2025-fiscal-year-revenue-surges-1088-to-4-59-billion | N7: 2026-09-29 | O7: 2026-10-08 | P7: Derived | R7: 未評 | S7: 推導 | T7: 由其他 SRC_ANT 列推得（本活頁簿以公式表示） | U7: 推導 | V7: Derived→公式 | W7: 4.59/(1+10.88)=0.386。報導未直接給 2024 營收數字；Reuters 稱 2025 年 '12-fold'，4.6/12≈0.38 一致 | X7: =IF(AND(COUNT($E7:$G7)=0,LEFT($H7,2)<>"定性",LEFT($H7,2)<>"文字",LEFT($H7,2)<>"日期"),1,0) -> 0 | Y7: =IF(OR($L7="",$M7=""),1,0) -> 0 | Z7: =IF(AND(ISNUMBER($E7),ISNUMBER($F7)),IF($F7>$E7,1,0),0)+IF(AND(ISNUMBER($E7),ISNUMBER($G7)),IF($E7>$G7,1,0),0)+IF(AND(ISNUMBER($F7),ISNUMBER($G7)),IF($F7>$G7,1,0),0) -> 0 | AA7: =IF(AND($P7="Derived",$V7="觀測"),1,0) -> 0 | AB7: CC 初評
A8: SRC_ANT_004 | B8: rev_2026_q1 | C8: A | D8: 2026 Q1 認列營收 | E8: 4.73 | H8: $B/季 | I8: 2026-Q1 | K8: 總額 | L8: Bloomberg（經 Axios 轉述）〈Anthropic's revenue run rate reportedly surpasses $65 billion pre-IPO〉 | M8: https://www.axios.com/2026/08/17/anthropic-revenue-run-rate-ipo-openai | N8: 2026-08-17 | O8: 2026-10-08 | P8: Interested-party | Q8: Anthropic（Bloomberg 取得之內部文件；IPO 前募資誘因） | R8: 2 | S8: 利害關係方 | T8: Anthropic（Bloomberg 取得之內部文件；IPO 前募資誘因） | U8: 二手 | V8: 觀測 | W8: 原文：'more than double Q1 revenue of $4.73 billion'。招股書外流（Fortune 9/29）亦引同值 | X8: =IF(AND(COUNT($E8:$G8)=0,LEFT($H8,2)<>"定性",LEFT($H8,2)<>"文字",LEFT($H8,2)<>"日期"),1,0) -> 0 | Y8: =IF(OR($L8="",$M8=""),1,0) -> 0 | Z8: =IF(AND(ISNUMBER($E8),ISNUMBER($F8)),IF($F8>$E8,1,0),0)+IF(AND(ISNUMBER($E8),ISNUMBER($G8)),IF($E8>$G8,1,0),0)+IF(AND(ISNUMBER($F8),ISNUMBER($G8)),IF($F8>$G8,1,0),0) -> 0 | AA8: =IF(AND($P8="Derived",$V8="觀測"),1,0) -> 0 | AB8: CC 初評
A9: SRC_ANT_005 | B9: rev_2026_q2 | C9: A | D9: 2026 Q2 認列營收（初步） | E9: 11.5 | H9: $B/季 | I9: 2026-Q2 | K9: 總額 | L9: Bloomberg（經 Axios 轉述） | M9: https://www.axios.com/2026/08/17/anthropic-revenue-run-rate-ipo-openai | N9: 2026-08-17 | O9: 2026-10-08 | P9: Interested-party | Q9: Anthropic（Bloomberg 取得之文件；IPO 前誘因） | R9: 2 | S9: 利害關係方 | T9: Anthropic（Bloomberg 取得之文件；IPO 前誘因） | U9: 二手 | V9: 觀測 | W9: 原文：'more than $11.5 billion in preliminary revenue in the second quarter'；'more than 14 times' 去年同季；初步數字可能修正 | X9: =IF(AND(COUNT($E9:$G9)=0,LEFT($H9,2)<>"定性",LEFT($H9,2)<>"文字",LEFT($H9,2)<>"日期"),1,0) -> 0 | Y9: =IF(OR($L9="",$M9=""),1,0) -> 0 | Z9: =IF(AND(ISNUMBER($E9),ISNUMBER($F9)),IF($F9>$E9,1,0),0)+IF(AND(ISNUMBER($E9),ISNUMBER($G9)),IF($E9>$G9,1,0),0)+IF(AND(ISNUMBER($F9),ISNUMBER($G9)),IF($F9>$G9,1,0),0) -> 0 | AA9: =IF(AND($P9="Derived",$V9="觀測"),1,0) -> 0 | AB9: CC 初評
A10: SRC_ANT_006 | B10: rev_2025_q2 | C10: A | D10: 2025 Q2 認列營收 | E10: 0.787 | H10: $B/季 | I10: 2025-Q2 | K10: 總額 | L10: The Next Web〈Anthropic's quarterly revenue passed $11.5bn, up more than 14-fold〉（引 Bloomberg 2026-08-14） | M10: https://thenextweb.com/news/anthropic-q2-2026-revenue-11-5-billion-operating-income | N10: 2026-08-15 | O10: 2026-10-08 | P10: Interested-party | Q10: Anthropic（Bloomberg 取得之文件） | R10: 2 | S10: 利害關係方 | T10: Anthropic（Bloomberg 取得之文件） | U10: 二手 | V10: 觀測 | W10: 原文：去年同季 '$787mn'；Q2 2026 'exceeded $11.5bn'；'positive adjusted operating income' | X10: =IF(AND(COUNT($E10:$G10)=0,LEFT($H10,2)<>"定性",LEFT($H10,2)<>"文字",LEFT($H10,2)<>"日期"),1,0) -> 0 | Y10: =IF(OR($L10="",$M10=""),1,0) -> 0 | Z10: =IF(AND(ISNUMBER($E10),ISNUMBER($F10)),IF($F10>$E10,1,0),0)+IF(AND(ISNUMBER($E10),ISNUMBER($G10)),IF($E10>$G10,1,0),0)+IF(AND(ISNUMBER($F10),ISNUMBER($G10)),IF($F10>$G10,1,0),0) -> 0 | AA10: =IF(AND($P10="Derived",$V10="觀測"),1,0) -> 0 | AB10: CC 初評
A11: SRC_ANT_007 | B11: rev_2026_h1_derived | C11: A | D11: 2026 上半年認列營收（Q1+Q2 加總） | E11: =SRC_ANT_004+SRC_ANT_005 -> 16.23 | H11: $B/半年 | I11: 2026-H1 | K11: 總額 | L11: 由 rev_2026_q1 + rev_2026_q2 推算 | M11: https://www.pymnts.com/news/artificial-intelligence/2026/anthropic-prospectus-shows-what-2-trillion-dollar-ai-company-costs-run/ | N11: 2026-09-29 | O11: 2026-10-08 | P11: Derived | R11: 未評 | S11: 推導 | T11: 由其他 SRC_ANT 列推得（本活頁簿以公式表示） | U11: 推導 | V11: Derived→公式 | W11: 4.73+11.5≈16.2；PYMNTS 列 '$4.73 billion in Q1 2026 and $11.5 billion in Q2 2026'，未直接給 H1 合計 | X11: =IF(AND(COUNT($E11:$G11)=0,LEFT($H11,2)<>"定性",LEFT($H11,2)<>"文字",LEFT($H11,2)<>"日期"),1,0) -> 0 | Y11: =IF(OR($L11="",$M11=""),1,0) -> 0 | Z11: =IF(AND(ISNUMBER($E11),ISNUMBER($F11)),IF($F11>$E11,1,0),0)+IF(AND(ISNUMBER($E11),ISNUMBER($G11)),IF($E11>$G11,1,0),0)+IF(AND(ISNUMBER($F11),ISNUMBER($G11)),IF($F11>$G11,1,0),0) -> 0 | AA11: =IF(AND($P11="Derived",$V11="觀測"),1,0) -> 0 | AB11: CC 初評
A12: SRC_ANT_008 | B12: rev_runrate_2024_12 | C12: A | D12: 年化營收（run-rate） | E12: 1 | H12: $B/年 | I12: 2024-12 | K12: 未明 | L12: Anthropic 新聞稿〈Anthropic raises Series F at US$183B post-money valuation〉 | M12: https://www.anthropic.com/news/anthropic-raises-series-f-at-usd183b-post-money-valuation | N12: 2025-09-02 | O12: 2026-10-08 | P12: Interested-party | Q12: Anthropic（募資誘因） | R12: 1 | S12: 利害關係方 | T12: Anthropic（募資誘因） | U12: 一手 | V12: 觀測 | W12: 原文：2025 年初 'run-rate revenue had grown to approximately $1 billion' | X12: =IF(AND(COUNT($E12:$G12)=0,LEFT($H12,2)<>"定性",LEFT($H12,2)<>"文字",LEFT($H12,2)<>"日期"),1,0) -> 0 | Y12: =IF(OR($L12="",$M12=""),1,0) -> 0 | Z12: =IF(AND(ISNUMBER($E12),ISNUMBER($F12)),IF($F12>$E12,1,0),0)+IF(AND(ISNUMBER($E12),ISNUMBER($G12)),IF($E12>$G12,1,0),0)+IF(AND(ISNUMBER($F12),ISNUMBER($G12)),IF($F12>$G12,1,0),0) -> 0 | AA12: =IF(AND($P12="Derived",$V12="觀測"),1,0) -> 0 | AB12: CC 初評
A13: SRC_ANT_009 | B13: rev_runrate_2024_12_b | C13: A | D13: 年化營收（run-rate） | E13: 1 | H13: $B/年 | I13: 2024-12 | K13: 未明 | L13: Reuters 獨家（2025-05-30，經 WizCase 轉述） | M13: https://www.wizcase.com/?p=2882381 | N13: 2025-06-03 | O13: 2026-10-08 | P13: Interested-party | Q13: Anthropic（知情人士；募資誘因） | R13: 2 | S13: 利害關係方 | T13: Anthropic（知情人士；募資誘因） | U13: 二手 | V13: 觀測 | W13: 原文：'around $1 billion in December 2024' | X13: =IF(AND(COUNT($E13:$G13)=0,LEFT($H13,2)<>"定性",LEFT($H13,2)<>"文字",LEFT($H13,2)<>"日期"),1,0) -> 0 | Y13: =IF(OR($L13="",$M13=""),1,0) -> 0 | Z13: =IF(AND(ISNUMBER($E13),ISNUMBER($F13)),IF($F13>$E13,1,0),0)+IF(AND(ISNUMBER($E13),ISNUMBER($G13)),IF($E13>$G13,1,0),0)+IF(AND(ISNUMBER($F13),ISNUMBER($G13)),IF($F13>$G13,1,0),0) -> 0 | AA13: =IF(AND($P13="Derived",$V13="觀測"),1,0) -> 0 | AB13: CC 初評
A14: SRC_ANT_010 | B14: rev_runrate_2025_03_early | C14: A | D14: 年化營收（run-rate） | E14: 1.4 | H14: $B/年 | I14: 2025-03（月初） | K14: 未明 | L14: The Information（經 Seeking Alpha 轉述） | M14: https://seekingalpha.com/news/4419473-anthropic-reaches-1_4b-in-annualized-revenue-report | N14: 2025-03-11 | O14: 2026-10-08 | P14: Interested-party | Q14: Anthropic（知情人士；募資誘因） | R14: 2 | S14: 利害關係方 | T14: Anthropic（知情人士；募資誘因） | U14: 二手 | V14: 觀測 | W14: 原文：'an annualized revenue of $1.4B as of earlier this month'；'around $1B at the end of 2024' | X14: =IF(AND(COUNT($E14:$G14)=0,LEFT($H14,2)<>"定性",LEFT($H14,2)<>"文字",LEFT($H14,2)<>"日期"),1,0) -> 0 | Y14: =IF(OR($L14="",$M14=""),1,0) -> 0 | Z14: =IF(AND(ISNUMBER($E14),ISNUMBER($F14)),IF($F14>$E14,1,0),0)+IF(AND(ISNUMBER($E14),ISNUMBER($G14)),IF($E14>$G14,1,0),0)+IF(AND(ISNUMBER($F14),ISNUMBER($G14)),IF($F14>$G14,1,0),0) -> 0 | AA14: =IF(AND($P14="Derived",$V14="觀測"),1,0) -> 0 | AB14: CC 初評
A15: SRC_ANT_011 | B15: rev_runrate_2025_03 | C15: A | D15: 年化營收（run-rate） | E15: 2 | H15: $B/年 | I15: 2025-03（月底） | K15: 未明 | L15: Reuters 獨家（2025-05-30，經 WizCase 轉述） | M15: https://www.wizcase.com/?p=2882381 | N15: 2025-06-03 | O15: 2026-10-08 | P15: Interested-party | Q15: Anthropic（知情人士；募資誘因） | R15: 2 | S15: 利害關係方 | T15: Anthropic（知情人士；募資誘因） | U15: 二手 | V15: 觀測 | W15: 原文：'hit $2 billion by the end of March'。與 The Information 3 月初 $1.4B 相差大，月內跳升或口徑不同 | X15: =IF(AND(COUNT($E15:$G15)=0,LEFT($H15,2)<>"定性",LEFT($H15,2)<>"文字",LEFT($H15,2)<>"日期"),1,0) -> 0 | Y15: =IF(OR($L15="",$M15=""),1,0) -> 0 | Z15: =IF(AND(ISNUMBER($E15),ISNUMBER($F15)),IF($F15>$E15,1,0),0)+IF(AND(ISNUMBER($E15),ISNUMBER($G15)),IF($E15>$G15,1,0),0)+IF(AND(ISNUMBER($F15),ISNUMBER($G15)),IF($F15>$G15,1,0),0) -> 0 | AA15: =IF(AND($P15="Derived",$V15="觀測"),1,0) -> 0 | AB15: CC 初評
A16: SRC_ANT_012 | B16: rev_runrate_2025_05 | C16: A | D16: 年化營收（run-rate） | E16: 3 | H16: $B/年 | I16: 2025-05 | K16: 未明 | L16: Reuters 獨家〈Anthropic hits $3 billion in annualized revenue on business demand for AI〉（經 WizCase 轉述） | M16: https://www.wizcase.com/?p=2882381 | N16: 2025-06-03 | O16: 2026-10-08 | P16: Interested-party | Q16: Anthropic（知情人士；募資誘因） | R16: 2 | S16: 利害關係方 | T16: Anthropic（知情人士；募資誘因） | U16: 二手 | V16: 觀測 | W16: 原文：'its $3 billion milestone in May' | X16: =IF(AND(COUNT($E16:$G16)=0,LEFT($H16,2)<>"定性",LEFT($H16,2)<>"文字",LEFT($H16,2)<>"日期"),1,0) -> 0 | Y16: =IF(OR($L16="",$M16=""),1,0) -> 0 | Z16: =IF(AND(ISNUMBER($E16),ISNUMBER($F16)),IF($F16>$E16,1,0),0)+IF(AND(ISNUMBER($E16),ISNUMBER($G16)),IF($E16>$G16,1,0),0)+IF(AND(ISNUMBER($F16),ISNUMBER($G16)),IF($F16>$G16,1,0),0) -> 0 | AA16: =IF(AND($P16="Derived",$V16="觀測"),1,0) -> 0 | AB16: CC 初評
A17: SRC_ANT_013 | B17: rev_runrate_2025_07 | C17: A | D17: 年化營收（run-rate） | E17: 4 | H17: $B/年 | I17: 2025-07（月初） | K17: 未明 | L17: The Information（經 Seeking Alpha 轉述） | M17: https://seekingalpha.com/news/4464440-anthropic-reaches-4b-in-annualized-revenue-report | N17: 2025-07-01 | O17: 2026-10-08 | P17: Interested-party | Q17: Anthropic（知情人士；募資誘因） | R17: 2 | S17: 利害關係方 | T17: Anthropic（知情人士；募資誘因） | U17: 二手 | V17: 觀測 | W17: 原文：'an annualized revenue rate of $4B'，'four times higher than the beginning of the year' | X17: =IF(AND(COUNT($E17:$G17)=0,LEFT($H17,2)<>"定性",LEFT($H17,2)<>"文字",LEFT($H17,2)<>"日期"),1,0) -> 0 | Y17: =IF(OR($L17="",$M17=""),1,0) -> 0 | Z17: =IF(AND(ISNUMBER($E17),ISNUMBER($F17)),IF($F17>$E17,1,0),0)+IF(AND(ISNUMBER($E17),ISNUMBER($G17)),IF($E17>$G17,1,0),0)+IF(AND(ISNUMBER($F17),ISNUMBER($G17)),IF($F17>$G17,1,0),0) -> 0 | AA17: =IF(AND($P17="Derived",$V17="觀測"),1,0) -> 0 | AB17: CC 初評
A18: SRC_ANT_014 | B18: rev_runrate_2025_07_b | C18: A | D18: 年化營收（run-rate） | E18: 4 | H18: $B/年 | I18: 2025-07 | K18: 未明 | L18: Bloomberg〈Anthropic's Revenue Run Rate Tops $9 Billion as VCs Pile In〉 | M18: https://www.bloomberg.com/news/articles/2026-01-21/anthropic-s-revenue-run-rate-tops-9-billion-as-vcs-pile-in | N18: 2026-01-21 | O18: 2026-10-08 | P18: Interested-party | Q18: Anthropic（知情人士；募資誘因） | R18: 2 | S18: 利害關係方 | T18: Anthropic（知情人士；募資誘因） | U18: 二手 | V18: 觀測 | W18: 原文：'was $4 billion in July of last year' | X18: =IF(AND(COUNT($E18:$G18)=0,LEFT($H18,2)<>"定性",LEFT($H18,2)<>"文字",LEFT($H18,2)<>"日期"),1,0) -> 0 | Y18: =IF(OR($L18="",$M18=""),1,0) -> 0 | Z18: =IF(AND(ISNUMBER($E18),ISNUMBER($F18)),IF($F18>$E18,1,0),0)+IF(AND(ISNUMBER($E18),ISNUMBER($G18)),IF($E18>$G18,1,0),0)+IF(AND(ISNUMBER($F18),ISNUMBER($G18)),IF($F18>$G18,1,0),0) -> 0 | AA18: =IF(AND($P18="Derived",$V18="觀測"),1,0) -> 0 | AB18: CC 初評
A19: SRC_ANT_015 | B19: rev_runrate_2025_08 | C19: A | D19: 年化營收（run-rate） | E19: 5 | H19: $B/年 | I19: 2025-08 | K19: 未明 | L19: Anthropic 新聞稿〈Anthropic raises Series F at US$183B post-money valuation〉 | M19: https://www.anthropic.com/news/anthropic-raises-series-f-at-usd183b-post-money-valuation | N19: 2025-09-02 | O19: 2026-10-08 | P19: Interested-party | Q19: Anthropic（募資誘因） | R19: 1 | S19: 利害關係方 | T19: Anthropic（募資誘因） | U19: 一手 | V19: 觀測 | W19: 原文：'By August 2025…our run-rate revenue reached over $5 billion'（下限值） | X19: =IF(AND(COUNT($E19:$G19)=0,LEFT($H19,2)<>"定性",LEFT($H19,2)<>"文字",LEFT($H19,2)<>"日期"),1,0) -> 0 | Y19: =IF(OR($L19="",$M19=""),1,0) -> 0 | Z19: =IF(AND(ISNUMBER($E19),ISNUMBER($F19)),IF($F19>$E19,1,0),0)+IF(AND(ISNUMBER($E19),ISNUMBER($G19)),IF($E19>$G19,1,0),0)+IF(AND(ISNUMBER($F19),ISNUMBER($G19)),IF($F19>$G19,1,0),0) -> 0 | AA19: =IF(AND($P19="Derived",$V19="觀測"),1,0) -> 0 | AB19: CC 初評
A20: SRC_ANT_016 | B20: rev_runrate_2025_10 | C20: A | D20: 年化營收（run-rate） | E20: 7 | G20: 7 | H20: $B/年 | I20: 2025-10 | K20: 未明 | L20: Reuters 獨家〈Anthropic aims to nearly triple annualized revenue in 2026, sources say〉 | M20: https://finance.yahoo.com/news/exclusive-anthropic-aims-nearly-triple-170234463.html | N20: 2025-10-15 | O20: 2026-10-08 | P20: Interested-party | Q20: Anthropic（公司向 Reuters 表示；募資誘因） | R20: 2 | S20: 利害關係方 | T20: Anthropic（公司向 Reuters 表示；募資誘因） | U20: 二手 | V20: 觀測 | W20: 原文：'annual revenue run rate is approaching $7 billion this month'（接近，未達） | X20: =IF(AND(COUNT($E20:$G20)=0,LEFT($H20,2)<>"定性",LEFT($H20,2)<>"文字",LEFT($H20,2)<>"日期"),1,0) -> 0 | Y20: =IF(OR($L20="",$M20=""),1,0) -> 0 | Z20: =IF(AND(ISNUMBER($E20),ISNUMBER($F20)),IF($F20>$E20,1,0),0)+IF(AND(ISNUMBER($E20),ISNUMBER($G20)),IF($E20>$G20,1,0),0)+IF(AND(ISNUMBER($F20),ISNUMBER($G20)),IF($F20>$G20,1,0),0) -> 0 | AA20: =IF(AND($P20="Derived",$V20="觀測"),1,0) -> 0 | AB20: CC 初評
A21: SRC_ANT_017 | B21: rev_runrate_2025_12 | C21: A | D21: 年化營收（run-rate） | E21: 9 | H21: $B/年 | I21: 2025-12 | K21: 未明 | L21: Anthropic 新聞稿〈Google and Broadcom partnership〉 | M21: https://www.anthropic.com/news/google-broadcom-partnership-compute | N21: 2026-04-06 | O21: 2026-10-08 | P21: Interested-party | Q21: Anthropic（募資、市場地位誘因） | R21: 1 | S21: 利害關係方 | T21: Anthropic（募資、市場地位誘因） | U21: 一手 | V21: 觀測 | W21: 原文：'up from approximately $9 billion at the end of 2025' | X21: =IF(AND(COUNT($E21:$G21)=0,LEFT($H21,2)<>"定性",LEFT($H21,2)<>"文字",LEFT($H21,2)<>"日期"),1,0) -> 0 | Y21: =IF(OR($L21="",$M21=""),1,0) -> 0 | Z21: =IF(AND(ISNUMBER($E21),ISNUMBER($F21)),IF($F21>$E21,1,0),0)+IF(AND(ISNUMBER($E21),ISNUMBER($G21)),IF($E21>$G21,1,0),0)+IF(AND(ISNUMBER($F21),ISNUMBER($G21)),IF($F21>$G21,1,0),0) -> 0 | AA21: =IF(AND($P21="Derived",$V21="觀測"),1,0) -> 0 | AB21: CC 初評
A22: SRC_ANT_018 | B22: rev_runrate_2025_12_b | C22: A | D22: 年化營收（run-rate） | E22: 9 | H22: $B/年 | I22: 2025-12 | K22: 未明 | L22: Bloomberg〈Anthropic's Revenue Run Rate Tops $9 Billion as VCs Pile In〉 | M22: https://www.bloomberg.com/news/articles/2026-01-21/anthropic-s-revenue-run-rate-tops-9-billion-as-vcs-pile-in | N22: 2026-01-21 | O22: 2026-10-08 | P22: Interested-party | Q22: Anthropic（知情人士；募資誘因） | R22: 2 | S22: 利害關係方 | T22: Anthropic（知情人士；募資誘因） | U22: 二手 | V22: 觀測 | W22: 原文：'hit over $9 billion at the end of 2025'（下限） | X22: =IF(AND(COUNT($E22:$G22)=0,LEFT($H22,2)<>"定性",LEFT($H22,2)<>"文字",LEFT($H22,2)<>"日期"),1,0) -> 0 | Y22: =IF(OR($L22="",$M22=""),1,0) -> 0 | Z22: =IF(AND(ISNUMBER($E22),ISNUMBER($F22)),IF($F22>$E22,1,0),0)+IF(AND(ISNUMBER($E22),ISNUMBER($G22)),IF($E22>$G22,1,0),0)+IF(AND(ISNUMBER($F22),ISNUMBER($G22)),IF($F22>$G22,1,0),0) -> 0 | AA22: =IF(AND($P22="Derived",$V22="觀測"),1,0) -> 0 | AB22: CC 初評
A23: SRC_ANT_019 | B23: rev_runrate_2026_02 | C23: A | D23: 年化營收（run-rate） | E23: 14 | H23: $B/年 | I23: 2026-02 | K23: 未明 | L23: Anthropic 新聞稿〈Anthropic raises $30 billion Series G at $380 billion post-money valuation〉 | M23: https://www.anthropic.com/news/anthropic-raises-30-billion-series-g-funding-380-billion-post-money-valuation | N23: 2026-02-12 | O23: 2026-10-08 | P23: Interested-party | Q23: Anthropic（募資誘因） | R23: 1 | S23: 利害關係方 | T23: Anthropic（募資誘因） | U23: 一手 | V23: 觀測 | W23: 原文：'Today, our run-rate revenue is $14 billion'，'growing over 10x annually' | X23: =IF(AND(COUNT($E23:$G23)=0,LEFT($H23,2)<>"定性",LEFT($H23,2)<>"文字",LEFT($H23,2)<>"日期"),1,0) -> 0 | Y23: =IF(OR($L23="",$M23=""),1,0) -> 0 | Z23: =IF(AND(ISNUMBER($E23),ISNUMBER($F23)),IF($F23>$E23,1,0),0)+IF(AND(ISNUMBER($E23),ISNUMBER($G23)),IF($E23>$G23,1,0),0)+IF(AND(ISNUMBER($F23),ISNUMBER($G23)),IF($F23>$G23,1,0),0) -> 0 | AA23: =IF(AND($P23="Derived",$V23="觀測"),1,0) -> 0 | AB23: CC 初評
A24: SRC_ANT_020 | B24: rev_runrate_2026_03 | C24: A | D24: 年化營收（run-rate） | E24: 19 | H24: $B/年 | I24: 2026-03（月初） | K24: 未明 | L24: Bloomberg〈Anthropic Nears $20 Billion Revenue Run Rate Amid Pentagon Feud〉 | M24: https://news.bgov.com/artificial-intelligence/anthropic-nears-20-billion-revenue-run-rate-amid-pentagon-feud | N24: 2026-03-03 | O24: 2026-10-08 | P24: Interested-party | Q24: Anthropic（知情人士；募資誘因） | R24: 2 | S24: 利害關係方 | T24: Anthropic（知情人士；募資誘因） | U24: 二手 | V24: 觀測 | W24: 原文：'surpassed $19 billion in run-rate revenue'；'roughly $14 billion a few weeks ago' | X24: =IF(AND(COUNT($E24:$G24)=0,LEFT($H24,2)<>"定性",LEFT($H24,2)<>"文字",LEFT($H24,2)<>"日期"),1,0) -> 0 | Y24: =IF(OR($L24="",$M24=""),1,0) -> 0 | Z24: =IF(AND(ISNUMBER($E24),ISNUMBER($F24)),IF($F24>$E24,1,0),0)+IF(AND(ISNUMBER($E24),ISNUMBER($G24)),IF($E24>$G24,1,0),0)+IF(AND(ISNUMBER($F24),ISNUMBER($G24)),IF($F24>$G24,1,0),0) -> 0 | AA24: =IF(AND($P24="Derived",$V24="觀測"),1,0) -> 0 | AB24: CC 初評
A25: SRC_ANT_021 | B25: rev_runrate_2026_04 | C25: A | D25: 年化營收（run-rate） | E25: 30 | H25: $B/年 | I25: 2026-04 | K25: 未明 | L25: Anthropic 新聞稿〈Google and Broadcom partnership〉 | M25: https://www.anthropic.com/news/google-broadcom-partnership-compute | N25: 2026-04-06 | O25: 2026-10-08 | P25: Interested-party | Q25: Anthropic（募資、市場地位誘因） | R25: 1 | S25: 利害關係方 | T25: Anthropic（募資、市場地位誘因） | U25: 一手 | V25: 觀測 | W25: 原文：'Our run-rate revenue has now surpassed $30 billion'（下限） | X25: =IF(AND(COUNT($E25:$G25)=0,LEFT($H25,2)<>"定性",LEFT($H25,2)<>"文字",LEFT($H25,2)<>"日期"),1,0) -> 0 | Y25: =IF(OR($L25="",$M25=""),1,0) -> 0 | Z25: =IF(AND(ISNUMBER($E25),ISNUMBER($F25)),IF($F25>$E25,1,0),0)+IF(AND(ISNUMBER($E25),ISNUMBER($G25)),IF($E25>$G25,1,0),0)+IF(AND(ISNUMBER($F25),ISNUMBER($G25)),IF($F25>$G25,1,0),0) -> 0 | AA25: =IF(AND($P25="Derived",$V25="觀測"),1,0) -> 0 | AB25: CC 初評
A26: SRC_ANT_022 | B26: rev_runrate_2026_05 | C26: A | D26: 年化營收（run-rate） | E26: 47 | H26: $B/年 | I26: 2026-05 | K26: 未明 | L26: Anthropic 新聞稿〈Series H〉 | M26: https://www.anthropic.com/news/series-h | N26: 2026-05-28 | O26: 2026-10-08 | P26: Interested-party | Q26: Anthropic（募資誘因） | R26: 1 | S26: 利害關係方 | T26: Anthropic（募資誘因） | U26: 一手 | V26: 觀測 | W26: 原文：'our run-rate revenue crossed $47 billion earlier this month' | X26: =IF(AND(COUNT($E26:$G26)=0,LEFT($H26,2)<>"定性",LEFT($H26,2)<>"文字",LEFT($H26,2)<>"日期"),1,0) -> 0 | Y26: =IF(OR($L26="",$M26=""),1,0) -> 0 | Z26: =IF(AND(ISNUMBER($E26),ISNUMBER($F26)),IF($F26>$E26,1,0),0)+IF(AND(ISNUMBER($E26),ISNUMBER($G26)),IF($E26>$G26,1,0),0)+IF(AND(ISNUMBER($F26),ISNUMBER($G26)),IF($F26>$G26,1,0),0) -> 0 | AA26: =IF(AND($P26="Derived",$V26="觀測"),1,0) -> 0 | AB26: CC 初評
A27: SRC_ANT_023 | B27: rev_runrate_2026_07 | C27: A | D27: 年化營收（run-rate） | E27: 65 | H27: $B/年 | I27: 2026-07（月底） | K27: 未明 | L27: Bloomberg（經 TechCrunch 轉述）〈Anthropic's annualized revenue surges to $65B〉 | M27: https://techcrunch.com/2026/08/17/anthropics-annualized-revenue-surges-to-65b/ | N27: 2026-08-17 | O27: 2026-10-08 | P27: Interested-party | Q27: Anthropic（告知投資人；IPO 誘因） | R27: 2 | S27: 利害關係方 | T27: Anthropic（告知投資人；IPO 誘因） | U27: 二手 | V27: 觀測 | W27: 原文：'surpassed $65 billion' at the end of July；'$47 billion in May'。截至 2026-10-08 未見更新的 run-rate | X27: =IF(AND(COUNT($E27:$G27)=0,LEFT($H27,2)<>"定性",LEFT($H27,2)<>"文字",LEFT($H27,2)<>"日期"),1,0) -> 0 | Y27: =IF(OR($L27="",$M27=""),1,0) -> 0 | Z27: =IF(AND(ISNUMBER($E27),ISNUMBER($F27)),IF($F27>$E27,1,0),0)+IF(AND(ISNUMBER($E27),ISNUMBER($G27)),IF($E27>$G27,1,0),0)+IF(AND(ISNUMBER($F27),ISNUMBER($G27)),IF($F27>$G27,1,0),0) -> 0 | AA27: =IF(AND($P27="Derived",$V27="觀測"),1,0) -> 0 | AB27: CC 初評
A28: SRC_ANT_024 | B28: rev_runrate_2026_07_b | C28: A | D28: 年化營收（run-rate） | E28: 65 | H28: $B/年 | I28: 2026-07 | K28: 未明 | L28: AI Magazine〈How Anthropic's Revenue Run Rate Topped US$65bn〉（引 Reuters 知情人士） | M28: https://aimagazine.com/news/how-anthropics-revenue-run-rate-topped-us-65bn | N28: 2026-08-18 | O28: 2026-10-08 | P28: Interested-party | Q28: Anthropic（知情人士；IPO 誘因） | R28: 2 | S28: 利害關係方 | T28: Anthropic（知情人士；IPO 誘因） | U28: 二手 | V28: 觀測 | W28: 原文：'US$65bn annual revenue run rate, reached by the end of July'；投資人預期年底 $100–120bn（FT） | X28: =IF(AND(COUNT($E28:$G28)=0,LEFT($H28,2)<>"定性",LEFT($H28,2)<>"文字",LEFT($H28,2)<>"日期"),1,0) -> 0 | Y28: =IF(OR($L28="",$M28=""),1,0) -> 0 | Z28: =IF(AND(ISNUMBER($E28),ISNUMBER($F28)),IF($F28>$E28,1,0),0)+IF(AND(ISNUMBER($E28),ISNUMBER($G28)),IF($E28>$G28,1,0),0)+IF(AND(ISNUMBER($F28),ISNUMBER($G28)),IF($F28>$G28,1,0),0) -> 0 | AA28: =IF(AND($P28="Derived",$V28="觀測"),1,0) -> 0 | AB28: CC 初評
A29: SRC_ANT_025 | B29: rev_mix_2025_subscription | C29: A | D29: 2025 訂閱營收 | E29: 0.789 | H29: $B/年 | I29: 2025 | K29: 總額 | L29: Reuters〈Anthropic IPO prospectus lays bare deep dependence on Big Tech partners〉（經 Khaleej Times 轉載） | M29: https://www.khaleejtimes.com/business/anthropic-ipo-prospectus-lays-bare-deep-dependence-on-big-tech-partners?amp=1 | N29: 2026-09-30 | O29: 2026-10-08 | P29: Interested-party | Q29: Anthropic（外流招股書；IPO 誘因） | R29: 2 | S29: 利害關係方 | T29: Anthropic（外流招股書；IPO 誘因） | U29: 二手 | V29: 觀測 | W29: 原文：'Subscription revenue came to $789 million'；約占 2025 營收 17%（推算） | X29: =IF(AND(COUNT($E29:$G29)=0,LEFT($H29,2)<>"定性",LEFT($H29,2)<>"文字",LEFT($H29,2)<>"日期"),1,0) -> 0 | Y29: =IF(OR($L29="",$M29=""),1,0) -> 0 | Z29: =IF(AND(ISNUMBER($E29),ISNUMBER($F29)),IF($F29>$E29,1,0),0)+IF(AND(ISNUMBER($E29),ISNUMBER($G29)),IF($E29>$G29,1,0),0)+IF(AND(ISNUMBER($F29),ISNUMBER($G29)),IF($F29>$G29,1,0),0) -> 0 | AA29: =IF(AND($P29="Derived",$V29="觀測"),1,0) -> 0 | AB29: CC 初評
A30: SRC_ANT_026 | B30: rev_mix_2025_consumption | C30: A | D30: 2025 用量計價（API／token）營收 | E30: 3.8 | H30: $B/年 | I30: 2025 | K30: 總額 | L30: Reuters（經 Khaleej Times 轉載） | M30: https://www.khaleejtimes.com/business/anthropic-ipo-prospectus-lays-bare-deep-dependence-on-big-tech-partners?amp=1 | N30: 2026-09-30 | O30: 2026-10-08 | P30: Interested-party | Q30: Anthropic（外流招股書；IPO 誘因） | R30: 2 | S30: 利害關係方 | T30: Anthropic（外流招股書；IPO 誘因） | U30: 二手 | V30: 觀測 | W30: 原文：consumption-based revenue 'about $3.8 billion'，預期仍為 'the substantial majority'；約 83%（推算） | X30: =IF(AND(COUNT($E30:$G30)=0,LEFT($H30,2)<>"定性",LEFT($H30,2)<>"文字",LEFT($H30,2)<>"日期"),1,0) -> 0 | Y30: =IF(OR($L30="",$M30=""),1,0) -> 0 | Z30: =IF(AND(ISNUMBER($E30),ISNUMBER($F30)),IF($F30>$E30,1,0),0)+IF(AND(ISNUMBER($E30),ISNUMBER($G30)),IF($E30>$G30,1,0),0)+IF(AND(ISNUMBER($F30),ISNUMBER($G30)),IF($F30>$G30,1,0),0) -> 0 | AA30: =IF(AND($P30="Derived",$V30="觀測"),1,0) -> 0 | AB30: CC 初評
A31: SRC_ANT_027 | B31: rev_mix_2025_cloud_partner_share | C31: A | D31: 經 Amazon／Google 雲端通路之營收占比 | E31: 0.47 | H31: 比例 | I31: 2025 | K31: 總額 | L31: Reuters（經 Khaleej Times 轉載） | M31: https://www.khaleejtimes.com/business/anthropic-ipo-prospectus-lays-bare-deep-dependence-on-big-tech-partners?amp=1 | N31: 2026-09-30 | O31: 2026-10-08 | P31: Interested-party | Q31: Anthropic（外流招股書；IPO 誘因） | R31: 2 | S31: 利害關係方 | T31: Anthropic（外流招股書；IPO 誘因） | U31: 二手 | V31: 觀測 | W31: 原文：'routed 47% of its sales…through cloud partners Amazon and Alphabet's Google'；未含 Microsoft | X31: =IF(AND(COUNT($E31:$G31)=0,LEFT($H31,2)<>"定性",LEFT($H31,2)<>"文字",LEFT($H31,2)<>"日期"),1,0) -> 0 | Y31: =IF(OR($L31="",$M31=""),1,0) -> 0 | Z31: =IF(AND(ISNUMBER($E31),ISNUMBER($F31)),IF($F31>$E31,1,0),0)+IF(AND(ISNUMBER($E31),ISNUMBER($G31)),IF($E31>$G31,1,0),0)+IF(AND(ISNUMBER($F31),ISNUMBER($G31)),IF($F31>$G31,1,0),0) -> 0 | AA31: =IF(AND($P31="Derived",$V31="觀測"),1,0) -> 0 | AB31: CC 初評
A32: SRC_ANT_028 | B32: rev_mix_2024_cloud_partner_share | C32: A | D32: 經 Amazon／Google 雲端通路之營收占比 | E32: 0.32 | H32: 比例 | I32: 2024 | K32: 總額 | L32: Reuters（經 Khaleej Times 轉載） | M32: https://www.khaleejtimes.com/business/anthropic-ipo-prospectus-lays-bare-deep-dependence-on-big-tech-partners?amp=1 | N32: 2026-09-30 | O32: 2026-10-08 | P32: Interested-party | Q32: Anthropic（外流招股書；IPO 誘因） | R32: 2 | S32: 利害關係方 | T32: Anthropic（外流招股書；IPO 誘因） | U32: 二手 | V32: 觀測 | W32: 原文：share 'rose from 11% in 2023 to 32% in 2024' | X32: =IF(AND(COUNT($E32:$G32)=0,LEFT($H32,2)<>"定性",LEFT($H32,2)<>"文字",LEFT($H32,2)<>"日期"),1,0) -> 0 | Y32: =IF(OR($L32="",$M32=""),1,0) -> 0 | Z32: =IF(AND(ISNUMBER($E32),ISNUMBER($F32)),IF($F32>$E32,1,0),0)+IF(AND(ISNUMBER($E32),ISNUMBER($G32)),IF($E32>$G32,1,0),0)+IF(AND(ISNUMBER($F32),ISNUMBER($G32)),IF($F32>$G32,1,0),0) -> 0 | AA32: =IF(AND($P32="Derived",$V32="觀測"),1,0) -> 0 | AB32: CC 初評
A33: SRC_ANT_029 | B33: rev_mix_2023_cloud_partner_share | C33: A | D33: 經 Amazon／Google 雲端通路之營收占比 | E33: 0.11 | H33: 比例 | I33: 2023 | K33: 總額 | L33: Reuters（經 Khaleej Times 轉載） | M33: https://www.khaleejtimes.com/business/anthropic-ipo-prospectus-lays-bare-deep-dependence-on-big-tech-partners?amp=1 | N33: 2026-09-30 | O33: 2026-10-08 | P33: Interested-party | Q33: Anthropic（外流招股書；IPO 誘因） | R33: 2 | S33: 利害關係方 | T33: Anthropic（外流招股書；IPO 誘因） | U33: 二手 | V33: 觀測 | W33: 原文：'from 11% in 2023' | X33: =IF(AND(COUNT($E33:$G33)=0,LEFT($H33,2)<>"定性",LEFT($H33,2)<>"文字",LEFT($H33,2)<>"日期"),1,0) -> 0 | Y33: =IF(OR($L33="",$M33=""),1,0) -> 0 | Z33: =IF(AND(ISNUMBER($E33),ISNUMBER($F33)),IF($F33>$E33,1,0),0)+IF(AND(ISNUMBER($E33),ISNUMBER($G33)),IF($E33>$G33,1,0),0)+IF(AND(ISNUMBER($F33),ISNUMBER($G33)),IF($F33>$G33,1,0),0) -> 0 | AA33: =IF(AND($P33="Derived",$V33="觀測"),1,0) -> 0 | AB33: CC 初評
A34: SRC_ANT_030 | B34: rev_recognition_gross | C34: A | D34: 雲端市集銷售之營收認列口徑 | H34: 定性 | I34: 2025 | K34: 總額 | L34: Reuters（經 Khaleej Times 轉載） | M34: https://www.khaleejtimes.com/business/anthropic-ipo-prospectus-lays-bare-deep-dependence-on-big-tech-partners?amp=1 | N34: 2026-09-30 | O34: 2026-10-08 | P34: Interested-party | Q34: Anthropic（外流招股書；IPO 誘因） | R34: 2 | S34: 利害關係方 | T34: Anthropic（外流招股書；IPO 誘因） | U34: 二手 | V34: 觀測 | W34: 總額認列：'books the full value of marketplace contracts as revenue and records the platforms' cut as a marketing cost'；自稱 'principal' | X34: =IF(AND(COUNT($E34:$G34)=0,LEFT($H34,2)<>"定性",LEFT($H34,2)<>"文字",LEFT($H34,2)<>"日期"),1,0) -> 0 | Y34: =IF(OR($L34="",$M34=""),1,0) -> 0 | Z34: =IF(AND(ISNUMBER($E34),ISNUMBER($F34)),IF($F34>$E34,1,0),0)+IF(AND(ISNUMBER($E34),ISNUMBER($G34)),IF($E34>$G34,1,0),0)+IF(AND(ISNUMBER($F34),ISNUMBER($G34)),IF($F34>$G34,1,0),0) -> 0 | AA34: =IF(AND($P34="Derived",$V34="觀測"),1,0) -> 0 | AB34: CC 初評
A35: SRC_ANT_031 | B35: rev_partner_fee_2025 | C35: A | D35: 2025 付給雲端平台之通路費 | E35: 0.351 | H35: $B/年 | I35: 2025 | K35: 總額 | L35: Reuters 分析（經 Khaleej Times 轉載） | M35: https://www.khaleejtimes.com/business/anthropic-ipo-prospectus-lays-bare-deep-dependence-on-big-tech-partners?amp=1 | N35: 2026-09-30 | O35: 2026-10-08 | P35: Derived | R35: 未評 | S35: 推導 | T35: 由其他 SRC_ANT 列推得（本活頁簿以公式表示） | U35: 推導 | V35: Derived→保留報導值（報導者計算後公布） | W35: 原文：'roughly $351 million back to the platforms in distribution fees'；Reuters 依招股書計算 | X35: =IF(AND(COUNT($E35:$G35)=0,LEFT($H35,2)<>"定性",LEFT($H35,2)<>"文字",LEFT($H35,2)<>"日期"),1,0) -> 0 | Y35: =IF(OR($L35="",$M35=""),1,0) -> 0 | Z35: =IF(AND(ISNUMBER($E35),ISNUMBER($F35)),IF($F35>$E35,1,0),0)+IF(AND(ISNUMBER($E35),ISNUMBER($G35)),IF($E35>$G35,1,0),0)+IF(AND(ISNUMBER($F35),ISNUMBER($G35)),IF($F35>$G35,1,0),0) -> 0 | AA35: =IF(AND($P35="Derived",$V35="觀測"),1,0) -> 0 | AB35: CC 初評
A36: SRC_ANT_032 | B36: rev_partner_fee_rate_2025 | C36: A | D36: 雲端通路抽成率（每 $1 通路營收） | E36: =SRC_ANT_031/(SRC_ANT_002*SRC_ANT_027) -> 0.16270338 | H36: 比例 | I36: 2025 | K36: 總額 | L36: Reuters 分析（經 Khaleej Times 轉載） | M36: https://www.khaleejtimes.com/business/anthropic-ipo-prospectus-lays-bare-deep-dependence-on-big-tech-partners?amp=1 | N36: 2026-09-30 | O36: 2026-10-08 | P36: Derived | R36: 未評 | S36: 推導 | T36: 由其他 SRC_ANT 列推得（本活頁簿以公式表示） | U36: 推導 | V36: Derived→公式 | W36: 原文：'some 16 cents for every dollar of those sales'。0.351/(4.59×0.47)≈0.16 一致 | X36: =IF(AND(COUNT($E36:$G36)=0,LEFT($H36,2)<>"定性",LEFT($H36,2)<>"文字",LEFT($H36,2)<>"日期"),1,0) -> 0 | Y36: =IF(OR($L36="",$M36=""),1,0) -> 0 | Z36: =IF(AND(ISNUMBER($E36),ISNUMBER($F36)),IF($F36>$E36,1,0),0)+IF(AND(ISNUMBER($E36),ISNUMBER($G36)),IF($E36>$G36,1,0),0)+IF(AND(ISNUMBER($F36),ISNUMBER($G36)),IF($F36>$G36,1,0),0) -> 0 | AA36: =IF(AND($P36="Derived",$V36="觀測"),1,0) -> 0 | AB36: CC 初評
A37: SRC_ANT_033 | B37: rev_partner_fee_2025_b | C37: A | D37: 2025 付給超大雲端之金額（券商估計） | E37: 1.9 | H37: $B/年 | I37: 2025 | K37: 總額 | L37: Forbes〈OpenAI And Anthropic Count Revenue Differently〉（引 Bank of America 2026-03 估計） | M37: https://www.forbes.com/sites/josipamajic/2026/03/25/openai-and-anthropic-count-revenue-differently-and-investors-are-looking-into-it/ | N37: 2026-03-25 | O37: 2026-10-08 | P37: Analogy | R37: 2 | S37: 第三方估計 | T37: 第三方估計；非公司揭露，作類比或區間 | U37: 二手 | V37: 觀測 | W37: 原文：'up to $6.4 billion in 2026…up from $1.9 billion in 2025'。與招股書 $351M 矛盾（BofA 口徑可能含算力租金），以招股書為準 | X37: =IF(AND(COUNT($E37:$G37)=0,LEFT($H37,2)<>"定性",LEFT($H37,2)<>"文字",LEFT($H37,2)<>"日期"),1,0) -> 0 | Y37: =IF(OR($L37="",$M37=""),1,0) -> 0 | Z37: =IF(AND(ISNUMBER($E37),ISNUMBER($F37)),IF($F37>$E37,1,0),0)+IF(AND(ISNUMBER($E37),ISNUMBER($G37)),IF($E37>$G37,1,0),0)+IF(AND(ISNUMBER($F37),ISNUMBER($G37)),IF($F37>$G37,1,0),0) -> 0 | AA37: =IF(AND($P37="Derived",$V37="觀測"),1,0) -> 0 | AB37: CC 初評
A38: SRC_ANT_034 | B38: rev_partner_fee_2026_est | C38: A | D38: 2026 付給超大雲端之金額（券商估計） | E38: 6.4 | G38: 6.4 | H38: $B/年 | I38: 2026 | K38: 總額 | L38: Forbes（引 Bank of America） | M38: https://www.forbes.com/sites/josipamajic/2026/03/25/openai-and-anthropic-count-revenue-differently-and-investors-are-looking-into-it/ | N38: 2026-03-25 | O38: 2026-10-08 | P38: Analogy | R38: 2 | S38: 第三方估計 | T38: 第三方估計；非公司揭露，作類比或區間 | U38: 二手 | V38: 觀測 | W38: 原文：'could pay hyperscale cloud providers up to $6.4 billion in 2026' | X38: =IF(AND(COUNT($E38:$G38)=0,LEFT($H38,2)<>"定性",LEFT($H38,2)<>"文字",LEFT($H38,2)<>"日期"),1,0) -> 0 | Y38: =IF(OR($L38="",$M38=""),1,0) -> 0 | Z38: =IF(AND(ISNUMBER($E38),ISNUMBER($F38)),IF($F38>$E38,1,0),0)+IF(AND(ISNUMBER($E38),ISNUMBER($G38)),IF($E38>$G38,1,0),0)+IF(AND(ISNUMBER($F38),ISNUMBER($G38)),IF($F38>$G38,1,0),0) -> 0 | AA38: =IF(AND($P38="Derived",$V38="觀測"),1,0) -> 0 | AB38: CC 初評
A39: SRC_ANT_035 | B39: rev_runrate_gross_dispute_2026_04 | C39: A | D39: OpenAI 估計之 Anthropic「淨額」run-rate | E39: 22 | H39: $B/年 | I39: 2026-04 | K39: 淨額 | L39: Implicator〈OpenAI CRO tells staff Anthropic inflates run rate by $8 billion〉（OpenAI CRO 內部備忘錄，The Verge／CNBC 取得） | M39: https://www.implicator.ai/openai-cro-tells-staff-anthropic-inflates-run-rate-by-8-billion/ | N39: 2026-04-13 | O39: 2026-10-08 | P39: Interested-party | Q39: OpenAI（競爭對手；貶低對手誘因） | R39: 2 | S39: 利害關係方 | T39: OpenAI（競爭對手；貶低對手誘因） | U39: 二手 | V39: 觀測 | W39: 原文：'Their stated run rate is inflated'；OpenAI 估 'true' run rate 約 $22B（對比公布的 $30B，差 $8B） | X39: =IF(AND(COUNT($E39:$G39)=0,LEFT($H39,2)<>"定性",LEFT($H39,2)<>"文字",LEFT($H39,2)<>"日期"),1,0) -> 0 | Y39: =IF(OR($L39="",$M39=""),1,0) -> 0 | Z39: =IF(AND(ISNUMBER($E39),ISNUMBER($F39)),IF($F39>$E39,1,0),0)+IF(AND(ISNUMBER($E39),ISNUMBER($G39)),IF($E39>$G39,1,0),0)+IF(AND(ISNUMBER($F39),ISNUMBER($G39)),IF($F39>$G39,1,0),0) -> 0 | AA39: =IF(AND($P39="Derived",$V39="觀測"),1,0) -> 0 | AB39: CC 初評
A40: SRC_ANT_036 | B40: rev_enterprise_share_2025_10 | C40: A | D40: 企業與商業客戶占營收比例 | E40: 0.8 | H40: 比例 | I40: 2025-10 | K40: 未明 | L40: Reuters 獨家〈Anthropic aims to nearly triple annualized revenue in 2026〉 | M40: https://finance.yahoo.com/news/exclusive-anthropic-aims-nearly-triple-170234463.html | N40: 2025-10-15 | O40: 2026-10-08 | P40: Interested-party | Q40: Anthropic（募資誘因） | R40: 2 | S40: 利害關係方 | T40: Anthropic（募資誘因） | U40: 二手 | V40: 觀測 | W40: 原文：business and enterprise customers 'account for about 80% of its revenue' | X40: =IF(AND(COUNT($E40:$G40)=0,LEFT($H40,2)<>"定性",LEFT($H40,2)<>"文字",LEFT($H40,2)<>"日期"),1,0) -> 0 | Y40: =IF(OR($L40="",$M40=""),1,0) -> 0 | Z40: =IF(AND(ISNUMBER($E40),ISNUMBER($F40)),IF($F40>$E40,1,0),0)+IF(AND(ISNUMBER($E40),ISNUMBER($G40)),IF($E40>$G40,1,0),0)+IF(AND(ISNUMBER($F40),ISNUMBER($G40)),IF($F40>$G40,1,0),0) -> 0 | AA40: =IF(AND($P40="Derived",$V40="觀測"),1,0) -> 0 | AB40: CC 初評
A41: SRC_ANT_037 | B41: rev_us_share_2025 | C41: A | D41: 美國占營收比例 | E41: 0.65 | F41: 0.6 | G41: 0.67 | H41: 比例 | I41: 2025 | K41: 總額 | L41: Reuters（經 Khaleej Times 轉載） | M41: https://www.khaleejtimes.com/business/anthropic-ipo-prospectus-lays-bare-deep-dependence-on-big-tech-partners?amp=1 | N41: 2026-09-30 | O41: 2026-10-08 | P41: Interested-party | Q41: Anthropic（外流招股書） | R41: 2 | S41: 利害關係方 | T41: Anthropic（外流招股書） | U41: 二手 | V41: 觀測 | W41: 原文：'The US accounted for nearly two-thirds of total sales'；value 為近似 | X41: =IF(AND(COUNT($E41:$G41)=0,LEFT($H41,2)<>"定性",LEFT($H41,2)<>"文字",LEFT($H41,2)<>"日期"),1,0) -> 0 | Y41: =IF(OR($L41="",$M41=""),1,0) -> 0 | Z41: =IF(AND(ISNUMBER($E41),ISNUMBER($F41)),IF($F41>$E41,1,0),0)+IF(AND(ISNUMBER($E41),ISNUMBER($G41)),IF($E41>$G41,1,0),0)+IF(AND(ISNUMBER($F41),ISNUMBER($G41)),IF($F41>$G41,1,0),0) -> 0 | AA41: =IF(AND($P41="Derived",$V41="觀測"),1,0) -> 0 | AB41: CC 初評
A42: SRC_ANT_038 | B42: rev_concentration_top2_2025 | C42: A | D42: 前兩大客戶占 2025 營收比例 | E42: 0.24 | H42: 比例 | I42: 2025 | K42: 總額 | L42: Reuters（經 Khaleej Times 轉載） | M42: https://www.khaleejtimes.com/business/anthropic-ipo-prospectus-lays-bare-deep-dependence-on-big-tech-partners?amp=1 | N42: 2026-09-30 | O42: 2026-10-08 | P42: Interested-party | Q42: Anthropic（外流招股書） | R42: 2 | S42: 利害關係方 | T42: Anthropic（外流招股書） | U42: 二手 | V42: 觀測 | W42: 原文：'Two unnamed customers each generated 12% of revenue last year'（12%+12%） | X42: =IF(AND(COUNT($E42:$G42)=0,LEFT($H42,2)<>"定性",LEFT($H42,2)<>"文字",LEFT($H42,2)<>"日期"),1,0) -> 0 | Y42: =IF(OR($L42="",$M42=""),1,0) -> 0 | Z42: =IF(AND(ISNUMBER($E42),ISNUMBER($F42)),IF($F42>$E42,1,0),0)+IF(AND(ISNUMBER($E42),ISNUMBER($G42)),IF($E42>$G42,1,0),0)+IF(AND(ISNUMBER($F42),ISNUMBER($G42)),IF($F42>$G42,1,0),0) -> 0 | AA42: =IF(AND($P42="Derived",$V42="觀測"),1,0) -> 0 | AB42: CC 初評
A43: SRC_ANT_039 | B43: rev_concentration_top2_2025_b | C43: A | D43: 前兩大客戶身分（媒體指稱） | E43: 0.24 | H43: 比例 | I43: 2025 | K43: 總額 | L43: Crypto Briefing〈Anthropic's IPO filing reveals Amazon and Google account for a quarter of its revenue〉 | M43: https://cryptobriefing.com/anthropic-ipo-amazon-google-revenue/ | N43: 2026-09-29 | O43: 2026-10-08 | P43: Interested-party | Q43: Anthropic（外流招股書；媒體推論） | R43: 未評 | S43: 利害關係方 | T43: Anthropic（外流招股書；媒體推論） | U43: 未評 | V43: 觀測 | W43: 原文：Amazon、Google 'each contributing about 12% of total sales'。與 Reuters「未具名」矛盾；OfficeChai 則推測為 Cursor／GitHub Copilot | X43: =IF(AND(COUNT($E43:$G43)=0,LEFT($H43,2)<>"定性",LEFT($H43,2)<>"文字",LEFT($H43,2)<>"日期"),1,0) -> 0 | Y43: =IF(OR($L43="",$M43=""),1,0) -> 0 | Z43: =IF(AND(ISNUMBER($E43),ISNUMBER($F43)),IF($F43>$E43,1,0),0)+IF(AND(ISNUMBER($E43),ISNUMBER($G43)),IF($E43>$G43,1,0),0)+IF(AND(ISNUMBER($F43),ISNUMBER($G43)),IF($F43>$G43,1,0),0) -> 0 | AA43: =IF(AND($P43="Derived",$V43="觀測"),1,0) -> 0 | AB43: CC 初評
A44: SRC_ANT_040 | B44: rev_concentration_cursor_copilot_2025 | C44: A | D44: Cursor＋GitHub Copilot 合計貢獻之年化營收 | E44: 1.2 | H44: $B/年 | I44: 2025-07 | K44: 未明 | L44: VentureBeat〈Anthropic revenue tied to two customers as AI pricing war threatens margins〉 | M44: https://venturebeat.com/ai/anthropic-revenue-tied-to-two-customers-as-ai-pricing-war-threatens-margins | N44: 2025-08-08 | O44: 2026-10-08 | P44: Interested-party | Q44: Anthropic（知情人士） | R44: 未評 | S44: 利害關係方 | T44: Anthropic（知情人士） | U44: 未評 | V44: 觀測 | W44: 原文：'approximately $1.2 billion of the company's $4 billion revenue milestone'（run-rate 口徑，約 30%） | X44: =IF(AND(COUNT($E44:$G44)=0,LEFT($H44,2)<>"定性",LEFT($H44,2)<>"文字",LEFT($H44,2)<>"日期"),1,0) -> 0 | Y44: =IF(OR($L44="",$M44=""),1,0) -> 0 | Z44: =IF(AND(ISNUMBER($E44),ISNUMBER($F44)),IF($F44>$E44,1,0),0)+IF(AND(ISNUMBER($E44),ISNUMBER($G44)),IF($E44>$G44,1,0),0)+IF(AND(ISNUMBER($F44),ISNUMBER($G44)),IF($F44>$G44,1,0),0) -> 0 | AA44: =IF(AND($P44="Derived",$V44="觀測"),1,0) -> 0 | AB44: CC 初評
A45: SRC_ANT_041 | B45: rev_microsoft_spend_2025 | C45: A | D45: Microsoft 每年向 Anthropic 支付金額（客戶身分） | E45: 0.5 | G45: 0.5 | H45: $B/年 | I45: 2025 | K45: 未明 | L45: The Decoder（引 The Information）〈Despite OpenAI partnership, Microsoft is one of Anthropic's biggest customers〉 | M45: https://the-decoder.com/despite-openai-partnership-microsoft-is-one-of-anthropics-biggest-customers/ | O45: 2026-10-08 | P45: Interested-party | Q45: Anthropic／Microsoft（知情人士） | R45: 2 | S45: 利害關係方 | T45: Anthropic／Microsoft（知情人士） | U45: 二手 | V45: 觀測 | W45: 原文：'nearly $500 million a year'；頁面無發布日期（內文提及 Microsoft 'last November' 投資，推測為 2025-12 至 2026 年初） | X45: =IF(AND(COUNT($E45:$G45)=0,LEFT($H45,2)<>"定性",LEFT($H45,2)<>"文字",LEFT($H45,2)<>"日期"),1,0) -> 0 | Y45: =IF(OR($L45="",$M45=""),1,0) -> 0 | Z45: =IF(AND(ISNUMBER($E45),ISNUMBER($F45)),IF($F45>$E45,1,0),0)+IF(AND(ISNUMBER($E45),ISNUMBER($G45)),IF($E45>$G45,1,0),0)+IF(AND(ISNUMBER($F45),ISNUMBER($G45)),IF($F45>$G45,1,0),0) -> 0 | AA45: =IF(AND($P45="Derived",$V45="觀測"),1,0) -> 0 | AB45: CC 初評
A46: SRC_ANT_042 | B46: gm_2025_projected_initial | C46: A | D46: 2025 毛利率（原預測） | E46: 0.5 | H46: 比例 | I46: 2025 | K46: 未明 | L46: Forbes（引 The Information） | M46: https://www.forbes.com/sites/josipamajic/2026/03/25/openai-and-anthropic-count-revenue-differently-and-investors-are-looking-into-it/ | N46: 2026-03-25 | O46: 2026-10-08 | P46: Interested-party | Q46: Anthropic（投資人預測文件） | R46: 2 | S46: 利害關係方 | T46: Anthropic（投資人預測文件） | U46: 二手 | V46: 觀測 | W46: 原文：'gross margin projections: 50% for 2025 and 77% by 2028, per The Information' | X46: =IF(AND(COUNT($E46:$G46)=0,LEFT($H46,2)<>"定性",LEFT($H46,2)<>"文字",LEFT($H46,2)<>"日期"),1,0) -> 0 | Y46: =IF(OR($L46="",$M46=""),1,0) -> 0 | Z46: =IF(AND(ISNUMBER($E46),ISNUMBER($F46)),IF($F46>$E46,1,0),0)+IF(AND(ISNUMBER($E46),ISNUMBER($G46)),IF($E46>$G46,1,0),0)+IF(AND(ISNUMBER($F46),ISNUMBER($G46)),IF($F46>$G46,1,0),0) -> 0 | AA46: =IF(AND($P46="Derived",$V46="觀測"),1,0) -> 0 | AB46: CC 初評
A47: SRC_ANT_043 | B47: gm_2025_revised | C47: A | D47: 2025 毛利率（下修後，付費企業與開發者） | E47: 0.4 | H47: 比例 | I47: 2025 | K47: 未明 | L47: The Information〈Anthropic Lowers Gross Margin Projection as Revenue Skyrockets〉 | M47: https://www.theinformation.com/articles/anthropic-lowers-profit-margin-projection-revenue-skyrockets | N47: 2026-01-21 | O47: 2026-10-08 | P47: Interested-party | Q47: Anthropic（投資人簡報） | R47: 2 | S47: 利害關係方 | T47: Anthropic（投資人簡報） | U47: 二手 | V47: 觀測 | W47: 原文：'projected it would generate a 40% gross profit margin from selling AI'，比先前低 10 個百分點 | X47: =IF(AND(COUNT($E47:$G47)=0,LEFT($H47,2)<>"定性",LEFT($H47,2)<>"文字",LEFT($H47,2)<>"日期"),1,0) -> 0 | Y47: =IF(OR($L47="",$M47=""),1,0) -> 0 | Z47: =IF(AND(ISNUMBER($E47),ISNUMBER($F47)),IF($F47>$E47,1,0),0)+IF(AND(ISNUMBER($E47),ISNUMBER($G47)),IF($E47>$G47,1,0),0)+IF(AND(ISNUMBER($F47),ISNUMBER($G47)),IF($F47>$G47,1,0),0) -> 0 | AA47: =IF(AND($P47="Derived",$V47="觀測"),1,0) -> 0 | AB47: CC 初評
A48: SRC_ANT_044 | B48: gm_2025_incl_free | C48: A | D48: 2025 毛利率（含免費用戶推論成本） | E48: 0.38 | H48: 比例 | I48: 2025 | K48: 未明 | L48: 華爾街見聞（經 Longbridge 轉載，引 The Information） | M48: https://longbridge.com/en/news/273327693 | N48: 2026-01-22 | O48: 2026-10-08 | P48: Interested-party | Q48: Anthropic（投資人簡報） | R48: 2 | S48: 利害關係方 | T48: Anthropic（投資人簡報） | U48: 二手 | V48: 觀測 | W48: 原文：including free users margin 'would further drop to about 38%' | X48: =IF(AND(COUNT($E48:$G48)=0,LEFT($H48,2)<>"定性",LEFT($H48,2)<>"文字",LEFT($H48,2)<>"日期"),1,0) -> 0 | Y48: =IF(OR($L48="",$M48=""),1,0) -> 0 | Z48: =IF(AND(ISNUMBER($E48),ISNUMBER($F48)),IF($F48>$E48,1,0),0)+IF(AND(ISNUMBER($E48),ISNUMBER($G48)),IF($E48>$G48,1,0),0)+IF(AND(ISNUMBER($F48),ISNUMBER($G48)),IF($F48>$G48,1,0),0) -> 0 | AA48: =IF(AND($P48="Derived",$V48="觀測"),1,0) -> 0 | AB48: CC 初評
A49: SRC_ANT_045 | B49: cost_inference_overrun_2025 | C49: A | D49: 2025 推論成本超出原預測幅度 | E49: 0.23 | H49: 比例 | I49: 2025 | K49: 未明 | L49: 華爾街見聞（經 Longbridge 轉載，引 The Information） | M49: https://longbridge.com/en/news/273327693 | N49: 2026-01-22 | O49: 2026-10-08 | P49: Interested-party | Q49: Anthropic（投資人簡報） | R49: 2 | S49: 利害關係方 | T49: Anthropic（投資人簡報） | U49: 二手 | V49: 觀測 | W49: 原文：inference costs '23% higher than expected'；推論成本金額未揭露 | X49: =IF(AND(COUNT($E49:$G49)=0,LEFT($H49,2)<>"定性",LEFT($H49,2)<>"文字",LEFT($H49,2)<>"日期"),1,0) -> 0 | Y49: =IF(OR($L49="",$M49=""),1,0) -> 0 | Z49: =IF(AND(ISNUMBER($E49),ISNUMBER($F49)),IF($F49>$E49,1,0),0)+IF(AND(ISNUMBER($E49),ISNUMBER($G49)),IF($E49>$G49,1,0),0)+IF(AND(ISNUMBER($F49),ISNUMBER($G49)),IF($F49>$G49,1,0),0) -> 0 | AA49: =IF(AND($P49="Derived",$V49="觀測"),1,0) -> 0 | AB49: CC 初評
A50: SRC_ANT_046 | B50: cost_training_2025 | C50: A | D50: 2025 訓練成本（預測） | E50: 4.1 | H50: $B/年 | I50: 2025 | K50: 未明 | L50: 華爾街見聞（經 Longbridge 轉載，引 The Information） | M50: https://longbridge.com/en/news/273327693 | N50: 2026-01-22 | O50: 2026-10-08 | P50: Interested-party | Q50: Anthropic（投資人簡報） | R50: 2 | S50: 利害關係方 | T50: Anthropic（投資人簡報） | U50: 二手 | V50: 觀測 | W50: 原文：'training costs to be about $4.1 billion in 2025' | X50: =IF(AND(COUNT($E50:$G50)=0,LEFT($H50,2)<>"定性",LEFT($H50,2)<>"文字",LEFT($H50,2)<>"日期"),1,0) -> 0 | Y50: =IF(OR($L50="",$M50=""),1,0) -> 0 | Z50: =IF(AND(ISNUMBER($E50),ISNUMBER($F50)),IF($F50>$E50,1,0),0)+IF(AND(ISNUMBER($E50),ISNUMBER($G50)),IF($E50>$G50,1,0),0)+IF(AND(ISNUMBER($F50),ISNUMBER($G50)),IF($F50>$G50,1,0),0) -> 0 | AA50: =IF(AND($P50="Derived",$V50="觀測"),1,0) -> 0 | AB50: CC 初評
A51: SRC_ANT_047 | B51: rev_2025_projected_info | C51: A | D51: 2025 營收（公司 2025-12 預測） | E51: 4.5 | H51: $B/年 | I51: 2025 | K51: 未明 | L51: 華爾街見聞（經 Longbridge 轉載，引 The Information） | M51: https://longbridge.com/en/news/273327693 | N51: 2026-01-22 | O51: 2026-10-08 | P51: Interested-party | Q51: Anthropic（投資人簡報） | R51: 2 | S51: 利害關係方 | T51: Anthropic（投資人簡報） | U51: 二手 | V51: 觀測 | W51: 原文：'expects its revenue to reach $4.5 billion in 2025'；與招股書 $4.59B 一致 | X51: =IF(AND(COUNT($E51:$G51)=0,LEFT($H51,2)<>"定性",LEFT($H51,2)<>"文字",LEFT($H51,2)<>"日期"),1,0) -> 0 | Y51: =IF(OR($L51="",$M51=""),1,0) -> 0 | Z51: =IF(AND(ISNUMBER($E51),ISNUMBER($F51)),IF($F51>$E51,1,0),0)+IF(AND(ISNUMBER($E51),ISNUMBER($G51)),IF($E51>$G51,1,0),0)+IF(AND(ISNUMBER($F51),ISNUMBER($G51)),IF($F51>$G51,1,0),0) -> 0 | AA51: =IF(AND($P51="Derived",$V51="觀測"),1,0) -> 0 | AB51: CC 初評
A52: SRC_ANT_048 | B52: rev_2025_recognized_c | C52: A | D52: 2025 營收（媒體引述 Amodei 達沃斯說法） | E52: 10 | H52: $B/年 | I52: 2025 | K52: 未明 | L52: WebProNews〈Anthropic Slashes 2025 Margin Forecast to 40% Amid AI Cost Surge〉 | M52: https://www.webpronews.com/anthropic-slashes-2025-margin-forecast-to-40-amid-ai-cost-surge/ | N52: 2026-01-22 | O52: 2026-10-08 | P52: Interested-party | Q52: Anthropic（執行長公開談話；市場地位誘因） | R52: 未評 | S52: 利害關係方 | T52: Anthropic（執行長公開談話；市場地位誘因） | U52: 未評 | V52: 觀測 | W52: 原文：2025 'about $10 billion'（引 Amodei 於 WEF）。與招股書 $4.6B 矛盾，應為 run-rate 誤植；不採用 | X52: =IF(AND(COUNT($E52:$G52)=0,LEFT($H52,2)<>"定性",LEFT($H52,2)<>"文字",LEFT($H52,2)<>"日期"),1,0) -> 0 | Y52: =IF(OR($L52="",$M52=""),1,0) -> 0 | Z52: =IF(AND(ISNUMBER($E52),ISNUMBER($F52)),IF($F52>$E52,1,0),0)+IF(AND(ISNUMBER($E52),ISNUMBER($G52)),IF($E52>$G52,1,0),0)+IF(AND(ISNUMBER($F52),ISNUMBER($G52)),IF($F52>$G52,1,0),0) -> 0 | AA52: =IF(AND($P52="Derived",$V52="觀測"),1,0) -> 0 | AB52: CC 初評
A53: SRC_ANT_049 | B53: gm_2026_pre_share | C53: A | D53: 毛利率（未扣通路分潤前） | E53: 0.8 | F53: 0.8 | H53: 比例 | I53: 2026-Q3 | K53: 總額 | L53: Reuters（引 FT）〈Anthropic tells investors it will be profitable for second straight quarter〉（The Star 轉載） | M53: https://www.thestar.com.my/tech/tech-news/2026/09/14/anthropic-tells-investors-it-will-be-profitable-for-second-straight-quarter-ft-reports | N53: 2026-09-13 | O53: 2026-10-08 | P53: Interested-party | Q53: Anthropic（告知投資人；IPO 誘因） | R53: 2 | S53: 利害關係方 | T53: Anthropic（告知投資人；IPO 誘因） | U53: 二手 | V53: 觀測 | W53: 原文：'gross margins are above 80% before accounting for revenue shared with distribution partners'（下限） | X53: =IF(AND(COUNT($E53:$G53)=0,LEFT($H53,2)<>"定性",LEFT($H53,2)<>"文字",LEFT($H53,2)<>"日期"),1,0) -> 0 | Y53: =IF(OR($L53="",$M53=""),1,0) -> 0 | Z53: =IF(AND(ISNUMBER($E53),ISNUMBER($F53)),IF($F53>$E53,1,0),0)+IF(AND(ISNUMBER($E53),ISNUMBER($G53)),IF($E53>$G53,1,0),0)+IF(AND(ISNUMBER($F53),ISNUMBER($G53)),IF($F53>$G53,1,0),0) -> 0 | AA53: =IF(AND($P53="Derived",$V53="觀測"),1,0) -> 0 | AB53: CC 初評
A54: SRC_ANT_050 | B54: gm_2026_pitchbook | C54: A | D54: 2026 毛利率（分析師估計） | E54: 0.44 | F54: 0.4 | G54: 0.5 | H54: 比例 | I54: 2026 | K54: 未明 | L54: PitchBook〈Anthropic's gross margin is the most important number in tech〉（Yahoo Finance 轉載） | M54: https://finance.yahoo.com/markets/stocks/articles/anthropics-gross-margin-most-important-070500338.html | N54: 2026-06-10 | O54: 2026-10-08 | P54: Analogy | R54: 2 | S54: 第三方估計 | T54: 第三方估計；非公司揭露，作類比或區間 | U54: 二手 | V54: 觀測 | W54: 原文：'on track for gross margins of roughly 44%'；估值隱含 '40% to 50% gross margins' | X54: =IF(AND(COUNT($E54:$G54)=0,LEFT($H54,2)<>"定性",LEFT($H54,2)<>"文字",LEFT($H54,2)<>"日期"),1,0) -> 0 | Y54: =IF(OR($L54="",$M54=""),1,0) -> 0 | Z54: =IF(AND(ISNUMBER($E54),ISNUMBER($F54)),IF($F54>$E54,1,0),0)+IF(AND(ISNUMBER($E54),ISNUMBER($G54)),IF($E54>$G54,1,0),0)+IF(AND(ISNUMBER($F54),ISNUMBER($G54)),IF($F54>$G54,1,0),0) -> 0 | AA54: =IF(AND($P54="Derived",$V54="觀測"),1,0) -> 0 | AB54: CC 初評
A55: SRC_ANT_051 | B55: cost_compute_per_rev_2026_q1 | C55: A | D55: 每 $1 營收之算力支出 | E55: 0.71 | H55: $/每$營收 | I55: 2026-Q1 | K55: 未明 | L55: PYMNTS〈Anthropic On Track for First Operating Profit as Revenue Surges〉（引 WSJ） | M55: https://www.pymnts.com/?p=3752527 | N55: 2026-05-20 | O55: 2026-10-08 | P55: Interested-party | Q55: Anthropic（WSJ 取得之投資人預測） | R55: 2 | S55: 利害關係方 | T55: Anthropic（WSJ 取得之投資人預測） | U55: 二手 | V55: 觀測 | W55: 原文：'spent 71 cents on compute for every dollar of revenue'；Q2 預期 '56 cents' | X55: =IF(AND(COUNT($E55:$G55)=0,LEFT($H55,2)<>"定性",LEFT($H55,2)<>"文字",LEFT($H55,2)<>"日期"),1,0) -> 0 | Y55: =IF(OR($L55="",$M55=""),1,0) -> 0 | Z55: =IF(AND(ISNUMBER($E55),ISNUMBER($F55)),IF($F55>$E55,1,0),0)+IF(AND(ISNUMBER($E55),ISNUMBER($G55)),IF($E55>$G55,1,0),0)+IF(AND(ISNUMBER($F55),ISNUMBER($G55)),IF($F55>$G55,1,0),0) -> 0 | AA55: =IF(AND($P55="Derived",$V55="觀測"),1,0) -> 0 | AB55: CC 初評
A56: SRC_ANT_052 | B56: cost_compute_per_rev_2026_q2 | C56: A | D56: 每 $1 營收之算力支出（預測） | E56: 0.56 | H56: $/每$營收 | I56: 2026-Q2 | K56: 未明 | L56: PYMNTS（引 WSJ） | M56: https://www.pymnts.com/?p=3752527 | N56: 2026-05-20 | O56: 2026-10-08 | P56: Interested-party | Q56: Anthropic（投資人預測） | R56: 2 | S56: 利害關係方 | T56: Anthropic（投資人預測） | U56: 二手 | V56: 觀測 | W56: 原文：'That ratio is expected to fall to 56 cents in the current quarter' | X56: =IF(AND(COUNT($E56:$G56)=0,LEFT($H56,2)<>"定性",LEFT($H56,2)<>"文字",LEFT($H56,2)<>"日期"),1,0) -> 0 | Y56: =IF(OR($L56="",$M56=""),1,0) -> 0 | Z56: =IF(AND(ISNUMBER($E56),ISNUMBER($F56)),IF($F56>$E56,1,0),0)+IF(AND(ISNUMBER($E56),ISNUMBER($G56)),IF($E56>$G56,1,0),0)+IF(AND(ISNUMBER($F56),ISNUMBER($G56)),IF($F56>$G56,1,0),0) -> 0 | AA56: =IF(AND($P56="Derived",$V56="觀測"),1,0) -> 0 | AB56: CC 初評
A57: SRC_ANT_053 | B57: rev_2026_q1_b | C57: A | D57: 2026 Q1 認列營收 | E57: 4.8 | H57: $B/季 | I57: 2026-Q1 | K57: 總額 | L57: PYMNTS（引 WSJ） | M57: https://www.pymnts.com/?p=3752527 | N57: 2026-05-20 | O57: 2026-10-08 | P57: Interested-party | Q57: Anthropic（投資人預測文件） | R57: 2 | S57: 利害關係方 | T57: Anthropic（投資人預測文件） | U57: 二手 | V57: 觀測 | W57: 原文：'up 130% from $4.8 billion in the first quarter'。與 Bloomberg $4.73B 小幅差異（四捨五入） | X57: =IF(AND(COUNT($E57:$G57)=0,LEFT($H57,2)<>"定性",LEFT($H57,2)<>"文字",LEFT($H57,2)<>"日期"),1,0) -> 0 | Y57: =IF(OR($L57="",$M57=""),1,0) -> 0 | Z57: =IF(AND(ISNUMBER($E57),ISNUMBER($F57)),IF($F57>$E57,1,0),0)+IF(AND(ISNUMBER($E57),ISNUMBER($G57)),IF($E57>$G57,1,0),0)+IF(AND(ISNUMBER($F57),ISNUMBER($G57)),IF($F57>$G57,1,0),0) -> 0 | AA57: =IF(AND($P57="Derived",$V57="觀測"),1,0) -> 0 | AB57: CC 初評
A58: SRC_ANT_054 | B58: rev_2026_q2_projected | C58: A | D58: 2026 Q2 營收（季前預測） | E58: 10.9 | H58: $B/季 | I58: 2026-Q2 | K58: 總額 | L58: PYMNTS（引 WSJ） | M58: https://www.pymnts.com/?p=3752527 | N58: 2026-05-20 | O58: 2026-10-08 | P58: Interested-party | Q58: Anthropic（投資人預測） | R58: 2 | S58: 利害關係方 | T58: Anthropic（投資人預測） | U58: 二手 | V58: 觀測 | W58: 原文：'projects $10.9 billion in revenue for the June quarter'；營業利益預測 '$559 million'；實際 >$11.5B | X58: =IF(AND(COUNT($E58:$G58)=0,LEFT($H58,2)<>"定性",LEFT($H58,2)<>"文字",LEFT($H58,2)<>"日期"),1,0) -> 0 | Y58: =IF(OR($L58="",$M58=""),1,0) -> 0 | Z58: =IF(AND(ISNUMBER($E58),ISNUMBER($F58)),IF($F58>$E58,1,0),0)+IF(AND(ISNUMBER($E58),ISNUMBER($G58)),IF($E58>$G58,1,0),0)+IF(AND(ISNUMBER($F58),ISNUMBER($G58)),IF($F58>$G58,1,0),0) -> 0 | AA58: =IF(AND($P58="Derived",$V58="觀測"),1,0) -> 0 | AB58: CC 初評
A59: SRC_ANT_055 | B59: cc_runrate_2025_08 | C59: A | D59: Claude Code 年化營收（run-rate） | E59: 0.5 | H59: $B/年 | I59: 2025-08 | L59: Anthropic 新聞稿〈Series F〉 | M59: https://www.anthropic.com/news/anthropic-raises-series-f-at-usd183b-post-money-valuation | N59: 2025-09-02 | O59: 2026-10-08 | P59: Interested-party | Q59: Anthropic（募資、招募、市場地位誘因） | R59: 1 | S59: 利害關係方 | T59: Anthropic（募資、招募、市場地位誘因） | U59: 一手 | V59: 觀測 | W59: 原文：Claude Code 'already generating over $500 million in run-rate revenue'；用量 3 個月成長 >10x（下限） | X59: =IF(AND(COUNT($E59:$G59)=0,LEFT($H59,2)<>"定性",LEFT($H59,2)<>"文字",LEFT($H59,2)<>"日期"),1,0) -> 0 | Y59: =IF(OR($L59="",$M59=""),1,0) -> 0 | Z59: =IF(AND(ISNUMBER($E59),ISNUMBER($F59)),IF($F59>$E59,1,0),0)+IF(AND(ISNUMBER($E59),ISNUMBER($G59)),IF($E59>$G59,1,0),0)+IF(AND(ISNUMBER($F59),ISNUMBER($G59)),IF($F59>$G59,1,0),0) -> 0 | AA59: =IF(AND($P59="Derived",$V59="觀測"),1,0) -> 0 | AB59: CC 初評
A60: SRC_ANT_056 | B60: cc_runrate_2025_10 | C60: A | D60: Claude Code 年化營收（run-rate） | E60: 1 | G60: 1 | H60: $B/年 | I60: 2025-10 | L60: Reuters 獨家〈Anthropic aims to nearly triple annualized revenue in 2026〉 | M60: https://finance.yahoo.com/news/exclusive-anthropic-aims-nearly-triple-170234463.html | N60: 2025-10-15 | O60: 2026-10-08 | P60: Interested-party | Q60: Anthropic（募資、招募、市場地位誘因） | R60: 2 | S60: 利害關係方 | T60: Anthropic（募資、招募、市場地位誘因） | U60: 二手 | V60: 觀測 | W60: 原文：Claude Code 'nearly $1 billion' annualized revenue run rate（接近） | X60: =IF(AND(COUNT($E60:$G60)=0,LEFT($H60,2)<>"定性",LEFT($H60,2)<>"文字",LEFT($H60,2)<>"日期"),1,0) -> 0 | Y60: =IF(OR($L60="",$M60=""),1,0) -> 0 | Z60: =IF(AND(ISNUMBER($E60),ISNUMBER($F60)),IF($F60>$E60,1,0),0)+IF(AND(ISNUMBER($E60),ISNUMBER($G60)),IF($E60>$G60,1,0),0)+IF(AND(ISNUMBER($F60),ISNUMBER($G60)),IF($F60>$G60,1,0),0) -> 0 | AA60: =IF(AND($P60="Derived",$V60="觀測"),1,0) -> 0 | AB60: CC 初評
A61: SRC_ANT_057 | B61: cc_runrate_2025_12 | C61: A | D61: Claude Code 年化營收（run-rate） | E61: 1 | H61: $B/年 | I61: 2025-11/12 | L61: Anthropic 新聞稿〈Anthropic acquires Bun as Claude Code reaches $1B milestone〉 | M61: https://www.anthropic.com/news/anthropic-acquires-bun-as-claude-code-reaches-usd1b-milestone | N61: 2025-12-03 | O61: 2026-10-08 | P61: Interested-party | Q61: Anthropic（募資、招募、市場地位誘因） | R61: 1 | S61: 利害關係方 | T61: Anthropic（募資、招募、市場地位誘因） | U61: 一手 | V61: 觀測 | W61: 原文：'it reached $1 billion in run-rate revenue'（公開上市約 6 個月後） | X61: =IF(AND(COUNT($E61:$G61)=0,LEFT($H61,2)<>"定性",LEFT($H61,2)<>"文字",LEFT($H61,2)<>"日期"),1,0) -> 0 | Y61: =IF(OR($L61="",$M61=""),1,0) -> 0 | Z61: =IF(AND(ISNUMBER($E61),ISNUMBER($F61)),IF($F61>$E61,1,0),0)+IF(AND(ISNUMBER($E61),ISNUMBER($G61)),IF($E61>$G61,1,0),0)+IF(AND(ISNUMBER($F61),ISNUMBER($G61)),IF($F61>$G61,1,0),0) -> 0 | AA61: =IF(AND($P61="Derived",$V61="觀測"),1,0) -> 0 | AB61: CC 初評
A62: SRC_ANT_058 | B62: cc_runrate_2026_02 | C62: A | D62: Claude Code 年化營收（run-rate） | E62: 2.5 | H62: $B/年 | I62: 2026-02 | L62: Anthropic 新聞稿〈Series G〉 | M62: https://www.anthropic.com/news/anthropic-raises-30-billion-series-g-funding-380-billion-post-money-valuation | N62: 2026-02-12 | O62: 2026-10-08 | P62: Interested-party | Q62: Anthropic（募資、招募、市場地位誘因） | R62: 1 | S62: 利害關係方 | T62: Anthropic（募資、招募、市場地位誘因） | U62: 一手 | V62: 觀測 | W62: 原文：'Claude Code's run-rate revenue has grown to over $2.5 billion'；年初以來翻倍以上 | X62: =IF(AND(COUNT($E62:$G62)=0,LEFT($H62,2)<>"定性",LEFT($H62,2)<>"文字",LEFT($H62,2)<>"日期"),1,0) -> 0 | Y62: =IF(OR($L62="",$M62=""),1,0) -> 0 | Z62: =IF(AND(ISNUMBER($E62),ISNUMBER($F62)),IF($F62>$E62,1,0),0)+IF(AND(ISNUMBER($E62),ISNUMBER($G62)),IF($E62>$G62,1,0),0)+IF(AND(ISNUMBER($F62),ISNUMBER($G62)),IF($F62>$G62,1,0),0) -> 0 | AA62: =IF(AND($P62="Derived",$V62="觀測"),1,0) -> 0 | AB62: CC 初評
A63: SRC_ANT_059 | B63: cc_enterprise_share_2026_02 | C63: A | D63: 企業用戶占 Claude Code 營收比例 | E63: 0.5 | F63: 0.5 | H63: 比例 | I63: 2026-02 | L63: Anthropic 新聞稿〈Series G〉 | M63: https://www.anthropic.com/news/anthropic-raises-30-billion-series-g-funding-380-billion-post-money-valuation | N63: 2026-02-12 | O63: 2026-10-08 | P63: Interested-party | Q63: Anthropic（募資、招募、市場地位誘因） | R63: 1 | S63: 利害關係方 | T63: Anthropic（募資、招募、市場地位誘因） | U63: 一手 | V63: 觀測 | W63: 原文：'enterprise use has grown to represent over half of all Claude Code revenue'（下限） | X63: =IF(AND(COUNT($E63:$G63)=0,LEFT($H63,2)<>"定性",LEFT($H63,2)<>"文字",LEFT($H63,2)<>"日期"),1,0) -> 0 | Y63: =IF(OR($L63="",$M63=""),1,0) -> 0 | Z63: =IF(AND(ISNUMBER($E63),ISNUMBER($F63)),IF($F63>$E63,1,0),0)+IF(AND(ISNUMBER($E63),ISNUMBER($G63)),IF($E63>$G63,1,0),0)+IF(AND(ISNUMBER($F63),ISNUMBER($G63)),IF($F63>$G63,1,0),0) -> 0 | AA63: =IF(AND($P63="Derived",$V63="觀測"),1,0) -> 0 | AB63: CC 初評
A64: SRC_ANT_060 | B64: cc_runrate_2026_05 | C64: A | D64: Claude Code 年化營收（第三方估計） | E64: 8 | F64: 5 | G64: 10 | H64: $B/年 | I64: 2026-05 | L64: FourWeekMBA〈Claude Code Scaled from $1B to $8B Annualized Run-Rate in Six Months〉（稱引 Sacra） | M64: https://fourweekmba.com/ai-claude-code-run-rate-agentic-layer/ | N64: 2026-05 | O64: 2026-10-08 | P64: Analogy | R64: 2 | S64: 第三方估計 | T64: 第三方估計；非公司揭露，作類比或區間 | U64: 二手 | V64: 觀測 | W64: 原文：'Run-rate reaches approximately $8 billion'（2026-05）。Sacra 頁面本身未見此數；無一手來源，僅供參考 | X64: =IF(AND(COUNT($E64:$G64)=0,LEFT($H64,2)<>"定性",LEFT($H64,2)<>"文字",LEFT($H64,2)<>"日期"),1,0) -> 0 | Y64: =IF(OR($L64="",$M64=""),1,0) -> 0 | Z64: =IF(AND(ISNUMBER($E64),ISNUMBER($F64)),IF($F64>$E64,1,0),0)+IF(AND(ISNUMBER($E64),ISNUMBER($G64)),IF($E64>$G64,1,0),0)+IF(AND(ISNUMBER($F64),ISNUMBER($G64)),IF($F64>$G64,1,0),0) -> 0 | AA64: =IF(AND($P64="Derived",$V64="觀測"),1,0) -> 0 | AB64: CC 初評
A65: SRC_ANT_061 | B65: rev_mix_api_share_sacra | C65: A | D65: API（按 token 計價）占營收比例（第三方估計） | E65: 0.725 | F65: 0.7 | G65: 0.75 | H65: 比例 | I65: 2026 | L65: Sacra〈Anthropic revenue, valuation & funding〉 | M65: https://sacra.com/c/anthropic/ | N65: 2026-08 | O65: 2026-10-08 | P65: Analogy | R65: 2 | S65: 第三方估計 | T65: 第三方估計；非公司揭露，作類比或區間 | U65: 二手 | V65: 觀測 | W65: 原文：API 'Approximately 70–75%'；訂閱 '10–15%'。招股書 2025 用量計價約 83%、訂閱 17% | X65: =IF(AND(COUNT($E65:$G65)=0,LEFT($H65,2)<>"定性",LEFT($H65,2)<>"文字",LEFT($H65,2)<>"日期"),1,0) -> 0 | Y65: =IF(OR($L65="",$M65=""),1,0) -> 0 | Z65: =IF(AND(ISNUMBER($E65),ISNUMBER($F65)),IF($F65>$E65,1,0),0)+IF(AND(ISNUMBER($E65),ISNUMBER($G65)),IF($E65>$G65,1,0),0)+IF(AND(ISNUMBER($F65),ISNUMBER($G65)),IF($F65>$G65,1,0),0) -> 0 | AA65: =IF(AND($P65="Derived",$V65="觀測"),1,0) -> 0 | AB65: CC 初評
A66: SRC_ANT_062 | B66: rev_mix_subscription_share_sacra | C66: A | D66: 訂閱占營收比例（第三方估計） | E66: 0.125 | F66: 0.1 | G66: 0.15 | H66: 比例 | I66: 2026 | L66: Sacra | M66: https://sacra.com/c/anthropic/ | N66: 2026-08 | O66: 2026-10-08 | P66: Analogy | R66: 2 | S66: 第三方估計 | T66: 第三方估計；非公司揭露，作類比或區間 | U66: 二手 | V66: 觀測 | W66: 原文：subscriptions '10–15% of total revenue' | X66: =IF(AND(COUNT($E66:$G66)=0,LEFT($H66,2)<>"定性",LEFT($H66,2)<>"文字",LEFT($H66,2)<>"日期"),1,0) -> 0 | Y66: =IF(OR($L66="",$M66=""),1,0) -> 0 | Z66: =IF(AND(ISNUMBER($E66),ISNUMBER($F66)),IF($F66>$E66,1,0),0)+IF(AND(ISNUMBER($E66),ISNUMBER($G66)),IF($E66>$G66,1,0),0)+IF(AND(ISNUMBER($F66),ISNUMBER($G66)),IF($F66>$G66,1,0),0) -> 0 | AA66: =IF(AND($P66="Derived",$V66="觀測"),1,0) -> 0 | AB66: CC 初評
A67: SRC_ANT_063 | B67: rev_mix_consumer_share_2025_jaipuria | C67: A | D67: 消費者訂閱占營收比例（分析師估計） | E67: 0.15 | F67: 0.1 | G67: 0.2 | H67: 比例 | I67: 2025 | L67: SaaStr〈Anthropic May Never Catch OpenAI. But It's Already 40% as Big.〉（引 Tanay Jaipuria） | M67: https://www.saastr.com/anthropic-may-never-catch-openai-but-its-already-40-as-big/ | N67: 2025-07-11 | O67: 2026-10-08 | P67: Analogy | R67: 2 | S67: 第三方估計 | T67: 第三方估計；非公司揭露，作類比或區間 | U67: 二手 | V67: 觀測 | W67: 約 15% 消費者訂閱、85% API（分析師估計，無日期） | X67: =IF(AND(COUNT($E67:$G67)=0,LEFT($H67,2)<>"定性",LEFT($H67,2)<>"文字",LEFT($H67,2)<>"日期"),1,0) -> 0 | Y67: =IF(OR($L67="",$M67=""),1,0) -> 0 | Z67: =IF(AND(ISNUMBER($E67),ISNUMBER($F67)),IF($F67>$E67,1,0),0)+IF(AND(ISNUMBER($E67),ISNUMBER($G67)),IF($E67>$G67,1,0),0)+IF(AND(ISNUMBER($F67),ISNUMBER($G67)),IF($F67>$G67,1,0),0) -> 0 | AA67: =IF(AND($P67="Derived",$V67="觀測"),1,0) -> 0 | AB67: CC 初評
A68: SRC_ANT_064 | B68: rev_receivables_2025 | C68: A | D68: 2025 年底應收帳款（客戶未付帳單） | E68: 0.909 | H68: $B | I68: 2025-12-31 | J68: 46022 | K68: 總額 | L68: Reuters（經 Khaleej Times 轉載） | M68: https://www.khaleejtimes.com/business/anthropic-ipo-prospectus-lays-bare-deep-dependence-on-big-tech-partners?amp=1 | N68: 2026-09-30 | O68: 2026-10-08 | P68: Interested-party | Q68: Anthropic（外流招股書） | R68: 2 | S68: 利害關係方 | T68: Anthropic（外流招股書） | U68: 二手 | V68: 觀測 | W68: 原文：60% of the '$909 million in customer bills outstanding' 由第三方收款（2024 年 42%） | X68: =IF(AND(COUNT($E68:$G68)=0,LEFT($H68,2)<>"定性",LEFT($H68,2)<>"文字",LEFT($H68,2)<>"日期"),1,0) -> 0 | Y68: =IF(OR($L68="",$M68=""),1,0) -> 0 | Z68: =IF(AND(ISNUMBER($E68),ISNUMBER($F68)),IF($F68>$E68,1,0),0)+IF(AND(ISNUMBER($E68),ISNUMBER($G68)),IF($E68>$G68,1,0),0)+IF(AND(ISNUMBER($F68),ISNUMBER($G68)),IF($F68>$G68,1,0),0) -> 0 | AA68: =IF(AND($P68="Derived",$V68="觀測"),1,0) -> 0 | AB68: CC 初評
A69: SRC_ANT_065 | B69: price_claude3_opus_in | C69: B | D69: API 牌價 Claude 3 Opus 輸入（上市 2024-03-04） | E69: 15 | H69: $/百萬token | I69: 2024-03-04 | J69: 45355 | L69: Anthropic〈Introducing the next generation of Claude〉 | M69: https://www.anthropic.com/news/claude-3-family | N69: 2024-03-04 | O69: 2026-10-08 | P69: Interested-party | Q69: Anthropic（官方牌價；市場地位誘因） | R69: 1 | S69: 利害關係方 | T69: Anthropic（官方牌價；市場地位誘因） | U69: 一手 | V69: 觀測 | W69: 價格表：'$15 | $75' | X69: =IF(AND(COUNT($E69:$G69)=0,LEFT($H69,2)<>"定性",LEFT($H69,2)<>"文字",LEFT($H69,2)<>"日期"),1,0) -> 0 | Y69: =IF(OR($L69="",$M69=""),1,0) -> 0 | Z69: =IF(AND(ISNUMBER($E69),ISNUMBER($F69)),IF($F69>$E69,1,0),0)+IF(AND(ISNUMBER($E69),ISNUMBER($G69)),IF($E69>$G69,1,0),0)+IF(AND(ISNUMBER($F69),ISNUMBER($G69)),IF($F69>$G69,1,0),0) -> 0 | AA69: =IF(AND($P69="Derived",$V69="觀測"),1,0) -> 0 | AB69: CC 初評
A70: SRC_ANT_066 | B70: price_claude3_opus_out | C70: B | D70: API 牌價 Claude 3 Opus 輸出（上市 2024-03-04） | E70: 75 | H70: $/百萬token | I70: 2024-03-04 | J70: 45355 | L70: Anthropic〈Introducing the next generation of Claude〉 | M70: https://www.anthropic.com/news/claude-3-family | N70: 2024-03-04 | O70: 2026-10-08 | P70: Interested-party | Q70: Anthropic（官方牌價；市場地位誘因） | R70: 1 | S70: 利害關係方 | T70: Anthropic（官方牌價；市場地位誘因） | U70: 一手 | V70: 觀測 | W70: 價格表：'$15 | $75' | X70: =IF(AND(COUNT($E70:$G70)=0,LEFT($H70,2)<>"定性",LEFT($H70,2)<>"文字",LEFT($H70,2)<>"日期"),1,0) -> 0 | Y70: =IF(OR($L70="",$M70=""),1,0) -> 0 | Z70: =IF(AND(ISNUMBER($E70),ISNUMBER($F70)),IF($F70>$E70,1,0),0)+IF(AND(ISNUMBER($E70),ISNUMBER($G70)),IF($E70>$G70,1,0),0)+IF(AND(ISNUMBER($F70),ISNUMBER($G70)),IF($F70>$G70,1,0),0) -> 0 | AA70: =IF(AND($P70="Derived",$V70="觀測"),1,0) -> 0 | AB70: CC 初評
A71: SRC_ANT_067 | B71: price_claude3_sonnet_in | C71: B | D71: API 牌價 Claude 3 Sonnet 輸入（上市 2024-03-04） | E71: 3 | H71: $/百萬token | I71: 2024-03-04 | J71: 45355 | L71: Anthropic〈Introducing the next generation of Claude〉 | M71: https://www.anthropic.com/news/claude-3-family | N71: 2024-03-04 | O71: 2026-10-08 | P71: Interested-party | Q71: Anthropic（官方牌價；市場地位誘因） | R71: 1 | S71: 利害關係方 | T71: Anthropic（官方牌價；市場地位誘因） | U71: 一手 | V71: 觀測 | W71: 價格表：'$3 | $15' | X71: =IF(AND(COUNT($E71:$G71)=0,LEFT($H71,2)<>"定性",LEFT($H71,2)<>"文字",LEFT($H71,2)<>"日期"),1,0) -> 0 | Y71: =IF(OR($L71="",$M71=""),1,0) -> 0 | Z71: =IF(AND(ISNUMBER($E71),ISNUMBER($F71)),IF($F71>$E71,1,0),0)+IF(AND(ISNUMBER($E71),ISNUMBER($G71)),IF($E71>$G71,1,0),0)+IF(AND(ISNUMBER($F71),ISNUMBER($G71)),IF($F71>$G71,1,0),0) -> 0 | AA71: =IF(AND($P71="Derived",$V71="觀測"),1,0) -> 0 | AB71: CC 初評
A72: SRC_ANT_068 | B72: price_claude3_sonnet_out | C72: B | D72: API 牌價 Claude 3 Sonnet 輸出（上市 2024-03-04） | E72: 15 | H72: $/百萬token | I72: 2024-03-04 | J72: 45355 | L72: Anthropic〈Introducing the next generation of Claude〉 | M72: https://www.anthropic.com/news/claude-3-family | N72: 2024-03-04 | O72: 2026-10-08 | P72: Interested-party | Q72: Anthropic（官方牌價；市場地位誘因） | R72: 1 | S72: 利害關係方 | T72: Anthropic（官方牌價；市場地位誘因） | U72: 一手 | V72: 觀測 | W72: 價格表：'$3 | $15' | X72: =IF(AND(COUNT($E72:$G72)=0,LEFT($H72,2)<>"定性",LEFT($H72,2)<>"文字",LEFT($H72,2)<>"日期"),1,0) -> 0 | Y72: =IF(OR($L72="",$M72=""),1,0) -> 0 | Z72: =IF(AND(ISNUMBER($E72),ISNUMBER($F72)),IF($F72>$E72,1,0),0)+IF(AND(ISNUMBER($E72),ISNUMBER($G72)),IF($E72>$G72,1,0),0)+IF(AND(ISNUMBER($F72),ISNUMBER($G72)),IF($F72>$G72,1,0),0) -> 0 | AA72: =IF(AND($P72="Derived",$V72="觀測"),1,0) -> 0 | AB72: CC 初評
A73: SRC_ANT_069 | B73: price_claude3_haiku_in | C73: B | D73: API 牌價 Claude 3 Haiku 輸入（上市 2024-03-04） | E73: 0.25 | H73: $/百萬token | I73: 2024-03-04 | J73: 45355 | L73: Anthropic〈Introducing the next generation of Claude〉 | M73: https://www.anthropic.com/news/claude-3-family | N73: 2024-03-04 | O73: 2026-10-08 | P73: Interested-party | Q73: Anthropic（官方牌價；市場地位誘因） | R73: 1 | S73: 利害關係方 | T73: Anthropic（官方牌價；市場地位誘因） | U73: 一手 | V73: 觀測 | W73: 價格表：'$0.25 | $1.25' | X73: =IF(AND(COUNT($E73:$G73)=0,LEFT($H73,2)<>"定性",LEFT($H73,2)<>"文字",LEFT($H73,2)<>"日期"),1,0) -> 0 | Y73: =IF(OR($L73="",$M73=""),1,0) -> 0 | Z73: =IF(AND(ISNUMBER($E73),ISNUMBER($F73)),IF($F73>$E73,1,0),0)+IF(AND(ISNUMBER($E73),ISNUMBER($G73)),IF($E73>$G73,1,0),0)+IF(AND(ISNUMBER($F73),ISNUMBER($G73)),IF($F73>$G73,1,0),0) -> 0 | AA73: =IF(AND($P73="Derived",$V73="觀測"),1,0) -> 0 | AB73: CC 初評
A74: SRC_ANT_070 | B74: price_claude3_haiku_out | C74: B | D74: API 牌價 Claude 3 Haiku 輸出（上市 2024-03-04） | E74: 1.25 | H74: $/百萬token | I74: 2024-03-04 | J74: 45355 | L74: Anthropic〈Introducing the next generation of Claude〉 | M74: https://www.anthropic.com/news/claude-3-family | N74: 2024-03-04 | O74: 2026-10-08 | P74: Interested-party | Q74: Anthropic（官方牌價；市場地位誘因） | R74: 1 | S74: 利害關係方 | T74: Anthropic（官方牌價；市場地位誘因） | U74: 一手 | V74: 觀測 | W74: 價格表：'$0.25 | $1.25' | X74: =IF(AND(COUNT($E74:$G74)=0,LEFT($H74,2)<>"定性",LEFT($H74,2)<>"文字",LEFT($H74,2)<>"日期"),1,0) -> 0 | Y74: =IF(OR($L74="",$M74=""),1,0) -> 0 | Z74: =IF(AND(ISNUMBER($E74),ISNUMBER($F74)),IF($F74>$E74,1,0),0)+IF(AND(ISNUMBER($E74),ISNUMBER($G74)),IF($E74>$G74,1,0),0)+IF(AND(ISNUMBER($F74),ISNUMBER($G74)),IF($F74>$G74,1,0),0) -> 0 | AA74: =IF(AND($P74="Derived",$V74="觀測"),1,0) -> 0 | AB74: CC 初評
A75: SRC_ANT_071 | B75: price_claude35_sonnet_in | C75: B | D75: API 牌價 Claude 3.5 Sonnet 輸入（上市 2024-06-20） | E75: 3 | H75: $/百萬token | I75: 2024-06-20 | J75: 45463 | L75: Anthropic〈Introducing Claude 3.5 Sonnet〉 | M75: https://www.anthropic.com/news/claude-3-5-sonnet | N75: 2024-06-21 | O75: 2026-10-08 | P75: Interested-party | Q75: Anthropic（官方牌價；市場地位誘因） | R75: 1 | S75: 利害關係方 | T75: Anthropic（官方牌價；市場地位誘因） | U75: 一手 | V75: 觀測 | W75: 原文：'$3 per million input tokens and $15 per million output tokens'；2024-10-22 新版同價 | X75: =IF(AND(COUNT($E75:$G75)=0,LEFT($H75,2)<>"定性",LEFT($H75,2)<>"文字",LEFT($H75,2)<>"日期"),1,0) -> 0 | Y75: =IF(OR($L75="",$M75=""),1,0) -> 0 | Z75: =IF(AND(ISNUMBER($E75),ISNUMBER($F75)),IF($F75>$E75,1,0),0)+IF(AND(ISNUMBER($E75),ISNUMBER($G75)),IF($E75>$G75,1,0),0)+IF(AND(ISNUMBER($F75),ISNUMBER($G75)),IF($F75>$G75,1,0),0) -> 0 | AA75: =IF(AND($P75="Derived",$V75="觀測"),1,0) -> 0 | AB75: CC 初評
A76: SRC_ANT_072 | B76: price_claude35_sonnet_out | C76: B | D76: API 牌價 Claude 3.5 Sonnet 輸出（上市 2024-06-20） | E76: 15 | H76: $/百萬token | I76: 2024-06-20 | J76: 45463 | L76: Anthropic〈Introducing Claude 3.5 Sonnet〉 | M76: https://www.anthropic.com/news/claude-3-5-sonnet | N76: 2024-06-21 | O76: 2026-10-08 | P76: Interested-party | Q76: Anthropic（官方牌價；市場地位誘因） | R76: 1 | S76: 利害關係方 | T76: Anthropic（官方牌價；市場地位誘因） | U76: 一手 | V76: 觀測 | W76: 原文：'$3 per million input tokens and $15 per million output tokens'；2024-10-22 新版同價 | X76: =IF(AND(COUNT($E76:$G76)=0,LEFT($H76,2)<>"定性",LEFT($H76,2)<>"文字",LEFT($H76,2)<>"日期"),1,0) -> 0 | Y76: =IF(OR($L76="",$M76=""),1,0) -> 0 | Z76: =IF(AND(ISNUMBER($E76),ISNUMBER($F76)),IF($F76>$E76,1,0),0)+IF(AND(ISNUMBER($E76),ISNUMBER($G76)),IF($E76>$G76,1,0),0)+IF(AND(ISNUMBER($F76),ISNUMBER($G76)),IF($F76>$G76,1,0),0) -> 0 | AA76: =IF(AND($P76="Derived",$V76="觀測"),1,0) -> 0 | AB76: CC 初評
A77: SRC_ANT_073 | B77: price_claude35_haiku_launch_in | C77: B | D77: API 牌價 Claude 3.5 Haiku（上市價） 輸入（上市 2024-11-04） | E77: 1 | H77: $/百萬token | I77: 2024-11-04 | J77: 45600 | L77: TechCrunch〈Anthropic hikes the price of its Haiku model〉 | M77: https://techcrunch.com/2024/11/04/anthropic-hikes-the-price-of-its-haiku-model | N77: 2024-11-04 | O77: 2026-10-08 | P77: Interested-party | Q77: Anthropic（牌價經第三方轉述） | R77: 2 | S77: 利害關係方 | T77: Anthropic（牌價經第三方轉述） | U77: 二手 | V77: 觀測 | W77: 原文：'starts at $1 per million input tokens…and $5 per million output tokens'；為 3 Haiku 的 4 倍 | X77: =IF(AND(COUNT($E77:$G77)=0,LEFT($H77,2)<>"定性",LEFT($H77,2)<>"文字",LEFT($H77,2)<>"日期"),1,0) -> 0 | Y77: =IF(OR($L77="",$M77=""),1,0) -> 0 | Z77: =IF(AND(ISNUMBER($E77),ISNUMBER($F77)),IF($F77>$E77,1,0),0)+IF(AND(ISNUMBER($E77),ISNUMBER($G77)),IF($E77>$G77,1,0),0)+IF(AND(ISNUMBER($F77),ISNUMBER($G77)),IF($F77>$G77,1,0),0) -> 0 | AA77: =IF(AND($P77="Derived",$V77="觀測"),1,0) -> 0 | AB77: CC 初評
A78: SRC_ANT_074 | B78: price_claude35_haiku_launch_out | C78: B | D78: API 牌價 Claude 3.5 Haiku（上市價） 輸出（上市 2024-11-04） | E78: 5 | H78: $/百萬token | I78: 2024-11-04 | J78: 45600 | L78: TechCrunch〈Anthropic hikes the price of its Haiku model〉 | M78: https://techcrunch.com/2024/11/04/anthropic-hikes-the-price-of-its-haiku-model | N78: 2024-11-04 | O78: 2026-10-08 | P78: Interested-party | Q78: Anthropic（牌價經第三方轉述） | R78: 2 | S78: 利害關係方 | T78: Anthropic（牌價經第三方轉述） | U78: 二手 | V78: 觀測 | W78: 原文：'starts at $1 per million input tokens…and $5 per million output tokens'；為 3 Haiku 的 4 倍 | X78: =IF(AND(COUNT($E78:$G78)=0,LEFT($H78,2)<>"定性",LEFT($H78,2)<>"文字",LEFT($H78,2)<>"日期"),1,0) -> 0 | Y78: =IF(OR($L78="",$M78=""),1,0) -> 0 | Z78: =IF(AND(ISNUMBER($E78),ISNUMBER($F78)),IF($F78>$E78,1,0),0)+IF(AND(ISNUMBER($E78),ISNUMBER($G78)),IF($E78>$G78,1,0),0)+IF(AND(ISNUMBER($F78),ISNUMBER($G78)),IF($F78>$G78,1,0),0) -> 0 | AA78: =IF(AND($P78="Derived",$V78="觀測"),1,0) -> 0 | AB78: CC 初評
A79: SRC_ANT_075 | B79: price_claude35_haiku_cut_in | C79: B | D79: API 牌價 Claude 3.5 Haiku（2024-12 降價後） 輸入（上市 2024-12-03） | E79: 0.8 | H79: $/百萬token | I79: 2024-12-03 | J79: 45629 | L79: Anthropic〈Introducing computer use, a new Claude 3.5 Sonnet, and Claude 3.5 Haiku〉（2024-12-03 更新） | M79: https://www.anthropic.com/news/3-5-models-and-computer-use | N79: 2024-12-03 | O79: 2026-10-08 | P79: Interested-party | Q79: Anthropic（官方牌價；市場地位誘因） | R79: 1 | S79: 利害關係方 | T79: Anthropic（官方牌價；市場地位誘因） | U79: 一手 | V79: 觀測 | W79: 原文：'now priced at $0.80 MTok input / $4 MTok output' | X79: =IF(AND(COUNT($E79:$G79)=0,LEFT($H79,2)<>"定性",LEFT($H79,2)<>"文字",LEFT($H79,2)<>"日期"),1,0) -> 0 | Y79: =IF(OR($L79="",$M79=""),1,0) -> 0 | Z79: =IF(AND(ISNUMBER($E79),ISNUMBER($F79)),IF($F79>$E79,1,0),0)+IF(AND(ISNUMBER($E79),ISNUMBER($G79)),IF($E79>$G79,1,0),0)+IF(AND(ISNUMBER($F79),ISNUMBER($G79)),IF($F79>$G79,1,0),0) -> 0 | AA79: =IF(AND($P79="Derived",$V79="觀測"),1,0) -> 0 | AB79: CC 初評
A80: SRC_ANT_076 | B80: price_claude35_haiku_cut_out | C80: B | D80: API 牌價 Claude 3.5 Haiku（2024-12 降價後） 輸出（上市 2024-12-03） | E80: 4 | H80: $/百萬token | I80: 2024-12-03 | J80: 45629 | L80: Anthropic〈Introducing computer use, a new Claude 3.5 Sonnet, and Claude 3.5 Haiku〉（2024-12-03 更新） | M80: https://www.anthropic.com/news/3-5-models-and-computer-use | N80: 2024-12-03 | O80: 2026-10-08 | P80: Interested-party | Q80: Anthropic（官方牌價；市場地位誘因） | R80: 1 | S80: 利害關係方 | T80: Anthropic（官方牌價；市場地位誘因） | U80: 一手 | V80: 觀測 | W80: 原文：'now priced at $0.80 MTok input / $4 MTok output' | X80: =IF(AND(COUNT($E80:$G80)=0,LEFT($H80,2)<>"定性",LEFT($H80,2)<>"文字",LEFT($H80,2)<>"日期"),1,0) -> 0 | Y80: =IF(OR($L80="",$M80=""),1,0) -> 0 | Z80: =IF(AND(ISNUMBER($E80),ISNUMBER($F80)),IF($F80>$E80,1,0),0)+IF(AND(ISNUMBER($E80),ISNUMBER($G80)),IF($E80>$G80,1,0),0)+IF(AND(ISNUMBER($F80),ISNUMBER($G80)),IF($F80>$G80,1,0),0) -> 0 | AA80: =IF(AND($P80="Derived",$V80="觀測"),1,0) -> 0 | AB80: CC 初評
... A138: SRC_ANT_134 | B138: price_haiku45_cache_read | C138: B | D138: API 牌價 Haiku 4.5 快取讀取 | E138: 0.1 | H138: $/百萬token | I138: 2026-10-07 | J138: 46302 | L138: Anthropic〈Introducing Claude Haiku 5.5〉價格表 | M138: https://www.anthropic.com/claude-haiku-5-5 | N138: 2026-10-07 | O138: 2026-10-08 | P138: Interested-party | Q138: Anthropic（官方牌價；市場地位誘因） | R138: 1 | S138: 利害關係方 | T138: Anthropic（官方牌價；市場地位誘因） | U138: 一手 | V138: 觀測 | W138: 價格表 Haiku 4.5 cache reads '$0.10' | X138: =IF(AND(COUNT($E138:$G138)=0,LEFT($H138,2)<>"定性",LEFT($H138,2)<>"文字",LEFT($H138,2)<>"日期"),1,0) -> 0 | Y138: =IF(OR($L138="",$M138=""),1,0) -> 0 | Z138: =IF(AND(ISNUMBER($E138),ISNUMBER($F138)),IF($F138>$E138,1,0),0)+IF(AND(ISNUMBER($E138),ISNUMBER($G138)),IF($E138>$G138,1,0),0)+IF(AND(ISNUMBER($F138),ISNUMBER($G138)),IF($F138>$G138,1,0),0) -> 0 | AA138: =IF(AND($P138="Derived",$V138="觀測"),1,0) -> 0 | AB138: CC 初評
A139: SRC_ANT_135 | B139: price_cache_write_5m_mult | C139: B | D139: 快取寫入倍數（5 分鐘 TTL） | E139: 1.25 | H139: 倍（相對輸入價） | I139: 2026-04 | L139: Morph〈Anthropic API Pricing: The Real Cost of Claude for Coding Agents〉（稱已對照 platform.claude.com） | M139: https://www.morphllm.com/anthropic-claude-api-pricing | N139: 2026-04-05 | O139: 2026-10-08 | P139: Analogy | R139: 未評 | S139: 第三方估計 | T139: 第三方估計；非公司揭露，作類比或區間 | U139: 未評 | V139: 觀測 | W139: 原文：5-minute cache write '1.25x base input'；官方定價頁本次無法開啟 | X139: =IF(AND(COUNT($E139:$G139)=0,LEFT($H139,2)<>"定性",LEFT($H139,2)<>"文字",LEFT($H139,2)<>"日期"),1,0) -> 0 | Y139: =IF(OR($L139="",$M139=""),1,0) -> 0 | Z139: =IF(AND(ISNUMBER($E139),ISNUMBER($F139)),IF($F139>$E139,1,0),0)+IF(AND(ISNUMBER($E139),ISNUMBER($G139)),IF($E139>$G139,1,0),0)+IF(AND(ISNUMBER($F139),ISNUMBER($G139)),IF($F139>$G139,1,0),0) -> 0 | AA139: =IF(AND($P139="Derived",$V139="觀測"),1,0) -> 0 | AB139: CC 初評
A140: SRC_ANT_136 | B140: price_cache_write_1h_mult | C140: B | D140: 快取寫入倍數（1 小時 TTL） | E140: 2 | H140: 倍（相對輸入價） | I140: 2026-04 | L140: Morph（同上） | M140: https://www.morphllm.com/anthropic-claude-api-pricing | N140: 2026-04-05 | O140: 2026-10-08 | P140: Analogy | R140: 未評 | S140: 第三方估計 | T140: 第三方估計；非公司揭露，作類比或區間 | U140: 未評 | V140: 觀測 | W140: 原文：1-hour cache write '2x base input' | X140: =IF(AND(COUNT($E140:$G140)=0,LEFT($H140,2)<>"定性",LEFT($H140,2)<>"文字",LEFT($H140,2)<>"日期"),1,0) -> 0 | Y140: =IF(OR($L140="",$M140=""),1,0) -> 0 | Z140: =IF(AND(ISNUMBER($E140),ISNUMBER($F140)),IF($F140>$E140,1,0),0)+IF(AND(ISNUMBER($E140),ISNUMBER($G140)),IF($E140>$G140,1,0),0)+IF(AND(ISNUMBER($F140),ISNUMBER($G140)),IF($F140>$G140,1,0),0) -> 0 | AA140: =IF(AND($P140="Derived",$V140="觀測"),1,0) -> 0 | AB140: CC 初評
A141: SRC_ANT_137 | B141: price_cache_read_mult | C141: B | D141: 快取讀取倍數 | E141: 0.1 | H141: 倍（相對輸入價） | I141: 2026-04 | L141: Morph（同上） | M141: https://www.morphllm.com/anthropic-claude-api-pricing | N141: 2026-04-05 | O141: 2026-10-08 | P141: Analogy | R141: 未評 | S141: 第三方估計 | T141: 第三方估計；非公司揭露，作類比或區間 | U141: 未評 | V141: 觀測 | W141: 原文：Cache read '0.1x base input'。2026-09 起 Opus 5.5／Sonnet 5.5 降至 0.05× | X141: =IF(AND(COUNT($E141:$G141)=0,LEFT($H141,2)<>"定性",LEFT($H141,2)<>"文字",LEFT($H141,2)<>"日期"),1,0) -> 0 | Y141: =IF(OR($L141="",$M141=""),1,0) -> 0 | Z141: =IF(AND(ISNUMBER($E141),ISNUMBER($F141)),IF($F141>$E141,1,0),0)+IF(AND(ISNUMBER($E141),ISNUMBER($G141)),IF($E141>$G141,1,0),0)+IF(AND(ISNUMBER($F141),ISNUMBER($G141)),IF($F141>$G141,1,0),0) -> 0 | AA141: =IF(AND($P141="Derived",$V141="觀測"),1,0) -> 0 | AB141: CC 初評
A142: SRC_ANT_138 | B142: price_batch_discount | C142: B | D142: Batch API 折扣 | E142: 0.5 | H142: 比例（折扣） | I142: 2026-04 | L142: Morph（同上） | M142: https://www.morphllm.com/anthropic-claude-api-pricing | N142: 2026-04-05 | O142: 2026-10-08 | P142: Analogy | R142: 未評 | S142: 第三方估計 | T142: 第三方估計；非公司揭露，作類比或區間 | U142: 未評 | V142: 觀測 | W142: 原文：'50% off standard'，'half price on both input and output tokens' | X142: =IF(AND(COUNT($E142:$G142)=0,LEFT($H142,2)<>"定性",LEFT($H142,2)<>"文字",LEFT($H142,2)<>"日期"),1,0) -> 0 | Y142: =IF(OR($L142="",$M142=""),1,0) -> 0 | Z142: =IF(AND(ISNUMBER($E142),ISNUMBER($F142)),IF($F142>$E142,1,0),0)+IF(AND(ISNUMBER($E142),ISNUMBER($G142)),IF($E142>$G142,1,0),0)+IF(AND(ISNUMBER($F142),ISNUMBER($G142)),IF($F142>$G142,1,0),0) -> 0 | AA142: =IF(AND($P142="Derived",$V142="觀測"),1,0) -> 0 | AB142: CC 初評
A143: SRC_ANT_139 | B143: price_batch_discount_b | C143: B | D143: Batch API 折扣 | E143: 0.5 | H143: 比例（折扣） | I143: 2026-05 | L143: Finout〈Claude Pricing in 2026〉 | M143: https://finout.io/blog/claude-pricing-in-2026-for-individuals-organizations-and-developers | N143: 2026-06-01 | O143: 2026-10-08 | P143: Analogy | R143: 未評 | S143: 第三方估計 | T143: 第三方估計；非公司揭露，作類比或區間 | U143: 未評 | V143: 觀測 | W143: 原文：'Batch processing = 50% off all token rates'；cache '5-min = 1.25×…1-hr = 2×'、hits '0.10×' | X143: =IF(AND(COUNT($E143:$G143)=0,LEFT($H143,2)<>"定性",LEFT($H143,2)<>"文字",LEFT($H143,2)<>"日期"),1,0) -> 0 | Y143: =IF(OR($L143="",$M143=""),1,0) -> 0 | Z143: =IF(AND(ISNUMBER($E143),ISNUMBER($F143)),IF($F143>$E143,1,0),0)+IF(AND(ISNUMBER($E143),ISNUMBER($G143)),IF($E143>$G143,1,0),0)+IF(AND(ISNUMBER($F143),ISNUMBER($G143)),IF($F143>$G143,1,0),0) -> 0 | AA143: =IF(AND($P143="Derived",$V143="觀測"),1,0) -> 0 | AB143: CC 初評
A144: SRC_ANT_140 | B144: price_1m_context_no_surcharge | C144: B | D144: Opus 4.6／Sonnet 4.6 1M 上下文 GA 後加價 | E144: 0 | H144: 加價比例 | I144: 2026-04 | L144: Morph（同上） | M144: https://www.morphllm.com/anthropic-claude-api-pricing | N144: 2026-04-05 | O144: 2026-10-08 | P144: Analogy | R144: 未評 | S144: 第三方估計 | T144: 第三方估計；非公司揭露，作類比或區間 | U144: 未評 | V144: 觀測 | W144: 原文：1M context GA 'at standard pricing, no surcharge'。與 Opus 4.6 上市頁 >200k 加價（$10/$37.50）矛盾，推測其後取消 | X144: =IF(AND(COUNT($E144:$G144)=0,LEFT($H144,2)<>"定性",LEFT($H144,2)<>"文字",LEFT($H144,2)<>"日期"),1,0) -> 0 | Y144: =IF(OR($L144="",$M144=""),1,0) -> 0 | Z144: =IF(AND(ISNUMBER($E144),ISNUMBER($F144)),IF($F144>$E144,1,0),0)+IF(AND(ISNUMBER($E144),ISNUMBER($G144)),IF($E144>$G144,1,0),0)+IF(AND(ISNUMBER($F144),ISNUMBER($G144)),IF($F144>$G144,1,0),0) -> 0 | AA144: =IF(AND($P144="Derived",$V144="觀測"),1,0) -> 0 | AB144: CC 初評
A145: SRC_ANT_141 | B145: plan_pro_monthly | C145: B | D145: Claude Pro 月付 | E145: 20 | H145: $/月 | I145: 2026-09 | L145: Suprmind〈Claude AI Pricing: Pro & Max Subscription Plans〉 | M145: https://suprmind.ai/hub/claude/pricing/ | N145: 2026-09 | O145: 2026-10-08 | P145: Interested-party | Q145: Anthropic（牌價經第三方轉述；官方定價頁本次無法開啟） | R145: 未評 | S145: 利害關係方 | T145: Anthropic（牌價經第三方轉述；官方定價頁本次無法開啟） | U145: 未評 | V145: 觀測 | W145: 原文：'Pro is $20/month, or $17/month billed annually ($200 up front)' | X145: =IF(AND(COUNT($E145:$G145)=0,LEFT($H145,2)<>"定性",LEFT($H145,2)<>"文字",LEFT($H145,2)<>"日期"),1,0) -> 0 | Y145: =IF(OR($L145="",$M145=""),1,0) -> 0 | Z145: =IF(AND(ISNUMBER($E145),ISNUMBER($F145)),IF($F145>$E145,1,0),0)+IF(AND(ISNUMBER($E145),ISNUMBER($G145)),IF($E145>$G145,1,0),0)+IF(AND(ISNUMBER($F145),ISNUMBER($G145)),IF($F145>$G145,1,0),0) -> 0 | AA145: =IF(AND($P145="Derived",$V145="觀測"),1,0) -> 0 | AB145: CC 初評
A146: SRC_ANT_142 | B146: plan_pro_annual | C146: B | D146: Claude Pro 年付（月均） | E146: 17 | H146: $/月 | I146: 2026-09 | L146: Suprmind（同上） | M146: https://suprmind.ai/hub/claude/pricing/ | N146: 2026-09 | O146: 2026-10-08 | P146: Interested-party | Q146: Anthropic（牌價經第三方轉述；官方定價頁本次無法開啟） | R146: 未評 | S146: 利害關係方 | T146: Anthropic（牌價經第三方轉述；官方定價頁本次無法開啟） | U146: 未評 | V146: 觀測 | W146: 原文：'$17/month billed annually ($200 up front)'；VantagePoint 2026-08 亦同 | X146: =IF(AND(COUNT($E146:$G146)=0,LEFT($H146,2)<>"定性",LEFT($H146,2)<>"文字",LEFT($H146,2)<>"日期"),1,0) -> 0 | Y146: =IF(OR($L146="",$M146=""),1,0) -> 0 | Z146: =IF(AND(ISNUMBER($E146),ISNUMBER($F146)),IF($F146>$E146,1,0),0)+IF(AND(ISNUMBER($E146),ISNUMBER($G146)),IF($E146>$G146,1,0),0)+IF(AND(ISNUMBER($F146),ISNUMBER($G146)),IF($F146>$G146,1,0),0) -> 0 | AA146: =IF(AND($P146="Derived",$V146="觀測"),1,0) -> 0 | AB146: CC 初評
A147: SRC_ANT_143 | B147: plan_max5x | C147: B | D147: Claude Max 5x 月付 | E147: 100 | H147: $/月 | I147: 2026-09 | L147: Suprmind（同上） | M147: https://suprmind.ai/hub/claude/pricing/ | N147: 2026-09 | O147: 2026-10-08 | P147: Interested-party | Q147: Anthropic（牌價經第三方轉述；官方定價頁本次無法開啟） | R147: 未評 | S147: 利害關係方 | T147: Anthropic（牌價經第三方轉述；官方定價頁本次無法開啟） | U147: 未評 | V147: 觀測 | W147: 原文：'Max 5x jumps to $100/month'；Max 僅月付 | X147: =IF(AND(COUNT($E147:$G147)=0,LEFT($H147,2)<>"定性",LEFT($H147,2)<>"文字",LEFT($H147,2)<>"日期"),1,0) -> 0 | Y147: =IF(OR($L147="",$M147=""),1,0) -> 0 | Z147: =IF(AND(ISNUMBER($E147),ISNUMBER($F147)),IF($F147>$E147,1,0),0)+IF(AND(ISNUMBER($E147),ISNUMBER($G147)),IF($E147>$G147,1,0),0)+IF(AND(ISNUMBER($F147),ISNUMBER($G147)),IF($F147>$G147,1,0),0) -> 0 | AA147: =IF(AND($P147="Derived",$V147="觀測"),1,0) -> 0 | AB147: CC 初評
A148: SRC_ANT_144 | B148: plan_max20x | C148: B | D148: Claude Max 20x 月付 | E148: 200 | H148: $/月 | I148: 2026-09 | L148: Suprmind（同上） | M148: https://suprmind.ai/hub/claude/pricing/ | N148: 2026-09 | O148: 2026-10-08 | P148: Interested-party | Q148: Anthropic（牌價經第三方轉述；官方定價頁本次無法開啟） | R148: 未評 | S148: 利害關係方 | T148: Anthropic（牌價經第三方轉述；官方定價頁本次無法開啟） | U148: 未評 | V148: 觀測 | W148: 原文：'Max 20x costs $200/month' | X148: =IF(AND(COUNT($E148:$G148)=0,LEFT($H148,2)<>"定性",LEFT($H148,2)<>"文字",LEFT($H148,2)<>"日期"),1,0) -> 0 | Y148: =IF(OR($L148="",$M148=""),1,0) -> 0 | Z148: =IF(AND(ISNUMBER($E148),ISNUMBER($F148)),IF($F148>$E148,1,0),0)+IF(AND(ISNUMBER($E148),ISNUMBER($G148)),IF($E148>$G148,1,0),0)+IF(AND(ISNUMBER($F148),ISNUMBER($G148)),IF($F148>$G148,1,0),0) -> 0 | AA148: =IF(AND($P148="Derived",$V148="觀測"),1,0) -> 0 | AB148: CC 初評
A149: SRC_ANT_145 | B149: plan_max_launch | C149: B | D149: Claude Max 方案上市（5x $100／20x $200） | E149: 100 | H149: $/月 | I149: 2025-04 | L149: GIGAZINE〈Anthropic launches Claude Max plan〉 | M149: https://gigazine.net/gsc_news/en/20250410-anthropic-claude-max-plan | N149: 2025-04-10 | O149: 2026-10-08 | P149: Interested-party | Q149: Anthropic（牌價經第三方轉述；官方定價頁本次無法開啟） | R149: 未評 | S149: 利害關係方 | T149: Anthropic（牌價經第三方轉述；官方定價頁本次無法開啟） | U149: 未評 | V149: 觀測 | W149: 標題：'5x the usage caps of Pro for $100/month and 20x the caps for $200/month' | X149: =IF(AND(COUNT($E149:$G149)=0,LEFT($H149,2)<>"定性",LEFT($H149,2)<>"文字",LEFT($H149,2)<>"日期"),1,0) -> 0 | Y149: =IF(OR($L149="",$M149=""),1,0) -> 0 | Z149: =IF(AND(ISNUMBER($E149),ISNUMBER($F149)),IF($F149>$E149,1,0),0)+IF(AND(ISNUMBER($E149),ISNUMBER($G149)),IF($E149>$G149,1,0),0)+IF(AND(ISNUMBER($F149),ISNUMBER($G149)),IF($F149>$G149,1,0),0) -> 0 | AA149: =IF(AND($P149="Derived",$V149="觀測"),1,0) -> 0 | AB149: CC 初評
A150: SRC_ANT_146 | B150: plan_team_standard_annual | C150: B | D150: Team 標準席位（年付，月均） | E150: 20 | H150: $/席/月 | I150: 2026-10 | L150: Tygart Media〈Claude Team Pricing: Standard vs Premium Seats (2026)〉 | M150: https://tygartmedia.com/claude-team-pricing-2026-standard-premium-seats/ | N150: 2026-10-05 | O150: 2026-10-08 | P150: Interested-party | Q150: Anthropic（牌價經第三方轉述；官方定價頁本次無法開啟） | R150: 未評 | S150: 利害關係方 | T150: Anthropic（牌價經第三方轉述；官方定價頁本次無法開啟） | U150: 未評 | V150: 觀測 | W150: 原文：'$25…on monthly billing, or $20…on annual billing'；最少 2 席 | X150: =IF(AND(COUNT($E150:$G150)=0,LEFT($H150,2)<>"定性",LEFT($H150,2)<>"文字",LEFT($H150,2)<>"日期"),1,0) -> 0 | Y150: =IF(OR($L150="",$M150=""),1,0) -> 0 | Z150: =IF(AND(ISNUMBER($E150),ISNUMBER($F150)),IF($F150>$E150,1,0),0)+IF(AND(ISNUMBER($E150),ISNUMBER($G150)),IF($E150>$G150,1,0),0)+IF(AND(ISNUMBER($F150),ISNUMBER($G150)),IF($F150>$G150,1,0),0) -> 0 | AA150: =IF(AND($P150="Derived",$V150="觀測"),1,0) -> 0 | AB150: CC 初評
A151: SRC_ANT_147 | B151: plan_team_standard_monthly | C151: B | D151: Team 標準席位（月付） | E151: 25 | H151: $/席/月 | I151: 2026-10 | L151: Tygart Media（同上） | M151: https://tygartmedia.com/claude-team-pricing-2026-standard-premium-seats/ | N151: 2026-10-05 | O151: 2026-10-08 | P151: Interested-party | Q151: Anthropic（牌價經第三方轉述；官方定價頁本次無法開啟） | R151: 未評 | S151: 利害關係方 | T151: Anthropic（牌價經第三方轉述；官方定價頁本次無法開啟） | U151: 未評 | V151: 觀測 | W151: 原文：'Standard seats cost $25 per seat per month on monthly billing' | X151: =IF(AND(COUNT($E151:$G151)=0,LEFT($H151,2)<>"定性",LEFT($H151,2)<>"文字",LEFT($H151,2)<>"日期"),1,0) -> 0 | Y151: =IF(OR($L151="",$M151=""),1,0) -> 0 | Z151: =IF(AND(ISNUMBER($E151),ISNUMBER($F151)),IF($F151>$E151,1,0),0)+IF(AND(ISNUMBER($E151),ISNUMBER($G151)),IF($E151>$G151,1,0),0)+IF(AND(ISNUMBER($F151),ISNUMBER($G151)),IF($F151>$G151,1,0),0) -> 0 | AA151: =IF(AND($P151="Derived",$V151="觀測"),1,0) -> 0 | AB151: CC 初評
A152: SRC_ANT_148 | B152: plan_team_premium_annual | C152: B | D152: Team Premium 席位（年付，月均） | E152: 100 | H152: $/席/月 | I152: 2026-10 | L152: Tygart Media（同上） | M152: https://tygartmedia.com/claude-team-pricing-2026-standard-premium-seats/ | N152: 2026-10-05 | O152: 2026-10-08 | P152: Interested-party | Q152: Anthropic（牌價經第三方轉述；官方定價頁本次無法開啟） | R152: 未評 | S152: 利害關係方 | T152: Anthropic（牌價經第三方轉述；官方定價頁本次無法開啟） | U152: 未評 | V152: 觀測 | W152: 原文：'$125…monthly billing, or $100…annual billing' | X152: =IF(AND(COUNT($E152:$G152)=0,LEFT($H152,2)<>"定性",LEFT($H152,2)<>"文字",LEFT($H152,2)<>"日期"),1,0) -> 0 | Y152: =IF(OR($L152="",$M152=""),1,0) -> 0 | Z152: =IF(AND(ISNUMBER($E152),ISNUMBER($F152)),IF($F152>$E152,1,0),0)+IF(AND(ISNUMBER($E152),ISNUMBER($G152)),IF($E152>$G152,1,0),0)+IF(AND(ISNUMBER($F152),ISNUMBER($G152)),IF($F152>$G152,1,0),0) -> 0 | AA152: =IF(AND($P152="Derived",$V152="觀測"),1,0) -> 0 | AB152: CC 初評
A153: SRC_ANT_149 | B153: plan_team_premium_monthly | C153: B | D153: Team Premium 席位（月付） | E153: 125 | H153: $/席/月 | I153: 2026-10 | L153: Tygart Media（同上） | M153: https://tygartmedia.com/claude-team-pricing-2026-standard-premium-seats/ | N153: 2026-10-05 | O153: 2026-10-08 | P153: Interested-party | Q153: Anthropic（牌價經第三方轉述；官方定價頁本次無法開啟） | R153: 未評 | S153: 利害關係方 | T153: Anthropic（牌價經第三方轉述；官方定價頁本次無法開啟） | U153: 未評 | V153: 觀測 | W153: 原文：'Premium seats cost $125 per seat per month on monthly billing' | X153: =IF(AND(COUNT($E153:$G153)=0,LEFT($H153,2)<>"定性",LEFT($H153,2)<>"文字",LEFT($H153,2)<>"日期"),1,0) -> 0 | Y153: =IF(OR($L153="",$M153=""),1,0) -> 0 | Z153: =IF(AND(ISNUMBER($E153),ISNUMBER($F153)),IF($F153>$E153,1,0),0)+IF(AND(ISNUMBER($E153),ISNUMBER($G153)),IF($E153>$G153,1,0),0)+IF(AND(ISNUMBER($F153),ISNUMBER($G153)),IF($F153>$G153,1,0),0) -> 0 | AA153: =IF(AND($P153="Derived",$V153="觀測"),1,0) -> 0 | AB153: CC 初評
A154: SRC_ANT_150 | B154: plan_team_standard_annual_b | C154: B | D154: Team 標準席位（年付，月均）— 舊報導值 | E154: 25 | H154: $/席/月 | I154: 2026-05 | L154: Finout〈Claude Pricing in 2026〉 | M154: https://finout.io/blog/claude-pricing-in-2026-for-individuals-organizations-and-developers | N154: 2026-06-01 | O154: 2026-10-08 | P154: Interested-party | Q154: Anthropic（牌價經第三方轉述；官方定價頁本次無法開啟） | R154: 未評 | S154: 利害關係方 | T154: Anthropic（牌價經第三方轉述；官方定價頁本次無法開啟） | U154: 未評 | V154: 觀測 | W154: 原文：'$25/user/mo (annual)' or '$30/mo billed monthly'；Premium '$150/user/mo'；最少 5 人。與 2026-09 後 $20/$25、$100/$125 矛盾，推測 2026 年中調降 | X154: =IF(AND(COUNT($E154:$G154)=0,LEFT($H154,2)<>"定性",LEFT($H154,2)<>"文字",LEFT($H154,2)<>"日期"),1,0) -> 0 | Y154: =IF(OR($L154="",$M154=""),1,0) -> 0 | Z154: =IF(AND(ISNUMBER($E154),ISNUMBER($F154)),IF($F154>$E154,1,0),0)+IF(AND(ISNUMBER($E154),ISNUMBER($G154)),IF($E154>$G154,1,0),0)+IF(AND(ISNUMBER($F154),ISNUMBER($G154)),IF($F154>$G154,1,0),0) -> 0 | AA154: =IF(AND($P154="Derived",$V154="觀測"),1,0) -> 0 | AB154: CC 初評
A155: SRC_ANT_151 | B155: plan_team_min_seats_change | C155: B | D155: Team 最低席位數（2026-09 起） | E155: 2 | H155: 席 | I155: 2026-09 | L155: Justin McKelvey〈Claude Team Plan (2026)〉 | M155: https://justinmckelvey.com/blog/claude-team-plan | N155: 2026-09-29 | O155: 2026-10-08 | P155: Interested-party | Q155: Anthropic（牌價經第三方轉述；官方定價頁本次無法開啟） | R155: 未評 | S155: 利害關係方 | T155: Anthropic（牌價經第三方轉述；官方定價頁本次無法開啟） | U155: 未評 | V155: 觀測 | W155: 原文：原 'Claude Team was $25 a seat and required five of them'；2026-09 改 2 席起、標準 $20 年付 | X155: =IF(AND(COUNT($E155:$G155)=0,LEFT($H155,2)<>"定性",LEFT($H155,2)<>"文字",LEFT($H155,2)<>"日期"),1,0) -> 0 | Y155: =IF(OR($L155="",$M155=""),1,0) -> 0 | Z155: =IF(AND(ISNUMBER($E155),ISNUMBER($F155)),IF($F155>$E155,1,0),0)+IF(AND(ISNUMBER($E155),ISNUMBER($G155)),IF($E155>$G155,1,0),0)+IF(AND(ISNUMBER($F155),ISNUMBER($G155)),IF($F155>$G155,1,0),0) -> 0 | AA155: =IF(AND($P155="Derived",$V155="觀測"),1,0) -> 0 | AB155: CC 初評
A156: SRC_ANT_152 | B156: plan_enterprise_seat_2026 | C156: B | D156: Enterprise 席位基本費（另按 API 牌價計用量） | E156: 20 | H156: $/席/月 | I156: 2026-02 | L156: The Register〈Anthropic ejects bundled tokens from Enterprise seats〉 | M156: https://www.theregister.com/2026/04/16/anthropic_ejects_bundled_tokens_enterprise/ | N156: 2026-04-16 | O156: 2026-10-08 | P156: Interested-party | Q156: Anthropic（經媒體轉述） | R156: 2 | S156: 利害關係方 | T156: Anthropic（經媒體轉述） | U156: 二手 | V156: 觀測 | W156: 原文：'a single $20-per-employee monthly fee'；'Every token gets billed at standard API rates on top'；自 2025-11 續約起改用量制 | X156: =IF(AND(COUNT($E156:$G156)=0,LEFT($H156,2)<>"定性",LEFT($H156,2)<>"文字",LEFT($H156,2)<>"日期"),1,0) -> 0 | Y156: =IF(OR($L156="",$M156=""),1,0) -> 0 | Z156: =IF(AND(ISNUMBER($E156),ISNUMBER($F156)),IF($F156>$E156,1,0),0)+IF(AND(ISNUMBER($E156),ISNUMBER($G156)),IF($E156>$G156,1,0),0)+IF(AND(ISNUMBER($F156),ISNUMBER($G156)),IF($F156>$G156,1,0),0) -> 0 | AA156: =IF(AND($P156="Derived",$V156="觀測"),1,0) -> 0 | AB156: CC 初評
A157: SRC_ANT_153 | B157: plan_enterprise_seat_legacy | C157: B | D157: Enterprise 席位價（舊制，第三方指稱） | E157: 60 | F157: 40 | G157: 60 | H157: $/席/月 | I157: 2025 | L157: Redress Compliance〈Claude Enterprise Licensing Guide 2026〉 | M157: https://redresscompliance.com/anthropic-claude-enterprise-licensing-guide-2026 | N157: 2025-07-07 | O157: 2026-10-08 | P157: Analogy | R157: 未評 | S157: 第三方估計 | T157: 第三方估計；非公司揭露，作類比或區間 | U157: 未評 | V157: 觀測 | W157: 原文：'Claude Enterprise…priced at $60 per user per month'；未引一手來源 | X157: =IF(AND(COUNT($E157:$G157)=0,LEFT($H157,2)<>"定性",LEFT($H157,2)<>"文字",LEFT($H157,2)<>"日期"),1,0) -> 0 | Y157: =IF(OR($L157="",$M157=""),1,0) -> 0 | Z157: =IF(AND(ISNUMBER($E157),ISNUMBER($F157)),IF($F157>$E157,1,0),0)+IF(AND(ISNUMBER($E157),ISNUMBER($G157)),IF($E157>$G157,1,0),0)+IF(AND(ISNUMBER($F157),ISNUMBER($G157)),IF($F157>$G157,1,0),0) -> 0 | AA157: =IF(AND($P157="Derived",$V157="觀測"),1,0) -> 0 | AB157: CC 初評
...

Sheet TK_Link
A1: TK_Link — Tokenomics 快照（第 0 層連結；不用 Excel 外部連結）
A2: 每列一個 Tokenomics 名稱。值（藍字）由 builder 從 Tokenomics master 的 model/CURRENT 讀出寫入；本模型公式只引用 TK_ 具名範圍。前 63 名與 OpenAI v0.6 相同，其後 5 名為 A2 新增（任務別每次嘗試 token）；再其後 14 名為 v0.1.2 新增（Tokenomics v18.0 的 L1_RevGW_PQ_VR200 等對照名稱，只對照、不回饋計算）；再其後 22 名為 v0.1.3 B 新增（IF_UtilActual、L1_TokGW_PaidCap_VR200、L1_Gap*，只供 EtaDiag 對照）；其後為 NonNV 表（Tokenomics 未設具名範圍，以列標籤＋欄標題讀表；狀態「讀表（非具名）」，列入 Tokenomics 缺口：建議 Tokenomics 把 NonNV 比例列進 Interface）。
A3: Tokenomics 檔案 | B3: 20261022_Tokenomics_v19.0.xlsx | C3: 檔案 SHA-256：d1728705daaf19bfdfa7657b667f3617ac57d67a4c8e55404ac66522b970b9d8
A4: Tokenomics 版本 | B4: v19.0
A5: Tokenomics 提交 SHA（master） | B5: 1916a06465bb0c7efed21383075f2ae098508e24
A6: 讀取日期 | B6: 2026-10-22
I7: 世代 | J7: Hopper H100 | K7: Hopper H100 | L7: Hopper H100 | M7: GB200 NVL72 | N7: GB200 NVL72 | O7: GB200 NVL72 | P7: GB300 NVL72 | Q7: GB300 NVL72 | R7: GB300 NVL72 | S7: VR200 NVL72 | T7: VR200 NVL72 | U7: VR200 NVL72 | V7: Rubin Ultra（MGX NVL 單架，72 GPU） | W7: Rubin Ultra（MGX NVL 單架，72 GPU） | X7: Rubin Ultra（MGX NVL 單架，72 GPU）
I8: 成本情境 | J8: 低成本 | K8: 基準 | L8: 高成本 | M8: 低成本 | N8: 基準 | O8: 高成本 | P8: 低成本 | Q8: 基準 | R8: 高成本 | S8: 低成本 | T8: 基準 | U8: 高成本 | V8: 低成本 | W8: 基準 | X8: 高成本
A9: Tokenomics 名稱 | B9: 本模型名稱 | C9: 說明 | D9: 單位 | E9: 欄數 | F9: 狀態 | G9: Tokenomics 版本 | H9: 提交 SHA | I9: 讀取日期 | J9: 值1 | K9: 值2 | L9: 值3 | M9: 值4 | N9: 值5 | O9: 值6 | P9: 值7 | Q9: 值8 | R9: 值9 | S9: 值10 | T9: 值11 | U9: 值12 | V9: 值13 | W9: 值14 | X9: 值15
A10: IF_TokGW_Astra | B10: TK_IF_TokGW_Astra | C10: 每 GW 總產出（100%） | D10: M tok/年 | E10: 15 | F10: OK | G10: v19.0 | H10: 1916a06 | I10: 2026-10-22 | J10: 6.8090257e+09 | K10: 6.8090257e+09 | L10: 6.8090257e+09 | M10: 3.3674782e+10 | N10: 3.3674782e+10 | O10: 3.3674782e+10 | P10: 3.9257828e+10 | Q10: 3.9257828e+10 | R10: 3.9257828e+10 | S10: 6.9625194e+10 | T10: 6.9625194e+10 | U10: 6.9625194e+10 | V10: 9.8521567e+10 | W10: 9.8521567e+10 | X10: 9.8521567e+10
A11: IF_TokGW_Luna | B11: TK_IF_TokGW_Luna | C11: 每 GW 總產出（100%） | D11: M tok/年 | E11: 15 | F11: OK | G11: v19.0 | H11: 1916a06 | I11: 2026-10-22 | J11: 1.1222824e+11 | K11: 1.1222824e+11 | L11: 1.1222824e+11 | M11: 5.5783891e+11 | N11: 5.5783891e+11 | O11: 5.5783891e+11 | P11: 7.2317604e+11 | Q11: 7.2317604e+11 | R11: 7.2317604e+11 | S11: 1.0432677e+12 | T11: 1.0432677e+12 | U11: 1.0432677e+12 | V11: 1.404588e+12 | W11: 1.404588e+12 | X11: 1.404588e+12
A12: IF_TokGW_Sol | B12: TK_IF_TokGW_Sol | C12: 每 GW 總產出（100%） | D12: M tok/年 | E12: 15 | F12: OK | G12: v19.0 | H12: 1916a06 | I12: 2026-10-22 | J12: 3.3634916e+10 | K12: 3.3634916e+10 | L12: 3.3634916e+10 | M12: 1.6371585e+11 | N12: 1.6371585e+11 | O12: 1.6371585e+11 | P12: 2.1233432e+11 | Q12: 2.1233432e+11 | R12: 2.1233432e+11 | S12: 3.189849e+11 | T12: 3.189849e+11 | U12: 3.189849e+11 | V12: 4.3438046e+11 | W12: 4.3438046e+11 | X12: 4.3438046e+11
A13: IF_Util | B13: TK_IF_Util | C13: 基準利用率（第 0 層；下游可覆寫） | D13: % | E13: 1 | F13: OK | G13: v19.0 | H13: 1916a06 | I13: 2026-10-22 | J13: 0.6
A14: IF_HoldEcon | B14: TK_IF_HoldEcon | C14: 每 GW 年持有成本 — 經濟口徑 | D14: $B/年 | E14: 15 | F14: OK | G14: v19.0 | H14: 1916a06 | I14: 2026-10-22 | J14: 6.7910747 | K14: 9.7030873 | L14: 16.66377 | M14: 6.6118163 | N14: 8.8281656 | O14: 14.318575 | P14: 8.4288991 | Q14: 10.886411 | R14: 18.534646 | S14: 9.5120769 | T14: 12.225471 | U14: 19.750627 | V14: 10.102545 | W14: 15.354483 | X14: 28.030245
A15: IF_FullCost_Astra | B15: TK_IF_FullCost_Astra | C15: 全成本 $/M（服務＋快取儲存＋自下而上攤提；基準利用率） | D15: $/M | E15: 15 | F15: OK | G15: v19.0 | H15: 1916a06 | I15: 2026-10-22 | J15: 4.4404114 | K15: 6.344364 | L15: 10.895446 | M15: 0.53031631 | N15: 0.708009 | O15: 1.1481948 | P15: 0.59852248 | Q15: 0.77296134 | R15: 1.3158475 | S15: 0.32897901 | T15: 0.42275916 | U15: 0.68284311 | V15: 0.22427424 | W15: 0.34075004 | X15: 0.62186904
A16: IF_FullCost_Luna | B16: TK_IF_FullCost_Luna | C16: 全成本 $/M（服務＋快取儲存＋自下而上攤提；基準利用率） | D16: $/M | E16: 15 | F16: OK | G16: v19.0 | H16: 1916a06 | I16: 2026-10-22 | J16: 0.14706463 | K16: 0.21012129 | L16: 0.36084777 | M16: 0.022499115 | N16: 0.03003742 | O16: 0.048711544 | P16: 0.022877902 | Q16: 0.029544976 | R16: 0.050294152 | S16: 0.016788463 | T16: 0.021574412 | U16: 0.034847464 | V16: 0.012809112 | W16: 0.019462463 | X16: 0.035520591
A17: IF_FullCost_Sol | B17: TK_IF_FullCost_Sol | C17: 全成本 $/M（服務＋快取儲存＋自下而上攤提；基準利用率） | D17: $/M | E17: 15 | F17: OK | G17: v19.0 | H17: 1916a06 | I17: 2026-10-22 | J17: 0.45057467 | K17: 0.64377448 | L17: 1.1055865 | M17: 0.075115753 | N17: 0.10029018 | O17: 0.16265305 | P17: 0.075557593 | Q17: 0.097582523 | R17: 0.16612821 | S17: 0.053782904 | T17: 0.069120513 | U17: 0.11165687 | V17: 0.040901542 | W17: 0.062156746 | X17: 0.11345703
A18: IF_PriceCached_Astra | B18: TK_IF_PriceCached_Astra | C18: 快取輸入 $/M — OpenAI 有效 | D18: $/M | E18: 1 | F18: OK | G18: v19.0 | H18: 1916a06 | I18: 2026-10-22 | J18: 0.8
A19: IF_PriceCached_Luna | B19: TK_IF_PriceCached_Luna | C19: 快取輸入 $/M — OpenAI 有效 | D19: $/M | E19: 1 | F19: OK | G19: v19.0 | H19: 1916a06 | I19: 2026-10-22 | J19: 0.008
A20: IF_PriceCached_Sol | B20: TK_IF_PriceCached_Sol | C20: 快取輸入 $/M — OpenAI 有效 | D20: $/M | E20: 1 | F20: OK | G20: v19.0 | H20: 1916a06 | I20: 2026-10-22 | J20: 0.16
A21: IF_PriceFresh_Astra | B21: TK_IF_PriceFresh_Astra | C21: 新鮮輸入 $/M — OpenAI 有效 | D21: $/M | E21: 1 | F21: OK | G21: v19.0 | H21: 1916a06 | I21: 2026-10-22 | J21: 8
A22: IF_PriceFresh_Luna | B22: TK_IF_PriceFresh_Luna | C22: 新鮮輸入 $/M — OpenAI 有效 | D22: $/M | E22: 1 | F22: OK | G22: v19.0 | H22: 1916a06 | I22: 2026-10-22 | J22: 0.08
A23: IF_PriceFresh_Sol | B23: TK_IF_PriceFresh_Sol | C23: 新鮮輸入 $/M — OpenAI 有效 | D23: $/M | E23: 1 | F23: OK | G23: v19.0 | H23: 1916a06 | I23: 2026-10-22 | J23: 1.6
A24: IF_PriceOut_Astra | B24: TK_IF_PriceOut_Astra | C24: 可見輸出 $/M — OpenAI 有效 | D24: $/M | E24: 1 | F24: OK | G24: v19.0 | H24: 1916a06 | I24: 2026-10-22 | J24: 40
A25: IF_PriceOut_Luna | B25: TK_IF_PriceOut_Luna | C25: 可見輸出 $/M — OpenAI 有效 | D25: $/M | E25: 1 | F25: OK | G25: v19.0 | H25: 1916a06 | I25: 2026-10-22 | J25: 0.4
A26: IF_PriceOut_Sol | B26: TK_IF_PriceOut_Sol | C26: 可見輸出 $/M — OpenAI 有效 | D26: $/M | E26: 1 | F26: OK | G26: v19.0 | H26: 1916a06 | I26: 2026-10-22 | J26: 8
A27: IF_PriceRef_Astra | B27: TK_IF_PriceRef_Astra | C27: 參考請求混合 $/M — OpenAI 有效 | D27: $/M | E27: 1 | F27: OK | G27: v19.0 | H27: 1916a06 | I27: 2026-10-22 | J27: 8.0355556
A28: IF_PriceRef_Luna | B28: TK_IF_PriceRef_Luna | C28: 參考請求混合 $/M — OpenAI 有效 | D28: $/M | E28: 1 | F28: OK | G28: v19.0 | H28: 1916a06 | I28: 2026-10-22 | J28: 0.080355556
A29: IF_PriceRef_Sol | B29: TK_IF_PriceRef_Sol | C29: 參考請求混合 $/M — OpenAI 有效 | D29: $/M | E29: 1 | F29: OK | G29: v19.0 | H29: 1916a06 | I29: 2026-10-22 | J29: 1.6071111
... A35: IF_FrontRef_Sol | B35: TK_IF_FrontRef_Sol | C35: 參考請求混合 $/M — 前緣有效 | D35: $/M | E35: 1 | F35: OK | G35: v19.0 | H35: 1916a06 | I35: 2026-10-22 | J35: 1.6071111
A36: IF_ProgGWyr_Astra | B36: TK_IF_ProgGWyr_Astra | C36: 研發計畫占 1 GW 一年 | D36: % | E36: 15 | F36: OK | G36: v19.0 | H36: 1916a06 | I36: 2026-10-22 | J36: 0.15684814 | K36: 0.15684814 | L36: 0.15684814 | M36: 0.057835529 | N36: 0.057835529 | O36: 0.057835529 | P36: 0.065586407 | Q36: 0.065586407 | R36: 0.065586407 | S36: 0.040017843 | T36: 0.040017843 | U36: 0.040017843 | V36: 0.027250415 | W36: 0.027250415 | X36: 0.027250415
A37: IF_ProgGWyr_Luna | B37: TK_IF_ProgGWyr_Luna | C37: 研發計畫占 1 GW 一年 | D37: % | E37: 15 | F37: OK | G37: v19.0 | H37: 1916a06 | I37: 2026-10-22 | J37: 0.009274344 | K37: 0.009274344 | L37: 0.009274344 | M37: 0.0027645609 | N37: 0.0027645609 | O37: 0.0027645609 | P37: 0.0033289655 | Q37: 0.0033289655 | R37: 0.0033289655 | S37: 0.0022043397 | T37: 0.0022043397 | U37: 0.0022043397 | V37: 0.0014304485 | W37: 0.0014304485 | X37: 0.0014304485
A38: IF_ProgGWyr_Sol | B38: TK_IF_ProgGWyr_Sol | C38: 研發計畫占 1 GW 一年 | D38: % | E38: 15 | F38: OK | G38: v19.0 | H38: 1916a06 | I38: 2026-10-22 | J38: 0.025757353 | K38: 0.025757353 | L38: 0.025757353 | M38: 0.0088777551 | N38: 0.0088777551 | O38: 0.0088777551 | P38: 0.010227304 | Q38: 0.010227304 | R38: 0.010227304 | S38: 0.006421121 | T38: 0.006421121 | U38: 0.006421121 | V38: 0.0043094856 | W38: 0.0043094856 | X38: 0.0043094856
A39: IF_RDMult | B39: TK_IF_RDMult | C39: 研發倍數（第 0 層基準；下游可覆寫） | D39: x | E39: 1 | F39: OK | G39: v19.0 | H39: 1916a06 | I39: 2026-10-22 | J39: 8
A40: IF_TrainGenDefault | B40: TK_IF_TrainGenDefault | C40: 下游預設訓練世代（索引；J13） | D40: 索引 | E40: 1 | F40: OK | G40: v19.0 | H40: 1916a06 | I40: 2026-10-22 | J40: 4
A41: SRC_DEM_004 | B41: TK_SRC_DEM_004 | C41: OpenAI 2025 推論支出（年度；json 一致集（與 005／006／007 同源）） | D41: $B | E41: 1 | F41: OK | G41: v19.0 | H41: 1916a06 | I41: 2026-10-22 | J41: 8.4
A42: SRC_DEM_005 | B42: TK_SRC_DEM_005 | C42: OpenAI 2025 非付費用戶推論支出（年度） | D42: $B | E42: 1 | F42: OK | G42: v19.0 | H42: 1916a06 | I42: 2026-10-22 | J42: 3.9
A43: SRC_DEM_006 | B43: TK_SRC_DEM_006 | C43: OpenAI 2025 訓練支出（年度；約值） | D43: $B | E43: 1 | F43: OK | G43: v19.0 | H43: 1916a06 | I43: 2026-10-22 | J43: 12
A44: SRC_DEM_007 | B44: TK_SRC_DEM_007 | C44: OpenAI 2025 營收（年度） | D44: $B | E44: 1 | F44: OK | G44: v19.0 | H44: 1916a06 | I44: 2026-10-22 | J44: 13.07
A45: SRC_DEM_008 | B45: TK_SRC_DEM_008 | C45: OpenAI 算力規模 2024 年底（GW 口徑未明（D1）） | D45: GW | E45: 1 | F45: OK | G45: v19.0 | H45: 1916a06 | I45: 2026-10-22 | J45: 0.6
A46: SRC_DEM_009 | B46: TK_SRC_DEM_009 | C46: OpenAI 算力規模 2025 年底（約值；口徑未明） | D46: GW | E46: 1 | F46: OK | G46: v19.0 | H46: 1916a06 | I46: 2026-10-22 | J46: 1.9
A47: SRC_DEM_010 | B47: TK_SRC_DEM_010 | C47: OpenAI API 處理量（時點值；API 全部） | D47: B tok/min | E47: 1 | F47: OK | G47: v19.0 | H47: 1916a06 | I47: 2026-10-22 | J47: 6
A48: SRC_DEM_011 | B48: TK_SRC_DEM_011 | C48: OpenAI API 處理量（時點值；「超過」；API 全部） | D48: B tok/min | E48: 1 | F48: OK | G48: v19.0 | H48: 1916a06 | I48: 2026-10-22 | J48: 15
A49: SRC_DEM_012 | B49: TK_SRC_DEM_012 | C49: ChatGPT 每日提示數（全球；其中美國約 0.33B） | D49: B 則/日 | E49: 1 | F49: OK | G49: v19.0 | H49: 1916a06 | I49: 2026-10-22 | J49: 2.5
A50: SRC_DEM_013 | B50: TK_SRC_DEM_013 | C50: 前沿實驗室（OpenAI）每日 token（由算力推估） | D50: T tok/日 | E50: 1 | F50: OK | G50: v19.0 | H50: 1916a06 | I50: 2026-10-22
A51: SRC_DEM_013_Lo | B51: TK_SRC_DEM_013_Lo | C51: 前沿實驗室（OpenAI）每日 token（由算力推估） | D51: T tok/日 | E51: 1 | F51: OK | G51: v19.0 | H51: 1916a06 | I51: 2026-10-22 | J51: 10
A52: SRC_DEM_013_Hi | B52: TK_SRC_DEM_013_Hi | C52: 前沿實驗室（OpenAI）每日 token（由算力推估） | D52: T tok/日 | E52: 1 | F52: OK | G52: v19.0 | H52: 1916a06 | I52: 2026-10-22 | J52: 100
A53: IF_AllocQ1 | B53: TK_IF_AllocQ1 | C53: 研發算力占比 Q1（R1：研發 GW ÷ 研發＋服務 GW；服務 GW＝支出路線，v8.0 D14 主口徑） | D53: % | E53: 1 | F53: OK | G53: v19.0 | H53: 1916a06 | I53: 2026-10-22 | J53: 0.18434736
A54: IF_AllocQ1_R2 | B54: TK_IF_AllocQ1_R2 | C54: 研發算力占比 Q1（R2：免費服務算作產品改良；服務 GW＝支出路線，免費服務 GW＝服務 GW × AL_FreeSpendShare；v9.0 M6） | D54: % | E54: 1 | F54: OK | G54: v19.0 | H54: 1916a06 | I54: 2026-10-22 | J54: 0.56304323
A55: IF_AllocQ2 | B55: TK_IF_AllocQ2 | C55: 研發算力成本占比 Q2（研發 GW × 持有成本 ÷（＋服務持有成本＝SRC_DEM_004，支出路線，v8.0 D14）；利用率不進入） | D55: % | E55: 1 | F55: OK | G55: v19.0 | H55: 1916a06 | I55: 2026-10-22 | J55: 0.1850086
A56: IF_AllocServeGW | B56: TK_IF_AllocServeGW | C56: 服務 GW 合計（支出路線＝SRC_DEM_004 ÷ Σ 世代占比 × 持有成本；v8.0 D14 主口徑；IT 關鍵電力） | D56: GW | E56: 1 | F56: OK | G56: v19.0 | H56: 1916a06 | I56: 2026-10-22 | J56: 0.89809617
A57: IF_AllocRDGW | B57: TK_IF_AllocRDGW | C57: 研發 GW 年（k ×（N_major × 家族＋N_refresh × 改版）；v8.0 L3：2025 研發世代組合加權，Alloc J 節） | D57: GW·年 | E57: 1 | F57: OK | G57: v19.0 | H57: 1916a06 | I57: 2026-10-22 | J57: 0.20298059
A58: IF_AllocDemand | B58: TK_IF_AllocDemand | C58: 需求 D 合計（API＋ChatGPT；付費＋免費 token；2025） | D58: M tok/年 | E58: 1 | F58: OK | G58: v19.0 | H58: 1916a06 | I58: 2026-10-22 | J58: 6015200000
A59: IF_AllocImpliedNk | B59: TK_IF_AllocImpliedNk | C59: 隱含 N × k（2025 支出比反推；以家族計畫當量；A3） [IF_AllocImpliedNk] ｜v10.0 N2（D4）：性質＝倒推（隱含 N × k／J8 落差由 2025 支出反推研發 GW，再除以計畫當量；不是觀測值） | D59: 個 | E59: 1 | F59: OK | G59: v19.0 | H59: 1916a06 | I59: 2026-10-22 | J59: 11.358895
A60: IF_TrainCost_Astra | B60: TK_IF_TrainCost_Astra | C60: 最終訓練成本 — 經濟（依成本情境） [IF_TrainCost_Astra]｜v15.0 O12 口徑：機隊占比取 2025 OpenAI 推論 ÷（推論＋訓練）支出比（B4_Serve×(1−B4_Free)，全部世代同值，Assumed）；訓練成本以 100% 利用率計、服務以 ÷IF_Util 計；縮放倍數與隱含家族計畫數為 Assumed，接受為決策（Decisions SL46-16） | D60: $M | E60: 15 | F60: OK | G60: v19.0 | H60: 1916a06 | I60: 2026-10-22 | J60: 133.14593 | K60: 190.2389 | L60: 326.71016 | M60: 47.799737 | N60: 63.822704 | O60: 103.51529 | P60: 69.102652 | Q60: 89.250074 | R60: 151.9526 | S60: 47.581601 | T60: 61.154623 | U60: 98.797187 | V60: 34.412316 | W60: 52.302002 | X60: 95.479474
A61: IF_TrainCost_Luna | B61: TK_IF_TrainCost_Luna | C61: 最終訓練成本 — 經濟（依成本情境） [IF_TrainCost_Luna]｜v15.0 O12 口徑：機隊占比取 2025 OpenAI 推論 ÷（推論＋訓練）支出比（B4_Serve×(1−B4_Free)，全部世代同值，Assumed）；訓練成本以 100% 利用率計、服務以 ÷IF_Util 計；縮放倍數與隱含家族計畫數為 Assumed，接受為決策（Decisions SL46-16） | D61: $M | E61: 15 | F61: OK | G61: v19.0 | H61: 1916a06 | I61: 2026-10-22 | J61: 7.8728453 | K61: 11.248721 | L61: 19.318192 | M61: 2.2848461 | N61: 3.0507501 | O61: 4.9480714 | P61: 3.5074393 | Q61: 4.5300608 | R61: 7.7126494 | S61: 2.6209811 | T61: 3.3686364 | U61: 5.4421363 | V61: 1.8063963 | W61: 2.7454746 | X61: 5.0119778
A62: IF_TrainCost_Sol | B62: TK_IF_TrainCost_Sol | C62: 最終訓練成本 — 經濟（依成本情境） [IF_TrainCost_Sol]｜v15.0 O12 口徑：機隊占比取 2025 OpenAI 推論 ÷（推論＋訓練）支出比（B4_Serve×(1−B4_Free)，全部世代同值，Assumed）；訓練成本以 100% 利用率計、服務以 ÷IF_Util 計；縮放倍數與隱含家族計畫數為 Assumed，接受為決策（Decisions SL46-16） | D62: $M | E62: 15 | F62: OK | G62: v19.0 | H62: 1916a06 | I62: 2026-10-22 | J62: 21.865014 | K62: 31.240731 | L62: 53.651825 | M62: 7.3372607 | N62: 9.7967864 | O62: 15.8896 | P62: 10.775615 | Q62: 13.91733 | R62: 23.694933 | S62: 7.6347746 | T62: 9.8126536 | U62: 15.852646 | V62: 5.4420963 | W62: 8.2712402 | X62: 15.099492
A63: IF_RevGW_Astra | B63: TK_IF_RevGW_Astra | C63: 每 GW 理論營收 — OpenAI 有效單價（理想上限） | D63: $B/年 | E63: 15 | F63: OK | G63: v19.0 | H63: 1916a06 | I63: 2026-10-22 | J63: 32.828583 | K63: 32.828583 | L63: 32.828583 | M63: 162.35735 | N63: 162.35735 | O63: 162.35735 | P63: 189.27508 | Q63: 189.27508 | R63: 189.27508 | S63: 335.68627 | T63: 335.68627 | U63: 335.68627 | V63: 475.00532 | W63: 475.00532 | X63: 475.00532
A64: IF_RevGW_Luna | B64: TK_IF_RevGW_Luna | C64: 每 GW 理論營收 — OpenAI 有效單價（理想上限） | D64: $B/年 | E64: 15 | F64: OK | G64: v19.0 | H64: 1916a06 | I64: 2026-10-22 | J64: 5.4108976 | K64: 5.4108976 | L64: 5.4108976 | M64: 26.895273 | N64: 26.895273 | O64: 26.895273 | P64: 34.866728 | Q64: 34.866728 | R64: 34.866728 | S64: 50.299414 | T64: 50.299414 | U64: 50.299414 | V64: 67.719869 | W64: 67.719869 | X64: 67.719869
A65: IF_RevGW_Sol | B65: TK_IF_RevGW_Sol | C65: 每 GW 理論營收 — OpenAI 有效單價（理想上限） | D65: $B/年 | E65: 15 | F65: OK | G65: v19.0 | H65: 1916a06 | I65: 2026-10-22 | J65: 32.433029 | K65: 32.433029 | L65: 32.433029 | M65: 157.86574 | N65: 157.86574 | O65: 157.86574 | P65: 204.74691 | Q65: 204.74691 | R65: 204.74691 | S65: 307.5865 | T65: 307.5865 | U65: 307.5865 | V65: 418.85859 | W65: 418.85859 | X65: 418.85859
A66: IF_FullCostDefault_Astra | B66: TK_IF_FullCostDefault_Astra | C66: 全成本 $/M（服務＋快取儲存＋K6 預設攤提；基準利用率；下游預設） [IF_FullCostDefault_Astra]｜v15.0 O12 口徑：機隊占比取 2025 OpenAI 推論 ÷（推論＋訓練）支出比（B4_Serve×(1−B4_Free)，全部世代同值，Assumed）；訓練成本以 100% 利用率計、服務以 ÷IF_Util 計；縮放倍數與隱含家族計畫數為 Assumed，接受為決策（Decisions SL46-16） | D66: $/M | E66: 15 | F66: OK | G66: v19.0 | H66: 1916a06 | I66: 2026-10-22 | J66: 8.3759713 | K66: 11.967214 | L66: 20.551484 | M66: 1.676047 | N66: 2.2375798 | O66: 3.6286264 | P66: 1.7628457 | Q66: 2.2765557 | R66: 3.8753169 | S66: 1.1877619 | T66: 1.5263351 | U66: 2.4653127 | V66: 0.90918461 | W66: 1.3813921 | X66: 2.5210836
A67: IF_FullCostDefault_Luna | B67: TK_IF_FullCostDefault_Luna | C67: 全成本 $/M（服務＋快取儲存＋K6 預設攤提；基準利用率；下游預設） [IF_FullCostDefault_Luna]｜v15.0 O12 口徑：機隊占比取 2025 OpenAI 推論 ÷（推論＋訓練）支出比（B4_Serve×(1−B4_Free)，全部世代同值，Assumed）；訓練成本以 100% 利用率計、服務以 ÷IF_Util 計；縮放倍數與隱含家族計畫數為 Assumed，接受為決策（Decisions SL46-16） | D67: $/M | E67: 15 | F67: OK | G67: v19.0 | H67: 1916a06 | I67: 2026-10-22 | J67: 0.21251361 | K67: 0.30363017 | L67: 0.52142919 | M67: 0.037902157 | N67: 0.050600756 | O67: 0.082058118 | P67: 0.03949907 | Q67: 0.051009372 | R67: 0.086831575 | S67: 0.030093029 | T67: 0.038671399 | U67: 0.062462111 | V67: 0.022920841 | W67: 0.034826064 | X67: 0.063559796
A68: IF_FullCostDefault_Sol | B68: TK_IF_FullCostDefault_Sol | C68: 全成本 $/M（服務＋快取儲存＋K6 預設攤提；基準利用率；下游預設） [IF_FullCostDefault_Sol]｜v15.0 O12 口徑：機隊占比取 2025 OpenAI 推論 ÷（推論＋訓練）支出比（B4_Serve×(1−B4_Free)，全部世代同值，Assumed）；訓練成本以 100% 利用率計、服務以 ÷IF_Util 計；縮放倍數與隱含家族計畫數為 Assumed，接受為決策（Decisions SL46-16） | D68: $/M | E68: 15 | F68: OK | G68: v19.0 | H68: 1916a06 | I68: 2026-10-22 | J68: 0.61214752 | K68: 0.87461837 | L68: 1.5020113 | M68: 0.11908317 | N68: 0.15898747 | O68: 0.25783963 | P68: 0.12094767 | Q68: 0.15619878 | R68: 0.26590678 | S68: 0.088232214 | T68: 0.11338948 | U68: 0.18315906 | V68: 0.067980133 | W68: 0.10329953 | X68: 0.18854431
A69: L1_Ans3 | B69: TK_L1_Ans3 | C69: 問 3：研發占整體成本 Q3（算力部分）（基準） | D69: $B/年 | E69: 1 | F69: OK | G69: v19.0 | H69: 1916a06 | I69: 2026-10-22 | J69: 1.9068572
A70: L1_Ans3_Lo | B70: TK_L1_Ans3_Lo | C70: 問 3：研發占整體成本 Q3（算力部分）（低） | D70: $B/年 | E70: 1 | F70: OK | G70: v19.0 | H70: 1916a06 | I70: 2026-10-22 | J70: 0.95342861
A71: L1_Ans3_Hi | B71: TK_L1_Ans3_Hi | C71: 問 3：研發占整體成本 Q3（算力部分）（高） | D71: $B/年 | E71: 1 | F71: OK | G71: v19.0 | H71: 1916a06 | I71: 2026-10-22 | J71: 13.348001
A72: IF_CapexTotal | B72: TK_IF_CapexTotal | C72: 每 GW 資本支出 — 合計 | D72: $B | E72: 15 | F72: OK | G72: v19.0 | H72: 1916a06 | I72: 2026-10-22 | J72: 31.632269 | K72: 40.180214 | L72: 50.306743 | M72: 30.85139 | N72: 36.685174 | O72: 43.836204 | P72: 38.766902 | Q72: 44.907224 | R72: 55.468606 | S72: 43.485403 | T72: 50.256352 | U72: 58.823575 | V72: 46.057578 | W72: 62.75578 | X72: 81.667558
A73: IF_HdrTask | B73: TK_IF_HdrTask | C73: 任務 | E73: 5 | F73: OK | G73: v19.0 | H73: 1916a06 | I73: 2026-10-22 | J73: 一般聊天 | K73: 推理聊天 | L73: 單代理（工具迴圈） | M73: 多代理研究 | N73: Coding agent（長程）
A74: IF_TaskLen | B74: TK_IF_TaskLen | C74: 任務長度（人類完成時間） | D74: hr | E74: 5 | F74: OK | G74: v19.0 | H74: 1916a06 | I74: 2026-10-22 | J74: 0.02 | K74: 0.1 | L74: 0.5 | M74: 2 | N74: 8
A75: IF_TaskTokFresh | B75: TK_IF_TaskTokFresh | C75: 每次嘗試 新鮮輸入 token（現行） | D75: tok | E75: 5 | F75: OK | G75: v19.0 | H75: 1916a06 | I75: 2026-10-22 | J75: 1500 | K75: 1500 | L75: 6840 | M75: 27360 | N75: 200400
A76: IF_TaskTokCached | B76: TK_IF_TaskTokCached | C76: 每次嘗試 快取輸入 token（現行） | D76: tok | E76: 5 | F76: OK | G76: v19.0 | H76: 1916a06 | I76: 2026-10-22 | J76: 1000 | K76: 1000 | L76: 18360 | M76: 73440 | N76: 1263600
A77: IF_TaskTokDec | B77: TK_IF_TaskTokDec | C77: 每次嘗試 decode token（思考＋可見；現行） | D77: tok | E77: 5 | F77: OK | G77: v19.0 | H77: 1916a06 | I77: 2026-10-22 | J77: 500 | K77: 3700 | L77: 2400 | M77: 9600 | N77: 30000
A78: L1_RevGW_PQ_VR200 | B78: TK_L1_RevGW_PQ_VR200 | C78: VR200 每 GW 營收 P × Q — 第一年（主口徑 m＝L1_M，2026 Q2）（基準） | D78: $B/GW/年 | E78: 1 | F78: OK | G78: v19.0 | H78: 1916a06 | I78: 2026-10-22 | J78: 48.787681
A79: L1_RevGW_PQ_VR200_Lo | B79: TK_L1_RevGW_PQ_VR200_Lo | C79: VR200 每 GW 營收 P × Q — 第一年（主口徑 m＝L1_M，2026 Q2）（低） | D79: $B/GW/年 | E79: 1 | F79: OK | G79: v19.0 | H79: 1916a06 | I79: 2026-10-22 | J79: 35.698303
A80: L1_RevGW_PQ_VR200_Hi | B80: TK_L1_RevGW_PQ_VR200_Hi | C80: VR200 每 GW 營收 P × Q — 第一年（主口徑 m＝L1_M，2026 Q2）（高） | D80: $B/GW/年 | E80: 1 | F80: OK | G80: v19.0 | H80: 1916a06 | I80: 2026-10-22 | J80: 77.346324
A81: L1_RevGW_PQ_VR200_FY | B81: TK_L1_RevGW_PQ_VR200_FY | C81: VR200 每 GW 營收 P × Q — 第一年（m 改用 FY2026：L1_M_FY2026）（基準） | D81: $B/GW/年 | E81: 1 | F81: OK | G81: v19.0 | H81: 1916a06 | I81: 2026-10-22 | J81: 52.002079
A82: L1_RevGW_PQ_VR200_FY_Lo | B82: TK_L1_RevGW_PQ_VR200_FY_Lo | C82: VR200 每 GW 營收 P × Q — 第一年（m 改用 FY2026：L1_M_FY2026）（低） | D82: $B/GW/年 | E82: 1 | F82: OK | G82: v19.0 | H82: 1916a06 | I82: 2026-10-22 | J82: 38.050301
A83: L1_RevGW_PQ_VR200_FY_Hi | B83: TK_L1_RevGW_PQ_VR200_FY_Hi | C83: VR200 每 GW 營收 P × Q — 第一年（m 改用 FY2026：L1_M_FY2026）（高） | D83: $B/GW/年 | E83: 1 | F83: OK | G83: v19.0 | H83: 1916a06 | I83: 2026-10-22 | J83: 82.44232
A84: L1_RevGW_PQ_VR200_Life | B84: TK_L1_RevGW_PQ_VR200_Life | C84: VR200 每 GW 營收 P × Q — 壽命期年均（第一年 × L1_LTotalDisc；假設 m 不變）（基準） | D84: $B/GW/年 | E84: 1 | F84: OK | G84: v19.0 | H84: 1916a06 | I84: 2026-10-22 | J84: 34.095004
A85: L1_RevGW_PQ_VR200_Life_Lo | B85: TK_L1_RevGW_PQ_VR200_Life_Lo | C85: VR200 每 GW 營收 P × Q — 壽命期年均（第一年 × L1_LTotalDisc；假設 m 不變）（低） | D85: $B/GW/年 | E85: 1 | F85: OK | G85: v19.0 | H85: 1916a06 | I85: 2026-10-22 | J85: 15.710264
A86: L1_RevGW_PQ_VR200_Life_Hi | B86: TK_L1_RevGW_PQ_VR200_Life_Hi | C86: VR200 每 GW 營收 P × Q — 壽命期年均（第一年 × L1_LTotalDisc；假設 m 不變）（高） | D86: $B/GW/年 | E86: 1 | F86: OK | G86: v19.0 | H86: 1916a06 | I86: 2026-10-22 | J86: 84.628048
A87: L1_TokGW_PaidPQ_VR200 | B87: TK_L1_TokGW_PaidPQ_VR200 | C87: VR200 每 GW 付費 token 實際產出 Q（M tok／年）（基準） | D87: M tok/年 | E87: 1 | F87: OK | G87: v19.0 | H87: 1916a06 | I87: 2026-10-22 | J87: 1.852522e+10
A88: L1_TokGW_PaidPQ_VR200_Lo | B88: TK_L1_TokGW_PaidPQ_VR200_Lo | C88: VR200 每 GW 付費 token 實際產出 Q（M tok／年）（低） | D88: M tok/年 | E88: 1 | F88: OK | G88: v19.0 | H88: 1916a06 | I88: 2026-10-22 | J88: 1.3555039e+10
A89: L1_TokGW_PaidPQ_VR200_Hi | B89: TK_L1_TokGW_PaidPQ_VR200_Hi | C89: VR200 每 GW 付費 token 實際產出 Q（M tok／年）（高） | D89: M tok/年 | E89: 1 | F89: OK | G89: v19.0 | H89: 1916a06 | I89: 2026-10-22 | J89: 2.9369252e+10
... A134: L1_GapUnexplained_Hi | B134: TK_L1_GapUnexplained_Hi | C134: 落差分解 5：未解釋＝實際缺口 ÷ 四項乘積（L1_ScaleServe2000 ÷ L1_GapProduct）；本分解不是定義式，未解釋部分的來源不可由本表得知（高） | D134: x | E134: 1 | F134: OK | G134: v19.0 | H134: 1916a06 | I134: 2026-10-22 | J134: 15.795508

Sheet OAI_Link
A1: OAI_Link — OpenAI v0.6 命題輸出快照（規格 D20；只作並排對照）
A2: 值由 builder 從 OpenAI v0.6 活頁簿的快取值讀出寫入（藍字）。本頁只被 Checks（與 A5 的 HTML）引用，任何計算頁不得引用（Checks 列 builder 掃描結果；tests 每次重驗）。
A3: OpenAI 的 2025 為其實際校準年。注意：OpenAI v0.6 用 Tokenomics v5.26 快照，本模型自 v0.1.2 起用 v18.0（見 TK_Link）；兩家的 η、供給 GW 與每 GW 產能口徑因此不同，並排對照時差異有一部分來自 Tokenomics 版本，而非公司本身。
A4: OpenAI 檔案 | B4: 20261008_OpenAI_v0.6.xlsx
A5: 檔案 SHA-256 | B5: 34fc34a7ea2c18e8f608356ca462d8bd208496ca61780589b559fd2efc6597fe
A6: git 提交（建置時） | B6: （非 git 工作目錄）
A7: 讀取日期 | B7: 2026-10-22
A9: OpenAI 名稱 | B9: 本模型名稱 | C9: 說明 | D9: 2025 | E9: 2026 | F9: 2027 | G9: 2028 | H9: 2029 | I9: 2030 | J9: 單位 | K9: OpenAI 位置
A10: REV_Gross | B10: OAI_REV_Gross | C10: 營收總額 | D10: 13.07 | E10: 34.203781 | F10: 54.795653 | G10: 78.424089 | H10: 102.12737 | I10: 126.38309 | J10: $B | K10: Revenue!$D$38:$I$38
A11: REV_Net | B11: OAI_REV_Net | C11: 營收淨額（扣 Microsoft 分成） | D11: 10.456 | E11: 27.363025 | F11: 43.836523 | G11: 62.739271 | H11: 97.612079 | I11: 126.38309 | J11: $B | K11: Revenue!$D$41:$I$41
A12: REV_NetCapped | B12: OAI_REV_NetCapped | C12: 營收淨額（容量截頂後） | D12: 10.456 | E12: 27.363025 | F12: 43.836523 | G12: 62.739271 | H12: 97.612079 | I12: 126.38309 | J12: $B | K12: Revenue!$D$77:$I$77
A13: REV_Sub | B13: OAI_REV_Sub | C13: 訂閱營收 | D13: 8.9214194 | E13: 16.936529 | F13: 25.382952 | G13: 33.851419 | H13: 40.685232 | I13: 46.56514 | J13: $B | K13: Revenue!$D$27:$I$27
A14: REV_API | B14: OAI_REV_API | C14: API 營收 | D14: 4.1485806 | E14: 16.524302 | F14: 27.554274 | G14: 41.662063 | H14: 57.285336 | I14: 74.241796 | J14: $B | K14: Revenue!$D$34:$I$34
A15: DEM_Tok_Total | B15: OAI_DEM_Tok_Total | C15: token 合計（付費＋免費） | D15: 3538.0601 | E15: 10018.624 | F15: 22447.299 | G15: 47137.552 | H15: 92412.32 | I15: 173673.87 | J15: T | K15: Demand!$D$51:$I$51
A16: CMP_SupplyGW | B16: OAI_CMP_SupplyGW | C16: 供給 GW | D16: 1.2296032 | E16: 2.8342063 | F16: 9.3367692 | G16: 11.538312 | H16: 14.038324 | I16: 16.09014 | J16: GW | K16: Compute!$D$87:$I$87
A17: CMP_Supply_VReq | B17: OAI_CMP_Supply_VReq | C17: 供給 VR 等值 GW | D17: 0.28264462 | E17: 1.1565252 | F17: 5.7520321 | G17: 8.9411774 | H17: 12.146409 | I17: 14.944726 | J17: GW | K17: Compute!$D$99:$I$99
A18: COST_Compute | B18: OAI_COST_Compute | C18: 算力成本（現金） | D18: 14.755238 | E18: 53.240635 | F18: 141.72603 | G18: 175.21143 | H18: 208.69683 | I18: 228.22222 | J18: $B | K18: Cost!$D$27:$I$27
A19: COST_FullCash | B19: OAI_COST_FullCash | C19: 全成本（現金，含股權報酬） | D19: 29.235238 | E19: 76.078955 | F19: 171.94384 | G19: 212.1254 | H19: 251.9209 | I19: 276.64452 | J19: $B | K19: Cost!$D$87:$I$87
A20: COST_PropRev_VR | B20: OAI_COST_PropRev_VR | C20: 每 VR 等值 GW 營收淨額 | D20: 36.993451 | E20: 23.659688 | F20: 7.6210498 | G20: 7.0168914 | H20: 8.0362912 | I20: 8.456702 | J20: $B/GW/年 | K20: Cost!$D$90:$I$90
A21: COST_PropFull_VR | B21: OAI_COST_PropFull_VR | C21: 每 VR 等值 GW 全成本 | D21: 103.43462 | E21: 65.782359 | F21: 29.892713 | G21: 23.724549 | H21: 20.740361 | I21: 18.511181 | J21: $B/GW/年 | K21: Cost!$D$94:$I$94
... A23: COST_Coverage | B23: OAI_COST_Coverage | C23: 覆蓋率（營收 ÷ 全成本） | D23: 0.35765058 | E23: 0.35966615 | F23: 0.25494674 | G23: 0.29576501 | H23: 0.38747114 | I23: 0.45684293 | J23: 倍 | K23: Cost!$D$98:$I$98
A24: FND_ExtNeed | B24: OAI_FND_ExtNeed | C24: 外部資金需求（當年） | E24: 0 | F24: 38.433249 | G24: 134.87813 | H24: 137.62462 | I24: 131.90881 | J24: $B | K24: Funding!$D$29:$I$29
A25: FND_ExtNeedCum | B25: OAI_FND_ExtNeedCum | C25: 累計外部資金需求（命題 2） | E25: 0 | F25: 38.433249 | G25: 173.31138 | H25: 310.936 | I25: 442.84481 | J25: $B | K25: Funding!$D$31:$I$31
A26: FND_CashEnd | B26: OAI_FND_CashEnd | C26: 年底現金 | D26: 40 | E26: 87.58407 | F26: 10 | G26: 10 | H26: 10 | I26: 10 | J26: $B | K26: Funding!$D$30:$I$30

Sheet Inputs
A1: Inputs — 假設輸入（藍字）：值、低、高、標記、依據、區間理由
A2: 長表格式：一列一個（參數 × 索引）。Analogy／Assumed 一律附區間（M 欄檢查）；Decision 為定義常數或開關（低＝高＝值）。來源 data/anthropic_inputs.yaml；ID 由 builder/id_registry.json 固定。
A3: 引用 OpenAI v0.6 同類參數作 Analogy 者，依據欄寫明「OpenAI v0.6 INP_nnn」與差異。
A4: INP_ID | B4: 參數 | C4: 索引 | D4: 單位 | E4: 值 | F4: 低 | G4: 高 | H4: 標記 | I4: 依據 | J4: 區間理由 | K4: 用途／備註 | L4: 區間順序異常（公式） | M4: Analogy／Assumed 缺區間（公式） | N4: key
A5: INP_001 | B5: 模型年度 | C5: 第 1 年 | D5: 年 | E5: 2025 | F5: 2025 | G5: 2025 | H5: Decision | I5: 曆年制；2025 為實際校準年（規格 D1、D14） | J5: 定義值 | K5: Demand／Revenue 第 6 列年度 | L5: =IF(AND(ISNUMBER($E5),ISNUMBER($F5),ISNUMBER($G5)),IF(AND($F5<=$E5,$E5<=$G5),0,1),0) -> 0 | M5: =IF(AND(OR($H5="Analogy",$H5="Assumed"),OR(NOT(ISNUMBER($F5)),NOT(ISNUMBER($G5)))),1,0) -> 0 | N5: year_2025
A6: INP_002 | B6: 模型年度 | C6: 第 2 年 | D6: 年 | E6: 2026 | F6: 2026 | G6: 2026 | H6: Decision | I6: 2026 為半校準年（規格 D15 r1） | J6: 定義值 | L6: =IF(AND(ISNUMBER($E6),ISNUMBER($F6),ISNUMBER($G6)),IF(AND($F6<=$E6,$E6<=$G6),0,1),0) -> 0 | M6: =IF(AND(OR($H6="Analogy",$H6="Assumed"),OR(NOT(ISNUMBER($F6)),NOT(ISNUMBER($G6)))),1,0) -> 0 | N6: year_2026
A7: INP_003 | B7: 模型年度 | C7: 第 3 年 | D7: 年 | E7: 2027 | F7: 2027 | G7: 2027 | H7: Decision | I7: 曆年制 | J7: 定義值 | L7: =IF(AND(ISNUMBER($E7),ISNUMBER($F7),ISNUMBER($G7)),IF(AND($F7<=$E7,$E7<=$G7),0,1),0) -> 0 | M7: =IF(AND(OR($H7="Analogy",$H7="Assumed"),OR(NOT(ISNUMBER($F7)),NOT(ISNUMBER($G7)))),1,0) -> 0 | N7: year_2027
A8: INP_004 | B8: 模型年度 | C8: 第 4 年 | D8: 年 | E8: 2028 | F8: 2028 | G8: 2028 | H8: Decision | I8: 曆年制 | J8: 定義值 | L8: =IF(AND(ISNUMBER($E8),ISNUMBER($F8),ISNUMBER($G8)),IF(AND($F8<=$E8,$E8<=$G8),0,1),0) -> 0 | M8: =IF(AND(OR($H8="Analogy",$H8="Assumed"),OR(NOT(ISNUMBER($F8)),NOT(ISNUMBER($G8)))),1,0) -> 0 | N8: year_2028
A9: INP_005 | B9: 模型年度 | C9: 第 5 年 | D9: 年 | E9: 2029 | F9: 2029 | G9: 2029 | H9: Decision | I9: 曆年制 | J9: 定義值 | L9: =IF(AND(ISNUMBER($E9),ISNUMBER($F9),ISNUMBER($G9)),IF(AND($F9<=$E9,$E9<=$G9),0,1),0) -> 0 | M9: =IF(AND(OR($H9="Analogy",$H9="Assumed"),OR(NOT(ISNUMBER($F9)),NOT(ISNUMBER($G9)))),1,0) -> 0 | N9: year_2029
A10: INP_006 | B10: 模型年度 | C10: 第 6 年 | D10: 年 | E10: 2030 | F10: 2030 | G10: 2030 | H10: Decision | I10: 曆年制 | J10: 定義值 | L10: =IF(AND(ISNUMBER($E10),ISNUMBER($F10),ISNUMBER($G10)),IF(AND($F10<=$E10,$E10<=$G10),0,1),0) -> 0 | M10: =IF(AND(OR($H10="Analogy",$H10="Assumed"),OR(NOT(ISNUMBER($F10)),NOT(ISNUMBER($G10)))),1,0) -> 0 | N10: year_2030
A11: INP_007 | B11: 每年天數（定義常數） | C11: — | D11: 天 | E11: 365 | F11: 365 | G11: 365 | H11: Decision | I11: 定義常數 | J11: 不適用 | K11: 每日任務 × 天數 → 年 token | L11: =IF(AND(ISNUMBER($E11),ISNUMBER($F11),ISNUMBER($G11)),IF(AND($F11<=$E11,$E11<=$G11),0,1),0) -> 0 | M11: =IF(AND(OR($H11="Analogy",$H11="Assumed"),OR(NOT(ISNUMBER($F11)),NOT(ISNUMBER($G11)))),1,0) -> 0 | N11: days_per_year
A12: INP_008 | B12: 每年月數（定義常數） | C12: — | D12: 月 | E12: 12 | F12: 12 | G12: 12 | H12: Decision | I12: 定義常數 | J12: 不適用 | K12: 月費 × 12 → 年營收 | L12: =IF(AND(ISNUMBER($E12),ISNUMBER($F12),ISNUMBER($G12)),IF(AND($F12<=$E12,$E12<=$G12),0,1),0) -> 0 | M12: =IF(AND(OR($H12="Analogy",$H12="Assumed"),OR(NOT(ISNUMBER($F12)),NOT(ISNUMBER($G12)))),1,0) -> 0 | N12: months_per_year
A13: INP_009 | B13: 下半年月數（定義常數） | C13: — | D13: 月 | E13: 6 | F13: 6 | G13: 6 | H13: Decision | I13: 定義常數；規格 D15 r1「下半年＝最新年化營收 ÷ 2」＝年化 × 6 ÷ 12 | J13: 不適用 | K13: 2026 半校準 | L13: =IF(AND(ISNUMBER($E13),ISNUMBER($F13),ISNUMBER($G13)),IF(AND($F13<=$E13,$E13<=$G13),0,1),0) -> 0 | M13: =IF(AND(OR($H13="Analogy",$H13="Assumed"),OR(NOT(ISNUMBER($F13)),NOT(ISNUMBER($G13)))),1,0) -> 0 | N13: h2_months
A14: INP_010 | B14: 年度起始月（定義常數） | C14: — | D14: 月 | E14: 1 | F14: 1 | G14: 1 | H14: Decision | I14: 曆年制 | J14: 不適用 | K14: DATE(年度 | L14: =IF(AND(ISNUMBER($E14),ISNUMBER($F14),ISNUMBER($G14)),IF(AND($F14<=$E14,$E14<=$G14),0,1),0) -> 0 | M14: =IF(AND(OR($H14="Analogy",$H14="Assumed"),OR(NOT(ISNUMBER($F14)),NOT(ISNUMBER($G14)))),1,0) -> 0 | N14: fy_start_month
A15: INP_011 | B15: 年度起始日（定義常數） | C15: — | D15: 日 | E15: 1 | F15: 1 | G15: 1 | H15: Decision | I15: 曆年制 | J15: 不適用 | K15: 同上 | L15: =IF(AND(ISNUMBER($E15),ISNUMBER($F15),ISNUMBER($G15)),IF(AND($F15<=$E15,$E15<=$G15),0,1),0) -> 0 | M15: =IF(AND(OR($H15="Analogy",$H15="Assumed"),OR(NOT(ISNUMBER($F15)),NOT(ISNUMBER($G15)))),1,0) -> 0 | N15: fy_start_day
A16: INP_012 | B16: 單位換算：$M → $B 的除數（定義常數） | C16: — | D16: $M／$B | E16: 1000 | F16: 1000 | G16: 1000 | H16: Decision | I16: 定義常數 | J16: 不適用 | K16: 人數（M）× 月費 × 12＝$M；T token × $/M token＝$M | L16: =IF(AND(ISNUMBER($E16),ISNUMBER($F16),ISNUMBER($G16)),IF(AND($F16<=$E16,$E16<=$G16),0,1),0) -> 0 | M16: =IF(AND(OR($H16="Analogy",$H16="Assumed"),OR(NOT(ISNUMBER($F16)),NOT(ISNUMBER($G16)))),1,0) -> 0 | N16: m_to_b
A17: INP_013 | B17: 單位換算：B token → T token 的除數（定義常數） | C17: — | D17: B／T | E17: 1000 | F17: 1000 | G17: 1000 | H17: Decision | I17: 定義常數 | J17: 不適用 | K17: 人數（M）× 任務 × 每任務 K token＝B token | L17: =IF(AND(ISNUMBER($E17),ISNUMBER($F17),ISNUMBER($G17)),IF(AND($F17<=$E17,$E17<=$G17),0,1),0) -> 0 | M17: =IF(AND(OR($H17="Analogy",$H17="Assumed"),OR(NOT(ISNUMBER($F17)),NOT(ISNUMBER($G17)))),1,0) -> 0 | N17: b_to_t
A18: INP_014 | B18: SpaceX 月費合約期間（月） | C18: — | D18: 月 | E18: 36 | F18: 36 | G18: 36 | H18: Decision | I18: SRC_ANT_227 期間「2026-05 至 2029-05」＝36 個月（定義值） | J18: 由揭露期間換算，不另設區間 | K18: SRC_ANT_230（Derived）＝月費 × 本列 | L18: =IF(AND(ISNUMBER($E18),ISNUMBER($F18),ISNUMBER($G18)),IF(AND($F18<=$E18,$E18<=$G18),0,1),0) -> 0 | M18: =IF(AND(OR($H18="Analogy",$H18="Assumed"),OR(NOT(ISNUMBER($F18)),NOT(ISNUMBER($G18)))),1,0) -> 0 | N18: spacex_term_months
A19: INP_015 | B19: 價格彈性起算年 | C19: — | D19: 年 | E19: 2027 | F19: 2027 | G19: 2027 | H19: Decision | I19: 2025 校準年、2026 半校準年（D14、D15 r1）不套彈性；同 OpenAI v0.6 INP_004 | J19: 定義值 | K19: Demand API 第三節 | L19: =IF(AND(ISNUMBER($E19),ISNUMBER($F19),ISNUMBER($G19)),IF(AND($F19<=$E19,$E19<=$G19),0,1),0) -> 0 | M19: =IF(AND(OR($H19="Analogy",$H19="Assumed"),OR(NOT(ISNUMBER($F19)),NOT(ISNUMBER($G19)))),1,0) -> 0 | N19: elasticity_start_year
A20: INP_017 | B20: 廣告營收（D3） | C20: — | D20: $B/年 | E20: 0 | F20: 0 | G20: 0 | H20: Decision | I20: 規格 D3：Anthropic 公開承諾 Claude 不放廣告，不設驅動 | J20: 公司公開立場；若反轉再加驅動 | K20: Revenue 第八節 | L20: =IF(AND(ISNUMBER($E20),ISNUMBER($F20),ISNUMBER($G20)),IF(AND($F20<=$E20,$E20<=$G20),0,1),0) -> 0 | M20: =IF(AND(OR($H20="Analogy",$H20="Assumed"),OR(NOT(ISNUMBER($F20)),NOT(ISNUMBER($G20)))),1,0) -> 0 | N20: ads_revenue
A21: INP_018 | B21: 2026 年營收對里程碑推估差距的 WARN 門檻 | C21: — | D21: 比例 | E21: 0.25 | F21: 0.25 | G21: 0.25 | H21: Decision | I21: 工作單 A2 第 6 步：2026 run-rate 對照差距 >25% 立 WARN（規格 D15） | J21: 工作單定值 | K21: Checks | L21: =IF(AND(ISNUMBER($E21),ISNUMBER($F21),ISNUMBER($G21)),IF(AND($F21<=$E21,$E21<=$G21),0,1),0) -> 0 | M21: =IF(AND(OR($H21="Analogy",$H21="Assumed"),OR(NOT(ISNUMBER($F21)),NOT(ISNUMBER($G21)))),1,0) -> 0 | N21: runrate_warn_threshold
A22: INP_180 | B22: U1 D15 r2 半校準開關（1＝2026 營收基準＝上半年實際＋Q3 實際＋Q4；0＝v0.1 的 r1＝Q1＋Q2＋2026-07 年化 × 6／12） | C22: — | D22: 開關 | E22: 1 | F22: 0 | G22: 1 | H22: Decision | I22: 工作單 20261021 U1；規格 D15 r2（S-1 草稿與 Q3 投資人簡報已給上半年與 Q3 實際） | J22: 開關 | K22: 設 0 可逐位元重現 v0.1 的 2026 基準（回歸測試） | L22: =IF(AND(ISNUMBER($E22),ISNUMBER($F22),ISNUMBER($G22)),IF(AND($F22<=$E22,$E22<=$G22),0,1),0) -> 0 | M22: =IF(AND(OR($H22="Analogy",$H22="Assumed"),OR(NOT(ISNUMBER($F22)),NOT(ISNUMBER($G22)))),1,0) -> 0 | N22: u1_switch
... A26: INP_019 | B26: Pro 年付占比 | C26: — | D26: 比例 | E26: 0.3 | F26: 0.1 | G26: 0.5 | H26: Assumed | I26: 工作單 A2 判斷類預設（年付占比 0.3）；Pro 年付月均 $17（SRC_ANT_142）vs 月付 $20（SRC_ANT_141） | J26: 工作單預設區間 0.1–0.5 | K26: Pro 實收月費＝月付 ×（1−占比）＋年付月均 × 占比 | L26: =IF(AND(ISNUMBER($E26),ISNUMBER($F26),ISNUMBER($G26)),IF(AND($F26<=$E26,$E26<=$G26),0,1),0) -> 0 | M26: =IF(AND(OR($H26="Analogy",$H26="Assumed"),OR(NOT(ISNUMBER($F26)),NOT(ISNUMBER($G26)))),1,0) -> 0 | N26: pro_annual_share
A27: INP_020 | B27: Team 年付占比（標準與 Premium 席位） | C27: — | D27: 比例 | E27: 0.3 | F27: 0.1 | G27: 0.5 | H27: Assumed | I27: 同 Pro 年付占比（工作單預設）；Team 年付 $20／$100 vs 月付 $25／$125（SRC_ANT_146–149） | J27: 同上 | L27: =IF(AND(ISNUMBER($E27),ISNUMBER($F27),ISNUMBER($G27)),IF(AND($F27<=$E27,$E27<=$G27),0,1),0) -> 0 | M27: =IF(AND(OR($H27="Analogy",$H27="Assumed"),OR(NOT(ISNUMBER($F27)),NOT(ISNUMBER($G27)))),1,0) -> 0 | N27: team_annual_share
A28: INP_021 | B28: 個人付費方案組合：Pro 占付費人數 | C28: 2025 | D28: 比例 | E28: 0.85 | F28: 0.75 | G28: 0.95 | H28: Assumed | I28: 方案別人數未揭露（A1 找不到）；Max 方案 2025-04 才上市（SRC_ANT_145），2025 年均以 Pro 為主 | J28: Max 上市後占比未知，給 ±0.1 | K28: Max 20x＝1 − Pro − Max 5x | L28: =IF(AND(ISNUMBER($E28),ISNUMBER($F28),ISNUMBER($G28)),IF(AND($F28<=$E28,$E28<=$G28),0,1),0) -> 0 | M28: =IF(AND(OR($H28="Analogy",$H28="Assumed"),OR(NOT(ISNUMBER($F28)),NOT(ISNUMBER($G28)))),1,0) -> 0 | N28: cons_mix_pro_2025
A29: INP_022 | B29: 個人付費方案組合：Max 5x 占付費人數 | C29: 2025 | D29: 比例 | E29: 0.1 | F29: 0.03 | G29: 0.15 | H29: Assumed | I29: 同上；Max 5x（$100）多於 Max 20x（$200） | J29: 上市首年占比低 | L29: =IF(AND(ISNUMBER($E29),ISNUMBER($F29),ISNUMBER($G29)),IF(AND($F29<=$E29,$E29<=$G29),0,1),0) -> 0 | M29: =IF(AND(OR($H29="Analogy",$H29="Assumed"),OR(NOT(ISNUMBER($F29)),NOT(ISNUMBER($G29)))),1,0) -> 0 | N29: cons_mix_max5_2025
A30: INP_023 | B30: 個人付費方案組合：Pro 占付費人數 | C30: 2026 起 | D30: 比例 | E30: 0.7 | F30: 0.55 | G30: 0.85 | H30: Assumed | I30: Claude Code 帶動 Max 需求（Claude Code 年化營收 2025-08 $0.5B → 2026-02 $2.5B，SRC_ANT_055、058；企業占一半 SRC_ANT_059） | J30: Max 占比可能更高或回落 | K30: 2027 起沿用 | L30: =IF(AND(ISNUMBER($E30),ISNUMBER($F30),ISNUMBER($G30)),IF(AND($F30<=$E30,$E30<=$G30),0,1),0) -> 0 | M30: =IF(AND(OR($H30="Analogy",$H30="Assumed"),OR(NOT(ISNUMBER($F30)),NOT(ISNUMBER($G30)))),1,0) -> 0 | N30: cons_mix_pro_2026
A31: INP_024 | B31: 個人付費方案組合：Max 5x 占付費人數 | C31: 2026 起 | D31: 比例 | E31: 0.18 | F31: 0.1 | G31: 0.25 | H31: Assumed | I31: 同上 | J31: 同上 | L31: =IF(AND(ISNUMBER($E31),ISNUMBER($F31),ISNUMBER($G31)),IF(AND($F31<=$E31,$E31<=$G31),0,1),0) -> 0 | M31: =IF(AND(OR($H31="Analogy",$H31="Assumed"),OR(NOT(ISNUMBER($F31)),NOT(ISNUMBER($G31)))),1,0) -> 0 | N31: cons_mix_max5_2026
A32: INP_025 | B32: 企業席位組合：Team 標準席位占席位數 | C32: 2025 | D32: 比例 | E32: 0.5 | F32: 0.3 | G32: 0.7 | H32: Assumed | I32: 席位別數量未揭露；大單（Deloitte 47 萬、Cognizant 35 萬，SRC_ANT_174、175）多為 Enterprise | J32: ±0.2 | K32: Enterprise＝1 − 標準 − Premium | L32: =IF(AND(ISNUMBER($E32),ISNUMBER($F32),ISNUMBER($G32)),IF(AND($F32<=$E32,$E32<=$G32),0,1),0) -> 0 | M32: =IF(AND(OR($H32="Analogy",$H32="Assumed"),OR(NOT(ISNUMBER($F32)),NOT(ISNUMBER($G32)))),1,0) -> 0 | N32: seat_mix_std_2025
A33: INP_026 | B33: 企業席位組合：Team Premium 席位占席位數 | C33: 2025 | D33: 比例 | E33: 0.15 | F33: 0.05 | G33: 0.3 | H33: Assumed | I33: Premium（含 Claude Code）以開發者為主 | J33: 同上 | L33: =IF(AND(ISNUMBER($E33),ISNUMBER($F33),ISNUMBER($G33)),IF(AND($F33<=$E33,$E33<=$G33),0,1),0) -> 0 | M33: =IF(AND(OR($H33="Analogy",$H33="Assumed"),OR(NOT(ISNUMBER($F33)),NOT(ISNUMBER($G33)))),1,0) -> 0 | N33: seat_mix_prem_2025
A34: INP_027 | B34: 企業席位組合：Team 標準席位占席位數 | C34: 2026 起 | D34: 比例 | E34: 0.35 | F34: 0.2 | G34: 0.5 | H34: Assumed | I34: 2026 大型企業部署（TCS、TELUS、Barclays，SRC_ANT_178–180）使 Enterprise 占比上升 | J34: ±0.15 | K34: 2027 起沿用 | L34: =IF(AND(ISNUMBER($E34),ISNUMBER($F34),ISNUMBER($G34)),IF(AND($F34<=$E34,$E34<=$G34),0,1),0) -> 0 | M34: =IF(AND(OR($H34="Analogy",$H34="Assumed"),OR(NOT(ISNUMBER($F34)),NOT(ISNUMBER($G34)))),1,0) -> 0 | N34: seat_mix_std_2026
A35: INP_028 | B35: 企業席位組合：Team Premium 席位占席位數 | C35: 2026 起 | D35: 比例 | E35: 0.2 | F35: 0.1 | G35: 0.35 | H35: Assumed | I35: 同上 | J35: 同上 | L35: =IF(AND(ISNUMBER($E35),ISNUMBER($F35),ISNUMBER($G35)),IF(AND($F35<=$E35,$E35<=$G35),0,1),0) -> 0 | M35: =IF(AND(OR($H35="Analogy",$H35="Assumed"),OR(NOT(ISNUMBER($F35)),NOT(ISNUMBER($G35)))),1,0) -> 0 | N35: seat_mix_prem_2026
A36: INP_029 | B36: 個人付費轉換率（付費 ÷ 月活；只用於 2025 未校準對照） | C36: 2025 | D36: 比例 | E36: 0.05 | F36: 0.03 | G36: 0.08 | H36: Analogy | I36: OpenAI ChatGPT 付費約占週活 4–5%（OpenAI v0.6 SRC_OAI 35M 付費 ÷ 約 700–800M 週活）；Anthropic 付費人數不揭露（SRC_ANT not_found） | J36: 消費 AI 訂閱常見 3–8% | K36: 只進 Revenue 第十一節未校準列，不進基準 | L36: =IF(AND(ISNUMBER($E36),ISNUMBER($F36),ISNUMBER($G36)),IF(AND($F36<=$E36,$E36<=$G36),0,1),0) -> 0 | M36: =IF(AND(OR($H36="Analogy",$H36="Assumed"),OR(NOT(ISNUMBER($F36)),NOT(ISNUMBER($G36)))),1,0) -> 0 | N36: paid_conv_2025
A37: INP_030 | B37: 個人付費人數年增率 | C37: 2026 | D37: 比例/年 | E37: 3 | F37: 1.5 | G37: 5 | H37: Assumed | I37: 「付費訂閱今年以來已翻倍以上」（2026-03，SRC_ANT_169）；App 月活年增 640%（SRC_ANT_171）。FY 平均 ÷ FY 平均，年初 3 個月已 ×2 | J37: 下限＝全年只再小幅成長；上限＝App 月活增速 | K37: 2026 只影響訂閱與 API 的拆分（總額由 D15 r1 半校準決定） | L37: =IF(AND(ISNUMBER($E37),ISNUMBER($F37),ISNUMBER($G37)),IF(AND($F37<=$E37,$E37<=$G37),0,1),0) -> 0 | M37: =IF(AND(OR($H37="Analogy",$H37="Assumed"),OR(NOT(ISNUMBER($F37)),NOT(ISNUMBER($G37)))),1,0) -> 0 | N37: g_cons_2026
A38: INP_031 | B38: 個人付費人數年增率 | C38: 2027 | D38: 比例/年 | E38: 0.6 | F38: 0.3 | G38: 1 | H38: Assumed | I38: 成長遞減；不以公司目標反推 | J38: ±0.3–0.4 | L38: =IF(AND(ISNUMBER($E38),ISNUMBER($F38),ISNUMBER($G38)),IF(AND($F38<=$E38,$E38<=$G38),0,1),0) -> 0 | M38: =IF(AND(OR($H38="Analogy",$H38="Assumed"),OR(NOT(ISNUMBER($F38)),NOT(ISNUMBER($G38)))),1,0) -> 0 | N38: g_cons_2027
A39: INP_032 | B39: 個人付費人數年增率 | C39: 2028 | D39: 比例/年 | E39: 0.4 | F39: 0.2 | G39: 0.7 | H39: Assumed | I39: 同上 | J39: 同上 | L39: =IF(AND(ISNUMBER($E39),ISNUMBER($F39),ISNUMBER($G39)),IF(AND($F39<=$E39,$E39<=$G39),0,1),0) -> 0 | M39: =IF(AND(OR($H39="Analogy",$H39="Assumed"),OR(NOT(ISNUMBER($F39)),NOT(ISNUMBER($G39)))),1,0) -> 0 | N39: g_cons_2028
A40: INP_033 | B40: 個人付費人數年增率 | C40: 2029 | D40: 比例/年 | E40: 0.3 | F40: 0.1 | G40: 0.5 | H40: Assumed | I40: 同上 | J40: 同上 | L40: =IF(AND(ISNUMBER($E40),ISNUMBER($F40),ISNUMBER($G40)),IF(AND($F40<=$E40,$E40<=$G40),0,1),0) -> 0 | M40: =IF(AND(OR($H40="Analogy",$H40="Assumed"),OR(NOT(ISNUMBER($F40)),NOT(ISNUMBER($G40)))),1,0) -> 0 | N40: g_cons_2029
A41: INP_034 | B41: 個人付費人數年增率 | C41: 2030 | D41: 比例/年 | E41: 0.2 | F41: 0.05 | G41: 0.4 | H41: Assumed | I41: 同上 | J41: 同上 | L41: =IF(AND(ISNUMBER($E41),ISNUMBER($F41),ISNUMBER($G41)),IF(AND($F41<=$E41,$E41<=$G41),0,1),0) -> 0 | M41: =IF(AND(OR($H41="Analogy",$H41="Assumed"),OR(NOT(ISNUMBER($F41)),NOT(ISNUMBER($G41)))),1,0) -> 0 | N41: g_cons_2030
A42: INP_035 | B42: 免費人數年增率 | C42: 2026 | D42: 比例/年 | E42: 1 | F42: 0.5 | G42: 2 | H42: Assumed | I42: 消費者用戶 1 | J42: 第三方估計分歧大 | K42: 免費只產生 token（A3 算力），不產生營收 | L42: =IF(AND(ISNUMBER($E42),ISNUMBER($F42),ISNUMBER($G42)),IF(AND($F42<=$E42,$E42<=$G42),0,1),0) -> 0 | M42: =IF(AND(OR($H42="Analogy",$H42="Assumed"),OR(NOT(ISNUMBER($F42)),NOT(ISNUMBER($G42)))),1,0) -> 0 | N42: g_free_2026
A43: INP_036 | B43: 免費人數年增率 | C43: 2027 | D43: 比例/年 | E43: 0.5 | F43: 0.2 | G43: 0.8 | H43: Assumed | I43: 成長遞減 | J43: ±0.3 | L43: =IF(AND(ISNUMBER($E43),ISNUMBER($F43),ISNUMBER($G43)),IF(AND($F43<=$E43,$E43<=$G43),0,1),0) -> 0 | M43: =IF(AND(OR($H43="Analogy",$H43="Assumed"),OR(NOT(ISNUMBER($F43)),NOT(ISNUMBER($G43)))),1,0) -> 0 | N43: g_free_2027
A44: INP_037 | B44: 免費人數年增率 | C44: 2028 | D44: 比例/年 | E44: 0.3 | F44: 0.1 | G44: 0.5 | H44: Assumed | I44: 同上 | J44: ±0.2 | L44: =IF(AND(ISNUMBER($E44),ISNUMBER($F44),ISNUMBER($G44)),IF(AND($F44<=$E44,$E44<=$G44),0,1),0) -> 0 | M44: =IF(AND(OR($H44="Analogy",$H44="Assumed"),OR(NOT(ISNUMBER($F44)),NOT(ISNUMBER($G44)))),1,0) -> 0 | N44: g_free_2028
A45: INP_038 | B45: 免費人數年增率 | C45: 2029 | D45: 比例/年 | E45: 0.2 | F45: 0.05 | G45: 0.4 | H45: Assumed | I45: 同上 | J45: 同上 | L45: =IF(AND(ISNUMBER($E45),ISNUMBER($F45),ISNUMBER($G45)),IF(AND($F45<=$E45,$E45<=$G45),0,1),0) -> 0 | M45: =IF(AND(OR($H45="Analogy",$H45="Assumed"),OR(NOT(ISNUMBER($F45)),NOT(ISNUMBER($G45)))),1,0) -> 0 | N45: g_free_2029
A46: INP_039 | B46: 免費人數年增率 | C46: 2030 | D46: 比例/年 | E46: 0.15 | F46: 0.05 | G46: 0.3 | H46: Assumed | I46: 同上 | J46: 同上 | L46: =IF(AND(ISNUMBER($E46),ISNUMBER($F46),ISNUMBER($G46)),IF(AND($F46<=$E46,$E46<=$G46),0,1),0) -> 0 | M46: =IF(AND(OR($H46="Analogy",$H46="Assumed"),OR(NOT(ISNUMBER($F46)),NOT(ISNUMBER($G46)))),1,0) -> 0 | N46: g_free_2030
A47: INP_040 | B47: 企業席位數年增率 | C47: 2026 | D47: 比例/年 | E47: 3 | F47: 1 | G47: 5 | H47: Assumed | I47: 2025-10 起大單陸續部署（Deloitte 47 萬、Cognizant 35 萬、TCS 5 萬、TELUS 5.7 萬，SRC_ANT_174–179）；2025 倒推席位約 16 萬 | J47: 大單部署時程與計費方式（席位 vs 用量）不明 | K47: Enterprise 2026 起改「$20 席位費＋用量按 API 計價」（SRC_ANT_152），用量落在 API 營收 | L47: =IF(AND(ISNUMBER($E47),ISNUMBER($F47),ISNUMBER($G47)),IF(AND($F47<=$E47,$E47<=$G47),0,1),0) -> 0 | M47: =IF(AND(OR($H47="Analogy",$H47="Assumed"),OR(NOT(ISNUMBER($F47)),NOT(ISNUMBER($G47)))),1,0) -> 0 | N47: g_seats_2026
A48: INP_041 | B48: 企業席位數年增率 | C48: 2027 | D48: 比例/年 | E48: 1 | F48: 0.5 | G48: 1.5 | H48: Assumed | I48: 成長遞減；不以公司目標反推 | J48: ±0.5 | L48: =IF(AND(ISNUMBER($E48),ISNUMBER($F48),ISNUMBER($G48)),IF(AND($F48<=$E48,$E48<=$G48),0,1),0) -> 0 | M48: =IF(AND(OR($H48="Analogy",$H48="Assumed"),OR(NOT(ISNUMBER($F48)),NOT(ISNUMBER($G48)))),1,0) -> 0 | N48: g_seats_2027
A49: INP_042 | B49: 企業席位數年增率 | C49: 2028 | D49: 比例/年 | E49: 0.5 | F49: 0.25 | G49: 0.8 | H49: Assumed | I49: 同上 | J49: 同上 | L49: =IF(AND(ISNUMBER($E49),ISNUMBER($F49),ISNUMBER($G49)),IF(AND($F49<=$E49,$E49<=$G49),0,1),0) -> 0 | M49: =IF(AND(OR($H49="Analogy",$H49="Assumed"),OR(NOT(ISNUMBER($F49)),NOT(ISNUMBER($G49)))),1,0) -> 0 | N49: g_seats_2028
A50: INP_043 | B50: 企業席位數年增率 | C50: 2029 | D50: 比例/年 | E50: 0.35 | F50: 0.15 | G50: 0.5 | H50: Assumed | I50: 同上 | J50: 同上 | L50: =IF(AND(ISNUMBER($E50),ISNUMBER($F50),ISNUMBER($G50)),IF(AND($F50<=$E50,$E50<=$G50),0,1),0) -> 0 | M50: =IF(AND(OR($H50="Analogy",$H50="Assumed"),OR(NOT(ISNUMBER($F50)),NOT(ISNUMBER($G50)))),1,0) -> 0 | N50: g_seats_2029
A51: INP_044 | B51: 企業席位數年增率 | C51: 2030 | D51: 比例/年 | E51: 0.25 | F51: 0.1 | G51: 0.4 | H51: Assumed | I51: 同上 | J51: 同上 | L51: =IF(AND(ISNUMBER($E51),ISNUMBER($F51),ISNUMBER($G51)),IF(AND($F51<=$E51,$E51<=$G51),0,1),0) -> 0 | M51: =IF(AND(OR($H51="Analogy",$H51="Assumed"),OR(NOT(ISNUMBER($F51)),NOT(ISNUMBER($G51)))),1,0) -> 0 | N51: g_seats_2030
A52: INP_045 | B52: 每人每日任務數：Free | C52: 2025 | D52: 任務/日 | E52: 2 | F52: 1 | G52: 4 | H52: Analogy | I52: OpenAI v0.6 INP_102（free 1.7） | J52: ×0.5–×2 | K52: 2026 起 ×（1＋每日任務數年增率） | L52: =IF(AND(ISNUMBER($E52),ISNUMBER($F52),ISNUMBER($G52)),IF(AND($F52<=$E52,$E52<=$G52),0,1),0) -> 0 | M52: =IF(AND(OR($H52="Analogy",$H52="Assumed"),OR(NOT(ISNUMBER($F52)),NOT(ISNUMBER($G52)))),1,0) -> 0 | N52: tasks_free
A53: INP_046 | B53: 每人每日任務數：Pro | C53: 2025 | D53: 任務/日 | E53: 8 | F53: 4 | G53: 15 | H53: Analogy | I53: OpenAI v0.6 INP_106（plus 13.4）；Pro 有用量上限（五小時窗） | J53: ×0.5–×2 | L53: =IF(AND(ISNUMBER($E53),ISNUMBER($F53),ISNUMBER($G53)),IF(AND($F53<=$E53,$E53<=$G53),0,1),0) -> 0 | M53: =IF(AND(OR($H53="Analogy",$H53="Assumed"),OR(NOT(ISNUMBER($F53)),NOT(ISNUMBER($G53)))),1,0) -> 0 | N53: tasks_pro
A54: INP_047 | B54: 每人每日任務數：Max 5x | C54: 2025 | D54: 任務/日 | E54: 20 | F54: 10 | G54: 40 | H54: Analogy | I54: OpenAI v0.6 INP_108（pro 41）；Max 5x 用量上限為 Pro 的 5 倍 | J54: ×0.5–×2 | L54: =IF(AND(ISNUMBER($E54),ISNUMBER($F54),ISNUMBER($G54)),IF(AND($F54<=$E54,$E54<=$G54),0,1),0) -> 0 | M54: =IF(AND(OR($H54="Analogy",$H54="Assumed"),OR(NOT(ISNUMBER($F54)),NOT(ISNUMBER($G54)))),1,0) -> 0 | N54: tasks_max5
A55: INP_048 | B55: 每人每日任務數：Max 20x | C55: 2025 | D55: 任務/日 | E55: 40 | F55: 20 | G55: 80 | H55: Analogy | I55: 同上；Max 20x 用量上限為 Pro 的 20 倍 | J55: ×0.5–×2 | L55: =IF(AND(ISNUMBER($E55),ISNUMBER($F55),ISNUMBER($G55)),IF(AND($F55<=$E55,$E55<=$G55),0,1),0) -> 0 | M55: =IF(AND(OR($H55="Analogy",$H55="Assumed"),OR(NOT(ISNUMBER($F55)),NOT(ISNUMBER($G55)))),1,0) -> 0 | N55: tasks_max20
A56: INP_049 | B56: 每席每日任務數：Team 標準 | C56: 2025 | D56: 任務/日 | E56: 6 | F56: 3 | G56: 12 | H56: Analogy | I56: OpenAI v0.6 INP_110（seats 10.7）；企業席位使用率不均 | J56: ×0.5–×2 | L56: =IF(AND(ISNUMBER($E56),ISNUMBER($F56),ISNUMBER($G56)),IF(AND($F56<=$E56,$E56<=$G56),0,1),0) -> 0 | M56: =IF(AND(OR($H56="Analogy",$H56="Assumed"),OR(NOT(ISNUMBER($F56)),NOT(ISNUMBER($G56)))),1,0) -> 0 | N56: tasks_team_std
A57: INP_050 | B57: 每席每日任務數：Team Premium | C57: 2025 | D57: 任務/日 | E57: 15 | F57: 8 | G57: 30 | H57: Assumed | I57: Premium 含 Claude Code，開發者用量高於標準席位 | J57: ×0.5–×2 | L57: =IF(AND(ISNUMBER($E57),ISNUMBER($F57),ISNUMBER($G57)),IF(AND($F57<=$E57,$E57<=$G57),0,1),0) -> 0 | M57: =IF(AND(OR($H57="Analogy",$H57="Assumed"),OR(NOT(ISNUMBER($F57)),NOT(ISNUMBER($G57)))),1,0) -> 0 | N57: tasks_team_prem
A58: INP_051 | B58: 每席每日任務數：Enterprise | C58: 2025 | D58: 任務/日 | E58: 8 | F58: 4 | G58: 15 | H58: Analogy | I58: OpenAI v0.6 INP_110（seats 10.7） | J58: ×0.5–×2 | L58: =IF(AND(ISNUMBER($E58),ISNUMBER($F58),ISNUMBER($G58)),IF(AND($F58<=$E58,$E58<=$G58),0,1),0) -> 0 | M58: =IF(AND(OR($H58="Analogy",$H58="Assumed"),OR(NOT(ISNUMBER($F58)),NOT(ISNUMBER($G58)))),1,0) -> 0 | N58: tasks_ent
A59: INP_052 | B59: 每人每日任務數年增率 | C59: 2026 起 | D59: 比例/年 | E59: 0.1 | F59: 0.05 | G59: 0.2 | H59: Analogy | I59: OpenAI v0.6 INP_122（0.1；0.05–0.2） | J59: 同 OpenAI | K59: 全部方案同一年增率 | L59: =IF(AND(ISNUMBER($E59),ISNUMBER($F59),ISNUMBER($G59)),IF(AND($F59<=$E59,$E59<=$G59),0,1),0) -> 0 | M59: =IF(AND(OR($H59="Analogy",$H59="Assumed"),OR(NOT(ISNUMBER($F59)),NOT(ISNUMBER($G59)))),1,0) -> 0 | N59: g_tasks
A60: INP_053 | B60: 任務類別占比：對話 | C60: Free | D60: 比例 | E60: 0.95 | F60: 0.85 | G60: 1 | H60: Assumed | I60: 免費方案不含 Claude Code | J60: ±0.1 | K60: 其他代理＝1 − 對話 − 程式代理 | L60: =IF(AND(ISNUMBER($E60),ISNUMBER($F60),ISNUMBER($G60)),IF(AND($F60<=$E60,$E60<=$G60),0,1),0) -> 0 | M60: =IF(AND(OR($H60="Analogy",$H60="Assumed"),OR(NOT(ISNUMBER($F60)),NOT(ISNUMBER($G60)))),1,0) -> 0 | N60: cat_chat_free
A61: INP_054 | B61: 任務類別占比：程式代理 | C61: Free | D61: 比例 | E61: 0 | F61: 0 | G61: 0.05 | H61: Assumed | I61: 免費方案不含 Claude Code | J61: 網頁版偶有程式任務 | L61: =IF(AND(ISNUMBER($E61),ISNUMBER($F61),ISNUMBER($G61)),IF(AND($F61<=$E61,$E61<=$G61),0,1),0) -> 0 | M61: =IF(AND(OR($H61="Analogy",$H61="Assumed"),OR(NOT(ISNUMBER($F61)),NOT(ISNUMBER($G61)))),1,0) -> 0 | N61: cat_code_free
A62: INP_055 | B62: 任務類別占比：對話 | C62: Pro | D62: 比例 | E62: 0.65 | F62: 0.5 | G62: 0.8 | H62: Assumed | I62: Pro 含 Claude Code（有用量上限） | J62: ±0.15 | L62: =IF(AND(ISNUMBER($E62),ISNUMBER($F62),ISNUMBER($G62)),IF(AND($F62<=$E62,$E62<=$G62),0,1),0) -> 0 | M62: =IF(AND(OR($H62="Analogy",$H62="Assumed"),OR(NOT(ISNUMBER($F62)),NOT(ISNUMBER($G62)))),1,0) -> 0 | N62: cat_chat_pro
A63: INP_056 | B63: 任務類別占比：程式代理 | C63: Pro | D63: 比例 | E63: 0.25 | F63: 0.1 | G63: 0.4 | H63: Assumed | I63: 同上 | J63: ±0.15 | L63: =IF(AND(ISNUMBER($E63),ISNUMBER($F63),ISNUMBER($G63)),IF(AND($F63<=$E63,$E63<=$G63),0,1),0) -> 0 | M63: =IF(AND(OR($H63="Analogy",$H63="Assumed"),OR(NOT(ISNUMBER($F63)),NOT(ISNUMBER($G63)))),1,0) -> 0 | N63: cat_code_pro
A64: INP_057 | B64: 任務類別占比：對話 | C64: Max 5x | D64: 比例 | E64: 0.3 | F64: 0.15 | G64: 0.5 | H64: Assumed | I64: Max 用戶以 Claude Code 為主（D4：Claude Code 營收落在 Max 與 Team Premium） | J64: ±0.15–0.2 | L64: =IF(AND(ISNUMBER($E64),ISNUMBER($F64),ISNUMBER($G64)),IF(AND($F64<=$E64,$E64<=$G64),0,1),0) -> 0 | M64: =IF(AND(OR($H64="Analogy",$H64="Assumed"),OR(NOT(ISNUMBER($F64)),NOT(ISNUMBER($G64)))),1,0) -> 0 | N64: cat_chat_max5
A65: INP_058 | B65: 任務類別占比：程式代理 | C65: Max 5x | D65: 比例 | E65: 0.6 | F65: 0.4 | G65: 0.75 | H65: Assumed | I65: 同上 | J65: 同上 | L65: =IF(AND(ISNUMBER($E65),ISNUMBER($F65),ISNUMBER($G65)),IF(AND($F65<=$E65,$E65<=$G65),0,1),0) -> 0 | M65: =IF(AND(OR($H65="Analogy",$H65="Assumed"),OR(NOT(ISNUMBER($F65)),NOT(ISNUMBER($G65)))),1,0) -> 0 | N65: cat_code_max5
A66: INP_059 | B66: 任務類別占比：對話 | C66: Max 20x | D66: 比例 | E66: 0.2 | F66: 0.1 | G66: 0.35 | H66: Assumed | I66: 同上 | J66: 同上 | L66: =IF(AND(ISNUMBER($E66),ISNUMBER($F66),ISNUMBER($G66)),IF(AND($F66<=$E66,$E66<=$G66),0,1),0) -> 0 | M66: =IF(AND(OR($H66="Analogy",$H66="Assumed"),OR(NOT(ISNUMBER($F66)),NOT(ISNUMBER($G66)))),1,0) -> 0 | N66: cat_chat_max20
A67: INP_060 | B67: 任務類別占比：程式代理 | C67: Max 20x | D67: 比例 | E67: 0.7 | F67: 0.5 | G67: 0.85 | H67: Assumed | I67: 同上 | J67: 同上 | L67: =IF(AND(ISNUMBER($E67),ISNUMBER($F67),ISNUMBER($G67)),IF(AND($F67<=$E67,$E67<=$G67),0,1),0) -> 0 | M67: =IF(AND(OR($H67="Analogy",$H67="Assumed"),OR(NOT(ISNUMBER($F67)),NOT(ISNUMBER($G67)))),1,0) -> 0 | N67: cat_code_max20
A68: INP_061 | B68: 任務類別占比：對話 | C68: Team 標準 | D68: 比例 | E68: 0.75 | F68: 0.6 | G68: 0.9 | H68: Assumed | I68: 標準席位以對話與文件為主 | J68: ±0.15 | L68: =IF(AND(ISNUMBER($E68),ISNUMBER($F68),ISNUMBER($G68)),IF(AND($F68<=$E68,$E68<=$G68),0,1),0) -> 0 | M68: =IF(AND(OR($H68="Analogy",$H68="Assumed"),OR(NOT(ISNUMBER($F68)),NOT(ISNUMBER($G68)))),1,0) -> 0 | N68: cat_chat_team_std
A69: INP_062 | B69: 任務類別占比：程式代理 | C69: Team 標準 | D69: 比例 | E69: 0.15 | F69: 0.05 | G69: 0.3 | H69: Assumed | I69: 同上 | J69: 同上 | L69: =IF(AND(ISNUMBER($E69),ISNUMBER($F69),ISNUMBER($G69)),IF(AND($F69<=$E69,$E69<=$G69),0,1),0) -> 0 | M69: =IF(AND(OR($H69="Analogy",$H69="Assumed"),OR(NOT(ISNUMBER($F69)),NOT(ISNUMBER($G69)))),1,0) -> 0 | N69: cat_code_team_std
A70: INP_063 | B70: 任務類別占比：對話 | C70: Team Premium | D70: 比例 | E70: 0.3 | F70: 0.15 | G70: 0.5 | H70: Assumed | I70: Premium 席位含 Claude Code | J70: 同上 | L70: =IF(AND(ISNUMBER($E70),ISNUMBER($F70),ISNUMBER($G70)),IF(AND($F70<=$E70,$E70<=$G70),0,1),0) -> 0 | M70: =IF(AND(OR($H70="Analogy",$H70="Assumed"),OR(NOT(ISNUMBER($F70)),NOT(ISNUMBER($G70)))),1,0) -> 0 | N70: cat_chat_team_prem
A71: INP_064 | B71: 任務類別占比：程式代理 | C71: Team Premium | D71: 比例 | E71: 0.6 | F71: 0.4 | G71: 0.75 | H71: Assumed | I71: 同上 | J71: 同上 | L71: =IF(AND(ISNUMBER($E71),ISNUMBER($F71),ISNUMBER($G71)),IF(AND($F71<=$E71,$E71<=$G71),0,1),0) -> 0 | M71: =IF(AND(OR($H71="Analogy",$H71="Assumed"),OR(NOT(ISNUMBER($F71)),NOT(ISNUMBER($G71)))),1,0) -> 0 | N71: cat_code_team_prem
A72: INP_065 | B72: 任務類別占比：對話 | C72: Enterprise | D72: 比例 | E72: 0.55 | F72: 0.4 | G72: 0.7 | H72: Assumed | I72: 企業部署含開發者與一般員工 | J72: ±0.15 | L72: =IF(AND(ISNUMBER($E72),ISNUMBER($F72),ISNUMBER($G72)),IF(AND($F72<=$E72,$E72<=$G72),0,1),0) -> 0 | M72: =IF(AND(OR($H72="Analogy",$H72="Assumed"),OR(NOT(ISNUMBER($F72)),NOT(ISNUMBER($G72)))),1,0) -> 0 | N72: cat_chat_ent
A73: INP_066 | B73: 任務類別占比：程式代理 | C73: Enterprise | D73: 比例 | E73: 0.3 | F73: 0.15 | G73: 0.45 | H73: Assumed | I73: 同上 | J73: 同上 | L73: =IF(AND(ISNUMBER($E73),ISNUMBER($F73),ISNUMBER($G73)),IF(AND($F73<=$E73,$E73<=$G73),0,1),0) -> 0 | M73: =IF(AND(OR($H73="Analogy",$H73="Assumed"),OR(NOT(ISNUMBER($F73)),NOT(ISNUMBER($G73)))),1,0) -> 0 | N73: cat_code_ent
A74: INP_102 | B74: 任務類別對應的 Tokenomics 任務：對話 | C74: 對話 | D74: 文字（TK_IF_HdrTask 的鍵） | E74: 一般聊天 | F74: 一般聊天 | G74: 一般聊天 | H74: Decision | I74: 每任務 token 屬 AI 技術資料，取自 Tokenomics Interface（IF_TaskTokFresh＋Cached＋Dec；v5.26 一般聊天 3 | J74: 對應關係，不設區間 | K74: SUMIFS 的鍵；Tokenomics 改名時 Checks 轉 ERR | L74: =IF(AND(ISNUMBER($E74),ISNUMBER($F74),ISNUMBER($G74)),IF(AND($F74<=$E74,$E74<=$G74),0,1),0) -> 0 | M74: =IF(AND(OR($H74="Analogy",$H74="Assumed"),OR(NOT(ISNUMBER($F74)),NOT(ISNUMBER($G74)))),1,0) -> 0 | N74: tk_task_chat
A75: INP_103 | B75: 任務類別對應的 Tokenomics 任務：程式代理 | C75: 程式代理 | D75: 文字（TK_IF_HdrTask 的鍵） | E75: Coding agent（長程） | F75: Coding agent（長程） | G75: Coding agent（長程） | H75: Decision | I75: Tokenomics「Coding agent（長程）」每次嘗試約 149 萬 token（任務長度 8 小時，IF_TaskLen） | J75: 同上 | L75: =IF(AND(ISNUMBER($E75),ISNUMBER($F75),ISNUMBER($G75)),IF(AND($F75<=$E75,$E75<=$G75),0,1),0) -> 0 | M75: =IF(AND(OR($H75="Analogy",$H75="Assumed"),OR(NOT(ISNUMBER($F75)),NOT(ISNUMBER($G75)))),1,0) -> 0 | N75: tk_task_code
A76: INP_104 | B76: 任務類別對應的 Tokenomics 任務：其他代理 | C76: 其他代理 | D76: 文字（TK_IF_HdrTask 的鍵） | E76: 單代理（工具迴圈） | F76: 單代理（工具迴圈） | G76: 單代理（工具迴圈） | H76: Decision | I76: Tokenomics「單代理（工具迴圈）」每次嘗試約 2.8 萬 token（0.5 小時） | J76: 同上 | L76: =IF(AND(ISNUMBER($E76),ISNUMBER($F76),ISNUMBER($G76)),IF(AND($F76<=$E76,$E76<=$G76),0,1),0) -> 0 | M76: =IF(AND(OR($H76="Analogy",$H76="Assumed"),OR(NOT(ISNUMBER($F76)),NOT(ISNUMBER($G76)))),1,0) -> 0 | N76: tk_task_other
A77: INP_105 | B77: 每任務 token 相對 Tokenomics 任務的倍數：對話 | C77: 2025 | D77: 倍 | E77: 1 | F77: 0.5 | G77: 2 | H77: Assumed | I77: Claude 對話與 Tokenomics 標準一般聊天同量級（OpenAI v0.6 INP_116 plus 4K 為對照） | J77: ×0.5–×2 | K77: 2026 起每任務 token ×（1＋年增率） | L77: =IF(AND(ISNUMBER($E77),ISNUMBER($F77),ISNUMBER($G77)),IF(AND($F77<=$E77,$E77<=$G77),0,1),0) -> 0 | M77: =IF(AND(OR($H77="Analogy",$H77="Assumed"),OR(NOT(ISNUMBER($F77)),NOT(ISNUMBER($G77)))),1,0) -> 0 | N77: k_ratio_chat
A78: INP_106 | B78: 每任務 token 相對 Tokenomics 任務的倍數：程式代理 | C78: 2025 | D78: 倍 | E78: 0.15 | F78: 0.05 | G78: 0.4 | H78: Assumed | I78: 訂閱方案的程式代理任務（Claude Code 一次工作階段）多為 1 小時上下，約為 Tokenomics 長程任務（8 小時）的 1/8；取 0.15（約 22 萬 token） | J78: 0.05（短任務）–0.4（3 小時以上長任務） | K78: Anthropic token 量未揭露（SRC_ANT not_found） | L78: =IF(AND(ISNUMBER($E78),ISNUMBER($F78),ISNUMBER($G78)),IF(AND($F78<=$E78,$E78<=$G78),0,1),0) -> 0 | M78: =IF(AND(OR($H78="Analogy",$H78="Assumed"),OR(NOT(ISNUMBER($F78)),NOT(ISNUMBER($G78)))),1,0) -> 0 | N78: k_ratio_code
A79: INP_107 | B79: 每任務 token 相對 Tokenomics 任務的倍數：其他代理 | C79: 2025 | D79: 倍 | E79: 1 | F79: 0.5 | G79: 4 | H79: Assumed | I79: 研究、瀏覽、文件代理與 Tokenomics 單代理（工具迴圈）同量級；多代理研究約為其 4 倍（Tokenomics 多代理研究） | J79: 上限＝多代理研究量級 | L79: =IF(AND(ISNUMBER($E79),ISNUMBER($F79),ISNUMBER($G79)),IF(AND($F79<=$E79,$E79<=$G79),0,1),0) -> 0 | M79: =IF(AND(OR($H79="Analogy",$H79="Assumed"),OR(NOT(ISNUMBER($F79)),NOT(ISNUMBER($G79)))),1,0) -> 0 | N79: k_ratio_other
A80: INP_108 | B80: 單位換算：token → K token 的除數（定義常數） | C80: — | D80: tok／K | E80: 1000 | F80: 1000 | G80: 1000 | H80: Decision | I80: 定義常數 | J80: 不適用 | K80: Tokenomics 每任務 token（tok）→ 本模型 K token | L80: =IF(AND(ISNUMBER($E80),ISNUMBER($F80),ISNUMBER($G80)),IF(AND($F80<=$E80,$E80<=$G80),0,1),0) -> 0 | M80: =IF(AND(OR($H80="Analogy",$H80="Assumed"),OR(NOT(ISNUMBER($F80)),NOT(ISNUMBER($G80)))),1,0) -> 0 | N80: tok_per_k
A81: INP_070 | B81: 每任務 token 年增率（訂閱與席位） | C81: 2026 起 | D81: 比例/年 | E81: 0.15 | F81: 0.05 | G81: 0.3 | H81: Analogy | I81: OpenAI v0.6 INP_123（0.15；0.1–0.25）；Anthropic 下限放寬 | J81: OpenAI 區間放寬 | L81: =IF(AND(ISNUMBER($E81),ISNUMBER($F81),ISNUMBER($G81)),IF(AND($F81<=$E81,$E81<=$G81),0,1),0) -> 0 | M81: =IF(AND(OR($H81="Analogy",$H81="Assumed"),OR(NOT(ISNUMBER($F81)),NOT(ISNUMBER($G81)))),1,0) -> 0 | N81: g_k
A82: INP_071 | B82: 層級組合：Haiku（低層）占 token | C82: 對話 | D82: 比例 | E82: 0.3 | F82: 0.15 | G82: 0.5 | H82: Assumed | I82: 對話以 Sonnet 為預設、Haiku 為輕量；A1 未取得 OpenRouter 模型別份額（資料缺口） | J82: ±0.15–0.2 | K82: Opus＝1 − Haiku − Sonnet | L82: =IF(AND(ISNUMBER($E82),ISNUMBER($F82),ISNUMBER($G82)),IF(AND($F82<=$E82,$E82<=$G82),0,1),0) -> 0 | M82: =IF(AND(OR($H82="Analogy",$H82="Assumed"),OR(NOT(ISNUMBER($F82)),NOT(ISNUMBER($G82)))),1,0) -> 0 | N82: tier_haiku_chat
A83: INP_072 | B83: 層級組合：Sonnet（中層）占 token | C83: 對話 | D83: 比例 | E83: 0.65 | F83: 0.45 | G83: 0.8 | H83: Assumed | I83: 同上 | J83: 同上 | L83: =IF(AND(ISNUMBER($E83),ISNUMBER($F83),ISNUMBER($G83)),IF(AND($F83<=$E83,$E83<=$G83),0,1),0) -> 0 | M83: =IF(AND(OR($H83="Analogy",$H83="Assumed"),OR(NOT(ISNUMBER($F83)),NOT(ISNUMBER($G83)))),1,0) -> 0 | N83: tier_sonnet_chat
A84: INP_073 | B84: 層級組合：Haiku（低層）占 token | C84: 程式代理 | D84: 比例 | E84: 0.05 | F84: 0 | G84: 0.15 | H84: Assumed | I84: 程式代理以 Sonnet／Opus 為主（Opus 4.5 降價後 Opus 占比上升，SRC_ANT_157） | J84: 同上 | L84: =IF(AND(ISNUMBER($E84),ISNUMBER($F84),ISNUMBER($G84)),IF(AND($F84<=$E84,$E84<=$G84),0,1),0) -> 0 | M84: =IF(AND(OR($H84="Analogy",$H84="Assumed"),OR(NOT(ISNUMBER($F84)),NOT(ISNUMBER($G84)))),1,0) -> 0 | N84: tier_haiku_code
A85: INP_074 | B85: 層級組合：Sonnet（中層）占 token | C85: 程式代理 | D85: 比例 | E85: 0.6 | F85: 0.4 | G85: 0.8 | H85: Assumed | I85: 同上 | J85: 同上 | L85: =IF(AND(ISNUMBER($E85),ISNUMBER($F85),ISNUMBER($G85)),IF(AND($F85<=$E85,$E85<=$G85),0,1),0) -> 0 | M85: =IF(AND(OR($H85="Analogy",$H85="Assumed"),OR(NOT(ISNUMBER($F85)),NOT(ISNUMBER($G85)))),1,0) -> 0 | N85: tier_sonnet_code
A86: INP_075 | B86: 層級組合：Haiku（低層）占 token | C86: 其他代理 | D86: 比例 | E86: 0.25 | F86: 0.1 | G86: 0.4 | H86: Assumed | I86: 代理子任務常用輕量模型 | J86: 同上 | L86: =IF(AND(ISNUMBER($E86),ISNUMBER($F86),ISNUMBER($G86)),IF(AND($F86<=$E86,$E86<=$G86),0,1),0) -> 0 | M86: =IF(AND(OR($H86="Analogy",$H86="Assumed"),OR(NOT(ISNUMBER($F86)),NOT(ISNUMBER($G86)))),1,0) -> 0 | N86: tier_haiku_other
A87: INP_076 | B87: 層級組合：Sonnet（中層）占 token | C87: 其他代理 | D87: 比例 | E87: 0.6 | F87: 0.4 | G87: 0.75 | H87: Assumed | I87: 同上 | J87: 同上 | L87: =IF(AND(ISNUMBER($E87),ISNUMBER($F87),ISNUMBER($G87)),IF(AND($F87<=$E87,$E87<=$G87),0,1),0) -> 0 | M87: =IF(AND(OR($H87="Analogy",$H87="Assumed"),OR(NOT(ISNUMBER($F87)),NOT(ISNUMBER($G87)))),1,0) -> 0 | N87: tier_sonnet_other
A88: INP_077 | B88: API token 層級組合：Haiku（低層） | C88: 2025 | D88: 比例 | E88: 0.2 | F88: 0.1 | G88: 0.35 | H88: Assumed | I88: 層級別用量未揭露（資料缺口；OpenRouter 只給公司份額 SRC_ANT_181） | J88: ±0.1–0.15 | K88: Opus＝1 − Haiku − Sonnet | L88: =IF(AND(ISNUMBER($E88),ISNUMBER($F88),ISNUMBER($G88)),IF(AND($F88<=$E88,$E88<=$G88),0,1),0) -> 0 | M88: =IF(AND(OR($H88="Analogy",$H88="Assumed"),OR(NOT(ISNUMBER($F88)),NOT(ISNUMBER($G88)))),1,0) -> 0 | N88: api_mix_haiku_2025
A89: INP_078 | B89: API token 層級組合：Sonnet（中層） | C89: 2025 | D89: 比例 | E89: 0.65 | F89: 0.5 | G89: 0.8 | H89: Assumed | I89: 2025 程式代理（Cursor、GitHub Copilot 合計約 $1.2B 年化，SRC_ANT_040）以 Sonnet 為主 | J89: ±0.15 | L89: =IF(AND(ISNUMBER($E89),ISNUMBER($F89),ISNUMBER($G89)),IF(AND($F89<=$E89,$E89<=$G89),0,1),0) -> 0 | M89: =IF(AND(OR($H89="Analogy",$H89="Assumed"),OR(NOT(ISNUMBER($F89)),NOT(ISNUMBER($G89)))),1,0) -> 0 | N89: api_mix_sonnet_2025
A90: INP_079 | B90: API token 層級組合：Haiku（低層） | C90: 2026 起 | D90: 比例 | E90: 0.15 | F90: 0.05 | G90: 0.3 | H90: Assumed | I90: 同上 | J90: 同上 | K90: 2027 起沿用 | L90: =IF(AND(ISNUMBER($E90),ISNUMBER($F90),ISNUMBER($G90)),IF(AND($F90<=$E90,$E90<=$G90),0,1),0) -> 0 | M90: =IF(AND(OR($H90="Analogy",$H90="Assumed"),OR(NOT(ISNUMBER($F90)),NOT(ISNUMBER($G90)))),1,0) -> 0 | N90: api_mix_haiku_2026
A91: INP_080 | B91: API token 層級組合：Sonnet（中層） | C91: 2026 起 | D91: 比例 | E91: 0.5 | F91: 0.35 | G91: 0.65 | H91: Assumed | I91: Opus 4.5 起 Opus 降價 2/3（SRC_ANT_157），頂層占比上升 | J91: ±0.15 | L91: =IF(AND(ISNUMBER($E91),ISNUMBER($F91),ISNUMBER($G91)),IF(AND($F91<=$E91,$E91<=$G91),0,1),0) -> 0 | M91: =IF(AND(OR($H91="Analogy",$H91="Assumed"),OR(NOT(ISNUMBER($F91)),NOT(ISNUMBER($G91)))),1,0) -> 0 | N91: api_mix_sonnet_2026
A92: INP_081 | B92: API 輸出 token 占比（含思考） | C92: — | D92: 比例 | E92: 0.2 | F92: 0.1 | G92: 0.35 | H92: Analogy | I92: OpenAI v0.6 INP_028（0.2；0.1–0.35） | J92: 同 OpenAI | K92: 有效單價＝（1−輸出占比）× 輸入價 × 快取倍數 ＋ 輸出占比 × 輸出價 | L92: =IF(AND(ISNUMBER($E92),ISNUMBER($F92),ISNUMBER($G92)),IF(AND($F92<=$E92,$E92<=$G92),0,1),0) -> 0 | M92: =IF(AND(OR($H92="Analogy",$H92="Assumed"),OR(NOT(ISNUMBER($F92)),NOT(ISNUMBER($G92)))),1,0) -> 0 | N92: api_out_share
A93: INP_082 | B93: API 快取命中（讀取）占輸入 token | C93: — | D93: 比例 | E93: 0.6 | F93: 0.3 | G93: 0.85 | H93: Analogy | I93: OpenAI v0.6 INP_029（0.55；0.3–0.75）；差異：Anthropic 程式代理比重高、長上下文重複讀取多，上限放寬至 0.85 | J93: OpenAI 區間上限放寬 | K93: 讀取價＝輸入價 × SRC_ANT_137（0.1） | L93: =IF(AND(ISNUMBER($E93),ISNUMBER($F93),ISNUMBER($G93)),IF(AND($F93<=$E93,$E93<=$G93),0,1),0) -> 0 | M93: =IF(AND(OR($H93="Analogy",$H93="Assumed"),OR(NOT(ISNUMBER($F93)),NOT(ISNUMBER($G93)))),1,0) -> 0 | N93: api_cache_hit
A94: INP_083 | B94: API 快取寫入占輸入 token | C94: — | D94: 比例 | E94: 0.05 | F94: 0 | G94: 0.15 | H94: Assumed | I94: 快取寫入價＝輸入價 × 1.25（SRC_ANT_135，5 分鐘 TTL） | J94: 0–0.15 | L94: =IF(AND(ISNUMBER($E94),ISNUMBER($F94),ISNUMBER($G94)),IF(AND($F94<=$E94,$E94<=$G94),0,1),0) -> 0 | M94: =IF(AND(OR($H94="Analogy",$H94="Assumed"),OR(NOT(ISNUMBER($F94)),NOT(ISNUMBER($G94)))),1,0) -> 0 | N94: api_cache_write
A95: INP_084 | B95: API Batch 占 token | C95: — | D95: 比例 | E95: 0.05 | F95: 0 | G95: 0.2 | H95: Assumed | I95: Batch 折扣 50%（SRC_ANT_138）；即時程式代理為主，批次占比低 | J95: 0–0.2 | L95: =IF(AND(ISNUMBER($E95),ISNUMBER($F95),ISNUMBER($G95)),IF(AND($F95<=$E95,$E95<=$G95),0,1),0) -> 0 | M95: =IF(AND(OR($H95="Analogy",$H95="Assumed"),OR(NOT(ISNUMBER($F95)),NOT(ISNUMBER($G95)))),1,0) -> 0 | N95: api_batch_share
A96: INP_085 | B96: API 企業議價與承諾用量折扣 | C96: — | D96: 比例 | E96: 0.1 | F96: 0 | G96: 0.25 | H96: Assumed | I96: OpenAI v0.6 INP_030 加權折扣 0.2（含 Batch）；本模型 Batch 另列，議價部分取 0.1 | J96: 0–0.25 | L96: =IF(AND(ISNUMBER($E96),ISNUMBER($F96),ISNUMBER($G96)),IF(AND($F96<=$E96,$E96<=$G96),0,1),0) -> 0 | M96: =IF(AND(OR($H96="Analogy",$H96="Assumed"),OR(NOT(ISNUMBER($F96)),NOT(ISNUMBER($G96)))),1,0) -> 0 | N96: api_neg_disc
A97: INP_086 | B97: API 基準每任務 token（層級正規化） | C97: 2025 | D97: K tok/任務 | E97: 50 | F97: 10 | G97: 200 | H97: Assumed | I97: 同 OpenAI v0.6 INP_031：只影響任務數與每任務 token 的水準拆分，不影響營收與 token 總量 | J97: 正規化值 | L97: =IF(AND(ISNUMBER($E97),ISNUMBER($F97),ISNUMBER($G97)),IF(AND($F97<=$E97,$E97<=$G97),0,1),0) -> 0 | M97: =IF(AND(OR($H97="Analogy",$H97="Assumed"),OR(NOT(ISNUMBER($F97)),NOT(ISNUMBER($G97)))),1,0) -> 0 | N97: api_k_base
A98: INP_087 | B98: API 每任務 token 成長率（不含價格） | C98: 2026 | D98: 比例/年 | E98: 0.2 | F98: 0.1 | G98: 0.3 | H98: Analogy | I98: OpenAI v0.6 INP_041（0.2）；區間 ×0.5–×1.5（同 OpenAI 情境倍數 INP_046、047） | J98: 同 OpenAI | K98: 2026 只影響任務數與每任務 token 的拆分（總量由半校準決定） | L98: =IF(AND(ISNUMBER($E98),ISNUMBER($F98),ISNUMBER($G98)),IF(AND($F98<=$E98,$E98<=$G98),0,1),0) -> 0 | M98: =IF(AND(OR($H98="Analogy",$H98="Assumed"),OR(NOT(ISNUMBER($F98)),NOT(ISNUMBER($G98)))),1,0) -> 0 | N98: api_gk_2026
A99: INP_088 | B99: API 每任務 token 成長率（不含價格） | C99: 2027 | D99: 比例/年 | E99: 0.15 | F99: 0.075 | G99: 0.225 | H99: Analogy | I99: OpenAI v0.6 INP_042 | J99: ×0.5–×1.5 | L99: =IF(AND(ISNUMBER($E99),ISNUMBER($F99),ISNUMBER($G99)),IF(AND($F99<=$E99,$E99<=$G99),0,1),0) -> 0 | M99: =IF(AND(OR($H99="Analogy",$H99="Assumed"),OR(NOT(ISNUMBER($F99)),NOT(ISNUMBER($G99)))),1,0) -> 0 | N99: api_gk_2027
A100: INP_089 | B100: API 每任務 token 成長率（不含價格） | C100: 2028 | D100: 比例/年 | E100: 0.12 | F100: 0.06 | G100: 0.18 | H100: Analogy | I100: OpenAI v0.6 INP_043 | J100: ×0.5–×1.5 | L100: =IF(AND(ISNUMBER($E100),ISNUMBER($F100),ISNUMBER($G100)),IF(AND($F100<=$E100,$E100<=$G100),0,1),0) -> 0 | M100: =IF(AND(OR($H100="Analogy",$H100="Assumed"),OR(NOT(ISNUMBER($F100)),NOT(ISNUMBER($G100)))),1,0) -> 0 | N100: api_gk_2028
A101: INP_090 | B101: API 每任務 token 成長率（不含價格） | C101: 2029 | D101: 比例/年 | E101: 0.1 | F101: 0.05 | G101: 0.15 | H101: Analogy | I101: OpenAI v0.6 INP_044 | J101: ×0.5–×1.5 | L101: =IF(AND(ISNUMBER($E101),ISNUMBER($F101),ISNUMBER($G101)),IF(AND($F101<=$E101,$E101<=$G101),0,1),0) -> 0 | M101: =IF(AND(OR($H101="Analogy",$H101="Assumed"),OR(NOT(ISNUMBER($F101)),NOT(ISNUMBER($G101)))),1,0) -> 0 | N101: api_gk_2029
A102: INP_091 | B102: API 每任務 token 成長率（不含價格） | C102: 2030 | D102: 比例/年 | E102: 0.08 | F102: 0.04 | G102: 0.12 | H102: Analogy | I102: OpenAI v0.6 INP_045 | J102: ×0.5–×1.5 | L102: =IF(AND(ISNUMBER($E102),ISNUMBER($F102),ISNUMBER($G102)),IF(AND($F102<=$E102,$E102<=$G102),0,1),0) -> 0 | M102: =IF(AND(OR($H102="Analogy",$H102="Assumed"),OR(NOT(ISNUMBER($F102)),NOT(ISNUMBER($G102)))),1,0) -> 0 | N102: api_gk_2030
A103: INP_092 | B103: API 任務數成長率（不含價格） | C103: 2027 | D103: 比例/年 | E103: 0.45 | F103: 0.225 | G103: 0.9 | H103: Analogy | I103: OpenAI v0.6 INP_034（0.45）；兩家同值以便並排（D1）。差異：Anthropic 2026 實際成長遠高於 OpenAI，上限放寬至 ×2；不以公司目標反推 | J103: ×0.5–×2 | K103: 2027 起正向推導（D15 r1） | L103: =IF(AND(ISNUMBER($E103),ISNUMBER($F103),ISNUMBER($G103)),IF(AND($F103<=$E103,$E103<=$G103),0,1),0) -> 0 | M103: =IF(AND(OR($H103="Analogy",$H103="Assumed"),OR(NOT(ISNUMBER($F103)),NOT(ISNUMBER($G103)))),1,0) -> 0 | N103: api_gn_2027
...

Sheet Demand
A1: Demand — 需求：個人方案人數、企業席位、任務類別 × 每任務 token × 層級組合；API 任務數 × 每任務 token；token 量（DEM_Tok_*：層級 × 付費／免費）
A2: 2025：個人付費人數＝個人訂閱營收 ÷ 加權月費（D14 校準）；企業席位同理；免費＝2025 月活 − 個人付費；API token＝API 營收 ÷ 組合有效單價（唯一倒推）。2026：API token 由半校準總額倒推（D15 r2）。2027 起 API＝任務數 ×（1＋成長）× 價格反應 (p/p前)^ε × 每任務 token（同 OpenAI v0.6）。
A3: 人數 M＝百萬；token T＝10^12；每任務 K token＝千 token；API 任務數＝十億。訂閱與免費 token 不產生營收，只供 A3 算力（推論 GW）。
A5: 編號 | B5: 項目 | C5: 單位 | D5: 2025 | E5: 2026 | F5: 2027 | G5: 2028 | H5: 2029 | I5: 2030 | K5: 說明
B6: 年度 | D6: =INP_001 -> 2025 | E6: =INP_002 -> 2026 | F6: =INP_003 -> 2027 | G6: =INP_004 -> 2028 | H6: =INP_005 -> 2029 | I6: =INP_006 -> 2030
A7: 一、方案組合與人數（M，FY 平均）
A8: D01 | B8: 個人付費方案組合：Pro | C8: 比例 | D8: =INP_021 -> 0.85 | E8: =INP_023 -> 0.7 | F8: =INP_023 -> 0.7 | G8: =INP_023 -> 0.7 | H8: =INP_023 -> 0.7 | I8: =INP_023 -> 0.7 | K8: Inputs（2025 一欄；2026 起一欄）
A9: D02 | B9: 個人付費方案組合：Max 5x | C9: 比例 | D9: =INP_022 -> 0.1 | E9: =INP_024 -> 0.18 | F9: =INP_024 -> 0.18 | G9: =INP_024 -> 0.18 | H9: =INP_024 -> 0.18 | I9: =INP_024 -> 0.18 | K9: Inputs（2025 一欄；2026 起一欄）
A10: D03 | B10: 個人付費方案組合：Max 20x | C10: 比例 | D10: =(1-D8-D9) -> 0.05 | E10: =(1-E8-E9) -> 0.12 | F10: =(1-F8-F9) -> 0.12 | G10: =(1-G8-G9) -> 0.12 | H10: =(1-H8-H9) -> 0.12 | I10: =(1-I8-I9) -> 0.12 | K10: ＝1 − Pro − Max 5x
A11: D04 | B11: 個人付費人數合計 | C11: M | D11: =Revenue!D43*INP_012/(Revenue!D40*INP_008) -> 1.5868635 | E11: =D11*(1+INP_030) -> 6.3474541 | F11: =E11*(1+INP_031) -> 10.155927 | G11: =F11*(1+INP_032) -> 14.218297 | H11: =G11*(1+INP_033) -> 18.483786 | I11: =H11*(1+INP_034) -> 22.180544 | K11: 2025＝個人訂閱營收 ÷（加權月費 × 12）（工作單預設：付費人數無官方值時由營收倒推）；2026 起 ×（1＋年增率）
A12: D05 | B12: Pro 人數 | C12: M | D12: =D11*D8 -> 1.348834 | E12: =E11*E8 -> 4.4432179 | F12: =F11*F8 -> 7.1091486 | G12: =G11*G8 -> 9.9528081 | H12: =H11*H8 -> 12.93865 | I12: =I11*I8 -> 15.526381
A13: D06 | B13: Max 5x 人數 | C13: M | D13: =D11*D9 -> 0.15868635 | E13: =E11*E9 -> 1.1425417 | F13: =F11*F9 -> 1.8280668 | G13: =G11*G9 -> 2.5592935 | H13: =H11*H9 -> 3.3270816 | I13: =I11*I9 -> 3.9924979
A14: D07 | B14: Max 20x 人數 | C14: M | D14: =D11*D10 -> 0.079343176 | E14: =E11*E10 -> 0.76169449 | F14: =F11*F10 -> 1.2187112 | G14: =G11*G10 -> 1.7061957 | H14: =H11*H10 -> 2.2180544 | I14: =I11*I10 -> 2.6616652
A15: D08 | B15: Free 人數 | C15: M | D15: =SRC_ANT_173-D11 -> 17.313136 | E15: =D15*(1+INP_035) -> 34.626273 | F15: =E15*(1+INP_036) -> 51.939409 | G15: =F15*(1+INP_037) -> 67.521232 | H15: =G15*(1+INP_038) -> 81.025479 | I15: =H15*(1+INP_039) -> 93.1793 | K15: 2025＝月活（SRC，第三方估計 1,890 萬）− 個人付費；2026 起 ×（1＋年增率）
A16: D09 | B16: 企業席位組合：Team 標準 | C16: 比例 | D16: =INP_025 -> 0.5 | E16: =INP_027 -> 0.35 | F16: =INP_027 -> 0.35 | G16: =INP_027 -> 0.35 | H16: =INP_027 -> 0.35 | I16: =INP_027 -> 0.35 | K16: Inputs（2025 一欄；2026 起一欄）
A17: D10 | B17: 企業席位組合：Team Premium | C17: 比例 | D17: =INP_026 -> 0.15 | E17: =INP_028 -> 0.2 | F17: =INP_028 -> 0.2 | G17: =INP_028 -> 0.2 | H17: =INP_028 -> 0.2 | I17: =INP_028 -> 0.2 | K17: Inputs（2025 一欄；2026 起一欄）
A18: D11 | B18: 企業席位組合：Enterprise | C18: 比例 | D18: =(1-D16-D17) -> 0.35 | E18: =(1-E16-E17) -> 0.45 | F18: =(1-F16-F17) -> 0.45 | G18: =(1-G16-G17) -> 0.45 | H18: =(1-H16-H17) -> 0.45 | I18: =(1-I16-I17) -> 0.45 | K18: ＝1 − 標準 − Premium
A19: D12 | B19: 企業席位數合計 | C19: M | D19: =Revenue!D44*INP_012/(Revenue!D41*INP_008) -> 0.16377171 | E19: =D19*(1+INP_040) -> 0.65508685 | F19: =E19*(1+INP_041) -> 1.3101737 | G19: =F19*(1+INP_042) -> 1.9652605 | H19: =G19*(1+INP_043) -> 2.6531017 | I19: =H19*(1+INP_044) -> 3.3163772 | K19: 2025＝企業席位訂閱營收 ÷（加權月費 × 12）；2026 起 ×（1＋年增率）
A20: D13 | B20: Team 標準 席位數 | C20: M | D20: =D19*D16 -> 0.081885856 | E20: =E19*E16 -> 0.2292804 | F20: =F19*F16 -> 0.45856079 | G20: =G19*G16 -> 0.68784119 | H20: =H19*H16 -> 0.92858561 | I20: =I19*I16 -> 1.160732
A21: D14 | B21: Team Premium 席位數 | C21: M | D21: =D19*D17 -> 0.024565757 | E21: =E19*E17 -> 0.13101737 | F21: =F19*F17 -> 0.26203474 | G21: =G19*G17 -> 0.39305211 | H21: =H19*H17 -> 0.53062035 | I21: =I19*I17 -> 0.66327543
A22: D15 | B22: Enterprise 席位數 | C22: M | D22: =D19*D18 -> 0.057320099 | E22: =E19*E18 -> 0.29478908 | F22: =F19*F18 -> 0.58957816 | G22: =G19*G18 -> 0.88436725 | H22: =H19*H18 -> 1.1938958 | I22: =I19*I18 -> 1.4923697
A23: 二、訂閱與席位使用量：每日任務數 × 任務類別 × 每任務 token（2026 起年增）
A24: D16 | B24: Free 每人（席）每日任務數 | C24: 任務/日 | D24: =INP_045 -> 2 | E24: =D24*(1+INP_052) -> 2.2 | F24: =E24*(1+INP_052) -> 2.42 | G24: =F24*(1+INP_052) -> 2.662 | H24: =G24*(1+INP_052) -> 2.9282 | I24: =H24*(1+INP_052) -> 3.22102 | K24: Inputs 2025；之後 ×（1＋年增率）
A25: D17 | B25: Pro 每人（席）每日任務數 | C25: 任務/日 | D25: =INP_046 -> 8 | E25: =D25*(1+INP_052) -> 8.8 | F25: =E25*(1+INP_052) -> 9.68 | G25: =F25*(1+INP_052) -> 10.648 | H25: =G25*(1+INP_052) -> 11.7128 | I25: =H25*(1+INP_052) -> 12.88408 | K25: Inputs 2025；之後 ×（1＋年增率）
A26: D18 | B26: Max 5x 每人（席）每日任務數 | C26: 任務/日 | D26: =INP_047 -> 20 | E26: =D26*(1+INP_052) -> 22 | F26: =E26*(1+INP_052) -> 24.2 | G26: =F26*(1+INP_052) -> 26.62 | H26: =G26*(1+INP_052) -> 29.282 | I26: =H26*(1+INP_052) -> 32.2102 | K26: Inputs 2025；之後 ×（1＋年增率）
A27: D19 | B27: Max 20x 每人（席）每日任務數 | C27: 任務/日 | D27: =INP_048 -> 40 | E27: =D27*(1+INP_052) -> 44 | F27: =E27*(1+INP_052) -> 48.4 | G27: =F27*(1+INP_052) -> 53.24 | H27: =G27*(1+INP_052) -> 58.564 | I27: =H27*(1+INP_052) -> 64.4204 | K27: Inputs 2025；之後 ×（1＋年增率）
A28: D20 | B28: Team 標準 每人（席）每日任務數 | C28: 任務/日 | D28: =INP_049 -> 6 | E28: =D28*(1+INP_052) -> 6.6 | F28: =E28*(1+INP_052) -> 7.26 | G28: =F28*(1+INP_052) -> 7.986 | H28: =G28*(1+INP_052) -> 8.7846 | I28: =H28*(1+INP_052) -> 9.66306 | K28: Inputs 2025；之後 ×（1＋年增率）
A29: D21 | B29: Team Premium 每人（席）每日任務數 | C29: 任務/日 | D29: =INP_050 -> 15 | E29: =D29*(1+INP_052) -> 16.5 | F29: =E29*(1+INP_052) -> 18.15 | G29: =F29*(1+INP_052) -> 19.965 | H29: =G29*(1+INP_052) -> 21.9615 | I29: =H29*(1+INP_052) -> 24.15765 | K29: Inputs 2025；之後 ×（1＋年增率）
A30: D22 | B30: Enterprise 每人（席）每日任務數 | C30: 任務/日 | D30: =INP_051 -> 8 | E30: =D30*(1+INP_052) -> 8.8 | F30: =E30*(1+INP_052) -> 9.68 | G30: =F30*(1+INP_052) -> 10.648 | H30: =G30*(1+INP_052) -> 11.7128 | I30: =H30*(1+INP_052) -> 12.88408 | K30: Inputs 2025；之後 ×（1＋年增率）
A31: D23 | B31: 每任務 token：對話 | C31: K tok/任務 | D31: =(SUMIFS(TK_IF_TaskTokFresh,TK_IF_HdrTask,INP_102)+SUMIFS(TK_IF_TaskTokCached,TK_IF_HdrTask,INP_102)+SUMIFS(TK_IF_TaskTokDec,TK_IF_HdrTask,INP_102))/INP_108*INP_105 -> 3 | E31: =D31*(1+INP_070) -> 3.45 | F31: =E31*(1+INP_070) -> 3.9675 | G31: =F31*(1+INP_070) -> 4.562625 | H31: =G31*(1+INP_070) -> 5.2470187 | I31: =H31*(1+INP_070) -> 6.0340716 | K31: 2025＝Tokenomics 對應任務每次嘗試 token（新鮮＋快取＋decode）× Inputs 倍數；之後 ×（1＋年增率）
A32: D24 | B32: 每任務 token：程式代理 | C32: K tok/任務 | D32: =(SUMIFS(TK_IF_TaskTokFresh,TK_IF_HdrTask,INP_103)+SUMIFS(TK_IF_TaskTokCached,TK_IF_HdrTask,INP_103)+SUMIFS(TK_IF_TaskTokDec,TK_IF_HdrTask,INP_103))/INP_108*INP_106 -> 224.1 | E32: =D32*(1+INP_070) -> 257.715 | F32: =E32*(1+INP_070) -> 296.37225 | G32: =F32*(1+INP_070) -> 340.82809 | H32: =G32*(1+INP_070) -> 391.9523 | I32: =H32*(1+INP_070) -> 450.74515 | K32: 2025＝Tokenomics 對應任務每次嘗試 token（新鮮＋快取＋decode）× Inputs 倍數；之後 ×（1＋年增率）
A33: D25 | B33: 每任務 token：其他代理 | C33: K tok/任務 | D33: =(SUMIFS(TK_IF_TaskTokFresh,TK_IF_HdrTask,INP_104)+SUMIFS(TK_IF_TaskTokCached,TK_IF_HdrTask,INP_104)+SUMIFS(TK_IF_TaskTokDec,TK_IF_HdrTask,INP_104))/INP_108*INP_107 -> 27.6 | E33: =D33*(1+INP_070) -> 31.74 | F33: =E33*(1+INP_070) -> 36.501 | G33: =F33*(1+INP_070) -> 41.97615 | H33: =G33*(1+INP_070) -> 48.272573 | I33: =H33*(1+INP_070) -> 55.513458 | K33: 2025＝Tokenomics 對應任務每次嘗試 token（新鮮＋快取＋decode）× Inputs 倍數；之後 ×（1＋年增率）
A34: D26 | B34: Free token | C34: T | D34: =D15*D24*(INP_053*D31+INP_054*D32+(1-INP_053-INP_054)*D33)*INP_007/INP_013 -> 53.461234 | E34: =E15*E24*(INP_053*E31+INP_054*E32+(1-INP_053-INP_054)*E33)*INP_007/INP_013 -> 135.25692 | F34: =F15*F24*(INP_053*F31+INP_054*F32+(1-INP_053-INP_054)*F33)*INP_007/INP_013 -> 256.65001 | G34: =G15*G24*(INP_053*G31+INP_054*G32+(1-INP_053-INP_054)*G33)*INP_007/INP_013 -> 422.06094 | H34: =H15*H24*(INP_053*H31+INP_054*H32+(1-INP_053-INP_054)*H33)*INP_007/INP_013 -> 640.68851 | I34: =I15*I24*(INP_053*I31+INP_054*I32+(1-INP_053-INP_054)*I33)*INP_007/INP_013 -> 932.04161 | K34: 人數（M）× 每日任務 × Σ 類別占比 × 每任務 K token × 天數 ÷ 1000
A35: D27 | B35: Pro token | C35: T | D35: =D12*D25*(INP_055*D31+INP_056*D32+(1-INP_055-INP_056)*D33)*INP_007/INP_013 -> 239.21058 | E35: =E12*E25*(INP_055*E31+INP_056*E32+(1-INP_055-INP_056)*E33)*INP_007/INP_013 -> 996.80458 | F35: =F12*F25*(INP_055*F31+INP_056*F32+(1-INP_055-INP_056)*F33)*INP_007/INP_013 -> 2017.5325 | G35: =G12*G25*(INP_055*G31+INP_056*G32+(1-INP_055-INP_056)*G33)*INP_007/INP_013 -> 3573.05 | H35: =H12*H25*(INP_055*H31+INP_056*H32+(1-INP_055-INP_056)*H33)*INP_007/INP_013 -> 5875.8807 | I35: =I12*I25*(INP_055*I31+INP_056*I32+(1-INP_055-INP_056)*I33)*INP_007/INP_013 -> 8919.5869 | K35: 人數（M）× 每日任務 × Σ 類別占比 × 每任務 K token × 天數 ÷ 1000
A36: D28 | B36: Max 5x token | C36: T | D36: =D13*D26*(INP_057*D31+INP_058*D32+(1-INP_057-INP_058)*D33)*INP_007/INP_013 -> 159.99964 | E36: =E13*E26*(INP_057*E31+INP_058*E32+(1-INP_057-INP_058)*E33)*INP_007/INP_013 -> 1457.2767 | F36: =F13*F26*(INP_057*F31+INP_058*F32+(1-INP_057-INP_058)*F33)*INP_007/INP_013 -> 2949.5281 | G36: =G13*G26*(INP_057*G31+INP_058*G32+(1-INP_057-INP_058)*G33)*INP_007/INP_013 -> 5223.6143 | H36: =H13*H26*(INP_057*H31+INP_058*H32+(1-INP_057-INP_058)*H33)*INP_007/INP_013 -> 8590.2337 | I36: =I13*I26*(INP_057*I31+INP_058*I32+(1-INP_057-INP_058)*I33)*INP_007/INP_013 -> 13039.975 | K36: 人數（M）× 每日任務 × Σ 類別占比 × 每任務 K token × 天數 ÷ 1000
A37: D29 | B37: Max 20x token | C37: T | D37: =D14*D27*(INP_059*D31+INP_060*D32+(1-INP_059-INP_060)*D33)*INP_007/INP_013 -> 185.61209 | E37: =E14*E27*(INP_059*E31+INP_060*E32+(1-INP_059-INP_060)*E33)*INP_007/INP_013 -> 2254.0733 | F37: =F14*F27*(INP_059*F31+INP_060*F32+(1-INP_059-INP_060)*F33)*INP_007/INP_013 -> 4562.2443 | G37: =G14*G27*(INP_059*G31+INP_060*G32+(1-INP_059-INP_060)*G33)*INP_007/INP_013 -> 8079.7347 | H37: =H14*H27*(INP_059*H31+INP_060*H32+(1-INP_059-INP_060)*H33)*INP_007/INP_013 -> 13287.124 | I37: =I14*I27*(INP_059*I31+INP_060*I32+(1-INP_059-INP_060)*I33)*INP_007/INP_013 -> 20169.854 | K37: 人數（M）× 每日任務 × Σ 類別占比 × 每任務 K token × 天數 ÷ 1000
A38: D30 | B38: Team 標準 token | C38: T | D38: =D20*D28*(INP_061*D31+INP_062*D32+(1-INP_061-INP_062)*D33)*INP_007/INP_013 -> 6.9266222 | E38: =E20*E28*(INP_061*E31+INP_062*E32+(1-INP_061-INP_062)*E33)*INP_007/INP_013 -> 24.534096 | F38: =F20*F28*(INP_061*F31+INP_062*F32+(1-INP_061-INP_062)*F33)*INP_007/INP_013 -> 62.071263 | G38: =G20*G28*(INP_061*G31+INP_062*G32+(1-INP_061-INP_062)*G33)*INP_007/INP_013 -> 117.78022 | H38: =H20*H28*(INP_061*H31+INP_062*H32+(1-INP_061-INP_062)*H33)*INP_007/INP_013 -> 201.13917 | I38: =I20*I28*(INP_061*I31+INP_062*I32+(1-INP_061-INP_062)*I33)*INP_007/INP_013 -> 318.05132 | K38: 人數（M）× 每日任務 × Σ 類別占比 × 每任務 K token × 天數 ÷ 1000
A39: D31 | B39: Team Premium token | C39: T | D39: =D21*D29*(INP_063*D31+INP_064*D32+(1-INP_063-INP_064)*D33)*INP_007/INP_013 -> 18.576797 | E39: =E21*E29*(INP_063*E31+INP_064*E32+(1-INP_063-INP_064)*E33)*INP_007/INP_013 -> 125.33146 | F39: =F21*F29*(INP_063*F31+INP_064*F32+(1-INP_063-INP_064)*F33)*INP_007/INP_013 -> 317.08859 | G39: =G21*G29*(INP_063*G31+INP_064*G32+(1-INP_063-INP_064)*G33)*INP_007/INP_013 -> 601.6756 | H39: =H21*H29*(INP_063*H31+INP_064*H32+(1-INP_063-INP_064)*H33)*INP_007/INP_013 -> 1027.5115 | I39: =I21*I29*(INP_063*I31+INP_064*I32+(1-INP_063-INP_064)*I33)*INP_007/INP_013 -> 1624.7526 | K39: 人數（M）× 每日任務 × Σ 類別占比 × 每任務 K token × 天數 ÷ 1000
A40: D32 | B40: Enterprise token | C40: T | D40: =D22*D30*(INP_065*D31+INP_066*D32+(1-INP_065-INP_066)*D33)*INP_007/INP_013 -> 12.2217 | E40: =E22*E30*(INP_065*E31+INP_066*E32+(1-INP_065-INP_066)*E33)*INP_007/INP_013 -> 79.510887 | F40: =F22*F30*(INP_065*F31+INP_066*F32+(1-INP_065-INP_066)*F33)*INP_007/INP_013 -> 201.16254 | G40: =G22*G30*(INP_065*G31+INP_066*G32+(1-INP_065-INP_066)*G33)*INP_007/INP_013 -> 381.70593 | H40: =H22*H30*(INP_065*H31+INP_066*H32+(1-INP_065-INP_066)*H33)*INP_007/INP_013 -> 651.8583 | I40: =I22*I30*(INP_065*I31+INP_066*I32+(1-INP_065-INP_066)*I33)*INP_007/INP_013 -> 1030.7509 | K40: 人數（M）× 每日任務 × Σ 類別占比 × 每任務 K token × 天數 ÷ 1000
A41: D33 | B41: 訂閱、席位與 Free token 合計 | C41: T | D41: =D34+D35+D36+D37+D38+D39+D40 -> 676.00867 | E41: =E34+E35+E36+E37+E38+E39+E40 -> 5072.788 | F41: =F34+F35+F36+F37+F38+F39+F40 -> 10366.277 | G41: =G34+G35+G36+G37+G38+G39+G40 -> 18399.622 | H41: =H34+H35+H36+H37+H38+H39+H40 -> 30274.436 | I41: =I34+I35+I36+I37+I38+I39+I40 -> 46035.012
A42: D34 | B42: 付費方案 token：對話 | C42: T | D42: =(D12*D25*INP_055+D13*D26*INP_057+D14*D27*INP_059+D20*D28*INP_061+D21*D29*INP_063+D22*D30*INP_065)*D31*INP_007/INP_013 -> 10.218585 | E42: =(E12*E25*INP_055+E13*E26*INP_057+E14*E27*INP_059+E20*E28*INP_061+E21*E29*INP_063+E22*E30*INP_065)*E31*INP_007/INP_013 -> 53.982973 | F42: =(F12*F25*INP_055+F13*F26*INP_057+F14*F27*INP_059+F20*F28*INP_061+F21*F29*INP_063+F22*F30*INP_065)*F31*INP_007/INP_013 -> 111.30705 | G42: =(G12*G25*INP_055+G13*G26*INP_057+G14*G27*INP_059+G20*G28*INP_061+G21*G29*INP_063+G22*G30*INP_065)*G31*INP_007/INP_013 -> 198.41857 | H42: =(H12*H25*INP_055+H13*H26*INP_057+H14*H27*INP_059+H20*H28*INP_061+H21*H29*INP_063+H22*H30*INP_065)*H31*INP_007/INP_013 -> 327.52681 | I42: =(I12*I25*INP_055+I13*I26*INP_057+I14*I27*INP_059+I20*I28*INP_061+I21*I29*INP_063+I22*I30*INP_065)*I31*INP_007/INP_013 -> 499.28193 | K42: Σ 付費方案（Pro、Max、席位）人數 × 每日任務 × 類別占比 × 該類每任務 token
A43: D35 | B43: 付費方案 token：程式代理 | C43: T | D43: =(D12*D25*INP_056+D13*D26*INP_058+D14*D27*INP_060+D20*D28*INP_062+D21*D29*INP_064+D22*D30*INP_066)*D32*INP_007/INP_013 -> 593.50481 | E43: =(E12*E25*INP_056+E13*E26*INP_058+E14*E27*INP_060+E20*E28*INP_062+E21*E29*INP_064+E22*E30*INP_066)*E32*INP_007/INP_013 -> 4761.5372 | F43: =(F12*F25*INP_056+F13*F26*INP_058+F14*F27*INP_060+F20*F28*INP_062+F21*F29*INP_064+F22*F30*INP_066)*F32*INP_007/INP_013 -> 9746.9349 | G43: =(G12*G25*INP_056+G13*G26*INP_058+G14*G27*INP_060+G20*G28*INP_062+G21*G29*INP_064+G22*G30*INP_066)*G32*INP_007/INP_013 -> 17331.133 | H43: =(H12*H25*INP_056+H13*H26*INP_058+H14*H27*INP_060+H20*H28*INP_062+H21*H29*INP_064+H22*H30*INP_066)*H32*INP_007/INP_013 -> 28566.808 | I43: =(I12*I25*INP_056+I13*I26*INP_058+I14*I27*INP_060+I20*I28*INP_062+I21*I29*INP_064+I22*I30*INP_066)*I32*INP_007/INP_013 -> 43476.715 | K43: Σ 付費方案（Pro、Max、席位）人數 × 每日任務 × 類別占比 × 該類每任務 token
A44: D36 | B44: 付費方案 token：其他代理 | C44: T | D44: =(D12*D25*(1-INP_055-INP_056)+D13*D26*(1-INP_057-INP_058)+D14*D27*(1-INP_059-INP_060)+D20*D28*(1-INP_061-INP_062)+D21*D29*(1-INP_063-INP_064)+D22*D30*(1-INP_065-INP_066))*D33*INP_007/INP_013 -> 18.824043 | E44: =(E12*E25*(1-INP_055-INP_056)+E13*E26*(1-INP_057-INP_058)+E14*E27*(1-INP_059-INP_060)+E20*E28*(1-INP_061-INP_062)+E21*E29*(1-INP_063-INP_064)+E22*E30*(1-INP_065-INP_066))*E33*INP_007/INP_013 -> 122.01085 | F44: =(F12*F25*(1-INP_055-INP_056)+F13*F26*(1-INP_057-INP_058)+F14*F27*(1-INP_059-INP_060)+F20*F28*(1-INP_061-INP_062)+F21*F29*(1-INP_063-INP_064)+F22*F30*(1-INP_065-INP_066))*F33*INP_007/INP_013 -> 251.38535 | G44: =(G12*G25*(1-INP_055-INP_056)+G13*G26*(1-INP_057-INP_058)+G14*G27*(1-INP_059-INP_060)+G20*G28*(1-INP_061-INP_062)+G21*G29*(1-INP_063-INP_064)+G22*G30*(1-INP_065-INP_066))*G33*INP_007/INP_013 -> 448.00883 | H44: =(H12*H25*(1-INP_055-INP_056)+H13*H26*(1-INP_057-INP_058)+H14*H27*(1-INP_059-INP_060)+H20*H28*(1-INP_061-INP_062)+H21*H29*(1-INP_063-INP_064)+H22*H30*(1-INP_065-INP_066))*H33*INP_007/INP_013 -> 739.41212 | I44: =(I12*I25*(1-INP_055-INP_056)+I13*I26*(1-INP_057-INP_058)+I14*I27*(1-INP_059-INP_060)+I20*I28*(1-INP_061-INP_062)+I21*I29*(1-INP_063-INP_064)+I22*I30*(1-INP_065-INP_066))*I33*INP_007/INP_013 -> 1126.973 | K44: Σ 付費方案（Pro、Max、席位）人數 × 每日任務 × 類別占比 × 該類每任務 token
A45: D37 | B45: Free token：對話 | C45: T | D45: =D15*D24*INP_053*D31*INP_007/INP_013 -> 36.01998 | E45: =E15*E24*INP_053*E31*INP_007/INP_013 -> 91.13055 | F45: =F15*F24*INP_053*F31*INP_007/INP_013 -> 172.92022 | G45: =G15*G24*INP_053*G31*INP_007/INP_013 -> 284.3673 | H45: =H15*H24*INP_053*H31*INP_007/INP_013 -> 431.66956 | I45: =I15*I24*INP_053*I31*INP_007/INP_013 -> 627.9713
A46: D38 | B46: Free token：程式代理 | C46: T | D46: =D15*D24*INP_054*D32*INP_007/INP_013 -> 0 | E46: =E15*E24*INP_054*E32*INP_007/INP_013 -> 0 | F46: =F15*F24*INP_054*F32*INP_007/INP_013 -> 0 | G46: =G15*G24*INP_054*G32*INP_007/INP_013 -> 0 | H46: =H15*H24*INP_054*H32*INP_007/INP_013 -> 0 | I46: =I15*I24*INP_054*I32*INP_007/INP_013 -> 0
A47: D39 | B47: Free token：其他代理 | C47: T | D47: =D15*D24*(1-INP_053-INP_054)*D33*INP_007/INP_013 -> 17.441254 | E47: =E15*E24*(1-INP_053-INP_054)*E33*INP_007/INP_013 -> 44.126372 | F47: =F15*F24*(1-INP_053-INP_054)*F33*INP_007/INP_013 -> 83.729791 | G47: =G15*G24*(1-INP_053-INP_054)*G33*INP_007/INP_013 -> 137.69364 | H47: =H15*H24*(1-INP_053-INP_054)*H33*INP_007/INP_013 -> 209.01895 | I47: =I15*I24*(1-INP_053-INP_054)*I33*INP_007/INP_013 -> 304.07031
A48: D40 | B48: 檢查：（類別合計 − 方案合計）÷ 方案合計（應為 0） | C48: 比例 | D48: =((D42+D45+D43+D46+D44+D47)-D41)/D41 -> 0 | E48: =((E42+E45+E43+E46+E44+E47)-E41)/E41 -> 0 | F48: =((F42+F45+F43+F46+F44+F47)-F41)/F41 -> 0 | G48: =((G42+G45+G43+G46+G44+G47)-G41)/G41 -> 0 | H48: =((H42+H45+H43+H46+H44+H47)-H41)/H41 -> 0 | I48: =((I42+I45+I43+I46+I44+I47)-I41)/I41 -> 0 | K48: 以相對差表示，避免大數相減的浮點雜訊
A49: D41 | B49: 程式代理占訂閱、席位與 Free token（D4：Claude Code 不另立營收線） | C49: 比例 | D49: =(D43+D46)/D41 -> 0.87795443 | E49: =(E43+E46)/E41 -> 0.93864306 | F49: =(F43+F46)/F41 -> 0.94025412 | G49: =(G43+G46)/G41 -> 0.94192879 | H49: =(H43+H46)/H41 -> 0.94359507 | I49: =(I43+I46)/I41 -> 0.94442716 | K49: Claude Code 營收落在 Max、Team Premium 訂閱與 API 用量
A50: 三、API 需求：任務數 × 每任務 token（2025、2026 由營收倒推；2027 起任務成長 × 每任務 token 成長 × 價格反應）
A51: D42 | B51: 價格反應底數 p/p前（API 組合有效單價） | C51: 倍 | E51: =Revenue!E32/Revenue!D32 -> 0.71643946 | F51: =Revenue!F32/Revenue!E32 -> 0.68018751 | G51: =Revenue!G32/Revenue!F32 -> 0.85 | H51: =Revenue!H32/Revenue!G32 -> 0.85 | I51: =Revenue!I32/Revenue!H32 -> 0.85 | K51: 價格反應只在年度 ≥ 彈性起算年（Inputs 2027）生效：底數^(ε ×（年度 ≥ 起算年））
A52: D43 | B52: API 每任務 token | C52: K tok/任務 | D52: =INP_086 -> 50 | E52: =D52*(1+INP_087)*E51^(INP_097*(E$6>=INP_015)) -> 60 | F52: =E52*(1+INP_088)*F51^(INP_097*(F$6>=INP_015)) -> 77.456968 | G52: =F52*(1+INP_089)*G51^(INP_097*(G$6>=INP_015)) -> 91.086254 | H52: =G52*(1+INP_090)*H51^(INP_097*(H$6>=INP_015)) -> 105.20099 | I52: =H52*(1+INP_091)*I51^(INP_097*(I$6>=INP_015)) -> 119.29381 | K52: 層級正規化（只影響任務數與每任務 token 的拆分，不影響營收）；之後 ×（1＋成長）× 價格反應
A53: D44 | B53: API 任務數 | C53: 十億任務 | D53: =D54/D52 -> 14.920705 | E53: =E54/E52 -> 207.12632 | F53: =E53*(1+INP_092)*F51^(INP_096*(F$6>=INP_015)) -> 393.33557 | G53: =F53*(1+INP_093)*G51^(INP_096*(G$6>=INP_015)) -> 594.98189 | H53: =G53*(1+INP_094)*H51^(INP_096*(H$6>=INP_015)) -> 833.33671 | I53: =H53*(1+INP_095)*I51^(INP_096*(I$6>=INP_015)) -> 1120.4914 | K53: 2025、2026＝計費 token ÷ 每任務 token；2027 起 ×（1＋成長）× 價格反應
A54: D45 | B54: API 計費 token | C54: T | D54: =Revenue!D57*INP_012/Revenue!D32 -> 746.03524 | E54: =Revenue!E57*INP_012/Revenue!E32 -> 12427.579 | F54: =F53*F52 -> 30466.581 | G54: =G53*G52 -> 54194.671 | H54: =H53*H52 -> 87667.851 | I54: =I53*I52 -> 133667.69 | K54: 2025、2026：API 營收校準值 ÷ 組合有效單價（D14、D15 r1）；之後＝任務數 × 每任務 token
A55: D46 | B55: API 任務數年增率（2026＝半校準隱含值） | C55: 比例/年 | E55: =(E53-D53)/D53 -> 12.881805 | F55: =(F53-E53)/E53 -> 0.89901303 | G55: =(G53-F53)/F53 -> 0.51265721 | H55: =(H53-G53)/G53 -> 0.40060852 | I55: =(I53-H53)/H53 -> 0.34458418 | K55: 2027 起含價格反應
A56: D47 | B56: API token：頂層（Opus→Astra） | C56: T | D56: =D54*Revenue!D31 -> 111.90529 | E56: =E54*Revenue!E31 -> 4349.6527 | F56: =F54*Revenue!F31 -> 10663.303 | G56: =G54*Revenue!G31 -> 18968.135 | H56: =H54*Revenue!H31 -> 30683.748 | I56: =I54*Revenue!I31 -> 46783.691 | K56: 計費 token × 層級組合（Revenue）
A57: D48 | B57: API token：中層（Sonnet→Sol） | C57: T | D57: =D54*Revenue!D29 -> 484.92291 | E57: =E54*Revenue!E29 -> 6213.7895 | F57: =F54*Revenue!F29 -> 15233.291 | G57: =G54*Revenue!G29 -> 27097.336 | H57: =H54*Revenue!H29 -> 43833.925 | I57: =I54*Revenue!I29 -> 66833.844 | K57: 計費 token × 層級組合（Revenue）
A58: D49 | B58: API token：低層（Haiku→Luna） | C58: T | D58: =D54*Revenue!D30 -> 149.20705 | E58: =E54*Revenue!E30 -> 1864.1369 | F58: =F54*Revenue!F30 -> 4569.9872 | G58: =G54*Revenue!G30 -> 8129.2007 | H58: =H54*Revenue!H30 -> 13150.178 | I58: =I54*Revenue!I30 -> 20050.153 | K58: 計費 token × 層級組合（Revenue）
A59: 四、輸出：token 量（層級 × 付費／免費；A3 推論 GW 用）
A60: D50 | B60: 免費 token：頂層（Opus→Astra） | C60: T | D60: =D45*(1-INP_071-INP_072)+D46*(1-INP_073-INP_074)+D47*(1-INP_075-INP_076) -> 4.4171871 | E60: =E45*(1-INP_071-INP_072)+E46*(1-INP_073-INP_074)+E47*(1-INP_075-INP_076) -> 11.175483 | F60: =F45*(1-INP_071-INP_072)+F46*(1-INP_073-INP_074)+F47*(1-INP_075-INP_076) -> 21.20548 | G60: =G45*(1-INP_071-INP_072)+G46*(1-INP_073-INP_074)+G47*(1-INP_075-INP_076) -> 34.872411 | H60: =H45*(1-INP_071-INP_072)+H46*(1-INP_073-INP_074)+H47*(1-INP_075-INP_076) -> 52.93632 | I60: =I45*(1-INP_071-INP_072)+I46*(1-INP_073-INP_074)+I47*(1-INP_075-INP_076) -> 77.009112 | K60: Σ 類別 token × 層級組合（Inputs）
A61: D51 | B61: 免費 token：中層（Sonnet→Sol） | C61: T | D61: =D45*INP_072+D46*INP_074+D47*INP_076 -> 33.877739 | E61: =E45*INP_072+E46*INP_074+E47*INP_076 -> 85.710681 | F61: =F45*INP_072+F46*INP_074+F47*INP_076 -> 162.63602 | G61: =G45*INP_072+G46*INP_074+G47*INP_076 -> 267.45493 | H61: =H45*INP_072+H46*INP_074+H47*INP_076 -> 405.99658 | I61: =I45*INP_072+I46*INP_074+I47*INP_076 -> 590.62353 | K61: Σ 類別 token × 層級組合（Inputs）
A62: D52 | B62: 免費 token：低層（Haiku→Luna） | C62: T | D62: =D45*INP_071+D46*INP_073+D47*INP_075 -> 15.166308 | E62: =E45*INP_071+E46*INP_073+E47*INP_075 -> 38.370758 | F62: =F45*INP_071+F46*INP_073+F47*INP_075 -> 72.808513 | G62: =G45*INP_071+G46*INP_073+G47*INP_075 -> 119.7336 | H62: =H45*INP_071+H46*INP_073+H47*INP_075 -> 181.75561 | I62: =I45*INP_071+I46*INP_073+I47*INP_075 -> 264.40897 | K62: Σ 類別 token × 層級組合（Inputs）
A63: D53 | B63: 付費 token：頂層（Opus→Astra） | C63: T | D63: =D42*(1-INP_071-INP_072)+D43*(1-INP_073-INP_074)+D44*(1-INP_075-INP_076)+D56 -> 322.96651 | E63: =E42*(1-INP_071-INP_072)+E43*(1-INP_073-INP_074)+E44*(1-INP_075-INP_076)+E56 -> 6037.1914 | F63: =F42*(1-INP_071-INP_072)+F43*(1-INP_073-INP_074)+F44*(1-INP_075-INP_076)+F56 -> 14118.004 | G63: =G42*(1-INP_071-INP_072)+G43*(1-INP_073-INP_074)+G44*(1-INP_075-INP_076)+G56 -> 25111.154 | H63: =H42*(1-INP_071-INP_072)+H43*(1-INP_073-INP_074)+H44*(1-INP_075-INP_076)+H56 -> 40809.419 | I63: =I42*(1-INP_071-INP_072)+I43*(1-INP_073-INP_074)+I44*(1-INP_075-INP_076)+I56 -> 62194.551 | K63: Σ 付費類別 token × 層級組合 ＋ API 該層級 token
A64: D54 | B64: 付費 token：中層（Sonnet→Sol） | C64: T | D64: =D42*INP_072+D43*INP_074+D44*INP_076+D57 -> 858.9623 | E64: =E42*INP_072+E43*INP_074+E44*INP_076+E57 -> 9179.0073 | F64: =F42*INP_072+F43*INP_074+F44*INP_076+F57 -> 21304.632 | G64: =G42*INP_072+G43*INP_074+G44*INP_076+G57 -> 37893.793 | H64: =H42*INP_072+H43*INP_074+H44*INP_076+H57 -> 61630.55 | I64: =I42*INP_072+I43*INP_074+I44*INP_076+I57 -> 93920.59 | K64: Σ 付費類別 token × 層級組合 ＋ API 該層級 token
A65: D55 | B65: 付費 token：低層（Haiku→Luna） | C65: T | D65: =D42*INP_071+D43*INP_073+D44*INP_075+D58 -> 186.65388 | E65: =E42*INP_071+E43*INP_073+E44*INP_075+E58 -> 2148.9113 | F65: =F42*INP_071+F43*INP_073+F44*INP_075+F58 -> 5153.5724 | G65: =G42*INP_071+G43*INP_073+G44*INP_075+G58 -> 9167.2852 | H65: =H42*INP_071+H43*INP_073+H44*INP_075+H58 -> 14861.629 | I65: =I42*INP_071+I43*INP_073+I44*INP_075+I58 -> 22655.517 | K65: Σ 付費類別 token × 層級組合 ＋ API 該層級 token
A66: D56 | B66: 免費 token 合計 | C66: T | D66: =D60+D61+D62 -> 53.461234 | E66: =E60+E61+E62 -> 135.25692 | F66: =F60+F61+F62 -> 256.65001 | G66: =G60+G61+G62 -> 422.06094 | H66: =H60+H61+H62 -> 640.68851 | I66: =I60+I61+I62 -> 932.04161
A67: D57 | B67: 付費 token 合計 | C67: T | D67: =D63+D64+D65 -> 1368.5827 | E67: =E63+E64+E65 -> 17365.11 | F67: =F63+F64+F65 -> 40576.208 | G67: =G63+G64+G65 -> 72172.232 | H67: =H63+H64+H65 -> 117301.6 | I67: =I63+I64+I65 -> 178770.66
A68: D58 | B68: token 合計（付費＋免費） | C68: T | D68: =D66+D67 -> 1422.0439 | E68: =E66+E67 -> 17500.367 | F68: =F66+F67 -> 40832.858 | G68: =G66+G67 -> 72594.293 | H68: =H66+H67 -> 117942.29 | I68: =I66+I67 -> 179702.7
A69: D59 | B69: 對照：訂閱、席位、Free 與 API 計費 token（層級拆分前；應＝合計） | C69: T | D69: =D41+D54 -> 1422.0439 | E69: =E41+E54 -> 17500.367 | F69: =F41+F54 -> 40832.858 | G69: =G41+G54 -> 72594.293 | H69: =H41+H54 -> 117942.29 | I69: =I41+I54 -> 179702.7 | K69: Checks 比對
A70: D60 | B70: API 占 token 合計 | C70: 比例 | D70: =D54/D68 -> 0.5246218 | E70: =E54/E68 -> 0.71013248 | F70: =F54/F68 -> 0.74612903 | G70: =G54/G68 -> 0.74654176 | H70: =H54/H68 -> 0.74331144 | I70: =I54/I68 -> 0.74382682
A71: 五、對照（只列示）
A72: D61 | B72: Claude Code 年化營收（SRC：2025-12、2026-02；D4 不另立營收線） | C72: $B/年 | D72: =SRC_ANT_057 -> 1 | E72: =SRC_ANT_058 -> 2.5 | K72: 只對照；其營收已含在 Max、Team Premium 訂閱與 API 用量

Sheet Revenue
A1: Revenue — 營收：API 牌價（價格事件天數加權）與有效單價、訂閱方案別、API 層級別、其他、廣告（＝0）、總額、雲端平台抽成、淨額、容量上限（A2 佔位）
A2: 2025 為校準年（D14）：訂閱＝SRC 訂閱營收、API＝SRC 用量計價營收、其他＝殘差，總額＝SRC 認列營收。2026 為半校準年（D15 r2，v0.1.1）：總額＝上半年實際（草擬 S-1）＋Q3 實際（投資人簡報）＋Q4（＝Q3 持平），API 為倒推項。2027 起正向推導（Demand 的任務數與每任務 token × 價格反應）。報導口徑為總額（雲端市集以總額認列），淨額＝總額 − 雲端平台抽成（D5 r1）；命題與現金流用淨額。
A3: 單位：營收 $B；牌價與有效單價 $/M token（百萬 token）；月費 $/月。run-rate 里程碑只作對照（D14、D23），不反推參數。
A5: 編號 | B5: 項目 | C5: 單位 | D5: 2025 | E5: 2026 | F5: 2027 | G5: 2028 | H5: 2029 | I5: 2030 | K5: 說明
B6: 年度 | D6: =INP_001 -> 2025 | E6: =INP_002 -> 2026 | F6: =INP_003 -> 2027 | G6: =INP_004 -> 2028 | H6: =INP_005 -> 2029 | I6: =INP_006 -> 2030
A7: 一、年度日期（價格事件天數加權用）
A8: R01 | B8: 年初日（日期序列值） | C8: 日期 | D8: =DATE(D$6,INP_010,INP_011) -> 45658 | E8: =DATE(E$6,INP_010,INP_011) -> 46023 | F8: =DATE(F$6,INP_010,INP_011) -> 46388 | G8: =DATE(G$6,INP_010,INP_011) -> 46753 | H8: =DATE(H$6,INP_010,INP_011) -> 47119 | I8: =DATE(I$6,INP_010,INP_011) -> 47484 | K8: DATE(年度, 起始月, 起始日)
A9: R02 | B9: 年底次日（日期序列值） | C9: 日期 | D9: =DATE((D$6+1),INP_010,INP_011) -> 46023 | E9: =DATE((E$6+1),INP_010,INP_011) -> 46388 | F9: =DATE((F$6+1),INP_010,INP_011) -> 46753 | G9: =DATE((G$6+1),INP_010,INP_011) -> 47119 | H9: =DATE((H$6+1),INP_010,INP_011) -> 47484 | I9: =DATE((I$6+1),INP_010,INP_011) -> 47849 | K9: 下一年度的年初日
A10: 二、API 牌價（$/M token；層級以該層最新模型為準；2025、2026 依價格事件公告日天數加權，2027 起＝2026 年底牌價 ×（1＋年變動率））
A11: R03 | B11: 頂層（Opus→Astra） 輸入牌價（價格事件天數加權） | C11: $/M | D11: =SUMPRODUCT($O$102:$O$110,D$102:D$110) -> 13.958904 | E11: =SUMPRODUCT($O$102:$O$110,E$102:E$110) -> 4.7232877 | F11: =SUMPRODUCT($O$102:$O$110,F$102:F$110) -> 4 | G11: =SUMPRODUCT($O$102:$O$110,G$102:G$110) -> 4 | H11: =SUMPRODUCT($O$102:$O$110,H$102:H$110) -> 4 | I11: =SUMPRODUCT($O$102:$O$110,I$102:I$110) -> 4 | K11: Σ（本事件價 − 前一事件價）× 該事件之後占當年的比例（第十二節事件表）；2027 起各事件比例皆為 1，即 2026 年底牌價
A12: R04 | B12: 頂層（Opus→Astra） 輸入牌價（FY 平均） | C12: $/M | D12: =D11 -> 13.958904 | E12: =E11 -> 4.7232877 | F12: =F11*(1+INP_098) -> 3.4 | G12: =F12*(1+INP_098) -> 2.89 | H12: =G12*(1+INP_098) -> 2.4565 | I12: =H12*(1+INP_098) -> 2.088025 | K12: 2025、2026＝事件加權；2027＝2026 年底牌價 ×（1＋年變動率）；之後逐年
A13: R05 | B13: 頂層（Opus→Astra） 輸出牌價（價格事件天數加權） | C13: $/M | D13: =SUMPRODUCT($O$111:$O$119,D$111:D$119) -> 69.794521 | E13: =SUMPRODUCT($O$111:$O$119,E$111:E$119) -> 23.616438 | F13: =SUMPRODUCT($O$111:$O$119,F$111:F$119) -> 20 | G13: =SUMPRODUCT($O$111:$O$119,G$111:G$119) -> 20 | H13: =SUMPRODUCT($O$111:$O$119,H$111:H$119) -> 20 | I13: =SUMPRODUCT($O$111:$O$119,I$111:I$119) -> 20 | K13: Σ（本事件價 − 前一事件價）× 該事件之後占當年的比例（第十二節事件表）；2027 起各事件比例皆為 1，即 2026 年底牌價
A14: R06 | B14: 頂層（Opus→Astra） 輸出牌價（FY 平均） | C14: $/M | D14: =D13 -> 69.794521 | E14: =E13 -> 23.616438 | F14: =F13*(1+INP_098) -> 17 | G14: =F14*(1+INP_098) -> 14.45 | H14: =G14*(1+INP_098) -> 12.2825 | I14: =H14*(1+INP_098) -> 10.440125 | K14: 2025、2026＝事件加權；2027＝2026 年底牌價 ×（1＋年變動率）；之後逐年
A15: R07 | B15: 中層（Sonnet→Sol） 輸入牌價（價格事件天數加權） | C15: $/M | D15: =SUMPRODUCT($O$120:$O$126,D$120:D$126) -> 3 | E15: =SUMPRODUCT($O$120:$O$126,E$120:E$126) -> 2.4931507 | F15: =SUMPRODUCT($O$120:$O$126,F$120:F$126) -> 2 | G15: =SUMPRODUCT($O$120:$O$126,G$120:G$126) -> 2 | H15: =SUMPRODUCT($O$120:$O$126,H$120:H$126) -> 2 | I15: =SUMPRODUCT($O$120:$O$126,I$120:I$126) -> 2 | K15: Σ（本事件價 − 前一事件價）× 該事件之後占當年的比例（第十二節事件表）；2027 起各事件比例皆為 1，即 2026 年底牌價
A16: R08 | B16: 中層（Sonnet→Sol） 輸入牌價（FY 平均） | C16: $/M | D16: =D15 -> 3 | E16: =E15 -> 2.4931507 | F16: =F15*(1+INP_098) -> 1.7 | G16: =F16*(1+INP_098) -> 1.445 | H16: =G16*(1+INP_098) -> 1.22825 | I16: =H16*(1+INP_098) -> 1.0440125 | K16: 2025、2026＝事件加權；2027＝2026 年底牌價 ×（1＋年變動率）；之後逐年
A17: R09 | B17: 中層（Sonnet→Sol） 輸出牌價（價格事件天數加權） | C17: $/M | D17: =SUMPRODUCT($O$127:$O$133,D$127:D$133) -> 15 | E17: =SUMPRODUCT($O$127:$O$133,E$127:E$133) -> 12.465753 | F17: =SUMPRODUCT($O$127:$O$133,F$127:F$133) -> 10 | G17: =SUMPRODUCT($O$127:$O$133,G$127:G$133) -> 10 | H17: =SUMPRODUCT($O$127:$O$133,H$127:H$133) -> 10 | I17: =SUMPRODUCT($O$127:$O$133,I$127:I$133) -> 10 | K17: Σ（本事件價 − 前一事件價）× 該事件之後占當年的比例（第十二節事件表）；2027 起各事件比例皆為 1，即 2026 年底牌價
A18: R10 | B18: 中層（Sonnet→Sol） 輸出牌價（FY 平均） | C18: $/M | D18: =D17 -> 15 | E18: =E17 -> 12.465753 | F18: =F17*(1+INP_098) -> 8.5 | G18: =F18*(1+INP_098) -> 7.225 | H18: =G18*(1+INP_098) -> 6.14125 | I18: =H18*(1+INP_098) -> 5.2200625 | K18: 2025、2026＝事件加權；2027＝2026 年底牌價 ×（1＋年變動率）；之後逐年
A19: R11 | B19: 低層（Haiku→Luna） 輸入牌價（價格事件天數加權） | C19: $/M | D19: =SUMPRODUCT($O$134:$O$136,D$134:D$136) -> 0.84273973 | E19: =SUMPRODUCT($O$134:$O$136,E$134:E$136) -> 0.78794521 | F19: =SUMPRODUCT($O$134:$O$136,F$134:F$136) -> 0.1 | G19: =SUMPRODUCT($O$134:$O$136,G$134:G$136) -> 0.1 | H19: =SUMPRODUCT($O$134:$O$136,H$134:H$136) -> 0.1 | I19: =SUMPRODUCT($O$134:$O$136,I$134:I$136) -> 0.1 | K19: Σ（本事件價 − 前一事件價）× 該事件之後占當年的比例（第十二節事件表）；2027 起各事件比例皆為 1，即 2026 年底牌價
A20: R12 | B20: 低層（Haiku→Luna） 輸入牌價（FY 平均） | C20: $/M | D20: =D19 -> 0.84273973 | E20: =E19 -> 0.78794521 | F20: =F19*(1+INP_098) -> 0.085 | G20: =F20*(1+INP_098) -> 0.07225 | H20: =G20*(1+INP_098) -> 0.0614125 | I20: =H20*(1+INP_098) -> 0.052200625 | K20: 2025、2026＝事件加權；2027＝2026 年底牌價 ×（1＋年變動率）；之後逐年
A21: R13 | B21: 低層（Haiku→Luna） 輸出牌價（價格事件天數加權） | C21: $/M | D21: =SUMPRODUCT($O$137:$O$139,D$137:D$139) -> 4.2136986 | E21: =SUMPRODUCT($O$137:$O$139,E$137:E$139) -> 3.939726 | F21: =SUMPRODUCT($O$137:$O$139,F$137:F$139) -> 0.5 | G21: =SUMPRODUCT($O$137:$O$139,G$137:G$139) -> 0.5 | H21: =SUMPRODUCT($O$137:$O$139,H$137:H$139) -> 0.5 | I21: =SUMPRODUCT($O$137:$O$139,I$137:I$139) -> 0.5 | K21: Σ（本事件價 − 前一事件價）× 該事件之後占當年的比例（第十二節事件表）；2027 起各事件比例皆為 1，即 2026 年底牌價
A22: R14 | B22: 低層（Haiku→Luna） 輸出牌價（FY 平均） | C22: $/M | D22: =D21 -> 4.2136986 | E22: =E21 -> 3.939726 | F22: =F21*(1+INP_098) -> 0.425 | G22: =F22*(1+INP_098) -> 0.36125 | H22: =G22*(1+INP_098) -> 0.3070625 | I22: =H22*(1+INP_098) -> 0.26100313 | K22: 2025、2026＝事件加權；2027＝2026 年底牌價 ×（1＋年變動率）；之後逐年
A23: 三、API 有效單價（$/M token；含輸出占比、快取讀寫、Batch 與議價折扣）
A24: R15 | B24: 輸入 token 價格倍數（快取讀寫加權） | C24: 倍 | D24: =(1-INP_082-INP_083)+INP_082*SRC_ANT_137+INP_083*SRC_ANT_135 -> 0.4725 | E24: =(1-INP_082-INP_083)+INP_082*SRC_ANT_137+INP_083*SRC_ANT_135 -> 0.4725 | F24: =(1-INP_082-INP_083)+INP_082*SRC_ANT_137+INP_083*SRC_ANT_135 -> 0.4725 | G24: =(1-INP_082-INP_083)+INP_082*SRC_ANT_137+INP_083*SRC_ANT_135 -> 0.4725 | H24: =(1-INP_082-INP_083)+INP_082*SRC_ANT_137+INP_083*SRC_ANT_135 -> 0.4725 | I24: =(1-INP_082-INP_083)+INP_082*SRC_ANT_137+INP_083*SRC_ANT_135 -> 0.4725 | K24: （1 − 讀 − 寫）× 1 ＋ 讀 × 讀取倍數（SRC_ANT 0.1）＋ 寫 × 寫入倍數（SRC_ANT 1.25）
A25: R16 | B25: 折扣係數（Batch × 議價） | C25: 倍 | D25: =(1-INP_084*SRC_ANT_138)*(1-INP_085) -> 0.8775 | E25: =(1-INP_084*SRC_ANT_138)*(1-INP_085) -> 0.8775 | F25: =(1-INP_084*SRC_ANT_138)*(1-INP_085) -> 0.8775 | G25: =(1-INP_084*SRC_ANT_138)*(1-INP_085) -> 0.8775 | H25: =(1-INP_084*SRC_ANT_138)*(1-INP_085) -> 0.8775 | I25: =(1-INP_084*SRC_ANT_138)*(1-INP_085) -> 0.8775 | K25: （1 − Batch 占比 × Batch 折扣）×（1 − 議價折扣）
A26: R17 | B26: 頂層（Opus→Astra） 有效單價 | C26: $/M | D26: =((1-INP_081)*D12*D24+INP_081*D14)*D25 -> 16.879037 | E26: =((1-INP_081)*E12*E24+INP_081*E14)*E25 -> 5.7113758 | F26: =((1-INP_081)*F12*F24+INP_081*F14)*F25 -> 4.111263 | G26: =((1-INP_081)*G12*G24+INP_081*G14)*G25 -> 3.4945736 | H26: =((1-INP_081)*H12*H24+INP_081*H14)*H25 -> 2.9703875 | I26: =((1-INP_081)*I12*I24+INP_081*I14)*I25 -> 2.5248294 | K26: （（1 − 輸出占比）× 輸入價 × 快取倍數 ＋ 輸出占比 × 輸出價）× 折扣係數
A27: R18 | B27: 中層（Sonnet→Sol） 有效單價 | C27: $/M | D27: =((1-INP_081)*D16*D24+INP_081*D18)*D25 -> 3.627585 | E27: =((1-INP_081)*E16*E24+INP_081*E18)*E25 -> 3.0147053 | F27: =((1-INP_081)*F16*F24+INP_081*F18)*F25 -> 2.0556315 | G27: =((1-INP_081)*G16*G24+INP_081*G18)*G25 -> 1.7472868 | H27: =((1-INP_081)*H16*H24+INP_081*H18)*H25 -> 1.4851938 | I27: =((1-INP_081)*I16*I24+INP_081*I18)*I25 -> 1.2624147 | K27: （（1 − 輸出占比）× 輸入價 × 快取倍數 ＋ 輸出占比 × 輸出價）× 折扣係數
A28: R19 | B28: 低層（Haiku→Luna） 有效單價 | C28: $/M | D28: =((1-INP_081)*D20*D24+INP_081*D22)*D25 -> 1.0190367 | E28: =((1-INP_081)*E20*E24+INP_081*E22)*E25 -> 0.9527794 | F28: =((1-INP_081)*F20*F24+INP_081*F22)*F25 -> 0.10278158 | G28: =((1-INP_081)*G20*G24+INP_081*G22)*G25 -> 0.087364339 | H28: =((1-INP_081)*H20*H24+INP_081*H22)*H25 -> 0.074259688 | I28: =((1-INP_081)*I20*I24+INP_081*I22)*I25 -> 0.063120735 | K28: （（1 − 輸出占比）× 輸入價 × 快取倍數 ＋ 輸出占比 × 輸出價）× 折扣係數
A29: R20 | B29: API token 層級組合：中層（Sonnet→Sol） | C29: 比例 | D29: =INP_078 -> 0.65 | E29: =INP_080 -> 0.5 | F29: =INP_080 -> 0.5 | G29: =INP_080 -> 0.5 | H29: =INP_080 -> 0.5 | I29: =INP_080 -> 0.5 | K29: Inputs（2025 一欄；2026 起一欄）
A30: R21 | B30: API token 層級組合：低層（Haiku→Luna） | C30: 比例 | D30: =INP_077 -> 0.2 | E30: =INP_079 -> 0.15 | F30: =INP_079 -> 0.15 | G30: =INP_079 -> 0.15 | H30: =INP_079 -> 0.15 | I30: =INP_079 -> 0.15 | K30: Inputs（2025 一欄；2026 起一欄）
A31: R22 | B31: API token 層級組合：頂層（Opus→Astra） | C31: 比例 | D31: =(1-D29-D30) -> 0.15 | E31: =(1-E29-E30) -> 0.35 | F31: =(1-F29-F30) -> 0.35 | G31: =(1-G29-G30) -> 0.35 | H31: =(1-H29-H30) -> 0.35 | I31: =(1-I29-I30) -> 0.35 | K31: ＝1 − 中層 − 低層
A32: R23 | B32: API 組合有效單價 | C32: $/M | D32: =D31*D26+D29*D27+D30*D28 -> 5.0935931 | E32: =E31*E26+E29*E27+E30*E28 -> 3.6492511 | F32: =F31*F26+F29*F27+F30*F28 -> 2.482175 | G32: =G31*G26+G29*G27+G30*G28 -> 2.1098488 | H32: =H31*H26+H29*H27+H30*H28 -> 1.7933715 | I32: =I31*I26+I29*I27+I30*I28 -> 1.5243657 | K32: Σ 層級占比 × 有效單價
A33: 四、訂閱實收月費（$/月；個人方案與企業席位）
A34: R24 | B34: Pro 實收月費 | C34: $/月 | D34: =SRC_ANT_141*(1-INP_019)+SRC_ANT_142*INP_019 -> 19.1 | E34: =SRC_ANT_141*(1-INP_019)+SRC_ANT_142*INP_019 -> 19.1 | F34: =SRC_ANT_141*(1-INP_019)+SRC_ANT_142*INP_019 -> 19.1 | G34: =SRC_ANT_141*(1-INP_019)+SRC_ANT_142*INP_019 -> 19.1 | H34: =SRC_ANT_141*(1-INP_019)+SRC_ANT_142*INP_019 -> 19.1 | I34: =SRC_ANT_141*(1-INP_019)+SRC_ANT_142*INP_019 -> 19.1 | K34: 月付 ×（1 − 年付占比）＋ 年付月均 × 年付占比
A35: R25 | B35: Max 5x 月費 | C35: $/月 | D35: =SRC_ANT_143 -> 100 | E35: =SRC_ANT_143 -> 100 | F35: =SRC_ANT_143 -> 100 | G35: =SRC_ANT_143 -> 100 | H35: =SRC_ANT_143 -> 100 | I35: =SRC_ANT_143 -> 100 | K35: 只有月付
A36: R26 | B36: Max 20x 月費 | C36: $/月 | D36: =SRC_ANT_144 -> 200 | E36: =SRC_ANT_144 -> 200 | F36: =SRC_ANT_144 -> 200 | G36: =SRC_ANT_144 -> 200 | H36: =SRC_ANT_144 -> 200 | I36: =SRC_ANT_144 -> 200 | K36: 只有月付
A37: R27 | B37: Team 標準席位實收月費 | C37: $/月 | D37: =SRC_ANT_147*(1-INP_020)+SRC_ANT_146*INP_020 -> 23.5 | E37: =SRC_ANT_147*(1-INP_020)+SRC_ANT_146*INP_020 -> 23.5 | F37: =SRC_ANT_147*(1-INP_020)+SRC_ANT_146*INP_020 -> 23.5 | G37: =SRC_ANT_147*(1-INP_020)+SRC_ANT_146*INP_020 -> 23.5 | H37: =SRC_ANT_147*(1-INP_020)+SRC_ANT_146*INP_020 -> 23.5 | I37: =SRC_ANT_147*(1-INP_020)+SRC_ANT_146*INP_020 -> 23.5 | K37: 同上（年付占比）
A38: R28 | B38: Team Premium 席位實收月費 | C38: $/月 | D38: =SRC_ANT_149*(1-INP_020)+SRC_ANT_148*INP_020 -> 117.5 | E38: =SRC_ANT_149*(1-INP_020)+SRC_ANT_148*INP_020 -> 117.5 | F38: =SRC_ANT_149*(1-INP_020)+SRC_ANT_148*INP_020 -> 117.5 | G38: =SRC_ANT_149*(1-INP_020)+SRC_ANT_148*INP_020 -> 117.5 | H38: =SRC_ANT_149*(1-INP_020)+SRC_ANT_148*INP_020 -> 117.5 | I38: =SRC_ANT_149*(1-INP_020)+SRC_ANT_148*INP_020 -> 117.5 | K38: 同上
A39: R29 | B39: Enterprise 席位月費 | C39: $/月 | D39: =SRC_ANT_153 -> 60 | E39: =SRC_ANT_152 -> 20 | F39: =SRC_ANT_152 -> 20 | G39: =SRC_ANT_152 -> 20 | H39: =SRC_ANT_152 -> 20 | I39: =SRC_ANT_152 -> 20 | K39: 2025＝舊制（第三方指稱 $60，SRC Analogy）；2026 起＝$20 席位費，用量另按 API 牌價計（落在 API 營收）
A40: R30 | B40: 個人付費加權月費 | C40: $/月 | D40: =Demand!D8*D34+Demand!D9*D35+Demand!D10*D36 -> 36.235 | E40: =Demand!E8*E34+Demand!E9*E35+Demand!E10*E36 -> 55.37 | F40: =Demand!F8*F34+Demand!F9*F35+Demand!F10*F36 -> 55.37 | G40: =Demand!G8*G34+Demand!G9*G35+Demand!G10*G36 -> 55.37 | H40: =Demand!H8*H34+Demand!H9*H35+Demand!H10*H36 -> 55.37 | I40: =Demand!I8*I34+Demand!I9*I35+Demand!I10*I36 -> 55.37 | K40: Σ 方案占比（Demand）× 月費
A41: R31 | B41: 企業席位加權月費 | C41: $/月 | D41: =Demand!D16*D37+Demand!D17*D38+Demand!D18*D39 -> 50.375 | E41: =Demand!E16*E37+Demand!E17*E38+Demand!E18*E39 -> 40.725 | F41: =Demand!F16*F37+Demand!F17*F38+Demand!F18*F39 -> 40.725 | G41: =Demand!G16*G37+Demand!G17*G38+Demand!G18*G39 -> 40.725 | H41: =Demand!H16*H37+Demand!H17*H38+Demand!H18*H39 -> 40.725 | I41: =Demand!I16*I37+Demand!I17*I38+Demand!I18*I39 -> 40.725 | K41: Σ 席位占比（Demand）× 月費
A42: 五、校準基準（2025 實際：D14；2026 半校準：D15 r2〔v0.1.1；v0.1 為 r1〕）
A43: R32 | B43: 2025 個人訂閱營收＝消費者訂閱占營收（SRC，Analogy）× 2025 營收 | C43: $B | D43: =SRC_ANT_063*SRC_ANT_001 -> 0.69 | K43: SRC_ANT 分析師估計 15%（10–20%）；個人付費人數由此倒推（工作單預設）
A44: R33 | B44: 2025 企業席位訂閱營收＝SRC 訂閱營收 − 個人訂閱 | C44: $B | D44: =SRC_ANT_025-D43 -> 0.099 | K44: 企業席位數由此倒推
A45: R34 | B45: 營收總額基準（2025＝SRC 認列營收；2026＝上半年實際＋Q3 實際＋Q4〔Q3 ×（1＋成長）〕；開關 0＝v0.1：Q1＋Q2＋2026-07 年化 × 下半年月數 ÷ 12） | C45: $B | D45: =SRC_ANT_001 -> 4.6 | E45: =E98+INP_180*(SRC_ANT_384+SRC_ANT_384*(1+INP_181))+(1-INP_180)*SRC_ANT_023*INP_009/INP_008 -> 49.9 | K45: D14；D15 r2（U1）：2026 已有上半年與 Q3 實際，Q4＝Q3 持平（Inputs 成長 0，保守；Decision）；D15 r1 的『下半年＝2026-07 年化 ÷ 2』僅在開關 0 時使用
A46: 六、訂閱營收（$B＝人數（M）× 實收月費 × 12 ÷ 1000）
A47: R35 | B47: Pro 訂閱營收 | C47: $B | D47: =Demand!D12*D34*INP_008/INP_012 -> 0.30915275 | E47: =Demand!E12*E34*INP_008/INP_012 -> 1.0183855 | F47: =Demand!F12*F34*INP_008/INP_012 -> 1.6294169 | G47: =Demand!G12*G34*INP_008/INP_012 -> 2.2811836 | H47: =Demand!H12*H34*INP_008/INP_012 -> 2.9655387 | I47: =Demand!I12*I34*INP_008/INP_012 -> 3.5586464
A48: R36 | B48: Max 5x 訂閱營收 | C48: $B | D48: =Demand!D13*D35*INP_008/INP_012 -> 0.19042362 | E48: =Demand!E13*E35*INP_008/INP_012 -> 1.3710501 | F48: =Demand!F13*F35*INP_008/INP_012 -> 2.1936801 | G48: =Demand!G13*G35*INP_008/INP_012 -> 3.0711522 | H48: =Demand!H13*H35*INP_008/INP_012 -> 3.9924979 | I48: =Demand!I13*I35*INP_008/INP_012 -> 4.7909974
A49: R37 | B49: Max 20x 訂閱營收 | C49: $B | D49: =Demand!D14*D36*INP_008/INP_012 -> 0.19042362 | E49: =Demand!E14*E36*INP_008/INP_012 -> 1.8280668 | F49: =Demand!F14*F36*INP_008/INP_012 -> 2.9249069 | G49: =Demand!G14*G36*INP_008/INP_012 -> 4.0948696 | H49: =Demand!H14*H36*INP_008/INP_012 -> 5.3233305 | I49: =Demand!I14*I36*INP_008/INP_012 -> 6.3879966
A50: R38 | B50: Team 標準 訂閱營收 | C50: $B | D50: =Demand!D20*D37*INP_008/INP_012 -> 0.023091811 | E50: =Demand!E20*E37*INP_008/INP_012 -> 0.064657072 | F50: =Demand!F20*F37*INP_008/INP_012 -> 0.12931414 | G50: =Demand!G20*G37*INP_008/INP_012 -> 0.19397122 | H50: =Demand!H20*H37*INP_008/INP_012 -> 0.26186114 | I50: =Demand!I20*I37*INP_008/INP_012 -> 0.32732643
A51: R39 | B51: Team Premium 訂閱營收 | C51: $B | D51: =Demand!D21*D38*INP_008/INP_012 -> 0.034637717 | E51: =Demand!E21*E38*INP_008/INP_012 -> 0.18473449 | F51: =Demand!F21*F38*INP_008/INP_012 -> 0.36946898 | G51: =Demand!G21*G38*INP_008/INP_012 -> 0.55420347 | H51: =Demand!H21*H38*INP_008/INP_012 -> 0.74817469 | I51: =Demand!I21*I38*INP_008/INP_012 -> 0.93521836
A52: R40 | B52: Enterprise 訂閱營收 | C52: $B | D52: =Demand!D22*D39*INP_008/INP_012 -> 0.041270471 | E52: =Demand!E22*E39*INP_008/INP_012 -> 0.07074938 | F52: =Demand!F22*F39*INP_008/INP_012 -> 0.14149876 | G52: =Demand!G22*G39*INP_008/INP_012 -> 0.21224814 | H52: =Demand!H22*H39*INP_008/INP_012 -> 0.28653499 | I52: =Demand!I22*I39*INP_008/INP_012 -> 0.35816873
A53: R41 | B53: 個人訂閱合計（Pro＋Max） | C53: $B | D53: =D47+D48+D49 -> 0.69 | E53: =E47+E48+E49 -> 4.2175024 | F53: =F47+F48+F49 -> 6.7480039 | G53: =G47+G48+G49 -> 9.4472054 | H53: =H47+H48+H49 -> 12.281367 | I53: =I47+I48+I49 -> 14.73764
A54: R42 | B54: 企業席位訂閱合計（Team＋Enterprise） | C54: $B | D54: =D50+D51+D52 -> 0.099 | E54: =E50+E51+E52 -> 0.32014094 | F54: =F50+F51+F52 -> 0.64028189 | G54: =G50+G51+G52 -> 0.96042283 | H54: =H50+H51+H52 -> 1.2965708 | I54: =I50+I51+I52 -> 1.6207135
A55: R43 | B55: 訂閱合計 | C55: $B | D55: =D53+D54 -> 0.789 | E55: =E53+E54 -> 4.5376434 | F55: =F53+F54 -> 7.3882857 | G55: =G53+G54 -> 10.407628 | H55: =H53+H54 -> 13.577938 | I55: =I53+I54 -> 16.358354
A56: 七、API 營收（$B＝計費 token（T）× 組合有效單價 ÷ 1000）
A57: R44 | B57: API 營收校準值（2025＝SRC 用量計價營收；2026＝總額基準 − 訂閱 − 其他 − 廣告） | C57: $B | D57: =SRC_ANT_026 -> 3.8 | E57: =E45-E55-E64-E65 -> 45.351357 | K57: Demand 的 2025、2026 API token 由此倒推（唯一倒推項）
A58: R45 | B58: API 營收 | C58: $B | D58: =Demand!D54*D32/INP_012 -> 3.8 | E58: =Demand!E54*E32/INP_012 -> 45.351357 | F58: =Demand!F54*F32/INP_012 -> 75.623387 | G58: =Demand!G54*G32/INP_012 -> 114.34256 | H58: =Demand!H54*H32/INP_012 -> 157.22102 | I58: =Demand!I54*I32/INP_012 -> 203.75844 | K58: 計費 token × 組合有效單價
A59: R46 | B59: API 營收：頂層（Opus→Astra） | C59: $B | D59: =Demand!D56*D26/INP_012 -> 1.8888535 | E59: =Demand!E56*E26/INP_012 -> 24.842501 | F59: =Demand!F56*F26/INP_012 -> 43.839645 | G59: =Demand!G56*G26/INP_012 -> 66.285543 | H59: =Demand!H56*H26/INP_012 -> 91.142621 | I59: =Demand!I56*I26/INP_012 -> 118.12084
A60: R47 | B60: API 營收：中層（Sonnet→Sol） | C60: $B | D60: =Demand!D57*D27/INP_012 -> 1.7590991 | E60: =Demand!E57*E27/INP_012 -> 18.732744 | F60: =Demand!F57*F27/INP_012 -> 31.314032 | G60: =Demand!G57*G27/INP_012 -> 47.346816 | H60: =Demand!H57*H27/INP_012 -> 65.101872 | I60: =Demand!I57*I27/INP_012 -> 84.372027
A61: R48 | B61: API 營收：低層（Haiku→Luna） | C61: $B | D61: =Demand!D58*D28/INP_012 -> 0.15204745 | E61: =Demand!E58*E28/INP_012 -> 1.7761112 | F61: =Demand!F58*F28/INP_012 -> 0.46971048 | G61: =Demand!G58*G28/INP_012 -> 0.71020225 | H61: =Demand!H58*H28/INP_012 -> 0.97652809 | I61: =Demand!I58*I28/INP_012 -> 1.2655804
A62: R49 | B62: 檢查：層級合計 − API 營收（應為 0） | C62: $B | D62: =D59+D60+D61-D58 -> 0 | E62: =E59+E60+E61-E58 -> 0 | F62: =F59+F60+F61-F58 -> 0 | G62: =G59+G60+G61-G58 -> 0 | H62: =H59+H60+H61-H58 -> 0 | I62: =I59+I60+I61-I58 -> 0
A63: 八、其他與廣告
A64: R50 | B64: 其他營收（政府、授權等；2025＝認列營收 − 訂閱 − 用量計價） | C64: $B | D64: =SRC_ANT_001-SRC_ANT_025-SRC_ANT_026 -> 0.011 | E64: =D64*(1+INP_101) -> 0.011 | F64: =E64*(1+INP_101) -> 0.011 | G64: =F64*(1+INP_101) -> 0.011 | H64: =G64*(1+INP_101) -> 0.011 | I64: =H64*(1+INP_101) -> 0.011 | K64: 2025 殘差（含四捨五入）；2026 起 ×（1＋年增率）
A65: R51 | B65: 廣告營收（D3：不放廣告） | C65: $B | D65: =INP_017 -> 0 | E65: =INP_017 -> 0 | F65: =INP_017 -> 0 | G65: =INP_017 -> 0 | H65: =INP_017 -> 0 | I65: =INP_017 -> 0 | K65: Decision＝0
A66: 九、總額、雲端平台抽成（D5 r1）、淨額；個人 vs 企業
A67: R52 | B67: 營收總額（報導口徑：雲端市集以總額認列） | C67: $B | D67: =D55+D58+D64+D65 -> 4.6 | E67: =E55+E58+E64+E65 -> 49.9 | F67: =F55+F58+F64+F65 -> 83.022673 | G67: =G55+G58+G64+G65 -> 124.76119 | H67: =H55+H58+H64+H65 -> 170.80996 | I67: =I55+I58+I64+I65 -> 220.1278
A68: R53 | B68: 雲端通路（AWS Bedrock、Google Vertex 等）占 API 營收比例 | C68: 比例 | D68: =SRC_ANT_001*SRC_ANT_027/SRC_ANT_026 -> 0.56894737 | E68: =D68+INP_099 -> 0.56894737 | F68: =D68+INP_099 -> 0.56894737 | G68: =D68+INP_099 -> 0.56894737 | H68: =D68+INP_099 -> 0.56894737 | I68: =D68+INP_099 -> 0.56894737 | K68: 2025＝認列營收 × 雲端通路占比 47%（SRC）÷ 用量計價營收（通路營收全歸 API）；2026 起＝2025 ＋ Inputs 變動
A69: R54 | B69: 雲端通路營收 | C69: $B | D69: =D58*D68 -> 2.162 | E69: =E58*E68 -> 25.802535 | F69: =F58*F68 -> 43.025727 | G69: =G58*G68 -> 65.054899 | H69: =H58*H68 -> 89.450487 | I69: =I58*I68 -> 115.92783
