Workbook

Sheet README
A1: 泰瑞達（Teradyne，TER US）收支與估值模型 v0.1.1（AI 半導體 Project 步驟 5：設備與材料） 2026-10-25
A2: 模型命題：泰瑞達的盈餘由 AI 加速器與 HBM 的測試需求決定：SoC 測試機約三成份額、記憶體測試機約三成份額，乘上與 Advantest 同一份測試機市場；機器人事業另列、不隨 AI 情境。股價要看兩件事：測試機市場在 2027 年是否真的再長四成（公司自己說測試對 WFE 比 2027 年可能回落），以及 GPU 與第二家雲端客戶的份額能否在 2027 年起明顯增加。
A4: 會計年度＝日曆年。金額為百萬美元，EPS 為 GAAP 稀釋（共識為 non-GAAP，差約每年 0.3）。3Q26 預定 2026-10-27 盤後公布，建置日（2026-10-25）尚未公布；FY2026 為錨點：上半年實績＋下半年＝ 2 × 3Q26 指引中點。
A6: 驅動因子 → 推導量
A7: SoC 測試機營收＝SoC 測試機市場（讀 Advantest 模型，CY，三情境同字母）× 泰瑞達市占（FY2026 錨點推得，約三成）；記憶體測試機＝記憶體測試機市場（Advantest 模型，HBM 位元與 DRAM 設備支出同字母）× 市占；IST 隨 SoC 市場；Product Test 前一年 × 成長率
A8: 測試事業稅前利益＝增量利益率 × 測試營收 − 固定成本（FY2025 實績與 FY2026 錨點兩點推導）；機器人營收與稅前利益另列（Assumed，三情境相同）；公司與沖銷、稅率、權益法投資損益沿用 FY2026
A9: 情境 A／B／C（順利／平平／不如預期）：測試機市場讀 Advantest 模型同字母（其顆數係數讀台積電模型：2028 ×1.0／0.8／0.6，2029 ×1.0／0.85／0.6）；泰瑞達 A、B 市占維持，C 與 Advantest 互補（Advantest FY2028 61%、FY2029 56% → 泰瑞達 +5／+10 個百分點）並承受同樣的價格壓力
A10: Val：目標價＝DCF 與 Comparable 加權（第 0 節）；規則值（十年 P/E 分位依循環位置）保留參考。Recon：公司指引、目標模型、共識、Advantest 份額、測試對 WFE 比。Sens：市占、市場、增量利益率、機器人等
A12: 標記：Verified、Interested-party、Analogy、Assumed、Derived。SemiAnalysis 未使用。公司 SEC 原文可開啟；法說數字取自逐字稿摘要網站，待複核。
A13: 已知限制：(1) 測試機市場整份取自 Advantest 模型（以 Advantest 自估的 CY2026 市場校準，Interested-party），CY2027 比 CY2026 高約四成，SoC＋記憶體 ÷ WFE 達一成，高於泰瑞達自己說的 7–9%；(2) 泰瑞達市占由 FY2026 錨點推得，錨點的下半年用 3Q26 指引中點、4Q＝3Q、非 SoC 事業下半年 +10%（Assumed）；(3) 利益率只有兩點，增量利益率 48% 偏高時 FY2027 以後高估；(4) 機器人營收與利益率全為 Assumed；(5) C 情境泰瑞達份額上升是與 Advantest 互補的結果，與「C 最不利」的公司變數方向相反（見 README）；(6) 模型為 GAAP，共識為 non-GAAP。
A14: 本版未做先驗，無 Andy 合理 P/E 對照。
A15: 估值 v2（2026-10-25）：Val 頁「0. 目標價」＝0.5 × DCF 目標價（FY2027–32 明確期＋永續，情境權重 A 0.3／B 0.5／C 0.2，情境價值下限 0）＋0.5 × Comparable 目標價；另列 Comparable 單獨目標價、市場共識目標價與差距拆解、歷史分位檢查。規則值情境加權保留為參考，不叫目標價。
... A17: v0.1.1（2026-10-25）：補上檔空間級距、投資建議、重點觀察（數值不變）。Val 頁末新增「上檔空間級距」「投資建議」兩列（Andy 2026-10-25 14:00、14:17 固定規則），README 頁末新增投資建議與重點觀察三點；既有儲存格位置與數值不變。
A18: ="投資建議："&Val!B138&"（依上檔空間固定規則）" -> 投資建議：中立（依上檔空間固定規則）
A19: ="重點觀察 1：目標價 US$"&TEXT(Val!$B$126,"#,##0.00")&"（DCF "&TEXT(Val!$B$111,"#,##0.00")&"、Comparable（相對倍數調整後）"&TEXT(tp_comp_adj,"#,##0.00")&"；DCF 權重 "&TEXT(tp_w_dcf,"0%")&"），比現價 "&TEXT(px,"#,##0.00")&"（2026-10-23）"&IF(Val!$B$129>=0,"高 "&TEXT(Val!$B$129,"0.0%"),"低 "&TEXT(-Val!$B$129,"0.0%"))&"，級距 "&Val!$B$137&"、投資建議 "&Val!$B$138&"。相對倍數調整係數 "&TEXT(rm_factor,"0.00")&"（本公司 10 年前瞻倍數中位數 ÷ 同業的中位數，夾在 0.5–2.0；Val 第 0.5 節），調整前加權上檔空間 "&TEXT((tp_w_dcf*Val!$B$111+(1-tp_w_dcf)*Val!$B$122)/px-1,"+0.0%;−0.0%")&"；Comparable 單獨（市場主流同業法、未調整）為 "&TEXT(Val!$B$130,"+0.0%;−0.0%")&"。"&"以下為 2026-10-29 相對倍數調整前撰寫的說明，其中數字為調整前：兩法分歧大：同業（Advantest、KLA、Cohu、FormFactor、應用材料）前瞻 P/E 中位數 28.2 倍 × 12 個月後前瞻 EPS 14.38 得 405，DCF 只有 219（比現價低 29.0%）；本模型前瞻 EPS 比共識 FY2027 EPS 11.30 高 27.3%（期間約早一年），共識目標"&"價 446.47 隱含 39.5 倍。" -> 重點觀察 1：目標價 US$354.25（DCF 218.29、Comparable（相對倍數調整後）490.22；DCF 權重 50%），比現價 308.85（2026-10-23）高 14.7%，級距 0%–25%、投資建議 中立。相對倍數調整係數 1.22（本公司 10 年前瞻倍數中位數 ÷ 同業的中位數，夾在 0.5–2.0；Val 第 0.5 節），調整前加權上檔空間 +0.5%；Comparable 單獨（市場主流同業法、未調整）為 +30.3%。以下為 2026-10-29 相對倍數調整前撰寫的說明，其中數字為調整前：兩法分歧大：同業（Advantest、KLA、Cohu、FormFactor、應用材料）前瞻 P/E 中位數 28.2 倍 × 12 個月後前瞻 EPS 14.38 得 405，DCF 只有 219（比現價低 29.0%）；本模型前瞻 EPS 比共識 FY2027 EPS 11.30 高 27.3%（期間約早一年），共識目標價 446.47 隱含 39.5 倍。
A20: 重點觀察 2：EPS 偏高的來源是測試機市場：整份取自 Advantest 模型，CY2027 比 CY2026 高約四成，高於泰瑞達自己說的測試對 WFE 比；SoC 測試機市場 −15% 時 FY2027 EPS −14.0%，SoC 市占 ±5pt 時 ±14.9%（Sens 頁）。
A21: 重點觀察 3：情境 B、C 從 FY2028 起分歧：FY2028 EPS A／B／C 為 16.61／14.15／12.31，DCF 價格帶 154～286。下一個檢驗點是 3Q26 財報（2026-10-27 盤後；建置日尚未公布、未納入）。
A23: 2026-10-29：加權目標價中的 Comparable 改用相對倍數調整後的值（Val 第 0.5 節：同業前瞻倍數中位數 × 本公司 10 年相對同業的倍數比，Bloomberg 前瞻倍數；Andy 2026-10-27「照建議做」、10-29 資料取回）。「Comparable 目標價（市場主流同業法）」維持不調整。重點觀察 1 的第一句已改為公式；重點觀察 2、3 與其他說明中的目標價與上檔空間數字為調整前撰寫，以 Val 頁為準。
A25: v0.2.1（2026-10-31）：依個股模型原則第 8 節調整 In 頁呈現（數值不變）。In 頁 D／F 欄名改「敏感度低」「敏感度高」（只用於 Sens 頁、不進目標價）；In 頁最後新增「情境驅動對照」一節，把上方各情境專屬輸入三情境並排（只引用上方各列，純展示）；HTML 驅動因子一節分「情境驅動」與「單一參數」兩張表。

Sheet In
A1: In — 輸入（藍字；基準欄 E，低 D、高 F）。金額：百萬美元（US$M），市場規模為十億美元（US$B）。每個輸入附兩個來源（來源2 找不到者寫「未找到」）；公司 SEC 原文算一個。【v0.2.1】基準欄 E 進主模型；D／F＝敏感度低／高，只用於 Sens 頁（一次動一個參數）、不進目標價；情境 A／B／C 的驅動見本頁最後一節「情境驅動對照」。
A2: 標記：Verified／Interested-party／Analogy／Assumed／Derived；Analogy、Assumed 給低／高區間。SemiAnalysis 未使用。公司原文（SEC 8-K 新聞稿、10-Q、10-K）在建置環境可開啟
A3: 鍵 | B3: 項目 | C3: 單位 | D3: 敏感度低 | E3: 基準 | F3: 敏感度高 | G3: 標記 | H3: 來源1 | I3: 來源2／說明
A4: A. 測試機市場（讀 Advantest 模型成品；與 Advantest 同一份市場，不另估）
A5: mk_soc25 | B5: SoC 測試機市場 CY2025 | C5: US$B | E5: 6.9 | G5: Interested-party | H5: advantest/dist/20261031_Advantest個股模型_v0.4.1.xlsx｜In!E45 | I5: Advantest（測試機廠）自估；與 Advantest 模型同一值
A6: mk_mem25 | B6: 記憶體測試機市場 CY2025 | C6: US$B | E6: 2.1 | G6: Interested-party | H6: advantest/dist/20261031_Advantest個股模型_v0.4.1.xlsx｜In!E46 | I6: 同上
A7: ms_A_2026 | B7: SoC 測試機市場 CY2026（A） | C7: US$B | E7: 11 | G7: Derived | H7: advantest/dist/20261031_Advantest個股模型_v0.4.1.xlsx｜PL!C47:F47 | I7: Advantest 模型：加速器顆數（markets/memory UNITS）× 每顆測試時間 × 每加權顆支出（以 CY2026 公司市場規模校準）＋非 AI；情境係數讀台積電模型
A8: ms_A_2027 | B8: SoC 測試機市場 CY2027（A） | C8: US$B | E8: 15.414358 | G8: Derived | H8: 同上 | I8: 同上
A9: ms_A_2028 | B9: SoC 測試機市場 CY2028（A） | C9: US$B | E9: 17.299184 | G9: Derived | H9: 同上 | I9: 同上
A10: ms_A_2029 | B10: SoC 測試機市場 CY2029（A） | C10: US$B | E10: 19.236176 | G10: Derived | H10: 同上 | I10: 同上
A11: ms_B_2026 | B11: SoC 測試機市場 CY2026（B） | C11: US$B | E11: 11 | G11: Derived | H11: advantest/dist/20261031_Advantest個股模型_v0.4.1.xlsx｜PL!C78:F78 | I11: 同上
A12: ms_B_2027 | B12: SoC 測試機市場 CY2027（B） | C12: US$B | E12: 15.414358 | G12: Derived | H12: 同上 | I12: 同上
A13: ms_B_2028 | B13: SoC 測試機市場 CY2028（B） | C13: US$B | E13: 14.769523 | G13: Derived | H13: 同上 | I13: 同上
A14: ms_B_2029 | B14: SoC 測試機市場 CY2029（B） | C14: US$B | E14: 17.076287 | G14: Derived | H14: 同上 | I14: 同上
A15: ms_C_2026 | B15: SoC 測試機市場 CY2026（C） | C15: US$B | E15: 11 | G15: Derived | H15: advantest/dist/20261031_Advantest個股模型_v0.4.1.xlsx｜PL!C109:F109 | I15: 同上
A16: ms_C_2027 | B16: SoC 測試機市場 CY2027（C） | C16: US$B | E16: 15.414358 | G16: Derived | H16: 同上 | I16: 同上
... A63: wfe_C_2029 | B63: 晶圓前段設備（WFE）CY2029（C） | C63: US$B | E63: 154.23638 | G63: Derived | H63: 同上 | I63: 同上
A64: B. 泰瑞達市占（FY2026 錨點推得；A、B 情境維持，C 情境與 Advantest 互補）
A65: s_soc | B65: 泰瑞達 SoC 測試機市占（FY2026 錨點 SoC 營收 ÷ CY2026 市場） | C65: % | D65: =s_soc-0.05 -> 0.24539273 | E65: =f26_soc/(ms_A_2026*1000) -> 0.29539273 | F65: =s_soc+0.05 -> 0.34539273 | G65: Derived | H65: Q 頁 FY2026 錨點 SoC 營收 ÷ Advantest 模型 CY2026 SoC 市場 11.0 | I65: 低／高＝±5 個百分點（Assumed）。分析師在 2Q26 法說估泰瑞達測試份額約 37%（公司未證實；口徑不同）
A66: s_mem | B66: 泰瑞達記憶體測試機市占（FY2026 錨點 ÷ CY2026 市場） | C66: % | D66: =s_mem-0.05 -> 0.26675636 | E66: =f26_mem/(mm_A_2026*1000) -> 0.31675636 | F66: =s_mem+0.05 -> 0.36675636 | G66: Derived | H66: Q 頁 FY2026 錨點記憶體營收 ÷ Advantest 模型 CY2026 記憶體市場 2.75 | I66: FY2025 隱含 24.0%（504.9 ÷ 2,100）；2Q26 公司：DRAM 強、NAND 最終測試回溫，記憶體營收創新高
A67: adv_sh26 | B67: Advantest SoC 市占 FY2026（三情境相同；互補計算的基準） | C67: % | E67: =as_A_2026 -> 0.66 | G67: Derived | H67: In 頁 as_A_2026 | I67: C 情境泰瑞達市占＝s_soc＋(adv_sh26 − Advantest 當年市占)，使兩家合計與其他廠份額不變
A68: C. FY2026 錨點（上半年實績＋下半年＝2 × 3Q26 指引中點；三情境相同）
A69: q3_rev | B69: 3Q26 營收指引中點（1,200–1,300） | C69: US$M | D69: 1200 | E69: 1250 | F69: 1300 | G69: Interested-party | H69: 公司 2Q26 新聞稿（8-K，2026-07-28）：3Q26 營收 1,200–1,300 | I69: earningswhispers 2Q26 逐字稿摘要；公司稱上半年約占全年 50–52%
A70: q3_eps | B70: 3Q26 GAAP 稀釋 EPS 指引中點（1.79–2.09） | C70: US$ | D70: 1.79 | E70: 1.94 | F70: 2.09 | G70: Interested-party | H70: 同上：GAAP 1.79–2.09；non-GAAP 1.85–2.15 | I70: MarketBeat 共識 3Q26 EPS 2.08（non-GAAP）
A71: q4_eq_q3 | B71: 4Q26 ÷ 3Q26（營收與 EPS） | C71: x | D71: 0.95 | E71: 1 | F71: 1.1 | G71: Assumed | H71: 無：公司未給 4Q26 指引；2Q26 法說稱下半年營業費用 4Q 與 3Q 相當、上半年占全年 50–52% | I71: 基準 1.0 → 全年營收約 5,111（上半 2,611 ÷ 5,111＝51.1%，在公司 50–52% 之內）
A72: h2g | B72: 下半年非 SoC 事業（記憶體、IST、Product Test、機器人）÷ 上半年 − 1 | C72: % | D72: 0 | E72: 0.1 | F72: 0.2 | G72: Assumed | H72: 公司 2Q26 法說：下半年記憶體、車用工業、IST、Product Test、機器人成長，行動與運算的訂單時點偏弱（earningswhispers 摘要） | I72: SoC＝下半年營收 − 非 SoC（殘差，Derived）
A73: rob_h2 | B73: 下半年機器人稅前利益 | C73: US$M | D73: -10 | E73: 0 | F73: 10 | G73: Assumed | H73: 公司目標 2026 年機器人損益兩平（4Q25 法說，fintool 摘要）；上半年 −3.5 | I73: —
A74: D. 其他事業（前一年 × 成長率；機器人不隨 AI 情境）
A75: g_pt_A | B75: Product Test 年成長 FY2027–29（A） | C75: % | D75: 0.04 | E75: 0.08 | F75: 0.12 | G75: Assumed | H75: FY2025 +8.1%（331.1→358.0，10-K）；2Q26 +26%（AI 相關與國防航太） | I75: —
A76: g_pt_B | B76: Product Test 年成長 FY2027–29（B） | C76: % | D76: 0.01 | E76: 0.05 | F76: 0.09 | G76: Assumed | H76: FY2025 +8.1%（331.1→358.0，10-K）；2Q26 +26%（AI 相關與國防航太） | I76: —
A77: g_pt_C | B77: Product Test 年成長 FY2027–29（C） | C77: % | D77: -0.02 | E77: 0.02 | F77: 0.06 | G77: Assumed | H77: FY2025 +8.1%（331.1→358.0，10-K）；2Q26 +26%（AI 相關與國防航太） | I77: —
A78: g_rob | B78: 機器人營收年成長 FY2027–29（三情境相同） | C78: % | D78: 0 | E78: 0.1 | F78: 0.2 | G78: Assumed | H78: 公司 2Q26：中期機器人隨公司整體成長；FY2025 −15.5%（364.8→308.3，10-K）、2Q26 +33% | I78: 機器人另列，不隨 AI 情境
A79: rm_2027 | B79: 機器人稅前利益率 FY2027 | C79: % | D79: -0.05 | E79: 0.02 | F79: 0.07 | G79: Assumed | H79: FY2025 −32.2%（−99.4 ÷ 308.3，含重組）；上半年 FY2026 −1.8%（−3.5 ÷ 191.2） | I79: 公司目標 2026 年兩平（Interested-party）
A80: rm_2028 | B80: 機器人稅前利益率 FY2028 | C80: % | D80: -0.03 | E80: 0.04 | F80: 0.09 | G80: Assumed | H80: FY2025 −32.2%（−99.4 ÷ 308.3，含重組）；上半年 FY2026 −1.8%（−3.5 ÷ 191.2） | I80: 公司目標 2026 年兩平（Interested-party）
A81: rm_2029 | B81: 機器人稅前利益率 FY2029 | C81: % | D81: -0.02 | E81: 0.05 | F81: 0.1 | G81: Assumed | H81: FY2025 −32.2%（−99.4 ÷ 308.3，含重組）；上半年 FY2026 −1.8%（−3.5 ÷ 191.2） | I81: 公司目標 2026 年兩平（Interested-party）
A82: E. 獲利結構（兩點推導：FY2025 實績與 FY2026 錨點；不寫死利益率）
A83: t_inc | B83: 測試事業（半導體測試＋Product Test）增量稅前利益率 | C83: % | D83: 0.4 | E83: =(f26_ttest-a25_ttest)/(f26_rtest-a25_rtest) -> 0.48265623 | F83: 0.56 | G83: Derived | H83: （FY2026 錨點測試稅前 − FY2025）÷（營收差）；Q 頁 | I83: 低／高 Assumed（固定成本重新推導，使 FY2026 錨點不變）
A84: t_fix | B84: 測試事業固定成本（＝增量利益率 × FY2026 營收 − FY2026 稅前） | C84: US$M | D84: =t_inc_lo*f26_rtest-f26_ttest -> 240.20126 | E84: =t_inc*f26_rtest-f26_ttest -> 629.51873 | F84: =t_inc_hi*f26_rtest-f26_ttest -> 993.81406 | G84: Derived | H84: 同上 | I84: 以 FY2026 錨點定錨（與 FY2025 兩點同一直線）
A85: corp | B85: 公司與沖銷（利息、匯兌、併購費用等）每年 | C85: US$M | E85: =f26_corp -> -10.4 | G85: Derived | H85: FY2026 錨點（上半年 −5.2 × 2） | I85: FY2025 −8.8（10-K）
A86: etr | B86: 有效稅率 | C86: % | D86: 0.12 | E86: =h1_tax/h1_pt -> 0.1417574 | F86: 0.17 | G86: Derived | H86: 上半年 FY2026：128.9 ÷ 909.3（10-Q） | I86: FY2025 12.1%；2Q26 15.1%
A87: aff | B87: 權益法投資損益（Technoprobe，含投資攤銷）每年 | C87: US$M | E87: =2*h1_aff -> -13.2 | G87: Derived | H87: 上半年 FY2026 −6.6 × 2（10-Q） | I87: FY2025 −19.9
A88: sh26 | B88: 稀釋股數 FY2026 | C88: 百萬股 | E88: 157.7 | G88: Verified | H88: 公司 2Q26 新聞稿：2Q26 稀釋加權股數 157.7 | I88: stockanalysis：流通股 156.34（2026-10-24）
A89: bb | B89: 稀釋股數每年減少（回購） | C89: % | D89: 0 | E89: 0.01 | F89: 0.02 | G89: Assumed | H89: FY2024→FY2025 −2.2%（163.3→159.7）、FY2025→2Q26 −1.3% | I89: 上半年 FY2026 回購僅 74.2（FY2025 702.1）
A90: gm_adj_C28 | B90: 情境 C：FY2028 測試事業利益率額外調整（價格競爭） | C90: pt | D90: -0.04 | E90: -0.01 | F90: 0 | G90: Assumed | H90: advantest/dist/20261031_Advantest個股模型_v0.4.1.xlsx｜In!E114 | I90: 與 Advantest 情境 C 毛利率調整同值（兩家同受價格競爭）
A91: gm_adj_C29 | B91: 情境 C：FY2029 測試事業利益率額外調整 | C91: pt | D91: -0.06 | E91: -0.02 | F91: 0 | G91: Assumed | H91: advantest/dist/20261031_Advantest個股模型_v0.4.1.xlsx｜In!E115 | I91: 同上
A92: m_soc | B92: SoC 測試機市場乘數（2027 起；Sens 用） | C92: x | D92: 0.85 | E92: 1 | F92: 1 | G92: Assumed | H92: 基準 1.0＝Advantest 模型市場；低 0.85＝測試對 WFE 比回到公司說的 7–9%（見 Recon） | I92: —
A93: F. 公司指引、目標模型與共識（只作對帳）
A94: h1sh_lo | B94: 上半年占全年營收：下緣 | C94: % | E94: 0.5 | G94: Interested-party | H94: 公司 2Q26 法說：上半年約占 50–52%（earningswhispers 摘要） | I94: 第二來源：未找到
A95: h1sh_hi | B95: 上半年占全年營收：上緣 | C95: % | E95: 0.52 | G95: Interested-party | H95: 同上 | I95: —
A96: cons_rev26 | B96: 共識營收 FY2026 | C96: US$M | E96: 5100 | G96: Interested-party | H96: stockanalysis：US$5.1B（16 位分析師，資料更新 2026-10-20） | I96: 第二來源：MarketBeat 3Q26 共識營收 1.26B（單季）
A97: cons_eps26 | B97: 共識 EPS FY2026（non-GAAP） | C97: US$ | E97: 9.09 | G97: Interested-party | H97: stockanalysis：9.09（區間 8.82–9.35；2026-10-20） | I97: MarketBeat：9.11
A98: cons_eps27 | B98: 共識 EPS FY2027（non-GAAP） | C98: US$ | E98: 11.3 | G98: Interested-party | H98: MarketBeat（2026-10-20）：11.30 | I98: stockanalysis 需付費，未取得
A99: tm_rev | B99: 公司目標模型：營收（ATE 市場 US$12–14B 時，未給年度） | C99: US$M | E99: 6000 | G99: Interested-party | H99: 公司 4Q25 法說（2026-02-03，fintool 摘要）：營收 6.0B、營業利益率 30–34%、non-GAAP EPS 9.50–11.00 | I99: 公司稱 4Q26 法說更新目標模型
A100: tm_eps_lo | B100: 公司目標模型：non-GAAP EPS 下緣 | C100: US$ | E100: 9.5 | G100: Interested-party | H100: 同上 | I100: —
A101: tm_eps_hi | B101: 公司目標模型：non-GAAP EPS 上緣 | C101: US$ | E101: 11 | G101: Interested-party | H101: 同上 | I101: —
A102: tw_lo | B102: 公司：測試對 WFE 比長期區間 下緣 | C102: % | E102: 0.07 | G102: Interested-party | H102: 公司 2Q26 法說：2023 約 4%、2025 約 7%、2026 前五月約 8%；長期 7–9%，2027 可能回到 7%（earningswhispers） | I102: gurufocus 2Q26 摘要（同數字）
A103: tw_hi | B103: 公司：測試對 WFE 比長期區間 上緣 | C103: % | E103: 0.09 | G103: Interested-party | H103: 同上 | I103: —
A104: an_share | B104: 分析師估泰瑞達測試份額（2Q26 法說提問） | C104: % | E104: 0.37 | G104: Interested-party | H104: earningswhispers 2Q26 逐字稿摘要：分析師估約 37%，公司未證實 | I104: 口徑未明（可能為 SoC 或 ATE 合計）
A105: pk_A | B105: 情境 A：設備市場見頂年度（日曆年；循環位置規則用） | C105: 年 | E105: 2029 | G105: Derived | H105: markets/equipment/dist/20261023_半導體設備市場模型_v0.1.3.xlsx｜Mkt!C12 | I105: 設備股共用規則（tools/cycle_position.py）：FY(t) 早於見頂年＝中段、等於＝見頂、晚於＝谷底；泰瑞達會計年度＝日曆年
... A109: sa_fpe | B109: 遠期 P/E（stockanalysis，2026-10-23 價格） | C109: x | E109: 32.52 | G109: Interested-party | H109: stockanalysis statistics（2026-10-24 更新） | I109: 自算見 Val
A110: I. 規則值情境權重（Val 頁「舊法：規則值情境加權（參考）」與目標價 DCF 共用；Andy 可改）
A111: tp_wA | B111: 目標價情境權重 A | C111: % | E111: 0.3 | G111: Assumed | H111: Andy 可改（工作單 2026-10-25 預設 A 0.3／B 0.5／C 0.2） | I111: 三者合計應為 100%
A112: tp_wB | B112: 目標價情境權重 B | C112: % | E112: 0.5 | G112: Assumed | H112: Andy 可改（工作單 2026-10-25 預設 A 0.3／B 0.5／C 0.2） | I112: 三者合計應為 100%
A113: tp_wC | B113: 目標價情境權重 C | C113: % | E113: 0.2 | G113: Assumed | H113: Andy 可改（工作單 2026-10-25 預設 A 0.3／B 0.5／C 0.2） | I113: 三者合計應為 100%
A115: J. 目標價（DCF 與 Comparable 加權）與 FY2030–32 收斂法參數（黃底＝Assumed，Andy 可改）
A116: tp_r | B116: 折現率（股東權益要求報酬；美、台、日、韓同一值） | C116: % | E116: 0.1 | G116: Assumed | H116: Andy 可改（工作單 2026-10-25 預設 10%） | I116: β 約 1.75（MarketBeat）高於市場，但依工作單不改值
A117: tp_g | B117: 長期成長率（永續成長；收斂法 FY2032 營收年增的基準） | C117: % | E117: 0.04 | G117: Assumed | H117: Andy 可改（工作單預設 4%） | I117: 情境 A＝tp_g＋2pt、B＝tp_g、C＝tp_g−2pt（PL 頁延伸區塊）
A118: tp_roe | B118: ROE（近三年平均，FY2023–FY2025） | C118: % | E118: =AVERAGE(Val!E14/AVERAGE(Val!G13:G14),Val!E15/AVERAGE(Val!G14:G15),Val!E16/AVERAGE(Val!G15:G16)) -> 0.19353862 | G118: Derived | H118: SEC XBRL（10-K）：淨利 ÷ 平均股東權益：FY2023 18.0%、FY2024 20.3%、FY2025 19.7%（Val 頁第 1 節） | I118: stockanalysis 近 12 月 ROE 36.46%（AI 期間，非三年平均）
A119: tp_w_dcf | B119: 目標價中 DCF 的權重；其餘為 Comparable | C119: % | E119: 0.5 | G119: Assumed | H119: Andy 可改（2026-10-25 11:53：DCF／Comparable 各半） | I119: —
A120: nim10 | B120: 十年平均淨利率（FY2016–FY2025，各年淨利 ÷ 營收的平均） | C120: % | E120: =AVERAGE(Val!E7/Val!F7,Val!E8/Val!F8,Val!E9/Val!F9,Val!E10/Val!F10,Val!E11/Val!F11,Val!E12/Val!F12,Val!E13/Val!F13,Val!E14/Val!F14,Val!E15/Val!F15,Val!E16/Val!F16) -> 0.18003103 | G120: Derived | H120: SEC XBRL（10-K）淨利 ÷ 營收（Val 頁第 1 節；含 FY2016 虧損） | I120: macrotrends EPS 逐年相同（第二來源）
A121: cons_tp | B121: 市場共識目標價（賣方平均） | C121: US$ | E121: 446.47 | G121: Interested-party | H121: stockanalysis：17 位分析師平均 US$446.47（中位數 450；區間 350–550），資料更新 2026-10-20 | I121: MarketBeat：396.80（11 買進、5 持有）；早於 2026-10-27 的 3Q26 財報
A122: cons_feps | B122: 共識前瞻 EPS（差距拆解用） | C122: US$ | E122: =cons_eps27 -> 11.3 | G122: Interested-party | H122: 共識前瞻 EPS＝MarketBeat FY2027 共識 11.30（non-GAAP）；比本模型 12 個月後前瞻 EPS（約 FY2028）早約一年，且為 non-GAAP，EPS 因素因此偏大 | I122: Interested-party
A124: 情境驅動對照（三情境並排，進主模型的加權目標價；本節只引用上方各列，修改請改上方藍字。上方「敏感度低／高」欄只用於 Sens 頁，不進目標價）
A125: 鍵 | B125: 項目 | C125: 單位 | D125: 情境 A（樂觀） | E125: 情境 B（基準） | F125: 情境 C（保守） | G125: 標記 | H125: 說明
A126: scn_ms__2026 | B126: SoC 測試機市場 CY2026 | C126: US$B | D126: =E7 -> 11 | E126: =E11 -> 11 | F126: =E15 -> 11 | G126: Derived | H126: 引用 In 頁 ms_A_2026／ms_B_2026／ms_C_2026；修改請改上方藍字
A127: scn_ms__2027 | B127: SoC 測試機市場 CY2027 | C127: US$B | D127: =E8 -> 15.414358 | E127: =E12 -> 15.414358 | F127: =E16 -> 15.414358 | G127: Derived | H127: 引用 In 頁 ms_A_2027／ms_B_2027／ms_C_2027；修改請改上方藍字
A128: scn_ms__2028 | B128: SoC 測試機市場 CY2028 | C128: US$B | D128: =E9 -> 17.299184 | E128: =E13 -> 14.769523 | F128: =E17 -> 12.239862 | G128: Derived | H128: 引用 In 頁 ms_A_2028／ms_B_2028／ms_C_2028；修改請改上方藍字
A129: scn_ms__2029 | B129: SoC 測試機市場 CY2029 | C129: US$B | D129: =E10 -> 19.236176 | E129: =E14 -> 17.076287 | F129: =E18 -> 13.476472 | G129: Derived | H129: 引用 In 頁 ms_A_2029／ms_B_2029／ms_C_2029；修改請改上方藍字
A130: scn_mm__2026 | B130: 記憶體測試機市場 CY2026 | C130: US$B | D130: =E19 -> 2.75 | E130: =E23 -> 2.75 | F130: =E27 -> 2.75 | G130: Derived | H130: 引用 In 頁 mm_A_2026／mm_B_2026／mm_C_2026；修改請改上方藍字
A131: scn_mm__2027 | B131: 記憶體測試機市場 CY2027 | C131: US$B | D131: =E20 -> 3.8800741 | E131: =E24 -> 3.8800741 | F131: =E28 -> 3.8800741 | G131: Derived | H131: 引用 In 頁 mm_A_2027／mm_B_2027／mm_C_2027；修改請改上方藍字
A132: scn_mm__2028 | B132: 記憶體測試機市場 CY2028 | C132: US$B | D132: =E21 -> 5.0460769 | E132: =E25 -> 4.7378491 | F132: =E29 -> 3.640828 | G132: Derived | H132: 引用 In 頁 mm_A_2028／mm_B_2028／mm_C_2028；修改請改上方藍字
A133: scn_mm__2029 | B133: 記憶體測試機市場 CY2029 | C133: US$B | D133: =E22 -> 6.2022378 | E133: =E26 -> 5.7899737 | F133: =E30 -> 4.3133587 | G133: Derived | H133: 引用 In 頁 mm_A_2029／mm_B_2029／mm_C_2029；修改請改上方藍字
A134: scn_as__2026 | B134: Advantest SoC 市占 FY2026（C；Advantest 會計年度 4–3 月） | C134: % | D134: =E31 -> 0.66 | E134: =E35 -> 0.66 | F134: =E39 -> 0.66 | G134: Derived | H134: 引用 In 頁 as_A_2026／as_B_2026／as_C_2026；修改請改上方藍字
A135: scn_as__2027 | B135: Advantest SoC 市占 FY2027（C；Advantest 會計年度 4–3 月） | C135: % | D135: =E32 -> 0.66 | E135: =E36 -> 0.66 | F135: =E40 -> 0.66 | G135: Derived | H135: 引用 In 頁 as_A_2027／as_B_2027／as_C_2027；修改請改上方藍字
A136: scn_as__2028 | B136: Advantest SoC 市占 FY2028（C；Advantest 會計年度 4–3 月） | C136: % | D136: =E33 -> 0.66 | E136: =E37 -> 0.66 | F136: =E41 -> 0.61 | G136: Derived | H136: 引用 In 頁 as_A_2028／as_B_2028／as_C_2028；修改請改上方藍字
A137: scn_as__2029 | B137: Advantest SoC 市占 FY2029（C；Advantest 會計年度 4–3 月） | C137: % | D137: =E34 -> 0.66 | E137: =E38 -> 0.66 | F137: =E42 -> 0.56 | G137: Derived | H137: 引用 In 頁 as_A_2029／as_B_2029／as_C_2029；修改請改上方藍字
A138: scn_um28 | B138: 2028 加速器顆數 ÷ 基準（說明用） | C138: x | D138: =E43 -> 1 | E138: =E45 -> 0.8 | F138: =E47 -> 0.6 | G138: Derived | H138: 引用 In 頁 um28_A／um28_B／um28_C；修改請改上方藍字
A139: scn_um29 | B139: 2029 加速器顆數 ÷ 基準（說明用） | C139: x | D139: =E44 -> 1 | E139: =E46 -> 0.85 | F139: =E48 -> 0.6 | G139: Derived | H139: 引用 In 頁 um29_A／um29_B／um29_C；修改請改上方藍字
A140: scn_wfe__2025 | B140: 晶圓前段設備（WFE）CY2025 | C140: US$B | D140: =E49 -> 116.89683 | E140: =E54 -> 116.89683 | F140: =E59 -> 116.89683 | G140: Derived | H140: 引用 In 頁 wfe_A_2025／wfe_B_2025／wfe_C_2025；修改請改上方藍字
A141: scn_wfe__2026 | B141: 晶圓前段設備（WFE）CY2026 | C141: US$B | D141: =E50 -> 160.04501 | E141: =E55 -> 160.04501 | F141: =E60 -> 160.04501 | G141: Derived | H141: 引用 In 頁 wfe_A_2026／wfe_B_2026／wfe_C_2026；修改請改上方藍字
A142: scn_wfe__2027 | B142: 晶圓前段設備（WFE）CY2027 | C142: US$B | D142: =E51 -> 192.79547 | E142: =E56 -> 192.79547 | F142: =E61 -> 192.79547 | G142: Derived | H142: 引用 In 頁 wfe_A_2027／wfe_B_2027／wfe_C_2027；修改請改上方藍字
A143: scn_wfe__2028 | B143: 晶圓前段設備（WFE）CY2028 | C143: US$B | D143: =E52 -> 216.62863 | E143: =E57 -> 192.79547 | F143: =E62 -> 154.23638 | G143: Derived | H143: 引用 In 頁 wfe_A_2028／wfe_B_2028／wfe_C_2028；修改請改上方藍字
A144: scn_wfe__2029 | B144: 晶圓前段設備（WFE）CY2029 | C144: US$B | D144: =E53 -> 228.90369 | E144: =E58 -> 183.1557 | F144: =E63 -> 154.23638 | G144: Derived | H144: 引用 In 頁 wfe_A_2029／wfe_B_2029／wfe_C_2029；修改請改上方藍字
A145: scn_g_pt | B145: Product Test 年成長 FY2027–29 | C145: % | D145: =E75 -> 0.08 | E145: =E76 -> 0.05 | F145: =E77 -> 0.02 | G145: Derived | H145: 引用 In 頁 g_pt_A／g_pt_B／g_pt_C；修改請改上方藍字
A146: scn_pk | B146: 設備市場見頂年度（日曆年；循環位置規則用） | C146: 年 | D146: =E105 -> 2029 | E146: =E106 -> 2028 | F146: =E107 -> 2027 | G146: Derived | H146: 引用 In 頁 pk_A／pk_B／pk_C；修改請改上方藍字
A147: scn_gm_adj_C28 | B147: FY2028 測試事業利益率額外調整（價格競爭） | C147: pt | D147: 0 | E147: 0 | F147: =E90 -> -0.01 | G147: Derived | H147: 引用 In 頁 gm_adj_C28；情境 A 無專屬輸入列；情境 B 無專屬輸入列，填 0
A148: scn_gm_adj_C29 | B148: FY2029 測試事業利益率額外調整 | C148: pt | D148: 0 | E148: 0 | F148: =E91 -> -0.02 | G148: Derived | H148: 引用 In 頁 gm_adj_C29；情境 A 無專屬輸入列；情境 B 無專屬輸入列，填 0
A149: scn_w | B149: 情境權重 | C149: % | D149: =E111 -> 0.3 | E149: =E112 -> 0.5 | F149: =E113 -> 0.2 | G149: Derived | H149: 引用 In 頁 tp_wA／tp_wB／tp_wC；修改請改上方藍字

Sheet Q
A1: Q — 實績（百萬美元；EPS 為美元，GAAP 稀釋）。會計年度＝日曆年。藍字＝輸入（SEC 8-K 新聞稿、10-Q、10-K）；黑字＝公式（Derived）
A2: 3Q26（2026-07～09）：預定 2026-10-27 美東 16:30 盤後公布（公司公告），建置日 2026-10-25 尚未公布，故不納入；FY2026 下半年以 3Q26 指引中點推估（見下方錨點）。公布後更新本頁 I 欄與 In 頁 C 節
A3: 項目 | B3: 1Q25 | C3: 2Q25 | D3: 3Q25 | E3: 4Q25 | F3: FY2025 | G3: 1Q26 | H3: 2Q26 | I3: 3Q26（未公布） | J3: 上半年 FY2026 | K3: 標記 | L3: 來源1（公司 SEC 文件） | M3: 來源2／說明
A4: SoC 測試機（System on-a-Chip） | B4: 406.4 | C4: 396.6 | D4: 440.2 | E4: =F4-SUM(B4:D4) -> 646.5 | F4: 1889.7 | G4: =J4-H4 -> 881.8 | H4: 843 | I4: 預定 2026-10-27 盤後公布，尚未公布 | J4: 1724.8 | K4: Verified／Derived | L4: 10-Q／10-K 收入拆分表（Disaggregation of Revenue）：2Q25 396.6、3Q25 440.2、FY2025 1,889.7、2Q26 843.0、上半年 1,724.8；1Q25＝上半年 803.0 − 2Q25 | M4: gurufocus 2Q26 法說摘要：SoC 843、記憶體 212、IST 67
A5: 記憶體測試機 | B5: 109.4 | C5: 60.9 | D5: 128.1 | E5: =F5-SUM(B5:D5) -> 206.5 | F5: 504.9 | G5: =J5-H5 -> 202.5 | H5: 212.3 | J5: 414.8 | K5: Verified／Derived | L5: 10-Q／10-K 收入拆分表（Disaggregation of Revenue）：1Q25＝上半年 170.4 − 2Q25；4Q25＝全年 − 前三季 | M5: 同上（記憶體 212，創新高）
A6: IST（整合系統測試） | B6: 26.7 | C6: 34.3 | D6: 37.6 | E6: =F6-SUM(B6:D6) -> 30.6 | F6: 129.2 | G6: =J6-H6 -> 26.6 | H6: 66.5 | J6: 93.1 | K6: Verified／Derived | L6: 10-Q／10-K 收入拆分表（Disaggregation of Revenue） | M6: 同上（IST 67，+94%）
A7: 半導體測試（SoC＋記憶體＋IST） | B7: =B4+B5+B6 -> 542.5 | C7: =C4+C5+C6 -> 491.8 | D7: =D4+D5+D6 -> 605.9 | E7: =E4+E5+E6 -> 883.6 | F7: =F4+F5+F6 -> 2523.8 | G7: =G4+G5+G6 -> 1110.9 | H7: =H4+H5+H6 -> 1121.8 | J7: =J4+J5+J6 -> 2232.7 | K7: Derived | L7: 公司新聞稿：1Q25 543、2Q25 492、3Q25 606、4Q25 883、1Q26 1,111、2Q26 1,122；FY2025 2,523.7（10-K） | M7: 檢查列見下
A8: Product Test | B8: 74.2 | C8: 85.1 | D8: 88.3 | E8: =F8-SUM(B8:D8) -> 110.4 | F8: 358 | G8: =J8-H8 -> 80.5 | H8: 107.2 | J8: 187.7 | K8: Verified／Derived | L8: 公司各季新聞稿（8-K Ex.99.1）與 10-K（FY2025 358.0） | M8: MD&A 各季比較表
A9: 機器人（Robotics） | B9: 69 | C9: 74.9 | D9: 75.1 | E9: =F9-SUM(B9:D9) -> 89.3 | F9: 308.3 | G9: =J9-H9 -> 91.3 | H9: 99.9 | J9: 191.2 | K9: Verified／Derived | L9: 公司各季新聞稿（8-K Ex.99.1）與 10-K（FY2025 308.3） | M9: MD&A 各季比較表
A10: 營收 | B10: 685.7 | C10: 651.8 | D10: 769.2 | E10: 1083.3 | F10: 3190 | G10: 1282.5 | H10: 1329 | J10: 2611.5 | K10: Verified | L10: 公司各季新聞稿（8-K Ex.99.1）：FY2025 3,190.0（+13%）；2Q26 1,329.0（+104%） | M10: stockanalysis／MarketBeat（2Q26 1.33B）
A11: 檢查：半導體測試＋Product Test＋機器人 − 營收（應約為 0；單季分項四捨五入） | B11: =B7+B8+B9-B10 -> 0 | C11: =C7+C8+C9-C10 -> 0 | D11: =D7+D8+D9-D10 -> 0.1 | E11: =E7+E8+E9-E10 -> 0 | F11: =F7+F8+F9-F10 -> 0.1 | G11: =G7+G8+G9-G10 -> 0.2 | H11: =H7+H8+H9-H10 -> -0.1 | J11: =J7+J8+J9-J10 -> 0.1 | K11: — | L11: — | M11: —
A12: 毛利 | B12: 415.3 | C12: 373 | D12: 449.3 | E12: 619.7 | F12: 1857.3 | G12: 780.9 | H12: 794.6 | J12: 1575.6 | K12: Verified | L12: 公司各季新聞稿（8-K Ex.99.1） | M12: —
A13: 毛利率 | B13: =B12/B10 -> 0.60565845 | C13: =C12/C10 -> 0.57226143 | D13: =D12/D10 -> 0.58411336 | E13: =E12/E10 -> 0.57204837 | F13: =F12/F10 -> 0.58222571 | G13: =G12/G10 -> 0.60888889 | H13: =H12/H10 -> 0.59789315 | J13: =J12/J10 -> 0.60333142 | K13: Derived | L13: — | M13: 公司：FY2025 58.3%（non-GAAP）；3Q26 指引 58–59%；全年約 59%（2Q26 法說）
A14: 營業利益（GAAP） | B14: 120.8 | C14: 90.7 | D14: 145.3 | E14: 293.2 | F14: 650.1 | G14: 473 | H14: 437.8 | J14: 910.8 | K14: Verified／Derived | L14: 公司各季新聞稿（8-K Ex.99.1）：1Q25＝上半年 211.5 − 2Q25 | M14: —
A15: 稅前利益（含權益法前） | B15: 119 | C15: 96.6 | D15: 148.1 | E15: 289.6 | F15: 653.3 | G15: 465.7 | H15: 443.6 | J15: 909.3 | K15: Verified／Derived | L15: 公司各季新聞稿（8-K Ex.99.1）：1Q25＝上半年 215.6 − 2Q25 | M15: —
A16: 所得稅 | B16: 14.5 | C16: 12.3 | D16: 23.3 | E16: 29.2 | F16: 79.3 | G16: 62.2 | H16: 66.8 | J16: 128.9 | K16: Verified／Derived | L16: 公司各季新聞稿（8-K Ex.99.1） | M16: —
A17: 權益法投資損益（Technoprobe） | B17: -5.6 | C17: -5.9 | D17: -5.2 | E17: -3.2 | F17: -19.9 | G17: -4.6 | H17: -1.9 | J17: -6.6 | K17: Verified／Derived | L17: 公司各季新聞稿（8-K Ex.99.1） | M17: —
A18: 淨利（歸屬泰瑞達） | B18: 98.9 | C18: 78.4 | D18: 119.6 | E18: 257.2 | F18: 554 | G18: 398.9 | H18: 374.5 | J18: 773.4 | K18: Verified | L18: 公司各季新聞稿（8-K Ex.99.1） | M18: —
A19: EPS（GAAP 稀釋） | B19: 0.61 | C19: 0.49 | D19: 0.75 | E19: 1.63 | F19: 3.47 | G19: 2.53 | H19: 2.38 | J19: 4.91 | K19: Verified | L19: 公司各季新聞稿（8-K Ex.99.1）（四季加總 3.48 與全年 3.47 差為股數加權） | M19: macrotrends 年度 EPS（FY2024 3.32 等）
A20: 稀釋加權股數（百萬股） | B20: 162 | C20: 160.1 | D20: 159.1 | E20: 157.7 | F20: 159.7 | G20: 157.6 | H20: 157.7 | J20: 157.7 | K20: Verified | L20: 公司各季新聞稿（8-K Ex.99.1） | M20: —
A22: 事業別稅前利益（10-K／10-Q 分部資訊；機器人另列）
A23: 事業 | B23: FY2024 | C23: FY2025 | D23: 上半年 FY2026 | E23: 2Q26 | K23: 標記 | L23: 來源1 | M23: 來源2／說明
A24: 半導體測試 | B24: 558.2 | C24: 700.7 | D24: 895.4 | E24: 427.3 | K24: Verified | L24: 10-K FY2025、10-Q 2Q26：Income (Loss) Before Income Taxes 分部表 | M24: FY2024 公司與沖銷含出售 DIS 事業利益 57.1
A25: Product Test | B25: 65.7 | C25: 60.7 | D25: 22.7 | E25: 18 | K25: Verified | L25: 10-K FY2025、10-Q 2Q26：Income (Loss) Before Income Taxes 分部表 | M25: FY2024 公司與沖銷含出售 DIS 事業利益 57.1
A26: 機器人 | B26: -77.6 | C26: -99.4 | D26: -3.5 | E26: -2.6 | K26: Verified | L26: 10-K FY2025、10-Q 2Q26：Income (Loss) Before Income Taxes 分部表 | M26: FY2024 公司與沖銷含出售 DIS 事業利益 57.1
A27: 公司與沖銷 | B27: 62.7 | C27: -8.8 | D27: -5.2 | E27: 0.9 | K27: Verified | L27: 10-K FY2025、10-Q 2Q26：Income (Loss) Before Income Taxes 分部表 | M27: FY2024 公司與沖銷含出售 DIS 事業利益 57.1
A28: 合計（應＝稅前利益） | B28: =SUM(B24:B27) -> 609 | C28: =SUM(C24:C27) -> 653.2 | D28: =SUM(D24:D27) -> 909.4 | E28: =SUM(E24:E27) -> 443.6 | M28: FY2025 應＝653.3；上半年應＝909.3（四捨五入差）
A30: FY2026 錨點（上半年實績＋下半年推估；三情境相同）
A31: 項目 | B31: 上半年（實績） | C31: 下半年（推估） | D31: FY2026 | K31: 標記 | L31: 說明
A32: SoC 測試機 | B32: =J4 -> 1724.8 | C32: =C40-C33-C34-C35-C36 -> 1524.52 | D32: =B32+C32 -> 3249.32 | L32: Derived：下半年營收 − 非 SoC 事業（殘差）
A33: 記憶體測試機 | B33: =J5 -> 414.8 | C33: =B33*(1+h2g) -> 456.28 | D33: =B33+C33 -> 871.08 | L33: 上半年 × (1＋h2g)
A34: IST | B34: =J6 -> 93.1 | C34: =B34*(1+h2g) -> 102.41 | D34: =B34+C34 -> 195.51 | L34: 同上
A35: Product Test | B35: =J8 -> 187.7 | C35: =B35*(1+h2g) -> 206.47 | D35: =B35+C35 -> 394.17 | L35: 同上
A36: 機器人 | B36: =J9 -> 191.2 | C36: =B36*(1+h2g) -> 210.32 | D36: =B36+C36 -> 401.52 | L36: 同上；不隨 AI 情境
A37: 測試事業營收（半導體測試＋Product Test） | B37: =B32+B33+B34+B35 -> 2420.4 | C37: =C32+C33+C34+C35 -> 2289.68 | D37: =B37+C37 -> 4710.08
A38: （保留）
A39: 營收：下半年＝3Q26 指引中點 ×（1＋4Q÷3Q） | C39: =q3_rev*(1+q4_eq_q3) -> 2500 | L39: Interested-party（指引）＋Assumed（4Q＝3Q）
A40: 營收 | B40: =J10 -> 2611.5 | C40: =C39 -> 2500 | D40: =B40+C40 -> 5111.5
A41: 上半年占全年（公司 50–52%） | D41: =B40/D40 -> 0.51090678
A42: 淨利（下半年＝3Q26 GAAP EPS 指引中點 ×（1＋4Q÷3Q）× 稀釋股數） | B42: =J18 -> 773.4 | C42: =q3_eps*(1+q4_eq_q3)*sh26 -> 611.876 | D42: =B42+C42 -> 1385.276
A43: 權益法投資損益（下半年＝上半年） | B43: =J17 -> -6.6 | C43: =B43 -> -6.6 | D43: =B43+C43 -> -13.2
A44: 稅前利益（下半年＝（淨利 − 權益法）÷（1 − 稅率）） | B44: =J15 -> 909.3 | C44: =(C42-C43)/(1-etr) -> 720.63074 | D44: =B44+C44 -> 1629.9307
A45: 所得稅 | B45: =J16 -> 128.9 | C45: =C44*etr -> 102.15474 | D45: =B45+C45 -> 231.05474
A46: 機器人稅前利益 | B46: =D26 -> -3.5 | C46: =rob_h2 -> 0 | D46: =B46+C46 -> -3.5
A47: 公司與沖銷（下半年＝上半年） | B47: =D27 -> -5.2 | C47: =B47 -> -5.2 | D47: =B47+C47 -> -10.4
A48: 測試事業稅前利益（稅前 − 機器人 − 公司與沖銷） | B48: =B44-B46-B47 -> 918 | C48: =C44-C46-C47 -> 725.83074 | D48: =B48+C48 -> 1643.8307
A49: EPS（GAAP 稀釋） | D49: =D42/sh26 -> 8.7842486
A50: 毛利率（上半年實績；下半年＝3Q26 指引中點 58.5%，全年約 59%） | B50: =J13 -> 0.60333142 | C50: 0.585 | D50: =(B40*B50+C40*C50)/D40 -> 0.59436565
A51: 對照：FY2025 測試事業營收、測試事業稅前利益（10-K） | B51: =F7+F8 -> 2881.8 | C51: =C24+C25 -> 761.4
A52: 上半年 FY2026：稅前、所得稅、權益法（10-Q） | B52: =J15 -> 909.3 | C52: =J16 -> 128.9 | D52: =J17 -> -6.6

Sheet Units
A1: Units — 測試機市場（十億美元；日曆年；讀 Advantest 模型成品）與 SoC 市占合計。泰瑞達 A、B 情境市占維持 FY2026 水準；C 情境與 Advantest 互補（Advantest 讓出的份額全由泰瑞達取得），三情境的「其他廠」份額相同
A3: 項目 | B3: 單位 | C3: CY2025 | D3: CY2026 | E3: CY2027 | F3: CY2028 | G3: CY2029 | H3: 說明
A4: 情境 A
A5: SoC 測試機市場 | B5: US$B | C5: =mk_soc25 -> 6.9 | D5: =ms_A_2026 -> 11 | E5: =ms_A_2027 -> 15.414358 | F5: =ms_A_2028 -> 17.299184 | G5: =ms_A_2029 -> 19.236176
A6: 記憶體測試機市場 | B6: US$B | C6: =mk_mem25 -> 2.1 | D6: =mm_A_2026 -> 2.75 | E6: =mm_A_2027 -> 3.8800741 | F6: =mm_A_2028 -> 5.0460769 | G6: =mm_A_2029 -> 6.2022378
A7: Advantest SoC 市占（Advantest 模型，FY 口徑） | B7: % | C7: =as_A_2026 -> 0.66 | D7: =as_A_2026 -> 0.66 | E7: =as_A_2027 -> 0.66 | F7: =as_A_2028 -> 0.66 | G7: =as_A_2029 -> 0.66
A8: 泰瑞達 SoC 市占 | B8: % | C8: =a25_soc/(mk_soc25*1000) -> 0.27386957 | D8: =s_soc -> 0.29539273 | E8: =s_soc -> 0.29539273 | F8: =s_soc -> 0.29539273 | G8: =s_soc -> 0.29539273
A9: 其他廠 SoC 市占（1 − Advantest − 泰瑞達） | B9: % | C9: =1-C7-C8 -> 0.066130435 | D9: =1-D7-D8 -> 0.044607273 | E9: =1-E7-E8 -> 0.044607273 | F9: =1-F7-F8 -> 0.044607273 | G9: =1-G7-G8 -> 0.044607273 | H9: CY2025 用 Advantest 自估 66% 對照；三情境 CY2026 起其他廠份額相同（互補設計）
A10: SoC＋記憶體測試機市場 ÷ 晶圓前段設備（WFE） | B10: % | C10: =(mk_soc25+mk_mem25)/wfe_A_2025 -> 0.076990966 | D10: =(ms_A_2026+mm_A_2026)/wfe_A_2026 -> 0.085913329 | E10: =(ms_A_2027+mm_A_2027)/wfe_A_2027 -> 0.10007721 | F10: =(ms_A_2028+mm_A_2028)/wfe_A_2028 -> 0.10315008 | G10: =(ms_A_2029+mm_A_2029)/wfe_A_2029 -> 0.11113152 | H10: 公司說法：測試對 WFE 比 2025 約 7%、2026 約 8%，長期 7–9%（口徑為 ATE 市場，含其他測試機；見 Recon）
A12: 情境 B
A13: SoC 測試機市場 | B13: US$B | C13: =mk_soc25 -> 6.9 | D13: =ms_B_2026 -> 11 | E13: =ms_B_2027 -> 15.414358 | F13: =ms_B_2028 -> 14.769523 | G13: =ms_B_2029 -> 17.076287
A14: 記憶體測試機市場 | B14: US$B | C14: =mk_mem25 -> 2.1 | D14: =mm_B_2026 -> 2.75 | E14: =mm_B_2027 -> 3.8800741 | F14: =mm_B_2028 -> 4.7378491 | G14: =mm_B_2029 -> 5.7899737
A15: Advantest SoC 市占（Advantest 模型，FY 口徑） | B15: % | C15: =as_A_2026 -> 0.66 | D15: =as_B_2026 -> 0.66 | E15: =as_B_2027 -> 0.66 | F15: =as_B_2028 -> 0.66 | G15: =as_B_2029 -> 0.66
A16: 泰瑞達 SoC 市占 | B16: % | C16: =a25_soc/(mk_soc25*1000) -> 0.27386957 | D16: =s_soc -> 0.29539273 | E16: =s_soc -> 0.29539273 | F16: =s_soc -> 0.29539273 | G16: =s_soc -> 0.29539273
A17: 其他廠 SoC 市占（1 − Advantest − 泰瑞達） | B17: % | C17: =1-C15-C16 -> 0.066130435 | D17: =1-D15-D16 -> 0.044607273 | E17: =1-E15-E16 -> 0.044607273 | F17: =1-F15-F16 -> 0.044607273 | G17: =1-G15-G16 -> 0.044607273 | H17: CY2025 用 Advantest 自估 66% 對照；三情境 CY2026 起其他廠份額相同（互補設計）
A18: SoC＋記憶體測試機市場 ÷ 晶圓前段設備（WFE） | B18: % | C18: =(mk_soc25+mk_mem25)/wfe_B_2025 -> 0.076990966 | D18: =(ms_B_2026+mm_B_2026)/wfe_B_2026 -> 0.085913329 | E18: =(ms_B_2027+mm_B_2027)/wfe_B_2027 -> 0.10007721 | F18: =(ms_B_2028+mm_B_2028)/wfe_B_2028 -> 0.10118169 | G18: =(ms_B_2029+mm_B_2029)/wfe_B_2029 -> 0.12484603 | H18: 公司說法：測試對 WFE 比 2025 約 7%、2026 約 8%，長期 7–9%（口徑為 ATE 市場，含其他測試機；見 Recon）
A20: 情境 C
A21: SoC 測試機市場 | B21: US$B | C21: =mk_soc25 -> 6.9 | D21: =ms_C_2026 -> 11 | E21: =ms_C_2027 -> 15.414358 | F21: =ms_C_2028 -> 12.239862 | G21: =ms_C_2029 -> 13.476472
A22: 記憶體測試機市場 | B22: US$B | C22: =mk_mem25 -> 2.1 | D22: =mm_C_2026 -> 2.75 | E22: =mm_C_2027 -> 3.8800741 | F22: =mm_C_2028 -> 3.640828 | G22: =mm_C_2029 -> 4.3133587
A23: Advantest SoC 市占（Advantest 模型，FY 口徑） | B23: % | C23: =as_A_2026 -> 0.66 | D23: =as_C_2026 -> 0.66 | E23: =as_C_2027 -> 0.66 | F23: =as_C_2028 -> 0.61 | G23: =as_C_2029 -> 0.56
A24: 泰瑞達 SoC 市占 | B24: % | C24: =a25_soc/(mk_soc25*1000) -> 0.27386957 | D24: =s_soc -> 0.29539273 | E24: =(s_soc+adv_sh26-as_C_2027) -> 0.29539273 | F24: =(s_soc+adv_sh26-as_C_2028) -> 0.34539273 | G24: =(s_soc+adv_sh26-as_C_2029) -> 0.39539273
A25: 其他廠 SoC 市占（1 − Advantest − 泰瑞達） | B25: % | C25: =1-C23-C24 -> 0.066130435 | D25: =1-D23-D24 -> 0.044607273 | E25: =1-E23-E24 -> 0.044607273 | F25: =1-F23-F24 -> 0.044607273 | G25: =1-G23-G24 -> 0.044607273 | H25: CY2025 用 Advantest 自估 66% 對照；三情境 CY2026 起其他廠份額相同（互補設計）
A26: SoC＋記憶體測試機市場 ÷ 晶圓前段設備（WFE） | B26: % | C26: =(mk_soc25+mk_mem25)/wfe_C_2025 -> 0.076990966 | D26: =(ms_C_2026+mm_C_2026)/wfe_C_2026 -> 0.085913329 | E26: =(ms_C_2027+mm_C_2027)/wfe_C_2027 -> 0.10007721 | F26: =(ms_C_2028+mm_C_2028)/wfe_C_2028 -> 0.10296333 | G26: =(ms_C_2029+mm_C_2029)/wfe_C_2029 -> 0.11534134 | H26: 公司說法：測試對 WFE 比 2025 約 7%、2026 約 8%，長期 7–9%（口徑為 ATE 市場，含其他測試機；見 Recon）

Sheet PL
A1: PL — 泰瑞達損益（US$M；FY2025 為實績，FY2026 為錨點（上半年實績＋下半年指引），FY2027–FY2029 為模型）。三情境各一個完整推導區塊（見下方），本頁頂端為摘要
A3: 情境／項目 | B3: 單位 | C3: FY2025A | D3: FY2026 | E3: FY2027 | F3: FY2028 | G3: FY2029 | H3: 說明
A4: 情境 A
A5: 營收 | B5: US$M | C5: =C61 -> 3190.1 | D5: =D61 -> 5111.6 | E5: =E61 -> 6923.6722 | F5: =F61 -> 7961.4985 | G5: =G61 -> 9019.6854
A6: SoC 測試機 | B6: US$M | C6: =C49 -> 1889.7 | D6: =D49 -> 3249.32 | E6: =E49 -> 4553.2893 | F6: =F49 -> 5110.053 | G6: =G49 -> 5682.2266
A7: 記憶體測試機 | B7: US$M | C7: =C51 -> 504.9 | D7: =D51 -> 871.08 | E7: =E51 -> 1229.0382 | F7: =F51 -> 1598.377 | G7: =G51 -> 1964.5983
A8: 機器人（不隨 AI 情境） | B8: US$M | C8: =C58 -> 308.3 | D8: =D58 -> 401.52 | E8: =E58 -> 441.672 | F8: =F58 -> 485.8392 | G8: =G58 -> 534.42312
A9: 毛利率（參考） | B9: % | C9: =C71 -> 0.58222571 | D9: =D71 -> 0.59436565 | E9: =E71 -> 0.60117502 | F9: =F71 -> 0.59627838 | G9: =G71 -> 0.5926001
A10: 稅前利益 | B10: US$M | C10: =C63 -> 653.2 | D10: =D63 -> 1629.9307 | E10: =E63 -> 2497.4925 | F10: =F63 -> 2987.6884 | G10: =G63 -> 3482.2672
A11: 稅前利益率 | B11: % | C11: =C64 -> 0.20475847 | D11: =D64 -> 0.31886899 | E11: =E64 -> 0.3607179 | F11: =F64 -> 0.37526709 | G11: =G64 -> 0.38607413
A12: 淨利 | B12: US$M | C12: =C67 -> 554 | D12: =D67 -> 1385.276 | E12: =E67 -> 2130.2545 | F12: =F67 -> 2550.9615 | G12: =G67 -> 2975.43
A13: EPS | B13: US$ | C13: =C69 -> 3.47 | D13: =D69 -> 8.7842486 | E13: =E69 -> 13.644719 | F13: =F69 -> 16.504479 | G13: =G69 -> 19.445202
A15: 情境 B
A16: 營收 | B16: US$M | C16: =C91 -> 3190.1 | D16: =D91 -> 5111.6 | E16: =E91 -> 6911.8471 | F16: =F91 -> 7046.4733 | G16: =G91 -> 8172.4539
A17: SoC 測試機 | B17: US$M | C17: =C79 -> 1889.7 | D17: =D79 -> 3249.32 | E17: =E79 -> 4553.2893 | F17: =F79 -> 4362.8097 | G17: =G79 -> 5044.211
A18: 記憶體測試機 | B18: US$M | C18: =C81 -> 504.9 | D18: =D81 -> 871.08 | E18: =E81 -> 1229.0382 | F18: =F81 -> 1500.7439 | G18: =G81 -> 1834.011
A19: 機器人（不隨 AI 情境） | B19: US$M | C19: =C88 -> 308.3 | D19: =D88 -> 401.52 | E19: =E88 -> 441.672 | F19: =F88 -> 485.8392 | G19: =G88 -> 534.42312
A20: 毛利率（參考） | B20: % | C20: =C101 -> 0.58222571 | D20: =D101 -> 0.59436565 | E20: =E101 -> 0.60152382 | F20: =F101 -> 0.58924189 | G20: =G101 -> 0.58864454
A21: 稅前利益 | B21: US$M | C21: =C93 -> 653.2 | D21: =D93 -> 1629.9307 | E21: =E93 -> 2491.7851 | F21: =F93 -> 2546.0458 | G21: =G93 -> 3073.3456
A22: 稅前利益率 | B22: % | C22: =C94 -> 0.20475847 | D22: =D94 -> 0.31886899 | E22: =E94 -> 0.36050928 | F22: =F94 -> 0.36132199 | G22: =G94 -> 0.37606154
A23: 淨利 | B23: US$M | C23: =C97 -> 554 | D23: =D97 -> 1385.276 | E23: =E97 -> 2125.3561 | F23: =F97 -> 2171.9249 | G23: =G97 -> 2624.4761
A24: EPS | B24: US$ | C24: =C99 -> 3.47 | D24: =D99 -> 8.7842486 | E24: =E99 -> 13.613344 | F24: =F99 -> 14.052148 | G24: =G99 -> 17.151628
A26: 情境 C
A27: 營收 | B27: US$M | C27: =C121 -> 3190.1 | D27: =D121 -> 5111.6 | E27: =E121 -> 6900.022 | F27: =F121 -> 6494.2954 | G27: =G121 -> 7887.0281
A28: SoC 測試機 | B28: US$M | C28: =C109 -> 1889.7 | D28: =D109 -> 3249.32 | E28: =E109 -> 4553.2893 | F28: =F109 -> 4227.5594 | G28: =G109 -> 5328.4989
A29: 記憶體測試機 | B29: US$M | C29: =C111 -> 504.9 | D29: =D111 -> 871.08 | E29: =E111 -> 1229.0382 | F29: =F111 -> 1153.2554 | G29: =G111 -> 1366.2838
A30: 機器人（不隨 AI 情境） | B30: US$M | C30: =C118 -> 308.3 | D30: =D118 -> 401.52 | E30: =E118 -> 441.672 | F30: =F118 -> 485.8392 | G30: =G118 -> 534.42312
A31: 毛利率（參考） | B31: % | C31: =C131 -> 0.58222571 | D31: =D131 -> 0.59436565 | E31: =E131 -> 0.60187382 | F31: =F131 -> 0.58910549 | G31: =G131 -> 0.58674344
A32: 稅前利益 | B32: US$M | C32: =C123 -> 653.2 | D32: =D123 -> 1629.9307 | E32: =E123 -> 2486.0776 | F32: =F123 -> 2219.4491 | G32: =G123 -> 2788.531
A33: 稅前利益率 | B33: % | C33: =C124 -> 0.20475847 | D33: =D124 -> 0.31886899 | E33: =E124 -> 0.36029995 | F33: =F124 -> 0.34175364 | G33: =G124 -> 0.35355915
A34: 淨利 | B34: US$M | C34: =C127 -> 554 | D34: =D127 -> 1385.276 | E34: =E127 -> 2120.4577 | F34: =F127 -> 1891.6258 | G34: =G127 -> 2380.0361
A35: EPS | B35: US$ | C35: =C129 -> 3.47 | D35: =D129 -> 8.7842486 | E35: =E129 -> 13.581969 | F35: =F129 -> 12.238639 | G35: =G129 -> 15.554149
A37: 核對：FY2026 EPS − 錨點（應為 0） | C37: =ABS(D13-f26_eps)+ABS(D35-f26_eps) -> 0
A44: 情境 A（順利）：加速器顆數續增；市占維持
A45: 項目 | B45: 單位 | C45: FY2025A | D45: FY2026（錨點） | E45: FY2027 | F45: FY2028 | G45: FY2029 | H45: 說明
A46: SoC 測試機市場 CY（Advantest 模型） | B46: US$B | C46: =mk_soc25 -> 6.9 | D46: =ms_A_2026 -> 11 | E46: =ms_A_2027*m_soc -> 15.414358 | F46: =ms_A_2028*m_soc -> 17.299184 | G46: =ms_A_2029*m_soc -> 19.236176
A47: 記憶體測試機市場 CY（Advantest 模型） | B47: US$B | C47: =mk_mem25 -> 2.1 | D47: =mm_A_2026 -> 2.75 | E47: =mm_A_2027 -> 3.8800741 | F47: =mm_A_2028 -> 5.0460769 | G47: =mm_A_2029 -> 6.2022378
A48: 泰瑞達 SoC 市占 | B48: % | C48: =a25_soc/(C46*1000) -> 0.27386957 | D48: =f26_soc/(D46*1000) -> 0.29539273 | E48: =s_soc -> 0.29539273 | F48: =s_soc -> 0.29539273 | G48: =s_soc -> 0.29539273 | H48: FY2025、FY2026＝實績／錨點隱含；之後維持
A49: SoC 測試機營收 | B49: US$M | C49: =a25_soc -> 1889.7 | D49: =f26_soc -> 3249.32 | E49: =E46*1000*E48 -> 4553.2893 | F49: =F46*1000*F48 -> 5110.053 | G49: =G46*1000*G48 -> 5682.2266 | H49: 市場 × 市占
A50: 泰瑞達記憶體測試機市占 | B50: % | C50: =a25_mem/(C47*1000) -> 0.24042857 | D50: =f26_mem/(D47*1000) -> 0.31675636 | E50: =s_mem -> 0.31675636 | F50: =s_mem -> 0.31675636 | G50: =s_mem -> 0.31675636
A51: 記憶體測試機營收 | B51: US$M | C51: =a25_mem -> 504.9 | D51: =f26_mem -> 871.08 | E51: =E47*1000*E50 -> 1229.0382 | F51: =F47*1000*F50 -> 1598.377 | G51: =G47*1000*G50 -> 1964.5983
A52: IST 營收（隨 SoC 市場） | B52: US$M | C52: =a25_ist -> 129.2 | D52: =f26_ist -> 195.51 | E52: =$D52*E46/$D46 -> 273.9692 | F52: =$D52*F46/$D46 -> 307.4694 | G52: =$D52*G46/$D46 -> 341.8968 | H52: FY2026 × SoC 市場相對 CY2026
A53: 半導體測試營收 | B53: US$M | C53: =C49+C51+C52 -> 2523.8 | D53: =D49+D51+D52 -> 4315.91 | E53: =E49+E51+E52 -> 6056.2966 | F53: =F49+F51+F52 -> 7015.8994 | G53: =G49+G51+G52 -> 7988.7216
A54: Product Test 營收 | B54: US$M | C54: =a25_pt -> 358 | D54: =f26_pt -> 394.17 | E54: =D54*(1+g_pt_A) -> 425.7036 | F54: =E54*(1+g_pt_A) -> 459.75989 | G54: =F54*(1+g_pt_A) -> 496.54068
A55: 測試事業營收（半導體測試＋Product Test） | B55: US$M | C55: =C53+C54 -> 2881.8 | D55: =D53+D54 -> 4710.08 | E55: =E53+E54 -> 6482.0002 | F55: =F53+F54 -> 7475.6593 | G55: =G53+G54 -> 8485.2623
A56: 測試事業稅前利益 | B56: US$M | C56: =a25_ttest -> 761.4 | D56: =f26_ttest -> 1643.8307 | E56: =t_inc*E55-t_fix+0*E55 -> 2499.0591 | F56: =t_inc*F55-t_fix+0*F55 -> 2978.6548 | G56: =t_inc*G55-t_fix+0*G55 -> 3465.946 | H56: 增量利益率 × 營收 − 固定成本（兩點推導）；C 情境另加價格競爭調整
A57: 測試事業稅前利益率 | B57: % | C57: =C56/C55 -> 0.26420987 | D57: =D56/D55 -> 0.34900272 | E57: =E56/E55 -> 0.38553826 | F57: =F56/F55 -> 0.39844711 | G57: =G56/G55 -> 0.40846657
A58: 機器人營收（不隨 AI 情境） | B58: US$M | C58: =a25_rob -> 308.3 | D58: =f26_rob -> 401.52 | E58: =D58*(1+g_rob) -> 441.672 | F58: =E58*(1+g_rob) -> 485.8392 | G58: =F58*(1+g_rob) -> 534.42312
A59: 機器人稅前利益 | B59: US$M | C59: =a25_trob -> -99.4 | D59: =f26_trob -> -3.5 | E59: =E58*rm_2027 -> 8.83344 | F59: =F58*rm_2028 -> 19.433568 | G59: =G58*rm_2029 -> 26.721156
A60: 公司與沖銷 | B60: US$M | C60: =a25_corp -> -8.8 | D60: =f26_corp -> -10.4 | E60: =corp -> -10.4 | F60: =corp -> -10.4 | G60: =corp -> -10.4
A61: 營收 | B61: US$M | C61: =C55+C58 -> 3190.1 | D61: =D55+D58 -> 5111.6 | E61: =E55+E58 -> 6923.6722 | F61: =F55+F58 -> 7961.4985 | G61: =G55+G58 -> 9019.6854
A62: 檢查：分部合計 − 合併營收（FY2025 實績、FY2026 錨點；四捨五入到百萬美元） | B62: US$M | C62: =ROUND(C53+C54+C58-a25_rev,0) -> 0 | D62: =ROUND(D53+D54+D58-f26_rev,0) -> 0 | H62: FY2025 分部合計 3,190.1 vs 公司合併營收 3,190.0：季度分部數字四捨五入差 0.1
A63: 稅前利益 | B63: US$M | C63: =C56+C59+C60 -> 653.2 | D63: =D56+D59+D60 -> 1629.9307 | E63: =E56+E59+E60 -> 2497.4925 | F63: =F56+F59+F60 -> 2987.6884 | G63: =G56+G59+G60 -> 3482.2672
A64: 稅前利益率 | B64: % | C64: =C63/C61 -> 0.20475847 | D64: =D63/D61 -> 0.31886899 | E64: =E63/E61 -> 0.3607179 | F64: =F63/F61 -> 0.37526709 | G64: =G63/G61 -> 0.38607413
A65: 所得稅 | B65: US$M | C65: =a25_tax -> 79.3 | D65: =f26_tax -> 231.05474 | E65: =E63*etr -> 354.03804 | F65: =F63*etr -> 423.52693 | G65: =G63*etr -> 493.63713
A66: 權益法投資損益（Technoprobe） | B66: US$M | C66: =a25_aff -> -19.9 | D66: =f26_aff -> -13.2 | E66: =aff -> -13.2 | F66: =aff -> -13.2 | G66: =aff -> -13.2
A67: 淨利 | B67: US$M | C67: =a25_ni -> 554 | D67: =f26_ni -> 1385.276 | E67: =E63-E65+E66 -> 2130.2545 | F67: =F63-F65+F66 -> 2550.9615 | G67: =G63-G65+G66 -> 2975.43 | H67: FY2026＝錨點（上半年實績＋下半年指引）
A68: 稀釋股數 | B68: 百萬股 | C68: =a25_dsh -> 159.7 | D68: =sh26 -> 157.7 | E68: =sh26*(1-bb)^1 -> 156.123 | F68: =sh26*(1-bb)^2 -> 154.56177 | G68: =sh26*(1-bb)^3 -> 153.01615
A69: EPS（GAAP 稀釋） | B69: US$ | C69: =a25_eps -> 3.47 | D69: =D67/D68 -> 8.7842486 | E69: =E67/E68 -> 13.644719 | F69: =F67/F68 -> 16.504479 | G69: =G67/G68 -> 19.445202
A70: SoC 占營收 | B70: % | C70: =C49/C61 -> 0.59236388 | D70: =D49/D61 -> 0.63567572 | E70: =E49/E61 -> 0.65764079 | F70: =F49/F61 -> 0.64184563 | G70: =G49/G61 -> 0.62998057
A71: 毛利率（參考；不進 EPS） | B71: % | C71: =a25_gp/a25_rev -> 0.58222571 | D71: =f26_gm -> 0.59436565 | E71: =f26_gm+(Q!J13-a25_gp/a25_rev)/(Q!J4/Q!J10-a25_soc/a25_rev)*(E70-D70) -> 0.60117502 | F71: =f26_gm+(Q!J13-a25_gp/a25_rev)/(Q!J4/Q!J10-a25_soc/a25_rev)*(F70-D70) -> 0.59627838 | G71: =f26_gm+(Q!J13-a25_gp/a25_rev)/(Q!J4/Q!J10-a25_soc/a25_rev)*(G70-D70) -> 0.5926001 | H71: FY2026＋斜率 ×（SoC 占營收 − FY2026）；斜率由 FY2025 與上半年 FY2026 兩點推得；EPS 由事業別稅前利益推導，本列只供參考
A74: 情境 B（平平）：2028 顆數 ×0.8、2029 ×0.85（Advantest 模型的 B 市場）
A75: 項目 | B75: 單位 | C75: FY2025A | D75: FY2026（錨點） | E75: FY2027 | F75: FY2028 | G75: FY2029 | H75: 說明
A76: SoC 測試機市場 CY（Advantest 模型） | B76: US$B | C76: =mk_soc25 -> 6.9 | D76: =ms_B_2026 -> 11 | E76: =ms_B_2027*m_soc -> 15.414358 | F76: =ms_B_2028*m_soc -> 14.769523 | G76: =ms_B_2029*m_soc -> 17.076287
A77: 記憶體測試機市場 CY（Advantest 模型） | B77: US$B | C77: =mk_mem25 -> 2.1 | D77: =mm_B_2026 -> 2.75 | E77: =mm_B_2027 -> 3.8800741 | F77: =mm_B_2028 -> 4.7378491 | G77: =mm_B_2029 -> 5.7899737
A78: 泰瑞達 SoC 市占 | B78: % | C78: =a25_soc/(C76*1000) -> 0.27386957 | D78: =f26_soc/(D76*1000) -> 0.29539273 | E78: =s_soc -> 0.29539273 | F78: =s_soc -> 0.29539273 | G78: =s_soc -> 0.29539273 | H78: FY2025、FY2026＝實績／錨點隱含；之後維持
A79: SoC 測試機營收 | B79: US$M | C79: =a25_soc -> 1889.7 | D79: =f26_soc -> 3249.32 | E79: =E76*1000*E78 -> 4553.2893 | F79: =F76*1000*F78 -> 4362.8097 | G79: =G76*1000*G78 -> 5044.211 | H79: 市場 × 市占
A80: 泰瑞達記憶體測試機市占 | B80: % | C80: =a25_mem/(C77*1000) -> 0.24042857 | D80: =f26_mem/(D77*1000) -> 0.31675636 | E80: =s_mem -> 0.31675636 | F80: =s_mem -> 0.31675636 | G80: =s_mem -> 0.31675636
A81: 記憶體測試機營收 | B81: US$M | C81: =a25_mem -> 504.9 | D81: =f26_mem -> 871.08 | E81: =E77*1000*E80 -> 1229.0382 | F81: =F77*1000*F80 -> 1500.7439 | G81: =G77*1000*G80 -> 1834.011
A82: IST 營收（隨 SoC 市場） | B82: US$M | C82: =a25_ist -> 129.2 | D82: =f26_ist -> 195.51 | E82: =$D82*E76/$D76 -> 273.9692 | F82: =$D82*F76/$D76 -> 262.50813 | G82: =$D82*G76/$D76 -> 303.50772 | H82: FY2026 × SoC 市場相對 CY2026
A83: 半導體測試營收 | B83: US$M | C83: =C79+C81+C82 -> 2523.8 | D83: =D79+D81+D82 -> 4315.91 | E83: =E79+E81+E82 -> 6056.2966 | F83: =F79+F81+F82 -> 6126.0616 | G83: =G79+G81+G82 -> 7181.7297
A84: Product Test 營收 | B84: US$M | C84: =a25_pt -> 358 | D84: =f26_pt -> 394.17 | E84: =D84*(1+g_pt_B) -> 413.8785 | F84: =E84*(1+g_pt_B) -> 434.57243 | G84: =F84*(1+g_pt_B) -> 456.30105
A85: 測試事業營收（半導體測試＋Product Test） | B85: US$M | C85: =C83+C84 -> 2881.8 | D85: =D83+D84 -> 4710.08 | E85: =E83+E84 -> 6470.1751 | F85: =F83+F84 -> 6560.6341 | G85: =G83+G84 -> 7638.0308
A86: 測試事業稅前利益 | B86: US$M | C86: =a25_ttest -> 761.4 | D86: =f26_ttest -> 1643.8307 | E86: =t_inc*E85-t_fix+0*E85 -> 2493.3516 | F86: =t_inc*F85-t_fix+0*F85 -> 2537.0122 | G86: =t_inc*G85-t_fix+0*G85 -> 3057.0244 | H86: 增量利益率 × 營收 − 固定成本（兩點推導）；C 情境另加價格競爭調整
A87: 測試事業稅前利益率 | B87: % | C87: =C86/C85 -> 0.26420987 | D87: =D86/D85 -> 0.34900272 | E87: =E86/E85 -> 0.38536076 | F87: =F86/F85 -> 0.38670229 | G87: =G86/G85 -> 0.40023725
A88: 機器人營收（不隨 AI 情境） | B88: US$M | C88: =a25_rob -> 308.3 | D88: =f26_rob -> 401.52 | E88: =D88*(1+g_rob) -> 441.672 | F88: =E88*(1+g_rob) -> 485.8392 | G88: =F88*(1+g_rob) -> 534.42312
A89: 機器人稅前利益 | B89: US$M | C89: =a25_trob -> -99.4 | D89: =f26_trob -> -3.5 | E89: =E88*rm_2027 -> 8.83344 | F89: =F88*rm_2028 -> 19.433568 | G89: =G88*rm_2029 -> 26.721156
A90: 公司與沖銷 | B90: US$M | C90: =a25_corp -> -8.8 | D90: =f26_corp -> -10.4 | E90: =corp -> -10.4 | F90: =corp -> -10.4 | G90: =corp -> -10.4
A91: 營收 | B91: US$M | C91: =C85+C88 -> 3190.1 | D91: =D85+D88 -> 5111.6 | E91: =E85+E88 -> 6911.8471 | F91: =F85+F88 -> 7046.4733 | G91: =G85+G88 -> 8172.4539
A92: 檢查：分部合計 − 合併營收（FY2025 實績、FY2026 錨點；四捨五入到百萬美元） | B92: US$M | C92: =ROUND(C83+C84+C88-a25_rev,0) -> 0 | D92: =ROUND(D83+D84+D88-f26_rev,0) -> 0 | H92: FY2025 分部合計 3,190.1 vs 公司合併營收 3,190.0：季度分部數字四捨五入差 0.1
A93: 稅前利益 | B93: US$M | C93: =C86+C89+C90 -> 653.2 | D93: =D86+D89+D90 -> 1629.9307 | E93: =E86+E89+E90 -> 2491.7851 | F93: =F86+F89+F90 -> 2546.0458 | G93: =G86+G89+G90 -> 3073.3456
A94: 稅前利益率 | B94: % | C94: =C93/C91 -> 0.20475847 | D94: =D93/D91 -> 0.31886899 | E94: =E93/E91 -> 0.36050928 | F94: =F93/F91 -> 0.36132199 | G94: =G93/G91 -> 0.37606154
A95: 所得稅 | B95: US$M | C95: =a25_tax -> 79.3 | D95: =f26_tax -> 231.05474 | E95: =E93*etr -> 353.22896 | F95: =F93*etr -> 360.92082 | G95: =G93*etr -> 435.66947
A96: 權益法投資損益（Technoprobe） | B96: US$M | C96: =a25_aff -> -19.9 | D96: =f26_aff -> -13.2 | E96: =aff -> -13.2 | F96: =aff -> -13.2 | G96: =aff -> -13.2
A97: 淨利 | B97: US$M | C97: =a25_ni -> 554 | D97: =f26_ni -> 1385.276 | E97: =E93-E95+E96 -> 2125.3561 | F97: =F93-F95+F96 -> 2171.9249 | G97: =G93-G95+G96 -> 2624.4761 | H97: FY2026＝錨點（上半年實績＋下半年指引）
A98: 稀釋股數 | B98: 百萬股 | C98: =a25_dsh -> 159.7 | D98: =sh26 -> 157.7 | E98: =sh26*(1-bb)^1 -> 156.123 | F98: =sh26*(1-bb)^2 -> 154.56177 | G98: =sh26*(1-bb)^3 -> 153.01615
A99: EPS（GAAP 稀釋） | B99: US$ | C99: =a25_eps -> 3.47 | D99: =D97/D98 -> 8.7842486 | E99: =E97/E98 -> 13.613344 | F99: =F97/F98 -> 14.052148 | G99: =G97/G98 -> 17.151628
A100: SoC 占營收 | B100: % | C100: =C79/C91 -> 0.59236388 | D100: =D79/D91 -> 0.63567572 | E100: =E79/E91 -> 0.65876591 | F100: =F79/F91 -> 0.61914798 | G100: =G79/G91 -> 0.6172211
A101: 毛利率（參考；不進 EPS） | B101: % | C101: =a25_gp/a25_rev -> 0.58222571 | D101: =f26_gm -> 0.59436565 | E101: =f26_gm+(Q!J13-a25_gp/a25_rev)/(Q!J4/Q!J10-a25_soc/a25_rev)*(E100-D100) -> 0.60152382 | F101: =f26_gm+(Q!J13-a25_gp/a25_rev)/(Q!J4/Q!J10-a25_soc/a25_rev)*(F100-D100) -> 0.58924189 | G101: =f26_gm+(Q!J13-a25_gp/a25_rev)/(Q!J4/Q!J10-a25_soc/a25_rev)*(G100-D100) -> 0.58864454 | H101: FY2026＋斜率 ×（SoC 占營收 − FY2026）；斜率由 FY2025 與上半年 FY2026 兩點推得；EPS 由事業別稅前利益推導，本列只供參考
A104: 情境 C（不如預期）：2028–29 顆數 ×0.6；泰瑞達自 Advantest 搶回份額但價格壓力
A105: 項目 | B105: 單位 | C105: FY2025A | D105: FY2026（錨點） | E105: FY2027 | F105: FY2028 | G105: FY2029 | H105: 說明
A106: SoC 測試機市場 CY（Advantest 模型） | B106: US$B | C106: =mk_soc25 -> 6.9 | D106: =ms_C_2026 -> 11 | E106: =ms_C_2027*m_soc -> 15.414358 | F106: =ms_C_2028*m_soc -> 12.239862 | G106: =ms_C_2029*m_soc -> 13.476472
A107: 記憶體測試機市場 CY（Advantest 模型） | B107: US$B | C107: =mk_mem25 -> 2.1 | D107: =mm_C_2026 -> 2.75 | E107: =mm_C_2027 -> 3.8800741 | F107: =mm_C_2028 -> 3.640828 | G107: =mm_C_2029 -> 4.3133587
A108: 泰瑞達 SoC 市占 | B108: % | C108: =a25_soc/(C106*1000) -> 0.27386957 | D108: =f26_soc/(D106*1000) -> 0.29539273 | E108: =(s_soc+adv_sh26-as_C_2027) -> 0.29539273 | F108: =(s_soc+adv_sh26-as_C_2028) -> 0.34539273 | G108: =(s_soc+adv_sh26-as_C_2029) -> 0.39539273 | H108: FY2025、FY2026＝實績／錨點隱含；C 情境與 Advantest 互補
A109: SoC 測試機營收 | B109: US$M | C109: =a25_soc -> 1889.7 | D109: =f26_soc -> 3249.32 | E109: =E106*1000*E108 -> 4553.2893 | F109: =F106*1000*F108 -> 4227.5594 | G109: =G106*1000*G108 -> 5328.4989 | H109: 市場 × 市占
A110: 泰瑞達記憶體測試機市占 | B110: % | C110: =a25_mem/(C107*1000) -> 0.24042857 | D110: =f26_mem/(D107*1000) -> 0.31675636 | E110: =s_mem -> 0.31675636 | F110: =s_mem -> 0.31675636 | G110: =s_mem -> 0.31675636
A111: 記憶體測試機營收 | B111: US$M | C111: =a25_mem -> 504.9 | D111: =f26_mem -> 871.08 | E111: =E107*1000*E110 -> 1229.0382 | F111: =F107*1000*F110 -> 1153.2554 | G111: =G107*1000*G110 -> 1366.2838
A112: IST 營收（隨 SoC 市場） | B112: US$M | C112: =a25_ist -> 129.2 | D112: =f26_ist -> 195.51 | E112: =$D112*E106/$D106 -> 273.9692 | F112: =$D112*F106/$D106 -> 217.54686 | G112: =$D112*G106/$D106 -> 239.52591 | H112: FY2026 × SoC 市場相對 CY2026
A113: 半導體測試營收 | B113: US$M | C113: =C109+C111+C112 -> 2523.8 | D113: =D109+D111+D112 -> 4315.91 | E113: =E109+E111+E112 -> 6056.2966 | F113: =F109+F111+F112 -> 5598.3617 | G113: =G109+G111+G112 -> 6934.3087
A114: Product Test 營收 | B114: US$M | C114: =a25_pt -> 358 | D114: =f26_pt -> 394.17 | E114: =D114*(1+g_pt_C) -> 402.0534 | F114: =E114*(1+g_pt_C) -> 410.09447 | G114: =F114*(1+g_pt_C) -> 418.29636
...

Sheet Val
A1: Val — 估值。目標價＝DCF 與 Comparable 加權（第 0 節，放在本頁後段）；規則值（十年年底 P/E 依循環位置取分位：見頂年 25 分位、中段中位數、谷底 75 分位）保留為參考。循環位置依設備股共用規則（第 4 節）
A2: P/E 定義（自算）：年底收盤價（macrotrends，股利調整後）÷ 當年度 GAAP 稀釋 EPS（會計年度＝日曆年）；FY2016 為虧損（EPS −0.21），P/E 無意義，不納入分位
A3: 目標價（DCF 與 Comparable 加權）：見本頁第 91 列起「0. 目標價」
A4: 1. 公司公布 EPS（GAAP 稀釋，美元）— 兩個來源
A5: 會計年度 | B5: 來源1：SEC XBRL（10-K） | C5: 來源2：macrotrends | D5: 兩者差距 | E5: 淨利 US$M（10-K） | F5: 營收 US$M（10-K） | G5: 股東權益 US$M（年底） | H5: 說明
A6: 2015 | B6: 0.97 | C6: 0.97 | D6: =IF(C6="","",B6-C6) -> 0 | E6: 206.5 | F6: 1639.6 | G6: 1965.8
A7: 2016 | B7: -0.21 | C7: -0.21 | D7: =IF(C7="","",B7-C7) -> 0 | E7: -43.4 | F7: 1753.3 | G7: 1828.7 | H7: 虧損年（Wireless Test 商譽減損）
A8: 2017 | B8: 1.28 | C8: 1.28 | D8: =IF(C8="","",B8-C8) -> 0 | E8: 257.7 | F8: 2136.6 | G8: 1953.6
A9: 2018 | B9: 2.35 | C9: 2.35 | D9: =IF(C9="","",B9-C9) -> 0 | E9: 451.8 | F9: 2100.8 | G9: 1522.4
A10: 2019 | B10: 2.6 | C10: 2.6 | D10: =IF(C10="","",B10-C10) -> 0 | E10: 467.5 | F10: 2295 | G10: 1480.2
A11: 2020 | B11: 4.28 | C11: 4.28 | D11: =IF(C11="","",B11-C11) -> 0 | E11: 784.1 | F11: 3121.5 | G11: 2207
A12: 2021 | B12: 5.53 | C12: 5.53 | D12: =IF(C12="","",B12-C12) -> 0 | E12: 1014.6 | F12: 3702.9 | G12: 2562.4
A13: 2022 | B13: 4.22 | C13: 4.22 | D13: =IF(C13="","",B13-C13) -> 0 | E13: 715.5 | F13: 3155 | G13: 2451.3
A14: 2023 | B14: 2.73 | C14: 2.73 | D14: =IF(C14="","",B14-C14) -> 0 | E14: 448.8 | F14: 2676.3 | G14: 2525.9
A15: 2024 | B15: 3.32 | C15: 3.32 | D15: =IF(C15="","",B15-C15) -> 0 | E15: 542.4 | F15: 2819.9 | G15: 2819.3
A16: 2025 | B16: 3.47 | D16: =IF(C16="","",B16-C16) | E16: 554 | F16: 3190 | G16: 2795.8 | H16: macrotrends 年表只到 2024；FY2025 第二來源：公司 4Q25 新聞稿 3.47（同一公司來源）
A17: 全部年度用 GAAP 稀釋 EPS。淨利、營收、股東權益取自 SEC XBRL（10-K），用於十年平均淨利率與近三年 ROE
A18: 2. 10 年 P/E（年底）
A19: 年底 | B19: 收盤價 US$（股利調整） | C19: 當年 EPS | E19: P/E 當年（自算） | G19: companiesmarketcap P/E | H19: 自算 − cmc | J19: 標記 | K19: 來源／說明
A20: 2016-12 | B20: 24.1472 | C20: =B7 -> -0.21 | E20: =IF(C20<=0,"",B20/C20) | G20: -115 | H20: =IF(E20="","",E20-G20) | J20: Verified／Derived | K20: EPS 為負，P/E 不納入分位（cmc 列 −115）
A21: 2017-12 | B21: 40.1225 | C21: =B8 -> 1.28 | E21: =IF(C21<=0,"",B21/C21) -> 31.345703 | G21: 31.2 | H21: =IF(E21="","",E21-G21) -> 0.14570313 | J21: Verified／Derived | K21: 收盤價：macrotrends 年表（年底收盤，股利調整後；泰瑞達 2016 年後無分割）
A22: 2018-12 | B22: 30.3431 | C22: =B9 -> 2.35 | E22: =IF(C22<=0,"",B22/C22) -> 12.911957 | G22: 12.5 | H22: =IF(E22="","",E22-G22) -> 0.41195745 | J22: Verified／Derived | K22: 收盤價：macrotrends 年表（年底收盤，股利調整後；泰瑞達 2016 年後無分割）
A23: 2019-12 | B23: 66.4325 | C23: =B10 -> 2.6 | E23: =IF(C23<=0,"",B23/C23) -> 25.550962 | G23: 23.6 | H23: =IF(E23="","",E23-G23) -> 1.9509615 | J23: Verified／Derived | K23: 收盤價：macrotrends 年表（年底收盤，股利調整後；泰瑞達 2016 年後無分割）
A24: 2020-12 | B24: 117.399 | C24: =B11 -> 4.28 | E24: =IF(C24<=0,"",B24/C24) -> 27.429673 | G24: 24.9 | H24: =IF(E24="","",E24-G24) -> 2.5296729 | J24: Verified／Derived | K24: 收盤價：macrotrends 年表（年底收盤，股利調整後；泰瑞達 2016 年後無分割）
A25: 2021-12 | B25: 160.61 | C25: =B12 -> 5.53 | E25: =IF(C25<=0,"",B25/C25) -> 29.0434 | G25: 26 | H25: =IF(E25="","",E25-G25) -> 3.0433996 | J25: Verified／Derived | K25: 收盤價：macrotrends 年表（年底收盤，股利調整後；泰瑞達 2016 年後無分割）
A26: 2022-12 | B26: 86.1704 | C26: =B13 -> 4.22 | E26: =IF(C26<=0,"",B26/C26) -> 20.419526 | G26: 19.1 | H26: =IF(E26="","",E26-G26) -> 1.3195261 | J26: Verified／Derived | K26: 收盤價：macrotrends 年表（年底收盤，股利調整後；泰瑞達 2016 年後無分割）
A27: 2023-12 | B27: 107.522 | C27: =B14 -> 2.73 | E27: =IF(C27<=0,"",B27/C27) -> 39.385348 | G27: 36.9 | H27: =IF(E27="","",E27-G27) -> 2.485348 | J27: Verified／Derived | K27: 收盤價：macrotrends 年表（年底收盤，股利調整後；泰瑞達 2016 年後無分割）
A28: 2024-12 | B28: 125.274 | C28: =B15 -> 3.32 | E28: =IF(C28<=0,"",B28/C28) -> 37.733133 | G28: 37 | H28: =IF(E28="","",E28-G28) -> 0.73313253 | J28: Verified／Derived | K28: 收盤價：macrotrends 年表（年底收盤，股利調整後；泰瑞達 2016 年後無分割）
A29: 2025-12 | B29: 193.406 | C29: =B16 -> 3.47 | E29: =IF(C29<=0,"",B29/C29) -> 55.736599 | G29: 55.5 | H29: =IF(E29="","",E29-G29) -> 0.23659942 | J29: Verified／Derived | K29: statmuse 2025-12-31 收盤 193.33（未調整，第二來源）；macrotrends 調整後 193.41
A31: 收盤價來源1：macrotrends（股利調整後年底收盤）；來源2：statmuse（僅 2025 年底 193.33）。股利調整使早年價格略低（每季 0.06–0.13 美元股利），P/E 偏低約 1–3%。companiesmarketcap（TTM 口徑）僅作對照，差距見 H 欄。
A33: 3. 分位（只含正 EPS 年度）
A34: 統計 | B34: P/E 當年（自算） | D34: cmc P/E（參考，正值） | E34: 用途
A35: 25 分位 | B35: =PERCENTILE(E20:E29,0.25) -> 25.550962 | D35: =PERCENTILE(G21:G29,0.25) -> 23.6 | E35: 見頂年
A36: 中位數 | B36: =PERCENTILE(E20:E29,0.5) -> 29.0434 | D36: =PERCENTILE(G21:G29,0.5) -> 26 | E36: 中段
A37: 75 分位 | B37: =PERCENTILE(E20:E29,0.75) -> 37.733133 | D37: =PERCENTILE(G21:G29,0.75) -> 36.9 | E37: 谷底
A38: 年數 | B38: =COUNT(E20:E29) -> 9 | D38: =COUNT(G21:G29) -> 9
A40: 4. 循環位置（設備股共用規則；見頂年度讀設備市場模型，不在本模型另訂）
A41: 循環位置（設備股共用規則）：各情境的見頂年度取自設備市場模型（markets/equipment 的 Mkt 頁「見頂年度」：A 2029、B 2028、C 2027）；會計年度 FY(t)＝日曆年 t：t 早於見頂年＝中段（中位數）、等於＝見頂（25 分位）、晚於＝谷底（75 分位）
A42: 情境 | B42: 設備市場見頂年度 | C42: FY2027 對照日曆年 | D42: 判定 | E42: 倍數 | F42: 規則
A43: A | B43: =pk_A -> 2029 | C43: 2027 | D43: =IF(C43<pk_A,"中段",IF(C43=pk_A,"見頂","谷底")) -> 中段 | E43: =IF(D43="見頂",pe_peak,IF(D43="谷底",pe_trough,pe_mid)) -> 29.0434 | F43: tools/cycle_position.py
A44: B | B44: =pk_B -> 2028 | C44: 2027 | D44: =IF(C44<pk_B,"中段",IF(C44=pk_B,"見頂","谷底")) -> 中段 | E44: =IF(D44="見頂",pe_peak,IF(D44="谷底",pe_trough,pe_mid)) -> 29.0434 | F44: tools/cycle_position.py
A45: C | B45: =pk_C -> 2027 | C45: 2027 | D45: =IF(C45<pk_C,"中段",IF(C45=pk_C,"見頂","谷底")) -> 見頂 | E45: =IF(D45="見頂",pe_peak,IF(D45="谷底",pe_trough,pe_mid)) -> 25.550962 | F45: tools/cycle_position.py
A47: 5. 隱含股價（美元）：規則值＝FY2027 EPS × 依循環位置的倍數；其餘倍數僅供參考
A48: 情境 | B48: EPS 年度 | C48: EPS | D48: 倍數類型 | E48: 倍數 | F48: 隱含股價 | G48: 相對現價 | H48: 備註
A49: A | B49: FY2027 | C49: =PL!E13 -> 13.644719 | D49: ="規則值："&D43 -> 規則值：中段 | E49: =E43 -> 29.0434 | F49: =C49*E49 -> 396.28903 | G49: =F49/px-1 -> 0.28311164
A50: A | B50: FY2027 | C50: =PL!E13 -> 13.644719 | D50: 參考：25 分位 | E50: =pe_peak -> 25.550962 | F50: =C50*E50 -> 348.63569 | G50: =F50/px-1 -> 0.12881882
A51: A | B51: FY2027 | C51: =PL!E13 -> 13.644719 | D51: 參考：中位數 | E51: =pe_mid -> 29.0434 | F51: =C51*E51 -> 396.28903 | G51: =F51/px-1 -> 0.28311164
A52: A | B52: FY2027 | C52: =PL!E13 -> 13.644719 | D52: 參考：75 分位 | E52: =pe_trough -> 37.733133 | F52: =C52*E52 -> 514.85799 | G52: =F52/px-1 -> 0.66701633
A53: A | B53: FY2028 | C53: =PL!F13 -> 16.504479 | D53: 參考：25 分位 | E53: =pe_peak -> 25.550962 | F53: =C53*E53 -> 421.70531 | G53: =F53/px-1 -> 0.36540491
A54: A | B54: FY2028 | C54: =PL!F13 -> 16.504479 | D54: 參考：中位數 | E54: =pe_mid -> 29.0434 | F54: =C54*E54 -> 479.34618 | G54: =F54/px-1 -> 0.55203554
A55: A | B55: FY2028 | C55: =PL!F13 -> 16.504479 | D55: 參考：75 分位 | E55: =pe_trough -> 37.733133 | F55: =C55*E55 -> 622.76569 | G55: =F55/px-1 -> 1.0164018
A56: B | B56: FY2027 | C56: =PL!E24 -> 13.613344 | D56: ="規則值："&D44 -> 規則值：中段 | E56: =E44 -> 29.0434 | F56: =C56*E56 -> 395.37779 | G56: =F56/px-1 -> 0.28016121
A57: B | B57: FY2027 | C57: =PL!E24 -> 13.613344 | D57: 參考：25 分位 | E57: =pe_peak -> 25.550962 | F57: =C57*E57 -> 347.83403 | G57: =F57/px-1 -> 0.12622318
A58: B | B58: FY2027 | C58: =PL!E24 -> 13.613344 | D58: 參考：中位數 | E58: =pe_mid -> 29.0434 | F58: =C58*E58 -> 395.37779 | G58: =F58/px-1 -> 0.28016121
A59: B | B59: FY2027 | C59: =PL!E24 -> 13.613344 | D59: 參考：75 分位 | E59: =pe_trough -> 37.733133 | F59: =C59*E59 -> 513.67411 | G59: =F59/px-1 -> 0.66318314
A60: B | B60: FY2028 | C60: =PL!F24 -> 14.052148 | D60: 參考：25 分位 | E60: =pe_peak -> 25.550962 | F60: =C60*E60 -> 359.04591 | G60: =F60/px-1 -> 0.16252519
A61: B | B61: FY2028 | C61: =PL!F24 -> 14.052148 | D61: 參考：中位數 | E61: =pe_mid -> 29.0434 | F61: =C61*E61 -> 408.12216 | G61: =F61/px-1 -> 0.32142517
A62: B | B62: FY2028 | C62: =PL!F24 -> 14.052148 | D62: 參考：75 分位 | E62: =pe_trough -> 37.733133 | F62: =C62*E62 -> 530.23158 | G62: =F62/px-1 -> 0.7167932
A63: C | B63: FY2027 | C63: =PL!E35 -> 13.581969 | D63: ="規則值："&D45 -> 規則值：見頂 | E63: =E45 -> 25.550962 | F63: =C63*E63 -> 347.03236 | G63: =F63/px-1 -> 0.12362753
A64: C | B64: FY2027 | C64: =PL!E35 -> 13.581969 | D64: 參考：25 分位 | E64: =pe_peak -> 25.550962 | F64: =C64*E64 -> 347.03236 | G64: =F64/px-1 -> 0.12362753
A65: C | B65: FY2027 | C65: =PL!E35 -> 13.581969 | D65: 參考：中位數 | E65: =pe_mid -> 29.0434 | F65: =C65*E65 -> 394.46655 | G65: =F65/px-1 -> 0.27721077
A66: C | B66: FY2027 | C66: =PL!E35 -> 13.581969 | D66: 參考：75 分位 | E66: =pe_trough -> 37.733133 | F66: =C66*E66 -> 512.49023 | G66: =F66/px-1 -> 0.65934994
A67: C | B67: FY2028 | C67: =PL!F35 -> 12.238639 | D67: 參考：25 分位 | E67: =pe_peak -> 25.550962 | F67: =C67*E67 -> 312.709 | G67: =F67/px-1 -> 0.012494752
A68: C | B68: FY2028 | C68: =PL!F35 -> 12.238639 | D68: 參考：中位數 | E68: =pe_mid -> 29.0434 | F68: =C68*E68 -> 355.45169 | G68: =F68/px-1 -> 0.15088779
A69: C | B69: FY2028 | C69: =PL!F35 -> 12.238639 | D69: 參考：75 分位 | E69: =pe_trough -> 37.733133 | F69: =C69*E69 -> 461.8022 | G69: =F69/px-1 -> 0.49523135
A71: 6. 目前遠期 P/E
A72: 項目 | B72: A（順利） | C72: B（平平） | D72: C（不如預期） | E72: 備註
A73: 現價（2026-10-23 收盤） | B73: =px -> 308.85 | E73: stockanalysis、equibles
A74: 遠期 P/E：stockanalysis | B74: =sa_fpe -> 32.52 | E74: 分析師共識前瞻 EPS（non-GAAP）
A75: 現價 ÷ FY2026 EPS（錨點） | B75: =px/f26_eps -> 35.159524 | E75: FY2026 三情境相同
A76: 現價 ÷ FY2027 EPS（模型） | B76: =px/PL!E13 -> 22.635131 | C76: =px/PL!E24 -> 22.687299 | D76: =px/PL!E35 -> 22.739708
A77: 現價 ÷ FY2028 EPS（模型） | B77: =px/PL!F13 -> 18.713102 | C77: =px/PL!F24 -> 21.978845 | D77: =px/PL!F35 -> 25.235648
A78: 現價 ÷ 共識 FY2027 EPS（non-GAAP） | B78: =px/cons_eps27 -> 27.331858 | E78: MarketBeat 11.30
A80: 舊法：規則值情境加權（參考）
A81: 項目 | B81: 數值 | E81: 說明
A82: 規則值情境加權價（12 個月；參考） | B82: =tp_wA*B84+tp_wB*B85+tp_wC*B86 -> 385.98208 | E82: 權重 × 各情境隱含價（第 5 節規則值）
A83: 相對現價（規則值情境加權價 ÷ 現價 − 1） | B83: =B82/px-1 -> 0.2497396 | E83: 現價＝In 頁 px（2026-10-23 收盤）
A84: 情境 A 隱含價（順利） | B84: =F49 -> 396.28903 | E84: ="FY2027 EPS × "&D49&" "&TEXT(E49,"0.0")&"x（第 5 節 F49）" -> FY2027 EPS × 規則值：中段 29.0x（第 5 節 F49）
A85: 情境 B 隱含價（平平） | B85: =F56 -> 395.37779 | E85: ="FY2027 EPS × "&D56&" "&TEXT(E56,"0.0")&"x（第 5 節 F56）" -> FY2027 EPS × 規則值：中段 29.0x（第 5 節 F56）
A86: 情境 C 隱含價（不如預期） | B86: =F63 -> 347.03236 | E86: ="FY2027 EPS × "&D63&" "&TEXT(E63,"0.0")&"x（第 5 節 F63）" -> FY2027 EPS × 規則值：見頂 25.6x（第 5 節 F63）
A87: 情境權重 A／B／C | B87: =tp_wA -> 0.3 | C87: =tp_wB -> 0.5 | D87: =tp_wC -> 0.2 | E87: ="合計 "&TEXT(B87+C87+D87,"0%")&"；In 頁 tp_wA／tp_wB／tp_wC（Assumed，Andy 可改）" -> 合計 100%；In 頁 tp_wA／tp_wB／tp_wC（Assumed，Andy 可改）
A88: 規則值方法 | B88: P/E：各情境 FY2027 EPS × 十年（2016–2025 年底）P/E 依循環位置取分位（設備股共用規則：A、B 中段＝中位數，C 見頂＝25 分位；FY2016 虧損不納入，實為 9 年）。隱含價約為 FY2027 年底的價格、未折現
A91: 0. 目標價
A92: 0.1 DCF（股東權益現金流，FY2027–FY2032 明確期＋FY2032 後永續）
A93: 項目 | B93: A（順利） | C93: B（平平） | D93: C（不如預期） | E93: 說明
A94: 情境 EPS（FY2027–FY2032） | E94: PL 頁延伸區塊；FY2030 起為收斂法
A95: FY2027 | B95: =PL!E142 -> 13.644719 | C95: =PL!E149 -> 13.613344 | D95: =PL!E156 -> 13.581969
A96: FY2028 | B96: =PL!F142 -> 16.504479 | C96: =PL!F149 -> 14.052148 | D96: =PL!F156 -> 12.238639
A97: FY2029 | B97: =PL!G142 -> 19.445202 | C97: =PL!G149 -> 17.151628 | D97: =PL!G156 -> 15.554149
A98: FY2030 | B98: =PL!H142 -> 21.55712 | C98: =PL!H149 -> 17.800853 | D98: =PL!H156 -> 15.477087
A99: FY2031 | B99: =PL!I142 -> 23.374479 | C99: =PL!I149 -> 17.704654 | D99: =PL!I156 -> 14.181348
A100: FY2032 | B100: =PL!J142 -> 24.776948 | C100: =PL!J149 -> 16.833038 | D100: =PL!J156 -> 11.804326
A101: 股東現金流＝EPS ×（1 − tp_g ÷ tp_roe） | E101: 模型無折舊與資本支出項目，故不用（淨利＋折舊－資本支出）；FY2025 資本支出 224.0、折舊 111.4（10-K 現金流量表），資本支出約為營收 7%，偏誤小
A102: 再投資率（tp_g ÷ tp_roe，上限 0.8） | B102: =MIN(tp_g/tp_roe,0.8) -> 0.20667709 | E102: ROE 為近三年平均（In 頁 tp_roe）
A103: FY2027 | B103: =B95*(1-$B$102) -> 10.824668 | C103: =C95*(1-$B$102) -> 10.799778 | D103: =D95*(1-$B$102) -> 10.774887
A104: FY2028 | B104: =B96*(1-$B$102) -> 13.093381 | C104: =C96*(1-$B$102) -> 11.147891 | D104: =D96*(1-$B$102) -> 9.709193
A105: FY2029 | B105: =B97*(1-$B$102) -> 15.426324 | C105: =C97*(1-$B$102) -> 13.606779 | D105: =D97*(1-$B$102) -> 12.339463
A106: FY2030 | B106: =B98*(1-$B$102) -> 17.101757 | C106: =C98*(1-$B$102) -> 14.121824 | D106: =D98*(1-$B$102) -> 12.278328
A107: FY2031 | B107: =B99*(1-$B$102) -> 18.54351 | C107: =C99*(1-$B$102) -> 14.045508 | D107: =D99*(1-$B$102) -> 11.250388
A108: FY2032 | B108: =B100*(1-$B$102) -> 19.65612 | C108: =C100*(1-$B$102) -> 13.354034 | D108: =D100*(1-$B$102) -> 9.3646424
...

Sheet Recon
A1: Recon — 本模型 vs 公司指引、目標模型、共識、Advantest 份額、測試對 WFE 比。只作事後對照，不為對上數字而調整參數。差距 > 10% 的原因見 README
A3: 項目 | B3: 對照值 | C3: 模型 A | D3: 差距 A | E3: 模型 B | F3: 差距 B | G3: 模型 C | H3: 差距 C | I3: 對照來源 | J3: 說明
A4: A. FY2026 vs 公司指引與共識
A5: 營收：上半年占 51%（公司 50–52% 中點）推得的全年 | B5: =Q!J10/0.51 -> 5120.5882 | C5: =PL!D5 -> 5111.6 | D5: =C5/B5-1 -> -0.001755313 | E5: =PL!D16 -> 5111.6 | F5: =E5/B5-1 -> -0.001755313 | G5: =PL!D27 -> 5111.6 | H5: =G5/B5-1 -> -0.001755313 | I5: 公司 2Q26 法說 | J5: 錨點由 3Q26 指引推得；與公司上半年占比一致性檢查
A6: 營收（共識） | B6: =cons_rev26 -> 5100 | C6: =PL!D5 -> 5111.6 | D6: =C6/B6-1 -> 0.0022745098 | E6: =PL!D16 -> 5111.6 | F6: =E6/B6-1 -> 0.0022745098 | G6: =PL!D27 -> 5111.6 | H6: =G6/B6-1 -> 0.0022745098 | I6: stockanalysis 2026-10-20
A7: EPS（共識，non-GAAP） | B7: =cons_eps26 -> 9.09 | C7: =PL!D13 -> 8.7842486 | D7: =C7/B7-1 -> -0.033636021 | E7: =PL!D24 -> 8.7842486 | F7: =E7/B7-1 -> -0.033636021 | G7: =PL!D35 -> 8.7842486 | H7: =G7/B7-1 -> -0.033636021 | I7: stockanalysis 2026-10-20 | J7: 模型為 GAAP；non-GAAP 另加權益法投資攤銷約 0.20、無形資產攤銷約 0.08／年（2Q26 新聞稿調節表）
A8: B. FY2027 vs 共識
A9: EPS（共識，non-GAAP） | B9: =cons_eps27 -> 11.3 | C9: =PL!E13 -> 13.644719 | D9: =C9/B9-1 -> 0.20749727 | E9: =PL!E24 -> 13.613344 | F9: =E9/B9-1 -> 0.2047207 | G9: =PL!E35 -> 13.581969 | H9: =G9/B9-1 -> 0.20194414 | I9: MarketBeat 2026-10-20 | J9: 差距大於 10% 的原因見 README
A10: C. 公司目標模型（ATE 市場 US$12–14B 時；未給年度）
A11: 營收 6.0B：模型 FY2027 | B11: =tm_rev -> 6000 | C11: =PL!E5 -> 6923.6722 | D11: =C11/B11-1 -> 0.15394537 | E11: =PL!E16 -> 6911.8471 | F11: =E11/B11-1 -> 0.15197452 | G11: =PL!E27 -> 6900.022 | H11: =G11/B11-1 -> 0.15000367 | I11: 公司 4Q25 法說（fintool） | J11: 目標模型未給年度；本列只看量級
A12: non-GAAP EPS 上緣 11.00：模型 FY2027（GAAP） | B12: =tm_eps_hi -> 11 | C12: =PL!E13 -> 13.644719 | D12: =C12/B12-1 -> 0.24042901 | E12: =PL!E24 -> 13.613344 | F12: =E12/B12-1 -> 0.23757672 | G12: =PL!E35 -> 13.581969 | H12: =G12/B12-1 -> 0.23472444 | I12: 同上
A13: D. 市占與市場規模
A14: CY2025 SoC：泰瑞達隱含市占 vs 1 − Advantest 自估 66% | B14: =1-as_A_2026 -> 0.34 | C14: =PL!C48 -> 0.27386957 | D14: =C14-B14 -> -0.066130435 | E14: =PL!C78 -> 0.27386957 | F14: =E14-B14 -> -0.066130435 | G14: =PL!C108 -> 0.27386957 | H14: =G14-B14 -> -0.066130435 | I14: Advantest 自估（Interested-party） | J14: 差額＝其他廠份額（CY2025 約 6.6%）
A15: CY2026 SoC 市占 vs 分析師估約 37% | B15: =an_share -> 0.37 | C15: =PL!D48 -> 0.29539273 | D15: =C15-B15 -> -0.074607273 | E15: =PL!D78 -> 0.29539273 | F15: =E15-B15 -> -0.074607273 | G15: =PL!D108 -> 0.29539273 | H15: =G15-B15 -> -0.074607273 | I15: 2Q26 法說分析師提問（公司未證實） | J15: 口徑不同：Advantest 的 SoC 市場含其自身所有 SoC 測試機；分析師口徑未明
A16: CY2026：SoC＋記憶體測試機 ÷ WFE vs 公司長期上緣 9% | B16: =tw_hi -> 0.09 | C16: =Units!D10 -> 0.085913329 | D16: =C16-B16 -> -0.0040866708 | E16: =Units!D18 -> 0.085913329 | F16: =E16-B16 -> -0.0040866708 | G16: =Units!D26 -> 0.085913329 | H16: =G16-B16 -> -0.0040866708 | I16: 公司 2Q26 法說（Interested-party）
A17: CY2027：SoC＋記憶體測試機 ÷ WFE vs 公司長期上緣 9% | B17: =tw_hi -> 0.09 | C17: =Units!E10 -> 0.10007721 | D17: =C17-B17 -> 0.010077207 | E17: =Units!E18 -> 0.10007721 | F17: =E17-B17 -> 0.010077207 | G17: =Units!E26 -> 0.10007721 | H17: =G17-B17 -> 0.010077207 | I17: 公司 2Q26 法說（Interested-party） | J17: 公司口徑為 ATE 市場（含類比等其他測試機）÷ WFE；本模型分子只有 SoC＋記憶體，口徑更窄卻已高於上緣
A18: CY2028：SoC＋記憶體測試機 ÷ WFE vs 公司長期上緣 9% | B18: =tw_hi -> 0.09 | C18: =Units!F10 -> 0.10315008 | D18: =C18-B18 -> 0.013150082 | E18: =Units!F18 -> 0.10118169 | F18: =E18-B18 -> 0.011181693 | G18: =Units!F26 -> 0.10296333 | H18: =G18-B18 -> 0.012963326 | I18: 公司 2Q26 法說（Interested-party）
A19: E. 其他資訊（非對帳）
A20: 上半年 FY2026 營收 ÷ 模型 FY2026 營收 | C20: =Q!J10/PL!D5 -> 0.51089678 | J20: 公司：上半年 50–52%
A21: 指引紀錄：1Q26、2Q26 營收皆高於指引上緣（1,250） | C21: =(Q!G10+Q!H10)/2/1250-1 -> 0.0446 | J21: 指引偏保守 → FY2026 錨點可能偏低（下半年以指引中點推估）

Sheet Sens
A1: Sens — 一次動一個輸入（情境 A）：對 FY2027、FY2028 營收與 EPS 的影響。每個案例是一個完整的推導區塊（本頁下方，與 PL 同一引擎）；FY2026 錨點不變
A3: 案例 | B3: 設定 | C3: FY2027 營收 US$M | D3: FY2027 EPS US$ | E3: 相對基準 | F3: FY2028 營收 US$M | G3: FY2028 EPS US$ | H3: 相對基準
A4: 基準（情境 A） | B4: PL 區塊 A | C4: =PL!E61 -> 6923.6722 | D4: =PL!E69 -> 13.644719 | E4: =D4/D$4-1 -> 0 | F4: =PL!F61 -> 7961.4985 | G4: =PL!F69 -> 16.504479 | H4: =G4/G$4-1 -> 0
A5: 泰瑞達 SoC 市占 −5 個百分點 | B5: A 情境 FY2027 起 | C5: =E57 -> 6152.9543 | D5: =E65 -> 11.599798 | E5: =D5/D$4-1 -> -0.14986905 | F5: =F57 -> 7096.5393 | G5: =F65 -> 14.186329 | H5: =G5/G$4-1 -> -0.14045581
A6: 泰瑞達 SoC 市占 +5 個百分點 | C6: =E89 -> 7694.3901 | D6: =E97 -> 15.68964 | E6: =D6/D$4-1 -> 0.14986905 | F6: =F89 -> 8826.4577 | G6: =F97 -> 18.822629 | H6: =G6/G$4-1 -> 0.14045581
A7: SoC 測試機市場 −15%（2027 起） | B7: 測試對 WFE 比回到公司說的區間 | C7: =E121 -> 6199.5835 | D7: =E129 -> 11.723518 | E7: =D7/D$4-1 -> -0.14080183 | F7: =F121 -> 7148.8701 | G7: =F129 -> 14.326579 | H7: =G7/G$4-1 -> -0.1319581
A8: 記憶體市占 −5 個百分點 | C8: =E153 -> 6729.6685 | D8: =E161 -> 13.129975 | E8: =D8/D$4-1 -> -0.037724763 | F8: =F153 -> 7709.1947 | G8: =F161 -> 15.828287 | H8: =G8/G$4-1 -> -0.040970189
A9: 記憶體市占 +5 個百分點 | C9: =E185 -> 7117.6759 | D9: =E193 -> 14.159463 | E9: =D9/D$4-1 -> 0.037724763 | F9: =F185 -> 8213.8024 | G9: =F193 -> 17.18067 | H9: =G9/G$4-1 -> 0.040970189
A10: 測試事業增量利益率 40% | B10: 固定成本重新推導（FY2026 錨點不變） | C10: =E217 -> 6923.6722 | D10: =E225 -> 12.839595 | E10: =D10/D$4-1 -> -0.059006296 | F10: =F217 -> 7961.4985 | G10: =F225 -> 15.235163 | H10: =G10/G$4-1 -> -0.076907358
A11: 測試事業增量利益率 56% | B11: 同上 | C11: =E249 -> 6923.6722 | D11: =E257 -> 14.398097 | E11: =D11/D$4-1 -> 0.055213855 | F11: =F249 -> 7961.4985 | G11: =F257 -> 17.692214 | H11: =G11/G$4-1 -> 0.071964384
A12: Product Test 成長 低 | B12: A 情境 4% | C12: =E281 -> 6907.9054 | D12: =E289 -> 13.602886 | E12: =D12/D$4-1 -> -0.0030659146 | F12: =F281 -> 7928.0729 | G12: =F289 -> 16.414896 | H12: =G12/G$4-1 -> -0.0054277959
A13: Product Test 成長 高 | B13: A 情境 12% | C13: =E313 -> 6939.439 | D13: =E321 -> 13.686553 | E13: =D13/D$4-1 -> 0.0030659146 | F13: =F313 -> 7996.1855 | G13: =F321 -> 16.597442 | H13: =G13/G$4-1 -> 0.0056326184
A14: 機器人成長 0% | B14: 三情境相同 | C14: =E345 -> 6883.5202 | D14: =E353 -> 13.640305 | E14: =D14/D$4-1 -> -0.0003235309 | F14: =F345 -> 7877.1793 | G14: =F353 -> 16.485751 | H14: =G14/G$4-1 -> -0.0011347303
A15: 機器人成長 20% | C15: =E377 -> 6963.8242 | D15: =E385 -> 13.649134 | E15: =D15/D$4-1 -> 0.0003235309 | F15: =F377 -> 8053.8481 | G15: =F385 -> 16.524991 | H15: =G15/G$4-1 -> 0.0012427998
A16: 機器人利益率 低 | B16: 每年 −7 個百分點 | C16: =E409 -> 6923.6722 | D16: =E417 -> 13.474761 | E16: =D16/D$4-1 -> -0.012455939 | F16: =F409 -> 7961.4985 | G16: =F417 -> 16.315637 | H16: =G16/G$4-1 -> -0.011441864
A17: 機器人利益率 高 | B17: 每年 +5 個百分點 | C17: =E441 -> 6923.6722 | D17: =E449 -> 13.766118 | E17: =D17/D$4-1 -> 0.0088970996 | F17: =F441 -> 7961.4985 | G17: =F449 -> 16.639366 | H17: =G17/G$4-1 -> 0.0081727597
A18: 稅率 12% | C18: =E473 -> 6923.6722 | D18: =E481 -> 13.992771 | E18: =D18/D$4-1 -> 0.025508189 | F18: =F473 -> 7961.4985 | G18: =F481 -> 16.925051 | H18: =G18/G$4-1 -> 0.025482282
A19: 稅率 17% | C19: =E505 -> 6923.6722 | D19: =E513 -> 13.192923 | E19: =D19/D$4-1 -> -0.033111393 | F19: =F505 -> 7961.4985 | G19: =F513 -> 15.958548 | H19: =G19/G$4-1 -> -0.033077764
A20: 回購 0%／年 | C20: =E537 -> 6923.6722 | D20: =E545 -> 13.508272 | E20: =D20/D$4-1 -> -0.01 | F20: =F537 -> 7961.4985 | G20: =F545 -> 16.17604 | H20: =G20/G$4-1 -> -0.0199
A21: 回購 2%／年 | C21: =E569 -> 6923.6722 | D21: =E577 -> 13.783951 | E21: =D21/D$4-1 -> 0.010204082 | F21: =F569 -> 7961.4985 | G21: =F577 -> 16.843023 | H21: =G21/G$4-1 -> 0.020512287
A22: 情境 B（平平） | B22: Advantest 模型的 B 市場；Product Test 成長 B | C22: =PL!E91 -> 6911.8471 | D22: =PL!E99 -> 13.613344 | E22: =D22/D$4-1 -> -0.002299436 | F22: =PL!F91 -> 7046.4733 | G22: =PL!F99 -> 14.052148 | H22: =G22/G$4-1 -> -0.14858575
A23: 情境 C（不如預期） | B23: C 市場；市占自 Advantest 搶回、利益率下調 | C23: =PL!E121 -> 6900.022 | D23: =PL!E129 -> 13.581969 | E23: =D23/D$4-1 -> -0.004598872 | F23: =PL!F121 -> 6494.2954 | G23: =PL!F129 -> 12.238639 | H23: =G23/G$4-1 -> -0.25846557
A25: 讀法：測試機市場（Advantest 模型）在 CY2027 已比 CY2026 高約四成，泰瑞達的 FY2027 主要取決於市場是否真的長到這個水準與市占；情境 B、C 的顆數係數從 2028 才生效，所以對 FY2027 無影響、對 FY2028 才明顯。
A40: 案例區塊：泰瑞達 SoC 市占 −5 個百分點（情境 A）
A41: 項目 | B41: 單位 | C41: FY2025A | D41: FY2026（錨點） | E41: FY2027 | F41: FY2028 | G41: FY2029 | H41: 說明
A42: SoC 測試機市場 CY（Advantest 模型） | B42: US$B | C42: =mk_soc25 -> 6.9 | D42: =ms_A_2026 -> 11 | E42: =ms_A_2027*m_soc -> 15.414358 | F42: =ms_A_2028*m_soc -> 17.299184 | G42: =ms_A_2029*m_soc -> 19.236176
A43: 記憶體測試機市場 CY（Advantest 模型） | B43: US$B | C43: =mk_mem25 -> 2.1 | D43: =mm_A_2026 -> 2.75 | E43: =mm_A_2027 -> 3.8800741 | F43: =mm_A_2028 -> 5.0460769 | G43: =mm_A_2029 -> 6.2022378
A44: 泰瑞達 SoC 市占 | B44: % | C44: =a25_soc/(C42*1000) -> 0.27386957 | D44: =f26_soc/(D42*1000) -> 0.29539273 | E44: =s_soc_lo -> 0.24539273 | F44: =s_soc_lo -> 0.24539273 | G44: =s_soc_lo -> 0.24539273 | H44: FY2025、FY2026＝實績／錨點隱含；之後維持
A45: SoC 測試機營收 | B45: US$M | C45: =a25_soc -> 1889.7 | D45: =f26_soc -> 3249.32 | E45: =E42*1000*E44 -> 3782.5714 | F45: =F42*1000*F44 -> 4245.0939 | G45: =G42*1000*G44 -> 4720.4177 | H45: 市場 × 市占
A46: 泰瑞達記憶體測試機市占 | B46: % | C46: =a25_mem/(C43*1000) -> 0.24042857 | D46: =f26_mem/(D43*1000) -> 0.31675636 | E46: =s_mem -> 0.31675636 | F46: =s_mem -> 0.31675636 | G46: =s_mem -> 0.31675636
A47: 記憶體測試機營收 | B47: US$M | C47: =a25_mem -> 504.9 | D47: =f26_mem -> 871.08 | E47: =E43*1000*E46 -> 1229.0382 | F47: =F43*1000*F46 -> 1598.377 | G47: =G43*1000*G46 -> 1964.5983
A48: IST 營收（隨 SoC 市場） | B48: US$M | C48: =a25_ist -> 129.2 | D48: =f26_ist -> 195.51 | E48: =$D48*E42/$D42 -> 273.9692 | F48: =$D48*F42/$D42 -> 307.4694 | G48: =$D48*G42/$D42 -> 341.8968 | H48: FY2026 × SoC 市場相對 CY2026
A49: 半導體測試營收 | B49: US$M | C49: =C45+C47+C48 -> 2523.8 | D49: =D45+D47+D48 -> 4315.91 | E49: =E45+E47+E48 -> 5285.5787 | F49: =F45+F47+F48 -> 6150.9402 | G49: =G45+G47+G48 -> 7026.9128
A50: Product Test 營收 | B50: US$M | C50: =a25_pt -> 358 | D50: =f26_pt -> 394.17 | E50: =D50*(1+g_pt_A) -> 425.7036 | F50: =E50*(1+g_pt_A) -> 459.75989 | G50: =F50*(1+g_pt_A) -> 496.54068
A51: 測試事業營收（半導體測試＋Product Test） | B51: US$M | C51: =C49+C50 -> 2881.8 | D51: =D49+D50 -> 4710.08 | E51: =E49+E50 -> 5711.2823 | F51: =F49+F50 -> 6610.7001 | G51: =G49+G50 -> 7523.4535
A52: 測試事業稅前利益 | B52: US$M | C52: =a25_ttest -> 761.4 | D52: =f26_ttest -> 1643.8307 | E52: =t_inc*E51-t_fix+0*E51 -> 2127.0673 | F52: =t_inc*F51-t_fix+0*F51 -> 2561.1769 | G52: =t_inc*G51-t_fix+0*G51 -> 3001.723 | H52: 增量利益率 × 營收 − 固定成本（兩點推導）；C 情境另加價格競爭調整
A53: 測試事業稅前利益率 | B53: % | C53: =C52/C51 -> 0.26420987 | D53: =D52/D51 -> 0.34900272 | E53: =E52/E51 -> 0.37243252 | F53: =F52/F51 -> 0.38742899 | G53: =G52/G51 -> 0.39898206
A54: 機器人營收（不隨 AI 情境） | B54: US$M | C54: =a25_rob -> 308.3 | D54: =f26_rob -> 401.52 | E54: =D54*(1+g_rob) -> 441.672 | F54: =E54*(1+g_rob) -> 485.8392 | G54: =F54*(1+g_rob) -> 534.42312
A55: 機器人稅前利益 | B55: US$M | C55: =a25_trob -> -99.4 | D55: =f26_trob -> -3.5 | E55: =E54*rm_2027 -> 8.83344 | F55: =F54*rm_2028 -> 19.433568 | G55: =G54*rm_2029 -> 26.721156
A56: 公司與沖銷 | B56: US$M | C56: =a25_corp -> -8.8 | D56: =f26_corp -> -10.4 | E56: =corp -> -10.4 | F56: =corp -> -10.4 | G56: =corp -> -10.4
A57: 營收 | B57: US$M | C57: =C51+C54 -> 3190.1 | D57: =D51+D54 -> 5111.6 | E57: =E51+E54 -> 6152.9543 | F57: =F51+F54 -> 7096.5393 | G57: =G51+G54 -> 8057.8766
A58: 檢查：分部合計 − 合併營收（FY2025 實績、FY2026 錨點；四捨五入到百萬美元） | B58: US$M | C58: =ROUND(C49+C50+C54-a25_rev,0) -> 0 | D58: =ROUND(D49+D50+D54-f26_rev,0) -> 0 | H58: FY2025 分部合計 3,190.1 vs 公司合併營收 3,190.0：季度分部數字四捨五入差 0.1
A59: 稅前利益 | B59: US$M | C59: =C52+C55+C56 -> 653.2 | D59: =D52+D55+D56 -> 1629.9307 | E59: =E52+E55+E56 -> 2125.5007 | F59: =F52+F55+F56 -> 2570.2105 | G59: =G52+G55+G56 -> 3018.0442
A60: 稅前利益率 | B60: % | C60: =C59/C57 -> 0.20475847 | D60: =D59/D57 -> 0.31886899 | E60: =E59/E57 -> 0.34544393 | F60: =F59/F57 -> 0.362178 | G60: =G59/G57 -> 0.37454584
A61: 所得稅 | B61: US$M | C61: =a25_tax -> 79.3 | D61: =f26_tax -> 231.05474 | E61: =E59*etr -> 301.30545 | F61: =F59*etr -> 364.34634 | G61: =G59*etr -> 427.83008
A62: 權益法投資損益（Technoprobe） | B62: US$M | C62: =a25_aff -> -19.9 | D62: =f26_aff -> -13.2 | E62: =aff -> -13.2 | F62: =aff -> -13.2 | G62: =aff -> -13.2
A63: 淨利 | B63: US$M | C63: =a25_ni -> 554 | D63: =f26_ni -> 1385.276 | E63: =E59-E61+E62 -> 1810.9953 | F63: =F59-F61+F62 -> 2192.6641 | G63: =G59-G61+G62 -> 2577.0141 | H63: FY2026＝錨點（上半年實績＋下半年指引）
A64: 稀釋股數 | B64: 百萬股 | C64: =a25_dsh -> 159.7 | D64: =sh26 -> 157.7 | E64: =sh26*(1-bb)^1 -> 156.123 | F64: =sh26*(1-bb)^2 -> 154.56177 | G64: =sh26*(1-bb)^3 -> 153.01615
A65: EPS（GAAP 稀釋） | B65: US$ | C65: =a25_eps -> 3.47 | D65: =D63/D64 -> 8.7842486 | E65: =E63/E64 -> 11.599798 | F65: =F63/F64 -> 14.186329 | G65: =G63/G64 -> 16.841451
A66: SoC 占營收 | B66: % | C66: =C45/C57 -> 0.59236388 | D66: =D45/D57 -> 0.63567572 | E66: =E45/E57 -> 0.61475694 | F66: =F45/F57 -> 0.59819211 | G66: =G45/G57 -> 0.5858141
A67: 毛利率（參考；不進 EPS） | B67: % | C67: =a25_gp/a25_rev -> 0.58222571 | D67: =f26_gm -> 0.59436565 | E67: =f26_gm+(Q!J13-a25_gp/a25_rev)/(Q!J4/Q!J10-a25_soc/a25_rev)*(E66-D66) -> 0.58788063 | F67: =f26_gm+(Q!J13-a25_gp/a25_rev)/(Q!J4/Q!J10-a25_soc/a25_rev)*(F66-D66) -> 0.58274538 | G67: =f26_gm+(Q!J13-a25_gp/a25_rev)/(Q!J4/Q!J10-a25_soc/a25_rev)*(G66-D66) -> 0.57890808 | H67: FY2026＋斜率 ×（SoC 占營收 − FY2026）；斜率由 FY2025 與上半年 FY2026 兩點推得；EPS 由事業別稅前利益推導，本列只供參考
A72: 案例區塊：泰瑞達 SoC 市占 +5 個百分點（情境 A）
A73: 項目 | B73: 單位 | C73: FY2025A | D73: FY2026（錨點） | E73: FY2027 | F73: FY2028 | G73: FY2029 | H73: 說明
A74: SoC 測試機市場 CY（Advantest 模型） | B74: US$B | C74: =mk_soc25 -> 6.9 | D74: =ms_A_2026 -> 11 | E74: =ms_A_2027*m_soc -> 15.414358 | F74: =ms_A_2028*m_soc -> 17.299184 | G74: =ms_A_2029*m_soc -> 19.236176
A75: 記憶體測試機市場 CY（Advantest 模型） | B75: US$B | C75: =mk_mem25 -> 2.1 | D75: =mm_A_2026 -> 2.75 | E75: =mm_A_2027 -> 3.8800741 | F75: =mm_A_2028 -> 5.0460769 | G75: =mm_A_2029 -> 6.2022378
A76: 泰瑞達 SoC 市占 | B76: % | C76: =a25_soc/(C74*1000) -> 0.27386957 | D76: =f26_soc/(D74*1000) -> 0.29539273 | E76: =s_soc_hi -> 0.34539273 | F76: =s_soc_hi -> 0.34539273 | G76: =s_soc_hi -> 0.34539273 | H76: FY2025、FY2026＝實績／錨點隱含；之後維持
A77: SoC 測試機營收 | B77: US$M | C77: =a25_soc -> 1889.7 | D77: =f26_soc -> 3249.32 | E77: =E74*1000*E76 -> 5324.0072 | F77: =F74*1000*F76 -> 5975.0122 | G77: =G74*1000*G76 -> 6644.0354 | H77: 市場 × 市占
A78: 泰瑞達記憶體測試機市占 | B78: % | C78: =a25_mem/(C75*1000) -> 0.24042857 | D78: =f26_mem/(D75*1000) -> 0.31675636 | E78: =s_mem -> 0.31675636 | F78: =s_mem -> 0.31675636 | G78: =s_mem -> 0.31675636
A79: 記憶體測試機營收 | B79: US$M | C79: =a25_mem -> 504.9 | D79: =f26_mem -> 871.08 | E79: =E75*1000*E78 -> 1229.0382 | F79: =F75*1000*F78 -> 1598.377 | G79: =G75*1000*G78 -> 1964.5983
A80: IST 營收（隨 SoC 市場） | B80: US$M | C80: =a25_ist -> 129.2 | D80: =f26_ist -> 195.51 | E80: =$D80*E74/$D74 -> 273.9692 | F80: =$D80*F74/$D74 -> 307.4694 | G80: =$D80*G74/$D74 -> 341.8968 | H80: FY2026 × SoC 市場相對 CY2026
A81: 半導體測試營收 | B81: US$M | C81: =C77+C79+C80 -> 2523.8 | D81: =D77+D79+D80 -> 4315.91 | E81: =E77+E79+E80 -> 6827.0145 | F81: =F77+F79+F80 -> 7880.8586 | G81: =G77+G79+G80 -> 8950.5305
A82: Product Test 營收 | B82: US$M | C82: =a25_pt -> 358 | D82: =f26_pt -> 394.17 | E82: =D82*(1+g_pt_A) -> 425.7036 | F82: =E82*(1+g_pt_A) -> 459.75989 | G82: =F82*(1+g_pt_A) -> 496.54068
A83: 測試事業營收（半導體測試＋Product Test） | B83: US$M | C83: =C81+C82 -> 2881.8 | D83: =D81+D82 -> 4710.08 | E83: =E81+E82 -> 7252.7181 | F83: =F81+F82 -> 8340.6185 | G83: =G81+G82 -> 9447.0711
A84: 測試事業稅前利益 | B84: US$M | C84: =a25_ttest -> 761.4 | D84: =f26_ttest -> 1643.8307 | E84: =t_inc*E83-t_fix+0*E83 -> 2871.0509 | F84: =t_inc*F83-t_fix+0*F83 -> 3396.1328 | G84: =t_inc*G83-t_fix+0*G83 -> 3930.169 | H84: 增量利益率 × 營收 − 固定成本（兩點推導）；C 情境另加價格競爭調整
A85: 測試事業稅前利益率 | B85: % | C85: =C84/C83 -> 0.26420987 | D85: =D84/D83 -> 0.34900272 | E85: =E84/E83 -> 0.3958586 | F85: =F84/F83 -> 0.40717997 | G85: =G84/G83 -> 0.41601984
A86: 機器人營收（不隨 AI 情境） | B86: US$M | C86: =a25_rob -> 308.3 | D86: =f26_rob -> 401.52 | E86: =D86*(1+g_rob) -> 441.672 | F86: =E86*(1+g_rob) -> 485.8392 | G86: =F86*(1+g_rob) -> 534.42312
A87: 機器人稅前利益 | B87: US$M | C87: =a25_trob -> -99.4 | D87: =f26_trob -> -3.5 | E87: =E86*rm_2027 -> 8.83344 | F87: =F86*rm_2028 -> 19.433568 | G87: =G86*rm_2029 -> 26.721156
A88: 公司與沖銷 | B88: US$M | C88: =a25_corp -> -8.8 | D88: =f26_corp -> -10.4 | E88: =corp -> -10.4 | F88: =corp -> -10.4 | G88: =corp -> -10.4
A89: 營收 | B89: US$M | C89: =C83+C86 -> 3190.1 | D89: =D83+D86 -> 5111.6 | E89: =E83+E86 -> 7694.3901 | F89: =F83+F86 -> 8826.4577 | G89: =G83+G86 -> 9981.4943
A90: 檢查：分部合計 − 合併營收（FY2025 實績、FY2026 錨點；四捨五入到百萬美元） | B90: US$M | C90: =ROUND(C81+C82+C86-a25_rev,0) -> 0 | D90: =ROUND(D81+D82+D86-f26_rev,0) -> 0 | H90: FY2025 分部合計 3,190.1 vs 公司合併營收 3,190.0：季度分部數字四捨五入差 0.1
A91: 稅前利益 | B91: US$M | C91: =C84+C87+C88 -> 653.2 | D91: =D84+D87+D88 -> 1629.9307 | E91: =E84+E87+E88 -> 2869.4843 | F91: =F84+F87+F88 -> 3405.1663 | G91: =G84+G87+G88 -> 3946.4902
A92: 稅前利益率 | B92: % | C92: =C91/C89 -> 0.20475847 | D92: =D91/D89 -> 0.31886899 | E92: =E91/E89 -> 0.372932 | F92: =F91/F89 -> 0.38579082 | G92: =G91/G89 -> 0.3953807
A93: 所得稅 | B93: US$M | C93: =a25_tax -> 79.3 | D93: =f26_tax -> 231.05474 | E93: =E91*etr -> 406.77062 | F93: =F91*etr -> 482.70751 | G93: =G91*etr -> 559.44417
A94: 權益法投資損益（Technoprobe） | B94: US$M | C94: =a25_aff -> -19.9 | D94: =f26_aff -> -13.2 | E94: =aff -> -13.2 | F94: =aff -> -13.2 | G94: =aff -> -13.2
A95: 淨利 | B95: US$M | C95: =a25_ni -> 554 | D95: =f26_ni -> 1385.276 | E95: =E91-E93+E94 -> 2449.5137 | F95: =F91-F93+F94 -> 2909.2588 | G95: =G91-G93+G94 -> 3373.846 | H95: FY2026＝錨點（上半年實績＋下半年指引）
A96: 稀釋股數 | B96: 百萬股 | C96: =a25_dsh -> 159.7 | D96: =sh26 -> 157.7 | E96: =sh26*(1-bb)^1 -> 156.123 | F96: =sh26*(1-bb)^2 -> 154.56177 | G96: =sh26*(1-bb)^3 -> 153.01615
A97: EPS（GAAP 稀釋） | B97: US$ | C97: =a25_eps -> 3.47 | D97: =D95/D96 -> 8.7842486 | E97: =E95/E96 -> 15.68964 | F97: =F95/F96 -> 18.822629 | G97: =G95/G96 -> 22.048953
A98: SoC 占營收 | B98: % | C98: =C77/C89 -> 0.59236388 | D98: =D77/D89 -> 0.63567572 | E98: =E77/E89 -> 0.69193361 | F98: =F77/F89 -> 0.67694339 | G98: =G77/G89 -> 0.66563534
A99: 毛利率（參考；不進 EPS） | B99: % | C99: =a25_gp/a25_rev -> 0.58222571 | D99: =f26_gm -> 0.59436565 | E99: =f26_gm+(Q!J13-a25_gp/a25_rev)/(Q!J4/Q!J10-a25_soc/a25_rev)*(E98-D98) -> 0.61180612 | F99: =f26_gm+(Q!J13-a25_gp/a25_rev)/(Q!J4/Q!J10-a25_soc/a25_rev)*(F98-D98) -> 0.60715901 | G99: =f26_gm+(Q!J13-a25_gp/a25_rev)/(Q!J4/Q!J10-a25_soc/a25_rev)*(G98-D98) -> 0.60365341 | H99: FY2026＋斜率 ×（SoC 占營收 − FY2026）；斜率由 FY2025 與上半年 FY2026 兩點推得；EPS 由事業別稅前利益推導，本列只供參考
A104: 案例區塊：SoC 測試機市場 −15%（2027 起）（情境 A）
A105: 項目 | B105: 單位 | C105: FY2025A | D105: FY2026（錨點） | E105: FY2027 | F105: FY2028 | G105: FY2029 | H105: 說明
A106: SoC 測試機市場 CY（Advantest 模型） | B106: US$B | C106: =mk_soc25 -> 6.9 | D106: =ms_A_2026 -> 11 | E106: =ms_A_2027*m_soc_lo -> 13.102204 | F106: =ms_A_2028*m_soc_lo -> 14.704306 | G106: =ms_A_2029*m_soc_lo -> 16.35075
A107: 記憶體測試機市場 CY（Advantest 模型） | B107: US$B | C107: =mk_mem25 -> 2.1 | D107: =mm_A_2026 -> 2.75 | E107: =mm_A_2027 -> 3.8800741 | F107: =mm_A_2028 -> 5.0460769 | G107: =mm_A_2029 -> 6.2022378
A108: 泰瑞達 SoC 市占 | B108: % | C108: =a25_soc/(C106*1000) -> 0.27386957 | D108: =f26_soc/(D106*1000) -> 0.29539273 | E108: =s_soc -> 0.29539273 | F108: =s_soc -> 0.29539273 | G108: =s_soc -> 0.29539273 | H108: FY2025、FY2026＝實績／錨點隱含；之後維持
A109: SoC 測試機營收 | B109: US$M | C109: =a25_soc -> 1889.7 | D109: =f26_soc -> 3249.32 | E109: =E106*1000*E108 -> 3870.2959 | F109: =F106*1000*F108 -> 4343.5451 | G109: =G106*1000*G108 -> 4829.8926 | H109: 市場 × 市占
A110: 泰瑞達記憶體測試機市占 | B110: % | C110: =a25_mem/(C107*1000) -> 0.24042857 | D110: =f26_mem/(D107*1000) -> 0.31675636 | E110: =s_mem -> 0.31675636 | F110: =s_mem -> 0.31675636 | G110: =s_mem -> 0.31675636
A111: 記憶體測試機營收 | B111: US$M | C111: =a25_mem -> 504.9 | D111: =f26_mem -> 871.08 | E111: =E107*1000*E110 -> 1229.0382 | F111: =F107*1000*F110 -> 1598.377 | G111: =G107*1000*G110 -> 1964.5983
A112: IST 營收（隨 SoC 市場） | B112: US$M | C112: =a25_ist -> 129.2 | D112: =f26_ist -> 195.51 | E112: =$D112*E106/$D106 -> 232.87382 | F112: =$D112*F106/$D106 -> 261.34899 | G112: =$D112*G106/$D106 -> 290.61228 | H112: FY2026 × SoC 市場相對 CY2026
A113: 半導體測試營收 | B113: US$M | C113: =C109+C111+C112 -> 2523.8 | D113: =D109+D111+D112 -> 4315.91 | E113: =E109+E111+E112 -> 5332.2079 | F113: =F109+F111+F112 -> 6203.2711 | G113: =G109+G111+G112 -> 7085.1031
A114: Product Test 營收 | B114: US$M | C114: =a25_pt -> 358 | D114: =f26_pt -> 394.17 | E114: =D114*(1+g_pt_A) -> 425.7036 | F114: =E114*(1+g_pt_A) -> 459.75989 | G114: =F114*(1+g_pt_A) -> 496.54068
A115: 測試事業營收（半導體測試＋Product Test） | B115: US$M | C115: =C113+C114 -> 2881.8 | D115: =D113+D114 -> 4710.08 | E115: =E113+E114 -> 5757.9115 | F115: =F113+F114 -> 6663.0309 | G115: =G113+G114 -> 7581.6438
A116: 測試事業稅前利益 | B116: US$M | C116: =a25_ttest -> 761.4 | D116: =f26_ttest -> 1643.8307 | E116: =t_inc*E115-t_fix+0*E115 -> 2149.5731 | F116: =t_inc*F115-t_fix+0*F115 -> 2586.4347 | G116: =t_inc*G115-t_fix+0*G115 -> 3029.8089 | H116: 增量利益率 × 營收 − 固定成本（兩點推導）；C 情境另加價格競爭調整
A117: 測試事業稅前利益率 | B117: % | C117: =C116/C115 -> 0.26420987 | D117: =D116/D115 -> 0.34900272 | E117: =E116/E115 -> 0.37332514 | F117: =F116/F115 -> 0.3881769 | G117: =G116/G115 -> 0.39962427
A118: 機器人營收（不隨 AI 情境） | B118: US$M | C118: =a25_rob -> 308.3 | D118: =f26_rob -> 401.52 | E118: =D118*(1+g_rob) -> 441.672 | F118: =E118*(1+g_rob) -> 485.8392 | G118: =F118*(1+g_rob) -> 534.42312
A119: 機器人稅前利益 | B119: US$M | C119: =a25_trob -> -99.4 | D119: =f26_trob -> -3.5 | E119: =E118*rm_2027 -> 8.83344 | F119: =F118*rm_2028 -> 19.433568 | G119: =G118*rm_2029 -> 26.721156
A120: 公司與沖銷 | B120: US$M | C120: =a25_corp -> -8.8 | D120: =f26_corp -> -10.4 | E120: =corp -> -10.4 | F120: =corp -> -10.4 | G120: =corp -> -10.4
A121: 營收 | B121: US$M | C121: =C115+C118 -> 3190.1 | D121: =D115+D118 -> 5111.6 | E121: =E115+E118 -> 6199.5835 | F121: =F115+F118 -> 7148.8701 | G121: =G115+G118 -> 8116.0669
A122: 檢查：分部合計 − 合併營收（FY2025 實績、FY2026 錨點；四捨五入到百萬美元） | B122: US$M | C122: =ROUND(C113+C114+C118-a25_rev,0) -> 0 | D122: =ROUND(D113+D114+D118-f26_rev,0) -> 0 | H122: FY2025 分部合計 3,190.1 vs 公司合併營收 3,190.0：季度分部數字四捨五入差 0.1
A123: 稅前利益 | B123: US$M | C123: =C116+C119+C120 -> 653.2 | D123: =D116+D119+D120 -> 1629.9307 | E123: =E116+E119+E120 -> 2148.0066 | F123: =F116+F119+F120 -> 2595.4683 | G123: =G116+G119+G120 -> 3046.1301
A124: 稅前利益率 | B124: % | C124: =C123/C121 -> 0.20475847 | D124: =D123/D121 -> 0.31886899 | E124: =E123/E121 -> 0.34647595 | F124: =F123/F121 -> 0.36305992 | G124: =G123/G121 -> 0.37532096
...

Sheet Sources
A1: 來源（公司 SEC 原文在建置環境可開啟；法說數字取自逐字稿摘要網站，待以公司原始逐字稿複核）
A2: 公司：2Q26 新聞稿（8-K Ex.99.1，2026-07-28） | B2: https://www.sec.gov/Archives/edgar/data/97210/000119312526321933/ter-ex99_1.htm
A3: 公司：2Q26 10-Q（收入拆分、分部稅前利益） | B3: https://www.sec.gov/Archives/edgar/data/97210/000119312526327715/ter-20260628.htm
A4: 公司：1Q26 新聞稿（2026-04-28） | B4: https://www.sec.gov/Archives/edgar/data/97210/000119312526188706/ter-ex99_1.htm
A5: 公司：1Q26 10-Q | B5: https://www.sec.gov/Archives/edgar/data/97210/000119312526201058/ter-20260329.htm
A6: 公司：4Q25 與 FY2025 新聞稿（2026-02-02） | B6: https://www.sec.gov/Archives/edgar/data/97210/000119312526034348/ter-ex99_1.htm
A7: 公司：FY2025 10-K（收入拆分 2023–2025、分部稅前利益） | B7: https://www.sec.gov/Archives/edgar/data/97210/000119312526059002/ter-20251231.htm
A8: 公司：3Q25 新聞稿與 10-Q | B8: https://www.sec.gov/Archives/edgar/data/97210/000119312525258477/ter-20250928.htm
A9: 公司：1Q25、2Q25 新聞稿 | B9: https://www.sec.gov/Archives/edgar/data/97210/000095017025099876/ter-ex99_1.htm
A10: SEC XBRL company facts（年度 EPS、淨利、營收、股東權益） | B10: https://data.sec.gov/api/xbrl/companyfacts/CIK0000097210.json
A11: 公司：3Q26 財報日期公告（2026-10-27 盤後） | B11: https://investingnews.com/teradyne-to-announce-third-quarter-2026-results/
A12: earningswhispers：2Q26 法說逐字稿（測試對 WFE 比、份額、上半年占比） | B12: https://earningswhispers.com/transcript/TER/Q22026
A13: gurufocus：2Q26 法說摘要（SoC 843、記憶體 212、IST 67） | B13: https://www.gurufocus.com/news/8987636/teradyne-inc-ter-q2-2026-earnings-call-highlights-record-revenue-and-robust-ai-demand-propel-growth
... A23: stockanalysis：同業遠期 P/E（Cohu、FormFactor；Advantest、KLA、AMAT 同站） | B23: https://stockanalysis.com/stocks/cohu/statistics/
A24: 本 repo：advantest／tsmc／markets/equipment 成品（唯讀）
A25: SemiAnalysis | B25: 未使用
