Workbook

Sheet README
A1: 泰瑞達（Teradyne，TER US）收支與估值模型 v0.1.1（AI 半導體 Project 步驟 5：設備與材料） 2026-10-25
A2: 模型命題：泰瑞達的盈餘由 AI 加速器與 HBM 的測試需求決定：SoC 測試機約三成份額、記憶體測試機約三成份額，乘上與 Advantest 同一份測試機市場；機器人事業另列、不隨 AI 情境。股價要看兩件事：測試機市場在 2027 年是否真的再長四成（公司自己說測試對 WFE 比 2027 年可能回落），以及 GPU 與第二家雲端客戶的份額能否在 2027 年起明顯增加。
A4: 會計年度＝日曆年。金額為百萬美元，EPS 為 GAAP 稀釋（共識為 non-GAAP，差約每年 0.3）。3Q26 預定 2026-10-27 盤後公布，建置日（2026-10-25）尚未公布；FY2026 為錨點：上半年實績＋下半年＝ 2 × 3Q26 指引中點。
A6: 驅動因子 → 推導量
A7: SoC 測試機營收＝SoC 測試機市場（讀 Advantest 模型，CY，三情境同字母）× 泰瑞達市占（FY2026 錨點推得，約三成）；記憶體測試機＝記憶體測試機市場（Advantest 模型，HBM 位元與 DRAM 設備支出同字母）× 市占；IST 隨 SoC 市場；Product Test 前一年 × 成長率
A8: 測試事業稅前利益＝增量利益率 × 測試營收 − 固定成本（FY2025 實績與 FY2026 錨點兩點推導）；機器人營收與稅前利益另列（Assumed，三情境相同）；公司與沖銷、稅率、權益法投資損益沿用 FY2026
A9: 情境 A／B／C（順利／平平／不如預期）：測試機市場讀 Advantest 模型同字母（其顆數係數讀台積電模型：2028 ×1.0／0.8／0.6，2029 ×1.0／0.85／0.6）；泰瑞達 A、B 市占維持，C 與 Advantest 互補（Advantest FY2028 61%、FY2029 56% → 泰瑞達 +5／+10 個百分點）並承受同樣的價格壓力
A10: Val：目標價＝DCF 與 Comparable 加權（第 0 節）；規則值（十年 P/E 分位依循環位置）保留參考。Recon：公司指引、目標模型、共識、Advantest 份額、測試對 WFE 比。Sens：市占、市場、增量利益率、機器人等
A12: 標記：Verified、Interested-party、Analogy、Assumed、Derived。SemiAnalysis 未使用。公司 SEC 原文可開啟；法說數字取自逐字稿摘要網站，待複核。
A13: 已知限制：(1) 測試機市場整份取自 Advantest 模型（以 Advantest 自估的 CY2026 市場校準，Interested-party），CY2027 比 CY2026 高約四成，SoC＋記憶體 ÷ WFE 達一成，高於泰瑞達自己說的 7–9%；(2) 泰瑞達市占由 FY2026 錨點推得，錨點的下半年用 3Q26 指引中點、4Q＝3Q、非 SoC 事業下半年 +10%（Assumed）；(3) 利益率只有兩點，增量利益率 48% 偏高時 FY2027 以後高估；(4) 機器人營收與利益率全為 Assumed；(5) C 情境泰瑞達份額上升是與 Advantest 互補的結果，與「C 最不利」的公司變數方向相反（見 README）；(6) 模型為 GAAP，共識為 non-GAAP。
A14: 本版未做先驗，無 Andy 合理 P/E 對照。
A15: 估值 v2（2026-10-25）：Val 頁「0. 目標價」＝0.5 × DCF 目標價（FY2027–32 明確期＋永續，情境權重 A 0.3／B 0.5／C 0.2，情境價值下限 0）＋0.5 × Comparable 目標價；另列 Comparable 單獨目標價、市場共識目標價與差距拆解、歷史分位檢查。規則值情境加權保留為參考，不叫目標價。
... A17: v0.1.1（2026-10-25）：補上檔空間級距、投資建議、重點觀察（數值不變）。Val 頁末新增「上檔空間級距」「投資建議」兩列（Andy 2026-10-25 14:00、14:17 固定規則），README 頁末新增投資建議與重點觀察三點；既有儲存格位置與數值不變。
A18: ="投資建議："&Val!B138&"（依上檔空間固定規則）" -> 投資建議：中立（依上檔空間固定規則）
A19: 重點觀察 1：目標價 US$312（DCF 219、Comparable 405 各半），比現價 308.85（2026-10-23）高 1.1%，級距 0%–25%；Comparable 單獨為 +31.2%。兩法分歧大：同業（Advantest、KLA、Cohu、FormFactor、應用材料）前瞻 P/E 中位數 28.2 倍 × 12 個月後前瞻 EPS 14.38 得 405，DCF 只有 219（比現價低 29.0%）；本模型前瞻 EPS 比共識 FY2027 EPS 11.30 高 27.3%（期間約早一年），共識目標價 446.47 隱含 39.5 倍。
A20: 重點觀察 2：EPS 偏高的來源是測試機市場：整份取自 Advantest 模型，CY2027 比 CY2026 高約四成，高於泰瑞達自己說的測試對 WFE 比；SoC 測試機市場 −15% 時 FY2027 EPS −14.0%，SoC 市占 ±5pt 時 ±14.9%（Sens 頁）。
A21: 重點觀察 3：情境 B、C 從 FY2028 起分歧：FY2028 EPS A／B／C 為 16.61／14.15／12.31，DCF 價格帶 154～286。下一個檢驗點是 3Q26 財報（2026-10-27 盤後；建置日尚未公布、未納入）。

Sheet In
A1: In — 輸入（藍字；基準欄 E，低 D、高 F）。金額：百萬美元（US$M），市場規模為十億美元（US$B）。每個輸入附兩個來源（來源2 找不到者寫「未找到」）；公司 SEC 原文算一個
A2: 標記：Verified／Interested-party／Analogy／Assumed／Derived；Analogy、Assumed 給低／高區間。SemiAnalysis 未使用。公司原文（SEC 8-K 新聞稿、10-Q、10-K）在建置環境可開啟
A3: 鍵 | B3: 項目 | C3: 單位 | D3: 低 | E3: 基準 | F3: 高 | G3: 標記 | H3: 來源1 | I3: 來源2／說明
A4: A. 測試機市場（讀 Advantest 模型成品；與 Advantest 同一份市場，不另估）
A5: mk_soc25 | B5: SoC 測試機市場 CY2025 | C5: US$B | E5: 6.9 | G5: Interested-party | H5: advantest/dist/20261025_Advantest模型_v0.3.xlsx｜In!E45 | I5: Advantest（測試機廠）自估；與 Advantest 模型同一值
A6: mk_mem25 | B6: 記憶體測試機市場 CY2025 | C6: US$B | E6: 2.1 | G6: Interested-party | H6: advantest/dist/20261025_Advantest模型_v0.3.xlsx｜In!E46 | I6: 同上
A7: ms_A_2026 | B7: SoC 測試機市場 CY2026（A） | C7: US$B | E7: 11 | G7: Derived | H7: advantest/dist/20261025_Advantest模型_v0.3.xlsx｜PL!C47:F47 | I7: Advantest 模型：加速器顆數（markets/memory UNITS）× 每顆測試時間 × 每加權顆支出（以 CY2026 公司市場規模校準）＋非 AI；情境係數讀台積電模型
A8: ms_A_2027 | B8: SoC 測試機市場 CY2027（A） | C8: US$B | E8: 15.414358 | G8: Derived | H8: 同上 | I8: 同上
A9: ms_A_2028 | B9: SoC 測試機市場 CY2028（A） | C9: US$B | E9: 17.299184 | G9: Derived | H9: 同上 | I9: 同上
A10: ms_A_2029 | B10: SoC 測試機市場 CY2029（A） | C10: US$B | E10: 19.236176 | G10: Derived | H10: 同上 | I10: 同上
A11: ms_B_2026 | B11: SoC 測試機市場 CY2026（B） | C11: US$B | E11: 11 | G11: Derived | H11: advantest/dist/20261025_Advantest模型_v0.3.xlsx｜PL!C76:F76 | I11: 同上
A12: ms_B_2027 | B12: SoC 測試機市場 CY2027（B） | C12: US$B | E12: 15.414358 | G12: Derived | H12: 同上 | I12: 同上
A13: ms_B_2028 | B13: SoC 測試機市場 CY2028（B） | C13: US$B | E13: 14.769523 | G13: Derived | H13: 同上 | I13: 同上
A14: ms_B_2029 | B14: SoC 測試機市場 CY2029（B） | C14: US$B | E14: 17.076287 | G14: Derived | H14: 同上 | I14: 同上
A15: ms_C_2026 | B15: SoC 測試機市場 CY2026（C） | C15: US$B | E15: 11 | G15: Derived | H15: advantest/dist/20261025_Advantest模型_v0.3.xlsx｜PL!C105:F105 | I15: 同上
A16: ms_C_2027 | B16: SoC 測試機市場 CY2027（C） | C16: US$B | E16: 15.414358 | G16: Derived | H16: 同上 | I16: 同上
... A63: wfe_C_2029 | B63: 晶圓前段設備（WFE）CY2029（C） | C63: US$B | E63: 154.23638 | G63: Derived | H63: 同上 | I63: 同上
A64: B. 泰瑞達市占（FY2026 錨點推得；A、B 情境維持，C 情境與 Advantest 互補）
A65: s_soc | B65: 泰瑞達 SoC 測試機市占（FY2026 錨點 SoC 營收 ÷ CY2026 市場） | C65: % | D65: =s_soc-0.05 -> 0.24539273 | E65: =f26_soc/(ms_A_2026*1000) -> 0.29539273 | F65: =s_soc+0.05 -> 0.34539273 | G65: Derived | H65: Q 頁 FY2026 錨點 SoC 營收 ÷ Advantest 模型 CY2026 SoC 市場 11.0 | I65: 低／高＝±5 個百分點（Assumed）。分析師在 2Q26 法說估泰瑞達測試份額約 37%（公司未證實；口徑不同）
A66: s_mem | B66: 泰瑞達記憶體測試機市占（FY2026 錨點 ÷ CY2026 市場） | C66: % | D66: =s_mem-0.05 -> 0.26675636 | E66: =f26_mem/(mm_A_2026*1000) -> 0.31675636 | F66: =s_mem+0.05 -> 0.36675636 | G66: Derived | H66: Q 頁 FY2026 錨點記憶體營收 ÷ Advantest 模型 CY2026 記憶體市場 2.75 | I66: FY2025 隱含 24.0%（504.9 ÷ 2,100）；2Q26 公司：DRAM 強、NAND 最終測試回溫，記憶體營收創新高
A67: adv_sh26 | B67: Advantest SoC 市占 FY2026（三情境相同；互補計算的基準） | C67: % | E67: =as_A_2026 -> 0.66 | G67: Derived | H67: In 頁 as_A_2026 | I67: C 情境泰瑞達市占＝s_soc＋(adv_sh26 − Advantest 當年市占)，使兩家合計與其他廠份額不變
A68: C. FY2026 錨點（上半年實績＋下半年＝2 × 3Q26 指引中點；三情境相同）
A69: q3_rev | B69: 3Q26 營收指引中點（1,200–1,300） | C69: US$M | D69: 1200 | E69: 1250 | F69: 1300 | G69: Interested-party | H69: 公司 2Q26 新聞稿（8-K，2026-07-28）：3Q26 營收 1,200–1,300 | I69: earningswhispers 2Q26 逐字稿摘要；公司稱上半年約占全年 50–52%
A70: q3_eps | B70: 3Q26 GAAP 稀釋 EPS 指引中點（1.79–2.09） | C70: US$ | D70: 1.79 | E70: 1.94 | F70: 2.09 | G70: Interested-party | H70: 同上：GAAP 1.79–2.09；non-GAAP 1.85–2.15 | I70: MarketBeat 共識 3Q26 EPS 2.08（non-GAAP）
A71: q4_eq_q3 | B71: 4Q26 ÷ 3Q26（營收與 EPS） | C71: x | D71: 0.95 | E71: 1 | F71: 1.1 | G71: Assumed | H71: 無：公司未給 4Q26 指引；2Q26 法說稱下半年營業費用 4Q 與 3Q 相當、上半年占全年 50–52% | I71: 基準 1.0 → 全年營收約 5,111（上半 2,611 ÷ 5,111＝51.1%，在公司 50–52% 之內）
A72: h2g | B72: 下半年非 SoC 事業（記憶體、IST、Product Test、機器人）÷ 上半年 − 1 | C72: % | D72: 0 | E72: 0.1 | F72: 0.2 | G72: Assumed | H72: 公司 2Q26 法說：下半年記憶體、車用工業、IST、Product Test、機器人成長，行動與運算的訂單時點偏弱（earningswhispers 摘要） | I72: SoC＝下半年營收 − 非 SoC（殘差，Derived）
A73: rob_h2 | B73: 下半年機器人稅前利益 | C73: US$M | D73: -10 | E73: 0 | F73: 10 | G73: Assumed | H73: 公司目標 2026 年機器人損益兩平（4Q25 法說，fintool 摘要）；上半年 −3.5 | I73: —
A74: D. 其他事業（前一年 × 成長率；機器人不隨 AI 情境）
A75: g_pt_A | B75: Product Test 年成長 FY2027–29（A） | C75: % | D75: 0.04 | E75: 0.08 | F75: 0.12 | G75: Assumed | H75: FY2025 +8.1%（331.1→358.0，10-K）；2Q26 +26%（AI 相關與國防航太） | I75: —
A76: g_pt_B | B76: Product Test 年成長 FY2027–29（B） | C76: % | D76: 0.01 | E76: 0.05 | F76: 0.09 | G76: Assumed | H76: FY2025 +8.1%（331.1→358.0，10-K）；2Q26 +26%（AI 相關與國防航太） | I76: —
A77: g_pt_C | B77: Product Test 年成長 FY2027–29（C） | C77: % | D77: -0.02 | E77: 0.02 | F77: 0.06 | G77: Assumed | H77: FY2025 +8.1%（331.1→358.0，10-K）；2Q26 +26%（AI 相關與國防航太） | I77: —
A78: g_rob | B78: 機器人營收年成長 FY2027–29（三情境相同） | C78: % | D78: 0 | E78: 0.1 | F78: 0.2 | G78: Assumed | H78: 公司 2Q26：中期機器人隨公司整體成長；FY2025 −15.5%（364.8→308.3，10-K）、2Q26 +33% | I78: 機器人另列，不隨 AI 情境
A79: rm_2027 | B79: 機器人稅前利益率 FY2027 | C79: % | D79: -0.05 | E79: 0.02 | F79: 0.07 | G79: Assumed | H79: FY2025 −32.2%（−99.4 ÷ 308.3，含重組）；上半年 FY2026 −1.8%（−3.5 ÷ 191.2） | I79: 公司目標 2026 年兩平（Interested-party）
A80: rm_2028 | B80: 機器人稅前利益率 FY2028 | C80: % | D80: -0.03 | E80: 0.04 | F80: 0.09 | G80: Assumed | H80: FY2025 −32.2%（−99.4 ÷ 308.3，含重組）；上半年 FY2026 −1.8%（−3.5 ÷ 191.2） | I80: 公司目標 2026 年兩平（Interested-party）
A81: rm_2029 | B81: 機器人稅前利益率 FY2029 | C81: % | D81: -0.02 | E81: 0.05 | F81: 0.1 | G81: Assumed | H81: FY2025 −32.2%（−99.4 ÷ 308.3，含重組）；上半年 FY2026 −1.8%（−3.5 ÷ 191.2） | I81: 公司目標 2026 年兩平（Interested-party）
A82: E. 獲利結構（兩點推導：FY2025 實績與 FY2026 錨點；不寫死利益率）
A83: t_inc | B83: 測試事業（半導體測試＋Product Test）增量稅前利益率 | C83: % | D83: 0.4 | E83: =(f26_ttest-a25_ttest)/(f26_rtest-a25_rtest) -> 0.48265623 | F83: 0.56 | G83: Derived | H83: （FY2026 錨點測試稅前 − FY2025）÷（營收差）；Q 頁 | I83: 低／高 Assumed（固定成本重新推導，使 FY2026 錨點不變）
A84: t_fix | B84: 測試事業固定成本（＝增量利益率 × FY2026 營收 − FY2026 稅前） | C84: US$M | D84: =t_inc_lo*f26_rtest-f26_ttest -> 240.20126 | E84: =t_inc*f26_rtest-f26_ttest -> 629.51873 | F84: =t_inc_hi*f26_rtest-f26_ttest -> 993.81406 | G84: Derived | H84: 同上 | I84: 以 FY2026 錨點定錨（與 FY2025 兩點同一直線）
A85: corp | B85: 公司與沖銷（利息、匯兌、併購費用等）每年 | C85: US$M | E85: =f26_corp -> -10.4 | G85: Derived | H85: FY2026 錨點（上半年 −5.2 × 2） | I85: FY2025 −8.8（10-K）
A86: etr | B86: 有效稅率 | C86: % | D86: 0.12 | E86: =h1_tax/h1_pt -> 0.1417574 | F86: 0.17 | G86: Derived | H86: 上半年 FY2026：128.9 ÷ 909.3（10-Q） | I86: FY2025 12.1%；2Q26 15.1%
A87: aff | B87: 權益法投資損益（Technoprobe，含投資攤銷）每年 | C87: US$M | E87: =2*h1_aff -> -13.2 | G87: Derived | H87: 上半年 FY2026 −6.6 × 2（10-Q） | I87: FY2025 −19.9
A88: sh26 | B88: 稀釋股數 FY2026 | C88: 百萬股 | E88: 157.7 | G88: Verified | H88: 公司 2Q26 新聞稿：2Q26 稀釋加權股數 157.7 | I88: stockanalysis：流通股 156.34（2026-10-24）
A89: bb | B89: 稀釋股數每年減少（回購） | C89: % | D89: 0 | E89: 0.01 | F89: 0.02 | G89: Assumed | H89: FY2024→FY2025 −2.2%（163.3→159.7）、FY2025→2Q26 −1.3% | I89: 上半年 FY2026 回購僅 74.2（FY2025 702.1）
A90: gm_adj_C28 | B90: 情境 C：FY2028 測試事業利益率額外調整（價格競爭） | C90: pt | D90: -0.04 | E90: -0.01 | F90: 0 | G90: Assumed | H90: advantest/dist/20261025_Advantest模型_v0.3.xlsx｜In!E114 | I90: 與 Advantest 情境 C 毛利率調整同值（兩家同受價格競爭）
A91: gm_adj_C29 | B91: 情境 C：FY2029 測試事業利益率額外調整 | C91: pt | D91: -0.06 | E91: -0.02 | F91: 0 | G91: Assumed | H91: advantest/dist/20261025_Advantest模型_v0.3.xlsx｜In!E115 | I91: 同上
A92: m_soc | B92: SoC 測試機市場乘數（2027 起；Sens 用） | C92: x | D92: 0.85 | E92: 1 | F92: 1 | G92: Assumed | H92: 基準 1.0＝Advantest 模型市場；低 0.85＝測試對 WFE 比回到公司說的 7–9%（見 Recon） | I92: —
A93: F. 公司指引、目標模型與共識（只作對帳）
A94: h1sh_lo | B94: 上半年占全年營收：下緣 | C94: % | E94: 0.5 | G94: Interested-party | H94: 公司 2Q26 法說：上半年約占 50–52%（earningswhispers 摘要） | I94: 第二來源：未找到
A95: h1sh_hi | B95: 上半年占全年營收：上緣 | C95: % | E95: 0.52 | G95: Interested-party | H95: 同上 | I95: —
A96: cons_rev26 | B96: 共識營收 FY2026 | C96: US$M | E96: 5100 | G96: Interested-party | H96: stockanalysis：US$5.1B（16 位分析師，資料更新 2026-10-20） | I96: 第二來源：MarketBeat 3Q26 共識營收 1.26B（單季）
A97: cons_eps26 | B97: 共識 EPS FY2026（non-GAAP） | C97: US$ | E97: 9.09 | G97: Interested-party | H97: stockanalysis：9.09（區間 8.82–9.35；2026-10-20） | I97: MarketBeat：9.11
A98: cons_eps27 | B98: 共識 EPS FY2027（non-GAAP） | C98: US$ | E98: 11.3 | G98: Interested-party | H98: MarketBeat（2026-10-20）：11.30 | I98: stockanalysis 需付費，未取得
A99: tm_rev | B99: 公司目標模型：營收（ATE 市場 US$12–14B 時，未給年度） | C99: US$M | E99: 6000 | G99: Interested-party | H99: 公司 4Q25 法說（2026-02-03，fintool 摘要）：營收 6.0B、營業利益率 30–34%、non-GAAP EPS 9.50–11.00 | I99: 公司稱 4Q26 法說更新目標模型
A100: tm_eps_lo | B100: 公司目標模型：non-GAAP EPS 下緣 | C100: US$ | E100: 9.5 | G100: Interested-party | H100: 同上 | I100: —
A101: tm_eps_hi | B101: 公司目標模型：non-GAAP EPS 上緣 | C101: US$ | E101: 11 | G101: Interested-party | H101: 同上 | I101: —
A102: tw_lo | B102: 公司：測試對 WFE 比長期區間 下緣 | C102: % | E102: 0.07 | G102: Interested-party | H102: 公司 2Q26 法說：2023 約 4%、2025 約 7%、2026 前五月約 8%；長期 7–9%，2027 可能回到 7%（earningswhispers） | I102: gurufocus 2Q26 摘要（同數字）
A103: tw_hi | B103: 公司：測試對 WFE 比長期區間 上緣 | C103: % | E103: 0.09 | G103: Interested-party | H103: 同上 | I103: —
A104: an_share | B104: 分析師估泰瑞達測試份額（2Q26 法說提問） | C104: % | E104: 0.37 | G104: Interested-party | H104: earningswhispers 2Q26 逐字稿摘要：分析師估約 37%，公司未證實 | I104: 口徑未明（可能為 SoC 或 ATE 合計）
A105: pk_A | B105: 情境 A：設備市場見頂年度（日曆年；循環位置規則用） | C105: 年 | E105: 2029 | G105: Derived | H105: markets/equipment/dist/20261023_半導體設備市場模型_v0.1.3.xlsx｜Mkt!C12 | I105: 設備股共用規則（tools/cycle_position.py）：FY(t) 早於見頂年＝中段、等於＝見頂、晚於＝谷底；泰瑞達會計年度＝日曆年
... A109: sa_fpe | B109: 遠期 P/E（stockanalysis，2026-10-23 價格） | C109: x | E109: 32.52 | G109: Interested-party | H109: stockanalysis statistics（2026-10-24 更新） | I109: 自算見 Val
A110: I. 規則值情境權重（Val 頁「舊法：規則值情境加權（參考）」與目標價 DCF 共用；Andy 可改）
A111: tp_wA | B111: 目標價情境權重 A | C111: % | E111: 0.3 | G111: Assumed | H111: Andy 可改（工作單 2026-10-25 預設 A 0.3／B 0.5／C 0.2） | I111: 三者合計應為 100%
A112: tp_wB | B112: 目標價情境權重 B | C112: % | E112: 0.5 | G112: Assumed | H112: Andy 可改（工作單 2026-10-25 預設 A 0.3／B 0.5／C 0.2） | I112: 三者合計應為 100%
A113: tp_wC | B113: 目標價情境權重 C | C113: % | E113: 0.2 | G113: Assumed | H113: Andy 可改（工作單 2026-10-25 預設 A 0.3／B 0.5／C 0.2） | I113: 三者合計應為 100%
A115: J. 目標價（DCF 與 Comparable 加權）與 FY2030–32 收斂法參數（黃底＝Assumed，Andy 可改）
A116: tp_r | B116: 折現率（股東權益要求報酬；美、台、日、韓同一值） | C116: % | E116: 0.1 | G116: Assumed | H116: Andy 可改（工作單 2026-10-25 預設 10%） | I116: β 約 1.75（MarketBeat）高於市場，但依工作單不改值
A117: tp_g | B117: 長期成長率（永續成長；收斂法 FY2032 營收年增的基準） | C117: % | E117: 0.04 | G117: Assumed | H117: Andy 可改（工作單預設 4%） | I117: 情境 A＝tp_g＋2pt、B＝tp_g、C＝tp_g−2pt（PL 頁延伸區塊）
A118: tp_roe | B118: ROE（近三年平均，FY2023–FY2025） | C118: % | E118: =AVERAGE(Val!E14/AVERAGE(Val!G13:G14),Val!E15/AVERAGE(Val!G14:G15),Val!E16/AVERAGE(Val!G15:G16)) -> 0.19353862 | G118: Derived | H118: SEC XBRL（10-K）：淨利 ÷ 平均股東權益：FY2023 18.0%、FY2024 20.3%、FY2025 19.7%（Val 頁第 1 節） | I118: stockanalysis 近 12 月 ROE 36.46%（AI 期間，非三年平均）
A119: tp_w_dcf | B119: 目標價中 DCF 的權重；其餘為 Comparable | C119: % | E119: 0.5 | G119: Assumed | H119: Andy 可改（2026-10-25 11:53：DCF／Comparable 各半） | I119: —
A120: nim10 | B120: 十年平均淨利率（FY2016–FY2025，各年淨利 ÷ 營收的平均） | C120: % | E120: =AVERAGE(Val!E7/Val!F7,Val!E8/Val!F8,Val!E9/Val!F9,Val!E10/Val!F10,Val!E11/Val!F11,Val!E12/Val!F12,Val!E13/Val!F13,Val!E14/Val!F14,Val!E15/Val!F15,Val!E16/Val!F16) -> 0.18003103 | G120: Derived | H120: SEC XBRL（10-K）淨利 ÷ 營收（Val 頁第 1 節；含 FY2016 虧損） | I120: macrotrends EPS 逐年相同（第二來源）
A121: cons_tp | B121: 市場共識目標價（賣方平均） | C121: US$ | E121: 446.47 | G121: Interested-party | H121: stockanalysis：17 位分析師平均 US$446.47（中位數 450；區間 350–550），資料更新 2026-10-20 | I121: MarketBeat：396.80（11 買進、5 持有）；早於 2026-10-27 的 3Q26 財報
A122: cons_feps | B122: 共識前瞻 EPS（差距拆解用） | C122: US$ | E122: =cons_eps27 -> 11.3 | G122: Interested-party | H122: 共識前瞻 EPS＝MarketBeat FY2027 共識 11.30（non-GAAP）；比本模型 12 個月後前瞻 EPS（約 FY2028）早約一年，且為 non-GAAP，EPS 因素因此偏大 | I122: Interested-party

Sheet Q
A1: Q — 實績（百萬美元；EPS 為美元，GAAP 稀釋）。會計年度＝日曆年。藍字＝輸入（SEC 8-K 新聞稿、10-Q、10-K）；黑字＝公式（Derived）
A2: 3Q26（2026-07～09）：預定 2026-10-27 美東 16:30 盤後公布（公司公告），建置日 2026-10-25 尚未公布，故不納入；FY2026 下半年以 3Q26 指引中點推估（見下方錨點）。公布後更新本頁 I 欄與 In 頁 C 節
A3: 項目 | B3: 1Q25 | C3: 2Q25 | D3: 3Q25 | E3: 4Q25 | F3: FY2025 | G3: 1Q26 | H3: 2Q26 | I3: 3Q26（未公布） | J3: 上半年 FY2026 | K3: 標記 | L3: 來源1（公司 SEC 文件） | M3: 來源2／說明
A4: SoC 測試機（System on-a-Chip） | B4: 406.4 | C4: 396.6 | D4: 440.2 | E4: =F4-SUM(B4:D4) -> 646.5 | F4: 1889.7 | G4: =J4-H4 -> 881.8 | H4: 843 | I4: 預定 2026-10-27 盤後公布，尚未公布 | J4: 1724.8 | K4: Verified／Derived | L4: 10-Q／10-K 收入拆分表（Disaggregation of Revenue）：2Q25 396.6、3Q25 440.2、FY2025 1,889.7、2Q26 843.0、上半年 1,724.8；1Q25＝上半年 803.0 − 2Q25 | M4: gurufocus 2Q26 法說摘要：SoC 843、記憶體 212、IST 67
A5: 記憶體測試機 | B5: 109.4 | C5: 60.9 | D5: 128.1 | E5: =F5-SUM(B5:D5) -> 206.5 | F5: 504.9 | G5: =J5-H5 -> 202.5 | H5: 212.3 | J5: 414.8 | K5: Verified／Derived | L5: 10-Q／10-K 收入拆分表（Disaggregation of Revenue）：1Q25＝上半年 170.4 − 2Q25；4Q25＝全年 − 前三季 | M5: 同上（記憶體 212，創新高）
A6: IST（整合系統測試） | B6: 26.7 | C6: 34.3 | D6: 37.6 | E6: =F6-SUM(B6:D6) -> 30.6 | F6: 129.2 | G6: =J6-H6 -> 26.6 | H6: 66.5 | J6: 93.1 | K6: Verified／Derived | L6: 10-Q／10-K 收入拆分表（Disaggregation of Revenue） | M6: 同上（IST 67，+94%）
A7: 半導體測試（SoC＋記憶體＋IST） | B7: =B4+B5+B6 -> 542.5 | C7: =C4+C5+C6 -> 491.8 | D7: =D4+D5+D6 -> 605.9 | E7: =E4+E5+E6 -> 883.6 | F7: =F4+F5+F6 -> 2523.8 | G7: =G4+G5+G6 -> 1110.9 | H7: =H4+H5+H6 -> 1121.8 | J7: =J4+J5+J6 -> 2232.7 | K7: Derived | L7: 公司新聞稿：1Q25 543、2Q25 492、3Q25 606、4Q25 883、1Q26 1,111、2Q26 1,122；FY2025 2,523.7（10-K） | M7: 檢查列見下
A8: Product Test | B8: 74.2 | C8: 85.1 | D8: 88.3 | E8: =F8-SUM(B8:D8) -> 110.4 | F8: 358 | G8: =J8-H8 -> 80.5 | H8: 107.2 | J8: 187.7 | K8: Verified／Derived | L8: 公司各季新聞稿（8-K Ex.99.1）與 10-K（FY2025 358.0） | M8: MD&A 各季比較表
A9: 機器人（Robotics） | B9: 69 | C9: 74.9 | D9: 75.1 | E9: =F9-SUM(B9:D9) -> 89.3 | F9: 308.3 | G9: =J9-H9 -> 91.3 | H9: 99.9 | J9: 191.2 | K9: Verified／Derived | L9: 公司各季新聞稿（8-K Ex.99.1）與 10-K（FY2025 308.3） | M9: MD&A 各季比較表
A10: 營收 | B10: 685.7 | C10: 651.8 | D10: 769.2 | E10: 1083.3 | F10: 3190 | G10: 1282.5 | H10: 1329 | J10: 2611.5 | K10: Verified | L10: 公司各季新聞稿（8-K Ex.99.1）：FY2025 3,190.0（+13%）；2Q26 1,329.0（+104%） | M10: stockanalysis／MarketBeat（2Q26 1.33B）
A11: 檢查：半導體測試＋Product Test＋機器人 − 營收（應約為 0；單季分項四捨五入） | B11: =B7+B8+B9-B10 -> 0 | C11: =C7+C8+C9-C10 -> 0 | D11: =D7+D8+D9-D10 -> 0.1 | E11: =E7+E8+E9-E10 -> 0 | F11: =F7+F8+F9-F10 -> 0.1 | G11: =G7+G8+G9-G10 -> 0.2 | H11: =H7+H8+H9-H10 -> -0.1 | J11: =J7+J8+J9-J10 -> 0.1 | K11: — | L11: — | M11: —
A12: 毛利 | B12: 415.3 | C12: 373 | D12: 449.3 | E12: 619.7 | F12: 1857.3 | G12: 780.9 | H12: 794.6 | J12: 1575.6 | K12: Verified | L12: 公司各季新聞稿（8-K Ex.99.1） | M12: —
A13: 毛利率 | B13: =B12/B10 -> 0.60565845 | C13: =C12/C10 -> 0.57226143 | D13: =D12/D10 -> 0.58411336 | E13: =E12/E10 -> 0.57204837 | F13: =F12/F10 -> 0.58222571 | G13: =G12/G10 -> 0.60888889 | H13: =H12/H10 -> 0.59789315 | J13: =J12/J10 -> 0.60333142 | K13: Derived | L13: — | M13: 公司：FY2025 58.3%（non-GAAP）；3Q26 指引 58–59%；全年約 59%（2Q26 法說）
A14: 營業利益（GAAP） | B14: 120.8 | C14: 90.7 | D14: 145.3 | E14: 293.2 | F14: 650.1 | G14: 473 | H14: 437.8 | J14: 910.8 | K14: Verified／Derived | L14: 公司各季新聞稿（8-K Ex.99.1）：1Q25＝上半年 211.5 − 2Q25 | M14: —
A15: 稅前利益（含權益法前） | B15: 119 | C15: 96.6 | D15: 148.1 | E15: 289.6 | F15: 653.3 | G15: 465.7 | H15: 443.6 | J15: 909.3 | K15: Verified／Derived | L15: 公司各季新聞稿（8-K Ex.99.1）：1Q25＝上半年 215.6 − 2Q25 | M15: —
A16: 所得稅 | B16: 14.5 | C16: 12.3 | D16: 23.3 | E16: 29.2 | F16: 79.3 | G16: 62.2 | H16: 66.8 | J16: 128.9 | K16: Verified／Derived | L16: 公司各季新聞稿（8-K Ex.99.1） | M16: —
A17: 權益法投資損益（Technoprobe） | B17: -5.6 | C17: -5.9 | D17: -5.2 | E17: -3.2 | F17: -19.9 | G17: -4.6 | H17: -1.9 | J17: -6.6 | K17: Verified／Derived | L17: 公司各季新聞稿（8-K Ex.99.1） | M17: —
A18: 淨利（歸屬泰瑞達） | B18: 98.9 | C18: 78.4 | D18: 119.6 | E18: 257.2 | F18: 554 | G18: 398.9 | H18: 374.5 | J18: 773.4 | K18: Verified | L18: 公司各季新聞稿（8-K Ex.99.1） | M18: —
A19: EPS（GAAP 稀釋） | B19: 0.61 | C19: 0.49 | D19: 0.75 | E19: 1.63 | F19: 3.47 | G19: 2.53 | H19: 2.38 | J19: 4.91 | K19: Verified | L19: 公司各季新聞稿（8-K Ex.99.1）（四季加總 3.48 與全年 3.47 差為股數加權） | M19: macrotrends 年度 EPS（FY2024 3.32 等）
A20: 稀釋加權股數（百萬股） | B20: 162 | C20: 160.1 | D20: 159.1 | E20: 157.7 | F20: 159.7 | G20: 157.6 | H20: 157.7 | J20: 157.7 | K20: Verified | L20: 公司各季新聞稿（8-K Ex.99.1） | M20: —
A22: 事業別稅前利益（10-K／10-Q 分部資訊；機器人另列）
A23: 事業 | B23: FY2024 | C23: FY2025 | D23: 上半年 FY2026 | E23: 2Q26 | K23: 標記 | L23: 來源1 | M23: 來源2／說明
A24: 半導體測試 | B24: 558.2 | C24: 700.7 | D24: 895.4 | E24: 427.3 | K24: Verified | L24: 10-K FY2025、10-Q 2Q26：Income (Loss) Before Income Taxes 分部表 | M24: FY2024 公司與沖銷含出售 DIS 事業利益 57.1
A25: Product Test | B25: 65.7 | C25: 60.7 | D25: 22.7 | E25: 18 | K25: Verified | L25: 10-K FY2025、10-Q 2Q26：Income (Loss) Before Income Taxes 分部表 | M25: FY2024 公司與沖銷含出售 DIS 事業利益 57.1
A26: 機器人 | B26: -77.6 | C26: -99.4 | D26: -3.5 | E26: -2.6 | K26: Verified | L26: 10-K FY2025、10-Q 2Q26：Income (Loss) Before Income Taxes 分部表 | M26: FY2024 公司與沖銷含出售 DIS 事業利益 57.1
A27: 公司與沖銷 | B27: 62.7 | C27: -8.8 | D27: -5.2 | E27: 0.9 | K27: Verified | L27: 10-K FY2025、10-Q 2Q26：Income (Loss) Before Income Taxes 分部表 | M27: FY2024 公司與沖銷含出售 DIS 事業利益 57.1
A28: 合計（應＝稅前利益） | B28: =SUM(B24:B27) -> 609 | C28: =SUM(C24:C27) -> 653.2 | D28: =SUM(D24:D27) -> 909.4 | E28: =SUM(E24:E27) -> 443.6 | M28: FY2025 應＝653.3；上半年應＝909.3（四捨五入差）
A30: FY2026 錨點（上半年實績＋下半年推估；三情境相同）
A31: 項目 | B31: 上半年（實績） | C31: 下半年（推估） | D31: FY2026 | K31: 標記 | L31: 說明
A32: SoC 測試機 | B32: =J4 -> 1724.8 | C32: =C40-C33-C34-C35-C36 -> 1524.52 | D32: =B32+C32 -> 3249.32 | L32: Derived：下半年營收 − 非 SoC 事業（殘差）
A33: 記憶體測試機 | B33: =J5 -> 414.8 | C33: =B33*(1+h2g) -> 456.28 | D33: =B33+C33 -> 871.08 | L33: 上半年 × (1＋h2g)
A34: IST | B34: =J6 -> 93.1 | C34: =B34*(1+h2g) -> 102.41 | D34: =B34+C34 -> 195.51 | L34: 同上
A35: Product Test | B35: =J8 -> 187.7 | C35: =B35*(1+h2g) -> 206.47 | D35: =B35+C35 -> 394.17 | L35: 同上
A36: 機器人 | B36: =J9 -> 191.2 | C36: =B36*(1+h2g) -> 210.32 | D36: =B36+C36 -> 401.52 | L36: 同上；不隨 AI 情境
A37: 測試事業營收（半導體測試＋Product Test） | B37: =B32+B33+B34+B35 -> 2420.4 | C37: =C32+C33+C34+C35 -> 2289.68 | D37: =B37+C37 -> 4710.08
A38: （保留）
A39: 營收：下半年＝3Q26 指引中點 ×（1＋4Q÷3Q） | C39: =q3_rev*(1+q4_eq_q3) -> 2500 | L39: Interested-party（指引）＋Assumed（4Q＝3Q）
A40: 營收 | B40: =J10 -> 2611.5 | C40: =C39 -> 2500 | D40: =B40+C40 -> 5111.5
A41: 上半年占全年（公司 50–52%） | D41: =B40/D40 -> 0.51090678
A42: 淨利（下半年＝3Q26 GAAP EPS 指引中點 ×（1＋4Q÷3Q）× 稀釋股數） | B42: =J18 -> 773.4 | C42: =q3_eps*(1+q4_eq_q3)*sh26 -> 611.876 | D42: =B42+C42 -> 1385.276
A43: 權益法投資損益（下半年＝上半年） | B43: =J17 -> -6.6 | C43: =B43 -> -6.6 | D43: =B43+C43 -> -13.2
A44: 稅前利益（下半年＝（淨利 − 權益法）÷（1 − 稅率）） | B44: =J15 -> 909.3 | C44: =(C42-C43)/(1-etr) -> 720.63074 | D44: =B44+C44 -> 1629.9307
A45: 所得稅 | B45: =J16 -> 128.9 | C45: =C44*etr -> 102.15474 | D45: =B45+C45 -> 231.05474
A46: 機器人稅前利益 | B46: =D26 -> -3.5 | C46: =rob_h2 -> 0 | D46: =B46+C46 -> -3.5
A47: 公司與沖銷（下半年＝上半年） | B47: =D27 -> -5.2 | C47: =B47 -> -5.2 | D47: =B47+C47 -> -10.4
A48: 測試事業稅前利益（稅前 − 機器人 − 公司與沖銷） | B48: =B44-B46-B47 -> 918 | C48: =C44-C46-C47 -> 725.83074 | D48: =B48+C48 -> 1643.8307
A49: EPS（GAAP 稀釋） | D49: =D42/sh26 -> 8.7842486
A50: 毛利率（上半年實績；下半年＝3Q26 指引中點 58.5%，全年約 59%） | B50: =J13 -> 0.60333142 | C50: 0.585 | D50: =(B40*B50+C40*C50)/D40 -> 0.59436565
A51: 對照：FY2025 測試事業營收、測試事業稅前利益（10-K） | B51: =F7+F8 -> 2881.8 | C51: =C24+C25 -> 761.4
A52: 上半年 FY2026：稅前、所得稅、權益法（10-Q） | B52: =J15 -> 909.3 | C52: =J16 -> 128.9 | D52: =J17 -> -6.6

Sheet Units
A1: Units — 測試機市場（十億美元；日曆年；讀 Advantest 模型成品）與 SoC 市占合計。泰瑞達 A、B 情境市占維持 FY2026 水準；C 情境與 Advantest 互補（Advantest 讓出的份額全由泰瑞達取得），三情境的「其他廠」份額相同
A3: 項目 | B3: 單位 | C3: CY2025 | D3: CY2026 | E3: CY2027 | F3: CY2028 | G3: CY2029 | H3: 說明
A4: 情境 A
A5: SoC 測試機市場 | B5: US$B | C5: =mk_soc25 -> 6.9 | D5: =ms_A_2026 -> 11 | E5: =ms_A_2027 -> 15.414358 | F5: =ms_A_2028 -> 17.299184 | G5: =ms_A_2029 -> 19.236176
A6: 記憶體測試機市場 | B6: US$B | C6: =mk_mem25 -> 2.1 | D6: =mm_A_2026 -> 2.75 | E6: =mm_A_2027 -> 3.9915065 | F6: =mm_A_2028 -> 5.1706953 | G6: =mm_A_2029 -> 6.3316064
A7: Advantest SoC 市占（Advantest 模型，FY 口徑） | B7: % | C7: =as_A_2026 -> 0.66 | D7: =as_A_2026 -> 0.66 | E7: =as_A_2027 -> 0.66 | F7: =as_A_2028 -> 0.66 | G7: =as_A_2029 -> 0.66
A8: 泰瑞達 SoC 市占 | B8: % | C8: =a25_soc/(mk_soc25*1000) -> 0.27386957 | D8: =s_soc -> 0.29539273 | E8: =s_soc -> 0.29539273 | F8: =s_soc -> 0.29539273 | G8: =s_soc -> 0.29539273
A9: 其他廠 SoC 市占（1 − Advantest − 泰瑞達） | B9: % | C9: =1-C7-C8 -> 0.066130435 | D9: =1-D7-D8 -> 0.044607273 | E9: =1-E7-E8 -> 0.044607273 | F9: =1-F7-F8 -> 0.044607273 | G9: =1-G7-G8 -> 0.044607273 | H9: CY2025 用 Advantest 自估 66% 對照；三情境 CY2026 起其他廠份額相同（互補設計）
A10: SoC＋記憶體測試機市場 ÷ 晶圓前段設備（WFE） | B10: % | C10: =(mk_soc25+mk_mem25)/wfe_A_2025 -> 0.076990966 | D10: =(ms_A_2026+mm_A_2026)/wfe_A_2026 -> 0.08805238 | E10: =(ms_A_2027+mm_A_2027)/wfe_A_2027 -> 0.10065519 | F10: =(ms_A_2028+mm_A_2028)/wfe_A_2028 -> 0.10372534 | G10: =(ms_A_2029+mm_A_2029)/wfe_A_2029 -> 0.11169668 | H10: 公司說法：測試對 WFE 比 2025 約 7%、2026 約 8%，長期 7–9%（口徑為 ATE 市場，含其他測試機；見 Recon）
A12: 情境 B
A13: SoC 測試機市場 | B13: US$B | C13: =mk_soc25 -> 6.9 | D13: =ms_B_2026 -> 11 | E13: =ms_B_2027 -> 15.414358 | F13: =ms_B_2028 -> 14.769523 | G13: =ms_B_2029 -> 17.076287
A14: 記憶體測試機市場 | B14: US$B | C14: =mk_mem25 -> 2.1 | D14: =mm_B_2026 -> 2.75 | E14: =mm_B_2027 -> 3.9915065 | F14: =mm_B_2028 -> 4.8492815 | G14: =mm_B_2029 -> 5.8958345
A15: Advantest SoC 市占（Advantest 模型，FY 口徑） | B15: % | C15: =as_A_2026 -> 0.66 | D15: =as_B_2026 -> 0.66 | E15: =as_B_2027 -> 0.66 | F15: =as_B_2028 -> 0.66 | G15: =as_B_2029 -> 0.66
A16: 泰瑞達 SoC 市占 | B16: % | C16: =a25_soc/(mk_soc25*1000) -> 0.27386957 | D16: =s_soc -> 0.29539273 | E16: =s_soc -> 0.29539273 | F16: =s_soc -> 0.29539273 | G16: =s_soc -> 0.29539273
A17: 其他廠 SoC 市占（1 − Advantest − 泰瑞達） | B17: % | C17: =1-C15-C16 -> 0.066130435 | D17: =1-D15-D16 -> 0.044607273 | E17: =1-E15-E16 -> 0.044607273 | F17: =1-F15-F16 -> 0.044607273 | G17: =1-G15-G16 -> 0.044607273 | H17: CY2025 用 Advantest 自估 66% 對照；三情境 CY2026 起其他廠份額相同（互補設計）
A18: SoC＋記憶體測試機市場 ÷ 晶圓前段設備（WFE） | B18: % | C18: =(mk_soc25+mk_mem25)/wfe_B_2025 -> 0.076990966 | D18: =(ms_B_2026+mm_B_2026)/wfe_B_2026 -> 0.08805238 | E18: =(ms_B_2027+mm_B_2027)/wfe_B_2027 -> 0.10065519 | F18: =(ms_B_2028+mm_B_2028)/wfe_B_2028 -> 0.10175968 | G18: =(ms_B_2029+mm_B_2029)/wfe_B_2029 -> 0.12542401 | H18: 公司說法：測試對 WFE 比 2025 約 7%、2026 約 8%，長期 7–9%（口徑為 ATE 市場，含其他測試機；見 Recon）
A20: 情境 C
A21: SoC 測試機市場 | B21: US$B | C21: =mk_soc25 -> 6.9 | D21: =ms_C_2026 -> 11 | E21: =ms_C_2027 -> 15.414358 | F21: =ms_C_2028 -> 12.239862 | G21: =ms_C_2029 -> 13.476472
A22: 記憶體測試機市場 | B22: US$B | C22: =mk_mem25 -> 2.1 | D22: =mm_C_2026 -> 2.75 | E22: =mm_C_2027 -> 3.9915065 | F22: =mm_C_2028 -> 3.7299739 | G22: =mm_C_2029 -> 4.4025046
A23: Advantest SoC 市占（Advantest 模型，FY 口徑） | B23: % | C23: =as_A_2026 -> 0.66 | D23: =as_C_2026 -> 0.66 | E23: =as_C_2027 -> 0.66 | F23: =as_C_2028 -> 0.61 | G23: =as_C_2029 -> 0.56
A24: 泰瑞達 SoC 市占 | B24: % | C24: =a25_soc/(mk_soc25*1000) -> 0.27386957 | D24: =s_soc -> 0.29539273 | E24: =(s_soc+adv_sh26-as_C_2027) -> 0.29539273 | F24: =(s_soc+adv_sh26-as_C_2028) -> 0.34539273 | G24: =(s_soc+adv_sh26-as_C_2029) -> 0.39539273
A25: 其他廠 SoC 市占（1 − Advantest − 泰瑞達） | B25: % | C25: =1-C23-C24 -> 0.066130435 | D25: =1-D23-D24 -> 0.044607273 | E25: =1-E23-E24 -> 0.044607273 | F25: =1-F23-F24 -> 0.044607273 | G25: =1-G23-G24 -> 0.044607273 | H25: CY2025 用 Advantest 自估 66% 對照；三情境 CY2026 起其他廠份額相同（互補設計）
A26: SoC＋記憶體測試機市場 ÷ 晶圓前段設備（WFE） | B26: % | C26: =(mk_soc25+mk_mem25)/wfe_C_2025 -> 0.076990966 | D26: =(ms_C_2026+mm_C_2026)/wfe_C_2026 -> 0.08805238 | E26: =(ms_C_2027+mm_C_2027)/wfe_C_2027 -> 0.10065519 | F26: =(ms_C_2028+mm_C_2028)/wfe_C_2028 -> 0.10354131 | G26: =(ms_C_2029+mm_C_2029)/wfe_C_2029 -> 0.11591932 | H26: 公司說法：測試對 WFE 比 2025 約 7%、2026 約 8%，長期 7–9%（口徑為 ATE 市場，含其他測試機；見 Recon）

Sheet PL
A1: PL — 泰瑞達損益（US$M；FY2025 為實績，FY2026 為錨點（上半年實績＋下半年指引），FY2027–FY2029 為模型）。三情境各一個完整推導區塊（見下方），本頁頂端為摘要
A3: 情境／項目 | B3: 單位 | C3: FY2025A | D3: FY2026 | E3: FY2027 | F3: FY2028 | G3: FY2029 | H3: 說明
A4: 情境 A
A5: 營收 | B5: US$M | C5: =C61 -> 3190.1 | D5: =D61 -> 5111.6 | E5: =E61 -> 6958.9691 | F5: =F61 -> 8000.9722 | G5: =G61 -> 9060.6638
A6: SoC 測試機 | B6: US$M | C6: =C49 -> 1889.7 | D6: =D49 -> 3249.32 | E6: =E49 -> 4553.2893 | F6: =F49 -> 5110.053 | G6: =G49 -> 5682.2266
A7: 記憶體測試機 | B7: US$M | C7: =C51 -> 504.9 | D7: =D51 -> 871.08 | E7: =E51 -> 1264.3351 | F7: =F51 -> 1637.8506 | G7: =G51 -> 2005.5766
A8: 機器人（不隨 AI 情境） | B8: US$M | C8: =C58 -> 308.3 | D8: =D58 -> 401.52 | E8: =E58 -> 441.672 | F8: =F58 -> 485.8392 | G8: =G58 -> 534.42312
A9: 毛利率（參考） | B9: % | C9: =C70 -> 0.58222571 | D9: =D70 -> 0.59436565 | E9: =E70 -> 0.60014094 | F9: =F70 -> 0.5952967 | G9: =G70 -> 0.59171682
A10: 稅前利益 | B10: US$M | C10: =C62 -> 653.2 | D10: =D62 -> 1629.9307 | E10: =E62 -> 2514.5288 | F10: =F62 -> 3006.7406 | G10: =G62 -> 3502.0456
A11: 稅前利益率 | B11: % | C11: =C63 -> 0.20475847 | D11: =D63 -> 0.31886899 | E11: =E63 -> 0.36133639 | F11: =F63 -> 0.37579691 | G11: =G63 -> 0.38651093
A12: 淨利 | B12: US$M | C12: =C66 -> 554 | D12: =D66 -> 1385.276 | E12: =E66 -> 2144.8757 | F12: =F66 -> 2567.3129 | G12: =G66 -> 2992.4048
A13: EPS | B13: US$ | C13: =C68 -> 3.47 | D13: =D68 -> 8.7842486 | E13: =E68 -> 13.738371 | F13: =F68 -> 16.610271 | G13: =G68 -> 19.556136
A15: 情境 B
A16: 營收 | B16: US$M | C16: =C90 -> 3190.1 | D16: =D90 -> 5111.6 | E16: =E90 -> 6947.144 | F16: =F90 -> 7081.7702 | G16: =G90 -> 8205.986
A17: SoC 測試機 | B17: US$M | C17: =C78 -> 1889.7 | D17: =D78 -> 3249.32 | E17: =E78 -> 4553.2893 | F17: =F78 -> 4362.8097 | G17: =G78 -> 5044.211
A18: 記憶體測試機 | B18: US$M | C18: =C80 -> 504.9 | D18: =D80 -> 871.08 | E18: =E80 -> 1264.3351 | F18: =F80 -> 1536.0408 | G18: =G80 -> 1867.5431
A19: 機器人（不隨 AI 情境） | B19: US$M | C19: =C87 -> 308.3 | D19: =D87 -> 401.52 | E19: =E87 -> 441.672 | F19: =F87 -> 485.8392 | G19: =G87 -> 534.42312
A20: 毛利率（參考） | B20: % | C20: =C99 -> 0.58222571 | D20: =D99 -> 0.59436565 | E20: =E99 -> 0.60048621 | F20: =F99 -> 0.58828522 | G20: =G99 -> 0.58786265
A21: 稅前利益 | B21: US$M | C21: =C91 -> 653.2 | D21: =D91 -> 1629.9307 | E21: =E91 -> 2508.8213 | F21: =F91 -> 2563.082 | G21: =G91 -> 3089.53
A22: 稅前利益率 | B22: % | C22: =C92 -> 0.20475847 | D22: =D92 -> 0.31886899 | E22: =E92 -> 0.36112989 | F22: =F92 -> 0.36192675 | G22: =G92 -> 0.37649712
A23: 淨利 | B23: US$M | C23: =C95 -> 554 | D23: =D95 -> 1385.276 | E23: =E95 -> 2139.9774 | F23: =F95 -> 2186.5462 | G23: =G95 -> 2638.3663
A24: EPS | B24: US$ | C24: =C97 -> 3.47 | D24: =D97 -> 8.7842486 | E24: =E97 -> 13.706996 | F24: =F97 -> 14.146747 | G24: =G97 -> 17.242404
A26: 情境 C
A27: 營收 | B27: US$M | C27: =C119 -> 3190.1 | D27: =D119 -> 5111.6 | E27: =E119 -> 6935.3189 | F27: =F119 -> 6522.5329 | G27: =G119 -> 7915.2657
A28: SoC 測試機 | B28: US$M | C28: =C107 -> 1889.7 | D28: =D107 -> 3249.32 | E28: =E107 -> 4553.2893 | F28: =F107 -> 4227.5594 | G28: =G107 -> 5328.4989
A29: 記憶體測試機 | B29: US$M | C29: =C109 -> 504.9 | D29: =D109 -> 871.08 | E29: =E109 -> 1264.3351 | F29: =F109 -> 1181.493 | G29: =G109 -> 1394.5213
A30: 機器人（不隨 AI 情境） | B30: US$M | C30: =C116 -> 308.3 | D30: =D116 -> 401.52 | E30: =E116 -> 441.672 | F30: =F116 -> 485.8392 | G30: =G116 -> 534.42312
A31: 毛利率（參考） | B31: % | C31: =C128 -> 0.58222571 | D31: =D128 -> 0.59436565 | E31: =E128 -> 0.60083265 | F31: =F128 -> 0.58823182 | G31: =G128 -> 0.58599626
A32: 稅前利益 | B32: US$M | C32: =C120 -> 653.2 | D32: =D120 -> 1629.9307 | E32: =E120 -> 2503.1139 | F32: =F120 -> 2232.7957 | G32: =G120 -> 2801.5952
A33: 稅前利益率 | B33: % | C33: =C121 -> 0.20475847 | D33: =D121 -> 0.31886899 | E33: =E121 -> 0.36092268 | F33: =F121 -> 0.34232035 | G33: =G121 -> 0.35394835
A34: 淨利 | B34: US$M | C34: =C124 -> 554 | D34: =D124 -> 1385.276 | E34: =E124 -> 2135.079 | F34: =F124 -> 1903.0804 | G34: =G124 -> 2391.2484
A35: EPS | B35: US$ | C35: =C126 -> 3.47 | D35: =D126 -> 8.7842486 | E35: =E126 -> 13.675621 | F35: =F126 -> 12.31275 | G35: =G126 -> 15.627425
A37: 核對：FY2026 EPS − 錨點（應為 0） | C37: =ABS(D13-f26_eps)+ABS(D35-f26_eps) -> 0
A44: 情境 A（順利）：加速器顆數續增；市占維持
A45: 項目 | B45: 單位 | C45: FY2025A | D45: FY2026（錨點） | E45: FY2027 | F45: FY2028 | G45: FY2029 | H45: 說明
A46: SoC 測試機市場 CY（Advantest 模型） | B46: US$B | C46: =mk_soc25 -> 6.9 | D46: =ms_A_2026 -> 11 | E46: =ms_A_2027*m_soc -> 15.414358 | F46: =ms_A_2028*m_soc -> 17.299184 | G46: =ms_A_2029*m_soc -> 19.236176
A47: 記憶體測試機市場 CY（Advantest 模型） | B47: US$B | C47: =mk_mem25 -> 2.1 | D47: =mm_A_2026 -> 2.75 | E47: =mm_A_2027 -> 3.9915065 | F47: =mm_A_2028 -> 5.1706953 | G47: =mm_A_2029 -> 6.3316064
A48: 泰瑞達 SoC 市占 | B48: % | C48: =a25_soc/(C46*1000) -> 0.27386957 | D48: =f26_soc/(D46*1000) -> 0.29539273 | E48: =s_soc -> 0.29539273 | F48: =s_soc -> 0.29539273 | G48: =s_soc -> 0.29539273 | H48: FY2025、FY2026＝實績／錨點隱含；之後維持
A49: SoC 測試機營收 | B49: US$M | C49: =a25_soc -> 1889.7 | D49: =f26_soc -> 3249.32 | E49: =E46*1000*E48 -> 4553.2893 | F49: =F46*1000*F48 -> 5110.053 | G49: =G46*1000*G48 -> 5682.2266 | H49: 市場 × 市占
A50: 泰瑞達記憶體測試機市占 | B50: % | C50: =a25_mem/(C47*1000) -> 0.24042857 | D50: =f26_mem/(D47*1000) -> 0.31675636 | E50: =s_mem -> 0.31675636 | F50: =s_mem -> 0.31675636 | G50: =s_mem -> 0.31675636
A51: 記憶體測試機營收 | B51: US$M | C51: =a25_mem -> 504.9 | D51: =f26_mem -> 871.08 | E51: =E47*1000*E50 -> 1264.3351 | F51: =F47*1000*F50 -> 1637.8506 | G51: =G47*1000*G50 -> 2005.5766
A52: IST 營收（隨 SoC 市場） | B52: US$M | C52: =a25_ist -> 129.2 | D52: =f26_ist -> 195.51 | E52: =$D52*E46/$D46 -> 273.9692 | F52: =$D52*F46/$D46 -> 307.4694 | G52: =$D52*G46/$D46 -> 341.8968 | H52: FY2026 × SoC 市場相對 CY2026
A53: 半導體測試營收 | B53: US$M | C53: =C49+C51+C52 -> 2523.8 | D53: =D49+D51+D52 -> 4315.91 | E53: =E49+E51+E52 -> 6091.5935 | F53: =F49+F51+F52 -> 7055.3731 | G53: =G49+G51+G52 -> 8029.7
A54: Product Test 營收 | B54: US$M | C54: =a25_pt -> 358 | D54: =f26_pt -> 394.17 | E54: =D54*(1+g_pt_A) -> 425.7036 | F54: =E54*(1+g_pt_A) -> 459.75989 | G54: =F54*(1+g_pt_A) -> 496.54068
A55: 測試事業營收（半導體測試＋Product Test） | B55: US$M | C55: =C53+C54 -> 2881.8 | D55: =D53+D54 -> 4710.08 | E55: =E53+E54 -> 6517.2971 | F55: =F53+F54 -> 7515.133 | G55: =G53+G54 -> 8526.2407
A56: 測試事業稅前利益 | B56: US$M | C56: =a25_ttest -> 761.4 | D56: =f26_ttest -> 1643.8307 | E56: =t_inc*E55-t_fix+0*E55 -> 2516.0954 | F56: =t_inc*F55-t_fix+0*F55 -> 2997.707 | G56: =t_inc*G55-t_fix+0*G55 -> 3485.7245 | H56: 增量利益率 × 營收 − 固定成本（兩點推導）；C 情境另加價格競爭調整
A57: 測試事業稅前利益率 | B57: % | C57: =C56/C55 -> 0.26420987 | D57: =D56/D55 -> 0.34900272 | E57: =E56/E55 -> 0.38606424 | F57: =F56/F55 -> 0.39888942 | G57: =G56/G55 -> 0.40882314
A58: 機器人營收（不隨 AI 情境） | B58: US$M | C58: =a25_rob -> 308.3 | D58: =f26_rob -> 401.52 | E58: =D58*(1+g_rob) -> 441.672 | F58: =E58*(1+g_rob) -> 485.8392 | G58: =F58*(1+g_rob) -> 534.42312
A59: 機器人稅前利益 | B59: US$M | C59: =a25_trob -> -99.4 | D59: =f26_trob -> -3.5 | E59: =E58*rm_2027 -> 8.83344 | F59: =F58*rm_2028 -> 19.433568 | G59: =G58*rm_2029 -> 26.721156
A60: 公司與沖銷 | B60: US$M | C60: =a25_corp -> -8.8 | D60: =f26_corp -> -10.4 | E60: =corp -> -10.4 | F60: =corp -> -10.4 | G60: =corp -> -10.4
A61: 營收 | B61: US$M | C61: =C55+C58 -> 3190.1 | D61: =D55+D58 -> 5111.6 | E61: =E55+E58 -> 6958.9691 | F61: =F55+F58 -> 8000.9722 | G61: =G55+G58 -> 9060.6638
A62: 稅前利益 | B62: US$M | C62: =C56+C59+C60 -> 653.2 | D62: =D56+D59+D60 -> 1629.9307 | E62: =E56+E59+E60 -> 2514.5288 | F62: =F56+F59+F60 -> 3006.7406 | G62: =G56+G59+G60 -> 3502.0456
A63: 稅前利益率 | B63: % | C63: =C62/C61 -> 0.20475847 | D63: =D62/D61 -> 0.31886899 | E63: =E62/E61 -> 0.36133639 | F63: =F62/F61 -> 0.37579691 | G63: =G62/G61 -> 0.38651093
A64: 所得稅 | B64: US$M | C64: =a25_tax -> 79.3 | D64: =f26_tax -> 231.05474 | E64: =E62*etr -> 356.45305 | F64: =F62*etr -> 426.22772 | G64: =G62*etr -> 496.44087
A65: 權益法投資損益（Technoprobe） | B65: US$M | C65: =a25_aff -> -19.9 | D65: =f26_aff -> -13.2 | E65: =aff -> -13.2 | F65: =aff -> -13.2 | G65: =aff -> -13.2
A66: 淨利 | B66: US$M | C66: =a25_ni -> 554 | D66: =f26_ni -> 1385.276 | E66: =E62-E64+E65 -> 2144.8757 | F66: =F62-F64+F65 -> 2567.3129 | G66: =G62-G64+G65 -> 2992.4048 | H66: FY2026＝錨點（上半年實績＋下半年指引）
A67: 稀釋股數 | B67: 百萬股 | C67: =a25_dsh -> 159.7 | D67: =sh26 -> 157.7 | E67: =sh26*(1-bb)^1 -> 156.123 | F67: =sh26*(1-bb)^2 -> 154.56177 | G67: =sh26*(1-bb)^3 -> 153.01615
A68: EPS（GAAP 稀釋） | B68: US$ | C68: =a25_eps -> 3.47 | D68: =D66/D67 -> 8.7842486 | E68: =E66/E67 -> 13.738371 | F68: =F66/F67 -> 16.610271 | G68: =G66/G67 -> 19.556136
A69: SoC 占營收 | B69: % | C69: =C49/C61 -> 0.59236388 | D69: =D49/D61 -> 0.63567572 | E69: =E49/E61 -> 0.65430514 | F69: =F49/F61 -> 0.63867902 | G69: =G49/G61 -> 0.62713138
A70: 毛利率（參考；不進 EPS） | B70: % | C70: =a25_gp/a25_rev -> 0.58222571 | D70: =f26_gm -> 0.59436565 | E70: =f26_gm+(Q!J13-a25_gp/a25_rev)/(Q!J4/Q!J10-a25_soc/a25_rev)*(E69-D69) -> 0.60014094 | F70: =f26_gm+(Q!J13-a25_gp/a25_rev)/(Q!J4/Q!J10-a25_soc/a25_rev)*(F69-D69) -> 0.5952967 | G70: =f26_gm+(Q!J13-a25_gp/a25_rev)/(Q!J4/Q!J10-a25_soc/a25_rev)*(G69-D69) -> 0.59171682 | H70: FY2026＋斜率 ×（SoC 占營收 − FY2026）；斜率由 FY2025 與上半年 FY2026 兩點推得；EPS 由事業別稅前利益推導，本列只供參考
A73: 情境 B（平平）：2028 顆數 ×0.8、2029 ×0.85（Advantest 模型的 B 市場）
A74: 項目 | B74: 單位 | C74: FY2025A | D74: FY2026（錨點） | E74: FY2027 | F74: FY2028 | G74: FY2029 | H74: 說明
A75: SoC 測試機市場 CY（Advantest 模型） | B75: US$B | C75: =mk_soc25 -> 6.9 | D75: =ms_B_2026 -> 11 | E75: =ms_B_2027*m_soc -> 15.414358 | F75: =ms_B_2028*m_soc -> 14.769523 | G75: =ms_B_2029*m_soc -> 17.076287
A76: 記憶體測試機市場 CY（Advantest 模型） | B76: US$B | C76: =mk_mem25 -> 2.1 | D76: =mm_B_2026 -> 2.75 | E76: =mm_B_2027 -> 3.9915065 | F76: =mm_B_2028 -> 4.8492815 | G76: =mm_B_2029 -> 5.8958345
A77: 泰瑞達 SoC 市占 | B77: % | C77: =a25_soc/(C75*1000) -> 0.27386957 | D77: =f26_soc/(D75*1000) -> 0.29539273 | E77: =s_soc -> 0.29539273 | F77: =s_soc -> 0.29539273 | G77: =s_soc -> 0.29539273 | H77: FY2025、FY2026＝實績／錨點隱含；之後維持
A78: SoC 測試機營收 | B78: US$M | C78: =a25_soc -> 1889.7 | D78: =f26_soc -> 3249.32 | E78: =E75*1000*E77 -> 4553.2893 | F78: =F75*1000*F77 -> 4362.8097 | G78: =G75*1000*G77 -> 5044.211 | H78: 市場 × 市占
A79: 泰瑞達記憶體測試機市占 | B79: % | C79: =a25_mem/(C76*1000) -> 0.24042857 | D79: =f26_mem/(D76*1000) -> 0.31675636 | E79: =s_mem -> 0.31675636 | F79: =s_mem -> 0.31675636 | G79: =s_mem -> 0.31675636
A80: 記憶體測試機營收 | B80: US$M | C80: =a25_mem -> 504.9 | D80: =f26_mem -> 871.08 | E80: =E76*1000*E79 -> 1264.3351 | F80: =F76*1000*F79 -> 1536.0408 | G80: =G76*1000*G79 -> 1867.5431
A81: IST 營收（隨 SoC 市場） | B81: US$M | C81: =a25_ist -> 129.2 | D81: =f26_ist -> 195.51 | E81: =$D81*E75/$D75 -> 273.9692 | F81: =$D81*F75/$D75 -> 262.50813 | G81: =$D81*G75/$D75 -> 303.50772 | H81: FY2026 × SoC 市場相對 CY2026
A82: 半導體測試營收 | B82: US$M | C82: =C78+C80+C81 -> 2523.8 | D82: =D78+D80+D81 -> 4315.91 | E82: =E78+E80+E81 -> 6091.5935 | F82: =F78+F80+F81 -> 6161.3586 | G82: =G78+G80+G81 -> 7215.2618
A83: Product Test 營收 | B83: US$M | C83: =a25_pt -> 358 | D83: =f26_pt -> 394.17 | E83: =D83*(1+g_pt_B) -> 413.8785 | F83: =E83*(1+g_pt_B) -> 434.57243 | G83: =F83*(1+g_pt_B) -> 456.30105
A84: 測試事業營收（半導體測試＋Product Test） | B84: US$M | C84: =C82+C83 -> 2881.8 | D84: =D82+D83 -> 4710.08 | E84: =E82+E83 -> 6505.472 | F84: =F82+F83 -> 6595.931 | G84: =G82+G83 -> 7671.5629
A85: 測試事業稅前利益 | B85: US$M | C85: =a25_ttest -> 761.4 | D85: =f26_ttest -> 1643.8307 | E85: =t_inc*E84-t_fix+0*E84 -> 2510.3879 | F85: =t_inc*F84-t_fix+0*F84 -> 2554.0485 | G85: =t_inc*G84-t_fix+0*G84 -> 3073.2089 | H85: 增量利益率 × 營收 − 固定成本（兩點推導）；C 情境另加價格競爭調整
A86: 測試事業稅前利益率 | B86: % | C86: =C85/C84 -> 0.26420987 | D86: =D85/D84 -> 0.34900272 | E86: =E85/E84 -> 0.38588866 | F86: =F85/F84 -> 0.38721577 | G86: =G85/G84 -> 0.4005975
A87: 機器人營收（不隨 AI 情境） | B87: US$M | C87: =a25_rob -> 308.3 | D87: =f26_rob -> 401.52 | E87: =D87*(1+g_rob) -> 441.672 | F87: =E87*(1+g_rob) -> 485.8392 | G87: =F87*(1+g_rob) -> 534.42312
A88: 機器人稅前利益 | B88: US$M | C88: =a25_trob -> -99.4 | D88: =f26_trob -> -3.5 | E88: =E87*rm_2027 -> 8.83344 | F88: =F87*rm_2028 -> 19.433568 | G88: =G87*rm_2029 -> 26.721156
A89: 公司與沖銷 | B89: US$M | C89: =a25_corp -> -8.8 | D89: =f26_corp -> -10.4 | E89: =corp -> -10.4 | F89: =corp -> -10.4 | G89: =corp -> -10.4
A90: 營收 | B90: US$M | C90: =C84+C87 -> 3190.1 | D90: =D84+D87 -> 5111.6 | E90: =E84+E87 -> 6947.144 | F90: =F84+F87 -> 7081.7702 | G90: =G84+G87 -> 8205.986
A91: 稅前利益 | B91: US$M | C91: =C85+C88+C89 -> 653.2 | D91: =D85+D88+D89 -> 1629.9307 | E91: =E85+E88+E89 -> 2508.8213 | F91: =F85+F88+F89 -> 2563.082 | G91: =G85+G88+G89 -> 3089.53
A92: 稅前利益率 | B92: % | C92: =C91/C90 -> 0.20475847 | D92: =D91/D90 -> 0.31886899 | E92: =E91/E90 -> 0.36112989 | F92: =F91/F90 -> 0.36192675 | G92: =G91/G90 -> 0.37649712
A93: 所得稅 | B93: US$M | C93: =a25_tax -> 79.3 | D93: =f26_tax -> 231.05474 | E93: =E91*etr -> 355.64398 | F93: =F91*etr -> 363.33583 | G93: =G91*etr -> 437.96373
A94: 權益法投資損益（Technoprobe） | B94: US$M | C94: =a25_aff -> -19.9 | D94: =f26_aff -> -13.2 | E94: =aff -> -13.2 | F94: =aff -> -13.2 | G94: =aff -> -13.2
A95: 淨利 | B95: US$M | C95: =a25_ni -> 554 | D95: =f26_ni -> 1385.276 | E95: =E91-E93+E94 -> 2139.9774 | F95: =F91-F93+F94 -> 2186.5462 | G95: =G91-G93+G94 -> 2638.3663 | H95: FY2026＝錨點（上半年實績＋下半年指引）
A96: 稀釋股數 | B96: 百萬股 | C96: =a25_dsh -> 159.7 | D96: =sh26 -> 157.7 | E96: =sh26*(1-bb)^1 -> 156.123 | F96: =sh26*(1-bb)^2 -> 154.56177 | G96: =sh26*(1-bb)^3 -> 153.01615
A97: EPS（GAAP 稀釋） | B97: US$ | C97: =a25_eps -> 3.47 | D97: =D95/D96 -> 8.7842486 | E97: =E95/E96 -> 13.706996 | F97: =F95/F96 -> 14.146747 | G97: =G95/G96 -> 17.242404
A98: SoC 占營收 | B98: % | C98: =C78/C90 -> 0.59236388 | D98: =D78/D90 -> 0.63567572 | E98: =E78/E90 -> 0.65541887 | F98: =F78/F90 -> 0.61606202 | G98: =G78/G90 -> 0.61469896
A99: 毛利率（參考；不進 EPS） | B99: % | C99: =a25_gp/a25_rev -> 0.58222571 | D99: =f26_gm -> 0.59436565 | E99: =f26_gm+(Q!J13-a25_gp/a25_rev)/(Q!J4/Q!J10-a25_soc/a25_rev)*(E98-D98) -> 0.60048621 | F99: =f26_gm+(Q!J13-a25_gp/a25_rev)/(Q!J4/Q!J10-a25_soc/a25_rev)*(F98-D98) -> 0.58828522 | G99: =f26_gm+(Q!J13-a25_gp/a25_rev)/(Q!J4/Q!J10-a25_soc/a25_rev)*(G98-D98) -> 0.58786265 | H99: FY2026＋斜率 ×（SoC 占營收 − FY2026）；斜率由 FY2025 與上半年 FY2026 兩點推得；EPS 由事業別稅前利益推導，本列只供參考
A102: 情境 C（不如預期）：2028–29 顆數 ×0.6；泰瑞達自 Advantest 搶回份額但價格壓力
A103: 項目 | B103: 單位 | C103: FY2025A | D103: FY2026（錨點） | E103: FY2027 | F103: FY2028 | G103: FY2029 | H103: 說明
A104: SoC 測試機市場 CY（Advantest 模型） | B104: US$B | C104: =mk_soc25 -> 6.9 | D104: =ms_C_2026 -> 11 | E104: =ms_C_2027*m_soc -> 15.414358 | F104: =ms_C_2028*m_soc -> 12.239862 | G104: =ms_C_2029*m_soc -> 13.476472
A105: 記憶體測試機市場 CY（Advantest 模型） | B105: US$B | C105: =mk_mem25 -> 2.1 | D105: =mm_C_2026 -> 2.75 | E105: =mm_C_2027 -> 3.9915065 | F105: =mm_C_2028 -> 3.7299739 | G105: =mm_C_2029 -> 4.4025046
A106: 泰瑞達 SoC 市占 | B106: % | C106: =a25_soc/(C104*1000) -> 0.27386957 | D106: =f26_soc/(D104*1000) -> 0.29539273 | E106: =(s_soc+adv_sh26-as_C_2027) -> 0.29539273 | F106: =(s_soc+adv_sh26-as_C_2028) -> 0.34539273 | G106: =(s_soc+adv_sh26-as_C_2029) -> 0.39539273 | H106: FY2025、FY2026＝實績／錨點隱含；C 情境與 Advantest 互補
A107: SoC 測試機營收 | B107: US$M | C107: =a25_soc -> 1889.7 | D107: =f26_soc -> 3249.32 | E107: =E104*1000*E106 -> 4553.2893 | F107: =F104*1000*F106 -> 4227.5594 | G107: =G104*1000*G106 -> 5328.4989 | H107: 市場 × 市占
A108: 泰瑞達記憶體測試機市占 | B108: % | C108: =a25_mem/(C105*1000) -> 0.24042857 | D108: =f26_mem/(D105*1000) -> 0.31675636 | E108: =s_mem -> 0.31675636 | F108: =s_mem -> 0.31675636 | G108: =s_mem -> 0.31675636
A109: 記憶體測試機營收 | B109: US$M | C109: =a25_mem -> 504.9 | D109: =f26_mem -> 871.08 | E109: =E105*1000*E108 -> 1264.3351 | F109: =F105*1000*F108 -> 1181.493 | G109: =G105*1000*G108 -> 1394.5213
A110: IST 營收（隨 SoC 市場） | B110: US$M | C110: =a25_ist -> 129.2 | D110: =f26_ist -> 195.51 | E110: =$D110*E104/$D104 -> 273.9692 | F110: =$D110*F104/$D104 -> 217.54686 | G110: =$D110*G104/$D104 -> 239.52591 | H110: FY2026 × SoC 市場相對 CY2026
A111: 半導體測試營收 | B111: US$M | C111: =C107+C109+C110 -> 2523.8 | D111: =D107+D109+D110 -> 4315.91 | E111: =E107+E109+E110 -> 6091.5935 | F111: =F107+F109+F110 -> 5626.5992 | G111: =G107+G109+G110 -> 6962.5462
A112: Product Test 營收 | B112: US$M | C112: =a25_pt -> 358 | D112: =f26_pt -> 394.17 | E112: =D112*(1+g_pt_C) -> 402.0534 | F112: =E112*(1+g_pt_C) -> 410.09447 | G112: =F112*(1+g_pt_C) -> 418.29636
A113: 測試事業營收（半導體測試＋Product Test） | B113: US$M | C113: =C111+C112 -> 2881.8 | D113: =D111+D112 -> 4710.08 | E113: =E111+E112 -> 6493.6469 | F113: =F111+F112 -> 6036.6937 | G113: =G111+G112 -> 7380.8425
A114: 測試事業稅前利益 | B114: US$M | C114: =a25_ttest -> 761.4 | D114: =f26_ttest -> 1643.8307 | E114: =t_inc*E113-t_fix+0*E113 -> 2504.6804 | F114: =t_inc*F113-t_fix+gm_adj_C28*F113 -> 2223.7622 | G114: =t_inc*G113-t_fix+gm_adj_C29*G113 -> 2785.2741 | H114: 增量利益率 × 營收 − 固定成本（兩點推導）；C 情境另加價格競爭調整
...

Sheet Val
A1: Val — 估值。目標價＝DCF 與 Comparable 加權（第 0 節，放在本頁後段）；規則值（十年年底 P/E 依循環位置取分位：見頂年 25 分位、中段中位數、谷底 75 分位）保留為參考。循環位置依設備股共用規則（第 4 節）
A2: P/E 定義（自算）：年底收盤價（macrotrends，股利調整後）÷ 當年度 GAAP 稀釋 EPS（會計年度＝日曆年）；FY2016 為虧損（EPS −0.21），P/E 無意義，不納入分位
A3: 目標價（DCF 與 Comparable 加權）：見本頁第 91 列起「0. 目標價」
A4: 1. 公司公布 EPS（GAAP 稀釋，美元）— 兩個來源
A5: 會計年度 | B5: 來源1：SEC XBRL（10-K） | C5: 來源2：macrotrends | D5: 兩者差距 | E5: 淨利 US$M（10-K） | F5: 營收 US$M（10-K） | G5: 股東權益 US$M（年底） | H5: 說明
A6: 2015 | B6: 0.97 | C6: 0.97 | D6: =IF(C6="","",B6-C6) -> 0 | E6: 206.5 | F6: 1639.6 | G6: 1965.8
A7: 2016 | B7: -0.21 | C7: -0.21 | D7: =IF(C7="","",B7-C7) -> 0 | E7: -43.4 | F7: 1753.3 | G7: 1828.7 | H7: 虧損年（Wireless Test 商譽減損）
A8: 2017 | B8: 1.28 | C8: 1.28 | D8: =IF(C8="","",B8-C8) -> 0 | E8: 257.7 | F8: 2136.6 | G8: 1953.6
A9: 2018 | B9: 2.35 | C9: 2.35 | D9: =IF(C9="","",B9-C9) -> 0 | E9: 451.8 | F9: 2100.8 | G9: 1522.4
A10: 2019 | B10: 2.6 | C10: 2.6 | D10: =IF(C10="","",B10-C10) -> 0 | E10: 467.5 | F10: 2295 | G10: 1480.2
A11: 2020 | B11: 4.28 | C11: 4.28 | D11: =IF(C11="","",B11-C11) -> 0 | E11: 784.1 | F11: 3121.5 | G11: 2207
A12: 2021 | B12: 5.53 | C12: 5.53 | D12: =IF(C12="","",B12-C12) -> 0 | E12: 1014.6 | F12: 3702.9 | G12: 2562.4
A13: 2022 | B13: 4.22 | C13: 4.22 | D13: =IF(C13="","",B13-C13) -> 0 | E13: 715.5 | F13: 3155 | G13: 2451.3
A14: 2023 | B14: 2.73 | C14: 2.73 | D14: =IF(C14="","",B14-C14) -> 0 | E14: 448.8 | F14: 2676.3 | G14: 2525.9
A15: 2024 | B15: 3.32 | C15: 3.32 | D15: =IF(C15="","",B15-C15) -> 0 | E15: 542.4 | F15: 2819.9 | G15: 2819.3
A16: 2025 | B16: 3.47 | D16: =IF(C16="","",B16-C16) | E16: 554 | F16: 3190 | G16: 2795.8 | H16: macrotrends 年表只到 2024；FY2025 第二來源：公司 4Q25 新聞稿 3.47（同一公司來源）
A17: 全部年度用 GAAP 稀釋 EPS。淨利、營收、股東權益取自 SEC XBRL（10-K），用於十年平均淨利率與近三年 ROE
A18: 2. 10 年 P/E（年底）
A19: 年底 | B19: 收盤價 US$（股利調整） | C19: 當年 EPS | E19: P/E 當年（自算） | G19: companiesmarketcap P/E | H19: 自算 − cmc | J19: 標記 | K19: 來源／說明
A20: 2016-12 | B20: 24.1472 | C20: =B7 -> -0.21 | E20: =IF(C20<=0,"",B20/C20) | G20: -115 | H20: =IF(E20="","",E20-G20) | J20: Verified／Derived | K20: EPS 為負，P/E 不納入分位（cmc 列 −115）
A21: 2017-12 | B21: 40.1225 | C21: =B8 -> 1.28 | E21: =IF(C21<=0,"",B21/C21) -> 31.345703 | G21: 31.2 | H21: =IF(E21="","",E21-G21) -> 0.14570313 | J21: Verified／Derived | K21: 收盤價：macrotrends 年表（年底收盤，股利調整後；泰瑞達 2016 年後無分割）
A22: 2018-12 | B22: 30.3431 | C22: =B9 -> 2.35 | E22: =IF(C22<=0,"",B22/C22) -> 12.911957 | G22: 12.5 | H22: =IF(E22="","",E22-G22) -> 0.41195745 | J22: Verified／Derived | K22: 收盤價：macrotrends 年表（年底收盤，股利調整後；泰瑞達 2016 年後無分割）
A23: 2019-12 | B23: 66.4325 | C23: =B10 -> 2.6 | E23: =IF(C23<=0,"",B23/C23) -> 25.550962 | G23: 23.6 | H23: =IF(E23="","",E23-G23) -> 1.9509615 | J23: Verified／Derived | K23: 收盤價：macrotrends 年表（年底收盤，股利調整後；泰瑞達 2016 年後無分割）
A24: 2020-12 | B24: 117.399 | C24: =B11 -> 4.28 | E24: =IF(C24<=0,"",B24/C24) -> 27.429673 | G24: 24.9 | H24: =IF(E24="","",E24-G24) -> 2.5296729 | J24: Verified／Derived | K24: 收盤價：macrotrends 年表（年底收盤，股利調整後；泰瑞達 2016 年後無分割）
A25: 2021-12 | B25: 160.61 | C25: =B12 -> 5.53 | E25: =IF(C25<=0,"",B25/C25) -> 29.0434 | G25: 26 | H25: =IF(E25="","",E25-G25) -> 3.0433996 | J25: Verified／Derived | K25: 收盤價：macrotrends 年表（年底收盤，股利調整後；泰瑞達 2016 年後無分割）
A26: 2022-12 | B26: 86.1704 | C26: =B13 -> 4.22 | E26: =IF(C26<=0,"",B26/C26) -> 20.419526 | G26: 19.1 | H26: =IF(E26="","",E26-G26) -> 1.3195261 | J26: Verified／Derived | K26: 收盤價：macrotrends 年表（年底收盤，股利調整後；泰瑞達 2016 年後無分割）
A27: 2023-12 | B27: 107.522 | C27: =B14 -> 2.73 | E27: =IF(C27<=0,"",B27/C27) -> 39.385348 | G27: 36.9 | H27: =IF(E27="","",E27-G27) -> 2.485348 | J27: Verified／Derived | K27: 收盤價：macrotrends 年表（年底收盤，股利調整後；泰瑞達 2016 年後無分割）
A28: 2024-12 | B28: 125.274 | C28: =B15 -> 3.32 | E28: =IF(C28<=0,"",B28/C28) -> 37.733133 | G28: 37 | H28: =IF(E28="","",E28-G28) -> 0.73313253 | J28: Verified／Derived | K28: 收盤價：macrotrends 年表（年底收盤，股利調整後；泰瑞達 2016 年後無分割）
A29: 2025-12 | B29: 193.406 | C29: =B16 -> 3.47 | E29: =IF(C29<=0,"",B29/C29) -> 55.736599 | G29: 55.5 | H29: =IF(E29="","",E29-G29) -> 0.23659942 | J29: Verified／Derived | K29: statmuse 2025-12-31 收盤 193.33（未調整，第二來源）；macrotrends 調整後 193.41
A31: 收盤價來源1：macrotrends（股利調整後年底收盤）；來源2：statmuse（僅 2025 年底 193.33）。股利調整使早年價格略低（每季 0.06–0.13 美元股利），P/E 偏低約 1–3%。companiesmarketcap（TTM 口徑）僅作對照，差距見 H 欄。
A33: 3. 分位（只含正 EPS 年度）
A34: 統計 | B34: P/E 當年（自算） | D34: cmc P/E（參考，正值） | E34: 用途
A35: 25 分位 | B35: =PERCENTILE(E20:E29,0.25) -> 25.550962 | D35: =PERCENTILE(G21:G29,0.25) -> 23.6 | E35: 見頂年
A36: 中位數 | B36: =PERCENTILE(E20:E29,0.5) -> 29.0434 | D36: =PERCENTILE(G21:G29,0.5) -> 26 | E36: 中段
A37: 75 分位 | B37: =PERCENTILE(E20:E29,0.75) -> 37.733133 | D37: =PERCENTILE(G21:G29,0.75) -> 36.9 | E37: 谷底
A38: 年數 | B38: =COUNT(E20:E29) -> 9 | D38: =COUNT(G21:G29) -> 9
A40: 4. 循環位置（設備股共用規則；見頂年度讀設備市場模型，不在本模型另訂）
A41: 循環位置（設備股共用規則）：各情境的見頂年度取自設備市場模型（markets/equipment 的 Mkt 頁「見頂年度」：A 2029、B 2028、C 2027）；會計年度 FY(t)＝日曆年 t：t 早於見頂年＝中段（中位數）、等於＝見頂（25 分位）、晚於＝谷底（75 分位）
A42: 情境 | B42: 設備市場見頂年度 | C42: FY2027 對照日曆年 | D42: 判定 | E42: 倍數 | F42: 規則
A43: A | B43: =pk_A -> 2029 | C43: 2027 | D43: =IF(C43<pk_A,"中段",IF(C43=pk_A,"見頂","谷底")) -> 中段 | E43: =IF(D43="見頂",pe_peak,IF(D43="谷底",pe_trough,pe_mid)) -> 29.0434 | F43: tools/cycle_position.py
A44: B | B44: =pk_B -> 2028 | C44: 2027 | D44: =IF(C44<pk_B,"中段",IF(C44=pk_B,"見頂","谷底")) -> 中段 | E44: =IF(D44="見頂",pe_peak,IF(D44="谷底",pe_trough,pe_mid)) -> 29.0434 | F44: tools/cycle_position.py
A45: C | B45: =pk_C -> 2027 | C45: 2027 | D45: =IF(C45<pk_C,"中段",IF(C45=pk_C,"見頂","谷底")) -> 見頂 | E45: =IF(D45="見頂",pe_peak,IF(D45="谷底",pe_trough,pe_mid)) -> 25.550962 | F45: tools/cycle_position.py
A47: 5. 隱含股價（美元）：規則值＝FY2027 EPS × 依循環位置的倍數；其餘倍數僅供參考
A48: 情境 | B48: EPS 年度 | C48: EPS | D48: 倍數類型 | E48: 倍數 | F48: 隱含股價 | G48: 相對現價 | H48: 備註
A49: A | B49: FY2027 | C49: =PL!E13 -> 13.738371 | D49: ="規則值："&D43 -> 規則值：中段 | E49: =E43 -> 29.0434 | F49: =C49*E49 -> 399.00901 | G49: =F49/px-1 -> 0.29191843
A50: A | B50: FY2027 | C50: =PL!E13 -> 13.738371 | D50: 參考：25 分位 | E50: =pe_peak -> 25.550962 | F50: =C50*E50 -> 351.0286 | G50: =F50/px-1 -> 0.13656661
A51: A | B51: FY2027 | C51: =PL!E13 -> 13.738371 | D51: 參考：中位數 | E51: =pe_mid -> 29.0434 | F51: =C51*E51 -> 399.00901 | G51: =F51/px-1 -> 0.29191843
A52: A | B52: FY2027 | C52: =PL!E13 -> 13.738371 | D52: 參考：75 分位 | E52: =pe_trough -> 37.733133 | F52: =C52*E52 -> 518.39178 | G52: =F52/px-1 -> 0.6784581
A53: A | B53: FY2028 | C53: =PL!F13 -> 16.610271 | D53: 參考：25 分位 | E53: =pe_peak -> 25.550962 | F53: =C53*E53 -> 424.40839 | G53: =F53/px-1 -> 0.37415702
A54: A | B54: FY2028 | C54: =PL!F13 -> 16.610271 | D54: 參考：中位數 | E54: =pe_mid -> 29.0434 | F54: =C54*E54 -> 482.41874 | G54: =F54/px-1 -> 0.56198393
A55: A | B55: FY2028 | C55: =PL!F13 -> 16.610271 | D55: 參考：75 分位 | E55: =pe_trough -> 37.733133 | F55: =C55*E55 -> 626.75756 | G55: =F55/px-1 -> 1.0293267
A56: B | B56: FY2027 | C56: =PL!E24 -> 13.706996 | D56: ="規則值："&D44 -> 規則值：中段 | E56: =E44 -> 29.0434 | F56: =C56*E56 -> 398.09777 | G56: =F56/px-1 -> 0.288968
A57: B | B57: FY2027 | C57: =PL!E24 -> 13.706996 | D57: 參考：25 分位 | E57: =pe_peak -> 25.550962 | F57: =C57*E57 -> 350.22693 | G57: =F57/px-1 -> 0.13397096
A58: B | B58: FY2027 | C58: =PL!E24 -> 13.706996 | D58: 參考：中位數 | E58: =pe_mid -> 29.0434 | F58: =C58*E58 -> 398.09777 | G58: =F58/px-1 -> 0.288968
A59: B | B59: FY2027 | C59: =PL!E24 -> 13.706996 | D59: 參考：75 分位 | E59: =pe_trough -> 37.733133 | F59: =C59*E59 -> 517.2079 | G59: =F59/px-1 -> 0.6746249
A60: B | B60: FY2028 | C60: =PL!F24 -> 14.146747 | D60: 參考：25 分位 | E60: =pe_peak -> 25.550962 | F60: =C60*E60 -> 361.46298 | G60: =F60/px-1 -> 0.17035124
A61: B | B61: FY2028 | C61: =PL!F24 -> 14.146747 | D61: 參考：中位數 | E61: =pe_mid -> 29.0434 | F61: =C61*E61 -> 410.86962 | G61: =F61/px-1 -> 0.33032092
A62: B | B62: FY2028 | C62: =PL!F24 -> 14.146747 | D62: 參考：75 分位 | E62: =pe_trough -> 37.733133 | F62: =C62*E62 -> 533.80107 | G62: =F62/px-1 -> 0.72835055
A63: C | B63: FY2027 | C63: =PL!E35 -> 13.675621 | D63: ="規則值："&D45 -> 規則值：見頂 | E63: =E45 -> 25.550962 | F63: =C63*E63 -> 349.42527 | G63: =F63/px-1 -> 0.13137531
A64: C | B64: FY2027 | C64: =PL!E35 -> 13.675621 | D64: 參考：25 分位 | E64: =pe_peak -> 25.550962 | F64: =C64*E64 -> 349.42527 | G64: =F64/px-1 -> 0.13137531
A65: C | B65: FY2027 | C65: =PL!E35 -> 13.675621 | D65: 參考：中位數 | E65: =pe_mid -> 29.0434 | F65: =C65*E65 -> 397.18653 | G65: =F65/px-1 -> 0.28601757
A66: C | B66: FY2027 | C66: =PL!E35 -> 13.675621 | D66: 參考：75 分位 | E66: =pe_trough -> 37.733133 | F66: =C66*E66 -> 516.02402 | G66: =F66/px-1 -> 0.67079171
A67: C | B67: FY2028 | C67: =PL!F35 -> 12.31275 | D67: 參考：25 分位 | E67: =pe_peak -> 25.550962 | F67: =C67*E67 -> 314.6026 | G67: =F67/px-1 -> 0.018625873
A68: C | B68: FY2028 | C68: =PL!F35 -> 12.31275 | D68: 參考：中位數 | E68: =pe_mid -> 29.0434 | F68: =C68*E68 -> 357.60412 | G68: =F68/px-1 -> 0.15785695
A69: C | B69: FY2028 | C69: =PL!F35 -> 12.31275 | D69: 參考：75 分位 | E69: =pe_trough -> 37.733133 | F69: =C69*E69 -> 464.59863 | G69: =F69/px-1 -> 0.50428566
A71: 6. 目前遠期 P/E
A72: 項目 | B72: A（順利） | C72: B（平平） | D72: C（不如預期） | E72: 備註
A73: 現價（2026-10-23 收盤） | B73: =px -> 308.85 | E73: stockanalysis、equibles
A74: 遠期 P/E：stockanalysis | B74: =sa_fpe -> 32.52 | E74: 分析師共識前瞻 EPS（non-GAAP）
A75: 現價 ÷ FY2026 EPS（錨點） | B75: =px/f26_eps -> 35.159524 | E75: FY2026 三情境相同
A76: 現價 ÷ FY2027 EPS（模型） | B76: =px/PL!E13 -> 22.480831 | C76: =px/PL!E24 -> 22.532289 | D76: =px/PL!E35 -> 22.583984
A77: 現價 ÷ FY2028 EPS（模型） | B77: =px/PL!F13 -> 18.593917 | C77: =px/PL!F24 -> 21.831875 | D77: =px/PL!F35 -> 25.083755
A78: 現價 ÷ 共識 FY2027 EPS（non-GAAP） | B78: =px/cons_eps27 -> 27.331858 | E78: MarketBeat 11.30
A80: 舊法：規則值情境加權（參考）
A81: 項目 | B81: 數值 | E81: 說明
A82: 規則值情境加權價（12 個月；參考） | B82: =tp_wA*B84+tp_wB*B85+tp_wC*B86 -> 388.63664 | E82: 權重 × 各情境隱含價（第 5 節規則值）
A83: 相對現價（規則值情境加權價 ÷ 現價 − 1） | B83: =B82/px-1 -> 0.25833459 | E83: 現價＝In 頁 px（2026-10-23 收盤）
A84: 情境 A 隱含價（順利） | B84: =F49 -> 399.00901 | E84: ="FY2027 EPS × "&D49&" "&TEXT(E49,"0.0")&"x（第 5 節 F49）" -> FY2027 EPS × 規則值：中段 29.0x（第 5 節 F49）
A85: 情境 B 隱含價（平平） | B85: =F56 -> 398.09777 | E85: ="FY2027 EPS × "&D56&" "&TEXT(E56,"0.0")&"x（第 5 節 F56）" -> FY2027 EPS × 規則值：中段 29.0x（第 5 節 F56）
A86: 情境 C 隱含價（不如預期） | B86: =F63 -> 349.42527 | E86: ="FY2027 EPS × "&D63&" "&TEXT(E63,"0.0")&"x（第 5 節 F63）" -> FY2027 EPS × 規則值：見頂 25.6x（第 5 節 F63）
A87: 情境權重 A／B／C | B87: =tp_wA -> 0.3 | C87: =tp_wB -> 0.5 | D87: =tp_wC -> 0.2 | E87: ="合計 "&TEXT(B87+C87+D87,"0%")&"；In 頁 tp_wA／tp_wB／tp_wC（Assumed，Andy 可改）" -> 合計 100%；In 頁 tp_wA／tp_wB／tp_wC（Assumed，Andy 可改）
A88: 規則值方法 | B88: P/E：各情境 FY2027 EPS × 十年（2016–2025 年底）P/E 依循環位置取分位（設備股共用規則：A、B 中段＝中位數，C 見頂＝25 分位；FY2016 虧損不納入，實為 9 年）。隱含價約為 FY2027 年底的價格、未折現
A91: 0. 目標價
A92: 0.1 DCF（股東權益現金流，FY2027–FY2032 明確期＋FY2032 後永續）
A93: 項目 | B93: A（順利） | C93: B（平平） | D93: C（不如預期） | E93: 說明
A94: 情境 EPS（FY2027–FY2032） | E94: PL 頁延伸區塊；FY2030 起為收斂法
A95: FY2027 | B95: =PL!E139 -> 13.738371 | C95: =PL!E146 -> 13.706996 | D95: =PL!E153 -> 13.675621
A96: FY2028 | B96: =PL!F139 -> 16.610271 | C96: =PL!F146 -> 14.146747 | D96: =PL!F153 -> 12.31275
A97: FY2029 | B97: =PL!G139 -> 19.556136 | C97: =PL!G146 -> 17.242404 | D97: =PL!G153 -> 15.627425
A98: FY2030 | B98: =PL!H139 -> 21.674006 | C98: =PL!H146 -> 17.881792 | D98: =PL!H153 -> 15.537609
A99: FY2031 | B99: =PL!I139 -> 23.49784 | C99: =PL!I146 -> 17.776931 | D99: =PL!I153 -> 14.227706
A100: FY2032 | B100: =PL!J139 -> 24.90771 | C100: =PL!J146 -> 16.898949 | D100: =PL!J153 -> 11.836833
A101: 股東現金流＝EPS ×（1 − tp_g ÷ tp_roe） | E101: 模型無折舊與資本支出項目，故不用（淨利＋折舊－資本支出）；FY2025 資本支出 224.0、折舊 111.4（10-K 現金流量表），資本支出約為營收 7%，偏誤小
A102: 再投資率（tp_g ÷ tp_roe，上限 0.8） | B102: =MIN(tp_g/tp_roe,0.8) -> 0.20667709 | E102: ROE 為近三年平均（In 頁 tp_roe）
A103: FY2027 | B103: =B95*(1-$B$102) -> 10.898965 | C103: =C95*(1-$B$102) -> 10.874074 | D103: =D95*(1-$B$102) -> 10.849183
A104: FY2028 | B104: =B96*(1-$B$102) -> 13.177308 | C104: =C96*(1-$B$102) -> 11.222938 | D104: =D96*(1-$B$102) -> 9.7679866
A105: FY2029 | B105: =B97*(1-$B$102) -> 15.514331 | C105: =C97*(1-$B$102) -> 13.678794 | D105: =D97*(1-$B$102) -> 12.397594
A106: FY2030 | B106: =B98*(1-$B$102) -> 17.194485 | C106: =C98*(1-$B$102) -> 14.186035 | D106: =D98*(1-$B$102) -> 12.326341
A107: FY2031 | B107: =B99*(1-$B$102) -> 18.641374 | C107: =C99*(1-$B$102) -> 14.102846 | D107: =D99*(1-$B$102) -> 11.287165
A108: FY2032 | B108: =B100*(1-$B$102) -> 19.759857 | C108: =C100*(1-$B$102) -> 13.406324 | D108: =D100*(1-$B$102) -> 9.3904307
...

Sheet Recon
A1: Recon — 本模型 vs 公司指引、目標模型、共識、Advantest 份額、測試對 WFE 比。只作事後對照，不為對上數字而調整參數。差距 > 10% 的原因見 README
A3: 項目 | B3: 對照值 | C3: 模型 A | D3: 差距 A | E3: 模型 B | F3: 差距 B | G3: 模型 C | H3: 差距 C | I3: 對照來源 | J3: 說明
A4: A. FY2026 vs 公司指引與共識
A5: 營收：上半年占 51%（公司 50–52% 中點）推得的全年 | B5: =Q!J10/0.51 -> 5120.5882 | C5: =PL!D5 -> 5111.6 | D5: =C5/B5-1 -> -0.001755313 | E5: =PL!D16 -> 5111.6 | F5: =E5/B5-1 -> -0.001755313 | G5: =PL!D27 -> 5111.6 | H5: =G5/B5-1 -> -0.001755313 | I5: 公司 2Q26 法說 | J5: 錨點由 3Q26 指引推得；與公司上半年占比一致性檢查
A6: 營收（共識） | B6: =cons_rev26 -> 5100 | C6: =PL!D5 -> 5111.6 | D6: =C6/B6-1 -> 0.0022745098 | E6: =PL!D16 -> 5111.6 | F6: =E6/B6-1 -> 0.0022745098 | G6: =PL!D27 -> 5111.6 | H6: =G6/B6-1 -> 0.0022745098 | I6: stockanalysis 2026-10-20
A7: EPS（共識，non-GAAP） | B7: =cons_eps26 -> 9.09 | C7: =PL!D13 -> 8.7842486 | D7: =C7/B7-1 -> -0.033636021 | E7: =PL!D24 -> 8.7842486 | F7: =E7/B7-1 -> -0.033636021 | G7: =PL!D35 -> 8.7842486 | H7: =G7/B7-1 -> -0.033636021 | I7: stockanalysis 2026-10-20 | J7: 模型為 GAAP；non-GAAP 另加權益法投資攤銷約 0.20、無形資產攤銷約 0.08／年（2Q26 新聞稿調節表）
A8: B. FY2027 vs 共識
A9: EPS（共識，non-GAAP） | B9: =cons_eps27 -> 11.3 | C9: =PL!E13 -> 13.738371 | D9: =C9/B9-1 -> 0.21578507 | E9: =PL!E24 -> 13.706996 | F9: =E9/B9-1 -> 0.21300851 | G9: =PL!E35 -> 13.675621 | H9: =G9/B9-1 -> 0.21023194 | I9: MarketBeat 2026-10-20 | J9: 差距大於 10% 的原因見 README
A10: C. 公司目標模型（ATE 市場 US$12–14B 時；未給年度）
A11: 營收 6.0B：模型 FY2027 | B11: =tm_rev -> 6000 | C11: =PL!E5 -> 6958.9691 | D11: =C11/B11-1 -> 0.15982819 | E11: =PL!E16 -> 6947.144 | F11: =E11/B11-1 -> 0.15785734 | G11: =PL!E27 -> 6935.3189 | H11: =G11/B11-1 -> 0.15588649 | I11: 公司 4Q25 法說（fintool） | J11: 目標模型未給年度；本列只看量級
A12: non-GAAP EPS 上緣 11.00：模型 FY2027（GAAP） | B12: =tm_eps_hi -> 11 | C12: =PL!E13 -> 13.738371 | D12: =C12/B12-1 -> 0.24894284 | E12: =PL!E24 -> 13.706996 | F12: =E12/B12-1 -> 0.24609056 | G12: =PL!E35 -> 13.675621 | H12: =G12/B12-1 -> 0.24323827 | I12: 同上
A13: D. 市占與市場規模
A14: CY2025 SoC：泰瑞達隱含市占 vs 1 − Advantest 自估 66% | B14: =1-as_A_2026 -> 0.34 | C14: =PL!C48 -> 0.27386957 | D14: =C14-B14 -> -0.066130435 | E14: =PL!C77 -> 0.27386957 | F14: =E14-B14 -> -0.066130435 | G14: =PL!C106 -> 0.27386957 | H14: =G14-B14 -> -0.066130435 | I14: Advantest 自估（Interested-party） | J14: 差額＝其他廠份額（CY2025 約 6.6%）
A15: CY2026 SoC 市占 vs 分析師估約 37% | B15: =an_share -> 0.37 | C15: =PL!D48 -> 0.29539273 | D15: =C15-B15 -> -0.074607273 | E15: =PL!D77 -> 0.29539273 | F15: =E15-B15 -> -0.074607273 | G15: =PL!D106 -> 0.29539273 | H15: =G15-B15 -> -0.074607273 | I15: 2Q26 法說分析師提問（公司未證實） | J15: 口徑不同：Advantest 的 SoC 市場含其自身所有 SoC 測試機；分析師口徑未明
A16: CY2026：SoC＋記憶體測試機 ÷ WFE vs 公司長期上緣 9% | B16: =tw_hi -> 0.09 | C16: =Units!D10 -> 0.08805238 | D16: =C16-B16 -> -0.0019476197 | E16: =Units!D18 -> 0.08805238 | F16: =E16-B16 -> -0.0019476197 | G16: =Units!D26 -> 0.08805238 | H16: =G16-B16 -> -0.0019476197 | I16: 公司 2Q26 法說（Interested-party）
A17: CY2027：SoC＋記憶體測試機 ÷ WFE vs 公司長期上緣 9% | B17: =tw_hi -> 0.09 | C17: =Units!E10 -> 0.10065519 | D17: =C17-B17 -> 0.01065519 | E17: =Units!E18 -> 0.10065519 | F17: =E17-B17 -> 0.01065519 | G17: =Units!E26 -> 0.10065519 | H17: =G17-B17 -> 0.01065519 | I17: 公司 2Q26 法說（Interested-party） | J17: 公司口徑為 ATE 市場（含類比等其他測試機）÷ WFE；本模型分子只有 SoC＋記憶體，口徑更窄卻已高於上緣
A18: CY2028：SoC＋記憶體測試機 ÷ WFE vs 公司長期上緣 9% | B18: =tw_hi -> 0.09 | C18: =Units!F10 -> 0.10372534 | D18: =C18-B18 -> 0.013725345 | E18: =Units!F18 -> 0.10175968 | F18: =E18-B18 -> 0.011759676 | G18: =Units!F26 -> 0.10354131 | H18: =G18-B18 -> 0.013541309 | I18: 公司 2Q26 法說（Interested-party）
A19: E. 其他資訊（非對帳）
A20: 上半年 FY2026 營收 ÷ 模型 FY2026 營收 | C20: =Q!J10/PL!D5 -> 0.51089678 | J20: 公司：上半年 50–52%
A21: 指引紀錄：1Q26、2Q26 營收皆高於指引上緣（1,250） | C21: =(Q!G10+Q!H10)/2/1250-1 -> 0.0446 | J21: 指引偏保守 → FY2026 錨點可能偏低（下半年以指引中點推估）

Sheet Sens
A1: Sens — 一次動一個輸入（情境 A）：對 FY2027、FY2028 營收與 EPS 的影響。每個案例是一個完整的推導區塊（本頁下方，與 PL 同一引擎）；FY2026 錨點不變
A3: 案例 | B3: 設定 | C3: FY2027 營收 US$M | D3: FY2027 EPS US$ | E3: 相對基準 | F3: FY2028 營收 US$M | G3: FY2028 EPS US$ | H3: 相對基準
A4: 基準（情境 A） | B4: PL 區塊 A | C4: =PL!E61 -> 6958.9691 | D4: =PL!E68 -> 13.738371 | E4: =D4/D$4-1 -> 0 | F4: =PL!F61 -> 8000.9722 | G4: =PL!F68 -> 16.610271 | H4: =G4/G$4-1 -> 0
A5: 泰瑞達 SoC 市占 −5 個百分點 | B5: A 情境 FY2027 起 | C5: =E57 -> 6188.2512 | D5: =E64 -> 11.69345 | E5: =D5/D$4-1 -> -0.14884742 | F5: =F57 -> 7136.013 | G5: =F64 -> 14.292121 | H5: =G5/G$4-1 -> -0.13956123
A6: 泰瑞達 SoC 市占 +5 個百分點 | C6: =E89 -> 7729.687 | D6: =E96 -> 15.783292 | E6: =D6/D$4-1 -> 0.14884742 | F6: =F89 -> 8865.9313 | G6: =F96 -> 18.928421 | H6: =G6/G$4-1 -> 0.13956123
A7: SoC 測試機市場 −15%（2027 起） | B7: 測試對 WFE 比回到公司說的區間 | C7: =E121 -> 6234.8804 | D7: =E128 -> 11.81717 | E7: =D7/D$4-1 -> -0.13984201 | F7: =F121 -> 7188.3438 | G7: =F128 -> 14.432371 | H7: =G7/G$4-1 -> -0.13111765
A8: 記憶體市占 −5 個百分點 | C8: =E153 -> 6759.3938 | D8: =E160 -> 13.208844 | E8: =D8/D$4-1 -> -0.038543637 | F8: =F153 -> 7742.4374 | G8: =F160 -> 15.91738 | H8: =G8/G$4-1 -> -0.041714605
A9: 記憶體市占 +5 個百分點 | C9: =E185 -> 7158.5445 | D9: =E192 -> 14.267898 | E9: =D9/D$4-1 -> 0.038543637 | F9: =F185 -> 8259.5069 | G9: =F192 -> 17.303162 | H9: =G9/G$4-1 -> 0.041714605
A10: 測試事業增量利益率 40% | B10: 固定成本重新推導（FY2026 錨點不變） | C10: =E217 -> 6958.9691 | D10: =E224 -> 12.917209 | E10: =D10/D$4-1 -> -0.059771462 | F10: =F217 -> 8000.9722 | G10: =F224 -> 15.322838 | H10: =G10/G$4-1 -> -0.077508252
A11: 測試事業增量利益率 56% | B11: 同上 | C11: =E249 -> 6958.9691 | D11: =E256 -> 14.506756 | E11: =D11/D$4-1 -> 0.055929842 | F11: =F249 -> 8000.9722 | G11: =F256 -> 17.814958 | H11: =G11/G$4-1 -> 0.072526657
A12: Product Test 成長 低 | B12: A 情境 4% | C12: =E281 -> 6943.2023 | D12: =E288 -> 13.696538 | E12: =D12/D$4-1 -> -0.0030450148 | F12: =F281 -> 7967.5465 | G12: =F288 -> 16.520688 | H12: =G12/G$4-1 -> -0.0053932259
A13: Product Test 成長 高 | B13: A 情境 12% | C13: =E313 -> 6974.7359 | D13: =E320 -> 13.780205 | E13: =D13/D$4-1 -> 0.0030450148 | F13: =F313 -> 8035.6591 | G13: =F320 -> 16.703234 | H13: =G13/G$4-1 -> 0.0055967438
A14: 機器人成長 0% | B14: 三情境相同 | C14: =E345 -> 6918.8171 | D14: =E352 -> 13.733957 | E14: =D14/D$4-1 -> -0.00032132544 | F14: =F345 -> 7916.653 | G14: =F352 -> 16.591543 | H14: =G14/G$4-1 -> -0.0011275031
A15: 機器人成長 20% | C15: =E377 -> 6999.1211 | D15: =E384 -> 13.742786 | E15: =D15/D$4-1 -> 0.00032132544 | F15: =F377 -> 8093.3218 | G15: =F384 -> 16.630783 | H15: =G15/G$4-1 -> 0.0012348843
A16: 機器人利益率 低 | B16: 每年 −7 個百分點 | C16: =E409 -> 6958.9691 | D16: =E416 -> 13.568413 | E16: =D16/D$4-1 -> -0.012371029 | F16: =F409 -> 8000.9722 | G16: =F416 -> 16.421429 | H16: =G16/G$4-1 -> -0.011368989
A17: 機器人利益率 高 | B17: 每年 +5 個百分點 | C17: =E441 -> 6958.9691 | D17: =E448 -> 13.85977 | E17: =D17/D$4-1 -> 0.0088364496 | F17: =F441 -> 8000.9722 | G17: =F448 -> 16.745158 | H17: =G17/G$4-1 -> 0.0081207067
A18: 稅率 12% | C18: =E473 -> 6958.9691 | D18: =E480 -> 14.088798 | E18: =D18/D$4-1 -> 0.025507118 | F18: =F473 -> 8000.9722 | G18: =F480 -> 17.033525 | H18: =G18/G$4-1 -> 0.025481446
A19: 稅率 17% | C19: =E505 -> 6958.9691 | D19: =E512 -> 13.283494 | E19: =D19/D$4-1 -> -0.033110003 | F19: =F505 -> 8000.9722 | G19: =F512 -> 16.060858 | H19: =G19/G$4-1 -> -0.033076679
A20: 回購 0%／年 | C20: =E537 -> 6958.9691 | D20: =E544 -> 13.600988 | E20: =D20/D$4-1 -> -0.01 | F20: =F537 -> 8000.9722 | G20: =F544 -> 16.279727 | H20: =G20/G$4-1 -> -0.0199
A21: 回購 2%／年 | C21: =E569 -> 6958.9691 | D21: =E576 -> 13.878559 | E21: =D21/D$4-1 -> 0.010204082 | F21: =F569 -> 8000.9722 | G21: =F576 -> 16.950986 | H21: =G21/G$4-1 -> 0.020512287
A22: 情境 B（平平） | B22: Advantest 模型的 B 市場；Product Test 成長 B | C22: =PL!E90 -> 6947.144 | D22: =PL!E97 -> 13.706996 | E22: =D22/D$4-1 -> -0.0022837611 | F22: =PL!F90 -> 7081.7702 | G22: =PL!F97 -> 14.146747 | H22: =G22/G$4-1 -> -0.14831331
A23: 情境 C（不如預期） | B23: C 市場；市占自 Advantest 搶回、利益率下調 | C23: =PL!E119 -> 6935.3189 | D23: =PL!E126 -> 13.675621 | E23: =D23/D$4-1 -> -0.0045675222 | F23: =PL!F119 -> 6522.5329 | G23: =PL!F126 -> 12.31275 | H23: =G23/G$4-1 -> -0.25872672
A25: 讀法：測試機市場（Advantest 模型）在 CY2027 已比 CY2026 高約四成，泰瑞達的 FY2027 主要取決於市場是否真的長到這個水準與市占；情境 B、C 的顆數係數從 2028 才生效，所以對 FY2027 無影響、對 FY2028 才明顯。
A40: 案例區塊：泰瑞達 SoC 市占 −5 個百分點（情境 A）
A41: 項目 | B41: 單位 | C41: FY2025A | D41: FY2026（錨點） | E41: FY2027 | F41: FY2028 | G41: FY2029 | H41: 說明
A42: SoC 測試機市場 CY（Advantest 模型） | B42: US$B | C42: =mk_soc25 -> 6.9 | D42: =ms_A_2026 -> 11 | E42: =ms_A_2027*m_soc -> 15.414358 | F42: =ms_A_2028*m_soc -> 17.299184 | G42: =ms_A_2029*m_soc -> 19.236176
A43: 記憶體測試機市場 CY（Advantest 模型） | B43: US$B | C43: =mk_mem25 -> 2.1 | D43: =mm_A_2026 -> 2.75 | E43: =mm_A_2027 -> 3.9915065 | F43: =mm_A_2028 -> 5.1706953 | G43: =mm_A_2029 -> 6.3316064
A44: 泰瑞達 SoC 市占 | B44: % | C44: =a25_soc/(C42*1000) -> 0.27386957 | D44: =f26_soc/(D42*1000) -> 0.29539273 | E44: =s_soc_lo -> 0.24539273 | F44: =s_soc_lo -> 0.24539273 | G44: =s_soc_lo -> 0.24539273 | H44: FY2025、FY2026＝實績／錨點隱含；之後維持
A45: SoC 測試機營收 | B45: US$M | C45: =a25_soc -> 1889.7 | D45: =f26_soc -> 3249.32 | E45: =E42*1000*E44 -> 3782.5714 | F45: =F42*1000*F44 -> 4245.0939 | G45: =G42*1000*G44 -> 4720.4177 | H45: 市場 × 市占
A46: 泰瑞達記憶體測試機市占 | B46: % | C46: =a25_mem/(C43*1000) -> 0.24042857 | D46: =f26_mem/(D43*1000) -> 0.31675636 | E46: =s_mem -> 0.31675636 | F46: =s_mem -> 0.31675636 | G46: =s_mem -> 0.31675636
A47: 記憶體測試機營收 | B47: US$M | C47: =a25_mem -> 504.9 | D47: =f26_mem -> 871.08 | E47: =E43*1000*E46 -> 1264.3351 | F47: =F43*1000*F46 -> 1637.8506 | G47: =G43*1000*G46 -> 2005.5766
A48: IST 營收（隨 SoC 市場） | B48: US$M | C48: =a25_ist -> 129.2 | D48: =f26_ist -> 195.51 | E48: =$D48*E42/$D42 -> 273.9692 | F48: =$D48*F42/$D42 -> 307.4694 | G48: =$D48*G42/$D42 -> 341.8968 | H48: FY2026 × SoC 市場相對 CY2026
A49: 半導體測試營收 | B49: US$M | C49: =C45+C47+C48 -> 2523.8 | D49: =D45+D47+D48 -> 4315.91 | E49: =E45+E47+E48 -> 5320.8756 | F49: =F45+F47+F48 -> 6190.4139 | G49: =G45+G47+G48 -> 7067.8912
A50: Product Test 營收 | B50: US$M | C50: =a25_pt -> 358 | D50: =f26_pt -> 394.17 | E50: =D50*(1+g_pt_A) -> 425.7036 | F50: =E50*(1+g_pt_A) -> 459.75989 | G50: =F50*(1+g_pt_A) -> 496.54068
A51: 測試事業營收（半導體測試＋Product Test） | B51: US$M | C51: =C49+C50 -> 2881.8 | D51: =D49+D50 -> 4710.08 | E51: =E49+E50 -> 5746.5792 | F51: =F49+F50 -> 6650.1738 | G51: =G49+G50 -> 7564.4319
A52: 測試事業稅前利益 | B52: US$M | C52: =a25_ttest -> 761.4 | D52: =f26_ttest -> 1643.8307 | E52: =t_inc*E51-t_fix+0*E51 -> 2144.1036 | F52: =t_inc*F51-t_fix+0*F51 -> 2580.2291 | G52: =t_inc*G51-t_fix+0*G51 -> 3021.5014 | H52: 增量利益率 × 營收 − 固定成本（兩點推導）；C 情境另加價格競爭調整
A53: 測試事業稅前利益率 | B53: % | C53: =C52/C51 -> 0.26420987 | D53: =D52/D51 -> 0.34900272 | E53: =E52/E51 -> 0.37310954 | F53: =F52/F51 -> 0.38799424 | G53: =G52/G51 -> 0.39943535
A54: 機器人營收（不隨 AI 情境） | B54: US$M | C54: =a25_rob -> 308.3 | D54: =f26_rob -> 401.52 | E54: =D54*(1+g_rob) -> 441.672 | F54: =E54*(1+g_rob) -> 485.8392 | G54: =F54*(1+g_rob) -> 534.42312
A55: 機器人稅前利益 | B55: US$M | C55: =a25_trob -> -99.4 | D55: =f26_trob -> -3.5 | E55: =E54*rm_2027 -> 8.83344 | F55: =F54*rm_2028 -> 19.433568 | G55: =G54*rm_2029 -> 26.721156
A56: 公司與沖銷 | B56: US$M | C56: =a25_corp -> -8.8 | D56: =f26_corp -> -10.4 | E56: =corp -> -10.4 | F56: =corp -> -10.4 | G56: =corp -> -10.4
A57: 營收 | B57: US$M | C57: =C51+C54 -> 3190.1 | D57: =D51+D54 -> 5111.6 | E57: =E51+E54 -> 6188.2512 | F57: =F51+F54 -> 7136.013 | G57: =G51+G54 -> 8098.855
A58: 稅前利益 | B58: US$M | C58: =C52+C55+C56 -> 653.2 | D58: =D52+D55+D56 -> 1629.9307 | E58: =E52+E55+E56 -> 2142.537 | F58: =F52+F55+F56 -> 2589.2627 | G58: =G52+G55+G56 -> 3037.8226
A59: 稅前利益率 | B59: % | C59: =C58/C57 -> 0.20475847 | D59: =D58/D57 -> 0.31886899 | E59: =E58/E57 -> 0.34622657 | F59: =F58/F57 -> 0.36284444 | G59: =G58/G57 -> 0.37509285
A60: 所得稅 | B60: US$M | C60: =a25_tax -> 79.3 | D60: =f26_tax -> 231.05474 | E60: =E58*etr -> 303.72046 | F60: =F58*etr -> 367.04713 | G60: =G58*etr -> 430.63382
A61: 權益法投資損益（Technoprobe） | B61: US$M | C61: =a25_aff -> -19.9 | D61: =f26_aff -> -13.2 | E61: =aff -> -13.2 | F61: =aff -> -13.2 | G61: =aff -> -13.2
A62: 淨利 | B62: US$M | C62: =a25_ni -> 554 | D62: =f26_ni -> 1385.276 | E62: =E58-E60+E61 -> 1825.6165 | F62: =F58-F60+F61 -> 2209.0155 | G62: =G58-G60+G61 -> 2593.9888 | H62: FY2026＝錨點（上半年實績＋下半年指引）
A63: 稀釋股數 | B63: 百萬股 | C63: =a25_dsh -> 159.7 | D63: =sh26 -> 157.7 | E63: =sh26*(1-bb)^1 -> 156.123 | F63: =sh26*(1-bb)^2 -> 154.56177 | G63: =sh26*(1-bb)^3 -> 153.01615
A64: EPS（GAAP 稀釋） | B64: US$ | C64: =a25_eps -> 3.47 | D64: =D62/D63 -> 8.7842486 | E64: =E62/E63 -> 11.69345 | F64: =F62/F63 -> 14.292121 | G64: =G62/G63 -> 16.952385
A65: SoC 占營收 | B65: % | C65: =C45/C57 -> 0.59236388 | D65: =D45/D57 -> 0.63567572 | E65: =E45/E57 -> 0.61125045 | F65: =F45/F57 -> 0.59488315 | G65: =G45/G57 -> 0.58285001
A66: 毛利率（參考；不進 EPS） | B66: % | C66: =a25_gp/a25_rev -> 0.58222571 | D66: =f26_gm -> 0.59436565 | E66: =f26_gm+(Q!J13-a25_gp/a25_rev)/(Q!J4/Q!J10-a25_soc/a25_rev)*(E65-D65) -> 0.58679358 | F66: =f26_gm+(Q!J13-a25_gp/a25_rev)/(Q!J4/Q!J10-a25_soc/a25_rev)*(F65-D65) -> 0.58171957 | G66: =f26_gm+(Q!J13-a25_gp/a25_rev)/(Q!J4/Q!J10-a25_soc/a25_rev)*(G65-D65) -> 0.57798918 | H66: FY2026＋斜率 ×（SoC 占營收 − FY2026）；斜率由 FY2025 與上半年 FY2026 兩點推得；EPS 由事業別稅前利益推導，本列只供參考
A72: 案例區塊：泰瑞達 SoC 市占 +5 個百分點（情境 A）
A73: 項目 | B73: 單位 | C73: FY2025A | D73: FY2026（錨點） | E73: FY2027 | F73: FY2028 | G73: FY2029 | H73: 說明
A74: SoC 測試機市場 CY（Advantest 模型） | B74: US$B | C74: =mk_soc25 -> 6.9 | D74: =ms_A_2026 -> 11 | E74: =ms_A_2027*m_soc -> 15.414358 | F74: =ms_A_2028*m_soc -> 17.299184 | G74: =ms_A_2029*m_soc -> 19.236176
A75: 記憶體測試機市場 CY（Advantest 模型） | B75: US$B | C75: =mk_mem25 -> 2.1 | D75: =mm_A_2026 -> 2.75 | E75: =mm_A_2027 -> 3.9915065 | F75: =mm_A_2028 -> 5.1706953 | G75: =mm_A_2029 -> 6.3316064
A76: 泰瑞達 SoC 市占 | B76: % | C76: =a25_soc/(C74*1000) -> 0.27386957 | D76: =f26_soc/(D74*1000) -> 0.29539273 | E76: =s_soc_hi -> 0.34539273 | F76: =s_soc_hi -> 0.34539273 | G76: =s_soc_hi -> 0.34539273 | H76: FY2025、FY2026＝實績／錨點隱含；之後維持
A77: SoC 測試機營收 | B77: US$M | C77: =a25_soc -> 1889.7 | D77: =f26_soc -> 3249.32 | E77: =E74*1000*E76 -> 5324.0072 | F77: =F74*1000*F76 -> 5975.0122 | G77: =G74*1000*G76 -> 6644.0354 | H77: 市場 × 市占
A78: 泰瑞達記憶體測試機市占 | B78: % | C78: =a25_mem/(C75*1000) -> 0.24042857 | D78: =f26_mem/(D75*1000) -> 0.31675636 | E78: =s_mem -> 0.31675636 | F78: =s_mem -> 0.31675636 | G78: =s_mem -> 0.31675636
A79: 記憶體測試機營收 | B79: US$M | C79: =a25_mem -> 504.9 | D79: =f26_mem -> 871.08 | E79: =E75*1000*E78 -> 1264.3351 | F79: =F75*1000*F78 -> 1637.8506 | G79: =G75*1000*G78 -> 2005.5766
A80: IST 營收（隨 SoC 市場） | B80: US$M | C80: =a25_ist -> 129.2 | D80: =f26_ist -> 195.51 | E80: =$D80*E74/$D74 -> 273.9692 | F80: =$D80*F74/$D74 -> 307.4694 | G80: =$D80*G74/$D74 -> 341.8968 | H80: FY2026 × SoC 市場相對 CY2026
A81: 半導體測試營收 | B81: US$M | C81: =C77+C79+C80 -> 2523.8 | D81: =D77+D79+D80 -> 4315.91 | E81: =E77+E79+E80 -> 6862.3114 | F81: =F77+F79+F80 -> 7920.3323 | G81: =G77+G79+G80 -> 8991.5088
A82: Product Test 營收 | B82: US$M | C82: =a25_pt -> 358 | D82: =f26_pt -> 394.17 | E82: =D82*(1+g_pt_A) -> 425.7036 | F82: =E82*(1+g_pt_A) -> 459.75989 | G82: =F82*(1+g_pt_A) -> 496.54068
A83: 測試事業營收（半導體測試＋Product Test） | B83: US$M | C83: =C81+C82 -> 2881.8 | D83: =D81+D82 -> 4710.08 | E83: =E81+E82 -> 7288.015 | F83: =F81+F82 -> 8380.0921 | G83: =G81+G82 -> 9488.0495
A84: 測試事業稅前利益 | B84: US$M | C84: =a25_ttest -> 761.4 | D84: =f26_ttest -> 1643.8307 | E84: =t_inc*E83-t_fix+0*E83 -> 2888.0872 | F84: =t_inc*F83-t_fix+0*F83 -> 3415.185 | G84: =t_inc*G83-t_fix+0*G83 -> 3949.9475 | H84: 增量利益率 × 營收 − 固定成本（兩點推導）；C 情境另加價格競爭調整
A85: 測試事業稅前利益率 | B85: % | C85: =C84/C83 -> 0.26420987 | D85: =D84/D83 -> 0.34900272 | E85: =E84/E83 -> 0.39627898 | F85: =F84/F83 -> 0.40753549 | G85: =G84/G83 -> 0.41630764
A86: 機器人營收（不隨 AI 情境） | B86: US$M | C86: =a25_rob -> 308.3 | D86: =f26_rob -> 401.52 | E86: =D86*(1+g_rob) -> 441.672 | F86: =E86*(1+g_rob) -> 485.8392 | G86: =F86*(1+g_rob) -> 534.42312
A87: 機器人稅前利益 | B87: US$M | C87: =a25_trob -> -99.4 | D87: =f26_trob -> -3.5 | E87: =E86*rm_2027 -> 8.83344 | F87: =F86*rm_2028 -> 19.433568 | G87: =G86*rm_2029 -> 26.721156
A88: 公司與沖銷 | B88: US$M | C88: =a25_corp -> -8.8 | D88: =f26_corp -> -10.4 | E88: =corp -> -10.4 | F88: =corp -> -10.4 | G88: =corp -> -10.4
A89: 營收 | B89: US$M | C89: =C83+C86 -> 3190.1 | D89: =D83+D86 -> 5111.6 | E89: =E83+E86 -> 7729.687 | F89: =F83+F86 -> 8865.9313 | G89: =G83+G86 -> 10022.473
A90: 稅前利益 | B90: US$M | C90: =C84+C87+C88 -> 653.2 | D90: =D84+D87+D88 -> 1629.9307 | E90: =E84+E87+E88 -> 2886.5206 | F90: =F84+F87+F88 -> 3424.2185 | G90: =G84+G87+G88 -> 3966.2686
A91: 稅前利益率 | B91: % | C91: =C90/C89 -> 0.20475847 | D91: =D90/D89 -> 0.31886899 | E91: =E90/E89 -> 0.37343305 | F91: =F90/F89 -> 0.38622209 | G91: =G90/G89 -> 0.39573754
A92: 所得稅 | B92: US$M | C92: =a25_tax -> 79.3 | D92: =f26_tax -> 231.05474 | E92: =E90*etr -> 409.18564 | F92: =F90*etr -> 485.4083 | G92: =G90*etr -> 562.24791
A93: 權益法投資損益（Technoprobe） | B93: US$M | C93: =a25_aff -> -19.9 | D93: =f26_aff -> -13.2 | E93: =aff -> -13.2 | F93: =aff -> -13.2 | G93: =aff -> -13.2
A94: 淨利 | B94: US$M | C94: =a25_ni -> 554 | D94: =f26_ni -> 1385.276 | E94: =E90-E92+E93 -> 2464.135 | F94: =F90-F92+F93 -> 2925.6102 | G94: =G90-G92+G93 -> 3390.8207 | H94: FY2026＝錨點（上半年實績＋下半年指引）
A95: 稀釋股數 | B95: 百萬股 | C95: =a25_dsh -> 159.7 | D95: =sh26 -> 157.7 | E95: =sh26*(1-bb)^1 -> 156.123 | F95: =sh26*(1-bb)^2 -> 154.56177 | G95: =sh26*(1-bb)^3 -> 153.01615
A96: EPS（GAAP 稀釋） | B96: US$ | C96: =a25_eps -> 3.47 | D96: =D94/D95 -> 8.7842486 | E96: =E94/E95 -> 15.783292 | F96: =F94/F95 -> 18.928421 | G96: =G94/G95 -> 22.159888
A97: SoC 占營收 | B97: % | C97: =C77/C89 -> 0.59236388 | D97: =D77/D89 -> 0.63567572 | E97: =E77/E89 -> 0.68877396 | F97: =F77/F89 -> 0.67392945 | G97: =G77/G89 -> 0.6629138
A98: 毛利率（參考；不進 EPS） | B98: % | C98: =a25_gp/a25_rev -> 0.58222571 | D98: =f26_gm -> 0.59436565 | E98: =f26_gm+(Q!J13-a25_gp/a25_rev)/(Q!J4/Q!J10-a25_soc/a25_rev)*(E97-D97) -> 0.6108266 | F98: =f26_gm+(Q!J13-a25_gp/a25_rev)/(Q!J4/Q!J10-a25_soc/a25_rev)*(F97-D97) -> 0.60622466 | G98: =f26_gm+(Q!J13-a25_gp/a25_rev)/(Q!J4/Q!J10-a25_soc/a25_rev)*(G97-D97) -> 0.60280971 | H98: FY2026＋斜率 ×（SoC 占營收 − FY2026）；斜率由 FY2025 與上半年 FY2026 兩點推得；EPS 由事業別稅前利益推導，本列只供參考
A104: 案例區塊：SoC 測試機市場 −15%（2027 起）（情境 A）
A105: 項目 | B105: 單位 | C105: FY2025A | D105: FY2026（錨點） | E105: FY2027 | F105: FY2028 | G105: FY2029 | H105: 說明
A106: SoC 測試機市場 CY（Advantest 模型） | B106: US$B | C106: =mk_soc25 -> 6.9 | D106: =ms_A_2026 -> 11 | E106: =ms_A_2027*m_soc_lo -> 13.102204 | F106: =ms_A_2028*m_soc_lo -> 14.704306 | G106: =ms_A_2029*m_soc_lo -> 16.35075
A107: 記憶體測試機市場 CY（Advantest 模型） | B107: US$B | C107: =mk_mem25 -> 2.1 | D107: =mm_A_2026 -> 2.75 | E107: =mm_A_2027 -> 3.9915065 | F107: =mm_A_2028 -> 5.1706953 | G107: =mm_A_2029 -> 6.3316064
A108: 泰瑞達 SoC 市占 | B108: % | C108: =a25_soc/(C106*1000) -> 0.27386957 | D108: =f26_soc/(D106*1000) -> 0.29539273 | E108: =s_soc -> 0.29539273 | F108: =s_soc -> 0.29539273 | G108: =s_soc -> 0.29539273 | H108: FY2025、FY2026＝實績／錨點隱含；之後維持
A109: SoC 測試機營收 | B109: US$M | C109: =a25_soc -> 1889.7 | D109: =f26_soc -> 3249.32 | E109: =E106*1000*E108 -> 3870.2959 | F109: =F106*1000*F108 -> 4343.5451 | G109: =G106*1000*G108 -> 4829.8926 | H109: 市場 × 市占
A110: 泰瑞達記憶體測試機市占 | B110: % | C110: =a25_mem/(C107*1000) -> 0.24042857 | D110: =f26_mem/(D107*1000) -> 0.31675636 | E110: =s_mem -> 0.31675636 | F110: =s_mem -> 0.31675636 | G110: =s_mem -> 0.31675636
A111: 記憶體測試機營收 | B111: US$M | C111: =a25_mem -> 504.9 | D111: =f26_mem -> 871.08 | E111: =E107*1000*E110 -> 1264.3351 | F111: =F107*1000*F110 -> 1637.8506 | G111: =G107*1000*G110 -> 2005.5766
A112: IST 營收（隨 SoC 市場） | B112: US$M | C112: =a25_ist -> 129.2 | D112: =f26_ist -> 195.51 | E112: =$D112*E106/$D106 -> 232.87382 | F112: =$D112*F106/$D106 -> 261.34899 | G112: =$D112*G106/$D106 -> 290.61228 | H112: FY2026 × SoC 市場相對 CY2026
A113: 半導體測試營收 | B113: US$M | C113: =C109+C111+C112 -> 2523.8 | D113: =D109+D111+D112 -> 4315.91 | E113: =E109+E111+E112 -> 5367.5048 | F113: =F109+F111+F112 -> 6242.7447 | G113: =G109+G111+G112 -> 7126.0815
A114: Product Test 營收 | B114: US$M | C114: =a25_pt -> 358 | D114: =f26_pt -> 394.17 | E114: =D114*(1+g_pt_A) -> 425.7036 | F114: =E114*(1+g_pt_A) -> 459.75989 | G114: =F114*(1+g_pt_A) -> 496.54068
A115: 測試事業營收（半導體測試＋Product Test） | B115: US$M | C115: =C113+C114 -> 2881.8 | D115: =D113+D114 -> 4710.08 | E115: =E113+E114 -> 5793.2084 | F115: =F113+F114 -> 6702.5046 | G115: =G113+G114 -> 7622.6222
A116: 測試事業稅前利益 | B116: US$M | C116: =a25_ttest -> 761.4 | D116: =f26_ttest -> 1643.8307 | E116: =t_inc*E115-t_fix+0*E115 -> 2166.6094 | F116: =t_inc*F115-t_fix+0*F115 -> 2605.4869 | G116: =t_inc*G115-t_fix+0*G115 -> 3049.5874 | H116: 增量利益率 × 營收 − 固定成本（兩點推導）；C 情境另加價格競爭調整
A117: 測試事業稅前利益率 | B117: % | C117: =C116/C115 -> 0.26420987 | D117: =D116/D115 -> 0.34900272 | E117: =E116/E115 -> 0.37399128 | F117: =F116/F115 -> 0.38873332 | G117: =G116/G115 -> 0.40007064
A118: 機器人營收（不隨 AI 情境） | B118: US$M | C118: =a25_rob -> 308.3 | D118: =f26_rob -> 401.52 | E118: =D118*(1+g_rob) -> 441.672 | F118: =E118*(1+g_rob) -> 485.8392 | G118: =F118*(1+g_rob) -> 534.42312
A119: 機器人稅前利益 | B119: US$M | C119: =a25_trob -> -99.4 | D119: =f26_trob -> -3.5 | E119: =E118*rm_2027 -> 8.83344 | F119: =F118*rm_2028 -> 19.433568 | G119: =G118*rm_2029 -> 26.721156
A120: 公司與沖銷 | B120: US$M | C120: =a25_corp -> -8.8 | D120: =f26_corp -> -10.4 | E120: =corp -> -10.4 | F120: =corp -> -10.4 | G120: =corp -> -10.4
A121: 營收 | B121: US$M | C121: =C115+C118 -> 3190.1 | D121: =D115+D118 -> 5111.6 | E121: =E115+E118 -> 6234.8804 | F121: =F115+F118 -> 7188.3438 | G121: =G115+G118 -> 8157.0453
A122: 稅前利益 | B122: US$M | C122: =C116+C119+C120 -> 653.2 | D122: =D116+D119+D120 -> 1629.9307 | E122: =E116+E119+E120 -> 2165.0428 | F122: =F116+F119+F120 -> 2614.5205 | G122: =G116+G119+G120 -> 3065.9085
A123: 稅前利益率 | B123: % | C123: =C122/C121 -> 0.20475847 | D123: =D122/D121 -> 0.31886899 | E123: =E122/E121 -> 0.34724689 | F123: =F122/F121 -> 0.36371667 | G123: =G122/G121 -> 0.37586018
A124: 所得稅 | B124: US$M | C124: =a25_tax -> 79.3 | D124: =f26_tax -> 231.05474 | E124: =E122*etr -> 306.91083 | F124: =F122*etr -> 370.62761 | G124: =G122*etr -> 434.61521
A125: 權益法投資損益（Technoprobe） | B125: US$M | C125: =a25_aff -> -19.9 | D125: =f26_aff -> -13.2 | E125: =aff -> -13.2 | F125: =aff -> -13.2 | G125: =aff -> -13.2
A126: 淨利 | B126: US$M | C126: =a25_ni -> 554 | D126: =f26_ni -> 1385.276 | E126: =E122-E124+E125 -> 1844.932 | F126: =F122-F124+F125 -> 2230.6928 | G126: =G122-G124+G125 -> 2618.0933 | H126: FY2026＝錨點（上半年實績＋下半年指引）
...

Sheet Sources
A1: 來源（公司 SEC 原文在建置環境可開啟；法說數字取自逐字稿摘要網站，待以公司原始逐字稿複核）
A2: 公司：2Q26 新聞稿（8-K Ex.99.1，2026-07-28） | B2: https://www.sec.gov/Archives/edgar/data/97210/000119312526321933/ter-ex99_1.htm
A3: 公司：2Q26 10-Q（收入拆分、分部稅前利益） | B3: https://www.sec.gov/Archives/edgar/data/97210/000119312526327715/ter-20260628.htm
A4: 公司：1Q26 新聞稿（2026-04-28） | B4: https://www.sec.gov/Archives/edgar/data/97210/000119312526188706/ter-ex99_1.htm
A5: 公司：1Q26 10-Q | B5: https://www.sec.gov/Archives/edgar/data/97210/000119312526201058/ter-20260329.htm
A6: 公司：4Q25 與 FY2025 新聞稿（2026-02-02） | B6: https://www.sec.gov/Archives/edgar/data/97210/000119312526034348/ter-ex99_1.htm
A7: 公司：FY2025 10-K（收入拆分 2023–2025、分部稅前利益） | B7: https://www.sec.gov/Archives/edgar/data/97210/000119312526059002/ter-20251231.htm
A8: 公司：3Q25 新聞稿與 10-Q | B8: https://www.sec.gov/Archives/edgar/data/97210/000119312525258477/ter-20250928.htm
A9: 公司：1Q25、2Q25 新聞稿 | B9: https://www.sec.gov/Archives/edgar/data/97210/000095017025099876/ter-ex99_1.htm
A10: SEC XBRL company facts（年度 EPS、淨利、營收、股東權益） | B10: https://data.sec.gov/api/xbrl/companyfacts/CIK0000097210.json
A11: 公司：3Q26 財報日期公告（2026-10-27 盤後） | B11: https://investingnews.com/teradyne-to-announce-third-quarter-2026-results/
A12: earningswhispers：2Q26 法說逐字稿（測試對 WFE 比、份額、上半年占比） | B12: https://earningswhispers.com/transcript/TER/Q22026
A13: gurufocus：2Q26 法說摘要（SoC 843、記憶體 212、IST 67） | B13: https://www.gurufocus.com/news/8987636/teradyne-inc-ter-q2-2026-earnings-call-highlights-record-revenue-and-robust-ai-demand-propel-growth
... A23: stockanalysis：同業遠期 P/E（Cohu、FormFactor；Advantest、KLA、AMAT 同站） | B23: https://stockanalysis.com/stocks/cohu/statistics/
A24: 本 repo：advantest／tsmc／markets/equipment 成品（唯讀）
A25: SemiAnalysis | B25: 未使用
