Workbook

Sheet README
A1: Arm Holdings（ARM）個股模型 v0.1（AI 半導體 Project：運算次產業；CPU 架構授權與權利金） 2026-10-31
A2: 版本：v0.1（2026-10-31，初版）。樣板 crdo/（美股、估值 v2）；敏感度與份額寫法比照 tuc/；行業變數讀 Siliconomics 快照 v0.10（siliconomics_snapshot_v0.10.json）。待 FQ2 財報（2026-11-04）更新錨點。
A3: 模型命題：Arm 的權利金＝各市場晶片出貨 × 每顆權利金率：智慧型手機（出貨持平到下滑，成長靠 v9 與 CSS 費率）、資料中心 Neoverse（NVIDIA Grace／Vera 顆數讀 Siliconomics、雲端自研 CPU 年增、每顆費率隨核心數上升）、車用、物聯網與其他；授權及其他＝授權（含 SoftBank 協議）＋自研 Arm AGI CPU 晶片。
A4: 核心問題：現價約 95 倍共識前瞻 EPS，市場是否已把資料中心權利金倍增、CSS 費率上升與自研晶片（客戶需求逾 20 億美元）全部算進去；Qualcomm 判決與手機出貨下修會讓權利金少多少。
A5: 會計年度：FY(t) 於 t 年 3 月 31 日結束（FY2027＝2026-04～2027-03）；上游日曆年以 9/12 × CY(t−1)＋3/12 × CY(t) 換算。預測期 FY2028–FY2029 由驅動因子推導，FY2030–FY2032 為收斂法。金額：十億美元；EPS：non-GAAP（GAAP EPS 另列）。
A6: 驅動因子：FY2027 錨點＝1Q27 實績＋2Q27 指引＋下半年年增假設；權利金分市場以 FY2026 比例（手機 43% 為 20-F，其餘 Assumed）拆分；FY2028 起資料中心＝FY2027 × CPU 顆數指數（NVIDIA 讀 Siliconomics 同字母情境）× 每顆費率指數；手機＝出貨 × 每支權利金（情境 A／B／C 費率年增 14%／11%／7%）；晶片營收情境 A／B／C。
A7: 估值：Val 第 0 節目標價＝0.5 × DCF 目標價（股東現金流＝EPS ×（1 − tp_g ÷ tp_roe），FY2027–FY2032 明確期＋永續，r 10%、g 4%，三情境權重 0.3／0.5／0.2，推到 12 個月後）＋0.5 × Comparable 目標價（高通、博通、邁威爾、Rambus、新思、益華前瞻 P/E 中位數 × 12 個月後前瞻 EPS）。本版未做先驗，無 Andy 合理 P/E 對照。Bloomberg 前瞻倍數待取（ARM 本身沒有，相對倍數係數＝1）。
A8: 已知限制：(1) 公司只揭露手機占權利金比例，其他市場拆分為 Assumed；(2) AGI CPU 晶片營收所在列與毛利率未揭露；(3) non-GAAP EPS 排除股票薪酬（FY2026 約占 non-GAAP 淨利一半）；(4) Qualcomm 法官審理部分未判、損害賠償未知；(5) 年底 P/E 只有 2023–2025 三年；(6) 2Q27 財報（2026-11-04）未納入。
A11: 相對倍數調整：加權目標價中的 Comparable 用相對倍數調整後的值（Val 第 0.5 節；tools/relative_multiple.py）。ARM 無 Bloomberg 前瞻倍數歷史（待取），係數＝1（不調整）。「Comparable 目標價（市場主流同業法）」不調整。
A13: In 頁版面（個股模型原則第 8 節）：D／F 欄＝敏感度低／高，只用於 Sens 頁、不進目標價；In 頁最後一節「情境驅動對照」把情境專屬輸入三情境並排（只引用上方各列，純展示）。
A15: ="投資建議："&Val!B46&"（依上檔空間固定規則；加權目標價上檔空間 "&TEXT(Val!B43,"+0.0%;−0.0%")&"）" -> 投資建議：強力放空（依上檔空間固定規則；加權目標價上檔空間 −76.6%）
A16: 重點觀察 1：目標價 US$53.52（DCF 34.56、Comparable 72.48 各半），比現價 228.88（2026-10-30）低 76.6%，級距小於 −50%、投資建議強力放空；Comparable 單獨為 −68.3%。差距全部來自倍數：本模型 12 個月後前瞻 EPS 2.90 反而比共識前瞻 EPS 高 20.1%（期間晚約一年），但現價約 94.7 倍共識前瞻 EPS、共識目標價 290.71 隱含 120.3 倍，同業前瞻 P/E 中位數只有 25.0 倍。DCF 偏低另因 GAAP ROE 近三年平均 10.5%（再投資率 38%）。SoftBank 持股約九成，流通市值約 247 億美元（總市值 2,472 億），流通量低可能撐住溢價，本模型不調整；ARM 無 Bloomberg 前瞻倍數，相對倍數係數＝1。
A17: 重點觀察 2：單一參數都翻不過來：最有利的單一案例是 DCF 權重 0.3（+14.2%），其次授權成長 15%（+6.8%）、營業費用年增 8%（+7.4%），目標價仍比現價低七成以上；授權成長 2% −10.3%、營業費用年增 18% −7.7%、晶片毛利率 35%／55% ±4.6%（Sens 頁）。
A18: 重點觀察 3：可追蹤的三件事：資料中心占權利金由 FY2026 14% 升到 FY2029 情境 B 24.9%（Grace／Vera 讀 Siliconomics、雲端自研 CPU 年增 30%）；AGI CPU 晶片營收 FY2028 情境 A／B／C＝14／10／5 億美元，對照公司稱 FY2027–28 客戶需求逾 20 億美元；Qualcomm 陪審團 2026-10-13 判 Arm 違約，法官審理部分待判。下一個檢驗點：2Q27 財報 2026-11-04（指引營收 13.8 億美元、non-GAAP EPS 0.47）。

Sheet In
A1: In — 輸入（藍字；基準欄 E）。金額：十億美元（US$B）；出貨：十億顆或百萬顆；比例：%。每個輸入附兩個來源（找不到者寫「未找到」）；公司原文算一個。【v0.1】基準欄 E 進主模型；D／F＝敏感度低／高，只用於 Sens 頁（一次動一個參數）、不進目標價；情境 A／B／C 的驅動見本頁最後一節「情境驅動對照」。
A2: 標記：Verified／Interested-party／Analogy／Assumed／Derived；Analogy、Assumed 給低／高區間。公司原文＝Arm 股東信與 6-K（SEC）、20-F、法說；公司指引為 Interested-party；共識與券商皆為 Interested-party。行業變數（加速器顆數、情境係數）讀 Siliconomics 快照 v0.10（siliconomics_snapshot_v0.10.json）；Siliconomics 沒有的行業變數（手機出貨、雲端自研 CPU 顆數）放本頁並標「待併入 Siliconomics」。
A3: 鍵 | B3: 項目 | C3: 單位 | D3: 敏感度低 | E3: 基準 | F3: 敏感度高 | G3: 標記 | H3: 來源1 | I3: 來源2／說明
A4: A. FY2027 錨點（1Q27 實績＋2Q27 公司指引＋下半年假設；2Q27 財報 2026-11-04 公布）
A5: q2_lg | B5: 2Q27 授權及其他年增（公司指引：mid-30%） | C5: % | D5: 0.3 | E5: 0.35 | F5: 0.38 | G5: Interested-party | H5: 公司 2Q27 指引：授權年增 mid-30%、權利金 low-teens、營收 13.8 億 ± 0.5 億美元（Longbridge 2026-07-29 轉述股東信） | I5: Hudson Labs：授權及其他年增約 30%
A6: q2_rg | B6: 2Q27 權利金年增（公司指引：low-teens） | C6: % | D6: 0.1 | E6: 0.12 | F6: 0.14 | G6: Interested-party | H6: 同上 | I6: 去年同期 6.20 億美元（2Q26）
A7: h2_lg | B7: 3Q27、4Q27 授權及其他年增 | C7: % | D7: 0.08 | E7: 0.2 | F7: 0.3 | G7: Assumed | H7: ACV 1Q27 年增 13%（股東信）；1Q27 授權年增 23%、2Q27 指引 mid-30% | I7: 去年同期 3Q26 5.05、4Q26 8.19 億美元（含 SoftBank 協議每季約 2 億美元）
A8: h2_rg | B8: 3Q27、4Q27 權利金年增 | C8: % | D8: 0.08 | E8: 0.15 | F8: 0.2 | G8: Assumed | H8: 1Q27 +22%、2Q27 指引 low-teens；資料中心權利金年增逾一倍（股東信） | I8: 管理層：FY2027 約 20% 成長「非常合理」（3Q26 法說，The Motley Fool 逐字稿）
A9: q2_opx | B9: 2Q27 non-GAAP 營業費用 | C9: US$B | E9: 0.78 | G9: Interested-party | H9: 公司 2Q27 指引約 7.8 億美元（股東信 2026-07-29） | I9: 1Q27 實績 7.33 億
A10: q3_opx | B10: 3Q27 non-GAAP 營業費用 | C10: US$B | D10: 0.78 | E10: 0.8 | F10: 0.83 | G10: Assumed | H10: 2Q27 指引 7.8 億；FY2026 季增約 2–4%（股東信） | I10: AGI CPU 與 CSS 研發投入
A11: q4_opx | B11: 4Q27 non-GAAP 營業費用 | C11: US$B | D11: 0.8 | E11: 0.82 | F11: 0.86 | G11: Assumed | H11: 同上 | I11: —
A12: cogs_r | B12: IP 營業成本 ÷ 營收（non-GAAP；不含晶片） | C12: % | D12: 0.015 | E12: 0.019 | F12: 0.025 | G12: Derived | H12: 1Q27 non-GAAP 毛利率 98.1%（股東信） | I12: FY2026：（營收 − 營業費用 − 營業利益）÷ 營收＝1.8%
A13: q_oth | B13: 每季業外收益（利息，non-GAAP） | C13: US$B | D13: 0.025 | E13: 0.034 | F13: 0.04 | G13: Derived | H13: 1Q27 non-GAAP 稅前 5.65 億 − 營業利益 5.31 億（股東信） | I13: 現金與短期投資利息
A14: q_tx | B14: non-GAAP 有效稅率（FY2027） | C14: % | D14: 0.13 | E14: 0.15 | F14: 0.18 | G14: Derived | H14: 1Q27 non-GAAP 稅 0.85 ÷ 稅前 5.65＝15.0%（股東信調節表） | I14: 英國 OECD 最低稅 15%
A15: q_sh | B15: 稀釋加權股數（FY2027） | C15: 十億股 | E15: 1.08 | G15: Derived | H15: 1Q27 1,078 百萬股（股東信） | I15: 4Q26 1,068；20-F：2026-03-31 普通股 1,064 百萬股
A16: chip_27 | B16: Arm AGI CPU 晶片營收 FY2027（含在授權及其他錨點內） | C16: US$B | D16: 0 | E16: 0.15 | F16: 0.4 | G16: Assumed | H16: 公司：AGI CPU 2026-03 推出，首批已交付多家美、中客戶；FY2027–28 客戶需求逾 20 億美元（股東信 2026-07-29） | I16: 晶片營收所在列公司未揭露：未找到；本模型暫列授權及其他之下
A17: B. 權利金分市場（FY2026 基期比例；公司只揭露手機占比）
A18: ph_s | B18: FY2026 智慧型手機（行動應用處理器）÷ 權利金 | C18: % | D18: 0.4 | E18: 0.43 | F18: 0.46 | G18: Verified | H18: 20-F（FY2026）：行動應用處理器權利金約占權利金 43% | I18: 管理層：手機約 40–45%（3Q26 法說）
A19: dc_s | B19: FY2026 資料中心（Neoverse）÷ 權利金 | C19: % | D19: 0.1 | E19: 0.14 | F19: 0.19 | G19: Interested-party | H19: 管理層：資料中心「十幾到接近 20%」（3Q26 法說，The Motley Fool 逐字稿） | I19: 1Q27 資料中心權利金年增逾一倍（股東信）
A20: au_s | B20: FY2026 車用 ÷ 權利金 | C20: % | D20: 0.07 | E20: 0.09 | F20: 0.11 | G20: Assumed | H20: 管理層：車用雙位數成長（3Q26 法說）；占比未揭露：未找到 | I20: 物聯網與其他（含 PC、消費電子、嵌入式）＝殘差
A21: ph_u26 | B21: FY2026 智慧型手機出貨（全球） | C21: 十億支 | D21: 1.15 | E21: 1.22 | F21: 1.28 | G21: Assumed | H21: 全球手機年出貨約 12 億支（IDC 量級；本專案未建立） | I21: Siliconomics 無手機出貨：待併入 Siliconomics
A22: g_ph27 | B22: FY2027 手機權利金年增 | C22: % | D22: 0.08 | E22: 0.12 | F22: 0.18 | G22: Interested-party | H22: Hudson Labs：管理層預期 FY2027 手機權利金年增 high-teens（原 20% 以上） | I22: 記憶體漲價使手機出貨下修（聯發科預期約 −15%；管理層：出貨 −20% 使權利金 −1–2%）；本模型取保守值
A23: g_dc27 | B23: FY2027 資料中心權利金年增 | C23: % | D23: 0.5 | E23: 0.7 | F23: 0.95 | G23: Interested-party | H23: 1Q27 資料中心權利金年增逾一倍（股東信）；全年假設低於上半年（Assumed） | I23: Neoverse 核心出貨逾 15 億顆，近 9 個月 5 億（新聞稿 2026-07-29）
A24: g_au27 | B24: FY2027 車用權利金年增 | C24: % | D24: 0.08 | E24: 0.15 | F24: 0.22 | G24: Assumed | H24: 管理層：車用雙位數成長（3Q26 法說） | I24: 物聯網與其他 FY2027＝錨點權利金 − 三個市場（殘差）
A25: C. 權利金驅動（FY2028 起：出貨 × 每顆權利金率）
A26: g_phu28 | B26: 手機出貨年增 FY2028 | C26: % | D26: -0.08 | E26: -0.02 | F26: 0.03 | G26: Assumed | H26: 記憶體價格上漲壓抑 2026–27 手機出貨（聯發科預期約 −15%，3Q26 法說轉述） | I26: Siliconomics 無手機出貨：待併入 Siliconomics
A27: g_phu29 | B27: 手機出貨年增 FY2029 | C27: % | D27: -0.03 | E27: 0.01 | F27: 0.04 | G27: Assumed | H27: 成熟市場，回到低個位數（Assumed） | I27: Siliconomics 無手機出貨：待併入 Siliconomics
A28: phr_A | B28: 情境 A：手機每支權利金率年增（FY2028–29；v9、CSS 滲透） | C28: % | E28: 0.14 | G28: Assumed | H28: 管理層：v9 CSS 權利金率每代上升；CSS 占權利金 FY2026 進入十幾 %、未來兩年可能逾 50%（3Q26 法說） | I28: —
A29: phr_B | B29: 情境 B：手機每支權利金率年增（FY2028–29；v9、CSS 滲透） | C29: % | E29: 0.11 | G29: Assumed | H29: 同上；情境 B 為基準 | I29: —
A30: phr_C | B30: 情境 C：手機每支權利金率年增（FY2028–29；v9、CSS 滲透） | C30: % | E30: 0.07 | G30: Assumed | H30: 情境 C：Qualcomm 2026-10-13 陪審團判 Arm 違約（架構授權），Arm 難以要求 Qualcomm 改用較高費率；加上 CSS 推廣較慢 | I30: Qualcomm 訴訟：Paul Weiss 2026-10-13；法官審理部分 10-20 結辯，判決未出
A31: qc_adj | B31: Qualcomm 相關手機權利金調整（FY2028 起；基準 0） | C31: % | D31: -0.06 | E31: 0 | F31: 0.02 | G31: Assumed | H31: 陪審團 2026-10-13 判 Arm 違反架構授權、干擾 Qualcomm 與 Meta 的業務關係（Paul Weiss）；損害賠償未揭露：未找到 | I31: 低值＝Qualcomm 擴大自研核心、Arm 失去部分手機權利金；高值＝和解後費率調升
A32: cpu_gpu | B32: 每顆 NVIDIA 資料中心 GPU 搭配的 Arm CPU（Grace／Vera） | C32: 顆 | D32: 0.4 | E32: 0.5 | F32: 0.5 | G32: Interested-party | H32: GB200／GB300 NVL72：72 顆 GPU 搭 36 顆 Grace；VR NVL144：72 顆封裝搭 36 顆 Vera（NVIDIA） | I32: 低值反映 HGX（x86 主機）出貨占比
A33: nvbw_26 | B33: NVIDIA Blackwell 顆數 CY2026（情境 A） | C33: 百萬顆 | E33: 5.4 | G33: Derived | H33: Siliconomics 快照 v0.10（siliconomics_snapshot_v0.10.json）｜SIF_UnitsPlat_bw[2026]；非本模型情境驅動（上游模型該情境的參考值） | I33: Siliconomics 加速器顆數（情境 A）；B、C 乘同字母顆數係數
A34: nvbw_27 | B34: NVIDIA Blackwell 顆數 CY2027（情境 A） | C34: 百萬顆 | E34: 2.4 | G34: Derived | H34: Siliconomics 快照 v0.10（siliconomics_snapshot_v0.10.json）｜SIF_UnitsPlat_bw[2027]；非本模型情境驅動（上游模型該情境的參考值） | I34: Siliconomics 加速器顆數（情境 A）；B、C 乘同字母顆數係數
A35: nvbw_28 | B35: NVIDIA Blackwell 顆數 CY2028（情境 A） | C35: 百萬顆 | E35: 0.5 | G35: Derived | H35: Siliconomics 快照 v0.10（siliconomics_snapshot_v0.10.json）｜SIF_UnitsPlat_bw[2028]；非本模型情境驅動（上游模型該情境的參考值） | I35: Siliconomics 加速器顆數（情境 A）；B、C 乘同字母顆數係數
A36: nvbw_29 | B36: NVIDIA Blackwell 顆數 CY2029（情境 A） | C36: 百萬顆 | E36: 0.25 | G36: Derived | H36: Siliconomics 快照 v0.10（siliconomics_snapshot_v0.10.json）｜SIF_UnitsPlat_bw[2029]；非本模型情境驅動（上游模型該情境的參考值） | I36: Siliconomics 加速器顆數（情境 A）；B、C 乘同字母顆數係數
A37: nvrb_26 | B37: NVIDIA Rubin 顆數 CY2026（情境 A） | C37: 百萬顆 | E37: 1.7 | G37: Derived | H37: Siliconomics 快照 v0.10（siliconomics_snapshot_v0.10.json）｜SIF_UnitsPlat_rb[2026]；非本模型情境驅動（上游模型該情境的參考值） | I37: Siliconomics 加速器顆數（情境 A）；B、C 乘同字母顆數係數
A38: nvrb_27 | B38: NVIDIA Rubin 顆數 CY2027（情境 A） | C38: 百萬顆 | E38: 7 | G38: Derived | H38: Siliconomics 快照 v0.10（siliconomics_snapshot_v0.10.json）｜SIF_UnitsPlat_rb[2027]；非本模型情境驅動（上游模型該情境的參考值） | I38: Siliconomics 加速器顆數（情境 A）；B、C 乘同字母顆數係數
A39: nvrb_28 | B39: NVIDIA Rubin 顆數 CY2028（情境 A） | C39: 百萬顆 | E39: 7 | G39: Derived | H39: Siliconomics 快照 v0.10（siliconomics_snapshot_v0.10.json）｜SIF_UnitsPlat_rb[2028]；非本模型情境驅動（上游模型該情境的參考值） | I39: Siliconomics 加速器顆數（情境 A）；B、C 乘同字母顆數係數
A40: nvrb_29 | B40: NVIDIA Rubin 顆數 CY2029（情境 A） | C40: 百萬顆 | E40: 8.05 | G40: Derived | H40: Siliconomics 快照 v0.10（siliconomics_snapshot_v0.10.json）｜SIF_UnitsPlat_rb[2029]；非本模型情境驅動（上游模型該情境的參考值） | I40: Siliconomics 加速器顆數（情境 A）；B、C 乘同字母顆數係數
A41: nvru_26 | B41: NVIDIA Rubin Ultra 顆數 CY2026（情境 A） | C41: 百萬顆 | E41: 0 | G41: Derived | H41: Siliconomics 快照 v0.10（siliconomics_snapshot_v0.10.json）｜SIF_UnitsPlat_ru[2026]；非本模型情境驅動（上游模型該情境的參考值） | I41: Siliconomics 加速器顆數（情境 A）；B、C 乘同字母顆數係數
A42: nvru_27 | B42: NVIDIA Rubin Ultra 顆數 CY2027（情境 A） | C42: 百萬顆 | E42: 0.3 | G42: Derived | H42: Siliconomics 快照 v0.10（siliconomics_snapshot_v0.10.json）｜SIF_UnitsPlat_ru[2027]；非本模型情境驅動（上游模型該情境的參考值） | I42: Siliconomics 加速器顆數（情境 A）；B、C 乘同字母顆數係數
A43: nvru_28 | B43: NVIDIA Rubin Ultra 顆數 CY2028（情境 A） | C43: 百萬顆 | E43: 2 | G43: Derived | H43: Siliconomics 快照 v0.10（siliconomics_snapshot_v0.10.json）｜SIF_UnitsPlat_ru[2028]；非本模型情境驅動（上游模型該情境的參考值） | I43: Siliconomics 加速器顆數（情境 A）；B、C 乘同字母顆數係數
A44: nvru_29 | B44: NVIDIA Rubin Ultra 顆數 CY2029（情境 A） | C44: 百萬顆 | E44: 2.3 | G44: Derived | H44: Siliconomics 快照 v0.10（siliconomics_snapshot_v0.10.json）｜SIF_UnitsPlat_ru[2029]；非本模型情境驅動（上游模型該情境的參考值） | I44: Siliconomics 加速器顆數（情境 A）；B、C 乘同字母顆數係數
... A50: uc29_C | B50: 情境 C：CY2029 顆數係數 | C50: x | E50: 0.6 | G50: Derived | H50: Siliconomics 快照 v0.10（siliconomics_snapshot_v0.10.json）｜SIF_UnitsCoef_C[2029] | I50: A＝1；B＝0.8／0.85；C＝0.6（與台積電、NVIDIA 模型同一套）
A51: nv_cy25 | B51: NVIDIA 資料中心 GPU 顆數 CY2025（Blackwell＋Hopper） | C51: 百萬顆 | D51: 5 | E51: 6 | F51: 7 | G51: Assumed | H51: Siliconomics 加速器顆數從 2026 年起：CY2025 未建立，待併入 Siliconomics | I51: 只用於 FY2026 的 NVIDIA CPU 指數基期
A52: w_nv | B52: FY2027 資料中心權利金中 NVIDIA Grace／Vera 的比重 | C52: % | D52: 0.2 | E52: 0.35 | F52: 0.5 | G52: Assumed | H52: 公司未揭露客戶別：未找到；NVIDIA Vera 88 核、AWS Graviton5 192 核、Microsoft Cobalt 200 132 核（3Q26 法說） | I52: 其餘＝雲端自研 CPU（Graviton、Axion、Cobalt 等）與網通、DPU
A53: g_hc | B53: 雲端自研 Arm CPU 顆數年增（Graviton、Axion、Cobalt 等；× 同字母顆數係數） | C53: % | D53: 0.15 | E53: 0.3 | F53: 0.45 | G53: Assumed | H53: 管理層：預期 Arm 在前幾大雲端業者的 CPU 份額達 50%（3Q26 法說）；IDC：Arm 加速伺服器平台支出兩季近倍增（新聞稿 2026-07-29） | I53: Siliconomics 無 CPU 顆數：待併入 Siliconomics
A54: dcr | B54: 資料中心每顆權利金率年增（核心數、CSS） | C54: % | D54: 0.04 | E54: 0.1 | F54: 0.15 | G54: Assumed | H54: 核心數：Graviton4 96 → Graviton5 192、Vera 72 → 88（3Q26 法說） | I54: —
A55: g_au | B55: 車用權利金年增（FY2028 起） | C55: % | D55: 0.08 | E55: 0.15 | F55: 0.22 | G55: Assumed | H55: 車用雙位數成長（3Q26 法說） | I55: —
A56: g_iot | B56: 物聯網與其他權利金年增（FY2028 起） | C56: % | D56: -0.02 | E56: 0.04 | F56: 0.08 | G56: Assumed | H56: 含 PC（Windows on Arm、NVIDIA RTX Spark）、消費電子、嵌入式；FY2027 殘差約持平 | I56: —
A57: D. 授權及其他（含 SoftBank 協議）與 Arm AGI CPU 晶片
A58: g_lic | B58: 授權（不含晶片）年增（FY2028 起） | C58: % | D58: 0.02 | E58: 0.1 | F58: 0.15 | G58: Assumed | H58: ACV 1Q27 年增 13%（股東信）；SoftBank 協議 3Q26 認列 2.0 億美元／季（3Q26 法說） | I58: SoftBank 協議期間與續約：未找到
A59: chip28_A | B59: 情境 A：Arm AGI CPU 晶片營收 FY2028 | C59: US$B | E59: 1.4 | G59: Assumed | H59: 客戶需求 FY2027–28 逾 20 億美元，已取得 10 億美元的產能（股東信 2026-07-29）；公司稱朝此業務 150 億美元的預估前進（4Q26 股東信） | I59: 產能為主要限制：第二個 10 億美元的製造產能尚未鎖定（Yahoo Finance 轉述 WSJ）
A60: chip28_B | B60: 情境 B：Arm AGI CPU 晶片營收 FY2028 | C60: US$B | E60: 1 | G60: Assumed | H60: 同上 | I60: —
A61: chip28_C | B61: 情境 C：Arm AGI CPU 晶片營收 FY2028 | C61: US$B | E61: 0.5 | G61: Assumed | H61: 同上 | I61: —
A62: chip29_A | B62: 情境 A：Arm AGI CPU 晶片營收 FY2029 | C62: US$B | E62: 3 | G62: Assumed | H62: 同上 | I62: —
A63: chip29_B | B63: 情境 B：Arm AGI CPU 晶片營收 FY2029 | C63: US$B | E63: 2 | G63: Assumed | H63: 同上 | I63: —
A64: chip29_C | B64: 情境 C：Arm AGI CPU 晶片營收 FY2029 | C64: US$B | E64: 0.8 | G64: Assumed | H64: 同上 | I64: —
A65: chip_gm | B65: 晶片毛利率 | C65: % | D65: 0.35 | E65: 0.45 | F65: 0.55 | G65: Assumed | H65: 晶片毛利率公司未揭露：未找到 | I65: Analogy：CPU 晶片業者 50–60%；首代晶片、委外製造與客戶議價（Assumed 較低）
A66: E. 營業費用、業外、稅與股數（FY2028 起；non-GAAP）
A67: g_opx | B67: non-GAAP 營業費用年增 | C67: % | D67: 0.08 | E67: 0.13 | F67: 0.18 | G67: Assumed | H67: FY2026 non-GAAP 營業費用年增 33%（研發 +43%）；FY2027 錨點約 +15%（股東信） | I67: 晶片業務需持續研發與銷售投入
A68: oth_f | B68: 業外收益（每年） | C68: US$B | D68: 0.08 | E68: 0.14 | F68: 0.18 | G68: Derived | H68: 1Q27 0.034 × 4（股東信） | I68: —
A69: tx_f | B69: non-GAAP 有效稅率 | C69: % | D69: 0.13 | E69: 0.15 | F69: 0.18 | G69: Derived | H69: 同 q_tx | I69: —
A70: sh_g | B70: 稀釋股數年變動 | C70: % | D70: 0 | E70: 0.008 | F70: 0.015 | G70: Assumed | H70: FY2025 1,063 → FY2026 1,068 → 1Q27 1,078 百萬股（股東信） | I70: 股票薪酬發行；公司未大量買回
A71: F. 共識與券商（只作 Recon 對帳，不作校準）
A72: c_eps27 | B72: 共識 FY2027 non-GAAP EPS（S&P Global 平均） | C72: US$ | E72: 2.23 | G72: Interested-party | H72: https://stockanalysis.com/stocks/arm/forecast/（stockanalysis，更新 2026-10-21） | I72: 高 2.38、低 2.06
A73: c_rev27 | B73: 共識 FY2027 營收（平均） | C73: US$B | E73: 6.1 | G73: Interested-party | H73: https://stockanalysis.com/stocks/arm/forecast/ | I73: Hudson Labs：60.58 億美元
A74: c_q2rev | B74: 共識 2Q27 營收 | C74: US$B | E74: 1.376 | G74: Interested-party | H74: https://www.hudson-labs.com/research/arm-q2-2027-earnings-preview-arm-revenue-and-outlook | I74: 公司指引 13.8 億 ± 0.5 億
A75: G. 價格與股權
A76: px | B76: 股價（2026-10-30 收盤） | C76: US$ | E76: 228.88 | G76: Interested-party | H76: InvestSmart 價格歷史：2026-10-30 收盤 228.88（+0.77%） | I76: digrin 10 月現價 228.77；stockanalysis 10-23 收盤 210.33
A77: sb_own | B77: SoftBank 集團持股（約） | C77: % | E77: 0.9 | G77: Interested-party | H77: 20-F：SoftBank 集團為控股股東；約九成（whoistheownerof「SoftBank's 90% grip」） | I77: 流通股約一成：只作說明，不進目標價
A78: H. 目標價（DCF 與 Comparable 加權）與收斂法參數（黃底＝Assumed，Andy 可改）
A79: tp_wA | B79: 目標價情境權重：情境 A（順利） | C79: 權重 | E79: 0.3 | G79: Assumed | H79: Andy 可改（2026-10-25 目標價規格預設 A／B／C＝0.3／0.5／0.2） | I79: 三個權重合計應為 1
A80: tp_wB | B80: 目標價情境權重：情境 B（平平） | C80: 權重 | E80: 0.5 | G80: Assumed | H80: Andy 可改（2026-10-25 目標價規格預設 A／B／C＝0.3／0.5／0.2） | I80: 三個權重合計應為 1
A81: tp_wC | B81: 目標價情境權重：情境 C（不如預期） | C81: 權重 | E81: 0.2 | G81: Assumed | H81: Andy 可改（2026-10-25 目標價規格預設 A／B／C＝0.3／0.5／0.2） | I81: 三個權重合計應為 1
A82: tp_r | B82: 折現率／要求報酬（DCF） | C82: % | D82: 0.09 | E82: 0.1 | F82: 0.11 | G82: Assumed | H82: Andy 可改（工作單預設 10%） | I82: Sens 頁 ±1pt
A83: tp_g | B83: 長期成長率（DCF 永續；情境 B 的 FY2032 營收年增收斂目標） | C83: % | D83: 0.03 | E83: 0.04 | F83: 0.05 | G83: Assumed | H83: Andy 可改（工作單預設 4%） | I83: Sens 頁 ±1pt（同時移動 PL 收斂目標 fade_g）
A84: tp_roe | B84: ROE（近三年平均） | C84: % | E84: =AVERAGE(0.0655,0.1305,0.1195) -> 0.10516667 | G84: Derived | H84: stockanalysis 比率頁（Return on Equity，GAAP）：FY2024 6.55%、FY2025 13.05%、FY2026 11.95% | I84: 單一來源；GAAP 淨利口徑（non-GAAP ROE 較高，見 README）
A85: tp_w_dcf | B85: 目標價中 DCF 的權重；其餘為 Comparable | C85: % | D85: 0.3 | E85: 0.5 | F85: 0.7 | G85: Assumed | H85: Andy 可改（2026-10-25 11:53：DCF／Comparable 各半） | I85: Sens 頁 0.3／0.7
A86: fade_gA | B86: 情境 A（順利）：FY2032 營收年增收斂目標（tp_g＋2pt） | C86: % | E86: =tp_g+0.02 -> 0.06 | G86: Assumed | H86: 工作單 2026-10-25 11:20 收斂法 | I86: FY2030 起由 FY2029 年增線性收斂，FY2032 達到
A87: fade_gB | B87: 情境 B（平平）：FY2032 營收年增收斂目標（＝tp_g） | C87: % | E87: =tp_g -> 0.04 | G87: Assumed | H87: 同上 | I87: —
A88: fade_gC | B88: 情境 C（不如預期）：FY2032 營收年增收斂目標（tp_g−2pt） | C88: % | E88: =tp_g-0.02 -> 0.02 | G88: Assumed | H88: 同上 | I88: —
A89: nim10_f | B89: 十年平均淨利率的替代：最後一年（FY2029）淨利率 ×（本值） | C89: x | E89: 0.8 | G89: Assumed | H89: 十年平均淨利率：未找到（2023 年 9 月才上市）；依工作單以最後一年 × 0.8 替代 | I89: 淨利率收斂目標：A＝FY2029、B＝中點、C＝替代值
A90: cons_tp | B90: 市場共識目標價（賣方平均） | C90: US$ | E90: 290.71 | G90: Interested-party | H90: stockanalysis forecast 頁（S&P Global）43 位分析師平均 290.71（中位數 278.60），更新 2026-10-21 | I90: UBS 320、RBC 340（marketscreener，2026-07-30）
A91: cons_feps | B91: 共識前瞻 12 月 EPS（＝價格 ÷ 前瞻 P/E） | C91: US$ | E91: =225.95/93.52 -> 2.4160607 | G91: Interested-party | H91: stockanalysis 個股頁（2026-10-27）：價格 225.95 ÷ Forward PE 93.52 | I91: 賣方共識，只作對帳與差距拆解，不作校準
A93: 情境驅動對照（三情境並排，進主模型的加權目標價；本節只引用上方各列，修改請改上方藍字。上方「敏感度低／高」欄只用於 Sens 頁，不進目標價）
A94: 鍵 | B94: 項目 | C94: 單位 | D94: 情境 A（樂觀） | E94: 情境 B（基準） | F94: 情境 C（保守） | G94: 標記 | H94: 說明
A95: scn_phr | B95: 手機每支權利金率年增（FY2028–29；v9、CSS 滲透） | C95: % | D95: =E28 -> 0.14 | E95: =E29 -> 0.11 | F95: =E30 -> 0.07 | G95: Derived | H95: 引用 In 頁 phr_A／phr_B／phr_C；修改請改上方藍字
A96: scn_uc28 | B96: CY2028 顆數係數 | C96: x | D96: =E45 -> 1 | E96: =E46 -> 0.8 | F96: =E47 -> 0.6 | G96: Derived | H96: 引用 In 頁 uc28_A／uc28_B／uc28_C；修改請改上方藍字
A97: scn_uc29 | B97: CY2029 顆數係數 | C97: x | D97: =E48 -> 1 | E97: =E49 -> 0.85 | F97: =E50 -> 0.6 | G97: Derived | H97: 引用 In 頁 uc29_A／uc29_B／uc29_C；修改請改上方藍字
A98: scn_chip28 | B98: Arm AGI CPU 晶片營收 FY2028 | C98: US$B | D98: =E59 -> 1.4 | E98: =E60 -> 1 | F98: =E61 -> 0.5 | G98: Derived | H98: 引用 In 頁 chip28_A／chip28_B／chip28_C；修改請改上方藍字
A99: scn_chip29 | B99: Arm AGI CPU 晶片營收 FY2029 | C99: US$B | D99: =E62 -> 3 | E99: =E63 -> 2 | F99: =E64 -> 0.8 | G99: Derived | H99: 引用 In 頁 chip29_A／chip29_B／chip29_C；修改請改上方藍字
A100: scn_fade_g | B100: （不如預期）FY2032 營收年增收斂目標（tp_g−2pt） | C100: % | D100: =E86 -> 0.06 | E100: =E87 -> 0.04 | F100: =E88 -> 0.02 | G100: Derived | H100: 引用 In 頁 fade_gA／fade_gB／fade_gC；修改請改上方藍字
A101: scn_w | B101: 情境權重 | C101: 權重 | D101: =E79 -> 0.3 | E101: =E80 -> 0.5 | F101: =E81 -> 0.2 | G101: Derived | H101: 引用 In 頁 tp_wA／tp_wB／tp_wC；修改請改上方藍字

Sheet Q
A1: Q — 實績與 FY2027 錨點（十億美元；EPS 美元；股數十億股；non-GAAP）。藍字＝輸入；黑字＝公式。實績取自 Arm 股東信（6-K Exhibit 99.2，SEC）
A2: FY2027 錨點＝1Q27 實績（2026-07-29）＋2Q27 公司指引（授權 mid-30%、權利金 low-teens、營業費用 7.8 億）＋3Q27、4Q27 假設（以去年同期 × (1＋年增)）。2Q27 財報 2026-11-04（美東盤後）公布後更新：待 FQ2 財報
A3: 項目 | B3: FY2025A | C3: FY2026A | D3: 1Q27（實績） | E3: 2Q27（指引） | F3: 3Q27（模型） | G3: 4Q27（模型） | H3: FY2027 錨點 | I3: 標記 | J3: 來源1 | K3: 來源2／說明
A4: 授權及其他營收（License and other） | B4: 1.839 | C4: 2.307 | D4: 0.574 | E4: =C21*(1+q2_lg) -> 0.69525 | F4: =C22*(1+h2_lg) -> 0.606 | G4: =C23*(1+h2_lg) -> 0.9828 | H4: =SUM(D4:G4) -> 2.85805 | I4: Verified／指引／Assumed | J4: FY2025：https://www.sec.gov/Archives/edgar/data/1973239/000197323925000010/exhibit992fye25q431-marx25.htm；FY2026：https://www.sec.gov/Archives/edgar/data/0001973239/000197323926000062/exhibit992fye26q431-marx26.htm | K4: 1Q27：https://www.sec.gov/Archives/edgar/data/0001973239/000197323926000113/exhibit992fye27q130-junx26.htm
A5: 權利金營收（Royalty） | B5: 2.168 | C5: 2.613 | D5: 0.715 | E5: =D21*(1+q2_rg) -> 0.6944 | F5: =D22*(1+h2_rg) -> 0.84755 | G5: =D23*(1+h2_rg) -> 0.77165 | H5: =SUM(D5:G5) -> 3.0286 | I5: Verified／指引／Assumed | J5: 同上 | K5: 同上
A6: 營收 | B6: =B4+B5 -> 4.007 | C6: =C4+C5 -> 4.92 | D6: =D4+D5 -> 1.289 | E6: =E4+E5 -> 1.38965 | F6: =F4+F5 -> 1.45355 | G6: =G4+G5 -> 1.75445 | H6: =SUM(D6:G6) -> 5.88665 | I6: Derived | J6: FY2025 40.07、FY2026 49.20、1Q27 12.89 億美元（股東信） | K6: 2Q27 指引 13.8 億 ± 0.5 億
A7: 營業成本（non-GAAP） | B7: =B6-B8-B9 -> 0.087 | C7: =C6-C8-C9 -> 0.088 | D7: =D6-D8-D9 -> 0.025 | E7: =E6*cogs_r -> 0.02640335 | F7: =F6*cogs_r -> 0.02761745 | G7: =G6*cogs_r -> 0.03333455 | H7: =SUM(D7:G7) -> 0.11235535 | I7: Derived | J7: 營收 − non-GAAP 營業費用 − non-GAAP 營業利益 | K7: 1Q27 non-GAAP 毛利率 98.1%
A8: 營業費用（non-GAAP；研發＋銷管） | B8: =1.34+0.709 -> 2.049 | C8: =1.911+0.806 -> 2.717 | D8: =0.53+0.203 -> 0.733 | E8: =q2_opx -> 0.78 | F8: =q3_opx -> 0.8 | G8: =q4_opx -> 0.82 | H8: =SUM(D8:G8) -> 3.133 | I8: Verified／指引／Assumed | J8: 股東信 non-GAAP 調節表
A9: 營業利益（non-GAAP） | B9: 1.871 | C9: 2.115 | D9: 0.531 | E9: =E6-E7-E8 -> 0.58324665 | F9: =F6-F7-F8 -> 0.62593255 | G9: =G6-G7-G8 -> 0.90111545 | H9: =SUM(D9:G9) -> 2.6412946 | I9: Verified／Derived | J9: 股東信 | K9: 1Q27 營益率 41.2%
A10: 營業利益率（non-GAAP） | B10: =B9/B6 -> 0.46693287 | C10: =C9/C6 -> 0.42987805 | D10: =D9/D6 -> 0.41194725 | E10: =E9/E6 -> 0.41970759 | F10: =F9/F6 -> 0.43062334 | G10: =G9/G6 -> 0.51361706 | H10: =H9/H6 -> 0.44869232 | I10: Derived
A11: 業外收益（non-GAAP） | D11: =0.565-0.531 -> 0.034 | E11: =q_oth -> 0.034 | F11: =q_oth -> 0.034 | G11: =q_oth -> 0.034 | H11: =SUM(D11:G11) -> 0.136 | I11: Derived／Assumed | J11: 1Q27 稅前 5.65 − 營業利益 5.31（股東信） | K11: FY2025、FY2026 含在淨利內
A12: 稅前利益（non-GAAP） | D12: 0.565 | E12: =E9+E11 -> 0.61724665 | F12: =F9+F11 -> 0.65993255 | G12: =G9+G11 -> 0.93511545 | H12: =SUM(D12:G12) -> 2.7772946 | I12: Verified／Derived | J12: 股東信
A13: 稅後淨利（non-GAAP） | B13: 1.737 | C13: 1.889 | D13: 0.48 | E13: =E12*(1-q_tx) -> 0.52465965 | F13: =F12*(1-q_tx) -> 0.56094267 | G13: =G12*(1-q_tx) -> 0.79484813 | H13: =SUM(D13:G13) -> 2.3604505 | I13: Verified／Derived | J13: 股東信 | K13: 1Q27 稅 0.85 億（15%）
A14: 稀釋加權股數（十億股） | B14: 1.063 | C14: 1.068 | D14: 1.078 | E14: =q_sh -> 1.08 | F14: =q_sh -> 1.08 | G14: =q_sh -> 1.08 | H14: =q_sh -> 1.08 | I14: Verified／Derived | J14: 股東信
A15: EPS（non-GAAP） | B15: =B13/B14 -> 1.6340546 | C15: =C13/C14 -> 1.7687266 | D15: =D13/D14 -> 0.44526902 | E15: =E13/E14 -> 0.48579597 | F15: =F13/F14 -> 0.51939136 | G15: =G13/G14 -> 0.73597049 | H15: =H13/H14 -> 2.1856023 | I15: Derived | J15: 淨利 ÷ 股數
A16: 公司揭露 non-GAAP EPS（2Q27 為指引中點） | B16: 1.63 | C16: 1.77 | D16: 0.45 | E16: 0.47 | I16: Verified／Interested-party | J16: 股東信 | K16: 2Q27 指引 0.47 ± 0.04
A17: 公司揭露 GAAP EPS（對照；含股票薪酬） | B17: 0.75 | C17: 0.85 | D17: 0.25 | I17: Verified | J17: 股東信 | K17: 1Q27 股票薪酬 3.43 億美元（股東信）
A19: 去年同期季資料（FY2026，十億美元；3Q27、4Q27 年增的基期）
A20: 季 | C20: 授權及其他 | D20: 權利金 | E20: 營收
A21: 2Q26 | C21: =C4-C22-C23-C24 -> 0.515 | D21: =C5-D22-D23-D24 -> 0.62 | E21: =C21+D21 -> 1.135 | I21: Derived | J21: ＝FY2026 − 1Q26 − 3Q26 − 4Q26（股東信全年數）
A22: 3Q26 | C22: 0.505 | D22: 0.737 | E22: =C22+D22 -> 1.242 | I22: Derived | J22: 3Q26 法說：權利金 7.37、授權 5.05 億（The Motley Fool 逐字稿）
A23: 4Q26 | C23: 0.819 | D23: 0.671 | E23: =C23+D23 -> 1.49 | I23: Verified | J23: 4Q26 股東信
A24: 1Q26 | C24: 0.468 | D24: 0.585 | E24: =C24+D24 -> 1.053 | I24: Verified | J24: 1Q27 股東信（去年同期欄）
A26: 核對：四季合計 − FY2026（應為 0） | C26: =SUM(C21:C24)-C4 -> 0 | D26: =SUM(D21:D24)-C5 -> 0
A28: FY2027 錨點的檢查（參考；校準未使用共識）
A29: FY2027 營收年增 | B29: =H6/C6-1 -> 0.19647358
A30: FY2027 營收 ÷ 共識 − 1 | B30: =H6/c_rev27-1 -> -0.03497541
A31: FY2027 EPS ÷ 共識 − 1 | B31: =H15/c_eps27-1 -> -0.019909296
A32: 2Q27 營收（模型）÷ 公司指引中點 − 1 | B32: =E6/1.38-1 -> 0.0069927536
A33: 2Q27 EPS（模型）÷ 公司指引中點 − 1 | B33: =E15/0.47-1 -> 0.033608456
A34: FY2027 營業費用年增 | B34: =H8/C8-1 -> 0.15311005

Sheet Units
A1: Units — 權利金＝出貨 × 每顆權利金率（分市場，情境 B）與資料中心 CPU 顆數（NVIDIA Grace／Vera 讀 Siliconomics 加速器顆數）。會計年度 3 月底
A3: 項目 | B3: 單位 | C3: FY2026A | D3: FY2027（錨點） | E3: FY2028 | F3: FY2029 | G3: 說明
A4: NVIDIA 資料中心 GPU 顆數（會計年度加權） | B4: 百萬顆 | C4: =IF(ISBLANK(PL!D104),"",PL!D104) -> 6.275 | D4: =IF(ISBLANK(PL!E104),"",PL!E104) -> 7.75 | E4: =IF(ISBLANK(PL!F104),"",PL!F104) -> 9.175 | F4: =IF(ISBLANK(PL!G104),"",PL!G104) -> 7.9525 | G4: Siliconomics（情境 B）
A5: NVIDIA Grace／Vera CPU 顆數 | B5: 百萬顆 | C5: =IF(ISBLANK(PL!D105),"",PL!D105) -> 3.1375 | D5: =IF(ISBLANK(PL!E105),"",PL!E105) -> 3.875 | E5: =IF(ISBLANK(PL!F105),"",PL!F105) -> 4.5875 | F5: =IF(ISBLANK(PL!G105),"",PL!G105) -> 3.97625 | G5: × 每顆 GPU 搭 0.5 顆 CPU
A6: 資料中心 CPU 顆數指數（FY2027＝1） | B6: x | C6: =IF(ISBLANK(PL!D107),"",PL!D107) | D6: =IF(ISBLANK(PL!E107),"",PL!E107) -> 1 | E6: =IF(ISBLANK(PL!F107),"",PL!F107) -> 1.2171048 | F6: =IF(ISBLANK(PL!G107),"",PL!G107) -> 1.2516764 | G6: NVIDIA 與雲端自研加權
A7: 資料中心每顆權利金率指數 | B7: x | C7: =IF(ISBLANK(PL!D108),"",PL!D108) | D7: =IF(ISBLANK(PL!E108),"",PL!E108) -> 1 | E7: =IF(ISBLANK(PL!F108),"",PL!F108) -> 1.1 | F7: =IF(ISBLANK(PL!G108),"",PL!G108) -> 1.21 | G7: Assumed
A8: 資料中心權利金 | B8: US$B | C8: =PL!D113 -> 0.36582 | D8: =PL!E113 -> 0.621894 | E8: =PL!F113 -> 0.83260122 | F8: =PL!G113 -> 0.94187616
A9: 智慧型手機出貨 | B9: 十億支 | C9: =PL!D110 -> 1.22 | D9: =PL!E110 -> 1.22 | E9: =PL!F110 -> 1.1956 | F9: =PL!G110 -> 1.207556 | G9: 待併入 Siliconomics
A10: 手機每支權利金 | B10: US$ | C10: =PL!D111 -> 0.92097541 | D10: =PL!E111 -> 1.0314925 | E10: =PL!F111 -> 1.1449566 | F10: =PL!G111 -> 1.2709019 | G10: Derived（FY2026）；之後 × 費率年增
A11: 智慧型手機權利金 | B11: US$B | C11: =PL!D112 -> 1.12359 | D11: =PL!E112 -> 1.2584208 | E11: =PL!F112 -> 1.3689101 | F11: =PL!G112 -> 1.5346852
A12: 車用權利金 | B12: US$B | C12: =PL!D114 -> 0.23517 | D12: =PL!E114 -> 0.2704455 | E12: =PL!F114 -> 0.31101232 | F12: =PL!G114 -> 0.35766417
A13: 物聯網與其他權利金 | B13: US$B | C13: =PL!D115 -> 0.88842 | D13: =PL!E115 -> 0.8778397 | E13: =PL!F115 -> 0.91295329 | F13: =PL!G115 -> 0.94947142
A14: 權利金合計 | B14: US$B | C14: =PL!D116 -> 2.613 | D14: =PL!E116 -> 3.0286 | E14: =PL!F116 -> 3.425477 | F14: =PL!G116 -> 3.7836969
A15: 資料中心 ÷ 權利金 | B15: % | C15: =PL!D126 -> 0.14 | D15: =PL!E126 -> 0.20534042 | E15: =PL!F126 -> 0.2430614 | F15: =PL!G126 -> 0.24893013
A16: Arm AGI CPU 晶片營收 | B16: US$B | C16: =PL!D119 -> 0 | D16: =PL!E119 -> 0.15 | E16: =PL!F119 -> 1 | F16: =PL!G119 -> 2 | G16: 列於授權及其他
A18: 讀法：權利金成長拆成「出貨」與「每顆權利金率」。手機出貨持平到下滑，成長幾乎全靠 v9 與 CSS 費率；資料中心同時有顆數（NVIDIA Grace／Vera 讀 Siliconomics、雲端自研 CPU 年增 Assumed）與每顆費率（核心數）兩個槓桿。

Sheet PL
A1: PL — Arm 損益（十億美元；EPS 美元；non-GAAP）。FY2025A、FY2026A 實績，FY2027 錨點（1Q27 實績＋2Q27 指引＋下半年假設），FY2028 起為模型。FY(t)＝t 年 3 月底結束。三情境各一個完整推導區塊（本頁下方），頂端為摘要；最下方延伸到 FY2032（FY2030 起為收斂法）
A3: 情境／項目 | B3: 單位 | C3: FY2025A | D3: FY2026A | E3: FY2027（錨點） | F3: FY2028 | G3: FY2029 | H3: 說明
A4: 情境 A
A5: 營收 | B5: US$B | C5: =C81 -> 4.007 | D5: =D81 -> 4.92 | E5: =E81 -> 5.88665 | F5: =F81 -> 7.8849068 | G5: =G81 -> 10.361439
A6: 營收年增 | B6: % | D6: =D82 -> 0.22785126 | E6: =E82 -> 0.19647358 | F6: =F82 -> 0.33945568 | G6: =G82 -> 0.31408518
A7: 權利金 | B7: US$B | C7: =C75 -> 2.168 | D7: =D75 -> 2.613 | E7: =E75 -> 3.0286 | F7: =F75 -> 3.5060518 | G7: =G75 -> 4.0846986
A8: 其中資料中心 | B8: US$B | C8: =C72 -> 0.30352 | D8: =D72 -> 0.36582 | E8: =E72 -> 0.621894 | F8: =F72 -> 0.87617843 | G8: =G72 -> 1.1588009
A9: 授權及其他 | B9: US$B | C9: =C80 -> 1.839 | D9: =D80 -> 2.307 | E9: =E80 -> 2.85805 | F9: =F80 -> 4.378855 | G9: =G80 -> 6.2767405
A10: 其中 AGI CPU 晶片 | B10: US$B | C10: =C78 -> 0 | D10: =D78 -> 0 | E10: =E78 -> 0.15 | F10: =F78 -> 1.4 | G10: =G78 -> 3
A11: 毛利率 | B11: % | C11: =C90 -> 0.978288 | D11: =D90 -> 0.98211382 | E11: =E90 -> 0.96738292 | F11: =F90 -> 0.88671861 | G11: =G90 -> 0.82725688
A12: 營業利益率 | B12: % | C12: =C93 -> 0.46693287 | D12: =D93 -> 0.42987805 | E12: =E93 -> 0.4351617 | F12: =F93 -> 0.43772281 | G12: =G93 -> 0.44115919
A13: 稅後淨利（non-GAAP） | B13: US$B | C13: =C94 -> 1.737 | D13: =D94 -> 1.889 | E13: =E94 -> 2.292748 | F13: =F94 -> 3.052693 | G13: =G94 -> 4.0043875
A14: EPS（non-GAAP） | B14: US$ | C14: =C97 -> 1.6340546 | D14: =D97 -> 1.7687266 | E14: =E97 -> 2.1229148 | F14: =F97 -> 2.8041345 | G14: =G97 -> 3.6491463
A15: EPS 年增 | B15: % | D15: =D98 -> 0.08241587 | E15: =E98 -> 0.20025038 | F15: =F98 -> 0.32088888 | G15: =G98 -> 0.30134494
A17: 情境 B
A18: 營收 | B18: US$B | C18: =C122 -> 4.007 | D18: =D122 -> 4.92 | E18: =E122 -> 5.88665 | F18: =F122 -> 7.404332 | G18: =G122 -> 9.0604374
A19: 營收年增 | B19: % | D19: =D123 -> 0.22785126 | E19: =E123 -> 0.19647358 | F19: =F123 -> 0.2578176 | G19: =G123 -> 0.2236671
A20: 權利金 | B20: US$B | C20: =C116 -> 2.168 | D20: =D116 -> 2.613 | E20: =E116 -> 3.0286 | F20: =F116 -> 3.425477 | G20: =G116 -> 3.7836969
A21: 其中資料中心 | B21: US$B | C21: =C113 -> 0.30352 | D21: =D113 -> 0.36582 | E21: =E113 -> 0.621894 | F21: =F113 -> 0.83260122 | G21: =G113 -> 0.94187616
A22: 授權及其他 | B22: US$B | C22: =C121 -> 1.839 | D22: =D121 -> 2.307 | E22: =E121 -> 2.85805 | F22: =F121 -> 3.978855 | G22: =G121 -> 5.2767405
A23: 其中 AGI CPU 晶片 | B23: US$B | C23: =C119 -> 0 | D23: =D119 -> 0 | E23: =E119 -> 0.15 | F23: =F119 -> 1 | G23: =G119 -> 2
A24: 毛利率 | B24: % | C24: =C131 -> 0.978288 | D24: =D131 -> 0.98211382 | E24: =E131 -> 0.96738292 | F24: =F131 -> 0.90928523 | G24: =G131 -> 0.86378712
A25: 營業利益率 | B25: % | C25: =C134 -> 0.46693287 | D25: =D134 -> 0.42987805 | E25: =E134 -> 0.4351617 | F25: =F134 -> 0.43114756 | G25: =G134 -> 0.42224908
A26: 稅後淨利（non-GAAP） | B26: US$B | C26: =C135 -> 1.737 | D26: =D135 -> 1.889 | E26: =E135 -> 2.292748 | F26: =F135 -> 2.8325057 | G26: =G135 -> 3.3708972
A27: EPS（non-GAAP） | B27: US$ | C27: =C138 -> 1.6340546 | D27: =D138 -> 1.7687266 | E27: =E138 -> 2.1229148 | F27: =F138 -> 2.6018755 | G27: =G138 -> 3.0718548
A28: EPS 年增 | B28: % | D28: =D139 -> 0.08241587 | E28: =E139 -> 0.20025038 | F28: =F139 -> 0.22561466 | G28: =G139 -> 0.180631
A30: 情境 C
A31: 營收 | B31: US$B | C31: =C163 -> 4.007 | D31: =D163 -> 4.92 | E31: =E163 -> 5.88665 | F31: =F163 -> 6.8114247 | G31: =G163 -> 7.5052268
A32: 營收年增 | B32: % | D32: =D164 -> 0.22785126 | E32: =E164 -> 0.19647358 | F32: =F164 -> 0.15709693 | G32: =G164 -> 0.10185859
A33: 權利金 | B33: US$B | C33: =C157 -> 2.168 | D33: =D157 -> 2.613 | E33: =E157 -> 3.0286 | F33: =F157 -> 3.3325697 | G33: =G157 -> 3.4284863
A34: 其中資料中心 | B34: US$B | C34: =C154 -> 0.30352 | D34: =D154 -> 0.36582 | E34: =E154 -> 0.621894 | F34: =F154 -> 0.789024 | G34: =G154 -> 0.69528052
A35: 授權及其他 | B35: US$B | C35: =C162 -> 1.839 | D35: =D162 -> 2.307 | E35: =E162 -> 2.85805 | F35: =F162 -> 3.478855 | G35: =G162 -> 4.0767405
A36: 其中 AGI CPU 晶片 | B36: US$B | C36: =C160 -> 0 | D36: =D160 -> 0 | E36: =E160 -> 0.15 | F36: =F160 -> 0.5 | G36: =G160 -> 0.8
A37: 毛利率 | B37: % | C37: =C172 -> 0.978288 | D37: =D172 -> 0.98211382 | E37: =E172 -> 0.96738292 | F37: =F172 -> 0.94202137 | G37: =G172 -> 0.92439945
A38: 營業利益率 | B38: % | C38: =C175 -> 0.46693287 | D38: =D175 -> 0.42987805 | E38: =E175 -> 0.4351617 | F38: =F175 -> 0.42226373 | G38: =G175 -> 0.39136722
A39: 稅後淨利（non-GAAP） | B39: US$B | C39: =C176 -> 1.737 | D39: =D176 -> 1.889 | E39: =E176 -> 2.292748 | F39: =F176 -> 2.563785 | G39: =G176 -> 2.6157048
A40: EPS（non-GAAP） | B40: US$ | C40: =C179 -> 1.6340546 | D40: =D179 -> 1.7687266 | E40: =E179 -> 2.1229148 | F40: =F179 -> 2.3550347 | G40: =G179 -> 2.3836578
A41: EPS 年增 | B41: % | D41: =D180 -> 0.08241587 | E41: =E180 -> 0.20025038 | F41: =F180 -> 0.10934019 | G41: =G180 -> 0.012154016
A43: 核對（應為 0）：營收、權利金、授權及其他 − 財報（FY2026）與錨點（FY2027）
A44: 情境 A：FY2026 營收差 | D44: =D81-a26_rev -> 0
A45: 情境 A：FY2027 營收差（錨點） | D45: =E81-a27_rev -> 0
A46: 情境 A：FY2027 權利金差（錨點） | D46: =E75-a27_ro -> 0
A47: 情境 A：FY2027 授權及其他差（錨點） | D47: =E80-a27_lo -> 0
A60: 情境 A：順利（Siliconomics 情境 A 顆數；晶片與手機費率最有利）
A61: 項目 | B61: 單位 | C61: FY2025A | D61: FY2026A | E61: FY2027（錨點） | F61: FY2028 | G61: FY2029 | H61: 說明
A62: A. 資料中心 CPU 顆數指數（NVIDIA Grace／Vera 讀 Siliconomics；雲端自研 CPU Assumed × 同字母係數）
A63: NVIDIA 資料中心 GPU 顆數（會計年度＝9/12 × CY(t−1)＋3/12 × CY(t)） | B63: 百萬顆 | D63: =0.75*nv_cy25+0.25*(nvbw_26+nvrb_26+nvru_26) -> 6.275 | E63: =0.75*(nvbw_26+nvrb_26+nvru_26)+0.25*(nvbw_27+nvrb_27+nvru_27) -> 7.75 | F63: =0.75*(nvbw_27+nvrb_27+nvru_27)+0.25*(nvbw_28+nvrb_28+nvru_28)*uc28_A -> 9.65 | G63: =0.75*(nvbw_28+nvrb_28+nvru_28)*uc28_A+0.25*(nvbw_29+nvrb_29+nvru_29)*uc29_A -> 9.775 | H63: Siliconomics SIF_UnitsPlat_bw＋rb＋ru × SIF_UnitsCoef_A；CY2025 為 In 頁 nv_cy25（待併入 Siliconomics）
A64: NVIDIA Grace／Vera CPU 顆數 ＝ GPU × 每顆 GPU 搭配 CPU | B64: 百萬顆 | D64: =D63*cpu_gpu -> 3.1375 | E64: =E63*cpu_gpu -> 3.875 | F64: =F63*cpu_gpu -> 4.825 | G64: =G63*cpu_gpu -> 4.8875
A65: 雲端自研 Arm CPU 顆數指數（FY2027＝1） | B65: x | E65: =1 -> 1 | F65: =E65*(1+g_hc)*(0.75*1+0.25*uc28_A) -> 1.3 | G65: =F65*(1+g_hc)*(0.75*uc28_A+0.25*uc29_A)/(0.75*1+0.25*uc28_A) -> 1.69 | H65: 年增 g_hc × 同字母顆數係數（行業情境）；Siliconomics 無 CPU 顆數：待併入 Siliconomics
A66: 資料中心 CPU 顆數指數（FY2027＝1）＝ w_nv × NVIDIA 指數＋（1 − w_nv）× 雲端自研指數 | B66: x | E66: =1 -> 1 | F66: =w_nv*F64/$E$64+(1-w_nv)*F65 -> 1.2808065 | G66: =w_nv*G64/$E$64+(1-w_nv)*G65 -> 1.5399516
A67: 資料中心每顆權利金率指數（FY2027＝1） | B67: x | E67: =1 -> 1 | F67: =E67*(1+dcr) -> 1.1 | G67: =F67*(1+dcr) -> 1.21
A68: B. 權利金（分市場）＝ 出貨 × 每顆權利金率
A69: 智慧型手機出貨 | B69: 十億支 | D69: =ph_u26 -> 1.22 | E69: =D69 -> 1.22 | F69: =E69*(1+g_phu28) -> 1.1956 | G69: =F69*(1+g_phu29) -> 1.207556 | H69: FY2027 出貨假設持平（權利金成長來自費率）；Siliconomics 無手機出貨：待併入 Siliconomics
A70: 手機每支權利金（美元）＝ 手機權利金 ÷ 出貨 | B70: US$ | D70: =ph_s*a26_ro/D69 -> 0.92097541 | E70: =D70*(1+g_ph27) -> 1.0314925 | F70: =E70*(1+phr_A) -> 1.1759014 | G70: =F70*(1+phr_A) -> 1.3405276 | H70: FY2026 Derived；FY2028–29 年增＝情境 A 的 phr_A（v9、CSS 滲透；C 含 Qualcomm 判決影響）
A71: 權利金：智慧型手機（行動應用處理器） | B71: US$B | C71: =ph_s*a25_ro -> 0.93224 | D71: =ph_s*a26_ro -> 1.12359 | E71: =E69*E70 -> 1.2584208 | F71: =F69*F70*(1+qc_adj) -> 1.4059077 | G71: =G69*G70*(1+qc_adj) -> 1.6187621 | H71: FY2025 拆分沿用 FY2026 比例（Assumed）；FY2028 起 × (1＋qc_adj)
A72: 權利金：資料中心（Neoverse；Grace、Vera、Graviton、Axion、Cobalt 等） | B72: US$B | C72: =dc_s*a25_ro -> 0.30352 | D72: =dc_s*a26_ro -> 0.36582 | E72: =D72*(1+g_dc27) -> 0.621894 | F72: =$E72*F66*F67 -> 0.87617843 | G72: =$E72*G66*G67 -> 1.1588009 | H72: FY2028 起＝FY2027 × CPU 顆數指數 × 每顆權利金率指數
A73: 權利金：車用 | B73: US$B | C73: =au_s*a25_ro -> 0.19512 | D73: =au_s*a26_ro -> 0.23517 | E73: =D73*(1+g_au27) -> 0.2704455 | F73: =E73*(1+g_au) -> 0.31101232 | G73: =F73*(1+g_au) -> 0.35766417
A74: 權利金：物聯網與其他（含 PC、消費電子、嵌入式；FY2027 前為殘差） | B74: US$B | C74: =a25_ro-C71-C72-C73 -> 0.73712 | D74: =a26_ro-D71-D72-D73 -> 0.88842 | E74: =a27_ro-E71-E72-E73 -> 0.8778397 | F74: =E74*(1+g_iot) -> 0.91295329 | G74: =F74*(1+g_iot) -> 0.94947142 | H74: FY2025–FY2027 為權利金 − 三個市場（殘差）；FY2028 起依成長率
A75: 權利金營收（Royalty） | B75: US$B | C75: =C71+C72+C73+C74 -> 2.168 | D75: =D71+D72+D73+D74 -> 2.613 | E75: =E71+E72+E73+E74 -> 3.0286 | F75: =F71+F72+F73+F74 -> 3.5060518 | G75: =G71+G72+G73+G74 -> 4.0846986 | H75: 官方營收類型；FY2025–FY2027 等於財報／錨點
A76: 權利金年增 | B76: % | D76: =D75/C75-1 -> 0.2052583 | E76: =E75/D75-1 -> 0.1590509 | F76: =F75/E75-1 -> 0.15764768 | G76: =G75/F75-1 -> 0.1650423
A77: C. 授權及其他（含 SoftBank 協議）與 Arm AGI CPU 晶片
A78: 授權及其他：Arm AGI CPU 晶片營收（公司未揭露所在列，暫列於此） | B78: US$B | C78: =0 -> 0 | D78: =0 -> 0 | E78: =chip_27 -> 0.15 | F78: =chip28_A -> 1.4 | G78: =chip29_A -> 3 | H78: 情境 A：chip28_A、chip29_A（Assumed；A 最高、C 最低）
A79: 授權及其他：授權（不含晶片；含 SoftBank 協議） | B79: US$B | C79: =a25_lo -> 1.839 | D79: =a26_lo -> 2.307 | E79: =a27_lo-E78 -> 2.70805 | F79: =E79*(1+g_lic) -> 2.978855 | G79: =F79*(1+g_lic) -> 3.2767405
A80: 授權及其他營收（License and other） | B80: US$B | C80: =C79+C78 -> 1.839 | D80: =D79+D78 -> 2.307 | E80: =E79+E78 -> 2.85805 | F80: =F79+F78 -> 4.378855 | G80: =G79+G78 -> 6.2767405 | H80: 官方營收類型；FY2025–FY2027 等於財報／錨點
A81: 營收 | B81: US$B | C81: =C80+C75 -> 4.007 | D81: =D80+D75 -> 4.92 | E81: =E80+E75 -> 5.88665 | F81: =F80+F75 -> 7.8849068 | G81: =G80+G75 -> 10.361439
A82: 營收年增 | B82: % | D82: =D81/C81-1 -> 0.22785126 | E82: =E81/D81-1 -> 0.19647358 | F82: =F81/E81-1 -> 0.33945568 | G82: =G81/F81-1 -> 0.31408518
A83: 檢查：分部合計 − 合併營收 | B83: US$B | C83: =C80+C75-C81+(C71+C72+C73+C74-C75)+(C79+C78-C80) -> 0 | D83: =D80+D75-D81+(D71+D72+D73+D74-D75)+(D79+D78-D80) -> 0 | E83: =E80+E75-E81+(E71+E72+E73+E74-E75)+(E79+E78-E80) -> 0 | F83: =F80+F75-F81+(F71+F72+F73+F74-F75)+(F79+F78-F80) -> 0 | G83: =G80+G75-G81+(G71+G72+G73+G74-G75)+(G79+G78-G80) -> 0 | H83: 授權及其他＋權利金 − 營收，加上兩類營收的子列合計 − 母列；FY2025–FY2027 營收＝財報／錨點（Q 頁）
A84: 核對：營收 − 財報（FY2025、FY2026）／錨點（FY2027） | B84: US$B | C84: =C81-a25_rev -> 0 | D84: =D81-a26_rev -> 0 | E84: =E81-a27_rev -> 0
A85: 資料中心 ÷ 權利金 | B85: % | C85: =C72/C75 -> 0.14 | D85: =D72/D75 -> 0.14 | E85: =E72/E75 -> 0.20534042 | F85: =F72/F75 -> 0.24990459 | G85: =G72/G75 -> 0.28369311
A86: 智慧型手機 ÷ 權利金 | B86: % | C86: =C71/C75 -> 0.43 | D86: =D71/D75 -> 0.43 | E86: =E71/E75 -> 0.41551238 | F86: =F71/F75 -> 0.40099457 | G86: =G71/G75 -> 0.39629904
A87: D. 損益（non-GAAP）
A88: 營業成本（IP × cogs_r＋晶片 ×（1 − 晶片毛利率）） | B88: US$B | C88: =a25_cogs -> 0.087 | D88: =a26_cogs -> 0.088 | E88: =a27_cogs+E78*(1-chip_gm-cogs_r) -> 0.19200535 | F88: =(F81-F78)*cogs_r+F78*(1-chip_gm) -> 0.89321323 | G88: =(G81-G78)*cogs_r+G78*(1-chip_gm) -> 1.7898673 | H88: FY2027 錨點的成本以 cogs_r 計，晶片部分另加（毛利率 chip_gm）
A89: 毛利 | B89: US$B | C89: =C81-C88 -> 3.92 | D89: =D81-D88 -> 4.832 | E89: =E81-E88 -> 5.6946446 | F89: =F81-F88 -> 6.9916935 | G89: =G81-G88 -> 8.5715718
A90: 毛利率 | B90: % | C90: =C89/C81 -> 0.978288 | D90: =D89/D81 -> 0.98211382 | E90: =E89/E81 -> 0.96738292 | F90: =F89/F81 -> 0.88671861 | G90: =G89/G81 -> 0.82725688
A91: 營業費用（non-GAAP） | B91: US$B | C91: =a25_opx -> 2.049 | D91: =a26_opx -> 2.717 | E91: =a27_opx -> 3.133 | F91: =E91*(1+g_opx) -> 3.54029 | G91: =F91*(1+g_opx) -> 4.0005277
A92: 營業利益（non-GAAP） | B92: US$B | C92: =C89-C91 -> 1.871 | D92: =D89-D91 -> 2.115 | E92: =E89-E91 -> 2.5616446 | F92: =F89-F91 -> 3.4514035 | G92: =G89-G91 -> 4.5710441
A93: 營業利益率 | B93: % | C93: =C92/C81 -> 0.46693287 | D93: =D92/D81 -> 0.42987805 | E93: =E92/E81 -> 0.4351617 | F93: =F92/F81 -> 0.43772281 | G93: =G92/G81 -> 0.44115919
A94: 稅後淨利（non-GAAP） | B94: US$B | C94: =a25_ni -> 1.737 | D94: =a26_ni -> 1.889 | E94: =a27_ni-E78*(1-chip_gm-cogs_r)*(1-q_tx) -> 2.292748 | F94: =(F92+oth_f)*(1-tx_f) -> 3.052693 | G94: =(G92+oth_f)*(1-tx_f) -> 4.0043875 | H94: FY2027＝錨點淨利扣除晶片成本差（晶片含在錨點營收內）
A95: 淨利率 | B95: % | C95: =C94/C81 -> 0.43349139 | D95: =D94/D81 -> 0.38394309 | E95: =E94/E81 -> 0.38948263 | F95: =F94/F81 -> 0.38715651 | G95: =G94/G81 -> 0.3864702
A96: 稀釋股數 | B96: 十億股 | C96: =a25_sh -> 1.063 | D96: =a26_sh -> 1.068 | E96: =a27_sh -> 1.08 | F96: =E96*(1+sh_g) -> 1.08864 | G96: =F96*(1+sh_g) -> 1.0973491
A97: EPS（non-GAAP） | B97: US$ | C97: =C94/C96 -> 1.6340546 | D97: =D94/D96 -> 1.7687266 | E97: =E94/E96 -> 2.1229148 | F97: =F94/F96 -> 2.8041345 | G97: =G94/G96 -> 3.6491463
A98: EPS 年增 | B98: % | D98: =D97/C97-1 -> 0.08241587 | E98: =E97/D97-1 -> 0.20025038 | F98: =F97/E97-1 -> 0.32088888 | G98: =G97/F97-1 -> 0.30134494
A101: 情境 B：平平（Siliconomics 情境 B：CY2028 顆數 ×0.8、CY2029 ×0.85）
A102: 項目 | B102: 單位 | C102: FY2025A | D102: FY2026A | E102: FY2027（錨點） | F102: FY2028 | G102: FY2029 | H102: 說明
A103: A. 資料中心 CPU 顆數指數（NVIDIA Grace／Vera 讀 Siliconomics；雲端自研 CPU Assumed × 同字母係數）
A104: NVIDIA 資料中心 GPU 顆數（會計年度＝9/12 × CY(t−1)＋3/12 × CY(t)） | B104: 百萬顆 | D104: =0.75*nv_cy25+0.25*(nvbw_26+nvrb_26+nvru_26) -> 6.275 | E104: =0.75*(nvbw_26+nvrb_26+nvru_26)+0.25*(nvbw_27+nvrb_27+nvru_27) -> 7.75 | F104: =0.75*(nvbw_27+nvrb_27+nvru_27)+0.25*(nvbw_28+nvrb_28+nvru_28)*uc28_B -> 9.175 | G104: =0.75*(nvbw_28+nvrb_28+nvru_28)*uc28_B+0.25*(nvbw_29+nvrb_29+nvru_29)*uc29_B -> 7.9525 | H104: Siliconomics SIF_UnitsPlat_bw＋rb＋ru × SIF_UnitsCoef_B；CY2025 為 In 頁 nv_cy25（待併入 Siliconomics）
A105: NVIDIA Grace／Vera CPU 顆數 ＝ GPU × 每顆 GPU 搭配 CPU | B105: 百萬顆 | D105: =D104*cpu_gpu -> 3.1375 | E105: =E104*cpu_gpu -> 3.875 | F105: =F104*cpu_gpu -> 4.5875 | G105: =G104*cpu_gpu -> 3.97625
A106: 雲端自研 Arm CPU 顆數指數（FY2027＝1） | B106: x | E106: =1 -> 1 | F106: =E106*(1+g_hc)*(0.75*1+0.25*uc28_B) -> 1.235 | G106: =F106*(1+g_hc)*(0.75*uc28_B+0.25*uc29_B)/(0.75*1+0.25*uc28_B) -> 1.373125 | H106: 年增 g_hc × 同字母顆數係數（行業情境）；Siliconomics 無 CPU 顆數：待併入 Siliconomics
A107: 資料中心 CPU 顆數指數（FY2027＝1）＝ w_nv × NVIDIA 指數＋（1 − w_nv）× 雲端自研指數 | B107: x | E107: =1 -> 1 | F107: =w_nv*F105/$E$105+(1-w_nv)*F106 -> 1.2171048 | G107: =w_nv*G105/$E$105+(1-w_nv)*G106 -> 1.2516764
A108: 資料中心每顆權利金率指數（FY2027＝1） | B108: x | E108: =1 -> 1 | F108: =E108*(1+dcr) -> 1.1 | G108: =F108*(1+dcr) -> 1.21
A109: B. 權利金（分市場）＝ 出貨 × 每顆權利金率
A110: 智慧型手機出貨 | B110: 十億支 | D110: =ph_u26 -> 1.22 | E110: =D110 -> 1.22 | F110: =E110*(1+g_phu28) -> 1.1956 | G110: =F110*(1+g_phu29) -> 1.207556 | H110: FY2027 出貨假設持平（權利金成長來自費率）；Siliconomics 無手機出貨：待併入 Siliconomics
A111: 手機每支權利金（美元）＝ 手機權利金 ÷ 出貨 | B111: US$ | D111: =ph_s*a26_ro/D110 -> 0.92097541 | E111: =D111*(1+g_ph27) -> 1.0314925 | F111: =E111*(1+phr_B) -> 1.1449566 | G111: =F111*(1+phr_B) -> 1.2709019 | H111: FY2026 Derived；FY2028–29 年增＝情境 B 的 phr_B（v9、CSS 滲透；C 含 Qualcomm 判決影響）
A112: 權利金：智慧型手機（行動應用處理器） | B112: US$B | C112: =ph_s*a25_ro -> 0.93224 | D112: =ph_s*a26_ro -> 1.12359 | E112: =E110*E111 -> 1.2584208 | F112: =F110*F111*(1+qc_adj) -> 1.3689101 | G112: =G110*G111*(1+qc_adj) -> 1.5346852 | H112: FY2025 拆分沿用 FY2026 比例（Assumed）；FY2028 起 × (1＋qc_adj)
A113: 權利金：資料中心（Neoverse；Grace、Vera、Graviton、Axion、Cobalt 等） | B113: US$B | C113: =dc_s*a25_ro -> 0.30352 | D113: =dc_s*a26_ro -> 0.36582 | E113: =D113*(1+g_dc27) -> 0.621894 | F113: =$E113*F107*F108 -> 0.83260122 | G113: =$E113*G107*G108 -> 0.94187616 | H113: FY2028 起＝FY2027 × CPU 顆數指數 × 每顆權利金率指數
A114: 權利金：車用 | B114: US$B | C114: =au_s*a25_ro -> 0.19512 | D114: =au_s*a26_ro -> 0.23517 | E114: =D114*(1+g_au27) -> 0.2704455 | F114: =E114*(1+g_au) -> 0.31101232 | G114: =F114*(1+g_au) -> 0.35766417
A115: 權利金：物聯網與其他（含 PC、消費電子、嵌入式；FY2027 前為殘差） | B115: US$B | C115: =a25_ro-C112-C113-C114 -> 0.73712 | D115: =a26_ro-D112-D113-D114 -> 0.88842 | E115: =a27_ro-E112-E113-E114 -> 0.8778397 | F115: =E115*(1+g_iot) -> 0.91295329 | G115: =F115*(1+g_iot) -> 0.94947142 | H115: FY2025–FY2027 為權利金 − 三個市場（殘差）；FY2028 起依成長率
A116: 權利金營收（Royalty） | B116: US$B | C116: =C112+C113+C114+C115 -> 2.168 | D116: =D112+D113+D114+D115 -> 2.613 | E116: =E112+E113+E114+E115 -> 3.0286 | F116: =F112+F113+F114+F115 -> 3.425477 | G116: =G112+G113+G114+G115 -> 3.7836969 | H116: 官方營收類型；FY2025–FY2027 等於財報／錨點
A117: 權利金年增 | B117: % | D117: =D116/C116-1 -> 0.2052583 | E117: =E116/D116-1 -> 0.1590509 | F117: =F116/E116-1 -> 0.13104305 | G117: =G116/F116-1 -> 0.1045752
A118: C. 授權及其他（含 SoftBank 協議）與 Arm AGI CPU 晶片
...

Sheet Val
A1: Val — 目標價（第 0 節：DCF 與 Comparable 加權）、現價隱含倍數與歷史 P/E 分位檢查（美元；non-GAAP EPS）。本版未做先驗，無 Andy 合理 P/E 對照
A2: 三情境欄 B／C／D＝A 順利／B 平平／C 不如預期（讀 Siliconomics 同字母情境）。現價＝In 頁 px（2026-10-30 收盤）。SoftBank 持股約九成、流通股約一成：Comparable 不另作流通量調整（見方法列）
A4: 0. 目標價（DCF 與 Comparable 加權）
A5: 0.1 DCF（股東權益現金流，FY2027–FY2032 明確期＋FY2032 後永續）
A6: 項目 | B6: A（順利） | C6: B（平平） | D6: C（不如預期） | E6: 說明
A7: 情境 EPS（FY2027–FY2032） | E7: PL 頁延伸表（non-GAAP）；FY2030 起為收斂法
A8: FY2027 | B8: =PL!E191 -> 2.1229148 | C8: =PL!E203 -> 2.1229148 | D8: =PL!E215 -> 2.1229148
A9: FY2028 | B9: =PL!F191 -> 2.8041345 | C9: =PL!F203 -> 2.6018755 | D9: =PL!F215 -> 2.3550347
A10: FY2029 | B10: =PL!G191 -> 3.6491463 | C10: =PL!G203 -> 3.0718548 | D10: =PL!G215 -> 2.3836578
A11: FY2030 | B11: =PL!H191 -> 4.4506194 | C11: =PL!H203 -> 3.4244373 | D11: =PL!H215 -> 2.3716786
A12: FY2031 | B12: =PL!I191 -> 5.0541687 | C12: =PL!I203 -> 3.612133 | D12: =PL!I215 -> 2.2881052
A13: FY2032 | B13: =PL!J191 -> 5.3148996 | C13: =PL!J203 -> 3.5937038 | D13: =PL!J215 -> 2.1372412
A14: 股東現金流＝EPS ×（1 − tp_g ÷ tp_roe）
A15: 再投資率（tp_g ÷ tp_roe，上限 0.8） | B15: =MIN(tp_g/tp_roe,0.8) -> 0.38034865 | E15: ROE 為近三年平均（In 頁 tp_roe，GAAP）
A16: FY2027 | B16: =B8*(1-$B$15) -> 1.315467 | C16: =C8*(1-$B$15) -> 1.315467 | D16: =D8*(1-$B$15) -> 1.315467
A17: FY2028 | B17: =B9*(1-$B$15) -> 1.7375857 | C17: =C9*(1-$B$15) -> 1.6122556 | D17: =D9*(1-$B$15) -> 1.4593004
A18: FY2029 | B18: =B10*(1-$B$15) -> 2.2611984 | C18: =C10*(1-$B$15) -> 1.903479 | D18: =D10*(1-$B$15) -> 1.4770368
A19: FY2030 | B19: =B11*(1-$B$15) -> 2.7578323 | C19: =C11*(1-$B$15) -> 2.1219572 | D19: =D11*(1-$B$15) -> 1.4696138
A20: FY2031 | B20: =B12*(1-$B$15) -> 3.1318224 | C20: =C12*(1-$B$15) -> 2.2382631 | D20: =D12*(1-$B$15) -> 1.4178275
A21: FY2032 | B21: =B13*(1-$B$15) -> 3.2933847 | C21: =C13*(1-$B$15) -> 2.2268434 | D21: =D13*(1-$B$15) -> 1.3243444
A22: DCF 情境每股價值（折現率 tp_r） | B22: =MAX(0,SUMPRODUCT(B16:B21,1/(1+tp_r)^{1;2;3;4;5;6})+B21*(1+tp_g)/(tp_r-tp_g)/(1+tp_r)^6) -> 42.241237 | C22: =MAX(0,SUMPRODUCT(C16:C21,1/(1+tp_r)^{1;2;3;4;5;6})+C21*(1+tp_g)/(tp_r-tp_g)/(1+tp_r)^6) -> 29.842453 | D22: =MAX(0,SUMPRODUCT(D16:D21,1/(1+tp_r)^{1;2;3;4;5;6})+D21*(1+tp_g)/(tp_r-tp_g)/(1+tp_r)^6) -> 19.100985 | E22: Σ 明確期現金流 ÷ (1＋r)^t ＋ 永續價值 ÷ (1＋r)^6；基準日 2026 年底，t＝1 對 FY2027（3 月底結束；近似）；低於 0 時取 0
A23: DCF 情境價值推到 12 個月後（×(1＋tp_r)） | B23: =B22*(1+tp_r) -> 46.465361 | C23: =C22*(1+tp_r) -> 32.826699 | D23: =D22*(1+tp_r) -> 21.011084
A24: DCF 目標價（情境加權） | B24: =tp_wA*B23+tp_wB*C23+tp_wC*D23 -> 34.555174 | E24: Σ tp_wA／wB／wC × 情境價值 ×(1＋tp_r)；權重見 In 頁
A26: 0.2 Comparable（市場主流同業前瞻 P/E）
A27: 同業與前瞻 P/E | B27: 代號 | C27: 前瞻 12 月 P/E | D27: 日期 | E27: 來源 | F27: 標記
A28: 高通（Qualcomm） | B28: QCOM | C28: 19.47 | D28: 2026-10-27 | E28: stockanalysis 個股頁 Forward PE（分析師共識；價格日期如左） | F28: Interested-party（賣方共識）
A29: 博通（Broadcom） | B29: AVGO | C29: 18.52 | D29: 2026-10-23 | E29: stockanalysis（經 mrvl、amd 模型 2026-10-23 取值；本次頁面快取過舊） | F29: Interested-party（賣方共識）
A30: 邁威爾（Marvell） | B30: MRVL | C30: 42.96 | D30: 2026-10-27 | E30: stockanalysis 個股頁 Forward PE（分析師共識；價格日期如左） | F30: Interested-party（賣方共識）
A31: Rambus | B31: RMBS | C31: 24.24 | D31: 2026-10-26 | E31: stockanalysis 個股頁 Forward PE（分析師共識；價格日期如左） | F31: Interested-party（賣方共識）
A32: 新思科技（Synopsys） | B32: SNPS | C32: 25.72 | D32: 2026-10-26 | E32: stockanalysis 個股頁 Forward PE（分析師共識；價格日期如左） | F32: Interested-party（賣方共識）
A33: 益華電腦（Cadence） | B33: CDNS | C33: 36 | D33: 2026-10-27 | E33: stockanalysis 個股頁 Forward PE（分析師共識；價格日期如左） | F33: Interested-party（賣方共識）
A34: 同業前瞻 P/E 中位數 | B34: =MEDIAN(C28:C33) -> 24.98 | E34: IP 授權與 EDA（Rambus、新思、益華）、手機與資料中心晶片客戶兼競爭者（高通、博通、邁威爾）；Synopsys、Cadence 已在 Bloomberg 前瞻倍數資料外，相對倍數只計 csv 內同業；非 A 股公司不列 A 股
A35: 12 個月後的前瞻 EPS（情境加權） | B35: =tp_wA*(0.416666666666667*B9+0.583333333333333*B10)+tp_wB*(0.416666666666667*C9+0.583333333333333*C10)+tp_wC*(0.416666666666667*D9+0.583333333333333*D10) -> 2.9014788 | E35: 約 2027-10 時的未來 12 月（2027-11～2028-10）≈ 5／12 × FY2028＋7／12 × FY2029（會計年度 3 月底）
A36: Comparable 目標價 | B36: =B34*B35 -> 72.47894 | E36: 同業中位數 × 上列 EPS
A38: 0.3 結論
A39: 項目 | B39: 數值 | E39: 說明
A40: 目標價（DCF 與 Comparable 加權） | B40: =tp_w_dcf*B24+(1-tp_w_dcf)*tp_comp_adj -> 53.517057 | E40: tp_w_dcf × DCF 目標價＋（1 − tp_w_dcf）× Comparable 目標價（相對倍數調整後，見第 0.5 節；ARM 無 Bloomberg 前瞻倍數，係數＝1）
A41: Comparable 目標價（市場主流同業法） | B41: =B36 -> 72.47894 | E41: 引用 0.2（未作相對倍數調整）
A42: 市場共識目標價 | B42: =cons_tp -> 290.71 | E42: stockanalysis（S&P Global）43 位平均 290.71，2026-10-21
A43: 上檔空間：加權目標價 | B43: =B40/px-1 -> -0.76617853 | E43: 現價＝In 頁 px（2026-10-30 收盤 228.88）
A44: 上檔空間：Comparable 目標價 | B44: =B41/px-1 -> -0.68333214
A45: 上檔空間級距 | B45: =IF(B43>0.5,"大於 50%",IF(B43>0.25,"25%–50%",IF(B43>=0,"0%–25%",IF(B43>=-0.25,"0%～−25%",IF(B43>=-0.5,"−25%～−50%","小於 −50%"))))) -> 小於 −50% | E45: 以「上檔空間：加權目標價」分六級（Andy 2026-10-25 14:00）
A46: 投資建議 | B46: =IF(B43>0.5,"強力買進",IF(B43>0.25,"買進",IF(B43>=-0.25,"中立",IF(B43>=-0.5,"放空","強力放空")))) -> 強力放空 | E46: 依上檔空間固定規則（Andy 2026-10-25 14:17）：大於 +50% 強力買進、+25%～+50% 買進、−25%～+25% 中立、−50%～−25% 放空、小於 −50% 強力放空
A47: 與市場共識目標價的差距：EPS 因素 | B47: =B35/cons_feps-1 -> 0.20091301 | E47: 本模型前瞻 EPS（約 2027-10 起 12 個月）÷ 共識前瞻 EPS（現在起 12 個月）− 1；期間差約一年
A48: 與市場共識目標價的差距：倍數因素 | B48: =(cons_tp/cons_feps)/B34-1 -> 3.8168119 | E48: ="共識目標價 ÷ 共識前瞻 EPS 隱含 "&TEXT(cons_tp/cons_feps,"0.0")&"x，同業中位數 "&TEXT(B34,"0.0")&"x" -> 共識目標價 ÷ 共識前瞻 EPS 隱含 120.3x，同業中位數 25.0x
A49: 價格帶（DCF 不如預期～順利） | B49: =TEXT(D23,"#,##0.00")&"～"&TEXT(B23,"#,##0.00") -> 21.01～46.47 | E49: C 情境價值～A 情境價值（推到 12 個月後）
A50: 歷史倍數檢查：現價隱含 P/E 的十年分位（A／B／C） | B50: =IF(px/B9<=MIN($B$54:$K$54),0,IF(px/B9>=MAX($B$54:$K$54),1,PERCENTRANK($B$54:$K$54,px/B9))) -> 1 | C50: =IF(px/C9<=MIN($B$54:$K$54),0,IF(px/C9>=MAX($B$54:$K$54),1,PERCENTRANK($B$54:$K$54,px/C9))) -> 1 | D50: =IF(px/D9<=MIN($B$54:$K$54),0,IF(px/D9>=MAX($B$54:$K$54),1,PERCENTRANK($B$54:$K$54,px/D9))) -> 1 | E50: 現價 ÷ 各情境 FY2028 EPS 在年底 P/E 分布（下方列；2023 年 9 月上市，只有 2023–2025 三年）的分位；低於最小值記 0%、高於最大值記 100%；只作檢查，不進目標價
A51: 目標價方法 | B51: DCF：股東現金流＝non-GAAP EPS ×（1 − g／ROE），r＝10%、g＝4%、ROE＝近三年平均約 10.5%（GAAP；再投資率約 38%），FY2027–29 驅動因子、FY2030–32 收斂法＋永續；non-GAAP EPS 排除股票薪酬（FY2026 GAAP EPS 0.85 vs non-GAAP 1.77），DCF 因此偏高估，但 ROE 低使再投資率高、偏低估。Comparable：高通、博通、邁威爾、Rambus、新思、益華前瞻 P/E 中位數；Arm 現價約 95 倍共識前瞻 EPS，遠高於同業，Comparable 法等於假設溢價在 12 個月內消失，偏低估。SoftBank 持股約九成、流通股約一成，市場流通量低可能支撐溢價；本模型不作流通量調整（只在方法說明）。ARM 無 Bloomberg 前瞻倍數歷史，相對倍數係數＝1。
A53: 年底 P/E（歷史分位檢查用；12 月收盤 ÷ 該月所在會計年度的 non-GAAP EPS；2023 年 9 月上市，2016–2022 年無資料） | B53: 2016 | C53: 2017 | D53: 2018 | E53: 2019 | F53: 2020 | G53: 2021 | H53: 2022 | I53: 2023 | J53: 2024 | K53: 2025
A54: 年底 P/E | I54: =75.14/1.27 -> 59.165354 | J54: =123.36/1.63 -> 75.680982 | K54: =109.31/1.77 -> 61.757062
A55: 來源：12 月收盤 digrin 月線（2023 75.14、2024 123.36、2025 109.31）；non-GAAP EPS FY2024 1.27、FY2025 1.63、FY2026 1.77（股東信）。stockanalysis GAAP P/E（會計年度末）FY2024 419.9、FY2025 142.1、FY2026 177.7 只作核對
A58: 1. 價格與市場隱含倍數
A59: 項目 | B59: A | C59: B | D59: C | E59: 說明
A60: 現價（2026-10-30 收盤） | B60: =px -> 228.88
A61: 現價 ÷ FY2026 EPS（實績） | B61: =px/PL!D14 -> 129.40383 | C61: =px/PL!D27 -> 129.40383 | D61: =px/PL!D40 -> 129.40383
A62: 現價 ÷ FY2027 EPS（模型） | B62: =px/PL!E14 -> 107.81403 | C62: =px/PL!E27 -> 107.81403 | D62: =px/PL!E40 -> 107.81403
A63: 現價 ÷ FY2028 EPS（模型） | B63: =px/PL!F14 -> 81.622332 | C63: =px/PL!F27 -> 87.967315 | D63: =px/PL!F40 -> 97.187528
A64: 現價 ÷ FY2029 EPS（模型） | B64: =px/PL!G14 -> 62.72152 | C64: =px/PL!G27 -> 74.508729 | D64: =px/PL!G40 -> 96.020494
A65: 近 12 月 non-GAAP EPS（2Q26～1Q27） | B65: =1.77-0.35+0.45 -> 1.87
A66: 現價 ÷ 近 12 月 non-GAAP EPS | B66: =px/B65 -> 122.39572
A67: 現價 ÷ 共識前瞻 EPS | B67: =px/cons_feps -> 94.732718
A68: 市值（現價 × 稀釋股數，十億美元） | B68: =px*q_sh -> 247.1904
A69: 流通市值（× (1 − SoftBank 持股)，十億美元） | B69: =px*q_sh*(1-sb_own) -> 24.71904
A72: 0.5 相對倍數調整（Comparable 目標倍數＝同業中位數 × 本公司 10 年相對同業的 P/E 比；Andy 2026-10-27 新增，放在本頁最後以免位移既有儲存格）
A73: 資料：2017–2026 各年度窗口（前一年 11 月～當年 10 月）Bloomberg 月底前瞻 P/E（BF）的中位數（tools/data/fwd_mult_hist.csv），[Verified] 來源、[Derived] 彙總；有效值 0 < 值 ≤ 200，無效值以「剔除:」文字列示、不進中位數。本公司或同業有效年數 < 7 不納入；有效同業 < 2 家或本公司不足時係數＝1（不調整）。
A74: 公司 | B74: 代號 | C74: 角色 | D74: 2016/11–2017/10 | E74: 2017/11–2018/10 | F74: 2018/11–2019/10 | G74: 2019/11–2020/10 | H74: 2020/11–2021/10 | I74: 2021/11–2022/10 | J74: 2022/11–2023/10 | K74: 2023/11–2024/10 | L74: 2024/11–2025/10 | M74: 2025/11–2026/10 | N74: 有效年數 | O74: 10 年中位數 | P74: 納入值 | Q74: 來源
A75: Arm | B75: ARM | C75: 本公司 | N75: =COUNT(D75:M75) -> 0 | O75: =IF(N75>0,MEDIAN(D75:M75),"") | P75: =IF(N75>=7,O75,"") | Q75: 未找到
A76: 高通（Qualcomm） | B76: QCOM | C76: 同業 | D76: 13.58 | E76: 16.82 | F76: 14.898 | G76: 17.535 | H76: 16.8875 | I76: 11.188 | J76: 12.0455 | K76: 15.679 | L76: 13.405 | M76: 15.5145 | N76: =COUNT(D76:M76) -> 10 | O76: =IF(N76>0,MEDIAN(D76:M76),"") -> 15.20625 | P76: =IF(N76>=7,O76,"") -> 15.20625 | Q76: Bloomberg QCOM US Equity BEST_PE_RATIO（BF＝未來 12 個月，月底）
A77: 博通（Broadcom） | B77: AVGO | C77: 同業 | D77: 14.324 | E77: 11.8025 | F77: 12.0165 | G77: 13.4005 | H77: 16.6275 | I77: 14.926 | J77: 16.6365 | K77: 26.099 | L77: 34.256 | M77: 25.1125 | N77: =COUNT(D77:M77) -> 10 | O77: =IF(N77>0,MEDIAN(D77:M77),"") -> 15.77675 | P77: =IF(N77>=7,O77,"") -> 15.77675 | Q77: Bloomberg AVGO US Equity BEST_PE_RATIO（BF＝未來 12 個月，月底）
A78: 邁威爾（Marvell） | B78: MRVL | C78: 同業 | D78: 15.149 | E78: 15.2585 | F78: 23.416 | G78: 29.4115 | H78: 35.586 | I78: 23.5535 | J78: 24.969 | K78: 35.5045 | L78: 25.813 | M78: 36.897 | N78: =COUNT(D78:M78) -> 10 | O78: =IF(N78>0,MEDIAN(D78:M78),"") -> 25.391 | P78: =IF(N78>=7,O78,"") -> 25.391 | Q78: Bloomberg MRVL US Equity BEST_PE_RATIO（BF＝未來 12 個月，月底）
A79: Rambus | B79: RMBS | C79: 同業 | D79: 19.1405 | E79: 14.7895 | F79: 12.3635 | G79: 14.111 | H79: 16.3885 | I79: 16.8025 | J79: 26.5045 | K79: 25.812 | L79: 24.1025 | M79: 31.7485 | N79: =COUNT(D79:M79) -> 10 | O79: =IF(N79>0,MEDIAN(D79:M79),"") -> 17.9715 | P79: =IF(N79>=7,O79,"") -> 17.9715 | Q79: Bloomberg RMBS US Equity BEST_PE_RATIO（BF＝未來 12 個月，月底）
A80: 新思科技（Synopsys） | B80: SNPS | C80: 同業 | N80: =COUNT(D80:M80) -> 0 | O80: =IF(N80>0,MEDIAN(D80:M80),"") | P80: =IF(N80>=7,O80,"") | Q80: 未找到
A81: 益華電腦（Cadence） | B81: CDNS | C81: 同業 | N81: =COUNT(D81:M81) -> 0 | O81: =IF(N81>0,MEDIAN(D81:M81),"") | P81: =IF(N81>=7,O81,"") | Q81: 未找到
A83: 本公司 10 年中位數（納入值） | B83: =P75 | E83: 空白＝本公司有效年數不足
A84: 納入的同業家數 | B84: =COUNT(P76:P81) -> 4
A85: 同業 10 年中位數的中位數 | B85: =IF(B84>0,MEDIAN(P76:P81),"") -> 16.874125
A86: 原始比值（本公司 ÷ 同業） | B86: =IF(AND(ISNUMBER(B83),B84>=2),B83/B85,"") | E86: ＜1＝本公司長期比同業便宜（折價），＞1＝長期溢價
A87: 夾值下限 | B87: 0.5 | E87: [Assumed] 避免單一歷史異常主導；tools/relative_multiple.py 的 RM_LO
A88: 夾值上限 | B88: 2 | E88: [Assumed] tools/relative_multiple.py 的 RM_HI
A89: 相對倍數調整係數 | B89: =IF(ISNUMBER(B86),MIN(MAX(B86,B87),B88),1) -> 1 | E89: 資料不足時＝1（不調整）
A90: Comparable 目標價（相對倍數調整後） | B90: =Val!$B$36*B89 -> 72.47894 | E90: ＝Comparable 目標價（市場主流同業法）× 調整係數；加權目標價使用本列

Sheet Recon
A1: Recon — 本模型 vs 公司指引與共識。只作事後對照，不為對上數字而調參數。分部共識（授權、權利金分列）：未找到；FY2028 共識 EPS：未找到
A3: 項目 | B3: 對照值 | C3: 模型 A | D3: 差距 A | E3: 模型 B | F3: 差距 B | G3: 模型 C | H3: 差距 C | I3: 對照來源 | J3: 說明
A4: A. 公司指引與共識（校準未使用共識）
A5: 2Q27 營收 vs 公司指引中點 | B5: =1.38 -> 1.38 | C5: =Q!E6 -> 1.38965 | D5: =C5/B5-1 -> 0.0069927536 | E5: =Q!E6 -> 1.38965 | F5: =E5/B5-1 -> 0.0069927536 | G5: =Q!E6 -> 1.38965 | H5: =G5/B5-1 -> 0.0069927536 | I5: 股東信 2026-07-29 | J5: 模型＝去年同期 × 指引年增
A6: 2Q27 營收 vs 共識 | B6: =c_q2rev -> 1.376 | C6: =Q!E6 -> 1.38965 | D6: =C6/B6-1 -> 0.0099200581 | E6: =Q!E6 -> 1.38965 | F6: =E6/B6-1 -> 0.0099200581 | G6: =Q!E6 -> 1.38965 | H6: =G6/B6-1 -> 0.0099200581 | I6: Hudson Labs
A7: 2Q27 non-GAAP EPS vs 公司指引中點 | B7: =0.47 -> 0.47 | C7: =Q!E15 -> 0.48579597 | D7: =C7/B7-1 -> 0.033608456 | E7: =Q!E15 -> 0.48579597 | F7: =E7/B7-1 -> 0.033608456 | G7: =Q!E15 -> 0.48579597 | H7: =G7/B7-1 -> 0.033608456 | I7: 股東信
A8: FY2027 營收 vs 共識 | B8: =c_rev27 -> 6.1 | C8: =PL!E81 -> 5.88665 | D8: =C8/B8-1 -> -0.03497541 | E8: =PL!E122 -> 5.88665 | F8: =E8/B8-1 -> -0.03497541 | G8: =PL!E163 -> 5.88665 | H8: =G8/B8-1 -> -0.03497541 | I8: stockanalysis（S&P Global）
A9: FY2027 non-GAAP EPS vs 共識 | B9: =c_eps27 -> 2.23 | C9: =PL!E97 -> 2.1229148 | D9: =C9/B9-1 -> -0.048020282 | E9: =PL!E138 -> 2.1229148 | F9: =E9/B9-1 -> -0.048020282 | G9: =PL!E179 -> 2.1229148 | H9: =G9/B9-1 -> -0.048020282 | I9: 同上 | J9: 高 2.38、低 2.06
A10: B. 權利金結構（機制檢查）
A11: FY2026 智慧型手機 ÷ 權利金（20-F） | B11: =ph_s -> 0.43 | C11: =PL!D86 -> 0.43 | D11: =C11-B11 -> 0 | E11: =PL!D127 -> 0.43 | F11: =E11-B11 -> 0 | G11: =PL!D168 -> 0.43 | H11: =G11-B11 -> 0 | I11: 20-F
A12: FY2028 資料中心 ÷ 權利金 | C12: =PL!F85 -> 0.24990459 | E12: =PL!F126 -> 0.2430614 | G12: =PL!F167 -> 0.23676144 | I12: — | J12: 管理層：資料中心將成為最大業務（4Q26 股東信）
A13: FY2029 資料中心 ÷ 權利金 | C13: =PL!G85 -> 0.28369311 | E13: =PL!G126 -> 0.24893013 | G13: =PL!G167 -> 0.20279519 | I13: —
A14: FY2026 手機每支權利金（美元） | C14: =PL!D70 -> 0.92097541 | E14: =PL!D111 -> 0.92097541 | G14: =PL!D152 -> 0.92097541 | I14: — | J14: Derived＝43% × 權利金 ÷ 出貨
A15: FY2028 NVIDIA Grace／Vera CPU（百萬顆） | C15: =PL!F64 -> 4.825 | E15: =PL!F105 -> 4.5875 | G15: =PL!F146 -> 4.35 | I15: Siliconomics 快照 v0.10（siliconomics_snapshot_v0.10.json）
A16: FY2028 AGI CPU 晶片營收（US$B） | C16: =PL!F78 -> 1.4 | E16: =PL!F119 -> 1 | G16: =PL!F160 -> 0.5 | I16: — | J16: 客戶需求 FY2027–28 逾 20 億美元（公司）
A17: FY2027 + FY2028 AGI CPU 晶片營收合計 vs 公司稱客戶需求 | B17: =2 -> 2 | C17: =PL!E78+PL!F78 -> 1.55 | D17: =C17/B17-1 -> -0.225 | E17: =PL!E119+PL!F119 -> 1.15 | F17: =E17/B17-1 -> -0.425 | G17: =PL!E160+PL!F160 -> 0.65 | H17: =G17/B17-1 -> -0.675 | I17: 股東信 2026-07-29 | J17: 需求≠營收（產能限制）

Sheet Sens
A1: Sens — 一次改一個輸入（In 頁敏感度低／高值），整本活頁簿以 LibreOffice 重算後的加權目標價（Val 第 0 節）與情境 B 的 FY2028 EPS；由 arm/sens_arm.py 產生 arm/sens.json，建置時寫入（數值）
A2: 相對基準＝案例目標價 ÷ 基準加權目標價 − 1；龍捲風依絕對值排序（HTML）。FY2027 錨點與 FY2026 比例的輸入（q2_lg、ph_s 等）透過錨點影響之後各年。tp_g 案例同時移動 DCF 永續成長與 PL 收斂目標 fade_g（fade_g 以 tp_g 為公式）。
A3: 驅動 | B3: 設定 | C3: 方向 | D3: 加權目標價 | E3: 相對基準 | F3: 鍵 | G3: FY2028 EPS（情境 B） | H3: FY2028 EPS 相對基準 | I3: 說明
A4: 基準 | B4: In 頁基準欄 | C4: — | D4: =tp_final -> 53.517057 | E4: 0 | G4: =PL!F27 -> 2.6018755 | H4: 0 | I4: 本活頁簿重算值
A5: 2Q27 授權及其他年增（公司指引：mid-30%）：低 | B5: 0.35 → 0.3 | C5: 低 | D5: 53.107663 | E5: =D5/D$4-1 -> -0.0076497888 | F5: q2_lg | G5: 2.5801798 | H5: =G5/G$4-1 -> -0.0083384832 | I5: 重算值（sens_arm.py）
A6: 2Q27 授權及其他年增（公司指引：mid-30%）：高 | B6: 0.35 → 0.38 | C6: 高 | D6: 53.762672 | E6: =D6/D$4-1 -> 0.0045894799 | F6: q2_lg | G6: 2.6148929 | H6: =G6/G$4-1 -> 0.0050030899 | I6: 重算值（sens_arm.py）
A7: 2Q27 權利金年增（公司指引：low-teens）：低 | B7: 0.12 → 0.1 | C7: 低 | D7: 53.339056 | E7: =D7/D$4-1 -> -0.0033260626 | F7: q2_rg | G7: 2.5919977 | H7: =G7/G$4-1 -> -0.0037964017 | I7: 重算值（sens_arm.py）
A8: 2Q27 權利金年增（公司指引：low-teens）：高 | B8: 0.12 → 0.14 | C8: 高 | D8: 53.695046 | E8: =D8/D$4-1 -> 0.0033258433 | F8: q2_rg | G8: 2.6117532 | H8: =G8/G$4-1 -> 0.0037964017 | I8: 重算值（sens_arm.py）
A9: 3Q27、4Q27 授權及其他年增：低 | B9: 0.2 → 0.08 | C9: 低 | D9: 50.990337 | E9: =D9/D$4-1 -> -0.047213358 | F9: h2_lg | G9: 2.4680109 | H9: =G9/G$4-1 -> -0.051449251 | I9: 重算值（sens_arm.py）
A10: 3Q27、4Q27 授權及其他年增：高 | B10: 0.2 → 0.3 | C10: 高 | D10: 55.621378 | E10: =D10/D$4-1 -> 0.039320564 | F10: h2_lg | G10: 2.7134293 | H10: =G10/G$4-1 -> 0.042874376 | I10: 重算值（sens_arm.py）
A11: 3Q27、4Q27 權利金年增：低 | B11: 0.15 → 0.08 | C11: 低 | D11: 52.101906 | E11: =D11/D$4-1 -> -0.026442987 | F11: h2_rg | G11: 2.5233632 | H11: =G11/G$4-1 -> -0.030175271 | I11: 重算值（sens_arm.py）
A12: 3Q27、4Q27 權利金年增：高 | B12: 0.15 → 0.2 | C12: 高 | D12: 54.527423 | E12: =D12/D$4-1 -> 0.01887933 | F12: h2_rg | G12: 2.6579557 | H12: =G12/G$4-1 -> 0.021553765 | I12: 重算值（sens_arm.py）
A13: 3Q27 non-GAAP 營業費用：低 | B13: 0.8 → 0.78 | C13: 低 | D13: 53.861904 | E13: =D13/D$4-1 -> 0.0064436901 | F13: q3_opx | G13: 2.6195213 | H13: =G13/G$4-1 -> 0.006781981 | I13: 重算值（sens_arm.py）
A14: 3Q27 non-GAAP 營業費用：高 | B14: 0.8 → 0.83 | C14: 高 | D14: 52.999786 | E14: =D14/D$4-1 -> -0.0096655351 | F14: q3_opx | G14: 2.5754067 | H14: =G14/G$4-1 -> -0.010172972 | I14: 重算值（sens_arm.py）
A15: 4Q27 non-GAAP 營業費用：低 | B15: 0.82 → 0.8 | C15: 低 | D15: 53.861904 | E15: =D15/D$4-1 -> 0.0064436901 | F15: q4_opx | G15: 2.6195213 | H15: =G15/G$4-1 -> 0.006781981 | I15: 重算值（sens_arm.py）
A16: 4Q27 non-GAAP 營業費用：高 | B16: 0.82 → 0.86 | C16: 高 | D16: 52.827362 | E16: =D16/D$4-1 -> -0.01288738 | F16: q4_opx | G16: 2.5665837 | H16: =G16/G$4-1 -> -0.013563962 | I16: 重算值（sens_arm.py）
... A76: 目標價中 DCF 的權重；其餘為 Comparable：高 | B76: 0.5 → 0.7 | C76: 高 | D76: 45.932304 | E76: =D76/D$4-1 -> -0.1417259 | F76: tp_w_dcf | G76: 2.6018755 | H76: =G76/G$4-1 -> 0 | I76: 重算值（sens_arm.py）
A78: 讀法：DCF 與 Comparable 目標價都遠低於現價，DCF 權重是最大的單一變數（Comparable 約為 DCF 的兩倍）；其次是影響 FY2028–29 EPS 的授權成長、營業費用與晶片毛利率。手機與資料中心的拆分比例只改變權利金的組成，對目標價影響小。

Sheet Sources
A1: 來源（公司原文＝Arm 股東信、6-K、20-F、法說；共識與券商皆為 Interested-party）
A2: 公司：1Q27 股東信（6-K Exhibit 99.2，2026-07-29；1Q27 實績、2Q27 指引、AGI CPU 需求、資料中心權利金） | B2: https://www.sec.gov/Archives/edgar/data/0001973239/000197323926000113/exhibit992fye27q130-junx26.htm
A3: 公司：4Q26 股東信（6-K，2026-05-06；FY2026 全年、AGI CPU、1Q27 指引） | B3: https://www.sec.gov/Archives/edgar/data/0001973239/000197323926000062/exhibit992fye26q431-marx26.htm
A4: 公司：4Q25 股東信（6-K，2025-05；FY2025 全年、FY2024 non-GAAP EPS） | B4: https://www.sec.gov/Archives/edgar/data/1973239/000197323925000010/exhibit992fye25q431-marx25.htm
A5: 公司：20-F（FY2026；手機權利金約 43%、前五大客戶 57%、Arm China 16%、SoftBank 控股） | B5: https://www.sec.gov/Archives/edgar/data/0001973239/000197323926000097/arm-20260331.htm
A6: 公司：3Q26 法說逐字稿（The Motley Fool 2026-02-04；資料中心占比、CSS、SoftBank 協議 2 億美元／季、FY2027 約 20%） | B6: https://www.fool.com/earnings/call-transcripts/2026/02/04/arm-holdings-arm-q3-2026-earnings-transcript/
A7: 公司：Arm 新聞室 1Q27 結果（2026-07-29） | B7: https://newsroom.arm.com/news/arm-q1-fye27-results
A8: 公司：2Q27 財報日公告（2026-11-04 美東盤後） | B8: https://newsroom.arm.com/news/arm-announces-earnings-release-date-for-second-quarter-fiscal-year-ending-2027
A9: 媒體：Longbridge 2026-07-29（2Q27 指引與共識） | B9: https://longbridge.com/news/294985711
A10: 研究：Hudson Labs 2Q27 財報預覽（共識、FY2027 手機權利金 high-teens） | B10: https://www.hudson-labs.com/research/arm-q2-2027-earnings-preview-arm-revenue-and-outlook
A11: 法律：Paul Weiss 2026-10-13（Qualcomm 對 Arm 陪審團判決） | B11: https://www.paulweiss.com/insights/client-news/qualcomm-wins-jury-verdict-in-breach-of-contract-and-interference-trial-against-arm
A12: 資料商：stockanalysis（共識 EPS、目標價、Forward PE、ROE；同業 Forward PE） | B12: https://stockanalysis.com/stocks/arm/forecast/
A13: 資料商：InvestSmart 價格歷史（2026-10-30 收盤 228.88）；digrin 月線（年底收盤） | B13: https://www.investsmart.com.au/security/nasdaq/arm/arm-holdings-plc/share-price
... A15: 待補（人工）：2Q27 財報（2026-11-04）；分市場權利金（公司只揭露手機）；AGI CPU 營收認列方式；Qualcomm 法官審理判決；FY2028 共識；Bloomberg 前瞻倍數（ARM 未取） | B15: 未找到
