Workbook

Sheet ①新增或變動列
A1: ① 本段（S2／v0.6-P2）新增或變動的每一列（前值＝S1 版 v0.6-P1.1；後值＝本版）
A3: 頁 | B3: 列名 | C3: ID／編號 | D3: 前值 | E3: 後值 | F3: 來源／標記／公式 | G3: 說明
A4: SRC_OAI | B4: API 價格事件 1 牌價：top 層 輸入（GPT-5.6 Sol） | C4: SRC_OAI_113 | D4: —（新增） | E4: 5 | F4: Verified；openai.com 2026-07-30 GPT-5.6 降價公告；GPT-6 Sol/Luna 2026-09-22 發布（Techzine、MarkTechPost）；GPT-6 Astra 2026-09-03；日期 2026-07-09 | G4: 07-09 GPT-5.6 Sol 輸入；N3a 層級角色＝top（GPT-6 Astra 上市前）
A5: SRC_OAI | B5: API 價格事件 1 牌價：top 層 輸出（GPT-5.6 Sol） | C5: SRC_OAI_114 | D5: —（新增） | E5: 30 | F5: Verified；openai.com 2026-07-30 GPT-5.6 降價公告；GPT-6 Sol/Luna 2026-09-22 發布（Techzine、MarkTechPost）；GPT-6 Astra 2026-09-03；日期 2026-07-09 | G5: 07-09 GPT-5.6 Sol 輸出；層級角色＝top
A6: SRC_OAI | B6: API 價格事件 1 牌價：mid 層 輸入（GPT-5.6 Terra） | C6: SRC_OAI_115 | D6: —（新增） | E6: 2.5 | F6: Verified；openai.com 2026-07-30 GPT-5.6 降價公告；GPT-6 Sol/Luna 2026-09-22 發布（Techzine、MarkTechPost）；GPT-6 Astra 2026-09-03；日期 2026-07-09 | G6: 07-09 GPT-5.6 Terra 輸入；層級角色＝mid
A7: SRC_OAI | B7: API 價格事件 1 牌價：mid 層 輸出（GPT-5.6 Terra） | C7: SRC_OAI_116 | D7: —（新增） | E7: 15 | F7: Verified；openai.com 2026-07-30 GPT-5.6 降價公告；GPT-6 Sol/Luna 2026-09-22 發布（Techzine、MarkTechPost）；GPT-6 Astra 2026-09-03；日期 2026-07-09 | G7: 07-09 GPT-5.6 Terra 輸出；層級角色＝mid
A8: SRC_OAI | B8: API 價格事件 1 牌價：low 層 輸入（GPT-5.6 Luna） | C8: SRC_OAI_117 | D8: —（新增） | E8: 1 | F8: Verified；openai.com 2026-07-30 GPT-5.6 降價公告；GPT-6 Sol/Luna 2026-09-22 發布（Techzine、MarkTechPost）；GPT-6 Astra 2026-09-03；日期 2026-07-09 | G8: 07-09 GPT-5.6 Luna 輸入；層級角色＝low
A9: SRC_OAI | B9: API 價格事件 1 牌價：low 層 輸出（GPT-5.6 Luna） | C9: SRC_OAI_118 | D9: —（新增） | E9: 6 | F9: Verified；openai.com 2026-07-30 GPT-5.6 降價公告；GPT-6 Sol/Luna 2026-09-22 發布（Techzine、MarkTechPost）；GPT-6 Astra 2026-09-03；日期 2026-07-09 | G9: 07-09 GPT-5.6 Luna 輸出；層級角色＝low
A10: SRC_OAI | B10: API 價格事件 2 牌價：mid 層 輸入（Terra 降價） | C10: SRC_OAI_119 | D10: —（新增） | E10: 2 | F10: Verified；openai.com 2026-07-30 GPT-5.6 降價公告；GPT-6 Sol/Luna 2026-09-22 發布（Techzine、MarkTechPost）；GPT-6 Astra 2026-09-03；日期 2026-07-30 | G10: 07-30 Terra 降價後輸入（−20%）
A11: SRC_OAI | B11: API 價格事件 2 牌價：mid 層 輸出（Terra 降價） | C11: SRC_OAI_120 | D11: —（新增） | E11: 12 | F11: Verified；openai.com 2026-07-30 GPT-5.6 降價公告；GPT-6 Sol/Luna 2026-09-22 發布（Techzine、MarkTechPost）；GPT-6 Astra 2026-09-03；日期 2026-07-30 | G11: 07-30 Terra 降價後輸出（−20%）
A12: SRC_OAI | B12: API 價格事件 2 牌價：low 層 輸入（Luna 降價） | C12: SRC_OAI_121 | D12: —（新增） | E12: 0.2 | F12: Verified；openai.com 2026-07-30 GPT-5.6 降價公告；GPT-6 Sol/Luna 2026-09-22 發布（Techzine、MarkTechPost）；GPT-6 Astra 2026-09-03；日期 2026-07-30 | G12: 07-30 Luna 降價後輸入（−80%）
A13: SRC_OAI | B13: API 價格事件 2 牌價：low 層 輸出（Luna 降價） | C13: SRC_OAI_122 | D13: —（新增） | E13: 1.2 | F13: Verified；openai.com 2026-07-30 GPT-5.6 降價公告；GPT-6 Sol/Luna 2026-09-22 發布（Techzine、MarkTechPost）；GPT-6 Astra 2026-09-03；日期 2026-07-30 | G13: 07-30 Luna 降價後輸出（−80%）
A14: SRC_OAI | B14: API 價格事件 3 牌價：top 層 輸入（Sol 促銷） | C14: SRC_OAI_123 | D14: —（新增） | E14: 4 | F14: Verified；openai.com 2026-07-30 GPT-5.6 降價公告；GPT-6 Sol/Luna 2026-09-22 發布（Techzine、MarkTechPost）；GPT-6 Astra 2026-09-03；日期 2026-08-22 | G14: 08-22 Sol 促銷輸入
A15: SRC_OAI | B15: API 價格事件 3 牌價：top 層 輸出（Sol 促銷） | C15: SRC_OAI_124 | D15: —（新增） | E15: 20 | F15: Verified；openai.com 2026-07-30 GPT-5.6 降價公告；GPT-6 Sol/Luna 2026-09-22 發布（Techzine、MarkTechPost）；GPT-6 Astra 2026-09-03；日期 2026-08-22 | G15: 08-22 Sol 促銷輸出
... A19: SRC_OAI | B19: API 價格事件 5 公告日（Excel 日期序列值） | C19: SRC_OAI_128 | D19: —（新增） | E19: 46287 | F19: Verified；openai.com 2026-07-30 GPT-5.6 降價公告；GPT-6 Sol/Luna 2026-09-22 發布（Techzine、MarkTechPost）；GPT-6 Astra 2026-09-03；日期 2026-09-22 | G19: 2026-09-22（GPT-6 Sol／Luna 上市（mid、low 層降價））；公告日＝生效日（v0.5 事件清單未區分）；序列值 46287＝2026-09-22
A20: Inputs | B20: 價格事件 2（07-30）生效日偏移 | C20: INP_246 | D20: —（新增） | E20: 0（-91～91） | F20: Assumed；E8c | G20: 基準 0＝SRC_OAI 公告日（Verified）；區間 ±91 天（±1 季，Assumed；S2 工作單預設）。偏移後日期限於 FY2026 內
A21: Inputs | B21: 價格事件 3（08-22）生效日偏移 | C21: INP_247 | D21: —（新增） | E21: 0（-91～91） | F21: Assumed；E8c | G21: 基準 0＝SRC_OAI 公告日（Verified）；區間 ±91 天（±1 季，Assumed；S2 工作單預設）。偏移後日期限於 FY2026 內
A22: Inputs | B22: 價格事件 4（09-03）生效日偏移 | C22: INP_248 | D22: —（新增） | E22: 0（-91～91） | F22: Assumed；E8c | G22: 基準 0＝SRC_OAI 公告日（Verified）；區間 ±91 天（±1 季，Assumed；S2 工作單預設）。偏移後日期限於 FY2026 內
A23: Inputs | B23: 價格事件 5（09-22）生效日偏移 | C23: INP_249 | D23: —（新增） | E23: 0（-91～91） | F23: Assumed；E8c | G23: 基準 0＝SRC_OAI 公告日（Verified）；區間 ±91 天（±1 季，Assumed；S2 工作單預設）。偏移後日期限於 FY2026 內
A24: Inputs | B24: FY2026 起日（定義常數；Excel 日期序列值） | C24: INP_250 | D24: —（新增） | E24: 46023（46023～46023） | F24: Decision；E6 | G24: 來源：定義常數；區間不適用（低＝高）；E6：公式內不得含常數，故進 Inputs。用途：46023＝2026-01-01；價格事件天數加權的年度起點
A25: Inputs | B25: 每年天數（定義常數） | C25: INP_251 | D25: —（新增） | E25: 365（365～365） | F25: Decision；E6 | G25: 來源：定義常數；區間不適用（低＝高）；E6：公式內不得含常數，故進 Inputs。用途：每日→年換算與 FY2026 天數加權的分母（2026 為 365 天）
A26: Inputs | B26: 每年月數（定義常數） | C26: INP_252 | D26: —（新增） | E26: 12（12～12） | F26: Decision；E6 | G26: 來源：定義常數；區間不適用（低＝高）；E6：公式內不得含常數，故進 Inputs。用途：月 ARPU → 年營收
A27: Inputs | B27: 單位換算：$M → $B 的除數（定義常數） | C27: INP_253 | D27: —（新增） | E27: 1000（1000～1000） | F27: Decision；E6 | G27: 來源：定義常數；區間不適用（低＝高）；E6：公式內不得含常數，故進 Inputs。用途：人數（M）× $ → $M；T token × $/M token → $M
A28: Inputs | B28: 單位換算：T token → M token 的乘數（定義常數） | C28: INP_254 | D28: —（新增） | E28: 1000000（1000000～1000000） | F28: Decision；E6 | G28: 來源：定義常數；區間不適用（低＝高）；E6：公式內不得含常數，故進 Inputs。用途：與 Tokenomics IF_AllocDemand（M tok/年）並列
A29: Inputs | B29: FY2026 獨立推估：下半年月數（定義常數） | C29: INP_255 | D29: —（新增） | E29: 6（6～6） | F29: Decision；E6 | G29: 來源：定義常數；區間不適用（低＝高）；E6：公式內不得含常數，故進 Inputs。用途：v0.5 fy2026Independent：Q1＋Q2＋下半年以 2026-08 ARR 外推
A30: Checks | B30: SRC_OAI 列數 | C30: C01 | D30: 106（OK） | E30: 122（OK） | F30: 列數隨新增列改變 | G30: 預期變動
A31: Checks | B31: Inputs 列數 | C31: C05 | D31: 233（OK） | E31: 243（OK） | F31: 列數隨新增列改變 | G31: 預期變動
A32: Checks | B32: E8c：listPriceFYAvg 2026 區間尚未傳遞（待 P2 事件時點 Inputs） | C32: C27 | D32: 待 P2（WARN） | E32: 退役（編號保留不重用） | F32: E8c 由事件時點 Inputs 傳遞 2026 區間，WARN 撤除
A33: Checks | B33: P2：2025 模型營收總額 − SRC 實際營收（$B；v0.5 校準恆等式） | C33: C28 | D33: —（新增） | E33: 0（OK） | F33: P2 檢查
A34: Checks | B34: P2：2025 API 計費比例 ∈ (0,1]（違反數） | C34: C29 | D34: —（新增） | E34: 0（OK） | F34: P2 檢查
A35: Checks | B35: P2：方案模型組合 luna＋sol＋astra≠1 的方案數 | C35: C30 | D35: —（新增） | E35: 0（OK） | F35: P2 檢查
A36: Checks | B36: P2：token 層級拆分合計 vs 拆分前總量（違反年數） | C36: C31 | D36: —（新增） | E36: 0（OK） | F36: P2 檢查
A37: Checks | B37: P2：消費端＋企業端＋其他 − 總額（各年絕對值合計，$B） | C37: C32 | D37: —（新增） | E37: 0（OK） | F37: P2 檢查
A38: Checks | B38: P2：Microsoft 分成累計超出上限的部分（$B） | C38: C33 | D38: —（新增） | E38: 0（OK） | F38: P2 檢查
A39: Checks | B39: E8c：價格事件生效日順序違反數（基準／提前／延後三欄） | C39: C34 | D39: —（新增） | E39: 0（OK） | F39: P2 檢查
A40: Checks | B40: E8c：2026 牌價區間 低 ≤ 基準 ≤ 高 的違反數（6 列） | C40: C35 | D40: —（新增） | E40: 0（OK） | F40: P2 檢查
A41: Checks | B41: D11：Inputs 情境 base 列＝各參數基準值（違反數） | C41: C36 | D41: —（新增） | E41: 0（OK） | F41: P2 檢查
A42: Checks | B42: P2 預覽：2025 token 合計 ÷ Tokenomics IF_AllocDemand | C42: C37 | D42: —（新增） | E42: 0.844365450322589（INFO） | F42: P2 檢查
A43: Checks | B43: P2 預覽：2025 未校準差距（$B）＝訂閱＋廣告＋其他＋處理 token×單價 − 實際 | C43: C38 | D43: —（新增） | E43: 1.02870549883871（INFO） | F43: P2 檢查
A44: Checks | B44: P2 預覽：2030 淨營收（$B） | C44: C39 | D44: —（新增） | E44: 126.38309270298（INFO） | F44: P2 檢查
A45: Map_v05 | B45: tokenRevenue.api.listPriceFYAvg.in.top.v.1 | C45: — | D45: P2（FY 平均牌價 2026：priceEvents 月加權） | E45: Revenue R01–R06 的 2026 欄（P2 實作：價格事件時點天數加權，Revenue 第七節；E8c） | F45: 去處文字改指本段實作位置 | G45: 去處類別不變（公式）
A46: Map_v05 | B46: tokenRevenue.api.listPriceFYAvg.in.top.lo.1 | C46: — | D46: P2（FY 平均牌價 2026：priceEvents 月加權） | E46: Revenue R01–R06 的 2026 欄（P2 實作：價格事件時點天數加權，Revenue 第七節；E8c） | F46: 去處文字改指本段實作位置 | G46: 去處類別不變（公式）
A47: Map_v05 | B47: tokenRevenue.api.listPriceFYAvg.in.top.hi.1 | C47: — | D47: P2（FY 平均牌價 2026：priceEvents 月加權） | E47: Revenue R01–R06 的 2026 欄（P2 實作：價格事件時點天數加權，Revenue 第七節；E8c） | F47: 去處文字改指本段實作位置 | G47: 去處類別不變（公式）
A48: Map_v05 | B48: tokenRevenue.api.listPriceFYAvg.in.mid.v.1 | C48: — | D48: P2（FY 平均牌價 2026：priceEvents 月加權） | E48: Revenue R01–R06 的 2026 欄（P2 實作：價格事件時點天數加權，Revenue 第七節；E8c） | F48: 去處文字改指本段實作位置 | G48: 去處類別不變（公式）
A49: Map_v05 | B49: tokenRevenue.api.listPriceFYAvg.in.mid.lo.1 | C49: — | D49: P2（FY 平均牌價 2026：priceEvents 月加權） | E49: Revenue R01–R06 的 2026 欄（P2 實作：價格事件時點天數加權，Revenue 第七節；E8c） | F49: 去處文字改指本段實作位置 | G49: 去處類別不變（公式）
A50: Map_v05 | B50: tokenRevenue.api.listPriceFYAvg.in.mid.hi.1 | C50: — | D50: P2（FY 平均牌價 2026：priceEvents 月加權） | E50: Revenue R01–R06 的 2026 欄（P2 實作：價格事件時點天數加權，Revenue 第七節；E8c） | F50: 去處文字改指本段實作位置 | G50: 去處類別不變（公式）
A51: Map_v05 | B51: tokenRevenue.api.listPriceFYAvg.in.low.v.1 | C51: — | D51: P2（FY 平均牌價 2026：priceEvents 月加權） | E51: Revenue R01–R06 的 2026 欄（P2 實作：價格事件時點天數加權，Revenue 第七節；E8c） | F51: 去處文字改指本段實作位置 | G51: 去處類別不變（公式）
A52: Map_v05 | B52: tokenRevenue.api.listPriceFYAvg.in.low.lo.1 | C52: — | D52: P2（FY 平均牌價 2026：priceEvents 月加權） | E52: Revenue R01–R06 的 2026 欄（P2 實作：價格事件時點天數加權，Revenue 第七節；E8c） | F52: 去處文字改指本段實作位置 | G52: 去處類別不變（公式）
A53: Map_v05 | B53: tokenRevenue.api.listPriceFYAvg.in.low.hi.1 | C53: — | D53: P2（FY 平均牌價 2026：priceEvents 月加權） | E53: Revenue R01–R06 的 2026 欄（P2 實作：價格事件時點天數加權，Revenue 第七節；E8c） | F53: 去處文字改指本段實作位置 | G53: 去處類別不變（公式）
A54: Map_v05 | B54: tokenRevenue.api.listPriceFYAvg.out.top.v.1 | C54: — | D54: P2（FY 平均牌價 2026：priceEvents 月加權） | E54: Revenue R01–R06 的 2026 欄（P2 實作：價格事件時點天數加權，Revenue 第七節；E8c） | F54: 去處文字改指本段實作位置 | G54: 去處類別不變（公式）
A55: Map_v05 | B55: tokenRevenue.api.listPriceFYAvg.out.top.lo.1 | C55: — | D55: P2（FY 平均牌價 2026：priceEvents 月加權） | E55: Revenue R01–R06 的 2026 欄（P2 實作：價格事件時點天數加權，Revenue 第七節；E8c） | F55: 去處文字改指本段實作位置 | G55: 去處類別不變（公式）
A56: Map_v05 | B56: tokenRevenue.api.listPriceFYAvg.out.top.hi.1 | C56: — | D56: P2（FY 平均牌價 2026：priceEvents 月加權） | E56: Revenue R01–R06 的 2026 欄（P2 實作：價格事件時點天數加權，Revenue 第七節；E8c） | F56: 去處文字改指本段實作位置 | G56: 去處類別不變（公式）
... A75: Map_v05 | B75: tokenRevenue.comparison.fy2026Independent.src | C75: — | D75: P2（FY2026 獨立推估：Q1＋Q2＋下半年 ARR 外推） | E75: Revenue R41（P2 實作：FY2026 獨立推估＝Q1＋Q2＋ARR×下半年月數÷12） | F75: 去處文字改指本段實作位置 | G75: 去處類別不變（公式）
A76: Demand | B76: 遷移率 μ（Plus→Go） | C76: D01 | D76: —（新頁） | E76: 、0.2413、0.2413、0.2413、0.2413、0.2413 | F76: =INP_013*(1-SRC_OAI_037/INP_073) | G76: 計畫幅度（Inputs 基準 0.3）×（1 − 公司計畫 Plus ÷ 無遷移 Plus 2026）；2026 起各年同值（v0.5）
A77: Demand | B77: Go 額外新增倍數 λ | C77: D02 | D77: —（新頁） | E77: 、1.95、1.95、1.95、1.95、1.95 | F77: =INP_013*(SRC_OAI_036-INP_073*(1-SRC_OAI_037/INP_073)-INP_065)/INP_065 | G77: ＝計畫幅度 ×（公司計畫 Go −（無遷移 Plus 2026 − 公司計畫 Plus）− 無遷移 Go 2026）÷ 無遷移 Go 2026；計畫幅度＝1 時，2026 Go 恰等於公司計畫 112M（v0.5；與 v0.5 寫法代數相同）
A78: Demand | B78: Free 人數 | C78: D03 | D78: —（新頁） | E78: 600、950、1250、1500、1700、1850 | F78: =V9_Free2026 | G78: 2025、2027+ Inputs；2026＝SRC WAU × 換算係數（Derived_V9 V01）
A79: Demand | B79: Go 人數 | C79: D04 | D79: —（新頁） | E79: 2、40.6、77.45、117、147.5、177.7 | F79: =INP_065*(1+E9)+INP_073*E8 | G79: 2026 起＝無遷移 Go ×（1＋λ）＋無遷移 Plus × μ
A80: Demand | B80: Plus 人數 | C80: D05 | D80: —（新頁） | E80: 30、34.9、39.45、43.25、46.28、48.56 | F80: =INP_073*(1-E8) | G80: 2025＝Derived_V9 V02（SRC 35M × 換算係數）；2026 起＝無遷移 Plus ×（1 − μ）
A81: Demand | B81: Pro 人數 | C81: D06 | D81: —（新頁） | E81: 0.2823、0.5645、0.8065、1.048、1.242、1.411 | F81: =V9_Pro2026 | G81: V12／V15：占比 × 付費總數（Derived_V9 V03、V04、V10–V13；付費總數口徑＝無遷移基準，沿用 P1 已審公式）
A82: Demand | B82: 企業席位人數 | C82: D07 | D82: —（新頁） | E82: 3、14、26、38、48、56 | F82: =INP_089 | G82: Inputs
A83: Demand | B83: 付費人數合計（Go＋Plus＋Pro＋席位） | C83: D08 | D83: —（新頁） | E83: 35.28、90.06、143.7、199.3、243、283.7 | F83: =E11+E12+E13+E14
A84: Demand | B84: 消費端付費人數（Go＋Plus＋Pro） | C84: D09 | D84: —（新頁） | E84: 32.28、76.06、117.7、161.3、195、227.7 | F84: =E11+E12+E13
A85: Demand | B85: Free 每日任務數 | C85: D10 | D85: —（新頁） | E85: 1.7、1.7、1.87、2.057、2.263、2.489 | F85: =INP_103 | G85: 2027 起 ×（1＋每日任務數年增率）
A86: Demand | B86: Go 每日任務數 | C86: D11 | D86: —（新頁） | E86: 5.3、5.7、6.27、6.897、7.587、8.345 | F86: =INP_105 | G86: 2027 起 ×（1＋每日任務數年增率）
A87: Demand | B87: Plus 每日任務數 | C87: D12 | D87: —（新頁） | E87: 13.4、17.9、19.69、21.66、23.82、26.21 | F87: =INP_107 | G87: 2027 起 ×（1＋每日任務數年增率）
A88: Demand | B88: Pro 每日任務數 | C88: D13 | D88: —（新頁） | E88: 41、51.4、56.54、62.19、68.41、75.25 | F88: =INP_109 | G88: 2027 起 ×（1＋每日任務數年增率）
A89: Demand | B89: 企業席位 每日任務數 | C89: D14 | D89: —（新頁） | E89: 10.7、14.3、15.73、17.3、19.03、20.94 | F89: =INP_111 | G89: 2027 起 ×（1＋每日任務數年增率）
A90: Demand | B90: Free 每任務 token | C90: D15 | D90: —（新頁） | E90: 2、2.94、3.381、3.888、4.471、5.142 | F90: =INP_113 | G90: 2027 起 ×（1＋每任務 token 年增率；D11 情境軸）
A91: Demand | B91: Go 每任務 token | C91: D16 | D91: —（新頁） | E91: 3、4.39、5.048、5.806、6.677、7.678 | F91: =INP_115 | G91: 2027 起 ×（1＋每任務 token 年增率；D11 情境軸）
A92: Demand | B92: Plus 每任務 token | C92: D17 | D92: —（新頁） | E92: 4、6.15、7.072、8.133、9.353、10.76 | F92: =INP_117 | G92: 2027 起 ×（1＋每任務 token 年增率；D11 情境軸）
A93: Demand | B93: Pro 每任務 token | C93: D18 | D93: —（新頁） | E93: 10、15.6、17.94、20.63、23.73、27.28 | F93: =INP_119 | G93: 2027 起 ×（1＋每任務 token 年增率；D11 情境軸）
A94: Demand | B94: 企業席位 每任務 token | C94: D19 | D94: —（新頁） | E94: 4、5.94、6.831、7.856、9.034、10.39 | F94: =INP_121 | G94: 2027 起 ×（1＋每任務 token 年增率；D11 情境軸）
A95: Demand | B95: Free token | C95: D20 | D95: —（新頁） | E95: 744.6、1733、2885、4379、6278、8642 | F95: =E10*E18*E23*INP_251/INP_239 | G95: 人數（M）× 每日任務 × 每任務 token（K）× 每年天數 ÷ 1000（B→T）
A96: Demand | B96: Go token | C96: D21 | D96: —（新頁） | E96: 11.61、370.8、894.8、1710、2727、4156 | F96: =E11*E19*E24*INP_251/INP_239 | G96: 人數（M）× 每日任務 × 每任務 token（K）× 每年天數 ÷ 1000（B→T）
A97: Demand | B97: Plus token | C97: D22 | D97: —（新頁） | E97: 586.9、1402、2005、2781、3764、4996 | F97: =E12*E20*E25*INP_251/INP_239 | G97: 人數（M）× 每日任務 × 每任務 token（K）× 每年天數 ÷ 1000（B→T）
A98: Demand | B98: Pro token | C98: D23 | D98: —（新頁） | E98: 42.24、165.2、298.6、491、735.8、1058 | F98: =E13*E21*E26*INP_251/INP_239 | G98: 人數（M）× 每日任務 × 每任務 token（K）× 每年天數 ÷ 1000（B→T）
A99: Demand | B99: 企業席位 token | C99: D24 | D99: —（新頁） | E99: 46.87、434.1、1020、1885、3013、4446 | F99: =E14*E22*E27*INP_251/INP_239 | G99: 人數（M）× 每日任務 × 每任務 token（K）× 每年天數 ÷ 1000（B→T）
A100: Demand | B100: 訂閱＋Free token 合計 | C100: D25 | D100: —（新頁） | E100: 1432、4105、7103、1.125e+04、1.652e+04、2.33e+04 | F100: =E28+E29+E30+E31+E32 | G100: workbook 口徑（v0.5 未校正）
A101: Demand | B101: 價格反應底數 p/p前（組合有效單價） | C101: D26 | D101: —（新頁） | E101: 、1.418、0.6426、0.6464、0.6503、0.6541 | F101: =Revenue!E21/Revenue!D21 | G101: ＝Revenue 組合有效單價 ÷ 前一年；價格反應只在年度 ≥ 彈性起算年（Inputs 2027）生效：底數^(ε×(年度≥起算年))
A102: Demand | B102: API 每任務 token | C102: D27 | D102: —（新頁） | E102: 10、12、15.76、20.12、25.18、30.89 | F102: =D36*(1+INP_041)*E35^(INP_049*(E$6>=INP_004)) | G102: 層級正規化（只影響任務數與每任務 token 的水準拆分，不影響營收）
A103: Demand | B103: API 任務數 | C103: D28 | D103: —（新頁） | E103: 210.6、492.8、973.8、1784、3014、4869 | F103: =D37*(1+INP_033)*E35^(INP_048*(E$6>=INP_004)) | G103: 2025＝計費 token ÷ 每任務 token；之後 ×（1＋成長）× 價格反應
A104: Demand | B104: API 計費 token | C104: D29 | D104: —（新頁） | E104: 2106、5913、1.534e+04、3.589e+04、7.59e+04、1.504e+05 | F104: =E37*E36 | G104: 2025：（FY2025 實際營收 − 訂閱 − 廣告 − 其他）÷ 組合有效單價（v0.5 校準，唯一倒推）；之後＝任務數 × 每任務 token
A105: Demand | B105: API token：頂層（Astra） | C105: D30 | D105: —（新頁） | E105: 842.3、887、2302、5384、1.138e+04、2.256e+04 | F105: =E38*Revenue!E18 | G105: 計費 token × 層級占比（Revenue）
A106: Demand | B106: API token：中層（Sol） | C106: D31 | D106: —（新頁） | E106: 842.3、2661、6905、1.615e+04、3.415e+04、6.767e+04 | F106: =E38*Revenue!E19 | G106: 計費 token × 層級占比（Revenue）
A107: Demand | B107: API token：低層（Luna） | C107: D32 | D107: —（新頁） | E107: 421.2、2365、6138、1.436e+04、3.036e+04、6.015e+04 | F107: =E38*Revenue!E20 | G107: 計費 token × 層級占比（Revenue）
A108: Demand | B108: 免費 token：頂層（Astra） | C108: D33 | D108: —（新頁） | E108: 0、0、0、0、0、0 | F108: =E28*INP_157 | G108: Free token × 方案模型組合（Inputs astra 占比；v0.5 inferenceCost.usage）
A109: Demand | B109: 免費 token：中層（Sol） | C109: D34 | D109: —（新頁） | E109: 74.46、173.3、288.5、437.9、627.8、864.2 | F109: =E28*INP_156 | G109: Free token × 方案模型組合（Inputs sol 占比；v0.5 inferenceCost.usage）
A110: Demand | B110: 免費 token：低層（Luna） | C110: D35 | D110: —（新頁） | E110: 670.1、1560、2596、3941、5650、7778 | F110: =E28*INP_155 | G110: Free token × 方案模型組合（Inputs luna 占比；v0.5 inferenceCost.usage）
A111: Demand | B111: 付費 token：頂層（Astra） | C111: D36 | D111: —（新頁） | E111: 890.9、1045、2572、5813、1.202e+04、2.345e+04 | F111: =E29*INP_162+E30*INP_167+E31*INP_172+E32*INP_177+E39 | G111: Σ 付費方案 token × 方案模型組合 ＋ API 該層級 token
A112: Demand | B112: 付費 token：中層（Sol） | C112: D37 | D112: —（新頁） | E112: 1248、3923、9054、1.955e+04、3.915e+04、7.471e+04 | F112: =E29*INP_161+E30*INP_166+E31*INP_171+E32*INP_176+E40 | G112: Σ 付費方案 token × 方案模型組合 ＋ API 該層級 token
A113: Demand | B113: 付費 token：低層（Luna） | C113: D38 | D113: —（新頁） | E113: 654.7、3318、7936、1.74e+04、3.497e+04、6.687e+04 | F113: =E29*INP_160+E30*INP_165+E31*INP_170+E32*INP_175+E41 | G113: Σ 付費方案 token × 方案模型組合 ＋ API 該層級 token
A114: Demand | B114: 免費 token 合計 | C114: D39 | D114: —（新頁） | E114: 744.6、1733、2885、4379、6278、8642 | F114: =E43+E44+E45
A115: Demand | B115: 付費 token 合計 | C115: D40 | D115: —（新頁） | E115: 2793、8286、1.956e+04、4.276e+04、8.613e+04、1.65e+05 | F115: =E46+E47+E48
A116: Demand | B116: token 合計（付費＋免費） | C116: D41 | D116: —（新頁） | E116: 3538、1.002e+04、2.245e+04、4.714e+04、9.241e+04、1.737e+05 | F116: =E49+E50
A117: Demand | B117: 對照：訂閱＋免費＋API 計費 token（應＝合計） | C117: D42 | D117: —（新頁） | E117: 3538、1.002e+04、2.245e+04、4.714e+04、9.241e+04、1.737e+05 | F117: =E33+E38 | G117: 層級拆分前的總量；與上一列之差應為 0（Checks）
A118: Demand | B118: Tokenomics IF_AllocDemand（需求 D 合計，2025） | C118: D43 | D118: —（新頁） | E118: 4.19e+09、、、、、 | F118: =TK_IF_AllocDemand | G118: TK 快照；口徑：API＋ChatGPT；付費＋免費 token
A119: Demand | B119: 本模型 2025 token 合計 | C119: D44 | D119: —（新頁） | E119: 3.538e+09、、、、、 | F119: =D51*INP_254 | G119: T × 10^6（Inputs 定義常數）
A120: Demand | B120: 差距：本模型 − Tokenomics | C120: D45 | D120: —（新頁） | E120: -6.521e+08、、、、、 | F120: =D55-D54
A121: Demand | B121: 比值：本模型 ÷ Tokenomics | C121: D46 | D121: —（新頁） | E121: 0.8444、、、、、 | F121: =D55/D54
A122: Demand | B122: API 處理 token（揭露推估，FY2025） | C122: D47 | D122: —（新頁） | E122: 2628、、、、、 | F122: =V9_ApiTok | G122: Derived_V9 V22：Inputs 每分鐘 5B × 525,600 ÷ 1000
...

Sheet ②關鍵輸出FY2025-2030
A1: ② 本段關鍵輸出（FY2025–FY2030；$B、T token；容量上限 V1a 於 P3 加入，本表未截頂）
A3: 區塊 | B3: 項目 | C3: 單位 | D3: 2025 | E3: 2026 | F3: 2027 | G3: 2028 | H3: 2029 | I3: 2030 | J3: 具名範圍
A4: 訂閱營收 | B4: Go | C4: $B | D4: 0.144 | E4: 2.9232 | F4: 5.5762435 | G4: 8.424313 | H4: 10.617809 | I4: 12.79393 | J4: REV_Sub_Go
A5: 訂閱營收 | B5: Plus | C5: $B | D5: 7.02 | E5: 7.9572 | F5: 8.9950957 | G5: 9.8600087 | H5: 10.551939 | I5: 11.070887 | J5: REV_Sub_Plus
A6: 訂閱營收 | B6: Pro | C6: $B | D6: 0.67741935 | E6: 1.016129 | F6: 1.4516129 | G6: 1.8870968 | H6: 2.2354839 | I6: 2.5403226 | J6: REV_Sub_Pro
A7: 訂閱營收 | B7: 企業席位 | C7: $B | D7: 1.08 | E7: 5.04 | F7: 9.36 | G7: 13.68 | H7: 17.28 | I7: 20.16 | J7: REV_Sub_Seats
A8: 訂閱營收 | B8: 訂閱合計 | C8: $B | D8: 8.9214194 | E8: 16.936529 | F8: 25.382952 | G8: 33.851419 | H8: 40.685232 | I8: 46.56514 | J8: REV_Sub
A9: API 營收 | B9: 頂層（Astra） | C9: $B | D9: 2.5674245 | E9: 7.03913 | F9: 12.786246 | G9: 20.935771 | H9: 30.989059 | I9: 42.980351 | J9: REV_API_Top
A10: API 營收 | B10: 中層（Sol） | C10: $B | D10: 1.4865455 | E10: 7.5756266 | F10: 11.794943 | G10: 16.553695 | H10: 21.002336 | I10: 24.967921 | J10: REV_API_Mid
A11: API 營收 | B11: 低層（Luna） | C11: $B | D11: 0.094610604 | E11: 1.9095458 | F11: 2.9730852 | G11: 4.1725972 | H11: 5.2939412 | I11: 6.2935239 | J11: REV_API_Low
A12: API 營收 | B12: API 合計 | C12: $B | D12: 4.1485806 | E12: 16.524302 | F12: 27.554274 | G12: 41.662063 | H12: 57.285336 | I12: 74.241796 | J12: REV_API
A13: 其他 | B13: 廣告 | C13: $B | D13: 0 | E13: 0.74295 | F13: 1.858427 | G13: 2.9106078 | H13: 4.1568065 | I13: 5.5761571 | J13: REV_Ads
A14: 其他 | B14: 其他營收 | C14: $B | D14: 0 | E14: 0 | F14: 0 | G14: 0 | H14: 0 | I14: 0 | J14: REV_Other
... A40: 單價 | B40: API 組合有效單價（扣折扣） | C40: $/M | D40: 1.970048 | E40: 2.7944948 | F40: 1.7957386 | G40: 1.1607723 | H40: 0.75479384 | I40: 0.49370761 | J40: REV_ApiPrice
A42: 2025 對 SRC 實際與 Tokenomics 的差距
B43: 2025 模型總額 − SRC 實際 13.07（v0.5 校準方式，恆為 0） | C43: $B | D43: 0
B44: 2025 未校準差距（API 改用處理 token 2,628T × 單價） | C44: $B | D44: 1.0287055
B45: 2025 API 計費比例（計費 ÷ 處理 token） | C45: 比例 | D45: 0.80130411
B46: 2025 token 合計 − TK IF_AllocDemand | C46: M tok/年 | D46: -6.5213989e+08
B47: 2025 token 合計 ÷ TK IF_AllocDemand | C47: 倍 | D47: 0.84436545
B48: FY2026 獨立推估（Q1＋Q2＋ARR×6/12） | C48: $B | D48: 32.4
B49: 2026 模型總額 − 獨立推估 | C49: $B | D49: 1.8037814
B50: 2026 模型總額 − 管理層目標 36 | C50: $B | D50: -1.7962186
B51: 2030 模型總額 − 管理層目標 350 | C51: $B | D51: -223.61691
A53: 2026 API 牌價（事件時點天數加權；區間＝事件時點 ±1 季）
A54: 層級 | B54: 輸入／輸出 | C54: 單位 | D54: 基準 | E54: 低 | F54: 高 | G54: v0.5 基準 | H54: v0.5 低 | I54: v0.5 高
A55: Top | B55: In | C55: $/M | D55: 6.6109589 | E55: 5.3643836 | F55: 7.8575342 | G55: 6.6 | H55: 5 | I55: 7.5
A56: Top | B56: Out | C56: $/M | D56: 36.246575 | E56: 31.260274 | F56: 41.232877 | G56: 35.8 | H56: 28 | I56: 40
A57: Mid | B57: In | C57: $/M | D57: 2.2876712 | E57: 2.1630137 | F57: 2.4123288 | G57: 2.29 | H57: 2 | I57: 2.5
A58: Mid | B58: Out | C58: $/M | D58: 13.172603 | E58: 11.926027 | F58: 14.419178 | G58: 13.25 | H58: 11 | I58: 15
A59: Low | B59: In | C59: $/M | D59: 0.63260274 | E59: 0.40821918 | F59: 0.8569863 | G59: 0.64 | H59: 0.4 | I59: 0.8
A60: Low | B60: Out | C60: $/M | D60: 3.7679452 | E60: 2.3967123 | F60: 5.1391781 | G60: 3.83 | H60: 2.5 | I60: 5
A62: 事件時點敏感度（$B）
A63: 情境 | B63: 項目 | D63: 2025 | E63: 2026 | F63: 2027 | G63: 2028 | H63: 2029 | I63: 2030
A64: 基準（公告日） | B64: 總額 | D64: 13.07 | E64: 34.203781 | F64: 54.795653 | G64: 78.424089 | H64: 102.12737 | I64: 126.38309
A65: 基準（公告日） | B65: 淨額 | D65: 10.456 | E65: 27.363025 | F65: 43.836523 | G65: 62.739271 | H65: 97.612079 | I65: 126.38309
A66: 全部提前一季 | B66: 總額 | D66: 13.07 | E66: 33.940376 | F66: 54.356425 | G66: 77.759975 | H66: 101.21422 | I66: 125.19964
A67: 全部提前一季 | B67: 淨額 | D67: 10.456 | E67: 27.152301 | F67: 43.48514 | G67: 62.20798 | H67: 96.425573 | I67: 125.19964
A68: 全部延後一季 | B68: 總額 | D68: 13.07 | E68: 34.467187 | F68: 55.234882 | G68: 79.088203 | H68: 103.04053 | I68: 127.56654
A69: 全部延後一季 | B69: 淨額 | D69: 10.456 | E69: 27.57375 | F69: 44.187906 | G69: 63.270562 | H69: 98.798585 | I69: 127.56654
A70: 年中一次性生效（替代） | B70: 總額 | D70: 13.07 | E70: 34.411951 | F70: 55.142776 | G70: 78.948939 | H70: 102.84904 | I70: 127.31838
A71: 年中一次性生效（替代） | B71: 淨額 | D71: 10.456 | E71: 27.529561 | F71: 44.114221 | G71: 63.159151 | H71: 98.549777 | I71: 127.31838

Sheet ③已套用的預設
A1: ③ 已套用的預設（工作單 S2 預設表 → r6 → 最保守常見口徑）
A3: # | B3: 問題 | C3: 採用的預設 | D3: 替代選項 | E3: 對結果的影響方向（量化）
A4: 1 | B4: 2026 價格事件時點（E8c） | C4: SRC_OAI 公告日為基準（Verified；公告日＝生效日）；區間＝基準 ±1 季（±91 天，Assumed；Inputs INP_246–249）；FY 平均價以天數加權（工作單預設） | D4: 年中一次性生效 | E4: 年中一次性：2026 組合有效單價 2.794→2.830 $/M（+1.3%）、2026 總額 +0.21B、2030 淨額 +0.94B；全部提前一季：2026 總額 −0.26B、2030 淨額 −1.18B；全部延後一季：+0.26B／+1.18B
A5: 2 | B5: 事件 1（07-09）之前的 2026 價格 | C5: 以事件 1 價格（GPT-5.6 Sol／Terra／Luna）回填 1/1 起（與 v0.5 月加權相同作法） | D5: 以 2025 FY 平均價銜接至首次變價 | E5: 未量化；資料缺口（2026 上半年牌價未登錄）
A6: 3 | B6: 事件 4、5 之後的價格 | C6: 引用既有 2026-09-25 牌價快照列（SRC_OAI_013–021），不另登事件價 | D6: 另登事件價列 | E6: 無（數值相同）
A7: 4 | B7: 天數加權 vs v0.5 月加權 | C7: 天數加權（工作單預設） | D7: v0.5 月加權 | E7: 2026 牌價：top 輸入 6.611（v0.5 6.6）、top 輸出 36.25（35.8）、mid 13.17（13.25）、low 輸出 3.768（3.83）；2026 組合單價 2.794（v0.5 2.794）
A8: 5 | B8: 2027 起 API 單價路徑 | C8: 沿用 v0.5：2026 值 ×（1＋牌價年變動率，Inputs INP_021–023）；不以 Tokenomics 前緣價改寫（工作單預設） | D8: 以 TK IF_FrontRef_* 年降幅外推 | E8: 列入建議後續
A9: 6 | B9: Pro 的「付費總數」口徑 | C9: 無遷移基準（go＋plus＋seats 取 Inputs 值；沿用 P1 已審 Derived_V9 V03–V13，與 r6 參考值 0.81／1.05／1.24／1.41M 一致） | D9: T4 遷移後的 Go、Plus | E9: 改用遷移後：pro 2026 0.565→0.722M，訂閱營收 +0.28B（2026）、+1.56B（2030）；2025 由 API 倒推吸收，總額不變
A10: 7 | B10: API token 需求口徑（供 P3） | C10: 計費 token（v0.5：2025 由營收倒推，之後任務數 × 每任務 token） | D10: 處理 token（＝計費 ÷ 2025 計費比例 0.80） | E10: 改用處理 token：2025 API +522T（+25%），P3 推論 GW 同比例上升；2025 計費比例 0.80（v0.5 0.70，差異來自 V12 pro 下修使 API 倒推值上升）
A11: 8 | B11: 訂閱 token 的層級拆分 | C11: 方案模型組合 INP_155–179（v0.5 inferenceCost.usage：luna／sol／astra 占比） | D11: apiEquivalentTier 單一對應（free、go→low；plus、seats→mid；pro→top） | E11: 改用單一對應：2025 付費 mid +228T、low −222T，免費 mid 74→0T；2030 付費 mid +3.2%、low −3.8%、top +0.7%
A12: 9 | B12: API 層級占比 2027–2030 | C12: 沿用 2026 值（v0.5 以最後一值延伸） | D12: 逐年 Inputs | E12: 無（與 v0.5 相同）
A13: 10 | B13: D11 情境選擇器 | C13: 未建；基準引用各參數 Inputs 值欄；情境 low／base／high 列只作對照（C36 檢查 base 列＝基準值） | D13: 建選擇器（v0.5 輸入!C5） | E13: 無（基準相同）；情境由 parity 情境與 S5 敏感度處理
A14: 11 | B14: ARPU plus、pro 的「2026 起」 | C14: 2026–2030 同值（v0.5 以最後一值延伸）；INP_098、INP_100 索引「待 P2 確認」→確認為 2026 起全期 | D14: 逐年 ARPU | E14: 無（與 v0.5 相同）
A15: 12 | B15: FY2026 獨立推估（v0.5 Derived 32.9） | C15: Q1＋Q2＋2026-08 ARR × 6 ÷ 12＝32.4（最簡口徑） | D15: 沿用 v0.5 32.9（外推細節未記錄） | E15: −0.5B（只對照，不驅動計算）
... A22: 19 | B22: 同日檔名 | C22: S1 版（同為 20261007_OpenAI_v0.6.xlsx）以 git mv 改名為 model/archive/20261007_OpenAI_v0.6-P1.1.xlsx | D22: — | E22: 工程類
