Workbook

Sheet README
A1: 智邦科技（2345）收支與估值模型 v0.2.1（AI 半導體 Project：網通系統端，白牌交換器 ODM） 2026-10-25
A2: 版本：v0.2.1（2026-10-25：補上檔空間級距、投資建議、重點觀察，數值不變）；v0.1（初版）。智邦在白牌 AI 乙太網路交換器的份額在本模型 Units 頁建立，為本專案權威資料（規則第 13 條）。
A3: 模型命題：智邦的 AI 交換器營收＝AI 資料中心乙太網路交換器市場（scale-out × 乙太網路占比＋非 NVIDIA scale-up 交換匣；本專案網通模型）× 白牌占比 × 智邦在白牌中的份額；另一半營收是 AWS Trainium 加速卡等網路應用產品（Trainium 顆數 × 每顆營收）；非 AI 另依成長率推。股價約 12 倍模型 FY2027 EPS（共識 FY2027 約 15 倍）：800G → 1.6T 換代與 Trainium 第二供應商之下，份額撐得住嗎？
A4: 核心問題：2027–28 年智邦在白牌交換器與 Trainium 加速卡的份額各掉一截，EPS 少多少；現價隱含的路徑合不合理。
A6: 會計年度＝日曆年，FY(t)＝CY(t)，不平移。預測期 FY2027–FY2029（三年）。金額：十億新台幣；市場以美元、匯率 32.0 換算。口徑：稅後淨利（公司公告）。
A8: 驅動因子 → 推導量（全部唯讀上游，不修改）
A9: AI 交換器：markets/network 的 scale-out 交換器市場 × 乙太網路占比（Assumed）＋非 NVIDIA scale-up 交換匣（Derived）→ × 情境顆數係數 × 白牌占比（Assumed）× 智邦白牌有效份額（FY2026 校準）× 份額相對值（Assumed）。800G → 1.6T 的單價上升含在網通模型每顆內容；換代的份額風險放在相對值與 Sens。
A10: 網路應用產品：Trainium 顆數（網通模型）× 每顆智邦營收（FY2026 校準）× 相對值（Assumed）。非 AI：FY2025 依公司揭露比例推得，FY2026 起依成長率（Assumed）。毛利率：網路應用產品比交換器與其他低 d_nap（Assumed）。
A11: 校準：FY2026 ＝ 1Q–2Q 實績＋3Q 營收實績（月營收）＋毛利率、費用與 4Q 假設；FY2026 網路應用產品占比 50%（Assumed）。不用共識（只在 Recon 對帳）。主要客戶 Amazon（Trainium、800G 交換器）與 2026 年新增的另一家美系超大規模業者（法人稱可能為 Meta 等）皆為 Interested-party 說法；客戶占比未找到。
A12: 估值：現價 ÷ FY2027、FY2028 EPS；十年 P/E 規則值（兩個資料商來源）× FY2027 EPS；目標價＝三情境規則值隱含價加權（0.3／0.5／0.2）。循環位置以本模型營收最高年判定。本版未做先驗，無 Andy 合理 P/E 對照。
A13: 標記：Verified、Interested-party、Analogy、Assumed、Derived。SemiAnalysis 未使用。公司原文只經媒體轉述（季報、月營收、法說摘要）。
A15: 已知限制：(1) FY2026 產品別拆分（網路應用產品 50%）與交換器的 AI 比例為 Assumed，決定 AI 交換器與 Trainium 兩條線的起點；(2) 白牌占比與份額相對值皆為 Assumed；(3) 網通模型 Trainium 顆數為 Assumed（年出貨未找到）；(4) 記憶體與 PCB 改客供（代購）會壓低營收、墊高毛利率，本版未拆；(5) 3Q26 財報未出，3Q 毛利率與費用為假設；(6) 十年 P/E 兩來源 2016–2017 年只有一個；(7) R4 產業部署路徑未建（Recon 預留列）。
... A18: v0.2.1（2026-10-25）：補上檔空間級距、投資建議、重點觀察（Val 頁 0.3 結論加「上檔空間級距」「投資建議」兩列、README 頁加重點觀察三點；數值不變，既有儲存格位置不變）。
A19: ="投資建議："&Val!B52&"（依上檔空間固定規則）" -> 投資建議：買進（依上檔空間固定規則）
A20: 重點觀察 1：目標價 NT$2,275（DCF 2,584、Comparable 1,966 各半），比現價 1,775（2026-10-22）高 28.2%，級距 25%–50%；Comparable 單獨為 +10.8%。主因是 DCF 不是 EPS：本模型 12 個月後前瞻 EPS 138.6 比共識前瞻 EPS 162.3 低 14.6%，在同業前瞻 P/E 中位數 14.2 倍下 Comparable 只高一成；DCF 單獨 +45.6%，因 ROE 44.8% 遠高於折現率 10%（可發放比例 91%），而現價只有 FY2027 EPS 的 12.0 倍。共識目標價 3,500 隱含 21.6 倍，比同業高 52.0%。
A21: 重點觀察 2：FY2028 EPS 三情境分歧大：A 169.2（與 FactSet 中位數 170.57 相近）、B 133.8（−20.9%）、C 95.7（−43.4%），差距來自 CY2028 起的顆數情境；單一變數中白牌份額流失（相對值 0.80／0.70）FY2028 EPS −18.2%、AI 交換器市場 ×0.8 −13.8%、Trainium 份額流失 −10.4%。
A22: 重點觀察 3：追蹤 3Q26 財報與法說（去年在 11-07，約 2026-11 上旬）與 10 月營收（11-10 前）：本版 3Q 毛利率與費用為假設，FY2026 網路應用產品占比 50% 為 Assumed（42%／58% 時 FY2028 EPS +6.3%／−6.7%）。網通 CPO 目前只有一條路徑、三情境相同，1.6T 換代的 CPO 份額風險待 markets/network 改版。

Sheet In
A1: In — 輸入（藍字；基準欄 E，低 D、高 F）。金額：十億新台幣（NT$B），市場為美元；比例：%。每個輸入附兩個來源（找不到者寫「未找到」）；公司原文算一個
A2: 標記：Verified／Interested-party／Analogy／Assumed／Derived；Analogy、Assumed 給低／高區間。SemiAnalysis 未使用。公司原文＝智邦季報與月營收公告（經經濟日報、工商時報、富果摘要轉述）；法人估計與券商目標價皆為 Interested-party
A3: 鍵 | B3: 項目 | C3: 單位 | D3: 低 | E3: 基準 | F3: 高 | G3: 標記 | H3: 來源1 | I3: 來源2／說明
A4: A. AI 交換器市場（讀 markets/network 成品；情境 A 基準，B／C 依顆數係數縮放）
A5: mkt_26 | B5: AI 後端 scale-out 交換器市場 2026 | C5: US$B | E5: 32.0719 | G5: Derived | H5: markets/network/dist/20261026_AI網通市場模型_v0.2.3.xlsx｜Mkt!C7:F7 | I5: 加速器顆數 × 每顆 scale-out 交換器內容（不分乙太網路與 InfiniBand）；800G → 1.6T 的單價上升已含在每顆內容（VR200 約為 GB300 的 2 倍）
A6: mkt_27 | B6: AI 後端 scale-out 交換器市場 2027 | C6: US$B | E6: 61.085 | G6: Derived | H6: markets/network/dist/20261026_AI網通市場模型_v0.2.3.xlsx｜Mkt!C7:F7 | I6: 同上
A7: mkt_28 | B7: AI 後端 scale-out 交換器市場 2028 | C7: US$B | E7: 69.005 | G7: Derived | H7: markets/network/dist/20261026_AI網通市場模型_v0.2.3.xlsx｜Mkt!C7:F7 | I7: 同上
A8: mkt_29 | B8: AI 後端 scale-out 交換器市場 2029 | C8: US$B | E8: 78.48215 | G8: Derived | H8: markets/network/dist/20261026_AI網通市場模型_v0.2.3.xlsx｜Mkt!C7:F7 | I8: 同上
A9: su_26 | B9: 非 NVIDIA scale-up 乙太網路交換匣市場 2026 | C9: US$B | E9: =(2*(600+800*(1-0.6))+1*(600+800*(1-0.6))+0.75*(300+100*(1-0.6)))/1000 -> 3.015 | G9: Derived | H9: markets/network/dist/20261026_AI網通市場模型_v0.2.3.xlsx｜Units!B10:E10（Trainium）、Units!B11:E11（其他 ASIC）、Units!B8:E8（AMD）× In 頁 c_TRN／c_ASIC／c_AMD8（2026）／c_AMDR（2027 起）_su_sw、_su_ic 與 su_cu | I9: Trainium、其他 ASIC、AMD 的 scale-up 交換晶片＋交換匣其他（扣銅纜）；TPU（ICI／OCS）與 NVLink 不計
A10: su_27 | B10: 非 NVIDIA scale-up 乙太網路交換匣市場 2027 | C10: US$B | E10: =(2.5*(600+800*(1-0.6))+4.5*(600+800*(1-0.6))+1.5*(2334+2334*(1-0.6)))/1000 -> 11.3414 | G10: Derived | H10: 同上 | I10: 同上
A11: su_28 | B11: 非 NVIDIA scale-up 乙太網路交換匣市場 2028 | C11: US$B | E11: =(3*(600+800*(1-0.6))+5*(600+800*(1-0.6))+2*(2334+2334*(1-0.6)))/1000 -> 13.8952 | G11: Derived | H11: 同上 | I11: 同上
A12: su_29 | B12: 非 NVIDIA scale-up 乙太網路交換匣市場 2029 | C12: US$B | E12: =(3.45*(600+800*(1-0.6))+5.75*(600+800*(1-0.6))+2.3*(2334+2334*(1-0.6)))/1000 -> 15.97948 | G12: Derived | H12: 同上 | I12: 同上
A13: trn_26 | B13: AWS Trainium 顆數 2026 | C13: 百萬顆 | E13: 2 | G13: Derived | H13: markets/network/dist/20261026_AI網通市場模型_v0.2.3.xlsx｜Units!B10:E10 | I13: 網通模型沿用記憶體模型顆數（Assumed：年出貨未找到）
A14: trn_27 | B14: AWS Trainium 顆數 2027 | C14: 百萬顆 | E14: 2.5 | G14: Derived | H14: markets/network/dist/20261026_AI網通市場模型_v0.2.3.xlsx｜Units!B10:E10 | I14: 同上
A15: trn_28 | B15: AWS Trainium 顆數 2028 | C15: 百萬顆 | E15: 3 | G15: Derived | H15: markets/network/dist/20261026_AI網通市場模型_v0.2.3.xlsx｜Units!B10:E10 | I15: 同上
A16: trn_29 | B16: AWS Trainium 顆數 2029 | C16: 百萬顆 | E16: 3.45 | G16: Derived | H16: markets/network/dist/20261026_AI網通市場模型_v0.2.3.xlsx｜Units!B10:E10 | I16: 同上
A17: itc_26 | B17: AI IT 資本支出 2026 | C17: US$B | E17: 781.87292 | G17: Derived | H17: markets/network/dist/20261026_AI網通市場模型_v0.2.3.xlsx｜Mkt!C27:F27 | I17: Recon 用：智邦 AI 營收 ÷ AI IT 資本支出
A18: itc_27 | B18: AI IT 資本支出 2027 | C18: US$B | E18: 1565.35 | G18: Derived | H18: markets/network/dist/20261026_AI網通市場模型_v0.2.3.xlsx｜Mkt!C27:F27 | I18: 同上
A19: itc_28 | B19: AI IT 資本支出 2028 | C19: US$B | E19: 1984.2639 | G19: Derived | H19: markets/network/dist/20261026_AI網通市場模型_v0.2.3.xlsx｜Mkt!C27:F27 | I19: 同上
A20: itc_29 | B20: AI IT 資本支出 2029 | C20: US$B | E20: 2260.3903 | G20: Derived | H20: markets/network/dist/20261026_AI網通市場模型_v0.2.3.xlsx｜Mkt!C27:F27 | I20: 同上
A21: um28_A | B21: 情境 A：2028 顆數 ÷ 基準 | C21: x | E21: 1 | G21: Assumed | H21: tsmc/dist/20261028_台積電個股模型_v0.4.xlsx｜In!E37 | I21: A＝基準；B＝AI 資本支出消化；C＝明顯下修（與台積電、Arista、廣達模型相同）
A22: um29_A | B22: 情境 A：2029 顆數 ÷ 基準 | C22: x | E22: 1 | G22: Assumed | H22: tsmc/dist/20261028_台積電個股模型_v0.4.xlsx｜In!E38 | I22: 同上
A23: um28_B | B23: 情境 B：2028 顆數 ÷ 基準 | C23: x | E23: 0.8 | G23: Assumed | H23: tsmc/dist/20261028_台積電個股模型_v0.4.xlsx｜In!E39 | I23: A＝基準；B＝AI 資本支出消化；C＝明顯下修（與台積電、Arista、廣達模型相同）
A24: um29_B | B24: 情境 B：2029 顆數 ÷ 基準 | C24: x | E24: 0.85 | G24: Assumed | H24: tsmc/dist/20261028_台積電個股模型_v0.4.xlsx｜In!E40 | I24: 同上
... A26: um29_C | B26: 情境 C：2029 顆數 ÷ 基準 | C26: x | E26: 0.6 | G26: Assumed | H26: tsmc/dist/20261028_台積電個股模型_v0.4.xlsx｜In!E42 | I26: 同上
A27: fx | B27: 匯率（新台幣 ÷ 美元） | C27: NT$/US$ | D27: 29 | E27: 32 | F27: 33 | G27: Assumed | H27: 與 quanta/ 模型相同 32.0 | I27: 份額在 FY2026 以同一匯率校準，匯率只在 FY2027 起變動時才影響結果
A28: B. 乙太網路占比、白牌占比與智邦份額（本專案為權威：白牌交換器廠份額，規則第 13 條）
A29: eth_26 | B29: 乙太網路 ÷ AI 後端交換器（金額）2026 | C29: % | D29: 0.7 | E29: 0.75 | F29: 0.8 | G29: Assumed | H29: 與 arista/ 模型同值；Dell'Oro 2026-03-10：2025 年乙太網路占 AI 叢集交換器三分之二以上（Interested-party） | I29: IDC 2Q26：800GbE 占資料中心交換器營收 41.2%（Interested-party）
A30: eth_27 | B30: 乙太網路 ÷ AI 後端交換器 2027 | C30: % | D30: 0.72 | E30: 0.8 | F30: 0.88 | G30: Assumed | H30: 同上；2027 年無公開預測：未找到 | I30: 外推（Assumed）
A31: eth_28 | B31: 乙太網路 ÷ AI 後端交換器 2028 | C31: % | D31: 0.74 | E31: 0.83 | F31: 0.9 | G31: Assumed | H31: 同上 | I31: —
A32: eth_29 | B32: 乙太網路 ÷ AI 後端交換器 2029 | C32: % | D32: 0.75 | E32: 0.85 | F32: 0.92 | G32: Assumed | H32: 同上 | I32: —
A33: wb_26 | B33: 白牌（ODM 直供）÷ AI 乙太網路交換器 2026 | C33: % | D33: 0.35 | E33: 0.45 | F33: 0.55 | G33: Assumed | H33: Dell'Oro 2025 AI 後端乙太網路：Celestica（白牌）與 NVIDIA 並列第一、合計約 50%，Arista 第三（Interested-party） | I33: IEEE ComSoc 2026-01：ODM 占資料中心乙太網路交換器約 20–25%（金額）、超大規模資料中心 30–40%（數量；來源未具名）
A34: wb_27 | B34: 白牌 ÷ AI 乙太網路交換器 2027 | C34: % | D34: 0.35 | E34: 0.47 | F34: 0.57 | G34: Assumed | H34: 超大規模業者自研網路作業系統、擴大白牌（方向）；NVIDIA Spectrum-X 搶占（反方向） | I34: 量化預測：未找到
A35: wb_28 | B35: 白牌 ÷ AI 乙太網路交換器 2028 | C35: % | D35: 0.35 | E35: 0.48 | F35: 0.58 | G35: Assumed | H35: 同上 | I35: —
A36: wb_29 | B36: 白牌 ÷ AI 乙太網路交換器 2029 | C36: % | D36: 0.35 | E36: 0.5 | F36: 0.6 | G36: Assumed | H36: 同上 | I36: —
A37: rel_27 | B37: 智邦白牌份額 2027 ÷ 2026（相對值） | C37: x | D37: 0.8 | E37: 1 | F37: 1.1 | G37: Assumed | H37: 2026 年新增一家超大規模客戶（800G；法人稱約貢獻營收 15%，Interested-party） | I37: 經濟日報 2026-07-09：更多組裝廠加入可能稀釋份額（法人，Interested-party）
A38: rel_28 | B38: 智邦白牌份額 2028 ÷ 2026 | C38: x | D38: 0.7 | E38: 0.95 | F38: 1.1 | G38: Assumed | H38: 1.6T 世代每代重新競標（Celestica、天弘以外的 ODM 加入） | I38: —
A39: rel_29 | B39: 智邦白牌份額 2029 ÷ 2026 | C39: x | D39: 0.65 | E39: 0.92 | F39: 1.1 | G39: Assumed | H39: 同上 | I39: —
A40: C. AI 加速卡等網路應用產品（AWS Trainium 加速卡模組、L10 等）
A41: nrel_27 | B41: 每顆 Trainium 的智邦營收 2027 ÷ 2026（份額 × 單價，相對值） | C41: x | D41: 0.65 | E41: 0.9 | F41: 1.1 | G41: Assumed | H41: 鏡週刊 2026-08-06：智邦自 2Q26 大量出貨 Trainium 3 OAM 模組（Interested-party） | I41: 經濟日報 2026-07-09：更多組裝廠可能稀釋份額；Trainium 4 預計 2H27（法人引述亞馬遜股東信，Interested-party）
A42: nrel_28 | B42: 每顆 Trainium 的智邦營收 2028 ÷ 2026 | C42: x | D42: 0.55 | E42: 0.85 | F42: 1.1 | G42: Assumed | H42: 同上 | I42: —
A43: nrel_29 | B43: 每顆 Trainium 的智邦營收 2029 ÷ 2026 | C43: x | D43: 0.5 | E43: 0.8 | F43: 1.1 | G43: Assumed | H43: 同上 | I43: —
A44: tf | B44: Trainium 顆數係數（Sens 用；FY2027 起） | C44: x | D44: 0.8 | E44: 1 | F44: 1.2 | G44: Assumed | H44: 網通模型 Trainium 顆數為 Assumed（年出貨未找到） | I44: ±20%
A45: D. 營收結構（FY2025 依公司揭露；FY2026 為 Assumed，用於校準）
A46: sw25s | B46: FY2025 網路交換器 ÷ 營收 | C46: % | D46: 0.31 | E46: 0.34 | F46: 0.36 | G46: Interested-party | H46: https://blog.fugle.tw/post/earnings-call-2345-2025-11-7：2025 年前三季網路交換器 34%、網路應用產品 63%、接取 2%（公司法說） | I46: brodoginvestment 2026-07-11：2025 年資料中心交換器約 31%（作者估計）
A47: nap25s | B47: FY2025 網路應用產品（AI 加速卡等）÷ 營收 | C47: % | D47: 0.6 | E47: 0.63 | F47: 0.65 | G47: Interested-party | H47: 同上：63%（前三季年增 361%） | I47: brodoginvestment：AI 加速卡與 scale-up 交換器約 63%（作者估計）
A48: af25 | B48: FY2025 交換器中 AI 資料中心的比例 | C48: % | D48: 0.45 | E48: 0.6 | F48: 0.75 | G48: Assumed | H48: 公司未揭露交換器的 AI／非 AI 拆分：未找到 | I48: 美洲占 2025 年前三季營收 81%（公司）；其餘為企業、電信與前端
A49: ns26 | B49: FY2026 網路應用產品 ÷ 營收 | C49: % | D49: 0.42 | E49: 0.5 | F49: 0.58 | G49: Assumed | H49: 美系外資 2026-03（工商時報轉述）：2026 年交換器占營收 48%（Interested-party）→ 網路應用產品約 50% | I49: 工商時報 2026-09-29：1Q26 起高階交換器比重明顯上升、AI 加速卡比重快速上升（Interested-party）
A50: g_nai26 | B50: 非 AI 營收年增 2026 | C50: % | D50: 0 | E50: 0.1 | F50: 0.2 | G50: Assumed | H50: IDC 2Q26：非資料中心乙太網路交換器年增 15.7%（Interested-party） | I50: 企業、電信、前端交換器與接取；公司未揭露
A51: g_nai27 | B51: 非 AI 營收年增 2027 | C51: % | D51: 0 | E51: 0.06 | F51: 0.12 | G51: Assumed | H51: 同上 | I51: —
A52: g_nai28 | B52: 非 AI 營收年增 2028 | C52: % | D52: 0 | E52: 0.05 | F52: 0.1 | G52: Assumed | H52: 同上 | I52: —
A53: g_nai29 | B53: 非 AI 營收年增 2029 | C53: % | D53: 0 | E53: 0.05 | F53: 0.1 | G53: Assumed | H53: 同上 | I53: —
A54: E. 毛利率
A55: d_nap | B55: 網路應用產品毛利率低於交換器與其他的幅度 | C55: pt | D55: 0.03 | E55: 0.06 | F55: 0.1 | G55: Assumed | H55: 公司：3Q25 毛利率下滑主因產品組合（AI 加速卡占比上升；富果法說摘要） | I55: 工商時報 2026-09-29：AI 加速卡比重上升使毛利率略低於上半年（法人）；產品別毛利率未揭露：未找到
A56: F. FY2026 錨點（1Q、2Q 實績＋3Q 營收實績＋假設）
A57: q3_rev | B57: 3Q26 營收（7–9 月月營收合計） | C57: NT$B | E57: 120.74 | G57: Verified | H57: https://www.chinatimes.com/realtimenews/20261006003734-260410：3Q26 營收 1,207.4 億（9 月 403.99 億） | I57: nstock：1–9 月 2,864.02 億 − 上半年 1,656.58 億＝1,207.44 億
A58: q3_gm | B58: 3Q26 毛利率 | C58: % | D58: 0.175 | E58: 0.185 | F58: 0.195 | G58: Assumed | H58: 1Q26 19.55%、2Q26 19.7%（公司）；法人估 3Q26 18.1%（工商時報 2026-09-29，Interested-party） | I58: 時報 2026-10-06：記憶體與 PCB 改代購（客供）使營收認列減少；零組件漲價（Interested-party）
A59: q4_g | B59: 4Q26 營收季增 | C59: % | D59: -0.05 | E59: 0.03 | F59: 0.08 | G59: Assumed | H59: 時報 2026-10-06：法人稱 4Q 仍有機會較 3Q 成長（Interested-party） | I59: 公司 4Q 指引：未找到（3Q 法說約 11 月上旬）
A60: q4_gm | B60: 4Q26 毛利率 | C60: % | D60: 0.17 | E60: 0.185 | F60: 0.2 | G60: Assumed | H60: 同 3Q 假設 | I60: —
A61: q_opx | B61: 3Q、4Q26 營業費用 ÷ 營收 | C61: % | D61: 0.037 | E61: 0.04 | F61: 0.045 | G61: Assumed | H61: 2Q26 4.70%、1Q26 5.22%（公司）；法人估 3Q26 3.9%（Interested-party） | I61: 營收跳增、費用落後
A62: q_nio | B62: 3Q、4Q26 淨利 ÷ 營業利益 | C62: x | D62: 0.75 | E62: 0.8 | F62: 0.84 | G62: Derived | H62: 1Q26 8.341 ÷ 10.049＝0.830、2Q26 11.053 ÷ 14.331＝0.771（公司） | I62: FY2025 0.82（推導）
A63: q_sh | B63: 股數（十億股；EPS 換算） | C63: 十億股 | E63: =19.394/34.7 -> 0.5589049 | G63: Derived | H63: https://money.udn.com/money/story/5710/9675501：上半年淨利 193.94 億 ÷ EPS 34.7 | I63: 資本額 56.11 億（面額 10 元，鉅亨）＝5.611 億股
A64: G. 營業費用、業外與稅、股數（FY2027 起）
A65: phi | B65: 營業費用成長對營收成長的彈性 | C65: x | D65: 0.4 | E65: 0.6 | F65: 0.8 | G65: Derived | H65: FY2026 錨點營業費用年增 ÷ 營收年增（Q 頁） | I65: 低／高 Assumed
A66: opx_adj | B66: 營業費用額外占營收比（Sens 用；基準 0） | C66: pt | D66: -0.005 | E66: 0 | F66: 0.005 | G66: Assumed | H66: 無 | I66: 營益率約 15%，±0.5 個百分點約 ±3% 營業利益
A67: nio_f | B67: 淨利 ÷ 營業利益 | C67: x | D67: 0.75 | E67: 0.8 | F67: 0.84 | G67: Derived | H67: FY2025 0.82、1H26 0.795（公司數字推導） | I67: 匯兌損益與稅率變動
A68: sh_g27 | B68: 股數年變動 2027（現金增資） | C68: % | D68: 0 | E68: 0.0178 | F68: 0.02 | G68: Interested-party | H68: 經濟日報 2026-10-23（網址見 Sources）：董事會 2026-10-22 通過現增至多 1,000 萬股、稀釋約 1.78%（公司公告轉述） | I68: 發行時程與價格未定：未找到
A69: sh_g | B69: 股數年變動 2028 起 | C69: % | D69: -0.005 | E69: 0 | F69: 0.01 | G69: Assumed | H69: 股本二十多年大致不變（經濟日報 2026-10-23） | I69: —
A70: mf | B70: AI 交換器市場係數（Sens 用；FY2027 起） | C70: x | D70: 0.8 | E70: 1 | F70: 1.2 | G70: Assumed | H70: 網通模型 2027 年 scale-out 交換器 +90%；智邦訂單能見度到 2028 年（法人轉述） | I70: ±20%
A71: H. 共識、市場資料（只作 Recon 對帳，不作校準）
A72: cons_rev26 | B72: 共識 FY2026 營收 | C72: NT$B | E72: 412.45 | G72: Interested-party | H72: https://news.cnyes.com/news/id/6629903：FactSet 10 位分析師中位數（2026-10-14） | I72: 平均 408.66
A73: cons_eps26 | B73: 共識 FY2026 EPS | C73: NT$ | E73: 85.85 | G73: Interested-party | H73: 同上（區間 78.59–89.99） | I73: 工商時報 2026-09-29 法人 85.18
A74: cons_rev27 | B74: 共識 FY2027 營收 | C74: NT$B | E74: 551.5 | G74: Interested-party | H74: 同上 | I74: —
A75: cons_eps27 | B75: 共識 FY2027 EPS | C75: NT$ | E75: 120.82 | G75: Interested-party | H75: 同上（區間 86.97–139.61） | I75: 工商時報 2026-09-29 法人 107.53
A76: cons_eps28 | B76: 共識 FY2028 EPS | C76: NT$ | E76: 170.57 | G76: Interested-party | H76: 同上（區間 145.77–205.86） | I76: —
A77: br_sw26 | B77: 法人：FY2026 交換器 ÷ 營收 | C77: % | E77: 0.48 | G77: Interested-party | H77: 美系外資 2026-03（旺得富 2026-03-06） | I77: —
A78: dell_top2 | B78: 2025 AI 後端乙太網路：Celestica＋NVIDIA 合計份額 | C78: % | E78: 0.5 | G78: Interested-party | H78: Dell'Oro 2026-03-10 | I78: —
A79: I. 價格與估值
A80: px | B80: 股價（2026-10-22 收盤） | C80: NT$ | E80: 1775 | G80: Interested-party | H80: 鉅亨網 2345（10-22 收盤 1,775、前收 1,815）；臺灣證券交易所 STOCK_DAY（115/10/22 收盤 1,775.00，2026-10-25 查詢） | I80: 永豐金 AI 投資、財報狗同值；工作單：台股無 10-23 收盤時用 10-22（證交所當月資料只到 10/22）；10-23 收盤：未找到
A81: pe_ttm | B81: 近 12 月 P/E（鉅亨，10-22） | C81: x | E81: 27.88 | G81: Interested-party | H81: 鉅亨網 | I81: 財報狗 27.89
A82: tp_wA | B82: 目標價情境權重 A（樂觀） | C82: % | E82: 0.3 | G82: Assumed | H82: Andy 可改 | I82: 三個權重合計應為 1
A83: tp_wB | B83: 目標價情境權重 B（基準） | C83: % | E83: 0.5 | G83: Assumed | H83: Andy 可改 | I83: —
A84: tp_wC | B84: 目標價情境權重 C（下檔） | C84: % | E84: 0.2 | G84: Assumed | H84: Andy 可改 | I84: —
A85: J. 目標價參數（v0.2 新增：DCF 與 Comparable 加權、FY2029 後收斂法；黃底＝Andy 可改）
A86: tp_r | B86: DCF 折現率（股東權益成本） | C86: % | E86: 0.1 | G86: Assumed | H86: Andy 可改（工作單 2026-10-25：美、台、日、韓同一值） | I86: Sens 頁 ±1pt
A87: tp_g | B87: 長期成長率（FY2032 後永續；PL 延伸期 B 情境的收斂目標） | C87: % | E87: 0.04 | G87: Assumed | H87: Andy 可改（工作單 2026-10-25） | I87: Sens 頁 ±1pt（只改 DCF 再投資率與永續成長，不改 PL 收斂路徑）
A88: tp_gd | B88: 延伸期 A／C 情境長期成長相對 tp_g 的差（A＋、C−） | C88: pt | E88: 0.02 | G88: Assumed | H88: 工作單 2026-10-25：A＝tp_g＋2pt、C＝tp_g−2pt | I88: —
A89: tp_roe | B89: 近三年平均 ROE（再投資率＝tp_g ÷ tp_roe） | C89: % | E89: 0.4475 | G89: Derived | H89: 永豐金 AI 投資 2345 頁（年度 ROE）：2023 39.11%、2024 39.01%、2025 56.13%，平均 44.75%（資料商，Interested-party） | I89: stockanalysis 近 12 月 ROE 65.58%
A90: tp_w_dcf | B90: 目標價中 DCF 的權重（其餘為 Comparable） | C90: % | E90: 0.5 | G90: Assumed | H90: Andy 可改（Andy 2026-10-25 11:53 定 50／50） | I90: Sens 頁 0.3／0.7
A91: nm10_k | B91: 延伸期 C 情境淨利率目標＝FY2029 淨利率 × 本係數（十年平均未找到） | C91: x | E91: 0.8 | G91: Assumed | H91: 工作單：找不到十年平均用最後一年 × 0.8。2016–2021 年淨利率：未找到 | I91: 參考：永豐金 AI 投資稅後淨利率 2022 10.58%、2023 10.60%、2024 10.87%、2025 10.59%（四年平均 10.66%）
A92: cons_tp | B92: 市場共識目標價（FactSet） | C92: NT$ | E92: 3500 | G92: Interested-party | H92: https://news.cnyes.com/news/id/6629903：FactSet 10 位分析師目標價 3,500（2026-10-14，鉅亨網） | I92: stockanalysis（13 位）平均 3,234.92（頁面現價日期不一致，不採）；賣方有目標價誘因，只作對照

Sheet Q
A1: Q — 實績（十億新台幣；EPS 為新台幣；股數為十億股）。口徑：合併營收、稅後淨利（公司公告）。藍字＝輸入；黑字＝公式。實績取自公司季報與月營收公告的媒體轉述（經濟日報、工商時報）
A2: FY2026 錨點＝1Q26、2Q26 實績＋3Q26 營收實績（月營收）與毛利率、費用假設＋4Q26 假設。3Q26 財報與法說約 11 月上旬（去年 11-07；確切日期未找到），公布後更新 E 欄。FY2025 毛利與營業利益由毛利率 18.09%、營益率 12.94%（永豐、Goodinfo）推導
A3: 項目 | B3: FY2025A | C3: 1Q26 | D3: 2Q26 | E3: 3Q26（營收實績＋假設） | F3: 4Q26（假設） | G3: FY2026 錨點 | H3: 標記 | I3: 來源1（公司） | J3: 來源2／說明
A4: 營收 | B4: 248.32 | C4: 70.121 | D4: 95.538 | E4: =q3_rev -> 120.74 | F4: =E4*(1+q4_g) -> 124.3622 | G4: =SUM(C4:F4) -> 410.7612 | H4: Verified／Assumed（4Q） | I4: FY2025：https://goodinfo.tw/tw/StockBzPerformance.asp?STOCK_ID=2345&RPT_CAT=M_YEAR（營收 2,483 億、毛利率 18.1%、營益率 12.9%、EPS 47.13）；1Q26：https://money.udn.com/money/story/5710/9488861；2Q26：https://money.udn.com/money/story/5710/9675501 | J4: 交叉：永豐金 AI 投資（2025 毛利率 18.09%、營益率 12.94%）；理財周刊 2026-04-21（2025 淨利 263.42 億、EPS 47.13）；工商時報 2026-09-29（2Q26 營業費用 44.91 億）
A5: 毛利 | B5: =B4*0.1809 -> 44.921088 | C5: 13.709 | D5: 18.823 | E5: =E4*q3_gm -> 22.3369 | F5: =F4*q4_gm -> 23.007007 | G5: =SUM(C5:F5) -> 77.875907 | H5: Verified／Derived（FY2025）／Assumed（3Q、4Q） | I5: FY2025：https://goodinfo.tw/tw/StockBzPerformance.asp?STOCK_ID=2345&RPT_CAT=M_YEAR（營收 2,483 億、毛利率 18.1%、營益率 12.9%、EPS 47.13）；1Q26：https://money.udn.com/money/story/5710/9488861；2Q26：https://money.udn.com/money/story/5710/9675501 | J5: 交叉：永豐金 AI 投資（2025 毛利率 18.09%、營益率 12.94%）；理財周刊 2026-04-21（2025 淨利 263.42 億、EPS 47.13）；工商時報 2026-09-29（2Q26 營業費用 44.91 億）
A6: 毛利率 | B6: =B5/B4 -> 0.1809 | C6: =C5/C4 -> 0.19550491 | D6: =D5/D4 -> 0.19702108 | E6: =E5/E4 -> 0.185 | F6: =F5/F4 -> 0.185 | G6: =G5/G4 -> 0.18958925 | H6: Derived | I6: — | J6: 1Q26 19.55%、2Q26 19.7%（公司）
A7: 營業費用 | B7: =B5-B8 -> 12.78848 | C7: =C5-C8 -> 3.66 | D7: =D5-D8 -> 4.492 | E7: =E4*q_opx -> 4.8296 | F7: =F4*q_opx -> 4.974488 | G7: =SUM(C7:F7) -> 17.956088 | H7: Derived（毛利 − 營業利益）／Assumed | I7: FY2025：https://goodinfo.tw/tw/StockBzPerformance.asp?STOCK_ID=2345&RPT_CAT=M_YEAR（營收 2,483 億、毛利率 18.1%、營益率 12.9%、EPS 47.13）；1Q26：https://money.udn.com/money/story/5710/9488861；2Q26：https://money.udn.com/money/story/5710/9675501 | J7: 交叉：永豐金 AI 投資（2025 毛利率 18.09%、營益率 12.94%）；理財周刊 2026-04-21（2025 淨利 263.42 億、EPS 47.13）；工商時報 2026-09-29（2Q26 營業費用 44.91 億）
A8: 營業利益 | B8: =B4*0.1294 -> 32.132608 | C8: 10.049 | D8: 14.331 | E8: =E5-E7 -> 17.5073 | F8: =F5-F7 -> 18.032519 | G8: =SUM(C8:F8) -> 59.919819 | H8: Verified／Derived | I8: FY2025：https://goodinfo.tw/tw/StockBzPerformance.asp?STOCK_ID=2345&RPT_CAT=M_YEAR（營收 2,483 億、毛利率 18.1%、營益率 12.9%、EPS 47.13）；1Q26：https://money.udn.com/money/story/5710/9488861；2Q26：https://money.udn.com/money/story/5710/9675501 | J8: 交叉：永豐金 AI 投資（2025 毛利率 18.09%、營益率 12.94%）；理財周刊 2026-04-21（2025 淨利 263.42 億、EPS 47.13）；工商時報 2026-09-29（2Q26 營業費用 44.91 億）
A9: 營業利益率 | B9: =B8/B4 -> 0.1294 | C9: =C8/C4 -> 0.14330942 | D9: =D8/D4 -> 0.15000314 | E9: =E8/E4 -> 0.145 | F9: =F8/F4 -> 0.145 | G9: =G8/G4 -> 0.14587507 | H9: Derived | I9: — | J9: —
A10: 稅後淨利 | B10: 26.342 | C10: 8.341 | D10: 11.053 | E10: =E8*q_nio -> 14.00584 | F10: =F8*q_nio -> 14.426015 | G10: =SUM(C10:F10) -> 47.825855 | H10: Verified／Derived（3Q、4Q） | I10: FY2025：https://goodinfo.tw/tw/StockBzPerformance.asp?STOCK_ID=2345&RPT_CAT=M_YEAR（營收 2,483 億、毛利率 18.1%、營益率 12.9%、EPS 47.13）；1Q26：https://money.udn.com/money/story/5710/9488861；2Q26：https://money.udn.com/money/story/5710/9675501 | J10: 交叉：永豐金 AI 投資（2025 毛利率 18.09%、營益率 12.94%）；理財周刊 2026-04-21（2025 淨利 263.42 億、EPS 47.13）；工商時報 2026-09-29（2Q26 營業費用 44.91 億）
A11: 淨利 ÷ 營業利益 | B11: =B10/B8 -> 0.81979029 | C11: =C10/C8 -> 0.83003284 | D11: =D10/D8 -> 0.77126509 | E11: =E10/E8 -> 0.8 | F11: =F10/F8 -> 0.8 | G11: =G10/G8 -> 0.79816421 | H11: Derived | I11: — | J11: 1Q26 稅前 103.62 億（業外 +3.1 億；公司）
A12: 股數（十億股） | B12: =26.342/47.13 -> 0.55892213 | C12: =8.341/14.92 -> 0.55904826 | D12: =11.053/19.78 -> 0.55879676 | E12: =q_sh -> 0.5589049 | F12: =q_sh -> 0.5589049 | G12: =q_sh -> 0.5589049 | H12: Derived | I12: FY2025：https://goodinfo.tw/tw/StockBzPerformance.asp?STOCK_ID=2345&RPT_CAT=M_YEAR（營收 2,483 億、毛利率 18.1%、營益率 12.9%、EPS 47.13）；1Q26：https://money.udn.com/money/story/5710/9488861；2Q26：https://money.udn.com/money/story/5710/9675501 | J12: 淨利 ÷ EPS
A13: EPS | B13: =B10/B12 -> 47.13 | C13: =C10/C12 -> 14.92 | D13: =D10/D12 -> 19.78 | E13: =E10/E12 -> 25.059433 | F13: =F10/F12 -> 25.811216 | G13: =G10/G12 -> 85.570649 | H13: Derived | I13: 淨利 ÷ 股數 | J13: —
A14: 公司揭露 EPS | B14: 47.13 | C14: 14.92 | D14: 19.78 | H14: Verified | I14: FY2025：https://goodinfo.tw/tw/StockBzPerformance.asp?STOCK_ID=2345&RPT_CAT=M_YEAR（營收 2,483 億、毛利率 18.1%、營益率 12.9%、EPS 47.13）；1Q26：https://money.udn.com/money/story/5710/9488861；2Q26：https://money.udn.com/money/story/5710/9675501 | J14: 永豐金 AI 投資列 2025 年 46.95、1Q26 14.87（口徑不同：疑為追溯調整）
A16: FY2026 錨點與共識的距離（參考；校準未使用共識）
A17: FY2026 營收 ÷ 共識 − 1 | B17: =G4/cons_rev26-1 -> -0.0040945569
A18: FY2026 EPS ÷ 共識 − 1 | B18: =G13/cons_eps26-1 -> -0.0032539377
A19: FY2026 營收年增 | B19: =G4/B4-1 -> 0.65416076
A20: FY2026 營業費用年增 | B20: =G7/B7-1 -> 0.40408305
A21: 營業費用彈性（營業費用年增 ÷ 營收年增；In 頁 phi 的依據） | B21: =B20/B19 -> 0.61771215
A22: 3Q26 EPS（模型）vs 法人估計 23.91 | B22: =E13/23.91-1 -> 0.048073326

Sheet Units
A1: Units — 智邦在白牌 AI 乙太網路交換器的份額（本專案權威，規則第 13 條）。市場取自 markets/network（scale-out 交換器＋非 NVIDIA scale-up 交換匣）
A3: 項目 | B3: 單位 | C3: CY2026 | D3: CY2027 | E3: CY2028 | F3: CY2029 | G3: 說明
A4: AI 乙太網路交換器市場（情境 A） | B4: US$B | C4: =PL!D70 -> 27.068925 | D4: =PL!E70 -> 60.2094 | E4: =PL!F70 -> 71.16935 | F4: =PL!G70 -> 82.689307 | G4: scale-out × 乙太網路占比＋scale-up 交換匣
A5: 其中非 NVIDIA scale-up 交換匣 | B5: US$B | C5: =PL!D69 -> 3.015 | D5: =PL!E69 -> 11.3414 | E5: =PL!F69 -> 13.8952 | F5: =PL!G69 -> 15.97948 | G5: Trainium、其他 ASIC、AMD
A6: 白牌占比 | B6: % | C6: =PL!D71 -> 0.45 | D6: =PL!E71 -> 0.47 | E6: =PL!F71 -> 0.48 | F6: =PL!G71 -> 0.5 | G6: In 頁 B 節（Assumed）
A7: 白牌 AI 乙太網路交換器市場 | B7: US$B | C7: =PL!D72 -> 12.181016 | D7: =PL!E72 -> 28.298418 | E7: =PL!F72 -> 34.161288 | F7: =PL!G72 -> 41.344654
A8: 智邦白牌有效份額（含前端資料中心） | B8: % | C8: =PL!D75 -> 0.41057065 | D8: =PL!E75 -> 0.41057065 | E8: =PL!F75 -> 0.39004212 | F8: =PL!G75 -> 0.377725 | G8: FY2026 以營收拆分校準
A9: 智邦 AI 交換器營收（情境 A） | B9: US$B | C9: =PL!D76/fx -> 5.0011677 | D9: =PL!E76/fx -> 11.6185 | E9: =PL!F76/fx -> 13.324341 | F9: =PL!G76/fx -> 15.616909
A10: 其他白牌（Celestica 等）＝ 白牌市場 − 智邦 | B10: US$B | C10: =PL!D72-PL!D76/fx -> 7.1798485 | D10: =PL!E72-PL!E76/fx -> 16.679918 | E10: =PL!F72-PL!F76/fx -> 20.836947 | F10: =PL!G72-PL!G76/fx -> 25.727745 | G10: 下限：智邦 AI 交換器含前端，所以此列偏低
A11: 智邦 ÷ AI 乙太網路交換器市場 | B11: % | C11: =PL!D76/fx/PL!D70 -> 0.18475679 | D11: =PL!E76/fx/PL!E70 -> 0.19296821 | E11: =PL!F76/fx/PL!F70 -> 0.18722022 | F11: =PL!G76/fx/PL!G70 -> 0.1888625
A12: AWS Trainium 顆數 | B12: 百萬顆 | C12: =PL!D78 -> 2 | D12: =PL!E78 -> 2.5 | E12: =PL!F78 -> 3 | F12: =PL!G78 -> 3.45 | G12: markets/network Units 頁
A13: 智邦 AI 營收 ÷ AI IT 資本支出 | B13: % | C13: =(PL!D76+PL!D81)/fx/itc_26 -> 0.014605074 | D13: =(PL!E76+PL!E81)/fx/itc_27 -> 0.012034952 | E13: =(PL!F76+PL!F81)/fx/itc_28 -> 0.010839019 | F13: =(PL!G76+PL!G81)/fx/itc_29 -> 0.010827311 | G13: markets/network 的 AI IT 資本支出
A15: 讀法：FY2026 智邦約占白牌 AI 乙太網路交換器四成上下，與 Dell'Oro「Celestica 為白牌第一」相容的前提是智邦的分子含前端；份額相對值與白牌占比都是 Assumed，是最需要每季檢查的輸入。

Sheet PL
A1: PL — 智邦損益（NT$B）。FY2025A 實績、FY2026 錨點（1Q–2Q 實績＋3Q 營收實績＋假設），FY2027 起為模型。FY(t)＝CY(t)。三情境各一個完整推導區塊（本頁下方），頂端為摘要。FY2026–FY2027 三情境相同（顆數係數從 CY2028 開始）
A3: 情境／項目 | B3: 單位 | C3: FY2025A | D3: FY2026（錨點） | E3: FY2027 | F3: FY2028 | G3: FY2029 | H3: 說明
A4: 情境 A
A5: 營收 | B5: NT$B | C5: =C84 -> 248.32 | D5: =D84 -> 410.7612 | E5: =E84 -> 650.909 | F5: =F84 -> 738.7062 | G5: =G84 -> 836.15669
A6: 營收年增 | B6: % | D6: =D90 -> 0.65416076 | E6: =E90 -> 0.5846409 | F6: =F90 -> 0.13488399 | G6: =G90 -> 0.1319205
A7: AI 交換器營收 | B7: NT$B | C7: =C76 -> 50.65728 | D7: =D76 -> 160.03737 | E7: =E76 -> 371.792 | F7: =F76 -> 426.37891 | G7: =G76 -> 499.7411
A8: 網路應用產品營收 | B8: NT$B | C8: =C81 -> 156.4416 | D8: =D81 -> 205.3806 | E8: =E81 -> 231.05318 | F8: =F81 -> 261.86027 | G8: =G81 -> 283.42523
A9: 非 AI 營收 | B9: NT$B | C9: =C83 -> 41.22112 | D9: =D83 -> 45.343232 | E9: =E83 -> 48.063826 | F9: =F83 -> 50.467017 | G9: =G83 -> 52.990368
A10: AI ÷ 營收 | B10: % | C10: =C91 -> 0.834 | D10: =D91 -> 0.8896117 | E10: =E91 -> 0.92615892 | F10: =F91 -> 0.93168188 | G10: =G91 -> 0.93662627
A11: 毛利率 | B11: % | C11: =C96 -> 0.1809 | D11: =D96 -> 0.18958925 | E11: =E96 -> 0.19829105 | F11: =F96 -> 0.19832015 | G11: =G96 -> 0.19925154
A12: 營業利益率 | B12: % | C12: =C100 -> 0.1294 | D12: =D100 -> 0.14587507 | E12: =E100 -> 0.16102807 | F12: =F100 -> 0.16282869 | G12: =G100 -> 0.16541463
A13: 稅後淨利 | B13: NT$B | C13: =C102 -> 26.342 | D13: =D102 -> 47.825855 | E13: =E102 -> 83.851696 | F13: =F102 -> 96.226052 | G13: =G102 -> 110.65004
A14: EPS | B14: NT$ | C14: =C104 -> 47.13 | D14: =D104 -> 85.570649 | E14: =E104 -> 147.40475 | F14: =F104 -> 169.15791 | G14: =G104 -> 194.51416
A15: EPS 年增 | B15: % | D15: =D105 -> 0.81563016 | E15: =E105 -> 0.7226088 | F15: =F105 -> 0.14757431 | G15: =G105 -> 0.14989693
A17: 情境 B
A18: 營收 | B18: NT$B | C18: =C132 -> 248.32 | D18: =D132 -> 410.7612 | E18: =E132 -> 650.909 | F18: =F132 -> 601.05836 | G18: =G132 -> 718.68174
A19: 營收年增 | B19: % | D19: =D138 -> 0.65416076 | E19: =E138 -> 0.5846409 | F19: =F138 -> -0.076586183 | G19: =G138 -> 0.19569378
A20: AI 交換器營收 | B20: NT$B | C20: =C124 -> 50.65728 | D20: =D124 -> 160.03737 | E20: =E124 -> 371.792 | F20: =F124 -> 341.10313 | G20: =G124 -> 424.77993
A21: 網路應用產品營收 | B21: NT$B | C21: =C129 -> 156.4416 | D21: =D129 -> 205.3806 | E21: =E129 -> 231.05318 | F21: =F129 -> 209.48821 | G21: =G129 -> 240.91144
A22: 非 AI 營收 | B22: NT$B | C22: =C131 -> 41.22112 | D22: =D131 -> 45.343232 | E22: =E131 -> 48.063826 | F22: =F131 -> 50.467017 | G22: =G131 -> 52.990368
A23: AI ÷ 營收 | B23: % | C23: =C139 -> 0.834 | D23: =D139 -> 0.8896117 | E23: =E139 -> 0.92615892 | F23: =F139 -> 0.91603641 | G23: =G139 -> 0.92626727
A24: 毛利率 | B24: % | C24: =C144 -> 0.1809 | D24: =D144 -> 0.18958925 | E24: =E144 -> 0.19829105 | F24: =F144 -> 0.19867731 | G24: =G144 -> 0.19947647
A25: 營業利益率 | B25: % | C25: =C148 -> 0.1294 | D25: =D148 -> 0.14587507 | E25: =E148 -> 0.16102807 | F25: =F148 -> 0.15832382 | G25: =G148 -> 0.16176476
A26: 稅後淨利 | B26: NT$B | C26: =C150 -> 26.342 | D26: =D150 -> 47.825855 | E26: =E150 -> 83.851696 | F26: =F150 -> 76.129484 | G26: =G150 -> 93.005906
A27: EPS | B27: NT$ | C27: =C152 -> 47.13 | D27: =D152 -> 85.570649 | E27: =E152 -> 147.40475 | F27: =F152 -> 133.82971 | G27: =G152 -> 163.49714
A28: EPS 年增 | B28: % | D28: =D153 -> 0.81563016 | E28: =E153 -> 0.7226088 | F28: =F153 -> -0.092093695 | G28: =G153 -> 0.2216805
A30: 情境 C
A31: 營收 | B31: NT$B | C31: =C180 -> 248.32 | D31: =D180 -> 410.7612 | E31: =E180 -> 650.909 | F31: =F180 -> 463.41053 | G31: =G180 -> 522.89016
A32: 營收年增 | B32: % | D32: =D186 -> 0.65416076 | E32: =E186 -> 0.5846409 | F32: =F186 -> -0.28805635 | G32: =G186 -> 0.12835193
A33: AI 交換器營收 | B33: NT$B | C33: =C172 -> 50.65728 | D33: =D172 -> 160.03737 | E33: =E172 -> 371.792 | F33: =F172 -> 255.82735 | G33: =G172 -> 299.84466
A34: 網路應用產品營收 | B34: NT$B | C34: =C177 -> 156.4416 | D34: =D177 -> 205.3806 | E34: =E177 -> 231.05318 | F34: =F177 -> 157.11616 | G34: =G177 -> 170.05514
A35: 非 AI 營收 | B35: NT$B | C35: =C179 -> 41.22112 | D35: =D179 -> 45.343232 | E35: =E179 -> 48.063826 | F35: =F179 -> 50.467017 | G35: =G179 -> 52.990368
A36: AI ÷ 營收 | B36: % | C36: =C187 -> 0.834 | D36: =D187 -> 0.8896117 | E36: =E187 -> 0.92615892 | F36: =F187 -> 0.89109652 | G36: =G187 -> 0.8986587
A37: 毛利率 | B37: % | C37: =C192 -> 0.1809 | D37: =D192 -> 0.18958925 | E37: =E192 -> 0.19829105 | F37: =F192 -> 0.19924666 | G37: =G192 -> 0.20007596
A38: 營業利益率 | B38: % | C38: =C196 -> 0.1294 | D38: =D196 -> 0.14587507 | E38: =E196 -> 0.16102807 | F38: =F196 -> 0.14690688 | G38: =G196 -> 0.15011767
A39: 稅後淨利 | B39: NT$B | C39: =C198 -> 26.342 | D39: =D198 -> 47.825855 | E39: =E198 -> 83.851696 | F39: =F198 -> 54.462554 | G39: =G198 -> 62.796042
A40: EPS | B40: NT$ | C40: =C200 -> 47.13 | D40: =D200 -> 85.570649 | E40: =E200 -> 147.40475 | F40: =F200 -> 95.740931 | G40: =G200 -> 110.39055
A41: EPS 年增 | B41: % | D41: =D201 -> 0.81563016 | E41: =E201 -> 0.7226088 | F41: =F201 -> -0.35048953 | G41: =G201 -> 0.15301316
A43: 核對（應為 0）：FY2026 模型營收 − 錨點；FY2026 模型毛利 − 錨點（校準恆等式）
A44: 情境 A：營收差（NT$B） | D44: =D84-a26_rev -> 0
A45: 情境 A：FY2025 營收差（NT$B） | D45: =C84-a25_rev -> 0
A46: 情境 A：毛利差（NT$B） | D46: =D94*(D76+D83)+(D94-d_nap)*D81-a26_gp -> 0
A60: 情境 A：基準顆數（顆數係數 1.0；目標價權重視為樂觀）
A61: 項目 | B61: 單位 | C61: FY2025A | D61: FY2026（錨點） | E61: FY2027 | F61: FY2028 | G61: FY2029 | H61: 說明
A62: A. 營收拆分（FY2025 依公司揭露比例；FY2026 校準：網路應用產品比例 Assumed，非 AI 依成長率，AI 交換器為殘差）
A63: 網路應用產品（AI 加速卡等） | B63: NT$B | C63: =a25_rev*nap25s -> 156.4416 | D63: =a26_rev*ns26 -> 205.3806
A64: 非 AI（企業、電信、前端交換器、接取） | B64: NT$B | C64: =a25_rev*(1-nap25s-sw25s*af25) -> 41.22112 | D64: =C64*(1+g_nai26) -> 45.343232
A65: AI 資料中心交換器（殘差） | B65: NT$B | C65: =a25_rev*sw25s*af25 -> 50.65728 | D65: =a26_rev-D63-D64 -> 160.03737 | H65: Derived：FY2026 交換器合計＝AI＋非 AI 交換器（見 Recon）
A66: B. AI 交換器（D 欄＝FY2026 校準年；E–G＝FY2027–FY2029）
A67: AI 後端 scale-out 交換器市場 × 情境顆數係數 | B67: US$B | D67: =mkt_26*1 -> 32.0719 | E67: =mkt_27*1*1 -> 61.085 | F67: =mkt_28*um28_A*1 -> 69.005 | G67: =mkt_29*um29_A*1 -> 78.48215
A68: 乙太網路占比 | B68: % | D68: =eth_26 -> 0.75 | E68: =eth_27 -> 0.8 | F68: =eth_28 -> 0.83 | G68: =eth_29 -> 0.85
A69: 非 NVIDIA scale-up 乙太網路交換匣市場 × 係數 | B69: US$B | D69: =su_26*1 -> 3.015 | E69: =su_27*1*1 -> 11.3414 | F69: =su_28*um28_A*1 -> 13.8952 | G69: =su_29*um29_A*1 -> 15.97948
A70: AI 乙太網路交換器市場（scale-out × 乙太網路＋scale-up） | B70: US$B | D70: =D67*D68+D69 -> 27.068925 | E70: =E67*E68+E69 -> 60.2094 | F70: =F67*F68+F69 -> 71.16935 | G70: =G67*G68+G69 -> 82.689307
A71: 白牌占比 | B71: % | D71: =wb_26 -> 0.45 | E71: =wb_27 -> 0.47 | F71: =wb_28 -> 0.48 | G71: =wb_29 -> 0.5
A72: 白牌 AI 乙太網路交換器市場 | B72: US$B | D72: =D70*D71 -> 12.181016 | E72: =E70*E71 -> 28.298418 | F72: =F70*F71 -> 34.161288 | G72: =G70*G71 -> 41.344654
A73: 智邦白牌有效份額（FY2026 校準）＝ AI 交換器營收 ÷ 匯率 ÷ 白牌市場 | B73: % | D73: =D65/fx/D72 -> 0.41057065 | H73: Derived：分子含前端資料中心交換器，所以高於純後端份額；FY2027 起乘相對值
A74: 份額相對值（÷ FY2026） | B74: x | D74: =1 -> 1 | E74: =rel_27 -> 1 | F74: =rel_28 -> 0.95 | G74: =rel_29 -> 0.92
A75: 智邦白牌有效份額 | B75: % | D75: =$D$73*D74 -> 0.41057065 | E75: =$D$73*E74 -> 0.41057065 | F75: =$D$73*F74 -> 0.39004212 | G75: =$D$73*G74 -> 0.377725
A76: AI 交換器營收 | B76: NT$B | C76: =C65 -> 50.65728 | D76: =D72*D75*fx -> 160.03737 | E76: =E72*E75*fx -> 371.792 | F76: =F72*F75*fx -> 426.37891 | G76: =G72*G75*fx -> 499.7411
A77: C. AI 加速卡等網路應用產品
A78: AWS Trainium 顆數 × 情境顆數係數 | B78: 百萬顆 | D78: =trn_26*1 -> 2 | E78: =trn_27*1*1 -> 2.5 | F78: =trn_28*um28_A*1 -> 3 | G78: =trn_29*um29_A*1 -> 3.45
A79: 每顆 Trainium 的智邦營收（FY2026 校準） | B79: 千新台幣／顆 | D79: =D63/D78 -> 102.6903 | H79: Derived：含加速卡模組、L10 等網路應用產品；晶片疑為客供（每顆約 3 千美元）
A80: 相對值（份額 × 單價，÷ FY2026） | B80: x | D80: =1 -> 1 | E80: =nrel_27 -> 0.9 | F80: =nrel_28 -> 0.85 | G80: =nrel_29 -> 0.8
A81: 網路應用產品營收 | B81: NT$B | C81: =C63 -> 156.4416 | D81: =D78*$D$79*D80 -> 205.3806 | E81: =E78*$D$79*E80 -> 231.05318 | F81: =F78*$D$79*F80 -> 261.86027 | G81: =G78*$D$79*G80 -> 283.42523
A82: D. 非 AI 與合計
A83: 非 AI 營收 | B83: NT$B | C83: =C64 -> 41.22112 | D83: =D64 -> 45.343232 | E83: =D83*(1+g_nai27) -> 48.063826 | F83: =E83*(1+g_nai28) -> 50.467017 | G83: =F83*(1+g_nai29) -> 52.990368
A84: 營收 | B84: NT$B | C84: =C76+C81+C83 -> 248.32 | D84: =D76+D81+D83 -> 410.7612 | E84: =E76+E81+E83 -> 650.909 | F84: =F76+F81+F83 -> 738.7062 | G84: =G76+G81+G83 -> 836.15669
A85: 非 AI 中的非 AI 交換器比例（固定在 FY2025 結構） | B85: % | C85: =sw25s*(1-af25)/(1-nap25s-sw25s*af25) -> 0.81927711 | H85: FY2025：交換器 34% ×（1 − AI 比例）÷ 非 AI 合計；之後各年沿用
A86: 網路交換器：非 AI（企業、電信、前端） | B86: NT$B | C86: =C83*$C$85 -> 33.77152 | D86: =D83*$C$85 -> 37.148672 | E86: =E83*$C$85 -> 39.377592 | F86: =F83*$C$85 -> 41.346472 | G86: =G83*$C$85 -> 43.413796
A87: 網路交換器營收（AI 資料中心＋非 AI） | B87: NT$B | C87: =C76+C86 -> 84.4288 | D87: =D76+D86 -> 197.18604 | E87: =E76+E86 -> 411.16959 | F87: =F76+F86 -> 467.72539 | G87: =G76+G86 -> 543.15489 | H87: 公司產品別：網路交換器（FY2025 前三季 34%）
A88: 接取與其他營收（＝非 AI − 非 AI 交換器） | B88: NT$B | C88: =C83-C86 -> 7.4496 | D88: =D83-D86 -> 8.19456 | E88: =E83-E86 -> 8.6862336 | F88: =F83-F86 -> 9.1205453 | G88: =G83-G86 -> 9.5765725 | H88: 公司產品別：接取（FY2025 前三季 2%）與其他
A89: 檢查：分部合計 − 合併營收（FY2025 實績起） | B89: NT$B | C89: =C87+C81+C88-a25_rev -> 0 | D89: =D87+D81+D88-D84 -> 0 | E89: =E87+E81+E88-E84 -> 0 | F89: =F87+F81+F88-F84 -> 0 | G89: =G87+G81+G88-G84 -> 0
A90: 營收年增 | B90: % | D90: =D84/C84-1 -> 0.65416076 | E90: =E84/D84-1 -> 0.5846409 | F90: =F84/E84-1 -> 0.13488399 | G90: =G84/F84-1 -> 0.1319205
A91: AI（交換器＋網路應用產品）÷ 營收 | B91: % | C91: =(C76+C81)/C84 -> 0.834 | D91: =(D76+D81)/D84 -> 0.8896117 | E91: =(E76+E81)/E84 -> 0.92615892 | F91: =(F76+F81)/F84 -> 0.93168188 | G91: =(G76+G81)/G84 -> 0.93662627
A92: 網路應用產品 ÷ 營收 | B92: % | C92: =C81/C84 -> 0.63 | D92: =D81/D84 -> 0.5 | E92: =E81/E84 -> 0.35497001 | F92: =F81/F84 -> 0.354485 | G92: =G81/G84 -> 0.33896186
A93: E. 損益
A94: 交換器與其他毛利率 ＝ 錨點毛利率 ＋ 差距 × 網路應用產品占比（FY2026 校準） | B94: % | D94: =a26_gp/a26_rev+d_nap*D92 -> 0.21958925 | H94: Derived：讓 FY2026 毛利率等於錨點；網路應用產品毛利率＝此值 − 差距
A95: 毛利 | B95: NT$B | C95: =a25_gp -> 44.921088 | D95: =a26_gp -> 77.875907 | E95: =$D$94*(E76+E83)+($D$94-d_nap)*E81 -> 129.06943 | F95: =$D$94*(F76+F83)+($D$94-d_nap)*F81 -> 146.50032 | G95: =$D$94*(G76+G83)+($D$94-d_nap)*G81 -> 166.60551
A96: 毛利率 | B96: % | C96: =C95/C84 -> 0.1809 | D96: =D95/D84 -> 0.18958925 | E96: =E95/E84 -> 0.19829105 | F96: =F95/F84 -> 0.19832015 | G96: =G95/G84 -> 0.19925154
A97: 營業費用（基準路徑） | B97: NT$B | C97: =a25_opx -> 12.78848 | D97: =a26_opx -> 17.956088 | E97: =D97*(1+MAX(0,phi*E90)) -> 24.254806 | F97: =E97*(1+MAX(0,phi*F90)) -> 26.217757 | G97: =F97*(1+MAX(0,phi*G90)) -> 28.292953
A98: 營業費用 | B98: NT$B | C98: =C97 -> 12.78848 | D98: =D97 -> 17.956088 | E98: =E97+0*E84 -> 24.254806 | F98: =F97+0*F84 -> 26.217757 | G98: =G97+0*G84 -> 28.292953
A99: 營業利益 | B99: NT$B | C99: =C95-C98 -> 32.132608 | D99: =D95-D98 -> 59.919819 | E99: =E95-E98 -> 104.81462 | F99: =F95-F98 -> 120.28257 | G99: =G95-G98 -> 138.31255
A100: 營業利益率 | B100: % | C100: =C99/C84 -> 0.1294 | D100: =D99/D84 -> 0.14587507 | E100: =E99/E84 -> 0.16102807 | F100: =F99/F84 -> 0.16282869 | G100: =G99/G84 -> 0.16541463
A101: 淨利 ÷ 營業利益 | B101: x | C101: =a25_ni/a25_oi -> 0.81979029 | D101: =a26_ni/a26_oi -> 0.79816421 | E101: =nio_f -> 0.8 | F101: =nio_f -> 0.8 | G101: =nio_f -> 0.8
A102: 稅後淨利 | B102: NT$B | C102: =a25_ni -> 26.342 | D102: =a26_ni -> 47.825855 | E102: =E99*E101 -> 83.851696 | F102: =F99*F101 -> 96.226052 | G102: =G99*G101 -> 110.65004
A103: 股數 | B103: 十億股 | C103: =a25_sh -> 0.55892213 | D103: =a26_sh -> 0.5589049 | E103: =D103*(1+sh_g27) -> 0.56885341 | F103: =E103*(1+sh_g) -> 0.56885341 | G103: =F103*(1+sh_g) -> 0.56885341
A104: EPS | B104: NT$ | C104: =C102/C103 -> 47.13 | D104: =D102/D103 -> 85.570649 | E104: =E102/E103 -> 147.40475 | F104: =F102/F103 -> 169.15791 | G104: =G102/G103 -> 194.51416
A105: EPS 年增 | B105: % | D105: =D104/C104-1 -> 0.81563016 | E105: =E104/D104-1 -> 0.7226088 | F105: =F104/E104-1 -> 0.14757431 | G105: =G104/F104-1 -> 0.14989693
A108: 情境 B：CY2028 顆數 ×0.8、CY2029 ×0.85
A109: 項目 | B109: 單位 | C109: FY2025A | D109: FY2026（錨點） | E109: FY2027 | F109: FY2028 | G109: FY2029 | H109: 說明
A110: A. 營收拆分（FY2025 依公司揭露比例；FY2026 校準：網路應用產品比例 Assumed，非 AI 依成長率，AI 交換器為殘差）
A111: 網路應用產品（AI 加速卡等） | B111: NT$B | C111: =a25_rev*nap25s -> 156.4416 | D111: =a26_rev*ns26 -> 205.3806
A112: 非 AI（企業、電信、前端交換器、接取） | B112: NT$B | C112: =a25_rev*(1-nap25s-sw25s*af25) -> 41.22112 | D112: =C112*(1+g_nai26) -> 45.343232
A113: AI 資料中心交換器（殘差） | B113: NT$B | C113: =a25_rev*sw25s*af25 -> 50.65728 | D113: =a26_rev-D111-D112 -> 160.03737 | H113: Derived：FY2026 交換器合計＝AI＋非 AI 交換器（見 Recon）
A114: B. AI 交換器（D 欄＝FY2026 校準年；E–G＝FY2027–FY2029）
A115: AI 後端 scale-out 交換器市場 × 情境顆數係數 | B115: US$B | D115: =mkt_26*1 -> 32.0719 | E115: =mkt_27*1*1 -> 61.085 | F115: =mkt_28*um28_B*1 -> 55.204 | G115: =mkt_29*um29_B*1 -> 66.709828
A116: 乙太網路占比 | B116: % | D116: =eth_26 -> 0.75 | E116: =eth_27 -> 0.8 | F116: =eth_28 -> 0.83 | G116: =eth_29 -> 0.85
A117: 非 NVIDIA scale-up 乙太網路交換匣市場 × 係數 | B117: US$B | D117: =su_26*1 -> 3.015 | E117: =su_27*1*1 -> 11.3414 | F117: =su_28*um28_B*1 -> 11.11616 | G117: =su_29*um29_B*1 -> 13.582558
A118: AI 乙太網路交換器市場（scale-out × 乙太網路＋scale-up） | B118: US$B | D118: =D115*D116+D117 -> 27.068925 | E118: =E115*E116+E117 -> 60.2094 | F118: =F115*F116+F117 -> 56.93548 | G118: =G115*G116+G117 -> 70.285911
A119: 白牌占比 | B119: % | D119: =wb_26 -> 0.45 | E119: =wb_27 -> 0.47 | F119: =wb_28 -> 0.48 | G119: =wb_29 -> 0.5
...

Sheet Val
A1: Val — P/E 估值（新台幣）。結論用「現價 ÷ FY2027、FY2028 EPS（模型）」與十年 P/E 規則值（年底落後 P/E，基準為 FY2027 EPS）；目標價為三情境規則值隱含價的加權
A2: 循環位置：智邦不是設備股，不套設備市場見頂年；以本模型營收最高的會計年度為見頂年（比照 Arista、廣達；FY(t)＝CY(t)，不平移）。營收到 FY2029 仍在增加時，見頂年未知，判為中段
A3: 0. 目標價（DCF 與 Comparable 加權；v0.2 新增，Andy 2026-10-25）
A4: 0.1 DCF（股東權益現金流，FY2027–FY2032 明確期＋FY2032 後永續）
A5: 項目 | B5: A | C5: B | D5: C | E5: 說明 | F5: 折現年數 t | G5: 期內占比（基準日後）
A6: 情境 EPS（FY2027–FY2032） | E6: 引用 PL 頁延伸表（上游結束後為收斂法）；三情境欄 B／C／D＝A／B／C
A7: FY2027 | B7: =PL!E213 -> 147.40475 | C7: =PL!E222 -> 147.40475 | D7: =PL!E231 -> 147.40475 | F7: 1 | G7: 1
A8: FY2028 | B8: =PL!F213 -> 169.15791 | C8: =PL!F222 -> 133.82971 | D8: =PL!F231 -> 95.740931 | F8: 2 | G8: 1
A9: FY2029 | B9: =PL!G213 -> 194.51416 | C9: =PL!G222 -> 163.49714 | D9: =PL!G231 -> 110.39055 | F9: 3 | G9: 1
A10: FY2030 | B10: =PL!H213 -> 215.51138 | C10: =PL!H222 -> 180.77377 | D10: =PL!H231 -> 112.53422 | F10: 4 | G10: 1
A11: FY2031 | B11: =PL!I213 -> 233.60862 | C11: =PL!I222 -> 190.58008 | D11: =PL!I231 -> 110.3601 | F11: 5 | G11: 1
A12: FY2032 | B12: =PL!J213 -> 247.62514 | C12: =PL!J222 -> 191.12459 | D12: =PL!J231 -> 103.90828 | F12: 6 | G12: 1
A13: 股東現金流＝EPS ×（1 − tp_g ÷ tp_roe） | B13: =1-MIN(0.8,tp_g/tp_roe) -> 0.91061453 | E13: B 欄＝可發放比例（1 − 再投資率；再投資率＝tp_g ÷ tp_roe，上限 0.8）；下列六列＝EPS × 可發放比例 × 期內占比
A14: FY2027 股東現金流 | B14: =B7*$B$13*$G$7 -> 134.22891 | C14: =C7*$B$13*$G$7 -> 134.22891 | D14: =D7*$B$13*$G$7 -> 134.22891
A15: FY2028 股東現金流 | B15: =B8*$B$13*$G$8 -> 154.03765 | C15: =C8*$B$13*$G$8 -> 121.86727 | D15: =D8*$B$13*$G$8 -> 87.183082
A16: FY2029 股東現金流 | B16: =B9*$B$13*$G$9 -> 177.12742 | C16: =C9*$B$13*$G$9 -> 148.88287 | D16: =D9*$B$13*$G$9 -> 100.52324
A17: FY2030 股東現金流 | B17: =B10*$B$13*$G$10 -> 196.24779 | C17: =C10*$B$13*$G$10 -> 164.61522 | D17: =D10*$B$13*$G$10 -> 102.4753
A18: FY2031 股東現金流 | B18: =B11*$B$13*$G$11 -> 212.72741 | C18: =C11*$B$13*$G$11 -> 173.54499 | D18: =D11*$B$13*$G$11 -> 100.49551
A19: FY2032 股東現金流 | B19: =B12*$B$13*$G$12 -> 225.49105 | C19: =C12*$B$13*$G$12 -> 174.04083 | D19: =D12*$B$13*$G$12 -> 94.620391
A20: 永續價值（FY2032 年底；FY2032 現金流 ×(1＋tp_g) ÷ (tp_r − tp_g)） | B20: =B19*(1+tp_g)/(tp_r-tp_g) -> 3908.5116 | C20: =C19*(1+tp_g)/(tp_r-tp_g) -> 3016.7077 | D20: =D19*(1+tp_g)/(tp_r-tp_g) -> 1640.0868
A21: DCF 情境每股價值（折現率 tp_r） | B21: =MAX(0,B14/(1+tp_r)^$F$7+B15/(1+tp_r)^$F$8+B16/(1+tp_r)^$F$9+B17/(1+tp_r)^$F$10+B18/(1+tp_r)^$F$11+B19/(1+tp_r)^$F$12+B20/(1+tp_r)^$F$12) -> 2982.0721 | C21: =MAX(0,C14/(1+tp_r)^$F$7+C15/(1+tp_r)^$F$8+C16/(1+tp_r)^$F$9+C17/(1+tp_r)^$F$10+C18/(1+tp_r)^$F$11+C19/(1+tp_r)^$F$12+C20/(1+tp_r)^$F$12) -> 2355.8875 | D21: =MAX(0,D14/(1+tp_r)^$F$7+D15/(1+tp_r)^$F$8+D16/(1+tp_r)^$F$9+D17/(1+tp_r)^$F$10+D18/(1+tp_r)^$F$11+D19/(1+tp_r)^$F$12+D20/(1+tp_r)^$F$12) -> 1381.1918 | E21: 基準日 2026 年底；明確期現金流與永續價值依 F 欄年數折現；小於 0 時取 0（Andy 2026-10-25 12:22）
A22: 其中：永續價值現值占比 | B22: =B20/(1+tp_r)^$F$12/B21 -> 0.73983887 | C22: =C20/(1+tp_r)^$F$12/C21 -> 0.72280737 | D22: =D20/(1+tp_r)^$F$12/D21 -> 0.67028072
A23: DCF 目標價（情境加權） | B23: =(tp_wA*B21+tp_wB*C21+tp_wC*D21)*(1+tp_r) -> 2583.6841 | E23: Σ 權重 × 情境價值 ×(1＋tp_r)：推到約 12 個月後
A25: 0.2 Comparable（市場主流同業前瞻 P/E）
A26: 同業與前瞻 P/E | B26: 代號 | C26: 前瞻 12 月 P/E | D26: 日期 | E26: 來源 | F26: 標記
A27: Arista Networks | B27: ANET | C27: 37.06 | D27: 2026-10-23 | E27: stockanalysis.com 統計頁（Forward PE） | F27: Interested-party（資料商彙整賣方預估）
A28: Celestica | B28: CLS | C28: 16.65 | D28: 2026-10-23 | E28: 同上 | F28: Interested-party（同上）
A29: 緯穎 | B29: 6669.TW | C29: 11.73 | D29: 2026-10-21 | E29: 同上（台股頁，價格延遲） | F29: Interested-party（同上）
A30: 廣達 | B30: 2382.TW | C30: 11.52 | D30: 2026-10-21 | E30: 同上（台股頁，價格延遲） | F30: Interested-party（同上）
A31: 同業選擇 | E31: 法人常用的資料中心網通與 AI 伺服器 ODM 同業（Arista 為品牌交換器、Celestica 為白牌交換器直接競爭者、緯穎與廣達為台灣 AI 伺服器 ODM）；不含 A 股（Andy 11:53）。前瞻 P/E 為資料商的未來 12 個月共識 EPS
A32: 同業前瞻 P/E 中位數 | B32: =MEDIAN(C27:C30) -> 14.19
A33: 各情境 12 個月後的前瞻 EPS | B33: =2/12*PL!E213+10/12*PL!F213 -> 165.53238 | C33: =2/12*PL!E222+10/12*PL!F222 -> 136.09221 | D33: =2/12*PL!E231+10/12*PL!F231 -> 104.35157 | E33: 會計年度＝日曆年：約 12 個月後（2027-10 底）的未來 12 個月＝2027-11～2028-10（2/12 × FY2027＋10/12 × FY2028）
A34: 12 個月後的前瞻 EPS（情境加權） | B34: =tp_wA*B33+tp_wB*C33+tp_wC*D33 -> 138.57614
A35: Comparable 目標價 | B35: =B32*B34 -> 1966.3954 | E35: 同業前瞻 P/E 中位數 × 12 個月後的前瞻 EPS（情境加權）
A37: 0.3 結論
A38: 項目 | B38: 數值 | C38: 對照 | D38: 對照 | E38: 說明
A39: 目標價（DCF 與 Comparable 加權） | B39: =tp_w_dcf*B23+(1-tp_w_dcf)*B35 -> 2275.0397 | E39: ="DCF 權重 "&TEXT(tp_w_dcf,"0%")&"、Comparable 權重 "&TEXT(1-tp_w_dcf,"0%")&"（In 頁 tp_w_dcf，Andy 可改）" -> DCF 權重 50%、Comparable 權重 50%（In 頁 tp_w_dcf，Andy 可改）
A40: Comparable 目標價（市場主流同業法） | B40: =B35 -> 1966.3954
A41: 市場共識目標價 | B41: =cons_tp -> 3500 | E41: FactSet：10 位分析師目標價（2026-10-14，鉅亨網轉述）；Interested-party
A42: 上檔空間：加權目標價 | B42: =B39/px-1 -> 0.28171253
A43: 上檔空間：Comparable 目標價 | B43: =B40/px-1 -> 0.10782837
A44: 與市場共識目標價的差距：EPS 因素 | B44: =B34/C44-1 -> -0.14605892 | C44: =2/12*cons_eps27+10/12*cons_eps28 -> 162.27833 | E44: B＝我們的前瞻 EPS（情境加權）÷ 共識前瞻 EPS − 1；C＝共識前瞻 EPS（同權重的共識 EPS：2/12 × FactSet FY2027 中位數 120.82＋10/12 × FY2028 中位數 170.57）
A45: 與市場共識目標價的差距：倍數因素 | B45: =C45/B32-1 -> 0.51993533 | C45: =B41/C44 -> 21.567882 | D45: =B32 -> 14.19 | E45: C＝市場共識目標價 ÷ 共識前瞻 EPS 隱含的倍數；D＝同業中位數；B＝C ÷ D − 1
A46: 價格帶（DCF 不如預期～順利） | B46: =D21*(1+tp_r) -> 1519.311 | C46: =B21*(1+tp_r) -> 3280.2794 | E46: B＝C 情境 DCF 價值、C＝A 情境 DCF 價值（皆推到 12 個月後）
A47: 檢查用：現價 ÷ 各情境 FY2028 EPS | B47: =px/PL!F213 -> 10.493154 | C47: =px/PL!F222 -> 13.263124 | D47: =px/PL!F231 -> 18.539615
A48: 歷史倍數檢查：現價隱含 P/E 的十年分位（A／B／C） | B48: =IF(B47<MIN(B115:B124),0,IF(B47>MAX(B115:B124),1,PERCENTRANK(B115:B124,B47))) -> 0 | C48: =IF(C47<MIN(B115:B124),0,IF(C47>MAX(B115:B124),1,PERCENTRANK(B115:B124,C47))) -> 0.0545 | D48: =IF(D47<MIN(B115:B124),0,IF(D47>MAX(B115:B124),1,PERCENTRANK(B115:B124,D47))) -> 0.442 | E48: 上一列在 2016–2025 年底 P/E 分布（Val!B115:B124）的分位（PERCENTRANK；低於最小＝0、高於最大＝1）；只作檢查，不進目標價
A49: 目標價方法 | B49: DCF：股東現金流＝EPS ×（1 − tp_g ÷ tp_roe），tp_r 10%、tp_g 4%、tp_roe 近三年平均 44.75%（再投資率約 9%）；基準日 2026 年底，FY2027 起逐年折現，FY2032 後永續。Comparable：Arista、Celestica、緯穎、廣達前瞻 P/E 中位數 × 12 個月後前瞻 EPS。偏誤方向：伺服器 ODM（緯穎、廣達）毛利率與成長低於智邦，中位數偏低（Comparable 偏保守）；C 情境 FY2030 起淨利率收斂到 FY2029 × 0.8（Assumed）；歷史分位用十年年底落後 P/E（companiesmarketcap）；永續價值占 DCF 價值過半（Sens 頁）。
A50: 檢查：情境權重合計（應為 1） | B50: =ROUND(tp_wA+tp_wB+tp_wC,6) -> 1
A51: 上檔空間級距 | B51: =IF(B42>0.5,"大於 50%",IF(B42>0.25,"25%–50%",IF(B42>=0,"0%–25%",IF(B42>=-0.25,"0%～−25%",IF(B42>=-0.5,"−25%～−50%","小於 −50%"))))) -> 25%–50% | E51: 以「上檔空間：加權目標價」分六級（Andy 2026-10-25 14:00）
A52: 投資建議 | B52: =IF(B42>0.5,"強力買進",IF(B42>0.25,"買進",IF(B42>=-0.25,"中立",IF(B42>=-0.5,"放空","強力放空")))) -> 買進 | E52: 依上檔空間固定規則（Andy 2026-10-25 14:17）：大於 +50% 強力買進、+25%～+50% 買進、−25%～+25% 中立、−50%～−25% 放空、小於 −50% 強力放空
A54: 舊法：規則值情境加權（參考）
A55: 項目 | B55: 值 | C55: 相對現價或權重 B | D55: 權重 C | E55: 說明
A56: 規則值情境加權價（參考，非目標價） | B56: =tp_wA*E83+tp_wB*E84+tp_wC*E85 -> 3452.5141 | E56: 約 FY2027 年底價格、未折現；權重見 In 頁 tp_wA／tp_wB／tp_wC
A57: 相對現價（參考） | B57: =B56/px-1 -> 0.94507839
A58: 情境 A 隱含價（樂觀） | B58: =E83 -> 3676.2746 | C58: =E83/px-1 -> 1.0711406 | E58: C 欄＝相對現價
A59: 情境 B 隱含價（基準） | B59: =E84 -> 3676.2746 | C59: =E84/px-1 -> 1.0711406
A60: 情境 C 隱含價（下檔） | B60: =E85 -> 2557.4725 | C60: =E85/px-1 -> 0.44082957
A61: 情境權重 A／B／C | B61: =tp_wA -> 0.3 | C61: =tp_wB -> 0.5 | D61: =tp_wC -> 0.2
A62: 舊法說明 | B62: P/E：各情境 FY2027 EPS × 十年（2016–2025）年底 P/E 依循環位置取分位（見頂 25 分位、中段中位數、谷底 75 分位；兩個資料商來源分別取分位再平均）；權重 A 0.3、B 0.5、C 0.2（In 頁，Andy 可改）。偏誤：十年倍數含 2016–2019 年企業網通期的低倍數（約 11–19x），也含 2020、2023–24 年的高倍數期，方向不明；FY2027 三情境 EPS 相同，情境差異只來自循環位置判定
A63: 權重合計（應為 1） | B63: =tp_wA+tp_wB+tp_wC -> 1
A64: 1. 價格與市場隱含倍數
A65: 項目 | B65: A | C65: B | D65: C | E65: 說明
A66: 現價（2026-10-22 收盤） | B66: =px -> 1775
A67: 現價 ÷ FY2026 EPS（錨點） | B67: =px/PL!D14 -> 20.743094 | C67: =px/PL!D27 -> 20.743094 | D67: =px/PL!D40 -> 20.743094
A68: 現價 ÷ FY2027 EPS（模型） | B68: =px/PL!E14 -> 12.041674 | C68: =px/PL!E27 -> 12.041674 | D68: =px/PL!E40 -> 12.041674 | E68: FY2027 三情境相同（顆數係數從 CY2028 開始）
A69: 現價 ÷ FY2028 EPS（模型） | B69: =px/PL!F14 -> 10.493154 | C69: =px/PL!F27 -> 13.263124 | D69: =px/PL!F40 -> 18.539615
A70: 現價 ÷ FY2029 EPS（模型） | B70: =px/PL!G14 -> 9.1252997 | C70: =px/PL!G27 -> 10.856459 | D70: =px/PL!G40 -> 16.079275
A71: 未來 12 月 EPS（模型 A）≈ 0.2 × FY2026＋0.8 × FY2027 | B71: =0.2*PL!D14+0.8*PL!E14 -> 135.03793
A72: 現價 ÷ 未來 12 月 EPS（模型 A） | B72: =px/B71 -> 13.144455
A73: 近 12 月 P/E（鉅亨，10-22） | B73: =pe_ttm -> 27.88
A75: 2. 循環位置（本模型營收最高年；FY(t)＝CY(t)）
A76: 情境 | B76: 營收最高年（FY2026–FY2029） | C76: FY2027 判定 | D76: 規則倍數（P/E） | E76: 見頂年是否未知 | F76: 說明
A77: A | B77: =INDEX({2026,2027,2028,2029},MATCH(MAX(PL!D84:G84),PL!D84:G84,0)) -> 2029 | C77: =IF(B77=2029,"中段",IF(2027<B77,"中段",IF(2027=B77,"見頂","谷底"))) -> 中段 | D77: =IF(C77="見頂",pe_peak,IF(C77="谷底",pe_trough,pe_mid)) -> 24.94 | E77: =IF(B77=2029,"是：營收到觀測期末仍在增加","否") -> 是：營收到觀測期末仍在增加 | F77: tools/cycle_position.py excel_rule；營收最高年取代設備市場見頂年
A78: B | B78: =INDEX({2026,2027,2028,2029},MATCH(MAX(PL!D132:G132),PL!D132:G132,0)) -> 2029 | C78: =IF(B78=2029,"中段",IF(2027<B78,"中段",IF(2027=B78,"見頂","谷底"))) -> 中段 | D78: =IF(C78="見頂",pe_peak,IF(C78="谷底",pe_trough,pe_mid)) -> 24.94 | E78: =IF(B78=2029,"是：營收到觀測期末仍在增加","否") -> 是：營收到觀測期末仍在增加 | F78: 同上
A79: C | B79: =INDEX({2026,2027,2028,2029},MATCH(MAX(PL!D180:G180),PL!D180:G180,0)) -> 2027 | C79: =IF(B79=2029,"中段",IF(2027<B79,"中段",IF(2027=B79,"見頂","谷底"))) -> 見頂 | D79: =IF(C79="見頂",pe_peak,IF(C79="谷底",pe_trough,pe_mid)) -> 17.35 | E79: =IF(B79=2029,"是：營收到觀測期末仍在增加","否") -> 否 | F79: 同上
A81: 3. 規則值隱含股價（新台幣；約 FY2027 年底，未折現）＝ FY2027 EPS × 規則倍數
A82: 情境 | B82: FY2027 EPS | C82: 規則基準 EPS | D82: 規則倍數 | E82: 隱含股價 | F82: 相對現價 | G82: 現價 ÷ 基準 EPS
A83: A | B83: =PL!E14 -> 147.40475 | C83: =B83 -> 147.40475 | D83: =D77 -> 24.94 | E83: =C83*D83 -> 3676.2746 | F83: =E83/px-1 -> 1.0711406 | G83: =px/C83 -> 12.041674
A84: B | B84: =PL!E27 -> 147.40475 | C84: =B84 -> 147.40475 | D84: =D78 -> 24.94 | E84: =C84*D84 -> 3676.2746 | F84: =E84/px-1 -> 1.0711406 | G84: =px/C84 -> 12.041674
A85: C | B85: =PL!E40 -> 147.40475 | C85: =B85 -> 147.40475 | D85: =D79 -> 17.35 | E85: =C85*D85 -> 2557.4725 | F85: =E85/px-1 -> 0.44082957 | G85: =px/C85 -> 12.041674
A86: 4. What must be true：FY2027 年底價 ＝ 現價 ×（1＋報酬）所需的倍數（FY2028 EPS；約 2027 年底的價格看下一年 EPS）
A87: FY2027 年底價 ÷ 現價 | B87: 所需倍數（÷ FY2028 EPS，A） | C87: 所需倍數（÷ FY2028 EPS，C） | D87: 對照：十年中位數
A88: 1 | B88: =px*A88/PL!F14 -> 10.493154 | C88: =px*A88/PL!F40 -> 18.539615 | D88: =pe_mid -> 24.94
A89: 1.1 | B89: =px*A89/PL!F14 -> 11.54247 | C89: =px*A89/PL!F40 -> 20.393577 | D89: =pe_mid -> 24.94
A90: 1.21 | B90: =px*A90/PL!F14 -> 12.696716 | C90: =px*A90/PL!F40 -> 22.432934 | D90: =pe_mid -> 24.94
A91: 1.5 | B91: =px*A91/PL!F14 -> 15.739731 | C91: =px*A91/PL!F40 -> 27.809423 | D91: =pe_mid -> 24.94
A92: 2 | B92: =px*A92/PL!F14 -> 20.986308 | C92: =px*A92/PL!F40 -> 37.07923 | D92: =pe_mid -> 24.94
A93: 讀法：1.00＝價格不變、1.21＝一年約 21%。所需倍數低於歷史中位數時，現價相對便宜；倍數是否合理，另看前瞻 P/E 歷史（Bloomberg）。本版未做先驗，無 Andy 合理 P/E 對照。
A110: 6. 十年倍數與規則值（2016–2025 年底；見頂年 25 分位、中段中位數、谷底 75 分位）
A111: 規則（Andy 2026-10-13）：合理倍數＝2016–2025 年底 P/E 依循環位置取分位，兩個來源分別取分位再平均。2016–2019 年為企業網通期（約 11–19x）；2020、2023–2024 年 AI 期重新定價（30–36x）；2025 年 EPS 倍增使年底 P/E 回落到約 25x。
A113: P/E：十年歷史倍數
A114: 年底 | B114: companiesmarketcap（年底 P/E） | C114: Goodinfo（年底收盤 ÷ EPS） | D114: 標記／說明
A115: 2016 | B115: 11.4 | D115: companiesmarketcap（年底 P/E）：Interested-party（資料商；2016–2025 共 10 年）；Goodinfo（年底收盤 ÷ EPS）：Derived（資料商收盤價與 EPS；2018–2025 共 8 年，2016–2017 年底收盤：未找到）
A116: 2017 | B116: 18.6
A117: 2018 | B117: 15.8 | C117: =98.6/5.33 -> 18.499062
A118: 2019 | B118: 16.3 | C118: =168/8.91 -> 18.855219
A119: 2020 | B119: 31.7 | C119: =316/9.07 -> 34.840132
A120: 2021 | B120: 28.6 | C120: =260/8.44 -> 30.805687
A121: 2022 | B121: 15.2 | C121: =234.5/14.64 -> 16.01776
A122: 2023 | B122: 31.7 | C122: =523/15.99 -> 32.707942
...

Sheet Recon
A1: Recon — 本模型 vs 共識（FactSet 2026-10-14）、法人拆分與研調份額。只作事後對照，不為對上數字而調參數
A3: 項目 | B3: 對照值 | C3: 模型 A | D3: 差距 A | E3: 模型 B | F3: 差距 B | G3: 模型 C | H3: 差距 C | I3: 對照來源 | J3: 說明
A4: A. 共識（校準未使用）
A5: FY2026 營收 vs 共識 | B5: =cons_rev26 -> 412.45 | C5: =PL!D84 -> 410.7612 | D5: =C5/B5-1 -> -0.0040945569 | E5: =PL!D132 -> 410.7612 | F5: =E5/B5-1 -> -0.0040945569 | G5: =PL!D180 -> 410.7612 | H5: =G5/B5-1 -> -0.0040945569 | I5: FactSet 中位數 | J5: 錨點＝實績＋3Q 營收實績＋4Q 假設
A6: FY2026 EPS vs 共識 | B6: =cons_eps26 -> 85.85 | C6: =PL!D104 -> 85.570649 | D6: =C6/B6-1 -> -0.0032539377 | E6: =PL!D152 -> 85.570649 | F6: =E6/B6-1 -> -0.0032539377 | G6: =PL!D200 -> 85.570649 | H6: =G6/B6-1 -> -0.0032539377 | I6: FactSet 中位數
A7: FY2027 營收 vs 共識 | B7: =cons_rev27 -> 551.5 | C7: =PL!E84 -> 650.909 | D7: =C7/B7-1 -> 0.18025203 | E7: =PL!E132 -> 650.909 | F7: =E7/B7-1 -> 0.18025203 | G7: =PL!E180 -> 650.909 | H7: =G7/B7-1 -> 0.18025203 | I7: FactSet 中位數
A8: FY2027 EPS vs 共識 | B8: =cons_eps27 -> 120.82 | C8: =PL!E104 -> 147.40475 | D8: =C8/B8-1 -> 0.22003604 | E8: =PL!E152 -> 147.40475 | F8: =E8/B8-1 -> 0.22003604 | G8: =PL!E200 -> 147.40475 | H8: =G8/B8-1 -> 0.22003604 | I8: FactSet 中位數 | J8: 分析師區間 86.97–139.61
A9: FY2028 EPS vs 共識 | B9: =cons_eps28 -> 170.57 | C9: =PL!F104 -> 169.15791 | D9: =C9/B9-1 -> -0.0082786647 | E9: =PL!F152 -> 133.82971 | F9: =E9/B9-1 -> -0.21539717 | G9: =PL!F200 -> 95.740931 | H9: =G9/B9-1 -> -0.43870006 | I9: FactSet 中位數
A10: B. 拆分與份額
A11: FY2026 交換器 ÷ 營收（AI＋非 AI 交換器，推導）vs 法人 | B11: =br_sw26 -> 0.48 | C11: =(PL!D76+a25_rev*sw25s*(1-af25)*(1+g_nai26))/PL!D84 -> 0.48005031 | D11: =C11-B11 -> 5.0306601e-05 | E11: =(PL!D124+a25_rev*sw25s*(1-af25)*(1+g_nai26))/PL!D132 -> 0.48005031 | F11: =E11-B11 -> 5.0306601e-05 | G11: =(PL!D172+a25_rev*sw25s*(1-af25)*(1+g_nai26))/PL!D180 -> 0.48005031 | H11: =G11-B11 -> 5.0306601e-05 | I11: 美系外資 2026-03 | J11: 非 AI 交換器假設與非 AI 營收同成長
A12: FY2026 智邦 ÷ AI 乙太網路交換器市場 vs 1 − Celestica、NVIDIA 合計（上限） | B12: =1-dell_top2 -> 0.5 | C12: =PL!D76/fx/PL!D70 -> 0.18475679 | D12: =C12-B12 -> -0.31524321 | E12: =PL!D124/fx/PL!D118 -> 0.18475679 | F12: =E12-B12 -> -0.31524321 | G12: =PL!D172/fx/PL!D166 -> 0.18475679 | H12: =G12-B12 -> -0.31524321 | I12: Dell'Oro 2025 | J12: 智邦未進前三，應低於上限
A13: FY2027 AI ÷ 營收 | C13: =PL!E91 -> 0.92615892 | E13: =PL!E139 -> 0.92615892 | G13: =PL!E187 -> 0.92615892 | I13: —
A14: FY2027 智邦 AI 營收 ÷ AI IT 資本支出 | C14: =(PL!E76+PL!E81)/fx/itc_27 -> 0.012034952 | E14: =(PL!E124+PL!E129)/fx/itc_27 -> 0.012034952 | G14: =(PL!E172+PL!E177)/fx/itc_27 -> 0.012034952 | I14: markets/network
A15: FY2026 每顆 Trainium 的智邦營收（千美元） | C15: =PL!D79/fx -> 3.2090719 | E15: =PL!D127/fx -> 3.2090719 | G15: =PL!D175/fx -> 3.2090719 | I15: — | J15: 晶片若為客供，約為加速卡＋L10 加工價值
A16: C. 校準
A17: 交換器與其他毛利率（Derived） | C17: =PL!D94 -> 0.21958925 | E17: =PL!D142 -> 0.21958925 | G17: =PL!D190 -> 0.21958925 | I17: FY2026 錨點 | J17: 網路應用產品毛利率＝此值 − d_nap
A18: FY2027 毛利率 vs FY2026（百分點） | B18: =a26_gp/a26_rev -> 0.18958925 | C18: =PL!E96 -> 0.19829105 | D18: =C18-B18 -> 0.0087017992 | E18: =PL!E144 -> 0.19829105 | F18: =E18-B18 -> 0.0087017992 | G18: =PL!E192 -> 0.19829105 | H18: =G18-B18 -> 0.0087017992 | I18: 錨點
A19: 3Q26 EPS（模型）vs 法人估計 23.91 | B19: 23.91 | C19: =Q!E13 -> 25.059433 | D19: =C19/B19-1 -> 0.048073326 | E19: =Q!E13 -> 25.059433 | F19: =E19/B19-1 -> 0.048073326 | G19: =Q!E13 -> 25.059433 | H19: =G19/B19-1 -> 0.048073326 | I19: 工商時報 2026-09-29
A20: D. 預留
A21: R4 產業部署路徑（markets/deploy_path/，尚未建立）：上線後以智邦 AI 營收 ÷ 部署 GW 計算每 GW 營收 | J21: 預留列：本版無數值

Sheet Sens
A1: Sens — 一次動一個輸入（情境 A；有效份額、每顆 Trainium 營收、交換器與其他毛利率在每個案例內依 FY2026 錨點重算，FY2026 營收與毛利恆等於錨點）：對 FY2027、FY2028 的營收、AI 交換器營收、毛利率與 EPS 的影響。每個案例是一個完整推導區塊（本頁下方）
A3: 案例 | B3: 設定 | C3: FY2027 營收 | D3: FY2027 AI 交換器營收 | E3: FY2027 毛利率 | F3: FY2027 EPS | G3: FY2027 EPS 相對基準 | H3: FY2028 營收 | I3: FY2028 AI 交換器營收 | J3: FY2028 毛利率 | K3: FY2028 EPS | L3: FY2028 EPS 相對基準
A4: 基準（情境 A） | B4: PL 區塊 A | C4: =PL!E84 -> 650.909 | D4: =PL!E76 -> 371.792 | E4: =PL!E96 -> 0.19829105 | F4: =PL!E104 -> 147.40475 | G4: =F4/F$4-1 -> 0 | H4: =PL!F84 -> 738.7062 | I4: =PL!F76 -> 426.37891 | J4: =PL!F96 -> 0.19832015 | K4: =PL!F104 -> 169.15791 | L4: =K4/K$4-1 -> 0
A5: 白牌份額流失（低） | B5: 份額相對值 2027 0.80、2028 0.70、2029 0.65（Celestica、新 ODM、NVIDIA 搶占） | C5: =E64 -> 576.5506 | D5: =E56 -> 297.4336 | E5: =E76 -> 0.19554419 | F5: =E84 -> 127.18444 | G5: =F5/F$4-1 -> -0.13717547 | H5: =F64 -> 626.50122 | I5: =F56 -> 314.17394 | J5: =F76 -> 0.1945109 | K5: =F84 -> 138.37995 | L5: =K5/K$4-1 -> -0.18194809
A6: 白牌份額提升（高） | B6: 份額相對值 1.10 | C6: =E112 -> 688.0882 | D6: =E104 -> 408.97119 | E6: =E124 -> 0.19944184 | F6: =E132 -> 157.51491 | G6: =F6/F$4-1 -> 0.068587737 | H6: =F112 -> 806.02918 | I6: =F104 -> 493.7019 | J6: =F124 -> 0.20009663 | K6: =F132 -> 187.68851 | L6: =K6/K$4-1 -> 0.10954615
A7: 白牌占比 低 | B7: 35%（持平） | C7: =E160 -> 635.08806 | D7: =E152 -> 355.97106 | E7: =E172 -> 0.19776048 | F7: =E180 -> 143.10256 | G7: =F7/F$4-1 -> -0.029186271 | H7: =F160 -> 712.05751 | I7: =F152 -> 399.73023 | J7: =F172 -> 0.19752415 | K7: =F180 -> 161.83452 | L7: =K7/K$4-1 -> -0.04329318
A8: 白牌占比 高 | B8: 2026 55% → 2029 60% | C8: =E208 -> 648.03246 | D8: =E200 -> 368.91546 | E8: =E220 -> 0.19819651 | F8: =E228 -> 146.62254 | G8: =F8/F$4-1 -> -0.0053065947 | H8: =F208 -> 733.86098 | I8: =F200 -> 421.5337 | J8: =F220 -> 0.19817972 | K8: =F228 -> 167.82608 | L8: =K8/K$4-1 -> -0.0078732685
A9: 乙太網路占比 低 | B9: 2026 70% → 2029 75% | C9: =E256 -> 642.24524 | D9: =E248 -> 363.12823 | E9: =E268 -> 0.19800374 | F9: =E276 -> 145.04881 | G9: =F9/F$4-1 -> -0.0159828 | H9: =F256 -> 726.00591 | I9: =F248 -> 413.67863 | J9: =F268 -> 0.19794808 | K9: =F276 -> 165.67182 | L9: =K9/K$4-1 -> -0.020608492
A10: 乙太網路占比 高 | B10: 2026 80% → 2029 92% | C10: =E304 -> 658.60366 | D10: =E296 -> 379.48666 | E10: =E316 -> 0.19853988 | F10: =E324 -> 149.49717 | G10: =F10/F$4-1 -> 0.01419503 | H10: =F304 -> 742.18007 | I10: =F296 -> 429.85278 | J10: =F316 -> 0.1984197 | K10: =F324 -> 170.08867 | L10: =K10/K$4-1 -> 0.0055023516
A11: AI 交換器市場 ×0.8 | B11: FY2027 起交換器市場 ×0.8（供給受限或內容不如預期） | C11: =E352 -> 576.5506 | D11: =E344 -> 297.4336 | E11: =E364 -> 0.19554419 | F11: =E372 -> 127.18444 | G11: =F11/F$4-1 -> -0.13717547 | H11: =F352 -> 653.43041 | I11: =F344 -> 341.10313 | J11: =F364 -> 0.19554443 | K11: =F372 -> 145.81707 | L11: =K11/K$4-1 -> -0.13798253
A12: AI 交換器市場 ×1.2 | B12: ×1.2 | C12: =E400 -> 725.2674 | D12: =E392 -> 446.15039 | E12: =E412 -> 0.20047466 | F12: =E420 -> 167.62507 | G12: =F12/F$4-1 -> 0.13717547 | H12: =F400 -> 823.98198 | I12: =F392 -> 511.6547 | J12: =F412 -> 0.20052134 | K12: =F420 -> 192.50066 | L12: =K12/K$4-1 -> 0.13799384
A13: Trainium 份額流失 | B13: 相對值 2027 0.65、2028 0.55、2029 0.50（第二供應商、Trainium 4） | C13: =E448 -> 586.72756 | D13: =E440 -> 371.792 | E13: =E460 -> 0.20252459 | F13: =E468 -> 135.36751 | G13: =F13/F$4-1 -> -0.081661166 | H13: =F448 -> 646.28493 | I13: =F440 -> 426.37891 | J13: =F460 -> 0.20385882 | K13: =F468 -> 151.60989 | L13: =K13/K$4-1 -> -0.10373748
A14: Trainium 顆數 ×0.8 | B14: FY2027 起 Trainium 顆數 ×0.8 | C14: =E496 -> 604.69836 | D14: =E488 -> 371.792 | E14: =E508 -> 0.20124861 | F14: =E516 -> 138.73794 | G14: =F14/F$4-1 -> -0.058796039 | H14: =F496 -> 686.33414 | I14: =F488 -> 426.37891 | J14: =F508 -> 0.20127558 | K14: =F516 -> 159.24389 | L14: =K14/K$4-1 -> -0.058608065
A15: 網路應用產品占比 42% | B15: FY2026 拆分：網路應用產品 42%（交換器較大） | C15: =E544 -> 690.28152 | D15: =E536 -> 448.13303 | E15: =E556 -> 0.1979192 | F15: =E564 -> 156.57107 | G15: =F15/F$4-1 -> 0.062184645 | H15: =F544 -> 784.35806 | I15: =F536 -> 513.92842 | J15: =F556 -> 0.19796306 | K15: =F564 -> 179.89677 | L15: =K15/K$4-1 -> 0.06348427
A16: 網路應用產品占比 58% | B16: FY2026 拆分：58% | C16: =E592 -> 611.53647 | D16: =E584 -> 295.45096 | E16: =E604 -> 0.1980927 | F16: =E612 -> 137.70688 | G16: =F16/F$4-1 -> -0.065790785 | H16: =F592 -> 693.05433 | I16: =F584 -> 338.8294 | J16: =F604 -> 0.19809192 | K16: =F612 -> 157.8038 | L16: =K16/K$4-1 -> -0.067121366
A17: 毛利率差距 3pt | B17: 網路應用產品毛利率只低 3 個百分點 | C17: =E640 -> 650.909 | D17: =E632 -> 371.792 | E17: =E652 -> 0.19394015 | F17: =E660 -> 143.42195 | G17: =F17/F$4-1 -> -0.02701951 | H17: =F640 -> 738.7062 | I17: =F632 -> 426.37891 | J17: =F652 -> 0.1939547 | K17: =F660 -> 164.62277 | L17: =K17/K$4-1 -> -0.026810078
A18: 毛利率差距 10pt | B18: 低 10 個百分點 | C18: =E688 -> 650.909 | D18: =E680 -> 371.792 | E18: =E700 -> 0.20409225 | F18: =E708 -> 152.71516 | G18: =F18/F$4-1 -> 0.036026013 | H18: =F688 -> 738.7062 | I18: =F680 -> 426.37891 | J18: =F700 -> 0.20414075 | K18: =F708 -> 175.20476 | L18: =K18/K$4-1 -> 0.035746771
A19: 淨利 ÷ 營業利益 0.75 | B19: 匯損或稅率上升 | C19: =E736 -> 650.909 | D19: =E728 -> 371.792 | E19: =E748 -> 0.19829105 | F19: =E756 -> 138.19196 | G19: =F19/F$4-1 -> -0.0625 | H19: =F736 -> 738.7062 | I19: =F728 -> 426.37891 | J19: =F748 -> 0.19832015 | K19: =F756 -> 158.58554 | L19: =K19/K$4-1 -> -0.0625
A20: 營業費用率 +0.5pt | B20: 營業費用額外 +0.5% × 營收 | C20: =E784 -> 650.909 | D20: =E776 -> 371.792 | E20: =E796 -> 0.19829105 | F20: =E804 -> 142.82776 | G20: =F20/F$4-1 -> -0.031050487 | H20: =F784 -> 738.7062 | I20: =F776 -> 426.37891 | J20: =F796 -> 0.19832015 | K20: =F804 -> 163.96356 | L20: =K20/K$4-1 -> -0.030707118
A21: 顆數情境 B | B21: CY2028 ×0.8、CY2029 ×0.85 | C21: =PL!E132 -> 650.909 | D21: =PL!E124 -> 371.792 | E21: =PL!E144 -> 0.19829105 | F21: =PL!E152 -> 147.40475 | G21: =F21/F$4-1 -> 0 | H21: =PL!F132 -> 601.05836 | I21: =PL!F124 -> 341.10313 | J21: =PL!F144 -> 0.19867731 | K21: =PL!F152 -> 133.82971 | L21: =K21/K$4-1 -> -0.20884748
A22: 顆數情境 C | B22: CY2028–29 ×0.6 | C22: =PL!E180 -> 650.909 | D22: =PL!E172 -> 371.792 | E22: =PL!E192 -> 0.19829105 | F22: =PL!E200 -> 147.40475 | G22: =F22/F$4-1 -> 0 | H22: =PL!F180 -> 463.41053 | I22: =PL!F172 -> 255.82735 | J22: =PL!F192 -> 0.19924666 | K22: =PL!F200 -> 95.740931 | L22: =K22/K$4-1 -> -0.43401446
A24: 讀法：FY2027 三情境相同；顆數情境 B、C 的差異從 FY2028 起（交換器與 Trainium 同時縮放）。拆分案例（網路應用產品占比）改變的是 FY2026 校準的起點，FY2026 合計恆等於錨點。
A26: 目標價參數敏感度（v0.2）：加權目標價（Val 第 0 節）一次動一個參數；PL 延伸期的收斂路徑不隨 tp_g 變動，tp_g 只改再投資率與永續成長
A27: 參數 | B27: 設定（低／高） | C27: 低：加權目標價 | D27: 低：相對基準 | E27: 高：加權目標價 | F27: 高：相對基準 | G27: 基準加權目標價
A28: tp_r ±1pt | B28: 折現率 −1pt／＋1pt | C28: =tp_w_dcf*(tp_wA*(MAX(0,Val!B7*Val!$G$7*(1-MIN(0.8,tp_g/tp_roe))/(1+(tp_r-0.01))^Val!$F$7+Val!B8*Val!$G$8*(1-MIN(0.8,tp_g/tp_roe))/(1+(tp_r-0.01))^Val!$F$8+Val!B9*Val!$G$9*(1-MIN(0.8,tp_g/tp_roe))/(1+(tp_r-0.01))^Val!$F$9+Val!B10*Val!$G$10*(1-MIN(0.8,tp_g/tp_roe))/(1+(tp_r-0.01))^Val!$F$10+Val!B11*Val!$G$11*(1-MIN(0.8,tp_g/tp_roe))/(1+(tp_r-0.01))^Val!$F$11+Val!B12*Val!$G$12*(1-MIN(0.8,tp_g/tp_roe))/(1+(tp_r-0.01))^Val!$F$12+Val!B12*(1-MIN(0.8,tp_g/tp_roe))*(1+tp_g)/((tp_r-0.01)-tp_g)/(1+(tp_r-0.01))^Val!$F$12))+tp_wB*(MAX(0,Val!C7*Val!$G$7*(1-MIN(0.8,tp_g/tp_roe))/(1+(tp_r-0.01))^Val!$F$7+Val!C8*Val!$G$8*(1-MIN(0.8,tp_g/tp_roe))/(1+(tp_r-0.01))^Val!$F$8+Val!C9*Val!$G$9*(1-MIN(0.8,tp_g/tp_roe))/(1+(tp_r-0.01))^Val!$F$9+Val!C10*Val!$G$10*(1-MIN(0.8,tp_g/tp_roe))/(1+(tp_r-0.01))^Val!$F$10+Val!C11*Val!$G$11*(1-MIN(0.8,tp_g/tp_roe))/(1+(tp_r-0.01))^Val!$F$11+Val!C12*Val!$G$12*(1-MIN(0.8,tp_g/tp_roe))/(1+(tp_r-0.01))^Val!$F$12+Val!C12*(1-MIN(0.8,tp_g/tp_roe))*(1+tp_g)/((tp_r-0.01)-tp_g)/(1+(tp_r-0.01))^Val!$F$12))+tp_wC*(MAX(0,Val!D7*Val!$G$7*(1-MIN(0.8,tp_g/tp_roe))/(1+(tp_r-0.01))^Val!$F$7+Val!D8*Val!$G$8*(1-MIN(0.8,tp_g/tp_roe))/(1+(tp_r-0.01))^Val!$F$8+Val!D9*Val!$G$9*(1-MIN(0.8,tp_g/tp_roe))/(1+(tp_r-0.01))^Val!$F$9+Val!D10*Val!$G$10*(1-MIN(0.8,tp_g/tp_roe))/(1+(tp_r-0.01))^Val!$F$10+Val!D11*Val!$G$11*(1-MIN(0.8,tp_g/tp_roe))/(1+(tp_r-0.01))^Val!$F$11+Val!D12*Val!$G$12*(1-MIN(0.8,tp_g/tp_roe))/(1+(tp_r-0.01))^Val!$F$12+Val!D12*(1-MIN(0.8,tp_g/tp_roe))*(1+tp_g)/((tp_r-0.01)-tp_g)/(1+(tp_r-0.01))^Val!$F$12)))*(1+(tp_r-0.01))+(1-tp_w_dcf)*Val!$B$35 -> 2522.2619 | D28: =C28/G28-1 -> 0.10866717 | E28: =tp_w_dcf*(tp_wA*(MAX(0,Val!B7*Val!$G$7*(1-MIN(0.8,tp_g/tp_roe))/(1+(tp_r+0.01))^Val!$F$7+Val!B8*Val!$G$8*(1-MIN(0.8,tp_g/tp_roe))/(1+(tp_r+0.01))^Val!$F$8+Val!B9*Val!$G$9*(1-MIN(0.8,tp_g/tp_roe))/(1+(tp_r+0.01))^Val!$F$9+Val!B10*Val!$G$10*(1-MIN(0.8,tp_g/tp_roe))/(1+(tp_r+0.01))^Val!$F$10+Val!B11*Val!$G$11*(1-MIN(0.8,tp_g/tp_roe))/(1+(tp_r+0.01))^Val!$F$11+Val!B12*Val!$G$12*(1-MIN(0.8,tp_g/tp_roe))/(1+(tp_r+0.01))^Val!$F$12+Val!B12*(1-MIN(0.8,tp_g/tp_roe))*(1+tp_g)/((tp_r+0.01)-tp_g)/(1+(tp_r+0.01))^Val!$F$12))+tp_wB*(MAX(0,Val!C7*Val!$G$7*(1-MIN(0.8,tp_g/tp_roe))/(1+(tp_r+0.01))^Val!$F$7+Val!C8*Val!$G$8*(1-MIN(0.8,tp_g/tp_roe))/(1+(tp_r+0.01))^Val!$F$8+Val!C9*Val!$G$9*(1-MIN(0.8,tp_g/tp_roe))/(1+(tp_r+0.01))^Val!$F$9+Val!C10*Val!$G$10*(1-MIN(0.8,tp_g/tp_roe))/(1+(tp_r+0.01))^Val!$F$10+Val!C11*Val!$G$11*(1-MIN(0.8,tp_g/tp_roe))/(1+(tp_r+0.01))^Val!$F$11+Val!C12*Val!$G$12*(1-MIN(0.8,tp_g/tp_roe))/(1+(tp_r+0.01))^Val!$F$12+Val!C12*(1-MIN(0.8,tp_g/tp_roe))*(1+tp_g)/((tp_r+0.01)-tp_g)/(1+(tp_r+0.01))^Val!$F$12))+tp_wC*(MAX(0,Val!D7*Val!$G$7*(1-MIN(0.8,tp_g/tp_roe))/(1+(tp_r+0.01))^Val!$F$7+Val!D8*Val!$G$8*(1-MIN(0.8,tp_g/tp_roe))/(1+(tp_r+0.01))^Val!$F$8+Val!D9*Val!$G$9*(1-MIN(0.8,tp_g/tp_roe))/(1+(tp_r+0.01))^Val!$F$9+Val!D10*Val!$G$10*(1-MIN(0.8,tp_g/tp_roe))/(1+(tp_r+0.01))^Val!$F$10+Val!D11*Val!$G$11*(1-MIN(0.8,tp_g/tp_roe))/(1+(tp_r+0.01))^Val!$F$11+Val!D12*Val!$G$12*(1-MIN(0.8,tp_g/tp_roe))/(1+(tp_r+0.01))^Val!$F$12+Val!D12*(1-MIN(0.8,tp_g/tp_roe))*(1+tp_g)/((tp_r+0.01)-tp_g)/(1+(tp_r+0.01))^Val!$F$12)))*(1+(tp_r+0.01))+(1-tp_w_dcf)*Val!$B$35 -> 2098.4775 | F28: =E28/G28-1 -> -0.077608415 | G28: =Val!$B$39 -> 2275.0397
A29: tp_g ±1pt | B29: 長期成長 −1pt／＋1pt | C29: =tp_w_dcf*(tp_wA*(MAX(0,Val!B7*Val!$G$7*(1-MIN(0.8,(tp_g-0.01)/tp_roe))/(1+tp_r)^Val!$F$7+Val!B8*Val!$G$8*(1-MIN(0.8,(tp_g-0.01)/tp_roe))/(1+tp_r)^Val!$F$8+Val!B9*Val!$G$9*(1-MIN(0.8,(tp_g-0.01)/tp_roe))/(1+tp_r)^Val!$F$9+Val!B10*Val!$G$10*(1-MIN(0.8,(tp_g-0.01)/tp_roe))/(1+tp_r)^Val!$F$10+Val!B11*Val!$G$11*(1-MIN(0.8,(tp_g-0.01)/tp_roe))/(1+tp_r)^Val!$F$11+Val!B12*Val!$G$12*(1-MIN(0.8,(tp_g-0.01)/tp_roe))/(1+tp_r)^Val!$F$12+Val!B12*(1-MIN(0.8,(tp_g-0.01)/tp_roe))*(1+(tp_g-0.01))/(tp_r-(tp_g-0.01))/(1+tp_r)^Val!$F$12))+tp_wB*(MAX(0,Val!C7*Val!$G$7*(1-MIN(0.8,(tp_g-0.01)/tp_roe))/(1+tp_r)^Val!$F$7+Val!C8*Val!$G$8*(1-MIN(0.8,(tp_g-0.01)/tp_roe))/(1+tp_r)^Val!$F$8+Val!C9*Val!$G$9*(1-MIN(0.8,(tp_g-0.01)/tp_roe))/(1+tp_r)^Val!$F$9+Val!C10*Val!$G$10*(1-MIN(0.8,(tp_g-0.01)/tp_roe))/(1+tp_r)^Val!$F$10+Val!C11*Val!$G$11*(1-MIN(0.8,(tp_g-0.01)/tp_roe))/(1+tp_r)^Val!$F$11+Val!C12*Val!$G$12*(1-MIN(0.8,(tp_g-0.01)/tp_roe))/(1+tp_r)^Val!$F$12+Val!C12*(1-MIN(0.8,(tp_g-0.01)/tp_roe))*(1+(tp_g-0.01))/(tp_r-(tp_g-0.01))/(1+tp_r)^Val!$F$12))+tp_wC*(MAX(0,Val!D7*Val!$G$7*(1-MIN(0.8,(tp_g-0.01)/tp_roe))/(1+tp_r)^Val!$F$7+Val!D8*Val!$G$8*(1-MIN(0.8,(tp_g-0.01)/tp_roe))/(1+tp_r)^Val!$F$8+Val!D9*Val!$G$9*(1-MIN(0.8,(tp_g-0.01)/tp_roe))/(1+tp_r)^Val!$F$9+Val!D10*Val!$G$10*(1-MIN(0.8,(tp_g-0.01)/tp_roe))/(1+tp_r)^Val!$F$10+Val!D11*Val!$G$11*(1-MIN(0.8,(tp_g-0.01)/tp_roe))/(1+tp_r)^Val!$F$11+Val!D12*Val!$G$12*(1-MIN(0.8,(tp_g-0.01)/tp_roe))/(1+tp_r)^Val!$F$12+Val!D12*(1-MIN(0.8,(tp_g-0.01)/tp_roe))*(1+(tp_g-0.01))/(tp_r-(tp_g-0.01))/(1+tp_r)^Val!$F$12)))*(1+tp_r)+(1-tp_w_dcf)*Val!$B$35 -> 2162.1281 | D29: =C29/G29-1 -> -0.049630605 | E29: =tp_w_dcf*(tp_wA*(MAX(0,Val!B7*Val!$G$7*(1-MIN(0.8,(tp_g+0.01)/tp_roe))/(1+tp_r)^Val!$F$7+Val!B8*Val!$G$8*(1-MIN(0.8,(tp_g+0.01)/tp_roe))/(1+tp_r)^Val!$F$8+Val!B9*Val!$G$9*(1-MIN(0.8,(tp_g+0.01)/tp_roe))/(1+tp_r)^Val!$F$9+Val!B10*Val!$G$10*(1-MIN(0.8,(tp_g+0.01)/tp_roe))/(1+tp_r)^Val!$F$10+Val!B11*Val!$G$11*(1-MIN(0.8,(tp_g+0.01)/tp_roe))/(1+tp_r)^Val!$F$11+Val!B12*Val!$G$12*(1-MIN(0.8,(tp_g+0.01)/tp_roe))/(1+tp_r)^Val!$F$12+Val!B12*(1-MIN(0.8,(tp_g+0.01)/tp_roe))*(1+(tp_g+0.01))/(tp_r-(tp_g+0.01))/(1+tp_r)^Val!$F$12))+tp_wB*(MAX(0,Val!C7*Val!$G$7*(1-MIN(0.8,(tp_g+0.01)/tp_roe))/(1+tp_r)^Val!$F$7+Val!C8*Val!$G$8*(1-MIN(0.8,(tp_g+0.01)/tp_roe))/(1+tp_r)^Val!$F$8+Val!C9*Val!$G$9*(1-MIN(0.8,(tp_g+0.01)/tp_roe))/(1+tp_r)^Val!$F$9+Val!C10*Val!$G$10*(1-MIN(0.8,(tp_g+0.01)/tp_roe))/(1+tp_r)^Val!$F$10+Val!C11*Val!$G$11*(1-MIN(0.8,(tp_g+0.01)/tp_roe))/(1+tp_r)^Val!$F$11+Val!C12*Val!$G$12*(1-MIN(0.8,(tp_g+0.01)/tp_roe))/(1+tp_r)^Val!$F$12+Val!C12*(1-MIN(0.8,(tp_g+0.01)/tp_roe))*(1+(tp_g+0.01))/(tp_r-(tp_g+0.01))/(1+tp_r)^Val!$F$12))+tp_wC*(MAX(0,Val!D7*Val!$G$7*(1-MIN(0.8,(tp_g+0.01)/tp_roe))/(1+tp_r)^Val!$F$7+Val!D8*Val!$G$8*(1-MIN(0.8,(tp_g+0.01)/tp_roe))/(1+tp_r)^Val!$F$8+Val!D9*Val!$G$9*(1-MIN(0.8,(tp_g+0.01)/tp_roe))/(1+tp_r)^Val!$F$9+Val!D10*Val!$G$10*(1-MIN(0.8,(tp_g+0.01)/tp_roe))/(1+tp_r)^Val!$F$10+Val!D11*Val!$G$11*(1-MIN(0.8,(tp_g+0.01)/tp_roe))/(1+tp_r)^Val!$F$11+Val!D12*Val!$G$12*(1-MIN(0.8,(tp_g+0.01)/tp_roe))/(1+tp_r)^Val!$F$12+Val!D12*(1-MIN(0.8,(tp_g+0.01)/tp_roe))*(1+(tp_g+0.01))/(tp_r-(tp_g+0.01))/(1+tp_r)^Val!$F$12)))*(1+tp_r)+(1-tp_w_dcf)*Val!$B$35 -> 2436.098 | F29: =E29/G29-1 -> 0.070793613 | G29: =Val!$B$39 -> 2275.0397
A30: tp_w_dcf 0.3／0.7 | B30: DCF 權重 0.3／0.7 | C30: =0.3*(tp_wA*(MAX(0,Val!B7*Val!$G$7*(1-MIN(0.8,tp_g/tp_roe))/(1+tp_r)^Val!$F$7+Val!B8*Val!$G$8*(1-MIN(0.8,tp_g/tp_roe))/(1+tp_r)^Val!$F$8+Val!B9*Val!$G$9*(1-MIN(0.8,tp_g/tp_roe))/(1+tp_r)^Val!$F$9+Val!B10*Val!$G$10*(1-MIN(0.8,tp_g/tp_roe))/(1+tp_r)^Val!$F$10+Val!B11*Val!$G$11*(1-MIN(0.8,tp_g/tp_roe))/(1+tp_r)^Val!$F$11+Val!B12*Val!$G$12*(1-MIN(0.8,tp_g/tp_roe))/(1+tp_r)^Val!$F$12+Val!B12*(1-MIN(0.8,tp_g/tp_roe))*(1+tp_g)/(tp_r-tp_g)/(1+tp_r)^Val!$F$12))+tp_wB*(MAX(0,Val!C7*Val!$G$7*(1-MIN(0.8,tp_g/tp_roe))/(1+tp_r)^Val!$F$7+Val!C8*Val!$G$8*(1-MIN(0.8,tp_g/tp_roe))/(1+tp_r)^Val!$F$8+Val!C9*Val!$G$9*(1-MIN(0.8,tp_g/tp_roe))/(1+tp_r)^Val!$F$9+Val!C10*Val!$G$10*(1-MIN(0.8,tp_g/tp_roe))/(1+tp_r)^Val!$F$10+Val!C11*Val!$G$11*(1-MIN(0.8,tp_g/tp_roe))/(1+tp_r)^Val!$F$11+Val!C12*Val!$G$12*(1-MIN(0.8,tp_g/tp_roe))/(1+tp_r)^Val!$F$12+Val!C12*(1-MIN(0.8,tp_g/tp_roe))*(1+tp_g)/(tp_r-tp_g)/(1+tp_r)^Val!$F$12))+tp_wC*(MAX(0,Val!D7*Val!$G$7*(1-MIN(0.8,tp_g/tp_roe))/(1+tp_r)^Val!$F$7+Val!D8*Val!$G$8*(1-MIN(0.8,tp_g/tp_roe))/(1+tp_r)^Val!$F$8+Val!D9*Val!$G$9*(1-MIN(0.8,tp_g/tp_roe))/(1+tp_r)^Val!$F$9+Val!D10*Val!$G$10*(1-MIN(0.8,tp_g/tp_roe))/(1+tp_r)^Val!$F$10+Val!D11*Val!$G$11*(1-MIN(0.8,tp_g/tp_roe))/(1+tp_r)^Val!$F$11+Val!D12*Val!$G$12*(1-MIN(0.8,tp_g/tp_roe))/(1+tp_r)^Val!$F$12+Val!D12*(1-MIN(0.8,tp_g/tp_roe))*(1+tp_g)/(tp_r-tp_g)/(1+tp_r)^Val!$F$12)))*(1+tp_r)+(1-0.3)*Val!$B$35 -> 2151.582 | D30: =C30/G30-1 -> -0.054266197 | E30: =0.7*(tp_wA*(MAX(0,Val!B7*Val!$G$7*(1-MIN(0.8,tp_g/tp_roe))/(1+tp_r)^Val!$F$7+Val!B8*Val!$G$8*(1-MIN(0.8,tp_g/tp_roe))/(1+tp_r)^Val!$F$8+Val!B9*Val!$G$9*(1-MIN(0.8,tp_g/tp_roe))/(1+tp_r)^Val!$F$9+Val!B10*Val!$G$10*(1-MIN(0.8,tp_g/tp_roe))/(1+tp_r)^Val!$F$10+Val!B11*Val!$G$11*(1-MIN(0.8,tp_g/tp_roe))/(1+tp_r)^Val!$F$11+Val!B12*Val!$G$12*(1-MIN(0.8,tp_g/tp_roe))/(1+tp_r)^Val!$F$12+Val!B12*(1-MIN(0.8,tp_g/tp_roe))*(1+tp_g)/(tp_r-tp_g)/(1+tp_r)^Val!$F$12))+tp_wB*(MAX(0,Val!C7*Val!$G$7*(1-MIN(0.8,tp_g/tp_roe))/(1+tp_r)^Val!$F$7+Val!C8*Val!$G$8*(1-MIN(0.8,tp_g/tp_roe))/(1+tp_r)^Val!$F$8+Val!C9*Val!$G$9*(1-MIN(0.8,tp_g/tp_roe))/(1+tp_r)^Val!$F$9+Val!C10*Val!$G$10*(1-MIN(0.8,tp_g/tp_roe))/(1+tp_r)^Val!$F$10+Val!C11*Val!$G$11*(1-MIN(0.8,tp_g/tp_roe))/(1+tp_r)^Val!$F$11+Val!C12*Val!$G$12*(1-MIN(0.8,tp_g/tp_roe))/(1+tp_r)^Val!$F$12+Val!C12*(1-MIN(0.8,tp_g/tp_roe))*(1+tp_g)/(tp_r-tp_g)/(1+tp_r)^Val!$F$12))+tp_wC*(MAX(0,Val!D7*Val!$G$7*(1-MIN(0.8,tp_g/tp_roe))/(1+tp_r)^Val!$F$7+Val!D8*Val!$G$8*(1-MIN(0.8,tp_g/tp_roe))/(1+tp_r)^Val!$F$8+Val!D9*Val!$G$9*(1-MIN(0.8,tp_g/tp_roe))/(1+tp_r)^Val!$F$9+Val!D10*Val!$G$10*(1-MIN(0.8,tp_g/tp_roe))/(1+tp_r)^Val!$F$10+Val!D11*Val!$G$11*(1-MIN(0.8,tp_g/tp_roe))/(1+tp_r)^Val!$F$11+Val!D12*Val!$G$12*(1-MIN(0.8,tp_g/tp_roe))/(1+tp_r)^Val!$F$12+Val!D12*(1-MIN(0.8,tp_g/tp_roe))*(1+tp_g)/(tp_r-tp_g)/(1+tp_r)^Val!$F$12)))*(1+tp_r)+(1-0.7)*Val!$B$35 -> 2398.4975 | F30: =E30/G30-1 -> 0.054266197 | G30: =Val!$B$39 -> 2275.0397
A40: 案例區塊：白牌份額流失（低）（情境 A）
A41: 項目 | B41: 單位 | C41: FY2025A | D41: FY2026（錨點） | E41: FY2027 | F41: FY2028 | G41: FY2029 | H41: 說明
A42: A. 營收拆分（FY2025 依公司揭露比例；FY2026 校準：網路應用產品比例 Assumed，非 AI 依成長率，AI 交換器為殘差）
A43: 網路應用產品（AI 加速卡等） | B43: NT$B | C43: =a25_rev*nap25s -> 156.4416 | D43: =a26_rev*ns26 -> 205.3806
A44: 非 AI（企業、電信、前端交換器、接取） | B44: NT$B | C44: =a25_rev*(1-nap25s-sw25s*af25) -> 41.22112 | D44: =C44*(1+g_nai26) -> 45.343232
A45: AI 資料中心交換器（殘差） | B45: NT$B | C45: =a25_rev*sw25s*af25 -> 50.65728 | D45: =a26_rev-D43-D44 -> 160.03737 | H45: Derived：FY2026 交換器合計＝AI＋非 AI 交換器（見 Recon）
A46: B. AI 交換器（D 欄＝FY2026 校準年；E–G＝FY2027–FY2029）
A47: AI 後端 scale-out 交換器市場 × 情境顆數係數 | B47: US$B | D47: =mkt_26*1 -> 32.0719 | E47: =mkt_27*1*1 -> 61.085 | F47: =mkt_28*um28_A*1 -> 69.005 | G47: =mkt_29*um29_A*1 -> 78.48215
A48: 乙太網路占比 | B48: % | D48: =eth_26 -> 0.75 | E48: =eth_27 -> 0.8 | F48: =eth_28 -> 0.83 | G48: =eth_29 -> 0.85
A49: 非 NVIDIA scale-up 乙太網路交換匣市場 × 係數 | B49: US$B | D49: =su_26*1 -> 3.015 | E49: =su_27*1*1 -> 11.3414 | F49: =su_28*um28_A*1 -> 13.8952 | G49: =su_29*um29_A*1 -> 15.97948
A50: AI 乙太網路交換器市場（scale-out × 乙太網路＋scale-up） | B50: US$B | D50: =D47*D48+D49 -> 27.068925 | E50: =E47*E48+E49 -> 60.2094 | F50: =F47*F48+F49 -> 71.16935 | G50: =G47*G48+G49 -> 82.689307
A51: 白牌占比 | B51: % | D51: =wb_26 -> 0.45 | E51: =wb_27 -> 0.47 | F51: =wb_28 -> 0.48 | G51: =wb_29 -> 0.5
A52: 白牌 AI 乙太網路交換器市場 | B52: US$B | D52: =D50*D51 -> 12.181016 | E52: =E50*E51 -> 28.298418 | F52: =F50*F51 -> 34.161288 | G52: =G50*G51 -> 41.344654
A53: 智邦白牌有效份額（FY2026 校準）＝ AI 交換器營收 ÷ 匯率 ÷ 白牌市場 | B53: % | D53: =D45/fx/D52 -> 0.41057065 | H53: Derived：分子含前端資料中心交換器，所以高於純後端份額；FY2027 起乘相對值
A54: 份額相對值（÷ FY2026） | B54: x | D54: =1 -> 1 | E54: =RLO_27 -> 0.8 | F54: =RLO_28 -> 0.7 | G54: =RLO_29 -> 0.65
A55: 智邦白牌有效份額 | B55: % | D55: =$D$53*D54 -> 0.41057065 | E55: =$D$53*E54 -> 0.32845652 | F55: =$D$53*F54 -> 0.28739945 | G55: =$D$53*G54 -> 0.26687092
A56: AI 交換器營收 | B56: NT$B | C56: =C45 -> 50.65728 | D56: =D52*D55*fx -> 160.03737 | E56: =E52*E55*fx -> 297.4336 | F56: =F52*F55*fx -> 314.17394 | G56: =G52*G55*fx -> 353.07795
A57: C. AI 加速卡等網路應用產品
A58: AWS Trainium 顆數 × 情境顆數係數 | B58: 百萬顆 | D58: =trn_26*1 -> 2 | E58: =trn_27*1*1 -> 2.5 | F58: =trn_28*um28_A*1 -> 3 | G58: =trn_29*um29_A*1 -> 3.45
A59: 每顆 Trainium 的智邦營收（FY2026 校準） | B59: 千新台幣／顆 | D59: =D43/D58 -> 102.6903 | H59: Derived：含加速卡模組、L10 等網路應用產品；晶片疑為客供（每顆約 3 千美元）
A60: 相對值（份額 × 單價，÷ FY2026） | B60: x | D60: =1 -> 1 | E60: =nrel_27 -> 0.9 | F60: =nrel_28 -> 0.85 | G60: =nrel_29 -> 0.8
A61: 網路應用產品營收 | B61: NT$B | C61: =C43 -> 156.4416 | D61: =D58*$D$59*D60 -> 205.3806 | E61: =E58*$D$59*E60 -> 231.05318 | F61: =F58*$D$59*F60 -> 261.86027 | G61: =G58*$D$59*G60 -> 283.42523
A62: D. 非 AI 與合計
A63: 非 AI 營收 | B63: NT$B | C63: =C44 -> 41.22112 | D63: =D44 -> 45.343232 | E63: =D63*(1+g_nai27) -> 48.063826 | F63: =E63*(1+g_nai28) -> 50.467017 | G63: =F63*(1+g_nai29) -> 52.990368
A64: 營收 | B64: NT$B | C64: =C56+C61+C63 -> 248.32 | D64: =D56+D61+D63 -> 410.7612 | E64: =E56+E61+E63 -> 576.5506 | F64: =F56+F61+F63 -> 626.50122 | G64: =G56+G61+G63 -> 689.49354
A65: 非 AI 中的非 AI 交換器比例（固定在 FY2025 結構） | B65: % | C65: =sw25s*(1-af25)/(1-nap25s-sw25s*af25) -> 0.81927711 | H65: FY2025：交換器 34% ×（1 − AI 比例）÷ 非 AI 合計；之後各年沿用
A66: 網路交換器：非 AI（企業、電信、前端） | B66: NT$B | C66: =C63*$C$65 -> 33.77152 | D66: =D63*$C$65 -> 37.148672 | E66: =E63*$C$65 -> 39.377592 | F66: =F63*$C$65 -> 41.346472 | G66: =G63*$C$65 -> 43.413796
A67: 網路交換器營收（AI 資料中心＋非 AI） | B67: NT$B | C67: =C56+C66 -> 84.4288 | D67: =D56+D66 -> 197.18604 | E67: =E56+E66 -> 336.81119 | F67: =F56+F66 -> 355.52041 | G67: =G56+G66 -> 396.49174 | H67: 公司產品別：網路交換器（FY2025 前三季 34%）
A68: 接取與其他營收（＝非 AI − 非 AI 交換器） | B68: NT$B | C68: =C63-C66 -> 7.4496 | D68: =D63-D66 -> 8.19456 | E68: =E63-E66 -> 8.6862336 | F68: =F63-F66 -> 9.1205453 | G68: =G63-G66 -> 9.5765725 | H68: 公司產品別：接取（FY2025 前三季 2%）與其他
A69: 檢查：分部合計 − 合併營收（FY2025 實績起） | B69: NT$B | C69: =C67+C61+C68-a25_rev -> 0 | D69: =D67+D61+D68-D64 -> 0 | E69: =E67+E61+E68-E64 -> 0 | F69: =F67+F61+F68-F64 -> 0 | G69: =G67+G61+G68-G64 -> 0
A70: 營收年增 | B70: % | D70: =D64/C64-1 -> 0.65416076 | E70: =E64/D64-1 -> 0.40361504 | F70: =F64/E64-1 -> 0.086637014 | G70: =G64/F64-1 -> 0.10054621
A71: AI（交換器＋網路應用產品）÷ 營收 | B71: % | C71: =(C56+C61)/C64 -> 0.834 | D71: =(D56+D61)/D64 -> 0.8896117 | E71: =(E56+E61)/E64 -> 0.91663555 | F71: =(F56+F61)/F64 -> 0.91944626 | G71: =(G56+G61)/G64 -> 0.92314595
A72: 網路應用產品 ÷ 營收 | B72: % | C72: =C61/C64 -> 0.63 | D72: =D61/D64 -> 0.5 | E72: =E61/E64 -> 0.40075091 | F72: =F61/F64 -> 0.41797247 | G72: =G61/G64 -> 0.41106292
A73: E. 損益
A74: 交換器與其他毛利率 ＝ 錨點毛利率 ＋ 差距 × 網路應用產品占比（FY2026 校準） | B74: % | D74: =a26_gp/a26_rev+d_nap*D72 -> 0.21958925 | H74: Derived：讓 FY2026 毛利率等於錨點；網路應用產品毛利率＝此值 − 差距
A75: 毛利 | B75: NT$B | C75: =a25_gp -> 44.921088 | D75: =a26_gp -> 77.875907 | E75: =$D$74*(E56+E63)+($D$74-d_nap)*E61 -> 112.74112 | F75: =$D$74*(F56+F63)+($D$74-d_nap)*F61 -> 121.86132 | G75: =$D$74*(G56+G63)+($D$74-d_nap)*G61 -> 134.39986
A76: 毛利率 | B76: % | C76: =C75/C64 -> 0.1809 | D76: =D75/D64 -> 0.18958925 | E76: =E75/E64 -> 0.19554419 | F76: =F75/F64 -> 0.1945109 | G76: =G75/G64 -> 0.19492547
A77: 營業費用（基準路徑） | B77: NT$B | C77: =a25_opx -> 12.78848 | D77: =a26_opx -> 17.956088 | E77: =D77*(1+MAX(0,phi*E70)) -> 22.304496 | F77: =E77*(1+MAX(0,phi*F70)) -> 23.463933 | G77: =F77*(1+MAX(0,phi*G70)) -> 24.879459
A78: 營業費用 | B78: NT$B | C78: =C77 -> 12.78848 | D78: =D77 -> 17.956088 | E78: =E77+0*E64 -> 22.304496 | F78: =F77+0*F64 -> 23.463933 | G78: =G77+0*G64 -> 24.879459
A79: 營業利益 | B79: NT$B | C79: =C75-C78 -> 32.132608 | D79: =D75-D78 -> 59.919819 | E79: =E75-E78 -> 90.436625 | F79: =F75-F78 -> 98.397382 | G79: =G75-G78 -> 109.5204
A80: 營業利益率 | B80: % | C80: =C79/C64 -> 0.1294 | D80: =D79/D64 -> 0.14587507 | E80: =E79/E64 -> 0.15685809 | F80: =F79/F64 -> 0.15705856 | G80: =G79/G64 -> 0.1588418
A81: 淨利 ÷ 營業利益 | B81: x | C81: =a25_ni/a25_oi -> 0.81979029 | D81: =a26_ni/a26_oi -> 0.79816421 | E81: =nio_f -> 0.8 | F81: =nio_f -> 0.8 | G81: =nio_f -> 0.8
A82: 稅後淨利 | B82: NT$B | C82: =a25_ni -> 26.342 | D82: =a26_ni -> 47.825855 | E82: =E79*E81 -> 72.3493 | F82: =F79*F81 -> 78.717906 | G82: =G79*G81 -> 87.616317
A83: 股數 | B83: 十億股 | C83: =a25_sh -> 0.55892213 | D83: =a26_sh -> 0.5589049 | E83: =D83*(1+sh_g27) -> 0.56885341 | F83: =E83*(1+sh_g) -> 0.56885341 | G83: =F83*(1+sh_g) -> 0.56885341
A84: EPS | B84: NT$ | C84: =C82/C83 -> 47.13 | D84: =D82/D83 -> 85.570649 | E84: =E82/E83 -> 127.18444 | F84: =F82/F83 -> 138.37995 | G84: =G82/G83 -> 154.02266
A85: EPS 年增 | B85: % | D85: =D84/C84-1 -> 0.81563016 | E85: =E84/D84-1 -> 0.48630912 | F85: =F84/E84-1 -> 0.08802581 | G85: =G84/F84-1 -> 0.11304176
A88: 案例區塊：白牌份額提升（高）（情境 A）
A89: 項目 | B89: 單位 | C89: FY2025A | D89: FY2026（錨點） | E89: FY2027 | F89: FY2028 | G89: FY2029 | H89: 說明
A90: A. 營收拆分（FY2025 依公司揭露比例；FY2026 校準：網路應用產品比例 Assumed，非 AI 依成長率，AI 交換器為殘差）
A91: 網路應用產品（AI 加速卡等） | B91: NT$B | C91: =a25_rev*nap25s -> 156.4416 | D91: =a26_rev*ns26 -> 205.3806
A92: 非 AI（企業、電信、前端交換器、接取） | B92: NT$B | C92: =a25_rev*(1-nap25s-sw25s*af25) -> 41.22112 | D92: =C92*(1+g_nai26) -> 45.343232
A93: AI 資料中心交換器（殘差） | B93: NT$B | C93: =a25_rev*sw25s*af25 -> 50.65728 | D93: =a26_rev-D91-D92 -> 160.03737 | H93: Derived：FY2026 交換器合計＝AI＋非 AI 交換器（見 Recon）
A94: B. AI 交換器（D 欄＝FY2026 校準年；E–G＝FY2027–FY2029）
A95: AI 後端 scale-out 交換器市場 × 情境顆數係數 | B95: US$B | D95: =mkt_26*1 -> 32.0719 | E95: =mkt_27*1*1 -> 61.085 | F95: =mkt_28*um28_A*1 -> 69.005 | G95: =mkt_29*um29_A*1 -> 78.48215
A96: 乙太網路占比 | B96: % | D96: =eth_26 -> 0.75 | E96: =eth_27 -> 0.8 | F96: =eth_28 -> 0.83 | G96: =eth_29 -> 0.85
A97: 非 NVIDIA scale-up 乙太網路交換匣市場 × 係數 | B97: US$B | D97: =su_26*1 -> 3.015 | E97: =su_27*1*1 -> 11.3414 | F97: =su_28*um28_A*1 -> 13.8952 | G97: =su_29*um29_A*1 -> 15.97948
A98: AI 乙太網路交換器市場（scale-out × 乙太網路＋scale-up） | B98: US$B | D98: =D95*D96+D97 -> 27.068925 | E98: =E95*E96+E97 -> 60.2094 | F98: =F95*F96+F97 -> 71.16935 | G98: =G95*G96+G97 -> 82.689307
A99: 白牌占比 | B99: % | D99: =wb_26 -> 0.45 | E99: =wb_27 -> 0.47 | F99: =wb_28 -> 0.48 | G99: =wb_29 -> 0.5
A100: 白牌 AI 乙太網路交換器市場 | B100: US$B | D100: =D98*D99 -> 12.181016 | E100: =E98*E99 -> 28.298418 | F100: =F98*F99 -> 34.161288 | G100: =G98*G99 -> 41.344654
A101: 智邦白牌有效份額（FY2026 校準）＝ AI 交換器營收 ÷ 匯率 ÷ 白牌市場 | B101: % | D101: =D93/fx/D100 -> 0.41057065 | H101: Derived：分子含前端資料中心交換器，所以高於純後端份額；FY2027 起乘相對值
A102: 份額相對值（÷ FY2026） | B102: x | D102: =1 -> 1 | E102: =RHI_27 -> 1.1 | F102: =RHI_28 -> 1.1 | G102: =RHI_29 -> 1.1
A103: 智邦白牌有效份額 | B103: % | D103: =$D$101*D102 -> 0.41057065 | E103: =$D$101*E102 -> 0.45162771 | F103: =$D$101*F102 -> 0.45162771 | G103: =$D$101*G102 -> 0.45162771
A104: AI 交換器營收 | B104: NT$B | C104: =C93 -> 50.65728 | D104: =D100*D103*fx -> 160.03737 | E104: =E100*E103*fx -> 408.97119 | F104: =F100*F103*fx -> 493.7019 | G104: =G100*G103*fx -> 597.51653
A105: C. AI 加速卡等網路應用產品
A106: AWS Trainium 顆數 × 情境顆數係數 | B106: 百萬顆 | D106: =trn_26*1 -> 2 | E106: =trn_27*1*1 -> 2.5 | F106: =trn_28*um28_A*1 -> 3 | G106: =trn_29*um29_A*1 -> 3.45
A107: 每顆 Trainium 的智邦營收（FY2026 校準） | B107: 千新台幣／顆 | D107: =D91/D106 -> 102.6903 | H107: Derived：含加速卡模組、L10 等網路應用產品；晶片疑為客供（每顆約 3 千美元）
A108: 相對值（份額 × 單價，÷ FY2026） | B108: x | D108: =1 -> 1 | E108: =nrel_27 -> 0.9 | F108: =nrel_28 -> 0.85 | G108: =nrel_29 -> 0.8
A109: 網路應用產品營收 | B109: NT$B | C109: =C91 -> 156.4416 | D109: =D106*$D$107*D108 -> 205.3806 | E109: =E106*$D$107*E108 -> 231.05318 | F109: =F106*$D$107*F108 -> 261.86027 | G109: =G106*$D$107*G108 -> 283.42523
A110: D. 非 AI 與合計
A111: 非 AI 營收 | B111: NT$B | C111: =C92 -> 41.22112 | D111: =D92 -> 45.343232 | E111: =D111*(1+g_nai27) -> 48.063826 | F111: =E111*(1+g_nai28) -> 50.467017 | G111: =F111*(1+g_nai29) -> 52.990368
A112: 營收 | B112: NT$B | C112: =C104+C109+C111 -> 248.32 | D112: =D104+D109+D111 -> 410.7612 | E112: =E104+E109+E111 -> 688.0882 | F112: =F104+F109+F111 -> 806.02918 | G112: =G104+G109+G111 -> 933.93212
A113: 非 AI 中的非 AI 交換器比例（固定在 FY2025 結構） | B113: % | C113: =sw25s*(1-af25)/(1-nap25s-sw25s*af25) -> 0.81927711 | H113: FY2025：交換器 34% ×（1 − AI 比例）÷ 非 AI 合計；之後各年沿用
A114: 網路交換器：非 AI（企業、電信、前端） | B114: NT$B | C114: =C111*$C$113 -> 33.77152 | D114: =D111*$C$113 -> 37.148672 | E114: =E111*$C$113 -> 39.377592 | F114: =F111*$C$113 -> 41.346472 | G114: =G111*$C$113 -> 43.413796
...

Sheet Sources
A1: 來源（公司原文＝季報與月營收公告，本版只經媒體轉述；法說內容經富果摘要）
A2: 公司（轉述）：2Q26 財報（營收、毛利、營業利益、淨利、EPS、上半年） | B2: https://money.udn.com/money/story/5710/9675501
A3: 公司（轉述）：1Q26 財報 | B3: https://money.udn.com/money/story/5710/9488861
A4: 公司（轉述）：3Q26 月營收（7–9 月） | B4: https://www.chinatimes.com/realtimenews/20261006003734-260410
A5: 公司（轉述）：3Q25 法說摘要（產品別營收比例、美洲占比） | B5: https://blog.fugle.tw/post/earnings-call-2345-2025-11-7
A6: 公司（轉述）：現金增資 1,000 萬股（2026-10-22 董事會） | B6: https://udn.com/news/story/7252/9832440
A7: 二手：工商時報 2026-09-29（法人 3Q26 估計、2026／2027 EPS） | B7: https://www.ctee.com.tw/news/20260929700959-430201
A8: 二手：旺得富 2026-03-06（美系外資：2026 交換器占 48%、新客戶約 15%） | B8: https://wantrich.chinatimes.com/news/20260306900323-420101
A9: 二手：經濟日報 2026-07-09（Trainium 3 交換匣、組裝廠稀釋份額） | B9: https://udn.com/news/story/7253/9617541
A10: 二手：鏡週刊 2026-08-06（Trainium 3 OAM 模組大量出貨） | B10: https://www.mirrormedia.mg/external/mirrordaily_77953
A11: 二手：brodoginvestment 2026-07-11（2025 年資料中心交換器約 31%） | B11: https://brodoginvestment.substack.com/p/2345
A12: 共識：FactSet（鉅亨 2026-10-14） | B12: https://news.cnyes.com/news/id/6629903
A13: 研調：Dell'Oro 2025 AI 後端（Celestica、NVIDIA 並列第一，Arista 第三） | B13: https://www.delloro.com/news/ethernet-more-than-doubles-size-of-infiniband-as-the-leading-fabric-for-ai-scale-out-networks-in-2025/
... A19: 市價：鉅亨網 2345（10-22 收盤 1,775、股本 56.11 億） | B19: https://www.cnyes.com/twstock/2345
A20: 市場層：markets/network、tsmc 成品（本 repo，唯讀）
A21: 待補（人工）：公司原始季報與法說簡報；FY2026 產品別營收比例；交換器的 AI／非 AI 拆分；產品別毛利率；客戶占比（年報 10% 以上客戶）；3Q26 法說日期；10-23 收盤；前瞻 P/E 十年歷史（Bloomberg） | B21: 未找到
A22: SemiAnalysis | B22: 未使用
