Workbook

Sheet README
A1: Advantest（6857.T）收支與估值模型 v0.2.3（AI 半導體 Project 步驟 5：設備與材料） 2026-10-25
A2: v0.2.2（2026-10-23）：引用的上游成品檔名更新（SK 海力士 v0.4.1、美光 v0.3.1、三星 v0.2.1、台積電 v0.2.1 升版）；所有數值不變。
A3: 模型命題：Advantest 的盈餘由 AI 加速器的 SoC 測試需求決定。每顆晶片的測試時間隨複雜度上升，Advantest 握有約三分之二的市占。股價取決於加速器顆數的成長在 FY2027 之後放緩時，測試機的投資會不會跟著回落。
A5: 會計年度：4 月到隔年 3 月（FY2026＝2026-04～2027-03）。金額以日圓（¥B）為主，另列美元；匯率基準 ¥150（公司第二季起的假設）放 In 頁。FY2026 第二季預定 2026-10-28 公布，建置日（2026-10-22）尚未公布，故不納入。
A7: 驅動因子 → 推導量
A8: SoC 測試機市場（日曆年）＝加速器顆數（markets/memory）× 每顆測試時間係數 × 每加權顆測試支出（以公司 CY2026 市場規模校準）＋非 AI SoC；日曆年轉會計年度：3/4、1/4 加權 → × Advantest 市占（基準 66%）× 匯率 → SoC 營收
A9: 記憶體測試機：公司 CY2026 市場規模為錨 × [w × HBM 出貨位元指數（markets/memory）＋(1−w) × DRAM 設備支出指數（markets/equipment）] × 市占（FY2025 實績推得）
A10: 其他系統、服務與其他：前一年 × 成長率（Assumed）。毛利率＝截距＋斜率 × SoC 占比（FY2025 與 FY2026 指引兩點推導）；營業費用＝固定＋變動 × 營收（兩點推導）；不寫死利益率
A11: 情境 A／B／C：顆數係數讀台積電模型成品（2028 ×1.0／0.8／0.6，2029 ×1.0／0.85／0.6）；情境 C 另加 Teradyne 搶回市占（FY2028 61%、FY2029 56%）與價格壓力
A12: Val：P/E 規則——10 年（2016–2025 年底）P/E 分位，見頂年 25 分位、中段中位數、谷底 75 分位；循環位置依設備股共用規則（各情境見頂年度讀設備市場模型：A 2029、B 2028、C 2027 → FY2027：A 中段、B 中段、C 見頂）。Recon：對公司指引、共識、公司市場規模、SEMI。Sens：市占、測試時間係數、顆數情境、營業費用變動比例等
A14: 標記：Verified、Interested-party、Analogy、Assumed、Derived。SemiAnalysis 未使用。公司原文（advantest.com）在建置環境無法開啟，數字取自搜尋引擎摘錄，原文待人工複核。
A15: 已知限制：(1) 每加權顆測試支出由「公司 CY2026 市場規模 − 非 AI 市場」校準，市場規模為測試機廠自估（Interested-party），非 AI 以 AI 前（CY2021–23）Teradyne 公布的 SoC 測試機市場為參照（Analogy，3.7–4.9）；平行測試效率提升不在基準，只在 Sens 列示；(2) 每顆測試時間係數無實證，只決定世代間相對權重；(3) HBM 出貨位元自 markets/memory v0.4 起隨情境顆數係數變動（2028–29）；供給三情境相同、單價假設未重估，B、C 的 HBM 位元與單價同時下修；記憶體測試機的情境差異來自 HBM 出貨位元與 DRAM 設備支出兩條線；(4) 無測試機效率（平行測試）提升的建模，可能高估 CY2027 之後市場；(5) CY2030 無市場層資料，持平假設；(6) 10 年 P/E 缺 2016 年底收盤價。
A16: v0.2.3（2026-10-25）：Val 頁新增「0. 目標價與上檔空間」（放在 Val 既有內容之後，不位移既有列）：目標價＝In 頁權重 tp_wA／tp_wB／tp_wC（預設 A 0.3／B 0.5／C 0.2，Assumed，Andy 可改）× 三情境規則值隱含價；引用的上游成品檔名更新（SK 海力士 v0.4.2）；其餘數值不變。

Sheet In
A1: In — 輸入（藍字；基準欄 E，低 D、高 F）。金額：十億日圓（¥B）、十億美元（US$B）；顆數：百萬顆。每個輸入附兩個來源（來源2 找不到者寫「未找到」）；公司原文算一個
A2: 標記：Verified／Interested-party／Analogy／Assumed／Derived；Analogy、Assumed 給低／高區間。SemiAnalysis 未使用。公司原文（advantest.com）在建置環境無法開啟，數字取自搜尋引擎對公司文件的摘錄，並與第二來源交叉；原文待人工複核
A3: 鍵 | B3: 項目 | C3: 單位 | D3: 低 | E3: 基準 | F3: 高 | G3: 標記 | H3: 來源1 | I3: 來源2／說明
A4: A. 加速器顆數（markets/memory 與 HBM、台積電模型同一份；情境係數讀台積電模型成品，不另訂）
A5: u_bw_26 | B5: NVIDIA Blackwell（B200／B300） 顆數 2026 | C5: 百萬顆 | E5: 5.4 | G5: Interested-party | H5: markets/memory/market.py UNITS：顆數：Morgan Stanley 2026-07（2026 5.4M）；AC Research 2027 約 2.4M；2028 Assumed。GB：B200 186、B300 288 組合 [Derived] | I5: 台積電模型 tsmc/dist/20261025_台積電模型_v0.2.2.xlsx｜In!E5（值相同，建置時檢查）
A6: u_bw_27 | B6: NVIDIA Blackwell（B200／B300） 顆數 2027 | C6: 百萬顆 | E6: 2.4 | G6: Interested-party | H6: 同上 | I6: 同上
A7: u_bw_28 | B7: NVIDIA Blackwell（B200／B300） 顆數 2028 | C7: 百萬顆 | E7: 0.5 | G7: Interested-party | H7: 同上 | I7: 同上
A8: g29_bw | B8: NVIDIA Blackwell（B200／B300） 2029 顆數成長 | C8: % | E8: -0.5 | G8: Assumed | H8: tsmc/dist/20261025_台積電模型_v0.2.2.xlsx｜In!E8 | I8: markets/memory 無 2029；沿用台積電模型
A9: u_rb_26 | B9: NVIDIA Rubin 顆數 2026 | C9: 百萬顆 | E9: 1.7 | G9: Interested-party | H9: markets/memory/market.py UNITS：2026：TrendForce 組合 Rubin 22% × 約 7.6M [Derived]；2027：Morgan Stanley 約 7.0M；2028 Assumed | I9: 台積電模型 tsmc/dist/20261025_台積電模型_v0.2.2.xlsx｜In!E9（值相同，建置時檢查）
A10: u_rb_27 | B10: NVIDIA Rubin 顆數 2027 | C10: 百萬顆 | E10: 7 | G10: Interested-party | H10: 同上 | I10: 同上
A11: u_rb_28 | B11: NVIDIA Rubin 顆數 2028 | C11: 百萬顆 | E11: 7 | G11: Interested-party | H11: 同上 | I11: 同上
A12: g29_rb | B12: NVIDIA Rubin 2029 顆數成長 | C12: % | E12: 0.15 | G12: Assumed | H12: tsmc/dist/20261025_台積電模型_v0.2.2.xlsx｜In!E12 | I12: markets/memory 無 2029；沿用台積電模型
A13: u_ru_26 | B13: NVIDIA Rubin Ultra 顆數 2026 | C13: 百萬顆 | E13: 0 | G13: Assumed | H13: markets/memory/market.py UNITS：時程 Assumed；GB：NVIDIA 1 TB／封裝 | I13: 台積電模型 tsmc/dist/20261025_台積電模型_v0.2.2.xlsx｜In!E13（值相同，建置時檢查）
A14: u_ru_27 | B14: NVIDIA Rubin Ultra 顆數 2027 | C14: 百萬顆 | E14: 0.3 | G14: Assumed | H14: 同上 | I14: 同上
A15: u_ru_28 | B15: NVIDIA Rubin Ultra 顆數 2028 | C15: 百萬顆 | E15: 2 | G15: Assumed | H15: 同上 | I15: 同上
A16: g29_ru | B16: NVIDIA Rubin Ultra 2029 顆數成長 | C16: % | E16: 0.15 | G16: Assumed | H16: tsmc/dist/20261025_台積電模型_v0.2.2.xlsx｜In!E16 | I16: markets/memory 無 2029；沿用台積電模型
... A42: um29_C | B42: 情境 C：2029 顆數 ÷ 基準 | C42: x | E42: 0.6 | G42: Assumed | H42: tsmc/dist/20261025_台積電模型_v0.2.2.xlsx｜In!E42 | I42: 同上
A43: cy30g | B43: 2030 年（日曆年）顆數與記憶體測試機相對 2029 的變化（只用於 FY2029 的 1／4） | C43: % | D43: -0.1 | E43: 0 | F43: 0.1 | G43: Assumed | H43: 無：市場層只到 2029 | I43: FY2029＝3/4×CY2029＋1/4×CY2030，需要 CY2030；基準持平
A44: B. SoC 測試機市場（日曆年）與校準：AI 市場＝加權顆數 × 每加權顆測試支出；另加非 AI SoC
A45: mk_soc25 | B45: SoC 測試機市場 CY2025 | C45: US$B | E45: 6.9 | G45: Interested-party | H45: Advantest（測試機廠，有誇大市場傾向）：CY2025 約 6.9（FY2025 簡報；經二手轉述，搜尋摘錄） | I45: 第二來源：未找到
A46: mk_mem25 | B46: 記憶體測試機市場 CY2025 | C46: US$B | E46: 2.1 | G46: Interested-party | H46: 同上：約 2.1 | I46: 第二來源：未找到
A47: mk_soc26 | B47: SoC 測試機市場 CY2026（公司上修後） | C47: US$B | D47: 10.5 | E47: 11 | F47: 11.5 | G47: Interested-party | H47: Advantest FY2025 簡報（2026-04-27）：10.5–11.5（二手轉述，搜尋摘錄；公司原文未開啟） | I47: 第二來源：未找到。SoC＋記憶體合計 13.0–14.5 的二手說法與 10.5+2.5、11.5+3.0 一致
A48: mk_mem26 | B48: 記憶體測試機市場 CY2026 | C48: US$B | D48: 2.5 | E48: 2.75 | F48: 3 | G48: Interested-party | H48: Advantest：2.5–3.0（公司原文未開啟，二手摘錄） | I48: 合計 13.0–14.5 的二手說法間接支持；第二來源：未找到
A49: nonai26 | B49: 非 AI SoC 測試機市場 CY2026（手機、車用、PC、工業等） | C49: US$B | D49: 3.7 | E49: 4.3 | F49: 4.9 | G49: Analogy | H49: AI 需求出現前的 SoC 測試機市場：Teradyne 4Q22 法說（marketbeat 逐字稿）CY2022 約 4.6、較 2021 −6%（2021 約 4.9，Derived）；Teradyne 2Q23 法說 CY2023 3.7–4.1（https://www.marketbeat.com/earnings/transcripts/86996 、/94281）。低＝CY2023 下緣 3.7，高＝CY2021 推得 4.9，基準＝兩者中點 4.3 | I49: 第二來源：Advantest FY2023 4Q Investor Note 列 SoC 測試機市場 4.3／4.0／3.3（年份標籤未能從摘錄確認，僅作數量級佐證）。搜尋過：Teradyne 4Q20／4Q22／2Q23 法說、Advantest 各季 Note 與 Investors Guide、Technavio／ResearchAndMarkets（只有增量或不一致的估計，未採）。與現在的差異：(1) 2021–22 已含早期 AI／運算（Teradyne 稱運算部分歷來僅 US$0.5–0.6B，2020）；(2) 2023 後手機大幅走弱（2020 年手機測試市場約 1.7）、車用 ADAS 與工業走強；(3) Teradyne 與 Advantest 對 TAM 的定義不同（兩家 CY2024 分別約 4.0–4.2 與 4.1，相近）；(4) 基準假設 2026 非 AI 回到 2021–23 區間的中點
A50: g_nonai | B50: 非 AI SoC 市場年增 | C50: % | D50: 0 | E50: 0.04 | F50: 0.08 | G50: Assumed | H50: 無 | I50: —
A51: eff_par | B51: 平行測試效率提升（每年降低每加權顆所需測試支出） | C51: %/年 | D51: 0.05 | E51: 0 | F51: 0.1 | G51: Assumed | H51: 無：基準為 0，不納入基準（納入等於用 SEMI 預測校準）；只在 Sens 列 5%／10% | I51: 低欄＝5%、高欄＝10%（Sens 用）；公司未揭露平行度提升
A52: asp_m | B52: 高階 SoC 測試機平均單價 | C52: US$M／台 | D52: 1 | E52: 1.5 | F52: 2.5 | G52: Assumed | H52: 無：公司不揭露台數與單價 | I52: 只影響「每百萬顆機台數」的顯示（k＝每顆支出 ÷ 單價），不影響營收與 EPS
A53: tt_bw | B53: 每顆測試時間係數（Blackwell＝1.0）：NVIDIA Blackwell | C53: x | D53: 0.9 | E53: 1 | F53: 1.1 | G53: Assumed | H53: 無實證：公司稱每顆測試時間隨複雜度與世代上升，未給倍數；基準世代（定義為 1.0） | I53: 第二來源：未找到。校準在 2026 年進行，所以係數只決定世代間的相對權重
A54: tt_rb | B54: 每顆測試時間係數（Blackwell＝1.0）：NVIDIA Rubin | C54: x | D54: 1.1 | E54: 1.3 | F54: 1.6 | G54: Assumed | H54: 無實證：公司稱每顆測試時間隨複雜度與世代上升，未給倍數；晶粒數、HBM4 堆疊數、介面速度上升；Assumed | I54: 第二來源：未找到。校準在 2026 年進行，所以係數只決定世代間的相對權重
A55: tt_ru | B55: 每顆測試時間係數（Blackwell＝1.0）：NVIDIA Rubin Ultra | C55: x | D55: 1.3 | E55: 1.7 | F55: 2.2 | G55: Assumed | H55: 無實證：公司稱每顆測試時間隨複雜度與世代上升，未給倍數；4 顆光罩尺寸晶粒＋16 疊 HBM4E（台積電模型 PP 表）；Assumed | I55: 第二來源：未找到。校準在 2026 年進行，所以係數只決定世代間的相對權重
A56: tt_hp | B56: 每顆測試時間係數（Blackwell＝1.0）：NVIDIA Hopper | C56: x | D56: 0.5 | E56: 0.6 | F56: 0.8 | G56: Assumed | H56: 無實證：公司稱每顆測試時間隨複雜度與世代上升，未給倍數；單晶粒、HBM3E；上一世代 | I56: 第二來源：未找到。校準在 2026 年進行，所以係數只決定世代間的相對權重
A57: tt_amd | B57: 每顆測試時間係數（Blackwell＝1.0）：AMD Instinct | C57: x | D57: 0.9 | E57: 1.1 | F57: 1.4 | G57: Assumed | H57: 無實證：公司稱每顆測試時間隨複雜度與世代上升，未給倍數；MI455X 12 疊 HBM4；Assumed | I57: 第二來源：未找到。校準在 2026 年進行，所以係數只決定世代間的相對權重
A58: tt_tpu | B58: 每顆測試時間係數（Blackwell＝1.0）：Google TPU | C58: x | D58: 0.8 | E58: 1 | F58: 1.3 | G58: Assumed | H58: 無實證：公司稱每顆測試時間隨複雜度與世代上升，未給倍數；TPU 7→8；Assumed | I58: 第二來源：未找到。校準在 2026 年進行，所以係數只決定世代間的相對權重
... A60: tt_oth | B60: 每顆測試時間係數（Blackwell＝1.0）：其他 ASIC | C60: x | D60: 0.5 | E60: 0.7 | F60: 1 | G60: Assumed | H60: 無實證：公司稱每顆測試時間隨複雜度與世代上升，未給倍數；中小型 ASIC；Assumed | I60: 第二來源：未找到。校準在 2026 年進行，所以係數只決定世代間的相對權重
A61: C. 市占
A62: sh_soc | B62: Advantest SoC 測試機市占（CY2025 公司自估；FY 口徑沿用） | C62: % | D62: 0.61 | E62: 0.66 | F62: 0.71 | G62: Interested-party | H62: Advantest FY2025 簡報：CY2024 56%→CY2025 66%（二手轉述，X：jukan05） | I62: 第二來源：未找到。低／高＝±5 個百分點（Assumed 區間）
A63: shC_28 | B63: 情境 C：FY2028 市占（Teradyne 搶回） | C63: % | D63: 0.56 | E63: 0.61 | F63: 0.66 | G63: Assumed | H63: 無：假設 2 年內回到 CY2024 的 56% | I63: Analogy：CY2024 市占 56%（Advantest 簡報）
A64: shC_29 | B64: 情境 C：FY2029 市占 | C64: % | D64: 0.51 | E64: 0.56 | F64: 0.61 | G64: Analogy | H64: CY2024 市占 56% | I64: 區間 ±5 個百分點
A65: sh_mem | B65: Advantest 記憶體測試機市占（FY2025 實績 ÷ FY2025 市場，Derived） | C65: % | D65: =sh_mem-0.05 -> 0.4553407 | E65: =a25_mem/(fmk_mem25*fx) -> 0.5053407 | F65: =sh_mem+0.05 -> 0.5553407 | G65: Derived | H65: FY2025 實績（Q 頁）÷（3/4×CY2025＋1/4×CY2026 市場）÷ 匯率 | I65: 公司稱 CY2025 記憶體市占略低於前一年（二手轉述）；±5 個百分點為 Assumed
A66: w_hbm | B66: 記憶體測試機需求中隨 HBM 位元成長的比重（其餘隨 DRAM 設備支出） | C66: % | D66: 0.3 | E66: 0.5 | F66: 0.7 | G66: Assumed | H66: 無：公司稱 HBM 測試機為記憶體成長主力 | I66: 第二來源：未找到
A67: D. 記憶體（讀 markets/memory 與 markets/equipment 成品；唯讀）
A68: hsA_25 | B68: HBM 出貨位元 2025（EB；A） | C68: EB | E68: 2.2251147 | G68: Derived | H68: skhynix/dist/20261025_SK海力士模型_v0.4.2.xlsx｜Mkt!C24:G24 | I68: markets/memory Mkt：出貨＝MIN(需求 × 情境顆數係數, 供給)；2028–29 隨情境，2026–27 三情境相同
A69: hsA_26 | B69: HBM 出貨位元 2026（EB；A） | C69: EB | E69: 3.782695 | G69: Derived | H69: skhynix/dist/20261025_SK海力士模型_v0.4.2.xlsx｜Mkt!C24:G24 | I69: markets/memory Mkt：出貨＝MIN(需求 × 情境顆數係數, 供給)；2028–29 隨情境，2026–27 三情境相同
A70: hsA_27 | B70: HBM 出貨位元 2027（EB；A） | C70: EB | E70: 5.8631772 | G70: Derived | H70: skhynix/dist/20261025_SK海力士模型_v0.4.2.xlsx｜Mkt!C24:G24 | I70: markets/memory Mkt：出貨＝MIN(需求 × 情境顆數係數, 供給)；2028–29 隨情境，2026–27 三情境相同
A71: hsA_28 | B71: HBM 出貨位元 2028（EB；A） | C71: EB | E71: 8.501607 | G71: Derived | H71: skhynix/dist/20261025_SK海力士模型_v0.4.2.xlsx｜Mkt!C24:G24 | I71: markets/memory Mkt：出貨＝MIN(需求 × 情境顆數係數, 供給)；2028–29 隨情境，2026–27 三情境相同
A72: hsA_29 | B72: HBM 出貨位元 2029（EB；A） | C72: EB | E72: 11.477169 | G72: Derived | H72: skhynix/dist/20261025_SK海力士模型_v0.4.2.xlsx｜Mkt!C24:G24 | I72: markets/memory Mkt：出貨＝MIN(需求 × 情境顆數係數, 供給)；2028–29 隨情境，2026–27 三情境相同
A73: hsB_25 | B73: HBM 出貨位元 2025（EB；B） | C73: EB | E73: 2.2251147 | G73: Derived | H73: skhynix/dist/20261025_SK海力士模型_v0.4.2.xlsx｜Mkt!C25:G25 | I73: markets/memory Mkt：出貨＝MIN(需求 × 情境顆數係數, 供給)；2028–29 隨情境，2026–27 三情境相同
A74: hsB_26 | B74: HBM 出貨位元 2026（EB；B） | C74: EB | E74: 3.782695 | G74: Derived | H74: skhynix/dist/20261025_SK海力士模型_v0.4.2.xlsx｜Mkt!C25:G25 | I74: markets/memory Mkt：出貨＝MIN(需求 × 情境顆數係數, 供給)；2028–29 隨情境，2026–27 三情境相同
A75: hsB_27 | B75: HBM 出貨位元 2027（EB；B） | C75: EB | E75: 5.8631772 | G75: Derived | H75: skhynix/dist/20261025_SK海力士模型_v0.4.2.xlsx｜Mkt!C25:G25 | I75: markets/memory Mkt：出貨＝MIN(需求 × 情境顆數係數, 供給)；2028–29 隨情境，2026–27 三情境相同
A76: hsB_28 | B76: HBM 出貨位元 2028（EB；B） | C76: EB | E76: 8.22296 | G76: Derived | H76: skhynix/dist/20261025_SK海力士模型_v0.4.2.xlsx｜Mkt!C25:G25 | I76: markets/memory Mkt：出貨＝MIN(需求 × 情境顆數係數, 供給)；2028–29 隨情境，2026–27 三情境相同
A77: hsB_29 | B77: HBM 出貨位元 2029（EB；B） | C77: EB | E77: 11.357964 | G77: Derived | H77: skhynix/dist/20261025_SK海力士模型_v0.4.2.xlsx｜Mkt!C25:G25 | I77: markets/memory Mkt：出貨＝MIN(需求 × 情境顆數係數, 供給)；2028–29 隨情境，2026–27 三情境相同
A78: hsC_25 | B78: HBM 出貨位元 2025（EB；C） | C78: EB | E78: 2.2251147 | G78: Derived | H78: skhynix/dist/20261025_SK海力士模型_v0.4.2.xlsx｜Mkt!C26:G26 | I78: markets/memory Mkt：出貨＝MIN(需求 × 情境顆數係數, 供給)；2028–29 隨情境，2026–27 三情境相同
A79: hsC_26 | B79: HBM 出貨位元 2026（EB；C） | C79: EB | E79: 3.782695 | G79: Derived | H79: skhynix/dist/20261025_SK海力士模型_v0.4.2.xlsx｜Mkt!C26:G26 | I79: markets/memory Mkt：出貨＝MIN(需求 × 情境顆數係數, 供給)；2028–29 隨情境，2026–27 三情境相同
... A100: semi_test28 | B100: SEMI 測試設備 2028 | C100: US$B | E100: 20.8 | G100: Interested-party | H100: markets/equipment/dist/20261023_半導體設備市場模型_v0.1.3.xlsx｜Mkt!C116:G116 | I100: 同上
A101: E. 其他系統與服務（前一年 × 成長率）
A102: g_oth_26 | B102: 其他系統 FY2026 成長（Q1 FY26 年化 ÷ FY2025 − 1） | C102: % | D102: 0.1 | E102: =q1_oth*4/a25_oth-1 -> 0.29192547 | F102: 0.35 | G102: Derived | H102: Q 頁：Q1 FY26 其他系統 26.0×4÷80.5 | I102: 低／高 Assumed；Q1 年化僅一季
A103: g_svc_26 | B103: 服務與其他 FY2026 成長（Q1 FY26 年化 ÷ FY2025 − 1） | C103: % | D103: 0.1 | E103: =q1_svc*4/a25_svc-1 -> 0.24175824 | F103: 0.3 | G103: Derived | H103: Q 頁：Q1 FY26 服務與其他 33.9×4÷109.2 | I103: 低／高 Assumed
A104: g_oth_A | B104: 其他系統 FY2027–29 年成長（A） | C104: % | D104: 0.1 | E104: 0.15 | F104: 0.2 | G104: Assumed | H104: 無：FY2025 其他系統無前年可比（公司僅揭露合計） | I104: —
A105: g_svc_A | B105: 服務與其他 FY2027–29 年成長（A） | C105: % | D105: 0.08 | E105: 0.12 | F105: 0.16 | G105: Assumed | H105: FY2025 +12.7%（公司：裝機量成長） | I105: —
A106: g_oth_B | B106: 其他系統 FY2027–29 年成長（B） | C106: % | D106: 0.05 | E106: 0.1 | F106: 0.15 | G106: Assumed | H106: 無：FY2025 其他系統無前年可比（公司僅揭露合計） | I106: —
A107: g_svc_B | B107: 服務與其他 FY2027–29 年成長（B） | C107: % | D107: 0.06 | E107: 0.1 | F107: 0.14 | G107: Assumed | H107: FY2025 +12.7%（公司：裝機量成長） | I107: —
A108: g_oth_C | B108: 其他系統 FY2027–29 年成長（C） | C108: % | D108: -0.05 | E108: 0 | F108: 0.05 | G108: Assumed | H108: 無：FY2025 其他系統無前年可比（公司僅揭露合計） | I108: —
A109: g_svc_C | B109: 服務與其他 FY2027–29 年成長（C） | C109: % | D109: 0.02 | E109: 0.06 | F109: 0.1 | G109: Assumed | H109: FY2025 +12.7%（公司：裝機量成長） | I109: —
A110: F. 毛利與營業費用（兩點推導：FY2025 實績與 FY2026 指引；不寫死利益率）
A111: gm_g | B111: FY2026 指引毛利率（66–67% 中點） | C111: % | D111: 0.66 | E111: 0.665 | F111: 0.67 | G111: Interested-party | H111: Advantest Q1 FY26 法說（2026-07-29）：全年毛利率 66–67%（Investing.com 逐字稿摘要） | I111: 第二來源：未找到
A112: gm_a | B112: 毛利率截距（＝FY2025 毛利率 − 斜率 × FY2025 SoC 占比） | C112: % | E112: =a25_gp/a25_rev-gm_b*a25_soc/a25_rev -> 0.31450693 | G112: Derived | H112: 兩點：FY2025（64.3%，SoC 占 68.0%）、FY2026 指引（66.5%，SoC 占 72.6%） | I112: 毛利率隨 SoC 占比上升（公司：產品組合改善）；只有兩點，等同線性外推
A113: gm_b | B113: 毛利率斜率（每增加 1 個百分點 SoC 占比的毛利率變化） | C113: x | E113: =(gm_g-a25_gp/a25_rev)/(g_soc/g_rev-a25_soc/a25_rev) -> 0.48310827 | G113: Derived | H113: 同上 | I113: —
A114: gm_adj_C28 | B114: 情境 C：FY2028 毛利率額外調整（價格競爭） | C114: pt | D114: -0.04 | E114: -0.01 | F114: 0 | G114: Assumed | H114: 無 | I114: Teradyne 搶回份額的價格壓力
A115: gm_adj_C29 | B115: 情境 C：FY2029 毛利率額外調整 | C115: pt | D115: -0.06 | E115: -0.02 | F115: 0 | G115: Assumed | H115: 無 | I115: —
A116: opex25 | B116: 營業費用 FY2025（毛利 − 營業利益） | C116: ¥B | E116: =a25_gp-a25_oi -> 226.5898 | G116: Derived | H116: Q 頁 | I116: —
A117: opex_g | B117: 營業費用 FY2026 指引（指引毛利率 × 指引營收 − 指引營業利益） | C117: ¥B | E117: =gm_g*g_rev-g_oi -> 293.81 | G117: Derived | H117: 指引 | I117: 公司：R&D 全年預測 110.0（較 4 月 +10.0）
A118: opex_var | B118: 營業費用變動部分占營收（兩點斜率） | C118: % | E118: =(opex_g-opex25)/(g_rev-a25_rev) -> 0.11482781 | G118: Derived | H118: （FY2026 指引營業費用 − FY2025）÷（營收差） | I118: —
A119: opex_fix | B119: 營業費用固定部分 | C119: ¥B | E119: =opex25-opex_var*a25_rev -> 96.995134 | G119: Derived | H119: FY2025 營業費用 − 變動部分 × FY2025 營收 | I119: —
A120: phi | B120: 營業費用中變動部分占比（FY2025；Sens 用） | C120: % | D120: 0.35 | E120: =opex_var*a25_rev/opex25 -> 0.57193513 | F120: 0.75 | G120: Derived | H120: 基準＝兩點推導值；低／高 Assumed | I120: —
A121: G. 淨利、股數、匯率
A122: nioi | B122: 淨利 ÷ 營業利益 | C122: x | D122: 0.72 | E122: =a25_ni/a25_oi -> 0.75215388 | F122: =g_ni/g_oi -> 0.78014184 | G122: Derived | H122: 基準＝FY2025 實績 0.752；高＝FY2026 指引隱含 0.780（含戰略投資評價益，屬一次性，不當基準，只在 Sens 列示；處理方式同台積電模型的一次性利益）；低 Assumed（稅率正常化） | I122: FY2025 Q4 含選擇權評價益約 ¥17.3B
A123: shares | B123: 股數（指引淨利 ÷ 指引 EPS） | C123: 百萬股 | E123: =g_ni/g_eps*1000 -> 723.96999 | G123: Derived | H123: 660.0B÷911.64＝約 724.0M | I123: FY2025 加權平均約 728.6M（淨利 375.4B÷515.15）
A124: fx | B124: 匯率 | C124: ¥/US$ | D124: 140 | E124: 150 | F124: 160 | G124: Interested-party | H124: 公司 FY2026 假設：第二季起 ¥150（Q1 FY26 法說；公司原文未開啟） | I124: 第二來源：未找到。FY2025 實績不換匯；只用於把美元市場換成日圓營收
A125: H. 公司指引（FY2026；2026-07-29 上修）與對帳來源
A126: g_rev | B126: 指引營收 FY2026 | C126: ¥B | E126: 1714 | G126: Interested-party | H126: Advantest 2027年3月期 第1四半期決算短信（2026-07-29，J_FR_FY2026_1Q.pdf） | I126: Investing.com Q1 FY26；kabutan（4 月版 1,420.0）
A127: g_oi | B127: 指引營業利益 FY2026 | C127: ¥B | E127: 846 | G127: Interested-party | H127: 同上 | I127: kabutan／gyokaidigest（4 月版 627.5）
A128: g_ni | B128: 指引淨利 FY2026（歸屬母公司） | C128: ¥B | E128: 660 | G128: Interested-party | H128: 同上 | I128: kabutan／gyokaidigest（4 月版 465.5）
A129: g_soc | B129: 指引 SoC 測試機 FY2026 | C129: ¥B | E129: 1243.5 | G129: Interested-party | H129: 公司 Q1 FY26 簡報；Investing.com：由 999.5 上修 | I129: —
A130: g_mem | B130: 指引記憶體測試機 FY2026 | C130: ¥B | E130: 227 | G130: Interested-party | H130: 公司 Q1 FY26 指引（原文未開啟）；4 月版 201.0（+17%，日經摘錄） | I130: 第二來源：未找到
A131: g_eps | B131: 指引 EPS FY2026（基本） | C131: ¥ | E131: 911.64 | G131: Interested-party | H131: 公司決算短信（Yahoo Japan 摘要） | I131: kabutan 記 913.83（差 0.2%，未解）
A132: cons_rev26 | B132: 共識營收 FY2026 | C132: ¥B | E132: 1760 | G132: Interested-party | H132: stockanalysis.com 2026-10-07：¥1.76T | I132: 第二來源：未找到
A133: cons_oi26 | B133: 共識營業利益 FY2026 | C133: ¥B | E133: 886.4 | G133: Interested-party | H133: stockanalysis.com 2026-10-07 | I133: 第二來源：未找到
A134: pk_A | B134: 情境 A：設備市場見頂年度（日曆年；循環位置規則用） | C134: 年 | E134: 2029 | G134: Derived | H134: markets/equipment/dist/20261023_半導體設備市場模型_v0.1.3.xlsx｜Mkt!C12 | I134: 設備股共用規則（tools/cycle_position.py）：FY(t) 早於見頂年＝中段、等於＝見頂、晚於＝谷底；設備市場模型 v0.1.2 的情境係數為 Assumed
A135: pk_B | B135: 情境 B：設備市場見頂年度（日曆年；循環位置規則用） | C135: 年 | E135: 2028 | G135: Derived | H135: markets/equipment/dist/20261023_半導體設備市場模型_v0.1.3.xlsx｜Mkt!C20 | I135: 同上
A136: pk_C | B136: 情境 C：設備市場見頂年度（日曆年；循環位置規則用） | C136: 年 | E136: 2027 | G136: Derived | H136: markets/equipment/dist/20261023_半導體設備市場模型_v0.1.3.xlsx｜Mkt!C28 | I136: 同上
A137: px | B137: 股價（stockanalysis 2026-10-21 收盤） | C137: ¥ | E137: 34440 | G137: Interested-party | H137: stockanalysis.com | I137: 第二來源：未找到
A138: sa_fpe | B138: 遠期 P/E（stockanalysis） | C138: x | E138: 37.7 | G138: Interested-party | H138: stockanalysis.com | I138: 自算：股價 ÷ 指引 EPS，見 Val
A139: I. 目標價情境權重（Val 頁「0. 目標價與上檔空間」用；Andy 可改）
A140: tp_wA | B140: 目標價情境權重 A | C140: % | E140: 0.3 | G140: Assumed | H140: Andy 可改（工作單 2026-10-25 預設 A 0.3／B 0.5／C 0.2） | I140: 三者合計應為 100%（Val 頁第 0 節列示）
A141: tp_wB | B141: 目標價情境權重 B | C141: % | E141: 0.5 | G141: Assumed | H141: Andy 可改（工作單 2026-10-25 預設 A 0.3／B 0.5／C 0.2） | I141: 三者合計應為 100%（Val 頁第 0 節列示）
A142: tp_wC | B142: 目標價情境權重 C | C142: % | E142: 0.2 | G142: Assumed | H142: Andy 可改（工作單 2026-10-25 預設 A 0.3／B 0.5／C 0.2） | I142: 三者合計應為 100%（Val 頁第 0 節列示）

Sheet Q
A1: Q — 實績（十億日圓；EPS 為日圓）。會計年度 4–3 月：FY2025＝2025-04～2026-03。藍字＝輸入；黑字＝公式（Derived）。公司原文（決算短信、Q 別簡報）在建置環境無法開啟，數字取自搜尋引擎對公司文件的摘錄，並與第二來源交叉
A2: FY2026 第二季（2026-07～09）：預定 2026-10-28 15:30 JST 公布（公司 IR 行事曆）；建置日 2026-10-22 尚未公布，故不納入，指引維持 2026-07-29 上修版。公布後更新本頁 H 欄與 In 頁指引
A3: 項目 | B3: FY25 Q1（4–6月） | C3: FY25 Q2（7–9月） | D3: FY25 Q3（10–12月） | E3: FY25 Q4（1–3月） | F3: FY2025 全年 | G3: FY26 Q1（4–6月） | H3: FY26 Q2（未公布） | I3: 標記 | J3: 來源1（公司） | K3: 來源2／說明
A4: SoC 測試機 | B4: 191.3 | C4: 173.7 | D4: 165.2 | E4: 237.2 | F4: 767.4 | G4: 259.6 | H4: 預定 2026-10-28 15:30 JST，尚未公布 | I4: Verified | J4: Advantest 各季 Investor Note（advantest.com/document/en/investors/ir-library/result/）：Q1 191.3（Q2 −17.6 → 173.7；Q4 +72.1 → 237.2）；Q3 以 Q4 反推 165.1–165.2 | K4: Investing.com 各季簡報報導（Q3 165.2、Q4 237.2、FY 767.4）；四季合計＝767.4（見檢查列）
A5: 記憶體測試機 | B5: 33.5 | C5: 43.9 | D5: 57.3 | E5: 36.8 | F5: 171.5 | G5: 48 | I5: Verified | J5: Advantest 各季 Investor Note（advantest.com/document/en/investors/ir-library/result/）：Q1 33.5、Q2 43.9、Q4 36.8（較 Q3 −20.6） | K5: Investing.com：Q3 57.3、FY 171.5、FY26 Q1 48.0；四季合計＝171.5
A6: 其他系統 | B6: 15.8 | D6: 22.6 | F6: 80.5 | G6: 26 | I6: Q1 Derived／其餘 Verified | J6: Q1：測試系統事業 240.6 − SoC − 記憶體（公司 FY2025 Q1 短信：測試系統 240.6）；FY26 Q1：測試系統 333.6 − SoC − 記憶體 | K6: Investing.com：Q3 22.6、FY 80.5；Q2、Q4 單季未找到（見下一列合計）
A7: 服務、支援與其他 | B7: 23.2 | D7: 28.7 | F7: 109.2 | G7: 33.9 | I7: Derived／Verified | J7: FY2025：公司事業別表「Services and Others」109.2（+12.7%）；單季＝營收 − 測試系統 | K7: MarketScreener（公司 FY2025 決算）：109.2 vs 96.9；Q2、Q4 單季未找到
A8: 其他系統＋服務與其他（Q2、Q4 單季未找到分項，列合計） | B8: =B6+B7 -> 39 | C8: =C9-C4-C5 -> 45.3 | D8: =D6+D7 -> 51.3 | E8: =E9-E4-E5 -> 54.1 | F8: =F6+F7 -> 189.7 | G8: =G6+G7 -> 59.9 | I8: Derived | J8: 營收 − SoC − 記憶體 | K8: —
A9: 營收 | B9: 263.8 | C9: 262.9 | D9: 273.8 | E9: 328.1 | F9: 1128.6 | G9: 367.5 | I9: Verified | J9: 公司決算：FY2025 1,128.6（+44.7%）；上半 526.7、前三季 800.5；FY26 Q1 367.5（+39.3%） | K9: Investing.com／kabutan；Q1 FY26 3,675 億日圓
A10: 檢查：SoC＋記憶體＋其他＋服務 − 營收（應為 0） | B10: =B4+B5+B8-B9 -> 0 | C10: =C4+C5+C8-C9 -> 0 | D10: =D4+D5+D8-D9 -> 0 | E10: =E4+E5+E8-E9 -> 0 | F10: =F4+F5+F8-F9 -> 0 | G10: =G4+G5+G8-G9 -> 0 | I10: — | J10: — | K10: —
A11: 毛利率 | B11: 0.651 | D11: 0.62 | E11: 0.674 | F11: 0.643 | G11: 0.695 | I11: Verified／Interested-party | J11: 公司簡報：FY26 Q1 69.5%（前年同期 65.1%）；Q4 67.4%；Q2 僅稱「高於 60%」 | K11: Investing.com：Q3 62.0%、FY2025 64.3%（FY2024 57.1%）
A12: 毛利 | B12: =B9*B11 -> 171.7338 | C12: =F12-B12-D12-E12 -> 163.0606 | D12: =D9*D11 -> 169.756 | E12: =E9*E11 -> 221.1394 | F12: =F9*F11 -> 725.6898 | G12: =G9*G11 -> 255.4125 | I12: Derived | J12: 營收 × 毛利率；Q2＝全年 − 其他三季（殘差，與公司「高於 60%」一致） | K12: Investing.com：Q3 毛利 169.7
A13: 營業利益 | B13: =232.4-C13 -> 124 | C13: 108.4 | D13: 113.6 | E13: 153.1 | F13: 499.1 | G13: 190 | I13: Q1 Derived／其餘 Verified | J13: 公司：上半營業利益 232.4、前三季 346.0、FY 499.1（+118.8%）、Q4 營益率 46.7%；FY26 Q1 190.0（+53.3%） | K13: Investing.com／kabutan；Q2 108.4 為單一二手（Desk Research Design）
A14: 營業利益率 | B14: =B13/B9 -> 0.47005307 | C14: =C13/C9 -> 0.41232408 | D14: =D13/D9 -> 0.41490139 | E14: =E13/E9 -> 0.46662603 | F14: =F13/F9 -> 0.44222931 | G14: =G13/G9 -> 0.5170068 | I14: Derived | J14: — | K14: 公司：FY2025 44.2%、Q4 46.7%、FY26 Q1 51.7%
A15: 營業費用（毛利 − 營業利益） | B15: =B12-B13 -> 47.7338 | C15: =C12-C13 -> 54.6606 | D15: =D12-D13 -> 56.156 | E15: =E12-E13 -> 68.0394 | F15: =F12-F13 -> 226.5898 | G15: =G12-G13 -> 65.4125 | I15: Derived | J15: — | K15: —
A16: 淨利（歸屬母公司） | B16: =169.8-C16 -> 90.2 | C16: 79.6 | D16: 78.7 | E16: 126.9 | F16: 375.4 | G16: 174.8 | I16: Q1 Derived／其餘 Verified | J16: 公司：上半 169.8、FY 375.4（+132.9%）；FY26 Q1 174.8（+93.8%，含戰略投資評價益） | K16: Investing.com；Q2 79.6 單一二手
A17: EPS（基本，日圓） | B17: 123.14 | C17: =232.19-B17 -> 109.05 | D17: =F17-232.19-E17 -> 108.9 | E17: 174.06 | F17: 515.15 | G17: 241.27 | I17: Verified／Derived | J17: 公司決算短信：Q1 123.14、上半 232.19、FY 515.15、Q4 174.06、FY26 Q1 241.27 | K17: 松井證券決算一覽（FY 515.15、Q4 174.06）；Q2、Q3 為差額（Derived）
A18: 檢查：四季合計 − 全年（SoC、記憶體、營收、營業利益、淨利、EPS 依序在 B–G 欄） | B18: =SUM(B4:E4)-F4 -> 0 | C18: =SUM(B5:E5)-F5 -> 0 | D18: =SUM(B9:E9)-F9 -> 0 | E18: =SUM(B13:E13)-F13 -> 0 | F18: =SUM(B16:E16)-F16 -> 0 | G18: =SUM(B17:E17)-F17 -> 0 | I18: — | J18: — | K18: —
A21: FY2026 公司指引（2026-07-29 上修；4 月版供對照）
A22: 項目 | B22: 4 月版 | C22: 7 月版（上修） | D22: 上修幅度 | E22: FY2025 實績 | F22: 7 月版年增 | I22: 標記 | J22: 來源1（公司） | K22: 來源2／說明
A23: 營收 | B23: 1420 | C23: =g_rev -> 1714 | D23: =C23/B23-1 -> 0.20704225 | E23: =a25_rev -> 1128.6 | F23: =C23/E23-1 -> 0.51869573 | I23: Interested-party | J23: 4 月版：公司 FY2025 決算（2026-04-27）；7 月版：Q1 FY26 決算短信（2026-07-29） | K23: kabutan、gyokaidigest、Investing.com；7 月 EPS 公司 911.64、kabutan 913.83
A24: SoC 測試機 | B24: 999.5 | C24: =g_soc -> 1243.5 | D24: =C24/B24-1 -> 0.24412206 | E24: =a25_soc -> 767.4 | F24: =C24/E24-1 -> 0.62040657 | I24: Interested-party | J24: 4 月版：公司 FY2025 決算（2026-04-27）；7 月版：Q1 FY26 決算短信（2026-07-29） | K24: kabutan、gyokaidigest、Investing.com；7 月 EPS 公司 911.64、kabutan 913.83
A25: 記憶體測試機 | B25: 201 | C25: =g_mem -> 227 | D25: =C25/B25-1 -> 0.12935323 | E25: =a25_mem -> 171.5 | F25: =C25/E25-1 -> 0.32361516 | I25: Interested-party | J25: 4 月版：公司 FY2025 決算（2026-04-27）；7 月版：Q1 FY26 決算短信（2026-07-29） | K25: kabutan、gyokaidigest、Investing.com；7 月 EPS 公司 911.64、kabutan 913.83
A26: 其他系統＋服務與其他（營收 − SoC − 記憶體，Derived） | B26: =B23-B24-B25 -> 219.5 | C26: =C23-C24-C25 -> 243.5 | D26: =C26/B26-1 -> 0.10933941 | E26: =a25_oth+a25_svc -> 189.7 | F26: =C26/E26-1 -> 0.28360569 | I26: Interested-party | J26: 4 月版：公司 FY2025 決算（2026-04-27）；7 月版：Q1 FY26 決算短信（2026-07-29） | K26: kabutan、gyokaidigest、Investing.com；7 月 EPS 公司 911.64、kabutan 913.83
A27: 營業利益 | B27: 627.5 | C27: =g_oi -> 846 | D27: =C27/B27-1 -> 0.34820717 | E27: =a25_oi -> 499.1 | F27: =C27/E27-1 -> 0.69505109 | I27: Interested-party | J27: 4 月版：公司 FY2025 決算（2026-04-27）；7 月版：Q1 FY26 決算短信（2026-07-29） | K27: kabutan、gyokaidigest、Investing.com；7 月 EPS 公司 911.64、kabutan 913.83
A28: 淨利 | B28: 465.5 | C28: =g_ni -> 660 | D28: =C28/B28-1 -> 0.41783029 | E28: =a25_ni -> 375.4 | F28: =C28/E28-1 -> 0.75812467 | I28: Interested-party | J28: 4 月版：公司 FY2025 決算（2026-04-27）；7 月版：Q1 FY26 決算短信（2026-07-29） | K28: kabutan、gyokaidigest、Investing.com；7 月 EPS 公司 911.64、kabutan 913.83
A29: EPS（基本，日圓） | C29: =g_eps -> 911.64 | E29: =a25_eps -> 515.15 | F29: =C29/E29-1 -> 0.76965932 | I29: Interested-party | J29: 4 月版：公司 FY2025 決算（2026-04-27）；7 月版：Q1 FY26 決算短信（2026-07-29） | K29: kabutan、gyokaidigest、Investing.com；7 月 EPS 公司 911.64、kabutan 913.83
A30: 營業利益率（指引） | B30: =B27/B23 -> 0.44190141 | C30: =C27/C23 -> 0.49358226 | E30: =a25_oi/a25_rev -> 0.44222931 | K30: 公司：49.4%（FY2025 44.2%）
A32: FY2025 四項合計與營收差約 ¥44B 的查明
A33: SoC＋記憶體＋其他系統＋服務（65.0，二手說法） | B33: =a25_soc+a25_mem+a25_oth+65 -> 1084.4
A34: 營收 − 上列 | B34: =a25_rev-B33 -> 44.2
A35: 「服務、支援與其他」全年（公司事業別表）− 65.0 | B35: =a25_svc-65 -> 44.2
A36: SoC＋記憶體＋其他系統＋「服務、支援與其他」109.2 − 營收（應為 0） | B36: =a25_soc+a25_mem+a25_oth+a25_svc-a25_rev -> 0
A37: 結論：差額 44.2 ＝ 109.2 − 65.0。65.0 是「服務／支援」的子項（二手說法），公司事業別表的第四項是「服務、支援與其他」109.2（含耗材等其他收入）；四項改用 109.2 後與營收完全相符（差 0）。65.0 未在公司原文核到。

Sheet Units
A1: Units — 加速器顆數（百萬顆；日曆年；與 HBM、台積電模型同一份）× 每顆測試時間係數 → 加權顆數；2026 年用公司 CY2026 市場規模校準每加權顆的測試支出
A3: 項目 | B3: 單位 | C3: CY2026 | D3: CY2027 | E3: CY2028 | F3: CY2029 | G3: CY2030 | H3: 說明
A4: 情境 A：加速器顆數
A5: NVIDIA Blackwell（B200／B300） | B5: 百萬顆 | C5: =u_bw_26 -> 5.4 | D5: =u_bw_27 -> 2.4 | E5: =u_bw_28*um28_A -> 0.5 | F5: =u_bw_28*(1+g29_bw)*um29_A -> 0.25 | G5: =F5*(1+cy30g) -> 0.25
A6: NVIDIA Rubin | B6: 百萬顆 | C6: =u_rb_26 -> 1.7 | D6: =u_rb_27 -> 7 | E6: =u_rb_28*um28_A -> 7 | F6: =u_rb_28*(1+g29_rb)*um29_A -> 8.05 | G6: =F6*(1+cy30g) -> 8.05
A7: NVIDIA Rubin Ultra | B7: 百萬顆 | C7: =u_ru_26 -> 0 | D7: =u_ru_27 -> 0.3 | E7: =u_ru_28*um28_A -> 2 | F7: =u_ru_28*(1+g29_ru)*um29_A -> 2.3 | G7: =F7*(1+cy30g) -> 2.3
A8: NVIDIA Hopper（H200 等） | B8: 百萬顆 | C8: =u_hp_26 -> 0.5 | D8: =u_hp_27 -> 0 | E8: =u_hp_28*um28_A -> 0 | F8: =u_hp_28*(1+g29_hp)*um29_A -> 0 | G8: =F8*(1+cy30g) -> 0
A9: AMD Instinct | B9: 百萬顆 | C9: =u_amd_26 -> 0.75 | D9: =u_amd_27 -> 1.5 | E9: =u_amd_28*um28_A -> 2 | F9: =u_amd_28*(1+g29_amd)*um29_A -> 2.3 | G9: =F9*(1+cy30g) -> 2.3
A10: Google TPU | B10: 百萬顆 | C10: =u_tpu_26 -> 3.85 | D10: =u_tpu_27 -> 5.5 | E10: =u_tpu_28*um28_A -> 7 | F10: =u_tpu_28*(1+g29_tpu)*um29_A -> 8.05 | G10: =F10*(1+cy30g) -> 8.05
A11: AWS Trainium | B11: 百萬顆 | C11: =u_trn_26 -> 2 | D11: =u_trn_27 -> 2.5 | E11: =u_trn_28*um28_A -> 3 | F11: =u_trn_28*(1+g29_trn)*um29_A -> 3.45 | G11: =F11*(1+cy30g) -> 3.45
A12: 其他 ASIC（MTIA、Maia、Ascend 等） | B12: 百萬顆 | C12: =u_oth_26 -> 1 | D12: =u_oth_27 -> 4.5 | E12: =u_oth_28*um28_A -> 5 | F12: =u_oth_28*(1+g29_oth)*um29_A -> 5.75 | G12: =F12*(1+cy30g) -> 5.75
A13: 合計 | B13: 百萬顆 | C13: =SUM(C5:C12) -> 15.2 | D13: =SUM(D5:D12) -> 23.7 | E13: =SUM(E5:E12) -> 26.5 | F13: =SUM(F5:F12) -> 30.15 | G13: =SUM(G5:G12) -> 30.15 | H13: 2026＝15.2、2027＝23.7、2028＝26.5（A）；與 markets/memory 的 UNITS 相同
A15: 情境 B：加速器顆數
A16: NVIDIA Blackwell（B200／B300） | B16: 百萬顆 | C16: =u_bw_26 -> 5.4 | D16: =u_bw_27 -> 2.4 | E16: =u_bw_28*um28_B -> 0.4 | F16: =u_bw_28*(1+g29_bw)*um29_B -> 0.2125 | G16: =F16*(1+cy30g) -> 0.2125
A17: NVIDIA Rubin | B17: 百萬顆 | C17: =u_rb_26 -> 1.7 | D17: =u_rb_27 -> 7 | E17: =u_rb_28*um28_B -> 5.6 | F17: =u_rb_28*(1+g29_rb)*um29_B -> 6.8425 | G17: =F17*(1+cy30g) -> 6.8425
A18: NVIDIA Rubin Ultra | B18: 百萬顆 | C18: =u_ru_26 -> 0 | D18: =u_ru_27 -> 0.3 | E18: =u_ru_28*um28_B -> 1.6 | F18: =u_ru_28*(1+g29_ru)*um29_B -> 1.955 | G18: =F18*(1+cy30g) -> 1.955
A19: NVIDIA Hopper（H200 等） | B19: 百萬顆 | C19: =u_hp_26 -> 0.5 | D19: =u_hp_27 -> 0 | E19: =u_hp_28*um28_B -> 0 | F19: =u_hp_28*(1+g29_hp)*um29_B -> 0 | G19: =F19*(1+cy30g) -> 0
A20: AMD Instinct | B20: 百萬顆 | C20: =u_amd_26 -> 0.75 | D20: =u_amd_27 -> 1.5 | E20: =u_amd_28*um28_B -> 1.6 | F20: =u_amd_28*(1+g29_amd)*um29_B -> 1.955 | G20: =F20*(1+cy30g) -> 1.955
A21: Google TPU | B21: 百萬顆 | C21: =u_tpu_26 -> 3.85 | D21: =u_tpu_27 -> 5.5 | E21: =u_tpu_28*um28_B -> 5.6 | F21: =u_tpu_28*(1+g29_tpu)*um29_B -> 6.8425 | G21: =F21*(1+cy30g) -> 6.8425
A22: AWS Trainium | B22: 百萬顆 | C22: =u_trn_26 -> 2 | D22: =u_trn_27 -> 2.5 | E22: =u_trn_28*um28_B -> 2.4 | F22: =u_trn_28*(1+g29_trn)*um29_B -> 2.9325 | G22: =F22*(1+cy30g) -> 2.9325
A23: 其他 ASIC（MTIA、Maia、Ascend 等） | B23: 百萬顆 | C23: =u_oth_26 -> 1 | D23: =u_oth_27 -> 4.5 | E23: =u_oth_28*um28_B -> 4 | F23: =u_oth_28*(1+g29_oth)*um29_B -> 4.8875 | G23: =F23*(1+cy30g) -> 4.8875
A24: 合計 | B24: 百萬顆 | C24: =SUM(C16:C23) -> 15.2 | D24: =SUM(D16:D23) -> 23.7 | E24: =SUM(E16:E23) -> 21.2 | F24: =SUM(F16:F23) -> 25.6275 | G24: =SUM(G16:G23) -> 25.6275 | H24: 2028–29 乘以情境係數 um28／um29（台積電模型）
A26: 情境 C：加速器顆數
A27: NVIDIA Blackwell（B200／B300） | B27: 百萬顆 | C27: =u_bw_26 -> 5.4 | D27: =u_bw_27 -> 2.4 | E27: =u_bw_28*um28_C -> 0.3 | F27: =u_bw_28*(1+g29_bw)*um29_C -> 0.15 | G27: =F27*(1+cy30g) -> 0.15
A28: NVIDIA Rubin | B28: 百萬顆 | C28: =u_rb_26 -> 1.7 | D28: =u_rb_27 -> 7 | E28: =u_rb_28*um28_C -> 4.2 | F28: =u_rb_28*(1+g29_rb)*um29_C -> 4.83 | G28: =F28*(1+cy30g) -> 4.83
A29: NVIDIA Rubin Ultra | B29: 百萬顆 | C29: =u_ru_26 -> 0 | D29: =u_ru_27 -> 0.3 | E29: =u_ru_28*um28_C -> 1.2 | F29: =u_ru_28*(1+g29_ru)*um29_C -> 1.38 | G29: =F29*(1+cy30g) -> 1.38
A30: NVIDIA Hopper（H200 等） | B30: 百萬顆 | C30: =u_hp_26 -> 0.5 | D30: =u_hp_27 -> 0 | E30: =u_hp_28*um28_C -> 0 | F30: =u_hp_28*(1+g29_hp)*um29_C -> 0 | G30: =F30*(1+cy30g) -> 0
A31: AMD Instinct | B31: 百萬顆 | C31: =u_amd_26 -> 0.75 | D31: =u_amd_27 -> 1.5 | E31: =u_amd_28*um28_C -> 1.2 | F31: =u_amd_28*(1+g29_amd)*um29_C -> 1.38 | G31: =F31*(1+cy30g) -> 1.38
A32: Google TPU | B32: 百萬顆 | C32: =u_tpu_26 -> 3.85 | D32: =u_tpu_27 -> 5.5 | E32: =u_tpu_28*um28_C -> 4.2 | F32: =u_tpu_28*(1+g29_tpu)*um29_C -> 4.83 | G32: =F32*(1+cy30g) -> 4.83
A33: AWS Trainium | B33: 百萬顆 | C33: =u_trn_26 -> 2 | D33: =u_trn_27 -> 2.5 | E33: =u_trn_28*um28_C -> 1.8 | F33: =u_trn_28*(1+g29_trn)*um29_C -> 2.07 | G33: =F33*(1+cy30g) -> 2.07
A34: 其他 ASIC（MTIA、Maia、Ascend 等） | B34: 百萬顆 | C34: =u_oth_26 -> 1 | D34: =u_oth_27 -> 4.5 | E34: =u_oth_28*um28_C -> 3 | F34: =u_oth_28*(1+g29_oth)*um29_C -> 3.45 | G34: =F34*(1+cy30g) -> 3.45
A35: 合計 | B35: 百萬顆 | C35: =SUM(C27:C34) -> 15.2 | D35: =SUM(D27:D34) -> 23.7 | E35: =SUM(E27:E34) -> 15.9 | F35: =SUM(F27:F34) -> 18.09 | G35: =SUM(G27:G34) -> 18.09 | H35: 2028–29 乘以情境係數 um28／um29（台積電模型）
A37: 測試時間加權顆數（Σ 顆數 × tt）
A38: 情境 A | B38: 百萬顆（Blackwell 等值） | C38: =C5*tt_bw+C6*tt_rb+C7*tt_ru+C8*tt_hp+C9*tt_amd+C10*tt_tpu+C11*tt_trn+C12*tt_oth -> 14.885 | D38: =D5*tt_bw+D6*tt_rb+D7*tt_ru+D8*tt_hp+D9*tt_amd+D10*tt_tpu+D11*tt_trn+D12*tt_oth -> 24.31 | E38: =E5*tt_bw+E6*tt_rb+E7*tt_ru+E8*tt_hp+E9*tt_amd+E10*tt_tpu+E11*tt_trn+E12*tt_oth -> 28.1 | F38: =F5*tt_bw+F6*tt_rb+F7*tt_ru+F8*tt_hp+F9*tt_amd+F10*tt_tpu+F11*tt_trn+F12*tt_oth -> 31.99 | G38: =G5*tt_bw+G6*tt_rb+G7*tt_ru+G8*tt_hp+G9*tt_amd+G10*tt_tpu+G11*tt_trn+G12*tt_oth -> 31.99
A39: 情境 B | B39: 百萬顆（Blackwell 等值） | C39: =C16*tt_bw+C17*tt_rb+C18*tt_ru+C19*tt_hp+C20*tt_amd+C21*tt_tpu+C22*tt_trn+C23*tt_oth -> 14.885 | D39: =D16*tt_bw+D17*tt_rb+D18*tt_ru+D19*tt_hp+D20*tt_amd+D21*tt_tpu+D22*tt_trn+D23*tt_oth -> 24.31 | E39: =E16*tt_bw+E17*tt_rb+E18*tt_ru+E19*tt_hp+E20*tt_amd+E21*tt_tpu+E22*tt_trn+E23*tt_oth -> 22.48 | F39: =F16*tt_bw+F17*tt_rb+F18*tt_ru+F19*tt_hp+F20*tt_amd+F21*tt_tpu+F22*tt_trn+F23*tt_oth -> 27.1915 | G39: =G16*tt_bw+G17*tt_rb+G18*tt_ru+G19*tt_hp+G20*tt_amd+G21*tt_tpu+G22*tt_trn+G23*tt_oth -> 27.1915
A40: 情境 C | B40: 百萬顆（Blackwell 等值） | C40: =C27*tt_bw+C28*tt_rb+C29*tt_ru+C30*tt_hp+C31*tt_amd+C32*tt_tpu+C33*tt_trn+C34*tt_oth -> 14.885 | D40: =D27*tt_bw+D28*tt_rb+D29*tt_ru+D30*tt_hp+D31*tt_amd+D32*tt_tpu+D33*tt_trn+D34*tt_oth -> 24.31 | E40: =E27*tt_bw+E28*tt_rb+E29*tt_ru+E30*tt_hp+E31*tt_amd+E32*tt_tpu+E33*tt_trn+E34*tt_oth -> 16.86 | F40: =F27*tt_bw+F28*tt_rb+F29*tt_ru+F30*tt_hp+F31*tt_amd+F32*tt_tpu+F33*tt_trn+F34*tt_oth -> 19.194 | G40: =G27*tt_bw+G28*tt_rb+G29*tt_ru+G30*tt_hp+G31*tt_amd+G32*tt_tpu+G33*tt_trn+G34*tt_oth -> 19.194
A42: 校準（只用公司 CY2026 市場規模，不用共識）
A43: CY2026 SoC 測試機市場（公司） | B43: US$B | C43: =mk_soc26 -> 11 | H43: Interested-party
A44: − 非 AI SoC（Analogy：AI 前的 SoC 測試機市場） | B44: US$B | C44: =nonai26 -> 4.3 | H44: Analogy，3.7–4.9；見 In 頁
A45: ＝ AI SoC 測試機市場 CY2026 | B45: US$B | C45: =C43-C44 -> 6.7 | H45: Derived
A46: ÷ CY2026 加權顆數（情境 A＝B＝C，2026 年無情境係數） | B46: 百萬顆 | C46: =C38 -> 14.885
A47: ＝ 每加權顆測試支出 | B47: US$／顆 | C47: =C45/C46*1000 -> 450.11757 | H47: Derived：每顆 Blackwell 等值的測試機支出
A48: ÷ 測試機單價（Assumed）＝ 每百萬顆所需機台數 k | B48: 台／百萬顆 | C48: =C47/asp_m -> 300.07838 | H48: Derived（單價為 Assumed 1.0–2.5 US$M；k 與單價只有乘積可識別）
A50: FY2025 市場（3/4×CY2025＋1/4×CY2026；用於 FY2025 隱含市占與記憶體市占）
A51: SoC 測試機 | B51: =0.75*mk_soc25+0.25*mk_soc26 -> 7.925
A52: 記憶體測試機 | B52: =0.75*mk_mem25+0.25*mk_mem26 -> 2.2625
A54: 測試時間係數（Assumed；Blackwell＝1.0）
A55: 平台 | C55: 低 | D55: 基準 | E55: 高
A56: NVIDIA Blackwell（B200／B300） | C56: =tt_bw_lo -> 0.9 | D56: =tt_bw -> 1 | E56: =tt_bw_hi -> 1.1
A57: NVIDIA Rubin | C57: =tt_rb_lo -> 1.1 | D57: =tt_rb -> 1.3 | E57: =tt_rb_hi -> 1.6
A58: NVIDIA Rubin Ultra | C58: =tt_ru_lo -> 1.3 | D58: =tt_ru -> 1.7 | E58: =tt_ru_hi -> 2.2
A59: NVIDIA Hopper（H200 等） | C59: =tt_hp_lo -> 0.5 | D59: =tt_hp -> 0.6 | E59: =tt_hp_hi -> 0.8
A60: AMD Instinct | C60: =tt_amd_lo -> 0.9 | D60: =tt_amd -> 1.1 | E60: =tt_amd_hi -> 1.4
A61: Google TPU | C61: =tt_tpu_lo -> 0.8 | D61: =tt_tpu -> 1 | E61: =tt_tpu_hi -> 1.3
A62: AWS Trainium | C62: =tt_trn_lo -> 0.6 | D62: =tt_trn -> 0.8 | E62: =tt_trn_hi -> 1.1
A63: 其他 ASIC（MTIA、Maia、Ascend 等） | C63: =tt_oth_lo -> 0.5 | D63: =tt_oth -> 0.7 | E63: =tt_oth_hi -> 1
A65: 核對（PL 引擎的加權顆數 − 本頁，應為 0）在 PL 頁底部。

Sheet PL
A1: PL — Advantest 損益（¥B；FY2025 為實績，FY2026–FY2029 為模型）。三情境各一個完整推導區塊（見下方），本頁頂端為摘要
A3: 情境／項目 | B3: 單位 | C3: FY2025A | D3: FY2026 | E3: FY2027 | F3: FY2028 | G3: FY2029 | H3: 說明
A4: 情境 A
A5: 營收 | B5: ¥B | C5: =C57 -> 1128.6 | D5: =D57 -> 1669.8353 | E5: =E57 -> 2169.0494 | F5: =F57 -> 2482.1404 | G5: =G57 -> 2737.792
A6: 營收 | B6: US$B | C6: =C66 -> 7.524 | D6: =D66 -> 11.132235 | E6: =E66 -> 14.46033 | F6: =F66 -> 16.547603 | G6: =G66 -> 18.251947
A7: SoC 測試機 | B7: ¥B | C7: =C53 -> 767.4 | D7: =D53 -> 1198.2554 | E7: =E53 -> 1572.6709 | F7: =F53 -> 1760.5597 | G7: =G53 -> 1909.17
A8: 記憶體測試機 | B8: ¥B | C8: =C54 -> 171.5 | D8: =D54 -> 231.97993 | E8: =E54 -> 324.90655 | F8: =F54 -> 413.944 | G8: =G54 -> 479.94276
A9: 毛利率 | B9: % | C9: =C59 -> 0.643 | D9: =D59 -> 0.66118008 | E9: =E59 -> 0.66478493 | F9: =F59 -> 0.65717125 | G9: =G59 -> 0.65139731
A10: 營業利益 | B10: ¥B | C10: =C62 -> 499.1 | D10: =D62 -> 815.32317 | E10: =E62 -> 1095.889 | F10: =F62 -> 1249.1774 | G10: =G62 -> 1372.0206
A11: 營業利益率 | B11: % | C11: =C63 -> 0.44222931 | D11: =D63 -> 0.48826562 | E11: =E63 -> 0.50523931 | F11: =F63 -> 0.50326623 | G11: =G63 -> 0.50114127
A12: 淨利 | B12: ¥B | C12: =C64 -> 375.4 | D12: =D64 -> 613.24848 | E12: =E64 -> 824.27719 | F12: =F64 -> 939.57365 | G12: =G64 -> 1031.9706
A13: EPS | B13: ¥ | C13: =C65 -> 515.15 | D13: =D65 -> 847.06341 | E13: =E65 -> 1138.5516 | F13: =F65 -> 1297.8075 | G13: =G65 -> 1425.4328
A15: 情境 B
A16: 營收 | B16: ¥B | C16: =C86 -> 1128.6 | D16: =D86 -> 1669.8353 | E16: =E86 -> 2092.4375 | F16: =F86 -> 2196.6045 | G16: =G86 -> 2461.1593
A17: 營收 | B17: US$B | C17: =C95 -> 7.524 | D17: =D95 -> 11.132235 | E17: =E95 -> 13.949583 | F17: =F95 -> 14.64403 | G17: =G95 -> 16.407729
A18: SoC 測試機 | B18: ¥B | C18: =C82 -> 767.4 | D18: =D82 -> 1198.2554 | E18: =E82 -> 1510.0618 | F18: =F82 -> 1519.2752 | G18: =G82 -> 1695.341
A19: 記憶體測試機 | B19: ¥B | C19: =C83 -> 171.5 | D19: =D83 -> 231.97993 | E19: =E83 -> 318.81568 | F19: =F83 -> 387.41336 | G19: =G83 -> 446.91077
A20: 毛利率 | B20: % | C20: =C88 -> 0.643 | D20: =D88 -> 0.66118008 | E20: =E88 -> 0.66315454 | F20: =F88 -> 0.64864736 | G20: =G88 -> 0.64729043
A21: 營業利益 | B21: ¥B | C21: =C91 -> 499.1 | D21: =D91 -> 815.32317 | E21: =E91 -> 1050.3443 | F21: =F91 -> 1075.5953 | G21: =G91 -> 1213.4802
A22: 營業利益率 | B22: % | C22: =C92 -> 0.44222931 | D22: =D92 -> 0.48826562 | E22: =E92 -> 0.50197164 | F22: =F92 -> 0.4896627 | G22: =G92 -> 0.49305228
A23: 淨利 | B23: ¥B | C23: =C93 -> 375.4 | D23: =D93 -> 613.24848 | E23: =E93 -> 790.0205 | F23: =F93 -> 809.01319 | G23: =G93 -> 912.72385
A24: EPS | B24: ¥ | C24: =C94 -> 515.15 | D24: =D94 -> 847.06341 | E24: =E94 -> 1091.2338 | F24: =F94 -> 1117.4679 | G24: =G94 -> 1260.7206
A26: 情境 C
A27: 營收 | B27: ¥B | C27: =C115 -> 1128.6 | D27: =D115 -> 1669.8353 | E27: =E115 -> 1992.7932 | F27: =F115 -> 1700.0758 | G27: =G115 -> 1735.3031
A28: 營收 | B28: US$B | C28: =C124 -> 7.524 | D28: =D124 -> 11.132235 | E28: =E124 -> 13.285288 | F28: =F124 -> 11.333839 | G28: =G124 -> 11.568687
A29: SoC 測試機 | B29: ¥B | C29: =C111 -> 767.4 | D29: =D111 -> 1198.2554 | E29: =E111 -> 1447.4527 | F29: =F111 -> 1148.2348 | G29: =G111 -> 1136.0866
A30: 記憶體測試機 | B30: ¥B | C30: =C112 -> 171.5 | D30: =D112 -> 231.97993 | E30: =E112 -> 297.60449 | F30: =F112 -> 295.48079 | G30: =G112 -> 333.71471
A31: 毛利率 | B31: % | C31: =C117 -> 0.643 | D31: =D117 -> 0.66118008 | E31: =E117 -> 0.66540955 | F31: =F117 -> 0.63079929 | G31: =G117 -> 0.61079337
A32: 營業利益 | B32: ¥B | C32: =C120 -> 499.1 | D32: =D120 -> 815.32317 | E32: =E120 -> 1000.2004 | F32: =F120 -> 780.19548 | G32: =G120 -> 763.65544
A33: 營業利益率 | B33: % | C33: =C121 -> 0.44222931 | D33: =D121 -> 0.48826562 | E33: =E121 -> 0.50190879 | F33: =F121 -> 0.45891806 | G33: =G121 -> 0.44007035
A34: 淨利 | B34: ¥B | C34: =C122 -> 375.4 | D34: =D122 -> 613.24848 | E34: =E122 -> 752.30461 | F34: =F122 -> 586.82705 | G34: =G122 -> 574.3864
A35: EPS | B35: ¥ | C35: =C123 -> 515.15 | D35: =D123 -> 847.06341 | E35: =E123 -> 1039.1378 | F35: =F123 -> 810.56821 | G35: =G123 -> 793.38427
A37: 核對：PL 引擎加權顆數 − Units（應為 0）
A38: 情境 A | C38: =ABS(C43-Units!C38)+ABS(D43-Units!D38)+ABS(E43-Units!E38)+ABS(F43-Units!F38)+ABS(G43-Units!G38) -> 0
A39: 情境 B | C39: =ABS(C72-Units!C39)+ABS(D72-Units!D39)+ABS(E72-Units!E39)+ABS(F72-Units!F39)+ABS(G72-Units!G39) -> 0
A40: 情境 C | C40: =ABS(C101-Units!C40)+ABS(D101-Units!D40)+ABS(E101-Units!E40)+ABS(F101-Units!F40)+ABS(G101-Units!G40) -> 0
A41: 項目 | B41: 單位 | C41: CY2026／FY2025 | D41: CY2027／FY2026 | E41: CY2028／FY2027 | F41: CY2029／FY2028 | G41: CY2030／FY2029 | H41: 說明
A42: A. 日曆年（C＝CY2026 … G＝CY2030）
A43: 測試時間加權顆數 | B43: 百萬顆 | C43: =u_bw_26*tt_bw+u_rb_26*tt_rb+u_ru_26*tt_ru+u_hp_26*tt_hp+u_amd_26*tt_amd+u_tpu_26*tt_tpu+u_trn_26*tt_trn+u_oth_26*tt_oth -> 14.885 | D43: =u_bw_27*tt_bw+u_rb_27*tt_rb+u_ru_27*tt_ru+u_hp_27*tt_hp+u_amd_27*tt_amd+u_tpu_27*tt_tpu+u_trn_27*tt_trn+u_oth_27*tt_oth -> 24.31 | E43: =u_bw_28*um28_A*tt_bw+u_rb_28*um28_A*tt_rb+u_ru_28*um28_A*tt_ru+u_hp_28*um28_A*tt_hp+u_amd_28*um28_A*tt_amd+u_tpu_28*um28_A*tt_tpu+u_trn_28*um28_A*tt_trn+u_oth_28*um28_A*tt_oth -> 28.1 | F43: =u_bw_28*(1+g29_bw)*um29_A*tt_bw+u_rb_28*(1+g29_rb)*um29_A*tt_rb+u_ru_28*(1+g29_ru)*um29_A*tt_ru+u_hp_28*(1+g29_hp)*um29_A*tt_hp+u_amd_28*(1+g29_amd)*um29_A*tt_amd+u_tpu_28*(1+g29_tpu)*um29_A*tt_tpu+u_trn_28*(1+g29_trn)*um29_A*tt_trn+u_oth_28*(1+g29_oth)*um29_A*tt_oth -> 31.99 | G43: =F43*(1+cy30g) -> 31.99 | H43: Σ 顆數 × tt；CY2030＝CY2029×(1+cy30g)
A44: 每加權顆測試支出（以 CY2026 校準） | B44: US$B／百萬顆 | C44: =(mk_soc26-nonai26)/C43 -> 0.45011757 | H44: （公司 CY2026 SoC 市場 − 非 AI）÷ 加權顆數
A45: AI SoC 測試機市場 | B45: US$B | C45: =$C$44*C43*(1-0)^0 -> 6.7 | D45: =$C$44*D43*(1-0)^1 -> 10.942358 | E45: =$C$44*E43*(1-0)^2 -> 12.648304 | F45: =$C$44*F43*(1-0)^3 -> 14.399261 | G45: =$C$44*G43*(1-0)^4 -> 14.399261
A46: 非 AI SoC 測試機市場 | B46: US$B | C46: =nonai26*(1+g_nonai)^0 -> 4.3 | D46: =nonai26*(1+g_nonai)^1 -> 4.472 | E46: =nonai26*(1+g_nonai)^2 -> 4.65088 | F46: =nonai26*(1+g_nonai)^3 -> 4.8369152 | G46: =nonai26*(1+g_nonai)^4 -> 5.0303918
A47: SoC 測試機市場 CY | B47: US$B | C47: =C45+C46 -> 11 | D47: =D45+D46 -> 15.414358 | E47: =E45+E46 -> 17.299184 | F47: =F45+F46 -> 19.236176 | G47: =G45+G46 -> 19.429653 | H47: CY2026 ＝ 公司規模（校準）
A48: 記憶體測試機市場 CY | B48: US$B | C48: =mk_mem26*(w_hbm*hsA_26/hsA_26+(1-w_hbm)*drA_26/drA_26) -> 2.75 | D48: =mk_mem26*(w_hbm*hsA_27/hsA_26+(1-w_hbm)*drA_27/drA_26) -> 3.9915065 | E48: =mk_mem26*(w_hbm*hsA_28/hsA_26+(1-w_hbm)*drA_28/drA_26) -> 5.1706953 | F48: =mk_mem26*(w_hbm*hsA_29/hsA_26+(1-w_hbm)*drA_29/drA_26) -> 6.3316064 | G48: =F48*(1+cy30g) -> 6.3316064 | H48: CY2026 錨定公司規模；之後＝w×HBM 出貨位元指數＋(1−w)×DRAM 設備支出指數
A49: B. 會計年度（C＝FY2025 … G＝FY2029；FY(t)＝3/4×CY(t)＋1/4×CY(t+1)）
A50: SoC 測試機市場 FY | B50: US$B | C50: =fmk_soc25 -> 7.925 | D50: =0.75*C47+0.25*D47 -> 12.10359 | E50: =0.75*D47+0.25*E47 -> 15.885564 | F50: =0.75*E47+0.25*F47 -> 17.783432 | G50: =0.75*F47+0.25*G47 -> 19.284545
A51: 記憶體測試機市場 FY | B51: US$B | C51: =fmk_mem25 -> 2.2625 | D51: =0.75*C48+0.25*D48 -> 3.0603766 | E51: =0.75*D48+0.25*E48 -> 4.2863037 | F51: =0.75*E48+0.25*F48 -> 5.4609231 | G51: =0.75*F48+0.25*G48 -> 6.3316064
A52: Advantest SoC 市占 | B52: % | C52: =a25_soc/(C50*fx) -> 0.64555205 | D52: =sh_soc -> 0.66 | E52: =sh_soc -> 0.66 | F52: =sh_soc -> 0.66 | G52: =sh_soc -> 0.66 | H52: FY2025＝實績隱含（對照公司自估 66%）
A53: SoC 測試機營收 | B53: ¥B | C53: =a25_soc -> 767.4 | D53: =D50*D52*fx -> 1198.2554 | E53: =E50*E52*fx -> 1572.6709 | F53: =F50*F52*fx -> 1760.5597 | G53: =G50*G52*fx -> 1909.17 | H53: 市場 × 市占 × 匯率
A54: 記憶體測試機營收 | B54: ¥B | C54: =a25_mem -> 171.5 | D54: =D51*sh_mem*fx -> 231.97993 | E54: =E51*sh_mem*fx -> 324.90655 | F54: =F51*sh_mem*fx -> 413.944 | G54: =G51*sh_mem*fx -> 479.94276
A55: 其他系統營收 | B55: ¥B | C55: =a25_oth -> 80.5 | D55: =C55*(1+g_oth_26) -> 104 | E55: =D55*(1+g_oth_A) -> 119.6 | F55: =E55*(1+g_oth_A) -> 137.54 | G55: =F55*(1+g_oth_A) -> 158.171
A56: 服務、支援與其他營收 | B56: ¥B | C56: =a25_svc -> 109.2 | D56: =C56*(1+g_svc_26) -> 135.6 | E56: =D56*(1+g_svc_A) -> 151.872 | F56: =E56*(1+g_svc_A) -> 170.09664 | G56: =F56*(1+g_svc_A) -> 190.50824
A57: 營收 | B57: ¥B | C57: =C53+C54+C55+C56 -> 1128.6 | D57: =D53+D54+D55+D56 -> 1669.8353 | E57: =E53+E54+E55+E56 -> 2169.0494 | F57: =F53+F54+F55+F56 -> 2482.1404 | G57: =G53+G54+G55+G56 -> 2737.792
A58: SoC 占營收 | B58: % | C58: =C53/C57 -> 0.67995747 | D58: =D53/D57 -> 0.71758896 | E58: =E53/E57 -> 0.72505073 | F58: =F53/F57 -> 0.70929096 | G58: =G53/G57 -> 0.69733931
A59: 毛利率 | B59: % | C59: =a25_gp/a25_rev -> 0.643 | D59: =gm_a+gm_b*D58+0 -> 0.66118008 | E59: =gm_a+gm_b*E58+0 -> 0.66478493 | F59: =gm_a+gm_b*F58+0 -> 0.65717125 | G59: =gm_a+gm_b*G58+0 -> 0.65139731 | H59: 截距＋斜率×SoC 占比（兩點推導）
A60: 毛利 | B60: ¥B | C60: =C57*C59 -> 725.6898 | D60: =D57*D59 -> 1104.0618 | E60: =E57*E59 -> 1441.9514 | F60: =F57*F59 -> 1631.1913 | G60: =G57*G59 -> 1783.3903
A61: 營業費用 | B61: ¥B | C61: =opex25 -> 226.5898 | D61: =opex_fix+opex_var*D57 -> 288.73866 | E61: =opex_fix+opex_var*E57 -> 346.06233 | F61: =opex_fix+opex_var*F57 -> 382.01388 | G61: =opex_fix+opex_var*G57 -> 411.36979 | H61: 固定＋變動×營收
A62: 營業利益 | B62: ¥B | C62: =C60-C61 -> 499.1 | D62: =D60-D61 -> 815.32317 | E62: =E60-E61 -> 1095.889 | F62: =F60-F61 -> 1249.1774 | G62: =G60-G61 -> 1372.0206
A63: 營業利益率 | B63: % | C63: =C62/C57 -> 0.44222931 | D63: =D62/D57 -> 0.48826562 | E63: =E62/E57 -> 0.50523931 | F63: =F62/F57 -> 0.50326623 | G63: =G62/G57 -> 0.50114127
A64: 淨利 | B64: ¥B | C64: =a25_ni -> 375.4 | D64: =D62*nioi -> 613.24848 | E64: =E62*nioi -> 824.27719 | F64: =F62*nioi -> 939.57365 | G64: =G62*nioi -> 1031.9706
A65: EPS | B65: ¥ | C65: =a25_eps -> 515.15 | D65: =D64*1000/shares -> 847.06341 | E65: =E64*1000/shares -> 1138.5516 | F65: =F64*1000/shares -> 1297.8075 | G65: =G64*1000/shares -> 1425.4328
A66: 營收（美元） | B66: US$B | C66: =C57/fx -> 7.524 | D66: =D57/fx -> 11.132235 | E66: =E57/fx -> 14.46033 | F66: =F57/fx -> 16.547603 | G66: =G57/fx -> 18.251947 | H66: FY2025 以基準匯率換算（顯示用）
A69: 情境 B：2028 顆數 ×0.8、2029 ×0.85
A70: 項目 | B70: 單位 | C70: CY2026／FY2025 | D70: CY2027／FY2026 | E70: CY2028／FY2027 | F70: CY2029／FY2028 | G70: CY2030／FY2029 | H70: 說明
A71: A. 日曆年（C＝CY2026 … G＝CY2030）
A72: 測試時間加權顆數 | B72: 百萬顆 | C72: =u_bw_26*tt_bw+u_rb_26*tt_rb+u_ru_26*tt_ru+u_hp_26*tt_hp+u_amd_26*tt_amd+u_tpu_26*tt_tpu+u_trn_26*tt_trn+u_oth_26*tt_oth -> 14.885 | D72: =u_bw_27*tt_bw+u_rb_27*tt_rb+u_ru_27*tt_ru+u_hp_27*tt_hp+u_amd_27*tt_amd+u_tpu_27*tt_tpu+u_trn_27*tt_trn+u_oth_27*tt_oth -> 24.31 | E72: =u_bw_28*um28_B*tt_bw+u_rb_28*um28_B*tt_rb+u_ru_28*um28_B*tt_ru+u_hp_28*um28_B*tt_hp+u_amd_28*um28_B*tt_amd+u_tpu_28*um28_B*tt_tpu+u_trn_28*um28_B*tt_trn+u_oth_28*um28_B*tt_oth -> 22.48 | F72: =u_bw_28*(1+g29_bw)*um29_B*tt_bw+u_rb_28*(1+g29_rb)*um29_B*tt_rb+u_ru_28*(1+g29_ru)*um29_B*tt_ru+u_hp_28*(1+g29_hp)*um29_B*tt_hp+u_amd_28*(1+g29_amd)*um29_B*tt_amd+u_tpu_28*(1+g29_tpu)*um29_B*tt_tpu+u_trn_28*(1+g29_trn)*um29_B*tt_trn+u_oth_28*(1+g29_oth)*um29_B*tt_oth -> 27.1915 | G72: =F72*(1+cy30g) -> 27.1915 | H72: Σ 顆數 × tt；CY2030＝CY2029×(1+cy30g)
A73: 每加權顆測試支出（以 CY2026 校準） | B73: US$B／百萬顆 | C73: =(mk_soc26-nonai26)/C72 -> 0.45011757 | H73: （公司 CY2026 SoC 市場 − 非 AI）÷ 加權顆數
A74: AI SoC 測試機市場 | B74: US$B | C74: =$C$73*C72*(1-0)^0 -> 6.7 | D74: =$C$73*D72*(1-0)^1 -> 10.942358 | E74: =$C$73*E72*(1-0)^2 -> 10.118643 | F74: =$C$73*F72*(1-0)^3 -> 12.239372 | G74: =$C$73*G72*(1-0)^4 -> 12.239372
A75: 非 AI SoC 測試機市場 | B75: US$B | C75: =nonai26*(1+g_nonai)^0 -> 4.3 | D75: =nonai26*(1+g_nonai)^1 -> 4.472 | E75: =nonai26*(1+g_nonai)^2 -> 4.65088 | F75: =nonai26*(1+g_nonai)^3 -> 4.8369152 | G75: =nonai26*(1+g_nonai)^4 -> 5.0303918
A76: SoC 測試機市場 CY | B76: US$B | C76: =C74+C75 -> 11 | D76: =D74+D75 -> 15.414358 | E76: =E74+E75 -> 14.769523 | F76: =F74+F75 -> 17.076287 | G76: =G74+G75 -> 17.269764 | H76: CY2026 ＝ 公司規模（校準）
A77: 記憶體測試機市場 CY | B77: US$B | C77: =mk_mem26*(w_hbm*hsB_26/hsB_26+(1-w_hbm)*drB_26/drB_26) -> 2.75 | D77: =mk_mem26*(w_hbm*hsB_27/hsB_26+(1-w_hbm)*drB_27/drB_26) -> 3.9915065 | E77: =mk_mem26*(w_hbm*hsB_28/hsB_26+(1-w_hbm)*drB_28/drB_26) -> 4.8492815 | F77: =mk_mem26*(w_hbm*hsB_29/hsB_26+(1-w_hbm)*drB_29/drB_26) -> 5.8958345 | G77: =F77*(1+cy30g) -> 5.8958345 | H77: CY2026 錨定公司規模；之後＝w×HBM 出貨位元指數＋(1−w)×DRAM 設備支出指數
A78: B. 會計年度（C＝FY2025 … G＝FY2029；FY(t)＝3/4×CY(t)＋1/4×CY(t+1)）
A79: SoC 測試機市場 FY | B79: US$B | C79: =fmk_soc25 -> 7.925 | D79: =0.75*C76+0.25*D76 -> 12.10359 | E79: =0.75*D76+0.25*E76 -> 15.253149 | F79: =0.75*E76+0.25*F76 -> 15.346214 | G79: =0.75*F76+0.25*G76 -> 17.124656
A80: 記憶體測試機市場 FY | B80: US$B | C80: =fmk_mem25 -> 2.2625 | D80: =0.75*C77+0.25*D77 -> 3.0603766 | E80: =0.75*D77+0.25*E77 -> 4.2059502 | F80: =0.75*E77+0.25*F77 -> 5.1109197 | G80: =0.75*F77+0.25*G77 -> 5.8958345
A81: Advantest SoC 市占 | B81: % | C81: =a25_soc/(C79*fx) -> 0.64555205 | D81: =sh_soc -> 0.66 | E81: =sh_soc -> 0.66 | F81: =sh_soc -> 0.66 | G81: =sh_soc -> 0.66 | H81: FY2025＝實績隱含（對照公司自估 66%）
A82: SoC 測試機營收 | B82: ¥B | C82: =a25_soc -> 767.4 | D82: =D79*D81*fx -> 1198.2554 | E82: =E79*E81*fx -> 1510.0618 | F82: =F79*F81*fx -> 1519.2752 | G82: =G79*G81*fx -> 1695.341 | H82: 市場 × 市占 × 匯率
A83: 記憶體測試機營收 | B83: ¥B | C83: =a25_mem -> 171.5 | D83: =D80*sh_mem*fx -> 231.97993 | E83: =E80*sh_mem*fx -> 318.81568 | F83: =F80*sh_mem*fx -> 387.41336 | G83: =G80*sh_mem*fx -> 446.91077
A84: 其他系統營收 | B84: ¥B | C84: =a25_oth -> 80.5 | D84: =C84*(1+g_oth_26) -> 104 | E84: =D84*(1+g_oth_B) -> 114.4 | F84: =E84*(1+g_oth_B) -> 125.84 | G84: =F84*(1+g_oth_B) -> 138.424
A85: 服務、支援與其他營收 | B85: ¥B | C85: =a25_svc -> 109.2 | D85: =C85*(1+g_svc_26) -> 135.6 | E85: =D85*(1+g_svc_B) -> 149.16 | F85: =E85*(1+g_svc_B) -> 164.076 | G85: =F85*(1+g_svc_B) -> 180.4836
A86: 營收 | B86: ¥B | C86: =C82+C83+C84+C85 -> 1128.6 | D86: =D82+D83+D84+D85 -> 1669.8353 | E86: =E82+E83+E84+E85 -> 2092.4375 | F86: =F82+F83+F84+F85 -> 2196.6045 | G86: =G82+G83+G84+G85 -> 2461.1593
A87: SoC 占營收 | B87: % | C87: =C82/C86 -> 0.67995747 | D87: =D82/D86 -> 0.71758896 | E87: =E82/E86 -> 0.72167595 | F87: =F82/F86 -> 0.69164711 | G87: =G82/G86 -> 0.68883836
A88: 毛利率 | B88: % | C88: =a25_gp/a25_rev -> 0.643 | D88: =gm_a+gm_b*D87+0 -> 0.66118008 | E88: =gm_a+gm_b*E87+0 -> 0.66315454 | F88: =gm_a+gm_b*F87+0 -> 0.64864736 | G88: =gm_a+gm_b*G87+0 -> 0.64729043 | H88: 截距＋斜率×SoC 占比（兩點推導）
A89: 毛利 | B89: ¥B | C89: =C86*C88 -> 725.6898 | D89: =D86*D88 -> 1104.0618 | E89: =E86*E88 -> 1387.6094 | F89: =F86*F88 -> 1424.8217 | G89: =G86*G88 -> 1593.0849
A90: 營業費用 | B90: ¥B | C90: =opex25 -> 226.5898 | D90: =opex_fix+opex_var*D86 -> 288.73866 | E90: =opex_fix+opex_var*E86 -> 337.26514 | F90: =opex_fix+opex_var*F86 -> 349.22642 | G90: =opex_fix+opex_var*G86 -> 379.60467 | H90: 固定＋變動×營收
A91: 營業利益 | B91: ¥B | C91: =C89-C90 -> 499.1 | D91: =D89-D90 -> 815.32317 | E91: =E89-E90 -> 1050.3443 | F91: =F89-F90 -> 1075.5953 | G91: =G89-G90 -> 1213.4802
A92: 營業利益率 | B92: % | C92: =C91/C86 -> 0.44222931 | D92: =D91/D86 -> 0.48826562 | E92: =E91/E86 -> 0.50197164 | F92: =F91/F86 -> 0.4896627 | G92: =G91/G86 -> 0.49305228
A93: 淨利 | B93: ¥B | C93: =a25_ni -> 375.4 | D93: =D91*nioi -> 613.24848 | E93: =E91*nioi -> 790.0205 | F93: =F91*nioi -> 809.01319 | G93: =G91*nioi -> 912.72385
A94: EPS | B94: ¥ | C94: =a25_eps -> 515.15 | D94: =D93*1000/shares -> 847.06341 | E94: =E93*1000/shares -> 1091.2338 | F94: =F93*1000/shares -> 1117.4679 | G94: =G93*1000/shares -> 1260.7206
A95: 營收（美元） | B95: US$B | C95: =C86/fx -> 7.524 | D95: =D86/fx -> 11.132235 | E95: =E86/fx -> 13.949583 | F95: =F86/fx -> 14.64403 | G95: =G86/fx -> 16.407729 | H95: FY2025 以基準匯率換算（顯示用）
A98: 情境 C：2028–29 顆數 ×0.6；Teradyne 搶回市占、價格壓力
A99: 項目 | B99: 單位 | C99: CY2026／FY2025 | D99: CY2027／FY2026 | E99: CY2028／FY2027 | F99: CY2029／FY2028 | G99: CY2030／FY2029 | H99: 說明
A100: A. 日曆年（C＝CY2026 … G＝CY2030）
A101: 測試時間加權顆數 | B101: 百萬顆 | C101: =u_bw_26*tt_bw+u_rb_26*tt_rb+u_ru_26*tt_ru+u_hp_26*tt_hp+u_amd_26*tt_amd+u_tpu_26*tt_tpu+u_trn_26*tt_trn+u_oth_26*tt_oth -> 14.885 | D101: =u_bw_27*tt_bw+u_rb_27*tt_rb+u_ru_27*tt_ru+u_hp_27*tt_hp+u_amd_27*tt_amd+u_tpu_27*tt_tpu+u_trn_27*tt_trn+u_oth_27*tt_oth -> 24.31 | E101: =u_bw_28*um28_C*tt_bw+u_rb_28*um28_C*tt_rb+u_ru_28*um28_C*tt_ru+u_hp_28*um28_C*tt_hp+u_amd_28*um28_C*tt_amd+u_tpu_28*um28_C*tt_tpu+u_trn_28*um28_C*tt_trn+u_oth_28*um28_C*tt_oth -> 16.86 | F101: =u_bw_28*(1+g29_bw)*um29_C*tt_bw+u_rb_28*(1+g29_rb)*um29_C*tt_rb+u_ru_28*(1+g29_ru)*um29_C*tt_ru+u_hp_28*(1+g29_hp)*um29_C*tt_hp+u_amd_28*(1+g29_amd)*um29_C*tt_amd+u_tpu_28*(1+g29_tpu)*um29_C*tt_tpu+u_trn_28*(1+g29_trn)*um29_C*tt_trn+u_oth_28*(1+g29_oth)*um29_C*tt_oth -> 19.194 | G101: =F101*(1+cy30g) -> 19.194 | H101: Σ 顆數 × tt；CY2030＝CY2029×(1+cy30g)
A102: 每加權顆測試支出（以 CY2026 校準） | B102: US$B／百萬顆 | C102: =(mk_soc26-nonai26)/C101 -> 0.45011757 | H102: （公司 CY2026 SoC 市場 − 非 AI）÷ 加權顆數
A103: AI SoC 測試機市場 | B103: US$B | C103: =$C$102*C101*(1-0)^0 -> 6.7 | D103: =$C$102*D101*(1-0)^1 -> 10.942358 | E103: =$C$102*E101*(1-0)^2 -> 7.5889822 | F103: =$C$102*F101*(1-0)^3 -> 8.6395566 | G103: =$C$102*G101*(1-0)^4 -> 8.6395566
A104: 非 AI SoC 測試機市場 | B104: US$B | C104: =nonai26*(1+g_nonai)^0 -> 4.3 | D104: =nonai26*(1+g_nonai)^1 -> 4.472 | E104: =nonai26*(1+g_nonai)^2 -> 4.65088 | F104: =nonai26*(1+g_nonai)^3 -> 4.8369152 | G104: =nonai26*(1+g_nonai)^4 -> 5.0303918
A105: SoC 測試機市場 CY | B105: US$B | C105: =C103+C104 -> 11 | D105: =D103+D104 -> 15.414358 | E105: =E103+E104 -> 12.239862 | F105: =F103+F104 -> 13.476472 | G105: =G103+G104 -> 13.669948 | H105: CY2026 ＝ 公司規模（校準）
A106: 記憶體測試機市場 CY | B106: US$B | C106: =mk_mem26*(w_hbm*hsC_26/hsC_26+(1-w_hbm)*drC_26/drC_26) -> 2.75 | D106: =mk_mem26*(w_hbm*hsC_27/hsC_26+(1-w_hbm)*drC_27/drC_26) -> 3.9915065 | E106: =mk_mem26*(w_hbm*hsC_28/hsC_26+(1-w_hbm)*drC_28/drC_26) -> 3.7299739 | F106: =mk_mem26*(w_hbm*hsC_29/hsC_26+(1-w_hbm)*drC_29/drC_26) -> 4.4025046 | G106: =F106*(1+cy30g) -> 4.4025046 | H106: CY2026 錨定公司規模；之後＝w×HBM 出貨位元指數＋(1−w)×DRAM 設備支出指數
A107: B. 會計年度（C＝FY2025 … G＝FY2029；FY(t)＝3/4×CY(t)＋1/4×CY(t+1)）
A108: SoC 測試機市場 FY | B108: US$B | C108: =fmk_soc25 -> 7.925 | D108: =0.75*C105+0.25*D105 -> 12.10359 | E108: =0.75*D105+0.25*E105 -> 14.620734 | F108: =0.75*E105+0.25*F105 -> 12.549015 | G108: =0.75*F105+0.25*G105 -> 13.524841
...

Sheet Val
A1: Val — P/E 估值。跨公司規則：合理倍數＝10 年（2016–2025 年底）P/E 的分位，依循環位置：見頂年 25 分位、中段中位數、谷底 75 分位。循環位置依設備股共用規則（見第 4 節；v0.2 以前三情境皆把 FY2027 歸為見頂年）
A2: P/E 定義（自算）：日曆年底收盤價 ÷ 「當期會計年度」公司公布的基本 EPS（年底所在會計年度，例如 2025-12 對 FY2025＝2026-03 期）；另列「前期」（上一個已結束會計年度）。所有價格與 EPS 為 2023-10 的 4 比 1 分割調整後
A4: 1. 公司公布 EPS（會計年度，日圓，分割調整後）— 兩個來源
A5: 會計年度（3 月結束） | B5: 來源1：irbank（分割調整後；2025-03 改用公司決算書） | C5: 來源2：公司原始 EPS（分割前） | D5: 來源2 ÷ 4 | E5: 兩者差距 | F5: 標記 | G5: 說明
A6: 2016-03 | B6: 9.59 | C6: 38.35 | D6: =C6/4 -> 9.5875 | E6: =B6/D6-1 -> 0.00026075619 | F6: Verified | G6: 公司 74th 年報：基本 38.35
A7: 2017-03 | B7: 20.27 | C7: 81.07 | D7: =C7/4 -> 20.2675 | E7: =B7/D7-1 -> 0.00012335019 | F7: Verified | G7: 公司 FY2017 決算附註：基本 81.07（摘要表另列 148.11，口徑不同，未採）
A8: 2018-03 | B8: 25.49 | C8: 101.94 | D8: =C8/4 -> 25.485 | E8: =B8/D8-1 -> 0.00019619384 | F8: Verified | G8: 公司 FY2018 決算附註：101.94（摘要表 256.28，未採）
A9: 2019-03 | B9: 75.59 | C9: 302.35 | D9: =C9/4 -> 75.5875 | E9: =B9/D9-1 -> 3.3074252e-05 | F9: Verified | G9: 公司 FY2019 決算附註：302.35
A10: 2020-03 | B10: 67.53 | C10: 270.12 | D10: =C10/4 -> 67.53 | E10: =B10/D10-1 -> 0 | F10: Verified | G10: 公司 FY2020 決算：270.12
A11: 2021-03 | B11: 88.47 | C11: 353.87 | D11: =C11/4 -> 88.4675 | E11: =B11/D11-1 -> 2.8258965e-05 | F11: Verified（單一來源＋還原） | G11: 公司 FY2020 決算 353.87；株探 353.9
A12: 2022-03 | B12: 112.39 | C12: 449.6 | D12: =C12/4 -> 112.4 | E12: =B12/D12-1 -> -8.8967972e-05 | F12: Verified（單一來源＋還原） | G12: 株探 449.6（公司值未直接取得）
A13: 2023-03 | B13: 174.35 | C13: 697.4 | D13: =C13/4 -> 174.35 | E13: =B13/D13-1 -> 0 | F13: Verified（單一來源＋還原） | G13: 株探 697.4（公司值未直接取得）
A14: 2024-03 | B14: 84.45 | C14: 337.8 | D14: =C14/4 -> 84.45 | E14: =B14/D14-1 -> 0 | F14: Verified（單一來源＋還原） | G14: 公司 FY2024 決算：84.45（分割後）；右欄為 84.45×4 的還原（Derived，非獨立來源）
A15: 2025-03 | B15: 226.24 | C15: 904.96 | D15: =C15/4 -> 226.24 | E15: =B15/D15-1 -> 0 | F15: Verified（單一來源＋還原） | G15: 公司 FY2025 決算書（FY2024 Consolidated Financial Results，E_FR_FY2024_FN.pdf）：基本 226.24、希薄化後 225.77；右欄為 ×4 還原。irbank／松井證券列 218.67，口徑未解，不採
A16: 2026-03 | B16: 515.15 | C16: 2060.6 | D16: =C16/4 -> 515.15 | E16: =B16/D16-1 -> 0 | F16: Verified（單一來源＋還原） | G16: 公司 FY2025 決算 515.15（Q 頁）；右欄為 ×4 還原
A17: 全部年度統一用基本 EPS（Basic）。公司決算書均區分基本與稀釋；2016–2020 年 3 月期取自公司決算附註的基本 EPS，2021-03 與 2024-03 以後取自公司決算的基本 EPS，2022-03、2023-03 為株探值（未直接取得公司值）
A18: 2. 10 年 P/E（年底）
A19: 年底 | B19: 收盤價 ¥（分割調整） | C19: 當期 FY EPS | D19: 前期 FY EPS | E19: P/E 當期（自算） | F19: P/E 前期（自算） | G19: companiesmarketcap P/E | H19: 自算當期 − cmc | I19: 自算前期 − cmc | J19: 標記 | K19: 來源／說明
A20: 2016-12 | C20: =B7 -> 20.27 | D20: =B6 -> 9.59 | E20: =IF(B20="","",B20/C20) | F20: =IF(B20="","",B20/D20) | G20: 23.9 | H20: =IF(OR(B20="",G20=""),"",E20-G20) | I20: =IF(OR(B20="",G20=""),"",F20-G20) | J20: Verified／Derived | K20: 收盤價未找到（檢索缺口，不是不存在）：不納入分位；補入的敏感度見下
A21: 2017-12 | B21: 522.8 | C21: =B8 -> 25.49 | D21: =B7 -> 20.27 | E21: =IF(B21="","",B21/C21) -> 20.510004 | F21: =IF(B21="","",B21/D21) -> 25.791811 | G21: 22.8 | H21: =IF(OR(B21="",G21=""),"",E21-G21) -> -2.2899961 | I21: =IF(OR(B21="",G21=""),"",F21-G21) -> 2.9918106 | J21: Verified／Derived | K21: 收盤價：日經新聞 過去 10 年股價推移（年底收盤）
A22: 2018-12 | B22: 561 | C22: =B9 -> 75.59 | D22: =B8 -> 25.49 | E22: =IF(B22="","",B22/C22) -> 7.4216166 | F22: =IF(B22="","",B22/D22) -> 22.008631 | G22: 19.6 | H22: =IF(OR(B22="",G22=""),"",E22-G22) -> -12.178383 | I22: =IF(OR(B22="",G22=""),"",F22-G22) -> 2.4086308 | J22: Verified／Derived | K22: 收盤價：日經新聞 過去 10 年股價推移（年底收盤）
A23: 2019-12 | B23: 1540 | C23: =B10 -> 67.53 | D23: =B9 -> 75.59 | E23: =IF(B23="","",B23/C23) -> 22.804679 | F23: =IF(B23="","",B23/D23) -> 20.373065 | G23: 8.1 | H23: =IF(OR(B23="",G23=""),"",E23-G23) -> 14.704679 | I23: =IF(OR(B23="",G23=""),"",F23-G23) -> 12.273065 | J23: Verified／Derived | K23: 收盤價：日經新聞 過去 10 年股價推移（年底收盤）
A24: 2020-12 | B24: 1932.5 | C24: =B11 -> 88.47 | D24: =B10 -> 67.53 | E24: =IF(B24="","",B24/C24) -> 21.843563 | F24: =IF(B24="","",B24/D24) -> 28.616911 | G24: 15.1 | H24: =IF(OR(B24="",G24=""),"",E24-G24) -> 6.7435628 | I24: =IF(OR(B24="",G24=""),"",F24-G24) -> 13.516911 | J24: Verified／Derived | K24: 收盤價：日經新聞 過去 10 年股價推移（年底收盤）
A25: 2021-12 | B25: 2725 | C25: =B12 -> 112.39 | D25: =B11 -> 88.47 | E25: =IF(B25="","",B25/C25) -> 24.245929 | F25: =IF(B25="","",B25/D25) -> 30.801402 | G25: 26.2 | H25: =IF(OR(B25="",G25=""),"",E25-G25) -> -1.9540706 | I25: =IF(OR(B25="",G25=""),"",F25-G25) -> 4.6014016 | J25: Verified／Derived | K25: 收盤價：日經新聞 過去 10 年股價推移（年底收盤）
A26: 2022-12 | B26: 2120 | C26: =B13 -> 174.35 | D26: =B12 -> 112.39 | E26: =IF(B26="","",B26/C26) -> 12.159449 | F26: =IF(B26="","",B26/D26) -> 18.862888 | G26: 21.1 | H26: =IF(OR(B26="",G26=""),"",E26-G26) -> -8.9405506 | I26: =IF(OR(B26="",G26=""),"",F26-G26) -> -2.2371118 | J26: Verified／Derived | K26: 收盤價：日經新聞 過去 10 年股價推移（年底收盤）
A27: 2023-12 | B27: 4797 | C27: =B14 -> 84.45 | D27: =B13 -> 174.35 | E27: =IF(B27="","",B27/C27) -> 56.802842 | F27: =IF(B27="","",B27/D27) -> 27.513622 | G27: 16.8 | H27: =IF(OR(B27="",G27=""),"",E27-G27) -> 40.002842 | I27: =IF(OR(B27="",G27=""),"",F27-G27) -> 10.713622 | J27: Verified／Derived | K27: 當期 EPS 84.45 偏低（FY2023 淨利 62.3B，Q 頁外）→ P/E 56.8 為極端值
A28: 2024-12 | B28: 9198 | C28: =B15 -> 226.24 | D28: =B14 -> 84.45 | E28: =IF(B28="","",B28/C28) -> 40.655941 | F28: =IF(B28="","",B28/D28) -> 108.91652 | G28: 76.3 | H28: =IF(OR(B28="",G28=""),"",E28-G28) -> -35.644059 | I28: =IF(OR(B28="",G28=""),"",F28-G28) -> 32.616519 | J28: Verified／Derived | K28: 收盤價：日經新聞 過去 10 年股價推移（年底收盤）
A29: 2025-12 | B29: 19635 | C29: =B16 -> 515.15 | D29: =B15 -> 226.24 | E29: =IF(B29="","",B29/C29) -> 38.115112 | F29: =IF(B29="","",B29/D29) -> 86.788366 | H29: =IF(OR(B29="",G29=""),"",E29-G29) | I29: =IF(OR(B29="",G29=""),"",F29-G29) | J29: Verified／Derived | K29: companiesmarketcap 2025 年底值未取得（搜尋摘錄缺列）；Yahoo Finance 2025-12-31 TTM P/E 55.18 可作參考
A31: 收盤價來源1：日經新聞 過去10年株價（nikkei.com/nkd/company/history/yprice/?scode=6857）；來源2：未找到（Yahoo Japan、kabutan 歷史頁未開啟）。EPS 來源1：irbank；來源2：公司決算（見上表）。companiesmarketcap（美元計價 TTM 口徑，與日圓自算不可直接比較）僅作對照，差距見 H、I 欄。
A33: 3. 分位（只含有價格的年度）
A34: 統計 | B34: P/E 當期（自算） | C34: P/E 前期（自算） | D34: cmc P/E（參考） | E34: 用途
A35: 25 分位 | B35: =PERCENTILE(E20:E29,0.25) -> 20.510004 | C35: =PERCENTILE(F20:F29,0.25) -> 22.008631 | D35: =PERCENTILE(G20:G29,0.25) -> 16.8 | E35: 見頂年
A36: 中位數 | B36: =PERCENTILE(E20:E29,0.5) -> 22.804679 | C36: =PERCENTILE(F20:F29,0.5) -> 27.513622 | D36: =PERCENTILE(G20:G29,0.5) -> 21.1 | E36: 中段
A37: 75 分位 | B37: =PERCENTILE(E20:E29,0.75) -> 38.115112 | C37: =PERCENTILE(F20:F29,0.75) -> 30.801402 | D37: =PERCENTILE(G20:G29,0.75) -> 23.9 | E37: 谷底
A38: 年數 | B38: =COUNT(E20:E29) -> 9 | C38: =COUNT(F20:F29) -> 9 | D38: =COUNT(G20:G29) -> 9
A40: 敏感度：補入 2016 年（價格未找到）。以假設的 2016 P/E 重算 25 分位（當期口徑）
A41: 2016 P/E 假設 | B41: 25 分位 | C41: 中位數 | D41: 75 分位
A42: 10 | B42: =PERCENTILE(B48:B57,0.25) -> 14.247088 | C42: =PERCENTILE(B48:B57,0.5) -> 22.324121 | D42: =PERCENTILE(B48:B57,0.75) -> 34.647816
A43: 20 | B43: =PERCENTILE(C48:C57,0.25) -> 20.127501 | C43: =PERCENTILE(C48:C57,0.5) -> 22.324121 | D43: =PERCENTILE(C48:C57,0.75) -> 34.647816
A44: 30 | B44: =PERCENTILE(D48:D57,0.25) -> 20.843394 | C44: =PERCENTILE(D48:D57,0.5) -> 23.525304 | D44: =PERCENTILE(D48:D57,0.75) -> 36.086334
A46: 輔助：10 個值（2016 以假設取代）
B47: =A42 -> 10 | C47: =A43 -> 20 | D47: =A44 -> 30
B48: =IF(E20="",B$47,E20) -> 10 | C48: =IF(E20="",C$47,E20) -> 20 | D48: =IF(E20="",D$47,E20) -> 30
B49: =IF(E21="",B$47,E21) -> 20.510004 | C49: =IF(E21="",C$47,E21) -> 20.510004 | D49: =IF(E21="",D$47,E21) -> 20.510004
B50: =IF(E22="",B$47,E22) -> 7.4216166 | C50: =IF(E22="",C$47,E22) -> 7.4216166 | D50: =IF(E22="",D$47,E22) -> 7.4216166
B51: =IF(E23="",B$47,E23) -> 22.804679 | C51: =IF(E23="",C$47,E23) -> 22.804679 | D51: =IF(E23="",D$47,E23) -> 22.804679
B52: =IF(E24="",B$47,E24) -> 21.843563 | C52: =IF(E24="",C$47,E24) -> 21.843563 | D52: =IF(E24="",D$47,E24) -> 21.843563
B53: =IF(E25="",B$47,E25) -> 24.245929 | C53: =IF(E25="",C$47,E25) -> 24.245929 | D53: =IF(E25="",D$47,E25) -> 24.245929
B54: =IF(E26="",B$47,E26) -> 12.159449 | C54: =IF(E26="",C$47,E26) -> 12.159449 | D54: =IF(E26="",D$47,E26) -> 12.159449
B55: =IF(E27="",B$47,E27) -> 56.802842 | C55: =IF(E27="",C$47,E27) -> 56.802842 | D55: =IF(E27="",D$47,E27) -> 56.802842
B56: =IF(E28="",B$47,E28) -> 40.655941 | C56: =IF(E28="",C$47,E28) -> 40.655941 | D56: =IF(E28="",D$47,E28) -> 40.655941
B57: =IF(E29="",B$47,E29) -> 38.115112 | C57: =IF(E29="",C$47,E29) -> 38.115112 | D57: =IF(E29="",D$47,E29) -> 38.115112
A59: 4. 循環位置（設備股共用規則；見頂年度讀設備市場模型，不在本模型另訂）
A60: 循環位置（設備股共用規則）：各情境的見頂年度取自設備市場模型（markets/equipment 的 Mkt 頁「見頂年度」：A 2029、B 2028、C 2027）；會計年度 FY(t) 對照日曆年 t（FY(t) 有 3/4 落在 t 年）：t 早於見頂年＝中段（中位數）、等於＝見頂（25 分位）、晚於＝谷底（75 分位）
A61: 情境 | B61: 設備市場見頂年度 | C61: FY2027 對照日曆年 | D61: 判定 | E61: 倍數 | F61: v0.2 判定（對照） | G61: v0.2 倍數 | H61: 規則
A62: A | B62: =pk_A -> 2029 | C62: 2027 | D62: =IF(C62<pk_A,"中段",IF(C62=pk_A,"見頂","谷底")) -> 中段 | E62: =IF(D62="見頂",pe_peak,IF(D62="谷底",pe_trough,pe_mid)) -> 22.804679 | F62: 見頂 | G62: =pe_peak -> 20.510004 | H62: tools/cycle_position.py
A63: B | B63: =pk_B -> 2028 | C63: 2027 | D63: =IF(C63<pk_B,"中段",IF(C63=pk_B,"見頂","谷底")) -> 中段 | E63: =IF(D63="見頂",pe_peak,IF(D63="谷底",pe_trough,pe_mid)) -> 22.804679 | F63: 見頂 | G63: =pe_peak -> 20.510004 | H63: tools/cycle_position.py
A64: C | B64: =pk_C -> 2027 | C64: 2027 | D64: =IF(C64<pk_C,"中段",IF(C64=pk_C,"見頂","谷底")) -> 見頂 | E64: =IF(D64="見頂",pe_peak,IF(D64="谷底",pe_trough,pe_mid)) -> 20.510004 | F64: 見頂 | G64: =pe_peak -> 20.510004 | H64: tools/cycle_position.py
A66: 5. 隱含股價（日圓）：規則值＝FY2027 EPS × 依循環位置的倍數；其餘倍數僅供參考
A67: 情境 | B67: EPS 年度 | C67: EPS | D67: 倍數類型 | E67: 倍數 | F67: 隱含股價 | G67: 相對現價 | H67: 備註
A68: A | B68: FY2027 | C68: =PL!E13 -> 1138.5516 | D68: ="規則值："&D62 -> 規則值：中段 | E68: =E62 -> 22.804679 | F68: =C68*E68 -> 25964.304 | G68: =F68/px-1 -> -0.24610034
A69: A | B69: FY2027 | C69: =PL!E13 -> 1138.5516 | D69: 參考：25 分位（v0.2 規則值） | E69: =pe_peak -> 20.510004 | F69: =C69*E69 -> 23351.698 | G69: =F69/px-1 -> -0.32195999
A70: A | B70: FY2027 | C70: =PL!E13 -> 1138.5516 | D70: 參考：中位數 | E70: =pe_mid -> 22.804679 | F70: =C70*E70 -> 25964.304 | G70: =F70/px-1 -> -0.24610034
A71: A | B71: FY2027 | C71: =PL!E13 -> 1138.5516 | D71: 參考：75 分位 | E71: =pe_trough -> 38.115112 | F71: =C71*E71 -> 43396.022 | G71: =F71/px-1 -> 0.2600471
A72: A | B72: FY2028 | C72: =PL!F13 -> 1297.8075 | D72: 參考：25 分位 | E72: =pe_peak -> 20.510004 | F72: =C72*E72 -> 26618.036 | G72: =F72/px-1 -> -0.22711858
A73: A | B73: FY2028 | C73: =PL!F13 -> 1297.8075 | D73: 參考：中位數 | E73: =pe_mid -> 22.804679 | F73: =C73*E73 -> 29596.083 | G73: =F73/px-1 -> -0.140648
A74: A | B74: FY2028 | C74: =PL!F13 -> 1297.8075 | D74: 參考：75 分位 | E74: =pe_trough -> 38.115112 | F74: =C74*E74 -> 49466.077 | G74: =F74/px-1 -> 0.43629723
A75: B | B75: FY2027 | C75: =PL!E24 -> 1091.2338 | D75: ="規則值："&D63 -> 規則值：中段 | E75: =E63 -> 22.804679 | F75: =C75*E75 -> 24885.236 | G75: =F75/px-1 -> -0.27743216
A76: B | B76: FY2027 | C76: =PL!E24 -> 1091.2338 | D76: 參考：25 分位（v0.2 規則值） | E76: =pe_peak -> 20.510004 | F76: =C76*E76 -> 22381.209 | G76: =F76/px-1 -> -0.35013911
A77: B | B77: FY2027 | C77: =PL!E24 -> 1091.2338 | D77: 參考：中位數 | E77: =pe_mid -> 22.804679 | F77: =C77*E77 -> 24885.236 | G77: =F77/px-1 -> -0.27743216
A78: B | B78: FY2027 | C78: =PL!E24 -> 1091.2338 | D78: 參考：75 分位 | E78: =pe_trough -> 38.115112 | F78: =C78*E78 -> 41592.498 | G78: =F78/px-1 -> 0.20767996
A79: B | B79: FY2028 | C79: =PL!F24 -> 1117.4679 | D79: 參考：25 分位 | E79: =pe_peak -> 20.510004 | F79: =C79*E79 -> 22919.27 | G79: =F79/px-1 -> -0.33451597
A80: B | B80: FY2028 | C80: =PL!F24 -> 1117.4679 | D80: 參考：中位數 | E80: =pe_mid -> 22.804679 | F80: =C80*E80 -> 25483.496 | G80: =F80/px-1 -> -0.26006109
A81: B | B81: FY2028 | C81: =PL!F24 -> 1117.4679 | D81: 參考：75 分位 | E81: =pe_trough -> 38.115112 | F81: =C81*E81 -> 42592.413 | G81: =F81/px-1 -> 0.23671349
A82: C | B82: FY2027 | C82: =PL!E35 -> 1039.1378 | D82: ="規則值："&D64 -> 規則值：見頂 | E82: =E64 -> 20.510004 | F82: =C82*E82 -> 21312.721 | G82: =F82/px-1 -> -0.38116373
A83: C | B83: FY2027 | C83: =PL!E35 -> 1039.1378 | D83: 參考：25 分位（v0.2 規則值） | E83: =pe_peak -> 20.510004 | F83: =C83*E83 -> 21312.721 | G83: =F83/px-1 -> -0.38116373
A84: C | B84: FY2027 | C84: =PL!E35 -> 1039.1378 | D84: 參考：中位數 | E84: =pe_mid -> 22.804679 | F84: =C84*E84 -> 23697.205 | G84: =F84/px-1 -> -0.31192784
A85: C | B85: FY2027 | C85: =PL!E35 -> 1039.1378 | D85: 參考：75 分位 | E85: =pe_trough -> 38.115112 | F85: =C85*E85 -> 39606.855 | G85: =F85/px-1 -> 0.15002483
A86: C | B86: FY2028 | C86: =PL!F35 -> 810.56821 | D86: 參考：25 分位 | E86: =pe_peak -> 20.510004 | F86: =C86*E86 -> 16624.757 | G86: =F86/px-1 -> -0.51728348
A87: C | B87: FY2028 | C87: =PL!F35 -> 810.56821 | D87: 參考：中位數 | E87: =pe_mid -> 22.804679 | F87: =C87*E87 -> 18484.748 | G87: =F87/px-1 -> -0.46327677
A88: C | B88: FY2028 | C88: =PL!F35 -> 810.56821 | D88: 參考：75 分位 | E88: =pe_trough -> 38.115112 | F88: =C88*E88 -> 30894.898 | G88: =F88/px-1 -> -0.1029356
A90: 6. 目前遠期 P/E
A91: 項目 | B91: 數值 | C91: 備註
A92: 現價（stockanalysis 2026-10-21 收盤） | B92: =px -> 34440
A93: 遠期 P/E：stockanalysis | B93: =sa_fpe -> 37.7 | C93: stockanalysis 顯示 37.7x
A94: 遠期 P/E：現價 ÷ 公司指引 EPS（911.64） | B94: =px/g_eps -> 37.77807 | C94: 自算 37.8x
A95: 兩者差距 | B95: =B94-B93 -> 0.078070291 | C95: stockanalysis 的遠期 EPS 為共識，非公司指引，故小差
A96: 現價 ÷ 模型 FY2026 EPS（A） | B96: =px/PL!D13 -> 40.658113
A97: 現價 ÷ 模型 FY2027 EPS（A／B／C） | B97: =px/PL!E13 -> 30.248958 | C97: =px/PL!E24 -> 31.560607 | D97: =px/PL!E35 -> 33.14286
A98: 現價隱含倍數 ÷ 規則倍數（情境 A）— 以 FY2027 A EPS | B98: =B97/E62 -> 1.3264365 | C98: >1＝現價高於規則給的倍數
A100: 0. 目標價與上檔空間
A101: 項目 | B101: 數值 | E101: 說明
A102: 目標價（12 個月，情境加權） | B102: =tp_wA*B104+tp_wB*B105+tp_wC*B106 -> 24494.454 | E102: 權重 × 各情境隱含價（第 5 節規則值）
A103: 上檔空間（目標價 ÷ 現價 − 1） | B103: =B102/px-1 -> -0.28877893 | E103: 現價＝In 頁 px（stockanalysis 2026-10-21 收盤）
A104: 情境 A 隱含價（樂觀） | B104: =F68 -> 25964.304 | E104: ="FY2027 EPS × "&D68&" "&TEXT(E68,"0.0")&"x（第 5 節 F68）" -> FY2027 EPS × 規則值：中段 22.8x（第 5 節 F68）
A105: 情境 B 隱含價（基準） | B105: =F75 -> 24885.236 | E105: ="FY2027 EPS × "&D75&" "&TEXT(E75,"0.0")&"x（第 5 節 F75）" -> FY2027 EPS × 規則值：中段 22.8x（第 5 節 F75）
A106: 情境 C 隱含價（下檔） | B106: =F82 -> 21312.721 | E106: ="FY2027 EPS × "&D82&" "&TEXT(E82,"0.0")&"x（第 5 節 F82）" -> FY2027 EPS × 規則值：見頂 20.5x（第 5 節 F82）
A107: 情境權重 A／B／C | B107: =tp_wA -> 0.3 | C107: =tp_wB -> 0.5 | D107: =tp_wC -> 0.2 | E107: ="合計 "&TEXT(B107+C107+D107,"0%")&"；In 頁 tp_wA／tp_wB／tp_wC（Assumed，Andy 可改）" -> 合計 100%；In 頁 tp_wA／tp_wB／tp_wC（Assumed，Andy 可改）
A108: 目標價方法 | B108: P/E：各情境 FY2027 EPS × 十年（2016–2025 年底）P/E 依循環位置取分位（設備股共用規則：A、B 中段＝中位數，C 見頂＝25 分位；2016 年底價格未找到，實為 9 年）。十年倍數多數來自 AI 前（2017–2022 年 7–24x），偏誤方向為低估；但 2023 年 EPS 低谷使該年 56.8x 偏高、拉高 75 分位（不影響中位數與 25 分位）。隱含價約為 FY2027 年底（2028-03）的價格、未折現

Sheet Recon
A1: Recon — 本模型 vs 公司指引、共識、公司公布的市場規模、SEMI。只作事後對照，不為對上數字而調整參數。差距 > 10% 的原因見 README
A3: 項目 | B3: 對照值 | C3: 模型 A | D3: 差距 A | E3: 模型 B | F3: 差距 B | G3: 模型 C | H3: 差距 C | I3: 對照來源 | J3: 說明
A4: A. FY2026 vs 公司指引（2026-07-29 上修；校準時未使用指引）
A5: 營收 | B5: =g_rev -> 1714 | C5: =PL!D5 -> 1669.8353 | D5: =C5/B5-1 -> -0.025767041 | E5: =PL!D16 -> 1669.8353 | F5: =E5/B5-1 -> -0.025767041 | G5: =PL!D27 -> 1669.8353 | H5: =G5/B5-1 -> -0.025767041 | I5: 公司 Q1 FY26 決算短信
A6: SoC 測試機 | B6: =g_soc -> 1243.5 | C6: =PL!D7 -> 1198.2554 | D6: =C6/B6-1 -> -0.036384912 | E6: =PL!D18 -> 1198.2554 | F6: =E6/B6-1 -> -0.036384912 | G6: =PL!D29 -> 1198.2554 | H6: =G6/B6-1 -> -0.036384912 | I6: 同上
A7: 記憶體測試機 | B7: =g_mem -> 227 | C7: =PL!D8 -> 231.97993 | D7: =C7/B7-1 -> 0.021938015 | E7: =PL!D19 -> 231.97993 | F7: =E7/B7-1 -> 0.021938015 | G7: =PL!D30 -> 231.97993 | H7: =G7/B7-1 -> 0.021938015 | I7: 同上（公司原文未開啟）
A8: 營業利益 | B8: =g_oi -> 846 | C8: =PL!D10 -> 815.32317 | D8: =C8/B8-1 -> -0.036261026 | E8: =PL!D21 -> 815.32317 | F8: =E8/B8-1 -> -0.036261026 | G8: =PL!D32 -> 815.32317 | H8: =G8/B8-1 -> -0.036261026 | I8: 同上
A9: 營業利益率（差距以百分點計） | B9: =g_oi/g_rev -> 0.49358226 | C9: =PL!D11 -> 0.48826562 | D9: =C9-B9 -> -0.0053166391 | E9: =PL!D22 -> 0.48826562 | F9: =E9-B9 -> -0.0053166391 | G9: =PL!D33 -> 0.48826562 | H9: =G9-B9 -> -0.0053166391 | I9: 同上（49.4%）
A10: 淨利 | B10: =g_ni -> 660 | C10: =PL!D12 -> 613.24848 | D10: =C10/B10-1 -> -0.070835629 | E10: =PL!D23 -> 613.24848 | F10: =E10/B10-1 -> -0.070835629 | G10: =PL!D34 -> 613.24848 | H10: =G10/B10-1 -> -0.070835629 | I10: 同上
A11: EPS（日圓） | B11: =g_eps -> 911.64 | C11: =PL!D13 -> 847.06341 | D11: =C11/B11-1 -> -0.070835629 | E11: =PL!D24 -> 847.06341 | F11: =E11/B11-1 -> -0.070835629 | G11: =PL!D35 -> 847.06341 | H11: =G11/B11-1 -> -0.070835629 | I11: 同上（911.64）
A12: B. FY2026 vs 共識（stockanalysis 2026-10-07）
A13: 營收 | B13: =cons_rev26 -> 1760 | C13: =PL!D5 -> 1669.8353 | D13: =C13/B13-1 -> -0.051229948 | E13: =PL!D16 -> 1669.8353 | F13: =E13/B13-1 -> -0.051229948 | G13: =PL!D27 -> 1669.8353 | H13: =G13/B13-1 -> -0.051229948 | I13: stockanalysis（¥1.76T）
A14: 營業利益 | B14: =cons_oi26 -> 886.4 | C14: =PL!D10 -> 815.32317 | D14: =C14/B14-1 -> -0.080185952 | E14: =PL!D21 -> 815.32317 | F14: =E14/B14-1 -> -0.080185952 | G14: =PL!D32 -> 815.32317 | H14: =G14/B14-1 -> -0.080185952 | I14: stockanalysis（¥886.4B）
A15: C. 市場規模與市占
A16: SoC 測試機市場 CY2026（US$B） | B16: =mk_soc26 -> 11 | C16: =PL!C47 -> 11 | D16: =C16/B16-1 -> 0 | E16: =PL!C76 -> 11 | F16: =E16/B16-1 -> 0 | G16: =PL!C105 -> 11 | H16: =G16/B16-1 -> 0 | I16: 公司：10.5–11.5（中點） | J16: 校準恆等式：模型 CY2026 以公司中點為錨，差距必為 0，不是獨立檢驗
A17: 記憶體測試機市場 CY2026（US$B） | B17: =mk_mem26 -> 2.75 | C17: =PL!C48 -> 2.75 | D17: =C17/B17-1 -> 0 | E17: =PL!C77 -> 2.75 | F17: =E17/B17-1 -> 0 | G17: =PL!C106 -> 2.75 | H17: =G17/B17-1 -> 0 | I17: 公司：2.5–3.0（中點） | J17: 同上，錨定
A18: Advantest FY2025 隱含 SoC 市占（FY2025 實績 ÷ 市場） | B18: =sh_soc -> 0.66 | C18: =PL!C52 -> 0.64555205 | D18: =C18-B18 -> -0.01444795 | E18: =PL!C81 -> 0.64555205 | F18: =E18-B18 -> -0.01444795 | G18: =PL!C110 -> 0.64555205 | H18: =G18-B18 -> -0.01444795 | I18: 公司自估 CY2025 66% | J18: 獨立檢驗：實績與公司市場規模推得的 FY 口徑市占，對照公司自估的 CY 口徑
A19: D. 測試設備合計（SoC＋記憶體測試機）vs SEMI 測試設備（markets/equipment 的 Mkt 頁，SEMI 2026-07）
A20: CY2026：SoC＋記憶體測試機市場（US$B） | B20: =semi_test26 -> 15.3 | C20: =PL!C47+PL!C48 -> 13.75 | D20: =C20/B20-1 -> -0.10130719 | E20: =PL!C76+PL!C77 -> 13.75 | F20: =E20/B20-1 -> -0.10130719 | G20: =PL!C105+PL!C106 -> 13.75 | H20: =G20/B20-1 -> -0.10130719 | I20: SEMI 2026-07（equipment 成品） | J20: SEMI 測試設備含探針台、分選機與其他 ATE，口徑較寬；2027 為 SEMI 內插值
A21: CY2027：SoC＋記憶體測試機市場（US$B） | B21: =semi_test27 -> 17.839282 | C21: =PL!D47+PL!D48 -> 19.405865 | D21: =C21/B21-1 -> 0.087816428 | E21: =PL!D76+PL!D77 -> 19.405865 | F21: =E21/B21-1 -> 0.087816428 | G21: =PL!D105+PL!D106 -> 19.405865 | H21: =G21/B21-1 -> 0.087816428 | I21: SEMI 2026-07（equipment 成品）
A22: CY2028：SoC＋記憶體測試機市場（US$B） | B22: =semi_test28 -> 20.8 | C22: =PL!E47+PL!E48 -> 22.469879 | D22: =C22/B22-1 -> 0.080282641 | E22: =PL!E76+PL!E77 -> 19.618804 | F22: =E22/B22-1 -> -0.056788249 | G22: =PL!E105+PL!E106 -> 15.969836 | H22: =G22/B22-1 -> -0.23221942 | I22: SEMI 2026-07（equipment 成品）
A23: E. 其他資訊（非對帳）
A24: FY26 Q1 實績營收 ÷ 模型 FY2026 全年（A） | C24: =q1_rev/PL!D5 -> 0.22008159 | J24: AI 需求逐季上升，Q1 低於 25% 屬正常
A25: FY26 Q1 SoC×4 ÷ 模型 FY2026 SoC（A） | C25: =q1_soc*4/PL!D7 -> 0.86659324

Sheet Sens
A1: Sens — 一次動一個輸入（情境 A）：對 FY2027、FY2028 營收與 EPS 的影響。每個案例是一個完整的推導區塊（本頁下方，與 PL 同一引擎）
A3: 案例 | B3: 設定 | C3: FY2027 營收 ¥B | D3: FY2027 EPS ¥ | E3: 相對基準 | F3: FY2028 營收 ¥B | G3: FY2028 EPS ¥ | H3: 相對基準
A4: 基準（情境 A） | B4: PL 區塊 A | C4: =PL!E57 -> 2169.0494 | D4: =PL!E65 -> 1138.5516 | E4: =D4/D$4-1 -> 0 | F4: =PL!F57 -> 2482.1404 | G4: =PL!F65 -> 1297.8075 | H4: =G4/G$4-1 -> 0
A5: 市占 −5 個百分點 | B5: SoC 市占 61% | C5: =E67 -> 2049.9077 | D5: =E75 -> 1054.0363 | E5: =D5/D$4-1 -> -0.074230574 | F5: =F67 -> 2348.7647 | G5: =F75 -> 1203.195 | H5: =G5/G$4-1 -> -0.07290179
A6: 市占 +5 個百分點 | B6: SoC 市占 71% | C6: =E99 -> 2288.1912 | D6: =E107 -> 1223.0669 | E6: =D6/D$4-1 -> 0.074230574 | F6: =F99 -> 2615.5161 | G6: =F107 -> 1392.4199 | H6: =G6/G$4-1 -> 0.07290179
A7: 平行測試效率每年 −5%（Assumed） | B7: 每加權顆測試支出每年 −5%（2027 起） | C7: =E131 -> 2097.904 | D7: =E139 -> 1088.0833 | E7: =D7/D$4-1 -> -0.04432676 | F7: =F131 -> 2339.7456 | G7: =F139 -> 1196.7972 | H7: =G7/G$4-1 -> -0.077831491
A8: 平行測試效率每年 −10%（Assumed） | B8: 每年 −10% | C8: =E163 -> 2028.3238 | D8: =E171 -> 1038.7253 | E8: =D8/D$4-1 -> -0.087678313 | F8: =F163 -> 2207.125 | G8: =F171 -> 1102.7203 | H8: =G8/G$4-1 -> -0.15032055
A9: 每顆測試時間係數 低 | B9: 各平台 tt 取低值 | C9: =E195 -> 2133.0314 | D9: =E203 -> 1113.0016 | E9: =D9/D$4-1 -> -0.022440818 | F9: =F195 -> 2425.1422 | G9: =F203 -> 1257.3748 | H9: =G9/G$4-1 -> -0.031154624
A10: 每顆測試時間係數 高 | B10: 各平台 tt 取高值 | C10: =E227 -> 2214.6757 | D10: =E235 -> 1170.9174 | E10: =D10/D$4-1 -> 0.028427198 | F10: =F227 -> 2549.212 | G10: =F235 -> 1345.3859 | H10: =G10/G$4-1 -> 0.036660643
A11: 營業費用變動比例 低（35%） | B11: FY2025 營業費用中變動部分 35%（固定 65%） | C11: =E259 -> 2169.0494 | D11: =E267 -> 1186.7168 | E11: =D11/D$4-1 -> 0.042303934 | F11: =F259 -> 2482.1404 | G11: =F267 -> 1360.4665 | H11: =G11/G$4-1 -> 0.048280688
A12: 營業費用變動比例 高（75%） | B12: 變動 75%（固定 25%） | C12: =E291 -> 2169.0494 | D12: =E299 -> 1099.9073 | E12: =D12/D$4-1 -> -0.03394165 | F12: =F291 -> 2482.1404 | G12: =F299 -> 1247.5343 | H12: =G12/G$4-1 -> -0.03873697
A13: CY2026 SoC 市場 低（10.5） | B13: 校準錨 10.5 | C13: =E323 -> 2085.0557 | D13: =E331 -> 1078.9692 | E13: =D13/D$4-1 -> -0.052331794 | F13: =F323 -> 2385.4599 | G13: =F331 -> 1229.2254 | H13: =G13/G$4-1 -> -0.052844537
A14: CY2026 SoC 市場 高（11.5） | B14: 校準錨 11.5 | C14: =E355 -> 2253.0431 | D14: =E363 -> 1198.1341 | E14: =D14/D$4-1 -> 0.052331794 | F14: =F355 -> 2578.8209 | G14: =F363 -> 1366.3895 | H14: =G14/G$4-1 -> 0.052844537
A15: 非 AI SoC 低（3.7） | B15: AI 占比較高 → 每顆支出較高 | C15: =E387 -> 2207.4481 | D15: =E395 -> 1165.7904 | E15: =D15/D$4-1 -> 0.023924079 | F15: =F387 -> 2533.2674 | G15: =F395 -> 1334.0754 | H15: =G15/G$4-1 -> 0.027945513
A16: 非 AI SoC 高（4.9） | B16: AI 占比較低 → 每顆支出較低 | C16: =E419 -> 2130.6508 | D16: =E427 -> 1111.3128 | E16: =D16/D$4-1 -> -0.023924079 | F16: =F419 -> 2431.0133 | G16: =F427 -> 1261.5396 | H16: =G16/G$4-1 -> -0.027945513
A17: 記憶體市占 −5pt | C17: =E451 -> 2136.9022 | D17: =E459 -> 1131.8826 | E17: =D17/D$4-1 -> -0.0058574725 | F17: =F451 -> 2441.1835 | G17: =F459 -> 1289.3108 | H17: =G17/G$4-1 -> -0.0065469019
A18: 記憶體市占 +5pt | C18: =E483 -> 2201.1967 | D18: =E491 -> 1145.2206 | E18: =D18/D$4-1 -> 0.0058574725 | F18: =F483 -> 2523.0973 | G18: =F491 -> 1306.3041 | H18: =G18/G$4-1 -> 0.0065469019
A19: 記憶體 HBM 比重 低（30%） | C19: =E515 -> 2155.2316 | D19: =E523 -> 1135.6851 | E19: =D19/D$4-1 -> -0.0025177169 | F19: =F515 -> 2443.9213 | G19: =F523 -> 1289.8788 | H19: =G19/G$4-1 -> -0.006109268
A20: 記憶體 HBM 比重 高（70%） | C20: =E547 -> 2182.8673 | D20: =E555 -> 1141.4182 | E20: =D20/D$4-1 -> 0.0025177169 | F20: =F547 -> 2520.3595 | G20: =F555 -> 1305.7361 | H20: =G20/G$4-1 -> 0.006109268
A21: 匯率 ¥140 | C21: =E579 -> 2042.5443 | D21: =E587 -> 1059.6846 | E21: =D21/D$4-1 -> -0.069269597 | F21: =F579 -> 2337.1735 | G21: =F587 -> 1208.8236 | H21: =G21/G$4-1 -> -0.068564797
A22: 匯率 ¥160 | C22: =E611 -> 2295.5546 | D22: =E619 -> 1217.4186 | E22: =D22/D$4-1 -> 0.069269597 | F22: =F611 -> 2627.1073 | G22: =F619 -> 1386.7914 | H22: =G22/G$4-1 -> 0.068564797
A23: 淨利÷營業利益 低（0.72） | C23: =E643 -> 2169.0494 | D23: =E651 -> 1089.8796 | E23: =D23/D$4-1 -> -0.042749068 | F23: =F643 -> 2482.1404 | G23: =F651 -> 1242.3274 | H23: =G23/G$4-1 -> -0.042749068
A24: 淨利÷營業利益 0.780（指引隱含） | B24: 含戰略投資評價益（一次性），不當基準 | C24: =E675 -> 2169.0494 | D24: =E683 -> 1180.9176 | E24: =D24/D$4-1 -> 0.037210427 | F24: =F675 -> 2482.1404 | G24: =F683 -> 1346.0994 | H24: =G24/G$4-1 -> 0.037210427
A25: 顆數情境 B | B25: 2028 ×0.8、2029 ×0.85；記憶體 B 路徑；服務／其他系統成長 B | C25: =PL!E86 -> 2092.4375 | D25: =PL!E94 -> 1091.2338 | E25: =D25/D$4-1 -> -0.041559671 | F25: =PL!F86 -> 2196.6045 | G25: =PL!F94 -> 1117.4679 | H25: =G25/G$4-1 -> -0.13895713
A26: 顆數情境 C | B26: 2028–29 ×0.6；市占回落、毛利率下調 | C26: =PL!E115 -> 1992.7932 | D26: =PL!E123 -> 1039.1378 | E26: =D26/D$4-1 -> -0.087316 | F26: =PL!F115 -> 1700.0758 | G26: =PL!F123 -> 810.56821 | H26: =G26/G$4-1 -> -0.37543262
A28: 讀法：FY2027 以上各案例的差異主要來自 CY2027 市場（FY2027＝3/4×CY2027＋1/4×CY2028）；顆數情境 B、C 的 2028 係數只影響 FY2027 的 1／4，所以對 FY2027 影響小、對 FY2028 才明顯。
A50: 案例區塊：市占 −5 個百分點（情境 A）
A51: 項目 | B51: 單位 | C51: CY2026／FY2025 | D51: CY2027／FY2026 | E51: CY2028／FY2027 | F51: CY2029／FY2028 | G51: CY2030／FY2029 | H51: 說明
A52: A. 日曆年（C＝CY2026 … G＝CY2030）
A53: 測試時間加權顆數 | B53: 百萬顆 | C53: =u_bw_26*tt_bw+u_rb_26*tt_rb+u_ru_26*tt_ru+u_hp_26*tt_hp+u_amd_26*tt_amd+u_tpu_26*tt_tpu+u_trn_26*tt_trn+u_oth_26*tt_oth -> 14.885 | D53: =u_bw_27*tt_bw+u_rb_27*tt_rb+u_ru_27*tt_ru+u_hp_27*tt_hp+u_amd_27*tt_amd+u_tpu_27*tt_tpu+u_trn_27*tt_trn+u_oth_27*tt_oth -> 24.31 | E53: =u_bw_28*um28_A*tt_bw+u_rb_28*um28_A*tt_rb+u_ru_28*um28_A*tt_ru+u_hp_28*um28_A*tt_hp+u_amd_28*um28_A*tt_amd+u_tpu_28*um28_A*tt_tpu+u_trn_28*um28_A*tt_trn+u_oth_28*um28_A*tt_oth -> 28.1 | F53: =u_bw_28*(1+g29_bw)*um29_A*tt_bw+u_rb_28*(1+g29_rb)*um29_A*tt_rb+u_ru_28*(1+g29_ru)*um29_A*tt_ru+u_hp_28*(1+g29_hp)*um29_A*tt_hp+u_amd_28*(1+g29_amd)*um29_A*tt_amd+u_tpu_28*(1+g29_tpu)*um29_A*tt_tpu+u_trn_28*(1+g29_trn)*um29_A*tt_trn+u_oth_28*(1+g29_oth)*um29_A*tt_oth -> 31.99 | G53: =F53*(1+cy30g) -> 31.99 | H53: Σ 顆數 × tt；CY2030＝CY2029×(1+cy30g)
A54: 每加權顆測試支出（以 CY2026 校準） | B54: US$B／百萬顆 | C54: =(mk_soc26-nonai26)/C53 -> 0.45011757 | H54: （公司 CY2026 SoC 市場 − 非 AI）÷ 加權顆數
A55: AI SoC 測試機市場 | B55: US$B | C55: =$C$54*C53*(1-0)^0 -> 6.7 | D55: =$C$54*D53*(1-0)^1 -> 10.942358 | E55: =$C$54*E53*(1-0)^2 -> 12.648304 | F55: =$C$54*F53*(1-0)^3 -> 14.399261 | G55: =$C$54*G53*(1-0)^4 -> 14.399261
A56: 非 AI SoC 測試機市場 | B56: US$B | C56: =nonai26*(1+g_nonai)^0 -> 4.3 | D56: =nonai26*(1+g_nonai)^1 -> 4.472 | E56: =nonai26*(1+g_nonai)^2 -> 4.65088 | F56: =nonai26*(1+g_nonai)^3 -> 4.8369152 | G56: =nonai26*(1+g_nonai)^4 -> 5.0303918
A57: SoC 測試機市場 CY | B57: US$B | C57: =C55+C56 -> 11 | D57: =D55+D56 -> 15.414358 | E57: =E55+E56 -> 17.299184 | F57: =F55+F56 -> 19.236176 | G57: =G55+G56 -> 19.429653 | H57: CY2026 ＝ 公司規模（校準）
A58: 記憶體測試機市場 CY | B58: US$B | C58: =mk_mem26*(w_hbm*hsA_26/hsA_26+(1-w_hbm)*drA_26/drA_26) -> 2.75 | D58: =mk_mem26*(w_hbm*hsA_27/hsA_26+(1-w_hbm)*drA_27/drA_26) -> 3.9915065 | E58: =mk_mem26*(w_hbm*hsA_28/hsA_26+(1-w_hbm)*drA_28/drA_26) -> 5.1706953 | F58: =mk_mem26*(w_hbm*hsA_29/hsA_26+(1-w_hbm)*drA_29/drA_26) -> 6.3316064 | G58: =F58*(1+cy30g) -> 6.3316064 | H58: CY2026 錨定公司規模；之後＝w×HBM 出貨位元指數＋(1−w)×DRAM 設備支出指數
A59: B. 會計年度（C＝FY2025 … G＝FY2029；FY(t)＝3/4×CY(t)＋1/4×CY(t+1)）
A60: SoC 測試機市場 FY | B60: US$B | C60: =fmk_soc25 -> 7.925 | D60: =0.75*C57+0.25*D57 -> 12.10359 | E60: =0.75*D57+0.25*E57 -> 15.885564 | F60: =0.75*E57+0.25*F57 -> 17.783432 | G60: =0.75*F57+0.25*G57 -> 19.284545
A61: 記憶體測試機市場 FY | B61: US$B | C61: =fmk_mem25 -> 2.2625 | D61: =0.75*C58+0.25*D58 -> 3.0603766 | E61: =0.75*D58+0.25*E58 -> 4.2863037 | F61: =0.75*E58+0.25*F58 -> 5.4609231 | G61: =0.75*F58+0.25*G58 -> 6.3316064
A62: Advantest SoC 市占 | B62: % | C62: =a25_soc/(C60*fx) -> 0.64555205 | D62: =sh_soc_lo -> 0.61 | E62: =sh_soc_lo -> 0.61 | F62: =sh_soc_lo -> 0.61 | G62: =sh_soc_lo -> 0.61 | H62: FY2025＝實績隱含（對照公司自估 66%）
A63: SoC 測試機營收 | B63: ¥B | C63: =a25_soc -> 767.4 | D63: =D60*D62*fx -> 1107.4784 | E63: =E60*E62*fx -> 1453.5291 | F63: =F60*F62*fx -> 1627.184 | G63: =G60*G62*fx -> 1764.5359 | H63: 市場 × 市占 × 匯率
A64: 記憶體測試機營收 | B64: ¥B | C64: =a25_mem -> 171.5 | D64: =D61*sh_mem*fx -> 231.97993 | E64: =E61*sh_mem*fx -> 324.90655 | F64: =F61*sh_mem*fx -> 413.944 | G64: =G61*sh_mem*fx -> 479.94276
A65: 其他系統營收 | B65: ¥B | C65: =a25_oth -> 80.5 | D65: =C65*(1+g_oth_26) -> 104 | E65: =D65*(1+g_oth_A) -> 119.6 | F65: =E65*(1+g_oth_A) -> 137.54 | G65: =F65*(1+g_oth_A) -> 158.171
A66: 服務、支援與其他營收 | B66: ¥B | C66: =a25_svc -> 109.2 | D66: =C66*(1+g_svc_26) -> 135.6 | E66: =D66*(1+g_svc_A) -> 151.872 | F66: =E66*(1+g_svc_A) -> 170.09664 | G66: =F66*(1+g_svc_A) -> 190.50824
A67: 營收 | B67: ¥B | C67: =C63+C64+C65+C66 -> 1128.6 | D67: =D63+D64+D65+D66 -> 1579.0584 | E67: =E63+E64+E65+E66 -> 2049.9077 | F67: =F63+F64+F65+F66 -> 2348.7647 | G67: =G63+G64+G65+G66 -> 2593.1579
A68: SoC 占營收 | B68: % | C68: =C63/C67 -> 0.67995747 | D68: =D63/D67 -> 0.70135371 | E68: =E63/E67 -> 0.70907053 | F68: =F63/F67 -> 0.69278291 | G68: =G63/G67 -> 0.68045833
A69: 毛利率 | B69: % | C69: =a25_gp/a25_rev -> 0.643 | D69: =gm_a+gm_b*D68+0 -> 0.6533367 | E69: =gm_a+gm_b*E68+0 -> 0.65706476 | F69: =gm_a+gm_b*F68+0 -> 0.64919608 | G69: =gm_a+gm_b*G68+0 -> 0.64324197 | H69: 截距＋斜率×SoC 占比（兩點推導）
A70: 毛利 | B70: ¥B | C70: =C67*C69 -> 725.6898 | D70: =D67*D69 -> 1031.6568 | E70: =E67*E69 -> 1346.9221 | F70: =F67*F69 -> 1524.8088 | G70: =G67*G69 -> 1668.028
A71: 營業費用 | B71: ¥B | C71: =opex25 -> 226.5898 | D71: =opex_fix+opex_var*D67 -> 278.31495 | E71: =opex_fix+opex_var*E67 -> 332.38155 | F71: =opex_fix+opex_var*F67 -> 366.69863 | G71: =opex_fix+opex_var*G67 -> 394.76178 | H71: 固定＋變動×營收
A72: 營業利益 | B72: ¥B | C72: =C70-C71 -> 499.1 | D72: =D70-D71 -> 753.34184 | E72: =E70-E71 -> 1014.5406 | F72: =F70-F71 -> 1158.1102 | G72: =G70-G71 -> 1273.2662
A73: 營業利益率 | B73: % | C73: =C72/C67 -> 0.44222931 | D73: =D72/D67 -> 0.47708296 | E73: =E72/E67 -> 0.49492012 | F73: =F72/F67 -> 0.49307203 | G73: =G72/G67 -> 0.49100991
A74: 淨利 | B74: ¥B | C74: =a25_ni -> 375.4 | D74: =D72*nioi -> 566.62898 | E74: =E72*nioi -> 763.09062 | F74: =F72*nioi -> 871.07705 | G74: =G72*nioi -> 957.69213
A75: EPS | B75: ¥ | C75: =a25_eps -> 515.15 | D75: =D74*1000/shares -> 782.66916 | E75: =E74*1000/shares -> 1054.0363 | F75: =F74*1000/shares -> 1203.195 | G75: =G74*1000/shares -> 1322.834
A76: 營收（美元） | B76: US$B | C76: =C67/fx -> 7.524 | D76: =D67/fx -> 10.527056 | E76: =E67/fx -> 13.666051 | F76: =F67/fx -> 15.658431 | G76: =G67/fx -> 17.287719 | H76: FY2025 以基準匯率換算（顯示用）
A82: 案例區塊：市占 +5 個百分點（情境 A）
A83: 項目 | B83: 單位 | C83: CY2026／FY2025 | D83: CY2027／FY2026 | E83: CY2028／FY2027 | F83: CY2029／FY2028 | G83: CY2030／FY2029 | H83: 說明
A84: A. 日曆年（C＝CY2026 … G＝CY2030）
A85: 測試時間加權顆數 | B85: 百萬顆 | C85: =u_bw_26*tt_bw+u_rb_26*tt_rb+u_ru_26*tt_ru+u_hp_26*tt_hp+u_amd_26*tt_amd+u_tpu_26*tt_tpu+u_trn_26*tt_trn+u_oth_26*tt_oth -> 14.885 | D85: =u_bw_27*tt_bw+u_rb_27*tt_rb+u_ru_27*tt_ru+u_hp_27*tt_hp+u_amd_27*tt_amd+u_tpu_27*tt_tpu+u_trn_27*tt_trn+u_oth_27*tt_oth -> 24.31 | E85: =u_bw_28*um28_A*tt_bw+u_rb_28*um28_A*tt_rb+u_ru_28*um28_A*tt_ru+u_hp_28*um28_A*tt_hp+u_amd_28*um28_A*tt_amd+u_tpu_28*um28_A*tt_tpu+u_trn_28*um28_A*tt_trn+u_oth_28*um28_A*tt_oth -> 28.1 | F85: =u_bw_28*(1+g29_bw)*um29_A*tt_bw+u_rb_28*(1+g29_rb)*um29_A*tt_rb+u_ru_28*(1+g29_ru)*um29_A*tt_ru+u_hp_28*(1+g29_hp)*um29_A*tt_hp+u_amd_28*(1+g29_amd)*um29_A*tt_amd+u_tpu_28*(1+g29_tpu)*um29_A*tt_tpu+u_trn_28*(1+g29_trn)*um29_A*tt_trn+u_oth_28*(1+g29_oth)*um29_A*tt_oth -> 31.99 | G85: =F85*(1+cy30g) -> 31.99 | H85: Σ 顆數 × tt；CY2030＝CY2029×(1+cy30g)
A86: 每加權顆測試支出（以 CY2026 校準） | B86: US$B／百萬顆 | C86: =(mk_soc26-nonai26)/C85 -> 0.45011757 | H86: （公司 CY2026 SoC 市場 − 非 AI）÷ 加權顆數
A87: AI SoC 測試機市場 | B87: US$B | C87: =$C$86*C85*(1-0)^0 -> 6.7 | D87: =$C$86*D85*(1-0)^1 -> 10.942358 | E87: =$C$86*E85*(1-0)^2 -> 12.648304 | F87: =$C$86*F85*(1-0)^3 -> 14.399261 | G87: =$C$86*G85*(1-0)^4 -> 14.399261
A88: 非 AI SoC 測試機市場 | B88: US$B | C88: =nonai26*(1+g_nonai)^0 -> 4.3 | D88: =nonai26*(1+g_nonai)^1 -> 4.472 | E88: =nonai26*(1+g_nonai)^2 -> 4.65088 | F88: =nonai26*(1+g_nonai)^3 -> 4.8369152 | G88: =nonai26*(1+g_nonai)^4 -> 5.0303918
A89: SoC 測試機市場 CY | B89: US$B | C89: =C87+C88 -> 11 | D89: =D87+D88 -> 15.414358 | E89: =E87+E88 -> 17.299184 | F89: =F87+F88 -> 19.236176 | G89: =G87+G88 -> 19.429653 | H89: CY2026 ＝ 公司規模（校準）
A90: 記憶體測試機市場 CY | B90: US$B | C90: =mk_mem26*(w_hbm*hsA_26/hsA_26+(1-w_hbm)*drA_26/drA_26) -> 2.75 | D90: =mk_mem26*(w_hbm*hsA_27/hsA_26+(1-w_hbm)*drA_27/drA_26) -> 3.9915065 | E90: =mk_mem26*(w_hbm*hsA_28/hsA_26+(1-w_hbm)*drA_28/drA_26) -> 5.1706953 | F90: =mk_mem26*(w_hbm*hsA_29/hsA_26+(1-w_hbm)*drA_29/drA_26) -> 6.3316064 | G90: =F90*(1+cy30g) -> 6.3316064 | H90: CY2026 錨定公司規模；之後＝w×HBM 出貨位元指數＋(1−w)×DRAM 設備支出指數
A91: B. 會計年度（C＝FY2025 … G＝FY2029；FY(t)＝3/4×CY(t)＋1/4×CY(t+1)）
A92: SoC 測試機市場 FY | B92: US$B | C92: =fmk_soc25 -> 7.925 | D92: =0.75*C89+0.25*D89 -> 12.10359 | E92: =0.75*D89+0.25*E89 -> 15.885564 | F92: =0.75*E89+0.25*F89 -> 17.783432 | G92: =0.75*F89+0.25*G89 -> 19.284545
A93: 記憶體測試機市場 FY | B93: US$B | C93: =fmk_mem25 -> 2.2625 | D93: =0.75*C90+0.25*D90 -> 3.0603766 | E93: =0.75*D90+0.25*E90 -> 4.2863037 | F93: =0.75*E90+0.25*F90 -> 5.4609231 | G93: =0.75*F90+0.25*G90 -> 6.3316064
A94: Advantest SoC 市占 | B94: % | C94: =a25_soc/(C92*fx) -> 0.64555205 | D94: =sh_soc_hi -> 0.71 | E94: =sh_soc_hi -> 0.71 | F94: =sh_soc_hi -> 0.71 | G94: =sh_soc_hi -> 0.71 | H94: FY2025＝實績隱含（對照公司自估 66%）
A95: SoC 測試機營收 | B95: ¥B | C95: =a25_soc -> 767.4 | D95: =D92*D94*fx -> 1289.0323 | E95: =E92*E94*fx -> 1691.8126 | F95: =F92*F94*fx -> 1893.9355 | G95: =G92*G94*fx -> 2053.8041 | H95: 市場 × 市占 × 匯率
A96: 記憶體測試機營收 | B96: ¥B | C96: =a25_mem -> 171.5 | D96: =D93*sh_mem*fx -> 231.97993 | E96: =E93*sh_mem*fx -> 324.90655 | F96: =F93*sh_mem*fx -> 413.944 | G96: =G93*sh_mem*fx -> 479.94276
A97: 其他系統營收 | B97: ¥B | C97: =a25_oth -> 80.5 | D97: =C97*(1+g_oth_26) -> 104 | E97: =D97*(1+g_oth_A) -> 119.6 | F97: =E97*(1+g_oth_A) -> 137.54 | G97: =F97*(1+g_oth_A) -> 158.171
A98: 服務、支援與其他營收 | B98: ¥B | C98: =a25_svc -> 109.2 | D98: =C98*(1+g_svc_26) -> 135.6 | E98: =D98*(1+g_svc_A) -> 151.872 | F98: =E98*(1+g_svc_A) -> 170.09664 | G98: =F98*(1+g_svc_A) -> 190.50824
A99: 營收 | B99: ¥B | C99: =C95+C96+C97+C98 -> 1128.6 | D99: =D95+D96+D97+D98 -> 1760.6122 | E99: =E95+E96+E97+E98 -> 2288.1912 | F99: =F95+F96+F97+F98 -> 2615.5161 | G99: =G95+G96+G97+G98 -> 2882.4261
A100: SoC 占營收 | B100: % | C100: =C95/C99 -> 0.67995747 | D100: =D95/D99 -> 0.73215003 | E100: =E95/E99 -> 0.73936681 | F100: =F95/F99 -> 0.72411539 | G100: =G95/G99 -> 0.71252619
A101: 毛利率 | B101: % | C101: =a25_gp/a25_rev -> 0.643 | D101: =gm_a+gm_b*D100+0 -> 0.66821466 | E101: =gm_a+gm_b*E100+0 -> 0.67170115 | F101: =gm_a+gm_b*F100+0 -> 0.66433306 | G101: =gm_a+gm_b*G100+0 -> 0.65873422 | H101: 截距＋斜率×SoC 占比（兩點推導）
A102: 毛利 | B102: ¥B | C102: =C99*C101 -> 725.6898 | D102: =D99*D101 -> 1176.4669 | E102: =E99*E101 -> 1536.9806 | F102: =F99*F101 -> 1737.5738 | G102: =G99*G101 -> 1898.7527
A103: 營業費用 | B103: ¥B | C103: =opex25 -> 226.5898 | D103: =opex_fix+opex_var*D99 -> 299.16238 | E103: =opex_fix+opex_var*E99 -> 359.74311 | F103: =opex_fix+opex_var*F99 -> 397.32912 | G103: =opex_fix+opex_var*G99 -> 427.97781 | H103: 固定＋變動×營收
A104: 營業利益 | B104: ¥B | C104: =C102-C103 -> 499.1 | D104: =D102-D103 -> 877.30451 | E104: =E102-E103 -> 1177.2375 | F104: =F102-F103 -> 1340.2447 | G104: =G102-G103 -> 1470.7749
A105: 營業利益率 | B105: % | C105: =C104/C99 -> 0.44222931 | D105: =D104/D99 -> 0.49829514 | E105: =E104/E99 -> 0.5144839 | F105: =F104/F99 -> 0.51242074 | G105: =G104/G99 -> 0.51025589
A106: 淨利 | B106: ¥B | C106: =a25_ni -> 375.4 | D106: =D104*nioi -> 659.86799 | E106: =E104*nioi -> 885.46376 | F106: =F104*nioi -> 1008.0702 | G106: =G104*nioi -> 1106.249
A107: EPS | B107: ¥ | C107: =a25_eps -> 515.15 | D107: =D106*1000/shares -> 911.45765 | E107: =E106*1000/shares -> 1223.0669 | F107: =F106*1000/shares -> 1392.4199 | G107: =G106*1000/shares -> 1528.0316
A108: 營收（美元） | B108: US$B | C108: =C99/fx -> 7.524 | D108: =D99/fx -> 11.737415 | E108: =E99/fx -> 15.254608 | F108: =F99/fx -> 17.436774 | G108: =G99/fx -> 19.216174 | H108: FY2025 以基準匯率換算（顯示用）
A114: 案例區塊：平行測試效率每年 −5%（Assumed）（情境 A）
A115: 項目 | B115: 單位 | C115: CY2026／FY2025 | D115: CY2027／FY2026 | E115: CY2028／FY2027 | F115: CY2029／FY2028 | G115: CY2030／FY2029 | H115: 說明
A116: A. 日曆年（C＝CY2026 … G＝CY2030）
A117: 測試時間加權顆數 | B117: 百萬顆 | C117: =u_bw_26*tt_bw+u_rb_26*tt_rb+u_ru_26*tt_ru+u_hp_26*tt_hp+u_amd_26*tt_amd+u_tpu_26*tt_tpu+u_trn_26*tt_trn+u_oth_26*tt_oth -> 14.885 | D117: =u_bw_27*tt_bw+u_rb_27*tt_rb+u_ru_27*tt_ru+u_hp_27*tt_hp+u_amd_27*tt_amd+u_tpu_27*tt_tpu+u_trn_27*tt_trn+u_oth_27*tt_oth -> 24.31 | E117: =u_bw_28*um28_A*tt_bw+u_rb_28*um28_A*tt_rb+u_ru_28*um28_A*tt_ru+u_hp_28*um28_A*tt_hp+u_amd_28*um28_A*tt_amd+u_tpu_28*um28_A*tt_tpu+u_trn_28*um28_A*tt_trn+u_oth_28*um28_A*tt_oth -> 28.1 | F117: =u_bw_28*(1+g29_bw)*um29_A*tt_bw+u_rb_28*(1+g29_rb)*um29_A*tt_rb+u_ru_28*(1+g29_ru)*um29_A*tt_ru+u_hp_28*(1+g29_hp)*um29_A*tt_hp+u_amd_28*(1+g29_amd)*um29_A*tt_amd+u_tpu_28*(1+g29_tpu)*um29_A*tt_tpu+u_trn_28*(1+g29_trn)*um29_A*tt_trn+u_oth_28*(1+g29_oth)*um29_A*tt_oth -> 31.99 | G117: =F117*(1+cy30g) -> 31.99 | H117: Σ 顆數 × tt；CY2030＝CY2029×(1+cy30g)
A118: 每加權顆測試支出（以 CY2026 校準） | B118: US$B／百萬顆 | C118: =(mk_soc26-nonai26)/C117 -> 0.45011757 | H118: （公司 CY2026 SoC 市場 − 非 AI）÷ 加權顆數
A119: AI SoC 測試機市場 | B119: US$B | C119: =$C$118*C117*(1-eff_par_lo)^0 -> 6.7 | D119: =$C$118*D117*(1-eff_par_lo)^1 -> 10.39524 | E119: =$C$118*E117*(1-eff_par_lo)^2 -> 11.415094 | F119: =$C$118*F117*(1-eff_par_lo)^3 -> 12.345566 | G119: =$C$118*G117*(1-eff_par_lo)^4 -> 11.728288
A120: 非 AI SoC 測試機市場 | B120: US$B | C120: =nonai26*(1+g_nonai)^0 -> 4.3 | D120: =nonai26*(1+g_nonai)^1 -> 4.472 | E120: =nonai26*(1+g_nonai)^2 -> 4.65088 | F120: =nonai26*(1+g_nonai)^3 -> 4.8369152 | G120: =nonai26*(1+g_nonai)^4 -> 5.0303918
A121: SoC 測試機市場 CY | B121: US$B | C121: =C119+C120 -> 11 | D121: =D119+D120 -> 14.86724 | E121: =E119+E120 -> 16.065974 | F121: =F119+F120 -> 17.182482 | G121: =G119+G120 -> 16.75868 | H121: CY2026 ＝ 公司規模（校準）
A122: 記憶體測試機市場 CY | B122: US$B | C122: =mk_mem26*(w_hbm*hsA_26/hsA_26+(1-w_hbm)*drA_26/drA_26) -> 2.75 | D122: =mk_mem26*(w_hbm*hsA_27/hsA_26+(1-w_hbm)*drA_27/drA_26) -> 3.9915065 | E122: =mk_mem26*(w_hbm*hsA_28/hsA_26+(1-w_hbm)*drA_28/drA_26) -> 5.1706953 | F122: =mk_mem26*(w_hbm*hsA_29/hsA_26+(1-w_hbm)*drA_29/drA_26) -> 6.3316064 | G122: =F122*(1+cy30g) -> 6.3316064 | H122: CY2026 錨定公司規模；之後＝w×HBM 出貨位元指數＋(1−w)×DRAM 設備支出指數
A123: B. 會計年度（C＝FY2025 … G＝FY2029；FY(t)＝3/4×CY(t)＋1/4×CY(t+1)）
A124: SoC 測試機市場 FY | B124: US$B | C124: =fmk_soc25 -> 7.925 | D124: =0.75*C121+0.25*D121 -> 11.96681 | E124: =0.75*D121+0.25*E121 -> 15.166924 | F124: =0.75*E121+0.25*F121 -> 16.345101 | G124: =0.75*F121+0.25*G121 -> 17.076531
A125: 記憶體測試機市場 FY | B125: US$B | C125: =fmk_mem25 -> 2.2625 | D125: =0.75*C122+0.25*D122 -> 3.0603766 | E125: =0.75*D122+0.25*E122 -> 4.2863037 | F125: =0.75*E122+0.25*F122 -> 5.4609231 | G125: =0.75*F122+0.25*G122 -> 6.3316064
A126: Advantest SoC 市占 | B126: % | C126: =a25_soc/(C124*fx) -> 0.64555205 | D126: =sh_soc -> 0.66 | E126: =sh_soc -> 0.66 | F126: =sh_soc -> 0.66 | G126: =sh_soc -> 0.66 | H126: FY2025＝實績隱含（對照公司自估 66%）
A127: SoC 測試機營收 | B127: ¥B | C127: =a25_soc -> 767.4 | D127: =D124*D126*fx -> 1184.7142 | E127: =E124*E126*fx -> 1501.5254 | F127: =F124*F126*fx -> 1618.165 | G127: =G124*G126*fx -> 1690.5766 | H127: 市場 × 市占 × 匯率
A128: 記憶體測試機營收 | B128: ¥B | C128: =a25_mem -> 171.5 | D128: =D125*sh_mem*fx -> 231.97993 | E128: =E125*sh_mem*fx -> 324.90655 | F128: =F125*sh_mem*fx -> 413.944 | G128: =G125*sh_mem*fx -> 479.94276
A129: 其他系統營收 | B129: ¥B | C129: =a25_oth -> 80.5 | D129: =C129*(1+g_oth_26) -> 104 | E129: =D129*(1+g_oth_A) -> 119.6 | F129: =E129*(1+g_oth_A) -> 137.54 | G129: =F129*(1+g_oth_A) -> 158.171
A130: 服務、支援與其他營收 | B130: ¥B | C130: =a25_svc -> 109.2 | D130: =C130*(1+g_svc_26) -> 135.6 | E130: =D130*(1+g_svc_A) -> 151.872 | F130: =E130*(1+g_svc_A) -> 170.09664 | G130: =F130*(1+g_svc_A) -> 190.50824
A131: 營收 | B131: ¥B | C131: =C127+C128+C129+C130 -> 1128.6 | D131: =D127+D128+D129+D130 -> 1656.2941 | E131: =E127+E128+E129+E130 -> 2097.904 | F131: =F127+F128+F129+F130 -> 2339.7456 | G131: =G127+G128+G129+G130 -> 2519.1986
A132: SoC 占營收 | B132: % | C132: =C127/C131 -> 0.67995747 | D132: =D127/D131 -> 0.71528008 | E132: =E127/E131 -> 0.71572648 | F132: =F127/F131 -> 0.69159868 | G132: =G127/G131 -> 0.67107714
A133: 毛利率 | B133: % | C133: =a25_gp/a25_rev -> 0.643 | D133: =gm_a+gm_b*D132+0 -> 0.66006465 | E133: =gm_a+gm_b*E132+0 -> 0.6602803 | F133: =gm_a+gm_b*F132+0 -> 0.64862397 | G133: =gm_a+gm_b*G132+0 -> 0.63870984 | H133: 截距＋斜率×SoC 占比（兩點推導）
...

Sheet Sources
A1: 來源（公司原文頁面在建置環境無法開啟；數字取自搜尋引擎對這些文件的摘錄，並與第二來源交叉；原文待人工複核）
A2: 公司：FY2025 決算（英文，2026-04-27） | B2: https://www.advantest.com/en/news/2026/a81o6o0000000hgw-att/E_FR_FY2025_FN.pdf
A3: 公司：FY2025 決算短信（日文） | B3: https://www.advantest.com/ja/news/2026/a81o6o0000000heh-att/J_FR_FY2025_FN.pdf
A4: 公司：FY2025 Q4 Investor Note（2026-04-27） | B4: https://www.advantest.com/document/en/investors/ir-library/result/JE_BIZ_260427_note.pdf
A5: 公司：FY2025 Q3 Investor Note（2026-01-28） | B5: https://www.advantest.com/document/en/investors/ir-library/result/JE_BIZ_260128_note.pdf
A6: 公司：FY2025 Q2 Investor Note（2025-10-28） | B6: https://www.advantest.com/document/en/investors/ir-library/result/E_BIZ_251028_note.pdf
A7: 公司：FY2025 Q1 Investor Note（2025-07-29） | B7: https://www.advantest.com/document/en/investors/ir-library/result/E_BIZ_250729_note.pdf
A8: 公司：FY2026 Q1 Investor Note（2026-07-29） | B8: https://www.advantest.com/document/en/investors/ir-library/result/JE_BIZ_260729_note.pdf
A9: 公司：FY2026 Q1 決算短信（日文，2026-07-29） | B9: https://www.advantest.com/ja/news/2026/qnpuno0000000cnr-att/J_FR_FY2026_1Q.pdf
A10: 公司：FY2025 Q2 決算短信（日文） | B10: https://www.advantest.com/ja/news/2025/g2l53r0000000oc1-att/J_FR_FY2025_2Q.pdf
A11: 公司：IR 行事曆（FY2026 Q2 預定 2026-10-28 15:30 JST） | B11: https://www.advantest.com/en/investors/ir-calendar/
A12: Investing.com：FY25 簡報摘要（營收分項、毛利率 64.3%） | B12: https://www.investing.com/news/company-news/advantest-fy25-slides-record-margins-as-ai-testing-demand-surges-93CH-4639589
A13: Investing.com：Q3 FY25 簡報摘要 | B13: https://www.investing.com/news/company-news/advantest-q3-fy25-slides-record-sales-drive-guidance-upgrade-on-ai-demand-93CH-4470612
... A26: X（jukan05）：SoC 市占 56%→66%（二手轉述） | B26: https://x.com/jukan05/status/2048660802736140321
A27: 市場層：markets/memory/market.py（UNITS）；tsmc／skhynix／equipment 成品（本 repo）
A28: SemiAnalysis | B28: 未使用
