Workbook

Sheet README
A1: OpenAI 收支模型 v0.6-P2（2026-10-07）
A2: 命題（Andy 2026-09-30）：OpenAI 每 VR 等值 GW 的營收能否覆蓋每 GW 全成本；若不能，缺口由誰、以什麼條件融資。FY2025–FY2030，曆年制。
A4: 本版範圍 | B4: P1：repo 骨架、SRC_OAI（公司財務原始數據）、TK_Link（Tokenomics 快照）、Inputs（v0.5 Assumed 項目遷入）。P2：Demand（需求與 token 量）、Revenue（營收、Microsoft 分成、淨額）。算力、成本、融資於 P3–P5。
A5: Excel 為唯一計算引擎 | B5: 藍字＝輸入（Excel 擁有）；黑字＝公式；綠字＝跨頁連結。builder 只產生結構，重建時保留 Excel 內已改過的藍字。
A6: SRC_OAI | B6: 122 列；v0.5『已取得的原始訊息』逐筆遷入（Interested-party／Verified）。
A7: TK_Link | B7: Tokenomics v5.24（20261007_Tokenomics_v5.24.xlsx），master 提交 bdb0de7，讀取日 2026-10-07；62 個名稱有值、0 個待 Tokenomics 提供。
A8: Inputs | B8: 243 列；v0.5 Assumed／Analogy／Decision 項目（長表）。
A9: Map_v05 | B9: v0.5 JSON 849 個葉節點的去處。
A10: Demand | B10: P2 需求：訂閱各方案人數、每日任務數 × 每任務 token、API 任務數與計費 token；token 量（層級 × 付費／免費，具名範圍 DEM_Tok_*，供 P3）。
A11: Revenue | B11: P2 營收：API 單價路徑（2026 依價格事件時點天數加權）、訂閱、API、廣告、其他、總額、Microsoft 分成、淨額（具名範圍 REV_*）。
A12: Checks | B12: P1、P2 檢查；CHK_Errors 必須為 0。
A13: 一手／二手圖例 | B13: 『二手（含一手公告轉載）』＝媒體轉載公司公開公告；『二手（含一手轉載）』＝F2，媒體轉載外流財報或內部文件；兩者不合併。（同文見 SRC_OAI 頁首說明）
A14: 標記 | B14: Verified／Interested-party／Analogy／Assumed／Derived（Analogy、Assumed 一律附區間）。
A15: 分層 | B15: 公司財務原始數據→SRC_OAI；AI 技術與算力→TK_Link（取自 Tokenomics 名稱）；假設→Inputs。

Sheet SRC_OAI
A1: SRC_OAI — 第 0 層 Source：OpenAI 公司財務原始數據（營收、合約、現金、融資輪、算力規模）
A2: 只存已取得的原始訊息（非計算、非假設；V5）。藍字＝原始值，由本活頁簿擁有；格式比照 Tokenomics SRC_Demand。AI 技術與算力原始數據不在此登錄（取自 TK_Link）。
A3: 來源等級（1 一手已讀原文／2 二手已讀或轉載／3 待查核）、立場、立場說明、一手／二手：依 builder/source_rules.py 的機械規則由 CC 初評（欄 Y 標『CC 初評』；V10）；規則無法判定者填『未評』。本包不做新查核。 圖例：『二手（含一手公告轉載）』＝媒體轉載公司公開公告；『二手（含一手轉載）』＝媒體轉載外流財報或內部文件（F2）；兩者不合併。
A4: SRC_ID | B4: 指標 | C4: 數值 | D4: 低 | E4: 高 | F4: 單位 | G4: 口徑 | H4: 適用對象 | I4: 日期 | J4: 出處（v0.5 原文） | K4: 來源等級 | L4: 立場 | M4: 立場說明 | N4: 一手／二手 | O4: 狀態 | P4: 取代者 | Q4: v0.5 標記 | R4: 查核狀態（v0.5 chk） | S4: v0.5 路徑 | T4: 模型使用位置 | U4: 備註 | V4: 缺值（公式） | W4: 缺出處（公式） | X4: 區間順序異常（公式） | Y4: 四欄標註
A5: SRC_OAI_001 | B5: 營收：FY2024 | C5: 3.7 | F5: $B | G5: FY2024 認列營收 | H5: OpenAI | I5: — | J5: OpenAI 揭露經媒體報導；workbook OpenAI_Sim B5 | K5: 2 | L5: 利害關係方 | M5: 公司公告：誘因為宣傳成長與用戶規模 | N5: 二手（含一手公告轉載） | O5: Active | P5: — | Q5: Interested-party | R5: — | S5: tokenRevenue.actuals.revenue2024 | T5: P2 校準；P5 對帳 | V5: =IF(AND($O5="Active",$C5="",$D5="",$E5="",$F5<>"文字"),1,0) -> 0 | W5: =IF(AND($O5="Active",OR($J5="",$J5="—")),1,0) -> 0 | X5: =IF(AND(ISNUMBER($C5),ISNUMBER($D5),ISNUMBER($E5)),IF(AND($D5<=$C5,$C5<=$E5),0,1),0) -> 0 | Y5: CC 初評
A6: SRC_OAI_002 | B6: 營收：FY2025 | C6: 13.07 | F6: $B | G6: FY2025 認列營收（外流經查核財報） | H6: OpenAI | I6: 2026-06 | J6: Fortune/FT 2026-06 報導之 FY2025 認列營收（經查核數字外流） | K6: 2 | L6: 利害關係方 | M6: 管理層、內部文件或外流數據：誘因為募資與議價，傾向呈現成長與算力需求 | N6: 二手（含一手轉載） | O6: Active | P6: — | Q6: Interested-party | R6: — | S6: tokenRevenue.actuals.revenue2025 | T6: P2 校準；P5 對帳 | V6: =IF(AND($O6="Active",$C6="",$D6="",$E6="",$F6<>"文字"),1,0) -> 0 | W6: =IF(AND($O6="Active",OR($J6="",$J6="—")),1,0) -> 0 | X6: =IF(AND(ISNUMBER($C6),ISNUMBER($D6),ISNUMBER($E6)),IF(AND($D6<=$C6,$C6<=$E6),0,1),0) -> 0 | Y6: CC 初評
A7: SRC_OAI_003 | B7: 營業成本（cost of revenue）：FY2025 | C7: 7.5 | F7: $B | G7: 含推論；FY2025 | H7: OpenAI | I7: 2026-06 | J7: Fortune/FT 2026-06 報導之 FY2025 認列營收（經查核數字外流）（追溯自「同上」鏈：本列←『營收：FY2025』；原文：同上；cost of revenue 含推論） | K7: 2 | L7: 利害關係方 | M7: 管理層、內部文件或外流數據：誘因為募資與議價，傾向呈現成長與算力需求 | N7: 二手（含一手轉載） | O7: Active | P7: — | Q7: Interested-party | R7: — | S7: tokenRevenue.actuals.cogs2025 | T7: P4 對帳 | V7: =IF(AND($O7="Active",$C7="",$D7="",$E7="",$F7<>"文字"),1,0) -> 0 | W7: =IF(AND($O7="Active",OR($J7="",$J7="—")),1,0) -> 0 | X7: =IF(AND(ISNUMBER($C7),ISNUMBER($D7),ISNUMBER($E7)),IF(AND($D7<=$C7,$C7<=$E7),0,1),0) -> 0 | Y7: CC 初評
A8: SRC_OAI_004 | B8: 營收：2026 Q1 | C8: 5.7 | F8: $B | G8: 2026 Q1（股東文件） | H8: OpenAI | I8: 2026-06-16 | J8: The Information 2026-06-16（股東文件） | K8: 2 | L8: 利害關係方 | M8: 管理層、內部文件或外流數據：誘因為募資與議價，傾向呈現成長與算力需求 | N8: 二手 | O8: Active | P8: — | Q8: Interested-party | R8: — | S8: tokenRevenue.actuals.revenueQ1_2026 | T8: P2 對照（fy2026Independent 的組成） | V8: =IF(AND($O8="Active",$C8="",$D8="",$E8="",$F8<>"文字"),1,0) -> 0 | W8: =IF(AND($O8="Active",OR($J8="",$J8="—")),1,0) -> 0 | X8: =IF(AND(ISNUMBER($C8),ISNUMBER($D8),ISNUMBER($E8)),IF(AND($D8<=$C8,$C8<=$E8),0,1),0) -> 0 | Y8: CC 初評
A9: SRC_OAI_005 | B9: 營收：2026 Q2 | C9: 6.7 | F9: $B | G9: 2026 Q2（告知投資人） | H9: OpenAI | I9: 2026-08-18 | J9: WSJ 2026-08-18（告知投資人） | K9: 2 | L9: 利害關係方 | M9: 管理層、內部文件或外流數據：誘因為募資與議價，傾向呈現成長與算力需求 | N9: 二手 | O9: Active | P9: — | Q9: Interested-party | R9: — | S9: tokenRevenue.actuals.revenueQ2_2026 | T9: P2 對照 | V9: =IF(AND($O9="Active",$C9="",$D9="",$E9="",$F9<>"文字"),1,0) -> 0 | W9: =IF(AND($O9="Active",OR($J9="",$J9="—")),1,0) -> 0 | X9: =IF(AND(ISNUMBER($C9),ISNUMBER($D9),ISNUMBER($E9)),IF(AND($D9<=$C9,$C9<=$E9),0,1),0) -> 0 | Y9: CC 初評
A10: SRC_OAI_006 | B10: 年化營收（ARR）：2026-08 | C10: 40 | F10: $B | G10: ARR；2026 年 8 月 | H10: OpenAI | I10: 2026-08-13 | J10: Bloomberg 2026-08-13；CNBC 2026-08-14 證實 | K10: 2 | L10: 利害關係方 | M10: 未評 | N10: 二手 | O10: Active | P10: — | Q10: Interested-party | R10: — | S10: tokenRevenue.actuals.arrAug2026 | T10: P2 對照 | V10: =IF(AND($O10="Active",$C10="",$D10="",$E10="",$F10<>"文字"),1,0) -> 0 | W10: =IF(AND($O10="Active",OR($J10="",$J10="—")),1,0) -> 0 | X10: =IF(AND(ISNUMBER($C10),ISNUMBER($D10),ISNUMBER($E10)),IF(AND($D10<=$C10,$C10<=$E10),0,1),0) -> 0 | Y10: CC 初評
A11: SRC_OAI_007 | B11: 消費端營收占比：2026 年初 | C11: 0.6 | F11: 比例 | G11: 年初消費／企業 60／40；8 月企業已超過消費端 | H11: OpenAI | I11: 2026-08-14 | J11: CFO Friar 2026-08-14 投資人會議：年初 60/40，8 月企業已超過消費端（CNBC） | K11: 2 | L11: 利害關係方 | M11: 管理層、內部文件或外流數據：誘因為募資與議價，傾向呈現成長與算力需求 | N11: 二手 | O11: Active | P11: — | Q11: Interested-party | R11: — | S11: tokenRevenue.actuals.consumerShareStart2026 | T11: P2 對照 | V11: =IF(AND($O11="Active",$C11="",$D11="",$E11="",$F11<>"文字"),1,0) -> 0 | W11: =IF(AND($O11="Active",OR($J11="",$J11="—")),1,0) -> 0 | X11: =IF(AND(ISNUMBER($C11),ISNUMBER($D11),ISNUMBER($E11)),IF(AND($D11<=$C11,$C11<=$E11),0,1),0) -> 0 | Y11: CC 初評
A12: SRC_OAI_008 | B12: API 每分鐘處理 token：2025-10 | C12: 6 | F12: B tok/min | G12: API 每分鐘 token；DevDay 揭露 | H12: OpenAI | I12: 2025-10 | J12: Altman DevDay 2025-10；2026 年更新揭露檢索未得 | K12: 2 | L12: 利害關係方 | M12: 未評 | N12: 一手 | O12: Active | P12: — | Q12: Interested-party | R12: — | S12: tokenRevenue.actuals.apiTokensPerMinOct2025 | T12: P2 校準檢查 | U12: 2026 年更新揭露檢索未得（v0.5 註記） | V12: =IF(AND($O12="Active",$C12="",$D12="",$E12="",$F12<>"文字"),1,0) -> 0 | W12: =IF(AND($O12="Active",OR($J12="",$J12="—")),1,0) -> 0 | X12: =IF(AND(ISNUMBER($C12),ISNUMBER($D12),ISNUMBER($E12)),IF(AND($D12<=$C12,$C12<=$E12),0,1),0) -> 0 | Y12: CC 初評
A13: SRC_OAI_009 | B13: Microsoft 營收分成率 | C13: 0.2 | F13: 比例 | G13: OpenAI 付 Microsoft 之營收分成 | H13: Microsoft | I13: 2026-04-27 | J13: CNBC 2026-04-27 引述知情人士；VentureBeat 同 | K13: 2 | L13: 利害關係方 | M13: 交易對手公告或轉述：誘因為宣傳合約規模與客戶關係 | N13: 二手 | O13: Active | P13: — | Q13: Interested-party | R13: — | S13: tokenRevenue.msShare.rate | T13: P2 淨額 | V13: =IF(AND($O13="Active",$C13="",$D13="",$E13="",$F13<>"文字"),1,0) -> 0 | W13: =IF(AND($O13="Active",OR($J13="",$J13="—")),1,0) -> 0 | X13: =IF(AND(ISNUMBER($C13),ISNUMBER($D13),ISNUMBER($E13)),IF(AND($D13<=$C13,$C13<=$E13),0,1),0) -> 0 | Y13: CC 初評
A14: SRC_OAI_010 | B14: Microsoft 分成總額上限 | C14: 38 | F14: $B | G14: 分成累計上限 | H14: Microsoft | I14: 2026-05 | J14: The Information 2026-05（經 AI Magazine、GuruFocus 轉述） | K14: 2 | L14: 利害關係方 | M14: 交易對手公告或轉述：誘因為宣傳合約規模與客戶關係 | N14: 二手 | O14: Active | P14: — | Q14: Interested-party | R14: — | S14: tokenRevenue.msShare.capTotal | T14: P2 淨額 | V14: =IF(AND($O14="Active",$C14="",$D14="",$E14="",$F14<>"文字"),1,0) -> 0 | W14: =IF(AND($O14="Active",OR($J14="",$J14="—")),1,0) -> 0 | X14: =IF(AND(ISNUMBER($C14),ISNUMBER($D14),ISNUMBER($E14)),IF(AND($D14<=$C14,$C14<=$E14),0,1),0) -> 0 | Y14: CC 初評
A15: SRC_OAI_011 | B15: Microsoft 分成付款持續至 | C15: 2030 | F15: 年 | G15: 付款持續至該年；受總額上限 | H15: Microsoft | I15: 2026-04-27 | J15: OpenAI／Microsoft 2026-04-27 公告：付款持續至 2030，受總額上限 | K15: 2 | L15: 利害關係方 | M15: 合約雙方公告；OpenAI 有募資與算力規模訊號誘因，供應商有營收與股價訊號誘因；金額為承諾總額，非實付 | N15: 一手 | O15: Active | P15: — | Q15: Verified | R15: — | S15: tokenRevenue.msShare.capThroughYear | T15: P2 淨額 | V15: =IF(AND($O15="Active",$C15="",$D15="",$E15="",$F15<>"文字"),1,0) -> 0 | W15: =IF(AND($O15="Active",OR($J15="",$J15="—")),1,0) -> 0 | X15: =IF(AND(ISNUMBER($C15),ISNUMBER($D15),ISNUMBER($E15)),IF(AND($D15<=$C15,$C15<=$E15),0,1),0) -> 0 | Y15: CC 初評
A16: SRC_OAI_012 | B16: Microsoft 對 OpenAI 的分潤（2026-04 後） | C16: 0 | F16: $B | G16: 2026-04-27 起 Microsoft 不再支付 OpenAI 分潤 | H16: Microsoft | I16: 2026-04-27 | J16: 2026-04-27 公告：Microsoft 不再支付 OpenAI 分潤 | K16: 2 | L16: 利害關係方 | M16: 合約雙方公告；OpenAI 有募資與算力規模訊號誘因，供應商有營收與股價訊號誘因；金額為承諾總額，非實付 | N16: 一手 | O16: Active | P16: — | Q16: Verified | R16: — | S16: tokenRevenue.msShare.azureInflowAfterApr2026 | T16: P2 淨額 | V16: =IF(AND($O16="Active",$C16="",$D16="",$E16="",$F16<>"文字"),1,0) -> 0 | W16: =IF(AND($O16="Active",OR($J16="",$J16="—")),1,0) -> 0 | X16: =IF(AND(ISNUMBER($C16),ISNUMBER($D16),ISNUMBER($E16)),IF(AND($D16<=$C16,$C16<=$E16),0,1),0) -> 0 | Y16: CC 初評
A17: SRC_OAI_013 | B17: API 牌價：top 層 輸入 | C17: 10 | F17: $/M tokens | G17: 短上下文 Standard；層級＝gpt-6-astra | H17: OpenAI | I17: 2026-09-25 | J17: developers.openai.com/api/docs/pricing（短上下文 Standard） | K17: 2 | L17: 利害關係方 | M17: 公開且具約束力的報價，誤報誘因低 | N17: 一手 | O17: Active | P17: — | Q17: Verified | R17: — | S17: tokenRevenue.api.listPriceSnapshot | T17: P2 單價路徑起點 | V17: =IF(AND($O17="Active",$C17="",$D17="",$E17="",$F17<>"文字"),1,0) -> 0 | W17: =IF(AND($O17="Active",OR($J17="",$J17="—")),1,0) -> 0 | X17: =IF(AND(ISNUMBER($C17),ISNUMBER($D17),ISNUMBER($E17)),IF(AND($D17<=$C17,$C17<=$E17),0,1),0) -> 0 | Y17: CC 初評
A18: SRC_OAI_014 | B18: API 牌價：top 層 快取輸入 | C18: 1 | F18: $/M tokens | G18: 短上下文 Standard；層級＝gpt-6-astra | H18: OpenAI | I18: 2026-09-25 | J18: developers.openai.com/api/docs/pricing（短上下文 Standard） | K18: 2 | L18: 利害關係方 | M18: 公開且具約束力的報價，誤報誘因低 | N18: 一手 | O18: Active | P18: — | Q18: Verified | R18: — | S18: tokenRevenue.api.listPriceSnapshot | T18: P2 單價路徑起點 | V18: =IF(AND($O18="Active",$C18="",$D18="",$E18="",$F18<>"文字"),1,0) -> 0 | W18: =IF(AND($O18="Active",OR($J18="",$J18="—")),1,0) -> 0 | X18: =IF(AND(ISNUMBER($C18),ISNUMBER($D18),ISNUMBER($E18)),IF(AND($D18<=$C18,$C18<=$E18),0,1),0) -> 0 | Y18: CC 初評
A19: SRC_OAI_015 | B19: API 牌價：top 層 輸出 | C19: 50 | F19: $/M tokens | G19: 短上下文 Standard；層級＝gpt-6-astra | H19: OpenAI | I19: 2026-09-25 | J19: developers.openai.com/api/docs/pricing（短上下文 Standard） | K19: 2 | L19: 利害關係方 | M19: 公開且具約束力的報價，誤報誘因低 | N19: 一手 | O19: Active | P19: — | Q19: Verified | R19: — | S19: tokenRevenue.api.listPriceSnapshot | T19: P2 單價路徑起點 | V19: =IF(AND($O19="Active",$C19="",$D19="",$E19="",$F19<>"文字"),1,0) -> 0 | W19: =IF(AND($O19="Active",OR($J19="",$J19="—")),1,0) -> 0 | X19: =IF(AND(ISNUMBER($C19),ISNUMBER($D19),ISNUMBER($E19)),IF(AND($D19<=$C19,$C19<=$E19),0,1),0) -> 0 | Y19: CC 初評
A20: SRC_OAI_016 | B20: API 牌價：mid 層 輸入 | C20: 2 | F20: $/M tokens | G20: 短上下文 Standard；層級＝gpt-6-sol | H20: OpenAI | I20: 2026-09-25 | J20: developers.openai.com/api/docs/pricing（短上下文 Standard） | K20: 2 | L20: 利害關係方 | M20: 公開且具約束力的報價，誤報誘因低 | N20: 一手 | O20: Active | P20: — | Q20: Verified | R20: — | S20: tokenRevenue.api.listPriceSnapshot | T20: P2 單價路徑起點 | V20: =IF(AND($O20="Active",$C20="",$D20="",$E20="",$F20<>"文字"),1,0) -> 0 | W20: =IF(AND($O20="Active",OR($J20="",$J20="—")),1,0) -> 0 | X20: =IF(AND(ISNUMBER($C20),ISNUMBER($D20),ISNUMBER($E20)),IF(AND($D20<=$C20,$C20<=$E20),0,1),0) -> 0 | Y20: CC 初評
A21: SRC_OAI_017 | B21: API 牌價：mid 層 快取輸入 | C21: 0.2 | F21: $/M tokens | G21: 短上下文 Standard；層級＝gpt-6-sol | H21: OpenAI | I21: 2026-09-25 | J21: developers.openai.com/api/docs/pricing（短上下文 Standard） | K21: 2 | L21: 利害關係方 | M21: 公開且具約束力的報價，誤報誘因低 | N21: 一手 | O21: Active | P21: — | Q21: Verified | R21: — | S21: tokenRevenue.api.listPriceSnapshot | T21: P2 單價路徑起點 | V21: =IF(AND($O21="Active",$C21="",$D21="",$E21="",$F21<>"文字"),1,0) -> 0 | W21: =IF(AND($O21="Active",OR($J21="",$J21="—")),1,0) -> 0 | X21: =IF(AND(ISNUMBER($C21),ISNUMBER($D21),ISNUMBER($E21)),IF(AND($D21<=$C21,$C21<=$E21),0,1),0) -> 0 | Y21: CC 初評
A22: SRC_OAI_018 | B22: API 牌價：mid 層 輸出 | C22: 10 | F22: $/M tokens | G22: 短上下文 Standard；層級＝gpt-6-sol | H22: OpenAI | I22: 2026-09-25 | J22: developers.openai.com/api/docs/pricing（短上下文 Standard） | K22: 2 | L22: 利害關係方 | M22: 公開且具約束力的報價，誤報誘因低 | N22: 一手 | O22: Active | P22: — | Q22: Verified | R22: — | S22: tokenRevenue.api.listPriceSnapshot | T22: P2 單價路徑起點 | V22: =IF(AND($O22="Active",$C22="",$D22="",$E22="",$F22<>"文字"),1,0) -> 0 | W22: =IF(AND($O22="Active",OR($J22="",$J22="—")),1,0) -> 0 | X22: =IF(AND(ISNUMBER($C22),ISNUMBER($D22),ISNUMBER($E22)),IF(AND($D22<=$C22,$C22<=$E22),0,1),0) -> 0 | Y22: CC 初評
A23: SRC_OAI_019 | B23: API 牌價：low 層 輸入 | C23: 0.1 | F23: $/M tokens | G23: 短上下文 Standard；層級＝gpt-6-luna | H23: OpenAI | I23: 2026-09-25 | J23: developers.openai.com/api/docs/pricing（短上下文 Standard） | K23: 2 | L23: 利害關係方 | M23: 公開且具約束力的報價，誤報誘因低 | N23: 一手 | O23: Active | P23: — | Q23: Verified | R23: — | S23: tokenRevenue.api.listPriceSnapshot | T23: P2 單價路徑起點 | V23: =IF(AND($O23="Active",$C23="",$D23="",$E23="",$F23<>"文字"),1,0) -> 0 | W23: =IF(AND($O23="Active",OR($J23="",$J23="—")),1,0) -> 0 | X23: =IF(AND(ISNUMBER($C23),ISNUMBER($D23),ISNUMBER($E23)),IF(AND($D23<=$C23,$C23<=$E23),0,1),0) -> 0 | Y23: CC 初評
A24: SRC_OAI_020 | B24: API 牌價：low 層 快取輸入 | C24: 0.01 | F24: $/M tokens | G24: 短上下文 Standard；層級＝gpt-6-luna | H24: OpenAI | I24: 2026-09-25 | J24: developers.openai.com/api/docs/pricing（短上下文 Standard） | K24: 2 | L24: 利害關係方 | M24: 公開且具約束力的報價，誤報誘因低 | N24: 一手 | O24: Active | P24: — | Q24: Verified | R24: — | S24: tokenRevenue.api.listPriceSnapshot | T24: P2 單價路徑起點 | V24: =IF(AND($O24="Active",$C24="",$D24="",$E24="",$F24<>"文字"),1,0) -> 0 | W24: =IF(AND($O24="Active",OR($J24="",$J24="—")),1,0) -> 0 | X24: =IF(AND(ISNUMBER($C24),ISNUMBER($D24),ISNUMBER($E24)),IF(AND($D24<=$C24,$C24<=$E24),0,1),0) -> 0 | Y24: CC 初評
A25: SRC_OAI_021 | B25: API 牌價：low 層 輸出 | C25: 0.5 | F25: $/M tokens | G25: 短上下文 Standard；層級＝gpt-6-luna | H25: OpenAI | I25: 2026-09-25 | J25: developers.openai.com/api/docs/pricing（短上下文 Standard） | K25: 2 | L25: 利害關係方 | M25: 公開且具約束力的報價，誤報誘因低 | N25: 一手 | O25: Active | P25: — | Q25: Verified | R25: — | S25: tokenRevenue.api.listPriceSnapshot | T25: P2 單價路徑起點 | V25: =IF(AND($O25="Active",$C25="",$D25="",$E25="",$F25<>"文字"),1,0) -> 0 | W25: =IF(AND($O25="Active",OR($J25="",$J25="—")),1,0) -> 0 | X25: =IF(AND(ISNUMBER($C25),ISNUMBER($D25),ISNUMBER($E25)),IF(AND($D25<=$C25,$C25<=$E25),0,1),0) -> 0 | Y25: CC 初評
A26: SRC_OAI_022 | B26: API 層級對應：top | C26: gpt-6-astra | F26: 文字 | G26: 2026-09 各層級的旗艦型號 | H26: OpenAI | I26: 2026-09-25 | J26: OpenAI 價格頁 developers.openai.com/api/docs/pricing（2026-09-25） | K26: 2 | L26: 利害關係方 | M26: 公開且具約束力的報價，誤報誘因低 | N26: 一手 | O26: Active | P26: — | Q26: Verified | R26: — | S26: tokenRevenue.api.tierMapSep2026.top | T26: P2 層級對照 | U26: E8b：文字列，只作標籤（Verified） | V26: =IF(AND($O26="Active",$C26="",$D26="",$E26="",$F26<>"文字"),1,0) -> 0 | W26: =IF(AND($O26="Active",OR($J26="",$J26="—")),1,0) -> 0 | X26: =IF(AND(ISNUMBER($C26),ISNUMBER($D26),ISNUMBER($E26)),IF(AND($D26<=$C26,$C26<=$E26),0,1),0) -> 0 | Y26: CC 初評
A27: SRC_OAI_023 | B27: API 層級對應：mid | C27: gpt-6-sol | F27: 文字 | G27: 2026-09 各層級的旗艦型號 | H27: OpenAI | I27: 2026-09-25 | J27: OpenAI 價格頁 developers.openai.com/api/docs/pricing（2026-09-25） | K27: 2 | L27: 利害關係方 | M27: 公開且具約束力的報價，誤報誘因低 | N27: 一手 | O27: Active | P27: — | Q27: Verified | R27: — | S27: tokenRevenue.api.tierMapSep2026.mid | T27: P2 層級對照 | U27: E8b：文字列，只作標籤（Verified） | V27: =IF(AND($O27="Active",$C27="",$D27="",$E27="",$F27<>"文字"),1,0) -> 0 | W27: =IF(AND($O27="Active",OR($J27="",$J27="—")),1,0) -> 0 | X27: =IF(AND(ISNUMBER($C27),ISNUMBER($D27),ISNUMBER($E27)),IF(AND($D27<=$C27,$C27<=$E27),0,1),0) -> 0 | Y27: CC 初評
A28: SRC_OAI_024 | B28: API 層級對應：low | C28: gpt-6-luna | F28: 文字 | G28: 2026-09 各層級的旗艦型號 | H28: OpenAI | I28: 2026-09-25 | J28: OpenAI 價格頁 developers.openai.com/api/docs/pricing（2026-09-25） | K28: 2 | L28: 利害關係方 | M28: 公開且具約束力的報價，誤報誘因低 | N28: 一手 | O28: Active | P28: — | Q28: Verified | R28: — | S28: tokenRevenue.api.tierMapSep2026.low | T28: P2 層級對照 | U28: E8b：文字列，只作標籤（Verified） | V28: =IF(AND($O28="Active",$C28="",$D28="",$E28="",$F28<>"文字"),1,0) -> 0 | W28: =IF(AND($O28="Active",OR($J28="",$J28="—")),1,0) -> 0 | X28: =IF(AND(ISNUMBER($C28),ISNUMBER($D28),ISNUMBER($E28)),IF(AND($D28<=$C28,$C28<=$E28),0,1),0) -> 0 | Y28: CC 初評
A29: SRC_OAI_025 | B29: API 價格事件 1 | C29: 07-09 GPT-5.6 Sol 5/30、Terra 2.5/15、Luna 1/6 | F29: 文字 | G29: 價格事件（輸入／輸出 $/M） | H29: OpenAI | I29: 2026-07-09 | J29: openai.com 2026-07-30 GPT-5.6 降價公告；GPT-6 Sol/Luna 2026-09-22 發布（Techzine、MarkTechPost）；GPT-6 Astra 2026-09-03 | K29: 2 | L29: 利害關係方 | M29: 公開且具約束力的報價，誤報誘因低 | N29: 一手 | O29: Active | P29: — | Q29: Verified | R29: — | S29: tokenRevenue.api.priceEvents2026 | T29: P2 FY 平均牌價（2026）的月加權依據 | V29: =IF(AND($O29="Active",$C29="",$D29="",$E29="",$F29<>"文字"),1,0) -> 0 | W29: =IF(AND($O29="Active",OR($J29="",$J29="—")),1,0) -> 0 | X29: =IF(AND(ISNUMBER($C29),ISNUMBER($D29),ISNUMBER($E29)),IF(AND($D29<=$C29,$C29<=$E29),0,1),0) -> 0 | Y29: CC 初評
A30: SRC_OAI_026 | B30: API 價格事件 2 | C30: 07-30 Terra 2/12（-20%）、Luna 0.2/1.2（-80%） | F30: 文字 | G30: 價格事件（輸入／輸出 $/M） | H30: OpenAI | I30: 2026-07-30 | J30: openai.com 2026-07-30 GPT-5.6 降價公告；GPT-6 Sol/Luna 2026-09-22 發布（Techzine、MarkTechPost）；GPT-6 Astra 2026-09-03 | K30: 2 | L30: 利害關係方 | M30: 公開且具約束力的報價，誤報誘因低 | N30: 一手 | O30: Active | P30: — | Q30: Verified | R30: — | S30: tokenRevenue.api.priceEvents2026 | T30: P2 FY 平均牌價（2026）的月加權依據 | V30: =IF(AND($O30="Active",$C30="",$D30="",$E30="",$F30<>"文字"),1,0) -> 0 | W30: =IF(AND($O30="Active",OR($J30="",$J30="—")),1,0) -> 0 | X30: =IF(AND(ISNUMBER($C30),ISNUMBER($D30),ISNUMBER($E30)),IF(AND($D30<=$C30,$C30<=$E30),0,1),0) -> 0 | Y30: CC 初評
A31: SRC_OAI_027 | B31: API 價格事件 3 | C31: 08-22 Sol 促銷 4/20 | F31: 文字 | G31: 價格事件（輸入／輸出 $/M） | H31: OpenAI | I31: 2026-08-22 | J31: openai.com 2026-07-30 GPT-5.6 降價公告；GPT-6 Sol/Luna 2026-09-22 發布（Techzine、MarkTechPost）；GPT-6 Astra 2026-09-03 | K31: 2 | L31: 利害關係方 | M31: 公開且具約束力的報價，誤報誘因低 | N31: 一手 | O31: Active | P31: — | Q31: Verified | R31: — | S31: tokenRevenue.api.priceEvents2026 | T31: P2 FY 平均牌價（2026）的月加權依據 | V31: =IF(AND($O31="Active",$C31="",$D31="",$E31="",$F31<>"文字"),1,0) -> 0 | W31: =IF(AND($O31="Active",OR($J31="",$J31="—")),1,0) -> 0 | X31: =IF(AND(ISNUMBER($C31),ISNUMBER($D31),ISNUMBER($E31)),IF(AND($D31<=$C31,$C31<=$E31),0,1),0) -> 0 | Y31: CC 初評
A32: SRC_OAI_028 | B32: API 價格事件 4 | C32: 09-03 GPT-6 Astra 10/50（新旗艦，層級價格上升） | F32: 文字 | G32: 價格事件（輸入／輸出 $/M） | H32: OpenAI | I32: 2026-09-03 | J32: openai.com 2026-07-30 GPT-5.6 降價公告；GPT-6 Sol/Luna 2026-09-22 發布（Techzine、MarkTechPost）；GPT-6 Astra 2026-09-03 | K32: 2 | L32: 利害關係方 | M32: 公開且具約束力的報價，誤報誘因低 | N32: 一手 | O32: Active | P32: — | Q32: Verified | R32: — | S32: tokenRevenue.api.priceEvents2026 | T32: P2 FY 平均牌價（2026）的月加權依據 | V32: =IF(AND($O32="Active",$C32="",$D32="",$E32="",$F32<>"文字"),1,0) -> 0 | W32: =IF(AND($O32="Active",OR($J32="",$J32="—")),1,0) -> 0 | X32: =IF(AND(ISNUMBER($C32),ISNUMBER($D32),ISNUMBER($E32)),IF(AND($D32<=$C32,$C32<=$E32),0,1),0) -> 0 | Y32: CC 初評
A33: SRC_OAI_029 | B33: API 價格事件 5 | C33: 09-22 GPT-6 Sol 2/10、Luna 0.1/0.5 | F33: 文字 | G33: 價格事件（輸入／輸出 $/M） | H33: OpenAI | I33: 2026-09-22 | J33: openai.com 2026-07-30 GPT-5.6 降價公告；GPT-6 Sol/Luna 2026-09-22 發布（Techzine、MarkTechPost）；GPT-6 Astra 2026-09-03 | K33: 2 | L33: 利害關係方 | M33: 公開且具約束力的報價，誤報誘因低 | N33: 一手 | O33: Active | P33: — | Q33: Verified | R33: — | S33: tokenRevenue.api.priceEvents2026 | T33: P2 FY 平均牌價（2026）的月加權依據 | V33: =IF(AND($O33="Active",$C33="",$D33="",$E33="",$F33<>"文字"),1,0) -> 0 | W33: =IF(AND($O33="Active",OR($J33="",$J33="—")),1,0) -> 0 | X33: =IF(AND(ISNUMBER($C33),ISNUMBER($D33),ISNUMBER($E33)),IF(AND($D33<=$C33,$C33<=$E33),0,1),0) -> 0 | Y33: CC 初評
A34: SRC_OAI_030 | B34: 快取輸入價占輸入價比 | C34: 0.1 | F34: 比例 | G34: 定價頁：cached input＝輸入價 10% | H34: OpenAI | I34: 2026-09 | J34: 定價頁：cached input = 輸入價 10% | K34: 2 | L34: 利害關係方 | M34: 公開且具約束力的報價，誤報誘因低 | N34: 一手 | O34: Active | P34: — | Q34: Verified | R34: — | S34: tokenRevenue.api.cachedInputRatio | T34: P2 | V34: =IF(AND($O34="Active",$C34="",$D34="",$E34="",$F34<>"文字"),1,0) -> 0 | W34: =IF(AND($O34="Active",OR($J34="",$J34="—")),1,0) -> 0 | X34: =IF(AND(ISNUMBER($C34),ISNUMBER($D34),ISNUMBER($E34)),IF(AND($D34<=$C34,$C34<=$E34),0,1),0) -> 0 | Y34: CC 初評
A35: SRC_OAI_031 | B35: 訂閱牌價：Go | C35: 8 | F35: $/月 | G35: ChatGPT 定價頁；美國牌價 | H35: OpenAI | I35: 2026-09 | J35: ChatGPT 定價頁（多家 2026-09 核對）；Enterprise 為議價 | K35: 2 | L35: 利害關係方 | M35: 公開且具約束力的報價，誤報誘因低 | N35: 一手 | O35: Active | P35: — | Q35: Verified | R35: — | S35: tokenRevenue.subscription.listPriceSep2026 | T35: P2 ARPU 上限參照 | V35: =IF(AND($O35="Active",$C35="",$D35="",$E35="",$F35<>"文字"),1,0) -> 0 | W35: =IF(AND($O35="Active",OR($J35="",$J35="—")),1,0) -> 0 | X35: =IF(AND(ISNUMBER($C35),ISNUMBER($D35),ISNUMBER($E35)),IF(AND($D35<=$C35,$C35<=$E35),0,1),0) -> 0 | Y35: CC 初評
A36: SRC_OAI_032 | B36: 訂閱牌價：Plus | C36: 20 | F36: $/月 | G36: ChatGPT 定價頁；美國牌價 | H36: OpenAI | I36: 2026-09 | J36: ChatGPT 定價頁（多家 2026-09 核對）；Enterprise 為議價 | K36: 2 | L36: 利害關係方 | M36: 公開且具約束力的報價，誤報誘因低 | N36: 一手 | O36: Active | P36: — | Q36: Verified | R36: — | S36: tokenRevenue.subscription.listPriceSep2026 | T36: P2 | V36: =IF(AND($O36="Active",$C36="",$D36="",$E36="",$F36<>"文字"),1,0) -> 0 | W36: =IF(AND($O36="Active",OR($J36="",$J36="—")),1,0) -> 0 | X36: =IF(AND(ISNUMBER($C36),ISNUMBER($D36),ISNUMBER($E36)),IF(AND($D36<=$C36,$C36<=$E36),0,1),0) -> 0 | Y36: CC 初評
A37: SRC_OAI_033 | B37: 訂閱牌價：Pro（低檔） | C37: 100 | F37: $/月 | G37: 2026 起 Pro 兩檔之一 | H37: OpenAI | I37: 2026-09 | J37: ChatGPT 定價頁（多家 2026-09 核對）；Enterprise 為議價 | K37: 2 | L37: 利害關係方 | M37: 公開且具約束力的報價，誤報誘因低 | N37: 一手 | O37: Active | P37: — | Q37: Verified | R37: — | S37: tokenRevenue.subscription.listPriceSep2026 | T37: P2 | V37: =IF(AND($O37="Active",$C37="",$D37="",$E37="",$F37<>"文字"),1,0) -> 0 | W37: =IF(AND($O37="Active",OR($J37="",$J37="—")),1,0) -> 0 | X37: =IF(AND(ISNUMBER($C37),ISNUMBER($D37),ISNUMBER($E37)),IF(AND($D37<=$C37,$C37<=$E37),0,1),0) -> 0 | Y37: CC 初評
A38: SRC_OAI_034 | B38: 訂閱牌價：Pro（高檔） | C38: 200 | F38: $/月 | G38: 2026 起 Pro 兩檔之一 | H38: OpenAI | I38: 2026-09 | J38: ChatGPT 定價頁（多家 2026-09 核對）；Enterprise 為議價 | K38: 2 | L38: 利害關係方 | M38: 公開且具約束力的報價，誤報誘因低 | N38: 一手 | O38: Active | P38: — | Q38: Verified | R38: — | S38: tokenRevenue.subscription.listPriceSep2026 | T38: P2 | V38: =IF(AND($O38="Active",$C38="",$D38="",$E38="",$F38<>"文字"),1,0) -> 0 | W38: =IF(AND($O38="Active",OR($J38="",$J38="—")),1,0) -> 0 | X38: =IF(AND(ISNUMBER($C38),ISNUMBER($D38),ISNUMBER($E38)),IF(AND($D38<=$C38,$C38<=$E38),0,1),0) -> 0 | Y38: CC 初評
A39: SRC_OAI_035 | B39: 訂閱牌價：Business 每席 | D39: 20 | E39: 25 | F39: $/席/月 | G39: Business 席位區間；Enterprise 為議價 | H39: OpenAI | I39: 2026-09 | J39: ChatGPT 定價頁（多家 2026-09 核對）；Enterprise 為議價 | K39: 2 | L39: 利害關係方 | M39: 公開且具約束力的報價，誤報誘因低 | N39: 一手 | O39: Active | P39: — | Q39: Verified | R39: — | S39: tokenRevenue.subscription.listPriceSep2026 | T39: P2 | V39: =IF(AND($O39="Active",$C39="",$D39="",$E39="",$F39<>"文字"),1,0) -> 0 | W39: =IF(AND($O39="Active",OR($J39="",$J39="—")),1,0) -> 0 | X39: =IF(AND(ISNUMBER($C39),ISNUMBER($D39),ISNUMBER($E39)),IF(AND($D39<=$C39,$C39<=$E39),0,1),0) -> 0 | Y39: CC 初評
A40: SRC_OAI_036 | B40: 公司 2026 計畫：Go 用戶數 | C40: 112 | F40: M | G40: 年初內部預測 | H40: OpenAI | I40: 2026-04-28 | J40: The Information 2026-04-28（年初內部預測） | K40: 3 | L40: 利害關係方 | M40: 管理層、內部文件或外流數據：誘因為募資與議價，傾向呈現成長與算力需求 | N40: 二手 | O40: Active | P40: — | Q40: Interested-party | R40: 待查核-報導 | S40: tokenRevenue.subscription.migration.planGo2026 | T40: P2 T4 遷移幅度 | V40: =IF(AND($O40="Active",$C40="",$D40="",$E40="",$F40<>"文字"),1,0) -> 0 | W40: =IF(AND($O40="Active",OR($J40="",$J40="—")),1,0) -> 0 | X40: =IF(AND(ISNUMBER($C40),ISNUMBER($D40),ISNUMBER($E40)),IF(AND($D40<=$C40,$C40<=$E40),0,1),0) -> 0 | Y40: CC 初評
A41: SRC_OAI_037 | B41: 公司 2026 計畫：Plus 用戶數 | C41: 9 | F41: M | G41: 年初內部預測 | H41: OpenAI | I41: 2026-04-28 | J41: The Information 2026-04-28（年初內部預測）（追溯自「同上」鏈：本列←『公司 2026 計畫：Go 用戶數』；原文：同上） | K41: 3 | L41: 利害關係方 | M41: 管理層、內部文件或外流數據：誘因為募資與議價，傾向呈現成長與算力需求 | N41: 二手 | O41: Active | P41: — | Q41: Interested-party | R41: 待查核-報導 | S41: tokenRevenue.subscription.migration.planPlus2026 | T41: P2 T4 遷移幅度 | V41: =IF(AND($O41="Active",$C41="",$D41="",$E41="",$F41<>"文字"),1,0) -> 0 | W41: =IF(AND($O41="Active",OR($J41="",$J41="—")),1,0) -> 0 | X41: =IF(AND(ISNUMBER($C41),ISNUMBER($D41),ISNUMBER($E41)),IF(AND($D41<=$C41,$C41<=$E41),0,1),0) -> 0 | Y41: CC 初評
A42: SRC_OAI_038 | B42: 內部廣告營收目標：2026 | C42: 2.5 | F42: $B | G42: 投資人簡報；假設 2030 年 2.75B 週用戶；僅對照 | H42: OpenAI | I42: 2026-04-09 | J42: Axios 2026-04-09（投資人簡報；假設 2030 年 2.75B 週用戶），僅對照 | K42: 2 | L42: 利害關係方 | M42: 管理層、內部文件或外流數據：誘因為募資與議價，傾向呈現成長與算力需求 | N42: 二手 | O42: Active | P42: — | Q42: Interested-party | R42: — | S42: tokenRevenue.other.ads.comparisonInternalTarget | T42: P2 對照（廣告） | V42: =IF(AND($O42="Active",$C42="",$D42="",$E42="",$F42<>"文字"),1,0) -> 0 | W42: =IF(AND($O42="Active",OR($J42="",$J42="—")),1,0) -> 0 | X42: =IF(AND(ISNUMBER($C42),ISNUMBER($D42),ISNUMBER($E42)),IF(AND($D42<=$C42,$C42<=$E42),0,1),0) -> 0 | Y42: CC 初評
A43: SRC_OAI_039 | B43: 內部廣告營收目標：2027 | C43: 11 | F43: $B | G43: 投資人簡報；假設 2030 年 2.75B 週用戶；僅對照 | H43: OpenAI | I43: 2026-04-09 | J43: Axios 2026-04-09（投資人簡報；假設 2030 年 2.75B 週用戶），僅對照 | K43: 2 | L43: 利害關係方 | M43: 管理層、內部文件或外流數據：誘因為募資與議價，傾向呈現成長與算力需求 | N43: 二手 | O43: Active | P43: — | Q43: Interested-party | R43: — | S43: tokenRevenue.other.ads.comparisonInternalTarget | T43: P2 對照（廣告） | V43: =IF(AND($O43="Active",$C43="",$D43="",$E43="",$F43<>"文字"),1,0) -> 0 | W43: =IF(AND($O43="Active",OR($J43="",$J43="—")),1,0) -> 0 | X43: =IF(AND(ISNUMBER($C43),ISNUMBER($D43),ISNUMBER($E43)),IF(AND($D43<=$C43,$C43<=$E43),0,1),0) -> 0 | Y43: CC 初評
A44: SRC_OAI_040 | B44: 內部廣告營收目標：2028 | C44: 25 | F44: $B | G44: 投資人簡報；假設 2030 年 2.75B 週用戶；僅對照 | H44: OpenAI | I44: 2026-04-09 | J44: Axios 2026-04-09（投資人簡報；假設 2030 年 2.75B 週用戶），僅對照 | K44: 2 | L44: 利害關係方 | M44: 管理層、內部文件或外流數據：誘因為募資與議價，傾向呈現成長與算力需求 | N44: 二手 | O44: Active | P44: — | Q44: Interested-party | R44: — | S44: tokenRevenue.other.ads.comparisonInternalTarget | T44: P2 對照（廣告） | V44: =IF(AND($O44="Active",$C44="",$D44="",$E44="",$F44<>"文字"),1,0) -> 0 | W44: =IF(AND($O44="Active",OR($J44="",$J44="—")),1,0) -> 0 | X44: =IF(AND(ISNUMBER($C44),ISNUMBER($D44),ISNUMBER($E44)),IF(AND($D44<=$C44,$C44<=$E44),0,1),0) -> 0 | Y44: CC 初評
A45: SRC_OAI_041 | B45: 內部廣告營收目標：2029 | C45: 53 | F45: $B | G45: 投資人簡報；假設 2030 年 2.75B 週用戶；僅對照 | H45: OpenAI | I45: 2026-04-09 | J45: Axios 2026-04-09（投資人簡報；假設 2030 年 2.75B 週用戶），僅對照 | K45: 2 | L45: 利害關係方 | M45: 管理層、內部文件或外流數據：誘因為募資與議價，傾向呈現成長與算力需求 | N45: 二手 | O45: Active | P45: — | Q45: Interested-party | R45: — | S45: tokenRevenue.other.ads.comparisonInternalTarget | T45: P2 對照（廣告） | V45: =IF(AND($O45="Active",$C45="",$D45="",$E45="",$F45<>"文字"),1,0) -> 0 | W45: =IF(AND($O45="Active",OR($J45="",$J45="—")),1,0) -> 0 | X45: =IF(AND(ISNUMBER($C45),ISNUMBER($D45),ISNUMBER($E45)),IF(AND($D45<=$C45,$C45<=$E45),0,1),0) -> 0 | Y45: CC 初評
A46: SRC_OAI_042 | B46: 內部廣告營收目標：2030 | C46: 100 | F46: $B | G46: 投資人簡報；假設 2030 年 2.75B 週用戶；僅對照 | H46: OpenAI | I46: 2026-04-09 | J46: Axios 2026-04-09（投資人簡報；假設 2030 年 2.75B 週用戶），僅對照 | K46: 2 | L46: 利害關係方 | M46: 管理層、內部文件或外流數據：誘因為募資與議價，傾向呈現成長與算力需求 | N46: 二手 | O46: Active | P46: — | Q46: Interested-party | R46: — | S46: tokenRevenue.other.ads.comparisonInternalTarget | T46: P2 對照（廣告） | V46: =IF(AND($O46="Active",$C46="",$D46="",$E46="",$F46<>"文字"),1,0) -> 0 | W46: =IF(AND($O46="Active",OR($J46="",$J46="—")),1,0) -> 0 | X46: =IF(AND(ISNUMBER($C46),ISNUMBER($D46),ISNUMBER($E46)),IF(AND($D46<=$C46,$C46<=$E46),0,1),0) -> 0 | Y46: CC 初評
A47: SRC_OAI_043 | B47: 管理層營收目標：2026 | C47: 36 | F47: $B | G47: 7 月投資人簡報；2027–29 未揭露 | H47: OpenAI | I47: 2026-09-18 | J47: FT 2026-09-18（7 月投資人簡報）；2027-29 未揭露 | K47: 2 | L47: 利害關係方 | M47: 管理層、內部文件或外流數據：誘因為募資與議價，傾向呈現成長與算力需求 | N47: 二手（含一手公告轉載） | O47: Active | P47: — | Q47: Interested-party | R47: — | S47: tokenRevenue.comparison.deckJul2026 | T47: P5 反向模式 | V47: =IF(AND($O47="Active",$C47="",$D47="",$E47="",$F47<>"文字"),1,0) -> 0 | W47: =IF(AND($O47="Active",OR($J47="",$J47="—")),1,0) -> 0 | X47: =IF(AND(ISNUMBER($C47),ISNUMBER($D47),ISNUMBER($E47)),IF(AND($D47<=$C47,$C47<=$E47),0,1),0) -> 0 | Y47: CC 初評
A48: SRC_OAI_044 | B48: 管理層營收目標：2030 | C48: 350 | F48: $B | G48: 7 月投資人簡報 | H48: OpenAI | I48: 2026-09-18 | J48: FT 2026-09-18（7 月投資人簡報）；2027-29 未揭露 | K48: 2 | L48: 利害關係方 | M48: 管理層、內部文件或外流數據：誘因為募資與議價，傾向呈現成長與算力需求 | N48: 二手（含一手公告轉載） | O48: Active | P48: — | Q48: Interested-party | R48: — | S48: tokenRevenue.comparison.deckJul2026 | T48: P5 反向模式 | V48: =IF(AND($O48="Active",$C48="",$D48="",$E48="",$F48<>"文字"),1,0) -> 0 | W48: =IF(AND($O48="Active",OR($J48="",$J48="—")),1,0) -> 0 | X48: =IF(AND(ISNUMBER($C48),ISNUMBER($D48),ISNUMBER($E48)),IF(AND($D48<=$C48,$C48<=$E48),0,1),0) -> 0 | Y48: CC 初評
A49: SRC_OAI_045 | B49: 管理層營收目標：2026–2030 累計 | C49: 840 | F49: $B | G49: 7 月投資人簡報 | H49: OpenAI | I49: 2026-09-18 | J49: FT 2026-09-18（7 月投資人簡報）；2027-29 未揭露 | K49: 2 | L49: 利害關係方 | M49: 管理層、內部文件或外流數據：誘因為募資與議價，傾向呈現成長與算力需求 | N49: 二手（含一手公告轉載） | O49: Active | P49: — | Q49: Interested-party | R49: — | S49: tokenRevenue.comparison.deckJul2026 | T49: P5 反向模式 | V49: =IF(AND($O49="Active",$C49="",$D49="",$E49="",$F49<>"文字"),1,0) -> 0 | W49: =IF(AND($O49="Active",OR($J49="",$J49="—")),1,0) -> 0 | X49: =IF(AND(ISNUMBER($C49),ISNUMBER($D49),ISNUMBER($E49)),IF(AND($D49<=$C49,$C49<=$E49),0,1),0) -> 0 | Y49: CC 初評
A50: SRC_OAI_046 | B50: 2030 週用戶數計畫 | C50: 2750 | F50: M | G50: 廣告預測之用戶假設 | H50: OpenAI | I50: 2026-04-09 | J50: Axios 2026-04-09 廣告預測之用戶假設 | K50: 2 | L50: 利害關係方 | M50: 管理層、內部文件或外流數據：誘因為募資與議價，傾向呈現成長與算力需求 | N50: 二手 | O50: Active | P50: — | Q50: Interested-party | R50: — | S50: tokenRevenue.comparison.weeklyUsers2030Plan | T50: P2 對照（廣告） | V50: =IF(AND($O50="Active",$C50="",$D50="",$E50="",$F50<>"文字"),1,0) -> 0 | W50: =IF(AND($O50="Active",OR($J50="",$J50="—")),1,0) -> 0 | X50: =IF(AND(ISNUMBER($C50),ISNUMBER($D50),ISNUMBER($E50)),IF(AND($D50<=$C50,$C50<=$E50),0,1),0) -> 0 | Y50: CC 初評
A51: SRC_OAI_047 | B51: 推論成本合計：2025 | C51: 8.4 | F51: $B | G51: 2025 推論支出（含付費與非付費用戶） | H51: OpenAI | I51: 2026-02 | J51: The Information 2026-02（投資人說明）；T1(a) | K51: 3 | L51: 利害關係方 | M51: 管理層、內部文件或外流數據：誘因為募資與議價，傾向呈現成長與算力需求 | N51: 二手 | O51: Active | P51: — | Q51: Interested-party | R51: 待查核-報導 | S51: tokenRevenue.inferenceCost.calibration2025.inferenceTotal | T51: P3 V2 η 的支出換算分子 | U51: T1(a) | V51: =IF(AND($O51="Active",$C51="",$D51="",$E51="",$F51<>"文字"),1,0) -> 0 | W51: =IF(AND($O51="Active",OR($J51="",$J51="—")),1,0) -> 0 | X51: =IF(AND(ISNUMBER($C51),ISNUMBER($D51),ISNUMBER($E51)),IF(AND($D51<=$C51,$C51<=$E51),0,1),0) -> 0 | Y51: CC 初評
A52: SRC_OAI_048 | B52: 推論成本：2025 非付費用戶 | C52: 3.9 | F52: $B | G52: 非付費用戶推論支出 | H52: OpenAI | I52: 2026-02 | J52: The Information 2026-02（投資人說明）；T1(a)（追溯自「同上」鏈：本列←『推論成本合計：2025』；原文：同上：非付費用戶約 $3.9B） | K52: 3 | L52: 利害關係方 | M52: 管理層、內部文件或外流數據：誘因為募資與議價，傾向呈現成長與算力需求 | N52: 二手 | O52: Active | P52: — | Q52: Interested-party | R52: 待查核-報導 | S52: tokenRevenue.inferenceCost.calibration2025.freeUsers | T52: P4 對照 | V52: =IF(AND($O52="Active",$C52="",$D52="",$E52="",$F52<>"文字"),1,0) -> 0 | W52: =IF(AND($O52="Active",OR($J52="",$J52="—")),1,0) -> 0 | X52: =IF(AND(ISNUMBER($C52),ISNUMBER($D52),ISNUMBER($E52)),IF(AND($D52<=$C52,$C52<=$E52),0,1),0) -> 0 | Y52: CC 初評
A53: SRC_OAI_049 | B53: 推論成本：2025 付費用戶 | C53: 4.5 | F53: $B | G53: 付費用戶推論支出 | H53: OpenAI | I53: 2026-02 | J53: The Information 2026-02（投資人說明）；T1(a)（追溯自「同上」鏈：本列←『推論成本：2025 非付費用戶』←『推論成本合計：2025』；原文：同上：付費用戶 $4.5B） | K53: 3 | L53: 利害關係方 | M53: 管理層、內部文件或外流數據：誘因為募資與議價，傾向呈現成長與算力需求 | N53: 二手 | O53: Active | P53: — | Q53: Interested-party | R53: 待查核-報導 | S53: tokenRevenue.inferenceCost.calibration2025.paidUsers | T53: P4 對照 | V53: =IF(AND($O53="Active",$C53="",$D53="",$E53="",$F53<>"文字"),1,0) -> 0 | W53: =IF(AND($O53="Active",OR($J53="",$J53="—")),1,0) -> 0 | X53: =IF(AND(ISNUMBER($C53),ISNUMBER($D53),ISNUMBER($E53)),IF(AND($D53<=$C53,$C53<=$E53),0,1),0) -> 0 | Y53: CC 初評
A54: SRC_OAI_050 | B54: 計畫推論成本：2026 | C54: 14.1 | F54: $B | G54: OpenAI 2026 預測；付費占比見下列 | H54: OpenAI | I54: 2026-02 | J54: The Information 2026-02：OpenAI 2026 預測 | K54: 2 | L54: 利害關係方 | M54: 管理層、內部文件或外流數據：誘因為募資與議價，傾向呈現成長與算力需求 | N54: 二手 | O54: Active | P54: — | Q54: Interested-party | R54: — | S54: tokenRevenue.inferenceCost.checks2026.inference | T54: P3 檢查 | U54: 含付費占比 0.66（v0.5 同節點） | V54: =IF(AND($O54="Active",$C54="",$D54="",$E54="",$F54<>"文字"),1,0) -> 0 | W54: =IF(AND($O54="Active",OR($J54="",$J54="—")),1,0) -> 0 | X54: =IF(AND(ISNUMBER($C54),ISNUMBER($D54),ISNUMBER($E54)),IF(AND($D54<=$C54,$C54<=$E54),0,1),0) -> 0 | Y54: CC 初評
A55: SRC_OAI_051 | B55: 計畫推論成本：2030 | C55: 85 | F55: $B | G55: OpenAI 2030 預測 | H55: OpenAI | I55: 2026-02 | J55: The Information 2026-02：OpenAI 2026 預測（追溯自「同上」鏈：本列←『計畫推論成本：2026』；原文：同上） | K55: 2 | L55: 利害關係方 | M55: 管理層、內部文件或外流數據：誘因為募資與議價，傾向呈現成長與算力需求 | N55: 二手 | O55: Active | P55: — | Q55: Interested-party | R55: — | S55: tokenRevenue.inferenceCost.checks2026.inference2030 | T55: P3 檢查 | U55: 含付費占比 0.94、毛利率目標 0.67（v0.5 同節點） | V55: =IF(AND($O55="Active",$C55="",$D55="",$E55="",$F55<>"文字"),1,0) -> 0 | W55: =IF(AND($O55="Active",OR($J55="",$J55="—")),1,0) -> 0 | X55: =IF(AND(ISNUMBER($C55),ISNUMBER($D55),ISNUMBER($E55)),IF(AND($D55<=$C55,$C55<=$E55),0,1),0) -> 0 | Y55: CC 初評
A56: SRC_OAI_054 | B56: 管理層目標：2026–2030 累計自由現金流 | C56: -278 | F56: $B | G56: Jul-2026 簡報 | H56: OpenAI | I56: 2026-09-18 | J56: FT 2026-09-18 | K56: 2 | L56: 利害關係方 | M56: 管理層、內部文件或外流數據：誘因為募資與議價，傾向呈現成長與算力需求 | N56: 二手 | O56: Active | P56: — | Q56: Interested-party | R56: — | S56: reverse.targetFCFcum2026_2030 | T56: P5 反向模式 | V56: =IF(AND($O56="Active",$C56="",$D56="",$E56="",$F56<>"文字"),1,0) -> 0 | W56: =IF(AND($O56="Active",OR($J56="",$J56="—")),1,0) -> 0 | X56: =IF(AND(ISNUMBER($C56),ISNUMBER($D56),ISNUMBER($E56)),IF(AND($D56<=$C56,$C56<=$E56),0,1),0) -> 0 | Y56: CC 初評
A57: SRC_OAI_055 | B57: 計畫算力支出：2026–2030 累計 | C57: 856 | D57: 600 | E57: 856 | F57: $B | G57: FT 2026-09-18（7 月簡報）$856B；Reuters 2026-02 約 $600B 為下限 | H57: OpenAI | I57: 2026-09-18 | J57: FT 2026-09-18（7 月簡報）$856B，與 R1 反向錨點同一版本；Reuters 2026-02 約 $600B 為下限 | K57: 3 | L57: 利害關係方 | M57: 管理層、內部文件或外流數據：誘因為募資與議價，傾向呈現成長與算力需求 | N57: 二手 | O57: Active | P57: — | Q57: Interested-party | R57: 待查核-報導 | S57: training.planCompute2026_2030 | T57: P3 檢查（計畫算力）；P5 反向目標 | U57: 併入 reverse.targetComputeCum2026_2030 與 spending.anchors.computeCum2026_2030_FT（同值同源） | V57: =IF(AND($O57="Active",$C57="",$D57="",$E57="",$F57<>"文字"),1,0) -> 0 | W57: =IF(AND($O57="Active",OR($J57="",$J57="—")),1,0) -> 0 | X57: =IF(AND(ISNUMBER($C57),ISNUMBER($D57),ISNUMBER($E57)),IF(AND($D57<=$C57,$C57<=$E57),0,1),0) -> 0 | Y57: CC 初評
A58: SRC_OAI_056 | B58: 管理層營收目標（舊版）：2030（2026-02 版） | C58: 280 | F58: $B | G58: 2026-02 版本的 2030 營收目標；只對照 | H58: OpenAI | I58: 2026-02 | J58: The Information 2026-02；只對照 | K58: 2 | L58: 利害關係方 | M58: 管理層、內部文件或外流數據：誘因為募資與議價，傾向呈現成長與算力需求 | N58: 二手 | O58: Active | P58: — | Q58: Interested-party | R58: — | S58: reverse.priorVintages | T58: P5 對照 | V58: =IF(AND($O58="Active",$C58="",$D58="",$E58="",$F58<>"文字"),1,0) -> 0 | W58: =IF(AND($O58="Active",OR($J58="",$J58="—")),1,0) -> 0 | X58: =IF(AND(ISNUMBER($C58),ISNUMBER($D58),ISNUMBER($E58)),IF(AND($D58<=$C58,$C58<=$E58),0,1),0) -> 0 | Y58: CC 初評
A59: SRC_OAI_057 | B59: 合約總額：Microsoft Azure（OpenAI 增購） | C59: 250 | F59: $B | G59: 2025-10 公告增購 Azure 承諾 | H59: Microsoft | I59: 2025-10 | J59: OpenAI／Microsoft 2025-10 公告增購 $250B Azure（v0.5：總額 [Verified]） | K59: 2 | L59: 利害關係方 | M59: 合約雙方公告；OpenAI 有募資與算力規模訊號誘因，供應商有營收與股價訊號誘因；金額為承諾總額，非實付 | N59: 一手 | O59: Active | P59: — | Q59: Verified | R59: — | S59: spending.contracts.microsoftAzure | T59: P3 供給；P4 成本 | V59: =IF(AND($O59="Active",$C59="",$D59="",$E59="",$F59<>"文字"),1,0) -> 0 | W59: =IF(AND($O59="Active",OR($J59="",$J59="—")),1,0) -> 0 | X59: =IF(AND(ISNUMBER($C59),ISNUMBER($D59),ISNUMBER($E59)),IF(AND($D59<=$C59,$C59<=$E59),0,1),0) -> 0 | Y59: CC 初評
A60: SRC_OAI_058 | B60: 合約總額：Oracle | C60: 300 | F60: $B | G60: 5 年、2027 起、約 4.5GW | H60: Oracle | I60: 2025-09 | J60: WSJ 2025-09；Oracle 公告 5 年、2027 起、約 4.5GW | K60: 2 | L60: 利害關係方 | M60: 交易對手公告或轉述：誘因為宣傳合約規模與客戶關係 | N60: 二手（含一手公告轉載） | O60: Active | P60: — | Q60: Interested-party | R60: — | S60: spending.contracts.oracle | T60: P3 供給；P3 V2 合約價 | V60: =IF(AND($O60="Active",$C60="",$D60="",$E60="",$F60<>"文字"),1,0) -> 0 | W60: =IF(AND($O60="Active",OR($J60="",$J60="—")),1,0) -> 0 | X60: =IF(AND(ISNUMBER($C60),ISNUMBER($D60),ISNUMBER($E60)),IF(AND($D60<=$C60,$C60<=$E60),0,1),0) -> 0 | Y60: CC 初評
A61: SRC_OAI_059 | B61: 合約期間起：Oracle | C61: 2027 | F61: 年 | G61: Oracle 公告 | H61: Oracle | I61: 2025-09 | J61: WSJ 2025-09；Oracle 公告 5 年、2027 起、約 4.5GW | K61: 2 | L61: 利害關係方 | M61: 交易對手公告或轉述：誘因為宣傳合約規模與客戶關係 | N61: 二手（含一手公告轉載） | O61: Active | P61: — | Q61: Interested-party | R61: — | S61: spending.contracts.oracle | T61: P3 | V61: =IF(AND($O61="Active",$C61="",$D61="",$E61="",$F61<>"文字"),1,0) -> 0 | W61: =IF(AND($O61="Active",OR($J61="",$J61="—")),1,0) -> 0 | X61: =IF(AND(ISNUMBER($C61),ISNUMBER($D61),ISNUMBER($E61)),IF(AND($D61<=$C61,$C61<=$E61),0,1),0) -> 0 | Y61: CC 初評
A62: SRC_OAI_060 | B62: 合約期間迄：Oracle | C62: 2031 | F62: 年 | G62: 5 年（2027–2031） | H62: Oracle | I62: 2025-09 | J62: WSJ 2025-09；Oracle 公告 5 年、2027 起、約 4.5GW | K62: 2 | L62: 利害關係方 | M62: 交易對手公告或轉述：誘因為宣傳合約規模與客戶關係 | N62: 二手（含一手公告轉載） | O62: Active | P62: — | Q62: Interested-party | R62: — | S62: spending.contracts.oracle | T62: P3 | V62: =IF(AND($O62="Active",$C62="",$D62="",$E62="",$F62<>"文字"),1,0) -> 0 | W62: =IF(AND($O62="Active",OR($J62="",$J62="—")),1,0) -> 0 | X62: =IF(AND(ISNUMBER($C62),ISNUMBER($D62),ISNUMBER($E62)),IF(AND($D62<=$C62,$C62<=$E62),0,1),0) -> 0 | Y62: CC 初評
A63: SRC_OAI_061 | B63: 合約容量：Oracle | C63: 4.5 | F63: GW | G63: 約 4.5GW；電力口徑未明 | H63: Oracle | I63: 2025-09 | J63: WSJ 2025-09；Oracle 公告 5 年、2027 起、約 4.5GW | K63: 2 | L63: 利害關係方 | M63: 交易對手公告或轉述：誘因為宣傳合約規模與客戶關係 | N63: 二手（含一手公告轉載） | O63: Active | P63: — | Q63: Interested-party | R63: — | S63: spending.contracts.oracle | T63: P3 V2 合約價 | V63: =IF(AND($O63="Active",$C63="",$D63="",$E63="",$F63<>"文字"),1,0) -> 0 | W63: =IF(AND($O63="Active",OR($J63="",$J63="—")),1,0) -> 0 | X63: =IF(AND(ISNUMBER($C63),ISNUMBER($D63),ISNUMBER($E63)),IF(AND($D63<=$C63,$C63<=$E63),0,1),0) -> 0 | Y63: CC 初評
A64: SRC_OAI_062 | B64: 合約總額：AWS（Nvidia 晶片） | C64: 38 | F64: $B | G64: AWS／OpenAI 公告；7 年 | H64: AWS | I64: 2025-11-03 | J64: AWS/OpenAI 2025-11-03，7 年 | K64: 2 | L64: 利害關係方 | M64: 合約雙方公告；OpenAI 有募資與算力規模訊號誘因，供應商有營收與股價訊號誘因；金額為承諾總額，非實付 | N64: 一手 | O64: Active | P64: — | Q64: Verified | R64: — | S64: spending.contracts.awsNvidia | T64: P3；P4 | V64: =IF(AND($O64="Active",$C64="",$D64="",$E64="",$F64<>"文字"),1,0) -> 0 | W64: =IF(AND($O64="Active",OR($J64="",$J64="—")),1,0) -> 0 | X64: =IF(AND(ISNUMBER($C64),ISNUMBER($D64),ISNUMBER($E64)),IF(AND($D64<=$C64,$C64<=$E64),0,1),0) -> 0 | Y64: CC 初評
A65: SRC_OAI_063 | B65: 合約期間起：AWS（Nvidia 晶片） | C65: 2025 | F65: 年 | G65: 同上 | H65: AWS | I65: 2025-11-03 | J65: AWS/OpenAI 2025-11-03，7 年 | K65: 2 | L65: 利害關係方 | M65: 合約雙方公告；OpenAI 有募資與算力規模訊號誘因，供應商有營收與股價訊號誘因；金額為承諾總額，非實付 | N65: 一手 | O65: Active | P65: — | Q65: Verified | R65: — | S65: spending.contracts.awsNvidia | T65: P3 | V65: =IF(AND($O65="Active",$C65="",$D65="",$E65="",$F65<>"文字"),1,0) -> 0 | W65: =IF(AND($O65="Active",OR($J65="",$J65="—")),1,0) -> 0 | X65: =IF(AND(ISNUMBER($C65),ISNUMBER($D65),ISNUMBER($E65)),IF(AND($D65<=$C65,$C65<=$E65),0,1),0) -> 0 | Y65: CC 初評
A66: SRC_OAI_064 | B66: 合約期間迄：AWS（Nvidia 晶片） | C66: 2031 | F66: 年 | G66: 7 年 | H66: AWS | I66: 2025-11-03 | J66: AWS/OpenAI 2025-11-03，7 年 | K66: 2 | L66: 利害關係方 | M66: 合約雙方公告；OpenAI 有募資與算力規模訊號誘因，供應商有營收與股價訊號誘因；金額為承諾總額，非實付 | N66: 一手 | O66: Active | P66: — | Q66: Verified | R66: — | S66: spending.contracts.awsNvidia | T66: P3 | V66: =IF(AND($O66="Active",$C66="",$D66="",$E66="",$F66<>"文字"),1,0) -> 0 | W66: =IF(AND($O66="Active",OR($J66="",$J66="—")),1,0) -> 0 | X66: =IF(AND(ISNUMBER($C66),ISNUMBER($D66),ISNUMBER($E66)),IF(AND($D66<=$C66,$C66<=$E66),0,1),0) -> 0 | Y66: CC 初評
A67: SRC_OAI_065 | B67: 合約總額：AWS（Trainium） | C67: 100 | F67: $B | G67: AWS 追加；8 年 | H67: AWS | I67: 2026-02 | J67: 2026-02 融資公告：AWS 追加 $100B／8 年、2GW Trainium | K67: 2 | L67: 利害關係方 | M67: 合約雙方公告；OpenAI 有募資與算力規模訊號誘因，供應商有營收與股價訊號誘因；金額為承諾總額，非實付 | N67: 一手 | O67: Active | P67: — | Q67: Verified | R67: — | S67: spending.contracts.awsTrainium | T67: P3；P4 | V67: =IF(AND($O67="Active",$C67="",$D67="",$E67="",$F67<>"文字"),1,0) -> 0 | W67: =IF(AND($O67="Active",OR($J67="",$J67="—")),1,0) -> 0 | X67: =IF(AND(ISNUMBER($C67),ISNUMBER($D67),ISNUMBER($E67)),IF(AND($D67<=$C67,$C67<=$E67),0,1),0) -> 0 | Y67: CC 初評
A68: SRC_OAI_066 | B68: 合約期間起：AWS（Trainium） | C68: 2026 | F68: 年 | G68: 同上 | H68: AWS | I68: 2026-02 | J68: 2026-02 融資公告：AWS 追加 $100B／8 年、2GW Trainium | K68: 2 | L68: 利害關係方 | M68: 合約雙方公告；OpenAI 有募資與算力規模訊號誘因，供應商有營收與股價訊號誘因；金額為承諾總額，非實付 | N68: 一手 | O68: Active | P68: — | Q68: Verified | R68: — | S68: spending.contracts.awsTrainium | T68: P3 | V68: =IF(AND($O68="Active",$C68="",$D68="",$E68="",$F68<>"文字"),1,0) -> 0 | W68: =IF(AND($O68="Active",OR($J68="",$J68="—")),1,0) -> 0 | X68: =IF(AND(ISNUMBER($C68),ISNUMBER($D68),ISNUMBER($E68)),IF(AND($D68<=$C68,$C68<=$E68),0,1),0) -> 0 | Y68: CC 初評
A69: SRC_OAI_067 | B69: 合約期間迄：AWS（Trainium） | C69: 2033 | F69: 年 | G69: 8 年 | H69: AWS | I69: 2026-02 | J69: 2026-02 融資公告：AWS 追加 $100B／8 年、2GW Trainium | K69: 2 | L69: 利害關係方 | M69: 合約雙方公告；OpenAI 有募資與算力規模訊號誘因，供應商有營收與股價訊號誘因；金額為承諾總額，非實付 | N69: 一手 | O69: Active | P69: — | Q69: Verified | R69: — | S69: spending.contracts.awsTrainium | T69: P3 | V69: =IF(AND($O69="Active",$C69="",$D69="",$E69="",$F69<>"文字"),1,0) -> 0 | W69: =IF(AND($O69="Active",OR($J69="",$J69="—")),1,0) -> 0 | X69: =IF(AND(ISNUMBER($C69),ISNUMBER($D69),ISNUMBER($E69)),IF(AND($D69<=$C69,$C69<=$E69),0,1),0) -> 0 | Y69: CC 初評
A70: SRC_OAI_068 | B70: 合約容量：AWS（Trainium） | C70: 2 | F70: GW | G70: 2026-02 公告 2GW Trainium | H70: AWS | I70: 2026-02 | J70: 2026-02 融資公告：AWS 追加 $100B／8 年、2GW Trainium | K70: 2 | L70: 利害關係方 | M70: 合約雙方公告；OpenAI 有募資與算力規模訊號誘因，供應商有營收與股價訊號誘因；金額為承諾總額，非實付 | N70: 一手 | O70: Active | P70: — | Q70: Verified | R70: — | S70: spending.contracts.awsTrainium | T70: P3 供給 | U70: 揭露口徑衝突：2026-02 公告 2GW Trainium；WSJ 2026-07 另載 3GW 推論＋2GW 訓練（VR）。取 2GW，區間 2–5 | V70: =IF(AND($O70="Active",$C70="",$D70="",$E70="",$F70<>"文字"),1,0) -> 0 | W70: =IF(AND($O70="Active",OR($J70="",$J70="—")),1,0) -> 0 | X70: =IF(AND(ISNUMBER($C70),ISNUMBER($D70),ISNUMBER($E70)),IF(AND($D70<=$C70,$C70<=$E70),0,1),0) -> 0 | Y70: CC 初評
A71: SRC_OAI_070 | B71: 合約總額：CoreWeave | C71: 22.4 | F71: $B | G71: $11.9B＋$4B＋$6.5B；日後可改接 CRWV 模型之 OpenAI 時程 | H71: CoreWeave | I71: 2025 | J71: CoreWeave 揭露：$11.9B＋$4B＋$6.5B；日後可改接 CRWV 模型之 OpenAI 時程 | K71: 2 | L71: 利害關係方 | M71: 合約雙方公告；OpenAI 有募資與算力規模訊號誘因，供應商有營收與股價訊號誘因；金額為承諾總額，非實付 | N71: 一手 | O71: Active | P71: — | Q71: Verified | R71: — | S71: spending.contracts.coreweave | T71: P3；P4 | V71: =IF(AND($O71="Active",$C71="",$D71="",$E71="",$F71<>"文字"),1,0) -> 0 | W71: =IF(AND($O71="Active",OR($J71="",$J71="—")),1,0) -> 0 | X71: =IF(AND(ISNUMBER($C71),ISNUMBER($D71),ISNUMBER($E71)),IF(AND($D71<=$C71,$C71<=$E71),0,1),0) -> 0 | Y71: CC 初評
A72: SRC_OAI_071 | B72: 合約期間起：CoreWeave | C72: 2025 | F72: 年 | G72: CoreWeave 揭露 | H72: CoreWeave | I72: 2025 | J72: CoreWeave 揭露：$11.9B＋$4B＋$6.5B；日後可改接 CRWV 模型之 OpenAI 時程 | K72: 2 | L72: 利害關係方 | M72: 合約雙方公告；OpenAI 有募資與算力規模訊號誘因，供應商有營收與股價訊號誘因；金額為承諾總額，非實付 | N72: 一手 | O72: Active | P72: — | Q72: Verified | R72: — | S72: spending.contracts.coreweave | T72: P3 | V72: =IF(AND($O72="Active",$C72="",$D72="",$E72="",$F72<>"文字"),1,0) -> 0 | W72: =IF(AND($O72="Active",OR($J72="",$J72="—")),1,0) -> 0 | X72: =IF(AND(ISNUMBER($C72),ISNUMBER($D72),ISNUMBER($E72)),IF(AND($D72<=$C72,$C72<=$E72),0,1),0) -> 0 | Y72: CC 初評
A73: SRC_OAI_072 | B73: 合約期間迄：CoreWeave | C73: 2029 | F73: 年 | G73: CoreWeave 揭露 | H73: CoreWeave | I73: 2025 | J73: CoreWeave 揭露：$11.9B＋$4B＋$6.5B；日後可改接 CRWV 模型之 OpenAI 時程 | K73: 2 | L73: 利害關係方 | M73: 合約雙方公告；OpenAI 有募資與算力規模訊號誘因，供應商有營收與股價訊號誘因；金額為承諾總額，非實付 | N73: 一手 | O73: Active | P73: — | Q73: Verified | R73: — | S73: spending.contracts.coreweave | T73: P3 | V73: =IF(AND($O73="Active",$C73="",$D73="",$E73="",$F73<>"文字"),1,0) -> 0 | W73: =IF(AND($O73="Active",OR($J73="",$J73="—")),1,0) -> 0 | X73: =IF(AND(ISNUMBER($C73),ISNUMBER($D73),ISNUMBER($E73)),IF(AND($D73<=$C73,$C73<=$E73),0,1),0) -> 0 | Y73: CC 初評
A74: SRC_OAI_073 | B74: 合約總額：Cerebras | C74: 20 | D74: 20 | F74: $B | G74: 總值逾 $20B（下限）；10-Q／8-K | H74: Cerebras | I74: 2026 | J74: Cerebras 10-Q／8-K：750MW、2026–28 分批部署、每批 3–4 年、總值逾 $20B；期間終點為推估 | K74: 2 | L74: 利害關係方 | M74: 合約雙方公告；OpenAI 有募資與算力規模訊號誘因，供應商有營收與股價訊號誘因；金額為承諾總額，非實付 | N74: 一手 | O74: Active | P74: — | Q74: Verified | R74: — | S74: spending.contracts.cerebras | T74: P3；P4 | U74: v0.5 total＝lo＝20；上緣 25 見 Inputs（Analogy） | V74: =IF(AND($O74="Active",$C74="",$D74="",$E74="",$F74<>"文字"),1,0) -> 0 | W74: =IF(AND($O74="Active",OR($J74="",$J74="—")),1,0) -> 0 | X74: =IF(AND(ISNUMBER($C74),ISNUMBER($D74),ISNUMBER($E74)),IF(AND($D74<=$C74,$C74<=$E74),0,1),0) -> 0 | Y74: CC 初評
A75: SRC_OAI_074 | B75: 合約期間起：Cerebras | C75: 2026 | F75: 年 | G75: 2026–28 分批部署 | H75: Cerebras | I75: 2026 | J75: Cerebras 10-Q／8-K：750MW、2026–28 分批部署、每批 3–4 年、總值逾 $20B；期間終點為推估 | K75: 2 | L75: 利害關係方 | M75: 合約雙方公告；OpenAI 有募資與算力規模訊號誘因，供應商有營收與股價訊號誘因；金額為承諾總額，非實付 | N75: 一手 | O75: Active | P75: — | Q75: Verified | R75: — | S75: spending.contracts.cerebras | T75: P3 | V75: =IF(AND($O75="Active",$C75="",$D75="",$E75="",$F75<>"文字"),1,0) -> 0 | W75: =IF(AND($O75="Active",OR($J75="",$J75="—")),1,0) -> 0 | X75: =IF(AND(ISNUMBER($C75),ISNUMBER($D75),ISNUMBER($E75)),IF(AND($D75<=$C75,$C75<=$E75),0,1),0) -> 0 | Y75: CC 初評
A76: SRC_OAI_075 | B76: 合約容量：Cerebras | C76: 0.75 | F76: GW | G76: 750MW | H76: Cerebras | I76: 2026 | J76: Cerebras 10-Q／8-K：750MW、2026–28 分批部署、每批 3–4 年、總值逾 $20B；期間終點為推估 | K76: 2 | L76: 利害關係方 | M76: 合約雙方公告；OpenAI 有募資與算力規模訊號誘因，供應商有營收與股價訊號誘因；金額為承諾總額，非實付 | N76: 一手 | O76: Active | P76: — | Q76: Verified | R76: — | S76: spending.contracts.cerebras | T76: P3 | V76: =IF(AND($O76="Active",$C76="",$D76="",$E76="",$F76<>"文字"),1,0) -> 0 | W76: =IF(AND($O76="Active",OR($J76="",$J76="—")),1,0) -> 0 | X76: =IF(AND(ISNUMBER($C76),ISNUMBER($D76),ISNUMBER($E76)),IF(AND($D76<=$C76,$C76<=$E76),0,1),0) -> 0 | Y76: CC 初評
A77: SRC_OAI_076 | B77: 計畫算力支出：2026–2030 累計（WSJ 口徑） | C77: 750 | F77: $B | G77: WSJ 2026-07-22 | H77: OpenAI | I77: 2026-07-22 | J77: WSJ 2026-07-22 | K77: 2 | L77: 利害關係方 | M77: 管理層、內部文件或外流數據：誘因為募資與議價，傾向呈現成長與算力需求 | N77: 二手 | O77: Active | P77: — | Q77: Interested-party | R77: — | S77: spending.anchors.computeCum2026_2030_WSJ | T77: P3 檢查；P5 | V77: =IF(AND($O77="Active",$C77="",$D77="",$E77="",$F77<>"文字"),1,0) -> 0 | W77: =IF(AND($O77="Active",OR($J77="",$J77="—")),1,0) -> 0 | X77: =IF(AND(ISNUMBER($C77),ISNUMBER($D77),ISNUMBER($E77)),IF(AND($D77<=$C77,$C77<=$E77),0,1),0) -> 0 | Y77: CC 初評
A78: SRC_OAI_077 | B78: 表外承諾存量 | C78: 665 | F78: $B | G78: S-1 草案轉述（Tokenomics v1_3 Sources #19） | H78: OpenAI | I78: — | J78: S-1 草案轉述（Tokenomics v1_3 Sources #19） | K78: 2 | L78: 利害關係方 | M78: 管理層、內部文件或外流數據：誘因為募資與議價，傾向呈現成長與算力需求 | N78: 二手 | O78: Active | P78: — | Q78: Interested-party | R78: — | S78: spending.anchors.offBalanceCommitmentsStock | T78: P5 對照 | V78: =IF(AND($O78="Active",$C78="",$D78="",$E78="",$F78<>"文字"),1,0) -> 0 | W78: =IF(AND($O78="Active",OR($J78="",$J78="—")),1,0) -> 0 | X78: =IF(AND(ISNUMBER($C78),ISNUMBER($D78),ISNUMBER($E78)),IF(AND($D78<=$C78,$C78<=$E78),0,1),0) -> 0 | Y78: CC 初評
A79: SRC_OAI_078 | B79: 2026 算力支出（證詞） | C79: 50 | F79: $B | G79: Brockman 證詞（commitments tracker 2026-05 轉述） | H79: OpenAI | I79: 2026-05 | J79: Brockman 證詞（commitments tracker 2026-05 轉述） | K79: 2 | L79: 利害關係方 | M79: 管理層、內部文件或外流數據：誘因為募資與議價，傾向呈現成長與算力需求 | N79: 二手（含一手公告轉載） | O79: Active | P79: — | Q79: Interested-party | R79: — | S79: spending.anchors.compute2026Testimony | T79: P4 對照 | V79: =IF(AND($O79="Active",$C79="",$D79="",$E79="",$F79<>"文字"),1,0) -> 0 | W79: =IF(AND($O79="Active",OR($J79="",$J79="—")),1,0) -> 0 | X79: =IF(AND(ISNUMBER($C79),ISNUMBER($D79),ISNUMBER($E79)),IF(AND($D79<=$C79,$C79<=$E79),0,1),0) -> 0 | Y79: CC 初評
A80: SRC_OAI_079 | B80: 現金：2025 年底 | C80: 40 | D80: 35 | E80: 45 | F80: $B | G80: 2025-12 約 $40B；2026 Q1 末 $73B（The Information 經 TNW 轉述） | H80: OpenAI | I80: — | J80: 2025-12 約 $40B；2026 Q1 末 $73B（The Information 經 TNW 轉述） | K80: 2 | L80: 利害關係方 | M80: 管理層、內部文件或外流數據：誘因為募資與議價，傾向呈現成長與算力需求 | N80: 二手 | O80: Active | P80: — | Q80: Interested-party | R80: — | S80: funding.cashEnd2025 | T80: P5 融資起點 | V80: =IF(AND($O80="Active",$C80="",$D80="",$E80="",$F80<>"文字"),1,0) -> 0 | W80: =IF(AND($O80="Active",OR($J80="",$J80="—")),1,0) -> 0 | X80: =IF(AND(ISNUMBER($C80),ISNUMBER($D80),ISNUMBER($E80)),IF(AND($D80<=$C80,$C80<=$E80),0,1),0) -> 0 | Y80: CC 初評
A81: SRC_OAI_080 | B81: 股權融資：2026-03 輪總額 | C81: 122 | F81: $B | G81: 2026-03 輪（headline） | H81: OpenAI | I81: 2026-03 | J81: OpenAI 公告（2026-03 融資輪；v0.5 該葉節點無出處，依 E8i 補記） | K81: 2 | L81: 利害關係方 | M81: 管理層、內部文件或外流數據：誘因為募資與議價，傾向呈現成長與算力需求 | N81: 一手 | O81: Active | P81: — | Q81: Interested-party | R81: — | S81: funding.equityRound2026Mar | T81: P5 | V81: =IF(AND($O81="Active",$C81="",$D81="",$E81="",$F81<>"文字"),1,0) -> 0 | W81: =IF(AND($O81="Active",OR($J81="",$J81="—")),1,0) -> 0 | X81: =IF(AND(ISNUMBER($C81),ISNUMBER($D81),ISNUMBER($E81)),IF(AND($D81<=$C81,$C81<=$E81),0,1),0) -> 0 | Y81: CC 初評
A82: SRC_OAI_082 | B82: 股權融資：條件式部分（Amazon） | C82: 35 | F82: $B | G82: Amazon 其餘以 IPO 或 AGI 里程碑為條件；base 不計入 | H82: OpenAI | I82: — | J82: Amazon 其餘 $35B 以 IPO 或 AGI 里程碑為條件（多家報導）；base 不計入，列情境 | K82: 2 | L82: 未評 | M82: 原始發布者不明（多家報導）；base 不計入，P5 情境使用時再評 | N82: 二手 | O82: Active | P82: — | Q82: Verified | R82: — | S82: funding.equityRound2026Mar.conditional | T82: P5 | V82: =IF(AND($O82="Active",$C82="",$D82="",$E82="",$F82<>"文字"),1,0) -> 0 | W82: =IF(AND($O82="Active",OR($J82="",$J82="—")),1,0) -> 0 | X82: =IF(AND(ISNUMBER($C82),ISNUMBER($D82),ISNUMBER($E82)),IF(AND($D82<=$C82,$C82<=$E82),0,1),0) -> 0 | Y82: CC 初評
A83: SRC_OAI_083 | B83: 或有負債：Nvidia 擔保 | C83: 250 | F83: $B | G83: WSJ（Tokenomics v1_3 Sources #21） | H83: OpenAI | I83: — | J83: WSJ（Tokenomics v1_3 Sources #21） | K83: 2 | L83: 利害關係方 | M83: 未評 | N83: 二手 | O83: Active | P83: — | Q83: Interested-party | R83: — | S83: funding.contingentLiabilities.nvidiaGuarantees | T83: P5（S4b 只列示） | V83: =IF(AND($O83="Active",$C83="",$D83="",$E83="",$F83<>"文字"),1,0) -> 0 | W83: =IF(AND($O83="Active",OR($J83="",$J83="—")),1,0) -> 0 | X83: =IF(AND(ISNUMBER($C83),ISNUMBER($D83),ISNUMBER($E83)),IF(AND($D83<=$C83,$C83<=$E83),0,1),0) -> 0 | Y83: CC 初評
A84: SRC_OAI_084 | B84: 或有負債：Nvidia 晶片融資洽談 | C84: 350 | F84: $B | G84: WSJ；洽談中 | H84: OpenAI | I84: — | J84: WSJ，洽談中 | K84: 2 | L84: 利害關係方 | M84: 管理層、內部文件或外流數據：誘因為募資與議價，傾向呈現成長與算力需求 | N84: 二手 | O84: Active | P84: — | Q84: Interested-party | R84: — | S84: funding.contingentLiabilities.nvidiaChipFinancingTalks | T84: P5（S4b 只列示） | V84: =IF(AND($O84="Active",$C84="",$D84="",$E84="",$F84<>"文字"),1,0) -> 0 | W84: =IF(AND($O84="Active",OR($J84="",$J84="—")),1,0) -> 0 | X84: =IF(AND(ISNUMBER($C84),ISNUMBER($D84),ISNUMBER($E84)),IF(AND($D84<=$C84,$C84<=$E84),0,1),0) -> 0 | Y84: CC 初評
A85: SRC_OAI_085 | B85: 訓練算力支出：2024 | C85: 3 | F85: $B | G85: Epoch（引 The Information/NYT）：2024 訓練算力 $3B、推論 $1.8B | H85: OpenAI | I85: — | J85: Epoch（引 The Information/NYT）：2024 訓練算力 $3B、推論 $1.8B | K85: 3 | L85: 利害關係方 | M85: 未評 | N85: 二手 | O85: Active | P85: — | Q85: Interested-party | R85: 待查核-報導 | S85: training.actual2024 | T85: P3 對照 | V85: =IF(AND($O85="Active",$C85="",$D85="",$E85="",$F85<>"文字"),1,0) -> 0 | W85: =IF(AND($O85="Active",OR($J85="",$J85="—")),1,0) -> 0 | X85: =IF(AND(ISNUMBER($C85),ISNUMBER($D85),ISNUMBER($E85)),IF(AND($D85<=$C85,$C85<=$E85),0,1),0) -> 0 | Y85: CC 初評
A86: SRC_OAI_087 | B86: 研發費用總額：2025 | C86: 19.18 | F86: $B | G86: 外流財報 R&D 總額（含人事） | H86: OpenAI | I86: — | J86: 外流財報 R&D 總額（含人事） | K86: 2 | L86: 利害關係方 | M86: 管理層、內部文件或外流數據：誘因為募資與議價，傾向呈現成長與算力需求 | N86: 二手（含一手轉載） | O86: Active | P86: — | Q86: Interested-party | R86: — | S86: training.rd2025 | T86: P4 V4 | V86: =IF(AND($O86="Active",$C86="",$D86="",$E86="",$F86<>"文字"),1,0) -> 0 | W86: =IF(AND($O86="Active",OR($J86="",$J86="—")),1,0) -> 0 | X86: =IF(AND(ISNUMBER($C86),ISNUMBER($D86),ISNUMBER($E86)),IF(AND($D86<=$C86,$C86<=$E86),0,1),0) -> 0 | Y86: CC 初評
A87: SRC_OAI_088 | B87: 算力規模：2023 年底 | C87: 0.2 | F87: GW | G87: CFO 部落格；口徑未明（IT／設施未標） | H87: OpenAI | I87: 2026-01-18 | J87: CFO Friar 部落格 2026-01-18：0.2／0.6／約 1.9 GW；ARR $2B／$6B／$20B+ | K87: 3 | L87: 利害關係方 | M87: 未評 | N87: 一手 | O87: Active | P87: — | Q87: Interested-party | R87: 待查核-報導 | S87: computeMW.actuals.gwEnd2023 | T87: P3 總需求 GW 對照 | V87: =IF(AND($O87="Active",$C87="",$D87="",$E87="",$F87<>"文字"),1,0) -> 0 | W87: =IF(AND($O87="Active",OR($J87="",$J87="—")),1,0) -> 0 | X87: =IF(AND(ISNUMBER($C87),ISNUMBER($D87),ISNUMBER($E87)),IF(AND($D87<=$C87,$C87<=$E87),0,1),0) -> 0 | Y87: CC 初評
A88: SRC_OAI_089 | B88: 算力規模：2024 年底 | C88: 0.6 | F88: GW | G88: 同上 | H88: OpenAI | I88: 2026-01-18 | J88: CFO Friar 部落格 2026-01-18：0.2／0.6／約 1.9 GW；ARR $2B／$6B／$20B+ | K88: 3 | L88: 利害關係方 | M88: 未評 | N88: 一手 | O88: Active | P88: — | Q88: Interested-party | R88: 待查核-報導 | S88: computeMW.actuals.gwEnd2024 | T88: P3 對照（工作單 P3-5：0.6） | V88: =IF(AND($O88="Active",$C88="",$D88="",$E88="",$F88<>"文字"),1,0) -> 0 | W88: =IF(AND($O88="Active",OR($J88="",$J88="—")),1,0) -> 0 | X88: =IF(AND(ISNUMBER($C88),ISNUMBER($D88),ISNUMBER($E88)),IF(AND($D88<=$C88,$C88<=$E88),0,1),0) -> 0 | Y88: CC 初評
A89: SRC_OAI_090 | B89: 算力規模：2025 年底 | C89: 1.9 | F89: GW | G89: 同上（約 1.9） | H89: OpenAI | I89: 2026-01-18 | J89: CFO Friar 部落格 2026-01-18：0.2／0.6／約 1.9 GW；ARR $2B／$6B／$20B+ | K89: 3 | L89: 利害關係方 | M89: 未評 | N89: 一手 | O89: Active | P89: — | Q89: Interested-party | R89: 待查核-報導 | S89: computeMW.actuals.gwEnd2025 | T89: P3 對照（工作單 P3-5：1.9） | V89: =IF(AND($O89="Active",$C89="",$D89="",$E89="",$F89<>"文字"),1,0) -> 0 | W89: =IF(AND($O89="Active",OR($J89="",$J89="—")),1,0) -> 0 | X89: =IF(AND(ISNUMBER($C89),ISNUMBER($D89),ISNUMBER($E89)),IF(AND($D89<=$C89,$C89<=$E89),0,1),0) -> 0 | Y89: CC 初評
A90: SRC_OAI_091 | B90: 年化營收（ARR）：2025 年底 | C90: 20 | F90: $B | G90: 同上（$20B+） | H90: OpenAI | I90: 2026-01-18 | J90: CFO Friar 部落格 2026-01-18：0.2／0.6／約 1.9 GW；ARR $2B／$6B／$20B+ | K90: 3 | L90: 利害關係方 | M90: 未評 | N90: 一手 | O90: Active | P90: — | Q90: Interested-party | R90: 待查核-報導 | S90: computeMW.actuals.arrEnd2025 | T90: P2 對照 | V90: =IF(AND($O90="Active",$C90="",$D90="",$E90="",$F90<>"文字"),1,0) -> 0 | W90: =IF(AND($O90="Active",OR($J90="",$J90="—")),1,0) -> 0 | X90: =IF(AND(ISNUMBER($C90),ISNUMBER($D90),ISNUMBER($E90)),IF(AND($D90<=$C90,$C90<=$E90),0,1),0) -> 0 | Y90: CC 初評
A91: SRC_OAI_092 | B91: ChatGPT 週活躍用戶（WAU）：2026-02 | C91: 900 | F91: M | G91: OpenAI 公告；週活躍用戶 | H91: OpenAI | I91: 2026-02 | J91: OpenAI 公告（v0.5 free 出處：WAU 900M，2026-02） | K91: 3 | L91: 利害關係方 | M91: 公司公告：誘因為宣傳成長與用戶規模 | N91: 一手 | O91: Active | P91: — | Q91: Interested-party | R91: 待查核-報導 | S91: tokenRevenue.subscription.subsFYAvg.free.r2.V9 出處文字 | T91: P2 免費用戶人數（2026 公式的依據） | U91: v0.5 出處文字內的觀測值（V9：拆出為 SRC_OAI 列） | V91: =IF(AND($O91="Active",$C91="",$D91="",$E91="",$F91<>"文字"),1,0) -> 0 | W91: =IF(AND($O91="Active",OR($J91="",$J91="—")),1,0) -> 0 | X91: =IF(AND(ISNUMBER($C91),ISNUMBER($D91),ISNUMBER($E91)),IF(AND($D91<=$C91,$C91<=$E91),0,1),0) -> 0 | Y91: CC 初評
A92: SRC_OAI_093 | B92: Go 付費用戶：2025 年底 | C92: 3 | F92: M | G92: 年底人數（非 FY 平均） | H92: OpenAI | I92: 2025-12 | J92: The Information（v0.5 go 出處：2025 年 3M，年底） | K92: 3 | L92: 利害關係方 | M92: 未評 | N92: 二手 | O92: Active | P92: — | Q92: Interested-party | R92: 待查核-報導 | S92: tokenRevenue.subscription.subsFYAvg.go.r2.V9 出處文字 | T92: P2 Go 2025 起點（錨點；FY 平均仍為 Assumed） | U92: v0.5 出處文字內的觀測值（V9：拆出為 SRC_OAI 列） | V92: =IF(AND($O92="Active",$C92="",$D92="",$E92="",$F92<>"文字"),1,0) -> 0 | W92: =IF(AND($O92="Active",OR($J92="",$J92="—")),1,0) -> 0 | X92: =IF(AND(ISNUMBER($C92),ISNUMBER($D92),ISNUMBER($E92)),IF(AND($D92<=$C92,$C92<=$E92),0,1),0) -> 0 | Y92: CC 初評
A93: SRC_OAI_094 | B93: ChatGPT Plus＋Pro 付費訂閱：2025-07 | C93: 35 | F93: M | G93: Plus＋Pro 合計約 35M | H93: OpenAI | I93: 2025-07 | J93: Reuters／The Information 2025-11（v0.5 plus 出處） | K93: 3 | L93: 利害關係方 | M93: 未評 | N93: 二手 | O93: Active | P93: — | Q93: Interested-party | R93: 待查核-報導 | S93: tokenRevenue.subscription.subsFYAvg.plus.r2.V9 出處文字 | T93: P2 Plus 2025 FY 平均（公式依據） | U93: v0.5 出處文字內的觀測值（V9：拆出為 SRC_OAI 列） | V93: =IF(AND($O93="Active",$C93="",$D93="",$E93="",$F93<>"文字"),1,0) -> 0 | W93: =IF(AND($O93="Active",OR($J93="",$J93="—")),1,0) -> 0 | X93: =IF(AND(ISNUMBER($C93),ISNUMBER($D93),ISNUMBER($E93)),IF(AND($D93<=$C93,$C93<=$E93),0,1),0) -> 0 | Y93: CC 初評
A94: SRC_OAI_095 | B94: ChatGPT 付費訂閱：2025 年（內部文件） | C94: 44 | F94: M | G94: OpenAI 內部文件 2025 年 44M | H94: OpenAI | I94: 2026-04-28 | J94: The Information 2026-04-28（v0.5 plus 出處） | K94: 3 | L94: 利害關係方 | M94: 管理層、內部文件或外流數據：誘因為募資與議價，傾向呈現成長與算力需求 | N94: 二手 | O94: Active | P94: — | Q94: Interested-party | R94: 待查核-報導 | S94: tokenRevenue.subscription.subsFYAvg.plus.r2.V9 出處文字 | T94: P2 Plus 2025 FY 平均（公式依據） | U94: v0.5 出處文字內的觀測值（V9：拆出為 SRC_OAI 列） | V94: =IF(AND($O94="Active",$C94="",$D94="",$E94="",$F94<>"文字"),1,0) -> 0 | W94: =IF(AND($O94="Active",OR($J94="",$J94="—")),1,0) -> 0 | X94: =IF(AND(ISNUMBER($C94),ISNUMBER($D94),ISNUMBER($E94)),IF(AND($D94<=$C94,$C94<=$E94),0,1),0) -> 0 | Y94: CC 初評
A95: SRC_OAI_097 | B95: 付費企業用戶：2026-02 | C95: 9 | D95: 9 | F95: M | G95: 逾 9M 付費企業用戶（『逾』＝下限） | H95: OpenAI | I95: 2026-02 | J95: OpenAI 2026-02（v0.5 seats 出處） | K95: 3 | L95: 利害關係方 | M95: 公司公告：誘因為宣傳成長與用戶規模 | N95: 一手 | O95: Active | P95: — | Q95: Interested-party | R95: 待查核-報導 | S95: tokenRevenue.subscription.subsFYAvg.seats.r2.V9 出處文字 | T95: P2 企業席位錨點（FY 平均仍為 Assumed） | U95: v0.5 出處文字內的觀測值（V9：拆出為 SRC_OAI 列） | V95: =IF(AND($O95="Active",$C95="",$D95="",$E95="",$F95<>"文字"),1,0) -> 0 | W95: =IF(AND($O95="Active",OR($J95="",$J95="—")),1,0) -> 0 | X95: =IF(AND(ISNUMBER($C95),ISNUMBER($D95),ISNUMBER($E95)),IF(AND($D95<=$C95,$C95<=$E95),0,1),0) -> 0 | Y95: CC 初評
A96: SRC_OAI_098 | B96: 研發費用中付 Microsoft 部分：2025 | C96: 10.59 | F96: $B | G96: 2025 R&D 付予 Microsoft（外流財報） | H96: OpenAI | I96: — | J96: 外流財報（v0.5 training.actual2025 出處：2025 R&D 付予 Microsoft $10.59B） | K96: 3 | L96: 利害關係方 | M96: 管理層、內部文件或外流數據：誘因為募資與議價，傾向呈現成長與算力需求 | N96: 二手（含一手轉載） | O96: Active | P96: — | Q96: Interested-party | R96: 待查核-報導 | S96: training.actual2025.src文字（r1 V6） | T96: P3 研發 GW；P4 V4（訓練支出＝10.59＋其他雲端） | U96: V6：訓練支出 12.0 拆開，付 Microsoft 的 10.59 進 SRC_OAI；其他雲端 1.41（0–2.91）見 Inputs；12.0（10.59–13.50）＝兩者相加的公式（Checks 衍生值列） | V96: =IF(AND($O96="Active",$C96="",$D96="",$E96="",$F96<>"文字"),1,0) -> 0 | W96: =IF(AND($O96="Active",OR($J96="",$J96="—")),1,0) -> 0 | X96: =IF(AND(ISNUMBER($C96),ISNUMBER($D96),ISNUMBER($E96)),IF(AND($D96<=$C96,$C96<=$E96),0,1),0) -> 0 | Y96: CC 初評
A97: SRC_OAI_099 | B97: 自有園區資本支出例：Project Camellia | C97: 20 | F97: $B | G97: 自有園區與晶片（例） | H97: OpenAI | I97: 2026-07-22 | J97: TechCrunch 2026-07-22（v0.5 ownedCapex 出處） | K97: 2 | L97: 利害關係方 | M97: 未評 | N97: 二手 | O97: Active | P97: — | Q97: Interested-party | R97: — | S97: spending.ownedCapex.src文字（V9 掃描） | T97: P4 自有資本支出 2026 的參照（錨點） | U97: v0.5 出處為『例』；2026 元素 20 為 Assumed 整體額，不等於此單一專案 | V97: =IF(AND($O97="Active",$C97="",$D97="",$E97="",$F97<>"文字"),1,0) -> 0 | W97: =IF(AND($O97="Active",OR($J97="",$J97="—")),1,0) -> 0 | X97: =IF(AND(ISNUMBER($C97),ISNUMBER($D97),ISNUMBER($E97)),IF(AND($D97<=$C97,$C97<=$E97),0,1),0) -> 0 | Y97: CC 初評
A98: SRC_OAI_100 | B98: ChatGPT 每日訊息數：2025-07 | C98: 2.5 | F98: B 則/日 | G98: 每日 2.5B 則訊息（總量對照） | H98: OpenAI | I98: 2025-07 | J98: OpenAI（v0.5 tasksPerDay 出處：總量對照） | K98: 3 | L98: 利害關係方 | M98: 公司公告：誘因為宣傳成長與用戶規模 | N98: 一手 | O98: Active | P98: — | Q98: Interested-party | R98: 待查核-workbook | S98: tokenRevenue.subscription.tasksPerDay.src文字（V9 掃描） | T98: P2 每日任務數的總量對照 | V98: =IF(AND($O98="Active",$C98="",$D98="",$E98="",$F98<>"文字"),1,0) -> 0 | W98: =IF(AND($O98="Active",OR($J98="",$J98="—")),1,0) -> 0 | X98: =IF(AND(ISNUMBER($C98),ISNUMBER($D98),ISNUMBER($E98)),IF(AND($D98<=$C98,$C98<=$E98),0,1),0) -> 0 | Y98: CC 初評
A99: SRC_OAI_101 | B99: Pro 用戶倍數：2026 對 2025（內部預測：倍增） | C99: 2 | F99: 倍 | G99: 內部預測：Pro 用戶 2026 為 2025 的 2 倍 | H99: OpenAI | I99: 2026-04-28 | J99: The Information 2026-04-28（v0.5 pro 出處：內部預測） | K99: 3 | L99: 利害關係方 | M99: 管理層、內部文件或外流數據：誘因為募資與議價，傾向呈現成長與算力需求 | N99: 二手 | O99: Active | P99: — | Q99: Interested-party | R99: 待查核-報導 | S99: tokenRevenue.subscription.subsFYAvg.pro.r2.V9 出處文字 | T99: V12 約束一：2025＝2026÷此倍數 | U99: v0.5 出處文字內的觀測值（V9：拆出為 SRC_OAI 列） | V99: =IF(AND($O99="Active",$C99="",$D99="",$E99="",$F99<>"文字"),1,0) -> 0 | W99: =IF(AND($O99="Active",OR($J99="",$J99="—")),1,0) -> 0 | X99: =IF(AND(ISNUMBER($C99),ISNUMBER($D99),ISNUMBER($E99)),IF(AND($D99<=$C99,$C99<=$E99),0,1),0) -> 0 | Y99: CC 初評
A100: SRC_OAI_102 | B100: Pro 占付費訂閱總數：2026 上限（內部預測：<1%） | E100: 0.01 | F100: 比例 | G100: 內部預測：Pro 占付費總數低於 1%（上限，非點值） | H100: OpenAI | I100: 2026-04-28 | J100: The Information 2026-04-28（v0.5 pro 出處：內部預測） | K100: 3 | L100: 利害關係方 | M100: 管理層、內部文件或外流數據：誘因為募資與議價，傾向呈現成長與算力需求 | N100: 二手 | O100: Active | P100: — | Q100: Interested-party | R100: 待查核-報導 | S100: tokenRevenue.subscription.subsFYAvg.pro.r2.V9 出處文字 | T100: V12 約束二：2026 占比不得超過此上限 | U100: v0.5 出處文字內的觀測值（V9：拆出為 SRC_OAI 列） | V100: =IF(AND($O100="Active",$C100="",$D100="",$E100="",$F100<>"文字"),1,0) -> 0 | W100: =IF(AND($O100="Active",OR($J100="",$J100="—")),1,0) -> 0 | X100: =IF(AND(ISNUMBER($C100),ISNUMBER($D100),ISNUMBER($E100)),IF(AND($D100<=$C100,$C100<=$E100),0,1),0) -> 0 | Y100: CC 初評
...

Sheet TK_Link
A1: TK_Link — Tokenomics 快照（第 0 層連結；不用 Excel 外部連結）
A2: 每列一個 Tokenomics 名稱（SRC_／IF_／L1_）。值（藍字）由 builder 從 Tokenomics master 的 model/CURRENT 讀出寫入；本模型公式只引用 TK_ 具名範圍。更新快照＝本模型的修補版。
A3: Tokenomics 檔案 | B3: 20261007_Tokenomics_v5.24.xlsx
A4: Tokenomics 版本 | B4: v5.24
A5: Tokenomics 提交 SHA（master） | B5: bdb0de7c0d94620591d665efa43856193f23fbba
A6: 讀取日期 | B6: 2026-10-07
I7: 世代 | J7: Hopper H100 | K7: Hopper H100 | L7: Hopper H100 | M7: GB200 NVL72 | N7: GB200 NVL72 | O7: GB200 NVL72 | P7: GB300 NVL72 | Q7: GB300 NVL72 | R7: GB300 NVL72 | S7: VR200 NVL72 | T7: VR200 NVL72 | U7: VR200 NVL72 | V7: Rubin Ultra（MGX NVL 單架，72 GPU） | W7: Rubin Ultra（MGX NVL 單架，72 GPU） | X7: Rubin Ultra（MGX NVL 單架，72 GPU）
I8: 成本情境 | J8: 低成本 | K8: 基準 | L8: 高成本 | M8: 低成本 | N8: 基準 | O8: 高成本 | P8: 低成本 | Q8: 基準 | R8: 高成本 | S8: 低成本 | T8: 基準 | U8: 高成本 | V8: 低成本 | W8: 基準 | X8: 高成本
A9: Tokenomics 名稱 | B9: 本模型名稱 | C9: 說明 | D9: 單位 | E9: 欄數 | F9: 狀態 | G9: Tokenomics 版本 | H9: 提交 SHA | I9: 讀取日期 | J9: 值1 | K9: 值2 | L9: 值3 | M9: 值4 | N9: 值5 | O9: 值6 | P9: 值7 | Q9: 值8 | R9: 值9 | S9: 值10 | T9: 值11 | U9: 值12 | V9: 值13 | W9: 值14 | X9: 值15
A10: IF_TokGW_Astra | B10: TK_IF_TokGW_Astra | C10: 每 GW 總產出（100%） | D10: M tok/年 | E10: 15 | F10: OK | G10: v5.24 | H10: bdb0de7 | I10: 2026-10-07 | J10: 3.8765183e+09 | K10: 3.8765183e+09 | L10: 3.8765183e+09 | M10: 2.0041839e+10 | N10: 2.0041839e+10 | O10: 2.0041839e+10 | P10: 2.4234238e+10 | Q10: 2.4234238e+10 | R10: 2.4234238e+10 | S10: 5.1167891e+10 | T10: 5.1167891e+10 | U10: 5.1167891e+10 | V10: 7.4400956e+10 | W10: 7.4400956e+10 | X10: 7.4400956e+10
A11: IF_TokGW_Luna | B11: TK_IF_TokGW_Luna | C11: 每 GW 總產出（100%） | D11: M tok/年 | E11: 15 | F11: OK | G11: v5.24 | H11: bdb0de7 | I11: 2026-10-07 | J11: 7.4067251e+10 | K11: 7.4067251e+10 | L11: 7.4067251e+10 | M11: 3.6230689e+11 | N11: 3.6230689e+11 | O11: 3.6230689e+11 | P11: 5.2747392e+11 | Q11: 5.2747392e+11 | R11: 5.2747392e+11 | S11: 7.727784e+11 | T11: 7.727784e+11 | U11: 7.727784e+11 | V11: 1.0443737e+12 | W11: 1.0443737e+12 | X11: 1.0443737e+12
A12: IF_TokGW_Sol | B12: TK_IF_TokGW_Sol | C12: 每 GW 總產出（100%） | D12: M tok/年 | E12: 15 | F12: OK | G12: v5.24 | H12: bdb0de7 | I12: 2026-10-07 | J12: 2.149043e+10 | K12: 2.149043e+10 | L12: 2.149043e+10 | M12: 1.041254e+11 | N12: 1.041254e+11 | O12: 1.041254e+11 | P12: 1.5159367e+11 | Q12: 1.5159367e+11 | R12: 1.5159367e+11 | S12: 2.3728734e+11 | T12: 2.3728734e+11 | U12: 2.3728734e+11 | V12: 3.2618567e+11 | W12: 3.2618567e+11 | X12: 3.2618567e+11
A13: IF_Util | B13: TK_IF_Util | C13: 基準利用率（第 0 層；下游可覆寫） | D13: % | E13: 1 | F13: OK | G13: v5.24 | H13: bdb0de7 | I13: 2026-10-07 | J13: 0.6
A14: IF_HoldEcon | B14: TK_IF_HoldEcon | C14: 每 GW 年持有成本 — 經濟口徑 | D14: $B/年 | E14: 15 | F14: OK | G14: v5.24 | H14: bdb0de7 | I14: 2026-10-07 | J14: 7.0000433 | K14: 10.095795 | L14: 17.405972 | M14: 6.813167 | N14: 9.1709819 | O14: 14.920029 | P14: 8.7074708 | Q14: 12.724746 | R14: 23.871869 | S14: 9.8366806 | T14: 12.762016 | U14: 20.678089 | V14: 10.452242 | W14: 16.069457 | X14: 29.454615
A15: IF_FullCost_Astra | B15: TK_IF_FullCost_Astra | C15: 全成本 $/M（服務＋快取儲存＋自下而上攤提；基準利用率） | D15: $/M | E15: 15 | F15: OK | G15: v5.24 | H15: bdb0de7 | I15: 2026-10-07 | J15: 6.9823234 | K15: 10.07014 | L15: 17.361579 | M15: 0.92982466 | N15: 1.2515294 | O15: 2.0359402 | P15: 0.93305227 | Q15: 1.3634219 | R15: 2.5576103 | S15: 0.42538461 | T15: 0.55182355 | U15: 0.89397238 | V15: 0.27809403 | W15: 0.42742659 | X15: 0.78326839
A16: IF_FullCost_Luna | B16: TK_IF_FullCost_Luna | C16: 全成本 $/M（服務＋快取儲存＋自下而上攤提；基準利用率） | D16: $/M | E16: 15 | F16: OK | G16: v5.24 | H16: bdb0de7 | I16: 2026-10-07 | J16: 0.13332981 | K16: 0.19228981 | L16: 0.33151542 | M16: 0.02765365 | N16: 0.037219928 | O16: 0.060545328 | P16: 0.024207999 | Q16: 0.035371595 | R16: 0.066348304 | S16: 0.018368232 | T16: 0.023827547 | U16: 0.038600674 | V16: 0.014351218 | W16: 0.022057988 | X16: 0.04042231
A17: IF_FullCost_Sol | B17: TK_IF_FullCost_Sol | C17: 全成本 $/M（服務＋快取儲存＋自下而上攤提；基準利用率） | D17: $/M | E17: 15 | F17: OK | G17: v5.24 | H17: bdb0de7 | I17: 2026-10-07 | J17: 0.53191053 | K17: 0.76713986 | L17: 1.3226004 | M17: 0.10319199 | N17: 0.13889806 | O17: 0.22595995 | P17: 0.090371238 | Q17: 0.13205779 | R17: 0.2477295 | S17: 0.061571891 | T17: 0.079878216 | U17: 0.12941586 | V17: 0.046474526 | W17: 0.07144248 | X17: 0.13093816
A18: IF_PriceCached_Astra | B18: TK_IF_PriceCached_Astra | C18: 快取輸入 $/M — OpenAI 有效 | D18: $/M | E18: 1 | F18: OK | G18: v5.24 | H18: bdb0de7 | I18: 2026-10-07 | J18: 0.8
A19: IF_PriceCached_Luna | B19: TK_IF_PriceCached_Luna | C19: 快取輸入 $/M — OpenAI 有效 | D19: $/M | E19: 1 | F19: OK | G19: v5.24 | H19: bdb0de7 | I19: 2026-10-07 | J19: 0.008
A20: IF_PriceCached_Sol | B20: TK_IF_PriceCached_Sol | C20: 快取輸入 $/M — OpenAI 有效 | D20: $/M | E20: 1 | F20: OK | G20: v5.24 | H20: bdb0de7 | I20: 2026-10-07 | J20: 0.16
A21: IF_PriceFresh_Astra | B21: TK_IF_PriceFresh_Astra | C21: 新鮮輸入 $/M — OpenAI 有效 | D21: $/M | E21: 1 | F21: OK | G21: v5.24 | H21: bdb0de7 | I21: 2026-10-07 | J21: 8
A22: IF_PriceFresh_Luna | B22: TK_IF_PriceFresh_Luna | C22: 新鮮輸入 $/M — OpenAI 有效 | D22: $/M | E22: 1 | F22: OK | G22: v5.24 | H22: bdb0de7 | I22: 2026-10-07 | J22: 0.08
A23: IF_PriceFresh_Sol | B23: TK_IF_PriceFresh_Sol | C23: 新鮮輸入 $/M — OpenAI 有效 | D23: $/M | E23: 1 | F23: OK | G23: v5.24 | H23: bdb0de7 | I23: 2026-10-07 | J23: 1.6
A24: IF_PriceOut_Astra | B24: TK_IF_PriceOut_Astra | C24: 可見輸出 $/M — OpenAI 有效 | D24: $/M | E24: 1 | F24: OK | G24: v5.24 | H24: bdb0de7 | I24: 2026-10-07 | J24: 40
A25: IF_PriceOut_Luna | B25: TK_IF_PriceOut_Luna | C25: 可見輸出 $/M — OpenAI 有效 | D25: $/M | E25: 1 | F25: OK | G25: v5.24 | H25: bdb0de7 | I25: 2026-10-07 | J25: 0.4
A26: IF_PriceOut_Sol | B26: TK_IF_PriceOut_Sol | C26: 可見輸出 $/M — OpenAI 有效 | D26: $/M | E26: 1 | F26: OK | G26: v5.24 | H26: bdb0de7 | I26: 2026-10-07 | J26: 8
A27: IF_PriceRef_Astra | B27: TK_IF_PriceRef_Astra | C27: 參考請求混合 $/M — OpenAI 有效 | D27: $/M | E27: 1 | F27: OK | G27: v5.24 | H27: bdb0de7 | I27: 2026-10-07 | J27: 8.0355556
A28: IF_PriceRef_Luna | B28: TK_IF_PriceRef_Luna | C28: 參考請求混合 $/M — OpenAI 有效 | D28: $/M | E28: 1 | F28: OK | G28: v5.24 | H28: bdb0de7 | I28: 2026-10-07 | J28: 0.080355556
A29: IF_PriceRef_Sol | B29: TK_IF_PriceRef_Sol | C29: 參考請求混合 $/M — OpenAI 有效 | D29: $/M | E29: 1 | F29: OK | G29: v5.24 | H29: bdb0de7 | I29: 2026-10-07 | J29: 1.6071111
... A35: IF_FrontRef_Sol | B35: TK_IF_FrontRef_Sol | C35: 參考請求混合 $/M — 前緣有效 | D35: $/M | E35: 1 | F35: OK | G35: v5.24 | H35: bdb0de7 | I35: 2026-10-07 | J35: 1.6071111
A36: IF_ProgGWyr_Astra | B36: TK_IF_ProgGWyr_Astra | C36: 研發計畫占 1 GW 一年 | D36: % | E36: 15 | F36: OK | G36: v5.24 | H36: bdb0de7 | I36: 2026-10-07 | J36: 0.14267939 | K36: 0.14267939 | L36: 0.14267939 | M36: 0.07039759 | N36: 0.07039759 | O36: 0.07039759 | P36: 0.065586407 | Q36: 0.065586407 | R36: 0.065586407 | S36: 0.040017843 | T36: 0.040017843 | U36: 0.040017843 | V36: 0.027250415 | W36: 0.027250415 | X36: 0.027250415
A37: IF_ProgGWyr_Luna | B37: TK_IF_ProgGWyr_Luna | C37: 研發計畫占 1 GW 一年 | D37: % | E37: 15 | F37: OK | G37: v5.24 | H37: bdb0de7 | I37: 2026-10-07 | J37: 0.0081323583 | K37: 0.0081323583 | L37: 0.0081323583 | M37: 0.0037853004 | N37: 0.0037853004 | O37: 0.0037853004 | P37: 0.0033289655 | Q37: 0.0033289655 | R37: 0.0033289655 | S37: 0.0022043397 | T37: 0.0022043397 | U37: 0.0022043397 | V37: 0.0014304485 | W37: 0.0014304485 | X37: 0.0014304485
A38: IF_ProgGWyr_Sol | B38: TK_IF_ProgGWyr_Sol | C38: 研發計畫占 1 GW 一年 | D38: % | E38: 15 | F38: OK | G38: v5.24 | H38: bdb0de7 | I38: 2026-10-07 | J38: 0.023146292 | K38: 0.023146292 | L38: 0.023146292 | M38: 0.011197547 | N38: 0.011197547 | O38: 0.011197547 | P38: 0.010227304 | Q38: 0.010227304 | R38: 0.010227304 | S38: 0.006421121 | T38: 0.006421121 | U38: 0.006421121 | V38: 0.0043094856 | W38: 0.0043094856 | X38: 0.0043094856
A39: IF_RDMult | B39: TK_IF_RDMult | C39: 研發倍數（第 0 層基準；下游可覆寫） | D39: x | E39: 1 | F39: OK | G39: v5.24 | H39: bdb0de7 | I39: 2026-10-07 | J39: 8
A40: IF_TrainGenDefault | B40: TK_IF_TrainGenDefault | C40: 下游預設訓練世代（索引；J13） | D40: 索引 | E40: 1 | F40: OK | G40: v5.24 | H40: bdb0de7 | I40: 2026-10-07 | J40: 4
A41: SRC_DEM_004 | B41: TK_SRC_DEM_004 | C41: OpenAI 2025 推論支出（年度） | D41: $B | E41: 1 | F41: OK | G41: v5.24 | H41: bdb0de7 | I41: 2026-10-07 | J41: 8.4
A42: SRC_DEM_005 | B42: TK_SRC_DEM_005 | C42: OpenAI 2025 非付費用戶推論支出（年度） | D42: $B | E42: 1 | F42: OK | G42: v5.24 | H42: bdb0de7 | I42: 2026-10-07 | J42: 3.9
A43: SRC_DEM_006 | B43: TK_SRC_DEM_006 | C43: OpenAI 2025 訓練支出（年度；約值） | D43: $B | E43: 1 | F43: OK | G43: v5.24 | H43: bdb0de7 | I43: 2026-10-07 | J43: 12
A44: SRC_DEM_007 | B44: TK_SRC_DEM_007 | C44: OpenAI 2025 營收（年度） | D44: $B | E44: 1 | F44: OK | G44: v5.24 | H44: bdb0de7 | I44: 2026-10-07 | J44: 13.07
A45: SRC_DEM_008 | B45: TK_SRC_DEM_008 | C45: OpenAI 算力規模 2024 年底（GW 口徑未明（D1）） | D45: GW | E45: 1 | F45: OK | G45: v5.24 | H45: bdb0de7 | I45: 2026-10-07 | J45: 0.6
A46: SRC_DEM_009 | B46: TK_SRC_DEM_009 | C46: OpenAI 算力規模 2025 年底（約值；口徑未明） | D46: GW | E46: 1 | F46: OK | G46: v5.24 | H46: bdb0de7 | I46: 2026-10-07 | J46: 1.9
A47: SRC_DEM_010 | B47: TK_SRC_DEM_010 | C47: OpenAI API 處理量（時點值；API 全部） | D47: B tok/min | E47: 1 | F47: OK | G47: v5.24 | H47: bdb0de7 | I47: 2026-10-07 | J47: 6
A48: SRC_DEM_011 | B48: TK_SRC_DEM_011 | C48: OpenAI API 處理量（時點值；「超過」；API 全部） | D48: B tok/min | E48: 1 | F48: OK | G48: v5.24 | H48: bdb0de7 | I48: 2026-10-07 | J48: 15
A49: SRC_DEM_012 | B49: TK_SRC_DEM_012 | C49: ChatGPT 每日提示數（全球；其中美國約 0.33B） | D49: B 則/日 | E49: 1 | F49: OK | G49: v5.24 | H49: bdb0de7 | I49: 2026-10-07 | J49: 2.5
A50: SRC_DEM_013 | B50: TK_SRC_DEM_013 | C50: 前沿實驗室（OpenAI）每日 token（由算力推估） | D50: T tok/日 | E50: 1 | F50: OK | G50: v5.24 | H50: bdb0de7 | I50: 2026-10-07
A51: SRC_DEM_013_Lo | B51: TK_SRC_DEM_013_Lo | C51: 前沿實驗室（OpenAI）每日 token（由算力推估） | D51: T tok/日 | E51: 1 | F51: OK | G51: v5.24 | H51: bdb0de7 | I51: 2026-10-07 | J51: 10
A52: SRC_DEM_013_Hi | B52: TK_SRC_DEM_013_Hi | C52: 前沿實驗室（OpenAI）每日 token（由算力推估） | D52: T tok/日 | E52: 1 | F52: OK | G52: v5.24 | H52: bdb0de7 | I52: 2026-10-07 | J52: 100
A53: IF_AllocQ1 | B53: TK_IF_AllocQ1 | C53: 研發算力占比 Q1（R1：研發 GW ÷ 研發＋服務 GW） | D53: % | E53: 1 | F53: OK | G53: v5.24 | H53: bdb0de7 | I53: 2026-10-07 | J53: 0.63609602
A54: IF_AllocQ1_R2 | B54: TK_IF_AllocQ1_R2 | C54: 研發算力占比 Q1（R2：免費服務算作產品改良） | D54: % | E54: 1 | F54: OK | G54: v5.24 | H54: bdb0de7 | I54: 2026-10-07 | J54: 0.66722015
A55: IF_AllocQ2 | B55: TK_IF_AllocQ2 | C55: 研發算力成本占比 Q2（已裝 GW × 各世代每 GW 年持有成本；利用率不進入） | D55: % | E55: 1 | F55: OK | G55: v5.24 | H55: bdb0de7 | I55: 2026-10-07 | J55: 0.66355656
A56: IF_AllocServeGW | B56: TK_IF_AllocServeGW | C56: 服務 GW 合計（token 路線；付費＋免費；IT 關鍵電力） | D56: GW | E56: 1 | F56: OK | G56: v5.24 | H56: bdb0de7 | I56: 2026-10-07 | J56: 0.051879785
A57: IF_AllocRDGW | B57: TK_IF_AllocRDGW | C57: 研發 GW 年（k ×（N_major × 家族＋N_refresh × 改版）；訓練世代＝IF_TrainGenDefault） | D57: GW·年 | E57: 1 | F57: OK | G57: v5.24 | H57: bdb0de7 | I57: 2026-10-07 | J57: 0.090684704
A58: IF_AllocDemand | B58: TK_IF_AllocDemand | C58: 需求 D 合計（API＋ChatGPT；付費＋免費 token；2025） | D58: M tok/年 | E58: 1 | F58: OK | G58: v5.24 | H58: bdb0de7 | I58: 2026-10-07 | J58: 4190200000
A59: IF_AllocImpliedNk | B59: TK_IF_AllocImpliedNk | C59: 隱含 N × k（2025 支出比反推；以家族計畫當量；A3） | D59: 個 | E59: 1 | F59: OK | G59: v5.24 | H59: bdb0de7 | I59: 2026-10-07 | J59: 1.5236214
A60: IF_TrainCost_Astra | B60: TK_IF_TrainCost_Astra | C60: 最終訓練成本 — 經濟（依成本情境） | D60: $M | E60: 15 | F60: OK | G60: v5.24 | H60: bdb0de7 | I60: 2026-10-07 | J60: 124.84524 | K60: 180.05774 | L60: 310.43419 | M60: 59.953817 | N60: 80.701878 | O60: 131.29176 | P60: 71.386466 | Q60: 104.3213 | R60: 195.70877 | S60: 49.205343 | T60: 63.838544 | U60: 103.43657 | V60: 35.60349 | W60: 54.737419 | X60: 100.33131
A61: IF_TrainCost_Luna | B61: TK_IF_TrainCost_Luna | C61: 最終訓練成本 — 經濟（依成本情境） | D61: $M | E61: 15 | F61: OK | G61: v5.24 | H61: bdb0de7 | I61: 2026-10-07 | J61: 7.1158576 | K61: 10.262828 | L61: 17.69395 | M61: 3.2237355 | N61: 4.3393652 | O61: 7.0595988 | P61: 3.6233587 | Q61: 5.2950302 | R61: 9.9335787 | S61: 2.7104232 | T61: 3.5164772 | U61: 5.6976916 | V61: 1.8689242 | W61: 2.8733163 | X61: 5.2666638
A62: IF_TrainCost_Sol | B62: TK_IF_TrainCost_Sol | C62: 最終訓練成本 — 經濟（依成本情境） | D62: $M | E62: 15 | F62: OK | G62: v5.24 | H62: bdb0de7 | I62: 2026-10-07 | J62: 20.253131 | K62: 29.210028 | L62: 50.360464 | M62: 9.5363448 | N62: 12.836563 | O62: 20.883466 | P62: 11.131744 | Q62: 16.267482 | R62: 30.51811 | S62: 7.8953145 | T62: 10.243306 | U62: 16.597064 | V62: 5.630473 | W62: 8.6563864 | X62: 15.86678
A63: IF_RevGW_Astra | B63: TK_IF_RevGW_Astra | C63: 每 GW 理論營收 — OpenAI 有效單價（理想上限） | D63: $B/年 | E63: 15 | F63: OK | G63: v5.24 | H63: bdb0de7 | I63: 2026-10-07 | J63: 18.689987 | K63: 18.689987 | L63: 18.689987 | M63: 96.628385 | N63: 96.628385 | O63: 96.628385 | P63: 116.84134 | Q63: 116.84134 | R63: 116.84134 | S63: 246.69746 | T63: 246.69746 | U63: 246.69746 | V63: 358.71181 | W63: 358.71181 | X63: 358.71181
A64: IF_RevGW_Luna | B64: TK_IF_RevGW_Luna | C64: 每 GW 理論營收 — OpenAI 有效單價（理想上限） | D64: $B/年 | E64: 15 | F64: OK | G64: v5.24 | H64: bdb0de7 | I64: 2026-10-07 | J64: 3.5710291 | K64: 3.5710291 | L64: 3.5710291 | M64: 17.468023 | N64: 17.468023 | O64: 17.468023 | P64: 25.431276 | Q64: 25.431276 | R64: 25.431276 | S64: 37.258223 | T64: 37.258223 | U64: 37.258223 | V64: 50.352738 | W64: 50.352738 | X64: 50.352738
A65: IF_RevGW_Sol | B65: TK_IF_RevGW_Sol | C65: 每 GW 理論營收 — OpenAI 有效單價（理想上限） | D65: $B/年 | E65: 15 | F65: OK | G65: v5.24 | H65: bdb0de7 | I65: 2026-10-07 | J65: 20.722505 | K65: 20.722505 | L65: 20.722505 | M65: 100.40465 | N65: 100.40465 | O65: 100.40465 | P65: 146.17673 | Q65: 146.17673 | R65: 146.17673 | S65: 228.80827 | T65: 228.80827 | U65: 228.80827 | V65: 314.52997 | W65: 314.52997 | X65: 314.52997
A66: IF_FullCostDefault_Astra | B66: TK_IF_FullCostDefault_Astra | C66: 全成本 $/M（服務＋快取儲存＋K6 預設攤提；基準利用率；下游預設） | D66: $/M | E66: 15 | F66: OK | G66: v5.24 | H66: bdb0de7 | I66: 2026-10-07 | J66: 12.125949 | K66: 17.488224 | L66: 30.150469 | M66: 2.4787428 | N66: 3.3362463 | O66: 5.4270923 | P66: 2.5035913 | Q66: 3.6582184 | R66: 6.862074 | S66: 1.4363673 | T66: 1.8632734 | U66: 3.0184984 | V66: 1.0697411 | W66: 1.6441809 | X66: 3.0130029
A67: IF_FullCostDefault_Luna | B67: TK_IF_FullCostDefault_Luna | C67: 全成本 $/M（服務＋快取儲存＋K6 預設攤提；基準利用率；下游預設） | D67: $/M | E67: 15 | F67: OK | G67: v5.24 | H67: bdb0de7 | I67: 2026-10-07 | J67: 0.14312525 | K67: 0.20641669 | L67: 0.35587038 | M67: 0.030515905 | N67: 0.041072288 | O67: 0.066811858 | P67: 0.026689888 | Q67: 0.038998013 | R67: 0.073150556 | S67: 0.020467808 | T67: 0.026551124 | U67: 0.043012821 | V67: 0.015974716 | W67: 0.02455329 | X67: 0.044995017
A68: IF_FullCostDefault_Sol | B68: TK_IF_FullCostDefault_Sol | C68: 全成本 $/M（服務＋快取儲存＋K6 預設攤提；基準利用率；下游預設） | D68: $/M | E68: 15 | F68: OK | G68: v5.24 | H68: bdb0de7 | I68: 2026-10-07 | J68: 0.65231102 | K68: 0.94078019 | L68: 1.621959 | M68: 0.13922176 | N68: 0.18739118 | O68: 0.30484239 | P68: 0.12451033 | Q68: 0.1819402 | R68: 0.34129642 | S68: 0.086330412 | T68: 0.11199505 | U68: 0.18144457 | V68: 0.06588753 | W68: 0.10128009 | X68: 0.18561637
A69: L1_Ans3 | B69: TK_L1_Ans3 | C69: 問 3：研發占整體成本 Q3（算力部分）（基準） | D69: $B/年 | E69: 1 | F69: OK | G69: v5.24 | H69: bdb0de7 | I69: 2026-10-07 | J69: 1.1573196
A70: L1_Ans3_Lo | B70: TK_L1_Ans3_Lo | C70: 問 3：研發占整體成本 Q3（算力部分）（低） | D70: $B/年 | E70: 1 | F70: OK | G70: v5.24 | H70: bdb0de7 | I70: 2026-10-07 | J70: 0.57865981
A71: L1_Ans3_Hi | B71: TK_L1_Ans3_Hi | C71: 問 3：研發占整體成本 Q3（算力部分）（高） | D71: $B/年 | E71: 1 | F71: OK | G71: v5.24 | H71: bdb0de7 | I71: 2026-10-07 | J71: 8.1012373

Sheet Inputs
A1: Inputs — 假設輸入（藍字）；v0.6-P1：只建表頭與 v0.5 Assumed／Analogy／Decision 項目的遷入
A2: 長表格式：一列一個（參數 × 索引）。標記沿用 v0.5；區間倍數（低／高情境倍數）另列。Analogy／Assumed 無區間者保留空白並於備註說明（不自行補值）。
A3: 屬 Tokenomics 領域的 v0.5 項目（rack、classes、serving、hwCostPerM、tokenomicsRef、genFactor.hopper／nextGen）不在此頁，見 Map_v05：『不遷入；改取 TK_Link』。
A4: INP_ID | B4: 參數 | C4: 索引 | D4: 單位 | E4: 值 | F4: 低 | G4: 高 | H4: 標記 | I4: v0.5 原決策 | J4: 狀態 | K4: v0.5 路徑 | L4: 備註 | M4: 區間順序異常（公式）
A5: INP_001 | B5: 基準年 | C5: — | D5: 年 | E5: 2025 | H5: Decision | I5: — | J5: v0.6 沿用 | K5: tokenRevenue.meta.baseYear | M5: =IF(AND(ISNUMBER($E5),ISNUMBER($F5),ISNUMBER($G5)),IF(AND($F5<=$E5,$E5<=$G5),0,1),0) -> 0
A6: INP_002 | B6: 校準年（第 1 個） | C6: — | D6: 年 | E6: 2025 | H6: Decision | I6: — | J6: v0.6 沿用 | K6: tokenRevenue.meta.calibrationYears.0 | L6: v0.5：2025、2026 為校準年；2026 為預測校準（見 demandGrowthExPrice 註記） | M6: =IF(AND(ISNUMBER($E6),ISNUMBER($F6),ISNUMBER($G6)),IF(AND($F6<=$E6,$E6<=$G6),0,1),0) -> 0
A7: INP_003 | B7: 校準年（第 2 個） | C7: — | D7: 年 | E7: 2026 | H7: Decision | I7: — | J7: v0.6 沿用 | K7: tokenRevenue.meta.calibrationYears.1 | M7: =IF(AND(ISNUMBER($E7),ISNUMBER($F7),ISNUMBER($G7)),IF(AND($F7<=$E7,$E7<=$G7),0,1),0) -> 0
A8: INP_004 | B8: 彈性起算年 | C8: — | D8: 年 | E8: 2027 | H8: Decision | I8: — | J8: v0.6 沿用 | K8: tokenRevenue.meta.elasticityFromYear | M8: =IF(AND(ISNUMBER($E8),ISNUMBER($F8),ISNUMBER($G8)),IF(AND($F8<=$E8,$E8<=$G8),0,1),0) -> 0
A9: INP_005 | B9: 模型年度 | C9: 第 1 年 | D9: 年 | E9: 2025 | H9: Decision | I9: D10→FY2030 | J9: v0.6 沿用 | K9: tokenRevenue.meta.years.0 | L9: 曆年制；2025 為實際校準年（工作單第 0 節） | M9: =IF(AND(ISNUMBER($E9),ISNUMBER($F9),ISNUMBER($G9)),IF(AND($F9<=$E9,$E9<=$G9),0,1),0) -> 0
A10: INP_006 | B10: 模型年度 | C10: 第 2 年 | D10: 年 | E10: 2026 | H10: Decision | I10: D10→FY2030 | J10: v0.6 沿用 | K10: tokenRevenue.meta.years.1 | L10: 曆年制；2025 為實際校準年（工作單第 0 節） | M10: =IF(AND(ISNUMBER($E10),ISNUMBER($F10),ISNUMBER($G10)),IF(AND($F10<=$E10,$E10<=$G10),0,1),0) -> 0
A11: INP_007 | B11: 模型年度 | C11: 第 3 年 | D11: 年 | E11: 2027 | H11: Decision | I11: D10→FY2030 | J11: v0.6 沿用 | K11: tokenRevenue.meta.years.2 | L11: 曆年制；2025 為實際校準年（工作單第 0 節） | M11: =IF(AND(ISNUMBER($E11),ISNUMBER($F11),ISNUMBER($G11)),IF(AND($F11<=$E11,$E11<=$G11),0,1),0) -> 0
A12: INP_008 | B12: 模型年度 | C12: 第 4 年 | D12: 年 | E12: 2028 | H12: Decision | I12: D10→FY2030 | J12: v0.6 沿用 | K12: tokenRevenue.meta.years.3 | L12: 曆年制；2025 為實際校準年（工作單第 0 節） | M12: =IF(AND(ISNUMBER($E12),ISNUMBER($F12),ISNUMBER($G12)),IF(AND($F12<=$E12,$E12<=$G12),0,1),0) -> 0
A13: INP_009 | B13: 模型年度 | C13: 第 5 年 | D13: 年 | E13: 2029 | H13: Decision | I13: D10→FY2030 | J13: v0.6 沿用 | K13: tokenRevenue.meta.years.4 | L13: 曆年制；2025 為實際校準年（工作單第 0 節） | M13: =IF(AND(ISNUMBER($E13),ISNUMBER($F13),ISNUMBER($G13)),IF(AND($F13<=$E13,$E13<=$G13),0,1),0) -> 0
A14: INP_010 | B14: 模型年度 | C14: 第 6 年 | D14: 年 | E14: 2030 | H14: Decision | I14: D10→FY2030 | J14: v0.6 沿用 | K14: tokenRevenue.meta.years.5 | L14: 曆年制；2025 為實際校準年（工作單第 0 節） | M14: =IF(AND(ISNUMBER($E14),ISNUMBER($F14),ISNUMBER($G14)),IF(AND($F14<=$E14,$E14<=$G14),0,1),0) -> 0
A15: INP_011 | B15: 分成上限起算年 | C15: — | D15: 年 | E15: 2026 | H15: Assumed | I15: N2a | J15: v0.6 沿用 | K15: tokenRevenue.msShare.capCountFromYear | L15: 起算點未揭露；Andy 2026-09-29 決定 N2a（v0.5 無區間，待 Project 補） | M15: =IF(AND(ISNUMBER($E15),ISNUMBER($F15),ISNUMBER($G15)),IF(AND($F15<=$E15,$E15<=$G15),0,1),0) -> 0
A16: INP_012 | B16: T4 遷移幅度（占公司計畫）— 低 | C16: — | D16: 比例 | E16: 0 | H16: Decision | I16: T4 | J16: v0.6 沿用 | K16: tokenRevenue.subscription.migration.planFraction | L16: 情境值：Plus→Go 遷移與 Go 額外新增的幅度比例 | M16: =IF(AND(ISNUMBER($E16),ISNUMBER($F16),ISNUMBER($G16)),IF(AND($F16<=$E16,$E16<=$G16),0,1),0) -> 0
A17: INP_013 | B17: T4 遷移幅度（占公司計畫）— 基準 | C17: — | D17: 比例 | E17: 0.3 | H17: Decision | I17: T4 | J17: v0.6 沿用 | K17: tokenRevenue.subscription.migration.planFraction | L17: Andy 2026-09-29 採預設 | M17: =IF(AND(ISNUMBER($E17),ISNUMBER($F17),ISNUMBER($G17)),IF(AND($F17<=$E17,$E17<=$G17),0,1),0) -> 0
A18: INP_014 | B18: T4 遷移幅度（占公司計畫）— 高 | C18: — | D18: 比例 | E18: 0.8 | H18: Decision | I18: T4 | J18: v0.6 沿用 | K18: tokenRevenue.subscription.migration.planFraction | M18: =IF(AND(ISNUMBER($E18),ISNUMBER($F18),ISNUMBER($G18)),IF(AND($F18<=$E18,$E18<=$G18),0,1),0) -> 0
A19: INP_015 | B19: FY 平均牌價（輸入）：top 層 | C19: 2025 | D19: $/M tokens | E19: 2.5 | F19: 1.5 | G19: 4 | H19: Analogy | I19: — | J19: v0.6 沿用 | K19: tokenRevenue.api.listPriceFYAvg.in.top | L19: 2025 為 Analogy（v0.5 標 Analogy/Derived 混合；2025 屬 Analogy） | M19: =IF(AND(ISNUMBER($E19),ISNUMBER($F19),ISNUMBER($G19)),IF(AND($F19<=$E19,$E19<=$G19),0,1),0) -> 0
A20: INP_016 | B20: FY 平均牌價（輸入）：mid 層 | C20: 2025 | D20: $/M tokens | E20: 1.5 | F20: 1 | G20: 2.5 | H20: Analogy | I20: — | J20: v0.6 沿用 | K20: tokenRevenue.api.listPriceFYAvg.in.mid | L20: 2025 為 Analogy（v0.5 標 Analogy/Derived 混合；2025 屬 Analogy） | M20: =IF(AND(ISNUMBER($E20),ISNUMBER($F20),ISNUMBER($G20)),IF(AND($F20<=$E20,$E20<=$G20),0,1),0) -> 0
A21: INP_017 | B21: FY 平均牌價（輸入）：low 層 | C21: 2025 | D21: $/M tokens | E21: 0.2 | F21: 0.1 | G21: 0.4 | H21: Analogy | I21: — | J21: v0.6 沿用 | K21: tokenRevenue.api.listPriceFYAvg.in.low | L21: 2025 為 Analogy（v0.5 標 Analogy/Derived 混合；2025 屬 Analogy） | M21: =IF(AND(ISNUMBER($E21),ISNUMBER($F21),ISNUMBER($G21)),IF(AND($F21<=$E21,$E21<=$G21),0,1),0) -> 0
A22: INP_018 | B22: FY 平均牌價（輸出）：top 層 | C22: 2025 | D22: $/M tokens | E22: 14 | F22: 8 | G22: 20 | H22: Analogy | I22: — | J22: v0.6 沿用 | K22: tokenRevenue.api.listPriceFYAvg.out.top | L22: 2025 為 Analogy（v0.5 標 Analogy/Derived 混合；2025 屬 Analogy） | M22: =IF(AND(ISNUMBER($E22),ISNUMBER($F22),ISNUMBER($G22)),IF(AND($F22<=$E22,$E22<=$G22),0,1),0) -> 0
A23: INP_019 | B23: FY 平均牌價（輸出）：mid 層 | C23: 2025 | D23: $/M tokens | E23: 8 | F23: 5 | G23: 10 | H23: Analogy | I23: — | J23: v0.6 沿用 | K23: tokenRevenue.api.listPriceFYAvg.out.mid | L23: 2025 為 Analogy（v0.5 標 Analogy/Derived 混合；2025 屬 Analogy） | M23: =IF(AND(ISNUMBER($E23),ISNUMBER($F23),ISNUMBER($G23)),IF(AND($F23<=$E23,$E23<=$G23),0,1),0) -> 0
A24: INP_020 | B24: FY 平均牌價（輸出）：low 層 | C24: 2025 | D24: $/M tokens | E24: 1 | F24: 0.5 | G24: 2 | H24: Analogy | I24: — | J24: v0.6 沿用 | K24: tokenRevenue.api.listPriceFYAvg.out.low | L24: 2025 為 Analogy（v0.5 標 Analogy/Derived 混合；2025 屬 Analogy） | M24: =IF(AND(ISNUMBER($E24),ISNUMBER($F24),ISNUMBER($G24)),IF(AND($F24<=$E24,$E24<=$G24),0,1),0) -> 0
A25: INP_021 | B25: 牌價年變動率：top 層 | C25: — | D25: 比例/年 | E25: -0.3 | F25: -0.45 | G25: -0.15 | H25: Assumed | I25: D11 | J25: v0.6 沿用 | K25: tokenRevenue.api.listPriceAnnualChange.top | L25: 2027 起每年；情境軸之一 | M25: =IF(AND(ISNUMBER($E25),ISNUMBER($F25),ISNUMBER($G25)),IF(AND($F25<=$E25,$E25<=$G25),0,1),0) -> 0
A26: INP_022 | B26: 牌價年變動率：mid 層 | C26: — | D26: 比例/年 | E26: -0.4 | F26: -0.6 | G26: -0.2 | H26: Assumed | I26: D11 | J26: v0.6 沿用 | K26: tokenRevenue.api.listPriceAnnualChange.mid | L26: 2027 起每年；情境軸之一 | M26: =IF(AND(ISNUMBER($E26),ISNUMBER($F26),ISNUMBER($G26)),IF(AND($F26<=$E26,$E26<=$G26),0,1),0) -> 0
A27: INP_023 | B27: 牌價年變動率：low 層 | C27: — | D27: 比例/年 | E27: -0.4 | F27: -0.6 | G27: -0.2 | H27: Assumed | I27: D11 | J27: v0.6 沿用 | K27: tokenRevenue.api.listPriceAnnualChange.low | L27: 2027 起每年；情境軸之一 | M27: =IF(AND(ISNUMBER($E27),ISNUMBER($F27),ISNUMBER($G27)),IF(AND($F27<=$E27,$E27<=$G27),0,1),0) -> 0
A28: INP_024 | B28: API token 層級占比：top 層 | C28: 陣列[0] | D28: 比例 | E28: 0.4 | F28: 0.25 | G28: 0.5 | H28: Assumed | I28: — | J28: v0.6 沿用 | K28: tokenRevenue.api.tokenMix.top | L28: v0.5 陣列兩位（年份對應待 P2 確認：占比 top 0.40→0.15 判斷為 2025→2026） | M28: =IF(AND(ISNUMBER($E28),ISNUMBER($F28),ISNUMBER($G28)),IF(AND($F28<=$E28,$E28<=$G28),0,1),0) -> 0
A29: INP_025 | B29: API token 層級占比：top 層 | C29: 陣列[1] | D29: 比例 | E29: 0.15 | F29: 0.08 | G29: 0.25 | H29: Assumed | I29: — | J29: v0.6 沿用 | K29: tokenRevenue.api.tokenMix.top | L29: v0.5 陣列兩位（年份對應待 P2 確認：占比 top 0.40→0.15 判斷為 2025→2026） | M29: =IF(AND(ISNUMBER($E29),ISNUMBER($F29),ISNUMBER($G29)),IF(AND($F29<=$E29,$E29<=$G29),0,1),0) -> 0
A30: INP_026 | B30: API token 層級占比：mid 層 | C30: 陣列[0] | D30: 比例 | E30: 0.4 | F30: 0.3 | G30: 0.5 | H30: Assumed | I30: — | J30: v0.6 沿用 | K30: tokenRevenue.api.tokenMix.mid | L30: v0.5 陣列兩位（年份對應待 P2 確認：占比 top 0.40→0.15 判斷為 2025→2026） | M30: =IF(AND(ISNUMBER($E30),ISNUMBER($F30),ISNUMBER($G30)),IF(AND($F30<=$E30,$E30<=$G30),0,1),0) -> 0
A31: INP_027 | B31: API token 層級占比：mid 層 | C31: 陣列[1] | D31: 比例 | E31: 0.45 | F31: 0.35 | G31: 0.55 | H31: Assumed | I31: — | J31: v0.6 沿用 | K31: tokenRevenue.api.tokenMix.mid | L31: v0.5 陣列兩位（年份對應待 P2 確認：占比 top 0.40→0.15 判斷為 2025→2026） | M31: =IF(AND(ISNUMBER($E31),ISNUMBER($F31),ISNUMBER($G31)),IF(AND($F31<=$E31,$E31<=$G31),0,1),0) -> 0
A32: INP_028 | B32: 輸出 token 占比（API） | C32: — | D32: 比例 | E32: 0.2 | F32: 0.1 | G32: 0.35 | H32: Analogy | I32: — | J32: v0.6 沿用 | K32: tokenRevenue.api.outputShare | M32: =IF(AND(ISNUMBER($E32),ISNUMBER($F32),ISNUMBER($G32)),IF(AND($F32<=$E32,$E32<=$G32),0,1),0) -> 0
A33: INP_029 | B33: 快取命中率（API） | C33: — | D33: 比例 | E33: 0.55 | F33: 0.3 | G33: 0.75 | H33: Assumed | I33: — | J33: v0.6 沿用 | K33: tokenRevenue.api.cacheHitRate | M33: =IF(AND(ISNUMBER($E33),ISNUMBER($F33),ISNUMBER($G33)),IF(AND($F33<=$E33,$E33<=$G33),0,1),0) -> 0
A34: INP_030 | B34: 加權折扣率（Batch/Flex／企業） | C34: — | D34: 比例 | E34: 0.2 | F34: 0.1 | G34: 0.3 | H34: Assumed | I34: — | J34: v0.6 沿用 | K34: tokenRevenue.api.discountRate | M34: =IF(AND(ISNUMBER($E34),ISNUMBER($F34),ISNUMBER($G34)),IF(AND($F34<=$E34,$E34<=$G34),0,1),0) -> 0
A35: INP_031 | B35: 基準每任務 token（層級正規化） | C35: — | D35: K tok/task | E35: 10 | F35: 5 | G35: 30 | H35: Assumed | I35: — | J35: v0.6 沿用 | K35: tokenRevenue.api.tokensPerTaskBase | L35: 只影響 N 與 k 的水準拆分，不影響營收 | M35: =IF(AND(ISNUMBER($E35),ISNUMBER($F35),ISNUMBER($G35)),IF(AND($F35<=$E35,$E35<=$G35),0,1),0) -> 0
A36: INP_032 | B36: 任務數成長率（不含價格） | C36: 2025 | D36: 比例/年 | E36: 0 | H36: Assumed | I36: — | J36: v0.6 沿用 | K36: tokenRevenue.api.demandGrowthExPrice.tasks | L36: 2025 欄為 0（基準年） | M36: =IF(AND(ISNUMBER($E36),ISNUMBER($F36),ISNUMBER($G36)),IF(AND($F36<=$E36,$E36<=$G36),0,1),0) -> 0
A37: INP_033 | B37: 任務數成長率（不含價格） | C37: 2026 | D37: 比例/年 | E37: 1.34 | H37: Assumed | I37: — | J37: v0.6 沿用 | K37: tokenRevenue.api.demandGrowthExPrice.tasks | M37: =IF(AND(ISNUMBER($E37),ISNUMBER($F37),ISNUMBER($G37)),IF(AND($F37<=$E37,$E37<=$G37),0,1),0) -> 0
A38: INP_034 | B38: 任務數成長率（不含價格） | C38: 2027 | D38: 比例/年 | E38: 0.45 | H38: Assumed | I38: — | J38: v0.6 沿用 | K38: tokenRevenue.api.demandGrowthExPrice.tasks | M38: =IF(AND(ISNUMBER($E38),ISNUMBER($F38),ISNUMBER($G38)),IF(AND($F38<=$E38,$E38<=$G38),0,1),0) -> 0
A39: INP_035 | B39: 任務數成長率（不含價格） | C39: 2028 | D39: 比例/年 | E39: 0.35 | H39: Assumed | I39: — | J39: v0.6 沿用 | K39: tokenRevenue.api.demandGrowthExPrice.tasks | M39: =IF(AND(ISNUMBER($E39),ISNUMBER($F39),ISNUMBER($G39)),IF(AND($F39<=$E39,$E39<=$G39),0,1),0) -> 0
A40: INP_036 | B40: 任務數成長率（不含價格） | C40: 2029 | D40: 比例/年 | E40: 0.25 | H40: Assumed | I40: — | J40: v0.6 沿用 | K40: tokenRevenue.api.demandGrowthExPrice.tasks | M40: =IF(AND(ISNUMBER($E40),ISNUMBER($F40),ISNUMBER($G40)),IF(AND($F40<=$E40,$E40<=$G40),0,1),0) -> 0
A41: INP_037 | B41: 任務數成長率（不含價格） | C41: 2030 | D41: 比例/年 | E41: 0.2 | H41: Assumed | I41: — | J41: v0.6 沿用 | K41: tokenRevenue.api.demandGrowthExPrice.tasks | M41: =IF(AND(ISNUMBER($E41),ISNUMBER($F41),ISNUMBER($G41)),IF(AND($F41<=$E41,$E41<=$G41),0,1),0) -> 0
A42: INP_038 | B42: 任務數成長率（不含價格）：低情境倍數 | C42: — | D42: 倍 | E42: 0.5 | H42: Assumed | I42: — | J42: v0.6 沿用 | K42: tokenRevenue.api.demandGrowthExPrice.tasks | L42: 區間＝基準 × 倍數 | M42: =IF(AND(ISNUMBER($E42),ISNUMBER($F42),ISNUMBER($G42)),IF(AND($F42<=$E42,$E42<=$G42),0,1),0) -> 0
A43: INP_039 | B43: 任務數成長率（不含價格）：高情境倍數 | C43: — | D43: 倍 | E43: 1.5 | H43: Assumed | I43: — | J43: v0.6 沿用 | K43: tokenRevenue.api.demandGrowthExPrice.tasks | L43: 區間＝基準 × 倍數 | M43: =IF(AND(ISNUMBER($E43),ISNUMBER($F43),ISNUMBER($G43)),IF(AND($F43<=$E43,$E43<=$G43),0,1),0) -> 0
A44: INP_040 | B44: 每任務 token 成長率（不含價格） | C44: 2025 | D44: 比例/年 | E44: 0 | H44: Assumed | I44: — | J44: v0.6 沿用 | K44: tokenRevenue.api.demandGrowthExPrice.tokensPerTask | L44: 2025 欄為 0（基準年） | M44: =IF(AND(ISNUMBER($E44),ISNUMBER($F44),ISNUMBER($G44)),IF(AND($F44<=$E44,$E44<=$G44),0,1),0) -> 0
A45: INP_041 | B45: 每任務 token 成長率（不含價格） | C45: 2026 | D45: 比例/年 | E45: 0.2 | H45: Assumed | I45: — | J45: v0.6 沿用 | K45: tokenRevenue.api.demandGrowthExPrice.tokensPerTask | M45: =IF(AND(ISNUMBER($E45),ISNUMBER($F45),ISNUMBER($G45)),IF(AND($F45<=$E45,$E45<=$G45),0,1),0) -> 0
A46: INP_042 | B46: 每任務 token 成長率（不含價格） | C46: 2027 | D46: 比例/年 | E46: 0.15 | H46: Assumed | I46: — | J46: v0.6 沿用 | K46: tokenRevenue.api.demandGrowthExPrice.tokensPerTask | M46: =IF(AND(ISNUMBER($E46),ISNUMBER($F46),ISNUMBER($G46)),IF(AND($F46<=$E46,$E46<=$G46),0,1),0) -> 0
A47: INP_043 | B47: 每任務 token 成長率（不含價格） | C47: 2028 | D47: 比例/年 | E47: 0.12 | H47: Assumed | I47: — | J47: v0.6 沿用 | K47: tokenRevenue.api.demandGrowthExPrice.tokensPerTask | M47: =IF(AND(ISNUMBER($E47),ISNUMBER($F47),ISNUMBER($G47)),IF(AND($F47<=$E47,$E47<=$G47),0,1),0) -> 0
A48: INP_044 | B48: 每任務 token 成長率（不含價格） | C48: 2029 | D48: 比例/年 | E48: 0.1 | H48: Assumed | I48: — | J48: v0.6 沿用 | K48: tokenRevenue.api.demandGrowthExPrice.tokensPerTask | M48: =IF(AND(ISNUMBER($E48),ISNUMBER($F48),ISNUMBER($G48)),IF(AND($F48<=$E48,$E48<=$G48),0,1),0) -> 0
A49: INP_045 | B49: 每任務 token 成長率（不含價格） | C49: 2030 | D49: 比例/年 | E49: 0.08 | H49: Assumed | I49: — | J49: v0.6 沿用 | K49: tokenRevenue.api.demandGrowthExPrice.tokensPerTask | M49: =IF(AND(ISNUMBER($E49),ISNUMBER($F49),ISNUMBER($G49)),IF(AND($F49<=$E49,$E49<=$G49),0,1),0) -> 0
A50: INP_046 | B50: 每任務 token 成長率（不含價格）：低情境倍數 | C50: — | D50: 倍 | E50: 0.5 | H50: Assumed | I50: — | J50: v0.6 沿用 | K50: tokenRevenue.api.demandGrowthExPrice.tokensPerTask | L50: 區間＝基準 × 倍數 | M50: =IF(AND(ISNUMBER($E50),ISNUMBER($F50),ISNUMBER($G50)),IF(AND($F50<=$E50,$E50<=$G50),0,1),0) -> 0
A51: INP_047 | B51: 每任務 token 成長率（不含價格）：高情境倍數 | C51: — | D51: 倍 | E51: 1.5 | H51: Assumed | I51: — | J51: v0.6 沿用 | K51: tokenRevenue.api.demandGrowthExPrice.tokensPerTask | L51: 區間＝基準 × 倍數 | M51: =IF(AND(ISNUMBER($E51),ISNUMBER($F51),ISNUMBER($G51)),IF(AND($F51<=$E51,$E51<=$G51),0,1),0) -> 0
A52: INP_048 | B52: 價格彈性：任務數 | C52: — | D52: 彈性 | E52: -0.7 | F52: -1.05 | G52: -0.35 | H52: Assumed | I52: D11 | J52: v0.6 沿用 | K52: tokenRevenue.api.elasticity.tasks | L52: 無法由公開資料分離（價格與能力同時變動） | M52: =IF(AND(ISNUMBER($E52),ISNUMBER($F52),ISNUMBER($G52)),IF(AND($F52<=$E52,$E52<=$G52),0,1),0) -> 0
A53: INP_049 | B53: 價格彈性：每任務 token | C53: — | D53: 彈性 | E53: -0.3 | F53: -0.45 | G53: -0.15 | H53: Assumed | I53: D11 | J53: v0.6 沿用 | K53: tokenRevenue.api.elasticity.tokensPerTask | M53: =IF(AND(ISNUMBER($E53),ISNUMBER($F53),ISNUMBER($G53)),IF(AND($F53<=$E53,$E53<=$G53),0,1),0) -> 0
A54: INP_050 | B54: 價格基準（開關） | C54: — | D54: 文字（tierRole） | E54: tierRole | H54: Decision | I54: N3a | J54: v0.6 沿用 | K54: tokenRevenue.api.priceBasis | L54: 新旗艦上市視為該層價格上升，不另立層級（Decision 標記 → Inputs 開關；補充 1 第 3 點） | M54: =IF(AND(ISNUMBER($E54),ISNUMBER($F54),ISNUMBER($G54)),IF(AND($F54<=$E54,$E54<=$G54),0,1),0) -> 0
A55: INP_051 | B55: 方案對應 API 層級：free | C55: free | D55: 文字 | E55: low | H55: Assumed | I55: — | J55: v0.6 沿用 | K55: tokenRevenue.subscription.apiEquivalentTier | L55: 2026-09 各方案預設模型（定價頁說明） | M55: =IF(AND(ISNUMBER($E55),ISNUMBER($F55),ISNUMBER($G55)),IF(AND($F55<=$E55,$E55<=$G55),0,1),0) -> 0
A56: INP_052 | B56: 方案對應 API 層級：go | C56: go | D56: 文字 | E56: low | H56: Assumed | I56: — | J56: v0.6 沿用 | K56: tokenRevenue.subscription.apiEquivalentTier | L56: 2026-09 各方案預設模型（定價頁說明） | M56: =IF(AND(ISNUMBER($E56),ISNUMBER($F56),ISNUMBER($G56)),IF(AND($F56<=$E56,$E56<=$G56),0,1),0) -> 0
A57: INP_053 | B57: 方案對應 API 層級：plus | C57: plus | D57: 文字 | E57: mid | H57: Assumed | I57: — | J57: v0.6 沿用 | K57: tokenRevenue.subscription.apiEquivalentTier | L57: 2026-09 各方案預設模型（定價頁說明） | M57: =IF(AND(ISNUMBER($E57),ISNUMBER($F57),ISNUMBER($G57)),IF(AND($F57<=$E57,$E57<=$G57),0,1),0) -> 0
A58: INP_054 | B58: 方案對應 API 層級：pro | C58: pro | D58: 文字 | E58: top | H58: Assumed | I58: — | J58: v0.6 沿用 | K58: tokenRevenue.subscription.apiEquivalentTier | L58: 2026-09 各方案預設模型（定價頁說明） | M58: =IF(AND(ISNUMBER($E58),ISNUMBER($F58),ISNUMBER($G58)),IF(AND($F58<=$E58,$E58<=$G58),0,1),0) -> 0
A59: INP_055 | B59: 方案對應 API 層級：seats | C59: seats | D59: 文字 | E59: mid | H59: Assumed | I59: — | J59: v0.6 沿用 | K59: tokenRevenue.subscription.apiEquivalentTier | L59: 2026-09 各方案預設模型（定價頁說明） | M59: =IF(AND(ISNUMBER($E59),ISNUMBER($F59),ISNUMBER($G59)),IF(AND($F59<=$E59,$E59<=$G59),0,1),0) -> 0
A60: INP_056 | B60: FY 平均用戶數：free | C60: 2025 | D60: M | E60: 600 | H60: Analogy | I60: — | J60: v0.6 沿用 | K60: tokenRevenue.subscription.subsFYAvg.free | L60: ；2025 元素 Analogy（v0.5 標記） | M60: =IF(AND(ISNUMBER($E60),ISNUMBER($F60),ISNUMBER($G60)),IF(AND($F60<=$E60,$E60<=$G60),0,1),0) -> 0
A61: INP_058 | B61: FY 平均用戶數：free | C61: 2027 | D61: M | E61: 1250 | H61: Assumed | I61: — | J61: v0.6 沿用 | K61: tokenRevenue.subscription.subsFYAvg.free | L61: V9：2026+ 為 Assumed（無遷移基準） | M61: =IF(AND(ISNUMBER($E61),ISNUMBER($F61),ISNUMBER($G61)),IF(AND($F61<=$E61,$E61<=$G61),0,1),0) -> 0
A62: INP_059 | B62: FY 平均用戶數：free | C62: 2028 | D62: M | E62: 1500 | H62: Assumed | I62: — | J62: v0.6 沿用 | K62: tokenRevenue.subscription.subsFYAvg.free | L62: V9：2026+ 為 Assumed（無遷移基準） | M62: =IF(AND(ISNUMBER($E62),ISNUMBER($F62),ISNUMBER($G62)),IF(AND($F62<=$E62,$E62<=$G62),0,1),0) -> 0
A63: INP_060 | B63: FY 平均用戶數：free | C63: 2029 | D63: M | E63: 1700 | H63: Assumed | I63: — | J63: v0.6 沿用 | K63: tokenRevenue.subscription.subsFYAvg.free | L63: V9：2026+ 為 Assumed（無遷移基準） | M63: =IF(AND(ISNUMBER($E63),ISNUMBER($F63),ISNUMBER($G63)),IF(AND($F63<=$E63,$E63<=$G63),0,1),0) -> 0
A64: INP_061 | B64: FY 平均用戶數：free | C64: 2030 | D64: M | E64: 1850 | H64: Assumed | I64: — | J64: v0.6 沿用 | K64: tokenRevenue.subscription.subsFYAvg.free | L64: V9：2026+ 為 Assumed（無遷移基準） | M64: =IF(AND(ISNUMBER($E64),ISNUMBER($F64),ISNUMBER($G64)),IF(AND($F64<=$E64,$E64<=$G64),0,1),0) -> 0
A65: INP_062 | B65: FY 平均用戶數：free：低情境倍數 | C65: — | D65: 倍 | E65: 0.8 | H65: Assumed | I65: — | J65: v0.6 沿用 | K65: tokenRevenue.subscription.subsFYAvg.free | L65: 區間＝基準 × 倍數（適用 Inputs 內的年份） | M65: =IF(AND(ISNUMBER($E65),ISNUMBER($F65),ISNUMBER($G65)),IF(AND($F65<=$E65,$E65<=$G65),0,1),0) -> 0
A66: INP_063 | B66: FY 平均用戶數：free：高情境倍數 | C66: — | D66: 倍 | E66: 1.2 | H66: Assumed | I66: — | J66: v0.6 沿用 | K66: tokenRevenue.subscription.subsFYAvg.free | L66: 區間＝基準 × 倍數（適用 Inputs 內的年份） | M66: =IF(AND(ISNUMBER($E66),ISNUMBER($F66),ISNUMBER($G66)),IF(AND($F66<=$E66,$E66<=$G66),0,1),0) -> 0
A67: INP_064 | B67: FY 平均用戶數：go | C67: 2025 | D67: M | E67: 2 | H67: Assumed | I67: — | J67: v0.6 沿用 | K67: tokenRevenue.subscription.subsFYAvg.go | M67: =IF(AND(ISNUMBER($E67),ISNUMBER($F67),ISNUMBER($G67)),IF(AND($F67<=$E67,$E67<=$G67),0,1),0) -> 0
A68: INP_065 | B68: FY 平均用戶數：go | C68: 2026 | D68: M | E68: 10 | H68: Assumed | I68: — | J68: v0.6 沿用 | K68: tokenRevenue.subscription.subsFYAvg.go | L68: V9：2026+ 為 Assumed（無遷移基準） | M68: =IF(AND(ISNUMBER($E68),ISNUMBER($F68),ISNUMBER($G68)),IF(AND($F68<=$E68,$E68<=$G68),0,1),0) -> 0
A69: INP_066 | B69: FY 平均用戶數：go | C69: 2027 | D69: M | E69: 22 | H69: Assumed | I69: — | J69: v0.6 沿用 | K69: tokenRevenue.subscription.subsFYAvg.go | L69: V9：2026+ 為 Assumed（無遷移基準） | M69: =IF(AND(ISNUMBER($E69),ISNUMBER($F69),ISNUMBER($G69)),IF(AND($F69<=$E69,$E69<=$G69),0,1),0) -> 0
A70: INP_067 | B70: FY 平均用戶數：go | C70: 2028 | D70: M | E70: 35 | H70: Assumed | I70: — | J70: v0.6 沿用 | K70: tokenRevenue.subscription.subsFYAvg.go | L70: V9：2026+ 為 Assumed（無遷移基準） | M70: =IF(AND(ISNUMBER($E70),ISNUMBER($F70),ISNUMBER($G70)),IF(AND($F70<=$E70,$E70<=$G70),0,1),0) -> 0
A71: INP_068 | B71: FY 平均用戶數：go | C71: 2029 | D71: M | E71: 45 | H71: Assumed | I71: — | J71: v0.6 沿用 | K71: tokenRevenue.subscription.subsFYAvg.go | L71: V9：2026+ 為 Assumed（無遷移基準） | M71: =IF(AND(ISNUMBER($E71),ISNUMBER($F71),ISNUMBER($G71)),IF(AND($F71<=$E71,$E71<=$G71),0,1),0) -> 0
A72: INP_069 | B72: FY 平均用戶數：go | C72: 2030 | D72: M | E72: 55 | H72: Assumed | I72: — | J72: v0.6 沿用 | K72: tokenRevenue.subscription.subsFYAvg.go | L72: V9：2026+ 為 Assumed（無遷移基準） | M72: =IF(AND(ISNUMBER($E72),ISNUMBER($F72),ISNUMBER($G72)),IF(AND($F72<=$E72,$E72<=$G72),0,1),0) -> 0
A73: INP_070 | B73: FY 平均用戶數：go：低情境倍數 | C73: — | D73: 倍 | E73: 0.6 | H73: Assumed | I73: — | J73: v0.6 沿用 | K73: tokenRevenue.subscription.subsFYAvg.go | L73: 區間＝基準 × 倍數（適用 Inputs 內的年份） | M73: =IF(AND(ISNUMBER($E73),ISNUMBER($F73),ISNUMBER($G73)),IF(AND($F73<=$E73,$E73<=$G73),0,1),0) -> 0
A74: INP_071 | B74: FY 平均用戶數：go：高情境倍數 | C74: — | D74: 倍 | E74: 1.5 | H74: Assumed | I74: — | J74: v0.6 沿用 | K74: tokenRevenue.subscription.subsFYAvg.go | L74: 區間＝基準 × 倍數（適用 Inputs 內的年份） | M74: =IF(AND(ISNUMBER($E74),ISNUMBER($F74),ISNUMBER($G74)),IF(AND($F74<=$E74,$E74<=$G74),0,1),0) -> 0
A75: INP_073 | B75: FY 平均用戶數：plus | C75: 2026 | D75: M | E75: 46 | H75: Assumed | I75: — | J75: v0.6 沿用 | K75: tokenRevenue.subscription.subsFYAvg.plus | L75: V9：2026+ 為 Assumed（無遷移基準） | M75: =IF(AND(ISNUMBER($E75),ISNUMBER($F75),ISNUMBER($G75)),IF(AND($F75<=$E75,$E75<=$G75),0,1),0) -> 0
A76: INP_074 | B76: FY 平均用戶數：plus | C76: 2027 | D76: M | E76: 52 | H76: Assumed | I76: — | J76: v0.6 沿用 | K76: tokenRevenue.subscription.subsFYAvg.plus | L76: V9：2026+ 為 Assumed（無遷移基準） | M76: =IF(AND(ISNUMBER($E76),ISNUMBER($F76),ISNUMBER($G76)),IF(AND($F76<=$E76,$E76<=$G76),0,1),0) -> 0
A77: INP_075 | B77: FY 平均用戶數：plus | C77: 2028 | D77: M | E77: 57 | H77: Assumed | I77: — | J77: v0.6 沿用 | K77: tokenRevenue.subscription.subsFYAvg.plus | L77: V9：2026+ 為 Assumed（無遷移基準） | M77: =IF(AND(ISNUMBER($E77),ISNUMBER($F77),ISNUMBER($G77)),IF(AND($F77<=$E77,$E77<=$G77),0,1),0) -> 0
A78: INP_076 | B78: FY 平均用戶數：plus | C78: 2029 | D78: M | E78: 61 | H78: Assumed | I78: — | J78: v0.6 沿用 | K78: tokenRevenue.subscription.subsFYAvg.plus | L78: V9：2026+ 為 Assumed（無遷移基準） | M78: =IF(AND(ISNUMBER($E78),ISNUMBER($F78),ISNUMBER($G78)),IF(AND($F78<=$E78,$E78<=$G78),0,1),0) -> 0
A79: INP_077 | B79: FY 平均用戶數：plus | C79: 2030 | D79: M | E79: 64 | H79: Assumed | I79: — | J79: v0.6 沿用 | K79: tokenRevenue.subscription.subsFYAvg.plus | L79: V9：2026+ 為 Assumed（無遷移基準） | M79: =IF(AND(ISNUMBER($E79),ISNUMBER($F79),ISNUMBER($G79)),IF(AND($F79<=$E79,$E79<=$G79),0,1),0) -> 0
... A81: INP_079 | B81: FY 平均用戶數：plus：高情境倍數 | C81: — | D81: 倍 | E81: 1.15 | H81: Assumed | I81: — | J81: v0.6 沿用 | K81: tokenRevenue.subscription.subsFYAvg.plus | L81: 區間＝基準 × 倍數（適用 Inputs 內的年份） | M81: =IF(AND(ISNUMBER($E81),ISNUMBER($F81),ISNUMBER($G81)),IF(AND($F81<=$E81,$E81<=$G81),0,1),0) -> 0
A82: INP_088 | B82: FY 平均用戶數：seats | C82: 2025 | D82: M | E82: 3 | H82: Assumed | I82: — | J82: v0.6 沿用 | K82: tokenRevenue.subscription.subsFYAvg.seats | M82: =IF(AND(ISNUMBER($E82),ISNUMBER($F82),ISNUMBER($G82)),IF(AND($F82<=$E82,$E82<=$G82),0,1),0) -> 0
A83: INP_089 | B83: FY 平均用戶數：seats | C83: 2026 | D83: M | E83: 14 | H83: Assumed | I83: — | J83: v0.6 沿用 | K83: tokenRevenue.subscription.subsFYAvg.seats | L83: V9：2026+ 為 Assumed（無遷移基準） | M83: =IF(AND(ISNUMBER($E83),ISNUMBER($F83),ISNUMBER($G83)),IF(AND($F83<=$E83,$E83<=$G83),0,1),0) -> 0
A84: INP_090 | B84: FY 平均用戶數：seats | C84: 2027 | D84: M | E84: 26 | H84: Assumed | I84: — | J84: v0.6 沿用 | K84: tokenRevenue.subscription.subsFYAvg.seats | L84: V9：2026+ 為 Assumed（無遷移基準） | M84: =IF(AND(ISNUMBER($E84),ISNUMBER($F84),ISNUMBER($G84)),IF(AND($F84<=$E84,$E84<=$G84),0,1),0) -> 0
A85: INP_091 | B85: FY 平均用戶數：seats | C85: 2028 | D85: M | E85: 38 | H85: Assumed | I85: — | J85: v0.6 沿用 | K85: tokenRevenue.subscription.subsFYAvg.seats | L85: V9：2026+ 為 Assumed（無遷移基準） | M85: =IF(AND(ISNUMBER($E85),ISNUMBER($F85),ISNUMBER($G85)),IF(AND($F85<=$E85,$E85<=$G85),0,1),0) -> 0
A86: INP_092 | B86: FY 平均用戶數：seats | C86: 2029 | D86: M | E86: 48 | H86: Assumed | I86: — | J86: v0.6 沿用 | K86: tokenRevenue.subscription.subsFYAvg.seats | L86: V9：2026+ 為 Assumed（無遷移基準） | M86: =IF(AND(ISNUMBER($E86),ISNUMBER($F86),ISNUMBER($G86)),IF(AND($F86<=$E86,$E86<=$G86),0,1),0) -> 0
A87: INP_093 | B87: FY 平均用戶數：seats | C87: 2030 | D87: M | E87: 56 | H87: Assumed | I87: — | J87: v0.6 沿用 | K87: tokenRevenue.subscription.subsFYAvg.seats | L87: V9：2026+ 為 Assumed（無遷移基準） | M87: =IF(AND(ISNUMBER($E87),ISNUMBER($F87),ISNUMBER($G87)),IF(AND($F87<=$E87,$E87<=$G87),0,1),0) -> 0
A88: INP_094 | B88: FY 平均用戶數：seats：低情境倍數 | C88: — | D88: 倍 | E88: 0.7 | H88: Assumed | I88: — | J88: v0.6 沿用 | K88: tokenRevenue.subscription.subsFYAvg.seats | L88: 區間＝基準 × 倍數（適用 Inputs 內的年份） | M88: =IF(AND(ISNUMBER($E88),ISNUMBER($F88),ISNUMBER($G88)),IF(AND($F88<=$E88,$E88<=$G88),0,1),0) -> 0
A89: INP_095 | B89: FY 平均用戶數：seats：高情境倍數 | C89: — | D89: 倍 | E89: 1.3 | H89: Assumed | I89: — | J89: v0.6 沿用 | K89: tokenRevenue.subscription.subsFYAvg.seats | L89: 區間＝基準 × 倍數（適用 Inputs 內的年份） | M89: =IF(AND(ISNUMBER($E89),ISNUMBER($F89),ISNUMBER($G89)),IF(AND($F89<=$E89,$E89<=$G89),0,1),0) -> 0
A90: INP_096 | B90: ARPU（實收）：go | C90: 全期 | D90: $/月 | E90: 6 | F90: 4 | G90: 8 | H90: Assumed | I90: — | J90: v0.6 沿用 | K90: tokenRevenue.subscription.arpu.go | M90: =IF(AND(ISNUMBER($E90),ISNUMBER($F90),ISNUMBER($G90)),IF(AND($F90<=$E90,$E90<=$G90),0,1),0) -> 0
A91: INP_097 | B91: ARPU（實收）：plus | C91: 2025 | D91: $/月 | E91: 19.5 | F91: 18 | G91: 20 | H91: Assumed | I91: — | J91: v0.6 沿用 | K91: tokenRevenue.subscription.arpu.plus | M91: =IF(AND(ISNUMBER($E91),ISNUMBER($F91),ISNUMBER($G91)),IF(AND($F91<=$E91,$E91<=$G91),0,1),0) -> 0
A92: INP_098 | B92: ARPU（實收）：plus | C92: 2026 起（v0.5 未標年份；待 P2 確認） | D92: $/月 | E92: 19 | F92: 17 | G92: 20 | H92: Assumed | I92: — | J92: v0.6 沿用 | K92: tokenRevenue.subscription.arpu.plus | M92: =IF(AND(ISNUMBER($E92),ISNUMBER($F92),ISNUMBER($G92)),IF(AND($F92<=$E92,$E92<=$G92),0,1),0) -> 0
A93: INP_099 | B93: ARPU（實收）：pro | C93: 2025 | D93: $/月 | E93: 200 | F93: 200 | G93: 200 | H93: Assumed | I93: — | J93: v0.6 沿用 | K93: tokenRevenue.subscription.arpu.pro | M93: =IF(AND(ISNUMBER($E93),ISNUMBER($F93),ISNUMBER($G93)),IF(AND($F93<=$E93,$E93<=$G93),0,1),0) -> 0
A94: INP_100 | B94: ARPU（實收）：pro | C94: 2026 起（v0.5 未標年份；待 P2 確認） | D94: $/月 | E94: 150 | F94: 120 | G94: 190 | H94: Assumed | I94: — | J94: v0.6 沿用 | K94: tokenRevenue.subscription.arpu.pro | M94: =IF(AND(ISNUMBER($E94),ISNUMBER($F94),ISNUMBER($G94)),IF(AND($F94<=$E94,$E94<=$G94),0,1),0) -> 0
A95: INP_101 | B95: ARPU（實收）：seats | C95: 全期 | D95: $/月 | E95: 30 | F95: 22 | G95: 45 | H95: Assumed | I95: — | J95: v0.6 沿用 | K95: tokenRevenue.subscription.arpu.seats | M95: =IF(AND(ISNUMBER($E95),ISNUMBER($F95),ISNUMBER($G95)),IF(AND($F95<=$E95,$E95<=$G95),0,1),0) -> 0
A96: INP_102 | B96: 每日任務數：free | C96: 2025 | D96: 任務/日 | E96: 1.7 | H96: Assumed | I96: — | J96: v0.6 沿用 | K96: tokenRevenue.subscription.tasksPerDay.free | L96: 2027 起年增（見成長率） | M96: =IF(AND(ISNUMBER($E96),ISNUMBER($F96),ISNUMBER($G96)),IF(AND($F96<=$E96,$E96<=$G96),0,1),0) -> 0
A97: INP_103 | B97: 每日任務數：free | C97: 2026 | D97: 任務/日 | E97: 1.7 | H97: Assumed | I97: — | J97: v0.6 沿用 | K97: tokenRevenue.subscription.tasksPerDay.free | L97: 2027 起年增（見成長率） | M97: =IF(AND(ISNUMBER($E97),ISNUMBER($F97),ISNUMBER($G97)),IF(AND($F97<=$E97,$E97<=$G97),0,1),0) -> 0
A98: INP_104 | B98: 每日任務數：go | C98: 2025 | D98: 任務/日 | E98: 5.3 | H98: Assumed | I98: — | J98: v0.6 沿用 | K98: tokenRevenue.subscription.tasksPerDay.go | L98: 2027 起年增（見成長率） | M98: =IF(AND(ISNUMBER($E98),ISNUMBER($F98),ISNUMBER($G98)),IF(AND($F98<=$E98,$E98<=$G98),0,1),0) -> 0
A99: INP_105 | B99: 每日任務數：go | C99: 2026 | D99: 任務/日 | E99: 5.7 | H99: Assumed | I99: — | J99: v0.6 沿用 | K99: tokenRevenue.subscription.tasksPerDay.go | L99: 2027 起年增（見成長率） | M99: =IF(AND(ISNUMBER($E99),ISNUMBER($F99),ISNUMBER($G99)),IF(AND($F99<=$E99,$E99<=$G99),0,1),0) -> 0
A100: INP_106 | B100: 每日任務數：plus | C100: 2025 | D100: 任務/日 | E100: 13.4 | H100: Assumed | I100: — | J100: v0.6 沿用 | K100: tokenRevenue.subscription.tasksPerDay.plus | L100: 2027 起年增（見成長率） | M100: =IF(AND(ISNUMBER($E100),ISNUMBER($F100),ISNUMBER($G100)),IF(AND($F100<=$E100,$E100<=$G100),0,1),0) -> 0
A101: INP_107 | B101: 每日任務數：plus | C101: 2026 | D101: 任務/日 | E101: 17.9 | H101: Assumed | I101: — | J101: v0.6 沿用 | K101: tokenRevenue.subscription.tasksPerDay.plus | L101: 2027 起年增（見成長率） | M101: =IF(AND(ISNUMBER($E101),ISNUMBER($F101),ISNUMBER($G101)),IF(AND($F101<=$E101,$E101<=$G101),0,1),0) -> 0
...

Sheet Derived_V9
A1: Derived_V9 — 跨年混合項目與 Derived 項目的公式（V9、V12、V15、E8）；v0.5 原值並列
A2: E6：公式不內含常數（算式中的 1－比例 為恆等式），換算係數與比例都在 Inputs（標記＋區間）。『v0.5 原值』欄為 builder 由 v0.5 JSON 寫入的對照常數，不參與計算。
A3: 月營收單位 $M/月＝人數（M）× ARPU（$/月）；年營收＝月營收×月數，月數換算只在報告文字，不進公式。
A4: 編號 | B4: 項目 | C4: 值（公式） | D4: v0.5 原值（對照） | E4: 差距＝值−v0.5（公式） | F4: 單位 | G4: 說明
A5: V01 | B5: free FY2026 平均用戶（M）＝WAU×換算係數 | C5: =SRC_OAI_092*INP_234 -> 950 | D5: 950 | E5: =IF(ISNUMBER(C5),C5-D5,"—") -> 0 | F5: M | G5: SRC_OAI WAU × Inputs 換算係數
A6: V02 | B6: Plus FY2025 平均用戶（M）＝2025-07 Plus＋Pro×換算係數 | C6: =SRC_OAI_094*INP_235 -> 30 | D6: 30 | E6: =IF(ISNUMBER(C6),C6-D6,"—") -> 0 | F6: M | G6: SRC_OAI 35M × Inputs 換算係數
A7: V03 | B7: Pro FY2026 用戶（M）＝比例×付費總數（含席位） | C7: =INP_236/(1-INP_236)*(INP_065+INP_073+INP_089) -> 0.56451613 | D7: 1 | E7: =IF(ISNUMBER(C7),C7-D7,"—") -> -0.43548387 | F7: M | G7: 付費總數＝go＋plus＋seats＋pro；pro＝比例×總數 ⇒ pro＝比例/(1−比例)×(go＋plus＋seats)，無循環
A8: V04 | B8: Pro FY2025 用戶（M）＝2026÷SRC 倍數 | C8: =C7/SRC_OAI_101 -> 0.28225806 | D8: 0.5 | E8: =IF(ISNUMBER(C8),C8-D8,"—") -> -0.21774194 | F8: M | G8: SRC_OAI 倍增約束
A9: V05 | B9: Pro 占付費總數 2026（含席位） | C9: =C7/((INP_065+INP_073+INP_089)+C7) -> 0.008 | D9: 0.014084507 | E9: =IF(ISNUMBER(C9),C9-D9,"—") -> -0.006084507 | F9: 比例 | G9: v0.5 原值欄為 v0.5 pro 1.0 ÷ (go＋plus＋seats＋pro)
A10: V06 | B10: 約束檢查：Pro 占比超出 SRC 上限的部分（0＝符合） | C10: =C9-MIN(C9,SRC_OAI!$E$100) -> 0 | G10: SRC_OAI『<1%』上限（僅 2026）
A11: V07 | B11: v0.5 原值對約束的差距（百分點）＝v0.5 占比−SRC 上限 | C11: =(D9-SRC_OAI!$E$100) -> 0.004084507 | F11: 比例 | G11: 正值＝v0.5 原值超出內部預測所稱『<1%』
A12: V08 | B12: Pro 月訂閱營收 2025（$M/月）＝用戶×ARPU | C12: =C8*INP_099 -> 56.451613 | D12: 100 | E12: =IF(ISNUMBER(C12),C12-D12,"—") -> -43.548387 | F12: $M/月 | G12: ARPU 為 Inputs（2025 欄）
A13: V09 | B13: Pro 月訂閱營收 2026（$M/月）＝用戶×ARPU | C13: =C7*INP_100 -> 84.677419 | D13: 150 | E13: =IF(ISNUMBER(C13),C13-D13,"—") -> -65.322581 | F13: $M/月 | G13: ARPU 為 Inputs（2026 起欄）
A14: V10 | B14: Pro FY2027 用戶（M）＝比例_t/(1−比例_t)×(go＋plus＋seats) | C14: =INP_240/(1-INP_240)*(INP_066+INP_074+INP_090) -> 0.80645161 | D14: 1.5 | E14: =IF(ISNUMBER(C14),C14-D14,"—") -> -0.69354839 | F14: M | G14: V15：逐年比例（Inputs，0.5–2.0%）
A15: V11 | B15: Pro FY2028 用戶（M）＝比例_t/(1−比例_t)×(go＋plus＋seats) | C15: =INP_241/(1-INP_241)*(INP_067+INP_075+INP_091) -> 1.0483871 | D15: 2 | E15: =IF(ISNUMBER(C15),C15-D15,"—") -> -0.9516129 | F15: M | G15: V15：逐年比例（Inputs，0.5–2.0%）
A16: V12 | B16: Pro FY2029 用戶（M）＝比例_t/(1−比例_t)×(go＋plus＋seats) | C16: =INP_242/(1-INP_242)*(INP_068+INP_076+INP_092) -> 1.2419355 | D16: 2.5 | E16: =IF(ISNUMBER(C16),C16-D16,"—") -> -1.2580645 | F16: M | G16: V15：逐年比例（Inputs，0.5–2.0%）
A17: V13 | B17: Pro FY2030 用戶（M）＝比例_t/(1−比例_t)×(go＋plus＋seats) | C17: =INP_243/(1-INP_243)*(INP_069+INP_077+INP_093) -> 1.4112903 | D17: 3 | E17: =IF(ISNUMBER(C17),C17-D17,"—") -> -1.5887097 | F17: M | G17: V15：逐年比例（Inputs，0.5–2.0%）
A18: V14 | B18: Pro 占付費總數 2027（含席位） | C18: =C14/((INP_066+INP_074+INP_090)+C14) -> 0.008 | D18: 0.014778325 | E18: =IF(ISNUMBER(C18),C18-D18,"—") -> -0.0067783251 | F18: 比例 | G18: v0.5 原值欄＝v0.5 pro ÷ (go＋plus＋seats＋pro)（約 1.48%→1.7%）
A19: V15 | B19: Pro 占付費總數 2028（含席位） | C19: =C15/((INP_067+INP_075+INP_091)+C15) -> 0.008 | D19: 0.015151515 | E19: =IF(ISNUMBER(C19),C19-D19,"—") -> -0.0071515152 | F19: 比例 | G19: v0.5 原值欄＝v0.5 pro ÷ (go＋plus＋seats＋pro)（約 1.48%→1.7%）
A20: V16 | B20: Pro 占付費總數 2029（含席位） | C20: =C16/((INP_068+INP_076+INP_092)+C16) -> 0.008 | D20: 0.015974441 | E20: =IF(ISNUMBER(C20),C20-D20,"—") -> -0.0079744409 | F20: 比例 | G20: v0.5 原值欄＝v0.5 pro ÷ (go＋plus＋seats＋pro)（約 1.48%→1.7%）
A21: V17 | B21: Pro 占付費總數 2030（含席位） | C21: =C17/((INP_069+INP_077+INP_093)+C17) -> 0.008 | D21: 0.016853933 | E21: =IF(ISNUMBER(C21),C21-D21,"—") -> -0.0088539326 | F21: 比例 | G21: v0.5 原值欄＝v0.5 pro ÷ (go＋plus＋seats＋pro)（約 1.48%→1.7%）
A22: V18 | B22: Pro 月訂閱營收 2027（$M/月）＝用戶×ARPU | C22: =C14*INP_100 -> 120.96774 | D22: 225 | E22: =IF(ISNUMBER(C22),C22-D22,"—") -> -104.03226 | F22: $M/月 | G22: ARPU 為 Inputs（2026 起欄）
A23: V19 | B23: Pro 月訂閱營收 2028（$M/月）＝用戶×ARPU | C23: =C15*INP_100 -> 157.25806 | D23: 300 | E23: =IF(ISNUMBER(C23),C23-D23,"—") -> -142.74194 | F23: $M/月 | G23: ARPU 為 Inputs（2026 起欄）
A24: V20 | B24: Pro 月訂閱營收 2029（$M/月）＝用戶×ARPU | C24: =C16*INP_100 -> 186.29032 | D24: 375 | E24: =IF(ISNUMBER(C24),C24-D24,"—") -> -188.70968 | F24: $M/月 | G24: ARPU 為 Inputs（2026 起欄）
A25: V21 | B25: Pro 月訂閱營收 2030（$M/月）＝用戶×ARPU | C25: =C17*INP_100 -> 211.69355 | D25: 450 | E25: =IF(ISNUMBER(C25),C25-D25,"—") -> -238.30645 | F25: $M/月 | G25: ARPU 為 Inputs（2026 起欄）
A26: V22 | B26: API FY2025 token（T）＝每分鐘 token×每年分鐘數÷單位換算 | C26: =INP_237*INP_238/INP_239 -> 2628 | D26: 2628 | E26: =IF(ISNUMBER(C26),C26-D26,"—") -> 0 | F26: T | G26: E8a：驅動值＝Inputs 5B/min
A27: V23 | B27: API FY2025 token 低（T） | C27: =Inputs!$F$229*INP_238/INP_239 -> 1997.28 | D27: 2000 | E27: =IF(ISNUMBER(C27),C27-D27,"—") -> -2.72 | F27: T | G27: E8a：驅動值低端 3.8
A28: V24 | B28: API FY2025 token 高（T） | C28: =Inputs!$G$229*INP_238/INP_239 -> 3206.16 | D28: 3200 | E28: =IF(ISNUMBER(C28),C28-D28,"—") -> 6.16 | F28: T | G28: E8a：驅動值高端 6.1
A29: V25 | B29: Oracle 合約年額（$B/年）＝總額÷年數 | C29: =IF(SRC_OAI_060>=SRC_OAI_059,SRC_OAI_058/(SRC_OAI_060-SRC_OAI_059+1),"期間無效") -> 60 | D29: 60 | E29: =IF(ISNUMBER(C29),C29-D29,"—") -> 0 | F29: $B | G29: E8f：v0.5 以數值 60 寫入，改公式
A30: V26 | B30: AWS Trainium WSJ 口徑合計 GW＝推論＋訓練 | C30: =SRC_OAI_103+SRC_OAI_104 -> 5 | D30: 5 | E30: =IF(ISNUMBER(C30),C30-D30,"—") -> 0 | F30: GW | G30: E8g：『5』改公式（v0.5 區間上緣 5）
A31: V27 | B31: 2026-03 輪無條件部分＝四個組成加總 | C31: =SRC_OAI_109+SRC_OAI_110+SRC_OAI_111+SRC_OAI_112 -> 87 | D31: 87 | E31: =IF(ISNUMBER(C31),C31-D31,"—") -> 0 | F31: $B | G31: E8j：87 拆為 SRC 組成

Sheet Demand
A1: Demand — 需求：訂閱各方案人數、每日任務數 × 每任務 token、API 任務數與計費 token；token 量（層級 × 付費／免費）
A2: 機制沿用 v0.5「訂閱與廣告」「API」頁（D、N、S 決定）。2025 為校準年：API 計費 token 由 FY2025 實際營收倒推（v0.5 唯一倒推）。2027 起需求成長（不含價格）× 價格反應 (p/p前)^ε。免費用戶只產生 token 需求，不產生訂閱營收。
A3: token 單位 T＝10^12；人數 M＝百萬；任務數（API）十億。v0.5 原值欄（K–P）為 v0.5 Excel 快取值，只作對照。容量上限（V1a）於 P3 加入，本頁不截頂。
A5: 編號 | B5: 項目 | C5: 單位 | D5: 2025 | E5: 2026 | F5: 2027 | G5: 2028 | H5: 2029 | I5: 2030 | K5: v0.5 2025 | L5: v0.5 2026 | M5: v0.5 2027 | N5: v0.5 2028 | O5: v0.5 2029 | P5: v0.5 2030 | Q5: 說明
B6: 年度 | D6: =INP_005 -> 2025 | E6: =INP_006 -> 2026 | F6: =INP_007 -> 2027 | G6: =INP_008 -> 2028 | H6: =INP_009 -> 2029 | I6: =INP_010 -> 2030
A7: 一、訂閱人數（M，FY 平均；T4：2026 起 Plus→Go 遷移與 Go 額外新增）
A8: D01 | B8: 遷移率 μ（Plus→Go） | C8: 比例 | E8: =INP_013*(1-SRC_OAI_037/INP_073) -> 0.24130435 | F8: =INP_013*(1-SRC_OAI_037/INP_073) -> 0.24130435 | G8: =INP_013*(1-SRC_OAI_037/INP_073) -> 0.24130435 | H8: =INP_013*(1-SRC_OAI_037/INP_073) -> 0.24130435 | I8: =INP_013*(1-SRC_OAI_037/INP_073) -> 0.24130435 | L8: 0.24130435 | M8: 0.24130435 | N8: 0.24130435 | O8: 0.24130435 | P8: 0.24130435 | Q8: 計畫幅度（Inputs 基準 0.3）×（1 − 公司計畫 Plus ÷ 無遷移 Plus 2026）；2026 起各年同值（v0.5）
A9: D02 | B9: Go 額外新增倍數 λ | C9: 倍 | E9: =INP_013*(SRC_OAI_036-INP_073*(1-SRC_OAI_037/INP_073)-INP_065)/INP_065 -> 1.95 | F9: =INP_013*(SRC_OAI_036-INP_073*(1-SRC_OAI_037/INP_073)-INP_065)/INP_065 -> 1.95 | G9: =INP_013*(SRC_OAI_036-INP_073*(1-SRC_OAI_037/INP_073)-INP_065)/INP_065 -> 1.95 | H9: =INP_013*(SRC_OAI_036-INP_073*(1-SRC_OAI_037/INP_073)-INP_065)/INP_065 -> 1.95 | I9: =INP_013*(SRC_OAI_036-INP_073*(1-SRC_OAI_037/INP_073)-INP_065)/INP_065 -> 1.95 | L9: 1.95 | M9: 1.95 | N9: 1.95 | O9: 1.95 | P9: 1.95 | Q9: ＝計畫幅度 ×（公司計畫 Go −（無遷移 Plus 2026 − 公司計畫 Plus）− 無遷移 Go 2026）÷ 無遷移 Go 2026；計畫幅度＝1 時，2026 Go 恰等於公司計畫 112M（v0.5；與 v0.5 寫法代數相同）
A10: D03 | B10: Free 人數 | C10: M | D10: =INP_056 -> 600 | E10: =V9_Free2026 -> 950 | F10: =INP_058 -> 1250 | G10: =INP_059 -> 1500 | H10: =INP_060 -> 1700 | I10: =INP_061 -> 1850 | K10: 600 | L10: 950 | M10: 1250 | N10: 1500 | O10: 1700 | P10: 1850 | Q10: 2025、2027+ Inputs；2026＝SRC WAU × 換算係數（Derived_V9 V01）
A11: D04 | B11: Go 人數 | C11: M | D11: =INP_064 -> 2 | E11: =INP_065*(1+E9)+INP_073*E8 -> 40.6 | F11: =INP_066*(1+F9)+INP_074*F8 -> 77.447826 | G11: =INP_067*(1+G9)+INP_075*G8 -> 117.00435 | H11: =INP_068*(1+H9)+INP_076*H8 -> 147.46957 | I11: =INP_069*(1+I9)+INP_077*I8 -> 177.69348 | K11: 2 | L11: 40.6 | M11: 77.447826 | N11: 117.00435 | O11: 147.46957 | P11: 177.69348 | Q11: 2026 起＝無遷移 Go ×（1＋λ）＋無遷移 Plus × μ
A12: D05 | B12: Plus 人數 | C12: M | D12: =V9_Plus2025 -> 30 | E12: =INP_073*(1-E8) -> 34.9 | F12: =INP_074*(1-F8) -> 39.452174 | G12: =INP_075*(1-G8) -> 43.245652 | H12: =INP_076*(1-H8) -> 46.280435 | I12: =INP_077*(1-I8) -> 48.556522 | K12: 30 | L12: 34.9 | M12: 39.452174 | N12: 43.245652 | O12: 46.280435 | P12: 48.556522 | Q12: 2025＝Derived_V9 V02（SRC 35M × 換算係數）；2026 起＝無遷移 Plus ×（1 − μ）
A13: D06 | B13: Pro 人數 | C13: M | D13: =V9_Pro2025 -> 0.28225806 | E13: =V9_Pro2026 -> 0.56451613 | F13: =V9_Pro2027 -> 0.80645161 | G13: =V9_Pro2028 -> 1.0483871 | H13: =V9_Pro2029 -> 1.2419355 | I13: =V9_Pro2030 -> 1.4112903 | K13: 0.5 | L13: 1 | M13: 1.5 | N13: 2 | O13: 2.5 | P13: 3 | Q13: V12／V15：占比 × 付費總數（Derived_V9 V03、V04、V10–V13；付費總數口徑＝無遷移基準，沿用 P1 已審公式）
A14: D07 | B14: 企業席位人數 | C14: M | D14: =INP_088 -> 3 | E14: =INP_089 -> 14 | F14: =INP_090 -> 26 | G14: =INP_091 -> 38 | H14: =INP_092 -> 48 | I14: =INP_093 -> 56 | K14: 3 | L14: 14 | M14: 26 | N14: 38 | O14: 48 | P14: 56 | Q14: Inputs
A15: D08 | B15: 付費人數合計（Go＋Plus＋Pro＋席位） | C15: M | D15: =D11+D12+D13+D14 -> 35.282258 | E15: =E11+E12+E13+E14 -> 90.064516 | F15: =F11+F12+F13+F14 -> 143.70645 | G15: =G11+G12+G13+G14 -> 199.29839 | H15: =H11+H12+H13+H14 -> 242.99194 | I15: =I11+I12+I13+I14 -> 283.66129
A16: D09 | B16: 消費端付費人數（Go＋Plus＋Pro） | C16: M | D16: =D11+D12+D13 -> 32.282258 | E16: =E11+E12+E13 -> 76.064516 | F16: =F11+F12+F13 -> 117.70645 | G16: =G11+G12+G13 -> 161.29839 | H16: =H11+H12+H13 -> 194.99194 | I16: =I11+I12+I13 -> 227.66129 | K16: 32.5 | L16: 76.5 | M16: 118.4 | N16: 162.25 | O16: 196.25 | P16: 229.25
A17: 二、訂閱使用量：每日任務數 × 每任務 token（2025、2026 為 Inputs；2027 起年增）
A18: D10 | B18: Free 每日任務數 | C18: 任務/日 | D18: =INP_102 -> 1.7 | E18: =INP_103 -> 1.7 | F18: =E18*(1+INP_122) -> 1.87 | G18: =F18*(1+INP_122) -> 2.057 | H18: =G18*(1+INP_122) -> 2.2627 | I18: =H18*(1+INP_122) -> 2.48897 | K18: 1.7 | L18: 1.7 | M18: 1.87 | N18: 2.057 | O18: 2.2627 | P18: 2.48897 | Q18: 2027 起 ×（1＋每日任務數年增率）
A19: D11 | B19: Go 每日任務數 | C19: 任務/日 | D19: =INP_104 -> 5.3 | E19: =INP_105 -> 5.7 | F19: =E19*(1+INP_122) -> 6.27 | G19: =F19*(1+INP_122) -> 6.897 | H19: =G19*(1+INP_122) -> 7.5867 | I19: =H19*(1+INP_122) -> 8.34537 | K19: 5.3 | L19: 5.7 | M19: 6.27 | N19: 6.897 | O19: 7.5867 | P19: 8.34537 | Q19: 2027 起 ×（1＋每日任務數年增率）
A20: D12 | B20: Plus 每日任務數 | C20: 任務/日 | D20: =INP_106 -> 13.4 | E20: =INP_107 -> 17.9 | F20: =E20*(1+INP_122) -> 19.69 | G20: =F20*(1+INP_122) -> 21.659 | H20: =G20*(1+INP_122) -> 23.8249 | I20: =H20*(1+INP_122) -> 26.20739 | K20: 13.4 | L20: 17.9 | M20: 19.69 | N20: 21.659 | O20: 23.8249 | P20: 26.20739 | Q20: 2027 起 ×（1＋每日任務數年增率）
A21: D13 | B21: Pro 每日任務數 | C21: 任務/日 | D21: =INP_108 -> 41 | E21: =INP_109 -> 51.4 | F21: =E21*(1+INP_122) -> 56.54 | G21: =F21*(1+INP_122) -> 62.194 | H21: =G21*(1+INP_122) -> 68.4134 | I21: =H21*(1+INP_122) -> 75.25474 | K21: 41 | L21: 51.4 | M21: 56.54 | N21: 62.194 | O21: 68.4134 | P21: 75.25474 | Q21: 2027 起 ×（1＋每日任務數年增率）
A22: D14 | B22: 企業席位 每日任務數 | C22: 任務/日 | D22: =INP_110 -> 10.7 | E22: =INP_111 -> 14.3 | F22: =E22*(1+INP_122) -> 15.73 | G22: =F22*(1+INP_122) -> 17.303 | H22: =G22*(1+INP_122) -> 19.0333 | I22: =H22*(1+INP_122) -> 20.93663 | K22: 10.7 | L22: 14.3 | M22: 15.73 | N22: 17.303 | O22: 19.0333 | P22: 20.93663 | Q22: 2027 起 ×（1＋每日任務數年增率）
A23: D15 | B23: Free 每任務 token | C23: K tok/任務 | D23: =INP_112 -> 2 | E23: =INP_113 -> 2.94 | F23: =E23*(1+INP_123) -> 3.381 | G23: =F23*(1+INP_123) -> 3.88815 | H23: =G23*(1+INP_123) -> 4.4713725 | I23: =H23*(1+INP_123) -> 5.1420784 | K23: 2 | L23: 2.94 | M23: 3.381 | N23: 3.88815 | O23: 4.4713725 | P23: 5.1420784 | Q23: 2027 起 ×（1＋每任務 token 年增率；D11 情境軸）
A24: D16 | B24: Go 每任務 token | C24: K tok/任務 | D24: =INP_114 -> 3 | E24: =INP_115 -> 4.39 | F24: =E24*(1+INP_123) -> 5.0485 | G24: =F24*(1+INP_123) -> 5.805775 | H24: =G24*(1+INP_123) -> 6.6766413 | I24: =H24*(1+INP_123) -> 7.6781374 | K24: 3 | L24: 4.39 | M24: 5.0485 | N24: 5.805775 | O24: 6.6766413 | P24: 7.6781374 | Q24: 2027 起 ×（1＋每任務 token 年增率；D11 情境軸）
A25: D17 | B25: Plus 每任務 token | C25: K tok/任務 | D25: =INP_116 -> 4 | E25: =INP_117 -> 6.15 | F25: =E25*(1+INP_123) -> 7.0725 | G25: =F25*(1+INP_123) -> 8.133375 | H25: =G25*(1+INP_123) -> 9.3533812 | I25: =H25*(1+INP_123) -> 10.756388 | K25: 4 | L25: 6.15 | M25: 7.0725 | N25: 8.133375 | O25: 9.3533812 | P25: 10.756388 | Q25: 2027 起 ×（1＋每任務 token 年增率；D11 情境軸）
A26: D18 | B26: Pro 每任務 token | C26: K tok/任務 | D26: =INP_118 -> 10 | E26: =INP_119 -> 15.6 | F26: =E26*(1+INP_123) -> 17.94 | G26: =F26*(1+INP_123) -> 20.631 | H26: =G26*(1+INP_123) -> 23.72565 | I26: =H26*(1+INP_123) -> 27.284498 | K26: 10 | L26: 15.6 | M26: 17.94 | N26: 20.631 | O26: 23.72565 | P26: 27.284498 | Q26: 2027 起 ×（1＋每任務 token 年增率；D11 情境軸）
A27: D19 | B27: 企業席位 每任務 token | C27: K tok/任務 | D27: =INP_120 -> 4 | E27: =INP_121 -> 5.94 | F27: =E27*(1+INP_123) -> 6.831 | G27: =F27*(1+INP_123) -> 7.85565 | H27: =G27*(1+INP_123) -> 9.0339975 | I27: =H27*(1+INP_123) -> 10.389097 | K27: 4 | L27: 5.94 | M27: 6.831 | N27: 7.85565 | O27: 9.0339975 | P27: 10.389097 | Q27: 2027 起 ×（1＋每任務 token 年增率；D11 情境軸）
A28: D20 | B28: Free token | C28: T | D28: =D10*D18*D23*INP_251/INP_239 -> 744.6 | E28: =E10*E18*E23*INP_251/INP_239 -> 1733.0565 | F28: =F10*F18*F23*INP_251/INP_239 -> 2884.6269 | G28: =G10*G18*G23*INP_251/INP_239 -> 4378.8637 | H28: =H10*H18*H23*INP_251/INP_239 -> 6277.8309 | I28: =I10*I18*I23*INP_251/INP_239 -> 8642.1728 | K28: 744.6 | L28: 1733.0565 | M28: 2884.6269 | N28: 4378.8637 | O28: 6277.8309 | P28: 8642.1728 | Q28: 人數（M）× 每日任務 × 每任務 token（K）× 每年天數 ÷ 1000（B→T）
A29: D21 | B29: Go token | C29: T | D29: =D11*D19*D24*INP_251/INP_239 -> 11.607 | E29: =E11*E19*E24*INP_251/INP_239 -> 370.81584 | F29: =F11*F19*F24*INP_251/INP_239 -> 894.81241 | G29: =G11*G19*G24*INP_251/INP_239 -> 1710.0755 | H29: =H11*H19*H24*INP_251/INP_239 -> 2726.5045 | I29: =I11*I19*I24*INP_251/INP_239 -> 4155.9071 | K29: 11.607 | L29: 370.81584 | M29: 894.81241 | N29: 1710.0755 | O29: 2726.5045 | P29: 4155.9071 | Q29: 人數（M）× 每日任務 × 每任務 token（K）× 每年天數 ÷ 1000（B→T）
A30: D22 | B30: Plus token | C30: T | D30: =D12*D20*D25*INP_251/INP_239 -> 586.92 | E30: =E12*E20*E25*INP_251/INP_239 -> 1402.3178 | F30: =F12*F20*F25*INP_251/INP_239 -> 2005.3144 | G30: =G12*G20*G25*INP_251/INP_239 -> 2780.6384 | H30: =H12*H20*H25*INP_251/INP_239 -> 3764.3502 | I30: =I12*I20*I25*INP_251/INP_239 -> 4996.0949 | K30: 586.92 | L30: 1402.3178 | M30: 2005.3144 | N30: 2780.6384 | O30: 3764.3502 | P30: 4996.0949 | Q30: 人數（M）× 每日任務 × 每任務 token（K）× 每年天數 ÷ 1000（B→T）
A31: D23 | B31: Pro token | C31: T | D31: =D13*D21*D26*INP_251/INP_239 -> 42.239919 | E31: =E13*E21*E26*INP_251/INP_239 -> 165.21784 | F31: =F13*F21*F26*INP_251/INP_239 -> 298.57224 | G31: =G13*G21*G26*INP_251/INP_239 -> 491.00204 | H31: =H13*H21*H26*INP_251/INP_239 -> 735.78545 | I31: =I13*I21*I26*INP_251/INP_239 -> 1057.6916 | K31: 74.825 | L31: 292.6716 | M31: 555.34436 | N31: 936.68082 | O31: 1481.1266 | P31: 2248.3501 | Q31: 人數（M）× 每日任務 × 每任務 token（K）× 每年天數 ÷ 1000（B→T）
A32: D24 | B32: 企業席位 token | C32: T | D32: =D14*D22*D27*INP_251/INP_239 -> 46.866 | E32: =E14*E22*E27*INP_251/INP_239 -> 434.05362 | F32: =F14*F22*F27*INP_251/INP_239 -> 1019.716 | G32: =G14*G22*G27*INP_251/INP_239 -> 1885.2979 | H32: =H14*H22*H27*INP_251/INP_239 -> 3012.5077 | I32: =I14*I22*I27*INP_251/INP_239 -> 4445.9592 | K32: 46.866 | L32: 434.05362 | M32: 1019.716 | N32: 1885.2979 | O32: 3012.5077 | P32: 4445.9592 | Q32: 人數（M）× 每日任務 × 每任務 token（K）× 每年天數 ÷ 1000（B→T）
A33: D25 | B33: 訂閱＋Free token 合計 | C33: T | D33: =D28+D29+D30+D31+D32 -> 1432.2329 | E33: =E28+E29+E30+E31+E32 -> 4105.4616 | F33: =F28+F29+F30+F31+F32 -> 7103.042 | G33: =G28+G29+G30+G31+G32 -> 11245.878 | H33: =H28+H29+H30+H31+H32 -> 16516.979 | I33: =I28+I29+I30+I31+I32 -> 23297.826 | K33: 1464.818 | L33: 4232.9153 | M33: 7359.8141 | N33: 11691.556 | O33: 17262.32 | P33: 24488.484 | Q33: workbook 口徑（v0.5 未校正）
A34: 三、API 需求：任務數 × 每任務 token（2025 由營收倒推；2027 起價格反應）
A35: D26 | B35: 價格反應底數 p/p前（組合有效單價） | C35: 倍 | E35: =Revenue!E21/Revenue!D21 -> 1.4184907 | F35: =Revenue!F21/Revenue!E21 -> 0.64259865 | G35: =Revenue!G21/Revenue!F21 -> 0.64640386 | H35: =Revenue!H21/Revenue!G21 -> 0.6502514 | I35: =Revenue!I21/Revenue!H21 -> 0.65409597 | L35: 1 | M35: 0.6422023 | N35: 0.64600047 | O35: 0.64984568 | P35: 0.65369271 | Q35: ＝Revenue 組合有效單價 ÷ 前一年；價格反應只在年度 ≥ 彈性起算年（Inputs 2027）生效：底數^(ε×(年度≥起算年))
A36: D27 | B36: API 每任務 token | C36: K tok/任務 | D36: =INP_031 -> 10 | E36: =D36*(1+INP_041)*E35^(INP_049*(E$6>=INP_004)) -> 12 | F36: =E36*(1+INP_042)*F35^(INP_049*(F$6>=INP_004)) -> 15.757857 | G36: =F36*(1+INP_043)*G35^(INP_049*(G$6>=INP_004)) -> 20.117036 | H36: =G36*(1+INP_044)*H35^(INP_049*(H$6>=INP_004)) -> 25.178641 | I36: =H36*(1+INP_045)*I35^(INP_049*(I$6>=INP_004)) -> 30.886137 | K36: 10 | L36: 12 | M36: 15.760774 | N36: 20.124528 | O36: 25.192735 | P36: 30.909144 | Q36: 層級正規化（只影響任務數與每任務 token 的水準拆分，不影響營收）
A37: D28 | B37: API 任務數 | C37: 十億 | D37: =D38/D36 -> 210.58272 | E37: =D37*(1+INP_033)*E35^(INP_048*(E$6>=INP_004)) -> 492.76356 | F37: =E37*(1+INP_034)*F35^(INP_048*(F$6>=INP_004)) -> 973.7528 | G37: =F37*(1+INP_035)*G35^(INP_048*(G$6>=INP_004)) -> 1784.1433 | H37: =G37*(1+INP_036)*H35^(INP_048*(H$6>=INP_004)) -> 3014.2748 | I37: =H37*(1+INP_037)*I35^(INP_048*(I$6>=INP_004)) -> 4868.7228 | K37: 184.05643 | L37: 430.69204 | M37: 851.46059 | N37: 1560.7572 | O37: 2638.0206 | P37: 4262.8287 | Q37: 2025＝計費 token ÷ 每任務 token；之後 ×（1＋成長）× 價格反應
A38: D29 | B38: API 計費 token | C38: T | D38: =Revenue!D33/Revenue!D21*INP_253 -> 2105.8272 | E38: =E37*E36 -> 5913.1628 | F38: =F37*F36 -> 15344.257 | G38: =G37*G36 -> 35891.674 | H38: =H37*H36 -> 75895.341 | I38: =I37*I36 -> 150376.04 | K38: 1840.5643 | L38: 5168.3045 | M38: 13419.678 | N38: 31409.501 | O38: 66458.954 | P38: 131760.39 | Q38: 2025：（FY2025 實際營收 − 訂閱 − 廣告 − 其他）÷ 組合有效單價（v0.5 校準，唯一倒推）；之後＝任務數 × 每任務 token
A39: D30 | B39: API token：頂層（Astra） | C39: T | D39: =D38*Revenue!D18 -> 842.33088 | E39: =E38*Revenue!E18 -> 886.97441 | F39: =F38*Revenue!F18 -> 2301.6386 | G39: =G38*Revenue!G18 -> 5383.7511 | H39: =H38*Revenue!H18 -> 11384.301 | I39: =I38*Revenue!I18 -> 22556.406 | K39: 736.22572 | L39: 775.24568 | M39: 2012.9516 | N39: 4711.4252 | O39: 9968.8431 | P39: 19764.058 | Q39: 計費 token × 層級占比（Revenue）
A40: D31 | B40: API token：中層（Sol） | C40: T | D40: =D38*Revenue!D19 -> 842.33088 | E40: =E38*Revenue!E19 -> 2660.9232 | F40: =F38*Revenue!F19 -> 6904.9157 | G40: =G38*Revenue!G19 -> 16151.253 | H40: =H38*Revenue!H19 -> 34152.904 | I40: =I38*Revenue!I19 -> 67669.218 | K40: 736.22572 | L40: 2325.737 | M40: 6038.8549 | N40: 14134.276 | O40: 29906.529 | P40: 59292.175 | Q40: 計費 token × 層級占比（Revenue）
A41: D32 | B41: API token：低層（Luna） | C41: T | D41: =D38*Revenue!D20 -> 421.16544 | E41: =E38*Revenue!E20 -> 2365.2651 | F41: =F38*Revenue!F20 -> 6137.7028 | G41: =G38*Revenue!G20 -> 14356.67 | H41: =H38*Revenue!H20 -> 30358.136 | I41: =I38*Revenue!I20 -> 60150.416 | K41: 368.11286 | L41: 2067.3218 | M41: 5367.871 | N41: 12563.8 | O41: 26583.582 | P41: 52704.155 | Q41: 計費 token × 層級占比（Revenue）
A42: 四、輸出：token 量（層級 × 付費／免費；供 P3 推論 GW）
A43: D33 | B43: 免費 token：頂層（Astra） | C43: T | D43: =D28*INP_157 -> 0 | E43: =E28*INP_157 -> 0 | F43: =F28*INP_157 -> 0 | G43: =G28*INP_157 -> 0 | H43: =H28*INP_157 -> 0 | I43: =I28*INP_157 -> 0 | Q43: Free token × 方案模型組合（Inputs astra 占比；v0.5 inferenceCost.usage）
A44: D34 | B44: 免費 token：中層（Sol） | C44: T | D44: =D28*INP_156 -> 74.46 | E44: =E28*INP_156 -> 173.30565 | F44: =F28*INP_156 -> 288.46269 | G44: =G28*INP_156 -> 437.88637 | H44: =H28*INP_156 -> 627.78309 | I44: =I28*INP_156 -> 864.21728 | Q44: Free token × 方案模型組合（Inputs sol 占比；v0.5 inferenceCost.usage）
A45: D35 | B45: 免費 token：低層（Luna） | C45: T | D45: =D28*INP_155 -> 670.14 | E45: =E28*INP_155 -> 1559.7508 | F45: =F28*INP_155 -> 2596.1642 | G45: =G28*INP_155 -> 3940.9773 | H45: =H28*INP_155 -> 5650.0478 | I45: =I28*INP_155 -> 7777.9555 | Q45: Free token × 方案模型組合（Inputs luna 占比；v0.5 inferenceCost.usage）
A46: D36 | B46: 付費 token：頂層（Astra） | C46: T | D46: =D29*INP_162+D30*INP_167+D31*INP_172+D32*INP_177+D39 -> 890.91614 | E46: =E29*INP_162+E30*INP_167+E31*INP_172+E32*INP_177+E39 -> 1044.8801 | F46: =F29*INP_162+F30*INP_167+F31*INP_172+F32*INP_177+F39 -> 2572.319 | G46: =G29*INP_162+G30*INP_167+G31*INP_172+G32*INP_177+G39 -> 5813.4488 | H46: =H29*INP_162+H30*INP_167+H31*INP_172+H32*INP_177+H39 -> 12017.458 | I46: =I29*INP_162+I30*INP_167+I31*INP_172+I32*INP_177+I39 -> 23451.585 | Q46: Σ 付費方案 token × 方案模型組合 ＋ API 該層級 token
A47: D37 | B47: 付費 token：中層（Sol） | C47: T | D47: =D29*INP_161+D30*INP_166+D31*INP_171+D32*INP_176+D40 -> 1247.8068 | E47: =E29*INP_161+E30*INP_166+E31*INP_171+E32*INP_176+E40 -> 3922.68 | F47: =F29*INP_161+F30*INP_166+F31*INP_171+F32*INP_176+F40 -> 9054.4277 | G47: =G29*INP_161+G30*INP_166+G31*INP_171+G32*INP_176+G40 -> 19547.092 | H47: =H29*INP_161+H30*INP_166+H31*INP_171+H32*INP_176+H40 -> 39146.512 | I47: =I29*INP_161+I30*INP_166+I31*INP_171+I32*INP_176+I40 -> 74708.98 | Q47: Σ 付費方案 token × 方案模型組合 ＋ API 該層級 token
A48: D38 | B48: 付費 token：低層（Luna） | C48: T | D48: =D29*INP_160+D30*INP_165+D31*INP_170+D32*INP_175+D41 -> 654.73718 | E48: =E29*INP_160+E30*INP_165+E31*INP_170+E32*INP_175+E41 -> 3318.0077 | F48: =F29*INP_160+F30*INP_165+F31*INP_170+F32*INP_175+F41 -> 7935.9254 | G48: =G29*INP_160+G30*INP_165+G31*INP_170+G32*INP_175+G41 -> 17398.147 | H48: =H29*INP_160+H30*INP_165+H31*INP_170+H32*INP_175+H41 -> 34970.519 | I48: =I29*INP_160+I30*INP_165+I31*INP_170+I32*INP_175+I41 -> 66871.127 | Q48: Σ 付費方案 token × 方案模型組合 ＋ API 該層級 token
A49: D39 | B49: 免費 token 合計 | C49: T | D49: =D43+D44+D45 -> 744.6 | E49: =E43+E44+E45 -> 1733.0565 | F49: =F43+F44+F45 -> 2884.6269 | G49: =G43+G44+G45 -> 4378.8637 | H49: =H43+H44+H45 -> 6277.8309 | I49: =I43+I44+I45 -> 8642.1728
A50: D40 | B50: 付費 token 合計 | C50: T | D50: =D46+D47+D48 -> 2793.4601 | E50: =E46+E47+E48 -> 8285.5678 | F50: =F46+F47+F48 -> 19562.672 | G50: =G46+G47+G48 -> 42758.688 | H50: =H46+H47+H48 -> 86134.489 | I50: =I46+I47+I48 -> 165031.69
A51: D41 | B51: token 合計（付費＋免費） | C51: T | D51: =D49+D50 -> 3538.0601 | E51: =E49+E50 -> 10018.624 | F51: =F49+F50 -> 22447.299 | G51: =G49+G50 -> 47137.552 | H51: =H49+H50 -> 92412.32 | I51: =I49+I50 -> 173673.87
A52: D42 | B52: 對照：訂閱＋免費＋API 計費 token（應＝合計） | C52: T | D52: =D33+D38 -> 3538.0601 | E52: =E33+E38 -> 10018.624 | F52: =F33+F38 -> 22447.299 | G52: =G33+G38 -> 47137.552 | H52: =H33+H38 -> 92412.32 | I52: =I33+I38 -> 173673.87 | Q52: 層級拆分前的總量；與上一列之差應為 0（Checks）
A53: 五、2025 對照（只列差距，不校準）
A54: D43 | B54: Tokenomics IF_AllocDemand（需求 D 合計，2025） | C54: M tok/年 | D54: =TK_IF_AllocDemand -> 4190200000 | Q54: TK 快照；口徑：API＋ChatGPT；付費＋免費 token
A55: D44 | B55: 本模型 2025 token 合計 | C55: M tok/年 | D55: =D51*INP_254 -> 3.5380601e+09 | Q55: T × 10^6（Inputs 定義常數）
A56: D45 | B56: 差距：本模型 − Tokenomics | C56: M tok/年 | D56: =D55-D54 -> -6.5213989e+08
A57: D46 | B57: 比值：本模型 ÷ Tokenomics | C57: 倍 | D57: =D55/D54 -> 0.84436545
A58: D47 | B58: API 處理 token（揭露推估，FY2025） | C58: T | D58: =V9_ApiTok -> 2628 | K58: 2628 | Q58: Derived_V9 V22：Inputs 每分鐘 5B × 525,600 ÷ 1000
A59: D48 | B59: API 計費比例＝計費 token ÷ 處理 token（2025） | C59: 比例 | D59: =D38/D58 -> 0.80130411 | K59: 0.70036693 | Q59: v0.5 檢查項；計費 token 為營收倒推值

Sheet Revenue
A1: Revenue — 營收：API 單價路徑、訂閱、API、廣告、其他、總額、Microsoft 分成、淨額（估值與命題用淨額）
A2: 機制沿用 v0.5「API」「訂閱與廣告」「營收彙總」頁。API 單價：2025 Inputs（Analogy）；2026 由價格事件按天數加權（E8c，事件時點見本頁下方）；2027 起 ×（1＋牌價年變動率）。訂閱營收＝人數 × 實收 ARPU × 12。
A3: 營收單位 $B；單價 $/M tokens。容量上限（V1a）於 P3 加入，本頁營收未截頂。v0.5 原值欄（K–P）只作對照。
A5: 編號 | B5: 項目 | C5: 單位 | D5: 2025 | E5: 2026 | F5: 2027 | G5: 2028 | H5: 2029 | I5: 2030 | K5: v0.5 2025 | L5: v0.5 2026 | M5: v0.5 2027 | N5: v0.5 2028 | O5: v0.5 2029 | P5: v0.5 2030 | Q5: 說明
B6: 年度 | D6: =INP_005 -> 2025 | E6: =INP_006 -> 2026 | F6: =INP_007 -> 2027 | G6: =INP_008 -> 2028 | H6: =INP_009 -> 2029 | I6: =INP_010 -> 2030
A7: 一、API 牌價（FY 平均，$/M tokens；N3a 層級角色口徑）
A8: R01 | B8: 頂層（Astra） 輸入牌價 | C8: $/M | D8: =INP_015 -> 2.5 | E8: =D65 -> 6.6109589 | F8: =E8*(1+INP_021) -> 4.6276712 | G8: =F8*(1+INP_021) -> 3.2393699 | H8: =G8*(1+INP_021) -> 2.2675589 | I8: =H8*(1+INP_021) -> 1.5872912 | K8: 2.5 | L8: 6.6 | M8: 4.62 | N8: 3.234 | O8: 2.2638 | P8: 1.58466 | Q8: 2025 Inputs（Analogy）；2026＝事件時點天數加權（下方第六節）；2027 起 ×（1＋年變動率）
A9: R02 | B9: 頂層（Astra） 輸出牌價 | C9: $/M | D9: =INP_018 -> 14 | E9: =D66 -> 36.246575 | F9: =E9*(1+INP_021) -> 25.372603 | G9: =F9*(1+INP_021) -> 17.760822 | H9: =G9*(1+INP_021) -> 12.432575 | I9: =H9*(1+INP_021) -> 8.7028027 | K9: 14 | L9: 35.8 | M9: 25.06 | N9: 17.542 | O9: 12.2794 | P9: 8.59558 | Q9: 2025 Inputs（Analogy）；2026＝事件時點天數加權（下方第六節）；2027 起 ×（1＋年變動率）
A10: R03 | B10: 中層（Sol） 輸入牌價 | C10: $/M | D10: =INP_016 -> 1.5 | E10: =D67 -> 2.2876712 | F10: =E10*(1+INP_022) -> 1.3726027 | G10: =F10*(1+INP_022) -> 0.82356164 | H10: =G10*(1+INP_022) -> 0.49413699 | I10: =H10*(1+INP_022) -> 0.29648219 | K10: 1.5 | L10: 2.29 | M10: 1.374 | N10: 0.8244 | O10: 0.49464 | P10: 0.296784 | Q10: 2025 Inputs（Analogy）；2026＝事件時點天數加權（下方第六節）；2027 起 ×（1＋年變動率）
A11: R04 | B11: 中層（Sol） 輸出牌價 | C11: $/M | D11: =INP_019 -> 8 | E11: =D68 -> 13.172603 | F11: =E11*(1+INP_022) -> 7.9035616 | G11: =F11*(1+INP_022) -> 4.742137 | H11: =G11*(1+INP_022) -> 2.8452822 | I11: =H11*(1+INP_022) -> 1.7071693 | K11: 8 | L11: 13.25 | M11: 7.95 | N11: 4.77 | O11: 2.862 | P11: 1.7172 | Q11: 2025 Inputs（Analogy）；2026＝事件時點天數加權（下方第六節）；2027 起 ×（1＋年變動率）
A12: R05 | B12: 低層（Luna） 輸入牌價 | C12: $/M | D12: =INP_017 -> 0.2 | E12: =D69 -> 0.63260274 | F12: =E12*(1+INP_023) -> 0.37956164 | G12: =F12*(1+INP_023) -> 0.22773699 | H12: =G12*(1+INP_023) -> 0.13664219 | I12: =H12*(1+INP_023) -> 0.081985315 | K12: 0.2 | L12: 0.64 | M12: 0.384 | N12: 0.2304 | O12: 0.13824 | P12: 0.082944 | Q12: 2025 Inputs（Analogy）；2026＝事件時點天數加權（下方第六節）；2027 起 ×（1＋年變動率）
A13: R06 | B13: 低層（Luna） 輸出牌價 | C13: $/M | D13: =INP_020 -> 1 | E13: =D70 -> 3.7679452 | F13: =E13*(1+INP_023) -> 2.2607671 | G13: =F13*(1+INP_023) -> 1.3564603 | H13: =G13*(1+INP_023) -> 0.81387616 | I13: =H13*(1+INP_023) -> 0.4883257 | K13: 1 | L13: 3.83 | M13: 2.298 | N13: 1.3788 | O13: 0.82728 | P13: 0.496368 | Q13: 2025 Inputs（Analogy）；2026＝事件時點天數加權（下方第六節）；2027 起 ×（1＋年變動率）
A14: 二、有效單價（$/M；含快取、輸出占比；折扣於組合列扣除）
A15: R07 | B15: 頂層（Astra）每 token 單價 | C15: $/M | D15: =(1-INP_028)*(INP_029*SRC_OAI_030+(1-INP_029))*D8+INP_028*D9 -> 3.81 | E15: =(1-INP_028)*(INP_029*SRC_OAI_030+(1-INP_029))*E8+INP_028*E9 -> 9.9201425 | F15: =(1-INP_028)*(INP_029*SRC_OAI_030+(1-INP_029))*F8+INP_028*F9 -> 6.9440997 | G15: =(1-INP_028)*(INP_029*SRC_OAI_030+(1-INP_029))*G8+INP_028*G9 -> 4.8608698 | H15: =(1-INP_028)*(INP_029*SRC_OAI_030+(1-INP_029))*H8+INP_028*H9 -> 3.4026089 | I15: =(1-INP_028)*(INP_029*SRC_OAI_030+(1-INP_029))*I8+INP_028*I9 -> 2.3818262 | K15: 3.81 | L15: 9.8264 | M15: 6.87848 | N15: 4.814936 | O15: 3.3704552 | P15: 2.3593186 | Q15: （1−輸出占比）×（快取命中 × 快取價比 ＋（1−快取命中））× 輸入價 ＋ 輸出占比 × 輸出價
A16: R08 | B16: 中層（Sol）每 token 單價 | C16: $/M | D16: =(1-INP_028)*(INP_029*SRC_OAI_030+(1-INP_029))*D10+INP_028*D11 -> 2.206 | E16: =(1-INP_028)*(INP_029*SRC_OAI_030+(1-INP_029))*E10+INP_028*E11 -> 3.5587397 | F16: =(1-INP_028)*(INP_029*SRC_OAI_030+(1-INP_029))*F10+INP_028*F11 -> 2.1352438 | G16: =(1-INP_028)*(INP_029*SRC_OAI_030+(1-INP_029))*G10+INP_028*G11 -> 1.2811463 | H16: =(1-INP_028)*(INP_029*SRC_OAI_030+(1-INP_029))*H10+INP_028*H11 -> 0.76868778 | I16: =(1-INP_028)*(INP_029*SRC_OAI_030+(1-INP_029))*I10+INP_028*I11 -> 0.46121267 | K16: 2.206 | L16: 3.57516 | M16: 2.145096 | N16: 1.2870576 | O16: 0.77223456 | P16: 0.46334074 | Q16: （1−輸出占比）×（快取命中 × 快取價比 ＋（1−快取命中））× 輸入價 ＋ 輸出占比 × 輸出價
A17: R09 | B17: 低層（Luna）每 token 單價 | C17: $/M | D17: =(1-INP_028)*(INP_029*SRC_OAI_030+(1-INP_029))*D12+INP_028*D13 -> 0.2808 | E17: =(1-INP_028)*(INP_029*SRC_OAI_030+(1-INP_029))*E12+INP_028*E13 -> 1.0091605 | F17: =(1-INP_028)*(INP_029*SRC_OAI_030+(1-INP_029))*F12+INP_028*F13 -> 0.60549633 | G17: =(1-INP_028)*(INP_029*SRC_OAI_030+(1-INP_029))*G12+INP_028*G13 -> 0.3632978 | H17: =(1-INP_028)*(INP_029*SRC_OAI_030+(1-INP_029))*H12+INP_028*H13 -> 0.21797868 | I17: =(1-INP_028)*(INP_029*SRC_OAI_030+(1-INP_029))*I12+INP_028*I13 -> 0.13078721 | K17: 0.2808 | L17: 1.02456 | M17: 0.614736 | N17: 0.3688416 | O17: 0.22130496 | P17: 0.13278298 | Q17: （1−輸出占比）×（快取命中 × 快取價比 ＋（1−快取命中））× 輸入價 ＋ 輸出占比 × 輸出價
A18: R10 | B18: API token 組合：頂層 | C18: 比例 | D18: =INP_024 -> 0.4 | E18: =INP_025 -> 0.15 | F18: =INP_025 -> 0.15 | G18: =INP_025 -> 0.15 | H18: =INP_025 -> 0.15 | I18: =INP_025 -> 0.15 | K18: 0.4 | L18: 0.15 | M18: 0.15 | N18: 0.15 | O18: 0.15 | P18: 0.15 | Q18: Inputs（2025、2026；2027 起沿用 2026，v0.5 以最後一值延伸）
A19: R11 | B19: API token 組合：中層 | C19: 比例 | D19: =INP_026 -> 0.4 | E19: =INP_027 -> 0.45 | F19: =INP_027 -> 0.45 | G19: =INP_027 -> 0.45 | H19: =INP_027 -> 0.45 | I19: =INP_027 -> 0.45 | K19: 0.4 | L19: 0.45 | M19: 0.45 | N19: 0.45 | O19: 0.45 | P19: 0.45 | Q19: 同上
A20: R12 | B20: API token 組合：低層 | C20: 比例 | D20: =(1-D18-D19) -> 0.2 | E20: =(1-E18-E19) -> 0.4 | F20: =(1-F18-F19) -> 0.4 | G20: =(1-G18-G19) -> 0.4 | H20: =(1-H18-H19) -> 0.4 | I20: =(1-I18-I19) -> 0.4 | K20: 0.2 | L20: 0.4 | M20: 0.4 | N20: 0.4 | O20: 0.4 | P20: 0.4 | Q20: ＝1 − 頂層 − 中層（v0.5：不另輸入）
A21: R13 | B21: 組合有效單價（扣折扣） | C21: $/M | D21: =(D18*D15+D19*D16+D20*D17)*(1-INP_030) -> 1.970048 | E21: =(E18*E15+E19*E16+E20*E17)*(1-INP_030) -> 2.7944948 | F21: =(F18*F15+F19*F16+F20*F17)*(1-INP_030) -> 1.7957386 | G21: =(G18*G15+G19*G16+G20*G17)*(1-INP_030) -> 1.1607723 | H21: =(H18*H15+H19*H16+H20*H17)*(1-INP_030) -> 0.75479384 | I21: =(I18*I15+I19*I16+I20*I17)*(1-INP_030) -> 0.49370761 | K21: 1.970048 | L21: 2.7940848 | M21: 1.7943677 | N21: 1.1591624 | O21: 0.75327665 | P21: 0.49241145 | Q21: Σ 層級占比 × 每 token 單價 ×（1 − 加權折扣）
A22: 三、訂閱營收（$B＝人數 × 實收 ARPU × 12 ÷ 1000）
A23: R14 | B23: Go 訂閱營收 | C23: $B | D23: =Demand!D11*INP_096*INP_252/INP_253 -> 0.144 | E23: =Demand!E11*INP_096*INP_252/INP_253 -> 2.9232 | F23: =Demand!F11*INP_096*INP_252/INP_253 -> 5.5762435 | G23: =Demand!G11*INP_096*INP_252/INP_253 -> 8.424313 | H23: =Demand!H11*INP_096*INP_252/INP_253 -> 10.617809 | I23: =Demand!I11*INP_096*INP_252/INP_253 -> 12.79393 | K23: 0.144 | L23: 2.9232 | M23: 5.5762435 | N23: 8.424313 | O23: 10.617809 | P23: 12.79393 | Q23: ARPU：plus、pro 2025 一欄、2026 起一欄（v0.5 以最後一值延伸）；go、seats 全期一欄
A24: R15 | B24: Plus 訂閱營收 | C24: $B | D24: =Demand!D12*INP_097*INP_252/INP_253 -> 7.02 | E24: =Demand!E12*INP_098*INP_252/INP_253 -> 7.9572 | F24: =Demand!F12*INP_098*INP_252/INP_253 -> 8.9950957 | G24: =Demand!G12*INP_098*INP_252/INP_253 -> 9.8600087 | H24: =Demand!H12*INP_098*INP_252/INP_253 -> 10.551939 | I24: =Demand!I12*INP_098*INP_252/INP_253 -> 11.070887 | K24: 7.02 | L24: 7.9572 | M24: 8.9950957 | N24: 9.8600087 | O24: 10.551939 | P24: 11.070887 | Q24: ARPU：plus、pro 2025 一欄、2026 起一欄（v0.5 以最後一值延伸）；go、seats 全期一欄
A25: R16 | B25: Pro 訂閱營收 | C25: $B | D25: =Demand!D13*INP_099*INP_252/INP_253 -> 0.67741935 | E25: =Demand!E13*INP_100*INP_252/INP_253 -> 1.016129 | F25: =Demand!F13*INP_100*INP_252/INP_253 -> 1.4516129 | G25: =Demand!G13*INP_100*INP_252/INP_253 -> 1.8870968 | H25: =Demand!H13*INP_100*INP_252/INP_253 -> 2.2354839 | I25: =Demand!I13*INP_100*INP_252/INP_253 -> 2.5403226 | K25: 1.2 | L25: 1.8 | M25: 2.7 | N25: 3.6 | O25: 4.5 | P25: 5.4 | Q25: ARPU：plus、pro 2025 一欄、2026 起一欄（v0.5 以最後一值延伸）；go、seats 全期一欄
A26: R17 | B26: 企業席位 訂閱營收 | C26: $B | D26: =Demand!D14*INP_101*INP_252/INP_253 -> 1.08 | E26: =Demand!E14*INP_101*INP_252/INP_253 -> 5.04 | F26: =Demand!F14*INP_101*INP_252/INP_253 -> 9.36 | G26: =Demand!G14*INP_101*INP_252/INP_253 -> 13.68 | H26: =Demand!H14*INP_101*INP_252/INP_253 -> 17.28 | I26: =Demand!I14*INP_101*INP_252/INP_253 -> 20.16 | K26: 1.08 | L26: 5.04 | M26: 9.36 | N26: 13.68 | O26: 17.28 | P26: 20.16 | Q26: ARPU：plus、pro 2025 一欄、2026 起一欄（v0.5 以最後一值延伸）；go、seats 全期一欄
A27: R18 | B27: 訂閱合計 | C27: $B | D27: =D23+D24+D25+D26 -> 8.9214194 | E27: =E23+E24+E25+E26 -> 16.936529 | F27: =F23+F24+F25+F26 -> 25.382952 | G27: =G23+G24+G25+G26 -> 33.851419 | H27: =H23+H24+H25+H26 -> 40.685232 | I27: =I23+I24+I25+I26 -> 46.56514 | K27: 9.444 | L27: 17.7204 | M27: 26.631339 | N27: 35.564322 | O27: 42.949748 | P27: 49.424817
A28: 四、廣告與其他（廣告為獨立、慢成長的一列，不進核心分析，N1b）
A29: R19 | B29: 廣告曝光用戶（Free＋Go） | C29: M | D29: =(Demand!D10+Demand!D11)*INP_124 -> 0 | E29: =(Demand!E10+Demand!E11)*INP_125 -> 247.65 | F29: =(Demand!F10+Demand!F11)*INP_126 -> 464.60674 | G29: =(Demand!G10+Demand!G11)*INP_127 -> 646.80174 | H29: =(Demand!H10+Demand!H11)*INP_128 -> 831.3613 | I29: =(Demand!I10+Demand!I11)*INP_129 -> 1013.8467 | K29: 0 | L29: 247.65 | M29: 464.60674 | N29: 646.80174 | O29: 831.3613 | P29: 1013.8467 | Q29: 曝光占比 Inputs（Andy 2026-09-29：2027→2030 不宜 8 倍）
A30: R20 | B30: 廣告營收 | C30: $B | D30: =D29*INP_130/INP_253 -> 0 | E30: =E29*INP_131/INP_253 -> 0.74295 | F30: =F29*INP_132/INP_253 -> 1.858427 | G30: =G29*INP_133/INP_253 -> 2.9106078 | H30: =H29*INP_134/INP_253 -> 4.1568065 | I30: =I29*INP_135/INP_253 -> 5.5761571 | K30: 0 | L30: 0.74295 | M30: 1.858427 | N30: 2.9106078 | O30: 4.1568065 | P30: 5.5761571 | Q30: 每曝光用戶年收入 Inputs（Analogy；上限參照 Meta ARPP）
A31: R21 | B31: 其他營收（授權、一次性交易） | C31: $B | D31: =INP_136 -> 0 | E31: =INP_136 -> 0 | F31: =INP_136 -> 0 | G31: =INP_136 -> 0 | H31: =INP_136 -> 0 | I31: =INP_136 -> 0 | K31: 0 | L31: 0 | M31: 0 | N31: 0 | O31: 0 | P31: 0 | Q31: Inputs（v0.5 residual，維持 0）
A32: 五、API 營收、總額、Microsoft 分成與淨額
A33: R22 | B33: 2025 校準：API 營收＝實際營收 − 訂閱 − 廣告 − 其他 | C33: $B | D33: =SRC_OAI_002-D27-D30-D31 -> 4.1485806 | Q33: v0.5 calibration：2025 API 為唯一倒推項
A34: R23 | B34: API 營收 | C34: $B | D34: =Demand!D38*D21/INP_253 -> 4.1485806 | E34: =Demand!E38*E21/INP_253 -> 16.524302 | F34: =Demand!F38*F21/INP_253 -> 27.554274 | G34: =Demand!G38*G21/INP_253 -> 41.662063 | H34: =Demand!H38*H21/INP_253 -> 57.285336 | I34: =Demand!I38*I21/INP_253 -> 74.241796 | K34: 3.626 | L34: 14.440681 | M34: 24.079836 | N34: 36.408712 | O34: 50.061979 | P34: 64.880324 | Q34: 計費 token × 組合有效單價 ÷ 1000
A35: R24 | B35: API 營收：頂層（Astra） | C35: $B | D35: =Demand!D38*D18*D15*(1-INP_030)/INP_253 -> 2.5674245 | E35: =Demand!E38*E18*E15*(1-INP_030)/INP_253 -> 7.03913 | F35: =Demand!F38*F18*F15*(1-INP_030)/INP_253 -> 12.786246 | G35: =Demand!G38*G18*G15*(1-INP_030)/INP_253 -> 20.935771 | H35: =Demand!H38*H18*H15*(1-INP_030)/INP_253 -> 30.989059 | I35: =Demand!I38*I18*I15*(1-INP_030)/INP_253 -> 42.980351 | K35: 2.244016 | L35: 6.0942993 | M35: 11.076838 | N35: 18.148169 | O35: 26.879631 | P35: 37.303769
A36: R25 | B36: API 營收：中層（Sol） | C36: $B | D36: =Demand!D38*D19*D16*(1-INP_030)/INP_253 -> 1.4865455 | E36: =Demand!E38*E19*E16*(1-INP_030)/INP_253 -> 7.5756266 | F36: =Demand!F38*F19*F16*(1-INP_030)/INP_253 -> 11.794943 | G36: =Demand!G38*G19*G16*(1-INP_030)/INP_253 -> 16.553695 | H36: =Demand!H38*H19*H16*(1-INP_030)/INP_253 -> 21.002336 | I36: =Demand!I38*I19*I16*(1-INP_030)/INP_253 -> 24.967921 | K36: 1.2992911 | L36: 6.6519056 | M36: 10.363139 | N36: 14.553301 | O36: 18.475884 | P36: 21.977984
A37: R26 | B37: API 營收：低層（Luna） | C37: $B | D37: =Demand!D38*D20*D17*(1-INP_030)/INP_253 -> 0.094610604 | E37: =Demand!E38*E20*E17*(1-INP_030)/INP_253 -> 1.9095458 | F37: =Demand!F38*F20*F17*(1-INP_030)/INP_253 -> 2.9730852 | G37: =Demand!G38*G20*G17*(1-INP_030)/INP_253 -> 4.1725972 | H37: =Demand!H38*H20*H17*(1-INP_030)/INP_253 -> 5.2939412 | I37: =Demand!I38*I20*I17*(1-INP_030)/INP_253 -> 6.2935239 | K37: 0.082692872 | L37: 1.6944762 | M37: 2.6398589 | N37: 3.7072418 | O37: 4.7064628 | P37: 5.5985717
A38: R27 | B38: 總額（訂閱＋API＋廣告＋其他） | C38: $B | D38: =D27+D34+D30+D31 -> 13.07 | E38: =E27+E34+E30+E31 -> 34.203781 | F38: =F27+F34+F30+F31 -> 54.795653 | G38: =G27+G34+G30+G31 -> 78.424089 | H38: =H27+H34+H30+H31 -> 102.12737 | I38: =I27+I34+I30+I31 -> 126.38309 | K38: 13.07 | L38: 32.904031 | M38: 52.569602 | N38: 74.883641 | O38: 97.168533 | P38: 119.8813 | Q38: 容量上限（V1a）於 P3 加入
A39: R28 | B39: Microsoft 分成 | C39: $B | D39: =SRC_OAI_009*D38*(D$6<INP_011)+(D$6>=INP_011)*(D$6<=SRC_OAI_011)*MIN(SRC_OAI_009*D38,SRC_OAI_010) -> 2.614 | E39: =SRC_OAI_009*E38*(E$6<INP_011)+(E$6>=INP_011)*(E$6<=SRC_OAI_011)*MIN(SRC_OAI_009*E38,SRC_OAI_010-D40) -> 6.8407563 | F39: =SRC_OAI_009*F38*(F$6<INP_011)+(F$6>=INP_011)*(F$6<=SRC_OAI_011)*MIN(SRC_OAI_009*F38,SRC_OAI_010-E40) -> 10.959131 | G39: =SRC_OAI_009*G38*(G$6<INP_011)+(G$6>=INP_011)*(G$6<=SRC_OAI_011)*MIN(SRC_OAI_009*G38,SRC_OAI_010-F40) -> 15.684818 | H39: =SRC_OAI_009*H38*(H$6<INP_011)+(H$6>=INP_011)*(H$6<=SRC_OAI_011)*MIN(SRC_OAI_009*H38,SRC_OAI_010-G40) -> 4.5152953 | I39: =SRC_OAI_009*I38*(I$6<INP_011)+(I$6>=INP_011)*(I$6<=SRC_OAI_011)*MIN(SRC_OAI_009*I38,SRC_OAI_010-H40) -> 0 | K39: 2.614 | L39: 6.5808062 | M39: 10.51392 | N39: 14.976728 | O39: 5.9285452 | P39: 0 | Q39: 起算年前：比率 × 總額；起算年至付款終年：MIN（比率 × 總額，上限 − 前一年累計）；之後 0（v0.5；以邏輯值相乘表示各期間）
A40: R29 | B40: Microsoft 分成累計（自起算年） | C40: $B | D40: =D39*(D$6>=INP_011) -> 0 | E40: =D40+E39*(E$6>=INP_011) -> 6.8407563 | F40: =E40+F39*(F$6>=INP_011) -> 17.799887 | G40: =F40+G39*(G$6>=INP_011) -> 33.484705 | H40: =G40+H39*(H$6>=INP_011) -> 38 | I40: =H40+I39*(I$6>=INP_011) -> 38 | K40: 0 | L40: 6.5808062 | M40: 17.094727 | N40: 32.071455 | O40: 38 | P40: 38 | Q40: 上限累計自 Inputs 起算年（N2a）
A41: R30 | B41: 淨額（總額 − Microsoft 分成） | C41: $B | D41: =D38-D39 -> 10.456 | E41: =E38-E39 -> 27.363025 | F41: =F38-F39 -> 43.836523 | G41: =G38-G39 -> 62.739271 | H41: =H38-H39 -> 97.612079 | I41: =I38-I39 -> 126.38309 | K41: 10.456 | L41: 26.323225 | M41: 42.055681 | N41: 59.906913 | O41: 91.239988 | P41: 119.8813 | Q41: 估值與命題用淨額
A42: R31 | B42: 消費端（Go＋Plus＋Pro＋廣告） | C42: $B | D42: =D23+D24+D25+D30 -> 7.8414194 | E42: =E23+E24+E25+E30 -> 12.639479 | F42: =F23+F24+F25+F30 -> 17.881379 | G42: =G23+G24+G25+G30 -> 23.082026 | H42: =H23+H24+H25+H30 -> 27.562038 | I42: =I23+I24+I25+I30 -> 31.981297 | K42: 8.364 | L42: 13.42335 | M42: 19.129766 | N42: 24.79493 | O42: 29.826554 | P42: 34.840974
A43: R32 | B43: 企業端（席位＋API） | C43: $B | D43: =D26+D34 -> 5.2285806 | E43: =E26+E34 -> 21.564302 | F43: =F26+F34 -> 36.914274 | G43: =G26+G34 -> 55.342063 | H43: =H26+H34 -> 74.565336 | I43: =I26+I34 -> 94.401796 | K43: 4.706 | L43: 19.480681 | M43: 33.439836 | N43: 50.088712 | O43: 67.341979 | P43: 85.040324
A44: R33 | B44: 企業端占（消費端＋企業端） | C44: 比例 | D44: =D43/(D42+D43) -> 0.40004443 | E44: =E43/(E42+E43) -> 0.63046545 | F44: =F43/(F42+F43) -> 0.67367158 | G44: =G43/(G42+G43) -> 0.70567683 | H44: =H43/(H42+H43) -> 0.73012096 | I44: =I43/(I42+I43) -> 0.74694956 | K44: 0.36006121 | L44: 0.59204543 | M44: 0.63610594 | N44: 0.66888723 | O44: 0.69304307 | P44: 0.70937106 | Q44: 對照：CFO 2026 年初消費／企業 60／40（SRC_OAI_007）
A45: R34 | B45: 檢查：消費端＋企業端＋其他 − 總額（應為 0） | C45: $B | D45: =D42+D43+D31-D38 -> 0 | E45: =E42+E43+E31-E38 -> 0 | F45: =F42+F43+F31-F38 -> 0 | G45: =G42+G43+G31-G38 -> 0 | H45: =H42+H43+H31-H38 -> 0 | I45: =I42+I43+I31-I38 -> 0 | K45: 0 | L45: 0 | M45: 0 | N45: 0 | O45: 0 | P45: 0
A46: R35 | B46: 總額年增率 | C46: 比例 | E46: =(E38-D38)/D38 -> 1.6169687 | F46: =(F38-E38)/E38 -> 0.60203495 | G46: =(G38-F38)/F38 -> 0.43121004 | H46: =(H38-G38)/G38 -> 0.30224496 | I46: =(I38-H38)/H38 -> 0.23750457 | L46: 1.5175234 | M46: 0.59766448 | N46: 0.42446659 | O46: 0.29759359 | P46: 0.2337461
A47: R36 | B47: 廣告占總額 | C47: 比例 | D47: =D30/D38 -> 0 | E47: =E30/E38 -> 0.021721283 | F47: =F30/F38 -> 0.033915591 | G47: =G30/G38 -> 0.037113696 | H47: =H30/H38 -> 0.040702178 | I47: =I30/I38 -> 0.044121068 | K47: 0 | L47: 0.0225793 | M47: 0.035351741 | N47: 0.038868407 | O47: 0.042779348 | P47: 0.046513986
A48: 六、對照與差距（只列差距，不校準）
A49: R37 | B49: 2025：模型總額 − SRC 實際營收（v0.5 校準方式，應為 0） | C49: $B | D49: =D38-SRC_OAI_002 -> 0 | Q49: 2025 API 為倒推項，總額恆等於 SRC 13.07
A50: R38 | B50: 2025 未校準總額：API 改以處理 token × 組合有效單價 | C50: $B | D50: =D27+D30+D31+V9_ApiTok*D21/INP_253 -> 14.098705 | Q50: 處理 token＝Derived_V9 V22（2,628T）；顯示自下而上口徑與實際的差距
A51: R39 | B51: 2025 未校準差距：未校準總額 − SRC 實際營收 | C51: $B | D51: =D50-SRC_OAI_002 -> 1.0287055
A52: R40 | B52: 2025 未校準差距（占實際） | C52: 比例 | D52: =D51/SRC_OAI_002 -> 0.078707383
A53: R41 | B53: FY2026 獨立推估＝Q1＋Q2＋2026-08 ARR × 下半年月數 ÷ 12 | C53: $B | E53: =SRC_OAI_004+SRC_OAI_005+SRC_OAI_006*INP_255/INP_252 -> 32.4 | L53: 32.9 | Q53: v0.5 fy2026Independent（Derived）；v0.5 值 32.9（31–36）的下半年外推細節未記錄，本列為最簡口徑
A54: R42 | B54: 2026：模型總額 − 獨立推估 | C54: $B | E54: =E38-E53 -> 1.8037814
A55: R43 | B55: 2026 下半年隱含（模型全年 − 上半年實際） | C55: $B | E55: =E38-SRC_OAI_004-SRC_OAI_005 -> 21.803781 | L55: 20.504031
A56: R44 | B56: 對照：管理層營收目標（只對照，D4c） | C56: $B | E56: =SRC_OAI_043 -> 36 | I56: =SRC_OAI_044 -> 350 | Q56: 7 月投資人簡報（SRC_OAI_043、044）；不驅動任何計算
A57: R45 | B57: 模型總額 − 管理層目標 | C57: $B | E57: =E38-E56 -> -1.7962186 | I57: =I38-I56 -> -223.61691
A59: 七、2026 API 牌價：價格事件時點天數加權（E8c；事件時點基準＝SRC_OAI 公告日，區間＝Inputs 偏移 ±1 季）
A60: 編號 | B60: 項目 | C60: 單位 | D60: 基準 | E60: 全部提前（偏移取低） | F60: 全部延後（偏移取高） | G60: 2026 低 | H60: 2026 高 | J60: v0.5 2026（對照） | K60: v0.5 低 | L60: v0.5 高
A61: E2 | B61: 價格事件 2 之後占 FY2026 的比例（天數加權） | C61: 比例 | D61: =(INP_250+INP_251-MAX(INP_250,MIN(INP_250+INP_251,SRC_OAI_125+INP_246)))/INP_251 -> 0.42465753 | E61: =(INP_250+INP_251-MAX(INP_250,MIN(INP_250+INP_251,SRC_OAI_125+Inputs!$F$238)))/INP_251 -> 0.6739726 | F61: =(INP_250+INP_251-MAX(INP_250,MIN(INP_250+INP_251,SRC_OAI_125+Inputs!$G$238)))/INP_251 -> 0.17534247 | Q61: ＝（年底次日 − 生效日）÷ 365；生效日＝SRC 公告日＋Inputs 偏移，限於 FY2026 內
A62: E3 | B62: 價格事件 3 之後占 FY2026 的比例（天數加權） | C62: 比例 | D62: =(INP_250+INP_251-MAX(INP_250,MIN(INP_250+INP_251,SRC_OAI_126+INP_247)))/INP_251 -> 0.36164384 | E62: =(INP_250+INP_251-MAX(INP_250,MIN(INP_250+INP_251,SRC_OAI_126+Inputs!$F$239)))/INP_251 -> 0.6109589 | F62: =(INP_250+INP_251-MAX(INP_250,MIN(INP_250+INP_251,SRC_OAI_126+Inputs!$G$239)))/INP_251 -> 0.11232877 | Q62: ＝（年底次日 − 生效日）÷ 365；生效日＝SRC 公告日＋Inputs 偏移，限於 FY2026 內
A63: E4 | B63: 價格事件 4 之後占 FY2026 的比例（天數加權） | C63: 比例 | D63: =(INP_250+INP_251-MAX(INP_250,MIN(INP_250+INP_251,SRC_OAI_127+INP_248)))/INP_251 -> 0.32876712 | E63: =(INP_250+INP_251-MAX(INP_250,MIN(INP_250+INP_251,SRC_OAI_127+Inputs!$F$240)))/INP_251 -> 0.57808219 | F63: =(INP_250+INP_251-MAX(INP_250,MIN(INP_250+INP_251,SRC_OAI_127+Inputs!$G$240)))/INP_251 -> 0.079452055 | Q63: ＝（年底次日 − 生效日）÷ 365；生效日＝SRC 公告日＋Inputs 偏移，限於 FY2026 內
A64: E5 | B64: 價格事件 5 之後占 FY2026 的比例（天數加權） | C64: 比例 | D64: =(INP_250+INP_251-MAX(INP_250,MIN(INP_250+INP_251,SRC_OAI_128+INP_249)))/INP_251 -> 0.27671233 | E64: =(INP_250+INP_251-MAX(INP_250,MIN(INP_250+INP_251,SRC_OAI_128+Inputs!$F$241)))/INP_251 -> 0.5260274 | F64: =(INP_250+INP_251-MAX(INP_250,MIN(INP_250+INP_251,SRC_OAI_128+Inputs!$G$241)))/INP_251 -> 0.02739726 | Q64: ＝（年底次日 − 生效日）÷ 365；生效日＝SRC 公告日＋Inputs 偏移，限於 FY2026 內
A65: PTI | B65: FY2026 平均牌價：頂層（Astra） 輸入 | C65: $/M | D65: =SRC_OAI_113+(SRC_OAI_123-SRC_OAI_113)*D62+(SRC_OAI_013-SRC_OAI_123)*D63 -> 6.6109589 | E65: =SRC_OAI_113+(SRC_OAI_123-SRC_OAI_113)*E62+(SRC_OAI_013-SRC_OAI_123)*E63 -> 7.8575342 | F65: =SRC_OAI_113+(SRC_OAI_123-SRC_OAI_113)*F62+(SRC_OAI_013-SRC_OAI_123)*F63 -> 5.3643836 | G65: =MIN(D65:F65) -> 5.3643836 | H65: =MAX(D65:F65) -> 7.8575342 | J65: 6.6 | K65: 5 | L65: 7.5 | Q65: 期初（1/1 至首次變價）回填事件 1 價（GPT-5.6 Sol）；事件 3、4 依序變價；事件 4、5 後＝2026-09-25 牌價快照
A66: PTO | B66: FY2026 平均牌價：頂層（Astra） 輸出 | C66: $/M | D66: =SRC_OAI_114+(SRC_OAI_124-SRC_OAI_114)*D62+(SRC_OAI_015-SRC_OAI_124)*D63 -> 36.246575 | E66: =SRC_OAI_114+(SRC_OAI_124-SRC_OAI_114)*E62+(SRC_OAI_015-SRC_OAI_124)*E63 -> 41.232877 | F66: =SRC_OAI_114+(SRC_OAI_124-SRC_OAI_114)*F62+(SRC_OAI_015-SRC_OAI_124)*F63 -> 31.260274 | G66: =MIN(D66:F66) -> 31.260274 | H66: =MAX(D66:F66) -> 41.232877 | J66: 35.8 | K66: 28 | L66: 40 | Q66: 期初（1/1 至首次變價）回填事件 1 價（GPT-5.6 Sol）；事件 3、4 依序變價；事件 4、5 後＝2026-09-25 牌價快照
A67: PMI | B67: FY2026 平均牌價：中層（Sol） 輸入 | C67: $/M | D67: =SRC_OAI_115+(SRC_OAI_119-SRC_OAI_115)*D61+(SRC_OAI_016-SRC_OAI_119)*D64 -> 2.2876712 | E67: =SRC_OAI_115+(SRC_OAI_119-SRC_OAI_115)*E61+(SRC_OAI_016-SRC_OAI_119)*E64 -> 2.1630137 | F67: =SRC_OAI_115+(SRC_OAI_119-SRC_OAI_115)*F61+(SRC_OAI_016-SRC_OAI_119)*F64 -> 2.4123288 | G67: =MIN(D67:F67) -> 2.1630137 | H67: =MAX(D67:F67) -> 2.4123288 | J67: 2.29 | K67: 2 | L67: 2.5 | Q67: 期初（1/1 至首次變價）回填事件 1 價（GPT-5.6 Terra）；事件 2、5 依序變價；事件 4、5 後＝2026-09-25 牌價快照
A68: PMO | B68: FY2026 平均牌價：中層（Sol） 輸出 | C68: $/M | D68: =SRC_OAI_116+(SRC_OAI_120-SRC_OAI_116)*D61+(SRC_OAI_018-SRC_OAI_120)*D64 -> 13.172603 | E68: =SRC_OAI_116+(SRC_OAI_120-SRC_OAI_116)*E61+(SRC_OAI_018-SRC_OAI_120)*E64 -> 11.926027 | F68: =SRC_OAI_116+(SRC_OAI_120-SRC_OAI_116)*F61+(SRC_OAI_018-SRC_OAI_120)*F64 -> 14.419178 | G68: =MIN(D68:F68) -> 11.926027 | H68: =MAX(D68:F68) -> 14.419178 | J68: 13.25 | K68: 11 | L68: 15 | Q68: 期初（1/1 至首次變價）回填事件 1 價（GPT-5.6 Terra）；事件 2、5 依序變價；事件 4、5 後＝2026-09-25 牌價快照
A69: PLI | B69: FY2026 平均牌價：低層（Luna） 輸入 | C69: $/M | D69: =SRC_OAI_117+(SRC_OAI_121-SRC_OAI_117)*D61+(SRC_OAI_019-SRC_OAI_121)*D64 -> 0.63260274 | E69: =SRC_OAI_117+(SRC_OAI_121-SRC_OAI_117)*E61+(SRC_OAI_019-SRC_OAI_121)*E64 -> 0.40821918 | F69: =SRC_OAI_117+(SRC_OAI_121-SRC_OAI_117)*F61+(SRC_OAI_019-SRC_OAI_121)*F64 -> 0.8569863 | G69: =MIN(D69:F69) -> 0.40821918 | H69: =MAX(D69:F69) -> 0.8569863 | J69: 0.64 | K69: 0.4 | L69: 0.8 | Q69: 期初（1/1 至首次變價）回填事件 1 價（GPT-5.6 Luna）；事件 2、5 依序變價；事件 4、5 後＝2026-09-25 牌價快照
A70: PLO | B70: FY2026 平均牌價：低層（Luna） 輸出 | C70: $/M | D70: =SRC_OAI_118+(SRC_OAI_122-SRC_OAI_118)*D61+(SRC_OAI_021-SRC_OAI_122)*D64 -> 3.7679452 | E70: =SRC_OAI_118+(SRC_OAI_122-SRC_OAI_118)*E61+(SRC_OAI_021-SRC_OAI_122)*E64 -> 2.3967123 | F70: =SRC_OAI_118+(SRC_OAI_122-SRC_OAI_118)*F61+(SRC_OAI_021-SRC_OAI_122)*F64 -> 5.1391781 | G70: =MIN(D70:F70) -> 2.3967123 | H70: =MAX(D70:F70) -> 5.1391781 | J70: 3.83 | K70: 2.5 | L70: 5 | Q70: 期初（1/1 至首次變價）回填事件 1 價（GPT-5.6 Luna）；事件 2、5 依序變價；事件 4、5 後＝2026-09-25 牌價快照

Sheet Checks
A1: Checks — P1 檢查（公式；結果 ERR 的格數＝CHK_Errors）
A2: OK／ERR：比對期望值；INFO：只列示。編號（C##）由 builder/id_registry.json 固定：新檢查取下一個號碼，退役號碼不重用（F1）。期望值為 builder 寫入的常數（黑字）。
A4: 編號 | B4: 檢查項 | C4: 值（公式） | D4: 期望 | E4: 結果 | F4: 說明
A5: C01 | B5: SRC_OAI 列數 | C5: =SUMPRODUCT(--(LEN(SRC_OAI!$A$5:$A$400)>0)) -> 122 | D5: 122 | E5: =IF(C5=D5,"OK","ERR") -> OK | F5: 報告所列筆數
A6: C02 | B6: SRC_OAI 缺值列數（Active） | C6: =SUM(SRC_OAI!$V$5:$V$400) -> 0 | D6: 0 | E6: =IF(C6=D6,"OK","ERR") -> OK | F6: 數值、低、高皆空且非文字列
A7: C03 | B7: SRC_OAI 缺出處列數（Active） | C7: =SUM(SRC_OAI!$W$5:$W$400) -> 0 | D7: 0 | E7: =IF(C7=D7,"OK","ERR") -> OK
A8: C04 | B8: SRC_OAI 區間順序異常列數 | C8: =SUM(SRC_OAI!$X$5:$X$400) -> 0 | D8: 0 | E8: =IF(C8=D8,"OK","ERR") -> OK | F8: 低 ≤ 值 ≤ 高
A9: C05 | B9: Inputs 列數 | C9: =SUMPRODUCT(--(LEN(Inputs!$A$5:$A$600)>0)) -> 243 | D9: 243 | E9: =IF(C9=D9,"OK","ERR") -> OK
A10: C06 | B10: Inputs 區間順序異常列數 | C10: =SUM(Inputs!$M$5:$M$600) -> 0 | D10: 0 | E10: =IF(C10=D10,"OK","ERR") -> OK | F10: 低 ≤ 值 ≤ 高（有三值者）
A11: C07 | B11: TK_Link 已取值名稱數 | C11: =COUNTIF(TK_Link!$F$10:$F$200,"OK") -> 62 | E11: INFO | F11: 取自 Tokenomics master CURRENT
A12: C08 | B12: TK_Link 待 Tokenomics 提供名稱數 | C12: =COUNTIF(TK_Link!$F$10:$F$200,"待 Tokenomics 提供") -> 0 | D12: 0 | E12: =IF(C12=D12,"OK","ERR") -> OK | F12: 工作單要求、Tokenomics 現行版尚無的名稱（值留空；v5.24 快照後為 0）
A13: C09 | B13: TK_Link 錯誤值格數 | C13: =SUMPRODUCT(--ISERROR(TK_Link!$J$10:$X$200)) -> 0 | D13: 0 | E13: =IF(C13=D13,"OK","ERR") -> OK
A14: C10 | B14: TK_IF_Util 介於 (0,1]（違反數） | C14: =IF(AND(TK_IF_Util>0,TK_IF_Util<=1),0,1) -> 0 | D14: 0 | E14: =IF(C14=D14,"OK","ERR") -> OK | F14: Tokenomics 基準利用率
A15: C11 | B15: 2025 推論支出：付費＋非付費−合計（$B） | C15: =SRC_OAI_049+SRC_OAI_048-SRC_OAI_047 -> 0 | D15: 0 | E15: =IF(ISNUMBER(C15),IF(ABS(C15-D15)<0.000000001,"OK","ERR"),"ERR") -> OK | F15: v0.5 三項同源（The Information 2026-02）
A16: C12 | B16: 2026-03 融資輪：無條件＋條件式−總額（$B） | C16: =SRC_OAI_109+SRC_OAI_110+SRC_OAI_111+SRC_OAI_112+SRC_OAI_082-SRC_OAI_080 -> 0 | D16: 0 | E16: =IF(ISNUMBER(C16),IF(ABS(C16-D16)<0.000000001,"OK","ERR"),"ERR") -> OK | F16: 122＝(15＋30＋30＋12)＋35（E8j：無條件部分由四個 SRC 組成加總）
A17: C13 | B17: 合約期間起>迄的合約數 | C17: =(SRC_OAI_059>SRC_OAI_060)+(SRC_OAI_063>SRC_OAI_064)+(SRC_OAI_066>SRC_OAI_067)+(SRC_OAI_071>SRC_OAI_072) -> 0 | D17: 0 | E17: =IF(C17=D17,"OK","ERR") -> OK | F17: Oracle、AWS×2、CoreWeave
A18: C14 | B18: 預覽：Oracle 隱含每 GW 年合約價（$B/GW/年） | C18: =IF(SRC_OAI_060-SRC_OAI_059+1>0,SRC_OAI_058/(SRC_OAI_060-SRC_OAI_059+1)/SRC_OAI_061,"期間無效") -> 13.333333 | E18: INFO | F18: P3 V2 可比（Oracle 遠期合約隱含 13.3；V8）
A19: C15 | B19: 預覽：AWS Trainium 隱含每 GW 年價（$B/GW/年） | C19: =IF(SRC_OAI_067-SRC_OAI_066+1>0,SRC_OAI_065/(SRC_OAI_067-SRC_OAI_066+1)/SRC_OAI_068,"期間無效") -> 6.25 | E19: INFO | F19: 自研晶片，只並列（工作單 P3-3）
A20: C16 | B20: 預覽：FY2025 推論支出−營業成本（$B） | C20: =SRC_OAI_047-SRC_OAI_003 -> 0.9 | E20: INFO | F20: 推論 8.4 高於營業成本 7.5：口徑差異，P3／P4 對帳時說明
A21: C17 | B21: 預覽：非算力研發 2025（$B）＝研發總額−訓練支出公式（V4） | C21: =SRC_OAI_087-C22 -> 7.18 | E21: INFO | F21: 工作單 V4：≈7.19（區間 5.68–8.59）
A22: C18 | B22: V6 衍生值：訓練支出 2025 基準（$B）＝SRC 10.59＋其他雲端 1.41 | C22: =SRC_OAI_098+Inputs!$E$223 -> 12 | D22: 12 | E22: =IF(ISNUMBER(C22),IF(ABS(C22-D22)<0.000000001,"OK","ERR"),"ERR") -> OK | F22: v0.5 值 12.0（對照）
A23: C19 | B23: V6 衍生值：訓練支出 2025 低（$B） | C23: =SRC_OAI_098+Inputs!$F$223 -> 10.59 | D23: 10.59 | E23: =IF(ISNUMBER(C23),IF(ABS(C23-D23)<0.000000001,"OK","ERR"),"ERR") -> OK | F23: v0.5 低 10.6
A24: C20 | B24: V6 衍生值：訓練支出 2025 高（$B） | C24: =SRC_OAI_098+Inputs!$G$223 -> 13.5 | D24: 13.5 | E24: =IF(ISNUMBER(C24),IF(ABS(C24-D24)<0.000000001,"OK","ERR"),"ERR") -> OK | F24: v0.5 高 13.5
A25: C21 | B25: V8：每 GW 年合約價參數列數（Inputs） | C25: =COUNTIF(Inputs!$B$5:$B$600,"*合約價*") -> 1 | D25: 1 | E25: =IF(C25=D25,"OK","ERR") -> OK | F25: 本模型只有一個合約價參數
A26: C22 | B26: V12：Pro 2026 占付費總數超出 SRC 上限的部分（0＝符合） | C26: =V9_ProViolation -> 0 | D26: 0 | E26: =IF(C26=D26,"OK","ERR") -> OK | F26: Inputs 比例須使 pro 占比 ≤ 內部預測『<1%』
A27: C23 | B27: E8d：tokenMix 的 low＝1−top−mid 在基準／低／高情境皆 ∈[0,1]（違反數） | C27: =((1-Inputs!$E$28-Inputs!$E$30)<0)+((1-Inputs!$E$28-Inputs!$E$30)>1)+((1-Inputs!$G$28-Inputs!$G$30)<0)+((1-Inputs!$G$28-Inputs!$G$30)>1)+((1-Inputs!$F$28-Inputs!$F$30)<0)+((1-Inputs!$F$28-Inputs!$F$30)>1)+((1-Inputs!$E$29-Inputs!$E$31)<0)+((1-Inputs!$E$29-Inputs!$E$31)>1)+((1-Inputs!$G$29-Inputs!$G$31)<0)+((1-Inputs!$G$29-Inputs!$G$31)>1)+((1-Inputs!$F$29-Inputs!$F$31)<0)+((1-Inputs!$F$29-Inputs!$F$31)>1) -> 0 | D27: 0 | E27: =IF(C27=D27,"OK","ERR") -> OK | F27: 兩個時點 × 三個情境；low 不另設區間
A28: C24 | B28: E8g：Inputs AWS 容量上限＝WSJ 推論＋訓練（GW） | C28: =Inputs!$G$236-V9_AwsWsj -> 0 | D28: 0 | E28: =IF(ISNUMBER(C28),IF(ABS(C28-D28)<0.000000001,"OK","ERR"),"ERR") -> OK | F28: 『5』由 SRC 兩筆揭露相加
A29: C25 | B29: E8j：無條件部分四個組成加總＝v0.5 值（$B） | C29: =V9_Uncond2026 -> 87 | D29: 87 | E29: =IF(ISNUMBER(C29),IF(ABS(C29-D29)<0.000000001,"OK","ERR"),"ERR") -> OK | F29: 15＋30＋30＋12
A30: C26 | B30: E8f：Oracle 合約年額＝v0.5 值（$B/年） | C30: =V9_OracleAnnual -> 60 | D30: 60 | E30: =IF(ISNUMBER(C30),IF(ABS(C30-D30)<0.000000001,"OK","ERR"),"ERR") -> OK | F30: 總額÷年數
A31: C28 | B31: P2：2025 模型營收總額 − SRC 實際營收（$B；v0.5 校準恆等式） | C31: =REV_Gap2025 -> 0 | D31: 0 | E31: =IF(ISNUMBER(C31),IF(ABS(C31-D31)<0.000000001,"OK","ERR"),"ERR") -> OK | F31: 2025 API 為倒推項；不為 0 表示校準鏈斷裂
A32: C29 | B32: P2：2025 API 計費比例 ∈ (0,1]（違反數） | C32: =IF(AND(DEM_ApiBilledRatio2025>0,DEM_ApiBilledRatio2025<=1),0,1) -> 0 | D32: 0 | E32: =IF(C32=D32,"OK","ERR") -> OK | F32: 計費 token（營收倒推）÷ 處理 token（Derived_V9 V22）；≤0 表示訂閱＋廣告已超過實際營收
A33: C30 | B33: P2：方案模型組合 luna＋sol＋astra≠1 的方案數 | C33: =(ABS(Inputs!$E$149+Inputs!$E$150+Inputs!$E$151-1)>0.000000001)+(ABS(Inputs!$E$154+Inputs!$E$155+Inputs!$E$156-1)>0.000000001)+(ABS(Inputs!$E$159+Inputs!$E$160+Inputs!$E$161-1)>0.000000001)+(ABS(Inputs!$E$164+Inputs!$E$165+Inputs!$E$166-1)>0.000000001)+(ABS(Inputs!$E$169+Inputs!$E$170+Inputs!$E$171-1)>0.000000001) -> 0 | D33: 0 | E33: =IF(C33=D33,"OK","ERR") -> OK | F33: Inputs INP_155–179；token 層級拆分的前提
A34: C31 | B34: P2：token 層級拆分合計 vs 拆分前總量（違反年數） | C34: =SUMPRODUCT(--(ABS(Demand!$D$51:$I$51-Demand!$D$52:$I$52)>0.000000001*Demand!$D$52:$I$52)) -> 0 | D34: 0 | E34: =IF(C34=D34,"OK","ERR") -> OK | F34: 付費＋免費（層級）＝訂閱＋免費＋API 計費 token
A35: C32 | B35: P2：消費端＋企業端＋其他 − 總額（各年絕對值合計，$B） | C35: =SUMPRODUCT(ABS(Revenue!$D$45:$I$45)) -> 0 | D35: 0 | E35: =IF(ISNUMBER(C35),IF(ABS(C35-D35)<0.000000001,"OK","ERR"),"ERR") -> OK | F35: v0.5 檢查列
A36: C33 | B36: P2：Microsoft 分成累計超出上限的部分（$B） | C36: =MAX(0,MAX(REV_MSCum)-SRC_OAI_010) -> 0 | D36: 0 | E36: =IF(ISNUMBER(C36),IF(ABS(C36-D36)<0.000000001,"OK","ERR"),"ERR") -> OK | F36: 上限 $38B（SRC_OAI）
A37: C34 | B37: E8c：價格事件生效日順序違反數（基準／提前／延後三欄） | C37: =(Revenue!D62<Revenue!D63)+(Revenue!D61<Revenue!D64)+(Revenue!E62<Revenue!E63)+(Revenue!E61<Revenue!E64)+(Revenue!F62<Revenue!F63)+(Revenue!F61<Revenue!F64) -> 0 | D37: 0 | E37: =IF(C37=D37,"OK","ERR") -> OK | F37: top 層：事件 3（促銷）須不晚於事件 4（Astra）；mid／low 層：事件 2 須不晚於事件 5
A38: C35 | B38: E8c：2026 牌價區間 低 ≤ 基準 ≤ 高 的違反數（6 列） | C38: =(Revenue!G65>Revenue!D65)+(Revenue!D65>Revenue!H65)+(Revenue!G66>Revenue!D66)+(Revenue!D66>Revenue!H66)+(Revenue!G67>Revenue!D67)+(Revenue!D67>Revenue!H67)+(Revenue!G68>Revenue!D68)+(Revenue!D68>Revenue!H68)+(Revenue!G69>Revenue!D69)+(Revenue!D69>Revenue!H69)+(Revenue!G70>Revenue!D70)+(Revenue!D70>Revenue!H70) -> 0 | D38: 0 | E38: =IF(C38=D38,"OK","ERR") -> OK | F38: listPriceFYAvg 2026 區間由事件時點 Inputs 傳遞（取代 C27 WARN）
A39: C36 | B39: D11：Inputs 情境 base 列＝各參數基準值（違反數） | C39: =(INP_143<>INP_048)+(INP_144<>INP_049)+(INP_145<>INP_123)+(INP_146<>INP_021)+(INP_147<>INP_022)+(INP_148<>INP_023) -> 0 | D39: 0 | E39: =IF(C39=D39,"OK","ERR") -> OK | F39: 本版未設情境選擇器；基準引用各參數 Inputs 值欄，情境列只作對照
A40: C37 | B40: P2 預覽：2025 token 合計 ÷ Tokenomics IF_AllocDemand | C40: =DEM_TkRatio2025 -> 0.84436545 | E40: INFO | F40: 口徑不同，只列差距（工作單 P2-3）
A41: C38 | B41: P2 預覽：2025 未校準差距（$B）＝訂閱＋廣告＋其他＋處理 token×單價 − 實際 | C41: =REV_GapUncal2025 -> 1.0287055 | E41: INFO | F41: 自下而上口徑對實際
A42: C39 | B42: P2 預覽：2030 淨營收（$B） | C42: =Revenue!$I$41 -> 126.38309 | E42: INFO | F42: 總額 − Microsoft 分成
A44: CHK_Errors | C44: =COUNTIF($E$5:$E$42,"ERR") -> 0

Sheet Map_v05
A1: Map_v05 — v0.5 JSON 每個葉節點的去處（表 1 的明細）
A2: 類別：SRC_OAI／Inputs／公式（後續工作包）／重複併入／不遷入／不遷入；改取 TK_Link。『值』欄為 v0.5 原值（含不遷入者）。
A4: v0.5 路徑 | B4: v0.5 值 | C4: 去處類別 | D4: 去處 | E4: 理由／備註
A5: _readme | B5: "v0.5（2026-09-30）：核心改為算力 MW（Vera Rubin 等值，VR-eq）。token 需求→推論 MW；合約與自建→供給 MW；成本＝MW×每 MW 成本；營收以可用 MW 為上限（V1a）；供應商資金僅列或有（V2a）。VR 規格預設沿用 Tokenomics v4，要改一起改。每個輸入附 chk 查核狀態。" | C5: 不遷入 | D5: — | E5: 版本說明文字；v0.6 的版本說明在 README／CHANGELOG
A6: tokenRevenue.meta.company | B6: "OpenAI" | C6: 不遷入 | D6: — | E6: 公司名稱：表頭文字，不是參數
A7: tokenRevenue.meta.fiscalYearEndMonth | B7: 12 | C7: 不遷入 | D7: — | E7: 工作單第 0 節已定：曆年制（12 月）；v0.6 不設此參數
A8: tokenRevenue.meta.years.0 | B8: 2025 | C8: Inputs | D8: INP_005
A9: tokenRevenue.meta.years.1 | B9: 2026 | C9: Inputs | D9: INP_006
A10: tokenRevenue.meta.years.2 | B10: 2027 | C10: Inputs | D10: INP_007
A11: tokenRevenue.meta.years.3 | B11: 2028 | C11: Inputs | D11: INP_008
A12: tokenRevenue.meta.years.4 | B12: 2029 | C12: Inputs | D12: INP_009
A13: tokenRevenue.meta.years.5 | B13: 2030 | C13: Inputs | D13: INP_010
A14: tokenRevenue.meta.baseYear | B14: 2025 | C14: Inputs | D14: INP_001
A15: tokenRevenue.meta.calibrationYears.0 | B15: 2025 | C15: Inputs | D15: INP_002
A16: tokenRevenue.meta.calibrationYears.1 | B16: 2026 | C16: Inputs | D16: INP_003
A17: tokenRevenue.meta.elasticityFromYear | B17: 2027 | C17: Inputs | D17: INP_004
A18: tokenRevenue.meta.units.revenue | B18: "$B" | C18: 不遷入 | D18: — | E18: 單位字串：v0.6 每列自帶單位欄
A19: tokenRevenue.meta.units.tokens | B19: "T (1e12)" | C19: 不遷入 | D19: — | E19: 單位字串：v0.6 每列自帶單位欄
A20: tokenRevenue.meta.units.price | B20: "$/M tokens" | C20: 不遷入 | D20: — | E20: 單位字串：v0.6 每列自帶單位欄
A21: tokenRevenue.meta.units.subs | B21: "M" | C21: 不遷入 | D21: — | E21: 單位字串：v0.6 每列自帶單位欄
A22: tokenRevenue.meta.units.arpu | B22: "$/month" | C22: 不遷入 | D22: — | E22: 單位字串：v0.6 每列自帶單位欄
A23: tokenRevenue.meta.decisions | B23: "D1c D2b D3b D4→正反兩模式 D5b D6 D7c D8a D10→FY2030 D11 D12a；N1b N2a N3a；S1c S2 S3 S4b S5a S6c S7；R1 R2 R3（Andy 2026-09-29）" | C23: 不遷入 | D23: — | E23: 決策 ID 清單：v0.6 逐項在 Inputs「v0.5 原決策」欄保留；完整文字見 reference/v0.5
A24: tokenRevenue.meta.version | B24: "0.4" | C24: 不遷入 | D24: — | E24: v0.4 的版本字串，已過時
A25: tokenRevenue.actuals.revenue2024.v | B25: 3.7 | C25: SRC_OAI | D25: SRC_OAI_001
A26: tokenRevenue.actuals.revenue2024.tag | B26: "Interested-party" | C26: SRC_OAI | D26: SRC_OAI_001 | E26: 隨附資訊
A27: tokenRevenue.actuals.revenue2024.src | B27: "OpenAI 揭露經媒體報導；workbook OpenAI_Sim B5" | C27: SRC_OAI | D27: SRC_OAI_001 | E27: 隨附資訊
A28: tokenRevenue.actuals.revenue2025.v | B28: 13.07 | C28: SRC_OAI | D28: SRC_OAI_002
A29: tokenRevenue.actuals.revenue2025.tag | B29: "Interested-party" | C29: SRC_OAI | D29: SRC_OAI_002 | E29: 隨附資訊
A30: tokenRevenue.actuals.revenue2025.src | B30: "Fortune/FT 2026-06 報導之 FY2025 認列營收（經查核數字外流）" | C30: SRC_OAI | D30: SRC_OAI_002 | E30: 隨附資訊
A31: tokenRevenue.actuals.cogs2025.v | B31: 7.5 | C31: SRC_OAI | D31: SRC_OAI_003
A32: tokenRevenue.actuals.cogs2025.tag | B32: "Interested-party" | C32: SRC_OAI | D32: SRC_OAI_003 | E32: 隨附資訊
A33: tokenRevenue.actuals.cogs2025.src | B33: "同上；cost of revenue 含推論" | C33: SRC_OAI | D33: SRC_OAI_003 | E33: 隨附資訊
A34: tokenRevenue.actuals.revenueQ1_2026.v | B34: 5.7 | C34: SRC_OAI | D34: SRC_OAI_004
A35: tokenRevenue.actuals.revenueQ1_2026.tag | B35: "Interested-party" | C35: SRC_OAI | D35: SRC_OAI_004 | E35: 隨附資訊
A36: tokenRevenue.actuals.revenueQ1_2026.src | B36: "The Information 2026-06-16（股東文件）" | C36: SRC_OAI | D36: SRC_OAI_004 | E36: 隨附資訊
A37: tokenRevenue.actuals.revenueQ2_2026.v | B37: 6.7 | C37: SRC_OAI | D37: SRC_OAI_005
A38: tokenRevenue.actuals.revenueQ2_2026.tag | B38: "Interested-party" | C38: SRC_OAI | D38: SRC_OAI_005 | E38: 隨附資訊
A39: tokenRevenue.actuals.revenueQ2_2026.src | B39: "WSJ 2026-08-18（告知投資人）" | C39: SRC_OAI | D39: SRC_OAI_005 | E39: 隨附資訊
A40: tokenRevenue.actuals.arrAug2026.v | B40: 40 | C40: SRC_OAI | D40: SRC_OAI_006
A41: tokenRevenue.actuals.arrAug2026.tag | B41: "Interested-party" | C41: SRC_OAI | D41: SRC_OAI_006 | E41: 隨附資訊
A42: tokenRevenue.actuals.arrAug2026.src | B42: "Bloomberg 2026-08-13；CNBC 2026-08-14 證實" | C42: SRC_OAI | D42: SRC_OAI_006 | E42: 隨附資訊
A43: tokenRevenue.actuals.consumerShareStart2026.v | B43: 0.6 | C43: SRC_OAI | D43: SRC_OAI_007
A44: tokenRevenue.actuals.consumerShareStart2026.tag | B44: "Interested-party" | C44: SRC_OAI | D44: SRC_OAI_007 | E44: 隨附資訊
A45: tokenRevenue.actuals.consumerShareStart2026.src | B45: "CFO Friar 2026-08-14 投資人會議：年初 60/40，8 月企業已超過消費端（CNBC）" | C45: SRC_OAI | D45: SRC_OAI_007 | E45: 隨附資訊
A46: tokenRevenue.actuals.apiTokensPerMinOct2025.v | B46: 6.0 | C46: SRC_OAI | D46: SRC_OAI_008
A47: tokenRevenue.actuals.apiTokensPerMinOct2025.unit | B47: "B tok/min" | C47: SRC_OAI | D47: SRC_OAI_008 | E47: 隨附資訊
A48: tokenRevenue.actuals.apiTokensPerMinOct2025.tag | B48: "Interested-party" | C48: SRC_OAI | D48: SRC_OAI_008 | E48: 隨附資訊
A49: tokenRevenue.actuals.apiTokensPerMinOct2025.src | B49: "Altman DevDay 2025-10；2026 年更新揭露檢索未得" | C49: SRC_OAI | D49: SRC_OAI_008 | E49: 隨附資訊
A50: tokenRevenue.actuals.apiTokensFY2025.v | B50: 2628 | C50: 公式（後續工作包） | D50: Derived_V9（V10–V12：API FY2025 token＝每分鐘 token×每年分鐘數÷單位換算） | E50: E8a：Derived→公式；驅動值『FY 平均每分鐘 5B token』進 Inputs（Assumed，3.8–6.1）；v0.5 值 2,628（2,000–3,200）並列於 Derived_V9
A51: tokenRevenue.actuals.apiTokensFY2025.lo | B51: 2000 | C51: 公式（後續工作包） | D51: Derived_V9（V10–V12：API FY2025 token＝每分鐘 token×每年分鐘數÷單位換算） | E51: E8a：Derived→公式；驅動值『FY 平均每分鐘 5B token』進 Inputs（Assumed，3.8–6.1）；v0.5 值 2,628（2,000–3,200）並列於 Derived_V9
A52: tokenRevenue.actuals.apiTokensFY2025.hi | B52: 3200 | C52: 公式（後續工作包） | D52: Derived_V9（V10–V12：API FY2025 token＝每分鐘 token×每年分鐘數÷單位換算） | E52: E8a：Derived→公式；驅動值『FY 平均每分鐘 5B token』進 Inputs（Assumed，3.8–6.1）；v0.5 值 2,628（2,000–3,200）並列於 Derived_V9
A53: tokenRevenue.actuals.apiTokensFY2025.unit | B53: "T processed" | C53: 公式（後續工作包） | D53: Derived_V9（V10–V12：API FY2025 token＝每分鐘 token×每年分鐘數÷單位換算） | E53: E8a：Derived→公式；驅動值『FY 平均每分鐘 5B token』進 Inputs（Assumed，3.8–6.1）；v0.5 值 2,628（2,000–3,200）並列於 Derived_V9
A54: tokenRevenue.actuals.apiTokensFY2025.tag | B54: "Derived" | C54: 公式（後續工作包） | D54: Derived_V9（V10–V12：API FY2025 token＝每分鐘 token×每年分鐘數÷單位換算） | E54: E8a：Derived→公式；驅動值『FY 平均每分鐘 5B token』進 Inputs（Assumed，3.8–6.1）；v0.5 值 2,628（2,000–3,200）並列於 Derived_V9
A55: tokenRevenue.actuals.apiTokensFY2025.src | B55: "FY 平均約 5B/min（workbook 列 242 估計）× 525,600 分" | C55: 公式（後續工作包） | D55: Derived_V9（V10–V12：API FY2025 token＝每分鐘 token×每年分鐘數÷單位換算） | E55: E8a：Derived→公式；驅動值『FY 平均每分鐘 5B token』進 Inputs（Assumed，3.8–6.1）；v0.5 值 2,628（2,000–3,200）並列於 Derived_V9
A56: tokenRevenue.actuals.apiTokensFY2025.chk | B56: "待查核-workbook" | C56: 公式（後續工作包） | D56: Derived_V9（V10–V12：API FY2025 token＝每分鐘 token×每年分鐘數÷單位換算） | E56: E8a：Derived→公式；驅動值『FY 平均每分鐘 5B token』進 Inputs（Assumed，3.8–6.1）；v0.5 值 2,628（2,000–3,200）並列於 Derived_V9
A57: tokenRevenue.msShare.rate.v | B57: 0.2 | C57: SRC_OAI | D57: SRC_OAI_009
A58: tokenRevenue.msShare.rate.tag | B58: "Interested-party" | C58: SRC_OAI | D58: SRC_OAI_009 | E58: 隨附資訊
A59: tokenRevenue.msShare.rate.src | B59: "CNBC 2026-04-27 引述知情人士；VentureBeat 同" | C59: SRC_OAI | D59: SRC_OAI_009 | E59: 隨附資訊
A60: tokenRevenue.msShare.capTotal.v | B60: 38 | C60: SRC_OAI | D60: SRC_OAI_010
A61: tokenRevenue.msShare.capTotal.tag | B61: "Interested-party" | C61: SRC_OAI | D61: SRC_OAI_010 | E61: 隨附資訊
A62: tokenRevenue.msShare.capTotal.src | B62: "The Information 2026-05（經 AI Magazine、GuruFocus 轉述）" | C62: SRC_OAI | D62: SRC_OAI_010 | E62: 隨附資訊
A63: tokenRevenue.msShare.capThroughYear.v | B63: 2030 | C63: SRC_OAI | D63: SRC_OAI_011
A64: tokenRevenue.msShare.capThroughYear.tag | B64: "Verified" | C64: SRC_OAI | D64: SRC_OAI_011 | E64: 隨附資訊
A65: tokenRevenue.msShare.capThroughYear.src | B65: "OpenAI／Microsoft 2026-04-27 公告：付款持續至 2030，受總額上限" | C65: SRC_OAI | D65: SRC_OAI_011 | E65: 隨附資訊
A66: tokenRevenue.msShare.capCountFromYear.v | B66: 2026 | C66: Inputs | D66: INP_011
A67: tokenRevenue.msShare.capCountFromYear.tag | B67: "Assumed" | C67: Inputs | D67: INP_011 | E67: 隨附資訊
A68: tokenRevenue.msShare.capCountFromYear.src | B68: "起算點未揭露；Andy 2026-09-29 決定 N2a" | C68: Inputs | D68: INP_011 | E68: 隨附資訊
A69: tokenRevenue.msShare.azureInflowAfterApr2026.v | B69: 0 | C69: SRC_OAI | D69: SRC_OAI_012
A70: tokenRevenue.msShare.azureInflowAfterApr2026.tag | B70: "Verified" | C70: SRC_OAI | D70: SRC_OAI_012 | E70: 隨附資訊
A71: tokenRevenue.msShare.azureInflowAfterApr2026.src | B71: "2026-04-27 公告：Microsoft 不再支付 OpenAI 分潤" | C71: SRC_OAI | D71: SRC_OAI_012 | E71: 隨附資訊
A72: tokenRevenue.api.tiers.0 | B72: "top" | C72: 不遷入 | D72: — | E72: 層級清單（top／mid／low）：結構，由公式頁的列結構體現
A73: tokenRevenue.api.tiers.1 | B73: "mid" | C73: 不遷入 | D73: — | E73: 層級清單（top／mid／low）：結構，由公式頁的列結構體現
A74: tokenRevenue.api.tiers.2 | B74: "low" | C74: 不遷入 | D74: — | E74: 層級清單（top／mid／low）：結構，由公式頁的列結構體現
A75: tokenRevenue.api.tierMapSep2026.top | B75: "gpt-6-astra" | C75: SRC_OAI | D75: SRC_OAI_022
A76: tokenRevenue.api.tierMapSep2026.mid | B76: "gpt-6-sol" | C76: SRC_OAI | D76: SRC_OAI_023
A77: tokenRevenue.api.tierMapSep2026.low | B77: "gpt-6-luna" | C77: SRC_OAI | D77: SRC_OAI_024
A78: tokenRevenue.api.listPriceSnapshot.date | B78: "2026-09-25" | C78: SRC_OAI | D78: API 牌價快照列 | E78: 快照日期：寫入各列日期欄
A79: tokenRevenue.api.listPriceSnapshot.tag | B79: "Verified" | C79: SRC_OAI | D79: SRC_OAI_013 | E79: 隨附資訊
A80: tokenRevenue.api.listPriceSnapshot.src | B80: "developers.openai.com/api/docs/pricing（短上下文 Standard）" | C80: SRC_OAI | D80: SRC_OAI_013 | E80: 隨附資訊
A81: tokenRevenue.api.listPriceSnapshot.top.in | B81: 10.0 | C81: SRC_OAI | D81: SRC_OAI_013
A82: tokenRevenue.api.listPriceSnapshot.top.cached | B82: 1.0 | C82: SRC_OAI | D82: SRC_OAI_014
A83: tokenRevenue.api.listPriceSnapshot.top.out | B83: 50.0 | C83: SRC_OAI | D83: SRC_OAI_015
A84: tokenRevenue.api.listPriceSnapshot.mid.in | B84: 2.0 | C84: SRC_OAI | D84: SRC_OAI_016
A85: tokenRevenue.api.listPriceSnapshot.mid.cached | B85: 0.2 | C85: SRC_OAI | D85: SRC_OAI_017
A86: tokenRevenue.api.listPriceSnapshot.mid.out | B86: 10.0 | C86: SRC_OAI | D86: SRC_OAI_018
A87: tokenRevenue.api.listPriceSnapshot.low.in | B87: 0.1 | C87: SRC_OAI | D87: SRC_OAI_019
A88: tokenRevenue.api.listPriceSnapshot.low.cached | B88: 0.01 | C88: SRC_OAI | D88: SRC_OAI_020
A89: tokenRevenue.api.listPriceSnapshot.low.out | B89: 0.5 | C89: SRC_OAI | D89: SRC_OAI_021
A90: tokenRevenue.api.priceEvents2026.tag | B90: "Verified" | C90: SRC_OAI | D90: SRC_OAI_025 | E90: 隨附資訊
A91: tokenRevenue.api.priceEvents2026.src | B91: "openai.com 2026-07-30 GPT-5.6 降價公告；GPT-6 Sol/Luna 2026-09-22 發布（Techzine、MarkTechPost）；GPT-6 Astra 2026-09-03" | C91: SRC_OAI | D91: SRC_OAI_025 | E91: 隨附資訊
A92: tokenRevenue.api.priceEvents2026.list.0 | B92: "07-09 GPT-5.6 Sol 5/30、Terra 2.5/15、Luna 1/6" | C92: SRC_OAI | D92: SRC_OAI_025
A93: tokenRevenue.api.priceEvents2026.list.1 | B93: "07-30 Terra 2/12（-20%）、Luna 0.2/1.2（-80%）" | C93: SRC_OAI | D93: SRC_OAI_026
A94: tokenRevenue.api.priceEvents2026.list.2 | B94: "08-22 Sol 促銷 4/20" | C94: SRC_OAI | D94: SRC_OAI_027
A95: tokenRevenue.api.priceEvents2026.list.3 | B95: "09-03 GPT-6 Astra 10/50（新旗艦，層級價格上升）" | C95: SRC_OAI | D95: SRC_OAI_028
A96: tokenRevenue.api.priceEvents2026.list.4 | B96: "09-22 GPT-6 Sol 2/10、Luna 0.1/0.5" | C96: SRC_OAI | D96: SRC_OAI_029
A97: tokenRevenue.api.listPriceFYAvg._note | B97: "依層級角色（top/mid/low）的 FY 平均牌價；2025 為 Analogy，2026 由上列事件按月加權 [Derived]" | C97: Inputs | D97: INP（listPriceFYAvg） | E97: 說明：2025 為 Analogy、2026 由事件月加權 [Derived]
A98: tokenRevenue.api.listPriceFYAvg.in.top.v.0 | B98: 2.5 | C98: Inputs | D98: INP_015
A99: tokenRevenue.api.listPriceFYAvg.in.top.v.1 | B99: 6.6 | C99: 公式（後續工作包） | D99: Revenue R01–R06 的 2026 欄（P2 實作：價格事件時點天數加權，Revenue 第七節；E8c） | E99: Derived：2026 由價格事件按月加權；v0.5 標 Analogy/Derived 混合，依元素分開（2025→Inputs、2026→公式）
A100: tokenRevenue.api.listPriceFYAvg.in.top.lo.0 | B100: 1.5 | C100: Inputs | D100: INP_015
A101: tokenRevenue.api.listPriceFYAvg.in.top.lo.1 | B101: 5.0 | C101: 公式（後續工作包） | D101: Revenue R01–R06 的 2026 欄（P2 實作：價格事件時點天數加權，Revenue 第七節；E8c） | E101: Derived：2026 由價格事件按月加權；v0.5 標 Analogy/Derived 混合，依元素分開（2025→Inputs、2026→公式）
...

Sheet _Defaults
A1: sheet | B1: id | C1: col | D1: builder 預設值（上次寫入）
A2: SRC_OAI | B2: SRC_OAI_001 | C2: C | D2: 3.7
A3: SRC_OAI | B3: SRC_OAI_001 | C3: D
A4: SRC_OAI | B4: SRC_OAI_001 | C4: E
A5: SRC_OAI | B5: SRC_OAI_002 | C5: C | D5: 13.07
A6: SRC_OAI | B6: SRC_OAI_002 | C6: D
A7: SRC_OAI | B7: SRC_OAI_002 | C7: E
A8: SRC_OAI | B8: SRC_OAI_003 | C8: C | D8: 7.5
A9: SRC_OAI | B9: SRC_OAI_003 | C9: D
A10: SRC_OAI | B10: SRC_OAI_003 | C10: E
A11: SRC_OAI | B11: SRC_OAI_004 | C11: C | D11: 5.7
A12: SRC_OAI | B12: SRC_OAI_004 | C12: D
A13: SRC_OAI | B13: SRC_OAI_004 | C13: E
A14: SRC_OAI | B14: SRC_OAI_005 | C14: C | D14: 6.7
A15: SRC_OAI | B15: SRC_OAI_005 | C15: D
A16: SRC_OAI | B16: SRC_OAI_005 | C16: E
A17: SRC_OAI | B17: SRC_OAI_006 | C17: C | D17: 40
A18: SRC_OAI | B18: SRC_OAI_006 | C18: D
A19: SRC_OAI | B19: SRC_OAI_006 | C19: E
A20: SRC_OAI | B20: SRC_OAI_007 | C20: C | D20: 0.6
A21: SRC_OAI | B21: SRC_OAI_007 | C21: D
A22: SRC_OAI | B22: SRC_OAI_007 | C22: E
A23: SRC_OAI | B23: SRC_OAI_008 | C23: C | D23: 6
A24: SRC_OAI | B24: SRC_OAI_008 | C24: D
A25: SRC_OAI | B25: SRC_OAI_008 | C25: E
A26: SRC_OAI | B26: SRC_OAI_009 | C26: C | D26: 0.2
A27: SRC_OAI | B27: SRC_OAI_009 | C27: D
A28: SRC_OAI | B28: SRC_OAI_009 | C28: E
A29: SRC_OAI | B29: SRC_OAI_010 | C29: C | D29: 38
A30: SRC_OAI | B30: SRC_OAI_010 | C30: D
A31: SRC_OAI | B31: SRC_OAI_010 | C31: E
A32: SRC_OAI | B32: SRC_OAI_011 | C32: C | D32: 2030
A33: SRC_OAI | B33: SRC_OAI_011 | C33: D
A34: SRC_OAI | B34: SRC_OAI_011 | C34: E
A35: SRC_OAI | B35: SRC_OAI_012 | C35: C | D35: 0
A36: SRC_OAI | B36: SRC_OAI_012 | C36: D
A37: SRC_OAI | B37: SRC_OAI_012 | C37: E
A38: SRC_OAI | B38: SRC_OAI_013 | C38: C | D38: 10
A39: SRC_OAI | B39: SRC_OAI_013 | C39: D
A40: SRC_OAI | B40: SRC_OAI_013 | C40: E
A41: SRC_OAI | B41: SRC_OAI_014 | C41: C | D41: 1
A42: SRC_OAI | B42: SRC_OAI_014 | C42: D
A43: SRC_OAI | B43: SRC_OAI_014 | C43: E
A44: SRC_OAI | B44: SRC_OAI_015 | C44: C | D44: 50
A45: SRC_OAI | B45: SRC_OAI_015 | C45: D
A46: SRC_OAI | B46: SRC_OAI_015 | C46: E
A47: SRC_OAI | B47: SRC_OAI_016 | C47: C | D47: 2
A48: SRC_OAI | B48: SRC_OAI_016 | C48: D
A49: SRC_OAI | B49: SRC_OAI_016 | C49: E
A50: SRC_OAI | B50: SRC_OAI_017 | C50: C | D50: 0.2
A51: SRC_OAI | B51: SRC_OAI_017 | C51: D
A52: SRC_OAI | B52: SRC_OAI_017 | C52: E
A53: SRC_OAI | B53: SRC_OAI_018 | C53: C | D53: 10
A54: SRC_OAI | B54: SRC_OAI_018 | C54: D
A55: SRC_OAI | B55: SRC_OAI_018 | C55: E
A56: SRC_OAI | B56: SRC_OAI_019 | C56: C | D56: 0.1
A57: SRC_OAI | B57: SRC_OAI_019 | C57: D
A58: SRC_OAI | B58: SRC_OAI_019 | C58: E
A59: SRC_OAI | B59: SRC_OAI_020 | C59: C | D59: 0.01
A60: SRC_OAI | B60: SRC_OAI_020 | C60: D
A61: SRC_OAI | B61: SRC_OAI_020 | C61: E
A62: SRC_OAI | B62: SRC_OAI_021 | C62: C | D62: 0.5
A63: SRC_OAI | B63: SRC_OAI_021 | C63: D
A64: SRC_OAI | B64: SRC_OAI_021 | C64: E
A65: SRC_OAI | B65: SRC_OAI_022 | C65: C | D65: gpt-6-astra
A66: SRC_OAI | B66: SRC_OAI_022 | C66: D
A67: SRC_OAI | B67: SRC_OAI_022 | C67: E
A68: SRC_OAI | B68: SRC_OAI_023 | C68: C | D68: gpt-6-sol
A69: SRC_OAI | B69: SRC_OAI_023 | C69: D
A70: SRC_OAI | B70: SRC_OAI_023 | C70: E
A71: SRC_OAI | B71: SRC_OAI_024 | C71: C | D71: gpt-6-luna
A72: SRC_OAI | B72: SRC_OAI_024 | C72: D
A73: SRC_OAI | B73: SRC_OAI_024 | C73: E
A74: SRC_OAI | B74: SRC_OAI_025 | C74: C | D74: 07-09 GPT-5.6 Sol 5/30、Terra 2.5/15、Luna 1/6
A75: SRC_OAI | B75: SRC_OAI_025 | C75: D
A76: SRC_OAI | B76: SRC_OAI_025 | C76: E
A77: SRC_OAI | B77: SRC_OAI_026 | C77: C | D77: 07-30 Terra 2/12（-20%）、Luna 0.2/1.2（-80%）
A78: SRC_OAI | B78: SRC_OAI_026 | C78: D
A79: SRC_OAI | B79: SRC_OAI_026 | C79: E
A80: SRC_OAI | B80: SRC_OAI_027 | C80: C | D80: 08-22 Sol 促銷 4/20
A81: SRC_OAI | B81: SRC_OAI_027 | C81: D
A82: SRC_OAI | B82: SRC_OAI_027 | C82: E
A83: SRC_OAI | B83: SRC_OAI_028 | C83: C | D83: 09-03 GPT-6 Astra 10/50（新旗艦，層級價格上升）
A84: SRC_OAI | B84: SRC_OAI_028 | C84: D
A85: SRC_OAI | B85: SRC_OAI_028 | C85: E
A86: SRC_OAI | B86: SRC_OAI_029 | C86: C | D86: 09-22 GPT-6 Sol 2/10、Luna 0.1/0.5
A87: SRC_OAI | B87: SRC_OAI_029 | C87: D
A88: SRC_OAI | B88: SRC_OAI_029 | C88: E
A89: SRC_OAI | B89: SRC_OAI_030 | C89: C | D89: 0.1
A90: SRC_OAI | B90: SRC_OAI_030 | C90: D
A91: SRC_OAI | B91: SRC_OAI_030 | C91: E
A92: SRC_OAI | B92: SRC_OAI_031 | C92: C | D92: 8
A93: SRC_OAI | B93: SRC_OAI_031 | C93: D
A94: SRC_OAI | B94: SRC_OAI_031 | C94: E
A95: SRC_OAI | B95: SRC_OAI_032 | C95: C | D95: 20
A96: SRC_OAI | B96: SRC_OAI_032 | C96: D
A97: SRC_OAI | B97: SRC_OAI_032 | C97: E
A98: SRC_OAI | B98: SRC_OAI_033 | C98: C | D98: 100
A99: SRC_OAI | B99: SRC_OAI_033 | C99: D
A100: SRC_OAI | B100: SRC_OAI_033 | C100: E
...
