Workbook

Sheet README
A1: 每 GW 晶片內容橋接表（AI 半導體專案 步驟 0）v0.2.1 2026-10-23
A2: v0.2.1：Tokenomics 快照改 v20.1（v19.0→v20.1 為 LifeSelf 主口徑與 L1_PriceReqBE 的 L 改動，與本表使用的名稱無關）；IF_CapexIT、IF_CapexFacility、IF_CapexTotal、IF_GPUsPerGW、IF_RacksPerGW 逐值相同，只更新版本標籤與說明文字，數值不變。
A3: 模型命題：買方每投入 1 GW 的資料中心資本支出，晶片內容（運算、HBM、非 HBM 記憶體、網通晶片、代工）各分到多少，作為後續 HBM、網通、台積電模型的共同分母。
A5: 取數：Tokenomics v20.1（repo YinchenChang/Tokenomics，model/20261023_Tokenomics_v20.1.xlsx，commit 4c4c27f，SHA-256 027fef9ebd3008d5cb7abdad911e4c2f0806bf1afb105f4a62e7b5b9826fd607；五個 IF_ 名稱的 75 個值〔5 名稱 × 5 世代 × 3 成本情境〕逐值與 v19.0 相同，Spec_Rack E11:F13、Inputs D13:F14 的抄錄值亦相同）。具名範圍：IF_RacksPerGW、IF_GPUsPerGW、IF_CapexIT、IF_CapexFacility、IF_CapexTotal；機架單價、scale-out 比率、儲存 $/GPU 不在 Interface，暫讀 Spec_Rack／Inputs 原格（修改申請 R1）。
A6: 範圍：NVIDIA GB300 NVL72、VR200 NVL72 各一個代表性 1 GW；不含 ASIC 與世代組合（屬步驟 1 加速器數量層）。
A8: 驅動因子 → 推導量（頁：輸入 → 推導 → 因果方向）
A9: In：Tokenomics 每 GW 機架數、GPU 數、IT／廠房 capex、機架價；機架內構件單價與數量 → 供 Rack、Bridge、Sens 使用
A10: Rack：GPU 售價、HBM GB × $/GB、台積電、其他製造 → NVIDIA 晶片毛利（殘差）；機架價 − 各構件 → 匣級殘差。HBM 價↑ → NVIDIA 毛利↓（吸收）或 機架價↑（轉嫁）
A11: Bridge：每架金額 × 每 GW 機架數 → 每 GW 樹狀拆分；核對 IT 合計＝IF_CapexIT、合計＝IF_CapexTotal
A12: Sens：一次動一個輸入 → HBM $/GW、HBM ÷ IT capex、NVIDIA 晶片毛利率、機架殘差
A14: 標記：TK＝Tokenomics 取數；Verified 公開一手；Interested-party 有利害關係；Analogy 類比；Assumed 無實證；Derived 推導。Analogy／Assumed 一律給區間（In 頁 低／基準／高）。
A15: 讀法注意：(1) 殘差不是單一公司的營收，是 NVIDIA 匣級加價、電路板、供電與 ODM 毛利的合計；(2) LPDDR、NAND 以供應商價格計，NVIDIA 對它們的加價落在殘差；(3) 2027 HBM 情境 E 欄高於 Tokenomics IT capex，差額即轉嫁額。
A16: SemiAnalysis 資料未使用。

Sheet In
A1: In — 輸入（藍字）。基準欄＝E（GB300）、H（VR200）。Tokenomics 列取自 v20.1（model/20261023_Tokenomics_v20.1.xlsx，SHA-256 027fef9e…d607；五個 IF_ 名稱逐值與 v19.0 相同）
A3: 鍵 | B3: 項目 | C3: 單位 | D3: GB300 低 | E3: GB300 基準 | F3: GB300 高 | G3: VR200 低 | H3: VR200 基準 | I3: VR200 高 | J3: 標記 | K3: 來源／說明
A4: A. Tokenomics v20.1（算力收支；只讀不改；五個 IF_ 名稱與 v19.0 逐值相同）
A5: rack | B5: 機架單價 | C5: $M/架 | D5: 4 | E5: 4.3 | F5: 5 | G5: 7.8 | H5: 8.4 | I5: 9.1 | J5: TK | K5: Spec_Rack E11:F13（非 Interface 具名範圍；已提修改申請 R1）
A6: racks | B6: 每 GW 機架數 | C6: 架 | D6: 6764 | E6: 6764 | F6: 6764 | G6: 4052 | H6: 4052 | I6: 4052 | J6: TK | K6: IF_RacksPerGW
A7: gpus | B7: 每 GW GPU 數 | C7: 顆 | D7: 487008 | E7: 487008 | F7: 487008 | G7: 291744 | H7: 291744 | I7: 291744 | J7: TK | K7: IF_GPUsPerGW
A8: so | B8: Scale-out 網路 ÷ 機架價格 | C8: % | D8: 0.05 | E8: 0.1 | F8: 0.15 | G8: 0.05 | H8: 0.1 | I8: 0.15 | J8: TK | K8: Inputs D13:F13（Analogy；非 Interface，R1）
A9: stor | B9: 儲存與管理 | C9: $/GPU | D9: 300 | E9: 500 | F9: 800 | G9: 300 | H9: 500 | I9: 800 | J9: TK | K9: Inputs D14:F14（Assumed；非 Interface，R1）
A10: capit | B10: 每 GW 資本支出 — IT 設備 | C10: $B | D10: 28.554902 | E10: 32.237224 | F10: 39.282606 | G10: 33.273403 | H10: 37.586352 | I10: 42.637575 | J10: TK | K10: IF_CapexIT
A11: capfac | B11: 每 GW 資本支出 — 廠房 | C11: $B | D11: 10.212 | E11: 12.67 | F11: 16.186 | G11: 10.212 | H11: 12.67 | I11: 16.186 | J11: TK | K11: IF_CapexFacility
A12: captot | B12: 每 GW 資本支出 — 合計 | C12: $B | D12: 38.766902 | E12: 44.907224 | F12: 55.468606 | G12: 43.485403 | H12: 50.256352 | I12: 58.823575 | J12: TK | K12: IF_CapexTotal
A13: B. 機架內構件（本專案蒐集；每數字盡量兩來源）
A14: gpu_n | B14: 每架 GPU 封裝數 | C14: 顆 | D14: 72 | E14: 72 | F14: 72 | G14: 72 | H14: 72 | I14: 72 | J14: Verified | K14: NVIDIA 規格頁
A15: gpu_p | B15: GPU 模組售價（NVIDIA 對買方） | C15: $K/顆 | D15: 37.6 | E15: 40.4 | F15: 47 | G15: 50 | H15: 55 | I15: 60 | J15: Interested-party／Derived | K15: GB300（v0.2 改）：Data Gravity 採購單 72 模組約 $3.4M、整架約 $5.0M（Wing VC 2026-08；＝Tokenomics v5.31 起的機架高值）→ 模組占整架 67.7%；依 Tokenomics 低／基準 4.0／4.3 等比例換算為 37.6／40.4，高 47 為採購單原值。v0.1 用 47 配 $5.0M 機架；Tokenomics 基準改 4.3 後若不換算，機架殘差為 −5.9%（構件超過售價）；Epoch B200 $30–40K。VR200：Morgan Stanley $55K（內文；標題 $50K，Tom's Hardware 2026-05-21）
A16: hbm_gb | B16: HBM 容量 | C16: GB/顆 | D16: 288 | E16: 288 | F16: 288 | G16: 288 | H16: 288 | I16: 288 | J16: Verified | K16: NVIDIA：GB300 20 TB、VR200 20.7 TB ÷ 72
A17: hbm_p | B17: HBM 單價（2026 合約） | C17: $/GB | D17: 12 | E17: 15.5 | F17: 17 | G17: 15.6 | H17: 16.7 | I17: 17.2 | J17: Derived | K17: GB300 HBM3E：Epoch $14–17/GB；Silicon Analysts B300 約 $4,900/顆（=$17/GB）。VR200 HBM4：首爾經濟日報 12 層 36GB 約 $600（=$16.7/GB，2026-10-01）；UBS 每顆 $4,943（=$17.2/GB，2026-08-10）
A18: hbm_p27 | B18: HBM4 單價（2027 合約情境） | C18: $/GB | G18: 30 | H18: 36 | I18: 37 | J18: Interested-party | K18: 首爾經濟日報 約 $1,300/36GB（2027）；TrendForce 2027 ASP +121%（2026-09-29）；UBS +79%（低）
A19: tsmc | B19: 台積電：邏輯晶圓＋CoWoS | C19: $K/顆 | D19: 1.9 | E19: 2.3 | F19: 2.7 | G19: 2.3 | H19: 2.8 | I19: 3.5 | J19: Derived | K19: B200：Silicon Analysts 邏輯 $850＋封裝 $1,100；Epoch 約 $1.9K；B300 封裝溢價 25–40%（Epoch）。Rubin：UBS『GPU 相關扣 HBM』約 $4.3K（含周邊）為上限參考；N3 晶圓較 4NP 貴
A20: oth | B20: 其他製造：基板、測試、輔助、封裝良率損失 | C20: $K/顆 | D20: 1 | E20: 1.5 | F20: 2 | G20: 1 | H20: 1.5 | I20: 2 | J20: Derived | K20: Epoch B200：封裝良率損失 $1,000（$430–1,700）＋輔助 $480；Rubin 為類比
A21: cpu_n | B21: 每架 CPU 數 | C21: 顆 | D21: 36 | E21: 36 | F21: 36 | G21: 36 | H21: 36 | I21: 36 | J21: Verified | K21: NVIDIA：36 Grace／36 Vera
A22: cpu_p | B22: CPU 單價 | C22: $K/顆 | D22: 3 | E22: 4 | F22: 5 | G22: 4 | H22: 5 | I22: 6 | J22: Analogy | K22: Vera $5K（Morgan Stanley）；Grace 以 Vera 類比
A23: lp_tb | B23: LPDDR5X 容量（每架） | C23: TB | D23: 17 | E23: 17 | F23: 36 | G23: 28 | H23: 28 | I23: 54 | J23: Verified／Interested-party | K23: GB300：NVIDIA 規格頁 17 TB（參考架構頁寫每顆 Grace 1 TB＝36 TB，作高）。VR200：NVIDIA 初步規格 54 TB（高）；TrendForce 2026-06-10、GF Securities 2026-07-26：SOCAMM 減半，約 28 TB（基準）
A24: lp_p | B24: LPDDR5X 單價 | C24: $/GB | D24: 8 | E24: 13 | F24: 21 | G24: 8 | H24: 13 | I24: 21 | J24: Interested-party | K24: SemiAnalysis 2026Q1 約 $8；UBS 2026-08 隱含約 $12.9（$19,355／1.5 TB）；TrendForce 2026Q2 預估約 $19–20、長約上限約 $21（Wccftech 2026-05-04）
A25: nic_n | B25: 每架 SuperNIC 數 | C25: 顆 | D25: 72 | E25: 72 | F25: 72 | G25: 72 | H25: 144 | I25: 144 | J25: Verified／Derived | K25: GB300：NVIDIA 參考架構 每匣 4 顆 CX-8。VR200：NVIDIA 技術部落格圖示 每匣 8 顆 CX-9（推導 144）
A26: nic_p | B26: SuperNIC 單價 | C26: $K/顆 | D26: 1.5 | E26: 2 | F26: 2.5 | G26: 2 | H26: 3 | I26: 4 | J26: Analogy／Assumed | K26: CX-8 零售約 $2,089（Newegg）；大客戶價較低。CX-9 無報價
A27: dpu_n | B27: 每架 DPU 數 | C27: 顆 | D27: 18 | E27: 18 | F27: 18 | G27: 18 | H27: 18 | I27: 18 | J27: Verified | K27: 每匣 1 顆 BlueField-3／BlueField-4
A28: dpu_p | B28: DPU 單價 | C28: $K/顆 | D28: 1.5 | E28: 2.5 | F28: 3.5 | G28: 3 | H28: 4 | I28: 5 | J28: Assumed | K28: 無可靠報價
A29: nand | B29: 機架內 NAND／SSD | C29: $M/架 | D29: 0.05 | E29: 0.1 | F29: 0.2 | G29: 0.2 | H29: 1 | I29: 1.2 | J29: Assumed／Interested-party | K29: GB300：每匣 4 顆 E1.S＋1 M.2（容量未揭露）。VR200：Morgan Stanley 約 $1M 以上（Tom's Hardware）；Tokenomics SRC_HW_008 引用同一篇，**不是獨立第二來源**；低值 0.2 為 Assumed（若 $1M 指的是架外 BlueField-4 STX 儲存）
A30: nvsw | B30: NVLink 交換匣＋背板 ÷ 機架 | C30: % | D30: 0.04 | E30: 0.05 | F30: 0.06 | G30: 0.04 | H30: 0.05 | I30: 0.06 | J30: Derived | K30: Wing VC：NVIDIA 內容 >92%（含 NVLink）− 運算匣約 87% ≈ 5%
... A33: cool | B33: 其中：機架內液冷 | C33: $K/架 | D33: 50 | E33: 50 | F33: 50 | G33: 56 | H33: 56 | I33: 56 | J33: Interested-party | K33: Morgan Stanley（Tom's Hardware）：GB300 約 $49,860、Vera Rubin 約 $56K

Sheet Rack
A1: Rack — 每架拆分（$M/架；各欄皆用基準值）。D 欄：2027 HBM 價、NVIDIA 吸收（售價不變）；E 欄：2027 HBM 價、全額轉嫁（GPU 與機架售價上調）
A3: 項目 | B3: GB300 NVL72 | C3: VR200（2026 HBM 價） | D3: VR200（2027 HBM 價，NVIDIA 吸收） | E3: VR200（2027 HBM 價，全額轉嫁） | F3: 說明
A4: HBM 單價 $/GB | B4: =In!E17 -> 15.5 | C4: =In!H17 -> 16.7 | D4: =In!H18 -> 36 | E4: =In!H18 -> 36
A5: 每顆 HBM 金額 $K | B5: =In!E16*B4/1000 -> 4.464 | C5: =In!H16*C4/1000 -> 4.8096 | D5: =In!H16*D4/1000 -> 10.368 | E5: =In!H16*E4/1000 -> 10.368
A6: GPU 模組售價 $K | B6: =In!E15 -> 40.4 | C6: =In!H15 -> 55 | D6: =In!H15 -> 55 | E6: =In!H15+(E5-C5) -> 60.5584 | F6: E 欄：HBM 增加額全額加到售價
A7: 台積電（邏輯＋CoWoS）$K | B7: =In!E19 -> 2.3 | C7: =In!H19 -> 2.8 | D7: =In!H19 -> 2.8 | E7: =In!H19 -> 2.8
A8: 其他製造 $K | B8: =In!E20 -> 1.5 | C8: =In!H20 -> 1.5 | D8: =In!H20 -> 1.5 | E8: =In!H20 -> 1.5
A9: NVIDIA 晶片毛利 $K（殘差） | B9: =B6-B5-B7-B8 -> 32.136 | C9: =C6-C5-C7-C8 -> 45.8904 | D9: =D6-D5-D7-D8 -> 40.332 | E9: =E6-E5-E7-E8 -> 45.8904
A10: NVIDIA 晶片層級毛利率 | B10: =B9/B6 -> 0.79544554 | C10: =C9/C6 -> 0.83437091 | D10: =D9/D6 -> 0.73330909 | E10: =E9/E6 -> 0.75778752
A11: HBM ÷ GPU 售價 | B11: =B5/B6 -> 0.11049505 | C11: =C5/C6 -> 0.087447273 | D11: =D5/D6 -> 0.18850909 | E11: =E5/E6 -> 0.17120664
A12: 台積電 ÷ GPU 售價 | B12: =B7/B6 -> 0.056930693 | C12: =C7/C6 -> 0.050909091 | D12: =D7/D6 -> 0.050909091 | E12: =E7/E6 -> 0.04623636
A14: 機架售價 $M | B14: =In!E5 -> 4.3 | C14: =In!H5 -> 8.4 | D14: =In!H5 -> 8.4 | E14: =In!H5+In!H14*(E6-C6)/1000 -> 8.8002048 | F14: B–D 欄＝Tokenomics 基準；E 欄＝加上轉嫁額
A15: GPU 模組（72 顆） | B15: =In!E14*B6/1000 -> 2.9088 | C15: =In!H14*C6/1000 -> 3.96 | D15: =In!H14*D6/1000 -> 3.96 | E15: =In!H14*E6/1000 -> 4.3602048
A16: HBM | B16: =In!E14*B5/1000 -> 0.321408 | C16: =In!H14*C5/1000 -> 0.3462912 | D16: =In!H14*D5/1000 -> 0.746496 | E16: =In!H14*E5/1000 -> 0.746496
A17: 台積電（邏輯＋CoWoS） | B17: =In!E14*B7/1000 -> 0.1656 | C17: =In!H14*C7/1000 -> 0.2016 | D17: =In!H14*D7/1000 -> 0.2016 | E17: =In!H14*E7/1000 -> 0.2016
A18: 其他製造 | B18: =In!E14*B8/1000 -> 0.108 | C18: =In!H14*C8/1000 -> 0.108 | D18: =In!H14*D8/1000 -> 0.108 | E18: =In!H14*E8/1000 -> 0.108
A19: NVIDIA 晶片毛利 | B19: =In!E14*B9/1000 -> 2.313792 | C19: =In!H14*C9/1000 -> 3.3041088 | D19: =In!H14*D9/1000 -> 2.903904 | E19: =In!H14*E9/1000 -> 3.3041088
A20: CPU（Grace／Vera） | B20: =In!E21*In!E22/1000 -> 0.144 | C20: =In!H21*In!H22/1000 -> 0.18 | D20: =In!H21*In!H22/1000 -> 0.18 | E20: =In!H21*In!H22/1000 -> 0.18
A21: 非 HBM DRAM（LPDDR5X） | B21: =In!E23*In!E24/1000 -> 0.221 | C21: =In!H23*In!H24/1000 -> 0.364 | D21: =In!H23*In!H24/1000 -> 0.364 | E21: =In!H23*In!H24/1000 -> 0.364 | F21: TB × $/GB ÷ 1000 ＝ $M
A22: NAND／SSD（機架內） | B22: =In!E29 -> 0.1 | C22: =In!H29 -> 1 | D22: =In!H29 -> 1 | E22: =In!H29 -> 1
A23: SuperNIC | B23: =In!E25*In!E26/1000 -> 0.144 | C23: =In!H25*In!H26/1000 -> 0.432 | D23: =In!H25*In!H26/1000 -> 0.432 | E23: =In!H25*In!H26/1000 -> 0.432
A24: DPU | B24: =In!E27*In!E28/1000 -> 0.045 | C24: =In!H27*In!H28/1000 -> 0.072 | D24: =In!H27*In!H28/1000 -> 0.072 | E24: =In!H27*In!H28/1000 -> 0.072
A25: NVLink 交換匣＋背板 | B25: =In!E30*In!E5 -> 0.215 | C25: =In!H30*In!H5 -> 0.42 | D25: =In!H30*In!H5 -> 0.42 | E25: =In!H30*In!H5 -> 0.42 | F25: 以 Tokenomics 機架價計（不隨 HBM 轉嫁放大）
A26: NVLink 交換晶片 | B26: =B25*In!E31 -> 0.1075 | C26: =C25*In!H31 -> 0.21 | D26: =D25*In!H31 -> 0.21 | E26: =E25*In!H31 -> 0.21
A27: 交換匣其他（含銅纜背板） | B27: =B25-B26 -> 0.1075 | C27: =C25-C26 -> 0.21 | D27: =D25-D26 -> 0.21 | E27: =E25-E26 -> 0.21
A28: 非 NVIDIA 機架內容（電源、冷卻、機構、整合） | B28: =In!E32*In!E5 -> 0.301 | C28: =In!H32*In!H5 -> 0.588 | D28: =In!H32*In!H5 -> 0.588 | E28: =In!H32*In!H5 -> 0.588
A29: 其中：液冷 | B29: =In!E33/1000 -> 0.05 | C29: =In!H33/1000 -> 0.056 | D29: =In!H33/1000 -> 0.056 | E29: =In!H33/1000 -> 0.056
A30: 殘差：匣級電路板、供電與 NVIDIA／ODM 匣級加價 | B30: =B14-B15-B20-B21-B22-B23-B24-B25-B28 -> 0.2212 | C30: =C14-C15-C20-C21-C22-C23-C24-C25-C28 -> 1.384 | D30: =D14-D15-D20-D21-D22-D23-D24-D25-D28 -> 1.384 | E30: =E14-E15-E20-E21-E22-E23-E24-E25-E28 -> 1.384 | F30: 負值＝輸入互相矛盾（構件加總超過售價）
A31: 殘差 ÷ 機架售價 | B31: =B30/B14 -> 0.05144186 | C31: =C30/C14 -> 0.1647619 | D31: =D30/D14 -> 0.1647619 | E31: =E30/E14 -> 0.15726907
A32: 核對：構件＋殘差－售價（應為 0） | B32: =B15+B20+B21+B22+B23+B24+B25+B28+B30-B14 -> 0 | C32: =C15+C20+C21+C22+C23+C24+C25+C28+C30-C14 -> 0 | D32: =D15+D20+D21+D22+D23+D24+D25+D28+D30-D14 -> 0 | E32: =E15+E20+E21+E22+E23+E24+E25+E28+E30-E14 -> 0

Sheet Bridge
A1: Bridge — 每 GW 晶片內容橋接表（軸 A：買方每一塊錢分到哪裡；$B/GW IT 關鍵電力）
A2: 每架項目 × 每 GW 機架數；scale-out 與儲存依 Tokenomics 口徑；廠房＝IF_CapexFacility。E 欄的 IT 合計高於 Tokenomics（轉嫁額），見核對列
A4: 項目（縮排＝樹狀層級） | B4: GB300 | C4: VR200 2026 | D4: VR200 2027 吸收 | E4: VR200 2027 轉嫁 | F4: GB300 ÷ 總 capex | G4: VR200 2026 ÷ 總 capex | H4: VR200 2027 吸收 ÷ 總 | I4: VR200 2027 轉嫁 ÷ 總 | J4: 下游歸屬
A5: 每 GW capex 合計 | B5: =B6+B7 -> 44.907224 | C5: =C6+C7 -> 50.256352 | D5: =D6+D7 -> 50.256352 | E5: =E6+E7 -> 51.877982 | F5: =B5/B$5 -> 1 | G5: =C5/C$5 -> 1 | H5: =D5/D$5 -> 1 | I5: =E5/E$5 -> 1
A6: ├ 廠房（機房、電力、冷卻） | B6: =In!E11 -> 12.67 | C6: =In!H11 -> 12.67 | D6: =In!H11 -> 12.67 | E6: =In!H11 -> 12.67 | F6: =B6/B$5 -> 0.28213723 | G6: =C6/C$5 -> 0.25210744 | H6: =D6/D$5 -> 0.25210744 | I6: =E6/E$5 -> 0.24422693 | J6: 電力基建專案
A7: └ IT 設備 | B7: =B8-B21-B22+B20+B24 -> 32.237224 | C7: =C8-C21-C22+C20+C24 -> 37.586352 | D7: =D8-D21-D22+D20+D24 -> 37.586352 | E7: =E8-E21-E22+E20+E24 -> 39.207982 | F7: =B7/B$5 -> 0.71786277 | G7: =C7/C$5 -> 0.74789256 | H7: =D7/D$5 -> 0.74789256 | I7: =E7/E$5 -> 0.75577307
A8: ├ 伺服器／機架 | B8: =Rack!B14*In!E6/1000 -> 29.0852 | C8: =Rack!C14*In!H6/1000 -> 34.0368 | D8: =Rack!D14*In!H6/1000 -> 34.0368 | E8: =Rack!E14*In!H6/1000 -> 35.65843 | F8: =B8/B$5 -> 0.64767308 | G8: =C8/C$5 -> 0.67726364 | H8: =D8/D$5 -> 0.67726364 | I8: =E8/E$5 -> 0.68735191 | J8: 註：NVLink 交換匣實體在機架內，此處移到『網通』列示，IT 合計已扣除避免重複
A9: │ ├ 加速器封裝（GPU 模組） | B9: =Rack!B15*In!E6/1000 -> 19.675123 | C9: =Rack!C15*In!H6/1000 -> 16.04592 | D9: =Rack!D15*In!H6/1000 -> 16.04592 | E9: =Rack!E15*In!H6/1000 -> 17.66755 | F9: =B9/B$5 -> 0.43812824 | G9: =C9/C$5 -> 0.31928143 | H9: =D9/D$5 -> 0.31928143 | I9: =E9/E$5 -> 0.3405597
A10: │ │ ├ GPU 晶片：NVIDIA 毛利（設計） | B10: =Rack!B19*In!E6/1000 -> 15.650489 | C10: =Rack!C19*In!H6/1000 -> 13.388249 | D10: =Rack!D19*In!H6/1000 -> 11.766619 | E10: =Rack!E19*In!H6/1000 -> 13.388249 | F10: =B10/B$5 -> 0.34850716 | G10: =C10/C$5 -> 0.26639914 | H10: =D10/D$5 -> 0.23413198 | I10: =E10/E$5 -> 0.25807189 | J10: NVDA
A11: │ │ ├ GPU 晶片＋CoWoS：台積電 | B11: =Rack!B17*In!E6/1000 -> 1.1201184 | C11: =Rack!C17*In!H6/1000 -> 0.8168832 | D11: =Rack!D17*In!H6/1000 -> 0.8168832 | E11: =Rack!E17*In!H6/1000 -> 0.8168832 | F11: =B11/B$5 -> 0.024942945 | G11: =C11/C$5 -> 0.016254327 | H11: =D11/D$5 -> 0.016254327 | I11: =E11/E$5 -> 0.015746241 | J11: 台積電（軸 B）
A12: │ │ ├ HBM | B12: =Rack!B16*In!E6/1000 -> 2.1740037 | C12: =Rack!C16*In!H6/1000 -> 1.4031719 | D12: =Rack!D16*In!H6/1000 -> 3.0248018 | E12: =Rack!E16*In!H6/1000 -> 3.0248018 | F12: =B12/B$5 -> 0.048411002 | G12: =C12/C$5 -> 0.02792029 | H12: =D12/D$5 -> 0.060187452 | I12: =E12/E$5 -> 0.058306081 | J12: SK 海力士／三星／美光
A13: │ │ └ 其他製造（基板、測試、良率損失） | B13: =Rack!B18*In!E6/1000 -> 0.730512 | C13: =Rack!C18*In!H6/1000 -> 0.437616 | D13: =Rack!D18*In!H6/1000 -> 0.437616 | E13: =Rack!E18*In!H6/1000 -> 0.437616 | F13: =B13/B$5 -> 0.016267138 | G13: =C13/C$5 -> 0.0087076754 | H13: =D13/D$5 -> 0.0087076754 | I13: =E13/E$5 -> 0.0084354862 | J13: 基板廠、封測
A14: │ ├ CPU（Grace／Vera） | B14: =Rack!B20*In!E6/1000 -> 0.974016 | C14: =Rack!C20*In!H6/1000 -> 0.72936 | D14: =Rack!D20*In!H6/1000 -> 0.72936 | E14: =Rack!E20*In!H6/1000 -> 0.72936 | F14: =B14/B$5 -> 0.021689517 | G14: =C14/C$5 -> 0.014512792 | H14: =D14/D$5 -> 0.014512792 | I14: =E14/E$5 -> 0.014059144 | J14: NVDA（台積電代工）
A15: │ ├ 非 HBM DRAM（LPDDR5X） | B15: =Rack!B21*In!E6/1000 -> 1.494844 | C15: =Rack!C21*In!H6/1000 -> 1.474928 | D15: =Rack!D21*In!H6/1000 -> 1.474928 | E15: =Rack!E21*In!H6/1000 -> 1.474928 | F15: =B15/B$5 -> 0.033287384 | G15: =C15/C$5 -> 0.029348091 | H15: =D15/D$5 -> 0.029348091 | I15: =E15/E$5 -> 0.028430713 | J15: 記憶體三家
A16: │ ├ NAND／SSD（機架內） | B16: =Rack!B22*In!E6/1000 -> 0.6764 | C16: =Rack!C22*In!H6/1000 -> 4.052 | D16: =Rack!D22*In!H6/1000 -> 4.052 | E16: =Rack!E22*In!H6/1000 -> 4.052 | F16: =B16/B$5 -> 0.015062165 | G16: =C16/C$5 -> 0.080626624 | H16: =D16/D$5 -> 0.080626624 | I16: =E16/E$5 -> 0.078106354 | J16: NAND 廠
A17: │ ├ SuperNIC＋DPU（scale-out 端點，機架內） | B17: =(Rack!B23+Rack!B24)*In!E6/1000 -> 1.278396 | C17: =(Rack!C23+Rack!C24)*In!H6/1000 -> 2.042208 | D17: =(Rack!D23+Rack!D24)*In!H6/1000 -> 2.042208 | E17: =(Rack!E23+Rack!E24)*In!H6/1000 -> 2.042208 | F17: =B17/B$5 -> 0.028467491 | G17: =C17/C$5 -> 0.040635819 | H17: =D17/D$5 -> 0.040635819 | I17: =E17/E$5 -> 0.039365602 | J17: NVDA
A18: │ ├ 非 NVIDIA 機架內容（電源、冷卻、機構、整合） | B18: =Rack!B28*In!E6/1000 -> 2.035964 | C18: =Rack!C28*In!H6/1000 -> 2.382576 | D18: =Rack!D28*In!H6/1000 -> 2.382576 | E18: =Rack!E28*In!H6/1000 -> 2.382576 | F18: =B18/B$5 -> 0.045337115 | G18: =C18/C$5 -> 0.047408455 | H18: =D18/D$5 -> 0.047408455 | I18: =E18/E$5 -> 0.045926536 | J18: 台系供應鏈（待定）
A19: │ └ 殘差：匣級電路板、供電、NVIDIA／ODM 匣級加價 | B19: =Rack!B30*In!E6/1000 -> 1.4961968 | C19: =Rack!C30*In!H6/1000 -> 5.607968 | D19: =Rack!D30*In!H6/1000 -> 5.607968 | E19: =Rack!E30*In!H6/1000 -> 5.607968 | F19: =B19/B$5 -> 0.033317508 | G19: =C19/C$5 -> 0.11158725 | H19: =D19/D$5 -> 0.11158725 | I19: =E19/E$5 -> 0.10809919 | J19: NVDA／ODM（未拆）
A20: ├ 網通 | B20: =B21+B22+B23 -> 4.36278 | C20: =C21+C22+C23 -> 5.10552 | D20: =D21+D22+D23 -> 5.10552 | E20: =E21+E22+E23 -> 5.10552 | F20: =B20/B$5 -> 0.097150962 | G20: =C20/C$5 -> 0.10158955 | H20: =D20/D$5 -> 0.10158955 | I20: =E20/E$5 -> 0.098414006
A21: │ ├ scale-up：NVLink 交換晶片 | B21: =Rack!B26*In!E6/1000 -> 0.72713 | C21: =Rack!C26*In!H6/1000 -> 0.85092 | D21: =Rack!D26*In!H6/1000 -> 0.85092 | E21: =Rack!E26*In!H6/1000 -> 0.85092 | F21: =B21/B$5 -> 0.016191827 | G21: =C21/C$5 -> 0.016931591 | H21: =D21/D$5 -> 0.016931591 | I21: =E21/E$5 -> 0.016402334 | J21: NVDA
A22: │ ├ scale-up：交換匣其他（含銅纜背板） | B22: =Rack!B27*In!E6/1000 -> 0.72713 | C22: =Rack!C27*In!H6/1000 -> 0.85092 | D22: =Rack!D27*In!H6/1000 -> 0.85092 | E22: =Rack!E27*In!H6/1000 -> 0.85092 | F22: =B22/B$5 -> 0.016191827 | G22: =C22/C$5 -> 0.016931591 | H22: =D22/D$5 -> 0.016931591 | I22: =E22/E$5 -> 0.016402334 | J22: NVDA／線纜
A23: │ └ scale-out：機架外（交換器、光模組、線纜；步驟 3 拆分） | B23: =In!E8*In!E5*In!E6/1000 -> 2.90852 | C23: =In!H8*In!H5*In!H6/1000 -> 3.40368 | D23: =In!H8*In!H5*In!H6/1000 -> 3.40368 | E23: =In!H8*In!H5*In!H6/1000 -> 3.40368 | F23: =B23/B$5 -> 0.064767308 | G23: =C23/C$5 -> 0.067726364 | H23: =D23/D$5 -> 0.067726364 | I23: =E23/E$5 -> 0.065609337 | J23: AVGO、NVDA、光模組
A24: └ 儲存與管理 | B24: =In!E9*In!E7/1000000000 -> 0.243504 | C24: =In!H9*In!H7/1000000000 -> 0.145872 | D24: =In!H9*In!H7/1000000000 -> 0.145872 | E24: =In!H9*In!H7/1000000000 -> 0.145872 | F24: =B24/B$5 -> 0.0054223793 | G24: =C24/C$5 -> 0.0029025585 | H24: =D24/D$5 -> 0.0029025585 | I24: =E24/E$5 -> 0.0028118287 | J24: 未拆
A26: 核對
A27: IT 合計 − Tokenomics IF_CapexIT（B–D 應為 0；E＝轉嫁額） | B27: =B7-In!E10 -> 0 | C27: =C7-In!H10 -> 0 | D27: =D7-In!H10 -> 0 | E27: =E7-In!H10 -> 1.6216298
A28: 合計 − Tokenomics IF_CapexTotal（B–D 應為 0） | B28: =B5-In!E12 -> 0 | C28: =C5-In!H12 -> 0 | D28: =D5-In!H12 -> 0 | E28: =E5-In!H12 -> 1.6216298
A30: 記憶體彙總（$B/GW）
A31: HBM | B31: =B12 -> 2.1740037 | C31: =C12 -> 1.4031719 | D31: =D12 -> 3.0248018 | E31: =E12 -> 3.0248018
A32: 非 HBM（LPDDR5X＋機架內 NAND） | B32: =B15+B16 -> 2.171244 | C32: =C15+C16 -> 5.526928 | D32: =D15+D16 -> 5.526928 | E32: =E15+E16 -> 5.526928
A33: 其中 DRAM（LPDDR5X） | B33: =B15 -> 1.494844 | C33: =C15 -> 1.474928 | D33: =D15 -> 1.474928 | E33: =E15 -> 1.474928
A34: 記憶體合計（不含儲存層、機架外） | B34: =B31+B32 -> 4.3452477 | C34: =C31+C32 -> 6.9300999 | D34: =D31+D32 -> 8.5517298 | E34: =E31+E32 -> 8.5517298
A35: HBM ÷ 記憶體合計 | B35: =B31/B34 -> 0.50031756 | C35: =C31/C34 -> 0.20247499 | D35: =D31/D34 -> 0.35370643 | E35: =E31/E34 -> 0.35370643
A36: HBM ÷ IT capex | B36: =B31/B7 -> 0.067437684 | C36: =C31/C7 -> 0.037331953 | D36: =D31/D7 -> 0.080476067 | E36: =E31/E7 -> 0.077147602
A37: DRAM（HBM＋LPDDR）÷ IT capex | B37: =(B31+B33)/B7 -> 0.11380781 | C37: =(C31+C33)/C7 -> 0.076573006 | D37: =(D31+D33)/D7 -> 0.11971712 | E37: =(E31+E33)/E7 -> 0.11476566
A39: 回饋算力收支的摘要數字（每顆加速器）
A40: 每顆加速器 HBM 金額 $K | B40: =Rack!B5 -> 4.464 | C40: =Rack!C5 -> 4.8096 | D40: =Rack!D5 -> 10.368 | E40: =Rack!E5 -> 10.368
A41: HBM ÷ GPU 售價 | B41: =Rack!B11 -> 0.11049505 | C41: =Rack!C11 -> 0.087447273 | D41: =Rack!D11 -> 0.18850909 | E41: =Rack!E11 -> 0.17120664
A42: 台積電 ÷ GPU 售價 | B42: =Rack!B12 -> 0.056930693 | C42: =Rack!C12 -> 0.050909091 | D42: =Rack!D12 -> 0.050909091 | E42: =Rack!E12 -> 0.04623636
A43: NVIDIA 晶片層級毛利率 | B43: =Rack!B10 -> 0.79544554 | C43: =Rack!C10 -> 0.83437091 | D43: =Rack!D10 -> 0.73330909 | E43: =Rack!E10 -> 0.75778752
A44: NVIDIA 合計 ÷ IT capex（GPU 毛利＋CPU＋NIC/DPU＋NVLink＋殘差） | B44: =(B10+B14+B17+B21+B22+B19)/B7 -> 0.64687201 | C44: =(C10+C14+C17+C21+C22+C19)/C7 -> 0.6244188 | D44: =(D10+D14+D17+D21+D22+D19)/D7 -> 0.58127469 | E44: =(E10+E14+E17+E21+E22+E19)/E7 -> 0.59859304

Sheet Sens
A1: Sens — 單變數敏感度（VR200；一次只動一個藍字輸入；其餘＝基準）。先看本頁，再看 Bridge 基準
A3: 情境 | B3: HBM $/GB | C3: LPDDR TB/架 | D3: LPDDR $/GB | E3: GPU 售價 $K | F3: 機架售價 $M | G3: 台積電 $K/顆 | H3: HBM $B/GW | I3: HBM ÷ IT capex | J3: LPDDR $B/GW | K3: NVIDIA 晶片毛利率 | L3: 機架殘差 ÷ 售價 | M3: HBM ÷ GPU 售價
A4: 基準（2026 HBM 價） | B4: =In!H17 -> 16.7 | C4: =In!H23 -> 28 | D4: =In!H24 -> 13 | E4: =In!H15 -> 55 | F4: =In!H5 -> 8.4 | G4: =In!H19 -> 2.8 | H4: =In!H7*In!H16*B4/1000000000 -> 1.4031719 | I4: =H4/(In!H6*F4*(1+In!H8)/1000+In!H7*In!H9/1000000000) -> 0.037331953 | J4: =In!H6*C4*D4/1000000 -> 1.474928 | K4: =(E4-In!H16*B4/1000-G4-In!H20)/E4 -> 0.83437091 | L4: =(F4-(In!H14*E4/1000+In!H21*In!H22/1000+C4*D4/1000+In!H29+In!H25*In!H26/1000+In!H27*In!H28/1000+F4*(In!H30+In!H32)))/F4 -> 0.1647619 | M4: =In!H16*B4/1000/E4 -> 0.087447273
A5: HBM 低（$15.6） | B5: =In!G17 -> 15.6 | C5: =In!H23 -> 28 | D5: =In!H24 -> 13 | E5: =In!H15 -> 55 | F5: =In!H5 -> 8.4 | G5: =In!H19 -> 2.8 | H5: =In!H7*In!H16*B5/1000000000 -> 1.3107474 | I5: =H5/(In!H6*F5*(1+In!H8)/1000+In!H7*In!H9/1000000000) -> 0.034872962 | J5: =In!H6*C5*D5/1000000 -> 1.474928 | K5: =(E5-In!H16*B5/1000-G5-In!H20)/E5 -> 0.84013091 | L5: =(F5-(In!H14*E5/1000+In!H21*In!H22/1000+C5*D5/1000+In!H29+In!H25*In!H26/1000+In!H27*In!H28/1000+F5*(In!H30+In!H32)))/F5 -> 0.1647619 | M5: =In!H16*B5/1000/E5 -> 0.081687273
A6: HBM 2027 低（$30，UBS +79%） | B6: =In!G18 -> 30 | C6: =In!H23 -> 28 | D6: =In!H24 -> 13 | E6: =In!H15 -> 55 | F6: =In!H5 -> 8.4 | G6: =In!H19 -> 2.8 | H6: =In!H7*In!H16*B6/1000000000 -> 2.5206682 | I6: =H6/(In!H6*F6*(1+In!H8)/1000+In!H7*In!H9/1000000000) -> 0.067063389 | J6: =In!H6*C6*D6/1000000 -> 1.474928 | K6: =(E6-In!H16*B6/1000-G6-In!H20)/E6 -> 0.76472727 | L6: =(F6-(In!H14*E6/1000+In!H21*In!H22/1000+C6*D6/1000+In!H29+In!H25*In!H26/1000+In!H27*In!H28/1000+F6*(In!H30+In!H32)))/F6 -> 0.1647619 | M6: =In!H16*B6/1000/E6 -> 0.15709091
A7: HBM 2027（$36，TrendForce +121%） | B7: =In!H18 -> 36 | C7: =In!H23 -> 28 | D7: =In!H24 -> 13 | E7: =In!H15 -> 55 | F7: =In!H5 -> 8.4 | G7: =In!H19 -> 2.8 | H7: =In!H7*In!H16*B7/1000000000 -> 3.0248018 | I7: =H7/(In!H6*F7*(1+In!H8)/1000+In!H7*In!H9/1000000000) -> 0.080476067 | J7: =In!H6*C7*D7/1000000 -> 1.474928 | K7: =(E7-In!H16*B7/1000-G7-In!H20)/E7 -> 0.73330909 | L7: =(F7-(In!H14*E7/1000+In!H21*In!H22/1000+C7*D7/1000+In!H29+In!H25*In!H26/1000+In!H27*In!H28/1000+F7*(In!H30+In!H32)))/F7 -> 0.1647619 | M7: =In!H16*B7/1000/E7 -> 0.18850909
A8: LPDDR 54 TB（NVIDIA 初步規格） | B8: =In!H17 -> 16.7 | C8: =In!I23 -> 54 | D8: =In!H24 -> 13 | E8: =In!H15 -> 55 | F8: =In!H5 -> 8.4 | G8: =In!H19 -> 2.8 | H8: =In!H7*In!H16*B8/1000000000 -> 1.4031719 | I8: =H8/(In!H6*F8*(1+In!H8)/1000+In!H7*In!H9/1000000000) -> 0.037331953 | J8: =In!H6*C8*D8/1000000 -> 2.844504 | K8: =(E8-In!H16*B8/1000-G8-In!H20)/E8 -> 0.83437091 | L8: =(F8-(In!H14*E8/1000+In!H21*In!H22/1000+C8*D8/1000+In!H29+In!H25*In!H26/1000+In!H27*In!H28/1000+F8*(In!H30+In!H32)))/F8 -> 0.12452381 | M8: =In!H16*B8/1000/E8 -> 0.087447273
A9: LPDDR $8／GB | B9: =In!H17 -> 16.7 | C9: =In!H23 -> 28 | D9: =In!G24 -> 8 | E9: =In!H15 -> 55 | F9: =In!H5 -> 8.4 | G9: =In!H19 -> 2.8 | H9: =In!H7*In!H16*B9/1000000000 -> 1.4031719 | I9: =H9/(In!H6*F9*(1+In!H8)/1000+In!H7*In!H9/1000000000) -> 0.037331953 | J9: =In!H6*C9*D9/1000000 -> 0.907648 | K9: =(E9-In!H16*B9/1000-G9-In!H20)/E9 -> 0.83437091 | L9: =(F9-(In!H14*E9/1000+In!H21*In!H22/1000+C9*D9/1000+In!H29+In!H25*In!H26/1000+In!H27*In!H28/1000+F9*(In!H30+In!H32)))/F9 -> 0.18142857 | M9: =In!H16*B9/1000/E9 -> 0.087447273
A10: LPDDR $21／GB | B10: =In!H17 -> 16.7 | C10: =In!H23 -> 28 | D10: =In!I24 -> 21 | E10: =In!H15 -> 55 | F10: =In!H5 -> 8.4 | G10: =In!H19 -> 2.8 | H10: =In!H7*In!H16*B10/1000000000 -> 1.4031719 | I10: =H10/(In!H6*F10*(1+In!H8)/1000+In!H7*In!H9/1000000000) -> 0.037331953 | J10: =In!H6*C10*D10/1000000 -> 2.382576 | K10: =(E10-In!H16*B10/1000-G10-In!H20)/E10 -> 0.83437091 | L10: =(F10-(In!H14*E10/1000+In!H21*In!H22/1000+C10*D10/1000+In!H29+In!H25*In!H26/1000+In!H27*In!H28/1000+F10*(In!H30+In!H32)))/F10 -> 0.13809524 | M10: =In!H16*B10/1000/E10 -> 0.087447273
A11: GPU 售價 $50K | B11: =In!H17 -> 16.7 | C11: =In!H23 -> 28 | D11: =In!H24 -> 13 | E11: =In!G15 -> 50 | F11: =In!H5 -> 8.4 | G11: =In!H19 -> 2.8 | H11: =In!H7*In!H16*B11/1000000000 -> 1.4031719 | I11: =H11/(In!H6*F11*(1+In!H8)/1000+In!H7*In!H9/1000000000) -> 0.037331953 | J11: =In!H6*C11*D11/1000000 -> 1.474928 | K11: =(E11-In!H16*B11/1000-G11-In!H20)/E11 -> 0.817808 | L11: =(F11-(In!H14*E11/1000+In!H21*In!H22/1000+C11*D11/1000+In!H29+In!H25*In!H26/1000+In!H27*In!H28/1000+F11*(In!H30+In!H32)))/F11 -> 0.20761905 | M11: =In!H16*B11/1000/E11 -> 0.096192
A12: GPU 售價 $60K | B12: =In!H17 -> 16.7 | C12: =In!H23 -> 28 | D12: =In!H24 -> 13 | E12: =In!I15 -> 60 | F12: =In!H5 -> 8.4 | G12: =In!H19 -> 2.8 | H12: =In!H7*In!H16*B12/1000000000 -> 1.4031719 | I12: =H12/(In!H6*F12*(1+In!H8)/1000+In!H7*In!H9/1000000000) -> 0.037331953 | J12: =In!H6*C12*D12/1000000 -> 1.474928 | K12: =(E12-In!H16*B12/1000-G12-In!H20)/E12 -> 0.84817333 | L12: =(F12-(In!H14*E12/1000+In!H21*In!H22/1000+C12*D12/1000+In!H29+In!H25*In!H26/1000+In!H27*In!H28/1000+F12*(In!H30+In!H32)))/F12 -> 0.12190476 | M12: =In!H16*B12/1000/E12 -> 0.08016
A13: 機架 $7.8M（MS BOM） | B13: =In!H17 -> 16.7 | C13: =In!H23 -> 28 | D13: =In!H24 -> 13 | E13: =In!H15 -> 55 | F13: =In!G5 -> 7.8 | G13: =In!H19 -> 2.8 | H13: =In!H7*In!H16*B13/1000000000 -> 1.4031719 | I13: =H13/(In!H6*F13*(1+In!H8)/1000+In!H7*In!H9/1000000000) -> 0.040191643 | J13: =In!H6*C13*D13/1000000 -> 1.474928 | K13: =(E13-In!H16*B13/1000-G13-In!H20)/E13 -> 0.83437091 | L13: =(F13-(In!H14*E13/1000+In!H21*In!H22/1000+C13*D13/1000+In!H29+In!H25*In!H26/1000+In!H27*In!H28/1000+F13*(In!H30+In!H32)))/F13 -> 0.10974359 | M13: =In!H16*B13/1000/E13 -> 0.087447273
A14: 機架 $9.1M（Bernstein） | B14: =In!H17 -> 16.7 | C14: =In!H23 -> 28 | D14: =In!H24 -> 13 | E14: =In!H15 -> 55 | F14: =In!I5 -> 9.1 | G14: =In!H19 -> 2.8 | H14: =In!H7*In!H16*B14/1000000000 -> 1.4031719 | I14: =H14/(In!H6*F14*(1+In!H8)/1000+In!H7*In!H9/1000000000) -> 0.034470555 | J14: =In!H6*C14*D14/1000000 -> 1.474928 | K14: =(E14-In!H16*B14/1000-G14-In!H20)/E14 -> 0.83437091 | L14: =(F14-(In!H14*E14/1000+In!H21*In!H22/1000+C14*D14/1000+In!H29+In!H25*In!H26/1000+In!H27*In!H28/1000+F14*(In!H30+In!H32)))/F14 -> 0.21978022 | M14: =In!H16*B14/1000/E14 -> 0.087447273
A15: 台積電 $2.3K | B15: =In!H17 -> 16.7 | C15: =In!H23 -> 28 | D15: =In!H24 -> 13 | E15: =In!H15 -> 55 | F15: =In!H5 -> 8.4 | G15: =In!G19 -> 2.3 | H15: =In!H7*In!H16*B15/1000000000 -> 1.4031719 | I15: =H15/(In!H6*F15*(1+In!H8)/1000+In!H7*In!H9/1000000000) -> 0.037331953 | J15: =In!H6*C15*D15/1000000 -> 1.474928 | K15: =(E15-In!H16*B15/1000-G15-In!H20)/E15 -> 0.84346182 | L15: =(F15-(In!H14*E15/1000+In!H21*In!H22/1000+C15*D15/1000+In!H29+In!H25*In!H26/1000+In!H27*In!H28/1000+F15*(In!H30+In!H32)))/F15 -> 0.1647619 | M15: =In!H16*B15/1000/E15 -> 0.087447273
A16: 台積電 $3.5K | B16: =In!H17 -> 16.7 | C16: =In!H23 -> 28 | D16: =In!H24 -> 13 | E16: =In!H15 -> 55 | F16: =In!H5 -> 8.4 | G16: =In!I19 -> 3.5 | H16: =In!H7*In!H16*B16/1000000000 -> 1.4031719 | I16: =H16/(In!H6*F16*(1+In!H8)/1000+In!H7*In!H9/1000000000) -> 0.037331953 | J16: =In!H6*C16*D16/1000000 -> 1.474928 | K16: =(E16-In!H16*B16/1000-G16-In!H20)/E16 -> 0.82164364 | L16: =(F16-(In!H14*E16/1000+In!H21*In!H22/1000+C16*D16/1000+In!H29+In!H25*In!H26/1000+In!H27*In!H28/1000+F16*(In!H30+In!H32)))/F16 -> 0.1647619 | M16: =In!H16*B16/1000/E16 -> 0.087447273
A17: LPDDR 54 TB × $21／GB（記憶體最緊） | B17: =In!H17 -> 16.7 | C17: =In!I23 -> 54 | D17: =In!I24 -> 21 | E17: =In!H15 -> 55 | F17: =In!H5 -> 8.4 | G17: =In!H19 -> 2.8 | H17: =In!H7*In!H16*B17/1000000000 -> 1.4031719 | I17: =H17/(In!H6*F17*(1+In!H8)/1000+In!H7*In!H9/1000000000) -> 0.037331953 | J17: =In!H6*C17*D17/1000000 -> 4.594968 | K17: =(E17-In!H16*B17/1000-G17-In!H20)/E17 -> 0.83437091 | L17: =(F17-(In!H14*E17/1000+In!H21*In!H22/1000+C17*D17/1000+In!H29+In!H25*In!H26/1000+In!H27*In!H28/1000+F17*(In!H30+In!H32)))/F17 -> 0.073095238 | M17: =In!H16*B17/1000/E17 -> 0.087447273
A20: 讀法：VR200 的 HBM ÷ IT capex 在 2026 價約 3.7%、2027 價（$36/GB）約 8.0%；LPDDR 54 TB × $21/GB 時非 HBM DRAM 每 GW 是 HBM 的 3 倍以上。機架殘差變負＝輸入組合不可能（售價必須上調或 NVIDIA 讓利）

Sheet Requests
A1: 給算力收支的修改申請與回饋（由算力收支決定是否升版）
A3: R1 | B3: 工程類（建議） | C3: Interface 新增 IF_RackPrice（Spec_Rack 第 11–13 列）、IF_ScaleOutShare（Inputs 第 13 列）、IF_StoragePerGPU（Inputs 第 14 列），使下游不必讀非契約儲存格。數值不變。
A4: R2 | B4: 判斷類（提請注意，不建議本版改） | C4: VR200 機架價 8.4 以 MS 2026-05 BOM 為底。之後兩個方向相反的訊息：LPDDR5X 減半（54→28 TB，約 −$0.34M/架）與 2027 HBM4 合約價約翻倍（若全額轉嫁約 +$1.4M/架，+17%）。淨效果視 NVIDIA 吸收比例而定；建議在步驟 2 HBM 市場模型完成後再提數值。
A5: F1 | B5: 回饋（摘要數字） | C5: 每顆加速器 HBM 金額：GB300 約 $4.5K、VR200 2026 價約 $4.8K、2027 價約 $10.4K；每 GW HBM：$2.17B／$1.40B／$3.03B；HBM ÷ IT capex：5.8%／3.7%／8.0%（見 Bridge）。VR200 每 GW 的 HBM 位元（約 84 PB）低於 GB300（約 140 PB），因每 GW GPU 數少 40%、每顆容量相同。

Sheet Sources
A1: 來源
A2: Tokenomics v20.1 | B2: https://github.com/YinchenChang/Tokenomics/blob/master/model/20261023_Tokenomics_v20.1.xlsx
A3: Tokenomics v19.0（對照：數值與 v20.1 相同） | B3: https://github.com/YinchenChang/Tokenomics/blob/master/model/archive/20261022_Tokenomics_v19.0.xlsx
A4: Wing VC / Data Gravity, How Much Does an NVIDIA NVL72 Cost?（2026-08） | B4: https://www.wing.vc/content/how-much-does-an-nvidia-nvl72-cost
A5: Tom's Hardware（Morgan Stanley VR200 $7.8M、Rubin $55K、Vera $5K、記憶體約 $2M，2026-05-21） | B5: https://www.tomshardware.com/tech-industry/artificial-intelligence/nvidias-memory-costs-soar-485-percent-latest-ai-systems-now-cost-usd7-8-million-to-build-memory-now-comprises-25-percent-of-the-total-cost-rubin-gpus-a-mere-usd50-000-apiece
A6: Epoch AI, B200 cost breakdown（2025-12-10） | B6: https://epoch.ai/data-insights/b200-cost-breakdown
A7: Epoch AI, AI chip component cost shares（2026-05-21） | B7: https://epoch.ai/data-insights/ai-chip-component-cost-shares
A8: Silicon Analysts, AI Accelerator Manufacturing Cost Estimates（2026-08） | B8: https://siliconanalysts.com/data/ai-chip-costs
A9: UBS Vera Rubin superchip BOM（Let's Data Science 轉述 Wccftech／ChosunBiz，2026-08-10） | B9: https://letsdatascience.com/news/nvidia-vera-rubin-memory-costs-dominate-superchip-bom-1c630dcd
A10: Goldman Sachs 記憶體占 superchip 物料 62%／53%（Crypto Briefing，2026-08-10） | B10: https://cryptobriefing.com/nvidia-vera-rubin-memory-costs-goldman-sachs/
A11: Vera Rubin LPDDR 減半（TrendForce 2026-06-10；GF Securities 2026-07-26） | B11: https://letsdatascience.com/news/nvidia-reportedly-reduces-vera-rubin-memory-configuration-01e36b5d
A12: Wccftech, LPDDR 合約價（2026-05-04） | B12: https://wccftech.com/mobile-dram-prices-expected-to-increase-by-100-quarter-over-quarter-as-long-term-agreements-now-getting-signed-at-prices-as-high-as-21-gb/amp/
A13: Silicon Analysts（TrendForce 2027 HBM ASP +121%、首爾經濟日報 HBM4 $600→$1,300，2026-10-01） | B13: https://siliconanalysts.com/market/trendforce-lifts-2027-hbm-asp-forecast-to-121-hbm4-stack-seen-doubling-to-1-300-2026-10-01
... A18: Newegg ConnectX-8 零售價 | B18: https://www.newegg.com/p/N82E16833942013
