Workbook
Name w_irr: 參數!$B$2
Name w_pos: 參數!$B$3
Name w_vc: 參數!$B$4
Name s_irr1: 參數!$B$5
Name s_irr2: 參數!$B$6
Name s_irr3: 參數!$B$7
Name s_pos1: 參數!$B$8
Name s_pos2: 參數!$B$9
Name s_pos3: 參數!$B$10
Name s_pos4: 參數!$B$11

Sheet README
A1: AI 投資地圖 資料活頁簿 v0.5.1（20261026）
A2: 用途：AI 投資地圖網站（markets/invest_map/dist/index.html）的唯一數字來源。網站只呈現本活頁簿重算後的值。
A3: 三個視角：(1) 供應鏈地圖＝「價值鏈」頁＋Tokenomics 每 GW 金額；(2) 產業地位＝「地位」頁；(3) 可投資性＝「估值」頁。
A4: 黃底＝判斷輸入（Andy 可直接改；重建時讀回，不被程式覆寫）。藍字＝自各模型或 Tokenomics 抄錄的值，旁欄註明來源儲存格。其餘為公式。
A5: Tokenomics：20261024_Tokenomics_v21.4.xlsx（commit 3ac70ac；擷取 2026-10-25）
A6: 公司模型：company-models 各公司 dist/*.xlsx（extract_models.py 抽數）。
A7: AI半導體 候選母體 v0.2.2（2026-10-24）：次產業排序、公司重要性、市場地位文字。權威在 AI半導體 Project。
A8: 收支關卡（Andy 2026-10-25 10:48）：先看收支、再看評價。模型期間（2026 起約五年）現金收支合計為負＝入不敷出、有資金缺口，不論估值空間多大，最終分級一律為「收支不足」。口徑：雲端／neocloud／MAG 模板一律用「營運缺口＋股東回饋（股利、回購）」；記憶體、模型商用自由現金流；只有損益的半導體模型以「各情境淨利皆為正」判定（現金流本專案未建立）。
A9: 可投資性口徑（v0.5，Andy 2026-10-25 18:14：數字引用個股模型，模型沒有的才自算）：半導體 52 家的中心價＝模型「目標價（DCF 與 Comparable 加權）」、中心空間＝模型「上檔空間：加權目標價」、現價＝模型現價（上檔空間的分母）、投資建議與上檔空間級距＝模型 Val 列；模型尚未補列者依 AI半導體 固定規則（>+50% 強力買進、+25～+50% 買進、−25～+25% 中立、−50～−25% 放空、<−50% 強力放空）以模型上檔空間自算。悲觀情境空間（v0.5.1 前稱「下檔空間」）＝C 情境 DCF 價值 ÷ 模型現價 − 1（模型無此欄，自算）；不是一般所說目標價相對現價的下跌幅度。雲端與 neocloud（v0.5.1）：上檔空間＝模型加權目標價 ÷ 最近外部收盤價 − 1，依同一五級規則自算（不用模型自身評等，不再出現「賣出」）；MiniMax 用反向檢驗折現價值，依同一固定規則自算。
A10: 本活頁簿是研究整理，不是投資建議；各模型的方法與假設見各自 README 與 Val／摘要頁。

Sheet 參數
A1: 名稱 | B1: 值 | C1: 說明
A2: w_irr | B2: 0.4 | C2: 地位分數權重：不可替代性
A3: w_pos | B3: 0.35 | C3: 地位分數權重：市場位置
A4: w_vc | B4: 0.25 | C4: 地位分數權重：價值鏈分量
A5: s_irr1 | B5: 100 | C5: 不可替代性／重要性 1 → 分數
A6: s_irr2 | B6: 60 | C6: 2 → 分數
A7: s_irr3 | B7: 30 | C7: 3 → 分數
A8: s_pos1 | B8: 100 | C8: 市場位置 1 龍頭 → 分數
A9: s_pos2 | B9: 75 | C9: 2 前二或寡占 → 分數
A10: s_pos3 | B10: 50 | C10: 3 主要參與者 → 分數
A11: s_pos4 | B11: 25 | C11: 4 追隨者 → 分數

Sheet 每GW
A1: 項目 | B1: 世代 | C1: 低 | D1: 基準 | E1: 高 | F1: 單位 | G1: Tokenomics 名稱 | H1: 來源儲存格（基準）
A2: 每 GW 資本支出：IT 設備 | B2: GB300 | C2: 28.554902 | D2: 32.237224 | E2: 39.282606 | F2: $B | G2: IF_CapexIT | H2: Interface!J9
A3: 每 GW 資本支出：IT 設備 | B3: VR200 | C3: 31.997023 | D3: 37.586352 | E3: 42.637575 | F3: $B | G3: IF_CapexIT | H3: Interface!M9
A4: 每 GW 資本支出：設施（電力、機房、冷卻） | B4: GB300 | C4: 10.212 | D4: 12.67 | E4: 16.186 | F4: $B | G4: IF_CapexFacility | H4: Interface!J10
A5: 每 GW 資本支出：設施（電力、機房、冷卻） | B5: VR200 | C5: 10.212 | D5: 12.67 | E5: 16.186 | F5: $B | G5: IF_CapexFacility | H5: Interface!M10
A6: 每 GW 資本支出：合計 | B6: GB300 | C6: 38.766902 | D6: 44.907224 | E6: 55.468606 | F6: $B | G6: IF_CapexTotal | H6: Interface!J11
A7: 每 GW 資本支出：合計 | B7: VR200 | C7: 42.209023 | D7: 50.256352 | E7: 58.823575 | F7: $B | G7: IF_CapexTotal | H7: Interface!M11
A8: 每 GW 年經濟持有成本 | B8: GB300 | C8: 8.4288991 | D8: 10.886411 | E8: 18.534646 | F8: $B/GW/年 | G8: IF_HoldEcon | H8: Interface!J13
A9: 每 GW 年經濟持有成本 | B9: VR200 | C9: 9.2190715 | D9: 12.225471 | E9: 19.750627 | F9: $B/GW/年 | G9: IF_HoldEcon | H9: Interface!M13
A10: VR200 每 GW 營收 P×Q：第一年（m＝2026 Q2） | B10: VR200 | C10: 36.229598 | D10: 49.513784 | E10: 78.497462 | F10: $B/GW/年 | G10: L1_RevGW_PQ_VR200 | H10: L1!D129
A11: VR200 每 GW 營收 P×Q：壽命期平均（含 L） | B11: VR200 | C11: 16.158351 | D11: 34.602437 | E11: 85.88756 | F11: $B/GW/年 | G11: L1_RevGW_PQ_VR200_Life | H11: L1!D131
A12: 實際 L（機隊、折現） | B12: 機隊 | C12: 0.47944189 | D12: 0.75859737 | E12: 1.1382722 | F12: x | G12: L1_LTotalFleetVDisc | H12: L1!D116
A13: 回本所需 L（全部算力持有成本口徑） | B13: 機隊 | C13: 0.71561734 | D13: 0.80707823 | E13: 0.89452167 | F13: x | G13: L1_LReqFleet_Full | H13: L1!D140
A14: 回本比值（實際 L ÷ 所需 L） | B14: 機隊 | D14: =D12/D13 | F14: 倍 | G14: [Derived] | H14: Tokenomics 交接：0.940，「未定」

Sheet 價值鏈
A1: 層級 | B1: 次產業 | C1: 占 AI IT 資本支出 | D1: 比例中值 | E1: 每 GW 金額（GB300，$B） | F1: 不可替代性（1–3） | G1: 價值鏈分量分 | H1: 依據
A2: L5 模型商 | B2: AI 模型商 | C2: 營收端（P×Q） | F2: 2 | G2: 75 | H2: 收入池最上游：每 GW 第一年 P×Q 營收高於持有成本，但回本比值約 0.94，未定 [Derived]；分量分為判斷
A3: L4 算力平台 | B3: AI 雲端平台 | C3: 持有算力資產 | F3: 2 | G3: 100 | H3: 持有並出租算力；年持有成本由此層支付，是上游資本支出的付款方 [判斷]
A4: L4 算力平台 | B4: Neocloud（GPU 租賃） | C4: 持有算力資產 | F4: 3 | G4: 50 | H4: 同為算力持有者，但客戶集中、融資依賴高、可替代 [判斷]
A5: L3 IT 設備 | B5: 運算 | C5: 57.3%（VR200 2027 約 37%） | D5: 0.573 | E5: =D5*每GW!$D$2 | F5: 1 | G5: 100 | H5: 晶片內容橋接表 v0.2.1 Bridge GB300 欄 B10＋B11＋B13＋B14（NVIDIA 晶片毛利 48.5%＋台積電 3.5%＋其他製造 2.3%＋CPU 3.0%）÷ B7；HBM 移到記憶體 [Derived]
A6: L3 IT 設備 | B6: 記憶體 | C6: 13.4%（VR200 2027 約 23%） | D6: 0.134 | E6: =D6*每GW!$D$2 | F6: 1 | G6: 100 | H6: 晶片內容橋接表 v0.2.1 Bridge GB300 欄 B12＋B15＋B16（HBM 6.7%＋LPDDR 4.6%＋機架內 SSD 2.1%）÷ B7；2027 HBM 合約價約翻倍，VR200 2027 約 23%，級距沿用 100 [Derived]
A7: L3 IT 設備 | B7: 網通 | C7: 17.5%（VR200 約 19%） | D7: 0.175 | E7: =D7*每GW!$D$2 | F7: 2 | G7: 75 | H7: 晶片內容橋接表 v0.2.1 Bridge GB300 欄 B17＋B20（網卡與 DPU 4.0%＋NVLink 4.5%＋機架外交換器、光模組、線纜 9.0%）÷ B7 [Derived]
A8: L3 IT 設備 | B8: 載板與 PCB | C8: 含在運算「其他製造」2.3% 內（ABF 約 0.3%），不另加 | D8: 0.003 | E8: =D8*每GW!$D$2 | F8: 2 | G8: 25 | H8: AI半導體 次產業排序 v0.2.2（Ibiden 比對）；屬 晶片內容橋接表 v0.2.1 Bridge GB300 欄 B13 的一部分，金額不與運算相加 [Assumed] 區間
A9: L3 IT 設備 | B9: 電源與散熱 | C9: 6.3%（電源、散熱、機構、整合；電源＋散熱約 3–5%） | D9: 0.063 | E9: =D9*每GW!$D$2 | F9: 2 | G9: 25 | H9: 晶片內容橋接表 v0.2.1 Bridge GB300 欄 B18 ÷ B7；電源＋散熱 3–5% 為 AI半導體 判斷，級距依 3–5% 給 25 [Derived]／[Assumed]
A10: L3 IT 設備 | B10: 伺服器組裝 | C10: 4.6%（板卡、供電與組裝加價；ODM 附加價值約 1–3%） | D10: 0.046 | E10: =D10*每GW!$D$2 | F10: 3 | G10: 25 | H10: 晶片內容橋接表 v0.2.1 Bridge GB300 欄 B19 ÷ B7（殘差：匣級電路板、供電、NVIDIA／ODM 匣級加價）；ODM 附加價值 1–3% 為 AI半導體 判斷 [Derived]
A11: L2 半導體製造與設備 | B11: 代工與封測 | C11: 約 3.5%（含在 L3 運算內，不另加；僅 NVIDIA 平台） | D11: 0.035 | F11: 1 | G11: 75 | H11: 例外：晶片內容橋接表 v0.2.1 Bridge GB300 欄 B11 ÷ B7 只見 3.5%，但先進製程與 CoWoS 的價值藏在運算的晶片成本內，給 75 [判斷]
A12: L2 半導體製造與設備 | B12: 設備與材料 | C12: 約 7.5%（軸 B，不可與軸 A 相加） | D12: 0.075 | F12: 1 | G12: 50 | H12: AI半導體 次產業排序 v0.2.2（設備模型情境 A：2027 AI 相關設備 117.8B ÷ 1,565B）

Sheet 地位
A1: 代號 | B1: 公司 | C1: 層級 | D1: 次產業 | E1: 公司重要性（1–3） | F1: 市場位置（1–4） | G1: 地位依據 | H1: 標記 | I1: 次產業不可替代性 | J1: 價值鏈分量分 | K1: 不可替代性分 | L1: 市場位置分 | M1: 地位分數 | N1: 排名
A2: NVDA | B2: NVIDIA | C2: =價值鏈!A5 | D2: 運算 | E2: 1 | F2: 1 | G2: AI 加速器金額份額 CY2027 約 75–82%（本專案推導） | H2: [D] | I2: =價值鏈!F5 | J2: =價值鏈!G5 | K2: =(CHOOSE(I2,s_irr1,s_irr2,s_irr3)+CHOOSE(E2,s_irr1,s_irr2,s_irr3))/2 | L2: =CHOOSE(F2,s_pos1,s_pos2,s_pos3,s_pos4) | M2: =w_irr*K2+w_pos*L2+w_vc*J2 | N2: =RANK(M2,$M$2:$M$64,0)
A3: AVGO | B3: Broadcom | C3: =價值鏈!A5 | D3: 運算 | E3: 1 | F3: 2 | G3: 客製 ASIC 約 80–85%（JPMorgan）；運算整體第二 | H3: [IP] | I3: =價值鏈!F5 | J3: =價值鏈!G5 | K3: =(CHOOSE(I3,s_irr1,s_irr2,s_irr3)+CHOOSE(E3,s_irr1,s_irr2,s_irr3))/2 | L3: =CHOOSE(F3,s_pos1,s_pos2,s_pos3,s_pos4) | M3: =w_irr*K3+w_pos*L3+w_vc*J3 | N3: =RANK(M3,$M$2:$M$64,0)
A4: 000660 | B4: SK 海力士 | C4: =價值鏈!A6 | D4: 記憶體 | E4: 1 | F4: 1 | G4: 2026 HBM 市占 52–55%（本專案） | H4: [D] | I4: =價值鏈!F6 | J4: =價值鏈!G6 | K4: =(CHOOSE(I4,s_irr1,s_irr2,s_irr3)+CHOOSE(E4,s_irr1,s_irr2,s_irr3))/2 | L4: =CHOOSE(F4,s_pos1,s_pos2,s_pos3,s_pos4) | M4: =w_irr*K4+w_pos*L4+w_vc*J4 | N4: =RANK(M4,$M$2:$M$64,0)
A5: 005930 | B5: 三星電子 | C5: =價值鏈!A6 | D5: 記憶體 | E5: 1 | F5: 2 | G5: 2026 HBM 市占 28–32%（本專案） | H5: [D] | I5: =價值鏈!F6 | J5: =價值鏈!G6 | K5: =(CHOOSE(I5,s_irr1,s_irr2,s_irr3)+CHOOSE(E5,s_irr1,s_irr2,s_irr3))/2 | L5: =CHOOSE(F5,s_pos1,s_pos2,s_pos3,s_pos4) | M5: =w_irr*K5+w_pos*L5+w_vc*J5 | N5: =RANK(M5,$M$2:$M$64,0)
A6: MU | B6: 美光 | C6: =價值鏈!A6 | D6: 記憶體 | E6: 1 | F6: 3 | G6: 2026 HBM 市占 18–20%（本專案） | H6: [D] | I6: =價值鏈!F6 | J6: =價值鏈!G6 | K6: =(CHOOSE(I6,s_irr1,s_irr2,s_irr3)+CHOOSE(E6,s_irr1,s_irr2,s_irr3))/2 | L6: =CHOOSE(F6,s_pos1,s_pos2,s_pos3,s_pos4) | M6: =w_irr*K6+w_pos*L6+w_vc*J6 | N6: =RANK(M6,$M$2:$M$64,0)
A7: ANET | B7: Arista | C7: =價值鏈!A7 | D7: 網通 | E7: 1 | F7: 2 | G7: AI 後端乙太網路交換器份額約 18.7%（本專案 Arista 比對）；NVIDIA、白牌競爭 | H7: [D] | I7: =價值鏈!F7 | J7: =價值鏈!G7 | K7: =(CHOOSE(I7,s_irr1,s_irr2,s_irr3)+CHOOSE(E7,s_irr1,s_irr2,s_irr3))/2 | L7: =CHOOSE(F7,s_pos1,s_pos2,s_pos3,s_pos4) | M7: =w_irr*K7+w_pos*L7+w_vc*J7 | N7: =RANK(M7,$M$2:$M$64,0)
A8: 300308 | B8: 中際旭創 | C8: =價值鏈!A7 | D8: 網通 | E8: 1 | F8: 1 | G8: 高速光模組出貨領先（媒體與券商） | H8: [IP] | I8: =價值鏈!F7 | J8: =價值鏈!G7 | K8: =(CHOOSE(I8,s_irr1,s_irr2,s_irr3)+CHOOSE(E8,s_irr1,s_irr2,s_irr3))/2 | L8: =CHOOSE(F8,s_pos1,s_pos2,s_pos3,s_pos4) | M8: =w_irr*K8+w_pos*L8+w_vc*J8 | N8: =RANK(M8,$M$2:$M$64,0)
A9: 2330 | B9: 台積電 | C9: =價值鏈!A11 | D9: 代工與封測 | E9: 1 | F9: 1 | G9: 先進製程晶圓與 CoWoS 接近獨占 | H9: [判斷] | I9: =價值鏈!F11 | J9: =價值鏈!G11 | K9: =(CHOOSE(I9,s_irr1,s_irr2,s_irr3)+CHOOSE(E9,s_irr1,s_irr2,s_irr3))/2 | L9: =CHOOSE(F9,s_pos1,s_pos2,s_pos3,s_pos4) | M9: =w_irr*K9+w_pos*L9+w_vc*J9 | N9: =RANK(M9,$M$2:$M$64,0)
A10: 4062 | B10: Ibiden | C10: =價值鏈!A8 | D10: 載板與 PCB | E10: 1 | F10: 1 | G10: 高階 AI 載板主要供應者 | H10: [判斷] | I10: =價值鏈!F8 | J10: =價值鏈!G8 | K10: =(CHOOSE(I10,s_irr1,s_irr2,s_irr3)+CHOOSE(E10,s_irr1,s_irr2,s_irr3))/2 | L10: =CHOOSE(F10,s_pos1,s_pos2,s_pos3,s_pos4) | M10: =w_irr*K10+w_pos*L10+w_vc*J10 | N10: =RANK(M10,$M$2:$M$64,0)
A11: 2308 | B11: 台達電 | C11: =價值鏈!A9 | D11: 電源與散熱 | E11: 1 | F11: 1 | G11: 伺服器電源龍頭 | H11: [判斷] | I11: =價值鏈!F9 | J11: =價值鏈!G9 | K11: =(CHOOSE(I11,s_irr1,s_irr2,s_irr3)+CHOOSE(E11,s_irr1,s_irr2,s_irr3))/2 | L11: =CHOOSE(F11,s_pos1,s_pos2,s_pos3,s_pos4) | M11: =w_irr*K11+w_pos*L11+w_vc*J11 | N11: =RANK(M11,$M$2:$M$64,0)
A12: 2382 | B12: 廣達 | C12: =價值鏈!A10 | D12: 伺服器組裝 | E12: 1 | F12: 2 | G12: 雲端與 NVIDIA 整櫃主要 ODM；鴻海為最大組裝廠 | H12: [判斷] | I12: =價值鏈!F10 | J12: =價值鏈!G10 | K12: =(CHOOSE(I12,s_irr1,s_irr2,s_irr3)+CHOOSE(E12,s_irr1,s_irr2,s_irr3))/2 | L12: =CHOOSE(F12,s_pos1,s_pos2,s_pos3,s_pos4) | M12: =w_irr*K12+w_pos*L12+w_vc*J12 | N12: =RANK(M12,$M$2:$M$64,0)
A13: 6857 | B13: Advantest | C13: =價值鏈!A12 | D13: 設備與材料 | E13: 1 | F13: 1 | G13: SoC 測試市占 66%（公司自估 CY2025） | H13: [IP] | I13: =價值鏈!F12 | J13: =價值鏈!G12 | K13: =(CHOOSE(I13,s_irr1,s_irr2,s_irr3)+CHOOSE(E13,s_irr1,s_irr2,s_irr3))/2 | L13: =CHOOSE(F13,s_pos1,s_pos2,s_pos3,s_pos4) | M13: =w_irr*K13+w_pos*L13+w_vc*J13 | N13: =RANK(M13,$M$2:$M$64,0)
A14: 6146 | B14: Disco | C14: =價值鏈!A12 | D14: 設備與材料 | E14: 2 | F14: 1 | G14: 研削與切割市占 60–80%（兩來源） | H14: [IP] | I14: =價值鏈!F12 | J14: =價值鏈!G12 | K14: =(CHOOSE(I14,s_irr1,s_irr2,s_irr3)+CHOOSE(E14,s_irr1,s_irr2,s_irr3))/2 | L14: =CHOOSE(F14,s_pos1,s_pos2,s_pos3,s_pos4) | M14: =w_irr*K14+w_pos*L14+w_vc*J14 | N14: =RANK(M14,$M$2:$M$64,0)
A15: AMZN | B15: Amazon | C15: =價值鏈!A3 | D15: AI 雲端平台 | E15: 1 | F15: 1 | G15: AWS 為最大公有雲；自研 Trainium | H15: [判斷] | I15: =價值鏈!F3 | J15: =價值鏈!G3 | K15: =(CHOOSE(I15,s_irr1,s_irr2,s_irr3)+CHOOSE(E15,s_irr1,s_irr2,s_irr3))/2 | L15: =CHOOSE(F15,s_pos1,s_pos2,s_pos3,s_pos4) | M15: =w_irr*K15+w_pos*L15+w_vc*J15 | N15: =RANK(M15,$M$2:$M$64,0)
A16: MSFT | B16: Microsoft | C16: =價值鏈!A3 | D16: AI 雲端平台 | E16: 1 | F16: 2 | G16: Azure 第二大公有雲；OpenAI 主要算力夥伴 | H16: [判斷] | I16: =價值鏈!F3 | J16: =價值鏈!G3 | K16: =(CHOOSE(I16,s_irr1,s_irr2,s_irr3)+CHOOSE(E16,s_irr1,s_irr2,s_irr3))/2 | L16: =CHOOSE(F16,s_pos1,s_pos2,s_pos3,s_pos4) | M16: =w_irr*K16+w_pos*L16+w_vc*J16 | N16: =RANK(M16,$M$2:$M$64,0)
A17: GOOGL | B17: Alphabet | C17: =價值鏈!A3 | D17: AI 雲端平台 | E17: 1 | F17: 2 | G17: TPU＋Gemini 垂直整合；雲端第三 | H17: [判斷] | I17: =價值鏈!F3 | J17: =價值鏈!G3 | K17: =(CHOOSE(I17,s_irr1,s_irr2,s_irr3)+CHOOSE(E17,s_irr1,s_irr2,s_irr3))/2 | L17: =CHOOSE(F17,s_pos1,s_pos2,s_pos3,s_pos4) | M17: =w_irr*K17+w_pos*L17+w_vc*J17 | N17: =RANK(M17,$M$2:$M$64,0)
A18: ORCL | B18: Oracle | C18: =價值鏈!A3 | D18: AI 雲端平台 | E18: 2 | F18: 3 | G18: OCI 規模較小；Stargate 主要承建方，客戶集中 | H18: [判斷] | I18: =價值鏈!F3 | J18: =價值鏈!G3 | K18: =(CHOOSE(I18,s_irr1,s_irr2,s_irr3)+CHOOSE(E18,s_irr1,s_irr2,s_irr3))/2 | L18: =CHOOSE(F18,s_pos1,s_pos2,s_pos3,s_pos4) | M18: =w_irr*K18+w_pos*L18+w_vc*J18 | N18: =RANK(M18,$M$2:$M$64,0)
A19: CRWV | B19: CoreWeave | C19: =價值鏈!A4 | D19: Neocloud（GPU 租賃） | E19: 2 | F19: 1 | G19: 最大 neocloud；客戶集中於 Microsoft、OpenAI | H19: [判斷] | I19: =價值鏈!F4 | J19: =價值鏈!G4 | K19: =(CHOOSE(I19,s_irr1,s_irr2,s_irr3)+CHOOSE(E19,s_irr1,s_irr2,s_irr3))/2 | L19: =CHOOSE(F19,s_pos1,s_pos2,s_pos3,s_pos4) | M19: =w_irr*K19+w_pos*L19+w_vc*J19 | N19: =RANK(M19,$M$2:$M$64,0)
A20: NBIS | B20: Nebius | C20: =價值鏈!A4 | D20: Neocloud（GPU 租賃） | E20: 2 | F20: 2 | G20: 歐洲為主的 neocloud；Microsoft 長約 | H20: [判斷] | I20: =價值鏈!F4 | J20: =價值鏈!G4 | K20: =(CHOOSE(I20,s_irr1,s_irr2,s_irr3)+CHOOSE(E20,s_irr1,s_irr2,s_irr3))/2 | L20: =CHOOSE(F20,s_pos1,s_pos2,s_pos3,s_pos4) | M20: =w_irr*K20+w_pos*L20+w_vc*J20 | N20: =RANK(M20,$M$2:$M$64,0)
A21: WYFI | B21: WhiteFiber | C21: =價值鏈!A4 | D21: Neocloud（GPU 租賃） | E21: 3 | F21: 4 | G21: 小型 neocloud＋託管 | H21: [判斷] | I21: =價值鏈!F4 | J21: =價值鏈!G4 | K21: =(CHOOSE(I21,s_irr1,s_irr2,s_irr3)+CHOOSE(E21,s_irr1,s_irr2,s_irr3))/2 | L21: =CHOOSE(F21,s_pos1,s_pos2,s_pos3,s_pos4) | M21: =w_irr*K21+w_pos*L21+w_vc*J21 | N21: =RANK(M21,$M$2:$M$64,0)
A22: OpenAI | B22: OpenAI | C22: =價值鏈!A2 | D22: AI 模型商 | E22: 1 | F22: 1 | G22: ChatGPT 與 API 用量最大的模型商；算力承諾最大（本專案 OpenAI 模型） | H22: [判斷] | I22: =價值鏈!F2 | J22: =價值鏈!G2 | K22: =(CHOOSE(I22,s_irr1,s_irr2,s_irr3)+CHOOSE(E22,s_irr1,s_irr2,s_irr3))/2 | L22: =CHOOSE(F22,s_pos1,s_pos2,s_pos3,s_pos4) | M22: =w_irr*K22+w_pos*L22+w_vc*J22 | N22: =RANK(M22,$M$2:$M$64,0)
A23: Anthropic | B23: Anthropic | C23: =價值鏈!A2 | D23: AI 模型商 | E23: 1 | F23: 2 | G23: 企業與程式開發用途為主的前沿模型商（本專案 Anthropic 模型） | H23: [判斷] | I23: =價值鏈!F2 | J23: =價值鏈!G2 | K23: =(CHOOSE(I23,s_irr1,s_irr2,s_irr3)+CHOOSE(E23,s_irr1,s_irr2,s_irr3))/2 | L23: =CHOOSE(F23,s_pos1,s_pos2,s_pos3,s_pos4) | M23: =w_irr*K23+w_pos*L23+w_vc*J23 | N23: =RANK(M23,$M$2:$M$64,0)
A24: 00100 | B24: MiniMax | C24: =價值鏈!A2 | D24: AI 模型商 | E24: 3 | F24: 3 | G24: 中國第二梯隊模型商；多模態、海外營收占比高 | H24: [判斷] | I24: =價值鏈!F2 | J24: =價值鏈!G2 | K24: =(CHOOSE(I24,s_irr1,s_irr2,s_irr3)+CHOOSE(E24,s_irr1,s_irr2,s_irr3))/2 | L24: =CHOOSE(F24,s_pos1,s_pos2,s_pos3,s_pos4) | M24: =w_irr*K24+w_pos*L24+w_vc*J24 | N24: =RANK(M24,$M$2:$M$64,0)
A25: 02513 | B25: 智譜 | C25: =價值鏈!A2 | D25: AI 模型商 | E25: 3 | F25: 3 | G25: 中國第二梯隊模型商；政企本地化部署 | H25: [判斷] | I25: =價值鏈!F2 | J25: =價值鏈!G2 | K25: =(CHOOSE(I25,s_irr1,s_irr2,s_irr3)+CHOOSE(E25,s_irr1,s_irr2,s_irr3))/2 | L25: =CHOOSE(F25,s_pos1,s_pos2,s_pos3,s_pos4) | M25: =w_irr*K25+w_pos*L25+w_vc*J25 | N25: =RANK(M25,$M$2:$M$64,0)
A26: AMD | B26: AMD | C26: =價值鏈!A5 | D26: 運算 | E26: 2 | F26: 3 | G26: AI 加速器金額份額 CY2027 約 3–6%（本專案推導）；2027 資料中心「超過一倍」（公司）（AI半導體 候選母體 v0.2.2；市場位置由次產業內優先序 3 換算） | H26: [判斷] | I26: =價值鏈!F5 | J26: =價值鏈!G5 | K26: =(CHOOSE(I26,s_irr1,s_irr2,s_irr3)+CHOOSE(E26,s_irr1,s_irr2,s_irr3))/2 | L26: =CHOOSE(F26,s_pos1,s_pos2,s_pos3,s_pos4) | M26: =w_irr*K26+w_pos*L26+w_vc*J26 | N26: =RANK(M26,$M$2:$M$64,0)
A27: 2454 | B27: 聯發科 | C27: =價值鏈!A5 | D27: 運算 | E27: 2 | F27: 3 | G27: Google TPU 合作（媒體報導）（AI半導體 候選母體 v0.2.2；市場位置由次產業內優先序 4 換算） | H27: [判斷] | I27: =價值鏈!F5 | J27: =價值鏈!G5 | K27: =(CHOOSE(I27,s_irr1,s_irr2,s_irr3)+CHOOSE(E27,s_irr1,s_irr2,s_irr3))/2 | L27: =CHOOSE(F27,s_pos1,s_pos2,s_pos3,s_pos4) | M27: =w_irr*K27+w_pos*L27+w_vc*J27 | N27: =RANK(M27,$M$2:$M$64,0)
A28: MRVL | B28: Marvell | C28: =價值鏈!A5 | D28: 運算 | E28: 2 | F28: 3 | G28: 光 DSP 主要供應商之一（AI半導體 候選母體 v0.2.2；市場位置由次產業內優先序 5 換算） | H28: [判斷] | I28: =價值鏈!F5 | J28: =價值鏈!G5 | K28: =(CHOOSE(I28,s_irr1,s_irr2,s_irr3)+CHOOSE(E28,s_irr1,s_irr2,s_irr3))/2 | L28: =CHOOSE(F28,s_pos1,s_pos2,s_pos3,s_pos4) | M28: =w_irr*K28+w_pos*L28+w_vc*J28 | N28: =RANK(M28,$M$2:$M$64,0)
A29: 3661 | B29: 世芯-KY | C29: =價值鏈!A5 | D29: 運算 | E29: 2 | F29: 4 | G29: 雲端客製晶片設計服務（AI半導體 候選母體 v0.2.2；市場位置由次產業內優先序 6 換算） | H29: [判斷] | I29: =價值鏈!F5 | J29: =價值鏈!G5 | K29: =(CHOOSE(I29,s_irr1,s_irr2,s_irr3)+CHOOSE(E29,s_irr1,s_irr2,s_irr3))/2 | L29: =CHOOSE(F29,s_pos1,s_pos2,s_pos3,s_pos4) | M29: =w_irr*K29+w_pos*L29+w_vc*J29 | N29: =RANK(M29,$M$2:$M$64,0)
A30: 3443 | B30: 創意 | C30: =價值鏈!A5 | D30: 運算 | E30: 3 | F30: 4 | G30: 台積電轉投資的設計服務廠（AI半導體 候選母體 v0.2.2；市場位置由次產業內優先序 7 換算） | H30: [判斷] | I30: =價值鏈!F5 | J30: =價值鏈!G5 | K30: =(CHOOSE(I30,s_irr1,s_irr2,s_irr3)+CHOOSE(E30,s_irr1,s_irr2,s_irr3))/2 | L30: =CHOOSE(F30,s_pos1,s_pos2,s_pos3,s_pos4) | M30: =w_irr*K30+w_pos*L30+w_vc*J30 | N30: =RANK(M30,$M$2:$M$64,0)
A31: 285A | B31: Kioxia | C31: =價值鏈!A6 | D31: 記憶體 | E31: 3 | F31: 3 | G31: NAND 主要廠之一；10-23 曾因「不能由既有層推得」排除，15:59 已取消該關卡（AI半導體 候選母體 v0.2.2；市場位置由次產業內優先序 4 換算） | H31: [判斷] | I31: =價值鏈!F6 | J31: =價值鏈!G6 | K31: =(CHOOSE(I31,s_irr1,s_irr2,s_irr3)+CHOOSE(E31,s_irr1,s_irr2,s_irr3))/2 | L31: =CHOOSE(F31,s_pos1,s_pos2,s_pos3,s_pos4) | M31: =w_irr*K31+w_pos*L31+w_vc*J31 | N31: =RANK(M31,$M$2:$M$64,0)
A32: SNDK | B32: SanDisk | C32: =價值鏈!A6 | D32: 記憶體 | E32: 3 | F32: 3 | G32: 與 Kioxia 合資產能（AI半導體 候選母體 v0.2.2；市場位置由次產業內優先序 5 換算） | H32: [判斷] | I32: =價值鏈!F6 | J32: =價值鏈!G6 | K32: =(CHOOSE(I32,s_irr1,s_irr2,s_irr3)+CHOOSE(E32,s_irr1,s_irr2,s_irr3))/2 | L32: =CHOOSE(F32,s_pos1,s_pos2,s_pos3,s_pos4) | M32: =w_irr*K32+w_pos*L32+w_vc*J32 | N32: =RANK(M32,$M$2:$M$64,0)
A33: COHR | B33: Coherent | C33: =價值鏈!A7 | D33: 網通 | E33: 2 | F33: 3 | G33: 光模組與元件垂直整合廠（AI半導體 候選母體 v0.2.2；市場位置由次產業內優先序 3 換算） | H33: [判斷] | I33: =價值鏈!F7 | J33: =價值鏈!G7 | K33: =(CHOOSE(I33,s_irr1,s_irr2,s_irr3)+CHOOSE(E33,s_irr1,s_irr2,s_irr3))/2 | L33: =CHOOSE(F33,s_pos1,s_pos2,s_pos3,s_pos4) | M33: =w_irr*K33+w_pos*L33+w_vc*J33 | N33: =RANK(M33,$M$2:$M$64,0)
A34: LITE | B34: Lumentum | C34: =價值鏈!A7 | D34: 網通 | E34: 2 | F34: 3 | G34: 高速 EML 雷射主要供應商之一（AI半導體 候選母體 v0.2.2；市場位置由次產業內優先序 4 換算） | H34: [判斷] | I34: =價值鏈!F7 | J34: =價值鏈!G7 | K34: =(CHOOSE(I34,s_irr1,s_irr2,s_irr3)+CHOOSE(E34,s_irr1,s_irr2,s_irr3))/2 | L34: =CHOOSE(F34,s_pos1,s_pos2,s_pos3,s_pos4) | M34: =w_irr*K34+w_pos*L34+w_vc*J34 | N34: =RANK(M34,$M$2:$M$64,0)
A35: 300502 | B35: 新易盛 | C35: =價值鏈!A7 | D35: 網通 | E35: 2 | F35: 3 | G35: 高速光模組第二梯隊領先者（AI半導體 候選母體 v0.2.2；市場位置由次產業內優先序 5 換算） | H35: [判斷] | I35: =價值鏈!F7 | J35: =價值鏈!G7 | K35: =(CHOOSE(I35,s_irr1,s_irr2,s_irr3)+CHOOSE(E35,s_irr1,s_irr2,s_irr3))/2 | L35: =CHOOSE(F35,s_pos1,s_pos2,s_pos3,s_pos4) | M35: =w_irr*K35+w_pos*L35+w_vc*J35 | N35: =RANK(M35,$M$2:$M$64,0)
A36: 2345 | B36: 智邦 | C36: =價值鏈!A7 | D36: 網通 | E36: 2 | F36: 4 | G36: 雲端白牌交換器主要 ODM（AI半導體 候選母體 v0.2.2；市場位置由次產業內優先序 6 換算） | H36: [判斷] | I36: =價值鏈!F7 | J36: =價值鏈!G7 | K36: =(CHOOSE(I36,s_irr1,s_irr2,s_irr3)+CHOOSE(E36,s_irr1,s_irr2,s_irr3))/2 | L36: =CHOOSE(F36,s_pos1,s_pos2,s_pos3,s_pos4) | M36: =w_irr*K36+w_pos*L36+w_vc*J36 | N36: =RANK(M36,$M$2:$M$64,0)
A37: FN | B37: Fabrinet | C37: =價值鏈!A7 | D37: 網通 | E37: 2 | F37: 4 | G37: NVIDIA 光模組主要代工之一（AI半導體 候選母體 v0.2.2；市場位置由次產業內優先序 7 換算） | H37: [判斷] | I37: =價值鏈!F7 | J37: =價值鏈!G7 | K37: =(CHOOSE(I37,s_irr1,s_irr2,s_irr3)+CHOOSE(E37,s_irr1,s_irr2,s_irr3))/2 | L37: =CHOOSE(F37,s_pos1,s_pos2,s_pos3,s_pos4) | M37: =w_irr*K37+w_pos*L37+w_vc*J37 | N37: =RANK(M37,$M$2:$M$64,0)
A38: CRDO | B38: Credo | C38: =價值鏈!A7 | D38: 網通 | E38: 2 | F38: 4 | G38: AEC 主要供應商（AI半導體 候選母體 v0.2.2；市場位置由次產業內優先序 8 換算） | H38: [判斷] | I38: =價值鏈!F7 | J38: =價值鏈!G7 | K38: =(CHOOSE(I38,s_irr1,s_irr2,s_irr3)+CHOOSE(E38,s_irr1,s_irr2,s_irr3))/2 | L38: =CHOOSE(F38,s_pos1,s_pos2,s_pos3,s_pos4) | M38: =w_irr*K38+w_pos*L38+w_vc*J38 | N38: =RANK(M38,$M$2:$M$64,0)
A39: ALAB | B39: Astera Labs | C39: =價值鏈!A7 | D39: 網通 | E39: 3 | F39: 4 | G39: retimer 主要供應商（AI半導體 候選母體 v0.2.2；市場位置由次產業內優先序 9 換算） | H39: [判斷] | I39: =價值鏈!F7 | J39: =價值鏈!G7 | K39: =(CHOOSE(I39,s_irr1,s_irr2,s_irr3)+CHOOSE(E39,s_irr1,s_irr2,s_irr3))/2 | L39: =CHOOSE(F39,s_pos1,s_pos2,s_pos3,s_pos4) | M39: =w_irr*K39+w_pos*L39+w_vc*J39 | N39: =RANK(M39,$M$2:$M$64,0)
A40: 2449 | B40: 京元電 | C40: =價值鏈!A11 | D40: 代工與封測 | E40: 2 | F40: 3 | G40: AI GPU 測試主要代工之一（媒體）（AI半導體 候選母體 v0.2.2；市場位置由次產業內優先序 3 換算） | H40: [判斷] | I40: =價值鏈!F11 | J40: =價值鏈!G11 | K40: =(CHOOSE(I40,s_irr1,s_irr2,s_irr3)+CHOOSE(E40,s_irr1,s_irr2,s_irr3))/2 | L40: =CHOOSE(F40,s_pos1,s_pos2,s_pos3,s_pos4) | M40: =w_irr*K40+w_pos*L40+w_vc*J40 | N40: =RANK(M40,$M$2:$M$64,0)
A41: AMKR | B41: Amkor | C41: =價值鏈!A11 | D41: 代工與封測 | E41: 2 | F41: 3 | G41: 全球第二大封測廠（AI半導體 候選母體 v0.2.2；市場位置由次產業內優先序 4 換算） | H41: [判斷] | I41: =價值鏈!F11 | J41: =價值鏈!G11 | K41: =(CHOOSE(I41,s_irr1,s_irr2,s_irr3)+CHOOSE(E41,s_irr1,s_irr2,s_irr3))/2 | L41: =CHOOSE(F41,s_pos1,s_pos2,s_pos3,s_pos4) | M41: =w_irr*K41+w_pos*L41+w_vc*J41 | N41: =RANK(M41,$M$2:$M$64,0)
A42: 2383 | B42: 台光電 | C42: =價值鏈!A8 | D42: 載板與 PCB | E42: 1 | F42: 2 | G42: AI 伺服器高速 CCL 主要供應者（AI半導體 候選母體 v0.2.2；市場位置由次產業內優先序 2 換算） | H42: [判斷] | I42: =價值鏈!F8 | J42: =價值鏈!G8 | K42: =(CHOOSE(I42,s_irr1,s_irr2,s_irr3)+CHOOSE(E42,s_irr1,s_irr2,s_irr3))/2 | L42: =CHOOSE(F42,s_pos1,s_pos2,s_pos3,s_pos4) | M42: =w_irr*K42+w_pos*L42+w_vc*J42 | N42: =RANK(M42,$M$2:$M$64,0)
A43: 3037 | B43: 欣興 | C43: =價值鏈!A8 | D43: 載板與 PCB | E43: 1 | F43: 3 | G43: ABF 載板主要廠之一（AI半導體 候選母體 v0.2.2；市場位置由次產業內優先序 3 換算） | H43: [判斷] | I43: =價值鏈!F8 | J43: =價值鏈!G8 | K43: =(CHOOSE(I43,s_irr1,s_irr2,s_irr3)+CHOOSE(E43,s_irr1,s_irr2,s_irr3))/2 | L43: =CHOOSE(F43,s_pos1,s_pos2,s_pos3,s_pos4) | M43: =w_irr*K43+w_pos*L43+w_vc*J43 | N43: =RANK(M43,$M$2:$M$64,0)
A44: 8046 | B44: 南電 | C44: =價值鏈!A8 | D44: 載板與 PCB | E44: 2 | F44: 3 | G44: ABF 載板主要廠之一（AI半導體 候選母體 v0.2.2；市場位置由次產業內優先序 5 換算） | H44: [判斷] | I44: =價值鏈!F8 | J44: =價值鏈!G8 | K44: =(CHOOSE(I44,s_irr1,s_irr2,s_irr3)+CHOOSE(E44,s_irr1,s_irr2,s_irr3))/2 | L44: =CHOOSE(F44,s_pos1,s_pos2,s_pos3,s_pos4) | M44: =w_irr*K44+w_pos*L44+w_vc*J44 | N44: =RANK(M44,$M$2:$M$64,0)
A45: 2368 | B45: 金像電 | C45: =價值鏈!A8 | D45: 載板與 PCB | E45: 2 | F45: 4 | G45: 雲端伺服器 PCB 主要廠（AI半導體 候選母體 v0.2.2；市場位置由次產業內優先序 6 換算） | H45: [判斷] | I45: =價值鏈!F8 | J45: =價值鏈!G8 | K45: =(CHOOSE(I45,s_irr1,s_irr2,s_irr3)+CHOOSE(E45,s_irr1,s_irr2,s_irr3))/2 | L45: =CHOOSE(F45,s_pos1,s_pos2,s_pos3,s_pos4) | M45: =w_irr*K45+w_pos*L45+w_vc*J45 | N45: =RANK(M45,$M$2:$M$64,0)
A46: 300476 | B46: 勝宏科技 | C46: =價值鏈!A8 | D46: 載板與 PCB | E46: 2 | F46: 4 | G46: NVIDIA 加速卡 PCB 主要供應商之一（媒體）（AI半導體 候選母體 v0.2.2；市場位置由次產業內優先序 7 換算） | H46: [判斷] | I46: =價值鏈!F8 | J46: =價值鏈!G8 | K46: =(CHOOSE(I46,s_irr1,s_irr2,s_irr3)+CHOOSE(E46,s_irr1,s_irr2,s_irr3))/2 | L46: =CHOOSE(F46,s_pos1,s_pos2,s_pos3,s_pos4) | M46: =w_irr*K46+w_pos*L46+w_vc*J46 | N46: =RANK(M46,$M$2:$M$64,0)
A47: ASML | B47: ASML | C47: =價值鏈!A12 | D47: 設備與材料 | E47: 1 | F47: 1 | G47: EUV 唯一供應者（AI半導體 候選母體 v0.2.2；市場位置由次產業內優先序 1 換算） | H47: [判斷] | I47: =價值鏈!F12 | J47: =價值鏈!G12 | K47: =(CHOOSE(I47,s_irr1,s_irr2,s_irr3)+CHOOSE(E47,s_irr1,s_irr2,s_irr3))/2 | L47: =CHOOSE(F47,s_pos1,s_pos2,s_pos3,s_pos4) | M47: =w_irr*K47+w_pos*L47+w_vc*J47 | N47: =RANK(M47,$M$2:$M$64,0)
A48: AMAT | B48: Applied Materials | C48: =價值鏈!A12 | D48: 設備與材料 | E48: 1 | F48: 2 | G48: 全球營收最大的設備商之一（AI半導體 候選母體 v0.2.2；市場位置由次產業內優先序 2 換算） | H48: [判斷] | I48: =價值鏈!F12 | J48: =價值鏈!G12 | K48: =(CHOOSE(I48,s_irr1,s_irr2,s_irr3)+CHOOSE(E48,s_irr1,s_irr2,s_irr3))/2 | L48: =CHOOSE(F48,s_pos1,s_pos2,s_pos3,s_pos4) | M48: =w_irr*K48+w_pos*L48+w_vc*J48 | N48: =RANK(M48,$M$2:$M$64,0)
A49: LRCX | B49: Lam Research | C49: =價值鏈!A12 | D49: 設備與材料 | E49: 1 | F49: 3 | G49: 記憶體蝕刻主要供應者（AI半導體 候選母體 v0.2.2；市場位置由次產業內優先序 3 換算） | H49: [判斷] | I49: =價值鏈!F12 | J49: =價值鏈!G12 | K49: =(CHOOSE(I49,s_irr1,s_irr2,s_irr3)+CHOOSE(E49,s_irr1,s_irr2,s_irr3))/2 | L49: =CHOOSE(F49,s_pos1,s_pos2,s_pos3,s_pos4) | M49: =w_irr*K49+w_pos*L49+w_vc*J49 | N49: =RANK(M49,$M$2:$M$64,0)
A50: KLAC | B50: KLA | C50: =價值鏈!A12 | D50: 設備與材料 | E50: 1 | F50: 3 | G50: 製程控制龍頭（AI半導體 候選母體 v0.2.2；市場位置由次產業內優先序 5 換算） | H50: [判斷] | I50: =價值鏈!F12 | J50: =價值鏈!G12 | K50: =(CHOOSE(I50,s_irr1,s_irr2,s_irr3)+CHOOSE(E50,s_irr1,s_irr2,s_irr3))/2 | L50: =CHOOSE(F50,s_pos1,s_pos2,s_pos3,s_pos4) | M50: =w_irr*K50+w_pos*L50+w_vc*J50 | N50: =RANK(M50,$M$2:$M$64,0)
A51: 042700 | B51: Hanmi | C51: =價值鏈!A12 | D51: 設備與材料 | E51: 2 | F51: 4 | G51: HBM TC 鍵合機約 71%（本專案 HBM 比對）（AI半導體 候選母體 v0.2.2；市場位置由次產業內優先序 8 換算） | H51: [判斷] | I51: =價值鏈!F12 | J51: =價值鏈!G12 | K51: =(CHOOSE(I51,s_irr1,s_irr2,s_irr3)+CHOOSE(E51,s_irr1,s_irr2,s_irr3))/2 | L51: =CHOOSE(F51,s_pos1,s_pos2,s_pos3,s_pos4) | M51: =w_irr*K51+w_pos*L51+w_vc*J51 | N51: =RANK(M51,$M$2:$M$64,0)
A52: TER | B52: Teradyne | C52: =價值鏈!A12 | D52: 設備與材料 | E52: 2 | F52: 4 | G52: SoC 測試第 2（Advantest 之後）（AI半導體 候選母體 v0.2.2；市場位置由次產業內優先序 9 換算） | H52: [判斷] | I52: =價值鏈!F12 | J52: =價值鏈!G12 | K52: =(CHOOSE(I52,s_irr1,s_irr2,s_irr3)+CHOOSE(E52,s_irr1,s_irr2,s_irr3))/2 | L52: =CHOOSE(F52,s_pos1,s_pos2,s_pos3,s_pos4) | M52: =w_irr*K52+w_pos*L52+w_vc*J52 | N52: =RANK(M52,$M$2:$M$64,0)
A53: BESI | B53: BESI | C53: =價值鏈!A12 | D53: 設備與材料 | E53: 3 | F53: 4 | G53: 混合鍵合領先者；主流化時點約 2029–30（本專案）（AI半導體 候選母體 v0.2.2；市場位置由次產業內優先序 10 換算） | H53: [判斷] | I53: =價值鏈!F12 | J53: =價值鏈!G12 | K53: =(CHOOSE(I53,s_irr1,s_irr2,s_irr3)+CHOOSE(E53,s_irr1,s_irr2,s_irr3))/2 | L53: =CHOOSE(F53,s_pos1,s_pos2,s_pos3,s_pos4) | M53: =w_irr*K53+w_pos*L53+w_vc*J53 | N53: =RANK(M53,$M$2:$M$64,0)
A54: 6315 | B54: TOWA | C54: =價值鏈!A12 | D54: 設備與材料 | E54: 3 | F54: 4 | G54: 市占約 2/3（本專案候選表）（AI半導體 候選母體 v0.2.2；市場位置由次產業內優先序 11 換算） | H54: [判斷] | I54: =價值鏈!F12 | J54: =價值鏈!G12 | K54: =(CHOOSE(I54,s_irr1,s_irr2,s_irr3)+CHOOSE(E54,s_irr1,s_irr2,s_irr3))/2 | L54: =CHOOSE(F54,s_pos1,s_pos2,s_pos3,s_pos4) | M54: =w_irr*K54+w_pos*L54+w_vc*J54 | N54: =RANK(M54,$M$2:$M$64,0)
A55: 7729 | B55: 東京精密 | C55: =價值鏈!A12 | D55: 設備與材料 | E55: 3 | F55: 4 | G55: 探針台主要廠之一（AI半導體 候選母體 v0.2.2；市場位置由次產業內優先序 12 換算） | H55: [判斷] | I55: =價值鏈!F12 | J55: =價值鏈!G12 | K55: =(CHOOSE(I55,s_irr1,s_irr2,s_irr3)+CHOOSE(E55,s_irr1,s_irr2,s_irr3))/2 | L55: =CHOOSE(F55,s_pos1,s_pos2,s_pos3,s_pos4) | M55: =w_irr*K55+w_pos*L55+w_vc*J55 | N55: =RANK(M55,$M$2:$M$64,0)
A56: 2317 | B56: 鴻海 | C56: =價值鏈!A10 | D56: 伺服器組裝 | E56: 1 | F56: 1 | G56: NVIDIA 整櫃最大組裝廠（AI半導體 候選母體 v0.2.2；市場位置由次產業內優先序 1 換算） | H56: [判斷] | I56: =價值鏈!F10 | J56: =價值鏈!G10 | K56: =(CHOOSE(I56,s_irr1,s_irr2,s_irr3)+CHOOSE(E56,s_irr1,s_irr2,s_irr3))/2 | L56: =CHOOSE(F56,s_pos1,s_pos2,s_pos3,s_pos4) | M56: =w_irr*K56+w_pos*L56+w_vc*J56 | N56: =RANK(M56,$M$2:$M$64,0)
A57: 3231 | B57: 緯創 | C57: =價值鏈!A10 | D57: 伺服器組裝 | E57: 1 | F57: 3 | G57: NVIDIA GPU 基板主要供應者（AI半導體 候選母體 v0.2.2；市場位置由次產業內優先序 3 換算） | H57: [判斷] | I57: =價值鏈!F10 | J57: =價值鏈!G10 | K57: =(CHOOSE(I57,s_irr1,s_irr2,s_irr3)+CHOOSE(E57,s_irr1,s_irr2,s_irr3))/2 | L57: =CHOOSE(F57,s_pos1,s_pos2,s_pos3,s_pos4) | M57: =w_irr*K57+w_pos*L57+w_vc*J57 | N57: =RANK(M57,$M$2:$M$64,0)
A58: 6669 | B58: 緯穎 | C58: =價值鏈!A10 | D58: 伺服器組裝 | E58: 2 | F58: 3 | G58: 雲端白牌伺服器主要 ODM（AI半導體 候選母體 v0.2.2；市場位置由次產業內優先序 4 換算） | H58: [判斷] | I58: =價值鏈!F10 | J58: =價值鏈!G10 | K58: =(CHOOSE(I58,s_irr1,s_irr2,s_irr3)+CHOOSE(E58,s_irr1,s_irr2,s_irr3))/2 | L58: =CHOOSE(F58,s_pos1,s_pos2,s_pos3,s_pos4) | M58: =w_irr*K58+w_pos*L58+w_vc*J58 | N58: =RANK(M58,$M$2:$M$64,0)
A59: DELL | B59: Dell | C59: =價值鏈!A10 | D59: 伺服器組裝 | E59: 2 | F59: 3 | G59: 企業與 neocloud 主要品牌（AI半導體 候選母體 v0.2.2；市場位置由次產業內優先序 5 換算） | H59: [判斷] | I59: =價值鏈!F10 | J59: =價值鏈!G10 | K59: =(CHOOSE(I59,s_irr1,s_irr2,s_irr3)+CHOOSE(E59,s_irr1,s_irr2,s_irr3))/2 | L59: =CHOOSE(F59,s_pos1,s_pos2,s_pos3,s_pos4) | M59: =w_irr*K59+w_pos*L59+w_vc*J59 | N59: =RANK(M59,$M$2:$M$64,0)
A60: SMCI | B60: Supermicro | C60: =價值鏈!A10 | D60: 伺服器組裝 | E60: 3 | F60: 4 | G60: 品牌伺服器第二梯隊；治理風險（AI半導體 候選母體 v0.2.2；市場位置由次產業內優先序 6 換算） | H60: [判斷] | I60: =價值鏈!F10 | J60: =價值鏈!G10 | K60: =(CHOOSE(I60,s_irr1,s_irr2,s_irr3)+CHOOSE(E60,s_irr1,s_irr2,s_irr3))/2 | L60: =CHOOSE(F60,s_pos1,s_pos2,s_pos3,s_pos4) | M60: =w_irr*K60+w_pos*L60+w_vc*J60 | N60: =RANK(M60,$M$2:$M$64,0)
A61: 3017 | B61: 奇鋐 | C61: =價值鏈!A9 | D61: 電源與散熱 | E61: 1 | F61: 2 | G61: AI 液冷冷板主要供應者（AI半導體 候選母體 v0.2.2；市場位置由次產業內優先序 2 換算） | H61: [判斷] | I61: =價值鏈!F9 | J61: =價值鏈!G9 | K61: =(CHOOSE(I61,s_irr1,s_irr2,s_irr3)+CHOOSE(E61,s_irr1,s_irr2,s_irr3))/2 | L61: =CHOOSE(F61,s_pos1,s_pos2,s_pos3,s_pos4) | M61: =w_irr*K61+w_pos*L61+w_vc*J61 | N61: =RANK(M61,$M$2:$M$64,0)
A62: 2301 | B62: 光寶 | C62: =價值鏈!A9 | D62: 電源與散熱 | E62: 2 | F62: 3 | G62: 伺服器電源第二大（AI半導體 候選母體 v0.2.2；市場位置由次產業內優先序 3 換算） | H62: [判斷] | I62: =價值鏈!F9 | J62: =價值鏈!G9 | K62: =(CHOOSE(I62,s_irr1,s_irr2,s_irr3)+CHOOSE(E62,s_irr1,s_irr2,s_irr3))/2 | L62: =CHOOSE(F62,s_pos1,s_pos2,s_pos3,s_pos4) | M62: =w_irr*K62+w_pos*L62+w_vc*J62 | N62: =RANK(M62,$M$2:$M$64,0)
A63: 3324 | B63: 雙鴻 | C63: =價值鏈!A9 | D63: 電源與散熱 | E63: 2 | F63: 3 | G63: 液冷主要廠之一（AI半導體 候選母體 v0.2.2；市場位置由次產業內優先序 4 換算） | H63: [判斷] | I63: =價值鏈!F9 | J63: =價值鏈!G9 | K63: =(CHOOSE(I63,s_irr1,s_irr2,s_irr3)+CHOOSE(E63,s_irr1,s_irr2,s_irr3))/2 | L63: =CHOOSE(F63,s_pos1,s_pos2,s_pos3,s_pos4) | M63: =w_irr*K63+w_pos*L63+w_vc*J63 | N63: =RANK(M63,$M$2:$M$64,0)
A64: 3653 | B64: 健策 | C64: =價值鏈!A9 | D64: 電源與散熱 | E64: 3 | F64: 4 | G64: 散熱元件（AI半導體 候選母體 v0.2.2；市場位置由次產業內優先序 6 換算） | H64: [判斷] | I64: =價值鏈!F9 | J64: =價值鏈!G9 | K64: =(CHOOSE(I64,s_irr1,s_irr2,s_irr3)+CHOOSE(E64,s_irr1,s_irr2,s_irr3))/2 | L64: =CHOOSE(F64,s_pos1,s_pos2,s_pos3,s_pos4) | M64: =w_irr*K64+w_pos*L64+w_vc*J64 | N64: =RANK(M64,$M$2:$M$64,0)

Sheet 價格
A1: 代號 | B1: 幣別 | C1: 模型內現價 | D1: 模型價日期 | E1: 模型價來源 | F1: 外部收盤（非半導體模型） | G1: 收盤來源 | H1: 採用價
A2: NVDA | B2: USD | C2: 210.96 | D2: 2026-10-23 | E2: nvidia/dist/20261025_NVIDIA模型_v0.2.xlsx Val!B57 | H2: =C2
A3: AVGO | B3: USD | C3: 321.68 | D3: 2026-10-23 | E3: avgo/dist/20261025_Broadcom模型_v0.2.xlsx Val!B57 | H3: =C3
A4: 000660 | B4: KRW | C4: 1277000 | D4: 2026-10-23 | E4: skhynix/dist/20261025_SK海力士模型_v0.5.xlsx In!E6 | H4: =C4
A5: 005930 | B5: KRW | C5: 215500 | D5: 2026-10-23 | E5: samsung/dist/20261025_三星電子模型_v0.3.xlsx In!E6 | H5: =C5
A6: MU | B6: USD | C6: 877.55 | D6: 2026-10-23 | E6: micron/dist/20261025_美光模型_v0.4.xlsx In!E5 | H6: =C6
A7: 2330 | B7: TWD | C7: 2385 | D7: 2026-10-22 | E7: tsmc/dist/20261025_台積電模型_v0.3.xlsx In!E135 | H7: =C7
A8: ANET | B8: USD | C8: 172.37 | D8: 2026-10-23 | E8: arista/dist/20261025_Arista模型_v0.2.xlsx Val!B57 | H8: =C8
A9: 300308 | B9: CNY | C9: 612.63 | D9: 2026-10-23 | E9: innolight/dist/20261025_中際旭創模型_v0.2.xlsx Val!B53 | H9: =C9
A10: 2308 | B10: TWD | C10: 1605 | D10: 2026-10-23 | E10: delta/dist/20261025_台達電模型_v0.2.xlsx Val!B6 | H10: =C10
A11: 2382 | B11: TWD | C11: 322 | D11: 2026-10-22 | E11: quanta/dist/20261025_廣達模型_v0.2.xlsx Val!B6 | H11: =C11
A12: 4062 | B12: JPY | C12: 8512 | D12: 2026-10-23 | E12: ibiden/dist/20261025_Ibiden模型_v0.2.xlsx Val!B6 | H12: =C12
A13: 6857 | B13: JPY | C13: 32340 | D13: 2026-10-23 | E13: advantest/dist/20261025_Advantest模型_v0.3.xlsx Val!B92 | H13: =C13
A14: 6146 | B14: JPY | C14: 49290 | D14: 2026-10-23 | E14: disco/dist/20261025_Disco模型_v0.2.1.xlsx Val!B53 | H14: =C14
A15: MSFT | B15: USD | C15: 529.76 | D15: 2026-10-07 | E15: microsoft/dist/20261025_Microsoft收支模型_v0_2_2.xlsx 輸入與假設!C345 | F15: 524.51 | G15: 2026-10-23｜stockscan；bullfincher | H15: =IF(ISNUMBER(F15),F15,C15)
A16: AMZN | B16: USD | C16: 259.92 | D16: 2026-10-07 | E16: amazon/dist/20261025_Amazon收支模型_v0_2_2.xlsx 輸入與假設!C328 | F16: 248 | G16: 2026-10-23｜stockanalysis；stockscan | H16: =IF(ISNUMBER(F16),F16,C16)
A17: GOOGL | B17: USD | C17: 350.5 | D17: 2026-10-07 | E17: alphabet/dist/20261025_Alphabet收支模型_v0_2_2.xlsx 輸入與假設!C374 | F17: 320.21 | G17: 2026-10-23｜stockscan；bullfincher | H17: =IF(ISNUMBER(F17),F17,C17)
A18: ORCL | B18: USD | C18: 129.13 | D18: 2026-10-21 | E18: oracle/dist/20261022_Oracle收支模型_v0_3_1.xlsx 輸入與假設!C175 | F18: 126.16 | G18: 2026-10-23｜stockanalysis；stockscan | H18: =IF(ISNUMBER(F18),F18,C18)
A19: CRWV | B19: USD | C19: 90.13 | D19: 2026-09-24 | E19: coreweave/dist/20261021_CoreWeave收支模型_v4_12.xlsx 輸入與假設!C221 | F19: 54.23 | G19: 2026-10-23｜stockscan；digrin | H19: =IF(ISNUMBER(F19),F19,C19)
A20: NBIS | B20: USD | C20: 249.87 | D20: 2026-10-06 | E20: nebius/dist/20261022_Nebius收支模型_v0_5.xlsx 輸入與假設!C125 | F20: 158.74 | G20: 2026-10-23｜stockscan（digrin 158.64） | H20: =IF(ISNUMBER(F20),F20,C20)
A21: WYFI | B21: USD | C21: 16.83 | D21: 2026-10-07 | E21: whitefiber/dist/20261022_WhiteFiber收支模型_v0_2.xlsx 輸入與假設!C228 | F21: 9.98 | G21: 2026-10-23｜stockscan；digrin | H21: =IF(ISNUMBER(F21),F21,C21)
A22: 00100 | B22: HKD | C22: 171.9 | D22: 2026-10-21 | E22: minimax/dist/20261022_MiniMax收支模型_v0_2.xlsx Valuation!D7 | F22: 187.6 | G22: 2026-10-23｜etnet；老虎 | H22: =IF(ISNUMBER(F22),F22,C22)
A23: 02513 | B23: HKD | F23: 499 | G23: 2026-10-23｜老虎 | H23: =IF(ISNUMBER(F23),F23,C23)
A24: OpenAI | B24: USD | H24: 未上市
A25: Anthropic | B25: USD | H25: 未上市
A26: AMD | B26: USD | C26: 516.79 | D26: 2026-10-23 | E26: amd/dist/20261025_AMD模型_v0.2.1.xlsx Val!B67 | H26: =C26
A27: 2454 | B27: TWD | C27: 4010 | D27: 2026-10-22 | E27: mediatek/dist/20261025_聯發科模型_v0.1.xlsx Val!B53 | H27: =C27
A28: MRVL | B28: USD | C28: 228.51 | D28: 2026-10-23 | E28: mrvl/dist/20261025_邁威爾模型_v0.2.xlsx Val!B68 | H28: =C28
A29: 3661 | B29: TWD | C29: 3495 | D29: 2026-10-22 | E29: alchip/dist/20261025_世芯-KY模型_v0.1.xlsx Val!B53 | H29: =C29
A30: 3443 | B30: TWD | C30: 7585 | D30: 2026-10-22 | E30: guc/dist/20261025_創意模型_v0.1.xlsx Val!B53 | H30: =C30
A31: 285A | B31: JPY | C31: 12755 | D31: 2026-10-23 | E31: kioxia/dist/20261025_Kioxia模型_v0.1.xlsx Val!B82 | H31: =C31
A32: SNDK | B32: USD | C32: 1238.03 | D32: 2026-10-23 | E32: sndk/dist/20261025_SanDisk模型_v0.1.xlsx Val!B82 | H32: =C32
A33: COHR | B33: USD | C33: 209.17 | D33: 2026-10-23 | E33: cohr/dist/20261025_Coherent模型_v0.2.xlsx Val!B64 | H33: =C33
A34: LITE | B34: USD | C34: 756.17 | D34: 2026-10-23 | E34: lite/dist/20261025_Lumentum模型_v0.2.xlsx Val!B63 | H34: =C34
A35: 300502 | B35: CNY | C35: 261 | D35: 2026-10-23 | E35: eoptolink/dist/20261025_新易盛模型_v0.2.xlsx Val!B63 | H35: =C35
A36: 2345 | B36: TWD | C36: 1775 | D36: 2026-10-22 | E36: accton/dist/20261025_智邦模型_v0.2.xlsx Val!B66 | H36: =C36
A37: FN | B37: USD | C37: 314.94 | D37: 2026-10-23 | E37: fabrinet/dist/20261025_Fabrinet模型_v0.1.xlsx Val!B64 | H37: =C37
... A64: 3653 | B64: TWD | C64: 6070 | D64: 2026-10-22 | E64: jentech/dist/20261025_健策模型_v0.1.xlsx Val!B56 | H64: =C64

Sheet 估值
A1: 代號 | B1: 公司 | C1: 層級 | D1: 次產業 | E1: 方法 | F1: 中心候選 1 | G1: 中心候選 1 來源 | H1: 中心候選 2 | I1: 中心候選 2 來源 | J1: 悲觀情境候選 1 | K1: 悲觀情境候選 1 來源 | L1: 悲觀情境候選 2 | M1: 悲觀情境候選 2 來源 | N1: 採用價 | O1: 中心價 | P1: 悲觀情境價 | Q1: 中心空間 | R1: 悲觀情境空間 | S1: 分級 | T1: 對照口徑空間 | U1: 對照口徑 | V1: 現價 ÷ 模型 FY2028 EPS（A／B／C） | W1: 註記 | X1: 輔助 1 | Y1: 輔助 2 | Z1: 模型價日以來漲跌 | AA1: 價格變動旗標 | AB1: 收支口徑 | AC1: 收支列（模型） | AD1: 收支序列 | AE1: 期間合計 | AF1: 最小值 | AG1: 收支來源 | AH1: 收支關卡 | AI1: 最終分級 | AJ1: 上檔空間級距 | AK1: 投資建議與上檔空間依據
A2: NVDA | B2: NVIDIA | C2: =價值鏈!A5 | D2: 運算 | E2: 加權目標價（DCF 50%＋Comparable 50%） | F2: 251.8803 | G2: nvidia/dist/20261025_NVIDIA模型_v0.2.xlsx Val!B40 | J2: 128.62269 | K2: nvidia/dist/20261025_NVIDIA模型_v0.2.xlsx Val!B47 | N2: =價格!H2 | O2: =MIN(F2,H2) | P2: =MIN(J2,L2) | Q2: 0.19397183 | R2: =P2/N2-1 | S2: =IF(Q2>0.5,"強力買進",IF(Q2>0.25,"買進",IF(Q2>=-0.25,"中立",IF(Q2>=-0.5,"放空","強力放空")))) | T2: =467.571184194614/N2-1 | U2: 舊法：規則值情境加權價（參考，Val!B170） | V2: 14.3 ／ 14.3 ／ 14.3 | W2: DCF 目標價 235.0（Val!B23）；Comparable 目標價 268.7（Val!B41）；市場共識目標價 328.9（Val!B42，外部、僅供對照）；價格帶 C～A 情境 DCF 128.6～313.1 | Z2: =IF(ISNUMBER(價格!C2),價格!H2/價格!C2-1,"") | AA2: =IF(Z2="","",IF(ABS(Z2)>0.2,"模型尚未反映期間變化","")) | AB2: 淨利 | AC2: PL 頁各情境模型年度淨利（不含實績） | AD2: 12 個情境年度淨利（不含實績），全部為正 | AE2: 4314.7715 | AF2: 219.76039 | AG2: [Derived] nvidia/dist/20261025_NVIDIA模型_v0.2.xlsx PL!D12…PL!G292 | AH2: =IF(AB2="淨利",IF(AF2>0,"通過（淨利）","不通過"),IF(AE2<0,"不通過","通過（現金流）")) | AI2: =IF(S2="未上市","未上市",IF(AH2="不通過","收支不足",S2)) | AJ2: =IF(Q2>0.5,"大於 50%",IF(Q2>0.25,"25%–50%",IF(Q2>=0,"0%–25%",IF(Q2>=-0.25,"0%～−25%",IF(Q2>=-0.5,"−25%～−50%","小於 −50%"))))) | AK2: 上檔空間 nvidia/dist/20261025_NVIDIA模型_v0.2.xlsx Val!B43；投資建議：模型尚未補列，依 AI半導體 固定規則自算；級距：模型尚未補列，依 AI半導體 固定規則自算
A3: AVGO | B3: Broadcom | C3: =價值鏈!A5 | D3: 運算 | E3: 加權目標價（DCF 50%＋Comparable 50%） | F3: 340.64325 | G3: avgo/dist/20261025_Broadcom模型_v0.2.xlsx Val!B40 | J3: 221.91455 | K3: avgo/dist/20261025_Broadcom模型_v0.2.xlsx Val!B47 | N3: =價格!H3 | O3: =MIN(F3,H3) | P3: =MIN(J3,L3) | Q3: 0.058950661 | R3: =P3/N3-1 | S3: =IF(Q3>0.5,"強力買進",IF(Q3>0.25,"買進",IF(Q3>=-0.25,"中立",IF(Q3>=-0.5,"放空","強力放空")))) | T3: =647.367676593253/N3-1 | U3: 舊法：規則值情境加權價（參考，Val!B104） | V3: 15.3 ／ 18.0 ／ 21.7 | W3: DCF 目標價 324.6（Val!B23）；Comparable 目標價 356.7（Val!B41）；市場共識目標價 529.1（Val!B42，外部、僅供對照）；價格帶 C～A 情境 DCF 221.9～394.3 | Z3: =IF(ISNUMBER(價格!C3),價格!H3/價格!C3-1,"") | AA3: =IF(Z3="","",IF(ABS(Z3)>0.2,"模型尚未反映期間變化","")) | AB3: 淨利 | AC3: PL 頁各情境模型年度淨利（不含實績） | AD3: 8 個情境年度淨利（不含實績），全部為正 | AE3: 711.22804 | AF3: 57.42012 | AG3: [Derived] avgo/dist/20261025_Broadcom模型_v0.2.xlsx PL!D13…PL!G39 | AH3: =IF(AB3="淨利",IF(AF3>0,"通過（淨利）","不通過"),IF(AE3<0,"不通過","通過（現金流）")) | AI3: =IF(S3="未上市","未上市",IF(AH3="不通過","收支不足",S3)) | AJ3: =IF(Q3>0.5,"大於 50%",IF(Q3>0.25,"25%–50%",IF(Q3>=0,"0%–25%",IF(Q3>=-0.25,"0%～−25%",IF(Q3>=-0.5,"−25%～−50%","小於 −50%"))))) | AK3: 上檔空間 avgo/dist/20261025_Broadcom模型_v0.2.xlsx Val!B43；投資建議：模型尚未補列，依 AI半導體 固定規則自算；級距：模型尚未補列，依 AI半導體 固定規則自算
A4: 000660 | B4: SK 海力士 | C4: =價值鏈!A6 | D4: 記憶體 | E4: 加權目標價（DCF 50%＋Comparable 50%） | F4: 3087845.4 | G4: skhynix/dist/20261025_SK海力士模型_v0.5.xlsx Val!B161 | J4: 1308904.1 | K4: skhynix/dist/20261025_SK海力士模型_v0.5.xlsx Val!D145 | N4: =價格!H4 | O4: =MIN(F4,H4) | P4: =MIN(J4,L4) | Q4: 1.4180465 | R4: =P4/N4-1 | S4: =IF(Q4>0.5,"強力買進",IF(Q4>0.25,"買進",IF(Q4>=-0.25,"中立",IF(Q4>=-0.5,"放空","強力放空")))) | T4: =1392208.55280262/N4-1 | U4: 舊法：規則值情境加權價（參考，Val!B176） | W4: DCF 目標價 3,709,129.8（Val!B146）；Comparable 目標價 2,466,561.0（Val!B162）；市場共識目標價 3,096,288.0（Val!B163，外部、僅供對照）；價格帶 C～A 情境 DCF 1,308,904.1～6,513,978.2 | Z4: =IF(ISNUMBER(價格!C4),價格!H4/價格!C4-1,"") | AA4: =IF(Z4="","",IF(ABS(Z4)>0.2,"模型尚未反映期間變化","")) | AB4: 現金流 | AC4: 自由現金流（淨利＋折舊 − 資本支出） | AD4: 2026（基準） 232.9、2027 A 301.3、2028 A 334.4、2029 A 372.3、2027 B 293.3、2028 B 151.6、2029 B 188.0、2027 C 293.3、2028 C 77.1、2029 C 63.7 | AE4: 2307.9577 | AF4: 63.73385 | AG4: [Derived] skhynix/dist/20261025_SK海力士模型_v0.5.xlsx Y!C22…Y!L22 | AH4: =IF(AB4="淨利",IF(AF4>0,"通過（淨利）","不通過"),IF(AE4<0,"不通過","通過（現金流）")) | AI4: =IF(S4="未上市","未上市",IF(AH4="不通過","收支不足",S4)) | AJ4: =IF(Q4>0.5,"大於 50%",IF(Q4>0.25,"25%–50%",IF(Q4>=0,"0%–25%",IF(Q4>=-0.25,"0%～−25%",IF(Q4>=-0.5,"−25%～−50%","小於 −50%"))))) | AK4: 上檔空間 skhynix/dist/20261025_SK海力士模型_v0.5.xlsx Val!B164；投資建議：模型尚未補列，依 AI半導體 固定規則自算；級距：模型尚未補列，依 AI半導體 固定規則自算
A5: 005930 | B5: 三星電子 | C5: =價值鏈!A6 | D5: 記憶體 | E5: 加權目標價（DCF 50%＋Comparable 50%） | F5: 477143.17 | G5: samsung/dist/20261025_三星電子模型_v0.3.xlsx Val!B161 | J5: 218882.5 | K5: samsung/dist/20261025_三星電子模型_v0.3.xlsx Val!D145 | N5: =價格!H5 | O5: =MIN(F5,H5) | P5: =MIN(J5,L5) | Q5: 1.2141215 | R5: =P5/N5-1 | S5: =IF(Q5>0.5,"強力買進",IF(Q5>0.25,"買進",IF(Q5>=-0.25,"中立",IF(Q5>=-0.5,"放空","強力放空")))) | T5: =255831.994790815/N5-1 | U5: 舊法：規則值情境加權價（參考，Val!B176） | W5: DCF 目標價 486,542.2（Val!B146）；Comparable 目標價 467,744.1（Val!B162）；市場共識目標價 478,906.0（Val!B163，外部、僅供對照）；價格帶 C～A 情境 DCF 218,882.5～818,535.4 | Z5: =IF(ISNUMBER(價格!C5),價格!H5/價格!C5-1,"") | AA5: =IF(Z5="","",IF(ABS(Z5)>0.2,"模型尚未反映期間變化","")) | AB5: 現金流 | AC5: 自由現金流（淨利＋折舊 − 資本支出） | AD5: 2026（基準） 291.2、2027 A 506.0、2028 A 561.3、2029 A 611.6、2027 B 492.5、2028 B 274.2、2029 B 324.1、2027 C 492.5、2028 C 165.3、2029 C 138.4 | AE5: 3857.2674 | AF5: 138.43 | AG5: [Derived] samsung/dist/20261025_三星電子模型_v0.3.xlsx Y!C22…Y!L22 | AH5: =IF(AB5="淨利",IF(AF5>0,"通過（淨利）","不通過"),IF(AE5<0,"不通過","通過（現金流）")) | AI5: =IF(S5="未上市","未上市",IF(AH5="不通過","收支不足",S5)) | AJ5: =IF(Q5>0.5,"大於 50%",IF(Q5>0.25,"25%–50%",IF(Q5>=0,"0%–25%",IF(Q5>=-0.25,"0%～−25%",IF(Q5>=-0.5,"−25%～−50%","小於 −50%"))))) | AK5: 上檔空間 samsung/dist/20261025_三星電子模型_v0.3.xlsx Val!B164；投資建議：模型尚未補列，依 AI半導體 固定規則自算；級距：模型尚未補列，依 AI半導體 固定規則自算
A6: MU | B6: 美光 | C6: =價值鏈!A6 | D6: 記憶體 | E6: 加權目標價（DCF 50%＋Comparable 50%） | F6: 684.08947 | G6: micron/dist/20261025_美光模型_v0.4.xlsx Val!B208 | J6: 321.89649 | K6: micron/dist/20261025_美光模型_v0.4.xlsx Val!D192 | N6: =價格!H6 | O6: =MIN(F6,H6) | P6: =MIN(J6,L6) | Q6: -0.22045528 | R6: =P6/N6-1 | S6: =IF(Q6>0.5,"強力買進",IF(Q6>0.25,"買進",IF(Q6>=-0.25,"中立",IF(Q6>=-0.5,"放空","強力放空")))) | T6: =348.754265504643/N6-1 | U6: 舊法：規則值情境加權價（參考，Val!B223） | W6: DCF 目標價 932.6（Val!B193）；Comparable 目標價 435.6（Val!B209）；市場共識目標價 1,560.6（Val!B210，外部、僅供對照）；價格帶 C～A 情境 DCF 321.9～1,714.0 | Z6: =IF(ISNUMBER(價格!C6),價格!H6/價格!C6-1,"") | AA6: =IF(Z6="","",IF(ABS(Z6)>0.2,"模型尚未反映期間變化","")) | AB6: 現金流 | AC6: 自由現金流（淨利＋折舊 − 資本支出） | AD6: FY2026（基準） 67.1、FY2027 A 152.2、FY2028 A 172.3、FY2029 A 191.8、FY2027 B 154.2、FY2028 B 87.7、FY2029 B 77.3、FY2027 C 154.2、FY2028 C 59.6、FY2029 C 8.8 | AE6: 1125.2991 | AF6: 8.8007654 | AG6: [Derived] micron/dist/20261025_美光模型_v0.4.xlsx Y!C22…Y!L22 | AH6: =IF(AB6="淨利",IF(AF6>0,"通過（淨利）","不通過"),IF(AE6<0,"不通過","通過（現金流）")) | AI6: =IF(S6="未上市","未上市",IF(AH6="不通過","收支不足",S6)) | AJ6: =IF(Q6>0.5,"大於 50%",IF(Q6>0.25,"25%–50%",IF(Q6>=0,"0%–25%",IF(Q6>=-0.25,"0%～−25%",IF(Q6>=-0.5,"−25%～−50%","小於 −50%"))))) | AK6: 上檔空間 micron/dist/20261025_美光模型_v0.4.xlsx Val!B211；投資建議：模型尚未補列，依 AI半導體 固定規則自算；級距：模型尚未補列，依 AI半導體 固定規則自算
A7: 2330 | B7: 台積電 | C7: =價值鏈!A11 | D7: 代工與封測 | E7: 加權目標價（DCF 50%＋Comparable 50%） | F7: 2446.0233 | G7: tsmc/dist/20261025_台積電模型_v0.3.xlsx Val!B94 | J7: 1495.889 | K7: tsmc/dist/20261025_台積電模型_v0.3.xlsx Val!D78 | N7: =價格!H7 | O7: =MIN(F7,H7) | P7: =MIN(J7,L7) | Q7: 0.025586289 | R7: =P7/N7-1 | S7: =IF(Q7>0.5,"強力買進",IF(Q7>0.25,"買進",IF(Q7>=-0.25,"中立",IF(Q7>=-0.5,"放空","強力放空")))) | T7: =3022.97680876707/N7-1 | U7: 舊法：規則值情境加權價（參考，Val!B107） | W7: DCF 目標價 2,150.2（Val!B79）；Comparable 目標價 2,741.9（Val!B95）；市場共識目標價 3,390.4（Val!B96，外部、僅供對照）；價格帶 C～A 情境 DCF 1,495.9～2,769.1 | Z7: =IF(ISNUMBER(價格!C7),價格!H7/價格!C7-1,"") | AA7: =IF(Z7="","",IF(ABS(Z7)>0.2,"模型尚未反映期間變化","")) | AB7: 淨利 | AC7: PL 頁各情境模型年度淨利（不含實績） | AD7: 19 個情境年度淨利（不含實績），全部為正 | AE7: 2206.9659 | AF7: 84.633409 | AG7: [Derived] tsmc/dist/20261025_台積電模型_v0.3.xlsx PL!B12…PL!T12 | AH7: =IF(AB7="淨利",IF(AF7>0,"通過（淨利）","不通過"),IF(AE7<0,"不通過","通過（現金流）")) | AI7: =IF(S7="未上市","未上市",IF(AH7="不通過","收支不足",S7)) | AJ7: =IF(Q7>0.5,"大於 50%",IF(Q7>0.25,"25%–50%",IF(Q7>=0,"0%–25%",IF(Q7>=-0.25,"0%～−25%",IF(Q7>=-0.5,"−25%～−50%","小於 −50%"))))) | AK7: 上檔空間 tsmc/dist/20261025_台積電模型_v0.3.xlsx Val!B97；投資建議：模型尚未補列，依 AI半導體 固定規則自算；級距：模型尚未補列，依 AI半導體 固定規則自算
A8: ANET | B8: Arista | C8: =價值鏈!A7 | D8: 網通 | E8: 加權目標價（DCF 50%＋Comparable 50%） | F8: 99.463038 | G8: arista/dist/20261025_Arista模型_v0.2.xlsx Val!B40 | J8: 66.550487 | K8: arista/dist/20261025_Arista模型_v0.2.xlsx Val!B47 | N8: =價格!H8 | O8: =MIN(F8,H8) | P8: =MIN(J8,L8) | Q8: -0.42296781 | R8: =P8/N8-1 | S8: =IF(Q8>0.5,"強力買進",IF(Q8>0.25,"買進",IF(Q8>=-0.25,"中立",IF(Q8>=-0.5,"放空","強力放空")))) | T8: =174.075889279442/N8-1 | U8: 舊法：規則值情境加權價（參考，Val!B137） | V8: 28.8 ／ 31.3 ／ 34.7 | W8: DCF 目標價 87.2（Val!B23）；Comparable 目標價 111.7（Val!B41）；市場共識目標價 243.6（Val!B42，外部、僅供對照）；價格帶 C～A 情境 DCF 66.6～101.9 | Z8: =IF(ISNUMBER(價格!C8),價格!H8/價格!C8-1,"") | AA8: =IF(Z8="","",IF(ABS(Z8)>0.2,"模型尚未反映期間變化","")) | AB8: 淨利 | AC8: PL 頁各情境模型年度淨利（不含實績） | AD8: 8 個情境年度淨利（不含實績），全部為正 | AE8: 56.290329 | AF8: 5.224907 | AG8: [Derived] arista/dist/20261025_Arista模型_v0.2.xlsx PL!D12…PL!G36 | AH8: =IF(AB8="淨利",IF(AF8>0,"通過（淨利）","不通過"),IF(AE8<0,"不通過","通過（現金流）")) | AI8: =IF(S8="未上市","未上市",IF(AH8="不通過","收支不足",S8)) | AJ8: =IF(Q8>0.5,"大於 50%",IF(Q8>0.25,"25%–50%",IF(Q8>=0,"0%–25%",IF(Q8>=-0.25,"0%～−25%",IF(Q8>=-0.5,"−25%～−50%","小於 −50%"))))) | AK8: 上檔空間 arista/dist/20261025_Arista模型_v0.2.xlsx Val!B43；投資建議：模型尚未補列，依 AI半導體 固定規則自算；級距：模型尚未補列，依 AI半導體 固定規則自算
A9: 300308 | B9: 中際旭創 | C9: =價值鏈!A7 | D9: 網通 | E9: 加權目標價（DCF 50%＋Comparable 50%） | F9: 1355.2557 | G9: innolight/dist/20261025_中際旭創模型_v0.2.xlsx Val!B39 | J9: 498.17609 | K9: innolight/dist/20261025_中際旭創模型_v0.2.xlsx Val!D23 | N9: =價格!H9 | O9: =MIN(F9,H9) | P9: =MIN(J9,L9) | Q9: 1.2121928 | R9: =P9/N9-1 | S9: =IF(Q9>0.5,"強力買進",IF(Q9>0.25,"買進",IF(Q9>=-0.25,"中立",IF(Q9>=-0.5,"放空","強力放空")))) | T9: =2265.72535634618/N9-1 | U9: 舊法：規則值情境加權價（參考，Val!B133） | V9: 12.3 ／ 15.5 ／ 21.0 | W9: DCF 目標價 831.5（Val!B24）；Comparable 目標價 1,879.1（Val!B40）；市場共識目標價 1,321.0（Val!B41，外部、僅供對照）；價格帶 C～A 情境 DCF 498.2～1,049.4 | Z9: =IF(ISNUMBER(價格!C9),價格!H9/價格!C9-1,"") | AA9: =IF(Z9="","",IF(ABS(Z9)>0.2,"模型尚未反映期間變化","")) | AB9: 淨利 | AC9: PL 頁各情境模型年度淨利（不含實績） | AD9: 17 個情境年度淨利（不含實績），全部為正 | AE9: 1034.1628 | AF9: 31.828119 | AG9: [Derived] innolight/dist/20261025_中際旭創模型_v0.2.xlsx PL!D12…PL!J36 | AH9: =IF(AB9="淨利",IF(AF9>0,"通過（淨利）","不通過"),IF(AE9<0,"不通過","通過（現金流）")) | AI9: =IF(S9="未上市","未上市",IF(AH9="不通過","收支不足",S9)) | AJ9: =IF(Q9>0.5,"大於 50%",IF(Q9>0.25,"25%–50%",IF(Q9>=0,"0%–25%",IF(Q9>=-0.25,"0%～−25%",IF(Q9>=-0.5,"−25%～−50%","小於 −50%"))))) | AK9: 上檔空間 innolight/dist/20261025_中際旭創模型_v0.2.xlsx Val!B42；投資建議：模型尚未補列，依 AI半導體 固定規則自算；級距：模型尚未補列，依 AI半導體 固定規則自算
A10: 2308 | B10: 台達電 | C10: =價值鏈!A9 | D10: 電源與散熱 | E10: 加權目標價（DCF 50%＋Comparable 50%） | F10: 1213.7702 | G10: delta/dist/20261025_台達電模型_v0.2.xlsx Val!B119 | J10: 639.32948 | K10: delta/dist/20261025_台達電模型_v0.2.xlsx Val!D104 | N10: =價格!H10 | O10: =MIN(F10,H10) | P10: =MIN(J10,L10) | Q10: -0.24375687 | R10: =P10/N10-1 | S10: =IF(Q10>0.5,"強力買進",IF(Q10>0.25,"買進",IF(Q10>=-0.25,"中立",IF(Q10>=-0.5,"放空","強力放空")))) | T10: =1360.0134167175/N10-1 | U10: 舊法：規則值情境加權價（參考，Val!B42） | V10: 20.8 ／ 24.5 ／ 31.8 | W10: DCF 目標價 999.1（Val!B105）；Comparable 目標價 1,428.4（Val!B120）；市場共識目標價 2,502.4（Val!B121，外部、僅供對照）；價格帶 C～A 情境 DCF 639.3～1,234.7 | Z10: =IF(ISNUMBER(價格!C10),價格!H10/價格!C10-1,"") | AA10: =IF(Z10="","",IF(ABS(Z10)>0.2,"模型尚未反映期間變化","")) | AB10: 淨利 | AC10: PL 頁各情境模型年度淨利（不含實績） | AD10: 8 個情境年度淨利（不含實績），全部為正 | AE10: 1331.0311 | AF10: 98.429236 | AG10: [Derived] delta/dist/20261025_台達電模型_v0.2.xlsx PL!D13…PL!G39 | AH10: =IF(AB10="淨利",IF(AF10>0,"通過（淨利）","不通過"),IF(AE10<0,"不通過","通過（現金流）")) | AI10: =IF(S10="未上市","未上市",IF(AH10="不通過","收支不足",S10)) | AJ10: =IF(Q10>0.5,"大於 50%",IF(Q10>0.25,"25%–50%",IF(Q10>=0,"0%–25%",IF(Q10>=-0.25,"0%～−25%",IF(Q10>=-0.5,"−25%～−50%","小於 −50%"))))) | AK10: 上檔空間 delta/dist/20261025_台達電模型_v0.2.xlsx Val!B122；投資建議：模型尚未補列，依 AI半導體 固定規則自算；級距：模型尚未補列，依 AI半導體 固定規則自算
A11: 2382 | B11: 廣達 | C11: =價值鏈!A10 | D11: 伺服器組裝 | E11: 加權目標價（DCF 50%＋Comparable 50%） | F11: 566.56229 | G11: quanta/dist/20261025_廣達模型_v0.2.xlsx Val!B120 | J11: 404.06783 | K11: quanta/dist/20261025_廣達模型_v0.2.xlsx Val!D104 | N11: =價格!H11 | O11: =MIN(F11,H11) | P11: =MIN(J11,L11) | Q11: 0.75951022 | R11: =P11/N11-1 | S11: =IF(Q11>0.5,"強力買進",IF(Q11>0.25,"買進",IF(Q11>=-0.25,"中立",IF(Q11>=-0.5,"放空","強力放空")))) | T11: =490.548184039647/N11-1 | U11: 舊法：規則值情境加權價（參考，Val!B42） | V11: 6.2 ／ 7.7 ／ 10.2 | W11: DCF 目標價 644.3（Val!B105）；Comparable 目標價 488.9（Val!B121）；市場共識目標價 427.8（Val!B122，外部、僅供對照）；價格帶 C～A 情境 DCF 404.1～808.7 | Z11: =IF(ISNUMBER(價格!C11),價格!H11/價格!C11-1,"") | AA11: =IF(Z11="","",IF(ABS(Z11)>0.2,"模型尚未反映期間變化","")) | AB11: 淨利 | AC11: PL 頁各情境模型年度淨利（不含實績） | AD11: 8 個情境年度淨利（不含實績），全部為正 | AE11: 1294.0293 | AF11: 110.71367 | AG11: [Derived] quanta/dist/20261025_廣達模型_v0.2.xlsx PL!D13…PL!G39 | AH11: =IF(AB11="淨利",IF(AF11>0,"通過（淨利）","不通過"),IF(AE11<0,"不通過","通過（現金流）")) | AI11: =IF(S11="未上市","未上市",IF(AH11="不通過","收支不足",S11)) | AJ11: =IF(Q11>0.5,"大於 50%",IF(Q11>0.25,"25%–50%",IF(Q11>=0,"0%–25%",IF(Q11>=-0.25,"0%～−25%",IF(Q11>=-0.5,"−25%～−50%","小於 −50%"))))) | AK11: 上檔空間 quanta/dist/20261025_廣達模型_v0.2.xlsx Val!B123；投資建議：模型尚未補列，依 AI半導體 固定規則自算；級距：模型尚未補列，依 AI半導體 固定規則自算
A12: 4062 | B12: Ibiden | C12: =價值鏈!A8 | D12: 載板與 PCB | E12: 加權目標價（DCF 50%＋Comparable 50%） | F12: 5236.2411 | G12: ibiden/dist/20261025_Ibiden模型_v0.2.xlsx Val!B96 | J12: 1293.7578 | K12: ibiden/dist/20261025_Ibiden模型_v0.2.xlsx Val!D80 | N12: =價格!H12 | O12: =MIN(F12,H12) | P12: =MIN(J12,L12) | Q12: -0.38484009 | R12: =P12/N12-1 | S12: =IF(Q12>0.5,"強力買進",IF(Q12>0.25,"買進",IF(Q12>=-0.25,"中立",IF(Q12>=-0.5,"放空","強力放空")))) | T12: =9531.45203105499/N12-1 | U12: 舊法：規則值情境加權價（參考，Val!B38） | V12: 38.9 ／ 46.1 ／ 56.8 | W12: DCF 目標價 1,931.2（Val!B81）；Comparable 目標價 8,541.2（Val!B97）；市場共識目標價 12,432.4（Val!B98，外部、僅供對照）；價格帶 C～A 情境 DCF 1,293.8～2,378.3 | Z12: =IF(ISNUMBER(價格!C12),價格!H12/價格!C12-1,"") | AA12: =IF(Z12="","",IF(ABS(Z12)>0.2,"模型尚未反映期間變化","")) | AB12: 淨利 | AC12: PL 頁各情境模型年度淨利（不含實績） | AD12: 8 個情境年度淨利（不含實績），全部為正 | AE12: 854.69359 | AF12: 84 | AG12: [Derived] ibiden/dist/20261025_Ibiden模型_v0.2.xlsx PL!D11…PL!G33 | AH12: =IF(AB12="淨利",IF(AF12>0,"通過（淨利）","不通過"),IF(AE12<0,"不通過","通過（現金流）")) | AI12: =IF(S12="未上市","未上市",IF(AH12="不通過","收支不足",S12)) | AJ12: =IF(Q12>0.5,"大於 50%",IF(Q12>0.25,"25%–50%",IF(Q12>=0,"0%–25%",IF(Q12>=-0.25,"0%～−25%",IF(Q12>=-0.5,"−25%～−50%","小於 −50%"))))) | AK12: 上檔空間 ibiden/dist/20261025_Ibiden模型_v0.2.xlsx Val!B99；投資建議：模型尚未補列，依 AI半導體 固定規則自算；級距：模型尚未補列，依 AI半導體 固定規則自算
A13: 6857 | B13: Advantest | C13: =價值鏈!A12 | D13: 設備與材料 | E13: 加權目標價（DCF 50%＋Comparable 50%） | F13: 23221.592 | G13: advantest/dist/20261025_Advantest模型_v0.3.xlsx Val!B146 | J13: 7893.3663 | K13: advantest/dist/20261025_Advantest模型_v0.3.xlsx Val!D130 | N13: =價格!H13 | O13: =MIN(F13,H13) | P13: =MIN(J13,L13) | Q13: -0.28195449 | R13: =P13/N13-1 | S13: =IF(Q13>0.5,"強力買進",IF(Q13>0.25,"買進",IF(Q13>=-0.25,"中立",IF(Q13>=-0.5,"放空","強力放空")))) | T13: =24494.453736442/N13-1 | U13: 舊法：規則值情境加權價（參考，Val!B102） | W13: DCF 目標價 16,539.5（Val!B131）；Comparable 目標價 29,903.7（Val!B147）；市場共識目標價 42,686.0（Val!B148，外部、僅供對照）；價格帶 C～A 情境 DCF 7,893.4～23,027.5 | Z13: =IF(ISNUMBER(價格!C13),價格!H13/價格!C13-1,"") | AA13: =IF(Z13="","",IF(ABS(Z13)>0.2,"模型尚未反映期間變化","")) | AB13: 淨利 | AC13: PL 頁各情境模型年度淨利（不含實績） | AD13: 10 個情境年度淨利（不含實績），全部為正 | AE13: 7834.3455 | AF13: 574.3864 | AG13: [Derived] advantest/dist/20261025_Advantest模型_v0.3.xlsx PL!D12…PL!G34 | AH13: =IF(AB13="淨利",IF(AF13>0,"通過（淨利）","不通過"),IF(AE13<0,"不通過","通過（現金流）")) | AI13: =IF(S13="未上市","未上市",IF(AH13="不通過","收支不足",S13)) | AJ13: =IF(Q13>0.5,"大於 50%",IF(Q13>0.25,"25%–50%",IF(Q13>=0,"0%–25%",IF(Q13>=-0.25,"0%～−25%",IF(Q13>=-0.5,"−25%～−50%","小於 −50%"))))) | AK13: 上檔空間 advantest/dist/20261025_Advantest模型_v0.3.xlsx Val!B149；投資建議：模型尚未補列，依 AI半導體 固定規則自算；級距：模型尚未補列，依 AI半導體 固定規則自算
A14: 6146 | B14: Disco | C14: =價值鏈!A12 | D14: 設備與材料 | E14: 加權目標價（DCF 50%＋Comparable 50%） | F14: 40374.83 | G14: disco/dist/20261025_Disco模型_v0.2.1.xlsx Val!B107 | J14: 16343.609 | K14: disco/dist/20261025_Disco模型_v0.2.1.xlsx Val!D91 | N14: =價格!H14 | O14: =MIN(F14,H14) | P14: =MIN(J14,L14) | Q14: -0.18087177 | R14: =P14/N14-1 | S14: =IF(Q14>0.5,"強力買進",IF(Q14>0.25,"買進",IF(Q14>=-0.25,"中立",IF(Q14>=-0.5,"放空","強力放空")))) | T14: =45104.6418701108/N14-1 | U14: 舊法：規則值情境加權價（參考，Val!B63） | W14: DCF 目標價 22,991.0（Val!B92）；Comparable 目標價 57,758.6（Val!B108）；市場共識目標價 81,575.0（Val!B109，外部、僅供對照）；價格帶 C～A 情境 DCF 16,343.6～27,699.3 | Z14: =IF(ISNUMBER(價格!C14),價格!H14/價格!C14-1,"") | AA14: =IF(Z14="","",IF(ABS(Z14)>0.2,"模型尚未反映期間變化","")) | AB14: 淨利 | AC14: PL 頁各情境模型年度淨利（不含實績） | AD14: 10 個情境年度淨利（不含實績），全部為正 | AE14: 1803.9672 | AF14: 143.89119 | AG14: [Derived] disco/dist/20261025_Disco模型_v0.2.1.xlsx PL!D16…PL!G52 | AH14: =IF(AB14="淨利",IF(AF14>0,"通過（淨利）","不通過"),IF(AE14<0,"不通過","通過（現金流）")) | AI14: =IF(S14="未上市","未上市",IF(AH14="不通過","收支不足",S14)) | AJ14: =IF(Q14>0.5,"大於 50%",IF(Q14>0.25,"25%–50%",IF(Q14>=0,"0%–25%",IF(Q14>=-0.25,"0%～−25%",IF(Q14>=-0.5,"−25%～−50%","小於 −50%"))))) | AK14: 上檔空間 disco/dist/20261025_Disco模型_v0.2.1.xlsx Val!B110；投資建議：模型尚未補列，依 AI半導體 固定規則自算；級距：模型尚未補列，依 AI半導體 固定規則自算
A15: MSFT | B15: Microsoft | C15: =價值鏈!A3 | D15: AI 雲端平台 | E15: 模型加權目標價 | F15: 359.05884 | G15: microsoft/dist/20261025_Microsoft收支模型_v0_2_2.xlsx 摘要!C7 | J15: 359.05884 | K15: microsoft/dist/20261025_Microsoft收支模型_v0_2_2.xlsx 摘要!C7 | L15: 360.15761 | M15: microsoft/dist/20261025_Microsoft收支模型_v0_2_2.xlsx 摘要!C10 | N15: =價格!H15 | O15: =MIN(F15,H15) | P15: =MIN(J15,L15) | Q15: =O15/N15-1 | R15: =P15/N15-1 | S15: =IF(Q15>0.5,"強力買進",IF(Q15>0.25,"買進",IF(Q15>=-0.25,"中立",IF(Q15>=-0.5,"放空","強力放空")))) | W15: 模型點位 $359.1（模型日現價 $529.76）；情境區間 $360.2–$380.6，方法區間 $353.5–$359.1｜MAG 模型終值占 EV 逾 90%，評價口徑待 MAG v0.3 | Z15: =IF(ISNUMBER(價格!C15),價格!H15/價格!C15-1,"") | AA15: =IF(Z15="","",IF(ABS(Z15)>0.2,"模型尚未反映期間變化","")) | AB15: 現金流 | AC15: 營運缺口＋股利＋回購 | AD15: FY27 -7.8、FY28 27.7、FY29 70.2、FY30 76.7、FY31 11.2 | AE15: 178.04013 | AF15: -7.8317387 | AG15: [Derived] microsoft/dist/20261025_Microsoft收支模型_v0_2_2.xlsx 各期收支!C54＋C23＋C24…各期收支!G54＋G23＋G24 | AH15: =IF(AB15="淨利",IF(AF15>0,"通過（淨利）","不通過"),IF(AE15<0,"不通過","通過（現金流）")) | AI15: =IF(S15="未上市","未上市",IF(AH15="不通過","收支不足",S15)) | AJ15: =IF(Q15>0.5,"大於 50%",IF(Q15>0.25,"25%–50%",IF(Q15>=0,"0%–25%",IF(Q15>=-0.25,"0%～−25%",IF(Q15>=-0.5,"−25%～−50%","小於 −50%"))))) | AK15: 上檔空間＝模型加權目標價 microsoft/dist/20261025_Microsoft收支模型_v0_2_2.xlsx 摘要!C7 ÷ 外部收盤價 − 1，依本地圖五級規則自算（模型自身評等以模型日價計、級距不同，不採用；原值見模型摘要頁）
A16: AMZN | B16: Amazon | C16: =價值鏈!A3 | D16: AI 雲端平台 | E16: 模型加權目標價 | F16: 201.71431 | G16: amazon/dist/20261025_Amazon收支模型_v0_2_2.xlsx 摘要!C7 | J16: 201.71431 | K16: amazon/dist/20261025_Amazon收支模型_v0_2_2.xlsx 摘要!C7 | L16: 201.13616 | M16: amazon/dist/20261025_Amazon收支模型_v0_2_2.xlsx 摘要!C10 | N16: =價格!H16 | O16: =MIN(F16,H16) | P16: =MIN(J16,L16) | Q16: =O16/N16-1 | R16: =P16/N16-1 | S16: =IF(Q16>0.5,"強力買進",IF(Q16>0.25,"買進",IF(Q16>=-0.25,"中立",IF(Q16>=-0.5,"放空","強力放空")))) | W16: 模型點位 $201.7（模型日現價 $259.92）；情境區間 $201.1–$212.3，方法區間 $197.5–$201.7｜MAG 模型終值占 EV 逾 90%，評價口徑待 MAG v0.3 | Z16: =IF(ISNUMBER(價格!C16),價格!H16/價格!C16-1,"") | AA16: =IF(Z16="","",IF(ABS(Z16)>0.2,"模型尚未反映期間變化","")) | AB16: 現金流 | AC16: 營運缺口＋股利＋回購 | AD16: 2026 -122.8、2027 -71.8、2028 -34.2、2029 6.1、2030 -70.1 | AE16: -292.84158 | AF16: -122.81974 | AG16: [Derived] amazon/dist/20261025_Amazon收支模型_v0_2_2.xlsx 各期收支!C54＋C23＋C24…各期收支!G54＋G23＋G24 | AH16: =IF(AB16="淨利",IF(AF16>0,"通過（淨利）","不通過"),IF(AE16<0,"不通過","通過（現金流）")) | AI16: =IF(S16="未上市","未上市",IF(AH16="不通過","收支不足",S16)) | AJ16: =IF(Q16>0.5,"大於 50%",IF(Q16>0.25,"25%–50%",IF(Q16>=0,"0%–25%",IF(Q16>=-0.25,"0%～−25%",IF(Q16>=-0.5,"−25%～−50%","小於 −50%"))))) | AK16: 上檔空間＝模型加權目標價 amazon/dist/20261025_Amazon收支模型_v0_2_2.xlsx 摘要!C7 ÷ 外部收盤價 − 1，依本地圖五級規則自算（模型自身評等以模型日價計、級距不同，不採用；原值見模型摘要頁）
A17: GOOGL | B17: Alphabet | C17: =價值鏈!A3 | D17: AI 雲端平台 | E17: 模型加權目標價 | F17: 146.09287 | G17: alphabet/dist/20261025_Alphabet收支模型_v0_2_2.xlsx 摘要!C7 | J17: 146.09287 | K17: alphabet/dist/20261025_Alphabet收支模型_v0_2_2.xlsx 摘要!C7 | L17: 122.88912 | M17: alphabet/dist/20261025_Alphabet收支模型_v0_2_2.xlsx 摘要!C10 | N17: =價格!H17 | O17: =MIN(F17,H17) | P17: =MIN(J17,L17) | Q17: =O17/N17-1 | R17: =P17/N17-1 | S17: =IF(Q17>0.5,"強力買進",IF(Q17>0.25,"買進",IF(Q17>=-0.25,"中立",IF(Q17>=-0.5,"放空","強力放空")))) | W17: 模型點位 $146.1（模型日現價 $350.50）；情境區間 $122.9–$175.1，方法區間 $144.1–$146.1｜MAG 模型終值占 EV 逾 90%，評價口徑待 MAG v0.3 | Z17: =IF(ISNUMBER(價格!C17),價格!H17/價格!C17-1,"") | AA17: =IF(Z17="","",IF(ABS(Z17)>0.2,"模型尚未反映期間變化","")) | AB17: 現金流 | AC17: 營運缺口＋股利＋回購 | AD17: 2026 -62.0、2027 -11.4、2028 10.9、2029 23.1、2030 -67.6 | AE17: -106.92794 | AF17: -67.601689 | AG17: [Derived] alphabet/dist/20261025_Alphabet收支模型_v0_2_2.xlsx 各期收支!C54＋C23＋C24…各期收支!G54＋G23＋G24 | AH17: =IF(AB17="淨利",IF(AF17>0,"通過（淨利）","不通過"),IF(AE17<0,"不通過","通過（現金流）")) | AI17: =IF(S17="未上市","未上市",IF(AH17="不通過","收支不足",S17)) | AJ17: =IF(Q17>0.5,"大於 50%",IF(Q17>0.25,"25%–50%",IF(Q17>=0,"0%–25%",IF(Q17>=-0.25,"0%～−25%",IF(Q17>=-0.5,"−25%～−50%","小於 −50%"))))) | AK17: 上檔空間＝模型加權目標價 alphabet/dist/20261025_Alphabet收支模型_v0_2_2.xlsx 摘要!C7 ÷ 外部收盤價 − 1，依本地圖五級規則自算（模型自身評等以模型日價計、級距不同，不採用；原值見模型摘要頁）
A18: ORCL | B18: Oracle | C18: =價值鏈!A3 | D18: AI 雲端平台 | E18: 模型加權目標價 | F18: 84.239968 | G18: oracle/dist/20261022_Oracle收支模型_v0_3_1.xlsx 摘要!C7 | J18: 84.239968 | K18: oracle/dist/20261022_Oracle收支模型_v0_3_1.xlsx 摘要!C7 | L18: 77.414689 | M18: oracle/dist/20261022_Oracle收支模型_v0_3_1.xlsx 摘要!C10 | N18: =價格!H18 | O18: =MIN(F18,H18) | P18: =MIN(J18,L18) | Q18: =O18/N18-1 | R18: =P18/N18-1 | S18: =IF(Q18>0.5,"強力買進",IF(Q18>0.25,"買進",IF(Q18>=-0.25,"中立",IF(Q18>=-0.5,"放空","強力放空")))) | W18: 模型點位 $84.2（模型日現價 $129.13）；情境區間 $77.4–$91.9，方法區間 $78.7–$84.2 | Z18: =IF(ISNUMBER(價格!C18),價格!H18/價格!C18-1,"") | AA18: =IF(Z18="","",IF(ABS(Z18)>0.2,"模型尚未反映期間變化","")) | AB18: 現金流 | AC18: 營運缺口＋股利 | AD18: FY27 -25.8、FY28 -21.1、FY29 23.7、FY30 9.7、FY31 8.1 | AE18: -5.4310994 | AF18: -25.803183 | AG18: [Derived] oracle/dist/20261022_Oracle收支模型_v0_3_1.xlsx 各期收支!C50＋C23…各期收支!G50＋G23 | AH18: =IF(AB18="淨利",IF(AF18>0,"通過（淨利）","不通過"),IF(AE18<0,"不通過","通過（現金流）")) | AI18: =IF(S18="未上市","未上市",IF(AH18="不通過","收支不足",S18)) | AJ18: =IF(Q18>0.5,"大於 50%",IF(Q18>0.25,"25%–50%",IF(Q18>=0,"0%–25%",IF(Q18>=-0.25,"0%～−25%",IF(Q18>=-0.5,"−25%～−50%","小於 −50%"))))) | AK18: 上檔空間＝模型加權目標價 oracle/dist/20261022_Oracle收支模型_v0_3_1.xlsx 摘要!C7 ÷ 外部收盤價 − 1，依本地圖五級規則自算（模型自身評等以模型日價計、級距不同，不採用；原值見模型摘要頁）
A19: CRWV | B19: CoreWeave | C19: =價值鏈!A4 | D19: Neocloud（GPU 租賃） | E19: 模型加權目標價 | F19: 31.986519 | G19: coreweave/dist/20261021_CoreWeave收支模型_v4_12.xlsx 摘要!C7 | J19: 31.986519 | K19: coreweave/dist/20261021_CoreWeave收支模型_v4_12.xlsx 摘要!C7 | L19: 14.715809 | M19: coreweave/dist/20261021_CoreWeave收支模型_v4_12.xlsx 摘要!C10 | N19: =價格!H19 | O19: =MIN(F19,H19) | P19: =MIN(J19,L19) | Q19: =O19/N19-1 | R19: =P19/N19-1 | S19: =IF(Q19>0.5,"強力買進",IF(Q19>0.25,"買進",IF(Q19>=-0.25,"中立",IF(Q19>=-0.5,"放空","強力放空")))) | W19: 模型點位 $32.0（模型日現價 $90.13）；情境區間 $14.7–$42.7，方法區間 $19.7–$32.0 | Z19: =IF(ISNUMBER(價格!C19),價格!H19/價格!C19-1,"") | AA19: =IF(Z19="","",IF(ABS(Z19)>0.2,"模型尚未反映期間變化","")) | AB19: 現金流 | AC19: 營運缺口（不含融資、不含還本；無股利與回購） | AD19: FY26 -28.0、FY27 -30.4、FY28 -17.6、FY29 -13.4、FY30 -16.3 | AE19: -105.70556 | AF19: -30.399858 | AG19: [Derived] coreweave/dist/20261021_CoreWeave收支模型_v4_12.xlsx 各期收支!C39…各期收支!G39 | AH19: =IF(AB19="淨利",IF(AF19>0,"通過（淨利）","不通過"),IF(AE19<0,"不通過","通過（現金流）")) | AI19: =IF(S19="未上市","未上市",IF(AH19="不通過","收支不足",S19)) | AJ19: =IF(Q19>0.5,"大於 50%",IF(Q19>0.25,"25%–50%",IF(Q19>=0,"0%–25%",IF(Q19>=-0.25,"0%～−25%",IF(Q19>=-0.5,"−25%～−50%","小於 −50%"))))) | AK19: 上檔空間＝模型加權目標價 coreweave/dist/20261021_CoreWeave收支模型_v4_12.xlsx 摘要!C7 ÷ 外部收盤價 − 1，依本地圖五級規則自算（模型自身評等以模型日價計、級距不同，不採用；原值見模型摘要頁）
A20: NBIS | B20: Nebius | C20: =價值鏈!A4 | D20: Neocloud（GPU 租賃） | E20: 模型加權目標價 | F20: 21.379205 | G20: nebius/dist/20261022_Nebius收支模型_v0_5.xlsx 摘要!C7 | J20: 21.379205 | K20: nebius/dist/20261022_Nebius收支模型_v0_5.xlsx 摘要!C7 | L20: 19.431647 | M20: nebius/dist/20261022_Nebius收支模型_v0_5.xlsx 摘要!C10 | N20: =價格!H20 | O20: =MIN(F20,H20) | P20: =MIN(J20,L20) | Q20: =O20/N20-1 | R20: =P20/N20-1 | S20: =IF(Q20>0.5,"強力買進",IF(Q20>0.25,"買進",IF(Q20>=-0.25,"中立",IF(Q20>=-0.5,"放空","強力放空")))) | W20: 模型點位 $21.4（模型日現價 $249.87）；情境區間 $19.4–$29.5，方法區間 $12.5–$21.4 | Z20: =IF(ISNUMBER(價格!C20),價格!H20/價格!C20-1,"") | AA20: =IF(Z20="","",IF(ABS(Z20)>0.2,"模型尚未反映期間變化","")) | AB20: 現金流 | AC20: 營運缺口（不含融資、不含還本；無股利與回購） | AD20: FY26 -15.1、FY27 -17.9、FY28 -18.2、FY29 -17.2、FY30 -25.5 | AE20: -94.001645 | AF20: -25.540217 | AG20: [Derived] nebius/dist/20261022_Nebius收支模型_v0_5.xlsx 各期收支!C45…各期收支!G45 | AH20: =IF(AB20="淨利",IF(AF20>0,"通過（淨利）","不通過"),IF(AE20<0,"不通過","通過（現金流）")) | AI20: =IF(S20="未上市","未上市",IF(AH20="不通過","收支不足",S20)) | AJ20: =IF(Q20>0.5,"大於 50%",IF(Q20>0.25,"25%–50%",IF(Q20>=0,"0%–25%",IF(Q20>=-0.25,"0%～−25%",IF(Q20>=-0.5,"−25%～−50%","小於 −50%"))))) | AK20: 上檔空間＝模型加權目標價 nebius/dist/20261022_Nebius收支模型_v0_5.xlsx 摘要!C7 ÷ 外部收盤價 − 1，依本地圖五級規則自算（模型自身評等以模型日價計、級距不同，不採用；原值見模型摘要頁）
A21: WYFI | B21: WhiteFiber | C21: =價值鏈!A4 | D21: Neocloud（GPU 租賃） | E21: 模型加權目標價 | F21: 15.248118 | G21: whitefiber/dist/20261022_WhiteFiber收支模型_v0_2.xlsx 摘要!C7 | J21: 15.248118 | K21: whitefiber/dist/20261022_WhiteFiber收支模型_v0_2.xlsx 摘要!C7 | L21: 11.479506 | M21: whitefiber/dist/20261022_WhiteFiber收支模型_v0_2.xlsx 摘要!C10 | N21: =價格!H21 | O21: =MIN(F21,H21) | P21: =MIN(J21,L21) | Q21: =O21/N21-1 | R21: =P21/N21-1 | S21: =IF(Q21>0.5,"強力買進",IF(Q21>0.25,"買進",IF(Q21>=-0.25,"中立",IF(Q21>=-0.5,"放空","強力放空")))) | W21: 模型點位 $15.2（模型日現價 $16.83）；情境區間 $11.5–$25.4，方法區間 $15.1–$15.2 | Z21: =IF(ISNUMBER(價格!C21),價格!H21/價格!C21-1,"") | AA21: =IF(Z21="","",IF(ABS(Z21)>0.2,"模型尚未反映期間變化","")) | AB21: 現金流 | AC21: 營運缺口＋股利 | AD21: FY26 -371.1、FY27 -383.6、FY28 -40.7、FY29 -1.9、FY30 -22.2 | AE21: -819.45109 | AF21: -383.61804 | AG21: [Derived] whitefiber/dist/20261022_WhiteFiber收支模型_v0_2.xlsx 各期收支!C52＋C24…各期收支!G52＋G24 | AH21: =IF(AB21="淨利",IF(AF21>0,"通過（淨利）","不通過"),IF(AE21<0,"不通過","通過（現金流）")) | AI21: =IF(S21="未上市","未上市",IF(AH21="不通過","收支不足",S21)) | AJ21: =IF(Q21>0.5,"大於 50%",IF(Q21>0.25,"25%–50%",IF(Q21>=0,"0%–25%",IF(Q21>=-0.25,"0%～−25%",IF(Q21>=-0.5,"−25%～−50%","小於 −50%"))))) | AK21: 上檔空間＝模型加權目標價 whitefiber/dist/20261022_WhiteFiber收支模型_v0_2.xlsx 摘要!C7 ÷ 外部收盤價 − 1，依本地圖五級規則自算（模型自身評等以模型日價計、級距不同，不採用；原值見模型摘要頁）
A22: 00100 | B22: MiniMax | C22: =價值鏈!A2 | D22: AI 模型商 | E22: 反向檢驗：折現價值 ÷ 市值 | F22: =X22*價格!C22 | G22: minimax/dist/20261022_MiniMax收支模型_v0_2.xlsx Valuation!I21 × 模型現價 | J22: =X22*價格!C22 | K22: 同中心（模型只有一個情境） | N22: =價格!H22 | O22: =MIN(F22,H22) | P22: =MIN(J22,L22) | Q22: =O22/N22-1 | R22: =P22/N22-1 | S22: =IF(Q22>0.5,"強力買進",IF(Q22>0.25,"買進",IF(Q22>=-0.25,"中立",IF(Q22>=-0.5,"放空","強力放空")))) | X22: 0.88197135 | Z22: =IF(ISNUMBER(價格!C22),價格!H22/價格!C22-1,"") | AA22: =IF(Z22="","",IF(ABS(Z22)>0.2,"模型尚未反映期間變化","")) | AB22: 現金流 | AC22: F06 營運燒錢（經調整淨利）＋F07 算力預付與自建資本支出 | AD22: FY2026 -900.3、FY2027 -826.5、FY2028 -1,129.9、FY2029 -1,433.3、FY2030 -1,693.3 | AE22: -5983.1855 | AF22: -1693.2786 | AG22: [Derived] minimax/dist/20261022_MiniMax收支模型_v0_2.xlsx Funding!E13＋E14…Funding!I13＋I14 | AH22: =IF(AB22="淨利",IF(AF22>0,"通過（淨利）","不通過"),IF(AE22<0,"不通過","通過（現金流）")) | AI22: =IF(S22="未上市","未上市",IF(AH22="不通過","收支不足",S22)) | AJ22: =IF(Q22>0.5,"大於 50%",IF(Q22>0.25,"25%–50%",IF(Q22>=0,"0%–25%",IF(Q22>=-0.25,"0%～−25%",IF(Q22>=-0.5,"−25%～−50%","小於 −50%"))))) | AK22: 模型無評等；依 AI半導體 固定規則自算
A23: 02513 | B23: 智譜 | C23: =價值鏈!A2 | D23: AI 模型商 | E23: 未估值（反向模式） | N23: =價格!H23 | S23: 未估值 | W23: 模型未出隱含價；2028 年共識營收需為正向推估的 2.47 倍（最低共識 1.91 倍；zhipu/dist/20261022_智譜收支模型_v0_1_1.xlsx Reverse!G30） | Z23: =IF(ISNUMBER(價格!C23),價格!H23/價格!C23-1,"") | AA23: =IF(Z23="","",IF(ABS(Z23)>0.2,"模型尚未反映期間變化","")) | AB23: 現金流 | AC23: F09 自由現金流 | AD23: 2026 -41.3、2027 -40.9、2028 -40.5、2029 -59.4、2030 -99.1 | AE23: -281.18818 | AF23: -99.053811 | AG23: [Derived] zhipu/dist/20261022_智譜收支模型_v0_1_1.xlsx Funding!E16…Funding!I16 | AH23: =IF(AB23="淨利",IF(AF23>0,"通過（淨利）","不通過"),IF(AE23<0,"不通過","通過（現金流）")) | AI23: =IF(S23="未上市","未上市",IF(AH23="不通過","收支不足",S23))
A24: OpenAI | B24: OpenAI | C24: =價值鏈!A2 | D24: AI 模型商 | E24: 未上市 | N24: =價格!H24 | S24: 未上市 | W24: 未上市：不評估可投資性；收支關卡結果只作參考。 | Z24: =IF(ISNUMBER(價格!C24),價格!H24/價格!C24-1,"") | AA24: =IF(Z24="","",IF(ABS(Z24)>0.2,"模型尚未反映期間變化","")) | AB24: 現金流 | AC24: F06 自由現金流 | AD24: 2026 -39.4、2027 -116.0、2028 -134.9、2029 -137.6、2030 -131.9 | AE24: -559.84481 | AF24: -137.62462 | AG24: [Derived] openai/dist/20261025_OpenAI收支模型_v0_6_3.xlsx Funding!E13…Funding!I13 | AH24: =IF(AB24="淨利",IF(AF24>0,"通過（淨利）","不通過"),IF(AE24<0,"不通過","通過（現金流）")) | AI24: =IF(S24="未上市","未上市",IF(AH24="不通過","收支不足",S24))
A25: Anthropic | B25: Anthropic | C25: =價值鏈!A2 | D25: AI 模型商 | E25: 未上市 | N25: =價格!H25 | S25: 未上市 | W25: 未上市：不評估可投資性；收支關卡結果只作參考。 | Z25: =IF(ISNUMBER(價格!C25),價格!H25/價格!C25-1,"") | AA25: =IF(Z25="","",IF(ABS(Z25)>0.2,"模型尚未反映期間變化","")) | AB25: 現金流 | AC25: F07 自由現金流 | AD25: 2026 -2.6、2027 -18.5、2028 -15.0、2029 47.6、2030 96.1 | AE25: 107.6782 | AF25: -18.503719 | AG25: [Derived] anthropic/dist/20261024_Anthropic收支模型_v0_1_5.xlsx Funding!E14…Funding!I14 | AH25: =IF(AB25="淨利",IF(AF25>0,"通過（淨利）","不通過"),IF(AE25<0,"不通過","通過（現金流）")) | AI25: =IF(S25="未上市","未上市",IF(AH25="不通過","收支不足",S25))
A26: AMD | B26: AMD | C26: =價值鏈!A5 | D26: 運算 | E26: 加權目標價（DCF 50%＋Comparable 50%） | F26: 177.104 | G26: amd/dist/20261025_AMD模型_v0.2.1.xlsx Val!B40 | J26: 120.52124 | K26: amd/dist/20261025_AMD模型_v0.2.1.xlsx Val!B47 | N26: =價格!H26 | O26: =MIN(F26,H26) | P26: =MIN(J26,L26) | Q26: -0.65729986 | R26: =P26/N26-1 | S26: =IF(Q26>0.5,"強力買進",IF(Q26>0.25,"買進",IF(Q26>=-0.25,"中立",IF(Q26>=-0.5,"放空","強力放空")))) | T26: =471.572606000429/N26-1 | U26: 舊法：規則值情境加權價（參考，Val!B57） | V26: 45.4 ／ 46.5 ／ 52.3 | W26: DCF 目標價 152.1（Val!B23）；Comparable 目標價 202.1（Val!B41）；市場共識目標價 637.6（Val!B42，外部、僅供對照）；價格帶 C～A 情境 DCF 120.5～168.7 | Z26: =IF(ISNUMBER(價格!C26),價格!H26/價格!C26-1,"") | AA26: =IF(Z26="","",IF(ABS(Z26)>0.2,"模型尚未反映期間變化","")) | AB26: 淨利 | AC26: PL 頁各情境模型年度淨利（不含實績） | AD26: 8 個情境年度淨利（不含實績），全部為正 | AE26: 150.29729 | AF26: 12.116863 | AG26: [Derived] amd/dist/20261025_AMD模型_v0.2.1.xlsx PL!D15…PL!G47 | AH26: =IF(AB26="淨利",IF(AF26>0,"通過（淨利）","不通過"),IF(AE26<0,"不通過","通過（現金流）")) | AI26: =IF(S26="未上市","未上市",IF(AH26="不通過","收支不足",S26)) | AJ26: =IF(Q26>0.5,"大於 50%",IF(Q26>0.25,"25%–50%",IF(Q26>=0,"0%–25%",IF(Q26>=-0.25,"0%～−25%",IF(Q26>=-0.5,"−25%～−50%","小於 −50%"))))) | AK26: 上檔空間 amd/dist/20261025_AMD模型_v0.2.1.xlsx Val!B43；投資建議：模型尚未補列，依 AI半導體 固定規則自算；級距：模型尚未補列，依 AI半導體 固定規則自算
A27: 2454 | B27: 聯發科 | C27: =價值鏈!A5 | D27: 運算 | E27: 加權目標價（DCF 50%＋Comparable 50%） | F27: 2056.73 | G27: mediatek/dist/20261025_聯發科模型_v0.1.xlsx Val!B39 | J27: 1011.8078 | K27: mediatek/dist/20261025_聯發科模型_v0.1.xlsx Val!D23 | N27: =價格!H27 | O27: =MIN(F27,H27) | P27: =MIN(J27,L27) | Q27: -0.48709975 | R27: =P27/N27-1 | S27: =IF(Q27>0.5,"強力買進",IF(Q27>0.25,"買進",IF(Q27>=-0.25,"中立",IF(Q27>=-0.5,"放空","強力放空")))) | V27: 26.9 ／ 33.6 ／ 47.0 | W27: DCF 目標價 1,845.6（Val!B24）；Comparable 目標價 2,267.9（Val!B40）；市場共識目標價 6,067.0（Val!B41，外部、僅供對照）；價格帶 C～A 情境 DCF 1,011.8～2,466.1 | Z27: =IF(ISNUMBER(價格!C27),價格!H27/價格!C27-1,"") | AA27: =IF(Z27="","",IF(ABS(Z27)>0.2,"模型尚未反映期間變化","")) | AB27: 淨利 | AC27: PL 頁各情境模型年度淨利（不含實績） | AD27: 19 個情境年度淨利（不含實績），全部為正 | AE27: 3774.2803 | AF27: 116.64494 | AG27: [Derived] mediatek/dist/20261025_聯發科模型_v0.1.xlsx PL!D13…PL!J41 | AH27: =IF(AB27="淨利",IF(AF27>0,"通過（淨利）","不通過"),IF(AE27<0,"不通過","通過（現金流）")) | AI27: =IF(S27="未上市","未上市",IF(AH27="不通過","收支不足",S27)) | AJ27: =IF(Q27>0.5,"大於 50%",IF(Q27>0.25,"25%–50%",IF(Q27>=0,"0%–25%",IF(Q27>=-0.25,"0%～−25%",IF(Q27>=-0.5,"−25%～−50%","小於 −50%"))))) | AK27: 上檔空間 mediatek/dist/20261025_聯發科模型_v0.1.xlsx Val!B42；投資建議：模型尚未補列，依 AI半導體 固定規則自算；級距：模型尚未補列，依 AI半導體 固定規則自算
A28: MRVL | B28: Marvell | C28: =價值鏈!A5 | D28: 運算 | E28: 加權目標價（DCF 50%＋Comparable 50%） | F28: 128.033 | G28: mrvl/dist/20261025_邁威爾模型_v0.2.xlsx Val!B40 | J28: 71.038234 | K28: mrvl/dist/20261025_邁威爾模型_v0.2.xlsx Val!B47 | N28: =價格!H28 | O28: =MIN(F28,H28) | P28: =MIN(J28,L28) | Q28: -0.43970503 | R28: =P28/N28-1 | S28: =IF(Q28>0.5,"強力買進",IF(Q28>0.25,"買進",IF(Q28>=-0.25,"中立",IF(Q28>=-0.5,"放空","強力放空")))) | T28: =203.164070486016/N28-1 | U28: 舊法：規則值情境加權價（參考，Val!B57） | V28: 35.1 ／ 35.1 ／ 35.1 | W28: DCF 目標價 116.4（Val!B23）；Comparable 目標價 139.6（Val!B41）；市場共識目標價 341.4（Val!B42，外部、僅供對照）；價格帶 C～A 情境 DCF 71.0～147.4 | Z28: =IF(ISNUMBER(價格!C28),價格!H28/價格!C28-1,"") | AA28: =IF(Z28="","",IF(ABS(Z28)>0.2,"模型尚未反映期間變化","")) | AB28: 淨利 | AC28: PL 頁各情境模型年度淨利（不含實績） | AD28: 8 個情境年度淨利（不含實績），全部為正 | AE28: 52.617935 | AF28: 3.839711 | AG28: [Derived] mrvl/dist/20261025_邁威爾模型_v0.2.xlsx PL!D13…PL!G39 | AH28: =IF(AB28="淨利",IF(AF28>0,"通過（淨利）","不通過"),IF(AE28<0,"不通過","通過（現金流）")) | AI28: =IF(S28="未上市","未上市",IF(AH28="不通過","收支不足",S28)) | AJ28: =IF(Q28>0.5,"大於 50%",IF(Q28>0.25,"25%–50%",IF(Q28>=0,"0%–25%",IF(Q28>=-0.25,"0%～−25%",IF(Q28>=-0.5,"−25%～−50%","小於 −50%"))))) | AK28: 上檔空間 mrvl/dist/20261025_邁威爾模型_v0.2.xlsx Val!B43；投資建議：模型尚未補列，依 AI半導體 固定規則自算；級距：模型尚未補列，依 AI半導體 固定規則自算
A29: 3661 | B29: 世芯-KY | C29: =價值鏈!A5 | D29: 運算 | E29: 加權目標價（DCF 50%＋Comparable 50%） | F29: 5925.8607 | G29: alchip/dist/20261025_世芯-KY模型_v0.1.xlsx Val!B39 | J29: 1226.2441 | K29: alchip/dist/20261025_世芯-KY模型_v0.1.xlsx Val!D23 | N29: =價格!H29 | O29: =MIN(F29,H29) | P29: =MIN(J29,L29) | Q29: 0.69552525 | R29: =P29/N29-1 | S29: =IF(Q29>0.5,"強力買進",IF(Q29>0.25,"買進",IF(Q29>=-0.25,"中立",IF(Q29>=-0.5,"放空","強力放空")))) | V29: 10.3 ／ 17.8 ／ 33.8 | W29: DCF 目標價 3,503.2（Val!B24）；Comparable 目標價 8,348.5（Val!B40）；市場共識目標價 5,803.2（Val!B41，外部、僅供對照）；價格帶 C～A 情境 DCF 1,226.2～5,691.2 | Z29: =IF(ISNUMBER(價格!C29),價格!H29/價格!C29-1,"") | AA29: =IF(Z29="","",IF(ABS(Z29)>0.2,"模型尚未反映期間變化","")) | AB29: 淨利 | AC29: PL 頁各情境模型年度淨利（不含實績） | AD29: 19 個情境年度淨利（不含實績），全部為正 | AE29: 389.36641 | AF29: 8.1798493 | AG29: [Derived] alchip/dist/20261025_世芯-KY模型_v0.1.xlsx PL!D11…PL!J35 | AH29: =IF(AB29="淨利",IF(AF29>0,"通過（淨利）","不通過"),IF(AE29<0,"不通過","通過（現金流）")) | AI29: =IF(S29="未上市","未上市",IF(AH29="不通過","收支不足",S29)) | AJ29: =IF(Q29>0.5,"大於 50%",IF(Q29>0.25,"25%–50%",IF(Q29>=0,"0%–25%",IF(Q29>=-0.25,"0%～−25%",IF(Q29>=-0.5,"−25%～−50%","小於 −50%"))))) | AK29: 上檔空間 alchip/dist/20261025_世芯-KY模型_v0.1.xlsx Val!B42；投資建議：模型尚未補列，依 AI半導體 固定規則自算；級距：模型尚未補列，依 AI半導體 固定規則自算
A30: 3443 | B30: 創意 | C30: =價值鏈!A5 | D30: 運算 | E30: 加權目標價（DCF 50%＋Comparable 50%） | F30: 2879.2041 | G30: guc/dist/20261025_創意模型_v0.1.xlsx Val!B39 | J30: 662.11994 | K30: guc/dist/20261025_創意模型_v0.1.xlsx Val!D23 | N30: =價格!H30 | O30: =MIN(F30,H30) | P30: =MIN(J30,L30) | Q30: -0.62040816 | R30: =P30/N30-1 | S30: =IF(Q30>0.5,"強力買進",IF(Q30>0.25,"買進",IF(Q30>=-0.25,"中立",IF(Q30>=-0.5,"放空","強力放空")))) | V30: 38.4 ／ 66.9 ／ 150.3 | W30: DCF 目標價 2,237.7（Val!B24）；Comparable 目標價 3,520.7（Val!B40）；市場共識目標價 6,722.4（Val!B41，外部、僅供對照）；價格帶 C～A 情境 DCF 662.1～3,747.5 | Z30: =IF(ISNUMBER(價格!C30),價格!H30/價格!C30-1,"") | AA30: =IF(Z30="","",IF(ABS(Z30)>0.2,"模型尚未反映期間變化","")) | AB30: 淨利 | AC30: PL 頁各情境模型年度淨利（不含實績） | AD30: 19 個情境年度淨利（不含實績），全部為正 | AE30: 342.44906 | AF30: 6.091635 | AG30: [Derived] guc/dist/20261025_創意模型_v0.1.xlsx PL!D13…PL!J41 | AH30: =IF(AB30="淨利",IF(AF30>0,"通過（淨利）","不通過"),IF(AE30<0,"不通過","通過（現金流）")) | AI30: =IF(S30="未上市","未上市",IF(AH30="不通過","收支不足",S30)) | AJ30: =IF(Q30>0.5,"大於 50%",IF(Q30>0.25,"25%–50%",IF(Q30>=0,"0%–25%",IF(Q30>=-0.25,"0%～−25%",IF(Q30>=-0.5,"−25%～−50%","小於 −50%"))))) | AK30: 上檔空間 guc/dist/20261025_創意模型_v0.1.xlsx Val!B42；投資建議：模型尚未補列，依 AI半導體 固定規則自算；級距：模型尚未補列，依 AI半導體 固定規則自算
A31: 285A | B31: Kioxia | C31: =價值鏈!A6 | D31: 記憶體 | E31: 加權目標價（DCF 50%＋Comparable 50%） | F31: 22268.388 | G31: kioxia/dist/20261025_Kioxia模型_v0.1.xlsx Val!B49 | J31: 8694.5744 | K31: kioxia/dist/20261025_Kioxia模型_v0.1.xlsx Val!D23 | N31: =價格!H31 | O31: =MIN(F31,H31) | P31: =MIN(J31,L31) | Q31: 0.74585558 | R31: =P31/N31-1 | S31: 強力買進 | T31: =13291.9681066088/N31-1 | U31: 舊法：規則值情境加權價（參考，Val!B155） | V31: 2.2 ／ 8.8 ／ 21.3 | W31: DCF 目標價 24,180.1（Val!B24）；Comparable 目標價 20,356.7（Val!B50）；市場共識目標價 36,929.2（Val!B51，外部、僅供對照）；價格帶 C～A 情境 DCF 8,694.6～45,985.8 | Z31: =IF(ISNUMBER(價格!C31),價格!H31/價格!C31-1,"") | AA31: =IF(Z31="","",IF(ABS(Z31)>0.2,"模型尚未反映期間變化","")) | AB31: 淨利 | AC31: PL 頁各情境模型年度淨利（不含實績） | AD31: 22 個情境年度淨利（不含實績），全部為正 | AE31: 76685.971 | AF31: 887.009 | AG31: [Derived] kioxia/dist/20261025_Kioxia模型_v0.1.xlsx PL!D9…PL!G123 | AH31: =IF(AB31="淨利",IF(AF31>0,"通過（淨利）","不通過"),IF(AE31<0,"不通過","通過（現金流）")) | AI31: =IF(S31="未上市","未上市",IF(AH31="不通過","收支不足",S31)) | AJ31: 大於 50% | AK31: 上檔空間 kioxia/dist/20261025_Kioxia模型_v0.1.xlsx Val!B52；投資建議 kioxia/dist/20261025_Kioxia模型_v0.1.xlsx Val!B55；級距 kioxia/dist/20261025_Kioxia模型_v0.1.xlsx Val!B54
A32: SNDK | B32: SanDisk | C32: =價值鏈!A6 | D32: 記憶體 | E32: 加權目標價（DCF 50%＋Comparable 50%） | F32: 952.85895 | G32: sndk/dist/20261025_SanDisk模型_v0.1.xlsx Val!B49 | J32: 492.9844 | K32: sndk/dist/20261025_SanDisk模型_v0.1.xlsx Val!D23 | N32: =價格!H32 | O32: =MIN(F32,H32) | P32: =MIN(J32,L32) | Q32: -0.2303426 | R32: =P32/N32-1 | S32: 中立 | T32: =456.06461830986/N32-1 | U32: 舊法：規則值情境加權價（參考，Val!B155） | V32: 3.6 ／ 5.6 ／ 6.3 | W32: DCF 目標價 1,139.2（Val!B24）；Comparable 目標價 766.6（Val!B50）；市場共識目標價 2,144.0（Val!B51，外部、僅供對照）；價格帶 C～A 情境 DCF 493.0～2,275.1 | Z32: =IF(ISNUMBER(價格!C32),價格!H32/價格!C32-1,"") | AA32: =IF(Z32="","",IF(ABS(Z32)>0.2,"模型尚未反映期間變化","")) | AB32: 淨利 | AC32: PL 頁各情境模型年度淨利（不含實績） | AD32: 12 個情境年度淨利（不含實績），全部為正 | AE32: 287.87903 | AF32: 3.615 | AG32: [Derived] sndk/dist/20261025_SanDisk模型_v0.1.xlsx PL!E9…PL!G51 | AH32: =IF(AB32="淨利",IF(AF32>0,"通過（淨利）","不通過"),IF(AE32<0,"不通過","通過（現金流）")) | AI32: =IF(S32="未上市","未上市",IF(AH32="不通過","收支不足",S32)) | AJ32: 0%～−25% | AK32: 上檔空間 sndk/dist/20261025_SanDisk模型_v0.1.xlsx Val!B52；投資建議 sndk/dist/20261025_SanDisk模型_v0.1.xlsx Val!B55；級距 sndk/dist/20261025_SanDisk模型_v0.1.xlsx Val!B54
A33: COHR | B33: Coherent | C33: =價值鏈!A7 | D33: 網通 | E33: 加權目標價（DCF 50%＋Comparable 50%） | F33: 322.27582 | G33: cohr/dist/20261025_Coherent模型_v0.2.xlsx Val!B39 | J33: 126.53922 | K33: cohr/dist/20261025_Coherent模型_v0.2.xlsx Val!D23 | N33: =價格!H33 | O33: =MIN(F33,H33) | P33: =MIN(J33,L33) | Q33: 0.54073634 | R33: =P33/N33-1 | S33: =IF(Q33>0.5,"強力買進",IF(Q33>0.25,"買進",IF(Q33>=-0.25,"中立",IF(Q33>=-0.5,"放空","強力放空")))) | T33: =319.789455314265/N33-1 | U33: 舊法：規則值情境加權價（參考，Val!B53） | V33: 14.3 ／ 15.5 ／ 17.0 | W33: DCF 目標價 206.3（Val!B24）；Comparable 目標價 438.2（Val!B40）；市場共識目標價 394.8（Val!B41，外部、僅供對照）；價格帶 C～A 情境 DCF 126.5～272.6 | Z33: =IF(ISNUMBER(價格!C33),價格!H33/價格!C33-1,"") | AA33: =IF(Z33="","",IF(ABS(Z33)>0.2,"模型尚未反映期間變化","")) | AB33: 淨利 | AC33: PL 頁各情境模型年度淨利（不含實績） | AD33: 16 個情境年度淨利（不含實績），全部為正 | AE33: 51.464808 | AF33: 2.0765673 | AG33: [Derived] cohr/dist/20261025_Coherent模型_v0.2.xlsx PL!E13…PL!J39 | AH33: =IF(AB33="淨利",IF(AF33>0,"通過（淨利）","不通過"),IF(AE33<0,"不通過","通過（現金流）")) | AI33: =IF(S33="未上市","未上市",IF(AH33="不通過","收支不足",S33)) | AJ33: =IF(Q33>0.5,"大於 50%",IF(Q33>0.25,"25%–50%",IF(Q33>=0,"0%–25%",IF(Q33>=-0.25,"0%～−25%",IF(Q33>=-0.5,"−25%～−50%","小於 −50%"))))) | AK33: 上檔空間 cohr/dist/20261025_Coherent模型_v0.2.xlsx Val!B42；投資建議：模型尚未補列，依 AI半導體 固定規則自算；級距：模型尚未補列，依 AI半導體 固定規則自算
A34: LITE | B34: Lumentum | C34: =價值鏈!A7 | D34: 網通 | E34: 加權目標價（DCF 50%＋Comparable 50%） | F34: 611.90354 | G34: lite/dist/20261025_Lumentum模型_v0.2.xlsx Val!B39 | J34: 216.97977 | K34: lite/dist/20261025_Lumentum模型_v0.2.xlsx Val!D23 | N34: =價格!H34 | O34: =MIN(F34,H34) | P34: =MIN(J34,L34) | Q34: -0.19078575 | R34: =P34/N34-1 | S34: =IF(Q34>0.5,"強力買進",IF(Q34>0.25,"買進",IF(Q34>=-0.25,"中立",IF(Q34>=-0.5,"放空","強力放空")))) | T34: =409.473484390874/N34-1 | U34: 舊法：規則值情境加權價（參考，Val!B53） | V34: 24.1 ／ 26.6 ／ 29.7 | W34: DCF 目標價 375.8（Val!B24）；Comparable 目標價 848.1（Val!B40）；市場共識目標價 1,165.0（Val!B41，外部、僅供對照）；價格帶 C～A 情境 DCF 217.0～508.3 | Z34: =IF(ISNUMBER(價格!C34),價格!H34/價格!C34-1,"") | AA34: =IF(Z34="","",IF(ABS(Z34)>0.2,"模型尚未反映期間變化","")) | AB34: 淨利 | AC34: PL 頁各情境模型年度淨利（不含實績） | AD34: 16 個情境年度淨利（不含實績），全部為正 | AE34: 48.07362 | AF34: 1.7072727 | AG34: [Derived] lite/dist/20261025_Lumentum模型_v0.2.xlsx PL!E13…PL!J39 | AH34: =IF(AB34="淨利",IF(AF34>0,"通過（淨利）","不通過"),IF(AE34<0,"不通過","通過（現金流）")) | AI34: =IF(S34="未上市","未上市",IF(AH34="不通過","收支不足",S34)) | AJ34: =IF(Q34>0.5,"大於 50%",IF(Q34>0.25,"25%–50%",IF(Q34>=0,"0%–25%",IF(Q34>=-0.25,"0%～−25%",IF(Q34>=-0.5,"−25%～−50%","小於 −50%"))))) | AK34: 上檔空間 lite/dist/20261025_Lumentum模型_v0.2.xlsx Val!B42；投資建議：模型尚未補列，依 AI半導體 固定規則自算；級距：模型尚未補列，依 AI半導體 固定規則自算
A35: 300502 | B35: 新易盛 | C35: =價值鏈!A7 | D35: 網通 | E35: 加權目標價（DCF 50%＋Comparable 50%） | F35: 797.81017 | G35: eoptolink/dist/20261025_新易盛模型_v0.2.xlsx Val!B39 | J35: 304.97904 | K35: eoptolink/dist/20261025_新易盛模型_v0.2.xlsx Val!D23 | N35: =價格!H35 | O35: =MIN(F35,H35) | P35: =MIN(J35,L35) | Q35: 2.0567439 | R35: =P35/N35-1 | S35: =IF(Q35>0.5,"強力買進",IF(Q35>0.25,"買進",IF(Q35>=-0.25,"中立",IF(Q35>=-0.5,"放空","強力放空")))) | T35: =1150.67817266164/N35-1 | U35: 舊法：規則值情境加權價（參考，Val!B53） | V35: 9.0 ／ 11.4 ／ 15.6 | W35: DCF 目標價 516.2（Val!B24）；Comparable 目標價 1,079.4（Val!B40）；市場共識目標價 460.9（Val!B41，外部、僅供對照）；價格帶 C～A 情境 DCF 305.0～652.7 | Z35: =IF(ISNUMBER(價格!C35),價格!H35/價格!C35-1,"") | AA35: =IF(Z35="","",IF(ABS(Z35)>0.2,"模型尚未反映期間變化","")) | AB35: 淨利 | AC35: PL 頁各情境模型年度淨利（不含實績） | AD35: 17 個情境年度淨利（不含實績），全部為正 | AE35: 721.2419 | AF35: 20.060518 | AG35: [Derived] eoptolink/dist/20261025_新易盛模型_v0.2.xlsx PL!D12…PL!J36 | AH35: =IF(AB35="淨利",IF(AF35>0,"通過（淨利）","不通過"),IF(AE35<0,"不通過","通過（現金流）")) | AI35: =IF(S35="未上市","未上市",IF(AH35="不通過","收支不足",S35)) | AJ35: =IF(Q35>0.5,"大於 50%",IF(Q35>0.25,"25%–50%",IF(Q35>=0,"0%–25%",IF(Q35>=-0.25,"0%～−25%",IF(Q35>=-0.5,"−25%～−50%","小於 −50%"))))) | AK35: 上檔空間 eoptolink/dist/20261025_新易盛模型_v0.2.xlsx Val!B42；投資建議：模型尚未補列，依 AI半導體 固定規則自算；級距：模型尚未補列，依 AI半導體 固定規則自算
A36: 2345 | B36: 智邦 | C36: =價值鏈!A7 | D36: 網通 | E36: 加權目標價（DCF 50%＋Comparable 50%） | F36: 2275.0397 | G36: accton/dist/20261025_智邦模型_v0.2.xlsx Val!B39 | J36: 1519.311 | K36: accton/dist/20261025_智邦模型_v0.2.xlsx Val!B46 | N36: =價格!H36 | O36: =MIN(F36,H36) | P36: =MIN(J36,L36) | Q36: 0.28171253 | R36: =P36/N36-1 | S36: =IF(Q36>0.5,"強力買進",IF(Q36>0.25,"買進",IF(Q36>=-0.25,"中立",IF(Q36>=-0.5,"放空","強力放空")))) | T36: =3452.51414467191/N36-1 | U36: 舊法：規則值情境加權價（參考，Val!B56） | V36: 10.5 ／ 13.3 ／ 18.5 | W36: DCF 目標價 2,583.7（Val!B23）；Comparable 目標價 1,966.4（Val!B40）；市場共識目標價 3,500.0（Val!B41，外部、僅供對照）；價格帶 C～A 情境 DCF 1,519.3～3,280.3 | Z36: =IF(ISNUMBER(價格!C36),價格!H36/價格!C36-1,"") | AA36: =IF(Z36="","",IF(ABS(Z36)>0.2,"模型尚未反映期間變化","")) | AB36: 淨利 | AC36: PL 頁各情境模型年度淨利（不含實績） | AD36: 8 個情境年度淨利（不含實績），全部為正 | AE36: 624.94763 | AF36: 47.825855 | AG36: [Derived] accton/dist/20261025_智邦模型_v0.2.xlsx PL!D13…PL!G39 | AH36: =IF(AB36="淨利",IF(AF36>0,"通過（淨利）","不通過"),IF(AE36<0,"不通過","通過（現金流）")) | AI36: =IF(S36="未上市","未上市",IF(AH36="不通過","收支不足",S36)) | AJ36: =IF(Q36>0.5,"大於 50%",IF(Q36>0.25,"25%–50%",IF(Q36>=0,"0%–25%",IF(Q36>=-0.25,"0%～−25%",IF(Q36>=-0.5,"−25%～−50%","小於 −50%"))))) | AK36: 上檔空間 accton/dist/20261025_智邦模型_v0.2.xlsx Val!B42；投資建議：模型尚未補列，依 AI半導體 固定規則自算；級距：模型尚未補列，依 AI半導體 固定規則自算
A37: FN | B37: Fabrinet | C37: =價值鏈!A7 | D37: 網通 | E37: 加權目標價（DCF 50%＋Comparable 50%） | F37: 360.6019 | G37: fabrinet/dist/20261025_Fabrinet模型_v0.1.xlsx Val!B39 | J37: 164.55228 | K37: fabrinet/dist/20261025_Fabrinet模型_v0.1.xlsx Val!D23 | N37: =價格!H37 | O37: =MIN(F37,H37) | P37: =MIN(J37,L37) | Q37: 0.14498601 | R37: =P37/N37-1 | S37: =IF(Q37>0.5,"強力買進",IF(Q37>0.25,"買進",IF(Q37>=-0.25,"中立",IF(Q37>=-0.5,"放空","強力放空")))) | T37: =406.817486657285/N37-1 | U37: 舊法：規則值情境加權價（參考，Val!B53） | V37: 11.7 ／ 14.3 ／ 18.1 | W37: DCF 目標價 332.2（Val!B24）；Comparable 目標價 389.0（Val!B40）；市場共識目標價 687.8（Val!B41，外部、僅供對照）；價格帶 C～A 情境 DCF 164.6～505.0 | Z37: =IF(ISNUMBER(價格!C37),價格!H37/價格!C37-1,"") | AA37: =IF(Z37="","",IF(ABS(Z37)>0.2,"模型尚未反映期間變化","")) | AB37: 淨利 | AC37: PL 頁各情境模型年度淨利（不含實績） | AD37: 18 個情境年度淨利（不含實績），全部為正 | AE37: 15.777405 | AF37: 0.45204184 | AG37: [Derived] fabrinet/dist/20261025_Fabrinet模型_v0.1.xlsx PL!E15…PL!J45 | AH37: =IF(AB37="淨利",IF(AF37>0,"通過（淨利）","不通過"),IF(AE37<0,"不通過","通過（現金流）")) | AI37: =IF(S37="未上市","未上市",IF(AH37="不通過","收支不足",S37)) | AJ37: =IF(Q37>0.5,"大於 50%",IF(Q37>0.25,"25%–50%",IF(Q37>=0,"0%–25%",IF(Q37>=-0.25,"0%～−25%",IF(Q37>=-0.5,"−25%～−50%","小於 −50%"))))) | AK37: 上檔空間 fabrinet/dist/20261025_Fabrinet模型_v0.1.xlsx Val!B42；投資建議：模型尚未補列，依 AI半導體 固定規則自算；級距：模型尚未補列，依 AI半導體 固定規則自算
A38: CRDO | B38: Credo | C38: =價值鏈!A7 | D38: 網通 | E38: 加權目標價（DCF 50%＋Comparable 50%） | F38: 195.6964 | G38: crdo/dist/20261025_Credo模型_v0.2.xlsx Val!B39 | J38: 53.125123 | K38: crdo/dist/20261025_Credo模型_v0.2.xlsx Val!D23 | N38: =價格!H38 | O38: =MIN(F38,H38) | P38: =MIN(J38,L38) | Q38: 0.32864687 | R38: =P38/N38-1 | S38: =IF(Q38>0.5,"強力買進",IF(Q38>0.25,"買進",IF(Q38>=-0.25,"中立",IF(Q38>=-0.5,"放空","強力放空")))) | T38: =620.46087778403/N38-1 | U38: 舊法：規則值情境加權價（參考，Val!B53） | V38: 16.0 ／ 17.3 ／ 18.9 | W38: DCF 目標價 101.3（Val!B24）；Comparable 目標價 290.1（Val!B40）；市場共識目標價 279.1（Val!B41，外部、僅供對照）；價格帶 C～A 情境 DCF 53.1～143.4 | Z38: =IF(ISNUMBER(價格!C38),價格!H38/價格!C38-1,"") | AA38: =IF(Z38="","",IF(ABS(Z38)>0.2,"模型尚未反映期間變化","")) | AB38: 淨利 | AC38: PL 頁各情境模型年度淨利（不含實績） | AD38: 16 個情境年度淨利（不含實績），全部為正 | AE38: 26.244784 | AF38: 0.79126305 | AG38: [Derived] crdo/dist/20261025_Credo模型_v0.2.xlsx PL!E13…PL!J39 | AH38: =IF(AB38="淨利",IF(AF38>0,"通過（淨利）","不通過"),IF(AE38<0,"不通過","通過（現金流）")) | AI38: =IF(S38="未上市","未上市",IF(AH38="不通過","收支不足",S38)) | AJ38: =IF(Q38>0.5,"大於 50%",IF(Q38>0.25,"25%–50%",IF(Q38>=0,"0%–25%",IF(Q38>=-0.25,"0%～−25%",IF(Q38>=-0.5,"−25%～−50%","小於 −50%"))))) | AK38: 上檔空間 crdo/dist/20261025_Credo模型_v0.2.xlsx Val!B42；投資建議：模型尚未補列，依 AI半導體 固定規則自算；級距：模型尚未補列，依 AI半導體 固定規則自算
A39: ALAB | B39: Astera Labs | C39: =價值鏈!A7 | D39: 網通 | E39: 加權目標價（DCF 50%＋Comparable 50%） | F39: 132.48529 | G39: alab/dist/20261025_Astera Labs模型_v0.1.xlsx Val!B39 | J39: 52.31899 | K39: alab/dist/20261025_Astera Labs模型_v0.1.xlsx Val!D23 | N39: =價格!H39 | O39: =MIN(F39,H39) | P39: =MIN(J39,L39) | Q39: -0.48481376 | R39: =P39/N39-1 | S39: =IF(Q39>0.5,"強力買進",IF(Q39>0.25,"買進",IF(Q39>=-0.25,"中立",IF(Q39>=-0.5,"放空","強力放空")))) | T39: =616.322122932452/N39-1 | U39: 舊法：規則值情境加權價（參考，Val!B53） | V39: 31.7 ／ 42.0 ／ 71.5 | W39: DCF 目標價 105.3（Val!B24）；Comparable 目標價 159.6（Val!B40）；市場共識目標價 388.4（Val!B41，外部、僅供對照）；價格帶 C～A 情境 DCF 52.3～138.7 | Z39: =IF(ISNUMBER(價格!C39),價格!H39/價格!C39-1,"") | AA39: =IF(Z39="","",IF(ABS(Z39)>0.2,"模型尚未反映期間變化","")) | AB39: 淨利 | AC39: PL 頁各情境模型年度淨利（不含實績） | AD39: 17 個情境年度淨利（不含實績），全部為正 | AE39: 22.82233 | AF39: 0.68167597 | AG39: [Derived] alab/dist/20261025_Astera Labs模型_v0.1.xlsx PL!D12…PL!J36 | AH39: =IF(AB39="淨利",IF(AF39>0,"通過（淨利）","不通過"),IF(AE39<0,"不通過","通過（現金流）")) | AI39: =IF(S39="未上市","未上市",IF(AH39="不通過","收支不足",S39)) | AJ39: =IF(Q39>0.5,"大於 50%",IF(Q39>0.25,"25%–50%",IF(Q39>=0,"0%–25%",IF(Q39>=-0.25,"0%～−25%",IF(Q39>=-0.5,"−25%～−50%","小於 −50%"))))) | AK39: 上檔空間 alab/dist/20261025_Astera Labs模型_v0.1.xlsx Val!B42；投資建議：模型尚未補列，依 AI半導體 固定規則自算；級距：模型尚未補列，依 AI半導體 固定規則自算
A40: 2449 | B40: 京元電 | C40: =價值鏈!A11 | D40: 代工與封測 | E40: 加權目標價（DCF 50%＋Comparable 50%） | F40: 173.35309 | G40: kyec/dist/20261025_京元電模型_v0.2.xlsx Val!B39 | J40: 85.733108 | K40: kyec/dist/20261025_京元電模型_v0.2.xlsx Val!D23 | N40: =價格!H40 | O40: =MIN(F40,H40) | P40: =MIN(J40,L40) | Q40: -0.33960727 | R40: =P40/N40-1 | S40: =IF(Q40>0.5,"強力買進",IF(Q40>0.25,"買進",IF(Q40>=-0.25,"中立",IF(Q40>=-0.5,"放空","強力放空")))) | V40: 23.7 ／ 29.1 ／ 42.5 | W40: DCF 目標價 138.6（Val!B24）；Comparable 目標價 208.1（Val!B40）；市場共識目標價 340.7（Val!B41，外部、僅供對照）；價格帶 C～A 情境 DCF 85.7～170.6 | Z40: =IF(ISNUMBER(價格!C40),價格!H40/價格!C40-1,"") | AA40: =IF(Z40="","",IF(ABS(Z40)>0.2,"模型尚未反映期間變化","")) | AB40: 淨利 | AC40: PL 頁各情境模型年度淨利（不含實績） | AD40: 17 個情境年度淨利（不含實績），全部為正 | AE40: 223.57211 | AF40: 7.9156664 | AG40: [Derived] kyec/dist/20261025_京元電模型_v0.2.xlsx PL!D14…PL!J42 | AH40: =IF(AB40="淨利",IF(AF40>0,"通過（淨利）","不通過"),IF(AE40<0,"不通過","通過（現金流）")) | AI40: =IF(S40="未上市","未上市",IF(AH40="不通過","收支不足",S40)) | AJ40: =IF(Q40>0.5,"大於 50%",IF(Q40>0.25,"25%–50%",IF(Q40>=0,"0%–25%",IF(Q40>=-0.25,"0%～−25%",IF(Q40>=-0.5,"−25%～−50%","小於 −50%"))))) | AK40: 上檔空間 kyec/dist/20261025_京元電模型_v0.2.xlsx Val!B42；投資建議：模型尚未補列，依 AI半導體 固定規則自算；級距：模型尚未補列，依 AI半導體 固定規則自算
A41: AMKR | B41: Amkor | C41: =價值鏈!A11 | D41: 代工與封測 | E41: 加權目標價（DCF 50%＋Comparable 50%） | F41: 55.668847 | G41: amkr/dist/20261025_艾克爾模型_v0.2.xlsx Val!B39 | J41: 22.021316 | K41: amkr/dist/20261025_艾克爾模型_v0.2.xlsx Val!D23 | N41: =價格!H41 | O41: =MIN(F41,H41) | P41: =MIN(J41,L41) | Q41: 0.4165101 | R41: =P41/N41-1 | S41: =IF(Q41>0.5,"強力買進",IF(Q41>0.25,"買進",IF(Q41>=-0.25,"中立",IF(Q41>=-0.5,"放空","強力放空")))) | V41: 9.8 ／ 12.1 ／ 17.0 | W41: DCF 目標價 36.0（Val!B24）；Comparable 目標價 75.3（Val!B40）；市場共識目標價 76.4（Val!B41，外部、僅供對照）；價格帶 C～A 情境 DCF 22.0～48.9 | Z41: =IF(ISNUMBER(價格!C41),價格!H41/價格!C41-1,"") | AA41: =IF(Z41="","",IF(ABS(Z41)>0.2,"模型尚未反映期間變化","")) | AB41: 淨利 | AC41: PL 頁各情境模型年度淨利（不含實績） | AD41: 19 個情境年度淨利（不含實績），全部為正 | AE41: 17601.291 | AF41: 579.13847 | AG41: [Derived] amkr/dist/20261025_艾克爾模型_v0.2.xlsx PL!D14…PL!J44 | AH41: =IF(AB41="淨利",IF(AF41>0,"通過（淨利）","不通過"),IF(AE41<0,"不通過","通過（現金流）")) | AI41: =IF(S41="未上市","未上市",IF(AH41="不通過","收支不足",S41)) | AJ41: =IF(Q41>0.5,"大於 50%",IF(Q41>0.25,"25%–50%",IF(Q41>=0,"0%–25%",IF(Q41>=-0.25,"0%～−25%",IF(Q41>=-0.5,"−25%～−50%","小於 −50%"))))) | AK41: 上檔空間 amkr/dist/20261025_艾克爾模型_v0.2.xlsx Val!B42；投資建議：模型尚未補列，依 AI半導體 固定規則自算；級距：模型尚未補列，依 AI半導體 固定規則自算
A42: 2383 | B42: 台光電 | C42: =價值鏈!A8 | D42: 載板與 PCB | E42: 加權目標價（DCF 50%＋Comparable 50%） | F42: 5477.3859 | G42: emc/dist/20261025_台光電模型_v0.2.xlsx Val!B118 | J42: 2690.6233 | K42: emc/dist/20261025_台光電模型_v0.2.xlsx Val!D104 | N42: =價格!H42 | O42: =MIN(F42,H42) | P42: =MIN(J42,L42) | Q42: 0.08035224 | R42: =P42/N42-1 | S42: =IF(Q42>0.5,"強力買進",IF(Q42>0.25,"買進",IF(Q42>=-0.25,"中立",IF(Q42>=-0.5,"放空","強力放空")))) | T42: =2904.876796827/N42-1 | U42: 舊法：規則值情境加權價（參考，Val!B36） | V42: 16.9 ／ 19.2 ／ 24.4 | W42: DCF 目標價 4,252.1（Val!B105）；Comparable 目標價 6,702.7（Val!B119）；市場共識目標價 7,803.0（Val!B120，外部、僅供對照）；價格帶 C～A 情境 DCF 2,690.6～5,427.6 | Z42: =IF(ISNUMBER(價格!C42),價格!H42/價格!C42-1,"") | AA42: =IF(Z42="","",IF(ABS(Z42)>0.2,"模型尚未反映期間變化","")) | AB42: 淨利 | AC42: PL 頁各情境模型年度淨利（不含實績） | AD42: 8 個情境年度淨利（不含實績），全部為正 | AE42: 691.46388 | AF42: 42.891099 | AG42: [Derived] emc/dist/20261025_台光電模型_v0.2.xlsx PL!D12…PL!G36 | AH42: =IF(AB42="淨利",IF(AF42>0,"通過（淨利）","不通過"),IF(AE42<0,"不通過","通過（現金流）")) | AI42: =IF(S42="未上市","未上市",IF(AH42="不通過","收支不足",S42)) | AJ42: =IF(Q42>0.5,"大於 50%",IF(Q42>0.25,"25%–50%",IF(Q42>=0,"0%–25%",IF(Q42>=-0.25,"0%～−25%",IF(Q42>=-0.5,"−25%～−50%","小於 −50%"))))) | AK42: 上檔空間 emc/dist/20261025_台光電模型_v0.2.xlsx Val!B121；投資建議：模型尚未補列，依 AI半導體 固定規則自算；級距：模型尚未補列，依 AI半導體 固定規則自算
A43: 3037 | B43: 欣興 | C43: =價值鏈!A8 | D43: 載板與 PCB | E43: 加權目標價（DCF 50%＋Comparable 50%） | F43: 726.78689 | G43: unimicron/dist/20261025_欣興模型_v0.1.xlsx Val!B39 | J43: 219.43321 | K43: unimicron/dist/20261025_欣興模型_v0.1.xlsx Val!D23 | N43: =價格!H43 | O43: =MIN(F43,H43) | P43: =MIN(J43,L43) | Q43: -0.33015033 | R43: =P43/N43-1 | S43: =IF(Q43>0.5,"強力買進",IF(Q43>0.25,"買進",IF(Q43>=-0.25,"中立",IF(Q43>=-0.5,"放空","強力放空")))) | V43: 35.6 ／ 46.7 ／ 67.6 | W43: DCF 目標價 388.5（Val!B24）；Comparable 目標價 1,065.0（Val!B40）；市場共識目標價 1,317.4（Val!B41，外部、僅供對照）；價格帶 C～A 情境 DCF 219.4～505.7 | Z43: =IF(ISNUMBER(價格!C43),價格!H43/價格!C43-1,"") | AA43: =IF(Z43="","",IF(ABS(Z43)>0.2,"模型尚未反映期間變化","")) | AB43: 淨利 | AC43: PL 頁各情境模型年度淨利（不含實績） | AD43: 17 個情境年度淨利（不含實績），全部為正 | AE43: 746.29657 | AF43: 26.319329 | AG43: [Derived] unimicron/dist/20261025_欣興模型_v0.1.xlsx PL!D13…PL!J41 | AH43: =IF(AB43="淨利",IF(AF43>0,"通過（淨利）","不通過"),IF(AE43<0,"不通過","通過（現金流）")) | AI43: =IF(S43="未上市","未上市",IF(AH43="不通過","收支不足",S43)) | AJ43: =IF(Q43>0.5,"大於 50%",IF(Q43>0.25,"25%–50%",IF(Q43>=0,"0%–25%",IF(Q43>=-0.25,"0%～−25%",IF(Q43>=-0.5,"−25%～−50%","小於 −50%"))))) | AK43: 上檔空間 unimicron/dist/20261025_欣興模型_v0.1.xlsx Val!B42；投資建議：模型尚未補列，依 AI半導體 固定規則自算；級距：模型尚未補列，依 AI半導體 固定規則自算
A44: 8046 | B44: 南電 | C44: =價值鏈!A8 | D44: 載板與 PCB | E44: 加權目標價（DCF 50%＋Comparable 50%） | F44: 906.79513 | G44: nanya_pcb/dist/20261025_南電模型_v0.1.xlsx Val!B39 | J44: 262.21893 | K44: nanya_pcb/dist/20261025_南電模型_v0.1.xlsx Val!D23 | N44: =價格!H44 | O44: =MIN(F44,H44) | P44: =MIN(J44,L44) | Q44: -0.28316591 | R44: =P44/N44-1 | S44: =IF(Q44>0.5,"強力買進",IF(Q44>0.25,"買進",IF(Q44>=-0.25,"中立",IF(Q44>=-0.5,"放空","強力放空")))) | V44: 35.2 ／ 41.3 ／ 54.2 | W44: DCF 目標價 466.3（Val!B24）；Comparable 目標價 1,347.3（Val!B40）；市場共識目標價 1,651.3（Val!B41，外部、僅供對照）；價格帶 C～A 情境 DCF 262.2～621.7 | Z44: =IF(ISNUMBER(價格!C44),價格!H44/價格!C44-1,"") | AA44: =IF(Z44="","",IF(ABS(Z44)>0.2,"模型尚未反映期間變化","")) | AB44: 淨利 | AC44: PL 頁各情境模型年度淨利（不含實績） | AD44: 19 個情境年度淨利（不含實績），全部為正 | AE44: 383.27339 | AF44: 11.509862 | AG44: [Derived] nanya_pcb/dist/20261025_南電模型_v0.1.xlsx PL!D13…PL!J41 | AH44: =IF(AB44="淨利",IF(AF44>0,"通過（淨利）","不通過"),IF(AE44<0,"不通過","通過（現金流）")) | AI44: =IF(S44="未上市","未上市",IF(AH44="不通過","收支不足",S44)) | AJ44: =IF(Q44>0.5,"大於 50%",IF(Q44>0.25,"25%–50%",IF(Q44>=0,"0%–25%",IF(Q44>=-0.25,"0%～−25%",IF(Q44>=-0.5,"−25%～−50%","小於 −50%"))))) | AK44: 上檔空間 nanya_pcb/dist/20261025_南電模型_v0.1.xlsx Val!B42；投資建議：模型尚未補列，依 AI半導體 固定規則自算；級距：模型尚未補列，依 AI半導體 固定規則自算
A45: 2368 | B45: 金像電 | C45: =價值鏈!A8 | D45: 載板與 PCB | E45: 加權目標價（DCF 50%＋Comparable 50%） | F45: 1267.217 | G45: gce/dist/20261025_金像電模型_v0.1.xlsx Val!B40 | J45: 559.0154 | K45: gce/dist/20261025_金像電模型_v0.1.xlsx Val!D23 | N45: =價格!H45 | O45: =MIN(F45,H45) | P45: =MIN(J45,L45) | Q45: 0.13651752 | R45: =P45/N45-1 | S45: =IF(Q45>0.5,"強力買進",IF(Q45>0.25,"買進",IF(Q45>=-0.25,"中立",IF(Q45>=-0.5,"放空","強力放空")))) | V45: 12.4 ／ 14.6 ／ 24.6 | W45: DCF 目標價 1,203.1（Val!B24）；Comparable 目標價 1,331.4（Val!B41）；市場共識目標價 1,554.0（Val!B42，外部、僅供對照）；價格帶 C～A 情境 DCF 559.0～1,723.4 | Z45: =IF(ISNUMBER(價格!C45),價格!H45/價格!C45-1,"") | AA45: =IF(Z45="","",IF(ABS(Z45)>0.2,"模型尚未反映期間變化","")) | AB45: 淨利 | AC45: PL 頁各情境模型年度淨利（不含實績） | AD45: 19 個情境年度淨利（不含實績），全部為正 | AE45: 777.56399 | AF45: 19.697729 | AG45: [Derived] gce/dist/20261025_金像電模型_v0.1.xlsx PL!D12…PL!J38 | AH45: =IF(AB45="淨利",IF(AF45>0,"通過（淨利）","不通過"),IF(AE45<0,"不通過","通過（現金流）")) | AI45: =IF(S45="未上市","未上市",IF(AH45="不通過","收支不足",S45)) | AJ45: =IF(Q45>0.5,"大於 50%",IF(Q45>0.25,"25%–50%",IF(Q45>=0,"0%–25%",IF(Q45>=-0.25,"0%～−25%",IF(Q45>=-0.5,"−25%～−50%","小於 −50%"))))) | AK45: 上檔空間 gce/dist/20261025_金像電模型_v0.1.xlsx Val!B43；投資建議：模型尚未補列，依 AI半導體 固定規則自算；級距：模型尚未補列，依 AI半導體 固定規則自算
A46: 300476 | B46: 勝宏科技 | C46: =價值鏈!A8 | D46: 載板與 PCB | E46: 加權目標價（DCF 50%＋Comparable 50%） | F46: 322.84376 | G46: victory_giant/dist/20261025_勝宏科技模型_v0.1.xlsx Val!B39 | J46: 98.54908 | K46: victory_giant/dist/20261025_勝宏科技模型_v0.1.xlsx Val!D23 | N46: =價格!H46 | O46: =MIN(F46,H46) | P46: =MIN(J46,L46) | Q46: 0.75955831 | R46: =P46/N46-1 | S46: =IF(Q46>0.5,"強力買進",IF(Q46>0.25,"買進",IF(Q46>=-0.25,"中立",IF(Q46>=-0.5,"放空","強力放空")))) | V46: 10.3 ／ 12.7 ／ 16.9 | W46: DCF 目標價 202.7（Val!B24）；Comparable 目標價 443.0（Val!B40）；市場共識目標價 388.3（Val!B41，外部、僅供對照）；價格帶 C～A 情境 DCF 98.5～287.4 | Z46: =IF(ISNUMBER(價格!C46),價格!H46/價格!C46-1,"") | AA46: =IF(Z46="","",IF(ABS(Z46)>0.2,"模型尚未反映期間變化","")) | AB46: 淨利 | AC46: PL 頁各情境模型年度淨利（不含實績） | AD46: 17 個情境年度淨利（不含實績），全部為正 | AE46: 253.13753 | AF46: 6.5441925 | AG46: [Derived] victory_giant/dist/20261025_勝宏科技模型_v0.1.xlsx PL!D12…PL!J38 | AH46: =IF(AB46="淨利",IF(AF46>0,"通過（淨利）","不通過"),IF(AE46<0,"不通過","通過（現金流）")) | AI46: =IF(S46="未上市","未上市",IF(AH46="不通過","收支不足",S46)) | AJ46: =IF(Q46>0.5,"大於 50%",IF(Q46>0.25,"25%–50%",IF(Q46>=0,"0%–25%",IF(Q46>=-0.25,"0%～−25%",IF(Q46>=-0.5,"−25%～−50%","小於 −50%"))))) | AK46: 上檔空間 victory_giant/dist/20261025_勝宏科技模型_v0.1.xlsx Val!B42；投資建議：模型尚未補列，依 AI半導體 固定規則自算；級距：模型尚未補列，依 AI半導體 固定規則自算
A47: ASML | B47: ASML | C47: =價值鏈!A12 | D47: 設備與材料 | E47: 加權目標價（DCF 50%＋Comparable 50%） | F47: 1126.4934 | G47: asml/dist/20261025_ASML模型_v0.2.xlsx Val!B115 | J47: 506.03768 | K47: asml/dist/20261025_ASML模型_v0.2.xlsx Val!D99 | N47: =價格!H47 | O47: =MIN(F47,H47) | P47: =MIN(J47,L47) | Q47: -0.19947885 | R47: =P47/N47-1 | S47: =IF(Q47>0.5,"強力買進",IF(Q47>0.25,"買進",IF(Q47>=-0.25,"中立",IF(Q47>=-0.5,"放空","強力放空")))) | T47: =1829.12787571104/N47-1 | U47: 舊法：規則值情境加權價（參考，Val!B6） | V47: 21.7 ／ 25.4 ／ 34.1 | W47: DCF 目標價 836.8（Val!B100）；Comparable 目標價 1,416.2（Val!B116）；市場共識目標價 2,108.0（Val!B117，外部、僅供對照）；價格帶 C～A 情境 DCF 506.0～1,218.9 | Z47: =IF(ISNUMBER(價格!C47),價格!H47/價格!C47-1,"") | AA47: =IF(Z47="","",IF(ABS(Z47)>0.2,"模型尚未反映期間變化","")) | AB47: 淨利 | AC47: PL 頁各情境模型年度淨利（不含實績） | AD47: 10 個情境年度淨利（不含實績），全部為正 | AE47: 199.63913 | AF47: 15.434426 | AG47: [Derived] asml/dist/20261025_ASML模型_v0.2.xlsx PL!D12…PL!G34 | AH47: =IF(AB47="淨利",IF(AF47>0,"通過（淨利）","不通過"),IF(AE47<0,"不通過","通過（現金流）")) | AI47: =IF(S47="未上市","未上市",IF(AH47="不通過","收支不足",S47)) | AJ47: =IF(Q47>0.5,"大於 50%",IF(Q47>0.25,"25%–50%",IF(Q47>=0,"0%–25%",IF(Q47>=-0.25,"0%～−25%",IF(Q47>=-0.5,"−25%～−50%","小於 −50%"))))) | AK47: 上檔空間 asml/dist/20261025_ASML模型_v0.2.xlsx Val!B118；投資建議：模型尚未補列，依 AI半導體 固定規則自算；級距：模型尚未補列，依 AI半導體 固定規則自算
A48: AMAT | B48: Applied Materials | C48: =價值鏈!A12 | D48: 設備與材料 | E48: 加權目標價（DCF 50%＋Comparable 50%） | F48: 351.97251 | G48: amat/dist/20261025_應用材料模型_v0.2.xlsx Val!B136 | J48: 160.76982 | K48: amat/dist/20261025_應用材料模型_v0.2.xlsx Val!D121 | N48: =價格!H48 | O48: =MIN(F48,H48) | P48: =MIN(J48,L48) | Q48: -0.066979893 | R48: =P48/N48-1 | S48: =IF(Q48>0.5,"強力買進",IF(Q48>0.25,"買進",IF(Q48>=-0.25,"中立",IF(Q48>=-0.5,"放空","強力放空")))) | T48: =309.834449680392/N48-1 | U48: 舊法：規則值情境加權價（參考，Val!B47） | V48: 19.0 ／ 21.4 ／ 27.0 | W48: DCF 目標價 252.9（Val!B122）；Comparable 目標價 451.0（Val!B137）；市場共識目標價 627.8（Val!B138，外部、僅供對照）；價格帶 C～A 情境 DCF 160.8～355.1 | Z48: =IF(ISNUMBER(價格!C48),價格!H48/價格!C48-1,"") | AA48: =IF(Z48="","",IF(ABS(Z48)>0.2,"模型尚未反映期間變化","")) | AB48: 淨利 | AC48: PL 頁各情境模型年度淨利（不含實績） | AD48: 10 個情境年度淨利（不含實績），全部為正 | AE48: 130460.75 | AF48: 10179.92 | AG48: [Derived] amat/dist/20261025_應用材料模型_v0.2.xlsx PL!D11…PL!G31 | AH48: =IF(AB48="淨利",IF(AF48>0,"通過（淨利）","不通過"),IF(AE48<0,"不通過","通過（現金流）")) | AI48: =IF(S48="未上市","未上市",IF(AH48="不通過","收支不足",S48)) | AJ48: =IF(Q48>0.5,"大於 50%",IF(Q48>0.25,"25%–50%",IF(Q48>=0,"0%–25%",IF(Q48>=-0.25,"0%～−25%",IF(Q48>=-0.5,"−25%～−50%","小於 −50%"))))) | AK48: 上檔空間 amat/dist/20261025_應用材料模型_v0.2.xlsx Val!B139；投資建議：模型尚未補列，依 AI半導體 固定規則自算；級距：模型尚未補列，依 AI半導體 固定規則自算
A49: LRCX | B49: Lam Research | C49: =價值鏈!A12 | D49: 設備與材料 | E49: 加權目標價（DCF 50%＋Comparable 50%） | F49: 202.85999 | G49: lrcx/dist/20261025_科林研發模型_v0.2.xlsx Val!B128 | J49: 85.760344 | K49: lrcx/dist/20261025_科林研發模型_v0.2.xlsx Val!D113 | N49: =價格!H49 | O49: =MIN(F49,H49) | P49: =MIN(J49,L49) | Q49: -0.11838334 | R49: =P49/N49-1 | S49: =IF(Q49>0.5,"強力買進",IF(Q49>0.25,"買進",IF(Q49>=-0.25,"中立",IF(Q49>=-0.5,"放空","強力放空")))) | T49: =154.25592051976/N49-1 | U49: 舊法：規則值情境加權價（參考，Val!B6） | V49: 21.5 ／ 23.0 ／ 26.3 | W49: DCF 目標價 146.9（Val!B114）；Comparable 目標價 258.8（Val!B129）；市場共識目標價 364.0（Val!B130，外部、僅供對照）；價格帶 C～A 情境 DCF 85.8～204.7 | Z49: =IF(ISNUMBER(價格!C49),價格!H49/價格!C49-1,"") | AA49: =IF(Z49="","",IF(ABS(Z49)>0.2,"模型尚未反映期間變化","")) | AB49: 淨利 | AC49: PL 頁各情境模型年度淨利（不含實績） | AD49: 7 個情境年度淨利（不含實績），全部為正 | AE49: 84.684075 | AF49: 9.3026246 | AG49: [Derived] lrcx/dist/20261025_科林研發模型_v0.2.xlsx PL!E11…PL!G31 | AH49: =IF(AB49="淨利",IF(AF49>0,"通過（淨利）","不通過"),IF(AE49<0,"不通過","通過（現金流）")) | AI49: =IF(S49="未上市","未上市",IF(AH49="不通過","收支不足",S49)) | AJ49: =IF(Q49>0.5,"大於 50%",IF(Q49>0.25,"25%–50%",IF(Q49>=0,"0%–25%",IF(Q49>=-0.25,"0%～−25%",IF(Q49>=-0.5,"−25%～−50%","小於 −50%"))))) | AK49: 上檔空間 lrcx/dist/20261025_科林研發模型_v0.2.xlsx Val!B131；投資建議：模型尚未補列，依 AI半導體 固定規則自算；級距：模型尚未補列，依 AI半導體 固定規則自算
A50: KLAC | B50: KLA | C50: =價值鏈!A12 | D50: 設備與材料 | E50: 加權目標價（DCF 50%＋Comparable 50%） | F50: 121.38128 | G50: klac/dist/20261025_科磊模型_v0.2.xlsx Val!B129 | J50: 57.675705 | K50: klac/dist/20261025_科磊模型_v0.2.xlsx Val!D113 | N50: =價格!H50 | O50: =MIN(F50,H50) | P50: =MIN(J50,L50) | Q50: -0.16639462 | R50: =P50/N50-1 | S50: =IF(Q50>0.5,"強力買進",IF(Q50>0.25,"買進",IF(Q50>=-0.25,"中立",IF(Q50>=-0.5,"放空","強力放空")))) | T50: =102.08226284068/N50-1 | U50: 舊法：規則值情境加權價（參考，Val!B6） | V50: 22.9 ／ 24.7 ／ 28.3 | W50: DCF 目標價 94.1（Val!B114）；Comparable 目標價 148.6（Val!B130）；市場共識目標價 232.4（Val!B131，外部、僅供對照）；價格帶 C～A 情境 DCF 57.7～131.3 | Z50: =IF(ISNUMBER(價格!C50),價格!H50/價格!C50-1,"") | AA50: =IF(Z50="","",IF(ABS(Z50)>0.2,"模型尚未反映期間變化","")) | AB50: 淨利 | AC50: PL 頁各情境模型年度淨利（不含實績） | AD50: 9 個情境年度淨利（不含實績），全部為正 | AE50: 66658.653 | AF50: 6143.6897 | AG50: [Derived] klac/dist/20261025_科磊模型_v0.2.xlsx PL!E12…PL!G34 | AH50: =IF(AB50="淨利",IF(AF50>0,"通過（淨利）","不通過"),IF(AE50<0,"不通過","通過（現金流）")) | AI50: =IF(S50="未上市","未上市",IF(AH50="不通過","收支不足",S50)) | AJ50: =IF(Q50>0.5,"大於 50%",IF(Q50>0.25,"25%–50%",IF(Q50>=0,"0%–25%",IF(Q50>=-0.25,"0%～−25%",IF(Q50>=-0.5,"−25%～−50%","小於 −50%"))))) | AK50: 上檔空間 klac/dist/20261025_科磊模型_v0.2.xlsx Val!B132；投資建議：模型尚未補列，依 AI半導體 固定規則自算；級距：模型尚未補列，依 AI半導體 固定規則自算
A51: 042700 | B51: Hanmi | C51: =價值鏈!A12 | D51: 設備與材料 | E51: 加權目標價（DCF 50%＋Comparable 50%） | F51: 48379.327 | G51: hanmi/dist/20261025_韓美半導體模型_v0.2.1.xlsx Val!B111 | J51: 16072.833 | K51: hanmi/dist/20261025_韓美半導體模型_v0.2.1.xlsx Val!D96 | N51: =價格!H51 | O51: =MIN(F51,H51) | P51: =MIN(J51,L51) | Q51: -0.74334574 | R51: =P51/N51-1 | S51: =IF(Q51>0.5,"強力買進",IF(Q51>0.25,"買進",IF(Q51>=-0.25,"中立",IF(Q51>=-0.5,"放空","強力放空")))) | T51: =64078.0210298826/N51-1 | U51: 舊法：規則值情境加權價（參考，Val!B6） | V51: 79.8 ／ 64.4 ／ 93.6 | W51: DCF 目標價 27,779.9（Val!B97）；Comparable 目標價 68,978.7（Val!B112）；市場共識目標價 271,429.0（Val!B113，外部、僅供對照）；價格帶 C～A 情境 DCF 16,072.8～36,052.3 | Z51: =IF(ISNUMBER(價格!C51),價格!H51/價格!C51-1,"") | AA51: =IF(Z51="","",IF(ABS(Z51)>0.2,"模型尚未反映期間變化","")) | AB51: 淨利 | AC51: PL 頁各情境模型年度淨利（不含實績） | AD51: 8 個情境年度淨利（不含實績），全部為正 | AE51: 18743.412 | AF51: 1335.389 | AG51: [Derived] hanmi/dist/20261025_韓美半導體模型_v0.2.1.xlsx PL!D11…PL!G31 | AH51: =IF(AB51="淨利",IF(AF51>0,"通過（淨利）","不通過"),IF(AE51<0,"不通過","通過（現金流）")) | AI51: =IF(S51="未上市","未上市",IF(AH51="不通過","收支不足",S51)) | AJ51: =IF(Q51>0.5,"大於 50%",IF(Q51>0.25,"25%–50%",IF(Q51>=0,"0%–25%",IF(Q51>=-0.25,"0%～−25%",IF(Q51>=-0.5,"−25%～−50%","小於 −50%"))))) | AK51: 上檔空間 hanmi/dist/20261025_韓美半導體模型_v0.2.1.xlsx Val!B114；投資建議：模型尚未補列，依 AI半導體 固定規則自算；級距：模型尚未補列，依 AI半導體 固定規則自算
A52: TER | B52: Teradyne | C52: =價值鏈!A12 | D52: 設備與材料 | E52: 加權目標價（DCF 50%＋Comparable 50%） | F52: 312.24975 | G52: ter/dist/20261025_泰瑞達模型_v0.1.xlsx Val!B126 | J52: 153.84187 | K52: ter/dist/20261025_泰瑞達模型_v0.1.xlsx Val!D110 | N52: =價格!H52 | O52: =MIN(F52,H52) | P52: =MIN(J52,L52) | Q52: 0.011007756 | R52: =P52/N52-1 | S52: =IF(Q52>0.5,"強力買進",IF(Q52>0.25,"買進",IF(Q52>=-0.25,"中立",IF(Q52>=-0.5,"放空","強力放空")))) | T52: =388.636638757835/N52-1 | U52: 舊法：規則值情境加權價（參考，Val!B82） | V52: 18.6 ／ 21.8 ／ 25.1 | W52: DCF 目標價 219.3（Val!B111）；Comparable 目標價 405.2（Val!B127）；市場共識目標價 446.5（Val!B128，外部、僅供對照）；價格帶 C～A 情境 DCF 153.8～286.3 | Z52: =IF(ISNUMBER(價格!C52),價格!H52/價格!C52-1,"") | AA52: =IF(Z52="","",IF(ABS(Z52)>0.2,"模型尚未反映期間變化","")) | AB52: 淨利 | AC52: PL 頁各情境模型年度淨利（不含實績） | AD52: 10 個情境年度淨利（不含實績），全部為正 | AE52: 22484.167 | AF52: 1385.276 | AG52: [Derived] ter/dist/20261025_泰瑞達模型_v0.1.xlsx PL!D12…PL!G34 | AH52: =IF(AB52="淨利",IF(AF52>0,"通過（淨利）","不通過"),IF(AE52<0,"不通過","通過（現金流）")) | AI52: =IF(S52="未上市","未上市",IF(AH52="不通過","收支不足",S52)) | AJ52: =IF(Q52>0.5,"大於 50%",IF(Q52>0.25,"25%–50%",IF(Q52>=0,"0%–25%",IF(Q52>=-0.25,"0%～−25%",IF(Q52>=-0.5,"−25%～−50%","小於 −50%"))))) | AK52: 上檔空間 ter/dist/20261025_泰瑞達模型_v0.1.xlsx Val!B129；投資建議：模型尚未補列，依 AI半導體 固定規則自算；級距：模型尚未補列，依 AI半導體 固定規則自算
A53: BESI | B53: BESI | C53: =價值鏈!A12 | D53: 設備與材料 | E53: 加權目標價（DCF 50%＋Comparable 50%） | F53: 133.69492 | G53: besi/dist/20261025_BESI模型_v0.1.xlsx Val!B112 | J53: 44.818175 | K53: besi/dist/20261025_BESI模型_v0.1.xlsx Val!D96 | N53: =價格!H53 | O53: =MIN(F53,H53) | P53: =MIN(J53,L53) | Q53: -0.078601529 | R53: =P53/N53-1 | S53: =IF(Q53>0.5,"強力買進",IF(Q53>0.25,"買進",IF(Q53>=-0.25,"中立",IF(Q53>=-0.5,"放空","強力放空")))) | T53: =188.684289175905/N53-1 | U53: 舊法：規則值情境加權價（參考，Val!B6） | V53: 15.5 ／ 22.0 ／ 44.6 | W53: DCF 目標價 97.7（Val!B97）；Comparable 目標價 169.7（Val!B113）；市場共識目標價 270.6（Val!B114，外部、僅供對照）；價格帶 C～A 情境 DCF 44.8～158.4 | Z53: =IF(ISNUMBER(價格!C53),價格!H53/價格!C53-1,"") | AA53: =IF(Z53="","",IF(ABS(Z53)>0.2,"模型尚未反映期間變化","")) | AB53: 淨利 | AC53: PL 頁各情境模型年度淨利（不含實績） | AD53: 10 個情境年度淨利（不含實績），全部為正 | AE53: 4792.3946 | AF53: 262.50145 | AG53: [Derived] besi/dist/20261025_BESI模型_v0.1.xlsx PL!D11…PL!G31 | AH53: =IF(AB53="淨利",IF(AF53>0,"通過（淨利）","不通過"),IF(AE53<0,"不通過","通過（現金流）")) | AI53: =IF(S53="未上市","未上市",IF(AH53="不通過","收支不足",S53)) | AJ53: =IF(Q53>0.5,"大於 50%",IF(Q53>0.25,"25%–50%",IF(Q53>=0,"0%–25%",IF(Q53>=-0.25,"0%～−25%",IF(Q53>=-0.5,"−25%～−50%","小於 −50%"))))) | AK53: 上檔空間 besi/dist/20261025_BESI模型_v0.1.xlsx Val!B115；投資建議：模型尚未補列，依 AI半導體 固定規則自算；級距：模型尚未補列，依 AI半導體 固定規則自算
A54: 6315 | B54: TOWA | C54: =價值鏈!A12 | D54: 設備與材料 | E54: 加權目標價（DCF 50%＋Comparable 50%） | F54: 1725.845 | G54: towa/dist/20261025_TOWA模型_v0.1.xlsx Val!B39 | J54: 759.56796 | K54: towa/dist/20261025_TOWA模型_v0.1.xlsx Val!D23 | N54: =價格!H54 | O54: =MIN(F54,H54) | P54: =MIN(J54,L54) | Q54: -0.12304624 | R54: =P54/N54-1 | S54: =IF(Q54>0.5,"強力買進",IF(Q54>0.25,"買進",IF(Q54>=-0.25,"中立",IF(Q54>=-0.5,"放空","強力放空")))) | T54: =1478.20786366597/N54-1 | U54: 舊法：規則值情境加權價（參考，Val!B120） | V54: 17.1 ／ 20.3 ／ 27.6 | W54: DCF 目標價 1,015.4（Val!B24）；Comparable 目標價 2,436.3（Val!B40）；市場共識目標價 3,300.0（Val!B41，外部、僅供對照）；價格帶 C～A 情境 DCF 759.6～1,353.8 | Z54: =IF(ISNUMBER(價格!C54),價格!H54/價格!C54-1,"") | AA54: =IF(Z54="","",IF(ABS(Z54)>0.2,"模型尚未反映期間變化","")) | AB54: 淨利 | AC54: PL 頁各情境模型年度淨利（不含實績） | AD54: 10 個情境年度淨利（不含實績），全部為正 | AE54: 69.959242 | AF54: 5.3531077 | AG54: [Derived] towa/dist/20261025_TOWA模型_v0.1.xlsx PL!D14…PL!G42 | AH54: =IF(AB54="淨利",IF(AF54>0,"通過（淨利）","不通過"),IF(AE54<0,"不通過","通過（現金流）")) | AI54: =IF(S54="未上市","未上市",IF(AH54="不通過","收支不足",S54)) | AJ54: =IF(Q54>0.5,"大於 50%",IF(Q54>0.25,"25%–50%",IF(Q54>=0,"0%–25%",IF(Q54>=-0.25,"0%～−25%",IF(Q54>=-0.5,"−25%～−50%","小於 −50%"))))) | AK54: 上檔空間 towa/dist/20261025_TOWA模型_v0.1.xlsx Val!B42；投資建議：模型尚未補列，依 AI半導體 固定規則自算；級距：模型尚未補列，依 AI半導體 固定規則自算
A55: 7729 | B55: 東京精密 | C55: =價值鏈!A12 | D55: 設備與材料 | E55: 加權目標價（DCF 50%＋Comparable 50%） | F55: 19528.092 | G55: accretech/dist/20261025_東京精密模型_v0.1.xlsx Val!B40 | J55: 6136.3038 | K55: accretech/dist/20261025_東京精密模型_v0.1.xlsx Val!D23 | N55: =價格!H55 | O55: =MIN(F55,H55) | P55: =MIN(J55,L55) | Q55: 0.25825337 | R55: =P55/N55-1 | S55: =IF(Q55>0.5,"強力買進",IF(Q55>0.25,"買進",IF(Q55>=-0.25,"中立",IF(Q55>=-0.5,"放空","強力放空")))) | T55: =11632.8169386252/N55-1 | U55: 舊法：規則值情境加權價（參考，Val!B111） | V55: 14.4 ／ 18.7 ／ 27.6 | W55: DCF 目標價 10,189.2（Val!B24）；Comparable 目標價 28,867.0（Val!B41）；市場共識目標價 20,900.0（Val!B42，外部、僅供對照）；價格帶 C～A 情境 DCF 6,136.3～15,099.6 | Z55: =IF(ISNUMBER(價格!C55),價格!H55/價格!C55-1,"") | AA55: =IF(Z55="","",IF(ABS(Z55)>0.2,"模型尚未反映期間變化","")) | AB55: 淨利 | AC55: PL 頁各情境模型年度淨利（不含實績） | AD55: 10 個情境年度淨利（不含實績），全部為正 | AE55: 335.6547 | AF55: 22.17878 | AG55: [Derived] accretech/dist/20261025_東京精密模型_v0.1.xlsx PL!D12…PL!G34 | AH55: =IF(AB55="淨利",IF(AF55>0,"通過（淨利）","不通過"),IF(AE55<0,"不通過","通過（現金流）")) | AI55: =IF(S55="未上市","未上市",IF(AH55="不通過","收支不足",S55)) | AJ55: =IF(Q55>0.5,"大於 50%",IF(Q55>0.25,"25%–50%",IF(Q55>=0,"0%–25%",IF(Q55>=-0.25,"0%～−25%",IF(Q55>=-0.5,"−25%～−50%","小於 −50%"))))) | AK55: 上檔空間 accretech/dist/20261025_東京精密模型_v0.1.xlsx Val!B43；投資建議：模型尚未補列，依 AI半導體 固定規則自算；級距：模型尚未補列，依 AI半導體 固定規則自算
A56: 2317 | B56: 鴻海 | C56: =價值鏈!A10 | D56: 伺服器組裝 | E56: 加權目標價（DCF 50%＋Comparable 50%） | F56: 349.91729 | G56: foxconn/dist/20261025_鴻海模型_v0.2.xlsx Val!B120 | J56: 209.88596 | K56: foxconn/dist/20261025_鴻海模型_v0.2.xlsx Val!D104 | N56: =價格!H56 | O56: =MIN(F56,H56) | P56: =MIN(J56,L56) | Q56: 0.42823383 | R56: =P56/N56-1 | S56: =IF(Q56>0.5,"強力買進",IF(Q56>0.25,"買進",IF(Q56>=-0.25,"中立",IF(Q56>=-0.5,"放空","強力放空")))) | T56: =261.429965980011/N56-1 | U56: 舊法：規則值情境加權價（參考，Val!B38） | V56: 7.8 ／ 8.8 ／ 10.4 | W56: DCF 目標價 290.3（Val!B105）；Comparable 目標價 409.5（Val!B121）；市場共識目標價 347.4（Val!B122，外部、僅供對照）；價格帶 C～A 情境 DCF 209.9～347.2 | Z56: =IF(ISNUMBER(價格!C56),價格!H56/價格!C56-1,"") | AA56: =IF(Z56="","",IF(ABS(Z56)>0.2,"模型尚未反映期間變化","")) | AB56: 淨利 | AC56: PL 頁各情境模型年度淨利（不含實績） | AD56: 8 個情境年度淨利（不含實績），全部為正 | AE56: 3063.3195 | AF56: 275.25709 | AG56: [Derived] foxconn/dist/20261025_鴻海模型_v0.2.xlsx PL!D13…PL!G39 | AH56: =IF(AB56="淨利",IF(AF56>0,"通過（淨利）","不通過"),IF(AE56<0,"不通過","通過（現金流）")) | AI56: =IF(S56="未上市","未上市",IF(AH56="不通過","收支不足",S56)) | AJ56: =IF(Q56>0.5,"大於 50%",IF(Q56>0.25,"25%–50%",IF(Q56>=0,"0%–25%",IF(Q56>=-0.25,"0%～−25%",IF(Q56>=-0.5,"−25%～−50%","小於 −50%"))))) | AK56: 上檔空間 foxconn/dist/20261025_鴻海模型_v0.2.xlsx Val!B123；投資建議：模型尚未補列，依 AI半導體 固定規則自算；級距：模型尚未補列，依 AI半導體 固定規則自算
A57: 3231 | B57: 緯創 | C57: =價值鏈!A10 | D57: 伺服器組裝 | E57: 加權目標價（DCF 50%＋Comparable 50%） | F57: 355.13356 | G57: wistron/dist/20261025_緯創模型_v0.1.xlsx Val!B39 | J57: 252.6854 | K57: wistron/dist/20261025_緯創模型_v0.1.xlsx Val!D23 | N57: =價格!H57 | O57: =MIN(F57,H57) | P57: =MIN(J57,L57) | Q57: 0.86912402 | R57: =P57/N57-1 | S57: =IF(Q57>0.5,"強力買進",IF(Q57>0.25,"買進",IF(Q57>=-0.25,"中立",IF(Q57>=-0.5,"放空","強力放空")))) | V57: 5.7 ／ 7.0 ／ 9.2 | W57: DCF 目標價 397.0（Val!B24）；Comparable 目標價 313.3（Val!B40）；市場共識目標價 268.7（Val!B41，外部、僅供對照）；價格帶 C～A 情境 DCF 252.7～495.5 | Z57: =IF(ISNUMBER(價格!C57),價格!H57/價格!C57-1,"") | AA57: =IF(Z57="","",IF(ABS(Z57)>0.2,"模型尚未反映期間變化","")) | AB57: 淨利 | AC57: PL 頁各情境模型年度淨利（不含實績） | AD57: 17 個情境年度淨利（不含實績），全部為正 | AE57: 1686.2207 | AF57: 59.670705 | AG57: [Derived] wistron/dist/20261025_緯創模型_v0.1.xlsx PL!D13…PL!J41 | AH57: =IF(AB57="淨利",IF(AF57>0,"通過（淨利）","不通過"),IF(AE57<0,"不通過","通過（現金流）")) | AI57: =IF(S57="未上市","未上市",IF(AH57="不通過","收支不足",S57)) | AJ57: =IF(Q57>0.5,"大於 50%",IF(Q57>0.25,"25%–50%",IF(Q57>=0,"0%–25%",IF(Q57>=-0.25,"0%～−25%",IF(Q57>=-0.5,"−25%～−50%","小於 −50%"))))) | AK57: 上檔空間 wistron/dist/20261025_緯創模型_v0.1.xlsx Val!B42；投資建議：模型尚未補列，依 AI半導體 固定規則自算；級距：模型尚未補列，依 AI半導體 固定規則自算
A58: 6669 | B58: 緯穎 | C58: =價值鏈!A10 | D58: 伺服器組裝 | E58: 加權目標價（DCF 50%＋Comparable 50%） | F58: 3314.4233 | G58: wiwynn/dist/20261025_緯穎模型_v0.1.xlsx Val!B39 | J58: 2411.9938 | K58: wiwynn/dist/20261025_緯穎模型_v0.1.xlsx Val!D23 | N58: =價格!H58 | O58: =MIN(F58,H58) | P58: =MIN(J58,L58) | Q58: 0.80131702 | R58: =P58/N58-1 | S58: =IF(Q58>0.5,"強力買進",IF(Q58>0.25,"買進",IF(Q58>=-0.25,"中立",IF(Q58>=-0.5,"放空","強力放空")))) | V58: 6.3 ／ 7.4 ／ 9.3 | W58: DCF 目標價 3,755.8（Val!B24）；Comparable 目標價 2,873.0（Val!B40）；市場共識目標價 2,845.7（Val!B41，外部、僅供對照）；價格帶 C～A 情境 DCF 2,412.0～4,736.9 | Z58: =IF(ISNUMBER(價格!C58),價格!H58/價格!C58-1,"") | AA58: =IF(Z58="","",IF(ABS(Z58)>0.2,"模型尚未反映期間變化","")) | AB58: 淨利 | AC58: PL 頁各情境模型年度淨利（不含實績） | AD58: 17 個情境年度淨利（不含實績），全部為正 | AE58: 2434.8169 | AF58: 77.032449 | AG58: [Derived] wiwynn/dist/20261025_緯穎模型_v0.1.xlsx PL!D12…PL!J38 | AH58: =IF(AB58="淨利",IF(AF58>0,"通過（淨利）","不通過"),IF(AE58<0,"不通過","通過（現金流）")) | AI58: =IF(S58="未上市","未上市",IF(AH58="不通過","收支不足",S58)) | AJ58: =IF(Q58>0.5,"大於 50%",IF(Q58>0.25,"25%–50%",IF(Q58>=0,"0%–25%",IF(Q58>=-0.25,"0%～−25%",IF(Q58>=-0.5,"−25%～−50%","小於 −50%"))))) | AK58: 上檔空間 wiwynn/dist/20261025_緯穎模型_v0.1.xlsx Val!B42；投資建議：模型尚未補列，依 AI半導體 固定規則自算；級距：模型尚未補列，依 AI半導體 固定規則自算
A59: DELL | B59: Dell | C59: =價值鏈!A10 | D59: 伺服器組裝 | E59: 加權目標價（DCF 50%＋Comparable 50%） | F59: 366.64755 | G59: dell/dist/20261025_戴爾模型_v0.1.xlsx Val!B39 | J59: 288.03826 | K59: dell/dist/20261025_戴爾模型_v0.1.xlsx Val!D23 | N59: =價格!H59 | O59: =MIN(F59,H59) | P59: =MIN(J59,L59) | Q59: -0.19672345 | R59: =P59/N59-1 | S59: 中立 | V59: 15.1 ／ 15.1 ／ 15.1 | W59: DCF 目標價 411.9（Val!B24）；Comparable 目標價 321.4（Val!B40）；市場共識目標價 593.0（Val!B41，外部、僅供對照）；價格帶 C～A 情境 DCF 288.0～510.8 | Z59: =IF(ISNUMBER(價格!C59),價格!H59/價格!C59-1,"") | AA59: =IF(Z59="","",IF(ABS(Z59)>0.2,"模型尚未反映期間變化","")) | AB59: 淨利 | AC59: PL 頁各情境模型年度淨利（不含實績） | AD59: 14 個情境年度淨利（不含實績），全部為正 | AE59: 245.48951 | AF59: 12.099776 | AG59: [Derived] dell/dist/20261025_戴爾模型_v0.1.xlsx PL!D13…PL!I41 | AH59: =IF(AB59="淨利",IF(AF59>0,"通過（淨利）","不通過"),IF(AE59<0,"不通過","通過（現金流）")) | AI59: =IF(S59="未上市","未上市",IF(AH59="不通過","收支不足",S59)) | AJ59: 0%～−25% | AK59: 上檔空間 dell/dist/20261025_戴爾模型_v0.1.xlsx Val!B42；投資建議 dell/dist/20261025_戴爾模型_v0.1.xlsx Val!B49；級距 dell/dist/20261025_戴爾模型_v0.1.xlsx Val!B48
A60: SMCI | B60: Supermicro | C60: =價值鏈!A10 | D60: 伺服器組裝 | E60: 加權目標價（DCF 50%＋Comparable 50%） | F60: 76.588493 | G60: smci/dist/20261025_美超微模型_v0.1.xlsx Val!B39 | J60: 31.419993 | K60: smci/dist/20261025_美超微模型_v0.1.xlsx Val!D23 | N60: =價格!H60 | O60: =MIN(F60,H60) | P60: =MIN(J60,L60) | Q60: 1.3250909 | R60: =P60/N60-1 | S60: =IF(Q60>0.5,"強力買進",IF(Q60>0.25,"買進",IF(Q60>=-0.25,"中立",IF(Q60>=-0.5,"放空","強力放空")))) | V60: 3.8 ／ 5.4 ／ 9.2 | W60: DCF 目標價 78.0（Val!B24）；Comparable 目標價 75.2（Val!B40）；市場共識目標價 43.3（Val!B41，外部、僅供對照）；價格帶 C～A 情境 DCF 31.4～128.1 | Z60: =IF(ISNUMBER(價格!C60),價格!H60/價格!C60-1,"") | AA60: =IF(Z60="","",IF(ABS(Z60)>0.2,"模型尚未反映期間變化","")) | AB60: 淨利 | AC60: PL 頁各情境模型年度淨利（不含實績） | AD60: 18 個情境年度淨利（不含實績），全部為正 | AE60: 87.289581 | AF60: 2.012016 | AG60: [Derived] smci/dist/20261025_美超微模型_v0.1.xlsx PL!E12…PL!J38 | AH60: =IF(AB60="淨利",IF(AF60>0,"通過（淨利）","不通過"),IF(AE60<0,"不通過","通過（現金流）")) | AI60: =IF(S60="未上市","未上市",IF(AH60="不通過","收支不足",S60)) | AJ60: =IF(Q60>0.5,"大於 50%",IF(Q60>0.25,"25%–50%",IF(Q60>=0,"0%–25%",IF(Q60>=-0.25,"0%～−25%",IF(Q60>=-0.5,"−25%～−50%","小於 −50%"))))) | AK60: 上檔空間 smci/dist/20261025_美超微模型_v0.1.xlsx Val!B42；投資建議：模型尚未補列，依 AI半導體 固定規則自算；級距：模型尚未補列，依 AI半導體 固定規則自算
A61: 3017 | B61: 奇鋐 | C61: =價值鏈!A9 | D61: 電源與散熱 | E61: 加權目標價（DCF 50%＋Comparable 50%） | F61: 3955.894 | G61: avc/dist/20261025_奇鋐模型_v0.2.xlsx Val!B119 | J61: 2016.199 | K61: avc/dist/20261025_奇鋐模型_v0.2.xlsx Val!D104 | N61: =價格!H61 | O61: =MIN(F61,H61) | P61: =MIN(J61,L61) | Q61: 0.25783592 | R61: =P61/N61-1 | S61: =IF(Q61>0.5,"強力買進",IF(Q61>0.25,"買進",IF(Q61>=-0.25,"中立",IF(Q61>=-0.5,"放空","強力放空")))) | T61: =2025.40760731771/N61-1 | U61: 舊法：規則值情境加權價（參考，Val!B75） | V61: 15.0 ／ 17.7 ／ 21.9 | W61: DCF 目標價 3,027.2（Val!B105）；Comparable 目標價 4,884.6（Val!B120）；市場共識目標價 4,130.0（Val!B121，外部、僅供對照）；價格帶 C～A 情境 DCF 2,016.2～3,706.7 | Z61: =IF(ISNUMBER(價格!C61),價格!H61/價格!C61-1,"") | AA61: =IF(Z61="","",IF(ABS(Z61)>0.2,"模型尚未反映期間變化","")) | AB61: 淨利 | AC61: PL 頁各情境模型年度淨利（不含實績） | AD61: 8 個情境年度淨利（不含實績），全部為正 | AE61: 547.0034 | AF61: 41.592309 | AG61: [Derived] avc/dist/20261025_奇鋐模型_v0.2.xlsx PL!D14…PL!G42 | AH61: =IF(AB61="淨利",IF(AF61>0,"通過（淨利）","不通過"),IF(AE61<0,"不通過","通過（現金流）")) | AI61: =IF(S61="未上市","未上市",IF(AH61="不通過","收支不足",S61)) | AJ61: =IF(Q61>0.5,"大於 50%",IF(Q61>0.25,"25%–50%",IF(Q61>=0,"0%–25%",IF(Q61>=-0.25,"0%～−25%",IF(Q61>=-0.5,"−25%～−50%","小於 −50%"))))) | AK61: 上檔空間 avc/dist/20261025_奇鋐模型_v0.2.xlsx Val!B122；投資建議：模型尚未補列，依 AI半導體 固定規則自算；級距：模型尚未補列，依 AI半導體 固定規則自算
A62: 2301 | B62: 光寶 | C62: =價值鏈!A9 | D62: 電源與散熱 | E62: 加權目標價（DCF 50%＋Comparable 50%） | F62: 423.95267 | G62: liteon/dist/20261025_光寶模型_v0.1.xlsx Val!B40 | J62: 120.89637 | K62: liteon/dist/20261025_光寶模型_v0.1.xlsx Val!D23 | N62: =價格!H62 | O62: =MIN(F62,H62) | P62: =MIN(J62,L62) | Q62: 0.65930596 | R62: =P62/N62-1 | S62: =IF(Q62>0.5,"強力買進",IF(Q62>0.25,"買進",IF(Q62>=-0.25,"中立",IF(Q62>=-0.5,"放空","強力放空")))) | V62: 8.5 ／ 12.2 ／ 18.7 | W62: DCF 目標價 318.7（Val!B24）；Comparable 目標價 529.2（Val!B41）；市場共識目標價 314.2（Val!B42，外部、僅供對照）；價格帶 C～A 情境 DCF 120.9～530.8 | Z62: =IF(ISNUMBER(價格!C62),價格!H62/價格!C62-1,"") | AA62: =IF(Z62="","",IF(ABS(Z62)>0.2,"模型尚未反映期間變化","")) | AB62: 淨利 | AC62: PL 頁各情境模型年度淨利（不含實績） | AD62: 19 個情境年度淨利（不含實績），全部為正 | AE62: 1037.716 | AF62: 20.477547 | AG62: [Derived] liteon/dist/20261025_光寶模型_v0.1.xlsx PL!D12…PL!J38 | AH62: =IF(AB62="淨利",IF(AF62>0,"通過（淨利）","不通過"),IF(AE62<0,"不通過","通過（現金流）")) | AI62: =IF(S62="未上市","未上市",IF(AH62="不通過","收支不足",S62)) | AJ62: =IF(Q62>0.5,"大於 50%",IF(Q62>0.25,"25%–50%",IF(Q62>=0,"0%–25%",IF(Q62>=-0.25,"0%～−25%",IF(Q62>=-0.5,"−25%～−50%","小於 −50%"))))) | AK62: 上檔空間 liteon/dist/20261025_光寶模型_v0.1.xlsx Val!B43；投資建議：模型尚未補列，依 AI半導體 固定規則自算；級距：模型尚未補列，依 AI半導體 固定規則自算
A63: 3324 | B63: 雙鴻 | C63: =價值鏈!A9 | D63: 電源與散熱 | E63: 加權目標價（DCF 50%＋Comparable 50%） | F63: 2768.7737 | G63: auras/dist/20261025_雙鴻模型_v0.1.xlsx Val!B39 | J63: 700.05948 | K63: auras/dist/20261025_雙鴻模型_v0.1.xlsx Val!D23 | N63: =價格!H63 | O63: =MIN(F63,H63) | P63: =MIN(J63,L63) | Q63: 1.035863 | R63: =P63/N63-1 | S63: =IF(Q63>0.5,"強力買進",IF(Q63>0.25,"買進",IF(Q63>=-0.25,"中立",IF(Q63>=-0.5,"放空","強力放空")))) | V63: 7.2 ／ 11.5 ／ 22.2 | W63: DCF 目標價 1,978.6（Val!B24）；Comparable 目標價 3,558.9（Val!B40）；市場共識目標價 1,523.0（Val!B41，外部、僅供對照）；價格帶 C～A 情境 DCF 700.1～3,222.7 | Z63: =IF(ISNUMBER(價格!C63),價格!H63/價格!C63-1,"") | AA63: =IF(Z63="","",IF(ABS(Z63)>0.2,"模型尚未反映期間變化","")) | AB63: 淨利 | AC63: PL 頁各情境模型年度淨利（不含實績） | AD63: 10 個情境年度淨利（不含實績），全部為正 | AE63: 106.78514 | AF63: 4.9238411 | AG63: [Derived] auras/dist/20261025_雙鴻模型_v0.1.xlsx PL!D14…PL!G42 | AH63: =IF(AB63="淨利",IF(AF63>0,"通過（淨利）","不通過"),IF(AE63<0,"不通過","通過（現金流）")) | AI63: =IF(S63="未上市","未上市",IF(AH63="不通過","收支不足",S63)) | AJ63: =IF(Q63>0.5,"大於 50%",IF(Q63>0.25,"25%–50%",IF(Q63>=0,"0%–25%",IF(Q63>=-0.25,"0%～−25%",IF(Q63>=-0.5,"−25%～−50%","小於 −50%"))))) | AK63: 上檔空間 auras/dist/20261025_雙鴻模型_v0.1.xlsx Val!B42；投資建議：模型尚未補列，依 AI半導體 固定規則自算；級距：模型尚未補列，依 AI半導體 固定規則自算
A64: 3653 | B64: 健策 | C64: =價值鏈!A9 | D64: 電源與散熱 | E64: 加權目標價（DCF 50%＋Comparable 50%） | F64: 3889.0673 | G64: jentech/dist/20261025_健策模型_v0.1.xlsx Val!B40 | J64: 1371.9595 | K64: jentech/dist/20261025_健策模型_v0.1.xlsx Val!D23 | N64: =價格!H64 | O64: =MIN(F64,H64) | P64: =MIN(J64,L64) | Q64: -0.35929699 | R64: =P64/N64-1 | S64: 放空 | V64: 23.7 ／ 36.4 ／ 59.8 | W64: DCF 目標價 3,242.1（Val!B24）；Comparable 目標價 4,536.0（Val!B41）；市場共識目標價 7,204.0（Val!B42，外部、僅供對照）；價格帶 C～A 情境 DCF 1,372.0～5,003.3 | Z64: =IF(ISNUMBER(價格!C64),價格!H64/價格!C64-1,"") | AA64: =IF(Z64="","",IF(ABS(Z64)>0.2,"模型尚未反映期間變化","")) | AB64: 淨利 | AC64: PL 頁各情境模型年度淨利（不含實績） | AD64: 19 個情境年度淨利（不含實績），全部為正 | AE64: 568.28094 | AF64: 10.344206 | AG64: [Derived] jentech/dist/20261025_健策模型_v0.1.xlsx PL!D13…PL!J41 | AH64: =IF(AB64="淨利",IF(AF64>0,"通過（淨利）","不通過"),IF(AE64<0,"不通過","通過（現金流）")) | AI64: =IF(S64="未上市","未上市",IF(AH64="不通過","收支不足",S64)) | AJ64: −25%～−50% | AK64: 上檔空間 jentech/dist/20261025_健策模型_v0.1.xlsx Val!B43；投資建議 jentech/dist/20261025_健策模型_v0.1.xlsx Val!B46；級距 jentech/dist/20261025_健策模型_v0.1.xlsx Val!B45

Sheet 地圖節點
A1: 次產業 | B1: 次產業內優先序 | C1: 公司 | D1: 代號 | E1: 掛牌 | F1: 角色 | G1: 供應鏈重要性（1–3） | H1: 市場地位 | I1: 標記 | J1: 研究狀態
A2: 運算 | B2: 1 | C2: NVIDIA | D2: NVDA | E2: 美 | F2: GPU、NVLink、整櫃系統 | G2: 1 | H2: AI 加速器金額份額 CY2027 約 75–82%（本專案推導） | I2: [D] | J2: 有模型
A3: 運算 | B3: 2 | C3: Broadcom | D3: AVGO | E3: 美 | F3: 客製 ASIC（TPU、MTIA、OpenAI 等 XPU）＋交換器 ASIC | G3: 1 | H3: 客製 ASIC 龍頭：占客製 ASIC 80–85%（JPMorgan）；AI 半導體營收 FY2026 約 US$58B（公司） | I3: [IP] | J3: 有模型
A4: 運算 | B4: 3 | C4: AMD | D4: AMD | E4: 美 | F4: GPU（MI450／Helios 整櫃） | G4: 2 | H4: AI 加速器金額份額 CY2027 約 3–6%（本專案推導）；2027 資料中心「超過一倍」（公司） | I4: [D]／[IP] | J4: 有模型
A5: 運算 | B5: 4 | C5: 聯發科 | D5: 2454 | E5: 台 | F5: TPU 部分世代的設計夥伴 | G5: 2 | H5: Google TPU 合作（媒體報導） | I5: [IP] | J5: 有模型
A6: 運算 | B6: 5 | C6: Marvell | D6: MRVL | E6: 美 | F6: 客製 ASIC（Trainium 部分世代）、光通訊 DSP | G6: 2 | H6: 光 DSP 主要供應商之一 | I6: [判斷] | J6: 有模型
A7: 運算 | B7: 6 | C7: 世芯-KY | D7: 3661 | E7: 台 | F7: ASIC 設計服務（Trainium） | G7: 2 | H7: 雲端客製晶片設計服務 | I7: [判斷] | J7: 有模型
A8: 運算 | B8: 7 | C8: 創意 | D8: 3443 | E8: 台 | F8: ASIC 設計服務（台積電體系） | G8: 3 | H8: 台積電轉投資的設計服務廠 | I8: [判斷] | J8: 有模型
A9: 記憶體 | B9: 1 | C9: SK 海力士 | D9: 000660 | E9: 韓 | F9: HBM、DRAM | G9: 1 | H9: 2026 HBM 市占 52–55%（本專案） | I9: [D] | J9: 有模型
A10: 記憶體 | B10: 2 | C10: 三星電子 | D10: 005930 | E10: 韓 | F10: HBM、DRAM、NAND | G10: 1 | H10: 2026 HBM 市占 28–32%（本專案） | I10: [D] | J10: 有模型
A11: 記憶體 | B11: 3 | C11: 美光 | D11: MU | E11: 美 | F11: HBM、DRAM、NAND | G11: 1 | H11: 2026 HBM 市占 18–20%（本專案） | I11: [D] | J11: 有模型
A12: 記憶體 | B12: 4 | C12: Kioxia | D12: 285A | E12: 日 | F12: NAND（企業級 SSD） | G12: 3 | H12: NAND 主要廠之一；10-23 曾因「不能由既有層推得」排除，15:59 已取消該關卡 | I12: [判斷] | J12: 有模型
... A61: 電源與散熱 | B61: 7 | C61: ABB | D61: ABBN | E61: 瑞士 | F61: 電網與機房配電 | G61: 3 | H61: 機房／電網層級；與「電力與機房」另案的邊界待定 | I61: [判斷] | J61: 待建（邊界待定）
A62: AI 雲端平台 | C62: Amazon | D62: AMZN | E62: 美 | G62: 1 | H62: AWS 為最大公有雲；自研 Trainium | I62: [判斷] | J62: 有模型
A63: AI 雲端平台 | C63: Microsoft | D63: MSFT | E63: 美 | G63: 1 | H63: Azure 第二大公有雲；OpenAI 主要算力夥伴 | I63: [判斷] | J63: 有模型
A64: AI 雲端平台 | C64: Alphabet | D64: GOOGL | E64: 美 | G64: 1 | H64: TPU＋Gemini 垂直整合；雲端第三 | I64: [判斷] | J64: 有模型
A65: AI 雲端平台 | C65: Oracle | D65: ORCL | E65: 美 | G65: 2 | H65: OCI 規模較小；Stargate 主要承建方，客戶集中 | I65: [判斷] | J65: 有模型
A66: Neocloud（GPU 租賃） | C66: CoreWeave | D66: CRWV | E66: 美 | G66: 2 | H66: 最大 neocloud；客戶集中於 Microsoft、OpenAI | I66: [判斷] | J66: 有模型
A67: Neocloud（GPU 租賃） | C67: Nebius | D67: NBIS | E67: 美 | G67: 2 | H67: 歐洲為主的 neocloud；Microsoft 長約 | I67: [判斷] | J67: 有模型
A68: Neocloud（GPU 租賃） | C68: WhiteFiber | D68: WYFI | E68: 美 | G68: 3 | H68: 小型 neocloud＋託管 | I68: [判斷] | J68: 有模型
A69: AI 模型商 | C69: OpenAI | D69: OpenAI | E69: 未上市 | G69: 1 | H69: ChatGPT 與 API 用量最大的模型商；算力承諾最大（本專案 OpenAI 模型） | I69: [判斷] | J69: 有模型
A70: AI 模型商 | C70: Anthropic | D70: Anthropic | E70: 未上市 | G70: 1 | H70: 企業與程式開發用途為主的前沿模型商（本專案 Anthropic 模型） | I70: [判斷] | J70: 有模型
A71: AI 模型商 | C71: MiniMax | D71: 00100 | E71: 港 | G71: 3 | H71: 中國第二梯隊模型商；多模態、海外營收占比高 | I71: [判斷] | J71: 有模型
A72: AI 模型商 | C72: 智譜 | D72: 02513 | E72: 港 | G72: 3 | H72: 中國第二梯隊模型商；政企本地化部署 | I72: [判斷] | J72: 有模型
