Workbook

Sheet README
A1: SanDisk（SNDK US）收支與估值模型 v0.1（AI 半導體 Project：記憶體——NAND） 2026-10-25
A2: 模型命題：SanDisk 是純 NAND 公司，盈餘由 NAND 合約價循環與 AI 推論帶動的企業級 SSD 位元決定，產能與 Kioxia 合資（Flash Ventures 49.9%）；問題是 2026 年的高價能維持多久（FY2028 起三情境分歧），以及現價隱含的倍數是否已反映循環見頂。
A3: 重點觀察
A4: ="1. 加權目標價 "&TEXT(Val!B49,"#,##0")&" 美元，相對現價 "&TEXT(px,"#,##0.00")&"（2026-10-23 收盤）"&TEXT(Val!B52,"+0.0%;−0.0%")&"，主因是 Comparable 偏低：同業前瞻 P/B 中位數 "&TEXT(Val!B32,"0.00")&"x，而共識目標價隱含約 "&TEXT(cons_tp/((cons_bv28+cons_bv29)/2),"0.00")&"x（倍數因素 "&TEXT(Val!B59,"+0%;−0%")&"）；DCF 目標價 "&TEXT(Val!B24,"#,##0")&" 高於 Comparable "&TEXT(Val!B34,"#,##0")&"。" -> 1. 加權目標價 953 美元，相對現價 1,238.03（2026-10-23 收盤）−23.0%，主因是 Comparable 偏低：同業前瞻 P/B 中位數 1.49x，而共識目標價隱含約 3.56x（倍數因素 +139%）；DCF 目標價 1,139 高於 Comparable 767。
A5: ="2. 本模型 FY2027 EPS（A）"&TEXT(PL!E10,"0")&" 美元，比共識 217.4 "&TEXT(PL!E10/cons_eps27-1,"+0%;−0%")&"；B、C 到 FY2028 才分歧（"&TEXT(PL!F20,"0")&"／"&TEXT(PL!F30,"0")&"），因為 2026Q3–2027Q2 的價格與位元三情境幾乎相同（markets/nand）。追蹤：2026-10-29 FQ1 FY27 財報與 FQ2 指引。" -> 2. 本模型 FY2027 EPS（A）263 美元，比共識 217.4 +21%；B、C 到 FY2028 才分歧（220／195），因為 2026Q3–2027Q2 的價格與位元三情境幾乎相同（markets/nand）。追蹤：2026-10-29 FQ1 FY27 財報與 FQ2 指引。
A6: ="3. 最敏感的是價格而非成本：2027 起季價 ±20% 使 FY2028 EPS（A）變動 "&TEXT(Sens!H5,"+0%;−0%")&"／"&TEXT(Sens!H6,"+0%;−0%")&"，成本年降 ±4pt 只有約 ±1%；情境 C 的 FY2029 毛利率降到 "&TEXT(PL!G26,"0%")&"（CY2028 NAND 價格跌回約 2025 年水準）。追蹤：TrendForce 每季初的 NAND 合約價與 Kioxia 2026-10-30 財報（合資群位元與價格）。" -> 3. 最敏感的是價格而非成本：2027 起季價 ±20% 使 FY2028 EPS（A）變動 −28%／+31%，成本年降 ±4pt 只有約 ±1%；情境 C 的 FY2029 毛利率降到 49%（CY2028 NAND 價格跌回約 2025 年水準）。追蹤：TrendForce 每季初的 NAND 合約價與 Kioxia 2026-10-30 財報（合資群位元與價格）。
A7: ="投資建議："&Val!B55&"（依上檔空間固定規則；上檔空間："&TEXT(Val!B52,"+0.0%;−0.0%")&"，級距："&Val!B54&"）" -> 投資建議：中立（依上檔空間固定規則；上檔空間：−23.0%，級距：0%～−25%）
A9: 驅動因子 → 推導量（因果方向：左邊決定右邊）
A10: Units｜markets/nand 成品：SanDisk 季度營收（市場營收 × 份額；同字母情境）與位元（季度出貨 × 份額）
A11: PL 區塊｜營收＝市場層 × 公司口徑係數；營業成本＝位元 × 每 EB 成本（FQ1 FY27 以指引毛利率校準，之後每年 × (1 − 成本年降)）；營業費用＝固定（指引校準）＋變動
A12: PL 區塊｜淨利＝（營業利益＋淨現金收益）×（1 − 稅率）；自由現金流＝淨利＋折舊 − 資本支出（含合資群分攤）；買回＝回饋比例 × FCF → 股數 → EPS、每股淨值
A13: Val｜第 0 節目標價＝DCF（FY2027–FY2032＋永續）與 Comparable（同業前瞻 P/B × 約 2028 年底每股淨值）各半；第 5–6 節目前倍數、十年倍數規則值（美光 Analogy）
A15: 會計年度：約 6 月底結束（FY2027＝2026-07～2027-06 ≈ CY2026Q3–CY2027Q2）。前瞻 EPS 依月份調整：12 個月後（約 2027-10）的未來 12 月＝8／12 FY2028＋4／12 FY2029。
A16: 情境：A＝順利、B＝平平、C＝不如預期，讀 markets/nand 同字母（價格＝markets/memory NAND_S；顆數＝SCEN_UNITS；合資群份額年變動）；公司特有變數（每位元成本年降 14%／12%／10%）A 最有利、C 最不利。FY2027 的 B、C EPS 略高於 A：上游 markets/memory 的 B、C 價格路徑 2027 上半年漲幅較大、下半年才回落（行業情境，不在公司層調整）。FY2030 起為收斂法，非驅動因子推導。
A17: 十年歷史不足：2025-02 自 WDC 分拆上市，十年 P/B、P/E 與十年平均淨利率以美光為 Analogy。本版未做先驗，無 Andy 合理 P/E 對照。

Sheet In
A1: In — 輸入（藍字；基準欄 E，低 D、高 F）。金額：十億美元（$B）；每股：美元；股數：百萬股。每個輸入附標記與來源；找不到者寫「未找到」
A2: 標記：Verified（公司文件、交易所資料）／Interested-party（寫明是誰、立場）／Analogy（寫明對照與差異）／Assumed（給低／高區間）／Derived（寫明換算）。SemiAnalysis 未使用
A3: 鍵 | B3: 項目 | C3: 單位 | D3: 低 | E3: 基準 | F3: 高 | G3: 標記 | H3: 來源1 | I3: 來源2／說明
A4: A. 季度實績與公司指引（$B；EPS 美元）
A5: q1_rev | B5: FQ1 FY26 營收 | C5: $B | E5: 2.308 | G5: Verified | H5: SanDisk FQ2 FY26 新聞稿（8-K，2026-01-29） | I5: FY26 合計 20.248（FQ4 新聞稿）
A6: q1_gm | B6: FQ1 FY26 GAAP 毛利率 | C6: % | E6: 0.298 | G6: Verified | H6: SanDisk FQ2 FY26 新聞稿（8-K，2026-01-29）
A7: q1_op | B7: FQ1 FY26 GAAP 營業利益 | C7: $B | E7: 0.176 | G7: Verified | H7: SanDisk FQ2 FY26 新聞稿（8-K，2026-01-29）
A8: q1_ni | B8: FQ1 FY26 GAAP 淨利 | C8: $B | E8: 0.112 | G8: Verified | H8: SanDisk FQ2 FY26 新聞稿（8-K，2026-01-29）
A9: q1_eps | B9: FQ1 FY26 GAAP 稀釋 EPS | C9: USD | E9: 0.75 | G9: Verified | H9: SanDisk FQ2 FY26 新聞稿（8-K，2026-01-29）
A10: q2_rev | B10: FQ2 FY26 營收 | C10: $B | E10: 3.025 | G10: Verified | H10: SanDisk FQ2 FY26 新聞稿（8-K，2026-01-29） | I10: FY26 合計 20.248（FQ4 新聞稿）
A11: q2_gm | B11: FQ2 FY26 GAAP 毛利率 | C11: % | E11: 0.509 | G11: Verified | H11: SanDisk FQ2 FY26 新聞稿（8-K，2026-01-29）
A12: q2_op | B12: FQ2 FY26 GAAP 營業利益 | C12: $B | E12: 1.065 | G12: Verified | H12: SanDisk FQ2 FY26 新聞稿（8-K，2026-01-29）
A13: q2_ni | B13: FQ2 FY26 GAAP 淨利 | C13: $B | E13: 0.803 | G13: Verified | H13: SanDisk FQ2 FY26 新聞稿（8-K，2026-01-29）
A14: q2_eps | B14: FQ2 FY26 GAAP 稀釋 EPS | C14: USD | E14: 5.15 | G14: Verified | H14: SanDisk FQ2 FY26 新聞稿（8-K，2026-01-29）
A15: q3_rev | B15: FQ3 FY26 營收 | C15: $B | E15: 5.95 | G15: Verified | H15: SanDisk FQ4 FY26 新聞稿（8-K，2026-08-05） | I15: FY26 合計 20.248（FQ4 新聞稿）
A16: q3_gm | B16: FQ3 FY26 GAAP 毛利率 | C16: % | E16: 0.784 | G16: Verified | H16: SanDisk FQ4 FY26 新聞稿（8-K，2026-08-05）
A17: q3_op | B17: FQ3 FY26 GAAP 營業利益 | C17: $B | E17: 4.111 | G17: Verified | H17: SanDisk FQ4 FY26 新聞稿（8-K，2026-08-05）
A18: q3_ni | B18: FQ3 FY26 GAAP 淨利 | C18: $B | E18: 3.615 | G18: Verified | H18: SanDisk FQ4 FY26 新聞稿（8-K，2026-08-05）
A19: q3_eps | B19: FQ3 FY26 GAAP 稀釋 EPS | C19: USD | E19: 23.03 | G19: Verified | H19: SanDisk FQ4 FY26 新聞稿（8-K，2026-08-05）
A20: q4_rev | B20: FQ4 FY26 營收 | C20: $B | E20: 8.965 | G20: Verified | H20: SanDisk FQ4 FY26 新聞稿（8-K，2026-08-05） | I20: FY26 合計 20.248（FQ4 新聞稿）
A21: q4_gm | B21: FQ4 FY26 GAAP 毛利率 | C21: % | E21: 0.846 | G21: Verified | H21: SanDisk FQ4 FY26 新聞稿（8-K，2026-08-05）
A22: q4_op | B22: FQ4 FY26 GAAP 營業利益 | C22: $B | E22: 7.037 | G22: Verified | H22: SanDisk FQ4 FY26 新聞稿（8-K，2026-08-05）
A23: q4_ni | B23: FQ4 FY26 GAAP 淨利 | C23: $B | E23: 6.903 | G23: Verified | H23: SanDisk FQ4 FY26 新聞稿（8-K，2026-08-05）
A24: q4_eps | B24: FQ4 FY26 GAAP 稀釋 EPS | C24: USD | E24: 43.97 | G24: Verified | H24: SanDisk FQ4 FY26 新聞稿（8-K，2026-08-05）
A25: a26_rev | B25: FY2026 營收（2025-07～2026-07-03） | C25: $B | E25: 20.248 | G25: Verified | H25: SanDisk FQ4 FY26 新聞稿（8-K，2026-08-05）：資料中心 5.153、邊緣 12.160、消費 2.935 | I25: MarketScreener 同值
A26: a26_ni | B26: FY2026 GAAP 淨利 | C26: $B | E26: 11.433 | G26: Verified | H26: SanDisk FQ4 FY26 新聞稿（8-K，2026-08-05） | I26: MarketScreener 同值
A27: a26_eps | B27: FY2026 GAAP 稀釋 EPS | C27: USD | E27: 73.76 | G27: Verified | H27: SanDisk FQ4 FY26 新聞稿（8-K，2026-08-05）（non-GAAP 70.88） | I27: MarketScreener 73.76
A28: a26_op | B28: FY2026 GAAP 營業利益 | C28: $B | E28: 12.389 | G28: Verified | H28: SanDisk FQ4 FY26 新聞稿（8-K，2026-08-05）
A29: a26_gm | B29: FY2026 GAAP 毛利率 | C29: % | E29: 0.715 | G29: Verified | H29: SanDisk FQ4 FY26 新聞稿（8-K，2026-08-05）
A30: a25_rev | B30: FY2025 營收 | C30: $B | E30: 7.355 | G30: Verified | H30: SanDisk FQ4 FY26 新聞稿（8-K，2026-08-05）（前期欄） | I30: MarketScreener 7,355
A31: a25_ni | B31: FY2025 GAAP 淨利 | C31: $B | E31: -1.641 | G31: Verified | H31: SanDisk FQ4 FY26 新聞稿（8-K，2026-08-05）（含商譽減損） | I31: MarketScreener −1,641
A32: a25_eps | B32: FY2025 GAAP 稀釋 EPS | C32: USD | E32: -11.32 | G32: Verified | H32: SanDisk FQ4 FY26 新聞稿（8-K，2026-08-05）
A33: g_rev | B33: 公司指引：FQ1 FY27（2026-07～09）營收中值 | C33: $B | D33: 10.3 | E33: 10.55 | F33: 10.8 | G33: Interested-party | H33: SanDisk FQ4 FY26 新聞稿（8-K，2026-08-05）：$10.3–10.8B | I33: 公司指引（立場：公司）；市場層 markets/nand 以此推 SanDisk 2026Q3 份額，因此本模型 FQ1 FY27 營收＝指引（恆等式）
A34: g_gm | B34: 公司指引：FQ1 FY27 GAAP 毛利率中值 | C34: % | D34: 0.83 | E34: 0.84 | F34: 0.849 | G34: Interested-party | H34: SanDisk FQ4 FY26 新聞稿（8-K，2026-08-05）：GAAP 83.0–84.9%（non-GAAP 83.0–85.0%） | I34: 用來校準單位成本（FQ1 FY27 為基準季）
A35: g_ox | B35: 公司指引：FQ1 FY27 GAAP 營業費用中值 | C35: $B | D35: 0.574 | E35: 0.594 | F35: 0.614 | G35: Interested-party | H35: SanDisk FQ4 FY26 新聞稿（8-K，2026-08-05）：GAAP $574–614M（non-GAAP $520–540M）
A36: g_eps | B36: 公司指引：FQ1 FY27 non-GAAP 稀釋 EPS 中值 | C36: USD | D36: 44 | E36: 45 | F36: 46 | G36: Interested-party | H36: SanDisk FQ4 FY26 新聞稿（8-K，2026-08-05）：$44.00–46.00；稀釋股數約 155 百萬股、non-GAAP 稅率 15%
A37: g_sh | B37: 公司指引：FQ1 FY27 稀釋股數 | C37: 百萬股 | E37: 155 | G37: Interested-party | H37: SanDisk FQ4 FY26 新聞稿（8-K，2026-08-05）
A38: B. 成本、費用、稅（公司特有；隨情境者 A 最有利、C 最不利）
A39: cd_A | B39: 情境 A：每位元成本年降 | C39: % | D39: 0.1 | E39: 0.14 | F39: 0.18 | G39: Assumed | H39: A：BiCS8→BiCS10（332 層，密度約 +59%）如期量產，每位元成本年降約 14% | I39: 以 FQ1 FY27 指引毛利率校準的單位成本為起點；歷史每位元成本年降約 15–20%（Analogy：產業製程轉換）
A40: cd_B | B40: 情境 B：每位元成本年降 | C40: % | D40: 0.08 | E40: 0.12 | F40: 0.16 | G40: Assumed | H40: B：轉換略延後 | I40: 同上
A41: cd_C | B41: 情境 C：每位元成本年降 | C41: % | D41: 0.06 | E41: 0.1 | F41: 0.14 | G41: Assumed | H41: C：需求轉弱、稼動率下降，固定成本攤提使年降縮小 | I41: 同上
A42: ox_var | B42: 營業費用變動率（÷ 營收） | C42: % | D42: 0.005 | E42: 0.01 | F42: 0.02 | G42: Assumed | H42: FY26 GAAP 營業費用 2.083 ÷ 營收 20.248 ≈ 10%，但多為固定；FQ4 0.545 ÷ 8.965 ≈ 6% | I42: 固定部分＝指引營業費用 − 變動率 × 指引營收（Derived）
A43: ox_g | B43: 營業費用固定部分年增 | C43: % | D43: 0.05 | E43: 0.1 | F43: 0.15 | G43: Assumed | H43: 研發（BiCS10、企業級 SSD 控制晶片）與獎金
A44: tax | B44: 有效稅率 | C44: % | D44: 0.12 | E44: 0.15 | F44: 0.2 | G44: Interested-party | H44: 公司指引 non-GAAP 稅率 15%（FQ1 FY27） | I44: GAAP 稅率未指引
A45: rf | B45: 淨現金收益率 | C45: % | D45: 0.03 | E45: 0.04 | F45: 0.05 | G45: Assumed | H45: 美元短期利率
A46: sd_k | B46: 公司營收 ÷ 市場層 SanDisk 營收（TrendForce 口徑） | C46: x | E46: =a26_rev/SUM(Units!E4:H4) -> 0.9994077 | G46: Derived | H46: FY2026 營收 ÷ 市場層 2025Q3–2026Q2 SanDisk 營收（Units 頁） | I46: 約 1.0：TrendForce 以公司財報為準
A47: C. 資本、股東回饋（FY2026 年底＝2026-07-03）
A48: eq0 | B48: FY2026 年底股東權益 | C48: $B | E48: 15.736 | G48: Verified | H48: SanDisk FQ4 FY26 新聞稿（8-K，2026-08-05）
A49: nc0 | B49: FY2026 年底淨現金（現金 − 負債） | C49: $B | E49: 4.762 | G49: Verified | H49: SanDisk FQ4 FY26 新聞稿（8-K，2026-08-05）：現金 4.762、負債 0（已全數清償）
A50: sh0 | B50: 流通股數（FY2026 年底後） | C50: 百萬股 | E50: 146.42 | G50: Verified | H50: stockanalysis 統計頁（2026-10-25）：146.42M | I50: MarketScreener FY2027 股數 146.419M；FQ4 已買回 $4.524B
A51: dil | B51: 稀釋股數 − 流通股數 | C51: 百萬股 | E51: =g_sh-sh0 -> 8.58 | G51: Derived | H51: 公司指引稀釋約 155 − 流通 146.42 | I51: 各年固定
A52: da_y | B52: 折舊攤銷（公司本身；年） | C52: $B | D52: 0.12 | E52: 0.16 | F52: 0.25 | G52: Verified／Assumed | H52: SanDisk FQ4 FY26 新聞稿（8-K，2026-08-05）：FY26 0.149 | I52: 合資廠折舊在晶圓成本（營業成本）內
A53: cap_r | B53: 資本支出 ÷ 營收（含合資群分攤；FY2027 起） | C53: % | D53: 0.03 | E53: 0.06 | F53: 0.09 | G53: Interested-party | H53: Motley Fool 2026-08-29：SanDisk FY27 毛資本支出約營收 6%（含與 Kioxia 合資的分攤） | I53: FY26 毛資本支出 0.562（其中合資分攤 0.519；SanDisk FQ4 FY26 簡報，markets/equipment In 頁）
A54: payout | B54: 買回 ÷ 自由現金流 | C54: % | D54: 0.3 | E54: 0.5 | F54: 0.8 | G54: Assumed | H54: SanDisk FQ4 FY26 新聞稿（8-K，2026-08-05）：新增 $14B 授權（合計剩餘 $15.5B）；FQ4 買回 $4.524B | I54: 無現金股利
A55: px | B55: 股價（2026-10-23 收盤） | C55: USD | E55: 1238.03 | G55: Verified | H55: stockanalysis 歷史股價（2026-10-23 收盤 1,238.03） | I55: MarketScreener 參考價 1,238.03（同日）；10-09 為 1,581.82
A56: bb_px | B56: 未來買回均價 | C56: USD | E56: =px -> 1238.03 | G56: Assumed | H56: ＝現價
A57: D. 共識與對帳參考（只放 Recon，不作校準）
A58: cons_rev27 | B58: 共識營收 FY2027 | C58: $B | D58: 43.4 | E58: 49.135 | F58: 53.2 | G58: Interested-party | H58: MarketScreener 預估頁（2026-10-25 擷取；頁面為 10-23 收盤；會計年度 6 月）：49,135；stockanalysis（21 位）平均 49.1、區間 43.4–53.2
A59: cons_rev28 | B59: 共識營收 FY2028 | C59: $B | E59: 58.436 | G59: Interested-party | H59: MarketScreener 預估頁（2026-10-25 擷取；頁面為 10-23 收盤；會計年度 6 月）
A60: cons_eps27 | B60: 共識 EPS FY2027 | C60: USD | D60: 186.97 | E60: 217.4 | F60: 238.36 | G60: Interested-party | H60: MarketScreener 預估頁（2026-10-25 擷取；頁面為 10-23 收盤；會計年度 6 月）：217.4；stockanalysis（21 位）non-GAAP 214.82、區間 186.97–238.36
A61: cons_eps28 | B61: 共識 EPS FY2028 | C61: USD | E61: 267.6 | G61: Interested-party | H61: MarketScreener 預估頁（2026-10-25 擷取；頁面為 10-23 收盤；會計年度 6 月）
A62: cons_eps29 | B62: 共識 EPS FY2029 | C62: USD | E62: 281.7 | G62: Interested-party | H62: MarketScreener 預估頁（2026-10-25 擷取；頁面為 10-23 收盤；會計年度 6 月）
A63: cons_bv27 | B63: 共識每股淨值 FY2027 年底（2027-06） | C63: USD | E63: 313.8 | G63: Interested-party | H63: MarketScreener 預估頁（2026-10-25 擷取；頁面為 10-23 收盤；會計年度 6 月）
A64: cons_bv28 | B64: 共識每股淨值 FY2028 年底（2028-06） | C64: USD | E64: 553.1 | G64: Interested-party | H64: MarketScreener 預估頁（2026-10-25 擷取；頁面為 10-23 收盤；會計年度 6 月）
A65: cons_bv29 | B65: 共識每股淨值 FY2029 年底（2029-06） | C65: USD | E65: 650.6 | G65: Interested-party | H65: MarketScreener 預估頁（2026-10-25 擷取；頁面為 10-23 收盤；會計年度 6 月）
A66: cons_ni27 | B66: 共識淨利 FY2027 | C66: $B | E66: 33.336 | G66: Interested-party | H66: MarketScreener 預估頁（2026-10-25 擷取；頁面為 10-23 收盤；會計年度 6 月）
A67: cons_ni28 | B67: 共識淨利 FY2028 | C67: $B | E67: 38.384 | G67: Interested-party | H67: MarketScreener 預估頁（2026-10-25 擷取；頁面為 10-23 收盤；會計年度 6 月）
A68: E. 目標價參數（黃底；Val 頁第 0 節 DCF＋Comparable 與收斂法用；Assumed 者 Andy 可改）
A69: tp_wA | B69: 目標價情境權重 A（A 順利／B 平平／C 不如預期） | C69: % | E69: 0.3 | G69: Assumed | H69: Andy 可改（工作單 2026-10-25 預設 A 0.3／B 0.5／C 0.2） | I69: 三者合計應為 100%
A70: tp_wB | B70: 目標價情境權重 B（A 順利／B 平平／C 不如預期） | C70: % | E70: 0.5 | G70: Assumed | H70: Andy 可改（工作單 2026-10-25 預設 A 0.3／B 0.5／C 0.2） | I70: 三者合計應為 100%
A71: tp_wC | B71: 目標價情境權重 C（A 順利／B 平平／C 不如預期） | C71: % | E71: 0.2 | G71: Assumed | H71: Andy 可改（工作單 2026-10-25 預設 A 0.3／B 0.5／C 0.2） | I71: 三者合計應為 100%
A72: tp_r | B72: 折現率（股東權益要求報酬；美、台、日、韓同一值） | C72: % | E72: 0.1 | G72: Assumed | H72: Andy 可改（工作單預設 10%） | I72: 記憶體循環股的盈餘波動大於一般大型股；依工作單不改值
A73: tp_g | B73: 長期成長率（永續；收斂法 B 的 FY2032 營收年增） | C73: % | E73: 0.04 | G73: Assumed | H73: Andy 可改（工作單預設 4%）
A74: tp_roe | B74: ROE（近年平均；FY2025–FY2026，上市不足三年） | C74: % | E74: =AVERAGE(-1.641/9.216,11.433/15.736) -> 0.27424534 | G74: Derived | H74: SanDisk FQ4 FY26 新聞稿（8-K，2026-08-05）：FY2025 淨利 −1.641 ÷ 權益 9.216、FY2026 11.433 ÷ 15.736 | I74: 2025-02 自 WDC 分拆上市，FY2024 以前為 WDC 快閃記憶體事業（無獨立權益）；只用兩年
A75: tp_w_dcf | B75: 目標價中 DCF 的權重；其餘為 Comparable | C75: % | E75: 0.5 | G75: Assumed | H75: Andy 可改（2026-10-25 11:53：DCF／Comparable 各半）
A76: nim10 | B76: 十年平均淨利率（Analogy：美光 FY2016–FY2025） | C76: % | E76: 0.14662864 | G76: Analogy | H76: micron/dist/20261025_美光模型_v0.4.xlsx｜In!E244 | I76: SanDisk 獨立上市不足十年（2025-02 分拆），以同為記憶體循環股的美光十年平均代替；差異：美光含 DRAM、HBM，NAND 純度低
A77: cyc_mA | B77: 循環中段係數：情境 A 淨利率收斂目標 ÷ 十年平均 | C77: x | E77: 1.2 | G77: Assumed | H77: 記憶體樣板預設 1.2（循環股收斂到循環中段，不延續高峰利潤率） | I77: Andy 可改
A78: cyc_mC | B78: 循環中段係數：情境 C 淨利率收斂目標 ÷ 十年平均 | C78: x | E78: 0.8 | G78: Assumed | H78: 記憶體樣板預設 0.8 | I78: Andy 可改
A79: fade_mA | B79: 情境 A：FY2032 淨利率收斂目標（循環中段：十年平均 × cyc_mA） | C79: % | E79: =nim10*cyc_mA -> 0.17595436 | G79: Derived | H79: 主串指示：循環產業 FY2030 後收斂用十年平均（記憶體樣板的循環中段） | I79: FY2030 起由 FY2029 淨利率線性收斂，FY2032 達到
A80: fade_mB | B80: 情境 B：FY2032 淨利率收斂目標（循環中段：＝十年平均） | C80: % | E80: =nim10 -> 0.14662864 | G80: Derived | H80: 主串指示：循環產業 FY2030 後收斂用十年平均（記憶體樣板的循環中段） | I80: FY2030 起由 FY2029 淨利率線性收斂，FY2032 達到
A81: fade_mC | B81: 情境 C：FY2032 淨利率收斂目標（循環中段：十年平均 × cyc_mC） | C81: % | E81: =nim10*cyc_mC -> 0.11730291 | G81: Derived | H81: 主串指示：循環產業 FY2030 後收斂用十年平均（記憶體樣板的循環中段） | I81: FY2030 起由 FY2029 淨利率線性收斂，FY2032 達到
A82: fade_gA | B82: 情境 A：FY2032 營收年增收斂目標（tp_g＋2pt） | C82: % | E82: =tp_g+0.02 -> 0.06 | G82: Assumed | H82: 工作單 2026-10-25 11:20 收斂法 | I82: FY2030 起由 FY2029 年增線性收斂
A83: fade_gB | B83: 情境 B：FY2032 營收年增收斂目標（＝tp_g） | C83: % | E83: =tp_g -> 0.04 | G83: Assumed | H83: 工作單 2026-10-25 11:20 收斂法 | I83: FY2030 起由 FY2029 年增線性收斂
A84: fade_gC | B84: 情境 C：FY2032 營收年增收斂目標（tp_g−2pt） | C84: % | E84: =tp_g-0.02 -> 0.02 | G84: Assumed | H84: 工作單 2026-10-25 11:20 收斂法 | I84: FY2030 起由 FY2029 年增線性收斂
A85: cons_tp | B85: 市場共識目標價（賣方平均；低／高＝最低／最高） | C85: USD | D85: 1000 | E85: 2144 | F85: 3600 | G85: Interested-party | H85: stockanalysis（S&P Global，25 位，2026-10-18 更新）：平均 2,144、中位數 2,150、區間 1,000–3,600 | I85: MarketScreener 25 位平均 2,173（10-09 收盤時）

Sheet Q
A1: Q — 季度實績（$B；EPS 美元）與公司指引。會計年度約 6 月底結束；FQ1＝7–9 月
A3: 項目 | B3: FQ1 FY26 | C3: FQ2 FY26 | D3: FQ3 FY26 | E3: FQ4 FY26 | F3: FY2026 | G3: FQ1 FY27 指引 | H3: 標記 | I3: 來源
A4: 營收 | B4: =q1_rev -> 2.308 | C4: =q2_rev -> 3.025 | D4: =q3_rev -> 5.95 | E4: =q4_rev -> 8.965 | F4: =SUM(B4:E4) -> 20.248 | G4: =g_rev -> 10.55 | H4: Verified | I4: SanDisk FQ2 FY26 新聞稿（8-K，2026-01-29）；SanDisk FQ4 FY26 新聞稿（8-K，2026-08-05）
A5: GAAP 毛利率 | B5: =q1_gm -> 0.298 | C5: =q2_gm -> 0.509 | D5: =q3_gm -> 0.784 | E5: =q4_gm -> 0.846 | F5: =SUMPRODUCT(B4:E4,B5:E5)/F4 -> 0.71496933 | G5: =g_gm -> 0.84 | H5: Verified | I5: SanDisk FQ2 FY26 新聞稿（8-K，2026-01-29）；SanDisk FQ4 FY26 新聞稿（8-K，2026-08-05）
A6: GAAP 營業利益 | B6: =q1_op -> 0.176 | C6: =q2_op -> 1.065 | D6: =q3_op -> 4.111 | E6: =q4_op -> 7.037 | F6: =SUM(B6:E6) -> 12.389 | H6: Verified | I6: SanDisk FQ2 FY26 新聞稿（8-K，2026-01-29）；SanDisk FQ4 FY26 新聞稿（8-K，2026-08-05）
A7: GAAP 淨利 | B7: =q1_ni -> 0.112 | C7: =q2_ni -> 0.803 | D7: =q3_ni -> 3.615 | E7: =q4_ni -> 6.903 | F7: =SUM(B7:E7) -> 11.433 | H7: Verified | I7: SanDisk FQ2 FY26 新聞稿（8-K，2026-01-29）；SanDisk FQ4 FY26 新聞稿（8-K，2026-08-05）
A8: GAAP 稀釋 EPS | B8: =q1_eps -> 0.75 | C8: =q2_eps -> 5.15 | D8: =q3_eps -> 23.03 | E8: =q4_eps -> 43.97 | F8: =a26_eps -> 73.76 | G8: =g_eps -> 45 | H8: Verified | I8: SanDisk FQ2 FY26 新聞稿（8-K，2026-01-29）；SanDisk FQ4 FY26 新聞稿（8-K，2026-08-05）
A9: 檢查：四季營收、淨利合計 − FY2026（應約為 0） | B9: =F4-a26_rev -> 0 | C9: =F7-a26_ni -> 0
A10: 季增：營收 | C10: =C4/B4-1 -> 0.31065858 | D10: =D4/C4-1 -> 0.96694215 | E10: =E4/D4-1 -> 0.50672269
A12: FQ1 FY27（2026-07～09）財報 2026-10-29 盤後公布（公司 2026-09-29 公告）；本版 FY2027 第一季＝市場層推導（營收等於公司指引中值，為恆等式）

Sheet Units
A1: Units — 市場層 markets/nand 成品的 SanDisk 季度營收與位元（三情境；唯讀抄錄，藍字）。來源：markets/nand/dist/20261025_NAND市場模型_v0.1.xlsx
A2: C..Z＝CY2025Q1..CY2030Q4；營收為 TrendForce 口徑（$B），位元為季度出貨 × 營收份額（EB）。合資群份額＝Kioxia＋SanDisk（與 kioxia/ 模型讀同一列）
A3: 項目 | B3: 單位 | C3: 2025Q1 | D3: 2025Q2 | E3: 2025Q3 | F3: 2025Q4 | G3: 2026Q1 | H3: 2026Q2 | I3: 2026Q3 | J3: 2026Q4 | K3: 2027Q1 | L3: 2027Q2 | M3: 2027Q3 | N3: 2027Q4 | O3: 2028Q1 | P3: 2028Q2 | Q3: 2028Q3 | R3: 2028Q4 | S3: 2029Q1 | T3: 2029Q2 | U3: 2029Q3 | V3: 2029Q4 | W3: 2030Q1 | X3: 2030Q2 | Y3: 2030Q3 | Z3: 2030Q4 | AA3: 來源
A4: SanDisk 營收（情境 A） | B4: $B | C4: 1.69 | D4: 1.9 | E4: 2.31 | F4: 3.03 | G4: 5.95 | H4: 8.97 | I4: 10.555884 | J4: 13.008548 | K4: 14.333827 | L4: 15.156177 | M4: 15.224421 | N4: 14.971015 | O4: 15.038425 | P4: 15.106138 | Q4: 15.174156 | R4: 15.242481 | S4: 15.369653 | T4: 15.654084 | U4: 15.943779 | V4: 16.238835 | W4: 15.878856 | X4: 15.891708 | Y4: 15.904571 | Z4: 15.917444 | AA4: markets/nand/dist/20261025_NAND市場模型_v0.1.xlsx｜Mkt!C44:Z44
A5: SanDisk 營收（情境 B） | B5: $B | C5: 1.69 | D5: 1.9 | E5: 2.31 | F5: 3.03 | G5: 5.95 | H5: 8.97 | I5: 10.555884 | J5: 13.008548 | K5: 14.444873 | L5: 15.579066 | M5: 14.825571 | N5: 12.540906 | O5: 8.7186957 | P5: 6.7713807 | Q5: 5.609597 | R5: 5.2280366 | S5: 5.7833132 | T5: 6.3632149 | U5: 6.8679068 | V5: 7.4126278 | W5: 7.165894 | X5: 7.1646076 | Y5: 7.1633215 | Z5: 7.1620355 | AA5: markets/nand/dist/20261025_NAND市場模型_v0.1.xlsx｜Mkt!C92:Z92
A6: SanDisk 營收（情境 C） | B6: $B | C6: 1.69 | D6: 1.9 | E6: 2.31 | F6: 3.03 | G6: 5.95 | H6: 8.97 | I6: 10.555884 | J6: 13.008548 | K6: 14.277592 | L6: 15.39865 | M6: 14.653881 | N6: 12.395674 | O6: 7.2948293 | P6: 4.7531296 | Q6: 3.5734861 | R6: 2.8657167 | S6: 3.0446912 | T6: 3.3131741 | U6: 3.7083416 | V6: 4.2275051 | W6: 4.0774623 | X6: 4.0679223 | Y6: 4.0584046 | Z6: 4.0489092 | AA6: markets/nand/dist/20261025_NAND市場模型_v0.1.xlsx｜Mkt!C140:Z140
A7: SanDisk 位元（情境 A） | B7: EB | C7: 31.287396 | D7: 29.615294 | E7: 31.15528 | F7: 33.514723 | G7: 38.069333 | H7: 33.617215 | I7: 34.400604 | J7: 36.079657 | K7: 38.597443 | L7: 40.811827 | M7: 43.153253 | N7: 45.62901 | O7: 48.246803 | P7: 51.014784 | Q7: 53.941566 | R7: 57.036262 | S7: 59.290856 | T7: 62.255767 | U7: 65.368941 | V7: 68.637793 | W7: 69.295811 | X7: 71.604068 | Y7: 73.989213 | Z7: 76.453808 | AA7: markets/nand/dist/20261025_NAND市場模型_v0.1.xlsx｜Mkt!C48:Z48
A8: SanDisk 位元（情境 B） | B8: EB | C8: 31.287396 | D8: 29.615294 | E8: 31.15528 | F8: 33.514723 | G8: 38.069333 | H8: 33.617215 | I8: 34.400604 | J8: 36.079657 | K8: 38.155576 | L8: 40.34461 | M8: 42.659231 | N8: 45.106645 | O8: 44.798668 | P8: 46.390553 | Q8: 48.039004 | R8: 49.746031 | S8: 52.409164 | T8: 54.918392 | U8: 57.547756 | V8: 60.303007 | W8: 60.188911 | X8: 62.13236 | Y8: 64.138561 | Z8: 66.20954 | AA8: markets/nand/dist/20261025_NAND市場模型_v0.1.xlsx｜Mkt!C96:Z96
A9: SanDisk 位元（情境 C） | B9: EB | C9: 31.287396 | D9: 29.615294 | E9: 31.15528 | F9: 33.514723 | G9: 38.069333 | H9: 33.617215 | I9: 34.400604 | J9: 36.079657 | K9: 37.71371 | L9: 39.877393 | M9: 42.16521 | N9: 44.584281 | O9: 40.365784 | P9: 40.463604 | Q9: 40.561662 | R9: 40.659956 | S9: 43.199319 | T9: 44.770157 | U9: 46.398115 | V9: 48.085269 | W9: 47.884748 | X9: 49.324107 | Y9: 50.806731 | Z9: 52.333922 | AA9: markets/nand/dist/20261025_NAND市場模型_v0.1.xlsx｜Mkt!C144:Z144
A10: Kioxia＋SanDisk 合資群份額（情境 A） | B10: % | C10: 0.27907731 | D10: 0.25560769 | E10: 0.27406433 | F10: 0.2689697 | G10: 0.27096015 | H10: 0.25018083 | I10: 0.26205287 | J10: 0.26205287 | K10: 0.26205287 | L10: 0.26205287 | M10: 0.26205287 | N10: 0.26205287 | O10: 0.26205287 | P10: 0.26205287 | Q10: 0.26205287 | R10: 0.26205287 | S10: 0.26205287 | T10: 0.26205287 | U10: 0.26205287 | V10: 0.26205287 | W10: 0.26205287 | X10: 0.26205287 | Y10: 0.26205287 | Z10: 0.26205287 | AA10: markets/nand/dist/20261025_NAND市場模型_v0.1.xlsx｜Mkt!C46:Z46
A11: Kioxia＋SanDisk 合資群份額（情境 B） | B11: % | C11: 0.27907731 | D11: 0.25560769 | E11: 0.27406433 | F11: 0.2689697 | G11: 0.27096015 | H11: 0.25018083 | I11: 0.26205287 | J11: 0.26205287 | K11: 0.25905287 | L11: 0.25905287 | M11: 0.25905287 | N11: 0.25905287 | O11: 0.25605287 | P11: 0.25605287 | Q11: 0.25605287 | R11: 0.25605287 | S11: 0.25305287 | T11: 0.25305287 | U11: 0.25305287 | V11: 0.25305287 | W11: 0.25005287 | X11: 0.25005287 | Y11: 0.25005287 | Z11: 0.25005287 | AA11: markets/nand/dist/20261025_NAND市場模型_v0.1.xlsx｜Mkt!C94:Z94
A12: Kioxia＋SanDisk 合資群份額（情境 C） | B12: % | C12: 0.27907731 | D12: 0.25560769 | E12: 0.27406433 | F12: 0.2689697 | G12: 0.27096015 | H12: 0.25018083 | I12: 0.26205287 | J12: 0.26205287 | K12: 0.25605287 | L12: 0.25605287 | M12: 0.25605287 | N12: 0.25605287 | O12: 0.25005287 | P12: 0.25005287 | Q12: 0.25005287 | R12: 0.25005287 | S12: 0.24405287 | T12: 0.24405287 | U12: 0.24405287 | V12: 0.24405287 | W12: 0.23805287 | X12: 0.23805287 | Y12: 0.23805287 | Z12: 0.23805287 | AA12: markets/nand/dist/20261025_NAND市場模型_v0.1.xlsx｜Mkt!C142:Z142

Sheet PL
A1: PL — SanDisk 損益（$B；FY2026 實績；FY2027–FY2029 由市場層 markets/nand 驅動；FY2030–FY2032 收斂法見底部）。頂端摘要，下方三情境各一個完整推導區塊
A3: 情境／項目 | B3: 單位 | C3: FY2025A | D3: FY2026A | E3: FY2027 | F3: FY2028 | G3: FY2029 | H3: 說明
A4: 情境 A（順利）
A5: 營收 | B5: $B | C5: =C55 -> 7.355 | D5: =D55 -> 20.248 | E5: =E55 -> 53.023012 | F5: =F55 -> 60.304259 | G5: =G55 -> 61.403984
A6: 毛利率 | B6: % | D6: =D57 -> 0.71496933 | E6: =E57 -> 0.86916237 | F6: =F57 -> 0.87586847 | G6: =G57 -> 0.87030465
A7: 營業利益 | B7: $B | D7: =D59 -> 12.389 | E7: =E59 -> 43.529557 | F7: =F59 -> 49.987154 | G7: =G59 -> 50.37489
A8: 營業利益率 | B8: % | D8: =D60 -> 0.6118629 | E8: =E60 -> 0.82095594 | F8: =F60 -> 0.82891582 | G8: =G60 -> 0.82038472
A9: 淨利 | B9: $B | C9: =C61 -> -1.641 | D9: =D61 -> 11.433 | E9: =E61 -> 37.162031 | F9: =F61 -> 43.23138 | G9: =G61 -> 44.237099
A10: EPS | B10: USD | C10: =C69 -> -11.32 | D10: =D69 -> 73.76 | E10: =E69 -> 263.16538 | F10: =F69 -> 345.44029 | G10: =G69 -> 406.94244
A11: 每股淨值 | B11: USD | D11: =D70 -> 107.47166 | E11: =E70 -> 270.12928 | F11: =F70 -> 507.6196 | G11: =G70 -> 829.48648
A12: 自由現金流 | B12: $B | D12: =D64 -> 11.031 | E12: =E64 -> 34.14065 | F12: =F64 -> 39.773124 | G12: =G64 -> 40.71286
A14: 情境 B（平平）
A15: 營收 | B15: $B | C15: =C91 -> 7.355 | D15: =D91 -> 20.248 | E15: =E91 -> 53.55663 | F15: =F91 -> 42.831169 | G15: =G91 -> 22.970548
A16: 毛利率 | B16: % | D16: =D93 -> 0.71496933 | E16: =E93 -> 0.87009133 | F16: =F93 -> 0.82809326 | G16: =G93 -> 0.67696637
A17: 營業利益 | B17: $B | D17: =D95 -> 12.389 | E17: =E95 -> 44.037773 | F17: =F95 -> 32.811488 | G17: =G95 -> 12.869341
A18: 營業利益率 | B18: % | D18: =D96 -> 0.6118629 | E18: =E96 -> 0.82226557 | F18: =F96 -> 0.76606567 | G18: =G96 -> 0.56025396
A19: 淨利 | B19: $B | C19: =C97 -> -1.641 | D19: =D97 -> 11.433 | E19: =E97 -> 37.594015 | F19: =F97 -> 28.638863 | G19: =G97 -> 12.133931
A20: EPS | B20: USD | C20: =C105 -> -11.32 | D20: =D105 -> 73.76 | E20: =E105 -> 266.52938 | F20: =F105 -> 219.527 | G20: =G105 -> 96.26388
A21: 每股淨值 | B21: USD | D21: =D106 -> 107.47166 | E21: =E106 -> 272.21001 | F21: =F106 -> 423.24652 | G21: =G106 -> 495.96348
A22: 自由現金流 | B22: $B | D22: =D100 -> 11.031 | E22: =E100 -> 34.540617 | F22: =F100 -> 26.228993 | G22: =G100 -> 10.915698
A24: 情境 C（不如預期）
A25: 營收 | B25: $B | C25: =C127 -> 7.355 | D25: =D127 -> 20.248 | E25: =E127 -> 53.209139 | F25: =F127 -> 39.074356 | G25: =G127 -> 12.789488
A26: 毛利率 | B26: % | D26: =D129 -> 0.71496933 | E26: =E129 -> 0.86889852 | F26: =F129 -> 0.81773371 | G26: =G129 -> 0.49496873
A27: 營業利益 | B27: $B | D27: =D131 -> 12.389 | E27: =E131 -> 43.675431 | F27: =F131 -> 29.333273 | G27: =G131 -> 3.7512594
A28: 營業利益率 | B28: % | D28: =D132 -> 0.6118629 | E28: =E132 -> 0.82082574 | F28: =F132 -> 0.75070392 | G28: =G132 -> 0.29330801
A29: 淨利 | B29: $B | C29: =C133 -> -1.641 | D29: =D133 -> 11.433 | E29: =E133 -> 37.286024 | F29: =F133 -> 25.677499 | G29: =G133 -> 4.3321693
A30: EPS | B30: USD | C30: =C141 -> -11.32 | D30: =D141 -> 73.76 | E30: =E141 -> 264.12867 | F30: =F141 -> 195.0021 | G30: =G141 -> 33.279902
A31: 每股淨值 | B31: USD | D31: =D142 -> 107.47166 | E31: =E142 -> 270.73182 | F31: =F142 -> 404.76889 | G31: =G142 -> 430.08823
A32: 自由現金流 | B32: $B | D32: =D136 -> 11.031 | E32: =E136 -> 34.253476 | F32: =F136 -> 23.493038 | G32: =G136 -> 3.7247999
A34: 核對：三情境 FY2026 − 實績（應為 0） | D34: =D73+D109+D145 -> 0
A40: 情境 A（順利）：markets/nand 情境 A（價格路徑 A、2028–29 顆數係數 A、合資群份額 A）；每位元成本年降 cd_A
A41: A. 季度 | B41: 單位 | C41: FQ1 FY26（2025Q3） | D41: FQ2 FY26（2025Q4） | E41: FQ3 FY26（2026Q1） | F41: FQ4 FY26（2026Q2） | G41: FQ1 FY27（2026Q3） | H41: FQ2 FY27（2026Q4） | I41: FQ3 FY27（2027Q1） | J41: FQ4 FY27（2027Q2） | K41: FQ1 FY28（2027Q3） | L41: FQ2 FY28（2027Q4） | M41: FQ3 FY28（2028Q1） | N41: FQ4 FY28（2028Q2） | O41: FQ1 FY29（2028Q3） | P41: FQ2 FY29（2028Q4） | Q41: FQ3 FY29（2029Q1） | R41: FQ4 FY29（2029Q2） | T41: 說明
A42: 市場層營收（TrendForce 口徑，同字母情境） | B42: $B | C42: =Units!E4*1 -> 2.31 | D42: =Units!F4*1 -> 3.03 | E42: =Units!G4*1 -> 5.95 | F42: =Units!H4*1 -> 8.97 | G42: =Units!I4*1 -> 10.555884 | H42: =Units!J4*1*1 -> 13.008548 | I42: =Units!K4*1*1 -> 14.333827 | J42: =Units!L4*1*1 -> 15.156177 | K42: =Units!M4*1*1 -> 15.224421 | L42: =Units!N4*1*1 -> 14.971015 | M42: =Units!O4*1*1 -> 15.038425 | N42: =Units!P4*1*1 -> 15.106138 | O42: =Units!Q4*1*1 -> 15.174156 | ... R42: =Units!T4*1*1 -> 15.654084 | T42: markets/nand；Sens 可乘份額係數、價格係數（FQ2 FY27 起）
A43: 位元（市場層；同字母） | B43: EB | C43: =Units!E7*1 -> 31.15528 | D43: =Units!F7*1 -> 33.514723 | E43: =Units!G7*1 -> 38.069333 | F43: =Units!H7*1 -> 33.617215 | G43: =Units!I7*1 -> 34.400604 | H43: =Units!J7*1 -> 36.079657 | I43: =Units!K7*1 -> 38.597443 | J43: =Units!L7*1 -> 40.811827 | ... R43: =Units!T7*1 -> 62.255767
A44: 營收 | B44: $B | C44: =q1_rev -> 2.308 | D44: =q2_rev -> 3.025 | E44: =q3_rev -> 5.95 | F44: =q4_rev -> 8.965 | G44: =G42*sd_k -> 10.549632 | H44: =H42*sd_k -> 13.000843 | I44: =I42*sd_k -> 14.325337 | J44: =J42*sd_k -> 15.1472 | K44: =K42*sd_k -> 15.215403 | L44: =L42*sd_k -> 14.962147 | M44: =M42*sd_k -> 15.029517 | N44: =N42*sd_k -> 15.097191 | ... R44: =R42*sd_k -> 15.644812 | T44: 實績季＝公司財報；之後＝市場層 × 公司口徑係數
A45: 每 EB 營業成本（FQ1 FY27 以指引毛利率校準，之後每年 × (1 − 成本年降)） | B45: $B/EB | C45: =C46/C43 -> 0.052004539 | D45: =D46/D43 -> 0.04431709 | E45: =E46/E43 -> 0.033759457 | F45: =F46/F43 -> 0.041068541 | G45: =(1-g_gm)*G44/G43 -> 0.049067194 | H45: =$G45*(1-cd_A)^(1/4) -> 0.047251525 | I45: =$G45*(1-cd_A)^(2/4) -> 0.045503043 | J45: =$G45*(1-cd_A)^(3/4) -> 0.043819262 | K45: =$G45*(1-cd_A)^(4/4) -> 0.042197787 | L45: =$G45*(1-cd_A)^(5/4) -> 0.040636312 | M45: =$G45*(1-cd_A)^(6/4) -> 0.039132617 | N45: =$G45*(1-cd_A)^(7/4) -> 0.037684565 | O45: =$G45*(1-cd_A)^(8/4) -> 0.036290096 | P45: =$G45*(1-cd_A)^(9/4) -> 0.034947228 | Q45: =$G45*(1-cd_A)^(10/4) -> 0.033654051 | R45: =$G45*(1-cd_A)^(11/4) -> 0.032408726
A46: 營業成本 | B46: $B | C46: =q1_rev*(1-q1_gm) -> 1.620216 | D46: =q2_rev*(1-q2_gm) -> 1.485275 | E46: =q3_rev*(1-q3_gm) -> 1.2852 | F46: =q4_rev*(1-q4_gm) -> 1.38061 | G46: =G43*G45 -> 1.6879411 | H46: =H43*H45 -> 1.7048188 | I46: =I43*I45 -> 1.7563011 | J46: =J43*J45 -> 1.7883441 | K46: =K43*K45 -> 1.8209718 | L46: =L43*L45 -> 1.8541947 | M46: =M43*M45 -> 1.8880237 | N46: =N43*N45 -> 1.9224699 | ... R46: =R43*R45 -> 2.0176301
A47: 毛利率 | B47: % | C47: =1-C46/C44 -> 0.298 | D47: =1-D46/D44 -> 0.509 | E47: =1-E46/E44 -> 0.784 | F47: =1-F46/F44 -> 0.846 | G47: =1-G46/G44 -> 0.84 | H47: =1-H46/H44 -> 0.86886859 | I47: =1-I46/I44 -> 0.87739897 | J47: =1-J46/J44 -> 0.88193566 | ... R47: =1-R46/R44 -> 0.8710352
A48: 營業費用 | B48: $B | C48: =q1_rev-q1_rev*(1-q1_gm)-q1_op -> 0.511784 | D48: =q2_rev-q2_rev*(1-q2_gm)-q2_op -> 0.474725 | E48: =q3_rev-q3_rev*(1-q3_gm)-q3_op -> 0.5538 | F48: =q4_rev-q4_rev*(1-q4_gm)-q4_op -> 0.54739 | G48: =(g_ox-ox_var*g_rev)*(1+ox_g)^(0/4)+ox_var*G44 -> 0.59399632 | H48: =(g_ox-ox_var*g_rev)*(1+ox_g)^(1/4)+ox_var*H44 -> 0.63028797 | I48: =(g_ox-ox_var*g_rev)*(1+ox_g)^(2/4)+ox_var*I44 -> 0.6555965 | J48: =(g_ox-ox_var*g_rev)*(1+ox_g)^(3/4)+ox_var*J44 -> 0.67616961 | K48: =(g_ox-ox_var*g_rev)*(1+ox_g)^(4/4)+ox_var*K44 -> 0.68950403 | L48: =(g_ox-ox_var*g_rev)*(1+ox_g)^(5/4)+ox_var*L44 -> 0.69992896 | M48: =(g_ox-ox_var*g_rev)*(1+ox_g)^(6/4)+ox_var*M44 -> 0.71387261 | N48: =(g_ox-ox_var*g_rev)*(1+ox_g)^(7/4)+ox_var*N44 -> 0.72813927 | O48: =(g_ox-ox_var*g_rev)*(1+ox_g)^(8/4)+ox_var*O44 -> 0.74273669 | P48: =(g_ox-ox_var*g_rev)*(1+ox_g)^(9/4)+ox_var*P44 -> 0.75767277 | Q48: =(g_ox-ox_var*g_rev)*(1+ox_g)^(10/4)+ox_var*Q44 -> 0.77354068 | R48: =(g_ox-ox_var*g_rev)*(1+ox_g)^(11/4)+ox_var*R44 -> 0.79133223 | T48: 固定部分以 FQ1 FY27 指引營業費用校準（Derived）
A49: 營業利益 | B49: $B | C49: =C44-C46-C48 -> 0.176 | D49: =D44-D46-D48 -> 1.065 | E49: =E44-E46-E48 -> 4.111 | F49: =F44-F46-F48 -> 7.037 | G49: =G44-G46-G48 -> 8.2676943 | H49: =H44-H46-H48 -> 10.665736 | I49: =I44-I46-I48 -> 11.91344 | J49: =J44-J46-J48 -> 12.682686 | ... R49: =R44-R46-R48 -> 12.83585
A51: 淨利 | B51: $B | C51: =q1_ni -> 0.112 | D51: =q2_ni -> 0.803 | E51: =q3_ni -> 3.615 | F51: =q4_ni -> 6.903 | G51: =(G49+rf*$D67/4)*(1-tax) -> 7.0680172 | H51: =(H49+rf*$D67/4)*(1-tax) -> 9.1063526 | I51: =(I49+rf*$D67/4)*(1-tax) -> 10.166901 | J51: =(J49+rf*$D67/4)*(1-tax) -> 10.82076 | K51: =(K49+rf*$E67/4)*(1-tax) -> 10.984763 | L51: =(L49+rf*$E67/4)*(1-tax) -> 10.732395 | M51: =(M49+rf*$E67/4)*(1-tax) -> 10.749053 | N51: =(N49+rf*$E67/4)*(1-tax) -> 10.765169 | O51: =(O49+rf*$F67/4)*(1-tax) -> 10.949765 | P51: =(P49+rf*$F67/4)*(1-tax) -> 10.964753 | Q51: =(Q49+rf*$F67/4)*(1-tax) -> 11.057497 | R51: =(R49+rf*$F67/4)*(1-tax) -> 11.265083 | T51: （營業利益＋上一年底淨現金 × 收益率 ÷ 4）×（1 − 稅率）
A52: 季 EPS（稀釋） | B52: USD | G52: =G51/(sh0+dil)*1000 -> 45.600111 | H52: =H51/(sh0+dil)*1000 -> 58.750662 | I52: =I51/(sh0+dil)*1000 -> 65.592909 | J52: =J51/(sh0+dil)*1000 -> 69.811358 | K52: =K51/(sh0+dil)*1000 -> 70.86944 | L52: =L51/(sh0+dil)*1000 -> 69.241257 | M52: =M51/(sh0+dil)*1000 -> 69.348726 | N52: =N51/(sh0+dil)*1000 -> 69.452703 | ... R52: =R51/(sh0+dil)*1000 -> 72.677955
A54: B. 年度（會計年度） | B54: 單位 | C54: FY2025A | D54: FY2026A | E54: FY2027 | F54: FY2028 | G54: FY2029 | T54: 說明
A55: 營收 | B55: $B | C55: =a25_rev -> 7.355 | D55: =SUM(C44:F44) -> 20.248 | E55: =SUM(G44:J44) -> 53.023012 | F55: =SUM(K44:N44) -> 60.304259 | G55: =SUM(O44:R44) -> 61.403984
A56: 營業成本 | B56: $B | D56: =SUM(C46:F46) -> 5.771301 | E56: =SUM(G46:J46) -> 6.9374052 | F56: =SUM(K46:N46) -> 7.4856601 | G56: =SUM(O46:R46) -> 7.9638115
A57: 毛利率 | B57: % | D57: =1-D56/D55 -> 0.71496933 | E57: =1-E56/E55 -> 0.86916237 | F57: =1-F56/F55 -> 0.87586847 | G57: =1-G56/G55 -> 0.87030465
A58: 營業費用 | B58: $B | D58: =SUM(C48:F48) -> 2.087699 | E58: =SUM(G48:J48) -> 2.5560504 | F58: =SUM(K48:N48) -> 2.8314449 | G58: =SUM(O48:R48) -> 3.0652824
A59: 營業利益 | B59: $B | D59: =SUM(C49:F49) -> 12.389 | E59: =SUM(G49:J49) -> 43.529557 | F59: =SUM(K49:N49) -> 49.987154 | G59: =SUM(O49:R49) -> 50.37489
A60: 營業利益率 | B60: % | D60: =D59/D55 -> 0.6118629 | E60: =E59/E55 -> 0.82095594 | F60: =F59/F55 -> 0.82891582 | G60: =G59/G55 -> 0.82038472
A61: 淨利 | B61: $B | C61: =a25_ni -> -1.641 | D61: =SUM(C51:F51) -> 11.433 | E61: =SUM(G51:J51) -> 37.162031 | F61: =SUM(K51:N51) -> 43.23138 | G61: =SUM(O51:R51) -> 44.237099
A62: 折舊攤銷（公司本身） | B62: $B | D62: =da_y -> 0.16 | E62: =da_y -> 0.16 | F62: =da_y -> 0.16 | G62: =da_y -> 0.16
A63: 資本支出（含合資群分攤） | B63: $B | D63: 0.562 | E63: =cap_r*E55 -> 3.1813807 | F63: =cap_r*F55 -> 3.6182555 | G63: =cap_r*G55 -> 3.684239 | T63: FY2026 毛資本支出 0.562（公司簡報；markets/equipment In 頁）
A64: 自由現金流（淨利＋折舊 − 資本支出） | B64: $B | D64: =D61+D62-D63 -> 11.031 | E64: =E61+E62-E63 -> 34.14065 | F64: =F61+F62-F63 -> 39.773124 | G64: =G61+G62-G63 -> 40.71286
A65: 買回 | B65: $B | D65: 4.524 | E65: =MAX(0,payout*E64) -> 17.070325 | F65: =MAX(0,payout*F64) -> 19.886562 | G65: =MAX(0,payout*G64) -> 20.35643 | T65: FY2026 實績 4.524（FQ4）
A66: 期末權益 | B66: $B | D66: =eq0 -> 15.736 | E66: =D66+E61-E65 -> 35.827706 | F66: =E66+F61-F65 -> 59.172524 | G66: =F66+G61-G65 -> 83.053192
A67: 期末淨現金 | B67: $B | D67: =nc0 -> 4.762 | E67: =D67+E64-E65 -> 21.832325 | F67: =E67+F64-F65 -> 41.718887 | G67: =F67+G64-G65 -> 62.075317
A68: 期末流通股數 | B68: 百萬股 | D68: =sh0 -> 146.42 | E68: =D68-E65/bb_px*1000 -> 132.6317 | F68: =E68-F65/bb_px*1000 -> 116.56863 | G68: =F68-G65/bb_px*1000 -> 100.12604
A69: EPS（稀釋：期末流通股數＋dil） | B69: USD | C69: =a25_eps -> -11.32 | D69: =a26_eps -> 73.76 | E69: =E61/(E68+dil)*1000 -> 263.16538 | F69: =F61/(F68+dil)*1000 -> 345.44029 | G69: =G61/(G68+dil)*1000 -> 406.94244
A70: 每股淨值 BVPS（期末流通股數） | B70: USD | D70: =D66/D68*1000 -> 107.47166 | E70: =E66/E68*1000 -> 270.12928 | F70: =F66/F68*1000 -> 507.6196 | G70: =G66/G68*1000 -> 829.48648
A71: ROE（期末權益） | B71: % | D71: =D61/D66 -> 0.72655058 | E71: =E61/E66 -> 1.0372428 | F71: =F61/F66 -> 0.73059889 | G71: =G61/G66 -> 0.53263574
A72: 每股自由現金流（稀釋） | B72: USD | E72: =E64/(E68+dil)*1000 -> 241.76927 | F72: =F64/(F68+dil)*1000 -> 317.8071 | G72: =G64/(G68+dil)*1000 -> 374.52253
A73: 檢查：FY2026 營收、淨利 − 實績（應為 0） | B73: $B | D73: =ABS(D55-a26_rev)+ABS(D61-a26_ni) -> 0
A76: 情境 B（平平）：markets/nand 情境 B（價格路徑 B、2028–29 顆數係數 B、合資群份額 B）；每位元成本年降 cd_B
A77: A. 季度 | B77: 單位 | C77: FQ1 FY26（2025Q3） | D77: FQ2 FY26（2025Q4） | E77: FQ3 FY26（2026Q1） | F77: FQ4 FY26（2026Q2） | G77: FQ1 FY27（2026Q3） | H77: FQ2 FY27（2026Q4） | I77: FQ3 FY27（2027Q1） | J77: FQ4 FY27（2027Q2） | K77: FQ1 FY28（2027Q3） | L77: FQ2 FY28（2027Q4） | M77: FQ3 FY28（2028Q1） | N77: FQ4 FY28（2028Q2） | O77: FQ1 FY29（2028Q3） | P77: FQ2 FY29（2028Q4） | Q77: FQ3 FY29（2029Q1） | R77: FQ4 FY29（2029Q2） | T77: 說明
A78: 市場層營收（TrendForce 口徑，同字母情境） | B78: $B | C78: =Units!E5*1 -> 2.31 | D78: =Units!F5*1 -> 3.03 | E78: =Units!G5*1 -> 5.95 | F78: =Units!H5*1 -> 8.97 | G78: =Units!I5*1 -> 10.555884 | H78: =Units!J5*1*1 -> 13.008548 | I78: =Units!K5*1*1 -> 14.444873 | J78: =Units!L5*1*1 -> 15.579066 | K78: =Units!M5*1*1 -> 14.825571 | L78: =Units!N5*1*1 -> 12.540906 | M78: =Units!O5*1*1 -> 8.7186957 | N78: =Units!P5*1*1 -> 6.7713807 | O78: =Units!Q5*1*1 -> 5.609597 | ... R78: =Units!T5*1*1 -> 6.3632149 | T78: markets/nand；Sens 可乘份額係數、價格係數（FQ2 FY27 起）
A79: 位元（市場層；同字母） | B79: EB | C79: =Units!E8*1 -> 31.15528 | D79: =Units!F8*1 -> 33.514723 | E79: =Units!G8*1 -> 38.069333 | F79: =Units!H8*1 -> 33.617215 | G79: =Units!I8*1 -> 34.400604 | H79: =Units!J8*1 -> 36.079657 | I79: =Units!K8*1 -> 38.155576 | J79: =Units!L8*1 -> 40.34461 | ... R79: =Units!T8*1 -> 54.918392
A80: 營收 | B80: $B | C80: =q1_rev -> 2.308 | D80: =q2_rev -> 3.025 | E80: =q3_rev -> 5.95 | F80: =q4_rev -> 8.965 | G80: =G78*sd_k -> 10.549632 | H80: =H78*sd_k -> 13.000843 | I80: =I78*sd_k -> 14.436317 | J80: =J78*sd_k -> 15.569838 | K80: =K78*sd_k -> 14.816789 | L80: =L78*sd_k -> 12.533478 | M80: =M78*sd_k -> 8.7135316 | N80: =N78*sd_k -> 6.76737 | ... R80: =R78*sd_k -> 6.359446 | T80: 實績季＝公司財報；之後＝市場層 × 公司口徑係數
A81: 每 EB 營業成本（FQ1 FY27 以指引毛利率校準，之後每年 × (1 − 成本年降)） | B81: $B/EB | C81: =C82/C79 -> 0.052004539 | D81: =D82/D79 -> 0.04431709 | E81: =E82/E79 -> 0.033759457 | F81: =F82/F79 -> 0.041068541 | G81: =(1-g_gm)*G80/G79 -> 0.049067194 | H81: =$G81*(1-cd_B)^(1/4) -> 0.04752388 | I81: =$G81*(1-cd_B)^(2/4) -> 0.046029108 | J81: =$G81*(1-cd_B)^(3/4) -> 0.044581351 | K81: =$G81*(1-cd_B)^(4/4) -> 0.04317913 | L81: =$G81*(1-cd_B)^(5/4) -> 0.041821014 | M81: =$G81*(1-cd_B)^(6/4) -> 0.040505615 | N81: =$G81*(1-cd_B)^(7/4) -> 0.039231589 | O81: =$G81*(1-cd_B)^(8/4) -> 0.037997635 | P81: =$G81*(1-cd_B)^(9/4) -> 0.036802492 | Q81: =$G81*(1-cd_B)^(10/4) -> 0.035644941 | R81: =$G81*(1-cd_B)^(11/4) -> 0.034523798
A82: 營業成本 | B82: $B | C82: =q1_rev*(1-q1_gm) -> 1.620216 | D82: =q2_rev*(1-q2_gm) -> 1.485275 | E82: =q3_rev*(1-q3_gm) -> 1.2852 | F82: =q4_rev*(1-q4_gm) -> 1.38061 | G82: =G79*G81 -> 1.6879411 | H82: =H79*H81 -> 1.7146453 | I82: =I79*I81 -> 1.7562671 | J82: =J79*J81 -> 1.7986172 | K82: =K79*K81 -> 1.8419885 | L82: =L79*L81 -> 1.8864057 | M82: =M79*M81 -> 1.8145976 | N82: =N79*N81 -> 1.8199751 | ... R82: =R79*R81 -> 1.8959915
A83: 毛利率 | B83: % | C83: =1-C82/C80 -> 0.298 | D83: =1-D82/D80 -> 0.509 | E83: =1-E82/E80 -> 0.784 | F83: =1-F82/F80 -> 0.846 | G83: =1-G82/G80 -> 0.84 | H83: =1-H82/H80 -> 0.86811276 | I83: =1-I82/I80 -> 0.87834383 | J83: =1-J82/J80 -> 0.88448067 | ... R83: =1-R82/R80 -> 0.70186216
A84: 營業費用 | B84: $B | C84: =q1_rev-q1_rev*(1-q1_gm)-q1_op -> 0.511784 | D84: =q2_rev-q2_rev*(1-q2_gm)-q2_op -> 0.474725 | E84: =q3_rev-q3_rev*(1-q3_gm)-q3_op -> 0.5538 | F84: =q4_rev-q4_rev*(1-q4_gm)-q4_op -> 0.54739 | G84: =(g_ox-ox_var*g_rev)*(1+ox_g)^(0/4)+ox_var*G80 -> 0.59399632 | H84: =(g_ox-ox_var*g_rev)*(1+ox_g)^(1/4)+ox_var*H80 -> 0.63028797 | I84: =(g_ox-ox_var*g_rev)*(1+ox_g)^(2/4)+ox_var*I80 -> 0.6567063 | J84: =(g_ox-ox_var*g_rev)*(1+ox_g)^(3/4)+ox_var*J80 -> 0.68039599 | K84: =(g_ox-ox_var*g_rev)*(1+ox_g)^(4/4)+ox_var*K80 -> 0.68551789 | L84: =(g_ox-ox_var*g_rev)*(1+ox_g)^(5/4)+ox_var*L80 -> 0.67564227 | M84: =(g_ox-ox_var*g_rev)*(1+ox_g)^(6/4)+ox_var*M80 -> 0.65071275 | N84: =(g_ox-ox_var*g_rev)*(1+ox_g)^(7/4)+ox_var*N80 -> 0.64484107 | O84: =(g_ox-ox_var*g_rev)*(1+ox_g)^(8/4)+ox_var*O80 -> 0.64714774 | P84: =(g_ox-ox_var*g_rev)*(1+ox_g)^(9/4)+ox_var*P80 -> 0.65758764 | Q84: =(g_ox-ox_var*g_rev)*(1+ox_g)^(10/4)+ox_var*Q80 -> 0.67773406 | R84: =(g_ox-ox_var*g_rev)*(1+ox_g)^(11/4)+ox_var*R80 -> 0.69847856 | T84: 固定部分以 FQ1 FY27 指引營業費用校準（Derived）
A85: 營業利益 | B85: $B | C85: =C80-C82-C84 -> 0.176 | D85: =D80-D82-D84 -> 1.065 | E85: =E80-E82-E84 -> 4.111 | F85: =F80-F82-F84 -> 7.037 | G85: =G80-G82-G84 -> 8.2676943 | H85: =H80-H82-H84 -> 10.65591 | I85: =I80-I82-I84 -> 12.023344 | J85: =J80-J82-J84 -> 13.090825 | ... R85: =R80-R82-R84 -> 3.7649759
A87: 淨利 | B87: $B | C87: =q1_ni -> 0.112 | D87: =q2_ni -> 0.803 | E87: =q3_ni -> 3.615 | F87: =q4_ni -> 6.903 | G87: =(G85+rf*$D103/4)*(1-tax) -> 7.0680172 | H87: =(H85+rf*$D103/4)*(1-tax) -> 9.0980002 | I87: =(I85+rf*$D103/4)*(1-tax) -> 10.260319 | J87: =(J85+rf*$D103/4)*(1-tax) -> 11.167678 | K87: =(K85+rf*$E103/4)*(1-tax) -> 10.633165 | L87: =(L85+rf*$E103/4)*(1-tax) -> 8.6629901 | M87: =(M85+rf*$E103/4)*(1-tax) -> 5.4982627 | N87: =(N85+rf*$E103/4)*(1-tax) -> 3.8444454 | O87: =(O85+rf*$F103/4)*(1-tax) -> 2.9624423 | P87: =(P85+rf*$F103/4)*(1-tax) -> 2.6248361 | Q87: =(Q85+rf*$F103/4)*(1-tax) -> 3.0476752 | R87: =(R85+rf*$F103/4)*(1-tax) -> 3.4989774 | T87: （營業利益＋上一年底淨現金 × 收益率 ÷ 4）×（1 − 稅率）
A88: 季 EPS（稀釋） | B88: USD | G88: =G87/(sh0+dil)*1000 -> 45.600111 | H88: =H87/(sh0+dil)*1000 -> 58.696775 | I88: =I87/(sh0+dil)*1000 -> 66.195609 | J88: =J87/(sh0+dil)*1000 -> 72.049537 | K88: =K87/(sh0+dil)*1000 -> 68.601066 | L88: =L87/(sh0+dil)*1000 -> 55.890259 | M88: =M87/(sh0+dil)*1000 -> 35.472662 | N88: =N87/(sh0+dil)*1000 -> 24.802873 | ... R88: =R87/(sh0+dil)*1000 -> 22.574048
A90: B. 年度（會計年度） | B90: 單位 | C90: FY2025A | D90: FY2026A | E90: FY2027 | F90: FY2028 | G90: FY2029 | T90: 說明
A91: 營收 | B91: $B | C91: =a25_rev -> 7.355 | D91: =SUM(C80:F80) -> 20.248 | E91: =SUM(G80:J80) -> 53.55663 | F91: =SUM(K80:N80) -> 42.831169 | G91: =SUM(O80:R80) -> 22.970548
A92: 營業成本 | B92: $B | D92: =SUM(C82:F82) -> 5.771301 | E92: =SUM(G82:J82) -> 6.9574707 | F92: =SUM(K82:N82) -> 7.3629668 | G92: =SUM(O82:R82) -> 7.4202595
A93: 毛利率 | B93: % | D93: =1-D92/D91 -> 0.71496933 | E93: =1-E92/E91 -> 0.87009133 | F93: =1-F92/F91 -> 0.82809326 | G93: =1-G92/G91 -> 0.67696637
A94: 營業費用 | B94: $B | D94: =SUM(C84:F84) -> 2.087699 | E94: =SUM(G84:J84) -> 2.5613866 | F94: =SUM(K84:N84) -> 2.656714 | G94: =SUM(O84:R84) -> 2.680948
A95: 營業利益 | B95: $B | D95: =SUM(C85:F85) -> 12.389 | E95: =SUM(G85:J85) -> 44.037773 | F95: =SUM(K85:N85) -> 32.811488 | G95: =SUM(O85:R85) -> 12.869341
A96: 營業利益率 | B96: % | D96: =D95/D91 -> 0.6118629 | E96: =E95/E91 -> 0.82226557 | F96: =F95/F91 -> 0.76606567 | G96: =G95/G91 -> 0.56025396
A97: 淨利 | B97: $B | C97: =a25_ni -> -1.641 | D97: =SUM(C87:F87) -> 11.433 | E97: =SUM(G87:J87) -> 37.594015 | F97: =SUM(K87:N87) -> 28.638863 | G97: =SUM(O87:R87) -> 12.133931
A98: 折舊攤銷（公司本身） | B98: $B | D98: =da_y -> 0.16 | E98: =da_y -> 0.16 | F98: =da_y -> 0.16 | G98: =da_y -> 0.16
A99: 資本支出（含合資群分攤） | B99: $B | D99: 0.562 | E99: =cap_r*E91 -> 3.2133978 | F99: =cap_r*F91 -> 2.5698701 | G99: =cap_r*G91 -> 1.3782329 | T99: FY2026 毛資本支出 0.562（公司簡報；markets/equipment In 頁）
A100: 自由現金流（淨利＋折舊 − 資本支出） | B100: $B | D100: =D97+D98-D99 -> 11.031 | E100: =E97+E98-E99 -> 34.540617 | F100: =F97+F98-F99 -> 26.228993 | G100: =G97+G98-G99 -> 10.915698
A101: 買回 | B101: $B | D101: 4.524 | E101: =MAX(0,payout*E100) -> 17.270309 | F101: =MAX(0,payout*F100) -> 13.114497 | G101: =MAX(0,payout*G100) -> 5.457849 | T101: FY2026 實績 4.524（FQ4）
A102: 期末權益 | B102: $B | D102: =eq0 -> 15.736 | E102: =D102+E97-E101 -> 36.059706 | F102: =E102+F97-F101 -> 51.584073 | G102: =F102+G97-G101 -> 58.260155
A103: 期末淨現金 | B103: $B | D103: =nc0 -> 4.762 | E103: =D103+E100-E101 -> 22.032309 | F103: =E103+F100-F101 -> 35.146805 | G103: =F103+G100-G101 -> 40.604654
A104: 期末流通股數 | B104: 百萬股 | D104: =sh0 -> 146.42 | E104: =D104-E101/bb_px*1000 -> 132.47017 | F104: =E104-F101/bb_px*1000 -> 121.87713 | G104: =F104-G101/bb_px*1000 -> 117.46864
A105: EPS（稀釋：期末流通股數＋dil） | B105: USD | C105: =a25_eps -> -11.32 | D105: =a26_eps -> 73.76 | E105: =E97/(E104+dil)*1000 -> 266.52938 | F105: =F97/(F104+dil)*1000 -> 219.527 | G105: =G97/(G104+dil)*1000 -> 96.26388
A106: 每股淨值 BVPS（期末流通股數） | B106: USD | D106: =D102/D104*1000 -> 107.47166 | E106: =E102/E104*1000 -> 272.21001 | F106: =F102/F104*1000 -> 423.24652 | G106: =G102/G104*1000 -> 495.96348
A107: ROE（期末權益） | B107: % | D107: =D97/D102 -> 0.72655058 | E107: =E97/E102 -> 1.0425491 | F107: =F97/F102 -> 0.5551881 | G107: =G97/G102 -> 0.20827152
A108: 每股自由現金流（稀釋） | B108: USD | E108: =E100/(E104+dil)*1000 -> 244.88178 | F108: =F100/(F104+dil)*1000 -> 201.0545 | G108: =G100/(G104+dil)*1000 -> 86.599096
A109: 檢查：FY2026 營收、淨利 − 實績（應為 0） | B109: $B | D109: =ABS(D91-a26_rev)+ABS(D97-a26_ni) -> 0
A112: 情境 C（不如預期）：markets/nand 情境 C（價格路徑 C、2028–29 顆數係數 C、合資群份額 C）；每位元成本年降 cd_C
A113: A. 季度 | B113: 單位 | C113: FQ1 FY26（2025Q3） | D113: FQ2 FY26（2025Q4） | E113: FQ3 FY26（2026Q1） | F113: FQ4 FY26（2026Q2） | G113: FQ1 FY27（2026Q3） | H113: FQ2 FY27（2026Q4） | I113: FQ3 FY27（2027Q1） | J113: FQ4 FY27（2027Q2） | K113: FQ1 FY28（2027Q3） | L113: FQ2 FY28（2027Q4） | M113: FQ3 FY28（2028Q1） | N113: FQ4 FY28（2028Q2） | O113: FQ1 FY29（2028Q3） | P113: FQ2 FY29（2028Q4） | Q113: FQ3 FY29（2029Q1） | R113: FQ4 FY29（2029Q2） | T113: 說明
A114: 市場層營收（TrendForce 口徑，同字母情境） | B114: $B | C114: =Units!E6*1 -> 2.31 | D114: =Units!F6*1 -> 3.03 | E114: =Units!G6*1 -> 5.95 | F114: =Units!H6*1 -> 8.97 | G114: =Units!I6*1 -> 10.555884 | H114: =Units!J6*1*1 -> 13.008548 | I114: =Units!K6*1*1 -> 14.277592 | J114: =Units!L6*1*1 -> 15.39865 | K114: =Units!M6*1*1 -> 14.653881 | L114: =Units!N6*1*1 -> 12.395674 | M114: =Units!O6*1*1 -> 7.2948293 | N114: =Units!P6*1*1 -> 4.7531296 | O114: =Units!Q6*1*1 -> 3.5734861 | ... R114: =Units!T6*1*1 -> 3.3131741 | T114: markets/nand；Sens 可乘份額係數、價格係數（FQ2 FY27 起）
A115: 位元（市場層；同字母） | B115: EB | C115: =Units!E9*1 -> 31.15528 | D115: =Units!F9*1 -> 33.514723 | E115: =Units!G9*1 -> 38.069333 | F115: =Units!H9*1 -> 33.617215 | G115: =Units!I9*1 -> 34.400604 | H115: =Units!J9*1 -> 36.079657 | I115: =Units!K9*1 -> 37.71371 | J115: =Units!L9*1 -> 39.877393 | ... R115: =Units!T9*1 -> 44.770157
A116: 營收 | B116: $B | C116: =q1_rev -> 2.308 | D116: =q2_rev -> 3.025 | E116: =q3_rev -> 5.95 | F116: =q4_rev -> 8.965 | G116: =G114*sd_k -> 10.549632 | H116: =H114*sd_k -> 13.000843 | I116: =I114*sd_k -> 14.269136 | J116: =J114*sd_k -> 15.389529 | K116: =K114*sd_k -> 14.645201 | L116: =L114*sd_k -> 12.388332 | M116: =M114*sd_k -> 7.2905085 | N116: =N114*sd_k -> 4.7503144 | ... R116: =R114*sd_k -> 3.3112117 | T116: 實績季＝公司財報；之後＝市場層 × 公司口徑係數
A117: 每 EB 營業成本（FQ1 FY27 以指引毛利率校準，之後每年 × (1 − 成本年降)） | B117: $B/EB | C117: =C118/C115 -> 0.052004539 | D117: =D118/D115 -> 0.04431709 | E117: =E118/E115 -> 0.033759457 | F117: =F118/F115 -> 0.041068541 | G117: =(1-g_gm)*G116/G115 -> 0.049067194 | H117: =$G117*(1-cd_C)^(1/4) -> 0.04779163 | I117: =$G117*(1-cd_C)^(2/4) -> 0.046549227 | J117: =$G117*(1-cd_C)^(3/4) -> 0.045339122 | K117: =$G117*(1-cd_C)^(4/4) -> 0.044160474 | L117: =$G117*(1-cd_C)^(5/4) -> 0.043012467 | M117: =$G117*(1-cd_C)^(6/4) -> 0.041894304 | N117: =$G117*(1-cd_C)^(7/4) -> 0.040805209 | O117: =$G117*(1-cd_C)^(8/4) -> 0.039744427 | P117: =$G117*(1-cd_C)^(9/4) -> 0.038711221 | Q117: =$G117*(1-cd_C)^(10/4) -> 0.037704874 | R117: =$G117*(1-cd_C)^(11/4) -> 0.036724688
...

Sheet Val
A1: Val — 估值。第 0 節為目標價（DCF 與 Comparable 加權；Comparable 依記憶體慣例用前瞻 P/B）；第 5–6 節為目前倍數、十年倍數與規則值（舊法參考）
A2: SanDisk 2025-02 自 WDC 分拆上市，無十年自身倍數歷史：十年 P/B、P/E 以美光（同為記憶體循環股）為 Analogy，見第 6 節
A4: 0. 目標價
A5: 0.1 DCF（股東權益現金流，FY2027–FY2032 明確期＋FY2032 後永續）
A6: 項目 | B6: A（順利） | C6: B（平平） | D6: C（不如預期） | E6: 說明
A7: 情境 EPS（FY2027–FY2032） | E7: PL 頁延伸區塊；FY2030 起為收斂法（灰底）
A8: FY2027 | B8: =PL!D156 -> 263.16538 | C8: =PL!D163 -> 266.52938 | D8: =PL!D170 -> 264.12867
A9: FY2028 | B9: =PL!E156 -> 345.44029 | C9: =PL!E163 -> 219.527 | D9: =PL!E170 -> 195.0021
A10: FY2029 | B10: =PL!F156 -> 406.94244 | C10: =PL!F163 -> 96.26388 | D10: =PL!F170 -> 33.279902
A11: FY2030 | B11: =PL!G156 -> 314.21453 | C11: =PL!G163 -> 51.465201 | D11: =PL!G170 -> 14.529168
A12: FY2031 | B12: =PL!H156 -> 218.00319 | C12: =PL!H163 -> 30.646596 | D12: =PL!H170 -> 8.2707856
A13: FY2032 | B13: =PL!I156 -> 113.75203 | C13: =PL!I163 -> 17.066727 | D13: =PL!I170 -> 5.1780797
A14: 股東現金流＝EPS ×（1 − tp_g ÷ tp_roe） | E14: 記憶體資本密集：FY2027–FY2029 改用每股（淨利＋折舊－資本支出）＝ PL 區塊每股自由現金流（資本支出含合資群分攤）；收斂期（FY2030 起）用 EPS ×（1 − 再投資率）
A15: 再投資率（tp_g ÷ tp_roe，上限 0.8；FY2030 起用） | B15: =MIN(tp_g/tp_roe,0.8) -> 0.1458548 | E15: ROE 為 FY2025–FY2026 平均（In 頁 tp_roe）
A16: FY2027（淨利＋折舊－資本支出，每股） | B16: =PL!E72 -> 241.76927 | C16: =PL!E108 -> 244.88178 | D16: =PL!E144 -> 242.64655
A17: FY2028（淨利＋折舊－資本支出，每股） | B17: =PL!F72 -> 317.8071 | C17: =PL!F108 -> 201.0545 | D17: =PL!F144 -> 178.41269
A18: FY2029（淨利＋折舊－資本支出，每股） | B18: =PL!G72 -> 374.52253 | C18: =PL!G108 -> 86.599096 | D18: =PL!G144 -> 28.614066
A19: FY2030（EPS ×（1 − 再投資率）） | B19: =B11*(1-$B$15) -> 268.38483 | C19: =C11*(1-$B$15) -> 43.958754 | D19: =D11*(1-$B$15) -> 12.410019
A20: FY2031（EPS ×（1 − 再投資率）） | B20: =B12*(1-$B$15) -> 186.20638 | C20: =C12*(1-$B$15) -> 26.176643 | D20: =D12*(1-$B$15) -> 7.0644518
A21: FY2032（EPS ×（1 − 再投資率）） | B21: =B13*(1-$B$15) -> 97.160752 | C21: =C13*(1-$B$15) -> 14.577463 | D21: =D13*(1-$B$15) -> 4.422832
A22: DCF 情境每股價值（折現率 tp_r） | B22: =MAX(0,SUMPRODUCT(B16:B21,1/(1+tp_r)^{1;2;3;4;5;6})+B21*(1+tp_g)/(tp_r-tp_g)/(1+tp_r)^6) -> 2068.2414 | C22: =MAX(0,SUMPRODUCT(C16:C21,1/(1+tp_r)^{1;2;3;4;5;6})+C21*(1+tp_g)/(tp_r-tp_g)/(1+tp_r)^6) -> 650.97941 | D22: =MAX(0,SUMPRODUCT(D16:D21,1/(1+tp_r)^{1;2;3;4;5;6})+D21*(1+tp_g)/(tp_r-tp_g)/(1+tp_r)^6) -> 448.16764 | E22: Σ 明確期現金流 ÷ (1＋r)^t ＋ 永續價值 ÷ (1＋r)^6；永續價值＝FY2032 現金流 ×(1＋g)÷(r−g)；基準日 2026 年底，t＝1 對 FY2027（FY2027 於 2027-06 結束，t 以會計年度計，略低估）；負值取 0（股東有限責任）
A23: DCF 情境價值推到 12 個月後（×(1＋tp_r)） | B23: =B22*(1+tp_r) -> 2275.0655 | C23: =C22*(1+tp_r) -> 716.07735 | D23: =D22*(1+tp_r) -> 492.9844
A24: DCF 目標價（情境加權） | B24: =tp_wA*B23+tp_wB*C23+tp_wC*D23 -> 1139.1552 | E24: Σ 權重 × 情境價值 ×(1＋r)；權重見 In 頁 tp_wA／tp_wB／tp_wC
A26: 0.2 Comparable（市場主流同業前瞻 P/B；記憶體慣例）
A27: 同業與前瞻 P/B | B27: 代號 | C27: 前瞻 P/B | D27: 日期 | E27: 來源 | F27: 標記
A28: 美光 | B28: MU | C28: 3.35 | D28: 2026-10-23 | E28: MarketScreener：現價 ÷ FY2027E（2027-09）每股淨值（micron/ 模型同值） | F28: Interested-party
A29: SK 海力士 | B29: 000660.KS | C29: 1.35 | D29: 2026-10-23 | E29: MarketScreener：現價 ÷ 2027E 每股淨值（skhynix/ 模型同值） | F29: Interested-party
A30: 三星電子 | B30: 005930.KS | C30: 1.26 | D30: 2026-10-23 | E30: MarketScreener：現價 ÷ 2027E 每股淨值（samsung/ 模型同值） | F30: Interested-party
A31: Kioxia | B31: 285A.T | C31: =12755/7808 -> 1.6335809 | D31: 2026-10-23 | E31: 現價 ¥12,755（stockanalysis，分割後）÷ MarketScreener FY2028E（2028-03）每股淨值 ¥7,808 | F31: Interested-party
A32: 同業前瞻 P/B 中位數 | B32: =MEDIAN(C28:C31) -> 1.4917905 | E32: 記憶體同業（美光、SK 海力士、三星、Kioxia；無 A 股）。WDC（硬碟）不列入 P/B：僅有落後 P/B 13.5x（stockanalysis），與記憶體不可比；P/E 並列參考見下方。SanDisk 自身現價 ÷ 2027 年底每股淨值（FY27、FY28 共識平均）約 2.9x
A33: 12 個月後的前瞻每股淨值（情境加權） | B33: =tp_wA*(PL!F70+PL!G70)/2+tp_wB*(PL!F106+PL!G106)/2+tp_wC*(PL!F142+PL!G142)/2 -> 513.85413 | E33: 同業倍數＝現價 ÷ 約 14 個月後（約 2027 年底）每股淨值；對應 12 個月後（約 2027-10）用約 2028 年底每股淨值＝（FY2028 年底＋FY2029 年底）÷ 2（會計年度 6 月，依月份調整）
A34: Comparable 目標價 | B34: =B32*B33 -> 766.56269 | E34: 同業中位數 × 前瞻每股淨值
A35: 12 個月後的前瞻 EPS（情境加權） | B35: =tp_wA*(8/12*B9+4/12*B10)+tp_wB*(8/12*C9+4/12*C10)+tp_wC*(8/12*D9+4/12*D10) -> 227.22089 | E35: 約 2027-10 時的未來 12 月（2027-11～2028-10）≈ 8／12 × FY2028（2027-07～2028-06）＋4／12 × FY2029（會計年度 6 月，依月份調整）
A37: 並列參考：同業前瞻 P/E（不進目標價）
A38: 同業與前瞻 P/E | B38: 代號 | C38: 前瞻 P/E | D38: 日期 | E38: 來源 | F38: 標記
A39: 美光 | B39: MU | C39: =877.55/173 -> 5.0725434 | D39: 2026-10-23 | E39: 現價 877.55 ÷ MarketScreener FY2027 共識 EPS 173（micron/ 模型 In 頁） | F39: Interested-party
A40: SK 海力士 | B40: 000660.KS | C40: =1277000/475721 -> 2.6843465 | D40: 2026-10-23 | E40: 現價 ÷ MarketScreener 2027 共識 EPS（skhynix/ 模型 In 頁） | F40: Interested-party
A41: 三星電子 | B41: 005930.KS | C41: =215500/72279 -> 2.9815022 | D41: 2026-10-23 | E41: 現價 ÷ MarketScreener 2027 共識 EPS（samsung/ 模型 In 頁） | F41: Interested-party
A42: Kioxia | B42: 285A.T | C42: =12755/3486 -> 3.6589214 | D42: 2026-10-23 | E42: 現價 ¥12,755 ÷ MarketScreener FY2027（2027-03）共識 EPS ¥3,486 | F42: Interested-party
A43: Western Digital | B43: WDC | C43: 11.91 | D43: 2026-10-23 | E43: stockanalysis 統計頁 Forward P/E（硬碟為主，參考） | F43: Interested-party
A44: 同業前瞻 P/E 中位數（並列參考） | B44: =MEDIAN(C39:C43) -> 3.6589214
A45: Comparable（P/E 並列參考）＝中位數 × 12 個月後前瞻 EPS | B45: =B44*B35 -> 831.38337 | E45: 不進目標價：高峰期 EPS × 低倍數，與 P/B 法互相對照
A47: 0.3 結論
A48: 項目 | B48: 數值 | E48: 說明
A49: 目標價（DCF 與 Comparable 加權） | B49: =tp_w_dcf*B24+(1-tp_w_dcf)*B34 -> 952.85895 | E49: tp_w_dcf × DCF 目標價＋（1 − tp_w_dcf）× Comparable 目標價；tp_w_dcf 見 In 頁
A50: Comparable 目標價（市場主流同業法） | B50: =B34 -> 766.56269 | E50: 引用 0.2（前瞻 P/B）
A51: 市場共識目標價 | B51: =cons_tp -> 2144 | E51: stockanalysis（S&P Global，25 位，2026-10-18 更新）：平均 2,144（中位數 2,150；區間 1,000–3,600）
A52: 上檔空間：加權目標價 | B52: =B49/px-1 -> -0.2303426 | E52: 現價＝In 頁 px（2026-10-23 收盤）
A53: 上檔空間：Comparable 目標價 | B53: =B50/px-1 -> -0.38082059
A54: 上檔空間級距 | B54: =IF(B52>0.5,"大於 50%",IF(B52>0.25,"25%–50%",IF(B52>=0,"0%–25%",IF(B52>=-0.25,"0%～−25%",IF(B52>=-0.5,"−25%～−50%","小於 −50%"))))) -> 0%～−25% | E54: 以「上檔空間：加權目標價」分六級（Andy 2026-10-25 14:00）
A55: 投資建議 | B55: =IF(B52>0.5,"強力買進",IF(B52>0.25,"買進",IF(B52>=-0.25,"中立",IF(B52>=-0.5,"放空","強力放空")))) -> 中立 | E55: 依上檔空間固定規則（Andy 2026-10-25 14:17）：>+50% 強力買進、+25～+50% 買進、−25～+25% 中立、−50～−25% 放空、<−50% 強力放空
A56: DCF ÷ 現價 | B56: =B23/px -> 1.8376498 | C56: =C23/px -> 0.57840064 | D56: =D23/px -> 0.39820069 | E56: 各情境 DCF 價值（推到 12 個月後）÷ 現價（A／B／C）
A57: 與市場共識目標價的差距：EPS 因素（記憶體以每股淨值計） | B57: =B33/((cons_bv28+cons_bv29)/2)-1 -> -0.14620898 | E57: 本模型約 2028 年底每股淨值（情境加權）÷ 共識（FY2028、FY2029 年底平均 601.9）− 1（Comparable 用 P/B，故以每股淨值代 EPS）
A58: 對照：前瞻 EPS ÷ 共識前瞻 EPS − 1 | B58: =B35/(8/12*cons_eps28+4/12*cons_eps29)-1 -> -0.16554944 | E58: 共識前瞻 EPS＝8／12 × FY2028 267.6＋4／12 × FY2029 281.7（MarketScreener）
A59: 與市場共識目標價的差距：倍數因素 | B59: =(cons_tp/((cons_bv28+cons_bv29)/2))/B32-1 -> 1.387969 | E59: ="共識目標價隱含 P/B "&TEXT(cons_tp/((cons_bv28+cons_bv29)/2),"0.00")&"x（÷ 共識約 2028 年底每股淨值），同業中位數 "&TEXT(B32,"0.00")&"x" -> 共識目標價隱含 P/B 3.56x（÷ 共識約 2028 年底每股淨值），同業中位數 1.49x
A60: 價格帶（DCF 不如預期～順利） | B60: =TEXT(D23,"#,##0")&"～"&TEXT(B23,"#,##0") -> 493～2,275 | E60: C 情境價值～A 情境價值（推到 12 個月後）
A61: 歷史倍數檢查：現價隱含 P/B 的十年分位（A／B／C） | B61: =IF(px/PL!F11>=MAX($B$95:$B$104),1,IF(px/PL!F11<=MIN($B$95:$B$104),0,PERCENTRANK($B$95:$B$104,px/PL!F11))) -> 0.979 | C61: =IF(px/PL!F21>=MAX($B$95:$B$104),1,IF(px/PL!F21<=MIN($B$95:$B$104),0,PERCENTRANK($B$95:$B$104,px/PL!F21))) -> 1 | D61: =IF(px/PL!F31>=MAX($B$95:$B$104),1,IF(px/PL!F31<=MIN($B$95:$B$104),0,PERCENTRANK($B$95:$B$104,px/PL!F31))) -> 1 | E61: 現價 ÷ 各情境 FY2028 年底每股淨值，在 2016–2025 年底 P/B（第 6 節，美光 Analogy）分布的分位（高於最大值記 100%、低於最小值記 0%）；只作檢查，不進目標價（記憶體主估值為 P/B，故以 P/B 代 P/E）
A62: 目標價方法 | B62: DCF：股東現金流 FY2027–FY2029 用每股（淨利＋折舊－資本支出；資本支出含合資群分攤，約營收 6%），FY2030–FY2032 收斂期用 EPS ×（1 − g／ROE），r 10%、g 4%、ROE 為 FY2025–FY2026 平均；明確期＋永續，基準日 2026 年底。Comparable：美光、SK 海力士、三星、Kioxia 前瞻 P/B 中位數 × 約 2028 年底每股淨值（情境加權）；P/E 並列參考不進目標價。偏誤：FY2027–FY2029 為高峰期盈餘、收斂期淨利率以美光十年平均代替（SanDisk 無自身歷史）；大量買回壓低帳面淨值，P/B 法偏低估。
A80: 5. 目前倍數（僅供參考）
A81: 項目 | B81: A／數值 | C81: B | D81: C | E81: 備註
A82: 現價（2026-10-23 收盤） | B82: =px -> 1238.03 | E82: stockanalysis、MarketScreener
A83: P/E：現價 ÷ FY2026 EPS 73.76 | B83: =px/a26_eps -> 16.784572 | E83: 落後
A84: P/B：現價 ÷ FY2026 年底每股淨值 | B84: =px/PL!D70 -> 11.519595 | E84: FY2026 年底權益 15.736 ÷ 146.42 百萬股
A85: 現價 ÷ FY2027 EPS（模型） | B85: =px/PL!E10 -> 4.7043802 | C85: =px/PL!E20 -> 4.6450038 | D85: =px/PL!E30 -> 4.687223 | E85: A／B／C
A86: 現價 ÷ FY2028 EPS（模型） | B86: =px/PL!F10 -> 3.583919 | C86: =px/PL!F20 -> 5.639534 | D86: =px/PL!F30 -> 6.3488034 | E86: A／B／C
A87: 現價 ÷ FY2028 年底每股淨值（模型） | B87: =px/PL!F11 -> 2.4388932 | C87: =px/PL!F21 -> 2.9250801 | D87: =px/PL!F31 -> 3.0586096 | E87: A／B／C；第 0 節歷史分位檢查用
A90: 6. 十年倍數與規則值（2016–2025 年底；見頂年 25 分位、中段中位數、谷底 75 分位）
A91: 規則（Andy 2026-10-13）：合理倍數＝2016–2025 年底倍數依循環位置取分位。SanDisk 無十年自身歷史，以美光為 Analogy（同為記憶體循環股；差異：美光 DRAM 為主）。見頂與中段用 FY2027 A、谷底用 FY2028 C。
A93: P/B（主）：十年歷史倍數
A94: 年底 | B94: 美光（Analogy；會計年度 8 月底） | C94: 標記／說明
A95: 2016 | B95: 1.29 | C95: 美光（Analogy；會計年度 8 月底）：Analogy
A96: 2017 | B96: 1.78 | C96: 來源：micron/dist/20261025_美光模型_v0.4.xlsx｜Val!B82:B91（macrotrends）；SanDisk 自身上市不足十年
A97: 2018 | B97: 1.79
A98: 2019 | B98: 1.33
A99: 2020 | B99: 1.27
A100: 2021 | B100: 1.83
A101: 2022 | B101: 1.22
A102: 2023 | B102: 1.72
A103: 2024 | B103: 2.35
A104: 2025 | B104: 2.46
A105: 25 分位（各來源） | B105: =PERCENTILE(B95:B104,0.25) -> 1.3
A106: 中位數（各來源） | B106: =MEDIAN(B95:B104) -> 1.75
A107: 75 分位（各來源） | B107: =PERCENTILE(B95:B104,0.75) -> 1.82
A108: 最小（各來源） | B108: =MIN(B95:B104) -> 1.22
A109: 最大（各來源） | B109: =MAX(B95:B104) -> 2.46
A110: 採用 25 分位（P/B） | B110: =ROUND(AVERAGE(B105),2) -> 1.3
A111: 採用 中位數（P/B） | B111: =ROUND(AVERAGE(B106),2) -> 1.75
A112: 採用 75 分位（P/B） | B112: =ROUND(AVERAGE(B107),2) -> 1.82
A113: 採用 最小（P/B） | B113: =ROUND(MIN(B108),2) -> 1.22
A114: 採用 最大（P/B） | B114: =ROUND(MAX(B109),2) -> 2.46
A116: P/B（主）：規則值
A117: 情形 | B117: 循環位置 | C117: 倍數 | D117: 基準 | E117: 每股基準 | F117: 隱含股價 | G117: 相對目前 | H117: 現價 ÷ 基準
A118: 規則值：見頂（P/B） | B118: 見頂年 → 25 分位 | C118: =B110 -> 1.3 | D118: FY2027 年底每股淨值（A） | E118: =PL!E70 -> 270.12928 | F118: =C118*E118 -> 351.16806 | G118: =F118/px-1 -> -0.71634931 | H118: =px/E118 -> 4.5831019
A119: 規則值：中段（P/B） | B119: 中段 → 中位數 | C119: =B111 -> 1.75 | D119: FY2027 年底每股淨值（A） | E119: =PL!E70 -> 270.12928 | F119: =C119*E119 -> 472.72623 | G119: =F119/px-1 -> -0.61816254 | H119: =px/E119 -> 4.5831019
A120: 規則值：谷底（P/B） | B120: 谷底 → 75 分位 | C120: =B112 -> 1.82 | D120: FY2028 年底每股淨值（C） | E120: =PL!F142 -> 404.76889 | F120: =C120*E120 -> 736.67938 | G120: =F120/px-1 -> -0.40495838 | H120: =px/E120 -> 3.0586096
A123: P/E（對照）：十年歷史倍數
A124: 年底 | B124: 美光（Analogy；SEC 10-K 換算） | C124: 標記／說明
A125: 2016 | C125: 美光（Analogy；SEC 10-K 換算）：Analogy
A126: 2017 | B126: 6.5131421 | C126: 來源：micron/dist/20261025_美光模型_v0.4.xlsx｜Val!B115:B124；虧損年不計
A127: 2018 | B127: 4.0895833
...

Sheet Recon
A1: Recon — 本模型 vs 公司實績、指引與共識（共識只作對照，未用於校準）。差距＝模型 ÷ 對照 − 1（百分點列為相減）
A3: 項目 | B3: 對照值 | C3: 模型 A | D3: 差距 A | E3: 模型 B | F3: 差距 B | G3: 模型 C | H3: 差距 C | I3: 對照來源 | J3: 說明
A4: A. 實績與公司指引
A5: FY2026 營收（實績重現） | B5: =a26_rev -> 20.248 | C5: =PL!D5 -> 20.248 | D5: =C5/B5-1 -> 0 | E5: =PL!D15 -> 20.248 | F5: =E5/B5-1 -> 0 | G5: =PL!D25 -> 20.248 | H5: =G5/B5-1 -> 0 | I5: SanDisk FQ4 FY26 新聞稿（8-K，2026-08-05） | J5: 恆等式
A6: FQ1 FY27 營收 vs 公司指引中值 | B6: =g_rev -> 10.55 | C6: =PL!G44 -> 10.549632 | D6: =C6/B6-1 -> -3.4905955e-05 | E6: =PL!G80 -> 10.549632 | F6: =E6/B6-1 -> -3.4905955e-05 | G6: =PL!G116 -> 10.549632 | H6: =G6/B6-1 -> -3.4905955e-05 | I6: SanDisk FQ4 FY26 新聞稿（8-K，2026-08-05） | J6: 恆等式（市場層份額由指引推得）
A7: FQ1 FY27 毛利率 vs 指引中值（百分點） | B7: =g_gm -> 0.84 | C7: =PL!G47 -> 0.84 | D7: =C7-B7 -> 0 | E7: =PL!G83 -> 0.84 | F7: =E7-B7 -> 0 | G7: =PL!G119 -> 0.84 | H7: =G7-B7 -> 0 | I7: SanDisk FQ4 FY26 新聞稿（8-K，2026-08-05） | J7: 恆等式（單位成本以此校準）
A8: FQ1 FY27 EPS vs 指引中值（non-GAAP） | B8: =g_eps -> 45 | C8: =PL!G52 -> 45.600111 | D8: =C8/B8-1 -> 0.013335798 | E8: =PL!G88 -> 45.600111 | F8: =E8/B8-1 -> 0.013335798 | G8: =PL!G124 -> 45.600111 | H8: =G8/B8-1 -> 0.013335798 | I8: SanDisk FQ4 FY26 新聞稿（8-K，2026-08-05） | J8: 本模型為 GAAP 營業費用＋15% 稅率，近似 non-GAAP（差約 SBC）
A9: B. 共識（MarketScreener 2026-10-23；只作參考）
A10: FY2027 營收 vs 共識 | B10: =cons_rev27 -> 49.135 | C10: =PL!E5 -> 53.023012 | D10: =C10/B10-1 -> 0.079129178 | E10: =PL!E15 -> 53.55663 | F10: =E10/B10-1 -> 0.08998942 | G10: =PL!E25 -> 53.209139 | H10: =G10/B10-1 -> 0.082917257 | I10: MarketScreener 預估頁（2026-10-25 擷取；頁面為 10-23 收盤；會計年度 6 月）
A11: FY2028 營收 vs 共識 | B11: =cons_rev28 -> 58.436 | C11: =PL!F5 -> 60.304259 | D11: =C11/B11-1 -> 0.031971022 | E11: =PL!F15 -> 42.831169 | F11: =E11/B11-1 -> -0.2670414 | G11: =PL!F25 -> 39.074356 | H11: =G11/B11-1 -> -0.33133075 | I11: MarketScreener 預估頁（2026-10-25 擷取；頁面為 10-23 收盤；會計年度 6 月）
A12: FY2027 EPS vs 共識 | B12: =cons_eps27 -> 217.4 | C12: =PL!E10 -> 263.16538 | D12: =C12/B12-1 -> 0.21051231 | E12: =PL!E20 -> 266.52938 | F12: =E12/B12-1 -> 0.22598613 | G12: =PL!E30 -> 264.12867 | H12: =G12/B12-1 -> 0.2149433 | I12: MarketScreener 預估頁（2026-10-25 擷取；頁面為 10-23 收盤；會計年度 6 月） | J12: 差距超過 30% 見 README
A13: FY2028 EPS vs 共識 | B13: =cons_eps28 -> 267.6 | C13: =PL!F10 -> 345.44029 | D13: =C13/B13-1 -> 0.29088298 | E13: =PL!F20 -> 219.527 | F13: =E13/B13-1 -> -0.17964498 | G13: =PL!F30 -> 195.0021 | H13: =G13/B13-1 -> -0.2712926 | I13: MarketScreener 預估頁（2026-10-25 擷取；頁面為 10-23 收盤；會計年度 6 月）
A14: FY2028 年底每股淨值 vs 共識 | B14: =cons_bv28 -> 553.1 | C14: =PL!F11 -> 507.6196 | D14: =C14/B14-1 -> -0.082228162 | E14: =PL!F21 -> 423.24652 | F14: =E14/B14-1 -> -0.23477396 | G14: =PL!F31 -> 404.76889 | H14: =G14/B14-1 -> -0.26818136 | I14: MarketScreener 預估頁（2026-10-25 擷取；頁面為 10-23 收盤；會計年度 6 月）
A15: C. 市場層一致性
A16: SanDisk 營收 ÷ 市場層（公司口徑係數 sd_k） | C16: =sd_k -> 0.9994077 | I16: In 頁
A17: Kioxia＋SanDisk 合資群份額 CY2027（市場層 Ann 頁，A／B／C） | C17: 0.26205287 | E17: 0.25905287 | G17: 0.25605287 | I17: markets/nand/dist/20261025_NAND市場模型_v0.1.xlsx｜Ann!F27（kioxia/ 模型讀同一組列）

Sheet Sens
A1: Sens — 一次動一個輸入（情境 A）：對 FY2027、FY2028 營收與 EPS 的影響。每個案例為一個完整推導區塊（本頁下方，與 PL 同一引擎）
A3: 案例 | B3: 設定 | C3: FY2027 營收 $B | D3: FY2027 EPS | E3: 相對基準 | F3: FY2028 營收 $B | G3: FY2028 EPS | H3: 相對基準 | I3: FY2027 毛利率
A4: 基準（情境 A） | B4: PL 區塊 A | C4: =PL!E55 -> 53.023012 | D4: =PL!E69 -> 263.16538 | E4: =D4/D$4-1 -> 0 | F4: =PL!F55 -> 60.304259 | G4: =PL!F69 -> 345.44029 | H4: =G4/G$4-1 -> 0 | I4: =PL!E57 -> 0.86916237
A5: 市場層營收 −20%（價格；FQ2 FY27 起） | B5: 價格係數 0.8 | C5: =E75 -> 44.528336 | D5: =E89 -> 208.58416 | E5: =D5/D$4-1 -> -0.20740274 | F5: =F75 -> 48.243407 | G5: =F89 -> 250.37072 | H5: =G5/G$4-1 -> -0.27521272 | I5: =E77 -> 0.84420246
A6: 市場層營收 +20%（價格） | B6: 價格係數 1.2 | C6: =E125 -> 61.517688 | D6: =E139 -> 319.85932 | E6: =D6/D$4-1 -> 0.21543085 | F6: =F125 -> 72.36511 | G6: =F139 -> 450.98277 | H6: =G6/G$4-1 -> 0.30553032 | I6: =E127 -> 0.8872291
A7: 份額 ×0.9（營收與位元） | B7: 份額係數 0.9 | C7: =E175 -> 47.720711 | D7: =E189 -> 233.37193 | E7: =D7/D$4-1 -> -0.11321186 | F7: =F175 -> 54.273833 | G7: =F189 -> 301.99764 | H7: =G7/G$4-1 -> -0.12576022 | I7: =E177 -> 0.86916237
A8: 份額 ×1.1 | B8: 份額係數 1.1 | C8: =E225 -> 58.325313 | D8: =E239 -> 293.57072 | E8: =D8/D$4-1 -> 0.11553702 | F8: =F225 -> 66.334685 | G8: =F239 -> 391.09427 | H8: =G8/G$4-1 -> 0.13216174 | I8: =E227 -> 0.86916237
A9: 每位元成本年降 10%（C 的值） | B9: cd_C | C9: =E275 -> 53.023012 | D9: =E289 -> 262.35391 | E9: =D9/D$4-1 -> -0.0030834972 | F9: =F275 -> 60.304259 | G9: =F289 -> 341.55726 | H9: =G9/G$4-1 -> -0.011240803 | I9: =E277 -> 0.86686346
A10: 每位元成本年降 18% | B10: cd_A 高 | C10: =E325 -> 53.023012 | D10: =E339 -> 263.99311 | E10: =D10/D$4-1 -> 0.0031452904 | F10: =F325 -> 60.304259 | G10: =F339 -> 349.26301 | H10: =G10/G$4-1 -> 0.011066236 | I10: =E327 -> 0.87150595
A11: 指引毛利率 83.0%（校準） | B11: g_gm 低 | C11: =E375 -> 53.023012 | D11: =E389 -> 260.28112 | E11: =D11/D$4-1 -> -0.010959876 | F11: =F375 -> 60.304259 | G11: =F389 -> 341.36161 | H11: =G11/G$4-1 -> -0.011807172 | I11: =E377 -> 0.86098502
A12: 指引毛利率 84.9% | B12: g_gm 高 | C12: =E425 -> 53.023012 | D12: =E439 -> 265.76641 | E12: =D12/D$4-1 -> 0.0098836615 | F12: =F425 -> 60.304259 | G12: =F439 -> 349.12852 | H12: =G12/G$4-1 -> 0.0106769 | I12: =E427 -> 0.87652199
A13: 營業費用變動率 2% | B13: ox_var 高 | C13: =E475 -> 53.023012 | D13: =E489 -> 262.54809 | E13: =D13/D$4-1 -> -0.0023456237 | F13: =F475 -> 60.304259 | G13: =F489 -> 344.39833 | H13: =G13/G$4-1 -> -0.0030163168 | I13: =E477 -> 0.86916237
A14: 稅率 20% | B14: tax 高 | C14: =E525 -> 53.023012 | D14: =E539 -> 246.14616 | E14: =D14/D$4-1 -> -0.064671201 | F14: =F525 -> 60.304259 | G14: =F539 -> 319.92233 | H14: =G14/G$4-1 -> -0.073870804 | I14: =E527 -> 0.86916237
A15: 稅率 12% | B15: tax 低 | C15: =E575 -> 53.023012 | D15: =E589 -> 273.47944 | E15: =D15/D$4-1 -> 0.039192333 | F15: =F575 -> 60.304259 | G15: =F589 -> 361.15057 | H15: =G15/G$4-1 -> 0.04547903 | I15: =E577 -> 0.86916237
A16: 買回 ÷ FCF 80% | B16: payout 高 | C16: =E625 -> 53.023012 | D16: =E639 -> 279.54256 | E16: =D16/D$4-1 -> 0.062231514 | F16: =F625 -> 60.304259 | G16: =F639 -> 399.05092 | H16: =G16/G$4-1 -> 0.1551951 | I16: =E627 -> 0.86916237
A17: 買回 ÷ FCF 30% | B17: payout 低 | C17: =E675 -> 53.023012 | D17: =E689 -> 253.27326 | E17: =D17/D$4-1 -> -0.037588978 | F17: =F675 -> 60.304259 | G17: =F689 -> 317.17586 | H17: =G17/G$4-1 -> -0.081821438 | I17: =E677 -> 0.86916237
A18: 情境 B | B18: markets/nand B；成本年降 12% | C18: =PL!E91 -> 53.55663 | D18: =PL!E105 -> 266.52938 | E18: =D18/D$4-1 -> 0.012782865 | F18: =PL!F91 -> 42.831169 | G18: =PL!F105 -> 219.527 | H18: =G18/G$4-1 -> -0.36450087 | I18: =PL!E93 -> 0.87009133
A19: 情境 C | B19: markets/nand C；成本年降 10% | C19: =PL!E127 -> 53.209139 | D19: =PL!E141 -> 264.12867 | E19: =D19/D$4-1 -> 0.0036604206 | F19: =PL!F127 -> 39.074356 | G19: =PL!F141 -> 195.0021 | H19: =G19/G$4-1 -> -0.43549694 | I19: =PL!E129 -> 0.86889852
A21: 讀法：FQ1 FY27 營收由市場層等於公司指引（恆等式），價格係數只作用在 FQ2 FY27 起；毛利率校準改變單位成本起點，之後每年依成本年降。
A60: 案例區塊：市場層營收 −20%（價格；FQ2 FY27 起）（情境 A）
A61: A. 季度 | B61: 單位 | C61: FQ1 FY26（2025Q3） | D61: FQ2 FY26（2025Q4） | E61: FQ3 FY26（2026Q1） | F61: FQ4 FY26（2026Q2） | G61: FQ1 FY27（2026Q3） | H61: FQ2 FY27（2026Q4） | I61: FQ3 FY27（2027Q1） | J61: FQ4 FY27（2027Q2） | K61: FQ1 FY28（2027Q3） | L61: FQ2 FY28（2027Q4） | M61: FQ3 FY28（2028Q1） | N61: FQ4 FY28（2028Q2） | O61: FQ1 FY29（2028Q3） | P61: FQ2 FY29（2028Q4） | Q61: FQ3 FY29（2029Q1） | R61: FQ4 FY29（2029Q2） | T61: 說明
A62: 市場層營收（TrendForce 口徑，同字母情境） | B62: $B | C62: =Units!E4*1 -> 2.31 | D62: =Units!F4*1 -> 3.03 | E62: =Units!G4*1 -> 5.95 | F62: =Units!H4*1 -> 8.97 | G62: =Units!I4*1 -> 10.555884 | H62: =Units!J4*1*0.8 -> 10.406838 | I62: =Units!K4*1*0.8 -> 11.467062 | J62: =Units!L4*1*0.8 -> 12.124942 | K62: =Units!M4*1*0.8 -> 12.179537 | L62: =Units!N4*1*0.8 -> 11.976812 | M62: =Units!O4*1*0.8 -> 12.03074 | N62: =Units!P4*1*0.8 -> 12.08491 | O62: =Units!Q4*1*0.8 -> 12.139325 | ... R62: =Units!T4*1*0.8 -> 12.523267 | T62: markets/nand；Sens 可乘份額係數、價格係數（FQ2 FY27 起）
A63: 位元（市場層；同字母） | B63: EB | C63: =Units!E7*1 -> 31.15528 | D63: =Units!F7*1 -> 33.514723 | E63: =Units!G7*1 -> 38.069333 | F63: =Units!H7*1 -> 33.617215 | G63: =Units!I7*1 -> 34.400604 | H63: =Units!J7*1 -> 36.079657 | I63: =Units!K7*1 -> 38.597443 | J63: =Units!L7*1 -> 40.811827 | ... R63: =Units!T7*1 -> 62.255767
A64: 營收 | B64: $B | C64: =q1_rev -> 2.308 | D64: =q2_rev -> 3.025 | E64: =q3_rev -> 5.95 | F64: =q4_rev -> 8.965 | G64: =G62*sd_k -> 10.549632 | H64: =H62*sd_k -> 10.400674 | I64: =I62*sd_k -> 11.46027 | J64: =J62*sd_k -> 12.11776 | K64: =K62*sd_k -> 12.172323 | L64: =L62*sd_k -> 11.969718 | M64: =M62*sd_k -> 12.023614 | N64: =N62*sd_k -> 12.077753 | ... R64: =R62*sd_k -> 12.51585 | T64: 實績季＝公司財報；之後＝市場層 × 公司口徑係數
A65: 每 EB 營業成本（FQ1 FY27 以指引毛利率校準，之後每年 × (1 − 成本年降)） | B65: $B/EB | C65: =C66/C63 -> 0.052004539 | D65: =D66/D63 -> 0.04431709 | E65: =E66/E63 -> 0.033759457 | F65: =F66/F63 -> 0.041068541 | G65: =(1-g_gm)*G64/G63 -> 0.049067194 | H65: =$G65*(1-cd_A)^(1/4) -> 0.047251525 | I65: =$G65*(1-cd_A)^(2/4) -> 0.045503043 | J65: =$G65*(1-cd_A)^(3/4) -> 0.043819262 | K65: =$G65*(1-cd_A)^(4/4) -> 0.042197787 | L65: =$G65*(1-cd_A)^(5/4) -> 0.040636312 | M65: =$G65*(1-cd_A)^(6/4) -> 0.039132617 | N65: =$G65*(1-cd_A)^(7/4) -> 0.037684565 | O65: =$G65*(1-cd_A)^(8/4) -> 0.036290096 | P65: =$G65*(1-cd_A)^(9/4) -> 0.034947228 | Q65: =$G65*(1-cd_A)^(10/4) -> 0.033654051 | R65: =$G65*(1-cd_A)^(11/4) -> 0.032408726
A66: 營業成本 | B66: $B | C66: =q1_rev*(1-q1_gm) -> 1.620216 | D66: =q2_rev*(1-q2_gm) -> 1.485275 | E66: =q3_rev*(1-q3_gm) -> 1.2852 | F66: =q4_rev*(1-q4_gm) -> 1.38061 | G66: =G63*G65 -> 1.6879411 | H66: =H63*H65 -> 1.7048188 | I66: =I63*I65 -> 1.7563011 | J66: =J63*J65 -> 1.7883441 | K66: =K63*K65 -> 1.8209718 | L66: =L63*L65 -> 1.8541947 | M66: =M63*M65 -> 1.8880237 | N66: =N63*N65 -> 1.9224699 | ... R66: =R63*R65 -> 2.0176301
A67: 毛利率 | B67: % | C67: =1-C66/C64 -> 0.298 | D67: =1-D66/D64 -> 0.509 | E67: =1-E66/E64 -> 0.784 | F67: =1-F66/F64 -> 0.846 | G67: =1-G66/G64 -> 0.84 | H67: =1-H66/H64 -> 0.83608574 | I67: =1-I66/I64 -> 0.84674871 | J67: =1-J66/J64 -> 0.85241958 | ... R67: =1-R66/R64 -> 0.838794
A68: 營業費用 | B68: $B | C68: =q1_rev-q1_rev*(1-q1_gm)-q1_op -> 0.511784 | D68: =q2_rev-q2_rev*(1-q2_gm)-q2_op -> 0.474725 | E68: =q3_rev-q3_rev*(1-q3_gm)-q3_op -> 0.5538 | F68: =q4_rev-q4_rev*(1-q4_gm)-q4_op -> 0.54739 | G68: =(g_ox-ox_var*g_rev)*(1+ox_g)^(0/4)+ox_var*G64 -> 0.59399632 | H68: =(g_ox-ox_var*g_rev)*(1+ox_g)^(1/4)+ox_var*H64 -> 0.60428628 | I68: =(g_ox-ox_var*g_rev)*(1+ox_g)^(2/4)+ox_var*I64 -> 0.62694582 | J68: =(g_ox-ox_var*g_rev)*(1+ox_g)^(3/4)+ox_var*J64 -> 0.64587521 | K68: =(g_ox-ox_var*g_rev)*(1+ox_g)^(4/4)+ox_var*K64 -> 0.65907323 | L68: =(g_ox-ox_var*g_rev)*(1+ox_g)^(5/4)+ox_var*L64 -> 0.67000467 | M68: =(g_ox-ox_var*g_rev)*(1+ox_g)^(6/4)+ox_var*M64 -> 0.68381357 | N68: =(g_ox-ox_var*g_rev)*(1+ox_g)^(7/4)+ox_var*N64 -> 0.69794489 | O68: =(g_ox-ox_var*g_rev)*(1+ox_g)^(8/4)+ox_var*O64 -> 0.71240635 | P68: =(g_ox-ox_var*g_rev)*(1+ox_g)^(9/4)+ox_var*P64 -> 0.72720586 | Q68: =(g_ox-ox_var*g_rev)*(1+ox_g)^(10/4)+ox_var*Q64 -> 0.74281958 | R68: =(g_ox-ox_var*g_rev)*(1+ox_g)^(11/4)+ox_var*R64 -> 0.7600426 | T68: 固定部分以 FQ1 FY27 指引營業費用校準（Derived）
A69: 營業利益 | B69: $B | C69: =C64-C66-C68 -> 0.176 | D69: =D64-D66-D68 -> 1.065 | E69: =E64-E66-E68 -> 4.111 | F69: =F64-F66-F68 -> 7.037 | G69: =G64-G66-G68 -> 8.2676943 | H69: =H64-H66-H68 -> 8.0915692 | I69: =I64-I66-I68 -> 9.077023 | J69: =J64-J66-J68 -> 9.6835408 | ... R69: =R64-R66-R68 -> 9.7381772
A71: 淨利 | B71: $B | C71: =q1_ni -> 0.112 | D71: =q2_ni -> 0.803 | E71: =q3_ni -> 3.615 | F71: =q4_ni -> 6.903 | G71: =(G69+rf*$D87/4)*(1-tax) -> 7.0680172 | H71: =(H69+rf*$D87/4)*(1-tax) -> 6.9183108 | I71: =(I69+rf*$D87/4)*(1-tax) -> 7.7559466 | J71: =(J69+rf*$D87/4)*(1-tax) -> 8.2714867 | K71: =(K69+rf*$E87/4)*(1-tax) -> 8.3957969 | L71: =(L69+rf*$E87/4)*(1-tax) -> 8.1860514 | M71: =(M69+rf*$E87/4)*(1-tax) -> 8.1913708 | N71: =(N69+rf*$E87/4)*(1-tax) -> 8.1960978 | O71: =(O69+rf*$F87/4)*(1-tax) -> 8.3287148 | P71: =(P69+rf*$F87/4)*(1-tax) -> 8.332211 | Q71: =(Q69+rf*$F87/4)*(1-tax) -> 8.4035646 | R71: =(R69+rf*$F87/4)*(1-tax) -> 8.5633089 | T71: （營業利益＋上一年底淨現金 × 收益率 ÷ 4）×（1 − 稅率）
A72: 季 EPS（稀釋） | B72: USD | G72: =G71/(sh0+dil)*1000 -> 45.600111 | H72: =H71/(sh0+dil)*1000 -> 44.634263 | I72: =I71/(sh0+dil)*1000 -> 50.038365 | J72: =J71/(sh0+dil)*1000 -> 53.36443 | K72: =K71/(sh0+dil)*1000 -> 54.166431 | L72: =L71/(sh0+dil)*1000 -> 52.813235 | M72: =M71/(sh0+dil)*1000 -> 52.847554 | N72: =N71/(sh0+dil)*1000 -> 52.878051 | ... R72: =R71/(sh0+dil)*1000 -> 55.247154
A74: B. 年度（會計年度） | B74: 單位 | C74: FY2025A | D74: FY2026A | E74: FY2027 | F74: FY2028 | G74: FY2029 | T74: 說明
A75: 營收 | B75: $B | C75: =a25_rev -> 7.355 | D75: =SUM(C64:F64) -> 20.248 | E75: =SUM(G64:J64) -> 44.528336 | F75: =SUM(K64:N64) -> 48.243407 | G75: =SUM(O64:R64) -> 49.123187
A76: 營業成本 | B76: $B | D76: =SUM(C66:F66) -> 5.771301 | E76: =SUM(G66:J66) -> 6.9374052 | F76: =SUM(K66:N66) -> 7.4856601 | G76: =SUM(O66:R66) -> 7.9638115
A77: 毛利率 | B77: % | D77: =1-D76/D75 -> 0.71496933 | E77: =1-E76/E75 -> 0.84420246 | F77: =1-F76/F75 -> 0.84483558 | G77: =1-G76/G75 -> 0.83788081
A78: 營業費用 | B78: $B | D78: =SUM(C68:F68) -> 2.087699 | E78: =SUM(G68:J68) -> 2.4711036 | F78: =SUM(K68:N68) -> 2.7108364 | G78: =SUM(O68:R68) -> 2.9424744
A79: 營業利益 | B79: $B | D79: =SUM(C69:F69) -> 12.389 | E79: =SUM(G69:J69) -> 35.119827 | F79: =SUM(K69:N69) -> 38.046911 | G79: =SUM(O69:R69) -> 38.216901
A80: 營業利益率 | B80: % | D80: =D79/D75 -> 0.6118629 | E80: =E79/E75 -> 0.78870738 | F80: =F79/F75 -> 0.78864477 | G80: =G79/G75 -> 0.7779809
A81: 淨利 | B81: $B | C81: =a25_ni -> -1.641 | D81: =SUM(C71:F71) -> 11.433 | E81: =SUM(G71:J71) -> 30.013761 | F81: =SUM(K71:N71) -> 32.969317 | G81: =SUM(O71:R71) -> 33.627799
A82: 折舊攤銷（公司本身） | B82: $B | D82: =da_y -> 0.16 | E82: =da_y -> 0.16 | F82: =da_y -> 0.16 | G82: =da_y -> 0.16
A83: 資本支出（含合資群分攤） | B83: $B | D83: 0.562 | E83: =cap_r*E75 -> 2.6717002 | F83: =cap_r*F75 -> 2.8946044 | G83: =cap_r*G75 -> 2.9473912 | T83: FY2026 毛資本支出 0.562（公司簡報；markets/equipment In 頁）
A84: 自由現金流（淨利＋折舊 − 資本支出） | B84: $B | D84: =D81+D82-D83 -> 11.031 | E84: =E81+E82-E83 -> 27.502061 | F84: =F81+F82-F83 -> 30.234713 | G84: =G81+G82-G83 -> 30.840408
A85: 買回 | B85: $B | D85: 4.524 | E85: =MAX(0,payout*E84) -> 13.751031 | F85: =MAX(0,payout*F84) -> 15.117356 | G85: =MAX(0,payout*G84) -> 15.420204 | T85: FY2026 實績 4.524（FQ4）
A86: 期末權益 | B86: $B | D86: =eq0 -> 15.736 | E86: =D86+E81-E85 -> 31.998731 | F86: =E86+F81-F85 -> 49.850691 | G86: =F86+G81-G85 -> 68.058287
A87: 期末淨現金 | B87: $B | D87: =nc0 -> 4.762 | E87: =D87+E84-E85 -> 18.513031 | F87: =E87+F84-F85 -> 33.630387 | G87: =F87+G84-G85 -> 49.050591
A88: 期末流通股數 | B88: 百萬股 | D88: =sh0 -> 146.42 | E88: =D88-E85/bb_px*1000 -> 135.31281 | F88: =E88-F85/bb_px*1000 -> 123.102 | G88: =F88-G85/bb_px*1000 -> 110.64656
A89: EPS（稀釋：期末流通股數＋dil） | B89: USD | C89: =a25_eps -> -11.32 | D89: =a26_eps -> 73.76 | E89: =E81/(E88+dil)*1000 -> 208.58416 | F89: =F81/(F88+dil)*1000 -> 250.37072 | G89: =G81/(G88+dil)*1000 -> 282.04956
A90: 每股淨值 BVPS（期末流通股數） | B90: USD | D90: =D86/D88*1000 -> 107.47166 | E90: =E86/E88*1000 -> 236.47968 | F90: =F86/F88*1000 -> 404.95437 | G90: =G86/G88*1000 -> 615.09627
A91: ROE（期末權益） | B91: % | D91: =D81/D86 -> 0.72655058 | E91: =E81/E86 -> 0.93796724 | F91: =F81/F86 -> 0.66136128 | G91: =G81/G86 -> 0.49410294
A92: 每股自由現金流（稀釋） | B92: USD | E92: =E84/(E88+dil)*1000 -> 191.1288 | F92: =F84/(F88+dil)*1000 -> 229.60399 | G92: =G84/(G88+dil)*1000 -> 258.67062
A93: 檢查：FY2026 營收、淨利 − 實績（應為 0） | B93: $B | D93: =ABS(D75-a26_rev)+ABS(D81-a26_ni) -> 0
A110: 案例區塊：市場層營收 +20%（價格）（情境 A）
A111: A. 季度 | B111: 單位 | C111: FQ1 FY26（2025Q3） | D111: FQ2 FY26（2025Q4） | E111: FQ3 FY26（2026Q1） | F111: FQ4 FY26（2026Q2） | G111: FQ1 FY27（2026Q3） | H111: FQ2 FY27（2026Q4） | I111: FQ3 FY27（2027Q1） | J111: FQ4 FY27（2027Q2） | K111: FQ1 FY28（2027Q3） | L111: FQ2 FY28（2027Q4） | M111: FQ3 FY28（2028Q1） | N111: FQ4 FY28（2028Q2） | O111: FQ1 FY29（2028Q3） | P111: FQ2 FY29（2028Q4） | Q111: FQ3 FY29（2029Q1） | R111: FQ4 FY29（2029Q2） | T111: 說明
A112: 市場層營收（TrendForce 口徑，同字母情境） | B112: $B | C112: =Units!E4*1 -> 2.31 | D112: =Units!F4*1 -> 3.03 | E112: =Units!G4*1 -> 5.95 | F112: =Units!H4*1 -> 8.97 | G112: =Units!I4*1 -> 10.555884 | H112: =Units!J4*1*1.2 -> 15.610257 | I112: =Units!K4*1*1.2 -> 17.200593 | J112: =Units!L4*1*1.2 -> 18.187413 | K112: =Units!M4*1*1.2 -> 18.269305 | L112: =Units!N4*1*1.2 -> 17.965217 | M112: =Units!O4*1*1.2 -> 18.046109 | N112: =Units!P4*1*1.2 -> 18.127366 | O112: =Units!Q4*1*1.2 -> 18.208988 | ... R112: =Units!T4*1*1.2 -> 18.784901 | T112: markets/nand；Sens 可乘份額係數、價格係數（FQ2 FY27 起）
A113: 位元（市場層；同字母） | B113: EB | C113: =Units!E7*1 -> 31.15528 | D113: =Units!F7*1 -> 33.514723 | E113: =Units!G7*1 -> 38.069333 | F113: =Units!H7*1 -> 33.617215 | G113: =Units!I7*1 -> 34.400604 | H113: =Units!J7*1 -> 36.079657 | I113: =Units!K7*1 -> 38.597443 | J113: =Units!L7*1 -> 40.811827 | ... R113: =Units!T7*1 -> 62.255767
A114: 營收 | B114: $B | C114: =q1_rev -> 2.308 | D114: =q2_rev -> 3.025 | E114: =q3_rev -> 5.95 | F114: =q4_rev -> 8.965 | G114: =G112*sd_k -> 10.549632 | H114: =H112*sd_k -> 15.601011 | I114: =I112*sd_k -> 17.190405 | J114: =J112*sd_k -> 18.17664 | K114: =K112*sd_k -> 18.258484 | L114: =L112*sd_k -> 17.954577 | M114: =M112*sd_k -> 18.035421 | N114: =N112*sd_k -> 18.116629 | ... R114: =R112*sd_k -> 18.773775 | T114: 實績季＝公司財報；之後＝市場層 × 公司口徑係數
A115: 每 EB 營業成本（FQ1 FY27 以指引毛利率校準，之後每年 × (1 − 成本年降)） | B115: $B/EB | C115: =C116/C113 -> 0.052004539 | D115: =D116/D113 -> 0.04431709 | E115: =E116/E113 -> 0.033759457 | F115: =F116/F113 -> 0.041068541 | G115: =(1-g_gm)*G114/G113 -> 0.049067194 | H115: =$G115*(1-cd_A)^(1/4) -> 0.047251525 | I115: =$G115*(1-cd_A)^(2/4) -> 0.045503043 | J115: =$G115*(1-cd_A)^(3/4) -> 0.043819262 | K115: =$G115*(1-cd_A)^(4/4) -> 0.042197787 | L115: =$G115*(1-cd_A)^(5/4) -> 0.040636312 | M115: =$G115*(1-cd_A)^(6/4) -> 0.039132617 | N115: =$G115*(1-cd_A)^(7/4) -> 0.037684565 | O115: =$G115*(1-cd_A)^(8/4) -> 0.036290096 | P115: =$G115*(1-cd_A)^(9/4) -> 0.034947228 | Q115: =$G115*(1-cd_A)^(10/4) -> 0.033654051 | R115: =$G115*(1-cd_A)^(11/4) -> 0.032408726
A116: 營業成本 | B116: $B | C116: =q1_rev*(1-q1_gm) -> 1.620216 | D116: =q2_rev*(1-q2_gm) -> 1.485275 | E116: =q3_rev*(1-q3_gm) -> 1.2852 | F116: =q4_rev*(1-q4_gm) -> 1.38061 | G116: =G113*G115 -> 1.6879411 | H116: =H113*H115 -> 1.7048188 | I116: =I113*I115 -> 1.7563011 | J116: =J113*J115 -> 1.7883441 | K116: =K113*K115 -> 1.8209718 | L116: =L113*L115 -> 1.8541947 | M116: =M113*M115 -> 1.8880237 | N116: =N113*N115 -> 1.9224699 | ... R116: =R113*R115 -> 2.0176301
A117: 毛利率 | B117: % | C117: =1-C116/C114 -> 0.298 | D117: =1-D116/D114 -> 0.509 | E117: =1-E116/E114 -> 0.784 | F117: =1-F116/F114 -> 0.846 | G117: =1-G116/G114 -> 0.84 | H117: =1-H116/H114 -> 0.89072383 | I117: =1-I116/I114 -> 0.89783248 | J117: =1-J116/J114 -> 0.90161305 | ... R117: =1-R116/R114 -> 0.89252933
A118: 營業費用 | B118: $B | C118: =q1_rev-q1_rev*(1-q1_gm)-q1_op -> 0.511784 | D118: =q2_rev-q2_rev*(1-q2_gm)-q2_op -> 0.474725 | E118: =q3_rev-q3_rev*(1-q3_gm)-q3_op -> 0.5538 | F118: =q4_rev-q4_rev*(1-q4_gm)-q4_op -> 0.54739 | G118: =(g_ox-ox_var*g_rev)*(1+ox_g)^(0/4)+ox_var*G114 -> 0.59399632 | H118: =(g_ox-ox_var*g_rev)*(1+ox_g)^(1/4)+ox_var*H114 -> 0.65628965 | I118: =(g_ox-ox_var*g_rev)*(1+ox_g)^(2/4)+ox_var*I114 -> 0.68424717 | J118: =(g_ox-ox_var*g_rev)*(1+ox_g)^(3/4)+ox_var*J114 -> 0.70646401 | K118: =(g_ox-ox_var*g_rev)*(1+ox_g)^(4/4)+ox_var*K114 -> 0.71993484 | L118: =(g_ox-ox_var*g_rev)*(1+ox_g)^(5/4)+ox_var*L114 -> 0.72985326 | M118: =(g_ox-ox_var*g_rev)*(1+ox_g)^(6/4)+ox_var*M114 -> 0.74393164 | N118: =(g_ox-ox_var*g_rev)*(1+ox_g)^(7/4)+ox_var*N114 -> 0.75833365 | O118: =(g_ox-ox_var*g_rev)*(1+ox_g)^(8/4)+ox_var*O114 -> 0.77306703 | P118: =(g_ox-ox_var*g_rev)*(1+ox_g)^(9/4)+ox_var*P114 -> 0.78813968 | Q118: =(g_ox-ox_var*g_rev)*(1+ox_g)^(10/4)+ox_var*Q114 -> 0.80426178 | R118: =(g_ox-ox_var*g_rev)*(1+ox_g)^(11/4)+ox_var*R114 -> 0.82262185 | T118: 固定部分以 FQ1 FY27 指引營業費用校準（Derived）
A119: 營業利益 | B119: $B | C119: =C114-C116-C118 -> 0.176 | D119: =D114-D116-D118 -> 1.065 | E119: =E114-E116-E118 -> 4.111 | F119: =F114-F116-F118 -> 7.037 | G119: =G114-G116-G118 -> 8.2676943 | H119: =H114-H116-H118 -> 13.239903 | I119: =I114-I116-I118 -> 14.749857 | J119: =J114-J116-J118 -> 15.681832 | ... R119: =R114-R116-R118 -> 15.933523
A121: 淨利 | B121: $B | C121: =q1_ni -> 0.112 | D121: =q2_ni -> 0.803 | E121: =q3_ni -> 3.615 | F121: =q4_ni -> 6.903 | G121: =(G119+rf*$D137/4)*(1-tax) -> 7.0680172 | H121: =(H119+rf*$D137/4)*(1-tax) -> 11.294394 | I121: =(I119+rf*$D137/4)*(1-tax) -> 12.577855 | J121: =(J119+rf*$D137/4)*(1-tax) -> 13.370034 | K121: =(K119+rf*$E137/4)*(1-tax) -> 13.57373 | L121: =(L119+rf*$E137/4)*(1-tax) -> 13.278738 | M121: =(M119+rf*$E137/4)*(1-tax) -> 13.306734 | N121: =(N119+rf*$E137/4)*(1-tax) -> 13.33424 | O121: =(O119+rf*$F137/4)*(1-tax) -> 13.570815 | P121: =(P119+rf*$F137/4)*(1-tax) -> 13.597296 | Q121: =(Q119+rf*$F137/4)*(1-tax) -> 13.71143 | R121: =(R119+rf*$F137/4)*(1-tax) -> 13.966857 | T121: （營業利益＋上一年底淨現金 × 收益率 ÷ 4）×（1 − 稅率）
A122: 季 EPS（稀釋） | B122: USD | G122: =G121/(sh0+dil)*1000 -> 45.600111 | H122: =H121/(sh0+dil)*1000 -> 72.867061 | I122: =I121/(sh0+dil)*1000 -> 81.147452 | J122: =J121/(sh0+dil)*1000 -> 86.258285 | K122: =K121/(sh0+dil)*1000 -> 87.572449 | L122: =L121/(sh0+dil)*1000 -> 85.669279 | M122: =M121/(sh0+dil)*1000 -> 85.849899 | N122: =N121/(sh0+dil)*1000 -> 86.027356 | ... R122: =R121/(sh0+dil)*1000 -> 90.108756
A124: B. 年度（會計年度） | B124: 單位 | C124: FY2025A | D124: FY2026A | E124: FY2027 | F124: FY2028 | G124: FY2029 | T124: 說明
A125: 營收 | B125: $B | C125: =a25_rev -> 7.355 | D125: =SUM(C114:F114) -> 20.248 | E125: =SUM(G114:J114) -> 61.517688 | F125: =SUM(K114:N114) -> 72.36511 | G125: =SUM(O114:R114) -> 73.684781
A126: 營業成本 | B126: $B | D126: =SUM(C116:F116) -> 5.771301 | E126: =SUM(G116:J116) -> 6.9374052 | F126: =SUM(K116:N116) -> 7.4856601 | G126: =SUM(O116:R116) -> 7.9638115
A127: 毛利率 | B127: % | D127: =1-D126/D125 -> 0.71496933 | E127: =1-E126/E125 -> 0.8872291 | F127: =1-F126/F125 -> 0.89655706 | G127: =1-G126/G125 -> 0.89192054
A128: 營業費用 | B128: $B | D128: =SUM(C118:F118) -> 2.087699 | E128: =SUM(G118:J118) -> 2.6409971 | F128: =SUM(K118:N118) -> 2.9520534 | G128: =SUM(O118:R118) -> 3.1880903
A129: 營業利益 | B129: $B | D129: =SUM(C119:F119) -> 12.389 | E129: =SUM(G119:J119) -> 51.939286 | F129: =SUM(K119:N119) -> 61.927397 | G129: =SUM(O119:R119) -> 62.532879
A130: 營業利益率 | B130: % | D130: =D129/D125 -> 0.6118629 | E130: =E129/E125 -> 0.8442984 | F130: =F129/F125 -> 0.85576318 | G130: =G129/G125 -> 0.84865393
A131: 淨利 | B131: $B | C131: =a25_ni -> -1.641 | D131: =SUM(C121:F121) -> 11.433 | E131: =SUM(G121:J121) -> 44.310301 | F131: =SUM(K121:N121) -> 53.493442 | G131: =SUM(O121:R121) -> 54.846398
A132: 折舊攤銷（公司本身） | B132: $B | D132: =da_y -> 0.16 | E132: =da_y -> 0.16 | F132: =da_y -> 0.16 | G132: =da_y -> 0.16
A133: 資本支出（含合資群分攤） | B133: $B | D133: 0.562 | E133: =cap_r*E125 -> 3.6910613 | F133: =cap_r*F125 -> 4.3419066 | G133: =cap_r*G125 -> 4.4210868 | T133: FY2026 毛資本支出 0.562（公司簡報；markets/equipment In 頁）
A134: 自由現金流（淨利＋折舊 − 資本支出） | B134: $B | D134: =D131+D132-D133 -> 11.031 | E134: =E131+E132-E133 -> 40.77924 | F134: =F131+F132-F133 -> 49.311536 | G134: =G131+G132-G133 -> 50.585311
A135: 買回 | B135: $B | D135: 4.524 | E135: =MAX(0,payout*E134) -> 20.38962 | F135: =MAX(0,payout*F134) -> 24.655768 | G135: =MAX(0,payout*G134) -> 25.292656 | T135: FY2026 實績 4.524（FQ4）
A136: 期末權益 | B136: $B | D136: =eq0 -> 15.736 | E136: =D136+E131-E135 -> 39.656681 | F136: =E136+F131-F135 -> 68.494356 | G136: =F136+G131-G135 -> 98.048098
A137: 期末淨現金 | B137: $B | D137: =nc0 -> 4.762 | E137: =D137+E134-E135 -> 25.15162 | F137: =E137+F134-F135 -> 49.807388 | G137: =F137+G134-G135 -> 75.100044
A138: 期末流通股數 | B138: 百萬股 | D138: =sh0 -> 146.42 | E138: =D138-E135/bb_px*1000 -> 129.95059 | F138: =E138-F135/bb_px*1000 -> 110.03527 | G138: =F138-G135/bb_px*1000 -> 89.60551
A139: EPS（稀釋：期末流通股數＋dil） | B139: USD | C139: =a25_eps -> -11.32 | D139: =a26_eps -> 73.76 | E139: =E131/(E138+dil)*1000 -> 319.85932 | F139: =F131/(F138+dil)*1000 -> 450.98277 | G139: =G131/(G138+dil)*1000 -> 558.59972
A140: 每股淨值 BVPS（期末流通股數） | B140: USD | D140: =D136/D138*1000 -> 107.47166 | E140: =E136/E138*1000 -> 305.16737 | F140: =F136/F138*1000 -> 622.47637 | G140: =G136/G138*1000 -> 1094.2195
A141: ROE（期末權益） | B141: % | D141: =D131/D136 -> 0.72655058 | E141: =E131/E136 -> 1.1173477 | F141: =F131/F136 -> 0.78099052 | G141: =G131/G136 -> 0.55938258
A142: 每股自由現金流（稀釋） | B142: USD | E142: =E134/(E138+dil)*1000 -> 294.36992 | F142: =F134/(F138+dil)*1000 -> 415.72671 | G142: =G134/(G138+dil)*1000 -> 515.20139
A143: 檢查：FY2026 營收、淨利 − 實績（應為 0） | B143: $B | D143: =ABS(D125-a26_rev)+ABS(D131-a26_ni) -> 0
A160: 案例區塊：份額 ×0.9（營收與位元）（情境 A）
A161: A. 季度 | B161: 單位 | C161: FQ1 FY26（2025Q3） | D161: FQ2 FY26（2025Q4） | E161: FQ3 FY26（2026Q1） | F161: FQ4 FY26（2026Q2） | G161: FQ1 FY27（2026Q3） | H161: FQ2 FY27（2026Q4） | I161: FQ3 FY27（2027Q1） | J161: FQ4 FY27（2027Q2） | K161: FQ1 FY28（2027Q3） | L161: FQ2 FY28（2027Q4） | M161: FQ3 FY28（2028Q1） | N161: FQ4 FY28（2028Q2） | O161: FQ1 FY29（2028Q3） | P161: FQ2 FY29（2028Q4） | Q161: FQ3 FY29（2029Q1） | R161: FQ4 FY29（2029Q2） | T161: 說明
A162: 市場層營收（TrendForce 口徑，同字母情境） | B162: $B | C162: =Units!E4*0.9 -> 2.079 | D162: =Units!F4*0.9 -> 2.727 | E162: =Units!G4*0.9 -> 5.355 | F162: =Units!H4*0.9 -> 8.073 | G162: =Units!I4*0.9 -> 9.5002956 | H162: =Units!J4*0.9*1 -> 11.707693 | I162: =Units!K4*0.9*1 -> 12.900445 | J162: =Units!L4*0.9*1 -> 13.640559 | K162: =Units!M4*0.9*1 -> 13.701979 | L162: =Units!N4*0.9*1 -> 13.473913 | M162: =Units!O4*0.9*1 -> 13.534582 | N162: =Units!P4*0.9*1 -> 13.595524 | O162: =Units!Q4*0.9*1 -> 13.656741 | ... R162: =Units!T4*0.9*1 -> 14.088676 | T162: markets/nand；Sens 可乘份額係數、價格係數（FQ2 FY27 起）
A163: 位元（市場層；同字母） | B163: EB | C163: =Units!E7*0.9 -> 28.039752 | D163: =Units!F7*0.9 -> 30.163251 | E163: =Units!G7*0.9 -> 34.2624 | F163: =Units!H7*0.9 -> 30.255494 | G163: =Units!I7*0.9 -> 30.960543 | H163: =Units!J7*0.9 -> 32.471692 | I163: =Units!K7*0.9 -> 34.737698 | J163: =Units!L7*0.9 -> 36.730644 | ... R163: =Units!T7*0.9 -> 56.03019
A164: 營收 | B164: $B | C164: =q1_rev -> 2.308 | D164: =q2_rev -> 3.025 | E164: =q3_rev -> 5.95 | F164: =q4_rev -> 8.965 | G164: =G162*sd_k -> 9.4946686 | H164: =H162*sd_k -> 11.700759 | I164: =I162*sd_k -> 12.892804 | J164: =J162*sd_k -> 13.63248 | K164: =K162*sd_k -> 13.693863 | L164: =L162*sd_k -> 13.465933 | M164: =M162*sd_k -> 13.526566 | N164: =N162*sd_k -> 13.587472 | ... R164: =R162*sd_k -> 14.080331 | T164: 實績季＝公司財報；之後＝市場層 × 公司口徑係數
A165: 每 EB 營業成本（FQ1 FY27 以指引毛利率校準，之後每年 × (1 − 成本年降)） | B165: $B/EB | C165: =C166/C163 -> 0.057782821 | D165: =D166/D163 -> 0.049241211 | E165: =E166/E163 -> 0.037510507 | F165: =F166/F163 -> 0.045631713 | G165: =(1-g_gm)*G164/G163 -> 0.049067194 | H165: =$G165*(1-cd_A)^(1/4) -> 0.047251525 | I165: =$G165*(1-cd_A)^(2/4) -> 0.045503043 | J165: =$G165*(1-cd_A)^(3/4) -> 0.043819262 | K165: =$G165*(1-cd_A)^(4/4) -> 0.042197787 | L165: =$G165*(1-cd_A)^(5/4) -> 0.040636312 | M165: =$G165*(1-cd_A)^(6/4) -> 0.039132617 | N165: =$G165*(1-cd_A)^(7/4) -> 0.037684565 | O165: =$G165*(1-cd_A)^(8/4) -> 0.036290096 | P165: =$G165*(1-cd_A)^(9/4) -> 0.034947228 | Q165: =$G165*(1-cd_A)^(10/4) -> 0.033654051 | R165: =$G165*(1-cd_A)^(11/4) -> 0.032408726
A166: 營業成本 | B166: $B | C166: =q1_rev*(1-q1_gm) -> 1.620216 | D166: =q2_rev*(1-q2_gm) -> 1.485275 | E166: =q3_rev*(1-q3_gm) -> 1.2852 | F166: =q4_rev*(1-q4_gm) -> 1.38061 | G166: =G163*G165 -> 1.519147 | H166: =H163*H165 -> 1.534337 | I166: =I163*I165 -> 1.580671 | J166: =J163*J165 -> 1.6095097 | K166: =K163*K165 -> 1.6388746 | L166: =L163*L165 -> 1.6687752 | M166: =M163*M165 -> 1.6992213 | N166: =N163*N165 -> 1.7302229 | ... R166: =R163*R165 -> 1.8158671
A167: 毛利率 | B167: % | C167: =1-C166/C164 -> 0.298 | D167: =1-D166/D164 -> 0.509 | E167: =1-E166/E164 -> 0.784 | F167: =1-F166/F164 -> 0.846 | G167: =1-G166/G164 -> 0.84 | H167: =1-H166/H164 -> 0.86886859 | I167: =1-I166/I164 -> 0.87739897 | J167: =1-J166/J164 -> 0.88193566 | ... R167: =1-R166/R164 -> 0.8710352
A168: 營業費用 | B168: $B | C168: =q1_rev-q1_rev*(1-q1_gm)-q1_op -> 0.511784 | D168: =q2_rev-q2_rev*(1-q2_gm)-q2_op -> 0.474725 | E168: =q3_rev-q3_rev*(1-q3_gm)-q3_op -> 0.5538 | F168: =q4_rev-q4_rev*(1-q4_gm)-q4_op -> 0.54739 | G168: =(g_ox-ox_var*g_rev)*(1+ox_g)^(0/4)+ox_var*G164 -> 0.58344669 | H168: =(g_ox-ox_var*g_rev)*(1+ox_g)^(1/4)+ox_var*H164 -> 0.61728712 | I168: =(g_ox-ox_var*g_rev)*(1+ox_g)^(2/4)+ox_var*I164 -> 0.64127116 | J168: =(g_ox-ox_var*g_rev)*(1+ox_g)^(3/4)+ox_var*J164 -> 0.66102241 | K168: =(g_ox-ox_var*g_rev)*(1+ox_g)^(4/4)+ox_var*K164 -> 0.67428863 | L168: =(g_ox-ox_var*g_rev)*(1+ox_g)^(5/4)+ox_var*L164 -> 0.68496682 | M168: =(g_ox-ox_var*g_rev)*(1+ox_g)^(6/4)+ox_var*M164 -> 0.69884309 | N168: =(g_ox-ox_var*g_rev)*(1+ox_g)^(7/4)+ox_var*N164 -> 0.71304208 | O168: =(g_ox-ox_var*g_rev)*(1+ox_g)^(8/4)+ox_var*O164 -> 0.72757152 | P168: =(g_ox-ox_var*g_rev)*(1+ox_g)^(9/4)+ox_var*P164 -> 0.74243932 | Q168: =(g_ox-ox_var*g_rev)*(1+ox_g)^(10/4)+ox_var*Q164 -> 0.75818013 | R168: =(g_ox-ox_var*g_rev)*(1+ox_g)^(11/4)+ox_var*R164 -> 0.77568741 | T168: 固定部分以 FQ1 FY27 指引營業費用校準（Derived）
A169: 營業利益 | B169: $B | C169: =C164-C166-C168 -> 0.176 | D169: =D164-D166-D168 -> 1.065 | E169: =E164-E166-E168 -> 4.111 | F169: =F164-F166-F168 -> 7.037 | G169: =G164-G166-G168 -> 7.3920749 | H169: =H164-H166-H168 -> 9.5491345 | I169: =I164-I166-I168 -> 10.670862 | J169: =J164-J166-J168 -> 11.361948 | ... R169: =R164-R166-R168 -> 11.488777
A171: 淨利 | B171: $B | C171: =q1_ni -> 0.112 | D171: =q2_ni -> 0.803 | E171: =q3_ni -> 3.615 | F171: =q4_ni -> 6.903 | G171: =(G169+rf*$D187/4)*(1-tax) -> 6.3237407 | H171: =(H169+rf*$D187/4)*(1-tax) -> 8.1572413 | I171: =(I169+rf*$D187/4)*(1-tax) -> 9.1107093 | J171: =(J169+rf*$D187/4)*(1-tax) -> 9.6981328 | K171: =(K169+rf*$E187/4)*(1-tax) -> 9.8440649 | L171: =(L169+rf*$E187/4)*(1-tax) -> 9.6158319 | M171: =(M169+rf*$E187/4)*(1-tax) -> 9.6296959 | N171: =(N169+rf*$E187/4)*(1-tax) -> 9.6430456 | O171: =(O169+rf*$F187/4)*(1-tax) -> 9.8073206 | P171: =(P169+rf*$F187/4)*(1-tax) -> 9.8195987 | Q171: =(Q169+rf*$F187/4)*(1-tax) -> 9.9018276 | R171: =(R169+rf*$F187/4)*(1-tax) -> 10.087384 | T171: （營業利益＋上一年底淨現金 × 收益率 ÷ 4）×（1 − 稅率）
A172: 季 EPS（稀釋） | B172: USD | G172: =G171/(sh0+dil)*1000 -> 40.798327 | H172: =H171/(sh0+dil)*1000 -> 52.627363 | I172: =I171/(sh0+dil)*1000 -> 58.77877 | J172: =J171/(sh0+dil)*1000 -> 62.568599 | K172: =K171/(sh0+dil)*1000 -> 63.510096 | L172: =L171/(sh0+dil)*1000 -> 62.037625 | M172: =M171/(sh0+dil)*1000 -> 62.127071 | N172: =N171/(sh0+dil)*1000 -> 62.213197 | ... R172: =R171/(sh0+dil)*1000 -> 65.079897
A174: B. 年度（會計年度） | B174: 單位 | C174: FY2025A | D174: FY2026A | E174: FY2027 | F174: FY2028 | G174: FY2029 | T174: 說明
A175: 營收 | B175: $B | C175: =a25_rev -> 7.355 | D175: =SUM(C164:F164) -> 20.248 | E175: =SUM(G164:J164) -> 47.720711 | F175: =SUM(K164:N164) -> 54.273833 | G175: =SUM(O164:R164) -> 55.263586
A176: 營業成本 | B176: $B | D176: =SUM(C166:F166) -> 5.771301 | E176: =SUM(G166:J166) -> 6.2436647 | F176: =SUM(K166:N166) -> 6.737094 | G176: =SUM(O166:R166) -> 7.1674303
A177: 毛利率 | B177: % | D177: =1-D176/D175 -> 0.71496933 | E177: =1-E176/E175 -> 0.86916237 | F177: =1-F176/F175 -> 0.87586847 | G177: =1-G176/G175 -> 0.87030465
A178: 營業費用 | B178: $B | D178: =SUM(C168:F168) -> 2.087699 | E178: =SUM(G168:J168) -> 2.5030274 | F178: =SUM(K168:N168) -> 2.7711406 | G178: =SUM(O168:R168) -> 3.0038784
...

Sheet Sources
A1: 來源
A2: SanDisk FQ4 FY26 新聞稿（8-K，2026-08-05） | B2: https://www.sec.gov/Archives/edgar/data/0002023554/000162828026053346/sndkq4-26ex991xpressrelease.htm
A3: SanDisk FQ2 FY26 新聞稿（8-K，2026-01-29） | B3: https://www.sec.gov/Archives/edgar/data/2023554/000162828026004121/sndkq2fy26ex991-pressrelea.htm
A4: SanDisk：FQ1 FY27 財報日 2026-10-29（2026-09-29 公告） | B4: https://investor.sandisk.com/news-releases/news-release-details/sandisk-report-first-quarter-fiscal-year-2027-results-october-29
A5: stockanalysis：歷史股價、統計、共識目標價 | B5: https://stockanalysis.com/stocks/sndk/forecast/
A6: MarketScreener：SanDisk 預估（EPS、每股淨值、股數） | B6: https://uk.marketscreener.com/quote/stock/SANDISK-CORPORATION-182801077/finances/
A7: MarketScreener：Kioxia 預估（同業 P/B、P/E） | B7: https://uk.marketscreener.com/quote/stock/KIOXIA-HOLDINGS-CORPORATI-180030735/finances/
A8: stockanalysis：WDC 統計（Forward P/E） | B8: https://stockanalysis.com/stocks/wdc/statistics/
A9: Motley Fool：SanDisk／Kioxia 日本投資、FY27 毛資本支出約營收 6%（2026-08-29） | B9: https://www.fool.com/investing/2026/08/29/sandisk-and-kioxia-plan-to-invest-more-than-usd31-billion-in-japanese-memory-plants-about-60-of-what-they-have-spent-there-in-25-years/
A10: 市場層：markets/nand/dist/20261025_NAND市場模型_v0.1.xlsx（markets/nand v0.1） | B10: 本 repo
A11: 美光十年倍數與淨利率（Analogy）：micron/dist/20261025_美光模型_v0.4.xlsx | B11: 本 repo
A12: SemiAnalysis | B12: 未使用
