Workbook

Sheet README
A1: SanDisk（SNDK US）收支與估值模型 v0.1（AI 半導體 Project：記憶體——NAND） 2026-10-25
A2: 模型命題：SanDisk 是純 NAND 公司，盈餘由 NAND 合約價循環與 AI 推論帶動的企業級 SSD 位元決定，產能與 Kioxia 合資（Flash Ventures 49.9%）；問題是 2026 年的高價能維持多久（FY2028 起三情境分歧），以及現價隱含的倍數是否已反映循環見頂。
A3: 重點觀察
A4: ="1. 加權目標價 "&TEXT(Val!B49,"#,##0")&" 美元，相對現價 "&TEXT(px,"#,##0.00")&"（2026-10-23 收盤）"&TEXT(Val!B52,"+0.0%;−0.0%")&"，主因是 Comparable 偏低：同業前瞻 P/B 中位數 "&TEXT(Val!B32,"0.00")&"x，而共識目標價隱含約 "&TEXT(cons_tp/((cons_bv28+cons_bv29)/2),"0.00")&"x（倍數因素 "&TEXT(Val!B59,"+0%;−0%")&"）；DCF 目標價 "&TEXT(Val!B24,"#,##0")&" 高於 Comparable "&TEXT(Val!B34,"#,##0")&"。" -> 1. 加權目標價 930 美元，相對現價 1,238.03（2026-10-23 收盤）−24.9%，主因是 Comparable 偏低：同業前瞻 P/B 中位數 1.49x，而共識目標價隱含約 3.56x（倍數因素 +139%）；DCF 目標價 1,122 高於 Comparable 739。
A5: ="2. 本模型 FY2027 EPS（A）"&TEXT(PL!E14,"0")&" 美元，比共識 217.4 "&TEXT(PL!E14/cons_eps27-1,"+0%;−0%")&"；B、C 到 FY2028 才分歧（"&TEXT(PL!F28,"0")&"／"&TEXT(PL!F42,"0")&"），因為 2026Q3–2027Q2 的價格與位元三情境幾乎相同（markets/nand）。v0.3 已滾入 FQ1 FY27 實績（營收 11.031）；v0.4 對帳：模型 FQ2 FY27 營收 "&TEXT(PL!H60,"0.00")&"，在指引 12.2–12.6 內（v0.3 為 13.59、高 9.6%）。原因是市場層把合約價當實現價：2026Q3 實現 +25%、2026Q4 改 +8.1%（兩季累計不變），SanDisk 2026Q3 份額由 11.6% 降為 10.7%（2026Q4 起取兩季平均 10.65%）；公司稱約一半位元在長約（底價＋浮動），同品項價格溫和上升。" -> 2. 本模型 FY2027 EPS（A）264 美元，比共識 217.4 +21%；B、C 到 FY2028 才分歧（215／190），因為 2026Q3–2027Q2 的價格與位元三情境幾乎相同（markets/nand）。v0.3 已滾入 FQ1 FY27 實績（營收 11.031）；v0.4 對帳：模型 FQ2 FY27 營收 12.45，在指引 12.2–12.6 內（v0.3 為 13.59、高 9.6%）。原因是市場層把合約價當實現價：2026Q3 實現 +25%、2026Q4 改 +8.1%（兩季累計不變），SanDisk 2026Q3 份額由 11.6% 降為 10.7%（2026Q4 起取兩季平均 10.65%）；公司稱約一半位元在長約（底價＋浮動），同品項價格溫和上升。
A6: ="3. 最敏感的是價格而非成本：2027 起季價 ±20% 使 FY2028 EPS（A）變動 "&TEXT(Sens!H5,"+0%;−0%")&"／"&TEXT(Sens!H6,"+0%;−0%")&"，成本年降 ±4pt 只有約 ±1%；情境 C 的 FY2029 毛利率降到 "&TEXT(PL!G38,"0%")&"（CY2028 NAND 價格跌回約 2025 年水準）。追蹤：TrendForce 每季初的 NAND 合約價與 Kioxia 2026-10-30 財報（合資群位元與價格）。" -> 3. 最敏感的是價格而非成本：2027 起季價 ±20% 使 FY2028 EPS（A）變動 −28%／+30%，成本年降 ±4pt 只有約 ±1%；情境 C 的 FY2029 毛利率降到 49%（CY2028 NAND 價格跌回約 2025 年水準）。追蹤：TrendForce 每季初的 NAND 合約價與 Kioxia 2026-10-30 財報（合資群位元與價格）。
A7: ="投資建議："&Val!B55&"（依上檔空間固定規則；上檔空間："&TEXT(Val!B52,"+0.0%;−0.0%")&"，級距："&Val!B54&"）" -> 投資建議：中立（依上檔空間固定規則；上檔空間：−24.9%，級距：0%～−25%）
A9: 驅動因子 → 推導量（因果方向：左邊決定右邊）
A10: Units｜markets/nand 成品：SanDisk 季度營收（市場營收 × 份額；同字母情境）與位元（季度出貨 × 份額）
A11: PL 區塊｜營收＝市場層 × 公司口徑係數；營業成本＝位元 × 每 EB 成本（FQ1 FY27 以實績毛利率校準，之後每年 × (1 − 成本年降)）；營業費用＝固定（FQ1 FY27 實績校準）＋變動
A12: PL 區塊｜淨利＝（營業利益＋淨現金收益）×（1 − 稅率）；自由現金流＝淨利＋折舊 − 資本支出（含合資群分攤）；買回＝回饋比例 × FCF → 股數 → EPS、每股淨值
A13: Val｜第 0 節目標價＝DCF（FY2027–FY2032＋永續）與 Comparable（同業前瞻 P/B × 約 2028 年底每股淨值）各半；第 5–6 節目前倍數、十年倍數規則值（美光 Analogy）
A15: 會計年度：約 6 月底結束（FY2027＝2026-07～2027-06 ≈ CY2026Q3–CY2027Q2）。前瞻 EPS 依月份調整：12 個月後（約 2027-10）的未來 12 月＝8／12 FY2028＋4／12 FY2029。
A16: 情境：A＝順利、B＝平平、C＝不如預期，讀 markets/nand 同字母（價格＝markets/memory NAND_S；顆數＝SCEN_UNITS；合資群份額年變動）；公司特有變數（每位元成本年降 14%／12%／10%）A 最有利、C 最不利。FY2027 的 B、C EPS 略高於 A：上游 markets/memory 的 B、C 價格路徑 2027 上半年漲幅較大、下半年才回落（行業情境，不在公司層調整）。FY2030 起為收斂法，非驅動因子推導。
A17: 十年歷史不足：2025-02 自 WDC 分拆上市，十年 P/B、P/E 與十年平均淨利率以美光為 Analogy。本版未做先驗，無 Andy 合理 P/E 對照。
A19: 2026-10-29：加權目標價中的 Comparable 改用相對倍數調整後的值（Val 第 0.5 節：同業前瞻倍數中位數 × 本公司 10 年相對同業的倍數比，Bloomberg 前瞻倍數；Andy 2026-10-27「照建議做」、10-29 資料取回）。「Comparable 目標價（市場主流同業法）」維持不調整。重點觀察 1 的第一句已改為公式；重點觀察 2、3 與其他說明中的目標價與上檔空間數字為調整前撰寫，以 Val 頁為準。
A21: v0.2.1（2026-10-30）：依個股模型原則第 8 節調整 In 頁呈現（數值不變）。In 頁 D／F 欄名改「敏感度低」「敏感度高」（只用於 Sens 頁、不進目標價）；In 頁最後新增「情境驅動對照」一節，把上方各情境專屬輸入三情境並排（只引用上方各列，純展示）；HTML 驅動因子一節分「情境驅動」與「單一參數」兩張表。

Sheet In
A1: In — 輸入（藍字；基準欄 E，低 D、高 F）。金額：十億美元（$B）；每股：美元；股數：百萬股。每個輸入附標記與來源；找不到者寫「未找到」。【v0.2.1】基準欄 E 進主模型；D／F＝敏感度低／高，只用於 Sens 頁（一次動一個參數）、不進目標價；情境 A／B／C 的驅動見本頁最後一節「情境驅動對照」。
A2: 標記：Verified（公司文件、交易所資料）／Interested-party（寫明是誰、立場）／Analogy（寫明對照與差異）／Assumed（給低／高區間）／Derived（寫明換算）。SemiAnalysis 未使用
A3: 鍵 | B3: 項目 | C3: 單位 | D3: 敏感度低 | E3: 基準 | F3: 敏感度高 | G3: 標記 | H3: 來源1 | I3: 來源2／說明
A4: A. 季度實績與公司指引（$B；EPS 美元）
A5: q1_rev | B5: FQ1 FY26 營收 | C5: $B | E5: 2.308 | G5: Verified | H5: SanDisk FQ2 FY26 新聞稿（8-K，2026-01-29） | I5: FY26 合計 20.248（FQ4 新聞稿）
A6: q1_gm | B6: FQ1 FY26 GAAP 毛利率 | C6: % | E6: 0.298 | G6: Verified | H6: SanDisk FQ2 FY26 新聞稿（8-K，2026-01-29）
A7: q1_op | B7: FQ1 FY26 GAAP 營業利益 | C7: $B | E7: 0.176 | G7: Verified | H7: SanDisk FQ2 FY26 新聞稿（8-K，2026-01-29）
A8: q1_ni | B8: FQ1 FY26 GAAP 淨利 | C8: $B | E8: 0.112 | G8: Verified | H8: SanDisk FQ2 FY26 新聞稿（8-K，2026-01-29）
A9: q1_eps | B9: FQ1 FY26 GAAP 稀釋 EPS | C9: USD | E9: 0.75 | G9: Verified | H9: SanDisk FQ2 FY26 新聞稿（8-K，2026-01-29）
A10: q2_rev | B10: FQ2 FY26 營收 | C10: $B | E10: 3.025 | G10: Verified | H10: SanDisk FQ2 FY26 新聞稿（8-K，2026-01-29） | I10: FY26 合計 20.248（FQ4 新聞稿）
A11: q2_gm | B11: FQ2 FY26 GAAP 毛利率 | C11: % | E11: 0.509 | G11: Verified | H11: SanDisk FQ2 FY26 新聞稿（8-K，2026-01-29）
A12: q2_op | B12: FQ2 FY26 GAAP 營業利益 | C12: $B | E12: 1.065 | G12: Verified | H12: SanDisk FQ2 FY26 新聞稿（8-K，2026-01-29）
A13: q2_ni | B13: FQ2 FY26 GAAP 淨利 | C13: $B | E13: 0.803 | G13: Verified | H13: SanDisk FQ2 FY26 新聞稿（8-K，2026-01-29）
A14: q2_eps | B14: FQ2 FY26 GAAP 稀釋 EPS | C14: USD | E14: 5.15 | G14: Verified | H14: SanDisk FQ2 FY26 新聞稿（8-K，2026-01-29）
A15: q3_rev | B15: FQ3 FY26 營收 | C15: $B | E15: 5.95 | G15: Verified | H15: SanDisk FQ4 FY26 新聞稿（8-K，2026-08-05） | I15: FY26 合計 20.248（FQ4 新聞稿）
A16: q3_gm | B16: FQ3 FY26 GAAP 毛利率 | C16: % | E16: 0.784 | G16: Verified | H16: SanDisk FQ4 FY26 新聞稿（8-K，2026-08-05）
A17: q3_op | B17: FQ3 FY26 GAAP 營業利益 | C17: $B | E17: 4.111 | G17: Verified | H17: SanDisk FQ4 FY26 新聞稿（8-K，2026-08-05）
A18: q3_ni | B18: FQ3 FY26 GAAP 淨利 | C18: $B | E18: 3.615 | G18: Verified | H18: SanDisk FQ4 FY26 新聞稿（8-K，2026-08-05）
A19: q3_eps | B19: FQ3 FY26 GAAP 稀釋 EPS | C19: USD | E19: 23.03 | G19: Verified | H19: SanDisk FQ4 FY26 新聞稿（8-K，2026-08-05）
A20: q4_rev | B20: FQ4 FY26 營收 | C20: $B | E20: 8.965 | G20: Verified | H20: SanDisk FQ4 FY26 新聞稿（8-K，2026-08-05） | I20: FY26 合計 20.248（FQ4 新聞稿）
A21: q4_gm | B21: FQ4 FY26 GAAP 毛利率 | C21: % | E21: 0.846 | G21: Verified | H21: SanDisk FQ4 FY26 新聞稿（8-K，2026-08-05）
A22: q4_op | B22: FQ4 FY26 GAAP 營業利益 | C22: $B | E22: 7.037 | G22: Verified | H22: SanDisk FQ4 FY26 新聞稿（8-K，2026-08-05）
A23: q4_ni | B23: FQ4 FY26 GAAP 淨利 | C23: $B | E23: 6.903 | G23: Verified | H23: SanDisk FQ4 FY26 新聞稿（8-K，2026-08-05）
A24: q4_eps | B24: FQ4 FY26 GAAP 稀釋 EPS | C24: USD | E24: 43.97 | G24: Verified | H24: SanDisk FQ4 FY26 新聞稿（8-K，2026-08-05）
A25: q1_dc | B25: FQ1 FY26 營收：資料中心 | C25: $B | E25: 0.269 | G25: Derived | H25: SanDisk 10-Q（FQ2 FY26，2026-01-02 止；FQ3 FY26，2026-04-03 止）營收依終端市場表：六個月 − FQ2 | I25: 官方分部：Datacenter／Edge／Consumer（依終端市場）
A26: q1_ed | B26: FQ1 FY26 營收：邊緣 | C26: $B | E26: 1.387 | G26: Derived | H26: SanDisk 10-Q（FQ2 FY26，2026-01-02 止；FQ3 FY26，2026-04-03 止）營收依終端市場表：六個月 − FQ2 | I26: Edge＝PC、手機、車用等 OEM 用 client SSD 與嵌入式
A27: q1_cs | B27: FQ1 FY26 營收：消費 | C27: $B | E27: 0.652 | G27: Derived | H27: SanDisk 10-Q（FQ2 FY26，2026-01-02 止；FQ3 FY26，2026-04-03 止）營收依終端市場表：六個月 − FQ2 | I27: Consumer＝記憶卡、隨身碟、零售 SSD
A28: q2_dc | B28: FQ2 FY26 營收：資料中心 | C28: $B | E28: 0.44 | G28: Verified | H28: SanDisk 10-Q（FQ2 FY26，2026-01-02 止；FQ3 FY26，2026-04-03 止）營收依終端市場表 | I28: 官方分部：Datacenter／Edge／Consumer（依終端市場）
A29: q2_ed | B29: FQ2 FY26 營收：邊緣 | C29: $B | E29: 1.678 | G29: Verified | H29: SanDisk 10-Q（FQ2 FY26，2026-01-02 止；FQ3 FY26，2026-04-03 止）營收依終端市場表 | I29: Edge＝PC、手機、車用等 OEM 用 client SSD 與嵌入式
A30: q2_cs | B30: FQ2 FY26 營收：消費 | C30: $B | E30: 0.907 | G30: Verified | H30: SanDisk 10-Q（FQ2 FY26，2026-01-02 止；FQ3 FY26，2026-04-03 止）營收依終端市場表 | I30: Consumer＝記憶卡、隨身碟、零售 SSD
A31: q3_dc | B31: FQ3 FY26 營收：資料中心 | C31: $B | E31: 1.467 | G31: Verified | H31: SanDisk 10-Q（FQ2 FY26，2026-01-02 止；FQ3 FY26，2026-04-03 止）營收依終端市場表 | I31: 官方分部：Datacenter／Edge／Consumer（依終端市場）
A32: q3_ed | B32: FQ3 FY26 營收：邊緣 | C32: $B | E32: 3.663 | G32: Verified | H32: SanDisk 10-Q（FQ2 FY26，2026-01-02 止；FQ3 FY26，2026-04-03 止）營收依終端市場表 | I32: Edge＝PC、手機、車用等 OEM 用 client SSD 與嵌入式
A33: q3_cs | B33: FQ3 FY26 營收：消費 | C33: $B | E33: 0.82 | G33: Verified | H33: SanDisk 10-Q（FQ2 FY26，2026-01-02 止；FQ3 FY26，2026-04-03 止）營收依終端市場表 | I33: Consumer＝記憶卡、隨身碟、零售 SSD
A34: q4_dc | B34: FQ4 FY26 營收：資料中心 | C34: $B | E34: 2.977 | G34: Derived | H34: SanDisk 10-K FY2026（2026-07-03 止） 全年 − 10-Q 九個月 | I34: 官方分部：Datacenter／Edge／Consumer（依終端市場）
A35: q4_ed | B35: FQ4 FY26 營收：邊緣 | C35: $B | E35: 5.432 | G35: Derived | H35: SanDisk 10-K FY2026（2026-07-03 止） 全年 − 10-Q 九個月 | I35: Edge＝PC、手機、車用等 OEM 用 client SSD 與嵌入式
A36: q4_cs | B36: FQ4 FY26 營收：消費 | C36: $B | E36: 0.556 | G36: Derived | H36: SanDisk 10-K FY2026（2026-07-03 止） 全年 − 10-Q 九個月 | I36: Consumer＝記憶卡、隨身碟、零售 SSD
A37: a26_dc | B37: FY2026 營收：資料中心 | C37: $B | E37: 5.153 | G37: Verified | H37: SanDisk 10-K FY2026（2026-07-03 止）；SanDisk FQ4 FY26 新聞稿（8-K，2026-08-05）
A38: a26_ed | B38: FY2026 營收：邊緣 | C38: $B | E38: 12.16 | G38: Verified | H38: SanDisk 10-K FY2026（2026-07-03 止）；SanDisk FQ4 FY26 新聞稿（8-K，2026-08-05）
A39: a26_cs | B39: FY2026 營收：消費 | C39: $B | E39: 2.935 | G39: Verified | H39: SanDisk 10-K FY2026（2026-07-03 止）；SanDisk FQ4 FY26 新聞稿（8-K，2026-08-05）
A40: a26_rev | B40: FY2026 營收（2025-07～2026-07-03） | C40: $B | E40: 20.248 | G40: Verified | H40: SanDisk FQ4 FY26 新聞稿（8-K，2026-08-05）：資料中心 5.153、邊緣 12.160、消費 2.935 | I40: MarketScreener 同值
A41: a26_ni | B41: FY2026 GAAP 淨利 | C41: $B | E41: 11.433 | G41: Verified | H41: SanDisk FQ4 FY26 新聞稿（8-K，2026-08-05） | I41: MarketScreener 同值
A42: a26_eps | B42: FY2026 GAAP 稀釋 EPS | C42: USD | E42: 73.76 | G42: Verified | H42: SanDisk FQ4 FY26 新聞稿（8-K，2026-08-05）（non-GAAP 70.88） | I42: MarketScreener 73.76
A43: a26_op | B43: FY2026 GAAP 營業利益 | C43: $B | E43: 12.389 | G43: Verified | H43: SanDisk FQ4 FY26 新聞稿（8-K，2026-08-05）
A44: a26_gm | B44: FY2026 GAAP 毛利率 | C44: % | E44: 0.715 | G44: Verified | H44: SanDisk FQ4 FY26 新聞稿（8-K，2026-08-05）
A45: a25_rev | B45: FY2025 營收 | C45: $B | E45: 7.355 | G45: Verified | H45: SanDisk FQ4 FY26 新聞稿（8-K，2026-08-05）（前期欄） | I45: MarketScreener 7,355
A46: a25_ni | B46: FY2025 GAAP 淨利 | C46: $B | E46: -1.641 | G46: Verified | H46: SanDisk FQ4 FY26 新聞稿（8-K，2026-08-05）（含商譽減損） | I46: MarketScreener −1,641
A47: a25_eps | B47: FY2025 GAAP 稀釋 EPS | C47: USD | E47: -11.32 | G47: Verified | H47: SanDisk FQ4 FY26 新聞稿（8-K，2026-08-05）
A48: g_rev | B48: FQ1 FY27（2026-07～09）營收實績 | C48: $B | E48: 11.031 | G48: Verified | H48: SanDisk FQ1 FY27 新聞稿與法說（2026-10-29；Benzinga／Motley Fool 逐字稿、Investing.com 簡報摘要）：$11.031B（資料中心 4.802、邊緣 5.832、消費 0.397） | I48: v0.3 前為公司指引 $10.3–10.8B；市場層 markets/nand 以此推 SanDisk 2026Q3 份額
A49: g_gm | B49: FQ1 FY27 GAAP 毛利率實績（校準單位成本） | C49: % | D49: 0.845 | E49: 0.8503 | F49: 0.855 | G49: Verified | H49: SanDisk FQ1 FY27 新聞稿與法說（2026-10-29；Benzinga／Motley Fool 逐字稿、Investing.com 簡報摘要）：GAAP 毛利 $9.38B ÷ 營收 11.031＝85.0%（non-GAAP 85.1%） | I49: 低／高 ±0.5pt 只供 Sens；FQ2 FY27 指引 GAAP 84.4–85.4%
A50: g_ox | B50: FQ1 FY27 GAAP 營業費用（推估；校準固定費用） | C50: $B | D50: 0.57 | E50: 0.582 | F50: 0.6 | G50: Derived | H50: non-GAAP 營業費用＝（毛利率 85.1% − 營業利益率 80.4%）× 11.031＝0.518；加股份報酬約 0.064（FQ1 指引附註 54–74M 中點） | I50: 公司 GAAP 營業費用原文未取得（新聞稿頁面未能開啟）
A51: g_eps | B51: FQ1 FY27 non-GAAP 稀釋 EPS 實績（分割前） | C51: USD | E51: 49.51 | G51: Verified | H51: SanDisk FQ1 FY27 新聞稿與法說（2026-10-29；Benzinga／Motley Fool 逐字稿、Investing.com 簡報摘要）：non-GAAP 49.51、GAAP 52.60 | I51: FQ2 FY27 指引 non-GAAP 55–57（分割前）
A52: g_sh | B52: 稀釋股數（FQ2 FY27 指引，分割前） | C52: 百萬股 | E52: 151 | G52: Interested-party | H52: SanDisk FQ1 FY27 新聞稿與法說（2026-10-29；Benzinga／Motley Fool 逐字稿、Investing.com 簡報摘要）：FQ2 FY27 指引假設完全稀釋 151 百萬股 | I52: FQ1 FY27 回購約 3.2 百萬股（$5.0B）
A53: B. 成本、費用、稅（公司特有；隨情境者 A 最有利、C 最不利）
A54: cd_A | B54: 情境 A：每位元成本年降 | C54: % | D54: 0.1 | E54: 0.14 | F54: 0.18 | G54: Assumed | H54: A：BiCS8→BiCS10（332 層，密度約 +59%）如期量產，每位元成本年降約 14% | I54: 以 FQ1 FY27 指引毛利率校準的單位成本為起點；歷史每位元成本年降約 15–20%（Analogy：產業製程轉換）
A55: cd_B | B55: 情境 B：每位元成本年降 | C55: % | D55: 0.08 | E55: 0.12 | F55: 0.16 | G55: Assumed | H55: B：轉換略延後 | I55: 同上
A56: cd_C | B56: 情境 C：每位元成本年降 | C56: % | D56: 0.06 | E56: 0.1 | F56: 0.14 | G56: Assumed | H56: C：需求轉弱、稼動率下降，固定成本攤提使年降縮小 | I56: 同上
A57: ox_var | B57: 營業費用變動率（÷ 營收） | C57: % | D57: 0.005 | E57: 0.01 | F57: 0.02 | G57: Assumed | H57: FY26 GAAP 營業費用 2.083 ÷ 營收 20.248 ≈ 10%，但多為固定；FQ4 0.545 ÷ 8.965 ≈ 6% | I57: 固定部分＝指引營業費用 − 變動率 × 指引營收（Derived）
A58: ox_g | B58: 營業費用固定部分年增 | C58: % | D58: 0.05 | E58: 0.1 | F58: 0.15 | G58: Assumed | H58: 研發（BiCS10、企業級 SSD 控制晶片）與獎金
A59: tax | B59: 有效稅率 | C59: % | D59: 0.12 | E59: 0.15 | F59: 0.2 | G59: Interested-party | H59: 公司指引 non-GAAP 稅率 15%（FQ1 FY27） | I59: GAAP 稅率未指引
A60: rf | B60: 淨現金收益率 | C60: % | D60: 0.03 | E60: 0.04 | F60: 0.05 | G60: Assumed | H60: 美元短期利率
A61: dcsh_27 | B61: FY2027 資料中心占營收 | C61: % | D61: 0.33 | E61: 0.38 | F61: 0.45 | G61: Assumed | H61: FQ1–FQ4 FY26 依序 11.7%、14.5%、24.7%、33.2%（10-Q、10-K）；企業級 SSD 位元占產業需求由 CY2025 30% 升到 CY2027 59%（markets/nand 情境 A） | I61: 低＝停在 FQ4 FY26 水準；分部拆分不影響合併營收與 EPS
A62: cssh_27 | B62: FY2027 消費占營收 | C62: % | D62: 0.04 | E62: 0.06 | F62: 0.09 | G62: Assumed | H62: FQ1–FQ4 FY26 依序 28.2%、30.0%、13.8%、6.2%（零售通路價格調整落後合約價） | I62: 邊緣＝1 − 資料中心 − 消費（Derived）
A63: dcsh_28 | B63: FY2028 資料中心占營收 | C63: % | D63: 0.33 | E63: 0.42 | F63: 0.5 | G63: Assumed | H63: FQ1–FQ4 FY26 依序 11.7%、14.5%、24.7%、33.2%（10-Q、10-K）；企業級 SSD 位元占產業需求由 CY2025 30% 升到 CY2027 59%（markets/nand 情境 A） | I63: 低＝停在 FQ4 FY26 水準；分部拆分不影響合併營收與 EPS
A64: cssh_28 | B64: FY2028 消費占營收 | C64: % | D64: 0.04 | E64: 0.06 | F64: 0.09 | G64: Assumed | H64: FQ1–FQ4 FY26 依序 28.2%、30.0%、13.8%、6.2%（零售通路價格調整落後合約價） | I64: 邊緣＝1 − 資料中心 − 消費（Derived）
A65: dcsh_29 | B65: FY2029 資料中心占營收 | C65: % | D65: 0.33 | E65: 0.45 | F65: 0.55 | G65: Assumed | H65: FQ1–FQ4 FY26 依序 11.7%、14.5%、24.7%、33.2%（10-Q、10-K）；企業級 SSD 位元占產業需求由 CY2025 30% 升到 CY2027 59%（markets/nand 情境 A） | I65: 低＝停在 FQ4 FY26 水準；分部拆分不影響合併營收與 EPS
A66: cssh_29 | B66: FY2029 消費占營收 | C66: % | D66: 0.04 | E66: 0.06 | F66: 0.09 | G66: Assumed | H66: FQ1–FQ4 FY26 依序 28.2%、30.0%、13.8%、6.2%（零售通路價格調整落後合約價） | I66: 邊緣＝1 − 資料中心 − 消費（Derived）
A67: sd_k | B67: 公司營收 ÷ 市場層 SanDisk 營收（TrendForce 口徑） | C67: x | E67: =a26_rev/SUM(Units!E4:H4) -> 0.9994077 | G67: Derived | H67: FY2026 營收 ÷ 市場層 2025Q3–2026Q2 SanDisk 營收（Units 頁） | I67: 約 1.0：TrendForce 以公司財報為準
A68: C. 資本、股東回饋（FY2026 年底＝2026-07-03）
A69: eq0 | B69: FY2026 年底股東權益 | C69: $B | E69: 15.736 | G69: Verified | H69: SanDisk FQ4 FY26 新聞稿（8-K，2026-08-05）
A70: nc0 | B70: FY2026 年底淨現金（現金 − 負債） | C70: $B | E70: 4.762 | G70: Verified | H70: SanDisk FQ4 FY26 新聞稿（8-K，2026-08-05）：現金 4.762、負債 0（已全數清償）
A71: sh0 | B71: 流通股數（FY2026 年底後） | C71: 百萬股 | E71: 146.42 | G71: Verified | H71: stockanalysis 統計頁（2026-10-25）：146.42M | I71: MarketScreener FY2027 股數 146.419M；FQ4 已買回 $4.524B
A72: dil | B72: 稀釋股數 − 流通股數 | C72: 百萬股 | E72: =g_sh-sh0 -> 4.58 | G72: Derived | H72: 公司指引稀釋約 155 − 流通 146.42 | I72: 各年固定
A73: da_y | B73: 折舊攤銷（公司本身；年） | C73: $B | D73: 0.12 | E73: 0.16 | F73: 0.25 | G73: Verified／Assumed | H73: SanDisk FQ4 FY26 新聞稿（8-K，2026-08-05）：FY26 0.149 | I73: 合資廠折舊在晶圓成本（營業成本）內
A74: cap_r | B74: 資本支出 ÷ 營收（含合資群分攤；FY2027 起） | C74: % | D74: 0.03 | E74: 0.06 | F74: 0.09 | G74: Interested-party | H74: Motley Fool 2026-08-29：SanDisk FY27 毛資本支出約營收 6%（含與 Kioxia 合資的分攤） | I74: FY26 毛資本支出 0.562（其中合資分攤 0.519；SanDisk FQ4 FY26 簡報，markets/equipment In 頁）
A75: payout | B75: 買回 ÷ 自由現金流 | C75: % | D75: 0.3 | E75: 0.5 | F75: 0.8 | G75: Assumed | H75: SanDisk FQ4 FY26 新聞稿（8-K，2026-08-05）：新增 $14B 授權（合計剩餘 $15.5B）；FQ4 買回 $4.524B | I75: 無現金股利
A76: px | B76: 股價（2026-10-23 收盤） | C76: USD | E76: 1238.03 | G76: Verified | H76: stockanalysis 歷史股價（2026-10-23 收盤 1,238.03） | I76: MarketScreener 參考價 1,238.03（同日）；10-09 為 1,581.82
A77: bb_px | B77: 未來買回均價 | C77: USD | E77: =px -> 1238.03 | G77: Assumed | H77: ＝現價
A78: D. 共識與對帳參考（只放 Recon，不作校準）
A79: cons_rev27 | B79: 共識營收 FY2027 | C79: $B | D79: 43.4 | E79: 49.135 | F79: 53.2 | G79: Interested-party | H79: MarketScreener 預估頁（2026-10-25 擷取；頁面為 10-23 收盤；會計年度 6 月）：49,135；stockanalysis（21 位）平均 49.1、區間 43.4–53.2
A80: cons_rev28 | B80: 共識營收 FY2028 | C80: $B | E80: 58.436 | G80: Interested-party | H80: MarketScreener 預估頁（2026-10-25 擷取；頁面為 10-23 收盤；會計年度 6 月）
A81: cons_eps27 | B81: 共識 EPS FY2027 | C81: USD | D81: 186.97 | E81: 217.4 | F81: 238.36 | G81: Interested-party | H81: MarketScreener 預估頁（2026-10-25 擷取；頁面為 10-23 收盤；會計年度 6 月）：217.4；stockanalysis（21 位）non-GAAP 214.82、區間 186.97–238.36
A82: cons_eps28 | B82: 共識 EPS FY2028 | C82: USD | E82: 267.6 | G82: Interested-party | H82: MarketScreener 預估頁（2026-10-25 擷取；頁面為 10-23 收盤；會計年度 6 月）
A83: cons_eps29 | B83: 共識 EPS FY2029 | C83: USD | E83: 281.7 | G83: Interested-party | H83: MarketScreener 預估頁（2026-10-25 擷取；頁面為 10-23 收盤；會計年度 6 月）
A84: cons_bv27 | B84: 共識每股淨值 FY2027 年底（2027-06） | C84: USD | E84: 313.8 | G84: Interested-party | H84: MarketScreener 預估頁（2026-10-25 擷取；頁面為 10-23 收盤；會計年度 6 月）
A85: cons_bv28 | B85: 共識每股淨值 FY2028 年底（2028-06） | C85: USD | E85: 553.1 | G85: Interested-party | H85: MarketScreener 預估頁（2026-10-25 擷取；頁面為 10-23 收盤；會計年度 6 月）
A86: cons_bv29 | B86: 共識每股淨值 FY2029 年底（2029-06） | C86: USD | E86: 650.6 | G86: Interested-party | H86: MarketScreener 預估頁（2026-10-25 擷取；頁面為 10-23 收盤；會計年度 6 月）
A87: cons_ni27 | B87: 共識淨利 FY2027 | C87: $B | E87: 33.336 | G87: Interested-party | H87: MarketScreener 預估頁（2026-10-25 擷取；頁面為 10-23 收盤；會計年度 6 月）
A88: cons_ni28 | B88: 共識淨利 FY2028 | C88: $B | E88: 38.384 | G88: Interested-party | H88: MarketScreener 預估頁（2026-10-25 擷取；頁面為 10-23 收盤；會計年度 6 月）
A89: E. 目標價參數（黃底；Val 頁第 0 節 DCF＋Comparable 與收斂法用；Assumed 者 Andy 可改）
A90: tp_wA | B90: 目標價情境權重 A（A 順利／B 平平／C 不如預期） | C90: % | E90: 0.3 | G90: Assumed | H90: Andy 可改（工作單 2026-10-25 預設 A 0.3／B 0.5／C 0.2） | I90: 三者合計應為 100%
A91: tp_wB | B91: 目標價情境權重 B（A 順利／B 平平／C 不如預期） | C91: % | E91: 0.5 | G91: Assumed | H91: Andy 可改（工作單 2026-10-25 預設 A 0.3／B 0.5／C 0.2） | I91: 三者合計應為 100%
A92: tp_wC | B92: 目標價情境權重 C（A 順利／B 平平／C 不如預期） | C92: % | E92: 0.2 | G92: Assumed | H92: Andy 可改（工作單 2026-10-25 預設 A 0.3／B 0.5／C 0.2） | I92: 三者合計應為 100%
A93: tp_r | B93: 折現率（股東權益要求報酬；美、台、日、韓同一值） | C93: % | E93: 0.1 | G93: Assumed | H93: Andy 可改（工作單預設 10%） | I93: 記憶體循環股的盈餘波動大於一般大型股；依工作單不改值
A94: tp_g | B94: 長期成長率（永續；收斂法 B 的 FY2032 營收年增） | C94: % | E94: 0.04 | G94: Assumed | H94: Andy 可改（工作單預設 4%）
A95: tp_roe | B95: ROE（近年平均；FY2025–FY2026，上市不足三年） | C95: % | E95: =AVERAGE(-1.641/9.216,11.433/15.736) -> 0.27424534 | G95: Derived | H95: SanDisk FQ4 FY26 新聞稿（8-K，2026-08-05）：FY2025 淨利 −1.641 ÷ 權益 9.216、FY2026 11.433 ÷ 15.736 | I95: 2025-02 自 WDC 分拆上市，FY2024 以前為 WDC 快閃記憶體事業（無獨立權益）；只用兩年
A96: tp_w_dcf | B96: 目標價中 DCF 的權重；其餘為 Comparable | C96: % | E96: 0.5 | G96: Assumed | H96: Andy 可改（2026-10-25 11:53：DCF／Comparable 各半）
A97: nim10 | B97: 十年平均淨利率（Analogy：美光 FY2016–FY2025） | C97: % | E97: 0.14662864 | G97: Analogy | H97: micron/dist/20261030_美光個股模型_v0.4.3.xlsx｜In!E244 | I97: SanDisk 獨立上市不足十年（2025-02 分拆），以同為記憶體循環股的美光十年平均代替；差異：美光含 DRAM、HBM，NAND 純度低
A98: cyc_mA | B98: 循環中段係數：情境 A 淨利率收斂目標 ÷ 十年平均 | C98: x | E98: 1.2 | G98: Assumed | H98: 記憶體樣板預設 1.2（循環股收斂到循環中段，不延續高峰利潤率） | I98: Andy 可改
A99: cyc_mC | B99: 循環中段係數：情境 C 淨利率收斂目標 ÷ 十年平均 | C99: x | E99: 0.8 | G99: Assumed | H99: 記憶體樣板預設 0.8 | I99: Andy 可改
A100: fade_mA | B100: 情境 A：FY2032 淨利率收斂目標（循環中段：十年平均 × cyc_mA） | C100: % | E100: =nim10*cyc_mA -> 0.17595436 | G100: Derived | H100: 主串指示：循環產業 FY2030 後收斂用十年平均（記憶體樣板的循環中段） | I100: FY2030 起由 FY2029 淨利率線性收斂，FY2032 達到
...

Sheet Q
A1: Q — 季度實績（$B；EPS 美元）與公司指引。會計年度約 6 月底結束；FQ1＝7–9 月
A3: 項目 | B3: FQ1 FY26 | C3: FQ2 FY26 | D3: FQ3 FY26 | E3: FQ4 FY26 | F3: FY2026 | G3: FQ1 FY27 實績 | H3: 標記 | I3: 來源
A4: 營收 | B4: =q1_rev -> 2.308 | C4: =q2_rev -> 3.025 | D4: =q3_rev -> 5.95 | E4: =q4_rev -> 8.965 | F4: =SUM(B4:E4) -> 20.248 | G4: =g_rev -> 11.031 | H4: Verified | I4: SanDisk FQ2 FY26 新聞稿（8-K，2026-01-29）；SanDisk FQ4 FY26 新聞稿（8-K，2026-08-05）
A5: GAAP 毛利率 | B5: =q1_gm -> 0.298 | C5: =q2_gm -> 0.509 | D5: =q3_gm -> 0.784 | E5: =q4_gm -> 0.846 | F5: =SUMPRODUCT(B4:E4,B5:E5)/F4 -> 0.71496933 | G5: =g_gm -> 0.8503 | H5: Verified | I5: SanDisk FQ2 FY26 新聞稿（8-K，2026-01-29）；SanDisk FQ4 FY26 新聞稿（8-K，2026-08-05）
A6: GAAP 營業利益 | B6: =q1_op -> 0.176 | C6: =q2_op -> 1.065 | D6: =q3_op -> 4.111 | E6: =q4_op -> 7.037 | F6: =SUM(B6:E6) -> 12.389 | H6: Verified | I6: SanDisk FQ2 FY26 新聞稿（8-K，2026-01-29）；SanDisk FQ4 FY26 新聞稿（8-K，2026-08-05）
A7: GAAP 淨利 | B7: =q1_ni -> 0.112 | C7: =q2_ni -> 0.803 | D7: =q3_ni -> 3.615 | E7: =q4_ni -> 6.903 | F7: =SUM(B7:E7) -> 11.433 | H7: Verified | I7: SanDisk FQ2 FY26 新聞稿（8-K，2026-01-29）；SanDisk FQ4 FY26 新聞稿（8-K，2026-08-05）
A8: GAAP 稀釋 EPS | B8: =q1_eps -> 0.75 | C8: =q2_eps -> 5.15 | D8: =q3_eps -> 23.03 | E8: =q4_eps -> 43.97 | F8: =a26_eps -> 73.76 | G8: =g_eps -> 49.51 | H8: Verified | I8: SanDisk FQ2 FY26 新聞稿（8-K，2026-01-29）；SanDisk FQ4 FY26 新聞稿（8-K，2026-08-05）
A9: 檢查：四季營收、淨利合計 − FY2026（應約為 0） | B9: =F4-a26_rev -> 0 | C9: =F7-a26_ni -> 0
A10: 季增：營收 | C10: =C4/B4-1 -> 0.31065858 | D10: =D4/C4-1 -> 0.96694215 | E10: =E4/D4-1 -> 0.50672269
A12: v0.3（2026-10-31）：FQ1 FY27（2026-07～09）實績已滾入（2026-10-29 公布：營收 11.031、資料中心 4.802、邊緣 5.832、消費 0.397；GAAP 毛利率 85.0%）；FY2027 第一季＝市場層推導（營收等於實績，為恆等式）。FQ2 FY27 指引：營收 12.2–12.6、non-GAAP 毛利率 84.5–85.5%、non-GAAP EPS 55–57（分割前）、稀釋股數 151。董事會核准一股分八股（2026-11-20 起分割後交易），本版 EPS 與股價仍為分割前

Sheet Units
A1: Units — 市場層 markets/nand 成品的 SanDisk 季度營收與位元（三情境；唯讀抄錄，藍字）。來源：markets/nand/dist/20261031_NAND市場模型_v0.3.xlsx
A2: C..Z＝CY2025Q1..CY2030Q4；營收為 TrendForce 口徑（$B），位元為季度出貨 × 營收份額（EB）。合資群份額＝Kioxia＋SanDisk（與 kioxia/ 模型讀同一列）
A3: 項目 | B3: 單位 | C3: 2025Q1 | D3: 2025Q2 | E3: 2025Q3 | F3: 2025Q4 | G3: 2026Q1 | H3: 2026Q2 | I3: 2026Q3 | J3: 2026Q4 | K3: 2027Q1 | L3: 2027Q2 | M3: 2027Q3 | N3: 2027Q4 | O3: 2028Q1 | P3: 2028Q2 | Q3: 2028Q3 | R3: 2028Q4 | S3: 2029Q1 | T3: 2029Q2 | U3: 2029Q3 | V3: 2029Q4 | W3: 2030Q1 | X3: 2030Q2 | Y3: 2030Q3 | Z3: 2030Q4 | AA3: 來源
A4: SanDisk 營收（情境 A） | B4: $B | C4: 1.69 | D4: 1.9 | E4: 2.31 | F4: 3.03 | G4: 5.95 | H4: 8.97 | I4: 11.037152 | J4: 12.460212 | K4: 13.729628 | L4: 14.517314 | M4: 14.582681 | N4: 14.339957 | O4: 14.404525 | P4: 14.469384 | Q4: 14.534536 | R4: 14.59998 | S4: 14.754735 | T4: 15.041568 | U4: 15.333977 | V4: 15.63207 | W4: 15.425215 | X4: 15.503292 | Y4: 15.581764 | Z4: 15.660633 | AA4: markets/nand/dist/20261031_NAND市場模型_v0.3.xlsx｜Mkt!C44:Z44
A5: SanDisk 營收（情境 B） | B5: $B | C5: 1.69 | D5: 1.9 | E5: 2.31 | F5: 3.03 | G5: 5.95 | H5: 8.97 | I5: 11.037152 | J5: 12.460212 | K5: 13.828805 | L5: 14.914624 | M5: 14.193265 | N5: 12.006041 | O5: 8.3424059 | P5: 6.479135 | Q5: 5.3674927 | R5: 5.0024 | S5: 5.5933415 | T5: 6.1826835 | U5: 6.7039477 | V5: 7.2691598 | W5: 6.9803209 | X5: 6.9805132 | Y5: 6.9807056 | Z5: 6.9808979 | AA5: markets/nand/dist/20261031_NAND市場模型_v0.3.xlsx｜Mkt!C92:Z92
A6: SanDisk 營收（情境 C） | B6: $B | C6: 1.69 | D6: 1.9 | E6: 2.31 | F6: 3.03 | G6: 5.95 | H6: 8.97 | I6: 11.037152 | J6: 12.460212 | K6: 13.661386 | L6: 14.73406 | M6: 14.021435 | N6: 11.86069 | O6: 6.9722938 | P6: 4.5429736 | Q6: 3.415487 | R6: 2.7390112 | S6: 2.9345422 | T6: 3.205746 | U6: 3.6020715 | V6: 4.1223463 | W6: 3.9508706 | X6: 3.9424527 | Y6: 3.9340527 | Z6: 3.9256706 | AA6: markets/nand/dist/20261031_NAND市場模型_v0.3.xlsx｜Mkt!C140:Z140
A7: SanDisk 位元（情境 A） | B7: EB | C7: 31.287396 | D7: 29.615294 | E7: 31.15528 | F7: 33.514723 | G7: 38.069333 | H7: 33.617215 | I7: 33.091489 | J7: 34.558829 | K7: 36.970484 | L7: 39.091528 | M7: 41.334258 | N7: 43.705657 | O7: 46.213105 | P7: 48.86441 | Q7: 51.667822 | R7: 54.632071 | S7: 56.918713 | T7: 59.81981 | U7: 62.868774 | V7: 66.07314 | W7: 67.316109 | X7: 69.853961 | Y7: 72.487491 | Z7: 75.220307 | AA7: markets/nand/dist/20261031_NAND市場模型_v0.3.xlsx｜Mkt!C48:Z48
A8: SanDisk 位元（情境 B） | B8: EB | C8: 31.287396 | D8: 29.615294 | E8: 31.15528 | F8: 33.514723 | G8: 38.069333 | H8: 33.617215 | I8: 33.091489 | J8: 34.558829 | K8: 36.528255 | L8: 38.623927 | M8: 40.839831 | N8: 43.182863 | O8: 42.865204 | P8: 44.388385 | Q8: 45.965691 | R8: 47.599045 | S8: 50.687615 | T8: 53.360297 | U8: 56.173905 | V8: 59.13587 | W8: 58.630216 | X8: 60.535871 | Y8: 62.503465 | Z8: 64.535011 | AA8: markets/nand/dist/20261031_NAND市場模型_v0.3.xlsx｜Mkt!C96:Z96
A9: SanDisk 位元（情境 C） | B9: EB | C9: 31.287396 | D9: 29.615294 | E9: 31.15528 | F9: 33.514723 | G9: 38.069333 | H9: 33.617215 | I9: 33.091489 | J9: 34.558829 | K9: 36.086026 | L9: 38.156327 | M9: 40.345404 | N9: 42.66007 | O9: 38.581041 | P9: 38.674536 | Q9: 38.768258 | R9: 38.862207 | S9: 41.63648 | T9: 43.318506 | U9: 45.068482 | V9: 46.889154 | W9: 46.398085 | X9: 47.802771 | Y9: 49.249983 | Z9: 50.741009 | AA9: markets/nand/dist/20261031_NAND市場模型_v0.3.xlsx｜Mkt!C144:Z144
A10: Kioxia＋SanDisk 合資群份額（情境 A） | B10: % | C10: 0.27907731 | D10: 0.25560769 | E10: 0.27406433 | F10: 0.2689697 | G10: 0.27096015 | H10: 0.25018083 | I10: 0.25187361 | J10: 0.24502666 | K10: 0.24502666 | L10: 0.24502666 | M10: 0.24502666 | N10: 0.24502666 | O10: 0.24502666 | P10: 0.24502666 | Q10: 0.24502666 | R10: 0.24502666 | S10: 0.24502666 | T10: 0.24502666 | U10: 0.24502666 | V10: 0.24502666 | W10: 0.24502666 | X10: 0.24502666 | Y10: 0.24502666 | Z10: 0.24502666 | AA10: markets/nand/dist/20261031_NAND市場模型_v0.3.xlsx｜Mkt!C46:Z46
A11: Kioxia＋SanDisk 合資群份額（情境 B） | B11: % | C11: 0.27907731 | D11: 0.25560769 | E11: 0.27406433 | F11: 0.2689697 | G11: 0.27096015 | H11: 0.25018083 | I11: 0.25187361 | J11: 0.24502666 | K11: 0.24202666 | L11: 0.24202666 | M11: 0.24202666 | N11: 0.24202666 | O11: 0.23902666 | P11: 0.23902666 | Q11: 0.23902666 | R11: 0.23902666 | S11: 0.23602666 | T11: 0.23602666 | U11: 0.23602666 | V11: 0.23602666 | W11: 0.23302666 | X11: 0.23302666 | Y11: 0.23302666 | Z11: 0.23302666 | AA11: markets/nand/dist/20261031_NAND市場模型_v0.3.xlsx｜Mkt!C94:Z94
A12: Kioxia＋SanDisk 合資群份額（情境 C） | B12: % | C12: 0.27907731 | D12: 0.25560769 | E12: 0.27406433 | F12: 0.2689697 | G12: 0.27096015 | H12: 0.25018083 | I12: 0.25187361 | J12: 0.24502666 | K12: 0.23902666 | L12: 0.23902666 | M12: 0.23902666 | N12: 0.23902666 | O12: 0.23302666 | P12: 0.23302666 | Q12: 0.23302666 | R12: 0.23302666 | S12: 0.22702666 | T12: 0.22702666 | U12: 0.22702666 | V12: 0.22702666 | W12: 0.22102666 | X12: 0.22102666 | Y12: 0.22102666 | Z12: 0.22102666 | AA12: markets/nand/dist/20261031_NAND市場模型_v0.3.xlsx｜Mkt!C142:Z142
A14: AI 企業級 SSD 占企業級 SSD 位元需求（日曆年；markets/nand Ann 頁）
A15: 項目 | B15: 單位 | C15: CY2025 | D15: CY2026 | E15: CY2027 | F15: CY2028 | G15: CY2029 | H15: CY2030 | I15: 來源
A16: AI ÷ 企業級 SSD（情境 A） | B16: % | C16: 0.55 | D16: 0.75434243 | E16: 0.83145024 | F16: 0.85505592 | G16: 0.87526234 | H16: 0.8833345 | I16: markets/nand/dist/20261031_NAND市場模型_v0.3.xlsx｜Ann!D6:I6 ÷（同列＋下一列）
A17: AI ÷ 企業級 SSD（情境 B） | B17: % | C17: 0.55 | D17: 0.75434243 | E17: 0.83145024 | F17: 0.82515557 | G17: 0.85641057 | H17: 0.86551525 | I17: markets/nand/dist/20261031_NAND市場模型_v0.3.xlsx｜Ann!D33:I33 ÷（同列＋下一列）
A18: AI ÷ 企業級 SSD（情境 C） | B18: % | C18: 0.55 | D18: 0.75434243 | E18: 0.83145024 | F18: 0.77971276 | G18: 0.80806492 | H18: 0.81958931 | I18: markets/nand/dist/20261031_NAND市場模型_v0.3.xlsx｜Ann!D60:I60 ÷（同列＋下一列）

Sheet PL
A1: PL — SanDisk 損益（$B；FY2026 實績；FY2027–FY2029 由市場層 markets/nand 驅動；FY2030–FY2032 收斂法見底部）。頂端摘要，下方三情境各一個完整推導區塊
A3: 情境／項目 | B3: 單位 | C3: FY2025A | D3: FY2026A | E3: FY2027 | F3: FY2028 | G3: FY2029 | H3: 說明
A4: 情境 A（順利）
A5: 營收 | B5: $B | C5: =C77 -> 7.355 | D5: =D77 -> 20.248 | E5: =E77 -> 51.713658 | F5: =F77 -> 57.762315 | G5: =G77 -> 58.895915
A6: 資料中心 | B6: $B | D6: =D78 -> 5.153 | E6: =E78 -> 19.65119 | F6: =F78 -> 24.260172 | G6: =G78 -> 26.503162
A7: 資料中心：AI 相關 | B7: $B | D7: =D79 -> 3.3606383 | E7: =E79 -> 15.581357 | F7: =F79 -> 20.457465 | G7: =G79 -> 22.929452
A8: 邊緣 | B8: $B | D8: =D80 -> 12.16 | E8: =E80 -> 28.959649 | F8: =F80 -> 30.036404 | G8: =G80 -> 28.858998
A9: 消費 | B9: $B | D9: =D81 -> 2.935 | E9: =E81 -> 3.1028195 | F9: =F81 -> 3.4657389 | G9: =G81 -> 3.5337549
A10: 毛利率 | B10: % | D10: =D84 -> 0.71496933 | E10: =E84 -> 0.86918603 | F10: =F84 -> 0.87376026 | G10: =G84 -> 0.86810242
A11: 營業利益 | B11: $B | D11: =D86 -> 12.389 | E11: =E86 -> 42.475544 | F11: =F86 -> 47.741072 | G11: =G86 -> 48.171835
A12: 營業利益率 | B12: % | D12: =D87 -> 0.6118629 | E12: =E87 -> 0.82136026 | F12: =F87 -> 0.82650898 | G12: =G87 -> 0.81791471
A13: 淨利 | B13: $B | C13: =C88 -> -1.641 | D13: =D88 -> 11.433 | E13: =E88 -> 36.26612 | F13: =F88 -> 41.308315 | G13: =G88 -> 42.320508
A14: EPS | B14: USD | C14: =C96 -> -11.32 | D14: =D96 -> 73.76 | E14: =E96 -> 263.67344 | F14: =F96 -> 338.05574 | G14: =G96 -> 397.50825
A15: 每股淨值 | B15: USD | D15: =D97 -> 107.47166 | E15: =E97 -> 265.79415 | F15: =F97 -> 490.14228 | G15: =G97 -> 790.05784
A16: 自由現金流 | B16: $B | D16: =D91 -> 11.031 | E16: =E91 -> 33.323301 | F16: =F91 -> 38.002577 | G16: =G91 -> 38.946753
A18: 情境 B（平平）
A19: 營收 | B19: $B | C19: =C124 -> 7.355 | D19: =D124 -> 20.248 | E19: =E124 -> 52.209851 | F19: =F124 -> 40.996551 | G19: =G124 -> 22.132801
A20: 資料中心 | B20: $B | D20: =D125 -> 5.153 | E20: =E125 -> 19.839743 | F20: =F125 -> 17.218551 | G20: =G125 -> 9.9597603
A21: 資料中心：AI 相關 | B21: $B | D21: =D126 -> 3.3606383 | E21: =E126 -> 15.73086 | F21: =F126 -> 14.262176 | G21: =G126 -> 8.3739978
A22: 邊緣 | B22: $B | D22: =D127 -> 12.16 | E22: =E127 -> 29.237516 | F22: =F127 -> 21.318206 | G22: =G127 -> 10.845072
A23: 消費 | B23: $B | D23: =D128 -> 2.935 | E23: =E128 -> 3.132591 | F23: =F128 -> 2.459793 | G23: =G128 -> 1.327968
A24: 毛利率 | B24: % | D24: =D131 -> 0.71496933 | E24: =E131 -> 0.87008934 | F24: =F131 -> 0.82518594 | G24: =G131 -> 0.67158716
A25: 營業利益 | B25: $B | D25: =D133 -> 12.389 | E25: =E133 -> 42.949027 | F25: =F133 -> 31.268092 | G25: =G133 -> 12.275885
A26: 營業利益率 | B26: % | D26: =D134 -> 0.6118629 | E26: =E134 -> 0.82262306 | F26: =F134 -> 0.76270056 | G26: =G134 -> 0.55464671
A27: 淨利 | B27: $B | C27: =C135 -> -1.641 | D27: =D135 -> 11.433 | E27: =E135 -> 36.668581 | F27: =F135 -> 27.312618 | G27: =G135 -> 11.59446
A28: EPS | B28: USD | C28: =C143 -> -11.32 | D28: =D143 -> 73.76 | E28: =E143 -> 266.8916 | F28: =F143 -> 214.571 | G28: =G143 -> 94.203781
A29: 每股淨值 | B29: USD | D29: =D144 -> 107.47166 | E29: =E144 -> 267.72262 | F29: =F144 -> 410.42318 | G29: =G144 -> 478.85843
A30: 自由現金流 | B30: $B | D30: =D138 -> 11.031 | E30: =E138 -> 33.69599 | F30: =F138 -> 25.012825 | G30: =G138 -> 10.426492
A32: 情境 C（不如預期）
A33: 營收 | B33: $B | C33: =C171 -> 7.355 | D33: =D171 -> 20.248 | E33: =E171 -> 51.862074 | F33: =F171 -> 37.375241 | G33: =G171 -> 12.287504
A34: 資料中心 | B34: $B | D34: =D172 -> 5.153 | E34: =E172 -> 19.707588 | F34: =F172 -> 15.697601 | G34: =G172 -> 5.5293769
A35: 資料中心：AI 相關 | B35: $B | D35: =D173 -> 3.3606383 | E35: =E173 -> 15.626075 | F35: =F173 -> 12.645697 | G35: =G173 -> 4.3897106
A36: 邊緣 | B36: $B | D36: =D174 -> 12.16 | E36: =E174 -> 29.042762 | F36: =F174 -> 19.435126 | G36: =G174 -> 6.0208771
A37: 消費 | B37: $B | D37: =D175 -> 2.935 | E37: =E175 -> 3.1117245 | F37: =F175 -> 2.2425145 | G37: =G175 -> 0.73725025
A38: 毛利率 | B38: % | D38: =D178 -> 0.71496933 | E38: =E178 -> 0.86890965 | F38: =F178 -> 0.81467111 | G38: =G178 -> 0.48635761
A39: 營業利益 | B39: $B | D39: =D180 -> 12.389 | E39: =E180 -> 42.588727 | F39: =F180 -> 27.923057 | G39: =G180 -> 3.4863544
A40: 營業利益率 | B40: % | D40: =D181 -> 0.6118629 | E40: =E181 -> 0.82119213 | F40: =F181 -> 0.74710039 | G40: =G181 -> 0.2837317
A41: 淨利 | B41: $B | C41: =C182 -> -1.641 | D41: =D182 -> 11.433 | E41: =E182 -> 36.362326 | F41: =F182 -> 24.464487 | G41: =G182 -> 4.073783
A42: EPS | B42: USD | C42: =C190 -> -11.32 | D42: =D190 -> 73.76 | E42: =E190 -> 264.44069 | F42: =F190 -> 190.43373 | G42: =G190 -> 32.063131
A43: 每股淨值 | B43: USD | D43: =D191 -> 107.47166 | E43: =E191 -> 266.26002 | F43: =F191 -> 392.82934 | G43: =G191 -> 416.34634
A44: 自由現金流 | B44: $B | D44: =D185 -> 11.031 | E44: =E185 -> 33.410602 | F44: =F185 -> 22.381972 | G44: =G185 -> 3.4965328
A46: 核對：三情境 FY2026 − 實績（應為 0） | D46: =D100+D147+D194 -> 0
A56: 情境 A（順利）：markets/nand 情境 A（價格路徑 A、2028–29 顆數係數 A、合資群份額 A）；每位元成本年降 cd_A
A57: A. 季度 | B57: 單位 | C57: FQ1 FY26（2025Q3） | D57: FQ2 FY26（2025Q4） | E57: FQ3 FY26（2026Q1） | F57: FQ4 FY26（2026Q2） | G57: FQ1 FY27（2026Q3） | H57: FQ2 FY27（2026Q4） | I57: FQ3 FY27（2027Q1） | J57: FQ4 FY27（2027Q2） | K57: FQ1 FY28（2027Q3） | L57: FQ2 FY28（2027Q4） | M57: FQ3 FY28（2028Q1） | N57: FQ4 FY28（2028Q2） | O57: FQ1 FY29（2028Q3） | P57: FQ2 FY29（2028Q4） | Q57: FQ3 FY29（2029Q1） | R57: FQ4 FY29（2029Q2） | T57: 說明
A58: 市場層營收（TrendForce 口徑，同字母情境） | B58: $B | C58: =Units!E4*1 -> 2.31 | D58: =Units!F4*1 -> 3.03 | E58: =Units!G4*1 -> 5.95 | F58: =Units!H4*1 -> 8.97 | G58: =Units!I4*1 -> 11.037152 | H58: =Units!J4*1*1 -> 12.460212 | I58: =Units!K4*1*1 -> 13.729628 | J58: =Units!L4*1*1 -> 14.517314 | K58: =Units!M4*1*1 -> 14.582681 | L58: =Units!N4*1*1 -> 14.339957 | M58: =Units!O4*1*1 -> 14.404525 | N58: =Units!P4*1*1 -> 14.469384 | O58: =Units!Q4*1*1 -> 14.534536 | ... R58: =Units!T4*1*1 -> 15.041568 | T58: markets/nand；Sens 可乘份額係數、價格係數（FQ2 FY27 起）
A59: 位元（市場層；同字母） | B59: EB | C59: =Units!E7*1 -> 31.15528 | D59: =Units!F7*1 -> 33.514723 | E59: =Units!G7*1 -> 38.069333 | F59: =Units!H7*1 -> 33.617215 | G59: =Units!I7*1 -> 33.091489 | H59: =Units!J7*1 -> 34.558829 | I59: =Units!K7*1 -> 36.970484 | J59: =Units!L7*1 -> 39.091528 | ... R59: =Units!T7*1 -> 59.81981
A60: 營收 | B60: $B | C60: =q1_rev -> 2.308 | D60: =q2_rev -> 3.025 | E60: =q3_rev -> 5.95 | F60: =q4_rev -> 8.965 | G60: =G58*sd_k -> 11.030615 | H60: =H58*sd_k -> 12.452832 | I60: =I58*sd_k -> 13.721496 | J60: =J58*sd_k -> 14.508716 | K60: =K58*sd_k -> 14.574044 | L60: =L58*sd_k -> 14.331463 | M60: =M58*sd_k -> 14.395993 | N60: =N58*sd_k -> 14.460814 | ... R60: =R58*sd_k -> 15.032659 | T60: 實績季＝公司財報；之後＝市場層 × 公司口徑係數
A61: 資料中心 | B61: $B | C61: =q1_dc -> 0.269 | D61: =q2_dc -> 0.44 | E61: =q3_dc -> 1.467 | F61: =q4_dc -> 2.977 | G61: =G60*dcsh_27 -> 4.1916337 | H61: =H60*dcsh_27 -> 4.732076 | I61: =I60*dcsh_27 -> 5.2141685 | J61: =J60*dcsh_27 -> 5.513312 | K61: =K60*dcsh_28 -> 6.1210985 | L61: =L60*dcsh_28 -> 6.0192145 | M61: =M60*dcsh_28 -> 6.0463172 | N61: =N60*dcsh_28 -> 6.073542 | O61: =O60*dcsh_29 -> 6.5366671 | P61: =P60*dcsh_29 -> 6.5660998 | Q61: =Q60*dcsh_29 -> 6.6356982 | R61: =R60*dcsh_29 -> 6.7646965 | T61: 官方分部；實績季＝10-Q／10-K；之後＝營收 × 資料中心占比（In）
A62: 資料中心：AI 相關（＝資料中心 × AI 企業級 SSD 占比） | B62: $B | C62: =C61*(Units!C16+Units!D16)/2 -> 0.17543406 | D62: =D61*(Units!C16+Units!D16)/2 -> 0.28695533 | E62: =E61*(Units!C16+Units!D16)/2 -> 0.95673517 | F62: =F61*(Units!C16+Units!D16)/2 -> 1.9415137 | G62: =G61*(Units!D16+Units!E16)/2 -> 3.323531 | H62: =H61*(Units!D16+Units!E16)/2 -> 3.7520457 | I62: =I61*(Units!D16+Units!E16)/2 -> 4.1342951 | J62: =J61*(Units!D16+Units!E16)/2 -> 4.3714849 | K62: =K61*(Units!E16+Units!F16)/2 -> 5.1616352 | L62: =L61*(Units!E16+Units!F16)/2 -> 5.0757212 | M62: =M61*(Units!E16+Units!F16)/2 -> 5.0985756 | N62: =N61*(Units!E16+Units!F16)/2 -> 5.121533 | O62: =O61*(Units!F16+Units!G16)/2 -> 5.6552573 | P62: =P61*(Units!F16+Units!G16)/2 -> 5.6807212 | Q62: =Q61*(Units!F16+Units!G16)/2 -> 5.7409349 | R62: =R61*(Units!F16+Units!G16)/2 -> 5.852539 | T62: 命題子列（Derived）：會計年度 ≈ 前後兩個日曆年平均；假設 SanDisk 資料中心組合與產業企業級 SSD 相同
A63: 資料中心：非 AI | B63: $B | C63: =C61-C62 -> 0.093565943 | D63: =D61-D62 -> 0.15304467 | E63: =E61-E62 -> 0.51026483 | F63: =F61-F62 -> 1.0354863 | G63: =G61-G62 -> 0.86810269 | H63: =H61-H62 -> 0.98003028 | I63: =I61-I62 -> 1.0798734 | J63: =J61-J62 -> 1.1418271 | ... R63: =R61-R62 -> 0.91215757
A64: 消費 | B64: $B | C64: =q1_cs -> 0.652 | D64: =q2_cs -> 0.907 | E64: =q3_cs -> 0.82 | F64: =q4_cs -> 0.556 | G64: =G60*cssh_27 -> 0.6618369 | H64: =H60*cssh_27 -> 0.7471699 | I64: =I60*cssh_27 -> 0.82328977 | J64: =J60*cssh_27 -> 0.87052294 | K64: =K60*cssh_28 -> 0.87444265 | L64: =L60*cssh_28 -> 0.85988779 | M64: =M60*cssh_28 -> 0.86375961 | N64: =N60*cssh_28 -> 0.86764886 | O64: =O60*cssh_29 -> 0.87155562 | P64: =P60*cssh_29 -> 0.87547997 | Q64: =Q60*cssh_29 -> 0.88475976 | R64: =R60*cssh_29 -> 0.90195954 | T64: 官方分部
A65: 邊緣 | B65: $B | C65: =q1_ed -> 1.387 | D65: =q2_ed -> 1.678 | E65: =q3_ed -> 3.663 | F65: =q4_ed -> 5.432 | G65: =G60-G61-G64 -> 6.1771444 | H65: =H60-H61-H64 -> 6.9735857 | I65: =I60-I61-I64 -> 7.6840378 | J65: =J60-J61-J64 -> 8.1248808 | K65: =K60-K61-K64 -> 7.5785029 | L65: =L60-L61-L64 -> 7.4523608 | M65: =M60-M61-M64 -> 7.4859166 | N65: =N60-N61-N64 -> 7.5196234 | ... R65: =R60-R61-R64 -> 7.3660029 | T65: 官方分部；預測季＝營收 − 資料中心 − 消費
A66: 檢查：分部合計 − 營收（季） | B66: $B | C66: =C61+C65+C64-C60 -> 0 | D66: =D61+D65+D64-D60 -> 0 | E66: =E61+E65+E64-E60 -> 0 | F66: =F61+F65+F64-F60 -> 0 | G66: =G61+G65+G64-G60 -> 0 | H66: =H61+H65+H64-H60 -> 0 | I66: =I61+I65+I64-I60 -> 0 | J66: =J61+J65+J64-J60 -> 0 | ... R66: =R61+R65+R64-R60 -> 0
A67: 每 EB 營業成本（FQ1 FY27 以實績毛利率校準，之後每年 × (1 − 成本年降)） | B67: $B/EB | C67: =C68/C59 -> 0.052004539 | D67: =D68/D59 -> 0.04431709 | E67: =E68/E59 -> 0.033759457 | F67: =F68/F59 -> 0.041068541 | G67: =(1-g_gm)*G60/G59 -> 0.049900536 | H67: =$G67*(1-cd_A)^(1/4) -> 0.048054031 | I67: =$G67*(1-cd_A)^(2/4) -> 0.046275853 | J67: =$G67*(1-cd_A)^(3/4) -> 0.044563475 | K67: =$G67*(1-cd_A)^(4/4) -> 0.042914461 | L67: =$G67*(1-cd_A)^(5/4) -> 0.041326467 | M67: =$G67*(1-cd_A)^(6/4) -> 0.039797234 | N67: =$G67*(1-cd_A)^(7/4) -> 0.038324588 | O67: =$G67*(1-cd_A)^(8/4) -> 0.036906436 | P67: =$G67*(1-cd_A)^(9/4) -> 0.035540761 | Q67: =$G67*(1-cd_A)^(10/4) -> 0.034225621 | R67: =$G67*(1-cd_A)^(11/4) -> 0.032959146
A68: 營業成本 | B68: $B | C68: =q1_rev*(1-q1_gm) -> 1.620216 | D68: =q2_rev*(1-q2_gm) -> 1.485275 | E68: =q3_rev*(1-q3_gm) -> 1.2852 | F68: =q4_rev*(1-q4_gm) -> 1.38061 | G68: =G59*G67 -> 1.6512831 | H68: =H59*H67 -> 1.660691 | I68: =I59*I67 -> 1.7108407 | J68: =J59*J67 -> 1.7420543 | K68: =K59*K67 -> 1.7738374 | L68: =L59*L67 -> 1.8062004 | M68: =M59*M67 -> 1.8391538 | N68: =N59*N67 -> 1.8727084 | ... R68: =R59*R67 -> 1.9716099
A69: 毛利率 | B69: % | C69: =1-C68/C60 -> 0.298 | D69: =1-D68/D60 -> 0.509 | E69: =1-E68/E60 -> 0.784 | F69: =1-F68/F60 -> 0.846 | G69: =1-G68/G60 -> 0.8503 | H69: =1-H68/H60 -> 0.86664149 | I69: =1-I68/I60 -> 0.87531675 | J69: =1-J68/J60 -> 0.8799305 | ... R69: =1-R68/R60 -> 0.8688449
A70: 營業費用 | B70: $B | C70: =q1_rev-q1_rev*(1-q1_gm)-q1_op -> 0.511784 | D70: =q2_rev-q2_rev*(1-q2_gm)-q2_op -> 0.474725 | E70: =q3_rev-q3_rev*(1-q3_gm)-q3_op -> 0.5538 | F70: =q4_rev-q4_rev*(1-q4_gm)-q4_op -> 0.54739 | G70: =(g_ox-ox_var*g_rev)*(1+ox_g)^(0/4)+ox_var*G60 -> 0.58199615 | H70: =(g_ox-ox_var*g_rev)*(1+ox_g)^(1/4)+ox_var*H60 -> 0.6075925 | I70: =(g_ox-ox_var*g_rev)*(1+ox_g)^(2/4)+ox_var*I60 -> 0.63192761 | J70: =(g_ox-ox_var*g_rev)*(1+ox_g)^(3/4)+ox_var*J60 -> 0.65172915 | K70: =(g_ox-ox_var*g_rev)*(1+ox_g)^(4/4)+ox_var*K60 -> 0.66459944 | L70: =(g_ox-ox_var*g_rev)*(1+ox_g)^(5/4)+ox_var*L60 -> 0.67468524 | M70: =(g_ox-ox_var*g_rev)*(1+ox_g)^(6/4)+ox_var*M60 -> 0.68814384 | N70: =(g_ox-ox_var*g_rev)*(1+ox_g)^(7/4)+ox_var*N60 -> 0.70191433 | O70: =(g_ox-ox_var*g_rev)*(1+ox_g)^(8/4)+ox_var*O60 -> 0.71600417 | P70: =(g_ox-ox_var*g_rev)*(1+ox_g)^(9/4)+ox_var*P60 -> 0.73042099 | Q70: =(g_ox-ox_var*g_rev)*(1+ox_g)^(10/4)+ox_var*Q60 -> 0.74606226 | R70: =(g_ox-ox_var*g_rev)*(1+ox_g)^(11/4)+ox_var*R60 -> 0.7633634 | T70: 固定部分以 FQ1 FY27 營業費用（實績推估）校準（Derived）
A71: 營業利益 | B71: $B | C71: =C60-C68-C70 -> 0.176 | D71: =D60-D68-D70 -> 1.065 | E71: =E60-E68-E70 -> 4.111 | F71: =F60-F68-F70 -> 7.037 | G71: =G60-G68-G70 -> 8.7973357 | H71: =H60-H68-H70 -> 10.184548 | I71: =I60-I68-I70 -> 11.378728 | J71: =J60-J68-J70 -> 12.114932 | ... R71: =R60-R68-R70 -> 12.297686
A73: 淨利 | B73: $B | C73: =q1_ni -> 0.112 | D73: =q2_ni -> 0.803 | E73: =q3_ni -> 3.615 | F73: =q4_ni -> 6.903 | G73: =(G71+rf*$D94/4)*(1-tax) -> 7.5182124 | H73: =(H71+rf*$D94/4)*(1-tax) -> 8.6973429 | I73: =(I71+rf*$D94/4)*(1-tax) -> 9.7123956 | J73: =(J71+rf*$D94/4)*(1-tax) -> 10.338169 | K73: =(K71+rf*$E94/4)*(1-tax) -> 10.497367 | L73: =(L71+rf*$E94/4)*(1-tax) -> 10.255092 | M73: =(M71+rf*$E94/4)*(1-tax) -> 10.270492 | N73: =(N71+rf*$E94/4)*(1-tax) -> 10.285364 | O73: =(O71+rf*$F94/4)*(1-tax) -> 10.461202 | P73: =(P71+rf*$F94/4)*(1-tax) -> 10.474972 | Q73: =(Q71+rf*$F94/4)*(1-tax) -> 10.587689 | R73: =(R71+rf*$F94/4)*(1-tax) -> 10.796645 | T73: （營業利益＋上一年底淨現金 × 收益率 ÷ 4）×（1 − 稅率）
A74: 季 EPS（稀釋） | B74: USD | G74: =G73/(sh0+dil)*1000 -> 49.789486 | H74: =H73/(sh0+dil)*1000 -> 57.598297 | I74: =I73/(sh0+dil)*1000 -> 64.320501 | J74: =J73/(sh0+dil)*1000 -> 68.464698 | K74: =K73/(sh0+dil)*1000 -> 69.518988 | L74: =L73/(sh0+dil)*1000 -> 67.914516 | M74: =M73/(sh0+dil)*1000 -> 68.016506 | N74: =N73/(sh0+dil)*1000 -> 68.114992 | ... R74: =R73/(sh0+dil)*1000 -> 71.500959
A76: B. 年度（會計年度） | B76: 單位 | C76: FY2025A | D76: FY2026A | E76: FY2027 | F76: FY2028 | G76: FY2029 | T76: 說明
A77: 營收 | B77: $B | C77: =a25_rev -> 7.355 | D77: =SUM(C60:F60) -> 20.248 | E77: =SUM(G60:J60) -> 51.713658 | F77: =SUM(K60:N60) -> 57.762315 | G77: =SUM(O60:R60) -> 58.895915
A78: 營收：資料中心 | B78: $B | D78: =SUM(C61:F61) -> 5.153 | E78: =SUM(G61:J61) -> 19.65119 | F78: =SUM(K61:N61) -> 24.260172 | G78: =SUM(O61:R61) -> 26.503162
A79: 資料中心：AI 相關 | B79: $B | D79: =SUM(C62:F62) -> 3.3606383 | E79: =SUM(G62:J62) -> 15.581357 | F79: =SUM(K62:N62) -> 20.457465 | G79: =SUM(O62:R62) -> 22.929452
A80: 營收：邊緣 | B80: $B | D80: =SUM(C65:F65) -> 12.16 | E80: =SUM(G65:J65) -> 28.959649 | F80: =SUM(K65:N65) -> 30.036404 | G80: =SUM(O65:R65) -> 28.858998
A81: 營收：消費 | B81: $B | D81: =SUM(C64:F64) -> 2.935 | E81: =SUM(G64:J64) -> 3.1028195 | F81: =SUM(K64:N64) -> 3.4657389 | G81: =SUM(O64:R64) -> 3.5337549
A82: 檢查：分部合計 − 合併營收（年；FY2026 另比 10-K 分部） | B82: $B | D82: =D78+D80+D81-D77+ABS(D78-a26_dc)+ABS(D80-a26_ed)+ABS(D81-a26_cs) -> 0 | E82: =E78+E80+E81-E77 -> 0 | F82: =F78+F80+F81-F77 -> 0 | G82: =G78+G80+G81-G77 -> 0
A83: 營業成本 | B83: $B | D83: =SUM(C68:F68) -> 5.771301 | E83: =SUM(G68:J68) -> 6.7648691 | F83: =SUM(K68:N68) -> 7.2918999 | G83: =SUM(O68:R68) -> 7.7682288
A84: 毛利率 | B84: % | D84: =1-D83/D77 -> 0.71496933 | E84: =1-E83/E77 -> 0.86918603 | F84: =1-F83/F77 -> 0.87376026 | G84: =1-G83/G77 -> 0.86810242
A85: 營業費用 | B85: $B | D85: =SUM(C70:F70) -> 2.087699 | E85: =SUM(G70:J70) -> 2.4732454 | F85: =SUM(K70:N70) -> 2.7293429 | G85: =SUM(O70:R70) -> 2.9558508
A86: 營業利益 | B86: $B | D86: =SUM(C71:F71) -> 12.389 | E86: =SUM(G71:J71) -> 42.475544 | F86: =SUM(K71:N71) -> 47.741072 | G86: =SUM(O71:R71) -> 48.171835
A87: 營業利益率 | B87: % | D87: =D86/D77 -> 0.6118629 | E87: =E86/E77 -> 0.82136026 | F87: =F86/F77 -> 0.82650898 | G87: =G86/G77 -> 0.81791471
A88: 淨利 | B88: $B | C88: =a25_ni -> -1.641 | D88: =SUM(C73:F73) -> 11.433 | E88: =SUM(G73:J73) -> 36.26612 | F88: =SUM(K73:N73) -> 41.308315 | G88: =SUM(O73:R73) -> 42.320508
A89: 折舊攤銷（公司本身） | B89: $B | D89: =da_y -> 0.16 | E89: =da_y -> 0.16 | F89: =da_y -> 0.16 | G89: =da_y -> 0.16
A90: 資本支出（含合資群分攤） | B90: $B | D90: 0.562 | E90: =cap_r*E77 -> 3.1028195 | F90: =cap_r*F77 -> 3.4657389 | G90: =cap_r*G77 -> 3.5337549 | T90: FY2026 毛資本支出 0.562（公司簡報；markets/equipment In 頁）
A91: 自由現金流（淨利＋折舊 − 資本支出） | B91: $B | D91: =D88+D89-D90 -> 11.031 | E91: =E88+E89-E90 -> 33.323301 | F91: =F88+F89-F90 -> 38.002577 | G91: =G88+G89-G90 -> 38.946753
A92: 買回 | B92: $B | D92: 4.524 | E92: =MAX(0,payout*E91) -> 16.66165 | F92: =MAX(0,payout*F91) -> 19.001288 | G92: =MAX(0,payout*G91) -> 19.473376 | T92: FY2026 實績 4.524（FQ4）
A93: 期末權益 | B93: $B | D93: =eq0 -> 15.736 | E93: =D93+E88-E92 -> 35.34047 | F93: =E93+F88-F92 -> 57.647497 | G93: =F93+G88-G92 -> 80.494628
A94: 期末淨現金 | B94: $B | D94: =nc0 -> 4.762 | E94: =D94+E91-E92 -> 21.42365 | F94: =E94+F91-F92 -> 40.424939 | G94: =F94+G91-G92 -> 59.898315
A95: 期末流通股數 | B95: 百萬股 | D95: =sh0 -> 146.42 | E95: =D95-E92/bb_px*1000 -> 132.9618 | F95: =E95-F92/bb_px*1000 -> 117.6138 | G95: =F95-G92/bb_px*1000 -> 101.88448
A96: EPS（稀釋：期末流通股數＋dil） | B96: USD | C96: =a25_eps -> -11.32 | D96: =a26_eps -> 73.76 | E96: =E88/(E95+dil)*1000 -> 263.67344 | F96: =F88/(F95+dil)*1000 -> 338.05574 | G96: =G88/(G95+dil)*1000 -> 397.50825
A97: 每股淨值 BVPS（期末流通股數） | B97: USD | D97: =D93/D95*1000 -> 107.47166 | E97: =E93/E95*1000 -> 265.79415 | F97: =F93/F95*1000 -> 490.14228 | G97: =G93/G95*1000 -> 790.05784
A98: ROE（期末權益） | B98: % | D98: =D88/D93 -> 0.72655058 | E98: =E88/E93 -> 1.0261924 | F98: =F88/F93 -> 0.71656737 | G98: =G88/G93 -> 0.52575568
A99: 每股自由現金流（稀釋） | B99: USD | E99: =E91/(E95+dil)*1000 -> 242.27762 | F99: =F91/(F95+dil)*1000 -> 311.00249 | G99: =G91/(G95+dil)*1000 -> 365.81923
A100: 檢查：FY2026 營收、淨利 − 實績（應為 0） | B100: $B | D100: =ABS(D77-a26_rev)+ABS(D88-a26_ni) -> 0
A103: 情境 B（平平）：markets/nand 情境 B（價格路徑 B、2028–29 顆數係數 B、合資群份額 B）；每位元成本年降 cd_B
A104: A. 季度 | B104: 單位 | C104: FQ1 FY26（2025Q3） | D104: FQ2 FY26（2025Q4） | E104: FQ3 FY26（2026Q1） | F104: FQ4 FY26（2026Q2） | G104: FQ1 FY27（2026Q3） | H104: FQ2 FY27（2026Q4） | I104: FQ3 FY27（2027Q1） | J104: FQ4 FY27（2027Q2） | K104: FQ1 FY28（2027Q3） | L104: FQ2 FY28（2027Q4） | M104: FQ3 FY28（2028Q1） | N104: FQ4 FY28（2028Q2） | O104: FQ1 FY29（2028Q3） | P104: FQ2 FY29（2028Q4） | Q104: FQ3 FY29（2029Q1） | R104: FQ4 FY29（2029Q2） | T104: 說明
A105: 市場層營收（TrendForce 口徑，同字母情境） | B105: $B | C105: =Units!E5*1 -> 2.31 | D105: =Units!F5*1 -> 3.03 | E105: =Units!G5*1 -> 5.95 | F105: =Units!H5*1 -> 8.97 | G105: =Units!I5*1 -> 11.037152 | H105: =Units!J5*1*1 -> 12.460212 | I105: =Units!K5*1*1 -> 13.828805 | J105: =Units!L5*1*1 -> 14.914624 | K105: =Units!M5*1*1 -> 14.193265 | L105: =Units!N5*1*1 -> 12.006041 | M105: =Units!O5*1*1 -> 8.3424059 | N105: =Units!P5*1*1 -> 6.479135 | O105: =Units!Q5*1*1 -> 5.3674927 | ... R105: =Units!T5*1*1 -> 6.1826835 | T105: markets/nand；Sens 可乘份額係數、價格係數（FQ2 FY27 起）
A106: 位元（市場層；同字母） | B106: EB | C106: =Units!E8*1 -> 31.15528 | D106: =Units!F8*1 -> 33.514723 | E106: =Units!G8*1 -> 38.069333 | F106: =Units!H8*1 -> 33.617215 | G106: =Units!I8*1 -> 33.091489 | H106: =Units!J8*1 -> 34.558829 | I106: =Units!K8*1 -> 36.528255 | J106: =Units!L8*1 -> 38.623927 | ... R106: =Units!T8*1 -> 53.360297
A107: 營收 | B107: $B | C107: =q1_rev -> 2.308 | D107: =q2_rev -> 3.025 | E107: =q3_rev -> 5.95 | F107: =q4_rev -> 8.965 | G107: =G105*sd_k -> 11.030615 | H107: =H105*sd_k -> 12.452832 | I107: =I105*sd_k -> 13.820614 | J107: =J105*sd_k -> 14.90579 | K107: =K105*sd_k -> 14.184859 | L107: =L105*sd_k -> 11.99893 | M107: =M105*sd_k -> 8.3374647 | N107: =N105*sd_k -> 6.4752974 | ... R107: =R105*sd_k -> 6.1790215 | T107: 實績季＝公司財報；之後＝市場層 × 公司口徑係數
A108: 資料中心 | B108: $B | C108: =q1_dc -> 0.269 | D108: =q2_dc -> 0.44 | E108: =q3_dc -> 1.467 | F108: =q4_dc -> 2.977 | G108: =G107*dcsh_27 -> 4.1916337 | H108: =H107*dcsh_27 -> 4.732076 | I108: =I107*dcsh_27 -> 5.2518332 | J108: =J107*dcsh_27 -> 5.6642003 | K108: =K107*dcsh_28 -> 5.9576407 | L108: =L107*dcsh_28 -> 5.0395505 | M108: =M107*dcsh_28 -> 3.5017352 | N108: =N107*dcsh_28 -> 2.7196249 | O108: =O107*dcsh_29 -> 2.4139411 | P108: =P107*dcsh_29 -> 2.2497467 | Q108: =Q107*dcsh_29 -> 2.5155128 | R108: =R107*dcsh_29 -> 2.7805597 | T108: 官方分部；實績季＝10-Q／10-K；之後＝營收 × 資料中心占比（In）
A109: 資料中心：AI 相關（＝資料中心 × AI 企業級 SSD 占比） | B109: $B | C109: =C108*(Units!C17+Units!D17)/2 -> 0.17543406 | D109: =D108*(Units!C17+Units!D17)/2 -> 0.28695533 | E109: =E108*(Units!C17+Units!D17)/2 -> 0.95673517 | F109: =F108*(Units!C17+Units!D17)/2 -> 1.9415137 | G109: =G108*(Units!D17+Units!E17)/2 -> 3.323531 | H109: =H108*(Units!D17+Units!E17)/2 -> 3.7520457 | I109: =I108*(Units!D17+Units!E17)/2 -> 4.1641593 | J109: =J108*(Units!D17+Units!E17)/2 -> 4.4911236 | K109: =K108*(Units!E17+Units!F17)/2 -> 4.9347311 | L109: =L108*(Units!E17+Units!F17)/2 -> 4.1742743 | M109: =M108*(Units!E17+Units!F17)/2 -> 2.9004974 | N109: =N108*(Units!E17+Units!F17)/2 -> 2.2526732 | O109: =O108*(Units!F17+Units!G17)/2 -> 2.0296008 | P109: =P108*(Units!F17+Units!G17)/2 -> 1.8915489 | Q109: =Q108*(Units!F17+Units!G17)/2 -> 2.1150006 | R109: =R108*(Units!F17+Units!G17)/2 -> 2.3378475 | T109: 命題子列（Derived）：會計年度 ≈ 前後兩個日曆年平均；假設 SanDisk 資料中心組合與產業企業級 SSD 相同
A110: 資料中心：非 AI | B110: $B | C110: =C108-C109 -> 0.093565943 | D110: =D108-D109 -> 0.15304467 | E110: =E108-E109 -> 0.51026483 | F110: =F108-F109 -> 1.0354863 | G110: =G108-G109 -> 0.86810269 | H110: =H108-H109 -> 0.98003028 | I110: =I108-I109 -> 1.0876739 | J110: =J108-J109 -> 1.1730766 | ... R110: =R108-R109 -> 0.44271217
A111: 消費 | B111: $B | C111: =q1_cs -> 0.652 | D111: =q2_cs -> 0.907 | E111: =q3_cs -> 0.82 | F111: =q4_cs -> 0.556 | G111: =G107*cssh_27 -> 0.6618369 | H111: =H107*cssh_27 -> 0.7471699 | I111: =I107*cssh_27 -> 0.82923682 | J111: =J107*cssh_27 -> 0.89434741 | K111: =K107*cssh_28 -> 0.85109153 | L111: =L107*cssh_28 -> 0.71993578 | M111: =M107*cssh_28 -> 0.50024788 | N111: =N107*cssh_28 -> 0.38851784 | O111: =O107*cssh_29 -> 0.32185881 | P111: =P107*cssh_29 -> 0.29996623 | Q111: =Q107*cssh_29 -> 0.33540171 | R111: =R107*cssh_29 -> 0.37074129 | T111: 官方分部
A112: 邊緣 | B112: $B | C112: =q1_ed -> 1.387 | D112: =q2_ed -> 1.678 | E112: =q3_ed -> 3.663 | F112: =q4_ed -> 5.432 | G112: =G107-G108-G111 -> 6.1771444 | H112: =H107-H108-H111 -> 6.9735857 | I112: =I107-I108-I111 -> 7.7395437 | J112: =J107-J108-J111 -> 8.3472425 | K112: =K107-K108-K111 -> 7.3761266 | L112: =L107-L108-L111 -> 6.2394434 | M112: =M107-M108-M111 -> 4.3354816 | N112: =N107-N108-N111 -> 3.3671546 | ... R112: =R107-R108-R111 -> 3.0277205 | T112: 官方分部；預測季＝營收 − 資料中心 − 消費
A113: 檢查：分部合計 − 營收（季） | B113: $B | C113: =C108+C112+C111-C107 -> 0 | D113: =D108+D112+D111-D107 -> 0 | E113: =E108+E112+E111-E107 -> 0 | F113: =F108+F112+F111-F107 -> 0 | G113: =G108+G112+G111-G107 -> 0 | H113: =H108+H112+H111-H107 -> 0 | I113: =I108+I112+I111-I107 -> 0 | J113: =J108+J112+J111-J107 -> 0 | ... R113: =R108+R112+R111-R107 -> 0
A114: 每 EB 營業成本（FQ1 FY27 以實績毛利率校準，之後每年 × (1 − 成本年降)） | B114: $B/EB | C114: =C115/C106 -> 0.052004539 | D114: =D115/D106 -> 0.04431709 | E114: =E115/E106 -> 0.033759457 | F114: =F115/F106 -> 0.041068541 | G114: =(1-g_gm)*G107/G106 -> 0.049900536 | H114: =$G114*(1-cd_B)^(1/4) -> 0.048331011 | I114: =$G114*(1-cd_B)^(2/4) -> 0.046810852 | J114: =$G114*(1-cd_B)^(3/4) -> 0.045338507 | K114: =$G114*(1-cd_B)^(4/4) -> 0.043912472 | L114: =$G114*(1-cd_B)^(5/4) -> 0.042531289 | M114: =$G114*(1-cd_B)^(6/4) -> 0.04119355 | N114: =$G114*(1-cd_B)^(7/4) -> 0.039897886 | O114: =$G114*(1-cd_B)^(8/4) -> 0.038642975 | P114: =$G114*(1-cd_B)^(9/4) -> 0.037427535 | Q114: =$G114*(1-cd_B)^(10/4) -> 0.036250324 | R114: =$G114*(1-cd_B)^(11/4) -> 0.03511014
A115: 營業成本 | B115: $B | C115: =q1_rev*(1-q1_gm) -> 1.620216 | D115: =q2_rev*(1-q2_gm) -> 1.485275 | E115: =q3_rev*(1-q3_gm) -> 1.2852 | F115: =q4_rev*(1-q4_gm) -> 1.38061 | G115: =G106*G114 -> 1.6512831 | H115: =H106*H114 -> 1.6702631 | I115: =I106*I114 -> 1.7099187 | J115: =J106*J114 -> 1.7511512 | K115: =K106*K114 -> 1.7933779 | L115: =L106*L114 -> 1.8366229 | M115: =M106*M114 -> 1.7657699 | N115: =N106*N114 -> 1.7710027 | ... R115: =R106*R114 -> 1.8734875
A116: 毛利率 | B116: % | C116: =1-C115/C107 -> 0.298 | D116: =1-D115/D107 -> 0.509 | E116: =1-E115/E107 -> 0.784 | F116: =1-F115/F107 -> 0.846 | G116: =1-G115/G107 -> 0.8503 | H116: =1-H115/H107 -> 0.86587283 | I116: =1-I115/I107 -> 0.87627765 | J116: =1-J115/J107 -> 0.88251873 | ... R116: =1-R115/R107 -> 0.69679868
A117: 營業費用 | B117: $B | C117: =q1_rev-q1_rev*(1-q1_gm)-q1_op -> 0.511784 | D117: =q2_rev-q2_rev*(1-q2_gm)-q2_op -> 0.474725 | E117: =q3_rev-q3_rev*(1-q3_gm)-q3_op -> 0.5538 | F117: =q4_rev-q4_rev*(1-q4_gm)-q4_op -> 0.54739 | G117: =(g_ox-ox_var*g_rev)*(1+ox_g)^(0/4)+ox_var*G107 -> 0.58199615 | H117: =(g_ox-ox_var*g_rev)*(1+ox_g)^(1/4)+ox_var*H107 -> 0.6075925 | I117: =(g_ox-ox_var*g_rev)*(1+ox_g)^(2/4)+ox_var*I107 -> 0.63291878 | J117: =(g_ox-ox_var*g_rev)*(1+ox_g)^(3/4)+ox_var*J107 -> 0.65569989 | K117: =(g_ox-ox_var*g_rev)*(1+ox_g)^(4/4)+ox_var*K107 -> 0.66070759 | L117: =(g_ox-ox_var*g_rev)*(1+ox_g)^(5/4)+ox_var*L107 -> 0.6513599 | M117: =(g_ox-ox_var*g_rev)*(1+ox_g)^(6/4)+ox_var*M107 -> 0.62755856 | N117: =(g_ox-ox_var*g_rev)*(1+ox_g)^(7/4)+ox_var*N107 -> 0.62205917 | O117: =(g_ox-ox_var*g_rev)*(1+ox_g)^(8/4)+ox_var*O107 -> 0.62438804 | P117: =(g_ox-ox_var*g_rev)*(1+ox_g)^(9/4)+ox_var*P107 -> 0.63450204 | Q117: =(g_ox-ox_var*g_rev)*(1+ox_g)^(10/4)+ox_var*Q107 -> 0.65450259 | R117: =(g_ox-ox_var*g_rev)*(1+ox_g)^(11/4)+ox_var*R107 -> 0.67482703 | T117: 固定部分以 FQ1 FY27 營業費用（實績推估）校準（Derived）
...

Sheet Val
A1: Val — 估值。第 0 節為目標價（DCF 與 Comparable 加權；Comparable 依記憶體慣例用前瞻 P/B）；第 5–6 節為目前倍數、十年倍數與規則值（舊法參考）
A2: SanDisk 2025-02 自 WDC 分拆上市，無十年自身倍數歷史：十年 P/B、P/E 以美光（同為記憶體循環股）為 Analogy，見第 6 節
A4: 0. 目標價
A5: 0.1 DCF（股東權益現金流，FY2027–FY2032 明確期＋FY2032 後永續）
A6: 項目 | B6: A（順利） | C6: B（平平） | D6: C（不如預期） | E6: 說明
A7: 情境 EPS（FY2027–FY2032） | E7: PL 頁延伸區塊；FY2030 起為收斂法（灰底）
A8: FY2027 | B8: =PL!D205 -> 263.67344 | C8: =PL!D212 -> 266.8916 | D8: =PL!D219 -> 264.44069
A9: FY2028 | B9: =PL!E205 -> 338.05574 | C9: =PL!E212 -> 214.571 | D9: =PL!E219 -> 190.43373
A10: FY2029 | B10: =PL!F205 -> 397.50825 | C10: =PL!F212 -> 94.203781 | D10: =PL!F219 -> 32.063131
A11: FY2030 | B11: =PL!G205 -> 307.29209 | C11: =PL!G212 -> 50.585304 | D11: =PL!G219 -> 14.067064
A12: FY2031 | B12: =PL!H205 -> 213.41599 | C12: =PL!H212 -> 30.222915 | D12: =PL!H219 -> 8.0579466
A13: FY2032 | B13: =PL!I205 -> 111.55225 | C13: =PL!I212 -> 16.921 | D13: =PL!I219 -> 5.1088987
A14: 股東現金流＝EPS ×（1 − tp_g ÷ tp_roe） | E14: 記憶體資本密集：FY2027–FY2029 改用每股（淨利＋折舊－資本支出）＝ PL 區塊每股自由現金流（資本支出含合資群分攤）；收斂期（FY2030 起）用 EPS ×（1 − 再投資率）
A15: 再投資率（tp_g ÷ tp_roe，上限 0.8；FY2030 起用） | B15: =MIN(tp_g/tp_roe,0.8) -> 0.1458548 | E15: ROE 為 FY2025–FY2026 平均（In 頁 tp_roe）
A16: FY2027（淨利＋折舊－資本支出，每股） | B16: =PL!E99 -> 242.27762 | C16: =PL!E146 -> 245.25565 | D16: =PL!E193 -> 242.97463
A17: FY2028（淨利＋折舊－資本支出，每股） | B17: =PL!F99 -> 311.00249 | C17: =PL!F146 -> 196.50356 | D17: =PL!F193 -> 174.22325
A18: FY2029（淨利＋折舊－資本支出，每股） | B18: =PL!G99 -> 365.81923 | C18: =PL!G146 -> 84.714162 | D18: =PL!G193 -> 27.519823
A19: FY2030（EPS ×（1 − 再投資率）） | B19: =B11*(1-$B$15) -> 262.47206 | C19: =C11*(1-$B$15) -> 43.207194 | D19: =D11*(1-$B$15) -> 12.015315
A20: FY2031（EPS ×（1 − 再投資率）） | B20: =B12*(1-$B$15) -> 182.28824 | C20: =C12*(1-$B$15) -> 25.814758 | D20: =D12*(1-$B$15) -> 6.8826564
A21: FY2032（EPS ×（1 − 再投資率）） | B21: =B13*(1-$B$15) -> 95.281821 | C21: =C13*(1-$B$15) -> 14.452991 | D21: =D13*(1-$B$15) -> 4.3637413
A22: DCF 情境每股價值（折現率 tp_r） | B22: =MAX(0,SUMPRODUCT(B16:B21,1/(1+tp_r)^{1;2;3;4;5;6})+B21*(1+tp_g)/(tp_r-tp_g)/(1+tp_r)^6) -> 2030.6251 | C22: =MAX(0,SUMPRODUCT(C16:C21,1/(1+tp_r)^{1;2;3;4;5;6})+C21*(1+tp_g)/(tp_r-tp_g)/(1+tp_r)^6) -> 644.11586 | D22: =MAX(0,SUMPRODUCT(D16:D21,1/(1+tp_r)^{1;2;3;4;5;6})+D21*(1+tp_g)/(tp_r-tp_g)/(1+tp_r)^6) -> 443.18744 | E22: Σ 明確期現金流 ÷ (1＋r)^t ＋ 永續價值 ÷ (1＋r)^6；永續價值＝FY2032 現金流 ×(1＋g)÷(r−g)；基準日 2026 年底，t＝1 對 FY2027（FY2027 於 2027-06 結束，t 以會計年度計，略低估）；負值取 0（股東有限責任）
A23: DCF 情境價值推到 12 個月後（×(1＋tp_r)） | B23: =B22*(1+tp_r) -> 2233.6877 | C23: =C22*(1+tp_r) -> 708.52745 | D23: =D22*(1+tp_r) -> 487.50619
A24: DCF 目標價（情境加權） | B24: =tp_wA*B23+tp_wB*C23+tp_wC*D23 -> 1121.8713 | E24: Σ 權重 × 情境價值 ×(1＋r)；權重見 In 頁 tp_wA／tp_wB／tp_wC
A26: 0.2 Comparable（市場主流同業前瞻 P/B；記憶體慣例）
A27: 同業與前瞻 P/B | B27: 代號 | C27: 前瞻 P/B | D27: 日期 | E27: 來源 | F27: 標記
A28: 美光 | B28: MU | C28: 3.35 | D28: 2026-10-23 | E28: MarketScreener：現價 ÷ FY2027E（2027-09）每股淨值（micron/ 模型同值） | F28: Interested-party
A29: SK 海力士 | B29: 000660.KS | C29: 1.35 | D29: 2026-10-23 | E29: MarketScreener：現價 ÷ 2027E 每股淨值（skhynix/ 模型同值） | F29: Interested-party
A30: 三星電子 | B30: 005930.KS | C30: 1.26 | D30: 2026-10-23 | E30: MarketScreener：現價 ÷ 2027E 每股淨值（samsung/ 模型同值） | F30: Interested-party
A31: Kioxia | B31: 285A.T | C31: =12755/7808 -> 1.6335809 | D31: 2026-10-23 | E31: 現價 ¥12,755（stockanalysis，分割後）÷ MarketScreener FY2028E（2028-03）每股淨值 ¥7,808 | F31: Interested-party
A32: 同業前瞻 P/B 中位數 | B32: =MEDIAN(C28:C31) -> 1.4917905 | E32: 記憶體同業（美光、SK 海力士、三星、Kioxia；無 A 股）。WDC（硬碟）不列入 P/B：僅有落後 P/B 13.5x（stockanalysis），與記憶體不可比；P/E 並列參考見下方。SanDisk 自身現價 ÷ 2027 年底每股淨值（FY27、FY28 共識平均）約 2.9x
A33: 12 個月後的前瞻每股淨值（情境加權） | B33: =tp_wA*(PL!F97+PL!G97)/2+tp_wB*(PL!F144+PL!G144)/2+tp_wC*(PL!F191+PL!G191)/2 -> 495.26799 | E33: 同業倍數＝現價 ÷ 約 14 個月後（約 2027 年底）每股淨值；對應 12 個月後（約 2027-10）用約 2028 年底每股淨值＝（FY2028 年底＋FY2029 年底）÷ 2（會計年度 6 月，依月份調整）
A34: Comparable 目標價 | B34: =B32*B33 -> 738.83607 | E34: 同業中位數 × 前瞻每股淨值
A35: 12 個月後的前瞻 EPS（情境加權） | B35: =tp_wA*(8/12*B9+4/12*B10)+tp_wB*(8/12*C9+4/12*C10)+tp_wC*(8/12*D9+4/12*D10) -> 222.11497 | E35: 約 2027-10 時的未來 12 月（2027-11～2028-10）≈ 8／12 × FY2028（2027-07～2028-06）＋4／12 × FY2029（會計年度 6 月，依月份調整）
A37: 並列參考：同業前瞻 P/E（不進目標價）
A38: 同業與前瞻 P/E | B38: 代號 | C38: 前瞻 P/E | D38: 日期 | E38: 來源 | F38: 標記
A39: 美光 | B39: MU | C39: =877.55/173 -> 5.0725434 | D39: 2026-10-23 | E39: 現價 877.55 ÷ MarketScreener FY2027 共識 EPS 173（micron/ 模型 In 頁） | F39: Interested-party
A40: SK 海力士 | B40: 000660.KS | C40: =1277000/475721 -> 2.6843465 | D40: 2026-10-23 | E40: 現價 ÷ MarketScreener 2027 共識 EPS（skhynix/ 模型 In 頁） | F40: Interested-party
A41: 三星電子 | B41: 005930.KS | C41: =215500/72279 -> 2.9815022 | D41: 2026-10-23 | E41: 現價 ÷ MarketScreener 2027 共識 EPS（samsung/ 模型 In 頁） | F41: Interested-party
A42: Kioxia | B42: 285A.T | C42: =12755/3486 -> 3.6589214 | D42: 2026-10-23 | E42: 現價 ¥12,755 ÷ MarketScreener FY2027（2027-03）共識 EPS ¥3,486 | F42: Interested-party
A43: Western Digital | B43: WDC | C43: 11.91 | D43: 2026-10-23 | E43: stockanalysis 統計頁 Forward P/E（硬碟為主，參考） | F43: Interested-party
A44: 同業前瞻 P/E 中位數（並列參考） | B44: =MEDIAN(C39:C43) -> 3.6589214
A45: Comparable（P/E 並列參考）＝中位數 × 12 個月後前瞻 EPS | B45: =B44*B35 -> 812.70123 | E45: 不進目標價：高峰期 EPS × 低倍數，與 P/B 法互相對照
A47: 0.3 結論
A48: 項目 | B48: 數值 | E48: 說明
A49: 目標價（DCF 與 Comparable 加權） | B49: =tp_w_dcf*B24+(1-tp_w_dcf)*tp_comp_adj -> 930.35366 | E49: tp_w_dcf × DCF 目標價＋（1 − tp_w_dcf）× Comparable 目標價；tp_w_dcf 見 In 頁
A50: Comparable 目標價（市場主流同業法） | B50: =B34 -> 738.83607 | E50: 引用 0.2（前瞻 P/B）
A51: 市場共識目標價 | B51: =cons_tp -> 2144 | E51: stockanalysis（S&P Global，25 位，2026-10-18 更新）：平均 2,144（中位數 2,150；區間 1,000–3,600）
A52: 上檔空間：加權目標價 | B52: =B49/px-1 -> -0.2485209 | E52: 現價＝In 頁 px（2026-10-23 收盤）
A53: 上檔空間：Comparable 目標價 | B53: =B50/px-1 -> -0.40321635
A54: 上檔空間級距 | B54: =IF(B52>0.5,"大於 50%",IF(B52>0.25,"25%–50%",IF(B52>=0,"0%–25%",IF(B52>=-0.25,"0%～−25%",IF(B52>=-0.5,"−25%～−50%","小於 −50%"))))) -> 0%～−25% | E54: 以「上檔空間：加權目標價」分六級（Andy 2026-10-25 14:00）
A55: 投資建議 | B55: =IF(B52>0.5,"強力買進",IF(B52>0.25,"買進",IF(B52>=-0.25,"中立",IF(B52>=-0.5,"放空","強力放空")))) -> 中立 | E55: 依上檔空間固定規則（Andy 2026-10-25 14:17）：>+50% 強力買進、+25～+50% 買進、−25～+25% 中立、−50～−25% 放空、<−50% 強力放空
A56: DCF ÷ 現價 | B56: =B23/px -> 1.8042274 | C56: =C23/px -> 0.57230233 | D56: =D23/px -> 0.39377575 | E56: 各情境 DCF 價值（推到 12 個月後）÷ 現價（A／B／C）
A57: 與市場共識目標價的差距：EPS 因素（記憶體以每股淨值計） | B57: =B33/((cons_bv28+cons_bv29)/2)-1 -> -0.17709066 | E57: 本模型約 2028 年底每股淨值（情境加權）÷ 共識（FY2028、FY2029 年底平均 601.9）− 1（Comparable 用 P/B，故以每股淨值代 EPS）
A58: 對照：前瞻 EPS ÷ 共識前瞻 EPS − 1 | B58: =B35/(8/12*cons_eps28+4/12*cons_eps29)-1 -> -0.1843005 | E58: 共識前瞻 EPS＝8／12 × FY2028 267.6＋4／12 × FY2029 281.7（MarketScreener）
A59: 與市場共識目標價的差距：倍數因素 | B59: =(cons_tp/((cons_bv28+cons_bv29)/2))/B32-1 -> 1.387969 | E59: ="共識目標價隱含 P/B "&TEXT(cons_tp/((cons_bv28+cons_bv29)/2),"0.00")&"x（÷ 共識約 2028 年底每股淨值），同業中位數 "&TEXT(B32,"0.00")&"x" -> 共識目標價隱含 P/B 3.56x（÷ 共識約 2028 年底每股淨值），同業中位數 1.49x
A60: 價格帶（DCF 不如預期～順利） | B60: =TEXT(D23,"#,##0")&"～"&TEXT(B23,"#,##0") -> 488～2,234 | E60: C 情境價值～A 情境價值（推到 12 個月後）
A61: 歷史倍數檢查：現價隱含 P/B 的十年分位（A／B／C） | B61: =IF(px/PL!F15>=MAX($B$95:$B$104),1,IF(px/PL!F15<=MIN($B$95:$B$104),0,PERCENTRANK($B$95:$B$104,px/PL!F15))) -> 1 | C61: =IF(px/PL!F29>=MAX($B$95:$B$104),1,IF(px/PL!F29<=MIN($B$95:$B$104),0,PERCENTRANK($B$95:$B$104,px/PL!F29))) -> 1 | D61: =IF(px/PL!F43>=MAX($B$95:$B$104),1,IF(px/PL!F43<=MIN($B$95:$B$104),0,PERCENTRANK($B$95:$B$104,px/PL!F43))) -> 1 | E61: 現價 ÷ 各情境 FY2028 年底每股淨值，在 2016–2025 年底 P/B（第 6 節，美光 Analogy）分布的分位（高於最大值記 100%、低於最小值記 0%）；只作檢查，不進目標價（記憶體主估值為 P/B，故以 P/B 代 P/E）
A62: 目標價方法 | B62: DCF：股東現金流 FY2027–FY2029 用每股（淨利＋折舊－資本支出；資本支出含合資群分攤，約營收 6%），FY2030–FY2032 收斂期用 EPS ×（1 − g／ROE），r 10%、g 4%、ROE 為 FY2025–FY2026 平均；明確期＋永續，基準日 2026 年底。Comparable：美光、SK 海力士、三星、Kioxia 前瞻 P/B 中位數 × 約 2028 年底每股淨值（情境加權）；P/E 並列參考不進目標價。偏誤：FY2027–FY2029 為高峰期盈餘、收斂期淨利率以美光十年平均代替（SanDisk 無自身歷史）；大量買回壓低帳面淨值，P/B 法偏低估。
A80: 5. 目前倍數（僅供參考）
A81: 項目 | B81: A／數值 | C81: B | D81: C | E81: 備註
A82: 現價（2026-10-23 收盤） | B82: =px -> 1238.03 | E82: stockanalysis、MarketScreener
A83: P/E：現價 ÷ FY2026 EPS 73.76 | B83: =px/a26_eps -> 16.784572 | E83: 落後
A84: P/B：現價 ÷ FY2026 年底每股淨值 | B84: =px/PL!D97 -> 11.519595 | E84: FY2026 年底權益 15.736 ÷ 146.42 百萬股
A85: 現價 ÷ FY2027 EPS（模型） | B85: =px/PL!E14 -> 4.6953156 | C85: =px/PL!E28 -> 4.6386997 | D85: =px/PL!E42 -> 4.6816925 | E85: A／B／C
A86: 現價 ÷ FY2028 EPS（模型） | B86: =px/PL!F14 -> 3.6622067 | C86: =px/PL!F28 -> 5.7697919 | D86: =px/PL!F42 -> 6.5011068 | E86: A／B／C
A87: 現價 ÷ FY2028 年底每股淨值（模型） | B87: =px/PL!F15 -> 2.5258584 | C87: =px/PL!F29 -> 3.0164719 | D87: =px/PL!F43 -> 3.1515721 | E87: A／B／C；第 0 節歷史分位檢查用
A90: 6. 十年倍數與規則值（2016–2025 年底；見頂年 25 分位、中段中位數、谷底 75 分位）
A91: 規則（Andy 2026-10-13）：合理倍數＝2016–2025 年底倍數依循環位置取分位。SanDisk 無十年自身歷史，以美光為 Analogy（同為記憶體循環股；差異：美光 DRAM 為主）。見頂與中段用 FY2027 A、谷底用 FY2028 C。
A93: P/B（主）：十年歷史倍數
A94: 年底 | B94: 美光（Analogy；會計年度 8 月底） | C94: 標記／說明
A95: 2016 | B95: 1.29 | C95: 美光（Analogy；會計年度 8 月底）：Analogy
A96: 2017 | B96: 1.78 | C96: 來源：micron/dist/20261030_美光個股模型_v0.4.3.xlsx｜Val!B82:B91（macrotrends）；SanDisk 自身上市不足十年
A97: 2018 | B97: 1.79
A98: 2019 | B98: 1.33
A99: 2020 | B99: 1.27
A100: 2021 | B100: 1.83
A101: 2022 | B101: 1.22
A102: 2023 | B102: 1.72
A103: 2024 | B103: 2.35
A104: 2025 | B104: 2.46
A105: 25 分位（各來源） | B105: =PERCENTILE(B95:B104,0.25) -> 1.3
A106: 中位數（各來源） | B106: =MEDIAN(B95:B104) -> 1.75
A107: 75 分位（各來源） | B107: =PERCENTILE(B95:B104,0.75) -> 1.82
A108: 最小（各來源） | B108: =MIN(B95:B104) -> 1.22
A109: 最大（各來源） | B109: =MAX(B95:B104) -> 2.46
A110: 採用 25 分位（P/B） | B110: =ROUND(AVERAGE(B105),2) -> 1.3
A111: 採用 中位數（P/B） | B111: =ROUND(AVERAGE(B106),2) -> 1.75
A112: 採用 75 分位（P/B） | B112: =ROUND(AVERAGE(B107),2) -> 1.82
A113: 採用 最小（P/B） | B113: =ROUND(MIN(B108),2) -> 1.22
A114: 採用 最大（P/B） | B114: =ROUND(MAX(B109),2) -> 2.46
A116: P/B（主）：規則值
A117: 情形 | B117: 循環位置 | C117: 倍數 | D117: 基準 | E117: 每股基準 | F117: 隱含股價 | G117: 相對目前 | H117: 現價 ÷ 基準
A118: 規則值：見頂（P/B） | B118: 見頂年 → 25 分位 | C118: =B110 -> 1.3 | D118: FY2027 年底每股淨值（A） | E118: =PL!E97 -> 265.79415 | F118: =C118*E118 -> 345.5324 | G118: =F118/px-1 -> -0.72090143 | H118: =px/E118 -> 4.6578527
A119: 規則值：中段（P/B） | B119: 中段 → 中位數 | C119: =B111 -> 1.75 | D119: FY2027 年底每股淨值（A） | E119: =PL!E97 -> 265.79415 | F119: =C119*E119 -> 465.13977 | G119: =F119/px-1 -> -0.62429039 | H119: =px/E119 -> 4.6578527
A120: 規則值：谷底（P/B） | B120: 谷底 → 75 分位 | C120: =B112 -> 1.82 | D120: FY2028 年底每股淨值（C） | E120: =PL!F191 -> 392.82934 | F120: =C120*E120 -> 714.94941 | G120: =F120/px-1 -> -0.42251043 | H120: =px/E120 -> 3.1515721
A123: P/E（對照）：十年歷史倍數
A124: 年底 | B124: 美光（Analogy；SEC 10-K 換算） | C124: 標記／說明
A125: 2016 | C125: 美光（Analogy；SEC 10-K 換算）：Analogy
A126: 2017 | B126: 6.5131421 | C126: 來源：micron/dist/20261030_美光個股模型_v0.4.3.xlsx｜Val!B115:B124；虧損年不計
A127: 2018 | B127: 4.0895833
...

Sheet Recon
A1: Recon — 本模型 vs 公司實績、指引與共識（共識只作對照，未用於校準）。差距＝模型 ÷ 對照 − 1（百分點列為相減）
A3: 項目 | B3: 對照值 | C3: 模型 A | D3: 差距 A | E3: 模型 B | F3: 差距 B | G3: 模型 C | H3: 差距 C | I3: 對照來源 | J3: 說明
A4: A. 實績與公司指引
A5: FY2026 營收（實績重現） | B5: =a26_rev -> 20.248 | C5: =PL!D5 -> 20.248 | D5: =C5/B5-1 -> 0 | E5: =PL!D19 -> 20.248 | F5: =E5/B5-1 -> 0 | G5: =PL!D33 -> 20.248 | H5: =G5/B5-1 -> 0 | I5: SanDisk FQ4 FY26 新聞稿（8-K，2026-08-05） | J5: 恆等式
A6: FQ1 FY27 營收 vs 公司實績 | B6: =g_rev -> 11.031 | C6: =PL!G60 -> 11.030615 | D6: =C6/B6-1 -> -3.4905955e-05 | E6: =PL!G107 -> 11.030615 | F6: =E6/B6-1 -> -3.4905955e-05 | G6: =PL!G154 -> 11.030615 | H6: =G6/B6-1 -> -3.4905955e-05 | I6: SanDisk FQ4 FY26 新聞稿（8-K，2026-08-05） | J6: 恆等式（市場層份額由指引推得）
A7: FQ1 FY27 毛利率 vs 實績（百分點） | B7: =g_gm -> 0.8503 | C7: =PL!G69 -> 0.8503 | D7: =C7-B7 -> 0 | E7: =PL!G116 -> 0.8503 | F7: =E7-B7 -> 0 | G7: =PL!G163 -> 0.8503 | H7: =G7-B7 -> 0 | I7: SanDisk FQ4 FY26 新聞稿（8-K，2026-08-05） | J7: 恆等式（單位成本以此校準）
A8: FQ1 FY27 EPS vs 實績（non-GAAP 49.51） | B8: =g_eps -> 49.51 | C8: =PL!G74 -> 49.789486 | D8: =C8/B8-1 -> 0.005645041 | E8: =PL!G121 -> 49.789486 | F8: =E8/B8-1 -> 0.005645041 | G8: =PL!G168 -> 49.789486 | H8: =G8/B8-1 -> 0.005645041 | I8: SanDisk FQ4 FY26 新聞稿（8-K，2026-08-05） | J8: 本模型為 GAAP 營業費用＋15% 稅率，近似 non-GAAP（差約 SBC）
A9: B. 共識（MarketScreener 2026-10-23；只作參考）
A10: FY2027 營收 vs 共識 | B10: =cons_rev27 -> 49.135 | C10: =PL!E5 -> 51.713658 | D10: =C10/B10-1 -> 0.052481091 | E10: =PL!E19 -> 52.209851 | F10: =E10/B10-1 -> 0.062579639 | G10: =PL!E33 -> 51.862074 | H10: =G10/B10-1 -> 0.055501668 | I10: MarketScreener 預估頁（2026-10-25 擷取；頁面為 10-23 收盤；會計年度 6 月）
A11: FY2028 營收 vs 共識 | B11: =cons_rev28 -> 58.436 | C11: =PL!F5 -> 57.762315 | D11: =C11/B11-1 -> -0.011528597 | E11: =PL!F19 -> 40.996551 | F11: =E11/B11-1 -> -0.29843674 | G11: =PL!F33 -> 37.375241 | H11: =G11/B11-1 -> -0.36040726 | I11: MarketScreener 預估頁（2026-10-25 擷取；頁面為 10-23 收盤；會計年度 6 月）
A12: FY2027 EPS vs 共識 | B12: =cons_eps27 -> 217.4 | C12: =PL!E14 -> 263.67344 | D12: =C12/B12-1 -> 0.2128493 | E12: =PL!E28 -> 266.8916 | F12: =E12/B12-1 -> 0.22765228 | G12: =PL!E42 -> 264.44069 | H12: =G12/B12-1 -> 0.21637853 | I12: MarketScreener 預估頁（2026-10-25 擷取；頁面為 10-23 收盤；會計年度 6 月） | J12: 差距超過 30% 見 README
A13: FY2028 EPS vs 共識 | B13: =cons_eps28 -> 267.6 | C13: =PL!F14 -> 338.05574 | D13: =C13/B13-1 -> 0.26328751 | E13: =PL!F28 -> 214.571 | F13: =E13/B13-1 -> -0.19816519 | G13: =PL!F42 -> 190.43373 | H13: =G13/B13-1 -> -0.28836425 | I13: MarketScreener 預估頁（2026-10-25 擷取；頁面為 10-23 收盤；會計年度 6 月）
A14: FY2028 年底每股淨值 vs 共識 | B14: =cons_bv28 -> 553.1 | C14: =PL!F15 -> 490.14228 | D14: =C14/B14-1 -> -0.113827 | E14: =PL!F29 -> 410.42318 | F14: =E14/B14-1 -> -0.25795844 | G14: =PL!F43 -> 392.82934 | H14: =G14/B14-1 -> -0.28976795 | I14: MarketScreener 預估頁（2026-10-25 擷取；頁面為 10-23 收盤；會計年度 6 月）
A15: C. 市場層一致性
A16: SanDisk 營收 ÷ 市場層（公司口徑係數 sd_k） | C16: =sd_k -> 0.9994077 | I16: In 頁
A17: Kioxia＋SanDisk 合資群份額 CY2027（市場層 Ann 頁，A／B／C） | C17: 0.24502666 | E17: 0.24202666 | G17: 0.23902666 | I17: markets/nand/dist/20261031_NAND市場模型_v0.3.xlsx｜Ann!F27（kioxia/ 模型讀同一組列）

Sheet Sens
A1: Sens — 一次動一個輸入（情境 A）：對 FY2027、FY2028 營收與 EPS 的影響。每個案例為一個完整推導區塊（本頁下方，與 PL 同一引擎）
A3: 案例 | B3: 設定 | C3: FY2027 營收 $B | D3: FY2027 EPS | E3: 相對基準 | F3: FY2028 營收 $B | G3: FY2028 EPS | H3: 相對基準 | I3: FY2027 毛利率
A4: 基準（情境 A） | B4: PL 區塊 A | C4: =PL!E77 -> 51.713658 | D4: =PL!E96 -> 263.67344 | E4: =D4/D$4-1 -> 0 | F4: =PL!F77 -> 57.762315 | G4: =PL!F96 -> 338.05574 | H4: =G4/G$4-1 -> 0 | I4: =PL!E84 -> 0.86918603
A5: 市場層營收 −20%（價格；FQ2 FY27 起） | B5: 價格係數 0.8 | C5: =E81 -> 43.57705 | D5: =E100 -> 209.97206 | E5: =D5/D$4-1 -> -0.20366625 | F5: =F81 -> 46.209852 | G5: =F100 -> 245.06333 | H5: =G5/G$4-1 -> -0.2750801 | I5: =E88 -> 0.84476074
A6: 市場層營收 +20%（價格） | B6: 價格係數 1.2 | C6: =E131 -> 59.850267 | D6: =E150 -> 319.41833 | E6: =D6/D$4-1 -> 0.21141641 | F6: =F131 -> 69.314778 | G6: =F150 -> 441.08721 | H6: =G6/G$4-1 -> 0.30477657 | I6: =E138 -> 0.88697011
A7: 份額 ×0.9（營收與位元） | B7: 份額係數 0.9 | C7: =E181 -> 46.542293 | D7: =E200 -> 233.83486 | E7: =D7/D$4-1 -> -0.11316491 | F7: =F181 -> 51.986083 | G7: =F200 -> 295.61781 | H7: =G7/G$4-1 -> -0.12553529 | I7: =E188 -> 0.86918603
A8: 份額 ×1.1 | B8: 份額係數 1.1 | C8: =E231 -> 56.885024 | D8: =E250 -> 294.12569 | E8: =D8/D$4-1 -> 0.1154923 | F8: =F231 -> 63.538546 | G8: =F250 -> 382.6274 | H8: =G8/G$4-1 -> 0.13184707 | I8: =E238 -> 0.86918603
A9: 每位元成本年降 10%（C 的值） | B9: cd_C | C9: =E281 -> 51.713658 | D9: =E300 -> 262.86173 | E9: =D9/D$4-1 -> -0.0030784565 | F9: =F281 -> 57.762315 | G9: =F300 -> 334.19404 | H9: =G9/G$4-1 -> -0.01142327 | I9: =E288 -> 0.86688992
A10: 每位元成本年降 18% | B10: cd_A 高 | C10: =E331 -> 51.713658 | D10: =E350 -> 264.50141 | E10: =D10/D$4-1 -> 0.0031401489 | F10: =F331 -> 57.762315 | G10: =F350 -> 341.85736 | H10: =G10/G$4-1 -> 0.011245537 | I10: =E338 -> 0.87152674
A11: 校準毛利率 84.5% | B11: g_gm 低 | C11: =E381 -> 51.713658 | D11: =E400 -> 262.03668 | E11: =D11/D$4-1 -> -0.0062075311 | F11: =F381 -> 57.762315 | G11: =F400 -> 335.75831 | H11: =G11/G$4-1 -> -0.0067959936 | I11: =E388 -> 0.86455467
A12: 校準毛利率 85.5% | B12: g_gm 高 | C12: =E431 -> 51.713658 | D12: =E450 -> 265.12654 | E12: =D12/D$4-1 -> 0.0055110038 | F12: =F431 -> 57.762315 | G12: =F450 -> 340.0985 | H12: =G12/G$4-1 -> 0.0060426842 | I12: =E438 -> 0.87329308
A13: 營業費用變動率 2% | B13: ox_var 高 | C13: =E481 -> 51.713658 | D13: =E500 -> 263.26541 | E13: =D13/D$4-1 -> -0.0015474577 | F13: =F481 -> 57.762315 | G13: =F500 -> 337.40294 | H13: =G13/G$4-1 -> -0.0019310484 | I13: =E488 -> 0.86918603
A14: 稅率 20% | B14: tax 高 | C14: =E531 -> 51.713658 | D14: =E550 -> 246.6184 | E14: =D14/D$4-1 -> -0.06468242 | F14: =F531 -> 57.762315 | G14: =F550 -> 313.13277 | H14: =G14/G$4-1 -> -0.073724422 | I14: =E538 -> 0.86918603
A15: 稅率 12% | B15: tax 低 | C15: =E581 -> 51.713658 | D15: =E600 -> 274.00941 | E15: =D15/D$4-1 -> 0.039199887 | F15: =F581 -> 57.762315 | G15: =F600 -> 353.39574 | H15: =G15/G$4-1 -> 0.045377144 | I15: =E588 -> 0.86918603
A16: 買回 ÷ FCF 80% | B16: payout 高 | C16: =E631 -> 51.713658 | D16: =E650 -> 280.11889 | E16: =D16/D$4-1 -> 0.062370524 | F16: =F631 -> 57.762315 | G16: =F650 -> 389.69397 | H16: =G16/G$4-1 -> 0.15275065 | I16: =E638 -> 0.86918603
A17: 買回 ÷ FCF 30% | B17: payout 低 | C17: =E681 -> 51.713658 | D17: =E700 -> 253.74217 | E17: =D17/D$4-1 -> -0.037665036 | F17: =F681 -> 57.762315 | G17: =F700 -> 310.74733 | H17: =G17/G$4-1 -> -0.08078079 | I17: =E688 -> 0.86918603
A18: 情境 B | B18: markets/nand B；成本年降 12% | C18: =PL!E124 -> 52.209851 | D18: =PL!E143 -> 266.8916 | E18: =D18/D$4-1 -> 0.012205123 | F18: =PL!F124 -> 40.996551 | G18: =PL!F143 -> 214.571 | H18: =G18/G$4-1 -> -0.36527924 | I18: =PL!E131 -> 0.87008934
A19: 情境 C | B19: markets/nand C；成本年降 10% | C19: =PL!E171 -> 51.862074 | D19: =PL!E190 -> 264.44069 | E19: =D19/D$4-1 -> 0.0029098649 | F19: =PL!F171 -> 37.375241 | G19: =PL!F190 -> 190.43373 | H19: =G19/G$4-1 -> -0.4366795 | I19: =PL!E178 -> 0.86890965
A21: 讀法：FQ1 FY27 營收由市場層等於公司指引（恆等式），價格係數只作用在 FQ2 FY27 起；毛利率校準改變單位成本起點，之後每年依成本年降。
A60: 案例區塊：市場層營收 −20%（價格；FQ2 FY27 起）（情境 A）
A61: A. 季度 | B61: 單位 | C61: FQ1 FY26（2025Q3） | D61: FQ2 FY26（2025Q4） | E61: FQ3 FY26（2026Q1） | F61: FQ4 FY26（2026Q2） | G61: FQ1 FY27（2026Q3） | H61: FQ2 FY27（2026Q4） | I61: FQ3 FY27（2027Q1） | J61: FQ4 FY27（2027Q2） | K61: FQ1 FY28（2027Q3） | L61: FQ2 FY28（2027Q4） | M61: FQ3 FY28（2028Q1） | N61: FQ4 FY28（2028Q2） | O61: FQ1 FY29（2028Q3） | P61: FQ2 FY29（2028Q4） | Q61: FQ3 FY29（2029Q1） | R61: FQ4 FY29（2029Q2） | T61: 說明
A62: 市場層營收（TrendForce 口徑，同字母情境） | B62: $B | C62: =Units!E4*1 -> 2.31 | D62: =Units!F4*1 -> 3.03 | E62: =Units!G4*1 -> 5.95 | F62: =Units!H4*1 -> 8.97 | G62: =Units!I4*1 -> 11.037152 | H62: =Units!J4*1*0.8 -> 9.9681695 | I62: =Units!K4*1*0.8 -> 10.983703 | J62: =Units!L4*1*0.8 -> 11.613851 | K62: =Units!M4*1*0.8 -> 11.666145 | L62: =Units!N4*1*0.8 -> 11.471965 | M62: =Units!O4*1*0.8 -> 11.52362 | N62: =Units!P4*1*0.8 -> 11.575508 | O62: =Units!Q4*1*0.8 -> 11.627629 | ... R62: =Units!T4*1*0.8 -> 12.033254 | T62: markets/nand；Sens 可乘份額係數、價格係數（FQ2 FY27 起）
A63: 位元（市場層；同字母） | B63: EB | C63: =Units!E7*1 -> 31.15528 | D63: =Units!F7*1 -> 33.514723 | E63: =Units!G7*1 -> 38.069333 | F63: =Units!H7*1 -> 33.617215 | G63: =Units!I7*1 -> 33.091489 | H63: =Units!J7*1 -> 34.558829 | I63: =Units!K7*1 -> 36.970484 | J63: =Units!L7*1 -> 39.091528 | ... R63: =Units!T7*1 -> 59.81981
A64: 營收 | B64: $B | C64: =q1_rev -> 2.308 | D64: =q2_rev -> 3.025 | E64: =q3_rev -> 5.95 | F64: =q4_rev -> 8.965 | G64: =G62*sd_k -> 11.030615 | H64: =H62*sd_k -> 9.9622653 | I64: =I62*sd_k -> 10.977197 | J64: =J62*sd_k -> 11.606973 | K64: =K62*sd_k -> 11.659235 | L64: =L62*sd_k -> 11.465171 | M64: =M62*sd_k -> 11.516795 | N64: =N62*sd_k -> 11.568651 | ... R64: =R62*sd_k -> 12.026127 | T64: 實績季＝公司財報；之後＝市場層 × 公司口徑係數
A65: 資料中心 | B65: $B | C65: =q1_dc -> 0.269 | D65: =q2_dc -> 0.44 | E65: =q3_dc -> 1.467 | F65: =q4_dc -> 2.977 | G65: =G64*dcsh_27 -> 4.1916337 | H65: =H64*dcsh_27 -> 3.7856608 | I65: =I64*dcsh_27 -> 4.1713348 | J65: =J64*dcsh_27 -> 4.4106496 | K65: =K64*dcsh_28 -> 4.8968788 | L65: =L64*dcsh_28 -> 4.8153716 | M65: =M64*dcsh_28 -> 4.8370538 | N65: =N64*dcsh_28 -> 4.8588336 | O65: =O64*dcsh_29 -> 5.2293337 | P65: =P64*dcsh_29 -> 5.2528798 | Q65: =Q64*dcsh_29 -> 5.3085586 | R65: =R64*dcsh_29 -> 5.4117572 | T65: 官方分部；實績季＝10-Q／10-K；之後＝營收 × 資料中心占比（In）
A66: 資料中心：AI 相關（＝資料中心 × AI 企業級 SSD 占比） | B66: $B | C66: =C65*(Units!C16+Units!D16)/2 -> 0.17543406 | D66: =D65*(Units!C16+Units!D16)/2 -> 0.28695533 | E66: =E65*(Units!C16+Units!D16)/2 -> 0.95673517 | F66: =F65*(Units!C16+Units!D16)/2 -> 1.9415137 | G66: =G65*(Units!D16+Units!E16)/2 -> 3.323531 | H66: =H65*(Units!D16+Units!E16)/2 -> 3.0016366 | I66: =I65*(Units!D16+Units!E16)/2 -> 3.3074361 | J66: =J65*(Units!D16+Units!E16)/2 -> 3.4971879 | K66: =K65*(Units!E16+Units!F16)/2 -> 4.1293081 | L66: =L65*(Units!E16+Units!F16)/2 -> 4.0605769 | M66: =M65*(Units!E16+Units!F16)/2 -> 4.0788605 | N66: =N65*(Units!E16+Units!F16)/2 -> 4.0972264 | O66: =O65*(Units!F16+Units!G16)/2 -> 4.5242058 | P66: =P65*(Units!F16+Units!G16)/2 -> 4.5445769 | Q66: =Q65*(Units!F16+Units!G16)/2 -> 4.5927479 | R66: =R65*(Units!F16+Units!G16)/2 -> 4.6820312 | T66: 命題子列（Derived）：會計年度 ≈ 前後兩個日曆年平均；假設 SanDisk 資料中心組合與產業企業級 SSD 相同
A67: 資料中心：非 AI | B67: $B | C67: =C65-C66 -> 0.093565943 | D67: =D65-D66 -> 0.15304467 | E67: =E65-E66 -> 0.51026483 | F67: =F65-F66 -> 1.0354863 | G67: =G65-G66 -> 0.86810269 | H67: =H65-H66 -> 0.78402423 | I67: =I65-I66 -> 0.86389873 | J67: =J65-J66 -> 0.91346169 | ... R67: =R65-R66 -> 0.72972605
A68: 消費 | B68: $B | C68: =q1_cs -> 0.652 | D68: =q2_cs -> 0.907 | E68: =q3_cs -> 0.82 | F68: =q4_cs -> 0.556 | G68: =G64*cssh_27 -> 0.6618369 | H68: =H64*cssh_27 -> 0.59773592 | I68: =I64*cssh_27 -> 0.65863181 | J68: =J64*cssh_27 -> 0.69641835 | K68: =K64*cssh_28 -> 0.69955412 | L68: =L64*cssh_28 -> 0.68791023 | M68: =M64*cssh_28 -> 0.69100768 | N68: =N64*cssh_28 -> 0.69411908 | O68: =O64*cssh_29 -> 0.69724449 | P68: =P64*cssh_29 -> 0.70038398 | Q68: =Q64*cssh_29 -> 0.70780781 | R68: =R64*cssh_29 -> 0.72156763 | T68: 官方分部
A69: 邊緣 | B69: $B | C69: =q1_ed -> 1.387 | D69: =q2_ed -> 1.678 | E69: =q3_ed -> 3.663 | F69: =q4_ed -> 5.432 | G69: =G64-G65-G68 -> 6.1771444 | H69: =H64-H65-H68 -> 5.5788686 | I69: =I64-I65-I68 -> 6.1472303 | J69: =J64-J65-J68 -> 6.4999046 | K69: =K64-K65-K68 -> 6.0628023 | L69: =L64-L65-L68 -> 5.9618887 | M69: =M64-M65-M68 -> 5.9887333 | N69: =N64-N65-N68 -> 6.0156987 | ... R69: =R64-R65-R68 -> 5.8928023 | T69: 官方分部；預測季＝營收 − 資料中心 − 消費
A70: 檢查：分部合計 − 營收（季） | B70: $B | C70: =C65+C69+C68-C64 -> 0 | D70: =D65+D69+D68-D64 -> 0 | E70: =E65+E69+E68-E64 -> 0 | F70: =F65+F69+F68-F64 -> 0 | G70: =G65+G69+G68-G64 -> 0 | H70: =H65+H69+H68-H64 -> 0 | I70: =I65+I69+I68-I64 -> 0 | J70: =J65+J69+J68-J64 -> 0 | ... R70: =R65+R69+R68-R64 -> 0
A71: 每 EB 營業成本（FQ1 FY27 以實績毛利率校準，之後每年 × (1 − 成本年降)） | B71: $B/EB | C71: =C72/C63 -> 0.052004539 | D71: =D72/D63 -> 0.04431709 | E71: =E72/E63 -> 0.033759457 | F71: =F72/F63 -> 0.041068541 | G71: =(1-g_gm)*G64/G63 -> 0.049900536 | H71: =$G71*(1-cd_A)^(1/4) -> 0.048054031 | I71: =$G71*(1-cd_A)^(2/4) -> 0.046275853 | J71: =$G71*(1-cd_A)^(3/4) -> 0.044563475 | K71: =$G71*(1-cd_A)^(4/4) -> 0.042914461 | L71: =$G71*(1-cd_A)^(5/4) -> 0.041326467 | M71: =$G71*(1-cd_A)^(6/4) -> 0.039797234 | N71: =$G71*(1-cd_A)^(7/4) -> 0.038324588 | O71: =$G71*(1-cd_A)^(8/4) -> 0.036906436 | P71: =$G71*(1-cd_A)^(9/4) -> 0.035540761 | Q71: =$G71*(1-cd_A)^(10/4) -> 0.034225621 | R71: =$G71*(1-cd_A)^(11/4) -> 0.032959146
A72: 營業成本 | B72: $B | C72: =q1_rev*(1-q1_gm) -> 1.620216 | D72: =q2_rev*(1-q2_gm) -> 1.485275 | E72: =q3_rev*(1-q3_gm) -> 1.2852 | F72: =q4_rev*(1-q4_gm) -> 1.38061 | G72: =G63*G71 -> 1.6512831 | H72: =H63*H71 -> 1.660691 | I72: =I63*I71 -> 1.7108407 | J72: =J63*J71 -> 1.7420543 | K72: =K63*K71 -> 1.7738374 | L72: =L63*L71 -> 1.8062004 | M72: =M63*M71 -> 1.8391538 | N72: =N63*N71 -> 1.8727084 | ... R72: =R63*R71 -> 1.9716099
A73: 毛利率 | B73: % | C73: =1-C72/C64 -> 0.298 | D73: =1-D72/D64 -> 0.509 | E73: =1-E72/E64 -> 0.784 | F73: =1-F72/F64 -> 0.846 | G73: =1-G72/G64 -> 0.8503 | H73: =1-H72/H64 -> 0.83330187 | I73: =1-I72/I64 -> 0.84414594 | J73: =1-J72/J64 -> 0.84991312 | ... R73: =1-R72/R64 -> 0.83605613
A74: 營業費用 | B74: $B | C74: =q1_rev-q1_rev*(1-q1_gm)-q1_op -> 0.511784 | D74: =q2_rev-q2_rev*(1-q2_gm)-q2_op -> 0.474725 | E74: =q3_rev-q3_rev*(1-q3_gm)-q3_op -> 0.5538 | F74: =q4_rev-q4_rev*(1-q4_gm)-q4_op -> 0.54739 | G74: =(g_ox-ox_var*g_rev)*(1+ox_g)^(0/4)+ox_var*G64 -> 0.58199615 | H74: =(g_ox-ox_var*g_rev)*(1+ox_g)^(1/4)+ox_var*H64 -> 0.58268684 | I74: =(g_ox-ox_var*g_rev)*(1+ox_g)^(2/4)+ox_var*I64 -> 0.60448461 | J74: =(g_ox-ox_var*g_rev)*(1+ox_g)^(3/4)+ox_var*J64 -> 0.62271172 | K74: =(g_ox-ox_var*g_rev)*(1+ox_g)^(4/4)+ox_var*K64 -> 0.63545135 | L74: =(g_ox-ox_var*g_rev)*(1+ox_g)^(5/4)+ox_var*L64 -> 0.64602231 | M74: =(g_ox-ox_var*g_rev)*(1+ox_g)^(6/4)+ox_var*M64 -> 0.65935186 | N74: =(g_ox-ox_var*g_rev)*(1+ox_g)^(7/4)+ox_var*N64 -> 0.67299271 | O74: =(g_ox-ox_var*g_rev)*(1+ox_g)^(8/4)+ox_var*O64 -> 0.68695232 | P74: =(g_ox-ox_var*g_rev)*(1+ox_g)^(9/4)+ox_var*P64 -> 0.70123833 | Q74: =(g_ox-ox_var*g_rev)*(1+ox_g)^(10/4)+ox_var*Q64 -> 0.71657027 | R74: =(g_ox-ox_var*g_rev)*(1+ox_g)^(11/4)+ox_var*R64 -> 0.73329808 | T74: 固定部分以 FQ1 FY27 營業費用（實績推估）校準（Derived）
A75: 營業利益 | B75: $B | C75: =C64-C72-C74 -> 0.176 | D75: =D64-D72-D74 -> 1.065 | E75: =E64-E72-E74 -> 4.111 | F75: =F64-F72-F74 -> 7.037 | G75: =G64-G72-G74 -> 8.7973357 | H75: =H64-H72-H74 -> 7.7188875 | I75: =I64-I72-I74 -> 8.6618716 | J75: =J64-J72-J74 -> 9.2422065 | ... R75: =R64-R72-R74 -> 9.3212192
A77: 淨利 | B77: $B | C77: =q1_ni -> 0.112 | D77: =q2_ni -> 0.803 | E77: =q3_ni -> 3.615 | F77: =q4_ni -> 6.903 | G77: =(G75+rf*$D98/4)*(1-tax) -> 7.5182124 | H77: =(H75+rf*$D98/4)*(1-tax) -> 6.6015313 | I77: =(I75+rf*$D98/4)*(1-tax) -> 7.4030678 | J77: =(J75+rf*$D98/4)*(1-tax) -> 7.8963525 | K77: =(K75+rf*$E98/4)*(1-tax) -> 8.0175308 | L77: =(L75+rf*$E98/4)*(1-tax) -> 7.816082 | M77: =(M75+rf*$E98/4)*(1-tax) -> 7.8206221 | N77: =(N75+rf*$E98/4)*(1-tax) -> 7.8245841 | O77: =(O75+rf*$F98/4)*(1-tax) -> 7.9506347 | P77: =(P75+rf*$F98/4)*(1-tax) -> 7.953396 | Q77: =(Q75+rf*$F98/4)*(1-tax) -> 8.0400838 | R77: =(R75+rf*$F98/4)*(1-tax) -> 8.2007941 | T77: （營業利益＋上一年底淨現金 × 收益率 ÷ 4）×（1 − 稅率）
A78: 季 EPS（稀釋） | B78: USD | G78: =G77/(sh0+dil)*1000 -> 49.789486 | H78: =H77/(sh0+dil)*1000 -> 43.718751 | I78: =I77/(sh0+dil)*1000 -> 49.026939 | J78: =J77/(sh0+dil)*1000 -> 52.293725 | K78: =K77/(sh0+dil)*1000 -> 53.096231 | L78: =L77/(sh0+dil)*1000 -> 51.762132 | M78: =M77/(sh0+dil)*1000 -> 51.792199 | N78: =N77/(sh0+dil)*1000 -> 51.818438 | ... R78: =R77/(sh0+dil)*1000 -> 54.309895
A80: B. 年度（會計年度） | B80: 單位 | C80: FY2025A | D80: FY2026A | E80: FY2027 | F80: FY2028 | G80: FY2029 | T80: 說明
A81: 營收 | B81: $B | C81: =a25_rev -> 7.355 | D81: =SUM(C64:F64) -> 20.248 | E81: =SUM(G64:J64) -> 43.57705 | F81: =SUM(K64:N64) -> 46.209852 | G81: =SUM(O64:R64) -> 47.116732
A82: 營收：資料中心 | B82: $B | D82: =SUM(C65:F65) -> 5.153 | E82: =SUM(G65:J65) -> 16.559279 | F82: =SUM(K65:N65) -> 19.408138 | G82: =SUM(O65:R65) -> 21.202529
A83: 資料中心：AI 相關 | B83: $B | D83: =SUM(C66:F66) -> 3.3606383 | E83: =SUM(G66:J66) -> 13.129792 | F83: =SUM(K66:N66) -> 16.365972 | G83: =SUM(O66:R66) -> 18.343562
A84: 營收：邊緣 | B84: $B | D84: =SUM(C69:F69) -> 12.16 | E84: =SUM(G69:J69) -> 24.403148 | F84: =SUM(K69:N69) -> 24.029123 | G84: =SUM(O69:R69) -> 23.087199
A85: 營收：消費 | B85: $B | D85: =SUM(C68:F68) -> 2.935 | E85: =SUM(G68:J68) -> 2.614623 | F85: =SUM(K68:N68) -> 2.7725911 | G85: =SUM(O68:R68) -> 2.8270039
A86: 檢查：分部合計 − 合併營收（年；FY2026 另比 10-K 分部） | B86: $B | D86: =D82+D84+D85-D81+ABS(D82-a26_dc)+ABS(D84-a26_ed)+ABS(D85-a26_cs) -> 0 | E86: =E82+E84+E85-E81 -> 0 | F86: =F82+F84+F85-F81 -> 0 | G86: =G82+G84+G85-G81 -> 0
A87: 營業成本 | B87: $B | D87: =SUM(C72:F72) -> 5.771301 | E87: =SUM(G72:J72) -> 6.7648691 | F87: =SUM(K72:N72) -> 7.2918999 | G87: =SUM(O72:R72) -> 7.7682288
A88: 毛利率 | B88: % | D88: =1-D87/D81 -> 0.71496933 | E88: =1-E87/E81 -> 0.84476074 | F88: =1-F87/F81 -> 0.84220032 | G88: =1-G87/G81 -> 0.83512802
A89: 營業費用 | B89: $B | D89: =SUM(C74:F74) -> 2.087699 | E89: =SUM(G74:J74) -> 2.3918793 | F89: =SUM(K74:N74) -> 2.6138182 | G89: =SUM(O74:R74) -> 2.838059
A90: 營業利益 | B90: $B | D90: =SUM(C75:F75) -> 12.389 | E90: =SUM(G75:J75) -> 34.420301 | F90: =SUM(K75:N75) -> 36.304134 | G90: =SUM(O75:R75) -> 36.510444
A91: 營業利益率 | B91: % | D91: =D90/D81 -> 0.6118629 | E91: =E90/E81 -> 0.78987223 | F91: =F90/F81 -> 0.78563623 | G91: =G90/G81 -> 0.77489339
A92: 淨利 | B92: $B | C92: =a25_ni -> -1.641 | D92: =SUM(C77:F77) -> 11.433 | E92: =SUM(G77:J77) -> 29.419164 | F92: =SUM(K77:N77) -> 31.478819 | G92: =SUM(O77:R77) -> 32.144909
A93: 折舊攤銷（公司本身） | B93: $B | D93: =da_y -> 0.16 | E93: =da_y -> 0.16 | F93: =da_y -> 0.16 | G93: =da_y -> 0.16
A94: 資本支出（含合資群分攤） | B94: $B | D94: 0.562 | E94: =cap_r*E81 -> 2.614623 | F94: =cap_r*F81 -> 2.7725911 | G94: =cap_r*G81 -> 2.8270039 | T94: FY2026 毛資本支出 0.562（公司簡報；markets/equipment In 頁）
A95: 自由現金流（淨利＋折舊 − 資本支出） | B95: $B | D95: =D92+D93-D94 -> 11.031 | E95: =E92+E93-E94 -> 26.964541 | F95: =F92+F93-F94 -> 28.866228 | G95: =G92+G93-G94 -> 29.477905
A96: 買回 | B96: $B | D96: 4.524 | E96: =MAX(0,payout*E95) -> 13.482271 | F96: =MAX(0,payout*F95) -> 14.433114 | G96: =MAX(0,payout*G95) -> 14.738952 | T96: FY2026 實績 4.524（FQ4）
A97: 期末權益 | B97: $B | D97: =eq0 -> 15.736 | E97: =D97+E92-E96 -> 31.672894 | F97: =E97+F92-F96 -> 48.718599 | G97: =F97+G92-G96 -> 66.124555
A98: 期末淨現金 | B98: $B | D98: =nc0 -> 4.762 | E98: =D98+E95-E96 -> 18.244271 | F98: =E98+F95-F96 -> 32.677384 | G98: =F98+G95-G96 -> 47.416337
A99: 期末流通股數 | B99: 百萬股 | D99: =sh0 -> 146.42 | E99: =D99-E96/bb_px*1000 -> 135.5299 | F99: =E99-F96/bb_px*1000 -> 123.87177 | G99: =F99-G96/bb_px*1000 -> 111.9666
A100: EPS（稀釋：期末流通股數＋dil） | B100: USD | C100: =a25_eps -> -11.32 | D100: =a26_eps -> 73.76 | E100: =E92/(E99+dil)*1000 -> 209.97206 | F100: =F92/(F99+dil)*1000 -> 245.06333 | G100: =G92/(G99+dil)*1000 -> 275.81163
A101: 每股淨值 BVPS（期末流通股數） | B101: USD | D101: =D97/D99*1000 -> 107.47166 | E101: =E97/E99*1000 -> 233.69672 | F101: =F97/F99*1000 -> 393.29864 | G101: =G97/G99*1000 -> 590.5739
A102: ROE（期末權益） | B102: % | D102: =D92/D97 -> 0.72655058 | E102: =E92/E97 -> 0.92884359 | F102: =F92/F97 -> 0.64613556 | G102: =G92/G97 -> 0.48612665
A103: 每股自由現金流（稀釋） | B103: USD | E103: =E95/(E99+dil)*1000 -> 192.45279 | F103: =F95/(F99+dil)*1000 -> 224.72425 | G103: =G95/(G99+dil)*1000 -> 252.92804
A104: 檢查：FY2026 營收、淨利 − 實績（應為 0） | B104: $B | D104: =ABS(D81-a26_rev)+ABS(D92-a26_ni) -> 0
A110: 案例區塊：市場層營收 +20%（價格）（情境 A）
A111: A. 季度 | B111: 單位 | C111: FQ1 FY26（2025Q3） | D111: FQ2 FY26（2025Q4） | E111: FQ3 FY26（2026Q1） | F111: FQ4 FY26（2026Q2） | G111: FQ1 FY27（2026Q3） | H111: FQ2 FY27（2026Q4） | I111: FQ3 FY27（2027Q1） | J111: FQ4 FY27（2027Q2） | K111: FQ1 FY28（2027Q3） | L111: FQ2 FY28（2027Q4） | M111: FQ3 FY28（2028Q1） | N111: FQ4 FY28（2028Q2） | O111: FQ1 FY29（2028Q3） | P111: FQ2 FY29（2028Q4） | Q111: FQ3 FY29（2029Q1） | R111: FQ4 FY29（2029Q2） | T111: 說明
A112: 市場層營收（TrendForce 口徑，同字母情境） | B112: $B | C112: =Units!E4*1 -> 2.31 | D112: =Units!F4*1 -> 3.03 | E112: =Units!G4*1 -> 5.95 | F112: =Units!H4*1 -> 8.97 | G112: =Units!I4*1 -> 11.037152 | H112: =Units!J4*1*1.2 -> 14.952254 | I112: =Units!K4*1*1.2 -> 16.475554 | J112: =Units!L4*1*1.2 -> 17.420777 | K112: =Units!M4*1*1.2 -> 17.499218 | L112: =Units!N4*1*1.2 -> 17.207948 | M112: =Units!O4*1*1.2 -> 17.28543 | N112: =Units!P4*1*1.2 -> 17.363261 | O112: =Units!Q4*1*1.2 -> 17.441443 | ... R112: =Units!T4*1*1.2 -> 18.049882 | T112: markets/nand；Sens 可乘份額係數、價格係數（FQ2 FY27 起）
A113: 位元（市場層；同字母） | B113: EB | C113: =Units!E7*1 -> 31.15528 | D113: =Units!F7*1 -> 33.514723 | E113: =Units!G7*1 -> 38.069333 | F113: =Units!H7*1 -> 33.617215 | G113: =Units!I7*1 -> 33.091489 | H113: =Units!J7*1 -> 34.558829 | I113: =Units!K7*1 -> 36.970484 | J113: =Units!L7*1 -> 39.091528 | ... R113: =Units!T7*1 -> 59.81981
A114: 營收 | B114: $B | C114: =q1_rev -> 2.308 | D114: =q2_rev -> 3.025 | E114: =q3_rev -> 5.95 | F114: =q4_rev -> 8.965 | G114: =G112*sd_k -> 11.030615 | H114: =H112*sd_k -> 14.943398 | I114: =I112*sd_k -> 16.465795 | J114: =J112*sd_k -> 17.410459 | K114: =K112*sd_k -> 17.488853 | L114: =L112*sd_k -> 17.197756 | M114: =M112*sd_k -> 17.275192 | N114: =N112*sd_k -> 17.352977 | ... R114: =R112*sd_k -> 18.039191 | T114: 實績季＝公司財報；之後＝市場層 × 公司口徑係數
A115: 資料中心 | B115: $B | C115: =q1_dc -> 0.269 | D115: =q2_dc -> 0.44 | E115: =q3_dc -> 1.467 | F115: =q4_dc -> 2.977 | G115: =G114*dcsh_27 -> 4.1916337 | H115: =H114*dcsh_27 -> 5.6784912 | I115: =I114*dcsh_27 -> 6.2570022 | J115: =J114*dcsh_27 -> 6.6159744 | K115: =K114*dcsh_28 -> 7.3453182 | L115: =L114*dcsh_28 -> 7.2230574 | M115: =M114*dcsh_28 -> 7.2555807 | N115: =N114*dcsh_28 -> 7.2882504 | O115: =O114*dcsh_29 -> 7.8440006 | P115: =P114*dcsh_29 -> 7.8793198 | Q115: =Q114*dcsh_29 -> 7.9628378 | R115: =R114*dcsh_29 -> 8.1176358 | T115: 官方分部；實績季＝10-Q／10-K；之後＝營收 × 資料中心占比（In）
A116: 資料中心：AI 相關（＝資料中心 × AI 企業級 SSD 占比） | B116: $B | C116: =C115*(Units!C16+Units!D16)/2 -> 0.17543406 | D116: =D115*(Units!C16+Units!D16)/2 -> 0.28695533 | E116: =E115*(Units!C16+Units!D16)/2 -> 0.95673517 | F116: =F115*(Units!C16+Units!D16)/2 -> 1.9415137 | G116: =G115*(Units!D16+Units!E16)/2 -> 3.323531 | H116: =H115*(Units!D16+Units!E16)/2 -> 4.5024549 | I116: =I115*(Units!D16+Units!E16)/2 -> 4.9611541 | J116: =J115*(Units!D16+Units!E16)/2 -> 5.2457818 | K116: =K115*(Units!E16+Units!F16)/2 -> 6.1939622 | L116: =L115*(Units!E16+Units!F16)/2 -> 6.0908654 | M116: =M115*(Units!E16+Units!F16)/2 -> 6.1182908 | N116: =N115*(Units!E16+Units!F16)/2 -> 6.1458396 | O116: =O115*(Units!F16+Units!G16)/2 -> 6.7863087 | P116: =P115*(Units!F16+Units!G16)/2 -> 6.8168654 | Q116: =Q115*(Units!F16+Units!G16)/2 -> 6.8891219 | R116: =R115*(Units!F16+Units!G16)/2 -> 7.0230467 | T116: 命題子列（Derived）：會計年度 ≈ 前後兩個日曆年平均；假設 SanDisk 資料中心組合與產業企業級 SSD 相同
A117: 資料中心：非 AI | B117: $B | C117: =C115-C116 -> 0.093565943 | D117: =D115-D116 -> 0.15304467 | E117: =E115-E116 -> 0.51026483 | F117: =F115-F116 -> 1.0354863 | G117: =G115-G116 -> 0.86810269 | H117: =H115-H116 -> 1.1760363 | I117: =I115-I116 -> 1.2958481 | J117: =J115-J116 -> 1.3701925 | ... R117: =R115-R116 -> 1.0945891
A118: 消費 | B118: $B | C118: =q1_cs -> 0.652 | D118: =q2_cs -> 0.907 | E118: =q3_cs -> 0.82 | F118: =q4_cs -> 0.556 | G118: =G114*cssh_27 -> 0.6618369 | H118: =H114*cssh_27 -> 0.89660388 | I118: =I114*cssh_27 -> 0.98794772 | J118: =J114*cssh_27 -> 1.0446275 | K118: =K114*cssh_28 -> 1.0493312 | L118: =L114*cssh_28 -> 1.0318653 | M118: =M114*cssh_28 -> 1.0365115 | N118: =N114*cssh_28 -> 1.0411786 | O118: =O114*cssh_29 -> 1.0458667 | P118: =P114*cssh_29 -> 1.050576 | Q118: =Q114*cssh_29 -> 1.0617117 | R118: =R114*cssh_29 -> 1.0823514 | T118: 官方分部
A119: 邊緣 | B119: $B | C119: =q1_ed -> 1.387 | D119: =q2_ed -> 1.678 | E119: =q3_ed -> 3.663 | F119: =q4_ed -> 5.432 | G119: =G114-G115-G118 -> 6.1771444 | H119: =H114-H115-H118 -> 8.3683029 | I119: =I114-I115-I118 -> 9.2208454 | J119: =J114-J115-J118 -> 9.7498569 | K119: =K114-K115-K118 -> 9.0942035 | L119: =L114-L115-L118 -> 8.942833 | M119: =M114-M115-M118 -> 8.9830999 | N119: =N114-N115-N118 -> 9.0235481 | ... R119: =R114-R115-R118 -> 8.8392035 | T119: 官方分部；預測季＝營收 − 資料中心 − 消費
A120: 檢查：分部合計 − 營收（季） | B120: $B | C120: =C115+C119+C118-C114 -> 0 | D120: =D115+D119+D118-D114 -> 0 | E120: =E115+E119+E118-E114 -> 0 | F120: =F115+F119+F118-F114 -> 0 | G120: =G115+G119+G118-G114 -> 0 | H120: =H115+H119+H118-H114 -> 0 | I120: =I115+I119+I118-I114 -> 0 | J120: =J115+J119+J118-J114 -> 0 | ... R120: =R115+R119+R118-R114 -> 0
A121: 每 EB 營業成本（FQ1 FY27 以實績毛利率校準，之後每年 × (1 − 成本年降)） | B121: $B/EB | C121: =C122/C113 -> 0.052004539 | D121: =D122/D113 -> 0.04431709 | E121: =E122/E113 -> 0.033759457 | F121: =F122/F113 -> 0.041068541 | G121: =(1-g_gm)*G114/G113 -> 0.049900536 | H121: =$G121*(1-cd_A)^(1/4) -> 0.048054031 | I121: =$G121*(1-cd_A)^(2/4) -> 0.046275853 | J121: =$G121*(1-cd_A)^(3/4) -> 0.044563475 | K121: =$G121*(1-cd_A)^(4/4) -> 0.042914461 | L121: =$G121*(1-cd_A)^(5/4) -> 0.041326467 | M121: =$G121*(1-cd_A)^(6/4) -> 0.039797234 | N121: =$G121*(1-cd_A)^(7/4) -> 0.038324588 | O121: =$G121*(1-cd_A)^(8/4) -> 0.036906436 | P121: =$G121*(1-cd_A)^(9/4) -> 0.035540761 | Q121: =$G121*(1-cd_A)^(10/4) -> 0.034225621 | R121: =$G121*(1-cd_A)^(11/4) -> 0.032959146
A122: 營業成本 | B122: $B | C122: =q1_rev*(1-q1_gm) -> 1.620216 | D122: =q2_rev*(1-q2_gm) -> 1.485275 | E122: =q3_rev*(1-q3_gm) -> 1.2852 | F122: =q4_rev*(1-q4_gm) -> 1.38061 | G122: =G113*G121 -> 1.6512831 | H122: =H113*H121 -> 1.660691 | I122: =I113*I121 -> 1.7108407 | J122: =J113*J121 -> 1.7420543 | K122: =K113*K121 -> 1.7738374 | L122: =L113*L121 -> 1.8062004 | M122: =M113*M121 -> 1.8391538 | N122: =N113*N121 -> 1.8727084 | ... R122: =R113*R121 -> 1.9716099
A123: 毛利率 | B123: % | C123: =1-C122/C114 -> 0.298 | D123: =1-D122/D114 -> 0.509 | E123: =1-E122/E114 -> 0.784 | F123: =1-F122/F114 -> 0.846 | G123: =1-G122/G114 -> 0.8503 | H123: =1-H122/H114 -> 0.88886791 | I123: =1-I122/I114 -> 0.89609729 | J123: =1-J122/J114 -> 0.89994208 | ... R123: =1-R122/R114 -> 0.89070408
A124: 營業費用 | B124: $B | C124: =q1_rev-q1_rev*(1-q1_gm)-q1_op -> 0.511784 | D124: =q2_rev-q2_rev*(1-q2_gm)-q2_op -> 0.474725 | E124: =q3_rev-q3_rev*(1-q3_gm)-q3_op -> 0.5538 | F124: =q4_rev-q4_rev*(1-q4_gm)-q4_op -> 0.54739 | G124: =(g_ox-ox_var*g_rev)*(1+ox_g)^(0/4)+ox_var*G114 -> 0.58199615 | H124: =(g_ox-ox_var*g_rev)*(1+ox_g)^(1/4)+ox_var*H114 -> 0.63249817 | I124: =(g_ox-ox_var*g_rev)*(1+ox_g)^(2/4)+ox_var*I114 -> 0.6593706 | J124: =(g_ox-ox_var*g_rev)*(1+ox_g)^(3/4)+ox_var*J114 -> 0.68074658 | K124: =(g_ox-ox_var*g_rev)*(1+ox_g)^(4/4)+ox_var*K114 -> 0.69374753 | L124: =(g_ox-ox_var*g_rev)*(1+ox_g)^(5/4)+ox_var*L114 -> 0.70334816 | M124: =(g_ox-ox_var*g_rev)*(1+ox_g)^(6/4)+ox_var*M114 -> 0.71693583 | N124: =(g_ox-ox_var*g_rev)*(1+ox_g)^(7/4)+ox_var*N114 -> 0.73083596 | O124: =(g_ox-ox_var*g_rev)*(1+ox_g)^(8/4)+ox_var*O114 -> 0.74505602 | P124: =(g_ox-ox_var*g_rev)*(1+ox_g)^(9/4)+ox_var*P114 -> 0.75960366 | Q124: =(g_ox-ox_var*g_rev)*(1+ox_g)^(10/4)+ox_var*Q114 -> 0.77555425 | R124: =(g_ox-ox_var*g_rev)*(1+ox_g)^(11/4)+ox_var*R114 -> 0.79342872 | T124: 固定部分以 FQ1 FY27 營業費用（實績推估）校準（Derived）
A125: 營業利益 | B125: $B | C125: =C114-C122-C124 -> 0.176 | D125: =D114-D122-D124 -> 1.065 | E125: =E114-E122-E124 -> 4.111 | F125: =F114-F122-F124 -> 7.037 | G125: =G114-G122-G124 -> 8.7973357 | H125: =H114-H122-H124 -> 12.650209 | I125: =I114-I122-I124 -> 14.095584 | J125: =J114-J122-J124 -> 14.987658 | ... R125: =R114-R122-R124 -> 15.274152
A127: 淨利 | B127: $B | C127: =q1_ni -> 0.112 | D127: =q2_ni -> 0.803 | E127: =q3_ni -> 3.615 | F127: =q4_ni -> 6.903 | G127: =(G125+rf*$D148/4)*(1-tax) -> 7.5182124 | H127: =(H125+rf*$D148/4)*(1-tax) -> 10.793154 | I127: =(I125+rf*$D148/4)*(1-tax) -> 12.021723 | J127: =(J125+rf*$D148/4)*(1-tax) -> 12.779986 | K127: =(K125+rf*$E148/4)*(1-tax) -> 12.977204 | L127: =(L125+rf*$E148/4)*(1-tax) -> 12.694102 | M127: =(M125+rf*$E148/4)*(1-tax) -> 12.720363 | N127: =(N125+rf*$E148/4)*(1-tax) -> 12.746144 | O127: =(O125+rf*$F148/4)*(1-tax) -> 12.97177 | P127: =(P125+rf*$F148/4)*(1-tax) -> 12.996547 | Q127: =(Q125+rf*$F148/4)*(1-tax) -> 13.135294 | R127: =(R125+rf*$F148/4)*(1-tax) -> 13.392496 | T127: （營業利益＋上一年底淨現金 × 收益率 ÷ 4）×（1 − 稅率）
A128: 季 EPS（稀釋） | B128: USD | G128: =G127/(sh0+dil)*1000 -> 49.789486 | H128: =H127/(sh0+dil)*1000 -> 71.477844 | I128: =I127/(sh0+dil)*1000 -> 79.614063 | J128: =J127/(sh0+dil)*1000 -> 84.635671 | K128: =K127/(sh0+dil)*1000 -> 85.941745 | L128: =L127/(sh0+dil)*1000 -> 84.0669 | M128: =M127/(sh0+dil)*1000 -> 84.240814 | N128: =N127/(sh0+dil)*1000 -> 84.411547 | ... R128: =R127/(sh0+dil)*1000 -> 88.692023
A130: B. 年度（會計年度） | B130: 單位 | C130: FY2025A | D130: FY2026A | E130: FY2027 | F130: FY2028 | G130: FY2029 | T130: 說明
A131: 營收 | B131: $B | C131: =a25_rev -> 7.355 | D131: =SUM(C114:F114) -> 20.248 | E131: =SUM(G114:J114) -> 59.850267 | F131: =SUM(K114:N114) -> 69.314778 | G131: =SUM(O114:R114) -> 70.675098
A132: 營收：資料中心 | B132: $B | D132: =SUM(C115:F115) -> 5.153 | E132: =SUM(G115:J115) -> 22.743101 | F132: =SUM(K115:N115) -> 29.112207 | G132: =SUM(O115:R115) -> 31.803794
A133: 資料中心：AI 相關 | B133: $B | D133: =SUM(C116:F116) -> 3.3606383 | E133: =SUM(G116:J116) -> 18.032922 | F133: =SUM(K116:N116) -> 24.548958 | G133: =SUM(O116:R116) -> 27.515343
A134: 營收：邊緣 | B134: $B | D134: =SUM(C119:F119) -> 12.16 | E134: =SUM(G119:J119) -> 33.51615 | F134: =SUM(K119:N119) -> 36.043685 | G134: =SUM(O119:R119) -> 34.630798
A135: 營收：消費 | B135: $B | D135: =SUM(C118:F118) -> 2.935 | E135: =SUM(G118:J118) -> 3.591016 | F135: =SUM(K118:N118) -> 4.1588867 | G135: =SUM(O118:R118) -> 4.2405059
A136: 檢查：分部合計 − 合併營收（年；FY2026 另比 10-K 分部） | B136: $B | D136: =D132+D134+D135-D131+ABS(D132-a26_dc)+ABS(D134-a26_ed)+ABS(D135-a26_cs) -> 0 | E136: =E132+E134+E135-E131 -> 0 | F136: =F132+F134+F135-F131 -> 0 | G136: =G132+G134+G135-G131 -> 0
A137: 營業成本 | B137: $B | D137: =SUM(C122:F122) -> 5.771301 | E137: =SUM(G122:J122) -> 6.7648691 | F137: =SUM(K122:N122) -> 7.2918999 | G137: =SUM(O122:R122) -> 7.7682288
A138: 毛利率 | B138: % | D138: =1-D137/D131 -> 0.71496933 | E138: =1-E137/E131 -> 0.88697011 | F138: =1-F137/F131 -> 0.89480021 | G138: =1-G137/G131 -> 0.89008535
A139: 營業費用 | B139: $B | D139: =SUM(C124:F124) -> 2.087699 | E139: =SUM(G124:J124) -> 2.5546115 | F139: =SUM(K124:N124) -> 2.8448675 | G139: =SUM(O124:R124) -> 3.0736427
A140: 營業利益 | B140: $B | D140: =SUM(C125:F125) -> 12.389 | E140: =SUM(G125:J125) -> 50.530787 | F140: =SUM(K125:N125) -> 59.178011 | G140: =SUM(O125:R125) -> 59.833226
A141: 營業利益率 | B141: % | D141: =D140/D131 -> 0.6118629 | E141: =E140/E131 -> 0.84428673 | F141: =F140/F131 -> 0.85375749 | G141: =G140/G131 -> 0.84659559
A142: 淨利 | B142: $B | C142: =a25_ni -> -1.641 | D142: =SUM(C127:F127) -> 11.433 | E142: =SUM(G127:J127) -> 43.113077 | F142: =SUM(K127:N127) -> 51.137812 | G142: =SUM(O127:R127) -> 52.496107
A143: 折舊攤銷（公司本身） | B143: $B | D143: =da_y -> 0.16 | E143: =da_y -> 0.16 | F143: =da_y -> 0.16 | G143: =da_y -> 0.16
A144: 資本支出（含合資群分攤） | B144: $B | D144: 0.562 | E144: =cap_r*E131 -> 3.591016 | F144: =cap_r*F131 -> 4.1588867 | G144: =cap_r*G131 -> 4.2405059 | T144: FY2026 毛資本支出 0.562（公司簡報；markets/equipment In 頁）
A145: 自由現金流（淨利＋折舊 − 資本支出） | B145: $B | D145: =D142+D143-D144 -> 11.031 | E145: =E142+E143-E144 -> 39.682061 | F145: =F142+F143-F144 -> 47.138925 | G145: =G142+G143-G144 -> 48.415601
A146: 買回 | B146: $B | D146: 4.524 | E146: =MAX(0,payout*E145) -> 19.84103 | F146: =MAX(0,payout*F145) -> 23.569463 | G146: =MAX(0,payout*G145) -> 24.207801 | T146: FY2026 實績 4.524（FQ4）
A147: 期末權益 | B147: $B | D147: =eq0 -> 15.736 | E147: =D147+E142-E146 -> 39.008046 | F147: =E147+F142-F146 -> 66.576396 | G147: =F147+G142-G146 -> 94.864702
A148: 期末淨現金 | B148: $B | D148: =nc0 -> 4.762 | E148: =D148+E145-E146 -> 24.60303 | F148: =E148+F145-F146 -> 48.172493 | G148: =F148+G145-G146 -> 72.380294
A149: 期末流通股數 | B149: 百萬股 | D149: =sh0 -> 146.42 | E149: =D149-E146/bb_px*1000 -> 130.39371 | F149: =E149-F146/bb_px*1000 -> 111.35583 | G149: =F149-G146/bb_px*1000 -> 91.802347
...

Sheet Sources
A1: 來源
A2: SanDisk FQ4 FY26 新聞稿（8-K，2026-08-05） | B2: https://www.sec.gov/Archives/edgar/data/0002023554/000162828026053346/sndkq4-26ex991xpressrelease.htm
A3: SanDisk FQ2 FY26 新聞稿（8-K，2026-01-29） | B3: https://www.sec.gov/Archives/edgar/data/2023554/000162828026004121/sndkq2fy26ex991-pressrelea.htm
A4: SanDisk：FQ1 FY27 財報日 2026-10-29（2026-09-29 公告） | B4: https://investor.sandisk.com/news-releases/news-release-details/sandisk-report-first-quarter-fiscal-year-2027-results-october-29
A5: stockanalysis：歷史股價、統計、共識目標價 | B5: https://stockanalysis.com/stocks/sndk/forecast/
A6: MarketScreener：SanDisk 預估（EPS、每股淨值、股數） | B6: https://uk.marketscreener.com/quote/stock/SANDISK-CORPORATION-182801077/finances/
A7: MarketScreener：Kioxia 預估（同業 P/B、P/E） | B7: https://uk.marketscreener.com/quote/stock/KIOXIA-HOLDINGS-CORPORATI-180030735/finances/
A8: stockanalysis：WDC 統計（Forward P/E） | B8: https://stockanalysis.com/stocks/wdc/statistics/
A9: Motley Fool：SanDisk／Kioxia 日本投資、FY27 毛資本支出約營收 6%（2026-08-29） | B9: https://www.fool.com/investing/2026/08/29/sandisk-and-kioxia-plan-to-invest-more-than-usd31-billion-in-japanese-memory-plants-about-60-of-what-they-have-spent-there-in-25-years/
A10: 市場層：markets/nand/dist/20261031_NAND市場模型_v0.3.xlsx（markets/nand v0.1） | B10: 本 repo
A11: 美光十年倍數與淨利率（Analogy）：micron/dist/20261030_美光個股模型_v0.4.3.xlsx | B11: 本 repo
A12: SemiAnalysis | B12: 未使用
