Workbook

Sheet README
A1: Applied Materials（AMAT）收支與估值模型 v0.2（AI 半導體 Project 步驟 5：設備與材料） 2026-10-25
A2: 模型命題：AMAT 的營收約四分之三來自半導體系統，跟著晶圓廠設備支出走；成長集中在先進代工邏輯、DRAM／HBM 與先進封裝，中國約占三成。股價取決於 2028 年設備支出會不會見頂，以及出口管制會不會再收緊。
A4: 會計年度：約 11 月到隔年 10 月底（52／53 週；FY2026＝2025-10-27～2026-10-25）。FY(t) 有 10/12 落在日曆年 t：日曆年轉會計年度用 FY(t)＝2/12×CY(t−1)＋10/12×CY(t)；循環位置把 FY(t) 直接對照日曆年 t。FY2026 已結束但第四季尚未公布（預定 2026-11-12），本版 FY2026＝前三季實績＋第四季公司指引（錨點）。金額為百萬美元；EPS 為 non-GAAP 稀釋（與指引、共識同口徑）。
A6: 驅動因子 → 推導量
A7: 半導體系統＝FY2026 錨點 × Σ（FY2026 終端市場權重 × 各終端市場設備支出的會計年度指數）× 份額係數。設備支出讀 markets/equipment 的三情境（晶圓代工邏輯＝先進邏輯＋其他代工邏輯＋其他前段；DRAM 含 HBM；NAND）。
A8: AGS 服務、其他（含顯示器）：前一年 × 成長率（A 取公司長期 mid-teens）。出口管制：情境 C 假設 BIS 關係企業規則在暫停期（至 2026-11-09）後恢復，每年少 US$600M（公司 2025-09 估計）。
A9: 毛利率：營業成本＝固定＋變動 × 營收；營業費用＝固定＋變動 × 營收（兩者都用 FY2025 實績與 FY2026 錨點兩點推導）；淨利＝營業利益 × FY2025 的 non-GAAP 淨利 ÷ 營業利益。不寫死利益率。
A10: Val：P/E 規則——10 年（2016–2025 年底）non-GAAP P/E 分位，見頂年 25 分位、中段中位數、谷底 75 分位；循環位置依設備股共用規則（各情境見頂年度讀設備市場模型：A 2029、B 2028、C 2027 → FY2027：A 中段、B 中段、C 見頂）。本版未做先驗，無 Andy 合理 P/E 對照。Recon：共識、第四季年化、SEMI、公司說法。Sens：份額、終端權重、會計年度權重、成本與費用的固定／變動拆分、AGS、出口管制、中國
A12: 標記：Verified、Interested-party、Analogy、Assumed、Derived。SemiAnalysis 未使用。
A13: 已知限制：(1) 半導體系統只用終端市場設備指數 × 份額係數，份額變化（環繞式閘極、背面供電、先進封裝、中國國產替代）只在 Sens；(2) FY2025 Q4 的重編分部由 FY2026 Q4 指引年增率（整數百分比）反推；(3) 毛利率與營業費用只有兩點；(4) 第四季終端市場組合、股數為 Assumed；(5) 中國約三成營收，出口管制只以單一金額（公司 2025-09 估計）建模；(6) 設備市場模型 2026 年以後高於 SEMI 約 7–10%，本模型只用成長指數；(7) FY2028 共識未找到。
A14: v0.2（2026-10-25）估值 v2：Val 頁新增「0. 目標價」（放在既有內容之後，不位移既有列）＝0.5 × DCF 目標價（股東現金流＝EPS ×（1 − g／ROE），FY2027–32 明確期＋永續，r 10%、g 4%，情境權重 A 0.3／B 0.5／C 0.2）＋0.5 × Comparable 目標價（同業前瞻 P/E 中位數 × 12 個月後前瞻 EPS）；另列 Comparable 單獨目標價、市場共識目標價與差距拆解、歷史分位檢查。原「0. 目標價與上檔空間」改名「舊法：規則值情境加權（參考）」，不再叫目標價。
A15: 預估期間延伸到 FY2032：FY2027–FY2029 由驅動因子推導；FY2030 起為收斂法，非驅動因子推導（PL 頁底部延伸區塊，灰底）。情境對應：A＝順利、B＝平平、C＝不如預期（原為顆數情境）。本版未做先驗，無 Andy 合理 P/E 對照。

Sheet In
A1: In — 輸入（藍字；基準欄 E，低 D、高 F）。金額：百萬美元（US$M），市場為十億美元（US$B）。每個輸入附兩個來源（來源2 找不到者寫「未找到」）；公司原文算一個
A2: 標記：Verified／Interested-party／Analogy／Assumed／Derived；Analogy、Assumed 給低／高區間。SemiAnalysis 未使用。公司新聞稿與 SEC 8-K 附件以網頁擷取工具讀取（同一份文件的兩個轉載不算兩個獨立來源）
A3: 鍵 | B3: 項目 | C3: 單位 | D3: 低 | E3: 基準 | F3: 高 | G3: 標記 | H3: 來源1 | I3: 來源2／說明
A4: A. 晶圓廠設備市場（日曆年，US$B；讀 markets/equipment 成品，三情境；唯讀，不自行重估）
A5: laA_25 | B5: 先進邏輯設備 CY2025（A） | C5: US$B | E5: 36.032336 | G5: Derived | H5: markets/equipment/dist/20261023_半導體設備市場模型_v0.1.3.xlsx｜Mkt!C120:G120 | I5: markets/equipment Mkt 第 5 節（公司資本支出 × 設備占比，2025 以 SEMI 實績校準）；2028–29 隨情境係數
A6: laA_26 | B6: 先進邏輯設備 CY2026（A） | C6: US$B | E6: 50.324843 | G6: Derived | H6: 同上
A7: laA_27 | B7: 先進邏輯設備 CY2027（A） | C7: US$B | E7: 60.776431 | G7: Derived | H7: 同上
A8: laA_28 | B8: 先進邏輯設備 CY2028（A） | C8: US$B | E8: 70.016145 | G8: Derived | H8: 同上
A9: laA_29 | B9: 先進邏輯設備 CY2029（A） | C9: US$B | E9: 74.209437 | G9: Derived | H9: 同上
A10: loA_25 | B10: 其他代工與邏輯設備 CY2025（A） | C10: US$B | E10: 29.569009 | G10: Derived | H10: markets/equipment/dist/20261023_半導體設備市場模型_v0.1.3.xlsx｜Mkt!C121:G121
A11: loA_26 | B11: 其他代工與邏輯設備 CY2026（A） | C11: US$B | E11: 31.93453 | G11: Derived | H11: 同上
A12: loA_27 | B12: 其他代工與邏輯設備 CY2027（A） | C12: US$B | E12: 34.489292 | G12: Derived | H12: 同上
A13: loA_28 | B13: 其他代工與邏輯設備 CY2028（A） | C13: US$B | E13: 37.248436 | G13: Derived | H13: 同上
A14: loA_29 | B14: 其他代工與邏輯設備 CY2029（A） | C14: US$B | E14: 40.228311 | G14: Derived | H14: 同上
A15: ofA_25 | B15: 其他前段設備（類比、功率、光罩、廠務等） CY2025（A） | C15: US$B | E15: 12.746775 | G15: Derived | H15: markets/equipment/dist/20261023_半導體設備市場模型_v0.1.3.xlsx｜Mkt!C124:G124
A16: ofA_26 | B16: 其他前段設備（類比、功率、光罩、廠務等） CY2026（A） | C16: US$B | E16: 17.027825 | G16: Derived | H16: 同上
A17: ofA_27 | B17: 其他前段設備（類比、功率、光罩、廠務等） CY2027（A） | C17: US$B | E17: 21.022986 | G17: Derived | H17: 同上
... A79: ndC_29 | B79: NAND 設備 CY2029（C） | C79: US$B | E79: 18.598422 | G79: Derived | H79: 同上
A80: fyw | B80: 會計年度落在前一個日曆年的比例（FY(t)＝fyw×CY(t−1)＋(1−fyw)×CY(t)） | C80: % | D80: 0.083333333 | E80: 0.16666667 | F80: 0.25 | G80: Derived | H80: 公司會計年度結束於 10 月最後一個星期日（FY2026：2025-10-27～2026-10-25），約 11–12 月兩個月落在前一年 → 2/12 | I80: 低 1/12、高 3/12（Assumed）：設備出貨與客戶資本支出約差一季，高值等於把市場往前移一季
A81: semi_wfe26 | B81: SEMI 晶圓前段設備（WFE） CY2026（對帳用） | C81: US$B | E81: 143.9 | G81: Interested-party | H81: markets/equipment/dist/20261023_半導體設備市場模型_v0.1.3.xlsx｜Mkt!C44:G44 | I81: SEMI 2026-07 年中預測（設備商協會，傾向樂觀）；只用於 Recon
A82: semi_fl26 | B82: SEMI 代工與邏輯設備 CY2026（對帳用） | C82: US$B | E82: 78 | G82: Interested-party | H82: markets/equipment/dist/20261023_半導體設備市場模型_v0.1.3.xlsx｜Mkt!C43:G43 | I82: SEMI 2026-07 年中預測（設備商協會，傾向樂觀）；只用於 Recon
A83: semi_dr26 | B83: SEMI DRAM 設備 CY2026（對帳用） | C83: US$B | E83: 38.8 | G83: Interested-party | H83: markets/equipment/dist/20261023_半導體設備市場模型_v0.1.3.xlsx｜Mkt!C41:G41 | I83: SEMI 2026-07 年中預測（設備商協會，傾向樂觀）；只用於 Recon
A84: semi_nd26 | B84: SEMI NAND 設備 CY2026（對帳用） | C84: US$B | E84: 13.9 | G84: Interested-party | H84: markets/equipment/dist/20261023_半導體設備市場模型_v0.1.3.xlsx｜Mkt!C42:G42 | I84: SEMI 2026-07 年中預測（設備商協會，傾向樂觀）；只用於 Recon
A85: ai_inc27 | B85: 設備市場模型：AI 相關設備占 2025→2027 增量（情境 A） | C85: % | E85: 0.62686064 | G85: Derived | H85: markets/equipment/dist/20261023_半導體設備市場模型_v0.1.3.xlsx｜Mkt!C10:G10（情境 A） | I85: 先進邏輯＋DRAM／HBM＋先進封裝；只用於 Recon
A86: co_ai27 | B86: 公司說法：先進代工邏輯、DRAM、先進封裝占 CY2026–27 晶圓廠設備成長約 80% | C86: % | E86: 0.8 | G86: Interested-party | H86: AMAT Q3 FY26 法說（2026-08-13；MarketBeat 法說重點） | I86: Nasdaq 法說重點（可能同一來源轉載）；只用於 Recon
A87: B. 半導體系統（Semiconductor Systems）：FY2026 錨點 × 各終端市場設備指數 × 份額係數
A88: q4_dr | B88: FY2026 第四季半導體系統中 DRAM 占比（公司未給） | C88: % | D88: 0.26 | E88: 0.3 | F88: 0.34 | G88: Assumed | H88: 公司：DRAM 營收 2H CY2026「very significant increase」（Q3 FY26 法說，MarketBeat）；Q3 26%、Q1 34% | I88: 低＝Q3 的 26%、高＝Q1 的 34%
A89: q4_nd | B89: FY2026 第四季半導體系統中 NAND（Flash）占比 | C89: % | D89: 0.04 | E89: 0.06 | F89: 0.08 | G89: Assumed | H89: Q1 4%、Q2 4%、Q3 7%（公司新聞稿） | I89: —
A90: m_dr | B90: FY2026 半導體系統 DRAM 權重（前三季實績＋第四季假設，金額加權） | C90: % | D90: =(SUMPRODUCT(Q!G19:I19,Q!G4:I4)+q4_dr_lo*Q!J4)/an_ss -> 0.28266106 | E90: =(SUMPRODUCT(Q!G19:I19,Q!G4:I4)+q4_dr*Q!J4)/an_ss -> 0.29479344 | F90: =(SUMPRODUCT(Q!G19:I19,Q!G4:I4)+q4_dr_hi*Q!J4)/an_ss -> 0.30692582 | G90: Derived | H90: Q 頁：各季營收 × 終端市場占比 | I90: 低／高對應 q4_dr 低／高
A91: m_nd | B91: FY2026 半導體系統 NAND 權重 | C91: % | E91: =(SUMPRODUCT(Q!G20:I20,Q!G4:I4)+q4_nd*Q!J4)/an_ss -> 0.054174921 | G91: Derived | H91: 同上 | I91: —
A92: m_fl | B92: FY2026 半導體系統 晶圓代工、邏輯與其他 權重（＝1 − DRAM − NAND） | C92: % | D92: =1-m_dr_lo-m_nd -> 0.66316402 | E92: =1-m_dr-m_nd -> 0.65103164 | F92: =1-m_dr_hi-m_nd -> 0.63889926 | G92: Derived | H92: 同上；公司「Foundry, logic and other」含 ICAPS（成熟製程、功率、類比等），故對應設備市場的先進邏輯＋其他代工邏輯＋其他前段 | I92: 低／高與 m_dr 對沖
A93: sf | B93: 份額係數（FY2027 起 AMAT 半導體系統營收 ÷ 依市場指數推得的營收） | C93: x | D93: 0.95 | E93: 1 | F93: 1.05 | G93: Assumed | H93: 無：基準假設 AMAT 在三個終端市場的份額維持 FY2026 水準 | I93: 上方＝環繞式閘極、背面供電、先進封裝的份額提升；下方＝中國國產替代、競爭（Lam、TEL、KLA）
A94: C. 出口管制與中國
A95: aff_hit | B95: BIS「關係企業規則」恢復時的年營收影響 | C95: US$M | D95: 300 | E95: 600 | F95: 900 | G95: Interested-party | H95: AMAT 8-K（2025-09-29）：該規則將使 FY2026 營收減少約 US$600M（Q4 FY25 約 US$110M） | I95: Reuters（Yahoo Finance 2025-11-14）：規則暫停後約 US$600M 營收可恢復；Skadden：暫停至 2026-11-09，除非 BIS 延長。低／高 Assumed（±50%）
A96: aff_A | B96: 情境 A：關係企業規則於 FY2027 起恢復（1＝是） | C96: 0/1 | E96: 0 | G96: Assumed | H96: 暫停期至 2026-11-09（Skadden 2025-11）；是否延長未知 | I96: A、B 假設延長；C 假設恢復（與設備市場下修同向的保守組合）
A97: aff_B | B97: 情境 B：關係企業規則於 FY2027 起恢復（1＝是） | C97: 0/1 | E97: 0 | G97: Assumed | H97: 同上 | I97: A、B 假設延長；C 假設恢復（與設備市場下修同向的保守組合）
A98: aff_C | B98: 情境 C：關係企業規則於 FY2027 起恢復（1＝是） | C98: 0/1 | E98: 1 | G98: Assumed | H98: 同上 | I98: A、B 假設延長；C 假設恢復（與設備市場下修同向的保守組合）
A99: cn_sh | B99: 中國占營收（FY2026 前三季，Derived） | C99: % | E99: =SUM(Q!G21:I21)/SUM(Q!G7:I7) -> 0.27823772 | G99: Derived | H99: Q 頁：前三季中國營收 ÷ 營收（公司新聞稿；Q3 為 28%） | I99: 公司：Q3 中國占半導體系統＋AGS 的 26%；預期 CY2026 中國營收增加（28nm 代工邏輯帶動）
A100: cn_cut | B100: 敏感度：中國營收下修比例（國產替代或新管制） | C100: % | D100: 0 | E100: 0 | F100: 0.4 | G100: Assumed | H100: 無；基準 0（市場層的「其他代工邏輯」已含中國擴產的成長假設） | I100: Sens 用高值 20%、40%（只對半導體系統＋AGS）
A101: D. AGS 服務與其他（含顯示器）：前一年 × 成長率
A102: g_ags_A | B102: AGS FY2027–29 年成長（A） | C102: % | D102: 0.11 | E102: 0.15 | F102: 0.19 | G102: Interested-party | H102: AMAT Q3 FY26 法說：AGS 長期年成長 mid-teens；CY2026 >20%（MarketBeat、Nasdaq 法說重點） | I102: 區間 ±4 個百分點（Assumed）
A103: g_ags_B | B103: AGS FY2027–29 年成長（B） | C103: % | D103: 0.07 | E103: 0.11 | F103: 0.15 | G103: Assumed | H103: 無：裝機量與稼動隨設備市場放緩（B／C 為 Assumed） | I103: 區間 ±4 個百分點（Assumed）
A104: g_ags_C | B104: AGS FY2027–29 年成長（C） | C104: % | D104: 0.03 | E104: 0.07 | F104: 0.11 | G104: Assumed | H104: 無：裝機量與稼動隨設備市場放緩（B／C 為 Assumed） | I104: 區間 ±4 個百分點（Assumed）
A105: g_oth_A | B105: 其他（主要為顯示器）FY2027–29 年成長（A） | C105: % | D105: -0.1 | E105: 0 | F105: 0.1 | G105: Assumed | H105: 無：顯示器設備隨面板廠投資起伏；Q4 FY26 指引約 US$510M 高於前三季（280–312） | I105: FY2026 為 1.4% 營收以下的小項；區間 ±10 個百分點
A106: g_oth_B | B106: 其他（主要為顯示器）FY2027–29 年成長（B） | C106: % | D106: -0.15 | E106: -0.05 | F106: 0.05 | G106: Assumed | H106: 無：顯示器設備隨面板廠投資起伏；Q4 FY26 指引約 US$510M 高於前三季（280–312） | I106: FY2026 為 1.4% 營收以下的小項；區間 ±10 個百分點
A107: g_oth_C | B107: 其他（主要為顯示器）FY2027–29 年成長（C） | C107: % | D107: -0.2 | E107: -0.1 | F107: 0 | G107: Assumed | H107: 無：顯示器設備隨面板廠投資起伏；Q4 FY26 指引約 US$510M 高於前三季（280–312） | I107: FY2026 為 1.4% 營收以下的小項；區間 ±10 個百分點
A108: E. 毛利、營業費用、淨利、股數（兩點推導：FY2025 實績與 FY2026 錨點；non-GAAP；不寫死利益率）
A109: cogs25 | B109: 營業成本 FY2025（營收 − non-GAAP 毛利） | C109: US$M | E109: =a25_rev-a25_gp -> 14529.148 | G109: Derived | H109: Q 頁 | I109: —
A110: cogs26 | B110: 營業成本 FY2026 錨點 | C110: US$M | E110: =an_rev-an_gp -> 17129.148 | G110: Derived | H110: Q 頁（前三季實績＋第四季指引毛利率 50.4%） | I110: —
A111: cv | B111: 營業成本變動部分占營收（兩點斜率） | C111: % | E111: =(cogs26-cogs25)/(an_rev-a25_rev) -> 0.43926339 | G111: Derived | H111: （FY2026 − FY2025 營業成本）÷ 營收差 | I111: 隱含毛利率隨營收上升而遞增、但趨緩
A112: cF | B112: 營業成本固定部分 | C112: US$M | E112: =cogs25-cv*a25_rev -> 2068.1242 | G112: Derived | H112: FY2025 營業成本 − 變動部分 | I112: —
A113: phic | B113: 營業成本中變動部分占比（FY2025；Sens 用） | C113: % | D113: 0.75 | E113: =cv*a25_rev/cogs25 -> 0.85765689 | F113: 0.95 | G113: Derived | H113: 基準＝兩點推導值；低／高 Assumed | I113: 低＝固定成本較多（營收增加時毛利率升得更快）
A114: opex25 | B114: 營業費用 FY2025（non-GAAP 毛利 − non-GAAP 營業利益） | C114: US$M | E114: =a25_gp-a25_oi -> 5276.852 | G114: Derived | H114: Q 頁 | I114: —
A115: opex26 | B115: 營業費用 FY2026 錨點（前三季＋第四季指引 US$1,580M） | C115: US$M | E115: =an_opx -> 5832.852 | G115: Derived | H115: Q 頁 | I115: 公司：FY2027 Q1 為 14 週，營業費用增幅大於往常（Q3 FY26 法說）
A116: ov | B116: 營業費用變動部分占營收（兩點斜率） | C116: % | E116: =(opex26-opex25)/(an_rev-a25_rev) -> 0.093934786 | G116: Derived | H116: （FY2026 − FY2025 營業費用）÷ 營收差 | I116: —
A117: oF | B117: 營業費用固定部分 | C117: US$M | E117: =opex25-ov*a25_rev -> 2612.11 | G117: Derived | H117: FY2025 營業費用 − 變動部分 | I117: —
A118: phi | B118: 營業費用中變動部分占比（FY2025；Sens 用） | C118: % | D118: 0.35 | E118: =ov*a25_rev/opex25 -> 0.50498707 | F118: 0.75 | G118: Derived | H118: 基準＝兩點推導值；低／高 Assumed | I118: 公司：產能 2028 年前倍增、Q3 增聘逾 1,500 人（費用前置的風險）
A119: nioi | B119: non-GAAP 淨利 ÷ non-GAAP 營業利益 | C119: x | D119: 0.85 | E119: =a25_ni/a25_oi -> 0.88846064 | F119: =an_ni/an_oi -> 0.89888918 | G119: Derived | H119: 基準＝FY2025 實績 0.888；高＝FY2026 錨點隱含（含公司內部無形資產移轉的稅務利益，Q1／Q2 指引各 US$0.04／股） | I119: 低 0.85（Assumed：全球最低稅負等稅率上升）
A120: sh_q4 | B120: FY2026 第四季稀釋股數（公司未給） | C120: 百萬股 | D120: 793 | E120: 796 | F120: 800 | G120: Assumed | H120: Q3 稀釋 800M；10-Q 封面流通股 793.6M（2026-07-26）；Q3 回購 US$440M | I120: 只影響 FY2026 錨點淨利（＝第四季指引 EPS × 股數）
A121: bb | B121: FY2027 起稀釋股數年減幅（淨回購） | C121: % | D121: 0 | E121: 0.01 | F121: 0.025 | G121: Assumed | H121: FY2025 稀釋股數 808M → FY2026 前三季 799M（約 −1.1%）；回購授權餘額 US$12.8B（Q3 FY26 法說） | I121: —
A122: F. 公司指引、共識、股價、循環位置
A123: g_rev_q4 | B123: 指引營收 FY2026 第四季（中點，±US$500M） | C123: US$M | D123: 9750 | E123: 10250 | F123: 10750 | G123: Interested-party | H123: AMAT Q3 FY26 新聞稿（2026-08-13） | I123: MarketBeat 法說重點；低／高＝公司指引區間（未進 Sens：錨點只影響 FY2026 水準）
A124: g_eps_q4 | B124: 指引 non-GAAP 稀釋 EPS FY2026 第四季（中點，±US$0.20） | C124: US$ | D124: 3.82 | E124: 4.02 | F124: 4.22 | G124: Interested-party | H124: 同上 | I124: 同上（低／高＝指引區間，未進 Sens）
A125: g_ss_q4 | B125: 指引 半導體系統 FY2026 第四季（約，年增 62%） | C125: US$M | E125: 7900 | G125: Interested-party | H125: AMAT Q3 FY26 法說（MarketBeat） | I125: Nasdaq 法說重點（可能同源）
A126: g_ags_q4 | B126: 指引 AGS FY2026 第四季（約，年增 22%） | C126: US$M | E126: 1840 | G126: Interested-party | H126: 同上 | I126: 同上
A127: g_oth_q4 | B127: 指引 其他（主要為顯示器）FY2026 第四季（約） | C127: US$M | E127: 510 | G127: Interested-party | H127: 同上 | I127: 同上
A128: g_gm_q4 | B128: 指引 non-GAAP 毛利率 FY2026 第四季 | C128: % | E128: 0.504 | G128: Interested-party | H128: 同上 | I128: 同上
A129: g_opx_q4 | B129: 指引 non-GAAP 營業費用 FY2026 第四季 | C129: US$M | E129: 1580 | G129: Interested-party | H129: 同上 | I129: 同上
A130: q4g_ss | B130: 第四季半導體系統指引年增（用於反推 FY2025 Q4 重編後數字） | C130: % | E130: 0.62 | G130: Interested-party | H130: 同上（約 62%） | I130: 四捨五入到整數百分比：反推值誤差約 ±0.3%
A131: q4g_ags | B131: 第四季 AGS 指引年增 | C131: % | E131: 0.22 | G131: Interested-party | H131: 同上（約 22%） | I131: 同上
A132: cons_rev26 | B132: 共識營收 FY2026 | C132: US$M | E132: 34260 | G132: Interested-party | H132: stockanalysis.com（資料更新 2026-10-16；34 位分析師） | I132: 第二來源：tickflow 31,430（明顯過時，低於前三季實績＋指引，未採）
A133: cons_eps26 | B133: 共識 non-GAAP EPS FY2026 | C133: US$ | E133: 12.79 | G133: Interested-party | H133: 同上 | I133: 同上：tickflow 11.05（過時，未採）
A134: cons_rev27 | B134: 共識營收 FY2027 | C134: US$M | E134: 46370 | G134: Interested-party | H134: stockanalysis.com（Next Year 摘要框） | I134: 第二來源：未找到（tickflow 37,670 過時，未採）
A135: cons_eps27 | B135: 共識 non-GAAP EPS FY2027 | C135: US$ | E135: 18.49 | G135: Interested-party | H135: 同上 | I135: 第二來源：未找到。FY2028 共識：未找到（stockanalysis 需付費）
A136: pk_A | B136: 情境 A：設備市場見頂年度（日曆年；循環位置規則用） | C136: 年 | E136: 2029 | G136: Derived | H136: markets/equipment/dist/20261023_半導體設備市場模型_v0.1.3.xlsx｜Mkt!C12 | I136: 設備股共用規則（tools/cycle_position.py）：FY(t) 早於見頂年＝中段、等於＝見頂、晚於＝谷底；AMAT 的 FY(t) 有 10/12 落在日曆年 t，直接對照 t（不平移）
... A140: sa_fpe | B140: 遠期 P/E（stockanalysis） | C140: x | E140: 21.39 | G140: Interested-party | H140: stockanalysis.com（2026-10-23） | I140: 自算：現價 ÷ 共識 FY2027 EPS，見 Val
A141: G. 目標價情境權重（Val 第 0 節用；Andy 可改）
A142: tp_wA | B142: 目標價情境權重：情境 A（樂觀） | C142: 權重 | E142: 0.3 | G142: Assumed | H142: Andy 可改（2026-10-25 目標價規格預設 A／B／C＝0.3／0.5／0.2） | I142: 三個權重合計應為 1；目標價＝Σ 權重 × 情境隱含價（Val 第 0 節）
A143: tp_wB | B143: 目標價情境權重：情境 B（基準） | C143: 權重 | E143: 0.5 | G143: Assumed | H143: Andy 可改（2026-10-25 目標價規格預設 A／B／C＝0.3／0.5／0.2） | I143: 三個權重合計應為 1；目標價＝Σ 權重 × 情境隱含價（Val 第 0 節）
A144: tp_wC | B144: 目標價情境權重：情境 C（下檔） | C144: 權重 | E144: 0.2 | G144: Assumed | H144: Andy 可改（2026-10-25 目標價規格預設 A／B／C＝0.3／0.5／0.2） | I144: 三個權重合計應為 1；目標價＝Σ 權重 × 情境隱含價（Val 第 0 節）
A146: J. 目標價（DCF 與 Comparable 加權）與 FY2030–32 收斂法參數（v2 新增；黃底＝Assumed，Andy 可改）
A147: tp_r | B147: 折現率（股東權益要求報酬；美、台、日、韓同一值） | C147: % | E147: 0.1 | G147: Assumed | H147: Andy 可改（工作單 2026-10-25 預設 10%） | I147: —
A148: tp_g | B148: 長期成長率（永續成長；收斂法 FY2032 營收年增的基準） | C148: % | E148: 0.04 | G148: Assumed | H148: Andy 可改（工作單預設 4%） | I148: 情境 A＝tp_g＋2pt、B＝tp_g、C＝tp_g−2pt（PL 頁延伸區塊）
A149: tp_roe | B149: ROE（近三年平均，FY2023–FY2025） | C149: % | E149: =AVERAGE(0.4804,0.4061,0.3551) -> 0.41386667 | G149: Derived | H149: stockanalysis 比率頁（2026-10-25 讀取）：FY2023 48.04%、FY2024 40.61%、FY2025 35.51% | I149: 單一來源；近 12 月 41.07%（同站）
A150: tp_w_dcf | B150: 目標價中 DCF 的權重；其餘為 Comparable | C150: % | E150: 0.5 | G150: Assumed | H150: Andy 可改（2026-10-25 11:53：DCF／Comparable 各半） | I150: —
A151: nim10 | B151: 十年平均淨利率（FY2016–FY2025，GAAP，各年淨利 ÷ 營收的平均） | C151: % | E151: =AVERAGE(1.72/10.82,3.52/14.7,3.04/16.7,2.71/14.61,3.62/17.2,5.89/23.06,6.53/25.79,6.86/26.52,7.18/27.18,7/28.37) -> 0.22546077 | G151: Derived | H151: vcpscanner.com 年度損益（US$B） | I151: 第二來源：stockanalysis 財報頁 FY2021–25 營收與淨利相同；模型淨利為 non-GAAP，十年平均為 GAAP（略低）
A152: cons_tp | B152: 市場共識目標價（賣方平均） | C152: US$ | E152: 627.83 | G152: Interested-party | H152: stockanalysis：40 位分析師平均 US$627.83（中位數 607.50；區間 358–900），資料更新 2026-10-16 | I152: 第二來源：未找到
A153: cons_feps | B153: 共識前瞻 EPS（差距拆解用） | C153: US$ | E153: =cons_eps27 -> 18.49 | G153: Interested-party | H153: 共識前瞻 EPS＝共識 FY2027 non-GAAP EPS（In 頁 cons_eps27，stockanalysis 18.49）；本模型前瞻 EPS 為 FY2028，晚一年，EPS 因素偏大 | I153: Derived

Sheet Q
A1: Q — 實績（百萬美元；EPS 為美元）。會計年度約 11 月～隔年 10 月：FY2026＝2025-10-27～2026-10-25。藍字＝輸入；黑字＝公式。損益為 non-GAAP（公司揭露），GAAP EPS 另列。分部自 FY2026 起重編（200mm 設備移入半導體系統、公司費用全數分攤），FY2025 Q1–Q3 用 FY2026 新聞稿的重編比較數
A2: FY2026 第四季（2026-07-27～2026-10-25）已結束、尚未公布：預定 2026-11-12 公布（stockanalysis）。本版 FY2026＝前三季實績＋第四季公司指引（錨點）。公布後更新 J 欄
A3: 項目 | B3: FY25 Q1（11–1月） | C3: FY25 Q2（2–4月） | D3: FY25 Q3（5–7月） | E3: FY25 Q4（8–10月） | F3: FY2025 全年 | G3: FY26 Q1 | H3: FY26 Q2 | I3: FY26 Q3 | J3: FY26 Q4（指引） | K3: FY2026 錨點 | L3: 標記 | M3: 來源1（公司） | N3: 來源2／說明
A4: 半導體系統（重編後） | B4: 5597 | C4: 5401 | D4: 5564 | E4: =J4/(1+q4g_ss) -> 4876.5432 | F4: =SUM(B4:E4) -> 21438.543 | G4: 5141 | H4: 5965 | I4: 7040 | J4: =g_ss_q4 -> 7900 | K4: =SUM(G4:J4) -> 26046 | L4: Verified／Derived | M4: AMAT 各季新聞稿（ir.appliedmaterials.com；SEC 8-K 附件 99.1）：FY25 Q1–Q3 為 FY26 各季新聞稿的重編比較數；FY25 Q4 由 FY26 Q4 指引 ÷ (1＋62%) 反推（Derived） | N4: FY2025 舊口徑 20,798（FY25 Q4 新聞稿）；重編差額主要為 200mm 設備由 AGS 移入
A5: AGS 服務（重編後） | B5: 1353 | C5: 1420 | D5: 1463 | E5: =J5/(1+q4g_ags) -> 1508.1967 | F5: =SUM(B5:E5) -> 5744.1967 | G5: 1559 | H5: 1665 | I5: 1781 | J5: =g_ags_q4 -> 1840 | K5: =SUM(G5:J5) -> 6845 | L5: Verified／Derived | M5: AMAT 各季新聞稿（ir.appliedmaterials.com；SEC 8-K 附件 99.1）：同上；FY25 Q4 由指引 ÷ (1＋22%) 反推 | N5: FY2025 舊口徑 6,385
A6: 其他（含顯示器） | B6: 216 | C6: 279 | D6: 275 | E6: =E7-E4-E5 -> 415.26007 | F6: =SUM(B6:E6) -> 1185.2601 | G6: 312 | H6: 280 | I6: 294 | J6: =g_oth_q4 -> 510 | K6: =SUM(G6:J6) -> 1396 | L6: Verified／Derived | M6: AMAT 各季新聞稿（ir.appliedmaterials.com；SEC 8-K 附件 99.1）；FY25 Q4＝營收 − 半導體系統 − AGS（Derived） | N6: FY2025 舊口徑顯示器 1,060（另含於公司與其他）
A7: 營收 | B7: 7166 | C7: 7100 | D7: 7302 | E7: 6800 | F7: 28368 | G7: 7012 | H7: 7910 | I7: 9115 | J7: =g_rev_q4 -> 10250 | K7: =SUM(G7:J7) -> 34287 | L7: Verified | M7: AMAT 各季新聞稿（ir.appliedmaterials.com；SEC 8-K 附件 99.1）：FY2025 28,368；FY26 前三季 24,037 | N7: stockanalysis 季報表（逐季相同）
A8: 檢查：分部合計 − 營收（應為 0） | B8: =B4+B5+B6-B7 -> 0 | C8: =C4+C5+C6-C7 -> 0 | D8: =D4+D5+D6-D7 -> 0 | E8: =E4+E5+E6-E7 -> 0 | F8: =F4+F5+F6-F7 -> 0 | G8: =G4+G5+G6-G7 -> 0 | H8: =H4+H5+H6-H7 -> 0 | I8: =I4+I5+I6-I7 -> 0 | ... K8: =K4+K5+K6-K7 -> 0 | L8: — | M8: — | N8: FY25 Q1–Q3 與 FY26 各季：公司分部表加總＝營收
A9: non-GAAP 毛利率 | B9: 0.489 | C9: 0.492 | D9: 0.489 | E9: 0.481 | F9: =F10/F7 -> 0.48783319 | G9: 0.491 | H9: 0.5 | I9: 0.504 | J9: =g_gm_q4 -> 0.504 | K9: =K10/K7 -> 0.50041858 | L9: Verified | M9: AMAT 各季新聞稿（ir.appliedmaterials.com；SEC 8-K 附件 99.1）：FY2025 全年 48.8%（四季加權 48.8%，見 F 欄） | N9: GAAP 毛利率：stockanalysis 季報表毛利 ÷ 營收（差 0.1 個百分點內）
A10: non-GAAP 毛利 | B10: =B7*B9 -> 3504.174 | C10: =C7*C9 -> 3493.2 | D10: =D7*D9 -> 3570.678 | E10: =E7*E9 -> 3270.8 | F10: =SUM(B10:E10) -> 13838.852 | G10: =G7*G9 -> 3442.892 | H10: =H7*H9 -> 3955 | I10: =I7*I9 -> 4593.96 | J10: =J7*J9 -> 5166 | K10: =SUM(G10:J10) -> 17157.852 | L10: Derived | M10: 營收 × 毛利率（毛利率為公司公布的一位小數） | N10: —
A11: non-GAAP 營業利益 | B11: 2190 | C11: 2180 | D11: 2245 | E11: 1947 | F11: =SUM(B11:E11) -> 8562 | G11: 2107 | H11: 2536 | I11: 3096 | J11: =J10-J12 -> 3586 | K11: =SUM(G11:J11) -> 11325 | L11: Verified／Derived | M11: AMAT 各季新聞稿（ir.appliedmaterials.com；SEC 8-K 附件 99.1）：FY2025 8,562；FY26 Q4＝指引毛利 − 指引營業費用 | N11: GAAP 營業利益（stockanalysis）：FY26 Q1 2,096 不含 BIS 和解金 253
A12: non-GAAP 營業費用（毛利 − 營業利益） | B12: =B10-B11 -> 1314.174 | C12: =C10-C11 -> 1313.2 | D12: =D10-D11 -> 1325.678 | E12: =E10-E11 -> 1323.8 | F12: =F10-F11 -> 5276.852 | G12: =G10-G11 -> 1335.892 | H12: =H10-H11 -> 1419 | I12: =I10-I11 -> 1497.96 | J12: =g_opx_q4 -> 1580 | K12: =SUM(G12:J12) -> 5832.852 | L12: Derived | M12: — | N12: FY26 Q4 為公司指引約 1,580
A13: non-GAAP 淨利 | B13: 1946 | C13: 1940 | D13: 1989 | E13: 1732 | F13: =SUM(B13:E13) -> 7607 | G13: 1899 | H13: 2286 | I13: 2795 | J13: =J15*J14 -> 3199.92 | K13: =SUM(G13:J13) -> 10179.92 | L13: Verified／Derived | M13: AMAT 各季新聞稿（ir.appliedmaterials.com；SEC 8-K 附件 99.1）：FY2025 7,607；FY26 Q4＝指引 EPS × 假設股數 | N13: —
A14: 稀釋加權股數（百萬股） | B14: 819 | C14: 812 | D14: 802 | E14: 798 | F14: 808 | G14: 799 | H14: 799 | I14: 800 | J14: =sh_q4 -> 796 | K14: =K13/K15 -> 797.79937 | L14: Verified／Derived | M14: AMAT 各季新聞稿（ir.appliedmaterials.com；SEC 8-K 附件 99.1） | N14: FY2026 錨點＝淨利 ÷ EPS（Derived）
A15: non-GAAP 稀釋 EPS（美元） | B15: 2.38 | C15: 2.39 | D15: 2.48 | E15: 2.17 | F15: 9.42 | G15: 2.38 | H15: 2.86 | I15: 3.5 | J15: =g_eps_q4 -> 4.02 | K15: =SUM(G15:J15) -> 12.76 | L15: Verified | M15: AMAT 各季新聞稿（ir.appliedmaterials.com；SEC 8-K 附件 99.1）：FY2025 9.42（四季合計 9.42） | N15: 共識 FY2026 12.79（stockanalysis）
A16: GAAP 稀釋 EPS（美元；參考） | B16: 1.45 | C16: 2.63 | D16: 2.22 | E16: 2.38 | F16: 8.66 | G16: 2.54 | H16: 3.51 | I16: 3.17 | L16: Verified | M16: AMAT 各季新聞稿（ir.appliedmaterials.com；SEC 8-K 附件 99.1）：FY2025 8.66（FY2024 8.61） | N16: stockanalysis 季報表（逐季相同）；FY26 Q1 含 BIS 和解金 253（每股 0.32）、Q2 含投資評價益
A17: GAAP 淨利（參考） | B17: 1185 | C17: 2137 | D17: 1779 | E17: 1897 | F17: 6998 | G17: 2026 | H17: 2806 | I17: 2538 | L17: Verified | M17: AMAT 各季新聞稿（ir.appliedmaterials.com；SEC 8-K 附件 99.1） | N17: stockanalysis 季報表
A18: 半導體系統：晶圓代工、邏輯與其他 占比 | B18: 0.69 | C18: 0.66 | D18: 0.69 | E18: 0.65 | G18: 0.62 | H18: 0.67 | I18: 0.67 | J18: =1-J19-J20 -> 0.64 | K18: =SUMPRODUCT(G18:J18,G4:J4)/K4 -> 0.65103164 | L18: Verified／Assumed | M18: AMAT 各季新聞稿（ir.appliedmaterials.com；SEC 8-K 附件 99.1）（FY25 Q4 為舊口徑：FY25 Q4 新聞稿；FY2025 全年 67%） | N18: FY26 Q4 為 Assumed（In 頁 q4_dr、q4_nd）
A19: 半導體系統：DRAM 占比 | B19: 0.27 | C19: 0.27 | D19: 0.22 | E19: 0.29 | G19: 0.34 | H19: 0.29 | I19: 0.26 | J19: =q4_dr -> 0.3 | K19: =SUMPRODUCT(G19:J19,G4:J4)/K4 -> 0.29479344 | L19: Verified／Assumed | M19: AMAT 各季新聞稿（ir.appliedmaterials.com；SEC 8-K 附件 99.1）（FY2025 全年 26%） | N19: Q3 FY26 DRAM（含 HBM 封裝）年增 52%（法說）
A20: 半導體系統：Flash（NAND）占比 | B20: 0.04 | C20: 0.07 | D20: 0.09 | E20: 0.06 | G20: 0.04 | H20: 0.04 | I20: 0.07 | J20: =q4_nd -> 0.06 | K20: =SUMPRODUCT(G20:J20,G4:J4)/K4 -> 0.054174921 | L20: Verified／Assumed | M20: AMAT 各季新聞稿（ir.appliedmaterials.com；SEC 8-K 附件 99.1）（FY2025 全年 7%） | N20: —
A21: 中國營收 | B21: 2243 | C21: 1774 | D21: 2548 | E21: 1964 | F21: =SUM(B21:E21) -> 8529 | G21: 2095 | H21: 2087 | I21: 2506 | L21: Verified | M21: AMAT 各季新聞稿（ir.appliedmaterials.com；SEC 8-K 附件 99.1）：FY2025 8,529（30%；FY2024 10,117、37%） | N21: Reuters：中國占比降至約 25%（Yahoo Finance 2025-11-14）
A22: 中國占營收 | B22: =B21/B7 -> 0.31300586 | C22: =C21/C7 -> 0.24985915 | D22: =D21/D7 -> 0.34894549 | E22: =E21/E7 -> 0.28882353 | F22: =F21/F7 -> 0.30065567 | G22: =G21/G7 -> 0.29877353 | H22: =H21/H7 -> 0.26384324 | I22: =I21/I7 -> 0.27493143 | L22: Derived | M22: 公司：Q1 30%、Q2 27%、Q3 28% | N22: —
A23: 檢查：四季合計 − 全年公布值（營收、毛利率、營業利益、淨利、EPS、中國 依序在 B–G 欄） | B23: =SUM(B7:E7)-F7 -> 0 | C23: =F9-0.488 -> -0.00016680767 | D23: =F11-8562 -> 0 | E23: =F13-7607 -> 0 | F23: =SUM(B15:E15)-F15 -> 0 | G23: =F21-8529 -> 0 | L23: — | M23: — | N23: 毛利率差為四捨五入（公司公布 48.8%）
A26: FY2026 錨點的組成（前三季實績＋第四季指引）
A27: 項目 | B27: 前三季實績 | C27: 第四季指引 | D27: FY2026 錨點 | E27: FY2025 | F27: 年增 | G27: 第四季 × 4（年化）
A28: 營收 | B28: =SUM(G7:I7) -> 24037 | C28: =J7 -> 10250 | D28: =K7 -> 34287 | E28: =F7 -> 28368 | F28: =D28/E28-1 -> 0.20865059 | G28: =C28*4 -> 41000
A29: 半導體系統 | B29: =SUM(G4:I4) -> 18146 | C29: =J4 -> 7900 | D29: =K4 -> 26046 | E29: =F4 -> 21438.543 | F29: =D29/E29-1 -> 0.21491464 | G29: =C29*4 -> 31600
A30: AGS | B30: =SUM(G5:I5) -> 5005 | C30: =J5 -> 1840 | D30: =K5 -> 6845 | E30: =F5 -> 5744.1967 | F30: =D30/E30-1 -> 0.19163746 | G30: =C30*4 -> 7360
A31: 其他 | B31: =SUM(G6:I6) -> 886 | C31: =J6 -> 510 | D31: =K6 -> 1396 | E31: =F6 -> 1185.2601 | F31: =D31/E31-1 -> 0.17780058 | G31: =C31*4 -> 2040
A32: non-GAAP 營業利益 | B32: =SUM(G11:I11) -> 7739 | C32: =J11 -> 3586 | D32: =K11 -> 11325 | E32: =F11 -> 8562 | F32: =D32/E32-1 -> 0.32270498 | G32: =C32*4 -> 14344
A33: non-GAAP EPS | B33: =SUM(G15:I15) -> 8.74 | C33: =J15 -> 4.02 | D33: =K15 -> 12.76 | E33: =F15 -> 9.42 | F33: =D33/E33-1 -> 0.35456476 | G33: =C33*4 -> 16.08
A35: non-GAAP 營業利益率：FY2025 | B35: =a25_oi/a25_rev -> 0.30181895
A36: non-GAAP 營業利益率：FY2026 錨點 | B36: =an_oi/an_rev -> 0.33030011
A37: 共識 FY2026 營收、EPS（stockanalysis；只作對照） | B37: =cons_rev26 -> 34260 | C37: =cons_eps26 -> 12.79

Sheet Units
A1: Units — 晶圓廠設備市場（US$B；markets/equipment 成品，三情境）：日曆年 → AMAT 會計年度（FY(t)＝fyw×CY(t−1)＋(1−fyw)×CY(t)），以及 AMAT 半導體系統占市場的隱含份額（只作檢驗，不校準）
A3: 項目 | B3: 單位 | C3: 2025 | D3: 2026 | E3: 2027 | F3: 2028 | G3: 2029 | H3: 說明
A4: 情境 A：日曆年（CY）
A5: 晶圓代工、邏輯與其他（先進邏輯＋其他代工邏輯＋其他前段） | B5: US$B | C5: =laA_25+loA_25+ofA_25 -> 78.348121 | D5: =laA_26+loA_26+ofA_26 -> 99.287198 | E5: =laA_27+loA_27+ofA_27 -> 116.28871 | F5: =laA_28+loA_28+ofA_28 -> 130.8864 | G5: =laA_29+loA_29+ofA_29 -> 139.39808
A6: DRAM（含 HBM） | B6: US$B | C6: =drA_25 -> 26.376109 | D6: =drA_26 -> 39.365947 | E6: =drA_27 -> 53.258733 | F6: =drA_28 -> 59.5609 | G6: =drA_29 -> 61.831293
A7: NAND | B7: US$B | C7: =ndA_25 -> 12.172602 | D7: =ndA_26 -> 17.503905 | E7: =ndA_27 -> 23.248027 | F7: =ndA_28 -> 26.181322 | G7: =ndA_29 -> 27.674313
A8: 合計（晶圓前段） | B8: US$B | C8: =SUM(C5:C7) -> 116.89683 | D8: =SUM(D5:D7) -> 156.15705 | E8: =SUM(E5:E7) -> 192.79547 | F8: =SUM(F5:F7) -> 216.62863 | G8: =SUM(G5:G7) -> 228.90369
A9: 情境 A：會計年度（FY；FY2025 需 CY2024，市場層沒有，留空）
A10: 晶圓代工、邏輯與其他 | B10: US$B | D10: =fyw*C5+(1-fyw)*D5 -> 95.797352 | E10: =fyw*D5+(1-fyw)*E5 -> 113.45512 | F10: =fyw*E5+(1-fyw)*F5 -> 128.45346 | G10: =fyw*F5+(1-fyw)*G5 -> 137.97947
A11: DRAM（含 HBM） | B11: US$B | D11: =fyw*C6+(1-fyw)*D6 -> 37.200974 | E11: =fyw*D6+(1-fyw)*E6 -> 50.943268 | F11: =fyw*E6+(1-fyw)*F6 -> 58.510539 | G11: =fyw*F6+(1-fyw)*G6 -> 61.452894
A12: NAND | B12: US$B | D12: =fyw*C7+(1-fyw)*D7 -> 16.615355 | E12: =fyw*D7+(1-fyw)*E7 -> 22.290674 | F12: =fyw*E7+(1-fyw)*F7 -> 25.692439 | G12: =fyw*F7+(1-fyw)*G7 -> 27.425481
A13: 合計（晶圓前段） | B13: US$B | D13: =fyw*C8+(1-fyw)*D8 -> 149.61368 | E13: =fyw*D8+(1-fyw)*E8 -> 186.68907 | F13: =fyw*E8+(1-fyw)*F8 -> 212.65643 | G13: =fyw*F8+(1-fyw)*G8 -> 226.85784
A15: 情境 B：日曆年（CY）
A16: 晶圓代工、邏輯與其他（先進邏輯＋其他代工邏輯＋其他前段） | B16: US$B | C16: =laB_25+loB_25+ofB_25 -> 78.348121 | D16: =laB_26+loB_26+ofB_26 -> 99.287198 | E16: =laB_27+loB_27+ofB_27 -> 116.28871 | F16: =laB_28+loB_28+ofB_28 -> 116.28871 | G16: =laB_29+loB_29+ofB_29 -> 110.47427
A17: DRAM（含 HBM） | B17: US$B | C17: =drB_25 -> 26.376109 | D17: =drB_26 -> 39.365947 | E17: =drB_27 -> 53.258733 | F17: =drB_28 -> 53.258733 | G17: =drB_29 -> 50.595796
A18: NAND | B18: US$B | C18: =ndB_25 -> 12.172602 | D18: =ndB_26 -> 17.503905 | E18: =ndB_27 -> 23.248027 | F18: =ndB_28 -> 23.248027 | G18: =ndB_29 -> 22.085626
A19: 合計（晶圓前段） | B19: US$B | C19: =SUM(C16:C18) -> 116.89683 | D19: =SUM(D16:D18) -> 156.15705 | E19: =SUM(E16:E18) -> 192.79547 | F19: =SUM(F16:F18) -> 192.79547 | G19: =SUM(G16:G18) -> 183.1557
A20: 情境 B：會計年度（FY；FY2025 需 CY2024，市場層沒有，留空）
A21: 晶圓代工、邏輯與其他 | B21: US$B | D21: =fyw*C16+(1-fyw)*D16 -> 95.797352 | E21: =fyw*D16+(1-fyw)*E16 -> 113.45512 | F21: =fyw*E16+(1-fyw)*F16 -> 116.28871 | G21: =fyw*F16+(1-fyw)*G16 -> 111.44335
A22: DRAM（含 HBM） | B22: US$B | D22: =fyw*C17+(1-fyw)*D17 -> 37.200974 | E22: =fyw*D17+(1-fyw)*E17 -> 50.943268 | F22: =fyw*E17+(1-fyw)*F17 -> 53.258733 | G22: =fyw*F17+(1-fyw)*G17 -> 51.039619
A23: NAND | B23: US$B | D23: =fyw*C18+(1-fyw)*D18 -> 16.615355 | E23: =fyw*D18+(1-fyw)*E18 -> 22.290674 | F23: =fyw*E18+(1-fyw)*F18 -> 23.248027 | G23: =fyw*F18+(1-fyw)*G18 -> 22.279359
A24: 合計（晶圓前段） | B24: US$B | D24: =fyw*C19+(1-fyw)*D19 -> 149.61368 | E24: =fyw*D19+(1-fyw)*E19 -> 186.68907 | F24: =fyw*E19+(1-fyw)*F19 -> 192.79547 | G24: =fyw*F19+(1-fyw)*G19 -> 184.76232
A26: 情境 C：日曆年（CY）
A27: 晶圓代工、邏輯與其他（先進邏輯＋其他代工邏輯＋其他前段） | B27: US$B | C27: =laC_25+loC_25+ofC_25 -> 78.348121 | D27: =laC_26+loC_26+ofC_26 -> 99.287198 | E27: =laC_27+loC_27+ofC_27 -> 116.28871 | F27: =laC_28+loC_28+ofC_28 -> 93.030967 | G27: =laC_29+loC_29+ofC_29 -> 93.030967
A28: DRAM（含 HBM） | B28: US$B | C28: =drC_25 -> 26.376109 | D28: =drC_26 -> 39.365947 | E28: =drC_27 -> 53.258733 | F28: =drC_28 -> 42.606986 | G28: =drC_29 -> 42.606986
A29: NAND | B29: US$B | C29: =ndC_25 -> 12.172602 | D29: =ndC_26 -> 17.503905 | E29: =ndC_27 -> 23.248027 | F29: =ndC_28 -> 18.598422 | G29: =ndC_29 -> 18.598422
A30: 合計（晶圓前段） | B30: US$B | C30: =SUM(C27:C29) -> 116.89683 | D30: =SUM(D27:D29) -> 156.15705 | E30: =SUM(E27:E29) -> 192.79547 | F30: =SUM(F27:F29) -> 154.23638 | G30: =SUM(G27:G29) -> 154.23638
A31: 情境 C：會計年度（FY；FY2025 需 CY2024，市場層沒有，留空）
A32: 晶圓代工、邏輯與其他 | B32: US$B | D32: =fyw*C27+(1-fyw)*D27 -> 95.797352 | E32: =fyw*D27+(1-fyw)*E27 -> 113.45512 | F32: =fyw*E27+(1-fyw)*F27 -> 96.907258 | G32: =fyw*F27+(1-fyw)*G27 -> 93.030967
A33: DRAM（含 HBM） | B33: US$B | D33: =fyw*C28+(1-fyw)*D28 -> 37.200974 | E33: =fyw*D28+(1-fyw)*E28 -> 50.943268 | F33: =fyw*E28+(1-fyw)*F28 -> 44.382277 | G33: =fyw*F28+(1-fyw)*G28 -> 42.606986
A34: NAND | B34: US$B | D34: =fyw*C29+(1-fyw)*D29 -> 16.615355 | E34: =fyw*D29+(1-fyw)*E29 -> 22.290674 | F34: =fyw*E29+(1-fyw)*F29 -> 19.373356 | G34: =fyw*F29+(1-fyw)*G29 -> 18.598422
A35: 合計（晶圓前段） | B35: US$B | D35: =fyw*C30+(1-fyw)*D30 -> 149.61368 | E35: =fyw*D30+(1-fyw)*E30 -> 186.68907 | F35: =fyw*E30+(1-fyw)*F30 -> 160.66289 | G35: =fyw*F30+(1-fyw)*G30 -> 154.23638
A37: AMAT 半導體系統 ÷ 會計年度晶圓前段市場（隱含份額；情境 A；FY2027 起份額係數 sf 決定變化）
A38: 情境 A | B38: % | D38: =PL!D65 -> 0.17408836 | E38: =PL!E65 -> 0.1740321 | F38: =PL!F65 -> 0.17396817 | G38: =PL!G65 -> 0.17383613 | H38: AMAT 半導體系統也含先進封裝等後段設備，故份額略高於純前段口徑
A40: 說明：AMAT「Foundry, logic and other」含 ICAPS（成熟製程、功率、類比、物聯網等），故以設備市場的先進邏輯＋其他代工邏輯＋其他前段為對應；設備市場模型 2026 年以後高於 SEMI 約 7–10%（markets/equipment Recon），本模型只用各終端市場的成長指數，水準由 AMAT FY2026 錨點決定。

Sheet PL
A1: PL — Applied Materials 損益（US$M；non-GAAP；FY2025 為實績，FY2026 為錨點（前三季實績＋第四季指引），FY2027–FY2029 為模型）。三情境各一個完整推導區塊（見下方），本頁頂端為摘要
A3: 情境／項目 | B3: 單位 | C3: FY2025A | D3: FY2026（錨點） | E3: FY2027 | F3: FY2028 | G3: FY2029 | H3: 說明
A4: 情境 A
A5: 營收 | B5: US$M | C5: =C56 -> 28368 | D5: =D56 -> 34287 | E5: =E56 -> 41757.639 | F5: =F56 -> 47443.964 | G5: =G56 -> 51242.48
A6: 半導體系統 | B6: US$M | C6: =C52 -> 21438.543 | D6: =D52 -> 26046 | E6: =E52 -> 32489.889 | F6: =F52 -> 36995.451 | G6: =G52 -> 39436.09
A7: AGS 服務 | B7: US$M | C7: =C53 -> 5744.1967 | D7: =D53 -> 6845 | E7: =E53 -> 7871.75 | F7: =F53 -> 9052.5125 | G7: =G53 -> 10410.389
A8: non-GAAP 毛利率 | B8: % | C8: =C57 -> 0.48783319 | D8: =D57 -> 0.50041858 | E8: =E57 -> 0.51120976 | F8: =F57 -> 0.51714573 | G8: =G57 -> 0.52037705
A9: non-GAAP 營業利益 | B9: US$M | C9: =C60 -> 8562 | D9: =D60 -> 11325 | E9: =E60 -> 14812.308 | F9: =F60 -> 17466.695 | G9: =G60 -> 19239.849
A10: non-GAAP 營業利益率 | B10: % | C10: =C61 -> 0.30181895 | D10: =D61 -> 0.33030011 | E10: =E61 -> 0.35472092 | F10: =F61 -> 0.3681542 | G10: =G61 -> 0.37546678
A11: non-GAAP 淨利 | B11: US$M | C11: =C62 -> 7607 | D11: =D62 -> 10179.92 | E11: =E62 -> 13160.153 | F11: =F62 -> 15518.471 | G11: =G62 -> 17093.848
A12: non-GAAP EPS | B12: US$ | C12: =C64 -> 9.42 | D12: =D64 -> 12.76 | E12: =E64 -> 16.662189 | F12: =F64 -> 19.846542 | G12: =G64 -> 22.08211
A14: 情境 B
A15: 營收 | B15: US$M | C15: =C84 -> 28368 | D15: =D84 -> 34287 | E15: =E84 -> 41414.039 | F15: =F84 -> 43244.276 | G15: =G84 -> 42711.047
A16: 半導體系統 | B16: US$M | C16: =C80 -> 21438.543 | D16: =D80 -> 26046 | E16: =E80 -> 32489.889 | F16: =F80 -> 33550.661 | G16: =G80 -> 32152.717
A17: AGS 服務 | B17: US$M | C17: =C81 -> 5744.1967 | D17: =D81 -> 6845 | E17: =E81 -> 7597.95 | F17: =F81 -> 8433.7245 | G17: =G81 -> 9361.4342
A18: non-GAAP 毛利率 | B18: % | C18: =C85 -> 0.48783319 | D18: =D85 -> 0.50041858 | E18: =E85 -> 0.51079886 | F18: =F85 -> 0.51291238 | G18: =G85 -> 0.51231532
A19: non-GAAP 營業利益 | B19: US$M | C19: =C88 -> 8562 | D19: =D88 -> 11325 | E19: =E88 -> 14651.915 | F19: =F88 -> 15506.273 | G19: =G88 -> 15257.36
A20: non-GAAP 營業利益率 | B20: % | C20: =C89 -> 0.30181895 | D20: =D89 -> 0.33030011 | E20: =E89 -> 0.35379101 | F20: =F89 -> 0.35857399 | G20: =G89 -> 0.35722282
A21: non-GAAP 淨利 | B21: US$M | C21: =C90 -> 7607 | D21: =D90 -> 10179.92 | E21: =E90 -> 13017.65 | F21: =F90 -> 13776.713 | G21: =G90 -> 13555.564
A22: non-GAAP EPS | B22: US$ | C22: =C92 -> 9.42 | D22: =D92 -> 12.76 | E22: =E92 -> 16.481764 | F22: =F92 -> 17.619011 | G22: =G92 -> 17.511297
A24: 情境 C
A25: 營收 | B25: US$M | C25: =C112 -> 28368 | D25: =D112 -> 34287 | E25: =E112 -> 40470.439 | F25: =F112 -> 36326.485 | G25: =G112 -> 35643.632
A26: 半導體系統 | B26: US$M | C26: =C108 -> 21438.543 | D26: =D108 -> 26046 | E26: =E108 -> 32489.889 | F26: =F108 -> 27958.884 | G26: =G108 -> 26840.529
A27: AGS 服務 | B27: US$M | C27: =C109 -> 5744.1967 | D27: =D109 -> 6845 | E27: =E109 -> 7324.15 | F27: =F109 -> 7836.8405 | G27: =G109 -> 8385.4193
A28: non-GAAP 毛利率 | B28: % | C28: =C113 -> 0.48783319 | D28: =D113 -> 0.50041858 | E28: =E113 -> 0.50963452 | F28: =F113 -> 0.50380503 | G28: =G113 -> 0.50271435
A29: non-GAAP 營業利益 | B29: US$M | C29: =C116 -> 8562 | D29: =D116 -> 11325 | E29: =E116 -> 14211.441 | F29: =F116 -> 12277.035 | G29: =G116 -> 11958.278
A30: non-GAAP 營業利益率 | B30: % | C30: =C117 -> 0.30181895 | D30: =D117 -> 0.33030011 | E30: =E117 -> 0.35115608 | F30: =F117 -> 0.33796376 | G30: =G117 -> 0.33549551
A31: non-GAAP 淨利 | B31: US$M | C31: =C118 -> 7607 | D31: =D118 -> 10179.92 | E31: =E118 -> 12626.306 | F31: =F118 -> 10907.663 | G31: =G118 -> 10624.46
A32: non-GAAP EPS | B32: US$ | C32: =C120 -> 9.42 | D32: =D120 -> 12.76 | E32: =E120 -> 15.98628 | F32: =F120 -> 13.949788 | G32: =G120 -> 13.724849
A34: 讀法：FY2026 三情境相同（錨點）；FY2027 的 1/6 落在 CY2026、5/6 在 CY2027，設備市場三情境在 CY2027 以前相同，所以 FY2027 只有情境 C 的出口管制調整造成差異；FY2028 起情境差異來自設備市場。
A40: 情境 A：設備市場續增（2028 +12.7%、2029 +5.9%；markets/equipment）
A41: 項目 | B41: 單位 | C41: 2025 | D41: 2026 | E41: 2027 | F41: 2028 | G41: 2029 | H41: 說明
A42: A. 市場（日曆年 CY，US$B；讀 In 頁的設備市場成品）
A43: 晶圓代工、邏輯與其他 CY | B43: US$B | C43: =laA_25+loA_25+ofA_25 -> 78.348121 | D43: =laA_26+loA_26+ofA_26 -> 99.287198 | E43: =laA_27+loA_27+ofA_27 -> 116.28871 | F43: =laA_28+loA_28+ofA_28 -> 130.8864 | G43: =laA_29+loA_29+ofA_29 -> 139.39808
A44: DRAM（含 HBM）CY | B44: US$B | C44: =drA_25 -> 26.376109 | D44: =drA_26 -> 39.365947 | E44: =drA_27 -> 53.258733 | F44: =drA_28 -> 59.5609 | G44: =drA_29 -> 61.831293
A45: NAND CY | B45: US$B | C45: =ndA_25 -> 12.172602 | D45: =ndA_26 -> 17.503905 | E45: =ndA_27 -> 23.248027 | F45: =ndA_28 -> 26.181322 | G45: =ndA_29 -> 27.674313
A46: B. 會計年度（FY；FY(t)＝fyw×CY(t−1)＋(1−fyw)×CY(t)）
A47: 晶圓代工、邏輯與其他 FY | B47: US$B | D47: =fyw*C43+(1-fyw)*D43 -> 95.797352 | E47: =fyw*D43+(1-fyw)*E43 -> 113.45512 | F47: =fyw*E43+(1-fyw)*F43 -> 128.45346 | G47: =fyw*F43+(1-fyw)*G43 -> 137.97947
A48: DRAM（含 HBM）FY | B48: US$B | D48: =fyw*C44+(1-fyw)*D44 -> 37.200974 | E48: =fyw*D44+(1-fyw)*E44 -> 50.943268 | F48: =fyw*E44+(1-fyw)*F44 -> 58.510539 | G48: =fyw*F44+(1-fyw)*G44 -> 61.452894
A49: NAND FY | B49: US$B | D49: =fyw*C45+(1-fyw)*D45 -> 16.615355 | E49: =fyw*D45+(1-fyw)*E45 -> 22.290674 | F49: =fyw*E45+(1-fyw)*F45 -> 25.692439 | G49: =fyw*F45+(1-fyw)*G45 -> 27.425481
A50: 半導體系統需求指數（FY2026＝1；以 FY2026 終端市場權重加權） | B50: x | D50: =m_fl*D47/$D47+m_dr*D48/$D48+m_nd*D49/$D49 -> 1 | E50: =m_fl*E47/$D47+m_dr*E48/$D48+m_nd*E49/$D49 -> 1.2474042 | F50: =m_fl*F47/$D47+m_dr*F48/$D48+m_nd*F49/$D49 -> 1.420389 | G50: =m_fl*G47/$D47+m_dr*G48/$D48+m_nd*G49/$D49 -> 1.5140939 | H50: Σ 權重 × FY 市場 ÷ FY2026 市場
A51: C. 損益（US$M；FY2025 實績、FY2026 錨點＝前三季實績＋第四季指引、FY2027 起模型）
A52: 半導體系統營收 | B52: US$M | C52: =a25_ss -> 21438.543 | D52: =an_ss -> 26046 | E52: =$D52*E50*sf -> 32489.889 | F52: =$D52*F50*sf -> 36995.451 | G52: =$D52*G50*sf -> 39436.09 | H52: FY2027 起＝FY2026 錨點 × 需求指數 × 份額係數
A53: AGS 服務營收 | B53: US$M | C53: =a25_ags -> 5744.1967 | D53: =an_ags -> 6845 | E53: =D53*(1+g_ags_A) -> 7871.75 | F53: =E53*(1+g_ags_A) -> 9052.5125 | G53: =F53*(1+g_ags_A) -> 10410.389
A54: 其他（含顯示器）營收 | B54: US$M | C54: =a25_oth -> 1185.2601 | D54: =an_oth -> 1396 | E54: =D54*(1+g_oth_A) -> 1396 | F54: =E54*(1+g_oth_A) -> 1396 | G54: =F54*(1+g_oth_A) -> 1396
A55: 出口管制與中國調整 | B55: US$M | C55: 0 | D55: 0 | E55: =-aff_hit*aff_A-0*cn_sh*(E52+E53) -> 0 | F55: =-aff_hit*aff_A-0*cn_sh*(F52+F53) -> 0 | G55: =-aff_hit*aff_A-0*cn_sh*(G52+G53) -> 0 | H55: 關係企業規則恢復（情境 C 或 Sens）；中國下修只在 Sens
A56: 營收 | B56: US$M | C56: =C52+C53+C54+C55 -> 28368 | D56: =D52+D53+D54+D55 -> 34287 | E56: =E52+E53+E54+E55 -> 41757.639 | F56: =F52+F53+F54+F55 -> 47443.964 | G56: =G52+G53+G54+G55 -> 51242.48
A57: non-GAAP 毛利率 | B57: % | C57: =a25_gp/a25_rev -> 0.48783319 | D57: =an_gp/an_rev -> 0.50041858 | E57: =1-(cF+cv*E56)/E56 -> 0.51120976 | F57: =1-(cF+cv*F56)/F56 -> 0.51714573 | G57: =1-(cF+cv*G56)/G56 -> 0.52037705 | H57: 營業成本＝固定＋變動×營收（兩點推導）
A58: non-GAAP 毛利 | B58: US$M | C58: =C56*C57 -> 13838.852 | D58: =D56*D57 -> 17157.852 | E58: =E56*E57 -> 21346.913 | F58: =F56*F57 -> 24535.443 | G58: =G56*G57 -> 26665.41
A59: non-GAAP 營業費用 | B59: US$M | C59: =opex25 -> 5276.852 | D59: =opex26 -> 5832.852 | E59: =oF+ov*E56 -> 6534.6049 | F59: =oF+ov*F56 -> 7068.7486 | G59: =oF+ov*G56 -> 7425.5614 | H59: 固定＋變動×營收（兩點推導）
A60: non-GAAP 營業利益 | B60: US$M | C60: =C58-C59 -> 8562 | D60: =D58-D59 -> 11325 | E60: =E58-E59 -> 14812.308 | F60: =F58-F59 -> 17466.695 | G60: =G58-G59 -> 19239.849
A61: non-GAAP 營業利益率 | B61: % | C61: =C60/C56 -> 0.30181895 | D61: =D60/D56 -> 0.33030011 | E61: =E60/E56 -> 0.35472092 | F61: =F60/F56 -> 0.3681542 | G61: =G60/G56 -> 0.37546678
A62: non-GAAP 淨利 | B62: US$M | C62: =a25_ni -> 7607 | D62: =an_ni -> 10179.92 | E62: =E60*nioi -> 13160.153 | F62: =F60*nioi -> 15518.471 | G62: =G60*nioi -> 17093.848
A63: 稀釋股數 | B63: 百萬股 | C63: =a25_sh -> 808 | D63: =an_sh -> 797.79937 | E63: =$D63*(1-bb)^1 -> 789.82138 | F63: =$D63*(1-bb)^2 -> 781.92317 | G63: =$D63*(1-bb)^3 -> 774.10393
A64: non-GAAP 稀釋 EPS | B64: US$ | C64: =a25_eps -> 9.42 | D64: =an_eps -> 12.76 | E64: =E62/E63 -> 16.662189 | F64: =F62/F63 -> 19.846542 | G64: =G62/G63 -> 22.08211 | H64: FY2026＝前三季實績 EPS 合計＋第四季指引 EPS
A65: 半導體系統 ÷ FY 晶圓前段市場（隱含份額） | B65: % | D65: =D52/1000/(D47+D48+D49) -> 0.17408836 | E65: =E52/1000/(E47+E48+E49) -> 0.1740321 | F65: =F52/1000/(F47+F48+F49) -> 0.17396817 | G65: =G52/1000/(G47+G48+G49) -> 0.17383613 | H65: 檢驗用；FY2027 起等於 FY2026 份額 × 份額係數 × 組合效果
A68: 情境 B：設備市場 2028 持平、2029 −5%；AGS 成長放緩
A69: 項目 | B69: 單位 | C69: 2025 | D69: 2026 | E69: 2027 | F69: 2028 | G69: 2029 | H69: 說明
A70: A. 市場（日曆年 CY，US$B；讀 In 頁的設備市場成品）
A71: 晶圓代工、邏輯與其他 CY | B71: US$B | C71: =laB_25+loB_25+ofB_25 -> 78.348121 | D71: =laB_26+loB_26+ofB_26 -> 99.287198 | E71: =laB_27+loB_27+ofB_27 -> 116.28871 | F71: =laB_28+loB_28+ofB_28 -> 116.28871 | G71: =laB_29+loB_29+ofB_29 -> 110.47427
A72: DRAM（含 HBM）CY | B72: US$B | C72: =drB_25 -> 26.376109 | D72: =drB_26 -> 39.365947 | E72: =drB_27 -> 53.258733 | F72: =drB_28 -> 53.258733 | G72: =drB_29 -> 50.595796
A73: NAND CY | B73: US$B | C73: =ndB_25 -> 12.172602 | D73: =ndB_26 -> 17.503905 | E73: =ndB_27 -> 23.248027 | F73: =ndB_28 -> 23.248027 | G73: =ndB_29 -> 22.085626
A74: B. 會計年度（FY；FY(t)＝fyw×CY(t−1)＋(1−fyw)×CY(t)）
A75: 晶圓代工、邏輯與其他 FY | B75: US$B | D75: =fyw*C71+(1-fyw)*D71 -> 95.797352 | E75: =fyw*D71+(1-fyw)*E71 -> 113.45512 | F75: =fyw*E71+(1-fyw)*F71 -> 116.28871 | G75: =fyw*F71+(1-fyw)*G71 -> 111.44335
A76: DRAM（含 HBM）FY | B76: US$B | D76: =fyw*C72+(1-fyw)*D72 -> 37.200974 | E76: =fyw*D72+(1-fyw)*E72 -> 50.943268 | F76: =fyw*E72+(1-fyw)*F72 -> 53.258733 | G76: =fyw*F72+(1-fyw)*G72 -> 51.039619
A77: NAND FY | B77: US$B | D77: =fyw*C73+(1-fyw)*D73 -> 16.615355 | E77: =fyw*D73+(1-fyw)*E73 -> 22.290674 | F77: =fyw*E73+(1-fyw)*F73 -> 23.248027 | G77: =fyw*F73+(1-fyw)*G73 -> 22.279359
A78: 半導體系統需求指數（FY2026＝1；以 FY2026 終端市場權重加權） | B78: x | D78: =m_fl*D75/$D75+m_dr*D76/$D76+m_nd*D77/$D77 -> 1 | E78: =m_fl*E75/$D75+m_dr*E76/$D76+m_nd*E77/$D77 -> 1.2474042 | F78: =m_fl*F75/$D75+m_dr*F76/$D76+m_nd*F77/$D77 -> 1.288131 | G78: =m_fl*G75/$D75+m_dr*G76/$D76+m_nd*G77/$D77 -> 1.2344589 | H78: Σ 權重 × FY 市場 ÷ FY2026 市場
A79: C. 損益（US$M；FY2025 實績、FY2026 錨點＝前三季實績＋第四季指引、FY2027 起模型）
A80: 半導體系統營收 | B80: US$M | C80: =a25_ss -> 21438.543 | D80: =an_ss -> 26046 | E80: =$D80*E78*sf -> 32489.889 | F80: =$D80*F78*sf -> 33550.661 | G80: =$D80*G78*sf -> 32152.717 | H80: FY2027 起＝FY2026 錨點 × 需求指數 × 份額係數
A81: AGS 服務營收 | B81: US$M | C81: =a25_ags -> 5744.1967 | D81: =an_ags -> 6845 | E81: =D81*(1+g_ags_B) -> 7597.95 | F81: =E81*(1+g_ags_B) -> 8433.7245 | G81: =F81*(1+g_ags_B) -> 9361.4342
A82: 其他（含顯示器）營收 | B82: US$M | C82: =a25_oth -> 1185.2601 | D82: =an_oth -> 1396 | E82: =D82*(1+g_oth_B) -> 1326.2 | F82: =E82*(1+g_oth_B) -> 1259.89 | G82: =F82*(1+g_oth_B) -> 1196.8955
A83: 出口管制與中國調整 | B83: US$M | C83: 0 | D83: 0 | E83: =-aff_hit*aff_B-0*cn_sh*(E80+E81) -> 0 | F83: =-aff_hit*aff_B-0*cn_sh*(F80+F81) -> 0 | G83: =-aff_hit*aff_B-0*cn_sh*(G80+G81) -> 0 | H83: 關係企業規則恢復（情境 C 或 Sens）；中國下修只在 Sens
A84: 營收 | B84: US$M | C84: =C80+C81+C82+C83 -> 28368 | D84: =D80+D81+D82+D83 -> 34287 | E84: =E80+E81+E82+E83 -> 41414.039 | F84: =F80+F81+F82+F83 -> 43244.276 | G84: =G80+G81+G82+G83 -> 42711.047
A85: non-GAAP 毛利率 | B85: % | C85: =a25_gp/a25_rev -> 0.48783319 | D85: =an_gp/an_rev -> 0.50041858 | E85: =1-(cF+cv*E84)/E84 -> 0.51079886 | F85: =1-(cF+cv*F84)/F84 -> 0.51291238 | G85: =1-(cF+cv*G84)/G84 -> 0.51231532 | H85: 營業成本＝固定＋變動×營收（兩點推導）
A86: non-GAAP 毛利 | B86: US$M | C86: =C84*C85 -> 13838.852 | D86: =D84*D85 -> 17157.852 | E86: =E84*E85 -> 21154.244 | F86: =F84*F85 -> 22180.524 | G86: =G84*G85 -> 21881.523
A87: non-GAAP 營業費用 | B87: US$M | C87: =opex25 -> 5276.852 | D87: =opex26 -> 5832.852 | E87: =oF+ov*E84 -> 6502.3289 | F87: =oF+ov*F84 -> 6674.2518 | G87: =oF+ov*G84 -> 6624.163 | H87: 固定＋變動×營收（兩點推導）
A88: non-GAAP 營業利益 | B88: US$M | C88: =C86-C87 -> 8562 | D88: =D86-D87 -> 11325 | E88: =E86-E87 -> 14651.915 | F88: =F86-F87 -> 15506.273 | G88: =G86-G87 -> 15257.36
A89: non-GAAP 營業利益率 | B89: % | C89: =C88/C84 -> 0.30181895 | D89: =D88/D84 -> 0.33030011 | E89: =E88/E84 -> 0.35379101 | F89: =F88/F84 -> 0.35857399 | G89: =G88/G84 -> 0.35722282
A90: non-GAAP 淨利 | B90: US$M | C90: =a25_ni -> 7607 | D90: =an_ni -> 10179.92 | E90: =E88*nioi -> 13017.65 | F90: =F88*nioi -> 13776.713 | G90: =G88*nioi -> 13555.564
A91: 稀釋股數 | B91: 百萬股 | C91: =a25_sh -> 808 | D91: =an_sh -> 797.79937 | E91: =$D91*(1-bb)^1 -> 789.82138 | F91: =$D91*(1-bb)^2 -> 781.92317 | G91: =$D91*(1-bb)^3 -> 774.10393
A92: non-GAAP 稀釋 EPS | B92: US$ | C92: =a25_eps -> 9.42 | D92: =an_eps -> 12.76 | E92: =E90/E91 -> 16.481764 | F92: =F90/F91 -> 17.619011 | G92: =G90/G91 -> 17.511297 | H92: FY2026＝前三季實績 EPS 合計＋第四季指引 EPS
A93: 半導體系統 ÷ FY 晶圓前段市場（隱含份額） | B93: % | D93: =D80/1000/(D75+D76+D77) -> 0.17408836 | E93: =E80/1000/(E75+E76+E77) -> 0.1740321 | F93: =F80/1000/(F75+F76+F77) -> 0.17402204 | G93: =G80/1000/(G75+G76+G77) -> 0.17402204 | H93: 檢驗用；FY2027 起等於 FY2026 份額 × 份額係數 × 組合效果
A96: 情境 C：設備市場 2028 −20%、2029 持平；關係企業規則恢復；AGS、顯示器放緩
A97: 項目 | B97: 單位 | C97: 2025 | D97: 2026 | E97: 2027 | F97: 2028 | G97: 2029 | H97: 說明
A98: A. 市場（日曆年 CY，US$B；讀 In 頁的設備市場成品）
A99: 晶圓代工、邏輯與其他 CY | B99: US$B | C99: =laC_25+loC_25+ofC_25 -> 78.348121 | D99: =laC_26+loC_26+ofC_26 -> 99.287198 | E99: =laC_27+loC_27+ofC_27 -> 116.28871 | F99: =laC_28+loC_28+ofC_28 -> 93.030967 | G99: =laC_29+loC_29+ofC_29 -> 93.030967
A100: DRAM（含 HBM）CY | B100: US$B | C100: =drC_25 -> 26.376109 | D100: =drC_26 -> 39.365947 | E100: =drC_27 -> 53.258733 | F100: =drC_28 -> 42.606986 | G100: =drC_29 -> 42.606986
A101: NAND CY | B101: US$B | C101: =ndC_25 -> 12.172602 | D101: =ndC_26 -> 17.503905 | E101: =ndC_27 -> 23.248027 | F101: =ndC_28 -> 18.598422 | G101: =ndC_29 -> 18.598422
A102: B. 會計年度（FY；FY(t)＝fyw×CY(t−1)＋(1−fyw)×CY(t)）
A103: 晶圓代工、邏輯與其他 FY | B103: US$B | D103: =fyw*C99+(1-fyw)*D99 -> 95.797352 | E103: =fyw*D99+(1-fyw)*E99 -> 113.45512 | F103: =fyw*E99+(1-fyw)*F99 -> 96.907258 | G103: =fyw*F99+(1-fyw)*G99 -> 93.030967
A104: DRAM（含 HBM）FY | B104: US$B | D104: =fyw*C100+(1-fyw)*D100 -> 37.200974 | E104: =fyw*D100+(1-fyw)*E100 -> 50.943268 | F104: =fyw*E100+(1-fyw)*F100 -> 44.382277 | G104: =fyw*F100+(1-fyw)*G100 -> 42.606986
A105: NAND FY | B105: US$B | D105: =fyw*C101+(1-fyw)*D101 -> 16.615355 | E105: =fyw*D101+(1-fyw)*E101 -> 22.290674 | F105: =fyw*E101+(1-fyw)*F101 -> 19.373356 | G105: =fyw*F101+(1-fyw)*G101 -> 18.598422
A106: 半導體系統需求指數（FY2026＝1；以 FY2026 終端市場權重加權） | B106: x | D106: =m_fl*D103/$D103+m_dr*D104/$D104+m_nd*D105/$D105 -> 1 | E106: =m_fl*E103/$D103+m_dr*E104/$D104+m_nd*E105/$D105 -> 1.2474042 | F106: =m_fl*F103/$D103+m_dr*F104/$D104+m_nd*F105/$D105 -> 1.0734425 | G106: =m_fl*G103/$D103+m_dr*G104/$D104+m_nd*G105/$D105 -> 1.0305048 | H106: Σ 權重 × FY 市場 ÷ FY2026 市場
A107: C. 損益（US$M；FY2025 實績、FY2026 錨點＝前三季實績＋第四季指引、FY2027 起模型）
A108: 半導體系統營收 | B108: US$M | C108: =a25_ss -> 21438.543 | D108: =an_ss -> 26046 | E108: =$D108*E106*sf -> 32489.889 | F108: =$D108*F106*sf -> 27958.884 | G108: =$D108*G106*sf -> 26840.529 | H108: FY2027 起＝FY2026 錨點 × 需求指數 × 份額係數
A109: AGS 服務營收 | B109: US$M | C109: =a25_ags -> 5744.1967 | D109: =an_ags -> 6845 | E109: =D109*(1+g_ags_C) -> 7324.15 | F109: =E109*(1+g_ags_C) -> 7836.8405 | G109: =F109*(1+g_ags_C) -> 8385.4193
A110: 其他（含顯示器）營收 | B110: US$M | C110: =a25_oth -> 1185.2601 | D110: =an_oth -> 1396 | E110: =D110*(1+g_oth_C) -> 1256.4 | F110: =E110*(1+g_oth_C) -> 1130.76 | G110: =F110*(1+g_oth_C) -> 1017.684
A111: 出口管制與中國調整 | B111: US$M | C111: 0 | D111: 0 | E111: =-aff_hit*aff_C-0*cn_sh*(E108+E109) -> -600 | F111: =-aff_hit*aff_C-0*cn_sh*(F108+F109) -> -600 | G111: =-aff_hit*aff_C-0*cn_sh*(G108+G109) -> -600 | H111: 關係企業規則恢復（情境 C 或 Sens）；中國下修只在 Sens
A112: 營收 | B112: US$M | C112: =C108+C109+C110+C111 -> 28368 | D112: =D108+D109+D110+D111 -> 34287 | E112: =E108+E109+E110+E111 -> 40470.439 | F112: =F108+F109+F110+F111 -> 36326.485 | G112: =G108+G109+G110+G111 -> 35643.632
A113: non-GAAP 毛利率 | B113: % | C113: =a25_gp/a25_rev -> 0.48783319 | D113: =an_gp/an_rev -> 0.50041858 | E113: =1-(cF+cv*E112)/E112 -> 0.50963452 | F113: =1-(cF+cv*F112)/F112 -> 0.50380503 | G113: =1-(cF+cv*G112)/G112 -> 0.50271435 | H113: 營業成本＝固定＋變動×營收（兩點推導）
...

Sheet Val
A1: Val — P/E 估值（美元；non-GAAP EPS）。跨公司規則：合理倍數＝10 年（2016–2025 年底）P/E 的分位，依循環位置：見頂年 25 分位、中段中位數、谷底 75 分位。循環位置依設備股共用規則（見第 4 節）。本版未做先驗，無 Andy 合理 P/E 對照
A2: P/E 定義（自算）：日曆年底收盤價（未調整股利）÷ 當年 10 月結束的會計年度 FY(t) 的 non-GAAP 稀釋 EPS（FY(t) 有 10/12 落在日曆年 t，與模型對 FY2027 EPS 套用倍數的口徑一致）；GAAP 口徑另列對照
A3: 目標價（DCF 與 Comparable 加權）：見本頁第 102 列起「0. 目標價」（估值 v2 新增，放在既有內容之後以免位移既有列）；原「0. 目標價與上檔空間」改名為「舊法：規則值情境加權（參考）」
A4: 1. 公司公布 EPS（會計年度，美元）— 兩個口徑、兩個來源
A5: 會計年度（10 月底結束） | B5: non-GAAP 稀釋 EPS（公司新聞稿） | C5: GAAP 稀釋 EPS（公司新聞稿） | D5: GAAP EPS（macrotrends） | E5: GAAP 兩來源差距 | F5: 標記 | G5: 說明
A6: FY2016 | B6: 1.75 | C6: 1.54 | D6: 1.54 | E6: =D6/C6-1 -> 0 | F6: Verified | G6: 公司 FY2016 Q4 新聞稿（SEC 8-K 2016-11）
A7: FY2017 | B7: 3.25 | C7: 3.17 | D7: 3.25 | E7: =D7/C7-1 -> 0.025236593 | F7: Verified | G7: 公司 FY2018 Q4 新聞稿（FY2017 比較數）；macrotrends 為 ASC 606 追溯重編後
A8: FY2018 | B8: 4.45 | C8: 3.23 | D8: 2.96 | E8: =D8/C8-1 -> -0.083591331 | F8: Verified | G8: 公司 FY2018 Q4 新聞稿；macrotrends 為 ASC 606 追溯重編後（FY2019 採用）
A9: FY2019 | B9: 3.04 | C9: 2.86 | D9: 2.86 | E9: =D9/C9-1 -> 0 | F9: Verified | G9: 公司 FY2020 Q4 新聞稿（FY2019 比較數）
A10: FY2020 | B10: 4.17 | C10: 3.92 | D10: 3.92 | E10: =D10/C10-1 -> 0 | F10: Verified | G10: 公司 FY2020 Q4 新聞稿
A11: FY2021 | B11: 6.84 | C11: 6.4 | D11: 6.4 | E11: =D11/C11-1 -> 0 | F11: Verified | G11: 公司 FY2021 Q4 新聞稿
A12: FY2022 | B12: 7.7 | C12: 7.44 | D12: 7.44 | E12: =D12/C12-1 -> 0 | F12: Verified | G12: 公司 FY2023 Q4 新聞稿（FY2022 比較數）
A13: FY2023 | B13: 8.05 | C13: 8.11 | D13: 8.11 | E13: =D13/C13-1 -> 0 | F13: Verified | G13: 公司 FY2023 Q4 新聞稿
A14: FY2024 | B14: 8.65 | C14: 8.61 | D14: 8.61 | E14: =D14/C14-1 -> 0 | F14: Verified | G14: 公司 FY2025 Q4 新聞稿（FY2024 比較數）
A15: FY2025 | B15: 9.42 | C15: 8.66 | D15: 8.66 | E15: =D15/C15-1 -> 0 | F15: Verified | G15: 公司 FY2025 Q4 新聞稿；stockanalysis 8.66
A16: 規則用 non-GAAP（模型 EPS、公司指引、共識同口徑）。non-GAAP 的第二來源：未找到（各資料商多列 GAAP）；GAAP 兩來源除 FY2017、FY2018（ASC 606 重編）外相同
A18: 2. 10 年 P/E（年底）
A19: 年底 | B19: 收盤價（未調整） | C19: non-GAAP EPS FY(t) | D19: GAAP EPS FY(t) | E19: P/E non-GAAP（自算） | F19: P/E GAAP（自算） | G19: companiesmarketcap P/E | H19: 自算 GAAP − cmc | I19: 股利調整後收盤（statmuse） | J19: 標記 | K19: 來源／說明 | L19: 輔助：不含 2018
A20: 2016-12 | B20: 32.27 | C20: =B6 -> 1.75 | D20: =C6 -> 1.54 | E20: =B20/C20 -> 18.44 | F20: =B20/D20 -> 20.954545 | G20: 18.6 | H20: =F20-G20 -> 2.3545455 | I20: 29.1 | J20: Verified／Derived | K20: 收盤價：digrin（Real price，未調整） | L20: =IF(A20="2018-12","",E20) -> 18.44
A21: 2017-12 | B21: 51.12 | C21: =B7 -> 3.25 | D21: =C7 -> 3.17 | E21: =B21/C21 -> 15.729231 | F21: =B21/D21 -> 16.126183 | G21: 14.7 | H21: =F21-G21 -> 1.426183 | I21: 46.52 | J21: Verified／Derived | K21: 收盤價：digrin（Real price，未調整） | L21: =IF(A21="2018-12","",E21) -> 15.729231
A22: 2018-12 | B22: 32.74 | C22: =B8 -> 4.45 | D22: =C8 -> 3.23 | E22: =B22/C22 -> 7.3573034 | F22: =B22/D22 -> 10.136223 | G22: 9.2 | H22: =F22-G22 -> 0.93622291 | I22: 30.27 | J22: Verified／Derived | K22: FY2018 non-GAAP EPS 4.45 為當年高峰（稅改後）→ P/E 7.4 為極端低值 | L22: =IF(A22="2018-12","",E22)
A23: 2019-12 | B23: 61.04 | C23: =B9 -> 3.04 | D23: =C9 -> 2.86 | E23: =B23/C23 -> 20.078947 | F23: =B23/D23 -> 21.342657 | G23: 20 | H23: =F23-G23 -> 1.3426573 | I23: 57.47 | J23: Verified／Derived | K23: 收盤價：digrin（Real price，未調整） | L23: =IF(A23="2018-12","",E23) -> 20.078947
A24: 2020-12 | B24: 86.3 | C24: =B10 -> 4.17 | D24: =C10 -> 3.92 | E24: =B24/C24 -> 20.695444 | F24: =B24/D24 -> 22.015306 | G24: 21 | H24: =F24-G24 -> 1.0153061 | I24: 82.31 | J24: Verified／Derived | K24: 收盤價：digrin（Real price，未調整） | L24: =IF(A24="2018-12","",E24) -> 20.695444
A25: 2021-12 | B25: 157.36 | C25: =B11 -> 6.84 | D25: =C11 -> 6.4 | E25: =B25/C25 -> 23.005848 | F25: =B25/D25 -> 24.5875 | G25: 23.5 | H25: =F25-G25 -> 1.0875 | J25: Verified／Derived | K25: 收盤價：digrin（Real price，未調整） | L25: =IF(A25="2018-12","",E25) -> 23.005848
A26: 2022-12 | B26: 97.38 | C26: =B12 -> 7.7 | D26: =C12 -> 7.44 | E26: =B26/C26 -> 12.646753 | F26: =B26/D26 -> 13.08871 | G26: 12.7 | H26: =F26-G26 -> 0.38870968 | J26: Verified／Derived | K26: 收盤價：digrin（Real price，未調整） | L26: =IF(A26="2018-12","",E26) -> 12.646753
A27: 2023-12 | B27: 162.07 | C27: =B13 -> 8.05 | D27: =C13 -> 8.11 | E27: =B27/C27 -> 20.132919 | F27: =B27/D27 -> 19.98397 | G27: 19.6 | H27: =F27-G27 -> 0.38397041 | J27: Verified／Derived | K27: 收盤價：digrin（Real price，未調整） | L27: =IF(A27="2018-12","",E27) -> 20.132919
A28: 2024-12 | B28: 162.63 | C28: =B14 -> 8.65 | D28: =C14 -> 8.61 | E28: =B28/C28 -> 18.801156 | F28: =B28/D28 -> 18.888502 | G28: 18.6 | H28: =F28-G28 -> 0.28850174 | J28: Verified／Derived | K28: 收盤價：digrin（Real price，未調整） | L28: =IF(A28="2018-12","",E28) -> 18.801156
A29: 2025-12 | B29: 256.99 | C29: =B15 -> 9.42 | D29: =C15 -> 8.66 | E29: =B29/C29 -> 27.281316 | F29: =B29/D29 -> 29.67552 | G29: 29.5 | H29: =F29-G29 -> 0.17551963 | I29: 256.08 | J29: Verified／Derived | K29: statmuse 2025-12-31 收盤 256.08（股利調整後）；digrin 未調整 256.99 | L29: =IF(A29="2018-12","",E29) -> 27.281316
A31: 收盤價來源1：digrin（AMAT Price History 的 Real price，未調整股利）；來源2：statmuse 年底收盤（股利調整後，2016–2020、2025）——兩者比值 0.90–1.00 隨年份遞增，符合股利調整，故未調整價可信；2021–2024 第二來源：未找到。companiesmarketcap 的年底 P/E 為 GAAP TTM 口徑，與自算 GAAP 差距見 H 欄（−1.0 至 +2.0）。
A33: 3. 分位（10 年）
A34: 統計 | B34: P/E non-GAAP（自算；規則用） | C34: P/E GAAP（自算；參考） | D34: cmc P/E（參考） | E34: 用途
A35: 25 分位 | B35: =PERCENTILE(E20:E29,0.25) -> 16.406923 | C35: =PERCENTILE(F20:F29,0.25) -> 16.816763 | D35: =PERCENTILE(G20:G29,0.25) -> 15.675 | E35: 見頂年
A36: 中位數 | B36: =PERCENTILE(E20:E29,0.5) -> 19.440052 | C36: =PERCENTILE(F20:F29,0.5) -> 20.469258 | D36: =PERCENTILE(G20:G29,0.5) -> 19.1 | E36: 中段
A37: 75 分位 | B37: =PERCENTILE(E20:E29,0.75) -> 20.554813 | C37: =PERCENTILE(F20:F29,0.75) -> 21.847144 | D37: =PERCENTILE(G20:G29,0.75) -> 20.75 | E37: 谷底
A38: 年數 | B38: =COUNT(E20:E29) -> 10 | C38: =COUNT(F20:F29) -> 10 | D38: =COUNT(G20:G29) -> 10
A40: 敏感度：去掉 2018 年（non-GAAP 極端低值 7.4）後的分位（9 年）
A41: 統計 | B41: P/E non-GAAP（不含 2018）
A42: 25 分位 | B42: =PERCENTILE(L20:L29,0.25) -> 18.44
A43: 中位數 | B43: =PERCENTILE(L20:L29,0.5) -> 20.078947
A44: 75 分位 | B44: =PERCENTILE(L20:L29,0.75) -> 20.695444
A46: 舊法：規則值情境加權（參考）（12 個月，情境加權；權重為 In 頁 tp_wA／tp_wB／tp_wC，Andy 可改）
A47: 規則值情境加權價（12 個月；參考） | B47: =tp_wA*B49+tp_wB*B50+tp_wC*B51 -> 309.83445 | E47: ＝權重 A × 情境 A 隱含價＋權重 B × 情境 B 隱含價＋權重 C × 情境 C 隱含價（US$）
A48: 相對現價（規則值情境加權價 ÷ 現價 − 1） | B48: =B47/px-1 -> -0.17868081 | E48: 相對「現價（stockanalysis 2026-10-23 收盤）」
A49: 情境 A 隱含價（樂觀） | B49: =F68 -> 323.91381 | E49: ＝規則值隱含股價 F68（情境 A：設備市場續增（2028 +12.7%、2029 +5.9%；markets/equipment））
A50: 情境 B 隱含價（基準） | B50: =F75 -> 320.40635 | E50: ＝規則值隱含股價 F75（情境 B：設備市場 2028 持平、2029 −5%；AGS 成長放緩）
A51: 情境 C 隱含價（下檔） | B51: =F82 -> 262.28567 | E51: ＝規則值隱含股價 F82（情境 C：設備市場 2028 −20%、2029 持平；關係企業規則恢復；AGS、顯示器放緩）
A52: 情境權重 A／B／C | B52: =tp_wA -> 0.3 | C52: =tp_wB -> 0.5 | D52: =tp_wC -> 0.2 | E52: In 頁輸入（Assumed，Andy 可改）：B 欄＝情境 A、C 欄＝情境 B、D 欄＝情境 C
A53: 規則值方法 | B53: P/E 規則值：各情境 FY2027 non-GAAP EPS × 2016–2025 年底 non-GAAP P/E（自算）依設備股共用循環規則取分位（見頂＝25 分位、中段＝中位數、谷底＝75 分位；見頂年讀 markets/equipment）。隱含價約為 FY2027 年底價、未折現，作 12 個月目標價的近似；情境 A／B／C 即本模型三個設備市場情境（A 最高、C 最低）。偏誤：十年倍數含 2018 年極端低值（7.4x），去掉後分位略高（第 3 節敏感度），目標價可能略偏低。
A59: 4. 循環位置（設備股共用規則；見頂年度讀設備市場模型，不在本模型另訂）
A60: 循環位置（設備股共用規則）：各情境的見頂年度取自設備市場模型（markets/equipment 的 Mkt 頁「見頂年度」：A 2029、B 2028、C 2027）；會計年度 FY(t) 對照日曆年 t（FY(t) 有 3/4 落在 t 年）：t 早於見頂年＝中段（中位數）、等於＝見頂（25 分位）、晚於＝谷底（75 分位）。AMAT 的 FY(t)（約 t−1 年 11 月～t 年 10 月）有 10/12 落在日曆年 t，直接對照 t，不平移
A61: 情境 | B61: 設備市場見頂年度 | C61: FY2027 對照日曆年 | D61: 判定 | E61: 倍數 | F61: 規則
A62: A | B62: =pk_A -> 2029 | C62: 2027 | D62: =IF(C62<pk_A,"中段",IF(C62=pk_A,"見頂","谷底")) -> 中段 | E62: =IF(D62="見頂",pe_peak,IF(D62="谷底",pe_trough,pe_mid)) -> 19.440052 | F62: tools/cycle_position.py
A63: B | B63: =pk_B -> 2028 | C63: 2027 | D63: =IF(C63<pk_B,"中段",IF(C63=pk_B,"見頂","谷底")) -> 中段 | E63: =IF(D63="見頂",pe_peak,IF(D63="谷底",pe_trough,pe_mid)) -> 19.440052 | F63: tools/cycle_position.py
A64: C | B64: =pk_C -> 2027 | C64: 2027 | D64: =IF(C64<pk_C,"中段",IF(C64=pk_C,"見頂","谷底")) -> 見頂 | E64: =IF(D64="見頂",pe_peak,IF(D64="谷底",pe_trough,pe_mid)) -> 16.406923 | F64: tools/cycle_position.py
A66: 5. 隱含股價（美元；約 FY2027 年底，未折現）：規則值＝FY2027 EPS × 依循環位置的倍數；其餘倍數僅供參考
A67: 情境 | B67: EPS 年度 | C67: EPS | D67: 倍數類型 | E67: 倍數 | F67: 隱含股價 | G67: 相對現價 | H67: 備註
A68: A | B68: FY2027 | C68: =PL!E12 -> 16.662189 | D68: ="規則值："&D62 -> 規則值：中段 | E68: =E62 -> 19.440052 | F68: =C68*E68 -> 323.91381 | G68: =F68/px-1 -> -0.1413588
A69: A | B69: FY2027 | C69: =PL!E12 -> 16.662189 | D69: 參考：25 分位 | E69: =pe_peak -> 16.406923 | F69: =C69*E69 -> 273.37525 | G69: =F69/px-1 -> -0.27532805
A70: A | B70: FY2027 | C70: =PL!E12 -> 16.662189 | D70: 參考：中位數 | E70: =pe_mid -> 19.440052 | F70: =C70*E70 -> 323.91381 | G70: =F70/px-1 -> -0.1413588
A71: A | B71: FY2027 | C71: =PL!E12 -> 16.662189 | D71: 參考：75 分位 | E71: =pe_trough -> 20.554813 | F71: =C71*E71 -> 342.48816 | G71: =F71/px-1 -> -0.092121298
A72: A | B72: FY2028 | C72: =PL!F12 -> 19.846542 | D72: 參考：25 分位 | E72: =pe_peak -> 16.406923 | F72: =C72*E72 -> 325.62068 | G72: =F72/px-1 -> -0.13683416
A73: A | B73: FY2028 | C73: =PL!F12 -> 19.846542 | D73: 參考：中位數 | E73: =pe_mid -> 19.440052 | F73: =C73*E73 -> 385.8178 | G73: =F73/px-1 -> 0.0227383
A74: A | B74: FY2028 | C74: =PL!F12 -> 19.846542 | D74: 參考：75 分位 | E74: =pe_trough -> 20.554813 | F74: =C74*E74 -> 407.94194 | G74: =F74/px-1 -> 0.081385705
A75: B | B75: FY2027 | C75: =PL!E22 -> 16.481764 | D75: ="規則值："&D63 -> 規則值：中段 | E75: =E63 -> 19.440052 | F75: =C75*E75 -> 320.40635 | G75: =F75/px-1 -> -0.15065648
A76: B | B76: FY2027 | C76: =PL!E22 -> 16.481764 | D76: 參考：25 分位 | E76: =pe_peak -> 16.406923 | F76: =C76*E76 -> 270.41504 | G76: =F76/px-1 -> -0.28317507
A77: B | B77: FY2027 | C77: =PL!E22 -> 16.481764 | D77: 參考：中位數 | E77: =pe_mid -> 19.440052 | F77: =C77*E77 -> 320.40635 | G77: =F77/px-1 -> -0.15065648
A78: B | B78: FY2027 | C78: =PL!E22 -> 16.481764 | D78: 參考：75 分位 | E78: =pe_trough -> 20.554813 | F78: =C78*E78 -> 338.77957 | G78: =F78/px-1 -> -0.10195214
A79: B | B79: FY2028 | C79: =PL!F22 -> 17.619011 | D79: 參考：25 分位 | E79: =pe_peak -> 16.406923 | F79: =C79*E79 -> 289.07376 | G79: =F79/px-1 -> -0.23371393
A80: B | B80: FY2028 | C80: =PL!F22 -> 17.619011 | D80: 參考：中位數 | E80: =pe_mid -> 19.440052 | F80: =C80*E80 -> 342.51449 | G80: =F80/px-1 -> -0.092051517
A81: B | B81: FY2028 | C81: =PL!F22 -> 17.619011 | D81: 參考：75 分位 | E81: =pe_trough -> 20.554813 | F81: =C81*E81 -> 362.15547 | G81: =F81/px-1 -> -0.039986562
A82: C | B82: FY2027 | C82: =PL!E32 -> 15.98628 | D82: ="規則值："&D64 -> 規則值：見頂 | E82: =E64 -> 16.406923 | F82: =C82*E82 -> 262.28567 | G82: =F82/px-1 -> -0.30472467
A83: C | B83: FY2027 | C83: =PL!E32 -> 15.98628 | D83: 參考：25 分位 | E83: =pe_peak -> 16.406923 | F83: =C83*E83 -> 262.28567 | G83: =F83/px-1 -> -0.30472467
A84: C | B84: FY2027 | C84: =PL!E32 -> 15.98628 | D84: 參考：中位數 | E84: =pe_mid -> 19.440052 | F84: =C84*E84 -> 310.77411 | G84: =F84/px-1 -> -0.17618993
A85: C | B85: FY2027 | C85: =PL!E32 -> 15.98628 | D85: 參考：75 分位 | E85: =pe_trough -> 20.554813 | F85: =C85*E85 -> 328.59499 | G85: =F85/px-1 -> -0.12894977
A86: C | B86: FY2028 | C86: =PL!F32 -> 13.949788 | D86: 參考：25 分位 | E86: =pe_peak -> 16.406923 | F86: =C86*E86 -> 228.8731 | G86: =F86/px-1 -> -0.39329577
A87: C | B87: FY2028 | C87: =PL!F32 -> 13.949788 | D87: 參考：中位數 | E87: =pe_mid -> 19.440052 | F87: =C87*E87 -> 271.1846 | G87: =F87/px-1 -> -0.28113507
A88: C | B88: FY2028 | C88: =PL!F32 -> 13.949788 | D88: 參考：75 分位 | E88: =pe_trough -> 20.554813 | F88: =C88*E88 -> 286.73528 | G88: =F88/px-1 -> -0.23991284
A90: 6. 目前倍數
A91: 項目 | B91: A | C91: B | D91: C | E91: 備註
A92: 現價（stockanalysis 2026-10-23 收盤） | B92: =px -> 377.24
A93: 遠期 P/E：stockanalysis | B93: =sa_fpe -> 21.39 | E93: stockanalysis 顯示 21.39x
A94: 現價 ÷ 共識 FY2027 EPS（18.49） | B94: =px/cons_eps27 -> 20.40238 | E94: 與 stockanalysis 遠期 P/E 接近（其遠期 EPS 為未來 12 月或 FY2027 共識）
A95: 現價 ÷ 近 12 月 non-GAAP EPS（FY25 Q4＋FY26 Q1–Q3） | B95: =px/(Q!E15+SUM(Q!G15:I15)) -> 34.577452 | E95: stockanalysis TTM P/E 32.54 為 GAAP 口徑
A96: 現價 ÷ FY2026 EPS（錨點） | B96: =px/PL!D12 -> 29.564263 | C96: =px/PL!D22 -> 29.564263 | D96: =px/PL!D32 -> 29.564263 | E96: 三情境相同
A97: 現價 ÷ FY2027 EPS（模型） | B97: =px/PL!E12 -> 22.640483 | C97: =px/PL!E22 -> 22.888326 | D97: =px/PL!E32 -> 23.597735
A98: 現價 ÷ FY2028 EPS（模型） | B98: =px/PL!F12 -> 19.007846 | C98: =px/PL!F22 -> 21.410963 | D98: =px/PL!F32 -> 27.042704
A99: 現價 ÷ FY2027 EPS（A）÷ 規則倍數（A） | B99: =B97/E62 -> 1.1646308 | E99: >1＝現價高於規則給的倍數
A102: 0. 目標價
A103: 0.1 DCF（股東權益現金流，FY2027–FY2032 明確期＋FY2032 後永續）
A104: 項目 | B104: A（順利） | C104: B（平平） | D104: C（不如預期） | E104: 說明
A105: 情境 EPS（FY2027–FY2032） | E105: PL 頁延伸區塊；FY2030 起為收斂法
A106: FY2027 | B106: =PL!E132 -> 16.662189 | C106: =PL!E139 -> 16.481764 | D106: =PL!E146 -> 15.98628
A107: FY2028 | B107: =PL!F132 -> 19.846542 | C107: =PL!F139 -> 17.619011 | D107: =PL!F146 -> 13.949788
A108: FY2029 | B108: =PL!G132 -> 22.08211 | C108: =PL!G139 -> 17.511297 | D108: =PL!G146 -> 13.724849
A109: FY2030 | B109: =PL!H132 -> 23.702396 | C109: =PL!H139 -> 16.751253 | D109: =PL!H146 -> 12.536387
A110: FY2031 | B110: =PL!I132 -> 25.283055 | C110: =PL!I139 -> 16.26036 | D110: =PL!I146 -> 11.509193
A111: FY2032 | B111: =PL!J132 -> 26.800038 | C111: =PL!J139 -> 16.007283 | D111: =PL!J146 -> 10.601266
A112: 股東現金流＝EPS ×（1 − tp_g ÷ tp_roe） | E112: 模型無折舊與資本支出項目，故不用（淨利＋折舊－資本支出）；設備股資本支出低（輕資產），此式偏誤小
A113: 再投資率（tp_g ÷ tp_roe，上限 0.8） | B113: =MIN(tp_g/tp_roe,0.8) -> 0.096649485 | E113: ROE 為近三年平均（In 頁 tp_roe）
A114: FY2027 | B114: =B106*(1-$B$113) -> 15.051797 | C114: =C106*(1-$B$113) -> 14.88881 | D114: =D106*(1-$B$113) -> 14.441214
...

Sheet Recon
A1: Recon — 本模型 vs 共識、公司說法、SEMI、第四季年化。只作事後對照，不為對上數字而調整參數。差距 > 10% 的原因見 README
A3: 項目 | B3: 對照值 | C3: 模型 A | D3: 差距 A | E3: 模型 B | F3: 差距 B | G3: 模型 C | H3: 差距 C | I3: 對照來源 | J3: 說明
A4: A. 共識（stockanalysis，資料更新 2026-10-16；只作對照）
A5: FY2026 營收（錨點） | B5: =cons_rev26 -> 34260 | C5: =PL!D5 -> 34287 | D5: =C5/B5-1 -> 0.00078809107 | E5: =PL!D15 -> 34287 | F5: =E5/B5-1 -> 0.00078809107 | G5: =PL!D25 -> 34287 | H5: =G5/B5-1 -> 0.00078809107 | I5: stockanalysis | J5: 錨點＝前三季實績＋第四季指引中點，非模型預測
A6: FY2026 non-GAAP EPS（錨點） | B6: =cons_eps26 -> 12.79 | C6: =PL!D12 -> 12.76 | D6: =C6/B6-1 -> -0.0023455825 | E6: =PL!D22 -> 12.76 | F6: =E6/B6-1 -> -0.0023455825 | G6: =PL!D32 -> 12.76 | H6: =G6/B6-1 -> -0.0023455825 | I6: stockanalysis
A7: FY2027 營收 | B7: =cons_rev27 -> 46370 | C7: =PL!E5 -> 41757.639 | D7: =C7/B7-1 -> -0.099468636 | E7: =PL!E15 -> 41414.039 | F7: =E7/B7-1 -> -0.1068786 | G7: =PL!E25 -> 40470.439 | H7: =G7/B7-1 -> -0.12722796 | I7: stockanalysis
A8: FY2027 non-GAAP EPS | B8: =cons_eps27 -> 18.49 | C8: =PL!E12 -> 16.662189 | D8: =C8/B8-1 -> -0.098854056 | E8: =PL!E22 -> 16.481764 | F8: =E8/B8-1 -> -0.10861199 | G8: =PL!E32 -> 15.98628 | H8: =G8/B8-1 -> -0.13540941 | I8: stockanalysis
A9: B. 第四季年化（FY2026 Q4 指引 × 4）vs FY2027 模型
A10: 半導體系統 | B10: =g_ss_q4*4 -> 31600 | C10: =PL!E6 -> 32489.889 | D10: =C10/B10-1 -> 0.028161055 | E10: =PL!E16 -> 32489.889 | F10: =E10/B10-1 -> 0.028161055 | G10: =PL!E26 -> 32489.889 | H10: =G10/B10-1 -> 0.028161055 | I10: 公司 Q4 指引 | J10: FY2027 模型若接近第四季年化，代表 FY2027 各季大致持平於第四季水準
A11: 營收 | B11: =g_rev_q4*4 -> 41000 | C11: =PL!E5 -> 41757.639 | D11: =C11/B11-1 -> 0.018479008 | E11: =PL!E15 -> 41414.039 | F11: =E11/B11-1 -> 0.01009852 | G11: =PL!E25 -> 40470.439 | H11: =G11/B11-1 -> -0.012916114 | I11: 公司 Q4 指引
A12: C. 市場與公司說法
A13: AGS FY2026 年增（重編口徑）vs 公司 CY2026「>20%」 | B13: 0.2 | C13: =PL!D53/PL!C53-1 -> 0.19163746 | D13: =C13-B13 -> -0.0083625384 | E13: =PL!D81/PL!C81-1 -> 0.19163746 | F13: =E13-B13 -> -0.0083625384 | G13: =PL!D109/PL!C109-1 -> 0.19163746 | H13: =G13-B13 -> -0.0083625384 | I13: 公司 Q3 FY26 法說 | J13: FY 與 CY 口徑差一季
A14: AI 相關占 2025→2027 設備增量：設備市場模型 vs 公司「約 80%」 | B14: =co_ai27 -> 0.8 | C14: =ai_inc27 -> 0.62686064 | D14: =C14-B14 -> -0.17313936 | E14: =ai_inc27 -> 0.62686064 | F14: =E14-B14 -> -0.17313936 | G14: =ai_inc27 -> 0.62686064 | H14: =G14-B14 -> -0.17313936 | I14: 公司 Q3 FY26 法說；markets/equipment | J14: 公司口徑含先進封裝與先進代工邏輯、DRAM；模型 63% 較低，代表公司看的成長更集中在 AI 相關（只作對照，不改上游）
A15: D. 其他資訊（非對帳）
A16: AMAT 半導體系統 FY2026 ÷ SEMI 晶圓前段 CY2026（隱含份額） | B16: =semi_wfe26 -> 143.9 | C16: =PL!D52/1000/semi_wfe26 -> 0.18100069 | I16: SEMI 2026-07（equipment 成品） | J16: 對設備市場模型的 FY 口徑為 17.4%（Units 頁）；SEMI 較低，故對 SEMI 的份額較高；AMAT 半導體系統另含先進封裝等
A17: FY2026 前三季營收 ÷ FY2026 錨點 | C17: =SUM(Q!G7:I7)/an_rev -> 0.70105288 | J17: 第四季指引占全年 30%：AI 需求逐季上升
A18: FY2027 營收年增（情境 A） | C18: =PL!E5/PL!D5-1 -> 0.21788548 | J18: 共識隱含 FY2027 年增見下一列
A19: 共識隱含 FY2027 營收年增 | C19: =cons_rev27/cons_rev26-1 -> 0.35347344

Sheet Sens
A1: Sens — 一次動一個輸入（情境 A）：對 FY2027、FY2028 營收與 EPS 的影響。每個案例是一個完整的推導區塊（本頁下方，與 PL 同一引擎）
A3: 案例 | B3: 設定 | C3: FY2027 營收 US$M | D3: FY2027 EPS US$ | E3: 相對基準 | F3: FY2028 營收 US$M | G3: FY2028 EPS US$ | H3: 相對基準
A4: 基準（情境 A） | B4: PL 區塊 A | C4: =PL!E56 -> 41757.639 | D4: =PL!E64 -> 16.662189 | E4: =D4/D$4-1 -> 0 | F4: =PL!F56 -> 47443.964 | G4: =PL!F64 -> 19.846542 | H4: =G4/G$4-1 -> 0
A5: 份額係數 0.95 | B5: AMAT 份額 −5%（中國國產替代、競爭） | C5: =E76 -> 40133.145 | D5: =E84 -> 15.809167 | E5: =D5/D$4-1 -> -0.051195059 | F5: =F76 -> 45594.191 | G5: =F84 -> 18.865415 | H5: =G5/G$4-1 -> -0.049435639
A6: 份額係數 1.05 | B6: 份額 +5%（環繞式閘極、背面供電、先進封裝） | C6: =E108 -> 43382.134 | D6: =E116 -> 17.51521 | E6: =D6/D$4-1 -> 0.051195059 | F6: =F108 -> 49293.736 | G6: =F116 -> 20.827668 | H6: =G6/G$4-1 -> 0.049435639
A7: 第四季 DRAM 占比 26% | B7: FY2026 終端權重偏向代工邏輯 | C7: =E140 -> 41699.153 | D7: =E148 -> 16.631477 | E7: =D7/D$4-1 -> -0.001843158 | F7: =F140 -> 47370.672 | G7: =F148 -> 19.807668 | H7: =G7/G$4-1 -> -0.0019587365
A8: 第四季 DRAM 占比 34% | B8: 權重偏向 DRAM | C8: =E172 -> 41816.125 | D8: =E180 -> 16.6929 | E8: =D8/D$4-1 -> 0.001843158 | F8: =F172 -> 47517.255 | G8: =F180 -> 19.885416 | H8: =G8/G$4-1 -> 0.0019587365
A9: 會計年度權重 1/12 | B9: FY 幾乎等於日曆年 | C9: =E204 -> 41569.87 | D9: =E212 -> 16.563591 | E9: =D9/D$4-1 -> -0.0059174631 | F9: =F204 -> 46975.953 | G9: =F212 -> 19.598307 | H9: =G9/G$4-1 -> -0.012507696
A10: 會計年度權重 3/12 | B10: 設備出貨領先一季 | C10: =E236 -> 41954.036 | D10: =E244 -> 16.765317 | E10: =D10/D$4-1 -> 0.0061893455 | F10: =F236 -> 47935.385 | G10: =F244 -> 20.107193 | H10: =G10/G$4-1 -> 0.013133362
A11: 營業成本變動比例 75% | B11: 固定成本較多 → 毛利率對營收更敏感 | C11: =E268 -> 41757.639 | D11: =E276 -> 17.492673 | E11: =D11/D$4-1 -> 0.04984245 | F11: =F268 -> 47443.964 | G11: =F276 -> 21.041668 | H11: =G11/G$4-1 -> 0.06021837
A12: 營業成本變動比例 95% | B12: 幾乎全變動 → 毛利率接近持平 | C12: =E300 -> 41757.639 | D12: =E308 -> 15.949837 | E12: =D12/D$4-1 -> -0.042752557 | F12: =F300 -> 47443.964 | G12: =F308 -> 18.821417 | H12: =G12/G$4-1 -> -0.051652543
A13: 營業費用變動比例 35% | B13: FY2025 營業費用中變動部分 35% | C13: =E332 -> 41757.639 | D13: =E340 -> 17.096419 | E13: =D13/D$4-1 -> 0.026060803 | F13: =F332 -> 47443.964 | G13: =F340 -> 20.47143 | H13: =G13/G$4-1 -> 0.031485994
A14: 營業費用變動比例 75% | B14: 變動 75%（費用隨營收擴張） | C14: =E364 -> 41757.639 | D14: =E372 -> 15.975731 | E14: =D14/D$4-1 -> -0.041198495 | F14: =F364 -> 47443.964 | G14: =F372 -> 18.858681 | H14: =G14/G$4-1 -> -0.049774965
A15: AGS 成長 11% | B15: 情境 A −4 個百分點 | C15: =E396 -> 41483.839 | D15: =E404 -> 16.518416 | E15: =D15/D$4-1 -> -0.0086286579 | F15: =F396 -> 46825.176 | G15: =F404 -> 19.518334 | H15: =G15/G$4-1 -> -0.016537266
A16: AGS 成長 19% | B16: 情境 A +4 個百分點 | C16: =E428 -> 42031.439 | D16: =E436 -> 16.805961 | E16: =D16/D$4-1 -> 0.0086286579 | F16: =F428 -> 48084.656 | G16: =F436 -> 20.186367 | H16: =G16/G$4-1 -> 0.017122656
A17: 其他 −10%／年 | B17: 顯示器下滑 | C17: =E460 -> 41618.039 | D17: =E468 -> 16.588885 | E17: =D17/D$4-1 -> -0.004399418 | F17: =F460 -> 47178.724 | G17: =F468 -> 19.705857 | H17: =G17/G$4-1 -> -0.007088606
A18: 其他 +10%／年 | C18: =E492 -> 41897.239 | D18: =E500 -> 16.735492 | E18: =D18/D$4-1 -> 0.004399418 | F18: =F492 -> 47737.124 | G18: =F500 -> 20.002035 | H18: =G18/G$4-1 -> 0.007834775
A19: 淨利÷營業利益 0.85 | B19: 稅率上升 | C19: =E524 -> 41757.639 | D19: =E532 -> 15.940898 | E19: =D19/D$4-1 -> -0.043289076 | F19: =F524 -> 47443.964 | G19: =F532 -> 18.987403 | H19: =G19/G$4-1 -> -0.043289076
A20: 淨利÷營業利益 FY2026 錨點值 | B20: 含稅務利益 | C20: =E556 -> 41757.639 | D20: =E564 -> 16.857765 | E20: =D20/D$4-1 -> 0.011737766 | F20: =F556 -> 47443.964 | G20: =F564 -> 20.079496 | H20: =G20/G$4-1 -> 0.011737766
A21: 淨回購 0%／年 | C21: =E588 -> 41757.639 | D21: =E596 -> 16.495567 | E21: =D21/D$4-1 -> -0.01 | F21: =F588 -> 47443.964 | G21: =F596 -> 19.451595 | H21: =G21/G$4-1 -> -0.0199
A22: 淨回購 2.5%／年 | C22: =E620 -> 41757.639 | D22: =E628 -> 16.91853 | E22: =D22/D$4-1 -> 0.015384615 | F22: =F620 -> 47443.964 | G22: =F628 -> 20.461902 | H22: =G22/G$4-1 -> 0.031005917
A23: 關係企業規則恢復（US$600M／年） | B23: 情境 A 加上 C 的出口管制假設 | C23: =E652 -> 41157.639 | D23: =E660 -> 16.347129 | E23: =D23/D$4-1 -> -0.018908673 | F23: =F652 -> 46843.964 | G23: =F660 -> 19.528299 | H23: =G23/G$4-1 -> -0.016035152
A24: 關係企業規則恢復（US$900M／年） | B24: 影響 +50% | C24: =E684 -> 40857.639 | D24: =E692 -> 16.189599 | E24: =D24/D$4-1 -> -0.02836301 | F24: =F684 -> 46543.964 | G24: =F692 -> 19.369178 | H24: =G24/G$4-1 -> -0.024052727
A25: 中國營收 −20% | B25: 半導體系統＋AGS 中的中國部分 −20% | C25: =E716 -> 39511.613 | D25: =E724 -> 15.482801 | E25: =D25/D$4-1 -> -0.070782289 | F25: =F716 -> 44881.508 | G25: =F724 -> 18.487405 | H25: =G25/G$4-1 -> -0.068482285
A26: 中國營收 −40% | C26: =E748 -> 37265.587 | D26: =E756 -> 14.303413 | E26: =D26/D$4-1 -> -0.14156458 | F26: =F748 -> 42319.051 | G26: =F756 -> 17.128269 | H26: =G26/G$4-1 -> -0.13696457
A27: 設備市場情境 B | B27: 2028 持平、2029 −5%；AGS 11%、其他 −5% | C27: =PL!E84 -> 41414.039 | D27: =PL!E92 -> 16.481764 | E27: =D27/D$4-1 -> -0.010828367 | F27: =PL!F84 -> 43244.276 | G27: =PL!F92 -> 17.619011 | H27: =G27/G$4-1 -> -0.11223772
A28: 設備市場情境 C | B28: 2028 −20%、2029 持平；關係企業規則恢復；AGS 7%、其他 −10% | C28: =PL!E112 -> 40470.439 | D28: =PL!E120 -> 15.98628 | E28: =D28/D$4-1 -> -0.040565407 | F28: =PL!F112 -> 36326.485 | G28: =PL!F120 -> 13.949788 | H28: =G28/G$4-1 -> -0.29711743
A30: 讀法：FY2027 有 5/6 落在 CY2027，而設備市場三情境在 CY2027 以前相同，所以市場情境對 FY2027 影響小、對 FY2028 才明顯；對 FY2027 最敏感的是份額、營業成本與營業費用的固定／變動拆分、出口管制。
A60: 案例區塊：份額係數 0.95（情境 A）
A61: 項目 | B61: 單位 | C61: 2025 | D61: 2026 | E61: 2027 | F61: 2028 | G61: 2029 | H61: 說明
A62: A. 市場（日曆年 CY，US$B；讀 In 頁的設備市場成品）
A63: 晶圓代工、邏輯與其他 CY | B63: US$B | C63: =laA_25+loA_25+ofA_25 -> 78.348121 | D63: =laA_26+loA_26+ofA_26 -> 99.287198 | E63: =laA_27+loA_27+ofA_27 -> 116.28871 | F63: =laA_28+loA_28+ofA_28 -> 130.8864 | G63: =laA_29+loA_29+ofA_29 -> 139.39808
A64: DRAM（含 HBM）CY | B64: US$B | C64: =drA_25 -> 26.376109 | D64: =drA_26 -> 39.365947 | E64: =drA_27 -> 53.258733 | F64: =drA_28 -> 59.5609 | G64: =drA_29 -> 61.831293
A65: NAND CY | B65: US$B | C65: =ndA_25 -> 12.172602 | D65: =ndA_26 -> 17.503905 | E65: =ndA_27 -> 23.248027 | F65: =ndA_28 -> 26.181322 | G65: =ndA_29 -> 27.674313
A66: B. 會計年度（FY；FY(t)＝fyw×CY(t−1)＋(1−fyw)×CY(t)）
A67: 晶圓代工、邏輯與其他 FY | B67: US$B | D67: =fyw*C63+(1-fyw)*D63 -> 95.797352 | E67: =fyw*D63+(1-fyw)*E63 -> 113.45512 | F67: =fyw*E63+(1-fyw)*F63 -> 128.45346 | G67: =fyw*F63+(1-fyw)*G63 -> 137.97947
A68: DRAM（含 HBM）FY | B68: US$B | D68: =fyw*C64+(1-fyw)*D64 -> 37.200974 | E68: =fyw*D64+(1-fyw)*E64 -> 50.943268 | F68: =fyw*E64+(1-fyw)*F64 -> 58.510539 | G68: =fyw*F64+(1-fyw)*G64 -> 61.452894
A69: NAND FY | B69: US$B | D69: =fyw*C65+(1-fyw)*D65 -> 16.615355 | E69: =fyw*D65+(1-fyw)*E65 -> 22.290674 | F69: =fyw*E65+(1-fyw)*F65 -> 25.692439 | G69: =fyw*F65+(1-fyw)*G65 -> 27.425481
A70: 半導體系統需求指數（FY2026＝1；以 FY2026 終端市場權重加權） | B70: x | D70: =m_fl*D67/$D67+m_dr*D68/$D68+m_nd*D69/$D69 -> 1 | E70: =m_fl*E67/$D67+m_dr*E68/$D68+m_nd*E69/$D69 -> 1.2474042 | F70: =m_fl*F67/$D67+m_dr*F68/$D68+m_nd*F69/$D69 -> 1.420389 | G70: =m_fl*G67/$D67+m_dr*G68/$D68+m_nd*G69/$D69 -> 1.5140939 | H70: Σ 權重 × FY 市場 ÷ FY2026 市場
A71: C. 損益（US$M；FY2025 實績、FY2026 錨點＝前三季實績＋第四季指引、FY2027 起模型）
A72: 半導體系統營收 | B72: US$M | C72: =a25_ss -> 21438.543 | D72: =an_ss -> 26046 | E72: =$D72*E70*sf_lo -> 30865.395 | F72: =$D72*F70*sf_lo -> 35145.679 | G72: =$D72*G70*sf_lo -> 37464.286 | H72: FY2027 起＝FY2026 錨點 × 需求指數 × 份額係數
A73: AGS 服務營收 | B73: US$M | C73: =a25_ags -> 5744.1967 | D73: =an_ags -> 6845 | E73: =D73*(1+g_ags_A) -> 7871.75 | F73: =E73*(1+g_ags_A) -> 9052.5125 | G73: =F73*(1+g_ags_A) -> 10410.389
A74: 其他（含顯示器）營收 | B74: US$M | C74: =a25_oth -> 1185.2601 | D74: =an_oth -> 1396 | E74: =D74*(1+g_oth_A) -> 1396 | F74: =E74*(1+g_oth_A) -> 1396 | G74: =F74*(1+g_oth_A) -> 1396
A75: 出口管制與中國調整 | B75: US$M | C75: 0 | D75: 0 | E75: =-aff_hit*aff_A-0*cn_sh*(E72+E73) -> 0 | F75: =-aff_hit*aff_A-0*cn_sh*(F72+F73) -> 0 | G75: =-aff_hit*aff_A-0*cn_sh*(G72+G73) -> 0 | H75: 關係企業規則恢復（情境 C 或 Sens）；中國下修只在 Sens
A76: 營收 | B76: US$M | C76: =C72+C73+C74+C75 -> 28368 | D76: =D72+D73+D74+D75 -> 34287 | E76: =E72+E73+E74+E75 -> 40133.145 | F76: =F72+F73+F74+F75 -> 45594.191 | G76: =G72+G73+G74+G75 -> 49270.675
A77: non-GAAP 毛利率 | B77: % | C77: =a25_gp/a25_rev -> 0.48783319 | D77: =an_gp/an_rev -> 0.50041858 | E77: =1-(cF+cv*E76)/E76 -> 0.50920504 | F77: =1-(cF+cv*F76)/F76 -> 0.51537723 | G77: =1-(cF+cv*G76)/G76 -> 0.51876186 | H77: 營業成本＝固定＋變動×營收（兩點推導）
A78: non-GAAP 毛利 | B78: US$M | C78: =C76*C77 -> 13838.852 | D78: =D76*D77 -> 17157.852 | E78: =E76*E77 -> 20435.999 | F78: =F76*F77 -> 23498.208 | G78: =G76*G77 -> 25559.747
A79: non-GAAP 營業費用 | B79: US$M | C79: =opex25 -> 5276.852 | D79: =opex26 -> 5832.852 | E79: =oF+ov*E76 -> 6382.0084 | F79: =oF+ov*F76 -> 6894.9906 | G79: =oF+ov*G76 -> 7240.3403 | H79: 固定＋變動×營收（兩點推導）
A80: non-GAAP 營業利益 | B80: US$M | C80: =C78-C79 -> 8562 | D80: =D78-D79 -> 11325 | E80: =E78-E79 -> 14053.991 | F80: =F78-F79 -> 16603.217 | G80: =G78-G79 -> 18319.407
A81: non-GAAP 營業利益率 | B81: % | C81: =C80/C76 -> 0.30181895 | D81: =D80/D76 -> 0.33030011 | E81: =E80/E76 -> 0.35018415 | F81: =F80/F76 -> 0.36415203 | G81: =G80/G76 -> 0.37181157
A82: non-GAAP 淨利 | B82: US$M | C82: =a25_ni -> 7607 | D82: =an_ni -> 10179.92 | E82: =E80*nioi -> 12486.418 | F82: =F80*nioi -> 14751.305 | G82: =G80*nioi -> 16276.072
A83: 稀釋股數 | B83: 百萬股 | C83: =a25_sh -> 808 | D83: =an_sh -> 797.79937 | E83: =$D83*(1-bb)^1 -> 789.82138 | F83: =$D83*(1-bb)^2 -> 781.92317 | G83: =$D83*(1-bb)^3 -> 774.10393
A84: non-GAAP 稀釋 EPS | B84: US$ | C84: =a25_eps -> 9.42 | D84: =an_eps -> 12.76 | E84: =E82/E83 -> 15.809167 | F84: =F82/F83 -> 18.865415 | G84: =G82/G83 -> 21.025693 | H84: FY2026＝前三季實績 EPS 合計＋第四季指引 EPS
A85: 半導體系統 ÷ FY 晶圓前段市場（隱含份額） | B85: % | D85: =D72/1000/(D67+D68+D69) -> 0.17408836 | E85: =E72/1000/(E67+E68+E69) -> 0.16533049 | F85: =F72/1000/(F67+F68+F69) -> 0.16526976 | G85: =G72/1000/(G67+G68+G69) -> 0.16514433 | H85: 檢驗用；FY2027 起等於 FY2026 份額 × 份額係數 × 組合效果
A92: 案例區塊：份額係數 1.05（情境 A）
A93: 項目 | B93: 單位 | C93: 2025 | D93: 2026 | E93: 2027 | F93: 2028 | G93: 2029 | H93: 說明
A94: A. 市場（日曆年 CY，US$B；讀 In 頁的設備市場成品）
A95: 晶圓代工、邏輯與其他 CY | B95: US$B | C95: =laA_25+loA_25+ofA_25 -> 78.348121 | D95: =laA_26+loA_26+ofA_26 -> 99.287198 | E95: =laA_27+loA_27+ofA_27 -> 116.28871 | F95: =laA_28+loA_28+ofA_28 -> 130.8864 | G95: =laA_29+loA_29+ofA_29 -> 139.39808
A96: DRAM（含 HBM）CY | B96: US$B | C96: =drA_25 -> 26.376109 | D96: =drA_26 -> 39.365947 | E96: =drA_27 -> 53.258733 | F96: =drA_28 -> 59.5609 | G96: =drA_29 -> 61.831293
A97: NAND CY | B97: US$B | C97: =ndA_25 -> 12.172602 | D97: =ndA_26 -> 17.503905 | E97: =ndA_27 -> 23.248027 | F97: =ndA_28 -> 26.181322 | G97: =ndA_29 -> 27.674313
A98: B. 會計年度（FY；FY(t)＝fyw×CY(t−1)＋(1−fyw)×CY(t)）
A99: 晶圓代工、邏輯與其他 FY | B99: US$B | D99: =fyw*C95+(1-fyw)*D95 -> 95.797352 | E99: =fyw*D95+(1-fyw)*E95 -> 113.45512 | F99: =fyw*E95+(1-fyw)*F95 -> 128.45346 | G99: =fyw*F95+(1-fyw)*G95 -> 137.97947
A100: DRAM（含 HBM）FY | B100: US$B | D100: =fyw*C96+(1-fyw)*D96 -> 37.200974 | E100: =fyw*D96+(1-fyw)*E96 -> 50.943268 | F100: =fyw*E96+(1-fyw)*F96 -> 58.510539 | G100: =fyw*F96+(1-fyw)*G96 -> 61.452894
A101: NAND FY | B101: US$B | D101: =fyw*C97+(1-fyw)*D97 -> 16.615355 | E101: =fyw*D97+(1-fyw)*E97 -> 22.290674 | F101: =fyw*E97+(1-fyw)*F97 -> 25.692439 | G101: =fyw*F97+(1-fyw)*G97 -> 27.425481
A102: 半導體系統需求指數（FY2026＝1；以 FY2026 終端市場權重加權） | B102: x | D102: =m_fl*D99/$D99+m_dr*D100/$D100+m_nd*D101/$D101 -> 1 | E102: =m_fl*E99/$D99+m_dr*E100/$D100+m_nd*E101/$D101 -> 1.2474042 | F102: =m_fl*F99/$D99+m_dr*F100/$D100+m_nd*F101/$D101 -> 1.420389 | G102: =m_fl*G99/$D99+m_dr*G100/$D100+m_nd*G101/$D101 -> 1.5140939 | H102: Σ 權重 × FY 市場 ÷ FY2026 市場
A103: C. 損益（US$M；FY2025 實績、FY2026 錨點＝前三季實績＋第四季指引、FY2027 起模型）
A104: 半導體系統營收 | B104: US$M | C104: =a25_ss -> 21438.543 | D104: =an_ss -> 26046 | E104: =$D104*E102*sf_hi -> 34114.384 | F104: =$D104*F102*sf_hi -> 38845.224 | G104: =$D104*G102*sf_hi -> 41407.895 | H104: FY2027 起＝FY2026 錨點 × 需求指數 × 份額係數
A105: AGS 服務營收 | B105: US$M | C105: =a25_ags -> 5744.1967 | D105: =an_ags -> 6845 | E105: =D105*(1+g_ags_A) -> 7871.75 | F105: =E105*(1+g_ags_A) -> 9052.5125 | G105: =F105*(1+g_ags_A) -> 10410.389
A106: 其他（含顯示器）營收 | B106: US$M | C106: =a25_oth -> 1185.2601 | D106: =an_oth -> 1396 | E106: =D106*(1+g_oth_A) -> 1396 | F106: =E106*(1+g_oth_A) -> 1396 | G106: =F106*(1+g_oth_A) -> 1396
A107: 出口管制與中國調整 | B107: US$M | C107: 0 | D107: 0 | E107: =-aff_hit*aff_A-0*cn_sh*(E104+E105) -> 0 | F107: =-aff_hit*aff_A-0*cn_sh*(F104+F105) -> 0 | G107: =-aff_hit*aff_A-0*cn_sh*(G104+G105) -> 0 | H107: 關係企業規則恢復（情境 C 或 Sens）；中國下修只在 Sens
A108: 營收 | B108: US$M | C108: =C104+C105+C106+C107 -> 28368 | D108: =D104+D105+D106+D107 -> 34287 | E108: =E104+E105+E106+E107 -> 43382.134 | F108: =F104+F105+F106+F107 -> 49293.736 | G108: =G104+G105+G106+G107 -> 53214.284
A109: non-GAAP 毛利率 | B109: % | C109: =a25_gp/a25_rev -> 0.48783319 | D109: =an_gp/an_rev -> 0.50041858 | E109: =1-(cF+cv*E108)/E108 -> 0.51306436 | F109: =1-(cF+cv*F108)/F108 -> 0.5187815 | G109: =1-(cF+cv*G108)/G108 -> 0.52187253 | H109: 營業成本＝固定＋變動×營收（兩點推導）
A110: non-GAAP 毛利 | B110: US$M | C110: =C108*C109 -> 13838.852 | D110: =D108*D109 -> 17157.852 | E110: =E108*E109 -> 22257.827 | F110: =F108*F109 -> 25572.678 | G110: =G108*G109 -> 27771.073
A111: non-GAAP 營業費用 | B111: US$M | C111: =opex25 -> 5276.852 | D111: =opex26 -> 5832.852 | E111: =oF+ov*E108 -> 6687.2014 | F111: =oF+ov*F108 -> 7242.5066 | G111: =oF+ov*G108 -> 7610.7824 | H111: 固定＋變動×營收（兩點推導）
A112: non-GAAP 營業利益 | B112: US$M | C112: =C110-C111 -> 8562 | D112: =D110-D111 -> 11325 | E112: =E110-E111 -> 15570.625 | F112: =F110-F111 -> 18330.172 | G112: =G110-G111 -> 20160.291
A113: non-GAAP 營業利益率 | B113: % | C113: =C112/C108 -> 0.30181895 | D113: =D112/D108 -> 0.33030011 | E113: =E112/E108 -> 0.35891792 | F113: =F112/F108 -> 0.37185601 | G113: =G112/G108 -> 0.37885111
A114: non-GAAP 淨利 | B114: US$M | C114: =a25_ni -> 7607 | D114: =an_ni -> 10179.92 | E114: =E112*nioi -> 13833.887 | F114: =F112*nioi -> 16285.636 | G114: =G112*nioi -> 17911.625
A115: 稀釋股數 | B115: 百萬股 | C115: =a25_sh -> 808 | D115: =an_sh -> 797.79937 | E115: =$D115*(1-bb)^1 -> 789.82138 | F115: =$D115*(1-bb)^2 -> 781.92317 | G115: =$D115*(1-bb)^3 -> 774.10393
A116: non-GAAP 稀釋 EPS | B116: US$ | C116: =a25_eps -> 9.42 | D116: =an_eps -> 12.76 | E116: =E114/E115 -> 17.51521 | F116: =F114/F115 -> 20.827668 | G116: =G114/G115 -> 23.138527 | H116: FY2026＝前三季實績 EPS 合計＋第四季指引 EPS
A117: 半導體系統 ÷ FY 晶圓前段市場（隱含份額） | B117: % | D117: =D104/1000/(D99+D100+D101) -> 0.17408836 | E117: =E104/1000/(E99+E100+E101) -> 0.1827337 | F117: =F104/1000/(F99+F100+F101) -> 0.18266658 | G117: =G104/1000/(G99+G100+G101) -> 0.18252794 | H117: 檢驗用；FY2027 起等於 FY2026 份額 × 份額係數 × 組合效果
A124: 案例區塊：第四季 DRAM 占比 26%（情境 A）
A125: 項目 | B125: 單位 | C125: 2025 | D125: 2026 | E125: 2027 | F125: 2028 | G125: 2029 | H125: 說明
A126: A. 市場（日曆年 CY，US$B；讀 In 頁的設備市場成品）
A127: 晶圓代工、邏輯與其他 CY | B127: US$B | C127: =laA_25+loA_25+ofA_25 -> 78.348121 | D127: =laA_26+loA_26+ofA_26 -> 99.287198 | E127: =laA_27+loA_27+ofA_27 -> 116.28871 | F127: =laA_28+loA_28+ofA_28 -> 130.8864 | G127: =laA_29+loA_29+ofA_29 -> 139.39808
A128: DRAM（含 HBM）CY | B128: US$B | C128: =drA_25 -> 26.376109 | D128: =drA_26 -> 39.365947 | E128: =drA_27 -> 53.258733 | F128: =drA_28 -> 59.5609 | G128: =drA_29 -> 61.831293
A129: NAND CY | B129: US$B | C129: =ndA_25 -> 12.172602 | D129: =ndA_26 -> 17.503905 | E129: =ndA_27 -> 23.248027 | F129: =ndA_28 -> 26.181322 | G129: =ndA_29 -> 27.674313
A130: B. 會計年度（FY；FY(t)＝fyw×CY(t−1)＋(1−fyw)×CY(t)）
A131: 晶圓代工、邏輯與其他 FY | B131: US$B | D131: =fyw*C127+(1-fyw)*D127 -> 95.797352 | E131: =fyw*D127+(1-fyw)*E127 -> 113.45512 | F131: =fyw*E127+(1-fyw)*F127 -> 128.45346 | G131: =fyw*F127+(1-fyw)*G127 -> 137.97947
A132: DRAM（含 HBM）FY | B132: US$B | D132: =fyw*C128+(1-fyw)*D128 -> 37.200974 | E132: =fyw*D128+(1-fyw)*E128 -> 50.943268 | F132: =fyw*E128+(1-fyw)*F128 -> 58.510539 | G132: =fyw*F128+(1-fyw)*G128 -> 61.452894
A133: NAND FY | B133: US$B | D133: =fyw*C129+(1-fyw)*D129 -> 16.615355 | E133: =fyw*D129+(1-fyw)*E129 -> 22.290674 | F133: =fyw*E129+(1-fyw)*F129 -> 25.692439 | G133: =fyw*F129+(1-fyw)*G129 -> 27.425481
A134: 半導體系統需求指數（FY2026＝1；以 FY2026 終端市場權重加權） | B134: x | D134: =m_fl_lo*D131/$D131+m_dr_lo*D132/$D132+m_nd*D133/$D133 -> 1 | E134: =m_fl_lo*E131/$D131+m_dr_lo*E132/$D132+m_nd*E133/$D133 -> 1.2451587 | F134: =m_fl_lo*F131/$D131+m_dr_lo*F132/$D132+m_nd*F133/$D133 -> 1.417575 | G134: =m_fl_lo*G131/$D131+m_dr_lo*G132/$D132+m_nd*G133/$D133 -> 1.5115268 | H134: Σ 權重 × FY 市場 ÷ FY2026 市場
A135: C. 損益（US$M；FY2025 實績、FY2026 錨點＝前三季實績＋第四季指引、FY2027 起模型）
A136: 半導體系統營收 | B136: US$M | C136: =a25_ss -> 21438.543 | D136: =an_ss -> 26046 | E136: =$D136*E134*sf -> 32431.403 | F136: =$D136*F134*sf -> 36922.159 | G136: =$D136*G134*sf -> 39369.228 | H136: FY2027 起＝FY2026 錨點 × 需求指數 × 份額係數
A137: AGS 服務營收 | B137: US$M | C137: =a25_ags -> 5744.1967 | D137: =an_ags -> 6845 | E137: =D137*(1+g_ags_A) -> 7871.75 | F137: =E137*(1+g_ags_A) -> 9052.5125 | G137: =F137*(1+g_ags_A) -> 10410.389
A138: 其他（含顯示器）營收 | B138: US$M | C138: =a25_oth -> 1185.2601 | D138: =an_oth -> 1396 | E138: =D138*(1+g_oth_A) -> 1396 | F138: =E138*(1+g_oth_A) -> 1396 | G138: =F138*(1+g_oth_A) -> 1396
A139: 出口管制與中國調整 | B139: US$M | C139: 0 | D139: 0 | E139: =-aff_hit*aff_A-0*cn_sh*(E136+E137) -> 0 | F139: =-aff_hit*aff_A-0*cn_sh*(F136+F137) -> 0 | G139: =-aff_hit*aff_A-0*cn_sh*(G136+G137) -> 0 | H139: 關係企業規則恢復（情境 C 或 Sens）；中國下修只在 Sens
A140: 營收 | B140: US$M | C140: =C136+C137+C138+C139 -> 28368 | D140: =D136+D137+D138+D139 -> 34287 | E140: =E136+E137+E138+E139 -> 41699.153 | F140: =F136+F137+F138+F139 -> 47370.672 | G140: =G136+G137+G138+G139 -> 51175.617
A141: non-GAAP 毛利率 | B141: % | C141: =a25_gp/a25_rev -> 0.48783319 | D141: =an_gp/an_rev -> 0.50041858 | E141: =1-(cF+cv*E140)/E140 -> 0.5111403 | F141: =1-(cF+cv*F140)/F140 -> 0.51707829 | G141: =1-(cF+cv*G140)/G140 -> 0.52032432 | H141: 營業成本＝固定＋變動×營收（兩點推導）
A142: non-GAAP 毛利 | B142: US$M | C142: =C140*C141 -> 13838.852 | D142: =D140*D141 -> 17157.852 | E142: =E140*E141 -> 21314.118 | F142: =F140*F141 -> 24494.346 | G142: =G140*G141 -> 26627.918
A143: non-GAAP 營業費用 | B143: US$M | C143: =opex25 -> 5276.852 | D143: =opex26 -> 5832.852 | E143: =oF+ov*E140 -> 6529.111 | F143: =oF+ov*F140 -> 7061.8639 | G143: =oF+ov*G140 -> 7419.2807 | H143: 固定＋變動×營收（兩點推導）
...

Sheet Sources
A1: 來源（公司新聞稿與 SEC 文件以網頁擷取工具讀取；10-Q 全文擷取在附註 5 前截斷，地區別與分部重編說明未能讀到）
A2: 公司：Q3 FY2026 新聞稿（2026-08-13） | B2: https://ir.appliedmaterials.com/news-releases/news-release-details/applied-materials-announces-third-quarter-2026-results
A3: 公司：Q2 FY2026 新聞稿（2026-05-14） | B3: https://ir.appliedmaterials.com/news-releases/news-release-details/applied-materials-announces-second-quarter-2026-results
A4: 公司：Q1 FY2026 新聞稿（2026-02-12；BIS 和解金 US$253M、分部重編） | B4: https://ir.appliedmaterials.com/news-releases/news-release-details/applied-materials-announces-first-quarter-2026-results/
A5: 公司：Q4 FY2025 新聞稿（SEC 8-K 附件，2025-11-13） | B5: https://www.sec.gov/Archives/edgar/data/6951/000162828025051998/exhibit991q42025earningsre.htm
A6: 公司：8-K（2025-09-29；BIS 關係企業規則影響 FY2026 約 US$600M） | B6: https://www.sec.gov/Archives/edgar/data/6951/000162828025043753/amat-20250929.htm
A7: 公司：10-Q Q3 FY2026（封面流通股 793,597,443） | B7: https://www.sec.gov/Archives/edgar/data/0000006951/000162828026058235/amat-20260726.htm
A8: 公司：Q1 FY2026 10-Q 分部附註（XBRL R21） | B8: https://www.sec.gov/Archives/edgar/data/6951/000162828026009694/R21.htm
A9: 公司：FY2023 Q4 新聞稿（FY2023、FY2022 EPS） | B9: https://www.sec.gov/Archives/edgar/data/6951/000000695123000035/exhibit991q42023earningsre.htm
A10: 公司：FY2021 Q4 新聞稿（FY2021、FY2020 EPS） | B10: https://investor.appliedmaterials.com/news-releases/news-release-details/applied-materials-announces-fourth-quarter-and-fiscal-year-2021
A11: 公司：FY2020 Q4 新聞稿（FY2020、FY2019 EPS） | B11: https://www.sec.gov/Archives/edgar/data/6951/000000695120000041/exhibit991q42020earnin.htm
A12: 公司：FY2018 Q4 新聞稿（FY2018、FY2017 EPS） | B12: https://www.sec.gov/Archives/edgar/data/0000006951/000000695118000032/exhibit991q42018earningsre.htm
A13: 公司：FY2016 Q4 新聞稿（FY2016 EPS） | B13: https://www.sec.gov/Archives/edgar/data/6951/000000695116000063/exhibit991earningsreleaseq.htm
... A25: companiesmarketcap：年底 P/E（GAAP TTM） | B25: https://companiesmarketcap.com/applied-materials/pe-ratio/
A26: 市場層：markets/equipment 成品（本 repo）；tools/cycle_position.py
A27: SemiAnalysis | B27: 未使用
