Workbook

Sheet README
A1: 光寶科（2301.TW）收支與估值模型 v0.1（AI 半導體 Project：電源與散熱次產業；AI 伺服器電源 PSU、電源櫃、BBU） 2026-10-25
A2: 版本：v0.1（初版）。AI 電源每 kW 內容沿用台達電模型（delta/dist In 頁，本專案權威，口徑一致），本模型只建光寶份額；Units 與 Recon 頁核對光寶＋台達電份額合計。
A3: 模型命題：光寶科的 AI 營收＝部署 GW（AI IT 資本支出 ÷ 每 GW IT 資本支出）× AI 電源每 kW 內容（台達電模型）× 光寶份額 ÷（1 − 非電源占比）；非 AI（一般雲端電源、光電、資訊與消費電子、車用）約占七成，另設低成長。AI 相關營收 2025 年約兩成、2026 年約三成，毛利率高於其他業務，使 AI 部署成為 EPS 的主要驅動。
A4: 核心問題：光寶在台達電主導的 AI 電源市場（800V HVDC 電源櫃、BBU、新 CSP 客戶）能不能把有效份額由約一成八往上拉；消費電子衰退與零組件成本會吃掉多少；現價約 20 倍前瞻 P/E 隱含什麼路徑。
A6: 會計年度＝日曆年，FY(t)＝CY(t)，不平移。預測期 FY2027–FY2029 由驅動因子推導，FY2030–FY2032 為收斂法。金額：十億新台幣；市場以美元計、以匯率 32.0 換算（與台達電模型相同）。口徑：歸屬母公司淨利（IFRS）。
A8: 驅動因子 → 推導量（全部唯讀上游，不修改）
A9: AI 營收：markets/network 的 AI IT 資本支出 × 同字母顆數係數（tsmc；＝markets/memory SCEN_UNITS）÷ 每 GW IT 資本支出（Tokenomics，經橋接表）＝部署 GW；× 每 kW 電源內容（台達電模型 450 → 600 → 680 → 720 美元）× 匯率 × 光寶有效份額（FY2026 以公司 AI 相關占比校準）× 份額相對值（Assumed）÷（1 − 非電源占比）。
A10: 非 AI：FY2026 殘差 × 成長率（Assumed，+3%）。毛利率：AI 相關比其他營收高 d_ai 12pt（Assumed，依 2Q26 雲端部門營益率約 24% vs 其他約 5–6%），其他毛利率為 FY2026 殘差（Derived）；另加 AI 毛利率額外改善（情境 A 高、C 低）。營業費用：彈性 phi 0.7（Assumed）。淨利 ÷ 稅前 0.76（1H26 實績）。
A11: 校準：FY2026 ＝ 1H26 財報＋3Q26 月營收實績（1–9 月累計 − 1H26）＋假設（3Q、4Q 毛利率 26%、營業費用率 11.8%、4Q 季增 3%）。3Q26 財報與法說預計 2026-10-30 前後，截至 2026-10-25 尚未公布。不用券商數字（只在 Recon 對帳）。
A12: 估值：Val 第 0 節目標價＝0.5 × DCF 目標價（股東現金流＝EPS ×（1 − g／ROE），FY2027–32 明確期＋永續，r 10%、g 4%，三情境權重 0.3／0.5／0.2，負值取 0）＋0.5 × Comparable 目標價（台達電、Vertiv、Eaton、Flex 前瞻 P/E 中位數 × 12 個月後前瞻 EPS；不放 A 股）；另列 Comparable 單獨目標價、市場共識目標價與差距拆解。十年 P/E 規則值 × FY2027 EPS 保留為參考（不是目標價）。本版未做先驗，無 Andy 合理 P/E 對照。
A13: 預估期間：FY2027–FY2029 由驅動因子推導；FY2030 起為收斂法，非驅動因子推導（營收年增由 FY2029 線性收斂到 fade_g、淨利率收斂到 fade_m，FY2032 達到；PL 頁灰底）。十年平均淨利率 6.5%（wearn 2016–2025，單一來源）。
A14: 情境與行業一致：A＝順利（tsmc 顆數係數 A、份額相對值與 AI 毛利率額外改善取高值）；B＝平平（係數 B、取基準）；C＝不如預期（係數 C、取低值）；每 kW 電源內容（台達電模型）與非 AI 成長各情境相同。
... A18: 已知限制：(1) AI 相關營收只有公司年度占比（2025 年超過 20%、2026 年超過 30%），季度金額未揭露；(2) 份額相對值與非電源占比為 Assumed；(3) 每 kW 內容沿用台達電模型（2028 起 Assumed）；(4) 部門別毛利率未揭露，AI 毛利率差距由部門營益率推估；(5) 未建資本支出與折舊（2026 年約 180 億），DCF 現金流可能偏高估；(6) 十年 P/E 只有一個採用來源，2016–2022 年為 AI 前低倍數；(7) Comparable 同業（台達電、Vertiv）倍數高於光寶歷史；(8) FY2027 起共識只有 MarketScreener 一個來源；(9) 3Q26 財報後更新錨點；R4 產業部署路徑未建。

Sheet In
A1: In — 輸入（藍字；基準欄 E，低 D、高 F）。金額：十億新台幣（NT$B），AI 電源市場與每 kW 內容為美元；比例：%。每個輸入附兩個來源（找不到者寫「未找到」）；公司原文算一個
A2: 標記：Verified／Interested-party／Analogy／Assumed／Derived；Analogy、Assumed 給低／高區間。SemiAnalysis 未使用。公司原文＝光寶科財報與法說會（經媒體、資料商轉述）、月營收公告；公司的 AI 占比、產品時程說法為 Interested-party；券商與媒體估計皆為 Interested-party
A3: 鍵 | B3: 項目 | C3: 單位 | D3: 低 | E3: 基準 | F3: 高 | G3: 標記 | H3: 來源1 | I3: 來源2／說明
A4: A. AI 部署規模（讀 markets/network、markets/chip_bridge、tsmc 成品；情境 A 基準，B／C 依同字母顆數係數縮放）
A5: itc_26 | B5: AI IT 資本支出 2026 | C5: US$B | E5: 781.87292 | G5: Derived | H5: markets/network/dist/20261023_AI網通市場模型_v0.2.2.xlsx｜Mkt!C27:F27 | I5: 加速器顆數 × 每顆 IT capex（含 ASIC）；本模型以此除以每 GW IT 資本支出得到部署 GW（與台達電模型相同）
A6: itc_27 | B6: AI IT 資本支出 2027 | C6: US$B | E6: 1565.35 | G6: Derived | H6: markets/network/dist/20261023_AI網通市場模型_v0.2.2.xlsx｜Mkt!C27:F27 | I6: 同上
A7: itc_28 | B7: AI IT 資本支出 2028 | C7: US$B | E7: 1984.2639 | G7: Derived | H7: markets/network/dist/20261023_AI網通市場模型_v0.2.2.xlsx｜Mkt!C27:F27 | I7: 同上
A8: itc_29 | B8: AI IT 資本支出 2029 | C8: US$B | E8: 2260.3903 | G8: Derived | H8: markets/network/dist/20261023_AI網通市場模型_v0.2.2.xlsx｜Mkt!C27:F27 | I8: 同上
A9: itpg_gb | B9: 每 GW IT 資本支出（GB300） | C9: US$B | E9: 32.237224 | G9: Derived | H9: markets/chip_bridge/dist/20261023_晶片內容橋接表_v0.2.1.xlsx｜In!E10（GB300）、H10（VR200） | I9: Tokenomics IF_CapexIT（經橋接表；唯讀）
A10: itpg_vr | B10: 每 GW IT 資本支出（VR200；2027 起） | C10: US$B | E10: 37.586352 | G10: Derived | H10: markets/chip_bridge/dist/20261023_晶片內容橋接表_v0.2.1.xlsx｜In!E10（GB300）、H10（VR200） | I10: 同上；Rubin Ultra 與 ASIC 機架未另訂（Assumed：同 VR200）
A11: vr26 | B11: 2026 年部署中 Rubin 世代占比（混合每 GW IT 資本支出用） | C11: % | D11: 0.15 | E11: 0.22 | F11: 0.3 | G11: Interested-party | H11: TrendForce 2026 組合 Rubin 22%（經 markets/memory；與台達電模型相同） | I11: —
A12: racks_vr | B12: 每 GW 機架數（VR200） | C12: 架 | E12: 4052 | G12: Derived | H12: markets/chip_bridge/dist/20261023_晶片內容橋接表_v0.2.1.xlsx｜In!E6（GB300）、H6（VR200） | I12: Units 頁每架內容換算用
A13: um28_A | B13: 情境 A：2028 顆數 ÷ 基準 | C13: x | E13: 1 | G13: Assumed | H13: tsmc/dist/20261025_台積電模型_v0.3.xlsx｜In!E37 | I13: A＝順利（基準）；B＝平平；C＝不如預期；與台積電、台達電模型相同（＝markets/memory SCEN_UNITS，建置時核對）
A14: um29_A | B14: 情境 A：2029 顆數 ÷ 基準 | C14: x | E14: 1 | G14: Assumed | H14: tsmc/dist/20261025_台積電模型_v0.3.xlsx｜In!E38 | I14: 同上
A15: um28_B | B15: 情境 B：2028 顆數 ÷ 基準 | C15: x | E15: 0.8 | G15: Assumed | H15: tsmc/dist/20261025_台積電模型_v0.3.xlsx｜In!E39 | I15: A＝順利（基準）；B＝平平；C＝不如預期；與台積電、台達電模型相同（＝markets/memory SCEN_UNITS，建置時核對）
A16: um29_B | B16: 情境 B：2029 顆數 ÷ 基準 | C16: x | E16: 0.85 | G16: Assumed | H16: tsmc/dist/20261025_台積電模型_v0.3.xlsx｜In!E40 | I16: 同上
A17: um28_C | B17: 情境 C：2028 顆數 ÷ 基準 | C17: x | E17: 0.6 | G17: Assumed | H17: tsmc/dist/20261025_台積電模型_v0.3.xlsx｜In!E41 | I17: A＝順利（基準）；B＝平平；C＝不如預期；與台積電、台達電模型相同（＝markets/memory SCEN_UNITS，建置時核對）
A18: um29_C | B18: 情境 C：2029 顆數 ÷ 基準 | C18: x | E18: 0.6 | G18: Assumed | H18: tsmc/dist/20261025_台積電模型_v0.3.xlsx｜In!E42 | I18: 同上
A19: fx | B19: 匯率（新台幣 ÷ 美元） | C19: NT$/US$ | D19: 30.5 | E19: 32 | F19: 33 | G19: Derived | H19: delta/dist/20261025_台達電模型_v0.2.xlsx｜In!D20:F20 | I19: 與台達電模型相同（唯讀）；10-23 收盤：未找到
A20: B. AI 電源內容（口徑與台達電一致：唯讀 delta/dist In 頁）與光寶份額
A21: pkw_26 | B21: AI 電源內容 2026（台達電模型） | C21: US$/kW | D21: 380 | E21: 450 | F21: 520 | G21: Derived | H21: delta/dist/20261025_台達電模型_v0.2.xlsx｜In!D22:F22 | I21: 唯讀台達電模型成品（本專案 AI 電源每 kW 內容權威；含機架電源櫃、PSU、BBU、HVDC 電源櫃）
A22: pkw_27 | B22: AI 電源內容 2027（VR200）（台達電模型） | C22: US$/kW | D22: 500 | E22: 600 | F22: 700 | G22: Derived | H22: delta/dist/20261025_台達電模型_v0.2.xlsx｜In!D23:F23 | I22: 同上；低／高亦取自台達電模型（Sens 用）
A23: pkw_28 | B23: AI 電源內容 2028（800V HVDC 放量）（台達電模型） | C23: US$/kW | D23: 550 | E23: 680 | F23: 800 | G23: Assumed | H23: delta/dist/20261025_台達電模型_v0.2.xlsx｜In!D24:F24 | I23: 同上；低／高亦取自台達電模型（Sens 用）
A24: pkw_29 | B24: AI 電源內容 2029（台達電模型） | C24: US$/kW | D24: 550 | E24: 720 | F24: 850 | G24: Assumed | H24: delta/dist/20261025_台達電模型_v0.2.xlsx｜In!D25:F25 | I24: 同上；低／高亦取自台達電模型（Sens 用）
A25: x_np | B25: AI 相關營收中非電源部分（液冷 CDU、Sidecar、AI 光電等）占比 | C25: % | D25: 0 | E25: 0.1 | F25: 0.25 | G25: Assumed | H25: 公司：液冷 120kW CDU、Sidecar 2Q26 起出貨（富果 2026-07-31 法說摘要）；凱基 2025-09：光寶 2026 年液冷營收目標約 5%（Interested-party） | I25: 只影響份額（分子）與光寶＋台達電份額合計，不影響營收（非電源部分隨 AI 電源同比例成長，Assumed）
A26: rel_27 | B26: 光寶 AI 電源份額 2027 ÷ 2026（相對值；情境 A 取高、B 基準、C 取低） | C26: x | D26: 0.85 | E26: 1 | F26: 1.1 | G26: Assumed | H26: 凱基 2025-09：台達電 AI 伺服器電源市占約 60–65%、長期略降；光寶為第二梯隊，新增美系雲端客戶，PSU 與 BBU 4Q25 出貨（Interested-party） | I26: 公司：800V HVDC Power Rack 2026-11 小量、1Q27 放量；110kW Power Shelf、BBU 驗證量產；新 CSP 客戶長期目標每家每年 10 億美元（富果 2026-07-31）
A27: rel_28 | B27: 光寶 AI 電源份額 2028 ÷ 2026（相對值；情境 A 取高、B 基準、C 取低） | C27: x | D27: 0.8 | E27: 1 | F27: 1.2 | G27: Assumed | H27: 同上 | I27: —
A28: rel_29 | B28: 光寶 AI 電源份額 2029 ÷ 2026（相對值；情境 A 取高、B 基準、C 取低） | C28: x | D28: 0.75 | E28: 1 | F28: 1.25 | G28: Assumed | H28: 同上 | I28: —
A29: C. 營收結構錨點（公司揭露比例 × 營收）
A30: ai_25 | B30: 2025 年 AI 相關營收 ÷ 營收 | C30: % | D30: 0.2 | E30: 0.21 | F30: 0.23 | G30: Interested-party | H30: https://uanalyze.com.tw/articles/1580848095：AI 相關營收超過 20%（公司，達標） | I30: https://blog.fugle.tw/post/earnings-call-2301-2026-02-25：2025 年 AI 占比超過 20%；雲端與物聯網 45%、光電 17%、資訊與消費電子 38%
A31: ai_26 | B31: 2026 年 AI 相關營收 ÷ 營收 | C31: % | D31: 0.3 | E31: 0.31 | F31: 0.35 | G31: Interested-party | H31: https://blog.fugle.tw/post/earnings-call-2301-2026-07-31：AI 相關產品 2026 年超過 30%（公司）；BBU 約占雲端營收 20–25% | I31: https://blog.fugle.tw/post/earnings-call-2301-2026-02-25：2026 年目標 30% 以上、長期 50% 以上
A32: g_nai27 | B32: 非 AI 營收年增 2027（一般雲端電源、光電、資訊與消費電子、車用） | C32: % | D32: -0.03 | E32: 0.03 | F32: 0.06 | G32: Assumed | H32: 公司 2026 指引：資訊產品 −6～−8%、手機 −4～−5%（記憶體短缺）；工控、標準電源、邊緣運算擴充（富果 2026-02-25） | I32: FY2026 非 AI 由錨點反推（Q 頁）；Denselight（新加坡 InP，持股 21%）2027–28 年貢獻未計入（Assumed：不另計）
A33: g_nai28 | B33: 非 AI 營收年增 2028（一般雲端電源、光電、資訊與消費電子、車用） | C33: % | D33: -0.03 | E33: 0.03 | F33: 0.06 | G33: Assumed | H33: 同上 | I33: —
A34: g_nai29 | B34: 非 AI 營收年增 2029（一般雲端電源、光電、資訊與消費電子、車用） | C34: % | D34: -0.03 | E34: 0.03 | F34: 0.06 | G34: Assumed | H34: 同上 | I34: —
A35: D. 毛利率
A36: d_ai | B36: AI 相關毛利率高於其他營收的幅度 | C36: pt | D36: 0.08 | E36: 0.12 | F36: 0.16 | G36: Assumed | H36: https://uanalyze.com.tw/articles/3402052563：2Q26 雲端與物聯網營收 288.9 億、營業利益 69 億（營益率約 24%）vs 公司 15.6%；其他部門合計約 5–6%（Derived） | I36: 部門別毛利率未揭露：未找到；毛利率 FY2025 22.9% → 2Q26 27.2%（AI 占比上升）
A37: gmu_27 | B37: AI 相關毛利率額外改善 2027（800V 電源櫃、組合；情境 A 取高、C 取低） | C37: pt | D37: -0.01 | E37: 0 | F37: 0.01 | G37: Assumed | H37: 公司：2026 年毛利率目標約 25%（富果 2026-07-31）；800V HVDC 電源櫃與 110kW Power Shelf 2027 放量（Interested-party） | I37: 下檔：零組件漲價、新廠（高雄二期、越南、德州）爬坡
A38: gmu_28 | B38: AI 相關毛利率額外改善 2028（800V 電源櫃、組合；情境 A 取高、C 取低） | C38: pt | D38: -0.015 | E38: 0 | F38: 0.015 | G38: Assumed | H38: 同上 | I38: —
A39: gmu_29 | B39: AI 相關毛利率額外改善 2029（800V 電源櫃、組合；情境 A 取高、C 取低） | C39: pt | D39: -0.02 | E39: 0 | F39: 0.02 | G39: Assumed | H39: 同上 | I39: —
A40: E. FY2026 錨點（1H26 財報＋3Q26 月營收實績＋假設；3Q26 財報與法說預計 2026-10-30 前後，截至 2026-10-25 尚未公布）
A41: ytd9 | B41: 2026 年 1–9 月營收（月營收累計，實績） | C41: NT$B | E41: 153.559 | G41: Verified | H41: https://finance.technews.tw/2026/10/08/ltc-2301-202609-financial-report/：9 月 188.48 億元、前 9 月 1,535.59 億元（年增 26.1%） | I41: https://www.nstock.tw/2301?status=2：9 月 188.48 億、前 9 月 1,535.59 億（同值）
A42: q3_rev | B42: 3Q26 營收（＝1–9 月累計 − 1H26） | C42: NT$B | E42: =ytd9-(43.407+52.703) -> 57.449 | G42: Derived | H42: 1H26 營收 961.1 億（優分析 2026-07-31） | I42: 7、8 月個別營收：未找到
A43: q4g | B43: 4Q26 營收季增 | C43: % | D43: -0.03 | E43: 0.03 | F43: 0.08 | G43: Assumed | H43: 公司：下半年「非常樂觀」；800V HVDC 電源櫃 11 月小量（富果 2026-07-31） | I43: 9 月月減 3.8%（technews）；資訊與消費電子下半年與上半年持平；共識 FY2026 營收 2,198 億（MarketScreener，只作 Recon）
A44: q_gm | B44: 3Q、4Q26 毛利率 | C44: % | D44: 0.25 | E44: 0.26 | F44: 0.275 | G44: Assumed | H44: 1Q26 21.7%、2Q26 27.2%、1H26 24.7%（stockanalysis、優分析） | I44: 公司 2026 年毛利率目標約 25%（富果 2026-07-31，Interested-party）
A45: q_opx | B45: 3Q、4Q26 營業費用 ÷ 營收 | C45: % | D45: 0.112 | E45: 0.118 | F45: 0.125 | G45: Assumed | H45: 1Q26 12.2%、2Q26 11.7%（毛利 − 營業利益；Q 頁） | I45: FY2025 12.8%；研發約占營收 5–5.5%（富果 2026-07-31）
A46: q_nop | B46: 3Q、4Q26 營業外淨額（每季） | C46: NT$B | D46: 0.5 | E46: 0.9 | F46: 1.2 | G46: Assumed | H46: 1H26 稅前 − 營業利益＝約 20.4 億（stockanalysis 稅前淨利率推算） | I46: FY2025 約 29.7 億（同上）
A47: q_nir | B47: 淨利 ÷ 稅前（1H26 實績；3Q、4Q26 沿用） | C47: % | D47: 0.73 | E47: =10.891/14.341 -> 0.759431 | F47: 0.78 | G47: Derived | H47: 1H26：淨利 108.91 ÷ 稅前約 143.41 億（stockanalysis 季度淨利、稅前淨利率推算） | I47: FY2025：151.16 ÷ 197.1＝0.767（同上）
A48: q_sh | B48: 股數（十億股；EPS 換算） | C48: 十億股 | E48: =10.891/4.8 -> 2.2689583 | G48: Derived | H48: 1H26 淨利 108.91 億 ÷ EPS 4.80（優分析 2026-07-31） | I48: stockanalysis 流通股數 22.7 億股（2026-10-22）
A49: F. 營業費用、業外、稅與股數（FY2027 起）
A50: phi | B50: 營業費用成長對營收成長的彈性 | C50: x | D50: 0.5 | E50: 0.7 | F50: 1 | G50: Assumed | H50: FY2026 錨點實測約 0.65（Q 頁 B26） | I50: FY2025：營業費用 +17% ÷ 營收 +21%（stockanalysis 推算）
A51: opx_adj | B51: 營業費用額外占營收比（Sens 用；基準 0） | C51: pt | D51: -0.01 | E51: 0 | F51: 0.01 | G51: Assumed | H51: 無 | I51: Sens 用 ±1 個百分點
A52: nop_f | B52: 營業外淨額（每年） | C52: NT$B | D52: 2 | E52: 3.5 | F52: 5 | G52: Assumed | H52: FY2025 約 29.7 億、1H26 約 20.4 億（stockanalysis 推算） | I52: 含利息收入、投資收益；Denselight 權益法損益未另計
A53: nir_f | B53: 淨利 ÷ 稅前（FY2027 起） | C53: % | D53: 0.73 | E53: 0.76 | F53: 0.78 | G53: Derived | H53: 同 q_nir（1H26 0.759；FY2025 0.767） | I53: —
A54: sh_g | B54: 股數年變動 | C54: % | D54: 0 | E54: 0 | F54: 0.005 | G54: Assumed | H54: FY2025 推導 22.8 億股 → 1H26 22.7 億股（淨利 ÷ EPS） | I54: —
A55: mf | B55: AI 部署係數（Sens 用；FY2027 起） | C55: x | D55: 0.8 | E55: 1 | F55: 1.2 | G55: Assumed | H55: 網通模型 2027 年 AI IT 資本支出約 2 倍 | I55: ±20%
A56: G. 共識、券商與台達電模型（只作 Recon 對帳，不作校準）
A57: cons_rev26 | B57: 共識 FY2026 營收（MarketScreener） | C57: NT$B | E57: 219.778 | G57: Interested-party | H57: https://www.marketscreener.com/quote/stock/LITE-ON-TECHNOLOGY-CORPOR-6492334/valuation/（參考價 255.50，2026-10-22） | I57: stockanalysis FY2026 2,193 億（區間 2,101–2,297）
A58: cons_eps26 | B58: 共識 FY2026 EPS（MarketScreener） | C58: NT$ | E58: 10.81 | G58: Interested-party | H58: https://www.marketscreener.com/quote/stock/LITE-ON-TECHNOLOGY-CORPOR-6492334/valuation/ | I58: stockanalysis FY2026 10.81（11 家，區間 10.06–11.79）
A59: cons_rev27 | B59: 共識 FY2027 營收（MarketScreener） | C59: NT$B | E59: 292.383 | G59: Interested-party | H59: https://www.marketscreener.com/quote/stock/LITE-ON-TECHNOLOGY-CORPOR-6492334/valuation/（參考價 255.50，2026-10-22） | I59: —
A60: cons_eps27 | B60: 共識 FY2027 EPS（MarketScreener） | C60: NT$ | E60: 14.99 | G60: Interested-party | H60: https://www.marketscreener.com/quote/stock/LITE-ON-TECHNOLOGY-CORPOR-6492334/valuation/ | I60: FY2027 以後第二來源：未找到
A61: cons_rev28 | B61: 共識 FY2028 營收（MarketScreener） | C61: NT$B | E61: 366.11 | G61: Interested-party | H61: https://www.marketscreener.com/quote/stock/LITE-ON-TECHNOLOGY-CORPOR-6492334/valuation/（參考價 255.50，2026-10-22） | I61: —
A62: cons_eps28 | B62: 共識 FY2028 EPS（MarketScreener） | C62: NT$ | E62: 20.74 | G62: Interested-party | H62: https://www.marketscreener.com/quote/stock/LITE-ON-TECHNOLOGY-CORPOR-6492334/valuation/ | I62: FY2027 以後第二來源：未找到
A63: d_sh26 | B63: 台達電模型：台達電 AI 電源有效份額 2026 | C63: % | E63: 0.58367194 | G63: Derived | H63: delta/dist/20261025_台達電模型_v0.2.xlsx｜Units!C8:F8 | I63: 唯讀台達電成品（三情境相同：份額相對值不隨情境變動）
A64: d_pmk26 | B64: 台達電模型：AI 電源市場 2026（情境 A） | C64: US$B | E64: 10.529792 | G64: Derived | H64: delta/dist/20261025_台達電模型_v0.2.xlsx｜Units!C7:F7 | I64: 唯讀台達電成品（Recon：與本模型情境 A 應相同）
A65: d_aip26 | B65: 台達電模型：台達電 AI 電源營收 2026（情境 A） | C65: US$B | E65: 6.1459442 | G65: Derived | H65: delta/dist/20261025_台達電模型_v0.2.xlsx｜Units!C9:F9 | I65: 唯讀台達電成品
A66: d_sh27 | B66: 台達電模型：台達電 AI 電源有效份額 2027 | C66: % | E66: 0.55448834 | G66: Derived | H66: delta/dist/20261025_台達電模型_v0.2.xlsx｜Units!C8:F8 | I66: 同上
A67: d_pmk27 | B67: 台達電模型：AI 電源市場 2027（情境 A） | C67: US$B | E67: 24.988059 | G67: Derived | H67: delta/dist/20261025_台達電模型_v0.2.xlsx｜Units!C7:F7 | I67: 同上
A68: d_aip27 | B68: 台達電模型：台達電 AI 電源營收 2027（情境 A） | C68: US$B | E68: 13.855588 | G68: Derived | H68: delta/dist/20261025_台達電模型_v0.2.xlsx｜Units!C9:F9 | I68: 同上
... A74: d_aip29 | B74: 台達電模型：台達電 AI 電源營收 2029（情境 A） | C74: US$B | E74: 21.48194 | G74: Derived | H74: delta/dist/20261025_台達電模型_v0.2.xlsx｜Units!C9:F9 | I74: 同上
A75: kgi_dsh | B75: 凱基：台達電 AI 伺服器電源市占（中點） | C75: % | D75: 0.6 | E75: 0.625 | F75: 0.65 | G75: Interested-party | H75: https://www.kgi.com.hk/zh-hk/-/media/files/kgishk/research-reports/tw-reports/power-supply-sector_20250926e.pdf：約 60–65%，長期略降 | I75: 光寶與 Flex 為第二梯隊（份額數字：未找到）
A76: H. 價格與估值
A77: px | B77: 股價（2026-10-22 收盤，臺灣證交所） | C77: NT$ | E77: 255.5 | G77: Interested-party | H77: https://stockanalysis.com/quote/tpe/2301/：10-22 255.50（−3.04%）、前收 263.50 | I77: nstock（網址見 Sources 頁）：10-22 255.5（成交 7,003 張；HiStock 同值）；10-23 收盤：未找到
A78: pe_ttm | B78: 近 12 月 P/E（stockanalysis，10-22） | C78: x | E78: 30.09 | G78: Interested-party | H78: https://stockanalysis.com/quote/tpe/2301/ | I78: 近 12 月 EPS 8.49
A79: fpe | B79: 前瞻 P/E（stockanalysis，10-22） | C79: x | E79: 19.7 | G79: Interested-party | H79: https://stockanalysis.com/quote/tpe/2301/ | I79: 口徑：頁面未明示（約未來 12 月）
A80: cons_feps | B80: 共識前瞻 12 月 EPS（現價 ÷ 前瞻 P/E） | C80: NT$ | E80: =px/fpe -> 12.969543 | G80: Derived | H80: stockanalysis 前瞻 P/E 19.70（2026-10-22） | I80: 共識前瞻 EPS 的直接數字：未找到
A81: cons_tp | B81: 市場共識目標價（賣方平均） | C81: NT$ | E81: 314.25 | G81: Interested-party | H81: https://stockanalysis.com/quote/tpe/2301/：12 位分析師（S&P Global）平均 314.25（頁面時間 2026-10-22） | I81: https://stockanalysis.com/quote/tpe/2301/forecast/：2026-09-23 頁面平均 302.67、中位數 292.50、區間 176–400
A82: nim_avg | B82: 十年平均淨利率（2016–2025） | C82: % | E82: =AVERAGE(0.041,0.0123,0.0385,0.0529,0.0626,0.0845,0.0818,0.0984,0.0872,0.091) -> 0.06502 | G82: Interested-party | H82: https://stock.wearn.com/financial.asp?kind=2301：稅後淨利率 2016–2025：4.10%、1.23%、3.85%、5.29%、6.26%、8.45%、8.18%、9.84%、8.72%、9.10%（資料商） | I82: 單一來源；2017 年 1.23% 含一次性損失（商譽減損）
A83: J. 目標價與收斂法參數（黃底；Assumed，Andy 可改）
A84: tp_wA | B84: 目標價情境權重 A（A 順利／B 平平／C 不如預期） | C84: % | E84: 0.3 | G84: Assumed（Andy 可改） | H84: Andy 可改（工作單 2026-10-25 預設 A 0.3／B 0.5／C 0.2） | I84: 三者合計應為 100%（Val 頁第 0 節列示）
A85: tp_wB | B85: 目標價情境權重 B（A 順利／B 平平／C 不如預期） | C85: % | E85: 0.5 | G85: Assumed（Andy 可改） | H85: Andy 可改（工作單 2026-10-25 預設 A 0.3／B 0.5／C 0.2） | I85: 三者合計應為 100%（Val 頁第 0 節列示）
A86: tp_wC | B86: 目標價情境權重 C（A 順利／B 平平／C 不如預期） | C86: % | E86: 0.2 | G86: Assumed（Andy 可改） | H86: Andy 可改（工作單 2026-10-25 預設 A 0.3／B 0.5／C 0.2） | I86: 三者合計應為 100%（Val 頁第 0 節列示）
A87: tp_r | B87: 折現率／要求報酬 | C87: % | E87: 0.1 | G87: Assumed（Andy 可改） | H87: Andy 可改（工作單預設 10%，各市場同一值） | I87: DCF 折現；情境價值推到 12 個月後
A88: tp_g | B88: 長期成長率 | C88: % | E88: 0.04 | G88: Assumed（Andy 可改） | H88: Andy 可改（工作單預設 4%） | I88: DCF 永續成長與 FY2032 收斂目標（情境 B）
A89: tp_roe | B89: ROE（近三年平均，FY2023–25） | C89: % | E89: =AVERAGE(0.1748,0.1359,0.1671) -> 0.15926667 | G89: Derived | H89: https://stock.wearn.com/financial.asp?kind=2301：股東權益報酬率 FY2023 17.48%、FY2024 13.59%、FY2025 16.71% | I89: 單一來源
A90: tp_w_dcf | B90: 目標價中 DCF 的權重；其餘為 Comparable | C90: % | E90: 0.5 | G90: Assumed（Andy 可改） | H90: Andy 可改（2026-10-25 11:53 定 DCF／Comparable 各半） | I90: —
A91: fade_gA | B91: 情境 A：FY2032 營收年增收斂目標（tp_g＋2pt） | C91: % | E91: =tp_g+0.02 -> 0.06 | G91: Assumed（Andy 可改） | H91: 工作單 2026-10-25 11:20 收斂法 | I91: FY2030 起由 FY2029 年增線性收斂
A92: fade_gB | B92: 情境 B：FY2032 營收年增收斂目標（＝tp_g） | C92: % | E92: =tp_g -> 0.04 | G92: Assumed（Andy 可改） | H92: 同上 | I92: —
A93: fade_gC | B93: 情境 C：FY2032 營收年增收斂目標（tp_g−2pt） | C93: % | E93: =tp_g-0.02 -> 0.02 | G93: Assumed（Andy 可改） | H93: 同上 | I93: —
A94: fade_mA | B94: 情境 A：FY2032 淨利率收斂目標（＝情境 A FY2029 淨利率） | C94: % | E94: =PL!G13 -> 0.17078517 | G94: Derived | H94: PL 頁情境 A FY2029（公式於建置時連結） | I94: —
A95: fade_mB | B95: 情境 B：FY2032 淨利率收斂目標（情境 B FY2029 與十年平均的中點） | C95: % | E95: =(PL!G26+nim_avg)/2 -> 0.10710186 | G95: Derived | H95: PL 頁情境 B FY2029、In 頁 nim_avg | I95: —
A96: fade_mC | B96: 情境 C：FY2032 淨利率收斂目標（＝十年平均淨利率 nim_avg） | C96: % | E96: =nim_avg -> 0.06502 | G96: Derived | H96: In 頁 nim_avg（wearn 2016–2025） | I96: —

Sheet Q
A1: Q — 實績與 FY2026 錨點（十億新台幣；EPS 為新台幣；股數為十億股）。藍字＝輸入；黑字＝公式。實績取自光寶科財報與月營收公告（經 stockanalysis、優分析、technews 轉述）
A2: FY2026 錨點＝1H26 財報＋3Q26 月營收實績（1–9 月累計 − 1H26）＋假設（3Q、4Q 毛利率、營業費用率、營業外；4Q 營收季增）。稅前利益＝營收 × stockanalysis 稅前淨利率（Derived，非公司原文）。3Q26 財報與法說預計 2026-10-30 前後（stockanalysis 估計；公司公告日期：未找到），截至 2026-10-25 尚未公布，公布後更新
A3: 項目 | B3: FY2025A | C3: 1H26（實績） | D3: 3Q26（營收實績） | E3: 4Q26（模型） | F3: FY2026 錨點 | G3: 標記 | H3: 來源1 | I3: 來源2／說明
A4: 營收 | B4: 166.085 | C4: =43.407+52.703 -> 96.11 | D4: =q3_rev -> 57.449 | E4: =D4*(1+q4g) -> 59.17247 | F4: =SUM(C4:E4) -> 212.73147 | G4: Verified／Assumed（4Q 季增） | H4: FY2025：https://stockanalysis.com/quote/tpe/2301/financials/（營收 1,660.85 億、毛利 380.39 億、營業利益 167.38 億、淨利 151.16 億）；1H26：https://stockanalysis.com/quote/tpe/2301/financials/?p=quarterly（1Q26、2Q26） | I4: FY2025：優分析 2026-02-25（營收 1,660.9 億、毛利率 22.9%、營益率 10.1%、淨利 151.2 億、EPS 6.64）；1H26：優分析 2026-07-31（營收 961.1 億、毛利率 24.7%、營業利益 123.0 億、淨利 108.9 億、EPS 4.80）；3Q26＝1–9 月月營收累計 − 1H26
A5: 毛利 | B5: 38.039 | C5: =9.403+14.348 -> 23.751 | D5: =D4*q_gm -> 14.93674 | E5: =E4*q_gm -> 15.384842 | F5: =SUM(C5:E5) -> 54.072582 | G5: Verified／Assumed | H5: FY2025：https://stockanalysis.com/quote/tpe/2301/financials/（營收 1,660.85 億、毛利 380.39 億、營業利益 167.38 億、淨利 151.16 億）；1H26：https://stockanalysis.com/quote/tpe/2301/financials/?p=quarterly（1Q26、2Q26） | I5: FY2025：優分析 2026-02-25（營收 1,660.9 億、毛利率 22.9%、營益率 10.1%、淨利 151.2 億、EPS 6.64）；1H26：優分析 2026-07-31（營收 961.1 億、毛利率 24.7%、營業利益 123.0 億、淨利 108.9 億、EPS 4.80）
A6: 毛利率 | B6: =B5/B4 -> 0.22903333 | C6: =C5/C4 -> 0.24712309 | D6: =D5/D4 -> 0.26 | E6: =E5/E4 -> 0.26 | F6: =F5/F4 -> 0.25418234 | G6: Derived | H6: — | I6: FY2025 22.9%；1H26 24.7%（公司）
A7: 營業費用 | B7: =B5-B8 -> 21.301 | C7: =C5-C8 -> 11.449 | D7: =D4*q_opx -> 6.778982 | E7: =E4*q_opx -> 6.9823515 | F7: =SUM(C7:E7) -> 25.210333 | G7: Derived／Assumed | H7: FY2025：https://stockanalysis.com/quote/tpe/2301/financials/（營收 1,660.85 億、毛利 380.39 億、營業利益 167.38 億、淨利 151.16 億）；1H26：https://stockanalysis.com/quote/tpe/2301/financials/?p=quarterly（1Q26、2Q26） | I7: 毛利 − 營業利益
A8: 營業利益 | B8: 16.738 | C8: =4.099+8.203 -> 12.302 | D8: =D5-D7 -> 8.157758 | E8: =E5-E7 -> 8.4024907 | F8: =SUM(C8:E8) -> 28.862249 | G8: Verified／Derived | H8: FY2025：https://stockanalysis.com/quote/tpe/2301/financials/（營收 1,660.85 億、毛利 380.39 億、營業利益 167.38 億、淨利 151.16 億）；1H26：https://stockanalysis.com/quote/tpe/2301/financials/?p=quarterly（1Q26、2Q26） | I8: FY2025：優分析 2026-02-25（營收 1,660.9 億、毛利率 22.9%、營益率 10.1%、淨利 151.2 億、EPS 6.64）；1H26：優分析 2026-07-31（營收 961.1 億、毛利率 24.7%、營業利益 123.0 億、淨利 108.9 億、EPS 4.80）
A9: 營業利益率 | B9: =B8/B4 -> 0.10077972 | C9: =C8/C4 -> 0.12799917 | D9: =D8/D4 -> 0.142 | E9: =E8/E4 -> 0.142 | F9: =F8/F4 -> 0.13567456 | G9: Derived | H9: — | I9: FY2025 10.1%；2Q26 15.6%（公司）
A10: 營業外淨額 | B10: =B11-B8 -> 2.9762895 | C10: =C11-C8 -> 2.039 | D10: =q_nop -> 0.9 | E10: =q_nop -> 0.9 | F10: =SUM(C10:E10) -> 3.839 | G10: Derived／Assumed | H10: 稅前 − 營業利益 | I10: —
A11: 稅前利益 | B11: =166.085*0.1187 -> 19.714289 | C11: =4.97+9.371 -> 14.341 | D11: =D8+D10 -> 9.057758 | E11: =E8+E10 -> 9.3024907 | F11: =SUM(C11:E11) -> 32.701249 | G11: Derived | H11: FY2025＝營收 × 稅前淨利率 11.87%（stockanalysis）；1H26＝1Q26 約 49.70 億＋2Q26 約 93.71 億（stockanalysis 季度稅前淨利率推算） | I11: 公司揭露稅前：未找到
A12: 歸屬母公司淨利 | B12: 15.116 | C12: =3.775+7.116 -> 10.891 | D12: =D11*q_nir -> 6.8787422 | E12: =E11*q_nir -> 7.0645999 | F12: =SUM(C12:E12) -> 24.834342 | G12: Verified／Derived（3Q、4Q） | H12: FY2025：https://stockanalysis.com/quote/tpe/2301/financials/（營收 1,660.85 億、毛利 380.39 億、營業利益 167.38 億、淨利 151.16 億）；1H26：https://stockanalysis.com/quote/tpe/2301/financials/?p=quarterly（1Q26、2Q26） | I12: 1Q26 37.75 億、2Q26 71.16 億（stockanalysis）；1H26 108.9 億（優分析）
A13: 淨利 ÷ 稅前（含稅與非控制權益） | B13: =B12/B11 -> 0.76675348 | C13: =C12/C11 -> 0.759431 | D13: =D12/D11 -> 0.759431 | E13: =E12/E11 -> 0.759431 | F13: =F12/F11 -> 0.759431 | G13: Derived | H13: — | I13: —
A14: 股數（十億股） | B14: =15.116/6.64 -> 2.276506 | C14: =q_sh -> 2.2689583 | D14: =q_sh -> 2.2689583 | E14: =q_sh -> 2.2689583 | F14: =q_sh -> 2.2689583 | G14: Derived | H14: FY2025：https://stockanalysis.com/quote/tpe/2301/financials/（營收 1,660.85 億、毛利 380.39 億、營業利益 167.38 億、淨利 151.16 億）；1H26：https://stockanalysis.com/quote/tpe/2301/financials/?p=quarterly（1Q26、2Q26） | I14: 淨利 ÷ EPS
A15: EPS | B15: =B12/B14 -> 6.64 | C15: =C12/C14 -> 4.8 | D15: =D12/D14 -> 3.0316741 | E15: =E12/E14 -> 3.1135873 | F15: =F12/F14 -> 10.945261 | G15: Derived | H15: 淨利 ÷ 股數 | I15: —
A16: 公司揭露 EPS | B16: 6.64 | C16: 4.8 | G16: Verified | H16: FY2025：https://stockanalysis.com/quote/tpe/2301/financials/（營收 1,660.85 億、毛利 380.39 億、營業利益 167.38 億、淨利 151.16 億）；1H26：https://stockanalysis.com/quote/tpe/2301/financials/?p=quarterly（1Q26、2Q26） | I16: FY2025 6.64（wearn 同值；stockanalysis 列 6.59，口徑未載明）；2Q26 3.14（優分析）
A17: AI 相關營收（＝營收 × AI 相關占比） | B17: =B4*ai_25 -> 34.87785 | F17: =F4*ai_26 -> 65.946756 | G17: Derived／Interested-party | H17: 公司 AI 相關占比（In 頁 C 節） | I17: 各季 AI 營收金額未揭露：未找到
A18: 其中 AI 電源（＝AI 相關 ×（1 − 非電源占比）） | B18: =B17*(1-x_np) -> 31.390065 | F18: =F17*(1-x_np) -> 59.35208 | G18: Derived／Assumed | H18: In 頁 x_np | I18: AI 電源含 PSU、Power Shelf、BBU、HVDC 電源櫃（與台達電模型的每 kW 內容口徑相同）
A19: 非 AI 營收（＝營收 − AI 相關） | B19: =B4-B17 -> 131.20715 | F19: =F4-F17 -> 146.78471 | G19: Derived | H19: — | I19: 一般雲端電源、光電、資訊與消費電子、車用
A23: FY2026 錨點的檢查（參考；校準未使用券商數字）
A24: FY2026 營收年增 | B24: =F4/B4-1 -> 0.28085902
A25: FY2026 營業費用年增 | B25: =F7/B7-1 -> 0.18352817
A26: 營業費用彈性（營業費用年增 ÷ 營收年增；In 頁 phi 的參考） | B26: =B25/B24 -> 0.65345299
A27: FY2026 營收 ÷ 共識（MarketScreener）− 1 | B27: =F4/cons_rev26-1 -> -0.032062035
A28: FY2026 EPS ÷ 共識（MarketScreener）− 1 | B28: =F15/cons_eps26-1 -> 0.012512619
A29: 非 AI 營收 FY2026 年增 | B29: =F19/B19-1 -> 0.11872497

Sheet Units
A1: Units — AI 電源市場（每 kW 內容口徑與台達電模型一致，唯讀 delta/dist；本專案權威在台達電模型）、光寶有效份額與光寶＋台達電份額合計（情境 B）。部署 GW＝AI IT 資本支出（markets/network）÷ 每 GW IT 資本支出（Tokenomics，經橋接表）
A3: 項目 | B3: 單位 | C3: CY2026 | D3: CY2027 | E3: CY2028 | F3: CY2029 | G3: 說明
A4: 部署 GW（情境 B） | B4: GW | C4: =PL!D103 -> 23.399538 | D4: =PL!E103 -> 41.646766 | E4: =PL!F103 -> 42.233711 | F4: =PL!G103 -> 51.117803 | G4: AI IT 資本支出 × 顆數係數 B ÷ 每 GW IT 資本支出
A5: AI 電源內容（台達電模型） | B5: US$/kW | C5: =PL!D104 -> 450 | D5: =PL!E104 -> 600 | E5: =PL!F104 -> 680 | F5: =PL!G104 -> 720 | G5: 唯讀 delta/dist In 頁（2026–27 Derived，2028 起 Assumed）
A6: 每架 AI 電源內容（以 VR200 每 GW 架數換算） | B6: US$K/架 | C6: =PL!D104*1000000/racks_vr/1000 -> 111.05627 | D6: =PL!E104*1000000/racks_vr/1000 -> 148.07502 | E6: =PL!F104*1000000/racks_vr/1000 -> 167.81836 | F6: =PL!G104*1000000/racks_vr/1000 -> 177.69003
A7: AI 電源市場 | B7: US$B | C7: =PL!D105 -> 10.529792 | D7: =PL!E105 -> 24.988059 | E7: =PL!F105 -> 28.718923 | F7: =PL!G105 -> 36.804818 | G7: 含 ASIC 機架（假設每 kW 內容相同）
A8: 光寶有效份額 | B8: % | C8: =PL!D109 -> 0.17614332 | D8: =PL!E109 -> 0.17614332 | E8: =PL!F109 -> 0.17614332 | F8: =PL!G109 -> 0.17614332 | G8: FY2026 以公司 AI 相關占比 ×（1 − 非電源占比）校準
A9: 台達電有效份額（台達電模型） | B9: % | C9: =d_sh26 -> 0.58367194 | D9: =d_sh27 -> 0.55448834 | E9: =d_sh28 -> 0.52530475 | F9: =d_sh29 -> 0.49612115 | G9: 唯讀 delta/dist Units 頁；台達電份額相對值不隨情境變動
A10: 光寶＋台達電份額合計 | B10: % | C10: =PL!D109+d_sh26 -> 0.75981526 | D10: =PL!E109+d_sh27 -> 0.73063166 | E10: =PL!F109+d_sh28 -> 0.70144806 | F10: =PL!G109+d_sh29 -> 0.67226446 | G10: 應低於 100%；其餘為 Flex、群電、康舒、Vertiv、麥格米特等
A11: 其他廠商份額（＝1 − 合計） | B11: % | C11: =1-PL!D109-d_sh26 -> 0.24018474 | D11: =1-PL!E109-d_sh27 -> 0.26936834 | E11: =1-PL!F109-d_sh28 -> 0.29855194 | F11: =1-PL!G109-d_sh29 -> 0.32773554
A12: 光寶 AI 電源營收 | B12: US$B | C12: =PL!D110/fx -> 1.8547525 | D12: =PL!E110/fx -> 4.4014797 | E12: =PL!F110/fx -> 5.0586464 | F12: =PL!G110/fx -> 6.4829227
A13: 光寶 AI 相關營收（含液冷等非電源） | B13: US$B | C13: =PL!D111/fx -> 2.0608361 | D13: =PL!E111/fx -> 4.890533 | E13: =PL!F111/fx -> 5.6207182 | F13: =PL!G111/fx -> 7.2032475
A14: 光寶 AI 電源營收 ÷ 台達電 AI 電源營收（份額比） | B14: x | C14: =PL!D109/d_sh26 -> 0.30178479 | D14: =PL!E109/d_sh27 -> 0.3176682 | E14: =PL!F109/d_sh28 -> 0.33531644 | F14: =PL!G109/d_sh29 -> 0.35504093 | G14: 同一市場，故等於份額比
A15: 每 GW 光寶 AI 相關營收 | B15: US$M/GW | C15: =PL!D117 -> 88.071658 | D15: =PL!E117 -> 117.42888 | E15: =PL!F117 -> 133.08606 | F15: =PL!G117 -> 140.91465
A17: 讀法：光寶與台達電讀同一個 AI 電源市場（部署 GW × 台達電模型每 kW 內容）。FY2026 光寶有效份額約一成八（AI 相關扣除一成非電源）、台達電約五成八，合計約七成六，與凱基「台達電 60–65%、光寶與 Flex 第二梯隊」相符；台達電模型的份額逐年下降（光寶、Flex、中國廠追趕），本模型光寶份額相對值在情境 A 上升、B 持平、C 下降，CY2029 合計約六成三（C）到七成二（A），其餘留給其他廠商，合計不超過 100%。

Sheet PL
A1: PL — 光寶科損益（十億新台幣；EPS 新台幣；歸屬母公司）。FY2025A 實績、FY2026 錨點（1H26 財報＋3Q26 月營收＋假設），FY2027 起為模型。FY(t)＝CY(t)。三情境各一個完整推導區塊（本頁下方），頂端為摘要。顆數係數從 CY2028 開始；份額相對值、AI 毛利率額外改善從 FY2027 起依情境取高／基準／低值
A2: 灰底＝FY2030–FY2032 收斂法（上游只到 2029）：營收年增線性收斂到 fade_g、淨利率線性收斂到 fade_m（In 頁 J 節），非驅動因子推導
A3: 情境／項目 | B3: 單位 | C3: FY2025A | D3: FY2026（錨點） | E3: FY2027 | F3: FY2028 | G3: FY2029 | H3: FY2030（收斂） | I3: FY2031（收斂） | J3: FY2032（收斂） | K3: 說明
A4: 情境 A
A5: 營收 | B5: NT$B | C5: =C76 -> 166.085 | D5: =D76 -> 212.73147 | E5: =E76 -> 323.33502 | F5: =F76 -> 425.51838 | G5: =G76 -> 499.37197 | H5: =H76 -> 567.14057 | I5: =I76 -> 622.63744 | J5: =J76 -> 659.99569
A6: 營收年增 | B6: % | D6: =D77 -> 0.28085902 | E6: =E77 -> 0.51992094 | F6: =F77 -> 0.31602937 | G6: =G77 -> 0.17356147 | H6: =H77 -> 0.13570765 | I6: =I77 -> 0.097853824 | J6: =J77 -> 0.06
A7: AI 相關營收（AI 電源、BBU、液冷） | B7: NT$B | C7: =C73 -> 34.87785 | D7: =D73 -> 65.946756 | E7: =E73 -> 172.14676 | F7: =F73 -> 269.79447 | G7: =G73 -> 338.97635
A8: 非 AI 營收 | B8: NT$B | C8: =C75 -> 131.20715 | D8: =D75 -> 146.78471 | E8: =E75 -> 151.18826 | F8: =F75 -> 155.7239 | G8: =G75 -> 160.39562
A9: AI 相關 ÷ 營收 | B9: % | C9: =C78 -> 0.21 | D9: =D78 -> 0.31 | E9: =E78 -> 0.53240989 | F9: =F78 -> 0.63403718 | G9: =G78 -> 0.67880532
A10: 毛利率 | B10: % | C10: =C84 -> 0.22903333 | D10: =D84 -> 0.25418234 | E10: =E84 -> 0.28619562 | F10: =F84 -> 0.30257736 | G10: =G84 -> 0.31201508
A11: 營業利益率 | B11: % | C11: =C88 -> 0.10077972 | D11: =D88 -> 0.13567456 | E11: =E88 -> 0.17984927 | F11: =F88 -> 0.20389236 | G11: =G88 -> 0.21770853
A12: 歸屬母公司淨利 | B12: NT$B | C12: =C91 -> 15.116 | D12: =D91 -> 24.834342 | E12: =E91 -> 46.855191 | F12: =F91 -> 68.597559 | G12: =G91 -> 85.285329 | H12: =H91 -> 96.859201 | I12: =I91 -> 106.33724 | J12: =J91 -> 112.71748
A13: 淨利率 | B13: % | C13: =C95 -> 0.091013638 | D13: =D95 -> 0.11674033 | E13: =E95 -> 0.14491221 | F13: =F95 -> 0.16120939 | G13: =G95 -> 0.17078517 | H13: =H95 -> 0.17078517 | I13: =I95 -> 0.17078517 | J13: =J95 -> 0.17078517
A14: EPS | B14: NT$ | C14: =C93 -> 6.64 | D14: =D93 -> 10.945261 | E14: =E93 -> 20.650529 | F14: =F93 -> 30.233063 | G14: =G93 -> 37.587878 | H14: =H93 -> 42.688841 | I14: =I93 -> 46.866107 | J14: =J93 -> 49.678073
A15: EPS 年增 | B15: % | D15: =D94 -> 0.64838274 | E15: =E94 -> 0.88670956 | F15: =F94 -> 0.4640333 | G15: =G94 -> 0.24327061 | H15: =H94 -> 0.13570765 | I15: =I94 -> 0.097853824 | J15: =J94 -> 0.06
A17: 情境 B
A18: 營收 | B18: NT$B | C18: =C114 -> 166.085 | D18: =D114 -> 212.73147 | E18: =E114 -> 307.68531 | F18: =F114 -> 335.58689 | G18: =G114 -> 390.89954 | H18: =H114 -> 439.06453 | I18: =I114 -> 474.89565 | J18: =J114 -> 493.89148
A19: 營收年增 | B19: % | D19: =D115 -> 0.28085902 | E19: =E115 -> 0.4463554 | F19: =F115 -> 0.09068218 | G19: =G115 -> 0.16482365 | H19: =H115 -> 0.12321576 | I19: =I115 -> 0.081607882 | J19: =J115 -> 0.04
A20: AI 相關營收（AI 電源、BBU、液冷） | B20: NT$B | C20: =C111 -> 34.87785 | D20: =D111 -> 65.946756 | E20: =E111 -> 156.49705 | F20: =F111 -> 179.86298 | G20: =G111 -> 230.50392
A21: 非 AI 營收 | B21: NT$B | C21: =C113 -> 131.20715 | D21: =D113 -> 146.78471 | E21: =E113 -> 151.18826 | F21: =F113 -> 155.7239 | G21: =G113 -> 160.39562
A22: AI 相關 ÷ 營收 | B22: % | C22: =C116 -> 0.21 | D22: =D116 -> 0.31 | E22: =E116 -> 0.50862699 | F22: =F116 -> 0.53596547 | G22: =G116 -> 0.5896756
A23: 毛利率 | B23: % | C23: =C122 -> 0.22903333 | D23: =D122 -> 0.25418234 | E23: =E122 -> 0.27801758 | F23: =F122 -> 0.28129819 | G23: =G122 -> 0.28774341
A24: 營業利益率 | B24: % | C24: =C126 -> 0.10077972 | D24: =D126 -> 0.13567456 | E24: =E126 -> 0.1704815 | F24: =F126 -> 0.17644437 | G24: =G126 -> 0.18734066
A25: 歸屬母公司淨利 | B25: NT$B | C25: =C129 -> 15.116 | D25: =D129 -> 24.834342 | E25: =E129 -> 42.525536 | F25: =F129 -> 47.661435 | G25: =G129 -> 58.315846 | H25: =H129 -> 59.342394 | I25: =I129 -> 57.523704 | J25: =J129 -> 52.896695
A26: 淨利率 | B26: % | C26: =C133 -> 0.091013638 | D26: =D133 -> 0.11674033 | E26: =E133 -> 0.13821114 | F26: =F133 -> 0.14202413 | G26: =G133 -> 0.14918372 | H26: =H133 -> 0.13515643 | I26: =I133 -> 0.12112914 | J26: =J133 -> 0.10710186
A27: EPS | B27: NT$ | C27: =C131 -> 6.64 | D27: =D131 -> 10.945261 | E27: =E131 -> 18.742317 | F27: =F131 -> 21.005866 | G27: =G131 -> 25.701594 | H27: =H131 -> 26.154025 | I27: =I131 -> 25.352472 | J27: =J131 -> 23.313207
A28: EPS 年增 | B28: % | D28: =D132 -> 0.64838274 | E28: =E132 -> 0.71236814 | F28: =F132 -> 0.12077212 | G28: =G132 -> 0.22354363 | H28: =H132 -> 0.017603241 | I28: =I132 -> -0.030647399 | J28: =J132 -> -0.08043656
A30: 情境 C
A31: 營收 | B31: NT$B | C31: =C152 -> 166.085 | D31: =D152 -> 212.73147 | E31: =E152 -> 284.21075 | F31: =F152 -> 263.64169 | G31: =G152 -> 282.42711 | H31: =H152 -> 297.72592 | I31: =I152 -> 308.76694 | J31: =J152 -> 314.94228
A32: 營收年增 | B32: % | D32: =D153 -> 0.28085902 | E32: =E153 -> 0.33600709 | F32: =F153 -> -0.07237256 | G32: =G153 -> 0.07125358 | H32: =H153 -> 0.054169053 | I32: =I153 -> 0.037084527 | J32: =J153 -> 0.02
A33: AI 相關營收（AI 電源、BBU、液冷） | B33: NT$B | C33: =C149 -> 34.87785 | D33: =D149 -> 65.946756 | E33: =E149 -> 133.0225 | F33: =F149 -> 107.91779 | G33: =G149 -> 122.03149
A34: 非 AI 營收 | B34: NT$B | C34: =C151 -> 131.20715 | D34: =D151 -> 146.78471 | E34: =E151 -> 151.18826 | F34: =F151 -> 155.7239 | G34: =G151 -> 160.39562
A35: AI 相關 ÷ 營收 | B35: % | C35: =C154 -> 0.21 | D35: =D154 -> 0.31 | E35: =E154 -> 0.46804175 | F35: =F154 -> 0.40933506 | G35: =G154 -> 0.43208135
A36: 毛利率 | B36: % | C36: =C160 -> 0.22903333 | D36: =D160 -> 0.25418234 | E36: =E160 -> 0.26846693 | F36: =F160 -> 0.25996252 | G36: =G160 -> 0.26019047
A37: 營業利益率 | B37: % | C37: =C164 -> 0.10077972 | D37: =D164 -> 0.13567456 | E37: =E164 -> 0.1589006 | F37: =F164 -> 0.14184793 | G37: =G164 -> 0.14443278
A38: 歸屬母公司淨利 | B38: NT$B | C38: =C167 -> 15.116 | D38: =D167 -> 24.834342 | E38: =E167 -> 36.982557 | F38: =F167 -> 31.081742 | G38: =G167 -> 33.661716 | H38: =H167 -> 30.109472 | I38: =I167 -> 25.651047 | J38: =J167 -> 20.477547
A39: 淨利率 | B39: % | C39: =C171 -> 0.091013638 | D39: =D171 -> 0.11674033 | E39: =E171 -> 0.13012371 | F39: =F171 -> 0.11789388 | G39: =G171 -> 0.11918727 | H39: =H171 -> 0.10113151 | I39: =I171 -> 0.083075757 | J39: =J171 -> 0.06502
A40: EPS | B40: NT$ | C40: =C169 -> 6.64 | D40: =D169 -> 10.945261 | E40: =E169 -> 16.299355 | F40: =F169 -> 13.698684 | G40: =G169 -> 14.835758 | H40: =H169 -> 13.270174 | I40: =I169 -> 11.305209 | J40: =J169 -> 9.0250873
A41: EPS 年增 | B41: % | D41: =D170 -> 0.64838274 | E41: =E170 -> 0.48916998 | F41: =F170 -> -0.15955669 | G41: =G170 -> 0.083006076 | H41: =H170 -> -0.1055277 | I41: =I170 -> -0.14807384 | J41: =J170 -> -0.20168768
A43: 核對（應為 0）：FY2026 模型 − 錨點
A44: 三情境：營收差（NT$B） | D44: =ABS(D76-a26_rev)+ABS(D114-a26_rev)+ABS(D152-a26_rev) -> 0
A45: 情境 B：AI 相關差（NT$B） | D45: =D111-a26_ai -> 0
A46: 情境 B：毛利差（NT$B） | D46: =D120*D111+D119*D113-a26_gp -> 0
A60: 情境 A（順利）：顆數基準（tsmc 係數 A＝1.0）；份額相對值、AI 毛利率額外改善取高值
A61: 項目 | B61: 單位 | C61: FY2025A | D61: FY2026（錨點） | E61: FY2027 | F61: FY2028 | G61: FY2029 | H61: FY2030（收斂） | I61: FY2031（收斂） | J61: FY2032（收斂） | K61: 說明
A62: A. AI 部署與 AI 電源市場（D 欄＝FY2026 校準年；每 kW 內容取自台達電模型）
A63: AI IT 資本支出 × 情境顆數係數 | B63: US$B | D63: =itc_26*1 -> 781.87292 | E63: =itc_27*1*1 -> 1565.35 | F63: =itc_28*um28_A*1 -> 1984.2639 | G63: =itc_29*um29_A*1 -> 2260.3903
A64: 每 GW IT 資本支出 | B64: US$B | D64: =itpg_gb*(1-vr26)+itpg_vr*vr26 -> 33.414032 | E64: =itpg_vr -> 37.586352 | F64: =itpg_vr -> 37.586352 | G64: =itpg_vr -> 37.586352
A65: 部署 GW（IT 電力） | B65: GW | D65: =D63/D64 -> 23.399538 | E65: =E63/E64 -> 41.646766 | F65: =F63/F64 -> 52.792138 | G65: =G63/G64 -> 60.138592
A66: AI 電源內容（台達電模型） | B66: US$/kW | D66: =pkw_26 -> 450 | E66: =pkw_27 -> 600 | F66: =pkw_28 -> 680 | G66: =pkw_29 -> 720
A67: AI 電源市場（美元） | B67: US$B | D67: =D65*D66/1000 -> 10.529792 | E67: =E65*E66/1000 -> 24.988059 | F67: =F65*F66/1000 -> 35.898654 | G67: =G65*G66/1000 -> 43.299786
A68: AI 電源市場（新台幣） | B68: NT$B | D68: =D67*fx -> 336.95335 | E68: =E67*fx -> 799.6179 | F68: =F67*fx -> 1148.7569 | G68: =G67*fx -> 1385.5932
A69: 光寶有效份額（FY2026 校準）＝ AI 電源營收 ÷ 市場 | B69: % | D69: =a26_aip/D68 -> 0.17614332 | K69: Derived：分子為公司 AI 相關占比 × 營收 ×（1 − 非電源占比）；分母為與台達電模型相同的 AI 電源市場（含 ASIC 機架）
A70: 份額相對值（÷ FY2026） | B70: x | D70: =1 -> 1 | E70: =RHI_27 -> 1.1 | F70: =RHI_28 -> 1.2 | G70: =RHI_29 -> 1.25
A71: 光寶有效份額 | B71: % | D71: =$D$69*D70 -> 0.17614332 | E71: =$D$69*E70 -> 0.19375765 | F71: =$D$69*F70 -> 0.21137198 | G71: =$D$69*G70 -> 0.22017915
A72: AI 電源營收 | B72: NT$B | C72: =a25_aip -> 31.390065 | D72: =D68*D71 -> 59.35208 | E72: =E68*E71 -> 154.93208 | F72: =F68*F71 -> 242.81503 | G72: =G68*G71 -> 305.07872
A73: AI 相關營收（＝AI 電源 ÷（1 − 非電源占比）） | B73: NT$B | C73: =a25_ai -> 34.87785 | D73: =D72/(1-x_np) -> 65.946756 | E73: =E72/(1-x_np) -> 172.14676 | F73: =F72/(1-x_np) -> 269.79447 | G73: =G72/(1-x_np) -> 338.97635 | K73: 非電源部分（液冷、AI 光電）隨 AI 電源同比例成長（Assumed）
A74: B. 非 AI 與合計
A75: 非 AI 營收 | B75: NT$B | C75: =a25_nai -> 131.20715 | D75: =a26_nai -> 146.78471 | E75: =D75*(1+g_nai27) -> 151.18826 | F75: =E75*(1+g_nai28) -> 155.7239 | G75: =F75*(1+g_nai29) -> 160.39562
A76: 營收 | B76: NT$B | C76: =C73+C75 -> 166.085 | D76: =D73+D75 -> 212.73147 | E76: =E73+E75 -> 323.33502 | F76: =F73+F75 -> 425.51838 | G76: =G73+G75 -> 499.37197 | H76: =G76*(1+H77) -> 567.14057 | I76: =H76*(1+I77) -> 622.63744 | J76: =I76*(1+J77) -> 659.99569 | K76: FY2030 起為收斂法：營收年增由 FY2029 線性收斂到 fade_g、淨利率收斂到 fade_m（FY2032 達到），非驅動因子推導
A77: 營收年增 | B77: % | D77: =D76/C76-1 -> 0.28085902 | E77: =E76/D76-1 -> 0.51992094 | F77: =F76/E76-1 -> 0.31602937 | G77: =G76/F76-1 -> 0.17356147 | H77: =$G77+(fade_gA-$G77)*1/3 -> 0.13570765 | I77: =$G77+(fade_gA-$G77)*2/3 -> 0.097853824 | J77: =$G77+(fade_gA-$G77)*3/3 -> 0.06
A78: AI 相關 ÷ 營收 | B78: % | C78: =C73/C76 -> 0.21 | D78: =D73/D76 -> 0.31 | E78: =E73/E76 -> 0.53240989 | F78: =F73/F76 -> 0.63403718 | G78: =G73/G76 -> 0.67880532
A79: 每 GW 光寶 AI 相關營收 | B79: US$M/GW | D79: =D73/fx/D65*1000 -> 88.071658 | E79: =E73/fx/E65*1000 -> 129.17177 | F79: =F73/fx/F65*1000 -> 159.70327 | G79: =G73/fx/G65*1000 -> 176.14332
A80: C. 損益
A81: 其他營收毛利率 ＝ 錨點毛利率 − 差距 × AI 占比（FY2026 校準） | B81: % | D81: =a26_gp/D76-d_ai*D78 -> 0.21698234 | K81: Derived：讓 FY2026 毛利率等於錨點；AI 相關毛利率＝其他＋差距
A82: AI 相關毛利率 ＝ 校準值 ＋ 額外改善 | B82: % | D82: =D81+d_ai -> 0.33698234 | E82: =$D$82+GUHI_27 -> 0.34698234 | F82: =$D$82+GUHI_28 -> 0.35198234 | G82: =$D$82+GUHI_29 -> 0.35698234 | K82: 額外改善為 800V 電源櫃與組合（Assumed；情境 A 高、C 低）
A83: 毛利 | B83: NT$B | C83: =a25_gp -> 38.039 | D83: =a26_gp -> 54.072582 | E83: =E73*E82+E75*$D$81 -> 92.537066 | F83: =F73*F82+F75*$D$81 -> 128.75223 | G83: =G73*G82+G75*$D$81 -> 155.81159
A84: 毛利率 | B84: % | C84: =C83/C76 -> 0.22903333 | D84: =D83/D76 -> 0.25418234 | E84: =E83/E76 -> 0.28619562 | F84: =F83/F76 -> 0.30257736 | G84: =G83/G76 -> 0.31201508
A85: 營業費用（基準路徑） | B85: NT$B | C85: =a25_opx -> 21.301 | D85: =a26_opx -> 25.210333 | E85: =D85*(1+MAX(0,phi*E77)) -> 34.3855 | F85: =E85*(1+MAX(0,phi*F77)) -> 41.992279 | G85: =F85*(1+MAX(0,phi*G77)) -> 47.094048
A86: 營業費用 | B86: NT$B | C86: =C85 -> 21.301 | D86: =D85 -> 25.210333 | E86: =E85+0*E76 -> 34.3855 | F86: =F85+0*F76 -> 41.992279 | G86: =G85+0*G76 -> 47.094048
A87: 營業利益 | B87: NT$B | C87: =C83-C86 -> 16.738 | D87: =D83-D86 -> 28.862249 | E87: =E83-E86 -> 58.151567 | F87: =F83-F86 -> 86.759947 | G87: =G83-G86 -> 108.71754
A88: 營業利益率 | B88: % | C88: =C87/C76 -> 0.10077972 | D88: =D87/D76 -> 0.13567456 | E88: =E87/E76 -> 0.17984927 | F88: =F87/F76 -> 0.20389236 | G88: =G87/G76 -> 0.21770853
A89: 營業外淨額 | B89: NT$B | C89: =a25_nop -> 2.9762895 | D89: =a26_nop -> 3.839 | E89: =nop_f -> 3.5 | F89: =nop_f -> 3.5 | G89: =nop_f -> 3.5
A90: 歸屬母公司淨利 ÷ 稅前 | B90: % | C90: =a25_ni/a25_pt -> 0.76675348 | D90: =a26_ni/a26_pt -> 0.759431 | E90: =nir_f -> 0.76 | F90: =nir_f -> 0.76 | G90: =nir_f -> 0.76
A91: 歸屬母公司淨利 | B91: NT$B | C91: =a25_ni -> 15.116 | D91: =a26_ni -> 24.834342 | E91: =(E87+E89)*E90 -> 46.855191 | F91: =(F87+F89)*F90 -> 68.597559 | G91: =(G87+G89)*G90 -> 85.285329 | H91: =H76*H95 -> 96.859201 | I91: =I76*I95 -> 106.33724 | J91: =J76*J95 -> 112.71748
A92: 股數 | B92: 十億股 | C92: =a25_sh -> 2.276506 | D92: =a26_sh -> 2.2689583 | E92: =D92*(1+sh_g) -> 2.2689583 | F92: =E92*(1+sh_g) -> 2.2689583 | G92: =F92*(1+sh_g) -> 2.2689583 | H92: =G92*(1+sh_g) -> 2.2689583 | I92: =H92*(1+sh_g) -> 2.2689583 | J92: =I92*(1+sh_g) -> 2.2689583
A93: EPS | B93: NT$ | C93: =C91/C92 -> 6.64 | D93: =D91/D92 -> 10.945261 | E93: =E91/E92 -> 20.650529 | F93: =F91/F92 -> 30.233063 | G93: =G91/G92 -> 37.587878 | H93: =H91/H92 -> 42.688841 | I93: =I91/I92 -> 46.866107 | J93: =J91/J92 -> 49.678073
A94: EPS 年增 | B94: % | D94: =D93/C93-1 -> 0.64838274 | E94: =E93/D93-1 -> 0.88670956 | F94: =F93/E93-1 -> 0.4640333 | G94: =G93/F93-1 -> 0.24327061 | H94: =H93/G93-1 -> 0.13570765 | I94: =I93/H93-1 -> 0.097853824 | J94: =J93/I93-1 -> 0.06
A95: 淨利率（歸屬母公司淨利 ÷ 營收） | B95: % | C95: =C91/C76 -> 0.091013638 | D95: =D91/D76 -> 0.11674033 | E95: =E91/E76 -> 0.14491221 | F95: =F91/F76 -> 0.16120939 | G95: =G91/G76 -> 0.17078517 | H95: =$G95+(fade_mA-$G95)*1/3 -> 0.17078517 | I95: =$G95+(fade_mA-$G95)*2/3 -> 0.17078517 | J95: =$G95+(fade_mA-$G95)*3/3 -> 0.17078517
A98: 情境 B（平平）：tsmc 係數 B（CY2028 ×0.8、CY2029 ×0.85）；公司特有變數取基準
A99: 項目 | B99: 單位 | C99: FY2025A | D99: FY2026（錨點） | E99: FY2027 | F99: FY2028 | G99: FY2029 | H99: FY2030（收斂） | I99: FY2031（收斂） | J99: FY2032（收斂） | K99: 說明
A100: A. AI 部署與 AI 電源市場（D 欄＝FY2026 校準年；每 kW 內容取自台達電模型）
A101: AI IT 資本支出 × 情境顆數係數 | B101: US$B | D101: =itc_26*1 -> 781.87292 | E101: =itc_27*1*1 -> 1565.35 | F101: =itc_28*um28_B*1 -> 1587.4111 | G101: =itc_29*um29_B*1 -> 1921.3317
A102: 每 GW IT 資本支出 | B102: US$B | D102: =itpg_gb*(1-vr26)+itpg_vr*vr26 -> 33.414032 | E102: =itpg_vr -> 37.586352 | F102: =itpg_vr -> 37.586352 | G102: =itpg_vr -> 37.586352
A103: 部署 GW（IT 電力） | B103: GW | D103: =D101/D102 -> 23.399538 | E103: =E101/E102 -> 41.646766 | F103: =F101/F102 -> 42.233711 | G103: =G101/G102 -> 51.117803
A104: AI 電源內容（台達電模型） | B104: US$/kW | D104: =pkw_26 -> 450 | E104: =pkw_27 -> 600 | F104: =pkw_28 -> 680 | G104: =pkw_29 -> 720
A105: AI 電源市場（美元） | B105: US$B | D105: =D103*D104/1000 -> 10.529792 | E105: =E103*E104/1000 -> 24.988059 | F105: =F103*F104/1000 -> 28.718923 | G105: =G103*G104/1000 -> 36.804818
A106: AI 電源市場（新台幣） | B106: NT$B | D106: =D105*fx -> 336.95335 | E106: =E105*fx -> 799.6179 | F106: =F105*fx -> 919.00554 | G106: =G105*fx -> 1177.7542
A107: 光寶有效份額（FY2026 校準）＝ AI 電源營收 ÷ 市場 | B107: % | D107: =a26_aip/D106 -> 0.17614332 | K107: Derived：分子為公司 AI 相關占比 × 營收 ×（1 − 非電源占比）；分母為與台達電模型相同的 AI 電源市場（含 ASIC 機架）
A108: 份額相對值（÷ FY2026） | B108: x | D108: =1 -> 1 | E108: =rel_27 -> 1 | F108: =rel_28 -> 1 | G108: =rel_29 -> 1
A109: 光寶有效份額 | B109: % | D109: =$D$107*D108 -> 0.17614332 | E109: =$D$107*E108 -> 0.17614332 | F109: =$D$107*F108 -> 0.17614332 | G109: =$D$107*G108 -> 0.17614332
A110: AI 電源營收 | B110: NT$B | C110: =a25_aip -> 31.390065 | D110: =D106*D109 -> 59.35208 | E110: =E106*E109 -> 140.84735 | F110: =F106*F109 -> 161.87668 | G110: =G106*G109 -> 207.45353
A111: AI 相關營收（＝AI 電源 ÷（1 − 非電源占比）） | B111: NT$B | C111: =a25_ai -> 34.87785 | D111: =D110/(1-x_np) -> 65.946756 | E111: =E110/(1-x_np) -> 156.49705 | F111: =F110/(1-x_np) -> 179.86298 | G111: =G110/(1-x_np) -> 230.50392 | K111: 非電源部分（液冷、AI 光電）隨 AI 電源同比例成長（Assumed）
A112: B. 非 AI 與合計
A113: 非 AI 營收 | B113: NT$B | C113: =a25_nai -> 131.20715 | D113: =a26_nai -> 146.78471 | E113: =D113*(1+g_nai27) -> 151.18826 | F113: =E113*(1+g_nai28) -> 155.7239 | G113: =F113*(1+g_nai29) -> 160.39562
A114: 營收 | B114: NT$B | C114: =C111+C113 -> 166.085 | D114: =D111+D113 -> 212.73147 | E114: =E111+E113 -> 307.68531 | F114: =F111+F113 -> 335.58689 | G114: =G111+G113 -> 390.89954 | H114: =G114*(1+H115) -> 439.06453 | I114: =H114*(1+I115) -> 474.89565 | J114: =I114*(1+J115) -> 493.89148 | K114: FY2030 起為收斂法：營收年增由 FY2029 線性收斂到 fade_g、淨利率收斂到 fade_m（FY2032 達到），非驅動因子推導
A115: 營收年增 | B115: % | D115: =D114/C114-1 -> 0.28085902 | E115: =E114/D114-1 -> 0.4463554 | F115: =F114/E114-1 -> 0.09068218 | G115: =G114/F114-1 -> 0.16482365 | H115: =$G115+(fade_gB-$G115)*1/3 -> 0.12321576 | I115: =$G115+(fade_gB-$G115)*2/3 -> 0.081607882 | J115: =$G115+(fade_gB-$G115)*3/3 -> 0.04
A116: AI 相關 ÷ 營收 | B116: % | C116: =C111/C114 -> 0.21 | D116: =D111/D114 -> 0.31 | E116: =E111/E114 -> 0.50862699 | F116: =F111/F114 -> 0.53596547 | G116: =G111/G114 -> 0.5896756
A117: 每 GW 光寶 AI 相關營收 | B117: US$M/GW | D117: =D111/fx/D103*1000 -> 88.071658 | E117: =E111/fx/E103*1000 -> 117.42888 | F117: =F111/fx/F103*1000 -> 133.08606 | G117: =G111/fx/G103*1000 -> 140.91465
A118: C. 損益
...

Sheet Val
A1: Val — P/E 估值（新台幣）。結論用「現價 ÷ FY2027、FY2028 EPS（模型）」；目標價＝DCF 與 Comparable 加權（第 0 節）；十年 P/E 規則值（第 3 節，年底落後 P/E）只作參考。本版未做先驗，無 Andy 合理 P/E 對照
A2: 循環位置：光寶科不是設備股，不套設備市場見頂年；以本模型營收最高的會計年度為見頂年（比照台達電；FY(t)＝CY(t)）。營收到 FY2029 仍在增加時，見頂年未知，判為中段
A4: 0. 目標價
A5: 0.1 DCF（股東權益現金流，FY2027–FY2032 明確期＋FY2032 後永續）
A6: 項目 | B6: A（順利） | C6: B（平平） | D6: C（不如預期） | E6: 說明
A7: 情境 EPS（FY2027–FY2032） | E7: PL 頁各情境；FY2030 起為收斂法
A8: FY2027 | B8: =PL!E14 -> 20.650529 | C8: =PL!E27 -> 18.742317 | D8: =PL!E40 -> 16.299355
A9: FY2028 | B9: =PL!F14 -> 30.233063 | C9: =PL!F27 -> 21.005866 | D9: =PL!F40 -> 13.698684
A10: FY2029 | B10: =PL!G14 -> 37.587878 | C10: =PL!G27 -> 25.701594 | D10: =PL!G40 -> 14.835758
A11: FY2030 | B11: =PL!H14 -> 42.688841 | C11: =PL!H27 -> 26.154025 | D11: =PL!H40 -> 13.270174
A12: FY2031 | B12: =PL!I14 -> 46.866107 | C12: =PL!I27 -> 25.352472 | D12: =PL!I40 -> 11.305209
A13: FY2032 | B13: =PL!J14 -> 49.678073 | C13: =PL!J27 -> 23.313207 | D13: =PL!J40 -> 9.0250873
A14: 股東現金流＝EPS ×（1 − tp_g ÷ tp_roe）
A15: 再投資率（tp_g ÷ tp_roe，上限 0.8） | B15: =MIN(tp_g/tp_roe,0.8) -> 0.25115111 | E15: ROE 為近三年平均（In 頁 tp_roe）
A16: FY2027 | B16: =B8*(1-$B$15) -> 15.464126 | C16: =C8*(1-$B$15) -> 14.035163 | D16: =D8*(1-$B$15) -> 12.205754
A17: FY2028 | B17: =B9*(1-$B$15) -> 22.639995 | C17: =C9*(1-$B$15) -> 15.73022 | D17: =D9*(1-$B$15) -> 10.258244
A18: FY2029 | B18: =B10*(1-$B$15) -> 28.147641 | C18: =C10*(1-$B$15) -> 19.24661 | D18: =D10*(1-$B$15) -> 11.109741
A19: FY2030 | B19: =B11*(1-$B$15) -> 31.967491 | C19: =C11*(1-$B$15) -> 19.585413 | D19: =D11*(1-$B$15) -> 9.9373553
A20: FY2031 | B20: =B12*(1-$B$15) -> 35.095632 | C20: =C12*(1-$B$15) -> 18.985171 | D20: =D12*(1-$B$15) -> 8.4658929
A21: FY2032 | B21: =B13*(1-$B$15) -> 37.20137 | C21: =C13*(1-$B$15) -> 17.458069 | D21: =D13*(1-$B$15) -> 6.7584266
A22: DCF 情境每股價值（折現率 tp_r） | B22: =MAX(0,SUMPRODUCT(B16:B21,1/(1+tp_r)^{1;2;3;4;5;6})+B21*(1+tp_g)/(tp_r-tp_g)/(1+tp_r)^6) -> 482.52803 | C22: =MAX(0,SUMPRODUCT(C16:C21,1/(1+tp_r)^{1;2;3;4;5;6})+C21*(1+tp_g)/(tp_r-tp_g)/(1+tp_r)^6) -> 246.0532 | D22: =MAX(0,SUMPRODUCT(D16:D21,1/(1+tp_r)^{1;2;3;4;5;6})+D21*(1+tp_g)/(tp_r-tp_g)/(1+tp_r)^6) -> 109.90579 | E22: Σ 明確期現金流 ÷ (1＋r)^t ＋ 永續價值 ÷ (1＋r)^6；永續價值＝FY2032 現金流 ×(1＋g)÷(r−g)；基準日 2026 年底；負值取 0（Andy 12:22）
A23: DCF 情境價值推到 12 個月後（×(1＋tp_r)） | B23: =B22*(1+tp_r) -> 530.78083 | C23: =C22*(1+tp_r) -> 270.65852 | D23: =D22*(1+tp_r) -> 120.89637
A24: DCF 目標價（情境加權） | B24: =tp_wA*B23+tp_wB*C23+tp_wC*D23 -> 318.74279 | E24: Σ 權重 × 情境價值 ×(1＋r)；權重見 In 頁
A26: 0.2 Comparable（市場主流同業前瞻 P/E；非 A 股公司，同業不放 A 股）
A27: 同業與前瞻 P/E | B27: 代號 | C27: 前瞻 12 月 P/E | D27: 日期 | E27: 來源 | F27: 標記
A28: 台達電（Delta Electronics） | B28: 2308.TW | C28: 30.51 | D28: 2026-10-22 | E28: stockanalysis.com forward PE（分析師共識；價格日期如左） | F28: Interested-party
A29: Vertiv | B29: VRT | C29: 24.53 | D29: 2026-10-23 | E29: stockanalysis.com forward PE（分析師共識；價格日期如左） | F29: Interested-party
A30: Eaton | B30: ETN | C30: 24.17 | D30: 2026-10-23 | E30: stockanalysis.com forward PE（分析師共識；價格日期如左） | F30: Interested-party
A31: Flex | B31: FLEX | C31: 14.74 | D31: 2026-10-23 | E31: stockanalysis.com forward PE（分析師共識；價格日期如左） | F31: Interested-party
A33: 未列入（資料過舊）：群電 6412.TW 前瞻 P/E 13.6x（stockanalysis 快取 2026-09-04）；康舒 6282.TW 前瞻 P/E：未找到。麥格米特 002851.SZ 為 A 股，依規則不列
A34: 同業前瞻 P/E 中位數 | B34: =MEDIAN(C28:C31) -> 24.35 | E34: AI 資料中心電源與電氣同業：台達電、Vertiv、Eaton、Flex（券商常用比較組；台達電模型的同業名單也含光寶）
A35: 12 個月後的前瞻 EPS（情境加權） | B35: =tp_wA*(2/12*B8+10/12*B9)+tp_wB*(2/12*C8+10/12*C9)+tp_wC*(2/12*D8+10/12*D9) -> 21.731522 | E35: 約 2027-10 時的未來 12 月 EPS ≈ 2／12 × FY2027＋10／12 × FY2028（會計年度＝日曆年）
A36: Comparable 目標價 | B36: =B34*B35 -> 529.16256 | E36: 同業中位數 × 前瞻 EPS
A38: 0.3 結論
A39: 項目 | B39: 數值 | E39: 說明
A40: 目標價（DCF 與 Comparable 加權） | B40: =tp_w_dcf*B24+(1-tp_w_dcf)*B36 -> 423.95267 | E40: tp_w_dcf × DCF＋（1 − tp_w_dcf）× Comparable；tp_w_dcf 見 In 頁
A41: Comparable 目標價（市場主流同業法） | B41: =B36 -> 529.16256
A42: 市場共識目標價 | B42: =cons_tp -> 314.25 | E42: stockanalysis（S&P Global）：12 位分析師平均 314.25（頁面時間 2026-10-22）
A43: 上檔空間：加權目標價 | B43: =B40/px-1 -> 0.65930596 | E43: 現價＝In 頁 px（2026-10-22 收盤）
A44: 上檔空間：Comparable 目標價 | B44: =B41/px-1 -> 1.0710863
A45: 與市場共識目標價的差距：EPS 因素 | B45: =B35/cons_feps-1 -> 0.67558114 | E45: 本模型前瞻 EPS ÷ 共識前瞻 EPS − 1；共識前瞻 EPS＝現價 ÷ 前瞻 P/E（In 頁 cons_feps；期間為現在起算 12 個月，與本模型不同）
A46: 與市場共識目標價的差距：倍數因素 | B46: =(cons_tp/cons_feps)/B34-1 -> -0.0049345608 | E46: ="共識目標價隱含 "&TEXT(cons_tp/cons_feps,"0.0")&"x，同業中位數 "&TEXT(B34,"0.0")&"x" -> 共識目標價隱含 24.2x，同業中位數 24.4x
A47: 價格帶（DCF 不如預期～順利） | B47: =TEXT(D23,"0.00")&"～"&TEXT(B23,"0.00") -> 120.90～530.78 | E47: C 情境價值～A 情境價值（推到 12 個月後）
A48: 歷史倍數檢查：現價隱含 P/E 的十年分位（A／B／C） | B48: =IF(px/B9<MIN($B$90:$B$99),0,IF(px/B9>MAX($B$90:$B$99),1,PERCENTRANK($B$90:$B$99,px/B9))) -> 0 | C48: =IF(px/C9<MIN($B$90:$B$99),0,IF(px/C9>MAX($B$90:$B$99),1,PERCENTRANK($B$90:$B$99,px/C9))) -> 0.518 | D48: =IF(px/D9<MIN($B$90:$B$99),0,IF(px/D9>MAX($B$90:$B$99),1,PERCENTRANK($B$90:$B$99,px/D9))) -> 0.707 | E48: 現價 ÷ 各情境 FY2028 EPS 在 2016–2025 年底 P/E（第 6 節自算）的分位；只作檢查，不進目標價
A49: 目標價方法 | B49: DCF：股東現金流＝歸母 EPS ×（1 − g／ROE），r＝10%、g＝4%、ROE 為近三年平均約 16%（再投資率約 25%），FY2027–32 明確期＋永續；光寶 2026 年資本支出約 180 億元（約營收的 8%，含德州廠），本模型未建資本支出與折舊，未改用淨利＋折舊－資本支出，擴產期現金流可能偏高估。Comparable：台達電、Vertiv、Eaton、Flex 前瞻 P/E 中位數（不放 A 股）；台達電與 Vertiv 的 AI 占比與市占較高、歷來倍數高於光寶，光寶十年 P/E 中位數約 12x，Comparable 可能偏高估。情境對應：A＝順利（顆數基準、份額與 AI 毛利率高值）、B＝平平（顆數 ×0.8／0.85、基準）、C＝不如預期（顆數 ×0.6、低值）
A51: 1. 價格與市場隱含倍數
A52: 項目 | B52: A | C52: B | D52: C | E52: 說明
A53: 現價（2026-10-22 收盤） | B53: =px -> 255.5
A54: 現價 ÷ FY2026 EPS（錨點） | B54: =px/PL!D14 -> 23.343435 | C54: =px/PL!D27 -> 23.343435 | D54: =px/PL!D40 -> 23.343435 | E54: FY2026 三情境相同（錨點）
A55: 現價 ÷ FY2027 EPS（模型） | B55: =px/PL!E14 -> 12.372564 | C55: =px/PL!E27 -> 13.632253 | D55: =px/PL!E40 -> 15.675467 | E55: FY2027 三情境差異只來自份額相對值、AI 毛利率額外改善（顆數係數從 CY2028 開始）
A56: 現價 ÷ FY2028 EPS（模型） | B56: =px/PL!F14 -> 8.4510128 | C56: =px/PL!F27 -> 12.163269 | D56: =px/PL!F40 -> 18.651427
A57: 現價 ÷ FY2029 EPS（模型） | B57: =px/PL!G14 -> 6.7974042 | C57: =px/PL!G27 -> 9.9410177 | D57: =px/PL!G40 -> 17.221904
A58: 未來 12 月 EPS（模型 B）≈ 0.2 × FY2026＋0.8 × FY2027 | B58: =0.2*PL!D27+0.8*PL!E27 -> 17.182906
A59: 現價 ÷ 未來 12 月 EPS（模型 B） | B59: =px/B58 -> 14.869429
A60: 近 12 月 P/E（stockanalysis，10-22） | B60: =pe_ttm -> 30.09
A61: 前瞻 P/E（stockanalysis，10-22） | B61: =fpe -> 19.7
A63: 2. 循環位置（本模型營收最高年；FY(t)＝CY(t)）
A64: 情境 | B64: 營收最高年（FY2026–FY2029） | C64: FY2027 判定 | D64: 規則倍數（P/E） | E64: 見頂年是否未知 | F64: 說明
A65: A | B65: =INDEX({2026,2027,2028,2029},MATCH(MAX(PL!D76:G76),PL!D76:G76,0)) -> 2029 | C65: =IF(B65=2029,"中段",IF(2027<B65,"中段",IF(2027=B65,"見頂","谷底"))) -> 中段 | D65: =IF(C65="見頂",pe_peak,IF(C65="谷底",pe_trough,pe_mid)) -> 12.12 | E65: =IF(B65=2029,"是：營收到觀測期末仍在增加","否") -> 是：營收到觀測期末仍在增加 | F65: tools/cycle_position.py excel_rule；營收最高年取代設備市場見頂年
A66: B | B66: =INDEX({2026,2027,2028,2029},MATCH(MAX(PL!D114:G114),PL!D114:G114,0)) -> 2029 | C66: =IF(B66=2029,"中段",IF(2027<B66,"中段",IF(2027=B66,"見頂","谷底"))) -> 中段 | D66: =IF(C66="見頂",pe_peak,IF(C66="谷底",pe_trough,pe_mid)) -> 12.12 | E66: =IF(B66=2029,"是：營收到觀測期末仍在增加","否") -> 是：營收到觀測期末仍在增加 | F66: 同上
A67: C | B67: =INDEX({2026,2027,2028,2029},MATCH(MAX(PL!D152:G152),PL!D152:G152,0)) -> 2027 | C67: =IF(B67=2029,"中段",IF(2027<B67,"中段",IF(2027=B67,"見頂","谷底"))) -> 見頂 | D67: =IF(C67="見頂",pe_peak,IF(C67="谷底",pe_trough,pe_mid)) -> 11.63 | E67: =IF(B67=2029,"是：營收到觀測期末仍在增加","否") -> 否 | F67: 同上
A69: 3. 規則值隱含股價（新台幣；約 FY2027 年底，未折現）＝ FY2027 EPS × 規則倍數（參考，不是目標價）
A70: 情境 | B70: FY2027 EPS | C70: （同左） | D70: 規則倍數 | E70: 隱含股價 | F70: 相對現價 | G70: 現價 ÷ FY2027 EPS
A71: A | B71: =PL!E14 -> 20.650529 | C71: =B71 -> 20.650529 | D71: =D65 -> 12.12 | E71: =C71*D71 -> 250.28442 | F71: =E71/px-1 -> -0.020413246 | G71: =px/C71 -> 12.372564
A72: B | B72: =PL!E27 -> 18.742317 | C72: =B72 -> 18.742317 | D72: =D66 -> 12.12 | E72: =C72*D72 -> 227.15688 | F72: =E72/px-1 -> -0.11093197 | G72: =px/C72 -> 13.632253
A73: C | B73: =PL!E40 -> 16.299355 | C73: =B73 -> 16.299355 | D73: =D67 -> 11.63 | E73: =C73*D73 -> 189.5615 | F73: =E73/px-1 -> -0.25807634 | G73: =px/C73 -> 15.675467
A75: 4. What must be true：FY2027 年底價 ＝ 現價 ×（1＋報酬）所需的倍數（FY2028 EPS；約 2027 年底的價格看下一年 EPS）
A76: FY2027 年底價 ÷ 現價 | B76: 所需倍數（÷ FY2028 EPS，A） | C76: 所需倍數（÷ FY2028 EPS，B） | D76: 所需倍數（÷ FY2028 EPS，C） | E76: 對照：十年中位數
A77: 1 | B77: =px*A77/PL!F14 -> 8.4510128 | C77: =px*A77/PL!F27 -> 12.163269 | D77: =px*A77/PL!F40 -> 18.651427 | E77: =pe_mid -> 12.12
A78: 1.1 | B78: =px*A78/PL!F14 -> 9.2961141 | C78: =px*A78/PL!F27 -> 13.379596 | D78: =px*A78/PL!F40 -> 20.51657 | E78: =pe_mid -> 12.12
A79: 1.21 | B79: =px*A79/PL!F14 -> 10.225726 | C79: =px*A79/PL!F27 -> 14.717555 | D79: =px*A79/PL!F40 -> 22.568227 | E79: =pe_mid -> 12.12
A80: 1.5 | B80: =px*A80/PL!F14 -> 12.676519 | C80: =px*A80/PL!F27 -> 18.244903 | D80: =px*A80/PL!F40 -> 27.977141 | E80: =pe_mid -> 12.12
A81: 2 | B81: =px*A81/PL!F14 -> 16.902026 | C81: =px*A81/PL!F27 -> 24.326538 | D81: =px*A81/PL!F40 -> 37.302854 | E81: =pe_mid -> 12.12
A82: 讀法：1.00＝價格不變、1.21＝一年約 21%。所需倍數低於歷史中位數時，現價相對便宜；倍數是否合理，另看前瞻 P/E 歷史（Bloomberg）。本版未做先驗，無 Andy 合理 P/E 對照。
A85: 6. 十年倍數與規則值（2016–2025 年底；見頂年 25 分位、中段中位數、谷底 75 分位）
A86: 規則（Andy 2026-10-13）：合理倍數＝2016–2025 年底 P/E 依循環位置取分位。採用自算（10 年）；HiStock 只有 2021–2025，與自算同量級，只作核對；companiesmarketcap 光寶頁無法取得（網站錯誤）。2016–2022 年光寶為低成長消費電子與電源零組件公司（約 10–12x，2017 年 EPS 1.13 含一次性損失使 P/E 偏高），AI 前後倍數口徑不同，規則值可能低估 AI 期的合理倍數。
A88: P/E：十年歷史倍數
A89: 年底 | B89: 自算（digrin 12 月未調整價格 ÷ 年度 EPS） | C89: HiStock（12 月 P/E） | D89: 標記／說明
A90: 2016 | B90: =48.6/4.05 -> 12 | D90: 自算（digrin 12 月未調整價格 ÷ 年度 EPS）：Derived（EPS：wearn 2016–2025；10 年）；HiStock（12 月 P/E）：Interested-party（資料商；只有 2021–2025，只作核對，不採用）
A91: 2017 | B91: =40.6/1.13 -> 35.929204
A92: 2018 | B92: =40.6/3.42 -> 11.871345
A93: 2019 | B93: =49.35/4.03 -> 12.245658
A94: 2020 | B94: =49.8/4.31 -> 11.554524
A95: 2021 | B95: =63.8/6.01 -> 10.615641 | C95: 10.89
A96: 2022 | B96: =63.8/6.19 -> 10.306947 | C96: 11.39
A97: 2023 | B97: =117/6.36 -> 18.396226 | C97: 18.03
A98: 2024 | B98: =99.5/5.21 -> 19.097889 | C98: 18.53
A99: 2025 | B99: =163.5/6.64 -> 24.623494 | C99: 25.95
A100: 25 分位（各來源） | B100: =PERCENTILE(B90:B99,0.25) -> 11.63373 | C100: =PERCENTILE(C90:C99,0.25) -> 11.39
A101: 中位數（各來源） | B101: =MEDIAN(B90:B99) -> 12.122829 | C101: =MEDIAN(C90:C99) -> 18.03
A102: 75 分位（各來源） | B102: =PERCENTILE(B90:B99,0.75) -> 18.922473 | C102: =PERCENTILE(C90:C99,0.75) -> 18.53
A103: 最小（各來源） | B103: =MIN(B90:B99) -> 10.306947 | C103: =MIN(C90:C99) -> 10.89
A104: 最大（各來源） | B104: =MAX(B90:B99) -> 35.929204 | C104: =MAX(C90:C99) -> 25.95
A105: 採用 25 分位（P/E） | B105: =ROUND(AVERAGE(B100),2) -> 11.63
A106: 採用 中位數（P/E） | B106: =ROUND(AVERAGE(B101),2) -> 12.12
A107: 採用 75 分位（P/E） | B107: =ROUND(AVERAGE(B102),2) -> 18.92
A108: 採用 最小（P/E） | B108: =ROUND(MIN(B103),2) -> 10.31
A109: 採用 最大（P/E） | B109: =ROUND(MAX(B104),2) -> 35.93
A111: P/E：規則值
A112: 情形 | B112: 循環位置 | C112: 倍數 | D112: 基準 | E112: 每股基準 | F112: 隱含股價 | G112: 相對目前 | H112: 現價 ÷ 基準
...

Sheet Recon
A1: Recon — 本模型 vs 共識（MarketScreener、stockanalysis）、台達電模型的 AI 電源市場與份額、凱基份額。只作事後對照，不為對上數字而調參數。FY2027 起共識只有一個來源
A3: 項目 | B3: 對照值 | C3: 模型 A | D3: 差距 A | E3: 模型 B | F3: 差距 B | G3: 模型 C | H3: 差距 C | I3: 對照來源 | J3: 說明
A4: A. 共識（校準未使用）
A5: FY2026 營收 vs 共識（MarketScreener） | B5: =cons_rev26 -> 219.778 | C5: =PL!D76 -> 212.73147 | D5: =C5/B5-1 -> -0.032062035 | E5: =PL!D114 -> 212.73147 | F5: =E5/B5-1 -> -0.032062035 | G5: =PL!D152 -> 212.73147 | H5: =G5/B5-1 -> -0.032062035 | I5: MarketScreener（參考價 2026-10-22） | J5: stockanalysis 2,193 億
A6: FY2026 EPS vs 共識（MarketScreener） | B6: =cons_eps26 -> 10.81 | C6: =PL!D93 -> 10.945261 | D6: =C6/B6-1 -> 0.012512619 | E6: =PL!D131 -> 10.945261 | F6: =E6/B6-1 -> 0.012512619 | G6: =PL!D169 -> 10.945261 | H6: =G6/B6-1 -> 0.012512619 | I6: MarketScreener | J6: stockanalysis 10.81（11 家）；3Q26 財報（10-30 前後）前
A7: FY2027 營收 vs 共識（MarketScreener） | B7: =cons_rev27 -> 292.383 | C7: =PL!E76 -> 323.33502 | D7: =C7/B7-1 -> 0.1058612 | E7: =PL!E114 -> 307.68531 | F7: =E7/B7-1 -> 0.052336526 | G7: =PL!E152 -> 284.21075 | H7: =G7/B7-1 -> -0.027950488 | I7: MarketScreener
A8: FY2027 EPS vs 共識（MarketScreener） | B8: =cons_eps27 -> 14.99 | C8: =PL!E93 -> 20.650529 | D8: =C8/B8-1 -> 0.37762037 | E8: =PL!E131 -> 18.742317 | F8: =E8/B8-1 -> 0.25032134 | G8: =PL!E169 -> 16.299355 | H8: =G8/B8-1 -> 0.087348547 | I8: MarketScreener | J8: 差距說明見 README（部署 GW 2027 年約 1.8 倍）
A9: FY2028 營收 vs 共識（MarketScreener） | B9: =cons_rev28 -> 366.11 | C9: =PL!F76 -> 425.51838 | D9: =C9/B9-1 -> 0.1622692 | E9: =PL!F114 -> 335.58689 | F9: =E9/B9-1 -> -0.083371431 | G9: =PL!F152 -> 263.64169 | H9: =G9/B9-1 -> -0.27988393 | I9: MarketScreener
A10: FY2028 EPS vs 共識（MarketScreener） | B10: =cons_eps28 -> 20.74 | C10: =PL!F93 -> 30.233063 | D10: =C10/B10-1 -> 0.45771758 | E10: =PL!F131 -> 21.005866 | F10: =E10/B10-1 -> 0.012819011 | G10: =PL!F169 -> 13.698684 | H10: =G10/B10-1 -> -0.33950416 | I10: MarketScreener
A11: B. AI 電源市場與份額（與台達電模型一致性檢查）
A12: CY2026 AI 電源市場（US$B）vs 台達電模型（情境 A） | B12: =d_pmk26 -> 10.529792 | C12: =PL!D67 -> 10.529792 | D12: =C12/B12-1 -> -3.5527137e-15 | E12: =PL!D105 -> 10.529792 | F12: =E12/B12-1 -> -3.5527137e-15 | G12: =PL!D143 -> 10.529792 | H12: =G12/B12-1 -> -3.5527137e-15 | I12: delta/dist Units 頁（唯讀） | J12: 情境 A 應為 0%（同一部署 GW × 同一每 kW 內容）
A13: CY2027 AI 電源市場（US$B）vs 台達電模型（情境 A） | B13: =d_pmk27 -> 24.988059 | C13: =PL!E67 -> 24.988059 | D13: =C13/B13-1 -> 0 | E13: =PL!E105 -> 24.988059 | F13: =E13/B13-1 -> 0 | G13: =PL!E143 -> 24.988059 | H13: =G13/B13-1 -> 0 | I13: 同上
A14: CY2028 AI 電源市場（US$B）vs 台達電模型（情境 A） | B14: =d_pmk28 -> 35.898654 | C14: =PL!F67 -> 35.898654 | D14: =C14/B14-1 -> 0 | E14: =PL!F105 -> 28.718923 | F14: =E14/B14-1 -> -0.2 | G14: =PL!F143 -> 21.539192 | H14: =G14/B14-1 -> -0.4 | I14: 同上 | J14: 情境 B、C 低於台達電情境 A：顆數係數
A15: CY2026 光寶＋台達電 AI 電源有效份額合計 | C15: =PL!D71+d_sh26 -> 0.75981526 | E15: =PL!D109+d_sh26 -> 0.75981526 | G15: =PL!D147+d_sh26 -> 0.75981526 | I15: 本模型＋delta/dist Units 頁 | J15: 應低於 100%；其餘為 Flex、群電、康舒、Vertiv、麥格米特等
A16: CY2027 光寶＋台達電 AI 電源有效份額合計 | C16: =PL!E71+d_sh27 -> 0.74824599 | E16: =PL!E109+d_sh27 -> 0.73063166 | G16: =PL!E147+d_sh27 -> 0.70421016 | I16: 本模型＋delta/dist Units 頁 | J16: —
A17: CY2028 光寶＋台達電 AI 電源有效份額合計 | C17: =PL!F71+d_sh28 -> 0.73667673 | E17: =PL!F109+d_sh28 -> 0.70144806 | G17: =PL!F147+d_sh28 -> 0.6662194 | I17: 本模型＋delta/dist Units 頁 | J17: —
A18: CY2029 光寶＋台達電 AI 電源有效份額合計 | C18: =PL!G71+d_sh29 -> 0.71630029 | E18: =PL!G109+d_sh29 -> 0.67226446 | G18: =PL!G147+d_sh29 -> 0.62822864 | I18: 本模型＋delta/dist Units 頁 | J18: —
A19: FY2026 台達電模型份額 vs 凱基台達電市占（中點） | B19: =kgi_dsh -> 0.625 | C19: =d_sh26 -> 0.58367194 | D19: =C19-B19 -> -0.041328061 | E19: =d_sh26 -> 0.58367194 | F19: =E19-B19 -> -0.041328061 | G19: =d_sh26 -> 0.58367194 | H19: =G19-B19 -> -0.041328061 | I19: 凱基 2025-09（Interested-party） | J19: 口徑不同：模型分母含 ASIC 機架、HVDC、BBU
A20: CY2027 光寶 AI 電源營收 ÷ 台達電 AI 電源營收 | C20: =PL!E71/d_sh27 -> 0.34943503 | E20: =PL!E109/d_sh27 -> 0.3176682 | G20: =PL!E147/d_sh27 -> 0.27001797 | I20: 本模型＋delta/dist | J20: 同一市場，等於份額比
A21: CY2027 每 GW 光寶 AI 相關營收（US$M） | C21: =PL!E79 -> 129.17177 | E21: =PL!E117 -> 117.42888 | G21: =PL!E155 -> 99.814546 | I21: — | J21: 台達電模型 CY2027 每 GW AI 營收（電源＋液冷）約 470
A22: C. 校準
A23: 其他營收毛利率（Derived） | C23: =PL!D81 -> 0.21698234 | E23: =PL!D119 -> 0.21698234 | G23: =PL!D157 -> 0.21698234 | I23: FY2026 錨點 | J23: AI 相關毛利率＝此值＋d_ai
A24: FY2027 毛利率 vs FY2026（百分點） | B24: =a26_gp/a26_rev -> 0.25418234 | C24: =PL!E84 -> 0.28619562 | D24: =C24-B24 -> 0.032013286 | E24: =PL!E122 -> 0.27801758 | F24: =E24-B24 -> 0.023835239 | G24: =PL!E160 -> 0.26846693 | H24: =G24-B24 -> 0.014284592 | I24: 錨點 | J24: AI 占比上升使毛利率上升
A25: FY2027 營業利益率 vs 2Q26 實績 15.6%（百分點） | B25: =8.203/52.703 -> 0.15564579 | C25: =PL!E88 -> 0.17984927 | D25: =C25-B25 -> 0.024203481 | E25: =PL!E126 -> 0.1704815 | F25: =E25-B25 -> 0.01483571 | G25: =PL!E164 -> 0.1589006 | H25: =G25-B25 -> 0.0032548106 | I25: stockanalysis 2Q26
A26: 4Q26 EPS（模型） | C26: =Q!E15 -> 3.1135873 | E26: =Q!E15 -> 3.1135873 | G26: =Q!E15 -> 3.1135873 | I26: — | J26: 3Q26 財報 10-30 前後公布
A27: D. 預留
A28: R4 產業部署路徑（markets/deploy_path/，尚未建立）：上線後以部署路徑取代「AI IT 資本支出 ÷ 每 GW IT 資本支出」 | J28: 預留列：本版無數值
A29: E. 目標價對帳（模型欄為情境加權值，只填 A 欄）
A30: 12 個月後的前瞻 EPS（情境加權）vs 共識前瞻 EPS | B30: =cons_feps -> 12.969543 | C30: =Val!B35 -> 21.731522 | D30: =C30/B30-1 -> 0.67558114 | I30: stockanalysis 前瞻 P/E（10-22） | J30: 共識只作對帳，不作校準
A31: 目標價（DCF 與 Comparable 加權）vs 市場共識目標價 | B31: =cons_tp -> 314.25 | C31: =Val!B40 -> 423.95267 | D31: =C31/B31-1 -> 0.34909363 | I31: stockanalysis（S&P Global）12 位分析師 | J31: 共識只作對帳，不作校準
A32: Comparable 目標價 vs 市場共識目標價 | B32: =cons_tp -> 314.25 | C32: =Val!B36 -> 529.16256 | D32: =C32/B32-1 -> 0.6838904 | I32: 同上 | J32: 共識只作對帳，不作校準

Sheet Sens
A1: Sens — 一次動一個輸入（情境 B＝基準輸入；有效份額、其他營收毛利率在每個案例內依 FY2026 錨點重算，FY2026 恆等於錨點）：對 FY2027、FY2028 的營收、AI 相關營收、毛利率與 EPS 的影響。每個案例是一個完整推導區塊（本頁下方）
A3: 案例 | B3: 設定 | C3: FY2027 營收 | D3: FY2027 AI 相關 | E3: FY2027 毛利率 | F3: FY2027 EPS | G3: FY2027 EPS 相對基準 | H3: FY2028 營收 | I3: FY2028 AI 相關 | J3: FY2028 毛利率 | K3: FY2028 EPS | L3: FY2028 EPS 相對基準
A4: 基準（情境 B） | B4: PL 區塊 B | C4: =PL!E114 -> 307.68531 | D4: =PL!E111 -> 156.49705 | E4: =PL!E122 -> 0.27801758 | F4: =PL!E131 -> 18.742317 | G4: =F4/F$4-1 -> 0 | H4: =PL!F114 -> 335.58689 | I4: =PL!F111 -> 179.86298 | J4: =PL!F122 -> 0.28129819 | K4: =PL!F131 -> 21.005866 | L4: =K4/K$4-1 -> 0
A5: 份額流失（低） | B5: 份額相對值 2027 0.85、2028 0.80、2029 0.75（台達電、Flex、中國廠競爭） | C5: =E66 -> 284.21075 | D5: =E63 -> 133.0225 | E5: =E74 -> 0.27314735 | F5: =E83 -> 16.744921 | G5: =F5/F$4-1 -> -0.10657146 | H5: =F66 -> 299.61429 | I5: =F63 -> 143.89039 | J5: =F74 -> 0.27461259 | K5: =F83 -> 17.905557 | L5: =K5/K$4-1 -> -0.14759255
A6: 份額提升（高） | B6: 份額相對值 2027 1.10、2028 1.20、2029 1.25（新 CSP 客戶、800V 電源櫃） | C6: =E104 -> 323.33502 | D6: =E101 -> 172.14676 | E6: =E112 -> 0.28087152 | F6: =E121 -> 20.073914 | G6: =F6/F$4-1 -> 0.071047641 | H6: =F104 -> 371.55948 | I6: =F101 -> 215.83558 | J6: =F112 -> 0.28668926 | K6: =F121 -> 24.132425 | L6: =K6/K$4-1 -> 0.14884218
A7: 電源內容 低 | B7: 每 kW：2026 380、2027 500、2028–29 550（台達電模型低值） | C7: =E142 -> 305.62614 | D7: =E139 -> 154.43788 | E7: =E150 -> 0.2776203 | F7: =E159 -> 18.567107 | G7: =F7/F$4-1 -> -0.0093483738 | H7: =F142 -> 327.99979 | I7: =F139 -> 172.27588 | J7: =F150 -> 0.28001014 | K7: =F159 -> 20.345208 | L7: =K7/K$4-1 -> -0.031451135
A8: 電源內容 高 | B8: 每 kW：2026 520、2027 700、2028 800、2029 850（台達電模型高值） | C8: =E180 -> 309.19009 | D8: =E177 -> 158.00183 | E8: =E188 -> 0.27830455 | F8: =E197 -> 18.870355 | G8: =F8/F$4-1 -> 0.0068315039 | H8: =F180 -> 338.84232 | I8: =F177 -> 183.11842 | J8: =F188 -> 0.28183318 | K8: =F197 -> 21.288199 | L8: =K8/K$4-1 -> 0.013440679
A9: AI 部署 ×0.8 | B9: FY2027 起 AI IT 資本支出 ×0.8 | C9: =E218 -> 276.3859 | D9: =E215 -> 125.19764 | E9: =E226 -> 0.27134009 | F9: =E235 -> 16.079122 | G9: =F9/F$4-1 -> -0.14209528 | H9: =F218 -> 299.61429 | I9: =F215 -> 143.89039 | J9: =F226 -> 0.27461259 | K9: =F235 -> 17.917858 | L9: =K9/K$4-1 -> -0.14700693
A10: AI 部署 ×1.2 | B10: ×1.2 | C10: =E256 -> 338.98472 | D10: =E253 -> 187.79647 | E10: =E264 -> 0.28346196 | F10: =E273 -> 21.405512 | G10: =F10/F$4-1 -> 0.14209528 | H10: =F256 -> 371.55948 | I10: =F253 -> 215.83558 | J10: =F264 -> 0.28668926 | K10: =F273 -> 24.096048 | L10: =K10/K$4-1 -> 0.14711042
A11: AI 毛利率差距 8pt | B11: AI 相關毛利率只高 8 個百分點 | C11: =E294 -> 307.68531 | D11: =E291 -> 156.49705 | E11: =E302 -> 0.2700725 | F11: =E311 -> 17.92349 | G11: =F11/F$4-1 -> -0.04368867 | H11: =F294 -> 335.58689 | I11: =F291 -> 179.86298 | J11: =F302 -> 0.27225957 | K11: =F311 -> 19.989865 | L11: =K11/K$4-1 -> -0.048367487
A12: AI 毛利率差距 16pt | B12: 高 16 個百分點 | C12: =E332 -> 307.68531 | D12: =E329 -> 156.49705 | E12: =E340 -> 0.28596266 | F12: =E349 -> 19.561144 | G12: =F12/F$4-1 -> 0.04368867 | H12: =F332 -> 335.58689 | I12: =F329 -> 179.86298 | J12: =F340 -> 0.29033681 | K12: =F349 -> 22.021867 | L12: =K12/K$4-1 -> 0.048367487
A13: AI 毛利率額外改善 低 | B13: 2027 −1pt、2028 −1.5pt、2029 −2pt | C13: =E370 -> 307.68531 | D13: =E367 -> 156.49705 | E13: =E378 -> 0.27293131 | F13: =E387 -> 18.218122 | G13: =F13/F$4-1 -> -0.027968551 | H13: =F370 -> 335.58689 | I13: =F367 -> 179.86298 | J13: =F378 -> 0.27325871 | K13: =F387 -> 20.102175 | L13: =K13/K$4-1 -> -0.043020903
A14: AI 毛利率額外改善 高 | B14: 2027 +1pt、2028 +1.5pt、2029 +2pt | C14: =E408 -> 307.68531 | D14: =E405 -> 156.49705 | E14: =E416 -> 0.28310385 | F14: =E425 -> 19.266512 | G14: =F14/F$4-1 -> 0.027968551 | H14: =F408 -> 335.58689 | I14: =F405 -> 179.86298 | J14: =F416 -> 0.28933768 | K14: =F425 -> 21.909558 | L14: =K14/K$4-1 -> 0.043020903
A15: 非 AI 成長 低 | B15: 2027–29 −3% | C15: =E446 -> 298.87823 | D15: =E443 -> 156.49705 | E15: =E454 -> 0.27981611 | F15: =E463 -> 18.34694 | G15: =F15/F$4-1 -> -0.021095403 | H15: =F446 -> 317.97272 | I15: =F443 -> 179.86298 | J15: =F454 -> 0.28486098 | K15: =F463 -> 20.189214 | L15: =K15/K$4-1 -> -0.038877363
A16: 非 AI 成長 高 | B16: 2027–29 +6% | C16: =E484 -> 312.08885 | D16: =E481 -> 156.49705 | E16: =E492 -> 0.27715638 | F16: =E501 -> 18.940005 | G16: =F16/F$4-1 -> 0.010547702 | H16: =F484 -> 344.79029 | I16: =F481 -> 179.86298 | J16: =F492 -> 0.27958143 | K16: =F501 -> 21.434042 | L16: =K16/K$4-1 -> 0.020383627
A17: 營業費用率 +1pt | B17: 營業費用額外 +1% × 營收 | C17: =E522 -> 307.68531 | D17: =E519 -> 156.49705 | E17: =E530 -> 0.27801758 | F17: =E539 -> 17.711708 | G17: =F17/F$4-1 -> -0.054988333 | H17: =F522 -> 335.58689 | I17: =F519 -> 179.86298 | J17: =F530 -> 0.28129819 | K17: =F539 -> 19.8818 | L17: =K17/K$4-1 -> -0.053512034
A18: 營業費用彈性 1.0 | B18: 基準 0.7 | C18: =E560 -> 307.68531 | D18: =E557 -> 156.49705 | E18: =E568 -> 0.27801758 | F18: =E577 -> 17.611564 | G18: =F18/F$4-1 -> -0.060331543 | H18: =F560 -> 335.58689 | I18: =F557 -> 179.86298 | J18: =F568 -> 0.28129819 | K18: =F577 -> 19.471072 | L18: =K18/K$4-1 -> -0.073065054
A19: 淨利 ÷ 稅前 0.73 | B19: 基準 0.76 | C19: =E598 -> 307.68531 | D19: =E595 -> 156.49705 | E19: =E606 -> 0.27801758 | F19: =E615 -> 18.002489 | G19: =F19/F$4-1 -> -0.039473684 | H19: =F598 -> 335.58689 | I19: =F595 -> 179.86298 | J19: =F606 -> 0.28129819 | K19: =F615 -> 20.176687 | L19: =K19/K$4-1 -> -0.039473684
A20: 淨利 ÷ 稅前 0.78 | C20: =E636 -> 307.68531 | D20: =E633 -> 156.49705 | E20: =E644 -> 0.27801758 | F20: =E653 -> 19.235536 | G20: =F20/F$4-1 -> 0.026315789 | H20: =F636 -> 335.58689 | I20: =F633 -> 179.86298 | J20: =F644 -> 0.28129819 | K20: =F653 -> 21.558652 | L20: =K20/K$4-1 -> 0.026315789
A21: 情境 A（全部） | B21: 顆數係數 A＋份額相對值、AI 毛利率額外改善高值 | C21: =PL!E76 -> 323.33502 | D21: =PL!E73 -> 172.14676 | E21: =PL!E84 -> 0.28619562 | F21: =PL!E93 -> 20.650529 | G21: =F21/F$4-1 -> 0.10181305 | H21: =PL!F76 -> 425.51838 | I21: =PL!F73 -> 269.79447 | J21: =PL!F84 -> 0.30257736 | K21: =PL!F93 -> 30.233063 | L21: =K21/K$4-1 -> 0.43926759
A22: 情境 C（全部） | B22: 顆數係數 C＋份額相對值、AI 毛利率額外改善低值 | C22: =PL!E152 -> 284.21075 | D22: =PL!E149 -> 133.0225 | E22: =PL!E160 -> 0.26846693 | F22: =PL!E169 -> 16.299355 | G22: =F22/F$4-1 -> -0.13034473 | H22: =PL!F152 -> 263.64169 | I22: =PL!F149 -> 107.91779 | J22: =PL!F160 -> 0.25996252 | K22: =PL!F169 -> 13.698684 | L22: =K22/K$4-1 -> -0.3478639
A24: 讀法：基準為情境 B（顆數係數 B 從 CY2028 起）。每個案例的 FY2026 有效份額與其他營收毛利率依該案例重算，所以 FY2026 恆等於錨點；「電源內容」案例的 FY2026 份額會反向調整（內容低 → 份額高），所以只影響 FY2027 起的成長路徑。AI 相關中非電源占比（x_np）只影響份額，不影響營收與 EPS，未列入。
A26: 目標價參數（只改 DCF 參數；PL 收斂法的 fade_g 不隨 tp_g 變動）
A27: 案例 | B27: 設定 | C27: DCF 目標價 | D27: Comparable 目標價 | E27: 加權目標價 | F27: 相對基準
A28: 基準 | B28: r 10%、g 4%、DCF 權重 0.5 | C28: =(tp_wA*MAX(0,Val!B8*(1-MIN(tp_g/tp_roe,0.8))/(1+tp_r)^1+Val!B9*(1-MIN(tp_g/tp_roe,0.8))/(1+tp_r)^2+Val!B10*(1-MIN(tp_g/tp_roe,0.8))/(1+tp_r)^3+Val!B11*(1-MIN(tp_g/tp_roe,0.8))/(1+tp_r)^4+Val!B12*(1-MIN(tp_g/tp_roe,0.8))/(1+tp_r)^5+Val!B13*(1-MIN(tp_g/tp_roe,0.8))/(1+tp_r)^6+Val!B13*(1-MIN(tp_g/tp_roe,0.8))*(1+tp_g)/(tp_r-tp_g)/(1+tp_r)^6)+tp_wB*MAX(0,Val!C8*(1-MIN(tp_g/tp_roe,0.8))/(1+tp_r)^1+Val!C9*(1-MIN(tp_g/tp_roe,0.8))/(1+tp_r)^2+Val!C10*(1-MIN(tp_g/tp_roe,0.8))/(1+tp_r)^3+Val!C11*(1-MIN(tp_g/tp_roe,0.8))/(1+tp_r)^4+Val!C12*(1-MIN(tp_g/tp_roe,0.8))/(1+tp_r)^5+Val!C13*(1-MIN(tp_g/tp_roe,0.8))/(1+tp_r)^6+Val!C13*(1-MIN(tp_g/tp_roe,0.8))*(1+tp_g)/(tp_r-tp_g)/(1+tp_r)^6)+tp_wC*MAX(0,Val!D8*(1-MIN(tp_g/tp_roe,0.8))/(1+tp_r)^1+Val!D9*(1-MIN(tp_g/tp_roe,0.8))/(1+tp_r)^2+Val!D10*(1-MIN(tp_g/tp_roe,0.8))/(1+tp_r)^3+Val!D11*(1-MIN(tp_g/tp_roe,0.8))/(1+tp_r)^4+Val!D12*(1-MIN(tp_g/tp_roe,0.8))/(1+tp_r)^5+Val!D13*(1-MIN(tp_g/tp_roe,0.8))/(1+tp_r)^6+Val!D13*(1-MIN(tp_g/tp_roe,0.8))*(1+tp_g)/(tp_r-tp_g)/(1+tp_r)^6))*(1+tp_r) -> 318.74279 | D28: =Val!B36 -> 529.16256 | E28: =tp_w_dcf*C28+(1-tp_w_dcf)*D28 -> 423.95267 | F28: =E28/E$28-1 -> 0
A29: 折現率 +1pt | B29: r 11% | C29: =(tp_wA*MAX(0,Val!B8*(1-MIN(tp_g/tp_roe,0.8))/(1+(tp_r+0.01))^1+Val!B9*(1-MIN(tp_g/tp_roe,0.8))/(1+(tp_r+0.01))^2+Val!B10*(1-MIN(tp_g/tp_roe,0.8))/(1+(tp_r+0.01))^3+Val!B11*(1-MIN(tp_g/tp_roe,0.8))/(1+(tp_r+0.01))^4+Val!B12*(1-MIN(tp_g/tp_roe,0.8))/(1+(tp_r+0.01))^5+Val!B13*(1-MIN(tp_g/tp_roe,0.8))/(1+(tp_r+0.01))^6+Val!B13*(1-MIN(tp_g/tp_roe,0.8))*(1+tp_g)/((tp_r+0.01)-tp_g)/(1+(tp_r+0.01))^6)+tp_wB*MAX(0,Val!C8*(1-MIN(tp_g/tp_roe,0.8))/(1+(tp_r+0.01))^1+Val!C9*(1-MIN(tp_g/tp_roe,0.8))/(1+(tp_r+0.01))^2+Val!C10*(1-MIN(tp_g/tp_roe,0.8))/(1+(tp_r+0.01))^3+Val!C11*(1-MIN(tp_g/tp_roe,0.8))/(1+(tp_r+0.01))^4+Val!C12*(1-MIN(tp_g/tp_roe,0.8))/(1+(tp_r+0.01))^5+Val!C13*(1-MIN(tp_g/tp_roe,0.8))/(1+(tp_r+0.01))^6+Val!C13*(1-MIN(tp_g/tp_roe,0.8))*(1+tp_g)/((tp_r+0.01)-tp_g)/(1+(tp_r+0.01))^6)+tp_wC*MAX(0,Val!D8*(1-MIN(tp_g/tp_roe,0.8))/(1+(tp_r+0.01))^1+Val!D9*(1-MIN(tp_g/tp_roe,0.8))/(1+(tp_r+0.01))^2+Val!D10*(1-MIN(tp_g/tp_roe,0.8))/(1+(tp_r+0.01))^3+Val!D11*(1-MIN(tp_g/tp_roe,0.8))/(1+(tp_r+0.01))^4+Val!D12*(1-MIN(tp_g/tp_roe,0.8))/(1+(tp_r+0.01))^5+Val!D13*(1-MIN(tp_g/tp_roe,0.8))/(1+(tp_r+0.01))^6+Val!D13*(1-MIN(tp_g/tp_roe,0.8))*(1+tp_g)/((tp_r+0.01)-tp_g)/(1+(tp_r+0.01))^6))*(1+(tp_r+0.01)) -> 275.43665 | D29: =Val!B36 -> 529.16256 | E29: =tp_w_dcf*C29+(1-tp_w_dcf)*D29 -> 402.2996 | F29: =E29/E$28-1 -> -0.051074259
A30: 折現率 −1pt | B30: r 9% | C30: =(tp_wA*MAX(0,Val!B8*(1-MIN(tp_g/tp_roe,0.8))/(1+(tp_r-0.01))^1+Val!B9*(1-MIN(tp_g/tp_roe,0.8))/(1+(tp_r-0.01))^2+Val!B10*(1-MIN(tp_g/tp_roe,0.8))/(1+(tp_r-0.01))^3+Val!B11*(1-MIN(tp_g/tp_roe,0.8))/(1+(tp_r-0.01))^4+Val!B12*(1-MIN(tp_g/tp_roe,0.8))/(1+(tp_r-0.01))^5+Val!B13*(1-MIN(tp_g/tp_roe,0.8))/(1+(tp_r-0.01))^6+Val!B13*(1-MIN(tp_g/tp_roe,0.8))*(1+tp_g)/((tp_r-0.01)-tp_g)/(1+(tp_r-0.01))^6)+tp_wB*MAX(0,Val!C8*(1-MIN(tp_g/tp_roe,0.8))/(1+(tp_r-0.01))^1+Val!C9*(1-MIN(tp_g/tp_roe,0.8))/(1+(tp_r-0.01))^2+Val!C10*(1-MIN(tp_g/tp_roe,0.8))/(1+(tp_r-0.01))^3+Val!C11*(1-MIN(tp_g/tp_roe,0.8))/(1+(tp_r-0.01))^4+Val!C12*(1-MIN(tp_g/tp_roe,0.8))/(1+(tp_r-0.01))^5+Val!C13*(1-MIN(tp_g/tp_roe,0.8))/(1+(tp_r-0.01))^6+Val!C13*(1-MIN(tp_g/tp_roe,0.8))*(1+tp_g)/((tp_r-0.01)-tp_g)/(1+(tp_r-0.01))^6)+tp_wC*MAX(0,Val!D8*(1-MIN(tp_g/tp_roe,0.8))/(1+(tp_r-0.01))^1+Val!D9*(1-MIN(tp_g/tp_roe,0.8))/(1+(tp_r-0.01))^2+Val!D10*(1-MIN(tp_g/tp_roe,0.8))/(1+(tp_r-0.01))^3+Val!D11*(1-MIN(tp_g/tp_roe,0.8))/(1+(tp_r-0.01))^4+Val!D12*(1-MIN(tp_g/tp_roe,0.8))/(1+(tp_r-0.01))^5+Val!D13*(1-MIN(tp_g/tp_roe,0.8))/(1+(tp_r-0.01))^6+Val!D13*(1-MIN(tp_g/tp_roe,0.8))*(1+tp_g)/((tp_r-0.01)-tp_g)/(1+(tp_r-0.01))^6))*(1+(tp_r-0.01)) -> 379.34442 | D30: =Val!B36 -> 529.16256 | E30: =tp_w_dcf*C30+(1-tp_w_dcf)*D30 -> 454.25349 | F30: =E30/E$28-1 -> 0.071472166
A31: 長期成長 +1pt | B31: g 5% | C31: =(tp_wA*MAX(0,Val!B8*(1-MIN((tp_g+0.01)/tp_roe,0.8))/(1+tp_r)^1+Val!B9*(1-MIN((tp_g+0.01)/tp_roe,0.8))/(1+tp_r)^2+Val!B10*(1-MIN((tp_g+0.01)/tp_roe,0.8))/(1+tp_r)^3+Val!B11*(1-MIN((tp_g+0.01)/tp_roe,0.8))/(1+tp_r)^4+Val!B12*(1-MIN((tp_g+0.01)/tp_roe,0.8))/(1+tp_r)^5+Val!B13*(1-MIN((tp_g+0.01)/tp_roe,0.8))/(1+tp_r)^6+Val!B13*(1-MIN((tp_g+0.01)/tp_roe,0.8))*(1+(tp_g+0.01))/(tp_r-(tp_g+0.01))/(1+tp_r)^6)+tp_wB*MAX(0,Val!C8*(1-MIN((tp_g+0.01)/tp_roe,0.8))/(1+tp_r)^1+Val!C9*(1-MIN((tp_g+0.01)/tp_roe,0.8))/(1+tp_r)^2+Val!C10*(1-MIN((tp_g+0.01)/tp_roe,0.8))/(1+tp_r)^3+Val!C11*(1-MIN((tp_g+0.01)/tp_roe,0.8))/(1+tp_r)^4+Val!C12*(1-MIN((tp_g+0.01)/tp_roe,0.8))/(1+tp_r)^5+Val!C13*(1-MIN((tp_g+0.01)/tp_roe,0.8))/(1+tp_r)^6+Val!C13*(1-MIN((tp_g+0.01)/tp_roe,0.8))*(1+(tp_g+0.01))/(tp_r-(tp_g+0.01))/(1+tp_r)^6)+tp_wC*MAX(0,Val!D8*(1-MIN((tp_g+0.01)/tp_roe,0.8))/(1+tp_r)^1+Val!D9*(1-MIN((tp_g+0.01)/tp_roe,0.8))/(1+tp_r)^2+Val!D10*(1-MIN((tp_g+0.01)/tp_roe,0.8))/(1+tp_r)^3+Val!D11*(1-MIN((tp_g+0.01)/tp_roe,0.8))/(1+tp_r)^4+Val!D12*(1-MIN((tp_g+0.01)/tp_roe,0.8))/(1+tp_r)^5+Val!D13*(1-MIN((tp_g+0.01)/tp_roe,0.8))/(1+tp_r)^6+Val!D13*(1-MIN((tp_g+0.01)/tp_roe,0.8))*(1+(tp_g+0.01))/(tp_r-(tp_g+0.01))/(1+tp_r)^6))*(1+tp_r) -> 336.32272 | D31: =Val!B36 -> 529.16256 | E31: =tp_w_dcf*C31+(1-tp_w_dcf)*D31 -> 432.74264 | F31: =E31/E$28-1 -> 0.020733369
A32: 長期成長 −1pt | B32: g 3% | C32: =(tp_wA*MAX(0,Val!B8*(1-MIN((tp_g-0.01)/tp_roe,0.8))/(1+tp_r)^1+Val!B9*(1-MIN((tp_g-0.01)/tp_roe,0.8))/(1+tp_r)^2+Val!B10*(1-MIN((tp_g-0.01)/tp_roe,0.8))/(1+tp_r)^3+Val!B11*(1-MIN((tp_g-0.01)/tp_roe,0.8))/(1+tp_r)^4+Val!B12*(1-MIN((tp_g-0.01)/tp_roe,0.8))/(1+tp_r)^5+Val!B13*(1-MIN((tp_g-0.01)/tp_roe,0.8))/(1+tp_r)^6+Val!B13*(1-MIN((tp_g-0.01)/tp_roe,0.8))*(1+(tp_g-0.01))/(tp_r-(tp_g-0.01))/(1+tp_r)^6)+tp_wB*MAX(0,Val!C8*(1-MIN((tp_g-0.01)/tp_roe,0.8))/(1+tp_r)^1+Val!C9*(1-MIN((tp_g-0.01)/tp_roe,0.8))/(1+tp_r)^2+Val!C10*(1-MIN((tp_g-0.01)/tp_roe,0.8))/(1+tp_r)^3+Val!C11*(1-MIN((tp_g-0.01)/tp_roe,0.8))/(1+tp_r)^4+Val!C12*(1-MIN((tp_g-0.01)/tp_roe,0.8))/(1+tp_r)^5+Val!C13*(1-MIN((tp_g-0.01)/tp_roe,0.8))/(1+tp_r)^6+Val!C13*(1-MIN((tp_g-0.01)/tp_roe,0.8))*(1+(tp_g-0.01))/(tp_r-(tp_g-0.01))/(1+tp_r)^6)+tp_wC*MAX(0,Val!D8*(1-MIN((tp_g-0.01)/tp_roe,0.8))/(1+tp_r)^1+Val!D9*(1-MIN((tp_g-0.01)/tp_roe,0.8))/(1+tp_r)^2+Val!D10*(1-MIN((tp_g-0.01)/tp_roe,0.8))/(1+tp_r)^3+Val!D11*(1-MIN((tp_g-0.01)/tp_roe,0.8))/(1+tp_r)^4+Val!D12*(1-MIN((tp_g-0.01)/tp_roe,0.8))/(1+tp_r)^5+Val!D13*(1-MIN((tp_g-0.01)/tp_roe,0.8))/(1+tp_r)^6+Val!D13*(1-MIN((tp_g-0.01)/tp_roe,0.8))*(1+(tp_g-0.01))/(tp_r-(tp_g-0.01))/(1+tp_r)^6))*(1+tp_r) -> 308.02893 | D32: =Val!B36 -> 529.16256 | E32: =tp_w_dcf*C32+(1-tp_w_dcf)*D32 -> 418.59575 | F32: =E32/E$28-1 -> -0.01263567
A33: DCF 權重 0.3 | C33: =(tp_wA*MAX(0,Val!B8*(1-MIN(tp_g/tp_roe,0.8))/(1+tp_r)^1+Val!B9*(1-MIN(tp_g/tp_roe,0.8))/(1+tp_r)^2+Val!B10*(1-MIN(tp_g/tp_roe,0.8))/(1+tp_r)^3+Val!B11*(1-MIN(tp_g/tp_roe,0.8))/(1+tp_r)^4+Val!B12*(1-MIN(tp_g/tp_roe,0.8))/(1+tp_r)^5+Val!B13*(1-MIN(tp_g/tp_roe,0.8))/(1+tp_r)^6+Val!B13*(1-MIN(tp_g/tp_roe,0.8))*(1+tp_g)/(tp_r-tp_g)/(1+tp_r)^6)+tp_wB*MAX(0,Val!C8*(1-MIN(tp_g/tp_roe,0.8))/(1+tp_r)^1+Val!C9*(1-MIN(tp_g/tp_roe,0.8))/(1+tp_r)^2+Val!C10*(1-MIN(tp_g/tp_roe,0.8))/(1+tp_r)^3+Val!C11*(1-MIN(tp_g/tp_roe,0.8))/(1+tp_r)^4+Val!C12*(1-MIN(tp_g/tp_roe,0.8))/(1+tp_r)^5+Val!C13*(1-MIN(tp_g/tp_roe,0.8))/(1+tp_r)^6+Val!C13*(1-MIN(tp_g/tp_roe,0.8))*(1+tp_g)/(tp_r-tp_g)/(1+tp_r)^6)+tp_wC*MAX(0,Val!D8*(1-MIN(tp_g/tp_roe,0.8))/(1+tp_r)^1+Val!D9*(1-MIN(tp_g/tp_roe,0.8))/(1+tp_r)^2+Val!D10*(1-MIN(tp_g/tp_roe,0.8))/(1+tp_r)^3+Val!D11*(1-MIN(tp_g/tp_roe,0.8))/(1+tp_r)^4+Val!D12*(1-MIN(tp_g/tp_roe,0.8))/(1+tp_r)^5+Val!D13*(1-MIN(tp_g/tp_roe,0.8))/(1+tp_r)^6+Val!D13*(1-MIN(tp_g/tp_roe,0.8))*(1+tp_g)/(tp_r-tp_g)/(1+tp_r)^6))*(1+tp_r) -> 318.74279 | D33: =Val!B36 -> 529.16256 | E33: =0.3*C33+(1-0.3)*D33 -> 466.03663 | F33: =E33/E$28-1 -> 0.09926569
A34: DCF 權重 0.7 | C34: =(tp_wA*MAX(0,Val!B8*(1-MIN(tp_g/tp_roe,0.8))/(1+tp_r)^1+Val!B9*(1-MIN(tp_g/tp_roe,0.8))/(1+tp_r)^2+Val!B10*(1-MIN(tp_g/tp_roe,0.8))/(1+tp_r)^3+Val!B11*(1-MIN(tp_g/tp_roe,0.8))/(1+tp_r)^4+Val!B12*(1-MIN(tp_g/tp_roe,0.8))/(1+tp_r)^5+Val!B13*(1-MIN(tp_g/tp_roe,0.8))/(1+tp_r)^6+Val!B13*(1-MIN(tp_g/tp_roe,0.8))*(1+tp_g)/(tp_r-tp_g)/(1+tp_r)^6)+tp_wB*MAX(0,Val!C8*(1-MIN(tp_g/tp_roe,0.8))/(1+tp_r)^1+Val!C9*(1-MIN(tp_g/tp_roe,0.8))/(1+tp_r)^2+Val!C10*(1-MIN(tp_g/tp_roe,0.8))/(1+tp_r)^3+Val!C11*(1-MIN(tp_g/tp_roe,0.8))/(1+tp_r)^4+Val!C12*(1-MIN(tp_g/tp_roe,0.8))/(1+tp_r)^5+Val!C13*(1-MIN(tp_g/tp_roe,0.8))/(1+tp_r)^6+Val!C13*(1-MIN(tp_g/tp_roe,0.8))*(1+tp_g)/(tp_r-tp_g)/(1+tp_r)^6)+tp_wC*MAX(0,Val!D8*(1-MIN(tp_g/tp_roe,0.8))/(1+tp_r)^1+Val!D9*(1-MIN(tp_g/tp_roe,0.8))/(1+tp_r)^2+Val!D10*(1-MIN(tp_g/tp_roe,0.8))/(1+tp_r)^3+Val!D11*(1-MIN(tp_g/tp_roe,0.8))/(1+tp_r)^4+Val!D12*(1-MIN(tp_g/tp_roe,0.8))/(1+tp_r)^5+Val!D13*(1-MIN(tp_g/tp_roe,0.8))/(1+tp_r)^6+Val!D13*(1-MIN(tp_g/tp_roe,0.8))*(1+tp_g)/(tp_r-tp_g)/(1+tp_r)^6))*(1+tp_r) -> 318.74279 | D34: =Val!B36 -> 529.16256 | E34: =0.7*C34+(1-0.7)*D34 -> 381.86872 | F34: =E34/E$28-1 -> -0.09926569
A50: 案例區塊：份額流失（低）（情境 B）
A51: 項目 | B51: 單位 | C51: FY2025A | D51: FY2026（錨點） | E51: FY2027 | F51: FY2028 | G51: FY2029 | H51: FY2030（收斂） | I51: FY2031（收斂） | J51: FY2032（收斂） | K51: 說明
A52: A. AI 部署與 AI 電源市場（D 欄＝FY2026 校準年；每 kW 內容取自台達電模型）
A53: AI IT 資本支出 × 情境顆數係數 | B53: US$B | D53: =itc_26*1 -> 781.87292 | E53: =itc_27*1*1 -> 1565.35 | F53: =itc_28*um28_B*1 -> 1587.4111 | G53: =itc_29*um29_B*1 -> 1921.3317
A54: 每 GW IT 資本支出 | B54: US$B | D54: =itpg_gb*(1-vr26)+itpg_vr*vr26 -> 33.414032 | E54: =itpg_vr -> 37.586352 | F54: =itpg_vr -> 37.586352 | G54: =itpg_vr -> 37.586352
A55: 部署 GW（IT 電力） | B55: GW | D55: =D53/D54 -> 23.399538 | E55: =E53/E54 -> 41.646766 | F55: =F53/F54 -> 42.233711 | G55: =G53/G54 -> 51.117803
A56: AI 電源內容（台達電模型） | B56: US$/kW | D56: =pkw_26 -> 450 | E56: =pkw_27 -> 600 | F56: =pkw_28 -> 680 | G56: =pkw_29 -> 720
A57: AI 電源市場（美元） | B57: US$B | D57: =D55*D56/1000 -> 10.529792 | E57: =E55*E56/1000 -> 24.988059 | F57: =F55*F56/1000 -> 28.718923 | G57: =G55*G56/1000 -> 36.804818
A58: AI 電源市場（新台幣） | B58: NT$B | D58: =D57*fx -> 336.95335 | E58: =E57*fx -> 799.6179 | F58: =F57*fx -> 919.00554 | G58: =G57*fx -> 1177.7542
A59: 光寶有效份額（FY2026 校準）＝ AI 電源營收 ÷ 市場 | B59: % | D59: =a26_aip/D58 -> 0.17614332 | K59: Derived：分子為公司 AI 相關占比 × 營收 ×（1 − 非電源占比）；分母為與台達電模型相同的 AI 電源市場（含 ASIC 機架）
A60: 份額相對值（÷ FY2026） | B60: x | D60: =1 -> 1 | E60: =RLO_27 -> 0.85 | F60: =RLO_28 -> 0.8 | G60: =RLO_29 -> 0.75
A61: 光寶有效份額 | B61: % | D61: =$D$59*D60 -> 0.17614332 | E61: =$D$59*E60 -> 0.14972182 | F61: =$D$59*F60 -> 0.14091465 | G61: =$D$59*G60 -> 0.13210749
A62: AI 電源營收 | B62: NT$B | C62: =a25_aip -> 31.390065 | D62: =D58*D61 -> 59.35208 | E62: =E58*E61 -> 119.72025 | F62: =F58*F61 -> 129.50135 | G62: =G58*G61 -> 155.59015
A63: AI 相關營收（＝AI 電源 ÷（1 − 非電源占比）） | B63: NT$B | C63: =a25_ai -> 34.87785 | D63: =D62/(1-x_np) -> 65.946756 | E63: =E62/(1-x_np) -> 133.0225 | F63: =F62/(1-x_np) -> 143.89039 | G63: =G62/(1-x_np) -> 172.87794 | K63: 非電源部分（液冷、AI 光電）隨 AI 電源同比例成長（Assumed）
A64: B. 非 AI 與合計
A65: 非 AI 營收 | B65: NT$B | C65: =a25_nai -> 131.20715 | D65: =a26_nai -> 146.78471 | E65: =D65*(1+g_nai27) -> 151.18826 | F65: =E65*(1+g_nai28) -> 155.7239 | G65: =F65*(1+g_nai29) -> 160.39562
A66: 營收 | B66: NT$B | C66: =C63+C65 -> 166.085 | D66: =D63+D65 -> 212.73147 | E66: =E63+E65 -> 284.21075 | F66: =F63+F65 -> 299.61429 | G66: =G63+G65 -> 333.27356 | H66: =G66*(1+H67) -> 362.67762 | I66: =H66*(1+I67) -> 385.93034 | J66: =I66*(1+J67) -> 401.36755 | K66: FY2030 起為收斂法：營收年增由 FY2029 線性收斂到 fade_g、淨利率收斂到 fade_m（FY2032 達到），非驅動因子推導
A67: 營收年增 | B67: % | D67: =D66/C66-1 -> 0.28085902 | E67: =E66/D66-1 -> 0.33600709 | F67: =F66/E66-1 -> 0.054197586 | G67: =G66/F66-1 -> 0.11234201 | H67: =$G67+(fade_gB-$G67)*1/3 -> 0.088228005 | I67: =$G67+(fade_gB-$G67)*2/3 -> 0.064114003 | J67: =$G67+(fade_gB-$G67)*3/3 -> 0.04
A68: AI 相關 ÷ 營收 | B68: % | C68: =C63/C66 -> 0.21 | D68: =D63/D66 -> 0.31 | E68: =E63/E66 -> 0.46804175 | F68: =F63/F66 -> 0.48025208 | G68: =G63/G66 -> 0.51872684
A69: 每 GW 光寶 AI 相關營收 | B69: US$M/GW | D69: =D63/fx/D55*1000 -> 88.071658 | E69: =E63/fx/E55*1000 -> 99.814546 | F69: =F63/fx/F55*1000 -> 106.46885 | G69: =G63/fx/G55*1000 -> 105.68599
A70: C. 損益
A71: 其他營收毛利率 ＝ 錨點毛利率 − 差距 × AI 占比（FY2026 校準） | B71: % | D71: =a26_gp/D66-d_ai*D68 -> 0.21698234 | K71: Derived：讓 FY2026 毛利率等於錨點；AI 相關毛利率＝其他＋差距
A72: AI 相關毛利率 ＝ 校準值 ＋ 額外改善 | B72: % | D72: =D71+d_ai -> 0.33698234 | E72: =$D$72+gmu_27 -> 0.33698234 | F72: =$D$72+gmu_28 -> 0.33698234 | G72: =$D$72+gmu_29 -> 0.33698234 | K72: 額外改善為 800V 電源櫃與組合（Assumed；情境 A 高、C 低）
A73: 毛利 | B73: NT$B | C73: =a25_gp -> 38.039 | D73: =a26_gp -> 54.072582 | E73: =E63*E72+E65*$D$71 -> 77.631413 | F73: =F63*F72+F65*$D$71 -> 82.277855 | G73: =G63*G72+G65*$D$71 -> 93.059829
A74: 毛利率 | B74: % | C74: =C73/C66 -> 0.22903333 | D74: =D73/D66 -> 0.25418234 | E74: =E73/E66 -> 0.27314735 | F74: =F73/F66 -> 0.27461259 | G74: =G73/G66 -> 0.27922956
A75: 營業費用（基準路徑） | B75: NT$B | C75: =a25_opx -> 21.301 | D75: =a26_opx -> 25.210333 | E75: =D75*(1+MAX(0,phi*E67)) -> 31.139929 | F75: =E75*(1+MAX(0,phi*F67)) -> 32.321325 | G75: =F75*(1+MAX(0,phi*G67)) -> 34.863055
A76: 營業費用 | B76: NT$B | C76: =C75 -> 21.301 | D76: =D75 -> 25.210333 | E76: =E75+0*E66 -> 31.139929 | F76: =F75+0*F66 -> 32.321325 | G76: =G75+0*G66 -> 34.863055
A77: 營業利益 | B77: NT$B | C77: =C73-C76 -> 16.738 | D77: =D73-D76 -> 28.862249 | E77: =E73-E76 -> 46.491484 | F77: =F73-F76 -> 49.95653 | G77: =G73-G76 -> 58.196773
A78: 營業利益率 | B78: % | C78: =C77/C66 -> 0.10077972 | D78: =D77/D66 -> 0.13567456 | E78: =E77/E66 -> 0.16358102 | F78: =F77/F66 -> 0.16673614 | G78: =G77/G66 -> 0.17462163
A79: 營業外淨額 | B79: NT$B | C79: =a25_nop -> 2.9762895 | D79: =a26_nop -> 3.839 | E79: =nop_f -> 3.5 | F79: =nop_f -> 3.5 | G79: =nop_f -> 3.5
A80: 歸屬母公司淨利 ÷ 稅前 | B80: % | C80: =a25_ni/a25_pt -> 0.76675348 | D80: =a26_ni/a26_pt -> 0.759431 | E80: =nir_f -> 0.76 | F80: =nir_f -> 0.76 | G80: =nir_f -> 0.76
A81: 歸屬母公司淨利 | B81: NT$B | C81: =a25_ni -> 15.116 | D81: =a26_ni -> 24.834342 | E81: =(E77+E79)*E80 -> 37.993528 | F81: =(F77+F79)*F80 -> 40.626962 | G81: =(G77+G79)*G80 -> 46.889548 | H81: =H66*H85 -> 46.965495 | I81: =I66*I85 -> 45.655248 | J81: =J66*J85 -> 42.98721
A82: 股數 | B82: 十億股 | C82: =a25_sh -> 2.276506 | D82: =a26_sh -> 2.2689583 | E82: =D82*(1+sh_g) -> 2.2689583 | F82: =E82*(1+sh_g) -> 2.2689583 | G82: =F82*(1+sh_g) -> 2.2689583 | H82: =G82*(1+sh_g) -> 2.2689583 | I82: =H82*(1+sh_g) -> 2.2689583 | J82: =I82*(1+sh_g) -> 2.2689583
A83: EPS | B83: NT$ | C83: =C81/C82 -> 6.64 | D83: =D81/D82 -> 10.945261 | E83: =E81/E82 -> 16.744921 | F83: =F81/F82 -> 17.905557 | G83: =G81/G82 -> 20.665672 | H83: =H81/H82 -> 20.699144 | I83: =I81/I82 -> 20.121678 | J83: =J81/J82 -> 18.945791
A84: EPS 年增 | B84: % | D84: =D83/C83-1 -> 0.64838274 | E84: =E83/D83-1 -> 0.52987857 | F84: =F83/E83-1 -> 0.069312721 | G84: =G83/F83-1 -> 0.1541485 | H84: =H83/G83-1 -> 0.0016197049 | I84: =I83/H83-1 -> -0.02789807 | J84: =J83/I83-1 -> -0.058438808
A85: 淨利率（歸屬母公司淨利 ÷ 營收） | B85: % | C85: =C81/C66 -> 0.091013638 | D85: =D81/D66 -> 0.11674033 | E85: =E81/E66 -> 0.13368082 | F85: =F81/F66 -> 0.13559755 | G85: =G81/G66 -> 0.14069387 | H85: =$G85+(fade_mB-$G85)*1/3 -> 0.12949653 | I85: =$G85+(fade_mB-$G85)*2/3 -> 0.1182992 | J85: =$G85+(fade_mB-$G85)*3/3 -> 0.10710186
A88: 案例區塊：份額提升（高）（情境 B）
A89: 項目 | B89: 單位 | C89: FY2025A | D89: FY2026（錨點） | E89: FY2027 | F89: FY2028 | G89: FY2029 | H89: FY2030（收斂） | I89: FY2031（收斂） | J89: FY2032（收斂） | K89: 說明
A90: A. AI 部署與 AI 電源市場（D 欄＝FY2026 校準年；每 kW 內容取自台達電模型）
A91: AI IT 資本支出 × 情境顆數係數 | B91: US$B | D91: =itc_26*1 -> 781.87292 | E91: =itc_27*1*1 -> 1565.35 | F91: =itc_28*um28_B*1 -> 1587.4111 | G91: =itc_29*um29_B*1 -> 1921.3317
A92: 每 GW IT 資本支出 | B92: US$B | D92: =itpg_gb*(1-vr26)+itpg_vr*vr26 -> 33.414032 | E92: =itpg_vr -> 37.586352 | F92: =itpg_vr -> 37.586352 | G92: =itpg_vr -> 37.586352
A93: 部署 GW（IT 電力） | B93: GW | D93: =D91/D92 -> 23.399538 | E93: =E91/E92 -> 41.646766 | F93: =F91/F92 -> 42.233711 | G93: =G91/G92 -> 51.117803
A94: AI 電源內容（台達電模型） | B94: US$/kW | D94: =pkw_26 -> 450 | E94: =pkw_27 -> 600 | F94: =pkw_28 -> 680 | G94: =pkw_29 -> 720
A95: AI 電源市場（美元） | B95: US$B | D95: =D93*D94/1000 -> 10.529792 | E95: =E93*E94/1000 -> 24.988059 | F95: =F93*F94/1000 -> 28.718923 | G95: =G93*G94/1000 -> 36.804818
A96: AI 電源市場（新台幣） | B96: NT$B | D96: =D95*fx -> 336.95335 | E96: =E95*fx -> 799.6179 | F96: =F95*fx -> 919.00554 | G96: =G95*fx -> 1177.7542
A97: 光寶有效份額（FY2026 校準）＝ AI 電源營收 ÷ 市場 | B97: % | D97: =a26_aip/D96 -> 0.17614332 | K97: Derived：分子為公司 AI 相關占比 × 營收 ×（1 − 非電源占比）；分母為與台達電模型相同的 AI 電源市場（含 ASIC 機架）
A98: 份額相對值（÷ FY2026） | B98: x | D98: =1 -> 1 | E98: =RHI_27 -> 1.1 | F98: =RHI_28 -> 1.2 | G98: =RHI_29 -> 1.25
A99: 光寶有效份額 | B99: % | D99: =$D$97*D98 -> 0.17614332 | E99: =$D$97*E98 -> 0.19375765 | F99: =$D$97*F98 -> 0.21137198 | G99: =$D$97*G98 -> 0.22017915
A100: AI 電源營收 | B100: NT$B | C100: =a25_aip -> 31.390065 | D100: =D96*D99 -> 59.35208 | E100: =E96*E99 -> 154.93208 | F100: =F96*F99 -> 194.25202 | G100: =G96*G99 -> 259.31691
A101: AI 相關營收（＝AI 電源 ÷（1 − 非電源占比）） | B101: NT$B | C101: =a25_ai -> 34.87785 | D101: =D100/(1-x_np) -> 65.946756 | E101: =E100/(1-x_np) -> 172.14676 | F101: =F100/(1-x_np) -> 215.83558 | G101: =G100/(1-x_np) -> 288.1299 | K101: 非電源部分（液冷、AI 光電）隨 AI 電源同比例成長（Assumed）
A102: B. 非 AI 與合計
A103: 非 AI 營收 | B103: NT$B | C103: =a25_nai -> 131.20715 | D103: =a26_nai -> 146.78471 | E103: =D103*(1+g_nai27) -> 151.18826 | F103: =E103*(1+g_nai28) -> 155.7239 | G103: =F103*(1+g_nai29) -> 160.39562
A104: 營收 | B104: NT$B | C104: =C101+C103 -> 166.085 | D104: =D101+D103 -> 212.73147 | E104: =E101+E103 -> 323.33502 | F104: =F101+F103 -> 371.55948 | G104: =G101+G103 -> 448.52552 | H104: =G104*(1+H105) -> 516.44521 | I104: =H104*(1+I105) -> 565.87647 | J104: =I104*(1+J105) -> 588.51153 | K104: FY2030 起為收斂法：營收年增由 FY2029 線性收斂到 fade_g、淨利率收斂到 fade_m（FY2032 達到），非驅動因子推導
A105: 營收年增 | B105: % | D105: =D104/C104-1 -> 0.28085902 | E105: =E104/D104-1 -> 0.51992094 | F105: =F104/E104-1 -> 0.14914706 | G105: =G104/F104-1 -> 0.20714325 | H105: =$G105+(fade_gB-$G105)*1/3 -> 0.15142883 | I105: =$G105+(fade_gB-$G105)*2/3 -> 0.095714416 | J105: =$G105+(fade_gB-$G105)*3/3 -> 0.04
A106: AI 相關 ÷ 營收 | B106: % | C106: =C101/C104 -> 0.21 | D106: =D101/D104 -> 0.31 | E106: =E101/E104 -> 0.53240989 | F106: =F101/F104 -> 0.58089105 | G106: =G101/G104 -> 0.64239355
A107: 每 GW 光寶 AI 相關營收 | B107: US$M/GW | D107: =D101/fx/D93*1000 -> 88.071658 | E107: =E101/fx/E93*1000 -> 129.17177 | F107: =F101/fx/F93*1000 -> 159.70327 | G107: =G101/fx/G93*1000 -> 176.14332
A108: C. 損益
A109: 其他營收毛利率 ＝ 錨點毛利率 − 差距 × AI 占比（FY2026 校準） | B109: % | D109: =a26_gp/D104-d_ai*D106 -> 0.21698234 | K109: Derived：讓 FY2026 毛利率等於錨點；AI 相關毛利率＝其他＋差距
A110: AI 相關毛利率 ＝ 校準值 ＋ 額外改善 | B110: % | D110: =D109+d_ai -> 0.33698234 | E110: =$D$110+gmu_27 -> 0.33698234 | F110: =$D$110+gmu_28 -> 0.33698234 | G110: =$D$110+gmu_29 -> 0.33698234 | K110: 額外改善為 800V 電源櫃與組合（Assumed；情境 A 高、C 低）
A111: 毛利 | B111: NT$B | C111: =a25_gp -> 38.039 | D111: =a26_gp -> 54.072582 | E111: =E101*E110+E103*$D$109 -> 90.815599 | F111: =F101*F110+F103*$D$109 -> 106.52211 | G111: =G101*G110+G103*$D$109 -> 131.8977
A112: 毛利率 | B112: % | C112: =C111/C104 -> 0.22903333 | D112: =D111/D104 -> 0.25418234 | E112: =E111/E104 -> 0.28087152 | F112: =F111/F104 -> 0.28668926 | G112: =G111/G104 -> 0.29406956
A113: 營業費用（基準路徑） | B113: NT$B | C113: =a25_opx -> 21.301 | D113: =a26_opx -> 25.210333 | E113: =D113*(1+MAX(0,phi*E105)) -> 34.3855 | F113: =E113*(1+MAX(0,phi*F105)) -> 37.975447 | G113: =F113*(1+MAX(0,phi*G105)) -> 43.481897
A114: 營業費用 | B114: NT$B | C114: =C113 -> 21.301 | D114: =D113 -> 25.210333 | E114: =E113+0*E104 -> 34.3855 | F114: =F113+0*F104 -> 37.975447 | G114: =G113+0*G104 -> 43.481897
A115: 營業利益 | B115: NT$B | C115: =C111-C114 -> 16.738 | D115: =D111-D114 -> 28.862249 | E115: =E111-E114 -> 56.430099 | F115: =F111-F114 -> 68.546667 | G115: =G111-G114 -> 88.415806
A116: 營業利益率 | B116: % | C116: =C115/C104 -> 0.10077972 | D116: =D115/D104 -> 0.13567456 | E116: =E115/E104 -> 0.17452517 | F116: =F115/F104 -> 0.1844837 | G116: =G115/G104 -> 0.19712548
A117: 營業外淨額 | B117: NT$B | C117: =a25_nop -> 2.9762895 | D117: =a26_nop -> 3.839 | E117: =nop_f -> 3.5 | F117: =nop_f -> 3.5 | G117: =nop_f -> 3.5
A118: 歸屬母公司淨利 ÷ 稅前 | B118: % | C118: =a25_ni/a25_pt -> 0.76675348 | D118: =a26_ni/a26_pt -> 0.759431 | E118: =nir_f -> 0.76 | F118: =nir_f -> 0.76 | G118: =nir_f -> 0.76
A119: 歸屬母公司淨利 | B119: NT$B | C119: =a25_ni -> 15.116 | D119: =a26_ni -> 24.834342 | E119: =(E115+E117)*E118 -> 45.546875 | F119: =(F115+F117)*F118 -> 54.755467 | G119: =(G115+G117)*G118 -> 69.856013 | H119: =H104*H123 -> 72.060232 | I119: =I104*I123 -> 69.781928 | J119: =J104*J123 -> 63.030678
A120: 股數 | B120: 十億股 | C120: =a25_sh -> 2.276506 | D120: =a26_sh -> 2.2689583 | E120: =D120*(1+sh_g) -> 2.2689583 | F120: =E120*(1+sh_g) -> 2.2689583 | G120: =F120*(1+sh_g) -> 2.2689583 | H120: =G120*(1+sh_g) -> 2.2689583 | I120: =H120*(1+sh_g) -> 2.2689583 | J120: =I120*(1+sh_g) -> 2.2689583
...

Sheet Sources
A1: 來源（公司原文＝光寶科財報、月營收公告與法說會，經資料商與媒體轉述；券商與媒體估計皆為 Interested-party）
A2: 二手：優分析 2026-07-31（2Q26、1H26 損益、雲端與物聯網營收與營業利益） | B2: https://uanalyze.com.tw/articles/3402052563
A3: 二手：富果 2026-07-31 法說摘要（AI 占比超過 30%、BBU 占雲端 20–25%、800V 時程、資本支出 180 億、產能） | B3: https://blog.fugle.tw/post/earnings-call-2301-2026-07-31
A4: 二手：優分析 2026-02-25（FY2025、4Q25 損益、AI 占比超過 20%） | B4: https://uanalyze.com.tw/articles/1580848095
A5: 二手：富果 2026-02-25 法說摘要（FY2025 部門占比、2026 指引、資本支出） | B5: https://blog.fugle.tw/post/earnings-call-2301-2026-02-25
A6: 二手：technews 2026-10-08（9 月營收 188.48 億、前 9 月 1,535.59 億） | B6: https://finance.technews.tw/2026/10/08/ltc-2301-202609-financial-report/
A7: 資料商：nstock（10-22 收盤、9 月營收） | B7: https://www.nstock.tw/2301?status=2
A8: 資料商：stockanalysis（現價、近 12 月與前瞻 P/E、股數、共識目標價；同業前瞻 P/E） | B8: https://stockanalysis.com/quote/tpe/2301/
A9: 資料商：stockanalysis 季度與年度損益（營收、毛利、營業利益、淨利、稅前淨利率） | B9: https://stockanalysis.com/quote/tpe/2301/financials/?p=quarterly
A10: 資料商：stockanalysis forecast（2026-09-23 目標價區間、FY2026 營收與 EPS） | B10: https://stockanalysis.com/quote/tpe/2301/forecast/
A11: 資料商：MarketScreener（FY2026–28 共識營收、淨利、EPS） | B11: https://www.marketscreener.com/quote/stock/LITE-ON-TECHNOLOGY-CORPOR-6492334/valuation/
A12: 資料商：wearn（2012–2025 年度 EPS、淨利率、ROE） | B12: https://stock.wearn.com/financial.asp?kind=2301
A13: 資料商：digrin（2014–2025 年 12 月價格，未調整） | B13: https://www.digrin.com/stocks/detail/2301.TW/price
... A15: 券商：凱基 Power supply sector 2025-09-26（台達電市占 60–65%、光寶第二梯隊、每架電源內容） | B15: https://www.kgi.com.hk/zh-hk/-/media/files/kgishk/research-reports/tw-reports/power-supply-sector_20250926e.pdf
A16: 市場層：markets/network、markets/chip_bridge、tsmc 成品；delta 成品（AI 電源每 kW 內容、台達電份額，本專案權威）（本 repo，唯讀）
A17: 無法取得：companiesmarketcap 光寶 P/E 頁（網站錯誤）；10-23 收盤；7、8 月個別營收 | B17: 未找到
A18: 待補（人工）：3Q26 財報與法說（10-30 前後）；10 月營收（11-10 前後）；部門別毛利率；AI 電源與 BBU 的季度金額；光寶 AI 電源市占的量化來源；資本支出與折舊路徑；前瞻 P/E 十年歷史（Bloomberg）；FY2027 起共識第二來源 | B18: 未找到
A19: SemiAnalysis | B19: 未使用
