Workbook

Sheet README
A1: 光寶科（2301.TW）個股模型 v0.2（AI 半導體 Project：電源與散熱次產業；AI 伺服器電源 PSU、電源櫃、BBU） 2026-10-28
A2: 版本：v0.2（2026-10-28：依個股模型原則重建營收層——營收列改為官方三大事業群〔雲端及物聯網、光電、資訊及消費性電子〕，AI 相關為雲端及物聯網的子列，分部合計＝合併營收；非 AI 單一成長率改為三條分部成長率；每 kW 內容改讀 Siliconomics）；v0.1.1（2026-10-25：補上檔空間級距、投資建議、重點觀察，數值不變）；v0.1（初版）。AI 電源每 kW 內容沿用台達電模型（delta/dist In 頁，本專案權威，口徑一致），本模型只建光寶份額；Units 與 Recon 頁核對光寶＋台達電份額合計。
A3: 模型命題：光寶科的 AI 營收＝部署 GW（AI IT 資本支出 ÷ 每 GW IT 資本支出）× AI 電源每 kW 內容（台達電模型）× 光寶份額 ÷（1 − 非電源占比）；非 AI（一般雲端電源、光電、資訊與消費電子、車用）約占七成，另設低成長。AI 相關營收 2025 年約兩成、2026 年約三成，毛利率高於其他業務，使 AI 部署成為 EPS 的主要驅動。
A4: 核心問題：光寶在台達電主導的 AI 電源市場（800V HVDC 電源櫃、BBU、新 CSP 客戶）能不能把有效份額由約一成八往上拉；消費電子衰退與零組件成本會吃掉多少；現價約 20 倍前瞻 P/E 隱含什麼路徑。
A6: 會計年度＝日曆年，FY(t)＝CY(t)，不平移。預測期 FY2027–FY2029 由驅動因子推導，FY2030–FY2032 為收斂法。金額：十億新台幣；市場以美元計、以匯率 32.0 換算（與台達電模型相同）。口徑：歸屬母公司淨利（IFRS）。
A8: 驅動因子 → 推導量（全部唯讀上游，不修改）
A9: AI 營收：markets/network 的 AI IT 資本支出 × 同字母顆數係數（tsmc；＝markets/memory SCEN_UNITS）÷ 每 GW IT 資本支出（Tokenomics，經橋接表）＝部署 GW；× 每 kW 電源內容（台達電模型 450 → 600 → 680 → 720 美元）× 匯率 × 光寶有效份額（FY2026 以公司 AI 相關占比校準）× 份額相對值（Assumed）÷（1 − 非電源占比）。
A10: 營收分部：雲端及物聯網＝AI 相關（命題模組）＋非 AI（FY2026 錨點 × 年增 5%，Assumed）；光電＝FY2026 錨點 × 年增 5%（Assumed）；資訊及消費性電子＝FY2026 錨點 × 年增 0%（Assumed，公司 2026 資訊產品 −6～−8%、低軌衛星電源倍增）。FY2026 各事業群＝1H26 實績（2Q26 簡報＋季增）＋3Q、4Q 依 2Q26 比例（Assumed）。毛利率：AI 相關比其他營收高 d_ai 12pt（Assumed，依 2Q26 雲端部門營益率約 24% vs 其他約 5–6%），其他毛利率為 FY2026 殘差（Derived）；另加 AI 毛利率額外改善（情境 A 高、C 低）。營業費用：彈性 phi 0.7（Assumed）。淨利 ÷ 稅前 0.76（1H26 實績）。
A11: 校準：FY2026 ＝ 1H26 財報＋3Q26 月營收實績（1–9 月累計 − 1H26）＋假設（3Q、4Q 毛利率 26%、營業費用率 11.8%、4Q 季增 3%）。3Q26 財報與法說預計 2026-10-30 前後，截至 2026-10-25 尚未公布。不用券商數字（只在 Recon 對帳）。
A12: 估值：Val 第 0 節目標價＝0.5 × DCF 目標價（股東現金流＝EPS ×（1 − g／ROE），FY2027–32 明確期＋永續，r 10%、g 4%，三情境權重 0.3／0.5／0.2，負值取 0）＋0.5 × Comparable 目標價（台達電、Vertiv、Eaton、Flex 前瞻 P/E 中位數 × 12 個月後前瞻 EPS；不放 A 股）；另列 Comparable 單獨目標價、市場共識目標價與差距拆解。十年 P/E 規則值 × FY2027 EPS 保留為參考（不是目標價）。本版未做先驗，無 Andy 合理 P/E 對照。
A13: 預估期間：FY2027–FY2029 由驅動因子推導；FY2030 起為收斂法，非驅動因子推導（營收年增由 FY2029 線性收斂到 fade_g、淨利率收斂到 fade_m，FY2032 達到；PL 頁灰底）。十年平均淨利率 6.5%（wearn 2016–2025，單一來源）。
A14: 情境與行業一致：A＝順利（tsmc 顆數係數 A、份額相對值與 AI 毛利率額外改善取高值）；B＝平平（係數 B、取基準）；C＝不如預期（係數 C、取低值）；每 kW 電源內容（台達電模型）與非 AI 成長各情境相同。
... A19: v0.1.1（2026-10-25）：補上檔空間級距、投資建議、重點觀察（Val 頁 0.3 結論加「上檔空間級距」「投資建議」兩列、README 頁加重點觀察三點；數值不變，既有儲存格位置不變）。
A20: ="投資建議："&Val!B119&"（依上檔空間固定規則）" -> 投資建議：中立（依上檔空間固定規則）
A21: ="重點觀察 1：目標價 NT$"&TEXT(Val!$B$40,"0.00")&"（DCF "&TEXT(Val!$B$24,"0.00")&"、Comparable（相對倍數調整後）"&TEXT(tp_comp_adj,"0.00")&"；DCF 權重 "&TEXT(tp_w_dcf,"0%")&"），比現價 "&TEXT(px,"0.00")&"（2026-10-22）"&IF(Val!$B$43>=0,"高 "&TEXT(Val!$B$43,"0.0%"),"低 "&TEXT(-Val!$B$43,"0.0%"))&"，級距 "&Val!$B$118&"、投資建議 "&Val!$B$119&"。相對倍數調整係數 "&TEXT(rm_factor,"0.00")&"（本公司 10 年前瞻倍數中位數 ÷ 同業的中位數，夾在 0.5–2.0；Val 第 0.5 節），調整前加權上檔空間 "&TEXT((tp_w_dcf*Val!$B$24+(1-tp_w_dcf)*Val!$B$36)/px-1,"+0.0%;−0.0%")&"；Comparable 單獨（市場主流同業法、未調整）為 "&TEXT(Val!$B$44,"+0.0%;−0.0%")&"。"&"以下為 2026-10-29 相對倍數調整前撰寫的說明，其中數字為調整前：主因是 EPS 不是倍數：本模型 12 個月後前瞻 EPS 21.73 比共識前瞻 EPS 12.97 高 67.6%（共識為現在起 12 個月，早約一年；本模型情境 B 的 FY2027 EPS 18.74 仍高 44.5%），同業（台達電、Vertiv、Eaton、Flex）前瞻 P/E 中位數 24.4 倍與共識目標價"&" 314.25 隱含的 24.2 倍相當；差距來自 AI 電源份額與 800V 電源櫃放量假設（Assumed）。DCF 單獨也有 +24.8%。" -> 重點觀察 1：目標價 NT$319.14（DCF 318.42、Comparable（相對倍數調整後）319.85；DCF 權重 50%），比現價 255.50（2026-10-22）高 24.9%，級距 0%–25%、投資建議 中立。相對倍數調整係數 0.60（本公司 10 年前瞻倍數中位數 ÷ 同業的中位數，夾在 0.5–2.0；Val 第 0.5 節），調整前加權上檔空間 +65.8%；Comparable 單獨（市場主流同業法、未調整）為 +106.9%。以下為 2026-10-29 相對倍數調整前撰寫的說明，其中數字為調整前：主因是 EPS 不是倍數：本模型 12 個月後前瞻 EPS 21.73 比共識前瞻 EPS 12.97 高 67.6%（共識為現在起 12 個月，早約一年；本模型情境 B 的 FY2027 EPS 18.74 仍高 44.5%），同業（台達電、Vertiv、Eaton、Flex）前瞻 P/E 中位數 24.4 倍與共識目標價 314.25 隱含的 24.2 倍相當；差距來自 AI 電源份額與 800V 電源櫃放量假設（Assumed）。DCF 單獨也有 +24.8%。
A22: 重點觀察 2：情境分歧大：情境 A／C（顆數、份額、AI 毛利率全部）FY2028 EPS 比 B 高 43.9%／低 34.8%，DCF 價格帶 121～531；單一變數中份額流失 −14.8%、AI 部署 ×0.8 −14.7%。
A23: 重點觀察 3：追蹤 3Q26 財報與法說（2026-10-30 前後）與 10 月營收（11-10 前後）：本版 3Q、4Q 毛利率 26% 為假設；AI 相關營收只有年度占比（2026 年超過 30%），季度金額未揭露。
A25: 2026-10-29：加權目標價中的 Comparable 改用相對倍數調整後的值（Val 第 0.5 節：同業前瞻倍數中位數 × 本公司 10 年相對同業的倍數比，Bloomberg 前瞻倍數；Andy 2026-10-27「照建議做」、10-29 資料取回）。「Comparable 目標價（市場主流同業法）」維持不調整。重點觀察 1 的第一句已改為公式；重點觀察 2、3 與其他說明中的目標價與上檔空間數字為調整前撰寫，以 Val 頁為準。

Sheet In
A1: In — 輸入（藍字；基準欄 E，低 D、高 F）。金額：十億新台幣（NT$B），AI 電源市場與每 kW 內容為美元；比例：%。每個輸入附兩個來源（找不到者寫「未找到」）；公司原文算一個
A2: 標記：Verified／Interested-party／Analogy／Assumed／Derived；Analogy、Assumed 給低／高區間。SemiAnalysis 未使用。公司原文＝光寶科財報與法說會（經媒體、資料商轉述）、月營收公告；公司的 AI 占比、產品時程說法為 Interested-party；券商與媒體估計皆為 Interested-party
A3: 鍵 | B3: 項目 | C3: 單位 | D3: 低 | E3: 基準 | F3: 高 | G3: 標記 | H3: 來源1 | I3: 來源2／說明
A4: A. AI 部署規模（讀 markets/network、markets/chip_bridge、tsmc 成品；情境 A 基準，B／C 依同字母顆數係數縮放）
A5: itc_26 | B5: AI IT 資本支出 2026 | C5: US$B | E5: 781.87292 | G5: Derived | H5: markets/network/dist/20261026_AI網通市場模型_v0.2.3.xlsx｜Mkt!C27:F27 | I5: 加速器顆數 × 每顆 IT capex（含 ASIC）；本模型以此除以每 GW IT 資本支出得到部署 GW（與台達電模型相同）
A6: itc_27 | B6: AI IT 資本支出 2027 | C6: US$B | E6: 1565.35 | G6: Derived | H6: markets/network/dist/20261026_AI網通市場模型_v0.2.3.xlsx｜Mkt!C27:F27 | I6: 同上
A7: itc_28 | B7: AI IT 資本支出 2028 | C7: US$B | E7: 1984.2639 | G7: Derived | H7: markets/network/dist/20261026_AI網通市場模型_v0.2.3.xlsx｜Mkt!C27:F27 | I7: 同上
A8: itc_29 | B8: AI IT 資本支出 2029 | C8: US$B | E8: 2260.3903 | G8: Derived | H8: markets/network/dist/20261026_AI網通市場模型_v0.2.3.xlsx｜Mkt!C27:F27 | I8: 同上
A9: itpg_gb | B9: 每 GW IT 資本支出（GB300） | C9: US$B | E9: 32.237224 | G9: Derived | H9: markets/chip_bridge/dist/20261027_晶片內容橋接表_v0.2.2.xlsx｜In!E10（GB300）、H10（VR200） | I9: Tokenomics IF_CapexIT（經橋接表；唯讀）
A10: itpg_vr | B10: 每 GW IT 資本支出（VR200；2027 起） | C10: US$B | E10: 37.586352 | G10: Derived | H10: markets/chip_bridge/dist/20261027_晶片內容橋接表_v0.2.2.xlsx｜In!E10（GB300）、H10（VR200） | I10: 同上；Rubin Ultra 與 ASIC 機架未另訂（Assumed：同 VR200）
A11: vr26 | B11: 2026 年部署中 Rubin 世代占比（混合每 GW IT 資本支出用） | C11: % | D11: 0.15 | E11: 0.22 | F11: 0.3 | G11: Interested-party | H11: TrendForce 2026 組合 Rubin 22%（經 markets/memory；與台達電模型相同） | I11: —
A12: racks_vr | B12: 每 GW 機架數（VR200） | C12: 架 | E12: 4052 | G12: Derived | H12: markets/chip_bridge/dist/20261027_晶片內容橋接表_v0.2.2.xlsx｜In!E6（GB300）、H6（VR200） | I12: Units 頁每架內容換算用
A13: um28_A | B13: 情境 A：2028 顆數 ÷ 基準 | C13: x | E13: 1 | G13: Assumed | H13: tsmc/dist/20261028_台積電個股模型_v0.4.xlsx｜In!E37 | I13: A＝順利（基準）；B＝平平；C＝不如預期；與台積電、台達電模型相同（＝markets/memory SCEN_UNITS，建置時核對）
A14: um29_A | B14: 情境 A：2029 顆數 ÷ 基準 | C14: x | E14: 1 | G14: Assumed | H14: tsmc/dist/20261028_台積電個股模型_v0.4.xlsx｜In!E38 | I14: 同上
A15: um28_B | B15: 情境 B：2028 顆數 ÷ 基準 | C15: x | E15: 0.8 | G15: Assumed | H15: tsmc/dist/20261028_台積電個股模型_v0.4.xlsx｜In!E39 | I15: A＝順利（基準）；B＝平平；C＝不如預期；與台積電、台達電模型相同（＝markets/memory SCEN_UNITS，建置時核對）
A16: um29_B | B16: 情境 B：2029 顆數 ÷ 基準 | C16: x | E16: 0.85 | G16: Assumed | H16: tsmc/dist/20261028_台積電個股模型_v0.4.xlsx｜In!E40 | I16: 同上
A17: um28_C | B17: 情境 C：2028 顆數 ÷ 基準 | C17: x | E17: 0.6 | G17: Assumed | H17: tsmc/dist/20261028_台積電個股模型_v0.4.xlsx｜In!E41 | I17: A＝順利（基準）；B＝平平；C＝不如預期；與台積電、台達電模型相同（＝markets/memory SCEN_UNITS，建置時核對）
A18: um29_C | B18: 情境 C：2029 顆數 ÷ 基準 | C18: x | E18: 0.6 | G18: Assumed | H18: tsmc/dist/20261028_台積電個股模型_v0.4.xlsx｜In!E42 | I18: 同上
A19: fx | B19: 匯率（新台幣 ÷ 美元） | C19: NT$/US$ | D19: 30.5 | E19: 32 | F19: 33 | G19: Derived | H19: delta/dist/20261028_台達電個股模型_v0.3.xlsx｜In!D20:F20 | I19: 與台達電模型相同（唯讀）；10-23 收盤：未找到
A20: B. AI 電源內容（口徑與台達電一致：唯讀 delta/dist In 頁）與光寶份額
A21: pkw_26 | B21: AI 電源內容 2026（台達電模型） | C21: US$/kW | D21: 380 | E21: 450 | F21: 520 | G21: Derived | H21: siliconomics｜SIF_pwr_pkw_26 | I21: Siliconomics 快照 In 頁 M17（本專案 AI 電源每 kW 內容唯一值；含機架電源櫃、PSU、BBU、HVDC 電源櫃；口徑與台達電模型相同）
A22: pkw_27 | B22: AI 電源內容 2027（VR200）（台達電模型） | C22: US$/kW | D22: 500 | E22: 600 | F22: 700 | G22: Derived | H22: siliconomics｜SIF_pwr_pkw_27 | I22: 同上；低／高亦取自本庫（Sens 用）
A23: pkw_28 | B23: AI 電源內容 2028（800V HVDC 放量）（台達電模型） | C23: US$/kW | D23: 550 | E23: 680 | F23: 800 | G23: Assumed | H23: siliconomics｜SIF_pwr_pkw_28 | I23: 同上；低／高亦取自本庫（Sens 用）
A24: pkw_29 | B24: AI 電源內容 2029（台達電模型） | C24: US$/kW | D24: 550 | E24: 720 | F24: 850 | G24: Assumed | H24: siliconomics｜SIF_pwr_pkw_29 | I24: 同上；低／高亦取自本庫（Sens 用）
A25: x_np | B25: AI 相關營收中非電源部分（液冷 CDU、Sidecar、AI 光電等）占比 | C25: % | D25: 0 | E25: 0.1 | F25: 0.25 | G25: Assumed | H25: 公司：液冷 120kW CDU、Sidecar 2Q26 起出貨（富果 2026-07-31 法說摘要）；凱基 2025-09：光寶 2026 年液冷營收目標約 5%（Interested-party） | I25: 只影響份額（分子）與光寶＋台達電份額合計，不影響營收（非電源部分隨 AI 電源同比例成長，Assumed）
A26: rel_27 | B26: 光寶 AI 電源份額 2027 ÷ 2026（相對值；情境 A 取高、B 基準、C 取低） | C26: x | D26: 0.85 | E26: 1 | F26: 1.1 | G26: Assumed | H26: 凱基 2025-09：台達電 AI 伺服器電源市占約 60–65%、長期略降；光寶為第二梯隊，新增美系雲端客戶，PSU 與 BBU 4Q25 出貨（Interested-party） | I26: 公司：800V HVDC Power Rack 2026-11 小量、1Q27 放量；110kW Power Shelf、BBU 驗證量產；新 CSP 客戶長期目標每家每年 10 億美元（富果 2026-07-31）
A27: rel_28 | B27: 光寶 AI 電源份額 2028 ÷ 2026（相對值；情境 A 取高、B 基準、C 取低） | C27: x | D27: 0.8 | E27: 1 | F27: 1.2 | G27: Assumed | H27: 同上 | I27: —
A28: rel_29 | B28: 光寶 AI 電源份額 2029 ÷ 2026（相對值；情境 A 取高、B 基準、C 取低） | C28: x | D28: 0.75 | E28: 1 | F28: 1.25 | G28: Assumed | H28: 同上 | I28: —
A29: C. 營收結構錨點（公司揭露比例 × 營收）
A30: ai_25 | B30: 2025 年 AI 相關營收 ÷ 營收 | C30: % | D30: 0.2 | E30: 0.21 | F30: 0.23 | G30: Interested-party | H30: https://uanalyze.com.tw/articles/1580848095：AI 相關營收超過 20%（公司，達標） | I30: https://blog.fugle.tw/post/earnings-call-2301-2026-02-25：2025 年 AI 占比超過 20%；雲端與物聯網 45%、光電 17%、資訊與消費電子 38%
A31: ai_26 | B31: 2026 年 AI 相關營收 ÷ 營收 | C31: % | D31: 0.3 | E31: 0.31 | F31: 0.35 | G31: Interested-party | H31: https://blog.fugle.tw/post/earnings-call-2301-2026-07-31：AI 相關產品 2026 年超過 30%（公司）；BBU 約占雲端營收 20–25% | I31: https://blog.fugle.tw/post/earnings-call-2301-2026-02-25：2026 年目標 30% 以上、長期 50% 以上
A32: C2. 營收分部（官方三大事業群：雲端及物聯網、光電、資訊及消費性電子；v0.2 依個股模型原則重建）
A33: s25_cl | B33: 2025 年雲端及物聯網 ÷ 營收 | C33: % | E33: 0.45 | G33: Interested-party | H33: https://blog.fugle.tw/post/earnings-call-2301-2026-02-25：2025 年雲端與物聯網 45%、光電 17%、資訊與消費電子 38%（公司法說） | I33: 月營收新聞稿 2025-12：雲端及物聯網 46%、光電 14%、資訊及消費性電子 40%（單月，旺得富 2026-01-08）
A34: s25_op | B34: 2025 年光電 ÷ 營收 | C34: % | E34: 0.17 | G34: Interested-party | H34: 同上 | I34: —
A35: s25_ic | B35: 2025 年資訊及消費性電子 ÷ 營收 | C35: % | E35: =1-s25_cl-s25_op -> 0.38 | G35: Derived | H35: 1 − 雲端及物聯網 − 光電（公司 38%） | I35: 公司比例為四捨五入值，合計 100%
A36: q2_cl | B36: 2Q26 雲端及物聯網營收 | C36: NT$B | E36: 28.9 | G36: Verified | H36: Investing.com 2026-07-31（Lite-On Q2 2026 slides 摘要）：2Q26 Cloud and AIoT 289 億（55%，季增 26%）、Opto-electronics 80 億（季增 12%）、IT and Consumer Electronics 158 億（季增 18%） | I36: 公司：2Q26 營收 527 億，雲端及物聯網占 55%（富果 2026-07-31）
A37: q2_op | B37: 2Q26 光電營收 | C37: NT$B | E37: 8 | G37: Verified | H37: Investing.com 2026-07-31（Lite-On Q2 2026 slides 摘要）：2Q26 Cloud and AIoT 289 億（55%，季增 26%）、Opto-electronics 80 億（季增 12%）、IT and Consumer Electronics 158 億（季增 18%） | I37: —
A38: q2_ic | B38: 2Q26 資訊及消費性電子營收 | C38: NT$B | E38: 15.8 | G38: Verified | H38: Investing.com 2026-07-31（Lite-On Q2 2026 slides 摘要）：2Q26 Cloud and AIoT 289 億（55%，季增 26%）、Opto-electronics 80 億（季增 12%）、IT and Consumer Electronics 158 億（季增 18%） | I38: 三事業群合計 527 億＝合併營收 52.703（差 0）
A39: g1_cl | B39: 2Q26 雲端及物聯網季增 | C39: % | E39: 0.26 | G39: Verified | H39: Investing.com 2026-07-31（Lite-On Q2 2026 slides 摘要）：2Q26 Cloud and AIoT 289 億（55%，季增 26%）、Opto-electronics 80 億（季增 12%）、IT and Consumer Electronics 158 億（季增 18%） | I39: 1Q26＝2Q26 ÷（1＋季增）（Derived）
A40: g1_op | B40: 2Q26 光電季增 | C40: % | E40: 0.12 | G40: Verified | H40: Investing.com 2026-07-31（Lite-On Q2 2026 slides 摘要）：2Q26 Cloud and AIoT 289 億（55%，季增 26%）、Opto-electronics 80 億（季增 12%）、IT and Consumer Electronics 158 億（季增 18%） | I40: 同上
A41: g1_ic | B41: 2Q26 資訊及消費性電子季增 | C41: % | E41: 0.18 | G41: Verified | H41: Investing.com 2026-07-31（Lite-On Q2 2026 slides 摘要）：2Q26 Cloud and AIoT 289 億（55%，季增 26%）、Opto-electronics 80 億（季增 12%）、IT and Consumer Electronics 158 億（季增 18%） | I41: 同上；1Q26 三者合計 434.7 億 vs 公司 434.07 億（季增四捨五入，差額併入資訊及消費性電子）
A42: s2h_cl | B42: 3Q、4Q26 雲端及物聯網 ÷ 營收 | C42: % | D42: 0.53 | E42: 0.55 | F42: 0.58 | G42: Assumed | H42: 沿用 2Q26 55%；3Q26 各事業群營收：未找到（月營收新聞稿未取得） | I42: 公司：雲端運算全年年增超過 70%（富果 2026-07-31）
A43: s2h_op | B43: 3Q、4Q26 光電 ÷ 營收 | C43: % | D43: 0.14 | E43: 0.152 | F43: 0.16 | G43: Assumed | H43: 沿用 2Q26 15.2%（80 ÷ 527） | I43: —
A44: g_cn27 | B44: 雲端及物聯網：非 AI 部分年增 2027（一般伺服器與網通電源、車用、工控與 IoT） | C44: % | D44: 0 | E44: 0.05 | F44: 0.1 | G44: Assumed | H44: 公司 2026：工控、標準電源、邊緣運算擴充；車用電源（富果 2026-02-25） | I44: FY2026 由錨點反推（雲端及物聯網 − AI 相關）
A45: g_cn28 | B45: 雲端及物聯網：非 AI 部分年增 2028（一般伺服器與網通電源、車用、工控與 IoT） | C45: % | D45: 0 | E45: 0.05 | F45: 0.1 | G45: Assumed | H45: 同上 | I45: —
A46: g_cn29 | B46: 雲端及物聯網：非 AI 部分年增 2029（一般伺服器與網通電源、車用、工控與 IoT） | C46: % | D46: 0 | E46: 0.05 | F46: 0.1 | G46: Assumed | H46: 同上 | I46: —
A47: g_op27 | B47: 光電年增 2027（光耦合器、感測、AI 伺服器與交換器指示燈） | C47: % | D47: 0 | E47: 0.05 | F47: 0.1 | G47: Assumed | H47: 公司：高階光耦合器用於工控、新能源與 AI 電能（technews 2026-03-10）；2Q26 季增 12% | I47: Denselight（新加坡 InP，持股 21%，權益法）不併入營收
A48: g_op28 | B48: 光電年增 2028（光耦合器、感測、AI 伺服器與交換器指示燈） | C48: % | D48: 0 | E48: 0.05 | F48: 0.1 | G48: Assumed | H48: 同上 | I48: —
A49: g_op29 | B49: 光電年增 2029（光耦合器、感測、AI 伺服器與交換器指示燈） | C49: % | D49: 0 | E49: 0.05 | F49: 0.1 | G49: Assumed | H49: 同上 | I49: —
A50: g_ic27 | B50: 資訊及消費性電子年增 2027（PC 與遊戲機電源、低軌衛星與高階電源、影像） | C50: % | D50: -0.05 | E50: 0 | F50: 0.05 | G50: Assumed | H50: 公司 2026 指引：資訊產品 −6～−8%、手機 −4～−5%（記憶體短缺）；下半年持平（富果 2026-07-31） | I50: 低軌衛星高階電源 2026 年增一倍以上（Investing.com 2026-07-31，Interested-party）
A51: g_ic28 | B51: 資訊及消費性電子年增 2028（PC 與遊戲機電源、低軌衛星與高階電源、影像） | C51: % | D51: -0.05 | E51: 0 | F51: 0.05 | G51: Assumed | H51: 同上 | I51: —
A52: g_ic29 | B52: 資訊及消費性電子年增 2029（PC 與遊戲機電源、低軌衛星與高階電源、影像） | C52: % | D52: -0.05 | E52: 0 | F52: 0.05 | G52: Assumed | H52: 同上 | I52: —
A53: D. 毛利率
A54: d_ai | B54: AI 相關毛利率高於其他營收的幅度 | C54: pt | D54: 0.08 | E54: 0.12 | F54: 0.16 | G54: Assumed | H54: https://uanalyze.com.tw/articles/3402052563：2Q26 雲端與物聯網營收 288.9 億、營業利益 69 億（營益率約 24%）vs 公司 15.6%；其他部門合計約 5–6%（Derived） | I54: 部門別毛利率未揭露：未找到；毛利率 FY2025 22.9% → 2Q26 27.2%（AI 占比上升）
A55: gmu_27 | B55: AI 相關毛利率額外改善 2027（800V 電源櫃、組合；情境 A 取高、C 取低） | C55: pt | D55: -0.01 | E55: 0 | F55: 0.01 | G55: Assumed | H55: 公司：2026 年毛利率目標約 25%（富果 2026-07-31）；800V HVDC 電源櫃與 110kW Power Shelf 2027 放量（Interested-party） | I55: 下檔：零組件漲價、新廠（高雄二期、越南、德州）爬坡
A56: gmu_28 | B56: AI 相關毛利率額外改善 2028（800V 電源櫃、組合；情境 A 取高、C 取低） | C56: pt | D56: -0.015 | E56: 0 | F56: 0.015 | G56: Assumed | H56: 同上 | I56: —
A57: gmu_29 | B57: AI 相關毛利率額外改善 2029（800V 電源櫃、組合；情境 A 取高、C 取低） | C57: pt | D57: -0.02 | E57: 0 | F57: 0.02 | G57: Assumed | H57: 同上 | I57: —
A58: E. FY2026 錨點（1H26 財報＋3Q26 月營收實績＋假設；3Q26 財報與法說預計 2026-10-30 前後，截至 2026-10-25 尚未公布）
A59: ytd9 | B59: 2026 年 1–9 月營收（月營收累計，實績） | C59: NT$B | E59: 153.559 | G59: Verified | H59: https://finance.technews.tw/2026/10/08/ltc-2301-202609-financial-report/：9 月 188.48 億元、前 9 月 1,535.59 億元（年增 26.1%） | I59: https://www.nstock.tw/2301?status=2：9 月 188.48 億、前 9 月 1,535.59 億（同值）
A60: q3_rev | B60: 3Q26 營收（＝1–9 月累計 − 1H26） | C60: NT$B | E60: =ytd9-(43.407+52.703) -> 57.449 | G60: Derived | H60: 1H26 營收 961.1 億（優分析 2026-07-31） | I60: 7、8 月個別營收：未找到
A61: q4g | B61: 4Q26 營收季增 | C61: % | D61: -0.03 | E61: 0.03 | F61: 0.08 | G61: Assumed | H61: 公司：下半年「非常樂觀」；800V HVDC 電源櫃 11 月小量（富果 2026-07-31） | I61: 9 月月減 3.8%（technews）；資訊與消費電子下半年與上半年持平；共識 FY2026 營收 2,198 億（MarketScreener，只作 Recon）
A62: q_gm | B62: 3Q、4Q26 毛利率 | C62: % | D62: 0.25 | E62: 0.26 | F62: 0.275 | G62: Assumed | H62: 1Q26 21.7%、2Q26 27.2%、1H26 24.7%（stockanalysis、優分析） | I62: 公司 2026 年毛利率目標約 25%（富果 2026-07-31，Interested-party）
A63: q_opx | B63: 3Q、4Q26 營業費用 ÷ 營收 | C63: % | D63: 0.112 | E63: 0.118 | F63: 0.125 | G63: Assumed | H63: 1Q26 12.2%、2Q26 11.7%（毛利 − 營業利益；Q 頁） | I63: FY2025 12.8%；研發約占營收 5–5.5%（富果 2026-07-31）
A64: q_nop | B64: 3Q、4Q26 營業外淨額（每季） | C64: NT$B | D64: 0.5 | E64: 0.9 | F64: 1.2 | G64: Assumed | H64: 1H26 稅前 − 營業利益＝約 20.4 億（stockanalysis 稅前淨利率推算） | I64: FY2025 約 29.7 億（同上）
A65: q_nir | B65: 淨利 ÷ 稅前（1H26 實績；3Q、4Q26 沿用） | C65: % | D65: 0.73 | E65: =10.891/14.341 -> 0.759431 | F65: 0.78 | G65: Derived | H65: 1H26：淨利 108.91 ÷ 稅前約 143.41 億（stockanalysis 季度淨利、稅前淨利率推算） | I65: FY2025：151.16 ÷ 197.1＝0.767（同上）
A66: q_sh | B66: 股數（十億股；EPS 換算） | C66: 十億股 | E66: =10.891/4.8 -> 2.2689583 | G66: Derived | H66: 1H26 淨利 108.91 億 ÷ EPS 4.80（優分析 2026-07-31） | I66: stockanalysis 流通股數 22.7 億股（2026-10-22）
A67: F. 營業費用、業外、稅與股數（FY2027 起）
A68: phi | B68: 營業費用成長對營收成長的彈性 | C68: x | D68: 0.5 | E68: 0.7 | F68: 1 | G68: Assumed | H68: FY2026 錨點實測約 0.65（Q 頁 B26） | I68: FY2025：營業費用 +17% ÷ 營收 +21%（stockanalysis 推算）
A69: opx_adj | B69: 營業費用額外占營收比（Sens 用；基準 0） | C69: pt | D69: -0.01 | E69: 0 | F69: 0.01 | G69: Assumed | H69: 無 | I69: Sens 用 ±1 個百分點
A70: nop_f | B70: 營業外淨額（每年） | C70: NT$B | D70: 2 | E70: 3.5 | F70: 5 | G70: Assumed | H70: FY2025 約 29.7 億、1H26 約 20.4 億（stockanalysis 推算） | I70: 含利息收入、投資收益；Denselight 權益法損益未另計
A71: nir_f | B71: 淨利 ÷ 稅前（FY2027 起） | C71: % | D71: 0.73 | E71: 0.76 | F71: 0.78 | G71: Derived | H71: 同 q_nir（1H26 0.759；FY2025 0.767） | I71: —
A72: sh_g | B72: 股數年變動 | C72: % | D72: 0 | E72: 0 | F72: 0.005 | G72: Assumed | H72: FY2025 推導 22.8 億股 → 1H26 22.7 億股（淨利 ÷ EPS） | I72: —
A73: mf | B73: AI 部署係數（Sens 用；FY2027 起） | C73: x | D73: 0.8 | E73: 1 | F73: 1.2 | G73: Assumed | H73: 網通模型 2027 年 AI IT 資本支出約 2 倍 | I73: ±20%
A74: G. 共識、券商與台達電模型（只作 Recon 對帳，不作校準）
A75: cons_rev26 | B75: 共識 FY2026 營收（MarketScreener） | C75: NT$B | E75: 219.778 | G75: Interested-party | H75: https://www.marketscreener.com/quote/stock/LITE-ON-TECHNOLOGY-CORPOR-6492334/valuation/（參考價 255.50，2026-10-22） | I75: stockanalysis FY2026 2,193 億（區間 2,101–2,297）
A76: cons_eps26 | B76: 共識 FY2026 EPS（MarketScreener） | C76: NT$ | E76: 10.81 | G76: Interested-party | H76: https://www.marketscreener.com/quote/stock/LITE-ON-TECHNOLOGY-CORPOR-6492334/valuation/ | I76: stockanalysis FY2026 10.81（11 家，區間 10.06–11.79）
A77: cons_rev27 | B77: 共識 FY2027 營收（MarketScreener） | C77: NT$B | E77: 292.383 | G77: Interested-party | H77: https://www.marketscreener.com/quote/stock/LITE-ON-TECHNOLOGY-CORPOR-6492334/valuation/（參考價 255.50，2026-10-22） | I77: —
A78: cons_eps27 | B78: 共識 FY2027 EPS（MarketScreener） | C78: NT$ | E78: 14.99 | G78: Interested-party | H78: https://www.marketscreener.com/quote/stock/LITE-ON-TECHNOLOGY-CORPOR-6492334/valuation/ | I78: FY2027 以後第二來源：未找到
A79: cons_rev28 | B79: 共識 FY2028 營收（MarketScreener） | C79: NT$B | E79: 366.11 | G79: Interested-party | H79: https://www.marketscreener.com/quote/stock/LITE-ON-TECHNOLOGY-CORPOR-6492334/valuation/（參考價 255.50，2026-10-22） | I79: —
A80: cons_eps28 | B80: 共識 FY2028 EPS（MarketScreener） | C80: NT$ | E80: 20.74 | G80: Interested-party | H80: https://www.marketscreener.com/quote/stock/LITE-ON-TECHNOLOGY-CORPOR-6492334/valuation/ | I80: FY2027 以後第二來源：未找到
A81: d_sh26 | B81: 台達電模型：台達電 AI 電源有效份額 2026 | C81: % | E81: 0.58367194 | G81: Derived | H81: delta/dist/20261028_台達電個股模型_v0.3.xlsx｜Units!C8:F8 | I81: 唯讀台達電成品（三情境相同：份額相對值不隨情境變動）
A82: d_pmk26 | B82: 台達電模型：AI 電源市場 2026（情境 A） | C82: US$B | E82: 10.529792 | G82: Derived | H82: delta/dist/20261028_台達電個股模型_v0.3.xlsx｜Units!C7:F7 | I82: 唯讀台達電成品（Recon：與本模型情境 A 應相同）
A83: d_aip26 | B83: 台達電模型：台達電 AI 電源營收 2026（情境 A） | C83: US$B | E83: 6.1459442 | G83: Derived | H83: delta/dist/20261028_台達電個股模型_v0.3.xlsx｜Units!C9:F9 | I83: 唯讀台達電成品
A84: d_sh27 | B84: 台達電模型：台達電 AI 電源有效份額 2027 | C84: % | E84: 0.55448834 | G84: Derived | H84: delta/dist/20261028_台達電個股模型_v0.3.xlsx｜Units!C8:F8 | I84: 同上
A85: d_pmk27 | B85: 台達電模型：AI 電源市場 2027（情境 A） | C85: US$B | E85: 24.988059 | G85: Derived | H85: delta/dist/20261028_台達電個股模型_v0.3.xlsx｜Units!C7:F7 | I85: 同上
A86: d_aip27 | B86: 台達電模型：台達電 AI 電源營收 2027（情境 A） | C86: US$B | E86: 13.855588 | G86: Derived | H86: delta/dist/20261028_台達電個股模型_v0.3.xlsx｜Units!C9:F9 | I86: 同上
... A92: d_aip29 | B92: 台達電模型：台達電 AI 電源營收 2029（情境 A） | C92: US$B | E92: 21.48194 | G92: Derived | H92: delta/dist/20261028_台達電個股模型_v0.3.xlsx｜Units!C9:F9 | I92: 同上
A93: kgi_dsh | B93: 凱基：台達電 AI 伺服器電源市占（中點） | C93: % | D93: 0.6 | E93: 0.625 | F93: 0.65 | G93: Interested-party | H93: https://www.kgi.com.hk/zh-hk/-/media/files/kgishk/research-reports/tw-reports/power-supply-sector_20250926e.pdf：約 60–65%，長期略降 | I93: 光寶與 Flex 為第二梯隊（份額數字：未找到）
A94: H. 價格與估值
A95: px | B95: 股價（2026-10-22 收盤，臺灣證交所） | C95: NT$ | E95: 255.5 | G95: Interested-party | H95: https://stockanalysis.com/quote/tpe/2301/：10-22 255.50（−3.04%）、前收 263.50 | I95: nstock（網址見 Sources 頁）：10-22 255.5（成交 7,003 張；HiStock 同值）；10-23 收盤：未找到
A96: pe_ttm | B96: 近 12 月 P/E（stockanalysis，10-22） | C96: x | E96: 30.09 | G96: Interested-party | H96: https://stockanalysis.com/quote/tpe/2301/ | I96: 近 12 月 EPS 8.49
A97: fpe | B97: 前瞻 P/E（stockanalysis，10-22） | C97: x | E97: 19.7 | G97: Interested-party | H97: https://stockanalysis.com/quote/tpe/2301/ | I97: 口徑：頁面未明示（約未來 12 月）
A98: cons_feps | B98: 共識前瞻 12 月 EPS（現價 ÷ 前瞻 P/E） | C98: NT$ | E98: =px/fpe -> 12.969543 | G98: Derived | H98: stockanalysis 前瞻 P/E 19.70（2026-10-22） | I98: 共識前瞻 EPS 的直接數字：未找到
A99: cons_tp | B99: 市場共識目標價（賣方平均） | C99: NT$ | E99: 314.25 | G99: Interested-party | H99: https://stockanalysis.com/quote/tpe/2301/：12 位分析師（S&P Global）平均 314.25（頁面時間 2026-10-22） | I99: https://stockanalysis.com/quote/tpe/2301/forecast/：2026-09-23 頁面平均 302.67、中位數 292.50、區間 176–400
A100: nim_avg | B100: 十年平均淨利率（2016–2025） | C100: % | E100: =AVERAGE(0.041,0.0123,0.0385,0.0529,0.0626,0.0845,0.0818,0.0984,0.0872,0.091) -> 0.06502 | G100: Interested-party | H100: https://stock.wearn.com/financial.asp?kind=2301：稅後淨利率 2016–2025：4.10%、1.23%、3.85%、5.29%、6.26%、8.45%、8.18%、9.84%、8.72%、9.10%（資料商） | I100: 單一來源；2017 年 1.23% 含一次性損失（商譽減損）
A101: J. 目標價與收斂法參數（黃底；Assumed，Andy 可改）
A102: tp_wA | B102: 目標價情境權重 A（A 順利／B 平平／C 不如預期） | C102: % | E102: 0.3 | G102: Assumed（Andy 可改） | H102: Andy 可改（工作單 2026-10-25 預設 A 0.3／B 0.5／C 0.2） | I102: 三者合計應為 100%（Val 頁第 0 節列示）
A103: tp_wB | B103: 目標價情境權重 B（A 順利／B 平平／C 不如預期） | C103: % | E103: 0.5 | G103: Assumed（Andy 可改） | H103: Andy 可改（工作單 2026-10-25 預設 A 0.3／B 0.5／C 0.2） | I103: 三者合計應為 100%（Val 頁第 0 節列示）
A104: tp_wC | B104: 目標價情境權重 C（A 順利／B 平平／C 不如預期） | C104: % | E104: 0.2 | G104: Assumed（Andy 可改） | H104: Andy 可改（工作單 2026-10-25 預設 A 0.3／B 0.5／C 0.2） | I104: 三者合計應為 100%（Val 頁第 0 節列示）
A105: tp_r | B105: 折現率／要求報酬 | C105: % | E105: 0.1 | G105: Assumed（Andy 可改） | H105: Andy 可改（工作單預設 10%，各市場同一值） | I105: DCF 折現；情境價值推到 12 個月後
...

Sheet Q
A1: Q — 實績與 FY2026 錨點（十億新台幣；EPS 為新台幣；股數為十億股）。藍字＝輸入；黑字＝公式。實績取自光寶科財報與月營收公告（經 stockanalysis、優分析、technews 轉述）
A2: FY2026 錨點＝1H26 財報＋3Q26 月營收實績（1–9 月累計 − 1H26）＋假設（3Q、4Q 毛利率、營業費用率、營業外；4Q 營收季增）。稅前利益＝營收 × stockanalysis 稅前淨利率（Derived，非公司原文）。3Q26 財報與法說預計 2026-10-30 前後（stockanalysis 估計；公司公告日期：未找到），截至 2026-10-25 尚未公布，公布後更新
A3: 項目 | B3: FY2025A | C3: 1H26（實績） | D3: 3Q26（營收實績） | E3: 4Q26（模型） | F3: FY2026 錨點 | G3: 標記 | H3: 來源1 | I3: 來源2／說明
A4: 營收 | B4: 166.085 | C4: =43.407+52.703 -> 96.11 | D4: =q3_rev -> 57.449 | E4: =D4*(1+q4g) -> 59.17247 | F4: =SUM(C4:E4) -> 212.73147 | G4: Verified／Assumed（4Q 季增） | H4: FY2025：https://stockanalysis.com/quote/tpe/2301/financials/（營收 1,660.85 億、毛利 380.39 億、營業利益 167.38 億、淨利 151.16 億）；1H26：https://stockanalysis.com/quote/tpe/2301/financials/?p=quarterly（1Q26、2Q26） | I4: FY2025：優分析 2026-02-25（營收 1,660.9 億、毛利率 22.9%、營益率 10.1%、淨利 151.2 億、EPS 6.64）；1H26：優分析 2026-07-31（營收 961.1 億、毛利率 24.7%、營業利益 123.0 億、淨利 108.9 億、EPS 4.80）；3Q26＝1–9 月月營收累計 − 1H26
A5: 毛利 | B5: 38.039 | C5: =9.403+14.348 -> 23.751 | D5: =D4*q_gm -> 14.93674 | E5: =E4*q_gm -> 15.384842 | F5: =SUM(C5:E5) -> 54.072582 | G5: Verified／Assumed | H5: FY2025：https://stockanalysis.com/quote/tpe/2301/financials/（營收 1,660.85 億、毛利 380.39 億、營業利益 167.38 億、淨利 151.16 億）；1H26：https://stockanalysis.com/quote/tpe/2301/financials/?p=quarterly（1Q26、2Q26） | I5: FY2025：優分析 2026-02-25（營收 1,660.9 億、毛利率 22.9%、營益率 10.1%、淨利 151.2 億、EPS 6.64）；1H26：優分析 2026-07-31（營收 961.1 億、毛利率 24.7%、營業利益 123.0 億、淨利 108.9 億、EPS 4.80）
A6: 毛利率 | B6: =B5/B4 -> 0.22903333 | C6: =C5/C4 -> 0.24712309 | D6: =D5/D4 -> 0.26 | E6: =E5/E4 -> 0.26 | F6: =F5/F4 -> 0.25418234 | G6: Derived | H6: — | I6: FY2025 22.9%；1H26 24.7%（公司）
A7: 營業費用 | B7: =B5-B8 -> 21.301 | C7: =C5-C8 -> 11.449 | D7: =D4*q_opx -> 6.778982 | E7: =E4*q_opx -> 6.9823515 | F7: =SUM(C7:E7) -> 25.210333 | G7: Derived／Assumed | H7: FY2025：https://stockanalysis.com/quote/tpe/2301/financials/（營收 1,660.85 億、毛利 380.39 億、營業利益 167.38 億、淨利 151.16 億）；1H26：https://stockanalysis.com/quote/tpe/2301/financials/?p=quarterly（1Q26、2Q26） | I7: 毛利 − 營業利益
A8: 營業利益 | B8: 16.738 | C8: =4.099+8.203 -> 12.302 | D8: =D5-D7 -> 8.157758 | E8: =E5-E7 -> 8.4024907 | F8: =SUM(C8:E8) -> 28.862249 | G8: Verified／Derived | H8: FY2025：https://stockanalysis.com/quote/tpe/2301/financials/（營收 1,660.85 億、毛利 380.39 億、營業利益 167.38 億、淨利 151.16 億）；1H26：https://stockanalysis.com/quote/tpe/2301/financials/?p=quarterly（1Q26、2Q26） | I8: FY2025：優分析 2026-02-25（營收 1,660.9 億、毛利率 22.9%、營益率 10.1%、淨利 151.2 億、EPS 6.64）；1H26：優分析 2026-07-31（營收 961.1 億、毛利率 24.7%、營業利益 123.0 億、淨利 108.9 億、EPS 4.80）
A9: 營業利益率 | B9: =B8/B4 -> 0.10077972 | C9: =C8/C4 -> 0.12799917 | D9: =D8/D4 -> 0.142 | E9: =E8/E4 -> 0.142 | F9: =F8/F4 -> 0.13567456 | G9: Derived | H9: — | I9: FY2025 10.1%；2Q26 15.6%（公司）
A10: 營業外淨額 | B10: =B11-B8 -> 2.9762895 | C10: =C11-C8 -> 2.039 | D10: =q_nop -> 0.9 | E10: =q_nop -> 0.9 | F10: =SUM(C10:E10) -> 3.839 | G10: Derived／Assumed | H10: 稅前 − 營業利益 | I10: —
A11: 稅前利益 | B11: =166.085*0.1187 -> 19.714289 | C11: =4.97+9.371 -> 14.341 | D11: =D8+D10 -> 9.057758 | E11: =E8+E10 -> 9.3024907 | F11: =SUM(C11:E11) -> 32.701249 | G11: Derived | H11: FY2025＝營收 × 稅前淨利率 11.87%（stockanalysis）；1H26＝1Q26 約 49.70 億＋2Q26 約 93.71 億（stockanalysis 季度稅前淨利率推算） | I11: 公司揭露稅前：未找到
A12: 歸屬母公司淨利 | B12: 15.116 | C12: =3.775+7.116 -> 10.891 | D12: =D11*q_nir -> 6.8787422 | E12: =E11*q_nir -> 7.0645999 | F12: =SUM(C12:E12) -> 24.834342 | G12: Verified／Derived（3Q、4Q） | H12: FY2025：https://stockanalysis.com/quote/tpe/2301/financials/（營收 1,660.85 億、毛利 380.39 億、營業利益 167.38 億、淨利 151.16 億）；1H26：https://stockanalysis.com/quote/tpe/2301/financials/?p=quarterly（1Q26、2Q26） | I12: 1Q26 37.75 億、2Q26 71.16 億（stockanalysis）；1H26 108.9 億（優分析）
A13: 淨利 ÷ 稅前（含稅與非控制權益） | B13: =B12/B11 -> 0.76675348 | C13: =C12/C11 -> 0.759431 | D13: =D12/D11 -> 0.759431 | E13: =E12/E11 -> 0.759431 | F13: =F12/F11 -> 0.759431 | G13: Derived | H13: — | I13: —
A14: 股數（十億股） | B14: =15.116/6.64 -> 2.276506 | C14: =q_sh -> 2.2689583 | D14: =q_sh -> 2.2689583 | E14: =q_sh -> 2.2689583 | F14: =q_sh -> 2.2689583 | G14: Derived | H14: FY2025：https://stockanalysis.com/quote/tpe/2301/financials/（營收 1,660.85 億、毛利 380.39 億、營業利益 167.38 億、淨利 151.16 億）；1H26：https://stockanalysis.com/quote/tpe/2301/financials/?p=quarterly（1Q26、2Q26） | I14: 淨利 ÷ EPS
A15: EPS | B15: =B12/B14 -> 6.64 | C15: =C12/C14 -> 4.8 | D15: =D12/D14 -> 3.0316741 | E15: =E12/E14 -> 3.1135873 | F15: =F12/F14 -> 10.945261 | G15: Derived | H15: 淨利 ÷ 股數 | I15: —
A16: 公司揭露 EPS | B16: 6.64 | C16: 4.8 | G16: Verified | H16: FY2025：https://stockanalysis.com/quote/tpe/2301/financials/（營收 1,660.85 億、毛利 380.39 億、營業利益 167.38 億、淨利 151.16 億）；1H26：https://stockanalysis.com/quote/tpe/2301/financials/?p=quarterly（1Q26、2Q26） | I16: FY2025 6.64（wearn 同值；stockanalysis 列 6.59，口徑未載明）；2Q26 3.14（優分析）
A17: AI 相關營收（＝營收 × AI 相關占比） | B17: =B4*ai_25 -> 34.87785 | F17: =F4*ai_26 -> 65.946756 | G17: Derived／Interested-party | H17: 公司 AI 相關占比（In 頁 C 節） | I17: 各季 AI 營收金額未揭露：未找到
A18: 其中 AI 電源（＝AI 相關 ×（1 − 非電源占比）） | B18: =B17*(1-x_np) -> 31.390065 | F18: =F17*(1-x_np) -> 59.35208 | G18: Derived／Assumed | H18: In 頁 x_np | I18: AI 電源含 PSU、Power Shelf、BBU、HVDC 電源櫃（與台達電模型的每 kW 內容口徑相同）
A19: 非 AI 營收（＝營收 − AI 相關） | B19: =B4-B17 -> 131.20715 | F19: =F4-F17 -> 146.78471 | G19: Derived | H19: — | I19: 一般雲端電源、光電、資訊與消費電子、車用
A23: FY2026 錨點的檢查（參考；校準未使用券商數字）
A24: FY2026 營收年增 | B24: =F4/B4-1 -> 0.28085902
A25: FY2026 營業費用年增 | B25: =F7/B7-1 -> 0.18352817
A26: 營業費用彈性（營業費用年增 ÷ 營收年增；In 頁 phi 的參考） | B26: =B25/B24 -> 0.65345299
A27: FY2026 營收 ÷ 共識（MarketScreener）− 1 | B27: =F4/cons_rev26-1 -> -0.032062035
A28: FY2026 EPS ÷ 共識（MarketScreener）− 1 | B28: =F15/cons_eps26-1 -> 0.012512619
A29: 非 AI 營收 FY2026 年增 | B29: =F19/B19-1 -> 0.11872497
A31: 營收分部（官方三大事業群；v0.2）
A32: 雲端及物聯網 | B32: =B4*s25_cl -> 74.73825 | C32: =q2_cl/(1+g1_cl)+q2_cl -> 51.836508 | D32: =D4*s2h_cl -> 31.59695 | E32: =E4*s2h_cl -> 32.544858 | F32: =SUM(C32:E32) -> 115.97832 | G32: Interested-party／Verified／Assumed | H32: FY2025＝營收 × 公司比例；1H26＝2Q26 實績＋2Q26 ÷（1＋季增） | I32: 3Q、4Q26 比例 Assumed（In 頁 s2h_cl）
A33: 光電 | B33: =B4*s25_op -> 28.23445 | C33: =q2_op/(1+g1_op)+q2_op -> 15.142857 | D33: =D4*s2h_op -> 8.732248 | E33: =E4*s2h_op -> 8.9942154 | F33: =SUM(C33:E33) -> 32.869321 | G33: Interested-party／Verified／Assumed | H33: 同上 | I33: 同上
A34: 資訊及消費性電子 | B34: =B4*s25_ic -> 63.1123 | C34: =C4-C32-C33 -> 29.130635 | D34: =D4-D32-D33 -> 17.119802 | E34: =E4-E32-E33 -> 17.633396 | F34: =SUM(C34:E34) -> 63.883833 | G34: Derived | H34: FY2025＝營收 × 公司比例；1H26 與 3Q、4Q＝營收 − 其餘兩事業群（1H26 公司值 158＋季增 18% 推得 291.9 億，差 0.6 億為季增四捨五入） | I34: —
A35: 檢查：分部合計 − 合併營收 | B35: =B32+B33+B34-B4 -> 0 | C35: =C32+C33+C34-C4 -> 0 | D35: =D32+D33+D34-D4 -> 0 | E35: =E32+E33+E34-E4 -> 0 | F35: =SUM(C35:E35) -> 0 | G35: Derived | H35: 應為 0 | I35: —
A36: 雲端及物聯網：AI 相關（＝第 17 列） | B36: =B17 -> 34.87785 | F36: =F17 -> 65.946756 | G36: Derived | H36: AI 相關全部歸雲端及物聯網（Assumed：AI 光電金額小，未拆） | I36: —
A37: 雲端及物聯網：非 AI（＝雲端及物聯網 − AI 相關） | B37: =B32-B36 -> 39.8604 | F37: =F32-F36 -> 50.031561 | G37: Derived | H37: — | I37: 一般伺服器與網通電源、車用、工控、IoT

Sheet Units
A1: Units — AI 電源市場（每 kW 內容口徑與台達電模型一致，唯讀 delta/dist；本專案權威在台達電模型）、光寶有效份額與光寶＋台達電份額合計（情境 B）。部署 GW＝AI IT 資本支出（markets/network）÷ 每 GW IT 資本支出（Tokenomics，經橋接表）
A3: 項目 | B3: 單位 | C3: CY2026 | D3: CY2027 | E3: CY2028 | F3: CY2029 | G3: 說明
A4: 部署 GW（情境 B） | B4: GW | C4: =PL!D123 -> 23.399538 | D4: =PL!E123 -> 41.646766 | E4: =PL!F123 -> 42.233711 | F4: =PL!G123 -> 51.117803 | G4: AI IT 資本支出 × 顆數係數 B ÷ 每 GW IT 資本支出
A5: AI 電源內容（台達電模型） | B5: US$/kW | C5: =PL!D124 -> 450 | D5: =PL!E124 -> 600 | E5: =PL!F124 -> 680 | F5: =PL!G124 -> 720 | G5: 唯讀 delta/dist In 頁（2026–27 Derived，2028 起 Assumed）
A6: 每架 AI 電源內容（以 VR200 每 GW 架數換算） | B6: US$K/架 | C6: =PL!D124*1000000/racks_vr/1000 -> 111.05627 | D6: =PL!E124*1000000/racks_vr/1000 -> 148.07502 | E6: =PL!F124*1000000/racks_vr/1000 -> 167.81836 | F6: =PL!G124*1000000/racks_vr/1000 -> 177.69003
A7: AI 電源市場 | B7: US$B | C7: =PL!D125 -> 10.529792 | D7: =PL!E125 -> 24.988059 | E7: =PL!F125 -> 28.718923 | F7: =PL!G125 -> 36.804818 | G7: 含 ASIC 機架（假設每 kW 內容相同）
A8: 光寶有效份額 | B8: % | C8: =PL!D129 -> 0.17614332 | D8: =PL!E129 -> 0.17614332 | E8: =PL!F129 -> 0.17614332 | F8: =PL!G129 -> 0.17614332 | G8: FY2026 以公司 AI 相關占比 ×（1 − 非電源占比）校準
A9: 台達電有效份額（台達電模型） | B9: % | C9: =d_sh26 -> 0.58367194 | D9: =d_sh27 -> 0.55448834 | E9: =d_sh28 -> 0.52530475 | F9: =d_sh29 -> 0.49612115 | G9: 唯讀 delta/dist Units 頁；台達電份額相對值不隨情境變動
A10: 光寶＋台達電份額合計 | B10: % | C10: =PL!D129+d_sh26 -> 0.75981526 | D10: =PL!E129+d_sh27 -> 0.73063166 | E10: =PL!F129+d_sh28 -> 0.70144806 | F10: =PL!G129+d_sh29 -> 0.67226446 | G10: 應低於 100%；其餘為 Flex、群電、康舒、Vertiv、麥格米特等
A11: 其他廠商份額（＝1 − 合計） | B11: % | C11: =1-PL!D129-d_sh26 -> 0.24018474 | D11: =1-PL!E129-d_sh27 -> 0.26936834 | E11: =1-PL!F129-d_sh28 -> 0.29855194 | F11: =1-PL!G129-d_sh29 -> 0.32773554
A12: 光寶 AI 電源營收 | B12: US$B | C12: =PL!D130/fx -> 1.8547525 | D12: =PL!E130/fx -> 4.4014797 | E12: =PL!F130/fx -> 5.0586464 | F12: =PL!G130/fx -> 6.4829227
A13: 光寶 AI 相關營收（含液冷等非電源） | B13: US$B | C13: =PL!D131/fx -> 2.0608361 | D13: =PL!E131/fx -> 4.890533 | E13: =PL!F131/fx -> 5.6207182 | F13: =PL!G131/fx -> 7.2032475
A14: 光寶 AI 電源營收 ÷ 台達電 AI 電源營收（份額比） | B14: x | C14: =PL!D129/d_sh26 -> 0.30178479 | D14: =PL!E129/d_sh27 -> 0.3176682 | E14: =PL!F129/d_sh28 -> 0.33531644 | F14: =PL!G129/d_sh29 -> 0.35504093 | G14: 同一市場，故等於份額比
A15: 每 GW 光寶 AI 相關營收 | B15: US$M/GW | C15: =PL!D142 -> 88.071658 | D15: =PL!E142 -> 117.42888 | E15: =PL!F142 -> 133.08606 | F15: =PL!G142 -> 140.91465
A17: 讀法：光寶與台達電讀同一個 AI 電源市場（部署 GW × 台達電模型每 kW 內容）。FY2026 光寶有效份額約一成八（AI 相關扣除一成非電源）、台達電約五成八，合計約七成六，與凱基「台達電 60–65%、光寶與 Flex 第二梯隊」相符；台達電模型的份額逐年下降（光寶、Flex、中國廠追趕），本模型光寶份額相對值在情境 A 上升、B 持平、C 下降，CY2029 合計約六成三（C）到七成二（A），其餘留給其他廠商，合計不超過 100%。

Sheet PL
A1: PL — 光寶科損益（十億新台幣；EPS 新台幣；歸屬母公司）。FY2025A 實績、FY2026 錨點（1H26 財報＋3Q26 月營收＋假設），FY2027 起為模型。FY(t)＝CY(t)。三情境各一個完整推導區塊（本頁下方），頂端為摘要。顆數係數從 CY2028 開始；份額相對值、AI 毛利率額外改善從 FY2027 起依情境取高／基準／低值
A2: 灰底＝FY2030–FY2032 收斂法（上游只到 2029）：營收年增線性收斂到 fade_g、淨利率線性收斂到 fade_m（In 頁 J 節），非驅動因子推導
A3: 情境／項目 | B3: 單位 | C3: FY2025A | D3: FY2026（錨點） | E3: FY2027 | F3: FY2028 | G3: FY2029 | H3: FY2030（收斂） | I3: FY2031（收斂） | J3: FY2032（收斂） | K3: 說明
A4: 情境 A
A5: 營收 | B5: NT$B | C5: =C95 -> 166.085 | D5: =D95 -> 212.73147 | E5: =E95 -> 323.07652 | F5: =F95 -> 425.07653 | G5: =G95 -> 498.82832 | H5: =H95 -> 566.50348 | I5: =I95 -> 621.92686 | J5: =J95 -> 659.24247
A6: 營收年增 | B6: % | D6: =D97 -> 0.28085902 | E6: =E97 -> 0.51870581 | F6: =F97 -> 0.31571471 | G6: =G97 -> 0.17350238 | H6: =H97 -> 0.13566825 | I6: =I97 -> 0.097834127 | J6: =J97 -> 0.06
A7: AI 相關營收（AI 電源、BBU、液冷） | B7: NT$B | C7: =C88 -> 34.87785 | D7: =D88 -> 65.946756 | E7: =E88 -> 172.14676 | F7: =F88 -> 269.79447 | G7: =G88 -> 338.97635
A8: 雲端及物聯網 | B8: NT$B | C8: =C91 -> 74.73825 | D8: =D91 -> 115.97832 | E8: =E91 -> 224.6799 | F8: =F91 -> 324.95427 | G8: =G91 -> 396.89414
A9: 其中非 AI | B9: NT$B | C9: =C90 -> 39.8604 | D9: =D90 -> 50.031561 | E9: =E90 -> 52.533139 | F9: =F90 -> 55.159796 | G9: =G90 -> 57.917785
A10: 光電 | B10: NT$B | C10: =C92 -> 28.23445 | D10: =D92 -> 32.869321 | E10: =E92 -> 34.512787 | F10: =F92 -> 36.238426 | G10: =G92 -> 38.050347
A11: 資訊及消費性電子 | B11: NT$B | C11: =C93 -> 63.1123 | D11: =D93 -> 63.883833 | E11: =E93 -> 63.883833 | F11: =F93 -> 63.883833 | G11: =G93 -> 63.883833
A12: 非 AI 營收 | B12: NT$B | C12: =C94 -> 131.20715 | D12: =D94 -> 146.78471 | E12: =E94 -> 150.92976 | F12: =F94 -> 155.28205 | G12: =G94 -> 159.85197
A13: AI 相關 ÷ 營收 | B13: % | C13: =C98 -> 0.21 | D13: =D98 -> 0.31 | E13: =E98 -> 0.53283588 | F13: =F98 -> 0.63469624 | G13: =G98 -> 0.67954513
A14: 毛利率 | B14: % | C14: =C104 -> 0.22903333 | D14: =D104 -> 0.25418234 | E14: =E104 -> 0.286251 | F14: =F104 -> 0.30266633 | G14: =G104 -> 0.31211865
A15: 營業利益率 | B15: % | C15: =C108 -> 0.10077972 | D15: =D108 -> 0.13567456 | E15: =E108 -> 0.17988593 | F15: =F108 -> 0.20395817 | G15: =G108 -> 0.2177887
A16: 歸屬母公司淨利 | B16: NT$B | C16: =C111 -> 15.116 | D16: =D111 -> 24.834342 | E16: =E111 -> 46.82886 | F16: =F111 -> 68.550351 | G16: =G111 -> 85.225768 | H16: =H111 -> 96.788199 | I16: =I111 -> 106.25739 | J16: =J111 -> 112.63283
A17: 淨利率 | B17: % | C17: =C115 -> 0.091013638 | D17: =D115 -> 0.11674033 | E17: =E115 -> 0.14494665 | F17: =F115 -> 0.1612659 | G17: =G115 -> 0.1708519 | H17: =H115 -> 0.1708519 | I17: =I115 -> 0.1708519 | J17: =J115 -> 0.1708519
A18: EPS | B18: NT$ | C18: =C113 -> 6.64 | D18: =D113 -> 10.945261 | E18: =E113 -> 20.638925 | F18: =F113 -> 30.212256 | G18: =G113 -> 37.561628 | H18: =H113 -> 42.657548 | I18: =I113 -> 46.830912 | J18: =J113 -> 49.640767
A19: EPS 年增 | B19: % | D19: =D114 -> 0.64838274 | E19: =E114 -> 0.88564931 | F19: =F114 -> 0.46384838 | G19: =G114 -> 0.24325794 | H19: =H114 -> 0.13566825 | I19: =I114 -> 0.097834127 | J19: =J114 -> 0.06
A21: 情境 B
A22: 營收 | B22: NT$B | C22: =C138 -> 166.085 | D22: =D138 -> 212.73147 | E22: =E138 -> 307.42681 | F22: =F138 -> 335.14504 | G22: =G138 -> 390.35588 | H22: =H138 -> 438.43138 | I22: =I138 -> 474.1982 | J22: =J138 -> 493.16613
A23: 營收年增 | B23: % | D23: =D140 -> 0.28085902 | E23: =E140 -> 0.44514027 | F23: =F140 -> 0.090162023 | G23: =G140 -> 0.16473718 | H23: =H140 -> 0.12315812 | I23: =I140 -> 0.08157906 | J23: =J140 -> 0.04
A24: AI 相關營收（AI 電源、BBU、液冷） | B24: NT$B | C24: =C131 -> 34.87785 | D24: =D131 -> 65.946756 | E24: =E131 -> 156.49705 | F24: =F131 -> 179.86298 | G24: =G131 -> 230.50392
A25: 雲端及物聯網 | B25: NT$B | C25: =C134 -> 74.73825 | D25: =D134 -> 115.97832 | E25: =E134 -> 209.03019 | F25: =F134 -> 235.02278 | G25: =G134 -> 288.4217
A26: 其中非 AI | B26: NT$B | C26: =C133 -> 39.8604 | D26: =D133 -> 50.031561 | E26: =E133 -> 52.533139 | F26: =F133 -> 55.159796 | G26: =G133 -> 57.917785
A27: 光電 | B27: NT$B | C27: =C135 -> 28.23445 | D27: =D135 -> 32.869321 | E27: =E135 -> 34.512787 | F27: =F135 -> 36.238426 | G27: =G135 -> 38.050347
A28: 資訊及消費性電子 | B28: NT$B | C28: =C136 -> 63.1123 | D28: =D136 -> 63.883833 | E28: =E136 -> 63.883833 | F28: =F136 -> 63.883833 | G28: =G136 -> 63.883833
A29: 非 AI 營收 | B29: NT$B | C29: =C137 -> 131.20715 | D29: =D137 -> 146.78471 | E29: =E137 -> 150.92976 | F29: =F137 -> 155.28205 | G29: =G137 -> 159.85197
A30: AI 相關 ÷ 營收 | B30: % | C30: =C141 -> 0.21 | D30: =D141 -> 0.31 | E30: =E141 -> 0.50905467 | F30: =F141 -> 0.53667207 | G30: =G141 -> 0.59049685
A31: 毛利率 | B31: % | C31: =C147 -> 0.22903333 | D31: =D147 -> 0.25418234 | E31: =E147 -> 0.2780689 | F31: =F147 -> 0.28138299 | G31: =G147 -> 0.28784196
A32: 營業利益率 | B32: % | C32: =C151 -> 0.10077972 | D32: =D151 -> 0.13567456 | E32: =E151 -> 0.17051215 | F32: =F151 -> 0.17649489 | G32: =G151 -> 0.18740439
A33: 歸屬母公司淨利 | B33: NT$B | C33: =C154 -> 15.116 | D33: =D154 -> 24.834342 | E33: =E154 -> 42.499206 | F33: =F154 -> 47.615053 | G33: =G154 -> 58.257348 | H33: =H154 -> 59.277979 | I33: =I154 -> 57.45753 | J33: =J154 -> 52.833289
A34: 淨利率 | B34: % | C34: =C158 -> 0.091013638 | D34: =D158 -> 0.11674033 | E34: =E158 -> 0.1382417 | F34: =F158 -> 0.14207298 | G34: =G158 -> 0.14924163 | H34: =H158 -> 0.13520469 | I34: =I158 -> 0.12116775 | J34: =J158 -> 0.10713081
A35: EPS | B35: NT$ | C35: =C156 -> 6.64 | D35: =D156 -> 10.945261 | E35: =E156 -> 18.730712 | F35: =F156 -> 20.985424 | G35: =G156 -> 25.675812 | H35: =H156 -> 26.125636 | I35: =I156 -> 25.323308 | J35: =J156 -> 23.285262
A36: EPS 年增 | B36: % | D36: =D157 -> 0.64838274 | E36: =E157 -> 0.71130789 | F36: =F157 -> 0.12037514 | G36: =G157 -> 0.22350693 | H36: =H157 -> 0.017519357 | I36: =I157 -> -0.030710375 | J36: =J157 -> -0.08048103
A38: 情境 C
A39: 營收 | B39: NT$B | C39: =C181 -> 166.085 | D39: =D181 -> 212.73147 | E39: =E181 -> 283.95226 | F39: =F181 -> 263.19984 | G39: =G181 -> 281.88345 | H39: =H181 -> 297.1026 | I39: =I181 -> 308.09405 | J39: =J181 -> 314.25593
A40: 營收年增 | B40: % | D40: =D183 -> 0.28085902 | E40: =E183 -> 0.33479196 | F40: =F183 -> -0.073084157 | G40: =G183 -> 0.070986396 | H40: =H183 -> 0.053990931 | I40: =I183 -> 0.036995465 | J40: =J183 -> 0.02
A41: AI 相關營收（AI 電源、BBU、液冷） | B41: NT$B | C41: =C174 -> 34.87785 | D41: =D174 -> 65.946756 | E41: =E174 -> 133.0225 | F41: =F174 -> 107.91779 | G41: =G174 -> 122.03149
A42: 雲端及物聯網 | B42: NT$B | C42: =C177 -> 74.73825 | D42: =D177 -> 115.97832 | E42: =E177 -> 185.55564 | F42: =F177 -> 163.07758 | G42: =G177 -> 179.94927
A43: 其中非 AI | B43: NT$B | C43: =C176 -> 39.8604 | D43: =D176 -> 50.031561 | E43: =E176 -> 52.533139 | F43: =F176 -> 55.159796 | G43: =G176 -> 57.917785
A44: 光電 | B44: NT$B | C44: =C178 -> 28.23445 | D44: =D178 -> 32.869321 | E44: =E178 -> 34.512787 | F44: =F178 -> 36.238426 | G44: =G178 -> 38.050347
A45: 資訊及消費性電子 | B45: NT$B | C45: =C179 -> 63.1123 | D45: =D179 -> 63.883833 | E45: =E179 -> 63.883833 | F45: =F179 -> 63.883833 | G45: =G179 -> 63.883833
A46: 非 AI 營收 | B46: NT$B | C46: =C180 -> 131.20715 | D46: =D180 -> 146.78471 | E46: =E180 -> 150.92976 | F46: =F180 -> 155.28205 | G46: =G180 -> 159.85197
A47: AI 相關 ÷ 營收 | B47: % | C47: =C184 -> 0.21 | D47: =D184 -> 0.31 | E47: =E184 -> 0.46846783 | F47: =F184 -> 0.41002224 | G47: =G184 -> 0.43291469
A48: 毛利率 | B48: % | C48: =C190 -> 0.22903333 | D48: =D190 -> 0.25418234 | E48: =E190 -> 0.2685138 | F48: =F190 -> 0.26003467 | G48: =G190 -> 0.26027381
A49: 營業利益率 | B49: % | C49: =C194 -> 0.10077972 | D49: =D194 -> 0.13567456 | E49: =E194 -> 0.15892324 | F49: =F194 -> 0.14180327 | G49: =G194 -> 0.14439337
A50: 歸屬母公司淨利 | B50: NT$B | C50: =C197 -> 15.116 | D50: =D197 -> 24.834342 | E50: =E197 -> 36.956226 | F50: =F197 -> 31.025176 | G50: =G197 -> 33.593597 | H50: =H197 -> 30.044101 | I50: =I197 -> 25.593936 | J50: =J197 -> 20.432921
A51: 淨利率 | B51: % | C51: =C201 -> 0.091013638 | D51: =D201 -> 0.11674033 | E51: =E201 -> 0.13014944 | F51: =F201 -> 0.11787688 | G51: =G201 -> 0.11917548 | H51: =H201 -> 0.10112366 | I51: =I201 -> 0.083071828 | J51: =J201 -> 0.06502
A52: EPS | B52: NT$ | C52: =C199 -> 6.64 | D52: =D199 -> 10.945261 | E52: =E199 -> 16.28775 | F52: =F199 -> 13.673753 | G52: =G199 -> 14.805736 | H52: =H199 -> 13.241363 | I52: =I199 -> 11.280038 | J52: =J199 -> 9.0054191
A53: EPS 年增 | B53: % | D53: =D200 -> 0.64838274 | E53: =E200 -> 0.48810973 | F53: =F200 -> -0.16048852 | G53: =G200 -> 0.082785061 | H53: =H200 -> -0.10565988 | I53: =I200 -> -0.1481211 | J53: =J200 -> -0.20164993
A55: 核對（應為 0）：FY2026 模型 − 錨點
A56: 三情境：營收差（NT$B） | D56: =ABS(D95-a26_rev)+ABS(D138-a26_rev)+ABS(D181-a26_rev) -> 0
A57: 情境 B：AI 相關差（NT$B） | D57: =D131-a26_ai -> 0
A58: 情境 B：毛利差（NT$B） | D58: =D145*D131+D144*D137-a26_gp -> 0
A75: 情境 A（順利）：顆數基準（tsmc 係數 A＝1.0）；份額相對值、AI 毛利率額外改善取高值
A76: 項目 | B76: 單位 | C76: FY2025A | D76: FY2026（錨點） | E76: FY2027 | F76: FY2028 | G76: FY2029 | H76: FY2030（收斂） | I76: FY2031（收斂） | J76: FY2032（收斂） | K76: 說明
A77: A. AI 部署與 AI 電源市場（D 欄＝FY2026 校準年；每 kW 內容取自台達電模型）
A78: AI IT 資本支出 × 情境顆數係數 | B78: US$B | D78: =itc_26*1 -> 781.87292 | E78: =itc_27*1*1 -> 1565.35 | F78: =itc_28*um28_A*1 -> 1984.2639 | G78: =itc_29*um29_A*1 -> 2260.3903
A79: 每 GW IT 資本支出 | B79: US$B | D79: =itpg_gb*(1-vr26)+itpg_vr*vr26 -> 33.414032 | E79: =itpg_vr -> 37.586352 | F79: =itpg_vr -> 37.586352 | G79: =itpg_vr -> 37.586352
A80: 部署 GW（IT 電力） | B80: GW | D80: =D78/D79 -> 23.399538 | E80: =E78/E79 -> 41.646766 | F80: =F78/F79 -> 52.792138 | G80: =G78/G79 -> 60.138592
A81: AI 電源內容（台達電模型） | B81: US$/kW | D81: =pkw_26 -> 450 | E81: =pkw_27 -> 600 | F81: =pkw_28 -> 680 | G81: =pkw_29 -> 720
A82: AI 電源市場（美元） | B82: US$B | D82: =D80*D81/1000 -> 10.529792 | E82: =E80*E81/1000 -> 24.988059 | F82: =F80*F81/1000 -> 35.898654 | G82: =G80*G81/1000 -> 43.299786
A83: AI 電源市場（新台幣） | B83: NT$B | D83: =D82*fx -> 336.95335 | E83: =E82*fx -> 799.6179 | F83: =F82*fx -> 1148.7569 | G83: =G82*fx -> 1385.5932
A84: 光寶有效份額（FY2026 校準）＝ AI 電源營收 ÷ 市場 | B84: % | D84: =a26_aip/D83 -> 0.17614332 | K84: Derived：分子為公司 AI 相關占比 × 營收 ×（1 − 非電源占比）；分母為與台達電模型相同的 AI 電源市場（含 ASIC 機架）
A85: 份額相對值（÷ FY2026） | B85: x | D85: =1 -> 1 | E85: =RHI_27 -> 1.1 | F85: =RHI_28 -> 1.2 | G85: =RHI_29 -> 1.25
A86: 光寶有效份額 | B86: % | D86: =$D$84*D85 -> 0.17614332 | E86: =$D$84*E85 -> 0.19375765 | F86: =$D$84*F85 -> 0.21137198 | G86: =$D$84*G85 -> 0.22017915
A87: AI 電源營收 | B87: NT$B | C87: =a25_aip -> 31.390065 | D87: =D83*D86 -> 59.35208 | E87: =E83*E86 -> 154.93208 | F87: =F83*F86 -> 242.81503 | G87: =G83*G86 -> 305.07872
A88: AI 相關營收（＝AI 電源 ÷（1 − 非電源占比）） | B88: NT$B | C88: =a25_ai -> 34.87785 | D88: =D87/(1-x_np) -> 65.946756 | E88: =E87/(1-x_np) -> 172.14676 | F88: =F87/(1-x_np) -> 269.79447 | G88: =G87/(1-x_np) -> 338.97635 | K88: 非電源部分（液冷、AI 光電）隨 AI 電源同比例成長（Assumed）
A89: B. 營收分部（官方三大事業群）與合計
A90: 雲端及物聯網：非 AI | B90: NT$B | C90: =a25_cn -> 39.8604 | D90: =a26_cn -> 50.031561 | E90: =D90*(1+g_cn27) -> 52.533139 | F90: =E90*(1+g_cn28) -> 55.159796 | G90: =F90*(1+g_cn29) -> 57.917785 | K90: 一般伺服器與網通電源、車用、工控、IoT；AI 相關（上列）為本分部的命題子列
A91: 雲端及物聯網 | B91: NT$B | C91: =C88+C90 -> 74.73825 | D91: =D88+D90 -> 115.97832 | E91: =E88+E90 -> 224.6799 | F91: =F88+F90 -> 324.95427 | G91: =G88+G90 -> 396.89414 | K91: ＝AI 相關＋非 AI（子列合計＝分部）
A92: 光電 | B92: NT$B | C92: =a25_op -> 28.23445 | D92: =a26_op -> 32.869321 | E92: =D92*(1+g_op27) -> 34.512787 | F92: =E92*(1+g_op28) -> 36.238426 | G92: =F92*(1+g_op29) -> 38.050347
A93: 資訊及消費性電子 | B93: NT$B | C93: =a25_ic -> 63.1123 | D93: =a26_ic -> 63.883833 | E93: =D93*(1+g_ic27) -> 63.883833 | F93: =E93*(1+g_ic28) -> 63.883833 | G93: =F93*(1+g_ic29) -> 63.883833
A94: 非 AI 營收（雲端非 AI＋光電＋資訊及消費性電子） | B94: NT$B | C94: =C90+C92+C93 -> 131.20715 | D94: =D90+D92+D93 -> 146.78471 | E94: =E90+E92+E93 -> 150.92976 | F94: =F90+F92+F93 -> 155.28205 | G94: =G90+G92+G93 -> 159.85197
A95: 營收 | B95: NT$B | C95: =C91+C92+C93 -> 166.085 | D95: =D91+D92+D93 -> 212.73147 | E95: =E91+E92+E93 -> 323.07652 | F95: =F91+F92+F93 -> 425.07653 | G95: =G91+G92+G93 -> 498.82832 | H95: =G95*(1+H97) -> 566.50348 | I95: =H95*(1+I97) -> 621.92686 | J95: =I95*(1+J97) -> 659.24247 | K95: FY2030 起為收斂法：營收年增由 FY2029 線性收斂到 fade_g、淨利率收斂到 fade_m（FY2032 達到），非驅動因子推導
A96: 檢查：分部合計 − 合併營收（FY2025 實績、FY2026 錨點） | B96: NT$B | C96: =C95-a25_rev -> 0 | D96: =D95-a26_rev -> 0
A97: 營收年增 | B97: % | D97: =D95/C95-1 -> 0.28085902 | E97: =E95/D95-1 -> 0.51870581 | F97: =F95/E95-1 -> 0.31571471 | G97: =G95/F95-1 -> 0.17350238 | H97: =$G97+(fade_gA-$G97)*1/3 -> 0.13566825 | I97: =$G97+(fade_gA-$G97)*2/3 -> 0.097834127 | J97: =$G97+(fade_gA-$G97)*3/3 -> 0.06
A98: AI 相關 ÷ 營收 | B98: % | C98: =C88/C95 -> 0.21 | D98: =D88/D95 -> 0.31 | E98: =E88/E95 -> 0.53283588 | F98: =F88/F95 -> 0.63469624 | G98: =G88/G95 -> 0.67954513
A99: 每 GW 光寶 AI 相關營收 | B99: US$M/GW | D99: =D88/fx/D80*1000 -> 88.071658 | E99: =E88/fx/E80*1000 -> 129.17177 | F99: =F88/fx/F80*1000 -> 159.70327 | G99: =G88/fx/G80*1000 -> 176.14332
A100: C. 損益
A101: 其他營收毛利率 ＝ 錨點毛利率 − 差距 × AI 占比（FY2026 校準） | B101: % | D101: =a26_gp/D95-d_ai*D98 -> 0.21698234 | K101: Derived：讓 FY2026 毛利率等於錨點；AI 相關毛利率＝其他＋差距
A102: AI 相關毛利率 ＝ 校準值 ＋ 額外改善 | B102: % | D102: =D101+d_ai -> 0.33698234 | E102: =$D$102+GUHI_27 -> 0.34698234 | F102: =$D$102+GUHI_28 -> 0.35198234 | G102: =$D$102+GUHI_29 -> 0.35698234 | K102: 額外改善為 800V 電源櫃與組合（Assumed；情境 A 高、C 低）
A103: 毛利 | B103: NT$B | C103: =a25_gp -> 38.039 | D103: =a26_gp -> 54.072582 | E103: =E88*E102+E94*$D$101 -> 92.480977 | F103: =F88*F102+F94*$D$101 -> 128.65635 | G103: =G88*G102+G94*$D$101 -> 155.69362
A104: 毛利率 | B104: % | C104: =C103/C95 -> 0.22903333 | D104: =D103/D95 -> 0.25418234 | E104: =E103/E95 -> 0.286251 | F104: =F103/F95 -> 0.30266633 | G104: =G103/G95 -> 0.31211865
A105: 營業費用（基準路徑） | B105: NT$B | C105: =a25_opx -> 21.301 | D105: =a26_opx -> 25.210333 | E105: =D105*(1+MAX(0,phi*E97)) -> 34.364056 | F105: =E105*(1+MAX(0,phi*F97)) -> 41.958522 | G105: =F105*(1+MAX(0,phi*G97)) -> 47.054455
A106: 營業費用 | B106: NT$B | C106: =C105 -> 21.301 | D106: =D105 -> 25.210333 | E106: =E105+0*E95 -> 34.364056 | F106: =F105+0*F95 -> 41.958522 | G106: =G105+0*G95 -> 47.054455
A107: 營業利益 | B107: NT$B | C107: =C103-C106 -> 16.738 | D107: =D103-D106 -> 28.862249 | E107: =E103-E106 -> 58.116921 | F107: =F103-F106 -> 86.69783 | G107: =G103-G106 -> 108.63917
A108: 營業利益率 | B108: % | C108: =C107/C95 -> 0.10077972 | D108: =D107/D95 -> 0.13567456 | E108: =E107/E95 -> 0.17988593 | F108: =F107/F95 -> 0.20395817 | G108: =G107/G95 -> 0.2177887
A109: 營業外淨額 | B109: NT$B | C109: =a25_nop -> 2.9762895 | D109: =a26_nop -> 3.839 | E109: =nop_f -> 3.5 | F109: =nop_f -> 3.5 | G109: =nop_f -> 3.5
A110: 歸屬母公司淨利 ÷ 稅前 | B110: % | C110: =a25_ni/a25_pt -> 0.76675348 | D110: =a26_ni/a26_pt -> 0.759431 | E110: =nir_f -> 0.76 | F110: =nir_f -> 0.76 | G110: =nir_f -> 0.76
A111: 歸屬母公司淨利 | B111: NT$B | C111: =a25_ni -> 15.116 | D111: =a26_ni -> 24.834342 | E111: =(E107+E109)*E110 -> 46.82886 | F111: =(F107+F109)*F110 -> 68.550351 | G111: =(G107+G109)*G110 -> 85.225768 | H111: =H95*H115 -> 96.788199 | I111: =I95*I115 -> 106.25739 | J111: =J95*J115 -> 112.63283
A112: 股數 | B112: 十億股 | C112: =a25_sh -> 2.276506 | D112: =a26_sh -> 2.2689583 | E112: =D112*(1+sh_g) -> 2.2689583 | F112: =E112*(1+sh_g) -> 2.2689583 | G112: =F112*(1+sh_g) -> 2.2689583 | H112: =G112*(1+sh_g) -> 2.2689583 | I112: =H112*(1+sh_g) -> 2.2689583 | J112: =I112*(1+sh_g) -> 2.2689583
A113: EPS | B113: NT$ | C113: =C111/C112 -> 6.64 | D113: =D111/D112 -> 10.945261 | E113: =E111/E112 -> 20.638925 | F113: =F111/F112 -> 30.212256 | G113: =G111/G112 -> 37.561628 | H113: =H111/H112 -> 42.657548 | I113: =I111/I112 -> 46.830912 | J113: =J111/J112 -> 49.640767
A114: EPS 年增 | B114: % | D114: =D113/C113-1 -> 0.64838274 | E114: =E113/D113-1 -> 0.88564931 | F114: =F113/E113-1 -> 0.46384838 | G114: =G113/F113-1 -> 0.24325794 | H114: =H113/G113-1 -> 0.13566825 | I114: =I113/H113-1 -> 0.097834127 | J114: =J113/I113-1 -> 0.06
A115: 淨利率（歸屬母公司淨利 ÷ 營收） | B115: % | C115: =C111/C95 -> 0.091013638 | D115: =D111/D95 -> 0.11674033 | E115: =E111/E95 -> 0.14494665 | F115: =F111/F95 -> 0.1612659 | G115: =G111/G95 -> 0.1708519 | H115: =$G115+(fade_mA-$G115)*1/3 -> 0.1708519 | I115: =$G115+(fade_mA-$G115)*2/3 -> 0.1708519 | J115: =$G115+(fade_mA-$G115)*3/3 -> 0.1708519
A118: 情境 B（平平）：tsmc 係數 B（CY2028 ×0.8、CY2029 ×0.85）；公司特有變數取基準
A119: 項目 | B119: 單位 | C119: FY2025A | D119: FY2026（錨點） | E119: FY2027 | F119: FY2028 | G119: FY2029 | H119: FY2030（收斂） | I119: FY2031（收斂） | J119: FY2032（收斂） | K119: 說明
A120: A. AI 部署與 AI 電源市場（D 欄＝FY2026 校準年；每 kW 內容取自台達電模型）
A121: AI IT 資本支出 × 情境顆數係數 | B121: US$B | D121: =itc_26*1 -> 781.87292 | E121: =itc_27*1*1 -> 1565.35 | F121: =itc_28*um28_B*1 -> 1587.4111 | G121: =itc_29*um29_B*1 -> 1921.3317
...

Sheet Val
A1: Val — P/E 估值（新台幣）。結論用「現價 ÷ FY2027、FY2028 EPS（模型）」；目標價＝DCF 與 Comparable 加權（第 0 節）；十年 P/E 規則值（第 3 節，年底落後 P/E）只作參考。本版未做先驗，無 Andy 合理 P/E 對照
A2: 循環位置：光寶科不是設備股，不套設備市場見頂年；以本模型營收最高的會計年度為見頂年（比照台達電；FY(t)＝CY(t)）。營收到 FY2029 仍在增加時，見頂年未知，判為中段
A4: 0. 目標價
A5: 0.1 DCF（股東權益現金流，FY2027–FY2032 明確期＋FY2032 後永續）
A6: 項目 | B6: A（順利） | C6: B（平平） | D6: C（不如預期） | E6: 說明
A7: 情境 EPS（FY2027–FY2032） | E7: PL 頁各情境；FY2030 起為收斂法
A8: FY2027 | B8: =PL!E18 -> 20.638925 | C8: =PL!E35 -> 18.730712 | D8: =PL!E52 -> 16.28775
A9: FY2028 | B9: =PL!F18 -> 30.212256 | C9: =PL!F35 -> 20.985424 | D9: =PL!F52 -> 13.673753
A10: FY2029 | B10: =PL!G18 -> 37.561628 | C10: =PL!G35 -> 25.675812 | D10: =PL!G52 -> 14.805736
A11: FY2030 | B11: =PL!H18 -> 42.657548 | C11: =PL!H35 -> 26.125636 | D11: =PL!H52 -> 13.241363
A12: FY2031 | B12: =PL!I18 -> 46.830912 | C12: =PL!I35 -> 25.323308 | D12: =PL!I52 -> 11.280038
A13: FY2032 | B13: =PL!J18 -> 49.640767 | C13: =PL!J35 -> 23.285262 | D13: =PL!J52 -> 9.0054191
A14: 股東現金流＝EPS ×（1 − tp_g ÷ tp_roe）
A15: 再投資率（tp_g ÷ tp_roe，上限 0.8） | B15: =MIN(tp_g/tp_roe,0.8) -> 0.25115111 | E15: ROE 為近三年平均（In 頁 tp_roe）
A16: FY2027 | B16: =B8*(1-$B$15) -> 15.455436 | C16: =C8*(1-$B$15) -> 14.026473 | D16: =D8*(1-$B$15) -> 12.197064
A17: FY2028 | B17: =B9*(1-$B$15) -> 22.624415 | C17: =C9*(1-$B$15) -> 15.714912 | D17: =D9*(1-$B$15) -> 10.239575
A18: FY2029 | B18: =B10*(1-$B$15) -> 28.127983 | C18: =C10*(1-$B$15) -> 19.227303 | D18: =D10*(1-$B$15) -> 11.087259
A19: FY2030 | B19: =B11*(1-$B$15) -> 31.944058 | C19: =C11*(1-$B$15) -> 19.564153 | D19: =D11*(1-$B$15) -> 9.9157802
A20: FY2031 | B20: =B12*(1-$B$15) -> 35.069277 | C20: =C12*(1-$B$15) -> 18.963331 | D20: =D12*(1-$B$15) -> 8.4470439
A21: FY2032 | B21: =B13*(1-$B$15) -> 37.173433 | C21: =C13*(1-$B$15) -> 17.437143 | D21: =D13*(1-$B$15) -> 6.7436981
A22: DCF 情境每股價值（折現率 tp_r） | B22: =MAX(0,SUMPRODUCT(B16:B21,1/(1+tp_r)^{1;2;3;4;5;6})+B21*(1+tp_g)/(tp_r-tp_g)/(1+tp_r)^6) -> 482.171 | C22: =MAX(0,SUMPRODUCT(C16:C21,1/(1+tp_r)^{1;2;3;4;5;6})+C21*(1+tp_g)/(tp_r-tp_g)/(1+tp_r)^6) -> 245.7735 | D22: =MAX(0,SUMPRODUCT(D16:D21,1/(1+tp_r)^{1;2;3;4;5;6})+D21*(1+tp_g)/(tp_r-tp_g)/(1+tp_r)^6) -> 109.68671 | E22: Σ 明確期現金流 ÷ (1＋r)^t ＋ 永續價值 ÷ (1＋r)^6；永續價值＝FY2032 現金流 ×(1＋g)÷(r−g)；基準日 2026 年底；負值取 0（Andy 12:22）
A23: DCF 情境價值推到 12 個月後（×(1＋tp_r)） | B23: =B22*(1+tp_r) -> 530.3881 | C23: =C22*(1+tp_r) -> 270.35085 | D23: =D22*(1+tp_r) -> 120.65538
A24: DCF 目標價（情境加權） | B24: =tp_wA*B23+tp_wB*C23+tp_wC*D23 -> 318.42293 | E24: Σ 權重 × 情境價值 ×(1＋r)；權重見 In 頁
A26: 0.2 Comparable（市場主流同業前瞻 P/E；非 A 股公司，同業不放 A 股）
A27: 同業與前瞻 P/E | B27: 代號 | C27: 前瞻 12 月 P/E | D27: 日期 | E27: 來源 | F27: 標記
A28: 台達電（Delta Electronics） | B28: 2308.TW | C28: 30.51 | D28: 2026-10-22 | E28: stockanalysis.com forward PE（分析師共識；價格日期如左） | F28: Interested-party
A29: Vertiv | B29: VRT | C29: 24.53 | D29: 2026-10-23 | E29: stockanalysis.com forward PE（分析師共識；價格日期如左） | F29: Interested-party
A30: Eaton | B30: ETN | C30: 24.17 | D30: 2026-10-23 | E30: stockanalysis.com forward PE（分析師共識；價格日期如左） | F30: Interested-party
A31: Flex | B31: FLEX | C31: 14.74 | D31: 2026-10-23 | E31: stockanalysis.com forward PE（分析師共識；價格日期如左） | F31: Interested-party
A33: 未列入（資料過舊）：群電 6412.TW 前瞻 P/E 13.6x（stockanalysis 快取 2026-09-04）；康舒 6282.TW 前瞻 P/E：未找到。麥格米特 002851.SZ 為 A 股，依規則不列
A34: 同業前瞻 P/E 中位數 | B34: =MEDIAN(C28:C31) -> 24.35 | E34: AI 資料中心電源與電氣同業：台達電、Vertiv、Eaton、Flex（券商常用比較組；台達電模型的同業名單也含光寶）
A35: 12 個月後的前瞻 EPS（情境加權） | B35: =tp_wA*(2/12*B8+10/12*B9)+tp_wB*(2/12*C8+10/12*C9)+tp_wC*(2/12*D8+10/12*D9) -> 21.711714 | E35: 約 2027-10 時的未來 12 月 EPS ≈ 2／12 × FY2027＋10／12 × FY2028（會計年度＝日曆年）
A36: Comparable 目標價 | B36: =B34*B35 -> 528.68023 | E36: 同業中位數 × 前瞻 EPS
A38: 0.3 結論
A39: 項目 | B39: 數值 | E39: 說明
A40: 目標價（DCF 與 Comparable 加權） | B40: =tp_w_dcf*B24+(1-tp_w_dcf)*tp_comp_adj -> 319.13716 | E40: tp_w_dcf × DCF＋（1 − tp_w_dcf）× Comparable；tp_w_dcf 見 In 頁
A41: Comparable 目標價（市場主流同業法） | B41: =B36 -> 528.68023
A42: 市場共識目標價 | B42: =cons_tp -> 314.25 | E42: stockanalysis（S&P Global）：12 位分析師平均 314.25（頁面時間 2026-10-22）
A43: 上檔空間：加權目標價 | B43: =B40/px-1 -> 0.24906912 | E43: 現價＝In 頁 px（2026-10-22 收盤）
A44: 上檔空間：Comparable 目標價 | B44: =B41/px-1 -> 1.0691985
A45: 與市場共識目標價的差距：EPS 因素 | B45: =B35/cons_feps-1 -> 0.67405385 | E45: 本模型前瞻 EPS ÷ 共識前瞻 EPS − 1；共識前瞻 EPS＝現價 ÷ 前瞻 P/E（In 頁 cons_feps；期間為現在起算 12 個月，與本模型不同）
A46: 與市場共識目標價的差距：倍數因素 | B46: =(cons_tp/cons_feps)/B34-1 -> -0.0049345608 | E46: ="共識目標價隱含 "&TEXT(cons_tp/cons_feps,"0.0")&"x，同業中位數 "&TEXT(B34,"0.0")&"x" -> 共識目標價隱含 24.2x，同業中位數 24.4x
A47: 價格帶（DCF 不如預期～順利） | B47: =TEXT(D23,"0.00")&"～"&TEXT(B23,"0.00") -> 120.66～530.39 | E47: C 情境價值～A 情境價值（推到 12 個月後）
A48: 歷史倍數檢查：現價隱含 P/E 的十年分位（A／B／C） | B48: =IF(px/B9<MIN($B$90:$B$99),0,IF(px/B9>MAX($B$90:$B$99),1,PERCENTRANK($B$90:$B$99,px/B9))) -> 0 | C48: =IF(px/C9<MIN($B$90:$B$99),0,IF(px/C9>MAX($B$90:$B$99),1,PERCENTRANK($B$90:$B$99,px/C9))) -> 0.524 | D48: =IF(px/D9<MIN($B$90:$B$99),0,IF(px/D9>MAX($B$90:$B$99),1,PERCENTRANK($B$90:$B$99,px/D9))) -> 0.712 | E48: 現價 ÷ 各情境 FY2028 EPS 在 2016–2025 年底 P/E（第 6 節自算）的分位；只作檢查，不進目標價
A49: 目標價方法 | B49: DCF：股東現金流＝歸母 EPS ×（1 − g／ROE），r＝10%、g＝4%、ROE 為近三年平均約 16%（再投資率約 25%），FY2027–32 明確期＋永續；光寶 2026 年資本支出約 180 億元（約營收的 8%，含德州廠），本模型未建資本支出與折舊，未改用淨利＋折舊－資本支出，擴產期現金流可能偏高估。Comparable：台達電、Vertiv、Eaton、Flex 前瞻 P/E 中位數（不放 A 股）；台達電與 Vertiv 的 AI 占比與市占較高、歷來倍數高於光寶，光寶十年 P/E 中位數約 12x，Comparable 可能偏高估。情境對應：A＝順利（顆數基準、份額與 AI 毛利率高值）、B＝平平（顆數 ×0.8／0.85、基準）、C＝不如預期（顆數 ×0.6、低值）
A51: 1. 價格與市場隱含倍數
A52: 項目 | B52: A | C52: B | D52: C | E52: 說明
A53: 現價（2026-10-22 收盤） | B53: =px -> 255.5
A54: 現價 ÷ FY2026 EPS（錨點） | B54: =px/PL!D18 -> 23.343435 | C54: =px/PL!D35 -> 23.343435 | D54: =px/PL!D52 -> 23.343435 | E54: FY2026 三情境相同（錨點）
A55: 現價 ÷ FY2027 EPS（模型） | B55: =px/PL!E18 -> 12.379521 | C55: =px/PL!E35 -> 13.640699 | D55: =px/PL!E52 -> 15.686636 | E55: FY2027 三情境差異只來自份額相對值、AI 毛利率額外改善（顆數係數從 CY2028 開始）
A56: 現價 ÷ FY2028 EPS（模型） | B56: =px/PL!F18 -> 8.4568328 | C56: =px/PL!F35 -> 12.175117 | D56: =px/PL!F52 -> 18.685433
A57: 現價 ÷ FY2029 EPS（模型） | B57: =px/PL!G18 -> 6.8021547 | C57: =px/PL!G35 -> 9.9509998 | D57: =px/PL!G52 -> 17.256826
A58: 未來 12 月 EPS（模型 B）≈ 0.2 × FY2026＋0.8 × FY2027 | B58: =0.2*PL!D35+0.8*PL!E35 -> 17.173622
A59: 現價 ÷ 未來 12 月 EPS（模型 B） | B59: =px/B58 -> 14.877467
A60: 近 12 月 P/E（stockanalysis，10-22） | B60: =pe_ttm -> 30.09
A61: 前瞻 P/E（stockanalysis，10-22） | B61: =fpe -> 19.7
A63: 2. 循環位置（本模型營收最高年；FY(t)＝CY(t)）
A64: 情境 | B64: 營收最高年（FY2026–FY2029） | C64: FY2027 判定 | D64: 規則倍數（P/E） | E64: 見頂年是否未知 | F64: 說明
A65: A | B65: =INDEX({2026,2027,2028,2029},MATCH(MAX(PL!D95:G95),PL!D95:G95,0)) -> 2029 | C65: =IF(B65=2029,"中段",IF(2027<B65,"中段",IF(2027=B65,"見頂","谷底"))) -> 中段 | D65: =IF(C65="見頂",pe_peak,IF(C65="谷底",pe_trough,pe_mid)) -> 12.12 | E65: =IF(B65=2029,"是：營收到觀測期末仍在增加","否") -> 是：營收到觀測期末仍在增加 | F65: tools/cycle_position.py excel_rule；營收最高年取代設備市場見頂年
A66: B | B66: =INDEX({2026,2027,2028,2029},MATCH(MAX(PL!D138:G138),PL!D138:G138,0)) -> 2029 | C66: =IF(B66=2029,"中段",IF(2027<B66,"中段",IF(2027=B66,"見頂","谷底"))) -> 中段 | D66: =IF(C66="見頂",pe_peak,IF(C66="谷底",pe_trough,pe_mid)) -> 12.12 | E66: =IF(B66=2029,"是：營收到觀測期末仍在增加","否") -> 是：營收到觀測期末仍在增加 | F66: 同上
A67: C | B67: =INDEX({2026,2027,2028,2029},MATCH(MAX(PL!D181:G181),PL!D181:G181,0)) -> 2027 | C67: =IF(B67=2029,"中段",IF(2027<B67,"中段",IF(2027=B67,"見頂","谷底"))) -> 見頂 | D67: =IF(C67="見頂",pe_peak,IF(C67="谷底",pe_trough,pe_mid)) -> 11.63 | E67: =IF(B67=2029,"是：營收到觀測期末仍在增加","否") -> 否 | F67: 同上
A69: 3. 規則值隱含股價（新台幣；約 FY2027 年底，未折現）＝ FY2027 EPS × 規則倍數（參考，不是目標價）
A70: 情境 | B70: FY2027 EPS | C70: （同左） | D70: 規則倍數 | E70: 隱含股價 | F70: 相對現價 | G70: 現價 ÷ FY2027 EPS
A71: A | B71: =PL!E18 -> 20.638925 | C71: =B71 -> 20.638925 | D71: =D65 -> 12.12 | E71: =C71*D71 -> 250.14377 | F71: =E71/px-1 -> -0.020963733 | G71: =px/C71 -> 12.379521
A72: B | B72: =PL!E35 -> 18.730712 | C72: =B72 -> 18.730712 | D72: =D66 -> 12.12 | E72: =C72*D72 -> 227.01623 | F72: =E72/px-1 -> -0.11148246 | G72: =px/C72 -> 13.640699
A73: C | B73: =PL!E52 -> 16.28775 | C73: =B73 -> 16.28775 | D73: =D67 -> 11.63 | E73: =C73*D73 -> 189.42653 | F73: =E73/px-1 -> -0.25860457 | G73: =px/C73 -> 15.686636
A75: 4. What must be true：FY2027 年底價 ＝ 現價 ×（1＋報酬）所需的倍數（FY2028 EPS；約 2027 年底的價格看下一年 EPS）
A76: FY2027 年底價 ÷ 現價 | B76: 所需倍數（÷ FY2028 EPS，A） | C76: 所需倍數（÷ FY2028 EPS，B） | D76: 所需倍數（÷ FY2028 EPS，C） | E76: 對照：十年中位數
A77: 1 | B77: =px*A77/PL!F18 -> 8.4568328 | C77: =px*A77/PL!F35 -> 12.175117 | D77: =px*A77/PL!F52 -> 18.685433 | E77: =pe_mid -> 12.12
A78: 1.1 | B78: =px*A78/PL!F18 -> 9.3025161 | C78: =px*A78/PL!F35 -> 13.392629 | D78: =px*A78/PL!F52 -> 20.553977 | E78: =pe_mid -> 12.12
A79: 1.21 | B79: =px*A79/PL!F18 -> 10.232768 | C79: =px*A79/PL!F35 -> 14.731892 | D79: =px*A79/PL!F52 -> 22.609374 | E79: =pe_mid -> 12.12
A80: 1.5 | B80: =px*A80/PL!F18 -> 12.685249 | C80: =px*A80/PL!F35 -> 18.262676 | D80: =px*A80/PL!F52 -> 28.02815 | E80: =pe_mid -> 12.12
A81: 2 | B81: =px*A81/PL!F18 -> 16.913666 | C81: =px*A81/PL!F35 -> 24.350234 | D81: =px*A81/PL!F52 -> 37.370867 | E81: =pe_mid -> 12.12
A82: 讀法：1.00＝價格不變、1.21＝一年約 21%。所需倍數低於歷史中位數時，現價相對便宜；倍數是否合理，另看前瞻 P/E 歷史（Bloomberg）。本版未做先驗，無 Andy 合理 P/E 對照。
A85: 6. 十年倍數與規則值（2016–2025 年底；見頂年 25 分位、中段中位數、谷底 75 分位）
A86: 規則（Andy 2026-10-13）：合理倍數＝2016–2025 年底 P/E 依循環位置取分位。採用自算（10 年）；HiStock 只有 2021–2025，與自算同量級，只作核對；companiesmarketcap 光寶頁無法取得（網站錯誤）。2016–2022 年光寶為低成長消費電子與電源零組件公司（約 10–12x，2017 年 EPS 1.13 含一次性損失使 P/E 偏高），AI 前後倍數口徑不同，規則值可能低估 AI 期的合理倍數。
A88: P/E：十年歷史倍數
A89: 年底 | B89: 自算（digrin 12 月未調整價格 ÷ 年度 EPS） | C89: HiStock（12 月 P/E） | D89: 標記／說明
A90: 2016 | B90: =48.6/4.05 -> 12 | D90: 自算（digrin 12 月未調整價格 ÷ 年度 EPS）：Derived（EPS：wearn 2016–2025；10 年）；HiStock（12 月 P/E）：Interested-party（資料商；只有 2021–2025，只作核對，不採用）
A91: 2017 | B91: =40.6/1.13 -> 35.929204
A92: 2018 | B92: =40.6/3.42 -> 11.871345
A93: 2019 | B93: =49.35/4.03 -> 12.245658
A94: 2020 | B94: =49.8/4.31 -> 11.554524
A95: 2021 | B95: =63.8/6.01 -> 10.615641 | C95: 10.89
A96: 2022 | B96: =63.8/6.19 -> 10.306947 | C96: 11.39
A97: 2023 | B97: =117/6.36 -> 18.396226 | C97: 18.03
A98: 2024 | B98: =99.5/5.21 -> 19.097889 | C98: 18.53
A99: 2025 | B99: =163.5/6.64 -> 24.623494 | C99: 25.95
A100: 25 分位（各來源） | B100: =PERCENTILE(B90:B99,0.25) -> 11.63373 | C100: =PERCENTILE(C90:C99,0.25) -> 11.39
A101: 中位數（各來源） | B101: =MEDIAN(B90:B99) -> 12.122829 | C101: =MEDIAN(C90:C99) -> 18.03
A102: 75 分位（各來源） | B102: =PERCENTILE(B90:B99,0.75) -> 18.922473 | C102: =PERCENTILE(C90:C99,0.75) -> 18.53
A103: 最小（各來源） | B103: =MIN(B90:B99) -> 10.306947 | C103: =MIN(C90:C99) -> 10.89
A104: 最大（各來源） | B104: =MAX(B90:B99) -> 35.929204 | C104: =MAX(C90:C99) -> 25.95
A105: 採用 25 分位（P/E） | B105: =ROUND(AVERAGE(B100),2) -> 11.63
A106: 採用 中位數（P/E） | B106: =ROUND(AVERAGE(B101),2) -> 12.12
A107: 採用 75 分位（P/E） | B107: =ROUND(AVERAGE(B102),2) -> 18.92
A108: 採用 最小（P/E） | B108: =ROUND(MIN(B103),2) -> 10.31
A109: 採用 最大（P/E） | B109: =ROUND(MAX(B104),2) -> 35.93
A111: P/E：規則值
A112: 情形 | B112: 循環位置 | C112: 倍數 | D112: 基準 | E112: 每股基準 | F112: 隱含股價 | G112: 相對目前 | H112: 現價 ÷ 基準
...

Sheet Recon
A1: Recon — 本模型 vs 共識（MarketScreener、stockanalysis）、台達電模型的 AI 電源市場與份額、凱基份額。只作事後對照，不為對上數字而調參數。FY2027 起共識只有一個來源
A3: 項目 | B3: 對照值 | C3: 模型 A | D3: 差距 A | E3: 模型 B | F3: 差距 B | G3: 模型 C | H3: 差距 C | I3: 對照來源 | J3: 說明
A4: A. 共識（校準未使用）
A5: FY2026 營收 vs 共識（MarketScreener） | B5: =cons_rev26 -> 219.778 | C5: =PL!D95 -> 212.73147 | D5: =C5/B5-1 -> -0.032062035 | E5: =PL!D138 -> 212.73147 | F5: =E5/B5-1 -> -0.032062035 | G5: =PL!D181 -> 212.73147 | H5: =G5/B5-1 -> -0.032062035 | I5: MarketScreener（參考價 2026-10-22） | J5: stockanalysis 2,193 億
A6: FY2026 EPS vs 共識（MarketScreener） | B6: =cons_eps26 -> 10.81 | C6: =PL!D113 -> 10.945261 | D6: =C6/B6-1 -> 0.012512619 | E6: =PL!D156 -> 10.945261 | F6: =E6/B6-1 -> 0.012512619 | G6: =PL!D199 -> 10.945261 | H6: =G6/B6-1 -> 0.012512619 | I6: MarketScreener | J6: stockanalysis 10.81（11 家）；3Q26 財報（10-30 前後）前
A7: FY2027 營收 vs 共識（MarketScreener） | B7: =cons_rev27 -> 292.383 | C7: =PL!E95 -> 323.07652 | D7: =C7/B7-1 -> 0.1049771 | E7: =PL!E138 -> 307.42681 | F7: =E7/B7-1 -> 0.051452421 | G7: =PL!E181 -> 283.95226 | H7: =G7/B7-1 -> -0.028834594 | I7: MarketScreener
A8: FY2027 EPS vs 共識（MarketScreener） | B8: =cons_eps27 -> 14.99 | C8: =PL!E113 -> 20.638925 | D8: =C8/B8-1 -> 0.3768462 | E8: =PL!E156 -> 18.730712 | F8: =E8/B8-1 -> 0.24954718 | G8: =PL!E199 -> 16.28775 | H8: =G8/B8-1 -> 0.086574382 | I8: MarketScreener | J8: 差距說明見 README（部署 GW 2027 年約 1.8 倍）
A9: FY2028 營收 vs 共識（MarketScreener） | B9: =cons_rev28 -> 366.11 | C9: =PL!F95 -> 425.07653 | D9: =C9/B9-1 -> 0.16106232 | E9: =PL!F138 -> 335.14504 | F9: =E9/B9-1 -> -0.084578305 | G9: =PL!F181 -> 263.19984 | H9: =G9/B9-1 -> -0.28109081 | I9: MarketScreener
A10: FY2028 EPS vs 共識（MarketScreener） | B10: =cons_eps28 -> 20.74 | C10: =PL!F113 -> 30.212256 | D10: =C10/B10-1 -> 0.45671438 | E10: =PL!F156 -> 20.985424 | F10: =E10/B10-1 -> 0.011833383 | G10: =PL!F199 -> 13.673753 | H10: =G10/B10-1 -> -0.34070622 | I10: MarketScreener
A11: B. AI 電源市場與份額（與台達電模型一致性檢查）
A12: CY2026 AI 電源市場（US$B）vs 台達電模型（情境 A） | B12: =d_pmk26 -> 10.529792 | C12: =PL!D82 -> 10.529792 | D12: =C12/B12-1 -> 4.6629367e-15 | E12: =PL!D125 -> 10.529792 | F12: =E12/B12-1 -> 4.6629367e-15 | G12: =PL!D168 -> 10.529792 | H12: =G12/B12-1 -> 4.6629367e-15 | I12: delta/dist Units 頁（唯讀） | J12: 情境 A 應為 0%（同一部署 GW × 同一每 kW 內容）
A13: CY2027 AI 電源市場（US$B）vs 台達電模型（情境 A） | B13: =d_pmk27 -> 24.988059 | C13: =PL!E82 -> 24.988059 | D13: =C13/B13-1 -> 0 | E13: =PL!E125 -> 24.988059 | F13: =E13/B13-1 -> 0 | G13: =PL!E168 -> 24.988059 | H13: =G13/B13-1 -> 0 | I13: 同上
A14: CY2028 AI 電源市場（US$B）vs 台達電模型（情境 A） | B14: =d_pmk28 -> 35.898654 | C14: =PL!F82 -> 35.898654 | D14: =C14/B14-1 -> 0 | E14: =PL!F125 -> 28.718923 | F14: =E14/B14-1 -> -0.2 | G14: =PL!F168 -> 21.539192 | H14: =G14/B14-1 -> -0.4 | I14: 同上 | J14: 情境 B、C 低於台達電情境 A：顆數係數
A15: CY2026 光寶＋台達電 AI 電源有效份額合計 | C15: =PL!D86+d_sh26 -> 0.75981526 | E15: =PL!D129+d_sh26 -> 0.75981526 | G15: =PL!D172+d_sh26 -> 0.75981526 | I15: 本模型＋delta/dist Units 頁 | J15: 應低於 100%；其餘為 Flex、群電、康舒、Vertiv、麥格米特等
A16: CY2027 光寶＋台達電 AI 電源有效份額合計 | C16: =PL!E86+d_sh27 -> 0.74824599 | E16: =PL!E129+d_sh27 -> 0.73063166 | G16: =PL!E172+d_sh27 -> 0.70421016 | I16: 本模型＋delta/dist Units 頁 | J16: —
A17: CY2028 光寶＋台達電 AI 電源有效份額合計 | C17: =PL!F86+d_sh28 -> 0.73667673 | E17: =PL!F129+d_sh28 -> 0.70144806 | G17: =PL!F172+d_sh28 -> 0.6662194 | I17: 本模型＋delta/dist Units 頁 | J17: —
A18: CY2029 光寶＋台達電 AI 電源有效份額合計 | C18: =PL!G86+d_sh29 -> 0.71630029 | E18: =PL!G129+d_sh29 -> 0.67226446 | G18: =PL!G172+d_sh29 -> 0.62822864 | I18: 本模型＋delta/dist Units 頁 | J18: —
A19: FY2026 台達電模型份額 vs 凱基台達電市占（中點） | B19: =kgi_dsh -> 0.625 | C19: =d_sh26 -> 0.58367194 | D19: =C19-B19 -> -0.041328061 | E19: =d_sh26 -> 0.58367194 | F19: =E19-B19 -> -0.041328061 | G19: =d_sh26 -> 0.58367194 | H19: =G19-B19 -> -0.041328061 | I19: 凱基 2025-09（Interested-party） | J19: 口徑不同：模型分母含 ASIC 機架、HVDC、BBU
A20: CY2027 光寶 AI 電源營收 ÷ 台達電 AI 電源營收 | C20: =PL!E86/d_sh27 -> 0.34943503 | E20: =PL!E129/d_sh27 -> 0.3176682 | G20: =PL!E172/d_sh27 -> 0.27001797 | I20: 本模型＋delta/dist | J20: 同一市場，等於份額比
A21: CY2027 每 GW 光寶 AI 相關營收（US$M） | C21: =PL!E99 -> 129.17177 | E21: =PL!E142 -> 117.42888 | G21: =PL!E185 -> 99.814546 | I21: — | J21: 台達電模型 CY2027 每 GW AI 營收（電源＋液冷）約 470
A22: C. 校準
A23: 其他營收毛利率（Derived） | C23: =PL!D101 -> 0.21698234 | E23: =PL!D144 -> 0.21698234 | G23: =PL!D187 -> 0.21698234 | I23: FY2026 錨點 | J23: AI 相關毛利率＝此值＋d_ai
A24: FY2027 毛利率 vs FY2026（百分點） | B24: =a26_gp/a26_rev -> 0.25418234 | C24: =PL!E104 -> 0.286251 | D24: =C24-B24 -> 0.032068664 | E24: =PL!E147 -> 0.2780689 | F24: =E24-B24 -> 0.02388656 | G24: =PL!E190 -> 0.2685138 | H24: =G24-B24 -> 0.014331461 | I24: 錨點 | J24: AI 占比上升使毛利率上升
A25: FY2027 營業利益率 vs 2Q26 實績 15.6%（百分點） | B25: =8.203/52.703 -> 0.15564579 | C25: =PL!E108 -> 0.17988593 | D25: =C25-B25 -> 0.024240144 | E25: =PL!E151 -> 0.17051215 | F25: =E25-B25 -> 0.014866363 | G25: =PL!E194 -> 0.15892324 | H25: =G25-B25 -> 0.0032774545 | I25: stockanalysis 2Q26
A26: 4Q26 EPS（模型） | C26: =Q!E15 -> 3.1135873 | E26: =Q!E15 -> 3.1135873 | G26: =Q!E15 -> 3.1135873 | I26: — | J26: 3Q26 財報 10-30 前後公布
A27: D. 預留
A28: R4 產業部署路徑（markets/deploy_path/，尚未建立）：上線後以部署路徑取代「AI IT 資本支出 ÷ 每 GW IT 資本支出」 | J28: 預留列：本版無數值
A29: E. 目標價對帳（模型欄為情境加權值，只填 A 欄）
A30: 12 個月後的前瞻 EPS（情境加權）vs 共識前瞻 EPS | B30: =cons_feps -> 12.969543 | C30: =Val!B35 -> 21.711714 | D30: =C30/B30-1 -> 0.67405385 | I30: stockanalysis 前瞻 P/E（10-22） | J30: 共識只作對帳，不作校準
A31: 目標價（DCF 與 Comparable 加權）vs 市場共識目標價 | B31: =cons_tp -> 314.25 | C31: =Val!B40 -> 319.13716 | D31: =C31/B31-1 -> 0.015551825 | I31: stockanalysis（S&P Global）12 位分析師 | J31: 共識只作對帳，不作校準
A32: Comparable 目標價 vs 市場共識目標價 | B32: =cons_tp -> 314.25 | C32: =Val!B36 -> 528.68023 | D32: =C32/B32-1 -> 0.68235554 | I32: 同上 | J32: 共識只作對帳，不作校準
A33: F. 營收分部（v0.2：官方三大事業群；共識的分部預估：未找到）
A34: FY2026 雲端及物聯網年增 vs 公司「雲端運算全年年增超過 70%」 | B34: 0.7 | C34: =PL!D91/PL!C91-1 -> 0.55179331 | D34: =C34-B34 -> -0.14820669 | E34: =PL!D134/PL!C134-1 -> 0.55179331 | F34: =E34-B34 -> -0.14820669 | G34: =PL!D177/PL!C177-1 -> 0.55179331 | H34: =G34-B34 -> -0.14820669 | I34: 富果 2026-07-31（公司法說，Interested-party） | J34: 口徑不同：公司說的是雲端運算（雲端及物聯網的一部分）；FY2026 雲端及物聯網年增由錨點推得
A35: 2Q26 雲端及物聯網營業利益率（實績） | B35: =6.9/28.9 -> 0.23875433 | I35: Investing.com 2026-07-31（Lite-On Q2 2026 slides 摘要） | J35: 營業利益 69 億、季增 102%
A36: 2Q26 光電營業利益率（實績） | B36: =0.729/8 -> 0.091125 | I36: Investing.com 2026-07-31（Lite-On Q2 2026 slides 摘要） | J36: 營業利益 7.29 億
A37: 2Q26 資訊及消費性電子營業利益率（實績） | B37: =1.4/15.8 -> 0.088607595 | I37: Investing.com 2026-07-31（Lite-On Q2 2026 slides 摘要） | J37: 營業利益 14 億
A38: 2Q26 三事業群營業利益合計 − 合併營業利益（未分攤，NT$B） | B38: =6.9+0.729+1.4-8.203 -> 0.826 | I38: Investing.com 2026-07-31（Lite-On Q2 2026 slides 摘要） | J38: 負向未分攤費用；本模型營業利益仍由合併毛利率與費用推導，分部利益只作對帳

Sheet Sens
A1: Sens — 一次動一個輸入（情境 B＝基準輸入；有效份額、其他營收毛利率在每個案例內依 FY2026 錨點重算，FY2026 恆等於錨點）：對 FY2027、FY2028 的營收、AI 相關營收、毛利率與 EPS 的影響。每個案例是一個完整推導區塊（本頁下方）
A3: 案例 | B3: 設定 | C3: FY2027 營收 | D3: FY2027 AI 相關 | E3: FY2027 毛利率 | F3: FY2027 EPS | G3: FY2027 EPS 相對基準 | H3: FY2028 營收 | I3: FY2028 AI 相關 | J3: FY2028 毛利率 | K3: FY2028 EPS | L3: FY2028 EPS 相對基準
A4: 基準（情境 B） | B4: PL 區塊 B | C4: =PL!E138 -> 307.42681 | D4: =PL!E131 -> 156.49705 | E4: =PL!E147 -> 0.2780689 | F4: =PL!E156 -> 18.730712 | G4: =F4/F$4-1 -> 0 | H4: =PL!F138 -> 335.14504 | I4: =PL!F131 -> 179.86298 | J4: =PL!F147 -> 0.28138299 | K4: =PL!F156 -> 20.985424 | L4: =K4/K$4-1 -> 0
A5: 份額流失（低） | B5: 份額相對值 2027 0.85、2028 0.80、2029 0.75（台達電、Flex、中國廠競爭） | C5: =E70 -> 283.95226 | D5: =E63 -> 133.0225 | E5: =E79 -> 0.27319848 | F5: =E88 -> 16.733316 | G5: =F5/F$4-1 -> -0.10663749 | H5: =F70 -> 299.17244 | I5: =F63 -> 143.89039 | J5: =F79 -> 0.2746977 | K5: =F88 -> 17.88525 | L5: =K5/K$4-1 -> -0.14772988
A6: 份額提升（高） | B6: 份額相對值 2027 1.10、2028 1.20、2029 1.25（新 CSP 客戶、800V 電源櫃） | C6: =E113 -> 323.07652 | D6: =E106 -> 172.14676 | E6: =E122 -> 0.28092264 | F6: =E131 -> 20.06231 | G6: =F6/F$4-1 -> 0.071091659 | H6: =F113 -> 371.11763 | I6: =F106 -> 215.83558 | J6: =F122 -> 0.28677226 | K6: =F131 -> 24.111856 | L6: =K6/K$4-1 -> 0.14898108
A7: 電源內容 低 | B7: 每 kW：2026 380、2027 500、2028–29 550（台達電模型低值） | C7: =E156 -> 305.36764 | D7: =E149 -> 154.43788 | E7: =E165 -> 0.27767163 | F7: =E174 -> 18.555502 | G7: =F7/F$4-1 -> -0.0093541656 | H7: =F156 -> 327.55794 | I7: =F149 -> 172.27588 | J7: =F165 -> 0.28009516 | K7: =F174 -> 20.324798 | L7: =K7/K$4-1 -> -0.031480225
A8: 電源內容 高 | B8: 每 kW：2026 520、2027 700、2028 800、2029 850（台達電模型高值） | C8: =E199 -> 308.93159 | D8: =E192 -> 158.00183 | E8: =E208 -> 0.27835586 | F8: =E217 -> 18.85875 | G8: =F8/F$4-1 -> 0.0068357364 | H8: =F199 -> 338.40048 | I8: =F192 -> 183.11842 | J8: =F208 -> 0.28191786 | K8: =F217 -> 21.267745 | L8: =K8/K$4-1 -> 0.013453189
A9: AI 部署 ×0.8 | B9: FY2027 起 AI IT 資本支出 ×0.8 | C9: =E242 -> 276.1274 | D9: =E235 -> 125.19764 | E9: =E251 -> 0.27139098 | F9: =E260 -> 16.067517 | G9: =F9/F$4-1 -> -0.14218332 | H9: =F242 -> 299.17244 | I9: =F235 -> 143.89039 | J9: =F251 -> 0.2746977 | K9: =F260 -> 17.897532 | L9: =K9/K$4-1 -> -0.14714462
A10: AI 部署 ×1.2 | B10: ×1.2 | C10: =E285 -> 338.72622 | D10: =E278 -> 187.79647 | E10: =E294 -> 0.28351269 | F10: =E303 -> 21.393907 | G10: =F10/F$4-1 -> 0.14218332 | H10: =F285 -> 371.11763 | I10: =F278 -> 215.83558 | J10: =F294 -> 0.28677226 | K10: =F303 -> 24.075514 | L10: =K10/K$4-1 -> 0.14724931
A11: AI 毛利率差距 8pt | B11: AI 相關毛利率只高 8 個百分點 | C11: =E328 -> 307.42681 | D11: =E321 -> 156.49705 | E11: =E337 -> 0.27010671 | F11: =E346 -> 17.910812 | G11: =F11/F$4-1 -> -0.043773058 | H11: =F328 -> 335.14504 | I11: =F321 -> 179.86298 | J11: =F337 -> 0.2723161 | K11: =F346 -> 19.967588 | L11: =K11/K$4-1 -> -0.048502053
A12: AI 毛利率差距 16pt | B12: 高 16 個百分點 | C12: =E371 -> 307.42681 | D12: =E364 -> 156.49705 | E12: =E380 -> 0.28603108 | F12: =E389 -> 19.550613 | G12: =F12/F$4-1 -> 0.043773058 | H12: =F371 -> 335.14504 | I12: =F364 -> 179.86298 | J12: =F380 -> 0.29044987 | K12: =F389 -> 22.003261 | L12: =K12/K$4-1 -> 0.048502053
A13: AI 毛利率額外改善 低 | B13: 2027 −1pt、2028 −1.5pt、2029 −2pt | C13: =E414 -> 307.42681 | D13: =E407 -> 156.49705 | E13: =E423 -> 0.27297835 | F13: =E432 -> 18.206517 | G13: =F13/F$4-1 -> -0.027985879 | H13: =F414 -> 335.14504 | I13: =F407 -> 179.86298 | J13: =F423 -> 0.2733329 | K13: =F432 -> 20.081733 | L13: =K13/K$4-1 -> -0.04306281
A14: AI 毛利率額外改善 高 | B14: 2027 +1pt、2028 +1.5pt、2029 +2pt | C14: =E457 -> 307.42681 | D14: =E450 -> 156.49705 | E14: =E466 -> 0.28315944 | F14: =E475 -> 19.254908 | G14: =F14/F$4-1 -> 0.027985879 | H14: =F457 -> 335.14504 | I14: =F450 -> 179.86298 | J14: =F466 -> 0.28943307 | K14: =F475 -> 21.889116 | L14: =K14/K$4-1 -> 0.04306281
A15: 非 AI 分部成長 低 | B15: 雲端非 AI、光電 0%；資訊及消費性電子 −5%（2027–29） | C15: =E500 -> 300.08758 | D15: =E493 -> 156.49705 | E15: =E509 -> 0.27956289 | F15: =E518 -> 18.401232 | G15: =F15/F$4-1 -> -0.017590394 | H15: =F500 -> 320.41902 | I15: =F493 -> 179.86298 | J15: =F509 -> 0.28434275 | K15: =F518 -> 20.302494 | L15: =K15/K$4-1 -> -0.032543094
A16: 非 AI 分部成長 高 | B16: 雲端非 AI、光電 +10%；資訊及消費性電子 +5% | C16: =E543 -> 314.76605 | D16: =E536 -> 156.49705 | E16: =E552 -> 0.27664457 | F16: =E561 -> 19.060193 | G16: =F16/F$4-1 -> 0.017590394 | H16: =F543 -> 350.60497 | I16: =F536 -> 179.86298 | J16: =F552 -> 0.27854324 | K16: =F561 -> 21.705139 | L16: =K16/K$4-1 -> 0.034295951
A17: 營業費用率 +1pt | B17: 營業費用額外 +1% × 營收 | C17: =E586 -> 307.42681 | D17: =E579 -> 156.49705 | E17: =E595 -> 0.2780689 | F17: =E604 -> 17.700969 | G17: =F17/F$4-1 -> -0.054976175 | H17: =F586 -> 335.14504 | I17: =F579 -> 179.86298 | J17: =F595 -> 0.28138299 | K17: =F604 -> 19.862838 | L17: =K17/K$4-1 -> -0.053493635
A18: 營業費用彈性 1.0 | B18: 基準 0.7 | C18: =E629 -> 307.42681 | D18: =E622 -> 156.49705 | E18: =E638 -> 0.2780689 | F18: =E647 -> 17.603038 | G18: =F18/F$4-1 -> -0.060204577 | H18: =F629 -> 335.14504 | I18: =F622 -> 179.86298 | J18: =F638 -> 0.28138299 | K18: =F647 -> 19.456497 | L18: =K18/K$4-1 -> -0.072856617
A19: 淨利 ÷ 稅前 0.73 | B19: 基準 0.76 | C19: =E672 -> 307.42681 | D19: =E665 -> 156.49705 | E19: =E681 -> 0.2780689 | F19: =E690 -> 17.991342 | G19: =F19/F$4-1 -> -0.039473684 | H19: =F672 -> 335.14504 | I19: =F665 -> 179.86298 | J19: =F681 -> 0.28138299 | K19: =F690 -> 20.157052 | L19: =K19/K$4-1 -> -0.039473684
A20: 淨利 ÷ 稅前 0.78 | C20: =E715 -> 307.42681 | D20: =E708 -> 156.49705 | E20: =E724 -> 0.2780689 | F20: =E733 -> 19.223626 | G20: =F20/F$4-1 -> 0.026315789 | H20: =F715 -> 335.14504 | I20: =F708 -> 179.86298 | J20: =F724 -> 0.28138299 | K20: =F733 -> 21.537672 | L20: =K20/K$4-1 -> 0.026315789
A21: 情境 A（全部） | B21: 顆數係數 A＋份額相對值、AI 毛利率額外改善高值 | C21: =PL!E95 -> 323.07652 | D21: =PL!E88 -> 172.14676 | E21: =PL!E104 -> 0.286251 | F21: =PL!E113 -> 20.638925 | G21: =F21/F$4-1 -> 0.10187613 | H21: =PL!F95 -> 425.07653 | I21: =PL!F88 -> 269.79447 | J21: =PL!F104 -> 0.30266633 | K21: =PL!F113 -> 30.212256 | L21: =K21/K$4-1 -> 0.43967812
A22: 情境 C（全部） | B22: 顆數係數 C＋份額相對值、AI 毛利率額外改善低值 | C22: =PL!E181 -> 283.95226 | D22: =PL!E174 -> 133.0225 | E22: =PL!E190 -> 0.2685138 | F22: =PL!E199 -> 16.28775 | G22: =F22/F$4-1 -> -0.13042548 | H22: =PL!F181 -> 263.19984 | I22: =PL!F174 -> 107.91779 | J22: =PL!F190 -> 0.26003467 | K22: =PL!F199 -> 13.673753 | L22: =K22/K$4-1 -> -0.34841665
A24: 讀法：基準為情境 B（顆數係數 B 從 CY2028 起）。每個案例的 FY2026 有效份額與其他營收毛利率依該案例重算，所以 FY2026 恆等於錨點；「電源內容」案例的 FY2026 份額會反向調整（內容低 → 份額高），所以只影響 FY2027 起的成長路徑。AI 相關中非電源占比（x_np）只影響份額，不影響營收與 EPS，未列入。
A26: 目標價參數（只改 DCF 參數；PL 收斂法的 fade_g 不隨 tp_g 變動）
A27: 案例 | B27: 設定 | C27: DCF 目標價 | D27: Comparable 目標價（相對倍數調整後） | E27: 加權目標價 | F27: 相對基準
A28: 基準 | B28: r 10%、g 4%、DCF 權重 0.5 | C28: =(tp_wA*MAX(0,Val!B8*(1-MIN(tp_g/tp_roe,0.8))/(1+tp_r)^1+Val!B9*(1-MIN(tp_g/tp_roe,0.8))/(1+tp_r)^2+Val!B10*(1-MIN(tp_g/tp_roe,0.8))/(1+tp_r)^3+Val!B11*(1-MIN(tp_g/tp_roe,0.8))/(1+tp_r)^4+Val!B12*(1-MIN(tp_g/tp_roe,0.8))/(1+tp_r)^5+Val!B13*(1-MIN(tp_g/tp_roe,0.8))/(1+tp_r)^6+Val!B13*(1-MIN(tp_g/tp_roe,0.8))*(1+tp_g)/(tp_r-tp_g)/(1+tp_r)^6)+tp_wB*MAX(0,Val!C8*(1-MIN(tp_g/tp_roe,0.8))/(1+tp_r)^1+Val!C9*(1-MIN(tp_g/tp_roe,0.8))/(1+tp_r)^2+Val!C10*(1-MIN(tp_g/tp_roe,0.8))/(1+tp_r)^3+Val!C11*(1-MIN(tp_g/tp_roe,0.8))/(1+tp_r)^4+Val!C12*(1-MIN(tp_g/tp_roe,0.8))/(1+tp_r)^5+Val!C13*(1-MIN(tp_g/tp_roe,0.8))/(1+tp_r)^6+Val!C13*(1-MIN(tp_g/tp_roe,0.8))*(1+tp_g)/(tp_r-tp_g)/(1+tp_r)^6)+tp_wC*MAX(0,Val!D8*(1-MIN(tp_g/tp_roe,0.8))/(1+tp_r)^1+Val!D9*(1-MIN(tp_g/tp_roe,0.8))/(1+tp_r)^2+Val!D10*(1-MIN(tp_g/tp_roe,0.8))/(1+tp_r)^3+Val!D11*(1-MIN(tp_g/tp_roe,0.8))/(1+tp_r)^4+Val!D12*(1-MIN(tp_g/tp_roe,0.8))/(1+tp_r)^5+Val!D13*(1-MIN(tp_g/tp_roe,0.8))/(1+tp_r)^6+Val!D13*(1-MIN(tp_g/tp_roe,0.8))*(1+tp_g)/(tp_r-tp_g)/(1+tp_r)^6))*(1+tp_r) -> 318.42293 | D28: =tp_comp_adj -> 319.85139 | E28: =tp_w_dcf*C28+(1-tp_w_dcf)*D28 -> 319.13716 | F28: =E28/E$28-1 -> 0
A29: 折現率 +1pt | B29: r 11% | C29: =(tp_wA*MAX(0,Val!B8*(1-MIN(tp_g/tp_roe,0.8))/(1+(tp_r+0.01))^1+Val!B9*(1-MIN(tp_g/tp_roe,0.8))/(1+(tp_r+0.01))^2+Val!B10*(1-MIN(tp_g/tp_roe,0.8))/(1+(tp_r+0.01))^3+Val!B11*(1-MIN(tp_g/tp_roe,0.8))/(1+(tp_r+0.01))^4+Val!B12*(1-MIN(tp_g/tp_roe,0.8))/(1+(tp_r+0.01))^5+Val!B13*(1-MIN(tp_g/tp_roe,0.8))/(1+(tp_r+0.01))^6+Val!B13*(1-MIN(tp_g/tp_roe,0.8))*(1+tp_g)/((tp_r+0.01)-tp_g)/(1+(tp_r+0.01))^6)+tp_wB*MAX(0,Val!C8*(1-MIN(tp_g/tp_roe,0.8))/(1+(tp_r+0.01))^1+Val!C9*(1-MIN(tp_g/tp_roe,0.8))/(1+(tp_r+0.01))^2+Val!C10*(1-MIN(tp_g/tp_roe,0.8))/(1+(tp_r+0.01))^3+Val!C11*(1-MIN(tp_g/tp_roe,0.8))/(1+(tp_r+0.01))^4+Val!C12*(1-MIN(tp_g/tp_roe,0.8))/(1+(tp_r+0.01))^5+Val!C13*(1-MIN(tp_g/tp_roe,0.8))/(1+(tp_r+0.01))^6+Val!C13*(1-MIN(tp_g/tp_roe,0.8))*(1+tp_g)/((tp_r+0.01)-tp_g)/(1+(tp_r+0.01))^6)+tp_wC*MAX(0,Val!D8*(1-MIN(tp_g/tp_roe,0.8))/(1+(tp_r+0.01))^1+Val!D9*(1-MIN(tp_g/tp_roe,0.8))/(1+(tp_r+0.01))^2+Val!D10*(1-MIN(tp_g/tp_roe,0.8))/(1+(tp_r+0.01))^3+Val!D11*(1-MIN(tp_g/tp_roe,0.8))/(1+(tp_r+0.01))^4+Val!D12*(1-MIN(tp_g/tp_roe,0.8))/(1+(tp_r+0.01))^5+Val!D13*(1-MIN(tp_g/tp_roe,0.8))/(1+(tp_r+0.01))^6+Val!D13*(1-MIN(tp_g/tp_roe,0.8))*(1+tp_g)/((tp_r+0.01)-tp_g)/(1+(tp_r+0.01))^6))*(1+(tp_r+0.01)) -> 275.16121 | D29: =tp_comp_adj -> 319.85139 | E29: =tp_w_dcf*C29+(1-tp_w_dcf)*D29 -> 297.5063 | F29: =E29/E$28-1 -> -0.0677792
A30: 折現率 −1pt | B30: r 9% | C30: =(tp_wA*MAX(0,Val!B8*(1-MIN(tp_g/tp_roe,0.8))/(1+(tp_r-0.01))^1+Val!B9*(1-MIN(tp_g/tp_roe,0.8))/(1+(tp_r-0.01))^2+Val!B10*(1-MIN(tp_g/tp_roe,0.8))/(1+(tp_r-0.01))^3+Val!B11*(1-MIN(tp_g/tp_roe,0.8))/(1+(tp_r-0.01))^4+Val!B12*(1-MIN(tp_g/tp_roe,0.8))/(1+(tp_r-0.01))^5+Val!B13*(1-MIN(tp_g/tp_roe,0.8))/(1+(tp_r-0.01))^6+Val!B13*(1-MIN(tp_g/tp_roe,0.8))*(1+tp_g)/((tp_r-0.01)-tp_g)/(1+(tp_r-0.01))^6)+tp_wB*MAX(0,Val!C8*(1-MIN(tp_g/tp_roe,0.8))/(1+(tp_r-0.01))^1+Val!C9*(1-MIN(tp_g/tp_roe,0.8))/(1+(tp_r-0.01))^2+Val!C10*(1-MIN(tp_g/tp_roe,0.8))/(1+(tp_r-0.01))^3+Val!C11*(1-MIN(tp_g/tp_roe,0.8))/(1+(tp_r-0.01))^4+Val!C12*(1-MIN(tp_g/tp_roe,0.8))/(1+(tp_r-0.01))^5+Val!C13*(1-MIN(tp_g/tp_roe,0.8))/(1+(tp_r-0.01))^6+Val!C13*(1-MIN(tp_g/tp_roe,0.8))*(1+tp_g)/((tp_r-0.01)-tp_g)/(1+(tp_r-0.01))^6)+tp_wC*MAX(0,Val!D8*(1-MIN(tp_g/tp_roe,0.8))/(1+(tp_r-0.01))^1+Val!D9*(1-MIN(tp_g/tp_roe,0.8))/(1+(tp_r-0.01))^2+Val!D10*(1-MIN(tp_g/tp_roe,0.8))/(1+(tp_r-0.01))^3+Val!D11*(1-MIN(tp_g/tp_roe,0.8))/(1+(tp_r-0.01))^4+Val!D12*(1-MIN(tp_g/tp_roe,0.8))/(1+(tp_r-0.01))^5+Val!D13*(1-MIN(tp_g/tp_roe,0.8))/(1+(tp_r-0.01))^6+Val!D13*(1-MIN(tp_g/tp_roe,0.8))*(1+tp_g)/((tp_r-0.01)-tp_g)/(1+(tp_r-0.01))^6))*(1+(tp_r-0.01)) -> 378.96241 | D30: =tp_comp_adj -> 319.85139 | E30: =tp_w_dcf*C30+(1-tp_w_dcf)*D30 -> 349.4069 | F30: =E30/E$28-1 -> 0.094848678
A31: 長期成長 +1pt | B31: g 5% | C31: =(tp_wA*MAX(0,Val!B8*(1-MIN((tp_g+0.01)/tp_roe,0.8))/(1+tp_r)^1+Val!B9*(1-MIN((tp_g+0.01)/tp_roe,0.8))/(1+tp_r)^2+Val!B10*(1-MIN((tp_g+0.01)/tp_roe,0.8))/(1+tp_r)^3+Val!B11*(1-MIN((tp_g+0.01)/tp_roe,0.8))/(1+tp_r)^4+Val!B12*(1-MIN((tp_g+0.01)/tp_roe,0.8))/(1+tp_r)^5+Val!B13*(1-MIN((tp_g+0.01)/tp_roe,0.8))/(1+tp_r)^6+Val!B13*(1-MIN((tp_g+0.01)/tp_roe,0.8))*(1+(tp_g+0.01))/(tp_r-(tp_g+0.01))/(1+tp_r)^6)+tp_wB*MAX(0,Val!C8*(1-MIN((tp_g+0.01)/tp_roe,0.8))/(1+tp_r)^1+Val!C9*(1-MIN((tp_g+0.01)/tp_roe,0.8))/(1+tp_r)^2+Val!C10*(1-MIN((tp_g+0.01)/tp_roe,0.8))/(1+tp_r)^3+Val!C11*(1-MIN((tp_g+0.01)/tp_roe,0.8))/(1+tp_r)^4+Val!C12*(1-MIN((tp_g+0.01)/tp_roe,0.8))/(1+tp_r)^5+Val!C13*(1-MIN((tp_g+0.01)/tp_roe,0.8))/(1+tp_r)^6+Val!C13*(1-MIN((tp_g+0.01)/tp_roe,0.8))*(1+(tp_g+0.01))/(tp_r-(tp_g+0.01))/(1+tp_r)^6)+tp_wC*MAX(0,Val!D8*(1-MIN((tp_g+0.01)/tp_roe,0.8))/(1+tp_r)^1+Val!D9*(1-MIN((tp_g+0.01)/tp_roe,0.8))/(1+tp_r)^2+Val!D10*(1-MIN((tp_g+0.01)/tp_roe,0.8))/(1+tp_r)^3+Val!D11*(1-MIN((tp_g+0.01)/tp_roe,0.8))/(1+tp_r)^4+Val!D12*(1-MIN((tp_g+0.01)/tp_roe,0.8))/(1+tp_r)^5+Val!D13*(1-MIN((tp_g+0.01)/tp_roe,0.8))/(1+tp_r)^6+Val!D13*(1-MIN((tp_g+0.01)/tp_roe,0.8))*(1+(tp_g+0.01))/(tp_r-(tp_g+0.01))/(1+tp_r)^6))*(1+tp_r) -> 335.98424 | D31: =tp_comp_adj -> 319.85139 | E31: =tp_w_dcf*C31+(1-tp_w_dcf)*D31 -> 327.91781 | F31: =E31/E$28-1 -> 0.027513723
A32: 長期成長 −1pt | B32: g 3% | C32: =(tp_wA*MAX(0,Val!B8*(1-MIN((tp_g-0.01)/tp_roe,0.8))/(1+tp_r)^1+Val!B9*(1-MIN((tp_g-0.01)/tp_roe,0.8))/(1+tp_r)^2+Val!B10*(1-MIN((tp_g-0.01)/tp_roe,0.8))/(1+tp_r)^3+Val!B11*(1-MIN((tp_g-0.01)/tp_roe,0.8))/(1+tp_r)^4+Val!B12*(1-MIN((tp_g-0.01)/tp_roe,0.8))/(1+tp_r)^5+Val!B13*(1-MIN((tp_g-0.01)/tp_roe,0.8))/(1+tp_r)^6+Val!B13*(1-MIN((tp_g-0.01)/tp_roe,0.8))*(1+(tp_g-0.01))/(tp_r-(tp_g-0.01))/(1+tp_r)^6)+tp_wB*MAX(0,Val!C8*(1-MIN((tp_g-0.01)/tp_roe,0.8))/(1+tp_r)^1+Val!C9*(1-MIN((tp_g-0.01)/tp_roe,0.8))/(1+tp_r)^2+Val!C10*(1-MIN((tp_g-0.01)/tp_roe,0.8))/(1+tp_r)^3+Val!C11*(1-MIN((tp_g-0.01)/tp_roe,0.8))/(1+tp_r)^4+Val!C12*(1-MIN((tp_g-0.01)/tp_roe,0.8))/(1+tp_r)^5+Val!C13*(1-MIN((tp_g-0.01)/tp_roe,0.8))/(1+tp_r)^6+Val!C13*(1-MIN((tp_g-0.01)/tp_roe,0.8))*(1+(tp_g-0.01))/(tp_r-(tp_g-0.01))/(1+tp_r)^6)+tp_wC*MAX(0,Val!D8*(1-MIN((tp_g-0.01)/tp_roe,0.8))/(1+tp_r)^1+Val!D9*(1-MIN((tp_g-0.01)/tp_roe,0.8))/(1+tp_r)^2+Val!D10*(1-MIN((tp_g-0.01)/tp_roe,0.8))/(1+tp_r)^3+Val!D11*(1-MIN((tp_g-0.01)/tp_roe,0.8))/(1+tp_r)^4+Val!D12*(1-MIN((tp_g-0.01)/tp_roe,0.8))/(1+tp_r)^5+Val!D13*(1-MIN((tp_g-0.01)/tp_roe,0.8))/(1+tp_r)^6+Val!D13*(1-MIN((tp_g-0.01)/tp_roe,0.8))*(1+(tp_g-0.01))/(tp_r-(tp_g-0.01))/(1+tp_r)^6))*(1+tp_r) -> 307.72067 | D32: =tp_comp_adj -> 319.85139 | E32: =tp_w_dcf*C32+(1-tp_w_dcf)*D32 -> 313.78603 | F32: =E32/E$28-1 -> -0.016767498
A33: DCF 權重 0.3 | C33: =(tp_wA*MAX(0,Val!B8*(1-MIN(tp_g/tp_roe,0.8))/(1+tp_r)^1+Val!B9*(1-MIN(tp_g/tp_roe,0.8))/(1+tp_r)^2+Val!B10*(1-MIN(tp_g/tp_roe,0.8))/(1+tp_r)^3+Val!B11*(1-MIN(tp_g/tp_roe,0.8))/(1+tp_r)^4+Val!B12*(1-MIN(tp_g/tp_roe,0.8))/(1+tp_r)^5+Val!B13*(1-MIN(tp_g/tp_roe,0.8))/(1+tp_r)^6+Val!B13*(1-MIN(tp_g/tp_roe,0.8))*(1+tp_g)/(tp_r-tp_g)/(1+tp_r)^6)+tp_wB*MAX(0,Val!C8*(1-MIN(tp_g/tp_roe,0.8))/(1+tp_r)^1+Val!C9*(1-MIN(tp_g/tp_roe,0.8))/(1+tp_r)^2+Val!C10*(1-MIN(tp_g/tp_roe,0.8))/(1+tp_r)^3+Val!C11*(1-MIN(tp_g/tp_roe,0.8))/(1+tp_r)^4+Val!C12*(1-MIN(tp_g/tp_roe,0.8))/(1+tp_r)^5+Val!C13*(1-MIN(tp_g/tp_roe,0.8))/(1+tp_r)^6+Val!C13*(1-MIN(tp_g/tp_roe,0.8))*(1+tp_g)/(tp_r-tp_g)/(1+tp_r)^6)+tp_wC*MAX(0,Val!D8*(1-MIN(tp_g/tp_roe,0.8))/(1+tp_r)^1+Val!D9*(1-MIN(tp_g/tp_roe,0.8))/(1+tp_r)^2+Val!D10*(1-MIN(tp_g/tp_roe,0.8))/(1+tp_r)^3+Val!D11*(1-MIN(tp_g/tp_roe,0.8))/(1+tp_r)^4+Val!D12*(1-MIN(tp_g/tp_roe,0.8))/(1+tp_r)^5+Val!D13*(1-MIN(tp_g/tp_roe,0.8))/(1+tp_r)^6+Val!D13*(1-MIN(tp_g/tp_roe,0.8))*(1+tp_g)/(tp_r-tp_g)/(1+tp_r)^6))*(1+tp_r) -> 318.42293 | D33: =tp_comp_adj -> 319.85139 | E33: =0.3*C33+(1-0.3)*D33 -> 319.42285 | F33: =E33/E$28-1 -> 0.00089519771
A34: DCF 權重 0.7 | C34: =(tp_wA*MAX(0,Val!B8*(1-MIN(tp_g/tp_roe,0.8))/(1+tp_r)^1+Val!B9*(1-MIN(tp_g/tp_roe,0.8))/(1+tp_r)^2+Val!B10*(1-MIN(tp_g/tp_roe,0.8))/(1+tp_r)^3+Val!B11*(1-MIN(tp_g/tp_roe,0.8))/(1+tp_r)^4+Val!B12*(1-MIN(tp_g/tp_roe,0.8))/(1+tp_r)^5+Val!B13*(1-MIN(tp_g/tp_roe,0.8))/(1+tp_r)^6+Val!B13*(1-MIN(tp_g/tp_roe,0.8))*(1+tp_g)/(tp_r-tp_g)/(1+tp_r)^6)+tp_wB*MAX(0,Val!C8*(1-MIN(tp_g/tp_roe,0.8))/(1+tp_r)^1+Val!C9*(1-MIN(tp_g/tp_roe,0.8))/(1+tp_r)^2+Val!C10*(1-MIN(tp_g/tp_roe,0.8))/(1+tp_r)^3+Val!C11*(1-MIN(tp_g/tp_roe,0.8))/(1+tp_r)^4+Val!C12*(1-MIN(tp_g/tp_roe,0.8))/(1+tp_r)^5+Val!C13*(1-MIN(tp_g/tp_roe,0.8))/(1+tp_r)^6+Val!C13*(1-MIN(tp_g/tp_roe,0.8))*(1+tp_g)/(tp_r-tp_g)/(1+tp_r)^6)+tp_wC*MAX(0,Val!D8*(1-MIN(tp_g/tp_roe,0.8))/(1+tp_r)^1+Val!D9*(1-MIN(tp_g/tp_roe,0.8))/(1+tp_r)^2+Val!D10*(1-MIN(tp_g/tp_roe,0.8))/(1+tp_r)^3+Val!D11*(1-MIN(tp_g/tp_roe,0.8))/(1+tp_r)^4+Val!D12*(1-MIN(tp_g/tp_roe,0.8))/(1+tp_r)^5+Val!D13*(1-MIN(tp_g/tp_roe,0.8))/(1+tp_r)^6+Val!D13*(1-MIN(tp_g/tp_roe,0.8))*(1+tp_g)/(tp_r-tp_g)/(1+tp_r)^6))*(1+tp_r) -> 318.42293 | D34: =tp_comp_adj -> 319.85139 | E34: =0.7*C34+(1-0.7)*D34 -> 318.85147 | F34: =E34/E$28-1 -> -0.00089519771
A50: 案例區塊：份額流失（低）（情境 B）
A51: 項目 | B51: 單位 | C51: FY2025A | D51: FY2026（錨點） | E51: FY2027 | F51: FY2028 | G51: FY2029 | H51: FY2030（收斂） | I51: FY2031（收斂） | J51: FY2032（收斂） | K51: 說明
A52: A. AI 部署與 AI 電源市場（D 欄＝FY2026 校準年；每 kW 內容取自台達電模型）
A53: AI IT 資本支出 × 情境顆數係數 | B53: US$B | D53: =itc_26*1 -> 781.87292 | E53: =itc_27*1*1 -> 1565.35 | F53: =itc_28*um28_B*1 -> 1587.4111 | G53: =itc_29*um29_B*1 -> 1921.3317
A54: 每 GW IT 資本支出 | B54: US$B | D54: =itpg_gb*(1-vr26)+itpg_vr*vr26 -> 33.414032 | E54: =itpg_vr -> 37.586352 | F54: =itpg_vr -> 37.586352 | G54: =itpg_vr -> 37.586352
A55: 部署 GW（IT 電力） | B55: GW | D55: =D53/D54 -> 23.399538 | E55: =E53/E54 -> 41.646766 | F55: =F53/F54 -> 42.233711 | G55: =G53/G54 -> 51.117803
A56: AI 電源內容（台達電模型） | B56: US$/kW | D56: =pkw_26 -> 450 | E56: =pkw_27 -> 600 | F56: =pkw_28 -> 680 | G56: =pkw_29 -> 720
A57: AI 電源市場（美元） | B57: US$B | D57: =D55*D56/1000 -> 10.529792 | E57: =E55*E56/1000 -> 24.988059 | F57: =F55*F56/1000 -> 28.718923 | G57: =G55*G56/1000 -> 36.804818
A58: AI 電源市場（新台幣） | B58: NT$B | D58: =D57*fx -> 336.95335 | E58: =E57*fx -> 799.6179 | F58: =F57*fx -> 919.00554 | G58: =G57*fx -> 1177.7542
A59: 光寶有效份額（FY2026 校準）＝ AI 電源營收 ÷ 市場 | B59: % | D59: =a26_aip/D58 -> 0.17614332 | K59: Derived：分子為公司 AI 相關占比 × 營收 ×（1 − 非電源占比）；分母為與台達電模型相同的 AI 電源市場（含 ASIC 機架）
A60: 份額相對值（÷ FY2026） | B60: x | D60: =1 -> 1 | E60: =RLO_27 -> 0.85 | F60: =RLO_28 -> 0.8 | G60: =RLO_29 -> 0.75
A61: 光寶有效份額 | B61: % | D61: =$D$59*D60 -> 0.17614332 | E61: =$D$59*E60 -> 0.14972182 | F61: =$D$59*F60 -> 0.14091465 | G61: =$D$59*G60 -> 0.13210749
A62: AI 電源營收 | B62: NT$B | C62: =a25_aip -> 31.390065 | D62: =D58*D61 -> 59.35208 | E62: =E58*E61 -> 119.72025 | F62: =F58*F61 -> 129.50135 | G62: =G58*G61 -> 155.59015
A63: AI 相關營收（＝AI 電源 ÷（1 − 非電源占比）） | B63: NT$B | C63: =a25_ai -> 34.87785 | D63: =D62/(1-x_np) -> 65.946756 | E63: =E62/(1-x_np) -> 133.0225 | F63: =F62/(1-x_np) -> 143.89039 | G63: =G62/(1-x_np) -> 172.87794 | K63: 非電源部分（液冷、AI 光電）隨 AI 電源同比例成長（Assumed）
A64: B. 營收分部（官方三大事業群）與合計
A65: 雲端及物聯網：非 AI | B65: NT$B | C65: =a25_cn -> 39.8604 | D65: =a26_cn -> 50.031561 | E65: =D65*(1+g_cn27) -> 52.533139 | F65: =E65*(1+g_cn28) -> 55.159796 | G65: =F65*(1+g_cn29) -> 57.917785 | K65: 一般伺服器與網通電源、車用、工控、IoT；AI 相關（上列）為本分部的命題子列
A66: 雲端及物聯網 | B66: NT$B | C66: =C63+C65 -> 74.73825 | D66: =D63+D65 -> 115.97832 | E66: =E63+E65 -> 185.55564 | F66: =F63+F65 -> 199.05018 | G66: =G63+G65 -> 230.79572 | K66: ＝AI 相關＋非 AI（子列合計＝分部）
A67: 光電 | B67: NT$B | C67: =a25_op -> 28.23445 | D67: =a26_op -> 32.869321 | E67: =D67*(1+g_op27) -> 34.512787 | F67: =E67*(1+g_op28) -> 36.238426 | G67: =F67*(1+g_op29) -> 38.050347
A68: 資訊及消費性電子 | B68: NT$B | C68: =a25_ic -> 63.1123 | D68: =a26_ic -> 63.883833 | E68: =D68*(1+g_ic27) -> 63.883833 | F68: =E68*(1+g_ic28) -> 63.883833 | G68: =F68*(1+g_ic29) -> 63.883833
A69: 非 AI 營收（雲端非 AI＋光電＋資訊及消費性電子） | B69: NT$B | C69: =C65+C67+C68 -> 131.20715 | D69: =D65+D67+D68 -> 146.78471 | E69: =E65+E67+E68 -> 150.92976 | F69: =F65+F67+F68 -> 155.28205 | G69: =G65+G67+G68 -> 159.85197
A70: 營收 | B70: NT$B | C70: =C66+C67+C68 -> 166.085 | D70: =D66+D67+D68 -> 212.73147 | E70: =E66+E67+E68 -> 283.95226 | F70: =F66+F67+F68 -> 299.17244 | G70: =G66+G67+G68 -> 332.72991 | H70: =G70*(1+H72) -> 362.04732 | I70: =H70*(1+I72) -> 385.23858 | J70: =I70*(1+J72) -> 400.64812 | K70: FY2030 起為收斂法：營收年增由 FY2029 線性收斂到 fade_g、淨利率收斂到 fade_m（FY2032 達到），非驅動因子推導
A71: 檢查：分部合計 − 合併營收（FY2025 實績、FY2026 錨點） | B71: NT$B | C71: =C70-a25_rev -> 0 | D71: =D70-a26_rev -> 0
A72: 營收年增 | B72: % | D72: =D70/C70-1 -> 0.28085902 | E72: =E70/D70-1 -> 0.33479196 | F72: =F70/E70-1 -> 0.053601213 | G72: =G70/F70-1 -> 0.11216763 | H72: =$G72+(fade_gB-$G72)*1/3 -> 0.088111756 | I72: =$G72+(fade_gB-$G72)*2/3 -> 0.064055878 | J72: =$G72+(fade_gB-$G72)*3/3 -> 0.04
A73: AI 相關 ÷ 營收 | B73: % | C73: =C63/C70 -> 0.21 | D73: =D63/D70 -> 0.31 | E73: =E63/E70 -> 0.46846783 | F73: =F63/F70 -> 0.48096137 | G73: =G63/G70 -> 0.5195744
A74: 每 GW 光寶 AI 相關營收 | B74: US$M/GW | D74: =D63/fx/D55*1000 -> 88.071658 | E74: =E63/fx/E55*1000 -> 99.814546 | F74: =F63/fx/F55*1000 -> 106.46885 | G74: =G63/fx/G55*1000 -> 105.68599
A75: C. 損益
A76: 其他營收毛利率 ＝ 錨點毛利率 − 差距 × AI 占比（FY2026 校準） | B76: % | D76: =a26_gp/D70-d_ai*D73 -> 0.21698234 | K76: Derived：讓 FY2026 毛利率等於錨點；AI 相關毛利率＝其他＋差距
A77: AI 相關毛利率 ＝ 校準值 ＋ 額外改善 | B77: % | D77: =D76+d_ai -> 0.33698234 | E77: =$D$77+gmu_27 -> 0.33698234 | F77: =$D$77+gmu_28 -> 0.33698234 | G77: =$D$77+gmu_29 -> 0.33698234 | K77: 額外改善為 800V 電源櫃與組合（Assumed；情境 A 高、C 低）
A78: 毛利 | B78: NT$B | C78: =a25_gp -> 38.039 | D78: =a26_gp -> 54.072582 | E78: =E63*E77+E69*$D$76 -> 77.575323 | F78: =F63*F77+F69*$D$76 -> 82.181982 | G78: =G63*G77+G69*$D$76 -> 92.941865
A79: 毛利率 | B79: % | C79: =C78/C70 -> 0.22903333 | D79: =D78/D70 -> 0.25418234 | E79: =E78/E70 -> 0.27319848 | F79: =F78/F70 -> 0.2746977 | G79: =G78/G70 -> 0.27933126
A80: 營業費用（基準路徑） | B80: NT$B | C80: =a25_opx -> 21.301 | D80: =a26_opx -> 25.210333 | E80: =D80*(1+MAX(0,phi*E72)) -> 31.118485 | F80: =E80*(1+MAX(0,phi*F72)) -> 32.286077 | G80: =F80*(1+MAX(0,phi*G72)) -> 34.821094
A81: 營業費用 | B81: NT$B | C81: =C80 -> 21.301 | D81: =D80 -> 25.210333 | E81: =E80+0*E70 -> 31.118485 | F81: =F80+0*F70 -> 32.286077 | G81: =G80+0*G70 -> 34.821094
A82: 營業利益 | B82: NT$B | C82: =C78-C81 -> 16.738 | D82: =D78-D81 -> 28.862249 | E82: =E78-E81 -> 46.456838 | F82: =F78-F81 -> 49.895904 | G82: =G78-G81 -> 58.120771
A83: 營業利益率 | B83: % | C83: =C82/C70 -> 0.10077972 | D83: =D82/D70 -> 0.13567456 | E83: =E82/E70 -> 0.16360792 | F83: =F82/F70 -> 0.16677975 | G83: =G82/G70 -> 0.17467853
A84: 營業外淨額 | B84: NT$B | C84: =a25_nop -> 2.9762895 | D84: =a26_nop -> 3.839 | E84: =nop_f -> 3.5 | F84: =nop_f -> 3.5 | G84: =nop_f -> 3.5
A85: 歸屬母公司淨利 ÷ 稅前 | B85: % | C85: =a25_ni/a25_pt -> 0.76675348 | D85: =a26_ni/a26_pt -> 0.759431 | E85: =nir_f -> 0.76 | F85: =nir_f -> 0.76 | G85: =nir_f -> 0.76
A86: 歸屬母公司淨利 | B86: NT$B | C86: =a25_ni -> 15.116 | D86: =a26_ni -> 24.834342 | E86: =(E82+E84)*E85 -> 37.967197 | F86: =(F82+F84)*F85 -> 40.580887 | G86: =(G82+G84)*G85 -> 46.831786 | H86: =H70*H90 -> 46.900953 | I86: =I70*I90 -> 45.588078 | J86: =J70*J90 -> 42.92176
A87: 股數 | B87: 十億股 | C87: =a25_sh -> 2.276506 | D87: =a26_sh -> 2.2689583 | E87: =D87*(1+sh_g) -> 2.2689583 | F87: =E87*(1+sh_g) -> 2.2689583 | G87: =F87*(1+sh_g) -> 2.2689583 | H87: =G87*(1+sh_g) -> 2.2689583 | I87: =H87*(1+sh_g) -> 2.2689583 | J87: =I87*(1+sh_g) -> 2.2689583
A88: EPS | B88: NT$ | C88: =C86/C87 -> 6.64 | D88: =D86/D87 -> 10.945261 | E88: =E86/E87 -> 16.733316 | F88: =F86/F87 -> 17.88525 | G88: =G86/G87 -> 20.640214 | H88: =H86/H87 -> 20.670698 | I88: =I86/I87 -> 20.092074 | J88: =J86/J87 -> 18.916945
A89: EPS 年增 | B89: % | D89: =D88/C88-1 -> 0.64838274 | E89: =E88/D88-1 -> 0.52881832 | F89: =F88/E88-1 -> 0.068840747 | G89: =G88/F88-1 -> 0.15403553 | H89: =H88/G88-1 -> 0.0014769183 | I89: =I88/H88-1 -> -0.027992482 | J89: =J88/I88-1 -> -0.058487196
A90: 淨利率（歸屬母公司淨利 ÷ 營收） | B90: % | C90: =C86/C70 -> 0.091013638 | D90: =D86/D70 -> 0.11674033 | E90: =E86/E70 -> 0.13370979 | F90: =F86/F70 -> 0.1356438 | G90: =G86/G70 -> 0.14075016 | H90: =$G90+(fade_mB-$G90)*1/3 -> 0.12954371 | I90: =$G90+(fade_mB-$G90)*2/3 -> 0.11833726 | J90: =$G90+(fade_mB-$G90)*3/3 -> 0.10713081
A93: 案例區塊：份額提升（高）（情境 B）
A94: 項目 | B94: 單位 | C94: FY2025A | D94: FY2026（錨點） | E94: FY2027 | F94: FY2028 | G94: FY2029 | H94: FY2030（收斂） | I94: FY2031（收斂） | J94: FY2032（收斂） | K94: 說明
A95: A. AI 部署與 AI 電源市場（D 欄＝FY2026 校準年；每 kW 內容取自台達電模型）
A96: AI IT 資本支出 × 情境顆數係數 | B96: US$B | D96: =itc_26*1 -> 781.87292 | E96: =itc_27*1*1 -> 1565.35 | F96: =itc_28*um28_B*1 -> 1587.4111 | G96: =itc_29*um29_B*1 -> 1921.3317
A97: 每 GW IT 資本支出 | B97: US$B | D97: =itpg_gb*(1-vr26)+itpg_vr*vr26 -> 33.414032 | E97: =itpg_vr -> 37.586352 | F97: =itpg_vr -> 37.586352 | G97: =itpg_vr -> 37.586352
A98: 部署 GW（IT 電力） | B98: GW | D98: =D96/D97 -> 23.399538 | E98: =E96/E97 -> 41.646766 | F98: =F96/F97 -> 42.233711 | G98: =G96/G97 -> 51.117803
A99: AI 電源內容（台達電模型） | B99: US$/kW | D99: =pkw_26 -> 450 | E99: =pkw_27 -> 600 | F99: =pkw_28 -> 680 | G99: =pkw_29 -> 720
A100: AI 電源市場（美元） | B100: US$B | D100: =D98*D99/1000 -> 10.529792 | E100: =E98*E99/1000 -> 24.988059 | F100: =F98*F99/1000 -> 28.718923 | G100: =G98*G99/1000 -> 36.804818
A101: AI 電源市場（新台幣） | B101: NT$B | D101: =D100*fx -> 336.95335 | E101: =E100*fx -> 799.6179 | F101: =F100*fx -> 919.00554 | G101: =G100*fx -> 1177.7542
A102: 光寶有效份額（FY2026 校準）＝ AI 電源營收 ÷ 市場 | B102: % | D102: =a26_aip/D101 -> 0.17614332 | K102: Derived：分子為公司 AI 相關占比 × 營收 ×（1 − 非電源占比）；分母為與台達電模型相同的 AI 電源市場（含 ASIC 機架）
A103: 份額相對值（÷ FY2026） | B103: x | D103: =1 -> 1 | E103: =RHI_27 -> 1.1 | F103: =RHI_28 -> 1.2 | G103: =RHI_29 -> 1.25
A104: 光寶有效份額 | B104: % | D104: =$D$102*D103 -> 0.17614332 | E104: =$D$102*E103 -> 0.19375765 | F104: =$D$102*F103 -> 0.21137198 | G104: =$D$102*G103 -> 0.22017915
A105: AI 電源營收 | B105: NT$B | C105: =a25_aip -> 31.390065 | D105: =D101*D104 -> 59.35208 | E105: =E101*E104 -> 154.93208 | F105: =F101*F104 -> 194.25202 | G105: =G101*G104 -> 259.31691
A106: AI 相關營收（＝AI 電源 ÷（1 − 非電源占比）） | B106: NT$B | C106: =a25_ai -> 34.87785 | D106: =D105/(1-x_np) -> 65.946756 | E106: =E105/(1-x_np) -> 172.14676 | F106: =F105/(1-x_np) -> 215.83558 | G106: =G105/(1-x_np) -> 288.1299 | K106: 非電源部分（液冷、AI 光電）隨 AI 電源同比例成長（Assumed）
A107: B. 營收分部（官方三大事業群）與合計
A108: 雲端及物聯網：非 AI | B108: NT$B | C108: =a25_cn -> 39.8604 | D108: =a26_cn -> 50.031561 | E108: =D108*(1+g_cn27) -> 52.533139 | F108: =E108*(1+g_cn28) -> 55.159796 | G108: =F108*(1+g_cn29) -> 57.917785 | K108: 一般伺服器與網通電源、車用、工控、IoT；AI 相關（上列）為本分部的命題子列
A109: 雲端及物聯網 | B109: NT$B | C109: =C106+C108 -> 74.73825 | D109: =D106+D108 -> 115.97832 | E109: =E106+E108 -> 224.6799 | F109: =F106+F108 -> 270.99537 | G109: =G106+G108 -> 346.04768 | K109: ＝AI 相關＋非 AI（子列合計＝分部）
A110: 光電 | B110: NT$B | C110: =a25_op -> 28.23445 | D110: =a26_op -> 32.869321 | E110: =D110*(1+g_op27) -> 34.512787 | F110: =E110*(1+g_op28) -> 36.238426 | G110: =F110*(1+g_op29) -> 38.050347
A111: 資訊及消費性電子 | B111: NT$B | C111: =a25_ic -> 63.1123 | D111: =a26_ic -> 63.883833 | E111: =D111*(1+g_ic27) -> 63.883833 | F111: =E111*(1+g_ic28) -> 63.883833 | G111: =F111*(1+g_ic29) -> 63.883833
A112: 非 AI 營收（雲端非 AI＋光電＋資訊及消費性電子） | B112: NT$B | C112: =C108+C110+C111 -> 131.20715 | D112: =D108+D110+D111 -> 146.78471 | E112: =E108+E110+E111 -> 150.92976 | F112: =F108+F110+F111 -> 155.28205 | G112: =G108+G110+G111 -> 159.85197
A113: 營收 | B113: NT$B | C113: =C109+C110+C111 -> 166.085 | D113: =D109+D110+D111 -> 212.73147 | E113: =E109+E110+E111 -> 323.07652 | F113: =F109+F110+F111 -> 371.11763 | G113: =G109+G110+G111 -> 447.98186 | H113: =G113*(1+H115) -> 515.81096 | I113: =H113*(1+I115) -> 565.17674 | J113: =I113*(1+J115) -> 587.78381 | K113: FY2030 起為收斂法：營收年增由 FY2029 線性收斂到 fade_g、淨利率收斂到 fade_m（FY2032 達到），非驅動因子推導
A114: 檢查：分部合計 − 合併營收（FY2025 實績、FY2026 錨點） | B114: NT$B | C114: =C113-a25_rev -> 0 | D114: =D113-a26_rev -> 0
A115: 營收年增 | B115: % | D115: =D113/C113-1 -> 0.28085902 | E115: =E113/D113-1 -> 0.51870581 | F115: =F113/E113-1 -> 0.14869887 | G115: =G113/F113-1 -> 0.20711555 | H115: =$G115+(fade_gB-$G115)*1/3 -> 0.15141036 | I115: =$G115+(fade_gB-$G115)*2/3 -> 0.095705182 | J115: =$G115+(fade_gB-$G115)*3/3 -> 0.04
A116: AI 相關 ÷ 營收 | B116: % | C116: =C106/C113 -> 0.21 | D116: =D106/D113 -> 0.31 | E116: =E106/E113 -> 0.53283588 | F116: =F106/F113 -> 0.58158266 | G116: =G106/G113 -> 0.64317313
A117: 每 GW 光寶 AI 相關營收 | B117: US$M/GW | D117: =D106/fx/D98*1000 -> 88.071658 | E117: =E106/fx/E98*1000 -> 129.17177 | F117: =F106/fx/F98*1000 -> 159.70327 | G117: =G106/fx/G98*1000 -> 176.14332
A118: C. 損益
A119: 其他營收毛利率 ＝ 錨點毛利率 − 差距 × AI 占比（FY2026 校準） | B119: % | D119: =a26_gp/D113-d_ai*D116 -> 0.21698234 | K119: Derived：讓 FY2026 毛利率等於錨點；AI 相關毛利率＝其他＋差距
A120: AI 相關毛利率 ＝ 校準值 ＋ 額外改善 | B120: % | D120: =D119+d_ai -> 0.33698234 | E120: =$D$120+gmu_27 -> 0.33698234 | F120: =$D$120+gmu_28 -> 0.33698234 | G120: =$D$120+gmu_29 -> 0.33698234 | K120: 額外改善為 800V 電源櫃與組合（Assumed；情境 A 高、C 低）
...

Sheet Sources
A1: 來源（公司原文＝光寶科財報、月營收公告與法說會，經資料商與媒體轉述；券商與媒體估計皆為 Interested-party）
A2: 二手：優分析 2026-07-31（2Q26、1H26 損益、雲端與物聯網營收與營業利益） | B2: https://uanalyze.com.tw/articles/3402052563
A3: 二手：富果 2026-07-31 法說摘要（AI 占比超過 30%、BBU 占雲端 20–25%、800V 時程、資本支出 180 億、產能） | B3: https://blog.fugle.tw/post/earnings-call-2301-2026-07-31
A4: 二手：優分析 2026-02-25（FY2025、4Q25 損益、AI 占比超過 20%） | B4: https://uanalyze.com.tw/articles/1580848095
A5: 二手：富果 2026-02-25 法說摘要（FY2025 部門占比、2026 指引、資本支出） | B5: https://blog.fugle.tw/post/earnings-call-2301-2026-02-25
A6: 二手：technews 2026-10-08（9 月營收 188.48 億、前 9 月 1,535.59 億） | B6: https://finance.technews.tw/2026/10/08/ltc-2301-202609-financial-report/
A7: 資料商：nstock（10-22 收盤、9 月營收） | B7: https://www.nstock.tw/2301?status=2
A8: 資料商：stockanalysis（現價、近 12 月與前瞻 P/E、股數、共識目標價；同業前瞻 P/E） | B8: https://stockanalysis.com/quote/tpe/2301/
A9: 資料商：stockanalysis 季度與年度損益（營收、毛利、營業利益、淨利、稅前淨利率） | B9: https://stockanalysis.com/quote/tpe/2301/financials/?p=quarterly
A10: 資料商：stockanalysis forecast（2026-09-23 目標價區間、FY2026 營收與 EPS） | B10: https://stockanalysis.com/quote/tpe/2301/forecast/
A11: 資料商：MarketScreener（FY2026–28 共識營收、淨利、EPS） | B11: https://www.marketscreener.com/quote/stock/LITE-ON-TECHNOLOGY-CORPOR-6492334/valuation/
A12: 資料商：wearn（2012–2025 年度 EPS、淨利率、ROE） | B12: https://stock.wearn.com/financial.asp?kind=2301
A13: 資料商：digrin（2014–2025 年 12 月價格，未調整） | B13: https://www.digrin.com/stocks/detail/2301.TW/price
... A15: 券商：凱基 Power supply sector 2025-09-26（台達電市占 60–65%、光寶第二梯隊、每架電源內容） | B15: https://www.kgi.com.hk/zh-hk/-/media/files/kgishk/research-reports/tw-reports/power-supply-sector_20250926e.pdf
A16: 市場層：markets/network、markets/chip_bridge、tsmc 成品；delta 成品（AI 電源每 kW 內容、台達電份額，本專案權威）（本 repo，唯讀）
A17: 無法取得：companiesmarketcap 光寶 P/E 頁（網站錯誤）；10-23 收盤；7、8 月個別營收 | B17: 未找到
A18: 待補（人工）：3Q26 財報與法說（10-30 前後）；10 月營收（11-10 前後）；部門別毛利率；AI 電源與 BBU 的季度金額；光寶 AI 電源市占的量化來源；資本支出與折舊路徑；前瞻 P/E 十年歷史（Bloomberg）；FY2027 起共識第二來源 | B18: 未找到
A19: SemiAnalysis | B19: 未使用
