Workbook

Sheet README
A1: Ibiden（4062）收支與估值模型 v0.2（AI 半導體 Project：載板與 PCB 樣板） 2026-10-25
A2: 版本：v0.2（2026-10-25：目標價改為 DCF 與 Comparable 加權、三情境延伸到 FY2032；FY2025–FY2029 數值不變）。前版：v0.1（初版）。Ibiden 在 AI 加速器載板的有效金額與份額在本模型 Units 頁建立，為本專案權威資料（規則第 13 條）。
A3: 模型命題：Ibiden 的 AI 伺服器載板營收＝AI 加速器顆數（本專案網通模型）× Ibiden 份額 × 每顆載板金額（面積、層數逐年增加）× 短缺溢價；電子事業的非 AI 部分、陶瓷與其他事業另依成長率推。股價約 54–65 倍前瞻 EPS：2028 年產能擴到 2.5 倍、競爭者同時擴產之後，短缺溢價能否守住電子事業約 29% 的營益率？
A4: 核心問題：短缺溢價回落多少、何時回落，FY2028 EPS 會少多少；現價隱含的溢價路徑合不合理。
A6: 會計年度 4 月至隔年 3 月：FY(t)＝t/4–(t+1)/3，對照 CY(t) 的加速器顆數（重疊 9 個月，不平移）。預測期 FY2027–FY2029（三年）。金額：十億日圓；EPS：日圓（2026-10-01 一拆二後）。
A8: 驅動因子 → 推導量（全部唯讀上游，不修改）
A9: AI 載板：markets/network 的加速器顆數（NVIDIA ＋ 權重 × 非 NVIDIA）× 每顆有效金額（FY2026 校準）× 金額指數（+18%／年，Analogy）× 份額相對值（Assumed）× 溢價指數（Assumed）。
A10: 利潤率：AI 載板營益率 FY2026 校準（非 AI 部分 15%，Assumed），之後＝ 1 −（1 − 校準值）÷ 溢價指數（成本不變）。陶瓷、其他事業營益率沿用 FY2026 預測。淨利 ÷ 營業利益 0.661（FY2026 預測）。
A11: 校準：FY2026 ＝ 公司 2026-08-04 上修後預測（營收 5,500 億、營業利益 1,270 億、淨利 840 億、EPS 149.68）；AI 伺服器載板占電子事業 65%（Assumed，公司未揭露）。
A12: 估值：Val 第 0 節目標價＝0.5 × DCF 目標價（股東現金流＝EPS ×（1 − tp_g ÷ tp_roe），FY2027–FY2032 明確期＋永續，r 10%、g 4%，三情境權重 0.3／0.5／0.2，推到 12 個月後）＋0.5 × Comparable 目標價（欣興、南電、景碩、三星電機、AT&S 前瞻 P/E 中位數 × 12 個月後前瞻 EPS）；另列 Comparable 單獨目標價、市場共識目標價與差距拆解（EPS 因素、倍數因素）、DCF 價格帶、十年 P/E 分位檢查（只作檢查）。會計年度 4 月制：12 個月後前瞻 EPS＝½ FY2027＋½ FY2028。（v0.1.1 原估值說明，保留作參考：現價 ÷ FY2026–FY2028 EPS 與 what must be true；十年 P/E 規則值待 Bloomberg（本版不計）；循環位置以本模型營收最高年判定。）
A13: 標記：Verified、Interested-party、Analogy、Assumed、Derived。SemiAnalysis 未使用。
A15: 已知限制：(1) AI 載板營收公司未揭露，以 Assumed 切分校準；(2) 溢價指數與份額相對值皆為 Assumed，是 FY2028 EPS 最敏感的輸入（Sens）；(3) 未設產能上限（2024 基準面積未找到）；(4) FY2026 錨點為公司預測，Q2 決算後更新；(5) 十年 P/E 規則值待 Bloomberg；(6) CB 轉換稀釋只在 Sens；(7) R4 產業部署路徑未建（Recon 預留列）。
... A19: 先驗：v0.1 的 Andy 合理 P/E 25x 對照（Val 第 4 節）保留不動，不進目標價；本版未新增先驗。

Sheet In
A1: In — 輸入（藍字；基準欄 E，低 D、高 F）。金額：十億日圓（¥B）；顆數：百萬顆；比例：%。每個輸入附兩個來源（找不到者寫「未找到」）；公司原文算一個
A2: 標記：Verified／Interested-party／Analogy／Assumed／Derived；Analogy、Assumed 給低／高區間。SemiAnalysis 未使用。公司原文＝Ibiden 決算短信與補足資料（TDnet）；公司預測為 Interested-party
A3: 鍵 | B3: 項目 | C3: 單位 | D3: 低 | E3: 基準 | F3: 高 | G3: 標記 | H3: 來源1 | I3: 來源2／說明
A4: A. 加速器顆數（讀 markets/network In 頁；CY2026–CY2028 為輸入、CY2029＝CY2028 ×（1＋成長率））
A5: u_bw_26 | B5: NVIDIA Blackwell（B200／B300） 顆數 2026 | C5: 百萬顆 | E5: 5.4 | G5: Derived | H5: markets/network/dist/20261023_AI網通市場模型_v0.2.2.xlsx｜In!E5 | I5: 唯讀上游；不在本模型另訂
A6: u_bw_27 | B6: NVIDIA Blackwell（B200／B300） 顆數 2027 | C6: 百萬顆 | E6: 2.4 | G6: Derived | H6: markets/network/dist/20261023_AI網通市場模型_v0.2.2.xlsx｜In!E6 | I6: 唯讀上游；不在本模型另訂
A7: u_bw_28 | B7: NVIDIA Blackwell（B200／B300） 顆數 2028 | C7: 百萬顆 | E7: 0.5 | G7: Derived | H7: markets/network/dist/20261023_AI網通市場模型_v0.2.2.xlsx｜In!E7 | I7: 唯讀上游；不在本模型另訂
A8: g29_bw | B8: NVIDIA Blackwell（B200／B300） 2029 顆數成長 | C8: % | E8: -0.5 | G8: Derived | H8: markets/network/dist/20261023_AI網通市場模型_v0.2.2.xlsx｜In!E8 | I8: 同上
A9: u_rb_26 | B9: NVIDIA Rubin 顆數 2026 | C9: 百萬顆 | E9: 1.7 | G9: Derived | H9: markets/network/dist/20261023_AI網通市場模型_v0.2.2.xlsx｜In!E9 | I9: 唯讀上游；不在本模型另訂
A10: u_rb_27 | B10: NVIDIA Rubin 顆數 2027 | C10: 百萬顆 | E10: 7 | G10: Derived | H10: markets/network/dist/20261023_AI網通市場模型_v0.2.2.xlsx｜In!E10 | I10: 唯讀上游；不在本模型另訂
A11: u_rb_28 | B11: NVIDIA Rubin 顆數 2028 | C11: 百萬顆 | E11: 7 | G11: Derived | H11: markets/network/dist/20261023_AI網通市場模型_v0.2.2.xlsx｜In!E11 | I11: 唯讀上游；不在本模型另訂
A12: g29_rb | B12: NVIDIA Rubin 2029 顆數成長 | C12: % | E12: 0.15 | G12: Derived | H12: markets/network/dist/20261023_AI網通市場模型_v0.2.2.xlsx｜In!E12 | I12: 同上
A13: u_ru_26 | B13: NVIDIA Rubin Ultra 顆數 2026 | C13: 百萬顆 | E13: 0 | G13: Derived | H13: markets/network/dist/20261023_AI網通市場模型_v0.2.2.xlsx｜In!E13 | I13: 唯讀上游；不在本模型另訂
A14: u_ru_27 | B14: NVIDIA Rubin Ultra 顆數 2027 | C14: 百萬顆 | E14: 0.3 | G14: Derived | H14: markets/network/dist/20261023_AI網通市場模型_v0.2.2.xlsx｜In!E14 | I14: 唯讀上游；不在本模型另訂
A15: u_ru_28 | B15: NVIDIA Rubin Ultra 顆數 2028 | C15: 百萬顆 | E15: 2 | G15: Derived | H15: markets/network/dist/20261023_AI網通市場模型_v0.2.2.xlsx｜In!E15 | I15: 唯讀上游；不在本模型另訂
A16: g29_ru | B16: NVIDIA Rubin Ultra 2029 顆數成長 | C16: % | E16: 0.15 | G16: Derived | H16: markets/network/dist/20261023_AI網通市場模型_v0.2.2.xlsx｜In!E16 | I16: 同上
... A46: um29_C | B46: 情境 C：2029 顆數 ÷ 基準 | C46: x | E46: 0.6 | G46: Assumed | H46: tsmc/dist/20261025_台積電模型_v0.2.2.xlsx｜In!E42 | I46: 同上
A47: B. Ibiden 份額與每顆載板金額（本專案權威：晶片商載板份額，規則第 13 條）
A48: w_ot | B48: 非 NVIDIA 加速器的權重（Ibiden 份額 × 每顆載板金額，相對 NVIDIA） | C48: x | D48: 0.2 | E48: 0.4 | F48: 0.6 | G48: Assumed | H48: 公開資料只有 NVIDIA 份額：BofA（經 thebuildout 2026-03-26）Ibiden 占 GPU 載板 70–80%；高階 FC-BGA 整體約 35%（Data Gravity 2026-06-14） | I48: ASIC 多由欣興、Shinko、AT&S 等分食（第三方研究，Interested-party）；每顆 ASIC 載板金額相對 GPU：未找到
A49: ai_e | B49: FY2026 AI 伺服器載板 ÷ 電子事業營收 | C49: % | D49: 0.55 | E49: 0.65 | F49: 0.75 | G49: Assumed | H49: 公司未揭露：未找到（決算短信只說「生成 AI 伺服器向け・汎用サーバー向け高機能 IC パッケージ基板」帶動） | I49: semi-connect 2026：AI 高階載板營收多數為 NVIDIA 向（估計，Interested-party）
A50: g_asp | B50: 每顆載板金額年增（面積、層數） | C50: % | D50: 0.1 | E50: 0.18 | F50: 0.22 | G50: Analogy | H50: Tom's Hardware：The state of ABF substrates in 2026：Ibiden 路線圖 2026 年 90×90 mm、2028 年 110×110 mm；每片 AI 伺服器載板的 SAP 負荷 2026 年為 2024 年 1.8 倍、2028 年 2.5 倍（→ 2026→2028 年約 +18%／年） | I50: Data Gravity 2026-06-14：ABF 載板平均單價 2024 $65 → 2025 $82（+26%，全品項）
A51: rel_27 | B51: Ibiden 份額 2027 ÷ 2026（相對值） | C51: x | D51: 0.85 | E51: 0.95 | F51: 1 | G51: Assumed | H51: 第三方研究：欣興 2025 年拿到 NVIDIA AI 載板約 30% 顆數（Encyclopedia of Stocks 2026-03-04） | I51: 三星電機獲 NVIDIA 載板擴產合作（Hardware Busters 2026）
A52: rel_28 | B52: Ibiden 份額 2028 ÷ 2026 | C52: x | D52: 0.75 | E52: 0.88 | F52: 1 | G52: Assumed | H52: 同上；競爭者擴產：欣興 2026 資本支出 NT$340 億、景碩 3 年 NT$235 億（Tom's Hardware：The state of ABF substrates in 2026） | I52: —
A53: rel_29 | B53: Ibiden 份額 2029 ÷ 2026 | C53: x | D53: 0.7 | E53: 0.85 | F53: 1 | G53: Assumed | H53: 同上 | I53: —
A54: C. 短缺溢價（價格指數；2026＝1）與 AI 載板利潤率
A55: pp_27 | B55: 價格溢價指數 2027 | C55: x | D55: 0.95 | E55: 1 | F55: 1.05 | G55: Assumed | H55: Tom's Hardware：The state of ABF substrates in 2026（未具名供應鏈分析）：ABF 供需缺口 2026 下半年約 10%、2027 約 21%、2028 超過 40% | I55: BofA：短缺延續到 2028（經 thebuildout）
A56: pp_28 | B56: 價格溢價指數 2028 | C56: x | D56: 0.85 | E56: 0.95 | F56: 1.05 | G56: Assumed | H56: Ibiden 產能 2028 年為 2024 年 2.5–2.8 倍（公司路線圖，Interested-party；Data Gravity 2026-06-14、Tom's Hardware：The state of ABF substrates in 2026） | I56: 欣興、景碩、三星電機同時擴產（同上）
A57: pp_29 | B57: 價格溢價指數 2029 | C57: x | D57: 0.75 | E57: 0.9 | F57: 1 | G57: Assumed | H57: 同上：新產能到位後溢價回落 | I57: —
A58: m_ne | B58: 電子事業非 AI 部分營業利益率 | C58: % | D58: 0.1 | E58: 0.15 | F58: 0.2 | G58: Assumed | H58: FY2024 電子事業營益率 13.6%（26.8 ÷ 197.2，AI 比重較低時；公司：2026 年 3 月期決算短信（Sources 頁）） | I58: FY2025 18.6%（45.2 ÷ 243.3）
A59: g_ne | B59: 電子事業非 AI 營收年增（通用伺服器、PC 載板等） | C59: % | D59: 0 | E59: 0.05 | F59: 0.1 | G59: Assumed | H59: SEMICON.TODAY 2026-08：通用伺服器市場緩步成長 | I59: PC：未找到
A60: D. 陶瓷、其他事業與全公司
A61: g_cer | B61: 陶瓷事業營收年增（DPF、汽車排氣） | C61: % | D61: -0.05 | E61: 0 | F61: 0.03 | G61: Assumed | H61: FY2025 −1.8%（84.1 → 82.6；公司：2026 年 3 月期決算短信（Sources 頁）） | I61: FY2026 預測 84.0（+1.8%；公司：Q1 補足資料（分部門預測、設備投資、匯率前提；Sources 頁））
A62: m_cer | B62: 陶瓷事業營益率 | C62: % | D62: 0.05 | E62: 0.077 | F62: 0.1 | G62: Derived | H62: FY2026 預測 6.5 ÷ 84.0（公司：Q1 補足資料（分部門預測、設備投資、匯率前提；Sources 頁）） | I62: FY2025 9.3%（7.6 ÷ 82.6）
A63: g_oth | B63: 其他事業營收年增（建材等） | C63: % | D63: 0 | E63: 0.03 | F63: 0.05 | G63: Assumed | H63: FY2025 +2.5%（88.1 → 90.3） | I63: FY2026 預測 91.0（+0.7%）
A64: m_oth | B64: 其他事業營益率 | C64: % | D64: 0.09 | E64: 0.115 | F64: 0.13 | G64: Derived | H64: FY2026 預測 10.5 ÷ 91.0（公司：Q1 補足資料（分部門預測、設備投資、匯率前提；Sources 頁）） | I64: FY2025 9.9%（9.0 ÷ 90.3）
A65: ni_oi | B65: 淨利 ÷ 營業利益（稅、非營業、少數股權） | C65: x | D65: 0.62 | E65: 0.661 | F65: 0.7 | G65: Derived | H65: FY2026 預測 84 ÷ 127（公司：Q1 補足資料（分部門預測、設備投資、匯率前提；Sources 頁）） | I65: FY2025 1.03（含政策持股出售利益，不具代表性）
A66: sh_g | B66: 股數年變動（2031 年到期 CB 轉換） | C66: % | D66: 0 | E66: 0 | F66: 0.03 | G66: Assumed | H66: CB 轉換價 ¥2,243.1（分割後；SEMICON.TODAY 2026-08），遠低於現價 | I66: CB 發行額：未找到；FY2025 稀釋 EPS 比基本低 5.8%（214.91 ÷ 228.16）
A67: fx | B67: 匯率（美元換算用） | C67: ¥／US$ | E67: 152 | G67: Interested-party | H67: 公司：Q1 補足資料（分部門預測、設備投資、匯率前提；Sources 頁）：FY2026 前提 ¥152 | I67: —
A68: E. FY2026 錨點（公司 2026-08-04 上修後預測；Q2 決算後更新）
A69: f_rev | B69: FY2026 營收預測 | C69: ¥B | E69: 550 | G69: Interested-party | H69: 公司：Q1 補足資料（分部門預測、設備投資、匯率前提；Sources 頁） | I69: LIMO 2026-08-15：5,500 億（+32.1%）
A70: f_e | B70: FY2026 電子事業營收預測 | C70: ¥B | E70: 375 | G70: Interested-party | H70: 公司：Q1 補足資料（分部門預測、設備投資、匯率前提；Sources 頁） | I70: Q1 實績 77.5（年增 37.7%；SEMICON.TODAY 2026-08）
A71: f_eoi | B71: FY2026 電子事業營業利益預測 | C71: ¥B | E71: 110 | G71: Interested-party | H71: 公司：Q1 補足資料（分部門預測、設備投資、匯率前提；Sources 頁） | I71: Q1 實績 21.4（營益率 27.6%）
A72: f_cer | B72: FY2026 陶瓷事業營收預測 | C72: ¥B | E72: 84 | G72: Interested-party | H72: 公司：Q1 補足資料（分部門預測、設備投資、匯率前提；Sources 頁） | I72: —
A73: f_ceroi | B73: FY2026 陶瓷事業營業利益預測 | C73: ¥B | E73: 6.5 | G73: Interested-party | H73: 公司：Q1 補足資料（分部門預測、設備投資、匯率前提；Sources 頁） | I73: —
A74: f_oth | B74: FY2026 其他事業營收預測 | C74: ¥B | E74: 91 | G74: Interested-party | H74: 公司：Q1 補足資料（分部門預測、設備投資、匯率前提；Sources 頁） | I74: —
A75: f_othoi | B75: FY2026 其他事業營業利益預測 | C75: ¥B | E75: 10.5 | G75: Interested-party | H75: 公司：Q1 補足資料（分部門預測、設備投資、匯率前提；Sources 頁） | I75: —
A76: f_oi | B76: FY2026 營業利益預測 | C76: ¥B | E76: 127 | G76: Interested-party | H76: 公司：Q1 補足資料（分部門預測、設備投資、匯率前提；Sources 頁） | I76: SEMICON.TODAY 2026-08：900 → 1,270 億
A77: f_ni | B77: FY2026 淨利預測（歸屬母公司） | C77: ¥B | E77: 84 | G77: Interested-party | H77: 公司：Q1 補足資料（分部門預測、設備投資、匯率前提；Sources 頁） | I77: SEMICON.TODAY 2026-08：580 → 840 億
A78: f_eps | B78: FY2026 EPS 預測（分割後） | C78: ¥ | E78: 149.68 | G78: Interested-party | H78: SEMICON.TODAY 2026-08：反映 2026-10-01 一拆二 | I78: —
A79: F. FY2025 實績（2026 年 3 月期）
A80: a_rev | B80: FY2025 營收 | C80: ¥B | E80: 416.201 | G80: Verified | H80: 公司：2026 年 3 月期決算短信（Sources 頁） | I80: SEMICON.TODAY、semi-connect 同值
A81: a_e | B81: FY2025 電子事業營收 | C81: ¥B | E81: 243.316 | G81: Verified | H81: 公司：2026 年 3 月期決算短信（Sources 頁） | I81: SEMICON.TODAY、semi-connect 同值
A82: a_eoi | B82: FY2025 電子事業營業利益 | C82: ¥B | E82: 45.248 | G82: Verified | H82: 公司：2026 年 3 月期決算短信（Sources 頁） | I82: —
A83: a_cer | B83: FY2025 陶瓷事業營收 | C83: ¥B | E83: 82.554 | G83: Verified | H83: 公司：2026 年 3 月期決算短信（Sources 頁） | I83: —
A84: a_ceroi | B84: FY2025 陶瓷事業營業利益 | C84: ¥B | E84: 7.646 | G84: Verified | H84: 公司：2026 年 3 月期決算短信（Sources 頁） | I84: —
A85: a_oth | B85: FY2025 其他事業營收 | C85: ¥B | E85: 90.33 | G85: Verified | H85: 公司：2026 年 3 月期決算短信（Sources 頁） | I85: —
A86: a_othoi | B86: FY2025 其他事業營業利益 | C86: ¥B | E86: 8.964 | G86: Verified | H86: 公司：2026 年 3 月期決算短信（Sources 頁） | I86: —
A87: a_oi | B87: FY2025 營業利益 | C87: ¥B | E87: 62.027 | G87: Verified | H87: 公司：2026 年 3 月期決算短信（Sources 頁） | I87: SEMICON.TODAY、semi-connect 同值
A88: a_gp | B88: FY2025 毛利 | C88: ¥B | E88: 131.668 | G88: Verified | H88: 公司：2026 年 3 月期決算短信（Sources 頁） | I88: —
A89: a_ni | B89: FY2025 淨利（歸屬母公司） | C89: ¥B | E89: 63.713 | G89: Verified | H89: 公司：2026 年 3 月期決算短信（Sources 頁） | I89: —
A90: a_eps | B90: FY2025 基本 EPS（分割後換算＝228.16 ÷ 2） | C90: ¥ | E90: =228.16/2 -> 114.08 | G90: Derived | H90: 公司：2026 年 3 月期決算短信（Sources 頁）：228.16（2026-01 一拆二後、2026-10 一拆二前） | I90: 2026-10-01 再一拆二
A91: G. 價格與市場資料（只作 Val、Recon 對照）
A92: px | B92: 股價（2026-10-23 收盤，分割後） | C92: ¥ | E92: 8512 | G92: Interested-party | H92: markets/invest_map/data/prices.csv：株探、松井證券（兩來源核對；v0.2 更新） | I92: v0.1.1 為 10-16 收盤 9,764（stockanalysis）；前瞻 P/E 隱含 EPS 仍以 9,764 計（In 頁 cons_feps）
A93: pe_fwd_sa | B93: 前瞻 P/E（stockanalysis） | C93: x | E93: 53.97 | G93: Interested-party | H93: stockanalysis（口徑：未來 12 個月共識，頁面未明示） | I93: 第二來源：未找到
A94: pe_ttm | B94: 近 12 月 P/E | C94: x | E94: 83.85 | G94: Interested-party | H94: stockanalysis | I94: —
A95: pe_fair_andy | B95: Andy 先驗：合理 P/E | C95: x | E95: 25 | G95: Assumed | H95: 先驗_Andy_Ibiden_20261024 I10b（Drive；不在本 repo） | I95: 只作對照
A96: tgt30_rev | B96: 公司 FY2030 目標營收 | C96: ¥B | E96: 1000 | G96: Interested-party | H96: Quartr FY2025 摘要（AI 摘要；營收數字有誤處未採用） | I96: 第二來源：未找到
A97: tgt30_oi | B97: 公司 FY2030 目標營業利益 | C97: ¥B | E97: 300 | G97: Interested-party | H97: 同上 | I97: 第二來源：未找到
A98: H. 目標價情境權重（v0.1.1 新增；Val 頁第 0 節用）
A99: tp_wA | B99: 目標價情境權重 A（順利） | C99: % | E99: 0.3 | G99: Assumed | H99: Andy 可改（工作單 2026-10-25 預設 A 0.3／B 0.5／C 0.2） | I99: 三者合計應為 100%；v0.2 起用於 DCF 與 Comparable 的情境加權（Val 第 0 節）
A100: tp_wB | B100: 目標價情境權重 B（平平） | C100: % | E100: 0.5 | G100: Assumed | H100: Andy 可改（工作單 2026-10-25 預設 A 0.3／B 0.5／C 0.2） | I100: 三者合計應為 100%；v0.2 起用於 DCF 與 Comparable 的情境加權（Val 第 0 節）
A101: tp_wC | B101: 目標價情境權重 C（不如預期） | C101: % | E101: 0.2 | G101: Assumed | H101: Andy 可改（工作單 2026-10-25 預設 A 0.3／B 0.5／C 0.2） | I101: 三者合計應為 100%；v0.2 起用於 DCF 與 Comparable 的情境加權（Val 第 0 節）
A102: J. 目標價（DCF 與 Comparable 加權）與收斂法參數（v0.2 新增；黃底＝Assumed，Andy 可改）
A103: tp_r | B103: 折現率／要求報酬（DCF） | C103: % | E103: 0.1 | G103: Assumed | H103: Andy 可改（工作單 2026-10-25 預設 10%；美、台、日、韓同一值） | I103: Sens 頁 ±1pt
A104: tp_g | B104: 長期成長率（DCF 永續；情境 B 的 FY2032 營收年增收斂目標） | C104: % | E104: 0.04 | G104: Assumed | H104: Andy 可改（工作單預設 4%） | I104: Sens 頁 ±1pt（只動 DCF，PL 收斂目標不隨之變動）
A105: tp_roe | B105: ROE（近三年平均） | C105: % | E105: =AVERAGE(0.1217,0.0682,0.0685) -> 0.086133333 | G105: Derived | H105: stockanalysis 比率頁（Return on Equity）：2026 年 3 月期 12.17%、2025 年 3 月期 6.82%、2024 年 3 月期 6.85%（即本模型 FY2025、FY2024、FY2023） | I105: 單一來源；近 12 月 12.65%（同站，2026-08-27）
A106: tp_w_dcf | B106: 目標價中 DCF 的權重；其餘為 Comparable | C106: % | E106: 0.5 | G106: Assumed | H106: Andy 可改（2026-10-25 11:53 改為 0.5：DCF／Comparable 各半） | I106: Sens 頁 0.4／0.8
A107: fade_gA | B107: 情境 A（順利）：FY2032 營收年增收斂目標（tp_g＋2pt） | C107: % | E107: =tp_g+0.02 -> 0.06 | G107: Assumed | H107: 工作單 2026-10-25 11:20 收斂法 | I107: FY2030 起由 FY2029 年增線性收斂，FY2032 達到
A108: fade_gB | B108: 情境 B（平平）：FY2032 營收年增收斂目標（＝tp_g） | C108: % | E108: =tp_g -> 0.04 | G108: Assumed | H108: 同上 | I108: —
A109: fade_gC | B109: 情境 C（不如預期）：FY2032 營收年增收斂目標（tp_g−2pt） | C109: % | E109: =tp_g-0.02 -> 0.02 | G109: Assumed | H109: 同上 | I109: —
A110: nim10_f | B110: 十年平均淨利率的替代：最後一年（FY2029）淨利率 ×（本值） | C110: x | E110: 0.8 | G110: Assumed | H110: 十年（2016–2025）平均淨利率：未找到（免費資料商只到近五年）；依工作單以最後一年 × 0.8 替代 | I110: 淨利率收斂目標：A＝FY2029、B＝FY2029 與替代值的中點、C＝替代值（PL 延伸表）
A111: cons_tp | B111: 市場共識目標價（賣方平均） | C111: ¥ | E111: 12432.35 | G111: Interested-party | H111: stockanalysis 個股頁（S&P Global 彙整）18 位分析師平均目標價 12,432（頁面價格日期 2026-10-16；分割後） | I111: 第二來源：未找到
A112: cons_feps | B112: 共識前瞻 12 月 EPS（＝價格 ÷ 前瞻 P/E） | C112: ¥ | E112: =9764/53.97 -> 180.91532 | G112: Interested-party | H112: stockanalysis 個股頁 2026-10-16：價格 9,764 ÷ Forward PE 53.97（即 In 頁 pe_fwd_sa） | I112: 賣方共識，只作對帳與差距拆解，不作校準

Sheet Q
A1: Q — FY2025 實績與 FY2026 錨點（¥B）。FY2026 錨點＝公司 2026-08-04 上修後的全年預測（Q1 公布時；分部門預測取自 Q1 補足資料）。Q2 決算（預計 10 月底或 11 月初）後更新
A2: 公司未揭露 AI 伺服器載板營收；本模型以 In 頁 ai_e（Assumed）切分電子事業，並據此校準每顆有效金額與 AI 載板營業利益率（Derived）
A3: 項目 | B3: FY2025A | C3: FY2026 錨點 | D3: 年增 | E3: 標記 | F3: 說明
A4: 營收 | B4: =a_rev -> 416.201 | C4: =f_rev -> 550 | D4: =C4/B4-1 -> 0.32147688 | E4: Verified／Interested-party
A5: 電子事業 | B5: =a_e -> 243.316 | C5: =f_e -> 375 | D5: =C5/B5-1 -> 0.54120567 | E5: Verified／Interested-party
A6: 陶瓷事業 | B6: =a_cer -> 82.554 | C6: =f_cer -> 84 | D6: =C6/B6-1 -> 0.017515808 | E6: Verified／Interested-party
A7: 其他事業 | B7: =a_oth -> 90.33 | C7: =f_oth -> 91 | D7: =C7/B7-1 -> 0.0074172479 | E7: Verified／Interested-party
A8: 營業利益 | B8: =a_oi -> 62.027 | C8: =f_oi -> 127 | D8: =C8/B8-1 -> 1.0474954 | E8: Verified／Interested-party
A9: 電子事業 | B9: =a_eoi -> 45.248 | C9: =f_eoi -> 110 | D9: =C9/B9-1 -> 1.4310467 | E9: Verified／Interested-party
A10: 陶瓷事業 | B10: =a_ceroi -> 7.646 | C10: =f_ceroi -> 6.5 | D10: =C10/B10-1 -> -0.14988229 | E10: Verified／Interested-party
A11: 其他事業 | B11: =a_othoi -> 8.964 | C11: =f_othoi -> 10.5 | D11: =C11/B11-1 -> 0.17135207 | E11: Verified／Interested-party
A12: 調整（全公司 − 三事業） | B12: =a_oi-a_eoi-a_ceroi-a_othoi -> 0.169 | C12: =f_oi-f_eoi-f_ceroi-f_othoi -> 0 | D12: =C12/B12-1 -> -1 | E12: Verified／Interested-party
A13: 淨利（歸屬母公司） | B13: =a_ni -> 63.713 | C13: =f_ni -> 84 | D13: =C13/B13-1 -> 0.31841225 | E13: Verified／Interested-party | F13: FY2025 含政策持股出售利益（稅後約 345 億，Quartr 摘要），淨利高於營業利益
A14: EPS（分割後，日圓） | B14: =a_eps -> 114.08 | C14: =f_eps -> 149.68 | D14: =C14/B14-1 -> 0.31206171 | E14: Verified／Interested-party
A16: 比率
A17: 電子事業營益率 | B17: =B9/B5 -> 0.18596393 | C17: =C9/C5 -> 0.29333333 | E17: Derived
A18: 營業利益率 | B18: =B8/B4 -> 0.14903136 | C18: =C8/C4 -> 0.23090909 | E18: Derived
A19: 電子事業 ÷ 營收 | B19: =B5/B4 -> 0.58461176 | C19: =C5/C4 -> 0.68181818 | E19: Derived
A20: 毛利率（FY2026 預測未揭露） | B20: =a_gp/a_rev -> 0.31635676 | E20: Derived
A21: 股數（十億股＝淨利 ÷ EPS） | B21: =B13/B14 -> 0.55849404 | C21: =C13/C14 -> 0.56119722 | E21: Derived | F21: FY2025 股數含政策持股出售前後變動，只作參考；預測期用 FY2026 錨點股數

Sheet Units
A1: Units — Ibiden 在 AI 加速器載板的有效金額與份額（本專案權威，規則第 13 條）。顆數取自 markets/network（情境 A）
A3: 項目 | B3: 單位 | C3: FY2026（CY2026） | D3: FY2027 | E3: FY2028 | F3: FY2029 | G3: 說明
A4: NVIDIA 加速器顆數 | B4: 百萬顆 | C4: =PL!D63 -> 7.6 | D4: =PL!E63 -> 9.7 | E4: =PL!F63 -> 9.5 | F4: =PL!G63 -> 10.6 | G4: markets/network
A5: 非 NVIDIA 加速器顆數 | B5: 百萬顆 | C5: =PL!D64 -> 7.6 | D5: =PL!E64 -> 14 | E5: =PL!F64 -> 17 | F5: =PL!G64 -> 19.55
A6: 有效顆數 | B6: 百萬顆 | C6: =PL!D65 -> 10.64 | D6: =PL!E65 -> 15.3 | E6: =PL!F65 -> 16.3 | F6: =PL!G65 -> 18.42 | G6: 非 NVIDIA × 權重 w_ot
A7: 每顆 NVIDIA 加速器的 Ibiden 營收（美元） | B7: US$ | C7: =PL!$D$67*PL!D68*PL!D69*PL!D70*1000/fx -> 150.71602 | D7: =PL!$D$67*PL!E68*PL!E69*PL!E70*1000/fx -> 168.95266 | E7: =PL!$D$67*PL!F68*PL!F69*PL!F70*1000/fx -> 175.44044 | F7: =PL!$D$67*PL!G68*PL!G69*PL!G70*1000/fx -> 189.4379 | G7: ＝份額 × 每顆載板金額
A8: 每顆 NVIDIA 載板金額（美元；假設 FY2026 份額 70%） | B8: US$ | C8: =PL!$D$67*PL!D68*PL!D70*1000/fx/0.7 -> 215.3086 | D8: =PL!$D$67*PL!E68*PL!E70*1000/fx/0.7 -> 254.06414 | E8: =PL!$D$67*PL!F68*PL!F70*1000/fx/0.7 -> 284.8059 | F8: =PL!$D$67*PL!G68*PL!G70*1000/fx/0.7 -> 318.38302 | G8: BofA：Ibiden 占 GPU 載板 70–80%（Interested-party）；先驗比對推導 $150–300
A9: AI 伺服器載板營收 | B9: ¥B | C9: =PL!D71 -> 243.75 | D9: =PL!E71 -> 392.91629 | E9: =PL!F71 -> 434.67123 | F9: =PL!G71 -> 530.3958
A10: AI 伺服器載板營收（美元） | B10: US$B | C10: =PL!D71/fx -> 1.6036184 | D10: =PL!E71/fx -> 2.5849756 | E10: =PL!F71/fx -> 2.8596791 | F10: =PL!G71/fx -> 3.4894461 | G10: ÷ 匯率 152
A11: AI 載板營收 ÷ AI IT 資本支出 | B11: % | C11: =PL!D71/fx/itc_26 -> 0.0020509963 | D11: =PL!E71/fx/itc_27 -> 0.0016513723 | E11: =PL!F71/fx/itc_28 -> 0.0014411788 | F11: =PL!G71/fx/itc_29 -> 0.0015437361 | G11: × 每 GW IT capex 即每 GW 營收
A12: 每 GW Ibiden 營收（VR200 每 GW IT capex 37.59B） | B12: US$M | C12: =PL!D71/fx/itc_26*37.59*1000 -> 77.096949 | D12: =PL!E71/fx/itc_27*37.59*1000 -> 62.075085 | E12: =PL!F71/fx/itc_28*37.59*1000 -> 54.173912 | F12: =PL!G71/fx/itc_29*37.59*1000 -> 58.02904 | G12: Tokenomics IF_CapexIT（VR200 基準，經橋接表）
A14: 讀法：每顆 NVIDIA 加速器 Ibiden 只分到約 1–2 百美元，每 GW 約數千萬美元；瓶頸反映在利潤率（電子事業營益率）與倍數，不在營收規模。

Sheet PL
A1: PL — Ibiden 損益（¥B；EPS 日圓）。FY2025A 實績、FY2026 錨點（公司上修後預測），FY2027 起為模型。FY(t)＝t/4–(t+1)/3，對照 CY(t) 顆數。三情境各一個完整推導區塊（本頁下方），頂端為摘要。FY2026–FY2027 三情境相同（顆數係數從 CY2028 開始）
A3: 情境／項目 | B3: 單位 | C3: FY2025A | D3: FY2026（錨點） | E3: FY2027 | F3: FY2028 | G3: FY2029 | H3: 說明
A4: 情境 A
A5: 營收 | B5: ¥B | C5: =C82 -> 416.2 | D5: =D82 -> 550 | E5: =E82 -> 708.45879 | F5: =F82 -> 759.91625 | G5: =G82 -> 865.77224
A6: 營收年增 | B6: % | D6: =D83 -> 0.32148006 | E6: =E83 -> 0.2881069 | F6: =F83 -> 0.072632957 | G6: =G83 -> 0.13929955
A7: AI 伺服器載板 | B7: ¥B | D7: =D71 -> 243.75 | E7: =E71 -> 392.91629 | F7: =F71 -> 434.67123 | G7: =G71 -> 530.3958
A8: 電子事業 | B8: ¥B | C8: =C74 -> 243.316 | D8: =D74 -> 375 | E8: =E74 -> 530.72879 | F8: =F74 -> 579.37435 | G8: =G74 -> 682.33408
A9: 電子事業營益率 | B9: % | C9: =C78 -> 0.18596393 | D9: =D78 -> 0.29333333 | E9: =E78 -> 0.31325302 | F9: =F78 -> 0.29058187 | G9: =G78 -> 0.26704177
A10: 營業利益率 | B10: % | C10: =C87 -> 0.14903172 | D10: =D87 -> 0.23090909 | E10: =E87 -> 0.25901203 | F10: =F87 -> 0.24466643 | G10: =G87 -> 0.23114057
A11: 淨利 | B11: ¥B | C11: =C88 -> 63.713 | D11: =D88 -> 84 | E11: =E88 -> 121.29307 | F11: =F88 -> 122.89709 | G11: =G88 -> 132.27608
A12: EPS | B12: ¥ | C12: =C90 -> 114.08 | D12: =D90 -> 149.68 | E12: =E90 -> 216.1327 | F12: =F90 -> 218.9909 | G12: =G90 -> 235.70337
A13: EPS 年增 | B13: % | D13: =D91 -> 0.31206171 | E13: =E91 -> 0.44396512 | F13: =F91 -> 0.013224293 | G13: =G91 -> 0.076315806
A15: 情境 B
A16: 營收 | B16: ¥B | C16: =C116 -> 416.2 | D16: =D116 -> 550 | E16: =E116 -> 708.45879 | F16: =F116 -> 672.98201 | G16: =G116 -> 786.21287
A17: 營收年增 | B17: % | D17: =D117 -> 0.32148006 | E17: =E117 -> 0.2881069 | F17: =F117 -> -0.050076008 | G17: =G117 -> 0.16825244
A18: AI 伺服器載板 | B18: ¥B | D18: =D105 -> 243.75 | E18: =E105 -> 392.91629 | F18: =F105 -> 347.73698 | G18: =G105 -> 450.83643
A19: 電子事業 | B19: ¥B | C19: =C108 -> 243.316 | D19: =D108 -> 375 | E19: =E108 -> 530.72879 | F19: =F108 -> 492.44011 | G19: =G108 -> 602.77471
A20: 電子事業營益率 | B20: % | C20: =C112 -> 0.18596393 | D20: =D112 -> 0.29333333 | E20: =E112 -> 0.31325302 | F20: =F112 -> 0.28231989 | G20: =G112 -> 0.26261646
A21: 營業利益率 | B21: % | C21: =C121 -> 0.14903172 | D21: =D121 -> 0.23090909 | E21: =E121 -> 0.25901203 | F21: =F121 -> 0.23268966 | G21: =G121 -> 0.22411481
A22: 淨利 | B22: ¥B | C22: =C122 -> 63.713 | D22: =D122 -> 84 | E22: =E122 -> 121.29307 | F22: =F122 -> 103.50993 | G22: =G122 -> 116.46949
A23: EPS | B23: ¥ | C23: =C124 -> 114.08 | D23: =D124 -> 149.68 | E23: =E124 -> 216.1327 | F23: =F124 -> 184.44483 | G23: =G124 -> 207.53753
A24: EPS 年增 | B24: % | D24: =D125 -> 0.31206171 | E24: =E125 -> 0.44396512 | F24: =F125 -> -0.14661302 | G24: =G125 -> 0.12520113
A26: 情境 C
A27: 營收 | B27: ¥B | C27: =C150 -> 416.2 | D27: =D150 -> 550 | E27: =E150 -> 708.45879 | F27: =F150 -> 586.04776 | G27: =G150 -> 653.61392
A28: 營收年增 | B28: % | D28: =D151 -> 0.32148006 | E28: =E151 -> 0.2881069 | F28: =F151 -> -0.17278497 | G28: =G151 -> 0.11529122
A29: AI 伺服器載板 | B29: ¥B | D29: =D139 -> 243.75 | E29: =E139 -> 392.91629 | F29: =F139 -> 260.80274 | G29: =G139 -> 318.23748
A30: 電子事業 | B30: ¥B | C30: =C142 -> 243.316 | D30: =D142 -> 375 | E30: =E142 -> 530.72879 | F30: =F142 -> 405.50586 | G30: =G142 -> 470.17576
A31: 電子事業營益率 | B31: % | C31: =C146 -> 0.18596393 | D31: =D146 -> 0.29333333 | E31: =E146 -> 0.31325302 | F31: =F146 -> 0.27051544 | G31: =G146 -> 0.25191285
A32: 營業利益率 | B32: % | C32: =C155 -> 0.14903172 | D32: =D155 -> 0.23090909 | E32: =E155 -> 0.25901203 | F32: =F155 -> 0.21715963 | G32: =G155 -> 0.20860435
A33: 淨利 | B33: ¥B | C33: =C156 -> 63.713 | D33: =D156 -> 84 | E33: =E156 -> 121.29307 | F33: =F156 -> 84.122769 | G33: =G156 -> 90.125173
A34: EPS | B34: ¥ | C34: =C158 -> 114.08 | D34: =D158 -> 149.68 | E34: =E158 -> 216.1327 | F34: =F158 -> 149.89876 | G34: =G158 -> 160.59448
A35: EPS 年增 | B35: % | D35: =D159 -> 0.31206171 | E35: =E159 -> 0.44396512 | F35: =F159 -> -0.30645033 | G35: =G159 -> 0.071352905
A37: 核對（應為 0）：FY2026 模型 − 錨點（校準恆等式）
A38: 情境 A：營收差（¥B） | D38: =D82-q26_rev -> 0
A39: 情境 A：營業利益差（¥B） | D39: =D86-q26_oi -> 0
A40: 情境 A：EPS 差（日圓） | D40: =D90-q26_eps -> 0
A60: 情境 A：基準（顆數係數 1.0）
A61: 項目 | B61: 單位 | C61: FY2025A | D61: FY2026（錨點） | E61: FY2027 | F61: FY2028 | G61: FY2029 | H61: 說明
A62: A. AI 伺服器載板（D 欄＝FY2026 校準年；FY(t) 對照 CY(t) 顆數）
A63: NVIDIA 加速器顆數 × 情境係數 | B63: 百萬顆 | D63: =(u_bw_26+u_rb_26+u_ru_26+u_hp_26)*1 -> 7.6 | E63: =(u_bw_27+u_rb_27+u_ru_27+u_hp_27)*1 -> 9.7 | F63: =(u_bw_28+u_rb_28+u_ru_28+u_hp_28)*um28_A -> 9.5 | G63: =(u_bw_28*(1+g29_bw)+u_rb_28*(1+g29_rb)+u_ru_28*(1+g29_ru)+u_hp_28*(1+g29_hp))*um29_A -> 10.6 | H63: markets/network In：Blackwell、Rubin、Rubin Ultra、Hopper
A64: 非 NVIDIA 加速器顆數 × 情境係數 | B64: 百萬顆 | D64: =(u_amd_26+u_tpu_26+u_trn_26+u_oth_26)*1 -> 7.6 | E64: =(u_amd_27+u_tpu_27+u_trn_27+u_oth_27)*1 -> 14 | F64: =(u_amd_28+u_tpu_28+u_trn_28+u_oth_28)*um28_A -> 17 | G64: =(u_amd_28*(1+g29_amd)+u_tpu_28*(1+g29_tpu)+u_trn_28*(1+g29_trn)+u_oth_28*(1+g29_oth))*um29_A -> 19.55 | H64: AMD、TPU、Trainium、其他 ASIC
A65: 有效顆數 ＝ NVIDIA ＋ 權重 × 非 NVIDIA | B65: 百萬顆 | D65: =D63+w_ot*D64 -> 10.64 | E65: =E63+w_ot*E64 -> 15.3 | F65: =F63+w_ot*F64 -> 16.3 | G65: =G63+w_ot*G64 -> 18.42
A66: FY2026 AI 載板營收（錨點電子事業 × AI 占比） | B66: ¥B | D66: =q26_e*ai_e -> 243.75 | H66: Assumed 切分；公司未揭露
A67: 每顆有效金額（Ibiden 份額 × 載板金額；FY2026 校準） | B67: 千日圓／顆 | D67: =D66/D65 -> 22.908835 | H67: Derived：¥B ÷ 百萬顆＝千日圓／顆。÷ 匯率即美元／顆（Units 頁）
A68: 每顆載板金額指數（面積、層數；FY2026＝1） | B68: x | D68: =1 -> 1 | E68: =D68*(1+g_asp) -> 1.18 | F68: =E68*(1+g_asp) -> 1.3924 | G68: =F68*(1+g_asp) -> 1.643032
A69: Ibiden 份額相對值（÷ FY2026） | B69: x | D69: =1 -> 1 | E69: =rel_27 -> 0.95 | F69: =rel_28 -> 0.88 | G69: =rel_29 -> 0.85
A70: 短缺溢價指數（FY2026＝1） | B70: x | D70: =1 -> 1 | E70: =pp_27 -> 1 | F70: =pp_28 -> 0.95 | G70: =pp_29 -> 0.9
A71: AI 伺服器載板營收 | B71: ¥B | D71: =D66 -> 243.75 | E71: =E65*$D$67*E68*E69*E70 -> 392.91629 | F71: =F65*$D$67*F68*F69*F70 -> 434.67123 | G71: =G65*$D$67*G68*G69*G70 -> 530.3958
A72: B. 電子事業
A73: 電子事業非 AI 營收（通用伺服器、PC 等） | B73: ¥B | D73: =q26_e-D71 -> 131.25 | E73: =D73*(1+g_ne) -> 137.8125 | F73: =E73*(1+g_ne) -> 144.70312 | G73: =F73*(1+g_ne) -> 151.93828
A74: 電子事業營收 | B74: ¥B | C74: =q25_e -> 243.316 | D74: =D71+D73 -> 375 | E74: =E71+E73 -> 530.72879 | F74: =F71+F73 -> 579.37435 | G74: =G71+G73 -> 682.33408
A75: AI 載板營業利益率（FY2026 校準） | B75: % | D75: =(q26_eoi-m_ne*D73)/D71 -> 0.37051282 | H75: Derived：使 FY2026 電子事業營業利益＝錨點；非 AI 營益率為 In 頁 m_ne
A76: AI 載板營業利益率 ＝ 1 −（1 − 校準值）÷ 溢價指數 | B76: % | D76: =D75 -> 0.37051282 | E76: =1-(1-$D$75)/E70 -> 0.37051282 | F76: =1-(1-$D$75)/F70 -> 0.33738192 | G76: =1-(1-$D$75)/G70 -> 0.3005698 | H76: Derived：每單位成本不變，價格隨溢價指數升降，差額全部落在利潤
A77: 電子事業營業利益 | B77: ¥B | C77: =q25_eoi -> 45.248 | D77: =D71*D76+D73*m_ne -> 110 | E77: =E71*E76+E73*m_ne -> 166.2524 | F77: =F71*F76+F73*m_ne -> 168.35568 | G77: =G71*G76+G73*m_ne -> 182.2117
A78: 電子事業營益率 | B78: % | C78: =C77/C74 -> 0.18596393 | D78: =D77/D74 -> 0.29333333 | E78: =E77/E74 -> 0.31325302 | F78: =F77/F74 -> 0.29058187 | G78: =G77/G74 -> 0.26704177
A79: C. 陶瓷、其他事業與全公司
A80: 陶瓷事業營收 | B80: ¥B | C80: =q25_cer -> 82.554 | D80: =q26_cer -> 84 | E80: =D80*(1+g_cer) -> 84 | F80: =E80*(1+g_cer) -> 84 | G80: =F80*(1+g_cer) -> 84
A81: 其他事業營收 | B81: ¥B | C81: =q25_oth -> 90.33 | D81: =q26_oth -> 91 | E81: =D81*(1+g_oth) -> 93.73 | F81: =E81*(1+g_oth) -> 96.5419 | G81: =F81*(1+g_oth) -> 99.438157
A82: 營收 | B82: ¥B | C82: =C74+C80+C81 -> 416.2 | D82: =D74+D80+D81 -> 550 | E82: =E74+E80+E81 -> 708.45879 | F82: =F74+F80+F81 -> 759.91625 | G82: =G74+G80+G81 -> 865.77224
A83: 營收年增 | B83: % | D83: =D82/C82-1 -> 0.32148006 | E83: =E82/D82-1 -> 0.2881069 | F83: =F82/E82-1 -> 0.072632957 | G83: =G82/F82-1 -> 0.13929955
A84: AI 伺服器載板 ÷ 營收 | B84: % | D84: =D71/D82 -> 0.44318182 | E84: =E71/E82 -> 0.55460712 | F84: =F71/F82 -> 0.57199886 | G84: =G71/G82 -> 0.61262741
A85: 陶瓷＋其他事業營業利益＋調整 | B85: ¥B | C85: =q25_oi-q25_eoi -> 16.779 | D85: =q26_oi-q26_eoi -> 17 | E85: =E80*m_cer+E81*m_oth+q26_adj -> 17.24695 | F85: =F80*m_cer+F81*m_oth+q26_adj -> 17.570318 | G85: =G80*m_cer+G81*m_oth+q26_adj -> 17.903388
A86: 營業利益 | B86: ¥B | C86: =C77+C85 -> 62.027 | D86: =D77+D85 -> 127 | E86: =E77+E85 -> 183.49935 | F86: =F77+F85 -> 185.926 | G86: =G77+G85 -> 200.11509
A87: 營業利益率 | B87: % | C87: =C86/C82 -> 0.14903172 | D87: =D86/D82 -> 0.23090909 | E87: =E86/E82 -> 0.25901203 | F87: =F86/F82 -> 0.24466643 | G87: =G86/G82 -> 0.23114057
A88: 淨利（歸屬母公司） | B88: ¥B | C88: =q25_ni -> 63.713 | D88: =q26_ni -> 84 | E88: =E86*ni_oi -> 121.29307 | F88: =F86*ni_oi -> 122.89709 | G88: =G86*ni_oi -> 132.27608
A89: 股數（分割後） | B89: 十億股 | D89: =q26_sh -> 0.56119722 | E89: =D89*(1+sh_g) -> 0.56119722 | F89: =E89*(1+sh_g) -> 0.56119722 | G89: =F89*(1+sh_g) -> 0.56119722
A90: EPS（日圓） | B90: ¥ | C90: =q25_eps -> 114.08 | D90: =D88/D89 -> 149.68 | E90: =E88/E89 -> 216.1327 | F90: =F88/F89 -> 218.9909 | G90: =G88/G89 -> 235.70337
A91: EPS 年增 | B91: % | D91: =D90/C90-1 -> 0.31206171 | E91: =E90/D90-1 -> 0.44396512 | F91: =F90/E90-1 -> 0.013224293 | G91: =G90/F90-1 -> 0.076315806
A94: 情境 B：CY2028 顆數 ×0.8、CY2029 ×0.85
A95: 項目 | B95: 單位 | C95: FY2025A | D95: FY2026（錨點） | E95: FY2027 | F95: FY2028 | G95: FY2029 | H95: 說明
A96: A. AI 伺服器載板（D 欄＝FY2026 校準年；FY(t) 對照 CY(t) 顆數）
A97: NVIDIA 加速器顆數 × 情境係數 | B97: 百萬顆 | D97: =(u_bw_26+u_rb_26+u_ru_26+u_hp_26)*1 -> 7.6 | E97: =(u_bw_27+u_rb_27+u_ru_27+u_hp_27)*1 -> 9.7 | F97: =(u_bw_28+u_rb_28+u_ru_28+u_hp_28)*um28_B -> 7.6 | G97: =(u_bw_28*(1+g29_bw)+u_rb_28*(1+g29_rb)+u_ru_28*(1+g29_ru)+u_hp_28*(1+g29_hp))*um29_B -> 9.01 | H97: markets/network In：Blackwell、Rubin、Rubin Ultra、Hopper
A98: 非 NVIDIA 加速器顆數 × 情境係數 | B98: 百萬顆 | D98: =(u_amd_26+u_tpu_26+u_trn_26+u_oth_26)*1 -> 7.6 | E98: =(u_amd_27+u_tpu_27+u_trn_27+u_oth_27)*1 -> 14 | F98: =(u_amd_28+u_tpu_28+u_trn_28+u_oth_28)*um28_B -> 13.6 | G98: =(u_amd_28*(1+g29_amd)+u_tpu_28*(1+g29_tpu)+u_trn_28*(1+g29_trn)+u_oth_28*(1+g29_oth))*um29_B -> 16.6175 | H98: AMD、TPU、Trainium、其他 ASIC
A99: 有效顆數 ＝ NVIDIA ＋ 權重 × 非 NVIDIA | B99: 百萬顆 | D99: =D97+w_ot*D98 -> 10.64 | E99: =E97+w_ot*E98 -> 15.3 | F99: =F97+w_ot*F98 -> 13.04 | G99: =G97+w_ot*G98 -> 15.657
A100: FY2026 AI 載板營收（錨點電子事業 × AI 占比） | B100: ¥B | D100: =q26_e*ai_e -> 243.75 | H100: Assumed 切分；公司未揭露
A101: 每顆有效金額（Ibiden 份額 × 載板金額；FY2026 校準） | B101: 千日圓／顆 | D101: =D100/D99 -> 22.908835 | H101: Derived：¥B ÷ 百萬顆＝千日圓／顆。÷ 匯率即美元／顆（Units 頁）
A102: 每顆載板金額指數（面積、層數；FY2026＝1） | B102: x | D102: =1 -> 1 | E102: =D102*(1+g_asp) -> 1.18 | F102: =E102*(1+g_asp) -> 1.3924 | G102: =F102*(1+g_asp) -> 1.643032
A103: Ibiden 份額相對值（÷ FY2026） | B103: x | D103: =1 -> 1 | E103: =rel_27 -> 0.95 | F103: =rel_28 -> 0.88 | G103: =rel_29 -> 0.85
A104: 短缺溢價指數（FY2026＝1） | B104: x | D104: =1 -> 1 | E104: =pp_27 -> 1 | F104: =pp_28 -> 0.95 | G104: =pp_29 -> 0.9
A105: AI 伺服器載板營收 | B105: ¥B | D105: =D100 -> 243.75 | E105: =E99*$D$101*E102*E103*E104 -> 392.91629 | F105: =F99*$D$101*F102*F103*F104 -> 347.73698 | G105: =G99*$D$101*G102*G103*G104 -> 450.83643
A106: B. 電子事業
A107: 電子事業非 AI 營收（通用伺服器、PC 等） | B107: ¥B | D107: =q26_e-D105 -> 131.25 | E107: =D107*(1+g_ne) -> 137.8125 | F107: =E107*(1+g_ne) -> 144.70312 | G107: =F107*(1+g_ne) -> 151.93828
A108: 電子事業營收 | B108: ¥B | C108: =q25_e -> 243.316 | D108: =D105+D107 -> 375 | E108: =E105+E107 -> 530.72879 | F108: =F105+F107 -> 492.44011 | G108: =G105+G107 -> 602.77471
A109: AI 載板營業利益率（FY2026 校準） | B109: % | D109: =(q26_eoi-m_ne*D107)/D105 -> 0.37051282 | H109: Derived：使 FY2026 電子事業營業利益＝錨點；非 AI 營益率為 In 頁 m_ne
A110: AI 載板營業利益率 ＝ 1 −（1 − 校準值）÷ 溢價指數 | B110: % | D110: =D109 -> 0.37051282 | E110: =1-(1-$D$109)/E104 -> 0.37051282 | F110: =1-(1-$D$109)/F104 -> 0.33738192 | G110: =1-(1-$D$109)/G104 -> 0.3005698 | H110: Derived：每單位成本不變，價格隨溢價指數升降，差額全部落在利潤
A111: 電子事業營業利益 | B111: ¥B | C111: =q25_eoi -> 45.248 | D111: =D105*D110+D107*m_ne -> 110 | E111: =E105*E110+E107*m_ne -> 166.2524 | F111: =F105*F110+F107*m_ne -> 139.02564 | G111: =G105*G110+G107*m_ne -> 158.29856
A112: 電子事業營益率 | B112: % | C112: =C111/C108 -> 0.18596393 | D112: =D111/D108 -> 0.29333333 | E112: =E111/E108 -> 0.31325302 | F112: =F111/F108 -> 0.28231989 | G112: =G111/G108 -> 0.26261646
A113: C. 陶瓷、其他事業與全公司
A114: 陶瓷事業營收 | B114: ¥B | C114: =q25_cer -> 82.554 | D114: =q26_cer -> 84 | E114: =D114*(1+g_cer) -> 84 | F114: =E114*(1+g_cer) -> 84 | G114: =F114*(1+g_cer) -> 84
A115: 其他事業營收 | B115: ¥B | C115: =q25_oth -> 90.33 | D115: =q26_oth -> 91 | E115: =D115*(1+g_oth) -> 93.73 | F115: =E115*(1+g_oth) -> 96.5419 | G115: =F115*(1+g_oth) -> 99.438157
A116: 營收 | B116: ¥B | C116: =C108+C114+C115 -> 416.2 | D116: =D108+D114+D115 -> 550 | E116: =E108+E114+E115 -> 708.45879 | F116: =F108+F114+F115 -> 672.98201 | G116: =G108+G114+G115 -> 786.21287
A117: 營收年增 | B117: % | D117: =D116/C116-1 -> 0.32148006 | E117: =E116/D116-1 -> 0.2881069 | F117: =F116/E116-1 -> -0.050076008 | G117: =G116/F116-1 -> 0.16825244
A118: AI 伺服器載板 ÷ 營收 | B118: % | D118: =D105/D116 -> 0.44318182 | E118: =E105/E116 -> 0.55460712 | F118: =F105/F116 -> 0.51671067 | G118: =G105/G116 -> 0.57342795
A119: 陶瓷＋其他事業營業利益＋調整 | B119: ¥B | C119: =q25_oi-q25_eoi -> 16.779 | D119: =q26_oi-q26_eoi -> 17 | E119: =E114*m_cer+E115*m_oth+q26_adj -> 17.24695 | F119: =F114*m_cer+F115*m_oth+q26_adj -> 17.570318 | G119: =G114*m_cer+G115*m_oth+q26_adj -> 17.903388
A120: 營業利益 | B120: ¥B | C120: =C111+C119 -> 62.027 | D120: =D111+D119 -> 127 | E120: =E111+E119 -> 183.49935 | F120: =F111+F119 -> 156.59596 | G120: =G111+G119 -> 176.20195
A121: 營業利益率 | B121: % | C121: =C120/C116 -> 0.14903172 | D121: =D120/D116 -> 0.23090909 | E121: =E120/E116 -> 0.25901203 | F121: =F120/F116 -> 0.23268966 | G121: =G120/G116 -> 0.22411481
A122: 淨利（歸屬母公司） | B122: ¥B | C122: =q25_ni -> 63.713 | D122: =q26_ni -> 84 | E122: =E120*ni_oi -> 121.29307 | F122: =F120*ni_oi -> 103.50993 | G122: =G120*ni_oi -> 116.46949
A123: 股數（分割後） | B123: 十億股 | D123: =q26_sh -> 0.56119722 | E123: =D123*(1+sh_g) -> 0.56119722 | F123: =E123*(1+sh_g) -> 0.56119722 | G123: =F123*(1+sh_g) -> 0.56119722
A124: EPS（日圓） | B124: ¥ | C124: =q25_eps -> 114.08 | D124: =D122/D123 -> 149.68 | E124: =E122/E123 -> 216.1327 | F124: =F122/F123 -> 184.44483 | G124: =G122/G123 -> 207.53753
A125: EPS 年增 | B125: % | D125: =D124/C124-1 -> 0.31206171 | E125: =E124/D124-1 -> 0.44396512 | F125: =F124/E124-1 -> -0.14661302 | G125: =G124/F124-1 -> 0.12520113
...

Sheet Val
A1: Val — P/E 估值（日圓）。結論用「現價 ÷ FY2026–FY2028 EPS（模型）」與 what must be true。十年 P/E 規則值待 Bloomberg（10-27 抓取單加 4062）：公開資料商的 Ibiden 十年 P/E 本版未取得，規則值本版不計
A2: 循環位置：Ibiden 不套設備股見頂年；以本模型營收最高的會計年度為見頂年（比照 NVIDIA、Arista）。營收到 FY2029 仍在增加時，見頂年未知，判為中段
A3: 目標價：見第 0 節（本頁第 61 列；v0.2 新增，DCF 與 Comparable 加權）。第 36 列「舊法：規則值情境加權（參考）」不再是目標價，只作參考
A4: 1. 價格與市場隱含倍數
A5: 項目 | B5: A | C5: B | D5: C | E5: 說明
A6: 現價（2026-10-23 收盤，分割後） | B6: =px -> 8512
A7: 現價 ÷ FY2026 EPS（錨點） | B7: =px/PL!D12 -> 56.867985 | C7: =px/PL!D23 -> 56.867985 | D7: =px/PL!D34 -> 56.867985
A8: 現價 ÷ FY2027 EPS（模型） | B8: =px/PL!E12 -> 39.383212 | C8: =px/PL!E23 -> 39.383212 | D8: =px/PL!E34 -> 39.383212 | E8: FY2027 三情境相同（顆數係數從 CY2028 開始）
A9: 現價 ÷ FY2028 EPS（模型） | B9: =px/PL!F12 -> 38.869195 | C9: =px/PL!F23 -> 46.149301 | D9: =px/PL!F34 -> 56.784992
A10: 現價 ÷ FY2029 EPS（模型） | B10: =px/PL!G12 -> 36.113188 | C10: =px/PL!G23 -> 41.014268 | D10: =px/PL!G34 -> 53.003069
A11: 前瞻 P/E（stockanalysis） | B11: =pe_fwd_sa -> 53.97 | E11: 口徑：未來 12 個月
A12: 隱含未來 12 月 EPS ＝ 取得時價格（10-16 9,764）÷ 前瞻 P/E | B12: =cons_feps -> 180.91532
A13: 近 12 月 P/E（stockanalysis） | B13: =pe_ttm -> 83.85
A15: 2. 循環位置（本模型營收最高年）
A16: 情境 | B16: 營收最高年（FY2026–FY2029） | C16: FY2027 判定 | D16: 見頂年是否未知 | E16: 說明
A17: A | B17: =INDEX({2026,2027,2028,2029},MATCH(MAX(PL!D82:G82),PL!D82:G82,0)) -> 2029 | C17: =IF(B17=2029,"中段",IF(2027<B17,"中段",IF(2027=B17,"見頂","谷底"))) -> 中段 | D17: =IF(B17=2029,"是：營收到觀測期末仍在增加","否") -> 是：營收到觀測期末仍在增加 | E17: tools/cycle_position.py excel_rule；營收最高年取代設備市場見頂年；對應倍數待十年 P/E
A18: B | B18: =INDEX({2026,2027,2028,2029},MATCH(MAX(PL!D116:G116),PL!D116:G116,0)) -> 2029 | C18: =IF(B18=2029,"中段",IF(2027<B18,"中段",IF(2027=B18,"見頂","谷底"))) -> 中段 | D18: =IF(B18=2029,"是：營收到觀測期末仍在增加","否") -> 是：營收到觀測期末仍在增加 | E18: 同上
A19: C | B19: =INDEX({2026,2027,2028,2029},MATCH(MAX(PL!D150:G150),PL!D150:G150,0)) -> 2027 | C19: =IF(B19=2029,"中段",IF(2027<B19,"中段",IF(2027=B19,"見頂","谷底"))) -> 見頂 | D19: =IF(B19=2029,"是：營收到觀測期末仍在增加","否") -> 否 | E19: 同上
A21: 3. What must be true：FY2027 年底價 ＝ 現價 ×（1＋報酬）所需的倍數（看 FY2028 EPS）
A22: FY2027 年底價 ÷ 現價 | B22: 所需倍數（÷ FY2028 EPS，A） | C22: 所需倍數（÷ FY2028 EPS，B） | D22: 所需倍數（÷ FY2028 EPS，C） | E22: 對照：Andy 合理 P/E
A23: 0.5 | B23: =px*A23/PL!F12 -> 19.434597 | C23: =px*A23/PL!F23 -> 23.07465 | D23: =px*A23/PL!F34 -> 28.392496 | E23: =pe_fair_andy -> 25
A24: 0.75 | B24: =px*A24/PL!F12 -> 29.151896 | C24: =px*A24/PL!F23 -> 34.611975 | D24: =px*A24/PL!F34 -> 42.588744 | E24: =pe_fair_andy -> 25
A25: 1 | B25: =px*A25/PL!F12 -> 38.869195 | C25: =px*A25/PL!F23 -> 46.149301 | D25: =px*A25/PL!F34 -> 56.784992 | E25: =pe_fair_andy -> 25
A26: 1.21 | B26: =px*A26/PL!F12 -> 47.031726 | C26: =px*A26/PL!F23 -> 55.840654 | D26: =px*A26/PL!F34 -> 68.70984 | E26: =pe_fair_andy -> 25
A27: 1.5 | B27: =px*A27/PL!F12 -> 58.303792 | C27: =px*A27/PL!F23 -> 69.223951 | D27: =px*A27/PL!F34 -> 85.177487 | E27: =pe_fair_andy -> 25
A28: 讀法：1.00＝價格不變、1.21＝一年約 21%。所需倍數愈高，現價愈依賴「短缺溢價延續到 2028 年以後」。
A30: 4. 對照：以 Andy 合理 P/E 25x 計算的隱含價（只作對照，非規則值）
A31: 情境 | B31: FY2027 EPS | C31: × 25x | D31: 相對現價 | E31: FY2028 EPS | F31: × 25x | G31: 相對現價
A32: A | B32: =PL!E12 -> 216.1327 | C32: =B32*pe_fair_andy -> 5403.3175 | D32: =C32/px-1 -> -0.36521176 | E32: =PL!F12 -> 218.9909 | F32: =E32*pe_fair_andy -> 5474.7725 | G32: =F32/px-1 -> -0.35681714
A33: B | B33: =PL!E23 -> 216.1327 | C33: =B33*pe_fair_andy -> 5403.3175 | D33: =C33/px-1 -> -0.36521176 | E33: =PL!F23 -> 184.44483 | F33: =E33*pe_fair_andy -> 4611.1208 | G33: =F33/px-1 -> -0.45827998
A34: C | B34: =PL!E34 -> 216.1327 | C34: =B34*pe_fair_andy -> 5403.3175 | D34: =C34/px-1 -> -0.36521176 | E34: =PL!F34 -> 149.89876 | F34: =E34*pe_fair_andy -> 3747.4691 | G34: =F34/px-1 -> -0.55974282
A36: 舊法：規則值情境加權（參考；v0.1.1 的「0. 目標價與上檔空間」改名，不再是目標價）
A37: 項目 | B37: 數值 | E37: 說明
A38: 舊法隱含價（情境加權，參考） | B38: =tp_wA*B40+tp_wB*B41+tp_wC*B42 -> 9531.452 | E38: 權重 × 各情境隱含價
A39: 舊法隱含價相對現價（÷ 現價 − 1） | B39: =B38/px-1 -> 0.11976645 | E39: 現價＝In 頁 px（2026-10-23 收盤，分割後）
A40: 情境 A 隱含價（樂觀） | B40: =$B$58*PL!E12 -> 9531.452 | E40: 情境 A FY2027 EPS（PL 頁）× 十年 P/E 中位數（第 0a 節）
A41: 情境 B 隱含價（基準） | B41: =$B$58*PL!E23 -> 9531.452 | E41: 情境 B FY2027 EPS（PL 頁）× 十年 P/E 中位數（第 0a 節）
A42: 情境 C 隱含價（下檔） | B42: =$B$58*PL!E34 -> 9531.452 | E42: 情境 C FY2027 EPS（PL 頁）× 十年 P/E 中位數（第 0a 節）
A43: 情境權重 A／B／C | B43: =tp_wA -> 0.3 | C43: =tp_wB -> 0.5 | D43: =tp_wC -> 0.2 | E43: ="合計 "&TEXT(B43+C43+D43,"0%")&"；In 頁 tp_wA／tp_wB／tp_wC（Assumed，Andy 可改）" -> 合計 100%；In 頁 tp_wA／tp_wB／tp_wC（Assumed，Andy 可改）
A44: 舊法說明 | B44: P/E：十年（2016–2025 日曆年年底）P/E 中位數（companiesmarketcap 單一來源，第 0a 節；2017 年虧損不計，9 年）× 各情境 FY2027 EPS（FY2027＝2027-04～2028-03）。本模型無規則值（十年 P/E 待 Bloomberg），依工作單改用此備案；倍數為日曆年年底口徑，與 3 月制會計年度不完全對齊。十年倍數多為 AI 載板需求前的時期（2019 年獲利低谷約 137x 為極值，中位數受影響小），偏誤方向不明確；FY2027 三情境 EPS 相同（情境差從 FY2028 起），故三情境隱含價相同；隱含價約為 FY2027 年底（2028-03）的價格、未折現，當作 12 個月目標價時偏高。
A46: 0a. 十年 P/E（舊法用；companiesmarketcap 日曆年年底 P/E，Interested-party，資料商；第二來源：未找到）
A47: 年底 | B47: P/E | C47: 計入中位數 | D47: 說明
A48: 2016 | B48: 44.1 | C48: 是 | D48: https://companiesmarketcap.com/ibiden/pe-ratio/（2026-10-25 讀取）
A49: 2017 | B49: -6.66 | C49: 否 | D49: 虧損年，P/E 為負，不計
A50: 2018 | B50: 35.3 | C50: 是
A51: 2019 | B51: 137 | C51: 是
A52: 2020 | B52: 55.2 | C52: 是
A53: 2021 | B53: 53.1 | C53: 是
A54: 2022 | B54: 40.7 | C54: 是
A55: 2023 | B55: 26.8 | C55: 是
A56: 2024 | B56: 57.2 | C56: 是
A57: 2025 | B57: 33.6 | C57: 是
A58: 中位數（計入者） | B58: =MEDIAN(B48,B50,B51,B52,B53,B54,B55,B56,B57) -> 44.1
A61: 0. 目標價（DCF 與 Comparable 加權；v0.2 新增，放在本頁既有內容之後以免位移既有儲存格；三情境欄 B／C／D＝A 順利／B 平平／C 不如預期）
A62: 0.1 DCF（股東權益現金流，FY2027–FY2032 明確期＋FY2032 後永續）
A63: 項目 | B63: A（順利） | C63: B（平平） | D63: C（不如預期） | E63: 說明
A64: 情境 EPS（FY2027–FY2032） | E64: PL 頁延伸表；FY2030 起為收斂法
A65: FY2027 | B65: =PL!E170 -> 216.1327 | C65: =PL!E182 -> 216.1327 | D65: =PL!E194 -> 216.1327
A66: FY2028 | B66: =PL!F170 -> 218.9909 | C66: =PL!F182 -> 184.44483 | D66: =PL!F194 -> 149.89876
A67: FY2029 | B67: =PL!G170 -> 235.70337 | C67: =PL!G182 -> 207.53753 | D67: =PL!G194 -> 160.59448
A68: FY2030 | B68: =PL!H170 -> 262.30635 | C68: =PL!H182 -> 225.7977 | D68: =PL!H194 -> 162.40796
A69: FY2031 | B69: =PL!I170 -> 284.97832 | C69: =PL!I182 -> 236.05221 | D69: =PL!I194 -> 158.61374
A70: FY2032 | B70: =PL!J170 -> 302.07702 | C70: =PL!J182 -> 236.72665 | D70: =PL!J194 -> 149.34094
A71: 股東現金流＝EPS ×（1 − tp_g ÷ tp_roe）
A72: 再投資率（tp_g ÷ tp_roe，上限 0.8） | B72: =MIN(tp_g/tp_roe,0.8) -> 0.46439628 | E72: ROE 為近三年平均（In 頁 tp_roe）
A73: FY2027 | B73: =B65*(1-$B$72) -> 115.76148 | C73: =C65*(1-$B$72) -> 115.76148 | D73: =D65*(1-$B$72) -> 115.76148
A74: FY2028 | B74: =B66*(1-$B$72) -> 117.29234 | C74: =C66*(1-$B$72) -> 98.789337 | D74: =D66*(1-$B$72) -> 80.286334
A75: FY2029 | B75: =B67*(1-$B$72) -> 126.2436 | C75: =C67*(1-$B$72) -> 111.15787 | D75: =D67*(1-$B$72) -> 86.014998
A76: FY2030 | B76: =B68*(1-$B$72) -> 140.49226 | C76: =C68*(1-$B$72) -> 120.93809 | D76: =D68*(1-$B$72) -> 86.986306
A77: FY2031 | B77: =B69*(1-$B$72) -> 152.63545 | C77: =C69*(1-$B$72) -> 126.43044 | D77: =D69*(1-$B$72) -> 84.954111
A78: FY2032 | B78: =B70*(1-$B$72) -> 161.79358 | C78: =C70*(1-$B$72) -> 126.79167 | D78: =D70*(1-$B$72) -> 79.987563
A79: DCF 情境每股價值（折現率 tp_r） | B79: =SUMPRODUCT(B73:B78,1/(1+tp_r)^{1;2;3;4;5;6})+B78*(1+tp_g)/(tp_r-tp_g)/(1+tp_r)^6 -> 2162.1063 | C79: =SUMPRODUCT(C73:C78,1/(1+tp_r)^{1;2;3;4;5;6})+C78*(1+tp_g)/(tp_r-tp_g)/(1+tp_r)^6 -> 1743.6296 | D79: =SUMPRODUCT(D73:D78,1/(1+tp_r)^{1;2;3;4;5;6})+D78*(1+tp_g)/(tp_r-tp_g)/(1+tp_r)^6 -> 1176.1434 | E79: Σ 明確期現金流 ÷ (1＋r)^t ＋ 永續價值 ÷ (1＋r)^6；永續價值＝FY2032 現金流 ×(1＋g)÷(r−g)；基準日 2026 年底，t＝1 對 FY2027
A80: DCF 情境價值推到 12 個月後（×(1＋tp_r)） | B80: =B79*(1+tp_r) -> 2378.3169 | C80: =C79*(1+tp_r) -> 1917.9925 | D80: =D79*(1+tp_r) -> 1293.7578
A81: DCF 目標價（情境加權） | B81: =tp_wA*B80+tp_wB*C80+tp_wC*D80 -> 1931.2429 | E81: Σ tp_wA／wB／wC × 情境價值 ×(1＋tp_r)；權重見 In 頁
A83: 0.2 Comparable（市場主流同業前瞻 P/E）
A84: 同業與前瞻 P/E | B84: 代號 | C84: 前瞻 12 月 P/E | D84: 日期 | E84: 來源 | F84: 標記
A85: 欣興（Unimicron） | B85: 3037.TW | C85: 42.28 | D85: 2026-10-22 | E85: stockanalysis.com 個股頁 Forward PE（分析師共識；價格日期如左） | F85: Interested-party（賣方共識）
A86: 南電（Nan Ya PCB） | B86: 8046.TW | C86: 33.73 | D86: 2026-09-07 | E86: stockanalysis.com 個股頁 Forward PE（分析師共識；價格日期如左） | F86: Interested-party（賣方共識）
A87: 景碩（Kinsus） | B87: 3189.TW | C87: 44.7 | D87: 2026-10-22 | E87: stockanalysis.com 個股頁 Forward PE（分析師共識；價格日期如左） | F87: Interested-party（賣方共識）
A88: 三星電機（Samsung Electro-Mechanics） | B88: 009150.KS | C88: 43.4 | D88: 2026-08-28 | E88: stockanalysis.com 個股頁 Forward PE（分析師共識；價格日期如左） | F88: Interested-party（賣方共識）
A89: AT&S | B89: ATS.VI | C89: 14.91 | D89: 2026-10-23 | E89: stockanalysis.com 個股頁 Forward PE（分析師共識；價格日期如左） | F89: Interested-party（賣方共識）
A90: 同業前瞻 P/E 中位數 | B90: =MEDIAN(C85:C89) -> 42.28 | E90: ABF／FC-BGA 載板同業：欣興、南電、景碩、三星電機、AT&S（券商常用的載板比較組；新光電氣 2025 年下市未列）。非 A 股公司的同業名單不放中國 A 股（A 股有結構性溢價；Andy 2026-10-25 11:53）
A91: 12 個月後的前瞻 EPS（情境加權） | B91: =tp_wA*(0.5*B65+0.5*B66)+tp_wB*(0.5*C65+0.5*C66)+tp_wC*(0.5*D65+0.5*D66) -> 202.01607 | E91: 會計年度 4 月至隔年 3 月：約 2027-10 時的未來 12 月（2027-10～2028-09）≈ 6／12 × FY2027＋6／12 × FY2028
A92: Comparable 目標價 | B92: =B90*B91 -> 8541.2394 | E92: 同業中位數 × 上列 EPS
A94: 0.3 結論
A95: 項目 | B95: 數值 | E95: 說明
A96: 目標價（DCF 與 Comparable 加權） | B96: =tp_w_dcf*B81+(1-tp_w_dcf)*B92 -> 5236.2411 | E96: tp_w_dcf × DCF 目標價＋（1 − tp_w_dcf）× Comparable 目標價；tp_w_dcf 見 In 頁
A97: Comparable 目標價（市場主流同業法） | B97: =B92 -> 8541.2394 | E97: 引用 0.2
A98: 市場共識目標價 | B98: =cons_tp -> 12432.35 | E98: stockanalysis 個股頁（S&P Global 彙整）18 位分析師平均目標價 12,432（頁面價格日期 2026-10-16；分割後）
A99: 上檔空間：加權目標價 | B99: =B96/px-1 -> -0.38484009 | E99: 現價＝In 頁 px（2026-10-23 收盤 8,512，分割後）
A100: 上檔空間：Comparable 目標價 | B100: =B97/px-1 -> 0.0034350801
A101: 與市場共識目標價的差距：EPS 因素 | B101: =B91/cons_feps-1 -> 0.11663327 | E101: 本模型前瞻 EPS ÷ 共識前瞻 EPS − 1；共識前瞻 EPS 見 In 頁 cons_feps 與 Recon
A102: 與市場共識目標價的差距：倍數因素 | B102: =(cons_tp/cons_feps)/B90-1 -> 0.62533503 | E102: ="共識目標價 ÷ 共識前瞻 EPS 隱含 "&TEXT(cons_tp/cons_feps,"0.0")&"x，同業中位數 "&TEXT(B90,"0.0")&"x" -> 共識目標價 ÷ 共識前瞻 EPS 隱含 68.7x，同業中位數 42.3x
A103: 價格帶（DCF 不如預期～順利） | B103: =TEXT(D80,"#,##0")&"～"&TEXT(B80,"#,##0") -> 1,294～2,378 | E103: C 情境價值～A 情境價值（推到 12 個月後）
A104: 歷史倍數檢查：現價隱含 P/E 的十年分位（A／B／C） | B104: =IF(px/B66<=MIN($B$108:$K$108),0,IF(px/B66>=MAX($B$108:$K$108),1,PERCENTRANK($B$108:$K$108,px/B66))) -> 0.333 | C104: =IF(px/C66<=MIN($B$108:$K$108),0,IF(px/C66>=MAX($B$108:$K$108),1,PERCENTRANK($B$108:$K$108,px/C66))) -> 0.528 | D104: =IF(px/D66<=MIN($B$108:$K$108),0,IF(px/D66>=MAX($B$108:$K$108),1,PERCENTRANK($B$108:$K$108,px/D66))) -> 0.849 | E104: 現價 ÷ 各情境 FY2028 EPS 在 2016–2025 年底 P/E 分布（下方列）的分位；低於最小值記 0%、高於最大值記 100%；只作檢查，不進目標價
A105: 目標價方法 | B105: DCF：股東現金流＝EPS ×（1 − g／ROE），r＝10%、g＝4%、ROE＝近三年平均約 8.6%（再投資率約 46%），FY2027–29 驅動因子、FY2030–32 收斂法＋永續；基準日 2026 年底（FY2027 實際於 2028-03 結束，未做半年調整）。Ibiden 資本密集（FY2026 設備投資 2,100 億），但模型無折舊與資本支出明細，未改用淨利＋折舊－資本支出，現金流偏高估。Comparable：欣興、南電、景碩、三星電機、AT&S 前瞻 P/E 中位數；台系載板股含 AI 題材溢價（約 34–45x），部分價格為 8–9 月，偏高估。情境對應：A＝順利、B＝平平、C＝不如預期（原顆數情境）。
A107: 十年年底 P/E（歷史分位檢查用；companiesmarketcap 日曆年年底 P/E，Interested-party；2017 年虧損不計） | B107: 2016 | C107: 2017 | D107: 2018 | E107: 2019 | F107: 2020 | G107: 2021 | H107: 2022 | I107: 2023 | J107: 2024 | K107: 2025
A108: 年底 P/E | B108: 44.1 | D108: 35.3 | E108: 137 | F108: 55.2 | G108: 53.1 | H108: 40.7 | I108: 26.8 | J108: 57.2 | K108: 33.6

Sheet Recon
A1: Recon — 本模型 vs 公司目標、研調份額、先驗。只作事後對照，不為對上數字而調參數。FY2027 以後的共識：未找到（付費）
A3: 項目 | B3: 對照值 | C3: 模型 A | D3: 差距 A | E3: 模型 B | F3: 差距 B | G3: 模型 C | H3: 差距 C | I3: 對照來源 | J3: 說明
A4: A. 公司目標與市場（校準未使用）
A5: FY2029 營收 vs 公司 FY2030 目標 ¥1 兆 | B5: =tgt30_rev -> 1000 | C5: =PL!G82 -> 865.77224 | D5: =C5/B5-1 -> -0.13422776 | E5: =PL!G116 -> 786.21287 | F5: =E5/B5-1 -> -0.21378713 | G5: =PL!G150 -> 653.61392 | H5: =G5/B5-1 -> -0.34638608 | I5: Quartr 摘要（Interested-party） | J5: 模型到 FY2029；目標年晚一年
A6: FY2029 營業利益 vs 公司 FY2030 目標 ¥3,000 億 | B6: =tgt30_oi -> 300 | C6: =PL!G86 -> 200.11509 | D6: =C6/B6-1 -> -0.3329497 | E6: =PL!G120 -> 176.20195 | F6: =E6/B6-1 -> -0.41266018 | G6: =PL!G154 -> 136.34671 | H6: =G6/B6-1 -> -0.54551098 | I6: 同上
A7: FY2027 EPS vs 前瞻 P/E 隱含未來 12 月 EPS | B7: =cons_feps -> 180.91532 | C7: =PL!E90 -> 216.1327 | D7: =C7/B7-1 -> 0.19466221 | E7: =PL!E124 -> 216.1327 | F7: =E7/B7-1 -> 0.19466221 | G7: =PL!E158 -> 216.1327 | H7: =G7/B7-1 -> 0.19466221 | I7: stockanalysis（推導） | J7: 未來 12 月 ≈ ½ FY2026＋½ FY2027，口徑不同，只作量級比較
A8: B. 份額與每顆金額（先驗比對的機制檢查）
A9: FY2026 每顆 NVIDIA 載板金額（美元）vs 先驗比對推導中點 $225 | B9: 225 | C9: =Units!C8 -> 215.3086 | D9: =C9/B9-1 -> -0.043072908 | E9: =Units!C8 -> 215.3086 | F9: =E9/B9-1 -> -0.043072908 | G9: =Units!C8 -> 215.3086 | H9: =G9/B9-1 -> -0.043072908 | I9: 先驗比對_Ibiden（Drive） | J9: 推導區間 $150–300；封裝全部（中介層＋載板＋組裝）B200 約 $1,100（Silicon Analysts）
A10: FY2026 每 GW Ibiden 營收（US$M）vs 先驗比對推導中點 75 | B10: 75 | C10: =Units!C12 -> 77.096949 | D10: =C10/B10-1 -> 0.027959321 | E10: =Units!C12 -> 77.096949 | F10: =E10/B10-1 -> 0.027959321 | G10: =Units!C12 -> 77.096949 | H10: =G10/B10-1 -> 0.027959321 | I10: 先驗比對_Ibiden（Drive）
A11: FY2027 AI 載板 ÷ 營收 | C11: =PL!E84 -> 0.55460712 | E11: =PL!E118 -> 0.55460712 | G11: =PL!E152 -> 0.55460712 | I11: —
A12: FY2028 電子事業營益率 vs FY2026 錨點（百分點） | B12: =q26_eoi/q26_e -> 0.29333333 | C12: =PL!F78 -> 0.29058187 | D12: =C12-B12 -> -0.0027514674 | E12: =PL!F112 -> 0.28231989 | F12: =E12-B12 -> -0.011013441 | G12: =PL!F146 -> 0.27051544 | H12: =G12-B12 -> -0.022817895 | I12: 錨點 | J12: 短缺溢價回落使營益率下滑
A13: C. 預留
A14: 產能上限（Ibiden 2028 年為 2024 年 2.5–2.8 倍）與需求面積的對照：2024 年基準面積未找到，本版不計 | J14: 預留列：本版無數值
A15: R4 產業部署路徑（markets/deploy_path/，尚未建立）：上線後以 AI 載板營收 ÷ 部署 GW 取代 Units 頁的每 GW 換算 | J15: 預留列：本版無數值
A17: E. 目標價對帳（v0.2；模型欄為情境加權值，非情境 A）
A18: 12 個月後的前瞻 EPS（情境加權）vs 共識前瞻 EPS | B18: =cons_feps -> 180.91532 | C18: =Val!B91 -> 202.01607 | D18: =C18/B18-1 -> 0.11663327 | I18: stockanalysis 個股頁 2026-10-16：價格 9,764 ÷ Forward PE 53.97（即 In 頁 pe_fwd_sa） | J18: 共識只作對帳，不作校準
A19: 目標價（DCF 與 Comparable 加權）vs 市場共識目標價 | B19: =cons_tp -> 12432.35 | C19: =Val!B96 -> 5236.2411 | D19: =C19/B19-1 -> -0.57882129 | I19: stockanalysis 個股頁（S&P Global 彙整）18 位分析師平均目標價 12,432（頁面價格日期 2026-10-16；分割後） | J19: 共識只作對帳，不作校準
A20: Comparable 目標價 vs 市場共識目標價 | B20: =cons_tp -> 12432.35 | C20: =Val!B92 -> 8541.2394 | D20: =C20/B20-1 -> -0.31298271 | I20: 同上 | J20: 共識只作對帳，不作校準

Sheet Sens
A1: Sens — 一次動一個輸入（情境 A；每顆有效金額與 AI 載板營益率在每個案例內依 FY2026 錨點重算，FY2026 恆等於錨點）：對 FY2027、FY2028 的營收、AI 載板營收、電子事業營益率與 EPS 的影響。每個案例是一個完整推導區塊（本頁下方）
A3: 案例 | B3: 設定 | C3: FY2027 營收 | D3: FY2027 AI 載板 | E3: FY2027 電子營益率 | F3: FY2027 EPS | G3: FY2027 EPS 相對基準 | H3: FY2028 營收 | I3: FY2028 AI 載板 | J3: FY2028 電子營益率 | K3: FY2028 EPS | L3: FY2028 EPS 相對基準
A4: 基準（情境 A） | B4: PL 區塊 A | C4: =PL!E82 -> 708.45879 | D4: =PL!E71 -> 392.91629 | E4: =PL!E78 -> 0.31325302 | F4: =PL!E90 -> 216.1327 | G4: =F4/F$4-1 -> 0 | H4: =PL!F82 -> 759.91625 | I4: =PL!F71 -> 434.67123 | J4: =PL!F78 -> 0.29058187 | K4: =PL!F90 -> 218.9909 | L4: =K4/K$4-1 -> 0
A5: 溢價快速回落 | B5: 價格溢價 2027 0.95、2028 0.85、2029 0.75（新產能提早到位） | C5: =E62 -> 688.81298 | D5: =E51 -> 373.27048 | E5: =E58 -> 0.28685476 | F5: =E70 -> 192.99309 | G5: =F5/F$4-1 -> -0.10706204 | H5: =F62 -> 714.16139 | I5: =F51 -> 388.91636 | J5: =F58 -> 0.22975326 | K5: =F70 -> 165.09903 | L5: =K5/K$4-1 -> -0.24609181
A6: 溢價延續 | B6: 價格溢價 2027 1.05、2028 1.05、2029 1.00 | C6: =E96 -> 728.10461 | D6: =E85 -> 412.56211 | E6: =E92 -> 0.3377667 | F6: =E104 -> 239.27231 | G6: =F6/F$4-1 -> 0.10706204 | H6: =F96 -> 805.67112 | I6: =F85 -> 480.42609 | J6: =F92 -> 0.34250606 | K6: =F104 -> 272.88277 | L6: =K6/K$4-1 -> 0.24609181
A7: 份額流失（低） | B7: 份額相對值 2027 0.85、2028 0.75、2029 0.70（欣興、三星電機加速） | C7: =E130 -> 667.09918 | D7: =E119 -> 351.55668 | E7: =E126 -> 0.30841364 | F7: =E138 -> 198.08318 | G7: =F7/F$4-1 -> -0.083511281 | H7: =F130 -> 695.70346 | I7: =F119 -> 370.45843 | J7: =F126 -> 0.28474843 | K7: =F138 -> 193.47392 | L7: =K7/K$4-1 -> -0.11652074
A8: 份額持平（高） | B8: 份額相對值 1.00 | C8: =E164 -> 729.1386 | D8: =E153 -> 413.5961 | E8: =E160 -> 0.31540047 | F8: =E172 -> 225.15746 | G8: =F8/F$4-1 -> 0.04175564 | H8: =F164 -> 819.1896 | I8: =F153 -> 493.94458 | J8: =F160 -> 0.29492541 | K8: =F172 -> 242.54504 | L8: =K8/K$4-1 -> 0.10755761
A9: 每顆金額年增 10% | B9: 面積、層數成長較慢 | C9: =E198 -> 681.8204 | D9: =E187 -> 366.2779 | E9: =E194 -> 0.31022716 | F9: =E206 -> 204.50759 | G9: =F9/F$4-1 -> -0.053786927 | H9: =F198 -> 702.97569 | I9: =F187 -> 377.73067 | J9: =F194 -> 0.28548108 | K9: =F206 -> 196.36377 | L9: =K9/K$4-1 -> -0.10332452
A10: 每顆金額年增 22% | B10: 較快 | C10: =E232 -> 721.77799 | D10: =E221 -> 406.23549 | E10: =E228 -> 0.31465484 | F10: =E240 -> 221.94526 | G10: =F10/F$4-1 -> 0.026893463 | H10: =F232 -> 789.88497 | I10: =F221 -> 464.63994 | J10: =F228 -> 0.29288359 | K10: =F240 -> 230.89992 | L10: =K10/K$4-1 -> 0.054381326
A11: 非 NVIDIA 權重 0.2 | B11: ASIC 多由其他載板廠供應 | C11: =E266 -> 690.05422 | D11: =E255 -> 374.51172 | E11: =E262 -> 0.31119604 | F11: =E274 -> 208.10086 | G11: =F11/F$4-1 -> -0.03716161 | H11: =F266 -> 726.58257 | I11: =F255 -> 401.33754 | J11: =F262 -> 0.2877249 | K11: =F274 -> 205.74471 | L11: =K11/K$4-1 -> -0.060487409
A12: 非 NVIDIA 權重 0.6 | B12: Ibiden 在 ASIC 份額較高 | C12: =E300 -> 722.26223 | D12: =E289 -> 406.71973 | E12: =E296 -> 0.31470451 | F12: =E308 -> 222.15658 | G12: =F12/F$4-1 -> 0.027871208 | H12: =F300 -> 784.91651 | I12: =F289 -> 459.67149 | J12: =F296 -> 0.29251777 | K12: =F308 -> 228.92555 | L12: =K12/K$4-1 -> 0.045365556
A13: AI 占電子事業 55% | B13: FY2026 切分較低（校準跟著變） | C13: =E334 -> 687.38513 | D13: =E323 -> 332.46763 | E13: =E330 -> 0.32000335 | F13: =E342 -> 212.40949 | G13: =F13/F$4-1 -> -0.017226487 | H13: =F334 -> 734.38751 | I13: =F323 -> 367.79873 | J13: =F330 -> 0.30246341 | K13: =F342 -> 218.00429 | L13: =K13/K$4-1 -> -0.0045052744
A14: AI 占電子事業 75% | B14: 較高 | C14: =E368 -> 729.53246 | D14: =E357 -> 453.36496 | E14: =E364 -> 0.30701829 | F14: =E376 -> 219.85591 | G14: =F14/F$4-1 -> 0.017226487 | H14: =F368 -> 785.445 | I14: =F357 -> 501.54372 | J14: =F364 -> 0.27970319 | K14: =F376 -> 219.97752 | L14: =K14/K$4-1 -> 0.0045052744
A15: 非 AI 營益率 10% | B15: 校準後 AI 載板營益率較高 | C15: =E402 -> 708.45879 | D15: =E391 -> 392.91629 | E15: =E398 -> 0.32020175 | F15: =E410 -> 220.47644 | G15: =F15/F$4-1 -> 0.020097568 | H15: =F402 -> 759.91625 | I15: =F391 -> 434.67123 | J15: =F398 -> 0.29935592 | K15: =F410 -> 224.9784 | L15: =K15/K$4-1 -> 0.027341316
A16: 非 AI 營益率 20% | B16: 較低 | C16: =E436 -> 708.45879 | D16: =E425 -> 392.91629 | E16: =E432 -> 0.30630429 | F16: =E444 -> 211.78896 | G16: =F16/F$4-1 -> -0.020097568 | H16: =F436 -> 759.91625 | I16: =F425 -> 434.67123 | J16: =F432 -> 0.28180781 | K16: =F444 -> 213.0034 | L16: =K16/K$4-1 -> -0.027341316
A17: 淨利 ÷ 營業利益 0.62 | B17: 稅與非營業較不利 | C17: =E470 -> 708.45879 | D17: =E459 -> 392.91629 | E17: =E466 -> 0.31325302 | F17: =E478 -> 202.72659 | G17: =F17/F$4-1 -> -0.062027231 | H17: =F470 -> 759.91625 | I17: =F459 -> 434.67123 | J17: =F466 -> 0.29058187 | K17: =F478 -> 205.4075 | L17: =K17/K$4-1 -> -0.062027231
A18: CB 轉換：股數 +3%／年 | B18: 2031 年到期 CB 轉換稀釋 | C18: =E504 -> 708.45879 | D18: =E493 -> 392.91629 | E18: =E500 -> 0.31325302 | F18: =E512 -> 209.83757 | G18: =F18/F$4-1 -> -0.029126214 | H18: =F504 -> 759.91625 | I18: =F493 -> 434.67123 | J18: =F500 -> 0.29058187 | K18: =F512 -> 206.41993 | L18: =K18/K$4-1 -> -0.057404091
A19: 顆數情境 B | B19: CY2028 ×0.8、CY2029 ×0.85 | C19: =PL!E116 -> 708.45879 | D19: =PL!E105 -> 392.91629 | E19: =PL!E112 -> 0.31325302 | F19: =PL!E124 -> 216.1327 | G19: =F19/F$4-1 -> 0 | H19: =PL!F116 -> 672.98201 | I19: =PL!F105 -> 347.73698 | J19: =PL!F112 -> 0.28231989 | K19: =PL!F124 -> 184.44483 | L19: =K19/K$4-1 -> -0.15775116
A20: 顆數情境 C | B20: CY2028–29 ×0.6 | C20: =PL!E150 -> 708.45879 | D20: =PL!E139 -> 392.91629 | E20: =PL!E146 -> 0.31325302 | F20: =PL!E158 -> 216.1327 | G20: =F20/F$4-1 -> 0 | H20: =PL!F150 -> 586.04776 | I20: =PL!F139 -> 260.80274 | J20: =PL!F146 -> 0.27051544 | K20: =PL!F158 -> 149.89876 | L20: =K20/K$4-1 -> -0.31550232
A22: 讀法：FY2027 三個顆數情境相同；B、C 的差異從 FY2028 起。溢價指數同時改變營收與 AI 載板營益率（成本不變），所以對 EPS 的影響大於對營收的影響。
A40: 案例區塊：溢價快速回落（情境 A）
A41: 項目 | B41: 單位 | C41: FY2025A | D41: FY2026（錨點） | E41: FY2027 | F41: FY2028 | G41: FY2029 | H41: 說明
A42: A. AI 伺服器載板（D 欄＝FY2026 校準年；FY(t) 對照 CY(t) 顆數）
A43: NVIDIA 加速器顆數 × 情境係數 | B43: 百萬顆 | D43: =(u_bw_26+u_rb_26+u_ru_26+u_hp_26)*1 -> 7.6 | E43: =(u_bw_27+u_rb_27+u_ru_27+u_hp_27)*1 -> 9.7 | F43: =(u_bw_28+u_rb_28+u_ru_28+u_hp_28)*um28_A -> 9.5 | G43: =(u_bw_28*(1+g29_bw)+u_rb_28*(1+g29_rb)+u_ru_28*(1+g29_ru)+u_hp_28*(1+g29_hp))*um29_A -> 10.6 | H43: markets/network In：Blackwell、Rubin、Rubin Ultra、Hopper
A44: 非 NVIDIA 加速器顆數 × 情境係數 | B44: 百萬顆 | D44: =(u_amd_26+u_tpu_26+u_trn_26+u_oth_26)*1 -> 7.6 | E44: =(u_amd_27+u_tpu_27+u_trn_27+u_oth_27)*1 -> 14 | F44: =(u_amd_28+u_tpu_28+u_trn_28+u_oth_28)*um28_A -> 17 | G44: =(u_amd_28*(1+g29_amd)+u_tpu_28*(1+g29_tpu)+u_trn_28*(1+g29_trn)+u_oth_28*(1+g29_oth))*um29_A -> 19.55 | H44: AMD、TPU、Trainium、其他 ASIC
A45: 有效顆數 ＝ NVIDIA ＋ 權重 × 非 NVIDIA | B45: 百萬顆 | D45: =D43+w_ot*D44 -> 10.64 | E45: =E43+w_ot*E44 -> 15.3 | F45: =F43+w_ot*F44 -> 16.3 | G45: =G43+w_ot*G44 -> 18.42
A46: FY2026 AI 載板營收（錨點電子事業 × AI 占比） | B46: ¥B | D46: =q26_e*ai_e -> 243.75 | H46: Assumed 切分；公司未揭露
A47: 每顆有效金額（Ibiden 份額 × 載板金額；FY2026 校準） | B47: 千日圓／顆 | D47: =D46/D45 -> 22.908835 | H47: Derived：¥B ÷ 百萬顆＝千日圓／顆。÷ 匯率即美元／顆（Units 頁）
A48: 每顆載板金額指數（面積、層數；FY2026＝1） | B48: x | D48: =1 -> 1 | E48: =D48*(1+g_asp) -> 1.18 | F48: =E48*(1+g_asp) -> 1.3924 | G48: =F48*(1+g_asp) -> 1.643032
A49: Ibiden 份額相對值（÷ FY2026） | B49: x | D49: =1 -> 1 | E49: =rel_27 -> 0.95 | F49: =rel_28 -> 0.88 | G49: =rel_29 -> 0.85
A50: 短缺溢價指數（FY2026＝1） | B50: x | D50: =1 -> 1 | E50: =PPLO_27 -> 0.95 | F50: =PPLO_28 -> 0.85 | G50: =PPLO_29 -> 0.75
A51: AI 伺服器載板營收 | B51: ¥B | D51: =D46 -> 243.75 | E51: =E45*$D$47*E48*E49*E50 -> 373.27048 | F51: =F45*$D$47*F48*F49*F50 -> 388.91636 | G51: =G45*$D$47*G48*G49*G50 -> 441.9965
A52: B. 電子事業
A53: 電子事業非 AI 營收（通用伺服器、PC 等） | B53: ¥B | D53: =q26_e-D51 -> 131.25 | E53: =D53*(1+g_ne) -> 137.8125 | F53: =E53*(1+g_ne) -> 144.70312 | G53: =F53*(1+g_ne) -> 151.93828
A54: 電子事業營收 | B54: ¥B | C54: =q25_e -> 243.316 | D54: =D51+D53 -> 375 | E54: =E51+E53 -> 511.08298 | F54: =F51+F53 -> 533.61949 | G54: =G51+G53 -> 593.93478
A55: AI 載板營業利益率（FY2026 校準） | B55: % | D55: =(q26_eoi-m_ne*D53)/D51 -> 0.37051282 | H55: Derived：使 FY2026 電子事業營業利益＝錨點；非 AI 營益率為 In 頁 m_ne
A56: AI 載板營業利益率 ＝ 1 −（1 − 校準值）÷ 溢價指數 | B56: % | D56: =D55 -> 0.37051282 | E56: =1-(1-$D$55)/E50 -> 0.33738192 | F56: =1-(1-$D$55)/F50 -> 0.25942685 | G56: =1-(1-$D$55)/G50 -> 0.16068376 | H56: Derived：每單位成本不變，價格隨溢價指數升降，差額全部落在利潤
A57: 電子事業營業利益 | B57: ¥B | C57: =q25_eoi -> 45.248 | D57: =D51*D56+D53*m_ne -> 110 | E57: =E51*E56+E53*m_ne -> 146.60658 | F57: =F51*F56+F53*m_ne -> 122.60081 | G57: =G51*G56+G53*m_ne -> 93.812402
A58: 電子事業營益率 | B58: % | C58: =C57/C54 -> 0.18596393 | D58: =D57/D54 -> 0.29333333 | E58: =E57/E54 -> 0.28685476 | F58: =F57/F54 -> 0.22975326 | G58: =G57/G54 -> 0.15795068
A59: C. 陶瓷、其他事業與全公司
A60: 陶瓷事業營收 | B60: ¥B | C60: =q25_cer -> 82.554 | D60: =q26_cer -> 84 | E60: =D60*(1+g_cer) -> 84 | F60: =E60*(1+g_cer) -> 84 | G60: =F60*(1+g_cer) -> 84
A61: 其他事業營收 | B61: ¥B | C61: =q25_oth -> 90.33 | D61: =q26_oth -> 91 | E61: =D61*(1+g_oth) -> 93.73 | F61: =E61*(1+g_oth) -> 96.5419 | G61: =F61*(1+g_oth) -> 99.438157
A62: 營收 | B62: ¥B | C62: =C54+C60+C61 -> 416.2 | D62: =D54+D60+D61 -> 550 | E62: =E54+E60+E61 -> 688.81298 | F62: =F54+F60+F61 -> 714.16139 | G62: =G54+G60+G61 -> 777.37294
A63: 營收年增 | B63: % | D63: =D62/C62-1 -> 0.32148006 | E63: =E62/D62-1 -> 0.25238724 | F63: =F62/E62-1 -> 0.036800128 | G63: =G62/F62-1 -> 0.088511584
A64: AI 伺服器載板 ÷ 營收 | B64: % | D64: =D51/D62 -> 0.44318182 | E64: =E51/E62 -> 0.54190396 | F64: =F51/F62 -> 0.54457769 | G64: =G51/G62 -> 0.56857716
A65: 陶瓷＋其他事業營業利益＋調整 | B65: ¥B | C65: =q25_oi-q25_eoi -> 16.779 | D65: =q26_oi-q26_eoi -> 17 | E65: =E60*m_cer+E61*m_oth+q26_adj -> 17.24695 | F65: =F60*m_cer+F61*m_oth+q26_adj -> 17.570318 | G65: =G60*m_cer+G61*m_oth+q26_adj -> 17.903388
A66: 營業利益 | B66: ¥B | C66: =C57+C65 -> 62.027 | D66: =D57+D65 -> 127 | E66: =E57+E65 -> 163.85353 | F66: =F57+F65 -> 140.17113 | G66: =G57+G65 -> 111.71579
A67: 營業利益率 | B67: % | C67: =C66/C62 -> 0.14903172 | D67: =D66/D62 -> 0.23090909 | E67: =E66/E62 -> 0.23787812 | F67: =F66/F62 -> 0.19627375 | G67: =G66/G62 -> 0.14370939
A68: 淨利（歸屬母公司） | B68: ¥B | C68: =q25_ni -> 63.713 | D68: =q26_ni -> 84 | E68: =E66*ni_oi -> 108.30719 | F68: =F66*ni_oi -> 92.653119 | G68: =G66*ni_oi -> 73.844138
A69: 股數（分割後） | B69: 十億股 | D69: =q26_sh -> 0.56119722 | E69: =D69*(1+sh_g) -> 0.56119722 | F69: =E69*(1+sh_g) -> 0.56119722 | G69: =F69*(1+sh_g) -> 0.56119722
A70: EPS（日圓） | B70: ¥ | C70: =q25_eps -> 114.08 | D70: =D68/D69 -> 149.68 | E70: =E68/E69 -> 192.99309 | F70: =F68/F69 -> 165.09903 | G70: =G68/G69 -> 131.58322
A71: EPS 年增 | B71: % | D71: =D70/C70-1 -> 0.31206171 | E71: =E70/D70-1 -> 0.28937127 | F71: =F70/E70-1 -> -0.14453397 | G71: =G70/F70-1 -> -0.2030043
A74: 案例區塊：溢價延續（情境 A）
A75: 項目 | B75: 單位 | C75: FY2025A | D75: FY2026（錨點） | E75: FY2027 | F75: FY2028 | G75: FY2029 | H75: 說明
A76: A. AI 伺服器載板（D 欄＝FY2026 校準年；FY(t) 對照 CY(t) 顆數）
A77: NVIDIA 加速器顆數 × 情境係數 | B77: 百萬顆 | D77: =(u_bw_26+u_rb_26+u_ru_26+u_hp_26)*1 -> 7.6 | E77: =(u_bw_27+u_rb_27+u_ru_27+u_hp_27)*1 -> 9.7 | F77: =(u_bw_28+u_rb_28+u_ru_28+u_hp_28)*um28_A -> 9.5 | G77: =(u_bw_28*(1+g29_bw)+u_rb_28*(1+g29_rb)+u_ru_28*(1+g29_ru)+u_hp_28*(1+g29_hp))*um29_A -> 10.6 | H77: markets/network In：Blackwell、Rubin、Rubin Ultra、Hopper
A78: 非 NVIDIA 加速器顆數 × 情境係數 | B78: 百萬顆 | D78: =(u_amd_26+u_tpu_26+u_trn_26+u_oth_26)*1 -> 7.6 | E78: =(u_amd_27+u_tpu_27+u_trn_27+u_oth_27)*1 -> 14 | F78: =(u_amd_28+u_tpu_28+u_trn_28+u_oth_28)*um28_A -> 17 | G78: =(u_amd_28*(1+g29_amd)+u_tpu_28*(1+g29_tpu)+u_trn_28*(1+g29_trn)+u_oth_28*(1+g29_oth))*um29_A -> 19.55 | H78: AMD、TPU、Trainium、其他 ASIC
A79: 有效顆數 ＝ NVIDIA ＋ 權重 × 非 NVIDIA | B79: 百萬顆 | D79: =D77+w_ot*D78 -> 10.64 | E79: =E77+w_ot*E78 -> 15.3 | F79: =F77+w_ot*F78 -> 16.3 | G79: =G77+w_ot*G78 -> 18.42
A80: FY2026 AI 載板營收（錨點電子事業 × AI 占比） | B80: ¥B | D80: =q26_e*ai_e -> 243.75 | H80: Assumed 切分；公司未揭露
A81: 每顆有效金額（Ibiden 份額 × 載板金額；FY2026 校準） | B81: 千日圓／顆 | D81: =D80/D79 -> 22.908835 | H81: Derived：¥B ÷ 百萬顆＝千日圓／顆。÷ 匯率即美元／顆（Units 頁）
A82: 每顆載板金額指數（面積、層數；FY2026＝1） | B82: x | D82: =1 -> 1 | E82: =D82*(1+g_asp) -> 1.18 | F82: =E82*(1+g_asp) -> 1.3924 | G82: =F82*(1+g_asp) -> 1.643032
A83: Ibiden 份額相對值（÷ FY2026） | B83: x | D83: =1 -> 1 | E83: =rel_27 -> 0.95 | F83: =rel_28 -> 0.88 | G83: =rel_29 -> 0.85
A84: 短缺溢價指數（FY2026＝1） | B84: x | D84: =1 -> 1 | E84: =PPHI_27 -> 1.05 | F84: =PPHI_28 -> 1.05 | G84: =PPHI_29 -> 1
A85: AI 伺服器載板營收 | B85: ¥B | D85: =D80 -> 243.75 | E85: =E79*$D$81*E82*E83*E84 -> 412.56211 | F85: =F79*$D$81*F82*F83*F84 -> 480.42609 | G85: =G79*$D$81*G82*G83*G84 -> 589.32867
A86: B. 電子事業
A87: 電子事業非 AI 營收（通用伺服器、PC 等） | B87: ¥B | D87: =q26_e-D85 -> 131.25 | E87: =D87*(1+g_ne) -> 137.8125 | F87: =E87*(1+g_ne) -> 144.70312 | G87: =F87*(1+g_ne) -> 151.93828
A88: 電子事業營收 | B88: ¥B | C88: =q25_e -> 243.316 | D88: =D85+D87 -> 375 | E88: =E85+E87 -> 550.37461 | F88: =F85+F87 -> 625.12922 | G88: =G85+G87 -> 741.26695
A89: AI 載板營業利益率（FY2026 校準） | B89: % | D89: =(q26_eoi-m_ne*D87)/D85 -> 0.37051282 | H89: Derived：使 FY2026 電子事業營業利益＝錨點；非 AI 營益率為 In 頁 m_ne
A90: AI 載板營業利益率 ＝ 1 −（1 − 校準值）÷ 溢價指數 | B90: % | D90: =D89 -> 0.37051282 | E90: =1-(1-$D$89)/E84 -> 0.4004884 | F90: =1-(1-$D$89)/F84 -> 0.4004884 | G90: =1-(1-$D$89)/G84 -> 0.37051282 | H90: Derived：每單位成本不變，價格隨溢價指數升降，差額全部落在利潤
A91: 電子事業營業利益 | B91: ¥B | C91: =q25_eoi -> 45.248 | D91: =D85*D90+D87*m_ne -> 110 | E91: =E85*E90+E87*m_ne -> 185.89821 | F91: =F85*F90+F87*m_ne -> 214.11055 | G91: =G85*G90+G87*m_ne -> 241.14457
A92: 電子事業營益率 | B92: % | C92: =C91/C88 -> 0.18596393 | D92: =D91/D88 -> 0.29333333 | E92: =E91/E88 -> 0.3377667 | F92: =F91/F88 -> 0.34250606 | G92: =G91/G88 -> 0.32531407
A93: C. 陶瓷、其他事業與全公司
A94: 陶瓷事業營收 | B94: ¥B | C94: =q25_cer -> 82.554 | D94: =q26_cer -> 84 | E94: =D94*(1+g_cer) -> 84 | F94: =E94*(1+g_cer) -> 84 | G94: =F94*(1+g_cer) -> 84
A95: 其他事業營收 | B95: ¥B | C95: =q25_oth -> 90.33 | D95: =q26_oth -> 91 | E95: =D95*(1+g_oth) -> 93.73 | F95: =E95*(1+g_oth) -> 96.5419 | G95: =F95*(1+g_oth) -> 99.438157
A96: 營收 | B96: ¥B | C96: =C88+C94+C95 -> 416.2 | D96: =D88+D94+D95 -> 550 | E96: =E88+E94+E95 -> 728.10461 | F96: =F88+F94+F95 -> 805.67112 | G96: =G88+G94+G95 -> 924.70511
A97: 營收年增 | B97: % | D97: =D96/C96-1 -> 0.32148006 | E97: =E96/D96-1 -> 0.32382656 | F97: =F96/E96-1 -> 0.10653209 | G97: =G96/F96-1 -> 0.14774514
A98: AI 伺服器載板 ÷ 營收 | B98: % | D98: =D85/D96 -> 0.44318182 | E98: =E85/E96 -> 0.56662477 | F98: =F85/F96 -> 0.59630547 | G98: =G85/G96 -> 0.63731525
A99: 陶瓷＋其他事業營業利益＋調整 | B99: ¥B | C99: =q25_oi-q25_eoi -> 16.779 | D99: =q26_oi-q26_eoi -> 17 | E99: =E94*m_cer+E95*m_oth+q26_adj -> 17.24695 | F99: =F94*m_cer+F95*m_oth+q26_adj -> 17.570318 | G99: =G94*m_cer+G95*m_oth+q26_adj -> 17.903388
A100: 營業利益 | B100: ¥B | C100: =C91+C99 -> 62.027 | D100: =D91+D99 -> 127 | E100: =E91+E99 -> 203.14516 | F100: =F91+F99 -> 231.68086 | G100: =G91+G99 -> 259.04796
A101: 營業利益率 | B101: % | C101: =C100/C96 -> 0.14903172 | D101: =D100/D96 -> 0.23090909 | E101: =E100/E96 -> 0.27900546 | F101: =F100/F96 -> 0.28756258 | G101: =G100/G96 -> 0.28014116
A102: 淨利（歸屬母公司） | B102: ¥B | C102: =q25_ni -> 63.713 | D102: =q26_ni -> 84 | E102: =E100*ni_oi -> 134.27895 | F102: =F100*ni_oi -> 153.14105 | G102: =G100*ni_oi -> 171.2307
A103: 股數（分割後） | B103: 十億股 | D103: =q26_sh -> 0.56119722 | E103: =D103*(1+sh_g) -> 0.56119722 | F103: =E103*(1+sh_g) -> 0.56119722 | G103: =F103*(1+sh_g) -> 0.56119722
A104: EPS（日圓） | B104: ¥ | C104: =q25_eps -> 114.08 | D104: =D102/D103 -> 149.68 | E104: =E102/E103 -> 239.27231 | F104: =F102/F103 -> 272.88277 | G104: =G102/G103 -> 305.1168
A105: EPS 年增 | B105: % | D105: =D104/C104-1 -> 0.31206171 | E105: =E104/D104-1 -> 0.59855897 | F105: =F104/E104-1 -> 0.1404695 | G105: =G104/F104-1 -> 0.1181241
A108: 案例區塊：份額流失（低）（情境 A）
A109: 項目 | B109: 單位 | C109: FY2025A | D109: FY2026（錨點） | E109: FY2027 | F109: FY2028 | G109: FY2029 | H109: 說明
A110: A. AI 伺服器載板（D 欄＝FY2026 校準年；FY(t) 對照 CY(t) 顆數）
A111: NVIDIA 加速器顆數 × 情境係數 | B111: 百萬顆 | D111: =(u_bw_26+u_rb_26+u_ru_26+u_hp_26)*1 -> 7.6 | E111: =(u_bw_27+u_rb_27+u_ru_27+u_hp_27)*1 -> 9.7 | F111: =(u_bw_28+u_rb_28+u_ru_28+u_hp_28)*um28_A -> 9.5 | G111: =(u_bw_28*(1+g29_bw)+u_rb_28*(1+g29_rb)+u_ru_28*(1+g29_ru)+u_hp_28*(1+g29_hp))*um29_A -> 10.6 | H111: markets/network In：Blackwell、Rubin、Rubin Ultra、Hopper
A112: 非 NVIDIA 加速器顆數 × 情境係數 | B112: 百萬顆 | D112: =(u_amd_26+u_tpu_26+u_trn_26+u_oth_26)*1 -> 7.6 | E112: =(u_amd_27+u_tpu_27+u_trn_27+u_oth_27)*1 -> 14 | F112: =(u_amd_28+u_tpu_28+u_trn_28+u_oth_28)*um28_A -> 17 | G112: =(u_amd_28*(1+g29_amd)+u_tpu_28*(1+g29_tpu)+u_trn_28*(1+g29_trn)+u_oth_28*(1+g29_oth))*um29_A -> 19.55 | H112: AMD、TPU、Trainium、其他 ASIC
A113: 有效顆數 ＝ NVIDIA ＋ 權重 × 非 NVIDIA | B113: 百萬顆 | D113: =D111+w_ot*D112 -> 10.64 | E113: =E111+w_ot*E112 -> 15.3 | F113: =F111+w_ot*F112 -> 16.3 | G113: =G111+w_ot*G112 -> 18.42
A114: FY2026 AI 載板營收（錨點電子事業 × AI 占比） | B114: ¥B | D114: =q26_e*ai_e -> 243.75 | H114: Assumed 切分；公司未揭露
A115: 每顆有效金額（Ibiden 份額 × 載板金額；FY2026 校準） | B115: 千日圓／顆 | D115: =D114/D113 -> 22.908835 | H115: Derived：¥B ÷ 百萬顆＝千日圓／顆。÷ 匯率即美元／顆（Units 頁）
A116: 每顆載板金額指數（面積、層數；FY2026＝1） | B116: x | D116: =1 -> 1 | E116: =D116*(1+g_asp) -> 1.18 | F116: =E116*(1+g_asp) -> 1.3924 | G116: =F116*(1+g_asp) -> 1.643032
A117: Ibiden 份額相對值（÷ FY2026） | B117: x | D117: =1 -> 1 | E117: =RLO_27 -> 0.85 | F117: =RLO_28 -> 0.75 | G117: =RLO_29 -> 0.7
A118: 短缺溢價指數（FY2026＝1） | B118: x | D118: =1 -> 1 | E118: =pp_27 -> 1 | F118: =pp_28 -> 0.95 | G118: =pp_29 -> 0.9
A119: AI 伺服器載板營收 | B119: ¥B | D119: =D114 -> 243.75 | E119: =E113*$D$115*E116*E117*E118 -> 351.55668 | F119: =F113*$D$115*F116*F117*F118 -> 370.45843 | G119: =G113*$D$115*G116*G117*G118 -> 436.79654
A120: B. 電子事業
A121: 電子事業非 AI 營收（通用伺服器、PC 等） | B121: ¥B | D121: =q26_e-D119 -> 131.25 | E121: =D121*(1+g_ne) -> 137.8125 | F121: =E121*(1+g_ne) -> 144.70312 | G121: =F121*(1+g_ne) -> 151.93828
A122: 電子事業營收 | B122: ¥B | C122: =q25_e -> 243.316 | D122: =D119+D121 -> 375 | E122: =E119+E121 -> 489.36918 | F122: =F119+F121 -> 515.16156 | G122: =G119+G121 -> 588.73483
A123: AI 載板營業利益率（FY2026 校準） | B123: % | D123: =(q26_eoi-m_ne*D121)/D119 -> 0.37051282 | H123: Derived：使 FY2026 電子事業營業利益＝錨點；非 AI 營益率為 In 頁 m_ne
...

Sheet Sources
A1: 來源（公司原文＝決算短信與補足資料；分部門預測取自 Q1 補足資料的轉載）
A2: 公司：2026 年 3 月期決算短信（FY2025 實績、分部門） | B2: https://www.ibiden.com/ir/items/ConsolidatedFinancialResultsFY2025.pdf
A3: 公司：2027 年 3 月期 Q1 決算短信（上修後全年預測） | B3: https://finance.biggo.jp/news/jpx_tdnet_140120260731504718
A4: 公司：Q1 補足資料（分部門全年預測、設備投資 2,100 億、匯率 ¥152） | B4: https://finance.biggo.jp/news/jpx_tdnet_140120260803507041
A5: 二手：SEMICON.TODAY Q1 深掘（分部門 Q1、EPS 分割後 149.68） | B5: https://semicon.today/archives/12352
A6: 二手：LIMO Q1（預收款、股價） | B6: https://finance.limo.media/articles/detail/683
A7: 二手：Quartr FY2025 摘要（FY2030 目標；AI 摘要，營收數字有誤處未採用） | B7: https://quartr.com/events/ibiden-co-ltd-4062-q4-2026_F9Xvd7IW
A8: 研調：Tom's Hardware ABF 2026（供需缺口、Ibiden 路線圖、競爭者擴產、ABF 膜漲價） | B8: https://www.tomshardware.com/tech-industry/semiconductors/the-state-of-abf-substrates-in-data-center-silicon-in-2026-solving-the-supply-crunch-and-material-wall-beneath-every-ai-accelerator
A9: 研調：Data Gravity（高階 FC-BGA 份額、ABF 載板平均單價） | B9: https://www.datagravity.dev/p/the-abf-substrate-bottleneck
A10: 研調：thebuildout（BofA：Ibiden 占 GPU 載板 70–80%、短缺到 2028） | B10: https://thebuildout.ai/intel/229c44f2-da57-4f46-b5fa-e5d03702236c
A11: 研調：Encyclopedia of Stocks（欣興 2025 年 NVIDIA 約 30%） | B11: https://encyclopediaofstocks.substack.com/p/abf-substrate-market-ai-driven-super
A12: 研調：Silicon Analysts（封裝成本，含載板） | B12: https://siliconanalysts.com/data/ai-chip-costs
A13: 市場：stockanalysis（10-16 股價、前瞻與近 12 月 P/E、共識目標價；同業前瞻 P/E、ROE） | B13: https://stockanalysis.com/quote/tyo/4062/
A14: 市場：10-23 收盤（markets/invest_map/data/prices.csv：株探、松井證券） | B14: https://kabutan.jp/stock/?code=4062
A15: 市場層：markets/network、tsmc 成品（本 repo，唯讀）
A16: 待補（人工）：十年 P/E 歷史（Bloomberg）；AI 伺服器載板營收（公司未揭露）；FY2027 以後共識（付費）；CB 發行額；ASIC 載板份額 | B16: 未找到
A17: SemiAnalysis | B17: 未使用
