Workbook

Sheet README
A1: Ibiden（4062）收支與估值模型 v0.2.1（AI 半導體 Project：載板與 PCB 樣板） 2026-10-25
A2: 版本：v0.2.1（2026-10-25：補上檔空間級距、投資建議、重點觀察，數值不變）。前版：v0.2（2026-10-25：目標價改為 DCF 與 Comparable 加權、三情境延伸到 FY2032；FY2025–FY2029 數值不變）。前版：v0.1（初版）。Ibiden 在 AI 加速器載板的有效金額與份額在本模型 Units 頁建立，為本專案權威資料（規則第 13 條）。
A3: 模型命題：Ibiden 的 AI 伺服器載板營收＝AI 加速器顆數（本專案網通模型）× Ibiden 份額 × 每顆載板金額（面積、層數逐年增加）× 短缺溢價；電子事業的非 AI 部分、陶瓷與其他事業另依成長率推。股價約 54–65 倍前瞻 EPS：2028 年產能擴到 2.5 倍、競爭者同時擴產之後，短缺溢價能否守住電子事業約 29% 的營益率？
A4: 核心問題：短缺溢價回落多少、何時回落，FY2028 EPS 會少多少；現價隱含的溢價路徑合不合理。
A6: 會計年度 4 月至隔年 3 月：FY(t)＝t/4–(t+1)/3，對照 CY(t) 的加速器顆數（重疊 9 個月，不平移）。預測期 FY2027–FY2029（三年）。金額：十億日圓；EPS：日圓（2026-10-01 一拆二後）。
A8: 驅動因子 → 推導量（全部唯讀上游，不修改）
A9: AI 載板：markets/network 的加速器顆數（NVIDIA ＋ 權重 × 非 NVIDIA）× 每顆有效金額（FY2026 校準）× 金額指數（+18%／年，Analogy）× 份額相對值（Assumed）× 溢價指數（Assumed）。
A10: 利潤率：AI 載板營益率 FY2026 校準（非 AI 部分 15%，Assumed），之後＝ 1 −（1 − 校準值）÷ 溢價指數（成本不變）。陶瓷、其他事業營益率沿用 FY2026 預測。淨利 ÷ 營業利益 0.661（FY2026 預測）。
A11: 校準：FY2026 ＝ 公司 2026-08-04 上修後預測（營收 5,500 億、營業利益 1,270 億、淨利 840 億、EPS 149.68）；AI 伺服器載板占電子事業 65%（Assumed，公司未揭露）。
A12: 估值：Val 第 0 節目標價＝0.5 × DCF 目標價（股東現金流＝EPS ×（1 − tp_g ÷ tp_roe），FY2027–FY2032 明確期＋永續，r 10%、g 4%，三情境權重 0.3／0.5／0.2，推到 12 個月後）＋0.5 × Comparable 目標價（欣興、南電、景碩、三星電機、AT&S 前瞻 P/E 中位數 × 12 個月後前瞻 EPS）；另列 Comparable 單獨目標價、市場共識目標價與差距拆解（EPS 因素、倍數因素）、DCF 價格帶、十年 P/E 分位檢查（只作檢查）。會計年度 4 月制：12 個月後前瞻 EPS＝½ FY2027＋½ FY2028。（v0.1.1 原估值說明，保留作參考：現價 ÷ FY2026–FY2028 EPS 與 what must be true；十年 P/E 規則值待 Bloomberg（本版不計）；循環位置以本模型營收最高年判定。）
A13: 標記：Verified、Interested-party、Analogy、Assumed、Derived。SemiAnalysis 未使用。
A15: 已知限制：(1) AI 載板營收公司未揭露，以 Assumed 切分校準；(2) 溢價指數與份額相對值皆為 Assumed，是 FY2028 EPS 最敏感的輸入（Sens）；(3) 未設產能上限（2024 基準面積未找到）；(4) FY2026 錨點為公司預測，Q2 決算後更新；(5) 十年 P/E 規則值待 Bloomberg；(6) CB 轉換稀釋只在 Sens；(7) R4 產業部署路徑未建（Recon 預留列）。
... A20: v0.2.1：補上檔空間級距、投資建議、重點觀察（數值不變）。Val 頁最後新增「上檔空間級距」「投資建議」兩列（第 109、110 列，依「上檔空間：加權目標價」的固定規則）；重點觀察見下方三列。PL 頁最後新增「自由現金流（淨利＋折舊 − 資本支出；不含營運資金變動）」一列（三情境 × FY2026–FY2032，表頭在其上一列），折舊、資本支出＝營收 × In 頁新增的 da_rev（15%）、cx_rev（25%）；不進 EPS 與目標價。
A21: ="投資建議："&Val!B110&"（依上檔空間固定規則）" -> 投資建議：中立（依上檔空間固定規則）
A22: ="重點觀察 1：目標價 ¥"&TEXT(Val!$B$96,"#,##0")&"（DCF "&TEXT(Val!$B$81,"#,##0")&"、Comparable（相對倍數調整後）"&TEXT(tp_comp_adj,"#,##0")&"；DCF 權重 "&TEXT(tp_w_dcf,"0%")&"），比現價 "&TEXT(px,"#,##0")&"（2026-10-23）"&IF(Val!$B$99>=0,"高 "&TEXT(Val!$B$99,"0.0%"),"低 "&TEXT(-Val!$B$99,"0.0%"))&"，級距 "&Val!$B$109&"、投資建議 "&Val!$B$110&"。相對倍數調整係數 "&TEXT(rm_factor,"0.00")&"（本公司 10 年前瞻倍數中位數 ÷ 同業的中位數，夾在 0.5–2.0；Val 第 0.5 節），調整前加權上檔空間 "&TEXT((tp_w_dcf*Val!$B$81+(1-tp_w_dcf)*Val!$B$92)/px-1,"+0.0%;−0.0%")&"；Comparable 單獨（市場主流同業法、未調整）為 "&TEXT(Val!$B$100,"+0.0%;−0.0%")&"。"&"以下為 2026-10-29 相對倍數調整前撰寫的說明，其中數字為調整前：主因是 DCF 不是 EPS：本模型 12 個月後前瞻 EPS 202.0 比共識前瞻 EPS 180.9 高 11.7%，但 ROE 近三年平均 8.6% 低於折現率 10%，再投資率 46% 使成長不創造價值，DCF 比現價低 77.3%；Comparable 端同業前瞻 P/E 中位數 42.3 倍、現價 ÷ 共識前瞻"&" EPS 47.0 倍、共識目標價 12,432 隱含 68.7 倍。ROE 用的是 AI 載板放量前的年度，DCF 對 ABF 漲價路徑的反映有限，待 Andy 判斷。" -> 重點觀察 1：目標價 ¥6,499（DCF 1,931、Comparable（相對倍數調整後）11,066；DCF 權重 50%），比現價 8,512（2026-10-23）低 23.7%，級距 0%～−25%、投資建議 中立。相對倍數調整係數 1.30（本公司 10 年前瞻倍數中位數 ÷ 同業的中位數，夾在 0.5–2.0；Val 第 0.5 節），調整前加權上檔空間 −38.5%；Comparable 單獨（市場主流同業法、未調整）為 +0.3%。以下為 2026-10-29 相對倍數調整前撰寫的說明，其中數字為調整前：主因是 DCF 不是 EPS：本模型 12 個月後前瞻 EPS 202.0 比共識前瞻 EPS 180.9 高 11.7%，但 ROE 近三年平均 8.6% 低於折現率 10%，再投資率 46% 使成長不創造價值，DCF 比現價低 77.3%；Comparable 端同業前瞻 P/E 中位數 42.3 倍、現價 ÷ 共識前瞻 EPS 47.0 倍、共識目標價 12,432 隱含 68.7 倍。ROE 用的是 AI 載板放量前的年度，DCF 對 ABF 漲價路徑的反映有限，待 Andy 判斷。
A23: 重點觀察 2：短缺溢價是最敏感的變數：溢價快速回落（2028 年指數 0.85）時 FY2028 EPS −24.6%、電子事業營益率由 29.1% 降到 23.0%，溢價延續則 +24.6%；份額流失（2028 年相對值 0.75）−11.7%；顆數情境 C −31.6%。
A24: 重點觀察 3：自由現金流（v0.2.1 新增；淨利＋折舊 − 資本支出，不含營運資金變動；折舊、資本支出各取營收的 15%、25%）情境 B 的 FY2027 為 ¥50.4B、FY2028 為 ¥36.2B；若 FY2026 照公司計畫（設備投資 2,100 億、折舊 810 億）則約 −¥45B，固定比率會攤平擴產前段的負值。下一個檢驗點是 FY2026 上半年決算（預計 2026-10 底或 11 月初）：全年預測與設備投資 2,100 億是否調整。
A26: 2026-10-29：加權目標價中的 Comparable 改用相對倍數調整後的值（Val 第 0.5 節：同業前瞻倍數中位數 × 本公司 10 年相對同業的倍數比，Bloomberg 前瞻倍數；Andy 2026-10-27「照建議做」、10-29 資料取回）。「Comparable 目標價（市場主流同業法）」維持不調整。重點觀察 1 的第一句已改為公式；重點觀察 2、3 與其他說明中的目標價與上檔空間數字為調整前撰寫，以 Val 頁為準。
A28: v0.3.1（2026-10-30）：依個股模型原則第 8 節調整 In 頁呈現（數值不變）。In 頁 D／F 欄名改「敏感度低」「敏感度高」（只用於 Sens 頁、不進目標價）；In 頁最後新增「情境驅動對照」一節，把上方各情境專屬輸入三情境並排（只引用上方各列，純展示）；HTML 驅動因子一節分「情境驅動」與「單一參數」兩張表。

Sheet In
A1: In — 輸入（藍字；基準欄 E，低 D、高 F）。金額：十億日圓（¥B）；顆數：百萬顆；比例：%。每個輸入附兩個來源（找不到者寫「未找到」）；公司原文算一個。【v0.3.1】基準欄 E 進主模型；D／F＝敏感度低／高，只用於 Sens 頁（一次動一個參數）、不進目標價；情境 A／B／C 的驅動見本頁最後一節「情境驅動對照」。
A2: 標記：Verified／Interested-party／Analogy／Assumed／Derived；Analogy、Assumed 給低／高區間。SemiAnalysis 未使用。公司原文＝Ibiden 決算短信與補足資料（TDnet）；公司預測為 Interested-party
A3: 鍵 | B3: 項目 | C3: 單位 | D3: 敏感度低 | E3: 基準 | F3: 敏感度高 | G3: 標記 | H3: 來源1 | I3: 來源2／說明
A4: A. 加速器顆數（讀 markets/network In 頁；CY2026–CY2028 為輸入、CY2029＝CY2028 ×（1＋成長率））
A5: u_bw_26 | B5: NVIDIA Blackwell（B200／B300） 顆數 2026 | C5: 百萬顆 | E5: 5.4 | G5: Derived | H5: markets/network/dist/20261026_AI網通市場模型_v0.2.3.xlsx｜In!E5 | I5: 唯讀上游；不在本模型另訂
A6: u_bw_27 | B6: NVIDIA Blackwell（B200／B300） 顆數 2027 | C6: 百萬顆 | E6: 2.4 | G6: Derived | H6: markets/network/dist/20261026_AI網通市場模型_v0.2.3.xlsx｜In!E6 | I6: 唯讀上游；不在本模型另訂
A7: u_bw_28 | B7: NVIDIA Blackwell（B200／B300） 顆數 2028 | C7: 百萬顆 | E7: 0.5 | G7: Derived | H7: markets/network/dist/20261026_AI網通市場模型_v0.2.3.xlsx｜In!E7 | I7: 唯讀上游；不在本模型另訂
A8: g29_bw | B8: NVIDIA Blackwell（B200／B300） 2029 顆數成長 | C8: % | E8: -0.5 | G8: Derived | H8: markets/network/dist/20261026_AI網通市場模型_v0.2.3.xlsx｜In!E8 | I8: 同上
A9: u_rb_26 | B9: NVIDIA Rubin 顆數 2026 | C9: 百萬顆 | E9: 1.7 | G9: Derived | H9: markets/network/dist/20261026_AI網通市場模型_v0.2.3.xlsx｜In!E9 | I9: 唯讀上游；不在本模型另訂
A10: u_rb_27 | B10: NVIDIA Rubin 顆數 2027 | C10: 百萬顆 | E10: 7 | G10: Derived | H10: markets/network/dist/20261026_AI網通市場模型_v0.2.3.xlsx｜In!E10 | I10: 唯讀上游；不在本模型另訂
A11: u_rb_28 | B11: NVIDIA Rubin 顆數 2028 | C11: 百萬顆 | E11: 7 | G11: Derived | H11: markets/network/dist/20261026_AI網通市場模型_v0.2.3.xlsx｜In!E11 | I11: 唯讀上游；不在本模型另訂
A12: g29_rb | B12: NVIDIA Rubin 2029 顆數成長 | C12: % | E12: 0.15 | G12: Derived | H12: markets/network/dist/20261026_AI網通市場模型_v0.2.3.xlsx｜In!E12 | I12: 同上
A13: u_ru_26 | B13: NVIDIA Rubin Ultra 顆數 2026 | C13: 百萬顆 | E13: 0 | G13: Derived | H13: markets/network/dist/20261026_AI網通市場模型_v0.2.3.xlsx｜In!E13 | I13: 唯讀上游；不在本模型另訂
A14: u_ru_27 | B14: NVIDIA Rubin Ultra 顆數 2027 | C14: 百萬顆 | E14: 0.3 | G14: Derived | H14: markets/network/dist/20261026_AI網通市場模型_v0.2.3.xlsx｜In!E14 | I14: 唯讀上游；不在本模型另訂
A15: u_ru_28 | B15: NVIDIA Rubin Ultra 顆數 2028 | C15: 百萬顆 | E15: 2 | G15: Derived | H15: markets/network/dist/20261026_AI網通市場模型_v0.2.3.xlsx｜In!E15 | I15: 唯讀上游；不在本模型另訂
A16: g29_ru | B16: NVIDIA Rubin Ultra 2029 顆數成長 | C16: % | E16: 0.15 | G16: Derived | H16: markets/network/dist/20261026_AI網通市場模型_v0.2.3.xlsx｜In!E16 | I16: 同上
... A46: um29_C | B46: 情境 C：2029 顆數 ÷ 基準 | C46: x | E46: 0.6 | G46: Assumed | H46: tsmc/dist/20261030_台積電個股模型_v0.4.1.xlsx｜In!E42 | I46: 同上
A47: B. Ibiden 份額與每顆載板金額（本專案權威：晶片商載板份額，規則第 13 條）
A48: w_ot | B48: 非 NVIDIA 加速器的權重（Ibiden 份額 × 每顆載板金額，相對 NVIDIA） | C48: x | D48: 0.2 | E48: 0.4 | F48: 0.6 | G48: Assumed | H48: 公開資料只有 NVIDIA 份額：BofA（經 thebuildout 2026-03-26）Ibiden 占 GPU 載板 70–80%；高階 FC-BGA 整體約 35%（Data Gravity 2026-06-14） | I48: ASIC 多由欣興、Shinko、AT&S 等分食（第三方研究，Interested-party）；每顆 ASIC 載板金額相對 GPU：未找到
A49: ai_e | B49: FY2026 AI 伺服器載板 ÷ 電子事業營收 | C49: % | D49: 0.55 | E49: 0.65 | F49: 0.75 | G49: Assumed | H49: 公司未揭露：未找到（決算短信只說「生成 AI 伺服器向け・汎用サーバー向け高機能 IC パッケージ基板」帶動） | I49: semi-connect 2026：AI 高階載板營收多數為 NVIDIA 向（估計，Interested-party）
A50: g_asp | B50: 每顆載板金額年增（面積、層數） | C50: % | D50: 0.1 | E50: 0.18 | F50: 0.22 | G50: Analogy | H50: Tom's Hardware：The state of ABF substrates in 2026：Ibiden 路線圖 2026 年 90×90 mm、2028 年 110×110 mm；每片 AI 伺服器載板的 SAP 負荷 2026 年為 2024 年 1.8 倍、2028 年 2.5 倍（→ 2026→2028 年約 +18%／年） | I50: Data Gravity 2026-06-14：ABF 載板平均單價 2024 $65 → 2025 $82（+26%，全品項）
A51: rel_27 | B51: Ibiden 份額 2027 ÷ 2026（相對值） | C51: x | D51: 0.85 | E51: 0.95 | F51: 1 | G51: Assumed | H51: 第三方研究：欣興 2025 年拿到 NVIDIA AI 載板約 30% 顆數（Encyclopedia of Stocks 2026-03-04） | I51: 三星電機獲 NVIDIA 載板擴產合作（Hardware Busters 2026）
A52: rel_28 | B52: Ibiden 份額 2028 ÷ 2026 | C52: x | D52: 0.75 | E52: 0.88 | F52: 1 | G52: Assumed | H52: 同上；競爭者擴產：欣興 2026 資本支出 NT$537 億（欣興模型 In 頁，2026-10 較新；Tom's Hardware 早期報導 NT$340 億已過時，CF02）、景碩 3 年 NT$235 億（Tom's Hardware：The state of ABF substrates in 2026） | I52: —
A53: rel_29 | B53: Ibiden 份額 2029 ÷ 2026 | C53: x | D53: 0.7 | E53: 0.85 | F53: 1 | G53: Assumed | H53: 同上 | I53: —
A54: C. 短缺溢價（價格指數；2026＝1）與 AI 載板利潤率
A55: pp_27 | B55: 價格溢價指數 2027 | C55: x | D55: 0.95 | E55: 1 | F55: 1.05 | G55: Assumed | H55: Tom's Hardware：The state of ABF substrates in 2026（未具名供應鏈分析）：ABF 供需缺口 2026 下半年約 10%、2027 約 21%、2028 超過 40% | I55: BofA：短缺延續到 2028（經 thebuildout）
A56: pp_28 | B56: 價格溢價指數 2028 | C56: x | D56: 0.85 | E56: 0.95 | F56: 1.05 | G56: Assumed | H56: Ibiden 產能 2028 年為 2024 年 2.5–2.8 倍（公司路線圖，Interested-party；Data Gravity 2026-06-14、Tom's Hardware：The state of ABF substrates in 2026） | I56: 欣興、景碩、三星電機同時擴產（同上）
A57: pp_29 | B57: 價格溢價指數 2029 | C57: x | D57: 0.75 | E57: 0.9 | F57: 1 | G57: Assumed | H57: 同上：新產能到位後溢價回落 | I57: —
A58: m_ne | B58: 電子事業非 AI 部分營業利益率 | C58: % | D58: 0.1 | E58: 0.15 | F58: 0.2 | G58: Assumed | H58: FY2024 電子事業營益率 13.6%（26.8 ÷ 197.2，AI 比重較低時；公司：2026 年 3 月期決算短信（Sources 頁）） | I58: FY2025 18.6%（45.2 ÷ 243.3）
A59: g_ne | B59: 電子事業非 AI 營收年增（通用伺服器、PC 載板等） | C59: % | D59: 0 | E59: 0.05 | F59: 0.1 | G59: Assumed | H59: SEMICON.TODAY 2026-08：通用伺服器市場緩步成長 | I59: PC：未找到
A60: D. 陶瓷、其他事業與全公司
A61: g_cer | B61: 陶瓷事業營收年增（DPF、汽車排氣） | C61: % | D61: -0.05 | E61: 0 | F61: 0.03 | G61: Assumed | H61: FY2025 −1.8%（84.1 → 82.6；公司：2026 年 3 月期決算短信（Sources 頁）） | I61: FY2026 預測 84.0（+1.8%；公司：Q1 補足資料（分部門預測、設備投資、匯率前提；Sources 頁））
A62: m_cer | B62: 陶瓷事業營益率 | C62: % | D62: 0.05 | E62: 0.077 | F62: 0.1 | G62: Derived | H62: FY2026 預測 6.5 ÷ 84.0（公司：Q1 補足資料（分部門預測、設備投資、匯率前提；Sources 頁）） | I62: FY2025 9.3%（7.6 ÷ 82.6）
A63: g_oth | B63: 其他事業營收年增（建材等） | C63: % | D63: 0 | E63: 0.03 | F63: 0.05 | G63: Assumed | H63: FY2025 +2.5%（88.1 → 90.3） | I63: FY2026 預測 91.0（+0.7%）
A64: m_oth | B64: 其他事業營益率 | C64: % | D64: 0.09 | E64: 0.115 | F64: 0.13 | G64: Derived | H64: FY2026 預測 10.5 ÷ 91.0（公司：Q1 補足資料（分部門預測、設備投資、匯率前提；Sources 頁）） | I64: FY2025 9.9%（9.0 ÷ 90.3）
A65: ni_oi | B65: 淨利 ÷ 營業利益（稅、非營業、少數股權） | C65: x | D65: 0.62 | E65: 0.661 | F65: 0.7 | G65: Derived | H65: FY2026 預測 84 ÷ 127（公司：Q1 補足資料（分部門預測、設備投資、匯率前提；Sources 頁）） | I65: FY2025 1.03（含政策持股出售利益，不具代表性）
A66: sh_g | B66: 股數年變動（2031 年到期 CB 轉換） | C66: % | D66: 0 | E66: 0 | F66: 0.03 | G66: Assumed | H66: CB 轉換價 ¥2,243.1（分割後；SEMICON.TODAY 2026-08），遠低於現價 | I66: CB 發行額：未找到；FY2025 稀釋 EPS 比基本低 5.8%（214.91 ÷ 228.16）
A67: fx | B67: 匯率（美元換算用） | C67: ¥／US$ | E67: 152 | G67: Interested-party | H67: 公司：Q1 補足資料（分部門預測、設備投資、匯率前提；Sources 頁）：FY2026 前提 ¥152 | I67: —
A68: E. FY2026 錨點（公司 2026-08-04 上修後預測；Q2 決算後更新）
A69: f_rev | B69: FY2026 營收預測 | C69: ¥B | E69: 550 | G69: Interested-party | H69: 公司：Q1 補足資料（分部門預測、設備投資、匯率前提；Sources 頁） | I69: LIMO 2026-08-15：5,500 億（+32.1%）
A70: f_e | B70: FY2026 電子事業營收預測 | C70: ¥B | E70: 375 | G70: Interested-party | H70: 公司：Q1 補足資料（分部門預測、設備投資、匯率前提；Sources 頁） | I70: Q1 實績 77.5（年增 37.7%；SEMICON.TODAY 2026-08）
A71: f_eoi | B71: FY2026 電子事業營業利益預測 | C71: ¥B | E71: 110 | G71: Interested-party | H71: 公司：Q1 補足資料（分部門預測、設備投資、匯率前提；Sources 頁） | I71: Q1 實績 21.4（營益率 27.6%）
A72: f_cer | B72: FY2026 陶瓷事業營收預測 | C72: ¥B | E72: 84 | G72: Interested-party | H72: 公司：Q1 補足資料（分部門預測、設備投資、匯率前提；Sources 頁） | I72: —
A73: f_ceroi | B73: FY2026 陶瓷事業營業利益預測 | C73: ¥B | E73: 6.5 | G73: Interested-party | H73: 公司：Q1 補足資料（分部門預測、設備投資、匯率前提；Sources 頁） | I73: —
A74: f_oth | B74: FY2026 其他事業營收預測 | C74: ¥B | E74: 91 | G74: Interested-party | H74: 公司：Q1 補足資料（分部門預測、設備投資、匯率前提；Sources 頁） | I74: —
A75: f_othoi | B75: FY2026 其他事業營業利益預測 | C75: ¥B | E75: 10.5 | G75: Interested-party | H75: 公司：Q1 補足資料（分部門預測、設備投資、匯率前提；Sources 頁） | I75: —
A76: f_oi | B76: FY2026 營業利益預測 | C76: ¥B | E76: 127 | G76: Interested-party | H76: 公司：Q1 補足資料（分部門預測、設備投資、匯率前提；Sources 頁） | I76: SEMICON.TODAY 2026-08：900 → 1,270 億
A77: f_ni | B77: FY2026 淨利預測（歸屬母公司） | C77: ¥B | E77: 84 | G77: Interested-party | H77: 公司：Q1 補足資料（分部門預測、設備投資、匯率前提；Sources 頁） | I77: SEMICON.TODAY 2026-08：580 → 840 億
A78: f_eps | B78: FY2026 EPS 預測（分割後） | C78: ¥ | E78: 149.68 | G78: Interested-party | H78: SEMICON.TODAY 2026-08：反映 2026-10-01 一拆二 | I78: —
A79: F. FY2025 實績（2026 年 3 月期）
A80: a_rev | B80: FY2025 營收 | C80: ¥B | E80: 416.201 | G80: Verified | H80: 公司：2026 年 3 月期決算短信（Sources 頁） | I80: SEMICON.TODAY、semi-connect 同值
A81: a_e | B81: FY2025 電子事業營收 | C81: ¥B | E81: 243.316 | G81: Verified | H81: 公司：2026 年 3 月期決算短信（Sources 頁） | I81: SEMICON.TODAY、semi-connect 同值
A82: a_eoi | B82: FY2025 電子事業營業利益 | C82: ¥B | E82: 45.248 | G82: Verified | H82: 公司：2026 年 3 月期決算短信（Sources 頁） | I82: —
A83: a_cer | B83: FY2025 陶瓷事業營收 | C83: ¥B | E83: 82.554 | G83: Verified | H83: 公司：2026 年 3 月期決算短信（Sources 頁） | I83: —
A84: a_ceroi | B84: FY2025 陶瓷事業營業利益 | C84: ¥B | E84: 7.646 | G84: Verified | H84: 公司：2026 年 3 月期決算短信（Sources 頁） | I84: —
A85: a_oth | B85: FY2025 其他事業營收 | C85: ¥B | E85: 90.33 | G85: Verified | H85: 公司：2026 年 3 月期決算短信（Sources 頁） | I85: —
A86: a_othoi | B86: FY2025 其他事業營業利益 | C86: ¥B | E86: 8.964 | G86: Verified | H86: 公司：2026 年 3 月期決算短信（Sources 頁） | I86: —
A87: a_oi | B87: FY2025 營業利益 | C87: ¥B | E87: 62.027 | G87: Verified | H87: 公司：2026 年 3 月期決算短信（Sources 頁） | I87: SEMICON.TODAY、semi-connect 同值
A88: a_gp | B88: FY2025 毛利 | C88: ¥B | E88: 131.668 | G88: Verified | H88: 公司：2026 年 3 月期決算短信（Sources 頁） | I88: —
A89: a_ni | B89: FY2025 淨利（歸屬母公司） | C89: ¥B | E89: 63.713 | G89: Verified | H89: 公司：2026 年 3 月期決算短信（Sources 頁） | I89: —
A90: a_eps | B90: FY2025 基本 EPS（分割後換算＝228.16 ÷ 2） | C90: ¥ | E90: =228.16/2 -> 114.08 | G90: Derived | H90: 公司：2026 年 3 月期決算短信（Sources 頁）：228.16（2026-01 一拆二後、2026-10 一拆二前） | I90: 2026-10-01 再一拆二
A91: G. 價格與市場資料（只作 Val、Recon 對照）
A92: px | B92: 股價（2026-10-23 收盤，分割後） | C92: ¥ | E92: 8512 | G92: Interested-party | H92: markets/invest_map/data/prices.csv：株探、松井證券（兩來源核對；v0.2 更新） | I92: v0.1.1 為 10-16 收盤 9,764（stockanalysis）；前瞻 P/E 隱含 EPS 仍以 9,764 計（In 頁 cons_feps）
A93: pe_fwd_sa | B93: 前瞻 P/E（stockanalysis） | C93: x | E93: 53.97 | G93: Interested-party | H93: stockanalysis 2026-10-16 取值（股價 9,764；口徑：未來 12 個月共識，頁面未明示；隨股價每日變動） | I93: 第二來源：未找到
A94: pe_ttm | B94: 近 12 月 P/E | C94: x | E94: 83.85 | G94: Interested-party | H94: stockanalysis | I94: —
A95: pe_fair_andy | B95: Andy 先驗：合理 P/E | C95: x | E95: 25 | G95: Assumed | H95: 先驗_Andy_Ibiden_20261024 I10b（Drive；不在本 repo） | I95: 只作對照
A96: tgt30_rev | B96: 公司 FY2030 目標營收 | C96: ¥B | E96: 1000 | G96: Interested-party | H96: Quartr FY2025 摘要（AI 摘要；營收數字有誤處未採用） | I96: 第二來源：未找到
A97: tgt30_oi | B97: 公司 FY2030 目標營業利益 | C97: ¥B | E97: 300 | G97: Interested-party | H97: 同上 | I97: 第二來源：未找到
A98: H. 目標價情境權重（v0.1.1 新增；Val 頁第 0 節用）
A99: tp_wA | B99: 目標價情境權重 A（順利） | C99: % | E99: 0.3 | G99: Assumed | H99: Andy 可改（工作單 2026-10-25 預設 A 0.3／B 0.5／C 0.2） | I99: 三者合計應為 100%；v0.2 起用於 DCF 與 Comparable 的情境加權（Val 第 0 節）
A100: tp_wB | B100: 目標價情境權重 B（平平） | C100: % | E100: 0.5 | G100: Assumed | H100: Andy 可改（工作單 2026-10-25 預設 A 0.3／B 0.5／C 0.2） | I100: 三者合計應為 100%；v0.2 起用於 DCF 與 Comparable 的情境加權（Val 第 0 節）
A101: tp_wC | B101: 目標價情境權重 C（不如預期） | C101: % | E101: 0.2 | G101: Assumed | H101: Andy 可改（工作單 2026-10-25 預設 A 0.3／B 0.5／C 0.2） | I101: 三者合計應為 100%；v0.2 起用於 DCF 與 Comparable 的情境加權（Val 第 0 節）
A102: J. 目標價（DCF 與 Comparable 加權）與收斂法參數（v0.2 新增；黃底＝Assumed，Andy 可改）
A103: tp_r | B103: 折現率／要求報酬（DCF） | C103: % | E103: 0.1 | G103: Assumed | H103: Andy 可改（工作單 2026-10-25 預設 10%；美、台、日、韓同一值） | I103: Sens 頁 ±1pt
A104: tp_g | B104: 長期成長率（DCF 永續；情境 B 的 FY2032 營收年增收斂目標） | C104: % | E104: 0.04 | G104: Assumed | H104: Andy 可改（工作單預設 4%） | I104: Sens 頁 ±1pt（只動 DCF，PL 收斂目標不隨之變動）
A105: tp_roe | B105: ROE（近三年平均） | C105: % | E105: =AVERAGE(0.1217,0.0682,0.0685) -> 0.086133333 | G105: Derived | H105: stockanalysis 比率頁（Return on Equity）：2026 年 3 月期 12.17%、2025 年 3 月期 6.82%、2024 年 3 月期 6.85%（即本模型 FY2025、FY2024、FY2023） | I105: 單一來源；近 12 月 12.65%（同站，2026-08-27）
A106: tp_w_dcf | B106: 目標價中 DCF 的權重；其餘為 Comparable | C106: % | E106: 0.5 | G106: Assumed | H106: Andy 可改（2026-10-25 11:53 改為 0.5：DCF／Comparable 各半） | I106: Sens 頁 0.4／0.8
A107: fade_gA | B107: 情境 A（順利）：FY2032 營收年增收斂目標（tp_g＋2pt） | C107: % | E107: =tp_g+0.02 -> 0.06 | G107: Assumed | H107: 工作單 2026-10-25 11:20 收斂法 | I107: FY2030 起由 FY2029 年增線性收斂，FY2032 達到
A108: fade_gB | B108: 情境 B（平平）：FY2032 營收年增收斂目標（＝tp_g） | C108: % | E108: =tp_g -> 0.04 | G108: Assumed | H108: 同上 | I108: —
A109: fade_gC | B109: 情境 C（不如預期）：FY2032 營收年增收斂目標（tp_g−2pt） | C109: % | E109: =tp_g-0.02 -> 0.02 | G109: Assumed | H109: 同上 | I109: —
A110: nim10_f | B110: 十年平均淨利率的替代：最後一年（FY2029）淨利率 ×（本值） | C110: x | E110: 0.8 | G110: Assumed | H110: 十年（2016–2025）平均淨利率：未找到（免費資料商只到近五年）；依工作單以最後一年 × 0.8 替代 | I110: 淨利率收斂目標：A＝FY2029、B＝FY2029 與替代值的中點、C＝替代值（PL 延伸表）
A111: cons_tp | B111: 市場共識目標價（賣方平均） | C111: ¥ | E111: 12432.35 | G111: Interested-party | H111: stockanalysis 個股頁（S&P Global 彙整）18 位分析師平均目標價 12,432（頁面價格日期 2026-10-16；分割後） | I111: 第二來源：未找到
A112: cons_feps | B112: 共識前瞻 12 月 EPS（＝價格 ÷ 前瞻 P/E） | C112: ¥ | E112: =9764/53.97 -> 180.91532 | G112: Interested-party | H112: stockanalysis 個股頁 2026-10-16：價格 9,764 ÷ Forward PE 53.97（即 In 頁 pe_fwd_sa） | I112: 賣方共識，只作對帳與差距拆解，不作校準
A114: K. 自由現金流假設（v0.2.1 新增；算力收支 2026-10-25 請求；只用於 PL 頁最後一列「自由現金流」，不進 EPS、DCF 與目標價）
A115: da_rev | B115: 折舊 ÷ 營收 | C115: % | D115: 0.13 | E115: 0.15 | F115: 0.17 | G115: Assumed | H115: FY2025 實績（2026 年 3 月期）：折舊攤銷 662 億 ÷ 營收 4,162 億＝15.9%（stockanalysis 現金流量表，Verified） | I115: FY2026 公司計畫：折舊 810 億 ÷ 營收預測 5,500 億＝14.7%（Q1 補足資料，Interested-party）；取兩者之間 15%，各年同比率（Assumed）
A116: cx_rev | B116: 資本支出 ÷ 營收 | C116: % | D116: 0.2 | E116: 0.25 | F116: 0.38 | G116: Assumed | H116: FY2025 實績：資本支出 1,061 億 ÷ 營收 4,162 億＝25.5%（stockanalysis 現金流量表，Verified）；公司計畫 2026–2028 年度三年約 5,000 億（EE Times Japan 2026-02-05，Interested-party）÷ 本模型情境 B 三年營收約 1.93 兆＝25.9% | I116: FY2026 單年計畫設備投資 2,100 億 ÷ 5,500 億＝38.2%（前段集中；高值）；FY2029 起擴產計畫結束，固定 25% 可能高估資本支出（Assumed）
A118: 情境驅動對照（三情境並排，進主模型的加權目標價；本節只引用上方各列，修改請改上方藍字。上方「敏感度低／高」欄只用於 Sens 頁，不進目標價）
A119: 鍵 | B119: 項目 | C119: 單位 | D119: 情境 A（樂觀） | E119: 情境 B（基準） | F119: 情境 C（保守） | G119: 標記 | H119: 說明
A120: scn_um28 | B120: 2028 顆數 ÷ 基準 | C120: x | D120: =E41 -> 1 | E120: =E43 -> 0.8 | F120: =E45 -> 0.6 | G120: Derived | H120: 引用 In 頁 um28_A／um28_B／um28_C；修改請改上方藍字
A121: scn_um29 | B121: 2029 顆數 ÷ 基準 | C121: x | D121: =E42 -> 1 | E121: =E44 -> 0.85 | F121: =E46 -> 0.6 | G121: Derived | H121: 引用 In 頁 um29_A／um29_B／um29_C；修改請改上方藍字
A122: scn_fade_g | B122: （不如預期）FY2032 營收年增收斂目標（tp_g−2pt） | C122: % | D122: =E107 -> 0.06 | E122: =E108 -> 0.04 | F122: =E109 -> 0.02 | G122: Derived | H122: 引用 In 頁 fade_gA／fade_gB／fade_gC；修改請改上方藍字
A123: scn_w | B123: 情境權重 | C123: % | D123: =E99 -> 0.3 | E123: =E100 -> 0.5 | F123: =E101 -> 0.2 | G123: Derived | H123: 引用 In 頁 tp_wA／tp_wB／tp_wC；修改請改上方藍字

Sheet Q
A1: Q — FY2025 實績與 FY2026 錨點（¥B）。FY2026 錨點＝公司 2026-08-04 上修後的全年預測（Q1 公布時；分部門預測取自 Q1 補足資料）。Q2 決算（預計 10 月底或 11 月初）後更新
A2: 公司未揭露 AI 伺服器載板營收；本模型以 In 頁 ai_e（Assumed）切分電子事業，並據此校準每顆有效金額與 AI 載板營業利益率（Derived）
A3: 項目 | B3: FY2025A | C3: FY2026 錨點 | D3: 年增 | E3: 標記 | F3: 說明
A4: 營收 | B4: =a_rev -> 416.201 | C4: =f_rev -> 550 | D4: =C4/B4-1 -> 0.32147688 | E4: Verified／Interested-party
A5: 電子事業 | B5: =a_e -> 243.316 | C5: =f_e -> 375 | D5: =C5/B5-1 -> 0.54120567 | E5: Verified／Interested-party
A6: 陶瓷事業 | B6: =a_cer -> 82.554 | C6: =f_cer -> 84 | D6: =C6/B6-1 -> 0.017515808 | E6: Verified／Interested-party
A7: 其他事業 | B7: =a_oth -> 90.33 | C7: =f_oth -> 91 | D7: =C7/B7-1 -> 0.0074172479 | E7: Verified／Interested-party
A8: 營業利益 | B8: =a_oi -> 62.027 | C8: =f_oi -> 127 | D8: =C8/B8-1 -> 1.0474954 | E8: Verified／Interested-party
A9: 電子事業 | B9: =a_eoi -> 45.248 | C9: =f_eoi -> 110 | D9: =C9/B9-1 -> 1.4310467 | E9: Verified／Interested-party
A10: 陶瓷事業 | B10: =a_ceroi -> 7.646 | C10: =f_ceroi -> 6.5 | D10: =C10/B10-1 -> -0.14988229 | E10: Verified／Interested-party
A11: 其他事業 | B11: =a_othoi -> 8.964 | C11: =f_othoi -> 10.5 | D11: =C11/B11-1 -> 0.17135207 | E11: Verified／Interested-party
A12: 調整（全公司 − 三事業） | B12: =a_oi-a_eoi-a_ceroi-a_othoi -> 0.169 | C12: =f_oi-f_eoi-f_ceroi-f_othoi -> 0 | D12: =C12/B12-1 -> -1 | E12: Verified／Interested-party
A13: 淨利（歸屬母公司） | B13: =a_ni -> 63.713 | C13: =f_ni -> 84 | D13: =C13/B13-1 -> 0.31841225 | E13: Verified／Interested-party | F13: FY2025 含政策持股出售利益（稅後約 345 億，Quartr 摘要），淨利高於營業利益
A14: EPS（分割後，日圓） | B14: =a_eps -> 114.08 | C14: =f_eps -> 149.68 | D14: =C14/B14-1 -> 0.31206171 | E14: Verified／Interested-party
A16: 比率
A17: 電子事業營益率 | B17: =B9/B5 -> 0.18596393 | C17: =C9/C5 -> 0.29333333 | E17: Derived
A18: 營業利益率 | B18: =B8/B4 -> 0.14903136 | C18: =C8/C4 -> 0.23090909 | E18: Derived
A19: 電子事業 ÷ 營收 | B19: =B5/B4 -> 0.58461176 | C19: =C5/C4 -> 0.68181818 | E19: Derived
A20: 毛利率（FY2026 預測未揭露） | B20: =a_gp/a_rev -> 0.31635676 | E20: Derived
A21: 股數（十億股＝淨利 ÷ EPS） | B21: =B13/B14 -> 0.55849404 | C21: =C13/C14 -> 0.56119722 | E21: Derived | F21: FY2025 股數含政策持股出售前後變動，只作參考；預測期用 FY2026 錨點股數

Sheet Units
A1: Units — Ibiden 在 AI 加速器載板的有效金額與份額（本專案權威，規則第 13 條）。顆數取自 markets/network（情境 A）
A3: 項目 | B3: 單位 | C3: FY2026（CY2026） | D3: FY2027 | E3: FY2028 | F3: FY2029 | G3: 說明
A4: NVIDIA 加速器顆數 | B4: 百萬顆 | C4: =PL!D63 -> 7.6 | D4: =PL!E63 -> 9.7 | E4: =PL!F63 -> 9.5 | F4: =PL!G63 -> 10.6 | G4: markets/network
A5: 非 NVIDIA 加速器顆數 | B5: 百萬顆 | C5: =PL!D64 -> 7.6 | D5: =PL!E64 -> 14 | E5: =PL!F64 -> 17 | F5: =PL!G64 -> 19.55
A6: 有效顆數 | B6: 百萬顆 | C6: =PL!D65 -> 10.64 | D6: =PL!E65 -> 15.3 | E6: =PL!F65 -> 16.3 | F6: =PL!G65 -> 18.42 | G6: 非 NVIDIA × 權重 w_ot
A7: 每顆 NVIDIA 加速器的 Ibiden 營收（美元） | B7: US$ | C7: =PL!$D$67*PL!D68*PL!D69*PL!D70*1000/fx -> 150.71602 | D7: =PL!$D$67*PL!E68*PL!E69*PL!E70*1000/fx -> 168.95266 | E7: =PL!$D$67*PL!F68*PL!F69*PL!F70*1000/fx -> 175.44044 | F7: =PL!$D$67*PL!G68*PL!G69*PL!G70*1000/fx -> 189.4379 | G7: ＝份額 × 每顆載板金額
A8: 每顆 NVIDIA 載板金額（美元；假設 FY2026 份額 70%） | B8: US$ | C8: =PL!$D$67*PL!D68*PL!D70*1000/fx/0.7 -> 215.3086 | D8: =PL!$D$67*PL!E68*PL!E70*1000/fx/0.7 -> 254.06414 | E8: =PL!$D$67*PL!F68*PL!F70*1000/fx/0.7 -> 284.8059 | F8: =PL!$D$67*PL!G68*PL!G70*1000/fx/0.7 -> 318.38302 | G8: BofA：Ibiden 占 GPU 載板 70–80%（Interested-party）；先驗比對推導 $150–300
A9: AI 伺服器載板營收 | B9: ¥B | C9: =PL!D71 -> 243.75 | D9: =PL!E71 -> 392.91629 | E9: =PL!F71 -> 434.67123 | F9: =PL!G71 -> 530.3958
A10: AI 伺服器載板營收（美元） | B10: US$B | C10: =PL!D71/fx -> 1.6036184 | D10: =PL!E71/fx -> 2.5849756 | E10: =PL!F71/fx -> 2.8596791 | F10: =PL!G71/fx -> 3.4894461 | G10: ÷ 匯率 152
A11: AI 載板營收 ÷ AI IT 資本支出 | B11: % | C11: =PL!D71/fx/itc_26 -> 0.0020509963 | D11: =PL!E71/fx/itc_27 -> 0.0016513723 | E11: =PL!F71/fx/itc_28 -> 0.0014411788 | F11: =PL!G71/fx/itc_29 -> 0.0015437361 | G11: × 每 GW IT capex 即每 GW 營收
A12: 每 GW Ibiden 營收（VR200 每 GW IT capex 37.59B） | B12: US$M | C12: =PL!D71/fx/itc_26*37.59*1000 -> 77.096949 | D12: =PL!E71/fx/itc_27*37.59*1000 -> 62.075085 | E12: =PL!F71/fx/itc_28*37.59*1000 -> 54.173912 | F12: =PL!G71/fx/itc_29*37.59*1000 -> 58.02904 | G12: Tokenomics IF_CapexIT（VR200 基準，經橋接表）
A14: 讀法：每顆 NVIDIA 加速器 Ibiden 只分到約 1–2 百美元，每 GW 約數千萬美元；瓶頸反映在利潤率（電子事業營益率）與倍數，不在營收規模。

Sheet PL
A1: PL — Ibiden 損益（¥B；EPS 日圓）。FY2025A 實績、FY2026 錨點（公司上修後預測），FY2027 起為模型。FY(t)＝t/4–(t+1)/3，對照 CY(t) 顆數。三情境各一個完整推導區塊（本頁下方），頂端為摘要。FY2026–FY2027 三情境相同（顆數係數從 CY2028 開始）
A3: 情境／項目 | B3: 單位 | C3: FY2025A | D3: FY2026（錨點） | E3: FY2027 | F3: FY2028 | G3: FY2029 | H3: 說明
A4: 情境 A
A5: 營收 | B5: ¥B | C5: =C82 -> 416.2 | D5: =D82 -> 550 | E5: =E82 -> 708.45879 | F5: =F82 -> 759.91625 | G5: =G82 -> 865.77224
A6: 營收年增 | B6: % | D6: =D84 -> 0.32148006 | E6: =E84 -> 0.2881069 | F6: =F84 -> 0.072632957 | G6: =G84 -> 0.13929955
A7: AI 伺服器載板 | B7: ¥B | D7: =D71 -> 243.75 | E7: =E71 -> 392.91629 | F7: =F71 -> 434.67123 | G7: =G71 -> 530.3958
A8: 電子事業 | B8: ¥B | C8: =C74 -> 243.316 | D8: =D74 -> 375 | E8: =E74 -> 530.72879 | F8: =F74 -> 579.37435 | G8: =G74 -> 682.33408
A9: 電子事業營益率 | B9: % | C9: =C78 -> 0.18596393 | D9: =D78 -> 0.29333333 | E9: =E78 -> 0.31325302 | F9: =F78 -> 0.29058187 | G9: =G78 -> 0.26704177
A10: 營業利益率 | B10: % | C10: =C88 -> 0.14903172 | D10: =D88 -> 0.23090909 | E10: =E88 -> 0.25901203 | F10: =F88 -> 0.24466643 | G10: =G88 -> 0.23114057
A11: 淨利 | B11: ¥B | C11: =C89 -> 63.713 | D11: =D89 -> 84 | E11: =E89 -> 121.29307 | F11: =F89 -> 122.89709 | G11: =G89 -> 132.27608
A12: EPS | B12: ¥ | C12: =C91 -> 114.08 | D12: =D91 -> 149.68 | E12: =E91 -> 216.1327 | F12: =F91 -> 218.9909 | G12: =G91 -> 235.70337
A13: EPS 年增 | B13: % | D13: =D92 -> 0.31206171 | E13: =E92 -> 0.44396512 | F13: =F92 -> 0.013224293 | G13: =G92 -> 0.076315806
A15: 情境 B
A16: 營收 | B16: ¥B | C16: =C117 -> 416.2 | D16: =D117 -> 550 | E16: =E117 -> 708.45879 | F16: =F117 -> 672.98201 | G16: =G117 -> 786.21287
A17: 營收年增 | B17: % | D17: =D119 -> 0.32148006 | E17: =E119 -> 0.2881069 | F17: =F119 -> -0.050076008 | G17: =G119 -> 0.16825244
A18: AI 伺服器載板 | B18: ¥B | D18: =D106 -> 243.75 | E18: =E106 -> 392.91629 | F18: =F106 -> 347.73698 | G18: =G106 -> 450.83643
A19: 電子事業 | B19: ¥B | C19: =C109 -> 243.316 | D19: =D109 -> 375 | E19: =E109 -> 530.72879 | F19: =F109 -> 492.44011 | G19: =G109 -> 602.77471
A20: 電子事業營益率 | B20: % | C20: =C113 -> 0.18596393 | D20: =D113 -> 0.29333333 | E20: =E113 -> 0.31325302 | F20: =F113 -> 0.28231989 | G20: =G113 -> 0.26261646
A21: 營業利益率 | B21: % | C21: =C123 -> 0.14903172 | D21: =D123 -> 0.23090909 | E21: =E123 -> 0.25901203 | F21: =F123 -> 0.23268966 | G21: =G123 -> 0.22411481
A22: 淨利 | B22: ¥B | C22: =C124 -> 63.713 | D22: =D124 -> 84 | E22: =E124 -> 121.29307 | F22: =F124 -> 103.50993 | G22: =G124 -> 116.46949
A23: EPS | B23: ¥ | C23: =C126 -> 114.08 | D23: =D126 -> 149.68 | E23: =E126 -> 216.1327 | F23: =F126 -> 184.44483 | G23: =G126 -> 207.53753
A24: EPS 年增 | B24: % | D24: =D127 -> 0.31206171 | E24: =E127 -> 0.44396512 | F24: =F127 -> -0.14661302 | G24: =G127 -> 0.12520113
A26: 情境 C
A27: 營收 | B27: ¥B | C27: =C152 -> 416.2 | D27: =D152 -> 550 | E27: =E152 -> 708.45879 | F27: =F152 -> 586.04776 | G27: =G152 -> 653.61392
A28: 營收年增 | B28: % | D28: =D154 -> 0.32148006 | E28: =E154 -> 0.2881069 | F28: =F154 -> -0.17278497 | G28: =G154 -> 0.11529122
A29: AI 伺服器載板 | B29: ¥B | D29: =D141 -> 243.75 | E29: =E141 -> 392.91629 | F29: =F141 -> 260.80274 | G29: =G141 -> 318.23748
A30: 電子事業 | B30: ¥B | C30: =C144 -> 243.316 | D30: =D144 -> 375 | E30: =E144 -> 530.72879 | F30: =F144 -> 405.50586 | G30: =G144 -> 470.17576
A31: 電子事業營益率 | B31: % | C31: =C148 -> 0.18596393 | D31: =D148 -> 0.29333333 | E31: =E148 -> 0.31325302 | F31: =F148 -> 0.27051544 | G31: =G148 -> 0.25191285
A32: 營業利益率 | B32: % | C32: =C158 -> 0.14903172 | D32: =D158 -> 0.23090909 | E32: =E158 -> 0.25901203 | F32: =F158 -> 0.21715963 | G32: =G158 -> 0.20860435
A33: 淨利 | B33: ¥B | C33: =C159 -> 63.713 | D33: =D159 -> 84 | E33: =E159 -> 121.29307 | F33: =F159 -> 84.122769 | G33: =G159 -> 90.125173
A34: EPS | B34: ¥ | C34: =C161 -> 114.08 | D34: =D161 -> 149.68 | E34: =E161 -> 216.1327 | F34: =F161 -> 149.89876 | G34: =G161 -> 160.59448
A35: EPS 年增 | B35: % | D35: =D162 -> 0.31206171 | E35: =E162 -> 0.44396512 | F35: =F162 -> -0.30645033 | G35: =G162 -> 0.071352905
A37: 核對（應為 0）：FY2026 模型 − 錨點（校準恆等式）
A38: 情境 A：營收差（¥B） | D38: =D82-q26_rev -> 0
A39: 情境 A：營業利益差（¥B） | D39: =D87-q26_oi -> 0
A40: 情境 A：EPS 差（日圓） | D40: =D91-q26_eps -> 0
A60: 情境 A：基準（顆數係數 1.0）
A61: 項目 | B61: 單位 | C61: FY2025A | D61: FY2026（錨點） | E61: FY2027 | F61: FY2028 | G61: FY2029 | H61: 說明
A62: A. AI 伺服器載板（D 欄＝FY2026 校準年；FY(t) 對照 CY(t) 顆數）
A63: NVIDIA 加速器顆數 × 情境係數 | B63: 百萬顆 | D63: =(u_bw_26+u_rb_26+u_ru_26+u_hp_26)*1 -> 7.6 | E63: =(u_bw_27+u_rb_27+u_ru_27+u_hp_27)*1 -> 9.7 | F63: =(u_bw_28+u_rb_28+u_ru_28+u_hp_28)*um28_A -> 9.5 | G63: =(u_bw_28*(1+g29_bw)+u_rb_28*(1+g29_rb)+u_ru_28*(1+g29_ru)+u_hp_28*(1+g29_hp))*um29_A -> 10.6 | H63: markets/network In：Blackwell、Rubin、Rubin Ultra、Hopper
A64: 非 NVIDIA 加速器顆數 × 情境係數 | B64: 百萬顆 | D64: =(u_amd_26+u_tpu_26+u_trn_26+u_oth_26)*1 -> 7.6 | E64: =(u_amd_27+u_tpu_27+u_trn_27+u_oth_27)*1 -> 14 | F64: =(u_amd_28+u_tpu_28+u_trn_28+u_oth_28)*um28_A -> 17 | G64: =(u_amd_28*(1+g29_amd)+u_tpu_28*(1+g29_tpu)+u_trn_28*(1+g29_trn)+u_oth_28*(1+g29_oth))*um29_A -> 19.55 | H64: AMD、TPU、Trainium、其他 ASIC
A65: 有效顆數 ＝ NVIDIA ＋ 權重 × 非 NVIDIA | B65: 百萬顆 | D65: =D63+w_ot*D64 -> 10.64 | E65: =E63+w_ot*E64 -> 15.3 | F65: =F63+w_ot*F64 -> 16.3 | G65: =G63+w_ot*G64 -> 18.42
A66: FY2026 AI 載板營收（錨點電子事業 × AI 占比） | B66: ¥B | D66: =q26_e*ai_e -> 243.75 | H66: Assumed 切分；公司未揭露
A67: 每顆有效金額（Ibiden 份額 × 載板金額；FY2026 校準） | B67: 千日圓／顆 | D67: =D66/D65 -> 22.908835 | H67: Derived：¥B ÷ 百萬顆＝千日圓／顆。÷ 匯率即美元／顆（Units 頁）
A68: 每顆載板金額指數（面積、層數；FY2026＝1） | B68: x | D68: =1 -> 1 | E68: =D68*(1+g_asp) -> 1.18 | F68: =E68*(1+g_asp) -> 1.3924 | G68: =F68*(1+g_asp) -> 1.643032
A69: Ibiden 份額相對值（÷ FY2026） | B69: x | D69: =1 -> 1 | E69: =rel_27 -> 0.95 | F69: =rel_28 -> 0.88 | G69: =rel_29 -> 0.85
A70: 短缺溢價指數（FY2026＝1） | B70: x | D70: =1 -> 1 | E70: =pp_27 -> 1 | F70: =pp_28 -> 0.95 | G70: =pp_29 -> 0.9
A71: AI 伺服器載板營收 | B71: ¥B | D71: =D66 -> 243.75 | E71: =E65*$D$67*E68*E69*E70 -> 392.91629 | F71: =F65*$D$67*F68*F69*F70 -> 434.67123 | G71: =G65*$D$67*G68*G69*G70 -> 530.3958
A72: B. 電子事業
A73: 電子事業非 AI 營收（通用伺服器、PC 等） | B73: ¥B | D73: =q26_e-D71 -> 131.25 | E73: =D73*(1+g_ne) -> 137.8125 | F73: =E73*(1+g_ne) -> 144.70312 | G73: =F73*(1+g_ne) -> 151.93828
A74: 電子事業營收 | B74: ¥B | C74: =q25_e -> 243.316 | D74: =D71+D73 -> 375 | E74: =E71+E73 -> 530.72879 | F74: =F71+F73 -> 579.37435 | G74: =G71+G73 -> 682.33408
A75: AI 載板營業利益率（FY2026 校準） | B75: % | D75: =(q26_eoi-m_ne*D73)/D71 -> 0.37051282 | H75: Derived：使 FY2026 電子事業營業利益＝錨點；非 AI 營益率為 In 頁 m_ne
A76: AI 載板營業利益率 ＝ 1 −（1 − 校準值）÷ 溢價指數 | B76: % | D76: =D75 -> 0.37051282 | E76: =1-(1-$D$75)/E70 -> 0.37051282 | F76: =1-(1-$D$75)/F70 -> 0.33738192 | G76: =1-(1-$D$75)/G70 -> 0.3005698 | H76: Derived：每單位成本不變，價格隨溢價指數升降，差額全部落在利潤
A77: 電子事業營業利益 | B77: ¥B | C77: =q25_eoi -> 45.248 | D77: =D71*D76+D73*m_ne -> 110 | E77: =E71*E76+E73*m_ne -> 166.2524 | F77: =F71*F76+F73*m_ne -> 168.35568 | G77: =G71*G76+G73*m_ne -> 182.2117
A78: 電子事業營益率 | B78: % | C78: =C77/C74 -> 0.18596393 | D78: =D77/D74 -> 0.29333333 | E78: =E77/E74 -> 0.31325302 | F78: =F77/F74 -> 0.29058187 | G78: =G77/G74 -> 0.26704177
A79: C. 陶瓷、其他事業與全公司
A80: 陶瓷事業營收 | B80: ¥B | C80: =q25_cer -> 82.554 | D80: =q26_cer -> 84 | E80: =D80*(1+g_cer) -> 84 | F80: =E80*(1+g_cer) -> 84 | G80: =F80*(1+g_cer) -> 84
A81: 其他事業營收 | B81: ¥B | C81: =q25_oth -> 90.33 | D81: =q26_oth -> 91 | E81: =D81*(1+g_oth) -> 93.73 | F81: =E81*(1+g_oth) -> 96.5419 | G81: =F81*(1+g_oth) -> 99.438157
A82: 營收 | B82: ¥B | C82: =C74+C80+C81 -> 416.2 | D82: =D74+D80+D81 -> 550 | E82: =E74+E80+E81 -> 708.45879 | F82: =F74+F80+F81 -> 759.91625 | G82: =G74+G80+G81 -> 865.77224
A83: 檢查：分部合計 − 合併營收（FY2025 實績、FY2026 錨點） | B83: ¥B | C83: =C74+C80+C81-q25_rev -> -0.001 | D83: =D74+D80+D81-q26_rev -> 0
A84: 營收年增 | B84: % | D84: =D82/C82-1 -> 0.32148006 | E84: =E82/D82-1 -> 0.2881069 | F84: =F82/E82-1 -> 0.072632957 | G84: =G82/F82-1 -> 0.13929955
A85: AI 伺服器載板 ÷ 營收 | B85: % | D85: =D71/D82 -> 0.44318182 | E85: =E71/E82 -> 0.55460712 | F85: =F71/F82 -> 0.57199886 | G85: =G71/G82 -> 0.61262741
A86: 陶瓷＋其他事業營業利益＋調整 | B86: ¥B | C86: =q25_oi-q25_eoi -> 16.779 | D86: =q26_oi-q26_eoi -> 17 | E86: =E80*m_cer+E81*m_oth+q26_adj -> 17.24695 | F86: =F80*m_cer+F81*m_oth+q26_adj -> 17.570318 | G86: =G80*m_cer+G81*m_oth+q26_adj -> 17.903388
A87: 營業利益 | B87: ¥B | C87: =C77+C86 -> 62.027 | D87: =D77+D86 -> 127 | E87: =E77+E86 -> 183.49935 | F87: =F77+F86 -> 185.926 | G87: =G77+G86 -> 200.11509
A88: 營業利益率 | B88: % | C88: =C87/C82 -> 0.14903172 | D88: =D87/D82 -> 0.23090909 | E88: =E87/E82 -> 0.25901203 | F88: =F87/F82 -> 0.24466643 | G88: =G87/G82 -> 0.23114057
A89: 淨利（歸屬母公司） | B89: ¥B | C89: =q25_ni -> 63.713 | D89: =q26_ni -> 84 | E89: =E87*ni_oi -> 121.29307 | F89: =F87*ni_oi -> 122.89709 | G89: =G87*ni_oi -> 132.27608
A90: 股數（分割後） | B90: 十億股 | D90: =q26_sh -> 0.56119722 | E90: =D90*(1+sh_g) -> 0.56119722 | F90: =E90*(1+sh_g) -> 0.56119722 | G90: =F90*(1+sh_g) -> 0.56119722
A91: EPS（日圓） | B91: ¥ | C91: =q25_eps -> 114.08 | D91: =D89/D90 -> 149.68 | E91: =E89/E90 -> 216.1327 | F91: =F89/F90 -> 218.9909 | G91: =G89/G90 -> 235.70337
A92: EPS 年增 | B92: % | D92: =D91/C91-1 -> 0.31206171 | E92: =E91/D91-1 -> 0.44396512 | F92: =F91/E91-1 -> 0.013224293 | G92: =G91/F91-1 -> 0.076315806
A95: 情境 B：CY2028 顆數 ×0.8、CY2029 ×0.85
A96: 項目 | B96: 單位 | C96: FY2025A | D96: FY2026（錨點） | E96: FY2027 | F96: FY2028 | G96: FY2029 | H96: 說明
A97: A. AI 伺服器載板（D 欄＝FY2026 校準年；FY(t) 對照 CY(t) 顆數）
A98: NVIDIA 加速器顆數 × 情境係數 | B98: 百萬顆 | D98: =(u_bw_26+u_rb_26+u_ru_26+u_hp_26)*1 -> 7.6 | E98: =(u_bw_27+u_rb_27+u_ru_27+u_hp_27)*1 -> 9.7 | F98: =(u_bw_28+u_rb_28+u_ru_28+u_hp_28)*um28_B -> 7.6 | G98: =(u_bw_28*(1+g29_bw)+u_rb_28*(1+g29_rb)+u_ru_28*(1+g29_ru)+u_hp_28*(1+g29_hp))*um29_B -> 9.01 | H98: markets/network In：Blackwell、Rubin、Rubin Ultra、Hopper
A99: 非 NVIDIA 加速器顆數 × 情境係數 | B99: 百萬顆 | D99: =(u_amd_26+u_tpu_26+u_trn_26+u_oth_26)*1 -> 7.6 | E99: =(u_amd_27+u_tpu_27+u_trn_27+u_oth_27)*1 -> 14 | F99: =(u_amd_28+u_tpu_28+u_trn_28+u_oth_28)*um28_B -> 13.6 | G99: =(u_amd_28*(1+g29_amd)+u_tpu_28*(1+g29_tpu)+u_trn_28*(1+g29_trn)+u_oth_28*(1+g29_oth))*um29_B -> 16.6175 | H99: AMD、TPU、Trainium、其他 ASIC
A100: 有效顆數 ＝ NVIDIA ＋ 權重 × 非 NVIDIA | B100: 百萬顆 | D100: =D98+w_ot*D99 -> 10.64 | E100: =E98+w_ot*E99 -> 15.3 | F100: =F98+w_ot*F99 -> 13.04 | G100: =G98+w_ot*G99 -> 15.657
A101: FY2026 AI 載板營收（錨點電子事業 × AI 占比） | B101: ¥B | D101: =q26_e*ai_e -> 243.75 | H101: Assumed 切分；公司未揭露
A102: 每顆有效金額（Ibiden 份額 × 載板金額；FY2026 校準） | B102: 千日圓／顆 | D102: =D101/D100 -> 22.908835 | H102: Derived：¥B ÷ 百萬顆＝千日圓／顆。÷ 匯率即美元／顆（Units 頁）
A103: 每顆載板金額指數（面積、層數；FY2026＝1） | B103: x | D103: =1 -> 1 | E103: =D103*(1+g_asp) -> 1.18 | F103: =E103*(1+g_asp) -> 1.3924 | G103: =F103*(1+g_asp) -> 1.643032
A104: Ibiden 份額相對值（÷ FY2026） | B104: x | D104: =1 -> 1 | E104: =rel_27 -> 0.95 | F104: =rel_28 -> 0.88 | G104: =rel_29 -> 0.85
A105: 短缺溢價指數（FY2026＝1） | B105: x | D105: =1 -> 1 | E105: =pp_27 -> 1 | F105: =pp_28 -> 0.95 | G105: =pp_29 -> 0.9
A106: AI 伺服器載板營收 | B106: ¥B | D106: =D101 -> 243.75 | E106: =E100*$D$102*E103*E104*E105 -> 392.91629 | F106: =F100*$D$102*F103*F104*F105 -> 347.73698 | G106: =G100*$D$102*G103*G104*G105 -> 450.83643
A107: B. 電子事業
A108: 電子事業非 AI 營收（通用伺服器、PC 等） | B108: ¥B | D108: =q26_e-D106 -> 131.25 | E108: =D108*(1+g_ne) -> 137.8125 | F108: =E108*(1+g_ne) -> 144.70312 | G108: =F108*(1+g_ne) -> 151.93828
A109: 電子事業營收 | B109: ¥B | C109: =q25_e -> 243.316 | D109: =D106+D108 -> 375 | E109: =E106+E108 -> 530.72879 | F109: =F106+F108 -> 492.44011 | G109: =G106+G108 -> 602.77471
A110: AI 載板營業利益率（FY2026 校準） | B110: % | D110: =(q26_eoi-m_ne*D108)/D106 -> 0.37051282 | H110: Derived：使 FY2026 電子事業營業利益＝錨點；非 AI 營益率為 In 頁 m_ne
A111: AI 載板營業利益率 ＝ 1 −（1 − 校準值）÷ 溢價指數 | B111: % | D111: =D110 -> 0.37051282 | E111: =1-(1-$D$110)/E105 -> 0.37051282 | F111: =1-(1-$D$110)/F105 -> 0.33738192 | G111: =1-(1-$D$110)/G105 -> 0.3005698 | H111: Derived：每單位成本不變，價格隨溢價指數升降，差額全部落在利潤
A112: 電子事業營業利益 | B112: ¥B | C112: =q25_eoi -> 45.248 | D112: =D106*D111+D108*m_ne -> 110 | E112: =E106*E111+E108*m_ne -> 166.2524 | F112: =F106*F111+F108*m_ne -> 139.02564 | G112: =G106*G111+G108*m_ne -> 158.29856
A113: 電子事業營益率 | B113: % | C113: =C112/C109 -> 0.18596393 | D113: =D112/D109 -> 0.29333333 | E113: =E112/E109 -> 0.31325302 | F113: =F112/F109 -> 0.28231989 | G113: =G112/G109 -> 0.26261646
A114: C. 陶瓷、其他事業與全公司
A115: 陶瓷事業營收 | B115: ¥B | C115: =q25_cer -> 82.554 | D115: =q26_cer -> 84 | E115: =D115*(1+g_cer) -> 84 | F115: =E115*(1+g_cer) -> 84 | G115: =F115*(1+g_cer) -> 84
A116: 其他事業營收 | B116: ¥B | C116: =q25_oth -> 90.33 | D116: =q26_oth -> 91 | E116: =D116*(1+g_oth) -> 93.73 | F116: =E116*(1+g_oth) -> 96.5419 | G116: =F116*(1+g_oth) -> 99.438157
A117: 營收 | B117: ¥B | C117: =C109+C115+C116 -> 416.2 | D117: =D109+D115+D116 -> 550 | E117: =E109+E115+E116 -> 708.45879 | F117: =F109+F115+F116 -> 672.98201 | G117: =G109+G115+G116 -> 786.21287
A118: 檢查：分部合計 − 合併營收（FY2025 實績、FY2026 錨點） | B118: ¥B | C118: =C109+C115+C116-q25_rev -> -0.001 | D118: =D109+D115+D116-q26_rev -> 0
A119: 營收年增 | B119: % | D119: =D117/C117-1 -> 0.32148006 | E119: =E117/D117-1 -> 0.2881069 | F119: =F117/E117-1 -> -0.050076008 | G119: =G117/F117-1 -> 0.16825244
A120: AI 伺服器載板 ÷ 營收 | B120: % | D120: =D106/D117 -> 0.44318182 | E120: =E106/E117 -> 0.55460712 | F120: =F106/F117 -> 0.51671067 | G120: =G106/G117 -> 0.57342795
A121: 陶瓷＋其他事業營業利益＋調整 | B121: ¥B | C121: =q25_oi-q25_eoi -> 16.779 | D121: =q26_oi-q26_eoi -> 17 | E121: =E115*m_cer+E116*m_oth+q26_adj -> 17.24695 | F121: =F115*m_cer+F116*m_oth+q26_adj -> 17.570318 | G121: =G115*m_cer+G116*m_oth+q26_adj -> 17.903388
A122: 營業利益 | B122: ¥B | C122: =C112+C121 -> 62.027 | D122: =D112+D121 -> 127 | E122: =E112+E121 -> 183.49935 | F122: =F112+F121 -> 156.59596 | G122: =G112+G121 -> 176.20195
A123: 營業利益率 | B123: % | C123: =C122/C117 -> 0.14903172 | D123: =D122/D117 -> 0.23090909 | E123: =E122/E117 -> 0.25901203 | F123: =F122/F117 -> 0.23268966 | G123: =G122/G117 -> 0.22411481
A124: 淨利（歸屬母公司） | B124: ¥B | C124: =q25_ni -> 63.713 | D124: =q26_ni -> 84 | E124: =E122*ni_oi -> 121.29307 | F124: =F122*ni_oi -> 103.50993 | G124: =G122*ni_oi -> 116.46949
A125: 股數（分割後） | B125: 十億股 | D125: =q26_sh -> 0.56119722 | E125: =D125*(1+sh_g) -> 0.56119722 | F125: =E125*(1+sh_g) -> 0.56119722 | G125: =F125*(1+sh_g) -> 0.56119722
...

Sheet Val
A1: Val — P/E 估值（日圓）。結論用「現價 ÷ FY2026–FY2028 EPS（模型）」與 what must be true。十年 P/E 規則值待 Bloomberg（10-27 抓取單加 4062）：公開資料商的 Ibiden 十年 P/E 本版未取得，規則值本版不計
A2: 循環位置：Ibiden 不套設備股見頂年；以本模型營收最高的會計年度為見頂年（比照 NVIDIA、Arista）。營收到 FY2029 仍在增加時，見頂年未知，判為中段
A3: 目標價：見第 0 節（本頁第 61 列；v0.2 新增，DCF 與 Comparable 加權）。第 36 列「舊法：規則值情境加權（參考）」不再是目標價，只作參考
A4: 1. 價格與市場隱含倍數
A5: 項目 | B5: A | C5: B | D5: C | E5: 說明
A6: 現價（2026-10-23 收盤，分割後） | B6: =px -> 8512
A7: 現價 ÷ FY2026 EPS（錨點） | B7: =px/PL!D12 -> 56.867985 | C7: =px/PL!D23 -> 56.867985 | D7: =px/PL!D34 -> 56.867985
A8: 現價 ÷ FY2027 EPS（模型） | B8: =px/PL!E12 -> 39.383212 | C8: =px/PL!E23 -> 39.383212 | D8: =px/PL!E34 -> 39.383212 | E8: FY2027 三情境相同（顆數係數從 CY2028 開始）
A9: 現價 ÷ FY2028 EPS（模型） | B9: =px/PL!F12 -> 38.869195 | C9: =px/PL!F23 -> 46.149301 | D9: =px/PL!F34 -> 56.784992
A10: 現價 ÷ FY2029 EPS（模型） | B10: =px/PL!G12 -> 36.113188 | C10: =px/PL!G23 -> 41.014268 | D10: =px/PL!G34 -> 53.003069
A11: 前瞻 P/E（stockanalysis） | B11: =pe_fwd_sa -> 53.97 | E11: 口徑：未來 12 個月
A12: 隱含未來 12 月 EPS ＝ 取得時價格（10-16 9,764）÷ 前瞻 P/E | B12: =cons_feps -> 180.91532
A13: 近 12 月 P/E（stockanalysis） | B13: =pe_ttm -> 83.85
A15: 2. 循環位置（本模型營收最高年）
A16: 情境 | B16: 營收最高年（FY2026–FY2029） | C16: FY2027 判定 | D16: 見頂年是否未知 | E16: 說明
A17: A | B17: =INDEX({2026,2027,2028,2029},MATCH(MAX(PL!D82:G82),PL!D82:G82,0)) -> 2029 | C17: =IF(B17=2029,"中段",IF(2027<B17,"中段",IF(2027=B17,"見頂","谷底"))) -> 中段 | D17: =IF(B17=2029,"是：營收到觀測期末仍在增加","否") -> 是：營收到觀測期末仍在增加 | E17: tools/cycle_position.py excel_rule；營收最高年取代設備市場見頂年；對應倍數待十年 P/E
A18: B | B18: =INDEX({2026,2027,2028,2029},MATCH(MAX(PL!D117:G117),PL!D117:G117,0)) -> 2029 | C18: =IF(B18=2029,"中段",IF(2027<B18,"中段",IF(2027=B18,"見頂","谷底"))) -> 中段 | D18: =IF(B18=2029,"是：營收到觀測期末仍在增加","否") -> 是：營收到觀測期末仍在增加 | E18: 同上
A19: C | B19: =INDEX({2026,2027,2028,2029},MATCH(MAX(PL!D152:G152),PL!D152:G152,0)) -> 2027 | C19: =IF(B19=2029,"中段",IF(2027<B19,"中段",IF(2027=B19,"見頂","谷底"))) -> 見頂 | D19: =IF(B19=2029,"是：營收到觀測期末仍在增加","否") -> 否 | E19: 同上
A21: 3. What must be true：FY2027 年底價 ＝ 現價 ×（1＋報酬）所需的倍數（看 FY2028 EPS）
A22: FY2027 年底價 ÷ 現價 | B22: 所需倍數（÷ FY2028 EPS，A） | C22: 所需倍數（÷ FY2028 EPS，B） | D22: 所需倍數（÷ FY2028 EPS，C） | E22: 對照：Andy 合理 P/E
A23: 0.5 | B23: =px*A23/PL!F12 -> 19.434597 | C23: =px*A23/PL!F23 -> 23.07465 | D23: =px*A23/PL!F34 -> 28.392496 | E23: =pe_fair_andy -> 25
A24: 0.75 | B24: =px*A24/PL!F12 -> 29.151896 | C24: =px*A24/PL!F23 -> 34.611975 | D24: =px*A24/PL!F34 -> 42.588744 | E24: =pe_fair_andy -> 25
A25: 1 | B25: =px*A25/PL!F12 -> 38.869195 | C25: =px*A25/PL!F23 -> 46.149301 | D25: =px*A25/PL!F34 -> 56.784992 | E25: =pe_fair_andy -> 25
A26: 1.21 | B26: =px*A26/PL!F12 -> 47.031726 | C26: =px*A26/PL!F23 -> 55.840654 | D26: =px*A26/PL!F34 -> 68.70984 | E26: =pe_fair_andy -> 25
A27: 1.5 | B27: =px*A27/PL!F12 -> 58.303792 | C27: =px*A27/PL!F23 -> 69.223951 | D27: =px*A27/PL!F34 -> 85.177487 | E27: =pe_fair_andy -> 25
A28: 讀法：1.00＝價格不變、1.21＝一年約 21%。所需倍數愈高，現價愈依賴「短缺溢價延續到 2028 年以後」。
A30: 4. 對照：以 Andy 合理 P/E 25x 計算的隱含價（只作對照，非規則值）
A31: 情境 | B31: FY2027 EPS | C31: × 25x | D31: 相對現價 | E31: FY2028 EPS | F31: × 25x | G31: 相對現價
A32: A | B32: =PL!E12 -> 216.1327 | C32: =B32*pe_fair_andy -> 5403.3175 | D32: =C32/px-1 -> -0.36521176 | E32: =PL!F12 -> 218.9909 | F32: =E32*pe_fair_andy -> 5474.7725 | G32: =F32/px-1 -> -0.35681714
A33: B | B33: =PL!E23 -> 216.1327 | C33: =B33*pe_fair_andy -> 5403.3175 | D33: =C33/px-1 -> -0.36521176 | E33: =PL!F23 -> 184.44483 | F33: =E33*pe_fair_andy -> 4611.1208 | G33: =F33/px-1 -> -0.45827998
A34: C | B34: =PL!E34 -> 216.1327 | C34: =B34*pe_fair_andy -> 5403.3175 | D34: =C34/px-1 -> -0.36521176 | E34: =PL!F34 -> 149.89876 | F34: =E34*pe_fair_andy -> 3747.4691 | G34: =F34/px-1 -> -0.55974282
A36: 舊法：規則值情境加權（參考；v0.1.1 的「0. 目標價與上檔空間」改名，不再是目標價）
A37: 項目 | B37: 數值 | E37: 說明
A38: 舊法隱含價（情境加權，參考） | B38: =tp_wA*B40+tp_wB*B41+tp_wC*B42 -> 9531.452 | E38: 權重 × 各情境隱含價
A39: 舊法隱含價相對現價（÷ 現價 − 1） | B39: =B38/px-1 -> 0.11976645 | E39: 現價＝In 頁 px（2026-10-23 收盤，分割後）
A40: 情境 A 隱含價（樂觀） | B40: =$B$58*PL!E12 -> 9531.452 | E40: 情境 A FY2027 EPS（PL 頁）× 十年 P/E 中位數（第 0a 節）
A41: 情境 B 隱含價（基準） | B41: =$B$58*PL!E23 -> 9531.452 | E41: 情境 B FY2027 EPS（PL 頁）× 十年 P/E 中位數（第 0a 節）
A42: 情境 C 隱含價（下檔） | B42: =$B$58*PL!E34 -> 9531.452 | E42: 情境 C FY2027 EPS（PL 頁）× 十年 P/E 中位數（第 0a 節）
A43: 情境權重 A／B／C | B43: =tp_wA -> 0.3 | C43: =tp_wB -> 0.5 | D43: =tp_wC -> 0.2 | E43: ="合計 "&TEXT(B43+C43+D43,"0%")&"；In 頁 tp_wA／tp_wB／tp_wC（Assumed，Andy 可改）" -> 合計 100%；In 頁 tp_wA／tp_wB／tp_wC（Assumed，Andy 可改）
A44: 舊法說明 | B44: P/E：十年（2016–2025 日曆年年底）P/E 中位數（companiesmarketcap 單一來源，第 0a 節；2017 年虧損不計，9 年）× 各情境 FY2027 EPS（FY2027＝2027-04～2028-03）。本模型無規則值（十年 P/E 待 Bloomberg），依工作單改用此備案；倍數為日曆年年底口徑，與 3 月制會計年度不完全對齊。十年倍數多為 AI 載板需求前的時期（2019 年獲利低谷約 137x 為極值，中位數受影響小），偏誤方向不明確；FY2027 三情境 EPS 相同（情境差從 FY2028 起），故三情境隱含價相同；隱含價約為 FY2027 年底（2028-03）的價格、未折現，當作 12 個月目標價時偏高。
A46: 0a. 十年 P/E（舊法用；companiesmarketcap 日曆年年底 P/E，Interested-party，資料商；第二來源：未找到）
A47: 年底 | B47: P/E | C47: 計入中位數 | D47: 說明
A48: 2016 | B48: 44.1 | C48: 是 | D48: https://companiesmarketcap.com/ibiden/pe-ratio/（2026-10-25 讀取）
A49: 2017 | B49: -6.66 | C49: 否 | D49: 虧損年，P/E 為負，不計
A50: 2018 | B50: 35.3 | C50: 是
A51: 2019 | B51: 137 | C51: 是
A52: 2020 | B52: 55.2 | C52: 是
A53: 2021 | B53: 53.1 | C53: 是
A54: 2022 | B54: 40.7 | C54: 是
A55: 2023 | B55: 26.8 | C55: 是
A56: 2024 | B56: 57.2 | C56: 是
A57: 2025 | B57: 33.6 | C57: 是
A58: 中位數（計入者） | B58: =MEDIAN(B48,B50,B51,B52,B53,B54,B55,B56,B57) -> 44.1
A61: 0. 目標價（DCF 與 Comparable 加權；v0.2 新增，放在本頁既有內容之後以免位移既有儲存格；三情境欄 B／C／D＝A 順利／B 平平／C 不如預期）
A62: 0.1 DCF（股東權益現金流，FY2027–FY2032 明確期＋FY2032 後永續）
A63: 項目 | B63: A（順利） | C63: B（平平） | D63: C（不如預期） | E63: 說明
A64: 情境 EPS（FY2027–FY2032） | E64: PL 頁延伸表；FY2030 起為收斂法
A65: FY2027 | B65: =PL!E173 -> 216.1327 | C65: =PL!E185 -> 216.1327 | D65: =PL!E197 -> 216.1327
A66: FY2028 | B66: =PL!F173 -> 218.9909 | C66: =PL!F185 -> 184.44483 | D66: =PL!F197 -> 149.89876
A67: FY2029 | B67: =PL!G173 -> 235.70337 | C67: =PL!G185 -> 207.53753 | D67: =PL!G197 -> 160.59448
A68: FY2030 | B68: =PL!H173 -> 262.30635 | C68: =PL!H185 -> 225.7977 | D68: =PL!H197 -> 162.40796
A69: FY2031 | B69: =PL!I173 -> 284.97832 | C69: =PL!I185 -> 236.05221 | D69: =PL!I197 -> 158.61374
A70: FY2032 | B70: =PL!J173 -> 302.07702 | C70: =PL!J185 -> 236.72665 | D70: =PL!J197 -> 149.34094
A71: 股東現金流＝EPS ×（1 − tp_g ÷ tp_roe）
A72: 再投資率（tp_g ÷ tp_roe，上限 0.8） | B72: =MIN(tp_g/tp_roe,0.8) -> 0.46439628 | E72: ROE 為近三年平均（In 頁 tp_roe）
A73: FY2027 | B73: =B65*(1-$B$72) -> 115.76148 | C73: =C65*(1-$B$72) -> 115.76148 | D73: =D65*(1-$B$72) -> 115.76148
A74: FY2028 | B74: =B66*(1-$B$72) -> 117.29234 | C74: =C66*(1-$B$72) -> 98.789337 | D74: =D66*(1-$B$72) -> 80.286334
A75: FY2029 | B75: =B67*(1-$B$72) -> 126.2436 | C75: =C67*(1-$B$72) -> 111.15787 | D75: =D67*(1-$B$72) -> 86.014998
A76: FY2030 | B76: =B68*(1-$B$72) -> 140.49226 | C76: =C68*(1-$B$72) -> 120.93809 | D76: =D68*(1-$B$72) -> 86.986306
A77: FY2031 | B77: =B69*(1-$B$72) -> 152.63545 | C77: =C69*(1-$B$72) -> 126.43044 | D77: =D69*(1-$B$72) -> 84.954111
A78: FY2032 | B78: =B70*(1-$B$72) -> 161.79358 | C78: =C70*(1-$B$72) -> 126.79167 | D78: =D70*(1-$B$72) -> 79.987563
A79: DCF 情境每股價值（折現率 tp_r） | B79: =SUMPRODUCT(B73:B78,1/(1+tp_r)^{1;2;3;4;5;6})+B78*(1+tp_g)/(tp_r-tp_g)/(1+tp_r)^6 -> 2162.1063 | C79: =SUMPRODUCT(C73:C78,1/(1+tp_r)^{1;2;3;4;5;6})+C78*(1+tp_g)/(tp_r-tp_g)/(1+tp_r)^6 -> 1743.6296 | D79: =SUMPRODUCT(D73:D78,1/(1+tp_r)^{1;2;3;4;5;6})+D78*(1+tp_g)/(tp_r-tp_g)/(1+tp_r)^6 -> 1176.1434 | E79: Σ 明確期現金流 ÷ (1＋r)^t ＋ 永續價值 ÷ (1＋r)^6；永續價值＝FY2032 現金流 ×(1＋g)÷(r−g)；基準日 2026 年底，t＝1 對 FY2027
A80: DCF 情境價值推到 12 個月後（×(1＋tp_r)） | B80: =B79*(1+tp_r) -> 2378.3169 | C80: =C79*(1+tp_r) -> 1917.9925 | D80: =D79*(1+tp_r) -> 1293.7578
A81: DCF 目標價（情境加權） | B81: =tp_wA*B80+tp_wB*C80+tp_wC*D80 -> 1931.2429 | E81: Σ tp_wA／wB／wC × 情境價值 ×(1＋tp_r)；權重見 In 頁
A83: 0.2 Comparable（市場主流同業前瞻 P/E）
A84: 同業與前瞻 P/E | B84: 代號 | C84: 前瞻 12 月 P/E | D84: 日期 | E84: 來源 | F84: 標記
A85: 欣興（Unimicron） | B85: 3037.TW | C85: 42.28 | D85: 2026-10-22 | E85: stockanalysis.com 個股頁 Forward PE（分析師共識；價格日期如左） | F85: Interested-party（賣方共識）
A86: 南電（Nan Ya PCB） | B86: 8046.TW | C86: 33.73 | D86: 2026-09-07 | E86: stockanalysis.com 個股頁 Forward PE（分析師共識；價格日期如左） | F86: Interested-party（賣方共識）
A87: 景碩（Kinsus） | B87: 3189.TW | C87: 44.7 | D87: 2026-10-22 | E87: stockanalysis.com 個股頁 Forward PE（分析師共識；價格日期如左） | F87: Interested-party（賣方共識）
A88: 三星電機（Samsung Electro-Mechanics） | B88: 009150.KS | C88: 43.4 | D88: 2026-08-28 | E88: stockanalysis.com 個股頁 Forward PE（分析師共識；價格日期如左） | F88: Interested-party（賣方共識）
A89: AT&S | B89: ATS.VI | C89: 14.91 | D89: 2026-10-23 | E89: stockanalysis.com 個股頁 Forward PE（分析師共識；價格日期如左） | F89: Interested-party（賣方共識）
A90: 同業前瞻 P/E 中位數 | B90: =MEDIAN(C85:C89) -> 42.28 | E90: ABF／FC-BGA 載板同業：欣興、南電、景碩、三星電機、AT&S（券商常用的載板比較組；新光電氣 2025 年下市未列）。非 A 股公司的同業名單不放中國 A 股（A 股有結構性溢價；Andy 2026-10-25 11:53）
A91: 12 個月後的前瞻 EPS（情境加權） | B91: =tp_wA*(0.5*B65+0.5*B66)+tp_wB*(0.5*C65+0.5*C66)+tp_wC*(0.5*D65+0.5*D66) -> 202.01607 | E91: 會計年度 4 月至隔年 3 月：約 2027-10 時的未來 12 月（2027-10～2028-09）≈ 6／12 × FY2027＋6／12 × FY2028
A92: Comparable 目標價 | B92: =B90*B91 -> 8541.2394 | E92: 同業中位數 × 上列 EPS
A94: 0.3 結論
A95: 項目 | B95: 數值 | E95: 說明
A96: 目標價（DCF 與 Comparable 加權） | B96: =tp_w_dcf*B81+(1-tp_w_dcf)*tp_comp_adj -> 6498.509 | E96: tp_w_dcf × DCF 目標價＋（1 − tp_w_dcf）× Comparable 目標價；tp_w_dcf 見 In 頁
A97: Comparable 目標價（市場主流同業法） | B97: =B92 -> 8541.2394 | E97: 引用 0.2
A98: 市場共識目標價 | B98: =cons_tp -> 12432.35 | E98: stockanalysis 個股頁（S&P Global 彙整）18 位分析師平均目標價 12,432（頁面價格日期 2026-10-16；分割後）
A99: 上檔空間：加權目標價 | B99: =B96/px-1 -> -0.23654734 | E99: 現價＝In 頁 px（2026-10-23 收盤 8,512，分割後）
A100: 上檔空間：Comparable 目標價 | B100: =B97/px-1 -> 0.0034350801
A101: 與市場共識目標價的差距：EPS 因素 | B101: =B91/cons_feps-1 -> 0.11663327 | E101: 本模型前瞻 EPS ÷ 共識前瞻 EPS − 1；共識前瞻 EPS 見 In 頁 cons_feps 與 Recon
A102: 與市場共識目標價的差距：倍數因素 | B102: =(cons_tp/cons_feps)/B90-1 -> 0.62533503 | E102: ="共識目標價 ÷ 共識前瞻 EPS 隱含 "&TEXT(cons_tp/cons_feps,"0.0")&"x，同業中位數 "&TEXT(B90,"0.0")&"x" -> 共識目標價 ÷ 共識前瞻 EPS 隱含 68.7x，同業中位數 42.3x
A103: 價格帶（DCF 不如預期～順利） | B103: =TEXT(D80,"#,##0")&"～"&TEXT(B80,"#,##0") -> 1,294～2,378 | E103: C 情境價值～A 情境價值（推到 12 個月後）
A104: 歷史倍數檢查：現價隱含 P/E 的十年分位（A／B／C） | B104: =IF(px/B66<=MIN($B$108:$K$108),0,IF(px/B66>=MAX($B$108:$K$108),1,PERCENTRANK($B$108:$K$108,px/B66))) -> 0.333 | C104: =IF(px/C66<=MIN($B$108:$K$108),0,IF(px/C66>=MAX($B$108:$K$108),1,PERCENTRANK($B$108:$K$108,px/C66))) -> 0.528 | D104: =IF(px/D66<=MIN($B$108:$K$108),0,IF(px/D66>=MAX($B$108:$K$108),1,PERCENTRANK($B$108:$K$108,px/D66))) -> 0.849 | E104: 現價 ÷ 各情境 FY2028 EPS 在 2016–2025 年底 P/E 分布（下方列）的分位；低於最小值記 0%、高於最大值記 100%；只作檢查，不進目標價
A105: 目標價方法 | B105: DCF：股東現金流＝EPS ×（1 − g／ROE），r＝10%、g＝4%、ROE＝近三年平均約 8.6%（再投資率約 46%），FY2027–29 驅動因子、FY2030–32 收斂法＋永續；基準日 2026 年底（FY2027 實際於 2028-03 結束，未做半年調整）。Ibiden 資本密集（FY2026 設備投資 2,100 億），但模型無折舊與資本支出明細，未改用淨利＋折舊－資本支出，現金流偏高估。Comparable：欣興、南電、景碩、三星電機、AT&S 前瞻 P/E 中位數；台系載板股含 AI 題材溢價（約 34–45x），部分價格為 8–9 月，偏高估。情境對應：A＝順利、B＝平平、C＝不如預期（原顆數情境）。
A107: 十年年底 P/E（歷史分位檢查用；companiesmarketcap 日曆年年底 P/E，Interested-party；2017 年虧損不計） | B107: 2016 | C107: 2017 | D107: 2018 | E107: 2019 | F107: 2020 | G107: 2021 | H107: 2022 | I107: 2023 | J107: 2024 | K107: 2025
A108: 年底 P/E | B108: 44.1 | D108: 35.3 | E108: 137 | F108: 55.2 | G108: 53.1 | H108: 40.7 | I108: 26.8 | J108: 57.2 | K108: 33.6
A109: 上檔空間級距 | B109: =IF(B99>0.5,"大於 50%",IF(B99>0.25,"25%–50%",IF(B99>=0,"0%–25%",IF(B99>=-0.25,"0%～−25%",IF(B99>=-0.5,"−25%～−50%","小於 −50%"))))) -> 0%～−25% | E109: 以「上檔空間：加權目標價」（第 99 列）分六級（Andy 2026-10-25 14:00）
A110: 投資建議 | B110: =IF(B99>0.5,"強力買進",IF(B99>0.25,"買進",IF(B99>=-0.25,"中立",IF(B99>=-0.5,"放空","強力放空")))) -> 中立 | E110: 依上檔空間固定規則（Andy 2026-10-25 14:17）：大於 +50% 強力買進、+25%～+50% 買進、−25%～+25% 中立、−50%～−25% 放空、小於 −50% 強力放空（剛好 +25% 為中立、+50% 為買進、−25% 為中立、−50% 為放空）
...

Sheet Recon
A1: Recon — 本模型 vs 公司目標、研調份額、先驗。只作事後對照，不為對上數字而調參數。FY2027 以後的共識：未找到（付費）
A3: 項目 | B3: 對照值 | C3: 模型 A | D3: 差距 A | E3: 模型 B | F3: 差距 B | G3: 模型 C | H3: 差距 C | I3: 對照來源 | J3: 說明
A4: A. 公司目標與市場（校準未使用）
A5: FY2029 營收 vs 公司 FY2030 目標 ¥1 兆 | B5: =tgt30_rev -> 1000 | C5: =PL!G82 -> 865.77224 | D5: =C5/B5-1 -> -0.13422776 | E5: =PL!G117 -> 786.21287 | F5: =E5/B5-1 -> -0.21378713 | G5: =PL!G152 -> 653.61392 | H5: =G5/B5-1 -> -0.34638608 | I5: Quartr 摘要（Interested-party） | J5: 模型到 FY2029；目標年晚一年
A6: FY2029 營業利益 vs 公司 FY2030 目標 ¥3,000 億 | B6: =tgt30_oi -> 300 | C6: =PL!G87 -> 200.11509 | D6: =C6/B6-1 -> -0.3329497 | E6: =PL!G122 -> 176.20195 | F6: =E6/B6-1 -> -0.41266018 | G6: =PL!G157 -> 136.34671 | H6: =G6/B6-1 -> -0.54551098 | I6: 同上
A7: FY2027 EPS vs 前瞻 P/E 隱含未來 12 月 EPS | B7: =cons_feps -> 180.91532 | C7: =PL!E91 -> 216.1327 | D7: =C7/B7-1 -> 0.19466221 | E7: =PL!E126 -> 216.1327 | F7: =E7/B7-1 -> 0.19466221 | G7: =PL!E161 -> 216.1327 | H7: =G7/B7-1 -> 0.19466221 | I7: stockanalysis（推導） | J7: 未來 12 月 ≈ ½ FY2026＋½ FY2027，口徑不同，只作量級比較
A8: B. 份額與每顆金額（先驗比對的機制檢查）
A9: FY2026 每顆 NVIDIA 載板金額（美元）vs 先驗比對推導中點 $225 | B9: 225 | C9: =Units!C8 -> 215.3086 | D9: =C9/B9-1 -> -0.043072908 | E9: =Units!C8 -> 215.3086 | F9: =E9/B9-1 -> -0.043072908 | G9: =Units!C8 -> 215.3086 | H9: =G9/B9-1 -> -0.043072908 | I9: 先驗比對_Ibiden（Drive） | J9: 推導區間 $150–300；封裝全部（中介層＋載板＋組裝）B200 約 $1,100（Silicon Analysts）
A10: FY2026 每 GW Ibiden 營收（US$M）vs 先驗比對推導中點 75 | B10: 75 | C10: =Units!C12 -> 77.096949 | D10: =C10/B10-1 -> 0.027959321 | E10: =Units!C12 -> 77.096949 | F10: =E10/B10-1 -> 0.027959321 | G10: =Units!C12 -> 77.096949 | H10: =G10/B10-1 -> 0.027959321 | I10: 先驗比對_Ibiden（Drive）
A11: FY2027 AI 載板 ÷ 營收 | C11: =PL!E85 -> 0.55460712 | E11: =PL!E120 -> 0.55460712 | G11: =PL!E155 -> 0.55460712 | I11: —
A12: FY2028 電子事業營益率 vs FY2026 錨點（百分點） | B12: =q26_eoi/q26_e -> 0.29333333 | C12: =PL!F78 -> 0.29058187 | D12: =C12-B12 -> -0.0027514674 | E12: =PL!F113 -> 0.28231989 | F12: =E12-B12 -> -0.011013441 | G12: =PL!F148 -> 0.27051544 | H12: =G12-B12 -> -0.022817895 | I12: 錨點 | J12: 短缺溢價回落使營益率下滑
A13: C. 預留
A14: 產能上限（Ibiden 2028 年為 2024 年 2.5–2.8 倍）與需求面積的對照：2024 年基準面積未找到，本版不計 | J14: 預留列：本版無數值
A15: R4 產業部署路徑（markets/deploy_path/，尚未建立）：上線後以 AI 載板營收 ÷ 部署 GW 取代 Units 頁的每 GW 換算 | J15: 預留列：本版無數值
A17: E. 目標價對帳（v0.2；模型欄為情境加權值，非情境 A）
A18: 12 個月後的前瞻 EPS（情境加權）vs 共識前瞻 EPS | B18: =cons_feps -> 180.91532 | C18: =Val!B91 -> 202.01607 | D18: =C18/B18-1 -> 0.11663327 | I18: stockanalysis 個股頁 2026-10-16：價格 9,764 ÷ Forward PE 53.97（即 In 頁 pe_fwd_sa） | J18: 共識只作對帳，不作校準
A19: 目標價（DCF 與 Comparable 加權）vs 市場共識目標價 | B19: =cons_tp -> 12432.35 | C19: =Val!B96 -> 6498.509 | D19: =C19/B19-1 -> -0.47729037 | I19: stockanalysis 個股頁（S&P Global 彙整）18 位分析師平均目標價 12,432（頁面價格日期 2026-10-16；分割後） | J19: 共識只作對帳，不作校準
A20: Comparable 目標價 vs 市場共識目標價 | B20: =cons_tp -> 12432.35 | C20: =Val!B92 -> 8541.2394 | D20: =C20/B20-1 -> -0.31298271 | I20: 同上 | J20: 共識只作對帳，不作校準

Sheet Sens
A1: Sens — 一次動一個輸入（情境 A；每顆有效金額與 AI 載板營益率在每個案例內依 FY2026 錨點重算，FY2026 恆等於錨點）：對 FY2027、FY2028 的營收、AI 載板營收、電子事業營益率與 EPS 的影響。每個案例是一個完整推導區塊（本頁下方）
A3: 案例 | B3: 設定 | C3: FY2027 營收 | D3: FY2027 AI 載板 | E3: FY2027 電子營益率 | F3: FY2027 EPS | G3: FY2027 EPS 相對基準 | H3: FY2028 營收 | I3: FY2028 AI 載板 | J3: FY2028 電子營益率 | K3: FY2028 EPS | L3: FY2028 EPS 相對基準
A4: 基準（情境 A） | B4: PL 區塊 A | C4: =PL!E82 -> 708.45879 | D4: =PL!E71 -> 392.91629 | E4: =PL!E78 -> 0.31325302 | F4: =PL!E91 -> 216.1327 | G4: =F4/F$4-1 -> 0 | H4: =PL!F82 -> 759.91625 | I4: =PL!F71 -> 434.67123 | J4: =PL!F78 -> 0.29058187 | K4: =PL!F91 -> 218.9909 | L4: =K4/K$4-1 -> 0
A5: 溢價快速回落 | B5: 價格溢價 2027 0.95、2028 0.85、2029 0.75（新產能提早到位） | C5: =E62 -> 688.81298 | D5: =E51 -> 373.27048 | E5: =E58 -> 0.28685476 | F5: =E71 -> 192.99309 | G5: =F5/F$4-1 -> -0.10706204 | H5: =F62 -> 714.16139 | I5: =F51 -> 388.91636 | J5: =F58 -> 0.22975326 | K5: =F71 -> 165.09903 | L5: =K5/K$4-1 -> -0.24609181
A6: 溢價延續 | B6: 價格溢價 2027 1.05、2028 1.05、2029 1.00 | C6: =E97 -> 728.10461 | D6: =E86 -> 412.56211 | E6: =E93 -> 0.3377667 | F6: =E106 -> 239.27231 | G6: =F6/F$4-1 -> 0.10706204 | H6: =F97 -> 805.67112 | I6: =F86 -> 480.42609 | J6: =F93 -> 0.34250606 | K6: =F106 -> 272.88277 | L6: =K6/K$4-1 -> 0.24609181
A7: 份額流失（低） | B7: 份額相對值 2027 0.85、2028 0.75、2029 0.70（欣興、三星電機加速） | C7: =E132 -> 667.09918 | D7: =E121 -> 351.55668 | E7: =E128 -> 0.30841364 | F7: =E141 -> 198.08318 | G7: =F7/F$4-1 -> -0.083511281 | H7: =F132 -> 695.70346 | I7: =F121 -> 370.45843 | J7: =F128 -> 0.28474843 | K7: =F141 -> 193.47392 | L7: =K7/K$4-1 -> -0.11652074
A8: 份額持平（高） | B8: 份額相對值 1.00 | C8: =E167 -> 729.1386 | D8: =E156 -> 413.5961 | E8: =E163 -> 0.31540047 | F8: =E176 -> 225.15746 | G8: =F8/F$4-1 -> 0.04175564 | H8: =F167 -> 819.1896 | I8: =F156 -> 493.94458 | J8: =F163 -> 0.29492541 | K8: =F176 -> 242.54504 | L8: =K8/K$4-1 -> 0.10755761
A9: 每顆金額年增 10% | B9: 面積、層數成長較慢 | C9: =E202 -> 681.8204 | D9: =E191 -> 366.2779 | E9: =E198 -> 0.31022716 | F9: =E211 -> 204.50759 | G9: =F9/F$4-1 -> -0.053786927 | H9: =F202 -> 702.97569 | I9: =F191 -> 377.73067 | J9: =F198 -> 0.28548108 | K9: =F211 -> 196.36377 | L9: =K9/K$4-1 -> -0.10332452
A10: 每顆金額年增 22% | B10: 較快 | C10: =E237 -> 721.77799 | D10: =E226 -> 406.23549 | E10: =E233 -> 0.31465484 | F10: =E246 -> 221.94526 | G10: =F10/F$4-1 -> 0.026893463 | H10: =F237 -> 789.88497 | I10: =F226 -> 464.63994 | J10: =F233 -> 0.29288359 | K10: =F246 -> 230.89992 | L10: =K10/K$4-1 -> 0.054381326
A11: 非 NVIDIA 權重 0.2 | B11: ASIC 多由其他載板廠供應 | C11: =E272 -> 690.05422 | D11: =E261 -> 374.51172 | E11: =E268 -> 0.31119604 | F11: =E281 -> 208.10086 | G11: =F11/F$4-1 -> -0.03716161 | H11: =F272 -> 726.58257 | I11: =F261 -> 401.33754 | J11: =F268 -> 0.2877249 | K11: =F281 -> 205.74471 | L11: =K11/K$4-1 -> -0.060487409
A12: 非 NVIDIA 權重 0.6 | B12: Ibiden 在 ASIC 份額較高 | C12: =E307 -> 722.26223 | D12: =E296 -> 406.71973 | E12: =E303 -> 0.31470451 | F12: =E316 -> 222.15658 | G12: =F12/F$4-1 -> 0.027871208 | H12: =F307 -> 784.91651 | I12: =F296 -> 459.67149 | J12: =F303 -> 0.29251777 | K12: =F316 -> 228.92555 | L12: =K12/K$4-1 -> 0.045365556
A13: AI 占電子事業 55% | B13: FY2026 切分較低（校準跟著變） | C13: =E342 -> 687.38513 | D13: =E331 -> 332.46763 | E13: =E338 -> 0.32000335 | F13: =E351 -> 212.40949 | G13: =F13/F$4-1 -> -0.017226487 | H13: =F342 -> 734.38751 | I13: =F331 -> 367.79873 | J13: =F338 -> 0.30246341 | K13: =F351 -> 218.00429 | L13: =K13/K$4-1 -> -0.0045052744
A14: AI 占電子事業 75% | B14: 較高 | C14: =E377 -> 729.53246 | D14: =E366 -> 453.36496 | E14: =E373 -> 0.30701829 | F14: =E386 -> 219.85591 | G14: =F14/F$4-1 -> 0.017226487 | H14: =F377 -> 785.445 | I14: =F366 -> 501.54372 | J14: =F373 -> 0.27970319 | K14: =F386 -> 219.97752 | L14: =K14/K$4-1 -> 0.0045052744
A15: 非 AI 營益率 10% | B15: 校準後 AI 載板營益率較高 | C15: =E412 -> 708.45879 | D15: =E401 -> 392.91629 | E15: =E408 -> 0.32020175 | F15: =E421 -> 220.47644 | G15: =F15/F$4-1 -> 0.020097568 | H15: =F412 -> 759.91625 | I15: =F401 -> 434.67123 | J15: =F408 -> 0.29935592 | K15: =F421 -> 224.9784 | L15: =K15/K$4-1 -> 0.027341316
A16: 非 AI 營益率 20% | B16: 較低 | C16: =E447 -> 708.45879 | D16: =E436 -> 392.91629 | E16: =E443 -> 0.30630429 | F16: =E456 -> 211.78896 | G16: =F16/F$4-1 -> -0.020097568 | H16: =F447 -> 759.91625 | I16: =F436 -> 434.67123 | J16: =F443 -> 0.28180781 | K16: =F456 -> 213.0034 | L16: =K16/K$4-1 -> -0.027341316
A17: 淨利 ÷ 營業利益 0.62 | B17: 稅與非營業較不利 | C17: =E482 -> 708.45879 | D17: =E471 -> 392.91629 | E17: =E478 -> 0.31325302 | F17: =E491 -> 202.72659 | G17: =F17/F$4-1 -> -0.062027231 | H17: =F482 -> 759.91625 | I17: =F471 -> 434.67123 | J17: =F478 -> 0.29058187 | K17: =F491 -> 205.4075 | L17: =K17/K$4-1 -> -0.062027231
A18: CB 轉換：股數 +3%／年 | B18: 2031 年到期 CB 轉換稀釋 | C18: =E517 -> 708.45879 | D18: =E506 -> 392.91629 | E18: =E513 -> 0.31325302 | F18: =E526 -> 209.83757 | G18: =F18/F$4-1 -> -0.029126214 | H18: =F517 -> 759.91625 | I18: =F506 -> 434.67123 | J18: =F513 -> 0.29058187 | K18: =F526 -> 206.41993 | L18: =K18/K$4-1 -> -0.057404091
A19: 顆數情境 B | B19: CY2028 ×0.8、CY2029 ×0.85 | C19: =PL!E117 -> 708.45879 | D19: =PL!E106 -> 392.91629 | E19: =PL!E113 -> 0.31325302 | F19: =PL!E126 -> 216.1327 | G19: =F19/F$4-1 -> 0 | H19: =PL!F117 -> 672.98201 | I19: =PL!F106 -> 347.73698 | J19: =PL!F113 -> 0.28231989 | K19: =PL!F126 -> 184.44483 | L19: =K19/K$4-1 -> -0.15775116
A20: 顆數情境 C | B20: CY2028–29 ×0.6 | C20: =PL!E152 -> 708.45879 | D20: =PL!E141 -> 392.91629 | E20: =PL!E148 -> 0.31325302 | F20: =PL!E161 -> 216.1327 | G20: =F20/F$4-1 -> 0 | H20: =PL!F152 -> 586.04776 | I20: =PL!F141 -> 260.80274 | J20: =PL!F148 -> 0.27051544 | K20: =PL!F161 -> 149.89876 | L20: =K20/K$4-1 -> -0.31550232
A22: 讀法：FY2027 三個顆數情境相同；B、C 的差異從 FY2028 起。溢價指數同時改變營收與 AI 載板營益率（成本不變），所以對 EPS 的影響大於對營收的影響。
A40: 案例區塊：溢價快速回落（情境 A）
A41: 項目 | B41: 單位 | C41: FY2025A | D41: FY2026（錨點） | E41: FY2027 | F41: FY2028 | G41: FY2029 | H41: 說明
A42: A. AI 伺服器載板（D 欄＝FY2026 校準年；FY(t) 對照 CY(t) 顆數）
A43: NVIDIA 加速器顆數 × 情境係數 | B43: 百萬顆 | D43: =(u_bw_26+u_rb_26+u_ru_26+u_hp_26)*1 -> 7.6 | E43: =(u_bw_27+u_rb_27+u_ru_27+u_hp_27)*1 -> 9.7 | F43: =(u_bw_28+u_rb_28+u_ru_28+u_hp_28)*um28_A -> 9.5 | G43: =(u_bw_28*(1+g29_bw)+u_rb_28*(1+g29_rb)+u_ru_28*(1+g29_ru)+u_hp_28*(1+g29_hp))*um29_A -> 10.6 | H43: markets/network In：Blackwell、Rubin、Rubin Ultra、Hopper
A44: 非 NVIDIA 加速器顆數 × 情境係數 | B44: 百萬顆 | D44: =(u_amd_26+u_tpu_26+u_trn_26+u_oth_26)*1 -> 7.6 | E44: =(u_amd_27+u_tpu_27+u_trn_27+u_oth_27)*1 -> 14 | F44: =(u_amd_28+u_tpu_28+u_trn_28+u_oth_28)*um28_A -> 17 | G44: =(u_amd_28*(1+g29_amd)+u_tpu_28*(1+g29_tpu)+u_trn_28*(1+g29_trn)+u_oth_28*(1+g29_oth))*um29_A -> 19.55 | H44: AMD、TPU、Trainium、其他 ASIC
A45: 有效顆數 ＝ NVIDIA ＋ 權重 × 非 NVIDIA | B45: 百萬顆 | D45: =D43+w_ot*D44 -> 10.64 | E45: =E43+w_ot*E44 -> 15.3 | F45: =F43+w_ot*F44 -> 16.3 | G45: =G43+w_ot*G44 -> 18.42
A46: FY2026 AI 載板營收（錨點電子事業 × AI 占比） | B46: ¥B | D46: =q26_e*ai_e -> 243.75 | H46: Assumed 切分；公司未揭露
A47: 每顆有效金額（Ibiden 份額 × 載板金額；FY2026 校準） | B47: 千日圓／顆 | D47: =D46/D45 -> 22.908835 | H47: Derived：¥B ÷ 百萬顆＝千日圓／顆。÷ 匯率即美元／顆（Units 頁）
A48: 每顆載板金額指數（面積、層數；FY2026＝1） | B48: x | D48: =1 -> 1 | E48: =D48*(1+g_asp) -> 1.18 | F48: =E48*(1+g_asp) -> 1.3924 | G48: =F48*(1+g_asp) -> 1.643032
A49: Ibiden 份額相對值（÷ FY2026） | B49: x | D49: =1 -> 1 | E49: =rel_27 -> 0.95 | F49: =rel_28 -> 0.88 | G49: =rel_29 -> 0.85
A50: 短缺溢價指數（FY2026＝1） | B50: x | D50: =1 -> 1 | E50: =PPLO_27 -> 0.95 | F50: =PPLO_28 -> 0.85 | G50: =PPLO_29 -> 0.75
A51: AI 伺服器載板營收 | B51: ¥B | D51: =D46 -> 243.75 | E51: =E45*$D$47*E48*E49*E50 -> 373.27048 | F51: =F45*$D$47*F48*F49*F50 -> 388.91636 | G51: =G45*$D$47*G48*G49*G50 -> 441.9965
A52: B. 電子事業
A53: 電子事業非 AI 營收（通用伺服器、PC 等） | B53: ¥B | D53: =q26_e-D51 -> 131.25 | E53: =D53*(1+g_ne) -> 137.8125 | F53: =E53*(1+g_ne) -> 144.70312 | G53: =F53*(1+g_ne) -> 151.93828
A54: 電子事業營收 | B54: ¥B | C54: =q25_e -> 243.316 | D54: =D51+D53 -> 375 | E54: =E51+E53 -> 511.08298 | F54: =F51+F53 -> 533.61949 | G54: =G51+G53 -> 593.93478
A55: AI 載板營業利益率（FY2026 校準） | B55: % | D55: =(q26_eoi-m_ne*D53)/D51 -> 0.37051282 | H55: Derived：使 FY2026 電子事業營業利益＝錨點；非 AI 營益率為 In 頁 m_ne
A56: AI 載板營業利益率 ＝ 1 −（1 − 校準值）÷ 溢價指數 | B56: % | D56: =D55 -> 0.37051282 | E56: =1-(1-$D$55)/E50 -> 0.33738192 | F56: =1-(1-$D$55)/F50 -> 0.25942685 | G56: =1-(1-$D$55)/G50 -> 0.16068376 | H56: Derived：每單位成本不變，價格隨溢價指數升降，差額全部落在利潤
A57: 電子事業營業利益 | B57: ¥B | C57: =q25_eoi -> 45.248 | D57: =D51*D56+D53*m_ne -> 110 | E57: =E51*E56+E53*m_ne -> 146.60658 | F57: =F51*F56+F53*m_ne -> 122.60081 | G57: =G51*G56+G53*m_ne -> 93.812402
A58: 電子事業營益率 | B58: % | C58: =C57/C54 -> 0.18596393 | D58: =D57/D54 -> 0.29333333 | E58: =E57/E54 -> 0.28685476 | F58: =F57/F54 -> 0.22975326 | G58: =G57/G54 -> 0.15795068
A59: C. 陶瓷、其他事業與全公司
A60: 陶瓷事業營收 | B60: ¥B | C60: =q25_cer -> 82.554 | D60: =q26_cer -> 84 | E60: =D60*(1+g_cer) -> 84 | F60: =E60*(1+g_cer) -> 84 | G60: =F60*(1+g_cer) -> 84
A61: 其他事業營收 | B61: ¥B | C61: =q25_oth -> 90.33 | D61: =q26_oth -> 91 | E61: =D61*(1+g_oth) -> 93.73 | F61: =E61*(1+g_oth) -> 96.5419 | G61: =F61*(1+g_oth) -> 99.438157
A62: 營收 | B62: ¥B | C62: =C54+C60+C61 -> 416.2 | D62: =D54+D60+D61 -> 550 | E62: =E54+E60+E61 -> 688.81298 | F62: =F54+F60+F61 -> 714.16139 | G62: =G54+G60+G61 -> 777.37294
A63: 檢查：分部合計 − 合併營收（FY2025 實績、FY2026 錨點） | B63: ¥B | C63: =C54+C60+C61-q25_rev -> -0.001 | D63: =D54+D60+D61-q26_rev -> 0
A64: 營收年增 | B64: % | D64: =D62/C62-1 -> 0.32148006 | E64: =E62/D62-1 -> 0.25238724 | F64: =F62/E62-1 -> 0.036800128 | G64: =G62/F62-1 -> 0.088511584
A65: AI 伺服器載板 ÷ 營收 | B65: % | D65: =D51/D62 -> 0.44318182 | E65: =E51/E62 -> 0.54190396 | F65: =F51/F62 -> 0.54457769 | G65: =G51/G62 -> 0.56857716
A66: 陶瓷＋其他事業營業利益＋調整 | B66: ¥B | C66: =q25_oi-q25_eoi -> 16.779 | D66: =q26_oi-q26_eoi -> 17 | E66: =E60*m_cer+E61*m_oth+q26_adj -> 17.24695 | F66: =F60*m_cer+F61*m_oth+q26_adj -> 17.570318 | G66: =G60*m_cer+G61*m_oth+q26_adj -> 17.903388
A67: 營業利益 | B67: ¥B | C67: =C57+C66 -> 62.027 | D67: =D57+D66 -> 127 | E67: =E57+E66 -> 163.85353 | F67: =F57+F66 -> 140.17113 | G67: =G57+G66 -> 111.71579
A68: 營業利益率 | B68: % | C68: =C67/C62 -> 0.14903172 | D68: =D67/D62 -> 0.23090909 | E68: =E67/E62 -> 0.23787812 | F68: =F67/F62 -> 0.19627375 | G68: =G67/G62 -> 0.14370939
A69: 淨利（歸屬母公司） | B69: ¥B | C69: =q25_ni -> 63.713 | D69: =q26_ni -> 84 | E69: =E67*ni_oi -> 108.30719 | F69: =F67*ni_oi -> 92.653119 | G69: =G67*ni_oi -> 73.844138
A70: 股數（分割後） | B70: 十億股 | D70: =q26_sh -> 0.56119722 | E70: =D70*(1+sh_g) -> 0.56119722 | F70: =E70*(1+sh_g) -> 0.56119722 | G70: =F70*(1+sh_g) -> 0.56119722
A71: EPS（日圓） | B71: ¥ | C71: =q25_eps -> 114.08 | D71: =D69/D70 -> 149.68 | E71: =E69/E70 -> 192.99309 | F71: =F69/F70 -> 165.09903 | G71: =G69/G70 -> 131.58322
A72: EPS 年增 | B72: % | D72: =D71/C71-1 -> 0.31206171 | E72: =E71/D71-1 -> 0.28937127 | F72: =F71/E71-1 -> -0.14453397 | G72: =G71/F71-1 -> -0.2030043
A75: 案例區塊：溢價延續（情境 A）
A76: 項目 | B76: 單位 | C76: FY2025A | D76: FY2026（錨點） | E76: FY2027 | F76: FY2028 | G76: FY2029 | H76: 說明
A77: A. AI 伺服器載板（D 欄＝FY2026 校準年；FY(t) 對照 CY(t) 顆數）
A78: NVIDIA 加速器顆數 × 情境係數 | B78: 百萬顆 | D78: =(u_bw_26+u_rb_26+u_ru_26+u_hp_26)*1 -> 7.6 | E78: =(u_bw_27+u_rb_27+u_ru_27+u_hp_27)*1 -> 9.7 | F78: =(u_bw_28+u_rb_28+u_ru_28+u_hp_28)*um28_A -> 9.5 | G78: =(u_bw_28*(1+g29_bw)+u_rb_28*(1+g29_rb)+u_ru_28*(1+g29_ru)+u_hp_28*(1+g29_hp))*um29_A -> 10.6 | H78: markets/network In：Blackwell、Rubin、Rubin Ultra、Hopper
A79: 非 NVIDIA 加速器顆數 × 情境係數 | B79: 百萬顆 | D79: =(u_amd_26+u_tpu_26+u_trn_26+u_oth_26)*1 -> 7.6 | E79: =(u_amd_27+u_tpu_27+u_trn_27+u_oth_27)*1 -> 14 | F79: =(u_amd_28+u_tpu_28+u_trn_28+u_oth_28)*um28_A -> 17 | G79: =(u_amd_28*(1+g29_amd)+u_tpu_28*(1+g29_tpu)+u_trn_28*(1+g29_trn)+u_oth_28*(1+g29_oth))*um29_A -> 19.55 | H79: AMD、TPU、Trainium、其他 ASIC
A80: 有效顆數 ＝ NVIDIA ＋ 權重 × 非 NVIDIA | B80: 百萬顆 | D80: =D78+w_ot*D79 -> 10.64 | E80: =E78+w_ot*E79 -> 15.3 | F80: =F78+w_ot*F79 -> 16.3 | G80: =G78+w_ot*G79 -> 18.42
A81: FY2026 AI 載板營收（錨點電子事業 × AI 占比） | B81: ¥B | D81: =q26_e*ai_e -> 243.75 | H81: Assumed 切分；公司未揭露
A82: 每顆有效金額（Ibiden 份額 × 載板金額；FY2026 校準） | B82: 千日圓／顆 | D82: =D81/D80 -> 22.908835 | H82: Derived：¥B ÷ 百萬顆＝千日圓／顆。÷ 匯率即美元／顆（Units 頁）
A83: 每顆載板金額指數（面積、層數；FY2026＝1） | B83: x | D83: =1 -> 1 | E83: =D83*(1+g_asp) -> 1.18 | F83: =E83*(1+g_asp) -> 1.3924 | G83: =F83*(1+g_asp) -> 1.643032
A84: Ibiden 份額相對值（÷ FY2026） | B84: x | D84: =1 -> 1 | E84: =rel_27 -> 0.95 | F84: =rel_28 -> 0.88 | G84: =rel_29 -> 0.85
A85: 短缺溢價指數（FY2026＝1） | B85: x | D85: =1 -> 1 | E85: =PPHI_27 -> 1.05 | F85: =PPHI_28 -> 1.05 | G85: =PPHI_29 -> 1
A86: AI 伺服器載板營收 | B86: ¥B | D86: =D81 -> 243.75 | E86: =E80*$D$82*E83*E84*E85 -> 412.56211 | F86: =F80*$D$82*F83*F84*F85 -> 480.42609 | G86: =G80*$D$82*G83*G84*G85 -> 589.32867
A87: B. 電子事業
A88: 電子事業非 AI 營收（通用伺服器、PC 等） | B88: ¥B | D88: =q26_e-D86 -> 131.25 | E88: =D88*(1+g_ne) -> 137.8125 | F88: =E88*(1+g_ne) -> 144.70312 | G88: =F88*(1+g_ne) -> 151.93828
A89: 電子事業營收 | B89: ¥B | C89: =q25_e -> 243.316 | D89: =D86+D88 -> 375 | E89: =E86+E88 -> 550.37461 | F89: =F86+F88 -> 625.12922 | G89: =G86+G88 -> 741.26695
A90: AI 載板營業利益率（FY2026 校準） | B90: % | D90: =(q26_eoi-m_ne*D88)/D86 -> 0.37051282 | H90: Derived：使 FY2026 電子事業營業利益＝錨點；非 AI 營益率為 In 頁 m_ne
A91: AI 載板營業利益率 ＝ 1 −（1 − 校準值）÷ 溢價指數 | B91: % | D91: =D90 -> 0.37051282 | E91: =1-(1-$D$90)/E85 -> 0.4004884 | F91: =1-(1-$D$90)/F85 -> 0.4004884 | G91: =1-(1-$D$90)/G85 -> 0.37051282 | H91: Derived：每單位成本不變，價格隨溢價指數升降，差額全部落在利潤
A92: 電子事業營業利益 | B92: ¥B | C92: =q25_eoi -> 45.248 | D92: =D86*D91+D88*m_ne -> 110 | E92: =E86*E91+E88*m_ne -> 185.89821 | F92: =F86*F91+F88*m_ne -> 214.11055 | G92: =G86*G91+G88*m_ne -> 241.14457
A93: 電子事業營益率 | B93: % | C93: =C92/C89 -> 0.18596393 | D93: =D92/D89 -> 0.29333333 | E93: =E92/E89 -> 0.3377667 | F93: =F92/F89 -> 0.34250606 | G93: =G92/G89 -> 0.32531407
A94: C. 陶瓷、其他事業與全公司
A95: 陶瓷事業營收 | B95: ¥B | C95: =q25_cer -> 82.554 | D95: =q26_cer -> 84 | E95: =D95*(1+g_cer) -> 84 | F95: =E95*(1+g_cer) -> 84 | G95: =F95*(1+g_cer) -> 84
A96: 其他事業營收 | B96: ¥B | C96: =q25_oth -> 90.33 | D96: =q26_oth -> 91 | E96: =D96*(1+g_oth) -> 93.73 | F96: =E96*(1+g_oth) -> 96.5419 | G96: =F96*(1+g_oth) -> 99.438157
A97: 營收 | B97: ¥B | C97: =C89+C95+C96 -> 416.2 | D97: =D89+D95+D96 -> 550 | E97: =E89+E95+E96 -> 728.10461 | F97: =F89+F95+F96 -> 805.67112 | G97: =G89+G95+G96 -> 924.70511
A98: 檢查：分部合計 − 合併營收（FY2025 實績、FY2026 錨點） | B98: ¥B | C98: =C89+C95+C96-q25_rev -> -0.001 | D98: =D89+D95+D96-q26_rev -> 0
A99: 營收年增 | B99: % | D99: =D97/C97-1 -> 0.32148006 | E99: =E97/D97-1 -> 0.32382656 | F99: =F97/E97-1 -> 0.10653209 | G99: =G97/F97-1 -> 0.14774514
A100: AI 伺服器載板 ÷ 營收 | B100: % | D100: =D86/D97 -> 0.44318182 | E100: =E86/E97 -> 0.56662477 | F100: =F86/F97 -> 0.59630547 | G100: =G86/G97 -> 0.63731525
A101: 陶瓷＋其他事業營業利益＋調整 | B101: ¥B | C101: =q25_oi-q25_eoi -> 16.779 | D101: =q26_oi-q26_eoi -> 17 | E101: =E95*m_cer+E96*m_oth+q26_adj -> 17.24695 | F101: =F95*m_cer+F96*m_oth+q26_adj -> 17.570318 | G101: =G95*m_cer+G96*m_oth+q26_adj -> 17.903388
A102: 營業利益 | B102: ¥B | C102: =C92+C101 -> 62.027 | D102: =D92+D101 -> 127 | E102: =E92+E101 -> 203.14516 | F102: =F92+F101 -> 231.68086 | G102: =G92+G101 -> 259.04796
A103: 營業利益率 | B103: % | C103: =C102/C97 -> 0.14903172 | D103: =D102/D97 -> 0.23090909 | E103: =E102/E97 -> 0.27900546 | F103: =F102/F97 -> 0.28756258 | G103: =G102/G97 -> 0.28014116
A104: 淨利（歸屬母公司） | B104: ¥B | C104: =q25_ni -> 63.713 | D104: =q26_ni -> 84 | E104: =E102*ni_oi -> 134.27895 | F104: =F102*ni_oi -> 153.14105 | G104: =G102*ni_oi -> 171.2307
A105: 股數（分割後） | B105: 十億股 | D105: =q26_sh -> 0.56119722 | E105: =D105*(1+sh_g) -> 0.56119722 | F105: =E105*(1+sh_g) -> 0.56119722 | G105: =F105*(1+sh_g) -> 0.56119722
A106: EPS（日圓） | B106: ¥ | C106: =q25_eps -> 114.08 | D106: =D104/D105 -> 149.68 | E106: =E104/E105 -> 239.27231 | F106: =F104/F105 -> 272.88277 | G106: =G104/G105 -> 305.1168
A107: EPS 年增 | B107: % | D107: =D106/C106-1 -> 0.31206171 | E107: =E106/D106-1 -> 0.59855897 | F107: =F106/E106-1 -> 0.1404695 | G107: =G106/F106-1 -> 0.1181241
A110: 案例區塊：份額流失（低）（情境 A）
A111: 項目 | B111: 單位 | C111: FY2025A | D111: FY2026（錨點） | E111: FY2027 | F111: FY2028 | G111: FY2029 | H111: 說明
A112: A. AI 伺服器載板（D 欄＝FY2026 校準年；FY(t) 對照 CY(t) 顆數）
A113: NVIDIA 加速器顆數 × 情境係數 | B113: 百萬顆 | D113: =(u_bw_26+u_rb_26+u_ru_26+u_hp_26)*1 -> 7.6 | E113: =(u_bw_27+u_rb_27+u_ru_27+u_hp_27)*1 -> 9.7 | F113: =(u_bw_28+u_rb_28+u_ru_28+u_hp_28)*um28_A -> 9.5 | G113: =(u_bw_28*(1+g29_bw)+u_rb_28*(1+g29_rb)+u_ru_28*(1+g29_ru)+u_hp_28*(1+g29_hp))*um29_A -> 10.6 | H113: markets/network In：Blackwell、Rubin、Rubin Ultra、Hopper
A114: 非 NVIDIA 加速器顆數 × 情境係數 | B114: 百萬顆 | D114: =(u_amd_26+u_tpu_26+u_trn_26+u_oth_26)*1 -> 7.6 | E114: =(u_amd_27+u_tpu_27+u_trn_27+u_oth_27)*1 -> 14 | F114: =(u_amd_28+u_tpu_28+u_trn_28+u_oth_28)*um28_A -> 17 | G114: =(u_amd_28*(1+g29_amd)+u_tpu_28*(1+g29_tpu)+u_trn_28*(1+g29_trn)+u_oth_28*(1+g29_oth))*um29_A -> 19.55 | H114: AMD、TPU、Trainium、其他 ASIC
A115: 有效顆數 ＝ NVIDIA ＋ 權重 × 非 NVIDIA | B115: 百萬顆 | D115: =D113+w_ot*D114 -> 10.64 | E115: =E113+w_ot*E114 -> 15.3 | F115: =F113+w_ot*F114 -> 16.3 | G115: =G113+w_ot*G114 -> 18.42
A116: FY2026 AI 載板營收（錨點電子事業 × AI 占比） | B116: ¥B | D116: =q26_e*ai_e -> 243.75 | H116: Assumed 切分；公司未揭露
A117: 每顆有效金額（Ibiden 份額 × 載板金額；FY2026 校準） | B117: 千日圓／顆 | D117: =D116/D115 -> 22.908835 | H117: Derived：¥B ÷ 百萬顆＝千日圓／顆。÷ 匯率即美元／顆（Units 頁）
A118: 每顆載板金額指數（面積、層數；FY2026＝1） | B118: x | D118: =1 -> 1 | E118: =D118*(1+g_asp) -> 1.18 | F118: =E118*(1+g_asp) -> 1.3924 | G118: =F118*(1+g_asp) -> 1.643032
A119: Ibiden 份額相對值（÷ FY2026） | B119: x | D119: =1 -> 1 | E119: =RLO_27 -> 0.85 | F119: =RLO_28 -> 0.75 | G119: =RLO_29 -> 0.7
A120: 短缺溢價指數（FY2026＝1） | B120: x | D120: =1 -> 1 | E120: =pp_27 -> 1 | F120: =pp_28 -> 0.95 | G120: =pp_29 -> 0.9
A121: AI 伺服器載板營收 | B121: ¥B | D121: =D116 -> 243.75 | E121: =E115*$D$117*E118*E119*E120 -> 351.55668 | F121: =F115*$D$117*F118*F119*F120 -> 370.45843 | G121: =G115*$D$117*G118*G119*G120 -> 436.79654
A122: B. 電子事業
A123: 電子事業非 AI 營收（通用伺服器、PC 等） | B123: ¥B | D123: =q26_e-D121 -> 131.25 | E123: =D123*(1+g_ne) -> 137.8125 | F123: =E123*(1+g_ne) -> 144.70312 | G123: =F123*(1+g_ne) -> 151.93828
...

Sheet Sources
A1: 來源（公司原文＝決算短信與補足資料；分部門預測取自 Q1 補足資料的轉載）
A2: 公司：2026 年 3 月期決算短信（FY2025 實績、分部門） | B2: https://www.ibiden.com/ir/items/ConsolidatedFinancialResultsFY2025.pdf
A3: 公司：2027 年 3 月期 Q1 決算短信（上修後全年預測） | B3: https://finance.biggo.jp/news/jpx_tdnet_140120260731504718
A4: 公司：Q1 補足資料（分部門全年預測、設備投資 2,100 億、匯率 ¥152） | B4: https://finance.biggo.jp/news/jpx_tdnet_140120260803507041
A5: 二手：SEMICON.TODAY Q1 深掘（分部門 Q1、EPS 分割後 149.68） | B5: https://semicon.today/archives/12352
A6: 二手：LIMO Q1（預收款、股價） | B6: https://finance.limo.media/articles/detail/683
A7: 二手：Quartr FY2025 摘要（FY2030 目標；AI 摘要，營收數字有誤處未採用） | B7: https://quartr.com/events/ibiden-co-ltd-4062-q4-2026_F9Xvd7IW
A8: 研調：Tom's Hardware ABF 2026（供需缺口、Ibiden 路線圖、競爭者擴產、ABF 膜漲價） | B8: https://www.tomshardware.com/tech-industry/semiconductors/the-state-of-abf-substrates-in-data-center-silicon-in-2026-solving-the-supply-crunch-and-material-wall-beneath-every-ai-accelerator
A9: 研調：Data Gravity（高階 FC-BGA 份額、ABF 載板平均單價） | B9: https://www.datagravity.dev/p/the-abf-substrate-bottleneck
A10: 研調：thebuildout（BofA：Ibiden 占 GPU 載板 70–80%、短缺到 2028） | B10: https://thebuildout.ai/intel/229c44f2-da57-4f46-b5fa-e5d03702236c
A11: 研調：Encyclopedia of Stocks（欣興 2025 年 NVIDIA 約 30%） | B11: https://encyclopediaofstocks.substack.com/p/abf-substrate-market-ai-driven-super
A12: 研調：Silicon Analysts（封裝成本，含載板） | B12: https://siliconanalysts.com/data/ai-chip-costs
A13: 市場：stockanalysis（10-16 股價、前瞻與近 12 月 P/E、共識目標價；同業前瞻 P/E、ROE） | B13: https://stockanalysis.com/quote/tyo/4062/
A14: 市場：10-23 收盤（markets/invest_map/data/prices.csv：株探、松井證券） | B14: https://kabutan.jp/stock/?code=4062
A15: 市場層：markets/network、tsmc 成品（本 repo，唯讀）
A16: 待補（人工）：十年 P/E 歷史（Bloomberg）；AI 伺服器載板營收（公司未揭露）；FY2027 以後共識（付費）；CB 發行額；ASIC 載板份額 | B16: 未找到
A17: SemiAnalysis | B17: 未使用
A18: [Verified] stockanalysis 現金流量表：2026 年 3 月期（本模型 FY2025）折舊攤銷 66,236、資本支出 106,118、營業現金流 106,407（百萬日圓） | B18: https://stockanalysis.com/quote/tyo/4062/financials/cash-flow-statement/
A19: [Verified] 公司 Q1 補足資料：2027 年 3 月期（本模型 FY2026）設備投資 2,100 億、折舊 810 億（公司計畫，Interested-party） | B19: https://finance.biggo.jp/news/jpx_tdnet_140120260803507041
A20: [Verified] EE Times Japan 2026-02-05：2026–2028 年度三年投資約 5,000 億（第一期約 2,200 億，河間 Cell 6，2027 年度起陸續投產） | B20: https://eetimes.itmedia.co.jp/ee/articles/2602/05/news037.html
A21: [Assumed] 折舊 ÷ 營收 15%、資本支出 ÷ 營收 25%（In 頁 da_rev、cx_rev；PL 頁自由現金流列用；FY2029 起擴產計畫結束後可能高估資本支出） | B21: —
