Workbook

Sheet README
A1: Broadcom（AVGO）收支與估值模型 v0.1（AI 半導體 Project：運算層第二個樣板，ASIC＋網通） 2026-10-23
A2: 版本：v0.1（初版）。ASIC 每顆規格（Broadcom 份額、核心售價、HBM 代購）在本模型 Units 頁建立，為本專案權威資料（規則第 13 條）。
A3: 模型命題：Broadcom 的 AI 營收＝各 XPU 平台的顆數 × Broadcom 份額 × 每顆售價（核心＋代購 HBM）＋網通附掛；2027–28 年的增量集中在 Anthropic、OpenAI 兩家靠融資部署的客戶。股價約 17 倍 FY2027 EPS：這個折價是在定價客戶信用風險，還是低估了營收？
A4: 核心問題：以市場層顆數往前推，Broadcom 的 AI 營收與 EPS 能否支撐公司展望（FY2027 約 115B、FY2028 約 230B）；差距要靠多少額外顆數補上。
A6: 會計年度：FY(t) 於 t 年 10 月底／11 月初結束，10/12 落在日曆年 t，FY(t) 直接對照 CY(t)，不做平移。預測期 FY2027–FY2029（三年）。口徑：公司 non-GAAP（排除股票薪酬、攤銷、重組）。
A8: 驅動因子 → 推導量（全部唯讀上游，不修改）
A9: XPU：Google TPU 與「其他 ASIC」顆數（markets/memory UNITS × 情境係數）× Broadcom 份額（Assumed）×（核心售價＋代購比例 × 每顆 HBM 容量 × HBM 單價）× k_x（FY2026 實績校準）→ XPU 營收。
A10: AI 網通：markets/network 的「Broadcom 網通（本模型歸屬）」× 情境顆數係數 × k_n（FY2026 實際推估校準）。非 AI 半導體、軟體：FY2026 錨點 × Assumed 成長率。
A11: 毛利率：網通、非 AI、軟體、代購 HBM 各用 Assumed 毛利率；XPU 核心毛利率 m_core 為 FY2026 殘差（Derived）。FY2027 起毛利率下滑來自代購 HBM 占比上升（HBM 2027 年 +80%、每顆容量上升）。
A12: 校準：FY2026 ＝ Q1–Q3 實績＋Q4 指引（營收 34.8、AI 21.7、營業利益率 66%）。不用共識、不用公司對 FY2027–28 的展望（只在 Recon 對帳）。
A13: 估值：結論用現價 ÷ FY2027、FY2028 EPS；十年 GAAP P/E 規則值不適用（攤銷扭曲），前瞻 P/E 歷史待 Bloomberg。循環位置（共用規則，不平移）只作紀錄：設備市場見頂年度 A 2029、B 2028、C 2027。
A14: 標記：Verified、Interested-party、Analogy、Assumed、Derived。SemiAnalysis 未使用。公司原文＝SEC EDGAR 8-K；法說內容只經二手轉述（標二手）。
A15: 已知限制：(1) k_x 是顆數、份額、核心單價的合併係數，無法分開識別；(2) Broadcom 各平台份額、核心售價、HBM 代購比例皆為 Assumed，FY2027 起的毛利率對代購比例高度敏感（Sens）；(3) 「其他 ASIC」含昇騰、Maia 等非 Broadcom 晶片，份額為粗估；(4) 客戶融資曝險不進基準 EPS（Recon F）；(5) 十年倍數待補；(6) R4 產業部署路徑未建（Recon 預留列）。

Sheet In
A1: In — 輸入（藍字；基準欄 E，低 D、高 F）。金額：十億美元（US$B）；每顆價格：千美元（US$K）；顆數：百萬顆；HBM：GB、US$/GB。每個輸入附兩個來源（找不到者寫「未找到」）；公司原文算一個
A2: 標記：Verified／Interested-party／Analogy／Assumed／Derived；Analogy、Assumed 給低／高區間。SemiAnalysis 未使用。公司原文＝Broadcom 8-K 新聞稿（SEC EDGAR、investors.broadcom.com）；公司對 FY2027、FY2028 的 AI 營收展望為 Interested-party，只放 Recon 對帳，不作校準
A3: 鍵 | B3: 項目 | C3: 單位 | D3: 低 | E3: 基準 | F3: 高 | G3: 標記 | H3: 來源1 | I3: 來源2／說明
A4: A. 加速器顆數（markets/memory 與 HBM、台積電、網通、NVIDIA 模型同一份；情境係數讀台積電模型成品，不另訂）
A5: u_bw_26 | B5: NVIDIA Blackwell（B200／B300） 顆數 2026 | C5: 百萬顆 | E5: 5.4 | G5: Interested-party | H5: markets/memory/market.py UNITS：顆數：Morgan Stanley 2026-07（2026 5.4M）；AC Research 2027 約 2.4M；2028 Assumed。GB：B200 186、B300 288 組合 [Derived] | I5: 台積電模型 tsmc/dist/20261023_台積電模型_v0.2.1.xlsx｜In!E5（值相同，建置時檢查）
A6: u_bw_27 | B6: NVIDIA Blackwell（B200／B300） 顆數 2027 | C6: 百萬顆 | E6: 2.4 | G6: Interested-party | H6: 同上 | I6: 同上
A7: u_bw_28 | B7: NVIDIA Blackwell（B200／B300） 顆數 2028 | C7: 百萬顆 | E7: 0.5 | G7: Interested-party | H7: 同上 | I7: 同上
A8: g29_bw | B8: NVIDIA Blackwell（B200／B300） 2029 顆數成長 | C8: % | E8: -0.5 | G8: Assumed | H8: tsmc/dist/20261023_台積電模型_v0.2.1.xlsx｜In!E8 | I8: markets/memory 無 2029；沿用台積電模型
A9: u_rb_26 | B9: NVIDIA Rubin 顆數 2026 | C9: 百萬顆 | E9: 1.7 | G9: Interested-party | H9: markets/memory/market.py UNITS：2026：TrendForce 組合 Rubin 22% × 約 7.6M [Derived]；2027：Morgan Stanley 約 7.0M；2028 Assumed | I9: 台積電模型 tsmc/dist/20261023_台積電模型_v0.2.1.xlsx｜In!E9（值相同，建置時檢查）
A10: u_rb_27 | B10: NVIDIA Rubin 顆數 2027 | C10: 百萬顆 | E10: 7 | G10: Interested-party | H10: 同上 | I10: 同上
A11: u_rb_28 | B11: NVIDIA Rubin 顆數 2028 | C11: 百萬顆 | E11: 7 | G11: Interested-party | H11: 同上 | I11: 同上
A12: g29_rb | B12: NVIDIA Rubin 2029 顆數成長 | C12: % | E12: 0.15 | G12: Assumed | H12: tsmc/dist/20261023_台積電模型_v0.2.1.xlsx｜In!E12 | I12: markets/memory 無 2029；沿用台積電模型
A13: u_ru_26 | B13: NVIDIA Rubin Ultra 顆數 2026 | C13: 百萬顆 | E13: 0 | G13: Assumed | H13: markets/memory/market.py UNITS：時程 Assumed；GB：NVIDIA 1 TB／封裝 | I13: 台積電模型 tsmc/dist/20261023_台積電模型_v0.2.1.xlsx｜In!E13（值相同，建置時檢查）
A14: u_ru_27 | B14: NVIDIA Rubin Ultra 顆數 2027 | C14: 百萬顆 | E14: 0.3 | G14: Assumed | H14: 同上 | I14: 同上
A15: u_ru_28 | B15: NVIDIA Rubin Ultra 顆數 2028 | C15: 百萬顆 | E15: 2 | G15: Assumed | H15: 同上 | I15: 同上
A16: g29_ru | B16: NVIDIA Rubin Ultra 2029 顆數成長 | C16: % | E16: 0.15 | G16: Assumed | H16: tsmc/dist/20261023_台積電模型_v0.2.1.xlsx｜In!E16 | I16: markets/memory 無 2029；沿用台積電模型
... A48: gb_oth_28 | B48: 其他 ASIC（MTIA、Maia、Ascend 等） 每顆 HBM 2028 | C48: GB | E48: 250 | G48: Derived／Assumed | H48: markets/memory/market.py UNITS | I48: 同上
A49: B. ASIC 每顆規格（本專案為權威，規則第 13 條）：Broadcom 在各平台的顆數份額、每顆核心售價（不含 HBM）、HBM 由 Broadcom 代購的比例
A50: sh_tpu_26 | B50: Broadcom 占 Google TPU 顆數 2026 | C50: % | D50: 0.8 | E50: 0.9 | F50: 1 | G50: Assumed | H50: Broadcom 為 TPU 主要設計夥伴（Ironwood／v7、v8i 量產；法說）；Google 與 MediaTek 另有合作（Counterpoint 2026-01，二手） | I50: 各家份額未揭露：未找到
A51: sh_tpu_27 | B51: Broadcom 占 Google TPU 顆數 2027 | C51: % | D51: 0.6 | E51: 0.8 | F51: 0.9 | G51: Assumed | H51: 同上；MediaTek 版 TPU 放量的時點未揭露 | I51: Anthropic 2027 年約 5 GW 的 TPU v8i（公司說法，Interested-party）屬 Broadcom
A52: sh_tpu_28 | B52: Broadcom 占 Google TPU 顆數 2028（2029 沿用） | C52: % | D52: 0.5 | E52: 0.75 | F52: 0.9 | G52: Assumed | H52: 同上 | I52: —
A53: sh_oth_26 | B53: Broadcom 占「其他 ASIC」顆數 2026 | C53: % | D53: 0.2 | E53: 0.35 | F53: 0.5 | G53: Assumed | H53: 其他 ASIC＝MTIA（Broadcom）、OpenAI 客製（Broadcom，2026 Q3 開始出貨）、Maia（非 Broadcom）、昇騰（華為）等 | I53: XPU 客戶 6 家：Google、Anthropic、OpenAI、Meta＋2 家未具名（法說，二手）
A54: sh_oth_27 | B54: Broadcom 占「其他 ASIC」顆數 2027 | C54: % | D54: 0.4 | E54: 0.55 | F54: 0.7 | G54: Assumed | H54: OpenAI 2027 年 1.3 GW、Meta 至 2028 年共 3 GW（公司說法，Interested-party） | I54: —
A55: sh_oth_28 | B55: Broadcom 占「其他 ASIC」顆數 2028（2029 沿用） | C55: % | D55: 0.4 | E55: 0.55 | F55: 0.7 | G55: Assumed | H55: OpenAI 2028 年 5 GW 以上（公司說法） | I55: —
A56: core_tpu | B56: TPU 每顆核心售價（Broadcom 營收，不含 HBM；2026 基準） | C56: US$K | D56: 6 | E56: 8 | F56: 11 | G56: Assumed | H56: 無：每顆 ASP 未揭露。NVIDIA 模型 pa_tpu（含 HBM）8–12–18K；192 GB × 2026 HBM 價約 2.8K | I56: nvidia/dist/20261023_NVIDIA模型_v0.1.1.xlsx｜In!E146（含 HBM 的對照值）
A57: core_oth | B57: 其他 ASIC 每顆核心售價（Broadcom 營收，不含 HBM；2026 基準） | C57: US$K | D57: 4 | E57: 6 | F57: 9 | G57: Assumed | H57: 無：未揭露。Maia 200 約為 NVIDIA 的 30–40%＝$9–12K（二手，含 HBM）作量級參照 | I57: nvidia/dist/20261023_NVIDIA模型_v0.1.1.xlsx｜In!E148（含 HBM 的對照值）
A58: f_hbm | B58: HBM 由 Broadcom 代購並計入營收的比例 | C58: x | D58: 0.3 | E58: 0.6 | F58: 1 | G58: Assumed | H58: 公司：毛利率下滑來自「記憶體含量高的 XPU」占比上升（Q3 FY26 法說，二手）→ 至少部分 HBM 經 Broadcom 轉售 | I58: 第二來源：未找到。客戶自購 HBM（consigned）的比例未揭露
A59: m_hbm | B59: 代購 HBM 的毛利率 | C59: x | D59: 0 | E59: 0.1 | F59: 0.2 | G59: Assumed | H59: 無：未揭露；轉售料件通常低加成 | I59: 第二來源：未找到
A60: pfc | B60: 2027 年起 XPU 核心售價係數（Sens 用；基準 1） | C60: x | D60: 0.8 | E60: 1 | F60: 1.2 | G60: Assumed | H60: 無：新一代（TPU v8、MTIA 新世代）核心單價變化未揭露 | I60: Sens 用 ±20%
A61: C. 記憶體價格路徑（讀 skhynix 成品；唯讀；情境別）
A62: hbm_A_26 | B62: HBM 混合單價 2026（A） | C62: US$/GB | E62: 14.6 | G62: Derived | H62: skhynix/dist/20261023_SK海力士模型_v0.4.1.xlsx｜Mkt!C30:G30 | I62: markets/memory：2026 BofA $14.6/GB；2027 +80% 三情境相同；2028–29 依情境
A63: hbm_A_27 | B63: HBM 混合單價 2027（A） | C63: US$/GB | E63: 26.28 | G63: Derived | H63: skhynix/dist/20261023_SK海力士模型_v0.4.1.xlsx｜Mkt!C30:G30 | I63: 同上
A64: hbm_A_28 | B64: HBM 混合單價 2028（A） | C64: US$/GB | E64: 28.908 | G64: Derived | H64: skhynix/dist/20261023_SK海力士模型_v0.4.1.xlsx｜Mkt!C30:G30 | I64: 同上
A65: hbm_A_29 | B65: HBM 混合單價 2029（A） | C65: US$/GB | E65: 27.4626 | G65: Derived | H65: skhynix/dist/20261023_SK海力士模型_v0.4.1.xlsx｜Mkt!C30:G30 | I65: 同上
A66: hbm_B_26 | B66: HBM 混合單價 2026（B） | C66: US$/GB | E66: 14.6 | G66: Derived | H66: skhynix/dist/20261023_SK海力士模型_v0.4.1.xlsx｜Mkt!C31:G31 | I66: 同上
A67: hbm_B_27 | B67: HBM 混合單價 2027（B） | C67: US$/GB | E67: 26.28 | G67: Derived | H67: skhynix/dist/20261023_SK海力士模型_v0.4.1.xlsx｜Mkt!C31:G31 | I67: 同上
A68: hbm_B_28 | B68: HBM 混合單價 2028（B） | C68: US$/GB | E68: 19.71 | G68: Derived | H68: skhynix/dist/20261023_SK海力士模型_v0.4.1.xlsx｜Mkt!C31:G31 | I68: 同上
A69: hbm_B_29 | B69: HBM 混合單價 2029（B） | C69: US$/GB | E69: 19.71 | G69: Derived | H69: skhynix/dist/20261023_SK海力士模型_v0.4.1.xlsx｜Mkt!C31:G31 | I69: 同上
A70: hbm_C_26 | B70: HBM 混合單價 2026（C） | C70: US$/GB | E70: 14.6 | G70: Derived | H70: skhynix/dist/20261023_SK海力士模型_v0.4.1.xlsx｜Mkt!C32:G32 | I70: 同上
A71: hbm_C_27 | B71: HBM 混合單價 2027（C） | C71: US$/GB | E71: 26.28 | G71: Derived | H71: skhynix/dist/20261023_SK海力士模型_v0.4.1.xlsx｜Mkt!C32:G32 | I71: 同上
A72: hbm_C_28 | B72: HBM 混合單價 2028（C） | C72: US$/GB | E72: 15.768 | G72: Derived | H72: skhynix/dist/20261023_SK海力士模型_v0.4.1.xlsx｜Mkt!C32:G32 | I72: 同上
A73: hbm_C_29 | B73: HBM 混合單價 2029（C） | C73: US$/GB | E73: 16.5564 | G73: Derived | H73: skhynix/dist/20261023_SK海力士模型_v0.4.1.xlsx｜Mkt!C32:G32 | I73: 同上
A74: D. AI 網通（讀 markets/network 成品；情境 A 基準，B／C 依顆數係數縮放）
A75: net_26 | B75: Broadcom 網通（本模型歸屬）2026 | C75: US$B | E75: 12.607573 | G75: Derived | H75: markets/network/dist/20261023_AI網通市場模型_v0.2.2.xlsx｜Mkt!C35:F35 | I75: 廠商歸屬比例為 Assumed（markets/network In 頁 avgo_su、avgo_so、avgo_nic、avgo_opt）；2026 較實際推估低約 28%（見 Recon）
A76: net_27 | B76: Broadcom 網通（本模型歸屬）2027 | C76: US$B | E76: 26.959549 | G76: Derived | H76: markets/network/dist/20261023_AI網通市場模型_v0.2.2.xlsx｜Mkt!C35:F35 | I76: 同上
A77: net_28 | B77: Broadcom 網通（本模型歸屬）2028 | C77: US$B | E77: 32.094922 | G77: Derived | H77: markets/network/dist/20261023_AI網通市場模型_v0.2.2.xlsx｜Mkt!C35:F35 | I77: 同上
A78: net_29 | B78: Broadcom 網通（本模型歸屬）2029 | C78: US$B | E78: 37.832817 | G78: Derived | H78: markets/network/dist/20261023_AI網通市場模型_v0.2.2.xlsx｜Mkt!C35:F35 | I78: 同上
A79: rep_avgo26 | B79: Broadcom AI 網通營收 FY2026（實際＋推估） | C79: US$B | D79: 16 | E79: 17.6 | F79: 20 | G79: Derived | H79: markets/network/dist/20261023_AI網通市場模型_v0.2.2.xlsx｜In!D121:F121 | I79: Q3 FY26：XPU 占 AI 營收 73%（法說，二手）→ 網通約 4.5；FY2026 AI 57.6 × 約 30%
A80: gm_net | B80: AI 網通毛利率 | C80: x | D80: 0.65 | E80: 0.72 | F80: 0.8 | G80: Assumed | H80: 無：公司不揭露產品別毛利率 | I80: 第二來源：未找到
A81: E. 非 AI 半導體與基礎架構軟體（VMware 等）
A82: gm_nai | B82: 非 AI 半導體毛利率 | C82: x | D82: 0.6 | E82: 0.65 | F82: 0.7 | G82: Assumed | H82: 無：公司不揭露；半導體部門整體毛利率約 67%（Q3 FY26 法說 Q&A 更正值，二手） | I82: 第二來源：未找到
A83: gm_sw | B83: 軟體毛利率（non-GAAP） | C83: x | D83: 0.9 | E83: 0.93 | F83: 0.95 | G83: Derived | H83: Q3 FY26：(non-GAAP 毛利 22.191 − 半導體 20.839 × 67%) ÷ 軟體 8.752 ≈ 94%（67% 為二手） | I83: 低／高 Assumed
A84: g_nai | B84: 非 AI 半導體營收年增（FY2027 起） | C84: % | D84: -0.05 | E84: 0.03 | F84: 0.08 | G84: Assumed | H84: FY2026 Q3 約 4.1／季（半導體 20.8 − AI 16.7；公司） | I84: 第二來源：未找到
A85: g_sw27 | B85: 軟體營收年增 FY2027 | C85: % | D85: 0.08 | E85: 0.12 | F85: 0.18 | G85: Assumed | H85: 公司：Q3 FY26 軟體年增 29%、ARR 年增 15%；Q4 預估約 8.7（約 +25%）（法說，二手） | I85: 第二來源：未找到
A86: g_sw | B86: 軟體營收年增 FY2028 起 | C86: % | D86: 0.04 | E86: 0.08 | F86: 0.12 | G86: Assumed | H86: VMware 漲價效果遞減（Assumed） | I86: —
A87: F. FY2026 錨點（Q1–Q3 實績＋Q4 指引）
A88: q4_rev | B88: Q4 FY26 營收指引 | C88: US$B | E88: 34.8 | G88: Interested-party | H88: https://investors.broadcom.com/news-releases/news-release-details/broadcom-inc-announces-third-quarter-fiscal-year-2026-financial：約 $34.8B（年增 93%） | I88: top1markets、BigGo（二手）同值
A89: q4_ai | B89: Q4 FY26 AI 半導體營收 | C89: US$B | E89: 21.7 | G89: Interested-party | H89: Q3 FY26 新聞稿 CEO 說明：$21.7B（年增 236%） | I89: BigGo、top1markets（二手）同值
A90: q4_sw | B90: Q4 FY26 軟體營收 | C90: US$B | D90: 8.5 | E90: 8.7 | F90: 8.9 | G90: Interested-party | H90: 法說轉述：Investing.com 逐字稿、BigGo Finance 摘要（2026-09-02；二手）：約 $8.7B | I90: 第二來源：未找到
A91: q4_gm | B91: Q4 FY26 non-GAAP 毛利率 | C91: % | D91: 0.72 | E91: 0.73 | F91: 0.74 | G91: Interested-party | H91: 法說轉述：Investing.com 逐字稿、BigGo Finance 摘要（2026-09-02；二手）：約 73%（去年同期 78%） | I91: 第二來源：未找到
A92: q4_oim | B92: Q4 FY26 non-GAAP 營業利益率指引 | C92: % | E92: 0.66 | G92: Interested-party | H92: https://investors.broadcom.com/news-releases/news-release-details/broadcom-inc-announces-third-quarter-fiscal-year-2026-financial：約 66% | I92: top1markets（二手）同值
A93: q4_int | B93: Q4 FY26 non-GAAP 利息費用 | C93: US$B | D93: 0.65 | E93: 0.7 | F93: 0.75 | G93: Derived | H93: Q3 FY26 0.703（公司） | I93: —
A94: q4_oth | B94: Q4 FY26 non-GAAP 其他收益 | C94: US$B | D94: 0.05 | E94: 0.1 | F94: 0.15 | G94: Derived | H94: Q1–Q3 0.118／0.118／0.098（公司） | I94: —
A95: q4_tx | B95: Q4 FY26 non-GAAP 有效稅率 | C95: % | D95: 0.155 | E95: 0.16 | F95: 0.165 | G95: Derived | H95: Q3 FY26 3.118 ÷ 19.490＝16.0%（公司） | I95: —
A96: q4_sh | B96: Q4 FY26 non-GAAP 稀釋股數 | C96: 十億股 | E96: 4.94 | G96: Derived | H96: Q3 FY26 4.937（公司） | I96: —
A97: G. 營業費用、利息、稅、股數（FY2027 起）
A98: phi | B98: 營業費用成長對營收成長的彈性 | C98: x | D98: 0.05 | E98: 0.1 | F98: 0.3 | G98: Derived | H98: FY2026 錨點營業費用年增 ÷ 營收年增（Q 頁，約 0.09） | I98: 低／高 Assumed
A99: g_opx_min | B99: 營業費用年增下限 | C99: % | D99: 0 | E99: 0.03 | F99: 0.06 | G99: Assumed | H99: 無 | I99: —
A100: opx_adj | B100: 營業費用額外占營收比（Sens 用；基準 0） | C100: pt | D100: -0.02 | E100: 0 | F100: 0.02 | G100: Assumed | H100: 無 | I100: Sens 用 ±2 個百分點
A101: int_f | B101: non-GAAP 利息費用（每年） | C101: US$B | D101: 2.5 | E101: 2.8 | F101: 4 | G101: Assumed | H101: FY2026 錨點約 2.9（Q 頁）；總債務 59.4（Q3 FY26，公司） | I101: 高端：客戶融資若改由 Broadcom 舉債承擔（見 Recon F 節）
A102: oth_f | B102: non-GAAP 其他收益（每年） | C102: US$B | D102: 0.2 | E102: 0.4 | F102: 0.6 | G102: Assumed | H102: FY2026 約 0.43（Q 頁） | I102: —
A103: tx_f | B103: non-GAAP 有效稅率 | C103: % | D103: 0.15 | E103: 0.16 | F103: 0.18 | G103: Derived | H103: FY2026 Q1–Q3 約 15.6–16.5%（公司） | I103: —
A104: sh_g | B104: 稀釋股數年變動 | C104: % | D104: -0.015 | E104: -0.005 | F104: 0 | G104: Derived | H104: FY2025 4.943 → Q3 FY26 4.937（公司） | I104: 低／高 Assumed
A105: uk | B105: Broadcom XPU 顆數係數（Sens 用；FY2027 起） | C105: x | D105: 0.9 | E105: 1 | F105: 1.1 | G105: Assumed | H105: 無 | I105: ±10%
A106: H. 公司展望與共識（只作 Recon 對帳，不作校準）
A107: co_ai26 | B107: 公司 FY2026 AI 營收展望 | C107: US$B | E107: 58 | G107: Interested-party | H107: 法說轉述：Investing.com 逐字稿、BigGo Finance 摘要（2026-09-02；二手） | I107: Q1–Q3 實績＋Q4 指引合計 57.6（Q 頁）
A108: co_ai27 | B108: 公司 FY2027 AI 營收展望 | C108: US$B | E108: 115 | G108: Interested-party | H108: 法說轉述：Investing.com 逐字稿、BigGo Finance 摘要（2026-09-02；二手）：約 $115B；公司稱不會逐季更新 | I108: JPMorgan：FY2027 超過 $150B（KuCoin 轉述，Interested-party）
A109: co_ai28 | B109: 公司 FY2028 AI 營收展望 | C109: US$B | E109: 230 | G109: Interested-party | H109: 法說轉述：Investing.com 逐字稿、BigGo Finance 摘要（2026-09-02；二手）：約 $230B | I109: top1markets 2026-10-22（二手）同值
A110: jpm_ai27 | B110: JPMorgan FY2027 AI 營收估計 | C110: US$B | E110: 150 | G110: Interested-party | H110: JPMorgan（KuCoin 2026-06-22 轉述）：超過 $150B | I110: —
A111: cons_rev26 | B111: 共識 FY2026 營收 | C111: US$B | E111: 105.98 | G111: Interested-party | H111: StockAnalysis（S&P Global，40 位分析師，2026-10-22） | I111: —
A112: cons_eps26 | B112: 共識 FY2026 non-GAAP EPS | C112: US$ | E112: 11.66 | G112: Interested-party | H112: 同上（區間 11.35–12.38） | I112: —
A113: cons_rev27 | B113: 共識 FY2027 營收 | C113: US$B | E113: 173.97 | G113: Interested-party | H113: 同上（「明年」欄，頁面未標年度） | I113: —
A114: cons_eps27 | B114: 共識 FY2027 non-GAAP EPS | C114: US$ | E114: 19.4 | G114: Interested-party | H114: 同上 | I114: —
A115: jpm_u27 | B115: 2027 年 ASIC 占加速器出貨顆數（JPMorgan） | C115: % | E115: 0.536 | G115: Interested-party | H115: JPMorgan（KuCoin 轉述）：ASIC 12.5M ÷ 23.3M | I115: 本專案市場層 ASIC 2027 12.5M 同一來源
A116: cp_sh27 | B116: 2027 年 Broadcom 占 ASIC 設計夥伴份額（Counterpoint） | C116: % | E116: 0.6 | G116: Interested-party | H116: Counterpoint（Benzinga／Yahoo 2026-01-28 轉述；口徑未說明） | I116: JPMorgan：高階 ASIC 80–85%
A117: I. 加速器每顆價格（金額份額計算用；讀 NVIDIA 模型成品，模組層級）
A118: pm_bw | B118: Blackwell 模組 每顆 | C118: US$K | E118: 40.4 | G118: Derived | H118: nvidia/dist/20261023_NVIDIA模型_v0.1.1.xlsx｜In!E56 | I118: NVIDIA 模型 In 頁（同一套價格；唯讀）
A119: pm_rb | B119: Rubin 模組 每顆 | C119: US$K | E119: 55 | G119: Derived | H119: nvidia/dist/20261023_NVIDIA模型_v0.1.1.xlsx｜In!E57 | I119: NVIDIA 模型 In 頁（同一套價格；唯讀）
A120: pm_ru | B120: Rubin Ultra 模組 每顆 | C120: US$K | E120: 75 | G120: Derived | H120: nvidia/dist/20261023_NVIDIA模型_v0.1.1.xlsx｜In!E58 | I120: NVIDIA 模型 In 頁（同一套價格；唯讀）
A121: pm_hp | B121: Hopper 模組 每顆 | C121: US$K | E121: 30 | G121: Derived | H121: nvidia/dist/20261023_NVIDIA模型_v0.1.1.xlsx｜In!E59 | I121: NVIDIA 模型 In 頁（同一套價格；唯讀）
A122: pa_amd | B122: AMD Instinct 每顆 | C122: US$K | E122: 30 | G122: Derived | H122: nvidia/dist/20261023_NVIDIA模型_v0.1.1.xlsx｜In!E145 | I122: NVIDIA 模型 In 頁（同一套價格；唯讀）
A123: pa_trn | B123: AWS Trainium 每顆 | C123: US$K | E123: 8 | G123: Derived | H123: nvidia/dist/20261023_NVIDIA模型_v0.1.1.xlsx｜In!E147 | I123: NVIDIA 模型 In 頁（同一套價格；唯讀）
A124: J. 價格、估值與客戶融資
A125: px | B125: 股價（2026-10-22 收盤） | C125: US$ | E125: 323.24 | G125: Interested-party | H125: StockAnalysis（2026-10-22 收盤） | I125: YCharts 同值（2026-10-22 收盤 323.24）
A126: pe_ttm_gaap | B126: 近 12 月 GAAP P/E | C126: x | E126: 41.26 | G126: Interested-party | H126: StockAnalysis | I126: top1markets：近 12 月約 45x（10 月報導）
A127: pe_fwd_sa | B127: 前瞻 P/E（StockAnalysis） | C127: x | E127: 18.61 | G127: Interested-party | H127: StockAnalysis（口徑未說明） | I127: GuruFocus 17.39；valueinvesting.io 49.62（2026-10-22；口徑不明，可能為 GAAP 或舊預估，不採）
A128: eps_q4_25 | B128: Q4 FY25 non-GAAP EPS（近 12 月計算用） | C128: US$ | E128: 1.95 | G128: Verified | H128: https://www.sec.gov/Archives/edgar/data/1730168/000173016825000116/avgo-11022025x8kxex99.htm | I128: —
A129: pe_fair_andy | B129: Andy 先驗：合理 P/E | C129: x | E129: 25 | G129: Assumed | H129: 先驗_Andy_AVGO_20261023 B9b（Drive；不在本 repo） | I129: 只作對照
A130: fin_anth | B130: Broadcom 對 Anthropic 放款上限（可轉股） | C130: US$B | E130: 42 | G130: Interested-party | H130: top1markets 2026-10-22 引 Reuters（Anthropic IPO 文件） | I130: Bloomberg：銀行團 $60B 中 $42B 優先擔保部分由 Broadcom 殘值支撐（二手）
A131: fin_oai | B131: Broadcom 為 OpenAI 安排的融資 | C131: US$B | E131: 50 | G131: Interested-party | H131: top1markets 引 WSJ：超過 $50B | I131: —
...

Sheet Q
A1: Q — 實績（十億美元；EPS 為美元；股數為十億股）。口徑：公司 non-GAAP（排除股票薪酬、無形資產攤銷、重組）。藍字＝輸入；黑字＝公式。實績取自 Broadcom 8-K 新聞稿（SEC EDGAR）
A2: FY2026 錨點＝Q1–Q3 實績＋Q4 指引（F 欄；假設見 In 頁 F 節）。AI 營收：Q1 8.4、Q2 10.8、Q3 16.7（公司）、Q4 21.7（公司指引）；AI 網通取 markets/network 的實際推估 rep_avgo26，XPU＝AI − 網通
A3: 項目 | B3: FY2025A | C3: FY26 Q1（～2026-02-01） | D3: FY26 Q2（～05-03） | E3: FY26 Q3（～08-02） | F3: FY26 Q4（指引） | G3: FY2026 錨點 | H3: 標記 | I3: 來源1（公司） | J3: 來源2／說明
A4: 營收 | B4: 63.887 | C4: 19.311 | D4: 22.187 | E4: 29.591 | F4: =q4_rev -> 34.8 | G4: =SUM(C4:F4) -> 105.889 | H4: Verified／Interested-party（Q4 指引） | I4: FY2025、Q4 FY25：https://www.sec.gov/Archives/edgar/data/1730168/000173016825000116/avgo-11022025x8kxex99.htm；Q1 FY26：https://www.sec.gov/Archives/edgar/data/1730168/000173016826000011/avgo-02012026x8kxex99.htm；Q2 FY26：https://www.sec.gov/Archives/edgar/data/1730168/000173016826000051/avgo-05032026x8kxex99.htm；Q3 FY26：https://investors.broadcom.com/news-releases/news-release-details/broadcom-inc-announces-third-quarter-fiscal-year-2026-financial | J4: 交叉：Q3 FY26 稿的九個月合計（營收 71.089、non-GAAP 毛利 54.168、營業利益 47.849、淨利 38.631）＝Q1＋Q2＋Q3（下方檢查列）
A5: 半導體解決方案 | B5: 36.858 | C5: 12.515 | D5: 15.009 | E5: 20.839 | F5: =F4-F6 -> 26.1 | G5: =SUM(C5:F5) -> 74.463 | H5: Verified／Derived（Q4） | I5: FY2025、Q4 FY25：https://www.sec.gov/Archives/edgar/data/1730168/000173016825000116/avgo-11022025x8kxex99.htm；Q1 FY26：https://www.sec.gov/Archives/edgar/data/1730168/000173016826000011/avgo-02012026x8kxex99.htm；Q2 FY26：https://www.sec.gov/Archives/edgar/data/1730168/000173016826000051/avgo-05032026x8kxex99.htm；Q3 FY26：https://investors.broadcom.com/news-releases/news-release-details/broadcom-inc-announces-third-quarter-fiscal-year-2026-financial | J5: 交叉：Q3 FY26 稿的九個月合計（營收 71.089、non-GAAP 毛利 54.168、營業利益 47.849、淨利 38.631）＝Q1＋Q2＋Q3（下方檢查列）
A6: 基礎架構軟體 | B6: 27.029 | C6: 6.796 | D6: 7.178 | E6: 8.752 | F6: =q4_sw -> 8.7 | G6: =SUM(C6:F6) -> 31.426 | H6: Verified／Interested-party（Q4） | I6: FY2025、Q4 FY25：https://www.sec.gov/Archives/edgar/data/1730168/000173016825000116/avgo-11022025x8kxex99.htm；Q1 FY26：https://www.sec.gov/Archives/edgar/data/1730168/000173016826000011/avgo-02012026x8kxex99.htm；Q2 FY26：https://www.sec.gov/Archives/edgar/data/1730168/000173016826000051/avgo-05032026x8kxex99.htm；Q3 FY26：https://investors.broadcom.com/news-releases/news-release-details/broadcom-inc-announces-third-quarter-fiscal-year-2026-financial | J6: 交叉：Q3 FY26 稿的九個月合計（營收 71.089、non-GAAP 毛利 54.168、營業利益 47.849、淨利 38.631）＝Q1＋Q2＋Q3（下方檢查列）
A7: AI 半導體營收 | B7: =co_ai26/(1+1.86) -> 20.27972 | C7: 8.4 | D7: 10.8 | E7: 16.7 | F7: =q4_ai -> 21.7 | G7: =SUM(C7:F7) -> 57.6 | H7: Verified／Interested-party（Q4）／Derived（FY2025） | I7: FY2025、Q4 FY25：https://www.sec.gov/Archives/edgar/data/1730168/000173016825000116/avgo-11022025x8kxex99.htm；Q1 FY26：https://www.sec.gov/Archives/edgar/data/1730168/000173016826000011/avgo-02012026x8kxex99.htm；Q2 FY26：https://www.sec.gov/Archives/edgar/data/1730168/000173016826000051/avgo-05032026x8kxex99.htm；Q3 FY26：https://investors.broadcom.com/news-releases/news-release-details/broadcom-inc-announces-third-quarter-fiscal-year-2026-financial | J7: FY2025＝公司 FY2026 展望 58 ÷（1＋186%）≈ 20.3（JPMorgan：約 20，二手）
A8: AI 網通（實際推估；markets/network rep_avgo26） | G8: =rep_avgo26 -> 17.6 | H8: Derived | I8: markets/network/dist/20261023_AI網通市場模型_v0.2.2.xlsx｜In!D121:F121 | J8: Q3 FY26：XPU 占 AI 73%（法說，二手，單一來源）
A9: XPU（＝AI − 網通） | G9: =G7-G8 -> 40 | H9: Derived | I9: — | J9: FY2026 XPU 占 AI 營收（下一列）
A10: XPU ÷ AI | G10: =G9/G7 -> 0.69444444 | H10: Derived | I10: — | J10: Q3 FY26 73%（法說，二手）
A11: 非 AI 半導體（＝半導體 − AI） | B11: =B5-B7 -> 16.57828 | C11: =C5-C7 -> 4.115 | D11: =D5-D7 -> 4.209 | E11: =E5-E7 -> 4.139 | F11: =F5-F7 -> 4.4 | G11: =SUM(C11:F11) -> 16.863 | H11: Derived | I11: FY2025、Q4 FY25：https://www.sec.gov/Archives/edgar/data/1730168/000173016825000116/avgo-11022025x8kxex99.htm；Q1 FY26：https://www.sec.gov/Archives/edgar/data/1730168/000173016826000011/avgo-02012026x8kxex99.htm；Q2 FY26：https://www.sec.gov/Archives/edgar/data/1730168/000173016826000051/avgo-05032026x8kxex99.htm；Q3 FY26：https://investors.broadcom.com/news-releases/news-release-details/broadcom-inc-announces-third-quarter-fiscal-year-2026-financial | J11: 交叉：Q3 FY26 稿的九個月合計（營收 71.089、non-GAAP 毛利 54.168、營業利益 47.849、淨利 38.631）＝Q1＋Q2＋Q3（下方檢查列）
A12: non-GAAP 毛利 | B12: 50.245 | C12: 14.868 | D12: 17.109 | E12: 22.191 | F12: =F4*q4_gm -> 25.404 | G12: =SUM(C12:F12) -> 79.572 | H12: Verified／Interested-party（Q4） | I12: FY2025、Q4 FY25：https://www.sec.gov/Archives/edgar/data/1730168/000173016825000116/avgo-11022025x8kxex99.htm；Q1 FY26：https://www.sec.gov/Archives/edgar/data/1730168/000173016826000011/avgo-02012026x8kxex99.htm；Q2 FY26：https://www.sec.gov/Archives/edgar/data/1730168/000173016826000051/avgo-05032026x8kxex99.htm；Q3 FY26：https://investors.broadcom.com/news-releases/news-release-details/broadcom-inc-announces-third-quarter-fiscal-year-2026-financial | J12: 交叉：Q3 FY26 稿的九個月合計（營收 71.089、non-GAAP 毛利 54.168、營業利益 47.849、淨利 38.631）＝Q1＋Q2＋Q3（下方檢查列）
A13: 毛利率 | B13: =B12/B4 -> 0.78646673 | C13: =C12/C4 -> 0.76992388 | D13: =D12/D4 -> 0.77112724 | E13: =E12/E4 -> 0.74992396 | F13: =F12/F4 -> 0.73 | G13: =G12/G4 -> 0.75146616 | H13: Derived | I13: — | J13: FY2025 78.6%；Q4 FY26 指引約 73%
A14: non-GAAP 營業費用 | B14: 8.248 | C14: 2.042 | D14: 2.181 | E14: 2.096 | F14: =F12-F15 -> 2.436 | G14: =SUM(C14:F14) -> 8.755 | H14: Verified／Derived（Q4＝毛利 − 營業利益） | I14: FY2025、Q4 FY25：https://www.sec.gov/Archives/edgar/data/1730168/000173016825000116/avgo-11022025x8kxex99.htm；Q1 FY26：https://www.sec.gov/Archives/edgar/data/1730168/000173016826000011/avgo-02012026x8kxex99.htm；Q2 FY26：https://www.sec.gov/Archives/edgar/data/1730168/000173016826000051/avgo-05032026x8kxex99.htm；Q3 FY26：https://investors.broadcom.com/news-releases/news-release-details/broadcom-inc-announces-third-quarter-fiscal-year-2026-financial | J14: 交叉：Q3 FY26 稿的九個月合計（營收 71.089、non-GAAP 毛利 54.168、營業利益 47.849、淨利 38.631）＝Q1＋Q2＋Q3（下方檢查列）
A15: non-GAAP 營業利益 | B15: 41.997 | C15: 12.826 | D15: 14.928 | E15: 20.095 | F15: =F4*q4_oim -> 22.968 | G15: =SUM(C15:F15) -> 70.817 | H15: Verified／Interested-party（Q4） | I15: FY2025、Q4 FY25：https://www.sec.gov/Archives/edgar/data/1730168/000173016825000116/avgo-11022025x8kxex99.htm；Q1 FY26：https://www.sec.gov/Archives/edgar/data/1730168/000173016826000011/avgo-02012026x8kxex99.htm；Q2 FY26：https://www.sec.gov/Archives/edgar/data/1730168/000173016826000051/avgo-05032026x8kxex99.htm；Q3 FY26：https://investors.broadcom.com/news-releases/news-release-details/broadcom-inc-announces-third-quarter-fiscal-year-2026-financial | J15: 交叉：Q3 FY26 稿的九個月合計（營收 71.089、non-GAAP 毛利 54.168、營業利益 47.849、淨利 38.631）＝Q1＋Q2＋Q3（下方檢查列）
A16: 營業利益率 | B16: =B15/B4 -> 0.65736378 | C16: =C15/C4 -> 0.66418104 | D16: =D15/D4 -> 0.67282643 | E16: =E15/E4 -> 0.67909162 | F16: =F15/F4 -> 0.66 | G16: =G15/G4 -> 0.66878524 | H16: Derived | I16: — | J16: —
A17: non-GAAP 利息費用 | B17: 3.072 | C17: 0.746 | D17: 0.745 | E17: 0.703 | F17: =q4_int -> 0.7 | G17: =SUM(C17:F17) -> 2.894 | H17: Verified／Derived（Q4） | I17: FY2025、Q4 FY25：https://www.sec.gov/Archives/edgar/data/1730168/000173016825000116/avgo-11022025x8kxex99.htm；Q1 FY26：https://www.sec.gov/Archives/edgar/data/1730168/000173016826000011/avgo-02012026x8kxex99.htm；Q2 FY26：https://www.sec.gov/Archives/edgar/data/1730168/000173016826000051/avgo-05032026x8kxex99.htm；Q3 FY26：https://investors.broadcom.com/news-releases/news-release-details/broadcom-inc-announces-third-quarter-fiscal-year-2026-financial | J17: 交叉：Q3 FY26 稿的九個月合計（營收 71.089、non-GAAP 毛利 54.168、營業利益 47.849、淨利 38.631）＝Q1＋Q2＋Q3（下方檢查列）
A18: non-GAAP 其他收益 | B18: 0.294 | C18: 0.118 | D18: 0.118 | E18: 0.098 | F18: =q4_oth -> 0.1 | G18: =SUM(C18:F18) -> 0.434 | H18: Verified／Derived（Q4） | I18: FY2025、Q4 FY25：https://www.sec.gov/Archives/edgar/data/1730168/000173016825000116/avgo-11022025x8kxex99.htm；Q1 FY26：https://www.sec.gov/Archives/edgar/data/1730168/000173016826000011/avgo-02012026x8kxex99.htm；Q2 FY26：https://www.sec.gov/Archives/edgar/data/1730168/000173016826000051/avgo-05032026x8kxex99.htm；Q3 FY26：https://investors.broadcom.com/news-releases/news-release-details/broadcom-inc-announces-third-quarter-fiscal-year-2026-financial | J18: 交叉：Q3 FY26 稿的九個月合計（營收 71.089、non-GAAP 毛利 54.168、營業利益 47.849、淨利 38.631）＝Q1＋Q2＋Q3（下方檢查列）
A19: 稅前利益 | B19: =B15-B17+B18 -> 39.219 | C19: =C15-C17+C18 -> 12.198 | D19: =D15-D17+D18 -> 14.301 | E19: =E15-E17+E18 -> 19.49 | F19: =F15-F17+F18 -> 22.368 | G19: =SUM(C19:F19) -> 68.357 | H19: Derived | I19: FY2025、Q4 FY25：https://www.sec.gov/Archives/edgar/data/1730168/000173016825000116/avgo-11022025x8kxex99.htm；Q1 FY26：https://www.sec.gov/Archives/edgar/data/1730168/000173016826000011/avgo-02012026x8kxex99.htm；Q2 FY26：https://www.sec.gov/Archives/edgar/data/1730168/000173016826000051/avgo-05032026x8kxex99.htm；Q3 FY26：https://investors.broadcom.com/news-releases/news-release-details/broadcom-inc-announces-third-quarter-fiscal-year-2026-financial | J19: 交叉：Q3 FY26 稿的九個月合計（營收 71.089、non-GAAP 毛利 54.168、營業利益 47.849、淨利 38.631）＝Q1＋Q2＋Q3（下方檢查列）
A20: non-GAAP 所得稅 | B20: 5.491 | C20: 2.013 | D20: 2.227 | E20: 3.118 | F20: =F19*q4_tx -> 3.57888 | G20: =SUM(C20:F20) -> 10.93688 | H20: Verified／Derived（Q4） | I20: FY2025、Q4 FY25：https://www.sec.gov/Archives/edgar/data/1730168/000173016825000116/avgo-11022025x8kxex99.htm；Q1 FY26：https://www.sec.gov/Archives/edgar/data/1730168/000173016826000011/avgo-02012026x8kxex99.htm；Q2 FY26：https://www.sec.gov/Archives/edgar/data/1730168/000173016826000051/avgo-05032026x8kxex99.htm；Q3 FY26：https://investors.broadcom.com/news-releases/news-release-details/broadcom-inc-announces-third-quarter-fiscal-year-2026-financial | J20: 交叉：Q3 FY26 稿的九個月合計（營收 71.089、non-GAAP 毛利 54.168、營業利益 47.849、淨利 38.631）＝Q1＋Q2＋Q3（下方檢查列）
A21: 有效稅率 | B21: =B20/B19 -> 0.14000867 | C21: =C20/C19 -> 0.16502705 | D21: =D20/D19 -> 0.15572338 | E21: =E20/E19 -> 0.15997948 | F21: =F20/F19 -> 0.16 | G21: =G20/G19 -> 0.15999649 | H21: Derived | I21: — | J21: —
A22: non-GAAP 淨利 | B22: =B19-B20 -> 33.728 | C22: =C19-C20 -> 10.185 | D22: =D19-D20 -> 12.074 | E22: =E19-E20 -> 16.372 | F22: =F19-F20 -> 18.78912 | G22: =SUM(C22:F22) -> 57.42012 | H22: Derived | I22: FY2025、Q4 FY25：https://www.sec.gov/Archives/edgar/data/1730168/000173016825000116/avgo-11022025x8kxex99.htm；Q1 FY26：https://www.sec.gov/Archives/edgar/data/1730168/000173016826000011/avgo-02012026x8kxex99.htm；Q2 FY26：https://www.sec.gov/Archives/edgar/data/1730168/000173016826000051/avgo-05032026x8kxex99.htm；Q3 FY26：https://investors.broadcom.com/news-releases/news-release-details/broadcom-inc-announces-third-quarter-fiscal-year-2026-financial | J22: 交叉：Q3 FY26 稿的九個月合計（營收 71.089、non-GAAP 毛利 54.168、營業利益 47.849、淨利 38.631）＝Q1＋Q2＋Q3（下方檢查列）
A23: 公司揭露 non-GAAP 淨利 | B23: 33.728 | C23: 10.185 | D23: 12.074 | E23: 16.372 | H23: Verified | I23: FY2025、Q4 FY25：https://www.sec.gov/Archives/edgar/data/1730168/000173016825000116/avgo-11022025x8kxex99.htm；Q1 FY26：https://www.sec.gov/Archives/edgar/data/1730168/000173016826000011/avgo-02012026x8kxex99.htm；Q2 FY26：https://www.sec.gov/Archives/edgar/data/1730168/000173016826000051/avgo-05032026x8kxex99.htm；Q3 FY26：https://investors.broadcom.com/news-releases/news-release-details/broadcom-inc-announces-third-quarter-fiscal-year-2026-financial | J23: 交叉：Q3 FY26 稿的九個月合計（營收 71.089、non-GAAP 毛利 54.168、營業利益 47.849、淨利 38.631）＝Q1＋Q2＋Q3（下方檢查列）
A24: non-GAAP 稀釋股數（十億股） | B24: 4.943 | C24: 4.957 | D24: 4.94 | E24: 4.937 | F24: =q4_sh -> 4.94 | G24: =AVERAGE(C24:F24) -> 4.9435 | H24: Verified／Derived（Q4） | I24: FY2025、Q4 FY25：https://www.sec.gov/Archives/edgar/data/1730168/000173016825000116/avgo-11022025x8kxex99.htm；Q1 FY26：https://www.sec.gov/Archives/edgar/data/1730168/000173016826000011/avgo-02012026x8kxex99.htm；Q2 FY26：https://www.sec.gov/Archives/edgar/data/1730168/000173016826000051/avgo-05032026x8kxex99.htm；Q3 FY26：https://investors.broadcom.com/news-releases/news-release-details/broadcom-inc-announces-third-quarter-fiscal-year-2026-financial | J24: 交叉：Q3 FY26 稿的九個月合計（營收 71.089、non-GAAP 毛利 54.168、營業利益 47.849、淨利 38.631）＝Q1＋Q2＋Q3（下方檢查列）
A25: non-GAAP EPS | B25: =B22/B24 -> 6.8233866 | C25: =C22/C24 -> 2.0546702 | D25: =D22/D24 -> 2.4441296 | E25: =E22/E24 -> 3.3161839 | F25: =F22/F24 -> 3.8034656 | G25: =G22/G24 -> 11.615277 | H25: Derived | I25: 淨利 ÷ 稀釋股數 | J25: —
A26: 公司揭露 non-GAAP EPS | B26: 6.82 | C26: 2.05 | D26: 2.44 | E26: 3.32 | H26: Verified | I26: FY2025、Q4 FY25：https://www.sec.gov/Archives/edgar/data/1730168/000173016825000116/avgo-11022025x8kxex99.htm；Q1 FY26：https://www.sec.gov/Archives/edgar/data/1730168/000173016826000011/avgo-02012026x8kxex99.htm；Q2 FY26：https://www.sec.gov/Archives/edgar/data/1730168/000173016826000051/avgo-05032026x8kxex99.htm；Q3 FY26：https://investors.broadcom.com/news-releases/news-release-details/broadcom-inc-announces-third-quarter-fiscal-year-2026-financial | J26: 交叉：Q3 FY26 稿的九個月合計（營收 71.089、non-GAAP 毛利 54.168、營業利益 47.849、淨利 38.631）＝Q1＋Q2＋Q3（下方檢查列）
A27: 檢查：淨利 − 公司揭露（應約為 0；四捨五入） | B27: =B22-B23 -> 0 | C27: =C22-C23 -> 0 | D27: =D22-D23 -> 0 | E27: =E22-E23 -> 0 | H27: — | I27: — | J27: —
A28: 檢查：Q1＋Q2＋Q3 − 九個月合計（營收、毛利、營業利益、淨利；應為 0） | G28: =(C4+D4+E4-71.089)+(C12+D12+E12-54.168)+(C15+D15+E15-47.849)+(C22+D22+E22-38.631) -> 0 | H28: — | I28: https://investors.broadcom.com/news-releases/news-release-details/broadcom-inc-announces-third-quarter-fiscal-year-2026-financial（九個月欄） | J28: —
A30: FY2026 錨點與共識、公司展望的距離（參考；校準未使用共識）
A31: FY2026 營收 ÷ 共識 − 1 | B31: =G4/cons_rev26-1 -> -0.00085865258
A32: FY2026 EPS ÷ 共識 − 1 | B32: =G25/cons_eps26-1 -> -0.0038356239
A33: FY2026 AI 營收 ÷ 公司展望 58 − 1 | B33: =G7/co_ai26-1 -> -0.0068965517
A34: FY2026 營收年增 | B34: =G4/B4-1 -> 0.65744205
A35: FY2026 營業費用年增 | B35: =G14/B14-1 -> 0.061469447
A36: 營業費用彈性（營業費用年增 ÷ 營收年增；In 頁 phi 的依據） | B36: =B35/B34 -> 0.093497895

Sheet Units
A1: Units — ASIC 每顆規格（本專案權威，規則第 13 條）與加速器金額份額。顆數：百萬顆（日曆年；與 HBM、台積電、網通、NVIDIA 模型同一份）；每顆價：US$K
A3: 項目 | B3: 單位 | C3: CY2026（FY2026） | D3: CY2027（FY2027） | E3: CY2028（FY2028） | F3: CY2029（FY2029） | G3: 說明
A4: 1. ASIC 每顆規格（情境 A；Broadcom 營收口徑＝核心售價＋代購 HBM，乘 k_x）
A5: Broadcom 份額：Google TPU | B5: % | C5: =PL!D75 -> 0.9 | D5: =PL!E75 -> 0.8 | E5: =PL!F75 -> 0.75 | F5: =PL!G75 -> 0.75 | G5: In 頁 B 節（Assumed）
A6: Broadcom 顆數：Google TPU | B6: 百萬顆 | C6: =PL!D77 -> 3.465 | D6: =PL!E77 -> 4.4 | E6: =PL!F77 -> 5.25 | F6: =PL!G77 -> 6.0375 | G6: 市場層顆數 × 份額
A7: 每顆 HBM：Google TPU | B7: GB | C7: =PL!D79 -> 192 | D7: =PL!E79 -> 250 | E7: =PL!F79 -> 288 | F7: =PL!G79 -> 288 | G7: markets/memory UNITS
A8: 每顆 HBM 金額：Google TPU | B8: US$K | C8: =PL!D84 -> 2.8032 | D8: =PL!E84 -> 6.57 | E8: =PL!F84 -> 8.325504 | F8: =PL!G84 -> 7.9092288 | G8: 容量 × HBM 單價（情境 A）
A9: 每顆 Broadcom 營收（校準後）：Google TPU | B9: US$K | C9: =PL!D86*PL!$D$89 -> 10.725586 | D9: =PL!E86*PL!$D$89 -> 13.229292 | E9: =PL!F86*PL!$D$89 -> 14.396135 | F9: =PL!G86*PL!$D$89 -> 14.119447 | G9: （核心＋代購比例 × HBM）× k_x
A10: 每顆總價（核心 × k_x ＋ 全部 HBM；金額份額用）：Google TPU | B10: US$K | C10: =PL!D82*PL!$D$89+PL!D84 -> 11.665563 | D10: =PL!E82*PL!$D$89+PL!E84 -> 15.432363 | E10: =PL!F82*PL!$D$89+PL!F84 -> 17.187867 | F10: =PL!G82*PL!$D$89+PL!G84 -> 16.771591 | G10: 與 NVIDIA 模組價同口徑（含全部 HBM，不論誰採購）
A11: Broadcom 份額：其他 ASIC（MTIA、Maia、Ascend 等） | B11: % | C11: =PL!D76 -> 0.35 | D11: =PL!E76 -> 0.55 | E11: =PL!F76 -> 0.55 | F11: =PL!G76 -> 0.55 | G11: In 頁 B 節（Assumed）
A12: Broadcom 顆數：其他 ASIC（MTIA、Maia、Ascend 等） | B12: 百萬顆 | C12: =PL!D78 -> 0.35 | D12: =PL!E78 -> 2.475 | E12: =PL!F78 -> 2.75 | F12: =PL!G78 -> 3.1625 | G12: 市場層顆數 × 份額
A13: 每顆 HBM：其他 ASIC（MTIA、Maia、Ascend 等） | B13: GB | C13: =PL!D80 -> 150 | D13: =PL!E80 -> 200 | E13: =PL!F80 -> 250 | F13: =PL!G80 -> 250 | G13: markets/memory UNITS
A14: 每顆 HBM 金額：其他 ASIC（MTIA、Maia、Ascend 等） | B14: US$K | C14: =PL!D85 -> 2.19 | D14: =PL!E85 -> 5.256 | E14: =PL!F85 -> 7.227 | F14: =PL!G85 -> 6.86565 | G14: 容量 × HBM 單價（情境 A）
A15: 每顆 Broadcom 營收（校準後）：其他 ASIC（MTIA、Maia、Ascend 等） | B15: US$K | C15: =PL!D87*PL!$D$89 -> 8.1024151 | D15: =PL!E87*PL!$D$89 -> 10.140315 | E15: =PL!F87*PL!$D$89 -> 11.450394 | F15: =PL!G87*PL!$D$89 -> 11.210213 | G15: （核心＋代購比例 × HBM）× k_x
A16: 每顆總價（核心 × k_x ＋ 全部 HBM；金額份額用）：其他 ASIC（MTIA、Maia、Ascend 等） | B16: US$K | C16: =PL!D83*PL!$D$89+PL!D85 -> 8.836772 | D16: =PL!E83*PL!$D$89+PL!E85 -> 11.902772 | E16: =PL!F83*PL!$D$89+PL!F85 -> 13.873772 | F16: =PL!G83*PL!$D$89+PL!G85 -> 13.512422 | G16: 與 NVIDIA 模組價同口徑（含全部 HBM，不論誰採購）
A18: 2. 校準值（只用 FY2026 已發生的實績與當季指引；不用共識、不用公司對 FY2027–28 的展望）
A19: XPU 校準係數 k_x | C19: =PL!D89 -> 1.1077953 | G19: FY2026 錨點 XPU ÷ 未校準由下而上；顆數、份額、核心單價的合併係數
A20: 網通校準係數 k_n | C20: =PL!D96 -> 1.3959864 | G20: rep_avgo26 ÷ markets/network 歸屬
A21: XPU 核心毛利率 m_core | C21: =PL!D108 -> 0.78755088 | G21: 讓 FY2026 毛利率等於錨點的殘差（Derived）
A22: FY2026 錨點 XPU | C22: =a26_xpu -> 40 | G22: AI 57.6 − 網通 17.6
A23: FY2026 未校準 XPU | C23: =PL!D88 -> 36.107753
A25: 3. 加速器金額份額（accel_share；各平台每顆總價 × 顆數；ASIC 用本頁第 1 節的 CY2027 每顆總價，其他平台讀 NVIDIA 模型）
A26: 情境 A：基準
A27: 顆數
A28: NVIDIA Blackwell（B200／B300） | B28: 百萬顆 | C28: =u_bw_26 -> 5.4 | D28: =u_bw_27 -> 2.4 | E28: =u_bw_28*um28_A -> 0.5 | F28: =u_bw_28*(1+g29_bw)*um29_A -> 0.25
A29: NVIDIA Rubin | B29: 百萬顆 | C29: =u_rb_26 -> 1.7 | D29: =u_rb_27 -> 7 | E29: =u_rb_28*um28_A -> 7 | F29: =u_rb_28*(1+g29_rb)*um29_A -> 8.05
A30: NVIDIA Rubin Ultra | B30: 百萬顆 | C30: =u_ru_26 -> 0 | D30: =u_ru_27 -> 0.3 | E30: =u_ru_28*um28_A -> 2 | F30: =u_ru_28*(1+g29_ru)*um29_A -> 2.3
A31: NVIDIA Hopper（H200 等） | B31: 百萬顆 | C31: =u_hp_26 -> 0.5 | D31: =u_hp_27 -> 0 | E31: =u_hp_28*um28_A -> 0 | F31: =u_hp_28*(1+g29_hp)*um29_A -> 0
A32: AMD Instinct | B32: 百萬顆 | C32: =u_amd_26 -> 0.75 | D32: =u_amd_27 -> 1.5 | E32: =u_amd_28*um28_A -> 2 | F32: =u_amd_28*(1+g29_amd)*um29_A -> 2.3
A33: Google TPU | B33: 百萬顆 | C33: =u_tpu_26 -> 3.85 | D33: =u_tpu_27 -> 5.5 | E33: =u_tpu_28*um28_A -> 7 | F33: =u_tpu_28*(1+g29_tpu)*um29_A -> 8.05
A34: AWS Trainium | B34: 百萬顆 | C34: =u_trn_26 -> 2 | D34: =u_trn_27 -> 2.5 | E34: =u_trn_28*um28_A -> 3 | F34: =u_trn_28*(1+g29_trn)*um29_A -> 3.45
A35: 其他 ASIC（MTIA、Maia、Ascend 等） | B35: 百萬顆 | C35: =u_oth_26 -> 1 | D35: =u_oth_27 -> 4.5 | E35: =u_oth_28*um28_A -> 5 | F35: =u_oth_28*(1+g29_oth)*um29_A -> 5.75
A36: 合計 | B36: 百萬顆 | C36: =SUM(C28:C35) -> 15.2 | D36: =SUM(D28:D35) -> 23.7 | E36: =SUM(E28:E35) -> 26.5 | F36: =SUM(F28:F35) -> 30.15
A37: 金額（顆數 × 每顆售價）
A38: NVIDIA Blackwell（B200／B300） | B38: US$B | C38: =u_bw_26*(pm_bw) -> 218.16 | D38: =u_bw_27*(pm_bw) -> 96.96 | E38: =u_bw_28*um28_A*(pm_bw) -> 20.2 | F38: =u_bw_28*(1+g29_bw)*um29_A*(pm_bw) -> 10.1
A39: NVIDIA Rubin | B39: US$B | C39: =u_rb_26*(pm_rb) -> 93.5 | D39: =u_rb_27*(pm_rb) -> 385 | E39: =u_rb_28*um28_A*(pm_rb) -> 385 | F39: =u_rb_28*(1+g29_rb)*um29_A*(pm_rb) -> 442.75
A40: NVIDIA Rubin Ultra | B40: US$B | C40: =u_ru_26*(pm_ru) -> 0 | D40: =u_ru_27*(pm_ru) -> 22.5 | E40: =u_ru_28*um28_A*(pm_ru) -> 150 | F40: =u_ru_28*(1+g29_ru)*um29_A*(pm_ru) -> 172.5
A41: NVIDIA Hopper（H200 等） | B41: US$B | C41: =u_hp_26*(pm_hp) -> 15 | D41: =u_hp_27*(pm_hp) -> 0 | E41: =u_hp_28*um28_A*(pm_hp) -> 0 | F41: =u_hp_28*(1+g29_hp)*um29_A*(pm_hp) -> 0
A42: AMD Instinct | B42: US$B | C42: =u_amd_26*(pa_amd) -> 22.5 | D42: =u_amd_27*(pa_amd) -> 45 | E42: =u_amd_28*um28_A*(pa_amd) -> 60 | F42: =u_amd_28*(1+g29_amd)*um29_A*(pa_amd) -> 69
A43: Google TPU | B43: US$B | C43: =u_tpu_26*(Units!$D$10) -> 59.414596 | D43: =u_tpu_27*(Units!$D$10) -> 84.877995 | E43: =u_tpu_28*um28_A*(Units!$D$10) -> 108.02654 | F43: =u_tpu_28*(1+g29_tpu)*um29_A*(Units!$D$10) -> 124.23052
A44: AWS Trainium | B44: US$B | C44: =u_trn_26*(pa_trn) -> 16 | D44: =u_trn_27*(pa_trn) -> 20 | E44: =u_trn_28*um28_A*(pa_trn) -> 24 | F44: =u_trn_28*(1+g29_trn)*um29_A*(pa_trn) -> 27.6
A45: 其他 ASIC（MTIA、Maia、Ascend 等） | B45: US$B | C45: =u_oth_26*(Units!$D$16) -> 11.902772 | D45: =u_oth_27*(Units!$D$16) -> 53.562474 | E45: =u_oth_28*um28_A*(Units!$D$16) -> 59.51386 | F45: =u_oth_28*(1+g29_oth)*um29_A*(Units!$D$16) -> 68.440939
A46: 合計 | B46: US$B | C46: =SUM(C38:C45) -> 436.47737 | D46: =SUM(D38:D45) -> 707.90047 | E46: =SUM(E38:E45) -> 806.7404 | F46: =SUM(F38:F45) -> 914.62146
A47: 顆數份額
A48: NVIDIA | B48: % | C48: =(C28+C29+C30+C31)/C36 -> 0.5 | D48: =(D28+D29+D30+D31)/D36 -> 0.4092827 | E48: =(E28+E29+E30+E31)/E36 -> 0.35849057 | F48: =(F28+F29+F30+F31)/F36 -> 0.35157546
A49: AMD | B49: % | C49: =(C32)/C36 -> 0.049342105 | D49: =(D32)/D36 -> 0.063291139 | E49: =(E32)/E36 -> 0.075471698 | F49: =(F32)/F36 -> 0.07628524
A50: Google TPU | B50: % | C50: =(C33)/C36 -> 0.25328947 | D50: =(D33)/D36 -> 0.23206751 | E50: =(E33)/E36 -> 0.26415094 | F50: =(F33)/F36 -> 0.26699834
A51: AWS Trainium | B51: % | C51: =(C34)/C36 -> 0.13157895 | D51: =(D34)/D36 -> 0.10548523 | E51: =(E34)/E36 -> 0.11320755 | F51: =(F34)/F36 -> 0.11442786
A52: 其他 ASIC | B52: % | C52: =(C35)/C36 -> 0.065789474 | D52: =(D35)/D36 -> 0.18987342 | E52: =(E35)/E36 -> 0.18867925 | F52: =(F35)/F36 -> 0.1907131
A53: 金額份額
A54: NVIDIA | B54: % | C54: =(C38+C39+C40+C41)/C46 -> 0.74840077 | D54: =(D38+D39+D40+D41)/D46 -> 0.7126143 | E54: =(E38+E39+E40+E41)/E46 -> 0.68820156 | F54: =(F38+F39+F40+F41)/F46 -> 0.68372548
A55: AMD | B55: % | C55: =(C42)/C46 -> 0.051549064 | D55: =(D42)/D46 -> 0.063568259 | E55: =(E42)/E46 -> 0.074373367 | F55: =(F42)/F46 -> 0.075441047
A56: Google TPU | B56: % | C56: =(C43)/C46 -> 0.13612297 | D56: =(D43)/D46 -> 0.11990103 | E56: =(E43)/E46 -> 0.13390496 | F56: =(F43)/F46 -> 0.13582725
A57: AWS Trainium | B57: % | C57: =(C44)/C46 -> 0.036657113 | D57: =(D44)/D46 -> 0.028252559 | E57: =(E44)/E46 -> 0.029749347 | F57: =(F44)/F46 -> 0.030176419
A58: 其他 ASIC | B58: % | C58: =(C45)/C46 -> 0.027270078 | D58: =(D45)/D46 -> 0.075663849 | E58: =(E45)/E46 -> 0.073770769 | F58: =(F45)/F46 -> 0.074829798
A59: ASIC 合計（TPU＋Trainium＋其他）金額份額 | C59: =C56+C57+C58 -> 0.20005016 | D59: =D56+D57+D58 -> 0.22381744 | E59: =E56+E57+E58 -> 0.23742507 | F59: =F56+F57+F58 -> 0.24083347
A60: ASIC 合計顆數份額 | C60: =C50+C51+C52 -> 0.45065789 | D60: =D50+D51+D52 -> 0.52742616 | E60: =E50+E51+E52 -> 0.56603774 | F60: =F50+F51+F52 -> 0.5721393
A61: Broadcom ÷ ASIC 金額（ASIC 總價口徑） | C61: =(PL!D77*C10+PL!D78*C16)/(C43+C44+C45) -> 0.49834352 | D61: =(PL!E77*D10+PL!E78*D16)/(D43+D44+D45) -> 0.61450056 | E61: =(PL!F77*E10+PL!F78*E16)/(E43+E44+E45) -> 0.67029814 | F61: =(PL!G77*F10+PL!G78*F16)/(F43+F44+F45) -> 0.6537003
A62: Broadcom ÷ ASIC 顆數 | C62: =PL!D93/(C33+C34+C35) -> 0.55693431 | D62: =PL!E93/(D33+D34+D35) -> 0.55 | E62: =PL!F93/(E33+E34+E35) -> 0.53333333 | F62: =PL!G93/(F33+F34+F35) -> 0.53333333
A64: 情境 B：2028 顆數 ×0.8、2029 ×0.85
A65: 顆數
A66: NVIDIA Blackwell（B200／B300） | B66: 百萬顆 | C66: =u_bw_26 -> 5.4 | D66: =u_bw_27 -> 2.4 | E66: =u_bw_28*um28_B -> 0.4 | F66: =u_bw_28*(1+g29_bw)*um29_B -> 0.2125
A67: NVIDIA Rubin | B67: 百萬顆 | C67: =u_rb_26 -> 1.7 | D67: =u_rb_27 -> 7 | E67: =u_rb_28*um28_B -> 5.6 | F67: =u_rb_28*(1+g29_rb)*um29_B -> 6.8425
A68: NVIDIA Rubin Ultra | B68: 百萬顆 | C68: =u_ru_26 -> 0 | D68: =u_ru_27 -> 0.3 | E68: =u_ru_28*um28_B -> 1.6 | F68: =u_ru_28*(1+g29_ru)*um29_B -> 1.955
A69: NVIDIA Hopper（H200 等） | B69: 百萬顆 | C69: =u_hp_26 -> 0.5 | D69: =u_hp_27 -> 0 | E69: =u_hp_28*um28_B -> 0 | F69: =u_hp_28*(1+g29_hp)*um29_B -> 0
A70: AMD Instinct | B70: 百萬顆 | C70: =u_amd_26 -> 0.75 | D70: =u_amd_27 -> 1.5 | E70: =u_amd_28*um28_B -> 1.6 | F70: =u_amd_28*(1+g29_amd)*um29_B -> 1.955
A71: Google TPU | B71: 百萬顆 | C71: =u_tpu_26 -> 3.85 | D71: =u_tpu_27 -> 5.5 | E71: =u_tpu_28*um28_B -> 5.6 | F71: =u_tpu_28*(1+g29_tpu)*um29_B -> 6.8425
A72: AWS Trainium | B72: 百萬顆 | C72: =u_trn_26 -> 2 | D72: =u_trn_27 -> 2.5 | E72: =u_trn_28*um28_B -> 2.4 | F72: =u_trn_28*(1+g29_trn)*um29_B -> 2.9325
A73: 其他 ASIC（MTIA、Maia、Ascend 等） | B73: 百萬顆 | C73: =u_oth_26 -> 1 | D73: =u_oth_27 -> 4.5 | E73: =u_oth_28*um28_B -> 4 | F73: =u_oth_28*(1+g29_oth)*um29_B -> 4.8875
A74: 合計 | B74: 百萬顆 | C74: =SUM(C66:C73) -> 15.2 | D74: =SUM(D66:D73) -> 23.7 | E74: =SUM(E66:E73) -> 21.2 | F74: =SUM(F66:F73) -> 25.6275
A75: 金額（顆數 × 每顆售價）
A76: NVIDIA Blackwell（B200／B300） | B76: US$B | C76: =u_bw_26*(pm_bw) -> 218.16 | D76: =u_bw_27*(pm_bw) -> 96.96 | E76: =u_bw_28*um28_B*(pm_bw) -> 16.16 | F76: =u_bw_28*(1+g29_bw)*um29_B*(pm_bw) -> 8.585
A77: NVIDIA Rubin | B77: US$B | C77: =u_rb_26*(pm_rb) -> 93.5 | D77: =u_rb_27*(pm_rb) -> 385 | E77: =u_rb_28*um28_B*(pm_rb) -> 308 | F77: =u_rb_28*(1+g29_rb)*um29_B*(pm_rb) -> 376.3375
A78: NVIDIA Rubin Ultra | B78: US$B | C78: =u_ru_26*(pm_ru) -> 0 | D78: =u_ru_27*(pm_ru) -> 22.5 | E78: =u_ru_28*um28_B*(pm_ru) -> 120 | F78: =u_ru_28*(1+g29_ru)*um29_B*(pm_ru) -> 146.625
A79: NVIDIA Hopper（H200 等） | B79: US$B | C79: =u_hp_26*(pm_hp) -> 15 | D79: =u_hp_27*(pm_hp) -> 0 | E79: =u_hp_28*um28_B*(pm_hp) -> 0 | F79: =u_hp_28*(1+g29_hp)*um29_B*(pm_hp) -> 0
A80: AMD Instinct | B80: US$B | C80: =u_amd_26*(pa_amd) -> 22.5 | D80: =u_amd_27*(pa_amd) -> 45 | E80: =u_amd_28*um28_B*(pa_amd) -> 48 | F80: =u_amd_28*(1+g29_amd)*um29_B*(pa_amd) -> 58.65
A81: Google TPU | B81: US$B | C81: =u_tpu_26*(Units!$D$10) -> 59.414596 | D81: =u_tpu_27*(Units!$D$10) -> 84.877995 | E81: =u_tpu_28*um28_B*(Units!$D$10) -> 86.421231 | F81: =u_tpu_28*(1+g29_tpu)*um29_B*(Units!$D$10) -> 105.59594
A82: AWS Trainium | B82: US$B | C82: =u_trn_26*(pa_trn) -> 16 | D82: =u_trn_27*(pa_trn) -> 20 | E82: =u_trn_28*um28_B*(pa_trn) -> 19.2 | F82: =u_trn_28*(1+g29_trn)*um29_B*(pa_trn) -> 23.46
A83: 其他 ASIC（MTIA、Maia、Ascend 等） | B83: US$B | C83: =u_oth_26*(Units!$D$16) -> 11.902772 | D83: =u_oth_27*(Units!$D$16) -> 53.562474 | E83: =u_oth_28*um28_B*(Units!$D$16) -> 47.611088 | F83: =u_oth_28*(1+g29_oth)*um29_B*(Units!$D$16) -> 58.174798
A84: 合計 | B84: US$B | C84: =SUM(C76:C83) -> 436.47737 | D84: =SUM(D76:D83) -> 707.90047 | E84: =SUM(E76:E83) -> 645.39232 | F84: =SUM(F76:F83) -> 777.42824
A85: 顆數份額
A86: NVIDIA | B86: % | C86: =(C66+C67+C68+C69)/C74 -> 0.5 | D86: =(D66+D67+D68+D69)/D74 -> 0.4092827 | E86: =(E66+E67+E68+E69)/E74 -> 0.35849057 | F86: =(F66+F67+F68+F69)/F74 -> 0.35157546
A87: AMD | B87: % | C87: =(C70)/C74 -> 0.049342105 | D87: =(D70)/D74 -> 0.063291139 | E87: =(E70)/E74 -> 0.075471698 | F87: =(F70)/F74 -> 0.07628524
A88: Google TPU | B88: % | C88: =(C71)/C74 -> 0.25328947 | D88: =(D71)/D74 -> 0.23206751 | E88: =(E71)/E74 -> 0.26415094 | F88: =(F71)/F74 -> 0.26699834
A89: AWS Trainium | B89: % | C89: =(C72)/C74 -> 0.13157895 | D89: =(D72)/D74 -> 0.10548523 | E89: =(E72)/E74 -> 0.11320755 | F89: =(F72)/F74 -> 0.11442786
A90: 其他 ASIC | B90: % | C90: =(C73)/C74 -> 0.065789474 | D90: =(D73)/D74 -> 0.18987342 | E90: =(E73)/E74 -> 0.18867925 | F90: =(F73)/F74 -> 0.1907131
A91: 金額份額
A92: NVIDIA | B92: % | C92: =(C76+C77+C78+C79)/C84 -> 0.74840077 | D92: =(D76+D77+D78+D79)/D84 -> 0.7126143 | E92: =(E76+E77+E78+E79)/E84 -> 0.68820156 | F92: =(F76+F77+F78+F79)/F84 -> 0.68372548
A93: AMD | B93: % | C93: =(C80)/C84 -> 0.051549064 | D93: =(D80)/D84 -> 0.063568259 | E93: =(E80)/E84 -> 0.074373367 | F93: =(F80)/F84 -> 0.075441047
A94: Google TPU | B94: % | C94: =(C81)/C84 -> 0.13612297 | D94: =(D81)/D84 -> 0.11990103 | E94: =(E81)/E84 -> 0.13390496 | F94: =(F81)/F84 -> 0.13582725
A95: AWS Trainium | B95: % | C95: =(C82)/C84 -> 0.036657113 | D95: =(D82)/D84 -> 0.028252559 | E95: =(E82)/E84 -> 0.029749347 | F95: =(F82)/F84 -> 0.030176419
A96: 其他 ASIC | B96: % | C96: =(C83)/C84 -> 0.027270078 | D96: =(D83)/D84 -> 0.075663849 | E96: =(E83)/E84 -> 0.073770769 | F96: =(F83)/F84 -> 0.074829798
A97: ASIC 合計（TPU＋Trainium＋其他）金額份額 | C97: =C94+C95+C96 -> 0.20005016 | D97: =D94+D95+D96 -> 0.22381744 | E97: =E94+E95+E96 -> 0.23742507 | F97: =F94+F95+F96 -> 0.24083347
A98: ASIC 合計顆數份額 | C98: =C88+C89+C90 -> 0.45065789 | D98: =D88+D89+D90 -> 0.52742616 | E98: =E88+E89+E90 -> 0.56603774 | F98: =F88+F89+F90 -> 0.5721393
A99: Broadcom ÷ ASIC 金額（ASIC 總價口徑） | C99: =(PL!D132*C10+PL!D133*C16)/(C81+C82+C83) -> 0.49834352 | D99: =(PL!E132*D10+PL!E133*D16)/(D81+D82+D83) -> 0.61450056 | E99: =(PL!F132*E10+PL!F133*E16)/(E81+E82+E83) -> 0.67029814 | F99: =(PL!G132*F10+PL!G133*F16)/(F81+F82+F83) -> 0.6537003
A100: Broadcom ÷ ASIC 顆數 | C100: =PL!D148/(C71+C72+C73) -> 0.55693431 | D100: =PL!E148/(D71+D72+D73) -> 0.55 | E100: =PL!F148/(E71+E72+E73) -> 0.53333333 | F100: =PL!G148/(F71+F72+F73) -> 0.53333333
A102: 情境 C：2028–29 顆數 ×0.6
A103: 顆數
A104: NVIDIA Blackwell（B200／B300） | B104: 百萬顆 | C104: =u_bw_26 -> 5.4 | D104: =u_bw_27 -> 2.4 | E104: =u_bw_28*um28_C -> 0.3 | F104: =u_bw_28*(1+g29_bw)*um29_C -> 0.15
A105: NVIDIA Rubin | B105: 百萬顆 | C105: =u_rb_26 -> 1.7 | D105: =u_rb_27 -> 7 | E105: =u_rb_28*um28_C -> 4.2 | F105: =u_rb_28*(1+g29_rb)*um29_C -> 4.83
...

Sheet PL
A1: PL — Broadcom 損益（US$B；non-GAAP）。FY2025A 實績、FY2026 錨點（Q1–Q3 實績＋Q4 指引），FY2027 起為由下而上。FY(t)＝CY(t)。三情境各一個完整推導區塊（本頁下方），頂端為摘要。FY2026–FY2027 三情境相同（顆數係數從 CY2028 開始；HBM 價格 2027 三情境相同）
A3: 情境／項目 | B3: 單位 | C3: FY2025A | D3: FY2026（錨點） | E3: FY2027 | F3: FY2028 | G3: FY2029 | H3: 說明
A4: 情境 A
A5: 營收 | B5: US$B | C5: =C103 -> 63.887 | D5: =D103 -> 105.889 | E5: =E103 -> 173.50734 | F5: =F103 -> 207.77522 | G5: =G103 -> 232.99313
A6: 營收年增 | B6: % | D6: =D105 -> 0.65744205 | E6: =E105 -> 0.63857755 | F6: =F105 -> 0.19750102 | G6: =G105 -> 0.12137115
A7: AI 半導體 | B7: US$B | C7: =C98 -> 20.27972 | D7: =D98 -> 57.6 | E7: =E98 -> 120.94133 | F7: =F98 -> 151.87237 | G7: =G98 -> 173.51256
A8: XPU | B8: US$B | D8: =D90 -> 40 | E8: =E90 -> 83.306165 | F8: =F90 -> 107.06829 | G8: =G90 -> 120.69846
A9: AI 網通 | B9: US$B | D9: =D97 -> 17.6 | E9: =E97 -> 37.635164 | F9: =F97 -> 44.804075 | G9: =G97 -> 52.814098
A10: 基礎架構軟體 | B10: US$B | C10: =C101 -> 27.029 | D10: =D101 -> 31.426 | E10: =E101 -> 35.19712 | F10: =F101 -> 38.01289 | G10: =G101 -> 41.053921
A11: 毛利率 | B11: % | C11: =C110 -> 0.78646673 | D11: =D110 -> 0.75146616 | E11: =E110 -> 0.67762206 | F11: =F110 -> 0.64735182 | G11: =G110 -> 0.65021026
A12: 營業利益率 | B12: % | C12: =C115 -> 0.65736378 | D12: =D115 -> 0.66878524 | E12: =E115 -> 0.62394091 | F12: =F115 -> 0.60117934 | G12: =G115 -> 0.60779999
A13: 淨利（non-GAAP） | B13: US$B | C13: =C119 -> 33.728 | D13: =D119 -> 57.42012 | E13: =E119 -> 88.920994 | F13: =F119 -> 102.90854 | G13: =G119 -> 116.93911
A14: EPS（non-GAAP） | B14: US$ | C14: =C121 -> 6.8233866 | D14: =D121 -> 11.615277 | E14: =E121 -> 18.077846 | F14: =F121 -> 21.026681 | G14: =G121 -> 24.01353
A15: EPS 年增 | B15: % | D15: =D122 -> 0.70227444 | E15: =E122 -> 0.55638534 | F15: =F122 -> 0.16311867 | G15: =G122 -> 0.14205043
A17: 情境 B
A18: 營收 | B18: US$B | C18: =C158 -> 63.887 | D18: =D158 -> 105.889 | E18: =E158 -> 173.50734 | F18: =F158 -> 166.64307 | G18: =G158 -> 195.88729
A19: 營收年增 | B19: % | D19: =D160 -> 0.65744205 | E19: =E160 -> 0.63857755 | F19: =F160 -> -0.039561814 | G19: =G160 -> 0.17549015
A20: AI 半導體 | B20: US$B | C20: =C153 -> 20.27972 | D20: =D153 -> 57.6 | E20: =E153 -> 120.94133 | F20: =F153 -> 110.74023 | G20: =G153 -> 136.40672
A21: XPU | B21: US$B | D21: =D145 -> 40 | E21: =E145 -> 83.306165 | F21: =F145 -> 74.896967 | G21: =G145 -> 91.514732
A22: AI 網通 | B22: US$B | D22: =D152 -> 17.6 | E22: =E152 -> 37.635164 | F22: =F152 -> 35.84326 | G22: =G152 -> 44.891983
A23: 基礎架構軟體 | B23: US$B | C23: =C156 -> 27.029 | D23: =D156 -> 31.426 | E23: =E156 -> 35.19712 | F23: =F156 -> 38.01289 | G23: =G156 -> 41.053921
A24: 毛利率 | B24: % | C24: =C165 -> 0.78646673 | D24: =D165 -> 0.75146616 | E24: =E165 -> 0.67762206 | F24: =F165 -> 0.69563801 | G24: =G165 -> 0.69012171
A25: 營業利益率 | B25: % | C25: =C170 -> 0.65736378 | D25: =D170 -> 0.66878524 | E25: =E170 -> 0.62394091 | F25: =F170 -> 0.63806888 | G25: =G170 -> 0.6396779
A26: 淨利（non-GAAP） | B26: US$B | C26: =C174 -> 33.728 | D26: =D174 -> 57.42012 | E26: =E174 -> 88.920994 | F26: =F174 -> 87.300998 | G26: =G174 -> 103.24001
A27: EPS（non-GAAP） | B27: US$ | C27: =C176 -> 6.8233866 | D27: =D176 -> 11.615277 | E27: =E176 -> 18.077846 | F27: =F176 -> 17.837686 | G27: =G176 -> 21.200409
A28: EPS 年增 | B28: % | D28: =D177 -> 0.70227444 | E28: =E177 -> 0.55638534 | F28: =F177 -> -0.013284804 | G28: =G177 -> 0.18851793
A30: 情境 C
A31: 營收 | B31: US$B | C31: =C213 -> 63.887 | D31: =D213 -> 105.889 | E31: =E213 -> 173.50734 | F31: =F213 -> 135.50019 | G31: =G213 -> 152.58647
A32: 營收年增 | B32: % | D32: =D215 -> 0.65744205 | E32: =E215 -> 0.63857755 | F32: =F215 -> -0.21905208 | G32: =G215 -> 0.12609781
A33: AI 半導體 | B33: US$B | C33: =C208 -> 20.27972 | D33: =D208 -> 57.6 | E33: =E208 -> 120.94133 | F33: =F208 -> 79.597349 | G33: =G208 -> 93.105897
A34: XPU | B34: US$B | D34: =D200 -> 40 | E34: =E200 -> 83.306165 | F34: =F200 -> 52.714904 | G34: =G200 -> 61.417438
A35: AI 網通 | B35: US$B | D35: =D207 -> 17.6 | E35: =E207 -> 37.635164 | F35: =F207 -> 26.882445 | G35: =G207 -> 31.688459
A36: 基礎架構軟體 | B36: US$B | C36: =C211 -> 27.029 | D36: =D211 -> 31.426 | E36: =E211 -> 35.19712 | F36: =F211 -> 38.01289 | G36: =G211 -> 41.053921
A37: 毛利率 | B37: % | C37: =C220 -> 0.78646673 | D37: =D220 -> 0.75146616 | E37: =E220 -> 0.67762206 | F37: =F220 -> 0.72576851 | G37: =G220 -> 0.71998218
A38: 營業利益率 | B38: % | C38: =C225 -> 0.65736378 | D38: =D225 -> 0.66878524 | E38: =E225 -> 0.62394091 | F38: =F225 -> 0.6549679 | G38: =G225 -> 0.65522347
A39: 淨利（non-GAAP） | B39: US$B | C39: =C229 -> 33.728 | D39: =D229 -> 57.42012 | E39: =E229 -> 88.920994 | F39: =F229 -> 72.532553 | G39: =G229 -> 81.965721
A40: EPS（non-GAAP） | B40: US$ | C40: =C231 -> 6.8233866 | D40: =D231 -> 11.615277 | E40: =E231 -> 18.077846 | F40: =F231 -> 14.820139 | G40: =G231 -> 16.831719
A41: EPS 年增 | B41: % | D41: =D232 -> 0.70227444 | E41: =E232 -> 0.55638534 | F41: =F232 -> -0.18020441 | G41: =G232 -> 0.13573293
A43: 核對（應為 0）：FY2026 由下而上營收 − 錨點；FY2026 由下而上 XPU − 錨點 XPU（k_x、k_n 校準恆等式）
A44: 情境 A：營收差（US$B） | D44: =D104-a26_rev -> 0
A45: 情境 A：XPU 差（US$B） | D45: =D90-a26_xpu -> 0
A70: 情境 A：基準（顆數係數 1.0）
A71: 項目 | B71: 單位 | C71: FY2025A | D71: FY2026（錨點） | E71: FY2027 | F71: FY2028 | G71: FY2029 | H71: 說明
A72: A. XPU（由下而上；D 欄＝FY2026 校準年，E–G＝FY2027–FY2029；FY(t)＝CY(t)）
A73: Google TPU 市場顆數 | B73: 百萬顆 | D73: =u_tpu_26 -> 3.85 | E73: =u_tpu_27 -> 5.5 | F73: =u_tpu_28*um28_A -> 7 | G73: =u_tpu_28*(1+g29_tpu)*um29_A -> 8.05
A74: 其他 ASIC（MTIA、Maia、Ascend 等） 市場顆數 | B74: 百萬顆 | D74: =u_oth_26 -> 1 | E74: =u_oth_27 -> 4.5 | F74: =u_oth_28*um28_A -> 5 | G74: =u_oth_28*(1+g29_oth)*um29_A -> 5.75
A75: Broadcom 份額：Google TPU | B75: % | D75: =sh_tpu_26 -> 0.9 | E75: =MIN(1,MAX(0,sh_tpu_27+0)) -> 0.8 | F75: =MIN(1,MAX(0,sh_tpu_28+0)) -> 0.75 | G75: =MIN(1,MAX(0,sh_tpu_28+0)) -> 0.75
A76: Broadcom 份額：其他 ASIC（MTIA、Maia、Ascend 等） | B76: % | D76: =sh_oth_26 -> 0.35 | E76: =MIN(1,MAX(0,sh_oth_27+0)) -> 0.55 | F76: =MIN(1,MAX(0,sh_oth_28+0)) -> 0.55 | G76: =MIN(1,MAX(0,sh_oth_28+0)) -> 0.55
A77: Broadcom 顆數：Google TPU | B77: 百萬顆 | D77: =D73*D75 -> 3.465 | E77: =E73*E75*1 -> 4.4 | F77: =F73*F75*1 -> 5.25 | G77: =G73*G75*1 -> 6.0375
A78: Broadcom 顆數：其他 ASIC（MTIA、Maia、Ascend 等） | B78: 百萬顆 | D78: =D74*D76 -> 0.35 | E78: =E74*E76*1 -> 2.475 | F78: =F74*F76*1 -> 2.75 | G78: =G74*G76*1 -> 3.1625
A79: 每顆 HBM：Google TPU | B79: GB | D79: =gb_tpu_26 -> 192 | E79: =gb_tpu_27 -> 250 | F79: =gb_tpu_28 -> 288 | G79: =gb_tpu_28 -> 288
A80: 每顆 HBM：其他 ASIC（MTIA、Maia、Ascend 等） | B80: GB | D80: =gb_oth_26 -> 150 | E80: =gb_oth_27 -> 200 | F80: =gb_oth_28 -> 250 | G80: =gb_oth_28 -> 250
A81: HBM 單價 | B81: US$/GB | D81: =hbm_A_26 -> 14.6 | E81: =hbm_A_27 -> 26.28 | F81: =hbm_A_28 -> 28.908 | G81: =hbm_A_29 -> 27.4626
A82: 每顆核心售價：Google TPU | B82: US$K | D82: =core_tpu -> 8 | E82: =core_tpu*1 -> 8 | F82: =core_tpu*1 -> 8 | G82: =core_tpu*1 -> 8
A83: 每顆核心售價：其他 ASIC（MTIA、Maia、Ascend 等） | B83: US$K | D83: =core_oth -> 6 | E83: =core_oth*1 -> 6 | F83: =core_oth*1 -> 6 | G83: =core_oth*1 -> 6
A84: 每顆 HBM 金額（全部）：Google TPU | B84: US$K | D84: =D79*D81/1000 -> 2.8032 | E84: =E79*E81/1000 -> 6.57 | F84: =F79*F81/1000 -> 8.325504 | G84: =G79*G81/1000 -> 7.9092288
A85: 每顆 HBM 金額（全部）：其他 ASIC（MTIA、Maia、Ascend 等） | B85: US$K | D85: =D80*D81/1000 -> 2.19 | E85: =E80*E81/1000 -> 5.256 | F85: =F80*F81/1000 -> 7.227 | G85: =G80*G81/1000 -> 6.86565
A86: 每顆 Broadcom 售價（核心＋代購 HBM）：Google TPU | B86: US$K | D86: =D82+f_hbm*D84 -> 9.68192 | E86: =E82+f_hbm*E84 -> 11.942 | F86: =F82+f_hbm*F84 -> 12.995302 | G86: =G82+f_hbm*G84 -> 12.745537 | H86: 核心售價 ＋ 代購比例 × HBM 金額（未乘 k_x）
A87: 每顆 Broadcom 售價（核心＋代購 HBM）：其他 ASIC（MTIA、Maia、Ascend 等） | B87: US$K | D87: =D83+f_hbm*D85 -> 7.314 | E87: =E83+f_hbm*E85 -> 9.1536 | F87: =F83+f_hbm*F85 -> 10.3362 | G87: =G83+f_hbm*G85 -> 10.11939
A88: XPU 營收（未校準） | B88: US$B | D88: =D77*D86+D78*D87 -> 36.107753 | E88: =E77*E86+E78*E87 -> 75.19996 | F88: =F77*F86+F78*F87 -> 96.649888 | G88: =G77*G86+G78*G87 -> 108.95375
A89: XPU 校準係數 k_x ＝ FY2026 錨點 XPU ÷ 未校準 | B89: x | D89: =a26_xpu/D88 -> 1.1077953 | H89: Derived：以已發生的實績（Q1–Q3＋Q4 指引）校準；FY2027 起沿用。顆數層、份額與核心單價無法分開識別，k_x 是合併係數
A90: XPU 營收 | B90: US$B | D90: =D88*$D$89 -> 40 | E90: =E88*$D$89 -> 83.306165 | F90: =F88*$D$89 -> 107.06829 | G90: =G88*$D$89 -> 120.69846
A91: 其中代購 HBM | B91: US$B | D91: =$D$89*f_hbm*(D77*D84+D78*D85) -> 6.9655432 | E91: =$D$89*f_hbm*(E77*E84+E78*E85) -> 27.861008 | F91: =$D$89*f_hbm*(F77*F84+F78*F85) -> 42.262267 | G91: =$D$89*f_hbm*(G77*G84+G78*G85) -> 46.171527
A92: 其中核心（設計＋邏輯晶片＋封裝） | B92: US$B | D92: =D90-D91 -> 33.034457 | E92: =E90-E91 -> 55.445156 | F92: =F90-F91 -> 64.806027 | G92: =G90-G91 -> 74.526931
A93: Broadcom XPU 顆數（未乘 k_x） | B93: 百萬顆 | D93: =D77+D78 -> 3.815 | E93: =E77+E78 -> 6.875 | F93: =F77+F78 -> 8 | G93: =G77+G78 -> 9.2
A94: B. AI 網通、非 AI 半導體、軟體
A95: AI 網通（markets/network 歸屬 × 情境顆數係數） | B95: US$B | D95: =net_26*1 -> 12.607573 | E95: =net_27*1*1 -> 26.959549 | F95: =net_28*um28_A*1 -> 32.094922 | G95: =net_29*um29_A*1 -> 37.832817
A96: 網通校準係數 k_n ＝ 實際推估 ÷ 歸屬（FY2026） | B96: x | D96: =a26_net/D95 -> 1.3959864 | H96: Derived：markets/network 的 Broadcom 歸屬比例為 Assumed，2026 較實際推估低；FY2027 起沿用
A97: AI 網通營收 | B97: US$B | D97: =D95*$D$96 -> 17.6 | E97: =E95*$D$96 -> 37.635164 | F97: =F95*$D$96 -> 44.804075 | G97: =G95*$D$96 -> 52.814098
A98: AI 半導體營收 | B98: US$B | C98: =a25_ai -> 20.27972 | D98: =D90+D97 -> 57.6 | E98: =E90+E97 -> 120.94133 | F98: =F90+F97 -> 151.87237 | G98: =G90+G97 -> 173.51256
A99: XPU ÷ AI | B99: % | D99: =D90/D98 -> 0.69444444 | E99: =E90/E98 -> 0.6888147 | F99: =F90/F98 -> 0.70498864 | G99: =G90/G98 -> 0.695618
A100: 非 AI 半導體 | B100: US$B | C100: =a25_nai -> 16.57828 | D100: =a26_nai -> 16.863 | E100: =D100*(1+g_nai) -> 17.36889 | F100: =E100*(1+g_nai) -> 17.889957 | G100: =F100*(1+g_nai) -> 18.426655
A101: 基礎架構軟體 | B101: US$B | C101: =a25_sw -> 27.029 | D101: =a26_sw -> 31.426 | E101: =D101*(1+g_sw27) -> 35.19712 | F101: =E101*(1+g_sw) -> 38.01289 | G101: =F101*(1+g_sw) -> 41.053921
A102: C. 報告值（FY2025A、FY2026 為實績與錨點；FY2027 起為由下而上）
A103: 營收 | B103: US$B | C103: =a25_rev -> 63.887 | D103: =a26_rev -> 105.889 | E103: =E98+E100+E101 -> 173.50734 | F103: =F98+F100+F101 -> 207.77522 | G103: =G98+G100+G101 -> 232.99313
A104: 由下而上營收（FY2026 應等於錨點） | B104: US$B | D104: =D98+D100+D101 -> 105.889 | E104: =E98+E100+E101 -> 173.50734 | F104: =F98+F100+F101 -> 207.77522 | G104: =G98+G100+G101 -> 232.99313
A105: 營收年增 | B105: % | D105: =D103/C103-1 -> 0.65744205 | E105: =E103/D103-1 -> 0.63857755 | F105: =F103/E103-1 -> 0.19750102 | G105: =G103/F103-1 -> 0.12137115
A106: AI ÷ 營收 | B106: % | C106: =C98/C103 -> 0.31743109 | D106: =D98/D103 -> 0.54396585 | E106: =E98/E103 -> 0.69703869 | F106: =F98/F103 -> 0.73094555 | G106: =G98/G103 -> 0.74471103
A107: 毛利：網通＋非 AI＋軟體＋代購 HBM | B107: US$B | D107: =gm_net*D97+gm_nai*D100+gm_sw*D101+m_hbm*D91 -> 53.555684 | E107: =gm_net*E97+gm_nai*E100+gm_sw*E101+m_hbm*E91 -> 73.906519 | F107: =gm_net*F97+gm_nai*F100+gm_sw*F101+m_hbm*F91 -> 83.46562 | G107: =gm_net*G97+gm_nai*G100+gm_sw*G101+m_hbm*G91 -> 92.800776
A108: XPU 核心毛利率 m_core ＝（錨點毛利 − 其他毛利）÷ 核心營收（FY2026） | B108: x | D108: =(a26_gp-D107)/D92 -> 0.78755088 | H108: Derived：讓 FY2026 毛利率等於錨點；FY2027 起的毛利率變化來自營收組合（代購 HBM 隨 HBM 漲價與容量上升）
A109: 毛利 | B109: US$B | C109: =a25_gp -> 50.245 | D109: =a26_gp -> 79.572 | E109: =E107+$D$108*E92 -> 117.5724 | F109: =F107+$D$108*F92 -> 134.50366 | G109: =G107+$D$108*G92 -> 151.49453
A110: 毛利率 | B110: % | C110: =C109/C103 -> 0.78646673 | D110: =D109/D103 -> 0.75146616 | E110: =E109/E103 -> 0.67762206 | F110: =F109/F103 -> 0.64735182 | G110: =G109/G103 -> 0.65021026
A111: 代購 HBM ÷ 營收 | B111: % | D111: =D91/D103 -> 0.065781556 | E111: =E91/E103 -> 0.16057539 | F111: =F91/F103 -> 0.2034038 | G111: =G91/G103 -> 0.1981669
A112: 營業費用（基準路徑） | B112: US$B | C112: =a25_opx -> 8.248 | D112: =a26_opx -> 8.755 | E112: =D112*(1+MAX(g_opx_min,phi*E105)) -> 9.3140746 | F112: =E112*(1+MAX(g_opx_min,phi*F105)) -> 9.5934969 | G112: =F112*(1+MAX(g_opx_min,phi*G105)) -> 9.8813018
A113: 營業費用 | B113: US$B | C113: =C112 -> 8.248 | D113: =D112 -> 8.755 | E113: =E112+0*E103 -> 9.3140746 | F113: =F112+0*F103 -> 9.5934969 | G113: =G112+0*G103 -> 9.8813018
A114: 營業利益 | B114: US$B | C114: =C109-C113 -> 41.997 | D114: =D109-D113 -> 70.817 | E114: =E109-E113 -> 108.25833 | F114: =F109-F113 -> 124.91017 | G114: =G109-G113 -> 141.61322
A115: 營業利益率 | B115: % | C115: =C114/C103 -> 0.65736378 | D115: =D114/D103 -> 0.66878524 | E115: =E114/E103 -> 0.62394091 | F115: =F114/F103 -> 0.60117934 | G115: =G114/G103 -> 0.60779999
A116: 利息費用 | B116: US$B | C116: =a25_int -> 3.072 | D116: =a26_int -> 2.894 | E116: =int_f -> 2.8 | F116: =int_f -> 2.8 | G116: =int_f -> 2.8
A117: 其他收益 | B117: US$B | C117: =a25_oth -> 0.294 | D117: =a26_oth -> 0.434 | E117: =oth_f -> 0.4 | F117: =oth_f -> 0.4 | G117: =oth_f -> 0.4
A118: 有效稅率 | B118: % | C118: =a25_tax/(a25_oi-a25_int+a25_oth) -> 0.14000867 | D118: =a26_tax/(a26_oi-a26_int+a26_oth) -> 0.15999649 | E118: =tx_f -> 0.16 | F118: =tx_f -> 0.16 | G118: =tx_f -> 0.16
A119: 淨利（non-GAAP） | B119: US$B | C119: =a25_ni -> 33.728 | D119: =a26_ni -> 57.42012 | E119: =(E114-E116+E117)*(1-E118) -> 88.920994 | F119: =(F114-F116+F117)*(1-F118) -> 102.90854 | G119: =(G114-G116+G117)*(1-G118) -> 116.93911
A120: 稀釋股數 | B120: 十億股 | C120: =a25_sh -> 4.943 | D120: =a26_sh -> 4.9435 | E120: =D120*(1+sh_g) -> 4.9187825 | F120: =E120*(1+sh_g) -> 4.8941886 | G120: =F120*(1+sh_g) -> 4.8697176
A121: EPS（non-GAAP） | B121: US$ | C121: =C119/C120 -> 6.8233866 | D121: =D119/D120 -> 11.615277 | E121: =E119/E120 -> 18.077846 | F121: =F119/F120 -> 21.026681 | G121: =G119/G120 -> 24.01353
A122: EPS 年增 | B122: % | D122: =D121/C121-1 -> 0.70227444 | E122: =E121/D121-1 -> 0.55638534 | F122: =F121/E121-1 -> 0.16311867 | G122: =G121/F121-1 -> 0.14205043
A125: 情境 B：CY2028 顆數 ×0.8、CY2029 ×0.85
A126: 項目 | B126: 單位 | C126: FY2025A | D126: FY2026（錨點） | E126: FY2027 | F126: FY2028 | G126: FY2029 | H126: 說明
A127: A. XPU（由下而上；D 欄＝FY2026 校準年，E–G＝FY2027–FY2029；FY(t)＝CY(t)）
A128: Google TPU 市場顆數 | B128: 百萬顆 | D128: =u_tpu_26 -> 3.85 | E128: =u_tpu_27 -> 5.5 | F128: =u_tpu_28*um28_B -> 5.6 | G128: =u_tpu_28*(1+g29_tpu)*um29_B -> 6.8425
A129: 其他 ASIC（MTIA、Maia、Ascend 等） 市場顆數 | B129: 百萬顆 | D129: =u_oth_26 -> 1 | E129: =u_oth_27 -> 4.5 | F129: =u_oth_28*um28_B -> 4 | G129: =u_oth_28*(1+g29_oth)*um29_B -> 4.8875
A130: Broadcom 份額：Google TPU | B130: % | D130: =sh_tpu_26 -> 0.9 | E130: =MIN(1,MAX(0,sh_tpu_27+0)) -> 0.8 | F130: =MIN(1,MAX(0,sh_tpu_28+0)) -> 0.75 | G130: =MIN(1,MAX(0,sh_tpu_28+0)) -> 0.75
...

Sheet Val
A1: Val — P/E 估值（美元；non-GAAP EPS）。結論用「現價 ÷ FY2027、FY2028 EPS（模型與共識）」。十年 P/E 規則值本版不適用：GAAP 落後 P/E 受無形資產攤銷扭曲（2016 年為負、2018 年 6.5x、2024 年 137x），前瞻 P/E 歷史待 Bloomberg（10-27 抓取單）
A2: 循環位置：共用規則（tools/cycle_position.py classify；AVGO 的 FY(t) 對照日曆年 t，不平移），見頂年度讀設備市場模型；本版只記錄判定，倍數待前瞻 P/E 歷史
A4: 1. 價格與市場隱含倍數
A5: 項目 | B5: A | C5: B | D5: C | E5: 說明
A6: 現價（2026-10-22 收盤） | B6: =px -> 323.24
A7: 現價 ÷ FY2026 EPS（錨點） | B7: =px/PL!D14 -> 27.828868 | C7: =px/PL!D27 -> 27.828868 | D7: =px/PL!D40 -> 27.828868
A8: 現價 ÷ FY2027 EPS（模型） | B8: =px/PL!E14 -> 17.880448 | C8: =px/PL!E27 -> 17.880448 | D8: =px/PL!E40 -> 17.880448 | E8: FY2027 三情境相同（顆數係數從 CY2028 開始）
A9: 現價 ÷ FY2028 EPS（模型） | B9: =px/PL!F14 -> 15.37285 | C9: =px/PL!F27 -> 18.121185 | D9: =px/PL!F40 -> 21.810862
A10: 現價 ÷ FY2029 EPS（模型） | B10: =px/PL!G14 -> 13.460745 | C10: =px/PL!G27 -> 15.246875 | D10: =px/PL!G40 -> 19.204217
A11: 現價 ÷ 共識 FY2027 EPS | B11: =px/cons_eps27 -> 16.661856
A12: 近 12 月 non-GAAP P/E（Q4 FY25＋Q1–Q3 FY26 EPS） | B12: =px/(eps_q4_25+Q!C26+Q!D26+Q!E26) -> 33.118852 | E12: Andy 先驗 B9a 答「前瞻 35x」：接近近 12 月 non-GAAP 倍數，而非前瞻倍數（見 Recon D 節）
A13: 近 12 月 GAAP P/E（StockAnalysis） | B13: =pe_ttm_gaap -> 41.26
A14: 前瞻 P/E（StockAnalysis；口徑未說明） | B14: =pe_fwd_sa -> 18.61
A16: 2. 循環位置（共用規則，FY(t) 對照 CY t）——只記錄判定；倍數待前瞻 P/E 歷史
A17: 情境 | B17: 設備市場見頂年度（CY） | C17: FY2027 判定 | D17: FY2028 判定 | E17: FY2029 判定 | F17: 規則
A18: A | B18: =pk_A -> 2029 | C18: =IF(2027<pk_A,"中段",IF(2027=pk_A,"見頂","谷底")) -> 中段 | D18: =IF(2028<pk_A,"中段",IF(2028=pk_A,"見頂","谷底")) -> 中段 | E18: =IF(2029<pk_A,"中段",IF(2029=pk_A,"見頂","谷底")) -> 見頂 | F18: tools/cycle_position.py classify（不平移）
A19: B | B19: =pk_B -> 2028 | C19: =IF(2027<pk_B,"中段",IF(2027=pk_B,"見頂","谷底")) -> 中段 | D19: =IF(2028<pk_B,"中段",IF(2028=pk_B,"見頂","谷底")) -> 見頂 | E19: =IF(2029<pk_B,"中段",IF(2029=pk_B,"見頂","谷底")) -> 谷底 | F19: tools/cycle_position.py classify（不平移）
A20: C | B20: =pk_C -> 2027 | C20: =IF(2027<pk_C,"中段",IF(2027=pk_C,"見頂","谷底")) -> 見頂 | D20: =IF(2028<pk_C,"中段",IF(2028=pk_C,"見頂","谷底")) -> 谷底 | E20: =IF(2029<pk_C,"中段",IF(2029=pk_C,"見頂","谷底")) -> 谷底 | F20: tools/cycle_position.py classify（不平移）
A22: 3. What must be true：FY2027 年底價 ＝ 現價 ×（1＋報酬）所需的倍數（情境 A 的 FY2028 EPS；約 2027-10 的價格看下一年 EPS）
A23: FY2027 年底價 ÷ 現價 | B23: 所需倍數（÷ FY2028 EPS，A） | C23: 所需倍數（÷ FY2028 EPS，C） | D23: 對照：Andy 合理 P/E | E23: 對照：現價 ÷ 共識 FY2027 EPS
A24: 1 | B24: =px*A24/PL!F14 -> 15.37285 | C24: =px*A24/PL!F40 -> 21.810862 | D24: =pe_fair_andy -> 25 | E24: =px/cons_eps27 -> 16.661856
A25: 1.1 | B25: =px*A25/PL!F14 -> 16.910135 | C25: =px*A25/PL!F40 -> 23.991948 | D25: =pe_fair_andy -> 25 | E25: =px/cons_eps27 -> 16.661856
A26: 1.21 | B26: =px*A26/PL!F14 -> 18.601148 | C26: =px*A26/PL!F40 -> 26.391143 | D26: =pe_fair_andy -> 25 | E26: =px/cons_eps27 -> 16.661856
A27: 1.5 | B27: =px*A27/PL!F14 -> 23.059275 | C27: =px*A27/PL!F40 -> 32.716293 | D27: =pe_fair_andy -> 25 | E27: =px/cons_eps27 -> 16.661856
A28: 2 | B28: =px*A28/PL!F14 -> 30.745699 | C28: =px*A28/PL!F40 -> 43.621724 | D28: =pe_fair_andy -> 25 | E28: =px/cons_eps27 -> 16.661856
A29: 讀法：1.00＝價格不變、1.21＝一年約 21%。所需倍數愈低，現價愈便宜；倍數是否合理，待前瞻 P/E 十年歷史（Bloomberg）。
A31: 4. 對照：以 Andy 合理 P/E 25x 計算的隱含價（只作對照，非規則值）
A32: 情境 | B32: FY2027 EPS | C32: × 25x | D32: 相對現價 | E32: FY2028 EPS | F32: × 25x | G32: 相對現價
A33: A | B33: =PL!E14 -> 18.077846 | C33: =B33*pe_fair_andy -> 451.94616 | D33: =C33/px-1 -> 0.39817522 | E33: =PL!F14 -> 21.026681 | F33: =E33*pe_fair_andy -> 525.66701 | G33: =F33/px-1 -> 0.6262437
A34: B | B34: =PL!E27 -> 18.077846 | C34: =B34*pe_fair_andy -> 451.94616 | D34: =C34/px-1 -> 0.39817522 | E34: =PL!F27 -> 17.837686 | F34: =E34*pe_fair_andy -> 445.94214 | G34: =F34/px-1 -> 0.37960074
A35: C | B35: =PL!E40 -> 18.077846 | C35: =B35*pe_fair_andy -> 451.94616 | D35: =C35/px-1 -> 0.39817522 | E35: =PL!F40 -> 14.820139 | F35: =E35*pe_fair_andy -> 370.50347 | G35: =F35/px-1 -> 0.14621787
A37: 5. 十年 GAAP P/E（Macrotrends，10 月 31 日；不適用——GAAP EPS 受攤銷扭曲，只作紀錄）
A38: 年底 | B38: P/E（GAAP 落後） | C38: 說明
A39: 2016 | C39: GAAP EPS 為負，P/E 無意義
A40: 2017 | B40: 49.57
A41: 2018 | B41: 6.5
A42: 2019 | B42: 38.87
A43: 2020 | B43: 49.77
A44: 2021 | B44: 32.75
A45: 2022 | B45: 16.88
A46: 2023 | B46: 24.95
A47: 2024 | B47: 137.36
A48: 2025 | C48: 頁面資料只到 2025-08：未找到
A49: 來源：macrotrends.net/stocks/charts/AVGO/broadcom/pe-ratio（Interested-party，資料商）；第二來源：未找到。前瞻 P/E 歷史待 Bloomberg 抓取單（10-27）

Sheet Recon
A1: Recon — 本模型 vs 公司展望、共識、市場層。只作事後對照，不為對上數字而調參數。公司 FY2027、FY2028 AI 營收展望（115、230）為 Interested-party，不用於校準
A3: 項目 | B3: 對照值 | C3: 模型 A | D3: 差距 A | E3: 模型 B | F3: 差距 B | G3: 模型 C | H3: 差距 C | I3: 對照來源 | J3: 說明
A4: A. AI 營收 vs 公司展望（Interested-party；校準未使用）
A5: FY2026 AI 營收 vs 公司展望 58 | B5: =co_ai26 -> 58 | C5: =PL!D98 -> 57.6 | D5: =C5/B5-1 -> -0.0068965517 | E5: =PL!D153 -> 57.6 | F5: =E5/B5-1 -> -0.0068965517 | G5: =PL!D208 -> 57.6 | H5: =G5/B5-1 -> -0.0068965517 | I5: 公司（法說） | J5: FY2026 為錨點（Q1–Q3 實績＋Q4 指引 57.6）
A6: FY2027 AI 營收 vs 公司展望 115 | B6: =co_ai27 -> 115 | C6: =PL!E98 -> 120.94133 | D6: =C6/B6-1 -> 0.051663727 | E6: =PL!E153 -> 120.94133 | F6: =E6/B6-1 -> 0.051663727 | G6: =PL!E208 -> 120.94133 | H6: =G6/B6-1 -> 0.051663727 | I6: 公司（法說）
A7: FY2027 AI 營收 vs JPMorgan 150 | B7: =jpm_ai27 -> 150 | C7: =PL!E98 -> 120.94133 | D7: =C7/B7-1 -> -0.19372448 | E7: =PL!E153 -> 120.94133 | F7: =E7/B7-1 -> -0.19372448 | G7: =PL!E208 -> 120.94133 | H7: =G7/B7-1 -> -0.19372448 | I7: JPMorgan（KuCoin 轉述）
A8: FY2028 AI 營收 vs 公司展望 230 | B8: =co_ai28 -> 230 | C8: =PL!F98 -> 151.87237 | D8: =C8/B8-1 -> -0.33968535 | E8: =PL!F153 -> 110.74023 | F8: =E8/B8-1 -> -0.51852075 | G8: =PL!F208 -> 79.597349 | H8: =G8/B8-1 -> -0.65392457 | I8: 公司（法說） | J8: 差距主要在顆數：公司說法含 Anthropic 2028 年再加約 10 GW、OpenAI 5 GW 以上
A9: B. What must be true：要達到公司展望，Broadcom XPU 顆數需要是模型的幾倍（網通、核心售價、HBM 不變）
A10: FY2027：所需 XPU 顆數倍數 | C10: =(co_ai27-PL!E97)/PL!E90 -> 0.9286808 | E10: =(co_ai27-PL!E152)/PL!E145 -> 0.9286808 | G10: =(co_ai27-PL!E207)/PL!E200 -> 0.9286808 | I10: — | J10: 倍數 >1＝公司展望需要比市場層更多的 Broadcom 顆數
A11: FY2028：所需 XPU 顆數倍數 | C11: =(co_ai28-PL!F97)/PL!F90 -> 1.729699 | E11: =(co_ai28-PL!F152)/PL!F145 -> 2.5923178 | G11: =(co_ai28-PL!F207)/PL!F200 -> 3.8531334 | I11: —
A12: FY2028：所需 Broadcom XPU 顆數（百萬顆）vs 模型 | B12: =PL!F93 -> 8 | C12: =(co_ai28-PL!F97)/PL!F90*PL!F93 -> 13.837592 | E12: =(co_ai28-PL!F152)/PL!F145*PL!F148 -> 16.590834 | G12: =(co_ai28-PL!F207)/PL!F200*PL!F203 -> 18.49504 | I12: — | J12: 對照值＝模型 A 的 Broadcom XPU 顆數
A13: C. 共識（校準未使用）
A14: FY2026 營收 vs 共識 | B14: =cons_rev26 -> 105.98 | C14: =PL!D103 -> 105.889 | D14: =C14/B14-1 -> -0.00085865258 | E14: =PL!D158 -> 105.889 | F14: =E14/B14-1 -> -0.00085865258 | G14: =PL!D213 -> 105.889 | H14: =G14/B14-1 -> -0.00085865258 | I14: StockAnalysis | J14: 錨點
A15: FY2026 EPS vs 共識 | B15: =cons_eps26 -> 11.66 | C15: =PL!D121 -> 11.615277 | D15: =C15/B15-1 -> -0.0038356239 | E15: =PL!D176 -> 11.615277 | F15: =E15/B15-1 -> -0.0038356239 | G15: =PL!D231 -> 11.615277 | H15: =G15/B15-1 -> -0.0038356239 | I15: StockAnalysis | J15: 錨點（Q4 依指引與 In 頁假設）
A16: FY2027 營收 vs 共識 | B16: =cons_rev27 -> 173.97 | C16: =PL!E103 -> 173.50734 | D16: =C16/B16-1 -> -0.0026594318 | E16: =PL!E158 -> 173.50734 | F16: =E16/B16-1 -> -0.0026594318 | G16: =PL!E213 -> 173.50734 | H16: =G16/B16-1 -> -0.0026594318 | I16: StockAnalysis
A17: FY2027 EPS vs 共識 | B17: =cons_eps27 -> 19.4 | C17: =PL!E121 -> 18.077846 | D17: =C17/B17-1 -> -0.068152252 | E17: =PL!E176 -> 18.077846 | F17: =E17/B17-1 -> -0.068152252 | G17: =PL!E231 -> 18.077846 | H17: =G17/B17-1 -> -0.068152252 | I17: StockAnalysis
A18: FY2027 共識隱含 AI 營收（共識營收 − 模型非 AI − 模型軟體） | C18: =cons_rev27-PL!E100-PL!E101 -> 121.40399 | E18: =cons_rev27-PL!E155-PL!E156 -> 121.40399 | G18: =cons_rev27-PL!E210-PL!E211 -> 121.40399 | I18: 推導 | J18: 與公司展望 115 比較
A19: D. 份額與顆數（先驗比對的機制檢查）
A20: 2027 年 ASIC 金額份額（模組層級）vs 先驗比對推導 14–19% 中點 | B20: 0.165 | C20: =Units!D59 -> 0.22381744 | D20: =C20-B20 -> 0.058817437 | E20: =Units!D97 -> 0.22381744 | F20: =E20-B20 -> 0.058817437 | G20: =Units!D135 -> 0.22381744 | H20: =G20-B20 -> 0.058817437 | I20: 先驗比對_AVGO（Drive）
A21: 2027 年 ASIC 顆數份額 vs JPMorgan 53.6% | B21: =jpm_u27 -> 0.536 | C21: =Units!D60 -> 0.52742616 | D21: =C21-B21 -> -0.0085738397 | E21: =Units!D98 -> 0.52742616 | F21: =E21-B21 -> -0.0085738397 | G21: =Units!D136 -> 0.52742616 | H21: =G21-B21 -> -0.0085738397 | I21: JPMorgan（二手）；市場層同一來源 | J21: 非獨立檢驗（市場層顆數即取自 JPMorgan）
A22: 2027 年 Broadcom ÷ ASIC 顆數 vs Counterpoint 60% | B22: =cp_sh27 -> 0.6 | C22: =Units!D62 -> 0.55 | D22: =C22-B22 -> -0.05 | E22: =Units!D100 -> 0.55 | F22: =E22-B22 -> -0.05 | G22: =Units!D138 -> 0.55 | H22: =G22-B22 -> -0.05 | I22: Counterpoint（二手；口徑未說明）
A23: 2027 年 Broadcom ÷ ASIC 金額 vs Counterpoint 60% | B23: =cp_sh27 -> 0.6 | C23: =Units!D61 -> 0.61450056 | D23: =C23-B23 -> 0.014500558 | E23: =Units!D99 -> 0.61450056 | F23: =E23-B23 -> 0.014500558 | G23: =Units!D137 -> 0.61450056 | H23: =G23-B23 -> 0.014500558 | I23: 同上 | J23: JPMorgan：高階 ASIC 80–85%
A24: 2027 年 NVIDIA 金額份額 | C24: =Units!D54 -> 0.7126143 | E24: =Units!D92 -> 0.7126143 | G24: =Units!D130 -> 0.7126143 | I24: accel_share | J24: NVIDIA 模型同一套價格
A25: 每顆價差：NVIDIA Rubin 模組 ÷ TPU 總價（CY2027） | C25: =pm_rb/Units!D10 -> 3.5639391 | E25: =pm_rb/Units!D10 -> 3.5639391 | G25: =pm_rb/Units!D10 -> 3.5639391 | I25: — | J25: 顆數份額約為金額份額數倍的原因
A26: 近 12 月 non-GAAP P/E vs Andy 先驗「前瞻 35x」 | B26: 35 | C26: =Val!B12 -> 33.118852 | D26: =C26/B26-1 -> -0.053747073 | E26: =Val!B12 -> 33.118852 | F26: =E26/B26-1 -> -0.053747073 | G26: =Val!B12 -> 33.118852 | H26: =G26/B26-1 -> -0.053747073 | I26: 先驗_Andy_AVGO B9a（Drive） | J26: 35x 接近近 12 月倍數；前瞻（FY2027 EPS）倍數見 Val 頁
A27: E. 校準與網通
A28: k_x（XPU 校準係數） | C28: =PL!D89 -> 1.1077953 | E28: =PL!D144 -> 1.1077953 | G28: =PL!D199 -> 1.1077953 | I28: FY2026 錨點 ÷ 未校準 | J28: 接近 1＝市場層顆數 × 份額 × 假設單價與實績一致
A29: k_n（網通校準係數） | C29: =PL!D96 -> 1.3959864 | E29: =PL!D151 -> 1.3959864 | G29: =PL!D206 -> 1.3959864 | I29: rep_avgo26 ÷ markets/network 歸屬 | J29: markets/network 的 Broadcom 歸屬比例偏低（Assumed）
A30: m_core（XPU 核心毛利率，Derived） | C30: =PL!D108 -> 0.78755088 | E30: =PL!D163 -> 0.78755088 | G30: =PL!D218 -> 0.78755088 | I30: FY2026 毛利殘差 | J30: 高＝設計與邏輯晶片加價高；代購 HBM 稀釋整體
A31: FY2027 毛利率 vs FY2026（百分點） | B31: =a26_gp/a26_rev -> 0.75146616 | C31: =PL!E110 -> 0.67762206 | D31: =C31-B31 -> -0.073844094 | E31: =PL!E165 -> 0.67762206 | F31: =E31-B31 -> -0.073844094 | G31: =PL!E220 -> 0.67762206 | H31: =G31-B31 -> -0.073844094 | I31: 錨點 | J31: 公司 Q4 FY26 指引約 73%，續降
A32: FY2027 毛利率 vs 共識隱含（約 72%：EPS 19.40 × 股數 ÷（1−稅）＋利息＋營業費用，÷ 共識營收） | B32: =(cons_eps27*a26_sh/(1-tx_f)+int_f-oth_f+PL!E113)/cons_rev27 -> 0.72360398 | C32: =PL!E110 -> 0.67762206 | D32: =C32-B32 -> -0.045981915 | E32: =PL!E165 -> 0.67762206 | F32: =E32-B32 -> -0.045981915 | G32: =PL!E220 -> 0.67762206 | H32: =G32-B32 -> -0.045981915 | I32: 推導（共識無毛利率）
A33: F. 客戶融資曝險（資訊；不進基準 EPS）
A34: Anthropic 放款＋OpenAI 融資安排（標題值）vs FY2027 AI 營收（模型） | B34: =fin_anth+fin_oai -> 92 | C34: =PL!E98 -> 120.94133 | E34: =PL!E153 -> 120.94133 | G34: =PL!E208 -> 120.94133 | I34: top1markets 引 Reuters、WSJ、Bloomberg | J34: 媒體：約 92B ≈ 公司 FY2027 AI 目標的 80%；非資產負債表曝險，部分在銀行團；另有一家客戶機架租賃擔保約 29B（季報），可能與上列重疊，不加總
A35: 兩家合計 ÷ FY2027 AI 營收（模型） | C35: =(fin_anth+fin_oai)/PL!E98 -> 0.76069943 | E35: =(fin_anth+fin_oai)/PL!E153 -> 0.76069943 | G35: =(fin_anth+fin_oai)/PL!E208 -> 0.76069943 | I35: —
A36: 兩家合計 ÷ FY2027 淨利（模型） | C36: =(fin_anth+fin_oai)/PL!E119 -> 1.0346263 | E36: =(fin_anth+fin_oai)/PL!E174 -> 1.0346263 | G36: =(fin_anth+fin_oai)/PL!E229 -> 1.0346263 | I36: — | J36: 若全數損失的量級（不含回收與銀行團分擔）
A37: G. 預留
A38: R4 產業部署路徑（markets/deploy_path/，尚未建立）：上線後以 Broadcom AI 營收 ÷ 部署 GW 對照 Tokenomics IF_NonNV_Hold_TPU 等比例 | J38: 預留列：本版無數值

Sheet Sens
A1: Sens — 一次動一個輸入（情境 A；k_x、k_n、m_core 在每個案例內依 FY2026 實績重算，FY2026 恆等於錨點）：對 FY2027、FY2028 的營收、AI 營收、毛利率與 EPS 的影響。每個案例是一個完整推導區塊（本頁下方）
A3: 案例 | B3: 設定 | C3: FY2027 營收 | D3: FY2027 AI 營收 | E3: FY2027 毛利率 | F3: FY2027 EPS | G3: FY2027 EPS 相對基準 | H3: FY2028 營收 | I3: FY2028 AI 營收 | J3: FY2028 毛利率 | K3: FY2028 EPS | L3: FY2028 EPS 相對基準
A4: 基準（情境 A） | B4: PL 區塊 A | C4: =PL!E103 -> 173.50734 | D4: =PL!E98 -> 120.94133 | E4: =PL!E110 -> 0.67762206 | F4: =PL!E121 -> 18.077846 | G4: =F4/F$4-1 -> 0 | H4: =PL!F103 -> 207.77522 | I4: =PL!F98 -> 151.87237 | J4: =PL!F110 -> 0.64735182 | K4: =PL!F121 -> 21.026681 | L4: =K4/K$4-1 -> 0
A5: XPU 顆數係數 ×0.9 | B5: FY2027 起 Broadcom XPU 顆數 ×0.9 | C5: =E73 -> 165.17672 | D5: =E68 -> 112.61071 | E5: =E80 -> 0.68367504 | F5: =E91 -> 17.29633 | G5: =F5/F$4-1 -> -0.04323061 | H5: =F73 -> 197.06839 | I5: =F68 -> 141.16554 | J5: =F80 -> 0.65447959 | K5: =F91 -> 20.090345 | L5: =K5/K$4-1 -> -0.044530854
A6: XPU 顆數係數 ×1.1 | B6: ×1.1 | C6: =E128 -> 181.83796 | D6: =E123 -> 129.27195 | E6: =E135 -> 0.6721237 | F6: =E146 -> 18.859363 | G6: =F6/F$4-1 -> 0.04323061 | H6: =F128 -> 218.48204 | I6: =F123 -> 162.5792 | J6: =F135 -> 0.64092265 | K6: =F146 -> 21.963017 | L6: =K6/K$4-1 -> 0.044530854
A7: TPU 份額 −15pt | B7: FY2027 起 Broadcom 占 TPU 顆數 −15 個百分點（MediaTek 版放量） | C7: =E183 -> 162.59317 | D7: =E178 -> 110.02716 | E7: =E190 -> 0.68547768 | F7: =E201 -> 17.048392 | G7: =F7/F$4-1 -> -0.056945644 | H7: =F183 -> 192.65927 | I7: =F178 -> 136.75643 | J7: =F190 -> 0.6570879 | K7: =F201 -> 19.685094 | L7: =K7/K$4-1 -> -0.063804005
A8: TPU 份額 +10pt | B8: +10 個百分點（上限 100%） | C8: =E238 -> 180.78345 | D8: =E233 -> 128.21744 | E8: =E245 -> 0.67291194 | F8: =E256 -> 18.764149 | G8: =F8/F$4-1 -> 0.037963763 | H8: =F238 -> 217.85251 | I8: =F233 -> 161.94966 | J8: =F245 -> 0.64161171 | K8: =F256 -> 21.921072 | L8: =K8/K$4-1 -> 0.042536003
A9: 其他 ASIC 份額 −15pt | B9: FY2027 起 −15 個百分點 | C9: =E293 -> 166.66263 | D9: =E288 -> 114.09662 | E9: =E300 -> 0.68283566 | F9: =E311 -> 17.443827 | G9: =F9/F$4-1 -> -0.035071634 | H9: =F293 -> 199.18742 | I9: =F288 -> 143.28457 | J9: =F300 -> 0.65374304 | K9: =F311 -> 20.301023 | L9: =K9/K$4-1 -> -0.034511295
A10: 其他 ASIC 份額 +15pt | B10: +15 個百分點 | C10: =E348 -> 180.35205 | D10: =E343 -> 127.78604 | E10: =E355 -> 0.6728042 | F10: =E366 -> 18.711866 | G10: =F10/F$4-1 -> 0.035071634 | H10: =F348 -> 216.36301 | I10: =F343 -> 160.46016 | J10: =F355 -> 0.64146796 | K10: =F366 -> 21.752339 | L10: =K10/K$4-1 -> 0.034511295
A11: 核心售價 ×0.8 | B11: FY2027 起 XPU 核心售價 ×0.8 | C11: =E403 -> 162.41831 | D11: =E398 -> 109.8523 | E11: =E410 -> 0.67011673 | F11: =E421 -> 16.602105 | G11: =F11/F$4-1 -> -0.081632608 | H11: =F403 -> 194.81401 | I11: =F398 -> 138.91116 | J11: =F410 -> 0.63802421 | K11: =F421 -> 19.290935 | L11: =K11/K$4-1 -> -0.082549664
A12: 核心售價 ×1.2 | B12: ×1.2 | C12: =E458 -> 184.59637 | D12: =E453 -> 132.03036 | E12: =E465 -> 0.68422568 | F12: =E476 -> 19.553588 | G12: =F12/F$4-1 -> 0.081632608 | H12: =F458 -> 220.73642 | I12: =F453 -> 164.83357 | J12: =F465 -> 0.65558403 | K12: =F476 -> 22.762426 | L12: =K12/K$4-1 -> 0.082549664
A13: HBM 代購比例 0.3 | B13: 代購 30%（k_x、m_core 重算） | C13: =E513 -> 166.19343 | D13: =E508 -> 113.62742 | E13: =E520 -> 0.70304231 | F13: =E531 -> 17.963271 | G13: =F13/F$4-1 -> -0.006337897 | H13: =F513 -> 194.8402 | I13: =F508 -> 138.93735 | J13: =F520 -> 0.68368931 | K13: =F531 -> 20.815364 | L13: =K13/K$4-1 -> -0.010049903
A14: HBM 代購比例 1.0 | B14: 全部代購 | C14: =E568 -> 181.48409 | D14: =E563 -> 128.91808 | E14: =E575 -> 0.65223389 | F14: =E586 -> 18.202806 | G14: =F14/F$4-1 -> 0.0069122842 | H14: =F568 -> 221.8825 | I14: =F563 -> 165.97965 | J14: =F575 -> 0.61255121 | K14: =F586 -> 21.257148 | L14: =K14/K$4-1 -> 0.0109607
A15: 代購 HBM 毛利率 0% | B15: 零加成 | C15: =E623 -> 173.50734 | D15: =E618 -> 120.94133 | E15: =E630 -> 0.66830257 | F15: =E641 -> 17.801705 | G15: =F15/F$4-1 -> -0.015275146 | H15: =F623 -> 207.77522 | I15: =F618 -> 151.87237 | J15: =F630 -> 0.63358816 | K15: =F641 -> 20.535856 | L15: =K15/K$4-1 -> -0.023342936
A16: 代購 HBM 毛利率 20% | B16: 20% | C16: =E678 -> 173.50734 | D16: =E673 -> 120.94133 | E16: =E685 -> 0.68694156 | F16: =E696 -> 18.353988 | G16: =F16/F$4-1 -> 0.015275146 | H16: =F678 -> 207.77522 | I16: =F673 -> 151.87237 | J16: =F685 -> 0.66111548 | K16: =F696 -> 21.517505 | L16: =K16/K$4-1 -> 0.023342936
A17: AI 網通 ×0.8 | B17: FY2027 起網通 ×0.8 | C17: =E733 -> 165.98031 | D17: =E728 -> 113.4143 | E17: =E740 -> 0.67570027 | F17: =E751 -> 17.162971 | G17: =F17/F$4-1 -> -0.050607539 | H17: =F733 -> 198.8144 | I17: =F728 -> 142.91155 | J17: =F740 -> 0.64407747 | K17: =F751 -> 19.930349 | L17: =K17/K$4-1 -> -0.052140045
A18: AI 網通 ×1.2 | B18: ×1.2 | C18: =E788 -> 181.03437 | D18: =E783 -> 128.46836 | E18: =E795 -> 0.67938405 | F18: =E806 -> 18.992722 | G18: =F18/F$4-1 -> 0.050607539 | H18: =F788 -> 216.73603 | I18: =F783 -> 160.83318 | J18: =F795 -> 0.65035541 | K18: =F806 -> 22.123013 | L18: =K18/K$4-1 -> 0.052140045
A19: 軟體成長 低 | B19: FY2027 +8%、之後 +4% | C19: =E843 -> 172.2503 | D19: =E838 -> 120.94133 | E19: =E850 -> 0.67578027 | F19: =E861 -> 17.879978 | G19: =F19/F$4-1 -> -0.010945326 | H19: =F843 -> 205.06001 | I19: =F838 -> 151.87237 | J19: =F850 -> 0.64360926 | K19: =F861 -> 20.595122 | L19: =K19/K$4-1 -> -0.020524312
A20: 軟體成長 高 | B20: FY2027 +18%、之後 +12% | C20: =E898 -> 175.3929 | D20: =E893 -> 120.94133 | E20: =E905 -> 0.68033525 | F20: =E916 -> 18.374648 | G20: =F20/F$4-1 -> 0.016417989 | H20: =F898 -> 211.29493 | I20: =F893 -> 151.87237 | J20: =F905 -> 0.65206012 | K20: =F916 -> 21.585734 | L20: =K20/K$4-1 -> 0.026587789
A21: 營業費用率 +2pt | B21: 營業費用額外 +2% × 營收 | C21: =E953 -> 173.50734 | D21: =E948 -> 120.94133 | E21: =E960 -> 0.67762206 | F21: =E971 -> 17.485236 | G21: =F21/F$4-1 -> -0.032781047 | H21: =F953 -> 207.77522 | I21: =F948 -> 151.87237 | J21: =F960 -> 0.64735182 | K21: =F971 -> 20.313463 | L21: =K21/K$4-1 -> -0.033919669
A22: 顆數情境 B | B22: CY2028 ×0.8、CY2029 ×0.85；記憶體 B 路徑 | C22: =PL!E158 -> 173.50734 | D22: =PL!E153 -> 120.94133 | E22: =PL!E165 -> 0.67762206 | F22: =PL!E176 -> 18.077846 | G22: =F22/F$4-1 -> 0 | H22: =PL!F158 -> 166.64307 | I22: =PL!F153 -> 110.74023 | J22: =PL!F165 -> 0.69563801 | K22: =PL!F176 -> 17.837686 | L22: =K22/K$4-1 -> -0.15166421
A23: 顆數情境 C | B23: CY2028–29 ×0.6；記憶體 C 路徑 | C23: =PL!E213 -> 173.50734 | D23: =PL!E208 -> 120.94133 | E23: =PL!E220 -> 0.67762206 | F23: =PL!E231 -> 18.077846 | G23: =F23/F$4-1 -> 0 | H23: =PL!F213 -> 135.50019 | I23: =PL!F208 -> 79.597349 | J23: =PL!F220 -> 0.72576851 | K23: =PL!F231 -> 14.820139 | L23: =K23/K$4-1 -> -0.2951746
A25: 讀法：FY2027 三情境相同；顆數情境 B、C 的差異從 FY2028 起。k_x 隨案例重算，所以 HBM 代購比例只改變營收組合與毛利率，不改 FY2026 水準。
A40: 案例區塊：XPU 顆數係數 ×0.9（情境 A）
A41: 項目 | B41: 單位 | C41: FY2025A | D41: FY2026（錨點） | E41: FY2027 | F41: FY2028 | G41: FY2029 | H41: 說明
A42: A. XPU（由下而上；D 欄＝FY2026 校準年，E–G＝FY2027–FY2029；FY(t)＝CY(t)）
A43: Google TPU 市場顆數 | B43: 百萬顆 | D43: =u_tpu_26 -> 3.85 | E43: =u_tpu_27 -> 5.5 | F43: =u_tpu_28*um28_A -> 7 | G43: =u_tpu_28*(1+g29_tpu)*um29_A -> 8.05
A44: 其他 ASIC（MTIA、Maia、Ascend 等） 市場顆數 | B44: 百萬顆 | D44: =u_oth_26 -> 1 | E44: =u_oth_27 -> 4.5 | F44: =u_oth_28*um28_A -> 5 | G44: =u_oth_28*(1+g29_oth)*um29_A -> 5.75
A45: Broadcom 份額：Google TPU | B45: % | D45: =sh_tpu_26 -> 0.9 | E45: =MIN(1,MAX(0,sh_tpu_27+0)) -> 0.8 | F45: =MIN(1,MAX(0,sh_tpu_28+0)) -> 0.75 | G45: =MIN(1,MAX(0,sh_tpu_28+0)) -> 0.75
A46: Broadcom 份額：其他 ASIC（MTIA、Maia、Ascend 等） | B46: % | D46: =sh_oth_26 -> 0.35 | E46: =MIN(1,MAX(0,sh_oth_27+0)) -> 0.55 | F46: =MIN(1,MAX(0,sh_oth_28+0)) -> 0.55 | G46: =MIN(1,MAX(0,sh_oth_28+0)) -> 0.55
A47: Broadcom 顆數：Google TPU | B47: 百萬顆 | D47: =D43*D45 -> 3.465 | E47: =E43*E45*uk_lo -> 3.96 | F47: =F43*F45*uk_lo -> 4.725 | G47: =G43*G45*uk_lo -> 5.43375
A48: Broadcom 顆數：其他 ASIC（MTIA、Maia、Ascend 等） | B48: 百萬顆 | D48: =D44*D46 -> 0.35 | E48: =E44*E46*uk_lo -> 2.2275 | F48: =F44*F46*uk_lo -> 2.475 | G48: =G44*G46*uk_lo -> 2.84625
A49: 每顆 HBM：Google TPU | B49: GB | D49: =gb_tpu_26 -> 192 | E49: =gb_tpu_27 -> 250 | F49: =gb_tpu_28 -> 288 | G49: =gb_tpu_28 -> 288
A50: 每顆 HBM：其他 ASIC（MTIA、Maia、Ascend 等） | B50: GB | D50: =gb_oth_26 -> 150 | E50: =gb_oth_27 -> 200 | F50: =gb_oth_28 -> 250 | G50: =gb_oth_28 -> 250
A51: HBM 單價 | B51: US$/GB | D51: =hbm_A_26 -> 14.6 | E51: =hbm_A_27 -> 26.28 | F51: =hbm_A_28 -> 28.908 | G51: =hbm_A_29 -> 27.4626
A52: 每顆核心售價：Google TPU | B52: US$K | D52: =core_tpu -> 8 | E52: =core_tpu*1 -> 8 | F52: =core_tpu*1 -> 8 | G52: =core_tpu*1 -> 8
A53: 每顆核心售價：其他 ASIC（MTIA、Maia、Ascend 等） | B53: US$K | D53: =core_oth -> 6 | E53: =core_oth*1 -> 6 | F53: =core_oth*1 -> 6 | G53: =core_oth*1 -> 6
A54: 每顆 HBM 金額（全部）：Google TPU | B54: US$K | D54: =D49*D51/1000 -> 2.8032 | E54: =E49*E51/1000 -> 6.57 | F54: =F49*F51/1000 -> 8.325504 | G54: =G49*G51/1000 -> 7.9092288
A55: 每顆 HBM 金額（全部）：其他 ASIC（MTIA、Maia、Ascend 等） | B55: US$K | D55: =D50*D51/1000 -> 2.19 | E55: =E50*E51/1000 -> 5.256 | F55: =F50*F51/1000 -> 7.227 | G55: =G50*G51/1000 -> 6.86565
A56: 每顆 Broadcom 售價（核心＋代購 HBM）：Google TPU | B56: US$K | D56: =D52+f_hbm*D54 -> 9.68192 | E56: =E52+f_hbm*E54 -> 11.942 | F56: =F52+f_hbm*F54 -> 12.995302 | G56: =G52+f_hbm*G54 -> 12.745537 | H56: 核心售價 ＋ 代購比例 × HBM 金額（未乘 k_x）
A57: 每顆 Broadcom 售價（核心＋代購 HBM）：其他 ASIC（MTIA、Maia、Ascend 等） | B57: US$K | D57: =D53+f_hbm*D55 -> 7.314 | E57: =E53+f_hbm*E55 -> 9.1536 | F57: =F53+f_hbm*F55 -> 10.3362 | G57: =G53+f_hbm*G55 -> 10.11939
A58: XPU 營收（未校準） | B58: US$B | D58: =D47*D56+D48*D57 -> 36.107753 | E58: =E47*E56+E48*E57 -> 67.679964 | F58: =F47*F56+F48*F57 -> 86.984899 | G58: =G47*G56+G48*G57 -> 98.058377
A59: XPU 校準係數 k_x ＝ FY2026 錨點 XPU ÷ 未校準 | B59: x | D59: =a26_xpu/D58 -> 1.1077953 | H59: Derived：以已發生的實績（Q1–Q3＋Q4 指引）校準；FY2027 起沿用。顆數層、份額與核心單價無法分開識別，k_x 是合併係數
A60: XPU 營收 | B60: US$B | D60: =D58*$D$59 -> 40 | E60: =E58*$D$59 -> 74.975548 | F60: =F58*$D$59 -> 96.361465 | G60: =G58*$D$59 -> 108.62861
A61: 其中代購 HBM | B61: US$B | D61: =$D$59*f_hbm*(D47*D54+D48*D55) -> 6.9655432 | E61: =$D$59*f_hbm*(E47*E54+E48*E55) -> 25.074907 | F61: =$D$59*f_hbm*(F47*F54+F48*F55) -> 38.036041 | G61: =$D$59*f_hbm*(G47*G54+G48*G55) -> 41.554374
A62: 其中核心（設計＋邏輯晶片＋封裝） | B62: US$B | D62: =D60-D61 -> 33.034457 | E62: =E60-E61 -> 49.900641 | F62: =F60-F61 -> 58.325424 | G62: =G60-G61 -> 67.074238
A63: Broadcom XPU 顆數（未乘 k_x） | B63: 百萬顆 | D63: =D47+D48 -> 3.815 | E63: =E47+E48 -> 6.1875 | F63: =F47+F48 -> 7.2 | G63: =G47+G48 -> 8.28
A64: B. AI 網通、非 AI 半導體、軟體
A65: AI 網通（markets/network 歸屬 × 情境顆數係數） | B65: US$B | D65: =net_26*1 -> 12.607573 | E65: =net_27*1*1 -> 26.959549 | F65: =net_28*um28_A*1 -> 32.094922 | G65: =net_29*um29_A*1 -> 37.832817
A66: 網通校準係數 k_n ＝ 實際推估 ÷ 歸屬（FY2026） | B66: x | D66: =a26_net/D65 -> 1.3959864 | H66: Derived：markets/network 的 Broadcom 歸屬比例為 Assumed，2026 較實際推估低；FY2027 起沿用
A67: AI 網通營收 | B67: US$B | D67: =D65*$D$66 -> 17.6 | E67: =E65*$D$66 -> 37.635164 | F67: =F65*$D$66 -> 44.804075 | G67: =G65*$D$66 -> 52.814098
A68: AI 半導體營收 | B68: US$B | C68: =a25_ai -> 20.27972 | D68: =D60+D67 -> 57.6 | E68: =E60+E67 -> 112.61071 | F68: =F60+F67 -> 141.16554 | G68: =G60+G67 -> 161.44271
A69: XPU ÷ AI | B69: % | D69: =D60/D68 -> 0.69444444 | E69: =E60/E68 -> 0.6657941 | F69: =F60/F68 -> 0.68261323 | G69: =G60/G68 -> 0.67286167
A70: 非 AI 半導體 | B70: US$B | C70: =a25_nai -> 16.57828 | D70: =a26_nai -> 16.863 | E70: =D70*(1+g_nai) -> 17.36889 | F70: =E70*(1+g_nai) -> 17.889957 | G70: =F70*(1+g_nai) -> 18.426655
A71: 基礎架構軟體 | B71: US$B | C71: =a25_sw -> 27.029 | D71: =a26_sw -> 31.426 | E71: =D71*(1+g_sw27) -> 35.19712 | F71: =E71*(1+g_sw) -> 38.01289 | G71: =F71*(1+g_sw) -> 41.053921
A72: C. 報告值（FY2025A、FY2026 為實績與錨點；FY2027 起為由下而上）
A73: 營收 | B73: US$B | C73: =a25_rev -> 63.887 | D73: =a26_rev -> 105.889 | E73: =E68+E70+E71 -> 165.17672 | F73: =F68+F70+F71 -> 197.06839 | G73: =G68+G70+G71 -> 220.92329
A74: 由下而上營收（FY2026 應等於錨點） | B74: US$B | D74: =D68+D70+D71 -> 105.889 | E74: =E68+E70+E71 -> 165.17672 | F74: =F68+F70+F71 -> 197.06839 | G74: =G68+G70+G71 -> 220.92329
A75: 營收年增 | B75: % | D75: =D73/C73-1 -> 0.65744205 | E75: =E73/D73-1 -> 0.55990445 | F75: =F73/E73-1 -> 0.19307602 | G75: =G73/F73-1 -> 0.12104885
A76: AI ÷ 營收 | B76: % | C76: =C68/C73 -> 0.31743109 | D76: =D68/D73 -> 0.54396585 | E76: =E68/E73 -> 0.68175897 | F76: =F68/F73 -> 0.71632768 | G76: =G68/G73 -> 0.73076366
A77: 毛利：網通＋非 AI＋軟體＋代購 HBM | B77: US$B | D77: =gm_net*D67+gm_nai*D70+gm_sw*D71+m_hbm*D61 -> 53.555684 | E77: =gm_net*E67+gm_nai*E70+gm_sw*E71+m_hbm*E61 -> 73.627909 | F77: =gm_net*F67+gm_nai*F70+gm_sw*F71+m_hbm*F61 -> 83.042997 | G77: =gm_net*G67+gm_nai*G70+gm_sw*G71+m_hbm*G61 -> 92.33906
A78: XPU 核心毛利率 m_core ＝（錨點毛利 − 其他毛利）÷ 核心營收（FY2026） | B78: x | D78: =(a26_gp-D77)/D62 -> 0.78755088 | H78: Derived：讓 FY2026 毛利率等於錨點；FY2027 起的毛利率變化來自營收組合（代購 HBM 隨 HBM 漲價與容量上升）
A79: 毛利 | B79: US$B | C79: =a25_gp -> 50.245 | D79: =a26_gp -> 79.572 | E79: =E77+$D$78*E62 -> 112.9272 | F79: =F77+$D$78*F62 -> 128.97724 | G79: =G77+$D$78*G62 -> 145.16344
A80: 毛利率 | B80: % | C80: =C79/C73 -> 0.78646673 | D80: =D79/D73 -> 0.75146616 | E80: =E79/E73 -> 0.68367504 | F80: =F79/F73 -> 0.65447959 | G80: =G79/G73 -> 0.65707621
A81: 代購 HBM ÷ 營收 | B81: % | D81: =D61/D73 -> 0.065781556 | E81: =E61/E73 -> 0.15180654 | F81: =F61/F73 -> 0.19300935 | G81: =G61/G73 -> 0.18809413
A82: 營業費用（基準路徑） | B82: US$B | C82: =a25_opx -> 8.248 | D82: =a26_opx -> 8.755 | E82: =D82*(1+MAX(g_opx_min,phi*E75)) -> 9.2451963 | F82: =E82*(1+MAX(g_opx_min,phi*F75)) -> 9.5225522 | G82: =F82*(1+MAX(g_opx_min,phi*G75)) -> 9.8082288
A83: 營業費用 | B83: US$B | C83: =C82 -> 8.248 | D83: =D82 -> 8.755 | E83: =E82+0*E73 -> 9.2451963 | F83: =F82+0*F73 -> 9.5225522 | G83: =G82+0*G73 -> 9.8082288
A84: 營業利益 | B84: US$B | C84: =C79-C83 -> 41.997 | D84: =D79-D83 -> 70.817 | E84: =E79-E83 -> 103.68201 | F84: =F79-F83 -> 119.45468 | G84: =G79-G83 -> 135.35521
A85: 營業利益率 | B85: % | C85: =C84/C73 -> 0.65736378 | D85: =D84/D73 -> 0.66878524 | E85: =E84/E73 -> 0.6277035 | F85: =F84/F73 -> 0.60615854 | G85: =G84/G73 -> 0.61267967
A86: 利息費用 | B86: US$B | C86: =a25_int -> 3.072 | D86: =a26_int -> 2.894 | E86: =int_f -> 2.8 | F86: =int_f -> 2.8 | G86: =int_f -> 2.8
A87: 其他收益 | B87: US$B | C87: =a25_oth -> 0.294 | D87: =a26_oth -> 0.434 | E87: =oth_f -> 0.4 | F87: =oth_f -> 0.4 | G87: =oth_f -> 0.4
A88: 有效稅率 | B88: % | C88: =a25_tax/(a25_oi-a25_int+a25_oth) -> 0.14000867 | D88: =a26_tax/(a26_oi-a26_int+a26_oth) -> 0.15999649 | E88: =tx_f -> 0.16 | F88: =tx_f -> 0.16 | G88: =tx_f -> 0.16
A89: 淨利（non-GAAP） | B89: US$B | C89: =a25_ni -> 33.728 | D89: =a26_ni -> 57.42012 | E89: =(E84-E86+E87)*(1-E88) -> 85.076885 | F89: =(F84-F86+F87)*(1-F88) -> 98.325935 | G89: =(G84-G86+G87)*(1-G88) -> 111.68237
A90: 稀釋股數 | B90: 十億股 | C90: =a25_sh -> 4.943 | D90: =a26_sh -> 4.9435 | E90: =D90*(1+sh_g) -> 4.9187825 | F90: =E90*(1+sh_g) -> 4.8941886 | G90: =F90*(1+sh_g) -> 4.8697176
A91: EPS（non-GAAP） | B91: US$ | C91: =C89/C90 -> 6.8233866 | D91: =D89/D90 -> 11.615277 | E91: =E89/E90 -> 17.29633 | F91: =F89/F90 -> 20.090345 | G91: =G89/G90 -> 22.934055
A92: EPS 年增 | B92: % | D92: =D91/C91-1 -> 0.70227444 | E92: =E91/D91-1 -> 0.48910186 | F92: =F91/E91-1 -> 0.161538 | G92: =G91/F91-1 -> 0.14154614
A95: 案例區塊：XPU 顆數係數 ×1.1（情境 A）
A96: 項目 | B96: 單位 | C96: FY2025A | D96: FY2026（錨點） | E96: FY2027 | F96: FY2028 | G96: FY2029 | H96: 說明
A97: A. XPU（由下而上；D 欄＝FY2026 校準年，E–G＝FY2027–FY2029；FY(t)＝CY(t)）
A98: Google TPU 市場顆數 | B98: 百萬顆 | D98: =u_tpu_26 -> 3.85 | E98: =u_tpu_27 -> 5.5 | F98: =u_tpu_28*um28_A -> 7 | G98: =u_tpu_28*(1+g29_tpu)*um29_A -> 8.05
A99: 其他 ASIC（MTIA、Maia、Ascend 等） 市場顆數 | B99: 百萬顆 | D99: =u_oth_26 -> 1 | E99: =u_oth_27 -> 4.5 | F99: =u_oth_28*um28_A -> 5 | G99: =u_oth_28*(1+g29_oth)*um29_A -> 5.75
A100: Broadcom 份額：Google TPU | B100: % | D100: =sh_tpu_26 -> 0.9 | E100: =MIN(1,MAX(0,sh_tpu_27+0)) -> 0.8 | F100: =MIN(1,MAX(0,sh_tpu_28+0)) -> 0.75 | G100: =MIN(1,MAX(0,sh_tpu_28+0)) -> 0.75
A101: Broadcom 份額：其他 ASIC（MTIA、Maia、Ascend 等） | B101: % | D101: =sh_oth_26 -> 0.35 | E101: =MIN(1,MAX(0,sh_oth_27+0)) -> 0.55 | F101: =MIN(1,MAX(0,sh_oth_28+0)) -> 0.55 | G101: =MIN(1,MAX(0,sh_oth_28+0)) -> 0.55
A102: Broadcom 顆數：Google TPU | B102: 百萬顆 | D102: =D98*D100 -> 3.465 | E102: =E98*E100*uk_hi -> 4.84 | F102: =F98*F100*uk_hi -> 5.775 | G102: =G98*G100*uk_hi -> 6.64125
A103: Broadcom 顆數：其他 ASIC（MTIA、Maia、Ascend 等） | B103: 百萬顆 | D103: =D99*D101 -> 0.35 | E103: =E99*E101*uk_hi -> 2.7225 | F103: =F99*F101*uk_hi -> 3.025 | G103: =G99*G101*uk_hi -> 3.47875
A104: 每顆 HBM：Google TPU | B104: GB | D104: =gb_tpu_26 -> 192 | E104: =gb_tpu_27 -> 250 | F104: =gb_tpu_28 -> 288 | G104: =gb_tpu_28 -> 288
A105: 每顆 HBM：其他 ASIC（MTIA、Maia、Ascend 等） | B105: GB | D105: =gb_oth_26 -> 150 | E105: =gb_oth_27 -> 200 | F105: =gb_oth_28 -> 250 | G105: =gb_oth_28 -> 250
A106: HBM 單價 | B106: US$/GB | D106: =hbm_A_26 -> 14.6 | E106: =hbm_A_27 -> 26.28 | F106: =hbm_A_28 -> 28.908 | G106: =hbm_A_29 -> 27.4626
A107: 每顆核心售價：Google TPU | B107: US$K | D107: =core_tpu -> 8 | E107: =core_tpu*1 -> 8 | F107: =core_tpu*1 -> 8 | G107: =core_tpu*1 -> 8
A108: 每顆核心售價：其他 ASIC（MTIA、Maia、Ascend 等） | B108: US$K | D108: =core_oth -> 6 | E108: =core_oth*1 -> 6 | F108: =core_oth*1 -> 6 | G108: =core_oth*1 -> 6
A109: 每顆 HBM 金額（全部）：Google TPU | B109: US$K | D109: =D104*D106/1000 -> 2.8032 | E109: =E104*E106/1000 -> 6.57 | F109: =F104*F106/1000 -> 8.325504 | G109: =G104*G106/1000 -> 7.9092288
A110: 每顆 HBM 金額（全部）：其他 ASIC（MTIA、Maia、Ascend 等） | B110: US$K | D110: =D105*D106/1000 -> 2.19 | E110: =E105*E106/1000 -> 5.256 | F110: =F105*F106/1000 -> 7.227 | G110: =G105*G106/1000 -> 6.86565
A111: 每顆 Broadcom 售價（核心＋代購 HBM）：Google TPU | B111: US$K | D111: =D107+f_hbm*D109 -> 9.68192 | E111: =E107+f_hbm*E109 -> 11.942 | F111: =F107+f_hbm*F109 -> 12.995302 | G111: =G107+f_hbm*G109 -> 12.745537 | H111: 核心售價 ＋ 代購比例 × HBM 金額（未乘 k_x）
A112: 每顆 Broadcom 售價（核心＋代購 HBM）：其他 ASIC（MTIA、Maia、Ascend 等） | B112: US$K | D112: =D108+f_hbm*D110 -> 7.314 | E112: =E108+f_hbm*E110 -> 9.1536 | F112: =F108+f_hbm*F110 -> 10.3362 | G112: =G108+f_hbm*G110 -> 10.11939
A113: XPU 營收（未校準） | B113: US$B | D113: =D102*D111+D103*D112 -> 36.107753 | E113: =E102*E111+E103*E112 -> 82.719956 | F113: =F102*F111+F103*F112 -> 106.31488 | G113: =G102*G111+G103*G112 -> 119.84913
A114: XPU 校準係數 k_x ＝ FY2026 錨點 XPU ÷ 未校準 | B114: x | D114: =a26_xpu/D113 -> 1.1077953 | H114: Derived：以已發生的實績（Q1–Q3＋Q4 指引）校準；FY2027 起沿用。顆數層、份額與核心單價無法分開識別，k_x 是合併係數
A115: XPU 營收 | B115: US$B | D115: =D113*$D$114 -> 40 | E115: =E113*$D$114 -> 91.636781 | F115: =F113*$D$114 -> 117.77512 | G115: =G113*$D$114 -> 132.7683
A116: 其中代購 HBM | B116: US$B | D116: =$D$114*f_hbm*(D102*D109+D103*D110) -> 6.9655432 | E116: =$D$114*f_hbm*(E102*E109+E103*E110) -> 30.647109 | F116: =$D$114*f_hbm*(F102*F109+F103*F110) -> 46.488494 | G116: =$D$114*f_hbm*(G102*G109+G103*G110) -> 50.78868
A117: 其中核心（設計＋邏輯晶片＋封裝） | B117: US$B | D117: =D115-D116 -> 33.034457 | E117: =E115-E116 -> 60.989672 | F117: =F115-F116 -> 71.28663 | G117: =G115-G116 -> 81.979624
A118: Broadcom XPU 顆數（未乘 k_x） | B118: 百萬顆 | D118: =D102+D103 -> 3.815 | E118: =E102+E103 -> 7.5625 | F118: =F102+F103 -> 8.8 | G118: =G102+G103 -> 10.12
...

Sheet Sources
A1: 來源（公司原文＝Broadcom 8-K 新聞稿，已逐份抓取；法說逐字稿只經二手轉述）
A2: 公司：FY2025 與 Q4 FY25 新聞稿（8-K） | B2: https://www.sec.gov/Archives/edgar/data/1730168/000173016825000116/avgo-11022025x8kxex99.htm
A3: 公司：Q1 FY26 新聞稿（8-K） | B3: https://www.sec.gov/Archives/edgar/data/1730168/000173016826000011/avgo-02012026x8kxex99.htm
A4: 公司：Q2 FY26 新聞稿（8-K） | B4: https://www.sec.gov/Archives/edgar/data/1730168/000173016826000051/avgo-05032026x8kxex99.htm
A5: 公司：Q3 FY26 新聞稿（含 Q4 指引、九個月合計） | B5: https://investors.broadcom.com/news-releases/news-release-details/broadcom-inc-announces-third-quarter-fiscal-year-2026-financial
A6: 二手：Q3 FY26 法說逐字稿（XPU 73%、客戶、毛利率路徑、FY2027–28 展望） | B6: https://www.investing.com/news/transcripts/earnings-call-transcript-broadcom-tops-q3-2026-estimates-as-ai-sales-surge-93CH-4886849
A7: 二手：BigGo Finance 法說摘要 | B7: https://finance.biggo.com/news/US_AVGO_2026-09-02
A8: 二手：StockAnalysis 共識、現價、前瞻 P/E | B8: https://stockanalysis.com/stocks/avgo/forecast/
A9: 二手：GuruFocus 前瞻 P/E | B9: https://www.gurufocus.com/term/forward-pe-ratio/AVGO
A10: 二手：valueinvesting.io 前瞻 P/E 49.62（口徑不明，不採） | B10: https://valueinvesting.io/AVGO/metric/forward-pe
A11: 二手：top1markets 客戶融資與股價（2026-10-22） | B11: https://www.top1markets.com/news/broadcom-stock-ai-revenue-230-billion-financing-risk
A12: 二手：JPMorgan（KuCoin 轉述）：ASIC 顆數、Broadcom AI 營收 | B12: https://www.kucoin.com/news/flash/jpmorgan-ai-custom-chip-shipments-to-surpass-gpus-by-2027
A13: 二手：Counterpoint（Yahoo 轉述）：Broadcom 2027 ASIC 份額約 60% | B13: https://finance.yahoo.com/news/broadcom-set-dominate-custom-ai-163116560.html
A14: 二手：Macrotrends GAAP P/E | B14: https://www.macrotrends.net/stocks/charts/AVGO/broadcom/pe-ratio
A15: 市場層：markets/memory/market.py（UNITS）；tsmc、skhynix、markets/network、nvidia 成品（本 repo，唯讀）
A16: 待補（人工）：前瞻 P/E 十年歷史（Bloomberg，10-27）；各客戶營收；XPU 產品別毛利率；HBM 代購比例 | B16: 未找到
A17: SemiAnalysis | B17: 未使用
