Workbook

Sheet README
A1: 京元電子（2449）收支與估值模型 v0.2（AI 半導體 Project：測試代工；AI GPU／ASIC 最終測試與 burn-in） 2026-10-25
A2: 版本：v0.2（2026-10-25：目標價改為 DCF 與 Comparable 加權，取代 v0.1 的短期法／長期法）。驅動邏輯比照 Advantest 模型（測試需求＝加速器顆數 × 每顆測試時間；顆數與情境係數讀台積電模型成品）；台股寫法比照台達電、台光電模型。
A3: 模型命題：京元電的 AI 測試營收＝加速器顆數（NVIDIA、ASIC）× 每顆測試時間（含 burn-in；Rubin 世代加長）× 京元電曝險 × 每加權顆營收（FY2026 校準）× 份額相對值 × 測試單價；非 AI（伺服器 CPU、手機、消費、車用）另依成長率推。毛利率由固定現金成本、變動現金成本與折舊推出，折舊由隨當年營收增量擴產的資本支出累積。股價約 32 倍 FY2026、24 倍 FY2027 EPS（模型）。
A4: 核心問題：2026 年 500 億的擴產（約為營收的一倍）能否在 2027–28 年被 AI 測試量吸收；顆數放緩或份額流失時，累積的折舊會讓毛利率掉多少；現價隱含的路徑合不合理。
A6: 會計年度＝日曆年，FY(t)＝CY(t)，不平移。預測期 FY2027–FY2029 由驅動因子推導；FY2030 起為收斂法，非驅動因子推導（營收年增與淨利率線性收斂，延伸到 FY2032；PL 頁綠底）。金額：十億新台幣。口徑：歸屬母公司淨利；FY2026 起以盈餘配股 5% 後的股數計 EPS。
A8: 驅動因子 → 推導量（全部唯讀上游，不修改）
A9: 需求面：tsmc 成品的加速器顆數（八個平台）× 情境顆數係數 × 每顆測試時間係數（Assumed／Analogy，比照 Advantest 模型並加 burn-in）× 京元電曝險（ASIC、AMD 相對 NVIDIA，Assumed）＝加權顆數；× 每加權顆營收（FY2026 以 AI 占比 35% 校準，Derived）× 份額相對值 × 測試單價指數（Assumed）＝AI 加速器測試營收。
A10: 供給面：資本支出＝維持性比例 × 營收＋κ × 當年營收增量（κ 以 FY2025 現金資本支出與 FY2025 營收增量校準）；FY2026 取公司預算 500 億的現金口徑 420 億（Derived）。折舊＝前一年 ×（1 − 到期）＋折舊率 × 資本支出平均。
A11: 毛利率：營收 − 現金營業成本（固定 F，FY2026 校準；變動 v × 測試量）− 折舊。營業費用：彈性 phi。淨利 ÷ 營業利益 0.84（Assumed：利息費用上升）。
A12: 校準：FY2026 ＝ 1H26 實績＋3Q26 營收實績（月營收）＋假設（4Q 季增 15%、毛利率 38.5％／39.5%、折舊 29.5／31.5 億、營業費用率 12.5%）。3Q26 財報約 11 月上旬公布。不用共識數字（只在 Recon 對帳）。
A13: 估值：現價 ÷ FY2027、FY2028 EPS；十年 P/E 規則值（年底收盤 ÷ 當年 EPS，10 年）× 各情境 FY2027 EPS；循環位置以本模型營收最高年判定（京元電不套設備股見頂年）。目標價（Val 第 0 節）＝0.5 × DCF（股東現金流＝EPS ×（1 − g／ROE），FY2027–32 明確期＋永續，r 10%、g 4%，情境權重 0.3／0.5／0.2）＋0.5 × Comparable（台美封測同業前瞻 P/E 中位數 × 12 個月後前瞻 EPS）；十年 P/E 規則值保留參考。本版未做先驗，無 Andy 合理 P/E 對照。
A14: 標記：Verified、Interested-party、Analogy、Assumed、Derived。SemiAnalysis 未使用。公司原文＝每季 Investor update 與月營收；AI 占比、客戶、資本支出預算多經媒體與券商轉述。
... A17: v0.2（2026-10-25）：Val 頁第 0 節由短期法／長期法改為「0. 目標價」（0.1 DCF、0.2 Comparable、0.3 結論），第 1 節起整體下移 23 列；In 頁 tp_mix 改為 tp_w_dcf，新增共識目標價與共識前瞻 EPS；Recon 的 Morgan Stanley 對照改用加權目標價；Sens 加目標價參數列。PL、FY2026–FY2032 EPS 不變。

Sheet In
A1: In — 輸入（藍字；基準欄 E，低 D、高 F）。金額：十億新台幣（NT$B）；顆數：百萬顆；比例：%。每個輸入附兩個來源（找不到者寫「未找到」）；公司原文算一個
A2: 標記：Verified／Interested-party／Analogy／Assumed／Derived；Analogy、Assumed 給低／高區間。SemiAnalysis 未使用。公司原文＝京元電每季 Investor update（英文簡報）與月營收公告；AI 占比、客戶與券商估計為 Interested-party（媒體、券商轉述）
A3: 鍵 | B3: 項目 | C3: 單位 | D3: 低 | E3: 基準 | F3: 高 | G3: 標記 | H3: 來源1 | I3: 來源2／說明
A4: A. 加速器顆數（讀 tsmc 成品 In 頁，與 HBM、台積電、Advantest 模型同一份；情境係數不另訂）
A5: u_bw_26 | B5: NVIDIA Blackwell 顆數 2026 | C5: 百萬顆 | E5: 5.4 | G5: Derived | H5: tsmc/dist/20261025_台積電模型_v0.3.xlsx｜In!E5 | I5: markets/memory UNITS（經台積電模型；顆數本身多為 Interested-party／Assumed，見上游）
A6: u_bw_27 | B6: NVIDIA Blackwell 顆數 2027 | C6: 百萬顆 | E6: 2.4 | G6: Derived | H6: tsmc/dist/20261025_台積電模型_v0.3.xlsx｜In!E6 | I6: 同上
A7: u_bw_28 | B7: NVIDIA Blackwell 顆數 2028 | C7: 百萬顆 | E7: 0.5 | G7: Derived | H7: tsmc/dist/20261025_台積電模型_v0.3.xlsx｜In!E7 | I7: 同上
A8: g29_bw | B8: NVIDIA Blackwell 2029 顆數成長 | C8: % | E8: -0.5 | G8: Assumed | H8: tsmc/dist/20261025_台積電模型_v0.3.xlsx｜In!E8 | I8: 沿用台積電模型
A9: u_rb_26 | B9: NVIDIA Rubin 顆數 2026 | C9: 百萬顆 | E9: 1.7 | G9: Derived | H9: tsmc/dist/20261025_台積電模型_v0.3.xlsx｜In!E9 | I9: markets/memory UNITS（經台積電模型；顆數本身多為 Interested-party／Assumed，見上游）
A10: u_rb_27 | B10: NVIDIA Rubin 顆數 2027 | C10: 百萬顆 | E10: 7 | G10: Derived | H10: tsmc/dist/20261025_台積電模型_v0.3.xlsx｜In!E10 | I10: 同上
A11: u_rb_28 | B11: NVIDIA Rubin 顆數 2028 | C11: 百萬顆 | E11: 7 | G11: Derived | H11: tsmc/dist/20261025_台積電模型_v0.3.xlsx｜In!E11 | I11: 同上
A12: g29_rb | B12: NVIDIA Rubin 2029 顆數成長 | C12: % | E12: 0.15 | G12: Assumed | H12: tsmc/dist/20261025_台積電模型_v0.3.xlsx｜In!E12 | I12: 沿用台積電模型
A13: u_ru_26 | B13: NVIDIA Rubin Ultra 顆數 2026 | C13: 百萬顆 | E13: 0 | G13: Derived | H13: tsmc/dist/20261025_台積電模型_v0.3.xlsx｜In!E13 | I13: markets/memory UNITS（經台積電模型；顆數本身多為 Interested-party／Assumed，見上游）
A14: u_ru_27 | B14: NVIDIA Rubin Ultra 顆數 2027 | C14: 百萬顆 | E14: 0.3 | G14: Derived | H14: tsmc/dist/20261025_台積電模型_v0.3.xlsx｜In!E14 | I14: 同上
A15: u_ru_28 | B15: NVIDIA Rubin Ultra 顆數 2028 | C15: 百萬顆 | E15: 2 | G15: Derived | H15: tsmc/dist/20261025_台積電模型_v0.3.xlsx｜In!E15 | I15: 同上
A16: g29_ru | B16: NVIDIA Rubin Ultra 2029 顆數成長 | C16: % | E16: 0.15 | G16: Assumed | H16: tsmc/dist/20261025_台積電模型_v0.3.xlsx｜In!E16 | I16: 沿用台積電模型
... A42: um29_C | B42: 情境 C：2029 顆數 ÷ 基準 | C42: x | E42: 0.6 | G42: Assumed | H42: tsmc/dist/20261025_台積電模型_v0.3.xlsx｜In!E42 | I42: 同上
A43: fx | B43: 匯率（新台幣 ÷ 美元；只用於每顆美元換算的顯示） | C43: NT$/US$ | D43: 30.5 | E43: 32 | F43: 33 | G43: Derived | H43: 與台達電、台光電模型相同 | I43: 不影響營收與 EPS
A44: B. 每顆測試時間（含 burn-in）係數與京元電曝險（Blackwell＝1.0；NVIDIA 曝險＝1.0）
A45: tt_bw | B45: 每顆測試時間（含 burn-in）係數：NVIDIA Blackwell | C45: x | E45: 1 | G45: Assumed | H45: 定義：Blackwell＝1.0 | I45: 校準在 FY2026 進行，係數只決定世代與平台間的相對權重
A46: tt_rb | B46: 每顆測試時間（含 burn-in）係數：NVIDIA Rubin | C46: x | D46: 1.2 | E46: 1.5 | F46: 1.8 | G46: Assumed | H46: Advantest 模型 ATE 測試時間 1.3（Analogy）＋ burn-in 加長：Morgan Stanley 估 R 系列 burn-in 增量占 2026 營收 3–5%（2026-06-23） | I46: 公司：GPU 客戶要求更高可靠度，burn-in 後需再做最終測試，總測試時間拉長（理財周刊 2026-09-24）
A47: tt_ru | B47: 每顆測試時間（含 burn-in）係數：NVIDIA Rubin Ultra | C47: x | D47: 1.5 | E47: 2 | F47: 2.6 | G47: Assumed | H47: Advantest 模型 1.7（4 顆光罩尺寸晶粒＋16 疊 HBM4E）＋ burn-in 功耗更高；Assumed | I47: 第二來源：未找到
A48: tt_hp | B48: 每顆測試時間（含 burn-in）係數：NVIDIA Hopper | C48: x | D48: 0.5 | E48: 0.6 | F48: 0.8 | G48: Analogy | H48: Advantest 模型 0.6；上一世代 | I48: 第二來源：未找到
A49: tt_amd | B49: 每顆測試時間（含 burn-in）係數：AMD Instinct | C49: x | D49: 0.9 | E49: 1.1 | F49: 1.4 | G49: Analogy | H49: Advantest 模型 1.1 | I49: 第二來源：未找到
A50: tt_tpu | B50: 每顆測試時間（含 burn-in）係數：Google TPU | C50: x | D50: 0.7 | E50: 0.9 | F50: 1.2 | G50: Assumed | H50: Advantest 模型 1.0；ASIC 的 burn-in 時間短於 GPU（Assumed） | I50: 第二來源：未找到
A51: tt_trn | B51: 每顆測試時間（含 burn-in）係數：AWS Trainium | C51: x | D51: 0.6 | E51: 0.8 | F51: 1.1 | G51: Analogy | H51: Advantest 模型 0.8 | I51: 第二來源：未找到
A52: tt_oth | B52: 每顆測試時間（含 burn-in）係數：其他 ASIC（MTIA、Maia 等） | C52: x | D52: 0.5 | E52: 0.7 | F52: 1 | G52: Analogy | H52: Advantest 模型 0.7 | I52: 第二來源：未找到
A53: ex_amd | B53: 京元電曝險（相對 NVIDIA＝1.0）：AMD Instinct | C53: x | D53: 0.1 | E53: 0.2 | F53: 0.4 | G53: Assumed | H53: AMD 委外測試主要在日月光、Amkor（Assumed）；京元電份額：未找到 | I53: 公司：GPU 測試是較大的營收來源，ASIC 2026–27 由低基期快速成長（富果 2025-11-28 法說摘要）
A54: ex_tpu | B54: 京元電曝險（相對 NVIDIA＝1.0）：Google TPU | C54: x | D54: 0.3 | E54: 0.5 | F54: 0.7 | G54: Assumed | H54: Google 相關（TPU、CPU、最終測試、部分晶圓測試）約占 2026 營收 10%（Morgan Stanley 2026-06-23）；聯發科 TPU 後段測試 9 月起量產（優分析 2026-09-18） | I54: —
A55: ex_trn | B55: 京元電曝險（相對 NVIDIA＝1.0）：AWS Trainium | C55: x | D55: 0.2 | E55: 0.4 | F55: 0.6 | G55: Assumed | H55: AWS ASIC 專案出貨中（優分析 2026-09-18）；份額：未找到 | I55: —
A56: ex_oth | B56: 京元電曝險（相對 NVIDIA＝1.0）：其他 ASIC（MTIA、Maia 等） | C56: x | D56: 0.2 | E56: 0.4 | F56: 0.6 | G56: Assumed | H56: Meta 等 ASIC（理財周刊 2026-09-24）；份額：未找到 | I56: —
A57: C. 份額、價格與 AI 部署係數（FY2027 起）
A58: rel_27 | B58: 京元電份額 2027 ÷ 2026（相對值；對 NVIDIA 與 ASIC 委外測試） | C58: x | D58: 0.88 | E58: 0.95 | F58: 1 | G58: Assumed | H58: NVIDIA 分散測試供應鏈（日月光、矽品、Amkor 擴最終測試與 burn-in）；京元電份額：未找到 | I58: Morgan Stanley：AI GPU 與 ASIC 最終測試市占穩固（2026-06-23，Interested-party）
A59: rel_28 | B59: 京元電份額 2028 ÷ 2026（相對值；對 NVIDIA 與 ASIC 委外測試） | C59: x | D59: 0.8 | E59: 0.92 | F59: 1 | G59: Assumed | H59: 同上 | I59: —
A60: rel_29 | B60: 京元電份額 2029 ÷ 2026（相對值；對 NVIDIA 與 ASIC 委外測試） | C60: x | D60: 0.75 | E60: 0.9 | F60: 1 | G60: Assumed | H60: 同上 | I60: —
A61: pp_27 | B61: 測試單價指數 2027（2026＝1；每單位測試時間的價格） | C61: x | D61: 0.95 | E61: 0.98 | F61: 1.02 | G61: Assumed | H61: 公司未揭露測試單價：未找到；低毛利手機、網通訂單移出，產品組合改善（工商時報 2026-07-28） | I61: 新產能到位後價格競爭（Assumed）
A62: pp_28 | B62: 測試單價指數 2028（2026＝1；每單位測試時間的價格） | C62: x | D62: 0.9 | E62: 0.96 | F62: 1 | G62: Assumed | H62: 同上 | I62: —
A63: pp_29 | B63: 測試單價指數 2029（2026＝1；每單位測試時間的價格） | C63: x | D63: 0.88 | E63: 0.95 | F63: 1 | G63: Assumed | H63: 同上 | I63: —
A64: mf | B64: AI 部署係數（Sens 用；FY2027 起乘在加權顆數上） | C64: x | D64: 0.8 | E64: 1 | F64: 1.2 | G64: Assumed | H64: 無 | I64: ±20%
A65: D. 營收結構錨點（AI 加速器測試＝NVIDIA GPU＋ASIC 的晶圓測試、最終測試、burn-in）
A66: ai_25 | B66: 2025 年 AI 加速器測試營收 ÷ 營收 | C66: % | D66: 0.25 | E66: 0.275 | F66: 0.3 | G66: Interested-party | H66: Morgan Stanley：2025 年 AI 占營收 25–30%（2026-06-23） | I66: 中央社 2026-03-06：法人稱 AI 相關測試超過 25%；只用於 FY2025 欄拆分
A67: ai_26 | B67: 2026 年 AI 加速器測試營收 ÷ 營收（校準用） | C67: % | D67: 0.28 | E67: 0.35 | F67: 0.45 | G67: Interested-party | H67: Morgan Stanley：2026 年超過 35%（2026-06-23）；中央社 2026-03-06：法人預估超過 30% | I67: 媒體另稱「AI 相關」2026 年 70% 以上（理財周刊 2026-09-01、優分析 2026-09-18），口徑含 CPU、網通等，不採；公司 2Q26 資料處理應用占營收 36.3%（poorstock 摘要公司簡報），上限參考
A68: g_nai27 | B68: 非 AI 營收年增 2027（伺服器 CPU、手機、消費、車用、工業） | C68: % | D68: 0.04 | E68: 0.12 | F68: 0.2 | G68: Assumed | H68: Morgan Stanley：最大客戶 CPU（V 系列）占 2026–27 營收 8–10%，加 Google CPU 後 2026 年 CPU 測試超過 15%（2026-06-23） | I68: 其他 IC 設計客戶 CPU 產能多在 2026 年底建置完成，支撐 2027 年（理財周刊 2026-09-01）；手機、網通訂單移出（工商時報 2026-07-28）
A69: g_nai28 | B69: 非 AI 營收年增 2028（伺服器 CPU、手機、消費、車用、工業） | C69: % | D69: 0 | E69: 0.07 | F69: 0.12 | G69: Assumed | H69: 同上 | I69: —
A70: g_nai29 | B70: 非 AI 營收年增 2029（伺服器 CPU、手機、消費、車用、工業） | C70: % | D70: 0 | E70: 0.05 | F70: 0.1 | G70: Assumed | H70: 同上 | I70: —
A71: E. 資本支出與折舊（毛利率的關鍵）
A72: capex_26 | B72: 2026 年資本支出（現金口徑） | C72: NT$B | D72: 35 | E72: 42 | F72: 50 | G72: Derived | H72: 董事會 2026 年預算 500 億（2026-07 由 393.72 億上修；工商時報 2026-07-28、理財周刊 2026-09-24）；約五成用於廠房與無塵室（Morgan Stanley） | I72: 1H26 現金資本支出 67.9＋71.0＝138.9 億（poorstock 摘要公司簡報）；2025 年預算約 370 億、現金 323.6 億 → 現金約為預算 87%；基準＝下半年加速（Assumed），高＝預算全額
A73: m_cx | B73: 維持性資本支出 ÷ 營收 | C73: % | D73: 0.06 | E73: 0.1 | F73: 0.15 | G73: Assumed | H73: 無：公司未拆分維持與擴產 | I73: 測試機汰換與升級（Assumed）
A74: rev24 | B74: 2024 年營收（κ 校準用） | C74: NT$B | E74: =34.93354/1.3008 -> 26.855427 | G74: Derived | H74: 2025 年營收 349.34 億、年增 30.08%（雅虎新聞 2026-01-27） | I74: HiStock：2025 年累計年增 30.1%
A75: dr | B75: 新增資本支出的年折舊率（設備約 5–6 年、廠房約 20 年的混合） | C75: %/年 | D75: 0.09 | E75: 0.11 | F75: 0.14 | G75: Assumed | H75: 約一半用於廠房與無塵室（Morgan Stanley 2026-06-23）：0.5 ÷ 6＋0.5 ÷ 20 ≈ 0.11 | I75: Recon 以同一公式回測 FY2026 折舊
A76: ret | B76: 既有折舊每年到期比例 | C76: %/年 | D76: 0 | E76: 0.05 | F76: 0.1 | G76: Assumed | H76: 無 | I76: —
A77: v_cc | B77: 變動現金營業成本 ÷ 營收（電力、耗材、直接人工） | C77: % | D77: 0.1 | E77: 0.2 | F77: 0.3 | G77: Assumed | H77: 季資料（Q 頁）：營收 1Q25 73 億 → 2Q26 111 億，現金營業成本只從 32 億增至 40 億（斜率約 0.2；同季比較 2Q25→2Q26 約 0.14，Q 頁） | I77: 公司：二季產能擴充後折舊、電費、人力成本上升（理財周刊 2026-09-24）；固定部分 F 由 FY2026 錨點推得
A78: F. FY2026 錨點（1H26 實績＋3Q26 營收實績＋假設；3Q26 財報約 11 月上旬公布）
A79: q3_rev | B79: 3Q26 營收（月營收合計＝前 9 月 − 上半年） | C79: NT$B | E79: =33.475818-21.33356 -> 12.142258 | G79: Verified | H79: https://finance.technews.tw/2026/10/08/kyec-2449-202609-financial-report/：9 月 40.71 億、前 9 月 334.76 億（年增 34.1%） | I79: HiStock 月營收：7 月 39.91、8 月 40.80、9 月 40.71 億（https://histock.tw/stock/financial.aspx?no=2449）
A80: q4g | B80: 4Q26 營收季增 | C80: % | D80: 0.08 | E80: 0.15 | F80: 0.22 | G80: Assumed | H80: 公司未給量化指引；法人估 4Q 季增約 20%（理財周刊 2026-09-01；優分析 2026-09-18 估 145.59 億） | I80: Rubin 首批測試延到 3Q 底、4Q 放量（優分析 2026-09-18）；9 月營收 40.71 億 × 3＝122 億（季增 0%）為下限參考
A81: q3_gm | B81: 3Q26 毛利率 | C81: % | D81: 0.37 | E81: 0.385 | F81: 0.4 | G81: Assumed | H81: 公司未給指引；2Q26 39.5%、1Q26 39.7%（公司簡報） | I81: 二季產能擴充後折舊、電費、人力上升（理財周刊 2026-09-24）
A82: q4_gm | B82: 4Q26 毛利率 | C82: % | D82: 0.375 | E82: 0.395 | F82: 0.41 | G82: Assumed | H82: 4Q 營收放量、稼動率上升（Assumed） | I82: —
A83: q3_da | B83: 3Q26 折舊攤提 | C83: NT$B | D83: 2.8 | E83: 2.95 | F83: 3.1 | G83: Assumed | H83: Q 頁：EBITDA − 營業利益，3Q25 1.91 → 4Q25 2.19 → 1Q26 2.49 → 2Q26 2.74（每季約 +0.25） | I83: 公司未直接揭露折舊金額：未找到
A84: q4_da | B84: 4Q26 折舊攤提 | C84: NT$B | D84: 2.9 | E84: 3.15 | F84: 3.4 | G84: Assumed | H84: 同上 | I84: —
A85: q_opx | B85: 3Q、4Q26 營業費用 ÷ 營收 | C85: % | D85: 0.115 | E85: 0.125 | F85: 0.14 | G85: Assumed | H85: 1Q26 12.5%、2Q26 14.1%（推銷管理＋研發；公司簡報） | I85: FY2025 10.1%
A86: q_nir | B86: 3Q、4Q26 歸屬母公司淨利 ÷ 營業利益 | C86: % | D86: 0.8 | E86: 0.85 | F86: 0.9 | G86: Derived | H86: 1H26：淨利 47.78 億 ÷ 營業利益 56.0 億＝0.853（公司簡報推得） | I86: 2Q–4Q25：0.899（不含 1Q25 處分利益）
A87: q_sh | B87: 股數（十億股；含 2026 年盈餘配股每股 0.5 元＝5%） | C87: 十億股 | E87: =2.492/2.04*1.05 -> 1.2826471 | G87: Derived | H87: 2Q26 淨利 24.92 億 ÷ EPS 2.04＝12.22 億股（理財周刊 2026-09-01）× 1.05（盈餘配股 0.5 元，2026-07-28 除權，工商時報） | I87: 鉅亨網 10-22 顯示股本 12.23 億股（可能尚未反映配股）；配股依會計準則追溯調整 EPS，FY2026 起以 12.83 億股計
A88: G. 營業費用、稅與股數（FY2027 起）
A89: phi | B89: 營業費用成長對營收成長的彈性 | C89: x | D89: 0.4 | E89: 0.6 | F89: 1 | G89: Assumed | H89: FY2026 錨點實測（Q 頁）；FY2026 費用率上升含美國廠籌設與員工酬勞 | I89: —
A90: opx_adj | B90: 營業費用額外占營收比（Sens 用；基準 0） | C90: pt | D90: -0.01 | E90: 0 | F90: 0.01 | G90: Assumed | H90: 無 | I90: —
A91: nir_f | B91: 歸屬母公司淨利 ÷ 營業利益 | C91: % | D91: 0.78 | E91: 0.84 | F91: 0.9 | G91: Assumed | H91: 1H26 0.853；資本支出擴大使利息費用上升（淨負債 ÷ 權益 2Q26 32.7%，poorstock 摘要公司簡報） | I91: 2Q–4Q25 0.899
A92: sh_g | B92: 股數年變動 | C92: % | D92: 0 | E92: 0 | F92: 0.05 | G92: Assumed | H92: 2025 年度配股 5%；之後是否續配股：未找到 | I92: 高＝每年再配股 5%
A93: H. 共識、券商與市場資料（只作 Recon 對帳，不作校準）
A94: c_eps26 | B94: FactSet 共識 FY2026 EPS 中位數（2026-04-06，15 位分析師） | C94: NT$ | E94: 9.9 | G94: Interested-party | H94: https://news.cnyes.com/news/id/6407870 | I94: 高 11.5、低 9.02；配股前股數口徑（推定）
A95: c_eps27 | B95: FactSet 共識 FY2027 EPS 中位數（2026-04-06） | C95: NT$ | E95: 14.4 | G95: Interested-party | H95: https://news.cnyes.com/news/id/6407870 | I95: 高 16.05、低 13.35
A96: c_eps28 | B96: FactSet 共識 FY2028 EPS 中位數（2026-04-06） | C96: NT$ | E96: 17.72 | G96: Interested-party | H96: https://news.cnyes.com/news/id/6407870 | I96: 高 18.77、低 16.67
A97: c_eps26b | B97: 法人 FY2026 EPS 中位數區間中點（理財周刊 2026-09-01：9.09–9.79） | C97: NT$ | E97: =(9.09+9.79)/2 -> 9.44 | G97: Interested-party | H97: https://www.moneyweekly.com.tw/_Article?AID=246195 | I97: 樂觀 10.79
A98: c_rev26 | B98: 法人 FY2026 營收（理財周刊 2026-09-01：近 500 億，485–500 億中點） | C98: NT$B | E98: 49.25 | G98: Interested-party | H98: https://www.moneyweekly.com.tw/_Article?AID=246195 | I98: 優分析 2026-09-18：年增約 36.7%（＝477.5 億）
A99: c_q4rev | B99: 法人 4Q26 營收估計 | C99: NT$B | E99: 14.559 | G99: Interested-party | H99: https://uanalyze.com.tw/articles/5209555591 | I99: 季增約 20%
A100: ms_tp | B100: Morgan Stanley 目標價（2026-06-23） | C100: NT$ | E100: 388 | G100: Interested-party | H100: https://finance.technews.tw/2026/06/23/morgan-stanley-expects-king-yuan-electronics-revenue-to-grow-by-40-in-2026/ | I100: 由 338 上調；法人目標價中位數 348–350（理財周刊 2026-09-01）
A101: ms_goog | B101: Morgan Stanley：Google 相關占 2026 營收（TPU、CPU、最終測試、部分晶圓測試） | C101: % | E101: 0.1 | G101: Interested-party | H101: https://finance.technews.tw/2026/06/23/morgan-stanley-expects-king-yuan-electronics-revenue-to-grow-by-40-in-2026/ | I101: 口徑含 CPU，比本模型 TPU 測試寬
A102: dp_26 | B102: 公司 2Q26 資料處理應用占營收 | C102: % | E102: 0.363 | G102: Interested-party | H102: https://poorstock.com/earningcall/2449（AI 摘要公司簡報，未核原文） | I102: 3Q25 32.8%（富果 2025-11-28 法說摘要）
A103: bi_25 | B103: Burn-in 占營收（3Q25） | C103: % | E103: 0.09 | G103: Interested-party | H103: https://blog.fugle.tw/post/earnings-call-2449-2025-11-28（AI 摘要公司法說） | I103: 最終測試 58.2%、晶圓測試 30.4%
A104: I. 價格與估值
A105: px | B105: 股價（2026-10-22 收盤） | C105: NT$ | E105: 262.5 | G105: Interested-party | H105: 鉅亨網 2449 個股頁（10-22 收盤 262.5，−5.58%；網址見 Sources） | I105: 財報狗、HiStock：10-22 收盤 262.5；10-23 收盤：未找到
A106: pe_ttm | B106: 近 12 月 P/E（鉅亨網，10-22） | C106: x | E106: 36.13 | G106: Interested-party | H106: https://www.cnyes.com/twstock/2449 | I106: HiStock 10 月本益比 34.40；stockanalysis 2026-09-03 為 36.12
A107: J. 目標價（DCF＋Comparable）與收斂法參數（黃底；Andy 可改；v0.2 由短期法／長期法改為 DCF＋Comparable）
A108: tp_wA | B108: 目標價情境權重 A（順利） | C108: % | E108: 0.3 | G108: Assumed | H108: Andy 可改（工作單 2026-10-25 預設 A 0.3／B 0.5／C 0.2） | I108: 三者合計應為 100%（Val 頁第 0 節列示）
A109: tp_wB | B109: 目標價情境權重 B（平平） | C109: % | E109: 0.5 | G109: Assumed | H109: Andy 可改（工作單 2026-10-25 預設 A 0.3／B 0.5／C 0.2） | I109: 三者合計應為 100%（Val 頁第 0 節列示）
A110: tp_wC | B110: 目標價情境權重 C（不如預期） | C110: % | E110: 0.2 | G110: Assumed | H110: Andy 可改（工作單 2026-10-25 預設 A 0.3／B 0.5／C 0.2） | I110: 三者合計應為 100%（Val 頁第 0 節列示）
A111: tp_r | B111: 折現率／要求報酬（DCF） | C111: % | E111: 0.1 | G111: Assumed | H111: Andy 可改（工作單預設 10%；各市場同一值） | I111: DCF 與 Sens
A112: tp_g | B112: 長期成長率（DCF 永續；收斂法情境 B 的 FY2032 營收年增） | C112: % | E112: 0.04 | G112: Assumed | H112: Andy 可改（工作單預設 4%） | I112: —
A113: tp_roe | B113: 近三年平均 ROE（2023–2025；DCF 再投資率＝tp_g ÷ tp_roe） | C113: % | E113: =(0.1584+0.1584+0.2377)/3 -> 0.18483333 | G113: Derived | H113: 玩股網年度 ROE：2023 15.84%、2024 15.84%、2025 23.77%（2025 含處分利益）；Andy 可改 | I113: stockanalysis：2023 11.13%、2024 11.24%、2025 16.83%（口徑不同，平均 13.1%，不採）
A114: tp_w_dcf | B114: 目標價中 DCF 的權重；其餘為 Comparable | C114: % | E114: 0.5 | G114: Assumed | H114: Andy 可改（工作單 2026-10-25 11:53 定 DCF／Comparable 各半） | I114: —
A115: fade_gA | B115: 收斂法：情境 A 於 FY2032 的營收年增（＝tp_g＋2pt） | C115: % | E115: =tp_g+0.02 -> 0.06 | G115: Assumed | H115: Andy 可改（工作單 11:20） | I115: FY2030 起為收斂法，非驅動因子推導
A116: fade_gC | B116: 收斂法：情境 C 於 FY2032 的營收年增（＝tp_g−2pt） | C116: % | E116: =tp_g-0.02 -> 0.02 | G116: Assumed | H116: Andy 可改（工作單 11:20）；情境 B 收斂到 tp_g | I116: —
A117: fade_mA | B117: 收斂法：情境 A 的中段淨利率（＝FY2029 淨利率） | C117: % | E117: =PL!G104/PL!G81 -> 0.22589701 | G117: Derived | H117: PL 頁情境 A FY2029 淨利 ÷ 營收 | I117: Andy 可改
A118: fade_mB | B118: 收斂法：情境 B 的中段淨利率（＝FY2029 與十年平均的中點） | C118: % | E118: =(PL!G155/PL!G132+PL!G155/PL!G132*0.8)/2 -> 0.19724721 | G118: Assumed | H118: 十年平均淨利率（2016–2025）：未找到，以 FY2029 × 0.8 代替（工作單規則）；本列＝（FY2029＋FY2029 × 0.8）÷ 2 | I118: Andy 可改
A119: fade_mC | B119: 收斂法：情境 C 的中段淨利率（＝十年平均） | C119: % | E119: =PL!G206/PL!G183*0.8 -> 0.13534419 | G119: Assumed | H119: 十年平均淨利率：未找到，以情境 C FY2029 淨利率 × 0.8 代替 | I119: Andy 可改
A120: cons_tp | B120: 市場共識目標價（賣方平均） | C120: NT$ | E120: 340.73 | G120: Interested-party | H120: stockanalysis 統計頁：15 位分析師平均 340.73（頁面價格日期 2026-10-06） | I120: 法人目標價中位數 348–350（理財周刊 2026-09-01）；Morgan Stanley 388（In 頁 ms_tp）
A121: cons_feps | B121: 共識 12 個月後前瞻 EPS（2/12 × FY2027＋10/12 × FY2028；換成配股後股數 ÷ 1.05） | C121: NT$ | E121: =(2/12*c_eps27+10/12*c_eps28)/1.05 -> 16.349206 | G121: Derived | H121: In 頁 FactSet 共識 FY2027、FY2028 中位數（2026-04-06；推定為配股前口徑） | I121: 共識只放 Recon 與本列，不作校準；共識日期較舊

Sheet Q
A1: Q — 實績與 FY2026 錨點（十億新台幣；EPS 為新台幣；股數為十億股）。藍字＝輸入；黑字＝公式。季資料取自京元電每季 Investor update（營收、毛利率、推銷管理費用、研發、EBITDA、EPS）；營業利益＝毛利 − 營業費用，折舊攤提＝EBITDA − 營業利益（Derived）
A2: FY2026 錨點＝1H26 實績＋3Q26 營收實績（月營收）＋3Q、4Q 假設（毛利率、折舊、營業費用率、淨利 ÷ 營業利益；4Q 營收＝3Q × (1＋季增)）。3Q26 財報約 11 月上旬公布（確切日期：未找到），公布後更新。FY2025 淨利含 1Q25 出售蘇州京隆科技的處分利益（法人估約每股 2 元，未拆出金額：未找到）
A3: 項目 | B3: FY2025A | C3: 1H26（實績） | D3: 3Q26（營收實績） | E3: 4Q26（模型） | F3: FY2026 錨點 | G3: 標記 | H3: 來源1 | I3: 來源2／說明
A4: 營收 | B4: =SUM(B26:E26) -> 34.9336 | C4: =SUM(F26:G26) -> 21.3335 | D4: =q3_rev -> 12.142258 | E4: =D4*(1+q4g) -> 13.963597 | F4: =SUM(C4:E4) -> 47.439355 | G4: Verified／Assumed（4Q 季增） | H4: 季資料（本頁下方）：公司 Investor update 1Q25–2Q26（https://kyec.com.tw/Upfiles/EDUp/files/關於京元/KYEC(2449TW)_2Q25 Investor update_English.pdf、https://www.kyec.com.tw/Upfiles/EDUp/files/投資人關係/每季營運報告/KYEC(2449)_4Q25 Investor update_English.pdf、https://www.kyec.com.tw/Upfiles/EDUp/files/投資人關係/每季營運報告/KYEC(2449)_2Q26 Investor update_English.pdf） | I4: FY2025 月營收合計 349.34 億（HiStock）、中央社 349.33 億；1H26 213.34 億（HiStock 月營收）；3Q26：https://finance.technews.tw/2026/10/08/kyec-2449-202609-financial-report/
A5: 毛利 | B5: =SUM(B31:E31) -> 12.520816 | C5: =SUM(F31:G31) -> 8.4511931 | D5: =D4*q3_gm -> 4.6747693 | E5: =E4*q4_gm -> 5.5156207 | F5: =SUM(C5:E5) -> 18.641583 | G5: Derived（營收 × 毛利率）／Assumed | H5: 季資料（本頁下方）：公司 Investor update 1Q25–2Q26（https://kyec.com.tw/Upfiles/EDUp/files/關於京元/KYEC(2449TW)_2Q25 Investor update_English.pdf、https://www.kyec.com.tw/Upfiles/EDUp/files/投資人關係/每季營運報告/KYEC(2449)_4Q25 Investor update_English.pdf、https://www.kyec.com.tw/Upfiles/EDUp/files/投資人關係/每季營運報告/KYEC(2449)_2Q26 Investor update_English.pdf） | I5: FY2025：中央社 2026-03-06（營收 349.33 億、毛利率 35.84%、營業利益 90.02 億、淨利 110.15 億、EPS 9.01）；3Q26：月營收
A6: 毛利率 | B6: =B5/B4 -> 0.35841757 | C6: =C5/C4 -> 0.39614658 | D6: =D5/D4 -> 0.385 | E6: =E5/E4 -> 0.395 | F6: =F5/F4 -> 0.39295608 | G6: Derived | H6: — | I6: FY2025 35.84%（中央社 2026-03-06）
A7: 折舊攤提（EBITDA − 營業利益） | B7: =SUM(B35:E35) -> 7.5143841 | C7: =SUM(F35:G35) -> 5.2277069 | D7: =q3_da -> 2.95 | E7: =q4_da -> 3.15 | F7: =SUM(C7:E7) -> 11.327707 | G7: Derived／Assumed | H7: 季資料（本頁下方）：公司 Investor update 1Q25–2Q26（https://kyec.com.tw/Upfiles/EDUp/files/關於京元/KYEC(2449TW)_2Q25 Investor update_English.pdf、https://www.kyec.com.tw/Upfiles/EDUp/files/投資人關係/每季營運報告/KYEC(2449)_4Q25 Investor update_English.pdf、https://www.kyec.com.tw/Upfiles/EDUp/files/投資人關係/每季營運報告/KYEC(2449)_2Q26 Investor update_English.pdf） | I7: 公司未直接揭露折舊金額：未找到；以公司 EBITDA 減營業利益推得
A8: 現金營業成本（營收 − 毛利 − 折舊攤提） | B8: =B4-B5-B7 -> 14.8984 | C8: =C4-C5-C7 -> 7.6546 | D8: =D4-D5-D7 -> 4.5174887 | E8: =E4-E5-E7 -> 5.297976 | F8: =SUM(C8:E8) -> 17.470065 | G8: Derived | H8: — | I8: 假設折舊攤提全部在營業成本（部分在營業費用，Assumed）
A9: 營業費用（推銷管理＋研發） | B9: =SUM(B32:E32) -> 3.5197 | C9: =SUM(F32:G32) -> 2.8509 | D9: =D4*q_opx -> 1.5177822 | E9: =E4*q_opx -> 1.7454496 | F9: =SUM(C9:E9) -> 6.1141318 | G9: Verified／Assumed | H9: 季資料（本頁下方）：公司 Investor update 1Q25–2Q26（https://kyec.com.tw/Upfiles/EDUp/files/關於京元/KYEC(2449TW)_2Q25 Investor update_English.pdf、https://www.kyec.com.tw/Upfiles/EDUp/files/投資人關係/每季營運報告/KYEC(2449)_4Q25 Investor update_English.pdf、https://www.kyec.com.tw/Upfiles/EDUp/files/投資人關係/每季營運報告/KYEC(2449)_2Q26 Investor update_English.pdf） | I9: FY2025：中央社 2026-03-06（營收 349.33 億、毛利率 35.84%、營業利益 90.02 億、淨利 110.15 億、EPS 9.01）；3Q26：月營收
A10: 營業利益 | B10: =B5-B9 -> 9.0011159 | C10: =C5-C9 -> 5.6002931 | D10: =D5-D9 -> 3.1569871 | E10: =E5-E9 -> 3.7701711 | F10: =SUM(C10:E10) -> 12.527451 | G10: Derived | H10: 季資料（本頁下方）：公司 Investor update 1Q25–2Q26（https://kyec.com.tw/Upfiles/EDUp/files/關於京元/KYEC(2449TW)_2Q25 Investor update_English.pdf、https://www.kyec.com.tw/Upfiles/EDUp/files/投資人關係/每季營運報告/KYEC(2449)_4Q25 Investor update_English.pdf、https://www.kyec.com.tw/Upfiles/EDUp/files/投資人關係/每季營運報告/KYEC(2449)_2Q26 Investor update_English.pdf） | I10: FY2025 公司 90.02 億（中央社）；1Q26 營益率 27.2%（科技新報 2026-05-11）
A11: 營業利益率 | B11: =B10/B4 -> 0.25766356 | C11: =C10/C4 -> 0.26251169 | D11: =D10/D4 -> 0.26 | E11: =E10/E4 -> 0.27 | F11: =F10/F4 -> 0.26407297 | G11: Derived | H11: — | I11: —
A12: 歸屬母公司淨利 | B12: 11.015 | C12: =2.286+2.492 -> 4.778 | D12: =D10*q_nir -> 2.683439 | E12: =E10*q_nir -> 3.2046454 | F12: =SUM(C12:E12) -> 10.666084 | G12: Verified／Derived（3Q、4Q） | H12: FY2025 110.15 億（中央社 2026-03-06）；1Q26 22.86 億（科技新報 2026-05-11）、2Q26 24.92 億（理財周刊 2026-09-01） | I12: 1H26 47.78 億（理財周刊）
A13: 淨利 ÷ 營業利益 | B13: =B12/B10 -> 1.2237372 | C13: =C12/C10 -> 0.85316964 | D13: =D12/D10 -> 0.85 | E13: =E12/E10 -> 0.85 | F13: =F12/F10 -> 0.85141696 | G13: Derived | H13: — | I13: FY2025 含處分利益
A14: 股數（十億股） | B14: =11.015/9.01 -> 1.2225305 | C14: =4.778/3.91 -> 1.2219949 | D14: =q_sh -> 1.2826471 | E14: =q_sh -> 1.2826471 | F14: =q_sh -> 1.2826471 | G14: Derived | H14: 淨利 ÷ EPS（FY2025、1H26 為配股前） | I14: FY2026 錨點用配股後 12.83 億股（In 頁 q_sh）
A15: EPS | B15: =B12/B14 -> 9.01 | C15: =C12/C14 -> 3.91 | D15: =D12/D14 -> 2.0921102 | E15: =E12/E14 -> 2.4984624 | F15: =F12/F14 -> 8.3156815 | G15: Derived | H15: 淨利 ÷ 股數 | I15: FY2026 以配股後股數計（1H26 追溯後約 3.72）
A16: 公司揭露 EPS（基本） | B16: 9.01 | C16: 3.91 | G16: Verified | H16: 中央社 2026-03-06；公司簡報 1Q26 1.87、2Q26 2.04 | I16: Yahoo 股市、HiStock 同值
A17: 資本支出（現金） | B17: 32.3554 | C17: =6.7858+7.0978 -> 13.8836 | F17: =capex_26 -> 42 | G17: Verified（單一來源）／Derived | H17: https://poorstock.com/earningcall/2449（AI 摘要公司簡報：2023 77.3、2024 148.6、2025 323.6 億；1Q26 67.9、2Q26 71.0 億） | I17: 預算：2025 約 370 億（雅虎 2026-01-27）、2026 年 500 億（工商時報 2026-07-28）
A18: AI 加速器測試營收（＝營收 × AI 占比） | B18: =B4*ai_25 -> 9.60674 | F18: =F4*ai_26 -> 16.603774 | G18: Derived／Interested-party | H18: In 頁 D 節 | I18: 公司未揭露 AI 營收金額：未找到
A19: 非 AI 營收（＝營收 − AI） | B19: =B4-B18 -> 25.32686 | F19: =F4-F18 -> 30.835581 | G19: Derived | H19: — | I19: 伺服器 CPU、手機、消費、車用、工業、網通
A21: 核對（參考）
A22: FY2025 營業利益（季資料推得）− 公司 90.02 億 | B22: =B10-9.002 -> -0.0008841
A23: FY2025 毛利率（季資料推得）− 公司 35.84% | B23: =B6-0.3584 -> 1.7566469e-05
A24: FY2026 營收年增（錨點） | B24: =F4/B4-1 -> 0.35798643
A25: 季資料（公司 Investor update） | B25: 1Q25 | C25: 2Q25 | D25: 3Q25 | E25: 4Q25 | F25: 1Q26 | G25: 2Q26 | H25: 標記 | I25: 來源
A26: 營收 | B26: 7.3155 | C26: 8.3619 | D26: 9.2905 | E26: 9.9657 | F26: 10.1919 | G26: 11.1416 | H26: Verified | I26: 公司簡報（2Q25、4Q25、2Q26 Investor update）；與 HiStock 月營收合計相符
A27: 毛利率 | B27: 0.335 | C27: 0.355 | D27: 0.36 | E27: 0.377 | F27: 0.3974 | G27: 0.395 | H27: Verified | I27: 公司簡報（四捨五入至 0.1%）；1Q26 39.74%（科技新報 2026-05-11）
A28: 推銷及管理費用 | B28: 0.6851 | C28: 0.5833 | D28: 0.6369 | E28: 0.6841 | F28: 0.9713 | G28: 1.2573 | H28: Verified | I28: 公司簡報
A29: 研發費用 | B29: 0.2426 | C29: 0.2121 | D29: 0.2178 | E29: 0.2578 | F29: 0.3073 | G29: 0.315 | H29: Verified | I29: 公司簡報
A30: EBITDA | B30: 3.1729 | C30: 3.9445 | D30: 4.396 | E30: 5.0021 | F30: 5.2584 | G30: 5.5696 | H30: Verified | I30: 公司簡報（定義未載明；本模型視為營業利益＋折舊攤提）
A31: 毛利（營收 × 毛利率） | B31: =B26*B27 -> 2.4506925 | C31: =C26*C27 -> 2.9684745 | D31: =D26*D27 -> 3.34458 | E31: =E26*E27 -> 3.7570689 | F31: =F26*F27 -> 4.0502611 | G31: =G26*G27 -> 4.400932 | H31: Derived
A32: 營業費用（推銷管理＋研發） | B32: =B28+B29 -> 0.9277 | C32: =C28+C29 -> 0.7954 | D32: =D28+D29 -> 0.8547 | E32: =E28+E29 -> 0.9419 | F32: =F28+F29 -> 1.2786 | G32: =G28+G29 -> 1.5723 | H32: Derived
A33: 營業利益（毛利 − 營業費用） | B33: =B31-B32 -> 1.5229925 | C33: =C31-C32 -> 2.1730745 | D33: =D31-D32 -> 2.48988 | E33: =E31-E32 -> 2.8151689 | F33: =F31-F32 -> 2.7716611 | G33: =G31-G32 -> 2.828632 | H33: Derived
A34: 營業利益率 | B34: =B33/B26 -> 0.20818707 | C34: =C33/C26 -> 0.25987808 | D34: =D33/D26 -> 0.2680028 | E34: =E33/E26 -> 0.28248582 | F34: =F33/F26 -> 0.27194743 | G34: =G33/G26 -> 0.25388023 | H34: Derived
A35: 折舊攤提（EBITDA − 營業利益） | B35: =B30-B33 -> 1.6499075 | C35: =C30-C33 -> 1.7714255 | D35: =D30-D33 -> 1.90612 | E35: =E30-E33 -> 2.1869311 | F35: =F30-F33 -> 2.4867389 | G35: =G30-G33 -> 2.740968 | H35: Derived
A36: 現金營業成本（營收 − 毛利 − 折舊攤提） | B36: =B26-B31-B35 -> 3.2149 | C36: =C26-C31-C35 -> 3.622 | D36: =D26-D31-D35 -> 4.0398 | E36: =E26-E31-E35 -> 4.0217 | F36: =F26-F31-F35 -> 3.6549 | G36: =G26-G31-G35 -> 3.9997 | H36: Derived
A37: EPS（基本，公司揭露） | B37: 3.51 | C37: 1.78 | D37: 1.88 | E37: 1.84 | F37: 1.87 | G37: 2.04 | H37: Verified | I37: 公司簡報；Yahoo 股市、HiStock 同值；1Q25 含處分利益
A38: 現金營業成本季增 ÷ 營收季增（2Q25→2Q26；In 頁 v_cc 的參考） | B38: =(G36-C36)/(G26-C26) -> 0.13587797 | H38: Derived | I38: 同季比較排除季節性；斜率小代表現金成本多為固定（人力、電力基本量）

Sheet Units
A1: Units — 加速器顆數（tsmc 成品）× 每顆測試時間（含 burn-in）× 京元電曝險 → 加權顆數；FY2026 以 AI 占比校準每加權顆營收。情境 A；FY(t)＝CY(t)
A3: 項目 | B3: 單位 | C3: CY2026 | D3: CY2027 | E3: CY2028 | F3: CY2029 | G3: 說明
A4: 加速器顆數合計（未加權） | B4: 百萬顆 | C4: =PL!D71 -> 15.2 | D4: =PL!E71 -> 23.7 | E4: =PL!F71 -> 26.5 | F4: =PL!G71 -> 30.15 | G4: 讀台積電模型 In 頁（與 HBM、Advantest 同一份）
A5: NVIDIA Blackwell：加權顆數 | B5: 百萬顆 | C5: =PL!D63 -> 5.4 | D5: =PL!E63 -> 2.4 | E5: =PL!F63 -> 0.5 | F5: =PL!G63 -> 0.25 | G5: 顆數 × 測試時間係數
A6: NVIDIA Rubin：加權顆數 | B6: 百萬顆 | C6: =PL!D64 -> 2.55 | D6: =PL!E64 -> 10.5 | E6: =PL!F64 -> 10.5 | F6: =PL!G64 -> 12.075 | G6: 顆數 × 測試時間係數
A7: NVIDIA Rubin Ultra：加權顆數 | B7: 百萬顆 | C7: =PL!D65 -> 0 | D7: =PL!E65 -> 0.6 | E7: =PL!F65 -> 4 | F7: =PL!G65 -> 4.6 | G7: 顆數 × 測試時間係數
A8: NVIDIA Hopper：加權顆數 | B8: 百萬顆 | C8: =PL!D66 -> 0.3 | D8: =PL!E66 -> 0 | E8: =PL!F66 -> 0 | F8: =PL!G66 -> 0 | G8: 顆數 × 測試時間係數
A9: AMD Instinct：加權顆數 | B9: 百萬顆 | C9: =PL!D67 -> 0.165 | D9: =PL!E67 -> 0.33 | E9: =PL!F67 -> 0.44 | F9: =PL!G67 -> 0.506 | G9: 顆數 × 測試時間係數 × 曝險
A10: Google TPU：加權顆數 | B10: 百萬顆 | C10: =PL!D68 -> 1.7325 | D10: =PL!E68 -> 2.475 | E10: =PL!F68 -> 3.15 | F10: =PL!G68 -> 3.6225 | G10: 顆數 × 測試時間係數 × 曝險
A11: AWS Trainium：加權顆數 | B11: 百萬顆 | C11: =PL!D69 -> 0.64 | D11: =PL!E69 -> 0.8 | E11: =PL!F69 -> 0.96 | F11: =PL!G69 -> 1.104 | G11: 顆數 × 測試時間係數 × 曝險
A12: 其他 ASIC（MTIA、Maia 等）：加權顆數 | B12: 百萬顆 | C12: =PL!D70 -> 0.28 | D12: =PL!E70 -> 1.26 | E12: =PL!F70 -> 1.4 | F12: =PL!G70 -> 1.61 | G12: 顆數 × 測試時間係數 × 曝險
A13: 加權顆數合計（Blackwell 等值） | B13: 百萬顆 | C13: =PL!D74 -> 11.0675 | D13: =PL!E74 -> 18.365 | E13: =PL!F74 -> 20.95 | F13: =PL!G74 -> 23.7675
A14: NVIDIA ÷ 加權顆數 | B14: % | C14: =PL!D84 -> 0.7454258 | D14: =PL!E84 -> 0.73509393 | E14: =PL!F84 -> 0.71599045 | F14: =PL!G84 -> 0.71210687 | G14: 公司：GPU 為較大的營收來源（富果 2025-11-28 法說摘要）
A15: 京元電 AI 加速器測試營收 | B15: US$B | C15: =PL!D79/fx -> 0.51886794 | D15: =PL!E79/fx -> 0.80158194 | E15: =PL!F79/fx -> 0.86746187 | F15: =PL!G79/fx -> 0.95270167
A16: 每顆 Blackwell 等值的京元電 AI 測試營收 | B16: US$／顆 | C16: =PL!D85 -> 46.882127 | D16: =PL!E85 -> 43.64726 | E16: =PL!F85 -> 41.406295 | F16: =PL!G85 -> 40.084219 | G16: FY2026 校準；之後 × 份額 × 單價
A17: 每顆加速器（未加權）的京元電 AI 測試營收 | B17: US$／顆 | C17: =PL!D79/fx/PL!D71*1000 -> 34.136049 | D17: =PL!E79/fx/PL!E71*1000 -> 33.822023 | E17: =PL!F79/fx/PL!F71*1000 -> 32.73441 | F17: =PL!G79/fx/PL!G71*1000 -> 31.598729 | G17: 世代組合升級使每顆金額上升
A18: 資本支出 | B18: NT$B | C18: =PL!D88 -> 42 | D18: =PL!E88 -> 51.562093 | E18: =PL!F88 -> 22.640712 | F18: =PL!G88 -> 23.275723
A19: 資本支出 ÷ 加權顆數增量 | B19: NT$／顆 | C19: ="—" -> — | D19: =IFERROR(PL!E88/(PL!E74-PL!D74)*1000,"—") -> 7065.7202 | E19: =IFERROR(PL!F88/(PL!F74-PL!E74)*1000,"—") -> 8758.496 | F19: =IFERROR(PL!G88/(PL!G74-PL!F74)*1000,"—") -> 8261.1263 | G19: 顆數下修（增量為負）時數值無意義
A20: 折舊攤提 ÷ 營收 | B20: % | C20: =PL!D91 -> 0.23878291 | D20: =PL!E91 -> 0.2642992 | E20: =PL!F91 -> 0.29659086 | F20: =PL!G91 -> 0.29960364 | G20: 毛利率的主要變數
A22: 讀法：加權顆數的絕對水準與曝險只影響 FY2026 校準出的每加權顆營收，不影響 FY2026 營收；影響成長的是世代組合（Rubin、Rubin Ultra 的測試時間與 burn-in）、ASIC 曝險、份額相對值與單價。京元電的份額無法單獨識別（公司不揭露客戶別營收），以「每顆 Blackwell 等值營收」與份額相對值表示。

Sheet PL
A1: PL — 京元電損益（十億新台幣；EPS 新台幣；歸屬母公司）。FY2025A 實績、FY2026 錨點（1H26 實績＋3Q26 營收實績＋假設），FY2027 起為模型。FY(t)＝CY(t)。三情境各一個完整推導區塊（本頁下方），頂端為摘要。FY2026–FY2027 三情境相同（顆數係數從 CY2028 開始）
A3: 情境／項目 | B3: 單位 | C3: FY2025A | D3: FY2026（錨點） | E3: FY2027 | F3: FY2028 | G3: FY2029 | H3: FY2030（收斂） | I3: FY2031（收斂） | J3: FY2032（收斂） | K3: 說明
A4: 情境 A
A5: 營收 | B5: NT$B | C5: =C81 -> 34.9336 | D5: =D81 -> 47.439355 | E5: =E81 -> 60.186472 | F5: =F81 -> 64.71214 | G5: =G81 -> 69.287481 | H5: =H216 -> 73.939119 | I5: =I216 -> 78.639255 | J5: =J216 -> 83.357611
A6: 營收年增 | B6: % | D6: =D82 -> 0.35798643 | E6: =E82 -> 0.26870343 | F6: =F82 -> 0.075194098 | G6: =G82 -> 0.070702984 | H6: =H215 -> 0.067135323 | I6: =I215 -> 0.063567661 | J6: =J215 -> 0.06
A7: AI 加速器測試營收 | B7: NT$B | C7: =C79 -> 9.60674 | D7: =D79 -> 16.603774 | E7: =E79 -> 25.650622 | F7: =F79 -> 27.75878 | G7: =G79 -> 30.486453
A8: 非 AI 營收 | B8: NT$B | C8: =C80 -> 25.32686 | D8: =D80 -> 30.835581 | E8: =E80 -> 34.53585 | F8: =F80 -> 36.95336 | G8: =G80 -> 38.801028
A9: 資本支出 | B9: NT$B | C9: =C88 -> 32.3554 | D9: =D88 -> 42 | E9: =E88 -> 51.562093 | F9: =F88 -> 22.640712 | G9: =G88 -> 23.275723
A10: 折舊攤提 ÷ 營收 | B10: % | C10: =C91 -> 0.21510477 | D10: =D91 -> 0.23878291 | E10: =E91 -> 0.2642992 | F10: =F91 -> 0.29659086 | G10: =G91 -> 0.29960364
A11: 毛利率 | B11: % | C11: =C97 -> 0.35841757 | D11: =D97 -> 0.39295608 | E11: =E97 -> 0.40133688 | F11: =F97 -> 0.37648524 | G11: =G97 -> 0.3805608
A12: 營業利益率 | B12: % | C12: =C101 -> 0.25766356 | D12: =D101 -> 0.26407297 | E12: =E101 -> 0.28337242 | F12: =F101 -> 0.26182074 | G12: =G101 -> 0.26892501
A13: 淨利率 | B13: % | C13: =C104/C81 -> 0.31531248 | D13: =D104/D81 -> 0.2248362 | E13: =E104/E81 -> 0.23803283 | F13: =F104/F81 -> 0.21992942 | G13: =G104/G81 -> 0.22589701 | H13: =H217 -> 0.22589701 | I13: =I217 -> 0.22589701 | J13: =J217 -> 0.22589701
A14: 歸屬母公司淨利 | B14: NT$B | C14: =C104 -> 11.015 | D14: =D104 -> 10.666084 | E14: =E104 -> 14.326356 | F14: =F104 -> 14.232103 | G14: =G104 -> 15.651835 | H14: =H218 -> 16.702626 | I14: =I218 -> 17.764372 | J14: =J218 -> 18.830235
A15: EPS | B15: NT$ | C15: =C107 -> 9.01 | D15: =D107 -> 8.3156815 | E15: =E107 -> 11.169367 | F15: =F107 -> 11.095884 | G15: =G107 -> 12.20276 | H15: =H220 -> 13.021997 | I15: =I220 -> 13.849774 | J15: =J220 -> 14.680761
A16: EPS 年增 | B16: % | D16: =D108 -> -0.077060873 | E16: =E108 -> 0.34316922 | F16: =F108 -> -0.0065789932 | G16: =G108 -> 0.099755544 | H16: =H15/G15-1 -> 0.067135323 | I16: =I15/H15-1 -> 0.063567661 | J16: =J15/I15-1 -> 0.06
A18: 情境 B
A19: 營收 | B19: NT$B | C19: =C132 -> 34.9336 | D19: =D132 -> 47.439355 | E19: =E132 -> 60.186472 | F19: =F132 -> 59.160384 | G19: =G132 -> 64.714513 | H19: =H225 -> 69.62775 | I19: =I225 -> 73.663434 | J19: =J225 -> 76.609972
A20: 營收年增 | B20: % | D20: =D133 -> 0.35798643 | E20: =E133 -> 0.26870343 | F20: =F133 -> -0.01704849 | G20: =G133 -> 0.093882579 | H20: =H224 -> 0.075921719 | I20: =I224 -> 0.05796086 | J20: =J224 -> 0.04
A21: AI 加速器測試營收 | B21: NT$B | C21: =C130 -> 9.60674 | D21: =D130 -> 16.603774 | E21: =E130 -> 25.650622 | F21: =F130 -> 22.207024 | G21: =G130 -> 25.913485
A22: 非 AI 營收 | B22: NT$B | C22: =C131 -> 25.32686 | D22: =D131 -> 30.835581 | E22: =E131 -> 34.53585 | F22: =F131 -> 36.95336 | G22: =G131 -> 38.801028
A23: 資本支出 | B23: NT$B | C23: =C139 -> 32.3554 | D23: =D139 -> 42 | E23: =E139 -> 51.562093 | F23: =F139 -> 5.9160384 | G23: =G139 -> 26.315482
A24: 折舊攤提 ÷ 營收 | B24: % | C24: =C142 -> 0.21510477 | D24: =D142 -> 0.23878291 | E24: =E142 -> 0.2642992 | F24: =F142 -> 0.30887515 | G24: =G142 -> 0.29564075
A25: 毛利率 | B25: % | C25: =C148 -> 0.35841757 | D25: =D148 -> 0.39295608 | E25: =E148 -> 0.40133688 | F25: =F148 -> 0.35307213 | G25: =G148 -> 0.3767995
A26: 營業利益率 | B26: % | C26: =C152 -> 0.25766356 | D26: =D152 -> 0.26407297 | E26: =E152 -> 0.28337242 | F26: =F152 -> 0.23306167 | G26: =G152 -> 0.260909
A27: 淨利率 | B27: % | C27: =C155/C132 -> 0.31531248 | D27: =D155/D132 -> 0.2248362 | E27: =E155/E132 -> 0.23803283 | F27: =F155/F132 -> 0.1957718 | G27: =G155/G132 -> 0.21916356 | H27: =H226 -> 0.21185811 | I27: =I226 -> 0.20455266 | J27: =J226 -> 0.19724721
A28: 歸屬母公司淨利 | B28: NT$B | C28: =C155 -> 11.015 | D28: =D155 -> 10.666084 | E28: =E155 -> 14.326356 | F28: =F155 -> 11.581935 | G28: =G155 -> 14.183063 | H28: =H227 -> 14.751204 | I28: =I227 -> 15.068051 | J28: =J227 -> 15.111103
A29: EPS | B29: NT$ | C29: =C158 -> 9.01 | D29: =D158 -> 8.3156815 | E29: =E158 -> 11.169367 | F29: =F158 -> 9.0297131 | G29: =G158 -> 11.057651 | H29: =H229 -> 11.500594 | I29: =I229 -> 11.747621 | J29: =J229 -> 11.781186
A30: EPS 年增 | B30: % | D30: =D159 -> -0.077060873 | E30: =E159 -> 0.34316922 | F30: =F159 -> -0.19156451 | G30: =G159 -> 0.22458495 | H30: =H29/G29-1 -> 0.040057662 | I30: =I29/H29-1 -> 0.021479451 | J30: =J29/I29-1 -> 0.0028571429
A32: 情境 C
A33: 營收 | B33: NT$B | C33: =C183 -> 34.9336 | D33: =D183 -> 47.439355 | E33: =E183 -> 60.186472 | F33: =F183 -> 53.608628 | G33: =G183 -> 57.0929 | H33: =H234 -> 59.94734 | I33: =I234 -> 62.045389 | J33: =J234 -> 63.286297
A34: 營收年增 | B34: % | D34: =D184 -> 0.35798643 | E34: =E184 -> 0.26870343 | F34: =F184 -> -0.10929108 | G34: =G184 -> 0.064994613 | H34: =H233 -> 0.049996409 | I34: =I233 -> 0.034998204 | J34: =J233 -> 0.02
A35: AI 加速器測試營收 | B35: NT$B | C35: =C181 -> 9.60674 | D35: =D181 -> 16.603774 | E35: =E181 -> 25.650622 | F35: =F181 -> 16.655268 | G35: =G181 -> 18.291872
A36: 非 AI 營收 | B36: NT$B | C36: =C182 -> 25.32686 | D36: =D182 -> 30.835581 | E36: =E182 -> 34.53585 | F36: =F182 -> 36.95336 | G36: =G182 -> 38.801028
A37: 資本支出 | B37: NT$B | C37: =C190 -> 32.3554 | D37: =D190 -> 42 | E37: =E190 -> 51.562093 | F37: =F190 -> 5.3608628 | G37: =G190 -> 18.158046
A38: 折舊攤提 ÷ 營收 | B38: % | C38: =C193 -> 0.21510477 | D38: =D193 -> 0.23878291 | E38: =E193 -> 0.2642992 | F38: =F193 -> 0.34029294 | G38: =G193 -> 0.32620598
A39: 毛利率 | B39: % | C39: =C199 -> 0.35841757 | D39: =D199 -> 0.39295608 | E39: =E199 -> 0.40133688 | F39: =F199 -> 0.30822048 | G39: =G199 -> 0.33061089
A40: 營業利益率 | B40: % | C40: =C203 -> 0.25766356 | D40: =D203 -> 0.26407297 | E40: =E203 -> 0.28337242 | F40: =F203 -> 0.17578164 | G40: =G203 -> 0.20140504
A41: 淨利率 | B41: % | C41: =C206/C183 -> 0.31531248 | D41: =D206/D183 -> 0.2248362 | E41: =E206/E183 -> 0.23803283 | F41: =F206/F183 -> 0.14765657 | G41: =G206/G183 -> 0.16918024 | H41: =H235 -> 0.15790155 | I41: =I235 -> 0.14662287 | J41: =J235 -> 0.13534419
A42: 歸屬母公司淨利 | B42: NT$B | C42: =C206 -> 11.015 | D42: =D206 -> 10.666084 | E42: =E206 -> 14.326356 | F42: =F206 -> 7.9156664 | G42: =G206 -> 9.6589903 | H42: =H236 -> 9.4657781 | I42: =I236 -> 9.0972731 | J42: =J236 -> 8.5654325
A43: EPS | B43: NT$ | C43: =C209 -> 9.01 | D43: =D209 -> 8.3156815 | E43: =E209 -> 11.169367 | F43: =F209 -> 6.1713519 | G43: =G209 -> 7.5305129 | H43: =H238 -> 7.3798774 | I43: =I238 -> 7.0925771 | J43: =J238 -> 6.6779341
A44: EPS 年增 | B44: % | D44: =D210 -> -0.077060873 | E44: =E210 -> 0.34316922 | F44: =F210 -> -0.44747526 | G44: =G210 -> 0.22023717 | H44: =H43/G43-1 -> -0.020003352 | I44: =I43/H43-1 -> -0.038930239 | J44: =J43/I43-1 -> -0.058461538
A46: 核對（應為 0）：FY2026 模型營收、毛利、營業利益 − 錨點（情境 A）
A47: 情境 A：營收差（NT$B） | D47: =D81-a26_rev -> 0
A48: 情境 A：毛利差（NT$B） | D48: =D96-a26_gp -> 0
A49: 情境 A：營業利益差（NT$B） | D49: =D100-a26_oi -> 0
A50: 情境 A：FY2025 毛利差（NT$B） | C50: =C96-a25_gp -> 0
A60: 情境 A：基準（顆數係數 1.0）
A61: 項目 | B61: 單位 | C61: FY2025A | D61: FY2026（錨點） | E61: FY2027 | F61: FY2028 | G61: FY2029 | H61: 說明
A62: A. AI 加速器測試需求（加權顆數＝顆數 × 每顆測試時間（含 burn-in）× 京元電曝險；FY(t)＝CY(t)）
A63: NVIDIA Blackwell：加權顆數 | B63: 百萬顆 | D63: =u_bw_26*tt_bw -> 5.4 | E63: =u_bw_27*1*tt_bw -> 2.4 | F63: =u_bw_28*um28_A*1*tt_bw -> 0.5 | G63: =u_bw_28*(1+g29_bw)*um29_A*1*tt_bw -> 0.25
A64: NVIDIA Rubin：加權顆數 | B64: 百萬顆 | D64: =u_rb_26*tt_rb -> 2.55 | E64: =u_rb_27*1*tt_rb -> 10.5 | F64: =u_rb_28*um28_A*1*tt_rb -> 10.5 | G64: =u_rb_28*(1+g29_rb)*um29_A*1*tt_rb -> 12.075
A65: NVIDIA Rubin Ultra：加權顆數 | B65: 百萬顆 | D65: =u_ru_26*tt_ru -> 0 | E65: =u_ru_27*1*tt_ru -> 0.6 | F65: =u_ru_28*um28_A*1*tt_ru -> 4 | G65: =u_ru_28*(1+g29_ru)*um29_A*1*tt_ru -> 4.6
A66: NVIDIA Hopper：加權顆數 | B66: 百萬顆 | D66: =u_hp_26*tt_hp -> 0.3 | E66: =u_hp_27*1*tt_hp -> 0 | F66: =u_hp_28*um28_A*1*tt_hp -> 0 | G66: =u_hp_28*(1+g29_hp)*um29_A*1*tt_hp -> 0
A67: AMD Instinct：加權顆數 | B67: 百萬顆 | D67: =u_amd_26*tt_amd*ex_amd -> 0.165 | E67: =u_amd_27*1*tt_amd*ex_amd -> 0.33 | F67: =u_amd_28*um28_A*1*tt_amd*ex_amd -> 0.44 | G67: =u_amd_28*(1+g29_amd)*um29_A*1*tt_amd*ex_amd -> 0.506
A68: Google TPU：加權顆數 | B68: 百萬顆 | D68: =u_tpu_26*tt_tpu*ex_tpu -> 1.7325 | E68: =u_tpu_27*1*tt_tpu*ex_tpu -> 2.475 | F68: =u_tpu_28*um28_A*1*tt_tpu*ex_tpu -> 3.15 | G68: =u_tpu_28*(1+g29_tpu)*um29_A*1*tt_tpu*ex_tpu -> 3.6225
A69: AWS Trainium：加權顆數 | B69: 百萬顆 | D69: =u_trn_26*tt_trn*ex_trn -> 0.64 | E69: =u_trn_27*1*tt_trn*ex_trn -> 0.8 | F69: =u_trn_28*um28_A*1*tt_trn*ex_trn -> 0.96 | G69: =u_trn_28*(1+g29_trn)*um29_A*1*tt_trn*ex_trn -> 1.104
A70: 其他 ASIC（MTIA、Maia 等）：加權顆數 | B70: 百萬顆 | D70: =u_oth_26*tt_oth*ex_oth -> 0.28 | E70: =u_oth_27*1*tt_oth*ex_oth -> 1.26 | F70: =u_oth_28*um28_A*1*tt_oth*ex_oth -> 1.4 | G70: =u_oth_28*(1+g29_oth)*um29_A*1*tt_oth*ex_oth -> 1.61
A71: 加速器顆數合計（未加權） | B71: 百萬顆 | D71: =u_bw_26+u_rb_26+u_ru_26+u_hp_26+u_amd_26+u_tpu_26+u_trn_26+u_oth_26 -> 15.2 | E71: =u_bw_27*1+u_rb_27*1+u_ru_27*1+u_hp_27*1+u_amd_27*1+u_tpu_27*1+u_trn_27*1+u_oth_27*1 -> 23.7 | F71: =u_bw_28*um28_A*1+u_rb_28*um28_A*1+u_ru_28*um28_A*1+u_hp_28*um28_A*1+u_amd_28*um28_A*1+u_tpu_28*um28_A*1+u_trn_28*um28_A*1+u_oth_28*um28_A*1 -> 26.5 | G71: =u_bw_28*(1+g29_bw)*um29_A*1+u_rb_28*(1+g29_rb)*um29_A*1+u_ru_28*(1+g29_ru)*um29_A*1+u_hp_28*(1+g29_hp)*um29_A*1+u_amd_28*(1+g29_amd)*um29_A*1+u_tpu_28*(1+g29_tpu)*um29_A*1+u_trn_28*(1+g29_trn)*um29_A*1+u_oth_28*(1+g29_oth)*um29_A*1 -> 30.15
A72: NVIDIA 加權顆數 | B72: 百萬顆 | D72: =D63+D64+D65+D66 -> 8.25 | E72: =E63+E64+E65+E66 -> 13.5 | F72: =F63+F64+F65+F66 -> 15 | G72: =G63+G64+G65+G66 -> 16.925
A73: AMD 與 ASIC 加權顆數（× 曝險） | B73: 百萬顆 | D73: =D67+D68+D69+D70 -> 2.8175 | E73: =E67+E68+E69+E70 -> 4.865 | F73: =F67+F68+F69+F70 -> 5.95 | G73: =G67+G68+G69+G70 -> 6.8425
A74: 加權顆數合計 | B74: 百萬顆 | D74: =D72+D73 -> 11.0675 | E74: =E72+E73 -> 18.365 | F74: =F72+F73 -> 20.95 | G74: =G72+G73 -> 23.7675
A75: FY2026 AI 加速器測試營收（校準）＝ 錨點營收 × AI 占比 | B75: NT$B | D75: =a26_rev*ai_26 -> 16.603774
A76: 每加權顆營收（FY2026 校準） | B76: NT$B／百萬顆 | D76: =D75/D74 -> 1.5002281 | H76: Derived：＝ 千元新台幣／顆；乘積（測試時間 × 每小時價格 × 份額）只能整體識別
A77: 份額相對值（÷ FY2026） | B77: x | D77: =1 -> 1 | E77: =rel_27 -> 0.95 | F77: =rel_28 -> 0.92 | G77: =rel_29 -> 0.9
A78: 測試單價指數（FY2026＝1） | B78: x | D78: =1 -> 1 | E78: =pp_27 -> 0.98 | F78: =pp_28 -> 0.96 | G78: =pp_29 -> 0.95
A79: AI 加速器測試營收 ＝ 每加權顆營收 × 加權顆數 × 份額 × 單價 | B79: NT$B | C79: =a25_rev*ai_25 -> 9.60674 | D79: =D75 -> 16.603774 | E79: =$D$76*E74*E77*E78 -> 25.650622 | F79: =$D$76*F74*F77*F78 -> 27.75878 | G79: =$D$76*G74*G77*G78 -> 30.486453
A80: 非 AI 營收 | B80: NT$B | C80: =a25_rev-C79 -> 25.32686 | D80: =a26_rev-D79 -> 30.835581 | E80: =D80*(1+g_nai27) -> 34.53585 | F80: =E80*(1+g_nai28) -> 36.95336 | G80: =F80*(1+g_nai29) -> 38.801028
A81: 營收 | B81: NT$B | C81: =C79+C80 -> 34.9336 | D81: =D79+D80 -> 47.439355 | E81: =E79+E80 -> 60.186472 | F81: =F79+F80 -> 64.71214 | G81: =G79+G80 -> 69.287481
A82: 營收年增 | B82: % | D82: =D81/C81-1 -> 0.35798643 | E82: =E81/D81-1 -> 0.26870343 | F82: =F81/E81-1 -> 0.075194098 | G82: =G81/F81-1 -> 0.070702984
A83: AI 加速器測試 ÷ 營收 | B83: % | C83: =C79/C81 -> 0.275 | D83: =D79/D81 -> 0.35 | E83: =E79/E81 -> 0.42618584 | F83: =F79/F81 -> 0.42895784 | G83: =G79/G81 -> 0.43999945
A84: NVIDIA ÷ 加權顆數 | B84: % | D84: =D72/D74 -> 0.7454258 | E84: =E72/E74 -> 0.73509393 | F84: =F72/F74 -> 0.71599045 | G84: =G72/G74 -> 0.71210687
A85: 每顆 Blackwell 等值的京元電 AI 測試營收 | B85: US$／顆 | D85: =D79/D74/fx*1000 -> 46.882127 | E85: =E79/E74/fx*1000 -> 43.64726 | F85: =F79/F74/fx*1000 -> 41.406295 | G85: =G79/G74/fx*1000 -> 40.084219 | H85: 含份額與單價指數；FY2027 起隨份額、單價變動
A86: B. 資本支出與折舊（資本支出＝維持性 × 營收＋κ × 當年營收增量；折舊＝前一年 × (1 − 到期)＋折舊率 × 當年與前一年資本支出平均）
A87: κ：每增加 1 元年營收所需擴產資本支出（FY2025 校準） | B87: x | C87: =(a25_capex-m_cx*a25_rev)/(a25_rev-rev24) -> 3.5728427 | H87: Derived：（FY2025 現金資本支出 − 維持性）÷（FY2025 營收 − FY2024 營收）
A88: 資本支出 | B88: NT$B | C88: =a25_capex -> 32.3554 | D88: =capex_26 -> 42 | E88: =m_cx*E81+$C$87*MAX(0,E81-D81) -> 51.562093 | F88: =m_cx*F81+$C$87*MAX(0,F81-E81) -> 22.640712 | G88: =m_cx*G81+$C$87*MAX(0,G81-F81) -> 23.275723 | H88: FY2026＝In 頁 capex_26（公式值見 Recon）；營收下滑時只剩維持性資本支出
A89: 資本支出 ÷ 營收 | B89: % | C89: =C88/C81 -> 0.92619713 | D89: =D88/D81 -> 0.88534088 | E89: =E88/E81 -> 0.85670569 | F89: =F88/F81 -> 0.34986808 | G89: =G88/G81 -> 0.33592971
A90: 折舊攤提 | B90: NT$B | C90: =a25_da -> 7.5143841 | D90: =a26_da -> 11.327707 | E90: =D90*(1-ret)+dr*(D88+E88)/2 -> 15.907237 | F90: =E90*(1-ret)+dr*(E88+F88)/2 -> 19.193029 | G90: =F90*(1-ret)+dr*(F88+G88)/2 -> 20.758782
A91: 折舊攤提 ÷ 營收 | B91: % | C91: =C90/C81 -> 0.21510477 | D91: =D90/D81 -> 0.23878291 | E91: =E90/E81 -> 0.2642992 | F91: =F90/F81 -> 0.29659086 | G91: =G90/G81 -> 0.29960364
A92: 回測：以同一公式算 FY2026 折舊 − 錨點 | B92: NT$B | D92: =C90*(1-ret)+dr*(C88+D88)/2-D90 -> -0.099495045 | H92: 校準檢查（非獨立檢驗）：正值＝公式高估
A93: C. 損益
A94: 固定現金成本 F（FY2026 校準＝錨點現金成本 − v × 營收） | B94: NT$B | D94: =a26_cc-v_cc*a26_rev -> 7.9821937 | H94: Derived：人力、電力基本量、租金等；FY2026 恆等於錨點
A95: 現金營業成本 ＝ F ＋ v ×（AI 營收 ÷ 單價指數＋非 AI 營收） | B95: NT$B | C95: =a25_cc -> 14.8984 | D95: =a26_cc -> 17.470065 | E95: =$D$94+v_cc*(E79/E78+E80) -> 20.124185 | F95: =$D$94+v_cc*(F79/F78+F80) -> 21.155945 | G95: =$D$94+v_cc*(G79/G78+G80) -> 22.1606 | H95: 成本隨測試量（不含價格）變動；單價下降全部落在毛利
A96: 毛利 ＝ 營收 − 現金營業成本 − 折舊攤提 | B96: NT$B | C96: =C81-C95-C90 -> 12.520816 | D96: =D81-D95-D90 -> 18.641583 | E96: =E81-E95-E90 -> 24.155051 | F96: =F81-F95-F90 -> 24.363166 | G96: =G81-G95-G90 -> 26.368099
A97: 毛利率 | B97: % | C97: =C96/C81 -> 0.35841757 | D97: =D96/D81 -> 0.39295608 | E97: =E96/E81 -> 0.40133688 | F97: =F96/F81 -> 0.37648524 | G97: =G96/G81 -> 0.3805608
A98: 營業費用（基準路徑） | B98: NT$B | C98: =a25_opx -> 3.5197 | D98: =a26_opx -> 6.1141318 | E98: =D98*(1+MAX(0,phi*E82)) -> 7.0998648 | F98: =E98*(1+MAX(0,phi*F82)) -> 7.4201855 | G98: =F98*(1+MAX(0,phi*G82)) -> 7.7349631
A99: 營業費用 | B99: NT$B | C99: =C98 -> 3.5197 | D99: =D98 -> 6.1141318 | E99: =E98+0*E81 -> 7.0998648 | F99: =F98+0*F81 -> 7.4201855 | G99: =G98+0*G81 -> 7.7349631
A100: 營業利益 | B100: NT$B | C100: =C96-C99 -> 9.0011159 | D100: =D96-D99 -> 12.527451 | E100: =E96-E99 -> 17.055186 | F100: =F96-F99 -> 16.94298 | G100: =G96-G99 -> 18.633136
A101: 營業利益率 | B101: % | C101: =C100/C81 -> 0.25766356 | D101: =D100/D81 -> 0.26407297 | E101: =E100/E81 -> 0.28337242 | F101: =F100/F81 -> 0.26182074 | G101: =G100/G81 -> 0.26892501
A102: EBITDA（營業利益＋折舊攤提） | B102: NT$B | C102: =C100+C90 -> 16.5155 | D102: =D100+D90 -> 23.855158 | E102: =E100+E90 -> 32.962423 | F102: =F100+F90 -> 36.136009 | G102: =G100+G90 -> 39.391918
A103: EBITDA − 資本支出（近似，未計稅與營運資金） | B103: NT$B | C103: =C102-C88 -> -15.8399 | D103: =D102-D88 -> -18.144842 | E103: =E102-E88 -> -18.59967 | F103: =F102-F88 -> 13.495297 | G103: =G102-G88 -> 16.116195
A104: 歸屬母公司淨利 | B104: NT$B | C104: =a25_ni -> 11.015 | D104: =a26_ni -> 10.666084 | E104: =E100*nir_f -> 14.326356 | F104: =F100*nir_f -> 14.232103 | G104: =G100*nir_f -> 15.651835 | H104: FY2025 含處分利益
A105: 淨利 ÷ 營業利益 | B105: % | C105: =C104/C100 -> 1.2237372 | D105: =D104/D100 -> 0.85141696 | E105: =E104/E100 -> 0.84 | F105: =F104/F100 -> 0.84 | G105: =G104/G100 -> 0.84
A106: 股數 | B106: 十億股 | C106: =a25_sh -> 1.2225305 | D106: =a26_sh -> 1.2826471 | E106: =D106*(1+sh_g) -> 1.2826471 | F106: =E106*(1+sh_g) -> 1.2826471 | G106: =F106*(1+sh_g) -> 1.2826471
A107: EPS | B107: NT$ | C107: =C104/C106 -> 9.01 | D107: =D104/D106 -> 8.3156815 | E107: =E104/E106 -> 11.169367 | F107: =F104/F106 -> 11.095884 | G107: =G104/G106 -> 12.20276
A108: EPS 年增 | B108: % | D108: =D107/C107-1 -> -0.077060873 | E108: =E107/D107-1 -> 0.34316922 | F108: =F107/E107-1 -> -0.0065789932 | G108: =G107/F107-1 -> 0.099755544 | H108: FY2026 對 FY2025：股數口徑不同（配股 5%）且 FY2025 含處分利益
A111: 情境 B：CY2028 顆數 ×0.8、CY2029 ×0.85
A112: 項目 | B112: 單位 | C112: FY2025A | D112: FY2026（錨點） | E112: FY2027 | F112: FY2028 | G112: FY2029 | H112: 說明
A113: A. AI 加速器測試需求（加權顆數＝顆數 × 每顆測試時間（含 burn-in）× 京元電曝險；FY(t)＝CY(t)）
A114: NVIDIA Blackwell：加權顆數 | B114: 百萬顆 | D114: =u_bw_26*tt_bw -> 5.4 | E114: =u_bw_27*1*tt_bw -> 2.4 | F114: =u_bw_28*um28_B*1*tt_bw -> 0.4 | G114: =u_bw_28*(1+g29_bw)*um29_B*1*tt_bw -> 0.2125
A115: NVIDIA Rubin：加權顆數 | B115: 百萬顆 | D115: =u_rb_26*tt_rb -> 2.55 | E115: =u_rb_27*1*tt_rb -> 10.5 | F115: =u_rb_28*um28_B*1*tt_rb -> 8.4 | G115: =u_rb_28*(1+g29_rb)*um29_B*1*tt_rb -> 10.26375
...

Sheet Val
A1: Val — P/E 估值（新台幣）。結論用「現價 ÷ FY2027、FY2028 EPS（模型）」與十年 P/E 規則值（年底落後 P/E，基準為各情境 FY2027 EPS）。本版未做先驗，無 Andy 合理 P/E 對照
A2: 循環位置：京元電是測試代工，不是設備股，不套設備市場見頂年；以本模型營收最高的會計年度為見頂年（比照 NVIDIA、台達電、台光電；FY(t)＝CY(t)）。營收到 FY2029 仍在增加時，見頂年未知，判為中段
A4: 0. 目標價
A5: 0.1 DCF（股東權益現金流，FY2027–FY2032 明確期＋FY2032 後永續）
A6: 項目 | B6: A（順利） | C6: B（平平） | D6: C（不如預期） | E6: 說明
A7: 情境 EPS（FY2027–FY2032） | E7: PL 頁各情境；FY2030 起為收斂法（PL 頁灰底）
A8: FY2027 | B8: =PL!E15 -> 11.169367 | C8: =PL!E29 -> 11.169367 | D8: =PL!E43 -> 11.169367
A9: FY2028 | B9: =PL!F15 -> 11.095884 | C9: =PL!F29 -> 9.0297131 | D9: =PL!F43 -> 6.1713519
A10: FY2029 | B10: =PL!G15 -> 12.20276 | C10: =PL!G29 -> 11.057651 | D10: =PL!G43 -> 7.5305129
A11: FY2030 | B11: =PL!H15 -> 13.021997 | C11: =PL!H29 -> 11.500594 | D11: =PL!H43 -> 7.3798774
A12: FY2031 | B12: =PL!I15 -> 13.849774 | C12: =PL!I29 -> 11.747621 | D12: =PL!I43 -> 7.0925771
A13: FY2032 | B13: =PL!J15 -> 14.680761 | C13: =PL!J29 -> 11.781186 | D13: =PL!J43 -> 6.6779341
A14: 股東現金流＝EPS ×（1 − tp_g ÷ tp_roe）
A15: 再投資率（tp_g ÷ tp_roe，上限 0.8） | B15: =IF(tp_roe<=tp_g,0.8,MIN(tp_g/tp_roe,0.8)) -> 0.21641118 | E15: ROE＝In 頁 tp_roe；tp_roe ≤ tp_g 時取上限 0.8
A16: FY2027 | B16: =B8*(1-$B$15) -> 8.7521915 | C16: =C8*(1-$B$15) -> 8.7521915 | D16: =D8*(1-$B$15) -> 8.7521915
A17: FY2028 | B17: =B9*(1-$B$15) -> 8.6946109 | C17: =C9*(1-$B$15) -> 7.0755822 | D17: =D9*(1-$B$15) -> 4.8358023
A18: FY2029 | B18: =B10*(1-$B$15) -> 9.5619465 | C18: =C10*(1-$B$15) -> 8.6646515 | D18: =D10*(1-$B$15) -> 5.9008257
A19: FY2030 | B19: =B11*(1-$B$15) -> 10.203891 | C19: =C11*(1-$B$15) -> 9.0117372 | D19: =D11*(1-$B$15) -> 5.7827894
A20: FY2031 | B20: =B12*(1-$B$15) -> 10.852528 | C20: =C12*(1-$B$15) -> 9.2053044 | D20: =D12*(1-$B$15) -> 5.5576641
A21: FY2032 | B21: =B13*(1-$B$15) -> 11.50368 | C21: =C13*(1-$B$15) -> 9.2316053 | D21: =D13*(1-$B$15) -> 5.2327545
A22: DCF 情境每股價值（折現率 tp_r） | B22: =SUMPRODUCT(B16:B21,1/(1+tp_r)^{1;2;3;4;5;6})+B21*(1+tp_g)/(tp_r-tp_g)/(1+tp_r)^6 -> 155.08216 | C22: =SUMPRODUCT(C16:C21,1/(1+tp_r)^{1;2;3;4;5;6})+C21*(1+tp_g)/(tp_r-tp_g)/(1+tp_r)^6 -> 127.71992 | D22: =SUMPRODUCT(D16:D21,1/(1+tp_r)^{1;2;3;4;5;6})+D21*(1+tp_g)/(tp_r-tp_g)/(1+tp_r)^6 -> 77.939189 | E22: Σ 明確期現金流 ÷ (1＋r)^t ＋ 永續價值 ÷ (1＋r)^6；永續價值＝FY2032 現金流 ×(1＋g)÷(r−g)；基準日 2026 年底，t＝1 對 FY2027
A23: DCF 情境價值推到 12 個月後（×(1＋tp_r)） | B23: =B22*(1+tp_r) -> 170.59038 | C23: =C22*(1+tp_r) -> 140.49192 | D23: =D22*(1+tp_r) -> 85.733108
A24: DCF 目標價（情境加權） | B24: =tp_wA*B23+tp_wB*C23+tp_wC*D23 -> 138.56969 | E24: Σ 權重 × 情境價值 ×(1＋r)；權重見 In 頁
A26: 0.2 Comparable（市場主流同業前瞻 P/E）
A27: 同業與前瞻 P/E | B27: 代號 | C27: 前瞻 12 月 P/E | D27: 日期 | E27: 來源 | F27: 標記
A28: 日月光投控（ASE Technology） | B28: ASX／3711.TW | C28: 27.37 | D28: 2026-10-23 | E28: stockanalysis forward PE（ASX；分析師共識） | F28: Interested-party
A29: Amkor Technology | B29: AMKR | C29: 14.02 | D29: 2026-10-23 | E29: stockanalysis forward PE（分析師共識） | F29: Interested-party
A30: 力成（Powertech） | B30: 6239.TW | C30: 20.6 | D30: 2026-10-02 | E30: stockanalysis forward PE（頁面價格日期較舊） | F30: Interested-party
A31: 矽格（Sigurd） | B31: 6257.TW | C31: 23.3 | D31: 2026-10-02 | E31: stockanalysis forward PE（頁面價格日期較舊） | F31: Interested-party
A32: 南茂（ChipMOS） | B32: IMOS／8150.TW | C32: 22.08 | D32: 2026-10-08 | E32: stockanalysis forward PE（IMOS；頁面價格日期較舊） | F32: Interested-party
A33: 同業前瞻 P/E 中位數 | B33: =MEDIAN(C28:C32) -> 22.08 | E33: 台美封測同業（不放 A 股：長電、通富等 A 股同業有結構性溢價；工作單 Andy 11:53）
A34: 12 個月後的前瞻 EPS（情境加權） | B34: =tp_wA*(2/12*B8+10/12*B9)+tp_wB*(2/12*C8+10/12*C9)+tp_wC*(2/12*D8+10/12*D9) -> 9.4264714 | E34: 約 2027-10 時的未來 12 月 EPS ≈ 2／12 × FY2027＋10／12 × FY2028（會計年度＝日曆年；配股後股數）
A35: Comparable 目標價 | B35: =B33*B34 -> 208.13649 | E35: 同業中位數 × 前瞻 EPS
A37: 0.3 結論
A38: 項目 | B38: 數值 | E38: 說明
A39: 目標價（DCF 與 Comparable 加權） | B39: =tp_w_dcf*B24+(1-tp_w_dcf)*B35 -> 173.35309 | E39: tp_w_dcf × DCF＋（1 − tp_w_dcf）× Comparable；tp_w_dcf 見 In 頁
A40: Comparable 目標價（市場主流同業法） | B40: =B35 -> 208.13649
A41: 市場共識目標價 | B41: =cons_tp -> 340.73 | E41: stockanalysis：15 位分析師平均 340.73（頁面價格日期 2026-10-06）；法人中位數 348–350、Morgan Stanley 388
A42: 上檔空間：加權目標價 | B42: =B39/px-1 -> -0.33960727 | E42: 現價＝In 頁 px
A43: 上檔空間：Comparable 目標價 | B43: =B40/px-1 -> -0.20709909
A44: 與市場共識目標價的差距：EPS 因素 | B44: =B34/cons_feps-1 -> -0.42342942 | E44: 本模型前瞻 EPS ÷ 共識前瞻 EPS − 1；共識前瞻 EPS＝In 頁 cons_feps（FactSet 2026-04-06，換成配股後股數）
A45: 與市場共識目標價的差距：倍數因素 | B45: =(cons_tp/cons_feps)/B33-1 -> -0.056124683 | E45: ="共識目標價隱含 "&TEXT(cons_tp/cons_feps,"0.0")&"x，同業中位數 "&TEXT(B33,"0.0")&"x" -> 共識目標價隱含 20.8x，同業中位數 22.1x
A46: 價格帶（DCF 不如預期～順利） | B46: =TEXT(D23,"#,##0.0")&"～"&TEXT(B23,"#,##0.0") -> 85.7～170.6 | E46: C 情境價值～A 情境價值（推到 12 個月後）
A47: 歷史倍數檢查：現價隱含 P/E 的十年分位（A／B／C） | B47: =IF(px/B9>MAX($B$92:$B$101),1,IF(px/B9<MIN($B$92:$B$101),0,PERCENTRANK($B$92:$B$101,px/B9))) -> 0.956 | C47: =IF(px/C9>MAX($B$92:$B$101),1,IF(px/C9<MIN($B$92:$B$101),0,PERCENTRANK($B$92:$B$101,px/C9))) -> 1 | D47: =IF(px/D9>MAX($B$92:$B$101),1,IF(px/D9<MIN($B$92:$B$101),0,PERCENTRANK($B$92:$B$101,px/D9))) -> 1 | E47: 現價 ÷ 各情境 FY2028 EPS 在 2016–2025 年底 P/E（第 6 節採用來源）的分位；高於十年最大值＝100%；只作檢查，不進目標價
A48: 目標價方法 | B48: DCF：股東現金流＝EPS ×（1 − g／ROE），r＝10%、g＝4%、ROE 為近三年平均約 18%（玩股網；2025 含處分利益，偏高，再投資率約 22%），FY2027–32 明確期＋永續，FY2030 起為收斂法。京元電為資本密集的測試代工，模型有資本支出與折舊，但 FY2030 起只有收斂法、未延伸資本支出，未改用淨利＋折舊－資本支出；2026–27 年大幅擴產期的現金流偏高估。Comparable：台美封測同業（日月光、Amkor、力成、矽格、南茂）前瞻 P/E 中位數；京元電以 AI 測試為主、成長較高，同業中位數偏低估。情境對應：顆數情境 A＝順利、B＝平平、C＝不如預期；FY2027 三情境 EPS 相同（差異從 CY2028 起）。
A51: 1. 價格與市場隱含倍數
A52: 項目 | B52: A | C52: B | D52: C | E52: 說明
A53: 現價（2026-10-22 收盤） | B53: =px -> 262.5
A54: 現價 ÷ FY2026 EPS（錨點） | B54: =px/PL!D15 -> 31.566865 | C54: =px/PL!D29 -> 31.566865 | D54: =px/PL!D43 -> 31.566865 | E54: FY2026 起以配股後股數計
A55: 現價 ÷ FY2027 EPS（模型） | B55: =px/PL!E15 -> 23.501778 | C55: =px/PL!E29 -> 23.501778 | D55: =px/PL!E43 -> 23.501778 | E55: FY2027 三情境相同（顆數係數從 CY2028 開始）
A56: 現價 ÷ FY2028 EPS（模型） | B56: =px/PL!F15 -> 23.65742 | C56: =px/PL!F29 -> 29.070691 | D56: =px/PL!F43 -> 42.535251
A57: 現價 ÷ FY2029 EPS（模型） | B57: =px/PL!G15 -> 21.511526 | C57: =px/PL!G29 -> 23.73922 | D57: =px/PL!G43 -> 34.858183
A58: 未來 12 月 EPS（模型 A）≈ ¼ FY2026＋¾ FY2027 | B58: =0.25*PL!D15+0.75*PL!E15 -> 10.455946
A59: 現價 ÷ 未來 12 月 EPS（模型 A） | B59: =px/B58 -> 25.105332
A60: 近 12 月 P/E（鉅亨網，10-22） | B60: =pe_ttm -> 36.13
A62: 2. 循環位置（本模型營收最高年；FY(t)＝CY(t)）
A63: 情境 | B63: 營收最高年（FY2026–FY2029） | C63: FY2027 判定 | D63: 規則倍數（P/E） | E63: 見頂年是否未知 | F63: 說明
A64: A | B64: =INDEX({2026,2027,2028,2029},MATCH(MAX(PL!D81:G81),PL!D81:G81,0)) -> 2029 | C64: =IF(B64=2029,"中段",IF(2027<B64,"中段",IF(2027=B64,"見頂","谷底"))) -> 中段 | D64: =IF(C64="見頂",pe_peak,IF(C64="谷底",pe_trough,pe_mid)) -> 15.45 | E64: =IF(B64=2029,"是：營收到觀測期末仍在增加","否") -> 是：營收到觀測期末仍在增加 | F64: tools/cycle_position.py excel_rule；營收最高年取代設備市場見頂年
A65: B | B65: =INDEX({2026,2027,2028,2029},MATCH(MAX(PL!D132:G132),PL!D132:G132,0)) -> 2029 | C65: =IF(B65=2029,"中段",IF(2027<B65,"中段",IF(2027=B65,"見頂","谷底"))) -> 中段 | D65: =IF(C65="見頂",pe_peak,IF(C65="谷底",pe_trough,pe_mid)) -> 15.45 | E65: =IF(B65=2029,"是：營收到觀測期末仍在增加","否") -> 是：營收到觀測期末仍在增加 | F65: 同上
A66: C | B66: =INDEX({2026,2027,2028,2029},MATCH(MAX(PL!D183:G183),PL!D183:G183,0)) -> 2027 | C66: =IF(B66=2029,"中段",IF(2027<B66,"中段",IF(2027=B66,"見頂","谷底"))) -> 見頂 | D66: =IF(C66="見頂",pe_peak,IF(C66="谷底",pe_trough,pe_mid)) -> 10.87 | E66: =IF(B66=2029,"是：營收到觀測期末仍在增加","否") -> 否 | F66: 同上
A68: 3. 規則值隱含股價（新台幣；約 FY2027 年底，未折現）＝ FY2027 EPS × 規則倍數
A69: 情境 | B69: FY2027 EPS | C69: （同左） | D69: 規則倍數 | E69: 隱含股價 | F69: 相對現價 | G69: 現價 ÷ FY2027 EPS
A70: A | B70: =PL!E15 -> 11.169367 | C70: =B70 -> 11.169367 | D70: =D64 -> 15.45 | E70: =C70*D70 -> 172.56673 | F70: =E70/px-1 -> -0.34260294 | G70: =px/C70 -> 23.501778
A71: B | B71: =PL!E29 -> 11.169367 | C71: =B71 -> 11.169367 | D71: =D65 -> 15.45 | E71: =C71*D71 -> 172.56673 | F71: =E71/px-1 -> -0.34260294 | G71: =px/C71 -> 23.501778
A72: C | B72: =PL!E43 -> 11.169367 | C72: =B72 -> 11.169367 | D72: =D66 -> 10.87 | E72: =C72*D72 -> 121.41102 | F72: =E72/px-1 -> -0.53748181 | G72: =px/C72 -> 23.501778
A74: 4. What must be true：FY2027 年底價 ＝ 現價 ×（1＋報酬）所需的倍數（FY2028 EPS；約 2027 年底的價格看下一年 EPS）
A75: FY2027 年底價 ÷ 現價 | B75: 所需倍數（÷ FY2028 EPS，A） | C75: 所需倍數（÷ FY2028 EPS，C） | D75: 對照：十年中位數 | E75: 對照：十年 75 分位
A76: 0.5 | B76: =px*A76/PL!F15 -> 11.82871 | C76: =px*A76/PL!F43 -> 21.267625 | D76: =pe_mid -> 15.45 | E76: =pe_trough -> 17.17
A77: 0.75 | B77: =px*A77/PL!F15 -> 17.743065 | C77: =px*A77/PL!F43 -> 31.901438 | D77: =pe_mid -> 15.45 | E77: =pe_trough -> 17.17
A78: 1 | B78: =px*A78/PL!F15 -> 23.65742 | C78: =px*A78/PL!F43 -> 42.535251 | D78: =pe_mid -> 15.45 | E78: =pe_trough -> 17.17
A79: 1.21 | B79: =px*A79/PL!F15 -> 28.625479 | C79: =px*A79/PL!F43 -> 51.467653 | D79: =pe_mid -> 15.45 | E79: =pe_trough -> 17.17
A80: 1.5 | B80: =px*A80/PL!F15 -> 35.486131 | C80: =px*A80/PL!F43 -> 63.802876 | D80: =pe_mid -> 15.45 | E80: =pe_trough -> 17.17
A81: 讀法：1.00＝價格不變、1.21＝一年約 21%。所需倍數遠高於歷史中位數時，現價依賴「AI 期倍數高於 2016–2022 年」與 FY2028 以後的成長延續；倍數是否合理，另看前瞻 P/E 歷史（Bloomberg）。
A87: 6. 十年倍數與規則值（2016–2025 年底；見頂年 25 分位、中段中位數、谷底 75 分位）
A88: 規則（Andy 2026-10-13）：合理倍數＝2016–2025 年底 P/E 依循環位置取分位。採用一個來源（年底收盤 ÷ 當年 EPS，Derived，10 年）；stockanalysis、HiStock 只有 2021–2025，與採用值同量級，只作核對。2016–2022 年京元電以手機、消費性晶片測試為主（約 6–16x），AI 前後倍數口徑不同；2025 年 EPS 含處分利益（每股約 2 元）使當年 P/E 偏低。兩者都使規則值可能低估 AI 期的合理倍數。
A90: P/E：十年歷史倍數
A91: 年底 | B91: 年底收盤 ÷ 當年 EPS（Yahoo Finance 12 月收盤 × 1.05、玩股網／HiStock EPS） | C91: stockanalysis 年度 P/E | D91: HiStock 12 月本益比 | E91: 標記／說明
A92: 2016 | B92: =24*1.05/2.56 -> 9.84375 | E92: 年底收盤 ÷ 當年 EPS（Yahoo Finance 12 月收盤 × 1.05、玩股網／HiStock EPS）：Derived（2016–2025 共 10 年，皆為正值且小於 200，無剔除；Yahoo 收盤已因 2026 年配股 5% 下調，乘 1.05 還原）；stockanalysis 年度 P/E：Interested-party（資料商；只有 2021–2025，只作核對，不採用）；HiStock 12 月本益比：Interested-party（資料商；近四季 EPS 口徑；只有 2021–2025，不採用）
A93: 2017 | B93: =28.81*1.05/1.88 -> 16.090691
A94: 2018 | B94: =22.14*1.05/1.47 -> 15.814286
A95: 2019 | B95: =35.76*1.05/2.49 -> 15.079518
A96: 2020 | B96: =33.1*1.05/2.97 -> 11.70202
A97: 2021 | B97: =42.67*1.05/4.23 -> 10.591844 | C97: 10.59 | D97: 12.95
A98: 2022 | B98: =34.48*1.05/5.59 -> 6.4765653 | C98: 6.47 | D98: 6.35
A99: 2023 | B99: =80.86*1.05/4.78 -> 17.762134 | C99: 17.77 | D99: 17.99
A100: 2024 | B100: =106.19*1.05/6.36 -> 17.531368 | C100: 17.52 | D100: 18.65
A101: 2025 | B101: =235.71*1.05/9.01 -> 27.468979 | C101: 27.47 | D101: 28.03
A102: 25 分位（各來源） | B102: =PERCENTILE(B92:B101,0.25) -> 10.869388 | C102: =PERCENTILE(C92:C101,0.25) -> 10.59 | D102: =PERCENTILE(D92:D101,0.25) -> 12.95
A103: 中位數（各來源） | B103: =MEDIAN(B92:B101) -> 15.446902 | C103: =MEDIAN(C92:C101) -> 17.52 | D103: =MEDIAN(D92:D101) -> 17.99
A104: 75 分位（各來源） | B104: =PERCENTILE(B92:B101,0.75) -> 17.171199 | C104: =PERCENTILE(C92:C101,0.75) -> 17.77 | D104: =PERCENTILE(D92:D101,0.75) -> 18.65
A105: 最小（各來源） | B105: =MIN(B92:B101) -> 6.4765653 | C105: =MIN(C92:C101) -> 6.47 | D105: =MIN(D92:D101) -> 6.35
A106: 最大（各來源） | B106: =MAX(B92:B101) -> 27.468979 | C106: =MAX(C92:C101) -> 27.47 | D106: =MAX(D92:D101) -> 28.03
A107: 採用 25 分位（P/E） | B107: =ROUND(AVERAGE(B102),2) -> 10.87
A108: 採用 中位數（P/E） | B108: =ROUND(AVERAGE(B103),2) -> 15.45
A109: 採用 75 分位（P/E） | B109: =ROUND(AVERAGE(B104),2) -> 17.17
A110: 採用 最小（P/E） | B110: =ROUND(MIN(B105),2) -> 6.48
A111: 採用 最大（P/E） | B111: =ROUND(MAX(B106),2) -> 27.47
A113: P/E：規則值
A114: 情形 | B114: 循環位置 | C114: 倍數 | D114: 基準 | E114: 每股基準 | F114: 隱含股價 | G114: 相對目前 | H114: 現價 ÷ 基準
A115: 規則值：見頂（P/E） | B115: 25 分位 | C115: =B107 -> 10.87 | D115: FY2027 EPS（A） | E115: =C70 -> 11.169367 | F115: =C115*E115 -> 121.41102 | G115: =F115/px-1 -> -0.53748181 | H115: =px/E115 -> 23.501778
...

Sheet Recon
A1: Recon — 本模型 vs 共識、券商估計與公司揭露的結構數字。只作事後對照，不為對上數字而調參數。共識為 FactSet（2026-04-06，經鉅亨網）與媒體轉述的法人估計
A3: 項目 | B3: 對照值 | C3: 模型 A | D3: 差距 A | E3: 模型 B | F3: 差距 B | G3: 模型 C | H3: 差距 C | I3: 對照來源 | J3: 說明
A4: A. 共識與法人估計（校準未使用）
A5: FY2026 營收 vs 法人（近 500 億） | B5: =c_rev26 -> 49.25 | C5: =PL!D81 -> 47.439355 | D5: =C5/B5-1 -> -0.036764372 | E5: =PL!D132 -> 47.439355 | F5: =E5/B5-1 -> -0.036764372 | G5: =PL!D183 -> 47.439355 | H5: =G5/B5-1 -> -0.036764372 | I5: 理財周刊 2026-09-01 | J5: 模型 4Q 季增 15%；法人約 20%
A6: 4Q26 營收 vs 法人估計 | B6: =c_q4rev -> 14.559 | C6: =Q!E4 -> 13.963597 | D6: =C6/B6-1 -> -0.040895893 | E6: =Q!E4 -> 13.963597 | F6: =E6/B6-1 -> -0.040895893 | G6: =Q!E4 -> 13.963597 | H6: =G6/B6-1 -> -0.040895893 | I6: 優分析 2026-09-18
A7: FY2026 EPS vs FactSet 中位數（04-06） | B7: =c_eps26 -> 9.9 | C7: =PL!D107 -> 8.3156815 | D7: =C7/B7-1 -> -0.16003217 | E7: =PL!D158 -> 8.3156815 | F7: =E7/B7-1 -> -0.16003217 | G7: =PL!D209 -> 8.3156815 | H7: =G7/B7-1 -> -0.16003217 | I7: FactSet（鉅亨網） | J7: 模型以配股後股數計；下一列換回配股前口徑
A8: FY2026 EPS（× 1.05，配股前口徑）vs FactSet 中位數 | B8: =c_eps26 -> 9.9 | C8: =PL!D107*1.05 -> 8.7314656 | D8: =C8/B8-1 -> -0.11803378 | E8: =PL!D158*1.05 -> 8.7314656 | F8: =E8/B8-1 -> -0.11803378 | G8: =PL!D209*1.05 -> 8.7314656 | H8: =G8/B8-1 -> -0.11803378 | I8: 同上 | J8: 共識的股數口徑未載明（推定為配股前）
A9: FY2026 EPS（× 1.05）vs 法人中位數區間中點（09-01） | B9: =c_eps26b -> 9.44 | C9: =PL!D107*1.05 -> 8.7314656 | D9: =C9/B9-1 -> -0.075056609 | E9: =PL!D158*1.05 -> 8.7314656 | F9: =E9/B9-1 -> -0.075056609 | G9: =PL!D209*1.05 -> 8.7314656 | H9: =G9/B9-1 -> -0.075056609 | I9: 理財周刊 2026-09-01 | J9: 3Q Rubin 延後後的估計
A10: FY2027 EPS vs FactSet 中位數（04-06） | B10: =c_eps27 -> 14.4 | C10: =PL!E107 -> 11.169367 | D10: =C10/B10-1 -> -0.22434948 | E10: =PL!E158 -> 11.169367 | F10: =E10/B10-1 -> -0.22434948 | G10: =PL!E209 -> 11.169367 | H10: =G10/B10-1 -> -0.22434948 | I10: FactSet（鉅亨網）
A11: FY2027 EPS（× 1.05）vs FactSet 中位數 | B11: =c_eps27 -> 14.4 | C11: =PL!E107*1.05 -> 11.727836 | D11: =C11/B11-1 -> -0.18556695 | E11: =PL!E158*1.05 -> 11.727836 | F11: =E11/B11-1 -> -0.18556695 | G11: =PL!E209*1.05 -> 11.727836 | H11: =G11/B11-1 -> -0.18556695 | I11: 同上 | J11: 高 16.05、低 13.35
A12: FY2028 EPS（× 1.05）vs FactSet 中位數 | B12: =c_eps28 -> 17.72 | C12: =PL!F107*1.05 -> 11.650678 | D12: =C12/B12-1 -> -0.3425125 | E12: =PL!F158*1.05 -> 9.4811988 | F12: =E12/B12-1 -> -0.46494364 | G12: =PL!F209*1.05 -> 6.4799195 | H12: =G12/B12-1 -> -0.63431606 | I12: 同上 | J12: 高 18.77、低 16.67
A13: 目標價（DCF 與 Comparable 加權，Val 第 0 節）vs Morgan Stanley 目標價 | B13: =ms_tp -> 388 | C13: =tp_final -> 173.35309 | D13: =C13/B13-1 -> -0.55321368 | E13: =tp_final -> 173.35309 | F13: =E13/B13-1 -> -0.55321368 | G13: =tp_final -> 173.35309 | H13: =G13/B13-1 -> -0.55321368 | I13: Morgan Stanley 2026-06-23 | J13: 三情境同一個加權目標價；券商目標價多以 25–30 倍前瞻 P/E 計
A14: B. 結構與機制檢查
A15: FY2026 Google TPU 測試 ÷ 營收 vs Morgan Stanley Google 相關 10% | B15: =ms_goog -> 0.1 | C15: =PL!D68/PL!D74*PL!D79/PL!D81 -> 0.054788796 | D15: =C15-B15 -> -0.045211204 | E15: =PL!D119/PL!D125*PL!D130/PL!D132 -> 0.054788796 | F15: =E15-B15 -> -0.045211204 | G15: =PL!D170/PL!D176*PL!D181/PL!D183 -> 0.054788796 | H15: =G15-B15 -> -0.045211204 | I15: Morgan Stanley 2026-06-23 | J15: 對照值含 Google CPU、晶圓測試，口徑較寬；模型應低於對照值
A16: FY2026 AI 加速器測試占比 vs 公司 2Q26 資料處理應用占比 | B16: =dp_26 -> 0.363 | C16: =PL!D83 -> 0.35 | D16: =C16-B16 -> -0.013 | E16: =PL!D134 -> 0.35 | F16: =E16-B16 -> -0.013 | G16: =PL!D185 -> 0.35 | H16: =G16-B16 -> -0.013 | I16: poorstock 摘要公司簡報 | J16: 資料處理含 AI GPU、ASIC 與 CPU；AI 占比應不高於此值
A17: FY2026 折舊公式回測（同一公式 − 錨點，NT$B） | C17: =PL!D92 -> -0.099495045 | E17: =PL!D143 -> -0.099495045 | G17: =PL!D194 -> -0.099495045 | I17: Q 頁、In 頁 dr、ret | J17: 接近 0 表示折舊率與到期比例和 FY2025–26 一致（校準檢查）
A18: FY2026 資本支出：公式值（維持性＋κ × FY2026 營收增量）vs 輸入 capex_26 | B18: =capex_26 -> 42 | C18: =m_cx*PL!D81+PL!C87*MAX(0,PL!D81-PL!C81) -> 49.42503 | D18: =C18/B18-1 -> 0.17678643 | E18: =m_cx*PL!D132+PL!C138*MAX(0,PL!D132-PL!C132) -> 49.42503 | F18: =E18/B18-1 -> 0.17678643 | G18: =m_cx*PL!D183+PL!C189*MAX(0,PL!D183-PL!C183) -> 49.42503 | H18: =G18/B18-1 -> 0.17678643 | I18: In 頁 capex_26（公司預算 500 億的現金口徑） | J18: 公式值接近預算 500 億、高於現金口徑輸入；差距反映預算與現金支出的時間差
A19: FY2027 每顆 Blackwell 等值 AI 測試營收（US$） | C19: =PL!E85 -> 43.64726 | E19: =PL!E136 -> 43.64726 | G19: =PL!E187 -> 43.64726 | I19: —
A20: FY2027 資本支出 ÷ 營收 | C20: =PL!E89 -> 0.85670569 | E20: =PL!E140 -> 0.85670569 | G20: =PL!E191 -> 0.85670569 | I20: — | J20: FY2025 92.6%、FY2026 預算約 105%（現金基準約 88%）
A21: FY2028 折舊攤提 ÷ 營收 | C21: =PL!F91 -> 0.29659086 | E21: =PL!F142 -> 0.30887515 | G21: =PL!F193 -> 0.34029294 | I21: — | J21: FY2025 21.5%
A22: FY2028 EBITDA − 資本支出（NT$B） | C22: =PL!F103 -> 13.495297 | E22: =PL!F154 -> 26.145152 | G22: =PL!F205 -> 22.305187 | I22: — | J22: 負值＝擴產仍需外部資金
A23: Burn-in 占營收（3Q25，公司法說） | B23: =bi_25 -> 0.09 | C23: =bi_25 -> 0.09 | E23: =bi_25 -> 0.09 | G23: =bi_25 -> 0.09 | I23: 富果 2025-11-28（AI 摘要） | J23: 本模型未拆 burn-in；Rubin 世代的 burn-in 加長含在測試時間係數內
A24: C. 預留
A25: 3Q26 財報（約 11 月上旬）：更新 Q 頁 3Q 毛利率、折舊、營業費用與淨利，並檢查 4Q 季增假設 | J25: 預留列：本版無數值
A26: R4 產業部署路徑（markets/deploy_path/，尚未建立）：上線後以部署路徑取代顆數輸入 | J26: 預留列：本版無數值

Sheet Sens
A1: Sens — 一次動一個輸入（情境 A；每加權顆營收、固定現金成本、κ 在每個案例內依 FY2026 錨點重算，FY2026 恆等於錨點）：對 FY2027、FY2028 的營收、AI 測試營收、毛利率與 EPS 的影響。每個案例是一個完整推導區塊（本頁下方）
A3: 案例 | B3: 設定 | C3: FY2027 營收 | D3: FY2027 AI 測試 | E3: FY2027 毛利率 | F3: FY2027 EPS | G3: FY2027 EPS 相對基準 | H3: FY2028 營收 | I3: FY2028 AI 測試 | J3: FY2028 毛利率 | K3: FY2028 EPS | L3: FY2028 EPS 相對基準
A4: 基準（情境 A） | B4: PL 區塊 A | C4: =PL!E81 -> 60.186472 | D4: =PL!E79 -> 25.650622 | E4: =PL!E97 -> 0.40133688 | F4: =PL!E107 -> 11.169367 | G4: =F4/F$4-1 -> 0 | H4: =PL!F81 -> 64.71214 | I4: =PL!F79 -> 27.75878 | J4: =PL!F97 -> 0.37648524 | K4: =PL!F107 -> 11.095884 | L4: =K4/K$4-1 -> 0
A5: 測試時間係數 低 | B5: 全部平台取低值（Rubin 1.2、Rubin Ultra 1.5、TPU 0.7） | C5: =E61 -> 57.983859 | D5: =E59 -> 23.448009 | E5: =E77 -> 0.39402159 | F5: =E87 -> 10.424207 | G5: =F5/F$4-1 -> -0.066714633 | H5: =F61 -> 61.407759 | I5: =F59 -> 24.454399 | J5: =F77 -> 0.37209488 | K5: =F87 -> 10.265139 | L5: =K5/K$4-1 -> -0.074869634
A6: 測試時間係數 高 | B6: 全部平台取高值（Rubin 1.8、Rubin Ultra 2.6、TPU 1.2） | C6: =E112 -> 61.886699 | D6: =E110 -> 27.350849 | E6: =E128 -> 0.40662754 | F6: =E138 -> 11.744567 | G6: =F6/F$4-1 -> 0.051497937 | H6: =F112 -> 67.510096 | I6: =F110 -> 30.556736 | J6: =F128 -> 0.38034866 | K6: =F138 -> 11.822033 | L6: =K6/K$4-1 -> 0.0654431
A7: ASIC 曝險 低 | B7: AMD 0.1、TPU 0.3、Trainium 0.2、其他 0.2 | C7: =E163 -> 59.974447 | D7: =E161 -> 25.438596 | E7: =E179 -> 0.40065607 | F7: =E189 -> 11.097638 | G7: =F7/F$4-1 -> -0.0064220118 | H7: =F163 -> 64.232942 | I7: =F161 -> 27.279582 | J7: =F179 -> 0.37554651 | K7: =F189 -> 10.961126 | L7: =K7/K$4-1 -> -0.012144845
A8: ASIC 曝險 高 | B8: AMD 0.4、TPU 0.7、Trainium 0.6、其他 0.6 | C8: =E214 -> 60.389859 | D8: =E212 -> 25.854009 | E8: =E230 -> 0.40198545 | F8: =E240 -> 11.238175 | G8: =F8/F$4-1 -> 0.0061603551 | H8: =F214 -> 65.168121 | I8: =F212 -> 28.214761 | J8: =F230 -> 0.37736073 | K8: =F240 -> 11.223923 | L8: =K8/K$4-1 -> 0.011539313
A9: 份額流失（低） | B9: 份額相對值 2027 0.88、2028 0.80、2029 0.75（日月光、Amkor 擴 GPU 測試） | C9: =E265 -> 58.296426 | D9: =E263 -> 23.760576 | E9: =E281 -> 0.39509334 | F9: =E291 -> 10.529951 | G9: =F9/F$4-1 -> -0.057247334 | H9: =F265 -> 61.091429 | I9: =F263 -> 24.13807 | J9: =F281 -> 0.36995833 | K9: =F291 -> 10.116526 | L9: =K9/K$4-1 -> -0.088263161
A10: 份額持平（高） | B10: 份額相對值 2027–29 1.00 | C10: =E316 -> 61.536505 | D10: =E314 -> 27.000655 | E10: =E332 -> 0.40556173 | F10: =E342 -> 11.626094 | G10: =F10/F$4-1 -> 0.040890953 | H10: =F316 -> 67.125947 | I10: =F314 -> 30.172587 | J10: =F332 -> 0.38018067 | K10: =F342 -> 11.737761 | L10: =K10/K$4-1 -> 0.057848198
A11: 測試單價下滑快 | B11: 單價指數 2027 0.95、2028 0.90、2029 0.88 | C11: =E367 -> 59.401249 | D11: =E365 -> 24.865399 | E11: =E383 -> 0.39609349 | F11: =E393 -> 10.798774 | G11: =F11/F$4-1 -> -0.03317946 | H11: =F367 -> 62.977216 | I11: =F365 -> 26.023856 | J11: =F383 -> 0.36733468 | K11: =F393 -> 10.373755 | L11: =K11/K$4-1 -> -0.065080823
A12: 測試單價持平 | B12: 單價指數 2027 1.02、2028–29 1.00 | C12: =E418 -> 61.233436 | D12: =E416 -> 26.697586 | E12: =E434 -> 0.40811888 | F12: =E444 -> 11.663492 | G12: =F12/F$4-1 -> 0.04423928 | H12: =F418 -> 65.868756 | I12: =F416 -> 28.915396 | J12: =F434 -> 0.38074897 | K12: =F444 -> 11.508144 | L12: =K12/K$4-1 -> 0.037154309
A13: AI 部署 ×0.8 | B13: FY2027 起加速器顆數 ×0.8 | C13: =E469 -> 55.056348 | D13: =E467 -> 20.520498 | E13: =E485 -> 0.38339282 | F13: =E495 -> 9.4338084 | G13: =F13/F$4-1 -> -0.15538562 | H13: =F469 -> 59.160384 | I13: =F467 -> 22.207024 | J13: =F485 -> 0.37359854 | K13: =F495 -> 9.888452 | L13: =K13/K$4-1 -> -0.10881804
A14: AI 部署 ×1.2 | B14: ×1.2 | C14: =E520 -> 65.316597 | D14: =E518 -> 30.780746 | E14: =E536 -> 0.4164622 | F14: =E546 -> 12.904927 | G14: =F14/F$4-1 -> 0.15538562 | H14: =F520 -> 70.263896 | I14: =F518 -> 33.310536 | J14: =F536 -> 0.37891577 | K14: =F546 -> 12.303415 | L14: =K14/K$4-1 -> 0.1088269
A15: FY2026 AI 占比 28% | B15: 校準用 AI 占比取低值（非 AI 基期較大） | C15: =E571 -> 58.775593 | D15: =E569 -> 20.520498 | E15: =E587 -> 0.39697249 | F15: =E597 -> 10.701998 | G15: =F15/F$4-1 -> -0.04184383 | H15: =F571 -> 63.139976 | I15: =F569 -> 22.207024 | J15: =F587 -> 0.37611358 | K15: =F597 -> 10.77014 | L15: =K15/K$4-1 -> -0.029357217
A16: FY2026 AI 占比 45% | B16: 取高值 | C16: =E622 -> 62.202014 | D16: =E620 -> 32.979371 | E16: =E638 -> 0.40722827 | F16: =E648 -> 11.837038 | G16: =F16/F$4-1 -> 0.0597769 | H16: =F622 -> 66.958087 | I16: =F620 -> 35.68986 | J16: =F638 -> 0.37698591 | K16: =F648 -> 11.561304 | L16: =K16/K$4-1 -> 0.041945281
A17: 變動現金成本 10% | B17: v＝10%（固定成本占比較高） | C17: =E673 -> 60.186472 | D17: =E671 -> 25.650622 | E17: =E689 -> 0.42338602 | F17: =E699 -> 12.038453 | G17: =F17/F$4-1 -> 0.077809761 | H17: =F673 -> 64.71214 | I17: =F671 -> 27.75878 | J17: =F689 -> 0.40496429 | K17: =F699 -> 12.302818 | L17: =K17/K$4-1 -> 0.10877308
A18: 變動現金成本 30% | B18: v＝30% | C18: =E724 -> 60.186472 | D18: =E722 -> 25.650622 | E18: =E740 -> 0.37928774 | F18: =E750 -> 10.300282 | G18: =F18/F$4-1 -> -0.077809761 | H18: =F724 -> 64.71214 | I18: =F722 -> 27.75878 | J18: =F740 -> 0.3480062 | K18: =F750 -> 9.8889508 | L18: =K18/K$4-1 -> -0.10877308
A19: 折舊率 9% | B19: 新增資本支出年折舊率 9% | C19: =E775 -> 60.186472 | D19: =E773 -> 25.650622 | E19: =E791 -> 0.41688225 | F19: =E801 -> 11.782102 | G19: =F19/F$4-1 -> 0.054858442 | H19: =F775 -> 64.71214 | I19: =F773 -> 27.75878 | J19: =F791 -> 0.40168713 | K19: =F801 -> 12.163933 | L19: =K19/K$4-1 -> 0.096256262
A20: 折舊率 14% | B20: 年折舊率 14%（設備占比較高） | C20: =E826 -> 60.186472 | D20: =E824 -> 25.650622 | E20: =E842 -> 0.37801882 | F20: =E852 -> 10.250266 | G20: =F20/F$4-1 -> -0.082287662 | H20: =F826 -> 64.71214 | I20: =F824 -> 27.75878 | J20: =F842 -> 0.33868242 | K20: =F852 -> 9.4938118 | L20: =K20/K$4-1 -> -0.14438439
A21: 維持性資本支出 6% | B21: 營收的 6% | C21: =E877 -> 60.186472 | D21: =E875 -> 25.650622 | E21: =E893 -> 0.40152192 | F21: =E903 -> 11.176661 | G21: =F21/F$4-1 -> 0.00065299934 | H21: =F877 -> 64.71214 | I21: =F875 -> 27.75878 | J21: =F893 -> 0.37835549 | K21: =F903 -> 11.175145 | L21: =K21/K$4-1 -> 0.007143237
A22: 維持性資本支出 15% | B22: 營收的 15% | C22: =E928 -> 60.186472 | D22: =E926 -> 25.650622 | E22: =E944 -> 0.40110558 | F22: =E954 -> 11.16025 | G22: =F22/F$4-1 -> -0.00081624917 | H22: =F928 -> 64.71214 | I22: =F926 -> 27.75878 | J22: =F944 -> 0.37414743 | K22: =F954 -> 10.996809 | L22: =K22/K$4-1 -> -0.0089290462
A23: 營業費用彈性 0.4 | C23: =E979 -> 60.186472 | D23: =E977 -> 25.650622 | E23: =E995 -> 0.40133688 | F23: =E1005 -> 11.384552 | G23: =F23/F$4-1 -> 0.019265556 | H23: =F979 -> 64.71214 | I23: =F977 -> 27.75878 | J23: =F995 -> 0.37648524 | K23: =F1005 -> 11.387466 | L23: =K23/K$4-1 -> 0.02627838
A24: 營業費用彈性 1.0 | B24: 營業費用與營收同步成長 | C24: =E1030 -> 60.186472 | D24: =E1028 -> 25.650622 | E24: =E1046 -> 0.40133688 | F24: =E1056 -> 10.738999 | G24: =F24/F$4-1 -> -0.038531112 | H24: =F1030 -> 64.71214 | I24: =F1028 -> 27.75878 | J24: =F1046 -> 0.37648524 | K24: =F1056 -> 10.493304 | L24: =K24/K$4-1 -> -0.05430666
A25: 淨利 ÷ 營業利益 0.78 | B25: 利息費用上升 | C25: =E1081 -> 60.186472 | D25: =E1079 -> 25.650622 | E25: =E1097 -> 0.40133688 | F25: =E1107 -> 10.371556 | G25: =F25/F$4-1 -> -0.071428571 | H25: =F1081 -> 64.71214 | I25: =F1079 -> 27.75878 | J25: =F1097 -> 0.37648524 | K25: =F1107 -> 10.303321 | L25: =K25/K$4-1 -> -0.071428571
A26: 淨利 ÷ 營業利益 0.90 | B26: 回到 2025 年水準 | C26: =E1132 -> 60.186472 | D26: =E1130 -> 25.650622 | E26: =E1148 -> 0.40133688 | F26: =E1158 -> 11.967179 | G26: =F26/F$4-1 -> 0.071428571 | H26: =F1132 -> 64.71214 | I26: =F1130 -> 27.75878 | J26: =F1148 -> 0.37648524 | K26: =F1158 -> 11.888447 | L26: =K26/K$4-1 -> 0.071428571
A27: 非 AI 成長 低 | B27: 2027 +4%、2028–29 0% | C27: =E1183 -> 57.719626 | D27: =E1181 -> 25.650622 | E27: =E1199 -> 0.39293208 | F27: =E1209 -> 10.328221 | G27: =F27/F$4-1 -> -0.075308331 | H27: =F1183 -> 59.827784 | I27: =F1181 -> 27.75878 | J27: =F1199 -> 0.36654077 | K27: =F1209 -> 9.7375186 | L27: =K27/K$4-1 -> -0.12242068
A28: 非 AI 成長 高 | B28: 2027 +20%、2028 +12%、2029 +10% | C28: =E1234 -> 62.653319 | D28: =E1232 -> 25.650622 | E28: =E1250 -> 0.40907984 | F28: =E1260 -> 12.010514 | G28: =F28/F$4-1 -> 0.075308331 | H28: =F1234 -> 69.2018 | I28: =F1232 -> 27.75878 | J28: =F1250 -> 0.38381926 | K28: =F1260 -> 12.320651 | L28: =K28/K$4-1 -> 0.1103803
A29: 顆數情境 B | B29: CY2028 ×0.8、CY2029 ×0.85 | C29: =PL!E132 -> 60.186472 | D29: =PL!E130 -> 25.650622 | E29: =PL!E148 -> 0.40133688 | F29: =PL!E158 -> 11.169367 | G29: =F29/F$4-1 -> 0 | H29: =PL!F132 -> 59.160384 | I29: =PL!F130 -> 22.207024 | J29: =PL!F148 -> 0.35307213 | K29: =PL!F158 -> 9.0297131 | L29: =K29/K$4-1 -> -0.18621059
A30: 顆數情境 C | B30: CY2028–29 ×0.6 | C30: =PL!E183 -> 60.186472 | D30: =PL!E181 -> 25.650622 | E30: =PL!E199 -> 0.40133688 | F30: =PL!E209 -> 11.169367 | G30: =F30/F$4-1 -> 0 | H30: =PL!F183 -> 53.608628 | I30: =PL!F181 -> 16.655268 | J30: =PL!F199 -> 0.30822048 | K30: =PL!F209 -> 6.1713519 | L30: =K30/K$4-1 -> -0.44381613
A32: 讀法：FY2027 三情境相同；顆數情境 B、C 的差異從 FY2028 起。資本支出隨當年營收增量擴產；FY2028 顆數下修、營收下滑時只剩維持性資本支出，但固定現金成本與既有折舊不降，毛利率跌幅大於營收。測試單價只改營收、不改成本，對 EPS 的影響大於對營收。
A40: 案例區塊：測試時間係數 低（情境 A）
A41: 項目 | B41: 單位 | C41: FY2025A | D41: FY2026（錨點） | E41: FY2027 | F41: FY2028 | G41: FY2029 | H41: 說明
A42: A. AI 加速器測試需求（加權顆數＝顆數 × 每顆測試時間（含 burn-in）× 京元電曝險；FY(t)＝CY(t)）
A43: NVIDIA Blackwell：加權顆數 | B43: 百萬顆 | D43: =u_bw_26*tt_bw_lo -> 5.4 | E43: =u_bw_27*1*tt_bw_lo -> 2.4 | F43: =u_bw_28*um28_A*1*tt_bw_lo -> 0.5 | G43: =u_bw_28*(1+g29_bw)*um29_A*1*tt_bw_lo -> 0.25
A44: NVIDIA Rubin：加權顆數 | B44: 百萬顆 | D44: =u_rb_26*tt_rb_lo -> 2.04 | E44: =u_rb_27*1*tt_rb_lo -> 8.4 | F44: =u_rb_28*um28_A*1*tt_rb_lo -> 8.4 | G44: =u_rb_28*(1+g29_rb)*um29_A*1*tt_rb_lo -> 9.66
A45: NVIDIA Rubin Ultra：加權顆數 | B45: 百萬顆 | D45: =u_ru_26*tt_ru_lo -> 0 | E45: =u_ru_27*1*tt_ru_lo -> 0.45 | F45: =u_ru_28*um28_A*1*tt_ru_lo -> 3 | G45: =u_ru_28*(1+g29_ru)*um29_A*1*tt_ru_lo -> 3.45
A46: NVIDIA Hopper：加權顆數 | B46: 百萬顆 | D46: =u_hp_26*tt_hp_lo -> 0.25 | E46: =u_hp_27*1*tt_hp_lo -> 0 | F46: =u_hp_28*um28_A*1*tt_hp_lo -> 0 | G46: =u_hp_28*(1+g29_hp)*um29_A*1*tt_hp_lo -> 0
A47: AMD Instinct：加權顆數 | B47: 百萬顆 | D47: =u_amd_26*tt_amd_lo*ex_amd -> 0.135 | E47: =u_amd_27*1*tt_amd_lo*ex_amd -> 0.27 | F47: =u_amd_28*um28_A*1*tt_amd_lo*ex_amd -> 0.36 | G47: =u_amd_28*(1+g29_amd)*um29_A*1*tt_amd_lo*ex_amd -> 0.414
A48: Google TPU：加權顆數 | B48: 百萬顆 | D48: =u_tpu_26*tt_tpu_lo*ex_tpu -> 1.3475 | E48: =u_tpu_27*1*tt_tpu_lo*ex_tpu -> 1.925 | F48: =u_tpu_28*um28_A*1*tt_tpu_lo*ex_tpu -> 2.45 | G48: =u_tpu_28*(1+g29_tpu)*um29_A*1*tt_tpu_lo*ex_tpu -> 2.8175
A49: AWS Trainium：加權顆數 | B49: 百萬顆 | D49: =u_trn_26*tt_trn_lo*ex_trn -> 0.48 | E49: =u_trn_27*1*tt_trn_lo*ex_trn -> 0.6 | F49: =u_trn_28*um28_A*1*tt_trn_lo*ex_trn -> 0.72 | G49: =u_trn_28*(1+g29_trn)*um29_A*1*tt_trn_lo*ex_trn -> 0.828
A50: 其他 ASIC（MTIA、Maia 等）：加權顆數 | B50: 百萬顆 | D50: =u_oth_26*tt_oth_lo*ex_oth -> 0.2 | E50: =u_oth_27*1*tt_oth_lo*ex_oth -> 0.9 | F50: =u_oth_28*um28_A*1*tt_oth_lo*ex_oth -> 1 | G50: =u_oth_28*(1+g29_oth)*um29_A*1*tt_oth_lo*ex_oth -> 1.15
A51: 加速器顆數合計（未加權） | B51: 百萬顆 | D51: =u_bw_26+u_rb_26+u_ru_26+u_hp_26+u_amd_26+u_tpu_26+u_trn_26+u_oth_26 -> 15.2 | E51: =u_bw_27*1+u_rb_27*1+u_ru_27*1+u_hp_27*1+u_amd_27*1+u_tpu_27*1+u_trn_27*1+u_oth_27*1 -> 23.7 | F51: =u_bw_28*um28_A*1+u_rb_28*um28_A*1+u_ru_28*um28_A*1+u_hp_28*um28_A*1+u_amd_28*um28_A*1+u_tpu_28*um28_A*1+u_trn_28*um28_A*1+u_oth_28*um28_A*1 -> 26.5 | G51: =u_bw_28*(1+g29_bw)*um29_A*1+u_rb_28*(1+g29_rb)*um29_A*1+u_ru_28*(1+g29_ru)*um29_A*1+u_hp_28*(1+g29_hp)*um29_A*1+u_amd_28*(1+g29_amd)*um29_A*1+u_tpu_28*(1+g29_tpu)*um29_A*1+u_trn_28*(1+g29_trn)*um29_A*1+u_oth_28*(1+g29_oth)*um29_A*1 -> 30.15
A52: NVIDIA 加權顆數 | B52: 百萬顆 | D52: =D43+D44+D45+D46 -> 7.69 | E52: =E43+E44+E45+E46 -> 11.25 | F52: =F43+F44+F45+F46 -> 11.9 | G52: =G43+G44+G45+G46 -> 13.36
A53: AMD 與 ASIC 加權顆數（× 曝險） | B53: 百萬顆 | D53: =D47+D48+D49+D50 -> 2.1625 | E53: =E47+E48+E49+E50 -> 3.695 | F53: =F47+F48+F49+F50 -> 4.53 | G53: =G47+G48+G49+G50 -> 5.2095
A54: 加權顆數合計 | B54: 百萬顆 | D54: =D52+D53 -> 9.8525 | E54: =E52+E53 -> 14.945 | F54: =F52+F53 -> 16.43 | G54: =G52+G53 -> 18.5695
A55: FY2026 AI 加速器測試營收（校準）＝ 錨點營收 × AI 占比 | B55: NT$B | D55: =a26_rev*ai_26 -> 16.603774
A56: 每加權顆營收（FY2026 校準） | B56: NT$B／百萬顆 | D56: =D55/D54 -> 1.6852346 | H56: Derived：＝ 千元新台幣／顆；乘積（測試時間 × 每小時價格 × 份額）只能整體識別
A57: 份額相對值（÷ FY2026） | B57: x | D57: =1 -> 1 | E57: =rel_27 -> 0.95 | F57: =rel_28 -> 0.92 | G57: =rel_29 -> 0.9
A58: 測試單價指數（FY2026＝1） | B58: x | D58: =1 -> 1 | E58: =pp_27 -> 0.98 | F58: =pp_28 -> 0.96 | G58: =pp_29 -> 0.95
A59: AI 加速器測試營收 ＝ 每加權顆營收 × 加權顆數 × 份額 × 單價 | B59: NT$B | C59: =a25_rev*ai_25 -> 9.60674 | D59: =D55 -> 16.603774 | E59: =$D$56*E54*E57*E58 -> 23.448009 | F59: =$D$56*F54*F57*F58 -> 24.454399 | G59: =$D$56*G54*G57*G58 -> 26.75634
A60: 非 AI 營收 | B60: NT$B | C60: =a25_rev-C59 -> 25.32686 | D60: =a26_rev-D59 -> 30.835581 | E60: =D60*(1+g_nai27) -> 34.53585 | F60: =E60*(1+g_nai28) -> 36.95336 | G60: =F60*(1+g_nai29) -> 38.801028
A61: 營收 | B61: NT$B | C61: =C59+C60 -> 34.9336 | D61: =D59+D60 -> 47.439355 | E61: =E59+E60 -> 57.983859 | F61: =F59+F60 -> 61.407759 | G61: =G59+G60 -> 65.557367
A62: 營收年增 | B62: % | D62: =D61/C61-1 -> 0.35798643 | E62: =E61/D61-1 -> 0.22227336 | F62: =F61/E61-1 -> 0.059049185 | G62: =G61/F61-1 -> 0.067574658
A63: AI 加速器測試 ÷ 營收 | B63: % | C63: =C59/C61 -> 0.275 | D63: =D59/D61 -> 0.35 | E63: =E59/E61 -> 0.40438856 | F63: =F59/F61 -> 0.39822979 | G63: =G59/G61 -> 0.40813627
A64: NVIDIA ÷ 加權顆數 | B64: % | D64: =D52/D54 -> 0.78051256 | E64: =E52/E54 -> 0.75276012 | F64: =F52/F54 -> 0.72428484 | G64: =G52/G54 -> 0.71945933
A65: 每顆 Blackwell 等值的京元電 AI 測試營收 | B65: US$／顆 | D65: =D59/D54/fx*1000 -> 52.663582 | E65: =E59/E54/fx*1000 -> 49.029795 | F65: =F59/F54/fx*1000 -> 46.512476 | G65: =G59/G54/fx*1000 -> 45.027363 | H65: 含份額與單價指數；FY2027 起隨份額、單價變動
A66: B. 資本支出與折舊（資本支出＝維持性 × 營收＋κ × 當年營收增量；折舊＝前一年 × (1 − 到期)＋折舊率 × 當年與前一年資本支出平均）
A67: κ：每增加 1 元年營收所需擴產資本支出（FY2025 校準） | B67: x | C67: =(a25_capex-m_cx*a25_rev)/(a25_rev-rev24) -> 3.5728427 | H67: Derived：（FY2025 現金資本支出 − 維持性）÷（FY2025 營收 − FY2024 營收）
A68: 資本支出 | B68: NT$B | C68: =a25_capex -> 32.3554 | D68: =capex_26 -> 42 | E68: =m_cx*E61+$C$67*MAX(0,E61-D61) -> 43.472242 | F68: =m_cx*F61+$C$67*MAX(0,F61-E61) -> 18.373831 | G68: =m_cx*G61+$C$67*MAX(0,G61-F61) -> 21.381635 | H68: FY2026＝In 頁 capex_26（公式值見 Recon）；營收下滑時只剩維持性資本支出
A69: 資本支出 ÷ 營收 | B69: % | C69: =C68/C61 -> 0.92619713 | D69: =D68/D61 -> 0.88534088 | E69: =E68/E61 -> 0.74973006 | F69: =F68/F61 -> 0.29921025 | G69: =G68/G61 -> 0.32615151
A70: 折舊攤提 | B70: NT$B | C70: =a25_da -> 7.5143841 | D70: =a26_da -> 11.327707 | E70: =D70*(1-ret)+dr*(D68+E68)/2 -> 15.462295 | F70: =E70*(1-ret)+dr*(E68+F68)/2 -> 18.090714 | G70: =F70*(1-ret)+dr*(F68+G68)/2 -> 19.372729
A71: 折舊攤提 ÷ 營收 | B71: % | C71: =C70/C61 -> 0.21510477 | D71: =D70/D61 -> 0.23878291 | E71: =E70/E61 -> 0.2666655 | F71: =F70/F61 -> 0.29459981 | G71: =G70/G61 -> 0.29550804
A72: 回測：以同一公式算 FY2026 折舊 − 錨點 | B72: NT$B | D72: =C70*(1-ret)+dr*(C68+D68)/2-D70 -> -0.099495045 | H72: 校準檢查（非獨立檢驗）：正值＝公式高估
A73: C. 損益
A74: 固定現金成本 F（FY2026 校準＝錨點現金成本 − v × 營收） | B74: NT$B | D74: =a26_cc-v_cc*a26_rev -> 7.9821937 | H74: Derived：人力、電力基本量、租金等；FY2026 恆等於錨點
A75: 現金營業成本 ＝ F ＋ v ×（AI 營收 ÷ 單價指數＋非 AI 營收） | B75: NT$B | C75: =a25_cc -> 14.8984 | D75: =a26_cc -> 17.470065 | E75: =$D$74+v_cc*(E59/E58+E60) -> 19.674672 | F75: =$D$74+v_cc*(F59/F58+F60) -> 20.467532 | G75: =$D$74+v_cc*(G59/G58+G60) -> 21.375313 | H75: 成本隨測試量（不含價格）變動；單價下降全部落在毛利
A76: 毛利 ＝ 營收 − 現金營業成本 − 折舊攤提 | B76: NT$B | C76: =C61-C75-C70 -> 12.520816 | D76: =D61-D75-D70 -> 18.641583 | E76: =E61-E75-E70 -> 22.846893 | F76: =F61-F75-F70 -> 22.849513 | G76: =G61-G75-G70 -> 24.809325
A77: 毛利率 | B77: % | C77: =C76/C61 -> 0.35841757 | D77: =D76/D61 -> 0.39295608 | E77: =E76/E61 -> 0.39402159 | F77: =F76/F61 -> 0.37209488 | G77: =G76/G61 -> 0.37843688
A78: 營業費用（基準路徑） | B78: NT$B | C78: =a25_opx -> 3.5197 | D78: =a26_opx -> 6.1141318 | E78: =D78*(1+MAX(0,phi*E62)) -> 6.929537 | F78: =E78*(1+MAX(0,phi*F62)) -> 7.1750471 | G78: =F78*(1+MAX(0,phi*G62)) -> 7.4659579
A79: 營業費用 | B79: NT$B | C79: =C78 -> 3.5197 | D79: =D78 -> 6.1141318 | E79: =E78+0*E61 -> 6.929537 | F79: =F78+0*F61 -> 7.1750471 | G79: =G78+0*G61 -> 7.4659579
A80: 營業利益 | B80: NT$B | C80: =C76-C79 -> 9.0011159 | D80: =D76-D79 -> 12.527451 | E80: =E76-E79 -> 15.917356 | F80: =F76-F79 -> 15.674465 | G80: =G76-G79 -> 17.343367
A81: 營業利益率 | B81: % | C81: =C80/C61 -> 0.25766356 | D81: =D80/D61 -> 0.26407297 | E81: =E80/E61 -> 0.27451356 | F81: =F80/F61 -> 0.2552522 | G81: =G80/G61 -> 0.26455253
A82: EBITDA（營業利益＋折舊攤提） | B82: NT$B | C82: =C80+C70 -> 16.5155 | D82: =D80+D70 -> 23.855158 | E82: =E80+E70 -> 31.379651 | F82: =F80+F70 -> 33.76518 | G82: =G80+G70 -> 36.716096
A83: EBITDA − 資本支出（近似，未計稅與營運資金） | B83: NT$B | C83: =C82-C68 -> -15.8399 | D83: =D82-D68 -> -18.144842 | E83: =E82-E68 -> -12.092592 | F83: =F82-F68 -> 15.391349 | G83: =G82-G68 -> 15.334462
A84: 歸屬母公司淨利 | B84: NT$B | C84: =a25_ni -> 11.015 | D84: =a26_ni -> 10.666084 | E84: =E80*nir_f -> 13.370579 | F84: =F80*nir_f -> 13.166551 | G84: =G80*nir_f -> 14.568429 | H84: FY2025 含處分利益
A85: 淨利 ÷ 營業利益 | B85: % | C85: =C84/C80 -> 1.2237372 | D85: =D84/D80 -> 0.85141696 | E85: =E84/E80 -> 0.84 | F85: =F84/F80 -> 0.84 | G85: =G84/G80 -> 0.84
A86: 股數 | B86: 十億股 | C86: =a25_sh -> 1.2225305 | D86: =a26_sh -> 1.2826471 | E86: =D86*(1+sh_g) -> 1.2826471 | F86: =E86*(1+sh_g) -> 1.2826471 | G86: =F86*(1+sh_g) -> 1.2826471
A87: EPS | B87: NT$ | C87: =C84/C86 -> 9.01 | D87: =D84/D86 -> 8.3156815 | E87: =E84/E86 -> 10.424207 | F87: =F84/F86 -> 10.265139 | G87: =G84/G86 -> 11.358096
A88: EPS 年增 | B88: % | D88: =D87/C87-1 -> -0.077060873 | E88: =E87/D87-1 -> 0.25356018 | F88: =F87/E87-1 -> -0.015259456 | G88: =G87/F87-1 -> 0.10647265 | H88: FY2026 對 FY2025：股數口徑不同（配股 5%）且 FY2025 含處分利益
A91: 案例區塊：測試時間係數 高（情境 A）
A92: 項目 | B92: 單位 | C92: FY2025A | D92: FY2026（錨點） | E92: FY2027 | F92: FY2028 | G92: FY2029 | H92: 說明
A93: A. AI 加速器測試需求（加權顆數＝顆數 × 每顆測試時間（含 burn-in）× 京元電曝險；FY(t)＝CY(t)）
A94: NVIDIA Blackwell：加權顆數 | B94: 百萬顆 | D94: =u_bw_26*tt_bw_hi -> 5.4 | E94: =u_bw_27*1*tt_bw_hi -> 2.4 | F94: =u_bw_28*um28_A*1*tt_bw_hi -> 0.5 | G94: =u_bw_28*(1+g29_bw)*um29_A*1*tt_bw_hi -> 0.25
A95: NVIDIA Rubin：加權顆數 | B95: 百萬顆 | D95: =u_rb_26*tt_rb_hi -> 3.06 | E95: =u_rb_27*1*tt_rb_hi -> 12.6 | F95: =u_rb_28*um28_A*1*tt_rb_hi -> 12.6 | G95: =u_rb_28*(1+g29_rb)*um29_A*1*tt_rb_hi -> 14.49
A96: NVIDIA Rubin Ultra：加權顆數 | B96: 百萬顆 | D96: =u_ru_26*tt_ru_hi -> 0 | E96: =u_ru_27*1*tt_ru_hi -> 0.78 | F96: =u_ru_28*um28_A*1*tt_ru_hi -> 5.2 | G96: =u_ru_28*(1+g29_ru)*um29_A*1*tt_ru_hi -> 5.98
A97: NVIDIA Hopper：加權顆數 | B97: 百萬顆 | D97: =u_hp_26*tt_hp_hi -> 0.4 | E97: =u_hp_27*1*tt_hp_hi -> 0 | F97: =u_hp_28*um28_A*1*tt_hp_hi -> 0 | G97: =u_hp_28*(1+g29_hp)*um29_A*1*tt_hp_hi -> 0
A98: AMD Instinct：加權顆數 | B98: 百萬顆 | D98: =u_amd_26*tt_amd_hi*ex_amd -> 0.21 | E98: =u_amd_27*1*tt_amd_hi*ex_amd -> 0.42 | F98: =u_amd_28*um28_A*1*tt_amd_hi*ex_amd -> 0.56 | G98: =u_amd_28*(1+g29_amd)*um29_A*1*tt_amd_hi*ex_amd -> 0.644
A99: Google TPU：加權顆數 | B99: 百萬顆 | D99: =u_tpu_26*tt_tpu_hi*ex_tpu -> 2.31 | E99: =u_tpu_27*1*tt_tpu_hi*ex_tpu -> 3.3 | F99: =u_tpu_28*um28_A*1*tt_tpu_hi*ex_tpu -> 4.2 | G99: =u_tpu_28*(1+g29_tpu)*um29_A*1*tt_tpu_hi*ex_tpu -> 4.83
A100: AWS Trainium：加權顆數 | B100: 百萬顆 | D100: =u_trn_26*tt_trn_hi*ex_trn -> 0.88 | E100: =u_trn_27*1*tt_trn_hi*ex_trn -> 1.1 | F100: =u_trn_28*um28_A*1*tt_trn_hi*ex_trn -> 1.32 | G100: =u_trn_28*(1+g29_trn)*um29_A*1*tt_trn_hi*ex_trn -> 1.518
A101: 其他 ASIC（MTIA、Maia 等）：加權顆數 | B101: 百萬顆 | D101: =u_oth_26*tt_oth_hi*ex_oth -> 0.4 | E101: =u_oth_27*1*tt_oth_hi*ex_oth -> 1.8 | F101: =u_oth_28*um28_A*1*tt_oth_hi*ex_oth -> 2 | G101: =u_oth_28*(1+g29_oth)*um29_A*1*tt_oth_hi*ex_oth -> 2.3
A102: 加速器顆數合計（未加權） | B102: 百萬顆 | D102: =u_bw_26+u_rb_26+u_ru_26+u_hp_26+u_amd_26+u_tpu_26+u_trn_26+u_oth_26 -> 15.2 | E102: =u_bw_27*1+u_rb_27*1+u_ru_27*1+u_hp_27*1+u_amd_27*1+u_tpu_27*1+u_trn_27*1+u_oth_27*1 -> 23.7 | F102: =u_bw_28*um28_A*1+u_rb_28*um28_A*1+u_ru_28*um28_A*1+u_hp_28*um28_A*1+u_amd_28*um28_A*1+u_tpu_28*um28_A*1+u_trn_28*um28_A*1+u_oth_28*um28_A*1 -> 26.5 | G102: =u_bw_28*(1+g29_bw)*um29_A*1+u_rb_28*(1+g29_rb)*um29_A*1+u_ru_28*(1+g29_ru)*um29_A*1+u_hp_28*(1+g29_hp)*um29_A*1+u_amd_28*(1+g29_amd)*um29_A*1+u_tpu_28*(1+g29_tpu)*um29_A*1+u_trn_28*(1+g29_trn)*um29_A*1+u_oth_28*(1+g29_oth)*um29_A*1 -> 30.15
A103: NVIDIA 加權顆數 | B103: 百萬顆 | D103: =D94+D95+D96+D97 -> 8.86 | E103: =E94+E95+E96+E97 -> 15.78 | F103: =F94+F95+F96+F97 -> 18.3 | G103: =G94+G95+G96+G97 -> 20.72
A104: AMD 與 ASIC 加權顆數（× 曝險） | B104: 百萬顆 | D104: =D98+D99+D100+D101 -> 3.8 | E104: =E98+E99+E100+E101 -> 6.62 | F104: =F98+F99+F100+F101 -> 8.08 | G104: =G98+G99+G100+G101 -> 9.292
A105: 加權顆數合計 | B105: 百萬顆 | D105: =D103+D104 -> 12.66 | E105: =E103+E104 -> 22.4 | F105: =F103+F104 -> 26.38 | G105: =G103+G104 -> 30.012
A106: FY2026 AI 加速器測試營收（校準）＝ 錨點營收 × AI 占比 | B106: NT$B | D106: =a26_rev*ai_26 -> 16.603774
A107: 每加權顆營收（FY2026 校準） | B107: NT$B／百萬顆 | D107: =D106/D105 -> 1.3115145 | H107: Derived：＝ 千元新台幣／顆；乘積（測試時間 × 每小時價格 × 份額）只能整體識別
A108: 份額相對值（÷ FY2026） | B108: x | D108: =1 -> 1 | E108: =rel_27 -> 0.95 | F108: =rel_28 -> 0.92 | G108: =rel_29 -> 0.9
A109: 測試單價指數（FY2026＝1） | B109: x | D109: =1 -> 1 | E109: =pp_27 -> 0.98 | F109: =pp_28 -> 0.96 | G109: =pp_29 -> 0.95
A110: AI 加速器測試營收 ＝ 每加權顆營收 × 加權顆數 × 份額 × 單價 | B110: NT$B | C110: =a25_rev*ai_25 -> 9.60674 | D110: =D106 -> 16.603774 | E110: =$D$107*E105*E108*E109 -> 27.350849 | F110: =$D$107*F105*F108*F109 -> 30.556736 | G110: =$D$107*G105*G108*G109 -> 33.653804
A111: 非 AI 營收 | B111: NT$B | C111: =a25_rev-C110 -> 25.32686 | D111: =a26_rev-D110 -> 30.835581 | E111: =D111*(1+g_nai27) -> 34.53585 | F111: =E111*(1+g_nai28) -> 36.95336 | G111: =F111*(1+g_nai29) -> 38.801028
...

Sheet Sources
A1: 來源（公司原文＝京元電每季 Investor update 與月營收；AI 占比、客戶與券商估計皆為 Interested-party）
A2: 公司：2Q26 Investor update（1Q26、2Q26 營收、毛利率、費用、EBITDA、EPS；安裝測試機 5,900 台以上） | B2: https://www.kyec.com.tw/Upfiles/EDUp/files/投資人關係/每季營運報告/KYEC(2449)_2Q26 Investor update_English.pdf
A3: 公司：4Q25 Investor update（3Q25、4Q25 營收、毛利率、費用、EBITDA、EPS） | B3: https://www.kyec.com.tw/Upfiles/EDUp/files/投資人關係/每季營運報告/KYEC(2449)_4Q25 Investor update_English.pdf
A4: 公司：2Q25 Investor update（1Q25、2Q25；不含已出售的中國子公司） | B4: https://kyec.com.tw/Upfiles/EDUp/files/關於京元/KYEC(2449TW)_2Q25 Investor update_English.pdf
A5: 中央社 2026-03-06（FY2025 營收、毛利率、營業利益、淨利、EPS；配股；處分利益） | B5: https://www.cna.com.tw/news/afe/202603060261.aspx
A6: 科技新報 2026-05-11（1Q26 毛利率 39.74%、營益率 27.2%、淨利） | B6: https://finance.technews.tw/2026/05/11/king-yuan-electrics-first-quarter-financial-report-hit-a-new-quarterly-high/
A7: 月營收：科技新報 2026-10-08（9 月 40.71 億、前 9 月 334.76 億） | B7: https://finance.technews.tw/2026/10/08/kyec-2449-202609-financial-report/
A8: 月營收：HiStock（2025-01 至 2026-09） | B8: https://histock.tw/stock/financial.aspx?no=2449
A9: 媒體：理財周刊 2026-09-01（2Q26 淨利、EPS；法人 2026 年營收與 EPS；目標價中位數） | B9: https://www.moneyweekly.com.tw/_Article?AID=246195
A10: 媒體：理財周刊 2026-09-24（資本支出 500 億、美國廠 14 億美元、Rubin 延後、ASIC 客戶） | B10: https://www.moneyweekly.com.tw/_Article?AID=251167
A11: 媒體：優分析 2026-09-18（4Q26 營收估計、Rubin 影響、聯發科 TPU、博通占比） | B11: https://uanalyze.com.tw/articles/5209555591
A12: 券商：Morgan Stanley（經科技新報 2026-06-23；AI 占比、Google 相關、CPU、burn-in、資本支出、目標價） | B12: https://finance.technews.tw/2026/06/23/morgan-stanley-expects-king-yuan-electronics-revenue-to-grow-by-40-in-2026/
A13: 媒體：雅虎新聞 2026-01-27（4Q25 營收、2025 年資本支出約 370 億、2026 年預算 393.72 億） | B13: https://n.yam.com/Article/20260127965778
... A20: 資料商：玩股網年度 EPS（2013–2025）；HiStock 季 EPS 與月本益比；stockanalysis 年度 P/E | B20: https://www.wantgoo.com/stock/2449/profitability/dividend-payout-ratio；https://histock.tw/stock/2449/%E6%9C%AC%E7%9B%8A%E6%AF%94；https://stockanalysis.com/quote/tpe/2449/financials/ratios/
A21: 市場層：tsmc 成品（加速器顆數與情境係數，本 repo，唯讀）
A22: 待補（人工）：3Q26 財報（約 11 月上旬）；10 月營收（11 月上旬）；折舊攤提金額（財報附註）；客戶別營收與 NVIDIA 委外份額；測試單價；處分利益金額；前瞻 P/E 十年歷史（Bloomberg）；FY2027–28 最新共識（付費） | B22: 未找到
A23: SemiAnalysis | B23: 未使用
