Workbook

Sheet README
A1: 台達電（2308）個股模型 v0.3（AI 半導體 Project：電源與散熱次產業樣板） 2026-10-28
A2: 版本：v0.2.1（2026-10-25：補上檔空間級距、投資建議、重點觀察；PL 頁最後新增三情境自由現金流列（淨利＋折舊 − 資本支出，不含營運資金變動）、In 頁最後新增折舊 ÷ 營收、資本支出 ÷ 營收（數值不變））。v0.2（2026-10-25：目標價改為 DCF 與 Comparable 加權、三情境延伸到 FY2032；FY2025–FY2029 數值不變）。前版：v0.3（2026-10-28：依個股模型原則重建營收層——營收列改為官方四大事業群〔電源及零組件、交通、自動化、基礎設施〕，AI 電源為電源及零組件子列、液冷為基礎設施子列，分部合計＝合併營收；非 AI 單一成長率改為四條分部成長率）；v0.2.x（2026-10-25～27：目標價、級距、Siliconomics 改讀）；v0.1.1（2026-10-25：Val 新增第 0 節「目標價與上檔空間」、In 新增情境權重 tp_wA／tp_wB／tp_wC；其餘數值與 v0.1 相同）。v0.1（初版）：AI 電源每 kW 內容、台達電份額、液冷每 GW 營收在本模型 Units 頁建立，為本專案權威資料（規則第 13 條）；奇鋐等散熱廠之後讀這條液冷線。
A3: 模型命題：台達電的 AI 營收＝部署 GW（AI IT 資本支出 ÷ 每 GW IT 資本支出）×（AI 電源每 kW 內容 × 台達電份額＋液冷每 GW 營收）。800V HVDC 把交流轉直流移到機架外，每 GW 可做的金額變大；同時光寶、Flex、中國廠追趕份額。股價兩週跌約兩成後，約 22–28 倍未來 12 月 EPS。
A4: 核心問題：每 kW 電源內容上升（800V）能不能抵銷份額流失與零組件成本，讓 AI 營收在 2027–28 年維持高成長；現價隱含的路徑合不合理。
A6: 會計年度＝日曆年，FY(t)＝CY(t)，不平移。預測期 FY2027–FY2029（三年）。金額：十億新台幣；市場以美元計、以匯率換算。口徑：歸屬母公司淨利。
A8: 驅動因子 → 推導量（全部唯讀上游，不修改）
A9: AI 電源營收：markets/network 的 AI IT 資本支出 × 情境顆數係數 ÷ 每 GW IT 資本支出（Tokenomics，經橋接表）＝部署 GW；× 每 kW 電源內容（凱基推導、2028 起 Assumed）× 匯率 × 台達電有效份額（FY2026 以公司 AI 相關占比校準）× 份額相對值（Assumed）。
A10: 液冷營收：FY2026 以公司液冷占比校準每 GW 營收 × 相對值（Assumed）。營收分部：電源及零組件＝AI 電源＋非 AI（年增 5／4／3%）；基礎設施＝液冷＋非液冷（年增 9／7／6%）；自動化（5／5／4%）；交通（0／2／2%）；皆 Assumed，FY2025、FY2026 依公司事業群比重（50／7／10／33%、51／6／8／35%）。毛利率：AI 電源比其他營收高 d_ai（Assumed），其他毛利率為 FY2026 殘差（Derived）。營業費用：彈性 phi（Derived）。
A11: 校準：FY2026 ＝ 1H26 實績＋3Q26 營收實績＋假設（4Q 季增、毛利率、營業費用率）。不用券商數字（只在 Recon 對帳）。
A12: 估值：Val 第 0 節目標價＝0.5 × DCF 目標價（股東現金流＝EPS ×（1 − tp_g ÷ tp_roe），FY2027–FY2032 明確期＋永續，r 10%、g 4%，三情境權重 0.3／0.5／0.2，推到 12 個月後）＋0.5 × Comparable 目標價（Vertiv、Eaton、Schneider Electric、光寶科 前瞻 P/E 中位數 × 12 個月後前瞻 EPS）；另列 Comparable 單獨目標價、市場共識目標價與差距拆解（EPS 因素、倍數因素）、DCF 價格帶、十年 P/E 分位檢查（只作檢查）。（v0.1.1 原估值說明，保留作參考：現價 ÷ FY2027、FY2028 EPS；十年 P/E 規則值（單一資料商來源）× FY2027 EPS；循環位置以本模型營收最高年判定（台達電不套設備股見頂年）。）
A13: 標記：Verified、Interested-party、Analogy、Assumed、Derived。SemiAnalysis 未使用。公司原文＝法說簡報與逐字稿；券商皆未具名或單一來源。
A15: 已知限制：(1)「AI 相關」是否含液冷，公司說法不一致（Sens「AI 相關含液冷」）；(2) 2028 年起每 kW 內容（800V）與份額相對值為 Assumed，是 FY2028 EPS 最敏感的輸入；(3) 部署 GW 以 VR200 每 GW IT 資本支出換算，ASIC 機架的每 GW 資本支出較低，GW 可能低估；(4) 十年 P/E 只有一個來源，且 2016–2019 年為 AI 前的低倍數；(5) 未計 Vicor 337 調查（垂直供電）與零組件短缺的下檔；(6) 3Q26 法說（10 月底）後更新錨點；R4 產業部署路徑未建。
... A18: 先驗：v0.1 的 Andy 合理 P/E 25x 對照（Val 第 5 節）保留不動，不進目標價；本版未新增先驗。
A19: ="投資建議："&Val!B135&"（依上檔空間固定規則）" -> 投資建議：中立（依上檔空間固定規則）
A20: ="重點觀察 1：目標價 NT$"&TEXT(Val!$B$119,"#,##0")&"（DCF "&TEXT(Val!$B$105,"#,##0")&"、Comparable（相對倍數調整後）"&TEXT(tp_comp_adj,"#,##0")&"；DCF 權重 "&TEXT(tp_w_dcf,"0%")&"），比現價 "&TEXT(px,"#,##0")&"（2026-10-23）"&IF(Val!$B$122>=0,"高 "&TEXT(Val!$B$122,"0.0%"),"低 "&TEXT(-Val!$B$122,"0.0%"))&"，級距 "&Val!$B$134&"、投資建議 "&Val!$B$135&"。相對倍數調整係數 "&TEXT(rm_factor,"0.00")&"（本公司 10 年前瞻倍數中位數 ÷ 同業的中位數，夾在 0.5–2.0；Val 第 0.5 節），調整前加權上檔空間 "&TEXT((tp_w_dcf*Val!$B$105+(1-tp_w_dcf)*Val!$B$115)/px-1,"+0.0%;−0.0%")&"；Comparable 單獨（市場主流同業法、未調整）為 "&TEXT(Val!$B$123,"+0.0%;−0.0%")&"。"&"以下為 2026-10-29 相對倍數調整前撰寫的說明，其中數字為調整前：主因是倍數不是 EPS：本模型 12 個月後前瞻 EPS 65.12 比共識前瞻 EPS 51.13 高 27.4%（兩者期間差約一年），但同業（Vertiv、Eaton、Schneider Electric、光寶科）前瞻 P/E 中位數 21.9 倍，現價隱含 31.4 倍、共識目標價 2,502 隱含 48.9 倍（比同"&"業高 123%）；DCF 只有前瞻 EPS 的 15.3 倍（ROE 18.2%、再投資率 22.0%），單獨為 −37.7%。" -> 重點觀察 1：目標價 NT$1,237（DCF 1,001、Comparable（相對倍數調整後）1,473；DCF 權重 50%），比現價 1,605（2026-10-23）低 22.9%，級距 0%～−25%、投資建議 中立。相對倍數調整係數 1.03（本公司 10 年前瞻倍數中位數 ÷ 同業的中位數，夾在 0.5–2.0；Val 第 0.5 節），調整前加權上檔空間 −24.3%；Comparable 單獨（市場主流同業法、未調整）為 −11.0%。以下為 2026-10-29 相對倍數調整前撰寫的說明，其中數字為調整前：主因是倍數不是 EPS：本模型 12 個月後前瞻 EPS 65.12 比共識前瞻 EPS 51.13 高 27.4%（兩者期間差約一年），但同業（Vertiv、Eaton、Schneider Electric、光寶科）前瞻 P/E 中位數 21.9 倍，現價隱含 31.4 倍、共識目標價 2,502 隱含 48.9 倍（比同業高 123%）；DCF 只有前瞻 EPS 的 15.3 倍（ROE 18.2%、再投資率 22.0%），單獨為 −37.7%。
A21: 重點觀察 2：上檔空間 −24.4% 離中立與放空的界線 −25% 只差 0.6 個百分點：DCF 權重改為 0.8 時目標價 1,085（上檔空間 −32.4%，落入放空），折現率 −1pt 時目標價 +7.9%；評等對估值參數敏感。
A22: 重點觀察 3：FY2027 EPS 60.71 低於券商 62.7–80.8；營業費用率 +2pt 時 FY2027 EPS −9.8%、AI 部署 ×0.8 時 −13.6%。3Q26 法說（10 月底）的 AI 電源與液冷營收、800V 時程是下一個檢驗點。
A24: 2026-10-29：加權目標價中的 Comparable 改用相對倍數調整後的值（Val 第 0.5 節：同業前瞻倍數中位數 × 本公司 10 年相對同業的倍數比，Bloomberg 前瞻倍數；Andy 2026-10-27「照建議做」、10-29 資料取回）。「Comparable 目標價（市場主流同業法）」維持不調整。重點觀察 1 的第一句已改為公式；重點觀察 2、3 與其他說明中的目標價與上檔空間數字為調整前撰寫，以 Val 頁為準。
A26: v0.3.1（2026-10-30）：依個股模型原則第 8 節調整 In 頁呈現（數值不變）。In 頁 D／F 欄名改「敏感度低」「敏感度高」（只用於 Sens 頁、不進目標價）；In 頁最後新增「情境驅動對照」一節，把上方各情境專屬輸入三情境並排（只引用上方各列，純展示）；HTML 驅動因子一節分「情境驅動」與「單一參數」兩張表。

Sheet In
A1: In — 輸入（藍字；基準欄 E，低 D、高 F）。金額：十億新台幣（NT$B），市場與每 kW 內容為美元；比例：%。每個輸入附兩個來源（找不到者寫「未找到」）；公司原文算一個。【v0.3.1】基準欄 E 進主模型；D／F＝敏感度低／高，只用於 Sens 頁（一次動一個參數）、不進目標價；情境 A／B／C 的驅動見本頁最後一節「情境驅動對照」。
A2: 標記：Verified／Interested-party／Analogy／Assumed／Derived；Analogy、Assumed 給低／高區間。SemiAnalysis 未使用。公司原文＝台達電法說簡報與逐字稿（filecenter.deltaww.com）、月營收公告；公司的 AI 占比與毛利率說法為 Interested-party；券商估計皆為 Interested-party
A3: 鍵 | B3: 項目 | C3: 單位 | D3: 敏感度低 | E3: 基準 | F3: 敏感度高 | G3: 標記 | H3: 來源1 | I3: 來源2／說明
A4: A. AI 部署規模（讀 markets/network、markets/chip_bridge、tsmc 成品；情境 A 基準，B／C 依顆數係數縮放）
A5: itc_26 | B5: AI IT 資本支出 2026 | C5: US$B | E5: 781.87292 | G5: Derived | H5: markets/network/dist/20261026_AI網通市場模型_v0.2.3.xlsx｜Mkt!C27:F27 | I5: 加速器顆數 × 每顆 IT capex（含 ASIC）；本模型以此除以每 GW IT 資本支出得到部署 GW
A6: itc_27 | B6: AI IT 資本支出 2027 | C6: US$B | E6: 1565.35 | G6: Derived | H6: markets/network/dist/20261026_AI網通市場模型_v0.2.3.xlsx｜Mkt!C27:F27 | I6: 同上
A7: itc_28 | B7: AI IT 資本支出 2028 | C7: US$B | E7: 1984.2639 | G7: Derived | H7: markets/network/dist/20261026_AI網通市場模型_v0.2.3.xlsx｜Mkt!C27:F27 | I7: 同上
A8: itc_29 | B8: AI IT 資本支出 2029 | C8: US$B | E8: 2260.3903 | G8: Derived | H8: markets/network/dist/20261026_AI網通市場模型_v0.2.3.xlsx｜Mkt!C27:F27 | I8: 同上
A9: itpg_gb | B9: 每 GW IT 資本支出（GB300） | C9: US$B | E9: 32.237224 | G9: Derived | H9: markets/chip_bridge/dist/20261027_晶片內容橋接表_v0.2.2.xlsx｜In!E10（GB300）、H10（VR200） | I9: Tokenomics v20.1 IF_CapexIT（經橋接表；唯讀）
A10: itpg_vr | B10: 每 GW IT 資本支出（VR200；2027 起） | C10: US$B | E10: 37.586352 | G10: Derived | H10: markets/chip_bridge/dist/20261027_晶片內容橋接表_v0.2.2.xlsx｜In!E10（GB300）、H10（VR200） | I10: 同上；Rubin Ultra 與 ASIC 機架未另訂（Assumed：同 VR200）
A11: vr26 | B11: 2026 年部署中 Rubin 世代占比（混合每 GW IT 資本支出用） | C11: % | D11: 0.15 | E11: 0.22 | F11: 0.3 | G11: Interested-party | H11: TrendForce 2026 組合 Rubin 22%（經 markets/memory） | I11: 公司 2Q26 法說：2026 年 Blackwell 出貨遠大於 Rubin
A12: racks_vr | B12: 每 GW 機架數（VR200） | C12: 架 | E12: 4052 | G12: Derived | H12: markets/chip_bridge/dist/20261027_晶片內容橋接表_v0.2.2.xlsx｜In!E6（GB300）、H6（VR200） | I12: Recon 用：每架內容換算
A13: cool_vr | B13: VR200 每架機架內液冷（冷板等，橋接表） | C13: US$K | E13: 56 | G13: Interested-party | H13: markets/chip_bridge/dist/20261027_晶片內容橋接表_v0.2.2.xlsx｜In!E33（GB300）、H33（VR200） | I13: Morgan Stanley（經 Tom's Hardware 2025-11-05）：VR NVL144 機架內冷卻 BOM US$55.7K；不含 CDU、分歧管
A14: um28_A | B14: 情境 A：2028 顆數 ÷ 基準 | C14: x | E14: 1 | G14: Assumed | H14: tsmc/dist/20261030_台積電個股模型_v0.4.1.xlsx｜In!E37 | I14: A＝基準；B＝AI 資本支出消化；C＝明顯下修（與台積電、NVIDIA、Arista 模型相同）
A15: um29_A | B15: 情境 A：2029 顆數 ÷ 基準 | C15: x | E15: 1 | G15: Assumed | H15: tsmc/dist/20261030_台積電個股模型_v0.4.1.xlsx｜In!E38 | I15: 同上
A16: um28_B | B16: 情境 B：2028 顆數 ÷ 基準 | C16: x | E16: 0.8 | G16: Assumed | H16: tsmc/dist/20261030_台積電個股模型_v0.4.1.xlsx｜In!E39 | I16: A＝基準；B＝AI 資本支出消化；C＝明顯下修（與台積電、NVIDIA、Arista 模型相同）
A17: um29_B | B17: 情境 B：2029 顆數 ÷ 基準 | C17: x | E17: 0.85 | G17: Assumed | H17: tsmc/dist/20261030_台積電個股模型_v0.4.1.xlsx｜In!E40 | I17: 同上
A18: um28_C | B18: 情境 C：2028 顆數 ÷ 基準 | C18: x | E18: 0.6 | G18: Assumed | H18: tsmc/dist/20261030_台積電個股模型_v0.4.1.xlsx｜In!E41 | I18: A＝基準；B＝AI 資本支出消化；C＝明顯下修（與台積電、NVIDIA、Arista 模型相同）
A19: um29_C | B19: 情境 C：2029 顆數 ÷ 基準 | C19: x | E19: 0.6 | G19: Assumed | H19: tsmc/dist/20261030_台積電個股模型_v0.4.1.xlsx｜In!E42 | I19: 同上
A20: fx | B20: 匯率（新台幣 ÷ 美元） | C20: NT$/US$ | D20: 30.5 | E20: 32 | F20: 33 | G20: Derived | H20: 公司 2Q26 法說換算 NT$183.2B ≈ US$5.6B（隱含約 32.7） | I20: 2026 年初 31.4（〈台幣〉開紅盤，uanalyze）；10-23 收盤：未找到
A21: B. AI 電源內容與台達電份額（本專案為權威：每架電源與液冷內容、台達電份額，規則第 13 條）
A22: pkw_26 | B22: AI 電源內容（機架電源櫃、PSU、BBU、HVDC 電源櫃）2026 | C22: US$/kW | D22: 380 | E22: 450 | F22: 520 | G22: Derived | H22: https://www.kgi.com.hk/en/-/media/files/kgishk/research-reports/tw-reports/power-supply-industry_01072025.pdf：GB300 每架 PSU US$60–70K ÷ 136kW＝440–515；GB200 35–40K ÷ 120kW＝290–330（Interested-party） | I22: 2026 年以 GB300 為主（公司：Blackwell 遠大於 Rubin）
A23: pkw_27 | B23: AI 電源內容 2027（VR200） | C23: US$/kW | D23: 500 | E23: 600 | F23: 700 | G23: Derived | H23: https://www.kgi.com.hk/en/-/media/files/kgishk/research-reports/tw-reports/power-supply-industry_01072025.pdf：VR200 每架 PSU 超過 US$150K ÷ 約 250kW＝600 以上 | I23: 每 GW 4,052 架（Tokenomics）→ 每架約 247kW，與 250kW 相符
A24: pkw_28 | B24: AI 電源內容 2028（800V HVDC 放量） | C24: US$/kW | D24: 550 | E24: 680 | F24: 800 | G24: Assumed | H24: 公司：±400V、800V 3Q26 量產、2027 才有量；券商估 ±400V、800V 電源櫃占 2027 營收 5–10%（旺得富 2026-10-01，Interested-party） | I24: 800V 把交流轉直流移到機架外電源櫃與 SST：每 kW 內容上升（Assumed）
A25: pkw_29 | B25: AI 電源內容 2029 | C25: US$/kW | D25: 550 | E25: 720 | F25: 850 | G25: Assumed | H25: 同上 | I25: —
A26: rel_27 | B26: 台達電 AI 電源份額 2027 ÷ 2026（相對值） | C26: x | D26: 0.85 | E26: 0.95 | F26: 1 | G26: Assumed | H26: https://www.kgi.com.hk/en/-/media/files/kgishk/research-reports/tw-reports/power-supply-industry_01072025.pdf：Blackwell 平台 AI 伺服器 PSU 台達電約 70%；光寶、Flex 追趕（Interested-party） | I26: 公司 2Q26 法說：Rubin 110kW PSU「領先」；對手：麥格米特、歐陸通（中國）、Vertiv、Flex（BigGo 摘要）
A27: rel_28 | B27: 台達電 AI 電源份額 2028 ÷ 2026 | C27: x | D27: 0.7 | E27: 0.9 | F27: 1 | G27: Assumed | H27: 同上 | I27: —
A28: rel_29 | B28: 台達電 AI 電源份額 2029 ÷ 2026 | C28: x | D28: 0.65 | E28: 0.85 | F28: 1 | G28: Assumed | H28: 同上 | I28: —
A29: lcr_27 | B29: 台達電液冷每 GW 營收 2027 ÷ 2026 | C29: x | D29: 0.9 | E29: 1.1 | F29: 1.3 | G29: Assumed | H29: 橋接表：機架內液冷 GB300 US$50K → VR200 US$56K／架（每 kW 下降：架數 6,764 → 4,052） | I29: 公司：液冷占營收 2025 約 10% → 2026 超過 12%；Liquid-to-Air 使用期比市場預期長（2Q26 法說）
A30: lcr_28 | B30: 台達電液冷每 GW 營收 2028 ÷ 2026 | C30: x | D30: 0.85 | E30: 1.15 | F30: 1.4 | G30: Assumed | H30: 同上 | I30: —
A31: lcr_29 | B31: 台達電液冷每 GW 營收 2029 ÷ 2026 | C31: x | D31: 0.8 | E31: 1.2 | F31: 1.5 | G31: Assumed | H31: 同上 | I31: —
A32: C. 營收結構錨點（公司揭露比例 × 營收）
A33: ai_25 | B33: 2025 年 AI 相關營收 ÷ 營收（讀為不含液冷） | C33: % | E33: 0.18 | G33: Interested-party | H33: https://finance.technews.tw/2026/10/12/delta-electronics-q3-revenue-nears-200-billion-record-high-q4-double-digit-growth：AI 相關營收 2025 年 18%、2026 年超過 25%（公司） | I33: 數位時代 2026-02-26：AI 電源超過 20%、液冷約 9%、合計約 30%（口徑不同，未採用）
A34: ai_26 | B34: 2026 年 AI 相關營收 ÷ 營收（讀為不含液冷） | C34: % | D34: 0.25 | E34: 0.26 | F34: 0.28 | G34: Interested-party | H34: https://filecenter.deltaww.com/IR/download/calendar/2Q26_Transcript.pdf：CFO「一定超過 25%」；BigGo 摘要：朝 28% 目標 | I34: 讀法（Assumed）：AI 相關＝AI 電源，不含液冷；另一讀法見 Sens「AI 相關含液冷」
A35: lc_25 | B35: 2025 年液冷營收 ÷ 營收 | C35: % | E35: 0.1 | G35: Interested-party | H35: https://filecenter.deltaww.com/IR/download/calendar/2Q26_Transcript.pdf：液冷約占 2025 年營收 10% | I35: 數位時代：約 9%
A36: lc_26 | B36: 2026 年液冷營收 ÷ 營收 | C36: % | D36: 0.12 | E36: 0.125 | F36: 0.13 | G36: Interested-party | H36: https://filecenter.deltaww.com/IR/download/calendar/2Q26_Transcript.pdf：2026 年超過 12% | I36: https://finance.technews.tw/2026/10/12/delta-electronics-q3-revenue-nears-200-billion-record-high-q4-double-digit-growth：液冷產品可望超過 12%
A37: C2. 營收分部（官方四大事業群：電源及零組件、交通、自動化、基礎設施；v0.3 依個股模型原則重建）
A38: s25_pe | B38: 2025 年電源及零組件 ÷ 營收 | C38: % | E38: 0.5 | G38: Verified | H38: 台達電 2025 年報（英文版 p.136，2026-03-30）：電源及零組件 50%、交通 7%、自動化 10%、基礎設施 33%（經 BESSmanufacturers 摘錄） | I38: 四捨五入值；基礎設施＝1 − 其餘
A39: s26_pe | B39: 2026 年電源及零組件 ÷ 營收 | C39: % | D39: 0.5 | E39: 0.51 | F39: 0.53 | G39: Interested-party | H39: FTNN 2026-10-12（台達電 9 月營收公告）：電源及零組件 51%、基礎設施 35%、自動化 8%、交通 6%（9 月或前三季比重，文中未區分；全年 Assumed 同此） | I39: 理財周刊 2026-08-05：2Q26 電源及零組件 962.96 億（約 52.6%）、基礎設施 629.38 億（約 34.3%）
A40: s25_mo | B40: 2025 年交通 ÷ 營收 | C40: % | E40: 0.07 | G40: Verified | H40: 台達電 2025 年報（英文版 p.136，2026-03-30）：電源及零組件 50%、交通 7%、自動化 10%、基礎設施 33%（經 BESSmanufacturers 摘錄） | I40: 四捨五入值；基礎設施＝1 − 其餘
A41: s26_mo | B41: 2026 年交通 ÷ 營收 | C41: % | D41: 0.05 | E41: 0.06 | F41: 0.07 | G41: Interested-party | H41: FTNN 2026-10-12（台達電 9 月營收公告）：電源及零組件 51%、基礎設施 35%、自動化 8%、交通 6%（9 月或前三季比重，文中未區分；全年 Assumed 同此） | I41: —
A42: s25_au | B42: 2025 年自動化 ÷ 營收 | C42: % | E42: 0.1 | G42: Verified | H42: 台達電 2025 年報（英文版 p.136，2026-03-30）：電源及零組件 50%、交通 7%、自動化 10%、基礎設施 33%（經 BESSmanufacturers 摘錄） | I42: 四捨五入值；基礎設施＝1 − 其餘
A43: s26_au | B43: 2026 年自動化 ÷ 營收 | C43: % | D43: 0.07 | E43: 0.08 | F43: 0.09 | G43: Interested-party | H43: FTNN 2026-10-12（台達電 9 月營收公告）：電源及零組件 51%、基礎設施 35%、自動化 8%、交通 6%（9 月或前三季比重，文中未區分；全年 Assumed 同此） | I43: —
A44: s25_inf | B44: 2025 年基礎設施 ÷ 營收 | C44: % | E44: =1-s25_pe-s25_mo-s25_au -> 0.33 | G44: Derived | H44: 1 − 其餘三事業群（公司 33%） | I44: —
A45: s26_inf | B45: 2026 年基礎設施 ÷ 營收 | C45: % | E45: =1-s26_pe-s26_mo-s26_au -> 0.35 | G45: Derived | H45: 1 − 其餘三事業群（公司 35%） | I45: 2Q26 基礎設施年增約 78%、營業利益年增約 121%（理財周刊 2026-08-05）
A46: g_pe27 | B46: 電源及零組件：非 AI（一般伺服器電源、消費與工業電源、零組件）年增 2027 | C46: % | D46: 0 | E46: 0.05 | F46: 0.1 | G46: Assumed | H46: 2Q26 電源及零組件年增約 50%（含 AI 電源；BigGo 法說摘要） | I46: AI 電源（命題子列）另由部署 GW × 每 kW × 份額推導
A47: g_pe28 | B47: 電源及零組件：非 AI（一般伺服器電源、消費與工業電源、零組件）年增 2028 | C47: % | D47: 0 | E47: 0.04 | F47: 0.08 | G47: Assumed | H47: 同上 | I47: —
A48: g_pe29 | B48: 電源及零組件：非 AI（一般伺服器電源、消費與工業電源、零組件）年增 2029 | C48: % | D48: 0 | E48: 0.03 | F48: 0.06 | G48: Assumed | H48: 同上 | I48: —
A49: g_inf27 | B49: 基礎設施：非液冷（資料中心 UPS 與電力、通訊電源、樓宇自動化、儲能）年增 2027 | C49: % | D49: 0.03 | E49: 0.09 | F49: 0.15 | G49: Assumed | H49: 2Q26 基礎設施年增約 78%（含液冷；理財周刊 2026-08-05）；資料中心與液冷需求、擴廠（BigGo） | I49: 液冷（命題子列）另由部署 GW × 每 GW 液冷營收推導
A50: g_inf28 | B50: 基礎設施：非液冷（資料中心 UPS 與電力、通訊電源、樓宇自動化、儲能）年增 2028 | C50: % | D50: 0 | E50: 0.07 | F50: 0.12 | G50: Assumed | H50: 同上 | I50: —
A51: g_inf29 | B51: 基礎設施：非液冷（資料中心 UPS 與電力、通訊電源、樓宇自動化、儲能）年增 2029 | C51: % | D51: 0 | E51: 0.06 | F51: 0.1 | G51: Assumed | H51: 同上 | I51: —
A52: g_au27 | B52: 自動化年增 2027 | C52: % | D52: 0 | E52: 0.05 | F52: 0.1 | G52: Assumed | H52: 2Q26 自動化年增約 15% 但虧損；記憶體供給改善後下半年轉盈（BigGo 法說摘要） | I52: 2025 自動化 +5%（4Q25 法說簡報）
A53: g_au28 | B53: 自動化年增 2028 | C53: % | D53: 0 | E53: 0.05 | F53: 0.1 | G53: Assumed | H53: 同上 | I53: —
A54: g_au29 | B54: 自動化年增 2029 | C54: % | D54: 0 | E54: 0.04 | F54: 0.08 | G54: Assumed | H54: 同上 | I54: —
A55: g_mo27 | B55: 交通（電動車）年增 2027 | C55: % | D55: -0.1 | E55: 0 | F55: 0.1 | G55: Assumed | H55: 交通 2026 年衰退、持續虧損，全年表現不佳；長期趨勢不變（BigGo 法說摘要） | I55: 2025 交通 −16%（4Q25 法說簡報）
A56: g_mo28 | B56: 交通（電動車）年增 2028 | C56: % | D56: -0.05 | E56: 0.02 | F56: 0.1 | G56: Assumed | H56: 同上 | I56: —
A57: g_mo29 | B57: 交通（電動車）年增 2029 | C57: % | D57: -0.05 | E57: 0.02 | F57: 0.1 | G57: Assumed | H57: 同上 | I57: —
A58: D. 毛利率
A59: d_ai | B59: AI 電源毛利率高於其他營收的幅度 | C59: pt | D59: 0.04 | E59: 0.08 | F59: 0.12 | G59: Assumed | H59: 券商：18kW PSU 與 HVDC 電源櫃毛利率約 50%（旺得富 2026-10-01，Interested-party）；公司整體 1H26 36.3% | I59: 部門別毛利率未揭露：未找到；電源及零組件 2025 部門利益率 20.1% vs 基礎設施 15.6%（4Q25 法說簡報）
A60: E. FY2026 錨點（1H26 實績＋3Q26 營收實績＋假設）
A61: q3_rev | B61: 3Q26 營收（月營收合計） | C61: NT$B | E61: 197.059 | G61: Verified | H61: https://finance.technews.tw/2026/10/12/delta-electronics-q3-revenue-nears-200-billion-record-high-q4-double-digit-growth：3Q26 1,970.59 億元、前三季 5,396.68 億元 | I61: 時報資訊 2026-10-12 同值（含更正稿）
A62: q4g | B62: 4Q26 營收季增 | C62: % | D62: 0.05 | E62: 0.1 | F62: 0.2 | G62: Interested-party | H62: 法人：第四季雙位數季增（TechNews 2026-10-12） | I62: 券商 2026-10-01：4Q26 2,511 億（季增 20%，以 3Q 2,093 億為基礎；3Q 實際 1,971 億）
A63: q_gm | B63: 3Q、4Q26 毛利率 | C63: % | D63: 0.35 | E63: 0.36 | F63: 0.38 | G63: Interested-party | H63: https://filecenter.deltaww.com/IR/download/calendar/2Q26_Transcript.pdf：董事長「35% 左右合理」、下半年優於上半年；2Q26 35.6% | I63: 券商 2026-10-01：4Q26 38.7%（新高）
A64: q_opx | B64: 3Q、4Q26 營業費用 ÷ 營收 | C64: % | D64: 0.175 | E64: 0.185 | F64: 0.195 | G64: Assumed | H64: 1H26 19.1%、4Q25 18.3%（公司） | I64: 研發 +33%、銷管 +40%（2Q26 年增）
A65: q_nop | B65: 3Q、4Q26 業外收益（每季） | C65: NT$B | D65: 0 | E65: 2 | F65: 4.4 | G65: Derived | H65: 2Q26 4.4（部分為未實現投資利益）、4Q25 −0.8（公司） | I65: FY2025 3.9（公司）
A66: q_nir | B66: 3Q、4Q26 歸屬母公司淨利 ÷ 稅前 | C66: % | D66: 0.67 | E66: 0.69 | F66: 0.71 | G66: Derived | H66: 1H26 45.7 ÷ 66.1＝0.691；FY2025 60.1 ÷ 87.9＝0.684（公司） | I66: 含稅率約 22% 與非控制權益（台達泰國等）
A67: q_sh | B67: 股數（十億股；EPS 換算） | C67: 十億股 | E67: =45.7/17.59 -> 2.5980671 | G67: Derived | H67: 1H26 淨利 45.7 ÷ EPS 17.59（公司） | I67: 已發行 2,597,543,329 股（HiStock）
A68: F. 營業費用、業外、稅與非控制權益、股數（FY2027 起）
A69: phi | B69: 營業費用成長對營收成長的彈性 | C69: x | D69: 0.6 | E69: 0.8 | F69: 1 | G69: Derived | H69: FY2026 錨點實測（Q 頁 B26） | I69: FY2025：營業費用 +20% ÷ 營收 +32%＝0.62（4Q25 法說簡報）
A70: opx_adj | B70: 營業費用額外占營收比（Sens 用；基準 0） | C70: pt | D70: -0.02 | E70: 0 | F70: 0.02 | G70: Assumed | H70: 無 | I70: Sens 用 ±2 個百分點
A71: nop_f | B71: 業外收益（每年） | C71: NT$B | D71: 4 | E71: 8 | F71: 12 | G71: Assumed | H71: FY2025 3.9、1H26 7.2（公司） | I71: —
A72: nir_f | B72: 歸屬母公司淨利 ÷ 稅前 | C72: % | D72: 0.66 | E72: 0.69 | F72: 0.71 | G72: Derived | H72: 同 q_nir | I72: —
A73: sh_g | B73: 股數年變動 | C73: % | D73: 0 | E73: 0 | F73: 0.005 | G73: Assumed | H73: FY2025 推導 2.598 → 1H26 2.598（公司 EPS 與淨利） | I73: —
A74: mf | B74: AI 部署係數（Sens 用；FY2027 起） | C74: x | D74: 0.8 | E74: 1 | F74: 1.2 | G74: Assumed | H74: 網通模型 2027 年 AI IT 資本支出約 2 倍 | I74: ±20%
A75: G. 共識、市場資料（只作 Recon 對帳，不作校準）
A76: b_rev26 | B76: 券商 FY2026 營收（2026-10-01，3Q 前） | C76: NT$B | E76: 803 | G76: Interested-party | H76: 旺得富 2026-10-01（本土投顧，未具名；由 826.4 下修） | I76: —
A77: b_eps26a | B77: 券商 FY2026 EPS（本土，2026-10-01） | C77: NT$ | E77: 43.1 | G77: Interested-party | H77: 旺得富 2026-10-01 | I77: —
A78: b_eps26b | B78: 券商 FY2026 EPS（美系，2026-05-04） | C78: NT$ | E78: 41.5 | G78: Interested-party | H78: CMoney 2026-05-04（美系大行，未具名） | I78: —
A79: b_eps27a | B79: 券商 FY2027 EPS（本土，2026-10-01） | C79: NT$ | E79: 80.8 | G79: Interested-party | H79: 旺得富 2026-10-01；2028 EPS 121.6 | I79: —
A80: b_eps27b | B80: 券商 FY2027 EPS（美系，2026-05-04） | C80: NT$ | E80: 65.1 | G80: Interested-party | H80: CMoney 2026-05-04；2028 EPS 98.5 | I80: —
A81: b_eps27c | B81: 券商 FY2027 EPS（投顧研究團隊，2026-10-12） | C81: NT$ | E81: 62.68 | G81: Interested-party | H81: Yahoo 新聞 2026-10-12（台達電 Q3 營收與 337 調查）：2027 營收 1.05 兆、EPS 62.68、38x | I81: —
A82: b_rev27 | B82: 券商 FY2027 營收 | C82: NT$B | E82: 1050 | G82: Interested-party | H82: 同上 | I82: 鉅亨：「2027 上看兆元」
A83: ubs_26 | B83: UBS：全球 AI 伺服器電源市場 2026 | C83: US$B | E83: 17.7 | G83: Interested-party | H83: TechNews 2026-10-12（引述 UBS；2027 38.2、2025–2030 年複合成長約 69%；網址見 Sources） | I83: 口徑（是否含 BBU、HVDC、非 NVIDIA）：未找到
A84: ubs_27 | B84: UBS：全球 AI 伺服器電源市場 2027 | C84: US$B | E84: 38.2 | G84: Interested-party | H84: 同上 | I84: —
A85: kgi_sh | B85: 凱基：Blackwell 平台 AI 伺服器 PSU 台達電份額 | C85: % | E85: 0.7 | G85: Interested-party | H85: 凱基 Power supply sector（2025-07-01；網址見 Sources） | I85: 第二個量化來源：未找到
A86: pe_fair_andy | B86: Andy 先驗：合理 P/E | C86: x | E86: 25 | G86: Assumed | H86: 先驗_Andy_台達電_20261024 D10b（Drive；不在本 repo） | I86: 只作對照
A87: H. 價格與估值
A88: px | B88: 股價（2026-10-23 收盤） | C88: NT$ | E88: 1605 | G88: Interested-party | H88: Yahoo 股市 2308（10-24 頁面「昨收」1,605） | I88: HiStock、Goodinfo：10-22 收盤 1,560（−4.0%）；兩週 −20.6%
A89: pe_ttm | B89: 近 12 月 P/E（10-22） | C89: x | E89: 49.65 | G89: Interested-party | H89: Goodinfo（10-22） | I89: HiStock 49.65
A90: I. 目標價情境權重（Val 第 0 節用；Andy 可改）
A91: tp_wA | B91: 目標價情境權重：情境 A（順利） | C91: 權重 | E91: 0.3 | G91: Assumed | H91: Andy 可改（2026-10-25 目標價規格預設 A／B／C＝0.3／0.5／0.2） | I91: 三個權重合計應為 1；v0.2 起用於 DCF 與 Comparable 的情境加權（Val 第 0 節）
A92: tp_wB | B92: 目標價情境權重：情境 B（平平） | C92: 權重 | E92: 0.5 | G92: Assumed | H92: Andy 可改（2026-10-25 目標價規格預設 A／B／C＝0.3／0.5／0.2） | I92: 三個權重合計應為 1；v0.2 起用於 DCF 與 Comparable 的情境加權（Val 第 0 節）
A93: tp_wC | B93: 目標價情境權重：情境 C（不如預期） | C93: 權重 | E93: 0.2 | G93: Assumed | H93: Andy 可改（2026-10-25 目標價規格預設 A／B／C＝0.3／0.5／0.2） | I93: 三個權重合計應為 1；v0.2 起用於 DCF 與 Comparable 的情境加權（Val 第 0 節）
A94: J. 目標價（DCF 與 Comparable 加權）與收斂法參數（v0.2 新增；黃底＝Assumed，Andy 可改）
A95: tp_r | B95: 折現率／要求報酬（DCF） | C95: % | E95: 0.1 | G95: Assumed | H95: Andy 可改（工作單 2026-10-25 預設 10%；美、台、日、韓同一值） | I95: Sens 頁 ±1pt
A96: tp_g | B96: 長期成長率（DCF 永續；情境 B 的 FY2032 營收年增收斂目標） | C96: % | E96: 0.04 | G96: Assumed | H96: Andy 可改（工作單預設 4%） | I96: Sens 頁 ±1pt（只動 DCF，PL 收斂目標不隨之變動）
A97: tp_roe | B97: ROE（近三年平均） | C97: % | E97: =AVERAGE(0.1661,0.1547,0.2246) -> 0.1818 | G97: Derived | H97: stockanalysis 比率頁（Return on Equity）：FY2023 16.61%、FY2024 15.47%、FY2025 22.46% | I97: 單一來源；近 12 月 29.97%（同站）
A98: tp_w_dcf | B98: 目標價中 DCF 的權重；其餘為 Comparable | C98: % | E98: 0.5 | G98: Assumed | H98: Andy 可改（2026-10-25 11:53 改為 0.5：DCF／Comparable 各半） | I98: Sens 頁 0.4／0.8
A99: fade_gA | B99: 情境 A（順利）：FY2032 營收年增收斂目標（tp_g＋2pt） | C99: % | E99: =tp_g+0.02 -> 0.06 | G99: Assumed | H99: 工作單 2026-10-25 11:20 收斂法 | I99: FY2030 起由 FY2029 年增線性收斂，FY2032 達到
A100: fade_gB | B100: 情境 B（平平）：FY2032 營收年增收斂目標（＝tp_g） | C100: % | E100: =tp_g -> 0.04 | G100: Assumed | H100: 同上 | I100: —
...

Sheet Q
A1: Q — 實績與 FY2026 錨點（十億新台幣；EPS 為新台幣；股數為十億股）。藍字＝輸入；黑字＝公式。實績取自台達電法說簡報、逐字稿與月營收
A2: FY2026 錨點＝1H26 實績＋3Q26 營收實績（月營收）＋3Q、4Q 假設（毛利率、營業費用率、業外、淨利 ÷ 稅前；4Q 營收＝3Q × (1＋季增)）。1H26 營業利益＝2Q26 30.6＋1Q26（2Q26 ÷ 1.08；公司稱季增 8%）。部門別損益只有年度簡報數字，季度部門數字只在簡報畫面：未找到
A3: 項目 | B3: FY2025A | C3: 1H26（實績） | D3: 3Q26（營收實績） | E3: 4Q26（模型） | F3: FY2026 錨點 | G3: 標記 | H3: 來源1（公司） | I3: 來源2／說明
A4: 營收 | B4: 554.885 | C4: 342.6 | D4: =q3_rev -> 197.059 | E4: =D4*(1+q4g) -> 216.7649 | F4: =SUM(C4:E4) -> 756.4239 | G4: Verified／Interested-party（4Q 季增） | H4: FY2025：https://filecenter.deltaww.com/ir/download/calendar/4Q25_Analyst Meeting.pdf；1H26：https://filecenter.deltaww.com/IR/download/calendar/2Q26_Transcript.pdf | I4: 3Q26 營收：月營收公告（TechNews 2026-10-12）
A5: 毛利 | B5: 190.2 | C5: 124.3 | D5: =D4*q_gm -> 70.94124 | E5: =E4*q_gm -> 78.035364 | F5: =SUM(C5:E5) -> 273.2766 | G5: Verified／Interested-party | H5: FY2025：https://filecenter.deltaww.com/ir/download/calendar/4Q25_Analyst Meeting.pdf；1H26：https://filecenter.deltaww.com/IR/download/calendar/2Q26_Transcript.pdf | I5: 3Q26 營收：月營收公告（TechNews 2026-10-12）
A6: 毛利率 | B6: =B5/B4 -> 0.34277373 | C6: =C5/C4 -> 0.36281378 | D6: =D5/D4 -> 0.36 | E6: =E5/E4 -> 0.36 | F6: =F5/F4 -> 0.36127442 | G6: Derived | H6: — | I6: FY2025 34.3%；1H26 36.3%
A7: 營業費用 | B7: =B5-B8 -> 106.3 | C7: =C5-C8 -> 65.366667 | D7: =D4*q_opx -> 36.455915 | E7: =E4*q_opx -> 40.101506 | F7: =SUM(C7:E7) -> 141.92409 | G7: Derived（毛利 − 營業利益）／Assumed | H7: FY2025：https://filecenter.deltaww.com/ir/download/calendar/4Q25_Analyst Meeting.pdf；1H26：https://filecenter.deltaww.com/IR/download/calendar/2Q26_Transcript.pdf | I7: 3Q26 營收：月營收公告（TechNews 2026-10-12）
A8: 營業利益 | B8: 83.9 | C8: =30.6+30.6/1.08 -> 58.933333 | D8: =D5-D7 -> 34.485325 | E8: =E5-E7 -> 37.933858 | F8: =SUM(C8:E8) -> 131.35252 | G8: Verified／Derived | H8: FY2025：https://filecenter.deltaww.com/ir/download/calendar/4Q25_Analyst Meeting.pdf；1H26：https://filecenter.deltaww.com/IR/download/calendar/2Q26_Transcript.pdf | I8: 3Q26 營收：月營收公告（TechNews 2026-10-12）
A9: 營業利益率 | B9: =B8/B4 -> 0.1512025 | C9: =C8/C4 -> 0.1720179 | D9: =D8/D4 -> 0.175 | E9: =E8/E4 -> 0.175 | F9: =F8/F4 -> 0.17364935 | G9: Derived | H9: — | I9: FY2025 15.1%；1H26 17.2%（公司）
A10: 業外收益 | B10: 3.934 | C10: =C11-C8 -> 7.1666667 | D10: =q_nop -> 2 | E10: =q_nop -> 2 | F10: =SUM(C10:E10) -> 11.166667 | G10: Verified／Derived | H10: FY2025：https://filecenter.deltaww.com/ir/download/calendar/4Q25_Analyst Meeting.pdf；1H26：https://filecenter.deltaww.com/IR/download/calendar/2Q26_Transcript.pdf | I10: 3Q26 營收：月營收公告（TechNews 2026-10-12）
A11: 稅前利益 | B11: =B8+B10 -> 87.834 | C11: 66.1 | D11: =D8+D10 -> 36.485325 | E11: =E8+E10 -> 39.933858 | F11: =SUM(C11:E11) -> 142.51918 | G11: Verified／Derived | H11: FY2025：https://filecenter.deltaww.com/ir/download/calendar/4Q25_Analyst Meeting.pdf；1H26：https://filecenter.deltaww.com/IR/download/calendar/2Q26_Transcript.pdf | I11: FY2025 公司揭露 87.9（四捨五入差）
A12: 歸屬母公司淨利 | B12: 60.108 | C12: 45.7 | D12: =D11*q_nir -> 25.174874 | E12: =E11*q_nir -> 27.554362 | F12: =SUM(C12:E12) -> 98.429236 | G12: Verified／Derived（3Q、4Q） | H12: FY2025：https://filecenter.deltaww.com/ir/download/calendar/4Q25_Analyst Meeting.pdf；1H26：https://filecenter.deltaww.com/IR/download/calendar/2Q26_Transcript.pdf | I12: 3Q26 營收：月營收公告（TechNews 2026-10-12）
A13: 淨利 ÷ 稅前（含稅與非控制權益） | B13: =B12/B11 -> 0.68433636 | C13: =C12/C11 -> 0.6913767 | D13: =D12/D11 -> 0.69 | E13: =E12/E11 -> 0.69 | F13: =F12/F11 -> 0.69063851 | G13: Derived | H13: — | I13: —
A14: 股數（十億股） | B14: =60.108/23.14 -> 2.5975799 | C14: =q_sh -> 2.5980671 | D14: =q_sh -> 2.5980671 | E14: =q_sh -> 2.5980671 | F14: =q_sh -> 2.5980671 | G14: Derived | H14: FY2025：https://filecenter.deltaww.com/ir/download/calendar/4Q25_Analyst Meeting.pdf；1H26：https://filecenter.deltaww.com/IR/download/calendar/2Q26_Transcript.pdf | I14: 淨利 ÷ EPS
A15: EPS | B15: =B12/B14 -> 23.14 | C15: =C12/C14 -> 17.59 | D15: =D12/D14 -> 9.6898477 | E15: =E12/E14 -> 10.605716 | F15: =F12/F14 -> 37.885564 | G15: Derived | H15: 淨利 ÷ 股數 | I15: —
A16: 公司揭露 EPS | B16: 23.14 | C16: 17.59 | G16: Verified | H16: FY2025：https://filecenter.deltaww.com/ir/download/calendar/4Q25_Analyst Meeting.pdf；1H26：https://filecenter.deltaww.com/IR/download/calendar/2Q26_Transcript.pdf | I16: 2Q26 9.68
A17: AI 電源營收（＝營收 × AI 相關占比） | B17: =B4*ai_25 -> 99.8793 | F17: =F4*ai_26 -> 196.67021 | G17: Derived／Interested-party | H17: 公司 AI 相關占比（In 頁 C 節） | I17: 各季 AI 營收未揭露：未找到
A18: 液冷營收（＝營收 × 液冷占比） | B18: =B4*lc_25 -> 55.4885 | F18: =F4*lc_26 -> 94.552988 | G18: Derived／Interested-party | H18: 公司液冷占比 | I18: —
A19: 非 AI 營收（＝營收 − AI 電源 − 液冷） | B19: =B4-B17-B18 -> 399.5172 | F19: =F4-F17-F18 -> 465.2007 | G19: Derived | H19: — | I19: 含非 AI 資料中心、電源零組件、自動化、交通
A20: AI 電源（另一讀法：AI 相關含液冷 → AI 電源＝營收 ×（AI 相關 − 液冷）） | B20: =B4*(ai_25-lc_25) -> 44.3908 | F20: =F4*(ai_26-lc_26) -> 102.11723 | G20: Derived | H20: Sens 用 | I20: —
A21: 非 AI（另一讀法） | B21: =B4-B20-B18 -> 455.0057 | F21: =F4-F20-F18 -> 559.75369 | G21: Derived | H21: Sens 用 | I21: —
A23: FY2026 錨點的檢查（參考；校準未使用券商數字）
A24: FY2026 營收年增 | B24: =F4/B4-1 -> 0.36320841
A25: FY2026 營業費用年增 | B25: =F7/B7-1 -> 0.33512783
A26: 營業費用彈性（營業費用年增 ÷ 營收年增；In 頁 phi 的依據） | B26: =B25/B24 -> 0.92268741
A27: FY2026 營收 ÷ 券商（10-01，3Q 前）− 1 | B27: =F4/b_rev26-1 -> -0.058002615
A28: FY2026 EPS ÷ 券商（本土 10-01）− 1 | B28: =F15/b_eps26a-1 -> -0.1209846
A29: 非 AI 營收 FY2026 年增 | B29: =F19/B19-1 -> 0.16440719
A31: 營收分部（官方四大事業群；v0.3）
A32: 電源及零組件 | B32: =B4*s25_pe -> 277.4425 | F32: =F4*s26_pe -> 385.77619 | G32: Verified（FY2025）／Interested-party（FY2026） | H32: 營收 × 事業群比重（In 頁 C2 節） | I32: 1H26、3Q26 各事業群金額：未全取得（2Q26 電源及零組件、基礎設施見 In 頁）
A33: 交通 | B33: =B4*s25_mo -> 38.84195 | F33: =F4*s26_mo -> 45.385434 | G33: Verified（FY2025）／Interested-party（FY2026） | H33: 營收 × 事業群比重（In 頁 C2 節） | I33: 1H26、3Q26 各事業群金額：未全取得（2Q26 電源及零組件、基礎設施見 In 頁）
A34: 自動化 | B34: =B4*s25_au -> 55.4885 | F34: =F4*s26_au -> 60.513912 | G34: Verified（FY2025）／Interested-party（FY2026） | H34: 營收 × 事業群比重（In 頁 C2 節） | I34: 1H26、3Q26 各事業群金額：未全取得（2Q26 電源及零組件、基礎設施見 In 頁）
A35: 基礎設施 | B35: =B4*s25_inf -> 183.11205 | F35: =F4*s26_inf -> 264.74836 | G35: Verified（FY2025）／Interested-party（FY2026） | H35: 營收 × 事業群比重（In 頁 C2 節） | I35: 1H26、3Q26 各事業群金額：未全取得（2Q26 電源及零組件、基礎設施見 In 頁）
A36: 檢查：分部合計 − 合併營收 | B36: =B32+B33+B34+B35-B4 -> 0 | F36: =F32+F33+F34+F35-F4 -> 0 | G36: Derived | H36: 應為 0 | I36: —

Sheet Units
A1: Units — AI 電源市場、台達電份額、每架內容（本專案權威，規則第 13 條）。部署 GW＝AI IT 資本支出（markets/network）÷ 每 GW IT 資本支出（Tokenomics，經橋接表）
A3: 項目 | B3: 單位 | C3: CY2026 | D3: CY2027 | E3: CY2028 | F3: CY2029 | G3: 說明
A4: 部署 GW（情境 A） | B4: GW | C4: =PL!D85 -> 23.399538 | D4: =PL!E85 -> 41.646766 | E4: =PL!F85 -> 52.792138 | F4: =PL!G85 -> 60.138592 | G4: AI IT 資本支出 ÷ 每 GW IT 資本支出
A5: AI 電源內容 | B5: US$/kW | C5: =PL!D86 -> 450 | D5: =PL!E86 -> 600 | E5: =PL!F86 -> 680 | F5: =PL!G86 -> 720 | G5: In 頁 B 節（2026–27 Derived，2028 起 Assumed）
A6: 每架 AI 電源內容（以 VR200 每 GW 架數換算） | B6: US$K/架 | C6: =PL!D86*1000000/racks_vr/1000 -> 111.05627 | D6: =PL!E86*1000000/racks_vr/1000 -> 148.07502 | E6: =PL!F86*1000000/racks_vr/1000 -> 167.81836 | F6: =PL!G86*1000000/racks_vr/1000 -> 177.69003 | G6: 1 GW ÷ 4,052 架 ≈ 247 kW／架
A7: AI 電源市場 | B7: US$B | C7: =PL!D87 -> 10.529792 | D7: =PL!E87 -> 24.988059 | E7: =PL!F87 -> 35.898654 | F7: =PL!G87 -> 43.299786 | G7: 含 ASIC 機架（假設每 kW 內容相同）
A8: 台達電有效份額 | B8: % | C8: =PL!D91 -> 0.58367194 | D8: =PL!E91 -> 0.55448834 | E8: =PL!F91 -> 0.52530475 | F8: =PL!G91 -> 0.49612115 | G8: FY2026 以公司 AI 相關占比校準
A9: 台達電 AI 電源營收 | B9: US$B | C9: =PL!D92/fx -> 6.1459442 | D9: =PL!E92/fx -> 13.855588 | E9: =PL!F92/fx -> 18.857733 | F9: =PL!G92/fx -> 21.48194
A10: 台達電液冷營收 | B10: US$B | C10: =PL!D96/fx -> 2.9547809 | D10: =PL!E96/fx -> 5.7848481 | E10: =PL!F96/fx -> 7.6662872 | F10: =PL!G96/fx -> 9.1128137 | G10: FY2026 以公司液冷占比校準
A11: 台達電液冷每架營收（以 VR200 架數換算） | B11: US$K/架 | C11: =PL!D96/fx/PL!D85/racks_vr*1000000 -> 31.163667 | D11: =PL!E96/fx/PL!E85/racks_vr*1000000 -> 34.280034 | E11: =PL!F96/fx/PL!F85/racks_vr*1000000 -> 35.838217 | F11: =PL!G96/fx/PL!G85/racks_vr*1000000 -> 37.396401 | G11: 對照：橋接表機架內液冷 VR200 US$56K（台達電多做機架外 CDU、Liquid-to-Air）
A12: 每 GW 台達電 AI 營收（電源＋液冷） | B12: US$M/GW | C12: =PL!D109 -> 388.92755 | D12: =PL!E109 -> 471.5957 | E12: =PL!F109 -> 502.42368 | F12: =PL!G109 -> 508.73744
A13: 其他廠商 AI 電源（光寶、Flex、麥格米特、Vertiv 等）＝ 市場 − 台達電 | B13: US$B | C13: =PL!D87-PL!D92/fx -> 4.3838479 | D13: =PL!E87-PL!E92/fx -> 11.132472 | E13: =PL!F87-PL!F92/fx -> 17.040921 | F13: =PL!G87-PL!G92/fx -> 21.817846
A15: 讀法：FY2026 有效份額低於凱基的 Blackwell PSU 約 70%，因為本模型分母含 ASIC 機架與 HVDC、BBU；份額路徑（相對值）與 2028 年起的每 kW 內容是 Assumed，是最需要每季檢查的輸入。

Sheet PL
A1: PL — 台達電損益（十億新台幣；EPS 新台幣；歸屬母公司）。FY2025A 實績、FY2026 錨點（1H26 實績＋3Q26 營收實績＋假設），FY2027 起為模型。FY(t)＝CY(t)。三情境各一個完整推導區塊（本頁下方），頂端為摘要。FY2026–FY2027 三情境相同（顆數係數從 CY2028 開始）
A3: 情境／項目 | B3: 單位 | C3: FY2025A | D3: FY2026（錨點） | E3: FY2027 | F3: FY2028 | G3: FY2029 | H3: 說明
A4: 情境 A
A5: 營收 | B5: NT$B | C5: =C104 -> 554.885 | D5: =D104 -> 756.4239 | E5: =E104 -> 1121.4932 | F5: =F104 -> 1366.781 | G5: =G104 -> 1518.744
A6: 營收年增 | B6: % | D6: =D106 -> 0.36320841 | E6: =E106 -> 0.48262531 | F6: =F106 -> 0.21871533 | G6: =G106 -> 0.11118315
A7: AI 電源營收 | B7: NT$B | C7: =C92 -> 99.8793 | D7: =D92 -> 196.67021 | E7: =E92 -> 443.37881 | F7: =F92 -> 603.44747 | G7: =G92 -> 687.42207
A8: 液冷營收 | B8: NT$B | C8: =C96 -> 55.4885 | D8: =D96 -> 94.552988 | E8: =E96 -> 185.11514 | F8: =F96 -> 245.32119 | G8: =G96 -> 291.61004
A9: 電源及零組件 | B9: NT$B | C9: =C98 -> 277.4425 | D9: =D98 -> 385.77619 | E9: =E98 -> 641.94008 | F9: =F98 -> 809.95119 | G9: =G98 -> 900.1209
A10: 基礎設施 | B10: NT$B | C10: =C100 -> 183.11205 | D10: =D100 -> 264.74836 | E10: =E100 -> 370.6281 | F10: =F100 -> 443.82006 | G10: =G100 -> 502.01884
A11: 自動化 | B11: NT$B | C11: =C101 -> 55.4885 | D11: =D101 -> 60.513912 | E11: =E101 -> 63.539608 | F11: =F101 -> 66.716588 | G11: =G101 -> 69.385251
A12: 交通 | B12: NT$B | C12: =C102 -> 38.84195 | D12: =D102 -> 45.385434 | E12: =E102 -> 45.385434 | F12: =F102 -> 46.293143 | G12: =G102 -> 47.219006
A13: 非 AI 營收 | B13: NT$B | C13: =C103 -> 399.5172 | D13: =D103 -> 465.2007 | E13: =E103 -> 492.99928 | F13: =F103 -> 518.01232 | G13: =G103 -> 539.71189
A14: AI 電源＋液冷 ÷ 營收 | B14: % | C14: =C108 -> 0.28 | D14: =D108 -> 0.385 | E14: =E108 -> 0.56040815 | F14: =F108 -> 0.62099829 | G14: =G108 -> 0.64463274
A15: 毛利率 | B15: % | C15: =C113 -> 0.34277373 | D15: =D113 -> 0.36127442 | E15: =E113 -> 0.37210217 | F15: =F113 -> 0.37579522 | G15: =G113 -> 0.37668445
A16: 營業利益率 | B16: % | C16: =C117 -> 0.1512025 | D16: =D117 -> 0.17364935 | E16: =E117 -> 0.19669226 | F16: =F117 -> 0.20668126 | G16: =G117 -> 0.21095475
A17: 歸屬母公司淨利 | B17: NT$B | C17: =C120 -> 60.108 | D17: =D120 -> 98.429236 | E17: =E120 -> 157.72644 | F17: =F120 -> 200.43673 | G17: =G120 -> 226.58652
A18: EPS | B18: NT$ | C18: =C122 -> 23.14 | D18: =D122 -> 37.885564 | E18: =E122 -> 60.709148 | F18: =F122 -> 77.148406 | G18: =G122 -> 87.213497
A19: EPS 年增 | B19: % | D19: =D123 -> 0.63723266 | E19: =E123 -> 0.60243486 | F19: =F123 -> 0.27078716 | G19: =G123 -> 0.13046402
A21: 情境 B
A22: 營收 | B22: NT$B | C22: =C150 -> 554.885 | D22: =D150 -> 756.4239 | E22: =E150 -> 1121.4932 | F22: =F150 -> 1197.0272 | G22: =G150 -> 1371.8892
A23: 營收年增 | B23: % | D23: =D152 -> 0.36320841 | E23: =E152 -> 0.48262531 | F23: =F152 -> 0.0673513 | G23: =G152 -> 0.14608016
A24: AI 電源營收 | B24: NT$B | C24: =C138 -> 99.8793 | D24: =D138 -> 196.67021 | E24: =E138 -> 443.37881 | F24: =F138 -> 482.75797 | G24: =G138 -> 584.30876
A25: 液冷營收 | B25: NT$B | C25: =C142 -> 55.4885 | D25: =D142 -> 94.552988 | E25: =E142 -> 185.11514 | F25: =F142 -> 196.25695 | G25: =G142 -> 247.86853
A26: 電源及零組件 | B26: NT$B | C26: =C144 -> 277.4425 | D26: =D144 -> 385.77619 | E26: =E144 -> 641.94008 | F26: =F144 -> 689.2617 | G26: =G144 -> 797.00759
A27: 基礎設施 | B27: NT$B | C27: =C146 -> 183.11205 | D27: =D146 -> 264.74836 | E27: =E146 -> 370.6281 | F27: =F146 -> 394.75582 | G27: =G146 -> 458.27733
A28: 自動化 | B28: NT$B | C28: =C147 -> 55.4885 | D28: =D147 -> 60.513912 | E28: =E147 -> 63.539608 | F28: =F147 -> 66.716588 | G28: =G147 -> 69.385251
A29: 交通 | B29: NT$B | C29: =C148 -> 38.84195 | D29: =D148 -> 45.385434 | E29: =E148 -> 45.385434 | F29: =F148 -> 46.293143 | G29: =G148 -> 47.219006
A30: 非 AI 營收 | B30: NT$B | C30: =C149 -> 399.5172 | D30: =D149 -> 465.2007 | E30: =E149 -> 492.99928 | F30: =F149 -> 518.01232 | G30: =G149 -> 539.71189
A31: AI 電源＋液冷 ÷ 營收 | B31: % | C31: =C154 -> 0.28 | D31: =D154 -> 0.385 | E31: =E154 -> 0.56040815 | F31: =F154 -> 0.56725102 | G31: =G154 -> 0.60659221
A32: 毛利率 | B32: % | C32: =C159 -> 0.34277373 | D32: =D159 -> 0.36127442 | E32: =E159 -> 0.37210217 | F32: =F159 -> 0.37273821 | G32: =G159 -> 0.37454765
A33: 營業利益率 | B33: % | C33: =C163 -> 0.1512025 | D33: =D163 -> 0.17364935 | E33: =E163 -> 0.19669226 | F33: =F163 -> 0.19954203 | G33: =G163 -> 0.20576661
A34: 歸屬母公司淨利 | B34: NT$B | C34: =C166 -> 60.108 | D34: =D166 -> 98.429236 | E34: =E166 -> 157.72644 | F34: =F166 -> 170.3315 | G34: =G166 -> 200.2994
A35: EPS | B35: NT$ | C35: =C168 -> 23.14 | D35: =D168 -> 37.885564 | E35: =E168 -> 60.709148 | F35: =F168 -> 65.560855 | G35: =G168 -> 77.095547
A36: EPS 年增 | B36: % | D36: =D169 -> 0.63723266 | E36: =E169 -> 0.60243486 | F36: =F169 -> 0.079917235 | G36: =G169 -> 0.1759387
A38: 情境 C
A39: 營收 | B39: NT$B | C39: =C196 -> 554.885 | D39: =D196 -> 756.4239 | E39: =E196 -> 1121.4932 | F39: =F196 -> 1027.2735 | G39: =G196 -> 1127.1312
A40: 營收年增 | B40: % | D40: =D198 -> 0.36320841 | E40: =E198 -> 0.48262531 | F40: =F198 -> -0.084012727 | G40: =G198 -> 0.097206478
A41: AI 電源營收 | B41: NT$B | C41: =C184 -> 99.8793 | D41: =D184 -> 196.67021 | E41: =E184 -> 443.37881 | F41: =F184 -> 362.06848 | G41: =G184 -> 412.45324
A42: 液冷營收 | B42: NT$B | C42: =C188 -> 55.4885 | D42: =D188 -> 94.552988 | E42: =E188 -> 185.11514 | F42: =F188 -> 147.19271 | G42: =G188 -> 174.96602
A43: 電源及零組件 | B43: NT$B | C43: =C190 -> 277.4425 | D43: =D190 -> 385.77619 | E43: =E190 -> 641.94008 | F43: =F190 -> 568.5722 | G43: =G190 -> 625.15208
A44: 基礎設施 | B44: NT$B | C44: =C192 -> 183.11205 | D44: =D192 -> 264.74836 | E44: =E192 -> 370.6281 | F44: =F192 -> 345.69158 | G44: =G192 -> 385.37482
A45: 自動化 | B45: NT$B | C45: =C193 -> 55.4885 | D45: =D193 -> 60.513912 | E45: =E193 -> 63.539608 | F45: =F193 -> 66.716588 | G45: =G193 -> 69.385251
A46: 交通 | B46: NT$B | C46: =C194 -> 38.84195 | D46: =D194 -> 45.385434 | E46: =E194 -> 45.385434 | F46: =F194 -> 46.293143 | G46: =G194 -> 47.219006
A47: 非 AI 營收 | B47: NT$B | C47: =C195 -> 399.5172 | D47: =D195 -> 465.2007 | E47: =E195 -> 492.99928 | F47: =F195 -> 518.01232 | G47: =G195 -> 539.71189
A48: AI 電源＋液冷 ÷ 營收 | B48: % | C48: =C200 -> 0.28 | D48: =D200 -> 0.385 | E48: =E200 -> 0.56040815 | F48: =F200 -> 0.4957406 | G48: =G200 -> 0.52116318
A49: 毛利率 | B49: % | C49: =C205 -> 0.34277373 | D49: =D205 -> 0.36127442 | E49: =E205 -> 0.37210217 | F49: =F205 -> 0.36867088 | G49: =G205 -> 0.36974897
A50: 營業利益率 | B50: % | C50: =C209 -> 0.1512025 | D50: =D209 -> 0.17364935 | E50: =E209 -> 0.19669226 | F50: =F209 -> 0.17717269 | G50: =G209 -> 0.18164392
A51: 歸屬母公司淨利 | B51: NT$B | C51: =C212 -> 60.108 | D51: =D212 -> 98.429236 | E51: =E212 -> 157.72644 | F51: =F212 -> 131.10332 | G51: =G212 -> 146.7882
A52: EPS | B52: NT$ | C52: =C214 -> 23.14 | D52: =D214 -> 37.885564 | E52: =E214 -> 60.709148 | F52: =F214 -> 50.46187 | G52: =G214 -> 56.499004
A53: EPS 年增 | B53: % | D53: =D215 -> 0.63723266 | E53: =E215 -> 0.60243486 | F53: =F215 -> -0.16879298 | G53: =G215 -> 0.11963753
A55: 核對（應為 0）：FY2026 模型營收 − 錨點；FY2026 模型 AI 電源 − 錨點；FY2026 毛利 − 錨點
A56: 情境 A：營收差（NT$B） | D56: =D104-a26_rev -> 0
A57: 情境 A：AI 電源差（NT$B） | D57: =D92-a26_aip -> 0
A58: 情境 A：毛利差（NT$B） | D58: =D111*D104+d_ai*D92-a26_gp -> 0
A80: 情境 A：基準（顆數係數 1.0）
A81: 項目 | B81: 單位 | C81: FY2025A | D81: FY2026（錨點） | E81: FY2027 | F81: FY2028 | G81: FY2029 | H81: 說明
A82: A. AI 部署與電源市場（D 欄＝FY2026 校準年；E–G＝FY2027–FY2029）
A83: AI IT 資本支出 × 情境顆數係數 | B83: US$B | D83: =itc_26*1 -> 781.87292 | E83: =itc_27*1*1 -> 1565.35 | F83: =itc_28*um28_A*1 -> 1984.2639 | G83: =itc_29*um29_A*1 -> 2260.3903
A84: 每 GW IT 資本支出 | B84: US$B | D84: =itpg_gb*(1-vr26)+itpg_vr*vr26 -> 33.414032 | E84: =itpg_vr -> 37.586352 | F84: =itpg_vr -> 37.586352 | G84: =itpg_vr -> 37.586352
A85: 部署 GW（IT 電力） | B85: GW | D85: =D83/D84 -> 23.399538 | E85: =E83/E84 -> 41.646766 | F85: =F83/F84 -> 52.792138 | G85: =G83/G84 -> 60.138592
A86: AI 電源內容 | B86: US$/kW | D86: =pkw_26 -> 450 | E86: =pkw_27 -> 600 | F86: =pkw_28 -> 680 | G86: =pkw_29 -> 720
A87: AI 電源市場（美元） | B87: US$B | D87: =D85*D86/1000 -> 10.529792 | E87: =E85*E86/1000 -> 24.988059 | F87: =F85*F86/1000 -> 35.898654 | G87: =G85*G86/1000 -> 43.299786
A88: AI 電源市場（新台幣） | B88: NT$B | D88: =D87*fx -> 336.95335 | E88: =E87*fx -> 799.6179 | F88: =F87*fx -> 1148.7569 | G88: =G87*fx -> 1385.5932
A89: 台達電有效份額（FY2026 校準）＝ AI 電源營收 ÷ 市場 | B89: % | D89: =a26_aip/D88 -> 0.58367194 | H89: Derived：分子為公司 AI 相關占比 × 營收；分母為本模型的 AI 電源市場（含 ASIC 機架）
A90: 份額相對值（÷ FY2026） | B90: x | D90: =1 -> 1 | E90: =rel_27 -> 0.95 | F90: =rel_28 -> 0.9 | G90: =rel_29 -> 0.85
A91: 台達電有效份額 | B91: % | D91: =$D$89*D90 -> 0.58367194 | E91: =$D$89*E90 -> 0.55448834 | F91: =$D$89*F90 -> 0.52530475 | G91: =$D$89*G90 -> 0.49612115
A92: AI 電源營收 | B92: NT$B | C92: =a25_aip -> 99.8793 | D92: =D88*D91 -> 196.67021 | E92: =E88*E91 -> 443.37881 | F92: =F88*F91 -> 603.44747 | G92: =G88*G91 -> 687.42207
A93: B. 液冷、非 AI 與合計
A94: 液冷每 GW 營收（FY2026 校準） | B94: NT$B/GW | D94: =a26_lc/D85 -> 4.0408057
A95: 液冷每 GW 相對值（÷ FY2026） | B95: x | D95: =1 -> 1 | E95: =lcr_27 -> 1.1 | F95: =lcr_28 -> 1.15 | G95: =lcr_29 -> 1.2
A96: 液冷營收 | B96: NT$B | C96: =a25_lc -> 55.4885 | D96: =D85*$D$94*D95 -> 94.552988 | E96: =E85*$D$94*E95 -> 185.11514 | F96: =F85*$D$94*F95 -> 245.32119 | G96: =G85*$D$94*G95 -> 291.61004
A97: 電源及零組件：非 AI | B97: NT$B | C97: =a25_pe-a25_aip -> 177.5632 | D97: =a26_pe-a26_aip -> 189.10598 | E97: =D97*(1+g_pe27) -> 198.56127 | F97: =E97*(1+g_pe28) -> 206.50372 | G97: =F97*(1+g_pe29) -> 212.69884 | H97: AI 電源（上列）為本分部的命題子列；FY2025、FY2026＝分部 − AI 電源
A98: 電源及零組件 | B98: NT$B | C98: =C92+C97 -> 277.4425 | D98: =D92+D97 -> 385.77619 | E98: =E92+E97 -> 641.94008 | F98: =F92+F97 -> 809.95119 | G98: =G92+G97 -> 900.1209 | H98: ＝AI 電源＋非 AI
A99: 基礎設施：非液冷 | B99: NT$B | C99: =a25_inf-a25_lc -> 127.62355 | D99: =a26_inf-a26_lc -> 170.19538 | E99: =D99*(1+g_inf27) -> 185.51296 | F99: =E99*(1+g_inf28) -> 198.49887 | G99: =F99*(1+g_inf29) -> 210.4088 | H99: 液冷（上列）為本分部的命題子列（Assumed：液冷全部歸基礎設施）
A100: 基礎設施 | B100: NT$B | C100: =C96+C99 -> 183.11205 | D100: =D96+D99 -> 264.74836 | E100: =E96+E99 -> 370.6281 | F100: =F96+F99 -> 443.82006 | G100: =G96+G99 -> 502.01884 | H100: ＝液冷＋非液冷
A101: 自動化 | B101: NT$B | C101: =a25_au -> 55.4885 | D101: =a26_au -> 60.513912 | E101: =D101*(1+g_au27) -> 63.539608 | F101: =E101*(1+g_au28) -> 66.716588 | G101: =F101*(1+g_au29) -> 69.385251
A102: 交通 | B102: NT$B | C102: =a25_mo -> 38.84195 | D102: =a26_mo -> 45.385434 | E102: =D102*(1+g_mo27) -> 45.385434 | F102: =E102*(1+g_mo28) -> 46.293143 | G102: =F102*(1+g_mo29) -> 47.219006
A103: 非 AI 營收（電源非 AI＋基礎設施非液冷＋自動化＋交通） | B103: NT$B | C103: =C97+C99+C101+C102 -> 399.5172 | D103: =D97+D99+D101+D102 -> 465.2007 | E103: =E97+E99+E101+E102 -> 492.99928 | F103: =F97+F99+F101+F102 -> 518.01232 | G103: =G97+G99+G101+G102 -> 539.71189
A104: 營收 | B104: NT$B | C104: =C98+C100+C101+C102 -> 554.885 | D104: =D98+D100+D101+D102 -> 756.4239 | E104: =E98+E100+E101+E102 -> 1121.4932 | F104: =F98+F100+F101+F102 -> 1366.781 | G104: =G98+G100+G101+G102 -> 1518.744 | H104: ＝四大事業群合計
A105: 檢查：分部合計 − 合併營收（FY2025 實績、FY2026 錨點） | B105: NT$B | C105: =C104-a25_rev -> 0 | D105: =D104-a26_rev -> 0
A106: 營收年增 | B106: % | D106: =D104/C104-1 -> 0.36320841 | E106: =E104/D104-1 -> 0.48262531 | F106: =F104/E104-1 -> 0.21871533 | G106: =G104/F104-1 -> 0.11118315
A107: AI 電源 ÷ 營收 | B107: % | C107: =C92/C104 -> 0.18 | D107: =D92/D104 -> 0.26 | E107: =E92/E104 -> 0.39534684 | F107: =F92/F104 -> 0.44151 | G107: =G92/G104 -> 0.45262537
A108: AI 電源＋液冷 ÷ 營收 | B108: % | C108: =(C92+C96)/C104 -> 0.28 | D108: =(D92+D96)/D104 -> 0.385 | E108: =(E92+E96)/E104 -> 0.56040815 | F108: =(F92+F96)/F104 -> 0.62099829 | G108: =(G92+G96)/G104 -> 0.64463274
A109: 每 GW 台達電 AI 營收（電源＋液冷） | B109: US$M/GW | D109: =(D92+D96)/fx/D85*1000 -> 388.92755 | E109: =(E92+E96)/fx/E85*1000 -> 471.5957 | F109: =(F92+F96)/fx/F85*1000 -> 502.42368 | G109: =(G92+G96)/fx/G85*1000 -> 508.73744
A110: C. 損益
A111: 其他營收毛利率 ＝ 錨點毛利率 − 差距 × AI 電源占比（FY2026 校準） | B111: % | D111: =a26_gp/D104-d_ai*D107 -> 0.34047442 | H111: Derived：讓 FY2026 毛利率等於錨點；AI 電源毛利率＝其他 + 差距。FY2027 起毛利率隨 AI 電源占比變動
A112: 毛利 | B112: NT$B | C112: =a25_gp -> 190.2 | D112: =a26_gp -> 273.2766 | E112: =$D$111*E104+d_ai*E92 -> 417.31006 | F112: =$D$111*F104+d_ai*F92 -> 513.62976 | G112: =$D$111*G104+d_ai*G92 -> 572.08724
A113: 毛利率 | B113: % | C113: =C112/C104 -> 0.34277373 | D113: =D112/D104 -> 0.36127442 | E113: =E112/E104 -> 0.37210217 | F113: =F112/F104 -> 0.37579522 | G113: =G112/G104 -> 0.37668445
A114: 營業費用（基準路徑） | B114: NT$B | C114: =a25_opx -> 106.3 | D114: =a26_opx -> 141.92409 | E114: =D114*(1+MAX(0,phi*E106)) -> 196.72101 | F114: =E114*(1+MAX(0,phi*F106)) -> 231.14174 | G114: =F114*(1+MAX(0,phi*G106)) -> 251.70099
A115: 營業費用 | B115: NT$B | C115: =C114 -> 106.3 | D115: =D114 -> 141.92409 | E115: =E114+0*E104 -> 196.72101 | F115: =F114+0*F104 -> 231.14174 | G115: =G114+0*G104 -> 251.70099
A116: 營業利益 | B116: NT$B | C116: =C112-C115 -> 83.9 | D116: =D112-D115 -> 131.35252 | E116: =E112-E115 -> 220.58904 | F116: =F112-F115 -> 282.48802 | G116: =G112-G115 -> 320.38626
A117: 營業利益率 | B117: % | C117: =C116/C104 -> 0.1512025 | D117: =D116/D104 -> 0.17364935 | E117: =E116/E104 -> 0.19669226 | F117: =F116/F104 -> 0.20668126 | G117: =G116/G104 -> 0.21095475
A118: 業外收益 | B118: NT$B | C118: =a25_nop -> 3.934 | D118: =a26_nop -> 11.166667 | E118: =nop_f -> 8 | F118: =nop_f -> 8 | G118: =nop_f -> 8
A119: 歸屬母公司淨利 ÷ 稅前 | B119: % | C119: =a25_ni/(a25_oi+a25_nop) -> 0.68433636 | D119: =a26_ni/(a26_oi+a26_nop) -> 0.69063851 | E119: =nir_f -> 0.69 | F119: =nir_f -> 0.69 | G119: =nir_f -> 0.69
A120: 歸屬母公司淨利 | B120: NT$B | C120: =a25_ni -> 60.108 | D120: =a26_ni -> 98.429236 | E120: =(E116+E118)*E119 -> 157.72644 | F120: =(F116+F118)*F119 -> 200.43673 | G120: =(G116+G118)*G119 -> 226.58652
A121: 股數 | B121: 十億股 | C121: =a25_sh -> 2.5975799 | D121: =a26_sh -> 2.5980671 | E121: =D121*(1+sh_g) -> 2.5980671 | F121: =E121*(1+sh_g) -> 2.5980671 | G121: =F121*(1+sh_g) -> 2.5980671
A122: EPS | B122: NT$ | C122: =C120/C121 -> 23.14 | D122: =D120/D121 -> 37.885564 | E122: =E120/E121 -> 60.709148 | F122: =F120/F121 -> 77.148406 | G122: =G120/G121 -> 87.213497
A123: EPS 年增 | B123: % | D123: =D122/C122-1 -> 0.63723266 | E123: =E122/D122-1 -> 0.60243486 | F123: =F122/E122-1 -> 0.27078716 | G123: =G122/F122-1 -> 0.13046402
A126: 情境 B：CY2028 顆數 ×0.8、CY2029 ×0.85
A127: 項目 | B127: 單位 | C127: FY2025A | D127: FY2026（錨點） | E127: FY2027 | F127: FY2028 | G127: FY2029 | H127: 說明
...

Sheet Val
A1: Val — P/E 估值（新台幣）。結論用「現價 ÷ FY2027、FY2028 EPS（模型）」與十年 P/E 規則值（年底落後 P/E，基準為 FY2027 EPS）
A2: 循環位置：台達電不是設備股，不套設備市場見頂年；以本模型營收最高的會計年度為見頂年（比照 NVIDIA、Arista；FY(t)＝CY(t)）。營收到 FY2029 仍在增加時，見頂年未知，判為中段
A3: 目標價：見第 0 節（本頁第 85 列；v0.2 新增，DCF 與 Comparable 加權）。第 41 列「舊法：規則值情境加權（參考）」不再是目標價，只作參考
A4: 1. 價格與市場隱含倍數
A5: 項目 | B5: A | C5: B | D5: C | E5: 說明
A6: 現價（2026-10-23 收盤） | B6: =px -> 1605
A7: 現價 ÷ FY2026 EPS（錨點） | B7: =px/PL!D18 -> 42.364422 | C7: =px/PL!D35 -> 42.364422 | D7: =px/PL!D52 -> 42.364422
A8: 現價 ÷ FY2027 EPS（模型） | B8: =px/PL!E18 -> 26.437531 | C8: =px/PL!E35 -> 26.437531 | D8: =px/PL!E52 -> 26.437531 | E8: FY2027 三情境相同（顆數係數從 CY2028 開始）
A9: 現價 ÷ FY2028 EPS（模型） | B9: =px/PL!F18 -> 20.804059 | C9: =px/PL!F35 -> 24.481072 | D9: =px/PL!F52 -> 31.806193
A10: 現價 ÷ FY2029 EPS（模型） | B10: =px/PL!G18 -> 18.403115 | C10: =px/PL!G35 -> 20.818323 | D10: =px/PL!G52 -> 28.407581
A11: 未來 12 月 EPS（模型 A）≈ ¼ FY2026＋¾ FY2027 | B11: =0.25*PL!D18+0.75*PL!E18 -> 55.003252
A12: 現價 ÷ 未來 12 月 EPS（模型 A） | B12: =px/B11 -> 29.180093 | E12: Andy 先驗 D10a 答 30x（未來 12 月）
A13: 近 12 月 P/E（Goodinfo，10-22） | B13: =pe_ttm -> 49.65
A15: 2. 循環位置（本模型營收最高年；FY(t)＝CY(t)）
A16: 情境 | B16: 營收最高年（FY2026–FY2029） | C16: FY2027 判定 | D16: 規則倍數（P/E） | E16: 見頂年是否未知 | F16: 說明
A17: A | B17: =INDEX({2026,2027,2028,2029},MATCH(MAX(PL!D104:G104),PL!D104:G104,0)) -> 2029 | C17: =IF(B17=2029,"中段",IF(2027<B17,"中段",IF(2027=B17,"見頂","谷底"))) -> 中段 | D17: =IF(C17="見頂",pe_peak,IF(C17="谷底",pe_trough,pe_mid)) -> 22.4 | E17: =IF(B17=2029,"是：營收到觀測期末仍在增加","否") -> 是：營收到觀測期末仍在增加 | F17: tools/cycle_position.py excel_rule；營收最高年取代設備市場見頂年
A18: B | B18: =INDEX({2026,2027,2028,2029},MATCH(MAX(PL!D150:G150),PL!D150:G150,0)) -> 2029 | C18: =IF(B18=2029,"中段",IF(2027<B18,"中段",IF(2027=B18,"見頂","谷底"))) -> 中段 | D18: =IF(C18="見頂",pe_peak,IF(C18="谷底",pe_trough,pe_mid)) -> 22.4 | E18: =IF(B18=2029,"是：營收到觀測期末仍在增加","否") -> 是：營收到觀測期末仍在增加 | F18: 同上
A19: C | B19: =INDEX({2026,2027,2028,2029},MATCH(MAX(PL!D196:G196),PL!D196:G196,0)) -> 2029 | C19: =IF(B19=2029,"中段",IF(2027<B19,"中段",IF(2027=B19,"見頂","谷底"))) -> 中段 | D19: =IF(C19="見頂",pe_peak,IF(C19="谷底",pe_trough,pe_mid)) -> 22.4 | E19: =IF(B19=2029,"是：營收到觀測期末仍在增加","否") -> 是：營收到觀測期末仍在增加 | F19: 同上
A21: 3. 規則值隱含股價（新台幣；約 FY2027 年底，未折現）＝ FY2027 EPS × 規則倍數
A22: 情境 | B22: FY2027 EPS | C22: （同左） | D22: 規則倍數 | E22: 隱含股價 | F22: 相對現價 | G22: 現價 ÷ FY2027 EPS
A23: A | B23: =PL!E18 -> 60.709148 | C23: =B23 -> 60.709148 | D23: =D17 -> 22.4 | E23: =C23*D23 -> 1359.8849 | F23: =E23/px-1 -> -0.15271968 | G23: =px/C23 -> 26.437531
A24: B | B24: =PL!E35 -> 60.709148 | C24: =B24 -> 60.709148 | D24: =D18 -> 22.4 | E24: =C24*D24 -> 1359.8849 | F24: =E24/px-1 -> -0.15271968 | G24: =px/C24 -> 26.437531
A25: C | B25: =PL!E52 -> 60.709148 | C25: =B25 -> 60.709148 | D25: =D19 -> 22.4 | E25: =C25*D25 -> 1359.8849 | F25: =E25/px-1 -> -0.15271968 | G25: =px/C25 -> 26.437531
A26: 4. What must be true：FY2027 年底價 ＝ 現價 ×（1＋報酬）所需的倍數（FY2028 EPS；約 2027 年底的價格看下一年 EPS）
A27: FY2027 年底價 ÷ 現價 | B27: 所需倍數（÷ FY2028 EPS，A） | C27: 所需倍數（÷ FY2028 EPS，C） | D27: 對照：Andy 合理 P/E | E27: 對照：十年中位數
A28: 1 | B28: =px*A28/PL!F18 -> 20.804059 | C28: =px*A28/PL!F52 -> 31.806193 | D28: =pe_fair_andy -> 25 | E28: =pe_mid -> 22.4
A29: 1.1 | B29: =px*A29/PL!F18 -> 22.884465 | C29: =px*A29/PL!F52 -> 34.986813 | D29: =pe_fair_andy -> 25 | E29: =pe_mid -> 22.4
A30: 1.21 | B30: =px*A30/PL!F18 -> 25.172912 | C30: =px*A30/PL!F52 -> 38.485494 | D30: =pe_fair_andy -> 25 | E30: =pe_mid -> 22.4
A31: 1.5 | B31: =px*A31/PL!F18 -> 31.206089 | C31: =px*A31/PL!F52 -> 47.70929 | D31: =pe_fair_andy -> 25 | E31: =pe_mid -> 22.4
A32: 2 | B32: =px*A32/PL!F18 -> 41.608118 | C32: =px*A32/PL!F52 -> 63.612387 | D32: =pe_fair_andy -> 25 | E32: =pe_mid -> 22.4
A33: 讀法：1.00＝價格不變、1.21＝一年約 21%。所需倍數低於歷史中位數時，現價相對便宜；倍數是否合理，另看前瞻 P/E 歷史（Bloomberg）。
A35: 5. 對照：以 Andy 合理 P/E 25x 計算的隱含價（只作對照，非規則值）
A36: 情境 | B36: FY2027 EPS | C36: × 25x | D36: 相對現價 | E36: FY2028 EPS | F36: × 25x | G36: 相對現價
A37: A | B37: =PL!E18 -> 60.709148 | C37: =B37*pe_fair_andy -> 1517.7287 | D37: =C37/px-1 -> -0.054374642 | E37: =PL!F18 -> 77.148406 | F37: =E37*pe_fair_andy -> 1928.7101 | G37: =F37/px-1 -> 0.20168857
A38: B | B38: =PL!E35 -> 60.709148 | C38: =B38*pe_fair_andy -> 1517.7287 | D38: =C38/px-1 -> -0.054374642 | E38: =PL!F35 -> 65.560855 | F38: =E38*pe_fair_andy -> 1639.0214 | G38: =F38/px-1 -> 0.021197122
A39: C | B39: =PL!E52 -> 60.709148 | C39: =B39*pe_fair_andy -> 1517.7287 | D39: =C39/px-1 -> -0.054374642 | E39: =PL!F52 -> 50.46187 | F39: =E39*pe_fair_andy -> 1261.5468 | G39: =F39/px-1 -> -0.21398956
A41: 舊法：規則值情境加權（參考；v0.1.1 的「0. 目標價與上檔空間」改名，不再是目標價；權重為 In 頁 tp_wA／tp_wB／tp_wC）
A42: 舊法隱含價（情境加權，參考） | B42: =tp_wA*B44+tp_wB*B45+tp_wC*B46 -> 1359.8849 | E42: ＝權重 A × 情境 A 隱含價＋權重 B × 情境 B 隱含價＋權重 C × 情境 C 隱含價（NT$）
A43: 舊法隱含價相對現價（÷ 現價 − 1） | B43: =B42/px-1 -> -0.15271968 | E43: 相對「現價（2026-10-23 收盤）」
A44: 情境 A 隱含價（樂觀） | B44: =E23 -> 1359.8849 | E44: ＝規則值隱含股價 E23（情境 A：基準（顆數係數 1.0））
A45: 情境 B 隱含價（基準） | B45: =E24 -> 1359.8849 | E45: ＝規則值隱含股價 E24（情境 B：CY2028 顆數 ×0.8、CY2029 ×0.85）
A46: 情境 C 隱含價（下檔） | B46: =E25 -> 1359.8849 | E46: ＝規則值隱含股價 E25（情境 C：CY2028–29 顆數 ×0.6）
A47: 情境權重 A／B／C | B47: =tp_wA -> 0.3 | C47: =tp_wB -> 0.5 | D47: =tp_wC -> 0.2 | E47: In 頁輸入（Assumed，Andy 可改）：B 欄＝情境 A、C 欄＝情境 B、D 欄＝情境 C
A48: 舊法說明 | B48: P/E 規則值：各情境 FY2027 EPS × 2016–2025 年底 P/E 依循環位置取分位（見頂＝25 分位、中段＝中位數、谷底＝75 分位；companiesmarketcap 一個來源）。隱含價約為 FY2027 年底價、未折現，作 12 個月目標價的近似；情境 A／B／C 即本模型三個顆數情境（A 最高、C 最低）。偏誤：十年倍數含 2016–2019 年低成長電源期低倍數（約 15–17x），目標價可能偏低。
A50: 6. 十年倍數與規則值（2016–2025 年底；見頂年 25 分位、中段中位數、谷底 75 分位）
A51: 規則（Andy 2026-10-13）：合理倍數＝2016–2025 年底 P/E 依循環位置取分位。只有一個來源（第二來源：未找到；Goodinfo 歷年加權平均 P/E 區間 20.96–44.37 只作量級核對）。2016–2019 年台達電為低成長電源零組件公司（約 15–17x），AI 前後的倍數口徑不同，規則值可能低估 AI 期的合理倍數。
A53: P/E：十年歷史倍數
A54: 年底 | B54: companiesmarketcap（年底 P/E） | C54: 標記／說明
A55: 2016 | B55: 17.2 | C55: companiesmarketcap（年底 P/E）：Interested-party（資料商；2016–2025 共 10 年）
A56: 2017 | B56: 16.4
A57: 2018 | B57: 15.3
A58: 2019 | B58: 14.9
A59: 2020 | B59: 23.8
A60: 2021 | B60: 24.4
A61: 2022 | B61: 21.3
A62: 2023 | B62: 23.5
A63: 2024 | B63: 31.5
A64: 2025 | B64: 41.5
A65: 25 分位（各來源） | B65: =PERCENTILE(B55:B64,0.25) -> 16.6
A66: 中位數（各來源） | B66: =MEDIAN(B55:B64) -> 22.4
A67: 75 分位（各來源） | B67: =PERCENTILE(B55:B64,0.75) -> 24.25
A68: 最小（各來源） | B68: =MIN(B55:B64) -> 14.9
A69: 最大（各來源） | B69: =MAX(B55:B64) -> 41.5
A70: 採用 25 分位（P/E） | B70: =ROUND(AVERAGE(B65),2) -> 16.6
A71: 採用 中位數（P/E） | B71: =ROUND(AVERAGE(B66),2) -> 22.4
A72: 採用 75 分位（P/E） | B72: =ROUND(AVERAGE(B67),2) -> 24.25
A73: 採用 最小（P/E） | B73: =ROUND(MIN(B68),2) -> 14.9
A74: 採用 最大（P/E） | B74: =ROUND(MAX(B69),2) -> 41.5
A76: P/E：規則值
A77: 情形 | B77: 循環位置 | C77: 倍數 | D77: 基準 | E77: 每股基準 | F77: 隱含股價 | G77: 相對目前 | H77: 現價 ÷ 基準
A78: 規則值：見頂（P/E） | B78: 25 分位 | C78: =B70 -> 16.6 | D78: FY2027 EPS（A） | E78: =C23 -> 60.709148 | F78: =C78*E78 -> 1007.7719 | G78: =F78/px-1 -> -0.37210476 | H78: =px/E78 -> 26.437531
A79: 規則值：中段（P/E） | B79: 中位數 | C79: =B71 -> 22.4 | D79: FY2027 EPS（A） | E79: =C23 -> 60.709148 | F79: =C79*E79 -> 1359.8849 | G79: =F79/px-1 -> -0.15271968 | H79: =px/E79 -> 26.437531
A80: 規則值：谷底（P/E） | B80: 75 分位 | C80: =B72 -> 24.25 | D80: FY2027 EPS（A） | E80: =C23 -> 60.709148 | F80: =C80*E80 -> 1472.1968 | G80: =F80/px-1 -> -0.082743403 | H80: =px/E80 -> 26.437531
A85: 0. 目標價（DCF 與 Comparable 加權；v0.2 新增，放在本頁既有內容之後以免位移既有儲存格；三情境欄 B／C／D＝A 順利／B 平平／C 不如預期）
A86: 0.1 DCF（股東權益現金流，FY2027–FY2032 明確期＋FY2032 後永續）
A87: 項目 | B87: A（順利） | C87: B（平平） | D87: C（不如預期） | E87: 說明
A88: 情境 EPS（FY2027–FY2032） | E88: PL 頁延伸表；FY2030 起為收斂法
A89: FY2027 | B89: =PL!E226 -> 60.709148 | C89: =PL!E238 -> 60.709148 | D89: =PL!E250 -> 60.709148
A90: FY2028 | B90: =PL!F226 -> 77.148406 | C90: =PL!F238 -> 65.560855 | D90: =PL!F250 -> 50.46187
A91: FY2029 | B91: =PL!G226 -> 87.213497 | C91: =PL!G238 -> 77.095547 | D91: =PL!G250 -> 56.499004
A92: FY2030 | B92: =PL!H226 -> 95.422215 | C92: =PL!H238 -> 82.777188 | D92: =PL!H250 -> 56.50124
A93: FY2031 | B93: =PL!I226 -> 102.77555 | C93: =PL!I238 -> 85.945789 | D93: =PL!I250 -> 54.86497
A94: FY2032 | B94: =PL!J226 -> 108.94208 | C94: =PL!J238 -> 86.191349 | D94: =PL!J250 -> 51.657479
A95: 股東現金流＝EPS ×（1 − tp_g ÷ tp_roe）
A96: 再投資率（tp_g ÷ tp_roe，上限 0.8） | B96: =MIN(tp_g/tp_roe,0.8) -> 0.220022 | E96: ROE 為近三年平均（In 頁 tp_roe）
A97: FY2027 | B97: =B89*(1-$B$96) -> 47.3518 | C97: =C89*(1-$B$96) -> 47.3518 | D97: =D89*(1-$B$96) -> 47.3518
A98: FY2028 | B98: =B90*(1-$B$96) -> 60.174059 | C98: =C90*(1-$B$96) -> 51.136025 | D98: =D90*(1-$B$96) -> 39.359148
A99: FY2029 | B99: =B91*(1-$B$96) -> 68.024609 | C99: =C91*(1-$B$96) -> 60.13283 | D99: =D91*(1-$B$96) -> 44.06798
A100: FY2030 | B100: =B92*(1-$B$96) -> 74.427228 | C100: =C92*(1-$B$96) -> 64.564386 | D100: =D92*(1-$B$96) -> 44.069724
A101: FY2031 | B101: =B93*(1-$B$96) -> 80.162669 | C101: =C93*(1-$B$96) -> 67.035825 | D101: =D93*(1-$B$96) -> 42.793469
A102: FY2032 | B102: =B94*(1-$B$96) -> 84.972429 | C102: =C94*(1-$B$96) -> 67.227356 | D102: =D94*(1-$B$96) -> 40.291697
A103: DCF 情境每股價值（折現率 tp_r） | B103: =SUMPRODUCT(B97:B102,1/(1+tp_r)^{1;2;3;4;5;6})+B102*(1+tp_g)/(tp_r-tp_g)/(1+tp_r)^6 -> 1123.8483 | C103: =SUMPRODUCT(C97:C102,1/(1+tp_r)^{1;2;3;4;5;6})+C102*(1+tp_g)/(tp_r-tp_g)/(1+tp_r)^6 -> 911.92425 | D103: =SUMPRODUCT(D97:D102,1/(1+tp_r)^{1;2;3;4;5;6})+D102*(1+tp_g)/(tp_r-tp_g)/(1+tp_r)^6 -> 582.32206 | E103: Σ 明確期現金流 ÷ (1＋r)^t ＋ 永續價值 ÷ (1＋r)^6；永續價值＝FY2032 現金流 ×(1＋g)÷(r−g)；基準日 2026 年底，t＝1 對 FY2027
A104: DCF 情境價值推到 12 個月後（×(1＋tp_r)） | B104: =B103*(1+tp_r) -> 1236.2332 | C104: =C103*(1+tp_r) -> 1003.1167 | D104: =D103*(1+tp_r) -> 640.55427
A105: DCF 目標價（情境加權） | B105: =tp_wA*B104+tp_wB*C104+tp_wC*D104 -> 1000.5391 | E105: Σ tp_wA／wB／wC × 情境價值 ×(1＋tp_r)；權重見 In 頁
A107: 0.2 Comparable（市場主流同業前瞻 P/E）
A108: 同業與前瞻 P/E | B108: 代號 | C108: 前瞻 12 月 P/E | D108: 日期 | E108: 來源 | F108: 標記
A109: Vertiv | B109: VRT | C109: 24.53 | D109: 2026-10-23 | E109: stockanalysis.com 個股頁 Forward PE（分析師共識；價格日期如左） | F109: Interested-party（賣方共識）
A110: Eaton | B110: ETN | C110: 24.17 | D110: 2026-10-23 | E110: stockanalysis.com 個股頁 Forward PE（分析師共識；價格日期如左） | F110: Interested-party（賣方共識）
A111: Schneider Electric | B111: SU.PA | C111: 19.13 | D111: 2026-10-23 | E111: stockanalysis.com 個股頁 Forward PE（分析師共識；價格日期如左） | F111: Interested-party（賣方共識）
A112: 光寶科（Lite-On） | B112: 2301.TW | C112: 19.7 | D112: 2026-10-22 | E112: stockanalysis.com 個股頁 Forward PE（分析師共識；價格日期如左） | F112: Interested-party（賣方共識）
...

Sheet Recon
A1: Recon — 本模型 vs 券商估計、研調市場與份額。只作事後對照，不為對上數字而調參數。券商皆未具名或單一來源；2027 共識（付費）未找到
A3: 項目 | B3: 對照值 | C3: 模型 A | D3: 差距 A | E3: 模型 B | F3: 差距 B | G3: 模型 C | H3: 差距 C | I3: 對照來源 | J3: 說明
A4: A. 券商估計（校準未使用）
A5: FY2026 營收 vs 券商（10-01，3Q 前） | B5: =b_rev26 -> 803 | C5: =PL!D104 -> 756.4239 | D5: =C5/B5-1 -> -0.058002615 | E5: =PL!D150 -> 756.4239 | F5: =E5/B5-1 -> -0.058002615 | G5: =PL!D196 -> 756.4239 | H5: =G5/B5-1 -> -0.058002615 | I5: 旺得富 2026-10-01 | J5: 券商 3Q 估 2,093 億，實際 1,971 億
A6: FY2026 EPS vs 本土券商（10-01） | B6: =b_eps26a -> 43.1 | C6: =PL!D122 -> 37.885564 | D6: =C6/B6-1 -> -0.1209846 | E6: =PL!D168 -> 37.885564 | F6: =E6/B6-1 -> -0.1209846 | G6: =PL!D214 -> 37.885564 | H6: =G6/B6-1 -> -0.1209846 | I6: 旺得富 2026-10-01
A7: FY2026 EPS vs 美系券商（05-04） | B7: =b_eps26b -> 41.5 | C7: =PL!D122 -> 37.885564 | D7: =C7/B7-1 -> -0.087094851 | E7: =PL!D168 -> 37.885564 | F7: =E7/B7-1 -> -0.087094851 | G7: =PL!D214 -> 37.885564 | H7: =G7/B7-1 -> -0.087094851 | I7: CMoney 2026-05-04
A8: FY2027 營收 vs 投顧研究團隊 | B8: =b_rev27 -> 1050 | C8: =PL!E104 -> 1121.4932 | D8: =C8/B8-1 -> 0.068088783 | E8: =PL!E150 -> 1121.4932 | F8: =E8/B8-1 -> 0.068088783 | G8: =PL!E196 -> 1121.4932 | H8: =G8/B8-1 -> 0.068088783 | I8: Yahoo 新聞 2026-10-12
A9: FY2027 EPS vs 投顧研究團隊（10-12） | B9: =b_eps27c -> 62.68 | C9: =PL!E122 -> 60.709148 | D9: =C9/B9-1 -> -0.031443077 | E9: =PL!E168 -> 60.709148 | F9: =E9/B9-1 -> -0.031443077 | G9: =PL!E214 -> 60.709148 | H9: =G9/B9-1 -> -0.031443077 | I9: Yahoo 新聞 2026-10-12
A10: FY2027 EPS vs 美系券商（05-04） | B10: =b_eps27b -> 65.1 | C10: =PL!E122 -> 60.709148 | D10: =C10/B10-1 -> -0.067447804 | E10: =PL!E168 -> 60.709148 | F10: =E10/B10-1 -> -0.067447804 | G10: =PL!E214 -> 60.709148 | H10: =G10/B10-1 -> -0.067447804 | I10: CMoney 2026-05-04
A11: FY2027 EPS vs 本土券商（10-01） | B11: =b_eps27a -> 80.8 | C11: =PL!E122 -> 60.709148 | D11: =C11/B11-1 -> -0.24864916 | E11: =PL!E168 -> 60.709148 | F11: =E11/B11-1 -> -0.24864916 | G11: =PL!E214 -> 60.709148 | H11: =G11/B11-1 -> -0.24864916 | I11: 旺得富 2026-10-01 | J11: 三家區間 62.7–80.8
A12: FY2027 營收年增（模型） | C12: =PL!E106 -> 0.48262531 | E12: =PL!E152 -> 0.48262531 | G12: =PL!E198 -> 0.48262531 | I12: —
A13: B. 市場與份額（先驗比對的機制檢查）
A14: CY2026 AI 電源市場（US$B）vs UBS | B14: =ubs_26 -> 17.7 | C14: =PL!D87 -> 10.529792 | D14: =C14/B14-1 -> -0.40509649 | E14: =PL!D133 -> 10.529792 | F14: =E14/B14-1 -> -0.40509649 | G14: =PL!D179 -> 10.529792 | H14: =G14/B14-1 -> -0.40509649 | I14: UBS（經 TechNews 2026-10-12） | J14: 口徑未知（是否含 BBU、HVDC、非 NVIDIA）
A15: CY2027 AI 電源市場（US$B）vs UBS | B15: =ubs_27 -> 38.2 | C15: =PL!E87 -> 24.988059 | D15: =C15/B15-1 -> -0.34586232 | E15: =PL!E133 -> 24.988059 | F15: =E15/B15-1 -> -0.34586232 | G15: =PL!E179 -> 24.988059 | H15: =G15/B15-1 -> -0.34586232 | I15: 同上
A16: FY2026 台達電有效份額 vs 凱基 Blackwell PSU 份額 | B16: =kgi_sh -> 0.7 | C16: =PL!D89 -> 0.58367194 | D16: =C16-B16 -> -0.11632806 | E16: =PL!D135 -> 0.58367194 | F16: =E16-B16 -> -0.11632806 | G16: =PL!D181 -> 0.58367194 | H16: =G16-B16 -> -0.11632806 | I16: 凱基 2025-07 | J16: 口徑不同：本模型分母含 ASIC 機架、HVDC、BBU
A17: FY2027 每 GW 台達電 AI 營收（US$M） | C17: =PL!E109 -> 471.5957 | E17: =PL!E155 -> 471.5957 | G17: =PL!E201 -> 471.5957 | I17: — | J17: 先驗比對推導約 300–550
A18: FY2027 台達電液冷每架（US$K，VR200 架數）vs 橋接表機架內液冷 | B18: =cool_vr -> 56 | C18: =Units!D11 -> 34.280034 | D18: =C18/B18-1 -> -0.38785654 | E18: =Units!D11 -> 34.280034 | F18: =E18/B18-1 -> -0.38785654 | G18: =Units!D11 -> 34.280034 | H18: =G18/B18-1 -> -0.38785654 | I18: 橋接表 v0.2.1（Morgan Stanley） | J18: 台達電液冷多在機架外（CDU、Liquid-to-Air），所以兩者不是同一個東西
A19: FY2027 AI 電源＋液冷 ÷ 營收 | C19: =PL!E108 -> 0.56040815 | E19: =PL!E154 -> 0.56040815 | G19: =PL!E200 -> 0.56040815 | I19: —
A20: C. 校準
A21: 其他營收毛利率（Derived） | C21: =PL!D111 -> 0.34047442 | E21: =PL!D157 -> 0.34047442 | G21: =PL!D203 -> 0.34047442 | I21: FY2026 錨點 | J21: AI 電源毛利率＝此值＋d_ai
A22: FY2027 毛利率 vs FY2026（百分點） | B22: =a26_gp/a26_rev -> 0.36127442 | C22: =PL!E113 -> 0.37210217 | D22: =C22-B22 -> 0.010827748 | E22: =PL!E159 -> 0.37210217 | F22: =E22-B22 -> 0.010827748 | G22: =PL!E205 -> 0.37210217 | H22: =G22-B22 -> 0.010827748 | I22: 錨點 | J22: AI 電源占比上升使毛利率上升
A23: 4Q26 EPS（模型） | C23: =Q!E15 -> 10.605716 | E23: =Q!E15 -> 10.605716 | G23: =Q!E15 -> 10.605716 | I23: — | J23: 券商 10-01 估 14.7（以 4Q 營收 2,511 億為基礎）
A24: D. 預留
A25: R4 產業部署路徑（markets/deploy_path/，尚未建立）：上線後以部署路徑取代「AI IT 資本支出 ÷ 每 GW IT 資本支出」 | J25: 預留列：本版無數值
A27: E. 目標價對帳（v0.2；模型欄為情境加權值，非情境 A）
A28: 12 個月後的前瞻 EPS（情境加權）vs 共識前瞻 EPS | B28: =cons_feps -> 51.130777 | C28: =Val!B114 -> 65.132627 | D28: =C28/B28-1 -> 0.27384389 | I28: stockanalysis 個股頁 2026-10-22：價格 1,560 ÷ Forward PE 30.51 | J28: 共識只作對帳，不作校準
A29: 目標價（DCF 與 Comparable 加權）vs 市場共識目標價 | B29: =cons_tp -> 2502.36 | C29: =Val!B119 -> 1236.8477 | D29: =C29/B29-1 -> -0.50572752 | I29: stockanalysis 個股與 forecast 頁（S&P Global）22 位分析師平均 2,502（中位數 2,500），頁面時間 2026-10-22 | J29: 共識只作對帳，不作校準
A30: Comparable 目標價 vs 市場共識目標價 | B30: =cons_tp -> 2502.36 | C30: =Val!B115 -> 1428.6842 | D30: =C30/B30-1 -> -0.42906529 | I30: 同上 | J30: 共識只作對帳，不作校準

Sheet Sens
A1: Sens — 一次動一個輸入（情境 A；有效份額、液冷每 GW、其他營收毛利率在每個案例內依 FY2026 錨點重算，FY2026 恆等於錨點）：對 FY2027、FY2028 的營收、AI 電源營收、毛利率與 EPS 的影響。每個案例是一個完整推導區塊（本頁下方）
A3: 案例 | B3: 設定 | C3: FY2027 營收 | D3: FY2027 AI 電源營收 | E3: FY2027 毛利率 | F3: FY2027 EPS | G3: FY2027 EPS 相對基準 | H3: FY2028 營收 | I3: FY2028 AI 電源營收 | J3: FY2028 毛利率 | K3: FY2028 EPS | L3: FY2028 EPS 相對基準
A4: 基準（情境 A） | B4: PL 區塊 A | C4: =PL!E104 -> 1121.4932 | D4: =PL!E92 -> 443.37881 | E4: =PL!E113 -> 0.37210217 | F4: =PL!E122 -> 60.709148 | G4: =F4/F$4-1 -> 0 | H4: =PL!F104 -> 1366.781 | I4: =PL!F92 -> 603.44747 | J4: =PL!F113 -> 0.37579522 | K4: =PL!F122 -> 77.148406 | L4: =K4/K$4-1 -> 0
A5: 份額流失（低） | B5: 份額相對值 2027 0.85、2028 0.70、2029 0.65（光寶、Flex、中國廠追趕） | C5: =E64 -> 1074.8218 | D5: =E52 -> 396.70735 | E5: =E73 -> 0.37000172 | F5: =E82 -> 57.357831 | G5: =F5/F$4-1 -> -0.05520284 | H5: =F64 -> 1232.6815 | I5: =F52 -> 469.34803 | J5: =F73 -> 0.37093471 | K5: =F82 -> 67.255421 | L5: =K5/K$4-1 -> -0.12823317
A6: 份額持平（高） | B6: 份額相對值 1.0 | C6: =E110 -> 1144.8289 | D6: =E98 -> 466.71453 | E6: =E119 -> 0.37308817 | F6: =E128 -> 62.384807 | G6: =F6/F$4-1 -> 0.02760142 | H6: =F110 -> 1433.8307 | I6: =F98 -> 670.49718 | J6: =F119 -> 0.37788454 | K6: =F128 -> 82.108146 | L6: =K6/K$4-1 -> 0.064288303
A7: 電源內容 低 | B7: 每 kW：2026 380、2027 500、2028–29 550 | C7: =E156 -> 1115.6593 | D7: =E144 -> 437.54487 | E7: =E165 -> 0.37184922 | F7: =E174 -> 60.290233 | G7: =F7/F$4-1 -> -0.006900355 | H7: =F156 -> 1341.326 | I7: =F144 -> 577.99244 | J7: =F165 -> 0.37494732 | K7: =F174 -> 75.2633 | L7: =K7/K$4-1 -> -0.024434805
A8: 電源內容 高 | B8: 每 kW：2026 520、2027 700、2028 800、2029 850 | C8: =E202 -> 1125.7565 | D8: =E190 -> 447.64206 | E8: =E211 -> 0.37228535 | F8: =E220 -> 61.015278 | G8: =F8/F$4-1 -> 0.0050425671 | H8: =F202 -> 1377.7031 | I8: =F190 -> 614.36959 | J8: =F211 -> 0.37614942 | K8: =F220 -> 77.955099 | L8: =K8/K$4-1 -> 0.01045638
A9: 液冷每 GW 低 | B9: 相對值 0.9／0.85／0.8 | C9: =E248 -> 1087.8359 | D9: =E236 -> 443.37881 | E9: =E257 -> 0.37308072 | F9: =E266 -> 59.007434 | G9: =F9/F$4-1 -> -0.028030594 | H9: =F248 -> 1302.7841 | I9: =F236 -> 603.44747 | J9: =F257 -> 0.37753029 | K9: =F266 -> 73.798222 | L9: =K9/K$4-1 -> -0.043425182
A10: 液冷每 GW 高 | B10: 相對值 1.3／1.4／1.5 | C10: =E294 -> 1155.1505 | D10: =E282 -> 443.37881 | E10: =E303 -> 0.37118064 | F10: =E312 -> 62.410861 | G10: =F10/F$4-1 -> 0.028030594 | H10: =F294 -> 1420.1117 | I10: =F282 -> 603.44747 | J10: =F303 -> 0.37446878 | K10: =F312 -> 79.93738 | L10: =K10/K$4-1 -> 0.036150762
A11: AI 部署 ×0.8 | B11: FY2027 起 AI IT 資本支出 ×0.8 | C11: =E340 -> 995.79443 | D11: =E328 -> 354.70304 | E11: =E349 -> 0.3689705 | F11: =E358 -> 52.46976 | G11: =F11/F$4-1 -> -0.13571905 | H11: =F340 -> 1197.0272 | I11: =F328 -> 482.75797 | J11: =F349 -> 0.37273821 | K11: =F358 -> 65.750486 | L11: =K11/K$4-1 -> -0.14774019
A12: AI 部署 ×1.2 | B12: ×1.2 | C12: =E386 -> 1247.192 | D12: =E374 -> 532.05457 | E12: =E395 -> 0.37460258 | F12: =E404 -> 68.948536 | G12: =F12/F$4-1 -> 0.13571905 | H12: =F386 -> 1536.5347 | I12: =F374 -> 724.13696 | J12: =F395 -> 0.37817676 | K12: =F404 -> 88.566545 | L12: =K12/K$4-1 -> 0.14800227
A13: 非 AI 分部成長 低 | B13: 四條非 AI 分部成長率取低值 | C13: =E432 -> 1094.262 | D13: =E420 -> 443.37881 | E13: =E441 -> 0.37288924 | F13: =E450 -> 59.332335 | G13: =F13/F$4-1 -> -0.022678838 | H13: =F432 -> 1312.4943 | I13: =F420 -> 603.44747 | J13: =F441 -> 0.37725614 | K13: =F450 -> 74.304251 | L13: =K13/K$4-1 -> -0.036866024
A14: 非 AI 分部成長 高 | B14: 四條非 AI 分部成長率取高值 | C14: =E478 -> 1148.7245 | D14: =E466 -> 443.37881 | E14: =E487 -> 0.37135241 | F14: =E496 -> 62.085961 | G14: =F14/F$4-1 -> 0.022678838 | H14: =F478 -> 1420.7764 | I14: =F466 -> 603.44747 | J14: =F487 -> 0.37445288 | K14: =F496 -> 79.982557 | L14: =K14/K$4-1 -> 0.036736353
A15: AI 毛利率差距 4pt | B15: AI 電源毛利率只高 4 個百分點 | C15: =E524 -> 1121.4932 | D15: =E512 -> 443.37881 | E15: =E533 -> 0.36668829 | F15: =E542 -> 59.096634 | G15: =F15/F$4-1 -> -0.026561303 | H15: =F524 -> 1366.781 | I15: =F512 -> 603.44747 | J15: =F533 -> 0.36853482 | K15: =F542 -> 74.512935 | L15: =K15/K$4-1 -> -0.034161052
A16: AI 毛利率差距 12pt | B16: 高 12 個百分點 | C16: =E570 -> 1121.4932 | D16: =E558 -> 443.37881 | E16: =E579 -> 0.37751604 | F16: =E588 -> 62.321662 | G16: =F16/F$4-1 -> 0.026561303 | H16: =F570 -> 1366.781 | I16: =F558 -> 603.44747 | J16: =F579 -> 0.38305562 | K16: =F588 -> 79.783877 | L16: =K16/K$4-1 -> 0.034161052
A17: 營業費用率 +2pt | B17: 營業費用額外 +2% × 營收 | C17: =E616 -> 1121.4932 | D17: =E604 -> 443.37881 | E17: =E625 -> 0.37210217 | F17: =E634 -> 54.752178 | G17: =F17/F$4-1 -> -0.098123096 | H17: =F616 -> 1366.781 | I17: =F604 -> 603.44747 | J17: =F625 -> 0.37579522 | K17: =F634 -> 69.888556 | L17: =K17/K$4-1 -> -0.094102399
A18: AI 相關含液冷（讀法） | B18: FY2026 AI 電源＝營收 ×（26% − 12.5%）；份額分子變小 | C18: =E662 -> 1007.611 | D18: =E650 -> 230.21592 | E18: =E671 -> 0.36875258 | F18: =E680 -> 53.098315 | G18: =F18/F$4-1 -> -0.12536551 | H18: =F662 -> 1179.9139 | I18: =F650 -> 313.32849 | J18: =F671 -> 0.37171858 | K18: =F680 -> 64.375871 | L18: =K18/K$4-1 -> -0.16555799
A19: 顆數情境 B | B19: CY2028 ×0.8、CY2029 ×0.85 | C19: =PL!E150 -> 1121.4932 | D19: =PL!E138 -> 443.37881 | E19: =PL!E159 -> 0.37210217 | F19: =PL!E168 -> 60.709148 | G19: =F19/F$4-1 -> 0 | H19: =PL!F150 -> 1197.0272 | I19: =PL!F138 -> 482.75797 | J19: =PL!F159 -> 0.37273821 | K19: =PL!F168 -> 65.560855 | L19: =K19/K$4-1 -> -0.15019819
A20: 顆數情境 C | B20: CY2028–29 ×0.6 | C20: =PL!E196 -> 1121.4932 | D20: =PL!E184 -> 443.37881 | E20: =PL!E205 -> 0.37210217 | F20: =PL!E214 -> 60.709148 | G20: =F20/F$4-1 -> 0 | H20: =PL!F196 -> 1027.2735 | I20: =PL!F184 -> 362.06848 | J20: =PL!F205 -> 0.36867088 | K20: =PL!F214 -> 50.46187 | L20: =K20/K$4-1 -> -0.3459117
A22: 讀法：FY2027 三情境相同；顆數情境 B、C 的差異從 FY2028 起。每個案例的 FY2026 有效份額與液冷每 GW 依該案例重算，所以 FY2026 恆等於錨點。「電源內容」案例的 FY2026 份額會反向調整（內容低 → 份額高），所以只影響 FY2027 起的成長路徑。
A40: 案例區塊：份額流失（低）（情境 A）
A41: 項目 | B41: 單位 | C41: FY2025A | D41: FY2026（錨點） | E41: FY2027 | F41: FY2028 | G41: FY2029 | H41: 說明
A42: A. AI 部署與電源市場（D 欄＝FY2026 校準年；E–G＝FY2027–FY2029）
A43: AI IT 資本支出 × 情境顆數係數 | B43: US$B | D43: =itc_26*1 -> 781.87292 | E43: =itc_27*1*1 -> 1565.35 | F43: =itc_28*um28_A*1 -> 1984.2639 | G43: =itc_29*um29_A*1 -> 2260.3903
A44: 每 GW IT 資本支出 | B44: US$B | D44: =itpg_gb*(1-vr26)+itpg_vr*vr26 -> 33.414032 | E44: =itpg_vr -> 37.586352 | F44: =itpg_vr -> 37.586352 | G44: =itpg_vr -> 37.586352
A45: 部署 GW（IT 電力） | B45: GW | D45: =D43/D44 -> 23.399538 | E45: =E43/E44 -> 41.646766 | F45: =F43/F44 -> 52.792138 | G45: =G43/G44 -> 60.138592
A46: AI 電源內容 | B46: US$/kW | D46: =pkw_26 -> 450 | E46: =pkw_27 -> 600 | F46: =pkw_28 -> 680 | G46: =pkw_29 -> 720
A47: AI 電源市場（美元） | B47: US$B | D47: =D45*D46/1000 -> 10.529792 | E47: =E45*E46/1000 -> 24.988059 | F47: =F45*F46/1000 -> 35.898654 | G47: =G45*G46/1000 -> 43.299786
A48: AI 電源市場（新台幣） | B48: NT$B | D48: =D47*fx -> 336.95335 | E48: =E47*fx -> 799.6179 | F48: =F47*fx -> 1148.7569 | G48: =G47*fx -> 1385.5932
A49: 台達電有效份額（FY2026 校準）＝ AI 電源營收 ÷ 市場 | B49: % | D49: =a26_aip/D48 -> 0.58367194 | H49: Derived：分子為公司 AI 相關占比 × 營收；分母為本模型的 AI 電源市場（含 ASIC 機架）
A50: 份額相對值（÷ FY2026） | B50: x | D50: =1 -> 1 | E50: =RLO_27 -> 0.85 | F50: =RLO_28 -> 0.7 | G50: =RLO_29 -> 0.65
A51: 台達電有效份額 | B51: % | D51: =$D$49*D50 -> 0.58367194 | E51: =$D$49*E50 -> 0.49612115 | F51: =$D$49*F50 -> 0.40857036 | G51: =$D$49*G50 -> 0.37938676
A52: AI 電源營收 | B52: NT$B | C52: =a25_aip -> 99.8793 | D52: =D48*D51 -> 196.67021 | E52: =E48*E51 -> 396.70735 | F52: =F48*F51 -> 469.34803 | G52: =G48*G51 -> 525.6757
A53: B. 液冷、非 AI 與合計
A54: 液冷每 GW 營收（FY2026 校準） | B54: NT$B/GW | D54: =a26_lc/D45 -> 4.0408057
A55: 液冷每 GW 相對值（÷ FY2026） | B55: x | D55: =1 -> 1 | E55: =lcr_27 -> 1.1 | F55: =lcr_28 -> 1.15 | G55: =lcr_29 -> 1.2
A56: 液冷營收 | B56: NT$B | C56: =a25_lc -> 55.4885 | D56: =D45*$D$54*D55 -> 94.552988 | E56: =E45*$D$54*E55 -> 185.11514 | F56: =F45*$D$54*F55 -> 245.32119 | G56: =G45*$D$54*G55 -> 291.61004
A57: 電源及零組件：非 AI | B57: NT$B | C57: =a25_pe-a25_aip -> 177.5632 | D57: =a26_pe-a26_aip -> 189.10598 | E57: =D57*(1+g_pe27) -> 198.56127 | F57: =E57*(1+g_pe28) -> 206.50372 | G57: =F57*(1+g_pe29) -> 212.69884 | H57: AI 電源（上列）為本分部的命題子列；FY2025、FY2026＝分部 − AI 電源
A58: 電源及零組件 | B58: NT$B | C58: =C52+C57 -> 277.4425 | D58: =D52+D57 -> 385.77619 | E58: =E52+E57 -> 595.26863 | F58: =F52+F57 -> 675.85175 | G58: =G52+G57 -> 738.37453 | H58: ＝AI 電源＋非 AI
A59: 基礎設施：非液冷 | B59: NT$B | C59: =a25_inf-a25_lc -> 127.62355 | D59: =a26_inf-a26_lc -> 170.19538 | E59: =D59*(1+g_inf27) -> 185.51296 | F59: =E59*(1+g_inf28) -> 198.49887 | G59: =F59*(1+g_inf29) -> 210.4088 | H59: 液冷（上列）為本分部的命題子列（Assumed：液冷全部歸基礎設施）
A60: 基礎設施 | B60: NT$B | C60: =C56+C59 -> 183.11205 | D60: =D56+D59 -> 264.74836 | E60: =E56+E59 -> 370.6281 | F60: =F56+F59 -> 443.82006 | G60: =G56+G59 -> 502.01884 | H60: ＝液冷＋非液冷
A61: 自動化 | B61: NT$B | C61: =a25_au -> 55.4885 | D61: =a26_au -> 60.513912 | E61: =D61*(1+g_au27) -> 63.539608 | F61: =E61*(1+g_au28) -> 66.716588 | G61: =F61*(1+g_au29) -> 69.385251
A62: 交通 | B62: NT$B | C62: =a25_mo -> 38.84195 | D62: =a26_mo -> 45.385434 | E62: =D62*(1+g_mo27) -> 45.385434 | F62: =E62*(1+g_mo28) -> 46.293143 | G62: =F62*(1+g_mo29) -> 47.219006
A63: 非 AI 營收（電源非 AI＋基礎設施非液冷＋自動化＋交通） | B63: NT$B | C63: =C57+C59+C61+C62 -> 399.5172 | D63: =D57+D59+D61+D62 -> 465.2007 | E63: =E57+E59+E61+E62 -> 492.99928 | F63: =F57+F59+F61+F62 -> 518.01232 | G63: =G57+G59+G61+G62 -> 539.71189
A64: 營收 | B64: NT$B | C64: =C58+C60+C61+C62 -> 554.885 | D64: =D58+D60+D61+D62 -> 756.4239 | E64: =E58+E60+E61+E62 -> 1074.8218 | F64: =F58+F60+F61+F62 -> 1232.6815 | G64: =G58+G60+G61+G62 -> 1356.9976 | H64: ＝四大事業群合計
A65: 檢查：分部合計 − 合併營收（FY2025 實績、FY2026 錨點） | B65: NT$B | C65: =C64-a25_rev -> 0 | D65: =D64-a26_rev -> 0
A66: 營收年增 | B66: % | D66: =D64/C64-1 -> 0.36320841 | E66: =E64/D64-1 -> 0.42092518 | F66: =F64/E64-1 -> 0.14687065 | G66: =G64/F64-1 -> 0.10085013
A67: AI 電源 ÷ 營收 | B67: % | C67: =C52/C64 -> 0.18 | D67: =D52/D64 -> 0.26 | E67: =E52/E64 -> 0.36909129 | F67: =F52/F64 -> 0.38075368 | G67: =G52/G64 -> 0.38738144
A68: AI 電源＋液冷 ÷ 營收 | B68: % | C68: =(C52+C56)/C64 -> 0.28 | D68: =(D52+D56)/D64 -> 0.385 | E68: =(E52+E56)/E64 -> 0.54131997 | F68: =(F52+F56)/F64 -> 0.57976792 | G68: =(G52+G56)/G64 -> 0.60227499
A69: 每 GW 台達電 AI 營收（電源＋液冷） | B69: US$M/GW | D69: =(D52+D56)/fx/D45*1000 -> 388.92755 | E69: =(E52+E56)/fx/E45*1000 -> 436.57539 | F69: =(F52+F56)/fx/F45*1000 -> 423.0443 | G69: =(G52+G56)/fx/G45*1000 -> 424.68868
A70: C. 損益
A71: 其他營收毛利率 ＝ 錨點毛利率 − 差距 × AI 電源占比（FY2026 校準） | B71: % | D71: =a26_gp/D64-d_ai*D67 -> 0.34047442 | H71: Derived：讓 FY2026 毛利率等於錨點；AI 電源毛利率＝其他 + 差距。FY2027 起毛利率隨 AI 電源占比變動
A72: 毛利 | B72: NT$B | C72: =a25_gp -> 190.2 | D72: =a26_gp -> 273.2766 | E72: =$D$71*E64+d_ai*E52 -> 397.6859 | F72: =$D$71*F64+d_ai*F52 -> 457.24437 | G72: =$D$71*G64+d_ai*G52 -> 504.07703
A73: 毛利率 | B73: % | C73: =C72/C64 -> 0.34277373 | D73: =D72/D64 -> 0.36127442 | E73: =E72/E64 -> 0.37000172 | F73: =F72/F64 -> 0.37093471 | G73: =G72/G64 -> 0.37146493
A74: 營業費用（基準路徑） | B74: NT$B | C74: =a25_opx -> 106.3 | D74: =a26_opx -> 141.92409 | E74: =D74*(1+MAX(0,phi*E66)) -> 189.71563 | F74: =E74*(1+MAX(0,phi*F66)) -> 212.00655 | G74: =F74*(1+MAX(0,phi*G66)) -> 229.11126
A75: 營業費用 | B75: NT$B | C75: =C74 -> 106.3 | D75: =D74 -> 141.92409 | E75: =E74+0*E64 -> 189.71563 | F75: =F74+0*F64 -> 212.00655 | G75: =G74+0*G64 -> 229.11126
A76: 營業利益 | B76: NT$B | C76: =C72-C75 -> 83.9 | D76: =D72-D75 -> 131.35252 | E76: =E72-E75 -> 207.97028 | F76: =F72-F75 -> 245.23782 | G76: =G72-G75 -> 274.96577
A77: 營業利益率 | B77: % | C77: =C76/C64 -> 0.1512025 | D77: =D76/D64 -> 0.17364935 | E77: =E76/E64 -> 0.1934928 | F77: =F76/F64 -> 0.19894661 | G77: =G76/G64 -> 0.20262804
A78: 業外收益 | B78: NT$B | C78: =a25_nop -> 3.934 | D78: =a26_nop -> 11.166667 | E78: =nop_f -> 8 | F78: =nop_f -> 8 | G78: =nop_f -> 8
A79: 歸屬母公司淨利 ÷ 稅前 | B79: % | C79: =a25_ni/(a25_oi+a25_nop) -> 0.68433636 | D79: =a26_ni/(a26_oi+a26_nop) -> 0.69063851 | E79: =nir_f -> 0.69 | F79: =nir_f -> 0.69 | G79: =nir_f -> 0.69
A80: 歸屬母公司淨利 | B80: NT$B | C80: =a25_ni -> 60.108 | D80: =a26_ni -> 98.429236 | E80: =(E76+E78)*E79 -> 149.01949 | F80: =(F76+F78)*F79 -> 174.7341 | G80: =(G76+G78)*G79 -> 195.24638
A81: 股數 | B81: 十億股 | C81: =a25_sh -> 2.5975799 | D81: =a26_sh -> 2.5980671 | E81: =D81*(1+sh_g) -> 2.5980671 | F81: =E81*(1+sh_g) -> 2.5980671 | G81: =F81*(1+sh_g) -> 2.5980671
A82: EPS | B82: NT$ | C82: =C80/C81 -> 23.14 | D82: =D80/D81 -> 37.885564 | E82: =E80/E81 -> 57.357831 | F82: =F80/F81 -> 67.255421 | G82: =G80/G81 -> 75.150632
A83: EPS 年增 | B83: % | D83: =D82/C82-1 -> 0.63723266 | E83: =E82/D82-1 -> 0.51397591 | F83: =F82/E82-1 -> 0.17255866 | G83: =G82/F82-1 -> 0.11739144
A86: 案例區塊：份額持平（高）（情境 A）
A87: 項目 | B87: 單位 | C87: FY2025A | D87: FY2026（錨點） | E87: FY2027 | F87: FY2028 | G87: FY2029 | H87: 說明
A88: A. AI 部署與電源市場（D 欄＝FY2026 校準年；E–G＝FY2027–FY2029）
A89: AI IT 資本支出 × 情境顆數係數 | B89: US$B | D89: =itc_26*1 -> 781.87292 | E89: =itc_27*1*1 -> 1565.35 | F89: =itc_28*um28_A*1 -> 1984.2639 | G89: =itc_29*um29_A*1 -> 2260.3903
A90: 每 GW IT 資本支出 | B90: US$B | D90: =itpg_gb*(1-vr26)+itpg_vr*vr26 -> 33.414032 | E90: =itpg_vr -> 37.586352 | F90: =itpg_vr -> 37.586352 | G90: =itpg_vr -> 37.586352
A91: 部署 GW（IT 電力） | B91: GW | D91: =D89/D90 -> 23.399538 | E91: =E89/E90 -> 41.646766 | F91: =F89/F90 -> 52.792138 | G91: =G89/G90 -> 60.138592
A92: AI 電源內容 | B92: US$/kW | D92: =pkw_26 -> 450 | E92: =pkw_27 -> 600 | F92: =pkw_28 -> 680 | G92: =pkw_29 -> 720
A93: AI 電源市場（美元） | B93: US$B | D93: =D91*D92/1000 -> 10.529792 | E93: =E91*E92/1000 -> 24.988059 | F93: =F91*F92/1000 -> 35.898654 | G93: =G91*G92/1000 -> 43.299786
A94: AI 電源市場（新台幣） | B94: NT$B | D94: =D93*fx -> 336.95335 | E94: =E93*fx -> 799.6179 | F94: =F93*fx -> 1148.7569 | G94: =G93*fx -> 1385.5932
A95: 台達電有效份額（FY2026 校準）＝ AI 電源營收 ÷ 市場 | B95: % | D95: =a26_aip/D94 -> 0.58367194 | H95: Derived：分子為公司 AI 相關占比 × 營收；分母為本模型的 AI 電源市場（含 ASIC 機架）
A96: 份額相對值（÷ FY2026） | B96: x | D96: =1 -> 1 | E96: =RHI_27 -> 1 | F96: =RHI_28 -> 1 | G96: =RHI_29 -> 1
A97: 台達電有效份額 | B97: % | D97: =$D$95*D96 -> 0.58367194 | E97: =$D$95*E96 -> 0.58367194 | F97: =$D$95*F96 -> 0.58367194 | G97: =$D$95*G96 -> 0.58367194
A98: AI 電源營收 | B98: NT$B | C98: =a25_aip -> 99.8793 | D98: =D94*D97 -> 196.67021 | E98: =E94*E97 -> 466.71453 | F98: =F94*F97 -> 670.49718 | G98: =G94*G97 -> 808.73184
A99: B. 液冷、非 AI 與合計
A100: 液冷每 GW 營收（FY2026 校準） | B100: NT$B/GW | D100: =a26_lc/D91 -> 4.0408057
A101: 液冷每 GW 相對值（÷ FY2026） | B101: x | D101: =1 -> 1 | E101: =lcr_27 -> 1.1 | F101: =lcr_28 -> 1.15 | G101: =lcr_29 -> 1.2
A102: 液冷營收 | B102: NT$B | C102: =a25_lc -> 55.4885 | D102: =D91*$D$100*D101 -> 94.552988 | E102: =E91*$D$100*E101 -> 185.11514 | F102: =F91*$D$100*F101 -> 245.32119 | G102: =G91*$D$100*G101 -> 291.61004
A103: 電源及零組件：非 AI | B103: NT$B | C103: =a25_pe-a25_aip -> 177.5632 | D103: =a26_pe-a26_aip -> 189.10598 | E103: =D103*(1+g_pe27) -> 198.56127 | F103: =E103*(1+g_pe28) -> 206.50372 | G103: =F103*(1+g_pe29) -> 212.69884 | H103: AI 電源（上列）為本分部的命題子列；FY2025、FY2026＝分部 − AI 電源
A104: 電源及零組件 | B104: NT$B | C104: =C98+C103 -> 277.4425 | D104: =D98+D103 -> 385.77619 | E104: =E98+E103 -> 665.27581 | F104: =F98+F103 -> 877.00091 | G104: =G98+G103 -> 1021.4307 | H104: ＝AI 電源＋非 AI
A105: 基礎設施：非液冷 | B105: NT$B | C105: =a25_inf-a25_lc -> 127.62355 | D105: =a26_inf-a26_lc -> 170.19538 | E105: =D105*(1+g_inf27) -> 185.51296 | F105: =E105*(1+g_inf28) -> 198.49887 | G105: =F105*(1+g_inf29) -> 210.4088 | H105: 液冷（上列）為本分部的命題子列（Assumed：液冷全部歸基礎設施）
A106: 基礎設施 | B106: NT$B | C106: =C102+C105 -> 183.11205 | D106: =D102+D105 -> 264.74836 | E106: =E102+E105 -> 370.6281 | F106: =F102+F105 -> 443.82006 | G106: =G102+G105 -> 502.01884 | H106: ＝液冷＋非液冷
A107: 自動化 | B107: NT$B | C107: =a25_au -> 55.4885 | D107: =a26_au -> 60.513912 | E107: =D107*(1+g_au27) -> 63.539608 | F107: =E107*(1+g_au28) -> 66.716588 | G107: =F107*(1+g_au29) -> 69.385251
A108: 交通 | B108: NT$B | C108: =a25_mo -> 38.84195 | D108: =a26_mo -> 45.385434 | E108: =D108*(1+g_mo27) -> 45.385434 | F108: =E108*(1+g_mo28) -> 46.293143 | G108: =F108*(1+g_mo29) -> 47.219006
A109: 非 AI 營收（電源非 AI＋基礎設施非液冷＋自動化＋交通） | B109: NT$B | C109: =C103+C105+C107+C108 -> 399.5172 | D109: =D103+D105+D107+D108 -> 465.2007 | E109: =E103+E105+E107+E108 -> 492.99928 | F109: =F103+F105+F107+F108 -> 518.01232 | G109: =G103+G105+G107+G108 -> 539.71189
A110: 營收 | B110: NT$B | C110: =C104+C106+C107+C108 -> 554.885 | D110: =D104+D106+D107+D108 -> 756.4239 | E110: =E104+E106+E107+E108 -> 1144.8289 | F110: =F104+F106+F107+F108 -> 1433.8307 | G110: =G104+G106+G107+G108 -> 1640.0538 | H110: ＝四大事業群合計
A111: 檢查：分部合計 − 合併營收（FY2025 實績、FY2026 錨點） | B111: NT$B | C111: =C110-a25_rev -> 0 | D111: =D110-a26_rev -> 0
A112: 營收年增 | B112: % | D112: =D110/C110-1 -> 0.36320841 | E112: =E110/D110-1 -> 0.51347538 | F112: =F110/E110-1 -> 0.25244099 | G112: =G110/F110-1 -> 0.14382666
A113: AI 電源 ÷ 營收 | B113: % | C113: =C98/C110 -> 0.18 | D113: =D98/D110 -> 0.26 | E113: =E98/E110 -> 0.40767185 | F113: =F98/F110 -> 0.46762647 | G113: =G98/G110 -> 0.493113
A114: AI 電源＋液冷 ÷ 營收 | B114: % | C114: =(C98+C102)/C110 -> 0.28 | D114: =(D98+D102)/D110 -> 0.385 | E114: =(E98+E102)/E110 -> 0.56936861 | F114: =(F98+F102)/F110 -> 0.63872142 | G114: =(G98+G102)/G110 -> 0.67091817
A115: 每 GW 台達電 AI 營收（電源＋液冷） | B115: US$M/GW | D115: =(D98+D102)/fx/D91*1000 -> 388.92755 | E115: =(E98+E102)/fx/E91*1000 -> 489.10586 | F115: =(F98+F102)/fx/F91*1000 -> 542.11337 | G115: =(G98+G102)/fx/G91*1000 -> 571.77401
A116: C. 損益
A117: 其他營收毛利率 ＝ 錨點毛利率 − 差距 × AI 電源占比（FY2026 校準） | B117: % | D117: =a26_gp/D110-d_ai*D113 -> 0.34047442 | H117: Derived：讓 FY2026 毛利率等於錨點；AI 電源毛利率＝其他 + 差距。FY2027 起毛利率隨 AI 電源占比變動
A118: 毛利 | B118: NT$B | C118: =a25_gp -> 190.2 | D118: =a26_gp -> 273.2766 | E118: =$D$117*E110+d_ai*E98 -> 427.12213 | F118: =$D$117*F110+d_ai*F98 -> 541.82245 | G118: =$D$117*G110+d_ai*G98 -> 623.0949
A119: 毛利率 | B119: % | C119: =C118/C110 -> 0.34277373 | D119: =D118/D110 -> 0.36127442 | E119: =E118/E110 -> 0.37308817 | F119: =F118/F110 -> 0.37788454 | G119: =G118/G110 -> 0.37992346
A120: 營業費用（基準路徑） | B120: NT$B | C120: =a25_opx -> 106.3 | D120: =a26_opx -> 141.92409 | E120: =D120*(1+MAX(0,phi*E112)) -> 200.22371 | F120: =E120*(1+MAX(0,phi*F112)) -> 240.65944 | G120: =F120*(1+MAX(0,phi*G112)) -> 268.35004
A121: 營業費用 | B121: NT$B | C121: =C120 -> 106.3 | D121: =D120 -> 141.92409 | E121: =E120+0*E110 -> 200.22371 | F121: =F120+0*F110 -> 240.65944 | G121: =G120+0*G110 -> 268.35004
...

Sheet Sources
A1: 來源（公司原文＝台達電法說簡報與逐字稿，已逐份抓取；券商與研調皆為 Interested-party）
A2: 公司：4Q25 法說簡報（FY2025 損益、部門營收與利益） | B2: https://filecenter.deltaww.com/ir/download/calendar/4Q25_Analyst Meeting.pdf
A3: 公司：2Q26 法說逐字稿（1H26 損益、AI 占比、液冷占比、800V 時程、資本支出、零組件短缺） | B3: https://filecenter.deltaww.com/IR/download/calendar/2Q26_Transcript.pdf
A4: 二手：BigGo 2Q26 法說摘要（AI 相關朝 28%；對手名單） | B4: https://finance.biggo.com/news/TW_2308.TW_2026-07-30
A5: 二手：數位時代 2026-02-26（2025 部門營收比重 50／33／10／7） | B5: https://www.bnext.com.tw/article/90178/2026-delta-earnings-call
A6: 二手：TechNews 2026-10-12（3Q26 營收、AI 相關 2025 年 18%、UBS AI 伺服器電源市場） | B6: https://finance.technews.tw/2026/10/12/delta-electronics-q3-revenue-nears-200-billion-record-high-q4-double-digit-growth
A7: 券商：凱基 Power supply sector 2025-07-01（每架 PSU 內容、Blackwell 份額約 70%） | B7: https://www.kgi.com.hk/en/-/media/files/kgishk/research-reports/tw-reports/power-supply-industry_01072025.pdf
A8: 券商：旺得富 2026-10-01（本土投顧 EPS、4Q26 估計、HVDC 占 2027 營收 5–10%、18kW 與 HVDC 毛利率約 50%） | B8: https://wantrich.chinatimes.com/news/20261001900208-420101
A9: 券商：CMoney 2026-05-04（美系 EPS 2026–28） | B9: https://www.cmoney.tw/notes/note-detail.aspx?nid=1180676
A10: 券商：Yahoo 新聞 2026-10-12（投顧 2027 營收 1.05 兆、EPS 62.68；Vicor 337 調查） | B10: https://tw.news.yahoo.com/%E5%8F%B0%E9%81%94%E9%9B%BBq3%E7%87%9F%E6%94%B6%E5%89%B5%E6%96%B0%E9%AB%98-337%E8%AA%BF%E6%9F%A5%E8%A1%9D%E6%93%8A-%E6%B3%95%E4%BA%BA%E9%80%99%E6%A8%A3%E7%9C%8B-035400801.html
A11: 研調：Morgan Stanley NVL72 冷卻 BOM（經 Tom's Hardware 2025-11-05） | B11: https://finance.yahoo.com/news/cooling-system-single-nvidia-blackwell-154500100.html
A12: 資料商：Yahoo 股市（10-23 收盤）、Goodinfo（10-22 收盤、近 12 月 P/E） | B12: https://tw.stock.yahoo.com/quote/2308.TW
A13: 資料商：companiesmarketcap 年底 P/E | B13: https://companiesmarketcap.com/delta-electronics/pe-ratio/
A14: 市場層：markets/network、markets/chip_bridge、tsmc 成品（本 repo，唯讀）
A15: 待補（人工）：3Q26 法說（10 月底）；部門季度損益；AI 電源與液冷的季度金額；P/E 第二來源；前瞻 P/E 十年歷史（Bloomberg）；券商共識（付費） | B15: 未找到
A16: SemiAnalysis | B16: 未使用
A17: [Verified] 台達電 FY2025 年報：折舊與攤銷 278.39 億元、資本支出 460.91 億元、營業現金流 984.74 億元（資料商轉載合併現金流量表） | B17: https://stockanalysis.com/quote/tpe/2308/financials/cash-flow-statement/
A18: [Assumed] FY2026 起折舊 ÷ 營收、資本支出 ÷ 營收沿用 FY2025 實績比率（In 頁 da_r、cx_r）；自由現金流不含營運資金變動 | B18: 本模型假設
