Workbook

Sheet README
A1: 金像電（2368.TW）收支與估值模型 v0.1（AI 半導體 Project：載板與 PCB 次產業；伺服器與交換器 PCB、高層數板） 2026-10-25
A2: 版本：v0.1（初版）。每 GW AI 高速 PCB 金額沿用勝宏模型（victory_giant/dist Units 頁，本專案權威，口徑一致），本模型只加金像電對中板／背板的參與係數；金像電份額與產值產能在本模型 Units 頁建立；Recon 頁對照勝宏模型與台光電每 GW CCL 金額。
A3: 模型命題：金像電的 AI 營收＝部署 GW（AI IT 資本支出 ÷ 每 GW IT 資本支出）× 每 GW 可參與 AI 高速 PCB 金額（勝宏模型三項，中板／背板 × 參與係數）× 金像電份額 × 價格指數，但受產值產能（FY2026 營收 × 擴產指數）限制（全產全銷）。非 AI（一般伺服器、網通、筆電）另設成長率。
A4: 核心問題：2026 年約 190 億元資本支出（台灣、蘇州、泰國二廠 2027 下半年開出）能讓產能在 2027–29 年擴大多少；ASIC 主板改 HDI＋HLC 混壓後份額守不守得住；現價約 20 倍前瞻 P/E 隱含什麼路徑。
A6: 會計年度＝日曆年，FY(t)＝CY(t)，不平移。預測期 FY2027–FY2029 由驅動因子推導，FY2030–FY2032 為收斂法。金額：十億新台幣；每 GW 金額以美元計、以匯率 32.0 換算。口徑：歸屬母公司淨利（IFRS）。
A8: 驅動因子 → 推導量（全部唯讀上游，不修改）
A9: 需求面：markets/network 的 AI IT 資本支出 × 同字母顆數係數（tsmc；＝markets/memory SCEN_UNITS）÷ 每 GW IT 資本支出（Tokenomics，經橋接表）＝部署 GW；× 每 GW PCB 金額（勝宏模型，US$450M → 682M）× 匯率 × 有效份額（FY2026 以錨點 AI 營收校準）× 份額相對值 × 價格指數（Assumed）。
A10: 產能面：FY2026 營收（產能吃緊、滿載）× 產值產能指數（2027 1.45、2028 1.90、2029 2.30；Assumed，依 2026 年約 190 億元資本支出與各廠時程）× 價格指數。AI 相關營收＝MIN（需求面、產能上限 − 非 AI）。
A11: 毛利率：AI 相關比其他營收高 d_ai 10pt（Assumed），其他毛利率為 FY2026 殘差（Derived）；價格指數變動全部落在 AI 毛利；另加新廠爬坡完成的額外改善（Assumed）。營業費用：彈性 phi 0.6（Assumed）。淨利 ÷ 稅前 0.685（1Q26 實績）。
A12: 校準：FY2026 ＝ 1H26 財報＋3Q26 月營收實績（297.19 億）＋假設（3Q、4Q 毛利率 35%、營業費用率 8%、4Q 季增 8%）。3Q26 財報與法說預計 2026-11 上旬，截至 2026-10-25 尚未公布。不用券商數字（只在 Recon 對帳）。
A13: 估值：Val 第 0 節目標價＝0.5 × DCF 目標價（股東現金流＝EPS ×（1 − g／ROE），FY2027–32 明確期＋永續，r 10%、g 4%，三情境權重 0.3／0.5／0.2，負值取 0）＋0.5 × Comparable 目標價（臺美同業健鼎、華通、臻鼎-KY、博智、TTM 前瞻 P/E 中位數 × 12 個月後前瞻 EPS；不放 A 股）；另列 Comparable 單獨目標價、市場共識目標價與差距拆解。十年 P/E 規則值 × FY2027 EPS 保留為參考（不是目標價）。本版未做先驗，無 Andy 合理 P/E 對照。
A14: 預估期間：FY2027–FY2029 由驅動因子推導；FY2030 起為收斂法，非驅動因子推導（營收年增由 FY2029 線性收斂到 fade_g、淨利率收斂到 fade_m，FY2032 達到；PL 頁灰底）。十年平均淨利率未找到（2016–2020 營收與淨利缺），依工作單以情境 C FY2029 淨利率 × 0.8 替代（Assumed）。
... A18: 已知限制：(1) 每 GW PCB 金額沿用勝宏模型（2026 水準 Assumed、世代指數 Analogy／Assumed），其升級主要來自 NVIDIA VR200 中板與 Kyber 背板；金像電以 ASIC 與交換器為主，參與係數 w_mid 為 Assumed；(2) 產值產能指數為 Assumed，公司未揭露產能（萬㎡）；(3) AI 占比 FY2025 取媒體轉述（約兩成到三成），FY2026 由非 AI 成長假設反推；(4) 未建資本支出與折舊（2026 年資本支出約 190 億、折舊約 14 億），DCF 現金流在擴產期偏高估；(5) 淨利 ÷ 稅前約 0.68（稅負偏高，含中國子公司），未拆分；(6) 十年 P/E 只有一個採用來源，2016–2019 年低獲利使 P/E 偏高；(7) 臺股同業前瞻 P/E 為 8–9 月快取值；(8) 3Q26 財報後更新錨點；R4 產業部署路徑未建。

Sheet In
A1: In — 輸入（藍字；基準欄 E，低 D、高 F）。金額：十億新台幣（NT$B），每 GW PCB 金額為百萬美元；比例：%。每個輸入附兩個來源（找不到者寫「未找到」）；公司原文算一個
A2: 標記：Verified／Interested-party／Analogy／Assumed／Derived；Analogy、Assumed 給低／高區間。SemiAnalysis 未使用。公司原文＝金像電財報（公開資訊觀測站）、月營收公告與法說會（經媒體轉述）；公司的訂單、產品組合與產能說法為 Interested-party；券商與媒體估計皆為 Interested-party
A3: 鍵 | B3: 項目 | C3: 單位 | D3: 低 | E3: 基準 | F3: 高 | G3: 標記 | H3: 來源1 | I3: 來源2／說明
A4: A. AI 部署規模（讀 markets/network、markets/chip_bridge、tsmc 成品；情境 A 基準，B／C 依同字母顆數係數縮放）
A5: itc_26 | B5: AI IT 資本支出 2026 | C5: US$B | E5: 781.87292 | G5: Derived | H5: markets/network/dist/20261023_AI網通市場模型_v0.2.2.xlsx｜Mkt!C27:F27 | I5: 加速器顆數 × 每顆 IT capex（含 ASIC）；本模型以此除以每 GW IT 資本支出得到部署 GW（與勝宏、台光電模型相同）
A6: itc_27 | B6: AI IT 資本支出 2027 | C6: US$B | E6: 1565.35 | G6: Derived | H6: markets/network/dist/20261023_AI網通市場模型_v0.2.2.xlsx｜Mkt!C27:F27 | I6: 同上
A7: itc_28 | B7: AI IT 資本支出 2028 | C7: US$B | E7: 1984.2639 | G7: Derived | H7: markets/network/dist/20261023_AI網通市場模型_v0.2.2.xlsx｜Mkt!C27:F27 | I7: 同上
A8: itc_29 | B8: AI IT 資本支出 2029 | C8: US$B | E8: 2260.3903 | G8: Derived | H8: markets/network/dist/20261023_AI網通市場模型_v0.2.2.xlsx｜Mkt!C27:F27 | I8: 同上
A9: itpg_gb | B9: 每 GW IT 資本支出（GB300） | C9: US$B | E9: 32.237224 | G9: Derived | H9: markets/chip_bridge/dist/20261023_晶片內容橋接表_v0.2.1.xlsx｜In!E10（GB300）、H10（VR200） | I9: Tokenomics IF_CapexIT（經橋接表；唯讀）
A10: itpg_vr | B10: 每 GW IT 資本支出（VR200；2027 起） | C10: US$B | E10: 37.586352 | G10: Derived | H10: markets/chip_bridge/dist/20261023_晶片內容橋接表_v0.2.1.xlsx｜In!E10（GB300）、H10（VR200） | I10: 同上；Rubin Ultra 與 ASIC 機架未另訂（Assumed：同 VR200）
A11: vr26 | B11: 2026 年部署中 Rubin 世代占比（混合每 GW IT 資本支出用） | C11: % | D11: 0.15 | E11: 0.22 | F11: 0.3 | G11: Interested-party | H11: TrendForce 2026 組合 Rubin 22%（經 markets/memory；與勝宏、台光電模型相同） | I11: —
A12: racks_gb | B12: 每 GW 機架數（GB300） | C12: 架 | E12: 6764 | G12: Derived | H12: markets/chip_bridge/dist/20261023_晶片內容橋接表_v0.2.1.xlsx｜In!E6（GB300）、H6（VR200） | I12: Recon 用
A13: racks_vr | B13: 每 GW 機架數（VR200） | C13: 架 | E13: 4052 | G13: Derived | H13: markets/chip_bridge/dist/20261023_晶片內容橋接表_v0.2.1.xlsx｜In!E6（GB300）、H6（VR200） | I13: Units 頁每架等值金額用
A14: um28_A | B14: 情境 A：2028 顆數 ÷ 基準 | C14: x | E14: 1 | G14: Assumed | H14: tsmc/dist/20261025_台積電模型_v0.3.xlsx｜In!E37 | I14: A＝順利（基準）；B＝平平；C＝不如預期；與台積電、勝宏模型相同（＝markets/memory SCEN_UNITS，建置時核對）
A15: um29_A | B15: 情境 A：2029 顆數 ÷ 基準 | C15: x | E15: 1 | G15: Assumed | H15: tsmc/dist/20261025_台積電模型_v0.3.xlsx｜In!E38 | I15: 同上
A16: um28_B | B16: 情境 B：2028 顆數 ÷ 基準 | C16: x | E16: 0.8 | G16: Assumed | H16: tsmc/dist/20261025_台積電模型_v0.3.xlsx｜In!E39 | I16: A＝順利（基準）；B＝平平；C＝不如預期；與台積電、勝宏模型相同（＝markets/memory SCEN_UNITS，建置時核對）
A17: um29_B | B17: 情境 B：2029 顆數 ÷ 基準 | C17: x | E17: 0.85 | G17: Assumed | H17: tsmc/dist/20261025_台積電模型_v0.3.xlsx｜In!E40 | I17: 同上
A18: um28_C | B18: 情境 C：2028 顆數 ÷ 基準 | C18: x | E18: 0.6 | G18: Assumed | H18: tsmc/dist/20261025_台積電模型_v0.3.xlsx｜In!E41 | I18: A＝順利（基準）；B＝平平；C＝不如預期；與台積電、勝宏模型相同（＝markets/memory SCEN_UNITS，建置時核對）
A19: um29_C | B19: 情境 C：2029 顆數 ÷ 基準 | C19: x | E19: 0.6 | G19: Assumed | H19: tsmc/dist/20261025_台積電模型_v0.3.xlsx｜In!E42 | I19: 同上
A20: fx | B20: 匯率（新台幣 ÷ 美元） | C20: NT$/US$ | D20: 30.5 | E20: 32 | F20: 33 | G20: Derived | H20: 與台光電、台達電、廣達模型相同（emc/dist In 頁 fx＝32.0） | I20: 10-23 收盤：未找到
A21: B. 每 GW AI 高速 PCB 金額（口徑與勝宏一致：唯讀 victory_giant/dist Units 頁）與金像電份額
A22: vg_cmp26 | B22: 每 GW PCB：加速器卡／運算板（GPU／ASIC 模組、運算匣主板） 2026（勝宏模型） | C22: US$M/GW | E22: 280 | G22: Derived | H22: victory_giant/dist/20261025_勝宏科技模型_v0.1.xlsx｜Units!C5:F5 | I22: 唯讀勝宏模型成品（本專案每 GW PCB 金額權威；2026 Assumed、之後 × 世代指數 Analogy／Assumed）
A23: vg_cmp27 | B23: 每 GW PCB：加速器卡／運算板（GPU／ASIC 模組、運算匣主板） 2027（勝宏模型） | C23: US$M/GW | E23: 420 | G23: Derived | H23: victory_giant/dist/20261025_勝宏科技模型_v0.1.xlsx｜Units!C5:F5 | I23: 同上
A24: vg_cmp28 | B24: 每 GW PCB：加速器卡／運算板（GPU／ASIC 模組、運算匣主板） 2028（勝宏模型） | C24: US$M/GW | E24: 462 | G24: Derived | H24: victory_giant/dist/20261025_勝宏科技模型_v0.1.xlsx｜Units!C5:F5 | I24: 同上
A25: vg_cmp29 | B25: 每 GW PCB：加速器卡／運算板（GPU／ASIC 模組、運算匣主板） 2029（勝宏模型） | C25: US$M/GW | E25: 504 | G25: Derived | H25: victory_giant/dist/20261025_勝宏科技模型_v0.1.xlsx｜Units!C5:F5 | I25: 同上
A26: vg_sw26 | B26: 每 GW PCB：交換器板（NVLink 交換匣＋scale-out 800G／1.6T 交換器） 2026（勝宏模型） | C26: US$M/GW | E26: 120 | G26: Derived | H26: victory_giant/dist/20261025_勝宏科技模型_v0.1.xlsx｜Units!C6:F6 | I26: 唯讀勝宏模型成品（本專案每 GW PCB 金額權威；2026 Assumed、之後 × 世代指數 Analogy／Assumed）
A27: vg_sw27 | B27: 每 GW PCB：交換器板（NVLink 交換匣＋scale-out 800G／1.6T 交換器） 2027（勝宏模型） | C27: US$M/GW | E27: 162 | G27: Derived | H27: victory_giant/dist/20261025_勝宏科技模型_v0.1.xlsx｜Units!C6:F6 | I27: 同上
A28: vg_sw28 | B28: 每 GW PCB：交換器板（NVLink 交換匣＋scale-out 800G／1.6T 交換器） 2028（勝宏模型） | C28: US$M/GW | E28: 180 | G28: Derived | H28: victory_giant/dist/20261025_勝宏科技模型_v0.1.xlsx｜Units!C6:F6 | I28: 同上
A29: vg_sw29 | B29: 每 GW PCB：交換器板（NVLink 交換匣＋scale-out 800G／1.6T 交換器） 2029（勝宏模型） | C29: US$M/GW | E29: 198 | G29: Derived | H29: victory_giant/dist/20261025_勝宏科技模型_v0.1.xlsx｜Units!C6:F6 | I29: 同上
A30: vg_mid26 | B30: 每 GW PCB：中板／正交背板／CPX 與其他 2026（勝宏模型） | C30: US$M/GW | E30: 50 | G30: Derived | H30: victory_giant/dist/20261025_勝宏科技模型_v0.1.xlsx｜Units!C7:F7 | I30: 唯讀勝宏模型成品（本專案每 GW PCB 金額權威；2026 Assumed、之後 × 世代指數 Analogy／Assumed）
A31: vg_mid27 | B31: 每 GW PCB：中板／正交背板／CPX 與其他 2027（勝宏模型） | C31: US$M/GW | E31: 100 | G31: Derived | H31: victory_giant/dist/20261025_勝宏科技模型_v0.1.xlsx｜Units!C7:F7 | I31: 同上
A32: vg_mid28 | B32: 每 GW PCB：中板／正交背板／CPX 與其他 2028（勝宏模型） | C32: US$M/GW | E32: 150 | G32: Derived | H32: victory_giant/dist/20261025_勝宏科技模型_v0.1.xlsx｜Units!C7:F7 | I32: 同上
A33: vg_mid29 | B33: 每 GW PCB：中板／正交背板／CPX 與其他 2029（勝宏模型） | C33: US$M/GW | E33: 175 | G33: Derived | H33: victory_giant/dist/20261025_勝宏科技模型_v0.1.xlsx｜Units!C7:F7 | I33: 同上
A34: w_mid | B34: 金像電對中板／背板／其他的參與係數（1＝與加速器卡、交換器板相同） | C34: x | D34: 0 | E34: 0.5 | F34: 1 | G34: Assumed | H34: 金像電以 ASIC 伺服器主板（Trainium、TPU）與 800G 交換器板為主（優分析 2026-09-09；Interested-party）；NVIDIA VR200 中板、Kyber 正交背板的參與度：未找到 | I34: 低＝不參與、高＝與其他兩項相同
A35: pgwf | B35: 每 GW 金額成長倍率（套在勝宏模型 2027–29 每 GW 金額相對 2026 的增量上；Sens 用） | C35: x | D35: 0.7 | E35: 1 | F35: 1.3 | G35: Assumed | H35: 勝宏模型的世代升級主要來自 NVIDIA VR200 中板與 CPX、Kyber 背板；ASIC 主板改 HDI＋HLC 混壓也提高每 GW 金額（優分析 2026-09-09） | I35: 基準＝與勝宏模型相同
A36: rel_27 | B36: 金像電份額 2027 ÷ 2026（相對值；情境 A 取高、B 基準、C 取低） | C36: x | D36: 0.85 | E36: 1 | F36: 1.08 | G36: Assumed | H36: 風險：ASIC 主板設計由高層數（HLC）轉 HDI＋HLC 混壓（Trainium4、TPU 新世代），2026-06 股價修正逾五成；公司以 3–4 階 HDI 混壓因應（優分析 2026-09-09，Interested-party） | I36: 利多：另一家美國雲端業者 ASIC 主板訂單、Amazon 私募入股（2026-09-29）；對手健鼎、TTM、勝宏、沪电擴產
A37: rel_28 | B37: 金像電份額 2028 ÷ 2026（相對值；情境 A 取高、B 基準、C 取低） | C37: x | D37: 0.75 | E37: 0.95 | F37: 1.08 | G37: Assumed | H37: 同上 | I37: —
A38: rel_29 | B38: 金像電份額 2029 ÷ 2026（相對值；情境 A 取高、B 基準、C 取低） | C38: x | D38: 0.7 | E38: 0.9 | F38: 1.05 | G38: Assumed | H38: 同上 | I38: —
A39: pp_27 | B39: PCB 價格指數 2027（2026＝1；同規格降價或漲價，不含世代升級；情境 A 取高、C 取低） | C39: x | D39: 0.96 | E39: 1 | F39: 1.03 | G39: Assumed | H39: 分析師：3Q26 成長動能含價格改善、產能吃緊（優分析 2026-09-09，Interested-party） | I39: 新產能（中壢、蘇州二廠、泰國二廠）2027 年下半年起開出後價格回落（Assumed）
A40: pp_28 | B40: PCB 價格指數 2028（2026＝1；同規格降價或漲價，不含世代升級；情境 A 取高、C 取低） | C40: x | D40: 0.92 | E40: 0.97 | F40: 1.02 | G40: Assumed | H40: 同上 | I40: —
A41: pp_29 | B41: PCB 價格指數 2029（2026＝1；同規格降價或漲價，不含世代升級；情境 A 取高、C 取低） | C41: x | D41: 0.88 | E41: 0.94 | F41: 1 | G41: Assumed | H41: 同上 | I41: —
A42: C. 產能（全產全銷：營收上限＝FY2026 營收 × 產值產能指數 × 價格指數；各情境相同）
A43: cx_27 | B43: 平均產值產能 2027 ÷ FY2026 營收（產能指數；以 FY2026 產品價格計） | C43: x | D43: 1.3 | E43: 1.45 | F43: 1.6 | G43: Assumed | H43: 公司：2026 年資本支出約 190 億元（2025 年約 50–60 億）；台灣、蘇州、常熟、泰國同步擴產；台灣 2026 下半年產能較去年增約五成、泰國產能年增 5–6 倍（理財周刊 2026-09-23，Interested-party） | I43: 蘇州二廠、泰國二廠 2027 年下半年量產；中壢新廠投資 138 億元（2026-09-04 董事會）；2027–29 每年一座新廠（優分析 2026-09-09）；2026-09-29 再通過 79 億元土地與資本支出
A44: cx_28 | B44: 平均產值產能 2028 ÷ FY2026 營收（產能指數；以 FY2026 產品價格計） | C44: x | D44: 1.6 | E44: 1.9 | F44: 2.15 | G44: Assumed | H44: 同上 | I44: 4Q26 年化營收約為 FY2026 的 1.2 倍（Q 頁），FY2027 指數下限據此
A45: cx_29 | B45: 平均產值產能 2029 ÷ FY2026 營收（產能指數；以 FY2026 產品價格計） | C45: x | D45: 1.9 | E45: 2.3 | F45: 2.6 | G45: Assumed | H45: 同上；每年一座新廠 | I45: —
A46: D. 營收結構錨點（公司與媒體揭露比例 × 營收）
A47: ai_25 | B47: 2025 年 AI 相關營收（AI 伺服器 GPU／ASIC 主板、800G 交換器）÷ 營收 | C47: % | D47: 0.2 | E47: 0.3 | F47: 0.4 | G47: Interested-party | H47: https://uanalyze.com.tw/articles/6187254928：AI 占比由約兩成升至約五成（2026-09-09） | I47: 公司法說 2025-11：3Q25 伺服器（一般＋AI）占 80%、網通 10%、筆電 7%、其他 3%，AI 未單獨揭露（富果整理）
A48: g_nai26 | B48: 2026 年非 AI 營收年增（一般伺服器、網通、筆電、其他） | C48: % | D48: 0.1 | E48: 0.2 | F48: 0.3 | G48: Assumed | H48: 一般伺服器平台換代與價格改善（Assumed）；FY2026 AI 相關營收＝錨點營收 − 非 AI（Derived） | I48: 理財周刊 2026-10-14：分析師稱 2Q26 AI 相關約占 40–50%、伺服器約 78%
A49: g_nai27 | B49: 非 AI 營收年增 2027 | C49: % | D49: -0.05 | E49: 0.05 | F49: 0.1 | G49: Assumed | H49: 產能優先給 AI 與高階板（Assumed） | I49: —
A50: g_nai28 | B50: 非 AI 營收年增 2028 | C50: % | D50: -0.05 | E50: 0.03 | F50: 0.08 | G50: Assumed | H50: 同上 | I50: —
A51: g_nai29 | B51: 非 AI 營收年增 2029 | C51: % | D51: -0.05 | E51: 0.03 | F51: 0.08 | G51: Assumed | H51: 同上 | I51: —
A52: E. 毛利率
A53: d_ai | B53: AI 相關（高層數 AI 伺服器板、800G 交換器板）毛利率高於其他營收的幅度 | C53: pt | D53: 0.06 | E53: 0.1 | F53: 0.14 | G53: Assumed | H53: 部門別毛利率未揭露：未找到；毛利率 FY2024 29.3% → FY2025 32.8% → 1H26 34.7%，同期 AI 占比由約兩成升至約五成 | I53: 泰國廠由一般伺服器板轉 AI 高單價板（優分析 2026-09-09）
A54: gmu_27 | B54: AI 相關毛利率額外改善 2027（新廠爬坡完成、組合；不含價格；情境 A 取高、C 取低） | C54: pt | D54: -0.01 | E54: 0.01 | F54: 0.02 | G54: Assumed | H54: 分析師：3Q26 起毛利率逐季上升（優分析 2026-09-09，Interested-party）；新廠（楊梅租賃廠 3Q26、中壢、泰國二廠）爬坡期折舊與良率壓力 | I54: —
A55: gmu_28 | B55: AI 相關毛利率額外改善 2028（新廠爬坡完成、組合；不含價格；情境 A 取高、C 取低） | C55: pt | D55: -0.01 | E55: 0.015 | F55: 0.03 | G55: Assumed | H55: 同上 | I55: —
A56: gmu_29 | B56: AI 相關毛利率額外改善 2029（新廠爬坡完成、組合；不含價格；情境 A 取高、C 取低） | C56: pt | D56: -0.01 | E56: 0.02 | F56: 0.035 | G56: Assumed | H56: 同上 | I56: —
A57: F. FY2026 錨點（1H26 財報＋3Q26 月營收實績＋假設；3Q26 財報與法說預計 2026-11 上旬，截至 2026-10-25 尚未公布）
A58: q1_rev | B58: 1Q26 營收（實績） | C58: NT$B | E58: 19.313 | G58: Verified | H58: https://stockanalysis.com/quote/tpe/2368/financials/?p=quarterly：1Q26 營收 19,313、毛利 6,722、營業利益 5,185、淨利 3,484 百萬元、稅前淨利率 26.34% | I58: 優分析 2026-08-11：1H26 營收 435.92 億、2Q26 242.79 億（相減得 1Q26 193.13 億）
A59: q3_rev | B59: 3Q26 營收（7–9 月月營收合計，實績） | C59: NT$B | E59: =10.015+10.384+9.32 -> 29.719 | G59: Verified | H59: https://finance.technews.tw/2026/10/08/gce-2368-202609-financial-report/：9 月 93.20 億、前 9 月 733.79 億；7 月 100.15 億、8 月 103.84 億（優分析） | I59: 理財周刊 2026-10-14：3Q26 營收 297.18 億（同值）
A60: q4g | B60: 4Q26 營收季增 | C60: % | D60: 0 | E60: 0.08 | F60: 0.15 | G60: Assumed | H60: 新 AI ASIC 產品線 4Q 開始出貨、楊梅租賃廠 3Q26 開出（優分析 2026-09-09、2026-03-10） | I60: 9 月營收月減 10.2%（technews）；共識 FY2026 營收 1,063 億（stockanalysis 8 家）隱含 4Q 約 327 億（只作 Recon）
A61: q_gm | B61: 3Q、4Q26 毛利率 | C61: % | D61: 0.34 | E61: 0.35 | F61: 0.365 | G61: Assumed | H61: 1Q26 34.81%、2Q26 34.65%、1H26 34.72%（優分析 2026-08-11） | I61: 分析師：3Q26 起逐季上升（Interested-party）
A62: q_opx | B62: 3Q、4Q26 營業費用 ÷ 營收 | C62: % | D62: 0.075 | E62: 0.08 | F62: 0.085 | G62: Assumed | H62: 1H26：毛利 151.35 − 營業利益 116.02 億＝35.33 億、8.1%（Q 頁） | I62: 2Q26 營業利益率 26.43%（理財周刊 2026-10-14）
A63: q_nop | B63: 3Q、4Q26 營業外淨額（每季） | C63: NT$B | D63: -0.2 | E63: 0 | F63: 0.3 | G63: Assumed | H63: 1Q26 稅前 − 營業利益＝−0.10 億（stockanalysis 稅前淨利率推算）；2Q26 由淨利 ÷ q_nir 推算約 +0.57 億（Derived） | I63: 可轉債利息、匯兌損益不外推
A64: q_nir | B64: 淨利 ÷ 稅前（1Q26 實績；3Q、4Q26 沿用） | C64: % | D64: 0.65 | E64: =3.484/(19.313*0.2634) -> 0.68487708 | F64: 0.75 | G64: Derived | H64: 1Q26：淨利 34.84 ÷（營收 193.13 × 稅前淨利率 26.34%）＝0.685（stockanalysis） | I64: FY2025：96.07 ÷ 141.73＝0.678（stockanalysis）；含中國子公司盈餘匯回與未分配盈餘稅（Assumed）
A65: sh_1h | B65: 1H26 加權股數（十億股） | C65: 十億股 | E65: =8.267/16.14 -> 0.5122057 | G65: Derived | H65: 1H26 淨利 82.67 億 ÷ EPS 16.14（優分析 2026-08-11） | I65: 理財周刊引 1H26 EPS 16.17（差異未說明）
A66: sh_h2 | B66: 下半年股數（十億股；含 Amazon 私募 185.6 萬股） | C66: 十億股 | E66: =0.5119+0.001856 -> 0.513756 | G66: Derived | H66: stockanalysis 流通股數 511.90 百萬股（2026-10-22） | I66: Amazon 私募 1,856,308 股、每股 856 元（理財周刊 2026-10-14）
A67: G. 營業費用、業外、稅與股數（FY2027 起）
A68: phi | B68: 營業費用成長對營收成長的彈性 | C68: x | D68: 0.4 | E68: 0.6 | F68: 1 | G68: Assumed | H68: 營業費用率 FY2025 9.4% → 1H26 8.1%（營收 +68%）（stockanalysis、Q 頁） | I68: 外資：成長三支柱含嚴格費用控制（technews 2026-05-13，Interested-party）
A69: opx_adj | B69: 營業費用額外占營收比（Sens 用；基準 0） | C69: pt | D69: -0.01 | E69: 0 | F69: 0.01 | G69: Assumed | H69: 無 | I69: Sens 用 ±1 個百分點
A70: nop_f | B70: 營業外淨額（每年） | C70: NT$B | D70: -1 | E70: 0 | F70: 1 | G70: Assumed | H70: FY2025 +1.30 億（stockanalysis 推算） | I70: 2025 年發行逾 90 億元無擔保可轉債（鉅亨 2025-09-26）
A71: nir_f | B71: 淨利 ÷ 稅前（FY2027 起） | C71: % | D71: 0.65 | E71: 0.685 | F71: 0.75 | G71: Derived | H71: 同 q_nir（1Q26 0.685；FY2025 0.678） | I71: —
A72: sh_g | B72: 股數年變動（可轉債轉換、員工酬勞） | C72: % | D72: 0 | E72: 0.01 | F72: 0.03 | G72: Assumed | H72: 2025 年逾 90 億元可轉債（鉅亨 2025-09-26）；轉換價：未找到 | I72: 理財周刊 2026-10-14 提示可轉債稀釋風險
A73: mf | B73: AI 部署係數（Sens 用；FY2027 起） | C73: x | D73: 0.8 | E73: 1 | F73: 1.2 | G73: Assumed | H73: 網通模型 2027 年 AI IT 資本支出約 2 倍 | I73: ±20%
A74: H. 共識、券商與上游（只作 Recon 對帳，不作校準）
A75: cons_rev26 | B75: 共識 FY2026 營收（MarketScreener） | C75: NT$B | E75: 106.371 | G75: Interested-party | H75: https://www.marketscreener.com/quote/stock/GOLD-CIRCUIT-ELECTRONICS--6496480/valuation/（2026-10-25 擷取，參考價 1,115） | I75: stockanalysis FY2026 1,063 億（8 家）
A76: cons_eps26 | B76: 共識 FY2026 EPS（MarketScreener） | C76: NT$ | E76: 41.22 | G76: Interested-party | H76: https://www.marketscreener.com/quote/stock/GOLD-CIRCUIT-ELECTRONICS--6496480/valuation/ | I76: stockanalysis FY2026 41.45（8 家，區間 37.24–46.54）
A77: cons_rev27 | B77: 共識 FY2027 營收（MarketScreener） | C77: NT$B | E77: 159.967 | G77: Interested-party | H77: https://www.marketscreener.com/quote/stock/GOLD-CIRCUIT-ELECTRONICS--6496480/valuation/（2026-10-25 擷取，參考價 1,115） | I77: —
A78: cons_eps27 | B78: 共識 FY2027 EPS（MarketScreener） | C78: NT$ | E78: 62.8 | G78: Interested-party | H78: https://www.marketscreener.com/quote/stock/GOLD-CIRCUIT-ELECTRONICS--6496480/valuation/ | I78: —
A79: cons_rev28 | B79: 共識 FY2028 營收（MarketScreener） | C79: NT$B | E79: 214.339 | G79: Interested-party | H79: https://www.marketscreener.com/quote/stock/GOLD-CIRCUIT-ELECTRONICS--6496480/valuation/（2026-10-25 擷取，參考價 1,115） | I79: —
A80: cons_eps28 | B80: 共識 FY2028 EPS（MarketScreener） | C80: NT$ | E80: 95.35 | G80: Interested-party | H80: https://www.marketscreener.com/quote/stock/GOLD-CIRCUIT-ELECTRONICS--6496480/valuation/ | I80: —
A81: fs_eps26 | B81: FactSet 中位數 FY2026 EPS（2026-09） | C81: NT$ | E81: 41.57 | G81: Interested-party | H81: https://www.moneyweekly.com.tw/_Article?AID=255441（理財周刊轉引） | I81: —
A82: fs_eps27 | B82: FactSet 中位數 FY2027 EPS（2026-09） | C82: NT$ | E82: 69.1 | G82: Interested-party | H82: https://www.moneyweekly.com.tw/_Article?AID=255441（理財周刊轉引） | I82: 理財周刊 2026-09-23：2027 年 67.32
A83: fs_eps28 | B83: FactSet 中位數 FY2028 EPS（2026-09） | C83: NT$ | E83: 95.07 | G83: Interested-party | H83: https://www.moneyweekly.com.tw/_Article?AID=255441（理財周刊轉引） | I83: —
A84: fb_eps27 | B84: 外資 FY2027 EPS（2026-05-13，目標價 1,310） | C84: NT$ | E84: 65.39 | G84: Interested-party | H84: https://finance.technews.tw/2026/05/13/three-pillars/ | I84: 券商名未載明
A85: emc_ccl26 | B85: 台光電模型：每 GW 高速 CCL 金額 2026（合計） | C85: US$M/GW | E85: 350 | G85: Derived | H85: emc/dist/20261025_台光電模型_v0.2.xlsx｜Units!C8:F8 | I85: 唯讀台光電成品（CCL 口徑；只在 Recon 對照）
A86: vg_pgw26 | B86: 勝宏模型：每 GW AI 高速 PCB 金額 2026（合計） | C86: US$M/GW | E86: 450 | G86: Derived | H86: victory_giant/dist/20261025_勝宏科技模型_v0.1.xlsx｜Units!C8:F8 | I86: 唯讀勝宏成品（Recon 用）
... A99: vg_sh26 | B99: 勝宏模型：勝宏有效份額 2026 | C99: % | E99: 0.24753179 | G99: Derived | H99: victory_giant/dist/20261025_勝宏科技模型_v0.1.xlsx｜Units!C13:F13 | I99: 唯讀勝宏成品
A100: I. 價格與估值
A101: px | B101: 股價（2026-10-22 收盤，臺灣證交所） | C101: NT$ | E101: 1115 | G101: Interested-party | H101: stockanalysis（網址見 Sources 頁）：10-22 收盤 1,115（−6.69%）、前收 1,195 | I101: nstock、聚財網 10-22：1,115；10-23 收盤：未找到
A102: pe_ttm | B102: 近 12 月 P/E（stockanalysis，10-22） | C102: x | E102: 39.79 | G102: Interested-party | H102: https://stockanalysis.com/quote/tpe/2368/ | I102: 近 12 月 EPS 28.02
A103: fpe | B103: 前瞻 P/E（stockanalysis，10-22） | C103: x | E103: 19.57 | G103: Interested-party | H103: https://stockanalysis.com/quote/tpe/2368/ | I103: 口徑：頁面未明示（約未來 12 月）
A104: cons_feps | B104: 共識前瞻 12 月 EPS（現價 ÷ 前瞻 P/E） | C104: NT$ | E104: =px/fpe -> 56.974962 | G104: Derived | H104: stockanalysis 前瞻 P/E 19.57（2026-10-22） | I104: 共識前瞻 EPS 的直接數字：未找到
A105: cons_tp | B105: 市場共識目標價（賣方平均） | C105: NT$ | E105: 1554 | G105: Interested-party | H105: https://stockanalysis.com/quote/tpe/2368/forecast/：9 位分析師（S&P Global）平均 1,554、中位數 1,610、區間 850–1,955（頁面時間 2026-09-04） | I105: 外資 1,310（technews 2026-05-13）
A106: nim_avg | B106: 十年平均淨利率替代值（2016–2020 營收與淨利未找到；依工作單以情境最後一年 × 0.8） | C106: % | E106: =PL!G39*0.8 -> 0.12587853 | G106: Assumed | H106: 工作單 2026-10-25：找不到十年平均時用最後一年 × 0.8；本值＝情境 C FY2029 淨利率 × 0.8（公式於建置時連結） | I106: 參考：FY2021–25 五年平均 13.4%（stockanalysis：11.0%、13.9%、11.7%、14.4%、16.0%）
A107: J. 目標價與收斂法參數（黃底；Assumed，Andy 可改）
A108: tp_wA | B108: 目標價情境權重 A（A 順利／B 平平／C 不如預期） | C108: % | E108: 0.3 | G108: Assumed（Andy 可改） | H108: Andy 可改（工作單 2026-10-25 預設 A 0.3／B 0.5／C 0.2） | I108: 三者合計應為 100%（Val 頁第 0 節列示）
A109: tp_wB | B109: 目標價情境權重 B（A 順利／B 平平／C 不如預期） | C109: % | E109: 0.5 | G109: Assumed（Andy 可改） | H109: Andy 可改（工作單 2026-10-25 預設 A 0.3／B 0.5／C 0.2） | I109: 三者合計應為 100%（Val 頁第 0 節列示）
A110: tp_wC | B110: 目標價情境權重 C（A 順利／B 平平／C 不如預期） | C110: % | E110: 0.2 | G110: Assumed（Andy 可改） | H110: Andy 可改（工作單 2026-10-25 預設 A 0.3／B 0.5／C 0.2） | I110: 三者合計應為 100%（Val 頁第 0 節列示）
A111: tp_r | B111: 折現率／要求報酬 | C111: % | E111: 0.1 | G111: Assumed（Andy 可改） | H111: Andy 可改（工作單預設 10%，各市場同一值） | I111: DCF 折現；情境價值推到 12 個月後
A112: tp_g | B112: 長期成長率 | C112: % | E112: 0.04 | G112: Assumed（Andy 可改） | H112: Andy 可改（工作單預設 4%） | I112: DCF 永續成長與 FY2032 收斂目標（情境 B）
...

Sheet Q
A1: Q — 實績與 FY2026 錨點（十億新台幣；EPS 為新台幣；股數為十億股）。藍字＝輸入；黑字＝公式。實績取自金像電財報與月營收公告（經 stockanalysis、優分析、technews 轉述）
A2: FY2026 錨點＝1H26 財報＋3Q26 月營收實績（7–9 月）＋假設（3Q 毛利率、營業費用率、營業外；4Q 營收季增）。1H26 毛利與營業利益＝1Q26（stockanalysis）＋2Q26（營收 × 毛利率 34.65%、營業利益率 26.43%）；1H26 稅前＝1Q26 稅前＋2Q26 淨利 ÷ q_nir（Derived）。3Q26 財報與法說預計 2026-11 上旬（stockanalysis 估 11-11；截至 2026-10-25 尚未公布），公布後更新
A3: 項目 | B3: FY2025A | C3: 1H26（實績） | D3: 3Q26（營收實績） | E3: 4Q26（模型） | F3: FY2026 錨點 | G3: 標記 | H3: 來源1 | I3: 來源2／說明
A4: 營收 | B4: 60.004 | C4: 43.592 | D4: =q3_rev -> 29.719 | E4: =D4*(1+q4g) -> 32.09652 | F4: =SUM(C4:E4) -> 105.40752 | G4: Verified／Assumed（4Q 季增） | H4: FY2025：stockanalysis 年度損益（營收 600.04 億、毛利 196.83 億、營業利益 140.43 億、淨利 96.07 億）；1H26：優分析 2026-08-11（營收 435.92 億、毛利率 34.72%、淨利 82.67 億、EPS 16.14） | I4: 3Q26＝7–9 月月營收合計（technews、優分析）；月營收與財報營收口徑可能略有差異
A5: 毛利 | B5: 19.683 | C5: =6.722+24.279*0.3465 -> 15.134673 | D5: =D4*q_gm -> 10.40165 | E5: =E4*q_gm -> 11.233782 | F5: =SUM(C5:E5) -> 36.770105 | G5: Verified／Assumed | H5: FY2025：stockanalysis 年度損益（營收 600.04 億、毛利 196.83 億、營業利益 140.43 億、淨利 96.07 億）；1H26：優分析 2026-08-11（營收 435.92 億、毛利率 34.72%、淨利 82.67 億、EPS 16.14） | I5: 2Q26 毛利率 34.65%（優分析）；1Q26 毛利 67.22 億（stockanalysis）
A6: 毛利率 | B6: =B5/B4 -> 0.32802813 | C6: =C5/C4 -> 0.34718924 | D6: =D5/D4 -> 0.35 | E6: =E5/E4 -> 0.35 | F6: =F5/F4 -> 0.34883759 | G6: Derived | H6: — | I6: 1H26 34.72%（優分析）；FY2025 32.8%
A7: 營業費用 | B7: =B5-B8 -> 5.64 | C7: =C5-C8 -> 3.5327338 | D7: =D4*q_opx -> 2.37752 | E7: =E4*q_opx -> 2.5677216 | F7: =SUM(C7:E7) -> 8.4779754 | G7: Derived／Assumed | H7: FY2025：stockanalysis 年度損益（營收 600.04 億、毛利 196.83 億、營業利益 140.43 億、淨利 96.07 億）；1H26：優分析 2026-08-11（營收 435.92 億、毛利率 34.72%、淨利 82.67 億、EPS 16.14） | I7: 毛利 − 營業利益
A8: 營業利益（毛利 − 營業費用） | B8: 14.043 | C8: =5.185+24.279*0.2643 -> 11.60194 | D8: =D5-D7 -> 8.02413 | E8: =E5-E7 -> 8.6660604 | F8: =SUM(C8:E8) -> 28.29213 | G8: Interested-party（stockanalysis）／Derived | H8: FY2025：stockanalysis 年度損益（營收 600.04 億、毛利 196.83 億、營業利益 140.43 億、淨利 96.07 億）；1H26：優分析 2026-08-11（營收 435.92 億、毛利率 34.72%、淨利 82.67 億、EPS 16.14） | I8: 1Q26 營業利益 51.85 億（stockanalysis）；2Q26 營業利益率 26.43%（理財周刊 2026-10-14）
A9: 營業利益率 | B9: =B8/B4 -> 0.2340344 | C9: =C8/C4 -> 0.26614837 | D9: =D8/D4 -> 0.27 | E9: =E8/E4 -> 0.27 | F9: =F8/F4 -> 0.26840713 | G9: Derived | H9: — | I9: —
A10: 營業外淨額 | B10: =B11-B8 -> 0.1299448 | C10: =C11-C8 -> 0.4688394 | D10: =q_nop -> 0 | E10: =q_nop -> 0 | F10: =SUM(C10:E10) -> 0.4688394 | G10: Derived／Assumed | H10: 稅前 − 營業利益 | I10: —
A11: 稅前利益 | B11: =60.004*0.2362 -> 14.172945 | C11: =19.313*0.2634+4.783/q_nir -> 12.070779 | D11: =D8+D10 -> 8.02413 | E11: =E8+E10 -> 8.6660604 | F11: =SUM(C11:E11) -> 28.76097 | G11: Derived | H11: FY2025＝營收 × 稅前淨利率 23.62%（stockanalysis）；1H26＝1Q26 營收 × 26.34%＋2Q26 淨利 47.83 億 ÷ q_nir | I11: 2Q26 稅前：未找到
A12: 歸屬母公司淨利 | B12: 9.607 | C12: 8.267 | D12: =D11*q_nir -> 5.4955428 | E12: =E11*q_nir -> 5.9351862 | F12: =SUM(C12:E12) -> 19.697729 | G12: Verified／Derived（3Q、4Q） | H12: FY2025：stockanalysis 年度損益（營收 600.04 億、毛利 196.83 億、營業利益 140.43 億、淨利 96.07 億）；1H26：優分析 2026-08-11（營收 435.92 億、毛利率 34.72%、淨利 82.67 億、EPS 16.14） | I12: FY2025 96.07 億（年增 71%）；1H26 82.67 億（2Q26 47.83 億）
A13: 淨利 ÷ 營業利益 | B13: =B12/B8 -> 0.68411308 | C13: =C12/C8 -> 0.71255326 | D13: =D12/D8 -> 0.68487708 | E13: =E12/E8 -> 0.68487708 | F13: =F12/F8 -> 0.69622644 | G13: Derived | H13: — | I13: —
A14: 股數（十億股；加權） | B14: =9.607/19.47 -> 0.49342578 | C14: =sh_1h -> 0.5122057 | D14: =sh_h2 -> 0.513756 | E14: =sh_h2 -> 0.513756 | F14: =(sh_1h+sh_h2)/2 -> 0.51298085 | G14: Derived | H14: FY2025：stockanalysis 年度損益（營收 600.04 億、毛利 196.83 億、營業利益 140.43 億、淨利 96.07 億）；1H26：優分析 2026-08-11（營收 435.92 億、毛利率 34.72%、淨利 82.67 億、EPS 16.14） | I14: 淨利 ÷ EPS；FY2026＝上半年與下半年平均
A15: EPS | B15: =B12/B14 -> 19.47 | C15: =C12/C14 -> 16.14 | D15: =D12/D14 -> 10.696795 | E15: =E12/E14 -> 11.552539 | F15: =F12/F14 -> 38.398566 | G15: Derived | H15: 淨利 ÷ 股數 | I15: —
A16: 公司揭露 EPS | B16: 19.47 | C16: 16.14 | G16: Verified | H16: FY2025：stockanalysis 年度損益（營收 600.04 億、毛利 196.83 億、營業利益 140.43 億、淨利 96.07 億）；1H26：優分析 2026-08-11（營收 435.92 億、毛利率 34.72%、淨利 82.67 億、EPS 16.14） | I16: FY2025 19.47（stockanalysis 列 19.00，口徑未載明）；1H26 16.14
A17: AI 相關營收（FY2025＝營收 × AI 占比；FY2026＝營收 − 非 AI） | B17: =B4*ai_25 -> 18.0012 | F17: =F4-F18 -> 55.00416 | G17: Interested-party／Derived | H17: AI 占比（In 頁 D 節） | I17: 各季 AI 營收金額未揭露：未找到
A18: 非 AI 營收（FY2026＝FY2025 ×（1＋g_nai26）） | B18: =B4-B17 -> 42.0028 | F18: =B18*(1+g_nai26) -> 50.40336 | G18: Derived／Assumed | H18: — | I18: 一般伺服器、網通、筆電、其他
A23: FY2026 錨點的檢查（參考；校準未使用券商數字）
A24: FY2026 營收年增 | B24: =F4/B4-1 -> 0.75667489
A25: FY2026 AI 相關 ÷ 營收 | B25: =F17/F4 -> 0.52182387
A26: FY2026 營業費用 ÷ 營收 | B26: =F7/F4 -> 0.080430461
A27: FY2026 營收 ÷ 共識（MarketScreener）− 1 | B27: =F4/cons_rev26-1 -> -0.0090577319
A28: FY2026 EPS ÷ 共識（MarketScreener）− 1 | B28: =F15/cons_eps26-1 -> -0.068448185
A29: 4Q26 年化營收 ÷ FY2026 營收 | B29: =E4*4/F4 -> 1.2179973

Sheet Units
A1: Units — 每 GW AI 高速 PCB 金額（口徑與勝宏模型一致，唯讀 victory_giant/dist；本專案權威在勝宏模型）、金像電參與係數、份額與產能。部署 GW＝AI IT 資本支出（markets/network）÷ 每 GW IT 資本支出（Tokenomics，經橋接表）
A3: 項目 | B3: 單位 | C3: CY2026 | D3: CY2027 | E3: CY2028 | F3: CY2029 | G3: 說明
A4: 部署 GW（情境 B） | B4: GW | C4: =PL!D111 -> 23.399538 | D4: =PL!E111 -> 41.646766 | E4: =PL!F111 -> 42.233711 | F4: =PL!G111 -> 51.117803 | G4: AI IT 資本支出 × 顆數係數 B ÷ 每 GW IT 資本支出
A5: 勝宏模型：每 GW AI 高速 PCB 金額（合計） | B5: US$M/GW | C5: =vg_pgw26 -> 450 | D5: =vg_pgw27 -> 682 | E5: =vg_pgw28 -> 792 | F5: =vg_pgw29 -> 877 | G5: 唯讀 victory_giant/dist（口徑來源）
A6: 每 GW PCB：加速器卡／運算板 | B6: US$M/GW | C6: =PL!D112 -> 280 | D6: =PL!E112 -> 420 | E6: =PL!F112 -> 462 | F6: =PL!G112 -> 504 | G6: 勝宏模型值；成長倍率 pgwf＝1 時相同
A7: 每 GW PCB：交換器板 | B7: US$M/GW | C7: =PL!D113 -> 120 | D7: =PL!E113 -> 162 | E7: =PL!F113 -> 180 | F7: =PL!G113 -> 198 | G7: 同上
A8: 每 GW PCB：中板／背板／其他 × 參與係數 | B8: US$M/GW | C8: =PL!D114 -> 25 | D8: =PL!E114 -> 50 | E8: =PL!F114 -> 75 | F8: =PL!G114 -> 87.5 | G8: 參與係數 w_mid（Assumed）
A9: 每 GW 金像電可參與 AI 高速 PCB 金額（不含價格指數） | B9: US$M/GW | C9: =PL!D115 -> 425 | D9: =PL!E115 -> 632 | E9: =PL!F115 -> 717 | F9: =PL!G115 -> 789.5
A10: 每架等值可參與金額（以 VR200 每 GW 架數換算） | B10: US$K/架 | C10: =PL!D115*1000/racks_vr -> 104.88648 | D10: =PL!E115*1000/racks_vr -> 155.97236 | E10: =PL!F115*1000/racks_vr -> 176.94965 | F10: =PL!G115*1000/racks_vr -> 194.84205
A11: 每 GW 可參與 PCB 金額 ÷ 台光電模型每 GW CCL 金額 | B11: x | C11: =PL!D115/emc_ccl26 -> 1.2142857 | D11: =PL!E115/emc_ccl27 -> 1.1981043 | E11: =PL!F115/emc_ccl28 -> 1.1773399 | F11: =PL!G115/emc_ccl29 -> 1.1916981 | G11: 見 Recon B 節
A12: 可參與 AI 高速 PCB 市場（含價格指數） | B12: US$B | C12: =PL!D116*PL!D118 -> 9.9448037 | D12: =PL!E116*PL!E118 -> 26.320756 | E12: =PL!F116*PL!F118 -> 29.373123 | F12: =PL!G116*PL!G118 -> 37.936055 | G12: 含 ASIC 部署（假設每 GW 金額相同）
A13: 金像電有效份額 | B13: % | C13: =PL!D121 -> 0.17284202 | D13: =PL!E121 -> 0.17284202 | E13: =PL!F121 -> 0.16419992 | F13: =PL!G121 -> 0.15555782 | G13: FY2026 以錨點 AI 相關營收校準
A14: 金像電 AI 相關營收（需求面） | B14: US$B | C14: =PL!D122/fx -> 1.71888 | D14: =PL!E122/fx -> 4.5493328 | E14: =PL!F122/fx -> 4.8230646 | F14: =PL!G122/fx -> 5.9012501
A15: 金像電 AI 相關營收（實際＝MIN 需求面、產能） | B15: US$B | C15: =PL!D127/fx -> 1.71888 | D15: =PL!E127/fx -> 3.122418 | E15: =PL!F127/fx -> 4.3673383 | F15: =PL!G127/fx -> 5.3670152
A16: 每 GW 金像電 AI 相關營收 | B16: US$M/GW | C16: =PL!D133 -> 73.45786 | D16: =PL!E133 -> 74.973841 | E16: =PL!F133 -> 103.40882 | F16: =PL!G133 -> 104.99307 | G16: 對照勝宏、台光電（Recon）
A17: 平均產值產能指數（FY2026＝1） | B17: x | C17: =PL!D124 -> 1 | D17: =PL!E124 -> 1.45 | E17: =PL!F124 -> 1.9 | F17: =PL!G124 -> 2.3 | G17: 公司擴產計畫（Assumed）
A18: 產能上限營收（含價格指數） | B18: NT$B | C18: =PL!D125 -> 105.40752 | D18: =PL!E125 -> 152.8409 | E18: =PL!F125 -> 194.26606 | F18: =PL!G125 -> 227.89106 | G18: FY2026 校準
A19: 需求面 ÷ 產能上限 | B19: % | C19: =PL!D132 -> 1 | D19: =PL!E132 -> 1.2987503 | E19: =PL!F132 -> 1.0750684 | F19: =PL!G132 -> 1.0750162 | G19: 大於 100%＝產能受限
A20: 其他廠商（健鼎、TTM、勝宏、沪电、華通等）＝ 可參與市場 − 金像電 | B20: US$B | C20: =PL!D116*PL!D118-PL!D127/fx -> 8.2259237 | D20: =PL!E116*PL!E118-PL!E127/fx -> 23.198338 | E20: =PL!F116*PL!F118-PL!F127/fx -> 25.005785 | F20: =PL!G116*PL!G118-PL!G127/fx -> 32.56904 | G20: 產能受限時，未滿足需求計入其他廠商
A22: 讀法：每 GW 金額的絕對水準只影響 FY2026 校準出的份額（金額高 → 份額低），不影響營收；影響營收的是金額成長（勝宏模型世代指數 × pgwf）、參與係數與份額相對值。產能受限的年度，營收由產值產能指數決定；擴產趕上需求後，份額與每 GW 金額重新成為主要變數。

Sheet PL
A1: PL — 金像電損益（十億新台幣；EPS 新台幣；歸屬母公司）。FY2025A 實績、FY2026 錨點（1H26 財報＋3Q26 月營收＋假設），FY2027 起為模型。FY(t)＝CY(t)。三情境各一個完整推導區塊（本頁下方），頂端為摘要。顆數係數從 CY2028 開始；份額、價格、AI 毛利率改善從 FY2027 起依情境取高／基準／低值
A2: 灰底＝FY2030–FY2032 收斂法（上游只到 2029）：營收年增線性收斂到 fade_g、淨利率線性收斂到 fade_m（In 頁 J 節），非驅動因子推導
A3: 情境／項目 | B3: 單位 | C3: FY2025A | D3: FY2026（錨點） | E3: FY2027 | F3: FY2028 | G3: FY2029 | H3: FY2030（收斂） | I3: FY2031（收斂） | J3: FY2032（收斂） | K3: 說明
A4: 情境 A
A5: 營收 | B5: NT$B | C5: =C83 -> 60.004 | D5: =D83 -> 105.40752 | E5: =E83 -> 157.42613 | F5: =F83 -> 204.27977 | G5: =G83 -> 242.4373 | H5: =H83 -> 277.47603 | I5: =I83 -> 305.8517 | J5: =J83 -> 324.2028
A6: 營收年增 | B6: % | D6: =D84 -> 0.75667489 | E6: =E84 -> 0.4935 | F6: =F84 -> 0.29762303 | G6: =G84 -> 0.18679051 | H6: =H84 -> 0.144527 | I6: =I84 -> 0.1022635 | J6: =J84 -> 0.06
A7: AI 相關營收（AI 伺服器主板、800G 交換器） | B7: NT$B | C7: =C81 -> 18.0012 | D7: =D81 -> 55.00416 | E7: =E81 -> 104.5026 | F7: =F81 -> 149.76854 | G7: =G81 -> 186.29073
A8: 非 AI 營收 | B8: NT$B | C8: =C80 -> 42.0028 | D8: =D80 -> 50.40336 | E8: =E80 -> 52.923528 | F8: =F80 -> 54.511234 | G8: =G80 -> 56.146571
A9: 需求面 ÷ 產能上限 | B9: % | D9: =D86 -> 1 | E9: =E86 -> 1.3648637 | F9: =F86 -> 1.3958261 | G9: =G86 -> 1.3689433
A10: 毛利率 | B10: % | C10: =C92 -> 0.32802813 | D10: =D92 -> 0.34883759 | E10: =E92 -> 0.387979 | F10: =F92 -> 0.40063865 | G10: =G92 -> 0.40039027
A11: 營業利益率 | B11: % | C11: =C96 -> 0.2340344 | D11: =D96 -> 0.26840713 | E11: =E96 -> 0.31817926 | F11: =F96 -> 0.33724262 | G11: =G96 -> 0.34098543
A12: 歸屬母公司淨利 | B12: NT$B | C12: =C98 -> 9.607 | D12: =D98 -> 19.697729 | E12: =E98 -> 34.311465 | F12: =F98 -> 47.190915 | G12: =G98 -> 56.627296 | H12: =H98 -> 64.811469 | I12: =I98 -> 71.439317 | J12: =J98 -> 75.725676
A13: 淨利率 | B13: % | C13: =C103 -> 0.16010599 | D13: =D103 -> 0.18687214 | E13: =E103 -> 0.21795279 | F13: =F103 -> 0.2310112 | G13: =G103 -> 0.23357502 | H13: =H103 -> 0.23357502 | I13: =I103 -> 0.23357502 | J13: =J103 -> 0.23357502
A14: EPS | B14: NT$ | C14: =C101 -> 19.47 | D14: =D101 -> 38.398566 | E14: =E101 -> 66.124283 | F14: =F101 -> 90.044822 | G14: =G101 -> 106.98054 | H14: =H101 -> 121.22982 | I14: =I101 -> 132.30417 | J14: =J101 -> 138.85388
A15: EPS 年增 | B15: % | D15: =D102 -> 0.97219136 | E15: =E102 -> 0.72205086 | F15: =F102 -> 0.36175119 | G15: =G102 -> 0.18808101 | H15: =H102 -> 0.13319505 | I15: =I102 -> 0.091350002 | J15: =J102 -> 0.04950495
A17: 情境 B
A18: 營收 | B18: NT$B | C18: =C129 -> 60.004 | D18: =D129 -> 105.40752 | E18: =E129 -> 152.8409 | F18: =F129 -> 194.26606 | G18: =G129 -> 227.89106 | H18: =H129 -> 257.22631 | I18: =I129 -> 278.92656 | J18: =J129 -> 290.08362
A19: 營收年增 | B19: % | D19: =D130 -> 0.75667489 | E19: =E130 -> 0.45 | F19: =F130 -> 0.27103448 | G19: =G130 -> 0.17308736 | H19: =H130 -> 0.12872491 | I19: =I130 -> 0.084362453 | J19: =J130 -> 0.04
A20: AI 相關營收（AI 伺服器主板、800G 交換器） | B20: NT$B | C20: =C127 -> 18.0012 | D20: =D127 -> 55.00416 | E20: =E127 -> 99.917376 | F20: =F127 -> 139.75483 | G20: =G127 -> 171.74449
A21: 非 AI 營收 | B21: NT$B | C21: =C126 -> 42.0028 | D21: =D126 -> 50.40336 | E21: =E126 -> 52.923528 | F21: =F126 -> 54.511234 | G21: =G126 -> 56.146571
A22: 需求面 ÷ 產能上限 | B22: % | D22: =D132 -> 1 | E22: =E132 -> 1.2987503 | F22: =F132 -> 1.0750684 | G22: =G132 -> 1.0750162
A23: 毛利率 | B23: % | C23: =C138 -> 0.32802813 | D23: =D138 -> 0.34883759 | E23: =E138 -> 0.368566 | F23: =F138 -> 0.36596201 | G23: =G138 -> 0.35806711
A24: 營業利益率 | B24: % | C24: =C142 -> 0.2340344 | D24: =D142 -> 0.26840713 | E24: =E142 -> 0.29812001 | F24: =F142 -> 0.30152476 | G24: =G142 -> 0.29743291
A25: 歸屬母公司淨利 | B25: NT$B | C25: =C144 -> 9.607 | D25: =D144 -> 19.697729 | E25: =E144 -> 31.211979 | F25: =F144 -> 40.124578 | G25: =G144 -> 46.430875 | H25: =H144 -> 49.069616 | I25: =I144 -> 49.589573 | J25: =J144 -> 47.808692
A26: 淨利率 | B26: % | C26: =C149 -> 0.16010599 | D26: =D149 -> 0.18687214 | E26: =E149 -> 0.20421221 | F26: =F149 -> 0.20654446 | G26: =G149 -> 0.20374154 | H26: =H149 -> 0.19076437 | I26: =I149 -> 0.1777872 | J26: =J149 -> 0.16481004
A27: EPS | B27: NT$ | C27: =C147 -> 19.47 | D27: =D147 -> 38.398566 | E27: =E147 -> 60.151023 | F27: =F147 -> 76.561569 | G27: =G147 -> 87.717419 | H27: =H147 -> 91.784693 | I27: =I147 -> 91.838882 | J27: =J147 -> 87.664086
A28: EPS 年增 | B28: % | D28: =D148 -> 0.97219136 | E28: =E148 -> 0.56649141 | F28: =F148 -> 0.27282238 | G28: =G148 -> 0.14571083 | H28: =H148 -> 0.04636792 | I28: =I148 -> 0.00059039546 | J28: =J148 -> -0.04545783
A30: 情境 C
A31: 營收 | B31: NT$B | C31: =C175 -> 60.004 | D31: =D175 -> 105.40752 | E31: =E175 -> 146.72727 | F31: =F175 -> 141.18508 | G31: =G175 -> 153.20576 | H31: =H175 -> 162.92323 | I31: =I175 -> 169.71937 | J31: =J175 -> 173.11376
A32: 營收年增 | B32: % | D32: =D176 -> 0.75667489 | E32: =E176 -> 0.392 | F32: =F176 -> -0.037772033 | G32: =G176 -> 0.08514131 | H32: =H176 -> 0.06342754 | I32: =I176 -> 0.04171377 | J32: =J176 -> 0.02
A33: AI 相關營收（AI 伺服器主板、800G 交換器） | B33: NT$B | C33: =C173 -> 18.0012 | D33: =D173 -> 55.00416 | E33: =E173 -> 93.80374 | F33: =F173 -> 86.673847 | G33: =G173 -> 97.059193
A34: 非 AI 營收 | B34: NT$B | C34: =C172 -> 42.0028 | D34: =D172 -> 50.40336 | E34: =E172 -> 52.923528 | F34: =F172 -> 54.511234 | G34: =G172 -> 56.146571
A35: 需求面 ÷ 產能上限 | B35: % | D35: =D178 -> 1 | E35: =E178 -> 1.1703053 | F35: =F178 -> 0.76625934 | G35: =G178 -> 0.71811335
A36: 毛利率 | B36: % | C36: =C184 -> 0.32802813 | D36: =D184 -> 0.34883759 | E36: =E184 -> 0.33812105 | F36: =F184 -> 0.31969817 | G36: =G184 -> 0.30154961
A37: 營業利益率 | B37: % | C37: =C188 -> 0.2340344 | D37: =D188 -> 0.26840713 | E37: =E188 -> 0.26675057 | F37: =F188 -> 0.24552606 | G37: =G188 -> 0.22970535
A38: 歸屬母公司淨利 | B38: NT$B | C38: =C190 -> 9.607 | D38: =D190 -> 19.697729 | E38: =E190 -> 26.810614 | F38: =F190 -> 23.745263 | G38: =G190 -> 24.106646 | H38: =H190 -> 23.926626 | I38: =I190 -> 23.144361 | J38: =J190 -> 21.791306
A39: 淨利率 | B39: % | C39: =C195 -> 0.16010599 | D39: =D195 -> 0.18687214 | E39: =E195 -> 0.18272414 | F39: =F195 -> 0.16818535 | G39: =G195 -> 0.15734816 | H39: =H195 -> 0.14685829 | I39: =I195 -> 0.13636841 | J39: =J195 -> 0.12587853
A40: EPS | B40: NT$ | C40: =C193 -> 19.47 | D40: =D193 -> 38.398566 | E40: =E193 -> 51.668812 | F40: =F193 -> 45.308254 | G40: =G193 -> 45.542384 | H40: =H193 -> 44.754743 | I40: =I193 -> 42.862886 | J40: =J193 -> 39.957481
A41: EPS 年增 | B41: % | D41: =D194 -> 0.97219136 | E41: =E194 -> 0.34559225 | F41: =F194 -> -0.12310247 | G41: =G194 -> 0.0051674866 | H41: =H194 -> -0.017294682 | I41: =I194 -> -0.04227164 | J41: =J194 -> -0.067783701
A43: 核對（應為 0）：FY2026 模型 − 錨點
A44: 三情境：營收差（NT$B） | D44: =ABS(D83-a26_rev)+ABS(D129-a26_rev)+ABS(D175-a26_rev) -> 0
A45: 情境 B：AI 相關差（NT$B） | D45: =D127-a26_ai -> 0
A46: 情境 B：毛利差（NT$B） | D46: =D136*D127+D135*D126-a26_gp -> 0
A47: 情境 B：產能上限 − 營收（NT$B；FY2026 校準恆等） | D47: =D125-D129 -> 0
A60: 情境 A（順利）：顆數基準（tsmc 係數 A＝1.0）；份額、價格、AI 毛利率改善取高值
A61: 項目 | B61: 單位 | C61: FY2025A | D61: FY2026（錨點） | E61: FY2027 | F61: FY2028 | G61: FY2029 | H61: FY2030（收斂） | I61: FY2031（收斂） | J61: FY2032（收斂） | K61: 說明
A62: A. AI 部署與每 GW AI 高速 PCB 金額（需求面；D 欄＝FY2026 校準年；每 GW 金額取自勝宏模型）
A63: AI IT 資本支出 × 情境顆數係數 | B63: US$B | D63: =itc_26*1 -> 781.87292 | E63: =itc_27*1*1 -> 1565.35 | F63: =itc_28*um28_A*1 -> 1984.2639 | G63: =itc_29*um29_A*1 -> 2260.3903
A64: 每 GW IT 資本支出 | B64: US$B | D64: =itpg_gb*(1-vr26)+itpg_vr*vr26 -> 33.414032 | E64: =itpg_vr -> 37.586352 | F64: =itpg_vr -> 37.586352 | G64: =itpg_vr -> 37.586352
A65: 部署 GW（IT 電力） | B65: GW | D65: =D63/D64 -> 23.399538 | E65: =E63/E64 -> 41.646766 | F65: =F63/F64 -> 52.792138 | G65: =G63/G64 -> 60.138592
A66: 每 GW PCB：加速器卡／運算板 | B66: US$M/GW | D66: =vg_cmp26 -> 280 | E66: =(vg_cmp26+(vg_cmp27-vg_cmp26)*pgwf) -> 420 | F66: =(vg_cmp26+(vg_cmp28-vg_cmp26)*pgwf) -> 462 | G66: =(vg_cmp26+(vg_cmp29-vg_cmp26)*pgwf) -> 504
A67: 每 GW PCB：交換器板 | B67: US$M/GW | D67: =vg_sw26 -> 120 | E67: =(vg_sw26+(vg_sw27-vg_sw26)*pgwf) -> 162 | F67: =(vg_sw26+(vg_sw28-vg_sw26)*pgwf) -> 180 | G67: =(vg_sw26+(vg_sw29-vg_sw26)*pgwf) -> 198
A68: 每 GW PCB：中板／背板／其他 × 金像電參與係數 | B68: US$M/GW | D68: =vg_mid26*w_mid -> 25 | E68: =(vg_mid26+(vg_mid27-vg_mid26)*pgwf)*w_mid -> 50 | F68: =(vg_mid26+(vg_mid28-vg_mid26)*pgwf)*w_mid -> 75 | G68: =(vg_mid26+(vg_mid29-vg_mid26)*pgwf)*w_mid -> 87.5
A69: 每 GW 金像電可參與 AI 高速 PCB 金額（三項合計） | B69: US$M/GW | D69: =D66+D67+D68 -> 425 | E69: =E66+E67+E68 -> 632 | F69: =F66+F67+F68 -> 717 | G69: =G66+G67+G68 -> 789.5
A70: 可參與 AI 高速 PCB 市場（美元；不含價格指數） | B70: US$B | D70: =D65*D69/1000 -> 9.9448037 | E70: =E65*E69/1000 -> 26.320756 | F70: =F65*F69/1000 -> 37.851963 | G70: =G65*G69/1000 -> 47.479418
A71: 可參與 AI 高速 PCB 市場（新台幣） | B71: NT$B | D71: =D70*fx -> 318.23372 | E71: =E70*fx -> 842.26419 | F71: =F70*fx -> 1211.2628 | G71: =G70*fx -> 1519.3414
A72: PCB 價格指數（FY2026＝1） | B72: x | D72: =1 -> 1 | E72: =PPHI_27 -> 1.03 | F72: =PPHI_28 -> 1.02 | G72: =PPHI_29 -> 1
A73: 金像電有效份額（FY2026 校準）＝ AI 相關營收 ÷ 可參與市場 | B73: % | D73: =a26_ai/D71 -> 0.17284202 | K73: Derived：分子為 FY2026 錨點營收 − 非 AI；分母為本模型的可參與市場（含 ASIC）
A74: 份額相對值（÷ FY2026） | B74: x | D74: =1 -> 1 | E74: =RHI_27 -> 1.08 | F74: =RHI_28 -> 1.08 | G74: =RHI_29 -> 1.05
A75: 金像電有效份額 | B75: % | D75: =$D$73*D74 -> 0.17284202 | E75: =$D$73*E74 -> 0.18666939 | F75: =$D$73*F74 -> 0.18666939 | G75: =$D$73*G74 -> 0.18148413
A76: AI 相關營收（需求面）＝ 市場 × 份額 × 價格指數 | B76: NT$B | D76: =D71*D75*D72 -> 55.00416 | E76: =E71*E75*E72 -> 161.94169 | F76: =F71*F75*F72 -> 230.6278 | G76: =G71*G75*G72 -> 275.73634
A77: B. 產能上限（全產全銷）與營收
A78: 平均產值產能指數（FY2026 營收＝1） | B78: x | D78: =1 -> 1 | E78: =cx_27 -> 1.45 | F78: =cx_28 -> 1.9 | G78: =cx_29 -> 2.3 | K78: FY2026 校準：公司稱產能吃緊、產線滿載，FY2026 營收視為產能（Derived）
A79: 產能上限營收 ＝ FY2026 營收 × 產能指數 × 價格指數 | B79: NT$B | D79: =a26_rev*D78*D72 -> 105.40752 | E79: =a26_rev*E78*E72 -> 157.42613 | F79: =a26_rev*F78*F72 -> 204.27977 | G79: =a26_rev*G78*G72 -> 242.4373
A80: 非 AI 營收 | B80: NT$B | C80: =a25_nai -> 42.0028 | D80: =a26_nai -> 50.40336 | E80: =D80*(1+g_nai27) -> 52.923528 | F80: =E80*(1+g_nai28) -> 54.511234 | G80: =F80*(1+g_nai29) -> 56.146571
A81: AI 相關營收 ＝ MIN（需求面、產能上限 − 非 AI） | B81: NT$B | C81: =a25_ai -> 18.0012 | D81: =D76 -> 55.00416 | E81: =MIN(E76,E79-E80) -> 104.5026 | F81: =MIN(F76,F79-F80) -> 149.76854 | G81: =MIN(G76,G79-G80) -> 186.29073 | K81: 產能不足時，非 AI 照成長率出貨、AI 取剩餘產能（Assumed）
A82: 產能是否受限 | E82: =IF(E76>E79-E80+0.0001,"受限","未受限") -> 受限 | F82: =IF(F76>F79-F80+0.0001,"受限","未受限") -> 受限 | G82: =IF(G76>G79-G80+0.0001,"受限","未受限") -> 受限
A83: 營收 | B83: NT$B | C83: =C81+C80 -> 60.004 | D83: =D81+D80 -> 105.40752 | E83: =E81+E80 -> 157.42613 | F83: =F81+F80 -> 204.27977 | G83: =G81+G80 -> 242.4373 | H83: =G83*(1+H84) -> 277.47603 | I83: =H83*(1+I84) -> 305.8517 | J83: =I83*(1+J84) -> 324.2028 | K83: FY2030 起為收斂法：營收年增由 FY2029 線性收斂到 fade_g、淨利率收斂到 fade_m（FY2032 達到），非驅動因子推導
A84: 營收年增 | B84: % | D84: =D83/C83-1 -> 0.75667489 | E84: =E83/D83-1 -> 0.4935 | F84: =F83/E83-1 -> 0.29762303 | G84: =G83/F83-1 -> 0.18679051 | H84: =$G84+(fade_gA-$G84)*1/3 -> 0.144527 | I84: =$G84+(fade_gA-$G84)*2/3 -> 0.1022635 | J84: =$G84+(fade_gA-$G84)*3/3 -> 0.06
A85: AI 相關 ÷ 營收 | B85: % | C85: =C81/C83 -> 0.3 | D85: =D81/D83 -> 0.52182387 | E85: =E81/E83 -> 0.66381993 | F85: =F81/F83 -> 0.73315403 | G85: =G81/G83 -> 0.76840787
A86: 需求面 ÷ 產能上限（AI 需求面＋非 AI） | B86: % | D86: =(D76+D80)/D79 -> 1 | E86: =(E76+E80)/E79 -> 1.3648637 | F86: =(F76+F80)/F79 -> 1.3958261 | G86: =(G76+G80)/G79 -> 1.3689433 | K86: 大於 100%＝需求超過產能（營收由產能決定）
A87: 每 GW 金像電 AI 相關營收 | B87: US$M/GW | D87: =D81/fx/D65*1000 -> 73.45786 | E87: =E81/fx/E65*1000 -> 78.414405 | F87: =F81/fx/F65*1000 -> 88.654619 | G87: =G81/fx/G65*1000 -> 96.802818
A88: C. 損益
A89: 其他營收毛利率 ＝ 錨點毛利率 − 差距 × AI 占比（FY2026 校準） | B89: % | D89: =a26_gp/D83-d_ai*D85 -> 0.29665521 | K89: Derived：讓 FY2026 毛利率等於錨點；AI 相關毛利率＝其他＋差距
A90: AI 相關毛利率 ＝ 1 −（1 − 校準值）÷ 價格指數 ＋ 額外改善 | B90: % | D90: =D89+d_ai -> 0.39665521 | E90: =1-(1-$D$90)/E72+GUHI_27 -> 0.43422835 | F90: =1-(1-$D$90)/F72+GUHI_28 -> 0.4384855 | G90: =1-(1-$D$90)/G72+GUHI_29 -> 0.43165521 | K90: Derived：同規格成本不變，價格升降全部落在毛利；額外改善為新廠爬坡完成與組合（Assumed）
A91: 毛利 | B91: NT$B | C91: =a25_gp -> 19.683 | D91: =a26_gp -> 36.770105 | E91: =E81*E90+E80*$D$89 -> 61.078033 | F91: =F81*F90+F80*$D$89 -> 81.842374 | G91: =G81*G90+G80*$D$89 -> 97.069534
A92: 毛利率 | B92: % | C92: =C91/C83 -> 0.32802813 | D92: =D91/D83 -> 0.34883759 | E92: =E91/E83 -> 0.387979 | F92: =F91/F83 -> 0.40063865 | G92: =G91/G83 -> 0.40039027
A93: 營業費用（基準路徑） | B93: NT$B | C93: =a25_opx -> 5.64 | D93: =a26_opx -> 8.4779754 | E93: =D93*(1+MAX(0,phi*E84)) -> 10.988304 | F93: =E93*(1+MAX(0,phi*F84)) -> 12.950527 | G93: =F93*(1+MAX(0,phi*G84)) -> 14.401949
A94: 營業費用 | B94: NT$B | C94: =C93 -> 5.64 | D94: =D93 -> 8.4779754 | E94: =E93+0*E83 -> 10.988304 | F94: =F93+0*F83 -> 12.950527 | G94: =G93+0*G83 -> 14.401949
A95: 營業利益 | B95: NT$B | C95: =C91-C94 -> 14.043 | D95: =D91-D94 -> 28.29213 | E95: =E91-E94 -> 50.08973 | F95: =F91-F94 -> 68.891846 | G95: =G91-G94 -> 82.667585
A96: 營業利益率 | B96: % | C96: =C95/C83 -> 0.2340344 | D96: =D95/D83 -> 0.26840713 | E96: =E95/E83 -> 0.31817926 | F96: =F95/F83 -> 0.33724262 | G96: =G95/G83 -> 0.34098543
A97: 營業外淨額 | B97: NT$B | E97: =nop_f -> 0 | F97: =nop_f -> 0 | G97: =nop_f -> 0 | K97: FY2025、FY2026 含在淨利錨點內
A98: 歸屬母公司淨利 | B98: NT$B | C98: =a25_ni -> 9.607 | D98: =a26_ni -> 19.697729 | E98: =(E95+E97)*nir_f -> 34.311465 | F98: =(F95+F97)*nir_f -> 47.190915 | G98: =(G95+G97)*nir_f -> 56.627296 | H98: =H83*H103 -> 64.811469 | I98: =I83*I103 -> 71.439317 | J98: =J83*J103 -> 75.725676
A99: 淨利 ÷ 營業利益 | B99: % | C99: =C98/C95 -> 0.68411308 | D99: =D98/D95 -> 0.69622644 | E99: =E98/E95 -> 0.685 | F99: =F98/F95 -> 0.685 | G99: =G98/G95 -> 0.685
A100: 股數 | B100: 十億股 | C100: =a25_sh -> 0.49342578 | D100: =a26_sh -> 0.51298085 | E100: =sh_h2*(1+sh_g) -> 0.51889356 | F100: =E100*(1+sh_g) -> 0.5240825 | G100: =F100*(1+sh_g) -> 0.52932332 | H100: =G100*(1+sh_g) -> 0.53461655 | I100: =H100*(1+sh_g) -> 0.53996272 | J100: =I100*(1+sh_g) -> 0.54536235 | K100: FY2027 起＝期末股數 ×（1＋sh_g）（FY2026 為加權）
A101: EPS | B101: NT$ | C101: =C98/C100 -> 19.47 | D101: =D98/D100 -> 38.398566 | E101: =E98/E100 -> 66.124283 | F101: =F98/F100 -> 90.044822 | G101: =G98/G100 -> 106.98054 | H101: =H98/H100 -> 121.22982 | I101: =I98/I100 -> 132.30417 | J101: =J98/J100 -> 138.85388
A102: EPS 年增 | B102: % | D102: =D101/C101-1 -> 0.97219136 | E102: =E101/D101-1 -> 0.72205086 | F102: =F101/E101-1 -> 0.36175119 | G102: =G101/F101-1 -> 0.18808101 | H102: =H101/G101-1 -> 0.13319505 | I102: =I101/H101-1 -> 0.091350002 | J102: =J101/I101-1 -> 0.04950495
A103: 淨利率（歸屬母公司淨利 ÷ 營收） | B103: % | C103: =C98/C83 -> 0.16010599 | D103: =D98/D83 -> 0.18687214 | E103: =E98/E83 -> 0.21795279 | F103: =F98/F83 -> 0.2310112 | G103: =G98/G83 -> 0.23357502 | H103: =$G103+(fade_mA-$G103)*1/3 -> 0.23357502 | I103: =$G103+(fade_mA-$G103)*2/3 -> 0.23357502 | J103: =$G103+(fade_mA-$G103)*3/3 -> 0.23357502
A106: 情境 B（平平）：tsmc 係數 B（CY2028 ×0.8、CY2029 ×0.85）；公司特有變數取基準
A107: 項目 | B107: 單位 | C107: FY2025A | D107: FY2026（錨點） | E107: FY2027 | F107: FY2028 | G107: FY2029 | H107: FY2030（收斂） | I107: FY2031（收斂） | J107: FY2032（收斂） | K107: 說明
A108: A. AI 部署與每 GW AI 高速 PCB 金額（需求面；D 欄＝FY2026 校準年；每 GW 金額取自勝宏模型）
A109: AI IT 資本支出 × 情境顆數係數 | B109: US$B | D109: =itc_26*1 -> 781.87292 | E109: =itc_27*1*1 -> 1565.35 | F109: =itc_28*um28_B*1 -> 1587.4111 | G109: =itc_29*um29_B*1 -> 1921.3317
A110: 每 GW IT 資本支出 | B110: US$B | D110: =itpg_gb*(1-vr26)+itpg_vr*vr26 -> 33.414032 | E110: =itpg_vr -> 37.586352 | F110: =itpg_vr -> 37.586352 | G110: =itpg_vr -> 37.586352
A111: 部署 GW（IT 電力） | B111: GW | D111: =D109/D110 -> 23.399538 | E111: =E109/E110 -> 41.646766 | F111: =F109/F110 -> 42.233711 | G111: =G109/G110 -> 51.117803
A112: 每 GW PCB：加速器卡／運算板 | B112: US$M/GW | D112: =vg_cmp26 -> 280 | E112: =(vg_cmp26+(vg_cmp27-vg_cmp26)*pgwf) -> 420 | F112: =(vg_cmp26+(vg_cmp28-vg_cmp26)*pgwf) -> 462 | G112: =(vg_cmp26+(vg_cmp29-vg_cmp26)*pgwf) -> 504
A113: 每 GW PCB：交換器板 | B113: US$M/GW | D113: =vg_sw26 -> 120 | E113: =(vg_sw26+(vg_sw27-vg_sw26)*pgwf) -> 162 | F113: =(vg_sw26+(vg_sw28-vg_sw26)*pgwf) -> 180 | G113: =(vg_sw26+(vg_sw29-vg_sw26)*pgwf) -> 198
A114: 每 GW PCB：中板／背板／其他 × 金像電參與係數 | B114: US$M/GW | D114: =vg_mid26*w_mid -> 25 | E114: =(vg_mid26+(vg_mid27-vg_mid26)*pgwf)*w_mid -> 50 | F114: =(vg_mid26+(vg_mid28-vg_mid26)*pgwf)*w_mid -> 75 | G114: =(vg_mid26+(vg_mid29-vg_mid26)*pgwf)*w_mid -> 87.5
A115: 每 GW 金像電可參與 AI 高速 PCB 金額（三項合計） | B115: US$M/GW | D115: =D112+D113+D114 -> 425 | E115: =E112+E113+E114 -> 632 | F115: =F112+F113+F114 -> 717 | G115: =G112+G113+G114 -> 789.5
A116: 可參與 AI 高速 PCB 市場（美元；不含價格指數） | B116: US$B | D116: =D111*D115/1000 -> 9.9448037 | E116: =E111*E115/1000 -> 26.320756 | F116: =F111*F115/1000 -> 30.28157 | G116: =G111*G115/1000 -> 40.357505
A117: 可參與 AI 高速 PCB 市場（新台幣） | B117: NT$B | D117: =D116*fx -> 318.23372 | E117: =E116*fx -> 842.26419 | F117: =F116*fx -> 969.01025 | G117: =G116*fx -> 1291.4402
...

Sheet Val
A1: Val — P/E 估值（新台幣）。結論用「現價 ÷ FY2027、FY2028 EPS（模型）」；目標價＝DCF 與 Comparable 加權（第 0 節）；十年 P/E 規則值（第 3 節，年底落後 P/E）只作參考。本版未做先驗，無 Andy 合理 P/E 對照
A2: 循環位置：金像電不是設備股，不套設備市場見頂年；以本模型營收最高的會計年度為見頂年（比照勝宏、台光電；FY(t)＝CY(t)）。營收到 FY2029 仍在增加時，見頂年未知，判為中段
A4: 0. 目標價
A5: 0.1 DCF（股東權益現金流，FY2027–FY2032 明確期＋FY2032 後永續）
A6: 項目 | B6: A（順利） | C6: B（平平） | D6: C（不如預期） | E6: 說明
A7: 情境 EPS（FY2027–FY2032） | E7: PL 頁各情境；FY2030 起為收斂法
A8: FY2027 | B8: =PL!E14 -> 66.124283 | C8: =PL!E27 -> 60.151023 | D8: =PL!E40 -> 51.668812
A9: FY2028 | B9: =PL!F14 -> 90.044822 | C9: =PL!F27 -> 76.561569 | D9: =PL!F40 -> 45.308254
A10: FY2029 | B10: =PL!G14 -> 106.98054 | C10: =PL!G27 -> 87.717419 | D10: =PL!G40 -> 45.542384
A11: FY2030 | B11: =PL!H14 -> 121.22982 | C11: =PL!H27 -> 91.784693 | D11: =PL!H40 -> 44.754743
A12: FY2031 | B12: =PL!I14 -> 132.30417 | C12: =PL!I27 -> 91.838882 | D12: =PL!I40 -> 42.862886
A13: FY2032 | B13: =PL!J14 -> 138.85388 | C13: =PL!J27 -> 87.664086 | D13: =PL!J40 -> 39.957481
A14: 股東現金流＝EPS ×（1 − tp_g ÷ tp_roe）
A15: 再投資率（tp_g ÷ tp_roe，上限 0.8） | B15: =MIN(tp_g/tp_roe,0.8) -> 0.13766204 | E15: ROE 為近三年平均（In 頁 tp_roe）
A16: FY2027 | B16: =B8*(1-$B$15) -> 57.02148 | C16: =C8*(1-$B$15) -> 51.870511 | D16: =D8*(1-$B$15) -> 44.555978
A17: FY2028 | B17: =B9*(1-$B$15) -> 77.649068 | C17: =C9*(1-$B$15) -> 66.021947 | D17: =D9*(1-$B$15) -> 39.071027
A18: FY2029 | B18: =B10*(1-$B$15) -> 92.253382 | C18: =C10*(1-$B$15) -> 75.64206 | D18: =D10*(1-$B$15) -> 39.272926
A19: FY2030 | B19: =B11*(1-$B$15) -> 104.54108 | C19: =C11*(1-$B$15) -> 79.149425 | D19: =D11*(1-$B$15) -> 38.593713
A20: FY2031 | B20: =B12*(1-$B$15) -> 114.0909 | C20: =C12*(1-$B$15) -> 79.196154 | D20: =D12*(1-$B$15) -> 36.962294
A21: FY2032 | B21: =B13*(1-$B$15) -> 119.73897 | C21: =C13*(1-$B$15) -> 75.596069 | D21: =D13*(1-$B$15) -> 34.456853
A22: DCF 情境每股價值（折現率 tp_r） | B22: =MAX(0,SUMPRODUCT(B16:B21,1/(1+tp_r)^{1;2;3;4;5;6})+B21*(1+tp_g)/(tp_r-tp_g)/(1+tp_r)^6) -> 1566.7076 | C22: =MAX(0,SUMPRODUCT(C16:C21,1/(1+tp_r)^{1;2;3;4;5;6})+C21*(1+tp_g)/(tp_r-tp_g)/(1+tp_r)^6) -> 1044.1045 | D22: =MAX(0,SUMPRODUCT(D16:D21,1/(1+tp_r)^{1;2;3;4;5;6})+D21*(1+tp_g)/(tp_r-tp_g)/(1+tp_r)^6) -> 508.19582 | E22: Σ 明確期現金流 ÷ (1＋r)^t ＋ 永續價值 ÷ (1＋r)^6；永續價值＝FY2032 現金流 ×(1＋g)÷(r−g)；基準日 2026 年底；負值取 0（Andy 12:22）
A23: DCF 情境價值推到 12 個月後（×(1＋tp_r)） | B23: =B22*(1+tp_r) -> 1723.3783 | C23: =C22*(1+tp_r) -> 1148.5149 | D23: =D22*(1+tp_r) -> 559.0154
A24: DCF 目標價（情境加權） | B24: =tp_wA*B23+tp_wB*C23+tp_wC*D23 -> 1203.0741 | E24: Σ 權重 × 情境價值 ×(1＋r)；權重見 In 頁
A26: 0.2 Comparable（市場主流同業前瞻 P/E；非 A 股公司，同業不放 A 股）
A27: 同業與前瞻 P/E | B27: 代號 | C27: 前瞻 12 月 P/E | D27: 日期 | E27: 來源 | F27: 標記
A28: 健鼎（Tripod Technology） | B28: 3044.TW | C28: 13.96 | D28: 2026-09-10 | E28: stockanalysis.com forward PE（分析師共識；價格日期如左，臺股頁面為快取日期） | F28: Interested-party
A29: 華通（Compeq） | B29: 2313.TW | C29: 20.76 | D29: 2026-08-20 | E29: stockanalysis.com forward PE（分析師共識；價格日期如左，臺股頁面為快取日期） | F29: Interested-party
A30: 臻鼎-KY（Zhen Ding） | B30: 4958.TW | C30: 25.13 | D30: 2026-08-31 | E30: stockanalysis.com forward PE（分析師共識；價格日期如左，臺股頁面為快取日期） | F30: Interested-party
A31: 博智（Allied Circuit） | B31: 8155.TWO | C31: 18.49 | D31: 2026-08-14 | E31: stockanalysis.com forward PE（分析師共識；價格日期如左，臺股頁面為快取日期） | F31: Interested-party
A32: TTM Technologies | B32: TTMI | C32: 10.31 | D32: 2026-10-23 | E32: stockanalysis.com forward PE（分析師共識；價格日期如左，臺股頁面為快取日期） | F32: Interested-party
A33: 並列參考（A 股，不進目標價）：勝宏科技 300476.SZ 前瞻 P/E 14.8x（10-23）、沪电股份 002463.SZ 20.7x（10-22）；stockanalysis，Interested-party
A34: 同業前瞻 P/E 中位數 | B34: =MEDIAN(C28:C32) -> 18.49 | E34: 臺美伺服器、網通 PCB 同業：健鼎、華通、臻鼎-KY、博智、TTM（臺股媒體與券商常用比較組）；定穎投控、瀚宇博前瞻 P/E 未找到
A35: 12 個月後的前瞻 EPS（情境加權） | B35: =tp_wA*(2/12*B8+10/12*B9)+tp_wB*(2/12*C8+10/12*C9)+tp_wC*(2/12*D8+10/12*D9) -> 72.004328 | E35: 約 2027-10 時的未來 12 月 EPS ≈ 2／12 × FY2027＋10／12 × FY2028（會計年度＝日曆年）
A36: Comparable 目標價 | B36: =B34*B35 -> 1331.36 | E36: 同業中位數 × 前瞻 EPS
A38: 0.3 結論
A39: 項目 | B39: 數值 | E39: 說明
A40: 目標價（DCF 與 Comparable 加權） | B40: =tp_w_dcf*B24+(1-tp_w_dcf)*B36 -> 1267.217 | E40: tp_w_dcf × DCF＋（1 − tp_w_dcf）× Comparable；tp_w_dcf 見 In 頁
A41: Comparable 目標價（市場主流同業法） | B41: =B36 -> 1331.36
A42: 市場共識目標價 | B42: =cons_tp -> 1554 | E42: stockanalysis（S&P Global）：9 位分析師平均 1,554、中位數 1,610（頁面時間 2026-09-04）
A43: 上檔空間：加權目標價 | B43: =B40/px-1 -> 0.13651752 | E43: 現價＝In 頁 px（2026-10-22 收盤）
A44: 上檔空間：Comparable 目標價 | B44: =B41/px-1 -> 0.19404486
A45: 與市場共識目標價的差距：EPS 因素 | B45: =B35/cons_feps-1 -> 0.26378897 | E45: 本模型前瞻 EPS ÷ 共識前瞻 EPS − 1；共識前瞻 EPS＝現價 ÷ 前瞻 P/E（In 頁 cons_feps；期間為現在起算 12 個月，與本模型不同）
A46: 與市場共識目標價的差距：倍數因素 | B46: =(cons_tp/cons_feps)/B34-1 -> 0.47512921 | E46: ="共識目標價隱含 "&TEXT(cons_tp/cons_feps,"0.0")&"x，同業中位數 "&TEXT(B34,"0.0")&"x" -> 共識目標價隱含 27.3x，同業中位數 18.5x
A47: 價格帶（DCF 不如預期～順利） | B47: =TEXT(D23,"0.00")&"～"&TEXT(B23,"0.00") -> 559.02～1723.38 | E47: C 情境價值～A 情境價值（推到 12 個月後）
A48: 歷史倍數檢查：現價隱含 P/E 的十年分位（A／B／C） | B48: =IF(px/B9<MIN($B$90:$B$99),0,IF(px/B9>MAX($B$90:$B$99),1,PERCENTRANK($B$90:$B$99,px/B9))) -> 0.111 | C48: =IF(px/C9<MIN($B$90:$B$99),0,IF(px/C9>MAX($B$90:$B$99),1,PERCENTRANK($B$90:$B$99,px/C9))) -> 0.272 | D48: =IF(px/D9<MIN($B$90:$B$99),0,IF(px/D9>MAX($B$90:$B$99),1,PERCENTRANK($B$90:$B$99,px/D9))) -> 0.425 | E48: 現價 ÷ 各情境 FY2028 EPS 在 2016–2025 年底 P/E（第 6 節自算）的分位；只作檢查，不進目標價
A49: 目標價方法 | B49: DCF：股東現金流＝歸母 EPS ×（1 − g／ROE），r＝10%、g＝4%、ROE 為近三年平均約 29%（再投資率約 14%），FY2027–32 明確期＋永續；金像電 2026 年資本支出約 190 億元（約營收的 18%，折舊約 14 億），本模型未建資本支出與折舊，未改用淨利＋折舊－資本支出，擴產期現金流偏高估。Comparable：健鼎、華通、臻鼎-KY、博智、TTM 前瞻 P/E 中位數（臺美同業，不放 A 股；臺股同業價格多為 8–9 月快取，TTM 倍數低），方向不確定。情境對應：A＝順利（顆數基準、份額價格高值）、B＝平平（顆數 ×0.8／0.85、基準）、C＝不如預期（顆數 ×0.6、低值）
A51: 1. 價格與市場隱含倍數
A52: 項目 | B52: A | C52: B | D52: C | E52: 說明
A53: 現價（2026-10-22 收盤） | B53: =px -> 1115
A54: 現價 ÷ FY2026 EPS（錨點） | B54: =px/PL!D14 -> 29.037543 | C54: =px/PL!D27 -> 29.037543 | D54: =px/PL!D40 -> 29.037543 | E54: FY2026 三情境相同（錨點）
A55: 現價 ÷ FY2027 EPS（模型） | B55: =px/PL!E14 -> 16.862187 | C55: =px/PL!E27 -> 18.536675 | D55: =px/PL!E40 -> 21.579749 | E55: FY2027 三情境差異只來自份額、價格、AI 毛利率改善（顆數係數從 CY2028 開始）
A56: 現價 ÷ FY2028 EPS（模型） | B56: =px/PL!F14 -> 12.382722 | C56: =px/PL!F27 -> 14.563442 | D56: =px/PL!F40 -> 24.609203
A57: 現價 ÷ FY2029 EPS（模型） | B57: =px/PL!G14 -> 10.422456 | C57: =px/PL!G27 -> 12.711272 | D57: =px/PL!G40 -> 24.482689
A58: 未來 12 月 EPS（模型 B）≈ 0.2 × FY2026＋0.8 × FY2027 | B58: =0.2*PL!D27+0.8*PL!E27 -> 55.800532
A59: 現價 ÷ 未來 12 月 EPS（模型 B） | B59: =px/B58 -> 19.981888
A60: 近 12 月 P/E（stockanalysis，10-22） | B60: =pe_ttm -> 39.79
A61: 前瞻 P/E（stockanalysis，10-22） | B61: =fpe -> 19.57
A63: 2. 循環位置（本模型營收最高年；FY(t)＝CY(t)）
A64: 情境 | B64: 營收最高年（FY2026–FY2029） | C64: FY2027 判定 | D64: 規則倍數（P/E） | E64: 見頂年是否未知 | F64: 說明
A65: A | B65: =INDEX({2026,2027,2028,2029},MATCH(MAX(PL!D83:G83),PL!D83:G83,0)) -> 2029 | C65: =IF(B65=2029,"中段",IF(2027<B65,"中段",IF(2027=B65,"見頂","谷底"))) -> 中段 | D65: =IF(C65="見頂",pe_peak,IF(C65="谷底",pe_trough,pe_mid)) -> 30.07 | E65: =IF(B65=2029,"是：營收到觀測期末仍在增加","否") -> 是：營收到觀測期末仍在增加 | F65: tools/cycle_position.py excel_rule；營收最高年取代設備市場見頂年
A66: B | B66: =INDEX({2026,2027,2028,2029},MATCH(MAX(PL!D129:G129),PL!D129:G129,0)) -> 2029 | C66: =IF(B66=2029,"中段",IF(2027<B66,"中段",IF(2027=B66,"見頂","谷底"))) -> 中段 | D66: =IF(C66="見頂",pe_peak,IF(C66="谷底",pe_trough,pe_mid)) -> 30.07 | E66: =IF(B66=2029,"是：營收到觀測期末仍在增加","否") -> 是：營收到觀測期末仍在增加 | F66: 同上
A67: C | B67: =INDEX({2026,2027,2028,2029},MATCH(MAX(PL!D175:G175),PL!D175:G175,0)) -> 2029 | C67: =IF(B67=2029,"中段",IF(2027<B67,"中段",IF(2027=B67,"見頂","谷底"))) -> 中段 | D67: =IF(C67="見頂",pe_peak,IF(C67="谷底",pe_trough,pe_mid)) -> 30.07 | E67: =IF(B67=2029,"是：營收到觀測期末仍在增加","否") -> 是：營收到觀測期末仍在增加 | F67: 同上
A69: 3. 規則值隱含股價（新台幣；約 FY2027 年底，未折現）＝ FY2027 EPS × 規則倍數（參考，不是目標價）
A70: 情境 | B70: FY2027 EPS | C70: （同左） | D70: 規則倍數 | E70: 隱含股價 | F70: 相對現價 | G70: 現價 ÷ FY2027 EPS
A71: A | B71: =PL!E14 -> 66.124283 | C71: =B71 -> 66.124283 | D71: =D65 -> 30.07 | E71: =C71*D71 -> 1988.3572 | F71: =E71/px-1 -> 0.78328 | G71: =px/C71 -> 16.862187
A72: B | B72: =PL!E27 -> 60.151023 | C72: =B72 -> 60.151023 | D72: =D66 -> 30.07 | E72: =C72*D72 -> 1808.7413 | F72: =E72/px-1 -> 0.62218948 | G72: =px/C72 -> 18.536675
A73: C | B73: =PL!E40 -> 51.668812 | C73: =B73 -> 51.668812 | D73: =D67 -> 30.07 | E73: =C73*D73 -> 1553.6812 | F73: =E73/px-1 -> 0.39343605 | G73: =px/C73 -> 21.579749
A75: 4. What must be true：FY2027 年底價 ＝ 現價 ×（1＋報酬）所需的倍數（FY2028 EPS；約 2027 年底的價格看下一年 EPS）
A76: FY2027 年底價 ÷ 現價 | B76: 所需倍數（÷ FY2028 EPS，A） | C76: 所需倍數（÷ FY2028 EPS，B） | D76: 所需倍數（÷ FY2028 EPS，C） | E76: 對照：十年中位數
A77: 1 | B77: =px*A77/PL!F14 -> 12.382722 | C77: =px*A77/PL!F27 -> 14.563442 | D77: =px*A77/PL!F40 -> 24.609203 | E77: =pe_mid -> 30.07
A78: 1.1 | B78: =px*A78/PL!F14 -> 13.620994 | C78: =px*A78/PL!F27 -> 16.019787 | D78: =px*A78/PL!F40 -> 27.070123 | E78: =pe_mid -> 30.07
A79: 1.21 | B79: =px*A79/PL!F14 -> 14.983094 | C79: =px*A79/PL!F27 -> 17.621765 | D79: =px*A79/PL!F40 -> 29.777135 | E79: =pe_mid -> 30.07
A80: 1.5 | B80: =px*A80/PL!F14 -> 18.574083 | C80: =px*A80/PL!F27 -> 21.845164 | D80: =px*A80/PL!F40 -> 36.913804 | E80: =pe_mid -> 30.07
A81: 2 | B81: =px*A81/PL!F14 -> 24.765444 | C81: =px*A81/PL!F27 -> 29.126885 | D81: =px*A81/PL!F40 -> 49.218405 | E81: =pe_mid -> 30.07
A82: 讀法：1.00＝價格不變、1.21＝一年約 21%。所需倍數低於歷史中位數時，現價相對便宜；倍數是否合理，另看前瞻 P/E 歷史（Bloomberg）。本版未做先驗，無 Andy 合理 P/E 對照。
A85: 6. 十年倍數與規則值（2016–2025 年底；見頂年 25 分位、中段中位數、谷底 75 分位）
A86: 規則（Andy 2026-10-13）：合理倍數＝2016–2025 年底 P/E 依循環位置取分位。採用自算（9 年；2017 年虧損留空）；MarketScreener 只有 2021–2025，與自算同量級，只作核對；HiStock 12 月 P/E 2021–2025：16.7、9.5、31.6、21.6、43.2。2016–2019 年 EPS 低於 0.5 元，P/E 被低獲利放大（2019 年 69x），十年分布偏高。
A88: P/E：十年歷史倍數
A89: 年底 | B89: 自算（digrin 12 月未調整收盤 ÷ 年度 EPS） | C89: MarketScreener（年度 P/E） | D89: 標記／說明
A90: 2016 | B90: =10.4/0.26 -> 40 | D90: 自算（digrin 12 月未調整收盤 ÷ 年度 EPS）：Derived（EPS：2016–2020 聚財網、2021–2025 stockanalysis／公司；2017 年 EPS −0.50 為虧損，P/E 無意義，留空；9 年）；MarketScreener（年度 P/E）：Interested-party（資料商；只有 2021–2025，只作核對，不採用）
A91: 2017
A92: 2018 | B92: =13.1/0.42 -> 31.190476
A93: 2019 | B93: =16.65/0.24 -> 69.375
A94: 2020 | B94: =50.5/3.82 -> 13.219895
A95: 2021 | B95: =76/5.98 -> 12.70903 | C95: 14.1
A96: 2022 | B96: =86.8/8.78 -> 9.8861048 | C96: 9.89
A97: 2023 | B97: =218/7.25 -> 30.068966 | C97: 30.1
A98: 2024 | B98: =241.5/11.54 -> 20.92721 | C98: 20.9
A99: 2025 | B99: =687/19.47 -> 35.285054 | C99: 35.3
A100: 25 分位（各來源） | B100: =PERCENTILE(B90:B99,0.25) -> 13.219895 | C100: =PERCENTILE(C90:C99,0.25) -> 14.1
A101: 中位數（各來源） | B101: =MEDIAN(B90:B99) -> 30.068966 | C101: =MEDIAN(C90:C99) -> 20.9
A102: 75 分位（各來源） | B102: =PERCENTILE(B90:B99,0.75) -> 35.285054 | C102: =PERCENTILE(C90:C99,0.75) -> 30.1
A103: 最小（各來源） | B103: =MIN(B90:B99) -> 9.8861048 | C103: =MIN(C90:C99) -> 9.89
A104: 最大（各來源） | B104: =MAX(B90:B99) -> 69.375 | C104: =MAX(C90:C99) -> 35.3
A105: 採用 25 分位（P/E） | B105: =ROUND(AVERAGE(B100),2) -> 13.22
A106: 採用 中位數（P/E） | B106: =ROUND(AVERAGE(B101),2) -> 30.07
A107: 採用 75 分位（P/E） | B107: =ROUND(AVERAGE(B102),2) -> 35.29
A108: 採用 最小（P/E） | B108: =ROUND(MIN(B103),2) -> 9.89
A109: 採用 最大（P/E） | B109: =ROUND(MAX(B104),2) -> 69.38
A111: P/E：規則值
...

Sheet Recon
A1: Recon — 本模型 vs 共識、券商估計與勝宏模型的每 GW PCB 金額、台光電模型的每 GW CCL 金額。只作事後對照，不為對上數字而調參數。共識取自 MarketScreener 與 FactSet（理財周刊轉引）；券商多為單一來源
A3: 項目 | B3: 對照值 | C3: 模型 A | D3: 差距 A | E3: 模型 B | F3: 差距 B | G3: 模型 C | H3: 差距 C | I3: 對照來源 | J3: 說明
A4: A. 共識與券商估計（校準未使用）
A5: FY2026 營收 vs 共識（MarketScreener） | B5: =cons_rev26 -> 106.371 | C5: =PL!D83 -> 105.40752 | D5: =C5/B5-1 -> -0.0090577319 | E5: =PL!D129 -> 105.40752 | F5: =E5/B5-1 -> -0.0090577319 | G5: =PL!D175 -> 105.40752 | H5: =G5/B5-1 -> -0.0090577319 | I5: MarketScreener（2026-10-25 擷取） | J5: stockanalysis 8 家 1,063 億；共識隱含 4Q26 約 327 億
A6: FY2026 EPS vs 共識（MarketScreener） | B6: =cons_eps26 -> 41.22 | C6: =PL!D101 -> 38.398566 | D6: =C6/B6-1 -> -0.068448185 | E6: =PL!D147 -> 38.398566 | F6: =E6/B6-1 -> -0.068448185 | G6: =PL!D193 -> 38.398566 | H6: =G6/B6-1 -> -0.068448185 | I6: MarketScreener | J6: 3Q26 財報（11 月上旬）前
A7: FY2026 EPS vs FactSet 中位數（2026-09） | B7: =fs_eps26 -> 41.57 | C7: =PL!D101 -> 38.398566 | D7: =C7/B7-1 -> -0.076291416 | E7: =PL!D147 -> 38.398566 | F7: =E7/B7-1 -> -0.076291416 | G7: =PL!D193 -> 38.398566 | H7: =G7/B7-1 -> -0.076291416 | I7: FactSet（理財周刊 2026-10-14 轉引）
A8: FY2027 營收 vs 共識（MarketScreener） | B8: =cons_rev27 -> 159.967 | C8: =PL!E83 -> 157.42613 | D8: =C8/B8-1 -> -0.015883707 | E8: =PL!E129 -> 152.8409 | F8: =E8/B8-1 -> -0.044547288 | G8: =PL!E175 -> 146.72727 | H8: =G8/B8-1 -> -0.082765396 | I8: MarketScreener
A9: FY2027 EPS vs 共識（MarketScreener） | B9: =cons_eps27 -> 62.8 | C9: =PL!E101 -> 66.124283 | D9: =C9/B9-1 -> 0.052934447 | E9: =PL!E147 -> 60.151023 | F9: =E9/B9-1 -> -0.042181156 | G9: =PL!E193 -> 51.668812 | H9: =G9/B9-1 -> -0.17724821 | I9: MarketScreener
A10: FY2027 EPS vs FactSet 中位數 | B10: =fs_eps27 -> 69.1 | C10: =PL!E101 -> 66.124283 | D10: =C10/B10-1 -> -0.043063918 | E10: =PL!E147 -> 60.151023 | F10: =E10/B10-1 -> -0.12950762 | G10: =PL!E193 -> 51.668812 | H10: =G10/B10-1 -> -0.25226031 | I10: FactSet（理財周刊轉引）
A11: FY2027 EPS vs 外資（2026-05-13） | B11: =fb_eps27 -> 65.39 | C11: =PL!E101 -> 66.124283 | D11: =C11/B11-1 -> 0.01122929 | E11: =PL!E147 -> 60.151023 | F11: =E11/B11-1 -> -0.080118926 | G11: =PL!E193 -> 51.668812 | H11: =G11/B11-1 -> -0.20983618 | I11: technews 2026-05-13（外資，名稱未載明） | J11: 目標價 1,310
A12: FY2028 營收 vs 共識（MarketScreener） | B12: =cons_rev28 -> 214.339 | C12: =PL!F83 -> 204.27977 | D12: =C12/B12-1 -> -0.046931386 | E12: =PL!F129 -> 194.26606 | F12: =E12/B12-1 -> -0.093650435 | G12: =PL!F175 -> 141.18508 | H12: =G12/B12-1 -> -0.34130009 | I12: MarketScreener
A13: FY2028 EPS vs 共識（MarketScreener） | B13: =cons_eps28 -> 95.35 | C13: =PL!F101 -> 90.044822 | D13: =C13/B13-1 -> -0.055638998 | E13: =PL!F147 -> 76.561569 | F13: =E13/B13-1 -> -0.19704699 | G13: =PL!F193 -> 45.308254 | H13: =G13/B13-1 -> -0.52482167 | I13: MarketScreener
A14: FY2028 EPS vs FactSet 中位數 | B14: =fs_eps28 -> 95.07 | C14: =PL!F101 -> 90.044822 | D14: =C14/B14-1 -> -0.052857668 | E14: =PL!F147 -> 76.561569 | F14: =E14/B14-1 -> -0.19468214 | G14: =PL!F193 -> 45.308254 | H14: =G14/B14-1 -> -0.52342218 | I14: FactSet（理財周刊轉引）
A15: B. 每 GW PCB 金額 vs 勝宏模型、台光電每 GW CCL 金額（機制檢查）
A16: CY2026 每 GW 可參與 PCB 金額（本模型）vs 勝宏模型每 GW PCB 金額 | B16: =vg_pgw26 -> 450 | C16: =PL!D69 -> 425 | D16: =C16/B16-1 -> -0.055555556 | E16: =PL!D115 -> 425 | F16: =E16/B16-1 -> -0.055555556 | G16: =PL!D161 -> 425 | H16: =G16/B16-1 -> -0.055555556 | I16: victory_giant/dist Units 頁（唯讀） | J16: 差距只來自中板／背板參與係數 w_mid（與成長倍率 pgwf）
A17: CY2027 每 GW 可參與 PCB 金額（本模型）vs 勝宏模型每 GW PCB 金額 | B17: =vg_pgw27 -> 682 | C17: =PL!E69 -> 632 | D17: =C17/B17-1 -> -0.073313783 | E17: =PL!E115 -> 632 | F17: =E17/B17-1 -> -0.073313783 | G17: =PL!E161 -> 632 | H17: =G17/B17-1 -> -0.073313783 | I17: victory_giant/dist Units 頁（唯讀） | J17: —
A18: CY2028 每 GW 可參與 PCB 金額（本模型）vs 勝宏模型每 GW PCB 金額 | B18: =vg_pgw28 -> 792 | C18: =PL!F69 -> 717 | D18: =C18/B18-1 -> -0.09469697 | E18: =PL!F115 -> 717 | F18: =E18/B18-1 -> -0.09469697 | G18: =PL!F161 -> 717 | H18: =G18/B18-1 -> -0.09469697 | I18: victory_giant/dist Units 頁（唯讀） | J18: —
A19: CY2026 每 GW 可參與 PCB 金額（本模型）vs 台光電模型每 GW CCL 金額 | B19: =emc_ccl26 -> 350 | C19: =PL!D69 -> 425 | D19: =C19/B19-1 -> 0.21428571 | E19: =PL!D115 -> 425 | F19: =E19/B19-1 -> 0.21428571 | G19: =PL!D161 -> 425 | H19: =G19/B19-1 -> 0.21428571 | I19: emc/dist Units 頁（唯讀） | J19: 差距＝PCB ÷ CCL − 1；勝宏模型已註明 PCB ÷ CCL 只有約 1.3 倍，低於 Morgan Stanley 每架口徑 5.2 倍（範圍不同）
A20: CY2027 每 GW 可參與 PCB 金額（本模型）vs 台光電模型每 GW CCL 金額 | B20: =emc_ccl27 -> 527.5 | C20: =PL!E69 -> 632 | D20: =C20/B20-1 -> 0.19810427 | E20: =PL!E115 -> 632 | F20: =E20/B20-1 -> 0.19810427 | G20: =PL!E161 -> 632 | H20: =G20/B20-1 -> 0.19810427 | I20: emc/dist Units 頁（唯讀） | J20: —
A21: CY2027 每 GW 金額指數（÷ CY2026）：本模型 vs 台光電 CCL | B21: =emc_ccl27/emc_ccl26 -> 1.5071429 | C21: =PL!E69/PL!D69 -> 1.4870588 | D21: =C21/B21-1 -> -0.013325899 | E21: =PL!E115/PL!D115 -> 1.4870588 | F21: =E21/B21-1 -> -0.013325899 | G21: =PL!E161/PL!D161 -> 1.4870588 | H21: =G21/B21-1 -> -0.013325899 | I21: emc/dist | J21: 世代升級幅度的對照
A22: CY2026 每 GW 金像電 AI 營收 vs 每 GW 勝宏 AI 營收（US$M） | B22: =vg_pge26 -> 111.38931 | C22: =PL!D87 -> 73.45786 | D22: =C22/B22-1 -> -0.34053041 | E22: =PL!D133 -> 73.45786 | F22: =E22/B22-1 -> -0.34053041 | G22: =PL!D179 -> 73.45786 | H22: =G22/B22-1 -> -0.34053041 | I22: victory_giant/dist | J22: 同為 AI 高速 PCB 廠；勝宏較偏 NVIDIA GPU 加速卡與 HDI
A23: CY2026 每 GW 金像電 AI 營收 vs 每 GW 台光電 AI 營收（US$M） | B23: =emc_pg26 -> 160.75716 | C23: =PL!D87 -> 73.45786 | D23: =C23/B23-1 -> -0.54305076 | E23: =PL!D133 -> 73.45786 | F23: =E23/B23-1 -> -0.54305076 | G23: =PL!D179 -> 73.45786 | H23: =G23/B23-1 -> -0.54305076 | I23: emc/dist | J23: 下游 PCB 廠 ÷ 上游 CCL 廠
A24: CY2027 每 GW 金像電 AI 營收 vs 每 GW 勝宏 AI 營收（US$M） | B24: =vg_pge27 -> 132.93349 | C24: =PL!E87 -> 78.414405 | D24: =C24/B24-1 -> -0.41012303 | E24: =PL!E133 -> 74.973841 | F24: =E24/B24-1 -> -0.43600488 | G24: =PL!E179 -> 70.386423 | H24: =G24/B24-1 -> -0.470514 | I24: victory_giant/dist | J24: —
A25: CY2027 每 GW 金像電 AI 營收 vs 每 GW 台光電 AI 營收（US$M） | B25: =emc_pg27 -> 180.40841 | C25: =PL!E87 -> 78.414405 | D25: =C25/B25-1 -> -0.56535062 | E25: =PL!E133 -> 74.973841 | F25: =E25/B25-1 -> -0.58442159 | G25: =PL!E179 -> 70.386423 | H25: =G25/B25-1 -> -0.60984955 | I25: emc/dist | J25: 下游 PCB 廠 ÷ 上游 CCL 廠
A26: FY2026 金像電有效份額 vs 勝宏有效份額（勝宏模型） | B26: =vg_sh26 -> 0.24753179 | C26: =PL!D73 -> 0.17284202 | D26: =C26-B26 -> -0.074689769 | E26: =PL!D119 -> 0.17284202 | F26: =E26-B26 -> -0.074689769 | G26: =PL!D165 -> 0.17284202 | H26: =G26-B26 -> -0.074689769 | I26: victory_giant/dist | J26: 分母不同：本模型為可參與市場（中板 × w_mid）
A27: C. 產能與校準
A28: FY2027 需求面 ÷ 產能上限 | C28: =PL!E86 -> 1.3648637 | E28: =PL!E132 -> 1.2987503 | G28: =PL!E178 -> 1.1703053 | I28: — | J28: 大於 100%＝產能受限
A29: FY2028 需求面 ÷ 產能上限 | C29: =PL!F86 -> 1.3958261 | E29: =PL!F132 -> 1.0750684 | G29: =PL!F178 -> 0.76625934 | I29: —
A30: 其他營收毛利率（Derived） | C30: =PL!D89 -> 0.29665521 | E30: =PL!D135 -> 0.29665521 | G30: =PL!D181 -> 0.29665521 | I30: FY2026 錨點 | J30: AI 相關毛利率＝此值＋d_ai
A31: FY2027 毛利率 vs FY2026（百分點） | B31: =a26_gp/a26_rev -> 0.34883759 | C31: =PL!E92 -> 0.387979 | D31: =C31-B31 -> 0.039141411 | E31: =PL!E138 -> 0.368566 | F31: =E31-B31 -> 0.019728411 | G31: =PL!E184 -> 0.33812105 | H31: =G31-B31 -> -0.010716543 | I31: 錨點
A32: FY2027 營業利益率 vs 2Q26 實績 26.43%（百分點） | B32: =0.2643 -> 0.2643 | C32: =PL!E96 -> 0.31817926 | D32: =C32-B32 -> 0.053879258 | E32: =PL!E142 -> 0.29812001 | F32: =E32-B32 -> 0.033820014 | G32: =PL!E188 -> 0.26675057 | H32: =G32-B32 -> 0.0024505716 | I32: 理財周刊 2026-10-14
A33: 4Q26 EPS（模型） | C33: =Q!E15 -> 11.552539 | E33: =Q!E15 -> 11.552539 | G33: =Q!E15 -> 11.552539 | I33: — | J33: 3Q26 財報 11 月上旬公布
A34: D. 預留
A35: R4 產業部署路徑（markets/deploy_path/，尚未建立）：上線後以部署路徑取代「AI IT 資本支出 ÷ 每 GW IT 資本支出」 | J35: 預留列：本版無數值

Sheet Sens
A1: Sens — 一次動一個輸入（情境 B＝基準輸入；有效份額、其他營收毛利率在每個案例內依 FY2026 錨點重算，FY2026 恆等於錨點）：對 FY2027、FY2028 的營收、AI 相關營收、毛利率與 EPS 的影響。每個案例是一個完整推導區塊（本頁下方）
A3: 案例 | B3: 設定 | C3: FY2027 營收 | D3: FY2027 AI 相關 | E3: FY2027 毛利率 | F3: FY2027 EPS | G3: FY2027 EPS 相對基準 | H3: FY2028 營收 | I3: FY2028 AI 相關 | J3: FY2028 毛利率 | K3: FY2028 EPS | L3: FY2028 EPS 相對基準
A4: 基準（情境 B） | B4: PL 區塊 B | C4: =PL!E129 -> 152.8409 | D4: =PL!E127 -> 99.917376 | E4: =PL!E138 -> 0.368566 | F4: =PL!E147 -> 60.151023 | G4: =F4/F$4-1 -> 0 | H4: =PL!F129 -> 194.26606 | I4: =PL!F127 -> 139.75483 | J4: =PL!F138 -> 0.36596201 | K4: =PL!F147 -> 76.561569 | L4: =K4/K$4-1 -> 0
A5: 每 GW 金額成長 低 | B5: 勝宏模型每 GW 金額增量 ×0.7 | C5: =E73 -> 152.8409 | D5: =E71 -> 99.917376 | E5: =E82 -> 0.368566 | F5: =E91 -> 60.151023 | G5: =F5/F$4-1 -> 0 | H5: =F73 -> 189.99293 | I5: =F71 -> 135.4817 | J5: =F82 -> 0.36535401 | K5: =F91 -> 74.602696 | L5: =K5/K$4-1 -> -0.025585589
A6: 每 GW 金額成長 高 | B6: 增量 ×1.3 | C6: =E119 -> 152.8409 | D6: =E117 -> 99.917376 | E6: =E128 -> 0.368566 | F6: =E137 -> 60.151023 | G6: =F6/F$4-1 -> 0 | H6: =F119 -> 194.26606 | I6: =F117 -> 139.75483 | J6: =F128 -> 0.36596201 | K6: =F137 -> 76.561569 | L6: =K6/K$4-1 -> 0
A7: 中板／背板不參與 | B7: 參與係數 0 | C7: =E165 -> 152.8409 | D7: =E163 -> 99.917376 | E7: =E174 -> 0.368566 | F7: =E183 -> 60.151023 | G7: =F7/F$4-1 -> 0 | H7: =F165 -> 194.26606 | I7: =F163 -> 139.75483 | J7: =F174 -> 0.36596201 | K7: =F183 -> 76.561569 | L7: =K7/K$4-1 -> 0
A8: 中板／背板全參與 | B8: 參與係數 1 | C8: =E211 -> 152.8409 | D8: =E209 -> 99.917376 | E8: =E220 -> 0.368566 | F8: =E229 -> 60.151023 | G8: =F8/F$4-1 -> 0 | H8: =F211 -> 194.26606 | I8: =F209 -> 139.75483 | J8: =F220 -> 0.36596201 | K8: =F229 -> 76.561569 | L8: =K8/K$4-1 -> 0
A9: 份額流失（低） | B9: 份額相對值 2027 0.85、2028 0.75、2029 0.70（ASIC 改 HDI 混壓情境） | C9: =E257 -> 152.8409 | D9: =E255 -> 99.917376 | E9: =E266 -> 0.368566 | F9: =E275 -> 60.151023 | G9: =F9/F$4-1 -> 0 | H9: =F257 -> 176.35708 | I9: =F255 -> 121.84584 | J9: =F266 -> 0.36321681 | K9: =F275 -> 68.351787 | L9: =K9/K$4-1 -> -0.10723111
A10: 份額提升（高） | B10: 份額相對值 2027–28 1.08、2029 1.05 | C10: =E303 -> 152.8409 | D10: =E301 -> 99.917376 | E10: =E312 -> 0.368566 | F10: =E321 -> 60.151023 | G10: =F10/F$4-1 -> 0 | H10: =F303 -> 194.26606 | I10: =F301 -> 139.75483 | J10: =F312 -> 0.36596201 | K10: =F321 -> 76.561569 | L10: =K10/K$4-1 -> 0
A11: 價格回落快 | B11: 價格指數 2027 0.96、2028 0.92、2029 0.88 | C11: =E349 -> 146.72727 | D11: =E347 -> 93.80374 | E11: =E358 -> 0.35090719 | F11: =E367 -> 54.14545 | G11: =F11/F$4-1 -> -0.099841584 | H11: =F349 -> 184.25234 | I11: =F347 -> 129.74111 | J11: =F358 -> 0.34068933 | K11: =F367 -> 66.25927 | L11: =K11/K$4-1 -> -0.13456227
A12: 價格延續 | B12: 價格指數 2027 1.03、2028 1.02、2029 1.00 | C12: =E395 -> 157.42613 | D12: =E393 -> 104.5026 | E12: =E404 -> 0.3813408 | F12: =E413 -> 64.744727 | G12: =F12/F$4-1 -> 0.076369501 | H12: =F395 -> 204.27977 | I12: =F393 -> 149.76854 | J12: =F404 -> 0.38964134 | K12: =F413 -> 87.108506 | L12: =K12/K$4-1 -> 0.13775758
A13: 擴產延遲 | B13: 產能指數 2027 1.30、2028 1.60、2029 1.90 | C13: =E441 -> 137.02978 | D13: =E439 -> 84.106248 | E13: =E450 -> 0.3641711 | F13: =E459 -> 52.670372 | G13: =F13/F$4-1 -> -0.12436449 | H13: =F441 -> 163.59247 | I13: =F439 -> 109.08124 | J13: =F450 -> 0.36089331 | K13: =F459 -> 62.570748 | L13: =K13/K$4-1 -> -0.18273948
A14: 擴產提前 | B14: 產能指數 2027 1.60、2028 2.15、2029 2.60 | C14: =E487 -> 168.65203 | D14: =E485 -> 115.7285 | E14: =E496 -> 0.37213687 | F14: =E505 -> 67.631675 | G14: =F14/F$4-1 -> 0.12436449 | H14: =F487 -> 208.8493 | I14: =F485 -> 154.33807 | J14: =F496 -> 0.36784963 | K14: =F505 -> 83.188545 | L14: =K14/K$4-1 -> 0.086557467
A15: AI 毛利率未改善 | B15: 額外改善 2027–29 皆 −1pt | C15: =E533 -> 152.8409 | D15: =E531 -> 99.917376 | E15: =E542 -> 0.35549131 | F15: =E551 -> 57.512972 | G15: =F15/F$4-1 -> -0.043857138 | H15: =F533 -> 194.26606 | I15: =F531 -> 139.75483 | J15: =F542 -> 0.34797703 | K15: =F551 -> 71.994919 | L15: =K15/K$4-1 -> -0.059646768
A16: AI 毛利率改善 快 | B16: 額外改善 2027 +2pt、2028 +3pt、2029 +3.5pt | C16: =E579 -> 152.8409 | D16: =E577 -> 99.917376 | E16: =E588 -> 0.37510335 | F16: =E597 -> 61.470049 | G16: =F16/F$4-1 -> 0.021928569 | H16: =F579 -> 194.26606 | I16: =F577 -> 139.75483 | J16: =F588 -> 0.37675299 | K16: =F597 -> 79.301559 | L16: =K16/K$4-1 -> 0.035788061
A17: AI 部署 ×0.8 | B17: FY2027 起 AI IT 資本支出 ×0.8 | C17: =E625 -> 152.8409 | D17: =E623 -> 99.917376 | E17: =E634 -> 0.368566 | F17: =E643 -> 60.151023 | G17: =F17/F$4-1 -> 0 | H17: =F625 -> 177.98169 | I17: =F623 -> 123.47045 | J17: =F634 -> 0.36348863 | K17: =F643 -> 69.096537 | L17: =K17/K$4-1 -> -0.09750365
A18: AI 部署 ×1.2 | B18: ×1.2 | C18: =E671 -> 152.8409 | D18: =E669 -> 99.917376 | E18: =E680 -> 0.368566 | F18: =E689 -> 60.151023 | G18: =F18/F$4-1 -> 0 | H18: =F671 -> 194.26606 | I18: =F669 -> 139.75483 | J18: =F680 -> 0.36596201 | K18: =F689 -> 76.561569 | L18: =K18/K$4-1 -> 0
A19: AI 毛利率差距 6pt | B19: AI 相關毛利率只高 6 個百分點 | C19: =E717 -> 152.8409 | D19: =E715 -> 99.917376 | E19: =E726 -> 0.36328958 | F19: =E735 -> 59.08641 | G19: =F19/F$4-1 -> -0.017699 | H19: =F717 -> 194.26606 | I19: =F715 -> 139.75483 | J19: =F726 -> 0.35763343 | K19: =F735 -> 74.446821 | L19: =K19/K$4-1 -> -0.02762153
A20: AI 毛利率差距 14pt | B20: 高 14 個百分點 | C20: =E763 -> 152.8409 | D20: =E761 -> 99.917376 | E20: =E772 -> 0.37384243 | F20: =E781 -> 61.215636 | G20: =F20/F$4-1 -> 0.017699 | H20: =F763 -> 194.26606 | I20: =F761 -> 139.75483 | J20: =F772 -> 0.37429058 | K20: =F781 -> 78.676317 | L20: =K20/K$4-1 -> 0.02762153
A21: 非 AI 成長 低 | B21: 2027–29 −5% | C21: =E809 -> 152.8409 | D21: =E807 -> 104.95771 | E21: =E818 -> 0.37219355 | F21: =E827 -> 60.882945 | G21: =F21/F$4-1 -> 0.012168063 | H21: =F809 -> 194.26606 | I21: =F807 -> 148.77703 | J21: =F818 -> 0.37043627 | K21: =F827 -> 77.69765 | L21: =K21/K$4-1 -> 0.014838793
A22: 非 AI 成長 高 | B22: 2027 +10%、2028–29 +8% | C22: =E855 -> 152.8409 | D22: =E853 -> 97.397208 | E22: =E864 -> 0.36675223 | F22: =E873 -> 59.785063 | G22: =F22/F$4-1 -> -0.0060840314 | H22: =F855 -> 194.26606 | I22: =F853 -> 134.38687 | J22: =F864 -> 0.36329994 | K22: =F873 -> 75.885632 | L22: =K22/K$4-1 -> -0.0088286675
A23: 營業費用彈性 1.0 | B23: 基準 0.6 | C23: =E901 -> 152.8409 | D23: =E899 -> 99.917376 | E23: =E910 -> 0.368566 | F23: =E919 -> 58.136479 | G23: =F23/F$4-1 -> -0.033491448 | H23: =F901 -> 194.26606 | I23: =F899 -> 139.75483 | J23: =F910 -> 0.36596201 | K23: =F919 -> 72.500657 | L23: =K23/K$4-1 -> -0.053041124
A24: 淨利 ÷ 稅前 0.65 | B24: 基準 0.685 | C24: =E947 -> 152.8409 | D24: =E945 -> 99.917376 | E24: =E956 -> 0.368566 | F24: =E965 -> 57.077613 | G24: =F24/F$4-1 -> -0.051094891 | H24: =F947 -> 194.26606 | I24: =F945 -> 139.75483 | J24: =F956 -> 0.36596201 | K24: =F965 -> 72.649664 | L24: =K24/K$4-1 -> -0.051094891
A25: 淨利 ÷ 稅前 0.75 | C25: =E993 -> 152.8409 | D25: =E991 -> 99.917376 | E25: =E1002 -> 0.368566 | F25: =E1011 -> 65.858785 | G25: =F25/F$4-1 -> 0.094890511 | H25: =F993 -> 194.26606 | I25: =F991 -> 139.75483 | J25: =F1002 -> 0.36596201 | K25: =F1011 -> 83.826535 | L25: =K25/K$4-1 -> 0.094890511
A26: 情境 A（全部） | B26: 顆數係數 A＋份額、價格、AI 毛利率改善高值 | C26: =PL!E83 -> 157.42613 | D26: =PL!E81 -> 104.5026 | E26: =PL!E92 -> 0.387979 | F26: =PL!E101 -> 66.124283 | G26: =F26/F$4-1 -> 0.099304377 | H26: =PL!F83 -> 204.27977 | I26: =PL!F81 -> 149.76854 | J26: =PL!F92 -> 0.40063865 | K26: =PL!F101 -> 90.044822 | L26: =K26/K$4-1 -> 0.17610993
A27: 情境 C（全部） | B27: 顆數係數 C＋份額、價格、AI 毛利率改善低值 | C27: =PL!E175 -> 146.72727 | D27: =PL!E173 -> 93.80374 | E27: =PL!E184 -> 0.33812105 | F27: =PL!E193 -> 51.668812 | G27: =F27/F$4-1 -> -0.14101524 | H27: =PL!F175 -> 141.18508 | I27: =PL!F173 -> 86.673847 | J27: =PL!F184 -> 0.31969817 | K27: =PL!F193 -> 45.308254 | L27: =K27/K$4-1 -> -0.40821153
A29: 讀法：基準為情境 B（顆數係數 B 從 CY2028 起）。產能受限的年度，需求面輸入（每 GW 金額、份額、AI 部署）對營收的影響被產能上限截斷，只有產能與價格會改變營收；價格指數同時改變產能上限營收與 AI 毛利率（成本不變），所以對 EPS 的影響大於對營收。
A31: 目標價參數（只改 DCF 參數；PL 收斂法的 fade_g 不隨 tp_g 變動）
A32: 案例 | B32: 設定 | C32: DCF 目標價 | D32: Comparable 目標價 | E32: 加權目標價 | F32: 相對基準
A33: 基準 | B33: r 10%、g 4%、DCF 權重 0.5 | C33: =(tp_wA*MAX(0,Val!B8*(1-MIN(tp_g/tp_roe,0.8))/(1+tp_r)^1+Val!B9*(1-MIN(tp_g/tp_roe,0.8))/(1+tp_r)^2+Val!B10*(1-MIN(tp_g/tp_roe,0.8))/(1+tp_r)^3+Val!B11*(1-MIN(tp_g/tp_roe,0.8))/(1+tp_r)^4+Val!B12*(1-MIN(tp_g/tp_roe,0.8))/(1+tp_r)^5+Val!B13*(1-MIN(tp_g/tp_roe,0.8))/(1+tp_r)^6+Val!B13*(1-MIN(tp_g/tp_roe,0.8))*(1+tp_g)/(tp_r-tp_g)/(1+tp_r)^6)+tp_wB*MAX(0,Val!C8*(1-MIN(tp_g/tp_roe,0.8))/(1+tp_r)^1+Val!C9*(1-MIN(tp_g/tp_roe,0.8))/(1+tp_r)^2+Val!C10*(1-MIN(tp_g/tp_roe,0.8))/(1+tp_r)^3+Val!C11*(1-MIN(tp_g/tp_roe,0.8))/(1+tp_r)^4+Val!C12*(1-MIN(tp_g/tp_roe,0.8))/(1+tp_r)^5+Val!C13*(1-MIN(tp_g/tp_roe,0.8))/(1+tp_r)^6+Val!C13*(1-MIN(tp_g/tp_roe,0.8))*(1+tp_g)/(tp_r-tp_g)/(1+tp_r)^6)+tp_wC*MAX(0,Val!D8*(1-MIN(tp_g/tp_roe,0.8))/(1+tp_r)^1+Val!D9*(1-MIN(tp_g/tp_roe,0.8))/(1+tp_r)^2+Val!D10*(1-MIN(tp_g/tp_roe,0.8))/(1+tp_r)^3+Val!D11*(1-MIN(tp_g/tp_roe,0.8))/(1+tp_r)^4+Val!D12*(1-MIN(tp_g/tp_roe,0.8))/(1+tp_r)^5+Val!D13*(1-MIN(tp_g/tp_roe,0.8))/(1+tp_r)^6+Val!D13*(1-MIN(tp_g/tp_roe,0.8))*(1+tp_g)/(tp_r-tp_g)/(1+tp_r)^6))*(1+tp_r) -> 1203.0741 | D33: =Val!B36 -> 1331.36 | E33: =tp_w_dcf*C33+(1-tp_w_dcf)*D33 -> 1267.217 | F33: =E33/E$33-1 -> 0
A34: 折現率 +1pt | B34: r 11% | C34: =(tp_wA*MAX(0,Val!B8*(1-MIN(tp_g/tp_roe,0.8))/(1+(tp_r+0.01))^1+Val!B9*(1-MIN(tp_g/tp_roe,0.8))/(1+(tp_r+0.01))^2+Val!B10*(1-MIN(tp_g/tp_roe,0.8))/(1+(tp_r+0.01))^3+Val!B11*(1-MIN(tp_g/tp_roe,0.8))/(1+(tp_r+0.01))^4+Val!B12*(1-MIN(tp_g/tp_roe,0.8))/(1+(tp_r+0.01))^5+Val!B13*(1-MIN(tp_g/tp_roe,0.8))/(1+(tp_r+0.01))^6+Val!B13*(1-MIN(tp_g/tp_roe,0.8))*(1+tp_g)/((tp_r+0.01)-tp_g)/(1+(tp_r+0.01))^6)+tp_wB*MAX(0,Val!C8*(1-MIN(tp_g/tp_roe,0.8))/(1+(tp_r+0.01))^1+Val!C9*(1-MIN(tp_g/tp_roe,0.8))/(1+(tp_r+0.01))^2+Val!C10*(1-MIN(tp_g/tp_roe,0.8))/(1+(tp_r+0.01))^3+Val!C11*(1-MIN(tp_g/tp_roe,0.8))/(1+(tp_r+0.01))^4+Val!C12*(1-MIN(tp_g/tp_roe,0.8))/(1+(tp_r+0.01))^5+Val!C13*(1-MIN(tp_g/tp_roe,0.8))/(1+(tp_r+0.01))^6+Val!C13*(1-MIN(tp_g/tp_roe,0.8))*(1+tp_g)/((tp_r+0.01)-tp_g)/(1+(tp_r+0.01))^6)+tp_wC*MAX(0,Val!D8*(1-MIN(tp_g/tp_roe,0.8))/(1+(tp_r+0.01))^1+Val!D9*(1-MIN(tp_g/tp_roe,0.8))/(1+(tp_r+0.01))^2+Val!D10*(1-MIN(tp_g/tp_roe,0.8))/(1+(tp_r+0.01))^3+Val!D11*(1-MIN(tp_g/tp_roe,0.8))/(1+(tp_r+0.01))^4+Val!D12*(1-MIN(tp_g/tp_roe,0.8))/(1+(tp_r+0.01))^5+Val!D13*(1-MIN(tp_g/tp_roe,0.8))/(1+(tp_r+0.01))^6+Val!D13*(1-MIN(tp_g/tp_roe,0.8))*(1+tp_g)/((tp_r+0.01)-tp_g)/(1+(tp_r+0.01))^6))*(1+(tp_r+0.01)) -> 1038.8516 | D34: =Val!B36 -> 1331.36 | E34: =tp_w_dcf*C34+(1-tp_w_dcf)*D34 -> 1185.1058 | F34: =E34/E$33-1 -> -0.064796501
A35: 折現率 −1pt | B35: r 9% | C35: =(tp_wA*MAX(0,Val!B8*(1-MIN(tp_g/tp_roe,0.8))/(1+(tp_r-0.01))^1+Val!B9*(1-MIN(tp_g/tp_roe,0.8))/(1+(tp_r-0.01))^2+Val!B10*(1-MIN(tp_g/tp_roe,0.8))/(1+(tp_r-0.01))^3+Val!B11*(1-MIN(tp_g/tp_roe,0.8))/(1+(tp_r-0.01))^4+Val!B12*(1-MIN(tp_g/tp_roe,0.8))/(1+(tp_r-0.01))^5+Val!B13*(1-MIN(tp_g/tp_roe,0.8))/(1+(tp_r-0.01))^6+Val!B13*(1-MIN(tp_g/tp_roe,0.8))*(1+tp_g)/((tp_r-0.01)-tp_g)/(1+(tp_r-0.01))^6)+tp_wB*MAX(0,Val!C8*(1-MIN(tp_g/tp_roe,0.8))/(1+(tp_r-0.01))^1+Val!C9*(1-MIN(tp_g/tp_roe,0.8))/(1+(tp_r-0.01))^2+Val!C10*(1-MIN(tp_g/tp_roe,0.8))/(1+(tp_r-0.01))^3+Val!C11*(1-MIN(tp_g/tp_roe,0.8))/(1+(tp_r-0.01))^4+Val!C12*(1-MIN(tp_g/tp_roe,0.8))/(1+(tp_r-0.01))^5+Val!C13*(1-MIN(tp_g/tp_roe,0.8))/(1+(tp_r-0.01))^6+Val!C13*(1-MIN(tp_g/tp_roe,0.8))*(1+tp_g)/((tp_r-0.01)-tp_g)/(1+(tp_r-0.01))^6)+tp_wC*MAX(0,Val!D8*(1-MIN(tp_g/tp_roe,0.8))/(1+(tp_r-0.01))^1+Val!D9*(1-MIN(tp_g/tp_roe,0.8))/(1+(tp_r-0.01))^2+Val!D10*(1-MIN(tp_g/tp_roe,0.8))/(1+(tp_r-0.01))^3+Val!D11*(1-MIN(tp_g/tp_roe,0.8))/(1+(tp_r-0.01))^4+Val!D12*(1-MIN(tp_g/tp_roe,0.8))/(1+(tp_r-0.01))^5+Val!D13*(1-MIN(tp_g/tp_roe,0.8))/(1+(tp_r-0.01))^6+Val!D13*(1-MIN(tp_g/tp_roe,0.8))*(1+tp_g)/((tp_r-0.01)-tp_g)/(1+(tp_r-0.01))^6))*(1+(tp_r-0.01)) -> 1432.9292 | D35: =Val!B36 -> 1331.36 | E35: =tp_w_dcf*C35+(1-tp_w_dcf)*D35 -> 1382.1446 | F35: =E35/E$33-1 -> 0.09069288
A36: 長期成長 +1pt | B36: g 5% | C36: =(tp_wA*MAX(0,Val!B8*(1-MIN((tp_g+0.01)/tp_roe,0.8))/(1+tp_r)^1+Val!B9*(1-MIN((tp_g+0.01)/tp_roe,0.8))/(1+tp_r)^2+Val!B10*(1-MIN((tp_g+0.01)/tp_roe,0.8))/(1+tp_r)^3+Val!B11*(1-MIN((tp_g+0.01)/tp_roe,0.8))/(1+tp_r)^4+Val!B12*(1-MIN((tp_g+0.01)/tp_roe,0.8))/(1+tp_r)^5+Val!B13*(1-MIN((tp_g+0.01)/tp_roe,0.8))/(1+tp_r)^6+Val!B13*(1-MIN((tp_g+0.01)/tp_roe,0.8))*(1+(tp_g+0.01))/(tp_r-(tp_g+0.01))/(1+tp_r)^6)+tp_wB*MAX(0,Val!C8*(1-MIN((tp_g+0.01)/tp_roe,0.8))/(1+tp_r)^1+Val!C9*(1-MIN((tp_g+0.01)/tp_roe,0.8))/(1+tp_r)^2+Val!C10*(1-MIN((tp_g+0.01)/tp_roe,0.8))/(1+tp_r)^3+Val!C11*(1-MIN((tp_g+0.01)/tp_roe,0.8))/(1+tp_r)^4+Val!C12*(1-MIN((tp_g+0.01)/tp_roe,0.8))/(1+tp_r)^5+Val!C13*(1-MIN((tp_g+0.01)/tp_roe,0.8))/(1+tp_r)^6+Val!C13*(1-MIN((tp_g+0.01)/tp_roe,0.8))*(1+(tp_g+0.01))/(tp_r-(tp_g+0.01))/(1+tp_r)^6)+tp_wC*MAX(0,Val!D8*(1-MIN((tp_g+0.01)/tp_roe,0.8))/(1+tp_r)^1+Val!D9*(1-MIN((tp_g+0.01)/tp_roe,0.8))/(1+tp_r)^2+Val!D10*(1-MIN((tp_g+0.01)/tp_roe,0.8))/(1+tp_r)^3+Val!D11*(1-MIN((tp_g+0.01)/tp_roe,0.8))/(1+tp_r)^4+Val!D12*(1-MIN((tp_g+0.01)/tp_roe,0.8))/(1+tp_r)^5+Val!D13*(1-MIN((tp_g+0.01)/tp_roe,0.8))/(1+tp_r)^6+Val!D13*(1-MIN((tp_g+0.01)/tp_roe,0.8))*(1+(tp_g+0.01))/(tp_r-(tp_g+0.01))/(1+tp_r)^6))*(1+tp_r) -> 1331.2636 | D36: =Val!B36 -> 1331.36 | E36: =tp_w_dcf*C36+(1-tp_w_dcf)*D36 -> 1331.3118 | F36: =E36/E$33-1 -> 0.050579163
A37: 長期成長 −1pt | B37: g 3% | C37: =(tp_wA*MAX(0,Val!B8*(1-MIN((tp_g-0.01)/tp_roe,0.8))/(1+tp_r)^1+Val!B9*(1-MIN((tp_g-0.01)/tp_roe,0.8))/(1+tp_r)^2+Val!B10*(1-MIN((tp_g-0.01)/tp_roe,0.8))/(1+tp_r)^3+Val!B11*(1-MIN((tp_g-0.01)/tp_roe,0.8))/(1+tp_r)^4+Val!B12*(1-MIN((tp_g-0.01)/tp_roe,0.8))/(1+tp_r)^5+Val!B13*(1-MIN((tp_g-0.01)/tp_roe,0.8))/(1+tp_r)^6+Val!B13*(1-MIN((tp_g-0.01)/tp_roe,0.8))*(1+(tp_g-0.01))/(tp_r-(tp_g-0.01))/(1+tp_r)^6)+tp_wB*MAX(0,Val!C8*(1-MIN((tp_g-0.01)/tp_roe,0.8))/(1+tp_r)^1+Val!C9*(1-MIN((tp_g-0.01)/tp_roe,0.8))/(1+tp_r)^2+Val!C10*(1-MIN((tp_g-0.01)/tp_roe,0.8))/(1+tp_r)^3+Val!C11*(1-MIN((tp_g-0.01)/tp_roe,0.8))/(1+tp_r)^4+Val!C12*(1-MIN((tp_g-0.01)/tp_roe,0.8))/(1+tp_r)^5+Val!C13*(1-MIN((tp_g-0.01)/tp_roe,0.8))/(1+tp_r)^6+Val!C13*(1-MIN((tp_g-0.01)/tp_roe,0.8))*(1+(tp_g-0.01))/(tp_r-(tp_g-0.01))/(1+tp_r)^6)+tp_wC*MAX(0,Val!D8*(1-MIN((tp_g-0.01)/tp_roe,0.8))/(1+tp_r)^1+Val!D9*(1-MIN((tp_g-0.01)/tp_roe,0.8))/(1+tp_r)^2+Val!D10*(1-MIN((tp_g-0.01)/tp_roe,0.8))/(1+tp_r)^3+Val!D11*(1-MIN((tp_g-0.01)/tp_roe,0.8))/(1+tp_r)^4+Val!D12*(1-MIN((tp_g-0.01)/tp_roe,0.8))/(1+tp_r)^5+Val!D13*(1-MIN((tp_g-0.01)/tp_roe,0.8))/(1+tp_r)^6+Val!D13*(1-MIN((tp_g-0.01)/tp_roe,0.8))*(1+(tp_g-0.01))/(tp_r-(tp_g-0.01))/(1+tp_r)^6))*(1+tp_r) -> 1114.7648 | D37: =Val!B36 -> 1331.36 | E37: =tp_w_dcf*C37+(1-tp_w_dcf)*D37 -> 1223.0624 | F37: =E37/E$33-1 -> -0.034843776
A38: DCF 權重 0.3 | C38: =(tp_wA*MAX(0,Val!B8*(1-MIN(tp_g/tp_roe,0.8))/(1+tp_r)^1+Val!B9*(1-MIN(tp_g/tp_roe,0.8))/(1+tp_r)^2+Val!B10*(1-MIN(tp_g/tp_roe,0.8))/(1+tp_r)^3+Val!B11*(1-MIN(tp_g/tp_roe,0.8))/(1+tp_r)^4+Val!B12*(1-MIN(tp_g/tp_roe,0.8))/(1+tp_r)^5+Val!B13*(1-MIN(tp_g/tp_roe,0.8))/(1+tp_r)^6+Val!B13*(1-MIN(tp_g/tp_roe,0.8))*(1+tp_g)/(tp_r-tp_g)/(1+tp_r)^6)+tp_wB*MAX(0,Val!C8*(1-MIN(tp_g/tp_roe,0.8))/(1+tp_r)^1+Val!C9*(1-MIN(tp_g/tp_roe,0.8))/(1+tp_r)^2+Val!C10*(1-MIN(tp_g/tp_roe,0.8))/(1+tp_r)^3+Val!C11*(1-MIN(tp_g/tp_roe,0.8))/(1+tp_r)^4+Val!C12*(1-MIN(tp_g/tp_roe,0.8))/(1+tp_r)^5+Val!C13*(1-MIN(tp_g/tp_roe,0.8))/(1+tp_r)^6+Val!C13*(1-MIN(tp_g/tp_roe,0.8))*(1+tp_g)/(tp_r-tp_g)/(1+tp_r)^6)+tp_wC*MAX(0,Val!D8*(1-MIN(tp_g/tp_roe,0.8))/(1+tp_r)^1+Val!D9*(1-MIN(tp_g/tp_roe,0.8))/(1+tp_r)^2+Val!D10*(1-MIN(tp_g/tp_roe,0.8))/(1+tp_r)^3+Val!D11*(1-MIN(tp_g/tp_roe,0.8))/(1+tp_r)^4+Val!D12*(1-MIN(tp_g/tp_roe,0.8))/(1+tp_r)^5+Val!D13*(1-MIN(tp_g/tp_roe,0.8))/(1+tp_r)^6+Val!D13*(1-MIN(tp_g/tp_roe,0.8))*(1+tp_g)/(tp_r-tp_g)/(1+tp_r)^6))*(1+tp_r) -> 1203.0741 | D38: =Val!B36 -> 1331.36 | E38: =0.3*C38+(1-0.3)*D38 -> 1292.8742 | F38: =E38/E$33-1 -> 0.020246883
A39: DCF 權重 0.7 | C39: =(tp_wA*MAX(0,Val!B8*(1-MIN(tp_g/tp_roe,0.8))/(1+tp_r)^1+Val!B9*(1-MIN(tp_g/tp_roe,0.8))/(1+tp_r)^2+Val!B10*(1-MIN(tp_g/tp_roe,0.8))/(1+tp_r)^3+Val!B11*(1-MIN(tp_g/tp_roe,0.8))/(1+tp_r)^4+Val!B12*(1-MIN(tp_g/tp_roe,0.8))/(1+tp_r)^5+Val!B13*(1-MIN(tp_g/tp_roe,0.8))/(1+tp_r)^6+Val!B13*(1-MIN(tp_g/tp_roe,0.8))*(1+tp_g)/(tp_r-tp_g)/(1+tp_r)^6)+tp_wB*MAX(0,Val!C8*(1-MIN(tp_g/tp_roe,0.8))/(1+tp_r)^1+Val!C9*(1-MIN(tp_g/tp_roe,0.8))/(1+tp_r)^2+Val!C10*(1-MIN(tp_g/tp_roe,0.8))/(1+tp_r)^3+Val!C11*(1-MIN(tp_g/tp_roe,0.8))/(1+tp_r)^4+Val!C12*(1-MIN(tp_g/tp_roe,0.8))/(1+tp_r)^5+Val!C13*(1-MIN(tp_g/tp_roe,0.8))/(1+tp_r)^6+Val!C13*(1-MIN(tp_g/tp_roe,0.8))*(1+tp_g)/(tp_r-tp_g)/(1+tp_r)^6)+tp_wC*MAX(0,Val!D8*(1-MIN(tp_g/tp_roe,0.8))/(1+tp_r)^1+Val!D9*(1-MIN(tp_g/tp_roe,0.8))/(1+tp_r)^2+Val!D10*(1-MIN(tp_g/tp_roe,0.8))/(1+tp_r)^3+Val!D11*(1-MIN(tp_g/tp_roe,0.8))/(1+tp_r)^4+Val!D12*(1-MIN(tp_g/tp_roe,0.8))/(1+tp_r)^5+Val!D13*(1-MIN(tp_g/tp_roe,0.8))/(1+tp_r)^6+Val!D13*(1-MIN(tp_g/tp_roe,0.8))*(1+tp_g)/(tp_r-tp_g)/(1+tp_r)^6))*(1+tp_r) -> 1203.0741 | D39: =Val!B36 -> 1331.36 | E39: =0.7*C39+(1-0.7)*D39 -> 1241.5598 | F39: =E39/E$33-1 -> -0.020246883
A50: 案例區塊：每 GW 金額成長 低（情境 B）
A51: 項目 | B51: 單位 | C51: FY2025A | D51: FY2026（錨點） | E51: FY2027 | F51: FY2028 | G51: FY2029 | H51: FY2030（收斂） | I51: FY2031（收斂） | J51: FY2032（收斂） | K51: 說明
A52: A. AI 部署與每 GW AI 高速 PCB 金額（需求面；D 欄＝FY2026 校準年；每 GW 金額取自勝宏模型）
A53: AI IT 資本支出 × 情境顆數係數 | B53: US$B | D53: =itc_26*1 -> 781.87292 | E53: =itc_27*1*1 -> 1565.35 | F53: =itc_28*um28_B*1 -> 1587.4111 | G53: =itc_29*um29_B*1 -> 1921.3317
A54: 每 GW IT 資本支出 | B54: US$B | D54: =itpg_gb*(1-vr26)+itpg_vr*vr26 -> 33.414032 | E54: =itpg_vr -> 37.586352 | F54: =itpg_vr -> 37.586352 | G54: =itpg_vr -> 37.586352
A55: 部署 GW（IT 電力） | B55: GW | D55: =D53/D54 -> 23.399538 | E55: =E53/E54 -> 41.646766 | F55: =F53/F54 -> 42.233711 | G55: =G53/G54 -> 51.117803
A56: 每 GW PCB：加速器卡／運算板 | B56: US$M/GW | D56: =vg_cmp26 -> 280 | E56: =(vg_cmp26+(vg_cmp27-vg_cmp26)*pgwf_lo) -> 378 | F56: =(vg_cmp26+(vg_cmp28-vg_cmp26)*pgwf_lo) -> 407.4 | G56: =(vg_cmp26+(vg_cmp29-vg_cmp26)*pgwf_lo) -> 436.8
A57: 每 GW PCB：交換器板 | B57: US$M/GW | D57: =vg_sw26 -> 120 | E57: =(vg_sw26+(vg_sw27-vg_sw26)*pgwf_lo) -> 149.4 | F57: =(vg_sw26+(vg_sw28-vg_sw26)*pgwf_lo) -> 162 | G57: =(vg_sw26+(vg_sw29-vg_sw26)*pgwf_lo) -> 174.6
A58: 每 GW PCB：中板／背板／其他 × 金像電參與係數 | B58: US$M/GW | D58: =vg_mid26*w_mid -> 25 | E58: =(vg_mid26+(vg_mid27-vg_mid26)*pgwf_lo)*w_mid -> 42.5 | F58: =(vg_mid26+(vg_mid28-vg_mid26)*pgwf_lo)*w_mid -> 60 | G58: =(vg_mid26+(vg_mid29-vg_mid26)*pgwf_lo)*w_mid -> 68.75
A59: 每 GW 金像電可參與 AI 高速 PCB 金額（三項合計） | B59: US$M/GW | D59: =D56+D57+D58 -> 425 | E59: =E56+E57+E58 -> 569.9 | F59: =F56+F57+F58 -> 629.4 | G59: =G56+G57+G58 -> 680.15
A60: 可參與 AI 高速 PCB 市場（美元；不含價格指數） | B60: US$B | D60: =D55*D59/1000 -> 9.9448037 | E60: =E55*E59/1000 -> 23.734492 | F60: =F55*F59/1000 -> 26.581897 | G60: =G55*G59/1000 -> 34.767774
A61: 可參與 AI 高速 PCB 市場（新台幣） | B61: NT$B | D61: =D60*fx -> 318.23372 | E61: =E60*fx -> 759.50374 | F61: =F60*fx -> 850.62072 | G61: =G60*fx -> 1112.5688
A62: PCB 價格指數（FY2026＝1） | B62: x | D62: =1 -> 1 | E62: =pp_27 -> 1 | F62: =pp_28 -> 0.97 | G62: =pp_29 -> 0.94
A63: 金像電有效份額（FY2026 校準）＝ AI 相關營收 ÷ 可參與市場 | B63: % | D63: =a26_ai/D61 -> 0.17284202 | K63: Derived：分子為 FY2026 錨點營收 − 非 AI；分母為本模型的可參與市場（含 ASIC）
A64: 份額相對值（÷ FY2026） | B64: x | D64: =1 -> 1 | E64: =rel_27 -> 1 | F64: =rel_28 -> 0.95 | G64: =rel_29 -> 0.9
A65: 金像電有效份額 | B65: % | D65: =$D$63*D64 -> 0.17284202 | E65: =$D$63*E64 -> 0.17284202 | F65: =$D$63*F64 -> 0.16419992 | G65: =$D$63*G64 -> 0.15555782
A66: AI 相關營收（需求面）＝ 市場 × 份額 × 價格指數 | B66: NT$B | D66: =D61*D65*D62 -> 55.00416 | E66: =E61*E65*E62 -> 131.27416 | F66: =F61*F65*F62 -> 135.4817 | G66: =G61*G65*G62 -> 162.68465
A67: B. 產能上限（全產全銷）與營收
A68: 平均產值產能指數（FY2026 營收＝1） | B68: x | D68: =1 -> 1 | E68: =cx_27 -> 1.45 | F68: =cx_28 -> 1.9 | G68: =cx_29 -> 2.3 | K68: FY2026 校準：公司稱產能吃緊、產線滿載，FY2026 營收視為產能（Derived）
A69: 產能上限營收 ＝ FY2026 營收 × 產能指數 × 價格指數 | B69: NT$B | D69: =a26_rev*D68*D62 -> 105.40752 | E69: =a26_rev*E68*E62 -> 152.8409 | F69: =a26_rev*F68*F62 -> 194.26606 | G69: =a26_rev*G68*G62 -> 227.89106
A70: 非 AI 營收 | B70: NT$B | C70: =a25_nai -> 42.0028 | D70: =a26_nai -> 50.40336 | E70: =D70*(1+g_nai27) -> 52.923528 | F70: =E70*(1+g_nai28) -> 54.511234 | G70: =F70*(1+g_nai29) -> 56.146571
A71: AI 相關營收 ＝ MIN（需求面、產能上限 − 非 AI） | B71: NT$B | C71: =a25_ai -> 18.0012 | D71: =D66 -> 55.00416 | E71: =MIN(E66,E69-E70) -> 99.917376 | F71: =MIN(F66,F69-F70) -> 135.4817 | G71: =MIN(G66,G69-G70) -> 162.68465 | K71: 產能不足時，非 AI 照成長率出貨、AI 取剩餘產能（Assumed）
A72: 產能是否受限 | E72: =IF(E66>E69-E70+0.0001,"受限","未受限") -> 受限 | F72: =IF(F66>F69-F70+0.0001,"受限","未受限") -> 未受限 | G72: =IF(G66>G69-G70+0.0001,"受限","未受限") -> 未受限
A73: 營收 | B73: NT$B | C73: =C71+C70 -> 60.004 | D73: =D71+D70 -> 105.40752 | E73: =E71+E70 -> 152.8409 | F73: =F71+F70 -> 189.99293 | G73: =G71+G70 -> 218.83122 | H73: =G73*(1+H74) -> 243.89266 | I73: =H73*(1+I74) -> 262.7363 | J73: =I73*(1+J74) -> 273.24575 | K73: FY2030 起為收斂法：營收年增由 FY2029 線性收斂到 fade_g、淨利率收斂到 fade_m（FY2032 達到），非驅動因子推導
A74: 營收年增 | B74: % | D74: =D73/C73-1 -> 0.75667489 | E74: =E73/D73-1 -> 0.45 | F74: =F73/E73-1 -> 0.24307649 | G74: =G73/F73-1 -> 0.15178608 | H74: =$G74+(fade_gB-$G74)*1/3 -> 0.11452405 | I74: =$G74+(fade_gB-$G74)*2/3 -> 0.077262027 | J74: =$G74+(fade_gB-$G74)*3/3 -> 0.04
A75: AI 相關 ÷ 營收 | B75: % | C75: =C71/C73 -> 0.3 | D75: =D71/D73 -> 0.52182387 | E75: =E71/E73 -> 0.65373453 | F75: =F71/F73 -> 0.7130881 | G75: =G71/G73 -> 0.74342522
A76: 需求面 ÷ 產能上限（AI 需求面＋非 AI） | B76: % | D76: =(D66+D70)/D69 -> 1 | E76: =(E66+E70)/E69 -> 1.2051597 | F76: =(F66+F70)/F69 -> 0.97800375 | G76: =(G66+G70)/G69 -> 0.96024486 | K76: 大於 100%＝需求超過產能（營收由產能決定）
A77: 每 GW 金像電 AI 相關營收 | B77: US$M/GW | D77: =D71/fx/D55*1000 -> 73.45786 | E77: =E71/fx/E55*1000 -> 74.973841 | F77: =F71/fx/F55*1000 -> 100.24701 | G77: =G71/fx/G55*1000 -> 99.454494
A78: C. 損益
A79: 其他營收毛利率 ＝ 錨點毛利率 − 差距 × AI 占比（FY2026 校準） | B79: % | D79: =a26_gp/D73-d_ai*D75 -> 0.29665521 | K79: Derived：讓 FY2026 毛利率等於錨點；AI 相關毛利率＝其他＋差距
A80: AI 相關毛利率 ＝ 1 −（1 − 校準值）÷ 價格指數 ＋ 額外改善 | B80: % | D80: =D79+d_ai -> 0.39665521 | E80: =1-(1-$D$80)/E62+gmu_27 -> 0.40665521 | F80: =1-(1-$D$80)/F62+gmu_28 -> 0.39299506 | G80: =1-(1-$D$80)/G62+gmu_29 -> 0.37814384 | K80: Derived：同規格成本不變，價格升降全部落在毛利；額外改善為新廠爬坡完成與組合（Assumed）
A81: 毛利 | B81: NT$B | C81: =a25_gp -> 19.683 | D81: =a26_gp -> 36.770105 | E81: =E71*E80+E70*$D$79 -> 56.331961 | F81: =F71*F80+F70*$D$79 -> 69.41468 | G81: =G71*G80+G70*$D$79 -> 78.174369
A82: 毛利率 | B82: % | C82: =C81/C73 -> 0.32802813 | D82: =D81/D73 -> 0.34883759 | E82: =E81/E73 -> 0.368566 | F82: =F81/F73 -> 0.36535401 | G82: =G81/G73 -> 0.35723591
A83: 營業費用（基準路徑） | B83: NT$B | C83: =a25_opx -> 5.64 | D83: =a26_opx -> 8.4779754 | E83: =D83*(1+MAX(0,phi*E74)) -> 10.767029 | F83: =E83*(1+MAX(0,phi*F74)) -> 12.337356 | G83: =F83*(1+MAX(0,phi*G74)) -> 13.460939
A84: 營業費用 | B84: NT$B | C84: =C83 -> 5.64 | D84: =D83 -> 8.4779754 | E84: =E83+0*E73 -> 10.767029 | F84: =F83+0*F73 -> 12.337356 | G84: =G83+0*G73 -> 13.460939
A85: 營業利益 | B85: NT$B | C85: =C81-C84 -> 14.043 | D85: =D81-D84 -> 28.29213 | E85: =E81-E84 -> 45.564932 | F85: =F81-F84 -> 57.077324 | G85: =G81-G84 -> 64.71343
A86: 營業利益率 | B86: % | C86: =C85/C73 -> 0.2340344 | D86: =D85/D73 -> 0.26840713 | E86: =E85/E73 -> 0.29812001 | F86: =F85/F73 -> 0.30041814 | G86: =G85/G73 -> 0.29572303
A87: 營業外淨額 | B87: NT$B | E87: =nop_f -> 0 | F87: =nop_f -> 0 | G87: =nop_f -> 0 | K87: FY2025、FY2026 含在淨利錨點內
A88: 歸屬母公司淨利 | B88: NT$B | C88: =a25_ni -> 9.607 | D88: =a26_ni -> 19.697729 | E88: =(E85+E87)*nir_f -> 31.211979 | F88: =(F85+F87)*nir_f -> 39.097967 | G88: =(G85+G87)*nir_f -> 44.328699 | H88: =H73*H93 -> 46.335587 | I88: =I73*I93 -> 46.608573 | J88: =J73*J93 -> 45.033642
A89: 淨利 ÷ 營業利益 | B89: % | C89: =C88/C85 -> 0.68411308 | D89: =D88/D85 -> 0.69622644 | E89: =E88/E85 -> 0.685 | F89: =F88/F85 -> 0.685 | G89: =G88/G85 -> 0.685
A90: 股數 | B90: 十億股 | C90: =a25_sh -> 0.49342578 | D90: =a26_sh -> 0.51298085 | E90: =sh_h2*(1+sh_g) -> 0.51889356 | F90: =E90*(1+sh_g) -> 0.5240825 | G90: =F90*(1+sh_g) -> 0.52932332 | H90: =G90*(1+sh_g) -> 0.53461655 | I90: =H90*(1+sh_g) -> 0.53996272 | J90: =I90*(1+sh_g) -> 0.54536235 | K90: FY2027 起＝期末股數 ×（1＋sh_g）（FY2026 為加權）
A91: EPS | B91: NT$ | C91: =C88/C90 -> 19.47 | D91: =D88/D90 -> 38.398566 | E91: =E88/E90 -> 60.151023 | F91: =F88/F90 -> 74.602696 | G91: =G88/G90 -> 83.745978 | H91: =H88/H90 -> 86.670693 | I91: =I88/I90 -> 86.318132 | J91: =J88/J90 -> 82.575634
A92: EPS 年增 | B92: % | D92: =D91/C91-1 -> 0.97219136 | E92: =E91/D91-1 -> 0.56649141 | F92: =F91/E91-1 -> 0.24025647 | G92: =G91/F91-1 -> 0.12255968 | H92: =H91/G91-1 -> 0.034923636 | I92: =I91/H91-1 -> -0.0040678138 | J92: =J91/I91-1 -> -0.043357031
A93: 淨利率（歸屬母公司淨利 ÷ 營收） | B93: % | C93: =C88/C73 -> 0.16010599 | D93: =D88/D73 -> 0.18687214 | E93: =E88/E73 -> 0.20421221 | F93: =F88/F73 -> 0.20578643 | G93: =G88/G73 -> 0.20257027 | H93: =$G93+(fade_mB-$G93)*1/3 -> 0.18998353 | I93: =$G93+(fade_mB-$G93)*2/3 -> 0.17739678 | J93: =$G93+(fade_mB-$G93)*3/3 -> 0.16481004
A96: 案例區塊：每 GW 金額成長 高（情境 B）
A97: 項目 | B97: 單位 | C97: FY2025A | D97: FY2026（錨點） | E97: FY2027 | F97: FY2028 | G97: FY2029 | H97: FY2030（收斂） | I97: FY2031（收斂） | J97: FY2032（收斂） | K97: 說明
A98: A. AI 部署與每 GW AI 高速 PCB 金額（需求面；D 欄＝FY2026 校準年；每 GW 金額取自勝宏模型）
A99: AI IT 資本支出 × 情境顆數係數 | B99: US$B | D99: =itc_26*1 -> 781.87292 | E99: =itc_27*1*1 -> 1565.35 | F99: =itc_28*um28_B*1 -> 1587.4111 | G99: =itc_29*um29_B*1 -> 1921.3317
A100: 每 GW IT 資本支出 | B100: US$B | D100: =itpg_gb*(1-vr26)+itpg_vr*vr26 -> 33.414032 | E100: =itpg_vr -> 37.586352 | F100: =itpg_vr -> 37.586352 | G100: =itpg_vr -> 37.586352
A101: 部署 GW（IT 電力） | B101: GW | D101: =D99/D100 -> 23.399538 | E101: =E99/E100 -> 41.646766 | F101: =F99/F100 -> 42.233711 | G101: =G99/G100 -> 51.117803
A102: 每 GW PCB：加速器卡／運算板 | B102: US$M/GW | D102: =vg_cmp26 -> 280 | E102: =(vg_cmp26+(vg_cmp27-vg_cmp26)*pgwf_hi) -> 462 | F102: =(vg_cmp26+(vg_cmp28-vg_cmp26)*pgwf_hi) -> 516.6 | G102: =(vg_cmp26+(vg_cmp29-vg_cmp26)*pgwf_hi) -> 571.2
A103: 每 GW PCB：交換器板 | B103: US$M/GW | D103: =vg_sw26 -> 120 | E103: =(vg_sw26+(vg_sw27-vg_sw26)*pgwf_hi) -> 174.6 | F103: =(vg_sw26+(vg_sw28-vg_sw26)*pgwf_hi) -> 198 | G103: =(vg_sw26+(vg_sw29-vg_sw26)*pgwf_hi) -> 221.4
A104: 每 GW PCB：中板／背板／其他 × 金像電參與係數 | B104: US$M/GW | D104: =vg_mid26*w_mid -> 25 | E104: =(vg_mid26+(vg_mid27-vg_mid26)*pgwf_hi)*w_mid -> 57.5 | F104: =(vg_mid26+(vg_mid28-vg_mid26)*pgwf_hi)*w_mid -> 90 | G104: =(vg_mid26+(vg_mid29-vg_mid26)*pgwf_hi)*w_mid -> 106.25
A105: 每 GW 金像電可參與 AI 高速 PCB 金額（三項合計） | B105: US$M/GW | D105: =D102+D103+D104 -> 425 | E105: =E102+E103+E104 -> 694.1 | F105: =F102+F103+F104 -> 804.6 | G105: =G102+G103+G104 -> 898.85
A106: 可參與 AI 高速 PCB 市場（美元；不含價格指數） | B106: US$B | D106: =D101*D105/1000 -> 9.9448037 | E106: =E101*E105/1000 -> 28.90702 | F106: =F101*F105/1000 -> 33.981244 | G106: =G101*G105/1000 -> 45.947237
A107: 可參與 AI 高速 PCB 市場（新台幣） | B107: NT$B | D107: =D106*fx -> 318.23372 | E107: =E106*fx -> 925.02465 | F107: =F106*fx -> 1087.3998 | G107: =G106*fx -> 1470.3116
A108: PCB 價格指數（FY2026＝1） | B108: x | D108: =1 -> 1 | E108: =pp_27 -> 1 | F108: =pp_28 -> 0.97 | G108: =pp_29 -> 0.94
A109: 金像電有效份額（FY2026 校準）＝ AI 相關營收 ÷ 可參與市場 | B109: % | D109: =a26_ai/D107 -> 0.17284202 | K109: Derived：分子為 FY2026 錨點營收 − 非 AI；分母為本模型的可參與市場（含 ASIC）
A110: 份額相對值（÷ FY2026） | B110: x | D110: =1 -> 1 | E110: =rel_27 -> 1 | F110: =rel_28 -> 0.95 | G110: =rel_29 -> 0.9
A111: 金像電有效份額 | B111: % | D111: =$D$109*D110 -> 0.17284202 | E111: =$D$109*E110 -> 0.17284202 | F111: =$D$109*F110 -> 0.16419992 | G111: =$D$109*G110 -> 0.15555782
A112: AI 相關營收（需求面）＝ 市場 × 份額 × 價格指數 | B112: NT$B | D112: =D107*D111*D108 -> 55.00416 | E112: =E107*E111*E108 -> 159.88313 | F112: =F107*F111*F108 -> 173.19443 | G112: =G107*G111*G108 -> 214.99536
A113: B. 產能上限（全產全銷）與營收
A114: 平均產值產能指數（FY2026 營收＝1） | B114: x | D114: =1 -> 1 | E114: =cx_27 -> 1.45 | F114: =cx_28 -> 1.9 | G114: =cx_29 -> 2.3 | K114: FY2026 校準：公司稱產能吃緊、產線滿載，FY2026 營收視為產能（Derived）
A115: 產能上限營收 ＝ FY2026 營收 × 產能指數 × 價格指數 | B115: NT$B | D115: =a26_rev*D114*D108 -> 105.40752 | E115: =a26_rev*E114*E108 -> 152.8409 | F115: =a26_rev*F114*F108 -> 194.26606 | G115: =a26_rev*G114*G108 -> 227.89106
...

Sheet Sources
A1: 來源（公司原文＝金像電財報、月營收公告與法說會，經資料商與媒體轉述；券商與媒體估計皆為 Interested-party）
A2: 二手：優分析 2026-08-11（1H26、2Q26 營收、毛利率、淨利、EPS；7 月營收） | B2: https://uanalyze.com.tw/articles/7465753217
A3: 資料商：stockanalysis 季度損益（1Q25–1Q26 營收、毛利、營業利益、稅前淨利率、淨利） | B3: https://stockanalysis.com/quote/tpe/2368/financials/?p=quarterly
A4: 二手：technews 2026-10-08（9 月營收 93.20 億、前 9 月 733.79 億） | B4: https://finance.technews.tw/2026/10/08/gce-2368-202609-financial-report/
A5: 二手：優分析 2026-09-09（8 月營收、AI 占比約五成、泰國廠產值、2026 資本支出、中壢新廠、ASIC 設計風險） | B5: https://uanalyze.com.tw/articles/6187254928
A6: 二手：優分析 2026-10-05（Amazon 私募、79 億元資本支出） | B6: https://uanalyze.com.tw/articles/9313556134
A7: 二手：理財周刊 2026-10-14（3Q26 營收、2Q26 營業利益率與淨利率、FactSet EPS 中位數、Amazon 私募股數） | B7: https://www.moneyweekly.com.tw/_Article?AID=255441
A8: 二手：理財周刊 2026-09-23（2026 資本支出 190 億、各廠擴產時程、產能年增） | B8: https://www.moneyweekly.com.tw/_Article?AID=250910
A9: 二手：優分析 2026-03-10（FY2025 營收、毛利率、淨利、EPS 19.47、股利、擴產） | B9: https://uanalyze.com.tw/articles/8548248766
A10: 二手：經濟日報 2026-03-11（FY2025 淨利、4Q25） | B10: https://money.udn.com/money/amp/story/5607/9371693
A11: 公司法說（富果整理 2025-11-28；3Q25 產品組合、資本支出、生產基地） | B11: https://blog.fugle.tw/post/earnings-call-2368-2025-11-28
A12: 二手：鉅亨 2025-09-26（可轉債逾 90 億元、泰國一二期） | B12: https://m.cnyes.com/news/id/6169890
A13: 券商：外資（technews 2026-05-13；FY2027 EPS 65.39、目標價 1,310） | B13: https://finance.technews.tw/2026/05/13/three-pillars/
... A19: 資料商：HiStock（12 月 P/E 2021–2025；年度 EPS 2018–2025） | B19: https://histock.tw/stock/2368/%E6%9C%AC%E7%9B%8A%E6%AF%94
A20: 市場層：markets/network、markets/chip_bridge、tsmc 成品；victory_giant 成品（每 GW PCB 金額）、emc 成品（台光電每 GW CCL，Recon 用）（本 repo，唯讀）
A21: 無法取得：companiesmarketcap 金像電 P/E 頁（網站錯誤）；10-23 收盤 | B21: 未找到
A22: 待補（人工）：3Q26 財報與法說（11 月上旬）；10 月營收（11-10 前後）；分產品（AI 伺服器、交換器）營收與毛利率；2016–2020 營收與淨利；產能（萬㎡）與產值的公司原文；可轉債轉換價；資本支出與折舊路徑；前瞻 P/E 十年歷史（Bloomberg） | B22: 未找到
A23: SemiAnalysis | B23: 未使用
