Workbook

Sheet README
A1: 創意電子（3443.TW）收支與估值模型 v0.1.2（AI 半導體 Project：運算層，ASIC 設計服務＋量產；台積電體系） 2026-10-25
A2: 版本：v0.1（初版）。CPU 顆數＝台積電模型的 Google TPU 顆數 × CPU 對 TPU 配比；其他 ASIC 顆數讀台積電模型、每顆核心售價讀 Broadcom 模型，份額與 Broadcom、Marvell、聯發科合計不超過 100%；車用與其他營收用簡化成長。本版未做先驗。
A3: 模型命題：創意的營收由 NRE 轉為 Google 自研 Arm CPU（Axion）的 turnkey 量產（晶圓與封裝轉售、毛利率低）。FY2026 營收約翻倍、3Q26 單季 187.5 億元；以 TPU 顆數 × CPU 配比推 CPU 顆數，再加其他 ASIC、車用與 NRE，FY2027–28 的營收與 EPS 有多少？現價約 90 倍前瞻 P/E 需要哪一條路徑？
A4: 核心問題：在市場層 TPU 顆數（CY2027 5.5 百萬顆）與 CPU 對 TPU 配比口徑下，創意 FY2027–28 的 CPU 顆數與 EPS 離法人估計（CPU 400 萬顆、FY2027 EPS 94–139 元）多遠；差距靠配比、份額還是車用；現價隱含的倍數與同業差多少。
A6: 會計年度＝日曆年，FY(t)＝CY(t)，不平移。FY2025A 實績、FY2026 錨點、FY2027–FY2029 驅動因子推導、FY2030–FY2032 收斂法。金額：十億新台幣；EPS：新台幣（基本）。口徑：歸屬母公司淨利（TIFRS）。3Q26 財報 2026-10-29 公布，本版只納入 3Q26 營收實績。
A8: 驅動因子 → 推導量（全部唯讀上游，不修改）
A9: Google CPU 量產：tsmc 成品的 Google TPU 顆數 × 情境係數（CY2028–29；tsmc／markets/memory 同字母）× CPU 對 TPU 配比（CY2026 0.325 校準；CY2027 起 A／B／C 0.6／0.5／0.4）× 創意份額（CY2028 起 100%／90%／70%）× 每顆營收 1.0K（CY2028 起 ×1.2／1.1／1.0）× k_c（FY2026 以錨點 CPU 拆分 48% 校準）× 匯率 32。
A10: AI ASIC 量產：tsmc 成品的其他 ASIC 顆數 × 創意份額（CY2026 3%；CY2027 6%／4%／2%；CY2028 起 8%／5%／2%）× Broadcom 模型核心售價 6K × k_o。車用：FY2026 錨點（營收 5%）× FY2027 ×4.0／3.0／2.0、FY2028 ×2.0／1.6／1.2。其他（NRE＋其他量產）：FY2027 +15%／+8%／−5%、之後 +10%／+5%／0%。
A11: 毛利：AI 量產（CPU、AI ASIC）毛利率 13%（Assumed；情境 A +1pt、C −2pt）、車用 16%；其他營收毛利率為 FY2026 殘差（Derived，含 NRE）後沿用。營業費用彈性 0.3、年增下限 8%；營業外 0.5、稅率 15%、股數 134.01M。
A12: 校準：FY2026 ＝ 1H26 實績＋3Q26 營收實績（月營收）＋公司方向性說法（3Q 毛利率較 2Q 下滑、費用持平）＋4Q26 假設（營收季增 35%、毛利率 18.5%）。營收拆分（CPU 48%、AI ASIC 3%、車用 5%）為 Assumed。不用券商數字（只在 Recon 對帳）。
A13: 估值：Val 第 0 節目標價＝0.5 × DCF 目標價（股東現金流＝EPS ×（1 − g／ROE），FY2027–32 明確期＋永續，r 10%、g 4%，三情境權重 0.3／0.5／0.2，情境價值負值取 0）＋0.5 × Comparable 目標價（世芯、聯發科、博通、邁威爾前瞻 P/E 中位數 × 12 個月後前瞻 EPS；不含 A 股）；另列 Comparable 單獨目標價、市場共識目標價與差距拆解。十年 P/E 規則值 × FY2027 EPS 保留為參考（不是目標價）。本版未做先驗，無 Andy 合理 P/E 對照。
A14: 預估期間：FY2027–FY2029 由驅動因子推導；FY2030 起為收斂法，非驅動因子推導（營收年增由 FY2029 線性收斂到 fade_g、淨利率收斂到 fade_m，FY2032 達到；PL 頁灰底）。十年平均淨利率未找到，B、C 依工作單以 FY2029 × 0.8 代替。
... A22: v0.1.1（2026-10-25）：補上檔空間級距、投資建議、重點觀察（數值不變）。Val 頁末新增「上檔空間級距」「投資建議」兩列（Andy 2026-10-25 14:00、14:17 固定規則），README 頁末新增投資建議與重點觀察三點；既有儲存格位置與數值不變。
A23: ="投資建議："&Val!B135&"（依上檔空間固定規則）" -> 投資建議：放空（依上檔空間固定規則）
A24: ="重點觀察 1：目標價 NT$"&TEXT(Val!$B$39,"#,##0.00")&"（DCF "&TEXT(Val!$B$24,"#,##0.00")&"、Comparable（相對倍數調整後）"&TEXT(tp_comp_adj,"#,##0.00")&"；DCF 權重 "&TEXT(tp_w_dcf,"0%")&"），比現價 "&TEXT(px,"#,##0.00")&"（2026-10-22）"&IF(Val!$B$42>=0,"高 "&TEXT(Val!$B$42,"0.0%"),"低 "&TEXT(-Val!$B$42,"0.0%"))&"，級距 "&Val!$B$134&"、投資建議 "&Val!$B$135&"。相對倍數調整係數 "&TEXT(rm_factor,"0.00")&"（本公司 10 年前瞻倍數中位數 ÷ 同業的中位數，夾在 0.5–2.0；Val 第 0.5 節），調整前加權上檔空間 "&TEXT((tp_w_dcf*Val!$B$24+(1-tp_w_dcf)*Val!$B$35)/px-1,"+0.0%;−0.0%")&"；Comparable 單獨（市場主流同業法、未調整）為 "&TEXT(Val!$B$43,"+0.0%;−0.0%")&"。"&"以下為 2026-10-29 相對倍數調整前撰寫的說明，其中數字為調整前：目標價 NT$3,968（DCF 2,268、Comparable 相對倍數調整後 5,668 各半），比現價 7,585（2026-10-22）低 47.7%，級距 −25%～−50%，投資建議維持放空。v0.2 滾入 3Q26 實績（營收 187.5 億、毛利率 20.58%、EPS 16.95；前三季 EPS 40.8"&"4）：毛利率與營業外收入高於原假設，FY2026 EPS 60.7 → 62.2，加權目標價 3,911 → 3,968（+1.5%）。" -> 重點觀察 1：目標價 NT$3,968.04（DCF 2,267.79、Comparable（相對倍數調整後）5,668.29；DCF 權重 50%），比現價 7,585.00（2026-10-22）低 47.7%，級距 −25%～−50%、投資建議 放空。相對倍數調整係數 1.59（本公司 10 年前瞻倍數中位數 ÷ 同業的中位數，夾在 0.5–2.0；Val 第 0.5 節），調整前加權上檔空間 −61.5%；Comparable 單獨（市場主流同業法、未調整）為 −52.9%。以下為 2026-10-29 相對倍數調整前撰寫的說明，其中數字為調整前：目標價 NT$3,968（DCF 2,268、Comparable 相對倍數調整後 5,668 各半），比現價 7,585（2026-10-22）低 47.7%，級距 −25%～−50%，投資建議維持放空。v0.2 滾入 3Q26 實績（營收 187.5 億、毛利率 20.58%、EPS 16.95；前三季 EPS 40.84）：毛利率與營業外收入高於原假設，FY2026 EPS 60.7 → 62.2，加權目標價 3,911 → 3,968（+1.5%）。
A25: 重點觀察 2：情境分歧最大：FY2028 EPS A／B／C 為 199.7／115.2／52.0，DCF 情境價值 3,785／1,992／682；即使 A 情境 DCF 也只有現價的 50%。12 個月後前瞻 EPS 124.8，同業前瞻 P/E 中位數下的 Comparable 為 3,573（未調整），市場給創意的 Google CPU 成長溢價本模型只以相對倍數調整部分反映。
A26: 重點觀察 3：4Q26 仍為假設（營收季增 35%、毛利率 18.5%；公司未給季度區間指引）；CPU 對 TPU 配比是 FY2027 EPS 最敏感的變數（Sens 頁）。下一個檢驗點是 10–12 月月營收與 4Q26 財報（2027-02）。
A27: v0.1.2（2026-10-28）：分部原則重建（數值不變）。創意為單一應報導部門；Q 頁第 33 列起追加 FY2025 部門營收、營收類別（NRE 約 34%、Turnkey 約 64%，經濟日報轉述）與核對列「分部合計 − 合併營收」。推估年仍以 Google CPU／AI ASIC／車用／其他拆分，不拆 NRE／Turnkey。
A29: 2026-10-29：加權目標價中的 Comparable 改用相對倍數調整後的值（Val 第 0.5 節：同業前瞻倍數中位數 × 本公司 10 年相對同業的倍數比，Bloomberg 前瞻倍數；Andy 2026-10-27「照建議做」、10-29 資料取回）。「Comparable 目標價（市場主流同業法）」維持不調整。重點觀察 1 的第一句已改為公式；重點觀察 2、3 與其他說明中的目標價與上檔空間數字為調整前撰寫，以 Val 頁為準。
A31: v0.2（2026-10-31）：滾入 3Q26 實績（2026-10-29 財報：前三季營收 440.99 億、毛利 99.68 億、營業利益 60.52 億、淨利 54.73 億、EPS 40.84；3Q26＝前三季 − 上半年：營收 187.5 億、毛利率 20.58%、營業利益 25.54 億、EPS 16.95）；FY2026 EPS 60.7 → 62.2，加權目標價 3,911 → 3,968，投資建議維持放空。
A33: v0.1.3（2026-10-30）：依個股模型原則第 8 節調整 In 頁呈現（數值不變）。In 頁 D／F 欄名改「敏感度低」「敏感度高」（只用於 Sens 頁、不進目標價）；In 頁最後新增「情境驅動對照」一節，把上方各情境專屬輸入三情境並排（只引用上方各列，純展示）；HTML 驅動因子一節分「情境驅動」與「單一參數」兩張表。

Sheet In
A1: In — 輸入（藍字；基準欄 E，低 D、高 F）。金額：十億新台幣（NT$B）；每顆價格：千美元（US$K）；顆數：百萬顆；匯率：新台幣／美元。每個輸入附兩個來源（找不到者寫「未找到」）；公司原文算一個。【v0.1.3】基準欄 E 進主模型；D／F＝敏感度低／高，只用於 Sens 頁（一次動一個參數）、不進目標價；情境 A／B／C 的驅動見本頁最後一節「情境驅動對照」。
A2: 標記：Verified／Interested-party／Analogy／Assumed／Derived；Analogy、Assumed 給低／高區間，不當點估計（放情境或 Sens）。SemiAnalysis 未使用。公司財報與法說內容多取自媒體轉述（公司自 2026 年起不再給季度區間指引）；公司說法為 Interested-party；券商、資料商、媒體為 Interested-party
A3: 鍵 | B3: 項目 | C3: 單位 | D3: 敏感度低 | E3: 基準 | F3: 敏感度高 | G3: 標記 | H3: 來源1 | I3: 來源2／說明
A4: A. AI 加速器顆數（tsmc 成品；與 HBM、台積電、Broadcom、Marvell、聯發科模型同一份；情境係數讀台積電模型＝markets/memory SCEN_UNITS，不另訂）
A5: u_tpu_26 | B5: Google TPU 顆數 CY2026 | C5: 百萬顆 | E5: 3.85 | G5: Interested-party | H5: tsmc/dist/20261030_台積電個股模型_v0.4.1.xlsx｜In!E25 | I5: avgo 成品同值、markets/memory UNITS 同值（建置時檢查）
A6: u_tpu_27 | B6: Google TPU 顆數 CY2027 | C6: 百萬顆 | E6: 5.5 | G6: Interested-party | H6: tsmc/dist/20261030_台積電個股模型_v0.4.1.xlsx｜In!E26 | I6: 同上
A7: u_tpu_28 | B7: Google TPU 顆數 CY2028 | C7: 百萬顆 | E7: 7 | G7: Interested-party | H7: tsmc/dist/20261030_台積電個股模型_v0.4.1.xlsx｜In!E27 | I7: 同上
A8: g29_tpu | B8: Google TPU CY2029 顆數成長 | C8: % | E8: 0.15 | G8: Assumed | H8: tsmc/dist/20261030_台積電個股模型_v0.4.1.xlsx｜In!E28 | I8: markets/memory 無 2029；沿用台積電模型
A9: u_oth_26 | B9: 其他 ASIC（MTIA、Maia、Ascend 等） 顆數 CY2026 | C9: 百萬顆 | E9: 1 | G9: Derived／Assumed | H9: tsmc/dist/20261030_台積電個股模型_v0.4.1.xlsx｜In!E33 | I9: avgo 成品同值、markets/memory UNITS 同值（建置時檢查）
A10: u_oth_27 | B10: 其他 ASIC（MTIA、Maia、Ascend 等） 顆數 CY2027 | C10: 百萬顆 | E10: 4.5 | G10: Derived／Assumed | H10: tsmc/dist/20261030_台積電個股模型_v0.4.1.xlsx｜In!E34 | I10: 同上
A11: u_oth_28 | B11: 其他 ASIC（MTIA、Maia、Ascend 等） 顆數 CY2028 | C11: 百萬顆 | E11: 5 | G11: Derived／Assumed | H11: tsmc/dist/20261030_台積電個股模型_v0.4.1.xlsx｜In!E35 | I11: 同上
A12: g29_oth | B12: 其他 ASIC（MTIA、Maia、Ascend 等） CY2029 顆數成長 | C12: % | E12: 0.15 | G12: Assumed | H12: tsmc/dist/20261030_台積電個股模型_v0.4.1.xlsx｜In!E36 | I12: markets/memory 無 2029；沿用台積電模型
A13: um28_A | B13: 情境 A：CY2028 顆數 ÷ 基準 | C13: x | E13: 1 | G13: Assumed | H13: tsmc/dist/20261030_台積電個股模型_v0.4.1.xlsx｜In!E37 | I13: A＝基準；B＝AI 資本支出消化；C＝明顯下修（與台積電、Broadcom、Marvell、聯發科模型相同；markets/memory SCEN_UNITS，建置時檢查）
A14: um29_A | B14: 情境 A：CY2029 顆數 ÷ 基準 | C14: x | E14: 1 | G14: Assumed | H14: tsmc/dist/20261030_台積電個股模型_v0.4.1.xlsx｜In!E38 | I14: 同上
A15: um28_B | B15: 情境 B：CY2028 顆數 ÷ 基準 | C15: x | E15: 0.8 | G15: Assumed | H15: tsmc/dist/20261030_台積電個股模型_v0.4.1.xlsx｜In!E39 | I15: 同上
A16: um29_B | B16: 情境 B：CY2029 顆數 ÷ 基準 | C16: x | E16: 0.85 | G16: Assumed | H16: tsmc/dist/20261030_台積電個股模型_v0.4.1.xlsx｜In!E40 | I16: 同上
... A18: um29_C | B18: 情境 C：CY2029 顆數 ÷ 基準 | C18: x | E18: 0.6 | G18: Assumed | H18: tsmc/dist/20261030_台積電個股模型_v0.4.1.xlsx｜In!E42 | I18: 同上
A19: B. Google 自研 Arm CPU（Axion）量產：CPU 顆數＝TPU 顆數 × CPU 對 TPU 配比 × 創意份額（CPU 不占 TPU 加速器份額）
A20: att26 | B20: CY2026 CPU 對 TPU 配比（CPU 顆數 ÷ TPU 顆數；校準年） | C20: x | D20: 0.25 | E20: 0.325 | F20: 0.4 | G20: Interested-party | H20: 經濟日報 2026-10-07（3Q26 營收、CPU 出貨估計）：2026 年 CPU 出貨約 125 萬顆（法人估計）÷ 市場層 TPU 3.85 百萬顆 | I20: CY2026 只用於校準（k_c 吸收）；公司未揭露客戶與顆數
A21: att_A | B21: CY2027 起 CPU 對 TPU 配比（情境 A） | C21: x | D21: 0.25 | E21: 0.6 | F21: 0.75 | G21: Assumed | H21: 經濟日報 2026-10-07（3Q26 營收、CPU 出貨估計）：新平台 CPU 對 TPU 配置由 1:4 提升到 1:2（法人） | I21: 經濟日報 2026-04-28（本國投顧：2027 營收結構）：第八代 AI ASIC 伺服器由每顆 x86 CPU 配 4 或 8 顆 ASIC 改為每顆 Arm CPU 配 2 顆（本國投顧）；A 另含一般運算 Axion 執行個體
A22: att_B | B22: CY2027 起 CPU 對 TPU 配比（情境 B） | C22: x | E22: 0.5 | G22: Assumed | H22: 同上 | I22: A 最有利、C 最不利
A23: att_C | B23: CY2027 起 CPU 對 TPU 配比（情境 C） | C23: x | E23: 0.4 | G23: Assumed | H23: 同上 | I23: A 最有利、C 最不利
A24: gsh26 | B24: 創意占 Google 自研 CPU 顆數 CY2026–27 | C24: % | D24: 0.8 | E24: 1 | F24: 1 | G24: Assumed | H24: 公司：最大 CPU 客戶產能已確保（2026-01-30 法說，工商時報轉述） | I24: 二手：Google Arm CPU 專案為創意（經濟日報 2026-01-31）；客戶名稱公司未揭露
A25: gsh28_A | B25: 創意占 Google 自研 CPU 顆數 CY2028 起（情境 A；下一代 CPU） | C25: % | D25: 0.5 | E25: 1 | F25: 1 | G25: Assumed | H25: 下一代 CPU 的設計夥伴：未找到 | I25: C＝下一代 CPU 部分轉給其他夥伴或客戶自行設計（COT）
A26: gsh28_B | B26: 創意占 Google 自研 CPU 顆數 CY2028 起（情境 B；下一代 CPU） | C26: % | E26: 0.9 | G26: Assumed | H26: 同上 | I26: A 最有利、C 最不利
A27: gsh28_C | B27: 創意占 Google 自研 CPU 顆數 CY2028 起（情境 C；下一代 CPU） | C27: % | E27: 0.7 | G27: Assumed | H27: 同上 | I27: A 最有利、C 最不利
A28: pc_cpu | B28: 每顆 CPU 營收（turnkey：晶圓＋封裝測試轉售；未校準） | C28: US$K | D28: 0.7 | E28: 1 | F28: 1.5 | G28: Assumed | H28: 公司未揭露；3 奈米大型 Arm CPU 晶圓與封裝成本（Assumed） | I28: 校準係數 k_c 以 FY2026 CPU 營收吸收單價誤差
A29: pfc_A | B29: CY2028 起每顆 CPU 營收係數（下一代 CPU；情境 A） | C29: x | D29: 0.8 | E29: 1.2 | F29: 1.5 | G29: Assumed | H29: 公司：第四季開始出貨下一代 CPU 產品（經濟日報 2026-10-07 轉述法人） | I29: 下一代製程與單價：未找到
A30: pfc_B | B30: CY2028 起每顆 CPU 營收係數（下一代 CPU；情境 B） | C30: x | E30: 1.1 | G30: Assumed | H30: 同上 | I30: A 最有利、C 最不利
A31: pfc_C | B31: CY2028 起每顆 CPU 營收係數（下一代 CPU；情境 C） | C31: x | E31: 1 | G31: Assumed | H31: 同上 | I31: A 最有利、C 最不利
A32: uf | B32: 創意 CPU 與 AI ASIC 顆數係數（Sens 用；CY2027 起） | C32: x | D32: 0.8 | E32: 1 | F32: 1.2 | G32: Assumed | H32: 無 | I32: ±20%
A33: C. AI ASIC 量產（其他 ASIC：Maia 等）：每顆規格讀 Broadcom 模型（唯讀）；份額與 Broadcom、Marvell、聯發科合計 ≤ 100%
A34: core_oth | B34: 其他 ASIC 每顆核心售價（不含 HBM） | C34: US$K | D34: 4 | E34: 6 | F34: 9 | G34: Assumed | H34: avgo/dist/20261030_Broadcom個股模型_v0.3.1.xlsx｜In!E57 | I34: Broadcom 模型的 ASIC 每顆規格（本專案權威）；創意 turnkey 只含晶圓與封裝轉售，以 k_o 校準
A35: av_oth_26 | B35: Broadcom 占其他 ASIC 顆數 CY2026（份額加總檢查用） | C35: % | E35: 0.35 | G35: Assumed | H35: avgo/dist/20261030_Broadcom個股模型_v0.3.1.xlsx｜In!E53 | I35: Broadcom 模型
A36: mv_oth_26 | B36: Marvell 占其他 ASIC 顆數 CY2026（份額加總檢查用） | C36: % | E36: 0.05 | G36: Assumed | H36: mrvl/dist/20261030_邁威爾個股模型_v0.2.4.xlsx｜In!E48 | I36: Marvell 模型
A37: mk_oth_26 | B37: 聯發科占其他 ASIC 顆數 CY2026（高值；份額加總檢查用） | C37: % | E37: 0.02 | G37: Assumed | H37: mediatek/dist/20261030_聯發科個股模型_v0.1.3.xlsx｜In!F45 | I37: 聯發科模型高值（基準 0）；世芯模型只有 Trainium 份額，其他 ASIC 為 0
A38: av_oth_27 | B38: Broadcom 占其他 ASIC 顆數 CY2027（份額加總檢查用） | C38: % | E38: 0.55 | G38: Assumed | H38: avgo/dist/20261030_Broadcom個股模型_v0.3.1.xlsx｜In!E54 | I38: Broadcom 模型
A39: mv_oth_27 | B39: Marvell 占其他 ASIC 顆數 CY2027（份額加總檢查用） | C39: % | E39: 0.06 | G39: Assumed | H39: mrvl/dist/20261030_邁威爾個股模型_v0.2.4.xlsx｜In!E49 | I39: Marvell 模型
A40: mk_oth_27 | B40: 聯發科占其他 ASIC 顆數 CY2027（高值；份額加總檢查用） | C40: % | E40: 0.03 | G40: Assumed | H40: mediatek/dist/20261030_聯發科個股模型_v0.1.3.xlsx｜In!F46 | I40: 聯發科模型高值（基準 0）；世芯模型只有 Trainium 份額，其他 ASIC 為 0
A41: av_oth_28 | B41: Broadcom 占其他 ASIC 顆數 CY2028（份額加總檢查用） | C41: % | E41: 0.55 | G41: Assumed | H41: avgo/dist/20261030_Broadcom個股模型_v0.3.1.xlsx｜In!E55 | I41: Broadcom 模型
A42: mv_oth_28 | B42: Marvell 占其他 ASIC 顆數 CY2028（份額加總檢查用） | C42: % | E42: 0.15 | G42: Assumed | H42: mrvl/dist/20261030_邁威爾個股模型_v0.2.4.xlsx｜In!E50 | I42: Marvell 模型
A43: mk_oth_28 | B43: 聯發科占其他 ASIC 顆數 CY2028（高值；份額加總檢查用） | C43: % | E43: 0.05 | G43: Assumed | H43: mediatek/dist/20261030_聯發科個股模型_v0.1.3.xlsx｜In!F47 | I43: 聯發科模型高值（基準 0）；世芯模型只有 Trainium 份額，其他 ASIC 為 0
A44: av_tpu_26 | B44: Broadcom＋Marvell＋聯發科占 Google TPU 顆數 CY2026（基準；對照） | C44: % | E44: 0.95 | G44: Derived | H44: avgo、mrvl、mediatek 成品 In 頁 | I44: 創意不占 TPU 加速器份額（CPU 另計）
A45: av_tpu_27 | B45: Broadcom＋Marvell＋聯發科占 Google TPU 顆數 CY2027（基準；對照） | C45: % | E45: 0.95 | G45: Derived | H45: avgo、mrvl、mediatek 成品 In 頁 | I45: 創意不占 TPU 加速器份額（CPU 另計）
A46: av_tpu_28 | B46: Broadcom＋Marvell＋聯發科占 Google TPU 顆數 CY2028（基準；對照） | C46: % | E46: 0.98 | G46: Derived | H46: avgo、mrvl、mediatek 成品 In 頁 | I46: 創意不占 TPU 加速器份額（CPU 另計）
A47: guc_oth_26 | B47: 創意占其他 ASIC 顆數 CY2026（三情境相同，校準年） | C47: % | D47: 0.01 | E47: 0.03 | F47: 0.06 | G47: Assumed | H47: 美銀：Microsoft Maia 200 開始貢獻營收（科技新報 2026-05-08，Interested-party） | I47: CY2026 份額只用於校準（k_o 吸收）；公司未揭露客戶
A48: go27_A | B48: 創意占其他 ASIC 顆數 CY2027（情境 A） | C48: % | D48: 0 | E48: 0.06 | F48: 0.1 | G48: Assumed | H48: 同上 | I48: A 最有利、C 最不利；高值受 1 − Broadcom − Marvell − 聯發科高值限制
A49: go27_B | B49: 創意占其他 ASIC 顆數 CY2027（情境 B） | C49: % | D49: 0 | E49: 0.04 | F49: 0.1 | G49: Assumed | H49: 同上 | I49: —
A50: go27_C | B50: 創意占其他 ASIC 顆數 CY2027（情境 C） | C50: % | D50: 0 | E50: 0.02 | F50: 0.1 | G50: Assumed | H50: 同上 | I50: —
A51: go28_A | B51: 創意占其他 ASIC 顆數 CY2028（情境 A；CY2029 沿用） | C51: % | D51: 0 | E51: 0.08 | F51: 0.12 | G51: Assumed | H51: 同上 | I51: A 最有利、C 最不利；高值受 1 − Broadcom − Marvell − 聯發科高值限制
A52: go28_B | B52: 創意占其他 ASIC 顆數 CY2028（情境 B；CY2029 沿用） | C52: % | D52: 0 | E52: 0.05 | F52: 0.12 | G52: Assumed | H52: 同上 | I52: —
A53: go28_C | B53: 創意占其他 ASIC 顆數 CY2028（情境 C；CY2029 沿用） | C53: % | D53: 0 | E53: 0.02 | F53: 0.12 | G53: Assumed | H53: 同上 | I53: —
A54: m_tk | B54: AI 量產（CPU、AI ASIC turnkey）毛利率 | C54: x | D54: 0.1 | E54: 0.13 | F54: 0.16 | G54: Assumed | H54: 公司：turnkey 毛利率低於其他業務、2Q26 turnkey 占 83%、毛利率 21.6%（經濟日報 2026-07-30） | I54: Q 頁核對：以 13% 推得其他業務毛利率約 30%（含 NRE）
A55: gta_A | B55: AI 量產毛利率調整（FY2027 起；情境 A） | C55: pt | E55: 0.01 | G55: Assumed | H55: 公司：毛利率受 turnkey 比重壓抑、營業利益率維持穩定（優分析 2026-09-22） | I55: A 最有利、C 最不利
A56: gta_B | B56: AI 量產毛利率調整（FY2027 起；情境 B） | C56: pt | E56: 0 | G56: Assumed | H56: 同上 | I56: A 最有利、C 最不利
A57: gta_C | B57: AI 量產毛利率調整（FY2027 起；情境 C） | C57: pt | E57: -0.02 | G57: Assumed | H57: 同上 | I57: A 最有利、C 最不利
A58: D. 車用（含北美車用客戶 AI 晶片，2H27 起量產）與其他營收（NRE＋BMC、SSD 控制器、加密貨幣等量產）：簡化成長（FY2027 起；情境別）
A59: am27_A | B59: 車用營收 FY2027 ÷ FY2026（情境 A） | C59: x | D59: 1.5 | E59: 4 | F59: 5 | G59: Assumed | H59: 公司：車用 2026 年占營收個位數、2027 年雙位數；北美專案金額大，主要在 2H27 後貢獻（優分析 2026-09-22） | I59: 科技新報 2026-05-05（摩根士丹利）：北美車用 AI 晶片 2H26 認證、明年中量產（Interested-party）
A60: am28_A | B60: 車用營收 FY2028 ÷ FY2027（情境 A） | C60: x | E60: 2 | G60: Assumed | H60: 2H27 量產的全年效果 | I60: —
A61: ag29_A | B61: 車用營收年增 FY2029（情境 A） | C61: % | E61: 0.2 | G61: Assumed | H61: 同上 | I61: —
A62: am27_B | B62: 車用營收 FY2027 ÷ FY2026（情境 B） | C62: x | E62: 3 | G62: Assumed | H62: 同上 | I62: —
A63: am28_B | B63: 車用營收 FY2028 ÷ FY2027（情境 B） | C63: x | E63: 1.6 | G63: Assumed | H63: 同上 | I63: —
A64: ag29_B | B64: 車用營收年增 FY2029（情境 B） | C64: % | E64: 0.1 | G64: Assumed | H64: 同上 | I64: —
A65: am27_C | B65: 車用營收 FY2027 ÷ FY2026（情境 C） | C65: x | E65: 2 | G65: Assumed | H65: 同上 | I65: —
A66: am28_C | B66: 車用營收 FY2028 ÷ FY2027（情境 C） | C66: x | E66: 1.2 | G66: Assumed | H66: 同上 | I66: —
A67: ag29_C | B67: 車用營收年增 FY2029（情境 C） | C67: % | E67: 0 | G67: Assumed | H67: 同上 | I67: —
A68: m_auto | B68: 車用量產毛利率 | C68: x | D68: 0.13 | E68: 0.16 | F68: 0.2 | G68: Assumed | H68: 科技新報 2026-05-05（摩根士丹利）：北美車用 AI 晶片毛利率高於 15%（Interested-party） | I68: 經濟日報 2026-10-07：北美車用專案 2H27 明顯改善獲利結構（法人）
A69: g_o27_A | B69: 其他營收年增 FY2027（情境 A） | C69: % | D69: -0.15 | E69: 0.15 | F69: 0.25 | G69: Assumed | H69: 公司：FY2026 NRE 年增 15–19%（優分析 2026-09-22）；BMC 占營收高個位數；加密貨幣降為個位數 | I69: 公司：2 奈米 HBM4 PHY、共同封裝光學（COUPE）認證（經濟日報 2026-09-08）
A70: g_oL_A | B70: 其他營收年增 FY2028–29（情境 A） | C70: % | D70: -0.15 | E70: 0.1 | F70: 0.25 | G70: Assumed | H70: 同上 | I70: —
A71: g_o27_B | B71: 其他營收年增 FY2027（情境 B） | C71: % | D71: -0.15 | E71: 0.08 | F71: 0.25 | G71: Assumed | H71: 同上 | I71: —
A72: g_oL_B | B72: 其他營收年增 FY2028–29（情境 B） | C72: % | D72: -0.15 | E72: 0.05 | F72: 0.25 | G72: Assumed | H72: 同上 | I72: —
A73: g_o27_C | B73: 其他營收年增 FY2027（情境 C） | C73: % | D73: -0.15 | E73: -0.05 | F73: 0.25 | G73: Assumed | H73: 同上 | I73: —
A74: g_oL_C | B74: 其他營收年增 FY2028–29（情境 C） | C74: % | D74: -0.15 | E74: 0 | F74: 0.25 | G74: Assumed | H74: 同上 | I74: —
A75: gmadj | B75: 其他營收毛利率調整（Sens 用；基準 0） | C75: pt | D75: -0.03 | E75: 0 | F75: 0.03 | G75: Assumed | H75: 無 | I75: 其他營收毛利率為 FY2026 殘差（Derived），之後沿用
A76: E. FY2026 錨點（1H26 實績＋3Q26 營收實績＋公司方向性說法＋4Q26 假設）與營收拆分
A77: cpu_sh26 | B77: FY2026 Google CPU 量產 ÷ 營收 | C77: % | D77: 0.35 | E77: 0.48 | F77: 0.55 | G77: Assumed | H77: 公司：CPU 為最大應用、turnkey 主要成長動能（優分析 2026-09-22） | I77: 科技新報 2026-05-05（摩根士丹利）：Google CPU 占 1Q26 營收接近 50%、全年超過 50%（Interested-party）；經濟日報 2026-01-31：法人估 30% 以上
A78: asic_sh26 | B78: FY2026 AI ASIC 量產（其他 ASIC）÷ 營收 | C78: % | D78: 0.01 | E78: 0.03 | F78: 0.06 | G78: Assumed | H78: 科技新報 2026-05-08（美銀）：Maia 200 開始貢獻（Interested-party） | I78: 公司未揭露；金額：未找到
A79: auto_sh26 | B79: FY2026 車用 ÷ 營收 | C79: % | D79: 0.03 | E79: 0.05 | F79: 0.08 | G79: Interested-party | H79: 優分析 2026-09-22（法說指引轉述）：車用 2026 年占營收個位數（公司） | I79: 取中間值（Assumed）
A80: cpu_sh25 | B80: FY2025 Google CPU 量產 ÷ 營收（對照用） | C80: % | D80: 0.1 | E80: 0.18 | F80: 0.25 | G80: Assumed | H80: 經濟日報 2026-01-31（FY2025 營收結構）：2025 年 AI 相關營收約 25% | I80: 公司：CSP 占 2025 全年營收 25%（優分析 2025-10-07）；CPU 量產自 2H25
A81: asic_sh25 | B81: FY2025 AI ASIC 量產 ÷ 營收（對照用） | C81: % | E81: 0.05 | G81: Assumed | H81: AI 相關 25% 扣 CPU | I81: —
A82: auto_sh25 | B82: FY2025 車用 ÷ 營收（對照用） | C82: % | E82: 0.03 | G82: Assumed | H82: 公司：中國、歐洲 ADAS 已量產（2026-01-30 法說） | I82: —
A83: fx26 | B83: FY2026 匯率（CPU、AI ASIC 美元營收換算） | C83: NT$/US$ | D83: 30.5 | E83: 31.6 | F83: 33 | G83: Assumed | H83: 與世芯模型 FY2026 假設相同 | I83: 實際 FY2026 平均匯率：未找到
A84: q3_rev | B84: 3Q26 營收（月營收實績；7–9 月合計） | C84: NT$B | E84: =44.099-11.448-13.897 -> 18.754 | G84: Verified | H84: 科技新報（9 月營收，2026-10-05）：前 9 月 440.99 億（9 月 71.45 億） | I84: 經濟日報 2026-10-07（3Q26 營收、CPU 出貨估計）：3Q26 187.5 億、季增 34.9%
A85: q3_gm | B85: 3Q26 毛利率（實績；前三季 − 上半年） | C85: % | E85: =Q!E10 -> 0.20579684 | G85: Derived | H85: 公司 115 年第三季財報（2026-10-29 董事會；公開資訊觀測站、財訊快報）：前三季營收 44,098.9、毛利 9,967.7、營業利益 6,051.7、稅前 6,306.2、淨利 5,473.4 百萬元，EPS 40.84 | I85: 中央社 2026-10-29：第三季毛利率 20.58%、EPS 16.95
A86: q3_opx | B86: 3Q26 營業費用（實績；毛利 − 營業利益） | C86: NT$B | E86: =Q!E11 -> 1.305437 | G86: Derived | H86: 公司 115 年第三季財報（2026-10-29 董事會；公開資訊觀測站、財訊快報）：前三季營收 44,098.9、毛利 9,967.7、營業利益 6,051.7、稅前 6,306.2、淨利 5,473.4 百萬元，EPS 40.84 | I86: 公司 9 月法說：與 2Q26 約持平（2Q26 1.326）
A87: q4_g | B87: 4Q26 營收季增 | C87: % | D87: 0.15 | E87: 0.35 | F87: 0.5 | G87: Assumed | H87: 優分析 2026-09-22（法說指引轉述）：第四季季增幅度可能進一步擴大（公司） | I87: 經濟日報 2026-10-07（3Q26 營收、CPU 出貨估計）：法人估季增 35–40%；下一代 CPU 第四季開始出貨
A88: q4_gm | B88: 4Q26 毛利率 | C88: % | D88: 0.17 | E88: 0.185 | F88: 0.2 | G88: Assumed | H88: 公司：全年毛利率 20% 以上（優分析 2026-09-22） | I88: turnkey 比重續升
A89: q4_opx | B89: 4Q26 營業費用 | C89: NT$B | D89: 1.35 | E89: 1.45 | F89: 1.6 | G89: Assumed | H89: 2Q26 研發費用 10.5 億、年增 25%（經濟日報 2026-07-30） | I89: —
A90: t_h1 | B90: 1H26 有效稅率（推估稅前利益用） | C90: % | E90: =1-5.228/6.049 -> 0.13572491 | G90: Derived | H90: stockanalysis.comfinancials/：近 12 月（至 2026-06）淨利 52.28 億 ÷ 稅前約 60.49 億 | I90: 1Q、2Q26 稅前利益與所得稅：未找到
A91: q_nonop | B91: 4Q26 營業外淨額（3Q26 起為實績） | C91: NT$B | D91: 0.05 | E91: 0.13 | F91: 0.2 | G91: Assumed | H91: 1H26 約 0.27（Derived） | I91: FY2025 約 0.09（stockanalysis 推得）
A92: q_tax | B92: 4Q26 有效稅率（3Q26 起為實績） | C92: % | D92: 0.12 | E92: 0.15 | F92: 0.18 | G92: Assumed | H92: FY2025 約 15.1%（stockanalysis 推得） | I92: —
A93: q_sh | B93: 加權股數 | C93: 十億股 | E93: 0.13401 | G93: Interested-party | H93: stockanalysis.com：流通股數 134.01M（2026-10-08 擷取） | I93: FY2025 淨利 ÷ EPS ＝ 134.0M（Derived）
A94: F. FY2027 起：營業費用、營業外、稅、股數、匯率
A95: phi | B95: 營業費用成長對營收成長的彈性 | C95: x | D95: 0.2 | E95: 0.3 | F95: 0.6 | G95: Assumed | H95: 公司：營業利益率維持穩定、全年雙位數（優分析 2026-09-22） | I95: FY2026 營業費用約 +32%、營收約 +100%（Q 頁）
A96: g_opx_min | B96: 營業費用年增下限 | C96: % | D96: 0.05 | E96: 0.08 | F96: 0.12 | G96: Assumed | H96: 研發年增 25%（2Q26）；先進封裝 IP、自建運算中心（2026-01-30 法說） | I96: —
A97: opx_adj | B97: 營業費用額外占營收比（Sens 用；基準 0） | C97: pt | D97: -0.02 | E97: 0 | F97: 0.02 | G97: Assumed | H97: 無 | I97: Sens 用 +2 個百分點
A98: nonop_f | B98: 營業外淨額（每年） | C98: NT$B | D98: 0.2 | E98: 0.5 | F98: 0.8 | G98: Assumed | H98: FY2025 約 0.09、1H26 約 0.27（Derived） | I98: 現金增加帶動利息收入：金額未找到
A99: tax | B99: 有效稅率（FY2027 起） | C99: % | D99: 0.12 | E99: 0.15 | F99: 0.2 | G99: Assumed | H99: FY2025 約 15.1%（Derived） | I99: —
A100: sh_g | B100: 加權股數年變動 | C100: % | D100: -0.005 | E100: 0 | F100: 0.005 | G100: Assumed | H100: FY2021–25 約 134–135M（stockanalysis 推得） | I100: —
A101: fx | B101: 匯率（FY2027 起；美元營收換算） | C101: NT$/US$ | D101: 30 | E101: 32 | F101: 34 | G101: Assumed | H101: 與聯發科、世芯、台積電模型相同假設 | I101: 車用與其他營收以新台幣成長率推，未另換算
...

Sheet Q
A1: Q — 實績與 FY2026 錨點（十億新台幣；EPS 為新台幣、基本；股數為十億股）。藍字＝輸入（媒體轉述公司財報、stockanalysis）；黑字＝公式。CPU、AI ASIC、車用、其他的拆分為 Assumed（公司未揭露金額）
A2: v0.2（2026-10-31）：FY2026 錨點＝1Q、2Q、3Q26 實績（3Q26＝前三季財報 − 上半年；2026-10-29 公布）＋4Q26 假設；公司自 2026 年起不給季度區間指引
A3: 項目 | B3: FY2025A | C3: 1Q26（實績） | D3: 2Q26（實績） | E3: 3Q26（實績） | F3: 4Q26（模型） | G3: FY2026 錨點 | H3: 標記 | I3: 來源1 | J3: 來源2／說明
A4: 營收 | B4: 34.141 | C4: 11.448 | D4: 13.897 | E4: =q3_rev -> 18.754 | F4: =E4*(1+q4_g) -> 25.3179 | G4: =SUM(C4:F4) -> 69.4169 | H4: Verified／Assumed（4Q） | I4: FY2025：stockanalysis 財報頁、經濟日報 2026-01-31；1Q26：科技新報 2026-05-05／05-08；2Q26：經濟日報 2026-07-30 | J4: 3Q26：月營收實績（科技新報）；1H26 253.4 億（經濟日報）
A5: Google CPU 量產（年度拆分） | B5: =B4*cpu_sh25 -> 6.14538 | G5: =G4*cpu_sh26 -> 33.320112 | H5: Assumed | I5: In 頁 E 節 | J5: 季度拆分未揭露；只在年度欄拆分
A6: AI ASIC 量產（其他 ASIC） | B6: =B4*asic_sh25 -> 1.70705 | G6: =G4*asic_sh26 -> 2.082507 | H6: Assumed | I6: In 頁 E 節 | J6: —
A7: 車用 | B7: =B4*auto_sh25 -> 1.02423 | G7: =G4*auto_sh26 -> 3.470845 | H7: Interested-party／Assumed | I7: In 頁 E 節 | J7: 公司：2026 年車用占營收個位數
A8: 其他（NRE＋BMC、SSD 控制器、加密貨幣等量產） | B8: =B4-B5-B6-B7 -> 25.26434 | G8: =G4-G5-G6-G7 -> 30.543436 | H8: Derived | I8: — | J8: FY2025 NRE 約占 34%（經濟日報 2026-01-31）；公司：FY2026 NRE 年增 15–19%
A9: 毛利 | B9: 8.454 | C9: =25.345*0.241-D9 -> 3.106393 | D9: =13.897*0.216 -> 3.001752 | E9: =9.967659-C9-D9 -> 3.859514 | F9: =F4*q4_gm -> 4.6838115 | G9: =SUM(C9:F9) -> 14.651471 | H9: Verified（毛利率 × 營收）／Interested-party（3Q）／Assumed（4Q） | I9: FY2025：stockanalysis 財報頁、經濟日報 2026-01-31；1Q26：科技新報 2026-05-05／05-08；2Q26：經濟日報 2026-07-30 | J9: 2Q26 毛利率 21.6%、1H26 24.1%（經濟日報；工商時報 2Q26 為 21.5%）；1Q26＝1H26 − 2Q26
A10: 毛利率 | B10: =B9/B4 -> 0.24762016 | C10: =C9/C4 -> 0.2713481 | D10: =D9/D4 -> 0.216 | E10: =E9/E4 -> 0.20579684 | F10: =F9/F4 -> 0.185 | G10: =G9/G4 -> 0.21106489 | H10: Derived | I10: — | J10: 公司：1Q26 約 27.2%、2Q26 21.6%
A11: 營業費用 | B11: =B9-B12 -> 4.104 | C11: =C9-C12 -> 1.284783 | D11: =D9-D12 -> 1.325752 | E11: =E9-E12 -> 1.305437 | F11: =q4_opx -> 1.45 | G11: =SUM(C11:F11) -> 5.365972 | H11: Derived／Interested-party／Assumed | I11: FY2025：stockanalysis 財報頁、經濟日報 2026-01-31；1Q26：科技新報 2026-05-05／05-08；2Q26：經濟日報 2026-07-30 | J11: 毛利 − 營業利益
A12: 營業利益 | B12: 4.35 | C12: =25.345*0.138-D12 -> 1.82161 | D12: 1.676 | E12: =6.051687-C12-D12 -> 2.554077 | F12: =F9-F11 -> 3.2338115 | G12: =SUM(C12:F12) -> 9.2854985 | H12: Verified／Derived | I12: FY2025：stockanalysis 財報頁、經濟日報 2026-01-31；1Q26：科技新報 2026-05-05／05-08；2Q26：經濟日報 2026-07-30 | J12: 2Q26 16.76 億；1H26 營業利益率 13.8%（經濟日報）
A13: 營業外淨額 | B13: =B14-B12 -> 0.092 | C13: =C14-C12 -> 0.082876228 | D13: =D14-D12 -> 0.12319568 | E13: =6.306235-6.051687-C13-D13 -> 0.048476095 | F13: =q_nonop -> 0.13 | G13: =SUM(C13:F13) -> 0.384548 | H13: Derived／Assumed | I13: FY2025：stockanalysis 財報頁、經濟日報 2026-01-31；1Q26：科技新報 2026-05-05／05-08；2Q26：經濟日報 2026-07-30 | J13: 稅前 − 營業利益
A14: 稅前利益 | B14: 4.442 | C14: =C17/(1-t_h1) -> 1.9044862 | D14: =D17/(1-t_h1) -> 1.7991957 | E14: =E12+E13 -> 2.6025531 | F14: =F12+F13 -> 3.3638115 | G14: =SUM(C14:F14) -> 9.6700465 | H14: Derived | I14: FY2025：stockanalysis 財報頁、經濟日報 2026-01-31；1Q26：科技新報 2026-05-05／05-08；2Q26：經濟日報 2026-07-30 | J14: FY2025：stockanalysis 稅前淨利率推得約 44.42 億；1Q、2Q26＝淨利 ÷（1 − 近 12 月稅率）
A15: 所得稅 | B15: =B14-B17 -> 0.672 | C15: =C14-C17 -> 0.25848623 | D15: =D14-D17 -> 0.24419568 | E15: =E14-E17 -> 0.33010809 | F15: =F14*q_tax -> 0.50457173 | G15: =SUM(C15:F15) -> 1.3373617 | H15: Derived／Assumed | I15: FY2025：stockanalysis 財報頁、經濟日報 2026-01-31；1Q26：科技新報 2026-05-05／05-08；2Q26：經濟日報 2026-07-30 | J15: 稅前 − 淨利
A16: 有效稅率 | B16: =B15/B14 -> 0.15128321 | C16: =C15/C14 -> 0.13572491 | D16: =D15/D14 -> 0.13572491 | E16: =E15/E14 -> 0.1268401 | F16: =F15/F14 -> 0.15 | G16: =G15/G14 -> 0.13829941 | H16: Derived | I16: — | J16: —
A17: 歸屬母公司淨利 | B17: 3.77 | C17: 1.646 | D17: 1.555 | E17: =5.473445-C17-D17 -> 2.272445 | F17: =F14-F15 -> 2.8592398 | G17: =SUM(C17:F17) -> 8.3326848 | H17: Verified／Derived | I17: FY2025：stockanalysis 財報頁、經濟日報 2026-01-31；1Q26：科技新報 2026-05-05／05-08；2Q26：經濟日報 2026-07-30 | J17: 無重大非控制權益（假設）
A18: 加權股數（十億股） | B18: =3.77/28.13 -> 0.13402062 | C18: =1.646/12.28 -> 0.13403909 | D18: =1.555/11.61 -> 0.13393626 | E18: =q_sh -> 0.13401 | F18: =q_sh -> 0.13401 | G18: =AVERAGE(C18:F18) -> 0.13399884 | H18: Derived | I18: 淨利 ÷ EPS（公司） | J18: —
A19: EPS（基本） | B19: =B17/B18 -> 28.13 | C19: =C17/C18 -> 12.28 | D19: =D17/D18 -> 11.61 | E19: =E17/E18 -> 16.957279 | F19: =F17/F18 -> 21.336018 | G19: =G17/G18 -> 62.184754 | H19: Derived | I19: 淨利 ÷ 股數 | J19: —
A20: 公司揭露 EPS | B20: 28.13 | C20: 12.28 | D20: 11.61 | E20: =40.84-C20-D20 -> 16.95 | H20: Verified | I20: FY2025：stockanalysis 財報頁、經濟日報 2026-01-31；1Q26：科技新報 2026-05-05／05-08；2Q26：經濟日報 2026-07-30 | J20: HiStock：FY2025 28.13（stockanalysis 28.01）、1Q26 12.28、2Q26 11.61；3Q26＝前三季 40.84 − 上半年（中央社：16.95）
A22: FY2026 錨點的檢查（參考；校準未使用券商數字）
A23: FY2026 營收年增 | B23: =G4/B4-1 -> 1.0332416
A24: 3Q26 營收季增 | B24: =E4/D4-1 -> 0.34949989
A25: FY2026 毛利率（公司：20% 以上） | B25: =G10 -> 0.21106489
A26: FY2026 營業利益率（公司：雙位數） | B26: =G12/G4 -> 0.13376423
A27: FY2026 其他營收年增 | B27: =G8/B8-1 -> 0.20895444
A28: 核對：FY2026 其他營收毛利率（以 m_tk、m_auto 推得） | B28: =(G9-m_tk*(G5+G6)-m_auto*G7)/G8 -> 0.3108293
A29: 檢查：1H26 營收 自算 − 公司 25.34（應約為 0） | B29: =C4+D4-25.34 -> 0.005
A30: 檢查：1H26 歸屬淨利 自算 − 公司 3.2（應約為 0） | B30: =C17+D17-3.2 -> 0.001
A31: 檢查：FY2025 營業費用 ÷ 營收 | B31: =B11/B4 -> 0.12020738
A33: 官方報告分部與營收類別（FY2025；分部原則第 3 條）
A34: 單一營運部門（ASIC 設計服務）營收 | B34: 34.141 | H34: Verified | I34: 公司 FY2025 財報：單一應報導部門 | J34: 與第 4 列 FY2025 營收同一數字（公司揭露）
A35: 委託設計（NRE） | B35: =B34*0.34 -> 11.60794 | H35: Interested-party | I35: 經濟日報 2026-01-31（萬寶週刊）：NRE 約占 34% | J35: 比重為媒體轉述公司數字；金額為推得
A36: 量產（Turnkey） | B36: =B34*0.64 -> 21.85024 | H36: Interested-party | I36: 同上：Turnkey 約占 64% | J36: 本模型的 Google CPU、AI ASIC、車用量產皆屬 Turnkey；推估年不拆 NRE／Turnkey
A37: 其他（差額） | B37: =B34-B35-B36 -> 0.68282 | H37: Derived | I37: — | J37: 原文未說明其餘約 2%
A38: 檢查：分部合計 − 合併營收 | B38: =B34-B4 -> 0 | H38: Derived | I38: — | J38: 應為 0

Sheet Units
A1: Units — 創意 CPU 與 AI ASIC 量產（情境 A）。顆數：百萬顆（日曆年；TPU、其他 ASIC 顆數與 HBM、台積電、Broadcom、Marvell、聯發科模型同一份）；其他 ASIC 每顆核心售價取自 Broadcom 模型（本專案權威，唯讀）；每顆價：US$K
A3: 項目 | B3: 單位 | C3: CY2026 | D3: CY2027 | E3: CY2028 | F3: CY2029 | G3: 說明
A4: 1. Google 自研 Arm CPU 與其他 ASIC（情境 A；創意營收口徑＝晶圓與封裝轉售，乘校準係數）
A5: Google TPU 市場顆數 | B5: 百萬顆 | C5: =PL!D63 -> 3.85 | D5: =PL!E63 -> 5.5 | E5: =PL!F63 -> 7 | F5: =PL!G63 -> 8.05 | G5: tsmc 成品 In 頁
A6: CPU 對 TPU 配比 | B6: x | C6: =PL!D64 -> 0.325 | D6: =PL!E64 -> 0.6 | E6: =PL!F64 -> 0.6 | F6: =PL!G64 -> 0.6 | G6: In 頁 B 節（CY2026 法人估計；CY2027 起 Assumed）
A7: 創意 CPU 顆數 | B7: 百萬顆 | C7: =PL!D66 -> 1.25125 | D7: =PL!E66 -> 3.3 | E7: =PL!F66 -> 4.2 | F7: =PL!G66 -> 4.83 | G7: TPU 顆數 × 配比 × 創意份額
A8: 每顆創意 CPU 營收（校準後） | B8: US$K | C8: =PL!D73 -> 0.84270443 | D8: =PL!E73 -> 0.84270443 | E8: =PL!F73 -> 1.0112453 | F8: =PL!G73 -> 1.0112453 | G8: 每顆營收 × k_c
A9: 創意 CPU 營收（美元） | B9: US$B | C9: =PL!D70 -> 1.0544339 | D9: =PL!E70 -> 2.7809246 | E9: =PL!F70 -> 4.2472304 | F9: =PL!G70 -> 4.8843149 | G9: —
A10: 其他 ASIC 市場顆數 | B10: 百萬顆 | C10: =PL!D75 -> 1 | D10: =PL!E75 -> 4.5 | E10: =PL!F75 -> 5 | F10: =PL!G75 -> 5.75 | G10: tsmc 成品 In 頁（含 Ascend 等非台積電產品，份額分母偏大）
A11: 創意份額：其他 ASIC | B11: % | C11: =PL!D76 -> 0.03 | D11: =PL!E76 -> 0.06 | E11: =PL!F76 -> 0.08 | F11: =PL!G76 -> 0.08 | G11: In 頁 C 節（Assumed）
A12: 創意 AI ASIC 顆數 | B12: 百萬顆 | C12: =PL!D77 -> 0.03 | D12: =PL!E77 -> 0.27 | E12: =PL!F77 -> 0.4 | F12: =PL!G77 -> 0.46 | G12: 市場層顆數 × 份額
A13: 創意 AI ASIC 營收（美元） | B13: US$B | C13: =PL!D80 -> 0.06590212 | D13: =PL!E80 -> 0.59311908 | E13: =PL!F80 -> 0.87869494 | F13: =PL!G80 -> 1.0104992 | G13: 顆數 × 每顆核心售價 × k_o
A15: 2. 份額加總檢查（Broadcom＋Marvell＋聯發科＋創意 ≤ 100%；各公司份額讀各自成品 In 頁；世芯只有 Trainium 份額）
A16: Broadcom＋Marvell＋聯發科（高）＋創意：其他 ASIC（情境 A） | B16: % | C16: =av_oth_26+mv_oth_26+mk_oth_26+PL!D76 -> 0.45 | D16: =av_oth_27+mv_oth_27+mk_oth_27+PL!E76 -> 0.7 | E16: =av_oth_28+mv_oth_28+mk_oth_28+PL!F76 -> 0.83 | F16: =av_oth_28+mv_oth_28+mk_oth_28+PL!G76 -> 0.83 | G16: 其餘為客戶自行設計（COT）或其他夥伴
A17: Broadcom＋Marvell＋聯發科（高）＋創意：其他 ASIC（情境 B） | B17: % | C17: =av_oth_26+mv_oth_26+mk_oth_26+PL!D124 -> 0.45 | D17: =av_oth_27+mv_oth_27+mk_oth_27+PL!E124 -> 0.68 | E17: =av_oth_28+mv_oth_28+mk_oth_28+PL!F124 -> 0.8 | F17: =av_oth_28+mv_oth_28+mk_oth_28+PL!G124 -> 0.8 | G17: 同上
A18: Broadcom＋Marvell＋聯發科（高）＋創意：其他 ASIC（情境 C） | B18: % | C18: =av_oth_26+mv_oth_26+mk_oth_26+PL!D172 -> 0.45 | D18: =av_oth_27+mv_oth_27+mk_oth_27+PL!E172 -> 0.66 | E18: =av_oth_28+mv_oth_28+mk_oth_28+PL!F172 -> 0.77 | F18: =av_oth_28+mv_oth_28+mk_oth_28+PL!G172 -> 0.77 | G18: 同上
A19: 創意其他 ASIC 份額上限（1 − Broadcom − Marvell − 聯發科高值） | B19: % | C19: =1-av_oth_26-mv_oth_26-mk_oth_26 -> 0.58 | D19: =1-av_oth_27-mv_oth_27-mk_oth_27 -> 0.36 | E19: =1-av_oth_28-mv_oth_28-mk_oth_28 -> 0.25 | F19: =1-av_oth_28-mv_oth_28-mk_oth_28 -> 0.25 | G19: In 頁份額高值受此上限限制（建置時檢查）
A20: Broadcom＋Marvell＋聯發科：Google TPU（基準；創意不占） | B20: % | C20: =av_tpu_26 -> 0.95 | D20: =av_tpu_27 -> 0.95 | E20: =av_tpu_28 -> 0.98 | F20: =av_tpu_28 -> 0.98 | G20: 創意的 Google 營收為 CPU，不占 TPU 加速器份額
A22: 3. 校準值（只用 FY2026 已發生的實績與錨點拆分；不用共識、不用 FY2027 起的目標）
A23: CPU 校準係數 k_c | C23: =PL!D69 -> 0.84270443 | G23: FY2026 CPU 營收 ÷ 未校準由下而上
A24: AI ASIC 校準係數 k_o | C24: =PL!D79 -> 0.36612289 | G24: FY2026 AI ASIC ÷（顆數 × Broadcom 核心售價）
A25: 其他營收毛利率（FY2026 殘差） | C25: =PL!D92 -> 0.3108293 | G25: 讓 FY2026 毛利等於錨點
A27: 讀法：創意的 AI 營收以 Google 自研 CPU 為主，顆數隨 TPU 顆數與 CPU 對 TPU 配比變動，不占 TPU 加速器份額；其他 ASIC 份額受 Broadcom、Marvell、聯發科份額共同限制。

Sheet PL
A1: PL — 創意損益（十億新台幣；EPS 新台幣、基本；歸屬母公司）。FY2025A 實績、FY2026 錨點（三情境相同），FY2027–FY2029 由驅動因子推導，FY2030–FY2032 為收斂法。FY(t)＝CY(t)。三情境各一個完整推導區塊（本頁下方），頂端為摘要
A2: 灰底＝FY2030–FY2032 收斂法（上游顆數只到 CY2029）：營收年增線性收斂到 fade_g、淨利率線性收斂到 fade_m（In 頁 I 節），非驅動因子推導
A3: 情境／項目 | B3: 單位 | C3: FY2025A | D3: FY2026（錨點） | E3: FY2027 | F3: FY2028 | G3: FY2029 | H3: FY2030（收斂） | I3: FY2031（收斂） | J3: FY2032（收斂） | K3: 說明
A4: 情境 A
A5: 營收 | B5: NT$B | C5: =C85 -> 34.141 | D5: =D85 -> 69.4169 | E5: =E85 -> 156.97773 | F5: =F85 -> 230.43382 | G5: =G85 -> 264.45535 | H5: =H85 -> 295.77414 | I5: =I85 -> 322.16126 | J5: =J85 -> 341.49094
A6: 營收年增 | B6: % | D6: =D86 -> 1.0332416 | E6: =E86 -> 1.2613763 | F6: =F86 -> 0.46793953 | G6: =G86 -> 0.14764126 | H6: =H86 -> 0.1184275 | I6: =I86 -> 0.089213752 | J6: =J86 -> 0.06
A7: Google CPU 量產 | B7: NT$B | C7: =C72 -> 6.14538 | D7: =D72 -> 33.320112 | E7: =E72 -> 88.989588 | F7: =F72 -> 135.91137 | G7: =G72 -> 156.29808
A8: AI ASIC 量產（其他 ASIC） | B8: NT$B | C8: =C81 -> 1.70705 | D8: =D81 -> 2.082507 | E8: =E81 -> 18.979811 | F8: =F81 -> 28.118238 | G8: =G81 -> 32.335974
A9: 車用 | B9: NT$B | C9: =C83 -> 1.02423 | D9: =D83 -> 3.470845 | E9: =E83 -> 13.88338 | F9: =F83 -> 27.76676 | G9: =G83 -> 33.320112
A10: 其他（NRE＋其他量產） | B10: NT$B | C10: =C84 -> 25.26434 | D10: =D84 -> 30.543436 | E10: =E84 -> 35.124951 | F10: =F84 -> 38.637447 | G10: =G84 -> 42.501191
A11: 毛利率 | B11: % | C11: =C94 -> 0.24762016 | D11: =D94 -> 0.21106489 | E11: =E94 -> 0.17999318 | F11: =F94 -> 0.17105336 | G11: =G94 -> 0.16997425
A12: 營業利益率 | B12: % | C12: =C97 -> 0.12741279 | D12: =D97 -> 0.13376423 | E12: =E97 -> 0.13287487 | F12: =F97 -> 0.13444908 | G12: =G97 -> 0.13552741
A13: 歸屬母公司淨利 | B13: NT$B | C13: =C101 -> 3.77 | D13: =D101 -> 8.3326848 | E13: =E101 -> 18.154636 | F13: =F101 -> 26.759372 | G13: =G101 -> 30.889806 | H13: =H101 -> 34.548009 | I13: =I101 -> 37.630167 | J13: =J101 -> 39.887977
A14: 淨利率 | B14: % | C14: =C105 -> 0.11042442 | D14: =D105 -> 0.12003827 | E14: =E105 -> 0.11565103 | F14: =F105 -> 0.11612607 | G14: =G105 -> 0.11680537 | H14: =H105 -> 0.11680537 | I14: =I105 -> 0.11680537 | J14: =J105 -> 0.11680537
A15: EPS | B15: NT$ | C15: =C103 -> 28.13 | D15: =D103 -> 62.184754 | E15: =E103 -> 135.47225 | F15: =F103 -> 199.68191 | G15: =G103 -> 230.50374 | H15: =H103 -> 257.80172 | I15: =I103 -> 280.80118 | J15: =J103 -> 297.64925
A16: EPS 年增 | B16: % | D16: =D104 -> 1.2106205 | E16: =E104 -> 1.1785445 | F16: =F104 -> 0.47396906 | G16: =G104 -> 0.15435467 | H16: =H104 -> 0.1184275 | I16: =I104 -> 0.089213752 | J16: =J104 -> 0.06
A18: 情境 B
A19: 營收 | B19: NT$B | C19: =C133 -> 34.141 | D19: =D133 -> 69.4169 | E19: =E133 -> 130.21064 | F19: =F133 -> 140.10669 | G19: =G133 -> 163.20931 | H19: =H133 -> 183.32682 | I19: =I133 -> 198.29197 | J19: =J133 -> 206.22365
A20: 營收年增 | B20: % | D20: =D134 -> 1.0332416 | E20: =E134 -> 0.87577727 | F20: =F134 -> 0.076000257 | G20: =G134 -> 0.16489306 | H20: =H134 -> 0.12326204 | I20: =I134 -> 0.08163102 | J20: =J134 -> 0.04
A21: Google CPU 量產 | B21: NT$B | C21: =C120 -> 6.14538 | D21: =D120 -> 33.320112 | E21: =E120 -> 74.15799 | F21: =F120 -> 74.751254 | G21: =G120 -> 91.336689
A22: AI ASIC 量產（其他 ASIC） | B22: NT$B | C22: =C129 -> 1.70705 | D22: =D129 -> 2.082507 | E22: =E129 -> 12.653207 | F22: =F129 -> 14.059119 | G22: =G129 -> 17.178486
A23: 車用 | B23: NT$B | C23: =C131 -> 1.02423 | D23: =D131 -> 3.470845 | E23: =E131 -> 10.412535 | F23: =F131 -> 16.660056 | G23: =G131 -> 18.326062
A24: 其他（NRE＋其他量產） | B24: NT$B | C24: =C132 -> 25.26434 | D24: =D132 -> 30.543436 | E24: =E132 -> 32.986911 | F24: =F132 -> 34.636256 | G24: =G132 -> 36.368069
A25: 毛利率 | B25: % | C25: =C142 -> 0.24762016 | D25: =D142 -> 0.21106489 | E25: =E142 -> 0.17820939 | F25: =F142 -> 0.17827073 | G25: =G142 -> 0.17366292
A26: 營業利益率 | B26: % | C26: =C145 -> 0.12741279 | D26: =D145 -> 0.13376423 | E26: =E145 -> 0.12617224 | F26: =F145 -> 0.12604014 | G26: =G145 -> 0.1252387
A27: 歸屬母公司淨利 | B27: NT$B | C27: =C149 -> 3.77 | D27: =D149 -> 8.3326848 | E27: =E149 -> 14.389623 | F27: =F149 -> 15.435207 | G27: =G149 -> 17.799103 | H27: =H149 -> 19.326622 | I27: =I149 -> 20.183437 | J27: =J149 -> 20.241104
A28: 淨利率 | B28: % | C28: =C153 -> 0.11042442 | D28: =D153 -> 0.12003827 | E28: =E153 -> 0.11051035 | F28: =F153 -> 0.11016752 | G28: =G153 -> 0.10905691 | H28: =H153 -> 0.10542168 | I28: =I153 -> 0.10178645 | J28: =J153 -> 0.098151223
A29: EPS | B29: NT$ | C29: =C151 -> 28.13 | D29: =D151 -> 62.184754 | E29: =E151 -> 107.37724 | F29: =F151 -> 115.17951 | G29: =G151 -> 132.81922 | H29: =H151 -> 144.21776 | I29: =I151 -> 150.61142 | J29: =J151 -> 151.04174
A30: EPS 年增 | B30: % | D30: =D152 -> 1.2106205 | E30: =E152 -> 0.72674537 | F30: =F152 -> 0.072662303 | G30: =G152 -> 0.15314966 | H30: =H152 -> 0.085819971 | I30: =I152 -> 0.044333398 | J30: =J152 -> 0.0028571429
A32: 情境 C
A33: 營收 | B33: NT$B | C33: =C181 -> 34.141 | D33: =D181 -> 69.4169 | E33: =E181 -> 101.61095 | F33: =F181 -> 73.276681 | G33: =G181 -> 78.66624 | H33: =H181 -> 83.047991 | I33: =I181 -> 86.191379 | J33: =J181 -> 87.915207
A34: 營收年增 | B34: % | D34: =D182 -> 1.0332416 | E34: =E182 -> 0.46377827 | F34: =F182 -> -0.27885054 | G34: =G182 -> 0.073550798 | H34: =H182 -> 0.055700532 | I34: =I182 -> 0.037850266 | J34: =J182 -> 0.02
A35: Google CPU 量產 | B35: NT$B | C35: =C168 -> 6.14538 | D35: =D168 -> 33.320112 | E35: =E168 -> 59.326392 | F35: =F168 -> 31.712653 | G35: =G168 -> 36.469551
A36: AI ASIC 量產（其他 ASIC） | B36: NT$B | C36: =C177 -> 1.70705 | D36: =D177 -> 2.082507 | E36: =E177 -> 6.3266035 | F36: =F177 -> 4.2177357 | G36: =G177 -> 4.8503961
A37: 車用 | B37: NT$B | C37: =C179 -> 1.02423 | D37: =D179 -> 3.470845 | E37: =E179 -> 6.94169 | F37: =F179 -> 8.330028 | G37: =G179 -> 8.330028
A38: 其他（NRE＋其他量產） | B38: NT$B | C38: =C180 -> 25.26434 | D38: =D180 -> 30.543436 | E38: =E180 -> 29.016264 | F38: =F180 -> 29.016264 | G38: =G180 -> 29.016264
A39: 毛利率 | B39: % | C39: =C190 -> 0.24762016 | D39: =D190 -> 0.21106489 | E39: =E190 -> 0.17076511 | F39: =F190 -> 0.19520879 | G39: =G190 -> 0.18937099
A40: 營業利益率 | B40: % | C40: =C193 -> 0.12741279 | D40: =D193 -> 0.13376423 | E40: =E193 -> 0.11060862 | F40: =F193 -> 0.10511788 | G40: =G193 -> 0.098738871
A41: 歸屬母公司淨利 | B41: NT$B | C41: =C197 -> 3.77 | D41: =D197 -> 8.3326848 | E41: =E197 -> 9.9781897 | F41: =F197 -> 6.9722859 | G41: =G197 -> 7.0273033 | H41: =H197 -> 6.924146 | I41: =I197 -> 6.6729249 | J41: =J197 -> 6.2828154
A42: 淨利率 | B42: % | C42: =C201 -> 0.11042442 | D42: =D201 -> 0.12003827 | E42: =E201 -> 0.098199945 | F42: =F201 -> 0.095150132 | G42: =G201 -> 0.089330612 | H42: =H201 -> 0.083375238 | I42: =I201 -> 0.077419864 | J42: =J201 -> 0.07146449
A43: EPS | B43: NT$ | C43: =C199 -> 28.13 | D43: =D199 -> 62.184754 | E43: =E199 -> 74.458545 | F43: =F199 -> 52.028102 | G43: =G199 -> 52.438649 | H43: =H199 -> 51.668876 | I43: =I199 -> 49.794231 | J43: =J199 -> 46.883183
A44: EPS 年增 | B44: % | D44: =D200 -> 1.2106205 | E44: =E200 -> 0.19737621 | F44: =F200 -> -0.3012474 | G44: =G200 -> 0.0078908725 | H44: =H200 -> -0.014679504 | I44: =I200 -> -0.036281896 | J44: =J200 -> -0.058461538
A46: 核對（應為 0）：FY2026 模型 − 錨點
A47: 三情境：營收差（NT$B） | D47: =ABS(D85-a26_rev)+ABS(D133-a26_rev)+ABS(D181-a26_rev) -> 0
A48: 三情境：EPS 差（NT$） | D48: =ABS(D103-a26_eps)+ABS(D151-a26_eps)+ABS(D199-a26_eps) -> 0
A49: 情境 A：CPU 由下而上 − Q 頁 CPU（NT$B） | D49: =D72-a26_cpu -> 0
A60: 情境 A（順利）：顆數基準（tsmc 情境 A）；CPU 對 TPU 配比 0.6；下一代 CPU 份額 100%、單價 ×1.2；其他 ASIC 份額 6%／8%；車用 ×4.0／×2.0；其他營收 +15%／+10%；量產毛利率 +1pt
A61: 項目 | B61: 單位 | C61: FY2025A | D61: FY2026（錨點） | E61: FY2027 | F61: FY2028 | G61: FY2029 | H61: FY2030（收斂） | I61: FY2031（收斂） | J61: FY2032（收斂） | K61: 說明
A62: A. Google 自研 Arm CPU 量產（由下而上；D 欄＝FY2026 校準年；FY(t)＝CY(t)）
A63: Google TPU 市場顆數（含情境係數） | B63: 百萬顆 | D63: =u_tpu_26 -> 3.85 | E63: =u_tpu_27 -> 5.5 | F63: =u_tpu_28*um28_A -> 7 | G63: =u_tpu_28*(1+g29_tpu)*um29_A -> 8.05
A64: CPU 對 TPU 配比 | B64: x | D64: =att26 -> 0.325 | E64: =MAX(0,att_A+0) -> 0.6 | F64: =MAX(0,att_A+0) -> 0.6 | G64: =MAX(0,att_A+0) -> 0.6
A65: 創意占 Google 自研 CPU | B65: % | D65: =gsh26 -> 1 | E65: =gsh26 -> 1 | F65: =MIN(1,gsh28_A) -> 1 | G65: =MIN(1,gsh28_A) -> 1
A66: 創意 CPU 顆數 | B66: 百萬顆 | D66: =D63*D64*D65 -> 1.25125 | E66: =E63*E64*E65*1 -> 3.3 | F66: =F63*F64*F65*1 -> 4.2 | G66: =G63*G64*G65*1 -> 4.83
A67: 每顆 CPU 營收（未校準；CY2028 起 × 下一代係數） | B67: US$K | D67: =pc_cpu -> 1 | E67: =pc_cpu -> 1 | F67: =pc_cpu*pfc_A -> 1.2 | G67: =pc_cpu*pfc_A -> 1.2
A68: CPU 營收（未校準） | B68: US$B | D68: =D66*D67 -> 1.25125 | E68: =E66*E67 -> 3.3 | F68: =F66*F67 -> 5.04 | G68: =G66*G67 -> 5.796
A69: CPU 校準係數 k_c ＝ FY2026 CPU 營收（錨點）÷ 未校準 | B69: x | D69: =a26_cpu/fx26/D68 -> 0.84270443 | K69: Derived：以 FY2026 錨點的 CPU 拆分校準；FY2027 起沿用。顆數、配比、單價的合併係數
A70: CPU 營收（美元） | B70: US$B | D70: =D68*$D$69 -> 1.0544339 | E70: =E68*$D$69 -> 2.7809246 | F70: =F68*$D$69 -> 4.2472304 | G70: =G68*$D$69 -> 4.8843149
A71: 匯率 | B71: NT$/US$ | D71: =fx26 -> 31.6 | E71: =fx -> 32 | F71: =fx -> 32 | G71: =fx -> 32
A72: Google CPU 量產營收 | B72: NT$B | C72: =a25_cpu -> 6.14538 | D72: =D70*D71 -> 33.320112 | E72: =E70*E71 -> 88.989588 | F72: =F70*F71 -> 135.91137 | G72: =G70*G71 -> 156.29808
A73: 每顆創意 CPU 營收（校準後） | B73: US$K | D73: =IF(D66>0,D70/D66,0) -> 0.84270443 | E73: =IF(E66>0,E70/E66,0) -> 0.84270443 | F73: =IF(F66>0,F70/F66,0) -> 1.0112453 | G73: =IF(G66>0,G70/G66,0) -> 1.0112453
A74: B. AI ASIC 量產（其他 ASIC：Maia 等；由下而上）
A75: 其他 ASIC 市場顆數（含情境係數） | B75: 百萬顆 | D75: =u_oth_26 -> 1 | E75: =u_oth_27 -> 4.5 | F75: =u_oth_28*um28_A -> 5 | G75: =u_oth_28*(1+g29_oth)*um29_A -> 5.75
A76: 創意份額：其他 ASIC | B76: % | D76: =guc_oth_26 -> 0.03 | E76: =MIN(1,MAX(0,go27_A+0)) -> 0.06 | F76: =MIN(1,MAX(0,go28_A+0)) -> 0.08 | G76: =MIN(1,MAX(0,go28_A+0)) -> 0.08
A77: 創意 AI ASIC 顆數 | B77: 百萬顆 | D77: =D75*D76 -> 0.03 | E77: =E75*E76*1 -> 0.27 | F77: =F75*F76*1 -> 0.4 | G77: =G75*G76*1 -> 0.46
A78: AI ASIC 營收（未校準）＝ 顆數 × 每顆核心售價（Broadcom 模型） | B78: US$B | D78: =D77*core_oth -> 0.18 | E78: =E77*core_oth -> 1.62 | F78: =F77*core_oth -> 2.4 | G78: =G77*core_oth -> 2.76
A79: AI ASIC 校準係數 k_o ＝ FY2026 AI ASIC（錨點）÷ 未校準 | B79: x | D79: =a26_asic/fx26/D78 -> 0.36612289 | K79: Derived：k_o < 1＝創意 turnkey 只含晶圓與封裝轉售，低於 Broadcom 的核心售價
A80: AI ASIC 營收（美元） | B80: US$B | D80: =D78*$D$79 -> 0.06590212 | E80: =E78*$D$79 -> 0.59311908 | F80: =F78*$D$79 -> 0.87869494 | G80: =G78*$D$79 -> 1.0104992
A81: AI ASIC 量產營收 | B81: NT$B | C81: =a25_asic -> 1.70705 | D81: =D80*D71 -> 2.082507 | E81: =E80*E71 -> 18.979811 | F81: =F80*F71 -> 28.118238 | G81: =G80*G71 -> 32.335974
A82: C. 車用與其他營收（FY2027 起簡化成長）
A83: 車用（含北美車用客戶 AI 晶片） | B83: NT$B | C83: =a25_auto -> 1.02423 | D83: =a26_auto -> 3.470845 | E83: =D83*am27_A -> 13.88338 | F83: =E83*am28_A -> 27.76676 | G83: =F83*(1+ag29_A) -> 33.320112
A84: 其他（NRE＋BMC、SSD 控制器、加密貨幣等量產） | B84: NT$B | C84: =a25_oth -> 25.26434 | D84: =a26_oth -> 30.543436 | E84: =D84*(1+g_o27_A) -> 35.124951 | F84: =E84*(1+g_oL_A) -> 38.637447 | G84: =F84*(1+g_oL_A) -> 42.501191
A85: 營收 | B85: NT$B | C85: =C72+C81+C83+C84 -> 34.141 | D85: =D72+D81+D83+D84 -> 69.4169 | E85: =E72+E81+E83+E84 -> 156.97773 | F85: =F72+F81+F83+F84 -> 230.43382 | G85: =G72+G81+G83+G84 -> 264.45535 | H85: =G85*(1+H86) -> 295.77414 | I85: =H85*(1+I86) -> 322.16126 | J85: =I85*(1+J86) -> 341.49094 | K85: FY2030 起為收斂法：營收年增由 FY2029 線性收斂到 fade_g、淨利率收斂到 fade_m（FY2032 達到），非驅動因子推導
A86: 營收年增 | B86: % | D86: =D85/C85-1 -> 1.0332416 | E86: =E85/D85-1 -> 1.2613763 | F86: =F85/E85-1 -> 0.46793953 | G86: =G85/F85-1 -> 0.14764126 | H86: =$G86+(fade_gA-$G86)*1/3 -> 0.1184275 | I86: =$G86+(fade_gA-$G86)*2/3 -> 0.089213752 | J86: =$G86+(fade_gA-$G86)*3/3 -> 0.06
A87: Google CPU ÷ 營收 | B87: % | C87: =C72/C85 -> 0.18 | D87: =D72/D85 -> 0.48 | E87: =E72/E85 -> 0.56689308 | F87: =F72/F85 -> 0.58980654 | G87: =G72/G85 -> 0.59101877
A88: 車用 ÷ 營收 | B88: % | C88: =C83/C85 -> 0.03 | D88: =D83/D85 -> 0.05 | E88: =E83/E85 -> 0.088441717 | F88: =F83/F85 -> 0.12049777 | G88: =G83/G85 -> 0.12599523
A89: D. 毛利與損益
A90: AI 量產毛利 ＝（m_tk＋情境調整）×（CPU＋AI ASIC） | B90: NT$B | D90: =m_tk*(D72+D81) -> 4.6023405 | E90: =(m_tk+gta_A)*(E72+E81) -> 15.115716 | F90: =(m_tk+gta_A)*(F72+F81) -> 22.964145 | G90: =(m_tk+gta_A)*(G72+G81) -> 26.408767
A91: 車用毛利 ＝ m_auto × 車用 | B91: NT$B | D91: =m_auto*D83 -> 0.5553352 | E91: =m_auto*E83 -> 2.2213408 | F91: =m_auto*F83 -> 4.4426816 | G91: =m_auto*G83 -> 5.3312179
A92: 其他營收毛利率（FY2026 殘差，之後沿用＋調整） | B92: % | C92: =(a25_gp-m_tk*(C72+C81)-m_auto*C83)/C84 -> 0.28772995 | D92: =(a26_gp-D90-D91)/D84 -> 0.3108293 | E92: =$D92+0 -> 0.3108293 | F92: =$D92+0 -> 0.3108293 | G92: =$D92+0 -> 0.3108293 | K92: Derived：讓 FY2026 毛利等於錨點（含 NRE，毛利率高）
A93: 毛利 | B93: NT$B | C93: =a25_gp -> 8.454 | D93: =a26_gp -> 14.651471 | E93: =E92*E84+E90+E91 -> 28.254921 | F93: =F92*F84+F90+F91 -> 39.416477 | G93: =G92*G84+G90+G91 -> 44.950601
A94: 毛利率 | B94: % | C94: =C93/C85 -> 0.24762016 | D94: =D93/D85 -> 0.21106489 | E94: =E93/E85 -> 0.17999318 | F94: =F93/F85 -> 0.17105336 | G94: =G93/G85 -> 0.16997425
A95: 營業費用 | B95: NT$B | C95: =a25_opx -> 4.104 | D95: =a26_opx -> 5.365972 | E95: =D95*(1+MAX(g_opx_min,phi*E86))+0*E85 -> 7.3965249 | F95: =E95*(1+MAX(g_opx_min,phi*F86))+0*F85 -> 8.4348628 | G95: =F95*(1+MAX(g_opx_min,phi*G86))+0*G85 -> 9.1096519
A96: 營業利益 | B96: NT$B | C96: =C93-C95 -> 4.35 | D96: =D93-D95 -> 9.2854985 | E96: =E93-E95 -> 20.858396 | F96: =F93-F95 -> 30.981615 | G96: =G93-G95 -> 35.840949
A97: 營業利益率 | B97: % | C97: =C96/C85 -> 0.12741279 | D97: =D96/D85 -> 0.13376423 | E97: =E96/E85 -> 0.13287487 | F97: =F96/F85 -> 0.13444908 | G97: =G96/G85 -> 0.13552741
A98: 營業外淨額 | B98: NT$B | C98: =a25_nonop -> 0.092 | D98: =a26_nonop -> 0.384548 | E98: =nonop_f -> 0.5 | F98: =nonop_f -> 0.5 | G98: =nonop_f -> 0.5
A99: 稅前利益 | B99: NT$B | C99: =C96+C98 -> 4.442 | D99: =D96+D98 -> 9.6700465 | E99: =E96+E98 -> 21.358396 | F99: =F96+F98 -> 31.481615 | G99: =G96+G98 -> 36.340949
A100: 所得稅 | B100: NT$B | C100: =a25_tax -> 0.672 | D100: =a26_tax -> 1.3373617 | E100: =E99*tax -> 3.2037594 | F100: =F99*tax -> 4.7222422 | G100: =G99*tax -> 5.4511423
A101: 歸屬母公司淨利 | B101: NT$B | C101: =C99-C100 -> 3.77 | D101: =D99-D100 -> 8.3326848 | E101: =E99-E100 -> 18.154636 | F101: =F99-F100 -> 26.759372 | G101: =G99-G100 -> 30.889806 | H101: =H85*H105 -> 34.548009 | I101: =I85*I105 -> 37.630167 | J101: =J85*J105 -> 39.887977
A102: 加權股數 | B102: 十億股 | C102: =a25_sh -> 0.13402062 | D102: =a26_sh -> 0.13399884 | E102: =q_sh*(1+sh_g) -> 0.13401 | F102: =E102*(1+sh_g) -> 0.13401 | G102: =F102*(1+sh_g) -> 0.13401 | H102: =G102*(1+sh_g) -> 0.13401 | I102: =H102*(1+sh_g) -> 0.13401 | J102: =I102*(1+sh_g) -> 0.13401
A103: EPS（基本） | B103: NT$ | C103: =C101/C102 -> 28.13 | D103: =D101/D102 -> 62.184754 | E103: =E101/E102 -> 135.47225 | F103: =F101/F102 -> 199.68191 | G103: =G101/G102 -> 230.50374 | H103: =H101/H102 -> 257.80172 | I103: =I101/I102 -> 280.80118 | J103: =J101/J102 -> 297.64925
A104: EPS 年增 | B104: % | D104: =D103/C103-1 -> 1.2106205 | E104: =E103/D103-1 -> 1.1785445 | F104: =F103/E103-1 -> 0.47396906 | G104: =G103/F103-1 -> 0.15435467 | H104: =H103/G103-1 -> 0.1184275 | I104: =I103/H103-1 -> 0.089213752 | J104: =J103/I103-1 -> 0.06
A105: 淨利率（歸屬母公司淨利 ÷ 營收） | B105: % | C105: =C101/C85 -> 0.11042442 | D105: =D101/D85 -> 0.12003827 | E105: =E101/E85 -> 0.11565103 | F105: =F101/F85 -> 0.11612607 | G105: =G101/G85 -> 0.11680537 | H105: =$G105+(fade_mA-$G105)*1/3 -> 0.11680537 | I105: =$G105+(fade_mA-$G105)*2/3 -> 0.11680537 | J105: =$G105+(fade_mA-$G105)*3/3 -> 0.11680537
A108: 情境 B（平平）：CY2028 顆數 ×0.8、CY2029 ×0.85（tsmc 情境 B）；配比 0.5；下一代 CPU 份額 90%、單價 ×1.1；其他 ASIC 4%／5%；車用 ×3.0／×1.6；其他營收 +8%／+5%
A109: 項目 | B109: 單位 | C109: FY2025A | D109: FY2026（錨點） | E109: FY2027 | F109: FY2028 | G109: FY2029 | H109: FY2030（收斂） | I109: FY2031（收斂） | J109: FY2032（收斂） | K109: 說明
A110: A. Google 自研 Arm CPU 量產（由下而上；D 欄＝FY2026 校準年；FY(t)＝CY(t)）
A111: Google TPU 市場顆數（含情境係數） | B111: 百萬顆 | D111: =u_tpu_26 -> 3.85 | E111: =u_tpu_27 -> 5.5 | F111: =u_tpu_28*um28_B -> 5.6 | G111: =u_tpu_28*(1+g29_tpu)*um29_B -> 6.8425
A112: CPU 對 TPU 配比 | B112: x | D112: =att26 -> 0.325 | E112: =MAX(0,att_B+0) -> 0.5 | F112: =MAX(0,att_B+0) -> 0.5 | G112: =MAX(0,att_B+0) -> 0.5
A113: 創意占 Google 自研 CPU | B113: % | D113: =gsh26 -> 1 | E113: =gsh26 -> 1 | F113: =MIN(1,gsh28_B) -> 0.9 | G113: =MIN(1,gsh28_B) -> 0.9
A114: 創意 CPU 顆數 | B114: 百萬顆 | D114: =D111*D112*D113 -> 1.25125 | E114: =E111*E112*E113*1 -> 2.75 | F114: =F111*F112*F113*1 -> 2.52 | G114: =G111*G112*G113*1 -> 3.079125
A115: 每顆 CPU 營收（未校準；CY2028 起 × 下一代係數） | B115: US$K | D115: =pc_cpu -> 1 | E115: =pc_cpu -> 1 | F115: =pc_cpu*pfc_B -> 1.1 | G115: =pc_cpu*pfc_B -> 1.1
...

Sheet Val
A1: Val — P/E 估值（新台幣）。結論用「現價 ÷ FY2027、FY2028 EPS（模型）」；目標價＝DCF 與 Comparable 加權（第 0 節）；十年 P/E 規則值（第 3 節，年底落後 P/E）只作參考
A2: 循環位置：創意不是設備股，不套設備市場見頂年；以本模型營收最高的會計年度為見頂年（比照聯發科、世芯；FY(t)＝CY(t)）。營收到 FY2029 仍在增加時，見頂年未知，判為中段
A4: 0. 目標價
A5: 0.1 DCF（股東權益現金流，FY2027–FY2032 明確期＋FY2032 後永續）
A6: 項目 | B6: A（順利） | C6: B（平平） | D6: C（不如預期） | E6: 說明
A7: 情境 EPS（FY2027–FY2032） | E7: PL 頁各情境；FY2030 起為收斂法
A8: FY2027 | B8: =PL!E15 -> 135.47225 | C8: =PL!E29 -> 107.37724 | D8: =PL!E43 -> 74.458545
A9: FY2028 | B9: =PL!F15 -> 199.68191 | C9: =PL!F29 -> 115.17951 | D9: =PL!F43 -> 52.028102
A10: FY2029 | B10: =PL!G15 -> 230.50374 | C10: =PL!G29 -> 132.81922 | D10: =PL!G43 -> 52.438649
A11: FY2030 | B11: =PL!H15 -> 257.80172 | C11: =PL!H29 -> 144.21776 | D11: =PL!H43 -> 51.668876
A12: FY2031 | B12: =PL!I15 -> 280.80118 | C12: =PL!I29 -> 150.61142 | D12: =PL!I43 -> 49.794231
A13: FY2032 | B13: =PL!J15 -> 297.64925 | C13: =PL!J29 -> 151.04174 | D13: =PL!J43 -> 46.883183
A14: 股東現金流＝EPS ×（1 − tp_g ÷ tp_roe）
A15: 再投資率（tp_g ÷ tp_roe，上限 0.8） | B15: =MIN(tp_g/tp_roe,0.8) -> 0.11585248 | E15: ROE 為近三年平均（In 頁 tp_roe）
A16: FY2027 | B16: =B8*(1-$B$15) -> 119.77745 | C16: =C8*(1-$B$15) -> 94.937317 | D16: =D8*(1-$B$15) -> 65.832338
A17: FY2028 | B17: =B9*(1-$B$15) -> 176.54826 | C17: =C9*(1-$B$15) -> 101.83568 | D17: =D9*(1-$B$15) -> 46.000517
A18: FY2029 | B18: =B10*(1-$B$15) -> 203.79931 | C18: =C10*(1-$B$15) -> 117.43178 | D18: =D10*(1-$B$15) -> 46.363501
A19: FY2030 | B19: =B11*(1-$B$15) -> 227.93475 | C19: =C11*(1-$B$15) -> 127.50977 | D19: =D11*(1-$B$15) -> 45.682908
A20: FY2031 | B20: =B12*(1-$B$15) -> 248.26967 | C20: =C12*(1-$B$15) -> 133.16272 | D20: =D12*(1-$B$15) -> 44.025446
A21: FY2032 | B21: =B13*(1-$B$15) -> 263.16585 | C21: =C13*(1-$B$15) -> 133.54318 | D21: =D13*(1-$B$15) -> 41.45165
A22: DCF 情境每股價值（折現率 tp_r） | B22: =MAX(0,SUMPRODUCT(B16:B21,1/(1+tp_r)^{1;2;3;4;5;6})+B21*(1+tp_g)/(tp_r-tp_g)/(1+tp_r)^6) -> 3441.1736 | C22: =MAX(0,SUMPRODUCT(C16:C21,1/(1+tp_r)^{1;2;3;4;5;6})+C21*(1+tp_g)/(tp_r-tp_g)/(1+tp_r)^6) -> 1810.4679 | D22: =MAX(0,SUMPRODUCT(D16:D21,1/(1+tp_r)^{1;2;3;4;5;6})+D21*(1+tp_g)/(tp_r-tp_g)/(1+tp_r)^6) -> 620.20673 | E22: Σ 明確期現金流 ÷ (1＋r)^t ＋ 永續價值 ÷ (1＋r)^6；永續價值＝FY2032 現金流 ×(1＋g)÷(r−g)；基準日 2026 年底；負值取 0
A23: DCF 情境價值推到 12 個月後（×(1＋tp_r)） | B23: =B22*(1+tp_r) -> 3785.2909 | C23: =C22*(1+tp_r) -> 1991.5147 | D23: =D22*(1+tp_r) -> 682.2274
A24: DCF 目標價（情境加權） | B24: =tp_wA*B23+tp_wB*C23+tp_wC*D23 -> 2267.7901 | E24: Σ 權重 × 情境價值 ×(1＋r)；權重見 In 頁
A26: 0.2 Comparable（市場主流同業前瞻 P/E）
A27: 同業與前瞻 P/E | B27: 代號 | C27: 前瞻 12 月 P/E | D27: 日期 | E27: 來源 | F27: 標記
A28: 世芯-KY（Alchip） | B28: 3661.TW | C28: 17.15 | D28: 2026-10-22 | E28: stockanalysis.com forward PE（分析師共識；價格日期如左；與聯發科、世芯模型同日擷取） | F28: Interested-party
A29: 聯發科（MediaTek） | B29: 2454.TW | C29: 38.75 | D29: 2026-10-22 | E29: stockanalysis.com forward PE（分析師共識；價格日期如左；與聯發科、世芯模型同日擷取） | F29: Interested-party
A30: 博通（Broadcom） | B30: AVGO | C30: 18.52 | D30: 2026-10-23 | E30: stockanalysis.com forward PE（分析師共識；價格日期如左；與聯發科、世芯模型同日擷取） | F30: Interested-party
A31: 邁威爾（Marvell） | B31: MRVL | C31: 40.44 | D31: 2026-10-23 | E31: stockanalysis.com forward PE（分析師共識；價格日期如左；與聯發科、世芯模型同日擷取） | F31: Interested-party
A33: 同業前瞻 P/E 中位數 | B33: =MEDIAN(C28:C31) -> 28.635 | E33: ASIC 設計服務與 ASIC 對手（世芯、聯發科、博通、邁威爾）；不含 A 股（非 A 股公司，Andy 2026-10-25 11:53）；智原資料日 2026-09-04 過舊，未列
A34: 12 個月後的前瞻 EPS（情境加權） | B34: =tp_wA*(2/12*B8+10/12*B9)+tp_wB*(2/12*C8+10/12*C9)+tp_wC*(2/12*D8+10/12*D9) -> 124.78696 | E34: 約 2027-10 時的未來 12 月 EPS ≈ 2／12 × FY2027＋10／12 × FY2028（會計年度＝日曆年）
A35: Comparable 目標價 | B35: =B33*B34 -> 3573.2745 | E35: 同業中位數 × 前瞻 EPS
A37: 0.3 結論
A38: 項目 | B38: 數值 | E38: 說明
A39: 目標價（DCF 與 Comparable 加權） | B39: =tp_w_dcf*B24+(1-tp_w_dcf)*tp_comp_adj -> 3968.0419 | E39: tp_w_dcf × DCF＋（1 − tp_w_dcf）× Comparable；tp_w_dcf 見 In 頁
A40: Comparable 目標價（市場主流同業法） | B40: =B35 -> 3573.2745
A41: 市場共識目標價 | B41: =cons_tp -> 6722.37 | E41: stockanalysis：19 位分析師平均 6,722，2026-10-08 擷取
A42: 上檔空間：加權目標價 | B42: =B39/px-1 -> -0.4768567 | E42: 現價＝In 頁 px（2026-10-22 收盤）
A43: 上檔空間：Comparable 目標價 | B43: =B40/px-1 -> -0.5289025
A44: 與市場共識目標價的差距：EPS 因素 | B44: =B34/cons_feps-1 -> 0.53520797 | E44: 本模型前瞻 EPS ÷ 共識前瞻 EPS − 1；共識前瞻 EPS＝2026-10-08 股價 ÷ 前瞻 P/E（In 頁 cons_feps）
A45: 與市場共識目標價的差距：倍數因素 | B45: =(cons_tp/cons_feps)/B33-1 -> 1.8881733 | E45: ="共識目標價隱含 "&TEXT(cons_tp/cons_feps,"0.0")&"x，同業中位數 "&TEXT(B33,"0.0")&"x" -> 共識目標價隱含 82.7x，同業中位數 28.6x
A46: 價格帶（DCF 不如預期～順利） | B46: =TEXT(D23,"#,##0")&"～"&TEXT(B23,"#,##0") -> 682～3,785 | E46: C 情境價值～A 情境價值（推到 12 個月後）
A47: 歷史倍數檢查：現價隱含 P/E 的十年分位（A／B／C） | B47: =IF(px/B9>=MAX($B$86:$B$95),1,IF(px/B9<=MIN($B$86:$B$95),0,PERCENTRANK($B$86:$B$95,px/B9))) -> 0.355 | C47: =IF(px/C9>=MAX($B$86:$B$95),1,IF(px/C9<=MIN($B$86:$B$95),0,PERCENTRANK($B$86:$B$95,px/C9))) -> 0.891 | D47: =IF(px/D9>=MAX($B$86:$B$95),1,IF(px/D9<=MIN($B$86:$B$95),0,PERCENTRANK($B$86:$B$95,px/D9))) -> 1 | E47: 現價 ÷ 各情境 FY2028 EPS 在 2016–2025 年底 P/E（第 5 節兩來源平均）的分位；高於十年最大值記為 100%、低於最小值記為 0%；只作檢查，不進目標價
A48: 目標價方法 | B48: DCF：股東現金流＝EPS ×（1 − g／ROE），r＝10%、g＝4%、ROE 為近三年平均約 35%（再投資率約 12%），FY2027–32 明確期＋永續；創意為輕資產設計服務公司（量產為轉售，資本支出小），不改用淨利＋折舊－資本支出；情境價值負值取 0。Comparable：世芯、聯發科、博通、邁威爾前瞻 P/E 中位數；創意本身前瞻 P/E 約 90–100 倍，遠高於同業，同業法偏向低估市場對創意的定價。主要偏誤：CPU 顆數綁 TPU 顆數與配比，未含一般運算 Axion 的獨立成長；車用、其他營收為簡化成長率；FY2030 起只用收斂法，DCF 偏低估；單一客戶集中（Google CPU 約一半營收）的下行只反映在情境 C。情境對應：A＝順利（tsmc 顆數 A、配比 0.6）、B＝平平（顆數 B、配比 0.5）、C＝不如預期（顆數 C、配比 0.4、下一代 CPU 份額 70%）
A51: 1. 價格與市場隱含倍數
A52: 項目 | B52: A | C52: B | D52: C | E52: 說明
A53: 現價（2026-10-22 收盤） | B53: =px -> 7585
A54: 現價 ÷ FY2026 EPS（錨點） | B54: =px/PL!D15 -> 121.97523 | C54: =px/PL!D29 -> 121.97523 | D54: =px/PL!D43 -> 121.97523 | E54: FY2026 三情境相同（錨點）
A55: 現價 ÷ FY2027 EPS（模型） | B55: =px/PL!E15 -> 55.989326 | C55: =px/PL!E29 -> 70.638808 | D55: =px/PL!E43 -> 101.86876 | E55: FY2027 三情境差在 CPU 配比、其他 ASIC 份額、車用與其他營收（顆數情境係數從 CY2028 開始）
A56: 現價 ÷ FY2028 EPS（模型） | B56: =px/PL!F15 -> 37.985415 | C56: =px/PL!F29 -> 65.853725 | D56: =px/PL!F43 -> 145.7866
A57: 現價 ÷ FY2029 EPS（模型） | B57: =px/PL!G15 -> 32.90619 | C57: =px/PL!G29 -> 57.1077 | D57: =px/PL!G43 -> 144.64522
A58: 未來 12 月 EPS（模型 B）≈ 0.2 × FY2026＋0.8 × FY2027 | B58: =0.2*PL!D29+0.8*PL!E29 -> 98.33874
A59: 現價 ÷ 未來 12 月 EPS（模型 B） | B59: =px/B58 -> 77.131352
A60: 近 12 月 P/E（現價 ÷ 近 12 月 EPS） | B60: =pe_ttm -> 194.98715
A61: 前瞻 P/E（stockanalysis，2026-10-08） | B61: =fpe -> 102.85
A63: 2. 循環位置（本模型營收最高年；FY(t)＝CY(t)）
A64: 情境 | B64: 營收最高年（FY2026–FY2029） | C64: FY2027 判定 | D64: 規則倍數（P/E） | E64: 見頂年是否未知 | F64: 說明
A65: A | B65: =INDEX({2026,2027,2028,2029},MATCH(MAX(PL!D85:G85),PL!D85:G85,0)) -> 2029 | C65: =IF(B65=2029,"中段",IF(2027<B65,"中段",IF(2027=B65,"見頂","谷底"))) -> 中段 | D65: =IF(C65="見頂",pe_peak,IF(C65="谷底",pe_trough,pe_mid)) -> 50.77 | E65: =IF(B65=2029,"是：營收到觀測期末仍在增加","否") -> 是：營收到觀測期末仍在增加 | F65: tools/cycle_position.py excel_rule；營收最高年取代設備市場見頂年
A66: B | B66: =INDEX({2026,2027,2028,2029},MATCH(MAX(PL!D133:G133),PL!D133:G133,0)) -> 2029 | C66: =IF(B66=2029,"中段",IF(2027<B66,"中段",IF(2027=B66,"見頂","谷底"))) -> 中段 | D66: =IF(C66="見頂",pe_peak,IF(C66="谷底",pe_trough,pe_mid)) -> 50.77 | E66: =IF(B66=2029,"是：營收到觀測期末仍在增加","否") -> 是：營收到觀測期末仍在增加 | F66: 同上
A67: C | B67: =INDEX({2026,2027,2028,2029},MATCH(MAX(PL!D181:G181),PL!D181:G181,0)) -> 2027 | C67: =IF(B67=2029,"中段",IF(2027<B67,"中段",IF(2027=B67,"見頂","谷底"))) -> 見頂 | D67: =IF(C67="見頂",pe_peak,IF(C67="谷底",pe_trough,pe_mid)) -> 36.35 | E67: =IF(B67=2029,"是：營收到觀測期末仍在增加","否") -> 否 | F67: 同上
A69: 3. 規則值隱含股價（新台幣；約 FY2027 年底，未折現）＝ FY2027 EPS × 規則倍數
A70: 情境 | B70: FY2027 EPS | C70: （同左） | D70: 規則倍數 | E70: 隱含股價 | F70: 相對現價 | G70: 現價 ÷ FY2027 EPS
A71: A | B71: =PL!E15 -> 135.47225 | C71: =B71 -> 135.47225 | D71: =D65 -> 50.77 | E71: =C71*D71 -> 6877.9262 | F71: =E71/px-1 -> -0.093220012 | G71: =px/C71 -> 55.989326
A72: B | B72: =PL!E29 -> 107.37724 | C72: =B72 -> 107.37724 | D72: =D66 -> 50.77 | E72: =C72*D72 -> 5451.5423 | F72: =E72/px-1 -> -0.28127326 | G72: =px/C72 -> 70.638808
A73: C | B73: =PL!E43 -> 74.458545 | C73: =B73 -> 74.458545 | D73: =D67 -> 36.35 | E73: =C73*D73 -> 2706.5681 | F73: =E73/px-1 -> -0.64316834 | G73: =px/C73 -> 101.86876
A75: 4. What must be true：FY2027 年底價 ＝ 現價 ×（1＋報酬）所需的倍數（FY2028 EPS；約 2027 年底的價格看下一年 EPS）
A76: FY2027 年底價 ÷ 現價 | B76: 所需倍數（÷ FY2028 EPS，A） | C76: 所需倍數（÷ FY2028 EPS，B） | D76: 所需倍數（÷ FY2028 EPS，C） | E76: 對照：十年中位數
A77: 1 | B77: =px*A77/PL!F15 -> 37.985415 | C77: =px*A77/PL!F29 -> 65.853725 | D77: =px*A77/PL!F43 -> 145.7866 | E77: =pe_mid -> 50.77
A78: 1.1 | B78: =px*A78/PL!F15 -> 41.783956 | C78: =px*A78/PL!F29 -> 72.439097 | D78: =px*A78/PL!F43 -> 160.36526 | E78: =pe_mid -> 50.77
A79: 1.21 | B79: =px*A79/PL!F15 -> 45.962352 | C79: =px*A79/PL!F29 -> 79.683007 | D79: =px*A79/PL!F43 -> 176.40178 | E79: =pe_mid -> 50.77
A80: 1.5 | B80: =px*A80/PL!F15 -> 56.978122 | C80: =px*A80/PL!F29 -> 98.780587 | D80: =px*A80/PL!F43 -> 218.6799 | E80: =pe_mid -> 50.77
A81: 2 | B81: =px*A81/PL!F15 -> 75.970829 | C81: =px*A81/PL!F29 -> 131.70745 | D81: =px*A81/PL!F43 -> 291.5732 | E81: =pe_mid -> 50.77
A82: 讀法：1.00＝價格不變、1.21＝一年約 21%。所需倍數低於歷史中位數時，現價相對便宜；倍數是否合理，另看前瞻 P/E 歷史（Bloomberg）。本版未做先驗，無 Andy 合理 P/E 對照。
A84: 5. 十年 P/E（2016–2025 年底；兩來源平均，分位排名用；無負值或 >200 需剔除）
A85: 年底 | B85: 兩來源平均 P/E | C85: companiesmarketcap | D85: 自算
A86: 2016 | B86: =IF(COUNT(C86:D86)=0,"",AVERAGE(C86:D86)) -> 16.9 | C86: =IF(B105="","",B105) -> 16.9 | D86: =IF(C105="","",C105)
A87: 2017 | B87: =IF(COUNT(C87:D87)=0,"",AVERAGE(C87:D87)) -> 35.3 | C87: =IF(B106="","",B106) -> 35.3 | D87: =IF(C106="","",C106)
A88: 2018 | B88: =IF(COUNT(C88:D88)=0,"",AVERAGE(C88:D88)) -> 26.425577 | C88: =IF(B107="","",B107) -> 24.9 | D88: =IF(C107="","",C107) -> 27.951153
A89: 2019 | B89: =IF(COUNT(C89:D89)=0,"",AVERAGE(C89:D89)) -> 48.925687 | C89: =IF(B108="","",B108) -> 46.9 | D89: =IF(C108="","",C108) -> 50.951374
A90: 2020 | B90: =IF(COUNT(C90:D90)=0,"",AVERAGE(C90:D90)) -> 51.685016 | C90: =IF(B109="","",B109) -> 49.9 | D90: =IF(C109="","",C109) -> 53.470032
A91: 2021 | B91: =IF(COUNT(C91:D91)=0,"",AVERAGE(C91:D91)) -> 52.530734 | C91: =IF(B110="","",B110) -> 51.3 | D91: =IF(C110="","",C110) -> 53.761468
A92: 2022 | B92: =IF(COUNT(C92:D92)=0,"",AVERAGE(C92:D92)) -> 22.774576 | C92: =IF(B111="","",B111) -> 22.4 | D92: =IF(C111="","",C111) -> 23.149151
A93: 2023 | B93: =IF(COUNT(C93:D93)=0,"",AVERAGE(C93:D93)) -> 65.681474 | C93: =IF(B112="","",B112) -> 64.9 | D93: =IF(C112="","",C112) -> 66.462949
A94: 2024 | B94: =IF(COUNT(C94:D94)=0,"",AVERAGE(C94:D94)) -> 51.757767 | C94: =IF(B113="","",B113) -> 50.7 | D94: =IF(C113="","",C113) -> 52.815534
A95: 2025 | B95: =IF(COUNT(C95:D95)=0,"",AVERAGE(C95:D95)) -> 74.221063 | C95: =IF(B114="","",B114) -> 72.9 | D95: =IF(C114="","",C114) -> 75.542126
A96: 年數 | B96: =COUNT($B$86:$B$95) -> 10
A100: 6. 十年倍數與規則值（2016–2025 年底；見頂年 25 分位、中段中位數、谷底 75 分位）
A101: 規則（Andy 2026-10-13）：合理倍數＝2016–2025 年底 P/E 依循環位置取分位，兩個來源分別取分位再平均。stockanalysis 2021–2025 年底 P/E（53.78、23.15、66.47、52.82、75.55）與自算相近，只作核對。十年 P/E 多為 NRE 比重高、營收規模小的時期（中位數約 50 倍），創意轉為 turnkey 量產為主後，倍數未必適用。
A103: P/E：十年歷史倍數
A104: 年底 | B104: companiesmarketcap（年底 P/E） | C104: 自算（digrin 12 月未調整股價 ÷ HiStock EPS） | D104: 標記／說明
A105: 2016 | B105: 16.9 | D105: companiesmarketcap（年底 P/E）：Interested-party（資料商；2016–2025 共 10 年）；自算（digrin 12 月未調整股價 ÷ HiStock EPS）：Derived（價格為月資料的 12 月值；EPS：HiStock 2018–2025；2016–2017 EPS 未找到）
A106: 2017 | B106: 35.3
A107: 2018 | B107: 24.9 | C107: =206/7.37 -> 27.951153
A108: 2019 | B108: 46.9 | C108: =241/4.73 -> 50.951374
A109: 2020 | B109: 49.9 | C109: =339/6.34 -> 53.470032
A110: 2021 | B110: 51.3 | C110: =586/10.9 -> 53.761468
A111: 2022 | B111: 22.4 | C111: =641/27.69 -> 23.149151
A112: 2023 | B112: 64.9 | C112: =1740/26.18 -> 66.462949
A113: 2024 | B113: 50.7 | C113: =1360/25.75 -> 52.815534
A114: 2025 | B114: 72.9 | C114: =2125/28.13 -> 75.542126
...

Sheet Recon
A1: Recon — 本模型 vs 公司說法、共識、券商。只作事後對照，不為對上數字而調參數。券商 FY2027–28 估計與法人 CPU 出貨估計為 Interested-party，不用於校準
A3: 項目 | B3: 對照值 | C3: 模型 A | D3: 差距 A | E3: 模型 B | F3: 差距 B | G3: 模型 C | H3: 差距 C | I3: 對照來源 | J3: 說明
A4: A. FY2026 錨點 vs 公司說法與共識
A5: FY2026 營收 vs 共識 | B5: =cons_rev26 -> 59.5 | C5: =PL!D85 -> 69.4169 | D5: =C5/B5-1 -> 0.16667059 | E5: =PL!D133 -> 69.4169 | F5: =E5/B5-1 -> 0.16667059 | G5: =PL!D181 -> 69.4169 | H5: =G5/B5-1 -> 0.16667059 | I5: stockanalysis（17 位；2026-09-04） | J5: 共識資料日在 3Q26 營收公布前；3Q26 營收季增 34.9%，遠高於公司說的高個位數至低雙位數
A6: FY2026 EPS vs 共識 | B6: =cons_eps26 -> 51.74 | C6: =PL!D103 -> 62.184754 | D6: =C6/B6-1 -> 0.20187001 | E6: =PL!D151 -> 62.184754 | F6: =E6/B6-1 -> 0.20187001 | G6: =PL!D199 -> 62.184754 | H6: =G6/B6-1 -> 0.20187001 | I6: stockanalysis（2026-09-04） | J6: 共識區間 45.73–60.51；外資 52.96；優分析 58.23
A7: FY2026 毛利率 vs 公司 20% 以上（百分點） | B7: =co_gm26 -> 0.2 | C7: =PL!D94 -> 0.21106489 | D7: =C7-B7 -> 0.011064892 | E7: =PL!D142 -> 0.21106489 | F7: =E7-B7 -> 0.011064892 | G7: =PL!D190 -> 0.21106489 | H7: =G7-B7 -> 0.011064892 | I7: 優分析 2026-09-22（法說）
A8: FY2026 營業利益率 vs 公司雙位數下限（百分點） | B8: =co_opm26 -> 0.1 | C8: =PL!D97 -> 0.13376423 | D8: =C8-B8 -> 0.033764235 | E8: =PL!D145 -> 0.13376423 | F8: =E8-B8 -> 0.033764235 | G8: =PL!D193 -> 0.13376423 | H8: =G8-B8 -> 0.033764235 | I8: 優分析 2026-09-22（法說）
A9: B. CPU 與車用 vs 法人（市場層 TPU 顆數 × 配比口徑）
A10: CY2027 創意 CPU 顆數 vs 法人約 400 萬顆 | B10: =cpu_u27 -> 4 | C10: =PL!E66 -> 3.3 | D10: =C10/B10-1 -> -0.175 | E10: =PL!E114 -> 2.75 | F10: =E10/B10-1 -> -0.3125 | G10: =PL!E162 -> 2.2 | H10: =G10/B10-1 -> -0.45 | I10: 經濟日報 2026-10-07 | J10: 法人另一說 350 萬顆（2026-09-08）；達到 400 萬顆需配比約 0.73（含一般運算 Axion）
A11: CY2027 達到法人 CPU 顆數所需配比（＝400 萬 ÷ TPU 顆數） | C11: =cpu_u27/PL!E63 -> 0.72727273 | E11: =cpu_u27/PL!E111 -> 0.72727273 | G11: =cpu_u27/PL!E159 -> 0.72727273 | I11: 推導 | J11: 市場層 CY2027 TPU 5.5 百萬顆
A12: FY2027 CPU ÷ 營收 vs 本國投顧 50.3%（百分點） | B12: =dom_cpu27 -> 0.503 | C12: =PL!E87 -> 0.56689308 | D12: =C12-B12 -> 0.063893075 | E12: =PL!E135 -> 0.56952326 | F12: =E12-B12 -> 0.066523262 | G12: =PL!E183 -> 0.58385826 | H12: =G12-B12 -> 0.080858258 | I12: 經濟日報 2026-04-28
A13: FY2027 車用 ÷ 營收 vs 公司雙位數下限（百分點） | B13: =co_auto27 -> 0.1 | C13: =PL!E88 -> 0.088441717 | D13: =C13-B13 -> -0.011558283 | E13: =PL!E136 -> 0.07996685 | F13: =E13-B13 -> -0.02003315 | G13: =PL!E184 -> 0.068316358 | H13: =G13-B13 -> -0.031683642 | I13: 優分析 2026-09-22（法說）
A14: FY2027 車用 ÷ 營收 vs 本國投顧北美車用 34.9%（百分點） | B14: =dom_ts27 -> 0.349 | C14: =PL!E88 -> 0.088441717 | D14: =C14-B14 -> -0.26055828 | E14: =PL!E136 -> 0.07996685 | F14: =E14-B14 -> -0.26903315 | G14: =PL!E184 -> 0.068316358 | H14: =G14-B14 -> -0.28068364 | I14: 經濟日報 2026-04-28 | J14: 本國投顧比重遠高於公司說法；北美專案主要在 2H27 後貢獻
A15: FY2027 每顆創意 CPU 營收（校準後） | C15: =PL!E73 -> 0.84270443 | E15: =PL!E121 -> 0.84270443 | G15: =PL!E169 -> 0.84270443 | I15: 推導 | J15: US$K；k_c × 每顆營收
A16: C. EPS vs 券商與共識（校準未使用）
A17: FY2027 EPS vs 市場共識（Visible Alpha） | B17: =va_eps27 -> 94.24 | C17: =PL!E103 -> 135.47225 | D17: =C17/B17-1 -> 0.43752389 | E17: =PL!E151 -> 107.37724 | F17: =E17/B17-1 -> 0.13940192 | G17: =PL!E199 -> 74.458545 | H17: =G17/B17-1 -> -0.20990508 | I17: 工商時報 2026-07-31 | J17: 資料日在 3Q26 營收公布前
A18: FY2027 EPS vs 外資 | B18: =fb_eps27 -> 104.14 | C18: =PL!E103 -> 135.47225 | D18: =C18/B18-1 -> 0.30086664 | E18: =PL!E151 -> 107.37724 | F18: =E18/B18-1 -> 0.031085428 | G18: =PL!E199 -> 74.458545 | H18: =G18/B18-1 -> -0.28501493 | I18: 工商時報 2026-07-31
A19: FY2027 EPS vs 優分析資料庫 | B19: =ua_eps27 -> 139.12 | C19: =PL!E103 -> 135.47225 | D19: =C19/B19-1 -> -0.026220159 | E19: =PL!E151 -> 107.37724 | F19: =E19/B19-1 -> -0.22816823 | G19: =PL!E199 -> 74.458545 | H19: =G19/B19-1 -> -0.46478906 | I19: 優分析 2026-09-22
A20: FY2028 EPS vs 外資 | B20: =fb_eps28 -> 155.25 | C20: =PL!F103 -> 199.68191 | D20: =C20/B20-1 -> 0.28619586 | E20: =PL!F151 -> 115.17951 | F20: =E20/B20-1 -> -0.25810297 | G20: =PL!F199 -> 52.028102 | H20: =G20/B20-1 -> -0.66487535 | I20: 工商時報 2026-07-31
A21: 共識前瞻 12 月 EPS vs 模型（情境加權 2／12 × FY2027＋10／12 × FY2028） | B21: =cons_feps -> 81.283422 | C21: =Val!B34 -> 124.78696 | D21: =C21/B21-1 -> 0.53520797 | E21: =Val!B34 -> 124.78696 | F21: =E21/B21-1 -> 0.53520797 | G21: =Val!B34 -> 124.78696 | H21: =G21/B21-1 -> 0.53520797 | I21: stockanalysis 前瞻 P/E 推得 | J21: 三欄同值（情境加權）
A22: D. 校準與份額
A23: k_c（CPU 校準係數） | C23: =PL!D69 -> 0.84270443 | E23: =PL!D117 -> 0.84270443 | G23: =PL!D165 -> 0.84270443 | I23: FY2026 CPU 營收 ÷ 未校準 | J23: 接近 1＝法人 CPU 顆數 × 每顆 1,000 美元與 FY2026 CPU 拆分一致
A24: k_o（AI ASIC 校準係數） | C24: =PL!D79 -> 0.36612289 | E24: =PL!D127 -> 0.36612289 | G24: =PL!D175 -> 0.36612289 | I24: FY2026 AI ASIC ÷ 未校準 | J24: < 1：創意 turnkey 只含晶圓與封裝轉售
A25: 其他營收毛利率（FY2026 殘差） | C25: =PL!D92 -> 0.3108293 | E25: =PL!D140 -> 0.3108293 | G25: =PL!D188 -> 0.3108293 | I25: FY2026 毛利殘差 | J25: 含 NRE（毛利率高）；FY2025 NRE 約占營收 34%
A26: CY2028 Broadcom＋Marvell＋聯發科（高）＋創意 其他 ASIC 份額 | B26: 1 | C26: =Units!E16 -> 0.83 | D26: =C26-B26 -> -0.17 | E26: =Units!E17 -> 0.8 | F26: =E26-B26 -> -0.2 | G26: =Units!E18 -> 0.77 | H26: =G26-B26 -> -0.23 | I26: avgo、mrvl、mediatek 成品 | J26: 應 ≤ 100%
A27: E. 預留
A28: R4 產業部署路徑（markets/deploy_path/，尚未建立）：上線後以創意 AI 量產營收 ÷ 部署 GW 對照 Tokenomics 非 NVIDIA 加速器比例 | J28: 預留列：本版無數值

Sheet Sens
A1: Sens — 一次動一個輸入（情境 A；FY2026 恆等於錨點，k_c、k_o 與其他營收毛利率在每個案例內重算）：對 FY2027、FY2028 營收、毛利率與 EPS 的影響。每個案例是一個完整推導區塊（本頁下方）
A3: 案例 | B3: 設定 | C3: FY2027 營收 | D3: FY2027 毛利率 | E3: FY2027 EPS | F3: FY2027 EPS 相對基準 | G3: FY2028 營收 | H3: FY2028 毛利率 | I3: FY2028 EPS | J3: FY2028 EPS 相對基準
A4: 基準（情境 A） | B4: PL 區塊 A | C4: =PL!E85 -> 156.97773 | D4: =PL!E94 -> 0.17999318 | E4: =PL!E103 -> 135.47225 | F4: =E4/E$4-1 -> 0 | G4: =PL!F85 -> 230.43382 | H4: =PL!F94 -> 0.17105336 | I4: =PL!F103 -> 199.68191 | J4: =I4/I$4-1 -> 0
A5: CPU 對 TPU 配比 −0.2 | B5: CY2027 起配比 0.6 → 0.4 | C5: =E65 -> 127.31453 | D5: =E74 -> 0.18931125 | E5: =E83 -> 113.49472 | F5: =E5/E$4-1 -> -0.16222904 | G5: =F65 -> 185.13003 | H5: =F74 -> 0.17865253 | I5: =F83 -> 164.60461 | J5: =I5/I$4-1 -> -0.17566586
A6: CPU 對 TPU 配比 +0.15 | B6: CY2027 起 0.75（含一般運算 Axion） | C6: =E113 -> 179.22513 | D6: =E122 -> 0.17502879 | E6: =E131 -> 151.9554 | F6: =E6/E$4-1 -> 0.12167178 | G6: =F113 -> 264.41166 | H6: =F122 -> 0.16706289 | I6: =F131 -> 226.01134 | J6: =I6/I$4-1 -> 0.13185689
A7: 下一代 CPU 份額 50% | B7: CY2028 起（基準 100%） | C7: =E161 -> 156.97773 | D7: =E170 -> 0.17999318 | E7: =E179 -> 135.47225 | F7: =E7/E$4-1 -> 0 | G7: =F161 -> 162.47813 | H7: =F170 -> 0.18404127 | I7: =F179 -> 142.1705 | J7: =I7/I$4-1 -> -0.28801509
A8: CPU 與 ASIC 顆數 ×0.8 | B8: CY2027 起 | C8: =E209 -> 135.38385 | D8: =E218 -> 0.18637214 | E8: =E227 -> 119.47329 | F8: =E8/E$4-1 -> -0.11809767 | G8: =F209 -> 197.62789 | H8: =F218 -> 0.17620816 | I8: =F227 -> 174.27995 | J8: =I8/I$4-1 -> -0.12721211
A9: CPU 與 ASIC 顆數 ×1.2 | B9: CY2027 起 | C9: =E257 -> 178.57161 | D9: =E266 -> 0.17515698 | E9: =E275 -> 151.47121 | F9: =E9/E$4-1 -> 0.11809767 | G9: =F257 -> 263.23974 | H9: =F266 -> 0.16718337 | I9: =F275 -> 225.098 | J9: =I9/I$4-1 -> 0.12728292
A10: 下一代 CPU 單價 ×1.5 | B10: CY2028 起（基準 ×1.2） | C10: =E305 -> 156.97773 | D10: =E314 -> 0.17999318 | E10: =E323 -> 135.47225 | F10: =E10/E$4-1 -> 0 | G10: =F305 -> 264.41166 | H10: =F314 -> 0.16706289 | I10: =F323 -> 226.8076 | J10: =I10/I$4-1 -> 0.13584451
A11: 下一代 CPU 單價 ×0.8 | B11: CY2028 起 | C11: =E353 -> 156.97773 | D11: =E362 -> 0.17999318 | E11: =E371 -> 135.47225 | F11: =E11/E$4-1 -> 0 | G11: =F353 -> 185.13003 | H11: =F362 -> 0.17865253 | I11: =F371 -> 162.28524 | J11: =I11/I$4-1 -> -0.18728121
A12: 其他 ASIC 份額 +4pt | B12: CY2027 起（Maia 等放量） | C12: =E401 -> 169.63094 | D12: =E410 -> 0.17700999 | E12: =E419 -> 144.84704 | F12: =E12/E$4-1 -> 0.069200826 | G12: =F401 -> 244.49293 | H12: =F410 -> 0.16926769 | I12: =F419 -> 210.43334 | J12: =I12/I$4-1 -> 0.053842806
A13: 其他 ASIC 份額 0 | B13: CY2027 起 | C13: =E449 -> 137.99792 | D13: =E458 -> 0.18549372 | E13: =E467 -> 121.41006 | F13: =E13/E$4-1 -> -0.10380124 | G13: =F449 -> 202.31558 | H13: =F458 -> 0.17536921 | I13: =F467 -> 177.92142 | J13: =I13/I$4-1 -> -0.10897575
A14: 量產毛利率 10% | B14: 基準 13%（＋情境 A 調整 1pt） | C14: =E497 -> 156.97773 | D14: =E506 -> 0.16713982 | E14: =E515 -> 122.67442 | F14: =E14/E$4-1 -> -0.094468313 | G14: =F497 -> 230.43382 | H14: =F506 -> 0.1555289 | I14: =F515 -> 176.9914 | J14: =I14/I$4-1 -> -0.11363327
A15: 量產毛利率 16% | C15: =E545 -> 156.97773 | D15: =E554 -> 0.19284654 | E15: =E563 -> 148.27009 | F15: =E15/E$4-1 -> 0.094468313 | G15: =F545 -> 230.43382 | H15: =F554 -> 0.18657781 | I15: =F563 -> 222.37242 | J15: =I15/I$4-1 -> 0.11363327
A16: 車用 情境 C 路徑 | B16: FY2027 ×2.0、FY2028 ×1.2 | C16: =E593 -> 150.03604 | D16: =E602 -> 0.1809182 | E16: =E611 -> 129.44854 | F16: =E16/E$4-1 -> -0.04446454 | G16: =F593 -> 210.99708 | H16: =F602 -> 0.17207157 | I16: =F611 -> 181.96948 | J16: =I16/I$4-1 -> -0.088703233
A17: 其他營收 情境 C 路徑 | B17: FY2027 −5%、之後 0% | C17: =E641 -> 150.86904 | D17: =E650 -> 0.17469562 | E17: =E659 -> 124.32732 | F17: =E17/E$4-1 -> -0.082267288 | G17: =F641 -> 220.81263 | H17: =F650 -> 0.16496308 | I17: =F659 -> 181.79796 | J17: =I17/I$4-1 -> -0.089562189
A18: 其他營收毛利率 −3pt | B18: FY2027 起 | C18: =E689 -> 156.97773 | D18: =E698 -> 0.17328045 | E18: =E707 -> 128.78852 | F18: =E18/E$4-1 -> -0.049336502 | G18: =F689 -> 230.43382 | H18: =F698 -> 0.16602318 | I18: =F707 -> 192.32981 | J18: =I18/I$4-1 -> -0.036819058
A19: 營業費用彈性 0.6 | B19: 基準 0.3 | C19: =E737 -> 156.97773 | D19: =E746 -> 0.17999318 | E19: =E755 -> 122.59284 | F19: =E19/E$4-1 -> -0.095070479 | G19: =F737 -> 230.43382 | H19: =F746 -> 0.17105336 | I19: =F755 -> 176.60044 | J19: =I19/I$4-1 -> -0.11559116
A20: 營業費用率 +2pt | B20: 營業費用額外 +2% × 營收 | C20: =E785 -> 156.97773 | D20: =E794 -> 0.17999318 | E20: =E803 -> 115.55865 | F20: =E20/E$4-1 -> -0.14699393 | G20: =F785 -> 230.43382 | H20: =F794 -> 0.17105336 | I20: =F803 -> 147.74084 | J20: =I20/I$4-1 -> -0.26011904
A21: 匯率 30 | B21: 基準 32（CPU、ASIC 美元營收換算） | C21: =E833 -> 150.22964 | D21: =E842 -> 0.18178961 | E21: =E851 -> 130.47258 | F21: =E21/E$4-1 -> -0.036905523 | G21: =F833 -> 220.18197 | H21: =F842 -> 0.17249922 | I21: =F851 -> 191.74199 | J21: =I21/I$4-1 -> -0.039762825
A22: 稅率 20% | B22: 基準 15% | C22: =E881 -> 156.97773 | D22: =E890 -> 0.17999318 | E22: =E899 -> 127.5033 | F22: =E22/E$4-1 -> -0.058823529 | G22: =F881 -> 230.43382 | H22: =F890 -> 0.17105336 | I22: =F899 -> 187.93591 | J22: =I22/I$4-1 -> -0.058823529
A23: 情境 B | B23: 顆數 B；配比 0.5；下一代 CPU 份額 90%；其他營收 +8% | C23: =PL!E133 -> 130.21064 | D23: =PL!E142 -> 0.17820939 | E23: =PL!E151 -> 107.37724 | F23: =E23/E$4-1 -> -0.20738575 | G23: =PL!F133 -> 140.10669 | H23: =PL!F142 -> 0.17827073 | I23: =PL!F151 -> 115.17951 | J23: =I23/I$4-1 -> -0.42318503
A24: 情境 C | B24: 顆數 C；配比 0.4；下一代 CPU 份額 70%；量產毛利率 −2pt | C24: =PL!E181 -> 101.61095 | D24: =PL!E190 -> 0.17076511 | E24: =PL!E199 -> 74.458545 | F24: =E24/E$4-1 -> -0.45037789 | G24: =PL!F181 -> 73.276681 | H24: =PL!F190 -> 0.19520879 | I24: =PL!F199 -> 52.028102 | J24: =I24/I$4-1 -> -0.73944509
A26: 讀法：FY2027 最大的單一變數是 CPU 對 TPU 配比（CPU 顆數）與量產毛利率；FY2028 再加上 TPU 顆數情境與下一代 CPU 份額。車用與其他營收的情境差異較小。
A28: 目標價參數（只改 DCF 參數；PL 收斂法的 fade_g 不隨 tp_g 變動）
A29: 案例 | B29: 設定 | C29: DCF 目標價 | D29: Comparable 目標價（相對倍數調整後） | E29: 加權目標價 | F29: 相對基準
A30: 基準 | B30: r 10%、g 4%、DCF 權重 0.5 | C30: =(tp_wA*MAX(0,Val!B8*(1-MIN(tp_g/tp_roe,0.8))/(1+tp_r)^1+Val!B9*(1-MIN(tp_g/tp_roe,0.8))/(1+tp_r)^2+Val!B10*(1-MIN(tp_g/tp_roe,0.8))/(1+tp_r)^3+Val!B11*(1-MIN(tp_g/tp_roe,0.8))/(1+tp_r)^4+Val!B12*(1-MIN(tp_g/tp_roe,0.8))/(1+tp_r)^5+Val!B13*(1-MIN(tp_g/tp_roe,0.8))/(1+tp_r)^6+Val!B13*(1-MIN(tp_g/tp_roe,0.8))*(1+tp_g)/(tp_r-tp_g)/(1+tp_r)^6)+tp_wB*MAX(0,Val!C8*(1-MIN(tp_g/tp_roe,0.8))/(1+tp_r)^1+Val!C9*(1-MIN(tp_g/tp_roe,0.8))/(1+tp_r)^2+Val!C10*(1-MIN(tp_g/tp_roe,0.8))/(1+tp_r)^3+Val!C11*(1-MIN(tp_g/tp_roe,0.8))/(1+tp_r)^4+Val!C12*(1-MIN(tp_g/tp_roe,0.8))/(1+tp_r)^5+Val!C13*(1-MIN(tp_g/tp_roe,0.8))/(1+tp_r)^6+Val!C13*(1-MIN(tp_g/tp_roe,0.8))*(1+tp_g)/(tp_r-tp_g)/(1+tp_r)^6)+tp_wC*MAX(0,Val!D8*(1-MIN(tp_g/tp_roe,0.8))/(1+tp_r)^1+Val!D9*(1-MIN(tp_g/tp_roe,0.8))/(1+tp_r)^2+Val!D10*(1-MIN(tp_g/tp_roe,0.8))/(1+tp_r)^3+Val!D11*(1-MIN(tp_g/tp_roe,0.8))/(1+tp_r)^4+Val!D12*(1-MIN(tp_g/tp_roe,0.8))/(1+tp_r)^5+Val!D13*(1-MIN(tp_g/tp_roe,0.8))/(1+tp_r)^6+Val!D13*(1-MIN(tp_g/tp_roe,0.8))*(1+tp_g)/(tp_r-tp_g)/(1+tp_r)^6))*(1+tp_r) -> 2267.7901 | D30: =tp_comp_adj -> 5668.2937 | E30: =tp_w_dcf*C30+(1-tp_w_dcf)*D30 -> 3968.0419 | F30: =E30/E$30-1 -> 0
A31: 折現率 +1pt | B31: r 11% | C31: =(tp_wA*MAX(0,Val!B8*(1-MIN(tp_g/tp_roe,0.8))/(1+(tp_r+0.01))^1+Val!B9*(1-MIN(tp_g/tp_roe,0.8))/(1+(tp_r+0.01))^2+Val!B10*(1-MIN(tp_g/tp_roe,0.8))/(1+(tp_r+0.01))^3+Val!B11*(1-MIN(tp_g/tp_roe,0.8))/(1+(tp_r+0.01))^4+Val!B12*(1-MIN(tp_g/tp_roe,0.8))/(1+(tp_r+0.01))^5+Val!B13*(1-MIN(tp_g/tp_roe,0.8))/(1+(tp_r+0.01))^6+Val!B13*(1-MIN(tp_g/tp_roe,0.8))*(1+tp_g)/((tp_r+0.01)-tp_g)/(1+(tp_r+0.01))^6)+tp_wB*MAX(0,Val!C8*(1-MIN(tp_g/tp_roe,0.8))/(1+(tp_r+0.01))^1+Val!C9*(1-MIN(tp_g/tp_roe,0.8))/(1+(tp_r+0.01))^2+Val!C10*(1-MIN(tp_g/tp_roe,0.8))/(1+(tp_r+0.01))^3+Val!C11*(1-MIN(tp_g/tp_roe,0.8))/(1+(tp_r+0.01))^4+Val!C12*(1-MIN(tp_g/tp_roe,0.8))/(1+(tp_r+0.01))^5+Val!C13*(1-MIN(tp_g/tp_roe,0.8))/(1+(tp_r+0.01))^6+Val!C13*(1-MIN(tp_g/tp_roe,0.8))*(1+tp_g)/((tp_r+0.01)-tp_g)/(1+(tp_r+0.01))^6)+tp_wC*MAX(0,Val!D8*(1-MIN(tp_g/tp_roe,0.8))/(1+(tp_r+0.01))^1+Val!D9*(1-MIN(tp_g/tp_roe,0.8))/(1+(tp_r+0.01))^2+Val!D10*(1-MIN(tp_g/tp_roe,0.8))/(1+(tp_r+0.01))^3+Val!D11*(1-MIN(tp_g/tp_roe,0.8))/(1+(tp_r+0.01))^4+Val!D12*(1-MIN(tp_g/tp_roe,0.8))/(1+(tp_r+0.01))^5+Val!D13*(1-MIN(tp_g/tp_roe,0.8))/(1+(tp_r+0.01))^6+Val!D13*(1-MIN(tp_g/tp_roe,0.8))*(1+tp_g)/((tp_r+0.01)-tp_g)/(1+(tp_r+0.01))^6))*(1+(tp_r+0.01)) -> 1954.585 | D31: =tp_comp_adj -> 5668.2937 | E31: =tp_w_dcf*C31+(1-tp_w_dcf)*D31 -> 3811.4394 | F31: =E31/E$30-1 -> -0.039465953
A32: 折現率 −1pt | B32: r 9% | C32: =(tp_wA*MAX(0,Val!B8*(1-MIN(tp_g/tp_roe,0.8))/(1+(tp_r-0.01))^1+Val!B9*(1-MIN(tp_g/tp_roe,0.8))/(1+(tp_r-0.01))^2+Val!B10*(1-MIN(tp_g/tp_roe,0.8))/(1+(tp_r-0.01))^3+Val!B11*(1-MIN(tp_g/tp_roe,0.8))/(1+(tp_r-0.01))^4+Val!B12*(1-MIN(tp_g/tp_roe,0.8))/(1+(tp_r-0.01))^5+Val!B13*(1-MIN(tp_g/tp_roe,0.8))/(1+(tp_r-0.01))^6+Val!B13*(1-MIN(tp_g/tp_roe,0.8))*(1+tp_g)/((tp_r-0.01)-tp_g)/(1+(tp_r-0.01))^6)+tp_wB*MAX(0,Val!C8*(1-MIN(tp_g/tp_roe,0.8))/(1+(tp_r-0.01))^1+Val!C9*(1-MIN(tp_g/tp_roe,0.8))/(1+(tp_r-0.01))^2+Val!C10*(1-MIN(tp_g/tp_roe,0.8))/(1+(tp_r-0.01))^3+Val!C11*(1-MIN(tp_g/tp_roe,0.8))/(1+(tp_r-0.01))^4+Val!C12*(1-MIN(tp_g/tp_roe,0.8))/(1+(tp_r-0.01))^5+Val!C13*(1-MIN(tp_g/tp_roe,0.8))/(1+(tp_r-0.01))^6+Val!C13*(1-MIN(tp_g/tp_roe,0.8))*(1+tp_g)/((tp_r-0.01)-tp_g)/(1+(tp_r-0.01))^6)+tp_wC*MAX(0,Val!D8*(1-MIN(tp_g/tp_roe,0.8))/(1+(tp_r-0.01))^1+Val!D9*(1-MIN(tp_g/tp_roe,0.8))/(1+(tp_r-0.01))^2+Val!D10*(1-MIN(tp_g/tp_roe,0.8))/(1+(tp_r-0.01))^3+Val!D11*(1-MIN(tp_g/tp_roe,0.8))/(1+(tp_r-0.01))^4+Val!D12*(1-MIN(tp_g/tp_roe,0.8))/(1+(tp_r-0.01))^5+Val!D13*(1-MIN(tp_g/tp_roe,0.8))/(1+(tp_r-0.01))^6+Val!D13*(1-MIN(tp_g/tp_roe,0.8))*(1+tp_g)/((tp_r-0.01)-tp_g)/(1+(tp_r-0.01))^6))*(1+(tp_r-0.01)) -> 2706.3712 | D32: =tp_comp_adj -> 5668.2937 | E32: =tp_w_dcf*C32+(1-tp_w_dcf)*D32 -> 4187.3325 | F32: =E32/E$30-1 -> 0.055264171
A33: 長期成長 +1pt | B33: g 5% | C33: =(tp_wA*MAX(0,Val!B8*(1-MIN((tp_g+0.01)/tp_roe,0.8))/(1+tp_r)^1+Val!B9*(1-MIN((tp_g+0.01)/tp_roe,0.8))/(1+tp_r)^2+Val!B10*(1-MIN((tp_g+0.01)/tp_roe,0.8))/(1+tp_r)^3+Val!B11*(1-MIN((tp_g+0.01)/tp_roe,0.8))/(1+tp_r)^4+Val!B12*(1-MIN((tp_g+0.01)/tp_roe,0.8))/(1+tp_r)^5+Val!B13*(1-MIN((tp_g+0.01)/tp_roe,0.8))/(1+tp_r)^6+Val!B13*(1-MIN((tp_g+0.01)/tp_roe,0.8))*(1+(tp_g+0.01))/(tp_r-(tp_g+0.01))/(1+tp_r)^6)+tp_wB*MAX(0,Val!C8*(1-MIN((tp_g+0.01)/tp_roe,0.8))/(1+tp_r)^1+Val!C9*(1-MIN((tp_g+0.01)/tp_roe,0.8))/(1+tp_r)^2+Val!C10*(1-MIN((tp_g+0.01)/tp_roe,0.8))/(1+tp_r)^3+Val!C11*(1-MIN((tp_g+0.01)/tp_roe,0.8))/(1+tp_r)^4+Val!C12*(1-MIN((tp_g+0.01)/tp_roe,0.8))/(1+tp_r)^5+Val!C13*(1-MIN((tp_g+0.01)/tp_roe,0.8))/(1+tp_r)^6+Val!C13*(1-MIN((tp_g+0.01)/tp_roe,0.8))*(1+(tp_g+0.01))/(tp_r-(tp_g+0.01))/(1+tp_r)^6)+tp_wC*MAX(0,Val!D8*(1-MIN((tp_g+0.01)/tp_roe,0.8))/(1+tp_r)^1+Val!D9*(1-MIN((tp_g+0.01)/tp_roe,0.8))/(1+tp_r)^2+Val!D10*(1-MIN((tp_g+0.01)/tp_roe,0.8))/(1+tp_r)^3+Val!D11*(1-MIN((tp_g+0.01)/tp_roe,0.8))/(1+tp_r)^4+Val!D12*(1-MIN((tp_g+0.01)/tp_roe,0.8))/(1+tp_r)^5+Val!D13*(1-MIN((tp_g+0.01)/tp_roe,0.8))/(1+tp_r)^6+Val!D13*(1-MIN((tp_g+0.01)/tp_roe,0.8))*(1+(tp_g+0.01))/(tp_r-(tp_g+0.01))/(1+tp_r)^6))*(1+tp_r) -> 2532.6551 | D33: =tp_comp_adj -> 5668.2937 | E33: =tp_w_dcf*C33+(1-tp_w_dcf)*D33 -> 4100.4744 | F33: =E33/E$30-1 -> 0.033374771
A34: 長期成長 −1pt | B34: g 3% | C34: =(tp_wA*MAX(0,Val!B8*(1-MIN((tp_g-0.01)/tp_roe,0.8))/(1+tp_r)^1+Val!B9*(1-MIN((tp_g-0.01)/tp_roe,0.8))/(1+tp_r)^2+Val!B10*(1-MIN((tp_g-0.01)/tp_roe,0.8))/(1+tp_r)^3+Val!B11*(1-MIN((tp_g-0.01)/tp_roe,0.8))/(1+tp_r)^4+Val!B12*(1-MIN((tp_g-0.01)/tp_roe,0.8))/(1+tp_r)^5+Val!B13*(1-MIN((tp_g-0.01)/tp_roe,0.8))/(1+tp_r)^6+Val!B13*(1-MIN((tp_g-0.01)/tp_roe,0.8))*(1+(tp_g-0.01))/(tp_r-(tp_g-0.01))/(1+tp_r)^6)+tp_wB*MAX(0,Val!C8*(1-MIN((tp_g-0.01)/tp_roe,0.8))/(1+tp_r)^1+Val!C9*(1-MIN((tp_g-0.01)/tp_roe,0.8))/(1+tp_r)^2+Val!C10*(1-MIN((tp_g-0.01)/tp_roe,0.8))/(1+tp_r)^3+Val!C11*(1-MIN((tp_g-0.01)/tp_roe,0.8))/(1+tp_r)^4+Val!C12*(1-MIN((tp_g-0.01)/tp_roe,0.8))/(1+tp_r)^5+Val!C13*(1-MIN((tp_g-0.01)/tp_roe,0.8))/(1+tp_r)^6+Val!C13*(1-MIN((tp_g-0.01)/tp_roe,0.8))*(1+(tp_g-0.01))/(tp_r-(tp_g-0.01))/(1+tp_r)^6)+tp_wC*MAX(0,Val!D8*(1-MIN((tp_g-0.01)/tp_roe,0.8))/(1+tp_r)^1+Val!D9*(1-MIN((tp_g-0.01)/tp_roe,0.8))/(1+tp_r)^2+Val!D10*(1-MIN((tp_g-0.01)/tp_roe,0.8))/(1+tp_r)^3+Val!D11*(1-MIN((tp_g-0.01)/tp_roe,0.8))/(1+tp_r)^4+Val!D12*(1-MIN((tp_g-0.01)/tp_roe,0.8))/(1+tp_r)^5+Val!D13*(1-MIN((tp_g-0.01)/tp_roe,0.8))/(1+tp_r)^6+Val!D13*(1-MIN((tp_g-0.01)/tp_roe,0.8))*(1+(tp_g-0.01))/(tp_r-(tp_g-0.01))/(1+tp_r)^6))*(1+tp_r) -> 2083.4171 | D34: =tp_comp_adj -> 5668.2937 | E34: =tp_w_dcf*C34+(1-tp_w_dcf)*D34 -> 3875.8554 | F34: =E34/E$30-1 -> -0.023232236
A35: DCF 權重 0.3 | C35: =(tp_wA*MAX(0,Val!B8*(1-MIN(tp_g/tp_roe,0.8))/(1+tp_r)^1+Val!B9*(1-MIN(tp_g/tp_roe,0.8))/(1+tp_r)^2+Val!B10*(1-MIN(tp_g/tp_roe,0.8))/(1+tp_r)^3+Val!B11*(1-MIN(tp_g/tp_roe,0.8))/(1+tp_r)^4+Val!B12*(1-MIN(tp_g/tp_roe,0.8))/(1+tp_r)^5+Val!B13*(1-MIN(tp_g/tp_roe,0.8))/(1+tp_r)^6+Val!B13*(1-MIN(tp_g/tp_roe,0.8))*(1+tp_g)/(tp_r-tp_g)/(1+tp_r)^6)+tp_wB*MAX(0,Val!C8*(1-MIN(tp_g/tp_roe,0.8))/(1+tp_r)^1+Val!C9*(1-MIN(tp_g/tp_roe,0.8))/(1+tp_r)^2+Val!C10*(1-MIN(tp_g/tp_roe,0.8))/(1+tp_r)^3+Val!C11*(1-MIN(tp_g/tp_roe,0.8))/(1+tp_r)^4+Val!C12*(1-MIN(tp_g/tp_roe,0.8))/(1+tp_r)^5+Val!C13*(1-MIN(tp_g/tp_roe,0.8))/(1+tp_r)^6+Val!C13*(1-MIN(tp_g/tp_roe,0.8))*(1+tp_g)/(tp_r-tp_g)/(1+tp_r)^6)+tp_wC*MAX(0,Val!D8*(1-MIN(tp_g/tp_roe,0.8))/(1+tp_r)^1+Val!D9*(1-MIN(tp_g/tp_roe,0.8))/(1+tp_r)^2+Val!D10*(1-MIN(tp_g/tp_roe,0.8))/(1+tp_r)^3+Val!D11*(1-MIN(tp_g/tp_roe,0.8))/(1+tp_r)^4+Val!D12*(1-MIN(tp_g/tp_roe,0.8))/(1+tp_r)^5+Val!D13*(1-MIN(tp_g/tp_roe,0.8))/(1+tp_r)^6+Val!D13*(1-MIN(tp_g/tp_roe,0.8))*(1+tp_g)/(tp_r-tp_g)/(1+tp_r)^6))*(1+tp_r) -> 2267.7901 | D35: =tp_comp_adj -> 5668.2937 | E35: =0.3*C35+(1-0.3)*D35 -> 4648.1426 | F35: =E35/E$30-1 -> 0.17139454
A36: DCF 權重 0.7 | C36: =(tp_wA*MAX(0,Val!B8*(1-MIN(tp_g/tp_roe,0.8))/(1+tp_r)^1+Val!B9*(1-MIN(tp_g/tp_roe,0.8))/(1+tp_r)^2+Val!B10*(1-MIN(tp_g/tp_roe,0.8))/(1+tp_r)^3+Val!B11*(1-MIN(tp_g/tp_roe,0.8))/(1+tp_r)^4+Val!B12*(1-MIN(tp_g/tp_roe,0.8))/(1+tp_r)^5+Val!B13*(1-MIN(tp_g/tp_roe,0.8))/(1+tp_r)^6+Val!B13*(1-MIN(tp_g/tp_roe,0.8))*(1+tp_g)/(tp_r-tp_g)/(1+tp_r)^6)+tp_wB*MAX(0,Val!C8*(1-MIN(tp_g/tp_roe,0.8))/(1+tp_r)^1+Val!C9*(1-MIN(tp_g/tp_roe,0.8))/(1+tp_r)^2+Val!C10*(1-MIN(tp_g/tp_roe,0.8))/(1+tp_r)^3+Val!C11*(1-MIN(tp_g/tp_roe,0.8))/(1+tp_r)^4+Val!C12*(1-MIN(tp_g/tp_roe,0.8))/(1+tp_r)^5+Val!C13*(1-MIN(tp_g/tp_roe,0.8))/(1+tp_r)^6+Val!C13*(1-MIN(tp_g/tp_roe,0.8))*(1+tp_g)/(tp_r-tp_g)/(1+tp_r)^6)+tp_wC*MAX(0,Val!D8*(1-MIN(tp_g/tp_roe,0.8))/(1+tp_r)^1+Val!D9*(1-MIN(tp_g/tp_roe,0.8))/(1+tp_r)^2+Val!D10*(1-MIN(tp_g/tp_roe,0.8))/(1+tp_r)^3+Val!D11*(1-MIN(tp_g/tp_roe,0.8))/(1+tp_r)^4+Val!D12*(1-MIN(tp_g/tp_roe,0.8))/(1+tp_r)^5+Val!D13*(1-MIN(tp_g/tp_roe,0.8))/(1+tp_r)^6+Val!D13*(1-MIN(tp_g/tp_roe,0.8))*(1+tp_g)/(tp_r-tp_g)/(1+tp_r)^6))*(1+tp_r) -> 2267.7901 | D36: =tp_comp_adj -> 5668.2937 | E36: =0.7*C36+(1-0.7)*D36 -> 3287.9412 | F36: =E36/E$30-1 -> -0.17139454
A40: 案例區塊：CPU 對 TPU 配比 −0.2（情境 A）
A41: 項目 | B41: 單位 | C41: FY2025A | D41: FY2026（錨點） | E41: FY2027 | F41: FY2028 | G41: FY2029 | H41: FY2030（收斂） | I41: FY2031（收斂） | J41: FY2032（收斂） | K41: 說明
A42: A. Google 自研 Arm CPU 量產（由下而上；D 欄＝FY2026 校準年；FY(t)＝CY(t)）
A43: Google TPU 市場顆數（含情境係數） | B43: 百萬顆 | D43: =u_tpu_26 -> 3.85 | E43: =u_tpu_27 -> 5.5 | F43: =u_tpu_28*um28_A -> 7 | G43: =u_tpu_28*(1+g29_tpu)*um29_A -> 8.05
A44: CPU 對 TPU 配比 | B44: x | D44: =att26 -> 0.325 | E44: =MAX(0,att_A+(-0.2)) -> 0.4 | F44: =MAX(0,att_A+(-0.2)) -> 0.4 | G44: =MAX(0,att_A+(-0.2)) -> 0.4
A45: 創意占 Google 自研 CPU | B45: % | D45: =gsh26 -> 1 | E45: =gsh26 -> 1 | F45: =MIN(1,gsh28_A) -> 1 | G45: =MIN(1,gsh28_A) -> 1
A46: 創意 CPU 顆數 | B46: 百萬顆 | D46: =D43*D44*D45 -> 1.25125 | E46: =E43*E44*E45*1 -> 2.2 | F46: =F43*F44*F45*1 -> 2.8 | G46: =G43*G44*G45*1 -> 3.22
A47: 每顆 CPU 營收（未校準；CY2028 起 × 下一代係數） | B47: US$K | D47: =pc_cpu -> 1 | E47: =pc_cpu -> 1 | F47: =pc_cpu*pfc_A -> 1.2 | G47: =pc_cpu*pfc_A -> 1.2
A48: CPU 營收（未校準） | B48: US$B | D48: =D46*D47 -> 1.25125 | E48: =E46*E47 -> 2.2 | F48: =F46*F47 -> 3.36 | G48: =G46*G47 -> 3.864
A49: CPU 校準係數 k_c ＝ FY2026 CPU 營收（錨點）÷ 未校準 | B49: x | D49: =a26_cpu/fx26/D48 -> 0.84270443 | K49: Derived：以 FY2026 錨點的 CPU 拆分校準；FY2027 起沿用。顆數、配比、單價的合併係數
A50: CPU 營收（美元） | B50: US$B | D50: =D48*$D$49 -> 1.0544339 | E50: =E48*$D$49 -> 1.8539498 | F50: =F48*$D$49 -> 2.8314869 | G50: =G48*$D$49 -> 3.2562099
A51: 匯率 | B51: NT$/US$ | D51: =fx26 -> 31.6 | E51: =fx -> 32 | F51: =fx -> 32 | G51: =fx -> 32
A52: Google CPU 量產營收 | B52: NT$B | C52: =a25_cpu -> 6.14538 | D52: =D50*D51 -> 33.320112 | E52: =E50*E51 -> 59.326392 | F52: =F50*F51 -> 90.607581 | G52: =G50*G51 -> 104.19872
A53: 每顆創意 CPU 營收（校準後） | B53: US$K | D53: =IF(D46>0,D50/D46,0) -> 0.84270443 | E53: =IF(E46>0,E50/E46,0) -> 0.84270443 | F53: =IF(F46>0,F50/F46,0) -> 1.0112453 | G53: =IF(G46>0,G50/G46,0) -> 1.0112453
A54: B. AI ASIC 量產（其他 ASIC：Maia 等；由下而上）
A55: 其他 ASIC 市場顆數（含情境係數） | B55: 百萬顆 | D55: =u_oth_26 -> 1 | E55: =u_oth_27 -> 4.5 | F55: =u_oth_28*um28_A -> 5 | G55: =u_oth_28*(1+g29_oth)*um29_A -> 5.75
A56: 創意份額：其他 ASIC | B56: % | D56: =guc_oth_26 -> 0.03 | E56: =MIN(1,MAX(0,go27_A+0)) -> 0.06 | F56: =MIN(1,MAX(0,go28_A+0)) -> 0.08 | G56: =MIN(1,MAX(0,go28_A+0)) -> 0.08
A57: 創意 AI ASIC 顆數 | B57: 百萬顆 | D57: =D55*D56 -> 0.03 | E57: =E55*E56*1 -> 0.27 | F57: =F55*F56*1 -> 0.4 | G57: =G55*G56*1 -> 0.46
A58: AI ASIC 營收（未校準）＝ 顆數 × 每顆核心售價（Broadcom 模型） | B58: US$B | D58: =D57*core_oth -> 0.18 | E58: =E57*core_oth -> 1.62 | F58: =F57*core_oth -> 2.4 | G58: =G57*core_oth -> 2.76
A59: AI ASIC 校準係數 k_o ＝ FY2026 AI ASIC（錨點）÷ 未校準 | B59: x | D59: =a26_asic/fx26/D58 -> 0.36612289 | K59: Derived：k_o < 1＝創意 turnkey 只含晶圓與封裝轉售，低於 Broadcom 的核心售價
A60: AI ASIC 營收（美元） | B60: US$B | D60: =D58*$D$59 -> 0.06590212 | E60: =E58*$D$59 -> 0.59311908 | F60: =F58*$D$59 -> 0.87869494 | G60: =G58*$D$59 -> 1.0104992
A61: AI ASIC 量產營收 | B61: NT$B | C61: =a25_asic -> 1.70705 | D61: =D60*D51 -> 2.082507 | E61: =E60*E51 -> 18.979811 | F61: =F60*F51 -> 28.118238 | G61: =G60*G51 -> 32.335974
A62: C. 車用與其他營收（FY2027 起簡化成長）
A63: 車用（含北美車用客戶 AI 晶片） | B63: NT$B | C63: =a25_auto -> 1.02423 | D63: =a26_auto -> 3.470845 | E63: =D63*am27_A -> 13.88338 | F63: =E63*am28_A -> 27.76676 | G63: =F63*(1+ag29_A) -> 33.320112
A64: 其他（NRE＋BMC、SSD 控制器、加密貨幣等量產） | B64: NT$B | C64: =a25_oth -> 25.26434 | D64: =a26_oth -> 30.543436 | E64: =D64*(1+g_o27_A) -> 35.124951 | F64: =E64*(1+g_oL_A) -> 38.637447 | G64: =F64*(1+g_oL_A) -> 42.501191
A65: 營收 | B65: NT$B | C65: =C52+C61+C63+C64 -> 34.141 | D65: =D52+D61+D63+D64 -> 69.4169 | E65: =E52+E61+E63+E64 -> 127.31453 | F65: =F52+F61+F63+F64 -> 185.13003 | G65: =G52+G61+G63+G64 -> 212.35599 | H65: =G65*(1+H66) -> 237.42307 | I65: =H65*(1+I66) -> 258.55879 | J65: =I65*(1+J66) -> 274.07232 | K65: FY2030 起為收斂法：營收年增由 FY2029 線性收斂到 fade_g、淨利率收斂到 fade_m（FY2032 達到），非驅動因子推導
A66: 營收年增 | B66: % | D66: =D65/C65-1 -> 1.0332416 | E66: =E65/D65-1 -> 0.83405675 | F66: =F65/E65-1 -> 0.4541154 | G66: =G65/F65-1 -> 0.14706404 | H66: =$G66+(fade_gA-$G66)*1/3 -> 0.11804269 | I66: =$G66+(fade_gA-$G66)*2/3 -> 0.089021347 | J66: =$G66+(fade_gA-$G66)*3/3 -> 0.06
A67: Google CPU ÷ 營收 | B67: % | C67: =C52/C65 -> 0.18 | D67: =D52/D65 -> 0.48 | E67: =E52/E65 -> 0.46598287 | F67: =F52/F65 -> 0.48942672 | G67: =G52/G65 -> 0.49067943
A68: 車用 ÷ 營收 | B68: % | C68: =C63/C65 -> 0.03 | D68: =D63/D65 -> 0.05 | E68: =E63/E65 -> 0.10904788 | F68: =F63/F65 -> 0.14998518 | G68: =G63/G65 -> 0.15690686
A69: D. 毛利與損益
A70: AI 量產毛利 ＝（m_tk＋情境調整）×（CPU＋AI ASIC） | B70: NT$B | D70: =m_tk*(D52+D61) -> 4.6023405 | E70: =(m_tk+gta_A)*(E52+E61) -> 10.962868 | F70: =(m_tk+gta_A)*(F52+F61) -> 16.621615 | G70: =(m_tk+gta_A)*(G52+G61) -> 19.114857
A71: 車用毛利 ＝ m_auto × 車用 | B71: NT$B | D71: =m_auto*D63 -> 0.5553352 | E71: =m_auto*E63 -> 2.2213408 | F71: =m_auto*F63 -> 4.4426816 | G71: =m_auto*G63 -> 5.3312179
A72: 其他營收毛利率（FY2026 殘差，之後沿用＋調整） | B72: % | C72: =(a25_gp-m_tk*(C52+C61)-m_auto*C63)/C64 -> 0.28772995 | D72: =(a26_gp-D70-D71)/D64 -> 0.3108293 | E72: =$D72+0 -> 0.3108293 | F72: =$D72+0 -> 0.3108293 | G72: =$D72+0 -> 0.3108293 | K72: Derived：讓 FY2026 毛利等於錨點（含 NRE，毛利率高）
A73: 毛利 | B73: NT$B | C73: =a25_gp -> 8.454 | D73: =a26_gp -> 14.651471 | E73: =E72*E64+E70+E71 -> 24.102073 | F73: =F72*F64+F70+F71 -> 33.073947 | G73: =G72*G64+G70+G71 -> 37.65669
A74: 毛利率 | B74: % | C74: =C73/C65 -> 0.24762016 | D74: =D73/D65 -> 0.21106489 | E74: =E73/E65 -> 0.18931125 | F74: =F73/F65 -> 0.17865253 | G74: =G73/G65 -> 0.17732812
A75: 營業費用 | B75: NT$B | C75: =a25_opx -> 4.104 | D75: =a26_opx -> 5.365972 | E75: =D75*(1+MAX(g_opx_min,phi*E66))+0*E65 -> 6.7086296 | F75: =E75*(1+MAX(g_opx_min,phi*F66))+0*F65 -> 7.6225772 | G75: =F75*(1+MAX(g_opx_min,phi*G66))+0*G65 -> 8.2323833
A76: 營業利益 | B76: NT$B | C76: =C73-C75 -> 4.35 | D76: =D73-D75 -> 9.2854985 | E76: =E73-E75 -> 17.393444 | F76: =F73-F75 -> 25.45137 | G76: =G73-G75 -> 29.424307
A77: 營業利益率 | B77: % | C77: =C76/C65 -> 0.12741279 | D77: =D76/D65 -> 0.13376423 | E77: =E76/E65 -> 0.1366179 | F77: =F76/F65 -> 0.13747835 | G77: =G76/G65 -> 0.13856123
A78: 營業外淨額 | B78: NT$B | C78: =a25_nonop -> 0.092 | D78: =a26_nonop -> 0.384548 | E78: =nonop_f -> 0.5 | F78: =nonop_f -> 0.5 | G78: =nonop_f -> 0.5
A79: 稅前利益 | B79: NT$B | C79: =C76+C78 -> 4.442 | D79: =D76+D78 -> 9.6700465 | E79: =E76+E78 -> 17.893444 | F79: =F76+F78 -> 25.95137 | G79: =G76+G78 -> 29.924307
A80: 所得稅 | B80: NT$B | C80: =a25_tax -> 0.672 | D80: =a26_tax -> 1.3373617 | E80: =E79*tax -> 2.6840166 | F80: =F79*tax -> 3.8927054 | G80: =G79*tax -> 4.488646
A81: 歸屬母公司淨利 | B81: NT$B | C81: =C79-C80 -> 3.77 | D81: =D79-D80 -> 8.3326848 | E81: =E79-E80 -> 15.209427 | F81: =F79-F80 -> 22.058664 | G81: =G79-G80 -> 25.435661 | H81: =H65*H85 -> 28.202867 | I81: =I65*I85 -> 30.45729 | J81: =J65*J85 -> 32.013119
A82: 加權股數 | B82: 十億股 | C82: =a25_sh -> 0.13402062 | D82: =a26_sh -> 0.13399884 | E82: =q_sh*(1+sh_g) -> 0.13401 | F82: =E82*(1+sh_g) -> 0.13401 | G82: =F82*(1+sh_g) -> 0.13401 | H82: =G82*(1+sh_g) -> 0.13401 | I82: =H82*(1+sh_g) -> 0.13401 | J82: =I82*(1+sh_g) -> 0.13401
A83: EPS（基本） | B83: NT$ | C83: =C81/C82 -> 28.13 | D83: =D81/D82 -> 62.184754 | E83: =E81/E82 -> 113.49472 | F83: =F81/F82 -> 164.60461 | G83: =G81/G82 -> 189.8042 | H83: =H81/H82 -> 210.45345 | I83: =I81/I82 -> 227.27625 | J83: =J81/J82 -> 238.88605
A84: EPS 年增 | B84: % | D84: =D83/C83-1 -> 1.2106205 | E84: =E83/D83-1 -> 0.82512127 | F84: =F83/E83-1 -> 0.4503284 | G84: =G83/F83-1 -> 0.15309163 | H84: =H83/G83-1 -> 0.10879237 | I84: =I83/H83-1 -> 0.079935962 | J84: =J83/I83-1 -> 0.051082335
A85: 淨利率（歸屬母公司淨利 ÷ 營收） | B85: % | C85: =C81/C65 -> 0.11042442 | D85: =D81/D65 -> 0.12003827 | E85: =E81/E65 -> 0.1194634 | F85: =F81/F65 -> 0.11915228 | G85: =G81/G65 -> 0.1197784 | H85: =$G85+(fade_mA-$G85)*1/3 -> 0.11878739 | I85: =$G85+(fade_mA-$G85)*2/3 -> 0.11779638 | J85: =$G85+(fade_mA-$G85)*3/3 -> 0.11680537
A88: 案例區塊：CPU 對 TPU 配比 +0.15（情境 A）
A89: 項目 | B89: 單位 | C89: FY2025A | D89: FY2026（錨點） | E89: FY2027 | F89: FY2028 | G89: FY2029 | H89: FY2030（收斂） | I89: FY2031（收斂） | J89: FY2032（收斂） | K89: 說明
A90: A. Google 自研 Arm CPU 量產（由下而上；D 欄＝FY2026 校準年；FY(t)＝CY(t)）
A91: Google TPU 市場顆數（含情境係數） | B91: 百萬顆 | D91: =u_tpu_26 -> 3.85 | E91: =u_tpu_27 -> 5.5 | F91: =u_tpu_28*um28_A -> 7 | G91: =u_tpu_28*(1+g29_tpu)*um29_A -> 8.05
A92: CPU 對 TPU 配比 | B92: x | D92: =att26 -> 0.325 | E92: =MAX(0,att_A+0.15) -> 0.75 | F92: =MAX(0,att_A+0.15) -> 0.75 | G92: =MAX(0,att_A+0.15) -> 0.75
A93: 創意占 Google 自研 CPU | B93: % | D93: =gsh26 -> 1 | E93: =gsh26 -> 1 | F93: =MIN(1,gsh28_A) -> 1 | G93: =MIN(1,gsh28_A) -> 1
A94: 創意 CPU 顆數 | B94: 百萬顆 | D94: =D91*D92*D93 -> 1.25125 | E94: =E91*E92*E93*1 -> 4.125 | F94: =F91*F92*F93*1 -> 5.25 | G94: =G91*G92*G93*1 -> 6.0375
A95: 每顆 CPU 營收（未校準；CY2028 起 × 下一代係數） | B95: US$K | D95: =pc_cpu -> 1 | E95: =pc_cpu -> 1 | F95: =pc_cpu*pfc_A -> 1.2 | G95: =pc_cpu*pfc_A -> 1.2
A96: CPU 營收（未校準） | B96: US$B | D96: =D94*D95 -> 1.25125 | E96: =E94*E95 -> 4.125 | F96: =F94*F95 -> 6.3 | G96: =G94*G95 -> 7.245
A97: CPU 校準係數 k_c ＝ FY2026 CPU 營收（錨點）÷ 未校準 | B97: x | D97: =a26_cpu/fx26/D96 -> 0.84270443 | K97: Derived：以 FY2026 錨點的 CPU 拆分校準；FY2027 起沿用。顆數、配比、單價的合併係數
A98: CPU 營收（美元） | B98: US$B | D98: =D96*$D$97 -> 1.0544339 | E98: =E96*$D$97 -> 3.4761558 | F98: =F96*$D$97 -> 5.3090379 | G98: =G96*$D$97 -> 6.1053936
A99: 匯率 | B99: NT$/US$ | D99: =fx26 -> 31.6 | E99: =fx -> 32 | F99: =fx -> 32 | G99: =fx -> 32
A100: Google CPU 量產營收 | B100: NT$B | C100: =a25_cpu -> 6.14538 | D100: =D98*D99 -> 33.320112 | E100: =E98*E99 -> 111.23699 | F100: =F98*F99 -> 169.88921 | G100: =G98*G99 -> 195.3726
A101: 每顆創意 CPU 營收（校準後） | B101: US$K | D101: =IF(D94>0,D98/D94,0) -> 0.84270443 | E101: =IF(E94>0,E98/E94,0) -> 0.84270443 | F101: =IF(F94>0,F98/F94,0) -> 1.0112453 | G101: =IF(G94>0,G98/G94,0) -> 1.0112453
A102: B. AI ASIC 量產（其他 ASIC：Maia 等；由下而上）
A103: 其他 ASIC 市場顆數（含情境係數） | B103: 百萬顆 | D103: =u_oth_26 -> 1 | E103: =u_oth_27 -> 4.5 | F103: =u_oth_28*um28_A -> 5 | G103: =u_oth_28*(1+g29_oth)*um29_A -> 5.75
A104: 創意份額：其他 ASIC | B104: % | D104: =guc_oth_26 -> 0.03 | E104: =MIN(1,MAX(0,go27_A+0)) -> 0.06 | F104: =MIN(1,MAX(0,go28_A+0)) -> 0.08 | G104: =MIN(1,MAX(0,go28_A+0)) -> 0.08
A105: 創意 AI ASIC 顆數 | B105: 百萬顆 | D105: =D103*D104 -> 0.03 | E105: =E103*E104*1 -> 0.27 | F105: =F103*F104*1 -> 0.4 | G105: =G103*G104*1 -> 0.46
A106: AI ASIC 營收（未校準）＝ 顆數 × 每顆核心售價（Broadcom 模型） | B106: US$B | D106: =D105*core_oth -> 0.18 | E106: =E105*core_oth -> 1.62 | F106: =F105*core_oth -> 2.4 | G106: =G105*core_oth -> 2.76
A107: AI ASIC 校準係數 k_o ＝ FY2026 AI ASIC（錨點）÷ 未校準 | B107: x | D107: =a26_asic/fx26/D106 -> 0.36612289 | K107: Derived：k_o < 1＝創意 turnkey 只含晶圓與封裝轉售，低於 Broadcom 的核心售價
A108: AI ASIC 營收（美元） | B108: US$B | D108: =D106*$D$107 -> 0.06590212 | E108: =E106*$D$107 -> 0.59311908 | F108: =F106*$D$107 -> 0.87869494 | G108: =G106*$D$107 -> 1.0104992
...

Sheet Sources
A1: 來源（公司財報與法說內容多為媒體轉述；券商、資料商、媒體皆為 Interested-party）
A2: 媒體：經濟日報 2026-07-30（2Q26 營收、營業利益、淨利、EPS、毛利率、turnkey 占 83%；1H26） | B2: https://udn.com/news/story/7252/9661575
A3: 媒體：工商時報 2026-07-31（2Q26 EPS；外資 FY2026–28 EPS、目標價 6,500；Visible Alpha 共識） | B3: https://www.ctee.com.tw/news/20260731701051-430201
A4: 媒體：優分析 2026-09-22（法說轉述：3Q26 營收、毛利率、費用方向；全年毛利率 20% 以上；NRE、turnkey 成長；車用占比） | B4: https://uanalyze.com.tw/articles/3528855768
A5: 媒體：優分析 2026-01-30（4Q25 法說：不再給季度區間指引；北美 68%；加密貨幣降為個位數） | B5: https://uanalyze.com.tw/articles/5074646989
A6: 媒體：科技新報（2026 年 9 月營收、前 9 月累計） | B6: https://finance.technews.tw/2026/10/05/guc-3443-202609-financial-report/
A7: 媒體：經濟日報 2026-10-07（3Q26 營收 187.5 億；CPU 出貨 2026 約 125 萬、2027 約 400 萬顆；CPU 對 TPU 1:2） | B7: https://money.udn.com/money/amp/story/5607/9800312
A8: 媒體：經濟日報 2026-09-08（CPU 2027 出貨由 250 萬上修至 350 萬顆；HBM4 PHY、COUPE） | B8: https://money.udn.com/money/amp/story/5607/9741296
A9: 媒體：經濟日報 2026-04-28（本國投顧：2027 CSP CPU 50.3%、北美車用 34.9%；每顆 Arm CPU 配 2 顆 ASIC） | B9: https://money.udn.com/money/amp/story/5607/9468975
A10: 媒體：經濟日報 2026-01-31（FY2025 營收 341.4 億；turnkey 約 64%、NRE 約 34%；AI 約 25%） | B10: https://money.udn.com/money/story/5607/9296878
A11: 券商轉述：科技新報 2026-05-05（摩根士丹利：Google CPU 占營收約一半、北美車用 AI 晶片毛利率高於 15%） | B11: https://technews.tw/2026/05/05/ms-see-guc-2026-q1/
A12: 券商轉述：科技新報 2026-05-08（美銀：1Q26 營收與淨利、Maia 200、Axion 3 奈米） | B12: https://technews.tw/2026/05/08/bofa-see-guc-2026/
A13: 資料商：stockanalysis（股數、近 12 月 EPS、前瞻 P/E、共識目標價） | B13: https://stockanalysis.com/quote/tpe/3443/
... A24: SemiAnalysis | B24: 未使用
