Workbook

Sheet README
A1: 台燿（6274）個股模型 v0.1（AI 半導體 Project：載板與 PCB 次產業；高速 CCL） 2026-10-31
A2: 版本：v0.1（2026-10-31，初版）。樣板 emc/（台光電）；行業變數讀 Siliconomics 快照 v0.10（siliconomics_snapshot_v0.10.json）。
A3: 模型命題：台燿的高速材料（ELL／SLL，M7 以上）營收＝AI 高速 CCL 市場（Siliconomics：部署 GW × 每 GW CCL 金額）× 台燿有效份額 × 年均售價指數，但受月產能 × 每張營收限制（全產全銷）；其他等級（VLL／LL、非低損耗、特殊應用）另依成長率推。份額相對台光電一致（兩家合計 < 100%）。
A4: 核心問題：泰國、常熟、中山新產能（月產能約 235 萬 → 310 萬 → 430 萬 → 530 萬張）開出時，台燿在 AI 伺服器與交換器的 M7 以上份額與單價能撐多久；份額與價格回落時 EPS 還剩多少；現價隱含的路徑合不合理。
A5: 會計年度＝日曆年，FY(t)＝CY(t)。預測期 FY2027–FY2029 由驅動因子推導，FY2030–FY2032 為收斂法。金額：十億新台幣；口徑：歸屬母公司淨利。
A6: 驅動因子：Siliconomics SIF_DeployGW_A／B／C × SIF_CCLperGW（＝SIF_CCLMkt_*）× 匯率 × 台燿有效份額（FY2026 以公司 ELL／SLL 占比校準）× 份額相對值（Assumed，待併入 Siliconomics）× 年均售價指數（Assumed，待併入 Siliconomics）；產能上限＝月產能 × 12 × 每張營收 × 組合指數 × 價格指數。
A7: 估值：Val 第 0 節目標價＝0.5 × DCF 目標價（股東現金流＝EPS ×（1 − tp_g ÷ tp_roe），FY2027–FY2032 明確期＋永續，r 10%、g 4%，三情境權重 0.3／0.5／0.2，推到 12 個月後）＋0.5 × Comparable 目標價（台光電、聯茂、金像電前瞻 P/E 中位數 × 12 個月後前瞻 EPS × 相對倍數係數）。本版未做先驗，無 Andy 合理 P/E 對照。
A8: 已知限制：(1) 高速材料（M7 以上）當作 AI 相關的代理，口徑未經公司確認；(2) 份額相對值、價格指數、組合指數皆 Assumed；(3) 官方營運部門以單一部門處理（財報附註原文未取得）；(4) 十年 P/E 只有 8 年（2016–2017 年 EPS 未找到）；(5) 10 月營收與 3Q26 法說未納入。
A11: 相對倍數調整：加權目標價中的 Comparable 用相對倍數調整後的值（Val 第 0.5 節：同業前瞻倍數中位數 × 本公司 10 年相對同業的倍數比，Bloomberg 前瞻倍數；tools/relative_multiple.py）。「Comparable 目標價（市場主流同業法）」不調整。
A13: In 頁版面（個股模型原則第 8 節）：D／F 欄＝敏感度低／高，只用於 Sens 頁、不進目標價；In 頁最後一節「情境驅動對照」把情境專屬輸入三情境並排（只引用上方各列，純展示）。
A15: ="投資建議："&Val!B43&"（依上檔空間固定規則；加權目標價上檔空間 "&TEXT(Val!B40,"+0.0%;−0.0%")&"）" -> 投資建議：買進（依上檔空間固定規則；加權目標價上檔空間 +44.5%）
A16: 重點觀察 1：目標價 NT$1,828（DCF 1,343、Comparable 相對倍數調整後 2,312 各半），比現價 1,265（2026-10-30）高 44.5%，級距 25%–50%、投資建議買進；Comparable 單獨（市場主流同業法 2,486）為 +96.5%。上檔主因是 EPS：本模型 12 個月後前瞻 EPS 90.44 比共識前瞻 EPS 53.85（stockanalysis 2026-10-22，早於 3Q26 財報 EPS 12.88）高 67.9%；現價只隱含 13.4 倍情境 B 的 FY2028 EPS，同業前瞻 P/E 中位數 27.5 倍。DCF 低於 Comparable，因 ROE 取近三年平均 16%（含 2023 年谷底）。
A17: 重點觀察 2：目標價最敏感的是 AI 高速 CCL 市場與價格：市場係數 ×0.8／×1.2 使加權目標價 −13.9%／+9.4%，2029 年售價指數 0.85 −10.5%、2028 年 0.90 −9.8%，2029 年份額相對值 0.90 −10.0%；DCF 權重 0.3／0.7 為 +10.6%／−10.6%（Sens 頁）。
A18: 重點觀察 3：FY2027 三情境需求面都超過產能（117%），EPS 73.78 由月產能 310 萬張與組合、價格指數決定，比 FactSet 08-04 共識 70.47 高 4.7%；常熟、泰國各 60 萬張 2027Q3 開出是關鍵時點。台光電＋台燿需求面份額 2026–29 年合計 50–56%，低於 100%。下一個檢驗點：10 月營收（約 2026-11-10）與 3Q26 法說（日期未找到）。

Sheet In
A1: In — 輸入（藍字；基準欄 E）。金額：十億新台幣（NT$B），CCL 市場與每 GW 金額為美元；產能：百萬張／月；比例：%。每個輸入附兩個來源（找不到者寫「未找到」）；公司原文算一個。【v0.1】基準欄 E 進主模型；D／F＝敏感度低／高，只用於 Sens 頁（一次動一個參數）、不進目標價；情境 A／B／C 的驅動見本頁最後一節「情境驅動對照」。
A2: 標記：Verified／Interested-party／Analogy／Assumed／Derived；Analogy、Assumed 給低／高區間。公司原文＝台燿財報（公開資訊觀測站，經 HiStock、nstock 轉載）、月營收公告與法說（經富果轉述）；券商估計皆為 Interested-party。行業變數（部署 GW、每 GW CCL 金額、匯率）讀 Siliconomics 快照 v0.10（siliconomics_snapshot_v0.10.json）；本頁不另訂行業路徑。
A3: 鍵 | B3: 項目 | C3: 單位 | D3: 敏感度低 | E3: 基準 | F3: 敏感度高 | G3: 標記 | H3: 來源1 | I3: 來源2／說明
A4: A. AI 部署與每 GW 高速 CCL 金額（讀 Siliconomics 快照；情境 A／B／C 讀同字母上游）
A5: gw_26 | B5: 部署 GW 2026（IT 電力；三情境相同） | C5: GW | E5: 23.399538 | G5: Derived | H5: Siliconomics 快照 v0.10（siliconomics_snapshot_v0.10.json）｜SIF_DeployGW_A[2026] | I5: AI IT 資本支出 ÷ 每 GW IT 資本支出（Siliconomics 推導；Tokenomics 量經 SIF_TK_*）
A6: gw_27 | B6: 部署 GW 2027（三情境相同） | C6: GW | E6: 41.646766 | G6: Derived | H6: Siliconomics 快照 v0.10（siliconomics_snapshot_v0.10.json）｜SIF_DeployGW_A[2027] | I6: 同上；顆數情境係數從 CY2028 開始
A7: gw28_A | B7: 情境 A：部署 GW 2028 | C7: GW | E7: 52.792138 | G7: Derived | H7: Siliconomics 快照 v0.10（siliconomics_snapshot_v0.10.json）｜SIF_DeployGW_A[2028] | I7: A＝顆數基準；B＝CY2028 ×0.8、CY2029 ×0.85；C＝CY2028–29 ×0.6（Siliconomics SIF_UnitsCoef_*；與台光電、台積電模型同一套）
A8: gw28_B | B8: 情境 B：部署 GW 2028 | C8: GW | E8: 42.233711 | G8: Derived | H8: Siliconomics 快照 v0.10（siliconomics_snapshot_v0.10.json）｜SIF_DeployGW_B[2028] | I8: A＝顆數基準；B＝CY2028 ×0.8、CY2029 ×0.85；C＝CY2028–29 ×0.6（Siliconomics SIF_UnitsCoef_*；與台光電、台積電模型同一套）
A9: gw28_C | B9: 情境 C：部署 GW 2028 | C9: GW | E9: 31.675283 | G9: Derived | H9: Siliconomics 快照 v0.10（siliconomics_snapshot_v0.10.json）｜SIF_DeployGW_C[2028] | I9: A＝顆數基準；B＝CY2028 ×0.8、CY2029 ×0.85；C＝CY2028–29 ×0.6（Siliconomics SIF_UnitsCoef_*；與台光電、台積電模型同一套）
A10: gw29_A | B10: 情境 A：部署 GW 2029 | C10: GW | E10: 60.138592 | G10: Derived | H10: Siliconomics 快照 v0.10（siliconomics_snapshot_v0.10.json）｜SIF_DeployGW_A[2029] | I10: A＝顆數基準；B＝CY2028 ×0.8、CY2029 ×0.85；C＝CY2028–29 ×0.6（Siliconomics SIF_UnitsCoef_*；與台光電、台積電模型同一套）
A11: gw29_B | B11: 情境 B：部署 GW 2029 | C11: GW | E11: 51.117803 | G11: Derived | H11: Siliconomics 快照 v0.10（siliconomics_snapshot_v0.10.json）｜SIF_DeployGW_B[2029] | I11: A＝顆數基準；B＝CY2028 ×0.8、CY2029 ×0.85；C＝CY2028–29 ×0.6（Siliconomics SIF_UnitsCoef_*；與台光電、台積電模型同一套）
A12: gw29_C | B12: 情境 C：部署 GW 2029 | C12: GW | E12: 36.083155 | G12: Derived | H12: Siliconomics 快照 v0.10（siliconomics_snapshot_v0.10.json）｜SIF_DeployGW_C[2029] | I12: A＝顆數基準；B＝CY2028 ×0.8、CY2029 ×0.85；C＝CY2028–29 ×0.6（Siliconomics SIF_UnitsCoef_*；與台光電、台積電模型同一套）
A13: pgw_26 | B13: 每 GW 高速 CCL 金額 2026（加速器／運算板＋交換器板＋UBB／中板，不含價格指數） | C13: US$M/GW | E13: 350 | G13: Derived | H13: Siliconomics 快照 v0.10（siliconomics_snapshot_v0.10.json）｜SIF_CCLperGW[2026] | I13: 2026 年三項 190／90／70（Assumed）× 世代指數（Analogy／Assumed）；元件與指數見 Siliconomics In 頁 M16（原在台光電模型）
A14: pgw_27 | B14: 每 GW 高速 CCL 金額 2027（加速器／運算板＋交換器板＋UBB／中板，不含價格指數） | C14: US$M/GW | E14: 527.5 | G14: Derived | H14: Siliconomics 快照 v0.10（siliconomics_snapshot_v0.10.json）｜SIF_CCLperGW[2027] | I14: 2026 年三項 190／90／70（Assumed）× 世代指數（Analogy／Assumed）；元件與指數見 Siliconomics In 頁 M16（原在台光電模型）
A15: pgw_28 | B15: 每 GW 高速 CCL 金額 2028（加速器／運算板＋交換器板＋UBB／中板，不含價格指數） | C15: US$M/GW | E15: 609 | G15: Derived | H15: Siliconomics 快照 v0.10（siliconomics_snapshot_v0.10.json）｜SIF_CCLperGW[2028] | I15: 2026 年三項 190／90／70（Assumed）× 世代指數（Analogy／Assumed）；元件與指數見 Siliconomics In 頁 M16（原在台光電模型）
A16: pgw_29 | B16: 每 GW 高速 CCL 金額 2029（加速器／運算板＋交換器板＋UBB／中板，不含價格指數） | C16: US$M/GW | E16: 662.5 | G16: Derived | H16: Siliconomics 快照 v0.10（siliconomics_snapshot_v0.10.json）｜SIF_CCLperGW[2029] | I16: 2026 年三項 190／90／70（Assumed）× 世代指數（Analogy／Assumed）；元件與指數見 Siliconomics In 頁 M16（原在台光電模型）
A17: fx | B17: 匯率（新台幣 ÷ 美元） | C17: NT$/US$ | D17: 30.5 | E17: 32 | F17: 33 | G17: Derived | H17: Siliconomics 快照 v0.10（siliconomics_snapshot_v0.10.json）｜SIF_fx_twd（與台光電、台達電模型相同） | I17: 低／高只用於 Sens
A18: B. 台燿份額與價格（公司變數；份額相對台光電一致：同一市場兩家合計不得超過 100%，見 Units 頁）
A19: rel_27 | B19: 台燿 AI 高速 CCL 有效份額 2027 ÷ 2026（相對值） | C19: x | D19: 0.95 | E19: 1.1 | F19: 1.25 | G19: Assumed | H19: 泰國廠 2026-07 起量產、4Q26 滿載（公司，富果 2026-07-30）；常熟、泰國各 +60 萬張／月 2027Q3 開出（富果 2026-03-12）；AI ASIC 專案 2026 年貢獻 5–6%（日系外資，旺得富 2026-06-30） | I19: Siliconomics 無 CCL 份額表（ShareTbl 無台燿、台光電）：本列放公司 In 頁，待併入 Siliconomics；台光電模型同期相對值 0.95／0.90／0.85（份額流失給台燿等追趕者）
A20: rel_28 | B20: 台燿 AI 高速 CCL 有效份額 2028 ÷ 2026（相對值） | C20: x | D20: 0.95 | E20: 1.15 | F20: 1.35 | G20: Assumed | H20: 同上 | I20: 待併入 Siliconomics
A21: rel_29 | B21: 台燿 AI 高速 CCL 有效份額 2029 ÷ 2026（相對值） | C21: x | D21: 0.9 | E21: 1.15 | F21: 1.4 | G21: Assumed | H21: 同上 | I21: 待併入 Siliconomics
A22: pp_27 | B22: 台燿 CCL 年均售價指數 2027（FY2026 年均＝1；含 2026 年中漲價的全年效果） | C22: x | D22: 0.97 | E22: 1.05 | F22: 1.12 | G22: Assumed | H22: 毛利率 1Q26 25.2% → 2Q26 29.7% → 3Q26 36.9%（財報），2026 年中漲價使 FY2026 年均價低於年底水準；美系外資預期 M7 以上 CCL 第二波季漲 10–15%（經濟日報 2026-07-20） | I22: 高階 CCL 價格屬行業變數，Siliconomics 尚無價格路徑：待併入 Siliconomics；台光電模型 2027–29 用 1.00／0.97／0.93（以 FY2026 年均為基期，台光電漲價較早）
A23: pp_28 | B23: 台燿 CCL 年均售價指數 2028（FY2026 年均＝1；含 2026 年中漲價的全年效果） | C23: x | D23: 0.9 | E23: 1 | F23: 1.08 | G23: Assumed | H23: 同上 | I23: 新產能到位後回落（Assumed）；待併入 Siliconomics
A24: pp_29 | B24: 台燿 CCL 年均售價指數 2029（FY2026 年均＝1；含 2026 年中漲價的全年效果） | C24: x | D24: 0.85 | E24: 0.95 | F24: 1.03 | G24: Assumed | H24: 同上 | I24: 新產能到位後回落（Assumed）；待併入 Siliconomics
A25: C. 產能（全產全銷：營收上限＝平均月產能 × 12 × 每張營收）
A26: cap_26 | B26: 平均月產能 2026 | C26: 百萬張／月 | D26: 2.25 | E26: 2.35 | F26: 2.45 | G26: Derived | H26: 集團 CCL 月產能逾 220 萬張（官方資料，理財周刊 2026-09-10）；泰國廠 2026-07 起量產、4Q 滿載（富果 2026-07-30） | I26: 市場估 2026 年底約 260 萬張（理財周刊，非公司指引）；年均＝220 萬 → 260 萬的時間加權
A27: cap_27 | B27: 平均月產能 2027 | C27: 百萬張／月 | D27: 2.75 | E27: 3.1 | F27: 3.3 | G27: Derived | H27: 常熟、泰國各 +60 萬張／月，2027Q3 投產（董事會 2026-03-11，富果 2026-03-12）；市場估 2027 年底趨近 380 萬（理財周刊 2026-09-10） | I27: 260 萬 ＋ 120 萬 × 5／12；低值反映設備交期延遲（泰國一期曾延兩個月）
A28: cap_28 | B28: 平均月產能 2028 | C28: 百萬張／月 | D28: 3.8 | E28: 4.3 | F28: 4.7 | G28: Derived | H28: 2028–29 年新增 195 萬張／月：中山 +120 萬、泰國二期 +75 萬（董事會，富果 2026-07-30）；可轉債 100 億元籌資 | I28: 380 萬 ＋ 195 萬於 2028–29 線性開出的年均（Assumed 時程）
A29: cap_29 | B29: 平均月產能 2029 | C29: 百萬張／月 | D29: 4.3 | E29: 5.3 | F29: 5.75 | G29: Assumed | H29: 同上；全部開出為 575 萬張／月 | I29: 低值＝新廠延後一年
A30: mix_27 | B30: 每張營收組合指數 2027（M7／M8 → M8+、層數；不含價格；2026＝1） | C30: x | D30: 1.08 | E30: 1.2 | F30: 1.35 | G30: Assumed | H30: ELL／SLL（M7、M8）占營收：2021 年 10% → 4Q25 36% → 1Q26 38% → 2Q26 39%（公司，富果 2026-03-12、07-30） | I30: AI ASIC 專案用 Low Dk2 玻纖布、HVLP4 銅箔（理財周刊 2026-09-10）；台光電模型組合指數 1.25／1.40／1.50（M9 較早量產）
A31: mix_28 | B31: 每張營收組合指數 2028（M7／M8 → M8+、層數；不含價格；2026＝1） | C31: x | D31: 1.12 | E31: 1.32 | F31: 1.55 | G31: Assumed | H31: 同上 | I31: —
A32: mix_29 | B32: 每張營收組合指數 2029（M7／M8 → M8+、層數；不含價格；2026＝1） | C32: x | D32: 1.15 | E32: 1.42 | F32: 1.7 | G32: Assumed | H32: 同上 | I32: —
A33: D. 營收結構錨點（公司揭露的損耗等級組合 × 營收）
A34: ai_25 | B34: 2025 年高速材料（ELL／SLL，M7 以上）÷ 營收 | C34: % | D34: 0.28 | E34: 0.32 | F34: 0.36 | G34: Assumed | H34: 公司：ELL／SLL 4Q25 36%（富果 2026-03-12）；全年比例未揭露，前三季低於 4Q（Assumed） | I34: 只用於 FY2025 欄的子列拆分
A35: ai_26 | B35: 2026 年高速材料（ELL／SLL，M7 以上）÷ 營收（＝AI 相關的代理） | C35: % | D35: 0.38 | E35: 0.42 | F35: 0.48 | G35: Interested-party | H35: 公司：1Q26 38%、2Q26 39%（富果 2026-07-30）；3Q26 毛利率跳升至 36.9%，高階占比續升（Assumed） | I35: 讀法：AI 伺服器、800G 交換器、AI ASIC 用 M7 以上；M4／M6 的一般伺服器與 400G 以下網通列入其他等級（Assumed 對應）
A36: g_nai27 | B36: 其他等級營收年增 2027（VLL／LL、非低損耗、特殊應用） | C36: % | D36: 0 | E36: 0.1 | F36: 0.18 | G36: Assumed | H36: 特殊應用（厚銅、電源）占營收 3Q25 8% → 2Q26 14%，2025 年年增 49%（公司，富果 2026-03-12、07-30） | I36: 非低損耗占比 18% → 16%（1Q26 → 2Q26）持續下降（公司）
A37: g_nai28 | B37: 其他等級營收年增 2028（VLL／LL、非低損耗、特殊應用） | C37: % | D37: 0 | E37: 0.07 | F37: 0.14 | G37: Assumed | H37: 同上 | I37: —
A38: g_nai29 | B38: 其他等級營收年增 2029（VLL／LL、非低損耗、特殊應用） | C38: % | D38: 0 | E38: 0.05 | F38: 0.1 | G38: Assumed | H38: 同上 | I38: —
A39: E. 毛利率
A40: d_ai | B40: 高速材料毛利率高於其他等級的幅度 | C40: pt | D40: 0.05 | E40: 0.08 | F40: 0.12 | G40: Assumed | H40: 等級別毛利率未揭露：未找到；毛利率隨 M7 以上占比與漲價上升：FY2025 22.7% → 3Q26 36.9%（財報） | I40: 與台光電模型同值（Analogy）
A41: F. FY2026 錨點（1H26、3Q26 財報實績＋4Q26 假設；3Q26 財報已公布，法說日期未找到）
A42: q4g | B42: 4Q26 營收季增 | C42: % | D42: 0 | E42: 0.05 | F42: 0.12 | G42: Assumed | H42: 公司未給 4Q 指引：未找到；9 月營收 61.26 億 × 3＝183.8 億（季增 2.4%，月營收公告） | I42: 泰國廠 4Q 滿載（公司，富果 2026-07-30）
A43: q4_gm | B43: 4Q26 毛利率 | C43: % | D43: 0.34 | E43: 0.36 | F43: 0.38 | G43: Assumed | H43: 3Q26 36.93%（財報；nstock 36.93%） | I43: 銅箔、玻纖布漲價壓縮毛利（公司，富果 2026-03-12）
A44: q4_opx | B44: 4Q26 營業費用 ÷ 營收 | C44: % | D44: 0.055 | E44: 0.06 | F44: 0.065 | G44: Assumed | H44: 3Q26 1.060 ÷ 17.949＝5.9%（財報） | I44: 2Q26 6.2%、FY2025 8.4%
A45: q4_nop | B45: 4Q26 業外收益 | C45: NT$B | D45: -0.1 | E45: 0.03 | F45: 0.15 | G45: Assumed | H45: 3Q26 0.026、2Q26 0.069（財報，稅前 − 營業利益） | I45: —
A46: q_nir | B46: 4Q26 稅後淨利 ÷ 稅前 | C46: % | D46: 0.66 | E46: 0.69 | F46: 0.75 | G46: Derived | H46: 3Q26 3.857 ÷ 5.594＝0.689；2Q26 0.683（財報） | I46: FY2025 0.754（財報）
A47: q_sh | B47: 股數（十億股；EPS 換算） | C47: 十億股 | E47: =3.856631/12.88 -> 0.29942787 | G47: Derived | H47: 3Q26 稅後淨利 38.57 億 ÷ EPS 12.88（HiStock、nstock） | I47: stockanalysis：流通股數 288.78 百萬股；可轉債轉換使加權股數上升
A48: G. 營業費用、業外、稅與股數（FY2027 起）
A49: phi | B49: 營業費用成長對營收成長的彈性 | C49: x | D49: 0.45 | E49: 0.6 | F49: 1 | G49: Derived | H49: FY2026 錨點實測約 0.46（Q 頁 B26） | I49: 與台光電模型同值
A50: nop_f | B50: 業外收益（每年） | C50: NT$B | D50: -0.3 | E50: 0.15 | F50: 0.5 | G50: Assumed | H50: FY2025 0.175、1H26 0.115（財報） | I50: —
A51: nir_f | B51: 稅後淨利 ÷ 稅前 | C51: % | D51: 0.66 | E51: 0.7 | F51: 0.76 | G51: Derived | H51: 1H26 0.680、3Q26 0.689、FY2025 0.754（財報） | I51: —
A52: sh_g | B52: 股數年變動 | C52: % | D52: 0 | E52: 0.01 | F52: 0.025 | G52: Assumed | H52: 董事會通過可轉債面額上限 100 億元、轉換價不低於 110%（優分析 2026-07-30）：全數轉換約稀釋 2.5% | I52: —
A53: mf | B53: AI 高速 CCL 市場係數（Sens 用；FY2027 起） | C53: x | D53: 0.8 | E53: 1 | F53: 1.2 | G53: Assumed | H53: Siliconomics 市場 × 本係數 | I53: ±20%
A54: H. 共識與券商（只作 Recon 對帳，不作校準）
A55: c_eps26f | B55: FactSet 共識 FY2026 EPS 中位數（2026-08-04，15 位） | C55: NT$ | E55: 36.05 | G55: Interested-party | H55: https://www.moneyweekly.com.tw/_Article?AID=247880（理財周刊轉引 FactSet） | I55: 營收中位數約 588.9 億
A56: c_eps27f | B56: FactSet 共識 FY2027 EPS 中位數（2026-08-04） | C56: NT$ | E56: 70.47 | G56: Interested-party | H56: https://www.moneyweekly.com.tw/_Article?AID=247880 | I56: 低 53.91、高 100.07；營收中位數約 1,007 億
A57: c_rev26f | B57: FactSet 共識 FY2026 營收中位數（2026-08-04） | C57: NT$B | E57: 58.89 | G57: Interested-party | H57: https://www.moneyweekly.com.tw/_Article?AID=247880 | I57: —
A58: c_rev27f | B58: FactSet 共識 FY2027 營收中位數（2026-08-04） | C58: NT$B | E58: 100.7 | G58: Interested-party | H58: https://www.moneyweekly.com.tw/_Article?AID=247880 | I58: —
A59: c_eps28f | B59: FactSet 共識 FY2028 EPS（2026-04-20，單一預估） | C59: NT$ | E59: 81.76 | G59: Interested-party | H59: https://news.cnyes.com/news/id/6426189 | I59: 期間早、只有一家，僅供量級參考
A60: b_eps26u | B60: 美系券商 FY2026 EPS（2026-07-20） | C60: NT$ | E60: 38.8 | G60: Interested-party | H60: https://money.udn.com/money/story/5607/9638268（經濟日報，未具名美系券商） | I60: 3Q26 毛利率估 32.3%
A61: b_eps27u | B61: 美系券商 FY2027 EPS（2026-07-20） | C61: NT$ | E61: 93.5 | G61: Interested-party | H61: https://money.udn.com/money/story/5607/9638268 | I61: —
A62: b_eps28u | B62: 美系券商 FY2028 EPS（2026-07-20） | C62: NT$ | E62: 168.7 | G62: Interested-party | H62: https://money.udn.com/money/story/5607/9638268 | I62: —
A63: I. 價格
A64: px | B64: 股價（2026-10-30 收盤） | C64: NT$ | E64: 1265 | G64: Interested-party | H64: HiStock 6274（10-30 13:30 收盤 1,265，−8.99%） | I64: nstock：10-30 收盤 1,265（前收 1,390）
A65: J. 目標價（DCF 與 Comparable 加權）與收斂法參數（黃底＝Assumed，Andy 可改）
A66: tp_wA | B66: 目標價情境權重：情境 A（順利） | C66: 權重 | E66: 0.3 | G66: Assumed | H66: Andy 可改（2026-10-25 目標價規格預設 A／B／C＝0.3／0.5／0.2） | I66: 三個權重合計應為 1
A67: tp_wB | B67: 目標價情境權重：情境 B（平平） | C67: 權重 | E67: 0.5 | G67: Assumed | H67: Andy 可改（2026-10-25 目標價規格預設 A／B／C＝0.3／0.5／0.2） | I67: 三個權重合計應為 1
A68: tp_wC | B68: 目標價情境權重：情境 C（不如預期） | C68: 權重 | E68: 0.2 | G68: Assumed | H68: Andy 可改（2026-10-25 目標價規格預設 A／B／C＝0.3／0.5／0.2） | I68: 三個權重合計應為 1
A69: tp_r | B69: 折現率／要求報酬（DCF） | C69: % | D69: 0.09 | E69: 0.1 | F69: 0.11 | G69: Assumed | H69: Andy 可改（工作單預設 10%；美、台、日、韓同一值） | I69: Sens 頁 ±1pt
A70: tp_g | B70: 長期成長率（DCF 永續；情境 B 的 FY2032 營收年增收斂目標） | C70: % | D70: 0.03 | E70: 0.04 | F70: 0.05 | G70: Assumed | H70: Andy 可改（工作單預設 4%） | I70: Sens 頁 ±1pt（同時移動 PL 收斂目標 fade_g）
A71: tp_roe | B71: ROE（近三年平均） | C71: % | E71: =AVERAGE(0.0703,0.201,0.2069) -> 0.1594 | G71: Derived | H71: stockanalysis 比率頁（Return on Equity）：FY2023 7.03%、FY2024 20.10%、FY2025 20.69% | I71: 單一來源；近 12 月 30.74%（同站，2026-10-26）
A72: tp_w_dcf | B72: 目標價中 DCF 的權重；其餘為 Comparable | C72: % | D72: 0.3 | E72: 0.5 | F72: 0.7 | G72: Assumed | H72: Andy 可改（2026-10-25 11:53：DCF／Comparable 各半） | I72: Sens 頁 0.3／0.7
A73: fade_gA | B73: 情境 A（順利）：FY2032 營收年增收斂目標（tp_g＋2pt） | C73: % | E73: =tp_g+0.02 -> 0.06 | G73: Assumed | H73: 工作單 2026-10-25 11:20 收斂法 | I73: FY2030 起由 FY2029 年增線性收斂，FY2032 達到
A74: fade_gB | B74: 情境 B（平平）：FY2032 營收年增收斂目標（＝tp_g） | C74: % | E74: =tp_g -> 0.04 | G74: Assumed | H74: 同上 | I74: —
A75: fade_gC | B75: 情境 C（不如預期）：FY2032 營收年增收斂目標（tp_g−2pt） | C75: % | E75: =tp_g-0.02 -> 0.02 | G75: Assumed | H75: 同上 | I75: —
A76: nim10_f | B76: 十年平均淨利率的替代：最後一年（FY2029）淨利率 ×（本值） | C76: x | E76: 0.8 | G76: Assumed | H76: 十年（2016–2025）平均淨利率：未找到（2016–2017 年財報數字未取得）；依工作單以最後一年 × 0.8 替代 | I76: 淨利率收斂目標：A＝FY2029、B＝中點、C＝替代值
A77: cons_tp | B77: 市場共識目標價（賣方平均） | C77: NT$ | E77: 2213 | G77: Interested-party | H77: stockanalysis 個股頁 Analyst price target 2,213（頁面時間 2026-10-22） | I77: FactSet 2026-04-20 目標價 900（較舊）；日系外資 2,115（2026-06-30）
A78: cons_feps | B78: 共識前瞻 12 月 EPS（＝價格 ÷ 前瞻 P/E） | C78: NT$ | E78: =1420/26.37 -> 53.849071 | G78: Interested-party | H78: stockanalysis 個股頁（2026-10-22）：價格 1,420 ÷ Forward PE 26.37 | I78: 賣方共識，只作對帳與差距拆解，不作校準
A80: 情境驅動對照（三情境並排，進主模型的加權目標價；本節只引用上方各列，修改請改上方藍字。上方「敏感度低／高」欄只用於 Sens 頁，不進目標價）
A81: 鍵 | B81: 項目 | C81: 單位 | D81: 情境 A（樂觀） | E81: 情境 B（基準） | F81: 情境 C（保守） | G81: 標記 | H81: 說明
A82: scn_gw28 | B82: 部署 GW 2028 | C82: GW | D82: =E7 -> 52.792138 | E82: =E8 -> 42.233711 | F82: =E9 -> 31.675283 | G82: Derived | H82: 引用 In 頁 gw28_A／gw28_B／gw28_C；修改請改上方藍字
A83: scn_gw29 | B83: 部署 GW 2029 | C83: GW | D83: =E10 -> 60.138592 | E83: =E11 -> 51.117803 | F83: =E12 -> 36.083155 | G83: Derived | H83: 引用 In 頁 gw29_A／gw29_B／gw29_C；修改請改上方藍字
A84: scn_fade_g | B84: （不如預期）FY2032 營收年增收斂目標（tp_g−2pt） | C84: % | D84: =E73 -> 0.06 | E84: =E74 -> 0.04 | F84: =E75 -> 0.02 | G84: Derived | H84: 引用 In 頁 fade_gA／fade_gB／fade_gC；修改請改上方藍字
A85: scn_w | B85: 情境權重 | C85: 權重 | D85: =E66 -> 0.3 | E85: =E67 -> 0.5 | F85: =E68 -> 0.2 | G85: Derived | H85: 引用 In 頁 tp_wA／tp_wB／tp_wC；修改請改上方藍字

Sheet Q
A1: Q — 實績與 FY2026 錨點（十億新台幣；EPS 為新台幣；股數為十億股）。藍字＝輸入；黑字＝公式。實績取自台燿合併財報（公開資訊觀測站，經 HiStock 損益表、nstock 轉載）與月營收公告
A2: FY2026 錨點＝1H26 財報＋3Q26 財報（10 月底公布）＋4Q26 假設（營收＝3Q × (1＋季增)、毛利率、營業費用率、業外、稅後 ÷ 稅前）。10 月營收（約 11-10）與 3Q26 法說（日期未找到）後更新
A3: 項目 | B3: FY2025A | C3: 1H26（實績） | D3: 3Q26（實績） | E3: 4Q26（模型） | F3: FY2026 錨點 | G3: 標記 | H3: 來源1 | I3: 來源2／說明
A4: 營收 | B4: =6.372144+6.780435+8.062873+9.124783 -> 30.340235 | C4: =10.053966+14.301042 -> 24.355008 | D4: 17.948807 | E4: =D4*(1+q4g) -> 18.846247 | F4: =SUM(C4:E4) -> 61.150062 | G4: Verified／Assumed（4Q 季增） | H4: HiStock 損益表（季，千元；公開資訊觀測站轉載）：https://histock.tw/stock/6274/損益表 | I4: 月營收：FY2025 303.44 億、1–9 月 423.04 億（HiStock 月營收 https://histock.tw/stock/6274/每月營收）；財報季營收合計 303.40 億
A5: 毛利 | B5: =1.533022+1.435244+1.914793+2.014734 -> 6.897793 | C5: =2.528558+4.249571 -> 6.778129 | D5: 6.628111 | E5: =E4*q4_gm -> 6.784649 | F5: =SUM(C5:E5) -> 20.190889 | G5: Verified／Assumed | H5: HiStock 損益表（季，千元；公開資訊觀測站轉載）：https://histock.tw/stock/6274/損益表 | I5: 1H26 毛利 67.78 億、毛利率 27.83%（工商時報 2026-07-31）；stockanalysis FY2025 毛利 68.98 億
A6: 毛利率 | B6: =B5/B4 -> 0.22734804 | C6: =C5/C4 -> 0.27830535 | D6: =D5/D4 -> 0.36927864 | E6: =E5/E4 -> 0.36 | F6: =F5/F4 -> 0.33018591 | G6: Derived | H6: — | I6: 3Q26 36.93%（nstock）
A7: 營業費用 | B7: =B5-B8 -> 2.554134 | C7: =C5-C8 -> 1.592657 | D7: =D5-D8 -> 1.060103 | E7: =E4*q4_opx -> 1.1307748 | F7: =SUM(C7:E7) -> 3.7835348 | G7: Derived（毛利 − 營業利益）／Assumed | H7: HiStock 損益表（季，千元；公開資訊觀測站轉載）：https://histock.tw/stock/6274/損益表 | I7: nstock 3Q26：毛利率 36.93%、營益率 31.02%、EPS 12.88；1H26：優分析 2026-07-30（營收 243.56 億、EPS 12.4）
A8: 營業利益 | B8: =0.935418+0.852572+1.265539+1.29013 -> 4.343659 | C8: =1.827536+3.357936 -> 5.185472 | D8: 5.568008 | E8: =E5-E7 -> 5.6538742 | F8: =SUM(C8:E8) -> 16.407354 | G8: Verified | H8: HiStock 損益表（季，千元；公開資訊觀測站轉載）：https://histock.tw/stock/6274/損益表 | I8: 1H26 營業利益 51.85 億、營益率 21.29%（工商時報 2026-07-31）
A9: 營業利益率 | B9: =B8/B4 -> 0.14316498 | C9: =C8/C4 -> 0.21291194 | D9: =D8/D4 -> 0.31021605 | E9: =E8/E4 -> 0.3 | F9: =F8/F4 -> 0.26831296 | G9: Derived | H9: — | I9: 3Q26 31.02%（nstock）
A10: 業外收益 | B10: =B11-B8 -> 0.174953 | C10: =C11-C8 -> 0.115316 | D10: =D11-D8 -> 0.026149 | E10: =q4_nop -> 0.03 | F10: =SUM(C10:E10) -> 0.171465 | G10: Derived（稅前 − 營業利益）／Assumed | H10: HiStock 損益表（季，千元；公開資訊觀測站轉載）：https://histock.tw/stock/6274/損益表 | I10: nstock 3Q26：毛利率 36.93%、營益率 31.02%、EPS 12.88；1H26：優分析 2026-07-30（營收 243.56 億、EPS 12.4）
A11: 稅前利益 | B11: =0.934823+0.839586+1.317663+1.42654 -> 4.518612 | C11: =1.873851+3.426937 -> 5.300788 | D11: 5.594157 | E11: =E8+E10 -> 5.6838742 | F11: =SUM(C11:E11) -> 16.578819 | G11: Verified | H11: HiStock 損益表（季，千元；公開資訊觀測站轉載）：https://histock.tw/stock/6274/損益表 | I11: nstock 3Q26：毛利率 36.93%、營益率 31.02%、EPS 12.88；1H26：優分析 2026-07-30（營收 243.56 億、EPS 12.4）
A12: 稅後淨利（歸屬母公司） | B12: =0.671947+0.651731+1.002514+1.082957 -> 3.409149 | C12: 3.602 | D12: 3.856631 | E12: =E11*q_nir -> 3.9218732 | F12: =SUM(C12:E12) -> 11.380504 | G12: Verified／Derived（4Q） | H12: HiStock 損益表（季，千元；公開資訊觀測站轉載）：https://histock.tw/stock/6274/損益表 | I12: 1H26 歸屬母公司淨利 36.02 億（理財周刊 2026-09-10）；HiStock 季稅後淨利 1Q 12.60、2Q 23.42 億
A13: 稅後 ÷ 稅前 | B13: =B12/B11 -> 0.75446819 | C13: =C12/C11 -> 0.67952161 | D13: =D12/D11 -> 0.68940343 | E13: =E12/E11 -> 0.69 | F13: =F12/F11 -> 0.68644842 | G13: Derived | H13: — | I13: —
A14: 股數（十億股） | B14: =B12/12.13 -> 0.28105103 | C14: =C12/12.4 -> 0.29048387 | D14: =q_sh -> 0.29942787 | E14: =q_sh -> 0.29942787 | F14: =q_sh -> 0.29942787 | G14: Derived | H14: HiStock 損益表（季，千元；公開資訊觀測站轉載）：https://histock.tw/stock/6274/損益表 | I14: 淨利 ÷ EPS（加權平均；可轉債轉換使股數上升）
A15: EPS | B15: =B12/B14 -> 12.13 | C15: =C12/C14 -> 12.4 | D15: =D12/D14 -> 12.88 | E15: =E12/E14 -> 13.09789 | F15: =F12/F14 -> 38.007498 | G15: Derived | H15: 淨利 ÷ 股數 | I15: FY2026 以 3Q26 股數換算（低估 1H 股數較少的效果，差約 1%）
A16: 公司揭露 EPS | B16: 12.13 | C16: 12.4 | D16: 12.88 | G16: Verified | H16: HiStock 每股盈餘 https://histock.tw/stock/6274/每股盈餘 | I16: 1Q26 4.36、2Q26 8.02、3Q26 12.88；FY2025 季 2.43／2.36／3.58／3.76（nstock 同值）
A17: 高速材料營收（ELL／SLL，M7 以上；＝營收 × 占比） | B17: =B4*ai_25 -> 9.7088752 | F17: =F4*ai_26 -> 25.683026 | G17: Derived／Interested-party | H17: 公司損耗等級組合（In 頁 D 節） | I17: 各季金額未揭露：未找到
A18: 其他等級營收（＝營收 − 高速材料） | B18: =B4-B17 -> 20.63136 | F18: =F4-F17 -> 35.467036 | G18: Derived | H18: — | I18: VLL／LL（M4、M6）、非低損耗、特殊應用（厚銅、電源）
A23: FY2026 錨點的檢查（參考；校準未使用券商數字）
A24: FY2026 營收年增 | B24: =F4/B4-1 -> 1.0154775
A25: FY2026 營業費用年增 | B25: =F7/B7-1 -> 0.48133764
A26: 營業費用彈性（營業費用年增 ÷ 營收年增；In 頁 phi 的依據） | B26: =B25/B24 -> 0.47400127
A27: FY2026 營收 ÷ FactSet 共識（08-04）− 1 | B27: =F4/c_rev26f-1 -> 0.038377693
A28: FY2026 EPS ÷ 美系券商（07-20）− 1 | B28: =F15/b_eps26u-1 -> -0.020425315
A29: 3Q26 營收季增（實績） | B29: =D4/14.301042-1 -> 0.25506988
A30: 季報合計 − 公司揭露 EPS（FY2025；四捨五入差） | B30: =B15-B16 -> 0

Sheet Units
A1: Units — AI 高速 CCL 市場（Siliconomics）、台燿份額與產能；份額相對台光電一致（同一市場兩家合計 ≤ 100%）。台光電數值讀 emc/dist/20261030_台光電個股模型_v0.3.1.xlsx（唯讀）
A3: 項目 | B3: 單位 | C3: CY2026 | D3: CY2027 | E3: CY2028 | F3: CY2029 | G3: 說明
A4: 部署 GW（情境 A） | B4: GW | C4: =PL!D63 -> 23.399538 | D4: =PL!E63 -> 41.646766 | E4: =PL!F63 -> 52.792138 | F4: =PL!G63 -> 60.138592 | G4: Siliconomics SIF_DeployGW_A
A5: 每 GW 高速 CCL 金額（不含價格指數） | B5: US$M/GW | C5: =PL!D64 -> 350 | D5: =PL!E64 -> 527.5 | E5: =PL!F64 -> 609 | F5: =PL!G64 -> 662.5 | G5: Siliconomics SIF_CCLperGW
A6: AI 高速 CCL 市場（情境 A；不含價格指數） | B6: US$B | C6: =PL!D65 -> 8.1898383 | D6: =PL!E65 -> 21.968669 | E6: =PL!F65 -> 32.150412 | F6: =PL!G65 -> 39.841817 | G6: ＝ SIF_CCLMkt_A
A7: 台燿有效份額（需求面） | B7: % | C7: =PL!D70 -> 0.097998829 | D7: =PL!E70 -> 0.10779871 | E7: =PL!F70 -> 0.11269865 | F7: =PL!G70 -> 0.11269865 | G7: FY2026 以公司 ELL／SLL 占比校準；之後 × 相對值
A8: 台燿高速材料營收（需求面） | B8: US$B | C8: =PL!D71/fx -> 0.80259457 | D8: =PL!E71/fx -> 2.4866039 | E8: =PL!F71/fx -> 3.6233082 | F8: =PL!G71/fx -> 4.2656132 | G8: 含台燿價格指數
A9: 台燿高速材料營收（實際＝MIN 需求面、產能） | B9: US$B | C9: =PL!D78/fx -> 0.80259457 | D9: =PL!E78/fx -> 1.9570459 | E9: =PL!F78/fx -> 3.3110067 | F9: =PL!G78/fx -> 4.2656132
A10: 台燿實際份額（實際營收 ÷ 市場 × 價格指數） | B10: % | C10: =PL!D78/PL!D66/PL!D67 -> 0.097998829 | D10: =PL!E78/PL!E66/PL!E67 -> 0.08484143 | E10: =PL!F78/PL!F66/PL!F67 -> 0.10298489 | F10: =PL!G78/PL!G66/PL!G67 -> 0.11269865 | G10: 產能受限時低於需求面份額
A11: 每 GW 台燿高速材料營收 | B11: US$M/GW | C11: =PL!D85 -> 34.29959 | D11: =PL!E85 -> 46.991547 | E11: =PL!F85 -> 62.717799 | F11: =PL!G85 -> 70.929715
A12: 平均月產能 | B12: 百萬張／月 | C12: =PL!D73 -> 2.35 | D12: =PL!E73 -> 3.1 | E12: =PL!F73 -> 4.3 | F12: =PL!G73 -> 5.3 | G12: 公司擴產計畫
A13: 每張營收（含組合與價格指數） | B13: NT$／張 | C13: =PL!$D$74*PL!D75*PL!D67 -> 2168.4419 | D13: =PL!$D$74*PL!E75*PL!E67 -> 2732.2368 | E13: =PL!$D$74*PL!F75*PL!F67 -> 2862.3433 | F13: =PL!$D$74*PL!G75*PL!G67 -> 2925.2282 | G13: FY2026 校準
A14: 需求面 ÷ 產能上限 | B14: % | C14: =PL!D84 -> 1 | D14: =PL!E84 -> 1.1667256 | E14: =PL!F84 -> 1.0676632 | F14: =PL!G84 -> 0.96929255 | G14: 大於 100%＝產能受限
A15: 台光電有效份額（需求面；台光電成品） | B15: % | C15: 0.45930617 | D15: 0.43634086 | E15: 0.41337555 | F15: 0.39041024 | G15: emc/dist/20261030_台光電個股模型_v0.3.1.xlsx｜Units!C11:F11
A16: 台光電 AI 相關營收（實際；台光電成品） | B16: US$B | C16: 3.7616432 | D16: 7.5134269 | E16: 11.935285 | F16: 14.433479 | G16: emc/dist/20261030_台光電個股模型_v0.3.1.xlsx｜Units!C13:F13
A17: 份額一致性：台光電＋台燿 需求面份額合計 | B17: % | C17: =C15+C7 -> 0.557305 | D17: =D15+D7 -> 0.54413957 | E17: =E15+E7 -> 0.5260742 | F17: =F15+F7 -> 0.50310889 | G17: 同一市場兩家合計須 ≤ 100%（建置時檢查）
A18: 份額一致性：台光電＋台燿 實際營收 ÷ 市場（不含價格指數） | B18: % | C18: =(C16+C9/PL!D67)/C6 -> 0.557305 | D18: =(D16+D9/PL!E67)/D6 -> 0.4268479 | E18: =(E16+E9/PL!F67)/E6 -> 0.4742176 | F18: =(F16+F9/PL!G67)/F6 -> 0.47496825 | G18: 台燿營收除以台燿價格指數；台光電營收含台光電價格指數（口徑近似）
A19: 其他廠商（斗山、生益、松下、聯茂等）＝ 1 − 兩家需求面份額 | B19: % | C19: =1-C17 -> 0.442695 | D19: =1-D17 -> 0.45586043 | E19: =1-E17 -> 0.4739258 | F19: =1-F17 -> 0.49689111
A21: 讀法：每 GW CCL 金額與市場讀 Siliconomics（情境 A 列示；B、C 見 PL 頁）；絕對水準只影響 FY2026 校準出的份額。Siliconomics 尚無 CCL 份額表，台燿份額相對值放本模型 In 頁（待併入 Siliconomics）；台光電份額讀台光電成品，兩家需求面份額合計 2026–29 年皆低於 100%。

Sheet PL
A1: PL — 台燿損益（十億新台幣；EPS 新台幣；歸屬母公司）。FY2025A 實績、FY2026 錨點（1H26、3Q26 財報＋4Q26 假設），FY2027 起為模型。FY(t)＝CY(t)。三情境各一個完整推導區塊（本頁下方），頂端為摘要；最下方延伸到 FY2032（FY2030 起為收斂法）
A3: 情境／項目 | B3: 單位 | C3: FY2025A | D3: FY2026（錨點） | E3: FY2027 | F3: FY2028 | G3: FY2029 | H3: 說明
A4: 情境 A
A5: 營收 | B5: NT$B | C5: =C80 -> 30.340235 | D5: =D80 -> 61.150062 | E5: =E80 -> 101.63921 | F5: =F80 -> 147.69692 | G5: =G80 -> 180.33156
A6: 營收年增 | B6: % | D6: =D81 -> 1.0154775 | E6: =E81 -> 0.66212766 | F6: =F81 -> 0.453149 | G6: =G81 -> 0.22095683
A7: 高速材料營收（M7 以上；AI 相關） | B7: NT$B | C7: =C78 -> 9.7088752 | D7: =D78 -> 25.683026 | E7: =E78 -> 62.62547 | F7: =F78 -> 105.95221 | G7: =G78 -> 136.49962
A8: 其他等級營收 | B8: NT$B | C8: =C77 -> 20.63136 | D8: =D77 -> 35.467036 | E8: =E77 -> 39.01374 | F8: =F77 -> 41.744702 | G8: =G77 -> 43.831937
A9: 需求面 ÷ 產能上限 | B9: % | D9: =D84 -> 1 | E9: =E84 -> 1.1667256 | F9: =F84 -> 1.0676632 | G9: =G84 -> 0.96929255
A10: 毛利率 | B10: % | C10: =C90 -> 0.22734804 | D10: =D90 -> 0.33018591 | E10: =E90 -> 0.36416969 | F10: =F90 -> 0.3539749 | G10: =G90 -> 0.33230481
A11: 營業利益率 | B11: % | C11: =C93 -> 0.14316498 | D11: =D93 -> 0.26831296 | E11: =E93 -> 0.31215585 | F11: =F93 -> 0.30844906 | G11: =G93 -> 0.29007449
A12: 稅後淨利（歸屬母公司） | B12: NT$B | C12: =C95 -> 3.409149 | D12: =D95 -> 11.380504 | E12: =E95 -> 22.314092 | F12: =F95 -> 31.994882 | G12: =G95 -> 36.721709
A13: EPS | B13: NT$ | C13: =C98 -> 12.13 | D13: =D98 -> 38.007498 | E13: =E98 -> 73.784582 | F13: =F98 -> 104.74795 | G13: =G98 -> 119.03277
A14: EPS 年增 | B14: % | D14: =D99 -> 2.1333469 | E14: =E99 -> 0.94131649 | F14: =F99 -> 0.41964553 | G14: =G99 -> 0.13637324
A16: 情境 B
A17: 營收 | B17: NT$B | C17: =C122 -> 30.340235 | D17: =D122 -> 61.150062 | E17: =E122 -> 101.63921 | F17: =F122 -> 134.50139 | G17: =G122 -> 159.85662
A18: 營收年增 | B18: % | D18: =D123 -> 1.0154775 | E18: =E123 -> 0.66212766 | F18: =F123 -> 0.32332188 | G18: =G123 -> 0.18851273
A19: 高速材料營收（M7 以上；AI 相關） | B19: NT$B | C19: =C120 -> 9.7088752 | D19: =D120 -> 25.683026 | E19: =E120 -> 62.62547 | F19: =F120 -> 92.756689 | G19: =G120 -> 116.02468
A20: 其他等級營收 | B20: NT$B | C20: =C119 -> 20.63136 | D20: =D119 -> 35.467036 | E20: =E119 -> 39.01374 | F20: =F119 -> 41.744702 | G20: =G119 -> 43.831937
A21: 需求面 ÷ 產能上限 | B21: % | D21: =D126 -> 1 | E21: =E126 -> 1.1667256 | F21: =F126 -> 0.91065808 | G21: =G126 -> 0.85923855
A22: 毛利率 | B22: % | C22: =C132 -> 0.22734804 | D22: =D132 -> 0.33018591 | E22: =E132 -> 0.36416969 | F22: =F132 -> 0.35175661 | G22: =G132 -> 0.33083571
A23: 營業利益率 | B23: % | C23: =C135 -> 0.14316498 | D23: =D135 -> 0.26831296 | E23: =E135 -> 0.31215585 | F23: =F135 -> 0.30482611 | G23: =G135 -> 0.28688272
A24: 稅後淨利（歸屬母公司） | B24: NT$B | C24: =C137 -> 3.409149 | D24: =D137 -> 11.380504 | E24: =E137 -> 22.314092 | F24: =F137 -> 28.804675 | G24: =G137 -> 32.20707
A25: EPS | B25: NT$ | C25: =C140 -> 12.13 | D25: =D140 -> 38.007498 | E25: =E140 -> 73.784582 | F25: =F140 -> 94.303541 | G25: =G140 -> 104.39865
A26: EPS 年增 | B26: % | D26: =D141 -> 2.1333469 | E26: =E141 -> 0.94131649 | F26: =F141 -> 0.27809277 | G26: =G141 -> 0.10704906
A28: 情境 C
A29: 營收 | B29: NT$B | C29: =C164 -> 30.340235 | D29: =D164 -> 61.150062 | E29: =E164 -> 101.63921 | F29: =F164 -> 111.31222 | G29: =G164 -> 125.73171
A30: 營收年增 | B30: % | D30: =D165 -> 1.0154775 | E30: =E165 -> 0.66212766 | F30: =F165 -> 0.095170048 | G30: =G165 -> 0.12954096
A31: 高速材料營收（M7 以上；AI 相關） | B31: NT$B | C31: =C162 -> 9.7088752 | D31: =D162 -> 25.683026 | E31: =E162 -> 62.62547 | F31: =F162 -> 69.567517 | G31: =G162 -> 81.899773
A32: 其他等級營收 | B32: NT$B | C32: =C161 -> 20.63136 | D32: =D161 -> 35.467036 | E32: =E161 -> 39.01374 | F32: =F161 -> 41.744702 | G32: =G161 -> 43.831937
A33: 需求面 ÷ 產能上限 | B33: % | D33: =D168 -> 1 | E33: =E168 -> 1.1667256 | F33: =F168 -> 0.75365296 | G33: =G168 -> 0.67581521
A34: 毛利率 | B34: % | C34: =C174 -> 0.22734804 | D34: =D174 -> 0.33018591 | E34: =E174 -> 0.36416969 | F34: =F174 -> 0.34658403 | G34: =G174 -> 0.32732395
A35: 營業利益率 | B35: % | C35: =C177 -> 0.14316498 | D35: =D177 -> 0.26831296 | E35: =E177 -> 0.31215585 | F35: =F177 -> 0.29637819 | G35: =G177 -> 0.27942125
A36: 稅後淨利（歸屬母公司） | B36: NT$B | C36: =C179 -> 3.409149 | D36: =D179 -> 11.380504 | E36: =E179 -> 22.314092 | F36: =F179 -> 23.19836 | G36: =G179 -> 24.697478
A37: EPS | B37: NT$ | C37: =C182 -> 12.13 | D37: =D182 -> 38.007498 | E37: =E182 -> 73.784582 | F37: =F182 -> 75.949044 | G37: =G182 -> 80.056439
A38: EPS 年增 | B38: % | D38: =D183 -> 2.1333469 | E38: =E183 -> 0.94131649 | F38: =F183 -> 0.029334876 | G38: =G183 -> 0.054080926
A40: 核對（應為 0）：FY2026 模型營收、高速材料、毛利 − 錨點
A41: 情境 A：營收差（NT$B） | D41: =D80-a26_rev -> 0
A42: 情境 A：高速材料差（NT$B） | D42: =D78-a26_ai -> 0
A43: 情境 A：毛利差（NT$B） | D43: =D88*D78+D87*D77-a26_gp -> 0
A44: 情境 A：產能上限 − 營收（NT$B；FY2026 校準恆等） | D44: =D76-D80 -> 0
A60: 情境 A：順利（Siliconomics 情境 A：顆數基準）
A61: 項目 | B61: 單位 | C61: FY2025A | D61: FY2026（錨點） | E61: FY2027 | F61: FY2028 | G61: FY2029 | H61: 說明
A62: A. AI 高速 CCL 市場（Siliconomics）與台燿份額（需求面；D 欄＝FY2026 校準年）
A63: 部署 GW（IT 電力） | B63: GW | D63: =gw_26 -> 23.399538 | E63: =gw_27 -> 41.646766 | F63: =gw28_A -> 52.792138 | G63: =gw29_A -> 60.138592 | H63: Siliconomics SIF_DeployGW_A
A64: 每 GW 高速 CCL 金額（不含價格指數） | B64: US$M/GW | D64: =pgw_26 -> 350 | E64: =pgw_27 -> 527.5 | F64: =pgw_28 -> 609 | G64: =pgw_29 -> 662.5 | H64: Siliconomics SIF_CCLperGW
A65: AI 高速 CCL 市場（美元；不含價格指數） | B65: US$B | D65: =D63*D64/1000 -> 8.1898383 | E65: =E63*E64/1000*mf -> 21.968669 | F65: =F63*F64/1000*mf -> 32.150412 | G65: =G63*G64/1000*mf -> 39.841817 | H65: ＝ Siliconomics SIF_CCLMkt_A（Recon 核對）；FY2027 起 × mf（Sens 用，基準 1）
A66: AI 高速 CCL 市場（新台幣） | B66: NT$B | D66: =D65*fx -> 262.07483 | E66: =E65*fx -> 702.99741 | F66: =F65*fx -> 1028.8132 | G66: =G65*fx -> 1274.9381
A67: 台燿年均售價指數（FY2026＝1） | B67: x | D67: =1 -> 1 | E67: =pp_27 -> 1.05 | F67: =pp_28 -> 1 | G67: =pp_29 -> 0.95
A68: 台燿有效份額（FY2026 校準）＝ 高速材料營收 ÷ 市場 | B68: % | D68: =a26_ai/D66 -> 0.097998829 | H68: Derived：分子為公司 ELL／SLL 占比 × 營收；分母為 AI 高速 CCL 市場（含 ASIC）
A69: 份額相對值（÷ FY2026） | B69: x | D69: =1 -> 1 | E69: =rel_27 -> 1.1 | F69: =rel_28 -> 1.15 | G69: =rel_29 -> 1.15
A70: 台燿有效份額 | B70: % | D70: =$D$68*D69 -> 0.097998829 | E70: =$D$68*E69 -> 0.10779871 | F70: =$D$68*F69 -> 0.11269865 | G70: =$D$68*G69 -> 0.11269865
A71: 高速材料營收（需求面）＝ 市場 × 份額 × 價格指數 | B71: NT$B | D71: =D66*D70*D67 -> 25.683026 | E71: =E66*E70*E67 -> 79.571326 | F71: =F66*F70*F67 -> 115.94586 | G71: =G66*G70*G67 -> 136.49962
A72: B. 產能上限（全產全銷）與營收
A73: 平均月產能 | B73: 百萬張／月 | D73: =cap_26 -> 2.35 | E73: =cap_27 -> 3.1 | F73: =cap_28 -> 4.3 | G73: =cap_29 -> 5.3
A74: 每張營收（FY2026 校準）＝ 錨點營收 ÷（月產能 × 12） | B74: NT$／張 | D74: =a26_rev/(D73*12)*1000 -> 2168.4419 | H74: Derived：全產全銷，FY2026 營收全部由產能吸收；含膠片與所有等級
A75: 每張營收組合指數（FY2026＝1） | B75: x | D75: =1 -> 1 | E75: =mix_27 -> 1.2 | F75: =mix_28 -> 1.32 | G75: =mix_29 -> 1.42
A76: 產能上限營收 ＝ 月產能 × 12 × 每張營收 × 組合指數 × 價格指數 | B76: NT$B | D76: =D73*12*$D$74*D75*D67/1000 -> 61.150062 | E76: =E73*12*$D$74*E75*E67/1000 -> 101.63921 | F76: =F73*12*$D$74*F75*F67/1000 -> 147.69692 | G76: =G73*12*$D$74*G75*G67/1000 -> 186.04451
A77: 其他等級營收（VLL／LL、非低損耗、特殊應用） | B77: NT$B | C77: =a25_nai -> 20.63136 | D77: =a26_nai -> 35.467036 | E77: =D77*(1+g_nai27) -> 39.01374 | F77: =E77*(1+g_nai28) -> 41.744702 | G77: =F77*(1+g_nai29) -> 43.831937
A78: 高速材料營收（ELL／SLL，M7 以上；AI 相關）＝ MIN（需求面、產能上限 − 其他等級） | B78: NT$B | C78: =a25_ai -> 9.7088752 | D78: =D71 -> 25.683026 | E78: =MIN(E71,E76-E77) -> 62.62547 | F78: =MIN(F71,F76-F77) -> 105.95221 | G78: =MIN(G71,G76-G77) -> 136.49962 | H78: 產能不足時，其他等級照成長率出貨、高速材料取剩餘產能（Assumed）
A79: 產能是否受限 | E79: =IF(E71>E76-E77+0.0001,"受限","未受限") -> 受限 | F79: =IF(F71>F76-F77+0.0001,"受限","未受限") -> 受限 | G79: =IF(G71>G76-G77+0.0001,"受限","未受限") -> 未受限
A80: 營收（單一應報導部門：銅箔基板與膠片） | B80: NT$B | C80: =C78+C77 -> 30.340235 | D80: =D78+D77 -> 61.150062 | E80: =E78+E77 -> 101.63921 | F80: =F78+F77 -> 147.69692 | G80: =G78+G77 -> 180.33156 | H80: 官方分部（segments.json）；子列＝高速材料＋其他等級
A81: 營收年增 | B81: % | D81: =D80/C80-1 -> 1.0154775 | E81: =E80/D80-1 -> 0.66212766 | F81: =F80/E80-1 -> 0.453149 | G81: =G80/F80-1 -> 0.22095683
A82: 檢查：分部合計 − 合併營收 | B82: NT$B | C82: =C78+C77-C80 -> 0 | D82: =D78+D77-D80 -> 0 | E82: =E78+E77-E80 -> 0 | F82: =F78+F77-F80 -> 0 | G82: =G78+G77-G80 -> 0 | H82: 子列（高速材料＋其他等級）合計 − 單一部門營收；FY2025、FY2026 單一部門營收＝財報（Q 頁）
A83: 高速材料 ÷ 營收 | B83: % | C83: =C78/C80 -> 0.32 | D83: =D78/D80 -> 0.42 | E83: =E78/E80 -> 0.61615463 | F83: =F78/F80 -> 0.7173624 | G83: =G78/G80 -> 0.75693696
A84: 需求面 ÷ 產能上限（高速材料需求面＋其他等級） | B84: % | D84: =(D71+D77)/D76 -> 1 | E84: =(E71+E77)/E76 -> 1.1667256 | F84: =(F71+F77)/F76 -> 1.0676632 | G84: =(G71+G77)/G76 -> 0.96929255 | H84: 大於 100%＝需求超過產能（營收由產能決定）
A85: 每 GW 台燿高速材料營收 | B85: US$M/GW | D85: =D78/fx/D63*1000 -> 34.29959 | E85: =E78/fx/E63*1000 -> 46.991547 | F85: =F78/fx/F63*1000 -> 62.717799 | G85: =G78/fx/G63*1000 -> 70.929715
A86: C. 損益
A87: 其他等級毛利率 ＝ 錨點毛利率 − 差距 × 高速材料占比（FY2026 校準） | B87: % | D87: =a26_gp/D80-d_ai*D83 -> 0.29658591 | H87: Derived：讓 FY2026 毛利率等於錨點；高速材料毛利率＝其他＋差距
A88: 高速材料毛利率 ＝ 1 −（1 − 校準值）÷ 價格指數 | B88: % | D88: =D87+d_ai -> 0.37658591 | E88: =1-(1-$D$88)/E67 -> 0.4062723 | F88: =1-(1-$D$88)/F67 -> 0.37658591 | G88: =1-(1-$D$88)/G67 -> 0.34377464 | H88: Derived：每張成本不變，價格升降全部落在毛利（組合升級的毛利效果未另計）
A89: 毛利 | B89: NT$B | C89: =a25_gp -> 6.897793 | D89: =a26_gp -> 20.190889 | E89: =E78*E88+E77*$D$87 -> 37.013919 | F89: =F78*F88+F77*$D$87 -> 52.281002 | G89: =G78*G88+G77*$D$87 -> 59.925044
A90: 毛利率 | B90: % | C90: =C89/C80 -> 0.22734804 | D90: =D89/D80 -> 0.33018591 | E90: =E89/E80 -> 0.36416969 | F90: =F89/F80 -> 0.3539749 | G90: =G89/G80 -> 0.33230481
A91: 營業費用 | B91: NT$B | C91: =a25_opx -> 2.554134 | D91: =a26_opx -> 3.7835348 | E91: =D91*(1+MAX(0,phi*E81)) -> 5.2866447 | F91: =E91*(1+MAX(0,phi*F81)) -> 6.7240273 | G91: =F91*(1+MAX(0,phi*G81)) -> 7.6154592
A92: 營業利益 | B92: NT$B | C92: =C89-C91 -> 4.343659 | D92: =D89-D91 -> 16.407354 | E92: =E89-E91 -> 31.727274 | F92: =F89-F91 -> 45.556974 | G92: =G89-G91 -> 52.309585
A93: 營業利益率 | B93: % | C93: =C92/C80 -> 0.14316498 | D93: =D92/D80 -> 0.26831296 | E93: =E92/E80 -> 0.31215585 | F93: =F92/F80 -> 0.30844906 | G93: =G92/G80 -> 0.29007449
A94: 業外收益 | B94: NT$B | E94: =nop_f -> 0.15 | F94: =nop_f -> 0.15 | G94: =nop_f -> 0.15 | H94: FY2025、FY2026 含在淨利錨點內
A95: 稅後淨利（歸屬母公司） | B95: NT$B | C95: =a25_ni -> 3.409149 | D95: =a26_ni -> 11.380504 | E95: =(E92+E94)*nir_f -> 22.314092 | F95: =(F92+F94)*nir_f -> 31.994882 | G95: =(G92+G94)*nir_f -> 36.721709
A96: 淨利率 | B96: % | C96: =C95/C80 -> 0.11236396 | D96: =D95/D80 -> 0.18610781 | E96: =E95/E80 -> 0.21954216 | F96: =F95/F80 -> 0.21662525 | G96: =G95/G80 -> 0.2036344
A97: 股數 | B97: 十億股 | C97: =a25_sh -> 0.28105103 | D97: =a26_sh -> 0.29942787 | E97: =D97*(1+sh_g) -> 0.30242215 | F97: =E97*(1+sh_g) -> 0.30544637 | G97: =F97*(1+sh_g) -> 0.30850084
A98: EPS | B98: NT$ | C98: =C95/C97 -> 12.13 | D98: =D95/D97 -> 38.007498 | E98: =E95/E97 -> 73.784582 | F98: =F95/F97 -> 104.74795 | G98: =G95/G97 -> 119.03277
A99: EPS 年增 | B99: % | D99: =D98/C98-1 -> 2.1333469 | E99: =E98/D98-1 -> 0.94131649 | F99: =F98/E98-1 -> 0.41964553 | G99: =G98/F98-1 -> 0.13637324
A102: 情境 B：平平（Siliconomics 情境 B：CY2028 顆數 ×0.8、CY2029 ×0.85）
A103: 項目 | B103: 單位 | C103: FY2025A | D103: FY2026（錨點） | E103: FY2027 | F103: FY2028 | G103: FY2029 | H103: 說明
A104: A. AI 高速 CCL 市場（Siliconomics）與台燿份額（需求面；D 欄＝FY2026 校準年）
A105: 部署 GW（IT 電力） | B105: GW | D105: =gw_26 -> 23.399538 | E105: =gw_27 -> 41.646766 | F105: =gw28_B -> 42.233711 | G105: =gw29_B -> 51.117803 | H105: Siliconomics SIF_DeployGW_B
A106: 每 GW 高速 CCL 金額（不含價格指數） | B106: US$M/GW | D106: =pgw_26 -> 350 | E106: =pgw_27 -> 527.5 | F106: =pgw_28 -> 609 | G106: =pgw_29 -> 662.5 | H106: Siliconomics SIF_CCLperGW
A107: AI 高速 CCL 市場（美元；不含價格指數） | B107: US$B | D107: =D105*D106/1000 -> 8.1898383 | E107: =E105*E106/1000*mf -> 21.968669 | F107: =F105*F106/1000*mf -> 25.72033 | G107: =G105*G106/1000*mf -> 33.865544 | H107: ＝ Siliconomics SIF_CCLMkt_B（Recon 核對）；FY2027 起 × mf（Sens 用，基準 1）
A108: AI 高速 CCL 市場（新台幣） | B108: NT$B | D108: =D107*fx -> 262.07483 | E108: =E107*fx -> 702.99741 | F108: =F107*fx -> 823.05055 | G108: =G107*fx -> 1083.6974
A109: 台燿年均售價指數（FY2026＝1） | B109: x | D109: =1 -> 1 | E109: =pp_27 -> 1.05 | F109: =pp_28 -> 1 | G109: =pp_29 -> 0.95
A110: 台燿有效份額（FY2026 校準）＝ 高速材料營收 ÷ 市場 | B110: % | D110: =a26_ai/D108 -> 0.097998829 | H110: Derived：分子為公司 ELL／SLL 占比 × 營收；分母為 AI 高速 CCL 市場（含 ASIC）
A111: 份額相對值（÷ FY2026） | B111: x | D111: =1 -> 1 | E111: =rel_27 -> 1.1 | F111: =rel_28 -> 1.15 | G111: =rel_29 -> 1.15
A112: 台燿有效份額 | B112: % | D112: =$D$110*D111 -> 0.097998829 | E112: =$D$110*E111 -> 0.10779871 | F112: =$D$110*F111 -> 0.11269865 | G112: =$D$110*G111 -> 0.11269865
A113: 高速材料營收（需求面）＝ 市場 × 份額 × 價格指數 | B113: NT$B | D113: =D108*D112*D109 -> 25.683026 | E113: =E108*E112*E109 -> 79.571326 | F113: =F108*F112*F109 -> 92.756689 | G113: =G108*G112*G109 -> 116.02468
A114: B. 產能上限（全產全銷）與營收
A115: 平均月產能 | B115: 百萬張／月 | D115: =cap_26 -> 2.35 | E115: =cap_27 -> 3.1 | F115: =cap_28 -> 4.3 | G115: =cap_29 -> 5.3
A116: 每張營收（FY2026 校準）＝ 錨點營收 ÷（月產能 × 12） | B116: NT$／張 | D116: =a26_rev/(D115*12)*1000 -> 2168.4419 | H116: Derived：全產全銷，FY2026 營收全部由產能吸收；含膠片與所有等級
A117: 每張營收組合指數（FY2026＝1） | B117: x | D117: =1 -> 1 | E117: =mix_27 -> 1.2 | F117: =mix_28 -> 1.32 | G117: =mix_29 -> 1.42
A118: 產能上限營收 ＝ 月產能 × 12 × 每張營收 × 組合指數 × 價格指數 | B118: NT$B | D118: =D115*12*$D$116*D117*D109/1000 -> 61.150062 | E118: =E115*12*$D$116*E117*E109/1000 -> 101.63921 | F118: =F115*12*$D$116*F117*F109/1000 -> 147.69692 | G118: =G115*12*$D$116*G117*G109/1000 -> 186.04451
A119: 其他等級營收（VLL／LL、非低損耗、特殊應用） | B119: NT$B | C119: =a25_nai -> 20.63136 | D119: =a26_nai -> 35.467036 | E119: =D119*(1+g_nai27) -> 39.01374 | F119: =E119*(1+g_nai28) -> 41.744702 | G119: =F119*(1+g_nai29) -> 43.831937
A120: 高速材料營收（ELL／SLL，M7 以上；AI 相關）＝ MIN（需求面、產能上限 − 其他等級） | B120: NT$B | C120: =a25_ai -> 9.7088752 | D120: =D113 -> 25.683026 | E120: =MIN(E113,E118-E119) -> 62.62547 | F120: =MIN(F113,F118-F119) -> 92.756689 | G120: =MIN(G113,G118-G119) -> 116.02468 | H120: 產能不足時，其他等級照成長率出貨、高速材料取剩餘產能（Assumed）
A121: 產能是否受限 | E121: =IF(E113>E118-E119+0.0001,"受限","未受限") -> 受限 | F121: =IF(F113>F118-F119+0.0001,"受限","未受限") -> 未受限 | G121: =IF(G113>G118-G119+0.0001,"受限","未受限") -> 未受限
...

Sheet Val
A1: Val — 目標價（第 0 節：DCF 與 Comparable 加權）、現價隱含倍數與十年 P/E 分位檢查（新台幣）。本版未做先驗，無 Andy 合理 P/E 對照
A2: 三情境欄 B／C／D＝A 順利／B 平平／C 不如預期（讀 Siliconomics 同字母情境）。現價＝In 頁 px（2026-10-30 收盤）
A4: 0. 目標價（DCF 與 Comparable 加權）
A5: 0.1 DCF（股東權益現金流，FY2027–FY2032 明確期＋FY2032 後永續）
A6: 項目 | B6: A（順利） | C6: B（平平） | D6: C（不如預期） | E6: 說明
A7: 情境 EPS（FY2027–FY2032） | E7: PL 頁延伸表；FY2030 起為收斂法
A8: FY2027 | B8: =PL!E194 -> 73.784582 | C8: =PL!E206 -> 73.784582 | D8: =PL!E218 -> 73.784582
A9: FY2028 | B9: =PL!F194 -> 104.74795 | C9: =PL!F206 -> 94.303541 | D9: =PL!F218 -> 75.949044
A10: FY2029 | B10: =PL!G194 -> 119.03277 | C10: =PL!G206 -> 104.39865 | D10: =PL!G218 -> 80.056439
A11: FY2030 | B11: =PL!H194 -> 137.57178 | C11: =PL!H206 -> 113.80916 | D11: =PL!H218 -> 80.861665
A12: FY2031 | B12: =PL!I194 -> 151.69022 | C12: =PL!I206 -> 118.5345 | D12: =PL!I218 -> 78.543769
A13: FY2032 | B13: =PL!J194 -> 159.19964 | C13: =PL!J206 -> 117.69621 | D13: =PL!J218 -> 73.219781
A14: 股東現金流＝EPS ×（1 − tp_g ÷ tp_roe）
A15: 再投資率（tp_g ÷ tp_roe，上限 0.8） | B15: =MIN(tp_g/tp_roe,0.8) -> 0.25094103 | E15: ROE 為近三年平均（In 頁 tp_roe）
A16: FY2027 | B16: =B8*(1-$B$15) -> 55.269003 | C16: =C8*(1-$B$15) -> 55.269003 | D16: =D8*(1-$B$15) -> 55.269003
A17: FY2028 | B17: =B9*(1-$B$15) -> 78.462393 | C17: =C9*(1-$B$15) -> 70.638914 | D17: =D9*(1-$B$15) -> 56.890313
A18: FY2029 | B18: =B10*(1-$B$15) -> 89.162564 | C18: =C10*(1-$B$15) -> 78.200743 | D18: =D10*(1-$B$15) -> 59.966993
A19: FY2030 | B19: =B11*(1-$B$15) -> 103.04937 | C19: =C11*(1-$B$15) -> 85.249769 | D19: =D11*(1-$B$15) -> 60.570156
A20: FY2031 | B20: =B12*(1-$B$15) -> 113.62492 | C20: =C12*(1-$B$15) -> 88.789334 | D20: =D12*(1-$B$15) -> 58.833915
A21: FY2032 | B21: =B13*(1-$B$15) -> 119.24992 | C21: =C13*(1-$B$15) -> 88.161403 | D21: =D13*(1-$B$15) -> 54.845934
A22: DCF 情境每股價值（折現率 tp_r） | B22: =MAX(0,SUMPRODUCT(B16:B21,1/(1+tp_r)^{1;2;3;4;5;6})+B21*(1+tp_g)/(tp_r-tp_g)/(1+tp_r)^6) -> 1557.0952 | C22: =MAX(0,SUMPRODUCT(C16:C21,1/(1+tp_r)^{1;2;3;4;5;6})+C21*(1+tp_g)/(tp_r-tp_g)/(1+tp_r)^6) -> 1193.09 | D22: =MAX(0,SUMPRODUCT(D16:D21,1/(1+tp_r)^{1;2;3;4;5;6})+D21*(1+tp_g)/(tp_r-tp_g)/(1+tp_r)^6) -> 787.80039 | E22: Σ 明確期現金流 ÷ (1＋r)^t ＋ 永續價值 ÷ (1＋r)^6；永續價值＝FY2032 現金流 ×(1＋g)÷(r−g)；基準日 2026 年底，t＝1 對 FY2027；低於 0 時取 0
A23: DCF 情境價值推到 12 個月後（×(1＋tp_r)） | B23: =B22*(1+tp_r) -> 1712.8047 | C23: =C22*(1+tp_r) -> 1312.399 | D23: =D22*(1+tp_r) -> 866.58043
A24: DCF 目標價（情境加權） | B24: =tp_wA*B23+tp_wB*C23+tp_wC*D23 -> 1343.357 | E24: Σ tp_wA／wB／wC × 情境價值 ×(1＋tp_r)；權重見 In 頁
A26: 0.2 Comparable（市場主流同業前瞻 P/E）
A27: 同業與前瞻 P/E | B27: 代號 | C27: 前瞻 12 月 P/E | D27: 日期 | E27: 來源 | F27: 標記
A28: 台光電（Elite Material） | B28: 2383.TW | C28: 32.17 | D28: 2026-09-04 | E28: stockanalysis 個股頁 Forward PE（頁面快取 2026-09-04；較新資料未找到） | F28: Interested-party（賣方共識）
A29: 聯茂（ITEQ） | B29: 6213.TW | C29: 27.49 | D29: 2026-10-22 | E29: stockanalysis 個股頁 Forward PE（分析師共識；價格日期如左） | F29: Interested-party（賣方共識）
A30: 金像電（Gold Circuit） | B30: 2368.TW | C30: 19.57 | D30: 2026-10-22 | E30: stockanalysis 個股頁 Forward PE（分析師共識；價格日期如左） | F30: Interested-party（賣方共識）
A31: 同業前瞻 P/E 中位數 | B31: =MEDIAN(C28:C30) -> 27.49 | E31: 高速 CCL 與 AI 伺服器 PCB 同業：台光電、聯茂（CCL）、金像電（下游 PCB）。生益科技（600183.SS）為 A 股，依規則不列；斗山電子材料、松下非單獨上市，未列
A32: 12 個月後的前瞻 EPS（情境加權） | B32: =tp_wA*(0.166666666666667*B8+0.833333333333333*B9)+tp_wB*(0.166666666666667*C8+0.833333333333333*C9)+tp_wC*(0.166666666666667*D8+0.833333333333333*D9) -> 90.435735 | E32: 約 2027-10 時的未來 12 月 EPS ≈ 2／12 × FY2027＋10／12 × FY2028（會計年度＝日曆年）
A33: Comparable 目標價 | B33: =B31*B32 -> 2486.0783 | E33: 同業中位數 × 上列 EPS
A35: 0.3 結論
A36: 項目 | B36: 數值 | E36: 說明
A37: 目標價（DCF 與 Comparable 加權） | B37: =tp_w_dcf*B24+(1-tp_w_dcf)*tp_comp_adj -> 1827.7441 | E37: tp_w_dcf × DCF 目標價＋（1 − tp_w_dcf）× Comparable 目標價（相對倍數調整後，見第 0.5 節）
A38: Comparable 目標價（市場主流同業法） | B38: =B33 -> 2486.0783 | E38: 引用 0.2（未作相對倍數調整）
A39: 市場共識目標價 | B39: =cons_tp -> 2213 | E39: stockanalysis 個股頁 Analyst price target 2,213（2026-10-22）
A40: 上檔空間：加權目標價 | B40: =B37/px-1 -> 0.44485698 | E40: 現價＝In 頁 px（2026-10-30 收盤 1,265）
A41: 上檔空間：Comparable 目標價 | B41: =B38/px-1 -> 0.96527932
A42: 上檔空間級距 | B42: =IF(B40>0.5,"大於 50%",IF(B40>0.25,"25%–50%",IF(B40>=0,"0%–25%",IF(B40>=-0.25,"0%～−25%",IF(B40>=-0.5,"−25%～−50%","小於 −50%"))))) -> 25%–50% | E42: 以「上檔空間：加權目標價」分六級（Andy 2026-10-25 14:00）
A43: 投資建議 | B43: =IF(B40>0.5,"強力買進",IF(B40>0.25,"買進",IF(B40>=-0.25,"中立",IF(B40>=-0.5,"放空","強力放空")))) -> 買進 | E43: 依上檔空間固定規則（Andy 2026-10-25 14:17）：大於 +50% 強力買進、+25%～+50% 買進、−25%～+25% 中立、−50%～−25% 放空、小於 −50% 強力放空
A44: 與市場共識目標價的差距：EPS 因素 | B44: =B32/cons_feps-1 -> 0.6794298 | E44: 本模型前瞻 EPS ÷ 共識前瞻 EPS − 1；共識前瞻 EPS 見 In 頁 cons_feps 與 Recon
A45: 與市場共識目標價的差距：倍數因素 | B45: =(cons_tp/cons_feps)/B31-1 -> 0.49495617 | E45: ="共識目標價 ÷ 共識前瞻 EPS 隱含 "&TEXT(cons_tp/cons_feps,"0.0")&"x，同業中位數 "&TEXT(B31,"0.0")&"x" -> 共識目標價 ÷ 共識前瞻 EPS 隱含 41.1x，同業中位數 27.5x
A46: 價格帶（DCF 不如預期～順利） | B46: =TEXT(D23,"#,##0")&"～"&TEXT(B23,"#,##0") -> 867～1,713 | E46: C 情境價值～A 情境價值（推到 12 個月後）
A47: 歷史倍數檢查：現價隱含 P/E 的十年分位（A／B／C） | B47: =IF(px/B9<=MIN($B$51:$K$51),0,IF(px/B9>=MAX($B$51:$K$51),1,PERCENTRANK($B$51:$K$51,px/B9))) -> 0.145 | C47: =IF(px/C9<=MIN($B$51:$K$51),0,IF(px/C9>=MAX($B$51:$K$51),1,PERCENTRANK($B$51:$K$51,px/C9))) -> 0.221 | D47: =IF(px/D9<=MIN($B$51:$K$51),0,IF(px/D9>=MAX($B$51:$K$51),1,PERCENTRANK($B$51:$K$51,px/D9))) -> 0.379 | E47: 現價 ÷ 各情境 FY2028 EPS 在 2016–2025 年底 P/E 分布（下方列；2016–2017 年 EPS 未找到，共 8 年）的分位；低於最小值記 0%、高於最大值記 100%；只作檢查，不進目標價
A48: 目標價方法 | B48: DCF：股東現金流＝EPS ×（1 − g／ROE），r＝10%、g＝4%、ROE＝近三年平均約 16%（含 2023 年谷底 7%，再投資率約 25%），FY2027–29 驅動因子、FY2030–32 收斂法＋永續；ROE 取三年平均使 DCF 偏低估（近 12 月 ROE 31%）。Comparable：台光電、聯茂、金像電前瞻 P/E 中位數（只有三家；金像電為下游 PCB，倍數較低），再乘相對倍數係數（第 0.5 節）。情境對應：A＝順利、B＝平平、C＝不如預期（Siliconomics 同字母顆數情境）。
A50: 十年年底 P/E（歷史分位檢查用；Yahoo Finance 12 月收盤 ÷ 當年 EPS〔HiStock〕；2016–2017 年 EPS 未找到） | B50: 2016 | C50: 2017 | D50: 2018 | E50: 2019 | F50: 2020 | G50: 2021 | H50: 2022 | I50: 2023 | J50: 2024 | K50: 2025
A51: 年底 P/E | D51: =89.8/7.46 -> 12.037534 | E51: =148/6.92 -> 21.387283 | F51: =121/6.67 -> 18.14093 | G51: =102/7.01 -> 14.550642 | H51: =51.4/4.69 -> 10.959488 | I51: =126/3.05 -> 41.311475 | J51: =170/9.56 -> 17.782427 | K51: =494/12.13 -> 40.725474
A52: 核對：stockanalysis 年度 P/E 2021–2025＝14.58、10.97、41.46、17.79、40.96（與上列同量級，只作核對）
A55: 1. 價格與市場隱含倍數
A56: 項目 | B56: A | C56: B | D56: C | E56: 說明
A57: 現價（2026-10-30 收盤） | B57: =px -> 1265
A58: 現價 ÷ FY2026 EPS（錨點） | B58: =px/PL!D13 -> 33.282907 | C58: =px/PL!D25 -> 33.282907 | D58: =px/PL!D37 -> 33.282907
A59: 現價 ÷ FY2027 EPS（模型） | B59: =px/PL!E13 -> 17.144503 | C59: =px/PL!E25 -> 17.144503 | D59: =px/PL!E37 -> 17.144503
A60: 現價 ÷ FY2028 EPS（模型） | B60: =px/PL!F13 -> 12.076608 | C60: =px/PL!F25 -> 13.41413 | D60: =px/PL!F37 -> 16.655904
A61: 現價 ÷ FY2029 EPS（模型） | B61: =px/PL!G13 -> 10.627326 | C61: =px/PL!G25 -> 12.117015 | D61: =px/PL!G37 -> 15.801352
A62: 近 12 月 EPS（4Q25＋1Q26～3Q26 揭露 EPS） | B62: =3.76+4.36+8.02+12.88 -> 29.02
A63: 現價 ÷ 近 12 月 EPS | B63: =px/B62 -> 43.590627
A66: 0.5 相對倍數調整（Comparable 目標倍數＝同業中位數 × 本公司 10 年相對同業的 P/E 比；Andy 2026-10-27 新增，放在本頁最後以免位移既有儲存格）
A67: 資料：2017–2026 各年度窗口（前一年 11 月～當年 10 月）Bloomberg 月底前瞻 P/E（BF）的中位數（tools/data/fwd_mult_hist.csv），[Verified] 來源、[Derived] 彙總；有效值 0 < 值 ≤ 200，無效值以「剔除:」文字列示、不進中位數。本公司或同業有效年數 < 7 不納入；有效同業 < 2 家或本公司不足時係數＝1（不調整）。
A68: 公司 | B68: 代號 | C68: 角色 | D68: 2016/11–2017/10 | E68: 2017/11–2018/10 | F68: 2018/11–2019/10 | G68: 2019/11–2020/10 | H68: 2020/11–2021/10 | I68: 2021/11–2022/10 | J68: 2022/11–2023/10 | K68: 2023/11–2024/10 | L68: 2024/11–2025/10 | M68: 2025/11–2026/10 | N68: 有效年數 | O68: 10 年中位數 | P68: 納入值 | Q68: 來源
A69: 台燿 | B69: 6274.TWO | C69: 本公司 | D69: 9.2055 | E69: 12.0875 | F69: 12.277 | G69: 12.6065 | H69: 11.2705 | I69: 8.3745 | J69: 10.8355 | K69: 15.1745 | L69: 13.1345 | M69: 22.3335 | N69: =COUNT(D69:M69) -> 10 | O69: =IF(N69>0,MEDIAN(D69:M69),"") -> 12.18225 | P69: =IF(N69>=7,O69,"") -> 12.18225 | Q69: Bloomberg 6274 TT Equity BEST_PE_RATIO（BF＝未來 12 個月，月底）
A70: 台光電（Elite Material） | B70: 2383.TW | C70: 同業 | D70: 10.67 | E70: 10.2075 | F70: 11.868 | G70: 11.6805 | H70: 12.4515 | I70: 11.1805 | J70: 13.276 | K70: 15.336 | L70: 18.3845 | M70: 28.217 | N70: =COUNT(D70:M70) -> 10 | O70: =IF(N70>0,MEDIAN(D70:M70),"") -> 12.15975 | P70: =IF(N70>=7,O70,"") -> 12.15975 | Q70: Bloomberg 2383 TT Equity BEST_PE_RATIO（BF＝未來 12 個月，月底）
A71: 聯茂（ITEQ） | B71: 6213.TW | C71: 同業 | D71: 10.5155 | E71: 10.966 | F71: 13.4605 | G71: 12.516 | H71: 12.9565 | I71: 11.1175 | J71: 13.241 | K71: 17.8015 | L71: 16.4055 | M71: 21.7305 | N71: =COUNT(D71:M71) -> 10 | O71: =IF(N71>0,MEDIAN(D71:M71),"") -> 13.09875 | P71: =IF(N71>=7,O71,"") -> 13.09875 | Q71: Bloomberg 6213 TT Equity BEST_PE_RATIO（BF＝未來 12 個月，月底）
A72: 金像電（Gold Circuit） | B72: 2368.TW | C72: 同業 | D72: 124.787 | E72: 19.303 | F72: 19.303 | G72: 19.303 | H72: 10.0765 | I72: 10.779 | J72: 11.369 | K72: 15.5915 | L72: 15.535 | M72: 21.815 | N72: =COUNT(D72:M72) -> 10 | O72: =IF(N72>0,MEDIAN(D72:M72),"") -> 17.44725 | P72: =IF(N72>=7,O72,"") -> 17.44725 | Q72: Bloomberg 2368 TT Equity BEST_PE_RATIO（BF＝未來 12 個月，月底）
A74: 本公司 10 年中位數（納入值） | B74: =P69 -> 12.18225 | E74: 空白＝本公司有效年數不足
A75: 納入的同業家數 | B75: =COUNT(P70:P72) -> 3
A76: 同業 10 年中位數的中位數 | B76: =IF(B75>0,MEDIAN(P70:P72),"") -> 13.09875
A77: 原始比值（本公司 ÷ 同業） | B77: =IF(AND(ISNUMBER(B74),B75>=2),B74/B76,"") -> 0.93003149 | E77: ＜1＝本公司長期比同業便宜（折價），＞1＝長期溢價
A78: 夾值下限 | B78: 0.5 | E78: [Assumed] 避免單一歷史異常主導；tools/relative_multiple.py 的 RM_LO
A79: 夾值上限 | B79: 2 | E79: [Assumed] tools/relative_multiple.py 的 RM_HI
A80: 相對倍數調整係數 | B80: =IF(ISNUMBER(B77),MIN(MAX(B77,B78),B79),1) -> 0.93003149 | E80: 資料不足時＝1（不調整）
A81: Comparable 目標價（相對倍數調整後） | B81: =Val!$B$33*B80 -> 2312.1312 | E81: ＝Comparable 目標價（市場主流同業法）× 調整係數；加權目標價使用本列

Sheet Recon
A1: Recon — 本模型 vs 共識、券商估計與 Siliconomics 市場。只作事後對照，不為對上數字而調參數。FY2028 共識（最新）：未找到
A3: 項目 | B3: 對照值 | C3: 模型 A | D3: 差距 A | E3: 模型 B | F3: 差距 B | G3: 模型 C | H3: 差距 C | I3: 對照來源 | J3: 說明
A4: A. 共識與券商（校準未使用）
A5: FY2026 營收 vs FactSet 共識（08-04） | B5: =c_rev26f -> 58.89 | C5: =PL!D80 -> 61.150062 | D5: =C5/B5-1 -> 0.038377693 | E5: =PL!D122 -> 61.150062 | F5: =E5/B5-1 -> 0.038377693 | G5: =PL!D164 -> 61.150062 | H5: =G5/B5-1 -> 0.038377693 | I5: FactSet（理財周刊 2026-09-10 轉引） | J5: 3Q26 實際營收 179.5 億，共識在 3Q 前
A6: FY2026 EPS vs FactSet 共識（08-04） | B6: =c_eps26f -> 36.05 | C6: =PL!D98 -> 38.007498 | D6: =C6/B6-1 -> 0.054299522 | E6: =PL!D140 -> 38.007498 | F6: =E6/B6-1 -> 0.054299522 | G6: =PL!D182 -> 38.007498 | H6: =G6/B6-1 -> 0.054299522 | I6: 同上
A7: FY2026 EPS vs 美系券商（07-20） | B7: =b_eps26u -> 38.8 | C7: =PL!D98 -> 38.007498 | D7: =C7/B7-1 -> -0.020425315 | E7: =PL!D140 -> 38.007498 | F7: =E7/B7-1 -> -0.020425315 | G7: =PL!D182 -> 38.007498 | H7: =G7/B7-1 -> -0.020425315 | I7: 經濟日報 2026-07-20
A8: FY2027 營收 vs FactSet 共識（08-04） | B8: =c_rev27f -> 100.7 | C8: =PL!E80 -> 101.63921 | D8: =C8/B8-1 -> 0.0093268125 | E8: =PL!E122 -> 101.63921 | F8: =E8/B8-1 -> 0.0093268125 | G8: =PL!E164 -> 101.63921 | H8: =G8/B8-1 -> 0.0093268125 | I8: FactSet
A9: FY2027 EPS vs FactSet 共識（08-04） | B9: =c_eps27f -> 70.47 | C9: =PL!E98 -> 73.784582 | D9: =C9/B9-1 -> 0.047035367 | E9: =PL!E140 -> 73.784582 | F9: =E9/B9-1 -> 0.047035367 | G9: =PL!E182 -> 73.784582 | H9: =G9/B9-1 -> 0.047035367 | I9: FactSet | J9: 低 53.91、高 100.07
A10: FY2027 EPS vs 美系券商（07-20） | B10: =b_eps27u -> 93.5 | C10: =PL!E98 -> 73.784582 | D10: =C10/B10-1 -> -0.21086008 | E10: =PL!E140 -> 73.784582 | F10: =E10/B10-1 -> -0.21086008 | G10: =PL!E182 -> 73.784582 | H10: =G10/B10-1 -> -0.21086008 | I10: 經濟日報 2026-07-20
A11: FY2028 EPS vs 美系券商（07-20） | B11: =b_eps28u -> 168.7 | C11: =PL!F98 -> 104.74795 | D11: =C11/B11-1 -> -0.37908742 | E11: =PL!F140 -> 94.303541 | F11: =E11/B11-1 -> -0.44099857 | G11: =PL!F182 -> 75.949044 | H11: =G11/B11-1 -> -0.5497982 | I11: 經濟日報 2026-07-20 | J11: 單一券商、偏樂觀端
A12: FY2028 EPS vs FactSet（04-20，單一預估） | B12: =c_eps28f -> 81.76 | C12: =PL!F98 -> 104.74795 | D12: =C12/B12-1 -> 0.2811638 | E12: =PL!F140 -> 94.303541 | F12: =E12/B12-1 -> 0.15341905 | G12: =PL!F182 -> 75.949044 | H12: =G12/B12-1 -> -0.071073338 | I12: 鉅亨 2026-04-20 | J12: 期間早，只作量級參考
A13: B. 市場與份額（機制檢查）
A14: CY2026 AI 高速 CCL 市場 vs Siliconomics SIF_CCLMkt（US$B） | C14: 8.1898383 | D14: =PL!D65-C14 -> 0 | E14: 8.1898383 | F14: =PL!D107-E14 -> 0 | G14: 8.1898383 | H14: =PL!D149-G14 -> 0 | I14: Siliconomics 快照 v0.10（siliconomics_snapshot_v0.10.json） | J14: 下一欄為本模型（÷ mf）
A15: CY2027 AI 高速 CCL 市場 vs Siliconomics SIF_CCLMkt（US$B） | C15: 21.968669 | D15: =PL!E65/mf-C15 -> 0 | E15: 21.968669 | F15: =PL!E107/mf-E15 -> 0 | G15: 21.968669 | H15: =PL!E149/mf-G15 -> 0 | I15: Siliconomics 快照 v0.10（siliconomics_snapshot_v0.10.json） | J15: 下一欄為本模型（÷ mf）
A16: CY2028 AI 高速 CCL 市場 vs Siliconomics SIF_CCLMkt（US$B） | C16: 32.150412 | D16: =PL!F65/mf-C16 -> 0 | E16: 25.72033 | F16: =PL!F107/mf-E16 -> 0 | G16: 19.290247 | H16: =PL!F149/mf-G16 -> 0 | I16: Siliconomics 快照 v0.10（siliconomics_snapshot_v0.10.json） | J16: 下一欄為本模型（÷ mf）
A17: CY2029 AI 高速 CCL 市場 vs Siliconomics SIF_CCLMkt（US$B） | C17: 39.841817 | D17: =PL!G65/mf-C17 -> 0 | E17: 33.865544 | F17: =PL!G107/mf-E17 -> 0 | G17: 23.90509 | H17: =PL!G149/mf-G17 -> 0 | I17: Siliconomics 快照 v0.10（siliconomics_snapshot_v0.10.json） | J17: 下一欄為本模型（÷ mf）
A18: FY2026 台燿有效份額（需求面） | C18: =PL!D68 -> 0.097998829 | E18: =PL!D110 -> 0.097998829 | G18: =PL!D152 -> 0.097998829 | I18: — | J18: 台光電同期 45.9%（台光電成品 Units）
A19: FY2027 需求面 ÷ 產能上限 | C19: =PL!E84 -> 1.1667256 | E19: =PL!E126 -> 1.1667256 | G19: =PL!E168 -> 1.1667256 | I19: — | J19: 大於 100%＝產能受限
A20: FY2028 需求面 ÷ 產能上限 | C20: =PL!F84 -> 1.0676632 | E20: =PL!F126 -> 0.91065808 | G20: =PL!F168 -> 0.75365296 | I20: —
A21: 每張營收 FY2026（NT$；校準） | C21: =PL!D74 -> 2168.4419 | E21: =PL!D116 -> 2168.4419 | G21: =PL!D158 -> 2168.4419 | I21: — | J21: FY2025：303.4 億 ÷（約 210 萬張 × 12）≈ NT$1,200；台光電 FY2026 約 NT$2,858
A22: 其他等級毛利率（Derived） | C22: =PL!D87 -> 0.29658591 | E22: =PL!D129 -> 0.29658591 | G22: =PL!D171 -> 0.29658591 | I22: FY2026 錨點 | J22: 高速材料毛利率＝此值＋d_ai
A23: 4Q26 EPS（模型） | C23: =Q!E15 -> 13.09789 | E23: =Q!E15 -> 13.09789 | G23: =Q!E15 -> 13.09789 | I23: — | J23: 3Q26 實績 12.88

Sheet Sens
A1: Sens — 一次改一個輸入（In 頁敏感度低／高值），整本活頁簿以 LibreOffice 重算後的加權目標價（Val 第 0 節）與情境 A 的 FY2028 EPS；由 tuc/sens_tuc.py 產生 tuc/sens.json，建置時寫入（數值）
A2: 相對基準＝案例目標價 ÷ 基準加權目標價 − 1；龍捲風依絕對值排序（HTML）。ai_25（2025 年高速材料占比）只影響 FY2025 欄的子列拆分，對目標價結構上恆為 0，仍列案例以示涵蓋。tp_g 案例同時移動 DCF 永續成長與 PL 收斂目標 fade_g（fade_g 以 tp_g 為公式）。
A3: 驅動 | B3: 設定 | C3: 方向 | D3: 加權目標價 | E3: 相對基準 | F3: 鍵 | G3: FY2028 EPS（情境 A） | H3: FY2028 EPS 相對基準 | I3: 說明
A4: 基準 | B4: In 頁基準欄 | C4: — | D4: =tp_final -> 1827.7441 | E4: 0 | G4: =PL!F13 -> 104.74795 | H4: 0 | I4: 本活頁簿重算值
A5: 匯率（新台幣 ÷ 美元）：低 | B5: 32 → 30.5 | C5: 低 | D5: 1827.7441 | E5: =D5/D$4-1 -> 0 | F5: fx | G5: 104.74795 | H5: =G5/G$4-1 -> 0 | I5: 重算值（sens_tuc.py）
A6: 匯率（新台幣 ÷ 美元）：高 | B6: 32 → 33 | C6: 高 | D6: 1827.7441 | E6: =D6/D$4-1 -> 0 | F6: fx | G6: 104.74795 | H6: =G6/G$4-1 -> 0 | I6: 重算值（sens_tuc.py）
A7: 台燿 AI 高速 CCL 有效份額 2027 ÷ 2026（相對值）：低 | B7: 1.1 → 0.95 | C7: 低 | D7: 1827.7441 | E7: =D7/D$4-1 -> 0 | F7: rel_27 | G7: 104.74795 | H7: =G7/G$4-1 -> 0 | I7: 重算值（sens_tuc.py）
A8: 台燿 AI 高速 CCL 有效份額 2027 ÷ 2026（相對值）：高 | B8: 1.1 → 1.25 | C8: 高 | D8: 1827.7441 | E8: =D8/D$4-1 -> 0 | F8: rel_27 | G8: 104.74795 | H8: =G8/G$4-1 -> 0 | I8: 重算值（sens_tuc.py）
A9: 台燿 AI 高速 CCL 有效份額 2028 ÷ 2026（相對值）：低 | B9: 1.15 → 0.95 | C9: 低 | D9: 1777.4261 | E9: =D9/D$4-1 -> -0.027530102 | F9: rel_28 | G9: 96.697606 | H9: =G9/G$4-1 -> -0.076854448 | I9: 重算值（sens_tuc.py）
A10: 台燿 AI 高速 CCL 有效份額 2028 ÷ 2026（相對值）：高 | B10: 1.15 → 1.35 | C10: 高 | D10: 1873.4119 | E10: =D10/D$4-1 -> 0.024985918 | F10: rel_28 | G10: 104.74795 | H10: =G10/G$4-1 -> 0 | I10: 重算值（sens_tuc.py）
A11: 台燿 AI 高速 CCL 有效份額 2029 ÷ 2026（相對值）：低 | B11: 1.15 → 0.9 | C11: 低 | D11: 1645.3395 | E11: =D11/D$4-1 -> -0.099797681 | F11: rel_29 | G11: 104.74795 | H11: =G11/G$4-1 -> 0 | I11: 重算值（sens_tuc.py）
A12: 台燿 AI 高速 CCL 有效份額 2029 ÷ 2026（相對值）：高 | B12: 1.15 → 1.4 | C12: 高 | D12: 1975.861 | E12: =D12/D$4-1 -> 0.081038112 | F12: rel_29 | G12: 104.74795 | H12: =G12/G$4-1 -> 0 | I12: 重算值（sens_tuc.py）
A13: 台燿 CCL 年均售價指數 2027（FY2026 年均＝1；含 2026 年中漲價的全年效果）：低 | B13: 1.05 → 0.97 | C13: 低 | D13: 1796.2217 | E13: =D13/D$4-1 -> -0.017246579 | F13: pp_27 | G13: 104.76208 | H13: =G13/G$4-1 -> 0.00013491416 | I13: 重算值（sens_tuc.py）
A14: 台燿 CCL 年均售價指數 2027（FY2026 年均＝1；含 2026 年中漲價的全年效果）：高 | B14: 1.05 → 1.12 | C14: 高 | D14: 1856.1615 | E14: =D14/D$4-1 -> 0.015547816 | F14: pp_27 | G14: 104.70636 | H14: =G14/G$4-1 -> -0.00039707044 | I14: 重算值（sens_tuc.py）
A15: 台燿 CCL 年均售價指數 2028（FY2026 年均＝1；含 2026 年中漲價的全年效果）：低 | B15: 1.0 → 0.9 | C15: 低 | D15: 1648.3458 | E15: =D15/D$4-1 -> -0.098152871 | F15: pp_28 | G15: 78.582897 | H15: =G15/G$4-1 -> -0.24979061 | I15: 重算值（sens_tuc.py）
A16: 台燿 CCL 年均售價指數 2028（FY2026 年均＝1；含 2026 年中漲價的全年效果）：高 | B16: 1.0 → 1.08 | C16: 高 | D16: 1981.3915 | E16: =D16/D$4-1 -> 0.084063941 | F16: pp_28 | G16: 126.56356 | H16: =G16/G$4-1 -> 0.20826762 | I16: 重算值（sens_tuc.py）
... A70: 目標價中 DCF 的權重；其餘為 Comparable：高 | B70: 0.5 → 0.7 | C70: 高 | D70: 1633.9893 | E70: =D70/D$4-1 -> -0.10600764 | F70: tp_w_dcf | G70: 104.74795 | H70: =G70/G$4-1 -> 0 | I70: 重算值（sens_tuc.py）
A72: 讀法：產能受限的年度（情境 A 的 FY2027–28），需求面輸入（份額相對值、市場係數）往上調時營收被產能上限截斷，只有產能、組合與價格指數會改變營收；價格指數同時改變產能上限營收與高速材料毛利率（成本不變），所以對 EPS 的影響大於對營收。

Sheet Sources
A1: 來源（公司原文＝台燿財報、月營收與法說，經 HiStock、nstock、富果轉述；券商皆為 Interested-party）
A2: 財報：HiStock 損益表（季；公開資訊觀測站轉載；1Q25–3Q26 營收、毛利、營業利益、稅前、稅後） | B2: https://histock.tw/stock/6274/損益表
A3: 財報：HiStock 每股盈餘（2018–2026 各季） | B3: https://histock.tw/stock/6274/每股盈餘
A4: 財報：nstock（3Q26 EPS 12.88、毛利率 36.93%、營益率 31.02%；10-30 收盤） | B4: https://www.nstock.tw/6274?status=6
A5: 月營收：HiStock（2025-01～2026-09） | B5: https://histock.tw/stock/6274/每月營收
A6: 二手：優分析 2026-07-30（2Q26 營收 143.01 億、毛利率 29.72%、EPS 8.02；1H26 EPS 12.4；可轉債 100 億元） | B6: https://uanalyze.com.tw/articles/1773952452
A7: 公司：2Q26 法說（富果 2026-07-30；損耗等級組合、泰國廠、2028–29 擴產 195 萬張） | B7: https://blog.fugle.tw/post/earnings-call-6274-2026-07-30
A8: 公司：4Q25 法說（富果 2026-03-12；ELL／SLL 36%、常熟與泰國各 +60 萬張） | B8: https://blog.fugle.tw/post/earnings-call-6274-2026-03-12
A9: 媒體：理財周刊 2026-09-10（集團月產能逾 220 萬張、市場估 2026／2027 年底 260／380 萬張；FactSet 08-04 共識） | B9: https://www.moneyweekly.com.tw/_Article?AID=247880
A10: 券商：經濟日報 2026-07-20（美系券商 2026–28 EPS 38.8／93.5／168.7） | B10: https://money.udn.com/money/story/5607/9638268
A11: 券商：旺得富 2026-06-30（日系外資目標價 2,115；AI ASIC 專案 2026 年貢獻 5–6%） | B11: https://wantrich.chinatimes.com/news/20260630900220-420101
A12: 共識：鉅亨 2026-04-20（FactSet 2026–28 EPS、目標價 900） | B12: https://news.cnyes.com/news/id/6426189
A13: 資料商：stockanalysis（共識目標價 2,213、Forward PE 26.37、ROE、年度 P/E；同業 Forward PE） | B13: https://stockanalysis.com/quote/tpex/6274/
... A16: 待補（人工）：10 月營收（約 11-10）；3Q26 法說（日期未找到）；財報附註的營運部門原文；2016–2017 年 EPS；FY2028 最新共識；Bloomberg 前瞻倍數歷史（已有 6274.TWO） | B16: 未找到
