Workbook

Sheet README
A1: Alphabet（GOOGL）個股模型 v0.3.1（2026-10-29；2026Q3 季度滾動）— 命題模組＋官方營收分部 → 損益表
A3: 命題：AI 改變搜尋之後，Google Search 的變現能否守住，同時 Google Cloud（含 TPU）能否把翻倍的資本支出變成營收；資本支出與 2026 年股權發行後的每股價值是否高於現價。
A4: 核心問題：Search & other 在 C 情境（AI 助理分流、每次查詢變現下降）下 FY2028 營收與利益率會掉多少，Cloud 的 AI 營收能否抵銷；加計 AI 折舊與股權發行後的每股價值。
A5: ="投資建議："&Val!B14&"（加權目標價 US$"&TEXT(Val!B8,"0.00")&"，上檔空間 "&TEXT(Val!B11,"+0.0%;-0.0%")&"；現價 "&TEXT(px,"0.00")&"，2026-10-28 收盤）" -> 投資建議：中立（加權目標價 US$258.21，上檔空間 -20.5%；現價 324.89，2026-10-28 收盤）
A6: ="重點觀察 1：目標價 "&TEXT(Val!B8,"0")&"＝DCF "&TEXT(Val!B6,"0")&"、分部加總 "&TEXT(Val!B7,"0")&" 各半；情境 A／B／C 為 "&TEXT(Val!B17,"0")&"／"&TEXT(Val!C17,"0")&"／"&TEXT(Val!D17,"0")&"，DCF 終值占 EV "&TEXT(Val!C19,"0%")&"（B）。市場共識目標價 "&TEXT(cons_tp,"0")&"。" -> 重點觀察 1：目標價 258＝DCF 189、分部加總 327 各半；情境 A／B／C 為 282／262／226，DCF 終值占 EV 79%（B）。市場共識目標價 429。
A7: ="重點觀察 2：C 情境 FY2028 Search & other "&TEXT(PL!I131,"0.0")&"（比 B 少 "&TEXT(1-PL!I131/PL!I72,"0.0%")&"），Google Services 營業利益率 "&TEXT(PL!I169,"0.0%")&"（B "&TEXT(PL!I110,"0.0%")&"）；同年 Cloud AI 營收 "&TEXT(PL!I77,"0.0")&"、Google Cloud 營業利益 "&TEXT(PL!I94,"0.0")&"，Cloud 營業利益比 FY2025 增加 "&TEXT(PL!I94-PL!D94,"0.0")&"，是 C 情境 Services 營業利益損失 "&TEXT(PL!I91-PL!I150,"0.0")&" 的 "&TEXT((PL!I94-PL!D94)/(PL!I91-PL!I150),"0%")&"（Cloud 的成長足以抵銷搜尋被侵蝕的利潤）。" -> 重點觀察 2：C 情境 FY2028 Search & other 284.2（比 B 少 14.5%），Google Services 營業利益率 30.4%（B 34.3%）；同年 Cloud AI 營收 57.3、Google Cloud 營業利益 85.8，Cloud 營業利益比 FY2025 增加 71.9，是 C 情境 Services 營業利益損失 33.5 的 214%（Cloud 的成長足以抵銷搜尋被侵蝕的利潤）。
A8: ="重點觀察 3：AI 折舊進損益——情境 B 新增 AI 折舊 FY2028 "&TEXT(PL!I104,"0.0")&"，合併營業利益率由 FY2025 "&TEXT(PL!D109,"0.0%")&" 變為 FY2028 "&TEXT(PL!I109,"0.0%")&"；收支關卡（FY2026–2030 自由現金流扣股利合計）B "&TEXT(CF!C6,"0.0")&"，"&CF!C9&"。" -> 重點觀察 3：AI 折舊進損益——情境 B 新增 AI 折舊 FY2028 65.1，合併營業利益率由 FY2025 32.0% 變為 FY2028 22.4%；收支關卡（FY2026–2030 自由現金流扣股利合計）B -0.6，需要舉債且減少回購。
A10: 驅動 → 推導對照表（每頁輸入、推導量、因果方向）
A11: 頁 | B11: 輸入（In 頁鍵） | C11: 推導量 | D11: 因果方向
A12: Thesis | B12: pace、ext_sh、mw_tot0、k（kl_px、ks_px、long_sh）、Tokenomics IF_HoldEcon／OpexGW／CapexIT | C12: Cloud AI 營收與 EBITDA、AI 資本支出、新增 AI 折舊、自用 AI 增量成本 | D12: MW → 收入（× 每 MW 持有成本 × k）；MW → 資本支出 → 折舊 → 分部營業利益
A13: Seg | B13: g0（Q 頁近四季）、gl_*、conv_n、dA／mA／dC／mC、tpu_*、ob_rev_* | C13: 四條產品線、三個分部、合併營收；非 AI 資本支出與折舊 | D13: 近四季年增 → 長期值；Search＝B 路徑 ×(1 − 分流)×(1＋變現變動)
A14: PL | B14: m_svc、inc_m、m_co、tpu_m、abc_rate、svc_sh、da_base、tax | C14: 分部 EBITDA、分部營業利益、合併營業利益、淨利、EPS | D14: 分部營收 → 分部 EBITDA − 折舊 → 營業利益 → 業外、稅 → EPS
A15: CF | B15: sbc_r、wc_*、dps、bb_t、min_cash、mat_*、anth_* | C15: 自由現金流、股利、回購、新債、淨現金、收支關卡 | D15: 淨利＋折舊 − 資本支出 → 自由現金流 → 股利 → 回購／舉債
A16: Val | B16: rf、beta、erp、kd、g_tv、ronic、同業倍數、持股、tp_w*、w_dcf | C16: DCF、分部加總、目標價、上檔空間、投資建議 | D16: 無槓桿 FCF 折現＋分部 EBITDA × 倍數 → 情境加權 → 50／50
A17: Sens | B17: In 頁低／高值 | C17: 加權目標價變動 | D17: 一次改一個輸入、整本重算
A19: 與 v0.3 的差異（v0.3.1：2026Q3 季度滾動）
A20: Q 頁加入 2026Q3（保留 2024Q4–2026Q3 八季）；FY2026＝9M 實績＋Q4 模型；評價日 2026-06-30 → 2026-09-30，目標日 2027-10-29（約 12 個月後）。
A21: Tokenomics v21.4 → v21.7（快照重取；契約名稱只有 IF_NonNV_Hold_TPU 改變）；TPU 係數由「同期 NVIDIA 世代 × 1.0」改讀 IF_NonNV_Hold_TPU（0.70），舊口徑列 Sens。
A22: C10：2026 資本支出指引維持 195–205 → AI MW 速度以 9M 實績 131.95＋Q4 公式＝200 重解。
A23: WACC 權益權重與回購價改用評價日股價（2026-09-30 收盤 344.08），現價只影響上檔空間與評等。
A24: 架構與 v0.3 相同（命題＋官方分部 → 損益表；讀法 2 主值）；v0.2.2 → v0.3 的差異見 dist/_待刪除/ 的 v0.3 成品與 docs/reports/20261027_alphabet_v0.3_分部架構.md。
A26: 工作表：README → In → Q → Thesis → Seg → PL → CF → Val → Recon → Sens → Sources。藍字＝輸入、黑字＝公式；黃底＝判斷題。建置：bash alphabet/make_v03.sh
A27: 數字標記：Verified（經查核）／Interested-party（公司或賣方自述）／Analogy／Assumed（給區間）／Derived（換算）。本模型是研究整理，不是投資建議以外的保證。

Sheet In
A1: In — 輸入（藍字；基準欄 E 進主模型；D／F＝敏感度低／高，只用於 Sens 頁、不進目標價；情境 A／B／C 的驅動見本頁最後一節「情境驅動對照」〔v0.3.3〕）。金額 US$B；每股 US$；股數十億股；MW＝IT MW。標記：Verified／Interested-party／Analogy／Assumed／Derived（Analogy、Assumed 一律給低／高區間）
A2: 「沿用 v0.2.2」＝MAG v0.2.2 已核准的參數（原出處：alphabet/legacy_v0.2/company.json、kspec.py、data/kevidence_alphabet_20261008.json；對照表 r1 C1–C23）。v0.3.1：Tokenomics 升級 v21.7（data/tokenomics_snapshot_v21.7.json）、2026Q3 實績（data/alphabet_facts_2026q3.json）、評價日 2026-09-30。黃底＝判斷題（Andy 可改）
A3: 鍵 | B3: 項目 | C3: 單位 | D3: 敏感度低 | E3: 基準 | F3: 敏感度高 | G3: 標記 | H3: 來源 | I3: 說明
A4: A. 現價、股數與資產負債（評價日 2026-09-30；2026Q3 財報新聞稿，10-Q 尚未提供）
A5: px | B5: 現價（2026-10-28 收盤） | C5: US$ | E5: 324.89 | G5: Verified | H5: BigGo Finance https://finance.biggo.com/news/747b8ed4-8d02-4fc5-84ac-f68ab61a7d20（10-28 收盤 324.89、盤後 294.20）；Investing.com GOOGL 報價 324.89（+1.34%）https://www.investing.com/news/company-news/alphabet-q3-2026-slides-128b-revenue-overshadowed-by-profit-miss-93CH-4981067（2026-10-29 讀取） | I5: 只影響上檔空間與評等（v0.3.1 起與 WACC、回購價脫鉤，見 px_val）。財報後盤後約 288–294（−9%～−11%）；10-29 收盤尚未產生。v0.3 現價 316.80（2026-10-26）
A6: px_val | B6: 評價日股價（2026-09-30 收盤；WACC 權益權重與回購價用） | C6: US$ | E6: 344.08 | G6: Verified | H6: FinancialContent GOOGL 歷史股價 https://www.financialcontent.com/quote/NQ%3AGOOGL/historical（2026-10-29 讀取：9/30 收盤 344.08；同頁 10/07 350.50、10/23 320.21 與 StockAnalysis 相同） | I6: v0.3.1 新增：評價日市值權重（與評價日一致）；v0.3 以現價代用
A7: sh_out | B7: 流通股數（2026-09-30，資產負債表股本說明） | C7: 十億股 | E7: 12.294 | G7: Interested-party | H7: mag/extract/docs/2026Q3/alphabet_2026Q3_新聞稿.pdf 第 4 頁資產負債表股本說明（2026-10-28；事實總帳 sh.out.20260930） | I7: 10-Q 封面股數尚未提供；Class A 5,888＋B 828＋C 5,578 百萬股
A8: sh_dil_q2 | B8: 2026Q3 稀釋加權股數 | C8: 十億股 | E8: 12.368 | G8: Interested-party | H8: mag/extract/docs/2026Q3/alphabet_2026Q3_新聞稿.pdf 第 5 頁（2026-10-28；事實總帳 sh.dilW.2026q3）
A9: sh_basic_q2 | B9: 2026Q3 基本加權股數 | C9: 十億股 | E9: 12.256 | G9: Interested-party | H9: mag/extract/docs/2026Q3/alphabet_2026Q3_新聞稿.pdf 第 5 頁（2026-10-28；事實總帳 sh.basicW.2026q3） | I9: Q3 ATM 發行 36M 股（在季內加權）；期末稀釋股數＝Q3 稀釋加權＋(9/30 流通股 − Q3 基本加權)
A10: conv_sh | B10: 強制轉換特別股 2029-05-15 轉換股數（上限） | C10: 十億股 | D10: 0.0436 | E10: 0.0546 | F10: 0.0546 | G10: Interested-party | H10: 8-K 2026-06-05：A 系列每股轉 2.2520–2.8160 股、B 系列 2.2740–2.8420 股 → 43.6–54.6M 股；沿用 v0.2.2（legacy_v0.2/company.json） debt.convertibles | I10: 取稀釋最大（保守）；評價時直接加入股數，特別股股利照付至轉換
A11: cash_0 | B11: 現金＋債權類有價證券（2026-09-30） | C11: US$B | E11: 174.698 | G11: Derived | H11: 新聞稿資產負債表：現金 56.334＋有價證券 208.764＝265.098 − 其中權益證券 90.4（法說；事實總帳 bs.cashTotal.2026q3、mkt.eqsec.2026q3） | I11: 10-Q 附註 3 尚未提供：權益證券以法說 90.4 代用（資料缺口）；2026-06-30 為 155.411
A12: cash_ye25 | B12: 現金＋債權類有價證券（2025-12-31） | C12: US$B | E12: 120.53 | G12: Derived | H12: 10-K 2025：30.708＋96.135 − 6.313（沿用 v0.2.2（legacy_v0.2/company.json） ytdActual.cash1231）
A13: debt_0 | B13: 債務面額（2026-09-30） | C13: US$B | E13: 126.455 | G13: Derived | H13: 2026-06-30 面額 101.085（10-Q 附註 6）＋Q3 發債淨額 28.996 − Q3 償還 3.626（新聞稿現金流量表） | I13: 10-Q 附註 6 尚未提供（資料缺口）；對照：資產負債表長期債務帳面 125.102（不含一年內到期）
A14: fines | B14: 應計罰款與和解（類債） | C14: US$B | E14: 12.156 | G14: Derived | H14: 2026-06-30 餘額 17.356（10-Q 2026Q2）− Q3 已付歐盟罰款 5.2（法說） | I14: 10-Q 尚未提供；v0.3 以 6/30 餘額扣除（付款在 Q3）
A15: nci | B15: 非控制權益（類債） | C15: US$B | E15: 7.1 | G15: Interested-party | H15: 10-Q 2026Q2（事實總帳 bs.nci；Waymo 等少數股權） | I15: 沿用 2026Q2（10-Q 尚未提供）
A16: B. 持股（分部加總與 DCF 皆加入；非上市 × (1 − 流動性折價)；上市不折價）
A17: ant_val | B17: Anthropic 最近一輪投後估值（Series H） | C17: US$B | E17: 965 | G17: Interested-party | H17: TechCrunch〈Anthropic raises $65 billion, nears $1T valuation ahead of IPO〉（經 anthropic/ SRC_ANT_299）（2026-05-28；事實總帳 rp.anthropic.val.seriesH）
A18: ant_stake | B18: Anthropic 持股比例 | C18: % | D18: 0.11 | E18: 0.125 | F18: 0.14 | G18: Assumed | H18: 一手不存在：2025 法院文件約 14%；非上市證券帳面 124.3B ÷ 965B 隱含上限 12.9%（沿用 v0.2.2（legacy_v0.2/company.json） valuation.holdings）
A19: illiq | B19: 非上市持股流動性折價 | C19: % | D19: 0 | E19: 0.2 | F19: 0.4 | G19: Assumed | H19: 工作單第 2 節 Val 0.2（1 − 流動性折價 20%）；對照表 r1 第 5 節第 9 條
A20: spacex | B20: SpaceX 持股公允價值（上市、限售；2026-09-30） | C20: US$B | E20: 85.436 | G20: Derived | H20: 2026-06-30 94.1（10-Q 附註 3：短期 80.0＋長期限售 14.1）＋Q3 權益證券淨損益 −8.664（新聞稿第 8 頁；法說：主要為 SpaceX 未實現損失） | I20: 假設 Q3 權益證券損失全數來自 SpaceX；10-Q 附註 3 尚未提供（資料缺口）
A21: oth_eq | B21: 其他有價權益證券 | C21: US$B | E21: 7.089 | G21: Derived | H21: 有價權益證券 87.063＋14.126 − SpaceX 94.1（沿用 v0.2.2（legacy_v0.2/company.json））
A22: C. 折現率與目標價規則
A23: rf | B23: 無風險利率（10 年美債，2026-10-27） | C23: % | E23: 0.0499 | G23: Verified | H23: 美國財政部每日殖利率曲線（Daily Treasury Par Yield Curve Rates，10 Yr）https://home.treasury.gov/resource-center/data-chart-center/interest-rates/TextView?type=daily_treasury_yield_curve&field_tdr_date_value_month=202610（2026-10-29 讀取）：10-27 4.99%、10-26 5.00%（最新公布日 10-27） | I23: v0.3 為 5.00%（10-26）
A24: beta_sa | B24: 原始 β：StockAnalysis 5 年月資料（Yahoo、MarketBeat 同值） | C24: x | E24: 1.21 | G24: Verified | H24: StockAnalysis〈GOOGL statistics〉（2026-10-07；事實總帳 val.beta.sa） | I24: 沿用 v0.2.2（legacy_v0.2/company.json）
A25: beta_gf | B25: 原始 β：GuruFocus 3 年 | C25: x | E25: 1.3669 | G25: Verified | H25: GuruFocus〈GOOGL Beta〉（2026-10-08；事實總帳 val.beta.gurufocus） | I25: 與 StockAnalysis 不同資料商、不同期間（C13）
A26: blume_a | B26: Blume 調整係數（β 調整＝a × 原始 β＋(1 − a)） | C26: x | E26: 0.67 | G26: Derived | H26: Blume（1971）；Bloomberg 調整 β 同式（修正一 F4）
A27: beta | B27: β（Blume 調整後兩個獨立來源的中位數） | C27: x | D27: 1.1407 | E27: =MEDIAN(blume_a*beta_sa+1-blume_a,blume_a*beta_gf+1-blume_a) -> 1.1932615 | F27: 1.2458 | G27: Derived | H27: 修正一 F4：Blume 調整（0.67 × 原始 β＋0.33），兩個獨立來源取中位數 | I27: 低／高＝兩個來源各自的調整值；v0.3 修正前用原始 β 平均 1.288
A28: erp | B28: 股權風險溢酬 | C28: % | D28: 0.04 | E28: 0.05 | F28: 0.06 | G28: Assumed | H28: 沿用 v0.2.2（legacy_v0.2/company.json）（val.erp）
A29: kd_sp | B29: 約 10 年期 AA 公司債利差（相對 10 年美債） | C29: % | D29: 0.004 | E29: 0.006 | F29: 0.009 | G29: Assumed | H29: 判斷：Aa2／AA+（事實總帳 debt.rating）10 年期利差約 50–90bp；2066 長債發行利差 T＋130bp 為 40 年期，不採（修正一 F4）
A30: kd | B30: 稅前債務成本（約 10 年期）＝rf＋利差 | C30: % | E30: =rf+kd_sp -> 0.0559 | G30: Derived | H30: 修正一 F4：kd＝約 10 年期公司債殖利率 | I30: v0.3 修正前用 2066 票據 6.527%（Alphabet 定價條款 FWP（2026-08-06；US$25B 票據）（2026-08-06；事實總帳 val.kd.2066））
A31: fin_lease | B31: 融資租賃負債（2026-06-30） | C31: US$B | E31: 2.59 | G31: Interested-party | H31: 10-Q 2026Q2 附註 4（事實總帳 lease.finLiab） | I31: 計入 WACC 負債與 DCF、分部加總的淨負債（修正一 F6）
A32: wacc_adj | B32: WACC 調整（Sens 格：±1pt） | C32: % | D32: -0.01 | E32: 0 | F32: 0.01 | G32: Assumed | H32: 修正一 F4：WACC ±1 個百分點的目標價格
A33: tax_w | B33: WACC 用稅率（2025 有效稅率） | C33: % | E33: 0.168 | G33: Derived | H33: 10-K 2025：所得稅 26.656 ÷ 稅前 158.826 | I33: 沿用 v0.2.2（legacy_v0.2/company.json）
A34: g_tv | B34: 永續成長率（FY2032 後） | C34: % | D34: 0.02 | E34: 0.03 | F34: 0.04 | G34: Assumed | H34: 工作單第 2 節 Val 0.1（g 3%）
A35: ronic_sp | B35: 永續期新投資報酬率 RONIC 相對 WACC 的差 | C35: % | E35: 0 | F35: 0.05 | G35: Assumed | H35: 修正一 F5：RONIC＝WACC（判斷；終值＝NOPAT(FY2033) ×(1 − g ÷ RONIC) ÷ (WACC − g)） | I35: Sens：WACC＋5pt；修正前固定 12%
A36: mid | B36: 期中慣例：年度現金流距年初 | C36: 年 | E36: 0.5 | G36: Derived | H36: 年度現金流平均發生在年中；Q4 26 為評價日後 0.125 年
A37: t_val | B37: 評價日（2026-09-30）的年份小數 | C37: 年 | E37: 2026.75 | G37: Derived | H37: v0.3.1：評價日由 2026-06-30（2026.5）滾到 2026-09-30；年度折現年數＝年度＋mid − t_val
A38: t_q4 | B38: Q4 26 現金流折現年數（評價日 2026-09-30 起，期中） | C38: 年 | E38: 0.125 | G38: Derived | H38: 2026-10-01～12-31 的中點
A39: tp_wA | B39: 情境權重 A | C39: % | E39: 0.25 | G39: Assumed | H39: 工作單第 2 節 Val 0.3（A 25%／B 50%／C 25%）
A40: tp_wB | B40: 情境權重 B | C40: % | E40: 0.5 | G40: Assumed | H40: 同上
A41: tp_wC | B41: 情境權重 C | C41: % | E41: 0.25 | G41: Assumed | H41: 同上
A42: w_dcf | B42: 目標價中 DCF 的權重（其餘＝分部加總 SOTP） | C42: % | D42: 0.3 | E42: 0.5 | F42: 0.7 | G42: Assumed | H42: 工作單第 2 節 Val 0.3（DCF 50%＋分部加總 50%；與 AI半導體「DCF＋Comparable 各半」一致）
A43: t_tgt | B43: 目標時點距評價日（2026-09-30 → 2027-10-29） | C43: 年 | E43: 1.0795 | G43: Derived | H43: (2027-10-29 − 2026-09-30) ÷ 365＝394 天 | I43: 目標價約 12 個月後（今天 2026-10-29 起算）；v0.3 為 2026-06-30 → 2027-10-27（1.3233）
A44: w_ntm27 | B44: 目標時點 NTM 中 FY2027 的權重 | C44: % | E44: 0.1726 | G44: Derived | H44: (2027-12-31 − 2027-10-29) ÷ 365＝63 天；FY2028 權重＝1 − 本值 | I44: 分部加總用目標時點的未來 12 個月 EBITDA
A45: cons_tp | B45: 市場共識目標價（平均） | C45: US$ | E45: 429.12 | G45: Interested-party | H45: StockAnalysis 預測頁 https://stockanalysis.com/stocks/googl/forecast/（2026-10-29 讀取，頁面仍為 2026-10-26 更新；61 位分析師；中位數 430、低 340、高 500） | I45: 財報後（10-28 盤後）的修正尚未反映；賣方有承銷關係，只作對照
A46: dps_tgt | B46: 評價日到目標時點的每股股利（推到目標價時扣除） | C46: US$ | E46: =dps/4+dps*(1+dps_g)*(1-w_ntm27) -> 0.9845176 | G46: Derived | H46: Q4 26 一季＋2027 年至 10-29（修正一 F6）
A47: t_px0 | B47: 現價日（2026-10-28）的年份小數 | C47: 年 | E47: 2026.82 | G47: Derived | H47: 只供對照（v0.3.1 起回購均價改用評價日股價 px_val × (1＋ke)^(期中 − t_val)）
A48: mb_ttm | B48: 分部利益率起點改用近四季（1＝是；0＝9M26） | C48: x | E48: 0 | F48: 1 | G48: Assumed | H48: 判斷：預設 9M26（最新已申報的年初至今，利潤率擴張中、與評價日機隊同時點）；1＝v0.2.2 的近四季口徑
A49: internal_ai_reading | B49: 自用 AI 讀法（2＝主值：自用 AI 價值中性，計影子效益；1＝敏感度：只計成本） | C49: x | D49: 1 | E49: 2 | G49: Assumed | H49: 修正一 F1；Andy 2026-10-27 15:03 決定讀法 2 為主值：自用增量 MW × Tokenomics IF_HoldEcon（k＝1）＝自用 AI 影子效益（非財報營收），進評價口徑 NOPAT、FCF、EPS；對照表 r1 C16 | I49: 營收列與分部對帳不動；Val 頁兩種讀法的目標價並列（皆為活公式）
A50: sbc_add | B50: DCF 加回股權報酬（1＝是；Sens 用） | C50: x | E50: 0 | F50: 1 | G50: Assumed | H50: 判斷：股權報酬視為真實成本、不加回（稀釋已在股數 dil）；1＝加回（稅後）
A51: tv_alt | B51: 終值改用 FY2032 無槓桿自由現金流 ×(1＋g)（1＝是；Sens 用） | C51: x | E51: 0 | F51: 1 | G51: Assumed | H51: 判斷：基準用價值驅動公式（ronic）；1＝替代口徑
A52: C2. 分部加總（SOTP）倍數：同業 NTM EV/EBITDA（沿用 v0.2.2 共用同業檔，基準日 2026-10-07；中位數在 Val 頁計算）
A53: pm_ads_meta | B53: 數位廣告（Search、YouTube、Network、Alphabet 層級費用）：Meta（META）NTM EV/EBITDA | C53: x | E53: 10.79 | G53: Derived | H53: data/peers_ads_20261009.json（C18；MAG 三家共用） | I53: EV（StockAnalysis）÷ NTM EBITDA（MarketScreener 共識 FY1／FY2 時間加權）
A54: pm_ads_pins | B54: 數位廣告（Search、YouTube、Network、Alphabet 層級費用）：Pinterest（PINS）NTM EV/EBITDA | C54: x | E54: 6.91 | G54: Derived | H54: data/peers_ads_20261009.json（C18；MAG 三家共用） | I54: EV（StockAnalysis）÷ NTM EBITDA（MarketScreener 共識 FY1／FY2 時間加權）
A55: pm_ads_ttd | B55: 數位廣告（Search、YouTube、Network、Alphabet 層級費用）：The Trade Desk（TTD）NTM EV/EBITDA | C55: x | E55: 6.53 | G55: Derived | H55: data/peers_ads_20261009.json（C18；MAG 三家共用） | I55: EV（StockAnalysis）÷ NTM EBITDA（MarketScreener 共識 FY1／FY2 時間加權）
A56: pm_ads_app | B56: 數位廣告（Search、YouTube、Network、Alphabet 層級費用）：AppLovin（APP）NTM EV/EBITDA | C56: x | E56: 11.38 | G56: Derived | H56: data/peers_ads_20261009.json（C18；MAG 三家共用） | I56: EV（StockAnalysis）÷ NTM EBITDA（MarketScreener 共識 FY1／FY2 時間加權）
A57: pm_ads_rddt | B57: 數位廣告（Search、YouTube、Network、Alphabet 層級費用）：Reddit（RDDT）NTM EV/EBITDA | C57: x | E57: 13.63 | G57: Derived | H57: data/peers_ads_20261009.json（C18；MAG 三家共用） | I57: EV（StockAnalysis）÷ NTM EBITDA（MarketScreener 共識 FY1／FY2 時間加權）
A58: pm_ads_snap | B58: 數位廣告（Search、YouTube、Network、Alphabet 層級費用）：Snap（SNAP）NTM EV/EBITDA | C58: x | E58: 7.43 | G58: Derived | H58: data/peers_ads_20261009.json（C18；MAG 三家共用） | I58: EV（StockAnalysis）÷ NTM EBITDA（MarketScreener 共識 FY1／FY2 時間加權）
A59: pm_subs_nflx | B59: 訂閱影音（Subscriptions, platforms, and devices）：Netflix（NFLX）NTM EV/EBITDA | C59: x | E59: 15.41 | G59: Derived | H59: legacy_v0.2/company.json valuation.segmentMultiples.subs（NFLX 為 NTM；SPOT、DIS 為 TTM，amazon/data 事實總帳） | I59: EV（StockAnalysis）÷ NTM EBITDA（MarketScreener 共識 FY1／FY2 時間加權）
A60: pm_subs_spot | B60: 訂閱影音（Subscriptions, platforms, and devices）：Spotify（SPOT）NTM EV/EBITDA | C60: x | E60: 31.97 | G60: Derived | H60: legacy_v0.2/company.json valuation.segmentMultiples.subs（NFLX 為 NTM；SPOT、DIS 為 TTM，amazon/data 事實總帳） | I60: EV（StockAnalysis）÷ NTM EBITDA（MarketScreener 共識 FY1／FY2 時間加權）
A61: pm_subs_dis | B61: 訂閱影音（Subscriptions, platforms, and devices）：Disney（DIS）NTM EV/EBITDA | C61: x | E61: 10.58 | G61: Derived | H61: legacy_v0.2/company.json valuation.segmentMultiples.subs（NFLX 為 NTM；SPOT、DIS 為 TTM，amazon/data 事實總帳） | I61: EV（StockAnalysis）÷ NTM EBITDA（MarketScreener 共識 FY1／FY2 時間加權）
A62: pm_cloud_orcl | B62: 非 AI 雲端／軟體（Cloud 其他）：Oracle（ORCL）NTM EV/EBITDA | C62: x | E62: 9.49 | G62: Derived | H62: data/peers_cloud_20261008.json（C12；MAG 三家共用） | I62: EV（StockAnalysis）÷ NTM EBITDA（MarketScreener 共識 FY1／FY2 時間加權）
A63: pm_cloud_ibm | B63: 非 AI 雲端／軟體（Cloud 其他）：IBM（IBM）NTM EV/EBITDA | C63: x | E63: 12.51 | G63: Derived | H63: data/peers_cloud_20261008.json（C12；MAG 三家共用） | I63: EV（StockAnalysis）÷ NTM EBITDA（MarketScreener 共識 FY1／FY2 時間加權）
A64: pm_cloud_sap | B64: 非 AI 雲端／軟體（Cloud 其他）：SAP（SAP）NTM EV/EBITDA | C64: x | E64: 15.13 | G64: Derived | H64: data/peers_cloud_20261008.json（C12；MAG 三家共用） | I64: EV（StockAnalysis）÷ NTM EBITDA（MarketScreener 共識 FY1／FY2 時間加權）
... A69: pm_cloud_docn | B69: 非 AI 雲端／軟體（Cloud 其他）：DigitalOcean（DOCN）NTM EV/EBITDA | C69: x | E69: 24.49 | G69: Derived | H69: data/peers_cloud_20261008.json（C12；MAG 三家共用） | I69: EV（StockAnalysis）÷ NTM EBITDA（MarketScreener 共識 FY1／FY2 時間加權）
A70: mult_ai | B70: TPU 系統銷售的 EV/EBITDA；Cloud AI 同業倍數對照 | C70: x | D70: 4 | E70: 6 | F70: 10 | G70: Assumed | H70: 沿用 v0.2.2（legacy_v0.2/company.json） valuation.evEbitda（AI 基礎設施 6×；CRWV TTM 25×、ORCL NTM 9.5× 為對照，事實總帳 val.peer.aiInfra） | I70: 修正一 F3：Cloud AI 主值改用 AI 模組自身 DCF；本倍數版只作對照列
A71: mult_ads_own | B71: Alphabet 自身 NTM EV/EBITDA（Sens 用） | C71: x | E71: 14.68 | G71: Derived | H71: 事實總帳 val.googl.ownNtm（2026-10-07）
A72: ads_mode | B72: Search、YouTube、Alphabet 層級的倍數（0＝META；1＝六家廣告同業中位數；2＝Alphabet 自身） | C72: x | D72: 1 | E72: 0 | F72: 2 | G72: Assumed | H72: 修正一：小型廣告科技（PINS、TTD、APP、RDDT、SNAP）規模與護城河不可比 → 預設 META NTM 10.79×；Network 仍用六家中位數 | I72: Sens：中位數 9.11×／自身 14.68×
A73: waymo_val | B73: Waymo Series D 投後估值（2026-02-02） | C73: US$B | E73: 126 | G73: Interested-party | H73: Fintool https://fintool.com/news/waymo-16-billion-126-billion-valuation；Bloomberg Law https://news.bloomberglaw.com/private-equity/waymo-raises-16-billion-from-alphabet-others-to-expand-service（2026-10-27 讀取）：募資 16.0、投後 126（含新資金） | I73: Bloomberg：Alphabet 出資約 13.0；修正二
A74: waymo_stake | B74: Alphabet 持有 Waymo 比例 | C74: % | D74: 0.6 | E74: 0.7 | F74: 0.8 | G74: Assumed | H74: 公司未揭露確切比例；Fintool：Alphabet 仍為多數股東（majority investor） | I74: 未找到：確切持股比例
A75: ob_val | B75: Other Bets 價值＝Waymo 估值 × 持股 ×(1 − 流動性折價) | C75: US$B | E75: =waymo_val*waymo_stake*(1-illiq) -> 70.56 | G75: Derived | H75: 修正二：分部加總與 DCF 一致以 Waymo 市場估值計 Other Bets（DCF 排除 Other Bets 營業虧損與資本支出，改加本值） | I75: 其他 Other Bets（Verily 等）不另計
A76: D. 命題模組：AI 容量（沿用 v0.2.2；總 AI MW＝對外 MW ÷ 對外比例）
A77: ext_sh | B77: 對外比例（Google Cloud 客戶 MW ÷ AI 總 MW） | C77: % | D77: 0.25 | E77: 0.3 | F77: 0.4 | G77: Assumed | H77: 事實總帳 mw.extShare（v0.1a 區間 25%–40%） | I77: 沿用 v0.2.2（legacy_v0.2/company.json） capexModel.extShare；C23：公司未揭露，是最大不確定（Sens 另列 ±20pt）
A78: mw_q2 | B78: AI 在役 IT MW（2026-06-30，自用＋對外） | C78: MW | D78: 5012 | E78: 6337 | F78: 7891 | G78: Derived | H78: Epoch AI〈AI Chip Owners〉資料集：cumulative by designer（CSV，2026-05-12 更新）（2026-05-12；事實總帳 mw.ai.it.2026q2） | I78: Epoch AI 晶片功耗 3,841 MW × IT/TDP 1.65；對外 1,901＝6,337 × 30%（沿用 v0.2.2（legacy_v0.2/company.json） defaults.billableOpen）
A79: mw_tot0 | B79: AI 在役 IT MW（評價日 2026-09-30）＝6/30 ＋ pace × 0.25 | C79: MW | E79: =mw_q2+pace*0.25 -> 7894.075 | G79: Derived | H79: v0.3.1：Q3 新增依 C10 基準速度（GB300 錨，2026 世代組合）；Q3 資本支出 51.4 已是實績 | I79: 期初機隊＝6/30 機隊（mix0）＋Q3 新增
A80: mw_ye25 | B80: AI 在役 IT MW（2025-12-31） | C80: MW | E80: 4873 | G80: Derived | H80: Epoch AI〈AI Chip Owners〉資料集：cumulative by designer（CSV，2026-05-12 更新）（2026-05-12；事實總帳 mw.ai.it.epoch.2025q4） | I80: 對外 1,462（沿用 v0.2.2（legacy_v0.2/company.json） defaults.mwYearEnd 2025）÷ 30%
A81: mw_ye24 | B81: AI 在役 IT MW（2024-12-31；汰換用） | C81: MW | E81: 2143.3 | G81: Derived | H81: 沿用 v0.2.2（legacy_v0.2/company.json） defaults.mwYearEnd 2024 對外 643 ÷ 30%
A82: mw_ye23 | B82: AI 在役 IT MW（2023-12-31；汰換用） | C82: MW | E82: 636.7 | G82: Derived | H82: 沿用 v0.2.2（legacy_v0.2/company.json） defaults.mwYearEnd 2023 對外 191 ÷ 30%
A83: pace | B83: AI 總 MW 每年新增（三情境相同；C10 重解） | C83: MW/年 | D83: 4152.4 | E83: 6228.3 | F83: 9342.5 | G83: Derived | H83: C10（v0.3.1 重解，alphabet/calib_pace_v031.py → data/pace_v031.json）：FY2026 資本支出＝9M 實績 131.953＋Q4 公式＝2026 指引中點 200（2026-10-28 法說維持 195–205），指引下限補足 ≈ 0 | I83: 低／高＝基準 × 2/3／× 1.5（v0.2.2 保守／積極的比例）；v0.3 為 4,159.67（v0.2.2 對外 1,247.9 ÷ 30%）；本版不作情境軸，只列 Sens
A84: pace_tpu1 | B84: AI 總 MW 每年新增：TPU 係數 1.0（舊 C2 口徑）時的 C10 解 | C84: MW/年 | E84: 5208.6 | G84: Derived | H84: 同上，tpu_f＝tpu_cf＝1 時重解；只供變動拆解 (c)／(d) 與 Sens「NonNV 舊口徑」使用
A85: mix0_h | B85: 期初機隊：Hopper 錨（TPU v4／v5、H100／H200） | C85: % | E85: 0.25 | G85: Assumed | H85: 沿用 v0.2.2（legacy_v0.2/company.json） pricing.chips（TPU v4／v5 15%＋Hopper 10%） | I85: C2：TPU 以同期 NVIDIA 世代代理
A86: mix0_b2 | B86: 期初機隊：GB200 錨（Trillium v6e、GB200／B200） | C86: % | E86: 0.45 | G86: Assumed | H86: 沿用 v0.2.2（legacy_v0.2/company.json）（Trillium 35%＋GB200 10%） | I86: C2
A87: mix0_b3 | B87: 期初機隊：GB300 錨（Ironwood） | C87: % | E87: 0.3 | G87: Assumed | H87: 沿用 v0.2.2（legacy_v0.2/company.json）（Ironwood 30%） | I87: C2
A88: am_26 | B88: 2026 新增中 GB300 錨占比（Ironwood＋GB300；其餘 VR200 錨） | C88: % | E88: 1 | G88: Assumed | H88: 沿用 v0.2.2（legacy_v0.2/company.json）（2026 Ironwood 75%＋GB300 25%）
A89: am_28 | B89: 2028 起新增中 VR200 錨占比（下一代 TPU＋VR200；其餘 GB300 錨） | C89: % | E89: 1 | G89: Assumed | H89: 沿用 v0.2.2（legacy_v0.2/company.json）（2028 起下一代 TPU 75%＋VR200 25%）
A90: cip_lag | B90: AI 資本支出到在役的時間差（年；0＝支出當年即依 phi_0 折舊） | C90: 年 | E90: 0 | F90: 1 | G90: Assumed | H90: 修正三：資本支出仍依 MW 路徑足額支付 2H26、FY2027 的新增 MW，在建工程 122.8 是另一筆已付資產（照原時程折舊、不另增 MW）→ 時間差取 0 才不會少提折舊 | I90: 1＝修正二口徑（在建工程視為新增 MW 來源但資本支出未相應減少，約 58 的資產少提折舊）
A91: conv_mw | B91: FY2029 起 MW 新增速度收斂年數（到 FY2032 只剩 g × 期初 MW） | C91: 年 | E91: 4 | G91: Assumed | H91: 修正一 F5：終值不得落在建置高峰
A92: am_27 | B92: 2027 新增中 GB300 錨占比（Ironwood＋GB300；其餘 VR200 錨） | C92: % | E92: 0.5 | G92: Assumed | H92: 沿用 v0.2.2（legacy_v0.2/company.json）（2027 Ironwood 40%＋GB300 10%） | I92: 2026 新增全為 GB300 錨（Ironwood 75%＋GB300 25%）；2028 起全為 VR200 錨（下一代 TPU＋VR200）
A93: tpu_sh | B93: TPU 占 AI MW 比例 | C93: % | E93: 0.75 | G93: Derived | H93: Epoch 2025 年新增功耗 TPU 約 77%（沿用 v0.2.2（legacy_v0.2/company.json） pricing.mixNote） | I93: 只在 TPU 係數不等於 1 時有作用
A94: tpu_hold | B94: Tokenomics IF_NonNV_Hold_TPU（TPU v7 每 GW 持有成本 ÷ VR200） | C94: x | D94: 0.65 | E94: 0.7 | F94: 0.9 | G94: Assumed | H94: data/tokenomics_snapshot_v21.7.json（20261025_Tokenomics_v21.7.xlsx，Interface!C375:E375；Tokenomics 標 Assumed，v21.6 起依每 kW 設備價推導） | I94: 權威在 Tokenomics（規則第 13 條；契約第 6 條）
A95: tpu_out | B95: Tokenomics IF_NonNV_Out_TPU（TPU v7 每 GW 產出 ÷ VR200） | C95: x | D95: 0.6 | E95: 0.8 | F95: 1.1 | G95: Assumed | H95: data/tokenomics_snapshot_v21.7.json（Interface!C370:E370；Tokenomics 標 Assumed、慣例值，PR #172 Q1 未決） | I95: 只作敏感度（收入改按產出比）
A96: tpu_f | B96: TPU 每 MW 收入錨係數（＝Tokenomics TPU 持有成本比） | C96: x | D96: 0.65 | E96: =tpu_hold -> 0.7 | F96: 1 | G96: Derived | H96: v0.3.1（工作單第 1 節第 3 項預設：改讀 Tokenomics）：TPU MW 的每 MW 收入＝k × TPU 持有成本＝k × IF_NonNV_Hold_TPU × 錨世代 IF_HoldEcon（持有成本比套用到各錨世代，近似） | I96: 高＝1.0 為舊 C2 口徑（同期 NVIDIA 世代 × 1.0，v0.3）；低＝Tokenomics 低端 0.65
A97: tpu_cf | B97: TPU 每 MW IT 資本支出係數（＝Tokenomics TPU 持有成本比） | C97: x | D97: 0.65 | E97: =tpu_hold -> 0.7 | F97: 1 | G97: Derived | H97: v0.3.1：IT 資本支出與持有成本同比例（持有成本以資本回收為主）；Tokenomics 未單列 TPU 每 GW 資本支出 | I97: 敏感度時與 tpu_f 同側
A98: E. 命題模組：每 MW 價格（k＝證據價格 ÷ Tokenomics 同世代成本；沿用 v0.2.2 kspec.py）
A99: kl_px | B99: 長約證據價格（判斷倍數 0.75 × v5.27 VR200 12.762） | C99: US$m/MW-年 | D99: 7.6572 | E99: 9.5715 | G99: Assumed | H99: legacy_v0.2/company.json pricing.kEvidence long.base／long.low（data/kevidence_alphabet_20261008.json kspecInputs） | I99: 不是觀察到的市場價格；分母＝VR200 IF_HoldEcon
A100: ks_px | B100: 現貨證據價格（Silicon Data H100 指數） | C100: US$/GPU-hr | E100: 2.82 | F100: 4.858 | G100: Verified | H100: Silicon Data H100 Index（2026-10-06）https://www.silicondata.com/products/silicon-index/h100；高＝GCP a3-highgpu-8g 3 年預留 4.858（Interested-party） | I100: 分母＝IF_GPUhrEcon｜H100；C1 三家一致
A101: long_sh | B101: 長約占比 | C101: % | D101: 0.4 | E101: 0.6 | F101: 0.8 | G101: Assumed | H101: 沿用 v0.2.2（legacy_v0.2/company.json） pricing.longShare（Cloud 積壓以多年期大客戶為主）
A102: he_h | B102: IF_HoldEcon｜H100（每 MW 年持有成本，經濟口徑） | C102: US$m/MW-年 | D102: 6.7910747 | E102: 9.7030873 | F102: 16.66377 | G102: Derived | H102: data/tokenomics_snapshot_v21.7.json（20261025_Tokenomics_v21.7.xlsx，Interface!C13:Q13） | I102: Tokenomics WACC 10% 下的打平持有成本；收入端不乘 IF_Util（MW-year 計價）
A103: he_b2 | B103: IF_HoldEcon｜GB200（每 MW 年持有成本，經濟口徑） | C103: US$m/MW-年 | D103: 6.6118163 | E103: 8.8281656 | F103: 14.318575 | G103: Derived | H103: data/tokenomics_snapshot_v21.7.json（20261025_Tokenomics_v21.7.xlsx，Interface!C13:Q13） | I103: Tokenomics WACC 10% 下的打平持有成本；收入端不乘 IF_Util（MW-year 計價）
A104: he_b3 | B104: IF_HoldEcon｜GB300（每 MW 年持有成本，經濟口徑） | C104: US$m/MW-年 | D104: 8.4288991 | E104: 10.886411 | F104: 18.534646 | G104: Derived | H104: data/tokenomics_snapshot_v21.7.json（20261025_Tokenomics_v21.7.xlsx，Interface!C13:Q13） | I104: Tokenomics WACC 10% 下的打平持有成本；收入端不乘 IF_Util（MW-year 計價）
...

Sheet Q
A1: Q — 實績（US$B；EPS 美元；股數十億股）。資料取自 data/alphabet_facts_20261008.json（MAG v0.1a 起的 SEC 一手資料）與 data/alphabet_facts_2026q3.json（2026Q3 新聞稿，v0.3.1）；季度數＝財報新聞稿 [Interested-party，10-Q 核閱]，年度＝10-K [Verified]
A2: 核對列（實績必須為 0）：產品線合計＝Google Services、分部合計＝合併營收、分部營業利益合計＝合併營業利益（Alphabet-level activities 含避險損益營收與未分攤費用）、營收 − 成本費用＝營業利益、FY2025 四季合計＝年報
A3: 項目 | B3: 2024Q4 | C3: 2025Q1 | D3: 2025Q2 | E3: 2025Q3 | F3: 2025Q4 | G3: 2026Q1 | H3: 2026Q2 | I3: 2026Q3 | J3: FY2024 | K3: FY2025 | L3: 9M26 | M3: 近四季 TTM | N3: 前四季 | O3: 標記 | P3: 來源
A4: 營收（官方分部與產品線）
A5: Google Search & other | B5: 54.034 | C5: 50.702 | D5: 54.19 | E5: 56.567 | F5: 63.073 | G5: 60.399 | H5: 63.271 | I5: 63.35 | J5: 198.084 | K5: 224.532 | L5: =G5+H5+I5 -> 187.02 | M5: =SUM(F5:I5) -> 250.093 | N5: =SUM(B5:E5) -> 215.493 | O5: Verified（年）／Interested-party（季） | P5: 季：Alphabet 財報新聞稿（8-K 附件 99.1，各季；事實總帳 is.*.2024q4–2026q2；2026Q3＝mag/extract/docs/2026Q3/alphabet_2026Q3_新聞稿.pdf，事實總帳 alphabet_facts_2026q3.json）；年：Form 10-K FY2024、FY2025（經查核）
A6: YouTube ads | B6: 10.473 | C6: 8.927 | D6: 9.796 | E6: 10.261 | F6: 11.383 | G6: 9.883 | H6: 11.055 | I6: 11.207 | J6: 36.147 | K6: 40.367 | L6: =G6+H6+I6 -> 32.145 | M6: =SUM(F6:I6) -> 43.528 | N6: =SUM(B6:E6) -> 39.457 | O6: Verified（年）／Interested-party（季） | P6: 季：Alphabet 財報新聞稿（8-K 附件 99.1，各季；事實總帳 is.*.2024q4–2026q2；2026Q3＝mag/extract/docs/2026Q3/alphabet_2026Q3_新聞稿.pdf，事實總帳 alphabet_facts_2026q3.json）；年：Form 10-K FY2024、FY2025（經查核）
A7: Google Network | B7: 7.954 | C7: 7.256 | D7: 7.354 | E7: 7.354 | F7: 7.828 | G7: 6.971 | H7: 7.303 | I7: 7.455 | J7: 30.359 | K7: 29.792 | L7: =G7+H7+I7 -> 21.729 | M7: =SUM(F7:I7) -> 29.557 | N7: =SUM(B7:E7) -> 29.918 | O7: Verified（年）／Interested-party（季） | P7: 季：Alphabet 財報新聞稿（8-K 附件 99.1，各季；事實總帳 is.*.2024q4–2026q2；2026Q3＝mag/extract/docs/2026Q3/alphabet_2026Q3_新聞稿.pdf，事實總帳 alphabet_facts_2026q3.json）；年：Form 10-K FY2024、FY2025（經查核）
A8: Google subscriptions, platforms, and devices | B8: 11.633 | C8: 10.379 | D8: 11.203 | E8: 12.87 | F8: 13.578 | G8: 12.384 | H8: 12.911 | I8: 14.29 | J8: 40.34 | K8: 48.03 | L8: =G8+H8+I8 -> 39.585 | M8: =SUM(F8:I8) -> 53.163 | N8: =SUM(B8:E8) -> 46.085 | O8: Verified（年）／Interested-party（季） | P8: 季：Alphabet 財報新聞稿（8-K 附件 99.1，各季；事實總帳 is.*.2024q4–2026q2；2026Q3＝mag/extract/docs/2026Q3/alphabet_2026Q3_新聞稿.pdf，事實總帳 alphabet_facts_2026q3.json）；年：Form 10-K FY2024、FY2025（經查核）
A9: Google Services（分部） | B9: 84.094 | C9: 77.264 | D9: 82.543 | E9: 87.052 | F9: 95.862 | G9: 89.637 | H9: 94.54 | I9: 96.302 | J9: 304.93 | K9: 342.721 | L9: =G9+H9+I9 -> 280.479 | M9: =SUM(F9:I9) -> 376.341 | N9: =SUM(B9:E9) -> 330.953 | O9: Verified（年）／Interested-party（季） | P9: 季：Alphabet 財報新聞稿（8-K 附件 99.1，各季；事實總帳 is.*.2024q4–2026q2；2026Q3＝mag/extract/docs/2026Q3/alphabet_2026Q3_新聞稿.pdf，事實總帳 alphabet_facts_2026q3.json）；年：Form 10-K FY2024、FY2025（經查核）
A10: 檢查：產品線合計 − Google Services | B10: =B5+B6+B7+B8-B9 -> 0 | C10: =C5+C6+C7+C8-C9 -> 0 | D10: =D5+D6+D7+D8-D9 -> 0 | E10: =E5+E6+E7+E8-E9 -> 0 | F10: =F5+F6+F7+F8-F9 -> 0 | G10: =G5+G6+G7+G8-G9 -> 0 | H10: =H5+H6+H7+H8-H9 -> 0 | I10: =I5+I6+I7+I8-I9 -> 0 | ... K10: =K5+K6+K7+K8-K9 -> 0 | L10: =G10+H10+I10 -> 0 | M10: =SUM(F10:I10) -> 0 | N10: =SUM(B10:E10) -> 0 | O10: — | P10: —
A11: Google Cloud（分部） | B11: 11.955 | C11: 12.26 | D11: 13.624 | E11: 15.157 | F11: 17.664 | G11: 20.028 | H11: 24.768 | I11: 30.709 | J11: 43.229 | K11: 58.705 | L11: =G11+H11+I11 -> 75.505 | M11: =SUM(F11:I11) -> 93.169 | N11: =SUM(B11:E11) -> 52.996 | O11: Verified（年）／Interested-party（季） | P11: 季：Alphabet 財報新聞稿（8-K 附件 99.1，各季；事實總帳 is.*.2024q4–2026q2；2026Q3＝mag/extract/docs/2026Q3/alphabet_2026Q3_新聞稿.pdf，事實總帳 alphabet_facts_2026q3.json）；年：Form 10-K FY2024、FY2025（經查核）
A12: Other Bets（分部） | B12: 0.4 | C12: 0.45 | D12: 0.373 | E12: 0.344 | F12: 0.37 | G12: 0.411 | H12: 0.382 | I12: 0.372 | J12: 1.648 | K12: 1.537 | L12: =G12+H12+I12 -> 1.165 | M12: =SUM(F12:I12) -> 1.535 | N12: =SUM(B12:E12) -> 1.567 | O12: Verified（年）／Interested-party（季） | P12: 季：Alphabet 財報新聞稿（8-K 附件 99.1，各季；事實總帳 is.*.2024q4–2026q2；2026Q3＝mag/extract/docs/2026Q3/alphabet_2026Q3_新聞稿.pdf，事實總帳 alphabet_facts_2026q3.json）；年：Form 10-K FY2024、FY2025（經查核）
A13: Hedging gains (losses)（Alphabet-level） | B13: 0.02 | C13: 0.26 | D13: -0.112 | E13: -0.207 | F13: -0.068 | G13: -0.18 | H13: 0.106 | I13: 0.194 | J13: 0.211 | K13: -0.127 | L13: =G13+H13+I13 -> 0.12 | M13: =SUM(F13:I13) -> 0.052 | N13: =SUM(B13:E13) -> -0.039 | O13: Verified（年）／Interested-party（季） | P13: 季：Alphabet 財報新聞稿（8-K 附件 99.1，各季；事實總帳 is.*.2024q4–2026q2；2026Q3＝mag/extract/docs/2026Q3/alphabet_2026Q3_新聞稿.pdf，事實總帳 alphabet_facts_2026q3.json）；年：Form 10-K FY2024、FY2025（經查核）
A14: 合併營收 | B14: 96.469 | C14: 90.234 | D14: 96.428 | E14: 102.346 | F14: 113.828 | G14: 109.896 | H14: 119.796 | I14: 127.577 | J14: 350.018 | K14: 402.836 | L14: =G14+H14+I14 -> 357.269 | M14: =SUM(F14:I14) -> 471.097 | N14: =SUM(B14:E14) -> 385.477 | O14: Verified（年）／Interested-party（季） | P14: 季：Alphabet 財報新聞稿（8-K 附件 99.1，各季；事實總帳 is.*.2024q4–2026q2；2026Q3＝mag/extract/docs/2026Q3/alphabet_2026Q3_新聞稿.pdf，事實總帳 alphabet_facts_2026q3.json）；年：Form 10-K FY2024、FY2025（經查核）
A15: 檢查：分部合計＋避險 − 合併營收 | B15: =B9+B11+B12+B13-B14 -> 0 | C15: =C9+C11+C12+C13-C14 -> 0 | D15: =D9+D11+D12+D13-D14 -> 0 | E15: =E9+E11+E12+E13-E14 -> 0 | F15: =F9+F11+F12+F13-F14 -> 0 | G15: =G9+G11+G12+G13-G14 -> 0 | H15: =H9+H11+H12+H13-H14 -> 0 | I15: =I9+I11+I12+I13-I14 -> 0 | ... K15: =K9+K11+K12+K13-K14 -> 0 | L15: =G15+H15+I15 -> 0 | M15: =SUM(F15:I15) -> 0 | N15: =SUM(B15:E15) -> 0 | O15: — | P15: —
A17: 分部營業利益
A18: Google Services 營業利益 | B18: 32.836 | C18: 32.682 | D18: 33.063 | E18: 33.527 | F18: 40.132 | G18: 40.589 | H18: 39.544 | I18: 39.157 | J18: 121.263 | K18: 139.404 | L18: =G18+H18+I18 -> 119.29 | M18: =SUM(F18:I18) -> 159.422 | N18: =SUM(B18:E18) -> 132.108 | O18: Verified（年）／Interested-party（季） | P18: 季：Alphabet 財報新聞稿（8-K 附件 99.1，各季；事實總帳 is.*.2024q4–2026q2；2026Q3＝mag/extract/docs/2026Q3/alphabet_2026Q3_新聞稿.pdf，事實總帳 alphabet_facts_2026q3.json）；年：Form 10-K FY2024、FY2025（經查核）
A19: Google Cloud 營業利益 | B19: 2.093 | C19: 2.177 | D19: 2.826 | E19: 3.594 | F19: 5.313 | G19: 6.598 | H19: 8.814 | I19: 11.121 | J19: 6.112 | K19: 13.91 | L19: =G19+H19+I19 -> 26.533 | M19: =SUM(F19:I19) -> 31.846 | N19: =SUM(B19:E19) -> 10.69 | O19: Verified（年）／Interested-party（季） | P19: 季：Alphabet 財報新聞稿（8-K 附件 99.1，各季；事實總帳 is.*.2024q4–2026q2；2026Q3＝mag/extract/docs/2026Q3/alphabet_2026Q3_新聞稿.pdf，事實總帳 alphabet_facts_2026q3.json）；年：Form 10-K FY2024、FY2025（經查核）
A20: Other Bets 營業利益 | B20: -1.174 | C20: -1.226 | D20: -1.246 | E20: -1.426 | F20: -3.617 | G20: -2.1 | H20: -1.799 | I20: -2.047 | J20: -4.444 | K20: -7.515 | L20: =G20+H20+I20 -> -5.946 | M20: =SUM(F20:I20) -> -9.563 | N20: =SUM(B20:E20) -> -5.072 | O20: Verified（年）／Interested-party（季） | P20: 季：Alphabet 財報新聞稿（8-K 附件 99.1，各季；事實總帳 is.*.2024q4–2026q2；2026Q3＝mag/extract/docs/2026Q3/alphabet_2026Q3_新聞稿.pdf，事實總帳 alphabet_facts_2026q3.json）；年：Form 10-K FY2024、FY2025（經查核）
A21: Alphabet-level activities（避險營收 − 未分攤費用） | B21: -2.783 | C21: -3.027 | D21: -3.372 | E21: -4.467 | F21: -5.894 | G21: -5.391 | H21: -5.789 | I21: -7.655 | J21: -10.541 | K21: -16.76 | L21: =G21+H21+I21 -> -18.835 | M21: =SUM(F21:I21) -> -24.729 | N21: =SUM(B21:E21) -> -13.649 | O21: Verified（年）／Interested-party（季） | P21: 季：Alphabet 財報新聞稿（8-K 附件 99.1，各季；事實總帳 is.*.2024q4–2026q2；2026Q3＝mag/extract/docs/2026Q3/alphabet_2026Q3_新聞稿.pdf，事實總帳 alphabet_facts_2026q3.json）；年：Form 10-K FY2024、FY2025（經查核）
A22: 合併營業利益 | B22: 30.972 | C22: 30.606 | D22: 31.271 | E22: 31.228 | F22: 35.934 | G22: 39.696 | H22: 40.77 | I22: 40.576 | J22: 112.39 | K22: 129.039 | L22: =G22+H22+I22 -> 121.042 | M22: =SUM(F22:I22) -> 156.976 | N22: =SUM(B22:E22) -> 124.077 | O22: Verified（年）／Interested-party（季） | P22: 季：Alphabet 財報新聞稿（8-K 附件 99.1，各季；事實總帳 is.*.2024q4–2026q2；2026Q3＝mag/extract/docs/2026Q3/alphabet_2026Q3_新聞稿.pdf，事實總帳 alphabet_facts_2026q3.json）；年：Form 10-K FY2024、FY2025（經查核）
A23: 檢查：分部營業利益合計 − 合併營業利益 | B23: =B18+B19+B20+B21-B22 -> 0 | C23: =C18+C19+C20+C21-C22 -> 0 | D23: =D18+D19+D20+D21-D22 -> 0 | E23: =E18+E19+E20+E21-E22 -> 0 | F23: =F18+F19+F20+F21-F22 -> 0 | G23: =G18+G19+G20+G21-G22 -> 0 | H23: =H18+H19+H20+H21-H22 -> 0 | I23: =I18+I19+I20+I21-I22 -> 0 | ... K23: =K18+K19+K20+K21-K22 -> 0 | L23: =G23+H23+I23 -> 0 | M23: =SUM(F23:I23) -> 0 | N23: =SUM(B23:E23) -> 0 | O23: — | P23: —
A25: 合併損益
A26: 營業成本 | B26: 40.613 | C26: 36.361 | D26: 39.039 | E26: 41.369 | F26: 45.766 | G26: 41.271 | H26: 45.943 | I26: 51.419 | J26: 146.306 | K26: 162.535 | L26: =G26+H26+I26 -> 138.633 | M26: =SUM(F26:I26) -> 184.399 | N26: =SUM(B26:E26) -> 157.382 | O26: Verified（年）／Interested-party（季） | P26: 季：Alphabet 財報新聞稿（8-K 附件 99.1，各季；事實總帳 is.*.2024q4–2026q2；2026Q3＝mag/extract/docs/2026Q3/alphabet_2026Q3_新聞稿.pdf，事實總帳 alphabet_facts_2026q3.json）；年：Form 10-K FY2024、FY2025（經查核）
A27: 其中：流量獲取成本 TAC | B27: 14.848 | C27: 13.748 | D27: 14.705 | E27: 14.876 | F27: 16.597 | G27: 15.228 | H27: 16.179 | I27: 16.366 | L27: =G27+H27+I27 -> 47.773 | M27: =SUM(F27:I27) -> 64.37 | N27: =SUM(B27:E27) -> 58.177 | O27: Verified（年）／Interested-party（季） | P27: 季：Alphabet 財報新聞稿（8-K 附件 99.1，各季；事實總帳 is.*.2024q4–2026q2；2026Q3＝mag/extract/docs/2026Q3/alphabet_2026Q3_新聞稿.pdf，事實總帳 alphabet_facts_2026q3.json）；年：Form 10-K FY2024、FY2025（經查核）
A28: 研發費用 | B28: 13.116 | C28: 13.556 | D28: 13.808 | E28: 15.151 | F28: 18.572 | G28: 17.032 | H28: 18.219 | I28: 20.64 | J28: 49.326 | K28: 61.087 | L28: =G28+H28+I28 -> 55.891 | M28: =SUM(F28:I28) -> 74.463 | N28: =SUM(B28:E28) -> 55.631 | O28: Verified（年）／Interested-party（季） | P28: 季：Alphabet 財報新聞稿（8-K 附件 99.1，各季；事實總帳 is.*.2024q4–2026q2；2026Q3＝mag/extract/docs/2026Q3/alphabet_2026Q3_新聞稿.pdf，事實總帳 alphabet_facts_2026q3.json）；年：Form 10-K FY2024、FY2025（經查核）
A29: 行銷費用 | B29: 7.363 | C29: 6.172 | D29: 7.101 | E29: 7.205 | F29: 8.215 | G29: 7.606 | H29: 8.403 | I29: 8.804 | J29: 27.808 | K29: 28.693 | L29: =G29+H29+I29 -> 24.813 | M29: =SUM(F29:I29) -> 33.028 | N29: =SUM(B29:E29) -> 27.841 | O29: Verified（年）／Interested-party（季） | P29: 季：Alphabet 財報新聞稿（8-K 附件 99.1，各季；事實總帳 is.*.2024q4–2026q2；2026Q3＝mag/extract/docs/2026Q3/alphabet_2026Q3_新聞稿.pdf，事實總帳 alphabet_facts_2026q3.json）；年：Form 10-K FY2024、FY2025（經查核）
A30: 管理費用 | B30: 4.405 | C30: 3.539 | D30: 5.209 | E30: 7.393 | F30: 5.341 | G30: 4.291 | H30: 6.461 | I30: 6.138 | J30: 14.188 | K30: 21.482 | L30: =G30+H30+I30 -> 16.89 | M30: =SUM(F30:I30) -> 22.231 | N30: =SUM(B30:E30) -> 20.546 | O30: Verified（年）／Interested-party（季） | P30: 季：Alphabet 財報新聞稿（8-K 附件 99.1，各季；事實總帳 is.*.2024q4–2026q2；2026Q3＝mag/extract/docs/2026Q3/alphabet_2026Q3_新聞稿.pdf，事實總帳 alphabet_facts_2026q3.json）；年：Form 10-K FY2024、FY2025（經查核）
A31: 檢查：營收 − 成本費用 − 營業利益 | B31: =B14-B26-B28-B29-B30-B22 -> 0 | C31: =C14-C26-C28-C29-C30-C22 -> 0 | D31: =D14-D26-D28-D29-D30-D22 -> 0 | E31: =E14-E26-E28-E29-E30-E22 -> 0 | F31: =F14-F26-F28-F29-F30-F22 -> 0 | G31: =G14-G26-G28-G29-G30-G22 -> 0 | H31: =H14-H26-H28-H29-H30-H22 -> 0 | I31: =I14-I26-I28-I29-I30-I22 -> 0 | ... K31: =K14-K26-K28-K29-K30-K22 -> 0 | L31: =G31+H31+I31 -> 0 | M31: =SUM(F31:I31) -> 0 | N31: =SUM(B31:E31) -> 0 | O31: — | P31: —
A32: 其他收益淨額（含權益證券損益） | B32: 1.271 | C32: 11.183 | D32: 2.662 | E32: 12.759 | F32: 3.183 | G32: 37.716 | H32: 97.983 | I32: -8.221 | J32: 7.425 | K32: 29.787 | L32: =G32+H32+I32 -> 127.478 | M32: =SUM(F32:I32) -> 130.661 | N32: =SUM(B32:E32) -> 27.875 | O32: Verified（年）／Interested-party（季） | P32: 季：Alphabet 財報新聞稿（8-K 附件 99.1，各季；事實總帳 is.*.2024q4–2026q2；2026Q3＝mag/extract/docs/2026Q3/alphabet_2026Q3_新聞稿.pdf，事實總帳 alphabet_facts_2026q3.json）；年：Form 10-K FY2024、FY2025（經查核）
A33: 其中：權益證券淨損益 | B33: 0.364 | C33: 9.758 | D33: 1.286 | E33: 10.734 | F33: 2.302 | G33: 36.915 | H33: 99.031 | I33: -8.664 | L33: =G33+H33+I33 -> 127.282 | M33: =SUM(F33:I33) -> 129.584 | N33: =SUM(B33:E33) -> 22.142 | O33: Verified（年）／Interested-party（季） | P33: 季：Alphabet 財報新聞稿（8-K 附件 99.1，各季；事實總帳 is.*.2024q4–2026q2；2026Q3＝mag/extract/docs/2026Q3/alphabet_2026Q3_新聞稿.pdf，事實總帳 alphabet_facts_2026q3.json）；年：Form 10-K FY2024、FY2025（經查核）
A34: 稅前利益 | B34: 32.243 | C34: 41.789 | D34: 33.933 | E34: 43.987 | F34: 39.117 | G34: 77.412 | H34: 138.753 | I34: 32.355 | J34: 119.815 | K34: 158.826 | L34: =G34+H34+I34 -> 248.52 | M34: =SUM(F34:I34) -> 287.637 | N34: =SUM(B34:E34) -> 151.952 | O34: Verified（年）／Interested-party（季） | P34: 季：Alphabet 財報新聞稿（8-K 附件 99.1，各季；事實總帳 is.*.2024q4–2026q2；2026Q3＝mag/extract/docs/2026Q3/alphabet_2026Q3_新聞稿.pdf，事實總帳 alphabet_facts_2026q3.json）；年：Form 10-K FY2024、FY2025（經查核）
A35: 檢查：營業利益＋其他收益 − 稅前利益 | B35: =B22+B32-B34 -> 0 | C35: =C22+C32-C34 -> 0 | D35: =D22+D32-D34 -> 0 | E35: =E22+E32-E34 -> 0 | F35: =F22+F32-F34 -> 0 | G35: =G22+G32-G34 -> 0 | H35: =H22+H32-H34 -> 0 | I35: =I22+I32-I34 -> 0 | ... K35: =K22+K32-K34 -> 0 | L35: =G35+H35+I35 -> 0 | M35: =SUM(F35:I35) -> 0 | N35: =SUM(B35:E35) -> 0 | O35: — | P35: —
A36: 所得稅 | B36: 5.707 | C36: 7.249 | D36: 5.737 | E36: 9.008 | F36: 4.662 | G36: 14.834 | H36: 26.56 | I36: 5.887 | J36: 19.697 | K36: 26.656 | L36: =G36+H36+I36 -> 47.281 | M36: =SUM(F36:I36) -> 51.943 | N36: =SUM(B36:E36) -> 27.701 | O36: Verified（年）／Interested-party（季） | P36: 季：Alphabet 財報新聞稿（8-K 附件 99.1，各季；事實總帳 is.*.2024q4–2026q2；2026Q3＝mag/extract/docs/2026Q3/alphabet_2026Q3_新聞稿.pdf，事實總帳 alphabet_facts_2026q3.json）；年：Form 10-K FY2024、FY2025（經查核）
A37: 淨利 | B37: 26.536 | C37: 34.54 | D37: 28.196 | E37: 34.979 | F37: 34.455 | G37: 62.578 | H37: 112.193 | I37: 26.468 | J37: 100.118 | K37: 132.17 | L37: =G37+H37+I37 -> 201.239 | M37: =SUM(F37:I37) -> 235.694 | N37: =SUM(B37:E37) -> 124.251 | O37: Verified（年）／Interested-party（季） | P37: 季：Alphabet 財報新聞稿（8-K 附件 99.1，各季；事實總帳 is.*.2024q4–2026q2；2026Q3＝mag/extract/docs/2026Q3/alphabet_2026Q3_新聞稿.pdf，事實總帳 alphabet_facts_2026q3.json）；年：Form 10-K FY2024、FY2025（經查核）
A38: 檢查：稅前 − 所得稅 − 淨利 | B38: =B34-B36-B37 -> 0 | C38: =C34-C36-C37 -> 0 | D38: =D34-D36-D37 -> 0 | E38: =E34-E36-E37 -> 0 | F38: =F34-F36-F37 -> 0 | G38: =G34-G36-G37 -> 0 | H38: =H34-H36-H37 -> 0 | I38: =I34-I36-I37 -> 0 | ... K38: =K34-K36-K37 -> 0 | L38: =G38+H38+I38 -> 0 | M38: =SUM(F38:I38) -> 0 | N38: =SUM(B38:E38) -> 0 | O38: — | P38: —
A39: 稀釋加權股數（十億股） | B39: 12.348 | C39: 12.291 | D39: 12.198 | E39: 12.203 | F39: 12.228 | G39: 12.238 | H39: 12.309 | I39: 12.368 | J39: 12.447 | K39: 12.23 | L39: =12.324 -> 12.324 | O39: Verified（年）／Interested-party（季） | P39: 季：Alphabet 財報新聞稿（8-K 附件 99.1，各季；事實總帳 is.*.2024q4–2026q2；2026Q3＝mag/extract/docs/2026Q3/alphabet_2026Q3_新聞稿.pdf，事實總帳 alphabet_facts_2026q3.json）；年：Form 10-K FY2024、FY2025（經查核）
A40: EPS（GAAP 稀釋，美元） | B40: 2.15 | C40: 2.81 | D40: 2.31 | E40: 2.87 | F40: 2.82 | G40: 5.11 | H40: 9.11 | I40: 2.12 | J40: 8.04 | K40: 10.81 | L40: =G40+H40+I40 -> 16.34 | M40: =SUM(F40:I40) -> 19.16 | N40: =SUM(B40:E40) -> 10.14 | O40: Verified（年）／Interested-party（季） | P40: 季：Alphabet 財報新聞稿（8-K 附件 99.1，各季；事實總帳 is.*.2024q4–2026q2；2026Q3＝mag/extract/docs/2026Q3/alphabet_2026Q3_新聞稿.pdf，事實總帳 alphabet_facts_2026q3.json）；年：Form 10-K FY2024、FY2025（經查核）
A42: 現金流、資本支出與股東回饋
A43: 折舊（不動產與設備） | B43: 4.205 | C43: 4.487 | D43: 4.998 | E43: 5.611 | F43: 6.04 | G43: 6.482 | H43: 7.104 | I43: 8.369 | J43: 15.311 | K43: 21.136 | L43: =G43+H43+I43 -> 21.955 | M43: =SUM(F43:I43) -> 27.995 | N43: =SUM(B43:E43) -> 19.301 | O43: Verified（年）／Interested-party（季） | P43: 季：Alphabet 財報新聞稿（8-K 附件 99.1，各季；事實總帳 is.*.2024q4–2026q2；2026Q3＝mag/extract/docs/2026Q3/alphabet_2026Q3_新聞稿.pdf，事實總帳 alphabet_facts_2026q3.json）；年：Form 10-K FY2024、FY2025（經查核）
A44: 股權報酬（SBC） | B44: 5.81 | C44: 5.516 | D44: 5.998 | E44: 6.368 | F44: 7.071 | G44: 6.751 | H44: 7.957 | I44: 8.63 | J44: 22.785 | K44: 24.953 | L44: =G44+H44+I44 -> 23.338 | M44: =SUM(F44:I44) -> 30.409 | N44: =SUM(B44:E44) -> 23.692 | O44: Verified（年）／Interested-party（季） | P44: 季：Alphabet 財報新聞稿（8-K 附件 99.1，各季；事實總帳 is.*.2024q4–2026q2；2026Q3＝mag/extract/docs/2026Q3/alphabet_2026Q3_新聞稿.pdf，事實總帳 alphabet_facts_2026q3.json）；年：Form 10-K FY2024、FY2025（經查核）
A45: 營運現金流 | B45: 39.113 | C45: 36.15 | D45: 27.747 | E45: 48.414 | F45: 52.402 | G45: 45.79 | H45: 39.069 | I45: 42.29 | J45: 125.299 | K45: 164.713 | L45: =G45+H45+I45 -> 127.149 | M45: =SUM(F45:I45) -> 179.551 | N45: =SUM(B45:E45) -> 151.424 | O45: Verified（年）／Interested-party（季） | P45: 季：Alphabet 財報新聞稿（8-K 附件 99.1，各季；事實總帳 is.*.2024q4–2026q2；2026Q3＝mag/extract/docs/2026Q3/alphabet_2026Q3_新聞稿.pdf，事實總帳 alphabet_facts_2026q3.json）；年：Form 10-K FY2024、FY2025（經查核）
A46: 資本支出（購置不動產與設備） | B46: 14.276 | C46: 17.197 | D46: 22.446 | E46: 23.953 | F46: 27.851 | G46: 35.674 | H46: 44.924 | I46: 51.355 | J46: 52.535 | K46: 91.447 | L46: =G46+H46+I46 -> 131.953 | M46: =SUM(F46:I46) -> 159.804 | N46: =SUM(B46:E46) -> 77.872 | O46: Verified（年）／Interested-party（季） | P46: 季：Alphabet 財報新聞稿（8-K 附件 99.1，各季；事實總帳 is.*.2024q4–2026q2；2026Q3＝mag/extract/docs/2026Q3/alphabet_2026Q3_新聞稿.pdf，事實總帳 alphabet_facts_2026q3.json）；年：Form 10-K FY2024、FY2025（經查核）
A47: 自由現金流（公司定義：營運現金流 − 資本支出） | B47: 24.837 | C47: 18.953 | D47: 5.301 | E47: 24.461 | F47: 24.551 | G47: 10.116 | H47: -5.855 | I47: -9.065 | J47: 72.764 | K47: 73.266 | L47: =G47+H47+I47 -> -4.804 | M47: =SUM(F47:I47) -> 19.747 | N47: =SUM(B47:E47) -> 73.552 | O47: Verified（年）／Interested-party（季） | P47: 季：Alphabet 財報新聞稿（8-K 附件 99.1，各季；事實總帳 is.*.2024q4–2026q2；2026Q3＝mag/extract/docs/2026Q3/alphabet_2026Q3_新聞稿.pdf，事實總帳 alphabet_facts_2026q3.json）；年：Form 10-K FY2024、FY2025（經查核）
A48: 檢查：營運現金流 − 資本支出 − 自由現金流 | B48: =B45-B46-B47 -> 0 | C48: =C45-C46-C47 -> 0 | D48: =D45-D46-D47 -> 0 | E48: =E45-E46-E47 -> 0 | F48: =F45-F46-F47 -> 0 | G48: =G45-G46-G47 -> 0 | H48: =H45-H46-H47 -> 0 | I48: =I45-I46-I47 -> 0 | ... K48: =K45-K46-K47 -> 0 | L48: =G48+H48+I48 -> 0 | M48: =SUM(F48:I48) -> 0 | N48: =SUM(B48:E48) -> 0 | O48: — | P48: —
A49: 回購 | B49: 15.551 | C49: 15.068 | D49: 13.238 | E49: 11.504 | F49: 5.499 | G49: 0 | H49: 0 | I49: 0 | J49: 62.222 | K49: 45.709 | L49: =G49+H49+I49 -> 0 | M49: =SUM(F49:I49) -> 5.499 | N49: =SUM(B49:E49) -> 55.361 | O49: Verified（年）／Interested-party（季） | P49: 季：Alphabet 財報新聞稿（8-K 附件 99.1，各季；事實總帳 is.*.2024q4–2026q2；2026Q3＝mag/extract/docs/2026Q3/alphabet_2026Q3_新聞稿.pdf，事實總帳 alphabet_facts_2026q3.json）；年：Form 10-K FY2024、FY2025（經查核）
A50: 股利（普通＋特別股） | B50: 2.442 | C50: 2.434 | D50: 2.543 | E50: 2.537 | F50: 2.536 | G50: 2.542 | H50: 2.689 | I50: 2.936 | J50: 7.363 | K50: 10.049 | L50: =G50+H50+I50 -> 8.167 | M50: =SUM(F50:I50) -> 10.703 | N50: =SUM(B50:E50) -> 9.956 | O50: Verified（年）／Interested-party（季） | P50: 季：Alphabet 財報新聞稿（8-K 附件 99.1，各季；事實總帳 is.*.2024q4–2026q2；2026Q3＝mag/extract/docs/2026Q3/alphabet_2026Q3_新聞稿.pdf，事實總帳 alphabet_facts_2026q3.json）；年：Form 10-K FY2024、FY2025（經查核）
A52: 核對彙總（實績必須為 0）
A53: 檢查：上列核對列絕對值合計（8 季＋FY2024＋FY2025） | B53: =SUMPRODUCT(ABS(B10:K10))+SUMPRODUCT(ABS(B15:K15))+SUMPRODUCT(ABS(B23:K23))+SUMPRODUCT(ABS(B31:K31))+SUMPRODUCT(ABS(B35:K35))+SUMPRODUCT(ABS(B38:K38))+SUMPRODUCT(ABS(B48:K48)) -> 0
A54: 檢查：FY2025 四季合計 − 年報（分部營收、產品線、分部營業利益、資本支出、營運現金、折舊） | B54: =ABS(SUM(C9:F9)-K9)+ABS(SUM(C11:F11)-K11)+ABS(SUM(C12:F12)-K12)+ABS(SUM(C13:F13)-K13)+ABS(SUM(C14:F14)-K14)+ABS(SUM(C18:F18)-K18)+ABS(SUM(C19:F19)-K19)+ABS(SUM(C20:F20)-K20)+ABS(SUM(C21:F21)-K21)+ABS(SUM(C22:F22)-K22)+ABS(SUM(C5:F5)-K5)+ABS(SUM(C6:F6)-K6)+ABS(SUM(C7:F7)-K7)+ABS(SUM(C8:F8)-K8)+ABS(SUM(C46:F46)-K46)+ABS(SUM(C45:F45)-K45)+ABS(SUM(C43:F43)-K43) -> 0
A55: 檢查：9M26（三季合計）− 2026Q3 新聞稿年初至今欄（營收、營業利益、成本費用、業外、稅前、稅、淨利、折舊、SBC、營運現金、資本支出） | B55: =ABS(L14-(357.269))+ABS(L22-(121.042))+ABS(L26-(138.633))+ABS(L28-(55.891))+ABS(L29-(24.813))+ABS(L30-(16.89))+ABS(L32-(127.478))+ABS(L34-(248.52))+ABS(L36-(47.281))+ABS(L37-(201.239))+ABS(L43-(21.955))+ABS(L44-(23.338))+ABS(L45-(127.149))+ABS(L46-(131.953)) -> 0
A57: 推導量（Seg、PL 頁的起始值；[Derived]）
A58: 項目 | B58: 數值 | C58: 說明
A59: 近四季年增：Google Search & other（g0s_q＝1 時改用 2026Q3 單季年增） | B59: =IF(g0s_q=1,I5/E5-1,M5/N5-1) -> 0.16056206 | C59: (2025Q4–2026Q3) ÷ (2024Q4–2025Q3) − 1；B 路徑 Q4 26 的年增，之後收斂到長期值
A60: 近四季年增：YouTube ads | B60: =M6/N6-1 -> 0.10317561 | C60: (2025Q4–2026Q3) ÷ (2024Q4–2025Q3) − 1；B 路徑 Q4 26 的年增，之後收斂到長期值
A61: 近四季年增：Google Network | B61: =M7/N7-1 -> -0.012066315 | C61: (2025Q4–2026Q3) ÷ (2024Q4–2025Q3) − 1；B 路徑 Q4 26 的年增，之後收斂到長期值
A62: 近四季年增：Google subscriptions, platforms, and devices | B62: =M8/N8-1 -> 0.15358577 | C62: (2025Q4–2026Q3) ÷ (2024Q4–2025Q3) − 1；B 路徑 Q4 26 的年增，之後收斂到長期值
A63: 近四季年增：Google Cloud | B63: =M11/N11-1 -> 0.75803834 | C63: (2025Q4–2026Q3) ÷ (2024Q4–2025Q3) − 1；B 路徑 Q4 26 的年增，之後收斂到長期值
A64: 近四季 Google Services 營收 | B64: =M9 -> 376.341
A65: 近四季三分部營收合計（不含避險） | B65: =M9+M11+M12 -> 471.045
A66: 折舊分攤比例：Google Services（按近四季營收） | B66: =M9/rev3_ttm -> 0.79894914 | C66: 公司不揭露分部折舊（技術基礎設施依使用量分攤，已含在分部營業利益）→ 按營收分攤（沿用 v0.2.2（legacy_v0.2/company.json）；替代＝依使用量，雲端占比更高）
A67: 折舊分攤比例：Google Cloud | B67: =M11/rev3_ttm -> 0.19779214
A68: 折舊分攤比例：Other Bets | B68: =M12/rev3_ttm -> 0.003258712
A69: 近四季折舊 | B69: =M43 -> 27.995
A70: Google Services EBITDA 率（近四季；營業利益＋分攤折舊） | B70: =(M18+da_ttm*sh_svc)/M9 -> 0.48304219 | C70: v0.2.2 口徑（mb_ttm＝1 時採用）
A71: 9M26 折舊分攤比例：Google Services | B71: =L9/(L9+L11+L12) -> 0.78532769
A72: 9M26 折舊分攤比例：Google Cloud | B72: =L11/(L9+L11+L12) -> 0.21141036
A73: Google Services EBITDA 率（9M26；營業利益＋分攤折舊） | B73: =(L18+L43*sh1_svc)/L9 -> 0.48678108 | C73: v0.3.1：由 1H26 滾為 9M26（最新已申報的年初至今）
A74: Google Services EBITDA 率（預測期採用） | B74: =IF(mb_ttm=1,m_svc_ttm,m_svc_1h) -> 0.48678108 | C74: 預設 9M26（利潤率仍在擴張；近四季口徑列 Sens）；自用 AI 增量成本另計
A75: 近四季 Google Cloud EBITDA（營業利益＋分攤折舊） | B75: =M19+da_ttm*sh_cloud -> 37.383191
A76: 近四季 Google Cloud 營收 | B76: =M11 -> 93.169
A77: 前四季 Google Cloud 營收 | B77: =N11 -> 52.996
A78: 近四季 Other Bets 營業利益 | B78: =M20 -> -9.563
A79: 近四季 Alphabet-level activities | B79: =M21 -> -24.729
A80: TAC ÷ (Search＋Network) 近四季 | B80: =M27/(M5+M7) -> 0.23018058 | C80: 增量 EBITDA 率 im 的參考
A81: 2026Q3 Google Cloud ÷ 9M26 Google Cloud（Q4 Cloud 其他的季度基期） | B81: =I11/L11 -> 0.40671479 | C81: Q4 26 Cloud 其他＝9M Cloud 其他 × 本比例 ×(1＋年增)^0.25

Sheet Thesis
A1: Thesis — 命題模組：AI 容量（MW）× 每 MW 收入（Tokenomics 持有成本 × k）→ Google Cloud 的 Cloud AI 子列；同一套 MW 推出 AI 資本支出、AI 折舊與營運成本，接到分部營業利益（對外 → Google Cloud；自用 → Google Services／Alphabet 層級）
A2: 三情境共用（本版的情境軸是 Search，見 Seg 頁）；MW 速度、對外比例、k 的區間在 Sens 頁。沿用 v0.2.2：k 規格（kspec.py）、對外比例 30%；v0.3.1：Tokenomics v21.7 快照、TPU 係數改讀 IF_NonNV_Hold_TPU、C10 速度依 2026 指引重解。不以 Cloud 營收、RPO 反推 k 或每 MW 價格（工作單第 4 節）
A4: A. 價格與起始值（單一數值，C 欄）
A5: 項目 | B5: 單位 | C5: 數值 | N5: 說明
A6: k_長約＝長約證據價格 ÷ IF_HoldEcon｜VR200 | B6: x | C6: =kl_px/he_vr -> 0.78291462 | N6: kspec.py（v0.2.2）：證據價格不變、分母隨 Tokenomics 快照
A7: k_現貨＝H100 現貨指數 ÷ IF_GPUhrEcon｜H100 | B7: x | C7: =ks_px/gpuhr_h -> 1.8280865 | N7: C1：MAG 三家一致
A8: 混合 k＝長約占比 × k_長約＋(1 − 長約占比) × k_現貨 | B8: x | C8: =long_sh*k_long+(1-long_sh)*k_spot -> 1.2009834 | N8: v0.2.2 為 1.201
A9: TPU 收入錨調整＝1 − TPU 占比 ×(1 − TPU 係數) | B9: x | C9: =1-tpu_sh*(1-tpu_f) -> 0.775 | N9: 基準 1（C2：TPU × 1.0）
A10: TPU IT 資本支出調整 | B10: x | C10: =1-tpu_sh*(1-tpu_cf) -> 0.775
A11: 期初機隊每 MW 年收入（對外） | B11: US$m/MW-年 | C11: =k_blend*tpu_adj*(mix0_h*he_h+mix0_b2*he_b2+mix0_b3*he_b3) -> 8.9952293
A12: 期初機隊每 MW 年營運費用（Tokenomics IF_OpexGW 加權） | B12: US$m/MW-年 | C12: =mix0_h*opx_h+mix0_b2*opx_b2+mix0_b3*opx_b3 -> 1.881462
A13: 近四季 Cloud AI 營收估計（近四季平均對外 MW × 期初每 MW 收入） | B13: US$B | C13: =ai_mw_ttm*permw0/1000 -> 15.227487 | N13: 只用於拆 Cloud 其他的起始成長率與利潤率
A14: 前四季 Cloud AI 營收估計 | B14: US$B | C14: =ai_mw_pttm*permw0/1000 -> 7.4449015
A15: 近四季 Cloud AI EBITDA 估計 | B15: US$B | C15: =ai_mw_ttm*(permw0-opex0)/1000 -> 12.042472
A16: Cloud 其他近四季年增（Cloud − Cloud AI 估計） | B16: % | C16: =(cloud_ttm-ai_ttm)/(cloud_pttm-ai_pttm)-1 -> 0.71107868 | N16: [Derived]；Cloud 其他＝Workspace、非 AI 雲端、Wiz（2026-03 併入）
A17: Cloud 其他 EBITDA 率（近四季：Cloud EBITDA − Cloud AI EBITDA 估計）÷ Cloud 其他營收 | B17: % | C17: =(cloud_ebitda_ttm-ai_ttm_e)/(cloud_ttm-ai_ttm) -> 0.3251248 | N17: [Derived]；mb_ttm＝1 時採用
A18: Cloud 其他 EBITDA 率（9M26） | B18: % | C18: =(Q!L19+Q!L43*sh1_cloud-E41)/(Q!L11-E38) -> 0.333016 | N18: [Derived]；(9M26 Cloud 營業利益＋分攤折舊 − Cloud AI 9M EBITDA) ÷ Cloud 其他 9M
A19: Cloud 其他 EBITDA 率（預測期採用，固定） | B19: % | C19: =IF(mb_ttm=1,m_co_ttm,m_co_1h) -> 0.333016 | N19: 預設 9M26（同 m_svc）
A21: B. AI 容量（AI 總 IT MW；期末）— 依 Tokenomics 世代錨分桶
A22: 項目 | B22: 單位 | C22: FY2024A | D22: FY2025A | E22: 9M26A | F22: Q4 26E | G22: FY2026E | H22: FY2027E | I22: FY2028E | J22: FY2029E | K22: FY2030E | L22: FY2031E | M22: FY2032E | N22: 說明
A23: AI 總 MW 新增（FY2029 起收斂到 g × 期初 MW） | B23: MW | F23: =pace*0.25 -> 1557.075 | G23: =F23 -> 1557.075 | H23: =pace -> 6228.3 | I23: =pace -> 6228.3 | J23: =pace+(g_tv*I28-pace)*MIN(1,(2029-2028)/conv_mw) -> 4835.5331 | K23: =pace+(g_tv*J28-pace)*MIN(1,(2030-2028)/conv_mw) -> 3515.2992 | L23: =pace+(g_tv*K28-pace)*MIN(1,(2031-2028)/conv_mw) -> 2237.8931 | M23: =pace+(g_tv*L28-pace)*MIN(1,(2032-2028)/conv_mw) -> 974.89426 | N23: 三情境相同；修正一 F5：FY2029–FY2032 線性收斂，FY2032 只剩與永續成長 g 一致的增量（另加汰換）
A24: 期末 MW：Hopper 錨 | B24: MW | E24: =mw_q2*mix0_h+pace*0.25*0 -> 1584.25 | F24: =E24+F23*0 -> 1584.25 | G24: =F24 -> 1584.25 | H24: =F24+H23*0 -> 1584.25 | I24: =H24+I23*0 -> 1584.25 | J24: =I24+J23*0 -> 1584.25 | K24: =J24+K23*0 -> 1584.25 | L24: =K24+L23*0 -> 1584.25 | M24: =L24+M23*0 -> 1584.25 | N24: 評價日（2026-09-30）＝6/30 機隊 × 期初占比＋Q3 新增（pace × 0.25，2026 世代組合）；新增依年度世代組合（2026 GB300 錨；2027 GB300／VR200 各半；2028 起 VR200 錨）
A25: 期末 MW：GB200 錨 | B25: MW | E25: =mw_q2*mix0_b2+pace*0.25*0 -> 2851.65 | F25: =E25+F23*0 -> 2851.65 | G25: =F25 -> 2851.65 | H25: =F25+H23*0 -> 2851.65 | I25: =H25+I23*0 -> 2851.65 | J25: =I25+J23*0 -> 2851.65 | K25: =J25+K23*0 -> 2851.65 | L25: =K25+L23*0 -> 2851.65 | M25: =L25+M23*0 -> 2851.65
A26: 期末 MW：GB300 錨 | B26: MW | E26: =mw_q2*mix0_b3+pace*0.25*am_26 -> 3458.175 | F26: =E26+F23*am_26 -> 5015.25 | G26: =F26 -> 5015.25 | H26: =F26+H23*am_27 -> 8129.4 | I26: =H26+I23*(1-am_28) -> 8129.4 | J26: =I26+J23*(1-am_28) -> 8129.4 | K26: =J26+K23*(1-am_28) -> 8129.4 | L26: =K26+L23*(1-am_28) -> 8129.4 | M26: =L26+M23*(1-am_28) -> 8129.4
A27: 期末 MW：VR200 錨 | B27: MW | E27: =mw_q2*0+pace*0.25*(1-am_26) -> 0 | F27: =E27+F23*(1-am_26) -> 0 | G27: =F27 -> 0 | H27: =F27+H23*(1-am_27) -> 3114.15 | I27: =H27+I23*am_28 -> 9342.45 | J27: =I27+J23*am_28 -> 14177.983 | K27: =J27+K23*am_28 -> 17693.282 | L27: =K27+L23*am_28 -> 19931.175 | M27: =L27+M23*am_28 -> 20906.07
A28: 期末 AI 總 MW | B28: MW | E28: =E24+E25+E26+E27 -> 7894.075 | F28: =F24+F25+F26+F27 -> 9451.15 | G28: =G24+G25+G26+G27 -> 9451.15 | H28: =H24+H25+H26+H27 -> 15679.45 | I28: =I24+I25+I26+I27 -> 21907.75 | J28: =J24+J25+J26+J27 -> 26743.283 | K28: =K24+K25+K26+K27 -> 30258.582 | L28: =L24+L25+L26+L27 -> 32496.475 | M28: =M24+M25+M26+M27 -> 33471.37
A29: 期末對外 MW（＝總 MW × 對外比例） | B29: MW | E29: =E28*ext_sh -> 2368.2225 | F29: =F28*ext_sh -> 2835.345 | G29: =G28*ext_sh -> 2835.345 | H29: =H28*ext_sh -> 4703.835 | I29: =I28*ext_sh -> 6572.325 | J29: =J28*ext_sh -> 8022.9849 | K29: =K28*ext_sh -> 9077.5747 | L29: =L28*ext_sh -> 9748.9426 | M29: =M28*ext_sh -> 10041.411 | N29: 2026-06-30 1,901（v0.2.2 defaults.billableOpen）＋Q3 新增 × 30%
A30: 平均在役 MW：Hopper 錨 | B30: MW | E30: =(mw_ye25*mix0_h+E24)/2 -> 1401.25 | F30: =(E24+F24)/2 -> 1584.25 | G30: =(E30+F30)/2 -> 1492.75 | H30: =(F24+H24)/2 -> 1584.25 | I30: =(H24+I24)/2 -> 1584.25 | J30: =(I24+J24)/2 -> 1584.25 | K30: =(J24+K24)/2 -> 1584.25 | L30: =(K24+L24)/2 -> 1584.25 | M30: =(L24+M24)/2 -> 1584.25
A31: 平均在役 MW：GB200 錨 | B31: MW | E31: =(mw_ye25*mix0_b2+E25)/2 -> 2522.25 | F31: =(E25+F25)/2 -> 2851.65 | G31: =(E31+F31)/2 -> 2686.95 | H31: =(F25+H25)/2 -> 2851.65 | I31: =(H25+I25)/2 -> 2851.65 | J31: =(I25+J25)/2 -> 2851.65 | K31: =(J25+K25)/2 -> 2851.65 | L31: =(K25+L25)/2 -> 2851.65 | M31: =(L25+M25)/2 -> 2851.65
A32: 平均在役 MW：GB300 錨 | B32: MW | E32: =(mw_ye25*mix0_b3+E26)/2 -> 2460.0375 | F32: =(E26+F26)/2 -> 4236.7125 | G32: =(E32+F32)/2 -> 3348.375 | H32: =(F26+H26)/2 -> 6572.325 | I32: =(H26+I26)/2 -> 8129.4 | J32: =(I26+J26)/2 -> 8129.4 | K32: =(J26+K26)/2 -> 8129.4 | L32: =(K26+L26)/2 -> 8129.4 | M32: =(L26+M26)/2 -> 8129.4
A33: 平均在役 MW：VR200 錨 | B33: MW | E33: =(mw_ye25*0+E27)/2 -> 0 | F33: =(E27+F27)/2 -> 0 | G33: =(E33+F33)/2 -> 0 | H33: =(F27+H27)/2 -> 1557.075 | I33: =(H27+I27)/2 -> 6228.3 | J33: =(I27+J27)/2 -> 11760.217 | K33: =(J27+K27)/2 -> 15935.633 | L33: =(K27+L27)/2 -> 18812.229 | M33: =(L27+M27)/2 -> 20418.623
A34: 平均在役 AI 總 MW | B34: MW | E34: =E30+E31+E32+E33 -> 6383.5375 | F34: =F30+F31+F32+F33 -> 8672.6125 | G34: =G30+G31+G32+G33 -> 7528.075 | H34: =H30+H31+H32+H33 -> 12565.3 | I34: =I30+I31+I32+I33 -> 18793.6 | J34: =J30+J31+J32+J33 -> 24325.517 | K34: =K30+K31+K32+K33 -> 28500.933 | L34: =L30+L31+L32+L33 -> 31377.529 | M34: =M30+M31+M32+M33 -> 32983.923
A35: 平均在役對外 MW | B35: MW | E35: =E34*ext_sh -> 1915.0612 | F35: =F34*ext_sh -> 2601.7838 | G35: =G34*ext_sh -> 2258.4225 | H35: =H34*ext_sh -> 3769.59 | I35: =I34*ext_sh -> 5638.08 | J35: =J34*ext_sh -> 7297.655 | K35: =K34*ext_sh -> 8550.2798 | L35: =L34*ext_sh -> 9413.2587 | M35: =M34*ext_sh -> 9895.1768
A37: C. Cloud AI（對外 AI 雲端；Google Cloud 的命題子列）
A38: Cloud AI 營收＝對外比例 × Σ 平均 MW × IF_HoldEcon × k × TPU 調整 | B38: US$B | E38: =ext_sh*k_blend*tpu_adj*(E30*he_h+E31*he_b2+E32*he_b3+E33*he_vr)/1000*0.75 -> 13.119056 | F38: =ext_sh*k_blend*tpu_adj*(F30*he_h+F31*he_b2+F32*he_b3+F33*he_vr)/1000*0.25 -> 6.050155 | G38: =E38+F38 -> 19.169211 | H38: =ext_sh*k_blend*tpu_adj*(H30*he_h+H31*he_b2+H32*he_b3+H33*he_vr)/1000*1 -> 36.615799 | I38: =ext_sh*k_blend*tpu_adj*(I30*he_h+I31*he_b2+I32*he_b3+I33*he_vr)/1000*1 -> 57.29516 | J38: =ext_sh*k_blend*tpu_adj*(J30*he_h+J31*he_b2+J32*he_b3+J33*he_vr)/1000*1 -> 76.179473 | K38: =ext_sh*k_blend*tpu_adj*(K30*he_h+K31*he_b2+K32*he_b3+K33*he_vr)/1000*1 -> 90.433098 | L38: =ext_sh*k_blend*tpu_adj*(L30*he_h+L31*he_b2+L32*he_b3+L33*he_vr)/1000*1 -> 100.25294 | M38: =ext_sh*k_blend*tpu_adj*(M30*he_h+M31*he_b2+M32*he_b3+M33*he_vr)/1000*1 -> 105.73669 | N38: 收入端不乘 IF_Util（MW-year 計價）；9M26 為模型估計（公司未揭露 AI 營收），Cloud 其他＝實際 Cloud − 本列
A39: 每 MW 年收入（對外） | B39: US$m/MW-年 | E39: =E38/(E35*0.75)*1000 -> 9.1339504 | F39: =F38/(F35*0.25)*1000 -> 9.3015493 | H39: =H38/(H35*1)*1000 -> 9.7134699 | I39: =I38/(I35*1)*1000 -> 10.162176 | J39: =J38/(J35*1)*1000 -> 10.438898 | K39: =K38/(K35*1)*1000 -> 10.576624 | L39: =L38/(L35*1)*1000 -> 10.650184 | M39: =M38/(M35*1)*1000 -> 10.68568
A40: Cloud AI 營運費用（Tokenomics IF_OpexGW，含電費） | B40: US$B | E40: =ext_sh*(E30*opx_h+E31*opx_b2+E32*opx_b3+E33*opx_vr)/1000*0.75 -> 2.7200588 | F40: =ext_sh*(F30*opx_h+F31*opx_b2+F32*opx_b3+F33*opx_vr)/1000*0.25 -> 1.2415119 | G40: =E40+F40 -> 3.9615707 | H40: =ext_sh*(H30*opx_h+H31*opx_b2+H32*opx_b3+H33*opx_vr)/1000*1 -> 7.3331664 | I40: =ext_sh*(I30*opx_h+I31*opx_b2+I32*opx_b3+I33*opx_vr)/1000*1 -> 11.193056 | J40: =ext_sh*(J30*opx_h+J31*opx_b2+J32*opx_b3+J33*opx_vr)/1000*1 -> 14.667369 | K40: =ext_sh*(K30*opx_h+K31*opx_b2+K32*opx_b3+K33*opx_vr)/1000*1 -> 17.289734 | L40: =ext_sh*(L30*opx_h+L31*opx_b2+L32*opx_b3+L33*opx_vr)/1000*1 -> 19.096376 | M40: =ext_sh*(M30*opx_h+M31*opx_b2+M32*opx_b3+M33*opx_vr)/1000*1 -> 20.105269
A41: Cloud AI EBITDA | B41: US$B | E41: =E38-E40 -> 10.398997 | F41: =F38-F40 -> 4.8086431 | G41: =G38-G40 -> 15.20764 | H41: =H38-H40 -> 29.282633 | I41: =I38-I40 -> 46.102104 | J41: =J38-J40 -> 61.512104 | K41: =K38-K40 -> 73.143364 | L41: =L38-L40 -> 81.156563 | M41: =M38-M40 -> 85.631418
A42: Cloud AI EBITDA 率 | B42: % | E42: =E41/E38 -> 0.79266352 | F42: =F41/F38 -> 0.79479668 | G42: =G41/G38 -> 0.79333679 | H42: =H41/H38 -> 0.79972671 | I42: =I41/I38 -> 0.8046422 | J42: =J41/J38 -> 0.80746297 | K42: =K41/K38 -> 0.80881188 | L42: =L41/L38 -> 0.80951804 | M42: =M41/M38 -> 0.80985531
A43: 上限檢查：每 MW 收入 ÷ 在役世代加權 IFW_RevGWFleet_Util（> 50% 示警；不得作預測） | B43: % | E43: =E39/((E30*cap_h+E31*cap_b2+E32*cap_b3+E33*cap_vr)/E34) -> 0.30396826 | F43: =F39/((F30*cap_h+F31*cap_b2+F32*cap_b3+F33*cap_vr)/F34) -> 0.29282969 | H43: =H39/((H30*cap_h+H31*cap_b2+H32*cap_b3+H33*cap_vr)/H34) -> 0.25812596 | I43: =I39/((I30*cap_h+I31*cap_b2+I32*cap_b3+I33*cap_vr)/I34) -> 0.22589326 | J43: =J39/((J30*cap_h+J31*cap_b2+J32*cap_b3+J33*cap_vr)/J34) -> 0.20943181 | K43: =K39/((K30*cap_h+K31*cap_b2+K32*cap_b3+K33*cap_vr)/K34) -> 0.20237927 | L43: =L39/((L30*cap_h+L31*cap_b2+L32*cap_b3+L33*cap_vr)/L34) -> 0.19887337 | M43: =M39/((M30*cap_h+M31*cap_b2+M32*cap_b3+M33*cap_vr)/M34) -> 0.19724142 | N43: v0.2.2 基準最高 38.0%
A45: D. AI 資本支出（新增 MW × Tokenomics 每 MW 成本；汰換只換 IT）
A46: AI IT 資本支出（成長） | B46: US$B | F46: =F23*(0*cit_h+0*cit_b2+am_26*cit_b3+(1-am_26)*cit_vr)*tpu_adjc/1000 -> 38.901726 | G46: =F46 -> 38.901726 | H46: =H23*(0*cit_h+0*cit_b2+am_27*cit_b3+(1-am_27)*cit_vr)*tpu_adjc/1000 -> 168.51684 | I46: =I23*(0*cit_h+0*cit_b2+(1-am_28)*cit_b3+am_28*cit_vr)*tpu_adjc/1000 -> 181.42678 | J46: =J23*(0*cit_h+0*cit_b2+(1-am_28)*cit_b3+am_28*cit_vr)*tpu_adjc/1000 -> 140.85629 | K46: =K23*(0*cit_h+0*cit_b2+(1-am_28)*cit_b3+am_28*cit_vr)*tpu_adjc/1000 -> 102.39864 | L46: =L23*(0*cit_h+0*cit_b2+(1-am_28)*cit_b3+am_28*cit_vr)*tpu_adjc/1000 -> 65.188534 | M46: =M23*(0*cit_h+0*cit_b2+(1-am_28)*cit_b3+am_28*cit_vr)*tpu_adjc/1000 -> 28.398107
A47: AI 機房資本支出（自建比例 × IF_CapexFacility） | B47: US$B | F47: =F23*selfb*cfac/1000 -> 16.768919 | G47: =F47 -> 16.768919 | H47: =H23*selfb*cfac/1000 -> 67.075677 | I47: =I23*selfb*cfac/1000 -> 67.075677 | J47: =J23*selfb*cfac/1000 -> 52.076274 | K47: =K23*selfb*cfac/1000 -> 37.858015 | L47: =L23*selfb*cfac/1000 -> 24.10099 | M47: =M23*selfb*cfac/1000 -> 10.499124
A48: 汰換 MW（6 年前上線的 MW，換成 VR200 錨 IT） | B48: MW | F48: 0 | G48: =F48 -> 0 | H48: 0 | I48: 0 | J48: =mw_ye23 -> 636.7 | K48: =mw_ye24-mw_ye23 -> 1506.6 | L48: =mw_ye25-mw_ye24 -> 2729.7 | M48: =mw_tot0-mw_ye25+F23 -> 4578.15 | N48: IT 壽命 6 年：2023 年底在役 → 2029 汰換，以此類推；汰換後 MW 照常在役（收入不變）
A49: AI 汰換資本支出（只含 IT） | B49: US$B | F49: =F48*cit_vr*tpu_adjc/1000 -> 0 | G49: =F49 -> 0 | H49: =H48*cit_vr*tpu_adjc/1000 -> 0 | I49: =I48*cit_vr*tpu_adjc/1000 -> 0 | J49: =J48*cit_vr*tpu_adjc/1000 -> 18.546703 | K49: =K48*cit_vr*tpu_adjc/1000 -> 43.886388 | L49: =L48*cit_vr*tpu_adjc/1000 -> 79.514585 | M49: =M48*cit_vr*tpu_adjc/1000 -> 133.35887
A50: AI 資本支出（公式） | B50: US$B | F50: =F46+F47+F49 -> 55.670645 | G50: =G46+G47+G49 -> 55.670645 | H50: =H46+H47+H49 -> 235.59252 | I50: =I46+I47+I49 -> 248.50246 | J50: =J46+J47+J49 -> 211.47927 | K50: =K46+K47+K49 -> 184.14304 | L50: =L46+L47+L49 -> 168.80411 | M50: =M46+M47+M49 -> 172.2561
A51: Q4 26 指引下限補足（MAX(0, 指引 − 9M 實績 − Q4 公式)；歸 AI IT） | B51: US$B | F51: =MAX(0,capex_g-capex_1h-(F50+Seg!F70)) -> 0.00032680947 | G51: =F51 -> 0.00032680947 | N51: C10：FY2026 資本支出＝MAX(9M 實績＋Q4 公式, 公司指引)；v0.3.1 已重解 pace 使本列 ≈ 0（Q4 26 三情境營收相同，用情境 B 的非 AI 資本支出）
A52: AI 資本支出（含指引下限補足） | B52: US$B | F52: =F50+F51 -> 55.670972 | G52: =F52 -> 55.670972 | H52: =H50 -> 235.59252 | I52: =I50 -> 248.50246 | J52: =J50 -> 211.47927 | K52: =K50 -> 184.14304 | L52: =L50 -> 168.80411 | M52: =M50 -> 172.2561
A53: Cloud AI 營收 ÷ AI 資本支出 | B53: x | F53: =F38/F52 -> 0.10867701 | H53: =H38/H52 -> 0.15542004 | I53: =I38/I52 -> 0.23056174 | J53: =J38/J52 -> 0.36022195 | K53: =K38/K52 -> 0.49110244 | L53: =L38/L52 -> 0.59390106 | M53: =M38/M52 -> 0.61383422
A55: E. AI 折舊（在建工程與新增資本支出依年限直線攤提；評價日在役資產的折舊在 PL 頁「基礎折舊」）
A56: 每個資本支出年度：當期 × phi_0、之後每年 1、最後一年 1 − phi_0（年限 life_it／life_fac；IT 含汰換與指引補足；在建工程 Q4 26 起轉入；Q4 26 欄的年折舊 × 0.25）
A57: 在建工程轉入：IT（2026 年度批次） | B57: US$B | F57: =cip_0*cip_it -> 92.65685
A58: 在建工程轉入：機房（2026 年度批次） | B58: US$B | F58: =cip_0*(1-cip_it) -> 49.89215
A59: IT 批次金額（成長＋汰換＋指引補足） | B59: US$B | F59: =F46+F49+F51 -> 38.902053 | H59: =H46+H49 -> 168.51684 | I59: =I46+I49 -> 181.42678 | J59: =J46+J49 -> 159.40299 | K59: =K46+K49 -> 146.28503 | L59: =L46+L49 -> 144.70312 | M59: =M46+M49 -> 161.75697
A60: 機房批次金額 | B60: US$B | F60: =F47 -> 16.768919 | H60: =H47 -> 67.075677 | I60: =I47 -> 67.075677 | J60: =J47 -> 52.076274 | K60: =K47 -> 37.858015 | L60: =L47 -> 24.10099 | M60: =M47 -> 10.499124
A61: 新增 AI 折舊：IT | B61: US$B | F61: =$F$57/life_it*IF((0)<0,0,IF((0)=0,phi_0,IF((0)<life_it,1,IF((0)=life_it,1-phi_0,0))))+$F$59/life_it*IF((0-cip_lag)<0,0,IF((0-cip_lag)=0,phi_0,IF((0-cip_lag)<life_it,1,IF((0-cip_lag)=life_it,1-phi_0,0)))) -> 5.481621 | G61: =F61 -> 5.481621 | H61: =$F$57/life_it*IF((1)<0,0,IF((1)=0,phi_0,IF((1)<life_it,1,IF((1)=life_it,1-phi_0,0))))+$F$59/life_it*IF((1-cip_lag)<0,0,IF((1-cip_lag)=0,phi_0,IF((1-cip_lag)<life_it,1,IF((1-cip_lag)=life_it,1-phi_0,0))))+$H$59/life_it*IF((0-cip_lag)<0,0,IF((0-cip_lag)=0,phi_0,IF((0-cip_lag)<life_it,1,IF((0-cip_lag)=life_it,1-phi_0,0)))) -> 28.948019 | I61: =$F$57/life_it*IF((2)<0,0,IF((2)=0,phi_0,IF((2)<life_it,1,IF((2)=life_it,1-phi_0,0))))+$F$59/life_it*IF((2-cip_lag)<0,0,IF((2-cip_lag)=0,phi_0,IF((2-cip_lag)<life_it,1,IF((2-cip_lag)=life_it,1-phi_0,0))))+$H$59/life_it*IF((1-cip_lag)<0,0,IF((1-cip_lag)=0,phi_0,IF((1-cip_lag)<life_it,1,IF((1-cip_lag)=life_it,1-phi_0,0))))+$I$59/life_it*IF((0-cip_lag)<0,0,IF((0-cip_lag)=0,phi_0,IF((0-cip_lag)<life_it,1,IF((0-cip_lag)=life_it,1-phi_0,0)))) -> 57.572074 | J61: =$F$57/life_it*IF((3)<0,0,IF((3)=0,phi_0,IF((3)<life_it,1,IF((3)=life_it,1-phi_0,0))))+$F$59/life_it*IF((3-cip_lag)<0,0,IF((3-cip_lag)=0,phi_0,IF((3-cip_lag)<life_it,1,IF((3-cip_lag)=life_it,1-phi_0,0))))+$H$59/life_it*IF((2-cip_lag)<0,0,IF((2-cip_lag)=0,phi_0,IF((2-cip_lag)<life_it,1,IF((2-cip_lag)=life_it,1-phi_0,0))))+$I$59/life_it*IF((1-cip_lag)<0,0,IF((1-cip_lag)=0,phi_0,IF((1-cip_lag)<life_it,1,IF((1-cip_lag)=life_it,1-phi_0,0))))+$J$59/life_it*IF((0-cip_lag)<0,0,IF((0-cip_lag)=0,phi_0,IF((0-cip_lag)<life_it,1,IF((0-cip_lag)=life_it,1-phi_0,0)))) -> 86.892213 | K61: =$F$57/life_it*IF((4)<0,0,IF((4)=0,phi_0,IF((4)<life_it,1,IF((4)=life_it,1-phi_0,0))))+$F$59/life_it*IF((4-cip_lag)<0,0,IF((4-cip_lag)=0,phi_0,IF((4-cip_lag)<life_it,1,IF((4-cip_lag)=life_it,1-phi_0,0))))+$H$59/life_it*IF((3-cip_lag)<0,0,IF((3-cip_lag)=0,phi_0,IF((3-cip_lag)<life_it,1,IF((3-cip_lag)=life_it,1-phi_0,0))))+$I$59/life_it*IF((2-cip_lag)<0,0,IF((2-cip_lag)=0,phi_0,IF((2-cip_lag)<life_it,1,IF((2-cip_lag)=life_it,1-phi_0,0))))+$J$59/life_it*IF((1-cip_lag)<0,0,IF((1-cip_lag)=0,phi_0,IF((1-cip_lag)<life_it,1,IF((1-cip_lag)=life_it,1-phi_0,0))))+$K$59/life_it*IF((0-cip_lag)<0,0,IF((0-cip_lag)=0,phi_0,IF((0-cip_lag)<life_it,1,IF((0-cip_lag)=life_it,1-phi_0,0)))) -> 112.9128 | L61: =$F$57/life_it*IF((5)<0,0,IF((5)=0,phi_0,IF((5)<life_it,1,IF((5)=life_it,1-phi_0,0))))+$F$59/life_it*IF((5-cip_lag)<0,0,IF((5-cip_lag)=0,phi_0,IF((5-cip_lag)<life_it,1,IF((5-cip_lag)=life_it,1-phi_0,0))))+$H$59/life_it*IF((4-cip_lag)<0,0,IF((4-cip_lag)=0,phi_0,IF((4-cip_lag)<life_it,1,IF((4-cip_lag)=life_it,1-phi_0,0))))+$I$59/life_it*IF((3-cip_lag)<0,0,IF((3-cip_lag)=0,phi_0,IF((3-cip_lag)<life_it,1,IF((3-cip_lag)=life_it,1-phi_0,0))))+$J$59/life_it*IF((2-cip_lag)<0,0,IF((2-cip_lag)=0,phi_0,IF((2-cip_lag)<life_it,1,IF((2-cip_lag)=life_it,1-phi_0,0))))+$K$59/life_it*IF((1-cip_lag)<0,0,IF((1-cip_lag)=0,phi_0,IF((1-cip_lag)<life_it,1,IF((1-cip_lag)=life_it,1-phi_0,0))))+$L$59/life_it*IF((0-cip_lag)<0,0,IF((0-cip_lag)=0,phi_0,IF((0-cip_lag)<life_it,1,IF((0-cip_lag)=life_it,1-phi_0,0)))) -> 137.22772 | M61: =$F$57/life_it*IF((6)<0,0,IF((6)=0,phi_0,IF((6)<life_it,1,IF((6)=life_it,1-phi_0,0))))+$F$59/life_it*IF((6-cip_lag)<0,0,IF((6-cip_lag)=0,phi_0,IF((6-cip_lag)<life_it,1,IF((6-cip_lag)=life_it,1-phi_0,0))))+$H$59/life_it*IF((5-cip_lag)<0,0,IF((5-cip_lag)=0,phi_0,IF((5-cip_lag)<life_it,1,IF((5-cip_lag)=life_it,1-phi_0,0))))+$I$59/life_it*IF((4-cip_lag)<0,0,IF((4-cip_lag)=0,phi_0,IF((4-cip_lag)<life_it,1,IF((4-cip_lag)=life_it,1-phi_0,0))))+$J$59/life_it*IF((3-cip_lag)<0,0,IF((3-cip_lag)=0,phi_0,IF((3-cip_lag)<life_it,1,IF((3-cip_lag)=life_it,1-phi_0,0))))+$K$59/life_it*IF((2-cip_lag)<0,0,IF((2-cip_lag)=0,phi_0,IF((2-cip_lag)<life_it,1,IF((2-cip_lag)=life_it,1-phi_0,0))))+$L$59/life_it*IF((1-cip_lag)<0,0,IF((1-cip_lag)=0,phi_0,IF((1-cip_lag)<life_it,1,IF((1-cip_lag)=life_it,1-phi_0,0))))+$M$59/life_it*IF((0-cip_lag)<0,0,IF((0-cip_lag)=0,phi_0,IF((0-cip_lag)<life_it,1,IF((0-cip_lag)=life_it,1-phi_0,0)))) -> 156.57386
A62: 新增 AI 折舊：機房 | B62: US$B | F62: =$F$58/life_fac*IF((0)<0,0,IF((0)=0,phi_0,IF((0)<life_fac,1,IF((0)=life_fac,1-phi_0,0))))+$F$60/life_fac*IF((0-cip_lag)<0,0,IF((0-cip_lag)=0,phi_0,IF((0-cip_lag)<life_fac,1,IF((0-cip_lag)=life_fac,1-phi_0,0)))) -> 0.83326337 | G62: =F62 -> 0.83326337 | H62: =$F$58/life_fac*IF((1)<0,0,IF((1)=0,phi_0,IF((1)<life_fac,1,IF((1)=life_fac,1-phi_0,0))))+$F$60/life_fac*IF((1-cip_lag)<0,0,IF((1-cip_lag)=0,phi_0,IF((1-cip_lag)<life_fac,1,IF((1-cip_lag)=life_fac,1-phi_0,0))))+$H$60/life_fac*IF((0-cip_lag)<0,0,IF((0-cip_lag)=0,phi_0,IF((0-cip_lag)<life_fac,1,IF((0-cip_lag)=life_fac,1-phi_0,0)))) -> 4.1714994 | I62: =$F$58/life_fac*IF((2)<0,0,IF((2)=0,phi_0,IF((2)<life_fac,1,IF((2)=life_fac,1-phi_0,0))))+$F$60/life_fac*IF((2-cip_lag)<0,0,IF((2-cip_lag)=0,phi_0,IF((2-cip_lag)<life_fac,1,IF((2-cip_lag)=life_fac,1-phi_0,0))))+$H$60/life_fac*IF((1-cip_lag)<0,0,IF((1-cip_lag)=0,phi_0,IF((1-cip_lag)<life_fac,1,IF((1-cip_lag)=life_fac,1-phi_0,0))))+$I$60/life_fac*IF((0-cip_lag)<0,0,IF((0-cip_lag)=0,phi_0,IF((0-cip_lag)<life_fac,1,IF((0-cip_lag)=life_fac,1-phi_0,0)))) -> 7.5252833 | J62: =$F$58/life_fac*IF((3)<0,0,IF((3)=0,phi_0,IF((3)<life_fac,1,IF((3)=life_fac,1-phi_0,0))))+$F$60/life_fac*IF((3-cip_lag)<0,0,IF((3-cip_lag)=0,phi_0,IF((3-cip_lag)<life_fac,1,IF((3-cip_lag)=life_fac,1-phi_0,0))))+$H$60/life_fac*IF((2-cip_lag)<0,0,IF((2-cip_lag)=0,phi_0,IF((2-cip_lag)<life_fac,1,IF((2-cip_lag)=life_fac,1-phi_0,0))))+$I$60/life_fac*IF((1-cip_lag)<0,0,IF((1-cip_lag)=0,phi_0,IF((1-cip_lag)<life_fac,1,IF((1-cip_lag)=life_fac,1-phi_0,0))))+$J$60/life_fac*IF((0-cip_lag)<0,0,IF((0-cip_lag)=0,phi_0,IF((0-cip_lag)<life_fac,1,IF((0-cip_lag)=life_fac,1-phi_0,0)))) -> 10.691575 | K62: =$F$58/life_fac*IF((4)<0,0,IF((4)=0,phi_0,IF((4)<life_fac,1,IF((4)=life_fac,1-phi_0,0))))+$F$60/life_fac*IF((4-cip_lag)<0,0,IF((4-cip_lag)=0,phi_0,IF((4-cip_lag)<life_fac,1,IF((4-cip_lag)=life_fac,1-phi_0,0))))+$H$60/life_fac*IF((3-cip_lag)<0,0,IF((3-cip_lag)=0,phi_0,IF((3-cip_lag)<life_fac,1,IF((3-cip_lag)=life_fac,1-phi_0,0))))+$I$60/life_fac*IF((2-cip_lag)<0,0,IF((2-cip_lag)=0,phi_0,IF((2-cip_lag)<life_fac,1,IF((2-cip_lag)=life_fac,1-phi_0,0))))+$J$60/life_fac*IF((1-cip_lag)<0,0,IF((1-cip_lag)=0,phi_0,IF((1-cip_lag)<life_fac,1,IF((1-cip_lag)=life_fac,1-phi_0,0))))+$K$60/life_fac*IF((0-cip_lag)<0,0,IF((0-cip_lag)=0,phi_0,IF((0-cip_lag)<life_fac,1,IF((0-cip_lag)=life_fac,1-phi_0,0)))) -> 13.11766 | L62: =$F$58/life_fac*IF((5)<0,0,IF((5)=0,phi_0,IF((5)<life_fac,1,IF((5)=life_fac,1-phi_0,0))))+$F$60/life_fac*IF((5-cip_lag)<0,0,IF((5-cip_lag)=0,phi_0,IF((5-cip_lag)<life_fac,1,IF((5-cip_lag)=life_fac,1-phi_0,0))))+$H$60/life_fac*IF((4-cip_lag)<0,0,IF((4-cip_lag)=0,phi_0,IF((4-cip_lag)<life_fac,1,IF((4-cip_lag)=life_fac,1-phi_0,0))))+$I$60/life_fac*IF((3-cip_lag)<0,0,IF((3-cip_lag)=0,phi_0,IF((3-cip_lag)<life_fac,1,IF((3-cip_lag)=life_fac,1-phi_0,0))))+$J$60/life_fac*IF((2-cip_lag)<0,0,IF((2-cip_lag)=0,phi_0,IF((2-cip_lag)<life_fac,1,IF((2-cip_lag)=life_fac,1-phi_0,0))))+$K$60/life_fac*IF((1-cip_lag)<0,0,IF((1-cip_lag)=0,phi_0,IF((1-cip_lag)<life_fac,1,IF((1-cip_lag)=life_fac,1-phi_0,0))))+$L$60/life_fac*IF((0-cip_lag)<0,0,IF((0-cip_lag)=0,phi_0,IF((0-cip_lag)<life_fac,1,IF((0-cip_lag)=life_fac,1-phi_0,0)))) -> 14.838598 | M62: =$F$58/life_fac*IF((6)<0,0,IF((6)=0,phi_0,IF((6)<life_fac,1,IF((6)=life_fac,1-phi_0,0))))+$F$60/life_fac*IF((6-cip_lag)<0,0,IF((6-cip_lag)=0,phi_0,IF((6-cip_lag)<life_fac,1,IF((6-cip_lag)=life_fac,1-phi_0,0))))+$H$60/life_fac*IF((5-cip_lag)<0,0,IF((5-cip_lag)=0,phi_0,IF((5-cip_lag)<life_fac,1,IF((5-cip_lag)=life_fac,1-phi_0,0))))+$I$60/life_fac*IF((4-cip_lag)<0,0,IF((4-cip_lag)=0,phi_0,IF((4-cip_lag)<life_fac,1,IF((4-cip_lag)=life_fac,1-phi_0,0))))+$J$60/life_fac*IF((3-cip_lag)<0,0,IF((3-cip_lag)=0,phi_0,IF((3-cip_lag)<life_fac,1,IF((3-cip_lag)=life_fac,1-phi_0,0))))+$K$60/life_fac*IF((2-cip_lag)<0,0,IF((2-cip_lag)=0,phi_0,IF((2-cip_lag)<life_fac,1,IF((2-cip_lag)=life_fac,1-phi_0,0))))+$L$60/life_fac*IF((1-cip_lag)<0,0,IF((1-cip_lag)=0,phi_0,IF((1-cip_lag)<life_fac,1,IF((1-cip_lag)=life_fac,1-phi_0,0))))+$M$60/life_fac*IF((0-cip_lag)<0,0,IF((0-cip_lag)=0,phi_0,IF((0-cip_lag)<life_fac,1,IF((0-cip_lag)=life_fac,1-phi_0,0)))) -> 15.873624
A63: 新增 AI 折舊合計 | B63: US$B | F63: =F61+F62 -> 6.3148843 | G63: =G61+G62 -> 6.3148843 | H63: =H61+H62 -> 33.119518 | I63: =I61+I62 -> 65.097357 | J63: =J61+J62 -> 97.583788 | K63: =K61+K62 -> 126.03046 | L63: =L61+L62 -> 152.06632 | M63: =M61+M62 -> 172.44749
A64: 其中：對外（→ Google Cloud） | B64: US$B | F64: =F63*ext_sh -> 1.8944653 | G64: =G63*ext_sh -> 1.8944653 | H64: =H63*ext_sh -> 9.9358555 | I64: =I63*ext_sh -> 19.529207 | J64: =J63*ext_sh -> 29.275136 | K64: =K63*ext_sh -> 37.809137 | L64: =L63*ext_sh -> 45.619896 | M64: =M63*ext_sh -> 51.734247 | N64: 按對外比例分攤（在建工程同）
A65: 其中：自用（→ Google Services／Alphabet 層級） | B65: US$B | F65: =F63*(1-ext_sh) -> 4.420419 | G65: =G63*(1-ext_sh) -> 4.420419 | H65: =H63*(1-ext_sh) -> 23.183663 | I65: =I63*(1-ext_sh) -> 45.56815 | J65: =J63*(1-ext_sh) -> 68.308651 | K65: =K63*(1-ext_sh) -> 88.22132 | L65: =L63*(1-ext_sh) -> 106.44642 | M65: =M63*(1-ext_sh) -> 120.71324
A67: F. 自用 AI 增量成本（相對評價日機隊；評價日機隊的成本已在近四季分部利益率內）
A68: 自用 AI 增量營運費用（Tokenomics IF_OpexGW；相對評價日機隊） | B68: US$B | F68: =(1-ext_sh)*((F30*opx_h+F31*opx_b2+F32*opx_b3+F33*opx_vr)-($E$24*opx_h+$E$25*opx_b2+$E$26*opx_b3+$E$27*opx_vr))/1000*0.25 -> 0.27012222 | G68: =F68 -> 0.27012222 | H68: =(1-ext_sh)*((H30*opx_h+H31*opx_b2+H32*opx_b3+H33*opx_vr)-($E$24*opx_h+$E$25*opx_b2+$E$26*opx_b3+$E$27*opx_vr))/1000*1 -> 6.6037662 | I68: =(1-ext_sh)*((I30*opx_h+I31*opx_b2+I32*opx_b3+I33*opx_vr)-($E$24*opx_h+$E$25*opx_b2+$E$26*opx_b3+$E$27*opx_vr))/1000*1 -> 15.610176 | J68: =(1-ext_sh)*((J30*opx_h+J31*opx_b2+J32*opx_b3+J33*opx_vr)-($E$24*opx_h+$E$25*opx_b2+$E$26*opx_b3+$E$27*opx_vr))/1000*1 -> 23.716906 | K68: =(1-ext_sh)*((K30*opx_h+K31*opx_b2+K32*opx_b3+K33*opx_vr)-($E$24*opx_h+$E$25*opx_b2+$E$26*opx_b3+$E$27*opx_vr))/1000*1 -> 29.835757 | L68: =(1-ext_sh)*((L30*opx_h+L31*opx_b2+L32*opx_b3+L33*opx_vr)-($E$24*opx_h+$E$25*opx_b2+$E$26*opx_b3+$E$27*opx_vr))/1000*1 -> 34.051256 | M68: =(1-ext_sh)*((M30*opx_h+M31*opx_b2+M32*opx_b3+M33*opx_vr)-($E$24*opx_h+$E$25*opx_b2+$E$26*opx_b3+$E$27*opx_vr))/1000*1 -> 36.40534
A69: SpaceX 算力租金（自用，營運成本） | B69: US$B | F69: =rent_2H -> 2.76 | G69: =F69 -> 2.76 | H69: =rent_27 -> 11.04 | I69: =rent_28 -> 11.04 | J69: =rent_29 -> 5.52 | K69: 0 | L69: 0 | M69: 0
A70: 自用 AI 增量成本合計（營運＋租金＋自用折舊） | B70: US$B | F70: =F68+F69+F65 -> 7.4505412 | G70: =G68+G69+G65 -> 7.4505412 | H70: =H68+H69+H65 -> 40.827429 | I70: =I68+I69+I65 -> 72.218326 | J70: =J68+J69+J65 -> 97.545557 | K70: =K68+K69+K65 -> 118.05708 | L70: =L68+L69+L65 -> 140.49768 | M70: =M68+M69+M65 -> 157.11858
A71: 歸 Google Services（× svc_sh） | B71: US$B | F71: =F70*svc_sh -> 4.4703247 | G71: =G70*svc_sh -> 4.4703247 | H71: =H70*svc_sh -> 24.496457 | I71: =I70*svc_sh -> 43.330996 | J71: =J70*svc_sh -> 58.527334 | K71: =K70*svc_sh -> 70.834246 | L71: =L70*svc_sh -> 84.298608 | M71: =M70*svc_sh -> 94.271149
A72: 歸 Alphabet-level activities（× (1 − svc_sh)） | B72: US$B | F72: =F70*(1-svc_sh) -> 2.9802165 | G72: =G70*(1-svc_sh) -> 2.9802165 | H72: =H70*(1-svc_sh) -> 16.330972 | I72: =I70*(1-svc_sh) -> 28.88733 | J72: =J70*(1-svc_sh) -> 39.018223 | K72: =K70*(1-svc_sh) -> 47.222831 | L72: =L70*(1-svc_sh) -> 56.199072 | M72: =M70*(1-svc_sh) -> 62.847433
A74: G. 評價日在役資產的基礎折舊（隨期初機隊汰換遞減；修正一 F6）
A75: 累計已汰換的期初機隊 MW（當年以半年計） | B75: MW | F75: =mid*F48 -> 0 | G75: =F75 -> 0 | H75: =F48+mid*H48 -> 0 | I75: =F48+H48+mid*I48 -> 0 | J75: =F48+H48+I48+mid*J48 -> 318.35 | K75: =F48+H48+I48+J48+mid*K48 -> 1390 | L75: =F48+H48+I48+J48+K48+mid*L48 -> 3508.15 | M75: =F48+H48+I48+J48+K48+L48+mid*M48 -> 7162.075
A76: 期初機隊每 MW IT 年折舊（Tokenomics IF_DeprIT 依期初占比加權） | B76: US$m/MW-年 | E76: =mix0_h*dpi_h+mix0_b2*dpi_b2+mix0_b3*dpi_b3 -> 4.5592582
A77: 基礎折舊＝da_base − MIN(da_base × IT 占比, 累計汰換 MW × 每 MW IT 折舊) | B77: US$B | F77: =(da_base-MIN(da_base*cip_it,F75*$E$76/1000))*0.25 -> 7.104 | G77: =F77 -> 7.104 | H77: =(da_base-MIN(da_base*cip_it,H75*$E$76/1000))*1 -> 28.416 | I77: =(da_base-MIN(da_base*cip_it,I75*$E$76/1000))*1 -> 28.416 | J77: =(da_base-MIN(da_base*cip_it,J75*$E$76/1000))*1 -> 26.96456 | K77: =(da_base-MIN(da_base*cip_it,K75*$E$76/1000))*1 -> 22.078631 | L77: =(da_base-MIN(da_base*cip_it,L75*$E$76/1000))*1 -> 12.421438 | M77: =(da_base-MIN(da_base*cip_it,M75*$E$76/1000))*1 -> 9.9456 | N77: 期初機隊汰換後由新購 IT 折舊取代，避免重複計折舊；IT 占比沿用 cip_it（60%）
A79: H. 自用 AI 影子效益（讀法 2：自用增量 MW 以 k＝1 計，＝Tokenomics 持有成本；非財報營收）
A80: 自用 AI 影子效益（自用增量 MW × IF_HoldEcon × TPU 調整） | B80: US$B | F80: =(1-ext_sh)*tpu_adj*((F30*he_h+F31*he_b2+F32*he_b3+F33*he_vr)-($E$24*he_h+$E$25*he_b2+$E$26*he_b3+$E$27*he_vr))/1000*0.25 -> 1.1494869 | G80: =F80 -> 1.1494869 | H80: =(1-ext_sh)*tpu_adj*((H30*he_h+H31*he_b2+H32*he_b3+H33*he_vr)-($E$24*he_h+$E$25*he_b2+$E$26*he_b3+$E$27*he_vr))/1000*1 -> 28.718806 | I80: =(1-ext_sh)*tpu_adj*((I30*he_h+I31*he_b2+I32*he_b3+I33*he_vr)-($E$24*he_h+$E$25*he_b2+$E$26*he_b3+$E$27*he_vr))/1000*1 -> 68.895751 | J80: =(1-ext_sh)*tpu_adj*((J30*he_h+J31*he_b2+J32*he_b3+J33*he_vr)-($E$24*he_h+$E$25*he_b2+$E$26*he_b3+$E$27*he_vr))/1000*1 -> 105.58518 | K80: =(1-ext_sh)*tpu_adj*((K30*he_h+K31*he_b2+K32*he_b3+K33*he_vr)-($E$24*he_h+$E$25*he_b2+$E$26*he_b3+$E$27*he_vr))/1000*1 -> 133.27787 | L80: =(1-ext_sh)*tpu_adj*((L30*he_h+L31*he_b2+L32*he_b3+L33*he_vr)-($E$24*he_h+$E$25*he_b2+$E$26*he_b3+$E$27*he_vr))/1000*1 -> 152.35637 | M80: =(1-ext_sh)*tpu_adj*((M30*he_h+M31*he_b2+M32*he_b3+M33*he_vr)-($E$24*he_h+$E$25*he_b2+$E$26*he_b3+$E$27*he_vr))/1000*1 -> 163.01048 | N80: 修正一 F1：讀法 2 進評價口徑（PL 頁「營業利益（評價口徑）」、Val）；營收列與分部對帳不動
A81: 歸 Google Services（× svc_sh） | B81: US$B | F81: =F80*svc_sh -> 0.68969212 | G81: =G80*svc_sh -> 0.68969212 | H81: =H80*svc_sh -> 17.231284 | I81: =I80*svc_sh -> 41.337451 | J81: =J80*svc_sh -> 63.351109 | K81: =K80*svc_sh -> 79.966721 | L81: =L80*svc_sh -> 91.413822 | M81: =M80*svc_sh -> 97.80629
A82: 歸 Alphabet-level（× (1 − svc_sh)） | B82: US$B | F82: =F80*(1-svc_sh) -> 0.45979475 | G82: =G80*(1-svc_sh) -> 0.45979475 | H82: =H80*(1-svc_sh) -> 11.487523 | I82: =I80*(1-svc_sh) -> 27.5583 | J82: =J80*(1-svc_sh) -> 42.234072 | K82: =K80*(1-svc_sh) -> 53.311148 | L82: =L80*(1-svc_sh) -> 60.942548 | M82: =M80*(1-svc_sh) -> 65.204193
A83: 影子效益 ÷ 自用 AI 增量成本 | B83: x | F83: =F80/F70 -> 0.15428233 | H83: =H80/H70 -> 0.70341942 | I83: =I80/I70 -> 0.95399263 | J83: =J80/J70 -> 1.0824192 | K83: =K80/K70 -> 1.1289274 | L83: =L80/L70 -> 1.0844049 | M83: =M80/M70 -> 1.0374997 | N83: 接近 1＝價值中性（Tokenomics 持有成本以 10% 資金成本回收資本）

Sheet Seg
A1: Seg — 營收分部層：官方分部（Google Services、Google Cloud、Other Bets）＋Alphabet 層級避險；產品線為子列。情境差異只在 Google Search & other（A 擴大變現／B 近四季成長收斂／C 查詢分流、變現下降），其餘三情境相同
A2: 成長路徑：Q4 26 年增＝近四季年增（Q 頁，2025Q4–2026Q3），之後線性收斂到長期值（conv_n 年，FY2030 到達）。Search 情境：Search＝B 路徑 ×(1 − 分流) ×(1＋每次查詢變現變動)，分流與變現變動自 FY2026 的 0 線性到 FY2030 的 In 頁值。Cloud AI 由 Thesis 頁帶入
A4: 情境 A（AI 搜尋擴大變現）
A5: 項目 | B5: 單位 | C5: FY2024A | D5: FY2025A | E5: 9M26A | F5: Q4 26E | G5: FY2026E | H5: FY2027E | I5: FY2028E | J5: FY2029E | K5: FY2030E | L5: FY2031E | M5: FY2032E | N5: 說明
A6: Search B 路徑年增 | B6: % | F6: =g0_search -> 0.16056206 | H6: =g0_search+(gl_search-g0_search)*MIN(1,(2027-2026)/conv_n) -> 0.14042155 | I6: =g0_search+(gl_search-g0_search)*MIN(1,(2028-2026)/conv_n) -> 0.12028103 | J6: =g0_search+(gl_search-g0_search)*MIN(1,(2029-2026)/conv_n) -> 0.10014052 | K6: =g0_search+(gl_search-g0_search)*MIN(1,(2030-2026)/conv_n) -> 0.08 | L6: =g0_search+(gl_search-g0_search)*MIN(1,(2031-2026)/conv_n) -> 0.08 | M6: =g0_search+(gl_search-g0_search)*MIN(1,(2032-2026)/conv_n) -> 0.08 | N6: Q4 26 年增＝近四季年增（Q 頁），FY2030 收斂到 gl_search
A7: Google Search & other：B 路徑 | B7: US$B | C7: =Q!J5 -> 198.084 | D7: =Q!K5 -> 224.532 | E7: =Q!L5 -> 187.02 | F7: =Q!F5*(1+F6) -> 73.200131 | G7: =E7+F7 -> 260.22013 | H7: =G7*(1+H6) -> 296.76064 | I7: =H7*(1+I6) -> 332.45532 | J7: =I7*(1+J6) -> 365.74757 | K7: =J7*(1+K6) -> 395.00737 | L7: =K7*(1+L6) -> 426.60796 | M7: =L7*(1+M6) -> 460.7366
A8: 情境爬坡（FY2026 0 → FY2030 1） | B8: x | F8: 0 | H8: =MIN(1,(2027-2026)/conv_n) -> 0.25 | I8: =MIN(1,(2028-2026)/conv_n) -> 0.5 | J8: =MIN(1,(2029-2026)/conv_n) -> 0.75 | K8: =MIN(1,(2030-2026)/conv_n) -> 1 | L8: =MIN(1,(2031-2026)/conv_n) -> 1 | M8: =MIN(1,(2032-2026)/conv_n) -> 1
A9: 查詢分流（相對 B 路徑） | B9: % | F9: =dA*F8 -> 0 | H9: =dA*H8 -> -0.0125 | I9: =dA*I8 -> -0.025 | J9: =dA*J8 -> -0.0375 | K9: =dA*K8 -> -0.05 | L9: =dA*L8 -> -0.05 | M9: =dA*M8 -> -0.05 | N9: In 頁 dA（負值＝AI 模式吸引查詢回流）
A10: 每次查詢變現變動（相對 B 路徑） | B10: % | F10: =mA*F8 -> 0 | H10: =mA*H8 -> 0.025 | I10: =mA*I8 -> 0.05 | J10: =mA*J8 -> 0.075 | K10: =mA*K8 -> 0.1 | L10: =mA*L8 -> 0.1 | M10: =mA*M8 -> 0.1
A11: Google Search & other | B11: US$B | C11: =C7 -> 198.084 | D11: =D7 -> 224.532 | E11: =E7 -> 187.02 | F11: =F7*(1-F9)*(1+F10) -> 73.200131 | G11: =E11+F11 -> 260.22013 | H11: =H7*(1-H9)*(1+H10) -> 307.98191 | I11: =I7*(1-I9)*(1+I10) -> 357.80504 | J11: =J7*(1-J9)*(1+J10) -> 407.92283 | K11: =K7*(1-K9)*(1+K10) -> 456.23351 | L11: =L7*(1-L9)*(1+L10) -> 492.7322 | M11: =M7*(1-M9)*(1+M10) -> 532.15077
A12: YouTube ads 年增 | B12: % | F12: =g0_yt -> 0.10317561 | H12: =g0_yt+(gl_yt-g0_yt)*MIN(1,(2027-2026)/conv_n) -> 0.097381707 | I12: =g0_yt+(gl_yt-g0_yt)*MIN(1,(2028-2026)/conv_n) -> 0.091587804 | J12: =g0_yt+(gl_yt-g0_yt)*MIN(1,(2029-2026)/conv_n) -> 0.085793902 | K12: =g0_yt+(gl_yt-g0_yt)*MIN(1,(2030-2026)/conv_n) -> 0.08 | L12: =g0_yt+(gl_yt-g0_yt)*MIN(1,(2031-2026)/conv_n) -> 0.08 | M12: =g0_yt+(gl_yt-g0_yt)*MIN(1,(2032-2026)/conv_n) -> 0.08 | N12: 三情境相同
A13: YouTube ads | B13: US$B | C13: =Q!J6 -> 36.147 | D13: =Q!K6 -> 40.367 | E13: =Q!L6 -> 32.145 | F13: =Q!F6*(1+F12) -> 12.557448 | G13: =E13+F13 -> 44.702448 | H13: =G13*(1+H12) -> 49.055649 | I13: =H13*(1+I12) -> 53.548548 | J13: =I13*(1+J12) -> 58.142687 | K13: =J13*(1+K12) -> 62.794102 | L13: =K13*(1+L12) -> 67.81763 | M13: =L13*(1+M12) -> 73.24304
A14: Google Network 年增 | B14: % | F14: =g0_net -> -0.012066315 | H14: =g0_net+(gl_net-g0_net)*MIN(1,(2027-2026)/conv_n) -> -0.0090497359 | I14: =g0_net+(gl_net-g0_net)*MIN(1,(2028-2026)/conv_n) -> -0.0060331573 | J14: =g0_net+(gl_net-g0_net)*MIN(1,(2029-2026)/conv_n) -> -0.0030165786 | K14: =g0_net+(gl_net-g0_net)*MIN(1,(2030-2026)/conv_n) -> 0 | L14: =g0_net+(gl_net-g0_net)*MIN(1,(2031-2026)/conv_n) -> 0 | M14: =g0_net+(gl_net-g0_net)*MIN(1,(2032-2026)/conv_n) -> 0 | N14: 三情境相同
A15: Google Network | B15: US$B | C15: =Q!J7 -> 30.359 | D15: =Q!K7 -> 29.792 | E15: =Q!L7 -> 21.729 | F15: =Q!F7*(1+F14) -> 7.7335449 | G15: =E15+F15 -> 29.462545 | H15: =G15*(1+H14) -> 29.195917 | I15: =H15*(1+I14) -> 29.019773 | J15: =I15*(1+J14) -> 28.932233 | K15: =J15*(1+K14) -> 28.932233 | L15: =K15*(1+L14) -> 28.932233 | M15: =L15*(1+M14) -> 28.932233
A16: Google subscriptions, platforms, and devices 年增 | B16: % | F16: =g0_subs -> 0.15358577 | H16: =g0_subs+(gl_subs-g0_subs)*MIN(1,(2027-2026)/conv_n) -> 0.14018932 | I16: =g0_subs+(gl_subs-g0_subs)*MIN(1,(2028-2026)/conv_n) -> 0.12679288 | J16: =g0_subs+(gl_subs-g0_subs)*MIN(1,(2029-2026)/conv_n) -> 0.11339644 | K16: =g0_subs+(gl_subs-g0_subs)*MIN(1,(2030-2026)/conv_n) -> 0.1 | L16: =g0_subs+(gl_subs-g0_subs)*MIN(1,(2031-2026)/conv_n) -> 0.1 | M16: =g0_subs+(gl_subs-g0_subs)*MIN(1,(2032-2026)/conv_n) -> 0.1 | N16: 三情境相同
A17: Google subscriptions, platforms, and devices | B17: US$B | C17: =Q!J8 -> 40.34 | D17: =Q!K8 -> 48.03 | E17: =Q!L8 -> 39.585 | F17: =Q!F8*(1+F16) -> 15.663388 | G17: =E17+F17 -> 55.248388 | H17: =G17*(1+H16) -> 62.993622 | I17: =H17*(1+I16) -> 70.980765 | J17: =I17*(1+J16) -> 79.029731 | K17: =J17*(1+K16) -> 86.932704 | L17: =K17*(1+L16) -> 95.625974 | M17: =L17*(1+M16) -> 105.18857
A18: Google Services | B18: US$B | C18: =Q!J9 -> 304.93 | D18: =Q!K9 -> 342.721 | E18: =Q!L9 -> 280.479 | F18: =F11+F13+F15+F17 -> 109.15451 | G18: =E18+F18 -> 389.63351 | H18: =H11+H13+H15+H17 -> 449.22709 | I18: =I11+I13+I15+I17 -> 511.35412 | J18: =J11+J13+J15+J17 -> 574.02748 | K18: =K11+K13+K15+K17 -> 634.89255 | L18: =L11+L13+L15+L17 -> 685.10803 | M18: =M11+M13+M15+M17 -> 739.51462
A19: Cloud AI（命題子列） | B19: US$B | E19: =Thesis!E38 -> 13.119056 | F19: =Thesis!F38 -> 6.050155 | G19: =Thesis!G38 -> 19.169211 | H19: =Thesis!H38 -> 36.615799 | I19: =Thesis!I38 -> 57.29516 | J19: =Thesis!J38 -> 76.179473 | K19: =Thesis!K38 -> 90.433098 | L19: =Thesis!L38 -> 100.25294 | M19: =Thesis!M38 -> 105.73669 | N19: Thesis 頁：對外 MW × 每 MW 收入（9M26 為模型估計）
A20: TPU 系統銷售（命題子列） | B20: US$B | E20: 0 | F20: =tpu_2h -> 1 | G20: =E20+F20 -> 1 | H20: =tpu_yr -> 13 | I20: =tpu_yr -> 13 | J20: =tpu_yr -> 13 | K20: =tpu_yr -> 13 | L20: =tpu_yr -> 13 | M20: =tpu_yr -> 13 | N20: C8 b：不走 MW × 每 MW；9M26 已認列但金額未揭露 → 0（含在 Cloud 其他）
A21: Cloud 其他年增 | B21: % | F21: =g0_co -> 0.71107868 | H21: =g0_co+(gl_co-g0_co)*MIN(1,(2027-2026)/conv_n) -> 0.55330901 | I21: =g0_co+(gl_co-g0_co)*MIN(1,(2028-2026)/conv_n) -> 0.39553934 | J21: =g0_co+(gl_co-g0_co)*MIN(1,(2029-2026)/conv_n) -> 0.23776967 | K21: =g0_co+(gl_co-g0_co)*MIN(1,(2030-2026)/conv_n) -> 0.08 | L21: =g0_co+(gl_co-g0_co)*MIN(1,(2031-2026)/conv_n) -> 0.08 | M21: =g0_co+(gl_co-g0_co)*MIN(1,(2032-2026)/conv_n) -> 0.08 | N21: 起始＝Cloud 其他近四季年增（Thesis 頁 g0_co），FY2030 收斂到 gl_co
A22: Cloud 其他（命題子列） | B22: US$B | E22: =Q!L11-E19-E20 -> 62.385944 | F22: =E22*q3sh_cloud*(1+F21)^0.25 -> 29.019786 | G22: =E22+F22 -> 91.40573 | H22: =G22*(1+H21) -> 141.98134 | I22: =H22*(1+I21) -> 198.14055 | J22: =I22*(1+J21) -> 245.25236 | K22: =J22*(1+K21) -> 264.87255 | L22: =K22*(1+L21) -> 286.06236 | M22: =L22*(1+M21) -> 308.94735 | N22: 9M26＝Google Cloud 實績 − Cloud AI 估計 − TPU；Q4 26＝9M26 × Q3 占 9M 比例（Q 頁 q3sh_cloud）×(1＋年增)^0.25
A23: Google Cloud | B23: US$B | C23: =Q!J11 -> 43.229 | D23: =Q!K11 -> 58.705 | E23: =Q!L11 -> 75.505 | F23: =F19+F20+F22 -> 36.069941 | G23: =E23+F23 -> 111.57494 | H23: =H19+H20+H22 -> 191.59714 | I23: =I19+I20+I22 -> 268.43571 | J23: =J19+J20+J22 -> 334.43184 | K23: =K19+K20+K22 -> 368.30565 | L23: =L19+L20+L22 -> 399.3153 | M23: =M19+M20+M22 -> 427.68403
A24: Other Bets | B24: US$B | C24: =Q!J12 -> 1.648 | D24: =Q!K12 -> 1.537 | E24: =Q!L12 -> 1.165 | F24: =ob_rev_2H -> 0.38 | G24: =E24+F24 -> 1.545 | H24: =ob_rev_27 -> 1.6 | I24: =ob_rev_28 -> 1.8 | J24: =ob_rev_29 -> 2 | K24: =ob_rev_30 -> 2.2 | L24: =ob_rev_31 -> 2.4 | M24: =ob_rev_32 -> 2.6
A25: Hedging gains (losses) | B25: US$B | C25: =Q!J13 -> 0.211 | D25: =Q!K13 -> -0.127 | E25: =Q!L13 -> 0.12 | F25: 0 | G25: =E25+F25 -> 0.12 | H25: 0 | I25: 0 | J25: 0 | K25: 0 | L25: 0 | M25: 0 | N25: Alphabet-level activities；預測期 0 [Assumed]
A26: 合併營收 | B26: US$B | C26: =Q!J14 -> 350.018 | D26: =Q!K14 -> 402.836 | E26: =Q!L14 -> 357.269 | F26: =F18+F23+F24+F25 -> 145.60445 | G26: =E26+F26 -> 502.87345 | H26: =H18+H23+H24+H25 -> 642.42424 | I26: =I18+I23+I24+I25 -> 781.58983 | J26: =J18+J23+J24+J25 -> 910.45932 | K26: =K18+K23+K24+K25 -> 1005.3982 | L26: =L18+L23+L24+L25 -> 1086.8233 | M26: =M18+M23+M24+M25 -> 1169.7986
A27: 檢查：產品線合計 − Google Services | B27: US$B | C27: =C11+C13+C15+C17-C18 -> 0 | D27: =D11+D13+D15+D17-D18 -> 0 | E27: =E11+E13+E15+E17-E18 -> 0 | F27: =F11+F13+F15+F17-F18 -> 0 | G27: =G11+G13+G15+G17-G18 -> 0 | H27: =H11+H13+H15+H17-H18 -> 0 | I27: =I11+I13+I15+I17-I18 -> 0 | J27: =J11+J13+J15+J17-J18 -> 0 | ... M27: =M11+M13+M15+M17-M18 -> 0
A28: 檢查：Cloud 子列合計 − Google Cloud | B28: US$B | E28: =E19+E20+E22-E23 -> 0 | F28: =F19+F20+F22-F23 -> 0 | G28: =G19+G20+G22-G23 -> 0 | H28: =H19+H20+H22-H23 -> 0 | I28: =I19+I20+I22-I23 -> 0 | J28: =J19+J20+J22-J23 -> 0 | K28: =K19+K20+K22-K23 -> 0 | L28: =L19+L20+L22-L23 -> 0 | M28: =M19+M20+M22-M23 -> 0
A29: 檢查：分部合計＋避險 − 合併營收 | B29: US$B | C29: =C18+C23+C24+C25-C26 -> 0 | D29: =D18+D23+D24+D25-D26 -> 0 | E29: =E18+E23+E24+E25-E26 -> 0 | F29: =F18+F23+F24+F25-F26 -> 0 | G29: =G18+G23+G24+G25-G26 -> 0 | H29: =H18+H23+H24+H25-H26 -> 0 | I29: =I18+I23+I24+I25-I26 -> 0 | J29: =J18+J23+J24+J25-J26 -> 0 | ... M29: =M18+M23+M24+M25-M26 -> 0
A30: 檢查：實績欄合併營收 − Q 頁（FY2024、FY2025、9M26） | B30: US$B | C30: =C26-Q!J14 -> 0 | D30: =D26-Q!K14 -> 0 | E30: =E26-Q!L14 -> 0
A31: 非 AI 資本支出：Google Services（營收 × cx_svc） | B31: US$B | F31: =F18*cx_svc -> 6.5492707 | G31: =F31 -> 6.5492707 | H31: =H18*cx_svc -> 26.953626 | I31: =I18*cx_svc -> 30.681247 | J31: =J18*cx_svc -> 34.441649 | K31: =K18*cx_svc -> 38.093553 | L31: =L18*cx_svc -> 41.106482 | M31: =M18*cx_svc -> 44.370877
A32: 非 AI 資本支出：Cloud 其他（營收 × cx_co） | B32: US$B | F32: =F22*cx_co -> 5.8039572 | G32: =F32 -> 5.8039572 | H32: =H22*cx_co -> 28.396269 | I32: =I22*cx_co -> 39.62811 | J32: =J22*cx_co -> 49.050473 | K32: =K22*cx_co -> 52.974511 | L32: =L22*cx_co -> 57.212472 | M32: =M22*cx_co -> 61.789469
A33: 非 AI 資本支出：Other Bets（營收 × cx_ob） | B33: US$B | F33: =F24*cx_ob -> 0.0228 | G33: =F33 -> 0.0228 | H33: =H24*cx_ob -> 0.096 | I33: =I24*cx_ob -> 0.108 | J33: =J24*cx_ob -> 0.12 | K33: =K24*cx_ob -> 0.132 | L33: =L24*cx_ob -> 0.144 | M33: =M24*cx_ob -> 0.156
A34: 非 AI 資本支出合計 | B34: US$B | F34: =F31+F32+F33 -> 12.376028 | G34: =G31+G32+G33 -> 12.376028 | H34: =H31+H32+H33 -> 55.445894 | I34: =I31+I32+I33 -> 70.417358 | J34: =J31+J32+J33 -> 83.612122 | K34: =K31+K32+K33 -> 91.200064 | L34: =L31+L32+L33 -> 98.462953 | M34: =M31+M32+M33 -> 106.31635
A35: 新增非 AI 折舊：Google Services（年限 life_na） | B35: US$B | F35: =$F$31/life_na*IF((0)<0,0,IF((0)=0,phi_0,IF((0)<life_na,1,IF((0)=life_na,1-phi_0,0)))) -> 0.16373177 | G35: =F35 -> 0.16373177 | H35: =$F$31/life_na*IF((1)<0,0,IF((1)=0,phi_0,IF((1)<life_na,1,IF((1)=life_na,1-phi_0,0))))+$H$31/life_na*IF((0)<0,0,IF((0)=0,phi_0,IF((0)<life_na,1,IF((0)=life_na,1-phi_0,0)))) -> 1.3287677 | I35: =$F$31/life_na*IF((2)<0,0,IF((2)=0,phi_0,IF((2)<life_na,1,IF((2)=life_na,1-phi_0,0))))+$H$31/life_na*IF((1)<0,0,IF((1)=0,phi_0,IF((1)<life_na,1,IF((1)=life_na,1-phi_0,0))))+$I$31/life_na*IF((0)<0,0,IF((0)=0,phi_0,IF((0)<life_na,1,IF((0)=life_na,1-phi_0,0)))) -> 4.1173208 | J35: =$F$31/life_na*IF((3)<0,0,IF((3)=0,phi_0,IF((3)<life_na,1,IF((3)=life_na,1-phi_0,0))))+$H$31/life_na*IF((2)<0,0,IF((2)=0,phi_0,IF((2)<life_na,1,IF((2)=life_na,1-phi_0,0))))+$I$31/life_na*IF((1)<0,0,IF((1)=0,phi_0,IF((1)<life_na,1,IF((1)=life_na,1-phi_0,0))))+$J$31/life_na*IF((0)<0,0,IF((0)=0,phi_0,IF((0)<life_na,1,IF((0)=life_na,1-phi_0,0)))) -> 7.2794556 | K35: =$F$31/life_na*IF((4)<0,0,IF((4)=0,phi_0,IF((4)<life_na,1,IF((4)=life_na,1-phi_0,0))))+$H$31/life_na*IF((3)<0,0,IF((3)=0,phi_0,IF((3)<life_na,1,IF((3)=life_na,1-phi_0,0))))+$I$31/life_na*IF((2)<0,0,IF((2)=0,phi_0,IF((2)<life_na,1,IF((2)=life_na,1-phi_0,0))))+$J$31/life_na*IF((1)<0,0,IF((1)=0,phi_0,IF((1)<life_na,1,IF((1)=life_na,1-phi_0,0))))+$K$31/life_na*IF((0)<0,0,IF((0)=0,phi_0,IF((0)<life_na,1,IF((0)=life_na,1-phi_0,0)))) -> 10.814918 | L35: =$F$31/life_na*IF((5)<0,0,IF((5)=0,phi_0,IF((5)<life_na,1,IF((5)=life_na,1-phi_0,0))))+$H$31/life_na*IF((4)<0,0,IF((4)=0,phi_0,IF((4)<life_na,1,IF((4)=life_na,1-phi_0,0))))+$I$31/life_na*IF((3)<0,0,IF((3)=0,phi_0,IF((3)<life_na,1,IF((3)=life_na,1-phi_0,0))))+$J$31/life_na*IF((2)<0,0,IF((2)=0,phi_0,IF((2)<life_na,1,IF((2)=life_na,1-phi_0,0))))+$K$31/life_na*IF((1)<0,0,IF((1)=0,phi_0,IF((1)<life_na,1,IF((1)=life_na,1-phi_0,0))))+$L$31/life_na*IF((0)<0,0,IF((0)=0,phi_0,IF((0)<life_na,1,IF((0)=life_na,1-phi_0,0)))) -> 14.699597 | M35: =$F$31/life_na*IF((6)<0,0,IF((6)=0,phi_0,IF((6)<life_na,1,IF((6)=life_na,1-phi_0,0))))+$H$31/life_na*IF((5)<0,0,IF((5)=0,phi_0,IF((5)<life_na,1,IF((5)=life_na,1-phi_0,0))))+$I$31/life_na*IF((4)<0,0,IF((4)=0,phi_0,IF((4)<life_na,1,IF((4)=life_na,1-phi_0,0))))+$J$31/life_na*IF((3)<0,0,IF((3)=0,phi_0,IF((3)<life_na,1,IF((3)=life_na,1-phi_0,0))))+$K$31/life_na*IF((2)<0,0,IF((2)=0,phi_0,IF((2)<life_na,1,IF((2)=life_na,1-phi_0,0))))+$L$31/life_na*IF((1)<0,0,IF((1)=0,phi_0,IF((1)<life_na,1,IF((1)=life_na,1-phi_0,0))))+$M$31/life_na*IF((0)<0,0,IF((0)=0,phi_0,IF((0)<life_na,1,IF((0)=life_na,1-phi_0,0)))) -> 18.891855
A36: 新增非 AI 折舊：Cloud 其他（年限 life_na） | B36: US$B | F36: =$F$32/life_na*IF((0)<0,0,IF((0)=0,phi_0,IF((0)<life_na,1,IF((0)=life_na,1-phi_0,0)))) -> 0.14509893 | G36: =F36 -> 0.14509893 | H36: =$F$32/life_na*IF((1)<0,0,IF((1)=0,phi_0,IF((1)<life_na,1,IF((1)=life_na,1-phi_0,0))))+$H$32/life_na*IF((0)<0,0,IF((0)=0,phi_0,IF((0)<life_na,1,IF((0)=life_na,1-phi_0,0)))) -> 1.2903024 | I36: =$F$32/life_na*IF((2)<0,0,IF((2)=0,phi_0,IF((2)<life_na,1,IF((2)=life_na,1-phi_0,0))))+$H$32/life_na*IF((1)<0,0,IF((1)=0,phi_0,IF((1)<life_na,1,IF((1)=life_na,1-phi_0,0))))+$I$32/life_na*IF((0)<0,0,IF((0)=0,phi_0,IF((0)<life_na,1,IF((0)=life_na,1-phi_0,0)))) -> 4.4107254 | J36: =$F$32/life_na*IF((3)<0,0,IF((3)=0,phi_0,IF((3)<life_na,1,IF((3)=life_na,1-phi_0,0))))+$H$32/life_na*IF((2)<0,0,IF((2)=0,phi_0,IF((2)<life_na,1,IF((2)=life_na,1-phi_0,0))))+$I$32/life_na*IF((1)<0,0,IF((1)=0,phi_0,IF((1)<life_na,1,IF((1)=life_na,1-phi_0,0))))+$J$32/life_na*IF((0)<0,0,IF((0)=0,phi_0,IF((0)<life_na,1,IF((0)=life_na,1-phi_0,0)))) -> 8.6090955 | K36: =$F$32/life_na*IF((4)<0,0,IF((4)=0,phi_0,IF((4)<life_na,1,IF((4)=life_na,1-phi_0,0))))+$H$32/life_na*IF((3)<0,0,IF((3)=0,phi_0,IF((3)<life_na,1,IF((3)=life_na,1-phi_0,0))))+$I$32/life_na*IF((2)<0,0,IF((2)=0,phi_0,IF((2)<life_na,1,IF((2)=life_na,1-phi_0,0))))+$J$32/life_na*IF((1)<0,0,IF((1)=0,phi_0,IF((1)<life_na,1,IF((1)=life_na,1-phi_0,0))))+$K$32/life_na*IF((0)<0,0,IF((0)=0,phi_0,IF((0)<life_na,1,IF((0)=life_na,1-phi_0,0)))) -> 13.612244 | L36: =$F$32/life_na*IF((5)<0,0,IF((5)=0,phi_0,IF((5)<life_na,1,IF((5)=life_na,1-phi_0,0))))+$H$32/life_na*IF((4)<0,0,IF((4)=0,phi_0,IF((4)<life_na,1,IF((4)=life_na,1-phi_0,0))))+$I$32/life_na*IF((3)<0,0,IF((3)=0,phi_0,IF((3)<life_na,1,IF((3)=life_na,1-phi_0,0))))+$J$32/life_na*IF((2)<0,0,IF((2)=0,phi_0,IF((2)<life_na,1,IF((2)=life_na,1-phi_0,0))))+$K$32/life_na*IF((1)<0,0,IF((1)=0,phi_0,IF((1)<life_na,1,IF((1)=life_na,1-phi_0,0))))+$L$32/life_na*IF((0)<0,0,IF((0)=0,phi_0,IF((0)<life_na,1,IF((0)=life_na,1-phi_0,0)))) -> 19.015644 | M36: =$F$32/life_na*IF((6)<0,0,IF((6)=0,phi_0,IF((6)<life_na,1,IF((6)=life_na,1-phi_0,0))))+$H$32/life_na*IF((5)<0,0,IF((5)=0,phi_0,IF((5)<life_na,1,IF((5)=life_na,1-phi_0,0))))+$I$32/life_na*IF((4)<0,0,IF((4)=0,phi_0,IF((4)<life_na,1,IF((4)=life_na,1-phi_0,0))))+$J$32/life_na*IF((3)<0,0,IF((3)=0,phi_0,IF((3)<life_na,1,IF((3)=life_na,1-phi_0,0))))+$K$32/life_na*IF((2)<0,0,IF((2)=0,phi_0,IF((2)<life_na,1,IF((2)=life_na,1-phi_0,0))))+$L$32/life_na*IF((1)<0,0,IF((1)=0,phi_0,IF((1)<life_na,1,IF((1)=life_na,1-phi_0,0))))+$M$32/life_na*IF((0)<0,0,IF((0)=0,phi_0,IF((0)<life_na,1,IF((0)=life_na,1-phi_0,0)))) -> 24.851316
A37: 新增非 AI 折舊：Other Bets（年限 life_na） | B37: US$B | F37: =$F$33/life_na*IF((0)<0,0,IF((0)=0,phi_0,IF((0)<life_na,1,IF((0)=life_na,1-phi_0,0)))) -> 0.00057 | G37: =F37 -> 0.00057 | H37: =$F$33/life_na*IF((1)<0,0,IF((1)=0,phi_0,IF((1)<life_na,1,IF((1)=life_na,1-phi_0,0))))+$H$33/life_na*IF((0)<0,0,IF((0)=0,phi_0,IF((0)<life_na,1,IF((0)=life_na,1-phi_0,0)))) -> 0.00468 | I37: =$F$33/life_na*IF((2)<0,0,IF((2)=0,phi_0,IF((2)<life_na,1,IF((2)=life_na,1-phi_0,0))))+$H$33/life_na*IF((1)<0,0,IF((1)=0,phi_0,IF((1)<life_na,1,IF((1)=life_na,1-phi_0,0))))+$I$33/life_na*IF((0)<0,0,IF((0)=0,phi_0,IF((0)<life_na,1,IF((0)=life_na,1-phi_0,0)))) -> 0.01458 | J37: =$F$33/life_na*IF((3)<0,0,IF((3)=0,phi_0,IF((3)<life_na,1,IF((3)=life_na,1-phi_0,0))))+$H$33/life_na*IF((2)<0,0,IF((2)=0,phi_0,IF((2)<life_na,1,IF((2)=life_na,1-phi_0,0))))+$I$33/life_na*IF((1)<0,0,IF((1)=0,phi_0,IF((1)<life_na,1,IF((1)=life_na,1-phi_0,0))))+$J$33/life_na*IF((0)<0,0,IF((0)=0,phi_0,IF((0)<life_na,1,IF((0)=life_na,1-phi_0,0)))) -> 0.02568 | K37: =$F$33/life_na*IF((4)<0,0,IF((4)=0,phi_0,IF((4)<life_na,1,IF((4)=life_na,1-phi_0,0))))+$H$33/life_na*IF((3)<0,0,IF((3)=0,phi_0,IF((3)<life_na,1,IF((3)=life_na,1-phi_0,0))))+$I$33/life_na*IF((2)<0,0,IF((2)=0,phi_0,IF((2)<life_na,1,IF((2)=life_na,1-phi_0,0))))+$J$33/life_na*IF((1)<0,0,IF((1)=0,phi_0,IF((1)<life_na,1,IF((1)=life_na,1-phi_0,0))))+$K$33/life_na*IF((0)<0,0,IF((0)=0,phi_0,IF((0)<life_na,1,IF((0)=life_na,1-phi_0,0)))) -> 0.03798 | L37: =$F$33/life_na*IF((5)<0,0,IF((5)=0,phi_0,IF((5)<life_na,1,IF((5)=life_na,1-phi_0,0))))+$H$33/life_na*IF((4)<0,0,IF((4)=0,phi_0,IF((4)<life_na,1,IF((4)=life_na,1-phi_0,0))))+$I$33/life_na*IF((3)<0,0,IF((3)=0,phi_0,IF((3)<life_na,1,IF((3)=life_na,1-phi_0,0))))+$J$33/life_na*IF((2)<0,0,IF((2)=0,phi_0,IF((2)<life_na,1,IF((2)=life_na,1-phi_0,0))))+$K$33/life_na*IF((1)<0,0,IF((1)=0,phi_0,IF((1)<life_na,1,IF((1)=life_na,1-phi_0,0))))+$L$33/life_na*IF((0)<0,0,IF((0)=0,phi_0,IF((0)<life_na,1,IF((0)=life_na,1-phi_0,0)))) -> 0.05148 | M37: =$F$33/life_na*IF((6)<0,0,IF((6)=0,phi_0,IF((6)<life_na,1,IF((6)=life_na,1-phi_0,0))))+$H$33/life_na*IF((5)<0,0,IF((5)=0,phi_0,IF((5)<life_na,1,IF((5)=life_na,1-phi_0,0))))+$I$33/life_na*IF((4)<0,0,IF((4)=0,phi_0,IF((4)<life_na,1,IF((4)=life_na,1-phi_0,0))))+$J$33/life_na*IF((3)<0,0,IF((3)=0,phi_0,IF((3)<life_na,1,IF((3)=life_na,1-phi_0,0))))+$K$33/life_na*IF((2)<0,0,IF((2)=0,phi_0,IF((2)<life_na,1,IF((2)=life_na,1-phi_0,0))))+$L$33/life_na*IF((1)<0,0,IF((1)=0,phi_0,IF((1)<life_na,1,IF((1)=life_na,1-phi_0,0))))+$M$33/life_na*IF((0)<0,0,IF((0)=0,phi_0,IF((0)<life_na,1,IF((0)=life_na,1-phi_0,0)))) -> 0.06618
A38: 新增非 AI 折舊合計 | B38: US$B | F38: =F35+F36+F37 -> 0.3094007 | G38: =G35+G36+G37 -> 0.3094007 | H38: =H35+H36+H37 -> 2.6237502 | I38: =I35+I36+I37 -> 8.5426262 | J38: =J35+J36+J37 -> 15.914231 | K38: =K35+K36+K37 -> 24.465142 | L38: =L35+L36+L37 -> 33.76672 | M38: =M35+M36+M37 -> 43.809351
A40: 情境 B（近四季成長收斂；基準）
A41: 項目 | B41: 單位 | C41: FY2024A | D41: FY2025A | E41: 9M26A | F41: Q4 26E | G41: FY2026E | H41: FY2027E | I41: FY2028E | J41: FY2029E | K41: FY2030E | L41: FY2031E | M41: FY2032E | N41: 說明
A42: Search B 路徑年增 | B42: % | F42: =g0_search -> 0.16056206 | H42: =g0_search+(gl_search-g0_search)*MIN(1,(2027-2026)/conv_n) -> 0.14042155 | I42: =g0_search+(gl_search-g0_search)*MIN(1,(2028-2026)/conv_n) -> 0.12028103 | J42: =g0_search+(gl_search-g0_search)*MIN(1,(2029-2026)/conv_n) -> 0.10014052 | K42: =g0_search+(gl_search-g0_search)*MIN(1,(2030-2026)/conv_n) -> 0.08 | L42: =g0_search+(gl_search-g0_search)*MIN(1,(2031-2026)/conv_n) -> 0.08 | M42: =g0_search+(gl_search-g0_search)*MIN(1,(2032-2026)/conv_n) -> 0.08 | N42: Q4 26 年增＝近四季年增（Q 頁），FY2030 收斂到 gl_search
A43: Google Search & other：B 路徑 | B43: US$B | C43: =Q!J5 -> 198.084 | D43: =Q!K5 -> 224.532 | E43: =Q!L5 -> 187.02 | F43: =Q!F5*(1+F42) -> 73.200131 | G43: =E43+F43 -> 260.22013 | H43: =G43*(1+H42) -> 296.76064 | I43: =H43*(1+I42) -> 332.45532 | J43: =I43*(1+J42) -> 365.74757 | K43: =J43*(1+K42) -> 395.00737 | L43: =K43*(1+L42) -> 426.60796 | M43: =L43*(1+M42) -> 460.7366
A44: 情境爬坡（FY2026 0 → FY2030 1） | B44: x | F44: 0 | H44: =MIN(1,(2027-2026)/conv_n) -> 0.25 | I44: =MIN(1,(2028-2026)/conv_n) -> 0.5 | J44: =MIN(1,(2029-2026)/conv_n) -> 0.75 | K44: =MIN(1,(2030-2026)/conv_n) -> 1 | L44: =MIN(1,(2031-2026)/conv_n) -> 1 | M44: =MIN(1,(2032-2026)/conv_n) -> 1
A45: 查詢分流（相對 B 路徑） | B45: % | F45: =0*F44 -> 0 | H45: =0*H44 -> 0 | I45: =0*I44 -> 0 | J45: =0*J44 -> 0 | K45: =0*K44 -> 0 | L45: =0*L44 -> 0 | M45: =0*M44 -> 0 | N45: 基準不設分流
A46: 每次查詢變現變動（相對 B 路徑） | B46: % | F46: =0*F44 -> 0 | H46: =0*H44 -> 0 | I46: =0*I44 -> 0 | J46: =0*J44 -> 0 | K46: =0*K44 -> 0 | L46: =0*L44 -> 0 | M46: =0*M44 -> 0
A47: Google Search & other | B47: US$B | C47: =C43 -> 198.084 | D47: =D43 -> 224.532 | E47: =E43 -> 187.02 | F47: =F43*(1-F45)*(1+F46) -> 73.200131 | G47: =E47+F47 -> 260.22013 | H47: =H43*(1-H45)*(1+H46) -> 296.76064 | I47: =I43*(1-I45)*(1+I46) -> 332.45532 | J47: =J43*(1-J45)*(1+J46) -> 365.74757 | K47: =K43*(1-K45)*(1+K46) -> 395.00737 | L47: =L43*(1-L45)*(1+L46) -> 426.60796 | M47: =M43*(1-M45)*(1+M46) -> 460.7366
A48: YouTube ads 年增 | B48: % | F48: =g0_yt -> 0.10317561 | H48: =g0_yt+(gl_yt-g0_yt)*MIN(1,(2027-2026)/conv_n) -> 0.097381707 | I48: =g0_yt+(gl_yt-g0_yt)*MIN(1,(2028-2026)/conv_n) -> 0.091587804 | J48: =g0_yt+(gl_yt-g0_yt)*MIN(1,(2029-2026)/conv_n) -> 0.085793902 | K48: =g0_yt+(gl_yt-g0_yt)*MIN(1,(2030-2026)/conv_n) -> 0.08 | L48: =g0_yt+(gl_yt-g0_yt)*MIN(1,(2031-2026)/conv_n) -> 0.08 | M48: =g0_yt+(gl_yt-g0_yt)*MIN(1,(2032-2026)/conv_n) -> 0.08 | N48: 三情境相同
A49: YouTube ads | B49: US$B | C49: =Q!J6 -> 36.147 | D49: =Q!K6 -> 40.367 | E49: =Q!L6 -> 32.145 | F49: =Q!F6*(1+F48) -> 12.557448 | G49: =E49+F49 -> 44.702448 | H49: =G49*(1+H48) -> 49.055649 | I49: =H49*(1+I48) -> 53.548548 | J49: =I49*(1+J48) -> 58.142687 | K49: =J49*(1+K48) -> 62.794102 | L49: =K49*(1+L48) -> 67.81763 | M49: =L49*(1+M48) -> 73.24304
A50: Google Network 年增 | B50: % | F50: =g0_net -> -0.012066315 | H50: =g0_net+(gl_net-g0_net)*MIN(1,(2027-2026)/conv_n) -> -0.0090497359 | I50: =g0_net+(gl_net-g0_net)*MIN(1,(2028-2026)/conv_n) -> -0.0060331573 | J50: =g0_net+(gl_net-g0_net)*MIN(1,(2029-2026)/conv_n) -> -0.0030165786 | K50: =g0_net+(gl_net-g0_net)*MIN(1,(2030-2026)/conv_n) -> 0 | L50: =g0_net+(gl_net-g0_net)*MIN(1,(2031-2026)/conv_n) -> 0 | M50: =g0_net+(gl_net-g0_net)*MIN(1,(2032-2026)/conv_n) -> 0 | N50: 三情境相同
A51: Google Network | B51: US$B | C51: =Q!J7 -> 30.359 | D51: =Q!K7 -> 29.792 | E51: =Q!L7 -> 21.729 | F51: =Q!F7*(1+F50) -> 7.7335449 | G51: =E51+F51 -> 29.462545 | H51: =G51*(1+H50) -> 29.195917 | I51: =H51*(1+I50) -> 29.019773 | J51: =I51*(1+J50) -> 28.932233 | K51: =J51*(1+K50) -> 28.932233 | L51: =K51*(1+L50) -> 28.932233 | M51: =L51*(1+M50) -> 28.932233
A52: Google subscriptions, platforms, and devices 年增 | B52: % | F52: =g0_subs -> 0.15358577 | H52: =g0_subs+(gl_subs-g0_subs)*MIN(1,(2027-2026)/conv_n) -> 0.14018932 | I52: =g0_subs+(gl_subs-g0_subs)*MIN(1,(2028-2026)/conv_n) -> 0.12679288 | J52: =g0_subs+(gl_subs-g0_subs)*MIN(1,(2029-2026)/conv_n) -> 0.11339644 | K52: =g0_subs+(gl_subs-g0_subs)*MIN(1,(2030-2026)/conv_n) -> 0.1 | L52: =g0_subs+(gl_subs-g0_subs)*MIN(1,(2031-2026)/conv_n) -> 0.1 | M52: =g0_subs+(gl_subs-g0_subs)*MIN(1,(2032-2026)/conv_n) -> 0.1 | N52: 三情境相同
A53: Google subscriptions, platforms, and devices | B53: US$B | C53: =Q!J8 -> 40.34 | D53: =Q!K8 -> 48.03 | E53: =Q!L8 -> 39.585 | F53: =Q!F8*(1+F52) -> 15.663388 | G53: =E53+F53 -> 55.248388 | H53: =G53*(1+H52) -> 62.993622 | I53: =H53*(1+I52) -> 70.980765 | J53: =I53*(1+J52) -> 79.029731 | K53: =J53*(1+K52) -> 86.932704 | L53: =K53*(1+L52) -> 95.625974 | M53: =L53*(1+M52) -> 105.18857
A54: Google Services | B54: US$B | C54: =Q!J9 -> 304.93 | D54: =Q!K9 -> 342.721 | E54: =Q!L9 -> 280.479 | F54: =F47+F49+F51+F53 -> 109.15451 | G54: =E54+F54 -> 389.63351 | H54: =H47+H49+H51+H53 -> 438.00583 | I54: =I47+I49+I51+I53 -> 486.0044 | J54: =J47+J49+J51+J53 -> 531.85222 | K54: =K47+K49+K51+K53 -> 573.66641 | L54: =L47+L49+L51+L53 -> 618.9838 | M54: =M47+M49+M51+M53 -> 668.10044
A55: Cloud AI（命題子列） | B55: US$B | E55: =Thesis!E38 -> 13.119056 | F55: =Thesis!F38 -> 6.050155 | G55: =Thesis!G38 -> 19.169211 | H55: =Thesis!H38 -> 36.615799 | I55: =Thesis!I38 -> 57.29516 | J55: =Thesis!J38 -> 76.179473 | K55: =Thesis!K38 -> 90.433098 | L55: =Thesis!L38 -> 100.25294 | M55: =Thesis!M38 -> 105.73669 | N55: Thesis 頁：對外 MW × 每 MW 收入（9M26 為模型估計）
A56: TPU 系統銷售（命題子列） | B56: US$B | E56: 0 | F56: =tpu_2h -> 1 | G56: =E56+F56 -> 1 | H56: =tpu_yr -> 13 | I56: =tpu_yr -> 13 | J56: =tpu_yr -> 13 | K56: =tpu_yr -> 13 | L56: =tpu_yr -> 13 | M56: =tpu_yr -> 13 | N56: C8 b：不走 MW × 每 MW；9M26 已認列但金額未揭露 → 0（含在 Cloud 其他）
A57: Cloud 其他年增 | B57: % | F57: =g0_co -> 0.71107868 | H57: =g0_co+(gl_co-g0_co)*MIN(1,(2027-2026)/conv_n) -> 0.55330901 | I57: =g0_co+(gl_co-g0_co)*MIN(1,(2028-2026)/conv_n) -> 0.39553934 | J57: =g0_co+(gl_co-g0_co)*MIN(1,(2029-2026)/conv_n) -> 0.23776967 | K57: =g0_co+(gl_co-g0_co)*MIN(1,(2030-2026)/conv_n) -> 0.08 | L57: =g0_co+(gl_co-g0_co)*MIN(1,(2031-2026)/conv_n) -> 0.08 | M57: =g0_co+(gl_co-g0_co)*MIN(1,(2032-2026)/conv_n) -> 0.08 | N57: 起始＝Cloud 其他近四季年增（Thesis 頁 g0_co），FY2030 收斂到 gl_co
A58: Cloud 其他（命題子列） | B58: US$B | E58: =Q!L11-E55-E56 -> 62.385944 | F58: =E58*q3sh_cloud*(1+F57)^0.25 -> 29.019786 | G58: =E58+F58 -> 91.40573 | H58: =G58*(1+H57) -> 141.98134 | I58: =H58*(1+I57) -> 198.14055 | J58: =I58*(1+J57) -> 245.25236 | K58: =J58*(1+K57) -> 264.87255 | L58: =K58*(1+L57) -> 286.06236 | M58: =L58*(1+M57) -> 308.94735 | N58: 9M26＝Google Cloud 實績 − Cloud AI 估計 − TPU；Q4 26＝9M26 × Q3 占 9M 比例（Q 頁 q3sh_cloud）×(1＋年增)^0.25
A59: Google Cloud | B59: US$B | C59: =Q!J11 -> 43.229 | D59: =Q!K11 -> 58.705 | E59: =Q!L11 -> 75.505 | F59: =F55+F56+F58 -> 36.069941 | G59: =E59+F59 -> 111.57494 | H59: =H55+H56+H58 -> 191.59714 | I59: =I55+I56+I58 -> 268.43571 | J59: =J55+J56+J58 -> 334.43184 | K59: =K55+K56+K58 -> 368.30565 | L59: =L55+L56+L58 -> 399.3153 | M59: =M55+M56+M58 -> 427.68403
A60: Other Bets | B60: US$B | C60: =Q!J12 -> 1.648 | D60: =Q!K12 -> 1.537 | E60: =Q!L12 -> 1.165 | F60: =ob_rev_2H -> 0.38 | G60: =E60+F60 -> 1.545 | H60: =ob_rev_27 -> 1.6 | I60: =ob_rev_28 -> 1.8 | J60: =ob_rev_29 -> 2 | K60: =ob_rev_30 -> 2.2 | L60: =ob_rev_31 -> 2.4 | M60: =ob_rev_32 -> 2.6
A61: Hedging gains (losses) | B61: US$B | C61: =Q!J13 -> 0.211 | D61: =Q!K13 -> -0.127 | E61: =Q!L13 -> 0.12 | F61: 0 | G61: =E61+F61 -> 0.12 | H61: 0 | I61: 0 | J61: 0 | K61: 0 | L61: 0 | M61: 0 | N61: Alphabet-level activities；預測期 0 [Assumed]
A62: 合併營收 | B62: US$B | C62: =Q!J14 -> 350.018 | D62: =Q!K14 -> 402.836 | E62: =Q!L14 -> 357.269 | F62: =F54+F59+F60+F61 -> 145.60445 | G62: =E62+F62 -> 502.87345 | H62: =H54+H59+H60+H61 -> 631.20297 | I62: =I54+I59+I60+I61 -> 756.24012 | J62: =J54+J59+J60+J61 -> 868.28405 | K62: =K54+K59+K60+K61 -> 944.17206 | L62: =L54+L59+L60+L61 -> 1020.6991 | M62: =M54+M59+M60+M61 -> 1098.3845
A63: 檢查：產品線合計 − Google Services | B63: US$B | C63: =C47+C49+C51+C53-C54 -> 0 | D63: =D47+D49+D51+D53-D54 -> 0 | E63: =E47+E49+E51+E53-E54 -> 0 | F63: =F47+F49+F51+F53-F54 -> 0 | G63: =G47+G49+G51+G53-G54 -> 0 | H63: =H47+H49+H51+H53-H54 -> 0 | I63: =I47+I49+I51+I53-I54 -> 0 | J63: =J47+J49+J51+J53-J54 -> 0 | ... M63: =M47+M49+M51+M53-M54 -> 0
A64: 檢查：Cloud 子列合計 − Google Cloud | B64: US$B | E64: =E55+E56+E58-E59 -> 0 | F64: =F55+F56+F58-F59 -> 0 | G64: =G55+G56+G58-G59 -> 0 | H64: =H55+H56+H58-H59 -> 0 | I64: =I55+I56+I58-I59 -> 0 | J64: =J55+J56+J58-J59 -> 0 | K64: =K55+K56+K58-K59 -> 0 | L64: =L55+L56+L58-L59 -> 0 | M64: =M55+M56+M58-M59 -> 0
A65: 檢查：分部合計＋避險 − 合併營收 | B65: US$B | C65: =C54+C59+C60+C61-C62 -> 0 | D65: =D54+D59+D60+D61-D62 -> 0 | E65: =E54+E59+E60+E61-E62 -> 0 | F65: =F54+F59+F60+F61-F62 -> 0 | G65: =G54+G59+G60+G61-G62 -> 0 | H65: =H54+H59+H60+H61-H62 -> 0 | I65: =I54+I59+I60+I61-I62 -> 0 | J65: =J54+J59+J60+J61-J62 -> 0 | ... M65: =M54+M59+M60+M61-M62 -> 0
A66: 檢查：實績欄合併營收 − Q 頁（FY2024、FY2025、9M26） | B66: US$B | C66: =C62-Q!J14 -> 0 | D66: =D62-Q!K14 -> 0 | E66: =E62-Q!L14 -> 0
A67: 非 AI 資本支出：Google Services（營收 × cx_svc） | B67: US$B | F67: =F54*cx_svc -> 6.5492707 | G67: =F67 -> 6.5492707 | H67: =H54*cx_svc -> 26.28035 | I67: =I54*cx_svc -> 29.160264 | J67: =J54*cx_svc -> 31.911133 | K67: =K54*cx_svc -> 34.419985 | L67: =L54*cx_svc -> 37.139028 | M67: =M54*cx_svc -> 40.086027
A68: 非 AI 資本支出：Cloud 其他（營收 × cx_co） | B68: US$B | F68: =F58*cx_co -> 5.8039572 | G68: =F68 -> 5.8039572 | H68: =H58*cx_co -> 28.396269 | I68: =I58*cx_co -> 39.62811 | J68: =J58*cx_co -> 49.050473 | K68: =K58*cx_co -> 52.974511 | L68: =L58*cx_co -> 57.212472 | M68: =M58*cx_co -> 61.789469
A69: 非 AI 資本支出：Other Bets（營收 × cx_ob） | B69: US$B | F69: =F60*cx_ob -> 0.0228 | G69: =F69 -> 0.0228 | H69: =H60*cx_ob -> 0.096 | I69: =I60*cx_ob -> 0.108 | J69: =J60*cx_ob -> 0.12 | K69: =K60*cx_ob -> 0.132 | L69: =L60*cx_ob -> 0.144 | M69: =M60*cx_ob -> 0.156
A70: 非 AI 資本支出合計 | B70: US$B | F70: =F67+F68+F69 -> 12.376028 | G70: =G67+G68+G69 -> 12.376028 | H70: =H67+H68+H69 -> 54.772619 | I70: =I67+I68+I69 -> 68.896375 | J70: =J67+J68+J69 -> 81.081606 | K70: =K67+K68+K69 -> 87.526495 | L70: =L67+L68+L69 -> 94.495499 | M70: =M67+M68+M69 -> 102.0315
A71: 新增非 AI 折舊：Google Services（年限 life_na） | B71: US$B | F71: =$F$67/life_na*IF((0)<0,0,IF((0)=0,phi_0,IF((0)<life_na,1,IF((0)=life_na,1-phi_0,0)))) -> 0.16373177 | G71: =F71 -> 0.16373177 | H71: =$F$67/life_na*IF((1)<0,0,IF((1)=0,phi_0,IF((1)<life_na,1,IF((1)=life_na,1-phi_0,0))))+$H$67/life_na*IF((0)<0,0,IF((0)=0,phi_0,IF((0)<life_na,1,IF((0)=life_na,1-phi_0,0)))) -> 1.3119358 | I71: =$F$67/life_na*IF((2)<0,0,IF((2)=0,phi_0,IF((2)<life_na,1,IF((2)=life_na,1-phi_0,0))))+$H$67/life_na*IF((1)<0,0,IF((1)=0,phi_0,IF((1)<life_na,1,IF((1)=life_na,1-phi_0,0))))+$I$67/life_na*IF((0)<0,0,IF((0)=0,phi_0,IF((0)<life_na,1,IF((0)=life_na,1-phi_0,0)))) -> 4.0119687 | J71: =$F$67/life_na*IF((3)<0,0,IF((3)=0,phi_0,IF((3)<life_na,1,IF((3)=life_na,1-phi_0,0))))+$H$67/life_na*IF((2)<0,0,IF((2)=0,phi_0,IF((2)<life_na,1,IF((2)=life_na,1-phi_0,0))))+$I$67/life_na*IF((1)<0,0,IF((1)=0,phi_0,IF((1)<life_na,1,IF((1)=life_na,1-phi_0,0))))+$J$67/life_na*IF((0)<0,0,IF((0)=0,phi_0,IF((0)<life_na,1,IF((0)=life_na,1-phi_0,0)))) -> 6.9967668 | K71: =$F$67/life_na*IF((4)<0,0,IF((4)=0,phi_0,IF((4)<life_na,1,IF((4)=life_na,1-phi_0,0))))+$H$67/life_na*IF((3)<0,0,IF((3)=0,phi_0,IF((3)<life_na,1,IF((3)=life_na,1-phi_0,0))))+$I$67/life_na*IF((2)<0,0,IF((2)=0,phi_0,IF((2)<life_na,1,IF((2)=life_na,1-phi_0,0))))+$J$67/life_na*IF((1)<0,0,IF((1)=0,phi_0,IF((1)<life_na,1,IF((1)=life_na,1-phi_0,0))))+$K$67/life_na*IF((0)<0,0,IF((0)=0,phi_0,IF((0)<life_na,1,IF((0)=life_na,1-phi_0,0)))) -> 10.250601 | L71: =$F$67/life_na*IF((5)<0,0,IF((5)=0,phi_0,IF((5)<life_na,1,IF((5)=life_na,1-phi_0,0))))+$H$67/life_na*IF((4)<0,0,IF((4)=0,phi_0,IF((4)<life_na,1,IF((4)=life_na,1-phi_0,0))))+$I$67/life_na*IF((3)<0,0,IF((3)=0,phi_0,IF((3)<life_na,1,IF((3)=life_na,1-phi_0,0))))+$J$67/life_na*IF((2)<0,0,IF((2)=0,phi_0,IF((2)<life_na,1,IF((2)=life_na,1-phi_0,0))))+$K$67/life_na*IF((1)<0,0,IF((1)=0,phi_0,IF((1)<life_na,1,IF((1)=life_na,1-phi_0,0))))+$L$67/life_na*IF((0)<0,0,IF((0)=0,phi_0,IF((0)<life_na,1,IF((0)=life_na,1-phi_0,0)))) -> 13.760576 | M71: =$F$67/life_na*IF((6)<0,0,IF((6)=0,phi_0,IF((6)<life_na,1,IF((6)=life_na,1-phi_0,0))))+$H$67/life_na*IF((5)<0,0,IF((5)=0,phi_0,IF((5)<life_na,1,IF((5)=life_na,1-phi_0,0))))+$I$67/life_na*IF((4)<0,0,IF((4)=0,phi_0,IF((4)<life_na,1,IF((4)=life_na,1-phi_0,0))))+$J$67/life_na*IF((3)<0,0,IF((3)=0,phi_0,IF((3)<life_na,1,IF((3)=life_na,1-phi_0,0))))+$K$67/life_na*IF((2)<0,0,IF((2)=0,phi_0,IF((2)<life_na,1,IF((2)=life_na,1-phi_0,0))))+$L$67/life_na*IF((1)<0,0,IF((1)=0,phi_0,IF((1)<life_na,1,IF((1)=life_na,1-phi_0,0))))+$M$67/life_na*IF((0)<0,0,IF((0)=0,phi_0,IF((0)<life_na,1,IF((0)=life_na,1-phi_0,0)))) -> 17.548154
A72: 新增非 AI 折舊：Cloud 其他（年限 life_na） | B72: US$B | F72: =$F$68/life_na*IF((0)<0,0,IF((0)=0,phi_0,IF((0)<life_na,1,IF((0)=life_na,1-phi_0,0)))) -> 0.14509893 | G72: =F72 -> 0.14509893 | H72: =$F$68/life_na*IF((1)<0,0,IF((1)=0,phi_0,IF((1)<life_na,1,IF((1)=life_na,1-phi_0,0))))+$H$68/life_na*IF((0)<0,0,IF((0)=0,phi_0,IF((0)<life_na,1,IF((0)=life_na,1-phi_0,0)))) -> 1.2903024 | I72: =$F$68/life_na*IF((2)<0,0,IF((2)=0,phi_0,IF((2)<life_na,1,IF((2)=life_na,1-phi_0,0))))+$H$68/life_na*IF((1)<0,0,IF((1)=0,phi_0,IF((1)<life_na,1,IF((1)=life_na,1-phi_0,0))))+$I$68/life_na*IF((0)<0,0,IF((0)=0,phi_0,IF((0)<life_na,1,IF((0)=life_na,1-phi_0,0)))) -> 4.4107254 | J72: =$F$68/life_na*IF((3)<0,0,IF((3)=0,phi_0,IF((3)<life_na,1,IF((3)=life_na,1-phi_0,0))))+$H$68/life_na*IF((2)<0,0,IF((2)=0,phi_0,IF((2)<life_na,1,IF((2)=life_na,1-phi_0,0))))+$I$68/life_na*IF((1)<0,0,IF((1)=0,phi_0,IF((1)<life_na,1,IF((1)=life_na,1-phi_0,0))))+$J$68/life_na*IF((0)<0,0,IF((0)=0,phi_0,IF((0)<life_na,1,IF((0)=life_na,1-phi_0,0)))) -> 8.6090955 | K72: =$F$68/life_na*IF((4)<0,0,IF((4)=0,phi_0,IF((4)<life_na,1,IF((4)=life_na,1-phi_0,0))))+$H$68/life_na*IF((3)<0,0,IF((3)=0,phi_0,IF((3)<life_na,1,IF((3)=life_na,1-phi_0,0))))+$I$68/life_na*IF((2)<0,0,IF((2)=0,phi_0,IF((2)<life_na,1,IF((2)=life_na,1-phi_0,0))))+$J$68/life_na*IF((1)<0,0,IF((1)=0,phi_0,IF((1)<life_na,1,IF((1)=life_na,1-phi_0,0))))+$K$68/life_na*IF((0)<0,0,IF((0)=0,phi_0,IF((0)<life_na,1,IF((0)=life_na,1-phi_0,0)))) -> 13.612244 | L72: =$F$68/life_na*IF((5)<0,0,IF((5)=0,phi_0,IF((5)<life_na,1,IF((5)=life_na,1-phi_0,0))))+$H$68/life_na*IF((4)<0,0,IF((4)=0,phi_0,IF((4)<life_na,1,IF((4)=life_na,1-phi_0,0))))+$I$68/life_na*IF((3)<0,0,IF((3)=0,phi_0,IF((3)<life_na,1,IF((3)=life_na,1-phi_0,0))))+$J$68/life_na*IF((2)<0,0,IF((2)=0,phi_0,IF((2)<life_na,1,IF((2)=life_na,1-phi_0,0))))+$K$68/life_na*IF((1)<0,0,IF((1)=0,phi_0,IF((1)<life_na,1,IF((1)=life_na,1-phi_0,0))))+$L$68/life_na*IF((0)<0,0,IF((0)=0,phi_0,IF((0)<life_na,1,IF((0)=life_na,1-phi_0,0)))) -> 19.015644 | M72: =$F$68/life_na*IF((6)<0,0,IF((6)=0,phi_0,IF((6)<life_na,1,IF((6)=life_na,1-phi_0,0))))+$H$68/life_na*IF((5)<0,0,IF((5)=0,phi_0,IF((5)<life_na,1,IF((5)=life_na,1-phi_0,0))))+$I$68/life_na*IF((4)<0,0,IF((4)=0,phi_0,IF((4)<life_na,1,IF((4)=life_na,1-phi_0,0))))+$J$68/life_na*IF((3)<0,0,IF((3)=0,phi_0,IF((3)<life_na,1,IF((3)=life_na,1-phi_0,0))))+$K$68/life_na*IF((2)<0,0,IF((2)=0,phi_0,IF((2)<life_na,1,IF((2)=life_na,1-phi_0,0))))+$L$68/life_na*IF((1)<0,0,IF((1)=0,phi_0,IF((1)<life_na,1,IF((1)=life_na,1-phi_0,0))))+$M$68/life_na*IF((0)<0,0,IF((0)=0,phi_0,IF((0)<life_na,1,IF((0)=life_na,1-phi_0,0)))) -> 24.851316
A73: 新增非 AI 折舊：Other Bets（年限 life_na） | B73: US$B | F73: =$F$69/life_na*IF((0)<0,0,IF((0)=0,phi_0,IF((0)<life_na,1,IF((0)=life_na,1-phi_0,0)))) -> 0.00057 | G73: =F73 -> 0.00057 | H73: =$F$69/life_na*IF((1)<0,0,IF((1)=0,phi_0,IF((1)<life_na,1,IF((1)=life_na,1-phi_0,0))))+$H$69/life_na*IF((0)<0,0,IF((0)=0,phi_0,IF((0)<life_na,1,IF((0)=life_na,1-phi_0,0)))) -> 0.00468 | I73: =$F$69/life_na*IF((2)<0,0,IF((2)=0,phi_0,IF((2)<life_na,1,IF((2)=life_na,1-phi_0,0))))+$H$69/life_na*IF((1)<0,0,IF((1)=0,phi_0,IF((1)<life_na,1,IF((1)=life_na,1-phi_0,0))))+$I$69/life_na*IF((0)<0,0,IF((0)=0,phi_0,IF((0)<life_na,1,IF((0)=life_na,1-phi_0,0)))) -> 0.01458 | J73: =$F$69/life_na*IF((3)<0,0,IF((3)=0,phi_0,IF((3)<life_na,1,IF((3)=life_na,1-phi_0,0))))+$H$69/life_na*IF((2)<0,0,IF((2)=0,phi_0,IF((2)<life_na,1,IF((2)=life_na,1-phi_0,0))))+$I$69/life_na*IF((1)<0,0,IF((1)=0,phi_0,IF((1)<life_na,1,IF((1)=life_na,1-phi_0,0))))+$J$69/life_na*IF((0)<0,0,IF((0)=0,phi_0,IF((0)<life_na,1,IF((0)=life_na,1-phi_0,0)))) -> 0.02568 | K73: =$F$69/life_na*IF((4)<0,0,IF((4)=0,phi_0,IF((4)<life_na,1,IF((4)=life_na,1-phi_0,0))))+$H$69/life_na*IF((3)<0,0,IF((3)=0,phi_0,IF((3)<life_na,1,IF((3)=life_na,1-phi_0,0))))+$I$69/life_na*IF((2)<0,0,IF((2)=0,phi_0,IF((2)<life_na,1,IF((2)=life_na,1-phi_0,0))))+$J$69/life_na*IF((1)<0,0,IF((1)=0,phi_0,IF((1)<life_na,1,IF((1)=life_na,1-phi_0,0))))+$K$69/life_na*IF((0)<0,0,IF((0)=0,phi_0,IF((0)<life_na,1,IF((0)=life_na,1-phi_0,0)))) -> 0.03798 | L73: =$F$69/life_na*IF((5)<0,0,IF((5)=0,phi_0,IF((5)<life_na,1,IF((5)=life_na,1-phi_0,0))))+$H$69/life_na*IF((4)<0,0,IF((4)=0,phi_0,IF((4)<life_na,1,IF((4)=life_na,1-phi_0,0))))+$I$69/life_na*IF((3)<0,0,IF((3)=0,phi_0,IF((3)<life_na,1,IF((3)=life_na,1-phi_0,0))))+$J$69/life_na*IF((2)<0,0,IF((2)=0,phi_0,IF((2)<life_na,1,IF((2)=life_na,1-phi_0,0))))+$K$69/life_na*IF((1)<0,0,IF((1)=0,phi_0,IF((1)<life_na,1,IF((1)=life_na,1-phi_0,0))))+$L$69/life_na*IF((0)<0,0,IF((0)=0,phi_0,IF((0)<life_na,1,IF((0)=life_na,1-phi_0,0)))) -> 0.05148 | M73: =$F$69/life_na*IF((6)<0,0,IF((6)=0,phi_0,IF((6)<life_na,1,IF((6)=life_na,1-phi_0,0))))+$H$69/life_na*IF((5)<0,0,IF((5)=0,phi_0,IF((5)<life_na,1,IF((5)=life_na,1-phi_0,0))))+$I$69/life_na*IF((4)<0,0,IF((4)=0,phi_0,IF((4)<life_na,1,IF((4)=life_na,1-phi_0,0))))+$J$69/life_na*IF((3)<0,0,IF((3)=0,phi_0,IF((3)<life_na,1,IF((3)=life_na,1-phi_0,0))))+$K$69/life_na*IF((2)<0,0,IF((2)=0,phi_0,IF((2)<life_na,1,IF((2)=life_na,1-phi_0,0))))+$L$69/life_na*IF((1)<0,0,IF((1)=0,phi_0,IF((1)<life_na,1,IF((1)=life_na,1-phi_0,0))))+$M$69/life_na*IF((0)<0,0,IF((0)=0,phi_0,IF((0)<life_na,1,IF((0)=life_na,1-phi_0,0)))) -> 0.06618
A74: 新增非 AI 折舊合計 | B74: US$B | F74: =F71+F72+F73 -> 0.3094007 | G74: =G71+G72+G73 -> 0.3094007 | H74: =H71+H72+H73 -> 2.6069183 | I74: =I71+I72+I73 -> 8.437274 | J74: =J71+J72+J73 -> 15.631542 | K74: =K71+K72+K73 -> 23.900825 | L74: =L71+L72+L73 -> 32.8277 | M74: =M71+M72+M73 -> 42.46565
A76: 情境 C（查詢被 AI 助理分流、每次查詢變現下降）
A77: 項目 | B77: 單位 | C77: FY2024A | D77: FY2025A | E77: 9M26A | F77: Q4 26E | G77: FY2026E | H77: FY2027E | I77: FY2028E | J77: FY2029E | K77: FY2030E | L77: FY2031E | M77: FY2032E | N77: 說明
A78: Search B 路徑年增 | B78: % | F78: =g0_search -> 0.16056206 | H78: =g0_search+(gl_search-g0_search)*MIN(1,(2027-2026)/conv_n) -> 0.14042155 | I78: =g0_search+(gl_search-g0_search)*MIN(1,(2028-2026)/conv_n) -> 0.12028103 | J78: =g0_search+(gl_search-g0_search)*MIN(1,(2029-2026)/conv_n) -> 0.10014052 | K78: =g0_search+(gl_search-g0_search)*MIN(1,(2030-2026)/conv_n) -> 0.08 | L78: =g0_search+(gl_search-g0_search)*MIN(1,(2031-2026)/conv_n) -> 0.08 | M78: =g0_search+(gl_search-g0_search)*MIN(1,(2032-2026)/conv_n) -> 0.08 | N78: Q4 26 年增＝近四季年增（Q 頁），FY2030 收斂到 gl_search
A79: Google Search & other：B 路徑 | B79: US$B | C79: =Q!J5 -> 198.084 | D79: =Q!K5 -> 224.532 | E79: =Q!L5 -> 187.02 | F79: =Q!F5*(1+F78) -> 73.200131 | G79: =E79+F79 -> 260.22013 | H79: =G79*(1+H78) -> 296.76064 | I79: =H79*(1+I78) -> 332.45532 | J79: =I79*(1+J78) -> 365.74757 | K79: =J79*(1+K78) -> 395.00737 | L79: =K79*(1+L78) -> 426.60796 | M79: =L79*(1+M78) -> 460.7366
A80: 情境爬坡（FY2026 0 → FY2030 1） | B80: x | F80: 0 | H80: =MIN(1,(2027-2026)/conv_n) -> 0.25 | I80: =MIN(1,(2028-2026)/conv_n) -> 0.5 | J80: =MIN(1,(2029-2026)/conv_n) -> 0.75 | K80: =MIN(1,(2030-2026)/conv_n) -> 1 | L80: =MIN(1,(2031-2026)/conv_n) -> 1 | M80: =MIN(1,(2032-2026)/conv_n) -> 1
A81: 查詢分流（相對 B 路徑） | B81: % | F81: =dC*F80 -> 0 | H81: =dC*H80 -> 0.05 | I81: =dC*I80 -> 0.1 | J81: =dC*J80 -> 0.15 | K81: =dC*K80 -> 0.2 | L81: =dC*L80 -> 0.2 | M81: =dC*M80 -> 0.2 | N81: In 頁 dC（壓力情境）
A82: 每次查詢變現變動（相對 B 路徑） | B82: % | F82: =mC*F80 -> 0 | H82: =mC*H80 -> -0.025 | I82: =mC*I80 -> -0.05 | J82: =mC*J80 -> -0.075 | K82: =mC*K80 -> -0.1 | L82: =mC*L80 -> -0.1 | M82: =mC*M80 -> -0.1
A83: Google Search & other | B83: US$B | C83: =C79 -> 198.084 | D83: =D79 -> 224.532 | E83: =E79 -> 187.02 | F83: =F79*(1-F81)*(1+F82) -> 73.200131 | G83: =E83+F83 -> 260.22013 | H83: =H79*(1-H81)*(1+H82) -> 274.87455 | I83: =I79*(1-I81)*(1+I82) -> 284.2493 | J83: =J79*(1-J81)*(1+J82) -> 287.56902 | K83: =K79*(1-K81)*(1+K82) -> 284.40531 | L83: =L79*(1-L81)*(1+L82) -> 307.15773 | M83: =M79*(1-M81)*(1+M82) -> 331.73035
A84: YouTube ads 年增 | B84: % | F84: =g0_yt -> 0.10317561 | H84: =g0_yt+(gl_yt-g0_yt)*MIN(1,(2027-2026)/conv_n) -> 0.097381707 | I84: =g0_yt+(gl_yt-g0_yt)*MIN(1,(2028-2026)/conv_n) -> 0.091587804 | J84: =g0_yt+(gl_yt-g0_yt)*MIN(1,(2029-2026)/conv_n) -> 0.085793902 | K84: =g0_yt+(gl_yt-g0_yt)*MIN(1,(2030-2026)/conv_n) -> 0.08 | L84: =g0_yt+(gl_yt-g0_yt)*MIN(1,(2031-2026)/conv_n) -> 0.08 | M84: =g0_yt+(gl_yt-g0_yt)*MIN(1,(2032-2026)/conv_n) -> 0.08 | N84: 三情境相同
A85: YouTube ads | B85: US$B | C85: =Q!J6 -> 36.147 | D85: =Q!K6 -> 40.367 | E85: =Q!L6 -> 32.145 | F85: =Q!F6*(1+F84) -> 12.557448 | G85: =E85+F85 -> 44.702448 | H85: =G85*(1+H84) -> 49.055649 | I85: =H85*(1+I84) -> 53.548548 | J85: =I85*(1+J84) -> 58.142687 | K85: =J85*(1+K84) -> 62.794102 | L85: =K85*(1+L84) -> 67.81763 | M85: =L85*(1+M84) -> 73.24304
A86: Google Network 年增 | B86: % | F86: =g0_net -> -0.012066315 | H86: =g0_net+(gl_net-g0_net)*MIN(1,(2027-2026)/conv_n) -> -0.0090497359 | I86: =g0_net+(gl_net-g0_net)*MIN(1,(2028-2026)/conv_n) -> -0.0060331573 | J86: =g0_net+(gl_net-g0_net)*MIN(1,(2029-2026)/conv_n) -> -0.0030165786 | K86: =g0_net+(gl_net-g0_net)*MIN(1,(2030-2026)/conv_n) -> 0 | L86: =g0_net+(gl_net-g0_net)*MIN(1,(2031-2026)/conv_n) -> 0 | M86: =g0_net+(gl_net-g0_net)*MIN(1,(2032-2026)/conv_n) -> 0 | N86: 三情境相同
A87: Google Network | B87: US$B | C87: =Q!J7 -> 30.359 | D87: =Q!K7 -> 29.792 | E87: =Q!L7 -> 21.729 | F87: =Q!F7*(1+F86) -> 7.7335449 | G87: =E87+F87 -> 29.462545 | H87: =G87*(1+H86) -> 29.195917 | I87: =H87*(1+I86) -> 29.019773 | J87: =I87*(1+J86) -> 28.932233 | K87: =J87*(1+K86) -> 28.932233 | L87: =K87*(1+L86) -> 28.932233 | M87: =L87*(1+M86) -> 28.932233
A88: Google subscriptions, platforms, and devices 年增 | B88: % | F88: =g0_subs -> 0.15358577 | H88: =g0_subs+(gl_subs-g0_subs)*MIN(1,(2027-2026)/conv_n) -> 0.14018932 | I88: =g0_subs+(gl_subs-g0_subs)*MIN(1,(2028-2026)/conv_n) -> 0.12679288 | J88: =g0_subs+(gl_subs-g0_subs)*MIN(1,(2029-2026)/conv_n) -> 0.11339644 | K88: =g0_subs+(gl_subs-g0_subs)*MIN(1,(2030-2026)/conv_n) -> 0.1 | L88: =g0_subs+(gl_subs-g0_subs)*MIN(1,(2031-2026)/conv_n) -> 0.1 | M88: =g0_subs+(gl_subs-g0_subs)*MIN(1,(2032-2026)/conv_n) -> 0.1 | N88: 三情境相同
A89: Google subscriptions, platforms, and devices | B89: US$B | C89: =Q!J8 -> 40.34 | D89: =Q!K8 -> 48.03 | E89: =Q!L8 -> 39.585 | F89: =Q!F8*(1+F88) -> 15.663388 | G89: =E89+F89 -> 55.248388 | H89: =G89*(1+H88) -> 62.993622 | I89: =H89*(1+I88) -> 70.980765 | J89: =I89*(1+J88) -> 79.029731 | K89: =J89*(1+K88) -> 86.932704 | L89: =K89*(1+L88) -> 95.625974 | M89: =L89*(1+M88) -> 105.18857
A90: Google Services | B90: US$B | C90: =Q!J9 -> 304.93 | D90: =Q!K9 -> 342.721 | E90: =Q!L9 -> 280.479 | F90: =F83+F85+F87+F89 -> 109.15451 | G90: =E90+F90 -> 389.63351 | H90: =H83+H85+H87+H89 -> 416.11973 | I90: =I83+I85+I87+I89 -> 437.79838 | J90: =J83+J85+J87+J89 -> 453.67367 | K90: =K83+K85+K87+K89 -> 463.06435 | L90: =L83+L85+L87+L89 -> 499.53357 | M90: =M83+M85+M87+M89 -> 539.0942
A91: Cloud AI（命題子列） | B91: US$B | E91: =Thesis!E38 -> 13.119056 | F91: =Thesis!F38 -> 6.050155 | G91: =Thesis!G38 -> 19.169211 | H91: =Thesis!H38 -> 36.615799 | I91: =Thesis!I38 -> 57.29516 | J91: =Thesis!J38 -> 76.179473 | K91: =Thesis!K38 -> 90.433098 | L91: =Thesis!L38 -> 100.25294 | M91: =Thesis!M38 -> 105.73669 | N91: Thesis 頁：對外 MW × 每 MW 收入（9M26 為模型估計）
A92: TPU 系統銷售（命題子列） | B92: US$B | E92: 0 | F92: =tpu_2h -> 1 | G92: =E92+F92 -> 1 | H92: =tpu_yr -> 13 | I92: =tpu_yr -> 13 | J92: =tpu_yr -> 13 | K92: =tpu_yr -> 13 | L92: =tpu_yr -> 13 | M92: =tpu_yr -> 13 | N92: C8 b：不走 MW × 每 MW；9M26 已認列但金額未揭露 → 0（含在 Cloud 其他）
A93: Cloud 其他年增 | B93: % | F93: =g0_co -> 0.71107868 | H93: =g0_co+(gl_co-g0_co)*MIN(1,(2027-2026)/conv_n) -> 0.55330901 | I93: =g0_co+(gl_co-g0_co)*MIN(1,(2028-2026)/conv_n) -> 0.39553934 | J93: =g0_co+(gl_co-g0_co)*MIN(1,(2029-2026)/conv_n) -> 0.23776967 | K93: =g0_co+(gl_co-g0_co)*MIN(1,(2030-2026)/conv_n) -> 0.08 | L93: =g0_co+(gl_co-g0_co)*MIN(1,(2031-2026)/conv_n) -> 0.08 | M93: =g0_co+(gl_co-g0_co)*MIN(1,(2032-2026)/conv_n) -> 0.08 | N93: 起始＝Cloud 其他近四季年增（Thesis 頁 g0_co），FY2030 收斂到 gl_co
A94: Cloud 其他（命題子列） | B94: US$B | E94: =Q!L11-E91-E92 -> 62.385944 | F94: =E94*q3sh_cloud*(1+F93)^0.25 -> 29.019786 | G94: =E94+F94 -> 91.40573 | H94: =G94*(1+H93) -> 141.98134 | I94: =H94*(1+I93) -> 198.14055 | J94: =I94*(1+J93) -> 245.25236 | K94: =J94*(1+K93) -> 264.87255 | L94: =K94*(1+L93) -> 286.06236 | M94: =L94*(1+M93) -> 308.94735 | N94: 9M26＝Google Cloud 實績 − Cloud AI 估計 − TPU；Q4 26＝9M26 × Q3 占 9M 比例（Q 頁 q3sh_cloud）×(1＋年增)^0.25
A95: Google Cloud | B95: US$B | C95: =Q!J11 -> 43.229 | D95: =Q!K11 -> 58.705 | E95: =Q!L11 -> 75.505 | F95: =F91+F92+F94 -> 36.069941 | G95: =E95+F95 -> 111.57494 | H95: =H91+H92+H94 -> 191.59714 | I95: =I91+I92+I94 -> 268.43571 | J95: =J91+J92+J94 -> 334.43184 | K95: =K91+K92+K94 -> 368.30565 | L95: =L91+L92+L94 -> 399.3153 | M95: =M91+M92+M94 -> 427.68403
A96: Other Bets | B96: US$B | C96: =Q!J12 -> 1.648 | D96: =Q!K12 -> 1.537 | E96: =Q!L12 -> 1.165 | F96: =ob_rev_2H -> 0.38 | G96: =E96+F96 -> 1.545 | H96: =ob_rev_27 -> 1.6 | I96: =ob_rev_28 -> 1.8 | J96: =ob_rev_29 -> 2 | K96: =ob_rev_30 -> 2.2 | L96: =ob_rev_31 -> 2.4 | M96: =ob_rev_32 -> 2.6
A97: Hedging gains (losses) | B97: US$B | C97: =Q!J13 -> 0.211 | D97: =Q!K13 -> -0.127 | E97: =Q!L13 -> 0.12 | F97: 0 | G97: =E97+F97 -> 0.12 | H97: 0 | I97: 0 | J97: 0 | K97: 0 | L97: 0 | M97: 0 | N97: Alphabet-level activities；預測期 0 [Assumed]
A98: 合併營收 | B98: US$B | C98: =Q!J14 -> 350.018 | D98: =Q!K14 -> 402.836 | E98: =Q!L14 -> 357.269 | F98: =F90+F95+F96+F97 -> 145.60445 | G98: =E98+F98 -> 502.87345 | H98: =H90+H95+H96+H97 -> 609.31688 | I98: =I90+I95+I96+I97 -> 708.03409 | J98: =J90+J95+J96+J97 -> 790.10551 | K98: =K90+K95+K96+K97 -> 833.57 | L98: =L90+L95+L96+L97 -> 901.24887 | M98: =M90+M95+M96+M97 -> 969.37823
A99: 檢查：產品線合計 − Google Services | B99: US$B | C99: =C83+C85+C87+C89-C90 -> 0 | D99: =D83+D85+D87+D89-D90 -> 0 | E99: =E83+E85+E87+E89-E90 -> 0 | F99: =F83+F85+F87+F89-F90 -> 0 | G99: =G83+G85+G87+G89-G90 -> 0 | H99: =H83+H85+H87+H89-H90 -> 0 | I99: =I83+I85+I87+I89-I90 -> 0 | J99: =J83+J85+J87+J89-J90 -> 0 | ... M99: =M83+M85+M87+M89-M90 -> 0
A100: 檢查：Cloud 子列合計 − Google Cloud | B100: US$B | E100: =E91+E92+E94-E95 -> 0 | F100: =F91+F92+F94-F95 -> 0 | G100: =G91+G92+G94-G95 -> 0 | H100: =H91+H92+H94-H95 -> 0 | I100: =I91+I92+I94-I95 -> 0 | J100: =J91+J92+J94-J95 -> 0 | K100: =K91+K92+K94-K95 -> 0 | L100: =L91+L92+L94-L95 -> 0 | M100: =M91+M92+M94-M95 -> 0
A101: 檢查：分部合計＋避險 − 合併營收 | B101: US$B | C101: =C90+C95+C96+C97-C98 -> 0 | D101: =D90+D95+D96+D97-D98 -> 0 | E101: =E90+E95+E96+E97-E98 -> 0 | F101: =F90+F95+F96+F97-F98 -> 0 | G101: =G90+G95+G96+G97-G98 -> 0 | H101: =H90+H95+H96+H97-H98 -> 0 | I101: =I90+I95+I96+I97-I98 -> 0 | J101: =J90+J95+J96+J97-J98 -> 0 | ... M101: =M90+M95+M96+M97-M98 -> 0
A102: 檢查：實績欄合併營收 − Q 頁（FY2024、FY2025、9M26） | B102: US$B | C102: =C98-Q!J14 -> 0 | D102: =D98-Q!K14 -> 0 | E102: =E98-Q!L14 -> 0
A103: 非 AI 資本支出：Google Services（營收 × cx_svc） | B103: US$B | F103: =F90*cx_svc -> 6.5492707 | G103: =F103 -> 6.5492707 | H103: =H90*cx_svc -> 24.967184 | I103: =I90*cx_svc -> 26.267903 | J103: =J90*cx_svc -> 27.22042 | K103: =K90*cx_svc -> 27.783861 | L103: =L90*cx_svc -> 29.972014 | M103: =M90*cx_svc -> 32.345652
...

Sheet PL
A1: PL — 分部營收 → 分部營業利益 → 合併營業利益 → 業外 → 稅 → 淨利 → EPS（三情境；US$B，EPS 美元）。實績欄（FY2024A、FY2025A、9M26A）取自 Q 頁；FY2026E＝9M 實績＋Q4 模型
A2: 分部營業利益＝分部 EBITDA − 分攤折舊。分部 EBITDA：Google Services＝B 路徑營收 × 近四季 EBITDA 率＋Search 情境差額 × 增量 EBITDA 率 − 自用 AI 增量營運成本 × svc_sh；Google Cloud＝Cloud AI EBITDA（Thesis）＋TPU × tpu_m＋Cloud 其他 × m_co。折舊＝評價日在役資產基礎折舊（按近四季營收分攤）＋新增 AI 折舊（對外→Cloud、自用→Services／Alphabet 層級）＋新增非 AI 折舊。持股評價損益預測期設 0
A4: 分部對帳彙總（三情境 × 全部年度取絕對值最大者；實績欄同列）
A5: 項目 | B5: 單位 | C5: FY2024A | D5: FY2025A | E5: 9M26A | F5: Q4 26E | G5: FY2026E | H5: FY2027E | I5: FY2028E | J5: FY2029E | K5: FY2030E | L5: FY2031E | M5: FY2032E | N5: 說明
A6: 檢查：產品線合計 − Google Services | B6: US$B | C6: =MAX(ABS(C26),ABS(C85),ABS(C144)) -> 0 | D6: =MAX(ABS(D26),ABS(D85),ABS(D144)) -> 0 | E6: =MAX(ABS(E26),ABS(E85),ABS(E144)) -> 0 | F6: =MAX(ABS(F26),ABS(F85),ABS(F144)) -> 0 | G6: =MAX(ABS(G26),ABS(G85),ABS(G144)) -> 0 | H6: =MAX(ABS(H26),ABS(H85),ABS(H144)) -> 0 | I6: =MAX(ABS(I26),ABS(I85),ABS(I144)) -> 0 | J6: =MAX(ABS(J26),ABS(J85),ABS(J144)) -> 0 | ... M6: =MAX(ABS(M26),ABS(M85),ABS(M144)) -> 0 | N6: 三情境各區塊同名核對列的最大絕對值；必須為 0（tools/segment_check 讀本列）
A7: 檢查：Cloud 子列合計 − Google Cloud | B7: US$B | E7: =MAX(ABS(E27),ABS(E86),ABS(E145)) -> 0 | F7: =MAX(ABS(F27),ABS(F86),ABS(F145)) -> 0 | G7: =MAX(ABS(G27),ABS(G86),ABS(G145)) -> 0 | H7: =MAX(ABS(H27),ABS(H86),ABS(H145)) -> 0 | I7: =MAX(ABS(I27),ABS(I86),ABS(I145)) -> 0 | J7: =MAX(ABS(J27),ABS(J86),ABS(J145)) -> 0 | K7: =MAX(ABS(K27),ABS(K86),ABS(K145)) -> 0 | L7: =MAX(ABS(L27),ABS(L86),ABS(L145)) -> 0 | M7: =MAX(ABS(M27),ABS(M86),ABS(M145)) -> 0 | N7: 三情境各區塊同名核對列的最大絕對值；必須為 0（tools/segment_check 讀本列）
A8: 檢查：分部合計＋避險 − 合併營收 | B8: US$B | C8: =MAX(ABS(C28),ABS(C87),ABS(C146)) -> 0 | D8: =MAX(ABS(D28),ABS(D87),ABS(D146)) -> 0 | E8: =MAX(ABS(E28),ABS(E87),ABS(E146)) -> 0 | F8: =MAX(ABS(F28),ABS(F87),ABS(F146)) -> 0 | G8: =MAX(ABS(G28),ABS(G87),ABS(G146)) -> 0 | H8: =MAX(ABS(H28),ABS(H87),ABS(H146)) -> 0 | I8: =MAX(ABS(I28),ABS(I87),ABS(I146)) -> 0 | J8: =MAX(ABS(J28),ABS(J87),ABS(J146)) -> 0 | ... M8: =MAX(ABS(M28),ABS(M87),ABS(M146)) -> 0 | N8: 三情境各區塊同名核對列的最大絕對值；必須為 0（tools/segment_check 讀本列）
A9: 檢查：分部營業利益合計 − 合併營業利益 | B9: US$B | C9: =MAX(ABS(C47),ABS(C106),ABS(C165)) -> 0 | D9: =MAX(ABS(D47),ABS(D106),ABS(D165)) -> 0 | E9: =MAX(ABS(E47),ABS(E106),ABS(E165)) -> 0 | F9: =MAX(ABS(F47),ABS(F106),ABS(F165)) -> 0 | G9: =MAX(ABS(G47),ABS(G106),ABS(G165)) -> 0 | H9: =MAX(ABS(H47),ABS(H106),ABS(H165)) -> 0 | I9: =MAX(ABS(I47),ABS(I106),ABS(I165)) -> 0 | J9: =MAX(ABS(J47),ABS(J106),ABS(J165)) -> 0 | ... M9: =MAX(ABS(M47),ABS(M106),ABS(M165)) -> 0 | N9: 三情境各區塊同名核對列的最大絕對值；必須為 0（tools/segment_check 讀本列）
A11: 情境 A（AI 搜尋擴大變現）
A12: 項目 | B12: 單位 | C12: FY2024A | D12: FY2025A | E12: 9M26A | F12: Q4 26E | G12: FY2026E | H12: FY2027E | I12: FY2028E | J12: FY2029E | K12: FY2030E | L12: FY2031E | M12: FY2032E | N12: 說明
A13: Google Search & other | B13: US$B | C13: =Seg!C11 -> 198.084 | D13: =Seg!D11 -> 224.532 | E13: =Seg!E11 -> 187.02 | F13: =Seg!F11 -> 73.200131 | G13: =Seg!G11 -> 260.22013 | H13: =Seg!H11 -> 307.98191 | I13: =Seg!I11 -> 357.80504 | J13: =Seg!J11 -> 407.92283 | ... M13: =Seg!M11 -> 532.15077
A14: YouTube ads | B14: US$B | C14: =Seg!C13 -> 36.147 | D14: =Seg!D13 -> 40.367 | E14: =Seg!E13 -> 32.145 | F14: =Seg!F13 -> 12.557448 | G14: =Seg!G13 -> 44.702448 | H14: =Seg!H13 -> 49.055649 | I14: =Seg!I13 -> 53.548548 | J14: =Seg!J13 -> 58.142687 | ... M14: =Seg!M13 -> 73.24304
A15: Google Network | B15: US$B | C15: =Seg!C15 -> 30.359 | D15: =Seg!D15 -> 29.792 | E15: =Seg!E15 -> 21.729 | F15: =Seg!F15 -> 7.7335449 | G15: =Seg!G15 -> 29.462545 | H15: =Seg!H15 -> 29.195917 | I15: =Seg!I15 -> 29.019773 | J15: =Seg!J15 -> 28.932233 | ... M15: =Seg!M15 -> 28.932233
A16: Google subscriptions, platforms, and devices | B16: US$B | C16: =Seg!C17 -> 40.34 | D16: =Seg!D17 -> 48.03 | E16: =Seg!E17 -> 39.585 | F16: =Seg!F17 -> 15.663388 | G16: =Seg!G17 -> 55.248388 | H16: =Seg!H17 -> 62.993622 | I16: =Seg!I17 -> 70.980765 | J16: =Seg!J17 -> 79.029731 | ... M16: =Seg!M17 -> 105.18857
A17: Google Services | B17: US$B | C17: =Seg!C18 -> 304.93 | D17: =Seg!D18 -> 342.721 | E17: =Seg!E18 -> 280.479 | F17: =Seg!F18 -> 109.15451 | G17: =Seg!G18 -> 389.63351 | H17: =Seg!H18 -> 449.22709 | I17: =Seg!I18 -> 511.35412 | J17: =Seg!J18 -> 574.02748 | ... M17: =Seg!M18 -> 739.51462
A18: Cloud AI（命題子列） | B18: US$B | E18: =Seg!E19 -> 13.119056 | F18: =Seg!F19 -> 6.050155 | G18: =Seg!G19 -> 19.169211 | H18: =Seg!H19 -> 36.615799 | I18: =Seg!I19 -> 57.29516 | J18: =Seg!J19 -> 76.179473 | K18: =Seg!K19 -> 90.433098 | L18: =Seg!L19 -> 100.25294 | M18: =Seg!M19 -> 105.73669
A19: TPU 系統銷售（命題子列） | B19: US$B | E19: =Seg!E20 -> 0 | F19: =Seg!F20 -> 1 | G19: =Seg!G20 -> 1 | H19: =Seg!H20 -> 13 | I19: =Seg!I20 -> 13 | J19: =Seg!J20 -> 13 | K19: =Seg!K20 -> 13 | L19: =Seg!L20 -> 13 | M19: =Seg!M20 -> 13
A20: Cloud 其他（命題子列） | B20: US$B | E20: =Seg!E22 -> 62.385944 | F20: =Seg!F22 -> 29.019786 | G20: =Seg!G22 -> 91.40573 | H20: =Seg!H22 -> 141.98134 | I20: =Seg!I22 -> 198.14055 | J20: =Seg!J22 -> 245.25236 | K20: =Seg!K22 -> 264.87255 | L20: =Seg!L22 -> 286.06236 | M20: =Seg!M22 -> 308.94735
A21: Google Cloud | B21: US$B | C21: =Seg!C23 -> 43.229 | D21: =Seg!D23 -> 58.705 | E21: =Seg!E23 -> 75.505 | F21: =Seg!F23 -> 36.069941 | G21: =Seg!G23 -> 111.57494 | H21: =Seg!H23 -> 191.59714 | I21: =Seg!I23 -> 268.43571 | J21: =Seg!J23 -> 334.43184 | ... M21: =Seg!M23 -> 427.68403
A22: Other Bets | B22: US$B | C22: =Seg!C24 -> 1.648 | D22: =Seg!D24 -> 1.537 | E22: =Seg!E24 -> 1.165 | F22: =Seg!F24 -> 0.38 | G22: =Seg!G24 -> 1.545 | H22: =Seg!H24 -> 1.6 | I22: =Seg!I24 -> 1.8 | J22: =Seg!J24 -> 2 | ... M22: =Seg!M24 -> 2.6
A23: Hedging gains (losses) | B23: US$B | C23: =Seg!C25 -> 0.211 | D23: =Seg!D25 -> -0.127 | E23: =Seg!E25 -> 0.12 | F23: =Seg!F25 -> 0 | G23: =Seg!G25 -> 0.12 | H23: =Seg!H25 -> 0 | I23: =Seg!I25 -> 0 | J23: =Seg!J25 -> 0 | ... M23: =Seg!M25 -> 0
A24: 合併營收 | B24: US$B | C24: =Seg!C26 -> 350.018 | D24: =Seg!D26 -> 402.836 | E24: =Seg!E26 -> 357.269 | F24: =Seg!F26 -> 145.60445 | G24: =Seg!G26 -> 502.87345 | H24: =Seg!H26 -> 642.42424 | I24: =Seg!I26 -> 781.58983 | J24: =Seg!J26 -> 910.45932 | ... M24: =Seg!M26 -> 1169.7986
A25: 合併營收年增 | B25: % | D25: =D24/C24-1 -> 0.15090081 | G25: =G24/D24-1 -> 0.24833295 | H25: =H24/G24-1 -> 0.27750676 | I25: =I24/H24-1 -> 0.2166257 | J25: =J24/I24-1 -> 0.16488122 | K25: =K24/J24-1 -> 0.10427581 | L25: =L24/K24-1 -> 0.080987936 | M25: =M24/L24-1 -> 0.07634665
A26: 檢查：產品線合計 − Google Services | B26: US$B | C26: =C13+C14+C15+C16-C17 -> 0 | D26: =D13+D14+D15+D16-D17 -> 0 | E26: =E13+E14+E15+E16-E17 -> 0 | F26: =F13+F14+F15+F16-F17 -> 0 | G26: =G13+G14+G15+G16-G17 -> 0 | H26: =H13+H14+H15+H16-H17 -> 0 | I26: =I13+I14+I15+I16-I17 -> 0 | J26: =J13+J14+J15+J16-J17 -> 0 | ... M26: =M13+M14+M15+M16-M17 -> 0
A27: 檢查：Cloud 子列合計 − Google Cloud | B27: US$B | E27: =E18+E19+E20-E21 -> 0 | F27: =F18+F19+F20-F21 -> 0 | G27: =G18+G19+G20-G21 -> 0 | H27: =H18+H19+H20-H21 -> 0 | I27: =I18+I19+I20-I21 -> 0 | J27: =J18+J19+J20-J21 -> 0 | K27: =K18+K19+K20-K21 -> 0 | L27: =L18+L19+L20-L21 -> 0 | M27: =M18+M19+M20-M21 -> 0
A28: 檢查：分部合計＋避險 − 合併營收 | B28: US$B | C28: =C17+C21+C22+C23-C24 -> 0 | D28: =D17+D21+D22+D23-D24 -> 0 | E28: =E17+E21+E22+E23-E24 -> 0 | F28: =F17+F21+F22+F23-F24 -> 0 | G28: =G17+G21+G22+G23-G24 -> 0 | H28: =H17+H21+H22+H23-H24 -> 0 | I28: =I17+I21+I22+I23-I24 -> 0 | J28: =J17+J21+J22+J23-J24 -> 0 | ... M28: =M17+M21+M22+M23-M24 -> 0
A29: Search 情境差額（相對 B 路徑） | B29: US$B | F29: =Seg!F11-Seg!F7 -> 0 | G29: =F29 -> 0 | H29: =Seg!H11-Seg!H7 -> 11.221262 | I29: =Seg!I11-Seg!I7 -> 25.349718 | J29: =Seg!J11-Seg!J7 -> 42.175266 | K29: =Seg!K11-Seg!K7 -> 61.226143 | L29: =Seg!L11-Seg!L7 -> 66.124234 | M29: =Seg!M11-Seg!M7 -> 71.414173
A30: Google Services EBITDA | B30: US$B | F30: =m_svc*(F17-F29)+inc_m*F29-svc_sh*(Thesis!F68+Thesis!F69) -> 51.316277 | H30: =m_svc*(H17-H29)+inc_m*H29-svc_sh*(Thesis!H68+Thesis!H69) -> 210.48157 | I30: =m_svc*(I17-I29)+inc_m*I29-svc_sh*(Thesis!I68+Thesis!I69) -> 238.33244 | J30: =m_svc*(J17-J29)+inc_m*J29-svc_sh*(Thesis!J68+Thesis!J69) -> 270.87614 | K30: =m_svc*(K17-K29)+inc_m*K29-svc_sh*(Thesis!K68+Thesis!K69) -> 304.2068 | L30: =m_svc*(L17-L29)+inc_m*L29-svc_sh*(Thesis!L68+Thesis!L69) -> 327.16581 | M30: =m_svc*(M17-M29)+inc_m*M29-svc_sh*(Thesis!M68+Thesis!M69) -> 353.36537 | N30: B 路徑營收 × m_svc（Q 頁；預設 9M26，mb_ttm＝1 時近四季）＋Search 差額 × inc_m − 自用 AI 增量營運與租金 × svc_sh
A31: Google Services 折舊（基礎分攤＋新增非 AI＋自用 AI × svc_sh） | B31: US$B | F31: =Thesis!F77*sh_svc+Seg!F35+Thesis!F65*svc_sh -> 8.4917179 | H31: =Thesis!H77*sh_svc+Seg!H35+Thesis!H65*svc_sh -> 37.941904 | I31: =Thesis!I77*sh_svc+Seg!I35+Thesis!I65*svc_sh -> 54.16115 | J31: =Thesis!J77*sh_svc+Seg!J35+Thesis!J65*svc_sh -> 69.807959 | K31: =Thesis!K77*sh_svc+Seg!K35+Thesis!K65*svc_sh -> 81.387413 | L31: =Thesis!L77*sh_svc+Seg!L35+Thesis!L65*svc_sh -> 88.491548 | M31: =Thesis!M77*sh_svc+Seg!M35+Thesis!M65*svc_sh -> 99.265829
A32: Google Services 營業利益 | B32: US$B | C32: =Q!J18 -> 121.263 | D32: =Q!K18 -> 139.404 | E32: =Q!L18 -> 119.29 | F32: =F30-F31 -> 42.824559 | G32: =E32+F32 -> 162.11456 | H32: =H30-H31 -> 172.53967 | I32: =I30-I31 -> 184.17129 | J32: =J30-J31 -> 201.06818 | K32: =K30-K31 -> 222.81938 | L32: =L30-L31 -> 238.67426 | M32: =M30-M31 -> 254.09954
A33: Google Cloud EBITDA | B33: US$B | F33: =Thesis!F41+F19*tpu_m+F20*m_co -> 14.722696 | H33: =Thesis!H41+H19*tpu_m+H20*m_co -> 79.814692 | I33: =Thesis!I41+I19*tpu_m+I20*m_co -> 115.33608 | J33: =Thesis!J41+J19*tpu_m+J20*m_co -> 146.43506 | K33: =Thesis!K41+K19*tpu_m+K20*m_co -> 164.60016 | L33: =Thesis!L41+L19*tpu_m+L20*m_co -> 179.6699 | M33: =Thesis!M41+M19*tpu_m+M20*m_co -> 191.76583 | N33: Cloud AI EBITDA（Tokenomics 營運成本）＋TPU × tpu_m＋Cloud 其他 × m_co
A34: Google Cloud 折舊（基礎分攤＋對外 AI＋新增非 AI） | B34: US$B | F34: =Thesis!F77*sh_cloud+Thesis!F64+Seg!F36 -> 3.4446796 | H34: =Thesis!H77*sh_cloud+Thesis!H64+Seg!H36 -> 16.84662 | I34: =Thesis!I77*sh_cloud+Thesis!I64+Seg!I36 -> 29.560394 | J34: =Thesis!J77*sh_cloud+Thesis!J64+Seg!J36 -> 43.21761 | K34: =Thesis!K77*sh_cloud+Thesis!K64+Seg!K36 -> 55.78836 | L34: =Thesis!L77*sh_cloud+Thesis!L64+Seg!L36 -> 67.092403 | M34: =Thesis!M77*sh_cloud+Thesis!M64+Seg!M36 -> 78.552724
A35: Google Cloud 營業利益 | B35: US$B | C35: =Q!J19 -> 6.112 | D35: =Q!K19 -> 13.91 | E35: =Q!L19 -> 26.533 | F35: =F33-F34 -> 11.278017 | G35: =E35+F35 -> 37.811017 | H35: =H33-H34 -> 62.968072 | I35: =I33-I34 -> 85.775683 | J35: =J33-J34 -> 103.21745 | K35: =K33-K34 -> 108.8118 | L35: =L33-L34 -> 112.5775 | M35: =M33-M34 -> 113.2131
A36: Other Bets 折舊（基礎分攤＋新增非 AI） | B36: US$B | F36: =Thesis!F77*sh_ob+Seg!F37 -> 0.02371989 | H36: =Thesis!H77*sh_ob+Seg!H37 -> 0.097279561 | I36: =Thesis!I77*sh_ob+Seg!I37 -> 0.10717956 | J36: =Thesis!J77*sh_ob+Seg!J37 -> 0.11354974 | K36: =Thesis!K77*sh_ob+Seg!K37 -> 0.1099279 | L36: =Thesis!L77*sh_ob+Seg!L37 -> 0.091957891 | M36: =Thesis!M77*sh_ob+Seg!M37 -> 0.098589846
A37: Other Bets 營業利益 | B37: US$B | C37: =Q!J20 -> -4.444 | D37: =Q!K20 -> -7.515 | E37: =Q!L20 -> -5.946 | F37: =ob_oi*0.25 -> -2.25 | G37: =E37+F37 -> -8.196 | H37: =ob_oi*1 -> -9 | I37: =ob_oi*1 -> -9 | J37: =ob_oi*1 -> -9 | K37: =ob_oi*1 -> -9 | L37: =ob_oi*1 -> -9 | M37: =ob_oi*1 -> -9
A38: Other Bets EBITDA | B38: US$B | F38: =F37+F36 -> -2.2262801 | H38: =H37+H36 -> -8.9027204 | I38: =I37+I36 -> -8.8928204 | J38: =J37+J36 -> -8.8864503 | K38: =K37+K36 -> -8.8900721 | L38: =L37+L36 -> -8.9080421 | M38: =M37+M36 -> -8.9014102
A39: Alphabet-level 折舊（自用 AI × (1 − svc_sh)） | B39: US$B | F39: =Thesis!F65*(1-svc_sh) -> 1.7681676 | H39: =Thesis!H65*(1-svc_sh) -> 9.2734652 | I39: =Thesis!I65*(1-svc_sh) -> 18.22726 | J39: =Thesis!J65*(1-svc_sh) -> 27.323461 | K39: =Thesis!K65*(1-svc_sh) -> 35.288528 | L39: =Thesis!L65*(1-svc_sh) -> 42.578569 | M39: =Thesis!M65*(1-svc_sh) -> 48.285297
A40: Alphabet-level activities（避險營收 − 未分攤費用 − 自用 AI 增量成本 × (1 − svc_sh)） | B40: US$B | C40: =Q!J21 -> -10.541 | D40: =Q!K21 -> -16.76 | E40: =Q!L21 -> -18.835 | F40: =F23-abc_rate*F24-Thesis!F72 -> -11.716484 | G40: =E40+F40 -> -30.551484 | H40: =H23-abc_rate*H24-Thesis!H72 -> -54.876426 | I40: =I23-abc_rate*I24-Thesis!I72 -> -75.782721 | J40: =J23-abc_rate*J24-Thesis!J72 -> -93.645782 | K40: =K23-abc_rate*K24-Thesis!K72 -> -107.54672 | L40: =L23-abc_rate*L24-Thesis!L72 -> -121.40847 | M40: =M23-abc_rate*M24-Thesis!M72 -> -133.03535
A41: Alphabet-level EBITDA | B41: US$B | F41: =F40+F39 -> -9.948316 | H41: =H40+H39 -> -45.602961 | I41: =I40+I39 -> -57.555461 | J41: =J40+J39 -> -66.322322 | K41: =K40+K39 -> -72.258195 | L41: =L40+L39 -> -78.829902 | M41: =M40+M39 -> -84.750055
A42: 分部營業利益合計 | B42: US$B | C42: =C32+C35+C37+C40 -> 112.39 | D42: =D32+D35+D37+D40 -> 129.039 | E42: =E32+E35+E37+E40 -> 121.042 | F42: =F32+F35+F37+F40 -> 40.136092 | G42: =G32+G35+G37+G40 -> 161.17809 | H42: =H32+H35+H37+H40 -> 171.63132 | I42: =I32+I35+I37+I40 -> 185.16426 | J42: =J32+J35+J37+J40 -> 201.63985 | ... M42: =M32+M35+M37+M40 -> 225.27729
A43: 合併 EBITDA（分部 EBITDA 合計） | B43: US$B | F43: =F30+F33+F38+F41 -> 53.864377 | H43: =H30+H33+H38+H41 -> 235.79058 | I43: =I30+I33+I38+I41 -> 287.22024 | J43: =J30+J33+J38+J41 -> 342.10243 | K43: =K30+K33+K38+K41 -> 387.65869 | L43: =L30+L33+L38+L41 -> 419.09777 | M43: =M30+M33+M38+M41 -> 451.47973
A44: 折舊合計（基礎＋新增 AI＋新增非 AI） | B44: US$B | C44: =Q!J43 -> 15.311 | D44: =Q!K43 -> 21.136 | E44: =Q!L43 -> 21.955 | F44: =Thesis!F77+Thesis!F63+Seg!F38 -> 13.728285 | G44: =E44+F44 -> 35.683285 | H44: =Thesis!H77+Thesis!H63+Seg!H38 -> 64.159269 | I44: =Thesis!I77+Thesis!I63+Seg!I38 -> 102.05598 | J44: =Thesis!J77+Thesis!J63+Seg!J38 -> 140.46258 | K44: =Thesis!K77+Thesis!K63+Seg!K38 -> 172.57423 | L44: =Thesis!L77+Thesis!L63+Seg!L38 -> 198.25448 | M44: =Thesis!M77+Thesis!M63+Seg!M38 -> 226.20244 | N44: 9M26 與以前為現金流量表實績
A45: 其中：新增 AI 折舊 | B45: US$B | F45: =Thesis!F63 -> 6.3148843 | G45: =F45 -> 6.3148843 | H45: =Thesis!H63 -> 33.119518 | I45: =Thesis!I63 -> 65.097357 | J45: =Thesis!J63 -> 97.583788 | K45: =Thesis!K63 -> 126.03046 | L45: =Thesis!L63 -> 152.06632 | M45: =Thesis!M63 -> 172.44749
A46: 合併營業利益 | B46: US$B | C46: =Q!J22 -> 112.39 | D46: =Q!K22 -> 129.039 | E46: =Q!L22 -> 121.042 | F46: =F43-F44 -> 40.136092 | G46: =E46+F46 -> 161.17809 | H46: =H43-H44 -> 171.63132 | I46: =I43-I44 -> 185.16426 | J46: =J43-J44 -> 201.63985 | K46: =K43-K44 -> 215.08446 | L46: =L43-L44 -> 220.84329 | M46: =M43-M44 -> 225.27729 | N46: 預測期＝合併 EBITDA − 折舊合計（與分部營業利益合計獨立計算，下一列核對折舊分攤）
A47: 檢查：分部營業利益合計 − 合併營業利益 | B47: US$B | C47: =C42-C46 -> 0 | D47: =D42-D46 -> 0 | E47: =E42-E46 -> 0 | F47: =F42-F46 -> 0 | G47: =G42-G46 -> 0 | H47: =H42-H46 -> 0 | I47: =I42-I46 -> 0 | J47: =J42-J46 -> 0 | ... M47: =M42-M46 -> 0
A48: 自用 AI 影子效益（讀法 2；非財報營收） | B48: US$B | F48: =Thesis!F80 -> 1.1494869 | G48: =F48 -> 1.1494869 | H48: =Thesis!H80 -> 28.718806 | I48: =Thesis!I80 -> 68.895751 | J48: =Thesis!J80 -> 105.58518 | K48: =Thesis!K80 -> 133.27787 | L48: =Thesis!L80 -> 152.35637 | M48: =Thesis!M80 -> 163.01048 | N48: 修正一 F1：自用增量 MW × IF_HoldEcon（k＝1）；只進評價口徑，不進營收與分部對帳
A49: 營業利益（評價口徑；讀法 2 含影子效益） | B49: US$B | C49: =C46 -> 112.39 | D49: =D46 -> 129.039 | E49: =E46 -> 121.042 | F49: =F46+(internal_ai_reading=2)*F48 -> 41.285579 | G49: =G46+(internal_ai_reading=2)*G48 -> 162.32758 | H49: =H46+(internal_ai_reading=2)*H48 -> 200.35012 | I49: =I46+(internal_ai_reading=2)*I48 -> 254.06001 | J49: =J46+(internal_ai_reading=2)*J48 -> 307.22503 | K49: =K46+(internal_ai_reading=2)*K48 -> 348.36233 | L49: =L46+(internal_ai_reading=2)*L48 -> 373.19966 | M49: =M46+(internal_ai_reading=2)*M48 -> 388.28778
A50: 營業利益率 | B50: % | C50: =C46/C24 -> 0.32109777 | D50: =D46/D24 -> 0.32032639 | E50: =E46/E24 -> 0.33879794 | F50: =F46/F24 -> 0.27565154 | G50: =G46/G24 -> 0.32051422 | H50: =H46/H24 -> 0.26716196 | I50: =I46/I24 -> 0.2369072 | J50: =J46/J24 -> 0.22147047 | ... M50: =M46/M24 -> 0.19257784
A51: Google Services 營業利益率 | B51: % | C51: =C32/C17 -> 0.39767488 | D51: =D32/D17 -> 0.40675652 | E51: =E32/E17 -> 0.42530813 | F51: =F32/F17 -> 0.39232972 | G51: =G32/G17 -> 0.41606934 | H51: =H32/H17 -> 0.38408117 | I51: =I32/I17 -> 0.3601639 | J51: =J32/J17 -> 0.35027622 | ... M51: =M32/M17 -> 0.34360314
A52: Google Cloud 營業利益率 | B52: % | C52: =C35/C21 -> 0.14138657 | D52: =D35/D21 -> 0.23694745 | E52: =E35/E21 -> 0.35140719 | F52: =F35/F21 -> 0.31267078 | G52: =G35/G21 -> 0.33888449 | H52: =H35/H21 -> 0.32864828 | I52: =I35/I21 -> 0.31953902 | J52: =J35/J21 -> 0.30863525 | ... M52: =M35/M21 -> 0.26471202
A53: 利息收入（期初現金 × r_cash） | B53: US$B | F53: =r_cash*CF!F31*0.25 -> 1.659631 | G53: =F53 -> 1.659631 | H53: =r_cash*CF!H31*1 -> 6.2232451 | I53: =r_cash*CF!I31*1 -> 3.3195148 | J53: =r_cash*CF!J31*1 -> 1.9 | K53: =r_cash*CF!K31*1 -> 3.1542939 | L53: =r_cash*CF!L31*1 -> 6.8535153 | M53: =r_cash*CF!M31*1 -> 12.562251
A54: 利息費用（期初債務 × r_debt） | B54: US$B | F54: =r_debt*CF!F38*0.25 -> 1.51746 | G54: =F54 -> 1.51746 | H54: =r_debt*CF!H38*1 -> 6.06984 | I54: =r_debt*CF!I38*1 -> 6.02184 | J54: =r_debt*CF!J38*1 -> 5.893392 | K54: =r_debt*CF!K38*1 -> 5.80872 | L54: =r_debt*CF!L38*1 -> 5.463792 | M54: =r_debt*CF!M38*1 -> 5.223792
A55: 權益證券淨損益（預測期設 0） | B55: US$B | D55: =SUM(Q!C33:F33) -> 24.08 | E55: =Q!L33 -> 127.282 | F55: 0 | G55: =E55+F55 -> 127.282 | H55: 0 | I55: 0 | J55: 0 | K55: 0 | L55: 0 | M55: 0 | N55: 2026 年 9M 127.3（1H 135.9 主要為 SpaceX 上市與 Anthropic 重估；Q3 −8.7 主要為 SpaceX 未實現損失）；預測期 0（工作單第 2 節 PL）
A56: 業外收益合計 | B56: US$B | C56: =Q!J32 -> 7.425 | D56: =Q!K32 -> 29.787 | E56: =Q!L32 -> 127.478 | F56: =F53-F54+F55 -> 0.142171 | G56: =E56+F56 -> 127.62017 | H56: =H53-H54+H55 -> 0.15340507 | I56: =I53-I54+I55 -> -2.7023252 | J56: =J53-J54+J55 -> -3.993392 | K56: =K53-K54+K55 -> -2.6544261 | L56: =L53-L54+L55 -> 1.3897233 | M56: =M53-M54+M55 -> 7.3384594
A57: 稅前利益 | B57: US$B | C57: =C46+C56 -> 119.815 | D57: =D46+D56 -> 158.826 | E57: =E46+E56 -> 248.52 | F57: =F46+F56 -> 40.278263 | G57: =G46+G56 -> 288.79826 | H57: =H46+H56 -> 171.78472 | I57: =I46+I56 -> 182.46193 | J57: =J46+J56 -> 197.64646 | ... M57: =M46+M56 -> 232.61575
A58: 所得稅 | B58: US$B | C58: =Q!J36 -> 19.697 | D58: =Q!K36 -> 26.656 | E58: =Q!L36 -> 47.281 | F58: =F57*tax -> 6.7667482 | G58: =E58+F58 -> 54.047748 | H58: =H57*tax -> 28.859833 | I58: =I57*tax -> 30.653605 | J58: =J57*tax -> 33.204605 | K58: =K57*tax -> 35.688246 | L58: =L57*tax -> 37.335147 | M58: =M57*tax -> 39.079446
A59: 淨利 | B59: US$B | C59: =C57-C58 -> 100.118 | D59: =D57-D58 -> 132.17 | E59: =E57-E58 -> 201.239 | F59: =F57-F58 -> 33.511515 | G59: =G57-G58 -> 234.75051 | H59: =H57-H58 -> 142.92489 | I59: =I57-I58 -> 151.80833 | J59: =J57-J58 -> 164.44185 | ... M59: =M57-M58 -> 193.53631
A60: 檢查：實績淨利 − Q 頁 | B60: US$B | C60: =C59-Q!J37 -> 0 | D60: =D59-Q!K37 -> 0 | E60: =E59-Q!L37 -> 0
A61: 特別股股利 | B61: US$B | E61: =pref_1H -> 0.384 | F61: =pref_2H -> 0.301 | G61: =E61+F61 -> 0.685 | H61: =pref_27 -> 1.203 | I61: =pref_28 -> 1.203 | J61: =pref_29 -> 0.602 | K61: 0 | L61: 0 | M61: 0
A62: 歸屬普通股淨利 | B62: US$B | E62: =E59-E61 -> 200.855 | F62: =F59-F61 -> 33.210515 | G62: =G59-G61 -> 234.06551 | H62: =H59-H61 -> 141.72189 | I62: =I59-I61 -> 150.60533 | J62: =J59-J61 -> 163.83985 | K62: =K59-K61 -> 176.74179 | L62: =L59-L61 -> 184.89787 | M62: =M59-M61 -> 193.53631
A63: 期末稀釋股數（十億股） | B63: 十億股 | E63: =sh_dil_q2+(sh_out-sh_basic_q2) -> 12.406 | F63: =E63*(1+dil*0.25)-CF!F34/CF!F41 -> 12.437015 | H63: =F63*(1+dil*1)-CF!H34/CF!H41 -> 12.515676 | I63: =H63*(1+dil*1)-CF!I34/CF!I41 -> 12.632357 | J63: =I63*(1+dil*1)-CF!J34/CF!J41+conv_sh -> 12.776153 | K63: =J63*(1+dil*1)-CF!K34/CF!K41 -> 12.870453 | L63: =K63*(1+dil*1)-CF!L34/CF!L41 -> 12.969 | M63: =L63*(1+dil*1)-CF!M34/CF!M41 -> 13.071511 | N63: 9M26 期末＝Q3 稀釋加權＋(9/30 流通股 − Q3 基本加權)；之後 ×(1＋dil × 期間長度) − 回購 ÷ 回購均價；2029 強制轉換特別股 +conv_sh
A64: 平均稀釋股數（十億股） | B64: 十億股 | C64: =Q!J39 -> 12.447 | D64: =Q!K39 -> 12.23 | E64: =Q!L39 -> 12.324 | F64: =E63*(1+dil*0.125) -> 12.421508 | G64: =0.75*E64+0.25*F64 -> 12.348377 | H64: =(F63+H63)/2 -> 12.476346 | I64: =(H63+I63)/2 -> 12.574017 | J64: =(I63+J63)/2 -> 12.704255 | K64: =(J63+K63)/2 -> 12.823303 | L64: =(K63+L63)/2 -> 12.919727 | M64: =(L63+M63)/2 -> 13.020255
A65: EPS（GAAP 稀釋，美元） | B65: US$ | C65: =C59/C64 -> 8.0435446 | D65: =D59/D64 -> 10.807032 | E65: =E62/E64 -> 16.297874 | F65: =F62/F64 -> 2.67363 | G65: =G62/G64 -> 18.955164 | H65: =H62/H64 -> 11.359247 | I65: =I62/I64 -> 11.977503 | J65: =J62/J64 -> 12.896455 | K65: =K62/K64 -> 13.78286 | L65: =L62/L64 -> 14.311283 | M65: =M62/M64 -> 14.864248
A66: EPS（不含權益證券損益，美元） | B66: US$ | E66: =(E62-E55*(1-tax_eq))/E64 -> 8.1387715 | F66: =(F62-F55*(1-tax_eq))/F64 -> 2.67363 | G66: =(G62-G55*(1-tax_eq))/G64 -> 10.812169 | H66: =(H62-H55*(1-tax_eq))/H64 -> 11.359247 | I66: =(I62-I55*(1-tax_eq))/I64 -> 11.977503 | J66: =(J62-J55*(1-tax_eq))/J64 -> 12.896455 | K66: =(K62-K55*(1-tax_eq))/K64 -> 13.78286 | L66: =(L62-L55*(1-tax_eq))/L64 -> 14.311283 | M66: =(M62-M55*(1-tax_eq))/M64 -> 14.864248 | N66: 權益證券損益以 tax_eq 21% 稅後扣除；可與共識 non-GAAP EPS 比較
A67: EPS（評價口徑；讀法 2 含稅後影子效益，美元） | B67: US$ | F67: =(F62+(internal_ai_reading=2)*F48*(1-tax))/F64 -> 2.7506233 | G67: =(G62+(internal_ai_reading=2)*G48*(1-tax))/G64 -> 19.032614 | H67: =(H62+(internal_ai_reading=2)*H48*(1-tax))/H64 -> 13.274395 | I67: =(I62+(internal_ai_reading=2)*I48*(1-tax))/I64 -> 16.536211 | J67: =(J62+(internal_ai_reading=2)*J48*(1-tax))/J64 -> 19.811215 | K67: =(K62+(internal_ai_reading=2)*K48*(1-tax))/K64 -> 22.430179 | L67: =(L62+(internal_ai_reading=2)*L48*(1-tax))/L64 -> 24.122675 | M67: =(M62+(internal_ai_reading=2)*M48*(1-tax))/M64 -> 25.280689 | N67: 評價口徑；財報口徑見上兩列
A68: 股權報酬（已含在分部營業利益內） | B68: US$B | C68: =Q!J44 -> 22.785 | D68: =Q!K44 -> 24.953 | E68: =Q!L44 -> 23.338 | F68: =F24*sbc_r -> 9.3914872 | G68: =E68+F68 -> 32.729487 | H68: =H24*sbc_r -> 41.436363 | I68: =I24*sbc_r -> 50.412544 | J68: =J24*sbc_r -> 58.724626 | K68: =K24*sbc_r -> 64.848184 | L68: =L24*sbc_r -> 70.100105 | M68: =M24*sbc_r -> 75.452013
A70: 情境 B（近四季成長收斂；基準）
A71: 項目 | B71: 單位 | C71: FY2024A | D71: FY2025A | E71: 9M26A | F71: Q4 26E | G71: FY2026E | H71: FY2027E | I71: FY2028E | J71: FY2029E | K71: FY2030E | L71: FY2031E | M71: FY2032E | N71: 說明
A72: Google Search & other | B72: US$B | C72: =Seg!C47 -> 198.084 | D72: =Seg!D47 -> 224.532 | E72: =Seg!E47 -> 187.02 | F72: =Seg!F47 -> 73.200131 | G72: =Seg!G47 -> 260.22013 | H72: =Seg!H47 -> 296.76064 | I72: =Seg!I47 -> 332.45532 | J72: =Seg!J47 -> 365.74757 | ... M72: =Seg!M47 -> 460.7366
A73: YouTube ads | B73: US$B | C73: =Seg!C49 -> 36.147 | D73: =Seg!D49 -> 40.367 | E73: =Seg!E49 -> 32.145 | F73: =Seg!F49 -> 12.557448 | G73: =Seg!G49 -> 44.702448 | H73: =Seg!H49 -> 49.055649 | I73: =Seg!I49 -> 53.548548 | J73: =Seg!J49 -> 58.142687 | ... M73: =Seg!M49 -> 73.24304
A74: Google Network | B74: US$B | C74: =Seg!C51 -> 30.359 | D74: =Seg!D51 -> 29.792 | E74: =Seg!E51 -> 21.729 | F74: =Seg!F51 -> 7.7335449 | G74: =Seg!G51 -> 29.462545 | H74: =Seg!H51 -> 29.195917 | I74: =Seg!I51 -> 29.019773 | J74: =Seg!J51 -> 28.932233 | ... M74: =Seg!M51 -> 28.932233
A75: Google subscriptions, platforms, and devices | B75: US$B | C75: =Seg!C53 -> 40.34 | D75: =Seg!D53 -> 48.03 | E75: =Seg!E53 -> 39.585 | F75: =Seg!F53 -> 15.663388 | G75: =Seg!G53 -> 55.248388 | H75: =Seg!H53 -> 62.993622 | I75: =Seg!I53 -> 70.980765 | J75: =Seg!J53 -> 79.029731 | ... M75: =Seg!M53 -> 105.18857
A76: Google Services | B76: US$B | C76: =Seg!C54 -> 304.93 | D76: =Seg!D54 -> 342.721 | E76: =Seg!E54 -> 280.479 | F76: =Seg!F54 -> 109.15451 | G76: =Seg!G54 -> 389.63351 | H76: =Seg!H54 -> 438.00583 | I76: =Seg!I54 -> 486.0044 | J76: =Seg!J54 -> 531.85222 | ... M76: =Seg!M54 -> 668.10044
A77: Cloud AI（命題子列） | B77: US$B | E77: =Seg!E55 -> 13.119056 | F77: =Seg!F55 -> 6.050155 | G77: =Seg!G55 -> 19.169211 | H77: =Seg!H55 -> 36.615799 | I77: =Seg!I55 -> 57.29516 | J77: =Seg!J55 -> 76.179473 | K77: =Seg!K55 -> 90.433098 | L77: =Seg!L55 -> 100.25294 | M77: =Seg!M55 -> 105.73669
A78: TPU 系統銷售（命題子列） | B78: US$B | E78: =Seg!E56 -> 0 | F78: =Seg!F56 -> 1 | G78: =Seg!G56 -> 1 | H78: =Seg!H56 -> 13 | I78: =Seg!I56 -> 13 | J78: =Seg!J56 -> 13 | K78: =Seg!K56 -> 13 | L78: =Seg!L56 -> 13 | M78: =Seg!M56 -> 13
A79: Cloud 其他（命題子列） | B79: US$B | E79: =Seg!E58 -> 62.385944 | F79: =Seg!F58 -> 29.019786 | G79: =Seg!G58 -> 91.40573 | H79: =Seg!H58 -> 141.98134 | I79: =Seg!I58 -> 198.14055 | J79: =Seg!J58 -> 245.25236 | K79: =Seg!K58 -> 264.87255 | L79: =Seg!L58 -> 286.06236 | M79: =Seg!M58 -> 308.94735
A80: Google Cloud | B80: US$B | C80: =Seg!C59 -> 43.229 | D80: =Seg!D59 -> 58.705 | E80: =Seg!E59 -> 75.505 | F80: =Seg!F59 -> 36.069941 | G80: =Seg!G59 -> 111.57494 | H80: =Seg!H59 -> 191.59714 | I80: =Seg!I59 -> 268.43571 | J80: =Seg!J59 -> 334.43184 | ... M80: =Seg!M59 -> 427.68403
A81: Other Bets | B81: US$B | C81: =Seg!C60 -> 1.648 | D81: =Seg!D60 -> 1.537 | E81: =Seg!E60 -> 1.165 | F81: =Seg!F60 -> 0.38 | G81: =Seg!G60 -> 1.545 | H81: =Seg!H60 -> 1.6 | I81: =Seg!I60 -> 1.8 | J81: =Seg!J60 -> 2 | ... M81: =Seg!M60 -> 2.6
A82: Hedging gains (losses) | B82: US$B | C82: =Seg!C61 -> 0.211 | D82: =Seg!D61 -> -0.127 | E82: =Seg!E61 -> 0.12 | F82: =Seg!F61 -> 0 | G82: =Seg!G61 -> 0.12 | H82: =Seg!H61 -> 0 | I82: =Seg!I61 -> 0 | J82: =Seg!J61 -> 0 | ... M82: =Seg!M61 -> 0
A83: 合併營收 | B83: US$B | C83: =Seg!C62 -> 350.018 | D83: =Seg!D62 -> 402.836 | E83: =Seg!E62 -> 357.269 | F83: =Seg!F62 -> 145.60445 | G83: =Seg!G62 -> 502.87345 | H83: =Seg!H62 -> 631.20297 | I83: =Seg!I62 -> 756.24012 | J83: =Seg!J62 -> 868.28405 | ... M83: =Seg!M62 -> 1098.3845
A84: 合併營收年增 | B84: % | D84: =D83/C83-1 -> 0.15090081 | G84: =G83/D83-1 -> 0.24833295 | H84: =H83/G83-1 -> 0.25519248 | I84: =I83/H83-1 -> 0.1980934 | J84: =J83/I83-1 -> 0.14815921 | K84: =K83/J83-1 -> 0.087399978 | L84: =L83/K83-1 -> 0.081052 | M84: =M83/L83-1 -> 0.076109974
A85: 檢查：產品線合計 − Google Services | B85: US$B | C85: =C72+C73+C74+C75-C76 -> 0 | D85: =D72+D73+D74+D75-D76 -> 0 | E85: =E72+E73+E74+E75-E76 -> 0 | F85: =F72+F73+F74+F75-F76 -> 0 | G85: =G72+G73+G74+G75-G76 -> 0 | H85: =H72+H73+H74+H75-H76 -> 0 | I85: =I72+I73+I74+I75-I76 -> 0 | J85: =J72+J73+J74+J75-J76 -> 0 | ... M85: =M72+M73+M74+M75-M76 -> 0
A86: 檢查：Cloud 子列合計 − Google Cloud | B86: US$B | E86: =E77+E78+E79-E80 -> 0 | F86: =F77+F78+F79-F80 -> 0 | G86: =G77+G78+G79-G80 -> 0 | H86: =H77+H78+H79-H80 -> 0 | I86: =I77+I78+I79-I80 -> 0 | J86: =J77+J78+J79-J80 -> 0 | K86: =K77+K78+K79-K80 -> 0 | L86: =L77+L78+L79-L80 -> 0 | M86: =M77+M78+M79-M80 -> 0
A87: 檢查：分部合計＋避險 − 合併營收 | B87: US$B | C87: =C76+C80+C81+C82-C83 -> 0 | D87: =D76+D80+D81+D82-D83 -> 0 | E87: =E76+E80+E81+E82-E83 -> 0 | F87: =F76+F80+F81+F82-F83 -> 0 | G87: =G76+G80+G81+G82-G83 -> 0 | H87: =H76+H80+H81+H82-H83 -> 0 | I87: =I76+I80+I81+I82-I83 -> 0 | J87: =J76+J80+J81+J82-J83 -> 0 | ... M87: =M76+M80+M81+M82-M83 -> 0
A88: Search 情境差額（相對 B 路徑） | B88: US$B | F88: =Seg!F47-Seg!F43 -> 0 | G88: =F88 -> 0 | H88: =Seg!H47-Seg!H43 -> 0 | I88: =Seg!I47-Seg!I43 -> 0 | J88: =Seg!J47-Seg!J43 -> 0 | K88: =Seg!K47-Seg!K43 -> 0 | L88: =Seg!L47-Seg!L43 -> 0 | M88: =Seg!M47-Seg!M43 -> 0
A89: Google Services EBITDA | B89: US$B | F89: =m_svc*(F76-F88)+inc_m*F88-svc_sh*(Thesis!F68+Thesis!F69) -> 51.316277 | H89: =m_svc*(H76-H88)+inc_m*H88-svc_sh*(Thesis!H68+Thesis!H69) -> 202.62669 | I89: =m_svc*(I76-I88)+inc_m*I88-svc_sh*(Thesis!I68+Thesis!I69) -> 220.58764 | J89: =m_svc*(J76-J88)+inc_m*J88-svc_sh*(Thesis!J68+Thesis!J69) -> 241.35345 | K89: =m_svc*(K76-K88)+inc_m*K88-svc_sh*(Thesis!K68+Thesis!K69) -> 261.3485 | L89: =m_svc*(L76-L88)+inc_m*L88-svc_sh*(Thesis!L68+Thesis!L69) -> 280.87885 | M89: =m_svc*(M76-M88)+inc_m*M88-svc_sh*(Thesis!M68+Thesis!M69) -> 303.37545 | N89: B 路徑營收 × m_svc（Q 頁；預設 9M26，mb_ttm＝1 時近四季）＋Search 差額 × inc_m − 自用 AI 增量營運與租金 × svc_sh
A90: Google Services 折舊（基礎分攤＋新增非 AI＋自用 AI × svc_sh） | B90: US$B | F90: =Thesis!F77*sh_svc+Seg!F71+Thesis!F65*svc_sh -> 8.4917179 | H90: =Thesis!H77*sh_svc+Seg!H71+Thesis!H65*svc_sh -> 37.925072 | I90: =Thesis!I77*sh_svc+Seg!I71+Thesis!I65*svc_sh -> 54.055798 | J90: =Thesis!J77*sh_svc+Seg!J71+Thesis!J65*svc_sh -> 69.52527 | K90: =Thesis!K77*sh_svc+Seg!K71+Thesis!K65*svc_sh -> 80.823097 | L90: =Thesis!L77*sh_svc+Seg!L71+Thesis!L65*svc_sh -> 87.552528 | M90: =Thesis!M77*sh_svc+Seg!M71+Thesis!M65*svc_sh -> 97.922128
A91: Google Services 營業利益 | B91: US$B | C91: =Q!J18 -> 121.263 | D91: =Q!K18 -> 139.404 | E91: =Q!L18 -> 119.29 | F91: =F89-F90 -> 42.824559 | G91: =E91+F91 -> 162.11456 | H91: =H89-H90 -> 164.70162 | I91: =I89-I90 -> 166.53184 | J91: =J89-J90 -> 171.82818 | K91: =K89-K90 -> 180.5254 | L91: =L89-L90 -> 193.32632 | M91: =M89-M90 -> 205.45332
A92: Google Cloud EBITDA | B92: US$B | F92: =Thesis!F41+F78*tpu_m+F79*m_co -> 14.722696 | H92: =Thesis!H41+H78*tpu_m+H79*m_co -> 79.814692 | I92: =Thesis!I41+I78*tpu_m+I79*m_co -> 115.33608 | J92: =Thesis!J41+J78*tpu_m+J79*m_co -> 146.43506 | K92: =Thesis!K41+K78*tpu_m+K79*m_co -> 164.60016 | L92: =Thesis!L41+L78*tpu_m+L79*m_co -> 179.6699 | M92: =Thesis!M41+M78*tpu_m+M79*m_co -> 191.76583 | N92: Cloud AI EBITDA（Tokenomics 營運成本）＋TPU × tpu_m＋Cloud 其他 × m_co
A93: Google Cloud 折舊（基礎分攤＋對外 AI＋新增非 AI） | B93: US$B | F93: =Thesis!F77*sh_cloud+Thesis!F64+Seg!F72 -> 3.4446796 | H93: =Thesis!H77*sh_cloud+Thesis!H64+Seg!H72 -> 16.84662 | I93: =Thesis!I77*sh_cloud+Thesis!I64+Seg!I72 -> 29.560394 | J93: =Thesis!J77*sh_cloud+Thesis!J64+Seg!J72 -> 43.21761 | K93: =Thesis!K77*sh_cloud+Thesis!K64+Seg!K72 -> 55.78836 | L93: =Thesis!L77*sh_cloud+Thesis!L64+Seg!L72 -> 67.092403 | M93: =Thesis!M77*sh_cloud+Thesis!M64+Seg!M72 -> 78.552724
A94: Google Cloud 營業利益 | B94: US$B | C94: =Q!J19 -> 6.112 | D94: =Q!K19 -> 13.91 | E94: =Q!L19 -> 26.533 | F94: =F92-F93 -> 11.278017 | G94: =E94+F94 -> 37.811017 | H94: =H92-H93 -> 62.968072 | I94: =I92-I93 -> 85.775683 | J94: =J92-J93 -> 103.21745 | K94: =K92-K93 -> 108.8118 | L94: =L92-L93 -> 112.5775 | M94: =M92-M93 -> 113.2131
A95: Other Bets 折舊（基礎分攤＋新增非 AI） | B95: US$B | F95: =Thesis!F77*sh_ob+Seg!F73 -> 0.02371989 | H95: =Thesis!H77*sh_ob+Seg!H73 -> 0.097279561 | I95: =Thesis!I77*sh_ob+Seg!I73 -> 0.10717956 | J95: =Thesis!J77*sh_ob+Seg!J73 -> 0.11354974 | K95: =Thesis!K77*sh_ob+Seg!K73 -> 0.1099279 | L95: =Thesis!L77*sh_ob+Seg!L73 -> 0.091957891 | M95: =Thesis!M77*sh_ob+Seg!M73 -> 0.098589846
A96: Other Bets 營業利益 | B96: US$B | C96: =Q!J20 -> -4.444 | D96: =Q!K20 -> -7.515 | E96: =Q!L20 -> -5.946 | F96: =ob_oi*0.25 -> -2.25 | G96: =E96+F96 -> -8.196 | H96: =ob_oi*1 -> -9 | I96: =ob_oi*1 -> -9 | J96: =ob_oi*1 -> -9 | K96: =ob_oi*1 -> -9 | L96: =ob_oi*1 -> -9 | M96: =ob_oi*1 -> -9
A97: Other Bets EBITDA | B97: US$B | F97: =F96+F95 -> -2.2262801 | H97: =H96+H95 -> -8.9027204 | I97: =I96+I95 -> -8.8928204 | J97: =J96+J95 -> -8.8864503 | K97: =K96+K95 -> -8.8900721 | L97: =L96+L95 -> -8.9080421 | M97: =M96+M95 -> -8.9014102
A98: Alphabet-level 折舊（自用 AI × (1 − svc_sh)） | B98: US$B | F98: =Thesis!F65*(1-svc_sh) -> 1.7681676 | H98: =Thesis!H65*(1-svc_sh) -> 9.2734652 | I98: =Thesis!I65*(1-svc_sh) -> 18.22726 | J98: =Thesis!J65*(1-svc_sh) -> 27.323461 | K98: =Thesis!K65*(1-svc_sh) -> 35.288528 | L98: =Thesis!L65*(1-svc_sh) -> 42.578569 | M98: =Thesis!M65*(1-svc_sh) -> 48.285297
A99: Alphabet-level activities（避險營收 − 未分攤費用 − 自用 AI 增量成本 × (1 − svc_sh)） | B99: US$B | C99: =Q!J21 -> -10.541 | D99: =Q!K21 -> -16.76 | E99: =Q!L21 -> -18.835 | F99: =F82-abc_rate*F83-Thesis!F72 -> -11.716484 | G99: =E99+F99 -> -30.551484 | H99: =H82-abc_rate*H83-Thesis!H72 -> -54.20315 | I99: =I82-abc_rate*I83-Thesis!I72 -> -74.261737 | J99: =J82-abc_rate*J83-Thesis!J72 -> -91.115266 | K99: =K82-abc_rate*K83-Thesis!K72 -> -103.87315 | L99: =L82-abc_rate*L83-Thesis!L72 -> -117.44102 | M99: =M82-abc_rate*M83-Thesis!M72 -> -128.7505
A100: Alphabet-level EBITDA | B100: US$B | F100: =F99+F98 -> -9.948316 | H100: =H99+H98 -> -44.929685 | I100: =I99+I98 -> -56.034477 | J100: =J99+J98 -> -63.791806 | K100: =K99+K98 -> -68.584626 | L100: =L99+L98 -> -74.862448 | M100: =M99+M98 -> -80.465205
A101: 分部營業利益合計 | B101: US$B | C101: =C91+C94+C96+C99 -> 112.39 | D101: =D91+D94+D96+D99 -> 129.039 | E101: =E91+E94+E96+E99 -> 121.042 | F101: =F91+F94+F96+F99 -> 40.136092 | G101: =G91+G94+G96+G99 -> 161.17809 | H101: =H91+H94+H96+H99 -> 164.46654 | I101: =I91+I94+I96+I99 -> 169.04579 | J101: =J91+J94+J96+J99 -> 174.93037 | ... M101: =M91+M94+M96+M99 -> 180.91592
A102: 合併 EBITDA（分部 EBITDA 合計） | B102: US$B | F102: =F89+F92+F97+F100 -> 53.864377 | H102: =H89+H92+H97+H100 -> 228.60898 | I102: =I89+I92+I97+I100 -> 270.99642 | J102: =J89+J92+J97+J100 -> 315.11026 | K102: =K89+K92+K97+K100 -> 348.47396 | L102: =L89+L92+L97+L100 -> 376.77826 | M102: =M89+M92+M97+M100 -> 405.77466
A103: 折舊合計（基礎＋新增 AI＋新增非 AI） | B103: US$B | C103: =Q!J43 -> 15.311 | D103: =Q!K43 -> 21.136 | E103: =Q!L43 -> 21.955 | F103: =Thesis!F77+Thesis!F63+Seg!F74 -> 13.728285 | G103: =E103+F103 -> 35.683285 | H103: =Thesis!H77+Thesis!H63+Seg!H74 -> 64.142437 | I103: =Thesis!I77+Thesis!I63+Seg!I74 -> 101.95063 | J103: =Thesis!J77+Thesis!J63+Seg!J74 -> 140.17989 | K103: =Thesis!K77+Thesis!K63+Seg!K74 -> 172.00991 | L103: =Thesis!L77+Thesis!L63+Seg!L74 -> 197.31546 | M103: =Thesis!M77+Thesis!M63+Seg!M74 -> 224.85874 | N103: 9M26 與以前為現金流量表實績
...

Sheet CF
A1: CF — 現金流（US$B）。營運現金＝淨利＋折舊＋股權報酬＋營運資金；資本支出＝AI（Thesis）＋非 AI（Seg）；自由現金流＝營運現金 − 資本支出 − 融資租賃本金。融資順序：現金 → 減少回購 → 新債（最低現金 50）
A2: 2026 年：9M 發行普通股 42.9B（承銷＋Berkshire＋Q3 ATM 12.4）與強制轉換特別股 19.1B、發債 85.2B、暫停回購（C4：現金牛最強，但 2026 已轉向外部融資）；Q4 26 回購 0；FY2027 起回購目標 17.0／年（現金不足時先減回購）
A4: 收支關卡（地圖讀這兩列；模型期間 FY2026–FY2030，FY2026 含 9M 實績）
A5: 項目 | B5: 情境 A | C5: 情境 B | D5: 情境 C | E5: 說明
A6: 收支關卡：自由現金流扣股利（五年合計） | B6: =SUM(G26:K26) -> 77.680883 | C6: =SUM(G58:K58) -> -0.64822598 | D6: =SUM(G90:K90) -> -145.76163 | E6: FY2026–FY2030 自由現金流（扣融資租賃本金）− 普通股與特別股股利；FY2026 含 9M 實績。負值＝入不敷出
A7: 其中：五年新增舉債 | B7: =SUM(G35:K35) -> 0 | C7: =SUM(G67:K67) -> 16.65153 | D7: =SUM(G99:K99) -> 72.791424
A8: 其中：五年回購合計（FY2027–FY2030 目標 4 × bb_t） | B8: =SUM(G34:K34) -> 54.507218 | C8: =SUM(G66:K66) -> 51.009 | D8: =SUM(G98:K98) -> 34.006
A9: 是否需要舉債或停止回購 | B9: =IF(B7>0.001,"需要舉債"&IF(B8<4*bb_t-0.001,"且減少回購",""),IF(B8<4*bb_t-0.001,"不需舉債，但須減少回購","不需舉債，回購照目標")) -> 不需舉債，但須減少回購 | C9: =IF(C7>0.001,"需要舉債"&IF(C8<4*bb_t-0.001,"且減少回購",""),IF(C8<4*bb_t-0.001,"不需舉債，但須減少回購","不需舉債，回購照目標")) -> 需要舉債且減少回購 | D9: =IF(D7>0.001,"需要舉債"&IF(D8<4*bb_t-0.001,"且減少回購",""),IF(D8<4*bb_t-0.001,"不需舉債，但須減少回購","不需舉債，回購照目標")) -> 需要舉債且減少回購 | E9: 依現金瀑布：現金 → 減少回購 → 新債（最低現金 50）；2026 年 9M 已發行股權 61.9、新債 85.2 為已發生事件
A10: 檢查：收支關卡 − 首年起五年逐欄加總（FY2026＋…＋FY2030） | B10: =B6-(G26+H26+I26+J26+K26) -> 0 | C10: =C6-(G58+H58+I58+J58+K58) -> 1.4210855e-14 | D10: =D6-(G90+H90+I90+J90+K90) -> 0
A11: 情境 A（AI 搜尋擴大變現）
A12: 項目 | B12: 單位 | C12: FY2024A | D12: FY2025A | E12: 9M26A | F12: Q4 26E | G12: FY2026E | H12: FY2027E | I12: FY2028E | J12: FY2029E | K12: FY2030E | L12: FY2031E | M12: FY2032E | N12: 說明
A13: 淨利 | B13: US$B | C13: =PL!C59 -> 100.118 | D13: =PL!D59 -> 132.17 | E13: =PL!E59 -> 201.239 | F13: =PL!F59 -> 33.511515 | G13: =PL!G59 -> 234.75051 | H13: =PL!H59 -> 142.92489 | I13: =PL!I59 -> 151.80833 | J13: =PL!J59 -> 164.44185 | ... M13: =PL!M59 -> 193.53631
A14: 折舊 | B14: US$B | C14: =PL!C44 -> 15.311 | D14: =PL!D44 -> 21.136 | E14: =PL!E44 -> 21.955 | F14: =PL!F44 -> 13.728285 | G14: =PL!G44 -> 35.683285 | H14: =PL!H44 -> 64.159269 | I14: =PL!I44 -> 102.05598 | J14: =PL!J44 -> 140.46258 | ... M14: =PL!M44 -> 226.20244
A15: 股權報酬（非現金） | B15: US$B | C15: =PL!C68 -> 22.785 | D15: =PL!D68 -> 24.953 | E15: =PL!E68 -> 23.338 | F15: =PL!F68 -> 9.3914872 | G15: =PL!G68 -> 32.729487 | H15: =PL!H68 -> 41.436363 | I15: =PL!I68 -> 50.412544 | J15: =PL!J68 -> 58.724626 | ... M15: =PL!M68 -> 75.452013
A16: 營運資金變動（流入＋） | B16: US$B | F16: =wc_2h -> 4.707 | G16: =F16 -> 4.707 | H16: =wc_k*(PL!H24-PL!G24) -> 1.6327442 | I16: =wc_k*(PL!I24-PL!H24) -> 1.6282375 | J16: =wc_k*(PL!J24-PL!I24) -> 1.507773 | K16: =wc_k*(PL!K24-PL!J24) -> 1.1107849 | L16: =wc_k*(PL!L24-PL!K24) -> 0.95267396 | M16: =wc_k*(PL!M24-PL!L24) -> 0.97081125 | N16: Q4 26＝上一年度同期實際（2025Q4，C14）；之後＝營收增量 × wc_k
A17: 其他非現金調整（實績差額：權益證券利益迴轉、遞延稅等） | B17: US$B | C17: =Q!J45-C13-C14-C15 -> -12.915 | D17: =Q!K45-D13-D14-D15 -> -13.546 | E17: =Q!L45-E13-E14-E15 -> -119.383 | F17: 0 | G17: =E17+F17 -> -119.383 | H17: 0 | I17: 0 | J17: 0 | K17: 0 | L17: 0 | M17: 0
A18: 營運現金流 | B18: US$B | C18: =C13+C14+C15+C16+C17 -> 125.299 | D18: =D13+D14+D15+D16+D17 -> 164.713 | E18: =E13+E14+E15+E16+E17 -> 127.149 | F18: =F13+F14+F15+F16+F17 -> 61.338287 | G18: =G13+G14+G15+G16+G17 -> 188.48729 | H18: =H13+H14+H15+H16+H17 -> 250.15326 | I18: =I13+I14+I15+I16+I17 -> 305.90509 | J18: =J13+J14+J15+J16+J17 -> 365.13683 | ... M18: =M13+M14+M15+M16+M17 -> 496.16157
A19: 資本支出：AI（Thesis；首期含指引下限補足） | B19: US$B | F19: =Thesis!F52 -> 55.670972 | G19: =F19 -> 55.670972 | H19: =Thesis!H52 -> 235.59252 | I19: =Thesis!I52 -> 248.50246 | J19: =Thesis!J52 -> 211.47927 | K19: =Thesis!K52 -> 184.14304 | L19: =Thesis!L52 -> 168.80411 | M19: =Thesis!M52 -> 172.2561
A20: 資本支出：非 AI（Seg） | B20: US$B | F20: =Seg!F34 -> 12.376028 | G20: =F20 -> 12.376028 | H20: =Seg!H34 -> 55.445894 | I20: =Seg!I34 -> 70.417358 | J20: =Seg!J34 -> 83.612122 | K20: =Seg!K34 -> 91.200064 | L20: =Seg!L34 -> 98.462953 | M20: =Seg!M34 -> 106.31635
A21: 資本支出合計 | B21: US$B | C21: =Q!J46 -> 52.535 | D21: =Q!K46 -> 91.447 | E21: =Q!L46 -> 131.953 | F21: =F19+F20 -> 68.047 | G21: =E21+F21 -> 200 | H21: =H19+H20 -> 291.03842 | I21: =I19+I20 -> 318.91982 | J21: =J19+J20 -> 295.09139 | K21: =K19+K20 -> 275.34311 | L21: =L19+L20 -> 267.26706 | M21: =M19+M20 -> 278.57244
A22: 融資租賃本金 | B22: US$B | E22: =lease_1H -> 0.943 | F22: =lease_2H -> 0.103 | G22: =E22+F22 -> 1.046 | H22: =lease_27 -> 0.387 | I22: =lease_28 -> 0.377 | J22: =lease_29 -> 0.356 | K22: =lease_30 -> 0.285 | L22: =lease_31 -> 0.25 | M22: =lease_32 -> 0.25 | N22: 9M26：1H 0.840（10-Q 附註 4）＋Q3 推估 0.103 [Derived]；FY2024–25 未列（公司 FCF 定義不扣）
A23: 自由現金流（營運現金 − 資本支出 − 融資租賃本金） | B23: US$B | C23: =C18-C21-N(C22) -> 72.764 | D23: =D18-D21-N(D22) -> 73.266 | E23: =E18-E21-N(E22) -> -5.747 | F23: =F18-F21-N(F22) -> -6.8117129 | G23: =G18-G21-N(G22) -> -12.558713 | H23: =H18-H21-N(H22) -> -41.272152 | I23: =I18-I21-N(I22) -> -13.391726 | J23: =J18-J21-N(J22) -> 69.689444 | ... M23: =M18-M21-N(M22) -> 217.33912
A24: 普通股股利 | B24: US$B | C24: =Q!J50 -> 7.363 | D24: =Q!K50 -> 10.049 | E24: =Q!L50-pref_paid_1H -> 7.866 | F24: =dps/4*sh_out -> 2.70468 | G24: =E24+F24 -> 10.57068 | H24: =dps*(1+dps_g)^(2027-2026)*PL!F63 -> 11.491802 | I24: =dps*(1+dps_g)^(2028-2026)*PL!H63 -> 12.142709 | J24: =dps*(1+dps_g)^(2029-2026)*PL!I63 -> 12.868709 | K24: =dps*(1+dps_g)^(2030-2026)*PL!J63 -> 13.665955 | L24: =dps*(1+dps_g)^(2031-2026)*PL!K63 -> 14.455163 | M24: =dps*(1+dps_g)^(2032-2026)*PL!L63 -> 15.294137 | N24: 9M26＝新聞稿股利支付 − 已付特別股股利 0.301；Q4 26＝0.22 × 流通股；之後每股 +5%／年 × 期初稀釋股數（避免與回購循環）
A25: 特別股股利 | B25: US$B | E25: =PL!E61 -> 0.384 | F25: =PL!F61 -> 0.301 | G25: =PL!G61 -> 0.685 | H25: =PL!H61 -> 1.203 | I25: =PL!I61 -> 1.203 | J25: =PL!J61 -> 0.602 | K25: =PL!K61 -> 0 | L25: =PL!L61 -> 0 | M25: =PL!M61 -> 0
A26: 自由現金流扣股利 | B26: US$B | C26: =C23-C24-N(C25) -> 65.401 | D26: =D23-D24-N(D25) -> 63.217 | E26: =E23-E24-N(E25) -> -13.997 | F26: =F23-F24-N(F25) -> -9.8173929 | G26: =G23-G24-N(G25) -> -23.814393 | H26: =H23-H24-N(H25) -> -53.966954 | I26: =I23-I24-N(I25) -> -26.737435 | J26: =J23-J24-N(J25) -> 56.218735 | ... M26: =M23-M24-N(M25) -> 202.04499
A27: 策略投資（Anthropic 出資；9M26 含 Wiz、Intersect 收購） | B27: US$B | E27: =anth_1H -> 57.267 | F27: =anth_2H -> 1.111 | G27: =E27+F27 -> 58.378 | H27: =anth_27 -> 4.444 | I27: =anth_28 -> 4.444 | J27: =anth_29 -> 4.444 | K27: =anth_30 -> 4.444 | L27: =anth_31 -> 0 | M27: =anth_32 -> 0 | N27: 9M26：非上市證券 − 出售＋收購＋其他投資（新聞稿年初至今）[Derived]；投資活動，不在自由現金流
A28: 債務到期償還 | B28: US$B | E28: =mat_1H -> 8.879 | F28: =mat_2H -> 0 | G28: =E28+F28 -> 8.879 | H28: =mat_27 -> 1 | I28: =mat_28 -> 2.676 | J28: =mat_29 -> 1.764 | K28: =mat_30 -> 7.186 | L28: =mat_31 -> 5 | M28: =mat_32 -> 5 | N28: 9M26：新聞稿償還債務 [Interested-party]
A29: 已發行新債 | B29: US$B | E29: =newd_1H -> 85.222 | F29: =debt_new_2h -> 0 | G29: =E29+F29 -> 85.222 | H29: 0 | I29: 0 | J29: 0 | K29: 0 | L29: 0 | M29: 0 | N29: 9M26：發債淨額 85.2（新聞稿；含 Q3 票據 28.7）；Q4 26：尚無公告
A30: 股權發行（普通股＋強制轉換特別股，淨額） | B30: US$B | E30: =eq_1H -> 61.933 | F30: 0 | G30: =E30+F30 -> 61.933 | H30: 0 | I30: 0 | J30: 0 | K30: 0 | L30: 0 | M30: 0 | N30: C4：9M26 普通股 42.9（含 Q3 ATM 12.4）＋特別股 19.1 [Interested-party]；ATM 剩餘 27.6 與代扣稅不建模
A31: 期初現金（現金＋債權類有價證券） | B31: US$B | E31: =cash_ye25 -> 120.53 | F31: =E36 -> 174.698 | H31: =F36 -> 163.76961 | I31: =H36 -> 87.355653 | J31: =I36 -> 50 | K31: =J36 -> 83.007735 | L31: =K36 -> 180.35566 | M31: =L36 -> 330.58556
A32: 其他（9M26 實績差額：代扣稅、出售合併個體權益、匯率、有價證券權益部分；預測期 0） | B32: US$B | E32: =cash_0-(E31+E23-E24-E25-E27-E28+E29+E30) -> -12.844 | F32: 0 | H32: 0 | I32: 0 | J32: 0 | K32: 0 | L32: 0 | M32: 0
A33: 回購前現金 | B33: US$B | E33: =E31+E23-E24-E25-E27-E28+E29+E30+E32 -> 174.698 | F33: =F31+F23-F24-F25-F27-F28+F29+F30+F32 -> 163.76961 | H33: =H31+H23-H24-H25-H27-H28+H29+H30+H32 -> 104.35865 | I33: =I31+I23-I24-I25-I27-I28+I29+I30+I32 -> 53.498218 | J33: =J31+J23-J24-J25-J27-J28+J29+J30+J32 -> 100.01074 | K33: =K31+K23-K24-K25-K27-K28+K29+K30+K32 -> 197.35866 | L33: =L31+L23-L24-L25-L27-L28+L29+L30+L32 -> 347.58856 | M33: =M31+M23-M24-M25-M27-M28+M29+M30+M32 -> 527.63055
A34: 回購 | B34: US$B | E34: =Q!L49 -> 0 | F34: 0 | G34: =E34+F34 -> 0 | H34: =MAX(0,MIN(bb_t,H33-min_cash)) -> 17.003 | I34: =MAX(0,MIN(bb_t,I33-min_cash)) -> 3.4982184 | J34: =MAX(0,MIN(bb_t,J33-min_cash)) -> 17.003 | K34: =MAX(0,MIN(bb_t,K33-min_cash)) -> 17.003 | L34: =MAX(0,MIN(bb_t,L33-min_cash)) -> 17.003 | M34: =MAX(0,MIN(bb_t,M33-min_cash)) -> 17.003 | N34: Q4 26＝0（暫停，C4；9M 回購 0）；之後＝MIN(回購目標, 回購前現金 − 最低現金)
A35: 新增舉債（現金低於最低現金時） | B35: US$B | E35: 0 | F35: =MAX(0,min_cash-(F33-F34)) -> 0 | G35: =E35+F35 -> 0 | H35: =MAX(0,min_cash-(H33-H34)) -> 0 | I35: =MAX(0,min_cash-(I33-I34)) -> 0 | J35: =MAX(0,min_cash-(J33-J34)) -> 0 | K35: =MAX(0,min_cash-(K33-K34)) -> 0 | L35: =MAX(0,min_cash-(L33-L34)) -> 0 | M35: =MAX(0,min_cash-(M33-M34)) -> 0
A36: 期末現金（現金＋債權類有價證券） | B36: US$B | E36: =E33-E34+E35 -> 174.698 | F36: =F33-F34+F35 -> 163.76961 | H36: =H33-H34+H35 -> 87.355653 | I36: =I33-I34+I35 -> 50 | J36: =J33-J34+J35 -> 83.007735 | K36: =K33-K34+K35 -> 180.35566 | L36: =L33-L34+L35 -> 330.58556 | M36: =M33-M34+M35 -> 510.62755
A37: 檢查：9M26 期末現金 − 2026-09-30（新聞稿推導；應為 0） | B37: US$B | E37: =E36-cash_0 -> 0
A38: 期初債務 | B38: US$B | E38: =debt_ye25 -> 49.085 | F38: =E39 -> 126.455 | H38: =F39 -> 126.455 | I38: =H39 -> 125.455 | J38: =I39 -> 122.779 | K38: =J39 -> 121.015 | L38: =K39 -> 113.829 | M38: =L39 -> 108.829 | N38: 2025-12-31 面額 49.085（事實總帳 debt.face.fy2025）
A39: 期末債務 | B39: US$B | E39: =debt_0 -> 126.455 | F39: =F38-F28+F29+F35 -> 126.455 | H39: =H38-H28+H29+H35 -> 125.455 | I39: =I38-I28+I29+I35 -> 122.779 | J39: =J38-J28+J29+J35 -> 121.015 | K39: =K38-K28+K29+K35 -> 113.829 | L39: =L38-L28+L29+L35 -> 108.829 | M39: =M38-M28+M29+M35 -> 103.829 | N39: 9M26＝6/30 面額＋Q3 發債 − Q3 償還（推導；10-Q 尚未提供）
A40: 淨現金（現金 − 債務） | B40: US$B | E40: =E36-E39 -> 48.243 | F40: =F36-F39 -> 37.314607 | H40: =H36-H39 -> -38.099347 | I40: =I36-I39 -> -72.779 | J40: =J36-J39 -> -38.007265 | K40: =K36-K39 -> 66.526665 | L40: =L36-L39 -> 221.75656 | M40: =M36-M39 -> 406.79855
A41: 回購均價（評價日股價 × (1＋ke)^年數） | B41: US$ | F41: =px_val -> 344.08 | H41: =px_val*(1+ke)^(2027+mid-t_val) -> 371.98329 | I41: =px_val*(1+ke)^(2028+mid-t_val) -> 412.73892 | J41: =px_val*(1+ke)^(2029+mid-t_val) -> 457.95986 | K41: =px_val*(1+ke)^(2030+mid-t_val) -> 508.13535 | L41: =px_val*(1+ke)^(2031+mid-t_val) -> 563.80823 | M41: =px_val*(1+ke)^(2032+mid-t_val) -> 625.58079
A43: 情境 B（近四季成長收斂；基準）
A44: 項目 | B44: 單位 | C44: FY2024A | D44: FY2025A | E44: 9M26A | F44: Q4 26E | G44: FY2026E | H44: FY2027E | I44: FY2028E | J44: FY2029E | K44: FY2030E | L44: FY2031E | M44: FY2032E | N44: 說明
A45: 淨利 | B45: US$B | C45: =PL!C118 -> 100.118 | D45: =PL!D118 -> 132.17 | E45: =PL!E118 -> 201.239 | F45: =PL!F118 -> 33.511515 | G45: =PL!G118 -> 234.75051 | H45: =PL!H118 -> 136.96379 | I45: =PL!I118 -> 138.20302 | J45: =PL!J118 -> 141.55457 | ... M45: =PL!M118 -> 152.91436
A46: 折舊 | B46: US$B | C46: =PL!C103 -> 15.311 | D46: =PL!D103 -> 21.136 | E46: =PL!E103 -> 21.955 | F46: =PL!F103 -> 13.728285 | G46: =PL!G103 -> 35.683285 | H46: =PL!H103 -> 64.142437 | I46: =PL!I103 -> 101.95063 | J46: =PL!J103 -> 140.17989 | ... M46: =PL!M103 -> 224.85874
A47: 股權報酬（非現金） | B47: US$B | C47: =PL!C127 -> 22.785 | D47: =PL!D127 -> 24.953 | E47: =PL!E127 -> 23.338 | F47: =PL!F127 -> 9.3914872 | G47: =PL!G127 -> 32.729487 | H47: =PL!H127 -> 40.712592 | I47: =PL!I127 -> 48.777488 | J47: =PL!J127 -> 56.004321 | ... M47: =PL!M127 -> 70.845799
A48: 營運資金變動（流入＋） | B48: US$B | F48: =wc_2h -> 4.707 | G48: =F48 -> 4.707 | H48: =wc_k*(PL!H83-PL!G83) -> 1.5014554 | I48: =wc_k*(PL!I83-PL!H83) -> 1.4629346 | J48: =wc_k*(PL!J83-PL!I83) -> 1.3109141 | K48: =wc_k*(PL!K83-PL!J83) -> 0.88788969 | L48: =wc_k*(PL!L83-PL!K83) -> 0.89536629 | M48: =wc_k*(PL!M83-PL!L83) -> 0.90891897 | N48: Q4 26＝上一年度同期實際（2025Q4，C14）；之後＝營收增量 × wc_k
A49: 其他非現金調整（實績差額：權益證券利益迴轉、遞延稅等） | B49: US$B | C49: =Q!J45-C45-C46-C47 -> -12.915 | D49: =Q!K45-D45-D46-D47 -> -13.546 | E49: =Q!L45-E45-E46-E47 -> -119.383 | F49: 0 | G49: =E49+F49 -> -119.383 | H49: 0 | I49: 0 | J49: 0 | K49: 0 | L49: 0 | M49: 0
A50: 營運現金流 | B50: US$B | C50: =C45+C46+C47+C48+C49 -> 125.299 | D50: =D45+D46+D47+D48+D49 -> 164.713 | E50: =E45+E46+E47+E48+E49 -> 127.149 | F50: =F45+F46+F47+F48+F49 -> 61.338287 | G50: =G45+G46+G47+G48+G49 -> 188.48729 | H50: =H45+H46+H47+H48+H49 -> 243.32028 | I50: =I45+I46+I47+I48+I49 -> 290.39407 | J50: =J45+J46+J47+J48+J49 -> 339.0497 | ... M50: =M45+M46+M47+M48+M49 -> 449.52782
A51: 資本支出：AI（Thesis；首期含指引下限補足） | B51: US$B | F51: =Thesis!F52 -> 55.670972 | G51: =F51 -> 55.670972 | H51: =Thesis!H52 -> 235.59252 | I51: =Thesis!I52 -> 248.50246 | J51: =Thesis!J52 -> 211.47927 | K51: =Thesis!K52 -> 184.14304 | L51: =Thesis!L52 -> 168.80411 | M51: =Thesis!M52 -> 172.2561
A52: 資本支出：非 AI（Seg） | B52: US$B | F52: =Seg!F70 -> 12.376028 | G52: =F52 -> 12.376028 | H52: =Seg!H70 -> 54.772619 | I52: =Seg!I70 -> 68.896375 | J52: =Seg!J70 -> 81.081606 | K52: =Seg!K70 -> 87.526495 | L52: =Seg!L70 -> 94.495499 | M52: =Seg!M70 -> 102.0315
A53: 資本支出合計 | B53: US$B | C53: =Q!J46 -> 52.535 | D53: =Q!K46 -> 91.447 | E53: =Q!L46 -> 131.953 | F53: =F51+F52 -> 68.047 | G53: =E53+F53 -> 200 | H53: =H51+H52 -> 290.36514 | I53: =I51+I52 -> 317.39884 | J53: =J51+J52 -> 292.56087 | K53: =K51+K52 -> 271.66954 | L53: =L51+L52 -> 263.29961 | M53: =M51+M52 -> 274.28759
A54: 融資租賃本金 | B54: US$B | E54: =lease_1H -> 0.943 | F54: =lease_2H -> 0.103 | G54: =E54+F54 -> 1.046 | H54: =lease_27 -> 0.387 | I54: =lease_28 -> 0.377 | J54: =lease_29 -> 0.356 | K54: =lease_30 -> 0.285 | L54: =lease_31 -> 0.25 | M54: =lease_32 -> 0.25 | N54: 9M26：1H 0.840（10-Q 附註 4）＋Q3 推估 0.103 [Derived]；FY2024–25 未列（公司 FCF 定義不扣）
A55: 自由現金流（營運現金 − 資本支出 − 融資租賃本金） | B55: US$B | C55: =C50-C53-N(C54) -> 72.764 | D55: =D50-D53-N(D54) -> 73.266 | E55: =E50-E53-N(E54) -> -5.747 | F55: =F50-F53-N(F54) -> -6.8117129 | G55: =G50-G53-N(G54) -> -12.558713 | H55: =H50-H53-N(H54) -> -47.431862 | I55: =I50-I53-N(I54) -> -27.381765 | J55: =J50-J53-N(J54) -> 46.132823 | ... M55: =M50-M53-N(M54) -> 174.99023
A56: 普通股股利 | B56: US$B | C56: =Q!J50 -> 7.363 | D56: =Q!K50 -> 10.049 | E56: =Q!L50-pref_paid_1H -> 7.866 | F56: =dps/4*sh_out -> 2.70468 | G56: =E56+F56 -> 10.57068 | H56: =dps*(1+dps_g)^(2027-2026)*PL!F122 -> 11.491802 | I56: =dps*(1+dps_g)^(2028-2026)*PL!H122 -> 12.142709 | J56: =dps*(1+dps_g)^(2029-2026)*PL!I122 -> 12.877343 | K56: =dps*(1+dps_g)^(2030-2026)*PL!J122 -> 13.675111 | L56: =dps*(1+dps_g)^(2031-2026)*PL!K122 -> 14.464874 | M56: =dps*(1+dps_g)^(2032-2026)*PL!L122 -> 15.304435 | N56: 9M26＝新聞稿股利支付 − 已付特別股股利 0.301；Q4 26＝0.22 × 流通股；之後每股 +5%／年 × 期初稀釋股數（避免與回購循環）
A57: 特別股股利 | B57: US$B | E57: =PL!E120 -> 0.384 | F57: =PL!F120 -> 0.301 | G57: =PL!G120 -> 0.685 | H57: =PL!H120 -> 1.203 | I57: =PL!I120 -> 1.203 | J57: =PL!J120 -> 0.602 | K57: =PL!K120 -> 0 | L57: =PL!L120 -> 0 | M57: =PL!M120 -> 0
A58: 自由現金流扣股利 | B58: US$B | C58: =C55-C56-N(C57) -> 65.401 | D58: =D55-D56-N(D57) -> 63.217 | E58: =E55-E56-N(E57) -> -13.997 | F58: =F55-F56-N(F57) -> -9.8173929 | G58: =G55-G56-N(G57) -> -23.814393 | H58: =H55-H56-N(H57) -> -60.126664 | I58: =I55-I56-N(I57) -> -40.727474 | J58: =J55-J56-N(J57) -> 32.65348 | ... M58: =M55-M56-N(M57) -> 159.68579
A59: 策略投資（Anthropic 出資；9M26 含 Wiz、Intersect 收購） | B59: US$B | E59: =anth_1H -> 57.267 | F59: =anth_2H -> 1.111 | G59: =E59+F59 -> 58.378 | H59: =anth_27 -> 4.444 | I59: =anth_28 -> 4.444 | J59: =anth_29 -> 4.444 | K59: =anth_30 -> 4.444 | L59: =anth_31 -> 0 | M59: =anth_32 -> 0 | N59: 9M26：非上市證券 − 出售＋收購＋其他投資（新聞稿年初至今）[Derived]；投資活動，不在自由現金流
A60: 債務到期償還 | B60: US$B | E60: =mat_1H -> 8.879 | F60: =mat_2H -> 0 | G60: =E60+F60 -> 8.879 | H60: =mat_27 -> 1 | I60: =mat_28 -> 2.676 | J60: =mat_29 -> 1.764 | K60: =mat_30 -> 7.186 | L60: =mat_31 -> 5 | M60: =mat_32 -> 5 | N60: 9M26：新聞稿償還債務 [Interested-party]
A61: 已發行新債 | B61: US$B | E61: =newd_1H -> 85.222 | F61: =debt_new_2h -> 0 | G61: =E61+F61 -> 85.222 | H61: 0 | I61: 0 | J61: 0 | K61: 0 | L61: 0 | M61: 0 | N61: 9M26：發債淨額 85.2（新聞稿；含 Q3 票據 28.7）；Q4 26：尚無公告
A62: 股權發行（普通股＋強制轉換特別股，淨額） | B62: US$B | E62: =eq_1H -> 61.933 | F62: 0 | G62: =E62+F62 -> 61.933 | H62: 0 | I62: 0 | J62: 0 | K62: 0 | L62: 0 | M62: 0 | N62: C4：9M26 普通股 42.9（含 Q3 ATM 12.4）＋特別股 19.1 [Interested-party]；ATM 剩餘 27.6 與代扣稅不建模
A63: 期初現金（現金＋債權類有價證券） | B63: US$B | E63: =cash_ye25 -> 120.53 | F63: =E68 -> 174.698 | H63: =F68 -> 163.76961 | I63: =H68 -> 81.195943 | J63: =I68 -> 50 | K63: =J68 -> 59.44248 | L63: =K68 -> 122.1763 | M63: =L68 -> 234.16964
A64: 其他（9M26 實績差額：代扣稅、出售合併個體權益、匯率、有價證券權益部分；預測期 0） | B64: US$B | E64: =cash_0-(E63+E55-E56-E57-E59-E60+E61+E62) -> -12.844 | F64: 0 | H64: 0 | I64: 0 | J64: 0 | K64: 0 | L64: 0 | M64: 0
A65: 回購前現金 | B65: US$B | E65: =E63+E55-E56-E57-E59-E60+E61+E62+E64 -> 174.698 | F65: =F63+F55-F56-F57-F59-F60+F61+F62+F64 -> 163.76961 | H65: =H63+H55-H56-H57-H59-H60+H61+H62+H64 -> 98.198943 | I65: =I63+I55-I56-I57-I59-I60+I61+I62+I64 -> 33.34847 | J65: =J63+J55-J56-J57-J59-J60+J61+J62+J64 -> 76.44548 | K65: =K63+K55-K56-K57-K59-K60+K61+K62+K64 -> 139.1793 | L65: =L63+L55-L56-L57-L59-L60+L61+L62+L64 -> 251.17264 | M65: =M63+M55-M56-M57-M59-M60+M61+M62+M64 -> 388.85544
A66: 回購 | B66: US$B | E66: =Q!L49 -> 0 | F66: 0 | G66: =E66+F66 -> 0 | H66: =MAX(0,MIN(bb_t,H65-min_cash)) -> 17.003 | I66: =MAX(0,MIN(bb_t,I65-min_cash)) -> 0 | J66: =MAX(0,MIN(bb_t,J65-min_cash)) -> 17.003 | K66: =MAX(0,MIN(bb_t,K65-min_cash)) -> 17.003 | L66: =MAX(0,MIN(bb_t,L65-min_cash)) -> 17.003 | M66: =MAX(0,MIN(bb_t,M65-min_cash)) -> 17.003 | N66: Q4 26＝0（暫停，C4；9M 回購 0）；之後＝MIN(回購目標, 回購前現金 − 最低現金)
A67: 新增舉債（現金低於最低現金時） | B67: US$B | E67: 0 | F67: =MAX(0,min_cash-(F65-F66)) -> 0 | G67: =E67+F67 -> 0 | H67: =MAX(0,min_cash-(H65-H66)) -> 0 | I67: =MAX(0,min_cash-(I65-I66)) -> 16.65153 | J67: =MAX(0,min_cash-(J65-J66)) -> 0 | K67: =MAX(0,min_cash-(K65-K66)) -> 0 | L67: =MAX(0,min_cash-(L65-L66)) -> 0 | M67: =MAX(0,min_cash-(M65-M66)) -> 0
A68: 期末現金（現金＋債權類有價證券） | B68: US$B | E68: =E65-E66+E67 -> 174.698 | F68: =F65-F66+F67 -> 163.76961 | H68: =H65-H66+H67 -> 81.195943 | I68: =I65-I66+I67 -> 50 | J68: =J65-J66+J67 -> 59.44248 | K68: =K65-K66+K67 -> 122.1763 | L68: =L65-L66+L67 -> 234.16964 | M68: =M65-M66+M67 -> 371.85244
A69: 檢查：9M26 期末現金 − 2026-09-30（新聞稿推導；應為 0） | B69: US$B | E69: =E68-cash_0 -> 0
A70: 期初債務 | B70: US$B | E70: =debt_ye25 -> 49.085 | F70: =E71 -> 126.455 | H70: =F71 -> 126.455 | I70: =H71 -> 125.455 | J70: =I71 -> 139.43053 | K70: =J71 -> 137.66653 | L70: =K71 -> 130.48053 | M70: =L71 -> 125.48053 | N70: 2025-12-31 面額 49.085（事實總帳 debt.face.fy2025）
A71: 期末債務 | B71: US$B | E71: =debt_0 -> 126.455 | F71: =F70-F60+F61+F67 -> 126.455 | H71: =H70-H60+H61+H67 -> 125.455 | I71: =I70-I60+I61+I67 -> 139.43053 | J71: =J70-J60+J61+J67 -> 137.66653 | K71: =K70-K60+K61+K67 -> 130.48053 | L71: =L70-L60+L61+L67 -> 125.48053 | M71: =M70-M60+M61+M67 -> 120.48053 | N71: 9M26＝6/30 面額＋Q3 發債 − Q3 償還（推導；10-Q 尚未提供）
A72: 淨現金（現金 − 債務） | B72: US$B | E72: =E68-E71 -> 48.243 | F72: =F68-F71 -> 37.314607 | H72: =H68-H71 -> -44.259057 | I72: =I68-I71 -> -89.43053 | J72: =J68-J71 -> -78.22405 | K72: =K68-K71 -> -8.304226 | L72: =L68-L71 -> 108.68911 | M72: =M68-M71 -> 251.37191
A73: 回購均價（評價日股價 × (1＋ke)^年數） | B73: US$ | F73: =px_val -> 344.08 | H73: =px_val*(1+ke)^(2027+mid-t_val) -> 371.98329 | I73: =px_val*(1+ke)^(2028+mid-t_val) -> 412.73892 | J73: =px_val*(1+ke)^(2029+mid-t_val) -> 457.95986 | K73: =px_val*(1+ke)^(2030+mid-t_val) -> 508.13535 | L73: =px_val*(1+ke)^(2031+mid-t_val) -> 563.80823 | M73: =px_val*(1+ke)^(2032+mid-t_val) -> 625.58079
A75: 情境 C（查詢被 AI 助理分流、每次查詢變現下降）
A76: 項目 | B76: 單位 | C76: FY2024A | D76: FY2025A | E76: 9M26A | F76: Q4 26E | G76: FY2026E | H76: FY2027E | I76: FY2028E | J76: FY2029E | K76: FY2030E | L76: FY2031E | M76: FY2032E | N76: 說明
A77: 淨利 | B77: US$B | C77: =PL!C177 -> 100.118 | D77: =PL!D177 -> 132.17 | E77: =PL!E177 -> 201.239 | F77: =PL!F177 -> 33.511515 | G77: =PL!G177 -> 234.75051 | H77: =PL!H177 -> 125.3372 | I77: =PL!I177 -> 112.32386 | J77: =PL!J177 -> 98.831133 | ... M77: =PL!M177 -> 79.568729
A78: 折舊 | B78: US$B | C78: =PL!C162 -> 15.311 | D78: =PL!D162 -> 21.136 | E78: =PL!E162 -> 21.955 | F78: =PL!F162 -> 13.728285 | G78: =PL!G162 -> 35.683285 | H78: =PL!H162 -> 64.109608 | I78: =PL!I162 -> 101.74701 | J78: =PL!J162 -> 139.64207 | ... M78: =PL!M162 -> 222.39529
A79: 股權報酬（非現金） | B79: US$B | C79: =PL!C186 -> 22.785 | D79: =PL!D186 -> 24.953 | E79: =PL!E186 -> 23.338 | F79: =PL!F186 -> 9.3914872 | G79: =PL!G186 -> 32.729487 | H79: =PL!H186 -> 39.300939 | I79: =PL!I186 -> 45.668199 | J79: =PL!J186 -> 50.961805 | ... M79: =PL!M186 -> 62.524896
A80: 營運資金變動（流入＋） | B80: US$B | F80: =wc_2h -> 4.707 | G80: =F80 -> 4.707 | H80: =wc_k*(PL!H142-PL!G142) -> 1.2453881 | I80: =wc_k*(PL!I142-PL!H142) -> 1.1549915 | J80: =wc_k*(PL!J142-PL!I142) -> 0.96023557 | K80: =wc_k*(PL!K142-PL!J142) -> 0.50853448 | L80: =wc_k*(PL!L142-PL!K142) -> 0.79184276 | M80: =wc_k*(PL!M142-PL!L142) -> 0.79711356 | N80: Q4 26＝上一年度同期實際（2025Q4，C14）；之後＝營收增量 × wc_k
A81: 其他非現金調整（實績差額：權益證券利益迴轉、遞延稅等） | B81: US$B | C81: =Q!J45-C77-C78-C79 -> -12.915 | D81: =Q!K45-D77-D78-D79 -> -13.546 | E81: =Q!L45-E77-E78-E79 -> -119.383 | F81: 0 | G81: =E81+F81 -> -119.383 | H81: 0 | I81: 0 | J81: 0 | K81: 0 | L81: 0 | M81: 0
A82: 營運現金流 | B82: US$B | C82: =C77+C78+C79+C80+C81 -> 125.299 | D82: =D77+D78+D79+D80+D81 -> 164.713 | E82: =E77+E78+E79+E80+E81 -> 127.149 | F82: =F77+F78+F79+F80+F81 -> 61.338287 | G82: =G77+G78+G79+G80+G81 -> 188.48729 | H82: =H77+H78+H79+H80+H81 -> 229.99313 | I82: =I77+I78+I79+I80+I81 -> 260.89405 | J82: =J77+J78+J79+J80+J81 -> 290.39524 | ... M82: =M77+M78+M79+M80+M81 -> 365.28603
A83: 資本支出：AI（Thesis；首期含指引下限補足） | B83: US$B | F83: =Thesis!F52 -> 55.670972 | G83: =F83 -> 55.670972 | H83: =Thesis!H52 -> 235.59252 | I83: =Thesis!I52 -> 248.50246 | J83: =Thesis!J52 -> 211.47927 | K83: =Thesis!K52 -> 184.14304 | L83: =Thesis!L52 -> 168.80411 | M83: =Thesis!M52 -> 172.2561
A84: 資本支出：非 AI（Seg） | B84: US$B | F84: =Seg!F106 -> 12.376028 | G84: =F84 -> 12.376028 | H84: =Seg!H106 -> 53.459453 | I84: =Seg!I106 -> 66.004013 | J84: =Seg!J106 -> 76.390893 | K84: =Seg!K106 -> 80.890371 | L84: =Seg!L106 -> 87.328486 | M84: =Seg!M106 -> 94.291121
A85: 資本支出合計 | B85: US$B | C85: =Q!J46 -> 52.535 | D85: =Q!K46 -> 91.447 | E85: =Q!L46 -> 131.953 | F85: =F83+F84 -> 68.047 | G85: =E85+F85 -> 200 | H85: =H83+H84 -> 289.05197 | I85: =I83+I84 -> 314.50647 | J85: =J83+J84 -> 287.87016 | K85: =K83+K84 -> 265.03341 | L85: =L83+L84 -> 256.1326 | M85: =M83+M84 -> 266.54722
A86: 融資租賃本金 | B86: US$B | E86: =lease_1H -> 0.943 | F86: =lease_2H -> 0.103 | G86: =E86+F86 -> 1.046 | H86: =lease_27 -> 0.387 | I86: =lease_28 -> 0.377 | J86: =lease_29 -> 0.356 | K86: =lease_30 -> 0.285 | L86: =lease_31 -> 0.25 | M86: =lease_32 -> 0.25 | N86: 9M26：1H 0.840（10-Q 附註 4）＋Q3 推估 0.103 [Derived]；FY2024–25 未列（公司 FCF 定義不扣）
A87: 自由現金流（營運現金 − 資本支出 − 融資租賃本金） | B87: US$B | C87: =C82-C85-N(C86) -> 72.764 | D87: =D82-D85-N(D86) -> 73.266 | E87: =E82-E85-N(E86) -> -5.747 | F87: =F82-F85-N(F86) -> -6.8117129 | G87: =G82-G85-N(G86) -> -12.558713 | H87: =H82-H85-N(H86) -> -59.445841 | I87: =I82-I85-N(I86) -> -53.98942 | J87: =J82-J85-N(J86) -> 2.1690836 | ... M87: =M82-M85-N(M86) -> 98.48881
A88: 普通股股利 | B88: US$B | C88: =Q!J50 -> 7.363 | D88: =Q!K50 -> 10.049 | E88: =Q!L50-pref_paid_1H -> 7.866 | F88: =dps/4*sh_out -> 2.70468 | G88: =E88+F88 -> 10.57068 | H88: =dps*(1+dps_g)^(2027-2026)*PL!F181 -> 11.491802 | I88: =dps*(1+dps_g)^(2028-2026)*PL!H181 -> 12.142709 | J88: =dps*(1+dps_g)^(2029-2026)*PL!I181 -> 12.877343 | K88: =dps*(1+dps_g)^(2030-2026)*PL!J181 -> 13.714825 | L88: =dps*(1+dps_g)^(2031-2026)*PL!K181 -> 14.50699 | M88: =dps*(1+dps_g)^(2032-2026)*PL!L181 -> 15.349099 | N88: 9M26＝新聞稿股利支付 − 已付特別股股利 0.301；Q4 26＝0.22 × 流通股；之後每股 +5%／年 × 期初稀釋股數（避免與回購循環）
A89: 特別股股利 | B89: US$B | E89: =PL!E179 -> 0.384 | F89: =PL!F179 -> 0.301 | G89: =PL!G179 -> 0.685 | H89: =PL!H179 -> 1.203 | I89: =PL!I179 -> 1.203 | J89: =PL!J179 -> 0.602 | K89: =PL!K179 -> 0 | L89: =PL!L179 -> 0 | M89: =PL!M179 -> 0
A90: 自由現金流扣股利 | B90: US$B | C90: =C87-C88-N(C89) -> 65.401 | D90: =D87-D88-N(D89) -> 63.217 | E90: =E87-E88-N(E89) -> -13.997 | F90: =F87-F88-N(F89) -> -9.8173929 | G90: =G87-G88-N(G89) -> -23.814393 | H90: =H87-H88-N(H89) -> -72.140643 | I90: =I87-I88-N(I89) -> -67.335129 | J90: =J87-J88-N(J89) -> -11.310259 | ... M90: =M87-M88-N(M89) -> 83.139712
A91: 策略投資（Anthropic 出資；9M26 含 Wiz、Intersect 收購） | B91: US$B | E91: =anth_1H -> 57.267 | F91: =anth_2H -> 1.111 | G91: =E91+F91 -> 58.378 | H91: =anth_27 -> 4.444 | I91: =anth_28 -> 4.444 | J91: =anth_29 -> 4.444 | K91: =anth_30 -> 4.444 | L91: =anth_31 -> 0 | M91: =anth_32 -> 0 | N91: 9M26：非上市證券 − 出售＋收購＋其他投資（新聞稿年初至今）[Derived]；投資活動，不在自由現金流
A92: 債務到期償還 | B92: US$B | E92: =mat_1H -> 8.879 | F92: =mat_2H -> 0 | G92: =E92+F92 -> 8.879 | H92: =mat_27 -> 1 | I92: =mat_28 -> 2.676 | J92: =mat_29 -> 1.764 | K92: =mat_30 -> 7.186 | L92: =mat_31 -> 5 | M92: =mat_32 -> 5 | N92: 9M26：新聞稿償還債務 [Interested-party]
A93: 已發行新債 | B93: US$B | E93: =newd_1H -> 85.222 | F93: =debt_new_2h -> 0 | G93: =E93+F93 -> 85.222 | H93: 0 | I93: 0 | J93: 0 | K93: 0 | L93: 0 | M93: 0 | N93: 9M26：發債淨額 85.2（新聞稿；含 Q3 票據 28.7）；Q4 26：尚無公告
A94: 股權發行（普通股＋強制轉換特別股，淨額） | B94: US$B | E94: =eq_1H -> 61.933 | F94: 0 | G94: =E94+F94 -> 61.933 | H94: 0 | I94: 0 | J94: 0 | K94: 0 | L94: 0 | M94: 0 | N94: C4：9M26 普通股 42.9（含 Q3 ATM 12.4）＋特別股 19.1 [Interested-party]；ATM 剩餘 27.6 與代扣稅不建模
A95: 期初現金（現金＋債權類有價證券） | B95: US$B | E95: =cash_ye25 -> 120.53 | F95: =E100 -> 174.698 | H95: =F100 -> 163.76961 | I95: =H100 -> 69.181964 | J95: =I100 -> 50 | K95: =J100 -> 50 | L95: =K100 -> 50.205794 | M95: =L100 -> 93.102643
A96: 其他（9M26 實績差額：代扣稅、出售合併個體權益、匯率、有價證券權益部分；預測期 0） | B96: US$B | E96: =cash_0-(E95+E87-E88-E89-E91-E92+E93+E94) -> -12.844 | F96: 0 | H96: 0 | I96: 0 | J96: 0 | K96: 0 | L96: 0 | M96: 0
A97: 回購前現金 | B97: US$B | E97: =E95+E87-E88-E89-E91-E92+E93+E94+E96 -> 174.698 | F97: =F95+F87-F88-F89-F91-F92+F93+F94+F96 -> 163.76961 | H97: =H95+H87-H88-H89-H91-H92+H93+H94+H96 -> 86.184964 | I97: =I95+I87-I88-I89-I91-I92+I93+I94+I96 -> -5.2731652 | J97: =J95+J87-J88-J89-J91-J92+J93+J94+J96 -> 32.481741 | K97: =K95+K87-K88-K89-K91-K92+K93+K94+K96 -> 67.208794 | L97: =L95+L87-L88-L89-L91-L92+L93+L94+L96 -> 110.10564 | M97: =M95+M87-M88-M89-M91-M92+M93+M94+M96 -> 171.24235
A98: 回購 | B98: US$B | E98: =Q!L49 -> 0 | F98: 0 | G98: =E98+F98 -> 0 | H98: =MAX(0,MIN(bb_t,H97-min_cash)) -> 17.003 | I98: =MAX(0,MIN(bb_t,I97-min_cash)) -> 0 | J98: =MAX(0,MIN(bb_t,J97-min_cash)) -> 0 | K98: =MAX(0,MIN(bb_t,K97-min_cash)) -> 17.003 | L98: =MAX(0,MIN(bb_t,L97-min_cash)) -> 17.003 | M98: =MAX(0,MIN(bb_t,M97-min_cash)) -> 17.003 | N98: Q4 26＝0（暫停，C4；9M 回購 0）；之後＝MIN(回購目標, 回購前現金 − 最低現金)
A99: 新增舉債（現金低於最低現金時） | B99: US$B | E99: 0 | F99: =MAX(0,min_cash-(F97-F98)) -> 0 | G99: =E99+F99 -> 0 | H99: =MAX(0,min_cash-(H97-H98)) -> 0 | I99: =MAX(0,min_cash-(I97-I98)) -> 55.273165 | J99: =MAX(0,min_cash-(J97-J98)) -> 17.518259 | K99: =MAX(0,min_cash-(K97-K98)) -> 0 | L99: =MAX(0,min_cash-(L97-L98)) -> 0 | M99: =MAX(0,min_cash-(M97-M98)) -> 0
A100: 期末現金（現金＋債權類有價證券） | B100: US$B | E100: =E97-E98+E99 -> 174.698 | F100: =F97-F98+F99 -> 163.76961 | H100: =H97-H98+H99 -> 69.181964 | I100: =I97-I98+I99 -> 50 | J100: =J97-J98+J99 -> 50 | K100: =K97-K98+K99 -> 50.205794 | L100: =L97-L98+L99 -> 93.102643 | M100: =M97-M98+M99 -> 154.23935
A101: 檢查：9M26 期末現金 − 2026-09-30（新聞稿推導；應為 0） | B101: US$B | E101: =E100-cash_0 -> 0
A102: 期初債務 | B102: US$B | E102: =debt_ye25 -> 49.085 | F102: =E103 -> 126.455 | H102: =F103 -> 126.455 | I102: =H103 -> 125.455 | J102: =I103 -> 178.05217 | K102: =J103 -> 193.80642 | L102: =K103 -> 186.62042 | M102: =L103 -> 181.62042 | N102: 2025-12-31 面額 49.085（事實總帳 debt.face.fy2025）
A103: 期末債務 | B103: US$B | E103: =debt_0 -> 126.455 | F103: =F102-F92+F93+F99 -> 126.455 | H103: =H102-H92+H93+H99 -> 125.455 | I103: =I102-I92+I93+I99 -> 178.05217 | J103: =J102-J92+J93+J99 -> 193.80642 | K103: =K102-K92+K93+K99 -> 186.62042 | L103: =L102-L92+L93+L99 -> 181.62042 | M103: =M102-M92+M93+M99 -> 176.62042 | N103: 9M26＝6/30 面額＋Q3 發債 − Q3 償還（推導；10-Q 尚未提供）
...

Sheet Val
A1: Val — 目標價（約 12 個月後，2027-10-29）＝DCF 50%＋分部加總（SOTP）50%；情境權重 A 25%／B 50%／C 25%（In 頁，黃底＝判斷題）。分部加總即本模型的 Comparable（在分部層做）。主值＝自用 AI 讀法 2（In 頁 internal_ai_reading），讀法 1 並列
A2: DCF：無槓桿自由現金流（NOPAT＋折舊 − 資本支出＋營運資金；股權報酬視為現金成本、不加回）以 WACC 折現到評價日 2026-09-30（期中慣例），終值＝NOPAT(FY2033) ×(1 − g ÷ RONIC) ÷ (WACC − g)，RONIC＝WACC；以 ke 推到目標時點並扣期間股利。SOTP：目標時點 NTM EBITDA（股權報酬加回，與同業倍數同口徑）× 同業 NTM EV/EBITDA；Cloud AI 用自身 DCF（F3）
A4: 0.3 結論
A5: 項目 | B5: 數值 | C5: 對照 | D5: 對照 | E5: 說明
A6: DCF 目標價（情境加權） | B6: =tp_wA*B109+tp_wB*C109+tp_wC*D109 -> 189.10434
A7: Comparable 目標價（市場主流同業法） | B7: =tp_wA*B153+tp_wB*C153+tp_wC*D153 -> 327.31571 | E7: ＝分部加總（SOTP）情境加權；各分部用各自同業倍數，Cloud AI 用自身 DCF
A8: 目標價（DCF 與 Comparable 加權） | B8: =w_dcf*B6+(1-w_dcf)*B7 -> 258.21003 | E8: ="DCF 權重 "&TEXT(w_dcf,"0%")&"、分部加總 "&TEXT(1-w_dcf,"0%")&"；自用 AI 讀法 "&internal_ai_reading -> DCF 權重 50%、分部加總 50%；自用 AI 讀法 2
A9: 現價（2026-10-28 收盤） | B9: =px -> 324.89 | E9: BigGo Finance、Investing.com（In 頁 px）；財報後盤後約 288–294
A10: 市場共識目標價 | B10: =cons_tp -> 429.12 | E10: StockAnalysis 61 位分析師平均（2026-10-26 更新，財報前）；只作對照
A11: 上檔空間：加權目標價 | B11: =B8/px-1 -> -0.20523862
A12: 上檔空間：Comparable 目標價 | B12: =B7/px-1 -> 0.007466244
A13: 上檔空間級距 | B13: =IF(B11>=0.5,"大於 50%",IF(B11>=0.25,"25%–50%",IF(B11>=0,"0%–25%",IF(B11>-0.25,"0%～−25%",IF(B11>-0.5,"−25%～−50%","小於 −50%"))))) -> 0%～−25% | E13: 以「上檔空間：加權目標價」分六級（Andy 2026-10-25 14:00）
A14: 投資建議 | B14: =IF(B11>=0.5,"強力買進",IF(B11>=0.25,"買進",IF(B11>-0.25,"中立",IF(B11>-0.5,"放空","強力放空")))) -> 中立 | E14: 五級固定規則：≥ +50% 強力買進、+25%～+50% 買進、−25%～+25% 中立、−50%～−25% 放空、≤ −50% 強力放空
A15: 價格帶（DCF 不如預期～順利） | B15: =D109 -> 149.34687 | C15: =B109 -> 218.80981 | E15: B＝C 情境 DCF、C＝A 情境 DCF（皆推到 12 個月後）
A16: 悲觀情境價（C 情境 DCF） | B16: =D109 -> 149.34687 | E16: 地圖「悲觀情境空間」＝本列 ÷ 現價 − 1
A17: 情境目標價（A／B／C；DCF 與分部加總加權） | B17: =w_dcf*B109+(1-w_dcf)*B153 -> 281.86211 | C17: =w_dcf*C109+(1-w_dcf)*C153 -> 262.3499 | D17: =w_dcf*D109+(1-w_dcf)*D153 -> 226.27819
A18: 情境上檔空間（A／B／C） | B18: =B17/px-1 -> -0.13243833 | C18: =C17/px-1 -> -0.19249622 | D18: =D17/px-1 -> -0.30352369
A19: DCF 終值占 EV（A／B／C） | B19: =B100 -> 0.77307908 | C19: =C100 -> 0.78701101 | D19: =D100 -> 0.82762951
A20: 讀法 2（自用 AI 價值中性）：目標價／上檔空間／投資建議 | B20: =w_dcf*(tp_wA*B108+tp_wB*C108+tp_wC*D108)+(1-w_dcf)*(tp_wA*B152+tp_wB*C152+tp_wC*D152) -> 258.21003 | C20: =B20/px-1 -> -0.20523862 | D20: =IF(C20>=0.5,"強力買進",IF(C20>=0.25,"買進",IF(C20>-0.25,"中立",IF(C20>-0.5,"放空","強力放空")))) -> 中立 | E20: 活公式（修正一 F1；主值）
A21: 讀法 1（自用 AI 只計成本）：目標價／上檔空間／投資建議 | B21: =w_dcf*(tp_wA*B107+tp_wB*C107+tp_wC*D107)+(1-w_dcf)*(tp_wA*B151+tp_wB*C151+tp_wC*D151) -> 188.30917 | C21: =B21/px-1 -> -0.42039098 | D21: =IF(C21>=0.5,"強力買進",IF(C21>=0.25,"買進",IF(C21>-0.25,"中立",IF(C21>-0.5,"放空","強力放空")))) -> 放空 | E21: 活公式（敏感度；v0.2.2 與 v0.3 修正前的主值）
A22: 讀法 1／2 的 DCF 目標價（情境加權） | B22: =tp_wA*B107+tp_wB*C107+tp_wC*D107 -> 92.805815 | C22: =tp_wA*B108+tp_wB*C108+tp_wC*D108 -> 189.10434
A23: 讀法 1／2 的分部加總目標價（情境加權） | B23: =tp_wA*B151+tp_wB*C151+tp_wC*D151 -> 283.81253 | C23: =tp_wA*B152+tp_wB*C152+tp_wC*D152 -> 327.31571
A24: 目標價方法 | B24: DCF（無槓桿 FCF、WACC、RONIC＝WACC）50%＋分部加總（各分部同業 NTM EV/EBITDA、Cloud AI 自身 DCF）50%；情境 25／50／25；自用 AI 讀法 2
A25: 檢查：情境權重合計（應為 1） | B25: =ROUND(tp_wA+tp_wB+tp_wC,6) -> 1
A26: 檢查：主值目標價 − 所選讀法的目標價（應為 0） | B26: =B8-IF(internal_ai_reading=2,B20,B21) -> 0
A32: 0.0 折現率（CAPM；修正一 F4：Blume β、約 10 年期 kd、負債含融資租賃）
A33: 項目 | B33: 數值 | E33: 說明
A34: 股權市值 E＝評價日股價 × 流通股 | B34: =px_val*sh_out -> 4230.1195 | E34: v0.3.1：評價日 2026-09-30 收盤 344.08（v0.3 用現價）
A35: 負債 D（債務面額＋融資租賃） | B35: =debt_0+fin_lease -> 129.045
A36: 股東權益成本 ke＝rf＋β × ERP | B36: =rf+beta*erp -> 0.10956307 | E36: ="β（Blume 調整、兩來源中位數）"&TEXT(beta,"0.000") -> β（Blume 調整、兩來源中位數）1.193
A37: 稅後債務成本（約 10 年期） | B37: =kd*(1-tax_w) -> 0.0465088
A38: WACC（＋wacc_adj，Sens 用） | B38: =(B34*ke+B35*B37)/(B34+B35)+wacc_adj -> 0.10769647 | E38: 修正前 11.56%（原始 β 1.288、kd 6.527%）
A39: 永續期新投資報酬 RONIC＝WACC＋ronic_sp | B39: =wacc+ronic_sp -> 0.10769647 | E39: 修正一 F5：RONIC＝WACC（Sens：＋5pt）
A41: 0.1 DCF（無槓桿自由現金流；三情境各一區塊；欄 F＝Q4 26、H–M＝FY2027–FY2032；不含影子效益的「財報口徑」與影子效益分開列）
A42: 情境 A（AI 搜尋擴大變現）
A43: 項目 | E43: 說明 | F43: Q4 26E | H43: FY2027E | I43: FY2028E | J43: FY2029E | K43: FY2030E | L43: FY2031E | M43: FY2032E
A44: 營業利益（財報口徑 EBIT） | F44: =PL!F46 -> 40.136092 | H44: =PL!H46 -> 171.63132 | I44: =PL!I46 -> 185.16426 | J44: =PL!J46 -> 201.63985 | K44: =PL!K46 -> 215.08446 | L44: =PL!L46 -> 220.84329 | M44: =PL!M46 -> 225.27729
A45: NOPAT＝(EBIT＋sbc_add × 股權報酬) ×(1 − 稅率) | F45: =(F44+sbc_add*PL!F68)*(1-tax) -> 33.393229 | H45: =(H44+sbc_add*PL!H68)*(1-tax) -> 142.79725 | I45: =(I44+sbc_add*PL!I68)*(1-tax) -> 154.05666 | J45: =(J44+sbc_add*PL!J68)*(1-tax) -> 167.76436 | K45: =(K44+sbc_add*PL!K68)*(1-tax) -> 178.95027 | L45: =(L44+sbc_add*PL!L68)*(1-tax) -> 183.74162 | M45: =(M44+sbc_add*PL!M68)*(1-tax) -> 187.43071
A46: ＋折舊 | F46: =PL!F44 -> 13.728285 | H46: =PL!H44 -> 64.159269 | I46: =PL!I44 -> 102.05598 | J46: =PL!J44 -> 140.46258 | K46: =PL!K44 -> 172.57423 | L46: =PL!L44 -> 198.25448 | M46: =PL!M44 -> 226.20244
A47: − 資本支出 | F47: =CF!F21 -> 68.047 | H47: =CF!H21 -> 291.03842 | I47: =CF!I21 -> 318.91982 | J47: =CF!J21 -> 295.09139 | K47: =CF!K21 -> 275.34311 | L47: =CF!L21 -> 267.26706 | M47: =CF!M21 -> 278.57244
A48: ＋營運資金變動 | F48: =CF!F16 -> 4.707 | H48: =CF!H16 -> 1.6327442 | I48: =CF!I16 -> 1.6282375 | J48: =CF!J16 -> 1.507773 | K48: =CF!K16 -> 1.1107849 | L48: =CF!L16 -> 0.95267396 | M48: =CF!M16 -> 0.97081125
A49: − Other Bets 自由現金流（營業利益 ×(1 − 稅率)＋折舊 − 資本支出；改以 Waymo 估值計） | E49: 修正二：與分部加總一致，Other Bets 以 ob_val 計，不在 DCF 現金流內 | F49: =PL!F37*(1-tax)+PL!F36-Seg!F33 -> -1.8710801 | H49: =PL!H37*(1-tax)+PL!H36-Seg!H33 -> -7.4867204 | I49: =PL!I37*(1-tax)+PL!I36-Seg!I33 -> -7.4888204 | J49: =PL!J37*(1-tax)+PL!J36-Seg!J33 -> -7.4944503 | K49: =PL!K37*(1-tax)+PL!K36-Seg!K33 -> -7.5100721 | L49: =PL!L37*(1-tax)+PL!L36-Seg!L33 -> -7.5400421 | M49: =PL!M37*(1-tax)+PL!M36-Seg!M33 -> -7.5454102
A50: 無槓桿自由現金流（財報口徑，不含 Other Bets） | E50: 股權報酬視為現金成本（修正一 F2） | F50: =F45+F46-F47+F48-F49 -> -14.347406 | H50: =H45+H46-H47+H48-H49 -> -74.962428 | I50: =I45+I46-I47+I48-I49 -> -53.690115 | J50: =J45+J46-J47+J48-J49 -> 22.13777 | K50: =K45+K46-K47+K48-K49 -> 84.802255 | L50: =L45+L46-L47+L48-L49 -> 123.22175 | M50: =M45+M46-M47+M48-M49 -> 143.57692
A51: 終值用 NOPAT（排除 Other Bets） | E51: 修正三：基礎折舊在 FY2032 仍約 11.4（約 54.5 未攤完）→ 保留在終值 NOPAT | F51: =F45-PL!F37*(1-tax) -> 35.265229 | H51: =H45-PL!H37*(1-tax) -> 150.28525 | I51: =I45-PL!I37*(1-tax) -> 161.54466 | J51: =J45-PL!J37*(1-tax) -> 175.25236 | K51: =K45-PL!K37*(1-tax) -> 186.43827 | L51: =L45-PL!L37*(1-tax) -> 191.22962 | M51: =M45-PL!M37*(1-tax) -> 194.91871
A52: 自用 AI 影子效益＋算力租金加回（稅後；讀法 2 加入） | E52: 修正三：租用算力（SpaceX）與自有自用 MW 同樣以價值中性計，與分部加總一致 | F52: =(PL!F48+Thesis!F69)*(1-tax) -> 3.2526931 | H52: =(PL!H48+Thesis!H69)*(1-tax) -> 33.079327 | I52: =(PL!I48+Thesis!I69)*(1-tax) -> 66.506545 | J52: =(PL!J48+Thesis!J69)*(1-tax) -> 92.439511 | K52: =(PL!K48+Thesis!K69)*(1-tax) -> 110.88719 | L52: =(PL!L48+Thesis!L69)*(1-tax) -> 126.7605 | M52: =(PL!M48+Thesis!M69)*(1-tax) -> 135.62472
A53: 折現年數（評價日 2026-09-30 起，期中） | F53: =t_q4 -> 0.125 | H53: =2027+mid-t_val -> 0.75 | I53: =2028+mid-t_val -> 1.75 | J53: =2029+mid-t_val -> 2.75 | K53: =2030+mid-t_val -> 3.75 | L53: =2031+mid-t_val -> 4.75 | M53: =2032+mid-t_val -> 5.75
A54: 折現因子 1 ÷ (1＋WACC)^年數 | F54: =1/(1+wacc)^F53 -> 0.98729606 | H54: =1/(1+wacc)^H53 -> 0.92615659 | I54: =1/(1+wacc)^I53 -> 0.83611045 | J54: =1/(1+wacc)^J53 -> 0.75481909 | K54: =1/(1+wacc)^K53 -> 0.68143134 | L54: =1/(1+wacc)^L53 -> 0.61517876 | M54: =1/(1+wacc)^M53 -> 0.55536763
A55: 現值（財報口徑） | F55: =F50*F54 -> -14.165138 | H55: =H50*H54 -> -69.426947 | I55: =I50*I54 -> -44.890866 | J55: =J50*J54 -> 16.710012 | K55: =K50*K54 -> 57.786915 | L55: =L50*L54 -> 75.803404 | M55: =M50*M54 -> 79.737976
A56: 現值（影子效益） | F56: =F52*F54 -> 3.2113711 | H56: =H52*H54 -> 30.636637 | I56: =I52*I54 -> 55.606817 | J56: =J52*J54 -> 69.775108 | K56: =K52*K54 -> 75.562005 | L56: =L52*L54 -> 77.980367 | M56: =M52*M54 -> 75.321581
A58: 情境 B（近四季成長收斂；基準）
A59: 項目 | E59: 說明 | F59: Q4 26E | H59: FY2027E | I59: FY2028E | J59: FY2029E | K59: FY2030E | L59: FY2031E | M59: FY2032E
A60: 營業利益（財報口徑 EBIT） | F60: =PL!F105 -> 40.136092 | H60: =PL!H105 -> 164.46654 | I60: =PL!I105 -> 169.04579 | J60: =PL!J105 -> 174.93037 | K60: =PL!K105 -> 176.46405 | L60: =PL!L105 -> 179.4628 | M60: =PL!M105 -> 180.91592
A61: NOPAT＝(EBIT＋sbc_add × 股權報酬) ×(1 − 稅率) | F61: =(F60+sbc_add*PL!F127)*(1-tax) -> 33.393229 | H61: =(H60+sbc_add*PL!H127)*(1-tax) -> 136.83616 | I61: =(I60+sbc_add*PL!I127)*(1-tax) -> 140.6461 | J61: =(J60+sbc_add*PL!J127)*(1-tax) -> 145.54207 | K61: =(K60+sbc_add*PL!K127)*(1-tax) -> 146.81809 | L61: =(L60+sbc_add*PL!L127)*(1-tax) -> 149.31305 | M61: =(M60+sbc_add*PL!M127)*(1-tax) -> 150.52205
A62: ＋折舊 | F62: =PL!F103 -> 13.728285 | H62: =PL!H103 -> 64.142437 | I62: =PL!I103 -> 101.95063 | J62: =PL!J103 -> 140.17989 | K62: =PL!K103 -> 172.00991 | L62: =PL!L103 -> 197.31546 | M62: =PL!M103 -> 224.85874
A63: − 資本支出 | F63: =CF!F53 -> 68.047 | H63: =CF!H53 -> 290.36514 | I63: =CF!I53 -> 317.39884 | J63: =CF!J53 -> 292.56087 | K63: =CF!K53 -> 271.66954 | L63: =CF!L53 -> 263.29961 | M63: =CF!M53 -> 274.28759
A64: ＋營運資金變動 | F64: =CF!F48 -> 4.707 | H64: =CF!H48 -> 1.5014554 | I64: =CF!I48 -> 1.4629346 | J64: =CF!J48 -> 1.3109141 | K64: =CF!K48 -> 0.88788969 | L64: =CF!L48 -> 0.89536629 | M64: =CF!M48 -> 0.90891897
A65: − Other Bets 自由現金流（營業利益 ×(1 − 稅率)＋折舊 − 資本支出；改以 Waymo 估值計） | E65: 修正二：與分部加總一致，Other Bets 以 ob_val 計，不在 DCF 現金流內 | F65: =PL!F96*(1-tax)+PL!F95-Seg!F69 -> -1.8710801 | H65: =PL!H96*(1-tax)+PL!H95-Seg!H69 -> -7.4867204 | I65: =PL!I96*(1-tax)+PL!I95-Seg!I69 -> -7.4888204 | J65: =PL!J96*(1-tax)+PL!J95-Seg!J69 -> -7.4944503 | K65: =PL!K96*(1-tax)+PL!K95-Seg!K69 -> -7.5100721 | L65: =PL!L96*(1-tax)+PL!L95-Seg!L69 -> -7.5400421 | M65: =PL!M96*(1-tax)+PL!M95-Seg!M69 -> -7.5454102
A66: 無槓桿自由現金流（財報口徑，不含 Other Bets） | E66: 股權報酬視為現金成本（修正一 F2） | F66: =F61+F62-F63+F64-F65 -> -14.347406 | H66: =H61+H62-H63+H64-H65 -> -80.398366 | I66: =I61+I62-I63+I64-I65 -> -65.850352 | J66: =J61+J62-J63+J64-J65 -> 1.9664496 | K66: =K61+K62-K63+K64-K65 -> 55.556427 | L66: =L61+L62-L63+L64-L65 -> 91.764309 | M66: =M61+M62-M63+M64-M65 -> 109.54752
A67: 終值用 NOPAT（排除 Other Bets） | E67: 修正三：基礎折舊在 FY2032 仍約 11.4（約 54.5 未攤完）→ 保留在終值 NOPAT | F67: =F61-PL!F96*(1-tax) -> 35.265229 | H67: =H61-PL!H96*(1-tax) -> 144.32416 | I67: =I61-PL!I96*(1-tax) -> 148.1341 | J67: =J61-PL!J96*(1-tax) -> 153.03007 | K67: =K61-PL!K96*(1-tax) -> 154.30609 | L67: =L61-PL!L96*(1-tax) -> 156.80105 | M67: =M61-PL!M96*(1-tax) -> 158.01005
A68: 自用 AI 影子效益＋算力租金加回（稅後；讀法 2 加入） | E68: 修正三：租用算力（SpaceX）與自有自用 MW 同樣以價值中性計，與分部加總一致 | F68: =(PL!F107+Thesis!F69)*(1-tax) -> 3.2526931 | H68: =(PL!H107+Thesis!H69)*(1-tax) -> 33.079327 | I68: =(PL!I107+Thesis!I69)*(1-tax) -> 66.506545 | J68: =(PL!J107+Thesis!J69)*(1-tax) -> 92.439511 | K68: =(PL!K107+Thesis!K69)*(1-tax) -> 110.88719 | L68: =(PL!L107+Thesis!L69)*(1-tax) -> 126.7605 | M68: =(PL!M107+Thesis!M69)*(1-tax) -> 135.62472
A69: 折現年數（評價日 2026-09-30 起，期中） | F69: =t_q4 -> 0.125 | H69: =2027+mid-t_val -> 0.75 | I69: =2028+mid-t_val -> 1.75 | J69: =2029+mid-t_val -> 2.75 | K69: =2030+mid-t_val -> 3.75 | L69: =2031+mid-t_val -> 4.75 | M69: =2032+mid-t_val -> 5.75
A70: 折現因子 1 ÷ (1＋WACC)^年數 | F70: =1/(1+wacc)^F69 -> 0.98729606 | H70: =1/(1+wacc)^H69 -> 0.92615659 | I70: =1/(1+wacc)^I69 -> 0.83611045 | J70: =1/(1+wacc)^J69 -> 0.75481909 | K70: =1/(1+wacc)^K69 -> 0.68143134 | L70: =1/(1+wacc)^L69 -> 0.61517876 | M70: =1/(1+wacc)^M69 -> 0.55536763
A71: 現值（財報口徑） | F71: =F66*F70 -> -14.165138 | H71: =H66*H70 -> -74.461477 | I71: =I66*I70 -> -55.058167 | J71: =J66*J70 -> 1.4843137 | K71: =K66*K70 -> 37.85789 | L71: =L66*L70 -> 56.451454 | M71: =M66*M70 -> 60.839147
A72: 現值（影子效益） | F72: =F68*F70 -> 3.2113711 | H72: =H68*H70 -> 30.636637 | I72: =I68*I70 -> 55.606817 | J72: =J68*J70 -> 69.775108 | K72: =K68*K70 -> 75.562005 | L72: =L68*L70 -> 77.980367 | M72: =M68*M70 -> 75.321581
A74: 情境 C（查詢被 AI 助理分流、每次查詢變現下降）
A75: 項目 | E75: 說明 | F75: Q4 26E | H75: FY2027E | I75: FY2028E | J75: FY2029E | K75: FY2030E | L75: FY2031E | M75: FY2032E
A76: 營業利益（財報口徑 EBIT） | F76: =PL!F164 -> 40.136092 | H76: =PL!H164 -> 150.49227 | I76: =PL!I164 -> 138.39756 | J76: =PL!J164 -> 125.43392 | K76: =PL!K164 -> 106.73426 | L76: =PL!L164 -> 104.74707 | M76: =PL!M164 -> 100.81537
A77: NOPAT＝(EBIT＋sbc_add × 股權報酬) ×(1 − 稅率) | F77: =(F76+sbc_add*PL!F186)*(1-tax) -> 33.393229 | H77: =(H76+sbc_add*PL!H186)*(1-tax) -> 125.20957 | I77: =(I76+sbc_add*PL!I186)*(1-tax) -> 115.14677 | J77: =(J76+sbc_add*PL!J186)*(1-tax) -> 104.36102 | K77: =(K76+sbc_add*PL!K186)*(1-tax) -> 88.8029 | L77: =(L76+sbc_add*PL!L186)*(1-tax) -> 87.14956 | M77: =(M76+sbc_add*PL!M186)*(1-tax) -> 83.878389
A78: ＋折舊 | F78: =PL!F162 -> 13.728285 | H78: =PL!H162 -> 64.109608 | I78: =PL!I162 -> 101.74701 | J78: =PL!J162 -> 139.64207 | K78: =PL!K162 -> 170.95439 | L78: =PL!L162 -> 195.58305 | M78: =PL!M162 -> 222.39529
A79: − 資本支出 | F79: =CF!F85 -> 68.047 | H79: =CF!H85 -> 289.05197 | I79: =CF!I85 -> 314.50647 | J79: =CF!J85 -> 287.87016 | K79: =CF!K85 -> 265.03341 | L79: =CF!L85 -> 256.1326 | M79: =CF!M85 -> 266.54722
A80: ＋營運資金變動 | F80: =CF!F80 -> 4.707 | H80: =CF!H80 -> 1.2453881 | I80: =CF!I80 -> 1.1549915 | J80: =CF!J80 -> 0.96023557 | K80: =CF!K80 -> 0.50853448 | L80: =CF!L80 -> 0.79184276 | M80: =CF!M80 -> 0.79711356
A81: − Other Bets 自由現金流（營業利益 ×(1 − 稅率)＋折舊 − 資本支出；改以 Waymo 估值計） | E81: 修正二：與分部加總一致，Other Bets 以 ob_val 計，不在 DCF 現金流內 | F81: =PL!F155*(1-tax)+PL!F154-Seg!F105 -> -1.8710801 | H81: =PL!H155*(1-tax)+PL!H154-Seg!H105 -> -7.4867204 | I81: =PL!I155*(1-tax)+PL!I154-Seg!I105 -> -7.4888204 | J81: =PL!J155*(1-tax)+PL!J154-Seg!J105 -> -7.4944503 | K81: =PL!K155*(1-tax)+PL!K154-Seg!K105 -> -7.5100721 | L81: =PL!L155*(1-tax)+PL!L154-Seg!L105 -> -7.5400421 | M81: =PL!M155*(1-tax)+PL!M154-Seg!M105 -> -7.5454102
A82: 無槓桿自由現金流（財報口徑，不含 Other Bets） | E82: 股權報酬視為現金成本（修正一 F2） | F82: =F77+F78-F79+F80-F81 -> -14.347406 | H82: =H77+H78-H79+H80-H81 -> -91.000692 | I82: =I77+I78-I79+I80-I81 -> -88.968885 | J82: =J77+J78-J79+J80-J81 -> -35.41238 | K82: =K77+K78-K79+K80-K81 -> 2.7424796 | L82: =L77+L78-L79+L80-L81 -> 34.931896 | M82: =M77+M78-M79+M80-M81 -> 48.068985
A83: 終值用 NOPAT（排除 Other Bets） | E83: 修正三：基礎折舊在 FY2032 仍約 11.4（約 54.5 未攤完）→ 保留在終值 NOPAT | F83: =F77-PL!F155*(1-tax) -> 35.265229 | H83: =H77-PL!H155*(1-tax) -> 132.69757 | I83: =I77-PL!I155*(1-tax) -> 122.63477 | J83: =J77-PL!J155*(1-tax) -> 111.84902 | K83: =K77-PL!K155*(1-tax) -> 96.2909 | L83: =L77-PL!L155*(1-tax) -> 94.63756 | M83: =M77-PL!M155*(1-tax) -> 91.366389
A84: 自用 AI 影子效益＋算力租金加回（稅後；讀法 2 加入） | E84: 修正三：租用算力（SpaceX）與自有自用 MW 同樣以價值中性計，與分部加總一致 | F84: =(PL!F166+Thesis!F69)*(1-tax) -> 3.2526931 | H84: =(PL!H166+Thesis!H69)*(1-tax) -> 33.079327 | I84: =(PL!I166+Thesis!I69)*(1-tax) -> 66.506545 | J84: =(PL!J166+Thesis!J69)*(1-tax) -> 92.439511 | K84: =(PL!K166+Thesis!K69)*(1-tax) -> 110.88719 | L84: =(PL!L166+Thesis!L69)*(1-tax) -> 126.7605 | M84: =(PL!M166+Thesis!M69)*(1-tax) -> 135.62472
A85: 折現年數（評價日 2026-09-30 起，期中） | F85: =t_q4 -> 0.125 | H85: =2027+mid-t_val -> 0.75 | I85: =2028+mid-t_val -> 1.75 | J85: =2029+mid-t_val -> 2.75 | K85: =2030+mid-t_val -> 3.75 | L85: =2031+mid-t_val -> 4.75 | M85: =2032+mid-t_val -> 5.75
A86: 折現因子 1 ÷ (1＋WACC)^年數 | F86: =1/(1+wacc)^F85 -> 0.98729606 | H86: =1/(1+wacc)^H85 -> 0.92615659 | I86: =1/(1+wacc)^I85 -> 0.83611045 | J86: =1/(1+wacc)^J85 -> 0.75481909 | K86: =1/(1+wacc)^K85 -> 0.68143134 | L86: =1/(1+wacc)^L85 -> 0.61517876 | M86: =1/(1+wacc)^M85 -> 0.55536763
A87: 現值（財報口徑） | F87: =F82*F86 -> -14.165138 | H87: =H82*H86 -> -84.280891 | I87: =I82*I86 -> -74.387814 | J87: =J82*J86 -> -26.729941 | K87: =K82*K86 -> 1.8688116 | L87: =L82*L86 -> 21.489361 | M87: =M82*M86 -> 26.695958
A88: 現值（影子效益） | F88: =F84*F86 -> 3.2113711 | H88: =H84*H86 -> 30.636637 | I88: =I84*I86 -> 55.606817 | J88: =J84*J86 -> 69.775108 | K88: =K84*K86 -> 75.562005 | L88: =L84*L86 -> 77.980367 | M88: =M84*M86 -> 75.321581
A90: DCF 彙總
A91: 項目 | B91: 情境 A | C91: 情境 B | D91: 情境 C | E91: 說明
A92: 明確期現值合計（財報口徑） | B92: =SUM(F55:M55) -> 101.55536 | C92: =SUM(F71:M71) -> 12.948024 | D92: =SUM(F87:M87) -> -149.50965
A93: 終值（FY2032 年底，財報口徑） | B93: =IF(tv_alt=1,M50*(1+g_tv)/(wacc-g_tv),M51*(1+g_tv)*(1-g_tv/ronic)/(wacc-g_tv)) -> 1864.1862 | C93: =IF(tv_alt=1,M66*(1+g_tv)/(wacc-g_tv),M67*(1+g_tv)*(1-g_tv/ronic)/(wacc-g_tv)) -> 1511.1948 | D93: =IF(tv_alt=1,M82*(1+g_tv)/(wacc-g_tv),M83*(1+g_tv)*(1-g_tv/ronic)/(wacc-g_tv)) -> 873.82048 | E93: 價值驅動：NOPAT(FY2033) ×(1 − g ÷ RONIC) ÷ (WACC − g)；tv_alt＝1 時改用 FY2032 無槓桿自由現金流 ×(1＋g)
A94: 終值現值（折現年數＝FY2032 期中＋mid） | B94: =B93/(1+wacc)^($M$53+mid) -> 983.69272 | C94: =C93/(1+wacc)^($M$69+mid) -> 797.42645 | D94: =D93/(1+wacc)^($M$85+mid) -> 461.0971
A95: 企業價值 EV（讀法 1：只計自用 AI 成本） | B95: =B92+B94 -> 1085.2481 | C95: =C92+C94 -> 810.37448 | D95: =D92+D94 -> 311.58745
A96: ＋自用 AI 影子效益現值：明確期 | B96: =SUM(F56:M56) -> 388.09389 | C96: =SUM(F72:M72) -> 388.09389 | D96: =SUM(F88:M88) -> 388.09389
