Workbook

Sheet 導覽
A1: Alphabet 收支與評價模型 — Excel 版 v0.2（更新 2026-10-09；與 HTML v0.2 同步；市價截至 2026-10-07 收盤）
A3: 這個活頁簿在回答什麼
A4: 一句話：AI 資本支出有沒有賺到資金成本：每 MW 收入能否覆蓋每 MW 全成本——Alphabet 用客戶預付款支應多少擴張資本支出，剩下的缺口要靠多少債務與新股。
A5: 所有分頁用同一組數字，改任何一個輸入，後面全部會跟著動。
A7: 分頁結構（依模組分組，分頁標籤顏色相同者為同一模組）
A8: 摘要 一頁摘要：結論、與市場共識的差異、現價隱含什麼、驗證點（全部活公式）。
A9: 輸入與假設 所有可調參數（A 情境 → B 產能與收入 → C 利潤率 → D 支出 → E 融資 → F 評價 → G 1H 實際 → H 情境區間運算表 → I 市場共識 → J 季度追蹤輸入）。
A10: 各期收支 類現金流量：來源（含客戶預付）、用途、融資前缺口、期前融資瀑布。
A11: 季度追蹤 焦點季的模型／共識／指引／實際與差距（由年度模型拆分，只用於追蹤；實際數填在輸入與假設 J 區）。
A12: 運營_產能與收入 已連網 MW → 在役 MW → 營收（MW × 每 MW 年收入 × 利用率）；RPO 排程只作對照與產能瓶頸旗標。
A13: 資產負債_既有債務／新債與新股／租賃承諾 類資產負債表：季報債務明細、每期現金與總債務與股數、租賃承諾。
A14: 損益 類損益表（2026＝1H 實際＋下半年模型）。
... A42: DCF 以融資後股數計每股，並加回新股募得現金的現值；EV/EBITDA 用錨定年末淨負債與錨定年末股數。

Sheet 摘要
A1: 一頁摘要 — 結論、與市場的差異、現價隱含什麼、驗證點（全部依輸入連動）
A2: ="模型端＝目前情境：" & CHOOSE(輸入與假設!$C$5,"保守 已交付＋已公開在建","基準 依資本支出指引","積極 依 2027 擴張幅度") & "（預設＝基準）；共識＝data/consensus_googl_20261008.json（2026-10-08）" -> 模型端＝目前情境：基準 依資本支出指引（預設＝基準）；共識＝data/consensus_googl_20261008.json（2026-10-08）
A4: 1｜結論
A5: 結論｜評等代碼（1＝買進、0＝中立、−1＝賣出） | C5: =評價_DCF與目標價!C99 -> -1
A6: 結論｜評等 | C6: =CHOOSE(C5+2,"賣出","中立","買進") -> 賣出
A7: 結論｜點位（加權目標價） | B7: US$ | C7: =評價_DCF與目標價!C51 -> 145.84769
A8: 結論｜現價 | B8: US$ | C8: =輸入與假設!$C$366 -> 350.5
A9: 結論｜空間 | B9: % | C9: =C7/C8-1 -> -0.58388676
A10: 結論｜情境區間（下緣／上緣） | B10: US$ | C10: =評價_DCF與目標價!C104 -> 121.98879 | D10: =評價_DCF與目標價!D104 -> 175.76831
A11: 結論｜方法區間（下緣／上緣） | B11: US$ | C11: =評價_DCF與目標價!C106 -> 143.98668 | D11: =評價_DCF與目標價!D106 -> 145.84769
A12: 結論｜賣出門檻價 | B12: US$ | C12: =評價_DCF與目標價!$C$100 -> 297.925
A13: 結論｜點位 − 賣出門檻 | B13: US$ | C13: =C7-C12 -> -152.07731
A14: 結論｜結論句 | C14: =C6&"：點位 $"&TEXT(C7,"0.0")&"，較現價 $"&TEXT(C8,"0.00")&" "&IF(C9>=0,"高","低")&" "&TEXT(ABS(C9)*100,"0")&"%；情境區間 $"&TEXT(C10,"0.0")&"–$"&TEXT(D10,"0.0")&"，方法區間 $"&TEXT(C11,"0.0")&"–$"&TEXT(D11,"0.0")&"；點位"&IF(C13<0,"低於","高於")&"賣出門檻 $"&TEXT(C12,"0.0")&" 達 $"&TEXT(ABS(C13),"0.0")&"。" -> 賣出：點位 $145.8，較現價 $350.50 低 58%；情境區間 $122.0–$175.8，方法區間 $144.0–$145.8；點位低於賣出門檻 $297.9 達 $152.1。
A15: 結論｜情境判斷句 | C15: =評價_DCF與目標價!C129 -> 情境區間上緣 $175.8 低於現價 $350.50：賣出在三個擴張情境下都成立。
A16: 結論｜投資級句 | C16: =IF(OR(輸入與假設!$C$334="ebitda",輸入與假設!$C$334="leaseAdj"),"需失去投資級才能融資的金額："&IF(SUM(各期收支!C93:G93)>0.05,"$"&TEXT(SUM(各期收支!C93:G93),"0.0")&"bn（五期高息債溢出）","$0")&"；投資級上限＝"&IF(輸入與假設!$C$334="leaseAdj","(總債務＋租賃負債) ≤ "&IF(輸入與假設!$C$335=INT(輸入與假設!$C$335),TEXT(輸入與假設!$C$335,"0"),TEXT(輸入與假設!$C$335,"0.0"))&"×(EBITDA＋租金)","總債務 ≤ "&IF(輸入與假設!$C$335=INT(輸入與假設!$C$335),TEXT(輸入與假設!$C$335,"0"),TEXT(輸入與假設!$C$335,"0.0"))&"× 當期 EBITDA")&"，股權每年 ≤ 現市值 "&IF(ROUND(ABS(輸入與假設!$C$345)*100,4)=INT(ROUND(ABS(輸入與假設!$C$345)*100,4)),TEXT(ROUND(ABS(輸入與假設!$C$345)*100,4),"0"),TEXT(ROUND(ABS(輸入與假設!$C$345)*100,4),"0.0"))&"%"&"。","") -> 需失去投資級才能融資的金額：$0；投資級上限＝(總債務＋租賃負債) ≤ 3×(EBITDA＋租金)，股權每年 ≤ 現市值 5%。
A17: 結論｜調整後槓桿句 | C17: ="調整後槓桿（(債務＋租賃負債) ÷ (EBITDA＋租金)）路徑 "&TEXT(資產負債_新債與新股!C37,"0.0")&"／"&TEXT(資產負債_新債與新股!D37,"0.0")&"／"&TEXT(資產負債_新債與新股!E37,"0.0")&"／"&TEXT(資產負債_新債與新股!F37,"0.0")&"／"&TEXT(資產負債_新債與新股!G37,"0.0")&"×；上限 "&IF(輸入與假設!$C$335=INT(輸入與假設!$C$335),TEXT(輸入與假設!$C$335,"0"),TEXT(輸入與假設!$C$335,"0.0"))&"×，"&IF(MAX(資產負債_新債與新股!$C$37:$G$37)>輸入與假設!$C$335+0.000000001,CHOOSE(MATCH(MAX(資產負債_新債與新股!$C$37:$G$37),資產負債_新債與新股!$C$37:$G$37,0),"2026","2027","2028","2029","2030")&" 超過 "&TEXT(MAX(資產負債_新債與新股!$C$37:$G$37)-輸入與假設!$C$335,"0.0")&"×：需股權或失去投資級。","最小空間 "&TEXT(輸入與假設!$C$335-MAX(資產負債_新債與新股!$C$37:$G$37),"0.0")&"×（"&CHOOSE(MATCH(MAX(資產負債_新債與新股!$C$37:$G$37),資產負債_新債與新股!$C$37:$G$37,0),"2026","2027","2028","2029","2030")&"）。") -> 調整後槓桿（(債務＋租賃負債) ÷ (EBITDA＋租金)）路徑 0.6／0.6／0.5／0.5／0.7×；上限 3×，最小空間 2.3×（2030）。
A18: 結論｜評價口徑敏感度句 | C18: ="評價口徑敏感度："&"WACC 9% $"&TEXT(評價_DCF與目標價!C114,"0.00")&"（"&CHOOSE(評價_DCF與目標價!D114+2,"賣出","中立","買進")&"）"&"、"&"WACC 10% $"&TEXT(評價_DCF與目標價!C115,"0.00")&"（"&CHOOSE(評價_DCF與目標價!D115+2,"賣出","中立","買進")&"）"&"、"&"WACC 11% $"&TEXT(評價_DCF與目標價!C116,"0.00")&"（"&CHOOSE(評價_DCF與目標價!D116+2,"賣出","中立","買進")&"）"&"；"&"非 AI 分部改用公司自身 NTM EV/EBITDA 14.68× $"&TEXT(評價_DCF與目標價!C119,"0.00")&"（"&CHOOSE(評價_DCF與目標價!D119+2,"賣出","中立","買進")&"）"&"、"&"AI 雲端 15× $"&TEXT(評價_DCF與目標價!C120,"0.00")&"（"&CHOOSE(評價_DCF與目標價!D120+2,"賣出","中立","買進")&"）"&"、"&"組合：WACC 9%＋非 AI 自身倍數＋AI 15× $"&TEXT(評價_DCF與目標價!C121,"0.00")&"（"&CHOOSE(評價_DCF與目標價!D121+2,"賣出","中立","買進")&"）"&"；評等翻轉點："&"WACC 約 "&TEXT(評價_DCF與目標價!C122*100,"0.0")&"%（ERP "&TEXT(評價_DCF與目標價!D122*100,"0.00")&"%）以下由「賣出」轉為「中立」"&"。" -> 評價口徑敏感度：WACC 9% $177.51（賣出）、WACC 10% $162.81（賣出）、WACC 11% $151.39（賣出）；非 AI 分部改用公司自身 NTM EV/EBITDA 14.68× $180.99（賣出）、AI 雲端 15× $161.17（賣出）、組合：WACC 9%＋非 AI 自身倍數＋AI 15× $232.52（賣出）；評等翻轉點：WACC 約 5.7%（ERP 0.29%）以下由「賣出」轉為「中立」。
A19: 結論｜終值占比規則句 | C19: ="評等規則：買進須空間 ≥ +"&IF(ROUND(ABS(輸入與假設!$C$457)*100,4)=INT(ROUND(ABS(輸入與假設!$C$457)*100,4)),TEXT(ROUND(ABS(輸入與假設!$C$457)*100,4),"0"),TEXT(ROUND(ABS(輸入與假設!$C$457)*100,4),"0.0"))&"%"&" 且終值占 EV < "&IF(ROUND(ABS(輸入與假設!$C$458)*100,4)=INT(ROUND(ABS(輸入與假設!$C$458)*100,4)),TEXT(ROUND(ABS(輸入與假設!$C$458)*100,4),"0"),TEXT(ROUND(ABS(輸入與假設!$C$458)*100,4),"0.0"))&"%"&"；目前終值占 EV "&TEXT(評價_DCF與目標價!C97*100,"0")&"%"&IF(評價_DCF與目標價!C97>=輸入與假設!$C$458,"，此規則下只可能「賣出」或「中立」","")&"（規則是否修改待 Andy 決定）。" -> 評等規則：買進須空間 ≥ +25% 且終值占 EV < 90%；目前終值占 EV 116%，此規則下只可能「賣出」或「中立」（規則是否修改待 Andy 決定）。
A20: 結論｜兩種讀法句 | C20: ="兩種讀法（自用 AI）：讀法 1（影子收入不進評價）$"&TEXT(評價_DCF與目標價!C51,"0.00")&"；讀法 2（自用 AI 價值中性：自用 MW 以 k＝1 計影子收入並進評價）$"&TEXT(評價_DCF與目標價!C73,"0.00")&"；差額 "&IF(評價_DCF與目標價!C73-評價_DCF與目標價!C51<0,"−","+")&"$"&TEXT(ABS(評價_DCF與目標價!C73-評價_DCF與目標價!C51),"0.00")&"。主值取哪一個是 Andy 的判斷（待決）。" -> 兩種讀法（自用 AI）：讀法 1（影子收入不進評價）$145.85；讀法 2（自用 AI 價值中性：自用 MW 以 k＝1 計影子收入並進評價）$218.47；差額 +$72.62。主值取哪一個是 Andy 的判斷（待決）。
A21: 結論｜對外比例句 | C21: ="對外比例無揭露（目前 "&TEXT(輸入與假設!$C$263*100,"0")&"%，[Assumed]），是最大不確定："&TEXT(評價_DCF與目標價!C112*100,"0")&"% → $"&TEXT(評價_DCF與目標價!D112,"0.00")&"、"&TEXT(評價_DCF與目標價!C113*100,"0")&"% → $"&TEXT(評價_DCF與目標價!D113,"0.00")&"（基準 $"&TEXT(評價_DCF與目標價!C51,"0.00")&"）。" -> 對外比例無揭露（目前 30%，[Assumed]），是最大不確定：10% → $99.72、50% → $179.43（基準 $145.85）。
A22: 結論｜主命題句 | C22: ="主命題（AI 資本支出有沒有賺到資金成本）：2029 對外 AI ROIC "&TEXT(AI增量報酬!F23*100,"0.0")&"% vs WACC "&TEXT(輸入與假設!$C$393*100,"0.0")&"%（"&IF(AI增量報酬!F25<0,"−","+")&TEXT(ABS(AI增量報酬!F25)*100,"0.0")&"pt）；打平 k "&TEXT(AI增量報酬!C29,"0.00")&"（目前 "&TEXT(輸入與假設!$C$58,"0.00")&"）；全 AI（含影子收入）"&TEXT(AI增量報酬!F27*100,"0.0")&"%。" -> 主命題（AI 資本支出有沒有賺到資金成本）：2029 對外 AI ROIC 12.7% vs WACC 11.6%（+1.1pt）；打平 k 1.12（目前 1.15）；全 AI（含影子收入）12.7%。
A23: 結論｜股東回饋與 FCF 句 | C23: ="股東回饋與 FCF：FCF "&IF(各期收支!C44<0,"首次為負 2026（−$"&TEXT(-各期收支!C44,"0.0")&"bn）",IF(各期收支!D44<0,"首次為負 2027（−$"&TEXT(-各期收支!D44,"0.0")&"bn）",IF(各期收支!E44<0,"首次為負 2028（−$"&TEXT(-各期收支!E44,"0.0")&"bn）",IF(各期收支!F44<0,"首次為負 2029（−$"&TEXT(-各期收支!F44,"0.0")&"bn）",IF(各期收支!G44<0,"首次為負 2030（−$"&TEXT(-各期收支!G44,"0.0")&"bn）","五期皆為正")))))&"；"&IF(SUM(各期收支!C75:G75)<=0.05,"無回購計畫（減少回購步驟不適用）",IF(SUM(各期收支!C77:G77)>0,"回購被迫減少："&MID(IF(各期收支!C77>0.05,"、2026 $"&TEXT(各期收支!C77,"0.0"),"")&IF(各期收支!D77>0.05,"、2027 $"&TEXT(各期收支!D77,"0.0"),"")&IF(各期收支!E77>0.05,"、2028 $"&TEXT(各期收支!E77,"0.0"),"")&IF(各期收支!F77>0.05,"、2029 $"&TEXT(各期收支!F77,"0.0"),"")&IF(各期收支!G77>0.05,"、2030 $"&TEXT(各期收支!G77,"0.0"),""),2,999)&"bn","回購未被迫減少"))&"；五期新債 $"&TEXT(SUM(各期收支!C86:G86)+SUM(各期收支!C93:G93),"0.0")&"bn、股權 $"&TEXT(SUM(各期收支!C92:G92),"0.0")&"bn。" -> 股東回饋與 FCF：FCF 首次為負 2026（−$4.2bn）；回購被迫減少：2030 $17.0bn；五期新債 $85.8bn、股權 $0.0bn。
A24: 結論｜延誤句 | C24: =IF(運營_產能與收入!$C$50>0,"建設延誤 "&IF(運營_產能與收入!$C$50=INT(運營_產能與收入!$C$50),TEXT(運營_產能與收入!$C$50,"0"),TEXT(運營_產能與收入!$C$50,"0.0"))&" 個月（GPU 資本支出照原時程）：閒置資本（已支出、尚未產生收入）峰值 $"&TEXT(MAX(運營_產能與收入!$C$55:$G$55),"0.0")&"bn（"&CHOOSE(MATCH(MAX(運營_產能與收入!$C$55:$G$55),運營_產能與收入!$C$55:$G$55,0),"2026","2027","2028","2029","2030")&" 末）。","建設延誤：本情境 0 個月（無閒置資本）。") -> 建設延誤：本情境 0 個月（無閒置資本）。
A26: 2｜與市場的差異（模型：目前情境 vs 共識；2026–2028）
A27: 項目 | B27: 單位 | C27: 2026 | D27: 2027 | E27: 2028
A28: 差異｜營收｜模型 | B28: US$bn | C28: =損益!C29 -> 492.26831 | D28: =損益!D29 -> 599.07596 | E28: =損益!E29 -> 695.23465
A29: 差異｜營收｜共識 | B29: US$bn | C29: =輸入與假設!$C$516 -> 498.69 | D29: =輸入與假設!$D$516 -> 615.038 | E29: =輸入與假設!$E$516 -> 734.199
A30: 差異｜營收｜差距 | B30: % | C30: =C28/C29-1 -> -0.012877118 | D30: =D28/D29-1 -> -0.025952941 | E30: =E28/E29-1 -> -0.053070554
A31: 差異｜調整後 EBITDA｜模型 | B31: US$bn | C31: =輸入與假設!$C$486+損益!C22 -> 194.47928 | D31: =損益!D34 -> 220.64084 | E31: =損益!E34 -> 256.85321
A32: 差異｜調整後 EBITDA｜共識 | B32: US$bn | C32: =輸入與假設!$C$517 -> 233.431 | D32: =輸入與假設!$D$517 -> 298.668 | E32: =輸入與假設!$E$517 -> 382.826
A33: 差異｜調整後 EBITDA｜差距 | B33: % | C33: =C31/C32-1 -> -0.16686611 | D33: =D31/D32-1 -> -0.26125048 | E33: =E31/E32-1 -> -0.32906018 | I33: 2026 模型＝1H 實際調整後 EBITDA（輸入與假設 G 區，報導轉述 [Verified]）＋2H 模型
A34: 差異｜調整後 EBITDA｜差距（金額） | B34: US$bn | C34: =C31-C32 -> -38.951723 | D34: =D31-D32 -> -78.027158 | E34: =E31-E32 -> -125.97279 | I34: 與 HTML 一頁摘要、市場共識分頁同一呈現；判斷門檻仍用上一列比例
A35: 差異｜EBITDA 率｜模型 | B35: % | C35: =C31/C28 -> 0.39506764 | D35: =D31/D28 -> 0.36830195 | E35: =E31/E28 -> 0.36944823
A36: 差異｜EBITDA 率｜共識 | B36: % | C36: =輸入與假設!$C$518 -> 0.46808839 | D36: =輸入與假設!$D$518 -> 0.48560902 | E36: =輸入與假設!$E$518 -> 0.52141994
A37: 差異｜EBITDA 率｜差距（百分點） | B37: pt | C37: =C35-C36 -> -0.073020756 | D37: =D35-D36 -> -0.11730707 | E37: =E35-E36 -> -0.15197172 | I37: EBITDA 率以百分點列差距，不納入判斷
A38: 差異｜CapEx（毛額）｜模型 | B38: US$bn | C38: =輸入與假設!$C$469+輸入與假設!C$323 -> 200.00479 | D38: =輸入與假設!D$323 -> 236.83502 | E38: =輸入與假設!E$323 -> 256.54578
A39: 差異｜CapEx（毛額）｜共識 | B39: US$bn | C39: =輸入與假設!$C$522 -> 201.748 | D39: =輸入與假設!$D$522 -> 300.979 | E39: =輸入與假設!$E$522 -> 339.451
A40: 差異｜CapEx（毛額）｜差距 | B40: % | C40: =C38/C39-1 -> -0.0086405296 | D40: =D38/D39-1 -> -0.21311778 | E40: =E38/E39-1 -> -0.24423325 | I40: 共識 CapEx 口徑未揭露；2026＝1H 實際毛額＋2H 模型毛額
A41: 差異｜淨負債｜模型 | B41: US$bn | C41: =資產負債_新債與新股!C25 -> -29.037907 | D41: =資產負債_新債與新股!D25 -> 12.149493 | E41: =資產負債_新債與新股!E25 -> 31.968035
A42: 差異｜淨負債｜共識 | B42: US$bn | C42: =輸入與假設!$C$524 -> -131.323 | D42: =輸入與假設!$D$524 -> -79.012 | E42: =輸入與假設!$E$524 -> -56.291
A43: 差異｜淨負債｜差距 | B43: % | C43: =C41/C42-1 -> -0.77888179 | D43: =D41/D42-1 -> -1.1537677 | E43: =E41/E42-1 -> -1.5679067 | I43: 共識淨負債不含租賃、口徑未揭露：只列不判斷
A44: 差異｜淨負債｜差距（金額） | B44: US$bn | C44: =C41-C42 -> 102.28509 | D44: =D41-D42 -> 91.161493 | E44: =E41-E42 -> 88.259035 | I44: 與 HTML 一頁摘要、市場共識分頁同一呈現；判斷門檻仍用上一列比例
A45: 差異｜分歧項目（超過門檻者） | C45: =MID(IF(ABS(C30)>輸入與假設!$C$545,"、營收 "&IF(C30<0,"−","+")&TEXT(ABS(C30)*100,"0.0")&"%","")&IF(ABS(C33)>輸入與假設!$C$545,"、EBITDA "&IF(C34<0,"−","+")&"$"&TEXT(ABS(C34),"#,##0.00")&"bn"&"／"&IF(C37<0,"−","+")&TEXT(ABS(C37)*100,"0.0")&"pt","")&IF(ABS(C40)>輸入與假設!$C$545,"、CapEx "&IF(C40<0,"−","+")&TEXT(ABS(C40)*100,"0.0")&"%",""),2,999) -> EBITDA −$38.95bn／−7.3pt | D45: =MID(IF(ABS(D30)>輸入與假設!$C$545,"、營收 "&IF(D30<0,"−","+")&TEXT(ABS(D30)*100,"0.0")&"%","")&IF(ABS(D33)>輸入與假設!$C$545,"、EBITDA "&IF(D34<0,"−","+")&"$"&TEXT(ABS(D34),"#,##0.00")&"bn"&"／"&IF(D37<0,"−","+")&TEXT(ABS(D37)*100,"0.0")&"pt","")&IF(ABS(D40)>輸入與假設!$C$545,"、CapEx "&IF(D40<0,"−","+")&TEXT(ABS(D40)*100,"0.0")&"%",""),2,999) -> EBITDA −$78.03bn／−11.7pt、CapEx −21.3% | E45: =MID(IF(ABS(E30)>輸入與假設!$C$545,"、營收 "&IF(E30<0,"−","+")&TEXT(ABS(E30)*100,"0.0")&"%","")&IF(ABS(E33)>輸入與假設!$C$545,"、EBITDA "&IF(E34<0,"−","+")&"$"&TEXT(ABS(E34),"#,##0.00")&"bn"&"／"&IF(E37<0,"−","+")&TEXT(ABS(E37)*100,"0.0")&"pt","")&IF(ABS(E40)>輸入與假設!$C$545,"、CapEx "&IF(E40<0,"−","+")&TEXT(ABS(E40)*100,"0.0")&"%",""),2,999) -> 營收 −5.3%、EBITDA −$125.97bn／−15.2pt、CapEx −24.4% | I45: 營收、EBITDA、CapEx 任一項差距絕對值超過門檻即列出（與 HTML 判斷句同一規則）
A46: 差異｜分歧起始年（1＝2026…3＝2028；0＝無） | C46: =IF(C45<>"",1,IF(D45<>"",2,IF(E45<>"",3,0))) -> 1
A47: 差異｜判斷句 | C47: =CHOOSE(C46+1,"2026–2028 營收、EBITDA、CapEx 與共識差距皆在 "&IF(ROUND(ABS(輸入與假設!$C$545)*100,4)=INT(ROUND(ABS(輸入與假設!$C$545)*100,4)),TEXT(ROUND(ABS(輸入與假設!$C$545)*100,4),"0"),TEXT(ROUND(ABS(輸入與假設!$C$545)*100,4),"0.0"))&"%"&" 以內。","分歧始於 2026（"&C45&"）"&"；2027 "&IF(D45="","回到 "&IF(ROUND(ABS(輸入與假設!$C$545)*100,4)=INT(ROUND(ABS(輸入與假設!$C$545)*100,4)),TEXT(ROUND(ABS(輸入與假設!$C$545)*100,4),"0"),TEXT(ROUND(ABS(輸入與假設!$C$545)*100,4),"0.0"))&"%"&" 以內",D45)&"；2028 "&IF(E45="","回到 "&IF(ROUND(ABS(輸入與假設!$C$545)*100,4)=INT(ROUND(ABS(輸入與假設!$C$545)*100,4)),TEXT(ROUND(ABS(輸入與假設!$C$545)*100,4),"0"),TEXT(ROUND(ABS(輸入與假設!$C$545)*100,4),"0.0"))&"%"&" 以內",E45)&"。","2026 營收、EBITDA、CapEx 與共識差距在 "&IF(ROUND(ABS(輸入與假設!$C$545)*100,4)=INT(ROUND(ABS(輸入與假設!$C$545)*100,4)),TEXT(ROUND(ABS(輸入與假設!$C$545)*100,4),"0"),TEXT(ROUND(ABS(輸入與假設!$C$545)*100,4),"0.0"))&"%"&" 以內；分歧始於 2027（"&D45&"）"&"；2028 "&IF(E45="","回到 "&IF(ROUND(ABS(輸入與假設!$C$545)*100,4)=INT(ROUND(ABS(輸入與假設!$C$545)*100,4)),TEXT(ROUND(ABS(輸入與假設!$C$545)*100,4),"0"),TEXT(ROUND(ABS(輸入與假設!$C$545)*100,4),"0.0"))&"%"&" 以內",E45)&"。","2026–2027 營收、EBITDA、CapEx 與共識差距在 "&IF(ROUND(ABS(輸入與假設!$C$545)*100,4)=INT(ROUND(ABS(輸入與假設!$C$545)*100,4)),TEXT(ROUND(ABS(輸入與假設!$C$545)*100,4),"0"),TEXT(ROUND(ABS(輸入與假設!$C$545)*100,4),"0.0"))&"%"&" 以內；分歧始於 2028（"&E45&"）。") -> 分歧始於 2026（EBITDA −$38.95bn／−7.3pt）；2027 EBITDA −$78.03bn／−11.7pt、CapEx −21.3%；2028 營收 −5.3%、EBITDA −$125.97bn／−15.2pt、CapEx −24.4%。
A48: 差異原因｜2026｜營收 | C48: =IF(ABS(C30)>輸入與假設!$C$545,"觀點","") | D48: =IF(ABS(C30)>輸入與假設!$C$545,"營收＝對外 AI 雲端（年底 "&IF((輸入與假設!C$36)<0,"−","")&TEXT(ABS((輸入與假設!C$36)),"#,##0")&" MW-IT × 每 MW 年收入，Tokenomics × k）＋搜尋／YouTube／聯播網／訂閱／Cloud 非 AI／TPU 銷售（近四季年增率收斂到長期值）；共識未揭露 MW 與單價假設","") | I48: C＝類型、D＝原因（需附原因時顯示；EBITDA 以利潤率差、其餘以比例門檻判斷）
A49: 差異原因｜2026｜EBITDA | C49: =IF(ABS(C37)>輸入與假設!$C$546,"觀點","") -> 觀點 | D49: =IF(ABS(C37)>輸入與假設!$C$546,"營收差距 "&IF((C30)<0,"−","+")&TEXT(ABS((C30))*100,"#,##0.0")&"%"&"；EBITDA 率 "&IF((C35)<0,"−","")&TEXT(ABS((C35))*100,"#,##0.0")&"%"&" 對共識 "&IF((C36)<0,"−","")&TEXT(ABS((C36))*100,"#,##0.0")&"%"&"（分部 EBITDA＝營業利益＋按營收分攤折舊，近四季收斂到近三年平均；含 Alphabet 層級費用與 Other Bets 虧損；AI 雲端以 Tokenomics 營運成本推得；共識 EBITDA（MarketScreener）含加回 SBC，模型不加回）","") -> 營收差距 −1.3%；EBITDA 率 39.5% 對共識 46.8%（分部 EBITDA＝營業利益＋按營收分攤折舊，近四季收斂到近三年平均；含 Alphabet 層級費用與 Other Bets 虧損；AI 雲端以 Tokenomics 營運成本推得；共識 EBITDA（MarketScreener）含加回 SBC，模型不加回）
A50: 差異原因｜2026｜CapEx | C50: =IF(ABS(C40)>輸入與假設!$C$545,"觀點","") | D50: =IF(ABS(C40)>輸入與假設!$C$545,"CapEx：首期取公司指引中點 200；公司 2027 只說「顯著增加」、無數字 → 依新增 AI MW（"&IF((輸入與假設!C$290)<0,"−","")&TEXT(ABS((輸入與假設!C$290)),"#,##0")&" MW-IT 對外）÷ 對外比例 × 每 MW $"&IF((輸入與假設!C$271)<0,"−","")&TEXT(ABS((輸入與假設!C$271)),"#,##0")&"m＋非 AI 強度推導；基準情境的新增速度由 2026 指引解出（C10），之後各年資本支出＝MW 路徑 × 每 MW 成本；共識 2027 301.0","")
A51: 差異原因｜2026｜淨負債 | C51: =IF(ABS(C43)>輸入與假設!$C$545,"觀點","") -> 觀點 | D51: =IF(ABS(C43)>輸入與假設!$C$545,"淨負債隨 CapEx、投資與融資瀑布而定（模型 CapEx 差距 "&IF((C40)<0,"−","+")&TEXT(ABS((C40))*100,"#,##0.0")&"%"&"）；共識淨負債不含租賃","") -> 淨負債隨 CapEx、投資與融資瀑布而定（模型 CapEx 差距 −0.9%）；共識淨負債不含租賃
A52: 差異原因｜2027｜營收 | C52: =IF(ABS(D30)>輸入與假設!$C$545,"觀點","") | D52: =IF(ABS(D30)>輸入與假設!$C$545,"營收＝對外 AI 雲端（年底 "&IF((輸入與假設!D$36)<0,"−","")&TEXT(ABS((輸入與假設!D$36)),"#,##0")&" MW-IT × 每 MW 年收入，Tokenomics × k）＋搜尋／YouTube／聯播網／訂閱／Cloud 非 AI／TPU 銷售（近四季年增率收斂到長期值）；共識未揭露 MW 與單價假設","")
A53: 差異原因｜2027｜EBITDA | C53: =IF(ABS(D37)>輸入與假設!$C$546,"觀點","") -> 觀點 | D53: =IF(ABS(D37)>輸入與假設!$C$546,"營收差距 "&IF((D30)<0,"−","+")&TEXT(ABS((D30))*100,"#,##0.0")&"%"&"；EBITDA 率 "&IF((D35)<0,"−","")&TEXT(ABS((D35))*100,"#,##0.0")&"%"&" 對共識 "&IF((D36)<0,"−","")&TEXT(ABS((D36))*100,"#,##0.0")&"%"&"（分部 EBITDA＝營業利益＋按營收分攤折舊，近四季收斂到近三年平均；含 Alphabet 層級費用與 Other Bets 虧損；AI 雲端以 Tokenomics 營運成本推得；共識 EBITDA（MarketScreener）含加回 SBC，模型不加回）","") -> 營收差距 −2.6%；EBITDA 率 36.8% 對共識 48.6%（分部 EBITDA＝營業利益＋按營收分攤折舊，近四季收斂到近三年平均；含 Alphabet 層級費用與 Other Bets 虧損；AI 雲端以 Tokenomics 營運成本推得；共識 EBITDA（MarketScreener）含加回 SBC，模型不加回）
A54: 差異原因｜2027｜CapEx | C54: =IF(ABS(D40)>輸入與假設!$C$545,"觀點","") -> 觀點 | D54: =IF(ABS(D40)>輸入與假設!$C$545,"CapEx：首期取公司指引中點 200；公司 2027 只說「顯著增加」、無數字 → 依新增 AI MW（"&IF((輸入與假設!D$290)<0,"−","")&TEXT(ABS((輸入與假設!D$290)),"#,##0")&" MW-IT 對外）÷ 對外比例 × 每 MW $"&IF((輸入與假設!D$271)<0,"−","")&TEXT(ABS((輸入與假設!D$271)),"#,##0")&"m＋非 AI 強度推導；基準情境的新增速度由 2026 指引解出（C10），之後各年資本支出＝MW 路徑 × 每 MW 成本；共識 2027 301.0","") -> CapEx：首期取公司指引中點 200；公司 2027 只說「顯著增加」、無數字 → 依新增 AI MW（1,246 MW-IT 對外）÷ 對外比例 × 每 MW $46m＋非 AI 強度推導；基準情境的新增速度由 2026 指引解出（C10），之後各年資本支出＝MW 路徑 × 每 MW 成本；共識 2027 301.0
A55: 差異原因｜2027｜淨負債 | C55: =IF(ABS(D43)>輸入與假設!$C$545,"觀點","") -> 觀點 | D55: =IF(ABS(D43)>輸入與假設!$C$545,"淨負債隨 CapEx、投資與融資瀑布而定（模型 CapEx 差距 "&IF((D40)<0,"−","+")&TEXT(ABS((D40))*100,"#,##0.0")&"%"&"）；共識淨負債不含租賃","") -> 淨負債隨 CapEx、投資與融資瀑布而定（模型 CapEx 差距 −21.3%）；共識淨負債不含租賃
A56: 差異原因｜2028｜營收 | C56: =IF(ABS(E30)>輸入與假設!$C$545,"觀點","") -> 觀點 | D56: =IF(ABS(E30)>輸入與假設!$C$545,"營收＝對外 AI 雲端（年底 "&IF((輸入與假設!E$36)<0,"−","")&TEXT(ABS((輸入與假設!E$36)),"#,##0")&" MW-IT × 每 MW 年收入，Tokenomics × k）＋搜尋／YouTube／聯播網／訂閱／Cloud 非 AI／TPU 銷售（近四季年增率收斂到長期值）；共識未揭露 MW 與單價假設","") -> 營收＝對外 AI 雲端（年底 5,016 MW-IT × 每 MW 年收入，Tokenomics × k）＋搜尋／YouTube／聯播網／訂閱／Cloud 非 AI／TPU 銷售（近四季年增率收斂到長期值）；共識未揭露 MW 與單價假設
A57: 差異原因｜2028｜EBITDA | C57: =IF(ABS(E37)>輸入與假設!$C$546,"觀點","") -> 觀點 | D57: =IF(ABS(E37)>輸入與假設!$C$546,"營收差距 "&IF((E30)<0,"−","+")&TEXT(ABS((E30))*100,"#,##0.0")&"%"&"；EBITDA 率 "&IF((E35)<0,"−","")&TEXT(ABS((E35))*100,"#,##0.0")&"%"&" 對共識 "&IF((E36)<0,"−","")&TEXT(ABS((E36))*100,"#,##0.0")&"%"&"（分部 EBITDA＝營業利益＋按營收分攤折舊，近四季收斂到近三年平均；含 Alphabet 層級費用與 Other Bets 虧損；AI 雲端以 Tokenomics 營運成本推得；共識 EBITDA（MarketScreener）含加回 SBC，模型不加回）","") -> 營收差距 −5.3%；EBITDA 率 36.9% 對共識 52.1%（分部 EBITDA＝營業利益＋按營收分攤折舊，近四季收斂到近三年平均；含 Alphabet 層級費用與 Other Bets 虧損；AI 雲端以 Tokenomics 營運成本推得；共識 EBITDA（MarketScreener）含加回 SBC，模型不加回）
A58: 差異原因｜2028｜CapEx | C58: =IF(ABS(E40)>輸入與假設!$C$545,"觀點","") -> 觀點 | D58: =IF(ABS(E40)>輸入與假設!$C$545,"CapEx：首期取公司指引中點 200；公司 2027 只說「顯著增加」、無數字 → 依新增 AI MW（"&IF((輸入與假設!E$290)<0,"−","")&TEXT(ABS((輸入與假設!E$290)),"#,##0")&" MW-IT 對外）÷ 對外比例 × 每 MW $"&IF((輸入與假設!E$271)<0,"−","")&TEXT(ABS((輸入與假設!E$271)),"#,##0")&"m＋非 AI 強度推導；基準情境的新增速度由 2026 指引解出（C10），之後各年資本支出＝MW 路徑 × 每 MW 成本；共識 2027 301.0","") -> CapEx：首期取公司指引中點 200；公司 2027 只說「顯著增加」、無數字 → 依新增 AI MW（1,246 MW-IT 對外）÷ 對外比例 × 每 MW $48m＋非 AI 強度推導；基準情境的新增速度由 2026 指引解出（C10），之後各年資本支出＝MW 路徑 × 每 MW 成本；共識 2027 301.0
A59: 差異原因｜2028｜淨負債 | C59: =IF(ABS(E43)>輸入與假設!$C$545,"觀點","") -> 觀點 | D59: =IF(ABS(E43)>輸入與假設!$C$545,"淨負債隨 CapEx、投資與融資瀑布而定（模型 CapEx 差距 "&IF((E40)<0,"−","+")&TEXT(ABS((E40))*100,"#,##0.0")&"%"&"）；共識淨負債不含租賃","") -> 淨負債隨 CapEx、投資與融資瀑布而定（模型 CapEx 差距 −24.4%）；共識淨負債不含租賃
A60: 差異｜需附原因項數 | C60: =SUMPRODUCT(--(ABS(C30:E30)>輸入與假設!$C$545))+SUMPRODUCT(--(ABS(C37:E37)>輸入與假設!$C$546))+SUMPRODUCT(--(ABS(C40:E40)>輸入與假設!$C$545))+SUMPRODUCT(--(ABS(C43:E43)>輸入與假設!$C$545)) -> 9 | I60: 營收、EBITDA（利潤率差）、CapEx、淨負債 × 2026–2028
A61: 差異｜差異原因摘要 | C61: =IF(C60=0,"","需附原因的 "&C60&" 項差距："&MID(IF((COUNTIF(C48,"觀點")+COUNTIF(C49,"觀點")+COUNTIF(C50,"觀點")+COUNTIF(C51,"觀點")+COUNTIF(C52,"觀點")+COUNTIF(C53,"觀點")+COUNTIF(C54,"觀點")+COUNTIF(C55,"觀點")+COUNTIF(C56,"觀點")+COUNTIF(C57,"觀點")+COUNTIF(C58,"觀點")+COUNTIF(C59,"觀點"))>0,"、觀點 "&(COUNTIF(C48,"觀點")+COUNTIF(C49,"觀點")+COUNTIF(C50,"觀點")+COUNTIF(C51,"觀點")+COUNTIF(C52,"觀點")+COUNTIF(C53,"觀點")+COUNTIF(C54,"觀點")+COUNTIF(C55,"觀點")+COUNTIF(C56,"觀點")+COUNTIF(C57,"觀點")+COUNTIF(C58,"觀點")+COUNTIF(C59,"觀點"))&" 項","")&IF((COUNTIF(C48,"拆法")+COUNTIF(C49,"拆法")+COUNTIF(C50,"拆法")+COUNTIF(C51,"拆法")+COUNTIF(C52,"拆法")+COUNTIF(C53,"拆法")+COUNTIF(C54,"拆法")+COUNTIF(C55,"拆法")+COUNTIF(C56,"拆法")+COUNTIF(C57,"拆法")+COUNTIF(C58,"拆法")+COUNTIF(C59,"拆法"))>0,"、拆法 "&(COUNTIF(C48,"拆法")+COUNTIF(C49,"拆法")+COUNTIF(C50,"拆法")+COUNTIF(C51,"拆法")+COUNTIF(C52,"拆法")+COUNTIF(C53,"拆法")+COUNTIF(C54,"拆法")+COUNTIF(C55,"拆法")+COUNTIF(C56,"拆法")+COUNTIF(C57,"拆法")+COUNTIF(C58,"拆法")+COUNTIF(C59,"拆法"))&" 項","")&IF((COUNTIF(C48,"已知限制")+COUNTIF(C49,"已知限制")+COUNTIF(C50,"已知限制")+COUNTIF(C51,"已知限制")+COUNTIF(C52,"已知限制")+COUNTIF(C53,"已知限制")+COUNTIF(C54,"已知限制")+COUNTIF(C55,"已知限制")+COUNTIF(C56,"已知限制")+COUNTIF(C57,"已知限制")+COUNTIF(C58,"已知限制")+COUNTIF(C59,"已知限制"))>0,"、已知限制 "&(COUNTIF(C48,"已知限制")+COUNTIF(C49,"已知限制")+COUNTIF(C50,"已知限制")+COUNTIF(C51,"已知限制")+COUNTIF(C52,"已知限制")+COUNTIF(C53,"已知限制")+COUNTIF(C54,"已知限制")+COUNTIF(C55,"已知限制")+COUNTIF(C56,"已知限制")+COUNTIF(C57,"已知限制")+COUNTIF(C58,"已知限制")+COUNTIF(C59,"已知限制"))&" 項","")&IF((C60-((COUNTIF(C48,"觀點")+COUNTIF(C49,"觀點")+COUNTIF(C50,"觀點")+COUNTIF(C51,"觀點")+COUNTIF(C52,"觀點")+COUNTIF(C53,"觀點")+COUNTIF(C54,"觀點")+COUNTIF(C55,"觀點")+COUNTIF(C56,"觀點")+COUNTIF(C57,"觀點")+COUNTIF(C58,"觀點")+COUNTIF(C59,"觀點"))+(COUNTIF(C48,"拆法")+COUNTIF(C49,"拆法")+COUNTIF(C50,"拆法")+COUNTIF(C51,"拆法")+COUNTIF(C52,"拆法")+COUNTIF(C53,"拆法")+COUNTIF(C54,"拆法")+COUNTIF(C55,"拆法")+COUNTIF(C56,"拆法")+COUNTIF(C57,"拆法")+COUNTIF(C58,"拆法")+COUNTIF(C59,"拆法"))+(COUNTIF(C48,"已知限制")+COUNTIF(C49,"已知限制")+COUNTIF(C50,"已知限制")+COUNTIF(C51,"已知限制")+COUNTIF(C52,"已知限制")+COUNTIF(C53,"已知限制")+COUNTIF(C54,"已知限制")+COUNTIF(C55,"已知限制")+COUNTIF(C56,"已知限制")+COUNTIF(C57,"已知限制")+COUNTIF(C58,"已知限制")+COUNTIF(C59,"已知限制"))))>0,"、未歸類 "&(C60-((COUNTIF(C48,"觀點")+COUNTIF(C49,"觀點")+COUNTIF(C50,"觀點")+COUNTIF(C51,"觀點")+COUNTIF(C52,"觀點")+COUNTIF(C53,"觀點")+COUNTIF(C54,"觀點")+COUNTIF(C55,"觀點")+COUNTIF(C56,"觀點")+COUNTIF(C57,"觀點")+COUNTIF(C58,"觀點")+COUNTIF(C59,"觀點"))+(COUNTIF(C48,"拆法")+COUNTIF(C49,"拆法")+COUNTIF(C50,"拆法")+COUNTIF(C51,"拆法")+COUNTIF(C52,"拆法")+COUNTIF(C53,"拆法")+COUNTIF(C54,"拆法")+COUNTIF(C55,"拆法")+COUNTIF(C56,"拆法")+COUNTIF(C57,"拆法")+COUNTIF(C58,"拆法")+COUNTIF(C59,"拆法"))+(COUNTIF(C48,"已知限制")+COUNTIF(C49,"已知限制")+COUNTIF(C50,"已知限制")+COUNTIF(C51,"已知限制")+COUNTIF(C52,"已知限制")+COUNTIF(C53,"已知限制")+COUNTIF(C54,"已知限制")+COUNTIF(C55,"已知限制")+COUNTIF(C56,"已知限制")+COUNTIF(C57,"已知限制")+COUNTIF(C58,"已知限制")+COUNTIF(C59,"已知限制"))))&" 項",""),2,999)&"；原因見「損益與評價 → 市場共識」。") -> 需附原因的 9 項差距：觀點 9 項；原因見「損益與評價 → 市場共識」。 | I61: 與 HTML 一頁摘要同一句
A63: 3｜現價隱含什麼
A64: 隱含｜共識平均目標價隱含 2028 EV/EBITDA | B64: x | C64: =(輸入與假設!$C$498*輸入與假設!$C$367+輸入與假設!$E$524)/輸入與假設!$E$517 -> 13.661703 | I64: ＝（共識平均目標價 × 股數＋共識 2028 淨負債）÷ 共識 2028 調整後 EBITDA
A65: 隱含｜現價隱含 2028 EV/EBITDA | B65: x | C65: =(輸入與假設!$C$366*輸入與假設!$C$367+輸入與假設!$E$524)/輸入與假設!$E$517 -> 11.122582 | I65: 同一共識 2028 數字，價格換成現價
A66: 隱含｜模型方法區間上緣 | B66: x | C66: =MAX(輸入與假設!$C$434,輸入與假設!$C$435) -> 6 | I66: 模型 EV/EBITDA 腿（AI 雲端 倍數）錨定 2029 並折回 2027-06-30，錨定年度與此不同
A67: 隱含｜模型 2028 非 AI 事業 EBITDA | B67: US$bn | C67: =輸入與假設!E$241 -> 221.24535 | I67: × 非 AI 事業 EV/EBITDA 倍數，自共識隱含 EV 扣除
A68: 隱含｜共識平均目標價隱含 2028 AI 雲端 EV/EBITDA | B68: x | C68: =IF(ABS((輸入與假設!$C$498*輸入與假設!$C$367+輸入與假設!$E$524-輸入與假設!E$241*輸入與假設!$C$430)/MAX(輸入與假設!$E$517-輸入與假設!E$241,0.01))<0.05,0,(輸入與假設!$C$498*輸入與假設!$C$367+輸入與假設!$E$524-輸入與假設!E$241*輸入與假設!$C$430)/MAX(輸入與假設!$E$517-輸入與假設!E$241,0.01)) -> 18.312027 | I68: ＝（隱含 EV − 非 AI 事業 EBITDA × 非 AI 事業倍數）÷（共識 EBITDA − 非 AI 事業 EBITDA）
A69: 隱含｜現價隱含 2028 AI 雲端 EV/EBITDA | B69: x | C69: =IF(ABS((輸入與假設!$C$366*輸入與假設!$C$367+輸入與假設!$E$524-輸入與假設!E$241*輸入與假設!$C$430)/MAX(輸入與假設!$E$517-輸入與假設!E$241,0.01))<0.05,0,(輸入與假設!$C$366*輸入與假設!$C$367+輸入與假設!$E$524-輸入與假設!E$241*輸入與假設!$C$430)/MAX(輸入與假設!$E$517-輸入與假設!E$241,0.01)) -> 12.296197 | I69: 同上，價格換成現價
A70: 隱含｜隱含倍數句 | C70: ="共識平均目標價 $"&TEXT(輸入與假設!$C$498,"0.00")&" 隱含 2028 EV/EBITDA "&TEXT(C64,"0.0")&"x（扣除非 AI 事業 "&TEXT(輸入與假設!$C$430,"0.0")&"x × 模型 EBITDA $"&TEXT(C67,"0.0")&"bn 後，AI 雲端 "&TEXT(C68,"0.0")&"x），AI 雲端 倍數"&IF(ROUND(C68,1)>C66,"高於",IF(ROUND(C68,1)<C66,"低於","等於"))&"模型方法區間上緣 "&IF(C66=INT(C66),TEXT(C66,"0"),TEXT(C66,"0.0"))&"x；現價 $"&TEXT(輸入與假設!$C$366,"0.00")&" 隱含 "&TEXT(C65,"0.0")&"x（AI 雲端 "&TEXT(C69,"0.0")&"x）。" -> 共識平均目標價 $429.47 隱含 2028 EV/EBITDA 13.7x（扣除非 AI 事業 10.3x × 模型 EBITDA $221.2bn 後，AI 雲端 18.3x），AI 雲端 倍數高於模型方法區間上緣 6x；現價 $350.50 隱含 11.1x（AI 雲端 12.3x）。
A71: 反向 DCF｜2030 每 MW 年收入（目前／隱含／變動） | C71: =評價_反向DCF!B18 -> 13.1035 | D71: =評價_反向DCF!C18 -> 無解 | E71: =評價_反向DCF!D18 -> 無解 | I71: 快照（預設輸入）：見『評價_反向DCF』；改輸入後請以目標搜尋重算
A72: 反向 DCF｜每 MW 建置成本（目前／隱含／變動） | C72: =評價_反向DCF!B19 -> 48.3559 | D72: =評價_反向DCF!C19 -> 無解 | E72: =評價_反向DCF!D19 -> 無解
A73: 反向 DCF｜穩態 EBITDA 率（目前／隱含／變動 pt） | C73: =評價_反向DCF!B20 -> 0.765 | D73: =評價_反向DCF!C20 -> 無解 | E73: =評價_反向DCF!D20 -> 無解
A74: 反向 DCF｜加權目標價＝現價所需每 MW 年收入（目前／隱含／變動） | C74: =評價_反向DCF!B21 -> 13.1035 | D74: =評價_反向DCF!C21 -> 無解 | E74: =評價_反向DCF!D21 -> 無解
A76: 4｜驗證點與市場看法（賣方與管理層數字標記 Interested-party）
A77: 驗證｜焦點季 | C77: =季度追蹤!C12 -> Q3 2026 | I77: 『輸入與假設』J 區選擇；季度層由年度模型拆分，只用於追蹤
A78: 驗證｜營收（模型／共識／指引低／指引高／實際） | B78: US$bn | C78: =季度追蹤!C6 -> 127.45744 | D78: =季度追蹤!D6 -> 不適用 | E78: =季度追蹤!F6 -> 不適用 | F78: =季度追蹤!G6 -> 不適用 | G78: =季度追蹤!I6 -> 待公布 | I78: 共識、指引為 Interested-party
A79: 驗證｜營收｜句 | C79: =INDEX(季度追蹤!$C$125:$H$125,輸入與假設!$C$551) -> 營收：模型 $127.46bn
A80: 驗證｜調整後營業利益（模型／共識／指引低／指引高／實際） | B80: US$bn | C80: =季度追蹤!C9 -> 37.018168 | D80: =季度追蹤!D9 -> 不適用 | E80: =季度追蹤!F9 -> 不適用 | F80: =季度追蹤!G9 -> 不適用 | G80: =季度追蹤!I9 -> 待公布 | I80: 共識、指引為 Interested-party
A81: 驗證｜調整後營業利益｜句 | C81: =INDEX(季度追蹤!$C$128:$H$128,輸入與假設!$C$551) -> 調整後營業利益：模型 $37.02bn
A82: 驗證｜CapEx（毛額）（模型／共識／指引低／指引高／實際） | B82: US$bn | C82: =季度追蹤!C10 -> 59.703395 | D82: =季度追蹤!D10 -> 不適用 | E82: =季度追蹤!F10 -> 不適用 | F82: =季度追蹤!G10 -> 不適用 | G82: =季度追蹤!I10 -> 待公布 | I82: 共識、指引為 Interested-party
A83: 驗證｜CapEx（毛額）｜句 | C83: =INDEX(季度追蹤!$C$129:$H$129,輸入與假設!$C$551) -> CapEx（毛額）：模型 $59.70bn
A84: 驗證｜評等分布（強力買進／買進／持有／賣出／強力賣出） | B84: 家 | C84: =輸入與假設!$C$509 -> 43 | D84: =輸入與假設!$C$510 -> 13 | E84: =輸入與假設!$C$511 -> 5 | F84: =輸入與假設!$C$512 -> 0 | G84: =輸入與假設!$C$513 -> 0 | I84: 2026-10，合計 61 家 [Interested-party]
A85: 驗證｜目標價（平均／中位數／最低／最高） | B85: US$ | C85: =輸入與假設!$C$498 -> 429.47 | D85: =輸入與假設!$C$499 -> 430 | E85: =輸入與假設!$C$500 -> 340 | F85: =輸入與假設!$C$501 -> 515 | I85: 61 家；S&P Global Market Intelligence（經 StockAnalysis.com），擷取 2026-10-08 [Interested-party]
A87: 來源獨立性：StockAnalysis.com 的目標價、評等、營收與 EPS 引用 S&P Global Market Intelligence；MarketScreener 的年度預估一般屬 S&P Capital IQ 系；Yahoo Finance 分析頁 2026／2027 營收 498.69／615.04 與 MarketScreener 498.690／615.038 完全相同、與 StockAnalysis 498.74／614.95 略異，三者視為同一或高度重疊的底層來源，不算獨立交叉驗證。MarketBeat 目標價與評等為自行彙整（獨立於 S&P），可作目標價的獨立交叉；Yahoo 目標價 429.47 與 S&P 完全相同，推測同源。
A88: 共識來源：MarketScreener（S&P Capital IQ 系共識）、S&P Global Market Intelligence（經 StockAnalysis.com）；擷取 2026-10-08。逐筆來源、日期與標記見『輸入與假設』I 區。

Sheet 輸入與假設
A1: 輸入（依類別排序；點左側 ＋／− 展開或收合。藍字可改；黃底為最關鍵假設）
A2: A 情境 → B 產能與收入 → C 利潤率 → D 支出（CapEx／折舊／租賃／JV）→ E 融資 → F 評價 → G 參考：1H26 實際 → H 情境區間運算表 → I 市場共識 → J 季度追蹤輸入。灰底『▸』為明細子區，預設收合
A4: A｜情境與規模（管理層擴張力道）
A5: 情境選擇（1＝保守 已交付＋已公開在建、2＝基準 依資本支出指引、3＝積極 依 2027 擴張幅度） | C5: 2 | D5: =CHOOSE(C5,"保守 已交付＋已公開在建","基準 依資本支出指引","積極 依 2027 擴張幅度") -> 基準 依資本支出指引 | I5: 三情境只改容量軸（對外 AI MW 路徑；世代組合隨新增 MW 改變每 MW 年收入）；價格軸另見 B0（對照表 r1 第 5 節第 1 條）
A6: ▸ 情境路徑明細（已連網 MW、在役比例、表外租金基準）
A7: 已連網 MW 路徑 | B7: 單位 | C7: 2026 | D7: 2027 | E7: 2028 | F7: 2029 | G7: 2030 | I7: 2031 新增 MW
A8: 評價日在役 MW（期初計費，三情境共用） | B8: MW | C8: 1901 | I8: company.json → defaults.billableOpen；來源見 scenarios.mwPath.note（第三方估計，不以營收校準）[Derived／Assumed]
A9: 保守 已交付＋已公開在建｜合約 MW 上限 | B9: MW | C9: 3171 | D9: 3171 | E9: 3171 | F9: 3171 | G9: 3171 | I9: company.json → scenarios.mwPath.contracted
A10: 保守 已交付＋已公開在建｜併網速度 | B10: MW／年 | C10: 850 | I10: company.json → scenarios.mwPath.pace
A11: 保守 已交付＋已公開在建 | B11: MW | C11: =MIN(C9,輸入與假設!$C$8+輸入與假設!$C$10*C$34) -> 2326 | D11: =MIN(D9,C11+輸入與假設!$C$10*D$34) -> 3171 | E11: =MIN(E9,D11+輸入與假設!$C$10*E$34) -> 3171 | F11: =MIN(F9,E11+輸入與假設!$C$10*F$34) -> 3171 | G11: =MIN(G9,F11+輸入與假設!$C$10*G$34) -> 3171 | I11: 0 | J11: 對外 AI MW-IT 只加已公開在建：Anthropic 於 Google Cloud 的 TPU 由約 0.77 GW 擴到 1.54 GW（anthropic/ 模型供給路徑）＋Google–Blackstone TPU 合資 0.5 GW（2027）＝+1,270，每年 +850、上限 3,171 [Derived／Interested-party]；I 欄＝2031 新增 MW
A12: 基準 依資本支出指引｜合約 MW 上限 | B12: MW | C12: 99999 | D12: 99999 | E12: 99999 | F12: 99999 | G12: 99999 | I12: company.json → scenarios.mwPath.contracted
A13: 基準 依資本支出指引｜併網速度 | B13: MW／年 | C13: 1246.1 | I13: company.json → scenarios.mwPath.pace
A14: 基準 依資本支出指引 | B14: MW | C14: =MIN(C12,輸入與假設!$C$8+輸入與假設!$C$13*C$34) -> 2524.05 | D14: =MIN(D12,C14+輸入與假設!$C$13*D$34) -> 3770.15 | E14: =MIN(E12,D14+輸入與假設!$C$13*E$34) -> 5016.25 | F14: =MIN(F12,E14+輸入與假設!$C$13*F$34) -> 6262.35 | G14: =MIN(G12,F14+輸入與假設!$C$13*G$34) -> 7508.45 | I14: 1246.1 | J14: 對外 AI MW 新增速度＝近端資本支出隱含的建置量：2026 全年指引中點 $200bn −（非 AI 公式值＋GPU 汰換）÷ 每 MW 全成本（Tokenomics IT＋自建 85% × 設施）× 對外 30%，依 λ 遞延上線（scripts/calib_pace.js 解，對帳落差＝0）；之後各年資本支出＝MW 路徑 × 每 MW 成本（同一套數字）[Derived]；I 欄＝2031 新增 MW
A15: 積極 依 2027 擴張幅度｜合約 MW 上限 | B15: MW | C15: 99999 | D15: 99999 | E15: 99999 | F15: 99999 | G15: 99999 | I15: company.json → scenarios.mwPath.contracted
A16: 積極 依 2027 擴張幅度｜併網速度 | B16: MW／年 | C16: 1869.1 | I16: company.json → scenarios.mwPath.pace
A17: 積極 依 2027 擴張幅度 | B17: MW | C17: =MIN(C15,輸入與假設!$C$8+輸入與假設!$C$16*C$34) -> 2835.55 | D17: =MIN(D15,C17+輸入與假設!$C$16*D$34) -> 4704.65 | E17: =MIN(E15,D17+輸入與假設!$C$16*E$34) -> 6573.75 | F17: =MIN(F15,E17+輸入與假設!$C$16*F$34) -> 8442.85 | G17: =MIN(G15,F17+輸入與假設!$C$16*G$34) -> 10311.95 | I17: 1869.1 | J17: 公司無 MW／GW 目標（只有「serving 容量每 6 個月倍增」的內部說法）→ 以 2027 擴張幅度代替：共識資本支出 2027 ÷ 2026＝1.49、Morgan Stanley TPU 產量 2027 ÷ 2026＝1.56，取 1.5 × 基準速度 [Derived；共識與賣方為 Interested-party]；I 欄＝2031 新增 MW
A18: 在役／已連網比例 | B18: % | C18: 1 | D18: 1 | E18: 1 | F18: 1 | G18: 1 | I18: 對外 AI MW 依 MW-year 計價：已連網即計費（在役比例 100%）；期初計費 MW＝第三方估計 1,901，不以 Google Cloud 營收校準（Cloud 營收含非 AI 與 Workspace）[Assumed]
A19: 未起租租賃總額（未折現） | B19: US$bn | C19: 85.2 | I19: 季報附註已簽約未起租租賃（company.json → leases.facts.notCommenced）[Interested-party]
A20: 未起租：評價日後第幾季開始起租（0＝首期第一季） | B20: 季 | C20: 0 | I20: company.json → leases.uncommenced.startQ
A21: 未起租：平均分攤起租的季數 | B21: 季 | C21: 22 | I21: company.json → leases.uncommenced.quarters（起租時程見該欄說明）[Assumed]
A22: 未起租：每筆租期 | B22: 年 | C22: 15 | I22: 季報 15–19 年取中點；敏感度 15／19 年見報告 [Assumed]
A23: B｜產能與收入（MW、每 MW 年收入、利用率、信用；RPO 只作對照）
A24: 6/30 RPO | B24: US$bn | C24: 0 | I24: 季報 RPO 519.5（只作對照與債務上限的 backlog）[Interested-party]
A25: 評價日後新增承諾 | B25: US$bn | C25: 0 | I25: 評價日後新簽、尚未進 RPO 的承諾；未揭露，取 0 [Assumed]
A26: 五期認列比例（至 2030 末） | B26: % | C26: 0 | I26: 季報 RPO 桶線性分攤後五期合計 0% [Derived]
A27: RPO 桶權重合計 | B27: % | C27: 0.725 | I27: 下方權重列的合計，用於歸一化
A28: 2025-12-31 主動電力 | B28: MW | C28: 1462 | I28: 2025 年底對外 AI MW-IT 估 1462（Epoch：TPU 2,223＋NVIDIA 730 MW TDP × 1.65 × 30%＝AI 在役 4,873 × 30%，[Derived／Assumed]）
A29: 6/30 Billable MW | B29: MW | C29: =輸入與假設!$C$8 -> 1901 | I29: 季末在役 MW 未揭露 [Derived]
A30: 收入用平均在役 MW（1=是） | C30: 1 | I30: 0＝用期末存量全期化；建議 1
A31: 營收驅動（mw＝MW × 每 MW 年收入；rpo＝RPO 排程） | C31: mw | I31: mw：新產能簽約率固定 100%，營收＝容量上限；RPO 只作對照與產能瓶頸旗標（company.json → defaults.revenueDriver）
A32: 每 MW 年收入倍數（整體） | B32: % | C32: 1 | I32: 反向 DCF 與壓力測試用；預設 100%。以『目標搜尋』調整此格即可反解市價隱含單價
A33: 項目 | B33: 單位 | C33: 2026 | D33: 2027 | E33: 2028 | F33: 2029 | G33: 2030 | I33: 來源／標籤
A34: 模型期長度（年） | C34: 0.5 | D34: 1 | E34: 1 | F34: 1 | G34: 1 | I34: 勿改。由 calendar_q.py 推算；只用於容量上限、電力、維護等年率換算 [Derived]
A35: RPO 桶權重 | B35: % | C35: 0.125 | D35: 0.25 | E35: 0.17 | F35: 0.09 | G35: 0.09 | H35: =SUM(C35:G35) -> 0.725 | I35: 季報 RPO 桶（RPO 519.5B（Cloud 513.9B；24 個月內略多於 50%，其後未分桶）含 Cloud 非 AI 與 Workspace，只作對照（模型排程歸 0：AI 雲端收入＝MW × 每 MW））桶內線性分攤 [Derived]
A36: Accepted MW（期末主動電力） | B36: MW | C36: =CHOOSE(輸入與假設!$C$5,C11,C14,C17) -> 2524.05 | D36: =CHOOSE(輸入與假設!$C$5,D11,D14,D17) -> 3770.15 | E36: =CHOOSE(輸入與假設!$C$5,E11,E14,E17) -> 5016.25 | F36: =CHOOSE(輸入與假設!$C$5,F11,F14,F17) -> 6262.35 | G36: =CHOOSE(輸入與假設!$C$5,G11,G14,G17) -> 7508.45 | I36: ＝依 A 區情境選擇器（已連網 MW-IT）
A37: Billable MW | B37: MW | C37: =ROUND(C36*C18,0) -> 2524 | D37: =ROUND(D36*D18,0) -> 3770 | E37: =ROUND(E36*E18,0) -> 5016 | F37: =ROUND(F36*F18,0) -> 6262 | G37: =ROUND(G36*G18,0) -> 7508 | I37: ＝已連網 × 在役比例（A 區）
A38: 利用率 | B38: % | C38: 1 | D38: 1 | E38: 1 | F38: 1 | G38: 1 | I38: 100%：按 MW-year 計價，收入端不乘 IF_Util（Tokenomics 下游契約第 3 條）
A39: 每 MW 年收入 | B39: US$bn/MW | C39: =C120*輸入與假設!$C$58/1000 -> 0.011500793 | D39: =D120*輸入與假設!$C$58/1000 -> 0.012107214 | E39: =E120*輸入與假設!$C$58/1000 -> 0.012604282 | F39: =F120*輸入與假設!$C$58/1000 -> 0.012903535 | G39: =G120*輸入與假設!$C$58/1000 -> 0.01310346 | I39: ＝加權每 MW 年持有成本 × 採用 k ÷ 1000（B0；Tokenomics × k，不以公司營收反推）
A40: 新產能簽約率 | B40: % | C40: 1 | D40: 1 | E40: 1 | F40: 1 | G40: 1 | I40: MW 驅動：100%（RPO 只作對照）
A41: 客戶違約率 | B41: % | C41: 0 | D41: 0 | E41: 0 | F41: 0 | G41: 0 | I41: 前三大客戶約 59% 營收的定價，非預測 [Assumed]
A42: 回收率 | B42: % | C42: 0.5 | D42: 0.5 | E42: 0.5 | F42: 0.5 | G42: 0.5 | I42: [Assumed]
A43: 非算力服務營收 | B43: US$bn | C43: 0 | D43: 0 | E43: 0 | F43: 0 | G43: 0 | I43: 預設 0：AI cloud 軟體已含在每 MW 年收入；其他事業另列 [Assumed]
A44: 其他事業 EBITDA（輸入） | B44: US$bn | C44: 0 | D44: 0 | E44: 0 | F44: 0 | G44: 0 | I44: 未分攤公司層費用改列 legacyBiz「Alphabet 層級費用」一線（C8 a）；此欄 0
A45: 租用算力｜SpaceX（xAI Colossus）雲端服務合約：約 11 萬顆 NVIDIA GPU｜年租金 | B45: US$bn／年 | C45: 11.04 | I45: 起租 2026-10、2.75 年、219 MW（internal）；company.json → leases.rentedCompute
A46: 租用算力｜SpaceX（xAI Colossus）雲端服務合約：約 11 萬顆 NVIDIA GPU｜在租年數 | B46: 年 | C46: 0.25 | D46: 1 | E46: 1 | F46: 0.5 | G46: 0 | I46: ＝各期與租約期間重疊的月數 ÷ 12（建置時由日曆推算）
A47: 租用算力租金（營運成本） | B47: US$bn | C47: =輸入與假設!$C$45*C46 -> 2.76 | D47: =輸入與假設!$C$45*D46 -> 11.04 | E47: =輸入與假設!$C$45*E46 -> 11.04 | F47: =輸入與假設!$C$45*F46 -> 5.52 | G47: =輸入與假設!$C$45*G46 -> 0 | I47: ＝Σ 年租金 × 在租年數（扣 EBITDA 與營運現金；不是資本支出）
A48: 其他事業 EBITDA | B48: US$bn | C48: =C44-C47 -> -2.76 | D48: =D44-D47 -> -11.04 | E48: =E44-E47 -> -11.04 | F48: =F44-F47 -> -5.52 | G48: =G44-G47 -> 0 | I48: ＝輸入 − 租用算力租金（下游引用此列）
A49: 股權報酬占營收（SBC，非現金加回） | B49: % | C49: 0.063129 | I49: 股權報酬（SBC）為非現金費用：分部營業利益已扣除，營運現金加回＝SBC 占營收 × 模型期總營收；近四季 SBC 28.147 ÷ 營收 445.866＝6.31%（現金流量表；[Derived]）。股權獎酬代扣稅款（2026 上半年 12.1B，融資活動）由 ATM 增發支應（公司稱 2026 約 30B），兩者都不建模（現金與股數影響大致相抵）。股數稀釋沿用模板每年 1%
A50: 2026 剩餘季度營運資金變動（上年同期實際，流入為正） | B50: US$bn | C50: 8.49 | I50: 首期剩餘季度（2026 下半年）營運資金變動＝上一年度同期實際：2025 全年「資產與負債變動」合計 +618（應收 −8,779、所得稅 −3,226、其他資產 −4,542、應付 +907、應計 +12,939、應計分潤 +899、遞延收入 +2,420；10-K）− 2025 上半年 −7,872（2026Q2 10-Q 比較欄：應收 −1,201、存貨 −628、所得稅 −2,434、其他資產 −2,139、應付 −327、應計 −1,779、遞延收入 +636）＝+8.490（流入）[Derived]；之後年度沿用營收增量比例（MAG 對照表 r1 C14；已實現的季節模式，非預測）
A51: ▸ B0｜對外 AI 雲端定價：每 MW 年收入＝Σ 在役世代占比 × Tokenomics 持有成本 × 晶片係數 × k（收入端不乘 IF_Util）
A52: 價格軸選擇（1＝低 長約下緣、2＝基準 C1 混合、3＝高 現貨改用 GCP 牌價） | C52: 2 | D52: =CHOOSE(C52,"低 長約下緣","基準 C1 混合","高 現貨改用 GCP 牌價") -> 基準 C1 混合 | I52: 價格軸與容量軸（A 區情境）分離；三容量情境預設都用基準 k，3 × 3 目標價矩陣見「評價_DCF與目標價」（對照表 r1 第 5 節第 1 條）
A53: k 組成（價格軸） | B53: 單位 | C53: 低 | D53: 基準 | E53: 高
A54: k｜長約 | B54: 倍 | C54: 0.6 | D54: 0.75 | E54: 0.75 | I54: 長約 k：Anthropic–Google／Broadcom TPU 0.63–0.75、Anthropic–Google Cloud 0.78–1.20（容量 [Assumed]）、IREN–Microsoft 0.76 → 基準 0.75（對照表 r1 C1）；低＝v0.1a 區間下緣 0.6 [Analogy]（kevidence k.lt.*）
A55: k｜現貨 | B55: 倍 | C55: 1.76 | D55: 1.76 | E55: 3.027 | I55: 現貨 k：基準 1.76＝與 Nebius／CRWV 同一市場現貨指數（對照表 r1 C1）；高＝GCP 牌價換算：H100（a3-highgpu-8g）3 年預留 4.86 ÷ IF_GPUhrEcon Hopper 1.605＝3.03（牌價最低層；隨需 6.89 為替代，kevidence k.gcp.a3-highgpu-8g.cud3y）
A56: 長約占比 | B56: % | C56: 0.6 | D56: 0.6 | E56: 0.6 | I56: 長約占比 60%（40%–80%，[Assumed]；Cloud 積壓以多年期大客戶為主，Anthropic ≥111.1B ≈ 積壓 21%）
A57: 混合 k | B57: 倍 | C57: =C56*C54+(1-C56)*C55 -> 1.064 | D57: =D56*D54+(1-D56)*D55 -> 1.154 | E57: =E56*E54+(1-E56)*E55 -> 1.6608 | I57: ＝長約占比 × k_長約＋(1 − 長約占比) × k_現貨
A58: 採用 k（依價格軸） | B58: 倍 | C58: =CHOOSE(輸入與假設!$C$52,C57,D57,E57) -> 1.154 | I58: ＝依上方價格軸選擇
A59: 自研晶片持有成本係數 | B59: 倍 | C59: 1 | I59: 自研晶片（TPU）每 MW 錨＝同期 NVIDIA 世代 IF_HoldEcon × 1.0（對照表 r1 C2：TPU v4／v5e／v5p → Hopper、Trillium（v6e）→ GB200、Ironwood → GB300；Ironwood 之後世代 → VR200 [Assumed]）；敏感度 × 0.7。C2 原文「TPU v6e → Hopper；Trillium → GB200」中 v6e 即 Trillium，本模型以「v6e 之前世代 → Hopper」解讀（見報告已套用的預設）。Tokenomics 無 NonNV 具名範圍（IF_NonNVRatio、IF_NonNVCostRatio 為 missing），已列缺口回報。
A60: 自研晶片 IT 資本支出係數 | B60: 倍 | C60: 1 | I60: 自研晶片（TPU）每 MW IT 資本支出係數：預設 1（TPU 的資本支出以同期 NVIDIA 世代 TK_CapexIT 計）；雙邊敏感度時與 customFactor 同乘 0.7（收入錨與資本支出同降）；機房成本不變 [Assumed]
A61: 上限檢查門檻（每 MW 年收入 ÷ 參考付費營收） | B61: % | C61: 0.5 | I61: 上限檢查：每 MW 年收入 ÷（Σ 世代占比 × IF_RevGWFleet／1000）> 50% 時示警（工作單 v0.1b 第 2 步）
A62: 項目 | B62: 單位 | C62: 2026 | D62: 2027 | E62: 2028 | F62: 2029 | G62: 2030 | I62: 來源／標籤
A63: 世代｜TPU v4／v5e／v5p｜每 MW 年持有成本 | B63: US$m/MW | C63: =TK_HoldEcon_H100*輸入與假設!$C$59 -> 9.7030873 | I63: Tokenomics IF_HoldEcon（H100）× 自研晶片係數（對照表 r1 C2）；US$B/GW＝US$m/MW
A64: 世代｜TPU v4／v5e／v5p｜每 MW 年營運成本 | B64: US$m/MW | C64: =TK_OpexGW_H100 -> 1.8846675 | I64: Tokenomics IF_OpexGW（H100；不含折舊，含電費）
A65: 世代｜TPU v4／v5e／v5p｜每 MW 參考付費營收（利用率層） | B65: US$m/MW | C65: =TK_IFW_RevGWFleet_Util_H100 -> 4.0048877 | I65: Tokenomics IFW_RevGWFleet_Util（H100；四層瀑布利用率層；上限，不得作預測，只作檢查）
A66: 世代｜TPU v4／v5e／v5p｜每 MW 參考付費營收（生產折減層） | B66: US$m/MW | C66: =TK_IFW_RevGWFleet_Prod_H100 -> 2.242962 | I66: Tokenomics IFW_RevGWFleet_Prod（H100；利用率層 × 生產折減；硬上限，只作檢查）
A67: 世代｜TPU v4／v5e／v5p｜期初在役占比 | B67: % | C67: 0.15 | I67: 期初在役（評價日，對外 MW）：TPU v4／v5 15%、Hopper GPU 10%、Trillium 35%、GB200／B200 10%、Ironwood 30% [Assumed]——依 Epoch 晶片功耗：NVIDIA 約占 21%、2024 年底前 TPU（v5 為主）991 MW、2025 年新增 1,232 MW（Trillium 為主、Q4 起 Ironwood）、2026 上半年 Ironwood 為主；對外客戶（Anthropic 等）以新世代為主。新增 MW：TPU 75%＋NVIDIA 25%（Epoch 2025 年新增功耗 TPU 約 77%）；TPU 2026 為 Ironwood、2027 Ironwood／下一代各半、2028 起下一代；NVIDIA 2026 GB300、2027 GB300／VR200、2028 起 VR200 [Assumed]。在役占比＝各世代累計 MW ÷ 對外 AI MW（不建模退役後的世代替換）。
A68: 世代｜TPU v4／v5e／v5p｜新增 MW 占比 | B68: % | C68: 0 | D68: 0 | E68: 0 | F68: 0 | G68: 0 | I68: 各期新增在役 MW 的世代組合 [Assumed]
A69: 世代｜TPU v4／v5e／v5p｜在役 MW | B69: MW | C69: =輸入與假設!$C$67*輸入與假設!$C$29+MAX(0,C36-輸入與假設!$C$29)*C68 -> 285.15 | D69: =C69+MAX(0,D36-C36)*D68 -> 285.15 | E69: =D69+MAX(0,E36-D36)*E68 -> 285.15 | F69: =E69+MAX(0,F36-E36)*F68 -> 285.15 | G69: =F69+MAX(0,G36-F36)*G68 -> 285.15 | I69: ＝前期＋本期新增 × 新增占比（首期＝評價日在役 × 期初占比＋新增）
A70: 世代｜Hopper（H100／H200）｜每 MW 年持有成本 | B70: US$m/MW | C70: =TK_HoldEcon_H100 -> 9.7030873 | I70: Tokenomics IF_HoldEcon（H100）；US$B/GW＝US$m/MW
A71: 世代｜Hopper（H100／H200）｜每 MW 年營運成本 | B71: US$m/MW | C71: =TK_OpexGW_H100 -> 1.8846675 | I71: Tokenomics IF_OpexGW（H100；不含折舊，含電費）
A72: 世代｜Hopper（H100／H200）｜每 MW 參考付費營收（利用率層） | B72: US$m/MW | C72: =TK_IFW_RevGWFleet_Util_H100 -> 4.0048877 | I72: Tokenomics IFW_RevGWFleet_Util（H100；四層瀑布利用率層；上限，不得作預測，只作檢查）
A73: 世代｜Hopper（H100／H200）｜每 MW 參考付費營收（生產折減層） | B73: US$m/MW | C73: =TK_IFW_RevGWFleet_Prod_H100 -> 2.242962 | I73: Tokenomics IFW_RevGWFleet_Prod（H100；利用率層 × 生產折減；硬上限，只作檢查）
A74: 世代｜Hopper（H100／H200）｜期初在役占比 | B74: % | C74: 0.1 | I74: 見第一個世代的說明 [Assumed]
A75: 世代｜Hopper（H100／H200）｜新增 MW 占比 | B75: % | C75: 0 | D75: 0 | E75: 0 | F75: 0 | G75: 0 | I75: 各期新增在役 MW 的世代組合 [Assumed]
A76: 世代｜Hopper（H100／H200）｜在役 MW | B76: MW | C76: =輸入與假設!$C$74*輸入與假設!$C$29+MAX(0,C36-輸入與假設!$C$29)*C75 -> 190.1 | D76: =C76+MAX(0,D36-C36)*D75 -> 190.1 | E76: =D76+MAX(0,E36-D36)*E75 -> 190.1 | F76: =E76+MAX(0,F36-E36)*F75 -> 190.1 | G76: =F76+MAX(0,G36-F36)*G75 -> 190.1 | I76: ＝前期＋本期新增 × 新增占比（首期＝評價日在役 × 期初占比＋新增）
A77: 世代｜TPU Trillium（v6e）｜每 MW 年持有成本 | B77: US$m/MW | C77: =TK_HoldEcon_GB200*輸入與假設!$C$59 -> 8.8281656 | I77: Tokenomics IF_HoldEcon（GB200）× 自研晶片係數（對照表 r1 C2）；US$B/GW＝US$m/MW
A78: 世代｜TPU Trillium（v6e）｜每 MW 年營運成本 | B78: US$m/MW | C78: =TK_OpexGW_GB200 -> 1.8122327 | I78: Tokenomics IF_OpexGW（GB200；不含折舊，含電費）
A79: 世代｜TPU Trillium（v6e）｜每 MW 參考付費營收（利用率層） | B79: US$m/MW | C79: =TK_IFW_RevGWFleet_Util_GB200 -> 20.174616 | I79: Tokenomics IFW_RevGWFleet_Util（GB200；四層瀑布利用率層；上限，不得作預測，只作檢查）
A80: 世代｜TPU Trillium（v6e）｜每 MW 參考付費營收（生產折減層） | B80: US$m/MW | C80: =TK_IFW_RevGWFleet_Prod_GB200 -> 15.285161 | I80: Tokenomics IFW_RevGWFleet_Prod（GB200；利用率層 × 生產折減；硬上限，只作檢查）
A81: 世代｜TPU Trillium（v6e）｜期初在役占比 | B81: % | C81: 0.35 | I81: 見第一個世代的說明 [Assumed]
A82: 世代｜TPU Trillium（v6e）｜新增 MW 占比 | B82: % | C82: 0 | D82: 0 | E82: 0 | F82: 0 | G82: 0 | I82: 各期新增在役 MW 的世代組合 [Assumed]
A83: 世代｜TPU Trillium（v6e）｜在役 MW | B83: MW | C83: =輸入與假設!$C$81*輸入與假設!$C$29+MAX(0,C36-輸入與假設!$C$29)*C82 -> 665.35 | D83: =C83+MAX(0,D36-C36)*D82 -> 665.35 | E83: =D83+MAX(0,E36-D36)*E82 -> 665.35 | F83: =E83+MAX(0,F36-E36)*F82 -> 665.35 | G83: =F83+MAX(0,G36-F36)*G82 -> 665.35 | I83: ＝前期＋本期新增 × 新增占比（首期＝評價日在役 × 期初占比＋新增）
A84: 世代｜GB200／B200｜每 MW 年持有成本 | B84: US$m/MW | C84: =TK_HoldEcon_GB200 -> 8.8281656 | I84: Tokenomics IF_HoldEcon（GB200）；US$B/GW＝US$m/MW
A85: 世代｜GB200／B200｜每 MW 年營運成本 | B85: US$m/MW | C85: =TK_OpexGW_GB200 -> 1.8122327 | I85: Tokenomics IF_OpexGW（GB200；不含折舊，含電費）
A86: 世代｜GB200／B200｜每 MW 參考付費營收（利用率層） | B86: US$m/MW | C86: =TK_IFW_RevGWFleet_Util_GB200 -> 20.174616 | I86: Tokenomics IFW_RevGWFleet_Util（GB200；四層瀑布利用率層；上限，不得作預測，只作檢查）
A87: 世代｜GB200／B200｜每 MW 參考付費營收（生產折減層） | B87: US$m/MW | C87: =TK_IFW_RevGWFleet_Prod_GB200 -> 15.285161 | I87: Tokenomics IFW_RevGWFleet_Prod（GB200；利用率層 × 生產折減；硬上限，只作檢查）
A88: 世代｜GB200／B200｜期初在役占比 | B88: % | C88: 0.1 | I88: 見第一個世代的說明 [Assumed]
A89: 世代｜GB200／B200｜新增 MW 占比 | B89: % | C89: 0 | D89: 0 | E89: 0 | F89: 0 | G89: 0 | I89: 各期新增在役 MW 的世代組合 [Assumed]
A90: 世代｜GB200／B200｜在役 MW | B90: MW | C90: =輸入與假設!$C$88*輸入與假設!$C$29+MAX(0,C36-輸入與假設!$C$29)*C89 -> 190.1 | D90: =C90+MAX(0,D36-C36)*D89 -> 190.1 | E90: =D90+MAX(0,E36-D36)*E89 -> 190.1 | F90: =E90+MAX(0,F36-E36)*F89 -> 190.1 | G90: =F90+MAX(0,G36-F36)*G89 -> 190.1 | I90: ＝前期＋本期新增 × 新增占比（首期＝評價日在役 × 期初占比＋新增）
A91: 世代｜TPU Ironwood（TPU7x）｜每 MW 年持有成本 | B91: US$m/MW | C91: =TK_HoldEcon_GB300*輸入與假設!$C$59 -> 10.886411 | I91: Tokenomics IF_HoldEcon（GB300）× 自研晶片係數（對照表 r1 C2）；US$B/GW＝US$m/MW
A92: 世代｜TPU Ironwood（TPU7x）｜每 MW 年營運成本 | B92: US$m/MW | C92: =TK_OpexGW_GB300 -> 1.9826348 | I92: Tokenomics IF_OpexGW（GB300；不含折舊，含電費）
A93: 世代｜TPU Ironwood（TPU7x）｜每 MW 參考付費營收（利用率層） | B93: US$m/MW | C93: =TK_IFW_RevGWFleet_Util_GB300 -> 26.265236 | I93: Tokenomics IFW_RevGWFleet_Util（GB300；四層瀑布利用率層；上限，不得作預測，只作檢查）
A94: 世代｜TPU Ironwood（TPU7x）｜每 MW 參考付費營收（生產折減層） | B94: US$m/MW | C94: =TK_IFW_RevGWFleet_Prod_GB300 -> 19.232465 | I94: Tokenomics IFW_RevGWFleet_Prod（GB300；利用率層 × 生產折減；硬上限，只作檢查）
A95: 世代｜TPU Ironwood（TPU7x）｜期初在役占比 | B95: % | C95: 0.3 | I95: 見第一個世代的說明 [Assumed]
A96: 世代｜TPU Ironwood（TPU7x）｜新增 MW 占比 | B96: % | C96: 0.75 | D96: 0.4 | E96: 0 | F96: 0 | G96: 0 | I96: 各期新增在役 MW 的世代組合 [Assumed]
A97: 世代｜TPU Ironwood（TPU7x）｜在役 MW | B97: MW | C97: =輸入與假設!$C$95*輸入與假設!$C$29+MAX(0,C36-輸入與假設!$C$29)*C96 -> 1037.5875 | D97: =C97+MAX(0,D36-C36)*D96 -> 1536.0275 | E97: =D97+MAX(0,E36-D36)*E96 -> 1536.0275 | F97: =E97+MAX(0,F36-E36)*F96 -> 1536.0275 | G97: =F97+MAX(0,G36-F36)*G96 -> 1536.0275 | I97: ＝前期＋本期新增 × 新增占比（首期＝評價日在役 × 期初占比＋新增）
A98: 世代｜GB300｜每 MW 年持有成本 | B98: US$m/MW | C98: =TK_HoldEcon_GB300 -> 10.886411 | I98: Tokenomics IF_HoldEcon（GB300）；US$B/GW＝US$m/MW
A99: 世代｜GB300｜每 MW 年營運成本 | B99: US$m/MW | C99: =TK_OpexGW_GB300 -> 1.9826348 | I99: Tokenomics IF_OpexGW（GB300；不含折舊，含電費）
A100: 世代｜GB300｜每 MW 參考付費營收（利用率層） | B100: US$m/MW | C100: =TK_IFW_RevGWFleet_Util_GB300 -> 26.265236 | I100: Tokenomics IFW_RevGWFleet_Util（GB300；四層瀑布利用率層；上限，不得作預測，只作檢查）
A101: 世代｜GB300｜每 MW 參考付費營收（生產折減層） | B101: US$m/MW | C101: =TK_IFW_RevGWFleet_Prod_GB300 -> 19.232465 | I101: Tokenomics IFW_RevGWFleet_Prod（GB300；利用率層 × 生產折減；硬上限，只作檢查）
...

Sheet 各期收支
A1: 支出與資金 — 五層支出、四層來源、現金橋
A2: 2026 欄＝1H 實際（季報現金流量表口徑）＋下半年模型；2027 以後為純模型。瀑布以「融資前現金」決定需求並直接由各支出列加總，因此沒有循環參照
A4: 項目 | B4: 單位 | C4: 2026 | D4: 2027 | E4: 2028 | F4: 2029 | G4: 2030 | I4: 公式／來源說明
A5: 支出（五層）
A6: ① 毛 CapEx（認列，備忘） | B6: US$bn | C6: =輸入與假設!$C$469+輸入與假設!C$323 -> 200.00479 | D6: =輸入與假設!D$323 -> 236.83502 | E6: =輸入與假設!E$323 -> 256.54578 | F6: =輸入與假設!F$323 -> 287.92653 | G6: =輸入與假設!G$323 -> 412.79175 | I6: 2026＝1H 實際認列 80.598＋2H 模型；對照公司全年指引 195–205。備忘列：用途合計採現金口徑，不用這一列
A7: 客戶預付率 | B7: % | C7: =輸入與假設!C$279 -> 0 | D7: =輸入與假設!D$279 -> 0 | E7: =輸入與假設!E$279 -> 0 | F7: =輸入與假設!F$279 -> 0 | G7: =輸入與假設!G$279 -> 0
A8: 客戶預付金額（抵減，2H 起） | B8: US$bn | C8: =輸入與假設!C$299*C7 -> 0 | D8: =輸入與假設!D$299*D7 -> 0 | E8: =輸入與假設!E$299*E7 -> 0 | F8: =輸入與假設!F$299*F7 -> 0 | G8: =輸入與假設!G$299*G7 -> 0 | I8: ＝成長型 CapEx × 預付比率（汰換 CapEx 不計）；1H 的預付已含在實際 CFO 內，不重複計入
A9: 合約負債期初（客戶預付餘額） | B9: US$bn | C9: =輸入與假設!$C$276 -> 0 | D9: =C12 -> 0 | E9: =D12 -> 0 | F9: =E12 -> 0 | G9: =F12 -> 0 | I9: 2026 期初＝6/30 季報遞延營收
A10: 合約負債利息累積（重大財務組成，非現金） | B10: US$bn | C10: =輸入與假設!$C$277*(C9+0.5*C8)*運營_產能與收入!C7 -> 0 | D10: =輸入與假設!$C$277*(D9+0.5*D8)*運營_產能與收入!D7 -> 0 | E10: =輸入與假設!$C$277*(E9+0.5*E8)*運營_產能與收入!E7 -> 0 | F10: =輸入與假設!$C$277*(F9+0.5*F8)*運營_產能與收入!F7 -> 0 | G10: =輸入與假設!$C$277*(G9+0.5*G8)*運營_產能與收入!G7 -> 0 | I10: ＝隱含利率 ×(期初合約負債＋本期預付流入 × ½)× 期間長度；進損益利息、不進現金（v0.1b）
A11: 預付認列（非現金營收） | B11: US$bn | C11: =MIN(C9+C10,(C9+C10)/輸入與假設!$C$275*運營_產能與收入!C7) -> 0 | D11: =MIN(D9+D10,(D9+D10)/輸入與假設!$C$275*運營_產能與收入!D7) -> 0 | E11: =MIN(E9+E10,(E9+E10)/輸入與假設!$C$275*運營_產能與收入!E7) -> 0 | F11: =MIN(F9+F10,(F9+F10)/輸入與假設!$C$275*運營_產能與收入!F7) -> 0 | G11: =MIN(G9+G10,(G9+G10)/輸入與假設!$C$275*運營_產能與收入!G7) -> 0 | I11: ＝(期初合約負債＋累積利息) ÷ 認列年數 × 期間長度；這部分營收已在預付時收現，自營運來源扣除
A12: 合約負債期末 | B12: US$bn | C12: =C9+C8+C10-C11 -> 0 | D12: =D9+D8+D10-D11 -> 0 | E12: =E9+E8+E10-E11 -> 0 | F12: =F9+F8+F10-F11 -> 0 | G12: =G9+G8+G10-G11 -> 0 | I12: ＝期初＋預付流入＋累積利息−認列
A13: ① CapEx（用途用：1H 現金／2H 毛額） | B13: US$bn | C13: =輸入與假設!$C$468+輸入與假設!C$323 -> 200.00479 | D13: =輸入與假設!D$323 -> 236.83502 | E13: =輸入與假設!E$323 -> 256.54578 | F13: =輸入與假設!F$323 -> 287.92653 | G13: =輸入與假設!G$323 -> 412.79175 | I13: 1H 採現金流量表的現金購置 80.598；2H 起採毛額，客戶預付在來源端抵回（避免重複計入）
A14: ② 在帳現金租金（備忘，1H 已含在 CFO） | B14: US$bn | C14: =輸入與假設!C$280 -> 2.042 | D14: =輸入與假設!D$280 -> 3.885 | E14: =輸入與假設!E$280 -> 3.356 | F14: =輸入與假設!F$280 -> 2.932 | G14: =輸入與假設!G$280 -> 2.331 | I14: 見『租賃與承諾』頁；2030 後尚有 9.707。2026 欄僅 2H：1H 租金 2.692 已含在實際 CFO 內
A15: ② 表外現金租金（未起租） | B15: US$bn | C15: =運營_產能與收入!C59 -> 0.19363636 | D15: =運營_產能與收入!D59 -> 1.1618182 | E15: =運營_產能與收入!E59 -> 2.1945455 | F15: =運營_產能與收入!F59 -> 3.2272727 | G15: =運營_產能與收入!G59 -> 4.26 | I15: 已簽約未起租租賃 85.2 的現金路徑
A16: 租金合計 | B16: US$bn | C16: =輸入與假設!C$283+C15*輸入與假設!$C$284 -> 0.23031376 | D16: =輸入與假設!D$283+D15*輸入與假設!$C$284 -> 0.53288254 | E16: =輸入與假設!E$283+E15*輸入與假設!$C$284 -> 0.65255591 | F16: =輸入與假設!F$283+F15*輸入與假設!$C$284 -> 0.76122927 | G16: =輸入與假設!G$283+G15*輸入與假設!$C$284 -> 0.81990264 | I16: ＝在帳融資租賃現金＋未起租 × 融資部分比例（MAG v0.1b：營業租賃已含在分部 EBITDA，不重複扣除；AI 雲端 EBITDA 由 Tokenomics 推得、未扣租金）
A17: ③ 存量債務利息（備忘，1H 已含在 CFO） | B17: US$bn | C17: =輸入與假設!C$363 -> 2.0126826 | D17: =輸入與假設!D$363 -> 3.9650359 | E17: =輸入與假設!E$363 -> 3.8911126 | F17: =輸入與假設!F$363 -> 3.8018253 | G17: =輸入與假設!G$363 -> 3.6218432 | I17: ="6/30 債務餘額的利息。2026 全年利息＝1H 實際 1.811＋2H "&TEXT(C17,"0.0")&"＝"&TEXT(1.811+C17,"0.00")&"（見下方備忘）" -> 6/30 債務餘額的利息。2026 全年利息＝1H 實際 1.811＋2H 2.0＝3.82（見下方備忘）
A18: 期初累積現金 | B18: US$bn | C18: =輸入與假設!$C$466 -> 120.53 | D18: =C56 -> 128.12291 | E18: =D56 -> 85.935507 | F18: =E56 -> 63.440965 | G18: =F56 -> 53.700182 | I18: 2026 自 2025-12-31 起算；之後＝前期期末累積現金
A19: 新債利率 | B19: % | C19: =IF(輸入與假設!$C$356=1,輸入與假設!C$362+MAX(0,輸入與假設!$C$355-450)/100*0.004,輸入與假設!C$362) -> 0.05 | D19: =IF(輸入與假設!$C$356=1,輸入與假設!D$362+MAX(0,輸入與假設!$C$355-450)/100*0.004,輸入與假設!D$362) -> 0.05 | E19: =IF(輸入與假設!$C$356=1,輸入與假設!E$362+MAX(0,輸入與假設!$C$355-450)/100*0.004,輸入與假設!E$362) -> 0.05 | F19: =IF(輸入與假設!$C$356=1,輸入與假設!F$362+MAX(0,輸入與假設!$C$355-450)/100*0.004,輸入與假設!F$362) -> 0.05 | G19: =IF(輸入與假設!$C$356=1,輸入與假設!G$362+MAX(0,輸入與假設!$C$355-450)/100*0.004,輸入與假設!G$362) -> 0.05 | I19: CDS 開關：＋MAX(0,CDS−450)×0.4bp/bp
A20: ③ 新債利息（瀑布） | B20: US$bn | C20: =C94 -> 0 | D20: =D94 -> 0 | E20: =E94 -> 0 | F20: =F94 -> 0 | G20: =G94 -> 4.2903038 | I20: ＝新債利率×期間長度×(期初新債＋本期舉借)；見下方「期前融資瀑布」
A21: 利息合計 | B21: US$bn | C21: =C17+C20 -> 2.0126826 | D21: =D17+D20 -> 3.9650359 | E21: =E17+E20 -> 3.8911126 | F21: =F17+F20 -> 3.8018253 | G21: =G17+G20 -> 7.912147
A22: ④ JV／策略投資出資 | B22: US$bn | C22: =輸入與假設!$C$470+輸入與假設!C$287 -> 57.662222 | D22: =輸入與假設!D$287 -> 4.444444 | E22: =輸入與假設!E$287 -> 4.444444 | F22: =輸入與假設!F$287 -> 4.444444 | G22: =輸入與假設!G$287 -> 4.444444 | I22: 2026＝1H 實際 55.44（JV 0.000＋策略投資 55.440）＋2H 模型。GOOGL 不發股息
A23: ⑧ 股利（普通股＋特別股） | B23: US$bn | C23: =輸入與假設!$C$485+4*輸入與假設!$C$337*(1+輸入與假設!$C$338)^0*運營_產能與收入!C7*(輸入與假設!$C$339+0+SUMPRODUCT(資產負債_既有債務!$D$27:$D$27*資產負債_既有債務!$H$23:$H$23*(資產負債_既有債務!$G$23:$G$23<0)))+輸入與假設!C$360 -> 11.1472 | D23: =4*輸入與假設!$C$337*(1+輸入與假設!$C$338)^1*運營_產能與收入!D7*(輸入與假設!$C$339+C97+SUMPRODUCT(資產負債_既有債務!$D$27:$D$27*資產負債_既有債務!$H$23:$H$23*(資產負債_既有債務!$G$23:$G$23<1)))+輸入與假設!D$360 -> 12.481108 | E23: =4*輸入與假設!$C$337*(1+輸入與假設!$C$338)^2*運營_產能與收入!E7*(輸入與假設!$C$339+D97+SUMPRODUCT(資產負債_既有債務!$D$27:$D$27*資產負債_既有債務!$H$23:$H$23*(資產負債_既有債務!$G$23:$G$23<2)))+輸入與假設!E$360 -> 12.997948 | F23: =4*輸入與假設!$C$337*(1+輸入與假設!$C$338)^3*運營_產能與收入!F7*(輸入與假設!$C$339+E97+SUMPRODUCT(資產負債_既有債務!$D$27:$D$27*資產負債_既有債務!$H$23:$H$23*(資產負債_既有債務!$G$23:$G$23<3)))+輸入與假設!F$360 -> 12.937277 | G23: =4*輸入與假設!$C$337*(1+輸入與假設!$C$338)^4*運營_產能與收入!G7*(輸入與假設!$C$339+F97+SUMPRODUCT(資產負債_既有債務!$D$27:$D$27*資產負債_既有債務!$H$23:$H$23*(資產負債_既有債務!$G$23:$G$23<4)))+輸入與假設!G$360 -> 12.958555 | I23: 普通股＝每股每季 × 4 × 期間長度 ×(基礎股數＋前期累計瀑布新股＋已強制轉換特別股)＋特別股股利；2026＝1H 實際＋2H 模型（v0.1b）
A24: ⑨ 回購（瀑布：現金不足時先減） | B24: US$bn | C24: =輸入與假設!$C$487+C76 -> 8.5015 | D24: =D76 -> 17.003 | E24: =E76 -> 17.003 | F24: =F76 -> 17.003 | G24: =G76 -> 0 | I24: 2026＝1H 實際＋2H 瀑布後實際回購；計畫與被迫減少見下方「期前融資瀑布」（MAG v0.1b）
A25: 電力（overlay） | B25: US$bn | C25: =IF(輸入與假設!$C$253=1,運營_產能與收入!C9*8760*輸入與假設!C$255*輸入與假設!C$254/1000000000*運營_產能與收入!C7,0) -> 0 | D25: =IF(輸入與假設!$C$253=1,運營_產能與收入!D9*8760*輸入與假設!D$255*輸入與假設!D$254/1000000000*運營_產能與收入!D7,0) -> 0 | E25: =IF(輸入與假設!$C$253=1,運營_產能與收入!E9*8760*輸入與假設!E$255*輸入與假設!E$254/1000000000*運營_產能與收入!E7,0) -> 0 | F25: =IF(輸入與假設!$C$253=1,運營_產能與收入!F9*8760*輸入與假設!F$255*輸入與假設!F$254/1000000000*運營_產能與收入!F7,0) -> 0 | G25: =IF(輸入與假設!$C$253=1,運營_產能與收入!G9*8760*輸入與假設!G$255*輸入與假設!G$254/1000000000*運營_產能與收入!G7,0) -> 0 | I25: ＝已連網 MW×8760×PUE×電價÷1e9×期間係數。EBITDA 率已含電費，預設關閉
A26: 維護（overlay） | B26: US$bn | C26: =IF(輸入與假設!$C$253=1,運營_產能與收入!C9*輸入與假設!C$256/1000*運營_產能與收入!C7,0) -> 0 | D26: =IF(輸入與假設!$C$253=1,運營_產能與收入!D9*輸入與假設!D$256/1000*運營_產能與收入!D7,0) -> 0 | E26: =IF(輸入與假設!$C$253=1,運營_產能與收入!E9*輸入與假設!E$256/1000*運營_產能與收入!E7,0) -> 0 | F26: =IF(輸入與假設!$C$253=1,運營_產能與收入!F9*輸入與假設!F$256/1000*運營_產能與收入!F7,0) -> 0 | G26: =IF(輸入與假設!$C$253=1,運營_產能與收入!G9*輸入與假設!G$256/1000*運營_產能與收入!G7,0) -> 0
A27: ⑤ 排程還本（季報到期表） | B27: US$bn | C27: =輸入與假設!$C$472+IF(輸入與假設!$C$332=1,輸入與假設!C$361,0)+資產負債_既有債務!C38 -> 7.253 | D27: =IF(輸入與假設!$C$332=1,輸入與假設!D$361,0)+資產負債_既有債務!D38 -> 1 | E27: =IF(輸入與假設!$C$332=1,輸入與假設!E$361,0)+資產負債_既有債務!E38 -> 2.676 | F27: =IF(輸入與假設!$C$332=1,輸入與假設!F$361,0)+資產負債_既有債務!F38 -> 1.764 | G27: =IF(輸入與假設!$C$332=1,輸入與假設!G$361,0)+資產負債_既有債務!G38 -> 7.186 | I27: 2026＝1H 實際還款 5.253＋2H 到期表 2.0
A28: ⑥ capped call 支出（1H 實際） | B28: US$bn | C28: =輸入與假設!$C$473 -> 1.011 | D28: =0 -> 0 | E28: =0 -> 0 | F28: =0 -> 0 | G28: =0 -> 0 | I28: 可轉債配套 capped call 現金支出（未見揭露，0）
A29: ⑦ 現金稅（2H 起） | B29: US$bn | C29: =輸入與假設!$C$354*MAX(0,運營_產能與收入!C38*輸入與假設!C$250+輸入與假設!C$48+輸入與假設!C$241-輸入與假設!C$242-運營_產能與收入!C62-輸入與假設!C$324-輸入與假設!C$363) -> 12.491842 | D29: =輸入與假設!$C$354*MAX(0,運營_產能與收入!D38*輸入與假設!D$250+輸入與假設!D$48+輸入與假設!D$241-輸入與假設!D$242-運營_產能與收入!D62-輸入與假設!D$324-輸入與假設!D$363) -> 24.385814 | E29: =輸入與假設!$C$354*MAX(0,運營_產能與收入!E38*輸入與假設!E$250+輸入與假設!E$48+輸入與假設!E$241-輸入與假設!E$242-運營_產能與收入!E62-輸入與假設!E$324-輸入與假設!E$363) -> 25.02638 | F29: =輸入與假設!$C$354*MAX(0,運營_產能與收入!F38*輸入與假設!F$250+輸入與假設!F$48+輸入與假設!F$241-輸入與假設!F$242-運營_產能與收入!F62-輸入與假設!F$324-輸入與假設!F$363) -> 25.729302 | G29: =輸入與假設!$C$354*MAX(0,運營_產能與收入!G38*輸入與假設!G$250+輸入與假設!G$48+輸入與假設!G$241-輸入與假設!G$242-運營_產能與收入!G62-輸入與假設!G$324-輸入與假設!G$363) -> 25.420532 | I29: ＝稅率 × MAX(0, 損益 EBITDA − 車隊 D&A − 存量利息)；1H 的稅已含在 CFO 內（v0.1b）
A30: 用途合計（現金口徑） | B30: US$bn | C30: =C13+C16+C21+C22+C25+C26+C27+C28+C29+C23+C24 -> 300.31455 | D30: =D13+D16+D21+D22+D25+D26+D27+D28+D29+D23+D24 -> 300.64731 | E30: =E13+E16+E21+E22+E25+E26+E27+E28+E29+E23+E24 -> 323.23722 | F30: =F13+F16+F21+F22+F25+F26+F27+F28+F29+F23+F24 -> 354.36761 | G30: =G13+G16+G21+G22+G25+G26+G27+G28+G29+G23+G24 -> 471.53333 | I30: 2026 的 1H 部分採季報現金流量表口徑（現金購置、還款、JV、capped call）；1H 的利息與租金已含在 CFO 內，不重複列
A31: 來源（四層）
A32: Ⓐ0 1H26 實際營運現金流（CFO） | B32: US$bn | C32: =輸入與假設!$C$467 -> 84.859 | D32: =0 -> 0 | E32: =0 -> 0 | F32: =0 -> 0 | G32: =0 -> 0 | I32: 季報實際值，取代模型推算；已含 1H 的利息、租金與客戶預付
A33: Ⓐ RPO 現金（2H 起） | B33: US$bn | C33: =運營_產能與收入!C40 -> 0 | D33: =運營_產能與收入!D40 -> 0 | E33: =運營_產能與收入!E40 -> 0 | F33: =運營_產能與收入!F40 -> 0 | G33: =運營_產能與收入!G40 -> 0
A34: Ⓑ 新簽約現金 | B34: US$bn | C34: =運營_產能與收入!C41 -> 10.613757 | D34: =運營_產能與收入!D41 -> 31.964935 | E34: =運營_產能與收入!E41 -> 46.647862 | F34: =運營_產能與收入!F41 -> 61.445159 | G34: =運營_產能與收入!G41 -> 76.299883
A35: Ⓒ 非算力服務現金 | B35: US$bn | C35: =輸入與假設!C$251 -> 0 | D35: =輸入與假設!D$251 -> 0 | E35: =輸入與假設!E$251 -> 0 | F35: =輸入與假設!F$251 -> 0 | G35: =輸入與假設!G$251 -> 0
A36: Ⓒ2 其他事業 EBITDA（2H 起） | B36: US$bn | C36: =輸入與假設!C$48 -> -2.76 | D36: =輸入與假設!D$48 -> -11.04 | E36: =輸入與假設!E$48 -> -11.04 | F36: =輸入與假設!F$48 -> -5.52 | G36: =輸入與假設!G$48 -> 0 | I36: 非核心事業 EBITDA（負值＝燒錢），視為現金（v0.1b）
A37: Ⓒ3 非 AI 事業 EBITDA（2H 起） | B37: US$bn | C37: =輸入與假設!C$241-輸入與假設!C$242 -> 92.57352 | D37: =輸入與假設!D$241-輸入與假設!D$242 -> 199.71591 | E37: =輸入與假設!E$241-輸入與假設!E$242 -> 221.24535 | F37: =輸入與假設!F$241-輸入與假設!F$242 -> 239.22461 | G37: =輸入與假設!G$241-輸入與假設!G$242 -> 251.65726 | I37: 各線 EBITDA − 其他攤銷（視為等額現金支出），視為現金（現金稅另列於用途；MAG v0.1b）
A38: Ⓒ4 減：延誤罰則（營業費用） | B38: US$bn | C38: =-運營_產能與收入!C62 -> 0 | D38: =-運營_產能與收入!D62 -> 0 | E38: =-運營_產能與收入!E62 -> 0 | F38: =-運營_產能與收入!F62 -> 0 | G38: =-運營_產能與收入!G62 -> 0 | I38: 建設延誤期間應計費而未計費營收 × 罰則比例（預設 0；v0.2）
A39: Ⓒ5 加回：股權報酬（非現金） | B39: US$bn | C39: =輸入與假設!$C$49*(運營_產能與收入!C38+輸入與假設!C$240) -> 16.57618 | D39: =輸入與假設!$C$49*(運營_產能與收入!D38+輸入與假設!D$240) -> 37.819066 | E39: =輸入與假設!$C$49*(運營_產能與收入!E38+輸入與假設!E$240) -> 43.889468 | F39: =輸入與假設!$C$49*(運營_產能與收入!F38+輸入與假設!F$240) -> 49.477061 | G39: =輸入與假設!$C$49*(運營_產能與收入!G38+輸入與假設!G$240) -> 54.069926 | I39: ＝SBC 占營收 × 模型期總營收（分部營業利益已扣 SBC；1H 已含在實際 CFO；MAG v0.1b）
A40: Ⓒ6 首期營運資金變動（上年同期實際） | B40: US$bn | C40: =IF(ISBLANK(輸入與假設!$C$50),0,輸入與假設!$C$50) -> 8.49 | D40: =0 -> 0 | E40: =0 -> 0 | F40: =0 -> 0 | G40: =0 -> 0 | I40: 2026 剩餘季度＝上一年度同期實際（流入為正；10-Q／10-K 現金流量表 [Derived]）；之後年度資金模型不計營運資金（MAG v0.1b r2 C14）
A41: Ⓓ 客戶預付（2H 起） | B41: US$bn | C41: =C8 -> 0 | D41: =D8 -> 0 | E41: =E8 -> 0 | F41: =F8 -> 0 | G41: =G8 -> 0
A42: Ⓓ2 減：預付認列（非現金營收） | B42: US$bn | C42: =-C11 -> 0 | D42: =-D11 -> 0 | E42: =-E11 -> 0 | F42: =-F11 -> 0 | G42: =-G11 -> 0 | I42: 營收中由合約負債轉入的部分已在預付時收現，不重複計入服務現金（v0.1b）
A43: 營運來源合計 | B43: US$bn | C43: =C32+C33+C34+C35+C36+C37+C38+C39+C40+C41+C42 -> 210.35246 | D43: =D32+D33+D34+D35+D36+D37+D38+D39+D40+D41+D42 -> 258.45991 | E43: =E32+E33+E34+E35+E36+E37+E38+E39+E40+E41+E42 -> 300.74268 | F43: =F32+F33+F34+F35+F36+F37+F38+F39+F40+F41+F42 -> 344.62683 | G43: =G32+G33+G34+G35+G36+G37+G38+G39+G40+G41+G42 -> 382.02707
A44: 自由現金流（FCF＝營運現金 − 現金資本支出） | B44: US$bn | C44: =C43-C29-C21-C13 -> -4.1568577 | D44: =D43-D29-D21-D13 -> -6.7259645 | E44: =E43-E29-E21-E13 -> 15.279406 | F44: =F43-F29-F21-F13 -> 27.169167 | G44: =G43-G29-G21-G13 -> -64.097355 | I44: 公司定義近似：營運來源（2026 含 1H 實際 CFO）− 現金稅 − 利息 − 現金資本支出（不扣融資租賃本金）；一頁摘要「FCF 首次為負的年份」（MAG v0.1b）
A45: Ⓔ 股權／可轉債（融資） | B45: US$bn | C45: =輸入與假設!$C$474+IF(輸入與假設!$C$329=1,輸入與假設!$C$328,0) -> 49.562 | D45: =0 -> 0 | E45: =0 -> 0 | F45: =0 -> 0 | G45: =0 -> 0 | I45: 2026＝1H 股權 49.6（普通股 30.5＋強制轉換特別股 19.1）＋2H 期後股權 0（瀑布另計）
A46: Ⓕ 1H26 實際借款（融資） | B46: US$bn | C46: =輸入與假設!$C$471 -> 56.226 | D46: =0 -> 0 | E46: =0 -> 0 | F46: =0 -> 0 | G46: =0 -> 0 | I46: 季報：H1 借款 56.226（2026-03 可轉債）
A47: Ⓖ 瀑布：新債（額度＋資產層） | B47: US$bn | C47: =C86 -> 0 | D47: =D86 -> 0 | E47: =E86 -> 0 | F47: =F86 -> 0 | G47: =G86 -> 85.806075 | I47: 見下方「期前融資瀑布」
A48: Ⓖ2 瀑布：可轉債 | B48: US$bn | C48: =C89 -> 0 | D48: =D89 -> 0 | E48: =E89 -> 0 | F48: =F89 -> 0 | G48: =G89 -> 0 | I48: 資產擔保融資用罄後、股權之前；每年不超過可轉債上限（v0.1b）
A49: Ⓗ 瀑布：股權募資 | B49: US$bn | C49: =C92 -> 0 | D49: =D92 -> 0 | E49: =E92 -> 0 | F49: =F92 -> 0 | G49: =G92 -> 0 | I49: 債務與可轉債用罄後的殘差；每年不超過股權吸收上限
A50: Ⓘ 瀑布：高息債（股權上限溢出） | B50: US$bn | C50: =C93 -> 0 | D50: =D93 -> 0 | E50: =E93 -> 0 | F50: =F93 -> 0 | G50: =G93 -> 0 | I50: 股權超過每年上限的部分；不受 backlog 上限約束
A51: 總來源（含融資） | B51: US$bn | C51: =C43+C45+C46+C47+C48+C49+C50 -> 316.14046 | D51: =D43+D45+D46+D47+D48+D49+D50 -> 258.45991 | E51: =E43+E45+E46+E47+E48+E49+E50 -> 300.74268 | F51: =F43+F45+F46+F47+F48+F49+F50 -> 344.62683 | G51: =G43+G45+G46+G47+G48+G49+G50 -> 467.83315
A52: 缺口與現金橋
A53: 1H 其他／受限現金調節 | B53: US$bn | C53: =輸入與假設!$C$327-(輸入與假設!$C$466+輸入與假設!$C$467+輸入與假設!$C$471+輸入與假設!$C$474-輸入與假設!$C$468-輸入與假設!$C$470-輸入與假設!$C$472-輸入與假設!$C$473-輸入與假設!$C$485-輸入與假設!$C$487) -> -8.233 | D53: =0 -> 0 | E53: =0 -> 0 | F53: =0 -> 0 | G53: =0 -> 0 | I53: 使 1H 實際流量接回 6/30 現金餘額；差額來自受限現金重分類與未逐項列出的項目
A54: 營運缺口（不含融資、不含還本） | B54: US$bn | C54: =C43-(C30-C27-C28) -> -81.698093 | D54: =D43-(D30-D27-D28) -> -41.187399 | E54: =E43-(E30-E27-E28) -> -19.818542 | F54: =F43-(F30-F27-F28) -> -7.9767834 | G54: =G43-(G30-G27-G28) -> -82.320257 | I54: 本業能不能自給：營運來源 −（用途 − 排程還本 − capped call）
A55: 期間缺口（含融資） | B55: US$bn | C55: =C51-C30+C53 -> 7.5929066 | D55: =D51-D30+D53 -> -42.187399 | E55: =E51-E30+E53 -> -22.494542 | F55: =F51-F30+F53 -> -9.7407834 | G55: =G51-G30+G53 -> -3.7001817
A56: 期末累積現金 | B56: US$bn | C56: =C18+C55 -> 128.12291 | D56: =D18+D55 -> 85.935507 | E56: =E18+E55 -> 63.440965 | F56: =F18+F55 -> 53.700182 | G56: =G18+G55 -> 50 | I56: 期前融資：每期末不低於最低現金
A58: 租賃負債（期末剩餘租金現值；調整後槓桿用，v0.2）
A59: 租賃折現率（加權平均） | B59: % | C59: 0.038 | I59: 10-K FY2026 營業／融資租賃加權平均折現率（事實總帳 lease.discRate.fy26）[Verified]；company.json → leases.liability.discRate
A60: 在帳租約：模型期後尾端年數 | B60: 年 | C60: 8 | I60: 到期表 2030 後的未折現付款平均分攤年數（10-K 營業租賃加權平均剩餘期限 12 年）[Derived]
A61: 在帳租賃負債（期末） | B61: US$bn | C61: =輸入與假設!D$280*(1+各期收支!$C$59)^(-(運營_產能與收入!$D$51-運營_產能與收入!$D$7/2-運營_產能與收入!$C$51))+輸入與假設!E$280*(1+各期收支!$C$59)^(-(運營_產能與收入!$E$51-運營_產能與收入!$E$7/2-運營_產能與收入!$C$51))+輸入與假設!F$280*(1+各期收支!$C$59)^(-(運營_產能與收入!$F$51-運營_產能與收入!$F$7/2-運營_產能與收入!$C$51))+輸入與假設!G$280*(1+各期收支!$C$59)^(-(運營_產能與收入!$G$51-運營_產能與收入!$G$7/2-運營_產能與收入!$C$51))+9.707/各期收支!$C$60*(1+各期收支!$C$59)^0.5*(1-(1+各期收支!$C$59)^(-各期收支!$C$60))/各期收支!$C$59*(1+各期收支!$C$59)^(-(運營_產能與收入!$G$51-運營_產能與收入!$C$51)) -> 18.932566 | D61: =輸入與假設!E$280*(1+各期收支!$C$59)^(-(運營_產能與收入!$E$51-運營_產能與收入!$E$7/2-運營_產能與收入!$D$51))+輸入與假設!F$280*(1+各期收支!$C$59)^(-(運營_產能與收入!$F$51-運營_產能與收入!$F$7/2-運營_產能與收入!$D$51))+輸入與假設!G$280*(1+各期收支!$C$59)^(-(運營_產能與收入!$G$51-運營_產能與收入!$G$7/2-運營_產能與收入!$D$51))+9.707/各期收支!$C$60*(1+各期收支!$C$59)^0.5*(1-(1+各期收支!$C$59)^(-各期收支!$C$60))/各期收支!$C$59*(1+各期收支!$C$59)^(-(運營_產能與收入!$G$51-運營_產能與收入!$D$51)) -> 15.693876 | E61: =輸入與假設!F$280*(1+各期收支!$C$59)^(-(運營_產能與收入!$F$51-運營_產能與收入!$F$7/2-運營_產能與收入!$E$51))+輸入與假設!G$280*(1+各期收支!$C$59)^(-(運營_產能與收入!$G$51-運營_產能與收入!$G$7/2-運營_產能與收入!$E$51))+9.707/各期收支!$C$60*(1+各期收支!$C$59)^0.5*(1-(1+各期收支!$C$59)^(-各期收支!$C$60))/各期收支!$C$59*(1+各期收支!$C$59)^(-(運營_產能與收入!$G$51-運營_產能與收入!$E$51)) -> 12.871074 | F61: =輸入與假設!G$280*(1+各期收支!$C$59)^(-(運營_產能與收入!$G$51-運營_產能與收入!$G$7/2-運營_產能與收入!$F$51))+9.707/各期收支!$C$60*(1+各期收支!$C$59)^0.5*(1-(1+各期收支!$C$59)^(-各期收支!$C$60))/各期收支!$C$59*(1+各期收支!$C$59)^(-(運營_產能與收入!$G$51-運營_產能與收入!$F$51)) -> 10.372986 | G61: =9.707/各期收支!$C$60*(1+各期收支!$C$59)^0.5*(1-(1+各期收支!$C$59)^(-各期收支!$C$60))/各期收支!$C$59*(1+各期收支!$C$59)^(-(運營_產能與收入!$G$51-運營_產能與收入!$G$51)) -> 8.3922839 | I61: ＝期末之後各期到期表現金（期中付款）＋模型期後尾端 9.707（平均分攤、年中付款）的現值
A62: 未起租租約已起租部分的租賃負債（期末） | B62: US$bn | C62: =IF(OR(運營_產能與收入!$C$50<=0,運營_產能與收入!$C$56<=0),1*輸入與假設!$C$19/輸入與假設!$C$21/輸入與假設!$C$22/4/((1+各期收支!$C$59)^0.25-1)*(MIN(MAX(0,輸入與假設!C$281-(輸入與假設!$C$20)),輸入與假設!$C$21)-(1+各期收支!$C$59)^(-(4*輸入與假設!$C$22-MAX(0,輸入與假設!C$281-(輸入與假設!$C$20)))/4)*(1-(1+各期收支!$C$59)^(-MIN(MAX(0,輸入與假設!C$281-(輸入與假設!$C$20)),輸入與假設!$C$21)/4))/(1-(1+各期收支!$C$59)^(-0.25))),(1-運營_產能與收入!$C$56)*輸入與假設!$C$19/輸入與假設!$C$21/輸入與假設!$C$22/4/((1+各期收支!$C$59)^0.25-1)*(MIN(MAX(0,輸入與假設!C$281-(輸入與假設!$C$20)),輸入與假設!$C$21)-(1+各期收支!$C$59)^(-(4*輸入與假設!$C$22-MAX(0,輸入與假設!C$281-(輸入與假設!$C$20)))/4)*(1-(1+各期收支!$C$59)^(-MIN(MAX(0,輸入與假設!C$281-(輸入與假設!$C$20)),輸入與假設!$C$21)/4))/(1-(1+各期收支!$C$59)^(-0.25)))+運營_產能與收入!$C$56*輸入與假設!$C$19/輸入與假設!$C$21/輸入與假設!$C$22/4/((1+各期收支!$C$59)^0.25-1)*(MIN(MAX(0,輸入與假設!C$281-(輸入與假設!$C$20+運營_產能與收入!$C$50/3)),輸入與假設!$C$21)-(1+各期收支!$C$59)^(-(4*輸入與假設!$C$22-MAX(0,輸入與假設!C$281-(輸入與假設!$C$20+運營_產能與收入!$C$50/3)))/4)*(1-(1+各期收支!$C$59)^(-MIN(MAX(0,輸入與假設!C$281-(輸入與假設!$C$20+運營_產能與收入!$C$50/3)),輸入與假設!$C$21)/4))/(1-(1+各期收支!$C$59)^(-0.25)))) -> 5.7935677 | D62: =IF(OR(運營_產能與收入!$C$50<=0,運營_產能與收入!$C$56<=0),1*輸入與假設!$C$19/輸入與假設!$C$21/輸入與假設!$C$22/4/((1+各期收支!$C$59)^0.25-1)*(MIN(MAX(0,輸入與假設!D$281-(輸入與假設!$C$20)),輸入與假設!$C$21)-(1+各期收支!$C$59)^(-(4*輸入與假設!$C$22-MAX(0,輸入與假設!D$281-(輸入與假設!$C$20)))/4)*(1-(1+各期收支!$C$59)^(-MIN(MAX(0,輸入與假設!D$281-(輸入與假設!$C$20)),輸入與假設!$C$21)/4))/(1-(1+各期收支!$C$59)^(-0.25))),(1-運營_產能與收入!$C$56)*輸入與假設!$C$19/輸入與假設!$C$21/輸入與假設!$C$22/4/((1+各期收支!$C$59)^0.25-1)*(MIN(MAX(0,輸入與假設!D$281-(輸入與假設!$C$20)),輸入與假設!$C$21)-(1+各期收支!$C$59)^(-(4*輸入與假設!$C$22-MAX(0,輸入與假設!D$281-(輸入與假設!$C$20)))/4)*(1-(1+各期收支!$C$59)^(-MIN(MAX(0,輸入與假設!D$281-(輸入與假設!$C$20)),輸入與假設!$C$21)/4))/(1-(1+各期收支!$C$59)^(-0.25)))+運營_產能與收入!$C$56*輸入與假設!$C$19/輸入與假設!$C$21/輸入與假設!$C$22/4/((1+各期收支!$C$59)^0.25-1)*(MIN(MAX(0,輸入與假設!D$281-(輸入與假設!$C$20+運營_產能與收入!$C$50/3)),輸入與假設!$C$21)-(1+各期收支!$C$59)^(-(4*輸入與假設!$C$22-MAX(0,輸入與假設!D$281-(輸入與假設!$C$20+運營_產能與收入!$C$50/3)))/4)*(1-(1+各期收支!$C$59)^(-MIN(MAX(0,輸入與假設!D$281-(輸入與假設!$C$20+運營_產能與收入!$C$50/3)),輸入與假設!$C$21)/4))/(1-(1+各期收支!$C$59)^(-0.25)))) -> 16.926854 | E62: =IF(OR(運營_產能與收入!$C$50<=0,運營_產能與收入!$C$56<=0),1*輸入與假設!$C$19/輸入與假設!$C$21/輸入與假設!$C$22/4/((1+各期收支!$C$59)^0.25-1)*(MIN(MAX(0,輸入與假設!E$281-(輸入與假設!$C$20)),輸入與假設!$C$21)-(1+各期收支!$C$59)^(-(4*輸入與假設!$C$22-MAX(0,輸入與假設!E$281-(輸入與假設!$C$20)))/4)*(1-(1+各期收支!$C$59)^(-MIN(MAX(0,輸入與假設!E$281-(輸入與假設!$C$20)),輸入與假設!$C$21)/4))/(1-(1+各期收支!$C$59)^(-0.25))),(1-運營_產能與收入!$C$56)*輸入與假設!$C$19/輸入與假設!$C$21/輸入與假設!$C$22/4/((1+各期收支!$C$59)^0.25-1)*(MIN(MAX(0,輸入與假設!E$281-(輸入與假設!$C$20)),輸入與假設!$C$21)-(1+各期收支!$C$59)^(-(4*輸入與假設!$C$22-MAX(0,輸入與假設!E$281-(輸入與假設!$C$20)))/4)*(1-(1+各期收支!$C$59)^(-MIN(MAX(0,輸入與假設!E$281-(輸入與假設!$C$20)),輸入與假設!$C$21)/4))/(1-(1+各期收支!$C$59)^(-0.25)))+運營_產能與收入!$C$56*輸入與假設!$C$19/輸入與假設!$C$21/輸入與假設!$C$22/4/((1+各期收支!$C$59)^0.25-1)*(MIN(MAX(0,輸入與假設!E$281-(輸入與假設!$C$20+運營_產能與收入!$C$50/3)),輸入與假設!$C$21)-(1+各期收支!$C$59)^(-(4*輸入與假設!$C$22-MAX(0,輸入與假設!E$281-(輸入與假設!$C$20+運營_產能與收入!$C$50/3)))/4)*(1-(1+各期收支!$C$59)^(-MIN(MAX(0,輸入與假設!E$281-(輸入與假設!$C$20+運營_產能與收入!$C$50/3)),輸入與假設!$C$21)/4))/(1-(1+各期收支!$C$59)^(-0.25)))) -> 27.435877 | F62: =IF(OR(運營_產能與收入!$C$50<=0,運營_產能與收入!$C$56<=0),1*輸入與假設!$C$19/輸入與假設!$C$21/輸入與假設!$C$22/4/((1+各期收支!$C$59)^0.25-1)*(MIN(MAX(0,輸入與假設!F$281-(輸入與假設!$C$20)),輸入與假設!$C$21)-(1+各期收支!$C$59)^(-(4*輸入與假設!$C$22-MAX(0,輸入與假設!F$281-(輸入與假設!$C$20)))/4)*(1-(1+各期收支!$C$59)^(-MIN(MAX(0,輸入與假設!F$281-(輸入與假設!$C$20)),輸入與假設!$C$21)/4))/(1-(1+各期收支!$C$59)^(-0.25))),(1-運營_產能與收入!$C$56)*輸入與假設!$C$19/輸入與假設!$C$21/輸入與假設!$C$22/4/((1+各期收支!$C$59)^0.25-1)*(MIN(MAX(0,輸入與假設!F$281-(輸入與假設!$C$20)),輸入與假設!$C$21)-(1+各期收支!$C$59)^(-(4*輸入與假設!$C$22-MAX(0,輸入與假設!F$281-(輸入與假設!$C$20)))/4)*(1-(1+各期收支!$C$59)^(-MIN(MAX(0,輸入與假設!F$281-(輸入與假設!$C$20)),輸入與假設!$C$21)/4))/(1-(1+各期收支!$C$59)^(-0.25)))+運營_產能與收入!$C$56*輸入與假設!$C$19/輸入與假設!$C$21/輸入與假設!$C$22/4/((1+各期收支!$C$59)^0.25-1)*(MIN(MAX(0,輸入與假設!F$281-(輸入與假設!$C$20+運營_產能與收入!$C$50/3)),輸入與假設!$C$21)-(1+各期收支!$C$59)^(-(4*輸入與假設!$C$22-MAX(0,輸入與假設!F$281-(輸入與假設!$C$20+運營_產能與收入!$C$50/3)))/4)*(1-(1+各期收支!$C$59)^(-MIN(MAX(0,輸入與假設!F$281-(輸入與假設!$C$20+運營_產能與收入!$C$50/3)),輸入與假設!$C$21)/4))/(1-(1+各期收支!$C$59)^(-0.25)))) -> 37.296913 | G62: =IF(OR(運營_產能與收入!$C$50<=0,運營_產能與收入!$C$56<=0),1*輸入與假設!$C$19/輸入與假設!$C$21/輸入與假設!$C$22/4/((1+各期收支!$C$59)^0.25-1)*(MIN(MAX(0,輸入與假設!G$281-(輸入與假設!$C$20)),輸入與假設!$C$21)-(1+各期收支!$C$59)^(-(4*輸入與假設!$C$22-MAX(0,輸入與假設!G$281-(輸入與假設!$C$20)))/4)*(1-(1+各期收支!$C$59)^(-MIN(MAX(0,輸入與假設!G$281-(輸入與假設!$C$20)),輸入與假設!$C$21)/4))/(1-(1+各期收支!$C$59)^(-0.25))),(1-運營_產能與收入!$C$56)*輸入與假設!$C$19/輸入與假設!$C$21/輸入與假設!$C$22/4/((1+各期收支!$C$59)^0.25-1)*(MIN(MAX(0,輸入與假設!G$281-(輸入與假設!$C$20)),輸入與假設!$C$21)-(1+各期收支!$C$59)^(-(4*輸入與假設!$C$22-MAX(0,輸入與假設!G$281-(輸入與假設!$C$20)))/4)*(1-(1+各期收支!$C$59)^(-MIN(MAX(0,輸入與假設!G$281-(輸入與假設!$C$20)),輸入與假設!$C$21)/4))/(1-(1+各期收支!$C$59)^(-0.25)))+運營_產能與收入!$C$56*輸入與假設!$C$19/輸入與假設!$C$21/輸入與假設!$C$22/4/((1+各期收支!$C$59)^0.25-1)*(MIN(MAX(0,輸入與假設!G$281-(輸入與假設!$C$20+運營_產能與收入!$C$50/3)),輸入與假設!$C$21)-(1+各期收支!$C$59)^(-(4*輸入與假設!$C$22-MAX(0,輸入與假設!G$281-(輸入與假設!$C$20+運營_產能與收入!$C$50/3)))/4)*(1-(1+各期收支!$C$59)^(-MIN(MAX(0,輸入與假設!G$281-(輸入與假設!$C$20+運營_產能與收入!$C$50/3)),輸入與假設!$C$21)/4))/(1-(1+各期收支!$C$59)^(-0.25)))) -> 46.485339 | I62: 每季起租 總額 ÷ 季數、每筆季末付租：已起租各筆剩餘租金現值合計（延誤連動部分起算季延後 延誤月數 ÷ 3）
A63: 租賃負債合計（期末） | B63: US$bn | C63: =C61+C62 -> 24.726133 | D63: =D61+D62 -> 32.620731 | E63: =E61+E62 -> 40.306951 | F63: =F61+F62 -> 47.669899 | G63: =G61+G62 -> 54.877622
A65: 期前融資瀑布（缺口在需要前一期先融好：額度 → 資產層新債 → 股權）
A66: 用途（不含新債利息） | B66: US$bn | C66: =C13+C16+C17+C22+C25+C26+C27+C28+C29+C23 -> 291.81305 | D66: =D13+D16+D17+D22+D25+D26+D27+D28+D29+D23 -> 283.64431 | E66: =E13+E16+E17+E22+E25+E26+E27+E28+E29+E23 -> 306.23422 | F66: =F13+F16+F17+F22+F25+F26+F27+F28+F29+F23 -> 337.36461 | G66: =G13+G16+G17+G22+G25+G26+G27+G28+G29+G23 -> 467.24303 | I66: 避免循環參照：直接由各支出列加總
A67: 新債期初餘額 | B67: US$bn | C67: =0 -> 0 | D67: =C98 -> 0 | E67: =D98 -> 0 | F67: =E98 -> 0 | G67: =F98 -> 0
A68: 新債利率 × 期間長度 | B68: % | C68: =C19*運營_產能與收入!C7 -> 0.025 | D68: =D19*運營_產能與收入!D7 -> 0.05 | E68: =E19*運營_產能與收入!E7 -> 0.05 | F68: =F19*運營_產能與收入!F7 -> 0.05 | G68: =G19*運營_產能與收入!G7 -> 0.05
A69: 高息債期初餘額 | B69: US$bn | C69: =0 -> 0 | D69: =C100 -> 0 | E69: =D100 -> 0 | F69: =E100 -> 0 | G69: =F100 -> 0
A70: 可轉債（瀑布）期初餘額 | B70: US$bn | C70: =0 -> 0 | D70: =C101 -> 0 | E70: =D101 -> 0 | F70: =E101 -> 0 | G70: =F101 -> 0
A71: 可轉債票息 × 期間長度 | B71: % | C71: =輸入與假設!$C$351*運營_產能與收入!C7 -> 0 | D71: =輸入與假設!$C$351*運營_產能與收入!D7 -> 0 | E71: =輸入與假設!$C$351*運營_產能與收入!E7 -> 0 | F71: =輸入與假設!$C$351*運營_產能與收入!F7 -> 0 | G71: =輸入與假設!$C$351*運營_產能與收入!G7 -> 0
A72: 高息債利率 × 期間長度 | B72: % | C72: =(輸入與假設!$C$353+IF(輸入與假設!$C$356=1,MAX(0,輸入與假設!$C$355-輸入與假設!$C$357)/10000*輸入與假設!$C$358,0))*運營_產能與收入!C7 -> 0.06 | D72: =(輸入與假設!$C$353+IF(輸入與假設!$C$356=1,MAX(0,輸入與假設!$C$355-輸入與假設!$C$357)/10000*輸入與假設!$C$358,0))*運營_產能與收入!D7 -> 0.12 | E72: =(輸入與假設!$C$353+IF(輸入與假設!$C$356=1,MAX(0,輸入與假設!$C$355-輸入與假設!$C$357)/10000*輸入與假設!$C$358,0))*運營_產能與收入!E7 -> 0.12 | F72: =(輸入與假設!$C$353+IF(輸入與假設!$C$356=1,MAX(0,輸入與假設!$C$355-輸入與假設!$C$357)/10000*輸入與假設!$C$358,0))*運營_產能與收入!F7 -> 0.12 | G72: =(輸入與假設!$C$353+IF(輸入與假設!$C$356=1,MAX(0,輸入與假設!$C$355-輸入與假設!$C$357)/10000*輸入與假設!$C$358,0))*運營_產能與收入!G7 -> 0.12
A73: 融資前現金（扣既有新債利息） | B73: US$bn | C73: =C18+C43+C45+C46+C53-C66-C68*C67-C72*C69-C71*C70 -> 136.62441 | D73: =D18+D43+D45+D46+D53-D66-D68*D67-D72*D69-D71*D70 -> 102.93851 | E73: =E18+E43+E45+E46+E53-E66-E68*E67-E72*E69-E71*E70 -> 80.443965 | F73: =F18+F43+F45+F46+F53-F66-F68*F67-F72*F69-F71*F70 -> 70.703182 | G73: =G18+G43+G45+G46+G53-G66-G68*G67-G72*G69-G71*G70 -> -31.515771
A74: 融資需求（補足至最低現金） | B74: US$bn | C74: =MAX(0,輸入與假設!$C$340-(C73-C76)) -> 0 | D74: =MAX(0,輸入與假設!$C$340-(D73-D76)) -> 0 | E74: =MAX(0,輸入與假設!$C$340-(E73-E76)) -> 0 | F74: =MAX(0,輸入與假設!$C$340-(F73-F76)) -> 0 | G74: =MAX(0,輸入與假設!$C$340-(G73-G76)) -> 81.515771 | I74: ＝MAX(0, 最低現金 −(融資前現金 − 實際回購))
A75: 回購計畫（基準年額 × 期間長度） | B75: US$bn | C75: =輸入與假設!$C$341*運營_產能與收入!C7 -> 8.5015 | D75: =輸入與假設!$C$341*運營_產能與收入!D7 -> 17.003 | E75: =輸入與假設!$C$341*運營_產能與收入!E7 -> 17.003 | F75: =輸入與假設!$C$341*運營_產能與收入!F7 -> 17.003 | G75: =輸入與假設!$C$341*運營_產能與收入!G7 -> 17.003 | I75: MAG v0.1b：瀑布第二步（現金之後、新債之前）
A76: 回購（實際，減少後） | B76: US$bn | C76: =MIN(C75,MAX(C75*輸入與假設!$C$342,C73-輸入與假設!$C$340)) -> 8.5015 | D76: =MIN(D75,MAX(D75*輸入與假設!$C$342,D73-輸入與假設!$C$340)) -> 17.003 | E76: =MIN(E75,MAX(E75*輸入與假設!$C$342,E73-輸入與假設!$C$340)) -> 17.003 | F76: =MIN(F75,MAX(F75*輸入與假設!$C$342,F73-輸入與假設!$C$340)) -> 17.003 | G76: =MIN(G75,MAX(G75*輸入與假設!$C$342,G73-輸入與假設!$C$340)) -> 0 | I76: ＝MIN(計畫, MAX(下限, 融資前現金 − 最低現金))
A77: 回購被迫減少 | B77: US$bn | C77: =C75-C76 -> 0 | D77: =D75-D76 -> 0 | E77: =E75-E76 -> 0 | F77: =F75-F76 -> 0 | G77: =G75-G76 -> 17.003 | I77: ＝計畫 − 實際（一頁摘要「回購被迫減少的年份與金額」）
A78: 回購股數 | B78: bn | C78: =C76/MAX(0.01,輸入與假設!$C$343) -> 0.02425535 | D78: =D76/MAX(0.01,輸入與假設!$C$343) -> 0.048510699 | E78: =E76/MAX(0.01,輸入與假設!$C$343) -> 0.048510699 | F78: =F76/MAX(0.01,輸入與假設!$C$343) -> 0.048510699 | G78: =G76/MAX(0.01,輸入與假設!$C$343) -> 0 | I78: ＝實際回購 ÷ 發行參考價（現價）
A79: 期初 backlog | B79: US$bn | C79: =輸入與假設!$C$24+輸入與假設!$C$25 -> 0 | D79: =C81 -> 63.61376 | E79: =D81 -> 63.480052 | F79: =E81 -> 59.917072 | G79: =F81 -> 39.3313 | I79: 2026 期初＝6/30 RPO 0.0＋期後新增 0.0
A80: 新簽合約增量（年化增量×年期） | B80: US$bn | C80: =MAX(0,運營_產能與收入!C24/運營_產能與收入!C7-0)*輸入與假設!$C$336 -> 76.336511 | D80: =MAX(0,運營_產能與收入!D24/運營_產能與收入!D7-運營_產能與收入!C24/運營_產能與收入!C7)*輸入與假設!$C$336 -> 37.967694 | E80: =MAX(0,運營_產能與收入!E24/運營_產能與收入!E7-運營_產能與收入!D24/運營_產能與收入!D7)*輸入與假設!$C$336 -> 51.807634 | F80: =MAX(0,運營_產能與收入!F24/運營_產能與收入!F7-運營_產能與收入!E24/運營_產能與收入!E7)*輸入與假設!$C$336 -> 52.177262 | G80: =MAX(0,運營_產能與收入!G24/運營_產能與收入!G7-運營_產能與收入!F24/運營_產能與收入!F7)*輸入與假設!$C$336 -> 52.36286
A81: 期末 backlog | B81: US$bn | C81: =C79-運營_產能與收入!C18-運營_產能與收入!C24+C80 -> 63.61376 | D81: =D79-運營_產能與收入!D18-運營_產能與收入!D24+D80 -> 63.480052 | E81: =E79-運營_產能與收入!E18-運營_產能與收入!E24+E80 -> 59.917072 | F81: =F79-運營_產能與收入!F18-運營_產能與收入!F24+F80 -> 39.3313 | G81: =G79-運營_產能與收入!G18-運營_產能與收入!G24+G80 -> 1.4768399 | I81: ＝期初 − 排程認列 − 新簽約認列 ＋ 新簽合約增量
A82: 既有債務＋期後可轉債（期末） | B82: US$bn | C82: =IF(輸入與假設!$C$332=1,資產負債_既有債務!C34,資產負債_既有債務!$E$16)+資產負債_既有債務!$E$19+資產負債_既有債務!C39 -> 99.085 | D82: =IF(輸入與假設!$C$332=1,資產負債_既有債務!D34,資產負債_既有債務!$E$16)+資產負債_既有債務!$E$19+資產負債_既有債務!D39 -> 98.085 | E82: =IF(輸入與假設!$C$332=1,資產負債_既有債務!E34,資產負債_既有債務!$E$16)+資產負債_既有債務!$E$19+資產負債_既有債務!E39 -> 95.409 | F82: =IF(輸入與假設!$C$332=1,資產負債_既有債務!F34,資產負債_既有債務!$E$16)+資產負債_既有債務!$E$19+資產負債_既有債務!F39 -> 93.645 | G82: =IF(輸入與假設!$C$332=1,資產負債_既有債務!G34,資產負債_既有債務!$E$16)+資產負債_既有債務!$E$19+資產負債_既有債務!G39 -> 86.459 | I82: ＝(依到期表遞減的既有本金，若關閉攤還則維持 101.085)＋期後新發可轉債 0
A83: 債務上限（投資級：倍數 × 當期 EBITDA；或債務／backlog） | B83: US$bn | C83: =IF(輸入與假設!$C$334="leaseAdj",輸入與假設!$C$335*(損益!C22+C16)/運營_產能與收入!C7-C63,IF(輸入與假設!$C$334="ebitda",輸入與假設!$C$335*損益!C22/運營_產能與收入!C7,輸入與假設!$C$333*C81)) -> 579.21941 | D83: =IF(輸入與假設!$C$334="leaseAdj",輸入與假設!$C$335*(損益!D22+D16)/運營_產能與收入!D7-D63,IF(輸入與假設!$C$334="ebitda",輸入與假設!$C$335*損益!D22/運營_產能與收入!D7,輸入與假設!$C$333*D81)) -> 630.90044 | E83: =IF(輸入與假設!$C$334="leaseAdj",輸入與假設!$C$335*(損益!E22+E16)/運營_產能與收入!E7-E63,IF(輸入與假設!$C$334="ebitda",輸入與假設!$C$335*損益!E22/運營_產能與收入!E7,輸入與假設!$C$333*E81)) -> 732.21034 | F83: =IF(輸入與假設!$C$334="leaseAdj",輸入與假設!$C$335*(損益!F22+F16)/運營_產能與收入!F7-F63,IF(輸入與假設!$C$334="ebitda",輸入與假設!$C$335*損益!F22/運營_產能與收入!F7,輸入與假設!$C$333*F81)) -> 840.06309 | G83: =IF(輸入與假設!$C$334="leaseAdj",輸入與假設!$C$335*(損益!G22+G16)/運營_產能與收入!G7-G63,IF(輸入與假設!$C$334="ebitda",輸入與假設!$C$335*損益!G22/運營_產能與收入!G7,輸入與假設!$C$333*G81)) -> 931.45353 | I83: leaseAdj：總債務 ≤ 倍數 ×(損益 EBITDA＋租金)（年化）− 租賃負債（v0.2）；ebitda：總債務 ≤ 倍數 × 損益 EBITDA（年化）；backlog：總債務 ≤ 倍數 × 期末 backlog（模板）
A84: 未動用額度（期初） | B84: US$bn | C84: =IF(輸入與假設!$C$331=1,輸入與假設!$C$330,0) -> 0 | D84: =C99 -> 0 | E84: =D99 -> 0 | F84: =E99 -> 0 | G84: =F99 -> 0
A85: 新債可借上限 | B85: US$bn | C85: =MAX(0,C83-(C82+C67+C70),C84) -> 480.13441 | D85: =MAX(0,D83-(D82+D67+D70),D84) -> 532.81544 | E85: =MAX(0,E83-(E82+E67+E70),E84) -> 636.80134 | F85: =MAX(0,F83-(F82+F67+F70),F84) -> 746.41809 | G85: =MAX(0,G83-(G82+G67+G70),G84) -> 844.99453 | I85: ＝MAX(上限 − 既有債務 − 期初新債 − 期初瀑布可轉債, 未動用額度)
A86: 新債舉借 | B86: US$bn | C86: =MIN(C85,C74/(1-C68)) -> 0 | D86: =MIN(D85,D74/(1-D68)) -> 0 | E86: =MIN(E85,E74/(1-E68)) -> 0 | F86: =MIN(F85,F74/(1-F68)) -> 0 | G86: =MIN(G85,G74/(1-G68)) -> 85.806075 | I86: 期前融資：期初到位，當期全額計息，所以需求要除以 (1−利率×期間)
A87: 債務後剩餘需求 | B87: US$bn | C87: =MAX(0,C74+C68*C86-C86) -> 0 | D87: =MAX(0,D74+D68*D86-D86) -> 0 | E87: =MAX(0,E74+E68*E86-E86) -> 0 | F87: =MAX(0,F74+F68*F86-F86) -> 0 | G87: =MAX(0,G74+G68*G86-G86) -> 0
A88: 可轉債可發行上限 | B88: US$bn | C88: =MAX(0,輸入與假設!$C$350)*運營_產能與收入!C7 -> 0 | D88: =MAX(0,輸入與假設!$C$350)*運營_產能與收入!D7 -> 0 | E88: =MAX(0,輸入與假設!$C$350)*運營_產能與收入!E7 -> 0 | F88: =MAX(0,輸入與假設!$C$350)*運營_產能與收入!F7 -> 0 | G88: =MAX(0,輸入與假設!$C$350)*運營_產能與收入!G7 -> 0 | I88: ＝每年上限（隨情境）× 期間長度
A89: 可轉債發行 | B89: US$bn | C89: =MIN(C88,C87/(1-C71)) -> 0 | D89: =MIN(D88,D87/(1-D71)) -> 0 | E89: =MIN(E88,E87/(1-E71)) -> 0 | F89: =MIN(F88,F87/(1-F71)) -> 0 | G89: =MIN(G88,G87/(1-G71)) -> 0 | I89: 期前融資：期初到位、當期全額計息
A90: 可轉債後剩餘需求 | B90: US$bn | C90: =MAX(0,C87+C71*C89-C89) -> 0 | D90: =MAX(0,D87+D71*D89-D89) -> 0 | E90: =MAX(0,E87+E71*E89-E89) -> 0 | F90: =MAX(0,F87+F71*F89-F89) -> 0 | G90: =MAX(0,G87+G71*G89-G89) -> 0
A91: 每年股權吸收上限 | B91: US$bn | C91: =IF(輸入與假設!$C$345>=9,1E+099,輸入與假設!$C$345*輸入與假設!$C$343*輸入與假設!$C$346*運營_產能與收入!C7) -> 107.16537 | D91: =IF(輸入與假設!$C$345>=9,1E+099,輸入與假設!$C$345*輸入與假設!$C$343*輸入與假設!$C$346*運營_產能與收入!D7) -> 214.33075 | E91: =IF(輸入與假設!$C$345>=9,1E+099,輸入與假設!$C$345*輸入與假設!$C$343*輸入與假設!$C$346*運營_產能與收入!E7) -> 214.33075 | F91: =IF(輸入與假設!$C$345>=9,1E+099,輸入與假設!$C$345*輸入與假設!$C$343*輸入與假設!$C$346*運營_產能與收入!F7) -> 214.33075 | G91: =IF(輸入與假設!$C$345>=9,1E+099,輸入與假設!$C$345*輸入與假設!$C$343*輸入與假設!$C$346*運營_產能與收入!G7) -> 214.33075 | I91: ＝現市值（發行參考價 × 12.23bn 股）× 上限 % × 期間長度
A92: 股權募資 | B92: US$bn | C92: =MIN(C90,C91) -> 0 | D92: =MIN(D90,D91) -> 0 | E92: =MIN(E90,E91) -> 0 | F92: =MIN(F90,F91) -> 0 | G92: =MIN(G90,G91) -> 0
A93: 高息債舉借（溢出） | B93: US$bn | C93: =(C90-C92)/(1-C72) -> 0 | D93: =(D90-D92)/(1-D72) -> 0 | E93: =(E90-E92)/(1-E72) -> 0 | F93: =(F90-F92)/(1-F72) -> 0 | G93: =(G90-G92)/(1-G72) -> 0
A94: 新債＋高息債利息（期初餘額＋本期舉借） | B94: US$bn | C94: =C68*(C67+C86)+C72*(C69+C93)+C71*(C70+C89) -> 0 | D94: =D68*(D67+D86)+D72*(D69+D93)+D71*(D70+D89) -> 0 | E94: =E68*(E67+E86)+E72*(E69+E93)+E71*(E70+E89) -> 0 | F94: =F68*(F67+F86)+F72*(F69+F93)+F71*(F70+F89) -> 0 | G94: =G68*(G67+G86)+G72*(G69+G93)+G71*(G70+G89) -> 4.2903038 | I94: 含瀑布可轉債票息（v0.1b）
A95: 發行價（現價×(1−折價)） | B95: US$ | C95: =輸入與假設!$C$343*(1-輸入與假設!$C$344) -> 315.45 | D95: =輸入與假設!$C$343*(1-輸入與假設!$C$344) -> 315.45 | E95: =輸入與假設!$C$343*(1-輸入與假設!$C$344) -> 315.45 | F95: =輸入與假設!$C$343*(1-輸入與假設!$C$344) -> 315.45 | G95: =輸入與假設!$C$343*(1-輸入與假設!$C$344) -> 315.45
A96: 新發行股數 | B96: bn | C96: =C92/C95 -> 0 | D96: =D92/D95 -> 0 | E96: =E92/E95 -> 0 | F96: =F92/F95 -> 0 | G96: =G92/G95 -> 0
A97: 累計新股 | B97: bn | C97: =C96-C78 -> -0.02425535 | D97: =C97+D96-D78 -> -0.072766049 | E97: =D97+E96-E78 -> -0.12127675 | F97: =E97+F96-F78 -> -0.16978745 | G97: =F97+G96-G78 -> -0.16978745
A98: 新債期末餘額 | B98: US$bn | C98: =C67+C86 -> 0 | D98: =D67+D86 -> 0 | E98: =E67+E86 -> 0 | F98: =F67+F86 -> 0 | G98: =G67+G86 -> 85.806075
A99: 未動用額度（期末） | B99: US$bn | C99: =C84-MIN(C84,C86) -> 0 | D99: =D84-MIN(D84,D86) -> 0 | E99: =E84-MIN(E84,E86) -> 0 | F99: =F84-MIN(F84,F86) -> 0 | G99: =G84-MIN(G84,G86) -> 0
A100: 高息債期末餘額 | B100: US$bn | C100: =C69+C93 -> 0 | D100: =D69+D93 -> 0 | E100: =E69+E93 -> 0 | F100: =F69+F93 -> 0 | G100: =G69+G93 -> 0
A101: 可轉債（瀑布）期末餘額 | B101: US$bn | C101: =C70+C89 -> 0 | D101: =D70+D89 -> 0 | E101: =E70+E89 -> 0 | F101: =F70+F89 -> 0 | G101: =G70+G89 -> 0
A102: 期末總債務（既有＋可轉債＋新債＋高息債） | B102: US$bn | C102: =C82+C98+C101+C100 -> 99.085 | D102: =D82+D98+D101+D100 -> 98.085 | E102: =E82+E98+E101+E100 -> 95.409 | F102: =F82+F98+F101+F100 -> 93.645 | G102: =G82+G98+G101+G100 -> 172.26508
A103: 融資前累積現金 | B103: US$bn | C103: =C18+C43+C45+C46+C53-C66 -> 136.62441 | D103: =C103+D43+D45-D66 -> 111.44001 | E103: =D103+E43+E45-E66 -> 105.94847 | F103: =E103+F43+F45-F66 -> 113.21068 | G103: =F103+G43+G45-G66 -> 27.994729 | I103: 若不做任何新融資的累積現金；負值＝外部資金需求
...

Sheet 季度追蹤
A1: 季度追蹤 — 焦點季的模型／共識／指引／實際與差距（由年度模型拆分；只用於追蹤，不影響年度數字與目標價）
A2: 設定與實際數在『輸入與假設』J 區，共識在 I 區；缺資料顯示「不適用」，實際數空白＝待公布。差距超過門檻的項目附差異原因（拆法＝所屬期間合計差距在門檻內）。第 2 區為 6 季路徑與拆分明細（預設收合）。
A4: 1｜焦點季（『輸入與假設』J 區選擇）：模型／共識／指引／實際與差距
A5: 指標 | B5: 單位 | C5: 模型 | D5: 共識 | E5: 模型 vs 共識 | F5: 指引（低） | G5: 指引（高） | H5: 模型 vs 指引中點 | I5: 實際 | J5: 實際 vs 模型 | K5: 實際 vs 共識 | L5: 實際 vs 指引中點 | M5: 利潤率 pt：模型 vs 共識 | N5: 模型 vs 指引 | O5: 實際 vs 模型 | P5: 實際 vs 共識 | Q5: 實際 vs 指引
A6: 焦點｜營收 | B6: US$bn | C6: =INDEX($C$22:$H$22,輸入與假設!$C$551) -> 127.45744 | D6: =INDEX($C$33:$H$33,輸入與假設!$C$551) -> 不適用 | E6: =INDEX($C$43:$H$43,輸入與假設!$C$551) -> 不適用 | F6: 不適用 | G6: 不適用 | H6: =INDEX($C$44:$H$44,輸入與假設!$C$551) -> 不適用 | I6: =IF(ISNUMBER(INDEX($C$37:$H$37,輸入與假設!$C$551)),INDEX($C$37:$H$37,輸入與假設!$C$551),"待公布") -> 待公布 | J6: =INDEX($C$45:$H$45,輸入與假設!$C$551) | K6: =INDEX($C$46:$H$46,輸入與假設!$C$551) | L6: =INDEX($C$47:$H$47,輸入與假設!$C$551)
A7: 焦點｜調整後 EBITDA | B7: US$bn | C7: =INDEX($C$28:$H$28,輸入與假設!$C$551) -> 49.047364 | D7: =INDEX($C$34:$H$34,輸入與假設!$C$551) -> 不適用 | E7: =INDEX($C$48:$H$48,輸入與假設!$C$551) -> 不適用 | F7: 不適用 | G7: 不適用 | H7: =INDEX($C$49:$H$49,輸入與假設!$C$551) -> 不適用 | I7: =IF(ISNUMBER(INDEX($C$38:$H$38,輸入與假設!$C$551)),INDEX($C$38:$H$38,輸入與假設!$C$551),"待公布") -> 待公布 | J7: =INDEX($C$50:$H$50,輸入與假設!$C$551) | K7: =INDEX($C$51:$H$51,輸入與假設!$C$551) | L7: =INDEX($C$52:$H$52,輸入與假設!$C$551) | M7: =INDEX($C$53:$H$53,輸入與假設!$C$551) -> 不適用 | N7: =INDEX($C$54:$H$54,輸入與假設!$C$551) -> 不適用 | O7: =INDEX($C$55:$H$55,輸入與假設!$C$551) | P7: =INDEX($C$56:$H$56,輸入與假設!$C$551) | Q7: =INDEX($C$57:$H$57,輸入與假設!$C$551)
A8: 焦點｜EBITDA 率 | B8: % | C8: =INDEX($C$27:$H$27,輸入與假設!$C$551) -> 0.38481367 | D8: =INDEX($C$35:$H$35,輸入與假設!$C$551) -> 不適用 | E8: =INDEX($C$58:$H$58,輸入與假設!$C$551) -> 不適用 | F8: 不適用 | G8: 不適用 | H8: =INDEX($C$59:$H$59,輸入與假設!$C$551) -> 不適用 | I8: =IF(ISNUMBER(INDEX($C$39:$H$39,輸入與假設!$C$551)),INDEX($C$39:$H$39,輸入與假設!$C$551),"待公布") -> 待公布 | J8: =INDEX($C$60:$H$60,輸入與假設!$C$551) | K8: =INDEX($C$61:$H$61,輸入與假設!$C$551) | L8: =INDEX($C$62:$H$62,輸入與假設!$C$551)
A9: 焦點｜調整後營業利益 | B9: US$bn | C9: =INDEX($C$31:$H$31,輸入與假設!$C$551) -> 37.018168 | D9: 不適用 | E9: =INDEX($C$63:$H$63,輸入與假設!$C$551) -> 不適用 | F9: 不適用 | G9: 不適用 | H9: =INDEX($C$64:$H$64,輸入與假設!$C$551) -> 不適用 | I9: =IF(ISNUMBER(INDEX($C$40:$H$40,輸入與假設!$C$551)),INDEX($C$40:$H$40,輸入與假設!$C$551),"待公布") -> 待公布 | J9: =INDEX($C$65:$H$65,輸入與假設!$C$551) | K9: =INDEX($C$66:$H$66,輸入與假設!$C$551) | L9: =INDEX($C$67:$H$67,輸入與假設!$C$551) | M9: =INDEX($C$68:$H$68,輸入與假設!$C$551) -> 不適用 | N9: =INDEX($C$69:$H$69,輸入與假設!$C$551) -> 不適用 | O9: =INDEX($C$70:$H$70,輸入與假設!$C$551) | P9: =INDEX($C$71:$H$71,輸入與假設!$C$551) | Q9: =INDEX($C$72:$H$72,輸入與假設!$C$551)
A10: 焦點｜CapEx（毛額） | B10: US$bn | C10: =INDEX($C$32:$H$32,輸入與假設!$C$551) -> 59.703395 | D10: 不適用 | E10: =INDEX($C$73:$H$73,輸入與假設!$C$551) -> 不適用 | F10: 不適用 | G10: 不適用 | H10: =INDEX($C$74:$H$74,輸入與假設!$C$551) -> 不適用 | I10: =IF(ISNUMBER(INDEX($C$41:$H$41,輸入與假設!$C$551)),INDEX($C$41:$H$41,輸入與假設!$C$551),"待公布") -> 待公布 | J10: =INDEX($C$75:$H$75,輸入與假設!$C$551) | K10: =INDEX($C$76:$H$76,輸入與假設!$C$551) | L10: =INDEX($C$77:$H$77,輸入與假設!$C$551)
A11: 焦點｜季末已連網 MW-IT | B11: MW | C11: =INDEX($C$19:$H$19,輸入與假設!$C$551) -> 2212.525 | D11: 不適用 | E11: =INDEX($C$78:$H$78,輸入與假設!$C$551) -> 不適用 | F11: 不適用 | G11: 不適用 | H11: =INDEX($C$79:$H$79,輸入與假設!$C$551) -> 不適用 | I11: =IF(ISNUMBER(INDEX($C$42:$H$42,輸入與假設!$C$551)),INDEX($C$42:$H$42,輸入與假設!$C$551),"待公布") -> 待公布 | J11: =INDEX($C$80:$H$80,輸入與假設!$C$551) | K11: =INDEX($C$81:$H$81,輸入與假設!$C$551) | L11: =INDEX($C$82:$H$82,輸入與假設!$C$551)
A12: 焦點｜季度 | C12: =INDEX($C$16:$H$16,輸入與假設!$C$551) -> Q3 2026
A13: 焦點｜差異原因 | C13: =IF(INDEX($C$119:$H$119,輸入與假設!$C$551)="","無（差距皆在 "&IF(ROUND(ABS(輸入與假設!$C$545)*100,4)=INT(ROUND(ABS(輸入與假設!$C$545)*100,4)),TEXT(ROUND(ABS(輸入與假設!$C$545)*100,4),"0"),TEXT(ROUND(ABS(輸入與假設!$C$545)*100,4),"0.0"))&"%"&" 以內）",INDEX($C$119:$H$119,輸入與假設!$C$551)) -> 無（差距皆在 5% 以內）
A15: 2｜6 季路徑、共識、指引、實際與差距（明細；第 1 區以焦點季引用本區）
A16: 項目 | B16: 單位 | C16: Q3 2026 | D16: Q4 2026 | E16: Q1 2027 | F16: Q2 2027 | G16: Q3 2027 | H16: Q4 2027
A17: 所屬期間 | C17: =輸入與假設!C$550 -> 1 | D17: =輸入與假設!D$550 -> 1 | E17: =輸入與假設!E$550 -> 2 | F17: =輸入與假設!F$550 -> 2 | G17: =輸入與假設!G$550 -> 2 | H17: =輸入與假設!H$550 -> 2 | J17: 1＝2H26、2＝2027
A18: 季序 | C18: 1 | D18: 2 | E18: 3 | F18: 4 | G18: 5 | H18: 6 | J18: EBITDA 率直線的 x 軸
A19: 季末已連網 MW-IT（模型） | B19: MW | C19: =輸入與假設!$C$553+(輸入與假設!C$36-輸入與假設!$C$553)*1/2 -> 2212.525 | D19: =輸入與假設!$C$553+(輸入與假設!C$36-輸入與假設!$C$553)*2/2 -> 2524.05 | E19: =輸入與假設!C$36+(輸入與假設!D$36-輸入與假設!C$36)*1/4 -> 2835.575 | F19: =輸入與假設!C$36+(輸入與假設!D$36-輸入與假設!C$36)*2/4 -> 3147.1 | G19: =輸入與假設!C$36+(輸入與假設!D$36-輸入與假設!C$36)*3/4 -> 3458.625 | H19: =輸入與假設!C$36+(輸入與假設!D$36-輸入與假設!C$36)*4/4 -> 3770.15 | J19: 期初與期末 Accepted 之間線性內插；第 1 期起點見 J 區
A20: 平均在役 MW（Billable，拆分依據） | B20: MW | C20: =輸入與假設!$C$29+(運營_產能與收入!C$11-輸入與假設!$C$29)*1/4 -> 2056.75 | D20: =輸入與假設!$C$29+(運營_產能與收入!C$11-輸入與假設!$C$29)*3/4 -> 2368.25 | E20: =運營_產能與收入!C$11+(運營_產能與收入!D$11-運營_產能與收入!C$11)*1/8 -> 2679.75 | F20: =運營_產能與收入!C$11+(運營_產能與收入!D$11-運營_產能與收入!C$11)*3/8 -> 2991.25 | G20: =運營_產能與收入!C$11+(運營_產能與收入!D$11-運營_產能與收入!C$11)*5/8 -> 3302.75 | H20: =運營_產能與收入!C$11+(運營_產能與收入!D$11-運營_產能與收入!C$11)*7/8 -> 3614.25 | J20: 期初與期末 Billable 之間線性內插的季平均
A21: 季內新增 Accepted MW | B21: MW | C21: =C19-輸入與假設!$C$553 -> 311.525 | D21: =D19-C19 -> 311.525 | E21: =E19-輸入與假設!C$36 -> 311.525 | F21: =F19-E19 -> 311.525 | G21: =G19-F19 -> 311.525 | H21: =H19-G19 -> 311.525 | J21: CapEx 拆分依據
A22: 營收（模型） | B22: US$bn | C22: =輸入與假設!$C$552+1*(損益!C9-2*輸入與假設!$C$552)/3 -> 127.45744 | D22: =輸入與假設!$C$552+2*(損益!C9-2*輸入與假設!$C$552)/3 -> 135.11887 | E22: =損益!D9*E20/(E20+F20+G20+H20) -> 127.53208 | F22: =損益!D9*F20/(E20+F20+G20+H20) -> 142.35669 | G22: =損益!D9*G20/(E20+F20+G20+H20) -> 157.18129 | H22: =損益!D9*H20/(E20+F20+G20+H20) -> 172.0059 | J22: 拆分方法見『輸入與假設』J 區與 HTML「拆分方法」
A23: EBITDA 率直線｜各期營收合計 S | C23: =C22+D22 -> 262.57631 | D23: =E22+F22+G22+H22 -> 599.07596 | J23: 欄＝期間（2H26、2027）
A24: EBITDA 率直線｜營收 × 季序合計 T | C24: =C22*C18+D22*D18 -> 397.69518 | D24: =E22*E18+F22*F18+G22*G18+H22*H18 -> 2769.9648 | J24: 欄＝期間（2H26、2027）
A25: EBITDA 率直線｜年度 EBITDA E | C25: =損益!C22 -> 100.42728 | D25: =損益!D22 -> 220.64084 | J25: 欄＝期間（2H26、2027）
A26: EBITDA 率直線｜截距 a／斜率 b | C26: =(C25*D24-C24*D25)/(C23*D24-C24*D23) -> 0.38937023 | D26: =(C23*D25-D23*C25)/(C23*D24-C24*D23) -> -0.0045565556 | J26: 解兩式：Σ營收×(a＋b×季序)＝各期年度 EBITDA
A27: EBITDA 率（模型） | B27: % | C27: =$C$26+$D$26*C18 -> 0.38481367 | D27: =$C$26+$D$26*D18 -> 0.38025712 | E27: =$C$26+$D$26*E18 -> 0.37570056 | F27: =$C$26+$D$26*F18 -> 0.371144 | G27: =$C$26+$D$26*G18 -> 0.36658745 | H27: =$C$26+$D$26*H18 -> 0.36203089 | J27: 跨季一條直線，季度 EBITDA 加總＝年度
A28: 調整後 EBITDA（模型） | B28: US$bn | C28: =C22*C27 -> 49.047364 | D28: =D22*D27 -> 51.379913 | E28: =E22*E27 -> 47.913873 | F28: =F22*F27 -> 52.83483 | G28: =G22*G27 -> 57.620689 | H28: =H22*H27 -> 62.27145
A29: 車隊折舊（模型） | B29: US$bn | C29: =輸入與假設!C$324/2 -> 12.029197 | D29: =輸入與假設!C$324/2 -> 12.029197 | E29: =輸入與假設!D$324/4 -> 17.880538 | F29: =輸入與假設!D$324/4 -> 17.880538 | G29: =輸入與假設!D$324/4 -> 17.880538 | H29: =輸入與假設!D$324/4 -> 17.880538 | J29: ＝期間 D&A（AI＋非 AI 分池）÷ 期內季數
A30: 其他攤銷（模型） | B30: US$bn | C30: =輸入與假設!C$242*C22/MAX(0.000000001,C23) -> 0 | D30: =輸入與假設!C$242*D22/MAX(0.000000001,C23) -> 0 | E30: =輸入與假設!D$242*E22/MAX(0.000000001,D23) -> 0 | F30: =輸入與假設!D$242*F22/MAX(0.000000001,D23) -> 0 | G30: =輸入與假設!D$242*G22/MAX(0.000000001,D23) -> 0 | H30: =輸入與假設!D$242*H22/MAX(0.000000001,D23) -> 0 | J30: ＝期間非 AI 事業其他攤銷 × 季營收占比（MAG v0.1b）
A31: 調整後營業利益（模型） | B31: US$bn | C31: =C28-C29-C30 -> 37.018168 | D31: =D28-D29-D30 -> 39.350716 | E31: =E28-E29-E30 -> 30.033335 | F31: =F28-F29-F30 -> 34.954293 | G31: =G28-G29-G30 -> 39.740152 | H31: =H28-H29-H30 -> 44.390912 | J31: ＝調整後 EBITDA − 車隊折舊 − 其他攤銷（未扣 SBC）
A32: CapEx（毛額）（模型） | B32: US$bn | C32: =IF((C21+D21)>0,輸入與假設!C$323*C21/(C21+D21),輸入與假設!C$323/2) -> 59.703395 | D32: =IF((C21+D21)>0,輸入與假設!C$323*D21/(C21+D21),輸入與假設!C$323/2) -> 59.703395 | E32: =IF((E21+F21+G21+H21)>0,輸入與假設!D$323*E21/(E21+F21+G21+H21),輸入與假設!D$323/4) -> 59.208756 | F32: =IF((E21+F21+G21+H21)>0,輸入與假設!D$323*F21/(E21+F21+G21+H21),輸入與假設!D$323/4) -> 59.208756 | G32: =IF((E21+F21+G21+H21)>0,輸入與假設!D$323*G21/(E21+F21+G21+H21),輸入與假設!D$323/4) -> 59.208756 | H32: =IF((E21+F21+G21+H21)>0,輸入與假設!D$323*H21/(E21+F21+G21+H21),輸入與假設!D$323/4) -> 59.208756 | J32: 依季內新增 Accepted MW
A33: 共識｜營收 | B33: US$bn | C33: 不適用 | D33: 不適用 | E33: 不適用 | F33: 不適用 | G33: 不適用 | H33: 不適用 | J33: I 區季度共識 [Interested-party]
A34: 共識｜調整後 EBITDA | B34: US$bn | C34: 不適用 | D34: 不適用 | E34: 不適用 | F34: 不適用 | G34: 不適用 | H34: 不適用 | J34: I 區季度共識 [Interested-party]
A35: 共識｜EBITDA 率 [Derived] | B35: % | C35: 不適用 | D35: 不適用 | E35: 不適用 | F35: 不適用 | G35: 不適用 | H35: 不適用 | J35: ＝共識 EBITDA ÷ 共識營收
A36: 共識 EBIT（供應商口徑） | B36: US$bn | C36: 不適用 | D36: 不適用 | E36: 不適用 | F36: 不適用 | G36: 不適用 | H36: 不適用 | J36: 口徑未揭露：只列不比較
A37: 實際｜營收 | B37: US$bn | C37: =IF(ISNUMBER(輸入與假設!C$554),輸入與假設!C$554,"") | D37: =IF(ISNUMBER(輸入與假設!D$554),輸入與假設!D$554,"") | E37: =IF(ISNUMBER(輸入與假設!E$554),輸入與假設!E$554,"") | F37: =IF(ISNUMBER(輸入與假設!F$554),輸入與假設!F$554,"") | G37: =IF(ISNUMBER(輸入與假設!G$554),輸入與假設!G$554,"") | H37: =IF(ISNUMBER(輸入與假設!H$554),輸入與假設!H$554,"")
A38: 實際｜調整後 EBITDA | B38: US$bn | C38: =IF(ISNUMBER(輸入與假設!C$555),輸入與假設!C$555,"") | D38: =IF(ISNUMBER(輸入與假設!D$555),輸入與假設!D$555,"") | E38: =IF(ISNUMBER(輸入與假設!E$555),輸入與假設!E$555,"") | F38: =IF(ISNUMBER(輸入與假設!F$555),輸入與假設!F$555,"") | G38: =IF(ISNUMBER(輸入與假設!G$555),輸入與假設!G$555,"") | H38: =IF(ISNUMBER(輸入與假設!H$555),輸入與假設!H$555,"")
A39: 實際｜EBITDA 率 | B39: % | C39: =IF(AND(ISNUMBER(輸入與假設!C$555),ISNUMBER(輸入與假設!C$554)),輸入與假設!C$555/輸入與假設!C$554,"") | D39: =IF(AND(ISNUMBER(輸入與假設!D$555),ISNUMBER(輸入與假設!D$554)),輸入與假設!D$555/輸入與假設!D$554,"") | E39: =IF(AND(ISNUMBER(輸入與假設!E$555),ISNUMBER(輸入與假設!E$554)),輸入與假設!E$555/輸入與假設!E$554,"") | F39: =IF(AND(ISNUMBER(輸入與假設!F$555),ISNUMBER(輸入與假設!F$554)),輸入與假設!F$555/輸入與假設!F$554,"") | G39: =IF(AND(ISNUMBER(輸入與假設!G$555),ISNUMBER(輸入與假設!G$554)),輸入與假設!G$555/輸入與假設!G$554,"") | H39: =IF(AND(ISNUMBER(輸入與假設!H$555),ISNUMBER(輸入與假設!H$554)),輸入與假設!H$555/輸入與假設!H$554,"") | J39: ＝實際 EBITDA ÷ 實際營收
A40: 實際｜調整後營業利益 | B40: US$bn | C40: =IF(ISNUMBER(輸入與假設!C$556),輸入與假設!C$556,"") | D40: =IF(ISNUMBER(輸入與假設!D$556),輸入與假設!D$556,"") | E40: =IF(ISNUMBER(輸入與假設!E$556),輸入與假設!E$556,"") | F40: =IF(ISNUMBER(輸入與假設!F$556),輸入與假設!F$556,"") | G40: =IF(ISNUMBER(輸入與假設!G$556),輸入與假設!G$556,"") | H40: =IF(ISNUMBER(輸入與假設!H$556),輸入與假設!H$556,"")
A41: 實際｜CapEx（毛額） | B41: US$bn | C41: =IF(ISNUMBER(輸入與假設!C$557),輸入與假設!C$557,"") | D41: =IF(ISNUMBER(輸入與假設!D$557),輸入與假設!D$557,"") | E41: =IF(ISNUMBER(輸入與假設!E$557),輸入與假設!E$557,"") | F41: =IF(ISNUMBER(輸入與假設!F$557),輸入與假設!F$557,"") | G41: =IF(ISNUMBER(輸入與假設!G$557),輸入與假設!G$557,"") | H41: =IF(ISNUMBER(輸入與假設!H$557),輸入與假設!H$557,"")
A42: 實際｜季末對外 AI MW（未揭露） | B42: MW | C42: =IF(ISNUMBER(輸入與假設!C$558),輸入與假設!C$558,"") | D42: =IF(ISNUMBER(輸入與假設!D$558),輸入與假設!D$558,"") | E42: =IF(ISNUMBER(輸入與假設!E$558),輸入與假設!E$558,"") | F42: =IF(ISNUMBER(輸入與假設!F$558),輸入與假設!F$558,"") | G42: =IF(ISNUMBER(輸入與假設!G$558),輸入與假設!G$558,"") | H42: =IF(ISNUMBER(輸入與假設!H$558),輸入與假設!H$558,"")
A43: 差距｜營收｜模型 vs 共識 | B43: % | C43: =IF(AND(ISNUMBER(C22),ISNUMBER(C33),C33<>0),C22/(C33)-1,"不適用") -> 不適用 | D43: =IF(AND(ISNUMBER(D22),ISNUMBER(D33),D33<>0),D22/(D33)-1,"不適用") -> 不適用 | E43: =IF(AND(ISNUMBER(E22),ISNUMBER(E33),E33<>0),E22/(E33)-1,"不適用") -> 不適用 | F43: =IF(AND(ISNUMBER(F22),ISNUMBER(F33),F33<>0),F22/(F33)-1,"不適用") -> 不適用 | G43: =IF(AND(ISNUMBER(G22),ISNUMBER(G33),G33<>0),G22/(G33)-1,"不適用") -> 不適用 | H43: =IF(AND(ISNUMBER(H22),ISNUMBER(H33),H33<>0),H22/(H33)-1,"不適用") -> 不適用
A44: 差距｜營收｜模型 vs 指引中點 | B44: % | C44: 不適用 | D44: 不適用 | E44: 不適用 | F44: 不適用 | G44: 不適用 | H44: 不適用
A45: 差距｜營收｜實際 vs 模型 | B45: % | C45: =IF(ISNUMBER(C37),IF(AND(ISNUMBER(C22),C22<>0),C37/(C22)-1,"不適用"),"") | D45: =IF(ISNUMBER(D37),IF(AND(ISNUMBER(D22),D22<>0),D37/(D22)-1,"不適用"),"") | E45: =IF(ISNUMBER(E37),IF(AND(ISNUMBER(E22),E22<>0),E37/(E22)-1,"不適用"),"") | F45: =IF(ISNUMBER(F37),IF(AND(ISNUMBER(F22),F22<>0),F37/(F22)-1,"不適用"),"") | G45: =IF(ISNUMBER(G37),IF(AND(ISNUMBER(G22),G22<>0),G37/(G22)-1,"不適用"),"") | H45: =IF(ISNUMBER(H37),IF(AND(ISNUMBER(H22),H22<>0),H37/(H22)-1,"不適用"),"")
A46: 差距｜營收｜實際 vs 共識 | B46: % | C46: =IF(ISNUMBER(C37),IF(AND(ISNUMBER(C33),C33<>0),C37/(C33)-1,"不適用"),"") | D46: =IF(ISNUMBER(D37),IF(AND(ISNUMBER(D33),D33<>0),D37/(D33)-1,"不適用"),"") | E46: =IF(ISNUMBER(E37),IF(AND(ISNUMBER(E33),E33<>0),E37/(E33)-1,"不適用"),"") | F46: =IF(ISNUMBER(F37),IF(AND(ISNUMBER(F33),F33<>0),F37/(F33)-1,"不適用"),"") | G46: =IF(ISNUMBER(G37),IF(AND(ISNUMBER(G33),G33<>0),G37/(G33)-1,"不適用"),"") | H46: =IF(ISNUMBER(H37),IF(AND(ISNUMBER(H33),H33<>0),H37/(H33)-1,"不適用"),"")
A47: 差距｜營收｜實際 vs 指引中點 | B47: % | C47: =IF(ISNUMBER(C37),"不適用","") | D47: =IF(ISNUMBER(D37),"不適用","") | E47: =IF(ISNUMBER(E37),"不適用","") | F47: =IF(ISNUMBER(F37),"不適用","") | G47: =IF(ISNUMBER(G37),"不適用","") | H47: =IF(ISNUMBER(H37),"不適用","")
A48: 差距｜調整後 EBITDA｜模型 vs 共識 | B48: US$bn | C48: =IF(AND(ISNUMBER(C28),ISNUMBER(C34)),C28-(C34),"不適用") -> 不適用 | D48: =IF(AND(ISNUMBER(D28),ISNUMBER(D34)),D28-(D34),"不適用") -> 不適用 | E48: =IF(AND(ISNUMBER(E28),ISNUMBER(E34)),E28-(E34),"不適用") -> 不適用 | F48: =IF(AND(ISNUMBER(F28),ISNUMBER(F34)),F28-(F34),"不適用") -> 不適用 | G48: =IF(AND(ISNUMBER(G28),ISNUMBER(G34)),G28-(G34),"不適用") -> 不適用 | H48: =IF(AND(ISNUMBER(H28),ISNUMBER(H34)),H28-(H34),"不適用") -> 不適用
A49: 差距｜調整後 EBITDA｜模型 vs 指引中點 | B49: US$bn | C49: 不適用 | D49: 不適用 | E49: 不適用 | F49: 不適用 | G49: 不適用 | H49: 不適用
A50: 差距｜調整後 EBITDA｜實際 vs 模型 | B50: US$bn | C50: =IF(ISNUMBER(C38),IF(AND(ISNUMBER(C28)),C38-(C28),"不適用"),"") | D50: =IF(ISNUMBER(D38),IF(AND(ISNUMBER(D28)),D38-(D28),"不適用"),"") | E50: =IF(ISNUMBER(E38),IF(AND(ISNUMBER(E28)),E38-(E28),"不適用"),"") | F50: =IF(ISNUMBER(F38),IF(AND(ISNUMBER(F28)),F38-(F28),"不適用"),"") | G50: =IF(ISNUMBER(G38),IF(AND(ISNUMBER(G28)),G38-(G28),"不適用"),"") | H50: =IF(ISNUMBER(H38),IF(AND(ISNUMBER(H28)),H38-(H28),"不適用"),"")
A51: 差距｜調整後 EBITDA｜實際 vs 共識 | B51: US$bn | C51: =IF(ISNUMBER(C38),IF(AND(ISNUMBER(C34)),C38-(C34),"不適用"),"") | D51: =IF(ISNUMBER(D38),IF(AND(ISNUMBER(D34)),D38-(D34),"不適用"),"") | E51: =IF(ISNUMBER(E38),IF(AND(ISNUMBER(E34)),E38-(E34),"不適用"),"") | F51: =IF(ISNUMBER(F38),IF(AND(ISNUMBER(F34)),F38-(F34),"不適用"),"") | G51: =IF(ISNUMBER(G38),IF(AND(ISNUMBER(G34)),G38-(G34),"不適用"),"") | H51: =IF(ISNUMBER(H38),IF(AND(ISNUMBER(H34)),H38-(H34),"不適用"),"")
A52: 差距｜調整後 EBITDA｜實際 vs 指引中點 | B52: US$bn | C52: =IF(ISNUMBER(C38),"不適用","") | D52: =IF(ISNUMBER(D38),"不適用","") | E52: =IF(ISNUMBER(E38),"不適用","") | F52: =IF(ISNUMBER(F38),"不適用","") | G52: =IF(ISNUMBER(G38),"不適用","") | H52: =IF(ISNUMBER(H38),"不適用","")
A53: 差距｜調整後 EBITDA｜模型 vs 共識（利潤率 pt） | B53: pt | C53: =IF(AND(ISNUMBER(C28),ISNUMBER(C22),C22<>0,ISNUMBER(C34),ISNUMBER(C33),C33<>0),C28/C22-C34/C33,"不適用") -> 不適用 | D53: =IF(AND(ISNUMBER(D28),ISNUMBER(D22),D22<>0,ISNUMBER(D34),ISNUMBER(D33),D33<>0),D28/D22-D34/D33,"不適用") -> 不適用 | E53: =IF(AND(ISNUMBER(E28),ISNUMBER(E22),E22<>0,ISNUMBER(E34),ISNUMBER(E33),E33<>0),E28/E22-E34/E33,"不適用") -> 不適用 | F53: =IF(AND(ISNUMBER(F28),ISNUMBER(F22),F22<>0,ISNUMBER(F34),ISNUMBER(F33),F33<>0),F28/F22-F34/F33,"不適用") -> 不適用 | G53: =IF(AND(ISNUMBER(G28),ISNUMBER(G22),G22<>0,ISNUMBER(G34),ISNUMBER(G33),G33<>0),G28/G22-G34/G33,"不適用") -> 不適用 | H53: =IF(AND(ISNUMBER(H28),ISNUMBER(H22),H22<>0,ISNUMBER(H34),ISNUMBER(H33),H33<>0),H28/H22-H34/H33,"不適用") -> 不適用
A54: 差距｜調整後 EBITDA｜模型 vs 指引中點（利潤率 pt） | B54: pt | C54: 不適用 | D54: 不適用 | E54: 不適用 | F54: 不適用 | G54: 不適用 | H54: 不適用
A55: 差距｜調整後 EBITDA｜實際 vs 模型（利潤率 pt） | B55: pt | C55: =IF(ISNUMBER(C38),IF(AND(ISNUMBER(C38),ISNUMBER(C37),C37<>0,ISNUMBER(C28),ISNUMBER(C22),C22<>0),C38/C37-C28/C22,"不適用"),"") | D55: =IF(ISNUMBER(D38),IF(AND(ISNUMBER(D38),ISNUMBER(D37),D37<>0,ISNUMBER(D28),ISNUMBER(D22),D22<>0),D38/D37-D28/D22,"不適用"),"") | E55: =IF(ISNUMBER(E38),IF(AND(ISNUMBER(E38),ISNUMBER(E37),E37<>0,ISNUMBER(E28),ISNUMBER(E22),E22<>0),E38/E37-E28/E22,"不適用"),"") | F55: =IF(ISNUMBER(F38),IF(AND(ISNUMBER(F38),ISNUMBER(F37),F37<>0,ISNUMBER(F28),ISNUMBER(F22),F22<>0),F38/F37-F28/F22,"不適用"),"") | G55: =IF(ISNUMBER(G38),IF(AND(ISNUMBER(G38),ISNUMBER(G37),G37<>0,ISNUMBER(G28),ISNUMBER(G22),G22<>0),G38/G37-G28/G22,"不適用"),"") | H55: =IF(ISNUMBER(H38),IF(AND(ISNUMBER(H38),ISNUMBER(H37),H37<>0,ISNUMBER(H28),ISNUMBER(H22),H22<>0),H38/H37-H28/H22,"不適用"),"")
A56: 差距｜調整後 EBITDA｜實際 vs 共識（利潤率 pt） | B56: pt | C56: =IF(ISNUMBER(C38),IF(AND(ISNUMBER(C38),ISNUMBER(C37),C37<>0,ISNUMBER(C34),ISNUMBER(C33),C33<>0),C38/C37-C34/C33,"不適用"),"") | D56: =IF(ISNUMBER(D38),IF(AND(ISNUMBER(D38),ISNUMBER(D37),D37<>0,ISNUMBER(D34),ISNUMBER(D33),D33<>0),D38/D37-D34/D33,"不適用"),"") | E56: =IF(ISNUMBER(E38),IF(AND(ISNUMBER(E38),ISNUMBER(E37),E37<>0,ISNUMBER(E34),ISNUMBER(E33),E33<>0),E38/E37-E34/E33,"不適用"),"") | F56: =IF(ISNUMBER(F38),IF(AND(ISNUMBER(F38),ISNUMBER(F37),F37<>0,ISNUMBER(F34),ISNUMBER(F33),F33<>0),F38/F37-F34/F33,"不適用"),"") | G56: =IF(ISNUMBER(G38),IF(AND(ISNUMBER(G38),ISNUMBER(G37),G37<>0,ISNUMBER(G34),ISNUMBER(G33),G33<>0),G38/G37-G34/G33,"不適用"),"") | H56: =IF(ISNUMBER(H38),IF(AND(ISNUMBER(H38),ISNUMBER(H37),H37<>0,ISNUMBER(H34),ISNUMBER(H33),H33<>0),H38/H37-H34/H33,"不適用"),"")
A57: 差距｜調整後 EBITDA｜實際 vs 指引中點（利潤率 pt） | B57: pt | C57: =IF(ISNUMBER(C38),"不適用","") | D57: =IF(ISNUMBER(D38),"不適用","") | E57: =IF(ISNUMBER(E38),"不適用","") | F57: =IF(ISNUMBER(F38),"不適用","") | G57: =IF(ISNUMBER(G38),"不適用","") | H57: =IF(ISNUMBER(H38),"不適用","")
A58: 差距｜EBITDA 率｜模型 vs 共識 | B58: pt | C58: =IF(AND(ISNUMBER(C27),ISNUMBER(C35)),C27-(C35),"不適用") -> 不適用 | D58: =IF(AND(ISNUMBER(D27),ISNUMBER(D35)),D27-(D35),"不適用") -> 不適用 | E58: =IF(AND(ISNUMBER(E27),ISNUMBER(E35)),E27-(E35),"不適用") -> 不適用 | F58: =IF(AND(ISNUMBER(F27),ISNUMBER(F35)),F27-(F35),"不適用") -> 不適用 | G58: =IF(AND(ISNUMBER(G27),ISNUMBER(G35)),G27-(G35),"不適用") -> 不適用 | H58: =IF(AND(ISNUMBER(H27),ISNUMBER(H35)),H27-(H35),"不適用") -> 不適用
A59: 差距｜EBITDA 率｜模型 vs 指引中點 | B59: pt | C59: 不適用 | D59: 不適用 | E59: 不適用 | F59: 不適用 | G59: 不適用 | H59: 不適用
A60: 差距｜EBITDA 率｜實際 vs 模型 | B60: pt | C60: =IF(ISNUMBER(C39),IF(AND(ISNUMBER(C27)),C39-(C27),"不適用"),"") | D60: =IF(ISNUMBER(D39),IF(AND(ISNUMBER(D27)),D39-(D27),"不適用"),"") | E60: =IF(ISNUMBER(E39),IF(AND(ISNUMBER(E27)),E39-(E27),"不適用"),"") | F60: =IF(ISNUMBER(F39),IF(AND(ISNUMBER(F27)),F39-(F27),"不適用"),"") | G60: =IF(ISNUMBER(G39),IF(AND(ISNUMBER(G27)),G39-(G27),"不適用"),"") | H60: =IF(ISNUMBER(H39),IF(AND(ISNUMBER(H27)),H39-(H27),"不適用"),"")
A61: 差距｜EBITDA 率｜實際 vs 共識 | B61: pt | C61: =IF(ISNUMBER(C39),IF(AND(ISNUMBER(C35)),C39-(C35),"不適用"),"") | D61: =IF(ISNUMBER(D39),IF(AND(ISNUMBER(D35)),D39-(D35),"不適用"),"") | E61: =IF(ISNUMBER(E39),IF(AND(ISNUMBER(E35)),E39-(E35),"不適用"),"") | F61: =IF(ISNUMBER(F39),IF(AND(ISNUMBER(F35)),F39-(F35),"不適用"),"") | G61: =IF(ISNUMBER(G39),IF(AND(ISNUMBER(G35)),G39-(G35),"不適用"),"") | H61: =IF(ISNUMBER(H39),IF(AND(ISNUMBER(H35)),H39-(H35),"不適用"),"")
A62: 差距｜EBITDA 率｜實際 vs 指引中點 | B62: pt | C62: =IF(ISNUMBER(C39),"不適用","") | D62: =IF(ISNUMBER(D39),"不適用","") | E62: =IF(ISNUMBER(E39),"不適用","") | F62: =IF(ISNUMBER(F39),"不適用","") | G62: =IF(ISNUMBER(G39),"不適用","") | H62: =IF(ISNUMBER(H39),"不適用","")
A63: 差距｜調整後營業利益｜模型 vs 共識 | B63: US$bn | C63: 不適用 | D63: 不適用 | E63: 不適用 | F63: 不適用 | G63: 不適用 | H63: 不適用
A64: 差距｜調整後營業利益｜模型 vs 指引中點 | B64: US$bn | C64: 不適用 | D64: 不適用 | E64: 不適用 | F64: 不適用 | G64: 不適用 | H64: 不適用
A65: 差距｜調整後營業利益｜實際 vs 模型 | B65: US$bn | C65: =IF(ISNUMBER(C40),IF(AND(ISNUMBER(C31)),C40-(C31),"不適用"),"") | D65: =IF(ISNUMBER(D40),IF(AND(ISNUMBER(D31)),D40-(D31),"不適用"),"") | E65: =IF(ISNUMBER(E40),IF(AND(ISNUMBER(E31)),E40-(E31),"不適用"),"") | F65: =IF(ISNUMBER(F40),IF(AND(ISNUMBER(F31)),F40-(F31),"不適用"),"") | G65: =IF(ISNUMBER(G40),IF(AND(ISNUMBER(G31)),G40-(G31),"不適用"),"") | H65: =IF(ISNUMBER(H40),IF(AND(ISNUMBER(H31)),H40-(H31),"不適用"),"")
A66: 差距｜調整後營業利益｜實際 vs 共識 | B66: US$bn | C66: =IF(ISNUMBER(C40),"不適用","") | D66: =IF(ISNUMBER(D40),"不適用","") | E66: =IF(ISNUMBER(E40),"不適用","") | F66: =IF(ISNUMBER(F40),"不適用","") | G66: =IF(ISNUMBER(G40),"不適用","") | H66: =IF(ISNUMBER(H40),"不適用","")
A67: 差距｜調整後營業利益｜實際 vs 指引中點 | B67: US$bn | C67: =IF(ISNUMBER(C40),"不適用","") | D67: =IF(ISNUMBER(D40),"不適用","") | E67: =IF(ISNUMBER(E40),"不適用","") | F67: =IF(ISNUMBER(F40),"不適用","") | G67: =IF(ISNUMBER(G40),"不適用","") | H67: =IF(ISNUMBER(H40),"不適用","")
A68: 差距｜調整後營業利益｜模型 vs 共識（利潤率 pt） | B68: pt | C68: 不適用 | D68: 不適用 | E68: 不適用 | F68: 不適用 | G68: 不適用 | H68: 不適用
A69: 差距｜調整後營業利益｜模型 vs 指引中點（利潤率 pt） | B69: pt | C69: 不適用 | D69: 不適用 | E69: 不適用 | F69: 不適用 | G69: 不適用 | H69: 不適用
A70: 差距｜調整後營業利益｜實際 vs 模型（利潤率 pt） | B70: pt | C70: =IF(ISNUMBER(C40),IF(AND(ISNUMBER(C40),ISNUMBER(C37),C37<>0,ISNUMBER(C31),ISNUMBER(C22),C22<>0),C40/C37-C31/C22,"不適用"),"") | D70: =IF(ISNUMBER(D40),IF(AND(ISNUMBER(D40),ISNUMBER(D37),D37<>0,ISNUMBER(D31),ISNUMBER(D22),D22<>0),D40/D37-D31/D22,"不適用"),"") | E70: =IF(ISNUMBER(E40),IF(AND(ISNUMBER(E40),ISNUMBER(E37),E37<>0,ISNUMBER(E31),ISNUMBER(E22),E22<>0),E40/E37-E31/E22,"不適用"),"") | F70: =IF(ISNUMBER(F40),IF(AND(ISNUMBER(F40),ISNUMBER(F37),F37<>0,ISNUMBER(F31),ISNUMBER(F22),F22<>0),F40/F37-F31/F22,"不適用"),"") | G70: =IF(ISNUMBER(G40),IF(AND(ISNUMBER(G40),ISNUMBER(G37),G37<>0,ISNUMBER(G31),ISNUMBER(G22),G22<>0),G40/G37-G31/G22,"不適用"),"") | H70: =IF(ISNUMBER(H40),IF(AND(ISNUMBER(H40),ISNUMBER(H37),H37<>0,ISNUMBER(H31),ISNUMBER(H22),H22<>0),H40/H37-H31/H22,"不適用"),"")
A71: 差距｜調整後營業利益｜實際 vs 共識（利潤率 pt） | B71: pt | C71: =IF(ISNUMBER(C40),"不適用","") | D71: =IF(ISNUMBER(D40),"不適用","") | E71: =IF(ISNUMBER(E40),"不適用","") | F71: =IF(ISNUMBER(F40),"不適用","") | G71: =IF(ISNUMBER(G40),"不適用","") | H71: =IF(ISNUMBER(H40),"不適用","")
A72: 差距｜調整後營業利益｜實際 vs 指引中點（利潤率 pt） | B72: pt | C72: =IF(ISNUMBER(C40),"不適用","") | D72: =IF(ISNUMBER(D40),"不適用","") | E72: =IF(ISNUMBER(E40),"不適用","") | F72: =IF(ISNUMBER(F40),"不適用","") | G72: =IF(ISNUMBER(G40),"不適用","") | H72: =IF(ISNUMBER(H40),"不適用","")
A73: 差距｜CapEx（毛額）｜模型 vs 共識 | B73: % | C73: 不適用 | D73: 不適用 | E73: 不適用 | F73: 不適用 | G73: 不適用 | H73: 不適用
A74: 差距｜CapEx（毛額）｜模型 vs 指引中點 | B74: % | C74: 不適用 | D74: 不適用 | E74: 不適用 | F74: 不適用 | G74: 不適用 | H74: 不適用
A75: 差距｜CapEx（毛額）｜實際 vs 模型 | B75: % | C75: =IF(ISNUMBER(C41),IF(AND(ISNUMBER(C32),C32<>0),C41/(C32)-1,"不適用"),"") | D75: =IF(ISNUMBER(D41),IF(AND(ISNUMBER(D32),D32<>0),D41/(D32)-1,"不適用"),"") | E75: =IF(ISNUMBER(E41),IF(AND(ISNUMBER(E32),E32<>0),E41/(E32)-1,"不適用"),"") | F75: =IF(ISNUMBER(F41),IF(AND(ISNUMBER(F32),F32<>0),F41/(F32)-1,"不適用"),"") | G75: =IF(ISNUMBER(G41),IF(AND(ISNUMBER(G32),G32<>0),G41/(G32)-1,"不適用"),"") | H75: =IF(ISNUMBER(H41),IF(AND(ISNUMBER(H32),H32<>0),H41/(H32)-1,"不適用"),"")
A76: 差距｜CapEx（毛額）｜實際 vs 共識 | B76: % | C76: =IF(ISNUMBER(C41),"不適用","") | D76: =IF(ISNUMBER(D41),"不適用","") | E76: =IF(ISNUMBER(E41),"不適用","") | F76: =IF(ISNUMBER(F41),"不適用","") | G76: =IF(ISNUMBER(G41),"不適用","") | H76: =IF(ISNUMBER(H41),"不適用","")
A77: 差距｜CapEx（毛額）｜實際 vs 指引中點 | B77: % | C77: =IF(ISNUMBER(C41),"不適用","") | D77: =IF(ISNUMBER(D41),"不適用","") | E77: =IF(ISNUMBER(E41),"不適用","") | F77: =IF(ISNUMBER(F41),"不適用","") | G77: =IF(ISNUMBER(G41),"不適用","") | H77: =IF(ISNUMBER(H41),"不適用","")
A78: 差距｜季末已連網 MW-IT｜模型 vs 共識 | B78: MW | C78: 不適用 | D78: 不適用 | E78: 不適用 | F78: 不適用 | G78: 不適用 | H78: 不適用
A79: 差距｜季末已連網 MW-IT｜模型 vs 指引中點 | B79: MW | C79: 不適用 | D79: 不適用 | E79: 不適用 | F79: 不適用 | G79: 不適用 | H79: 不適用
A80: 差距｜季末已連網 MW-IT｜實際 vs 模型 | B80: MW | C80: =IF(ISNUMBER(C42),IF(AND(ISNUMBER(C19)),C42-(C19),"不適用"),"") | D80: =IF(ISNUMBER(D42),IF(AND(ISNUMBER(D19)),D42-(D19),"不適用"),"") | E80: =IF(ISNUMBER(E42),IF(AND(ISNUMBER(E19)),E42-(E19),"不適用"),"") | F80: =IF(ISNUMBER(F42),IF(AND(ISNUMBER(F19)),F42-(F19),"不適用"),"") | G80: =IF(ISNUMBER(G42),IF(AND(ISNUMBER(G19)),G42-(G19),"不適用"),"") | H80: =IF(ISNUMBER(H42),IF(AND(ISNUMBER(H19)),H42-(H19),"不適用"),"")
A81: 差距｜季末已連網 MW-IT｜實際 vs 共識 | B81: MW | C81: =IF(ISNUMBER(C42),"不適用","") | D81: =IF(ISNUMBER(D42),"不適用","") | E81: =IF(ISNUMBER(E42),"不適用","") | F81: =IF(ISNUMBER(F42),"不適用","") | G81: =IF(ISNUMBER(G42),"不適用","") | H81: =IF(ISNUMBER(H42),"不適用","")
A82: 差距｜季末已連網 MW-IT｜實際 vs 指引中點 | B82: MW | C82: =IF(ISNUMBER(C42),"不適用","") | D82: =IF(ISNUMBER(D42),"不適用","") | E82: =IF(ISNUMBER(E42),"不適用","") | F82: =IF(ISNUMBER(F42),"不適用","") | G82: =IF(ISNUMBER(G42),"不適用","") | H82: =IF(ISNUMBER(H42),"不適用","")
A83: 合計基準｜營收｜vs 共識 | B83: US$bn | C83: =IF(COUNT(C33,D33)=2,C33+D33,"不適用") -> 不適用 | D83: =IF(COUNT(C33,D33)=2,C33+D33,"不適用") -> 不適用 | E83: =IF(COUNT(E33,F33,G33,H33)=4,E33+F33+G33+H33,"不適用") -> 不適用 | F83: =IF(COUNT(E33,F33,G33,H33)=4,E33+F33+G33+H33,"不適用") -> 不適用 | G83: =IF(COUNT(E33,F33,G33,H33)=4,E33+F33+G33+H33,"不適用") -> 不適用 | H83: =IF(COUNT(E33,F33,G33,H33)=4,E33+F33+G33+H33,"不適用") -> 不適用 | J83: 所屬期間的季度共識合計
A84: 拆解｜營收｜vs 共識｜水準 | B84: US$bn | C84: =IF(AND(ISNUMBER(C83),C83<>0,ISNUMBER(C33),ISNUMBER(C22)),(損益!C9-C83)*(C33)/C83,"不適用") -> 不適用 | D84: =IF(AND(ISNUMBER(D83),D83<>0,ISNUMBER(D33),ISNUMBER(D22)),(損益!C9-D83)*(D33)/D83,"不適用") -> 不適用 | E84: =IF(AND(ISNUMBER(E83),E83<>0,ISNUMBER(E33),ISNUMBER(E22)),(損益!D9-E83)*(E33)/E83,"不適用") -> 不適用 | F84: =IF(AND(ISNUMBER(F83),F83<>0,ISNUMBER(F33),ISNUMBER(F22)),(損益!D9-F83)*(F33)/F83,"不適用") -> 不適用 | G84: =IF(AND(ISNUMBER(G83),G83<>0,ISNUMBER(G33),ISNUMBER(G22)),(損益!D9-G83)*(G33)/G83,"不適用") -> 不適用 | H84: =IF(AND(ISNUMBER(H83),H83<>0,ISNUMBER(H33),ISNUMBER(H22)),(損益!D9-H83)*(H33)/H83,"不適用") -> 不適用 | J84: (模型期間 − 比較期間) × 比較的季占比
A85: 拆解｜營收｜vs 共識｜分配 | B85: US$bn | C85: =IF(AND(ISNUMBER(C83),C83<>0,ISNUMBER(C33),ISNUMBER(C22)),(C22/損益!C9-(C33)/C83)*損益!C9,"不適用") -> 不適用 | D85: =IF(AND(ISNUMBER(D83),D83<>0,ISNUMBER(D33),ISNUMBER(D22)),(D22/損益!C9-(D33)/D83)*損益!C9,"不適用") -> 不適用 | E85: =IF(AND(ISNUMBER(E83),E83<>0,ISNUMBER(E33),ISNUMBER(E22)),(E22/損益!D9-(E33)/E83)*損益!D9,"不適用") -> 不適用 | F85: =IF(AND(ISNUMBER(F83),F83<>0,ISNUMBER(F33),ISNUMBER(F22)),(F22/損益!D9-(F33)/F83)*損益!D9,"不適用") -> 不適用 | G85: =IF(AND(ISNUMBER(G83),G83<>0,ISNUMBER(G33),ISNUMBER(G22)),(G22/損益!D9-(G33)/G83)*損益!D9,"不適用") -> 不適用 | H85: =IF(AND(ISNUMBER(H83),H83<>0,ISNUMBER(H33),ISNUMBER(H22)),(H22/損益!D9-(H33)/H83)*損益!D9,"不適用") -> 不適用 | J85: (模型季占比 − 比較季占比) × 模型期間；水準＋分配＝季度差距
A86: 原因｜營收｜vs 共識 | C86: =IF(ISNUMBER(C43),IF(ABS(C43)>輸入與假設!$C$545,IF(ISNUMBER(C84),IF(ABS(C85)>ABS(C84),"營收 vs 共識 "&IF(C43<0,"−","+")&TEXT(ABS(C43)*100,"#,##0.0")&"%"&"：拆法（分配 "&IF(C85<0,"−","+")&IF(ABS(C85)<0,"−","")&"$"&TEXT(ABS(ABS(C85)),"#,##0.000")&"bn"&"（Q3 2026 占 2H26 "&TEXT((C22/損益!C9)*100,"#,##0.0")&"%"&"，共識合計 "&TEXT(((C33)/C83)*100,"#,##0.0")&"%"&"）；水準 "&IF(C84<0,"−","+")&IF(ABS(C84)<0,"−","")&"$"&TEXT(ABS(ABS(C84)),"#,##0.000")&"bn"&"）","營收 vs 共識 "&IF(C43<0,"−","+")&TEXT(ABS(C43)*100,"#,##0.0")&"%"&"：觀點（水準 "&IF(C84<0,"−","+")&IF(ABS(C84)<0,"−","")&"$"&TEXT(ABS(ABS(C84)),"#,##0.000")&"bn"&"（2H26 模型 "&IF(損益!C9<0,"−","")&"$"&TEXT(ABS(損益!C9),"#,##0.000")&"bn"&"，共識合計 "&IF(C83<0,"−","")&"$"&TEXT(ABS(C83),"#,##0.000")&"bn"&"）；分配 "&IF(C85<0,"−","+")&IF(ABS(C85)<0,"−","")&"$"&TEXT(ABS(ABS(C85)),"#,##0.000")&"bn"&"；"&"營收＝對外 AI 雲端（在役 MW × 每 MW 年收入，Tokenomics × k）＋各分部依近四季年增率收斂；年度總額線性分到各季，未建模第四季季節性"&"）"),"營收 vs 共識 "&IF(C43<0,"−","+")&TEXT(ABS(C43)*100,"#,##0.0")&"%"&"：觀點（"&"營收＝對外 AI 雲端（在役 MW × 每 MW 年收入，Tokenomics × k）＋各分部依近四季年增率收斂；年度總額線性分到各季，未建模第四季季節性"&"）"),""),"") | D86: =IF(ISNUMBER(D43),IF(ABS(D43)>輸入與假設!$C$545,IF(ISNUMBER(D84),IF(ABS(D85)>ABS(D84),"營收 vs 共識 "&IF(D43<0,"−","+")&TEXT(ABS(D43)*100,"#,##0.0")&"%"&"：拆法（分配 "&IF(D85<0,"−","+")&IF(ABS(D85)<0,"−","")&"$"&TEXT(ABS(ABS(D85)),"#,##0.000")&"bn"&"（Q4 2026 占 2H26 "&TEXT((D22/損益!C9)*100,"#,##0.0")&"%"&"，共識合計 "&TEXT(((D33)/D83)*100,"#,##0.0")&"%"&"）；水準 "&IF(D84<0,"−","+")&IF(ABS(D84)<0,"−","")&"$"&TEXT(ABS(ABS(D84)),"#,##0.000")&"bn"&"）","營收 vs 共識 "&IF(D43<0,"−","+")&TEXT(ABS(D43)*100,"#,##0.0")&"%"&"：觀點（水準 "&IF(D84<0,"−","+")&IF(ABS(D84)<0,"−","")&"$"&TEXT(ABS(ABS(D84)),"#,##0.000")&"bn"&"（2H26 模型 "&IF(損益!C9<0,"−","")&"$"&TEXT(ABS(損益!C9),"#,##0.000")&"bn"&"，共識合計 "&IF(D83<0,"−","")&"$"&TEXT(ABS(D83),"#,##0.000")&"bn"&"）；分配 "&IF(D85<0,"−","+")&IF(ABS(D85)<0,"−","")&"$"&TEXT(ABS(ABS(D85)),"#,##0.000")&"bn"&"；"&"營收＝對外 AI 雲端（在役 MW × 每 MW 年收入，Tokenomics × k）＋各分部依近四季年增率收斂；年度總額線性分到各季，未建模第四季季節性"&"）"),"營收 vs 共識 "&IF(D43<0,"−","+")&TEXT(ABS(D43)*100,"#,##0.0")&"%"&"：觀點（"&"營收＝對外 AI 雲端（在役 MW × 每 MW 年收入，Tokenomics × k）＋各分部依近四季年增率收斂；年度總額線性分到各季，未建模第四季季節性"&"）"),""),"") | E86: =IF(ISNUMBER(E43),IF(ABS(E43)>輸入與假設!$C$545,IF(ISNUMBER(E84),IF(ABS(E85)>ABS(E84),"營收 vs 共識 "&IF(E43<0,"−","+")&TEXT(ABS(E43)*100,"#,##0.0")&"%"&"：拆法（分配 "&IF(E85<0,"−","+")&IF(ABS(E85)<0,"−","")&"$"&TEXT(ABS(ABS(E85)),"#,##0.000")&"bn"&"（Q1 2027 占 2027 "&TEXT((E22/損益!D9)*100,"#,##0.0")&"%"&"，共識合計 "&TEXT(((E33)/E83)*100,"#,##0.0")&"%"&"）；水準 "&IF(E84<0,"−","+")&IF(ABS(E84)<0,"−","")&"$"&TEXT(ABS(ABS(E84)),"#,##0.000")&"bn"&"）","營收 vs 共識 "&IF(E43<0,"−","+")&TEXT(ABS(E43)*100,"#,##0.0")&"%"&"：觀點（水準 "&IF(E84<0,"−","+")&IF(ABS(E84)<0,"−","")&"$"&TEXT(ABS(ABS(E84)),"#,##0.000")&"bn"&"（2027 模型 "&IF(損益!D9<0,"−","")&"$"&TEXT(ABS(損益!D9),"#,##0.000")&"bn"&"，共識合計 "&IF(E83<0,"−","")&"$"&TEXT(ABS(E83),"#,##0.000")&"bn"&"）；分配 "&IF(E85<0,"−","+")&IF(ABS(E85)<0,"−","")&"$"&TEXT(ABS(ABS(E85)),"#,##0.000")&"bn"&"；"&"營收＝對外 AI 雲端（在役 MW × 每 MW 年收入，Tokenomics × k）＋各分部依近四季年增率收斂；年度總額線性分到各季，未建模第四季季節性"&"）"),"營收 vs 共識 "&IF(E43<0,"−","+")&TEXT(ABS(E43)*100,"#,##0.0")&"%"&"：觀點（"&"營收＝對外 AI 雲端（在役 MW × 每 MW 年收入，Tokenomics × k）＋各分部依近四季年增率收斂；年度總額線性分到各季，未建模第四季季節性"&"）"),""),"") | F86: =IF(ISNUMBER(F43),IF(ABS(F43)>輸入與假設!$C$545,IF(ISNUMBER(F84),IF(ABS(F85)>ABS(F84),"營收 vs 共識 "&IF(F43<0,"−","+")&TEXT(ABS(F43)*100,"#,##0.0")&"%"&"：拆法（分配 "&IF(F85<0,"−","+")&IF(ABS(F85)<0,"−","")&"$"&TEXT(ABS(ABS(F85)),"#,##0.000")&"bn"&"（Q2 2027 占 2027 "&TEXT((F22/損益!D9)*100,"#,##0.0")&"%"&"，共識合計 "&TEXT(((F33)/F83)*100,"#,##0.0")&"%"&"）；水準 "&IF(F84<0,"−","+")&IF(ABS(F84)<0,"−","")&"$"&TEXT(ABS(ABS(F84)),"#,##0.000")&"bn"&"）","營收 vs 共識 "&IF(F43<0,"−","+")&TEXT(ABS(F43)*100,"#,##0.0")&"%"&"：觀點（水準 "&IF(F84<0,"−","+")&IF(ABS(F84)<0,"−","")&"$"&TEXT(ABS(ABS(F84)),"#,##0.000")&"bn"&"（2027 模型 "&IF(損益!D9<0,"−","")&"$"&TEXT(ABS(損益!D9),"#,##0.000")&"bn"&"，共識合計 "&IF(F83<0,"−","")&"$"&TEXT(ABS(F83),"#,##0.000")&"bn"&"）；分配 "&IF(F85<0,"−","+")&IF(ABS(F85)<0,"−","")&"$"&TEXT(ABS(ABS(F85)),"#,##0.000")&"bn"&"；"&"營收＝對外 AI 雲端（在役 MW × 每 MW 年收入，Tokenomics × k）＋各分部依近四季年增率收斂；年度總額線性分到各季，未建模第四季季節性"&"）"),"營收 vs 共識 "&IF(F43<0,"−","+")&TEXT(ABS(F43)*100,"#,##0.0")&"%"&"：觀點（"&"營收＝對外 AI 雲端（在役 MW × 每 MW 年收入，Tokenomics × k）＋各分部依近四季年增率收斂；年度總額線性分到各季，未建模第四季季節性"&"）"),""),"") | G86: =IF(ISNUMBER(G43),IF(ABS(G43)>輸入與假設!$C$545,IF(ISNUMBER(G84),IF(ABS(G85)>ABS(G84),"營收 vs 共識 "&IF(G43<0,"−","+")&TEXT(ABS(G43)*100,"#,##0.0")&"%"&"：拆法（分配 "&IF(G85<0,"−","+")&IF(ABS(G85)<0,"−","")&"$"&TEXT(ABS(ABS(G85)),"#,##0.000")&"bn"&"（Q3 2027 占 2027 "&TEXT((G22/損益!D9)*100,"#,##0.0")&"%"&"，共識合計 "&TEXT(((G33)/G83)*100,"#,##0.0")&"%"&"）；水準 "&IF(G84<0,"−","+")&IF(ABS(G84)<0,"−","")&"$"&TEXT(ABS(ABS(G84)),"#,##0.000")&"bn"&"）","營收 vs 共識 "&IF(G43<0,"−","+")&TEXT(ABS(G43)*100,"#,##0.0")&"%"&"：觀點（水準 "&IF(G84<0,"−","+")&IF(ABS(G84)<0,"−","")&"$"&TEXT(ABS(ABS(G84)),"#,##0.000")&"bn"&"（2027 模型 "&IF(損益!D9<0,"−","")&"$"&TEXT(ABS(損益!D9),"#,##0.000")&"bn"&"，共識合計 "&IF(G83<0,"−","")&"$"&TEXT(ABS(G83),"#,##0.000")&"bn"&"）；分配 "&IF(G85<0,"−","+")&IF(ABS(G85)<0,"−","")&"$"&TEXT(ABS(ABS(G85)),"#,##0.000")&"bn"&"；"&"營收＝對外 AI 雲端（在役 MW × 每 MW 年收入，Tokenomics × k）＋各分部依近四季年增率收斂；年度總額線性分到各季，未建模第四季季節性"&"）"),"營收 vs 共識 "&IF(G43<0,"−","+")&TEXT(ABS(G43)*100,"#,##0.0")&"%"&"：觀點（"&"營收＝對外 AI 雲端（在役 MW × 每 MW 年收入，Tokenomics × k）＋各分部依近四季年增率收斂；年度總額線性分到各季，未建模第四季季節性"&"）"),""),"") | H86: =IF(ISNUMBER(H43),IF(ABS(H43)>輸入與假設!$C$545,IF(ISNUMBER(H84),IF(ABS(H85)>ABS(H84),"營收 vs 共識 "&IF(H43<0,"−","+")&TEXT(ABS(H43)*100,"#,##0.0")&"%"&"：拆法（分配 "&IF(H85<0,"−","+")&IF(ABS(H85)<0,"−","")&"$"&TEXT(ABS(ABS(H85)),"#,##0.000")&"bn"&"（Q4 2027 占 2027 "&TEXT((H22/損益!D9)*100,"#,##0.0")&"%"&"，共識合計 "&TEXT(((H33)/H83)*100,"#,##0.0")&"%"&"）；水準 "&IF(H84<0,"−","+")&IF(ABS(H84)<0,"−","")&"$"&TEXT(ABS(ABS(H84)),"#,##0.000")&"bn"&"）","營收 vs 共識 "&IF(H43<0,"−","+")&TEXT(ABS(H43)*100,"#,##0.0")&"%"&"：觀點（水準 "&IF(H84<0,"−","+")&IF(ABS(H84)<0,"−","")&"$"&TEXT(ABS(ABS(H84)),"#,##0.000")&"bn"&"（2027 模型 "&IF(損益!D9<0,"−","")&"$"&TEXT(ABS(損益!D9),"#,##0.000")&"bn"&"，共識合計 "&IF(H83<0,"−","")&"$"&TEXT(ABS(H83),"#,##0.000")&"bn"&"）；分配 "&IF(H85<0,"−","+")&IF(ABS(H85)<0,"−","")&"$"&TEXT(ABS(ABS(H85)),"#,##0.000")&"bn"&"；"&"營收＝對外 AI 雲端（在役 MW × 每 MW 年收入，Tokenomics × k）＋各分部依近四季年增率收斂；年度總額線性分到各季，未建模第四季季節性"&"）"),"營收 vs 共識 "&IF(H43<0,"−","+")&TEXT(ABS(H43)*100,"#,##0.0")&"%"&"：觀點（"&"營收＝對外 AI 雲端（在役 MW × 每 MW 年收入，Tokenomics × k）＋各分部依近四季年增率收斂；年度總額線性分到各季，未建模第四季季節性"&"）"),""),"")
A87: 原因類型｜營收｜vs 共識 | C87: =IF(ISNUMBER(C43),IF(ABS(C43)>輸入與假設!$C$545,IF(ISNUMBER(C84),IF(ABS(C85)>ABS(C84),"拆法","觀點"),"觀點"),""),"") | D87: =IF(ISNUMBER(D43),IF(ABS(D43)>輸入與假設!$C$545,IF(ISNUMBER(D84),IF(ABS(D85)>ABS(D84),"拆法","觀點"),"觀點"),""),"") | E87: =IF(ISNUMBER(E43),IF(ABS(E43)>輸入與假設!$C$545,IF(ISNUMBER(E84),IF(ABS(E85)>ABS(E84),"拆法","觀點"),"觀點"),""),"") | F87: =IF(ISNUMBER(F43),IF(ABS(F43)>輸入與假設!$C$545,IF(ISNUMBER(F84),IF(ABS(F85)>ABS(F84),"拆法","觀點"),"觀點"),""),"") | G87: =IF(ISNUMBER(G43),IF(ABS(G43)>輸入與假設!$C$545,IF(ISNUMBER(G84),IF(ABS(G85)>ABS(G84),"拆法","觀點"),"觀點"),""),"") | H87: =IF(ISNUMBER(H43),IF(ABS(H43)>輸入與假設!$C$545,IF(ISNUMBER(H84),IF(ABS(H85)>ABS(H84),"拆法","觀點"),"觀點"),""),"")
A88: 原因｜營收｜vs 指引中點
A89: 原因類型｜營收｜vs 指引中點
A90: 原因｜營收｜實際 vs 模型 | C90: =IF(ISNUMBER(C45),IF(ABS(C45)>輸入與假設!$C$545,"營收 實際 vs 模型 "&IF(C45<0,"−","+")&TEXT(ABS(C45)*100,"#,##0.0")&"%"&"：觀點（"&"營收＝對外 AI 雲端（在役 MW × 每 MW 年收入，Tokenomics × k）＋各分部依近四季年增率收斂；年度總額線性分到各季，未建模第四季季節性"&"）",""),"") | D90: =IF(ISNUMBER(D45),IF(ABS(D45)>輸入與假設!$C$545,"營收 實際 vs 模型 "&IF(D45<0,"−","+")&TEXT(ABS(D45)*100,"#,##0.0")&"%"&"：觀點（"&"營收＝對外 AI 雲端（在役 MW × 每 MW 年收入，Tokenomics × k）＋各分部依近四季年增率收斂；年度總額線性分到各季，未建模第四季季節性"&"）",""),"") | E90: =IF(ISNUMBER(E45),IF(ABS(E45)>輸入與假設!$C$545,"營收 實際 vs 模型 "&IF(E45<0,"−","+")&TEXT(ABS(E45)*100,"#,##0.0")&"%"&"：觀點（"&"營收＝對外 AI 雲端（在役 MW × 每 MW 年收入，Tokenomics × k）＋各分部依近四季年增率收斂；年度總額線性分到各季，未建模第四季季節性"&"）",""),"") | F90: =IF(ISNUMBER(F45),IF(ABS(F45)>輸入與假設!$C$545,"營收 實際 vs 模型 "&IF(F45<0,"−","+")&TEXT(ABS(F45)*100,"#,##0.0")&"%"&"：觀點（"&"營收＝對外 AI 雲端（在役 MW × 每 MW 年收入，Tokenomics × k）＋各分部依近四季年增率收斂；年度總額線性分到各季，未建模第四季季節性"&"）",""),"") | G90: =IF(ISNUMBER(G45),IF(ABS(G45)>輸入與假設!$C$545,"營收 實際 vs 模型 "&IF(G45<0,"−","+")&TEXT(ABS(G45)*100,"#,##0.0")&"%"&"：觀點（"&"營收＝對外 AI 雲端（在役 MW × 每 MW 年收入，Tokenomics × k）＋各分部依近四季年增率收斂；年度總額線性分到各季，未建模第四季季節性"&"）",""),"") | H90: =IF(ISNUMBER(H45),IF(ABS(H45)>輸入與假設!$C$545,"營收 實際 vs 模型 "&IF(H45<0,"−","+")&TEXT(ABS(H45)*100,"#,##0.0")&"%"&"：觀點（"&"營收＝對外 AI 雲端（在役 MW × 每 MW 年收入，Tokenomics × k）＋各分部依近四季年增率收斂；年度總額線性分到各季，未建模第四季季節性"&"）",""),"")
A91: 原因類型｜營收｜實際 vs 模型 | C91: =IF(ISNUMBER(C45),IF(ABS(C45)>輸入與假設!$C$545,"觀點",""),"") | D91: =IF(ISNUMBER(D45),IF(ABS(D45)>輸入與假設!$C$545,"觀點",""),"") | E91: =IF(ISNUMBER(E45),IF(ABS(E45)>輸入與假設!$C$545,"觀點",""),"") | F91: =IF(ISNUMBER(F45),IF(ABS(F45)>輸入與假設!$C$545,"觀點",""),"") | G91: =IF(ISNUMBER(G45),IF(ABS(G45)>輸入與假設!$C$545,"觀點",""),"") | H91: =IF(ISNUMBER(H45),IF(ABS(H45)>輸入與假設!$C$545,"觀點",""),"")
A92: 合計基準｜調整後 EBITDA｜vs 共識 | B92: US$bn | C92: =IF(COUNT(C34,D34)=2,C34+D34,"不適用") -> 不適用 | D92: =IF(COUNT(C34,D34)=2,C34+D34,"不適用") -> 不適用 | E92: =IF(COUNT(E34,F34,G34,H34)=4,E34+F34+G34+H34,"不適用") -> 不適用 | F92: =IF(COUNT(E34,F34,G34,H34)=4,E34+F34+G34+H34,"不適用") -> 不適用 | G92: =IF(COUNT(E34,F34,G34,H34)=4,E34+F34+G34+H34,"不適用") -> 不適用 | H92: =IF(COUNT(E34,F34,G34,H34)=4,E34+F34+G34+H34,"不適用") -> 不適用 | J92: 所屬期間的季度共識合計
A93: 拆解｜調整後 EBITDA｜vs 共識｜水準 | B93: US$bn | C93: =IF(AND(ISNUMBER(C92),C92<>0,ISNUMBER(C34),ISNUMBER(C28)),(損益!C22-C92)*(C34)/C92,"不適用") -> 不適用 | D93: =IF(AND(ISNUMBER(D92),D92<>0,ISNUMBER(D34),ISNUMBER(D28)),(損益!C22-D92)*(D34)/D92,"不適用") -> 不適用 | E93: =IF(AND(ISNUMBER(E92),E92<>0,ISNUMBER(E34),ISNUMBER(E28)),(損益!D22-E92)*(E34)/E92,"不適用") -> 不適用 | F93: =IF(AND(ISNUMBER(F92),F92<>0,ISNUMBER(F34),ISNUMBER(F28)),(損益!D22-F92)*(F34)/F92,"不適用") -> 不適用 | G93: =IF(AND(ISNUMBER(G92),G92<>0,ISNUMBER(G34),ISNUMBER(G28)),(損益!D22-G92)*(G34)/G92,"不適用") -> 不適用 | H93: =IF(AND(ISNUMBER(H92),H92<>0,ISNUMBER(H34),ISNUMBER(H28)),(損益!D22-H92)*(H34)/H92,"不適用") -> 不適用 | J93: (模型期間 − 比較期間) × 比較的季占比
A94: 拆解｜調整後 EBITDA｜vs 共識｜分配 | B94: US$bn | C94: =IF(AND(ISNUMBER(C92),C92<>0,ISNUMBER(C34),ISNUMBER(C28)),(C28/損益!C22-(C34)/C92)*損益!C22,"不適用") -> 不適用 | D94: =IF(AND(ISNUMBER(D92),D92<>0,ISNUMBER(D34),ISNUMBER(D28)),(D28/損益!C22-(D34)/D92)*損益!C22,"不適用") -> 不適用 | E94: =IF(AND(ISNUMBER(E92),E92<>0,ISNUMBER(E34),ISNUMBER(E28)),(E28/損益!D22-(E34)/E92)*損益!D22,"不適用") -> 不適用 | F94: =IF(AND(ISNUMBER(F92),F92<>0,ISNUMBER(F34),ISNUMBER(F28)),(F28/損益!D22-(F34)/F92)*損益!D22,"不適用") -> 不適用 | G94: =IF(AND(ISNUMBER(G92),G92<>0,ISNUMBER(G34),ISNUMBER(G28)),(G28/損益!D22-(G34)/G92)*損益!D22,"不適用") -> 不適用 | H94: =IF(AND(ISNUMBER(H92),H92<>0,ISNUMBER(H34),ISNUMBER(H28)),(H28/損益!D22-(H34)/H92)*損益!D22,"不適用") -> 不適用 | J94: (模型季占比 − 比較季占比) × 模型期間；水準＋分配＝季度差距
A95: 原因｜調整後 EBITDA｜vs 共識 | C95: =IF(ISNUMBER(C48),IF(IF(ISNUMBER(C53),ABS(C53)>輸入與假設!$C$546,OR(AND(C34<>0,ABS(C48)>輸入與假設!$C$545*ABS(C34)),AND(C34=0,C48<>0))),IF(ISNUMBER(C93),IF(ABS(C94)>ABS(C93),"調整後 EBITDA vs 共識 "&IF(C48<0,"−","+")&IF(ABS(C48)<0,"−","")&"$"&TEXT(ABS(ABS(C48)),"#,##0.00")&"bn"&IF(ISNUMBER(C53),"／"&IF(C53<0,"−","+")&TEXT(ABS(C53)*100,"#,##0.0")&"pt","")&"：拆法（分配 "&IF(C94<0,"−","+")&IF(ABS(C94)<0,"−","")&"$"&TEXT(ABS(ABS(C94)),"#,##0.000")&"bn"&"（Q3 2026 占 2H26 "&TEXT((C28/損益!C22)*100,"#,##0.0")&"%"&"，共識合計 "&TEXT(((C34)/C92)*100,"#,##0.0")&"%"&"）；水準 "&IF(C93<0,"−","+")&IF(ABS(C93)<0,"−","")&"$"&TEXT(ABS(ABS(C93)),"#,##0.000")&"bn"&"）","調整後 EBITDA vs 共識 "&IF(C48<0,"−","+")&IF(ABS(C48)<0,"−","")&"$"&TEXT(ABS(ABS(C48)),"#,##0.00")&"bn"&IF(ISNUMBER(C53),"／"&IF(C53<0,"−","+")&TEXT(ABS(C53)*100,"#,##0.0")&"pt","")&"：觀點（水準 "&IF(C93<0,"−","+")&IF(ABS(C93)<0,"−","")&"$"&TEXT(ABS(ABS(C93)),"#,##0.000")&"bn"&"（2H26 模型 "&IF(損益!C22<0,"−","")&"$"&TEXT(ABS(損益!C22),"#,##0.000")&"bn"&"，共識合計 "&IF(C92<0,"−","")&"$"&TEXT(ABS(C92),"#,##0.000")&"bn"&"）；分配 "&IF(C94<0,"−","+")&IF(ABS(C94)<0,"−","")&"$"&TEXT(ABS(ABS(C94)),"#,##0.000")&"bn"&"；"&"模型 EBITDA 率 "&IF((C27)<0,"−","")&TEXT(ABS((C27))*100,"#,##0.0")&"%"&"；EBITDA＝分部營業利益＋分攤 D&A 與 AI 雲端 Tokenomics 由下而上營運成本"&"）"),"調整後 EBITDA vs 共識 "&IF(C48<0,"−","+")&IF(ABS(C48)<0,"−","")&"$"&TEXT(ABS(ABS(C48)),"#,##0.00")&"bn"&IF(ISNUMBER(C53),"／"&IF(C53<0,"−","+")&TEXT(ABS(C53)*100,"#,##0.0")&"pt","")&"：觀點（"&"模型 EBITDA 率 "&IF((C27)<0,"−","")&TEXT(ABS((C27))*100,"#,##0.0")&"%"&"；EBITDA＝分部營業利益＋分攤 D&A 與 AI 雲端 Tokenomics 由下而上營運成本"&"）"),""),"") | D95: =IF(ISNUMBER(D48),IF(IF(ISNUMBER(D53),ABS(D53)>輸入與假設!$C$546,OR(AND(D34<>0,ABS(D48)>輸入與假設!$C$545*ABS(D34)),AND(D34=0,D48<>0))),IF(ISNUMBER(D93),IF(ABS(D94)>ABS(D93),"調整後 EBITDA vs 共識 "&IF(D48<0,"−","+")&IF(ABS(D48)<0,"−","")&"$"&TEXT(ABS(ABS(D48)),"#,##0.00")&"bn"&IF(ISNUMBER(D53),"／"&IF(D53<0,"−","+")&TEXT(ABS(D53)*100,"#,##0.0")&"pt","")&"：拆法（分配 "&IF(D94<0,"−","+")&IF(ABS(D94)<0,"−","")&"$"&TEXT(ABS(ABS(D94)),"#,##0.000")&"bn"&"（Q4 2026 占 2H26 "&TEXT((D28/損益!C22)*100,"#,##0.0")&"%"&"，共識合計 "&TEXT(((D34)/D92)*100,"#,##0.0")&"%"&"）；水準 "&IF(D93<0,"−","+")&IF(ABS(D93)<0,"−","")&"$"&TEXT(ABS(ABS(D93)),"#,##0.000")&"bn"&"）","調整後 EBITDA vs 共識 "&IF(D48<0,"−","+")&IF(ABS(D48)<0,"−","")&"$"&TEXT(ABS(ABS(D48)),"#,##0.00")&"bn"&IF(ISNUMBER(D53),"／"&IF(D53<0,"−","+")&TEXT(ABS(D53)*100,"#,##0.0")&"pt","")&"：觀點（水準 "&IF(D93<0,"−","+")&IF(ABS(D93)<0,"−","")&"$"&TEXT(ABS(ABS(D93)),"#,##0.000")&"bn"&"（2H26 模型 "&IF(損益!C22<0,"−","")&"$"&TEXT(ABS(損益!C22),"#,##0.000")&"bn"&"，共識合計 "&IF(D92<0,"−","")&"$"&TEXT(ABS(D92),"#,##0.000")&"bn"&"）；分配 "&IF(D94<0,"−","+")&IF(ABS(D94)<0,"−","")&"$"&TEXT(ABS(ABS(D94)),"#,##0.000")&"bn"&"；"&"模型 EBITDA 率 "&IF((D27)<0,"−","")&TEXT(ABS((D27))*100,"#,##0.0")&"%"&"；EBITDA＝分部營業利益＋分攤 D&A 與 AI 雲端 Tokenomics 由下而上營運成本"&"）"),"調整後 EBITDA vs 共識 "&IF(D48<0,"−","+")&IF(ABS(D48)<0,"−","")&"$"&TEXT(ABS(ABS(D48)),"#,##0.00")&"bn"&IF(ISNUMBER(D53),"／"&IF(D53<0,"−","+")&TEXT(ABS(D53)*100,"#,##0.0")&"pt","")&"：觀點（"&"模型 EBITDA 率 "&IF((D27)<0,"−","")&TEXT(ABS((D27))*100,"#,##0.0")&"%"&"；EBITDA＝分部營業利益＋分攤 D&A 與 AI 雲端 Tokenomics 由下而上營運成本"&"）"),""),"") | E95: =IF(ISNUMBER(E48),IF(IF(ISNUMBER(E53),ABS(E53)>輸入與假設!$C$546,OR(AND(E34<>0,ABS(E48)>輸入與假設!$C$545*ABS(E34)),AND(E34=0,E48<>0))),IF(ISNUMBER(E93),IF(ABS(E94)>ABS(E93),"調整後 EBITDA vs 共識 "&IF(E48<0,"−","+")&IF(ABS(E48)<0,"−","")&"$"&TEXT(ABS(ABS(E48)),"#,##0.00")&"bn"&IF(ISNUMBER(E53),"／"&IF(E53<0,"−","+")&TEXT(ABS(E53)*100,"#,##0.0")&"pt","")&"：拆法（分配 "&IF(E94<0,"−","+")&IF(ABS(E94)<0,"−","")&"$"&TEXT(ABS(ABS(E94)),"#,##0.000")&"bn"&"（Q1 2027 占 2027 "&TEXT((E28/損益!D22)*100,"#,##0.0")&"%"&"，共識合計 "&TEXT(((E34)/E92)*100,"#,##0.0")&"%"&"）；水準 "&IF(E93<0,"−","+")&IF(ABS(E93)<0,"−","")&"$"&TEXT(ABS(ABS(E93)),"#,##0.000")&"bn"&"）","調整後 EBITDA vs 共識 "&IF(E48<0,"−","+")&IF(ABS(E48)<0,"−","")&"$"&TEXT(ABS(ABS(E48)),"#,##0.00")&"bn"&IF(ISNUMBER(E53),"／"&IF(E53<0,"−","+")&TEXT(ABS(E53)*100,"#,##0.0")&"pt","")&"：觀點（水準 "&IF(E93<0,"−","+")&IF(ABS(E93)<0,"−","")&"$"&TEXT(ABS(ABS(E93)),"#,##0.000")&"bn"&"（2027 模型 "&IF(損益!D22<0,"−","")&"$"&TEXT(ABS(損益!D22),"#,##0.000")&"bn"&"，共識合計 "&IF(E92<0,"−","")&"$"&TEXT(ABS(E92),"#,##0.000")&"bn"&"）；分配 "&IF(E94<0,"−","+")&IF(ABS(E94)<0,"−","")&"$"&TEXT(ABS(ABS(E94)),"#,##0.000")&"bn"&"；"&"模型 EBITDA 率 "&IF((E27)<0,"−","")&TEXT(ABS((E27))*100,"#,##0.0")&"%"&"；EBITDA＝分部營業利益＋分攤 D&A 與 AI 雲端 Tokenomics 由下而上營運成本"&"）"),"調整後 EBITDA vs 共識 "&IF(E48<0,"−","+")&IF(ABS(E48)<0,"−","")&"$"&TEXT(ABS(ABS(E48)),"#,##0.00")&"bn"&IF(ISNUMBER(E53),"／"&IF(E53<0,"−","+")&TEXT(ABS(E53)*100,"#,##0.0")&"pt","")&"：觀點（"&"模型 EBITDA 率 "&IF((E27)<0,"−","")&TEXT(ABS((E27))*100,"#,##0.0")&"%"&"；EBITDA＝分部營業利益＋分攤 D&A 與 AI 雲端 Tokenomics 由下而上營運成本"&"）"),""),"") | F95: =IF(ISNUMBER(F48),IF(IF(ISNUMBER(F53),ABS(F53)>輸入與假設!$C$546,OR(AND(F34<>0,ABS(F48)>輸入與假設!$C$545*ABS(F34)),AND(F34=0,F48<>0))),IF(ISNUMBER(F93),IF(ABS(F94)>ABS(F93),"調整後 EBITDA vs 共識 "&IF(F48<0,"−","+")&IF(ABS(F48)<0,"−","")&"$"&TEXT(ABS(ABS(F48)),"#,##0.00")&"bn"&IF(ISNUMBER(F53),"／"&IF(F53<0,"−","+")&TEXT(ABS(F53)*100,"#,##0.0")&"pt","")&"：拆法（分配 "&IF(F94<0,"−","+")&IF(ABS(F94)<0,"−","")&"$"&TEXT(ABS(ABS(F94)),"#,##0.000")&"bn"&"（Q2 2027 占 2027 "&TEXT((F28/損益!D22)*100,"#,##0.0")&"%"&"，共識合計 "&TEXT(((F34)/F92)*100,"#,##0.0")&"%"&"）；水準 "&IF(F93<0,"−","+")&IF(ABS(F93)<0,"−","")&"$"&TEXT(ABS(ABS(F93)),"#,##0.000")&"bn"&"）","調整後 EBITDA vs 共識 "&IF(F48<0,"−","+")&IF(ABS(F48)<0,"−","")&"$"&TEXT(ABS(ABS(F48)),"#,##0.00")&"bn"&IF(ISNUMBER(F53),"／"&IF(F53<0,"−","+")&TEXT(ABS(F53)*100,"#,##0.0")&"pt","")&"：觀點（水準 "&IF(F93<0,"−","+")&IF(ABS(F93)<0,"−","")&"$"&TEXT(ABS(ABS(F93)),"#,##0.000")&"bn"&"（2027 模型 "&IF(損益!D22<0,"−","")&"$"&TEXT(ABS(損益!D22),"#,##0.000")&"bn"&"，共識合計 "&IF(F92<0,"−","")&"$"&TEXT(ABS(F92),"#,##0.000")&"bn"&"）；分配 "&IF(F94<0,"−","+")&IF(ABS(F94)<0,"−","")&"$"&TEXT(ABS(ABS(F94)),"#,##0.000")&"bn"&"；"&"模型 EBITDA 率 "&IF((F27)<0,"−","")&TEXT(ABS((F27))*100,"#,##0.0")&"%"&"；EBITDA＝分部營業利益＋分攤 D&A 與 AI 雲端 Tokenomics 由下而上營運成本"&"）"),"調整後 EBITDA vs 共識 "&IF(F48<0,"−","+")&IF(ABS(F48)<0,"−","")&"$"&TEXT(ABS(ABS(F48)),"#,##0.00")&"bn"&IF(ISNUMBER(F53),"／"&IF(F53<0,"−","+")&TEXT(ABS(F53)*100,"#,##0.0")&"pt","")&"：觀點（"&"模型 EBITDA 率 "&IF((F27)<0,"−","")&TEXT(ABS((F27))*100,"#,##0.0")&"%"&"；EBITDA＝分部營業利益＋分攤 D&A 與 AI 雲端 Tokenomics 由下而上營運成本"&"）"),""),"") | G95: =IF(ISNUMBER(G48),IF(IF(ISNUMBER(G53),ABS(G53)>輸入與假設!$C$546,OR(AND(G34<>0,ABS(G48)>輸入與假設!$C$545*ABS(G34)),AND(G34=0,G48<>0))),IF(ISNUMBER(G93),IF(ABS(G94)>ABS(G93),"調整後 EBITDA vs 共識 "&IF(G48<0,"−","+")&IF(ABS(G48)<0,"−","")&"$"&TEXT(ABS(ABS(G48)),"#,##0.00")&"bn"&IF(ISNUMBER(G53),"／"&IF(G53<0,"−","+")&TEXT(ABS(G53)*100,"#,##0.0")&"pt","")&"：拆法（分配 "&IF(G94<0,"−","+")&IF(ABS(G94)<0,"−","")&"$"&TEXT(ABS(ABS(G94)),"#,##0.000")&"bn"&"（Q3 2027 占 2027 "&TEXT((G28/損益!D22)*100,"#,##0.0")&"%"&"，共識合計 "&TEXT(((G34)/G92)*100,"#,##0.0")&"%"&"）；水準 "&IF(G93<0,"−","+")&IF(ABS(G93)<0,"−","")&"$"&TEXT(ABS(ABS(G93)),"#,##0.000")&"bn"&"）","調整後 EBITDA vs 共識 "&IF(G48<0,"−","+")&IF(ABS(G48)<0,"−","")&"$"&TEXT(ABS(ABS(G48)),"#,##0.00")&"bn"&IF(ISNUMBER(G53),"／"&IF(G53<0,"−","+")&TEXT(ABS(G53)*100,"#,##0.0")&"pt","")&"：觀點（水準 "&IF(G93<0,"−","+")&IF(ABS(G93)<0,"−","")&"$"&TEXT(ABS(ABS(G93)),"#,##0.000")&"bn"&"（2027 模型 "&IF(損益!D22<0,"−","")&"$"&TEXT(ABS(損益!D22),"#,##0.000")&"bn"&"，共識合計 "&IF(G92<0,"−","")&"$"&TEXT(ABS(G92),"#,##0.000")&"bn"&"）；分配 "&IF(G94<0,"−","+")&IF(ABS(G94)<0,"−","")&"$"&TEXT(ABS(ABS(G94)),"#,##0.000")&"bn"&"；"&"模型 EBITDA 率 "&IF((G27)<0,"−","")&TEXT(ABS((G27))*100,"#,##0.0")&"%"&"；EBITDA＝分部營業利益＋分攤 D&A 與 AI 雲端 Tokenomics 由下而上營運成本"&"）"),"調整後 EBITDA vs 共識 "&IF(G48<0,"−","+")&IF(ABS(G48)<0,"−","")&"$"&TEXT(ABS(ABS(G48)),"#,##0.00")&"bn"&IF(ISNUMBER(G53),"／"&IF(G53<0,"−","+")&TEXT(ABS(G53)*100,"#,##0.0")&"pt","")&"：觀點（"&"模型 EBITDA 率 "&IF((G27)<0,"−","")&TEXT(ABS((G27))*100,"#,##0.0")&"%"&"；EBITDA＝分部營業利益＋分攤 D&A 與 AI 雲端 Tokenomics 由下而上營運成本"&"）"),""),"") | H95: =IF(ISNUMBER(H48),IF(IF(ISNUMBER(H53),ABS(H53)>輸入與假設!$C$546,OR(AND(H34<>0,ABS(H48)>輸入與假設!$C$545*ABS(H34)),AND(H34=0,H48<>0))),IF(ISNUMBER(H93),IF(ABS(H94)>ABS(H93),"調整後 EBITDA vs 共識 "&IF(H48<0,"−","+")&IF(ABS(H48)<0,"−","")&"$"&TEXT(ABS(ABS(H48)),"#,##0.00")&"bn"&IF(ISNUMBER(H53),"／"&IF(H53<0,"−","+")&TEXT(ABS(H53)*100,"#,##0.0")&"pt","")&"：拆法（分配 "&IF(H94<0,"−","+")&IF(ABS(H94)<0,"−","")&"$"&TEXT(ABS(ABS(H94)),"#,##0.000")&"bn"&"（Q4 2027 占 2027 "&TEXT((H28/損益!D22)*100,"#,##0.0")&"%"&"，共識合計 "&TEXT(((H34)/H92)*100,"#,##0.0")&"%"&"）；水準 "&IF(H93<0,"−","+")&IF(ABS(H93)<0,"−","")&"$"&TEXT(ABS(ABS(H93)),"#,##0.000")&"bn"&"）","調整後 EBITDA vs 共識 "&IF(H48<0,"−","+")&IF(ABS(H48)<0,"−","")&"$"&TEXT(ABS(ABS(H48)),"#,##0.00")&"bn"&IF(ISNUMBER(H53),"／"&IF(H53<0,"−","+")&TEXT(ABS(H53)*100,"#,##0.0")&"pt","")&"：觀點（水準 "&IF(H93<0,"−","+")&IF(ABS(H93)<0,"−","")&"$"&TEXT(ABS(ABS(H93)),"#,##0.000")&"bn"&"（2027 模型 "&IF(損益!D22<0,"−","")&"$"&TEXT(ABS(損益!D22),"#,##0.000")&"bn"&"，共識合計 "&IF(H92<0,"−","")&"$"&TEXT(ABS(H92),"#,##0.000")&"bn"&"）；分配 "&IF(H94<0,"−","+")&IF(ABS(H94)<0,"−","")&"$"&TEXT(ABS(ABS(H94)),"#,##0.000")&"bn"&"；"&"模型 EBITDA 率 "&IF((H27)<0,"−","")&TEXT(ABS((H27))*100,"#,##0.0")&"%"&"；EBITDA＝分部營業利益＋分攤 D&A 與 AI 雲端 Tokenomics 由下而上營運成本"&"）"),"調整後 EBITDA vs 共識 "&IF(H48<0,"−","+")&IF(ABS(H48)<0,"−","")&"$"&TEXT(ABS(ABS(H48)),"#,##0.00")&"bn"&IF(ISNUMBER(H53),"／"&IF(H53<0,"−","+")&TEXT(ABS(H53)*100,"#,##0.0")&"pt","")&"：觀點（"&"模型 EBITDA 率 "&IF((H27)<0,"−","")&TEXT(ABS((H27))*100,"#,##0.0")&"%"&"；EBITDA＝分部營業利益＋分攤 D&A 與 AI 雲端 Tokenomics 由下而上營運成本"&"）"),""),"")
A96: 原因類型｜調整後 EBITDA｜vs 共識 | C96: =IF(ISNUMBER(C48),IF(IF(ISNUMBER(C53),ABS(C53)>輸入與假設!$C$546,OR(AND(C34<>0,ABS(C48)>輸入與假設!$C$545*ABS(C34)),AND(C34=0,C48<>0))),IF(ISNUMBER(C93),IF(ABS(C94)>ABS(C93),"拆法","觀點"),"觀點"),""),"") | D96: =IF(ISNUMBER(D48),IF(IF(ISNUMBER(D53),ABS(D53)>輸入與假設!$C$546,OR(AND(D34<>0,ABS(D48)>輸入與假設!$C$545*ABS(D34)),AND(D34=0,D48<>0))),IF(ISNUMBER(D93),IF(ABS(D94)>ABS(D93),"拆法","觀點"),"觀點"),""),"") | E96: =IF(ISNUMBER(E48),IF(IF(ISNUMBER(E53),ABS(E53)>輸入與假設!$C$546,OR(AND(E34<>0,ABS(E48)>輸入與假設!$C$545*ABS(E34)),AND(E34=0,E48<>0))),IF(ISNUMBER(E93),IF(ABS(E94)>ABS(E93),"拆法","觀點"),"觀點"),""),"") | F96: =IF(ISNUMBER(F48),IF(IF(ISNUMBER(F53),ABS(F53)>輸入與假設!$C$546,OR(AND(F34<>0,ABS(F48)>輸入與假設!$C$545*ABS(F34)),AND(F34=0,F48<>0))),IF(ISNUMBER(F93),IF(ABS(F94)>ABS(F93),"拆法","觀點"),"觀點"),""),"") | G96: =IF(ISNUMBER(G48),IF(IF(ISNUMBER(G53),ABS(G53)>輸入與假設!$C$546,OR(AND(G34<>0,ABS(G48)>輸入與假設!$C$545*ABS(G34)),AND(G34=0,G48<>0))),IF(ISNUMBER(G93),IF(ABS(G94)>ABS(G93),"拆法","觀點"),"觀點"),""),"") | H96: =IF(ISNUMBER(H48),IF(IF(ISNUMBER(H53),ABS(H53)>輸入與假設!$C$546,OR(AND(H34<>0,ABS(H48)>輸入與假設!$C$545*ABS(H34)),AND(H34=0,H48<>0))),IF(ISNUMBER(H93),IF(ABS(H94)>ABS(H93),"拆法","觀點"),"觀點"),""),"")
A97: 原因｜調整後 EBITDA｜vs 指引中點
A98: 原因類型｜調整後 EBITDA｜vs 指引中點
A99: 原因｜調整後 EBITDA｜實際 vs 模型 | C99: =IF(ISNUMBER(C50),IF(IF(ISNUMBER(C55),ABS(C55)>輸入與假設!$C$546,OR(AND(C28<>0,ABS(C50)>輸入與假設!$C$545*ABS(C28)),AND(C28=0,C50<>0))),"調整後 EBITDA 實際 vs 模型 "&IF(C50<0,"−","+")&IF(ABS(C50)<0,"−","")&"$"&TEXT(ABS(ABS(C50)),"#,##0.00")&"bn"&IF(ISNUMBER(C55),"／"&IF(C55<0,"−","+")&TEXT(ABS(C55)*100,"#,##0.0")&"pt","")&"：觀點（"&"模型 EBITDA 率 "&IF((C27)<0,"−","")&TEXT(ABS((C27))*100,"#,##0.0")&"%"&"；EBITDA＝分部營業利益＋分攤 D&A 與 AI 雲端 Tokenomics 由下而上營運成本"&"）",""),"") | D99: =IF(ISNUMBER(D50),IF(IF(ISNUMBER(D55),ABS(D55)>輸入與假設!$C$546,OR(AND(D28<>0,ABS(D50)>輸入與假設!$C$545*ABS(D28)),AND(D28=0,D50<>0))),"調整後 EBITDA 實際 vs 模型 "&IF(D50<0,"−","+")&IF(ABS(D50)<0,"−","")&"$"&TEXT(ABS(ABS(D50)),"#,##0.00")&"bn"&IF(ISNUMBER(D55),"／"&IF(D55<0,"−","+")&TEXT(ABS(D55)*100,"#,##0.0")&"pt","")&"：觀點（"&"模型 EBITDA 率 "&IF((D27)<0,"−","")&TEXT(ABS((D27))*100,"#,##0.0")&"%"&"；EBITDA＝分部營業利益＋分攤 D&A 與 AI 雲端 Tokenomics 由下而上營運成本"&"）",""),"") | E99: =IF(ISNUMBER(E50),IF(IF(ISNUMBER(E55),ABS(E55)>輸入與假設!$C$546,OR(AND(E28<>0,ABS(E50)>輸入與假設!$C$545*ABS(E28)),AND(E28=0,E50<>0))),"調整後 EBITDA 實際 vs 模型 "&IF(E50<0,"−","+")&IF(ABS(E50)<0,"−","")&"$"&TEXT(ABS(ABS(E50)),"#,##0.00")&"bn"&IF(ISNUMBER(E55),"／"&IF(E55<0,"−","+")&TEXT(ABS(E55)*100,"#,##0.0")&"pt","")&"：觀點（"&"模型 EBITDA 率 "&IF((E27)<0,"−","")&TEXT(ABS((E27))*100,"#,##0.0")&"%"&"；EBITDA＝分部營業利益＋分攤 D&A 與 AI 雲端 Tokenomics 由下而上營運成本"&"）",""),"") | F99: =IF(ISNUMBER(F50),IF(IF(ISNUMBER(F55),ABS(F55)>輸入與假設!$C$546,OR(AND(F28<>0,ABS(F50)>輸入與假設!$C$545*ABS(F28)),AND(F28=0,F50<>0))),"調整後 EBITDA 實際 vs 模型 "&IF(F50<0,"−","+")&IF(ABS(F50)<0,"−","")&"$"&TEXT(ABS(ABS(F50)),"#,##0.00")&"bn"&IF(ISNUMBER(F55),"／"&IF(F55<0,"−","+")&TEXT(ABS(F55)*100,"#,##0.0")&"pt","")&"：觀點（"&"模型 EBITDA 率 "&IF((F27)<0,"−","")&TEXT(ABS((F27))*100,"#,##0.0")&"%"&"；EBITDA＝分部營業利益＋分攤 D&A 與 AI 雲端 Tokenomics 由下而上營運成本"&"）",""),"") | G99: =IF(ISNUMBER(G50),IF(IF(ISNUMBER(G55),ABS(G55)>輸入與假設!$C$546,OR(AND(G28<>0,ABS(G50)>輸入與假設!$C$545*ABS(G28)),AND(G28=0,G50<>0))),"調整後 EBITDA 實際 vs 模型 "&IF(G50<0,"−","+")&IF(ABS(G50)<0,"−","")&"$"&TEXT(ABS(ABS(G50)),"#,##0.00")&"bn"&IF(ISNUMBER(G55),"／"&IF(G55<0,"−","+")&TEXT(ABS(G55)*100,"#,##0.0")&"pt","")&"：觀點（"&"模型 EBITDA 率 "&IF((G27)<0,"−","")&TEXT(ABS((G27))*100,"#,##0.0")&"%"&"；EBITDA＝分部營業利益＋分攤 D&A 與 AI 雲端 Tokenomics 由下而上營運成本"&"）",""),"") | H99: =IF(ISNUMBER(H50),IF(IF(ISNUMBER(H55),ABS(H55)>輸入與假設!$C$546,OR(AND(H28<>0,ABS(H50)>輸入與假設!$C$545*ABS(H28)),AND(H28=0,H50<>0))),"調整後 EBITDA 實際 vs 模型 "&IF(H50<0,"−","+")&IF(ABS(H50)<0,"−","")&"$"&TEXT(ABS(ABS(H50)),"#,##0.00")&"bn"&IF(ISNUMBER(H55),"／"&IF(H55<0,"−","+")&TEXT(ABS(H55)*100,"#,##0.0")&"pt","")&"：觀點（"&"模型 EBITDA 率 "&IF((H27)<0,"−","")&TEXT(ABS((H27))*100,"#,##0.0")&"%"&"；EBITDA＝分部營業利益＋分攤 D&A 與 AI 雲端 Tokenomics 由下而上營運成本"&"）",""),"")
A100: 原因類型｜調整後 EBITDA｜實際 vs 模型 | C100: =IF(ISNUMBER(C50),IF(IF(ISNUMBER(C55),ABS(C55)>輸入與假設!$C$546,OR(AND(C28<>0,ABS(C50)>輸入與假設!$C$545*ABS(C28)),AND(C28=0,C50<>0))),"觀點",""),"") | D100: =IF(ISNUMBER(D50),IF(IF(ISNUMBER(D55),ABS(D55)>輸入與假設!$C$546,OR(AND(D28<>0,ABS(D50)>輸入與假設!$C$545*ABS(D28)),AND(D28=0,D50<>0))),"觀點",""),"") | E100: =IF(ISNUMBER(E50),IF(IF(ISNUMBER(E55),ABS(E55)>輸入與假設!$C$546,OR(AND(E28<>0,ABS(E50)>輸入與假設!$C$545*ABS(E28)),AND(E28=0,E50<>0))),"觀點",""),"") | F100: =IF(ISNUMBER(F50),IF(IF(ISNUMBER(F55),ABS(F55)>輸入與假設!$C$546,OR(AND(F28<>0,ABS(F50)>輸入與假設!$C$545*ABS(F28)),AND(F28=0,F50<>0))),"觀點",""),"") | G100: =IF(ISNUMBER(G50),IF(IF(ISNUMBER(G55),ABS(G55)>輸入與假設!$C$546,OR(AND(G28<>0,ABS(G50)>輸入與假設!$C$545*ABS(G28)),AND(G28=0,G50<>0))),"觀點",""),"") | H100: =IF(ISNUMBER(H50),IF(IF(ISNUMBER(H55),ABS(H55)>輸入與假設!$C$546,OR(AND(H28<>0,ABS(H50)>輸入與假設!$C$545*ABS(H28)),AND(H28=0,H50<>0))),"觀點",""),"")
A101: 原因｜調整後營業利益｜vs 共識
A102: 原因類型｜調整後營業利益｜vs 共識
...

Sheet 運營_產能與收入
A1: 產能與收入 — 合約排程 vs 機房產能
A2: 兩條線獨立產生後相減：排程>容量→瓶頸（收不到）；容量>排程→剩餘產能（要靠新簽約賣掉）
A3: 2026 欄口徑：MW 為年底存量；標示「（模型期）」的收入列只含 2026 下半年——RPO 桶自 2026-06-30 起算，1H 收入已實現、不再受產能約束。1H 實際單列，兩者相加即 2026 全年（見本頁「FY26 全年」列）。
A5: 項目 | B5: 單位 | C5: 2026 | D5: 2027 | E5: 2028 | F5: 2029 | G5: 2030 | I5: 公式／來源說明
A6: 模型期間 | C6: ="2026-07-01~12-31" -> 2026-07-01~12-31 | D6: ="2027 全年" -> 2027 全年 | E6: ="2028 全年" -> 2028 全年 | F6: ="2029 全年" -> 2029 全年 | G6: ="2030 全年" -> 2030 全年 | I6: 2026 的模型期只有下半年；1H 已實現的營收單列於下方
A7: 模型期長度（年） | C7: =輸入與假設!C$34 -> 0.5 | D7: =輸入與假設!D$34 -> 1 | E7: =輸入與假設!E$34 -> 1 | F7: =輸入與假設!F$34 -> 1 | G7: =輸入與假設!G$34 -> 1 | I7: 只用於下方三處：容量上限、電力、維護——把年率換算成該期金額
A8: （A）機房：容量上限
A9: Accepted MW（已驗收，單調不減） | B9: MW | C9: =MAX(0,輸入與假設!C$36) -> 2524.05 | D9: =MAX(輸入與假設!D$36,C9) -> 3770.15 | E9: =MAX(輸入與假設!E$36,D9) -> 5016.25 | F9: =MAX(輸入與假設!F$36,E9) -> 6262.35 | G9: =MAX(輸入與假設!G$36,F9) -> 7508.45 | I9: 引擎規則：不得低於前期（產能不會消失）
A10: Billable MW（上限為 Accepted） | B10: MW | C10: =MIN(MAX(0,輸入與假設!C$37),C9) -> 2524 | D10: =MIN(MAX(0,輸入與假設!D$37),D9) -> 3770 | E10: =MIN(MAX(0,輸入與假設!E$37),E9) -> 5016 | F10: =MIN(MAX(0,輸入與假設!F$37),F9) -> 6262 | G10: =MIN(MAX(0,輸入與假設!G$37),G9) -> 7508 | I10: 引擎規則：可計費不得超過已驗收
A11: Billable MW（延誤後，計費用） | B11: MW | C11: =IF($C$50<=0,$C$10,輸入與假設!$C$29+($C$10-輸入與假設!$C$29)*MAX(0,MIN(1,($C$51-$C$50/12-0)/$C$7))+($D$10-$C$10)*MAX(0,MIN(1,($C$51-$C$50/12-$C$51)/$D$7))+($E$10-$D$10)*MAX(0,MIN(1,($C$51-$C$50/12-$D$51)/$E$7))+($F$10-$E$10)*MAX(0,MIN(1,($C$51-$C$50/12-$E$51)/$F$7))+($G$10-$F$10)*MAX(0,MIN(1,($C$51-$C$50/12-$F$51)/$G$7))) -> 2524 | D11: =IF($C$50<=0,$D$10,輸入與假設!$C$29+($C$10-輸入與假設!$C$29)*MAX(0,MIN(1,($D$51-$C$50/12-0)/$C$7))+($D$10-$C$10)*MAX(0,MIN(1,($D$51-$C$50/12-$C$51)/$D$7))+($E$10-$D$10)*MAX(0,MIN(1,($D$51-$C$50/12-$D$51)/$E$7))+($F$10-$E$10)*MAX(0,MIN(1,($D$51-$C$50/12-$E$51)/$F$7))+($G$10-$F$10)*MAX(0,MIN(1,($D$51-$C$50/12-$F$51)/$G$7))) -> 3770 | E11: =IF($C$50<=0,$E$10,輸入與假設!$C$29+($C$10-輸入與假設!$C$29)*MAX(0,MIN(1,($E$51-$C$50/12-0)/$C$7))+($D$10-$C$10)*MAX(0,MIN(1,($E$51-$C$50/12-$C$51)/$D$7))+($E$10-$D$10)*MAX(0,MIN(1,($E$51-$C$50/12-$D$51)/$E$7))+($F$10-$E$10)*MAX(0,MIN(1,($E$51-$C$50/12-$E$51)/$F$7))+($G$10-$F$10)*MAX(0,MIN(1,($E$51-$C$50/12-$F$51)/$G$7))) -> 5016 | F11: =IF($C$50<=0,$F$10,輸入與假設!$C$29+($C$10-輸入與假設!$C$29)*MAX(0,MIN(1,($F$51-$C$50/12-0)/$C$7))+($D$10-$C$10)*MAX(0,MIN(1,($F$51-$C$50/12-$C$51)/$D$7))+($E$10-$D$10)*MAX(0,MIN(1,($F$51-$C$50/12-$D$51)/$E$7))+($F$10-$E$10)*MAX(0,MIN(1,($F$51-$C$50/12-$E$51)/$F$7))+($G$10-$F$10)*MAX(0,MIN(1,($F$51-$C$50/12-$F$51)/$G$7))) -> 6262 | G11: =IF($C$50<=0,$G$10,輸入與假設!$C$29+($C$10-輸入與假設!$C$29)*MAX(0,MIN(1,($G$51-$C$50/12-0)/$C$7))+($D$10-$C$10)*MAX(0,MIN(1,($G$51-$C$50/12-$C$51)/$D$7))+($E$10-$D$10)*MAX(0,MIN(1,($G$51-$C$50/12-$D$51)/$E$7))+($F$10-$E$10)*MAX(0,MIN(1,($G$51-$C$50/12-$E$51)/$F$7))+($G$10-$F$10)*MAX(0,MIN(1,($G$51-$C$50/12-$F$51)/$G$7))) -> 7508 | I11: ＝上列往後平移建設延誤月數（以期間長度線性內插；評價日之前取期初校準值）；延誤 0 時＝上列；見（E）區（v0.2）
A12: 期初在役 MW | B12: MW | C12: =輸入與假設!$C$29 -> 1901 | D12: =C11 -> 2524 | E12: =D11 -> 3770 | F12: =E11 -> 5016 | G12: =F11 -> 6262 | I12: 前期期末＝本期期初（延誤後）
A13: 平均在役 MW（2026 欄為下半年平均） | B13: MW | C13: =IF(輸入與假設!$C$30=1,(C12+C11)/2,C11) -> 2212.5 | D13: =IF(輸入與假設!$C$30=1,(D12+D11)/2,D11) -> 3147 | E13: =IF(輸入與假設!$C$30=1,(E12+E11)/2,E11) -> 4393 | F13: =IF(輸入與假設!$C$30=1,(F12+F11)/2,F11) -> 5639 | G13: =IF(輸入與假設!$C$30=1,(G12+G11)/2,G11) -> 6885 | I13: 開關在輸入頁：1＝(期初+期末)/2，0＝期末全期化
A14: 利用率 | B14: % | C14: =輸入與假設!C$38 -> 1 | D14: =輸入與假設!D$38 -> 1 | E14: =輸入與假設!E$38 -> 1 | F14: =輸入與假設!F$38 -> 1 | G14: =輸入與假設!G$38 -> 1
A15: 每 MW 年收入 | B15: US$bn/MW | C15: =輸入與假設!C$39 -> 0.011500793 | D15: =輸入與假設!D$39 -> 0.012107214 | E15: =輸入與假設!E$39 -> 0.012604282 | F15: =輸入與假設!F$39 -> 0.012903535 | G15: =輸入與假設!G$39 -> 0.01310346
A16: 容量上限（模型期最多能交付的收入） | B16: US$bn | C16: =C13*輸入與假設!C$39*輸入與假設!$C$32*輸入與假設!C$38*C7 -> 12.722752 | D16: =D13*輸入與假設!D$39*輸入與假設!$C$32*輸入與假設!D$38*D7 -> 38.101402 | E16: =E13*輸入與假設!E$39*輸入與假設!$C$32*輸入與假設!E$38*E7 -> 55.370613 | F16: =F13*輸入與假設!F$39*輸入與假設!$C$32*輸入與假設!F$38*F7 -> 72.763033 | G16: =G13*輸入與假設!G$39*輸入與假設!$C$32*輸入與假設!G$38*G7 -> 90.21732 | I16: ＝平均在役 MW × 每 MW 年收入 × 利用率 × 期間係數。只看機房，不看合約
A17: （B）合約：排程 RPO
A18: 排程 RPO（模型期，依季報桶分攤） | B18: US$bn | C18: =(輸入與假設!$C$24+輸入與假設!$C$25)*(輸入與假設!C$35/輸入與假設!$C$27)*輸入與假設!$C$26 -> 0 | D18: =(輸入與假設!$C$24+輸入與假設!$C$25)*(輸入與假設!D$35/輸入與假設!$C$27)*輸入與假設!$C$26 -> 0 | E18: =(輸入與假設!$C$24+輸入與假設!$C$25)*(輸入與假設!E$35/輸入與假設!$C$27)*輸入與假設!$C$26 -> 0 | F18: =(輸入與假設!$C$24+輸入與假設!$C$25)*(輸入與假設!F$35/輸入與假設!$C$27)*輸入與假設!$C$26 -> 0 | G18: =(輸入與假設!$C$24+輸入與假設!$C$25)*(輸入與假設!G$35/輸入與假設!$C$27)*輸入與假設!$C$26 -> 0 | I18: ＝(6/30 RPO＋評價日後新增)×本期權重÷權重合計×五期認列比例。只看合約，不看機房
A19: （C）兩條線相減
A20: 產能瓶頸（模型期：排程 − 容量） | B20: US$bn | C20: =MAX(0,C18-C16) -> 0 | D20: =MAX(0,D18-D16) -> 0 | E20: =MAX(0,E18-E16) -> 0 | F20: =MAX(0,F18-F16) -> 0 | G20: =MAX(0,G18-G16) -> 0 | I20: 合約有、機房沒有 → 本期收不到，且不遞延到下期（保守處理）
A21: 期初 RPO 轉換收入（模型期） | B21: US$bn | C21: =C18-C20 -> 0 | D21: =D18-D20 -> 0 | E21: =E18-E20 -> 0 | F21: =F18-F20 -> 0 | G21: =G18-G20 -> 0 | I21: ＝排程 − 瓶頸。當瓶頸>0 時，此值恆等於容量上限
A22: 未被期初 RPO 占用的產能 | B22: US$bn | C22: =MAX(0,C16-C18) -> 12.722752 | D22: =MAX(0,D16-D18) -> 38.101402 | E22: =MAX(0,E16-E18) -> 55.370613 | F22: =MAX(0,F16-F18) -> 72.763033 | G22: =MAX(0,G16-G18) -> 90.21732 | I22: 容量 − 排程。機房有、期初合約沒占滿 → 要靠新簽約
A23: 新產能簽約率 | B23: % | C23: =IF(輸入與假設!$C$31="mw",1,輸入與假設!C$40) -> 1 | D23: =IF(輸入與假設!$C$31="mw",1,輸入與假設!D$40) -> 1 | E23: =IF(輸入與假設!$C$31="mw",1,輸入與假設!E$40) -> 1 | F23: =IF(輸入與假設!$C$31="mw",1,輸入與假設!F$40) -> 1 | G23: =IF(輸入與假設!$C$31="mw",1,輸入與假設!G$40) -> 1 | I23: MW 驅動時固定 100%
A24: 新簽約收入 | B24: US$bn | C24: =C22*C23 -> 12.722752 | D24: =D22*D23 -> 38.101402 | E24: =E22*E23 -> 55.370613 | F24: =F22*F23 -> 72.763033 | G24: =G22*G23 -> 90.21732 | I24: 超出期初 RPO 的產能收入（MW 驅動，簽約率 100%）
A25: 未售產能（浪費） | B25: US$bn | C25: =MAX(0,C16-C21-C24) -> 0 | D25: =MAX(0,D16-D21-D24) -> 0 | E25: =MAX(0,E16-E21-E24) -> 0 | F25: =MAX(0,F16-F21-F24) -> 0 | G25: =MAX(0,G16-G21-G24) -> 0 | I25: 蓋好但賣不掉（MW 驅動時為 0）
A26: 損益用算力收入（模型期＝RPO 轉換＋新簽約） | B26: US$bn | C26: =C21+C24 -> 12.722752 | D26: =D21+D24 -> 38.101402 | E26: =E21+E24 -> 55.370613 | F26: =F21+F24 -> 72.763033 | G26: =G21+G24 -> 90.21732 | I26: 損益與評價頁的算力收入由此連結，確保現金與損益同一組數字
A27: 核對：算力收入 − 平均在役 MW × 每 MW × 利用率 × 期間 | B27: US$bn | C27: =C26-C13*輸入與假設!C$39*輸入與假設!$C$32*輸入與假設!C$38*C7 -> 0 | D27: =D26-D13*輸入與假設!D$39*輸入與假設!$C$32*輸入與假設!D$38*D7 -> 0 | E27: =E26-E13*輸入與假設!E$39*輸入與假設!$C$32*輸入與假設!E$38*E7 -> 0 | F27: =F26-F13*輸入與假設!F$39*輸入與假設!$C$32*輸入與假設!F$38*F7 -> 0 | G27: =G26-G13*輸入與假設!G$39*輸入與假設!$C$32*輸入與假設!G$38*G7 -> 0 | I27: MW 驅動時應為 0：營收可追溯為 MW × 每 MW 年收入 × 利用率（v0.1b）
A28: 對照：評價日起 36 個月營收權重 | B28: % | C28: 1 | D28: 1 | E28: 1 | F28: 0.5 | G28: 0 | I28: RPO 36 個月內轉換的對照用（只作對照，不驅動營收）
A29: 對照：評價日起 36 個月 MW 驅動營收 | B29: US$bn | C29: =C26*C28 -> 12.722752 | D29: =D26*D28 -> 38.101402 | E29: =E26*E28 -> 55.370613 | F29: =F26*F28 -> 36.381517 | G29: =G26*G28 -> 0 | I29: 合計對照季報 RPO 519.5 × 36 個月內 59%（含非 AI 事業 RPO）；差額不回推每 MW 單價
A30: 1H26 實際營收（季報，已實現） | B30: US$bn | C30: =輸入與假設!$C$477 -> 229.692 | D30: =0 -> 0 | E30: =0 -> 0 | F30: =0 -> 0 | G30: =0 -> 0 | I30: 2026-01-01 至 06-30 已認列營收。已實現，不受下半年產能約束，故不進入上方的瓶頸計算
A31: 2026 全年總營收（1H 實際＋模型期算力＋服務＋非 AI 事業） | B31: US$bn | C31: =C30+C26+輸入與假設!C$43+輸入與假設!C$240 -> 492.26831 | D31: =D30+D26+輸入與假設!D$43+輸入與假設!D$240 -> 599.07596 | E31: =E30+E26+輸入與假設!E$43+輸入與假設!E$240 -> 695.23465 | F31: =F30+F26+輸入與假設!F$43+輸入與假設!F$240 -> 783.74537 | G31: =G30+G26+輸入與假設!G$43+輸入與假設!G$240 -> 856.49901 | I31: 2026 欄對照公司全年指引 未給全年營收指引；2027 以後即為該年度總營收
A32: （D）收入 → 現金：三道折扣
A33: 客戶違約率 | B33: % | C33: =輸入與假設!C$41 -> 0 | D33: =輸入與假設!D$41 -> 0 | E33: =輸入與假設!E$41 -> 0 | F33: =輸入與假設!F$41 -> 0 | G33: =輸入與假設!G$41 -> 0
A34: 回收率 | B34: % | C34: =輸入與假設!C$42 -> 0.5 | D34: =輸入與假設!D$42 -> 0.5 | E34: =輸入與假設!E$42 -> 0.5 | F34: =輸入與假設!F$42 -> 0.5 | G34: =輸入與假設!G$42 -> 0.5
A35: 信用損失（期初 RPO 部分） | B35: US$bn | C35: =C21*輸入與假設!C$41*(1-輸入與假設!C$42) -> 0 | D35: =D21*輸入與假設!D$41*(1-輸入與假設!D$42) -> 0 | E35: =E21*輸入與假設!E$41*(1-輸入與假設!E$42) -> 0 | F35: =F21*輸入與假設!F$41*(1-輸入與假設!F$42) -> 0 | G35: =G21*輸入與假設!G$41*(1-輸入與假設!G$42) -> 0 | I35: ＝收入 × 違約率 × (1−回收率)
A36: 收現（期初 RPO 部分） | B36: US$bn | C36: =C21-C35 -> 0 | D36: =D21-D35 -> 0 | E36: =E21-E35 -> 0 | F36: =F21-F35 -> 0 | G36: =G21-G35 -> 0
A37: EBITDA 率（損益與資金共用） | B37: % | C37: =輸入與假設!C$250 -> 0.83423438 | D37: =輸入與假設!D$250 -> 0.83894381 | E37: =輸入與假設!E$250 -> 0.84246605 | F37: =輸入與假設!F$250 -> 0.84445571 | G37: =輸入與假設!G$250 -> 0.84573431 | I37: 起始→穩態線性爬升
A38: 模型期總營收（算力＋服務） | B38: US$bn | C38: =C26+輸入與假設!C$43 -> 12.722752 | D38: =D26+輸入與假設!D$43 -> 38.101402 | E38: =E26+輸入與假設!E$43 -> 55.370613 | F38: =F26+輸入與假設!F$43 -> 72.763033 | G38: =G26+輸入與假設!G$43 -> 90.21732
A39: EBITDAR 率（EBITDA 率＋租金÷營收） | B39: % | C39: =輸入與假設!C$250 -> 0.83423438 | D39: =輸入與假設!D$250 -> 0.83894381 | E39: =輸入與假設!E$250 -> 0.84246605 | F39: =輸入與假設!F$250 -> 0.84445571 | G39: =輸入與假設!G$250 -> 0.84573431 | I39: 租金前的 EBITDA 率。EBITDA 已扣租金，而資金模型把租金列在支出端，所以要加回，避免重複扣除
A40: RPO 現金（可支應資本用途） | B40: US$bn | C40: =C36*C39 -> 0 | D40: =D36*D39 -> 0 | E40: =E36*E39 -> 0 | F40: =F36*F39 -> 0 | G40: =G36*G39 -> 0 | I40: ×EBITDAR 率。租金與利息在支出頁單獨列示
A41: 新簽約現金 | B41: US$bn | C41: =C24*(1-輸入與假設!C$41*(1-輸入與假設!C$42))*C39 -> 10.613757 | D41: =D24*(1-輸入與假設!D$41*(1-輸入與假設!D$42))*D39 -> 31.964935 | E41: =E24*(1-輸入與假設!E$41*(1-輸入與假設!E$42))*E39 -> 46.647862 | F41: =F24*(1-輸入與假設!F$41*(1-輸入與假設!F$42))*F39 -> 61.445159 | G41: =G24*(1-輸入與假設!G$41*(1-輸入與假設!G$42))*G39 -> 76.299883 | I41: 同樣扣信用損失、乘 EBITDAR 率
A43: 讀法：2026（2H）與 2027 瓶頸>0，合約多於機房；2028 起反轉，收入愈來愈靠『新簽約收入』這一列。
A44: 把『新產能簽約率』調到 0，就能看到只靠期初 RPO 的資金缺口有多大——這是最重要的一個壓力測試。
A46: （E）建設延誤（v0.2）：計費 MW 往後平移；GPU 資本支出與客戶出資照原時程；折舊自投入使用時點起算
A47: 建設延誤月數｜保守 已交付＋已公開在建 | B47: 月 | C47: 0 | I47: company.json → scenarios.delayMonths；依據見該欄 note [Assumed]
A48: 建設延誤月數｜基準 依資本支出指引 | B48: 月 | C48: 0 | I48: company.json → scenarios.delayMonths；依據見該欄 note [Assumed]
A49: 建設延誤月數｜積極 依 2027 擴張幅度 | B49: 月 | C49: 0 | I49: company.json → scenarios.delayMonths；依據見該欄 note [Assumed]
A50: 建設延誤月數（目前情境） | B50: 月 | C50: =CHOOSE(輸入與假設!$C$5,運營_產能與收入!$C$47,運營_產能與收入!$C$48,運營_產能與收入!$C$49) -> 0 | I50: ＝依『輸入與假設』A 區情境選擇器；0＝不延誤（＝v0.1）
A51: 期末時點（評價日起，年） | B51: 年 | C51: =SUM($C$7:C7) -> 0.5 | D51: =SUM($C$7:D7) -> 1.5 | E51: =SUM($C$7:E7) -> 2.5 | F51: =SUM($C$7:F7) -> 3.5 | G51: =SUM($C$7:G7) -> 4.5 | I51: ＝累計期間長度
A52: 成長型 CapEx 累計（原時程，評價日起） | B52: US$bn | C52: =SUM(輸入與假設!$C$299:C$299) -> 119.40679 | D52: =SUM(輸入與假設!$C$299:D$299) -> 356.24181 | E52: =SUM(輸入與假設!$C$299:E$299) -> 612.78759 | F52: =SUM(輸入與假設!$C$299:F$299) -> 876.78415 | G52: =SUM(輸入與假設!$C$299:G$299) -> 1145.7997 | I52: GPU 與網通照原併網時程採購、交貨等電（客戶出資覆蓋比同樣依原時程）
A53: 已投入使用累計（延誤後） | B53: US$bn | C53: =IF($C$50<=0,$C$52,0+($C$52-0)*MAX(0,MIN(1,($C$51-$C$50/12-0)/$C$7))+($D$52-$C$52)*MAX(0,MIN(1,($C$51-$C$50/12-$C$51)/$D$7))+($E$52-$D$52)*MAX(0,MIN(1,($C$51-$C$50/12-$D$51)/$E$7))+($F$52-$E$52)*MAX(0,MIN(1,($C$51-$C$50/12-$E$51)/$F$7))+($G$52-$F$52)*MAX(0,MIN(1,($C$51-$C$50/12-$F$51)/$G$7))) -> 119.40679 | D53: =IF($C$50<=0,$D$52,0+($C$52-0)*MAX(0,MIN(1,($D$51-$C$50/12-0)/$C$7))+($D$52-$C$52)*MAX(0,MIN(1,($D$51-$C$50/12-$C$51)/$D$7))+($E$52-$D$52)*MAX(0,MIN(1,($D$51-$C$50/12-$D$51)/$E$7))+($F$52-$E$52)*MAX(0,MIN(1,($D$51-$C$50/12-$E$51)/$F$7))+($G$52-$F$52)*MAX(0,MIN(1,($D$51-$C$50/12-$F$51)/$G$7))) -> 356.24181 | E53: =IF($C$50<=0,$E$52,0+($C$52-0)*MAX(0,MIN(1,($E$51-$C$50/12-0)/$C$7))+($D$52-$C$52)*MAX(0,MIN(1,($E$51-$C$50/12-$C$51)/$D$7))+($E$52-$D$52)*MAX(0,MIN(1,($E$51-$C$50/12-$D$51)/$E$7))+($F$52-$E$52)*MAX(0,MIN(1,($E$51-$C$50/12-$E$51)/$F$7))+($G$52-$F$52)*MAX(0,MIN(1,($E$51-$C$50/12-$F$51)/$G$7))) -> 612.78759 | F53: =IF($C$50<=0,$F$52,0+($C$52-0)*MAX(0,MIN(1,($F$51-$C$50/12-0)/$C$7))+($D$52-$C$52)*MAX(0,MIN(1,($F$51-$C$50/12-$C$51)/$D$7))+($E$52-$D$52)*MAX(0,MIN(1,($F$51-$C$50/12-$D$51)/$E$7))+($F$52-$E$52)*MAX(0,MIN(1,($F$51-$C$50/12-$E$51)/$F$7))+($G$52-$F$52)*MAX(0,MIN(1,($F$51-$C$50/12-$F$51)/$G$7))) -> 876.78415 | G53: =IF($C$50<=0,$G$52,0+($C$52-0)*MAX(0,MIN(1,($G$51-$C$50/12-0)/$C$7))+($D$52-$C$52)*MAX(0,MIN(1,($G$51-$C$50/12-$C$51)/$D$7))+($E$52-$D$52)*MAX(0,MIN(1,($G$51-$C$50/12-$D$51)/$E$7))+($F$52-$E$52)*MAX(0,MIN(1,($G$51-$C$50/12-$E$51)/$F$7))+($G$52-$F$52)*MAX(0,MIN(1,($G$51-$C$50/12-$F$51)/$G$7))) -> 1145.7997 | I53: ＝上列往後平移建設延誤月數（線性內插）；延誤 0 時＝上列
A54: 本期投入使用的成長型 CapEx（折舊基礎） | B54: US$bn | C54: =C53 -> 119.40679 | D54: =D53-C53 -> 236.83502 | E54: =E53-D53 -> 256.54578 | F54: =F53-E53 -> 263.99656 | G54: =G53-F53 -> 269.0156 | I54: 車隊折舊自投入使用時點起算（『輸入與假設』期初毛 PP&E 與 D&A 引用此列）
A55: 閒置資本（已支出未產生收入，期末） | B55: US$bn | C55: =C52-C53 -> 0 | D55: =D52-D53 -> 0 | E55: =E52-E53 -> 0 | F55: =F52-F53 -> 0 | G55: =G52-G53 -> 0 | I55: ＝原時程累計 − 已投入使用累計；延誤 0 時為 0。一頁摘要以一句呈現峰值
A56: 未起租租約起租連動比例（delayLink） | B56: % | C56: 0 | I56: 未起租租金中此比例的起租時點隨延誤月數後移（開發商交付晚），其餘照原時程（company.json → leases.uncommenced.delayLink）[Assumed]；替代 0／1
A57: 延誤罰則（應計費而未計費營收的 %） | B57: % | C57: 0 | I57: 公司未揭露合約條款：預設 0（不存在／未揭露）；敏感度 5%／10%（company.json → defaults.delayPenalty）[Assumed]
A58: 表外現金租金：全部隨延誤平移（對照） | B58: US$bn | C58: =輸入與假設!$C$19/輸入與假設!$C$21/輸入與假設!$C$22/4*((MIN(MAX(0,輸入與假設!C$281-(輸入與假設!$C$20+運營_產能與收入!$C$50/3)),輸入與假設!$C$21)*(MIN(MAX(0,輸入與假設!C$281-(輸入與假設!$C$20+運營_產能與收入!$C$50/3)),輸入與假設!$C$21)+1)/2+輸入與假設!$C$21*MAX(0,MAX(0,輸入與假設!C$281-(輸入與假設!$C$20+運營_產能與收入!$C$50/3))-輸入與假設!$C$21))-(MIN(MAX(0,0-(輸入與假設!$C$20+運營_產能與收入!$C$50/3)),輸入與假設!$C$21)*(MIN(MAX(0,0-(輸入與假設!$C$20+運營_產能與收入!$C$50/3)),輸入與假設!$C$21)+1)/2+輸入與假設!$C$21*MAX(0,MAX(0,0-(輸入與假設!$C$20+運營_產能與收入!$C$50/3))-輸入與假設!$C$21))) -> 0.19363636 | D58: =輸入與假設!$C$19/輸入與假設!$C$21/輸入與假設!$C$22/4*((MIN(MAX(0,輸入與假設!D$281-(輸入與假設!$C$20+運營_產能與收入!$C$50/3)),輸入與假設!$C$21)*(MIN(MAX(0,輸入與假設!D$281-(輸入與假設!$C$20+運營_產能與收入!$C$50/3)),輸入與假設!$C$21)+1)/2+輸入與假設!$C$21*MAX(0,MAX(0,輸入與假設!D$281-(輸入與假設!$C$20+運營_產能與收入!$C$50/3))-輸入與假設!$C$21))-(MIN(MAX(0,輸入與假設!C$281-(輸入與假設!$C$20+運營_產能與收入!$C$50/3)),輸入與假設!$C$21)*(MIN(MAX(0,輸入與假設!C$281-(輸入與假設!$C$20+運營_產能與收入!$C$50/3)),輸入與假設!$C$21)+1)/2+輸入與假設!$C$21*MAX(0,MAX(0,輸入與假設!C$281-(輸入與假設!$C$20+運營_產能與收入!$C$50/3))-輸入與假設!$C$21))) -> 1.1618182 | E58: =輸入與假設!$C$19/輸入與假設!$C$21/輸入與假設!$C$22/4*((MIN(MAX(0,輸入與假設!E$281-(輸入與假設!$C$20+運營_產能與收入!$C$50/3)),輸入與假設!$C$21)*(MIN(MAX(0,輸入與假設!E$281-(輸入與假設!$C$20+運營_產能與收入!$C$50/3)),輸入與假設!$C$21)+1)/2+輸入與假設!$C$21*MAX(0,MAX(0,輸入與假設!E$281-(輸入與假設!$C$20+運營_產能與收入!$C$50/3))-輸入與假設!$C$21))-(MIN(MAX(0,輸入與假設!D$281-(輸入與假設!$C$20+運營_產能與收入!$C$50/3)),輸入與假設!$C$21)*(MIN(MAX(0,輸入與假設!D$281-(輸入與假設!$C$20+運營_產能與收入!$C$50/3)),輸入與假設!$C$21)+1)/2+輸入與假設!$C$21*MAX(0,MAX(0,輸入與假設!D$281-(輸入與假設!$C$20+運營_產能與收入!$C$50/3))-輸入與假設!$C$21))) -> 2.1945455 | F58: =輸入與假設!$C$19/輸入與假設!$C$21/輸入與假設!$C$22/4*((MIN(MAX(0,輸入與假設!F$281-(輸入與假設!$C$20+運營_產能與收入!$C$50/3)),輸入與假設!$C$21)*(MIN(MAX(0,輸入與假設!F$281-(輸入與假設!$C$20+運營_產能與收入!$C$50/3)),輸入與假設!$C$21)+1)/2+輸入與假設!$C$21*MAX(0,MAX(0,輸入與假設!F$281-(輸入與假設!$C$20+運營_產能與收入!$C$50/3))-輸入與假設!$C$21))-(MIN(MAX(0,輸入與假設!E$281-(輸入與假設!$C$20+運營_產能與收入!$C$50/3)),輸入與假設!$C$21)*(MIN(MAX(0,輸入與假設!E$281-(輸入與假設!$C$20+運營_產能與收入!$C$50/3)),輸入與假設!$C$21)+1)/2+輸入與假設!$C$21*MAX(0,MAX(0,輸入與假設!E$281-(輸入與假設!$C$20+運營_產能與收入!$C$50/3))-輸入與假設!$C$21))) -> 3.2272727 | G58: =輸入與假設!$C$19/輸入與假設!$C$21/輸入與假設!$C$22/4*((MIN(MAX(0,輸入與假設!G$281-(輸入與假設!$C$20+運營_產能與收入!$C$50/3)),輸入與假設!$C$21)*(MIN(MAX(0,輸入與假設!G$281-(輸入與假設!$C$20+運營_產能與收入!$C$50/3)),輸入與假設!$C$21)+1)/2+輸入與假設!$C$21*MAX(0,MAX(0,輸入與假設!G$281-(輸入與假設!$C$20+運營_產能與收入!$C$50/3))-輸入與假設!$C$21))-(MIN(MAX(0,輸入與假設!F$281-(輸入與假設!$C$20+運營_產能與收入!$C$50/3)),輸入與假設!$C$21)*(MIN(MAX(0,輸入與假設!F$281-(輸入與假設!$C$20+運營_產能與收入!$C$50/3)),輸入與假設!$C$21)+1)/2+輸入與假設!$C$21*MAX(0,MAX(0,輸入與假設!F$281-(輸入與假設!$C$20+運營_產能與收入!$C$50/3))-輸入與假設!$C$21))) -> 4.26 | I58: ＝未起租排程的起算季延後 延誤月數 ÷ 3 季（其餘同『輸入與假設』表外現金租金）
A59: 表外現金租金（未起租，延誤連動後） | B59: US$bn | C59: =IF(OR(運營_產能與收入!$C$50<=0,運營_產能與收入!$C$56<=0),輸入與假設!C$282,(1-運營_產能與收入!$C$56)*輸入與假設!C$282+運營_產能與收入!$C$56*C58) -> 0.19363636 | D59: =IF(OR(運營_產能與收入!$C$50<=0,運營_產能與收入!$C$56<=0),輸入與假設!D$282,(1-運營_產能與收入!$C$56)*輸入與假設!D$282+運營_產能與收入!$C$56*D58) -> 1.1618182 | E59: =IF(OR(運營_產能與收入!$C$50<=0,運營_產能與收入!$C$56<=0),輸入與假設!E$282,(1-運營_產能與收入!$C$56)*輸入與假設!E$282+運營_產能與收入!$C$56*E58) -> 2.1945455 | F59: =IF(OR(運營_產能與收入!$C$50<=0,運營_產能與收入!$C$56<=0),輸入與假設!F$282,(1-運營_產能與收入!$C$56)*輸入與假設!F$282+運營_產能與收入!$C$56*F58) -> 3.2272727 | G59: =IF(OR(運營_產能與收入!$C$50<=0,運營_產能與收入!$C$56<=0),輸入與假設!G$282,(1-運營_產能與收入!$C$56)*輸入與假設!G$282+運營_產能與收入!$C$56*G58) -> 4.26 | I59: ＝(1 − 連動比例)× 原排程＋連動比例 × 平移後排程；延誤 0 時＝原排程（『各期收支』租金引用此列）
A60: 容量上限（未延誤，對照） | B60: US$bn | C60: =IF(輸入與假設!$C$30=1,(輸入與假設!$C$29+C10)/2,C10)*輸入與假設!C$39*輸入與假設!$C$32*輸入與假設!C$38*C7 -> 12.722752 | D60: =IF(輸入與假設!$C$30=1,(C10+D10)/2,D10)*輸入與假設!D$39*輸入與假設!$C$32*輸入與假設!D$38*D7 -> 38.101402 | E60: =IF(輸入與假設!$C$30=1,(D10+E10)/2,E10)*輸入與假設!E$39*輸入與假設!$C$32*輸入與假設!E$38*E7 -> 55.370613 | F60: =IF(輸入與假設!$C$30=1,(E10+F10)/2,F10)*輸入與假設!F$39*輸入與假設!$C$32*輸入與假設!F$38*F7 -> 72.763033 | G60: =IF(輸入與假設!$C$30=1,(F10+G10)/2,G10)*輸入與假設!G$39*輸入與假設!$C$32*輸入與假設!G$38*G7 -> 90.21732 | I60: ＝未延誤的平均可計費 MW × 每 MW 年收入 × 利用率 × 期間長度
A61: 應計費而未計費營收（延誤造成） | B61: US$bn | C61: =IF(運營_產能與收入!$C$50<=0,0,MAX(0,C60-C16)) -> 0 | D61: =IF(運營_產能與收入!$C$50<=0,0,MAX(0,D60-D16)) -> 0 | E61: =IF(運營_產能與收入!$C$50<=0,0,MAX(0,E60-E16)) -> 0 | F61: =IF(運營_產能與收入!$C$50<=0,0,MAX(0,F60-F16)) -> 0 | G61: =IF(運營_產能與收入!$C$50<=0,0,MAX(0,G60-G16)) -> 0 | I61: ＝未延誤容量上限 − 延誤後容量上限
A62: 延誤罰則（營業費用） | B62: US$bn | C62: =運營_產能與收入!$C$57*C61 -> 0 | D62: =運營_產能與收入!$C$57*D61 -> 0 | E62: =運營_產能與收入!$C$57*E61 -> 0 | F62: =運營_產能與收入!$C$57*F61 -> 0 | G62: =運營_產能與收入!$C$57*G61 -> 0 | I62: ＝罰則比例 × 應計費而未計費營收；扣 EBITDA、營運來源、稅基與債務上限。客戶預付不因延誤退還（已知限制）

Sheet 運營_站點
A1: 站點租賃 — 公司揭露 vs 季報總額（檢驗租金路徑用）
A2: 季報不揭露逐站租金；下表為具名站點（company.json → defaults.sites），有租約金額者用來檢驗『每 MW 年租金』與模型租金路徑是否一致
A4: 站點 | B4: 營運方 | C4: 契約 MW | D4: 已驗收 MW | E4: 合約總值 $bn | F4: 年期 | G4: 年租金 $bn | H4: 每 MW 年租金 $m | I4: 時程 | J4: 季報對應 | K4: 說明
A5: Mesa, AZ | B5: Google 自建 | C5: 183 | D5: 183 | E5: 未揭露 | F5: 未揭露 | I5: 2026 | J5: — | K5: Epoch AI 資料中心目錄：IT 電力 183 MW（估計 2026-08-15 營運；事實總帳 mw.site.mesa）[第三方]
A6: 具名站點合計 | C6: =SUM(C5:C5) -> 183 | D6: =SUM(D5:D5) -> 183 | E6: =SUM(E5:E5) -> 0 | G6: =SUM(G5:G5) -> 0 | H6: =IF(I6>0,G6/I6*1000,0) -> 0 | I6: =SUMPRODUCT(ISNUMBER(G5:G5)*C5:C5) -> 0 | K6: 加權每 MW 年租金＝具名站點的市場基準（I 欄＝有租約金額站點的契約 MW；沒有時為 0，不適用）
A8: 對帳：具名站點 vs 季報租賃承諾總額
A9: 季報在帳租賃（未折現，已起租） | E9: 24.253 | K9: company.json → leases.facts.onBal
A10: 季報未起租租賃（未折現） | E10: 85.2 | K10: company.json → leases.facts.notCommenced
A11: 季報單站按造價計租上限 | E11: 0 | K11: company.json → leases.facts.singleCap（無則 0）
A12: 季報已揭露租賃承諾合計 | E12: =SUM(E9:E11) -> 109.453 | K12: 未折現金額
A13: 減：具名站點合約總值 | E13: =-E6 -> 0
A14: ＝ 未具名站點（殘差） | E14: =E12+E13 -> 109.453 | K14: 未具名站點；公司不揭露逐站租金，殘差大是必然
A15: 殘差占季報總額 | E15: =IF(E12<>0,E14/E12,0) -> 1
A17: 檢驗：模型租金路徑 ÷ 在役 MW vs 市場基準
A18: 項目 | B18: 單位 | C18: 2026 | D18: 2027 | E18: 2028 | F18: 2029 | G18: 2030
A19: 模型租金（在帳＋表外） | B19: US$bn | C19: =各期收支!C16 -> 0.23031376 | D19: =各期收支!D16 -> 0.53288254 | E19: =各期收支!E16 -> 0.65255591 | F19: =各期收支!F16 -> 0.76122927 | G19: =各期收支!G16 -> 0.81990264
A20: 平均在役 MW（已連網） | B20: MW | C20: =(輸入與假設!C$289+輸入與假設!C$36)/2 -> 1993.025 | D20: =(輸入與假設!D$289+輸入與假設!D$36)/2 -> 3147.1 | E20: =(輸入與假設!E$289+輸入與假設!E$36)/2 -> 4393.2 | F20: =(輸入與假設!F$289+輸入與假設!F$36)/2 -> 5639.3 | G20: =(輸入與假設!G$289+輸入與假設!G$36)/2 -> 6885.4
A21: 模型期長度（年） | B21: 年 | C21: =輸入與假設!C$34 -> 0.5 | D21: =輸入與假設!D$34 -> 1 | E21: =輸入與假設!E$34 -> 1 | F21: =輸入與假設!F$34 -> 1 | G21: =輸入與假設!G$34 -> 1
A22: 模型每 MW 年租金 | B22: US$m/MW | C22: =C19/C21/C20*1000 -> 0.23111979 | D22: =D19/D21/D20*1000 -> 0.16932495 | E22: =E19/E21/E20*1000 -> 0.14853772 | F22: =F19/F21/F20*1000 -> 0.13498648 | G22: =G19/G21/G20*1000 -> 0.11907843 | K22: 2026 欄只含下半年租金、MW 取全期平均，略有低估
A23: 第三方租賃占比 | C23: 1 | K23: 其餘為自建，成本走 CapEx（company.json → leases.facts.share）[Assumed]
A24: 基準租金（MW×市場基準×占比） | B24: US$bn | C24: =C20*運營_站點!$H$6/1000*$C$23*C21 -> 0 | D24: =D20*運營_站點!$H$6/1000*$C$23*D21 -> 0 | E24: =E20*運營_站點!$H$6/1000*$C$23*E21 -> 0 | F24: =F20*運營_站點!$H$6/1000*$C$23*F21 -> 0 | G24: =G20*運營_站點!$H$6/1000*$C$23*G21 -> 0 | K24: 具名站點有租約金額時才有意義；否則為 0
A25: 差額（基準 − 模型） | B25: US$bn | C25: =C24-C19 -> -0.23031376 | D25: =D24-D19 -> -0.53288254 | E25: =E24-E19 -> -0.65255591 | F25: =F24-F19 -> -0.76122927 | G25: =G24-G19 -> -0.81990264 | K25: 正值＝模型租金可能低估的金額
A26: 五期差額合計 | C26: =SUM(C25:G25) -> -2.9968841

Sheet 資產負債_既有債務
A1: 債務明細 — 季報（2026-06-30）逐筆＋存量利息推導
A2: 有效利率為現金票息口徑（可轉債＝票息 ÷ 到期累積倍數，本金以到期累積本金計）。本頁算出的存量利息連回『輸入』頁，再進入支出與資金頁
A4: 工具 | B4: 類別 | C4: 到期 | D4: 有效利率 | E4: 6/30 本金 | F4: 年化利息 | I4: 備註
A5: 2016 美元票據（2.0B） | B5: 無擔保 | C5: 2026-08 | D5: 0.0223 | E5: 2 | F5: =D5*E5 -> 0.0446 | I5: 10-Q 2026Q2 附註 6：面額 2,000、票面 2.00%、有效利率 2.23%、2026 到期 [Interested-party]
A6: 2020 美元票據（9.0B） | B6: 無擔保 | C6: 2040-08 | D6: 0.0163 | E6: 9 | F6: =D6*E6 -> 0.1467 | I6: 10-Q 附註 6：面額 9,000、有效利率 0.93%–2.33%（取中點）、到期 2027–2060；到期日取區間中段 [Assumed]
A7: 2025 美元票據（22.5B；含浮動 0.5B） | B7: 無擔保 | C7: 2045-05 | D7: 0.04895 | E7: 22.5 | F7: =D7*E7 -> 1.101375 | I7: 10-Q 附註 6：面額 22,500、有效利率 4.00%–5.79%（取中點）、到期 2028–2075；到期日取區間中段 [Assumed]
A8: 2025 歐元票據 | B8: 無擔保 | C8: 2042-11 | D8: 0.0354 | E8: 15.074 | F8: =D8*E8 -> 0.5336196 | I8: 10-Q 附註 6：面額 15,074（含匯率）、有效利率 2.57%–4.51%（取中點）、到期 2028–2064 [Assumed 到期日]
A9: 2026 美元票據（20.0B） | B9: 無擔保 | C9: 2041-02 | D9: 0.048 | E9: 20 | F9: =D9*E9 -> 0.96 | I9: 10-Q 附註 6：面額 20,000、加權票面 4.80%、加權年限 15 年（2026Q1 發行）[Interested-party]
A10: 2026 英鎊票據（£5.5B） | B10: 無擔保 | C10: 2057-02 | D10: 0.0531 | E10: 7.263 | F10: =D10*E10 -> 0.3856653 | I10: 10-Q 附註 6：面額 7,263、加權票面 5.31%、加權年限 31 年 [Interested-party]
A11: 2026 瑞士法郎票據（CHF3.1B） | B11: 無擔保 | C11: 2036-02 | D11: 0.0106 | E11: 3.772 | F11: =D11*E11 -> 0.0399832 | I11: 10-Q 附註 6：面額 3,772、加權票面 1.06%、加權年限 10 年 [Interested-party]
A12: 2026 歐元票據（€9.0B） | B12: 無擔保 | C12: 2039-05 | D12: 0.039 | E12: 10.239 | F12: =D12*E12 -> 0.399321 | I12: 10-Q 附註 6：面額 10,239、加權票面 3.90%、加權年限 13 年 [Interested-party]
A13: 2026 加幣票據（C$8.5B） | B13: 無擔保 | C13: 2041-05 | D13: 0.0435 | E13: 5.985 | F13: =D13*E13 -> 0.2603475 | I13: 10-Q 附註 6：面額 5,985、加權票面 4.35%、加權年限 15 年 [Interested-party]
A14: 2026 日圓票據（¥576.5B） | B14: 無擔保 | C14: 2034-05 | D14: 0.0265 | E14: 3.566 | F14: =D14*E14 -> 0.094499 | I14: 10-Q 附註 6：面額 3,566、加權票面 2.65%、加權年限 8 年 [Interested-party]
A15: 其他長期債（含信用額度動用 1.3B） | B15: 無擔保 | C15: 2030-04 | D15: 0.059 | E15: 1.686 | F15: =D15*E15 -> 0.099474 | I15: 10-Q 附註 6：其他長期債 1,686；信用額度動用 1,300 利率 SOFR＋1.5%–2.25%（約 5.9%，[Derived]）、至 2030-04 到期
A16: 合計（6/30） | E16: =SUM(E5:E15) -> 101.085 | F16: =SUM(F5:F15) -> 4.0655846 | I16: 應等於最新季報本金合計 101.085（company.json → latestQuarter.debtPrincipal）
A17: 加權有效利率 | D17: =F16/E16 -> 0.040219465 | I17: ＝年化利息 ÷ 本金（company.json → debt.instruments 的有效利率）
A19: 評價日後新發可轉債 | D19: 0 | E19: 0 | F19: =D19*E19 -> 0 | I19: company.json → debt.convertible（期後新發；不在五期還本表內，只計利息）
A21: 可轉債逐檔（若轉換法：有效轉換價 < 判斷價 → 視為轉股，不計利息與還本）
A22: 可轉債 | B22: 到期 | C22: 票息 | D22: 原始本金 | E22: 到期累積倍數 | F22: 轉換價 | G22: 到期所屬模型期 | H22: 強制轉換（1＝是） | I22: 備註
A23: 6.25% 強制轉換特別股（A、B 系列，2026-06） | B23: 2029-05 | C23: 0.0625 | D23: 19.25 | E23: 1 | F23: 352.56 | G23: 3 | H23: 1 | I23: 清算價 $19.25B（19.25M 股 × $1,000；385M 存託股）；2029-05-15 強制轉換：A 系列每股轉 2.2520–2.8160 股 A 股、B 系列 2.2740–2.8420 股 C 股 → 43.6–54.6M 股，一律轉股，取稀釋最大 54.6M 股（轉換價下限約 $352.56；8-K 2026-06-05 [Interested-party]）；6.25% 股利列於 defaults.dividend.preferred；權益，不列債務本金；capped call 上限 532.67（A）／527.80（C）未建模
I24: 到期所屬模型期：0＝首期 … 4＝末期、5＝模型期後（建置時依期末日推算）
A26: 可轉債（推導） | C26: 到期本金 | D26: 若轉換股數 | E26: 有效轉換價 | F26: 融資分類 | G26: 評價第一輪 | H26: 評價第二輪 | I26: 說明
A27: =A23 -> 6.25% 強制轉換特別股（A、B 系列，2026-06） | C27: =D23*E23 -> 19.25 | D27: =D23/F23 -> 0.054600635 | E27: =F23*E23 -> 352.56 | F27: =IF(OR(H23=1,E27<輸入與假設!$C$343),1,0) -> 1 | G27: =IF(OR(H23=1,E27<輸入與假設!$C$366),1,0) -> 1 | H27: =IF(OR(H23=1,E27<評價_DCF與目標價!$C$87),1,0) -> 1
A28: 合計 | C28: =SUM(C27:C27) -> 19.25 | D28: =SUM(D27:D27) -> 0.054600635 | I28: 分類 1＝轉股（若轉換法）、0＝債務。強制轉換者一律為 1。融資分類判斷價＝股權發行價；評價第一輪＝現價；第二輪＝MIN(現價, 第一輪加權目標價)
A30: 存量利息推導（本金依季報到期表遞減）
A31: 項目 | B31: 單位 | C31: 2026 | D31: 2027 | E31: 2028 | F31: 2029 | G31: 2030 | I31: 公式／來源說明
A32: 期初本金 | B32: US$bn | C32: =E16 -> 101.085 | D32: =C34 -> 99.085 | E32: =D34 -> 98.085 | F32: =E34 -> 95.409 | G32: =F34 -> 93.645 | I32: 2026 期初為 6/30 本金（模型期起點）
A33: 排程還本 | B33: US$bn | C33: =輸入與假設!C$361 -> 2 | D33: =輸入與假設!D$361 -> 1 | E33: =輸入與假設!E$361 -> 2.676 | F33: =輸入與假設!F$361 -> 1.764 | G33: =輸入與假設!G$361 -> 7.186 | I33: 季報到期表
A34: 期末本金 | B34: US$bn | C34: =C32-C33 -> 99.085 | D34: =D32-D33 -> 98.085 | E34: =E32-E33 -> 95.409 | F34: =F32-F33 -> 93.645 | G34: =G32-G33 -> 86.459
A35: 平均本金 | B35: US$bn | C35: =(C32+C34)/2 -> 100.085 | D35: =(D32+D34)/2 -> 98.585 | E35: =(E32+E34)/2 -> 96.747 | F35: =(F32+F34)/2 -> 94.527 | G35: =(G32+G34)/2 -> 90.052
A36: 存量債務利息 | B36: US$bn | C36: =C35*資產負債_既有債務!$D$17*輸入與假設!C$34 -> 2.0126826 | D36: =D35*資產負債_既有債務!$D$17*輸入與假設!D$34 -> 3.9650359 | E36: =E35*資產負債_既有債務!$D$17*輸入與假設!E$34 -> 3.8911126 | F36: =F35*資產負債_既有債務!$D$17*輸入與假設!F$34 -> 3.8018253 | G36: =G35*資產負債_既有債務!$D$17*輸入與假設!G$34 -> 3.6218432 | I36: ＝平均本金×加權有效利率×期間長度。限制：假設利率組合不變；可轉債折價攤銷（非現金）不計
A37: 期後新發可轉債利息 | B37: US$bn | C37: =資產負債_既有債務!$F$19*輸入與假設!C$34 -> 0 | D37: =資產負債_既有債務!$F$19*輸入與假設!D$34 -> 0 | E37: =資產負債_既有債務!$F$19*輸入與假設!E$34 -> 0 | F37: =資產負債_既有債務!$F$19*輸入與假設!F$34 -> 0 | G37: =資產負債_既有債務!$F$19*輸入與假設!G$34 -> 0
A38: 可轉債到期還本（債務處理） | B38: US$bn | C38: =IF(輸入與假設!$C$332=1,SUMPRODUCT((1-資產負債_既有債務!$F$27:$F$27)*資產負債_既有債務!$C$27:$C$27*(資產負債_既有債務!$G$23:$G$23=0)),0) -> 0 | D38: =IF(輸入與假設!$C$332=1,SUMPRODUCT((1-資產負債_既有債務!$F$27:$F$27)*資產負債_既有債務!$C$27:$C$27*(資產負債_既有債務!$G$23:$G$23=1)),0) -> 0 | E38: =IF(輸入與假設!$C$332=1,SUMPRODUCT((1-資產負債_既有債務!$F$27:$F$27)*資產負債_既有債務!$C$27:$C$27*(資產負債_既有債務!$G$23:$G$23=2)),0) -> 0 | F38: =IF(輸入與假設!$C$332=1,SUMPRODUCT((1-資產負債_既有債務!$F$27:$F$27)*資產負債_既有債務!$C$27:$C$27*(資產負債_既有債務!$G$23:$G$23=3)),0) -> 0 | G38: =IF(輸入與假設!$C$332=1,SUMPRODUCT((1-資產負債_既有債務!$F$27:$F$27)*資產負債_既有債務!$C$27:$C$27*(資產負債_既有債務!$G$23:$G$23=4)),0) -> 0 | I38: 融資分類為債務的可轉債，到期當期以到期累積本金現金還本
A39: 可轉債期末餘額（債務處理） | B39: US$bn | C39: =IF(輸入與假設!$C$332=1,SUMPRODUCT((1-資產負債_既有債務!$F$27:$F$27)*資產負債_既有債務!$C$27:$C$27*(資產負債_既有債務!$G$23:$G$23>0)),SUMPRODUCT((1-資產負債_既有債務!$F$27:$F$27)*資產負債_既有債務!$C$27:$C$27)) -> 0 | D39: =IF(輸入與假設!$C$332=1,SUMPRODUCT((1-資產負債_既有債務!$F$27:$F$27)*資產負債_既有債務!$C$27:$C$27*(資產負債_既有債務!$G$23:$G$23>1)),SUMPRODUCT((1-資產負債_既有債務!$F$27:$F$27)*資產負債_既有債務!$C$27:$C$27)) -> 0 | E39: =IF(輸入與假設!$C$332=1,SUMPRODUCT((1-資產負債_既有債務!$F$27:$F$27)*資產負債_既有債務!$C$27:$C$27*(資產負債_既有債務!$G$23:$G$23>2)),SUMPRODUCT((1-資產負債_既有債務!$F$27:$F$27)*資產負債_既有債務!$C$27:$C$27)) -> 0 | F39: =IF(輸入與假設!$C$332=1,SUMPRODUCT((1-資產負債_既有債務!$F$27:$F$27)*資產負債_既有債務!$C$27:$C$27*(資產負債_既有債務!$G$23:$G$23>3)),SUMPRODUCT((1-資產負債_既有債務!$F$27:$F$27)*資產負債_既有債務!$C$27:$C$27)) -> 0 | G39: =IF(輸入與假設!$C$332=1,SUMPRODUCT((1-資產負債_既有債務!$F$27:$F$27)*資產負債_既有債務!$C$27:$C$27*(資產負債_既有債務!$G$23:$G$23>4)),SUMPRODUCT((1-資產負債_既有債務!$F$27:$F$27)*資產負債_既有債務!$C$27:$C$27)) -> 0 | I39: 到期累積本金；關閉攤還時維持全額
A40: 可轉債票息（債務處理） | B40: US$bn | C40: =IF(輸入與假設!$C$332=1,SUMPRODUCT((1-資產負債_既有債務!$F$27:$F$27)*資產負債_既有債務!$D$23:$D$23*資產負債_既有債務!$C$23:$C$23*((資產負債_既有債務!$G$23:$G$23>0)+0.5*(資產負債_既有債務!$G$23:$G$23=0))),SUMPRODUCT((1-資產負債_既有債務!$F$27:$F$27)*資產負債_既有債務!$D$23:$D$23*資產負債_既有債務!$C$23:$C$23))*輸入與假設!C$34 -> 0 | D40: =IF(輸入與假設!$C$332=1,SUMPRODUCT((1-資產負債_既有債務!$F$27:$F$27)*資產負債_既有債務!$D$23:$D$23*資產負債_既有債務!$C$23:$C$23*((資產負債_既有債務!$G$23:$G$23>1)+0.5*(資產負債_既有債務!$G$23:$G$23=1))),SUMPRODUCT((1-資產負債_既有債務!$F$27:$F$27)*資產負債_既有債務!$D$23:$D$23*資產負債_既有債務!$C$23:$C$23))*輸入與假設!D$34 -> 0 | E40: =IF(輸入與假設!$C$332=1,SUMPRODUCT((1-資產負債_既有債務!$F$27:$F$27)*資產負債_既有債務!$D$23:$D$23*資產負債_既有債務!$C$23:$C$23*((資產負債_既有債務!$G$23:$G$23>2)+0.5*(資產負債_既有債務!$G$23:$G$23=2))),SUMPRODUCT((1-資產負債_既有債務!$F$27:$F$27)*資產負債_既有債務!$D$23:$D$23*資產負債_既有債務!$C$23:$C$23))*輸入與假設!E$34 -> 0 | F40: =IF(輸入與假設!$C$332=1,SUMPRODUCT((1-資產負債_既有債務!$F$27:$F$27)*資產負債_既有債務!$D$23:$D$23*資產負債_既有債務!$C$23:$C$23*((資產負債_既有債務!$G$23:$G$23>3)+0.5*(資產負債_既有債務!$G$23:$G$23=3))),SUMPRODUCT((1-資產負債_既有債務!$F$27:$F$27)*資產負債_既有債務!$D$23:$D$23*資產負債_既有債務!$C$23:$C$23))*輸入與假設!F$34 -> 0 | G40: =IF(輸入與假設!$C$332=1,SUMPRODUCT((1-資產負債_既有債務!$F$27:$F$27)*資產負債_既有債務!$D$23:$D$23*資產負債_既有債務!$C$23:$C$23*((資產負債_既有債務!$G$23:$G$23>4)+0.5*(資產負債_既有債務!$G$23:$G$23=4))),SUMPRODUCT((1-資產負債_既有債務!$F$27:$F$27)*資產負債_既有債務!$D$23:$D$23*資產負債_既有債務!$C$23:$C$23))*輸入與假設!G$34 -> 0 | I40: ＝原始本金 × 票息 × 期間長度；到期當期計半期
A41: 首期新增借款利息校準 | B41: US$bn | C41: =0 -> 0 | D41: =0 -> 0 | E41: =0 -> 0 | F41: =0 -> 0 | G41: =0 -> 0 | I41: 讓首期模型利息對上公司季度利息指引的校準值（company.json → defaults.intCal）；無指引時為 0
A42: 存量利息合計（連回輸入頁） | B42: US$bn | C42: =C36+C37+C40+C41 -> 2.0126826 | D42: =D36+D37+D40+D41 -> 3.9650359 | E42: =E36+E37+E40+E41 -> 3.8911126 | F42: =F36+F37+F40+F41 -> 3.8018253 | G42: =G36+G37+G40+G41 -> 3.6218432 | I42: ＝存量債務利息＋期後新發可轉債利息＋可轉債票息＋首期校準

Sheet 資產負債_新債與新股
A1: 新債與新股（類資產負債表：現金、債務、股本、槓桿）
A2: 全部為連結公式。2026 欄的現金自 2026-06-30 起算（模型期），與 HTML『資產與負債 → 新債與新股』同口徑
A4: 項目 | B4: 單位 | C4: 2026 | D4: 2027 | E4: 2028 | F4: 2029 | G4: 2030 | I4: 公式／來源說明
A5: 現金
A6: 期初現金 | B6: US$bn | C6: =輸入與假設!$C$327 -> 155.411 | D6: =各期收支!C56 -> 128.12291 | E6: =各期收支!D56 -> 85.935507 | F6: =各期收支!E56 -> 63.440965 | G6: =各期收支!F56 -> 53.700182 | I6: 2026＝6/30 現金（模型期起點）
A7: 營運收支淨額（含期後股權／可轉債，不含瀑布） | B7: US$bn | C7: =各期收支!C103-輸入與假設!$C$327 -> -18.786593 | D7: =各期收支!D103-各期收支!C103 -> -25.184399 | E7: =各期收支!E103-各期收支!D103 -> -5.4915424 | F7: =各期收支!F103-各期收支!E103 -> 7.2622166 | G7: =各期收支!G103-各期收支!F103 -> -85.215953 | I7: ＝融資前累積現金的當期變動；負值即當期外部資金需求
A8: ＋ 瀑布：新債（額度＋資產層） | B8: US$bn | C8: =各期收支!C86 -> 0 | D8: =各期收支!D86 -> 0 | E8: =各期收支!E86 -> 0 | F8: =各期收支!F86 -> 0 | G8: =各期收支!G86 -> 85.806075
A9: ＋ 瀑布：可轉債 | B9: US$bn | C9: =各期收支!C89 -> 0 | D9: =各期收支!D89 -> 0 | E9: =各期收支!E89 -> 0 | F9: =各期收支!F89 -> 0 | G9: =各期收支!G89 -> 0
A10: ＋ 瀑布：高息債 | B10: US$bn | C10: =各期收支!C93 -> 0 | D10: =各期收支!D93 -> 0 | E10: =各期收支!E93 -> 0 | F10: =各期收支!F93 -> 0 | G10: =各期收支!G93 -> 0
A11: ＋ 瀑布：股權募資 | B11: US$bn | C11: =各期收支!C92 -> 0 | D11: =各期收支!D92 -> 0 | E11: =各期收支!E92 -> 0 | F11: =各期收支!F92 -> 0 | G11: =各期收支!G92 -> 0
A12: − 回購（瀑布第二步） | B12: US$bn | C12: =-各期收支!C76 -> -8.5015 | D12: =-各期收支!D76 -> -17.003 | E12: =-各期收支!E76 -> -17.003 | F12: =-各期收支!F76 -> -17.003 | G12: =-各期收支!G76 -> 0
A13: − 新融資利息（新債＋可轉債＋高息債） | B13: US$bn | C13: =-各期收支!C94 -> 0 | D13: =-各期收支!D94 -> 0 | E13: =-各期收支!E94 -> 0 | F13: =-各期收支!F94 -> 0 | G13: =-各期收支!G94 -> -4.2903038
A14: 期末現金 | B14: US$bn | C14: =SUM(C6:C13) -> 128.12291 | D14: =SUM(D6:D13) -> 85.935507 | E14: =SUM(E6:E13) -> 63.440965 | F14: =SUM(F6:F13) -> 53.700182 | G14: =SUM(G6:G13) -> 50 | I14: 應等於『各期收支』期末累積現金（見下列驗算）
A15: 驗算：與各期收支期末現金差異 | B15: US$bn | C15: =C14-各期收支!C56 -> 0 | D15: =D14-各期收支!D56 -> 0 | E15: =E14-各期收支!E56 -> 0 | F15: =F14-各期收支!F56 -> 0 | G15: =G14-各期收支!G56 -> 0 | I15: 應為 0
A16: 債務
A17: 既有債務期初（季報本金） | B17: US$bn | C17: =資產負債_既有債務!$E$16+SUMPRODUCT((1-資產負債_既有債務!$F$27:$F$27)*資產負債_既有債務!$C$27:$C$27) -> 101.085 | D17: =C19 -> 99.085 | E17: =D19 -> 98.085 | F17: =E19 -> 95.409 | G17: =F19 -> 93.645 | I17: 2026＝其他借款＋債務處理可轉債到期本金（轉股處理者不列）
A18: − 排程還本（模型期） | B18: US$bn | C18: =-IF(輸入與假設!$C$332=1,輸入與假設!C$361,0)-資產負債_既有債務!C38 -> -2 | D18: =-IF(輸入與假設!$C$332=1,輸入與假設!D$361,0)-資產負債_既有債務!D38 -> -1 | E18: =-IF(輸入與假設!$C$332=1,輸入與假設!E$361,0)-資產負債_既有債務!E38 -> -2.676 | F18: =-IF(輸入與假設!$C$332=1,輸入與假設!F$361,0)-資產負債_既有債務!F38 -> -1.764 | G18: =-IF(輸入與假設!$C$332=1,輸入與假設!G$361,0)-資產負債_既有債務!G38 -> -7.186
A19: 既有債務期末 | B19: US$bn | C19: =各期收支!C82-0 -> 99.085 | D19: =各期收支!D82-0 -> 98.085 | E19: =各期收支!E82-0 -> 95.409 | F19: =各期收支!F82-0 -> 93.645 | G19: =各期收支!G82-0 -> 86.459 | I19: ＝依到期表遞減（關閉攤還時維持期初）
A20: ＋ 期後新發可轉債 | B20: US$bn | C20: =0 -> 0 | D20: =0 -> 0 | E20: =0 -> 0 | F20: =0 -> 0 | G20: =0 -> 0
A21: ＋ 瀑布新債餘額 | B21: US$bn | C21: =各期收支!C98 -> 0 | D21: =各期收支!D98 -> 0 | E21: =各期收支!E98 -> 0 | F21: =各期收支!F98 -> 0 | G21: =各期收支!G98 -> 85.806075
A22: ＋ 瀑布可轉債餘額 | B22: US$bn | C22: =各期收支!C101 -> 0 | D22: =各期收支!D101 -> 0 | E22: =各期收支!E101 -> 0 | F22: =各期收支!F101 -> 0 | G22: =各期收支!G101 -> 0
A23: ＋ 高息債餘額 | B23: US$bn | C23: =各期收支!C100 -> 0 | D23: =各期收支!D100 -> 0 | E23: =各期收支!E100 -> 0 | F23: =各期收支!F100 -> 0 | G23: =各期收支!G100 -> 0
A24: 總債務 | B24: US$bn | C24: =SUM(C19:C23) -> 99.085 | D24: =SUM(D19:D23) -> 98.085 | E24: =SUM(E19:E23) -> 95.409 | F24: =SUM(F19:F23) -> 93.645 | G24: =SUM(G19:G23) -> 172.26508 | I24: 應等於『各期收支』期末總債務
A25: 淨負債（總債務 − 期末現金） | B25: US$bn | C25: =C24-C14 -> -29.037907 | D25: =D24-D14 -> 12.149493 | E25: =E24-E14 -> 31.968035 | F25: =F24-F14 -> 39.944818 | G25: =G24-G14 -> 122.26508
A26: 股本
A27: 基礎股數（含 ATM 上限、SBC 稀釋） | B27: bn | C27: =損益!C23 -> 12.363601 | D27: =損益!D23 -> 12.487237 | E27: =損益!E23 -> 12.612109 | F27: =損益!F23 -> 12.73823 | G27: =損益!G23 -> 12.865612
A28: ＋ 本期新股 | B28: bn | C28: =各期收支!C96 -> 0 | D28: =各期收支!D96 -> 0 | E28: =各期收支!E96 -> 0 | F28: =各期收支!F96 -> 0 | G28: =各期收支!G96 -> 0
A29: 總股數（期末） | B29: bn | C29: =損益!C24 -> 12.339345 | D29: =損益!D24 -> 12.414471 | E29: =損益!E24 -> 12.490832 | F29: =損益!F24 -> 12.568443 | G29: =損益!G24 -> 12.695825 | I29: ＝基礎股數＋累計新股
A30: 槓桿
A31: 期末 backlog | B31: US$bn | C31: =各期收支!C81 -> 63.61376 | D31: =各期收支!D81 -> 63.480052 | E31: =各期收支!E81 -> 59.917072 | F31: =各期收支!F81 -> 39.3313 | G31: =各期收支!G81 -> 1.4768399
A32: 債務上限（債務／backlog × 期末 backlog） | B32: US$bn | C32: =各期收支!C83 -> 579.21941 | D32: =各期收支!D83 -> 630.90044 | E32: =各期收支!E83 -> 732.21034 | F32: =各期收支!F83 -> 840.06309 | G32: =各期收支!G83 -> 931.45353
A33: 總債務 ÷ 期末 backlog | B33: x | C33: =C24/MAX(0.01,C31) -> 1.5576033 | D33: =D24/MAX(0.01,D31) -> 1.5451311 | E33: =E24/MAX(0.01,E31) -> 1.5923508 | F33: =F24/MAX(0.01,F31) -> 2.3809281 | G33: =G24/MAX(0.01,G31) -> 116.64438 | I33: 高息債不受 backlog 上限約束
A34: 總債務 ÷ EBITDA（年化） | B34: x | C34: =C24/MAX(0.01,損益!C22/輸入與假設!C$34) -> 0.49331717 | D34: =D24/MAX(0.01,損益!D22/輸入與假設!D$34) -> 0.44454598 | E34: =E24/MAX(0.01,損益!E22/輸入與假設!E$34) -> 0.37145341 | F34: =F24/MAX(0.01,損益!F22/輸入與假設!F$34) -> 0.3172796 | G34: =G24/MAX(0.01,損益!G22/輸入與假設!G$34) -> 0.52526703 | I34: 2026 模型期 EBITDA 以模型期長度年化
A35: 租賃負債（期末） | B35: US$bn | C35: =各期收支!C63 -> 24.726133 | D35: =各期收支!D63 -> 32.620731 | E35: =各期收支!E63 -> 40.306951 | F35: =各期收支!F63 -> 47.669899 | G35: =各期收支!G63 -> 54.877622 | I35: 見『各期收支』租賃負債（期末剩餘租金現值，5.7%）
A36: EBITDAR（年化＝(EBITDA＋租金) ÷ 期間長度） | B36: US$bn | C36: =(損益!C22+各期收支!C16)/輸入與假設!C$34 -> 201.31518 | D36: =(損益!D22+各期收支!D16)/輸入與假設!D$34 -> 221.17372 | E36: =(損益!E22+各期收支!E16)/輸入與假設!E$34 -> 257.50577 | F36: =(損益!F22+各期收支!F16)/輸入與假設!F$34 -> 295.911 | G36: =(損益!G22+各期收支!G16)/輸入與假設!G$34 -> 328.77705
A37: 調整後槓桿（(總債務＋租賃負債) ÷ EBITDAR） | B37: x | C37: =(C24+C35)/MAX(0.01,C36) -> 0.61501141 | D37: =(D24+D35)/MAX(0.01,D36) -> 0.5909641 | E37: =(E24+E35)/MAX(0.01,E36) -> 0.52704044 | F37: =(F24+F35)/MAX(0.01,F36) -> 0.4775588 | G37: =(G24+G35)/MAX(0.01,G36) -> 0.69087151 | I37: S&P 降評門檻 >4.5×（[Interested-party] 二手轉述）；S&P 自身口徑另含全部未起租承諾與無條件採購義務，較本列高（見報告）
A38: 距投資級上限的空間（上限 − 調整後槓桿） | B38: x | C38: =輸入與假設!$C$335-C37 -> 2.3849886 | D38: =輸入與假設!$C$335-D37 -> 2.4090359 | E38: =輸入與假設!$C$335-E37 -> 2.4729596 | F38: =輸入與假設!$C$335-F37 -> 2.5224412 | G38: =輸入與假設!$C$335-G37 -> 2.3091285 | I38: 負值＝超過上限：需股權或失去投資級

Sheet 資產負債_租賃承諾
A1: 租賃與承諾 — 季報（2026-06-30）原始揭露
A2: 本頁為硬編碼的申報數字（藍字），支出與資金頁的租金與還本列由此而來
A4: 在帳租賃到期表（未折現）
A5: 項目 | B5: 單位 | C5: 2026 下半 | D5: 2027 | E5: 2028 | F5: 2029 | G5: 2030 | H5: 其後
A6: 營業租賃付款 | B6: US$bn | C6: 1.836 | D6: 3.498 | E6: 2.979 | F6: 2.576 | G6: 2.046 | H6: 8.398
A7: 融資租賃付款 | B7: US$bn | C7: 0.206 | D7: 0.387 | E7: 0.377 | F7: 0.356 | G7: 0.285 | H7: 1.309
A8: 合計（＝支出頁「在帳現金租金」） | C8: =SUM(C6:C7) -> 2.042 | D8: =SUM(D6:D7) -> 3.885 | E8: =SUM(E6:E7) -> 3.356 | F8: =SUM(F6:F7) -> 2.932 | G8: =SUM(G6:G7) -> 2.331 | H8: =SUM(H6:H7) -> 9.707 | I8: 營業租賃負債現值 18.037、融資租賃 2.59；年報加權剩餘租期 12／14 年、折現率 5.7% [Verified]
A10: 債務本金到期表
A11: 項目 | B11: 單位 | C11: 2026 下半 | D11: 2027 | E11: 2028 | F11: 2029 | G11: 2030 | H11: 其後
A12: 本金（＝支出頁「排程還本」） | B12: US$bn | C12: 2 | D12: 1 | E12: 2.676 | F12: 1.764 | G12: 7.186 | H12: 86.459 | I12: 其他借款到期表（company.json → debt.amortization）；可轉債到期還本依融資分類另計，見『資產負債_既有債務』逐檔表
A13: 合計 | C13: =SUM(C12:H12) -> 101.085
A15: 表外與契約性承諾（未入表）
A16: 項目 | B16: 單位 | C16: 金額 | D16: 時程 | E16: 入表？ | F16: 模型位置
A17: 未起租租賃（未折現） | B17: US$bn | C17: 85.2 | D17: 季報揭露之已簽約未起租租賃 | E17: 否 | F17: 表外現金租金
A18: 單站按造價計租，上限 | B18: US$bn | C18: 0 | D18: 無此類揭露時為 0 | E18: 否 | F18: 表外現金租金
A19: 未動用信用額度 | B19: US$bn | C19: 10.4 | D19: company.json → defaults.facility（信用額度 11.7B（已動用 1.3B）；商業本票額度 25B 未動用） | E19: 否（來源） | F19: 瀑布：未動用額度
A20: 已揭露金額之承諾合計（未起租＋單站上限） | C20: =C17+C18 -> 85.2
A21: 模型表外租金五期合計 | C21: =SUM(各期收支!C15:G15) -> 11.037273
A22: 模型表外租金尾端（模型期後未付＝總額 − 五期） | C22: =MAX(0,輸入與假設!$C$19-C21) -> 74.162727
A23: 模型路徑合計 ÷ 已承諾（≥0.8 為合理） | C23: =(C21+C22)/C20 -> 1 | I23: 起租排程依季報附註（起租期間與期限）平均分攤；五期＋尾端＝未起租總額

Sheet 損益
A1: 損益（類損益表）— 與資金模型同一組收入
A2: 算力收入、Cash CapEx、利息皆由前面分頁連結而來；改資金假設，此頁會跟著動
A4: 項目 | B4: 單位 | C4: 2026 | D4: 2027 | E4: 2028 | F4: 2029 | G4: 2030 | I4: 公式／來源說明
A5: 損益表
A6: 算力收入 | B6: US$bn | C6: =運營_產能與收入!C26 -> 12.722752 | D6: =運營_產能與收入!D26 -> 38.101402 | E6: =運營_產能與收入!E26 -> 55.370613 | F6: =運營_產能與收入!F26 -> 72.763033 | G6: =運營_產能與收入!G26 -> 90.21732 | I6: ＝RPO 轉換＋新簽約
A7: 非算力服務 | B7: US$bn | C7: =輸入與假設!C$43 -> 0 | D7: =輸入與假設!D$43 -> 0 | E7: =輸入與假設!E$43 -> 0 | F7: =輸入與假設!F$43 -> 0 | G7: =輸入與假設!G$43 -> 0
A8: 非 AI 事業 | B8: US$bn | C8: =輸入與假設!C$240 -> 249.85356 | D8: =輸入與假設!D$240 -> 560.97455 | E8: =輸入與假設!E$240 -> 639.86404 | F8: =輸入與假設!F$240 -> 710.98233 | G8: =輸入與假設!G$240 -> 766.28169 | I8: 非 AI 事業各線合計（B2）
A9: 總營收 | B9: US$bn | C9: =C6+C7+C8 -> 262.57631 | D9: =D6+D7+D8 -> 599.07596 | E9: =E6+E7+E8 -> 695.23465 | F9: =F6+F7+F8 -> 783.74537 | G9: =G6+G7+G8 -> 856.49901
A10: EBITDA 率 | B10: % | C10: =輸入與假設!C$250 -> 0.83423438 | D10: =輸入與假設!D$250 -> 0.83894381 | E10: =輸入與假設!E$250 -> 0.84246605 | F10: =輸入與假設!F$250 -> 0.84445571 | G10: =輸入與假設!G$250 -> 0.84573431
A11: 延誤罰則（服務抵減，營業費用） | B11: US$bn | C11: =運營_產能與收入!C62 -> 0 | D11: =運營_產能與收入!D62 -> 0 | E11: =運營_產能與收入!E62 -> 0 | F11: =運營_產能與收入!F62 -> 0 | G11: =運營_產能與收入!G62 -> 0 | I11: 建設延誤期間應計費而未計費營收 × 罰則比例（預設 0；v0.2）
A12: 營業利益（EBIT） | B12: US$bn | C12: =(C6+C7)*輸入與假設!C$250+輸入與假設!C$48+輸入與假設!C$241-輸入與假設!C$242-C11-輸入與假設!C$324 -> 76.368884 | D12: =(D6+D7)*輸入與假設!D$250+輸入與假設!D$48+輸入與假設!D$241-輸入與假設!D$242-D11-輸入與假設!D$324 -> 149.11869 | E12: =(E6+E7)*輸入與假設!E$250+輸入與假設!E$48+輸入與假設!E$241-輸入與假設!E$242-E11-輸入與假設!E$324 -> 152.85766 | F12: =(F6+F7)*輸入與假設!F$250+輸入與假設!F$48+輸入與假設!F$241-輸入與假設!F$242-F11-輸入與假設!F$324 -> 156.95243 | G12: =(G6+G7)*輸入與假設!G$250+輸入與假設!G$48+輸入與假設!G$241-輸入與假設!G$242-G11-輸入與假設!G$324 -> 154.93453 | I12: ＝(算力＋服務營收)×EBITDA 率＋其他事業 EBITDA＋非 AI 事業 EBITDA − 非 AI 事業其他攤銷 − 延誤罰則 − 車隊 D&A
A13: 利息（含瀑布新債） | B13: US$bn | C13: =各期收支!C21 -> 2.0126826 | D13: =各期收支!D21 -> 3.9650359 | E13: =各期收支!E21 -> 3.8911126 | F13: =各期收支!F21 -> 3.8018253 | G13: =各期收支!G21 -> 7.912147
A14: 預付財務組成利息（非現金） | B14: US$bn | C14: =各期收支!C10 -> 0 | D14: =各期收支!D10 -> 0 | E14: =各期收支!E10 -> 0 | F14: =各期收支!F10 -> 0 | G14: =各期收支!G10 -> 0 | I14: 客戶預付的重大財務組成：合約負債以隱含利率累積的利息（v0.1b）
A15: 稅前損益 | B15: US$bn | C15: =C12-C13-C14 -> 74.356201 | D15: =D12-D13-D14 -> 145.15366 | E15: =E12-E13-E14 -> 148.96655 | F15: =F12-F13-F14 -> 153.1506 | G15: =G12-G13-G14 -> 147.02239
A16: NOL 期初餘額 | B16: US$bn | C16: =輸入與假設!$C$396 -> 0 | D16: =C18 -> 0 | E16: =D18 -> 0 | F16: =E18 -> 0 | G16: =F18 -> 0 | I16: 6/30 累積虧損約 0.0
A17: 本期動用 NOL | B17: US$bn | C17: =MIN(C16,MAX(0,C15)*輸入與假設!$C$397) -> 0 | D17: =MIN(D16,MAX(0,D15)*輸入與假設!$C$397) -> 0 | E17: =MIN(E16,MAX(0,E15)*輸入與假設!$C$397) -> 0 | F17: =MIN(F16,MAX(0,F15)*輸入與假設!$C$397) -> 0 | G17: =MIN(G16,MAX(0,G15)*輸入與假設!$C$397) -> 0 | I17: 美國規定：抵扣上限為應稅所得 80%
A18: NOL 期末餘額 | B18: US$bn | C18: =C16-C17+MAX(0,-C15) -> 0 | D18: =D16-D17+MAX(0,-D15) -> 0 | E18: =E16-E17+MAX(0,-E15) -> 0 | F18: =F16-F17+MAX(0,-F15) -> 0 | G18: =G16-G17+MAX(0,-G15) -> 0
A19: 所得稅 | B19: US$bn | C19: =MAX(0,C15-C17)*輸入與假設!$C$383 -> 12.491842 | D19: =MAX(0,D15-D17)*輸入與假設!$C$383 -> 24.385814 | E19: =MAX(0,E15-E17)*輸入與假設!$C$383 -> 25.02638 | F19: =MAX(0,F15-F17)*輸入與假設!$C$383 -> 25.729302 | G19: =MAX(0,G15-G17)*輸入與假設!$C$383 -> 24.699761 | I19: 虧損年不認列稅盾（與公司評價備抵一致）
A20: 淨利 | B20: US$bn | C20: =C15-C19 -> 61.86436 | D20: =D15-D19 -> 120.76784 | E20: =E15-E19 -> 123.94017 | F20: =F15-F19 -> 127.4213 | G20: =G15-G19 -> 122.32262
A21: D&A | B21: US$bn | C21: =輸入與假設!C$324+輸入與假設!C$242 -> 24.058393 | D21: =輸入與假設!D$324+輸入與假設!D$242 -> 71.52215 | E21: =輸入與假設!E$324+輸入與假設!E$242 -> 103.99555 | F21: =輸入與假設!F$324+輸入與假設!F$242 -> 138.19734 | G21: =輸入與假設!G$324+輸入與假設!G$242 -> 173.02261 | I21: 車隊折舊＋非 AI 事業其他攤銷，見輸入頁
A22: EBITDA | B22: US$bn | C22: =C12+C21 -> 100.42728 | D22: =D12+D21 -> 220.64084 | E22: =E12+E21 -> 256.85321 | F22: =F12+F21 -> 295.14977 | G22: =G12+G21 -> 327.95715
A23: 基礎股數（每年 +SBC 稀釋） | B23: bn | C23: =評價_DCF與目標價!$C$90 -> 12.363601 | D23: =C23*(1+輸入與假設!$C$436) -> 12.487237 | E23: =D23*(1+輸入與假設!$C$436) -> 12.612109 | F23: =E23*(1+輸入與假設!$C$436) -> 12.73823 | G23: =F23*(1+輸入與假設!$C$436) -> 12.865612 | I23: 2026＝評價股數（含價內可轉債轉股，見『評價_DCF與目標價』可轉債區）；之後每年 ×(1＋股數年增)
A24: 股數（含瀑布新股） | B24: bn | C24: =C23+各期收支!C97 -> 12.339345 | D24: =D23+各期收支!D97 -> 12.414471 | E24: =E23+各期收支!E97 -> 12.490832 | F24: =F23+各期收支!F97 -> 12.568443 | G24: =G23+各期收支!G97 -> 12.695825 | I24: ＝基礎股數＋累計瀑布新股
A25: 每股盈餘（EPS，模型期） | B25: US$ | C25: =C20/C24 -> 5.0135853 | D25: =D20/D24 -> 9.7279897 | E25: =E20/E24 -> 9.9224906 | F25: =F20/F24 -> 10.138193 | G25: =G20/G24 -> 9.6348702 | I25: 2026 欄只含下半年；全年口徑見下方
A27: 損益表（全年口徑；2026＝1H 實際＋下半年模型；與 HTML 損益簡表一致）
A28: 1H26 實際營收（已實現） | B28: US$bn | C28: =輸入與假設!$C$477 -> 229.692 | D28: =0 -> 0 | E28: =0 -> 0 | F28: =0 -> 0 | G28: =0 -> 0
A29: 全年總營收 | B29: US$bn | C29: =C28+C9 -> 492.26831 | D29: =D28+D9 -> 599.07596 | E29: =E28+E9 -> 695.23465 | F29: =F28+F9 -> 783.74537 | G29: =G28+G9 -> 856.49901 | I29: 2026 可對照指引 未給全年營收指引
A30: 營收 YoY | B30: % | C30: =C29/402.836-1 -> 0.22200675 | D30: =D29/C29-1 -> 0.21697039 | E30: =E29/D29-1 -> 0.16051169 | F30: =F29/E29-1 -> 0.12731056 | G30: =G29/F29-1 -> 0.092828163 | I30: 2025 實際 402.836
A31: 全年 GAAP 營業利益 | B31: US$bn | C31: =輸入與假設!$C$478+C12 -> 156.83488 | D31: =D12 -> 149.11869 | E31: =E12 -> 152.85766 | F31: =F12 -> 156.95243 | G31: =G12 -> 154.93453
A32: 營利率 | B32: % | C32: =C31/C29 -> 0.31859634 | D32: =D31/D29 -> 0.2489145 | E32: =E31/E29 -> 0.21986484 | F32: =F31/F29 -> 0.20025947 | G32: =G31/G29 -> 0.18089283
A33: 全年 D&A | B33: US$bn | C33: =輸入與假設!$C$481+C21 -> 37.644393 | D33: =D21 -> 71.52215 | E33: =E21 -> 103.99555 | F33: =F21 -> 138.19734 | G33: =G21 -> 173.02261 | I33: 1H 實際 13.586
A34: 全年 EBITDA | B34: US$bn | C34: =C31+C33 -> 194.47928 | D34: =D31+D33 -> 220.64084 | E34: =E31+E33 -> 256.85321 | F34: =F31+F33 -> 295.14977 | G34: =G31+G33 -> 327.95715
A35: 全年利息（含瀑布新債） | B35: US$bn | C35: =輸入與假設!$C$475+C13 -> 3.8236826 | D35: =D13 -> 3.9650359 | E35: =E13 -> 3.8911126 | F35: =F13 -> 3.8018253 | G35: =G13 -> 7.912147 | I35: 2027 起瀑布新債利息與新股同時影響 EPS
A36: 全年淨利 | B36: US$bn | C36: =輸入與假設!$C$479+C20 -> 236.63536 | D36: =D20 -> 120.76784 | E36: =E20 -> 123.94017 | F36: =F20 -> 127.4213 | G36: =G20 -> 122.32262
A37: 淨利率 | B37: % | C37: =C36/C29 -> 0.48070403 | D37: =D36/D29 -> 0.2015902 | E37: =E36/E29 -> 0.17827098 | F37: =F36/F29 -> 0.16257998 | G37: =G36/G29 -> 0.14281701
A38: 全年 GAAP EPS | B38: US$ | C38: =輸入與假設!$C$483+C20/C24 -> 19.233585 | D38: =D20/D24 -> 9.7279897 | E38: =E20/E24 -> 9.9224906 | F38: =F20/F24 -> 10.138193 | G38: =G20/G24 -> 9.6348702 | I38: 2026＝1H 實際 EPS 14.22＋下半年淨利÷股數
A39: 全年 EPS（加回 SBC） | B39: US$ | C39: =輸入與假設!$C$484+(C20+輸入與假設!$C$437*輸入與假設!C$34)/C24 -> 21.594124 | D39: =(D20+輸入與假設!$C$437*輸入與假設!D$34)/D24 -> 11.995263 | E39: =(E20+輸入與假設!$C$437*輸入與假設!E$34)/E24 -> 12.175903 | F39: =(F20+輸入與假設!$C$437*輸入與假設!F$34)/F24 -> 12.377691 | G39: =(G20+輸入與假設!$C$437*輸入與假設!G$34)/G24 -> 11.851898 | I39: ＝(淨利＋SBC)÷股數；NOL 狀態無現金稅，SBC 全額加回

Sheet 評價_DCF與目標價
A1: 評價 — DCF、EV/EBITDA、加權目標價
A2: 營收、營業利益、D&A、EBITDA、股數引用『損益』頁；Cash CapEx 與融資引用『各期收支』頁
A4: 項目 | B4: 單位 | C4: 2026 | D4: 2027 | E4: 2028 | F4: 2029 | G4: 2030 | I4: 公式／來源說明
A5: DCF（無槓桿自由現金流；起點為 2026-06-30）
A6: 現金 CapEx（2026-06-30 之後） | B6: US$bn | C6: =輸入與假設!C$323-各期收支!C8 -> 119.40679 | D6: =輸入與假設!D$323-各期收支!D8 -> 236.83502 | E6: =輸入與假設!E$323-各期收支!E8 -> 256.54578 | F6: =輸入與假設!F$323-各期收支!F8 -> 287.92653 | G6: =輸入與假設!G$323-各期收支!G8 -> 412.79175 | I6: DCF 起點為 6/30，故 2026 欄只含 2H 的建置支出，不含 1H 已發生的 80.598
A7: 比較基期營收 | B7: US$bn | C7: =402.836 -> 402.836 | D7: =229.692+損益!C9 -> 492.26831 | E7: =損益!D9 -> 599.07596 | F7: =損益!E9 -> 695.23465 | G7: =損益!F9 -> 783.74537 | I7: 2025 實際 402.836；2027 基期＝1H 實際 229.692＋2026 模型期營收
A8: 預付認列（非現金營收，扣除） | B8: US$bn | C8: =各期收支!C11 -> 0 | D8: =各期收支!D11 -> 0 | E8: =各期收支!E11 -> 0 | F8: =各期收支!F11 -> 0 | G8: =各期收支!G11 -> 0 | I8: 營收中由合約負債轉入的部分已在預付時收現（預付流入已自現金 CapEx 抵減），UFCF 扣除以免重複（v0.1b）
A9: 營運資金變動 | B9: US$bn | C9: =IF(ISBLANK(輸入與假設!$C$50),輸入與假設!$C$398*MAX(0,損益!C9-C7),-輸入與假設!$C$50) -> -8.49 | D9: =輸入與假設!$C$398*MAX(0,損益!D9-D7) -> 0 | E9: =輸入與假設!$C$398*MAX(0,損益!E9-E7) -> 0 | F9: =輸入與假設!$C$398*MAX(0,損益!F9-F7) -> 0 | G9: =輸入與假設!$C$398*MAX(0,損益!G9-G7) -> 0 | I9: 2026＝−上年同期實際（輸入非空白時；MAG v0.1b r2 C14）；之後＝營收增量的 0%
A10: 無槓桿 NOL 期初 | B10: US$bn | C10: =輸入與假設!$C$396 -> 0 | D10: =C12 -> 0 | E10: =D12 -> 0 | F10: =E12 -> 0 | G10: =F12 -> 0 | I10: DCF 用無槓桿稅（利息不可抵稅，否則稅盾被計兩次：一次在 UFCF、一次在 WACC）
A11: 本期動用（無槓桿） | B11: US$bn | C11: =MIN(C10,MAX(0,損益!C12)*輸入與假設!$C$397) -> 0 | D11: =MIN(D10,MAX(0,損益!D12)*輸入與假設!$C$397) -> 0 | E11: =MIN(E10,MAX(0,損益!E12)*輸入與假設!$C$397) -> 0 | F11: =MIN(F10,MAX(0,損益!F12)*輸入與假設!$C$397) -> 0 | G11: =MIN(G10,MAX(0,損益!G12)*輸入與假設!$C$397) -> 0
A12: 無槓桿 NOL 期末 | B12: US$bn | C12: =C10-C11+MAX(0,-損益!C12) -> 0 | D12: =D10-D11+MAX(0,-損益!D12) -> 0 | E12: =E10-E11+MAX(0,-損益!E12) -> 0 | F12: =F10-F11+MAX(0,-損益!F12) -> 0 | G12: =G10-G11+MAX(0,-損益!G12) -> 0
A13: 無槓桿所得稅（DCF 用） | B13: US$bn | C13: =MAX(0,損益!C12-C11)*輸入與假設!$C$383 -> 12.829973 | D13: =MAX(0,損益!D12-D11)*輸入與假設!$C$383 -> 25.05194 | E13: =MAX(0,損益!E12-E11)*輸入與假設!$C$383 -> 25.680087 | F13: =MAX(0,損益!F12-F11)*輸入與假設!$C$383 -> 26.368008 | G13: =MAX(0,損益!G12-G11)*輸入與假設!$C$383 -> 26.029002 | I13: 與損益表的所得稅不同：此處不扣利息，數字較高，這是 DCF 的正確口徑
A14: UFCF | B14: US$bn | C14: =損益!C12-C13+損益!C21-輸入與假設!C$242-C6-C9-C8 -> -23.319486 | D14: =損益!D12-D13+損益!D21-輸入與假設!D$242-D6-D9-D8 -> -41.246121 | E14: =損益!E12-E13+損益!E21-輸入與假設!E$242-E6-E9-E8 -> -25.372657 | F14: =損益!F12-F13+損益!F21-輸入與假設!F$242-F6-F9-F8 -> -19.144775 | G14: =損益!G12-G13+損益!G21-輸入與假設!G$242-G6-G9-G8 -> -110.8636 | I14: ＝EBIT−無槓桿稅＋D&A−現金 CapEx（已扣客戶預付）−營運資金−預付認列。建置期全為負是正常的
A15: 折現期數 | B15: 年 | C15: =輸入與假設!$C$454 -> 0.5 | D15: =輸入與假設!$D$454 -> 1.5 | E15: =輸入與假設!$E$454 -> 2.5 | F15: =輸入與假設!$F$454 -> 3.5 | G15: =輸入與假設!$G$454 -> 4.5 | I15: 自 2026-06-30 起算；2026 模型期（下半年）的現金流平均落在 0.5 年
A16: 折現因子 | C16: =1/(1+輸入與假設!$C$393)^C15 -> 0.94669935 | D16: =1/(1+輸入與假設!$C$393)^D15 -> 0.84846951 | E16: =1/(1+輸入與假設!$C$393)^E15 -> 0.76043202 | F16: =1/(1+輸入與假設!$C$393)^F15 -> 0.68152934 | G16: =1/(1+輸入與假設!$C$393)^G15 -> 0.61081363
A17: UFCF 現值 | B17: US$bn | C17: =C14*C16 -> -22.076542 | D17: =D14*D16 -> -34.996076 | E17: =E14*E16 -> -19.294181 | F17: =F14*F16 -> -13.047726 | G17: =G14*G16 -> -67.716999
A19: 五期 UFCF 現值合計 | C19: =SUM(C17:G17) -> -157.13152 | I19: 建置期現金流現值
A20: 終值基準 FCF（2030 UFCF，含汰換 CapEx） | C20: =G14+輸入與假設!G299*(1-各期收支!G7) -> 158.152 | I20: v0.1c：終值基準＝末期 UFCF（含穩態汰換 CapEx，已扣客戶預付覆蓋）＋加回末期成長型 CapEx（扣預付後；成長由 g 表達，預設情境為 0）；GPU 不是永續資產，終值年須持續再投資
A21: 終值（Gordon） | C21: =IF(C30=1,0,C20*(1+輸入與假設!$C$394)/(輸入與假設!$C$393-輸入與假設!$C$394)) -> 1899.1593 | I21: ＝常態化 FCF×(1+g)÷(WACC−g)
A22: 終值現值 | C22: =C21*G16 -> 1160.0324
A23: 企業價值 EV | C23: =C19+C22 -> 1002.9009
A24: 減：淨負債 | C24: =-評價_DCF與目標價!$C$91 -> 227.559 | I24: ＝評價淨負債（不含可轉債的淨負債＋債務處理可轉債到期本金＋調整項；見下方可轉債區）
A25: 股權價值 | C25: =C23+C24 -> 1230.4599
A26: DCF 每股 | C26: =IF(C30=1,0,IF(輸入與假設!$C$439=2,C32,C31)) -> 96.647821 | I26: 採用值：失效時為 0 且權重歸零；否則依「DCF 下限方式」取 0 截斷或選擇權
A27: 終值占 EV 比重 | C27: =C22/C23 -> 1.156677 | I27: ="超過 "&IF(ROUND(ABS(輸入與假設!$C$463)*100,4)=INT(ROUND(ABS(輸入與假設!$C$463)*100,4)),TEXT(ROUND(ABS(輸入與假設!$C$463)*100,4),"0"),TEXT(ROUND(ABS(輸入與假設!$C$463)*100,4),"0.0"))&"%"&" 表示結論由終值假設決定，不由現金流決定" -> 超過 85% 表示結論由終值假設決定，不由現金流決定
A28: 新股募得現金（現值） | C28: =(各期收支!C92-各期收支!C76)/(1+輸入與假設!$C$393)^輸入與假設!$C$455+(各期收支!D92-各期收支!D76)/(1+輸入與假設!$C$393)^輸入與假設!$D$455+(各期收支!E92-各期收支!E76)/(1+輸入與假設!$C$393)^輸入與假設!$E$455+(各期收支!F92-各期收支!F76)/(1+輸入與假設!$C$393)^輸入與假設!$F$455+(各期收支!G92-各期收支!G76)/(1+輸入與假設!$C$393)^輸入與假設!$G$455 -> -51.954382 | I28: 期初到位，折現期數 0／0.5／1.5／2.5／3.5 年；MAG v0.1b：扣瀑布回購現金（淨股權）
A29: 融資後股數（含瀑布新股） | C29: =評價_DCF與目標價!$C$90+各期收支!G97 -> 12.193813
A30: DCF 失效？（WACC ≤ g 或常態化 FCF ≤ 0） | C30: =IF(OR(輸入與假設!$C$393<=輸入與假設!$C$394,C20<=0),1,0) -> 0 | I30: 1＝失效：DCF 權重歸零、EV/EBITDA 100%。股權為負不算失效
A31: DCF 每股：0 截斷 | C31: =MAX(0,(C25+C28)/C29) -> 96.647821
A32: DCF 每股：選擇權（Merton） | C32: =IF((C23+C28)<=0,0,IF(評價_DCF與目標價!$C$91<=0,(C23+C28),(C23+C28)*NORMSDIST(C33)-評價_DCF與目標價!$C$91*EXP(-輸入與假設!$C$384*輸入與假設!$C$441)*NORMSDIST(C34))/C29) -> 77.98598 | I32: Black-Scholes：S＝企業價值＋新股現值、K＝淨負債
A33: d1 | C33: =IF(OR((C23+C28)<=0,評價_DCF與目標價!$C$91<=0),0,(LN((C23+C28)/評價_DCF與目標價!$C$91)+(輸入與假設!$C$384+輸入與假設!$C$440^2/2)*輸入與假設!$C$441)/(輸入與假設!$C$440*SQRT(輸入與假設!$C$441))) -> 0
A34: d2 | C34: =C33-輸入與假設!$C$440*SQRT(輸入與假設!$C$441) -> -1.0606602
A36: 倍數法（錨定年度，預設 2029；折回 2027-06-30）
A37: 錨定年度 | C37: =CHOOSE(輸入與假設!$C$431,"2027","2028","2029","2030") -> 2029 | I37: 輸入與假設 F 區可改
A38: 錨定年度 EBITDA | C38: =INDEX(損益!$D$22:$G$22,1,輸入與假設!$C$431) -> 295.14977
A39: 錨定年度企業價值（倍數 × EBITDA） | C39: =C45*輸入與假設!$C$399+C44*輸入與假設!$C$430 -> 2791.3024 | I39: 分部加總：AI 雲端 EBITDA × EV/EBITDA 倍數＋非 AI 事業 EBITDA × 非 AI 事業倍數（下方兩列）
A40: 錨定年度末淨負債（總債務 − 現金） | C40: =INDEX(各期收支!$D$102:$G$102,1,輸入與假設!$C$431)-INDEX(各期收支!$D$56:$G$56,1,輸入與假設!$C$431)+評價_DCF與目標價!$C$92 -> -133.28818 | I40: 含瀑布新債；加可轉債分類調整與淨負債調整項（見下方可轉債區）
A41: 錨定年度末股數（含瀑布新股） | C41: =INDEX(損益!$D$24:$G$24,1,輸入與假設!$C$431) -> 12.568443 | I41: 損益股數：SBC 逐年稀釋＋瀑布新股
A42: 折回 2027-06-30 的折現因子 | C42: =1/(1+輸入與假設!$C$393)^(輸入與假設!$C$431-輸入與假設!$C$451) -> 0.76043202 | I42: 以 WACC 折現 [Assumed]
A43: EV/EBITDA 每股（融資後） | C43: =MAX(0,(C39-C40)/C41)*C42 -> 176.94733 | I43: 以 0 為下限
A44: 錨定年度非 AI 事業 EBITDA | C44: =INDEX(輸入與假設!$D$241:$G$241,1,輸入與假設!$C$431) -> 239.22461 | I44: × 非 AI 事業 EV/EBITDA 倍數（同業 NTM 中位數）
A45: 錨定年度 AI 雲端 EBITDA（算力＋服務＋其他） | C45: =C38-C44 -> 55.925159 | I45: ＝錨定年度 EBITDA − 非 AI 事業；× EV/EBITDA 倍數
A47: 加權目標價
A48: DCF 每股（推到目標價時點） | C48: =C26*(1+輸入與假設!$C$393)^輸入與假設!$C$447 -> 107.83703 | I48: ＝DCF 每股 ×（1＋WACC）^（評價日至目標價時點的年數）
A49: DCF 每股 × 有效權重 | C49: =C48*IF(C30=1,0,輸入與假設!$C$432) -> 48.526662
A50: EV/EBITDA（融資後）× 有效權重 | C50: =C43*IF(C30=1,1,1-輸入與假設!$C$432) -> 97.321029
A51: 加權目標價 | C51: =SUM(C49:C50) -> 145.84769 | I51: 期前融資瀑布：缺口先由額度與資產層新債支應，殘差以股權募足；估值不再扣缺口本金
A52: 現價 | C52: =輸入與假設!$C$366 -> 350.5
A53: 潛在空間 | C53: =C51/C52-1 -> -0.58388676
A55: 讀法 2｜自用 AI 價值中性（自用 MW 以 k＝1 計影子收入進評價；讀法 1＝影子收入不進評價，主值不變）
A56: 讀法 2｜自用 AI 影子 EBITDA（k＝1） | B56: US$bn | C56: =運營_產能與收入!C26*(1/輸入與假設!$C$58-(1-輸入與假設!C$250))*(1/輸入與假設!$C$263-1) -> 20.803814 | D56: =運營_產能與收入!D26*(1/輸入與假設!$C$58-(1-輸入與假設!D$250))*(1/輸入與假設!$C$263-1) -> 62.720807 | E56: =運營_產能與收入!E26*(1/輸入與假設!$C$58-(1-輸入與假設!E$250))*(1/輸入與假設!$C$263-1) -> 91.60367 | F56: =運營_產能與收入!F26*(1/輸入與假設!$C$58-(1-輸入與假設!F$250))*(1/輸入與假設!$C$263-1) -> 120.71503 | G56: =運營_產能與收入!G26*(1/輸入與假設!$C$58-(1-輸入與假設!G$250))*(1/輸入與假設!$C$263-1) -> 149.94113 | I56: ＝對外 AI 營收 ÷ k ×(1 ÷ 對外比例 − 1) − 同口徑營運成本：自用 AI 剛好回收 Tokenomics 持有成本（不創造也不毀損價值）
A57: 讀法 2｜EBIT | B57: US$bn | C57: =損益!C12+C56 -> 97.172698 | D57: =損益!D12+D56 -> 211.8395 | E57: =損益!E12+E56 -> 244.46133 | F57: =損益!F12+F56 -> 277.66746 | G57: =損益!G12+G56 -> 304.87566
A58: 讀法 2｜無槓桿 NOL 期初 | B58: US$bn | C58: =輸入與假設!$C$396 -> 0 | D58: =C60 -> 0 | E58: =D60 -> 0 | F58: =E60 -> 0 | G58: =F60 -> 0
A59: 讀法 2｜本期動用（無槓桿） | B59: US$bn | C59: =MIN(C58,MAX(0,C57)*輸入與假設!$C$397) -> 0 | D59: =MIN(D58,MAX(0,D57)*輸入與假設!$C$397) -> 0 | E59: =MIN(E58,MAX(0,E57)*輸入與假設!$C$397) -> 0 | F59: =MIN(F58,MAX(0,F57)*輸入與假設!$C$397) -> 0 | G59: =MIN(G58,MAX(0,G57)*輸入與假設!$C$397) -> 0
A60: 讀法 2｜無槓桿 NOL 期末 | B60: US$bn | C60: =C58-C59+MAX(0,-C57) -> 0 | D60: =D58-D59+MAX(0,-D57) -> 0 | E60: =E58-E59+MAX(0,-E57) -> 0 | F60: =F58-F59+MAX(0,-F57) -> 0 | G60: =G58-G59+MAX(0,-G57) -> 0
A61: 讀法 2｜無槓桿所得稅 | B61: US$bn | C61: =MAX(0,C57-C59)*輸入與假設!$C$383 -> 16.325013 | D61: =MAX(0,D57-D59)*輸入與假設!$C$383 -> 35.589036 | E61: =MAX(0,E57-E59)*輸入與假設!$C$383 -> 41.069503 | F61: =MAX(0,F57-F59)*輸入與假設!$C$383 -> 46.648134 | G61: =MAX(0,G57-G59)*輸入與假設!$C$383 -> 51.219111
A62: 讀法 2｜UFCF | B62: US$bn | C62: =C14+C56-(C61-C13) -> -6.0107128 | D62: =D14+D56-(D61-D13) -> 10.937591 | E62: =E14+E56-(E61-E13) -> 50.841597 | F62: =F14+F56-(F61-F13) -> 81.290132 | G62: =G14+G56-(G61-G13) -> 13.887415 | I62: ＝讀法 1 UFCF＋影子 EBITDA − 稅差
A63: 讀法 2｜UFCF 現值 | B63: US$bn | C63: =C62*C16 -> -5.6903379 | D63: =D62*D16 -> 9.2802122 | E63: =E62*E16 -> 38.661578 | F63: =F62*F16 -> 55.40161 | G63: =G62*G16 -> 8.4826226
A64: 讀法 2｜五期 UFCF 現值合計 | C64: =SUM(C63:G63) -> 106.13569
A65: 讀法 2｜終值基準 FCF | C65: =C20-G14+G62 -> 282.90302 | I65: ＝讀法 1 終值基準＋末期影子現金流差
A66: 讀法 2｜DCF 失效？ | C66: =IF(OR(輸入與假設!$C$393<=輸入與假設!$C$394,C65<=0),1,0) -> 0
A67: 讀法 2｜終值現值 | C67: =IF(C66=1,0,C65*(1+輸入與假設!$C$394)/(輸入與假設!$C$393-輸入與假設!$C$394))*G16 -> 2075.0712
A68: 讀法 2｜企業價值 EV | C68: =C64+C67 -> 2181.2069
A69: 讀法 2｜d1 | C69: =IF(OR((C68+C28)<=0,評價_DCF與目標價!$C$91<=0),0,(LN((C68+C28)/評價_DCF與目標價!$C$91)+(輸入與假設!$C$384+輸入與假設!$C$440^2/2)*輸入與假設!$C$441)/(輸入與假設!$C$440*SQRT(輸入與假設!$C$441))) -> 0
A70: 讀法 2｜DCF 每股（評價日） | C70: =IF(C66=1,0,IF(輸入與假設!$C$439=2,IF((C68+C28)<=0,0,IF(評價_DCF與目標價!$C$91<=0,(C68+C28),(C68+C28)*NORMSDIST(C69)-評價_DCF與目標價!$C$91*EXP(-輸入與假設!$C$384*輸入與假設!$C$441)*NORMSDIST(C69-輸入與假設!$C$440*SQRT(輸入與假設!$C$441)))/C29),MAX(0,(C68-評價_DCF與目標價!$C$91+C28)/C29))) -> 193.27929 | I70: 與讀法 1 同股數、同淨負債
A71: 讀法 2｜DCF 每股（推到目標價時點） | C71: =C70*(1+輸入與假設!$C$393)^輸入與假設!$C$447 -> 215.65581
A72: 讀法 2｜EV/EBITDA 每股（融資後） | C72: =MAX(0,(C39+INDEX($D$56:$G$56,1,輸入與假設!$C$431)*輸入與假設!$C$399-C40)/C41)*C42 -> 220.76926 | I72: 錨定年 AI 雲端 EBITDA 加影子 EBITDA × AI 雲端倍數
A73: 讀法 2｜加權目標價 | C73: =C71*IF(C66=1,0,輸入與假設!$C$432)+C72*IF(C66=1,1,1-輸入與假設!$C$432) -> 218.46821 | I73: 只有對外 AI 的超額報酬影響目標價（對照表 r1 C16）
A74: 讀法 2 − 讀法 1（目標價差額） | C74: =C73-C51 -> 72.620515 | I74: 主值取哪一個是 Andy 的判斷（待決）
A76: 可轉債稀釋（若轉換法；第一輪判斷價＝現價，第二輪＝MIN(現價, 第一輪目標價)）
A77: 第一輪：轉股股數 | C77: =SUMPRODUCT(資產負債_既有債務!$D$27:$D$27*資產負債_既有債務!$G$27:$G$27) -> 0.054600635 | I77: 有效轉換價 < 現價的可轉債：原始本金 ÷ 轉換價
A78: 第一輪：評價股數 | C78: =輸入與假設!$C$367+C77 -> 12.363601
A79: 第一輪：評價淨負債 | C79: =輸入與假設!$C$368+SUMPRODUCT(資產負債_既有債務!$C$27:$C$27*(1-資產負債_既有債務!$G$27:$G$27))+輸入與假設!$C$382 -> -227.559 | I79: ＝不含可轉債的淨負債＋債務處理可轉債到期本金＋調整項
A80: 第一輪：DCF 融資後股數 | C80: =C78+各期收支!G97 -> 12.193813
A81: 第一輪：d1 | C81: =IF(OR((C23+C28)<=0,C79<=0),0,(LN((C23+C28)/C79)+(輸入與假設!$C$384+輸入與假設!$C$440^2/2)*輸入與假設!$C$441)/(輸入與假設!$C$440*SQRT(輸入與假設!$C$441))) -> 0
A82: 第一輪：DCF 每股（評價日） | C82: =IF(C30=1,0,IF(輸入與假設!$C$439=2,IF((C23+C28)<=0,0,IF(C79<=0,(C23+C28),(C23+C28)*NORMSDIST(C81)-C79*EXP(-輸入與假設!$C$384*輸入與假設!$C$441)*NORMSDIST(C81-輸入與假設!$C$440*SQRT(輸入與假設!$C$441)))/C80),MAX(0,(C23-C79+C28)/C80))) -> 96.647821 | I82: 與上方 DCF 同算法，只換股數與淨負債
A83: 第一輪：錨定年末淨負債 | C83: =INDEX(各期收支!$D$102:$G$102,1,輸入與假設!$C$431)-INDEX(各期收支!$D$56:$G$56,1,輸入與假設!$C$431)+SUMPRODUCT(資產負債_既有債務!$C$27:$C$27*(資產負債_既有債務!$F$27:$F$27-資產負債_既有債務!$G$27:$G$27))+輸入與假設!$C$382 -> -133.28818 | I83: ＝融資表錨定年末淨負債＋（融資分類為轉股、評價分類為債務的到期本金）＋調整項
A84: 第一輪：錨定年末股數 | C84: =C78*(1+輸入與假設!$C$436)^輸入與假設!$C$431+INDEX(各期收支!$D$97:$G$97,1,輸入與假設!$C$431) -> 12.568443
A85: 第一輪：EV/EBITDA 每股 | C85: =MAX(0,(C39-C83)/C84)*C42 -> 176.94733
A86: 第一輪：加權目標價 | C86: =C82*(1+輸入與假設!$C$393)^輸入與假設!$C$447*IF(C30=1,0,輸入與假設!$C$432)+C85*IF(C30=1,1,1-輸入與假設!$C$432) -> 145.84769
A87: 第二輪判斷價 | C87: =MIN(輸入與假設!$C$366,C86) -> 145.84769 | I87: ＝MIN(現價, 第一輪加權目標價)：以較保守者判斷是否價內
A88: 第二輪：轉股股數 | C88: =SUMPRODUCT(資產負債_既有債務!$D$27:$D$27*資產負債_既有債務!$H$27:$H$27) -> 0.054600635 | I88: 有效轉換價 < 第二輪判斷價的可轉債
A89: 第二輪：債務處理到期本金 | C89: =SUMPRODUCT(資產負債_既有債務!$C$27:$C$27*(1-資產負債_既有債務!$H$27:$H$27)) -> 0
A90: 評價股數（含可轉債轉股） | C90: =輸入與假設!$C$367+C88 -> 12.363601 | I90: DCF、損益股數與錨定年末股數的起點
A91: 評價淨負債（含可轉債與調整項） | C91: =輸入與假設!$C$368+C89+輸入與假設!$C$382 -> -227.559 | I91: DCF 減項與 Merton 履約價
A92: 錨定年末淨負債調整（可轉債分類差＋調整項） | C92: =SUMPRODUCT(資產負債_既有債務!$C$27:$C$27*(資產負債_既有債務!$F$27:$F$27-資產負債_既有債務!$H$27:$H$27))+輸入與假設!$C$382 -> -173.233 | I92: 融資現金流依『融資分類』（判斷價＝股權發行價）；評價依第二輪分類，差額在錨定年末淨負債補回
A93: DCF 權重說明 | C93: =IF(C30=1,"DCF 失效，已以 EV/EBITDA 100% 計。",IF(AND(輸入與假設!$C$439<>2,C108<0),"DCF 為 $0 仍計 "&TEXT(輸入與假設!$C$432,"0%")&" 權重的原因：DCF 沒有失效，而是算出的股權價值為負（每股約 −$"&TEXT(ABS(C108),"0.0")&"），代表自由現金流折現後的企業價值不足以償還淨負債。EV/EBITDA 沒有扣除 GPU 汰換與擴張支出，保留 DCF 權重，是為了讓目標價反映「EBITDA 付不起資本成本」。若不計 DCF，目標價為 $"&TEXT(C43,"0.0")&"（"&CHOOSE(D107+2,"賣出","中立","買進")&"）；"&TEXT(輸入與假設!$C$432,"0%")&"／"&TEXT(1-輸入與假設!$C$432,"0%")&" 為判斷值。","")) | I93: 只在 DCF 被 0 截斷時顯示；DCF 失效時改為一句；DCF 為正時空白（與 HTML 同一字串）
A95: 目標價區間（情境區間、方法區間；評等仍依點位）
A96: 目標價區間｜點位（目前輸入的加權目標價） | C96: =C51 -> 145.84769 | I96: ="評等規則不變：空間 ≥"&IF(ROUND(ABS(輸入與假設!$C$457)*100,4)=INT(ROUND(ABS(輸入與假設!$C$457)*100,4)),TEXT(ROUND(ABS(輸入與假設!$C$457)*100,4),"0"),TEXT(ROUND(ABS(輸入與假設!$C$457)*100,4),"0.0"))&"%"&" 且終值占比 <"&IF(ROUND(ABS(輸入與假設!$C$458)*100,4)=INT(ROUND(ABS(輸入與假設!$C$458)*100,4)),TEXT(ROUND(ABS(輸入與假設!$C$458)*100,4),"0"),TEXT(ROUND(ABS(輸入與假設!$C$458)*100,4),"0.0"))&"%"&"、股權募資 ≤"&IF(輸入與假設!$C$460=INT(輸入與假設!$C$460),TEXT(輸入與假設!$C$460,"0"),TEXT(輸入與假設!$C$460,"0.0"))&" 倍現市值 → 買進；空間 ≤−"&IF(ROUND(ABS(輸入與假設!$C$459)*100,4)=INT(ROUND(ABS(輸入與假設!$C$459)*100,4)),TEXT(ROUND(ABS(輸入與假設!$C$459)*100,4),"0"),TEXT(ROUND(ABS(輸入與假設!$C$459)*100,4),"0.0"))&"%"&"，或股權募資 >"&IF(輸入與假設!$C$460=INT(輸入與假設!$C$460),TEXT(輸入與假設!$C$460,"0"),TEXT(輸入與假設!$C$460,"0.0"))&" 倍且空間 ≤−"&IF(ROUND(ABS(輸入與假設!$C$461)*100,4)=INT(ROUND(ABS(輸入與假設!$C$461)*100,4)),TEXT(ROUND(ABS(輸入與假設!$C$461)*100,4),"0"),TEXT(ROUND(ABS(輸入與假設!$C$461)*100,4),"0.0"))&"%"&" → 賣出；其餘中立" -> 評等規則不變：空間 ≥25% 且終值占比 <90%、股權募資 ≤1.5 倍現市值 → 買進；空間 ≤−15%，或股權募資 >1.5 倍且空間 ≤−8% → 賣出；其餘中立
A97: 目標價區間｜終值占 EV（評等用） | C97: =C22/MAX(ABS(C23),1)*IF(C23=0,1,SIGN(C23)) -> 1.156677
A98: 目標價區間｜股權募資 ÷ 現市值（評等用） | C98: =SUM(各期收支!C92:G92)/(輸入與假設!$C$366*輸入與假設!$C$367) -> 0
A99: 目標價區間｜點位評等代碼（1＝買進、0＝中立、−1＝賣出） | C99: =IF(AND((C51/MAX(輸入與假設!$C$366,0.01)-1)>=輸入與假設!$C$457,$C$97<輸入與假設!$C$458,$C$98<=輸入與假設!$C$460),1,IF(OR((C51/MAX(輸入與假設!$C$366,0.01)-1)<=輸入與假設!$C$459,AND($C$98>輸入與假設!$C$460,(C51/MAX(輸入與假設!$C$366,0.01)-1)<=輸入與假設!$C$461)),-1,0)) -> -1 | D99: =CHOOSE(C99+2,"賣出","中立","買進") -> 賣出
A100: 目標價區間｜賣出門檻價（現價 × (1 − 15%)） | C100: =輸入與假設!$C$366*(1+輸入與假設!$C$459) -> 297.925
A101: 目標價區間｜保守 已交付＋已公開在建（加權目標價／評等代碼／距賣出門檻） | C101: =輸入與假設!D491 -> 175.76831 | D101: =輸入與假設!E491 -> -1 | E101: =C101-$C$100 -> -122.15669 | I101: 引用『輸入與假設』底部模擬運算表（情境選擇 1／2／3），保留其餘手動輸入
A102: 目標價區間｜基準 依資本支出指引（加權目標價／評等代碼／距賣出門檻） | C102: =輸入與假設!D492 -> 145.84769 | D102: =輸入與假設!E492 -> -1 | E102: =C102-$C$100 -> -152.07731
A103: 目標價區間｜積極 依 2027 擴張幅度（加權目標價／評等代碼／距賣出門檻） | C103: =輸入與假設!D493 -> 121.98879 | D103: =輸入與假設!E493 -> -1 | E103: =C103-$C$100 -> -175.93621
A104: 目標價區間｜情境區間（下緣／上緣） | C104: =MIN(C101,C103) -> 121.98879 | D104: =MAX(C101,C103) -> 175.76831
A105: 目標價區間｜方法區間倍數（下端／上端） | C105: =MIN(輸入與假設!$C$434,輸入與假設!$C$435) -> 5 | D105: =MAX(輸入與假設!$C$434,輸入與假設!$C$435) -> 6
A106: 目標價區間｜方法區間（下緣／上緣） | C106: =MIN(C48*IF(C30=1,0,輸入與假設!$C$432)+MAX(0,(C45*C105+C44*輸入與假設!$C$430-C40)/C41)*C42*IF(C30=1,1,1-輸入與假設!$C$432),C48*IF(C30=1,0,輸入與假設!$C$432)+MAX(0,(C45*D105+C44*輸入與假設!$C$430-C40)/C41)*C42*IF(C30=1,1,1-輸入與假設!$C$432)) -> 143.98668 | D106: =MAX(C48*IF(C30=1,0,輸入與假設!$C$432)+MAX(0,(C45*C105+C44*輸入與假設!$C$430-C40)/C41)*C42*IF(C30=1,1,1-輸入與假設!$C$432),C48*IF(C30=1,0,輸入與假設!$C$432)+MAX(0,(C45*D105+C44*輸入與假設!$C$430-C40)/C41)*C42*IF(C30=1,1,1-輸入與假設!$C$432)) -> 145.84769 | I106: ＝DCF 採用值 × 有效權重 ＋ EV/EBITDA 腿（倍數換成兩端）× 有效權重
A107: 目標價區間｜100% EV/EBITDA 目標價（價位／評等代碼） | C107: =C43 -> 176.94733 | D107: =IF(AND((C43/MAX(輸入與假設!$C$366,0.01)-1)>=輸入與假設!$C$457,$C$97<輸入與假設!$C$458,$C$98<=輸入與假設!$C$460),1,IF(OR((C43/MAX(輸入與假設!$C$366,0.01)-1)<=輸入與假設!$C$459,AND($C$98>輸入與假設!$C$460,(C43/MAX(輸入與假設!$C$366,0.01)-1)<=輸入與假設!$C$461)),-1,0)) -> -1 | E107: =CHOOSE(D107+2,"賣出","中立","買進") -> 賣出
...

Sheet 評價_反向DCF
A1: 反向 DCF — 現價隱含什麼樣的收入與成本
A2: 不是問「值多少」，而是問「要值現價，營運要長什麼樣」。Excel 以『目標搜尋』反解；下方另附 HTML 即時計算結果的快照（v4.0 預設輸入）
A4: 即時：目前 DCF 與現價的差距
A5: 現價 | B5: =輸入與假設!$C$366 -> 350.5
A6: 目前 DCF 每股（依下限方式） | B6: =評價_DCF與目標價!C26 -> 96.647821
A7: 差距（DCF − 現價）＝目標搜尋的『設定儲存格』 | B7: =B6-B5 -> -253.85218
A8: 目前每 MW 年收入倍數／建置成本倍數 | B8: =輸入與假設!$C$32 -> 1 | C8: =輸入與假設!$C$269 -> 1
A10: 操作：用『目標搜尋』反解（資料 → 模擬分析 → 目標搜尋）
A11: ① 設定儲存格：本頁 B7；目標值：0
A12: ② 變數儲存格（擇一）：輸入與假設 B 區『每 MW 年收入倍數』→ 市價隱含單價；或 D 區『每 MW 建置成本倍數』→ 市價隱含建置成本；或 C 區『穩態 EBITDA 率』
A13: ③ 解完請記下結果，再把倍數改回 100%（或按 Ctrl+Z）。DCF 以 0 截斷時，負值區域斜率為 0，請從 100% 以上開始搜尋
A14: ④ 組合分析：先把 D 區建置成本倍數與 C 區穩態 EBITDA 率設為想測的值，再對『每 MW 年收入倍數』做目標搜尋，即得下方矩陣中的一格
A16: 快照：單一槓桿（HTML v4.0 預設輸入，DCF 0 截斷）
A17: 單一槓桿（其他不變） | B17: 目前 | C17: 市價隱含 | D17: 變動 | G17: 對照
A18: 2030 每 MW 年收入（US$m） | B18: 13.1035 | C18: 無解 | D18: 無解 | G18: Alphabet 對照：Anthropic–Google Cloud 合約隱含 10.0–15.3 US$m/MW-年
A19: 每 MW 建置成本（US$m） | B19: 48.3559 | C19: 無解 | D19: 無解 | G19: Tokenomics 每 MW 全成本（IT＋自建 85% 機房）2026 約 $43.0m → 2028 起 $48.4m/MW-IT（v5.31；新增世代由 Ironwood／GB300 轉向下一代／VR200）
A20: 穩態 EBITDA 率（2030） | B20: 0.765 | C20: 無解 | D20: 無解 | G20: AI 雲端（算力）EBITDA 率；非 AI 事業 EBITDA 率固定不動。可觀察 neocloud 區間 IREN 約 35%、CRWV 約 59%（變動為百分點）
A21: （對照）加權目標價＝現價所需每 MW 年收入 | B21: 13.1035 | C21: 無解 | D21: 無解 | G21: 含 EV/EBITDA 腿（2029 錨定）；非純反向 DCF
A23: 快照：收入與成本的綜合影響——要值現價，2030 每 MW 年收入需要多少（US$m）
A24: 建置成本 ＼ 穩態 EBITDA 率 | B24: 0.35 | C24: 0.47 | D24: 0.59 | E24: 0.7 | I24: 矩陣保留 AI 雲端 EBITDA 率維度：非 AI 事業（EBITDA 率與同業倍數）不隨此表變動，表內只測算力業務的單位經濟
A25: $33.8m（-30%） | B25: — | C25: — | D25: — | E25: —
A26: $38.7m（-20%） | B26: — | C26: — | D26: — | E26: —
A27: $43.5m（-10%） | B27: — | C27: — | D27: — | E27: —
A28: $48.4m（目前） | B28: — | C28: — | D28: — | E28: —
A29: $53.2m（+10%） | B29: — | C29: — | D29: — | E29: —
A30: 快照為靜態數值（HTML 以同一引擎即時計算）；改變輸入後請以目標搜尋重算，或參考 HTML『評價 → 反向 DCF』

Sheet 評價_可比公司
A1: 可比公司 — 以 EV/Sales 為主（市值：2026-09-21 收盤）
A2: EV＝市值＋（有息負債−非受限現金）；含租賃＝EV＋營業租賃負債。EV/EBITDA 僅供參考（GAAP EBITDA 為負者顯示 n/m）。此表不進入目標價。與 HTML Comps 分頁同一組數字
A4: 公司 | B4: 市值 | C4: 淨負債 | D4: EV | E4: TTM 營收 | F4: EV/Sales（TTM） | G4: 含租賃 EV/Sales | H4: TTM EBITDA | I4: EV/EBITDA | J4: 資料期 | K4: 備註
A5: CRWV CoreWeave | B5: 49.11 | C5: 46.03 | D5: =B5+C5 -> 95.14 | E5: 7.59 | F5: =D5/E5 -> 12.534914 | G5: =(D5+16.54)/E5 -> 14.714097 | H5: =-0.231+3.991 -> 3.76 | I5: =IF(H5>0,D5/H5,"n/m") -> 25.303191 | J5: TTM 至 Q2（6/30，10-Q）；市值與 EV 2026-10-07 | K5: 營業租賃負債 16.54；GAAP 營業損益 -0.231＋D&A 3.991。CRWV 市值與 EV 2026-10-07；TTM 至 Q2；租賃負債 16.54
A6: NBIS Nebius | B6: 68.49 | C6: 2.15 | D6: =B6+C6 -> 70.64 | E6: 1.36 | F6: =D6/E6 -> 51.941176 | G6: =(D6+1.6253)/E6 -> 53.13625 | H6: =-0.612+0.418 -> -0.194 | I6: =IF(H6>0,D6/H6,"n/m") -> n/m | J6: 營收 TTM 至 Q2；營業損益與 D&A 為 FY2025（20-F）；市值與 EV 2026-10-06 | K6: 營業租賃負債 1.6253；GAAP 營業損益 -0.612＋D&A 0.418。NBIS 市值與 EV 2026-10-06；EBITDA 用 FY2025
A7: IREN | B7: 18.61 | C7: 1.7 | D7: =B7+C7 -> 20.31 | E7: 0.707 | F7: =D7/E7 -> 28.727016 | G7: =(D7+0.003)/E7 -> 28.731259 | H7: =-1.047+0.418 -> -0.629 | I7: =IF(H7>0,D7/H7,"n/m") -> n/m | J7: FY26 10-K（6/30）；未更新，日期 2026-09-21 | K7: 營業租賃負債 0.003；GAAP 營業損益 -1.047＋D&A 0.418。自有電廠、營業租賃負債僅 0.003bn；FY26 合約 ARR 4.0bn
A8: APLD Applied Digital | B8: 8.22 | C8: 3.37 | D8: =B8+C8 -> 11.59 | E8: 0.6113 | F8: =D8/E8 -> 18.959594 | G8: =(D8+0.066)/E8 -> 19.067561 | H8: =-0.236+0.067 -> -0.169 | I8: =IF(H8>0,D8/H8,"n/m") -> n/m | J8: FY26 10-K（5/31）；未更新，日期 2026-09-21 | K8: 營業租賃負債 0.066；GAAP 營業損益 -0.236＋D&A 0.067。租約多未起租，營收尚未反映約 36bn 合約
A9: CORZ Core Scientific | B9: 5.9 | C9: 2.53 | D9: =B9+C9 -> 8.43 | E9: 0.4403 | F9: =D9/E9 -> 19.146037 | G9: =(D9+0.109)/E9 -> 19.393595 | H9: =-0.561+0.063 -> -0.498 | I9: =IF(H9>0,D9/H9,"n/m") -> n/m | J9: TTM 至 Q2（6/30）；未更新，日期 2026-09-21 | K9: 營業租賃負債 0.109；GAAP 營業損益 -0.561＋D&A 0.063。託管轉型期
A10: 同業中位數 | F10: =MEDIAN(F5:F9) -> 19.146037 | G10: =MEDIAN(G5:G9) -> 19.393595
A11: GOOGL（TTM 至 Q2 2026） | B11: 4286.615 | C11: =輸入與假設!$C$368+SUMPRODUCT(資產負債_既有債務!$C$27:$C$27*(1-資產負債_既有債務!$H$23:$H$23))+輸入與假設!$C$382 -> -227.559 | D11: =B11+C11 -> 4059.056 | E11: 445.866 | F11: =D11/E11 -> 9.1037576 | G11: =(D11+18.037)/E11 -> 9.1442115 | H11: =147.628+25.237 -> 172.865 | I11: =IF(H11>0,D11/H11,"n/m") -> 23.481075 | J11: TTM 至 Q2 2026 | K11: EV 用 2026-09-21 市值（基本股）與評價日淨負債（可轉債全數以到期本金計入）；含租賃再加營業租賃負債 18.037
A12: GOOGL 模型 2027E | B12: =輸入與假設!$C$366*評價_DCF與目標價!$C$90 -> 4333.442 | C12: =評價_DCF與目標價!$C$91 -> -227.559 | D12: =B12+C12 -> 4105.883 | E12: =損益!D9 -> 599.07596 | F12: =D12/E12 -> 6.8536936 | G12: =(D12+18.037)/E12 -> 6.8838016 | H12: =損益!D22 -> 220.64084 | I12: =D12/H12 -> 18.608898 | K12: 市值用評價股數（含價內可轉債轉股）、淨負債用評價淨負債；分母為模型 2027 營收
A14: 讀法：GOOGL 為整體公司（搜尋＋YouTube＋Cloud），倍數不可直接與純 AI 基礎設施同業比較；
A15: CRWV 以租約取得機房，加入營業租賃負債後倍數上升；GOOGL 以自建為主（另有未起租承諾 85.2B 尚未入表）。
A16: 前瞻：見下方 GOOGL 模型列。此表為市場比較用，不進入目標價。

Sheet AI增量報酬
A1: AI 增量報酬：對外 AI ROIC ＝(對外 AI 雲端 EBITDA − AI 折舊 × 對外比例)×(1 − 稅率) ÷ (平均 AI 投入資本 × 對外比例)，對 WACC
A2: 年化＝模型期 ÷ 期間長度（2026 只含 2H）；投入資本（全 AI）＝AI 期初毛額 × 淨額比＋累計 AI 成長型與汰換 − 累計 AI 折舊；對外口徑＝投入資本與折舊 × 對外比例（主值）；全 AI 口徑（含影子收入）只作對照；打平 k＝使錨定期對外 AI ROIC＝WACC 的 k（解出的門檻，不是輸入）
A4: 項目 | B4: 單位 | C4: 2026 | D4: 2027 | E4: 2028 | F4: 2029 | G4: 2030 | I4: 公式／來源說明
A5: 對外 AI 雲端營收（年化） | B5: US$bn | C5: =運營_產能與收入!C26/輸入與假設!C$34 -> 25.445504 | D5: =運營_產能與收入!D26/輸入與假設!D$34 -> 38.101402 | E5: =運營_產能與收入!E26/輸入與假設!E$34 -> 55.370613 | F5: =運營_產能與收入!F26/輸入與假設!F$34 -> 72.763033 | G5: =運營_產能與收入!G26/輸入與假設!G$34 -> 90.21732
A6: AI 雲端 EBITDA 率 | B6: % | C6: =輸入與假設!C$250 -> 0.83423438 | D6: =輸入與假設!D$250 -> 0.83894381 | E6: =輸入與假設!E$250 -> 0.84246605 | F6: =輸入與假設!F$250 -> 0.84445571 | G6: =輸入與假設!G$250 -> 0.84573431 | I6: Tokenomics 營運成本推得（輸入與假設 C 區）
A7: AI 雲端 EBITDA（年化） | B7: US$bn | C7: =C5*C6 -> 21.227514 | D7: =D5*D6 -> 31.964935 | E7: =E5*E6 -> 46.647862 | F7: =F5*F6 -> 61.445159 | G7: =G5*G6 -> 76.299883
A8: AI 營運成本（年化） | B8: US$bn | C8: =C5-C7 -> 4.2179898 | D8: =D5-D7 -> 6.1364668 | E8: =E5-E7 -> 8.7227511 | F8: =F5-F7 -> 11.317875 | G8: =G5-G7 -> 13.917437
A9: AI 折舊（年化） | B9: US$bn | C9: =輸入與假設!C$319/輸入與假設!C$34 -> 39.191179 | D9: =輸入與假設!D$319/輸入與假設!D$34 -> 59.279054 | E9: =輸入與假設!E$319/輸入與假設!E$34 -> 86.613361 | F9: =輸入與假設!F$319/輸入與假設!F$34 -> 114.87344 | G9: =輸入與假設!G$319/輸入與假設!G$34 -> 143.13352 | I9: D&A 分池（輸入與假設 D 區）
A10: 有效在役對外 MW（＝營收 ÷ 每 MW 年收入） | B10: MW | C10: =C5/MAX(0.000000000001,輸入與假設!C120*輸入與假設!$C$58/1000) -> 2212.5 | D10: =D5/MAX(0.000000000001,輸入與假設!D120*輸入與假設!$C$58/1000) -> 3147 | E10: =E5/MAX(0.000000000001,輸入與假設!E120*輸入與假設!$C$58/1000) -> 4393 | F10: =F5/MAX(0.000000000001,輸入與假設!F120*輸入與假設!$C$58/1000) -> 5639 | G10: =G5/MAX(0.000000000001,輸入與假設!G120*輸入與假設!$C$58/1000) -> 6885
A11: 租用對外 MW（平均） | B11: MW | C11: =(輸入與假設!$C$292+輸入與假設!C$293)/2 -> 0 | D11: =(輸入與假設!C$293+輸入與假設!D$293)/2 -> 0 | E11: =(輸入與假設!D$293+輸入與假設!E$293)/2 -> 0 | F11: =(輸入與假設!E$293+輸入與假設!F$293)/2 -> 0 | G11: =(輸入與假設!F$293+輸入與假設!G$293)/2 -> 0 | I11: capexModel.rentedExt（C20）：收入照算、投入資本與折舊不計
A12: 自有對外占自有 AI MW 比例 | B12: % | C12: =MAX(0,C10-C11)/MAX(0.000000001,C10/輸入與假設!$C$263-C11) -> 0.3 | D12: =MAX(0,D10-D11)/MAX(0.000000001,D10/輸入與假設!$C$263-D11) -> 0.3 | E12: =MAX(0,E10-E11)/MAX(0.000000001,E10/輸入與假設!$C$263-E11) -> 0.3 | F12: =MAX(0,F10-F11)/MAX(0.000000001,F10/輸入與假設!$C$263-F11) -> 0.3 | G12: =MAX(0,G10-G11)/MAX(0.000000001,G10/輸入與假設!$C$263-G11) -> 0.3 | I12: 投入資本與折舊按此比例分攤（無租用時＝對外比例；C11、C20）
A13: 每 MW 機房年租金（Tokenomics 機房成本 × 資本回收係數） | B13: US$bn/MW | C13: =(輸入與假設!C69*TK_CapexFacility_H100+輸入與假設!C76*TK_CapexFacility_H100+輸入與假設!C83*TK_CapexFacility_GB200+輸入與假設!C90*TK_CapexFacility_GB200+輸入與假設!C97*TK_CapexFacility_GB300+輸入與假設!C104*TK_CapexFacility_GB300+輸入與假設!C111*TK_CapexFacility_VR200+輸入與假設!C118*TK_CapexFacility_VR200)/MAX(0.000000001,輸入與假設!C119)/1000*0.1/(1-(1+0.1)^(-輸入與假設!$C$310)) -> 0.0014889304 | D13: =(輸入與假設!D69*TK_CapexFacility_H100+輸入與假設!D76*TK_CapexFacility_H100+輸入與假設!D83*TK_CapexFacility_GB200+輸入與假設!D90*TK_CapexFacility_GB200+輸入與假設!D97*TK_CapexFacility_GB300+輸入與假設!D104*TK_CapexFacility_GB300+輸入與假設!D111*TK_CapexFacility_VR200+輸入與假設!D118*TK_CapexFacility_VR200)/MAX(0.000000001,輸入與假設!D119)/1000*0.1/(1-(1+0.1)^(-輸入與假設!$C$310)) -> 0.0014889304 | E13: =(輸入與假設!E69*TK_CapexFacility_H100+輸入與假設!E76*TK_CapexFacility_H100+輸入與假設!E83*TK_CapexFacility_GB200+輸入與假設!E90*TK_CapexFacility_GB200+輸入與假設!E97*TK_CapexFacility_GB300+輸入與假設!E104*TK_CapexFacility_GB300+輸入與假設!E111*TK_CapexFacility_VR200+輸入與假設!E118*TK_CapexFacility_VR200)/MAX(0.000000001,輸入與假設!E119)/1000*0.1/(1-(1+0.1)^(-輸入與假設!$C$310)) -> 0.0014889304 | F13: =(輸入與假設!F69*TK_CapexFacility_H100+輸入與假設!F76*TK_CapexFacility_H100+輸入與假設!F83*TK_CapexFacility_GB200+輸入與假設!F90*TK_CapexFacility_GB200+輸入與假設!F97*TK_CapexFacility_GB300+輸入與假設!F104*TK_CapexFacility_GB300+輸入與假設!F111*TK_CapexFacility_VR200+輸入與假設!F118*TK_CapexFacility_VR200)/MAX(0.000000001,輸入與假設!F119)/1000*0.1/(1-(1+0.1)^(-輸入與假設!$C$310)) -> 0.0014889304 | G13: =(輸入與假設!G69*TK_CapexFacility_H100+輸入與假設!G76*TK_CapexFacility_H100+輸入與假設!G83*TK_CapexFacility_GB200+輸入與假設!G90*TK_CapexFacility_GB200+輸入與假設!G97*TK_CapexFacility_GB300+輸入與假設!G104*TK_CapexFacility_GB300+輸入與假設!G111*TK_CapexFacility_VR200+輸入與假設!G118*TK_CapexFacility_VR200)/MAX(0.000000001,輸入與假設!G119)/1000*0.1/(1-(1+0.1)^(-輸入與假設!$C$310)) -> 0.0014889304 | I13: 出租方打平租金＝在役世代加權 TK_CapexFacility × 10% 資本回收係數（機房年限）[Derived]（C22）
A14: 機房租金（自有對外 MW ×(1 − 自建比例)） | B14: US$bn | C14: =(1-輸入與假設!$C$264)*MAX(0,C10-C11)*C13 -> 0.49413879 | D14: =(1-輸入與假設!$C$264)*MAX(0,D10-D11)*D13 -> 0.70284961 | E14: =(1-輸入與假設!$C$264)*MAX(0,E10-E11)*E13 -> 0.98113071 | F14: =(1-輸入與假設!$C$264)*MAX(0,F10-F11)*F13 -> 1.2594118 | G14: =(1-輸入與假設!$C$264)*MAX(0,G10-G11)*G13 -> 1.5376929 | I14: 只進 AI 增量報酬（資金與評價的租金現金已在租賃承諾內，不重複扣；C22）
A15: 租用對外 MW 租金 | B15: US$bn | C15: =C11*0/1000 -> 0 | D15: =D11*0/1000 -> 0 | E15: =E11*0/1000 -> 0 | F15: =F11*0/1000 -> 0 | G15: =G11*0/1000 -> 0 | I15: ＝租用對外 MW × 每 MW 年租金（capexModel.rentedExt.rentMW；C20）
A16: 對外 AI EBITDA（扣租金） | B16: US$bn | C16: =C7-C14-C15 -> 20.733375 | D16: =D7-D14-D15 -> 31.262085 | E16: =E7-E14-E15 -> 45.666731 | F16: =F7-F14-F15 -> 60.185747 | G16: =G7-G14-G15 -> 74.76219
A17: 對外 AI 折舊（年化，按對外比例分攤） | B17: US$bn | C17: =C9*C12 -> 11.757354 | D17: =D9*D12 -> 17.783716 | E17: =E9*E12 -> 25.984008 | F17: =F9*F12 -> 34.462032 | G17: =G9*G12 -> 42.940055
A18: 對外 AI NOPAT（年化） | B18: US$bn | C18: =(C16-C17)*(1-輸入與假設!$C$383) -> 7.4680499 | D18: =(D16-D17)*(1-輸入與假設!$C$383) -> 11.214003 | E18: =(E16-E17)*(1-輸入與假設!$C$383) -> 16.376025 | F18: =(F16-F17)*(1-輸入與假設!$C$383) -> 21.402131 | G18: =(G16-G17)*(1-輸入與假設!$C$383) -> 26.476016 | I18: ＝(對外 EBITDA − 對外折舊)×(1 − 稅率)
A19: AI 投入資本（期初） | B19: US$bn | C19: =(輸入與假設!$C$308+輸入與假設!$C$309)*輸入與假設!$C$313 -> 181.1893 | D19: =C21 -> 261.7409 | E19: =D21 -> 392.20669 | F19: =E21 -> 506.44741 | G19: =F21 -> 616.35804 | I19: 2026＝AI 期初毛額 × 淨額比；之後＝前期期末
A20: AI 投入（成長型＋汰換，模型期） | B20: US$bn | C20: =輸入與假設!C$300+輸入與假設!C$304 -> 100.14719 | D20: =輸入與假設!D$300+輸入與假設!D$304 -> 189.74484 | E20: =輸入與假設!E$300+輸入與假設!E$304 -> 200.85409 | F20: =輸入與假設!F$300+輸入與假設!F$304 -> 224.78407 | G20: =輸入與假設!G$300+輸入與假設!G$304 -> 344.63024
A21: AI 投入資本（期末） | B21: US$bn | C21: =C19+C20-輸入與假設!C$319 -> 261.7409 | D21: =D19+D20-輸入與假設!D$319 -> 392.20669 | E21: =E19+E20-輸入與假設!E$319 -> 506.44741 | F21: =F19+F20-輸入與假設!F$319 -> 616.35804 | G21: =G19+G20-輸入與假設!G$319 -> 817.85476 | I21: ＝期初＋投入 − AI 折舊
A22: 對外 AI 平均投入資本（按對外比例分攤） | B22: US$bn | C22: =(C19+C21)/2*C12 -> 66.439529 | D22: =(D19+D21)/2*D12 -> 98.092137 | E22: =(E19+E21)/2*E12 -> 134.79811 | F22: =(F19+F21)/2*F12 -> 168.42082 | G22: =(G19+G21)/2*G12 -> 215.13192
A23: 對外 AI ROIC（主值） | B23: % | C23: =C18/MAX(0.000000001,C22) -> 0.11240372 | D23: =D18/MAX(0.000000001,D22) -> 0.11432112 | E23: =E18/MAX(0.000000001,E22) -> 0.12148557 | F23: =F18/MAX(0.000000001,F22) -> 0.12707533 | G23: =G18/MAX(0.000000001,G22) -> 0.12306875 | I23: ＝對外 NOPAT ÷ 對外平均投入資本（對照表 r1 C11）
A24: WACC | B24: % | C24: =輸入與假設!$C$393 -> 0.11577298 | D24: =輸入與假設!$C$393 -> 0.11577298 | E24: =輸入與假設!$C$393 -> 0.11577298 | F24: =輸入與假設!$C$393 -> 0.11577298 | G24: =輸入與假設!$C$393 -> 0.11577298
A25: 對外 AI ROIC − WACC | B25: % | C25: =C23-C24 -> -0.0033692665 | D25: =D23-D24 -> -0.0014518594 | E25: =E23-E24 -> 0.005712584 | F25: =F23-F24 -> 0.011302347 | G25: =G23-G24 -> 0.0072957668 | I25: 負值＝AI 投資未賺到資金成本
A26: 影子收入（自用 AI MW × 每 MW 年收入，年化） | B26: US$bn | C26: =C5*(1/輸入與假設!$C$263-1) -> 59.372842 | D26: =D5*(1/輸入與假設!$C$263-1) -> 88.903271 | E26: =E5*(1/輸入與假設!$C$263-1) -> 129.1981 | F26: =F5*(1/輸入與假設!$C$263-1) -> 169.78041 | G26: =G5*(1/輸入與假設!$C$263-1) -> 210.50708 | I26: 自用 AI MW＝對外 ×(1 ÷ 對外比例 − 1)；只作對照，不進評價（對照表 r1 D2）
A27: 全 AI ROIC（含影子收入，對照） | B27: % | C27: =(C7+C26*C6-(1-輸入與假設!$C$264)*MAX(0.000000001,C10/輸入與假設!$C$263-C11)*C13-C15-C9)*(1-輸入與假設!$C$383)/MAX(0.000000001,(C19+C21)/2) -> 0.11240372 | D27: =(D7+D26*D6-(1-輸入與假設!$C$264)*MAX(0.000000001,D10/輸入與假設!$C$263-D11)*D13-D15-D9)*(1-輸入與假設!$C$383)/MAX(0.000000001,(D19+D21)/2) -> 0.11432112 | E27: =(E7+E26*E6-(1-輸入與假設!$C$264)*MAX(0.000000001,E10/輸入與假設!$C$263-E11)*E13-E15-E9)*(1-輸入與假設!$C$383)/MAX(0.000000001,(E19+E21)/2) -> 0.12148557 | F27: =(F7+F26*F6-(1-輸入與假設!$C$264)*MAX(0.000000001,F10/輸入與假設!$C$263-F11)*F13-F15-F9)*(1-輸入與假設!$C$383)/MAX(0.000000001,(F19+F21)/2) -> 0.12707533 | G27: =(G7+G26*G6-(1-輸入與假設!$C$264)*MAX(0.000000001,G10/輸入與假設!$C$263-G11)*G13-G15-G9)*(1-輸入與假設!$C$383)/MAX(0.000000001,(G19+G21)/2) -> 0.12306875 | I27: 全 AI 機房租金＝(1 − 自建)× 自有 AI 總 MW × 每 MW 機房年租金（C22）
A29: 打平 k（使 2029 對外 AI ROIC＝WACC） | C29: =輸入與假設!$C$58*(輸入與假設!$C$393*F22/(1-輸入與假設!$C$383)+F8+F14+F15+F17)/MAX(0.000000001,F5) -> 1.1177143 | I29: ＝k ×(WACC × 對外平均投入資本 ÷ (1 − 稅率)＋營運成本＋租金＋對外折舊) ÷ 營收（AI EBITDA 對 k 線性，閉式解；對外口徑）
A30: 目前採用 k | C30: =輸入與假設!$C$58 -> 1.154
A32: C15 一致性檢查（2029，對外口徑；序列拆解，各步差額加總＝總差距）
A33: IF_HoldEcon 隱含報酬（Tokenomics WACC，經濟口徑） | C33: 0.1 | I33: IF_HoldEcon 的資本回收年金折現率：Tokenomics Inputs!E28「WACC（經濟口徑）」基準 10%（builder v5：L1_HoldEconGW＝資本回收年金（WACC 10%）＋營運費用）；非具名範圍，換 Tokenomics 版本時核對 [Verified]；只用於一致性檢查（對照表 r1 C15）
A34: 在役對外 MW（有效，＝營收 ÷ 每 MW 年收入） | C34: =F10 -> 5639
A35: 自有在役對外 MW（有效 − 租用） | C35: =MAX(0,C34-F11) -> 5639
A36: k＝1 營收（Σ 在役世代 × IF_HoldEcon，不含晶片係數） | C36: =C34*(輸入與假設!F69*TK_HoldEcon_H100+輸入與假設!F76*TK_HoldEcon_H100+輸入與假設!F83*TK_HoldEcon_GB200+輸入與假設!F90*TK_HoldEcon_GB200+輸入與假設!F97*TK_HoldEcon_GB300+輸入與假設!F104*TK_HoldEcon_GB300+輸入與假設!F111*TK_HoldEcon_VR200+輸入與假設!F118*TK_HoldEcon_VR200)/MAX(0.000000001,輸入與假設!F119)/1000 -> 63.052889
A37: Tokenomics 營運成本（Σ 在役世代 × IF_OpexGW） | C37: =C34*(輸入與假設!F69*TK_OpexGW_H100+輸入與假設!F76*TK_OpexGW_H100+輸入與假設!F83*TK_OpexGW_GB200+輸入與假設!F90*TK_OpexGW_GB200+輸入與假設!F97*TK_OpexGW_GB300+輸入與假設!F104*TK_OpexGW_GB300+輸入與假設!F111*TK_OpexGW_VR200+輸入與假設!F118*TK_OpexGW_VR200)/MAX(0.000000001,輸入與假設!F119)/1000 -> 11.317875
A38: 累計汰換（對外，至錨定期中點） | C38: =F12*(輸入與假設!C$304+輸入與假設!D$304+輸入與假設!E$304+輸入與假設!F$304/2) -> 3.5894966
A39: 穩態投入資本（自有在役 MW ×(IT＋自建 × 機房)× ½） | C39: =C35*((輸入與假設!F69*TK_CapexIT_H100+輸入與假設!F76*TK_CapexIT_H100+輸入與假設!F83*TK_CapexIT_GB200+輸入與假設!F90*TK_CapexIT_GB200+輸入與假設!F97*TK_CapexIT_GB300+輸入與假設!F104*TK_CapexIT_GB300+輸入與假設!F111*TK_CapexIT_VR200+輸入與假設!F118*TK_CapexIT_VR200)/MAX(0.000000001,輸入與假設!F119)/1000+輸入與假設!$C$264*(輸入與假設!F69*TK_CapexFacility_H100+輸入與假設!F76*TK_CapexFacility_H100+輸入與假設!F83*TK_CapexFacility_GB200+輸入與假設!F90*TK_CapexFacility_GB200+輸入與假設!F97*TK_CapexFacility_GB300+輸入與假設!F104*TK_CapexFacility_GB300+輸入與假設!F111*TK_CapexFacility_VR200+輸入與假設!F118*TK_CapexFacility_VR200)/MAX(0.000000001,輸入與假設!F119)/1000)*0.5 -> 124.58187
A40: 穩態折舊（自有在役 MW ×(IT ÷ 壽命＋自建 × 機房 ÷ 機房壽命)） | C40: =C35*((輸入與假設!F69*TK_CapexIT_H100+輸入與假設!F76*TK_CapexIT_H100+輸入與假設!F83*TK_CapexIT_GB200+輸入與假設!F90*TK_CapexIT_GB200+輸入與假設!F97*TK_CapexIT_GB300+輸入與假設!F104*TK_CapexIT_GB300+輸入與假設!F111*TK_CapexIT_VR200+輸入與假設!F118*TK_CapexIT_VR200)/MAX(0.000000001,輸入與假設!F119)/1000/輸入與假設!$C$262+輸入與假設!$C$264*(輸入與假設!F69*TK_CapexFacility_H100+輸入與假設!F76*TK_CapexFacility_H100+輸入與假設!F83*TK_CapexFacility_GB200+輸入與假設!F90*TK_CapexFacility_GB200+輸入與假設!F97*TK_CapexFacility_GB300+輸入與假設!F104*TK_CapexFacility_GB300+輸入與假設!F111*TK_CapexFacility_VR200+輸入與假設!F118*TK_CapexFacility_VR200)/MAX(0.000000001,輸入與假設!F119)/1000/輸入與假設!$C$310) -> 34.44661
