Workbook

Sheet README
A1: Alphabet（GOOGL）個股模型 v0.3（2026-10-27）— 命題模組＋官方營收分部 → 損益表
A3: 命題：AI 改變搜尋之後，Google Search 的變現能否守住，同時 Google Cloud（含 TPU）能否把翻倍的資本支出變成營收；資本支出與 2026 年股權發行後的每股價值是否高於現價。
A4: 核心問題：Search & other 在 C 情境（AI 助理分流、每次查詢變現下降）下 FY2028 營收與利益率會掉多少，Cloud 的 AI 營收能否抵銷；加計 AI 折舊與股權發行後的每股價值。
A5: ="投資建議："&Val!B14&"（加權目標價 US$"&TEXT(Val!B8,"0.00")&"，上檔空間 "&TEXT(Val!B11,"+0.0%;-0.0%")&"；現價 "&TEXT(px,"0.00")&"，2026-10-26）" -> 投資建議：中立（加權目標價 US$248.94，上檔空間 -21.4%；現價 316.80，2026-10-26）
A6: ="重點觀察 1：目標價 "&TEXT(Val!B8,"0")&"＝DCF "&TEXT(Val!B6,"0")&"、分部加總 "&TEXT(Val!B7,"0")&" 各半；情境 A／B／C 為 "&TEXT(Val!B17,"0")&"／"&TEXT(Val!C17,"0")&"／"&TEXT(Val!D17,"0")&"，DCF 終值占 EV "&TEXT(Val!C19,"0%")&"（B）。市場共識目標價 "&TEXT(cons_tp,"0")&"。" -> 重點觀察 1：目標價 249＝DCF 180、分部加總 318 各半；情境 A／B／C 為 273／253／216，DCF 終值占 EV 74%（B）。市場共識目標價 429。
A7: ="重點觀察 2：C 情境 FY2028 Search & other "&TEXT(PL!I131,"0.0")&"（比 B 少 "&TEXT(1-PL!I131/PL!I72,"0.0%")&"），Google Services 營業利益率 "&TEXT(PL!I169,"0.0%")&"（B "&TEXT(PL!I110,"0.0%")&"）；同年 Cloud AI 營收 "&TEXT(PL!I77,"0.0")&"、Google Cloud 營業利益 "&TEXT(PL!I94,"0.0")&"，Cloud 營業利益比 FY2025 增加 "&TEXT(PL!I94-PL!D94,"0.0")&"，是 C 情境 Services 營業利益損失 "&TEXT(PL!I91-PL!I150,"0.0")&" 的 "&TEXT((PL!I94-PL!D94)/(PL!I91-PL!I150),"0%")&"（Cloud 的成長足以抵銷搜尋被侵蝕的利潤）。" -> 重點觀察 2：C 情境 FY2028 Search & other 290.1（比 B 少 14.5%），Google Services 營業利益率 32.1%（B 35.8%）；同年 Cloud AI 營收 56.7、Google Cloud 營業利益 62.1，Cloud 營業利益比 FY2025 增加 48.2，是 C 情境 Services 營業利益損失 34.2 的 141%（Cloud 的成長足以抵銷搜尋被侵蝕的利潤）。
A8: ="重點觀察 3：AI 折舊進損益——情境 B 新增 AI 折舊 FY2028 "&TEXT(PL!I104,"0.0")&"，合併營業利益率由 FY2025 "&TEXT(PL!D109,"0.0%")&" 變為 FY2028 "&TEXT(PL!I109,"0.0%")&"；收支關卡（FY2026–2030 自由現金流扣股利合計）B "&TEXT(CF!C6,"0.0")&"，"&CF!C9&"。" -> 重點觀察 3：AI 折舊進損益——情境 B 新增 AI 折舊 FY2028 62.0，合併營業利益率由 FY2025 32.0% 變為 FY2028 24.2%；收支關卡（FY2026–2030 自由現金流扣股利合計）B 180.0，不需舉債，回購照目標。
A10: 驅動 → 推導對照表（每頁輸入、推導量、因果方向）
A11: 頁 | B11: 輸入（In 頁鍵） | C11: 推導量 | D11: 因果方向
A12: Thesis | B12: pace、ext_sh、mw_tot0、k（kl_px、ks_px、long_sh）、Tokenomics IF_HoldEcon／OpexGW／CapexIT | C12: Cloud AI 營收與 EBITDA、AI 資本支出、新增 AI 折舊、自用 AI 增量成本 | D12: MW → 收入（× 每 MW 持有成本 × k）；MW → 資本支出 → 折舊 → 分部營業利益
A13: Seg | B13: g0（Q 頁近四季）、gl_*、conv_n、dA／mA／dC／mC、tpu_*、ob_rev_* | C13: 四條產品線、三個分部、合併營收；非 AI 資本支出與折舊 | D13: 近四季年增 → 長期值；Search＝B 路徑 ×(1 − 分流)×(1＋變現變動)
A14: PL | B14: m_svc、inc_m、m_co、tpu_m、abc_rate、svc_sh、da_base、tax | C14: 分部 EBITDA、分部營業利益、合併營業利益、淨利、EPS | D14: 分部營收 → 分部 EBITDA − 折舊 → 營業利益 → 業外、稅 → EPS
A15: CF | B15: sbc_r、wc_*、dps、bb_t、min_cash、mat_*、anth_* | C15: 自由現金流、股利、回購、新債、淨現金、收支關卡 | D15: 淨利＋折舊 − 資本支出 → 自由現金流 → 股利 → 回購／舉債
A16: Val | B16: rf、beta、erp、kd、g_tv、ronic、同業倍數、持股、tp_w*、w_dcf | C16: DCF、分部加總、目標價、上檔空間、投資建議 | D16: 無槓桿 FCF 折現＋分部 EBITDA × 倍數 → 情境加權 → 50／50
A17: Sens | B17: In 頁低／高值 | C17: 加權目標價變動 | D17: 一次改一個輸入、整本重算
A19: 與 v0.2.2 的差異
A20: 營收主軸由「AI 雲端 MW × 每 MW 收入＋其餘成長率線」改為官方分部（Google Services 四條產品線、Google Cloud、Other Bets、Alphabet 層級）；Cloud AI 只是 Google Cloud 的子列。
A21: 情境軸由「AI 容量（保守／基準／積極）」改為 Search（A 擴大變現／B 近四季成長收斂／C 查詢分流）；AI 容量三情境相同，改列 Sens。
A22: AI 資本支出接到折舊與分部營業利益（對外 → Cloud、自用 → Services 與 Alphabet 層級），不只接現金。
A23: 評價由 DCF 45%＋EV/EBITDA 55%（錨定 2029）改為 DCF 50%＋分部加總 50%（各分部同業倍數）；評等改五級（上檔空間）。
A24: 融資瀑布、站點、租賃承諾、RPO 等 CRWV 頁面移除（舊引擎保留在 legacy_v0.2/）。
A25: 修正一（獨立核對後）：自用 AI 讀法 2 為主值（影子效益進評價口徑）、分部加總 SBC 加回同口徑、Cloud AI 用自身 DCF、搜尋／YouTube 用 META 倍數、Blume β 與 10 年期 kd、MW 新增 FY2029 起收斂、基礎折舊隨汰換遞減、Other Bets 以 0 計（Waymo 估值未找到）。
A27: 工作表：README → In → Q → Thesis → Seg → PL → CF → Val → Recon → Sens → Sources。藍字＝輸入、黑字＝公式；黃底＝判斷題。建置：bash alphabet/make_v03.sh
A28: 數字標記：Verified（經查核）／Interested-party（公司或賣方自述）／Analogy／Assumed（給區間）／Derived（換算）。本模型是研究整理，不是投資建議以外的保證。

Sheet In
A1: In — 輸入（藍字；基準欄 E，低 D、高 F）。金額 US$B；每股 US$；股數十億股；MW＝IT MW。標記：Verified／Interested-party／Analogy／Assumed／Derived（Analogy、Assumed 一律給低／高區間）
A2: 「沿用 v0.2.2」＝MAG v0.2.2 已核准的參數（原出處：alphabet/legacy_v0.2/company.json、kspec.py、data/kevidence_alphabet_20261008.json、data/tokenomics_snapshot_v21.4.json；對照表 r1 C1–C23）。Tokenomics 維持 v21.4。黃底＝判斷題（Andy 可改）
A3: 鍵 | B3: 項目 | C3: 單位 | D3: 低 | E3: 基準 | F3: 高 | G3: 標記 | H3: 來源 | I3: 說明
A4: A. 現價、股數與資產負債（評價日 2026-06-30，2026Q2 10-Q）
A5: px | B5: 現價（2026-10-26 收盤） | C5: US$ | E5: 316.8 | G5: Verified | H5: StockAnalysis 歷史股價頁 https://stockanalysis.com/stocks/googl/history/（2026-10-27 讀取：10-26 收盤 316.80、10-23 收盤 320.21） | I5: 第二來源：markets/invest_map/data/prices.csv 2026-10-23 收盤 320.21（stockscan、bullfincher）與同頁 10-23 值相同。v0.2.2 現價 350.50（2026-10-07）
A6: sh_out | B6: 流通股數（2026-07-15，10-Q 封面） | C6: 十億股 | E6: 12.23 | G6: Verified | H6: Alphabet Form 10-Q 2026Q2（期末 2026-06-30，核閱數）（2026-07-23；事實總帳 sh.out.20260715）
A7: sh_dil_q2 | B7: 2026Q2 稀釋加權股數 | C7: 十億股 | E7: 12.309 | G7: Interested-party | H7: Alphabet 2026Q2 財報新聞稿（8-K 附件 99.1）（2026-07-22；事實總帳 sh.dilW.2026q2）
A8: sh_basic_q2 | B8: 2026Q2 基本加權股數 | C8: 十億股 | E8: 12.151 | G8: Interested-party | H8: Alphabet 2026Q2 10-Q（2026-07-23）；legacy_v0.2/company.json latestQuarter.basicWaso | I8: 2026-06 股權發行（6/4）只在 Q2 部分期間加權；期末稀釋股數＝Q2 稀釋加權＋(流通股 − Q2 基本加權)
A9: conv_sh | B9: 強制轉換特別股 2029-05-15 轉換股數（上限） | C9: 十億股 | D9: 0.0436 | E9: 0.0546 | F9: 0.0546 | G9: Interested-party | H9: 8-K 2026-06-05：A 系列每股轉 2.2520–2.8160 股、B 系列 2.2740–2.8420 股 → 43.6–54.6M 股；沿用 v0.2.2（legacy_v0.2/company.json） debt.convertibles | I9: 取稀釋最大（保守）；評價時直接加入股數，特別股股利照付至轉換
A10: cash_0 | B10: 現金＋債權類有價證券（2026-06-30） | C10: US$B | E10: 155.411 | G10: Derived | H10: 10-Q 2026Q2：現金 55.911＋有價證券 186.563 − 有價權益證券 87.063（事實總帳 bs.cash、bs.mktsec、bs.mktEq） | I10: 沿用 v0.2.2（legacy_v0.2/company.json） defaults.cash（權益證券改列持股）
A11: cash_ye25 | B11: 現金＋債權類有價證券（2025-12-31） | C11: US$B | E11: 120.53 | G11: Derived | H11: 10-K 2025：30.708＋96.135 − 6.313（沿用 v0.2.2（legacy_v0.2/company.json） ytdActual.cash1231）
A12: debt_0 | B12: 債務面額（2026-06-30） | C12: US$B | E12: 101.085 | G12: Interested-party | H12: 10-Q 2026Q2 附註 6（事實總帳 debt.face）
A13: fines | B13: 應計罰款與和解（類債） | C13: US$B | E13: 17.356 | G13: Interested-party | H13: 10-Q 2026Q2（事實總帳 bs.accruedFines） | I13: 2026-07 已付 Android 案 5.2B（仍以 6/30 餘額扣除，與 v0.2.2 同）
A14: nci | B14: 非控制權益（類債） | C14: US$B | E14: 7.1 | G14: Interested-party | H14: 10-Q 2026Q2（事實總帳 bs.nci；Waymo 等少數股權）
A15: B. 持股（分部加總與 DCF 皆加入；非上市 × (1 − 流動性折價)；上市不折價）
A16: ant_val | B16: Anthropic 最近一輪投後估值（Series H） | C16: US$B | E16: 965 | G16: Interested-party | H16: TechCrunch〈Anthropic raises $65 billion, nears $1T valuation ahead of IPO〉（經 anthropic/ SRC_ANT_299）（2026-05-28；事實總帳 rp.anthropic.val.seriesH）
A17: ant_stake | B17: Anthropic 持股比例 | C17: % | D17: 0.11 | E17: 0.125 | F17: 0.14 | G17: Assumed | H17: 一手不存在：2025 法院文件約 14%；非上市證券帳面 124.3B ÷ 965B 隱含上限 12.9%（沿用 v0.2.2（legacy_v0.2/company.json） valuation.holdings）
A18: illiq | B18: 非上市持股流動性折價 | C18: % | D18: 0 | E18: 0.2 | F18: 0.4 | G18: Assumed | H18: 工作單第 2 節 Val 0.2（1 − 流動性折價 20%）；對照表 r1 第 5 節第 9 條
A19: spacex | B19: SpaceX 持股公允價值（上市、限售） | C19: US$B | E19: 94.1 | G19: Interested-party | H19: 10-Q 2026Q2 附註 3：短期 80.0＋長期限售 14.1（事實總帳 rp.spacex.holding） | I19: 評價日公允價值；之後股價變動未更新（資料缺口）
A20: oth_eq | B20: 其他有價權益證券 | C20: US$B | E20: 7.089 | G20: Derived | H20: 有價權益證券 87.063＋14.126 − SpaceX 94.1（沿用 v0.2.2（legacy_v0.2/company.json））
A21: C. 折現率與目標價規則
A22: rf | B22: 無風險利率（10 年美債，2026-10-07） | C22: % | E22: 0.0528 | G22: Verified | H22: U.S. Treasury〈Daily Treasury Par Yield Curve Rates〉（2026-10）（2026-10-07；事實總帳 val.rf.10y） | I22: 沿用 v0.2.2（legacy_v0.2/company.json）
A23: beta_sa | B23: 原始 β：StockAnalysis 5 年月資料（Yahoo、MarketBeat 同值） | C23: x | E23: 1.21 | G23: Verified | H23: StockAnalysis〈GOOGL statistics〉（2026-10-07；事實總帳 val.beta.sa） | I23: 沿用 v0.2.2（legacy_v0.2/company.json）
A24: beta_gf | B24: 原始 β：GuruFocus 3 年 | C24: x | E24: 1.3669 | G24: Verified | H24: GuruFocus〈GOOGL Beta〉（2026-10-08；事實總帳 val.beta.gurufocus） | I24: 與 StockAnalysis 不同資料商、不同期間（C13）
A25: blume_a | B25: Blume 調整係數（β 調整＝a × 原始 β＋(1 − a)） | C25: x | E25: 0.67 | G25: Derived | H25: Blume（1971）；Bloomberg 調整 β 同式（修正一 F4）
A26: beta | B26: β（Blume 調整後兩個獨立來源的中位數） | C26: x | D26: 1.1407 | E26: =MEDIAN(blume_a*beta_sa+1-blume_a,blume_a*beta_gf+1-blume_a) -> 1.1932615 | F26: 1.2458 | G26: Derived | H26: 修正一 F4：Blume 調整（0.67 × 原始 β＋0.33），兩個獨立來源取中位數 | I26: 低／高＝兩個來源各自的調整值；v0.3 修正前用原始 β 平均 1.288
A27: erp | B27: 股權風險溢酬 | C27: % | D27: 0.04 | E27: 0.05 | F27: 0.06 | G27: Assumed | H27: 沿用 v0.2.2（legacy_v0.2/company.json）（val.erp）
A28: kd_sp | B28: 約 10 年期 AA 公司債利差（相對 10 年美債） | C28: % | D28: 0.004 | E28: 0.006 | F28: 0.009 | G28: Assumed | H28: 判斷：Aa2／AA+（事實總帳 debt.rating）10 年期利差約 50–90bp；2066 長債發行利差 T＋130bp 為 40 年期，不採（修正一 F4）
A29: kd | B29: 稅前債務成本（約 10 年期）＝rf＋利差 | C29: % | E29: =rf+kd_sp -> 0.0588 | G29: Derived | H29: 修正一 F4：kd＝約 10 年期公司債殖利率 | I29: v0.3 修正前用 2066 票據 6.527%（Alphabet 定價條款 FWP（2026-08-06；US$25B 票據）（2026-08-06；事實總帳 val.kd.2066））
A30: fin_lease | B30: 融資租賃負債（2026-06-30） | C30: US$B | E30: 2.59 | G30: Interested-party | H30: 10-Q 2026Q2 附註 4（事實總帳 lease.finLiab） | I30: 計入 WACC 負債與 DCF、分部加總的淨負債（修正一 F6）
A31: wacc_adj | B31: WACC 調整（Sens 格：±1pt） | C31: % | D31: -0.01 | E31: 0 | F31: 0.01 | G31: Assumed | H31: 修正一 F4：WACC ±1 個百分點的目標價格
A32: tax_w | B32: WACC 用稅率（2025 有效稅率） | C32: % | E32: 0.168 | G32: Derived | H32: 10-K 2025：所得稅 26.656 ÷ 稅前 158.826 | I32: 沿用 v0.2.2（legacy_v0.2/company.json）
A33: g_tv | B33: 永續成長率（FY2032 後） | C33: % | D33: 0.02 | E33: 0.03 | F33: 0.04 | G33: Assumed | H33: 工作單第 2 節 Val 0.1（g 3%）
A34: ronic_sp | B34: 永續期新投資報酬率 RONIC 相對 WACC 的差 | C34: % | E34: 0 | F34: 0.05 | G34: Assumed | H34: 修正一 F5：RONIC＝WACC（判斷；終值＝NOPAT(FY2033) ×(1 − g ÷ RONIC) ÷ (WACC − g)） | I34: Sens：WACC＋5pt；修正前固定 12%
A35: mid | B35: 期中慣例：年度現金流距年初 | C35: 年 | E35: 0.5 | G35: Derived | H35: 年度現金流平均發生在年中；2H26 為評價日後 0.25 年
A36: t_2h | B36: 2H26 現金流折現年數（評價日 2026-06-30 起，期中） | C36: 年 | E36: 0.25 | G36: Derived | H36: 2026-07-01～12-31 的中點
A37: tp_wA | B37: 情境權重 A | C37: % | E37: 0.25 | G37: Assumed | H37: 工作單第 2 節 Val 0.3（A 25%／B 50%／C 25%）
A38: tp_wB | B38: 情境權重 B | C38: % | E38: 0.5 | G38: Assumed | H38: 同上
A39: tp_wC | B39: 情境權重 C | C39: % | E39: 0.25 | G39: Assumed | H39: 同上
A40: w_dcf | B40: 目標價中 DCF 的權重（其餘＝分部加總 SOTP） | C40: % | D40: 0.3 | E40: 0.5 | F40: 0.7 | G40: Assumed | H40: 工作單第 2 節 Val 0.3（DCF 50%＋分部加總 50%；與 AI半導體「DCF＋Comparable 各半」一致）
A41: t_tgt | B41: 目標時點距評價日（2026-06-30 → 2027-10-27） | C41: 年 | E41: 1.3233 | G41: Derived | H41: (2027-10-27 − 2026-06-30) ÷ 365＝483 天 | I41: 目標價約 12 個月後（今天 2026-10-27 起算）
A42: w_ntm27 | B42: 目標時點 NTM 中 FY2027 的權重 | C42: % | E42: 0.1781 | G42: Derived | H42: (2027-12-31 − 2027-10-27) ÷ 365＝65 天；FY2028 權重＝1 − 本值 | I42: 分部加總用目標時點的未來 12 個月 EBITDA
A43: cons_tp | B43: 市場共識目標價（平均） | C43: US$ | E43: 429.12 | G43: Interested-party | H43: StockAnalysis 預測頁 https://stockanalysis.com/stocks/googl/forecast/（2026-10-26 更新；61 位分析師；中位數 430、低 340、高 500） | I43: v0.2.2 時 429.47（2026-10-08）；賣方有承銷關係，只作對照
A44: dps_tgt | B44: 評價日到目標時點的每股股利（推到目標價時扣除） | C44: US$ | E44: =dps/2+dps*(1+dps_g)*(1-w_ntm27) -> 1.1994356 | G44: Derived | H44: 2H26 兩季＋2027 年至 10-27（修正一 F6）
A45: t_px0 | B45: 現價日（2026-10-26）的年份小數 | C45: 年 | E45: 2026.82 | G45: Derived | H45: 回購均價 ＝ 現價 × (1＋ke)^(期中 − 本值)
A46: mb_ttm | B46: 分部利益率起點改用近四季（1＝是；0＝1H26） | C46: x | E46: 0 | F46: 1 | G46: Assumed | H46: 判斷：預設 1H26（利潤率擴張中、與評價日機隊同時點）；1＝v0.2.2 的近四季口徑
A47: internal_ai_reading | B47: 自用 AI 讀法（2＝主值：自用 AI 價值中性，計影子效益；1＝敏感度：只計成本） | C47: x | D47: 1 | E47: 2 | G47: Assumed | H47: 修正一 F1（chat 端預設，已向 Andy 提出）：自用增量 MW × Tokenomics IF_HoldEcon（k＝1）＝自用 AI 影子效益（非財報營收），進評價口徑 NOPAT、FCF、EPS；對照表 r1 C16 | I47: 營收列與分部對帳不動；Val 頁兩種讀法的目標價並列（皆為活公式）
A48: sbc_add | B48: DCF 加回股權報酬（1＝是；Sens 用） | C48: x | E48: 0 | F48: 1 | G48: Assumed | H48: 判斷：股權報酬視為真實成本、不加回（稀釋已在股數 dil）；1＝加回（稅後）
A49: tv_alt | B49: 終值改用 FY2032 無槓桿自由現金流 ×(1＋g)（1＝是；Sens 用） | C49: x | E49: 0 | F49: 1 | G49: Assumed | H49: 判斷：基準用價值驅動公式（ronic）；1＝替代口徑
A50: C2. 分部加總（SOTP）倍數：同業 NTM EV/EBITDA（沿用 v0.2.2 共用同業檔，基準日 2026-10-07；中位數在 Val 頁計算）
A51: pm_ads_meta | B51: 數位廣告（Search、YouTube、Network、Alphabet 層級費用）：Meta（META）NTM EV/EBITDA | C51: x | E51: 10.79 | G51: Derived | H51: data/peers_ads_20261009.json（C18；MAG 三家共用） | I51: EV（StockAnalysis）÷ NTM EBITDA（MarketScreener 共識 FY1／FY2 時間加權）
A52: pm_ads_pins | B52: 數位廣告（Search、YouTube、Network、Alphabet 層級費用）：Pinterest（PINS）NTM EV/EBITDA | C52: x | E52: 6.91 | G52: Derived | H52: data/peers_ads_20261009.json（C18；MAG 三家共用） | I52: EV（StockAnalysis）÷ NTM EBITDA（MarketScreener 共識 FY1／FY2 時間加權）
A53: pm_ads_ttd | B53: 數位廣告（Search、YouTube、Network、Alphabet 層級費用）：The Trade Desk（TTD）NTM EV/EBITDA | C53: x | E53: 6.53 | G53: Derived | H53: data/peers_ads_20261009.json（C18；MAG 三家共用） | I53: EV（StockAnalysis）÷ NTM EBITDA（MarketScreener 共識 FY1／FY2 時間加權）
A54: pm_ads_app | B54: 數位廣告（Search、YouTube、Network、Alphabet 層級費用）：AppLovin（APP）NTM EV/EBITDA | C54: x | E54: 11.38 | G54: Derived | H54: data/peers_ads_20261009.json（C18；MAG 三家共用） | I54: EV（StockAnalysis）÷ NTM EBITDA（MarketScreener 共識 FY1／FY2 時間加權）
A55: pm_ads_rddt | B55: 數位廣告（Search、YouTube、Network、Alphabet 層級費用）：Reddit（RDDT）NTM EV/EBITDA | C55: x | E55: 13.63 | G55: Derived | H55: data/peers_ads_20261009.json（C18；MAG 三家共用） | I55: EV（StockAnalysis）÷ NTM EBITDA（MarketScreener 共識 FY1／FY2 時間加權）
A56: pm_ads_snap | B56: 數位廣告（Search、YouTube、Network、Alphabet 層級費用）：Snap（SNAP）NTM EV/EBITDA | C56: x | E56: 7.43 | G56: Derived | H56: data/peers_ads_20261009.json（C18；MAG 三家共用） | I56: EV（StockAnalysis）÷ NTM EBITDA（MarketScreener 共識 FY1／FY2 時間加權）
A57: pm_subs_nflx | B57: 訂閱影音（Subscriptions, platforms, and devices）：Netflix（NFLX）NTM EV/EBITDA | C57: x | E57: 15.41 | G57: Derived | H57: legacy_v0.2/company.json valuation.segmentMultiples.subs（NFLX 為 NTM；SPOT、DIS 為 TTM，amazon/data 事實總帳） | I57: EV（StockAnalysis）÷ NTM EBITDA（MarketScreener 共識 FY1／FY2 時間加權）
A58: pm_subs_spot | B58: 訂閱影音（Subscriptions, platforms, and devices）：Spotify（SPOT）NTM EV/EBITDA | C58: x | E58: 31.97 | G58: Derived | H58: legacy_v0.2/company.json valuation.segmentMultiples.subs（NFLX 為 NTM；SPOT、DIS 為 TTM，amazon/data 事實總帳） | I58: EV（StockAnalysis）÷ NTM EBITDA（MarketScreener 共識 FY1／FY2 時間加權）
A59: pm_subs_dis | B59: 訂閱影音（Subscriptions, platforms, and devices）：Disney（DIS）NTM EV/EBITDA | C59: x | E59: 10.58 | G59: Derived | H59: legacy_v0.2/company.json valuation.segmentMultiples.subs（NFLX 為 NTM；SPOT、DIS 為 TTM，amazon/data 事實總帳） | I59: EV（StockAnalysis）÷ NTM EBITDA（MarketScreener 共識 FY1／FY2 時間加權）
A60: pm_cloud_orcl | B60: 非 AI 雲端／軟體（Cloud 其他）：Oracle（ORCL）NTM EV/EBITDA | C60: x | E60: 9.49 | G60: Derived | H60: data/peers_cloud_20261008.json（C12；MAG 三家共用） | I60: EV（StockAnalysis）÷ NTM EBITDA（MarketScreener 共識 FY1／FY2 時間加權）
A61: pm_cloud_ibm | B61: 非 AI 雲端／軟體（Cloud 其他）：IBM（IBM）NTM EV/EBITDA | C61: x | E61: 12.51 | G61: Derived | H61: data/peers_cloud_20261008.json（C12；MAG 三家共用） | I61: EV（StockAnalysis）÷ NTM EBITDA（MarketScreener 共識 FY1／FY2 時間加權）
A62: pm_cloud_sap | B62: 非 AI 雲端／軟體（Cloud 其他）：SAP（SAP）NTM EV/EBITDA | C62: x | E62: 15.13 | G62: Derived | H62: data/peers_cloud_20261008.json（C12；MAG 三家共用） | I62: EV（StockAnalysis）÷ NTM EBITDA（MarketScreener 共識 FY1／FY2 時間加權）
... A67: pm_cloud_docn | B67: 非 AI 雲端／軟體（Cloud 其他）：DigitalOcean（DOCN）NTM EV/EBITDA | C67: x | E67: 24.49 | G67: Derived | H67: data/peers_cloud_20261008.json（C12；MAG 三家共用） | I67: EV（StockAnalysis）÷ NTM EBITDA（MarketScreener 共識 FY1／FY2 時間加權）
A68: mult_ai | B68: TPU 系統銷售的 EV/EBITDA；Cloud AI 同業倍數對照 | C68: x | D68: 4 | E68: 6 | F68: 10 | G68: Assumed | H68: 沿用 v0.2.2（legacy_v0.2/company.json） valuation.evEbitda（AI 基礎設施 6×；CRWV TTM 25×、ORCL NTM 9.5× 為對照，事實總帳 val.peer.aiInfra） | I68: 修正一 F3：Cloud AI 主值改用 AI 模組自身 DCF；本倍數版只作對照列
A69: mult_ads_own | B69: Alphabet 自身 NTM EV/EBITDA（Sens 用） | C69: x | E69: 14.68 | G69: Derived | H69: 事實總帳 val.googl.ownNtm（2026-10-07）
A70: ads_mode | B70: Search、YouTube、Alphabet 層級的倍數（0＝META；1＝六家廣告同業中位數；2＝Alphabet 自身） | C70: x | D70: 1 | E70: 0 | F70: 2 | G70: Assumed | H70: 修正一：小型廣告科技（PINS、TTD、APP、RDDT、SNAP）規模與護城河不可比 → 預設 META NTM 10.79×；Network 仍用六家中位數 | I70: Sens：中位數 9.11×／自身 14.68×
A71: ob_val | B71: Other Bets 分部加總價值 | C71: US$B | E71: 0 | G71: Assumed | H71: 修正一：Waymo 最近一輪估值未找到（2026-02 募資 16.0 已知；本次網路搜尋額度用盡）→ 分部加總以 0 計；DCF 仍含 Other Bets 虧損 | I71: 未找到：Waymo 2026 年募資估值
A72: D. 命題模組：AI 容量（沿用 v0.2.2；總 AI MW＝對外 MW ÷ 對外比例）
A73: ext_sh | B73: 對外比例（Google Cloud 客戶 MW ÷ AI 總 MW） | C73: % | D73: 0.25 | E73: 0.3 | F73: 0.4 | G73: Assumed | H73: 事實總帳 mw.extShare（v0.1a 區間 25%–40%） | I73: 沿用 v0.2.2（legacy_v0.2/company.json） capexModel.extShare；C23：公司未揭露，是最大不確定（Sens 另列 ±20pt）
A74: mw_tot0 | B74: AI 在役 IT MW（2026-06-30，自用＋對外） | C74: MW | D74: 5012 | E74: 6337 | F74: 7891 | G74: Derived | H74: Epoch AI〈AI Chip Owners〉資料集：cumulative by designer（CSV，2026-05-12 更新）（2026-05-12；事實總帳 mw.ai.it.2026q2） | I74: Epoch AI 晶片功耗 3,841 MW × IT/TDP 1.65；對外 1,901＝6,337 × 30%（沿用 v0.2.2（legacy_v0.2/company.json） defaults.billableOpen）
A75: mw_ye25 | B75: AI 在役 IT MW（2025-12-31） | C75: MW | E75: 4873 | G75: Derived | H75: Epoch AI〈AI Chip Owners〉資料集：cumulative by designer（CSV，2026-05-12 更新）（2026-05-12；事實總帳 mw.ai.it.epoch.2025q4） | I75: 對外 1,462（沿用 v0.2.2（legacy_v0.2/company.json） defaults.mwYearEnd 2025）÷ 30%
A76: mw_ye24 | B76: AI 在役 IT MW（2024-12-31；汰換用） | C76: MW | E76: 2143.3 | G76: Derived | H76: 沿用 v0.2.2（legacy_v0.2/company.json） defaults.mwYearEnd 2024 對外 643 ÷ 30%
A77: mw_ye23 | B77: AI 在役 IT MW（2023-12-31；汰換用） | C77: MW | E77: 636.7 | G77: Derived | H77: 沿用 v0.2.2（legacy_v0.2/company.json） defaults.mwYearEnd 2023 對外 191 ÷ 30%
A78: pace | B78: AI 總 MW 每年新增（三情境相同） | C78: MW/年 | D78: 2833.3 | E78: 4159.67 | F78: 6239.67 | G78: Derived | H78: 沿用 v0.2.2（legacy_v0.2/company.json）：對外速度 1,247.9 MW／年（C10：2026 資本支出指引中點 200B 解出，scripts/calib_pace.js）÷ 30% | I78: 低＝v0.2.2 保守 850 ÷ 30%（已公開在建）、高＝積極 1,871.9 ÷ 30%（1.5 × 基準）；本版不作情境軸（預設 1，見報告第 5 節），只列 Sens
A79: mix0_h | B79: 期初機隊：Hopper 錨（TPU v4／v5、H100／H200） | C79: % | E79: 0.25 | G79: Assumed | H79: 沿用 v0.2.2（legacy_v0.2/company.json） pricing.chips（TPU v4／v5 15%＋Hopper 10%） | I79: C2：TPU 以同期 NVIDIA 世代代理
A80: mix0_b2 | B80: 期初機隊：GB200 錨（Trillium v6e、GB200／B200） | C80: % | E80: 0.45 | G80: Assumed | H80: 沿用 v0.2.2（legacy_v0.2/company.json）（Trillium 35%＋GB200 10%） | I80: C2
A81: mix0_b3 | B81: 期初機隊：GB300 錨（Ironwood） | C81: % | E81: 0.3 | G81: Assumed | H81: 沿用 v0.2.2（legacy_v0.2/company.json）（Ironwood 30%） | I81: C2
A82: am_26 | B82: 2026 新增中 GB300 錨占比（Ironwood＋GB300；其餘 VR200 錨） | C82: % | E82: 1 | G82: Assumed | H82: 沿用 v0.2.2（legacy_v0.2/company.json）（2026 Ironwood 75%＋GB300 25%）
A83: am_28 | B83: 2028 起新增中 VR200 錨占比（下一代 TPU＋VR200；其餘 GB300 錨） | C83: % | E83: 1 | G83: Assumed | H83: 沿用 v0.2.2（legacy_v0.2/company.json）（2028 起下一代 TPU 75%＋VR200 25%）
A84: conv_mw | B84: FY2029 起 MW 新增速度收斂年數（到 FY2032 只剩 g × 期初 MW） | C84: 年 | E84: 4 | G84: Assumed | H84: 修正一 F5：終值不得落在建置高峰
A85: am_27 | B85: 2027 新增中 GB300 錨占比（Ironwood＋GB300；其餘 VR200 錨） | C85: % | E85: 0.5 | G85: Assumed | H85: 沿用 v0.2.2（legacy_v0.2/company.json）（2027 Ironwood 40%＋GB300 10%） | I85: 2026 新增全為 GB300 錨（Ironwood 75%＋GB300 25%）；2028 起全為 VR200 錨（下一代 TPU＋VR200）
A86: tpu_sh | B86: TPU 占 AI MW 比例 | C86: % | E86: 0.75 | G86: Derived | H86: Epoch 2025 年新增功耗 TPU 約 77%（沿用 v0.2.2（legacy_v0.2/company.json） pricing.mixNote） | I86: 只在 TPU 係數不等於 1 時有作用
A87: tpu_f | B87: TPU 每 MW 收入錨係數（相對同期 NVIDIA 世代） | C87: x | D87: 0.7 | E87: 1 | F87: 1 | G87: Assumed | H87: C2：基準 × 1.0、敏感度 × 0.7（沿用 v0.2.2（legacy_v0.2/company.json） pricing.customFactor） | I87: Tokenomics v21.4 NonNV（IF_NonNV_Hold_TPU 0.8）只登錄、不切換（工作單：Tokenomics 本版維持 v21.4）
A88: tpu_cf | B88: TPU 每 MW IT 資本支出係數 | C88: x | D88: 0.7 | E88: 1 | F88: 1 | G88: Assumed | H88: 沿用 v0.2.2（legacy_v0.2/company.json） pricing.customCapexFactor | I88: 雙邊敏感度時與 tpu_f 同乘 0.7
A89: E. 命題模組：每 MW 價格（k＝證據價格 ÷ Tokenomics 同世代成本；沿用 v0.2.2 kspec.py）
A90: kl_px | B90: 長約證據價格（判斷倍數 0.75 × v5.27 VR200 12.762） | C90: US$m/MW-年 | D90: 7.6572 | E90: 9.5715 | G90: Assumed | H90: legacy_v0.2/company.json pricing.kEvidence long.base／long.low（data/kevidence_alphabet_20261008.json kspecInputs） | I90: 不是觀察到的市場價格；分母＝VR200 IF_HoldEcon
A91: ks_px | B91: 現貨證據價格（Silicon Data H100 指數） | C91: US$/GPU-hr | E91: 2.82 | F91: 4.858 | G91: Verified | H91: Silicon Data H100 Index（2026-10-06）https://www.silicondata.com/products/silicon-index/h100；高＝GCP a3-highgpu-8g 3 年預留 4.858（Interested-party） | I91: 分母＝IF_GPUhrEcon｜H100；C1 三家一致
A92: long_sh | B92: 長約占比 | C92: % | D92: 0.4 | E92: 0.6 | F92: 0.8 | G92: Assumed | H92: 沿用 v0.2.2（legacy_v0.2/company.json） pricing.longShare（Cloud 積壓以多年期大客戶為主）
A93: he_h | B93: IF_HoldEcon｜H100（每 MW 年持有成本，經濟口徑） | C93: US$m/MW-年 | D93: 6.7910747 | E93: 9.7030873 | F93: 16.66377 | G93: Derived | H93: data/tokenomics_snapshot_v21.4.json（20261024_Tokenomics_v21.4.xlsx，Interface!C13:Q13） | I93: Tokenomics WACC 10% 下的打平持有成本；收入端不乘 IF_Util（MW-year 計價）
A94: he_b2 | B94: IF_HoldEcon｜GB200（每 MW 年持有成本，經濟口徑） | C94: US$m/MW-年 | D94: 6.6118163 | E94: 8.8281656 | F94: 14.318575 | G94: Derived | H94: data/tokenomics_snapshot_v21.4.json（20261024_Tokenomics_v21.4.xlsx，Interface!C13:Q13） | I94: Tokenomics WACC 10% 下的打平持有成本；收入端不乘 IF_Util（MW-year 計價）
A95: he_b3 | B95: IF_HoldEcon｜GB300（每 MW 年持有成本，經濟口徑） | C95: US$m/MW-年 | D95: 8.4288991 | E95: 10.886411 | F95: 18.534646 | G95: Derived | H95: data/tokenomics_snapshot_v21.4.json（20261024_Tokenomics_v21.4.xlsx，Interface!C13:Q13） | I95: Tokenomics WACC 10% 下的打平持有成本；收入端不乘 IF_Util（MW-year 計價）
A96: he_vr | B96: IF_HoldEcon｜VR200（每 MW 年持有成本，經濟口徑） | C96: US$m/MW-年 | D96: 9.2190715 | E96: 12.225471 | F96: 19.750627 | G96: Derived | H96: data/tokenomics_snapshot_v21.4.json（20261024_Tokenomics_v21.4.xlsx，Interface!C13:Q13） | I96: Tokenomics WACC 10% 下的打平持有成本；收入端不乘 IF_Util（MW-year 計價）
A97: gpuhr_h | B97: IF_GPUhrEcon｜H100 | C97: US$/GPU-hr | E97: 1.5425965 | G97: Derived | H97: data/tokenomics_snapshot_v21.4.json
A98: opx_h | B98: IF_OpexGW｜H100（每 MW 年營運費用，不含折舊） | C98: US$m/MW-年 | E98: 1.8846675 | G98: Derived | H98: data/tokenomics_snapshot_v21.4.json
A99: opx_b2 | B99: IF_OpexGW｜GB200（每 MW 年營運費用，不含折舊） | C99: US$m/MW-年 | E99: 1.8122327 | G99: Derived | H99: data/tokenomics_snapshot_v21.4.json
A100: opx_b3 | B100: IF_OpexGW｜GB300（每 MW 年營運費用，不含折舊） | C100: US$m/MW-年 | E100: 1.9826348 | G100: Derived | H100: data/tokenomics_snapshot_v21.4.json
A101: opx_vr | B101: IF_OpexGW｜VR200（每 MW 年營運費用，不含折舊） | C101: US$m/MW-年 | E101: 2.0934955 | G101: Derived | H101: data/tokenomics_snapshot_v21.4.json
A102: cit_h | B102: IF_CapexIT｜H100（每 MW IT 資本支出） | C102: US$m/MW | E102: 27.510214 | G102: Derived | H102: data/tokenomics_snapshot_v21.4.json
A103: cit_b2 | B103: IF_CapexIT｜GB200（每 MW IT 資本支出） | C103: US$m/MW | E103: 24.015174 | G103: Derived | H103: data/tokenomics_snapshot_v21.4.json
A104: cit_b3 | B104: IF_CapexIT｜GB300（每 MW IT 資本支出） | C104: US$m/MW | E104: 32.237224 | G104: Derived | H104: data/tokenomics_snapshot_v21.4.json
...

Sheet Q
A1: Q — 實績（US$B；EPS 美元；股數十億股）。資料取自 data/alphabet_facts_20261008.json（MAG v0.1a 起的 SEC 一手資料；季度數＝財報新聞稿 [Interested-party，10-Q 核閱]，年度＝10-K [Verified]）
A2: 核對列（實績必須為 0）：產品線合計＝Google Services、分部合計＝合併營收、分部營業利益合計＝合併營業利益（Alphabet-level activities 含避險損益營收與未分攤費用）、營收 − 成本費用＝營業利益、FY2025 四季合計＝年報
A3: 項目 | B3: 2024Q3 | C3: 2024Q4 | D3: 2025Q1 | E3: 2025Q2 | F3: 2025Q3 | G3: 2025Q4 | H3: 2026Q1 | I3: 2026Q2 | J3: FY2024 | K3: FY2025 | L3: 1H26 | M3: 近四季 TTM | N3: 前四季 | O3: 標記 | P3: 來源
A4: 營收（官方分部與產品線）
A5: Google Search & other | B5: 49.385 | C5: 54.034 | D5: 50.702 | E5: 54.19 | F5: 56.567 | G5: 63.073 | H5: 60.399 | I5: 63.271 | J5: 198.084 | K5: 224.532 | L5: =H5+I5 -> 123.67 | M5: =SUM(F5:I5) -> 243.31 | N5: =SUM(B5:E5) -> 208.311 | O5: Verified（年）／Interested-party（季） | P5: 季：Alphabet 財報新聞稿（8-K 附件 99.1，各季；事實總帳 is.*.2024q3–2026q2）；年：Form 10-K FY2024、FY2025（經查核）；例：2026Q2 https://www.sec.gov/Archives/edgar/data/1652044/000165204426000066/googexhibit991q22026.htm
A6: YouTube ads | B6: 8.921 | C6: 10.473 | D6: 8.927 | E6: 9.796 | F6: 10.261 | G6: 11.383 | H6: 9.883 | I6: 11.055 | J6: 36.147 | K6: 40.367 | L6: =H6+I6 -> 20.938 | M6: =SUM(F6:I6) -> 42.582 | N6: =SUM(B6:E6) -> 38.117 | O6: Verified（年）／Interested-party（季） | P6: 季：Alphabet 財報新聞稿（8-K 附件 99.1，各季；事實總帳 is.*.2024q3–2026q2）；年：Form 10-K FY2024、FY2025（經查核）；例：2026Q2 https://www.sec.gov/Archives/edgar/data/1652044/000165204426000066/googexhibit991q22026.htm
A7: Google Network | B7: 7.548 | C7: 7.954 | D7: 7.256 | E7: 7.354 | F7: 7.354 | G7: 7.828 | H7: 6.971 | I7: 7.303 | J7: 30.359 | K7: 29.792 | L7: =H7+I7 -> 14.274 | M7: =SUM(F7:I7) -> 29.456 | N7: =SUM(B7:E7) -> 30.112 | O7: Verified（年）／Interested-party（季） | P7: 季：Alphabet 財報新聞稿（8-K 附件 99.1，各季；事實總帳 is.*.2024q3–2026q2）；年：Form 10-K FY2024、FY2025（經查核）；例：2026Q2 https://www.sec.gov/Archives/edgar/data/1652044/000165204426000066/googexhibit991q22026.htm
A8: Google subscriptions, platforms, and devices | B8: 10.656 | C8: 11.633 | D8: 10.379 | E8: 11.203 | F8: 12.87 | G8: 13.578 | H8: 12.384 | I8: 12.911 | J8: 40.34 | K8: 48.03 | L8: =H8+I8 -> 25.295 | M8: =SUM(F8:I8) -> 51.743 | N8: =SUM(B8:E8) -> 43.871 | O8: Verified（年）／Interested-party（季） | P8: 季：Alphabet 財報新聞稿（8-K 附件 99.1，各季；事實總帳 is.*.2024q3–2026q2）；年：Form 10-K FY2024、FY2025（經查核）；例：2026Q2 https://www.sec.gov/Archives/edgar/data/1652044/000165204426000066/googexhibit991q22026.htm
A9: Google Services（分部） | B9: 76.51 | C9: 84.094 | D9: 77.264 | E9: 82.543 | F9: 87.052 | G9: 95.862 | H9: 89.637 | I9: 94.54 | J9: 304.93 | K9: 342.721 | L9: =H9+I9 -> 184.177 | M9: =SUM(F9:I9) -> 367.091 | N9: =SUM(B9:E9) -> 320.411 | O9: Verified（年）／Interested-party（季） | P9: 季：Alphabet 財報新聞稿（8-K 附件 99.1，各季；事實總帳 is.*.2024q3–2026q2）；年：Form 10-K FY2024、FY2025（經查核）；例：2026Q2 https://www.sec.gov/Archives/edgar/data/1652044/000165204426000066/googexhibit991q22026.htm
A10: 檢查：產品線合計 − Google Services | B10: =B5+B6+B7+B8-B9 -> 0 | C10: =C5+C6+C7+C8-C9 -> 0 | D10: =D5+D6+D7+D8-D9 -> 0 | E10: =E5+E6+E7+E8-E9 -> 0 | F10: =F5+F6+F7+F8-F9 -> 0 | G10: =G5+G6+G7+G8-G9 -> 0 | H10: =H5+H6+H7+H8-H9 -> 0 | I10: =I5+I6+I7+I8-I9 -> 0 | ... K10: =K5+K6+K7+K8-K9 -> 0 | L10: =H10+I10 -> 0 | M10: =SUM(F10:I10) -> 0 | N10: =SUM(B10:E10) -> 0 | O10: — | P10: —
A11: Google Cloud（分部） | B11: 11.353 | C11: 11.955 | D11: 12.26 | E11: 13.624 | F11: 15.157 | G11: 17.664 | H11: 20.028 | I11: 24.768 | J11: 43.229 | K11: 58.705 | L11: =H11+I11 -> 44.796 | M11: =SUM(F11:I11) -> 77.617 | N11: =SUM(B11:E11) -> 49.192 | O11: Verified（年）／Interested-party（季） | P11: 季：Alphabet 財報新聞稿（8-K 附件 99.1，各季；事實總帳 is.*.2024q3–2026q2）；年：Form 10-K FY2024、FY2025（經查核）；例：2026Q2 https://www.sec.gov/Archives/edgar/data/1652044/000165204426000066/googexhibit991q22026.htm
A12: Other Bets（分部） | B12: 0.388 | C12: 0.4 | D12: 0.45 | E12: 0.373 | F12: 0.344 | G12: 0.37 | H12: 0.411 | I12: 0.382 | J12: 1.648 | K12: 1.537 | L12: =H12+I12 -> 0.793 | M12: =SUM(F12:I12) -> 1.507 | N12: =SUM(B12:E12) -> 1.611 | O12: Verified（年）／Interested-party（季） | P12: 季：Alphabet 財報新聞稿（8-K 附件 99.1，各季；事實總帳 is.*.2024q3–2026q2）；年：Form 10-K FY2024、FY2025（經查核）；例：2026Q2 https://www.sec.gov/Archives/edgar/data/1652044/000165204426000066/googexhibit991q22026.htm
A13: Hedging gains (losses)（Alphabet-level） | B13: 0.017 | C13: 0.02 | D13: 0.26 | E13: -0.112 | F13: -0.207 | G13: -0.068 | H13: -0.18 | I13: 0.106 | J13: 0.211 | K13: -0.127 | L13: =H13+I13 -> -0.074 | M13: =SUM(F13:I13) -> -0.349 | N13: =SUM(B13:E13) -> 0.185 | O13: Verified（年）／Interested-party（季） | P13: 季：Alphabet 財報新聞稿（8-K 附件 99.1，各季；事實總帳 is.*.2024q3–2026q2）；年：Form 10-K FY2024、FY2025（經查核）；例：2026Q2 https://www.sec.gov/Archives/edgar/data/1652044/000165204426000066/googexhibit991q22026.htm
A14: 合併營收 | B14: 88.268 | C14: 96.469 | D14: 90.234 | E14: 96.428 | F14: 102.346 | G14: 113.828 | H14: 109.896 | I14: 119.796 | J14: 350.018 | K14: 402.836 | L14: =H14+I14 -> 229.692 | M14: =SUM(F14:I14) -> 445.866 | N14: =SUM(B14:E14) -> 371.399 | O14: Verified（年）／Interested-party（季） | P14: 季：Alphabet 財報新聞稿（8-K 附件 99.1，各季；事實總帳 is.*.2024q3–2026q2）；年：Form 10-K FY2024、FY2025（經查核）；例：2026Q2 https://www.sec.gov/Archives/edgar/data/1652044/000165204426000066/googexhibit991q22026.htm
A15: 檢查：分部合計＋避險 − 合併營收 | B15: =B9+B11+B12+B13-B14 -> 0 | C15: =C9+C11+C12+C13-C14 -> 0 | D15: =D9+D11+D12+D13-D14 -> 0 | E15: =E9+E11+E12+E13-E14 -> 0 | F15: =F9+F11+F12+F13-F14 -> 0 | G15: =G9+G11+G12+G13-G14 -> 0 | H15: =H9+H11+H12+H13-H14 -> 0 | I15: =I9+I11+I12+I13-I14 -> 0 | ... K15: =K9+K11+K12+K13-K14 -> 0 | L15: =H15+I15 -> 0 | M15: =SUM(F15:I15) -> 0 | N15: =SUM(B15:E15) -> 0 | O15: — | P15: —
A17: 分部營業利益
A18: Google Services 營業利益 | B18: 30.856 | C18: 32.836 | D18: 32.682 | E18: 33.063 | F18: 33.527 | G18: 40.132 | H18: 40.589 | I18: 39.544 | J18: 121.263 | K18: 139.404 | L18: =H18+I18 -> 80.133 | M18: =SUM(F18:I18) -> 153.792 | N18: =SUM(B18:E18) -> 129.437 | O18: Verified（年）／Interested-party（季） | P18: 季：Alphabet 財報新聞稿（8-K 附件 99.1，各季；事實總帳 is.*.2024q3–2026q2）；年：Form 10-K FY2024、FY2025（經查核）；例：2026Q2 https://www.sec.gov/Archives/edgar/data/1652044/000165204426000066/googexhibit991q22026.htm
A19: Google Cloud 營業利益 | B19: 1.947 | C19: 2.093 | D19: 2.177 | E19: 2.826 | F19: 3.594 | G19: 5.313 | H19: 6.598 | I19: 8.814 | J19: 6.112 | K19: 13.91 | L19: =H19+I19 -> 15.412 | M19: =SUM(F19:I19) -> 24.319 | N19: =SUM(B19:E19) -> 9.043 | O19: Verified（年）／Interested-party（季） | P19: 季：Alphabet 財報新聞稿（8-K 附件 99.1，各季；事實總帳 is.*.2024q3–2026q2）；年：Form 10-K FY2024、FY2025（經查核）；例：2026Q2 https://www.sec.gov/Archives/edgar/data/1652044/000165204426000066/googexhibit991q22026.htm
A20: Other Bets 營業利益 | B20: -1.116 | C20: -1.174 | D20: -1.226 | E20: -1.246 | F20: -1.426 | G20: -3.617 | H20: -2.1 | I20: -1.799 | J20: -4.444 | K20: -7.515 | L20: =H20+I20 -> -3.899 | M20: =SUM(F20:I20) -> -8.942 | N20: =SUM(B20:E20) -> -4.762 | O20: Verified（年）／Interested-party（季） | P20: 季：Alphabet 財報新聞稿（8-K 附件 99.1，各季；事實總帳 is.*.2024q3–2026q2）；年：Form 10-K FY2024、FY2025（經查核）；例：2026Q2 https://www.sec.gov/Archives/edgar/data/1652044/000165204426000066/googexhibit991q22026.htm
A21: Alphabet-level activities（避險營收 − 未分攤費用） | B21: -3.166 | C21: -2.783 | D21: -3.027 | E21: -3.372 | F21: -4.467 | G21: -5.894 | H21: -5.391 | I21: -5.789 | J21: -10.541 | K21: -16.76 | L21: =H21+I21 -> -11.18 | M21: =SUM(F21:I21) -> -21.541 | N21: =SUM(B21:E21) -> -12.348 | O21: Verified（年）／Interested-party（季） | P21: 季：Alphabet 財報新聞稿（8-K 附件 99.1，各季；事實總帳 is.*.2024q3–2026q2）；年：Form 10-K FY2024、FY2025（經查核）；例：2026Q2 https://www.sec.gov/Archives/edgar/data/1652044/000165204426000066/googexhibit991q22026.htm
A22: 合併營業利益 | B22: 28.521 | C22: 30.972 | D22: 30.606 | E22: 31.271 | F22: 31.228 | G22: 35.934 | H22: 39.696 | I22: 40.77 | J22: 112.39 | K22: 129.039 | L22: =H22+I22 -> 80.466 | M22: =SUM(F22:I22) -> 147.628 | N22: =SUM(B22:E22) -> 121.37 | O22: Verified（年）／Interested-party（季） | P22: 季：Alphabet 財報新聞稿（8-K 附件 99.1，各季；事實總帳 is.*.2024q3–2026q2）；年：Form 10-K FY2024、FY2025（經查核）；例：2026Q2 https://www.sec.gov/Archives/edgar/data/1652044/000165204426000066/googexhibit991q22026.htm
A23: 檢查：分部營業利益合計 − 合併營業利益 | B23: =B18+B19+B20+B21-B22 -> 0 | C23: =C18+C19+C20+C21-C22 -> 0 | D23: =D18+D19+D20+D21-D22 -> 0 | E23: =E18+E19+E20+E21-E22 -> 0 | F23: =F18+F19+F20+F21-F22 -> 0 | G23: =G18+G19+G20+G21-G22 -> 0 | H23: =H18+H19+H20+H21-H22 -> 0 | I23: =I18+I19+I20+I21-I22 -> 0 | ... K23: =K18+K19+K20+K21-K22 -> 0 | L23: =H23+I23 -> 0 | M23: =SUM(F23:I23) -> 0 | N23: =SUM(B23:E23) -> 0 | O23: — | P23: —
A25: 合併損益
A26: 營業成本 | B26: 36.474 | C26: 40.613 | D26: 36.361 | E26: 39.039 | F26: 41.369 | G26: 45.766 | H26: 41.271 | I26: 45.943 | J26: 146.306 | K26: 162.535 | L26: =H26+I26 -> 87.214 | M26: =SUM(F26:I26) -> 174.349 | N26: =SUM(B26:E26) -> 152.487 | O26: Verified（年）／Interested-party（季） | P26: 季：Alphabet 財報新聞稿（8-K 附件 99.1，各季；事實總帳 is.*.2024q3–2026q2）；年：Form 10-K FY2024、FY2025（經查核）；例：2026Q2 https://www.sec.gov/Archives/edgar/data/1652044/000165204426000066/googexhibit991q22026.htm
A27: 其中：流量獲取成本 TAC | B27: 13.719 | C27: 14.848 | D27: 13.748 | E27: 14.705 | F27: 14.876 | G27: 16.597 | H27: 15.228 | I27: 16.179 | L27: =H27+I27 -> 31.407 | M27: =SUM(F27:I27) -> 62.88 | N27: =SUM(B27:E27) -> 57.02 | O27: Verified（年）／Interested-party（季） | P27: 季：Alphabet 財報新聞稿（8-K 附件 99.1，各季；事實總帳 is.*.2024q3–2026q2）；年：Form 10-K FY2024、FY2025（經查核）；例：2026Q2 https://www.sec.gov/Archives/edgar/data/1652044/000165204426000066/googexhibit991q22026.htm
A28: 研發費用 | B28: 12.447 | C28: 13.116 | D28: 13.556 | E28: 13.808 | F28: 15.151 | G28: 18.572 | H28: 17.032 | I28: 18.219 | J28: 49.326 | K28: 61.087 | L28: =H28+I28 -> 35.251 | M28: =SUM(F28:I28) -> 68.974 | N28: =SUM(B28:E28) -> 52.927 | O28: Verified（年）／Interested-party（季） | P28: 季：Alphabet 財報新聞稿（8-K 附件 99.1，各季；事實總帳 is.*.2024q3–2026q2）；年：Form 10-K FY2024、FY2025（經查核）；例：2026Q2 https://www.sec.gov/Archives/edgar/data/1652044/000165204426000066/googexhibit991q22026.htm
A29: 行銷費用 | B29: 7.227 | C29: 7.363 | D29: 6.172 | E29: 7.101 | F29: 7.205 | G29: 8.215 | H29: 7.606 | I29: 8.403 | J29: 27.808 | K29: 28.693 | L29: =H29+I29 -> 16.009 | M29: =SUM(F29:I29) -> 31.429 | N29: =SUM(B29:E29) -> 27.863 | O29: Verified（年）／Interested-party（季） | P29: 季：Alphabet 財報新聞稿（8-K 附件 99.1，各季；事實總帳 is.*.2024q3–2026q2）；年：Form 10-K FY2024、FY2025（經查核）；例：2026Q2 https://www.sec.gov/Archives/edgar/data/1652044/000165204426000066/googexhibit991q22026.htm
A30: 管理費用 | B30: 3.599 | C30: 4.405 | D30: 3.539 | E30: 5.209 | F30: 7.393 | G30: 5.341 | H30: 4.291 | I30: 6.461 | J30: 14.188 | K30: 21.482 | L30: =H30+I30 -> 10.752 | M30: =SUM(F30:I30) -> 23.486 | N30: =SUM(B30:E30) -> 16.752 | O30: Verified（年）／Interested-party（季） | P30: 季：Alphabet 財報新聞稿（8-K 附件 99.1，各季；事實總帳 is.*.2024q3–2026q2）；年：Form 10-K FY2024、FY2025（經查核）；例：2026Q2 https://www.sec.gov/Archives/edgar/data/1652044/000165204426000066/googexhibit991q22026.htm
A31: 檢查：營收 − 成本費用 − 營業利益 | B31: =B14-B26-B28-B29-B30-B22 -> 0 | C31: =C14-C26-C28-C29-C30-C22 -> 0 | D31: =D14-D26-D28-D29-D30-D22 -> 0 | E31: =E14-E26-E28-E29-E30-E22 -> 0 | F31: =F14-F26-F28-F29-F30-F22 -> 0 | G31: =G14-G26-G28-G29-G30-G22 -> 0 | H31: =H14-H26-H28-H29-H30-H22 -> 0 | I31: =I14-I26-I28-I29-I30-I22 -> 0 | ... K31: =K14-K26-K28-K29-K30-K22 -> 0 | L31: =H31+I31 -> 0 | M31: =SUM(F31:I31) -> 0 | N31: =SUM(B31:E31) -> 0 | O31: — | P31: —
A32: 其他收益淨額（含權益證券損益） | B32: 3.185 | C32: 1.271 | D32: 11.183 | E32: 2.662 | F32: 12.759 | G32: 3.183 | H32: 37.716 | I32: 97.983 | J32: 7.425 | K32: 29.787 | L32: =H32+I32 -> 135.699 | M32: =SUM(F32:I32) -> 151.641 | N32: =SUM(B32:E32) -> 18.301 | O32: Verified（年）／Interested-party（季） | P32: 季：Alphabet 財報新聞稿（8-K 附件 99.1，各季；事實總帳 is.*.2024q3–2026q2）；年：Form 10-K FY2024、FY2025（經查核）；例：2026Q2 https://www.sec.gov/Archives/edgar/data/1652044/000165204426000066/googexhibit991q22026.htm
A33: 其中：權益證券淨損益 | B33: 1.821 | C33: 0.364 | D33: 9.758 | E33: 1.286 | F33: 10.734 | G33: 2.302 | H33: 36.915 | I33: 99.031 | L33: =H33+I33 -> 135.946 | M33: =SUM(F33:I33) -> 148.982 | N33: =SUM(B33:E33) -> 13.229 | O33: Verified（年）／Interested-party（季） | P33: 季：Alphabet 財報新聞稿（8-K 附件 99.1，各季；事實總帳 is.*.2024q3–2026q2）；年：Form 10-K FY2024、FY2025（經查核）；例：2026Q2 https://www.sec.gov/Archives/edgar/data/1652044/000165204426000066/googexhibit991q22026.htm
A34: 稅前利益 | B34: 31.706 | C34: 32.243 | D34: 41.789 | E34: 33.933 | F34: 43.987 | G34: 39.117 | H34: 77.412 | I34: 138.753 | J34: 119.815 | K34: 158.826 | L34: =H34+I34 -> 216.165 | M34: =SUM(F34:I34) -> 299.269 | N34: =SUM(B34:E34) -> 139.671 | O34: Verified（年）／Interested-party（季） | P34: 季：Alphabet 財報新聞稿（8-K 附件 99.1，各季；事實總帳 is.*.2024q3–2026q2）；年：Form 10-K FY2024、FY2025（經查核）；例：2026Q2 https://www.sec.gov/Archives/edgar/data/1652044/000165204426000066/googexhibit991q22026.htm
A35: 檢查：營業利益＋其他收益 − 稅前利益 | B35: =B22+B32-B34 -> 0 | C35: =C22+C32-C34 -> 0 | D35: =D22+D32-D34 -> 0 | E35: =E22+E32-E34 -> 0 | F35: =F22+F32-F34 -> 0 | G35: =G22+G32-G34 -> 0 | H35: =H22+H32-H34 -> 0 | I35: =I22+I32-I34 -> 0 | ... K35: =K22+K32-K34 -> 0 | L35: =H35+I35 -> 0 | M35: =SUM(F35:I35) -> 0 | N35: =SUM(B35:E35) -> 0 | O35: — | P35: —
A36: 所得稅 | B36: 5.405 | C36: 5.707 | D36: 7.249 | E36: 5.737 | F36: 9.008 | G36: 4.662 | H36: 14.834 | I36: 26.56 | J36: 19.697 | K36: 26.656 | L36: =H36+I36 -> 41.394 | M36: =SUM(F36:I36) -> 55.064 | N36: =SUM(B36:E36) -> 24.098 | O36: Verified（年）／Interested-party（季） | P36: 季：Alphabet 財報新聞稿（8-K 附件 99.1，各季；事實總帳 is.*.2024q3–2026q2）；年：Form 10-K FY2024、FY2025（經查核）；例：2026Q2 https://www.sec.gov/Archives/edgar/data/1652044/000165204426000066/googexhibit991q22026.htm
A37: 淨利 | B37: 26.301 | C37: 26.536 | D37: 34.54 | E37: 28.196 | F37: 34.979 | G37: 34.455 | H37: 62.578 | I37: 112.193 | J37: 100.118 | K37: 132.17 | L37: =H37+I37 -> 174.771 | M37: =SUM(F37:I37) -> 244.205 | N37: =SUM(B37:E37) -> 115.573 | O37: Verified（年）／Interested-party（季） | P37: 季：Alphabet 財報新聞稿（8-K 附件 99.1，各季；事實總帳 is.*.2024q3–2026q2）；年：Form 10-K FY2024、FY2025（經查核）；例：2026Q2 https://www.sec.gov/Archives/edgar/data/1652044/000165204426000066/googexhibit991q22026.htm
A38: 檢查：稅前 − 所得稅 − 淨利 | B38: =B34-B36-B37 -> 0 | C38: =C34-C36-C37 -> 0 | D38: =D34-D36-D37 -> 0 | E38: =E34-E36-E37 -> 0 | F38: =F34-F36-F37 -> 0 | G38: =G34-G36-G37 -> 0 | H38: =H34-H36-H37 -> 0 | I38: =I34-I36-I37 -> 0 | ... K38: =K34-K36-K37 -> 0 | L38: =H38+I38 -> 0 | M38: =SUM(F38:I38) -> 0 | N38: =SUM(B38:E38) -> 0 | O38: — | P38: —
A39: 稀釋加權股數（十億股） | B39: 12.419 | C39: 12.348 | D39: 12.291 | E39: 12.198 | F39: 12.203 | G39: 12.228 | H39: 12.238 | I39: 12.309 | J39: 12.447 | K39: 12.23 | L39: =AVERAGE(H39:I39) -> 12.2735 | O39: Verified（年）／Interested-party（季） | P39: 季：Alphabet 財報新聞稿（8-K 附件 99.1，各季；事實總帳 is.*.2024q3–2026q2）；年：Form 10-K FY2024、FY2025（經查核）；例：2026Q2 https://www.sec.gov/Archives/edgar/data/1652044/000165204426000066/googexhibit991q22026.htm
A40: EPS（GAAP 稀釋，美元） | B40: 2.12 | C40: 2.15 | D40: 2.81 | E40: 2.31 | F40: 2.87 | G40: 2.82 | H40: 5.11 | I40: 9.11 | J40: 8.04 | K40: 10.81 | L40: =H40+I40 -> 14.22 | M40: =SUM(F40:I40) -> 19.91 | N40: =SUM(B40:E40) -> 9.39 | O40: Verified（年）／Interested-party（季） | P40: 季：Alphabet 財報新聞稿（8-K 附件 99.1，各季；事實總帳 is.*.2024q3–2026q2）；年：Form 10-K FY2024、FY2025（經查核）；例：2026Q2 https://www.sec.gov/Archives/edgar/data/1652044/000165204426000066/googexhibit991q22026.htm
A42: 現金流、資本支出與股東回饋
A43: 折舊（不動產與設備） | B43: 3.985 | C43: 4.205 | D43: 4.487 | E43: 4.998 | F43: 5.611 | G43: 6.04 | H43: 6.482 | I43: 7.104 | J43: 15.311 | K43: 21.136 | L43: =H43+I43 -> 13.586 | M43: =SUM(F43:I43) -> 25.237 | N43: =SUM(B43:E43) -> 17.675 | O43: Verified（年）／Interested-party（季） | P43: 季：Alphabet 財報新聞稿（8-K 附件 99.1，各季；事實總帳 is.*.2024q3–2026q2）；年：Form 10-K FY2024、FY2025（經查核）；例：2026Q2 https://www.sec.gov/Archives/edgar/data/1652044/000165204426000066/googexhibit991q22026.htm
A44: 股權報酬（SBC） | B44: 5.846 | C44: 5.81 | D44: 5.516 | E44: 5.998 | F44: 6.368 | G44: 7.071 | H44: 6.751 | I44: 7.957 | J44: 22.785 | K44: 24.953 | L44: =H44+I44 -> 14.708 | M44: =SUM(F44:I44) -> 28.147 | N44: =SUM(B44:E44) -> 23.17 | O44: Verified（年）／Interested-party（季） | P44: 季：Alphabet 財報新聞稿（8-K 附件 99.1，各季；事實總帳 is.*.2024q3–2026q2）；年：Form 10-K FY2024、FY2025（經查核）；例：2026Q2 https://www.sec.gov/Archives/edgar/data/1652044/000165204426000066/googexhibit991q22026.htm
A45: 營運現金流 | B45: 30.698 | C45: 39.113 | D45: 36.15 | E45: 27.747 | F45: 48.414 | G45: 52.402 | H45: 45.79 | I45: 39.069 | J45: 125.299 | K45: 164.713 | L45: =H45+I45 -> 84.859 | M45: =SUM(F45:I45) -> 185.675 | N45: =SUM(B45:E45) -> 133.708 | O45: Verified（年）／Interested-party（季） | P45: 季：Alphabet 財報新聞稿（8-K 附件 99.1，各季；事實總帳 is.*.2024q3–2026q2）；年：Form 10-K FY2024、FY2025（經查核）；例：2026Q2 https://www.sec.gov/Archives/edgar/data/1652044/000165204426000066/googexhibit991q22026.htm
A46: 資本支出（購置不動產與設備） | B46: 13.061 | C46: 14.276 | D46: 17.197 | E46: 22.446 | F46: 23.953 | G46: 27.851 | H46: 35.674 | I46: 44.924 | J46: 52.535 | K46: 91.447 | L46: =H46+I46 -> 80.598 | M46: =SUM(F46:I46) -> 132.402 | N46: =SUM(B46:E46) -> 66.98 | O46: Verified（年）／Interested-party（季） | P46: 季：Alphabet 財報新聞稿（8-K 附件 99.1，各季；事實總帳 is.*.2024q3–2026q2）；年：Form 10-K FY2024、FY2025（經查核）；例：2026Q2 https://www.sec.gov/Archives/edgar/data/1652044/000165204426000066/googexhibit991q22026.htm
A47: 自由現金流（公司定義：營運現金流 − 資本支出） | B47: 17.637 | C47: 24.837 | D47: 18.953 | E47: 5.301 | F47: 24.461 | G47: 24.551 | H47: 10.116 | I47: -5.855 | J47: 72.764 | K47: 73.266 | L47: =H47+I47 -> 4.261 | M47: =SUM(F47:I47) -> 53.273 | N47: =SUM(B47:E47) -> 66.728 | O47: Verified（年）／Interested-party（季） | P47: 季：Alphabet 財報新聞稿（8-K 附件 99.1，各季；事實總帳 is.*.2024q3–2026q2）；年：Form 10-K FY2024、FY2025（經查核）；例：2026Q2 https://www.sec.gov/Archives/edgar/data/1652044/000165204426000066/googexhibit991q22026.htm
A48: 檢查：營運現金流 − 資本支出 − 自由現金流 | B48: =B45-B46-B47 -> 0 | C48: =C45-C46-C47 -> 0 | D48: =D45-D46-D47 -> 0 | E48: =E45-E46-E47 -> 0 | F48: =F45-F46-F47 -> 0 | G48: =G45-G46-G47 -> 0 | H48: =H45-H46-H47 -> 0 | I48: =I45-I46-I47 -> 0 | ... K48: =K45-K46-K47 -> 0 | L48: =H48+I48 -> 0 | M48: =SUM(F48:I48) -> 0 | N48: =SUM(B48:E48) -> 0 | O48: — | P48: —
A49: 回購 | B49: 15.291 | C49: 15.551 | D49: 15.068 | E49: 13.238 | F49: 11.504 | G49: 5.499 | H49: 0 | I49: 0 | J49: 62.222 | K49: 45.709 | L49: =H49+I49 -> 0 | M49: =SUM(F49:I49) -> 17.003 | N49: =SUM(B49:E49) -> 59.148 | O49: Verified（年）／Interested-party（季） | P49: 季：Alphabet 財報新聞稿（8-K 附件 99.1，各季；事實總帳 is.*.2024q3–2026q2）；年：Form 10-K FY2024、FY2025（經查核）；例：2026Q2 https://www.sec.gov/Archives/edgar/data/1652044/000165204426000066/googexhibit991q22026.htm
A50: 普通股股利 | B50: 2.455 | C50: 2.442 | D50: 2.434 | E50: 2.543 | F50: 2.537 | G50: 2.536 | H50: 2.542 | I50: 2.689 | J50: 7.363 | K50: 10.049 | L50: =H50+I50 -> 5.231 | M50: =SUM(F50:I50) -> 10.304 | N50: =SUM(B50:E50) -> 9.874 | O50: Verified（年）／Interested-party（季） | P50: 季：Alphabet 財報新聞稿（8-K 附件 99.1，各季；事實總帳 is.*.2024q3–2026q2）；年：Form 10-K FY2024、FY2025（經查核）；例：2026Q2 https://www.sec.gov/Archives/edgar/data/1652044/000165204426000066/googexhibit991q22026.htm
A52: 核對彙總（實績必須為 0）
A53: 檢查：上列核對列絕對值合計（8 季＋FY2024＋FY2025） | B53: =SUMPRODUCT(ABS(B10:K10))+SUMPRODUCT(ABS(B15:K15))+SUMPRODUCT(ABS(B23:K23))+SUMPRODUCT(ABS(B31:K31))+SUMPRODUCT(ABS(B35:K35))+SUMPRODUCT(ABS(B38:K38))+SUMPRODUCT(ABS(B48:K48)) -> 0
A54: 檢查：FY2025 四季合計 − 年報（分部營收、產品線、分部營業利益、資本支出、營運現金、折舊） | B54: =ABS(SUM(D9:G9)-K9)+ABS(SUM(D11:G11)-K11)+ABS(SUM(D12:G12)-K12)+ABS(SUM(D13:G13)-K13)+ABS(SUM(D14:G14)-K14)+ABS(SUM(D18:G18)-K18)+ABS(SUM(D19:G19)-K19)+ABS(SUM(D20:G20)-K20)+ABS(SUM(D21:G21)-K21)+ABS(SUM(D22:G22)-K22)+ABS(SUM(D5:G5)-K5)+ABS(SUM(D6:G6)-K6)+ABS(SUM(D7:G7)-K7)+ABS(SUM(D8:G8)-K8)+ABS(SUM(D46:G46)-K46)+ABS(SUM(D45:G45)-K45)+ABS(SUM(D43:G43)-K43) -> 0
A56: 推導量（Seg、PL 頁的起始值；[Derived]）
A57: 項目 | B57: 數值 | C57: 說明
A58: 近四季年增：Google Search & other | B58: =M5/N5-1 -> 0.16801321 | C58: (2025Q3–2026Q2) ÷ (2024Q3–2025Q2) − 1；B 路徑 2H26 的年增，之後收斂到長期值
A59: 近四季年增：YouTube ads | B59: =M6/N6-1 -> 0.11713933 | C59: (2025Q3–2026Q2) ÷ (2024Q3–2025Q2) − 1；B 路徑 2H26 的年增，之後收斂到長期值
A60: 近四季年增：Google Network | B60: =M7/N7-1 -> -0.021785335 | C60: (2025Q3–2026Q2) ÷ (2024Q3–2025Q2) − 1；B 路徑 2H26 的年增，之後收斂到長期值
A61: 近四季年增：Google subscriptions, platforms, and devices | B61: =M8/N8-1 -> 0.17943516 | C61: (2025Q3–2026Q2) ÷ (2024Q3–2025Q2) − 1；B 路徑 2H26 的年增，之後收斂到長期值
A62: 近四季年增：Google Cloud | B62: =M11/N11-1 -> 0.57783786 | C62: (2025Q3–2026Q2) ÷ (2024Q3–2025Q2) − 1；B 路徑 2H26 的年增，之後收斂到長期值
A63: 近四季 Google Services 營收 | B63: =M9 -> 367.091
A64: 近四季三分部營收合計（不含避險） | B64: =M9+M11+M12 -> 446.215
A65: 折舊分攤比例：Google Services（按近四季營收） | B65: =M9/rev3_ttm -> 0.82267741 | C65: 公司不揭露分部折舊（技術基礎設施依使用量分攤，已含在分部營業利益）→ 按營收分攤（沿用 v0.2.2（legacy_v0.2/company.json）；替代＝依使用量，雲端占比更高）
A66: 折舊分攤比例：Google Cloud | B66: =M11/rev3_ttm -> 0.1739453
A67: 折舊分攤比例：Other Bets | B67: =M12/rev3_ttm -> 0.0033772957
A68: 近四季折舊 | B68: =M43 -> 25.237
A69: Google Services EBITDA 率（近四季；營業利益＋分攤折舊） | B69: =(M18+da_ttm*sh_svc)/M9 -> 0.47550583 | C69: v0.2.2 口徑 47.55%（mb_ttm＝1 時採用）
A70: 1H26 折舊分攤比例：Google Services | B70: =L9/(L9+L11+L12) -> 0.80158509
A71: 1H26 折舊分攤比例：Google Cloud | B71: =L11/(L9+L11+L12) -> 0.19496357
A72: Google Services EBITDA 率（1H26；營業利益＋分攤折舊） | B72: =(L18+L43*sh1_svc)/L9 -> 0.49421662 | C72: 與評價日機隊與 2026Q2 折舊年化（da_base）同一時點
A73: Google Services EBITDA 率（預測期採用） | B73: =IF(mb_ttm=1,m_svc_ttm,m_svc_1h) -> 0.49421662 | C73: 預設 1H26（最新已申報半年，利潤率仍在擴張；近四季口徑列 Sens）；自用 AI 增量成本另計
A74: 近四季 Google Cloud EBITDA（營業利益＋分攤折舊） | B74: =M19+da_ttm*sh_cloud -> 28.708857
A75: 近四季 Google Cloud 營收 | B75: =M11 -> 77.617
A76: 前四季 Google Cloud 營收 | B76: =N11 -> 49.192
A77: 近四季 Other Bets 營業利益 | B77: =M20 -> -8.942
A78: 近四季 Alphabet-level activities | B78: =M21 -> -21.541
A79: TAC ÷ (Search＋Network) 近四季 | B79: =M27/(M5+M7) -> 0.23052727 | C79: 增量 EBITDA 率 im 的參考

Sheet Thesis
A1: Thesis — 命題模組：AI 容量（MW）× 每 MW 收入（Tokenomics 持有成本 × k）→ Google Cloud 的 Cloud AI 子列；同一套 MW 推出 AI 資本支出、AI 折舊與營運成本，接到分部營業利益（對外 → Google Cloud；自用 → Google Services／Alphabet 層級）
A2: 三情境共用（本版的情境軸是 Search，見 Seg 頁）；MW 速度、對外比例、k 的區間在 Sens 頁。沿用 v0.2.2：k 規格（kspec.py）、C10 基準速度、對外比例 30%、Tokenomics v21.4 快照。不以 Cloud 營收、RPO 反推 k 或每 MW 價格（工作單第 4 節）
A4: A. 價格與起始值（單一數值，C 欄）
A5: 項目 | B5: 單位 | C5: 數值 | N5: 說明
A6: k_長約＝長約證據價格 ÷ IF_HoldEcon｜VR200 | B6: x | C6: =kl_px/he_vr -> 0.78291462 | N6: kspec.py（v0.2.2）：證據價格不變、分母隨 Tokenomics 快照
A7: k_現貨＝H100 現貨指數 ÷ IF_GPUhrEcon｜H100 | B7: x | C7: =ks_px/gpuhr_h -> 1.8280865 | N7: C1：MAG 三家一致
A8: 混合 k＝長約占比 × k_長約＋(1 − 長約占比) × k_現貨 | B8: x | C8: =long_sh*k_long+(1-long_sh)*k_spot -> 1.2009834 | N8: v0.2.2 為 1.201
A9: TPU 收入錨調整＝1 − TPU 占比 ×(1 − TPU 係數) | B9: x | C9: =1-tpu_sh*(1-tpu_f) -> 1 | N9: 基準 1（C2：TPU × 1.0）
A10: TPU IT 資本支出調整 | B10: x | C10: =1-tpu_sh*(1-tpu_cf) -> 1
A11: 期初機隊每 MW 年收入（對外） | B11: US$m/MW-年 | C11: =k_blend*tpu_adj*(mix0_h*he_h+mix0_b2*he_b2+mix0_b3*he_b3) -> 11.606747
A12: 期初機隊每 MW 年營運費用（Tokenomics IF_OpexGW 加權） | B12: US$m/MW-年 | C12: =mix0_h*opx_h+mix0_b2*opx_b2+mix0_b3*opx_b3 -> 1.881462
A13: 近四季 Cloud AI 營收估計（近四季平均對外 MW × 期初每 MW 收入） | B13: US$B | C13: =ai_mw_ttm*permw0/1000 -> 16.80541 | N13: 只用於拆 Cloud 其他的起始成長率與利潤率
A14: 前四季 Cloud AI 營收估計 | B14: US$B | C14: =ai_mw_pttm*permw0/1000 -> 7.6291151
A15: 近四季 Cloud AI EBITDA 估計 | B15: US$B | C15: =ai_mw_ttm*(permw0-opex0)/1000 -> 14.081241
A16: Cloud 其他近四季年增（Cloud − Cloud AI 估計） | B16: % | C16: =(cloud_ttm-ai_ttm)/(cloud_pttm-ai_pttm)-1 -> 0.46312246 | N16: [Derived]；Cloud 其他＝Workspace、非 AI 雲端、Wiz（2026-03 併入）
A17: Cloud 其他 EBITDA 率（近四季：Cloud EBITDA − Cloud AI EBITDA 估計）÷ Cloud 其他營收 | B17: % | C17: =(cloud_ebitda_ttm-ai_ttm_e)/(cloud_ttm-ai_ttm) -> 0.24053995 | N17: [Derived]；mb_ttm＝1 時採用
A18: Cloud 其他 EBITDA 率（1H26） | B18: % | C18: =(Q!L19+Q!L43*sh1_cloud-E41)/(Q!L11-E38) -> 0.28210362 | N18: [Derived]；(1H26 Cloud 營業利益＋分攤折舊 − Cloud AI 1H EBITDA) ÷ Cloud 其他 1H
A19: Cloud 其他 EBITDA 率（預測期採用，固定） | B19: % | C19: =IF(mb_ttm=1,m_co_ttm,m_co_1h) -> 0.28210362 | N19: 預設 1H26（同 m_svc）
A21: B. AI 容量（AI 總 IT MW；期末）— 依 Tokenomics 世代錨分桶
A22: 項目 | B22: 單位 | C22: FY2024A | D22: FY2025A | E22: 1H26A | F22: 2H26E | G22: FY2026E | H22: FY2027E | I22: FY2028E | J22: FY2029E | K22: FY2030E | L22: FY2031E | M22: FY2032E | N22: 說明
A23: AI 總 MW 新增（FY2029 起收斂到 g × 期初 MW） | B23: MW | F23: =pace*0.5 -> 2079.835 | G23: =F23 -> 2079.835 | H23: =pace -> 4159.67 | I23: =pace -> 4159.67 | J23: =pace+(g_tv*I28-pace)*MIN(1,(2029-2028)/conv_mw) -> 3245.2738 | K23: =pace+(g_tv*J28-pace)*MIN(1,(2030-2028)/conv_mw) -> 2379.5567 | L23: =pace+(g_tv*K28-pace)*MIN(1,(2031-2028)/conv_mw) -> 1543.0401 | M23: =pace+(g_tv*L28-pace)*MIN(1,(2032-2028)/conv_mw) -> 717.12137 | N23: 三情境相同；修正一 F5：FY2029–FY2032 線性收斂，FY2032 只剩與永續成長 g 一致的增量（另加汰換）
A24: 期末 MW：Hopper 錨 | B24: MW | E24: =mw_tot0*mix0_h -> 1584.25 | F24: =E24+F23*0 -> 1584.25 | G24: =F24 -> 1584.25 | H24: =F24+H23*0 -> 1584.25 | I24: =H24+I23*0 -> 1584.25 | J24: =I24+J23*0 -> 1584.25 | K24: =J24+K23*0 -> 1584.25 | L24: =K24+L23*0 -> 1584.25 | M24: =L24+M23*0 -> 1584.25 | N24: 期初（2026-06-30）＝AI 在役 MW × 期初機隊占比；新增依年度世代組合（2026 GB300 錨；2027 GB300／VR200 各半；2028 起 VR200 錨）
A25: 期末 MW：GB200 錨 | B25: MW | E25: =mw_tot0*mix0_b2 -> 2851.65 | F25: =E25+F23*0 -> 2851.65 | G25: =F25 -> 2851.65 | H25: =F25+H23*0 -> 2851.65 | I25: =H25+I23*0 -> 2851.65 | J25: =I25+J23*0 -> 2851.65 | K25: =J25+K23*0 -> 2851.65 | L25: =K25+L23*0 -> 2851.65 | M25: =L25+M23*0 -> 2851.65
A26: 期末 MW：GB300 錨 | B26: MW | E26: =mw_tot0*mix0_b3 -> 1901.1 | F26: =E26+F23*am_26 -> 3980.935 | G26: =F26 -> 3980.935 | H26: =F26+H23*am_27 -> 6060.77 | I26: =H26+I23*(1-am_28) -> 6060.77 | J26: =I26+J23*(1-am_28) -> 6060.77 | K26: =J26+K23*(1-am_28) -> 6060.77 | L26: =K26+L23*(1-am_28) -> 6060.77 | M26: =L26+M23*(1-am_28) -> 6060.77
A27: 期末 MW：VR200 錨 | B27: MW | E27: =mw_tot0*0 -> 0 | F27: =E27+F23*(1-am_26) -> 0 | G27: =F27 -> 0 | H27: =F27+H23*(1-am_27) -> 2079.835 | I27: =H27+I23*am_28 -> 6239.505 | J27: =I27+J23*am_28 -> 9484.7788 | K27: =J27+K23*am_28 -> 11864.336 | L27: =K27+L23*am_28 -> 13407.376 | M27: =L27+M23*am_28 -> 14124.497
A28: 期末 AI 總 MW | B28: MW | E28: =E24+E25+E26+E27 -> 6337 | F28: =F24+F25+F26+F27 -> 8416.835 | G28: =G24+G25+G26+G27 -> 8416.835 | H28: =H24+H25+H26+H27 -> 12576.505 | I28: =I24+I25+I26+I27 -> 16736.175 | J28: =J24+J25+J26+J27 -> 19981.449 | K28: =K24+K25+K26+K27 -> 22361.006 | L28: =L24+L25+L26+L27 -> 23904.046 | M28: =M24+M25+M26+M27 -> 24621.167
A29: 期末對外 MW（＝總 MW × 對外比例） | B29: MW | E29: =E28*ext_sh -> 1901.1 | F29: =F28*ext_sh -> 2525.0505 | G29: =G28*ext_sh -> 2525.0505 | H29: =H28*ext_sh -> 3772.9515 | I29: =I28*ext_sh -> 5020.8525 | J29: =J28*ext_sh -> 5994.4346 | K29: =K28*ext_sh -> 6708.3017 | L29: =L28*ext_sh -> 7171.2137 | M29: =M28*ext_sh -> 7386.3501 | N29: 評價日 1,901（v0.2.2 defaults.billableOpen）
A30: 平均在役 MW：Hopper 錨 | B30: MW | E30: =(mw_ye25+mw_tot0)/2*mix0_h -> 1401.25 | F30: =(E24+F24)/2 -> 1584.25 | G30: =(E30+F30)/2 -> 1492.75 | H30: =(F24+H24)/2 -> 1584.25 | I30: =(H24+I24)/2 -> 1584.25 | J30: =(I24+J24)/2 -> 1584.25 | K30: =(J24+K24)/2 -> 1584.25 | L30: =(K24+L24)/2 -> 1584.25 | M30: =(L24+M24)/2 -> 1584.25
A31: 平均在役 MW：GB200 錨 | B31: MW | E31: =(mw_ye25+mw_tot0)/2*mix0_b2 -> 2522.25 | F31: =(E25+F25)/2 -> 2851.65 | G31: =(E31+F31)/2 -> 2686.95 | H31: =(F25+H25)/2 -> 2851.65 | I31: =(H25+I25)/2 -> 2851.65 | J31: =(I25+J25)/2 -> 2851.65 | K31: =(J25+K25)/2 -> 2851.65 | L31: =(K25+L25)/2 -> 2851.65 | M31: =(L25+M25)/2 -> 2851.65
A32: 平均在役 MW：GB300 錨 | B32: MW | E32: =(mw_ye25+mw_tot0)/2*mix0_b3 -> 1681.5 | F32: =(E26+F26)/2 -> 2941.0175 | G32: =(E32+F32)/2 -> 2311.2587 | H32: =(F26+H26)/2 -> 5020.8525 | I32: =(H26+I26)/2 -> 6060.77 | J32: =(I26+J26)/2 -> 6060.77 | K32: =(J26+K26)/2 -> 6060.77 | L32: =(K26+L26)/2 -> 6060.77 | M32: =(L26+M26)/2 -> 6060.77
A33: 平均在役 MW：VR200 錨 | B33: MW | E33: =(mw_ye25+mw_tot0)/2*0 -> 0 | F33: =(E27+F27)/2 -> 0 | G33: =(E33+F33)/2 -> 0 | H33: =(F27+H27)/2 -> 1039.9175 | I33: =(H27+I27)/2 -> 4159.67 | J33: =(I27+J27)/2 -> 7862.1419 | K33: =(J27+K27)/2 -> 10674.557 | L33: =(K27+L27)/2 -> 12635.856 | M33: =(L27+M27)/2 -> 13765.936
A34: 平均在役 AI 總 MW | B34: MW | E34: =E30+E31+E32+E33 -> 5605 | F34: =F30+F31+F32+F33 -> 7376.9175 | G34: =G30+G31+G32+G33 -> 6490.9587 | H34: =H30+H31+H32+H33 -> 10496.67 | I34: =I30+I31+I32+I33 -> 14656.34 | J34: =J30+J31+J32+J33 -> 18358.812 | K34: =K30+K31+K32+K33 -> 21171.227 | L34: =L30+L31+L32+L33 -> 23132.526 | M34: =M30+M31+M32+M33 -> 24262.606
A35: 平均在役對外 MW | B35: MW | E35: =E34*ext_sh -> 1681.5 | F35: =F34*ext_sh -> 2213.0752 | G35: =G34*ext_sh -> 1947.2876 | H35: =H34*ext_sh -> 3149.001 | I35: =I34*ext_sh -> 4396.902 | J35: =J34*ext_sh -> 5507.6436 | K35: =K34*ext_sh -> 6351.3682 | L35: =L34*ext_sh -> 6939.7577 | M35: =M34*ext_sh -> 7278.7819
A37: C. Cloud AI（對外 AI 雲端；Google Cloud 的命題子列）
A38: Cloud AI 營收＝對外比例 × Σ 平均 MW × IF_HoldEcon × k × TPU 調整 | B38: US$B | E38: =ext_sh*k_blend*tpu_adj*(E30*he_h+E31*he_b2+E32*he_b3+E33*he_vr)/1000*0.5 -> 9.7583729 | F38: =ext_sh*k_blend*tpu_adj*(F30*he_h+F31*he_b2+F32*he_b3+F33*he_vr)/1000*0.5 -> 13.072238 | G38: =E38+F38 -> 22.830611 | H38: =ext_sh*k_blend*tpu_adj*(H30*he_h+H31*he_b2+H32*he_b3+H33*he_vr)/1000*1 -> 38.882858 | I38: =ext_sh*k_blend*tpu_adj*(I30*he_h+I31*he_b2+I32*he_b3+I33*he_vr)/1000*1 -> 56.703559 | J38: =ext_sh*k_blend*tpu_adj*(J30*he_h+J31*he_b2+J32*he_b3+J33*he_vr)/1000*1 -> 73.012119 | K38: =ext_sh*k_blend*tpu_adj*(K30*he_h+K31*he_b2+K32*he_b3+K33*he_vr)/1000*1 -> 85.400179 | L38: =ext_sh*k_blend*tpu_adj*(L30*he_h+L31*he_b2+L32*he_b3+L33*he_vr)/1000*1 -> 94.03926 | M38: =ext_sh*k_blend*tpu_adj*(M30*he_h+M31*he_b2+M32*he_b3+M33*he_vr)/1000*1 -> 99.017013 | N38: 收入端不乘 IF_Util（MW-year 計價）；1H26 為模型估計（公司未揭露 AI 營收），Cloud 其他＝實際 Cloud − 本列
A39: 每 MW 年收入（對外） | B39: US$m/MW-年 | E39: =E38/(E35*0.5)*1000 -> 11.606747 | F39: =F38/(F35*0.5)*1000 -> 11.813641 | H39: =H38/(H35*1)*1000 -> 12.34768 | I39: =I38/(I35*1)*1000 -> 12.896253 | J39: =J38/(J35*1)*1000 -> 13.256508 | K39: =K38/(K35*1)*1000 -> 13.44595 | L39: =L38/(L35*1)*1000 -> 13.550799 | M39: =M38/(M35*1)*1000 -> 13.603514
A40: Cloud AI 營運費用（Tokenomics IF_OpexGW，含電費） | B40: US$B | E40: =ext_sh*(E30*opx_h+E31*opx_b2+E32*opx_b3+E33*opx_vr)/1000*0.5 -> 1.5818392 | F40: =ext_sh*(F30*opx_h+F31*opx_b2+F32*opx_b3+F33*opx_vr)/1000*0.5 -> 2.0976902 | G40: =E40+F40 -> 3.6795295 | H40: =ext_sh*(H30*opx_h+H31*opx_b2+H32*opx_b3+H33*opx_vr)/1000*1 -> 6.0855653 | I40: =ext_sh*(I30*opx_h+I31*opx_b2+I32*opx_b3+I33*opx_vr)/1000*1 -> 8.6634547 | J40: =ext_sh*(J30*opx_h+J31*opx_b2+J32*opx_b3+J33*opx_vr)/1000*1 -> 10.988787 | K40: =ext_sh*(K30*opx_h+K31*opx_b2+K32*opx_b3+K33*opx_vr)/1000*1 -> 12.755121 | L40: =ext_sh*(L30*opx_h+L31*opx_b2+L32*opx_b3+L33*opx_vr)/1000*1 -> 13.986912 | M40: =ext_sh*(M30*opx_h+M31*opx_b2+M32*opx_b3+M33*opx_vr)/1000*1 -> 14.696657
A41: Cloud AI EBITDA | B41: US$B | E41: =E38-E40 -> 8.1765337 | F41: =F38-F40 -> 10.974548 | G41: =G38-G40 -> 19.151082 | H41: =H38-H40 -> 32.797293 | I41: =I38-I40 -> 48.040104 | J41: =J38-J40 -> 62.023332 | K41: =K38-K40 -> 72.645058 | L41: =L38-L40 -> 80.052348 | M41: =M38-M40 -> 84.320356
A42: Cloud AI EBITDA 率 | B42: % | E42: =E41/E38 -> 0.83789929 | F42: =F41/F38 -> 0.8395309 | G42: =G41/G38 -> 0.83883351 | H42: =H41/H38 -> 0.84348976 | I42: =I41/I38 -> 0.84721497 | J42: =J41/J38 -> 0.84949366 | K42: =K41/K38 -> 0.85064293 | L42: =L41/L38 -> 0.85126519 | M42: =M41/M38 -> 0.85157442
A43: 上限檢查：每 MW 收入 ÷ 在役世代加權 IFW_RevGWFleet_Util（> 50% 示警；不得作預測） | B43: % | E43: =E39/((E30*cap_h+E31*cap_b2+E32*cap_b3+E33*cap_vr)/E34) -> 0.40541575 | F43: =F39/((F30*cap_h+F31*cap_b2+F32*cap_b3+F33*cap_vr)/F34) -> 0.39027147 | H43: =H39/((H30*cap_h+H31*cap_b2+H32*cap_b3+H33*cap_vr)/H34) -> 0.34465881 | I43: =I39/((I30*cap_h+I31*cap_b2+I32*cap_b3+I33*cap_vr)/I34) -> 0.30246186 | J43: =J39/((J30*cap_h+J31*cap_b2+J32*cap_b3+J33*cap_vr)/J34) -> 0.27956196 | K43: =K39/((K30*cap_h+K31*cap_b2+K32*cap_b3+K33*cap_vr)/K34) -> 0.26927931 | L43: =L39/((L30*cap_h+L31*cap_b2+L32*cap_b3+L33*cap_vr)/L34) -> 0.26402136 | M43: =M39/((M30*cap_h+M31*cap_b2+M32*cap_b3+M33*cap_vr)/M34) -> 0.26148405 | N43: v0.2.2 基準最高 38.0%
A45: D. AI 資本支出（新增 MW × Tokenomics 每 MW 成本；汰換只換 IT）
A46: AI IT 資本支出（成長） | B46: US$B | F46: =F23*(0*cit_h+0*cit_b2+am_26*cit_b3+(1-am_26)*cit_vr)*tpu_adjc/1000 -> 67.048107 | G46: =F46 -> 67.048107 | H46: =H23*(0*cit_h+0*cit_b2+am_27*cit_b3+(1-am_27)*cit_vr)*tpu_adjc/1000 -> 145.22152 | I46: =I23*(0*cit_h+0*cit_b2+(1-am_28)*cit_b3+am_28*cit_vr)*tpu_adjc/1000 -> 156.34682 | J46: =J23*(0*cit_h+0*cit_b2+(1-am_28)*cit_b3+am_28*cit_vr)*tpu_adjc/1000 -> 121.978 | K46: =K23*(0*cit_h+0*cit_b2+(1-am_28)*cit_b3+am_28*cit_vr)*tpu_adjc/1000 -> 89.438857 | L46: =L23*(0*cit_h+0*cit_b2+(1-am_28)*cit_b3+am_28*cit_vr)*tpu_adjc/1000 -> 57.997249 | M46: =M23*(0*cit_h+0*cit_b2+(1-am_28)*cit_b3+am_28*cit_vr)*tpu_adjc/1000 -> 26.953976
A47: AI 機房資本支出（自建比例 × IF_CapexFacility） | B47: US$B | F47: =F23*selfb*cfac/1000 -> 22.398783 | G47: =F47 -> 22.398783 | H47: =H23*selfb*cfac/1000 -> 44.797566 | I47: =I23*selfb*cfac/1000 -> 44.797566 | J47: =J23*selfb*cfac/1000 -> 34.949976 | K47: =K23*selfb*cfac/1000 -> 25.626636 | L47: =L23*selfb*cfac/1000 -> 16.617771 | M47: =M23*selfb*cfac/1000 -> 7.7230386
A48: 汰換 MW（6 年前上線的 MW，換成 VR200 錨 IT） | B48: MW | F48: 0 | G48: =F48 -> 0 | H48: 0 | I48: 0 | J48: =mw_ye23 -> 636.7 | K48: =mw_ye24-mw_ye23 -> 1506.6 | L48: =mw_ye25-mw_ye24 -> 2729.7 | M48: =mw_tot0-mw_ye25+F23 -> 3543.835 | N48: IT 壽命 6 年：2023 年底在役 → 2029 汰換，以此類推；汰換後 MW 照常在役（收入不變）
A49: AI 汰換資本支出（只含 IT） | B49: US$B | F49: =F48*cit_vr*tpu_adjc/1000 -> 0 | G49: =F49 -> 0 | H49: =H48*cit_vr*tpu_adjc/1000 -> 0 | I49: =I48*cit_vr*tpu_adjc/1000 -> 0 | J49: =J48*cit_vr*tpu_adjc/1000 -> 23.93123 | K49: =K48*cit_vr*tpu_adjc/1000 -> 56.627598 | L49: =L48*cit_vr*tpu_adjc/1000 -> 102.59947 | M49: =M48*cit_vr*tpu_adjc/1000 -> 133.19983
A50: AI 資本支出（公式） | B50: US$B | F50: =F46+F47+F49 -> 89.44689 | G50: =G46+G47+G49 -> 89.44689 | H50: =H46+H47+H49 -> 190.01908 | I50: =I46+I47+I49 -> 201.14439 | J50: =J46+J47+J49 -> 180.85921 | K50: =K46+K47+K49 -> 171.69309 | L50: =L46+L47+L49 -> 177.21448 | M50: =M46+M47+M49 -> 167.87684
A51: 2H26 指引下限補足（MAX(0, 指引 − 上半年 − 公式)；歸 AI IT） | B51: US$B | F51: =MAX(0,capex_g-capex_1h-(F50+Seg!F70)) -> 8.8359103 | G51: =F51 -> 8.8359103 | N51: C10：首期資本支出＝MAX(公式, 公司指引)；2H26 三情境營收相同（情境爬坡自 FY2027 起），用情境 B 的非 AI 資本支出
A52: AI 資本支出（含指引下限補足） | B52: US$B | F52: =F50+F51 -> 98.2828 | G52: =F52 -> 98.2828 | H52: =H50 -> 190.01908 | I52: =I50 -> 201.14439 | J52: =J50 -> 180.85921 | K52: =K50 -> 171.69309 | L52: =L50 -> 177.21448 | M52: =M50 -> 167.87684
A53: Cloud AI 營收 ÷ AI 資本支出 | B53: x | F53: =F38/F52 -> 0.13300637 | H53: =H38/H52 -> 0.20462607 | I53: =I38/I52 -> 0.28190475 | J53: =J38/J52 -> 0.40369589 | K53: =K38/K52 -> 0.49740021 | L53: =L38/L52 -> 0.53065222 | M53: =M38/M52 -> 0.58981936
A55: E. AI 折舊（在建工程與新增資本支出依年限直線攤提；評價日在役資產的折舊在 PL 頁「基礎折舊」）
A56: 每個資本支出年度：當期 × phi_0、之後每年 1、最後一年 1 − phi_0（年限 life_it／life_fac；IT 含汰換與指引補足；在建工程 2026H2 起轉入）
A57: 在建工程轉入：IT（2026 年度批次） | B57: US$B | F57: =cip_0*cip_it -> 73.6884
A58: 在建工程轉入：機房與網通（2026 年度批次） | B58: US$B | F58: =cip_0*(1-cip_it) -> 49.1256
A59: IT 批次金額（成長＋汰換＋指引補足） | B59: US$B | F59: =F46+F49+F51 -> 75.884017 | H59: =H46+H49 -> 145.22152 | I59: =I46+I49 -> 156.34682 | J59: =J46+J49 -> 145.90923 | K59: =K46+K49 -> 146.06645 | L59: =L46+L49 -> 160.59671 | M59: =M46+M49 -> 160.15381
A60: 機房批次金額 | B60: US$B | F60: =F47 -> 22.398783 | H60: =H47 -> 44.797566 | I60: =I47 -> 44.797566 | J60: =J47 -> 34.949976 | K60: =K47 -> 25.626636 | L60: =L47 -> 16.617771 | M60: =M47 -> 7.7230386
A61: 新增 AI 折舊：IT | B61: US$B | F61: =$F$57/life_it*IF(0=0,phi_0,IF(0<life_it,1,IF(0=life_it,1-phi_0,0)))+$F$59/life_it*IF(0=0,phi_0,IF(0<life_it,1,IF(0=life_it,1-phi_0,0))) -> 6.232184 | G61: =F61 -> 6.232184 | H61: =$F$57/life_it*IF(1=0,phi_0,IF(1<life_it,1,IF(1=life_it,1-phi_0,0)))+$F$59/life_it*IF(1=0,phi_0,IF(1<life_it,1,IF(1=life_it,1-phi_0,0)))+$H$59/life_it*IF(0=0,phi_0,IF(0<life_it,1,IF(0=life_it,1-phi_0,0))) -> 30.979633 | I61: =$F$57/life_it*IF(2=0,phi_0,IF(2<life_it,1,IF(2=life_it,1-phi_0,0)))+$F$59/life_it*IF(2=0,phi_0,IF(2<life_it,1,IF(2=life_it,1-phi_0,0)))+$H$59/life_it*IF(1=0,phi_0,IF(1<life_it,1,IF(1=life_it,1-phi_0,0)))+$I$59/life_it*IF(0=0,phi_0,IF(0<life_it,1,IF(0=life_it,1-phi_0,0))) -> 55.646773 | J61: =$F$57/life_it*IF(3=0,phi_0,IF(3<life_it,1,IF(3=life_it,1-phi_0,0)))+$F$59/life_it*IF(3=0,phi_0,IF(3<life_it,1,IF(3=life_it,1-phi_0,0)))+$H$59/life_it*IF(2=0,phi_0,IF(2<life_it,1,IF(2=life_it,1-phi_0,0)))+$I$59/life_it*IF(1=0,phi_0,IF(1<life_it,1,IF(1=life_it,1-phi_0,0)))+$J$59/life_it*IF(0=0,phi_0,IF(0<life_it,1,IF(0=life_it,1-phi_0,0))) -> 81.269677 | K61: =$F$57/life_it*IF(4=0,phi_0,IF(4<life_it,1,IF(4=life_it,1-phi_0,0)))+$F$59/life_it*IF(4=0,phi_0,IF(4<life_it,1,IF(4=life_it,1-phi_0,0)))+$H$59/life_it*IF(3=0,phi_0,IF(3<life_it,1,IF(3=life_it,1-phi_0,0)))+$I$59/life_it*IF(2=0,phi_0,IF(2<life_it,1,IF(2=life_it,1-phi_0,0)))+$J$59/life_it*IF(1=0,phi_0,IF(1<life_it,1,IF(1=life_it,1-phi_0,0)))+$K$59/life_it*IF(0=0,phi_0,IF(0<life_it,1,IF(0=life_it,1-phi_0,0))) -> 105.59443 | L61: =$F$57/life_it*IF(5=0,phi_0,IF(5<life_it,1,IF(5=life_it,1-phi_0,0)))+$F$59/life_it*IF(5=0,phi_0,IF(5<life_it,1,IF(5=life_it,1-phi_0,0)))+$H$59/life_it*IF(4=0,phi_0,IF(4<life_it,1,IF(4=life_it,1-phi_0,0)))+$I$59/life_it*IF(3=0,phi_0,IF(3<life_it,1,IF(3=life_it,1-phi_0,0)))+$J$59/life_it*IF(2=0,phi_0,IF(2<life_it,1,IF(2=life_it,1-phi_0,0)))+$K$59/life_it*IF(1=0,phi_0,IF(1<life_it,1,IF(1=life_it,1-phi_0,0)))+$L$59/life_it*IF(0=0,phi_0,IF(0<life_it,1,IF(0=life_it,1-phi_0,0))) -> 130.54427 | M61: =$F$57/life_it*IF(6=0,phi_0,IF(6<life_it,1,IF(6=life_it,1-phi_0,0)))+$F$59/life_it*IF(6=0,phi_0,IF(6<life_it,1,IF(6=life_it,1-phi_0,0)))+$H$59/life_it*IF(5=0,phi_0,IF(5<life_it,1,IF(5=life_it,1-phi_0,0)))+$I$59/life_it*IF(4=0,phi_0,IF(4<life_it,1,IF(4=life_it,1-phi_0,0)))+$J$59/life_it*IF(3=0,phi_0,IF(3<life_it,1,IF(3=life_it,1-phi_0,0)))+$K$59/life_it*IF(2=0,phi_0,IF(2<life_it,1,IF(2=life_it,1-phi_0,0)))+$L$59/life_it*IF(1=0,phi_0,IF(1<life_it,1,IF(1=life_it,1-phi_0,0)))+$M$59/life_it*IF(0=0,phi_0,IF(0<life_it,1,IF(0=life_it,1-phi_0,0))) -> 151.05975
A62: 新增 AI 折舊：機房 | B62: US$B | F62: =$F$58/life_fac*IF(0=0,phi_0,IF(0<life_fac,1,IF(0=life_fac,1-phi_0,0)))+$F$60/life_fac*IF(0=0,phi_0,IF(0<life_fac,1,IF(0=life_fac,1-phi_0,0))) -> 0.89405479 | G62: =F62 -> 0.89405479 | H62: =$F$58/life_fac*IF(1=0,phi_0,IF(1<life_fac,1,IF(1=life_fac,1-phi_0,0)))+$F$60/life_fac*IF(1=0,phi_0,IF(1<life_fac,1,IF(1=life_fac,1-phi_0,0)))+$H$60/life_fac*IF(0=0,phi_0,IF(0<life_fac,1,IF(0=life_fac,1-phi_0,0))) -> 4.1361887 | I62: =$F$58/life_fac*IF(2=0,phi_0,IF(2<life_fac,1,IF(2=life_fac,1-phi_0,0)))+$F$60/life_fac*IF(2=0,phi_0,IF(2<life_fac,1,IF(2=life_fac,1-phi_0,0)))+$H$60/life_fac*IF(1=0,phi_0,IF(1<life_fac,1,IF(1=life_fac,1-phi_0,0)))+$I$60/life_fac*IF(0=0,phi_0,IF(0<life_fac,1,IF(0=life_fac,1-phi_0,0))) -> 6.376067 | J62: =$F$58/life_fac*IF(3=0,phi_0,IF(3<life_fac,1,IF(3=life_fac,1-phi_0,0)))+$F$60/life_fac*IF(3=0,phi_0,IF(3<life_fac,1,IF(3=life_fac,1-phi_0,0)))+$H$60/life_fac*IF(2=0,phi_0,IF(2<life_fac,1,IF(2=life_fac,1-phi_0,0)))+$I$60/life_fac*IF(1=0,phi_0,IF(1<life_fac,1,IF(1=life_fac,1-phi_0,0)))+$J$60/life_fac*IF(0=0,phi_0,IF(0<life_fac,1,IF(0=life_fac,1-phi_0,0))) -> 8.4928505 | K62: =$F$58/life_fac*IF(4=0,phi_0,IF(4<life_fac,1,IF(4=life_fac,1-phi_0,0)))+$F$60/life_fac*IF(4=0,phi_0,IF(4<life_fac,1,IF(4=life_fac,1-phi_0,0)))+$H$60/life_fac*IF(3=0,phi_0,IF(3<life_fac,1,IF(3=life_fac,1-phi_0,0)))+$I$60/life_fac*IF(2=0,phi_0,IF(2<life_fac,1,IF(2=life_fac,1-phi_0,0)))+$J$60/life_fac*IF(1=0,phi_0,IF(1<life_fac,1,IF(1=life_fac,1-phi_0,0)))+$K$60/life_fac*IF(0=0,phi_0,IF(0<life_fac,1,IF(0=life_fac,1-phi_0,0))) -> 10.123808 | L62: =$F$58/life_fac*IF(5=0,phi_0,IF(5<life_fac,1,IF(5=life_fac,1-phi_0,0)))+$F$60/life_fac*IF(5=0,phi_0,IF(5<life_fac,1,IF(5=life_fac,1-phi_0,0)))+$H$60/life_fac*IF(4=0,phi_0,IF(4<life_fac,1,IF(4=life_fac,1-phi_0,0)))+$I$60/life_fac*IF(3=0,phi_0,IF(3<life_fac,1,IF(3=life_fac,1-phi_0,0)))+$J$60/life_fac*IF(2=0,phi_0,IF(2<life_fac,1,IF(2=life_fac,1-phi_0,0)))+$K$60/life_fac*IF(1=0,phi_0,IF(1<life_fac,1,IF(1=life_fac,1-phi_0,0)))+$L$60/life_fac*IF(0=0,phi_0,IF(0<life_fac,1,IF(0=life_fac,1-phi_0,0))) -> 11.292529 | M62: =$F$58/life_fac*IF(6=0,phi_0,IF(6<life_fac,1,IF(6=life_fac,1-phi_0,0)))+$F$60/life_fac*IF(6=0,phi_0,IF(6<life_fac,1,IF(6=life_fac,1-phi_0,0)))+$H$60/life_fac*IF(5=0,phi_0,IF(5<life_fac,1,IF(5=life_fac,1-phi_0,0)))+$I$60/life_fac*IF(4=0,phi_0,IF(4<life_fac,1,IF(4=life_fac,1-phi_0,0)))+$J$60/life_fac*IF(3=0,phi_0,IF(3<life_fac,1,IF(3=life_fac,1-phi_0,0)))+$K$60/life_fac*IF(2=0,phi_0,IF(2<life_fac,1,IF(2=life_fac,1-phi_0,0)))+$L$60/life_fac*IF(1=0,phi_0,IF(1<life_fac,1,IF(1=life_fac,1-phi_0,0)))+$M$60/life_fac*IF(0=0,phi_0,IF(0<life_fac,1,IF(0=life_fac,1-phi_0,0))) -> 12.012233
A63: 新增 AI 折舊合計 | B63: US$B | F63: =F61+F62 -> 7.1262388 | G63: =G61+G62 -> 7.1262388 | H63: =H61+H62 -> 35.115821 | I63: =I61+I62 -> 62.02284 | J63: =J61+J62 -> 89.762528 | K63: =K61+K62 -> 115.71824 | L63: =L61+L62 -> 141.8368 | M63: =M61+M62 -> 163.07198
A64: 其中：對外（→ Google Cloud） | B64: US$B | F64: =F63*ext_sh -> 2.1378716 | G64: =G63*ext_sh -> 2.1378716 | H64: =H63*ext_sh -> 10.534746 | I64: =I63*ext_sh -> 18.606852 | J64: =J63*ext_sh -> 26.928758 | K64: =K63*ext_sh -> 34.715472 | L64: =L63*ext_sh -> 42.55104 | M64: =M63*ext_sh -> 48.921595 | N64: 按對外比例分攤（在建工程同）
A65: 其中：自用（→ Google Services／Alphabet 層級） | B65: US$B | F65: =F63*(1-ext_sh) -> 4.9883672 | G65: =G63*(1-ext_sh) -> 4.9883672 | H65: =H63*(1-ext_sh) -> 24.581075 | I65: =I63*(1-ext_sh) -> 43.415988 | J65: =J63*(1-ext_sh) -> 62.833769 | K65: =K63*(1-ext_sh) -> 81.002769 | L65: =L63*(1-ext_sh) -> 99.285759 | M65: =M63*(1-ext_sh) -> 114.15039
A67: F. 自用 AI 增量成本（相對評價日機隊；評價日機隊的成本已在近四季分部利益率內）
A68: 自用 AI 增量營運費用（Tokenomics IF_OpexGW） | B68: US$B | F68: =(1-ext_sh)*((F30*opx_h+F31*opx_b2+F32*opx_b3+F33*opx_vr)-mw_tot0*opex0)/1000*0.5 -> 0.72162182 | G68: =F68 -> 0.72162182 | H68: =(1-ext_sh)*((H30*opx_h+H31*opx_b2+H32*opx_b3+H33*opx_vr)-mw_tot0*opex0)/1000*1 -> 5.8536748 | I68: =(1-ext_sh)*((I30*opx_h+I31*opx_b2+I32*opx_b3+I33*opx_vr)-mw_tot0*opex0)/1000*1 -> 11.86875 | J68: =(1-ext_sh)*((J30*opx_h+J31*opx_b2+J32*opx_b3+J33*opx_vr)-mw_tot0*opex0)/1000*1 -> 17.294526 | K68: =(1-ext_sh)*((K30*opx_h+K31*opx_b2+K32*opx_b3+K33*opx_vr)-mw_tot0*opex0)/1000*1 -> 21.415971 | L68: =(1-ext_sh)*((L30*opx_h+L31*opx_b2+L32*opx_b3+L33*opx_vr)-mw_tot0*opex0)/1000*1 -> 24.29015 | M68: =(1-ext_sh)*((M30*opx_h+M31*opx_b2+M32*opx_b3+M33*opx_vr)-mw_tot0*opex0)/1000*1 -> 25.946223
A69: SpaceX 算力租金（自用，營運成本） | B69: US$B | F69: =rent_2H -> 2.76 | G69: =F69 -> 2.76 | H69: =rent_27 -> 11.04 | I69: =rent_28 -> 11.04 | J69: =rent_29 -> 5.52 | K69: 0 | L69: 0 | M69: 0
A70: 自用 AI 增量成本合計（營運＋租金＋自用折舊） | B70: US$B | F70: =F68+F69+F65 -> 8.469989 | G70: =G68+G69+G65 -> 8.469989 | H70: =H68+H69+H65 -> 41.47475 | I70: =I68+I69+I65 -> 66.324738 | J70: =J68+J69+J65 -> 85.648295 | K70: =K68+K69+K65 -> 102.41874 | L70: =L68+L69+L65 -> 123.57591 | M70: =M68+M69+M65 -> 140.09661
A71: 歸 Google Services（× svc_sh） | B71: US$B | F71: =F70*svc_sh -> 5.0819934 | G71: =G70*svc_sh -> 5.0819934 | H71: =H70*svc_sh -> 24.88485 | I71: =I70*svc_sh -> 39.794843 | J71: =J70*svc_sh -> 51.388977 | K71: =K70*svc_sh -> 61.451244 | L71: =L70*svc_sh -> 74.145545 | M71: =M70*svc_sh -> 84.057967
A72: 歸 Alphabet-level activities（× (1 − svc_sh)） | B72: US$B | F72: =F70*(1-svc_sh) -> 3.3879956 | G72: =G70*(1-svc_sh) -> 3.3879956 | H72: =H70*(1-svc_sh) -> 16.5899 | I72: =I70*(1-svc_sh) -> 26.529895 | J72: =J70*(1-svc_sh) -> 34.259318 | K72: =K70*(1-svc_sh) -> 40.967496 | L72: =L70*(1-svc_sh) -> 49.430364 | M72: =M70*(1-svc_sh) -> 56.038645
A74: G. 評價日在役資產的基礎折舊（隨期初機隊汰換遞減；修正一 F6）
A75: 累計已汰換的期初機隊 MW（當年以半年計） | B75: MW | F75: =mid*F48 -> 0 | G75: =F75 -> 0 | H75: =F48+mid*H48 -> 0 | I75: =F48+H48+mid*I48 -> 0 | J75: =F48+H48+I48+mid*J48 -> 318.35 | K75: =F48+H48+I48+J48+mid*K48 -> 1390 | L75: =F48+H48+I48+J48+K48+mid*L48 -> 3508.15 | M75: =F48+H48+I48+J48+K48+L48+mid*M48 -> 6644.9175
A76: 期初機隊每 MW IT 年折舊（Tokenomics IF_DeprIT 依期初占比加權） | B76: US$m/MW-年 | E76: =mix0_h*dpi_h+mix0_b2*dpi_b2+mix0_b3*dpi_b3 -> 4.5592582
A77: 基礎折舊＝da_base − MIN(da_base × IT 占比, 累計汰換 MW × 每 MW IT 折舊) | B77: US$B | F77: =(da_base-MIN(da_base*cip_it,F75*$E$76/1000))*0.5 -> 14.208 | G77: =F77 -> 14.208 | H77: =(da_base-MIN(da_base*cip_it,H75*$E$76/1000))*1 -> 28.416 | I77: =(da_base-MIN(da_base*cip_it,I75*$E$76/1000))*1 -> 28.416 | J77: =(da_base-MIN(da_base*cip_it,J75*$E$76/1000))*1 -> 26.96456 | K77: =(da_base-MIN(da_base*cip_it,K75*$E$76/1000))*1 -> 22.078631 | L77: =(da_base-MIN(da_base*cip_it,L75*$E$76/1000))*1 -> 12.421438 | M77: =(da_base-MIN(da_base*cip_it,M75*$E$76/1000))*1 -> 11.3664 | N77: 期初機隊汰換後由新購 IT 折舊取代，避免重複計折舊；IT 占比沿用 cip_it（60%）
A79: H. 自用 AI 影子效益（讀法 2：自用增量 MW 以 k＝1 計，＝Tokenomics 持有成本；非財報營收）
A80: 自用 AI 影子效益（自用增量 MW × IF_HoldEcon × TPU 調整） | B80: US$B | F80: =(1-ext_sh)*tpu_adj*((F30*he_h+F31*he_b2+F32*he_b3+F33*he_vr)-(mix0_h*he_h+mix0_b2*he_b2+mix0_b3*he_b3)*mw_tot0)/1000*0.5 -> 3.9623393 | G80: =F80 -> 3.9623393 | H80: =(1-ext_sh)*tpu_adj*((H30*he_h+H31*he_b2+H32*he_b3+H33*he_vr)-(mix0_h*he_h+mix0_b2*he_b2+mix0_b3*he_b3)*mw_tot0)/1000*1 -> 32.673472 | I80: =(1-ext_sh)*tpu_adj*((I30*he_h+I31*he_b2+I32*he_b3+I33*he_vr)-(mix0_h*he_h+mix0_b2*he_b2+mix0_b3*he_b3)*mw_tot0)/1000*1 -> 67.296462 | J80: =(1-ext_sh)*tpu_adj*((J30*he_h+J31*he_b2+J32*he_b3+J33*he_vr)-(mix0_h*he_h+mix0_b2*he_b2+mix0_b3*he_b3)*mw_tot0)/1000*1 -> 98.981586 | K80: =(1-ext_sh)*tpu_adj*((K30*he_h+K31*he_b2+K32*he_b3+K33*he_vr)-(mix0_h*he_h+mix0_b2*he_b2+mix0_b3*he_b3)*mw_tot0)/1000*1 -> 123.04976 | L80: =(1-ext_sh)*tpu_adj*((L30*he_h+L31*he_b2+L32*he_b3+L33*he_vr)-(mix0_h*he_h+mix0_b2*he_b2+mix0_b3*he_b3)*mw_tot0)/1000*1 -> 139.83421 | M80: =(1-ext_sh)*tpu_adj*((M30*he_h+M31*he_b2+M32*he_b3+M33*he_vr)-(mix0_h*he_h+mix0_b2*he_b2+mix0_b3*he_b3)*mw_tot0)/1000*1 -> 149.50525 | N80: 修正一 F1：讀法 2 進評價口徑（PL 頁「營業利益（評價口徑）」、Val）；營收列與分部對帳不動
A81: 歸 Google Services（× svc_sh） | B81: US$B | F81: =F80*svc_sh -> 2.3774036 | G81: =G80*svc_sh -> 2.3774036 | H81: =H80*svc_sh -> 19.604083 | I81: =I80*svc_sh -> 40.377877 | J81: =J80*svc_sh -> 59.388951 | K81: =K80*svc_sh -> 73.829854 | L81: =L80*svc_sh -> 83.900529 | M81: =M80*svc_sh -> 89.703152
A82: 歸 Alphabet-level（× (1 − svc_sh)） | B82: US$B | F82: =F80*(1-svc_sh) -> 1.5849357 | G82: =G80*(1-svc_sh) -> 1.5849357 | H82: =H80*(1-svc_sh) -> 13.069389 | I82: =I80*(1-svc_sh) -> 26.918585 | J82: =J80*(1-svc_sh) -> 39.592634 | K82: =K80*(1-svc_sh) -> 49.219903 | L82: =L80*(1-svc_sh) -> 55.933686 | M82: =M80*(1-svc_sh) -> 59.802101
A83: 影子效益 ÷ 自用 AI 增量成本 | B83: x | F83: =F80/F70 -> 0.46780926 | H83: =H80/H70 -> 0.78779191 | I83: =I80/I70 -> 1.014651 | J83: =J80/J70 -> 1.1556749 | K83: =K80/K70 -> 1.2014379 | L83: =L80/L70 -> 1.1315653 | M83: =M80/M70 -> 1.0671582 | N83: 接近 1＝價值中性（Tokenomics 持有成本以 10% 資金成本回收資本）

Sheet Seg
A1: Seg — 營收分部層：官方分部（Google Services、Google Cloud、Other Bets）＋Alphabet 層級避險；產品線為子列。情境差異只在 Google Search & other（A 擴大變現／B 近四季成長收斂／C 查詢分流、變現下降），其餘三情境相同
A2: 成長路徑：2H26 年增＝近四季年增（Q 頁），之後線性收斂到長期值（conv_n 年，FY2030 到達）。Search 情境：Search＝B 路徑 ×(1 − 分流) ×(1＋每次查詢變現變動)，分流與變現變動自 FY2026 的 0 線性到 FY2030 的 In 頁值。Cloud AI 由 Thesis 頁帶入
A4: 情境 A（AI 搜尋擴大變現）
A5: 項目 | B5: 單位 | C5: FY2024A | D5: FY2025A | E5: 1H26A | F5: 2H26E | G5: FY2026E | H5: FY2027E | I5: FY2028E | J5: FY2029E | K5: FY2030E | L5: FY2031E | M5: FY2032E | N5: 說明
A6: Search B 路徑年增 | B6: % | F6: =g0_search -> 0.16801321 | H6: =g0_search+(gl_search-g0_search)*MIN(1,(2027-2026)/conv_n) -> 0.14600991 | I6: =g0_search+(gl_search-g0_search)*MIN(1,(2028-2026)/conv_n) -> 0.12400661 | J6: =g0_search+(gl_search-g0_search)*MIN(1,(2029-2026)/conv_n) -> 0.1020033 | K6: =g0_search+(gl_search-g0_search)*MIN(1,(2030-2026)/conv_n) -> 0.08 | L6: =g0_search+(gl_search-g0_search)*MIN(1,(2031-2026)/conv_n) -> 0.08 | M6: =g0_search+(gl_search-g0_search)*MIN(1,(2032-2026)/conv_n) -> 0.08 | N6: 2H26 年增＝近四季 +16.8%（Q 頁），FY2030 收斂到 gl_search
A7: Google Search & other：B 路徑 | B7: US$B | C7: =Q!J5 -> 198.084 | D7: =Q!K5 -> 224.532 | E7: =Q!L5 -> 123.67 | F7: =(Q!F5+Q!G5)*(1+F6) -> 139.7411 | G7: =E7+F7 -> 263.4111 | H7: =G7*(1+H6) -> 301.87173 | I7: =H7*(1+I6) -> 339.30582 | J7: =I7*(1+J6) -> 373.91613 | K7: =J7*(1+K6) -> 403.82942 | L7: =K7*(1+L6) -> 436.13578 | M7: =L7*(1+M6) -> 471.02664
A8: 情境爬坡（FY2026 0 → FY2030 1） | B8: x | F8: 0 | H8: =MIN(1,(2027-2026)/conv_n) -> 0.25 | I8: =MIN(1,(2028-2026)/conv_n) -> 0.5 | J8: =MIN(1,(2029-2026)/conv_n) -> 0.75 | K8: =MIN(1,(2030-2026)/conv_n) -> 1 | L8: =MIN(1,(2031-2026)/conv_n) -> 1 | M8: =MIN(1,(2032-2026)/conv_n) -> 1
A9: 查詢分流（相對 B 路徑） | B9: % | F9: =dA*F8 -> 0 | H9: =dA*H8 -> -0.0125 | I9: =dA*I8 -> -0.025 | J9: =dA*J8 -> -0.0375 | K9: =dA*K8 -> -0.05 | L9: =dA*L8 -> -0.05 | M9: =dA*M8 -> -0.05 | N9: In 頁 dA（負值＝AI 模式吸引查詢回流）
A10: 每次查詢變現變動（相對 B 路徑） | B10: % | F10: =mA*F8 -> 0 | H10: =mA*H8 -> 0.025 | I10: =mA*I8 -> 0.05 | J10: =mA*J8 -> 0.075 | K10: =mA*K8 -> 0.1 | L10: =mA*L8 -> 0.1 | M10: =mA*M8 -> 0.1
A11: Google Search & other | B11: US$B | C11: =C7 -> 198.084 | D11: =D7 -> 224.532 | E11: =E7 -> 123.67 | F11: =F7*(1-F9)*(1+F10) -> 139.7411 | G11: =E11+F11 -> 263.4111 | H11: =H7*(1-H9)*(1+H10) -> 313.28626 | I11: =I7*(1-I9)*(1+I10) -> 365.17789 | J11: =J7*(1-J9)*(1+J10) -> 417.03334 | K11: =K7*(1-K9)*(1+K10) -> 466.42299 | L11: =L7*(1-L9)*(1+L10) -> 503.73682 | M11: =M7*(1-M9)*(1+M10) -> 544.03577
A12: YouTube ads 年增 | B12: % | F12: =g0_yt -> 0.11713933 | H12: =g0_yt+(gl_yt-g0_yt)*MIN(1,(2027-2026)/conv_n) -> 0.1078545 | I12: =g0_yt+(gl_yt-g0_yt)*MIN(1,(2028-2026)/conv_n) -> 0.098569667 | J12: =g0_yt+(gl_yt-g0_yt)*MIN(1,(2029-2026)/conv_n) -> 0.089284834 | K12: =g0_yt+(gl_yt-g0_yt)*MIN(1,(2030-2026)/conv_n) -> 0.08 | L12: =g0_yt+(gl_yt-g0_yt)*MIN(1,(2031-2026)/conv_n) -> 0.08 | M12: =g0_yt+(gl_yt-g0_yt)*MIN(1,(2032-2026)/conv_n) -> 0.08 | N12: 三情境相同
A13: YouTube ads | B13: US$B | C13: =Q!J6 -> 36.147 | D13: =Q!K6 -> 40.367 | E13: =Q!L6 -> 20.938 | F13: =(Q!F6+Q!G6)*(1+F12) -> 24.179364 | G13: =E13+F13 -> 45.117364 | H13: =G13*(1+H12) -> 49.983474 | I13: =H13*(1+I12) -> 54.910329 | J13: =I13*(1+J12) -> 59.812989 | K13: =J13*(1+K12) -> 64.598028 | L13: =K13*(1+L12) -> 69.76587 | M13: =L13*(1+M12) -> 75.347139
A14: Google Network 年增 | B14: % | F14: =g0_net -> -0.021785335 | H14: =g0_net+(gl_net-g0_net)*MIN(1,(2027-2026)/conv_n) -> -0.016339001 | I14: =g0_net+(gl_net-g0_net)*MIN(1,(2028-2026)/conv_n) -> -0.010892667 | J14: =g0_net+(gl_net-g0_net)*MIN(1,(2029-2026)/conv_n) -> -0.0054463337 | K14: =g0_net+(gl_net-g0_net)*MIN(1,(2030-2026)/conv_n) -> 0 | L14: =g0_net+(gl_net-g0_net)*MIN(1,(2031-2026)/conv_n) -> 0 | M14: =g0_net+(gl_net-g0_net)*MIN(1,(2032-2026)/conv_n) -> 0 | N14: 三情境相同
A15: Google Network | B15: US$B | C15: =Q!J7 -> 30.359 | D15: =Q!K7 -> 29.792 | E15: =Q!L7 -> 14.274 | F15: =(Q!F7+Q!G7)*(1+F14) -> 14.851255 | G15: =E15+F15 -> 29.125255 | H15: =G15*(1+H14) -> 28.649377 | I15: =H15*(1+I14) -> 28.337309 | J15: =I15*(1+J14) -> 28.182975 | K15: =J15*(1+K14) -> 28.182975 | L15: =K15*(1+L14) -> 28.182975 | M15: =L15*(1+M14) -> 28.182975
A16: Google subscriptions, platforms, and devices 年增 | B16: % | F16: =g0_subs -> 0.17943516 | H16: =g0_subs+(gl_subs-g0_subs)*MIN(1,(2027-2026)/conv_n) -> 0.15957637 | I16: =g0_subs+(gl_subs-g0_subs)*MIN(1,(2028-2026)/conv_n) -> 0.13971758 | J16: =g0_subs+(gl_subs-g0_subs)*MIN(1,(2029-2026)/conv_n) -> 0.11985879 | K16: =g0_subs+(gl_subs-g0_subs)*MIN(1,(2030-2026)/conv_n) -> 0.1 | L16: =g0_subs+(gl_subs-g0_subs)*MIN(1,(2031-2026)/conv_n) -> 0.1 | M16: =g0_subs+(gl_subs-g0_subs)*MIN(1,(2032-2026)/conv_n) -> 0.1 | N16: 三情境相同
A17: Google subscriptions, platforms, and devices | B17: US$B | C17: =Q!J8 -> 40.34 | D17: =Q!K8 -> 48.03 | E17: =Q!L8 -> 25.295 | F17: =(Q!F8+Q!G8)*(1+F16) -> 31.193701 | G17: =E17+F17 -> 56.488701 | H17: =G17*(1+H16) -> 65.502963 | I17: =H17*(1+I16) -> 74.654879 | J17: =I17*(1+J16) -> 83.602922 | K17: =J17*(1+K16) -> 91.963214 | L17: =K17*(1+L16) -> 101.15954 | M17: =L17*(1+M16) -> 111.27549
A18: Google Services | B18: US$B | C18: =Q!J9 -> 304.93 | D18: =Q!K9 -> 342.721 | E18: =Q!L9 -> 184.177 | F18: =F11+F13+F15+F17 -> 209.96542 | G18: =E18+F18 -> 394.14242 | H18: =H11+H13+H15+H17 -> 457.42207 | I18: =I11+I13+I15+I17 -> 523.08041 | J18: =J11+J13+J15+J17 -> 588.63222 | K18: =K11+K13+K15+K17 -> 651.1672 | L18: =L11+L13+L15+L17 -> 702.84521 | M18: =M11+M13+M15+M17 -> 758.84137
A19: Cloud AI（命題子列） | B19: US$B | E19: =Thesis!E38 -> 9.7583729 | F19: =Thesis!F38 -> 13.072238 | G19: =Thesis!G38 -> 22.830611 | H19: =Thesis!H38 -> 38.882858 | I19: =Thesis!I38 -> 56.703559 | J19: =Thesis!J38 -> 73.012119 | K19: =Thesis!K38 -> 85.400179 | L19: =Thesis!L38 -> 94.03926 | M19: =Thesis!M38 -> 99.017013 | N19: Thesis 頁：對外 MW × 每 MW 收入（1H26 為模型估計）
A20: TPU 系統銷售（命題子列） | B20: US$B | E20: 0 | F20: =tpu_2h -> 1 | G20: =E20+F20 -> 1 | H20: =tpu_yr -> 13 | I20: =tpu_yr -> 13 | J20: =tpu_yr -> 13 | K20: =tpu_yr -> 13 | L20: =tpu_yr -> 13 | M20: =tpu_yr -> 13 | N20: C8 b：不走 MW × 每 MW；1H26 金額未揭露 → 0
A21: Cloud 其他年增 | B21: % | F21: =g0_co -> 0.46312246 | H21: =g0_co+(gl_co-g0_co)*MIN(1,(2027-2026)/conv_n) -> 0.36734184 | I21: =g0_co+(gl_co-g0_co)*MIN(1,(2028-2026)/conv_n) -> 0.27156123 | J21: =g0_co+(gl_co-g0_co)*MIN(1,(2029-2026)/conv_n) -> 0.17578061 | K21: =g0_co+(gl_co-g0_co)*MIN(1,(2030-2026)/conv_n) -> 0.08 | L21: =g0_co+(gl_co-g0_co)*MIN(1,(2031-2026)/conv_n) -> 0.08 | M21: =g0_co+(gl_co-g0_co)*MIN(1,(2032-2026)/conv_n) -> 0.08 | N21: 起始＝Cloud 其他近四季年增（Thesis 頁 g0_co），FY2030 收斂到 gl_co
A22: Cloud 其他（命題子列） | B22: US$B | E22: =Q!L11-E19-E20 -> 35.037627 | F22: =E22*(1+F21)^0.5 -> 42.381373 | G22: =E22+F22 -> 77.419 | H22: =G22*(1+H21) -> 105.85824 | I22: =H22*(1+I21) -> 134.60523 | J22: =I22*(1+J21) -> 158.26622 | K22: =J22*(1+K21) -> 170.92752 | L22: =K22*(1+L21) -> 184.60172 | M22: =L22*(1+M21) -> 199.36986 | N22: 1H26＝Google Cloud 實績 − Cloud AI 估計 − TPU；2H26＝1H26 ×(1＋年增)^0.5
A23: Google Cloud | B23: US$B | C23: =Q!J11 -> 43.229 | D23: =Q!K11 -> 58.705 | E23: =Q!L11 -> 44.796 | F23: =F19+F20+F22 -> 56.453611 | G23: =E23+F23 -> 101.24961 | H23: =H19+H20+H22 -> 157.7411 | I23: =I19+I20+I22 -> 204.30879 | J23: =J19+J20+J22 -> 244.27834 | K23: =K19+K20+K22 -> 269.3277 | L23: =L19+L20+L22 -> 291.64098 | M23: =M19+M20+M22 -> 311.38687
A24: Other Bets | B24: US$B | C24: =Q!J12 -> 1.648 | D24: =Q!K12 -> 1.537 | E24: =Q!L12 -> 0.793 | F24: =ob_rev_2H -> 0.75 | G24: =E24+F24 -> 1.543 | H24: =ob_rev_27 -> 1.6 | I24: =ob_rev_28 -> 1.8 | J24: =ob_rev_29 -> 2 | K24: =ob_rev_30 -> 2.2 | L24: =ob_rev_31 -> 2.4 | M24: =ob_rev_32 -> 2.6
A25: Hedging gains (losses) | B25: US$B | C25: =Q!J13 -> 0.211 | D25: =Q!K13 -> -0.127 | E25: =Q!L13 -> -0.074 | F25: 0 | G25: =E25+F25 -> -0.074 | H25: 0 | I25: 0 | J25: 0 | K25: 0 | L25: 0 | M25: 0 | N25: Alphabet-level activities；預測期 0 [Assumed]
A26: 合併營收 | B26: US$B | C26: =Q!J14 -> 350.018 | D26: =Q!K14 -> 402.836 | E26: =Q!L14 -> 229.692 | F26: =F18+F23+F24+F25 -> 267.16903 | G26: =E26+F26 -> 496.86103 | H26: =H18+H23+H24+H25 -> 616.76317 | I26: =I18+I23+I24+I25 -> 729.1892 | J26: =J18+J23+J24+J25 -> 834.91057 | K26: =K18+K23+K24+K25 -> 922.6949 | L26: =L18+L23+L24+L25 -> 996.88619 | M26: =M18+M23+M24+M25 -> 1072.8282
A27: 檢查：產品線合計 − Google Services | B27: US$B | C27: =C11+C13+C15+C17-C18 -> 0 | D27: =D11+D13+D15+D17-D18 -> 0 | E27: =E11+E13+E15+E17-E18 -> 0 | F27: =F11+F13+F15+F17-F18 -> 0 | G27: =G11+G13+G15+G17-G18 -> 0 | H27: =H11+H13+H15+H17-H18 -> 0 | I27: =I11+I13+I15+I17-I18 -> 0 | J27: =J11+J13+J15+J17-J18 -> 0 | ... M27: =M11+M13+M15+M17-M18 -> 0
A28: 檢查：Cloud 子列合計 − Google Cloud | B28: US$B | E28: =E19+E20+E22-E23 -> 0 | F28: =F19+F20+F22-F23 -> 0 | G28: =G19+G20+G22-G23 -> 0 | H28: =H19+H20+H22-H23 -> 0 | I28: =I19+I20+I22-I23 -> 0 | J28: =J19+J20+J22-J23 -> 0 | K28: =K19+K20+K22-K23 -> 0 | L28: =L19+L20+L22-L23 -> 0 | M28: =M19+M20+M22-M23 -> 0
A29: 檢查：分部合計＋避險 − 合併營收 | B29: US$B | C29: =C18+C23+C24+C25-C26 -> 0 | D29: =D18+D23+D24+D25-D26 -> 0 | E29: =E18+E23+E24+E25-E26 -> 0 | F29: =F18+F23+F24+F25-F26 -> 0 | G29: =G18+G23+G24+G25-G26 -> 0 | H29: =H18+H23+H24+H25-H26 -> 0 | I29: =I18+I23+I24+I25-I26 -> 0 | J29: =J18+J23+J24+J25-J26 -> 0 | ... M29: =M18+M23+M24+M25-M26 -> 0
A30: 檢查：實績欄合併營收 − Q 頁（FY2024、FY2025、1H26） | B30: US$B | C30: =C26-Q!J14 -> 0 | D30: =D26-Q!K14 -> 0 | E30: =E26-Q!L14 -> 0
A31: 非 AI 資本支出：Google Services（營收 × cx_svc） | B31: US$B | F31: =F18*cx_svc -> 12.597925 | G31: =F31 -> 12.597925 | H31: =H18*cx_svc -> 27.445324 | I31: =I18*cx_svc -> 31.384824 | J31: =J18*cx_svc -> 35.317933 | K31: =K18*cx_svc -> 39.070032 | L31: =L18*cx_svc -> 42.170712 | M31: =M18*cx_svc -> 45.530482
A32: 非 AI 資本支出：Cloud 其他（營收 × cx_co） | B32: US$B | F32: =F22*cx_co -> 8.4762747 | G32: =F32 -> 8.4762747 | H32: =H22*cx_co -> 21.171648 | I32: =I22*cx_co -> 26.921046 | J32: =J22*cx_co -> 31.653245 | K32: =K22*cx_co -> 34.185504 | L32: =L22*cx_co -> 36.920344 | M32: =M22*cx_co -> 39.873972
A33: 非 AI 資本支出：Other Bets（營收 × cx_ob） | B33: US$B | F33: =F24*cx_ob -> 0.045 | G33: =F33 -> 0.045 | H33: =H24*cx_ob -> 0.096 | I33: =I24*cx_ob -> 0.108 | J33: =J24*cx_ob -> 0.12 | K33: =K24*cx_ob -> 0.132 | L33: =L24*cx_ob -> 0.144 | M33: =M24*cx_ob -> 0.156
A34: 非 AI 資本支出合計 | B34: US$B | F34: =F31+F32+F33 -> 21.1192 | G34: =G31+G32+G33 -> 21.1192 | H34: =H31+H32+H33 -> 48.712972 | I34: =I31+I32+I33 -> 58.413871 | J34: =J31+J32+J33 -> 67.091178 | K34: =K31+K32+K33 -> 73.387536 | L34: =L31+L32+L33 -> 79.235057 | M34: =M31+M32+M33 -> 85.560454
A35: 新增非 AI 折舊：Google Services（年限 life_na） | B35: US$B | F35: =$F$31/life_na*IF(0=0,phi_0,IF(0<life_na,1,IF(0=life_na,1-phi_0,0))) -> 0.31494813 | G35: =F35 -> 0.31494813 | H35: =$F$31/life_na*IF(1=0,phi_0,IF(1<life_na,1,IF(1=life_na,1-phi_0,0)))+$H$31/life_na*IF(0=0,phi_0,IF(0<life_na,1,IF(0=life_na,1-phi_0,0))) -> 1.9459256 | I35: =$F$31/life_na*IF(2=0,phi_0,IF(2<life_na,1,IF(2=life_na,1-phi_0,0)))+$H$31/life_na*IF(1=0,phi_0,IF(1<life_na,1,IF(1=life_na,1-phi_0,0)))+$I$31/life_na*IF(0=0,phi_0,IF(0<life_na,1,IF(0=life_na,1-phi_0,0))) -> 4.7889456 | J35: =$F$31/life_na*IF(3=0,phi_0,IF(3<life_na,1,IF(3=life_na,1-phi_0,0)))+$H$31/life_na*IF(2=0,phi_0,IF(2<life_na,1,IF(2=life_na,1-phi_0,0)))+$I$31/life_na*IF(1=0,phi_0,IF(1<life_na,1,IF(1=life_na,1-phi_0,0)))+$J$31/life_na*IF(0=0,phi_0,IF(0<life_na,1,IF(0=life_na,1-phi_0,0))) -> 8.0257557 | K35: =$F$31/life_na*IF(4=0,phi_0,IF(4<life_na,1,IF(4=life_na,1-phi_0,0)))+$H$31/life_na*IF(3=0,phi_0,IF(3<life_na,1,IF(3=life_na,1-phi_0,0)))+$I$31/life_na*IF(2=0,phi_0,IF(2<life_na,1,IF(2=life_na,1-phi_0,0)))+$J$31/life_na*IF(1=0,phi_0,IF(1<life_na,1,IF(1=life_na,1-phi_0,0)))+$K$31/life_na*IF(0=0,phi_0,IF(0<life_na,1,IF(0=life_na,1-phi_0,0))) -> 11.651352 | L35: =$F$31/life_na*IF(5=0,phi_0,IF(5<life_na,1,IF(5=life_na,1-phi_0,0)))+$H$31/life_na*IF(4=0,phi_0,IF(4<life_na,1,IF(4=life_na,1-phi_0,0)))+$I$31/life_na*IF(3=0,phi_0,IF(3<life_na,1,IF(3=life_na,1-phi_0,0)))+$J$31/life_na*IF(2=0,phi_0,IF(2<life_na,1,IF(2=life_na,1-phi_0,0)))+$K$31/life_na*IF(1=0,phi_0,IF(1<life_na,1,IF(1=life_na,1-phi_0,0)))+$L$31/life_na*IF(0=0,phi_0,IF(0<life_na,1,IF(0=life_na,1-phi_0,0))) -> 15.635872 | M35: =$F$31/life_na*IF(6=0,phi_0,IF(6<life_na,1,IF(6=life_na,1-phi_0,0)))+$H$31/life_na*IF(5=0,phi_0,IF(5<life_na,1,IF(5=life_na,1-phi_0,0)))+$I$31/life_na*IF(4=0,phi_0,IF(4<life_na,1,IF(4=life_na,1-phi_0,0)))+$J$31/life_na*IF(3=0,phi_0,IF(3<life_na,1,IF(3=life_na,1-phi_0,0)))+$K$31/life_na*IF(2=0,phi_0,IF(2<life_na,1,IF(2=life_na,1-phi_0,0)))+$L$31/life_na*IF(1=0,phi_0,IF(1<life_na,1,IF(1=life_na,1-phi_0,0)))+$M$31/life_na*IF(0=0,phi_0,IF(0<life_na,1,IF(0=life_na,1-phi_0,0))) -> 19.936937
A36: 新增非 AI 折舊：Cloud 其他（年限 life_na） | B36: US$B | F36: =$F$32/life_na*IF(0=0,phi_0,IF(0<life_na,1,IF(0=life_na,1-phi_0,0))) -> 0.21190687 | G36: =F36 -> 0.21190687 | H36: =$F$32/life_na*IF(1=0,phi_0,IF(1<life_na,1,IF(1=life_na,1-phi_0,0)))+$H$32/life_na*IF(0=0,phi_0,IF(0<life_na,1,IF(0=life_na,1-phi_0,0))) -> 1.3769187 | I36: =$F$32/life_na*IF(2=0,phi_0,IF(2<life_na,1,IF(2=life_na,1-phi_0,0)))+$H$32/life_na*IF(1=0,phi_0,IF(1<life_na,1,IF(1=life_na,1-phi_0,0)))+$I$32/life_na*IF(0=0,phi_0,IF(0<life_na,1,IF(0=life_na,1-phi_0,0))) -> 3.6378184 | J36: =$F$32/life_na*IF(3=0,phi_0,IF(3<life_na,1,IF(3=life_na,1-phi_0,0)))+$H$32/life_na*IF(2=0,phi_0,IF(2<life_na,1,IF(2=life_na,1-phi_0,0)))+$I$32/life_na*IF(1=0,phi_0,IF(1<life_na,1,IF(1=life_na,1-phi_0,0)))+$J$32/life_na*IF(0=0,phi_0,IF(0<life_na,1,IF(0=life_na,1-phi_0,0))) -> 6.448228 | K36: =$F$32/life_na*IF(4=0,phi_0,IF(4<life_na,1,IF(4=life_na,1-phi_0,0)))+$H$32/life_na*IF(3=0,phi_0,IF(3<life_na,1,IF(3=life_na,1-phi_0,0)))+$I$32/life_na*IF(2=0,phi_0,IF(2<life_na,1,IF(2=life_na,1-phi_0,0)))+$J$32/life_na*IF(1=0,phi_0,IF(1<life_na,1,IF(1=life_na,1-phi_0,0)))+$K$32/life_na*IF(0=0,phi_0,IF(0<life_na,1,IF(0=life_na,1-phi_0,0))) -> 9.6768589 | L36: =$F$32/life_na*IF(5=0,phi_0,IF(5<life_na,1,IF(5=life_na,1-phi_0,0)))+$H$32/life_na*IF(4=0,phi_0,IF(4<life_na,1,IF(4=life_na,1-phi_0,0)))+$I$32/life_na*IF(3=0,phi_0,IF(3<life_na,1,IF(3=life_na,1-phi_0,0)))+$J$32/life_na*IF(2=0,phi_0,IF(2<life_na,1,IF(2=life_na,1-phi_0,0)))+$K$32/life_na*IF(1=0,phi_0,IF(1<life_na,1,IF(1=life_na,1-phi_0,0)))+$L$32/life_na*IF(0=0,phi_0,IF(0<life_na,1,IF(0=life_na,1-phi_0,0))) -> 13.16378 | M36: =$F$32/life_na*IF(6=0,phi_0,IF(6<life_na,1,IF(6=life_na,1-phi_0,0)))+$H$32/life_na*IF(5=0,phi_0,IF(5<life_na,1,IF(5=life_na,1-phi_0,0)))+$I$32/life_na*IF(4=0,phi_0,IF(4<life_na,1,IF(4=life_na,1-phi_0,0)))+$J$32/life_na*IF(3=0,phi_0,IF(3<life_na,1,IF(3=life_na,1-phi_0,0)))+$K$32/life_na*IF(2=0,phi_0,IF(2<life_na,1,IF(2=life_na,1-phi_0,0)))+$L$32/life_na*IF(1=0,phi_0,IF(1<life_na,1,IF(1=life_na,1-phi_0,0)))+$M$32/life_na*IF(0=0,phi_0,IF(0<life_na,1,IF(0=life_na,1-phi_0,0))) -> 16.929655
A37: 新增非 AI 折舊：Other Bets（年限 life_na） | B37: US$B | F37: =$F$33/life_na*IF(0=0,phi_0,IF(0<life_na,1,IF(0=life_na,1-phi_0,0))) -> 0.001125 | G37: =F37 -> 0.001125 | H37: =$F$33/life_na*IF(1=0,phi_0,IF(1<life_na,1,IF(1=life_na,1-phi_0,0)))+$H$33/life_na*IF(0=0,phi_0,IF(0<life_na,1,IF(0=life_na,1-phi_0,0))) -> 0.0069 | I37: =$F$33/life_na*IF(2=0,phi_0,IF(2<life_na,1,IF(2=life_na,1-phi_0,0)))+$H$33/life_na*IF(1=0,phi_0,IF(1<life_na,1,IF(1=life_na,1-phi_0,0)))+$I$33/life_na*IF(0=0,phi_0,IF(0<life_na,1,IF(0=life_na,1-phi_0,0))) -> 0.0168 | J37: =$F$33/life_na*IF(3=0,phi_0,IF(3<life_na,1,IF(3=life_na,1-phi_0,0)))+$H$33/life_na*IF(2=0,phi_0,IF(2<life_na,1,IF(2=life_na,1-phi_0,0)))+$I$33/life_na*IF(1=0,phi_0,IF(1<life_na,1,IF(1=life_na,1-phi_0,0)))+$J$33/life_na*IF(0=0,phi_0,IF(0<life_na,1,IF(0=life_na,1-phi_0,0))) -> 0.0279 | K37: =$F$33/life_na*IF(4=0,phi_0,IF(4<life_na,1,IF(4=life_na,1-phi_0,0)))+$H$33/life_na*IF(3=0,phi_0,IF(3<life_na,1,IF(3=life_na,1-phi_0,0)))+$I$33/life_na*IF(2=0,phi_0,IF(2<life_na,1,IF(2=life_na,1-phi_0,0)))+$J$33/life_na*IF(1=0,phi_0,IF(1<life_na,1,IF(1=life_na,1-phi_0,0)))+$K$33/life_na*IF(0=0,phi_0,IF(0<life_na,1,IF(0=life_na,1-phi_0,0))) -> 0.0402 | L37: =$F$33/life_na*IF(5=0,phi_0,IF(5<life_na,1,IF(5=life_na,1-phi_0,0)))+$H$33/life_na*IF(4=0,phi_0,IF(4<life_na,1,IF(4=life_na,1-phi_0,0)))+$I$33/life_na*IF(3=0,phi_0,IF(3<life_na,1,IF(3=life_na,1-phi_0,0)))+$J$33/life_na*IF(2=0,phi_0,IF(2<life_na,1,IF(2=life_na,1-phi_0,0)))+$K$33/life_na*IF(1=0,phi_0,IF(1<life_na,1,IF(1=life_na,1-phi_0,0)))+$L$33/life_na*IF(0=0,phi_0,IF(0<life_na,1,IF(0=life_na,1-phi_0,0))) -> 0.0537 | M37: =$F$33/life_na*IF(6=0,phi_0,IF(6<life_na,1,IF(6=life_na,1-phi_0,0)))+$H$33/life_na*IF(5=0,phi_0,IF(5<life_na,1,IF(5=life_na,1-phi_0,0)))+$I$33/life_na*IF(4=0,phi_0,IF(4<life_na,1,IF(4=life_na,1-phi_0,0)))+$J$33/life_na*IF(3=0,phi_0,IF(3<life_na,1,IF(3=life_na,1-phi_0,0)))+$K$33/life_na*IF(2=0,phi_0,IF(2<life_na,1,IF(2=life_na,1-phi_0,0)))+$L$33/life_na*IF(1=0,phi_0,IF(1<life_na,1,IF(1=life_na,1-phi_0,0)))+$M$33/life_na*IF(0=0,phi_0,IF(0<life_na,1,IF(0=life_na,1-phi_0,0))) -> 0.0684
A38: 新增非 AI 折舊合計 | B38: US$B | F38: =F35+F36+F37 -> 0.52798 | G38: =G35+G36+G37 -> 0.52798 | H38: =H35+H36+H37 -> 3.3297443 | I38: =I35+I36+I37 -> 8.443564 | J38: =J35+J36+J37 -> 14.501884 | K38: =K35+K36+K37 -> 21.36841 | L38: =L35+L36+L37 -> 28.853352 | M38: =M35+M36+M37 -> 36.934993
A40: 情境 B（近四季成長收斂；基準）
A41: 項目 | B41: 單位 | C41: FY2024A | D41: FY2025A | E41: 1H26A | F41: 2H26E | G41: FY2026E | H41: FY2027E | I41: FY2028E | J41: FY2029E | K41: FY2030E | L41: FY2031E | M41: FY2032E | N41: 說明
A42: Search B 路徑年增 | B42: % | F42: =g0_search -> 0.16801321 | H42: =g0_search+(gl_search-g0_search)*MIN(1,(2027-2026)/conv_n) -> 0.14600991 | I42: =g0_search+(gl_search-g0_search)*MIN(1,(2028-2026)/conv_n) -> 0.12400661 | J42: =g0_search+(gl_search-g0_search)*MIN(1,(2029-2026)/conv_n) -> 0.1020033 | K42: =g0_search+(gl_search-g0_search)*MIN(1,(2030-2026)/conv_n) -> 0.08 | L42: =g0_search+(gl_search-g0_search)*MIN(1,(2031-2026)/conv_n) -> 0.08 | M42: =g0_search+(gl_search-g0_search)*MIN(1,(2032-2026)/conv_n) -> 0.08 | N42: 2H26 年增＝近四季 +16.8%（Q 頁），FY2030 收斂到 gl_search
A43: Google Search & other：B 路徑 | B43: US$B | C43: =Q!J5 -> 198.084 | D43: =Q!K5 -> 224.532 | E43: =Q!L5 -> 123.67 | F43: =(Q!F5+Q!G5)*(1+F42) -> 139.7411 | G43: =E43+F43 -> 263.4111 | H43: =G43*(1+H42) -> 301.87173 | I43: =H43*(1+I42) -> 339.30582 | J43: =I43*(1+J42) -> 373.91613 | K43: =J43*(1+K42) -> 403.82942 | L43: =K43*(1+L42) -> 436.13578 | M43: =L43*(1+M42) -> 471.02664
A44: 情境爬坡（FY2026 0 → FY2030 1） | B44: x | F44: 0 | H44: =MIN(1,(2027-2026)/conv_n) -> 0.25 | I44: =MIN(1,(2028-2026)/conv_n) -> 0.5 | J44: =MIN(1,(2029-2026)/conv_n) -> 0.75 | K44: =MIN(1,(2030-2026)/conv_n) -> 1 | L44: =MIN(1,(2031-2026)/conv_n) -> 1 | M44: =MIN(1,(2032-2026)/conv_n) -> 1
A45: 查詢分流（相對 B 路徑） | B45: % | F45: =0*F44 -> 0 | H45: =0*H44 -> 0 | I45: =0*I44 -> 0 | J45: =0*J44 -> 0 | K45: =0*K44 -> 0 | L45: =0*L44 -> 0 | M45: =0*M44 -> 0 | N45: 基準不設分流
A46: 每次查詢變現變動（相對 B 路徑） | B46: % | F46: =0*F44 -> 0 | H46: =0*H44 -> 0 | I46: =0*I44 -> 0 | J46: =0*J44 -> 0 | K46: =0*K44 -> 0 | L46: =0*L44 -> 0 | M46: =0*M44 -> 0
A47: Google Search & other | B47: US$B | C47: =C43 -> 198.084 | D47: =D43 -> 224.532 | E47: =E43 -> 123.67 | F47: =F43*(1-F45)*(1+F46) -> 139.7411 | G47: =E47+F47 -> 263.4111 | H47: =H43*(1-H45)*(1+H46) -> 301.87173 | I47: =I43*(1-I45)*(1+I46) -> 339.30582 | J47: =J43*(1-J45)*(1+J46) -> 373.91613 | K47: =K43*(1-K45)*(1+K46) -> 403.82942 | L47: =L43*(1-L45)*(1+L46) -> 436.13578 | M47: =M43*(1-M45)*(1+M46) -> 471.02664
A48: YouTube ads 年增 | B48: % | F48: =g0_yt -> 0.11713933 | H48: =g0_yt+(gl_yt-g0_yt)*MIN(1,(2027-2026)/conv_n) -> 0.1078545 | I48: =g0_yt+(gl_yt-g0_yt)*MIN(1,(2028-2026)/conv_n) -> 0.098569667 | J48: =g0_yt+(gl_yt-g0_yt)*MIN(1,(2029-2026)/conv_n) -> 0.089284834 | K48: =g0_yt+(gl_yt-g0_yt)*MIN(1,(2030-2026)/conv_n) -> 0.08 | L48: =g0_yt+(gl_yt-g0_yt)*MIN(1,(2031-2026)/conv_n) -> 0.08 | M48: =g0_yt+(gl_yt-g0_yt)*MIN(1,(2032-2026)/conv_n) -> 0.08 | N48: 三情境相同
A49: YouTube ads | B49: US$B | C49: =Q!J6 -> 36.147 | D49: =Q!K6 -> 40.367 | E49: =Q!L6 -> 20.938 | F49: =(Q!F6+Q!G6)*(1+F48) -> 24.179364 | G49: =E49+F49 -> 45.117364 | H49: =G49*(1+H48) -> 49.983474 | I49: =H49*(1+I48) -> 54.910329 | J49: =I49*(1+J48) -> 59.812989 | K49: =J49*(1+K48) -> 64.598028 | L49: =K49*(1+L48) -> 69.76587 | M49: =L49*(1+M48) -> 75.347139
A50: Google Network 年增 | B50: % | F50: =g0_net -> -0.021785335 | H50: =g0_net+(gl_net-g0_net)*MIN(1,(2027-2026)/conv_n) -> -0.016339001 | I50: =g0_net+(gl_net-g0_net)*MIN(1,(2028-2026)/conv_n) -> -0.010892667 | J50: =g0_net+(gl_net-g0_net)*MIN(1,(2029-2026)/conv_n) -> -0.0054463337 | K50: =g0_net+(gl_net-g0_net)*MIN(1,(2030-2026)/conv_n) -> 0 | L50: =g0_net+(gl_net-g0_net)*MIN(1,(2031-2026)/conv_n) -> 0 | M50: =g0_net+(gl_net-g0_net)*MIN(1,(2032-2026)/conv_n) -> 0 | N50: 三情境相同
A51: Google Network | B51: US$B | C51: =Q!J7 -> 30.359 | D51: =Q!K7 -> 29.792 | E51: =Q!L7 -> 14.274 | F51: =(Q!F7+Q!G7)*(1+F50) -> 14.851255 | G51: =E51+F51 -> 29.125255 | H51: =G51*(1+H50) -> 28.649377 | I51: =H51*(1+I50) -> 28.337309 | J51: =I51*(1+J50) -> 28.182975 | K51: =J51*(1+K50) -> 28.182975 | L51: =K51*(1+L50) -> 28.182975 | M51: =L51*(1+M50) -> 28.182975
A52: Google subscriptions, platforms, and devices 年增 | B52: % | F52: =g0_subs -> 0.17943516 | H52: =g0_subs+(gl_subs-g0_subs)*MIN(1,(2027-2026)/conv_n) -> 0.15957637 | I52: =g0_subs+(gl_subs-g0_subs)*MIN(1,(2028-2026)/conv_n) -> 0.13971758 | J52: =g0_subs+(gl_subs-g0_subs)*MIN(1,(2029-2026)/conv_n) -> 0.11985879 | K52: =g0_subs+(gl_subs-g0_subs)*MIN(1,(2030-2026)/conv_n) -> 0.1 | L52: =g0_subs+(gl_subs-g0_subs)*MIN(1,(2031-2026)/conv_n) -> 0.1 | M52: =g0_subs+(gl_subs-g0_subs)*MIN(1,(2032-2026)/conv_n) -> 0.1 | N52: 三情境相同
A53: Google subscriptions, platforms, and devices | B53: US$B | C53: =Q!J8 -> 40.34 | D53: =Q!K8 -> 48.03 | E53: =Q!L8 -> 25.295 | F53: =(Q!F8+Q!G8)*(1+F52) -> 31.193701 | G53: =E53+F53 -> 56.488701 | H53: =G53*(1+H52) -> 65.502963 | I53: =H53*(1+I52) -> 74.654879 | J53: =I53*(1+J52) -> 83.602922 | K53: =J53*(1+K52) -> 91.963214 | L53: =K53*(1+L52) -> 101.15954 | M53: =L53*(1+M52) -> 111.27549
A54: Google Services | B54: US$B | C54: =Q!J9 -> 304.93 | D54: =Q!K9 -> 342.721 | E54: =Q!L9 -> 184.177 | F54: =F47+F49+F51+F53 -> 209.96542 | G54: =E54+F54 -> 394.14242 | H54: =H47+H49+H51+H53 -> 446.00755 | I54: =I47+I49+I51+I53 -> 497.20834 | J54: =J47+J49+J51+J53 -> 545.51502 | K54: =K47+K49+K51+K53 -> 588.57364 | L54: =L47+L49+L51+L53 -> 635.24416 | M54: =M47+M49+M51+M53 -> 685.83224
A55: Cloud AI（命題子列） | B55: US$B | E55: =Thesis!E38 -> 9.7583729 | F55: =Thesis!F38 -> 13.072238 | G55: =Thesis!G38 -> 22.830611 | H55: =Thesis!H38 -> 38.882858 | I55: =Thesis!I38 -> 56.703559 | J55: =Thesis!J38 -> 73.012119 | K55: =Thesis!K38 -> 85.400179 | L55: =Thesis!L38 -> 94.03926 | M55: =Thesis!M38 -> 99.017013 | N55: Thesis 頁：對外 MW × 每 MW 收入（1H26 為模型估計）
A56: TPU 系統銷售（命題子列） | B56: US$B | E56: 0 | F56: =tpu_2h -> 1 | G56: =E56+F56 -> 1 | H56: =tpu_yr -> 13 | I56: =tpu_yr -> 13 | J56: =tpu_yr -> 13 | K56: =tpu_yr -> 13 | L56: =tpu_yr -> 13 | M56: =tpu_yr -> 13 | N56: C8 b：不走 MW × 每 MW；1H26 金額未揭露 → 0
A57: Cloud 其他年增 | B57: % | F57: =g0_co -> 0.46312246 | H57: =g0_co+(gl_co-g0_co)*MIN(1,(2027-2026)/conv_n) -> 0.36734184 | I57: =g0_co+(gl_co-g0_co)*MIN(1,(2028-2026)/conv_n) -> 0.27156123 | J57: =g0_co+(gl_co-g0_co)*MIN(1,(2029-2026)/conv_n) -> 0.17578061 | K57: =g0_co+(gl_co-g0_co)*MIN(1,(2030-2026)/conv_n) -> 0.08 | L57: =g0_co+(gl_co-g0_co)*MIN(1,(2031-2026)/conv_n) -> 0.08 | M57: =g0_co+(gl_co-g0_co)*MIN(1,(2032-2026)/conv_n) -> 0.08 | N57: 起始＝Cloud 其他近四季年增（Thesis 頁 g0_co），FY2030 收斂到 gl_co
A58: Cloud 其他（命題子列） | B58: US$B | E58: =Q!L11-E55-E56 -> 35.037627 | F58: =E58*(1+F57)^0.5 -> 42.381373 | G58: =E58+F58 -> 77.419 | H58: =G58*(1+H57) -> 105.85824 | I58: =H58*(1+I57) -> 134.60523 | J58: =I58*(1+J57) -> 158.26622 | K58: =J58*(1+K57) -> 170.92752 | L58: =K58*(1+L57) -> 184.60172 | M58: =L58*(1+M57) -> 199.36986 | N58: 1H26＝Google Cloud 實績 − Cloud AI 估計 − TPU；2H26＝1H26 ×(1＋年增)^0.5
A59: Google Cloud | B59: US$B | C59: =Q!J11 -> 43.229 | D59: =Q!K11 -> 58.705 | E59: =Q!L11 -> 44.796 | F59: =F55+F56+F58 -> 56.453611 | G59: =E59+F59 -> 101.24961 | H59: =H55+H56+H58 -> 157.7411 | I59: =I55+I56+I58 -> 204.30879 | J59: =J55+J56+J58 -> 244.27834 | K59: =K55+K56+K58 -> 269.3277 | L59: =L55+L56+L58 -> 291.64098 | M59: =M55+M56+M58 -> 311.38687
A60: Other Bets | B60: US$B | C60: =Q!J12 -> 1.648 | D60: =Q!K12 -> 1.537 | E60: =Q!L12 -> 0.793 | F60: =ob_rev_2H -> 0.75 | G60: =E60+F60 -> 1.543 | H60: =ob_rev_27 -> 1.6 | I60: =ob_rev_28 -> 1.8 | J60: =ob_rev_29 -> 2 | K60: =ob_rev_30 -> 2.2 | L60: =ob_rev_31 -> 2.4 | M60: =ob_rev_32 -> 2.6
A61: Hedging gains (losses) | B61: US$B | C61: =Q!J13 -> 0.211 | D61: =Q!K13 -> -0.127 | E61: =Q!L13 -> -0.074 | F61: 0 | G61: =E61+F61 -> -0.074 | H61: 0 | I61: 0 | J61: 0 | K61: 0 | L61: 0 | M61: 0 | N61: Alphabet-level activities；預測期 0 [Assumed]
A62: 合併營收 | B62: US$B | C62: =Q!J14 -> 350.018 | D62: =Q!K14 -> 402.836 | E62: =Q!L14 -> 229.692 | F62: =F54+F59+F60+F61 -> 267.16903 | G62: =E62+F62 -> 496.86103 | H62: =H54+H59+H60+H61 -> 605.34864 | I62: =I54+I59+I60+I61 -> 703.31713 | J62: =J54+J59+J60+J61 -> 791.79336 | K62: =K54+K59+K60+K61 -> 860.10134 | L62: =L54+L59+L60+L61 -> 929.28514 | M62: =M54+M59+M60+M61 -> 999.81912
A63: 檢查：產品線合計 − Google Services | B63: US$B | C63: =C47+C49+C51+C53-C54 -> 0 | D63: =D47+D49+D51+D53-D54 -> 0 | E63: =E47+E49+E51+E53-E54 -> 0 | F63: =F47+F49+F51+F53-F54 -> 0 | G63: =G47+G49+G51+G53-G54 -> 0 | H63: =H47+H49+H51+H53-H54 -> 0 | I63: =I47+I49+I51+I53-I54 -> 0 | J63: =J47+J49+J51+J53-J54 -> 0 | ... M63: =M47+M49+M51+M53-M54 -> 0
A64: 檢查：Cloud 子列合計 − Google Cloud | B64: US$B | E64: =E55+E56+E58-E59 -> 0 | F64: =F55+F56+F58-F59 -> 0 | G64: =G55+G56+G58-G59 -> 0 | H64: =H55+H56+H58-H59 -> 0 | I64: =I55+I56+I58-I59 -> 0 | J64: =J55+J56+J58-J59 -> 0 | K64: =K55+K56+K58-K59 -> 0 | L64: =L55+L56+L58-L59 -> 0 | M64: =M55+M56+M58-M59 -> 0
A65: 檢查：分部合計＋避險 − 合併營收 | B65: US$B | C65: =C54+C59+C60+C61-C62 -> 0 | D65: =D54+D59+D60+D61-D62 -> 0 | E65: =E54+E59+E60+E61-E62 -> 0 | F65: =F54+F59+F60+F61-F62 -> 0 | G65: =G54+G59+G60+G61-G62 -> 0 | H65: =H54+H59+H60+H61-H62 -> 0 | I65: =I54+I59+I60+I61-I62 -> 0 | J65: =J54+J59+J60+J61-J62 -> 0 | ... M65: =M54+M59+M60+M61-M62 -> 0
A66: 檢查：實績欄合併營收 − Q 頁（FY2024、FY2025、1H26） | B66: US$B | C66: =C62-Q!J14 -> 0 | D66: =D62-Q!K14 -> 0 | E66: =E62-Q!L14 -> 0
A67: 非 AI 資本支出：Google Services（營收 × cx_svc） | B67: US$B | F67: =F54*cx_svc -> 12.597925 | G67: =F67 -> 12.597925 | H67: =H54*cx_svc -> 26.760453 | I67: =I54*cx_svc -> 29.8325 | J67: =J54*cx_svc -> 32.730901 | K67: =K54*cx_svc -> 35.314419 | L67: =L54*cx_svc -> 38.11465 | M67: =M54*cx_svc -> 41.149935
A68: 非 AI 資本支出：Cloud 其他（營收 × cx_co） | B68: US$B | F68: =F58*cx_co -> 8.4762747 | G68: =F68 -> 8.4762747 | H68: =H58*cx_co -> 21.171648 | I68: =I58*cx_co -> 26.921046 | J68: =J58*cx_co -> 31.653245 | K68: =K58*cx_co -> 34.185504 | L68: =L58*cx_co -> 36.920344 | M68: =M58*cx_co -> 39.873972
A69: 非 AI 資本支出：Other Bets（營收 × cx_ob） | B69: US$B | F69: =F60*cx_ob -> 0.045 | G69: =F69 -> 0.045 | H69: =H60*cx_ob -> 0.096 | I69: =I60*cx_ob -> 0.108 | J69: =J60*cx_ob -> 0.12 | K69: =K60*cx_ob -> 0.132 | L69: =L60*cx_ob -> 0.144 | M69: =M60*cx_ob -> 0.156
A70: 非 AI 資本支出合計 | B70: US$B | F70: =F67+F68+F69 -> 21.1192 | G70: =G67+G68+G69 -> 21.1192 | H70: =H67+H68+H69 -> 48.028101 | I70: =I67+I68+I69 -> 56.861547 | J70: =J67+J68+J69 -> 64.504146 | K70: =K67+K68+K69 -> 69.631923 | L70: =L67+L68+L69 -> 75.178994 | M70: =M67+M68+M69 -> 81.179907
A71: 新增非 AI 折舊：Google Services（年限 life_na） | B71: US$B | F71: =$F$67/life_na*IF(0=0,phi_0,IF(0<life_na,1,IF(0=life_na,1-phi_0,0))) -> 0.31494813 | G71: =F71 -> 0.31494813 | H71: =$F$67/life_na*IF(1=0,phi_0,IF(1<life_na,1,IF(1=life_na,1-phi_0,0)))+$H$67/life_na*IF(0=0,phi_0,IF(0<life_na,1,IF(0=life_na,1-phi_0,0))) -> 1.9288038 | I71: =$F$67/life_na*IF(2=0,phi_0,IF(2<life_na,1,IF(2=life_na,1-phi_0,0)))+$H$67/life_na*IF(1=0,phi_0,IF(1<life_na,1,IF(1=life_na,1-phi_0,0)))+$I$67/life_na*IF(0=0,phi_0,IF(0<life_na,1,IF(0=life_na,1-phi_0,0))) -> 4.6816503 | J71: =$F$67/life_na*IF(3=0,phi_0,IF(3<life_na,1,IF(3=life_na,1-phi_0,0)))+$H$67/life_na*IF(2=0,phi_0,IF(2<life_na,1,IF(2=life_na,1-phi_0,0)))+$I$67/life_na*IF(1=0,phi_0,IF(1<life_na,1,IF(1=life_na,1-phi_0,0)))+$J$67/life_na*IF(0=0,phi_0,IF(0<life_na,1,IF(0=life_na,1-phi_0,0))) -> 7.7373604 | K71: =$F$67/life_na*IF(4=0,phi_0,IF(4<life_na,1,IF(4=life_na,1-phi_0,0)))+$H$67/life_na*IF(3=0,phi_0,IF(3<life_na,1,IF(3=life_na,1-phi_0,0)))+$I$67/life_na*IF(2=0,phi_0,IF(2<life_na,1,IF(2=life_na,1-phi_0,0)))+$J$67/life_na*IF(1=0,phi_0,IF(1<life_na,1,IF(1=life_na,1-phi_0,0)))+$K$67/life_na*IF(0=0,phi_0,IF(0<life_na,1,IF(0=life_na,1-phi_0,0))) -> 11.075038 | L71: =$F$67/life_na*IF(5=0,phi_0,IF(5<life_na,1,IF(5=life_na,1-phi_0,0)))+$H$67/life_na*IF(4=0,phi_0,IF(4<life_na,1,IF(4=life_na,1-phi_0,0)))+$I$67/life_na*IF(3=0,phi_0,IF(3<life_na,1,IF(3=life_na,1-phi_0,0)))+$J$67/life_na*IF(2=0,phi_0,IF(2<life_na,1,IF(2=life_na,1-phi_0,0)))+$K$67/life_na*IF(1=0,phi_0,IF(1<life_na,1,IF(1=life_na,1-phi_0,0)))+$L$67/life_na*IF(0=0,phi_0,IF(0<life_na,1,IF(0=life_na,1-phi_0,0))) -> 14.676486 | M71: =$F$67/life_na*IF(6=0,phi_0,IF(6<life_na,1,IF(6=life_na,1-phi_0,0)))+$H$67/life_na*IF(5=0,phi_0,IF(5<life_na,1,IF(5=life_na,1-phi_0,0)))+$I$67/life_na*IF(4=0,phi_0,IF(4<life_na,1,IF(4=life_na,1-phi_0,0)))+$J$67/life_na*IF(3=0,phi_0,IF(3<life_na,1,IF(3=life_na,1-phi_0,0)))+$K$67/life_na*IF(2=0,phi_0,IF(2<life_na,1,IF(2=life_na,1-phi_0,0)))+$L$67/life_na*IF(1=0,phi_0,IF(1<life_na,1,IF(1=life_na,1-phi_0,0)))+$M$67/life_na*IF(0=0,phi_0,IF(0<life_na,1,IF(0=life_na,1-phi_0,0))) -> 18.563833
A72: 新增非 AI 折舊：Cloud 其他（年限 life_na） | B72: US$B | F72: =$F$68/life_na*IF(0=0,phi_0,IF(0<life_na,1,IF(0=life_na,1-phi_0,0))) -> 0.21190687 | G72: =F72 -> 0.21190687 | H72: =$F$68/life_na*IF(1=0,phi_0,IF(1<life_na,1,IF(1=life_na,1-phi_0,0)))+$H$68/life_na*IF(0=0,phi_0,IF(0<life_na,1,IF(0=life_na,1-phi_0,0))) -> 1.3769187 | I72: =$F$68/life_na*IF(2=0,phi_0,IF(2<life_na,1,IF(2=life_na,1-phi_0,0)))+$H$68/life_na*IF(1=0,phi_0,IF(1<life_na,1,IF(1=life_na,1-phi_0,0)))+$I$68/life_na*IF(0=0,phi_0,IF(0<life_na,1,IF(0=life_na,1-phi_0,0))) -> 3.6378184 | J72: =$F$68/life_na*IF(3=0,phi_0,IF(3<life_na,1,IF(3=life_na,1-phi_0,0)))+$H$68/life_na*IF(2=0,phi_0,IF(2<life_na,1,IF(2=life_na,1-phi_0,0)))+$I$68/life_na*IF(1=0,phi_0,IF(1<life_na,1,IF(1=life_na,1-phi_0,0)))+$J$68/life_na*IF(0=0,phi_0,IF(0<life_na,1,IF(0=life_na,1-phi_0,0))) -> 6.448228 | K72: =$F$68/life_na*IF(4=0,phi_0,IF(4<life_na,1,IF(4=life_na,1-phi_0,0)))+$H$68/life_na*IF(3=0,phi_0,IF(3<life_na,1,IF(3=life_na,1-phi_0,0)))+$I$68/life_na*IF(2=0,phi_0,IF(2<life_na,1,IF(2=life_na,1-phi_0,0)))+$J$68/life_na*IF(1=0,phi_0,IF(1<life_na,1,IF(1=life_na,1-phi_0,0)))+$K$68/life_na*IF(0=0,phi_0,IF(0<life_na,1,IF(0=life_na,1-phi_0,0))) -> 9.6768589 | L72: =$F$68/life_na*IF(5=0,phi_0,IF(5<life_na,1,IF(5=life_na,1-phi_0,0)))+$H$68/life_na*IF(4=0,phi_0,IF(4<life_na,1,IF(4=life_na,1-phi_0,0)))+$I$68/life_na*IF(3=0,phi_0,IF(3<life_na,1,IF(3=life_na,1-phi_0,0)))+$J$68/life_na*IF(2=0,phi_0,IF(2<life_na,1,IF(2=life_na,1-phi_0,0)))+$K$68/life_na*IF(1=0,phi_0,IF(1<life_na,1,IF(1=life_na,1-phi_0,0)))+$L$68/life_na*IF(0=0,phi_0,IF(0<life_na,1,IF(0=life_na,1-phi_0,0))) -> 13.16378 | M72: =$F$68/life_na*IF(6=0,phi_0,IF(6<life_na,1,IF(6=life_na,1-phi_0,0)))+$H$68/life_na*IF(5=0,phi_0,IF(5<life_na,1,IF(5=life_na,1-phi_0,0)))+$I$68/life_na*IF(4=0,phi_0,IF(4<life_na,1,IF(4=life_na,1-phi_0,0)))+$J$68/life_na*IF(3=0,phi_0,IF(3<life_na,1,IF(3=life_na,1-phi_0,0)))+$K$68/life_na*IF(2=0,phi_0,IF(2<life_na,1,IF(2=life_na,1-phi_0,0)))+$L$68/life_na*IF(1=0,phi_0,IF(1<life_na,1,IF(1=life_na,1-phi_0,0)))+$M$68/life_na*IF(0=0,phi_0,IF(0<life_na,1,IF(0=life_na,1-phi_0,0))) -> 16.929655
A73: 新增非 AI 折舊：Other Bets（年限 life_na） | B73: US$B | F73: =$F$69/life_na*IF(0=0,phi_0,IF(0<life_na,1,IF(0=life_na,1-phi_0,0))) -> 0.001125 | G73: =F73 -> 0.001125 | H73: =$F$69/life_na*IF(1=0,phi_0,IF(1<life_na,1,IF(1=life_na,1-phi_0,0)))+$H$69/life_na*IF(0=0,phi_0,IF(0<life_na,1,IF(0=life_na,1-phi_0,0))) -> 0.0069 | I73: =$F$69/life_na*IF(2=0,phi_0,IF(2<life_na,1,IF(2=life_na,1-phi_0,0)))+$H$69/life_na*IF(1=0,phi_0,IF(1<life_na,1,IF(1=life_na,1-phi_0,0)))+$I$69/life_na*IF(0=0,phi_0,IF(0<life_na,1,IF(0=life_na,1-phi_0,0))) -> 0.0168 | J73: =$F$69/life_na*IF(3=0,phi_0,IF(3<life_na,1,IF(3=life_na,1-phi_0,0)))+$H$69/life_na*IF(2=0,phi_0,IF(2<life_na,1,IF(2=life_na,1-phi_0,0)))+$I$69/life_na*IF(1=0,phi_0,IF(1<life_na,1,IF(1=life_na,1-phi_0,0)))+$J$69/life_na*IF(0=0,phi_0,IF(0<life_na,1,IF(0=life_na,1-phi_0,0))) -> 0.0279 | K73: =$F$69/life_na*IF(4=0,phi_0,IF(4<life_na,1,IF(4=life_na,1-phi_0,0)))+$H$69/life_na*IF(3=0,phi_0,IF(3<life_na,1,IF(3=life_na,1-phi_0,0)))+$I$69/life_na*IF(2=0,phi_0,IF(2<life_na,1,IF(2=life_na,1-phi_0,0)))+$J$69/life_na*IF(1=0,phi_0,IF(1<life_na,1,IF(1=life_na,1-phi_0,0)))+$K$69/life_na*IF(0=0,phi_0,IF(0<life_na,1,IF(0=life_na,1-phi_0,0))) -> 0.0402 | L73: =$F$69/life_na*IF(5=0,phi_0,IF(5<life_na,1,IF(5=life_na,1-phi_0,0)))+$H$69/life_na*IF(4=0,phi_0,IF(4<life_na,1,IF(4=life_na,1-phi_0,0)))+$I$69/life_na*IF(3=0,phi_0,IF(3<life_na,1,IF(3=life_na,1-phi_0,0)))+$J$69/life_na*IF(2=0,phi_0,IF(2<life_na,1,IF(2=life_na,1-phi_0,0)))+$K$69/life_na*IF(1=0,phi_0,IF(1<life_na,1,IF(1=life_na,1-phi_0,0)))+$L$69/life_na*IF(0=0,phi_0,IF(0<life_na,1,IF(0=life_na,1-phi_0,0))) -> 0.0537 | M73: =$F$69/life_na*IF(6=0,phi_0,IF(6<life_na,1,IF(6=life_na,1-phi_0,0)))+$H$69/life_na*IF(5=0,phi_0,IF(5<life_na,1,IF(5=life_na,1-phi_0,0)))+$I$69/life_na*IF(4=0,phi_0,IF(4<life_na,1,IF(4=life_na,1-phi_0,0)))+$J$69/life_na*IF(3=0,phi_0,IF(3<life_na,1,IF(3=life_na,1-phi_0,0)))+$K$69/life_na*IF(2=0,phi_0,IF(2<life_na,1,IF(2=life_na,1-phi_0,0)))+$L$69/life_na*IF(1=0,phi_0,IF(1<life_na,1,IF(1=life_na,1-phi_0,0)))+$M$69/life_na*IF(0=0,phi_0,IF(0<life_na,1,IF(0=life_na,1-phi_0,0))) -> 0.0684
A74: 新增非 AI 折舊合計 | B74: US$B | F74: =F71+F72+F73 -> 0.52798 | G74: =G71+G72+G73 -> 0.52798 | H74: =H71+H72+H73 -> 3.3126225 | I74: =I71+I72+I73 -> 8.3362687 | J74: =J71+J72+J73 -> 14.213488 | K74: =K71+K72+K73 -> 20.792097 | L74: =L71+L72+L73 -> 27.893966 | M74: =M71+M72+M73 -> 35.561889
A76: 情境 C（查詢被 AI 助理分流、每次查詢變現下降）
A77: 項目 | B77: 單位 | C77: FY2024A | D77: FY2025A | E77: 1H26A | F77: 2H26E | G77: FY2026E | H77: FY2027E | I77: FY2028E | J77: FY2029E | K77: FY2030E | L77: FY2031E | M77: FY2032E | N77: 說明
A78: Search B 路徑年增 | B78: % | F78: =g0_search -> 0.16801321 | H78: =g0_search+(gl_search-g0_search)*MIN(1,(2027-2026)/conv_n) -> 0.14600991 | I78: =g0_search+(gl_search-g0_search)*MIN(1,(2028-2026)/conv_n) -> 0.12400661 | J78: =g0_search+(gl_search-g0_search)*MIN(1,(2029-2026)/conv_n) -> 0.1020033 | K78: =g0_search+(gl_search-g0_search)*MIN(1,(2030-2026)/conv_n) -> 0.08 | L78: =g0_search+(gl_search-g0_search)*MIN(1,(2031-2026)/conv_n) -> 0.08 | M78: =g0_search+(gl_search-g0_search)*MIN(1,(2032-2026)/conv_n) -> 0.08 | N78: 2H26 年增＝近四季 +16.8%（Q 頁），FY2030 收斂到 gl_search
A79: Google Search & other：B 路徑 | B79: US$B | C79: =Q!J5 -> 198.084 | D79: =Q!K5 -> 224.532 | E79: =Q!L5 -> 123.67 | F79: =(Q!F5+Q!G5)*(1+F78) -> 139.7411 | G79: =E79+F79 -> 263.4111 | H79: =G79*(1+H78) -> 301.87173 | I79: =H79*(1+I78) -> 339.30582 | J79: =I79*(1+J78) -> 373.91613 | K79: =J79*(1+K78) -> 403.82942 | L79: =K79*(1+L78) -> 436.13578 | M79: =L79*(1+M78) -> 471.02664
A80: 情境爬坡（FY2026 0 → FY2030 1） | B80: x | F80: 0 | H80: =MIN(1,(2027-2026)/conv_n) -> 0.25 | I80: =MIN(1,(2028-2026)/conv_n) -> 0.5 | J80: =MIN(1,(2029-2026)/conv_n) -> 0.75 | K80: =MIN(1,(2030-2026)/conv_n) -> 1 | L80: =MIN(1,(2031-2026)/conv_n) -> 1 | M80: =MIN(1,(2032-2026)/conv_n) -> 1
A81: 查詢分流（相對 B 路徑） | B81: % | F81: =dC*F80 -> 0 | H81: =dC*H80 -> 0.05 | I81: =dC*I80 -> 0.1 | J81: =dC*J80 -> 0.15 | K81: =dC*K80 -> 0.2 | L81: =dC*L80 -> 0.2 | M81: =dC*M80 -> 0.2 | N81: In 頁 dC（壓力情境）
A82: 每次查詢變現變動（相對 B 路徑） | B82: % | F82: =mC*F80 -> 0 | H82: =mC*H80 -> -0.025 | I82: =mC*I80 -> -0.05 | J82: =mC*J80 -> -0.075 | K82: =mC*K80 -> -0.1 | L82: =mC*L80 -> -0.1 | M82: =mC*M80 -> -0.1
A83: Google Search & other | B83: US$B | C83: =C79 -> 198.084 | D83: =D79 -> 224.532 | E83: =E79 -> 123.67 | F83: =F79*(1-F81)*(1+F82) -> 139.7411 | G83: =E83+F83 -> 263.4111 | H83: =H79*(1-H81)*(1+H82) -> 279.60869 | I83: =I79*(1-I81)*(1+I82) -> 290.10648 | J83: =J79*(1-J81)*(1+J82) -> 293.99156 | K83: =K79*(1-K81)*(1+K82) -> 290.75719 | L83: =L79*(1-L81)*(1+L82) -> 314.01776 | M83: =M79*(1-M81)*(1+M82) -> 339.13918
A84: YouTube ads 年增 | B84: % | F84: =g0_yt -> 0.11713933 | H84: =g0_yt+(gl_yt-g0_yt)*MIN(1,(2027-2026)/conv_n) -> 0.1078545 | I84: =g0_yt+(gl_yt-g0_yt)*MIN(1,(2028-2026)/conv_n) -> 0.098569667 | J84: =g0_yt+(gl_yt-g0_yt)*MIN(1,(2029-2026)/conv_n) -> 0.089284834 | K84: =g0_yt+(gl_yt-g0_yt)*MIN(1,(2030-2026)/conv_n) -> 0.08 | L84: =g0_yt+(gl_yt-g0_yt)*MIN(1,(2031-2026)/conv_n) -> 0.08 | M84: =g0_yt+(gl_yt-g0_yt)*MIN(1,(2032-2026)/conv_n) -> 0.08 | N84: 三情境相同
A85: YouTube ads | B85: US$B | C85: =Q!J6 -> 36.147 | D85: =Q!K6 -> 40.367 | E85: =Q!L6 -> 20.938 | F85: =(Q!F6+Q!G6)*(1+F84) -> 24.179364 | G85: =E85+F85 -> 45.117364 | H85: =G85*(1+H84) -> 49.983474 | I85: =H85*(1+I84) -> 54.910329 | J85: =I85*(1+J84) -> 59.812989 | K85: =J85*(1+K84) -> 64.598028 | L85: =K85*(1+L84) -> 69.76587 | M85: =L85*(1+M84) -> 75.347139
A86: Google Network 年增 | B86: % | F86: =g0_net -> -0.021785335 | H86: =g0_net+(gl_net-g0_net)*MIN(1,(2027-2026)/conv_n) -> -0.016339001 | I86: =g0_net+(gl_net-g0_net)*MIN(1,(2028-2026)/conv_n) -> -0.010892667 | J86: =g0_net+(gl_net-g0_net)*MIN(1,(2029-2026)/conv_n) -> -0.0054463337 | K86: =g0_net+(gl_net-g0_net)*MIN(1,(2030-2026)/conv_n) -> 0 | L86: =g0_net+(gl_net-g0_net)*MIN(1,(2031-2026)/conv_n) -> 0 | M86: =g0_net+(gl_net-g0_net)*MIN(1,(2032-2026)/conv_n) -> 0 | N86: 三情境相同
A87: Google Network | B87: US$B | C87: =Q!J7 -> 30.359 | D87: =Q!K7 -> 29.792 | E87: =Q!L7 -> 14.274 | F87: =(Q!F7+Q!G7)*(1+F86) -> 14.851255 | G87: =E87+F87 -> 29.125255 | H87: =G87*(1+H86) -> 28.649377 | I87: =H87*(1+I86) -> 28.337309 | J87: =I87*(1+J86) -> 28.182975 | K87: =J87*(1+K86) -> 28.182975 | L87: =K87*(1+L86) -> 28.182975 | M87: =L87*(1+M86) -> 28.182975
A88: Google subscriptions, platforms, and devices 年增 | B88: % | F88: =g0_subs -> 0.17943516 | H88: =g0_subs+(gl_subs-g0_subs)*MIN(1,(2027-2026)/conv_n) -> 0.15957637 | I88: =g0_subs+(gl_subs-g0_subs)*MIN(1,(2028-2026)/conv_n) -> 0.13971758 | J88: =g0_subs+(gl_subs-g0_subs)*MIN(1,(2029-2026)/conv_n) -> 0.11985879 | K88: =g0_subs+(gl_subs-g0_subs)*MIN(1,(2030-2026)/conv_n) -> 0.1 | L88: =g0_subs+(gl_subs-g0_subs)*MIN(1,(2031-2026)/conv_n) -> 0.1 | M88: =g0_subs+(gl_subs-g0_subs)*MIN(1,(2032-2026)/conv_n) -> 0.1 | N88: 三情境相同
A89: Google subscriptions, platforms, and devices | B89: US$B | C89: =Q!J8 -> 40.34 | D89: =Q!K8 -> 48.03 | E89: =Q!L8 -> 25.295 | F89: =(Q!F8+Q!G8)*(1+F88) -> 31.193701 | G89: =E89+F89 -> 56.488701 | H89: =G89*(1+H88) -> 65.502963 | I89: =H89*(1+I88) -> 74.654879 | J89: =I89*(1+J88) -> 83.602922 | K89: =J89*(1+K88) -> 91.963214 | L89: =K89*(1+L88) -> 101.15954 | M89: =L89*(1+M88) -> 111.27549
A90: Google Services | B90: US$B | C90: =Q!J9 -> 304.93 | D90: =Q!K9 -> 342.721 | E90: =Q!L9 -> 184.177 | F90: =F83+F85+F87+F89 -> 209.96542 | G90: =E90+F90 -> 394.14242 | H90: =H83+H85+H87+H89 -> 423.74451 | I90: =I83+I85+I87+I89 -> 448.00899 | J90: =J83+J85+J87+J89 -> 465.59045 | K90: =K83+K85+K87+K89 -> 475.5014 | L90: =L83+L85+L87+L89 -> 513.12614 | M90: =M83+M85+M87+M89 -> 553.94479
A91: Cloud AI（命題子列） | B91: US$B | E91: =Thesis!E38 -> 9.7583729 | F91: =Thesis!F38 -> 13.072238 | G91: =Thesis!G38 -> 22.830611 | H91: =Thesis!H38 -> 38.882858 | I91: =Thesis!I38 -> 56.703559 | J91: =Thesis!J38 -> 73.012119 | K91: =Thesis!K38 -> 85.400179 | L91: =Thesis!L38 -> 94.03926 | M91: =Thesis!M38 -> 99.017013 | N91: Thesis 頁：對外 MW × 每 MW 收入（1H26 為模型估計）
A92: TPU 系統銷售（命題子列） | B92: US$B | E92: 0 | F92: =tpu_2h -> 1 | G92: =E92+F92 -> 1 | H92: =tpu_yr -> 13 | I92: =tpu_yr -> 13 | J92: =tpu_yr -> 13 | K92: =tpu_yr -> 13 | L92: =tpu_yr -> 13 | M92: =tpu_yr -> 13 | N92: C8 b：不走 MW × 每 MW；1H26 金額未揭露 → 0
A93: Cloud 其他年增 | B93: % | F93: =g0_co -> 0.46312246 | H93: =g0_co+(gl_co-g0_co)*MIN(1,(2027-2026)/conv_n) -> 0.36734184 | I93: =g0_co+(gl_co-g0_co)*MIN(1,(2028-2026)/conv_n) -> 0.27156123 | J93: =g0_co+(gl_co-g0_co)*MIN(1,(2029-2026)/conv_n) -> 0.17578061 | K93: =g0_co+(gl_co-g0_co)*MIN(1,(2030-2026)/conv_n) -> 0.08 | L93: =g0_co+(gl_co-g0_co)*MIN(1,(2031-2026)/conv_n) -> 0.08 | M93: =g0_co+(gl_co-g0_co)*MIN(1,(2032-2026)/conv_n) -> 0.08 | N93: 起始＝Cloud 其他近四季年增（Thesis 頁 g0_co），FY2030 收斂到 gl_co
A94: Cloud 其他（命題子列） | B94: US$B | E94: =Q!L11-E91-E92 -> 35.037627 | F94: =E94*(1+F93)^0.5 -> 42.381373 | G94: =E94+F94 -> 77.419 | H94: =G94*(1+H93) -> 105.85824 | I94: =H94*(1+I93) -> 134.60523 | J94: =I94*(1+J93) -> 158.26622 | K94: =J94*(1+K93) -> 170.92752 | L94: =K94*(1+L93) -> 184.60172 | M94: =L94*(1+M93) -> 199.36986 | N94: 1H26＝Google Cloud 實績 − Cloud AI 估計 − TPU；2H26＝1H26 ×(1＋年增)^0.5
A95: Google Cloud | B95: US$B | C95: =Q!J11 -> 43.229 | D95: =Q!K11 -> 58.705 | E95: =Q!L11 -> 44.796 | F95: =F91+F92+F94 -> 56.453611 | G95: =E95+F95 -> 101.24961 | H95: =H91+H92+H94 -> 157.7411 | I95: =I91+I92+I94 -> 204.30879 | J95: =J91+J92+J94 -> 244.27834 | K95: =K91+K92+K94 -> 269.3277 | L95: =L91+L92+L94 -> 291.64098 | M95: =M91+M92+M94 -> 311.38687
A96: Other Bets | B96: US$B | C96: =Q!J12 -> 1.648 | D96: =Q!K12 -> 1.537 | E96: =Q!L12 -> 0.793 | F96: =ob_rev_2H -> 0.75 | G96: =E96+F96 -> 1.543 | H96: =ob_rev_27 -> 1.6 | I96: =ob_rev_28 -> 1.8 | J96: =ob_rev_29 -> 2 | K96: =ob_rev_30 -> 2.2 | L96: =ob_rev_31 -> 2.4 | M96: =ob_rev_32 -> 2.6
A97: Hedging gains (losses) | B97: US$B | C97: =Q!J13 -> 0.211 | D97: =Q!K13 -> -0.127 | E97: =Q!L13 -> -0.074 | F97: 0 | G97: =E97+F97 -> -0.074 | H97: 0 | I97: 0 | J97: 0 | K97: 0 | L97: 0 | M97: 0 | N97: Alphabet-level activities；預測期 0 [Assumed]
A98: 合併營收 | B98: US$B | C98: =Q!J14 -> 350.018 | D98: =Q!K14 -> 402.836 | E98: =Q!L14 -> 229.692 | F98: =F90+F95+F96+F97 -> 267.16903 | G98: =E98+F98 -> 496.86103 | H98: =H90+H95+H96+H97 -> 583.0856 | I98: =I90+I95+I96+I97 -> 654.11778 | J98: =J90+J95+J96+J97 -> 711.86879 | K98: =K90+K95+K96+K97 -> 747.0291 | L98: =L90+L95+L96+L97 -> 807.16712 | M98: =M90+M95+M96+M97 -> 867.93166
A99: 檢查：產品線合計 − Google Services | B99: US$B | C99: =C83+C85+C87+C89-C90 -> 0 | D99: =D83+D85+D87+D89-D90 -> 0 | E99: =E83+E85+E87+E89-E90 -> 0 | F99: =F83+F85+F87+F89-F90 -> 0 | G99: =G83+G85+G87+G89-G90 -> 0 | H99: =H83+H85+H87+H89-H90 -> 0 | I99: =I83+I85+I87+I89-I90 -> 0 | J99: =J83+J85+J87+J89-J90 -> 0 | ... M99: =M83+M85+M87+M89-M90 -> 0
A100: 檢查：Cloud 子列合計 − Google Cloud | B100: US$B | E100: =E91+E92+E94-E95 -> 0 | F100: =F91+F92+F94-F95 -> 0 | G100: =G91+G92+G94-G95 -> 0 | H100: =H91+H92+H94-H95 -> 0 | I100: =I91+I92+I94-I95 -> 0 | J100: =J91+J92+J94-J95 -> 0 | K100: =K91+K92+K94-K95 -> 0 | L100: =L91+L92+L94-L95 -> 0 | M100: =M91+M92+M94-M95 -> 0
A101: 檢查：分部合計＋避險 − 合併營收 | B101: US$B | C101: =C90+C95+C96+C97-C98 -> 0 | D101: =D90+D95+D96+D97-D98 -> 0 | E101: =E90+E95+E96+E97-E98 -> 0 | F101: =F90+F95+F96+F97-F98 -> 0 | G101: =G90+G95+G96+G97-G98 -> 0 | H101: =H90+H95+H96+H97-H98 -> 0 | I101: =I90+I95+I96+I97-I98 -> 0 | J101: =J90+J95+J96+J97-J98 -> 0 | ... M101: =M90+M95+M96+M97-M98 -> 0
A102: 檢查：實績欄合併營收 − Q 頁（FY2024、FY2025、1H26） | B102: US$B | C102: =C98-Q!J14 -> 0 | D102: =D98-Q!K14 -> 0 | E102: =E98-Q!L14 -> 0
A103: 非 AI 資本支出：Google Services（營收 × cx_svc） | B103: US$B | F103: =F90*cx_svc -> 12.597925 | G103: =F103 -> 12.597925 | H103: =H90*cx_svc -> 25.42467 | I103: =I90*cx_svc -> 26.88054 | J103: =J90*cx_svc -> 27.935427 | K103: =K90*cx_svc -> 28.530084 | L103: =L90*cx_svc -> 30.787568 | M103: =M90*cx_svc -> 33.236687
...

Sheet PL
A1: PL — 分部營收 → 分部營業利益 → 合併營業利益 → 業外 → 稅 → 淨利 → EPS（三情境；US$B，EPS 美元）。實績欄（FY2024A、FY2025A、1H26A）取自 Q 頁；FY2026E＝1H 實績＋2H 模型
A2: 分部營業利益＝分部 EBITDA − 分攤折舊。分部 EBITDA：Google Services＝B 路徑營收 × 近四季 EBITDA 率＋Search 情境差額 × 增量 EBITDA 率 − 自用 AI 增量營運成本 × svc_sh；Google Cloud＝Cloud AI EBITDA（Thesis）＋TPU × tpu_m＋Cloud 其他 × m_co。折舊＝評價日在役資產基礎折舊（按近四季營收分攤）＋新增 AI 折舊（對外→Cloud、自用→Services／Alphabet 層級）＋新增非 AI 折舊。持股評價損益預測期設 0
A4: 分部對帳彙總（三情境 × 全部年度取絕對值最大者；實績欄同列）
A5: 項目 | B5: 單位 | C5: FY2024A | D5: FY2025A | E5: 1H26A | F5: 2H26E | G5: FY2026E | H5: FY2027E | I5: FY2028E | J5: FY2029E | K5: FY2030E | L5: FY2031E | M5: FY2032E | N5: 說明
A6: 檢查：產品線合計 − Google Services | B6: US$B | C6: =MAX(ABS(C26),ABS(C85),ABS(C144)) -> 0 | D6: =MAX(ABS(D26),ABS(D85),ABS(D144)) -> 0 | E6: =MAX(ABS(E26),ABS(E85),ABS(E144)) -> 0 | F6: =MAX(ABS(F26),ABS(F85),ABS(F144)) -> 0 | G6: =MAX(ABS(G26),ABS(G85),ABS(G144)) -> 0 | H6: =MAX(ABS(H26),ABS(H85),ABS(H144)) -> 0 | I6: =MAX(ABS(I26),ABS(I85),ABS(I144)) -> 0 | J6: =MAX(ABS(J26),ABS(J85),ABS(J144)) -> 0 | ... M6: =MAX(ABS(M26),ABS(M85),ABS(M144)) -> 0 | N6: 三情境各區塊同名核對列的最大絕對值；必須為 0（tools/segment_check 讀本列）
A7: 檢查：Cloud 子列合計 − Google Cloud | B7: US$B | E7: =MAX(ABS(E27),ABS(E86),ABS(E145)) -> 0 | F7: =MAX(ABS(F27),ABS(F86),ABS(F145)) -> 0 | G7: =MAX(ABS(G27),ABS(G86),ABS(G145)) -> 0 | H7: =MAX(ABS(H27),ABS(H86),ABS(H145)) -> 0 | I7: =MAX(ABS(I27),ABS(I86),ABS(I145)) -> 0 | J7: =MAX(ABS(J27),ABS(J86),ABS(J145)) -> 0 | K7: =MAX(ABS(K27),ABS(K86),ABS(K145)) -> 0 | L7: =MAX(ABS(L27),ABS(L86),ABS(L145)) -> 0 | M7: =MAX(ABS(M27),ABS(M86),ABS(M145)) -> 0 | N7: 三情境各區塊同名核對列的最大絕對值；必須為 0（tools/segment_check 讀本列）
A8: 檢查：分部合計＋避險 − 合併營收 | B8: US$B | C8: =MAX(ABS(C28),ABS(C87),ABS(C146)) -> 0 | D8: =MAX(ABS(D28),ABS(D87),ABS(D146)) -> 0 | E8: =MAX(ABS(E28),ABS(E87),ABS(E146)) -> 0 | F8: =MAX(ABS(F28),ABS(F87),ABS(F146)) -> 0 | G8: =MAX(ABS(G28),ABS(G87),ABS(G146)) -> 0 | H8: =MAX(ABS(H28),ABS(H87),ABS(H146)) -> 0 | I8: =MAX(ABS(I28),ABS(I87),ABS(I146)) -> 0 | J8: =MAX(ABS(J28),ABS(J87),ABS(J146)) -> 0 | ... M8: =MAX(ABS(M28),ABS(M87),ABS(M146)) -> 0 | N8: 三情境各區塊同名核對列的最大絕對值；必須為 0（tools/segment_check 讀本列）
A9: 檢查：分部營業利益合計 − 合併營業利益 | B9: US$B | C9: =MAX(ABS(C47),ABS(C106),ABS(C165)) -> 0 | D9: =MAX(ABS(D47),ABS(D106),ABS(D165)) -> 0 | E9: =MAX(ABS(E47),ABS(E106),ABS(E165)) -> 0 | F9: =MAX(ABS(F47),ABS(F106),ABS(F165)) -> 0 | G9: =MAX(ABS(G47),ABS(G106),ABS(G165)) -> 0 | H9: =MAX(ABS(H47),ABS(H106),ABS(H165)) -> 0 | I9: =MAX(ABS(I47),ABS(I106),ABS(I165)) -> 0 | J9: =MAX(ABS(J47),ABS(J106),ABS(J165)) -> 0 | ... M9: =MAX(ABS(M47),ABS(M106),ABS(M165)) -> 0 | N9: 三情境各區塊同名核對列的最大絕對值；必須為 0（tools/segment_check 讀本列）
A11: 情境 A（AI 搜尋擴大變現）
A12: 項目 | B12: 單位 | C12: FY2024A | D12: FY2025A | E12: 1H26A | F12: 2H26E | G12: FY2026E | H12: FY2027E | I12: FY2028E | J12: FY2029E | K12: FY2030E | L12: FY2031E | M12: FY2032E | N12: 說明
A13: Google Search & other | B13: US$B | C13: =Seg!C11 -> 198.084 | D13: =Seg!D11 -> 224.532 | E13: =Seg!E11 -> 123.67 | F13: =Seg!F11 -> 139.7411 | G13: =Seg!G11 -> 263.4111 | H13: =Seg!H11 -> 313.28626 | I13: =Seg!I11 -> 365.17789 | J13: =Seg!J11 -> 417.03334 | ... M13: =Seg!M11 -> 544.03577
A14: YouTube ads | B14: US$B | C14: =Seg!C13 -> 36.147 | D14: =Seg!D13 -> 40.367 | E14: =Seg!E13 -> 20.938 | F14: =Seg!F13 -> 24.179364 | G14: =Seg!G13 -> 45.117364 | H14: =Seg!H13 -> 49.983474 | I14: =Seg!I13 -> 54.910329 | J14: =Seg!J13 -> 59.812989 | ... M14: =Seg!M13 -> 75.347139
A15: Google Network | B15: US$B | C15: =Seg!C15 -> 30.359 | D15: =Seg!D15 -> 29.792 | E15: =Seg!E15 -> 14.274 | F15: =Seg!F15 -> 14.851255 | G15: =Seg!G15 -> 29.125255 | H15: =Seg!H15 -> 28.649377 | I15: =Seg!I15 -> 28.337309 | J15: =Seg!J15 -> 28.182975 | ... M15: =Seg!M15 -> 28.182975
A16: Google subscriptions, platforms, and devices | B16: US$B | C16: =Seg!C17 -> 40.34 | D16: =Seg!D17 -> 48.03 | E16: =Seg!E17 -> 25.295 | F16: =Seg!F17 -> 31.193701 | G16: =Seg!G17 -> 56.488701 | H16: =Seg!H17 -> 65.502963 | I16: =Seg!I17 -> 74.654879 | J16: =Seg!J17 -> 83.602922 | ... M16: =Seg!M17 -> 111.27549
A17: Google Services | B17: US$B | C17: =Seg!C18 -> 304.93 | D17: =Seg!D18 -> 342.721 | E17: =Seg!E18 -> 184.177 | F17: =Seg!F18 -> 209.96542 | G17: =Seg!G18 -> 394.14242 | H17: =Seg!H18 -> 457.42207 | I17: =Seg!I18 -> 523.08041 | J17: =Seg!J18 -> 588.63222 | ... M17: =Seg!M18 -> 758.84137
A18: Cloud AI（命題子列） | B18: US$B | E18: =Seg!E19 -> 9.7583729 | F18: =Seg!F19 -> 13.072238 | G18: =Seg!G19 -> 22.830611 | H18: =Seg!H19 -> 38.882858 | I18: =Seg!I19 -> 56.703559 | J18: =Seg!J19 -> 73.012119 | K18: =Seg!K19 -> 85.400179 | L18: =Seg!L19 -> 94.03926 | M18: =Seg!M19 -> 99.017013
A19: TPU 系統銷售（命題子列） | B19: US$B | E19: =Seg!E20 -> 0 | F19: =Seg!F20 -> 1 | G19: =Seg!G20 -> 1 | H19: =Seg!H20 -> 13 | I19: =Seg!I20 -> 13 | J19: =Seg!J20 -> 13 | K19: =Seg!K20 -> 13 | L19: =Seg!L20 -> 13 | M19: =Seg!M20 -> 13
A20: Cloud 其他（命題子列） | B20: US$B | E20: =Seg!E22 -> 35.037627 | F20: =Seg!F22 -> 42.381373 | G20: =Seg!G22 -> 77.419 | H20: =Seg!H22 -> 105.85824 | I20: =Seg!I22 -> 134.60523 | J20: =Seg!J22 -> 158.26622 | K20: =Seg!K22 -> 170.92752 | L20: =Seg!L22 -> 184.60172 | M20: =Seg!M22 -> 199.36986
A21: Google Cloud | B21: US$B | C21: =Seg!C23 -> 43.229 | D21: =Seg!D23 -> 58.705 | E21: =Seg!E23 -> 44.796 | F21: =Seg!F23 -> 56.453611 | G21: =Seg!G23 -> 101.24961 | H21: =Seg!H23 -> 157.7411 | I21: =Seg!I23 -> 204.30879 | J21: =Seg!J23 -> 244.27834 | ... M21: =Seg!M23 -> 311.38687
A22: Other Bets | B22: US$B | C22: =Seg!C24 -> 1.648 | D22: =Seg!D24 -> 1.537 | E22: =Seg!E24 -> 0.793 | F22: =Seg!F24 -> 0.75 | G22: =Seg!G24 -> 1.543 | H22: =Seg!H24 -> 1.6 | I22: =Seg!I24 -> 1.8 | J22: =Seg!J24 -> 2 | ... M22: =Seg!M24 -> 2.6
A23: Hedging gains (losses) | B23: US$B | C23: =Seg!C25 -> 0.211 | D23: =Seg!D25 -> -0.127 | E23: =Seg!E25 -> -0.074 | F23: =Seg!F25 -> 0 | G23: =Seg!G25 -> -0.074 | H23: =Seg!H25 -> 0 | I23: =Seg!I25 -> 0 | J23: =Seg!J25 -> 0 | ... M23: =Seg!M25 -> 0
A24: 合併營收 | B24: US$B | C24: =Seg!C26 -> 350.018 | D24: =Seg!D26 -> 402.836 | E24: =Seg!E26 -> 229.692 | F24: =Seg!F26 -> 267.16903 | G24: =Seg!G26 -> 496.86103 | H24: =Seg!H26 -> 616.76317 | I24: =Seg!I26 -> 729.1892 | J24: =Seg!J26 -> 834.91057 | ... M24: =Seg!M26 -> 1072.8282
A25: 合併營收年增 | B25: % | D25: =D24/C24-1 -> 0.15090081 | G25: =G24/D24-1 -> 0.23340772 | H25: =H24/G24-1 -> 0.24131926 | I25: =I24/H24-1 -> 0.18228395 | J25: =J24/I24-1 -> 0.14498483 | K25: =K24/J24-1 -> 0.1051422 | L25: =L24/K24-1 -> 0.080407169 | M25: =M24/L24-1 -> 0.076179268
A26: 檢查：產品線合計 − Google Services | B26: US$B | C26: =C13+C14+C15+C16-C17 -> 0 | D26: =D13+D14+D15+D16-D17 -> 0 | E26: =E13+E14+E15+E16-E17 -> 0 | F26: =F13+F14+F15+F16-F17 -> 0 | G26: =G13+G14+G15+G16-G17 -> 0 | H26: =H13+H14+H15+H16-H17 -> 0 | I26: =I13+I14+I15+I16-I17 -> 0 | J26: =J13+J14+J15+J16-J17 -> 0 | ... M26: =M13+M14+M15+M16-M17 -> 0
A27: 檢查：Cloud 子列合計 − Google Cloud | B27: US$B | E27: =E18+E19+E20-E21 -> 0 | F27: =F18+F19+F20-F21 -> 0 | G27: =G18+G19+G20-G21 -> 0 | H27: =H18+H19+H20-H21 -> 0 | I27: =I18+I19+I20-I21 -> 0 | J27: =J18+J19+J20-J21 -> 0 | K27: =K18+K19+K20-K21 -> 0 | L27: =L18+L19+L20-L21 -> 0 | M27: =M18+M19+M20-M21 -> 0
A28: 檢查：分部合計＋避險 − 合併營收 | B28: US$B | C28: =C17+C21+C22+C23-C24 -> 0 | D28: =D17+D21+D22+D23-D24 -> 0 | E28: =E17+E21+E22+E23-E24 -> 0 | F28: =F17+F21+F22+F23-F24 -> 0 | G28: =G17+G21+G22+G23-G24 -> 0 | H28: =H17+H21+H22+H23-H24 -> 0 | I28: =I17+I21+I22+I23-I24 -> 0 | J28: =J17+J21+J22+J23-J24 -> 0 | ... M28: =M17+M21+M22+M23-M24 -> 0
A29: Search 情境差額（相對 B 路徑） | B29: US$B | F29: =Seg!F11-Seg!F7 -> 0 | G29: =F29 -> 0 | H29: =Seg!H11-Seg!H7 -> 11.414525 | I29: =Seg!I11-Seg!I7 -> 25.872069 | J29: =Seg!J11-Seg!J7 -> 43.117204 | K29: =Seg!K11-Seg!K7 -> 62.593561 | L29: =Seg!L11-Seg!L7 -> 67.601046 | M29: =Seg!M11-Seg!M7 -> 73.009129
A30: Google Services EBITDA | B30: US$B | F30: =m_svc*(F17-F29)+inc_m*F29-svc_sh*(Thesis!F68+Thesis!F69) -> 101.67943 | H30: =m_svc*(H17-H29)+inc_m*H29-svc_sh*(Thesis!H68+Thesis!H69) -> 218.27831 | I30: =m_svc*(I17-I29)+inc_m*I29-svc_sh*(Thesis!I68+Thesis!I69) -> 250.09382 | J30: =m_svc*(J17-J29)+inc_m*J29-svc_sh*(Thesis!J68+Thesis!J69) -> 286.09592 | K30: =m_svc*(K17-K29)+inc_m*K29-svc_sh*(Thesis!K68+Thesis!K69) -> 321.84879 | L30: =m_svc*(L17-L29)+inc_m*L29-svc_sh*(Thesis!L68+Thesis!L69) -> 346.69487 | M30: =m_svc*(M17-M29)+inc_m*M29-svc_sh*(Thesis!M68+Thesis!M69) -> 374.48835 | N30: B 路徑營收 × m_svc（Q 頁；預設 1H26 49.4%，mb_ttm＝1 時近四季 47.6%）＋Search 差額 × inc_m − 自用 AI 增量營運與租金 × svc_sh
A31: Google Services 折舊（基礎分攤＋新增非 AI＋自用 AI × svc_sh） | B31: US$B | F31: =Thesis!F77*sh_svc+Seg!F35+Thesis!F65*svc_sh -> 14.996569 | H31: =Thesis!H77*sh_svc+Seg!H35+Thesis!H65*svc_sh -> 40.071772 | I31: =Thesis!I77*sh_svc+Seg!I35+Thesis!I65*svc_sh -> 54.21574 | J31: =Thesis!J77*sh_svc+Seg!J35+Thesis!J65*svc_sh -> 67.909152 | K31: =Thesis!K77*sh_svc+Seg!K35+Thesis!K65*svc_sh -> 78.416604 | L31: =Thesis!L77*sh_svc+Seg!L35+Thesis!L65*svc_sh -> 85.426164 | M31: =Thesis!M77*sh_svc+Seg!M35+Thesis!M65*svc_sh -> 97.778051
A32: Google Services 營業利益 | B32: US$B | C32: =Q!J18 -> 121.263 | D32: =Q!K18 -> 139.404 | E32: =Q!L18 -> 80.133 | F32: =F30-F31 -> 86.682859 | G32: =E32+F32 -> 166.81586 | H32: =H30-H31 -> 178.20653 | I32: =I30-I31 -> 195.87808 | J32: =J30-J31 -> 218.18677 | K32: =K30-K31 -> 243.43218 | L32: =L30-L31 -> 261.2687 | M32: =M30-M31 -> 276.7103
A33: Google Cloud EBITDA | B33: US$B | F33: =Thesis!F41+F19*tpu_m+F20*m_co -> 23.180487 | H33: =Thesis!H41+H19*tpu_m+H20*m_co -> 65.910285 | I33: =Thesis!I41+I19*tpu_m+I20*m_co -> 89.262727 | J33: =Thesis!J41+J19*tpu_m+J20*m_co -> 109.92081 | K33: =Thesis!K41+K19*tpu_m+K20*m_co -> 124.11433 | L33: =Thesis!L41+L19*tpu_m+L20*m_co -> 135.37916 | M33: =Thesis!M41+M19*tpu_m+M20*m_co -> 143.81331 | N33: Cloud AI EBITDA（Tokenomics 營運成本）＋TPU × tpu_m＋Cloud 其他 × m_co
A34: Google Cloud 折舊（基礎分攤＋對外 AI＋新增非 AI） | B34: US$B | F34: =Thesis!F77*sh_cloud+Thesis!F64+Seg!F36 -> 4.8211933 | H34: =Thesis!H77*sh_cloud+Thesis!H64+Seg!H36 -> 16.854495 | I34: =Thesis!I77*sh_cloud+Thesis!I64+Seg!I36 -> 27.1875 | J34: =Thesis!J77*sh_cloud+Thesis!J64+Seg!J36 -> 38.067345 | K34: =Thesis!K77*sh_cloud+Thesis!K64+Seg!K36 -> 48.232805 | L34: =Thesis!L77*sh_cloud+Thesis!L64+Seg!L36 -> 57.875471 | M34: =Thesis!M77*sh_cloud+Thesis!M64+Seg!M36 -> 67.828382
A35: Google Cloud 營業利益 | B35: US$B | C35: =Q!J19 -> 6.112 | D35: =Q!K19 -> 13.91 | E35: =Q!L19 -> 15.412 | F35: =F33-F34 -> 18.359293 | G35: =E35+F35 -> 33.771293 | H35: =H33-H34 -> 49.05579 | I35: =I33-I34 -> 62.075227 | J35: =J33-J34 -> 71.853461 | K35: =K33-K34 -> 75.881525 | L35: =L33-L34 -> 77.503691 | M35: =M33-M34 -> 75.984932
A36: Other Bets 折舊（基礎分攤＋新增非 AI） | B36: US$B | F36: =Thesis!F77*sh_ob+Seg!F37 -> 0.049109617 | H36: =Thesis!H77*sh_ob+Seg!H37 -> 0.10286923 | I36: =Thesis!I77*sh_ob+Seg!I37 -> 0.11276923 | J36: =Thesis!J77*sh_ob+Seg!J37 -> 0.11896729 | K36: =Thesis!K77*sh_ob+Seg!K37 -> 0.11476607 | L36: =Thesis!L77*sh_ob+Seg!L37 -> 0.095650871 | M36: =Thesis!M77*sh_ob+Seg!M37 -> 0.10678769
A37: Other Bets 營業利益 | B37: US$B | C37: =Q!J20 -> -4.444 | D37: =Q!K20 -> -7.515 | E37: =Q!L20 -> -3.899 | F37: =ob_oi*0.5 -> -4.5 | G37: =E37+F37 -> -8.399 | H37: =ob_oi*1 -> -9 | I37: =ob_oi*1 -> -9 | J37: =ob_oi*1 -> -9 | K37: =ob_oi*1 -> -9 | L37: =ob_oi*1 -> -9 | M37: =ob_oi*1 -> -9
A38: Other Bets EBITDA | B38: US$B | F38: =F37+F36 -> -4.4508904 | H38: =H37+H36 -> -8.8971308 | I38: =I37+I36 -> -8.8872308 | J38: =J37+J36 -> -8.8810327 | K38: =K37+K36 -> -8.8852339 | L38: =L37+L36 -> -8.9043491 | M38: =M37+M36 -> -8.8932123
A39: Alphabet-level 折舊（自用 AI × (1 − svc_sh)） | B39: US$B | F39: =Thesis!F65*(1-svc_sh) -> 1.9953469 | H39: =Thesis!H65*(1-svc_sh) -> 9.83243 | I39: =Thesis!I65*(1-svc_sh) -> 17.366395 | J39: =Thesis!J65*(1-svc_sh) -> 25.133508 | K39: =Thesis!K65*(1-svc_sh) -> 32.401108 | L39: =Thesis!L65*(1-svc_sh) -> 39.714304 | M39: =Thesis!M65*(1-svc_sh) -> 45.660155
A40: Alphabet-level activities（避險營收 − 未分攤費用 − 自用 AI 增量成本 × (1 − svc_sh)） | B40: US$B | C40: =Q!J21 -> -10.541 | D40: =Q!K21 -> -16.76 | E40: =Q!L21 -> -11.18 | F40: =F23-abc_rate*F24-Thesis!F72 -> -16.29226 | G40: =E40+F40 -> -27.47226 | H40: =H23-abc_rate*H24-Thesis!H72 -> -46.379561 | I40: =I23-abc_rate*I24-Thesis!I72 -> -61.749733 | J40: =J23-abc_rate*J24-Thesis!J72 -> -74.585498 | K40: =K23-abc_rate*K24-Thesis!K72 -> -85.53366 | L40: =L23-abc_rate*L24-Thesis!L72 -> -97.579966 | M40: =M23-abc_rate*M24-Thesis!M72 -> -107.85625
A41: Alphabet-level EBITDA | B41: US$B | F41: =F40+F39 -> -14.296913 | H41: =H40+H39 -> -36.547131 | I41: =I40+I39 -> -44.383338 | J41: =J40+J39 -> -49.451991 | K41: =K40+K39 -> -53.132552 | L41: =L40+L39 -> -57.865663 | M41: =M40+M39 -> -62.196094
A42: 分部營業利益合計 | B42: US$B | C42: =C32+C35+C37+C40 -> 112.39 | D42: =D32+D35+D37+D40 -> 129.039 | E42: =E32+E35+E37+E40 -> 80.466 | F42: =F32+F35+F37+F40 -> 84.249893 | G42: =G32+G35+G37+G40 -> 164.71589 | H42: =H32+H35+H37+H40 -> 171.88276 | I42: =I32+I35+I37+I40 -> 187.20358 | J42: =J32+J35+J37+J40 -> 206.45473 | ... M42: =M32+M35+M37+M40 -> 235.83899
A43: 合併 EBITDA（分部 EBITDA 合計） | B43: US$B | F43: =F30+F33+F38+F41 -> 106.11211 | H43: =H30+H33+H38+H41 -> 238.74433 | I43: =I30+I33+I38+I41 -> 286.08598 | J43: =J30+J33+J38+J41 -> 337.6837 | K43: =K30+K33+K38+K41 -> 383.94533 | L43: =L30+L33+L38+L41 -> 415.30402 | M43: =M30+M33+M38+M41 -> 447.21236
A44: 折舊合計（基礎＋新增 AI＋新增非 AI） | B44: US$B | C44: =Q!J43 -> 15.311 | D44: =Q!K43 -> 21.136 | E44: =Q!L43 -> 13.586 | F44: =Thesis!F77+Thesis!F63+Seg!F38 -> 21.862219 | G44: =E44+F44 -> 35.448219 | H44: =Thesis!H77+Thesis!H63+Seg!H38 -> 66.861566 | I44: =Thesis!I77+Thesis!I63+Seg!I38 -> 98.882404 | J44: =Thesis!J77+Thesis!J63+Seg!J38 -> 131.22897 | K44: =Thesis!K77+Thesis!K63+Seg!K38 -> 159.16528 | L44: =Thesis!L77+Thesis!L63+Seg!L38 -> 183.11159 | M44: =Thesis!M77+Thesis!M63+Seg!M38 -> 211.37338 | N44: 1H26 與以前為現金流量表實績
A45: 其中：新增 AI 折舊 | B45: US$B | F45: =Thesis!F63 -> 7.1262388 | G45: =F45 -> 7.1262388 | H45: =Thesis!H63 -> 35.115821 | I45: =Thesis!I63 -> 62.02284 | J45: =Thesis!J63 -> 89.762528 | K45: =Thesis!K63 -> 115.71824 | L45: =Thesis!L63 -> 141.8368 | M45: =Thesis!M63 -> 163.07198
A46: 合併營業利益 | B46: US$B | C46: =Q!J22 -> 112.39 | D46: =Q!K22 -> 129.039 | E46: =Q!L22 -> 80.466 | F46: =F43-F44 -> 84.249893 | G46: =E46+F46 -> 164.71589 | H46: =H43-H44 -> 171.88276 | I46: =I43-I44 -> 187.20358 | J46: =J43-J44 -> 206.45473 | K46: =K43-K44 -> 224.78005 | L46: =L43-L44 -> 232.19243 | M46: =M43-M44 -> 235.83899 | N46: 預測期＝合併 EBITDA − 折舊合計（與分部營業利益合計獨立計算，下一列核對折舊分攤）
A47: 檢查：分部營業利益合計 − 合併營業利益 | B47: US$B | C47: =C42-C46 -> 0 | D47: =D42-D46 -> 0 | E47: =E42-E46 -> 0 | F47: =F42-F46 -> 0 | G47: =G42-G46 -> 0 | H47: =H42-H46 -> 0 | I47: =I42-I46 -> 0 | J47: =J42-J46 -> 0 | ... M47: =M42-M46 -> 0
A48: 自用 AI 影子效益（讀法 2；非財報營收） | B48: US$B | F48: =Thesis!F80 -> 3.9623393 | G48: =F48 -> 3.9623393 | H48: =Thesis!H80 -> 32.673472 | I48: =Thesis!I80 -> 67.296462 | J48: =Thesis!J80 -> 98.981586 | K48: =Thesis!K80 -> 123.04976 | L48: =Thesis!L80 -> 139.83421 | M48: =Thesis!M80 -> 149.50525 | N48: 修正一 F1：自用增量 MW × IF_HoldEcon（k＝1）；只進評價口徑，不進營收與分部對帳
A49: 營業利益（評價口徑；讀法 2 含影子效益） | B49: US$B | C49: =C46 -> 112.39 | D49: =D46 -> 129.039 | E49: =E46 -> 80.466 | F49: =F46+(internal_ai_reading=2)*F48 -> 88.212232 | G49: =G46+(internal_ai_reading=2)*G48 -> 168.67823 | H49: =H46+(internal_ai_reading=2)*H48 -> 204.55624 | I49: =I46+(internal_ai_reading=2)*I48 -> 254.50004 | J49: =J46+(internal_ai_reading=2)*J48 -> 305.43632 | K49: =K46+(internal_ai_reading=2)*K48 -> 347.82981 | L49: =L46+(internal_ai_reading=2)*L48 -> 372.02664 | M49: =M46+(internal_ai_reading=2)*M48 -> 385.34424
A50: 營業利益率 | B50: % | C50: =C46/C24 -> 0.32109777 | D50: =D46/D24 -> 0.32032639 | E50: =E46/E24 -> 0.3503213 | F50: =F46/F24 -> 0.31534303 | G50: =G46/G24 -> 0.331513 | H50: =H46/H24 -> 0.27868519 | I50: =I46/I24 -> 0.2567284 | J50: =J46/J24 -> 0.24727766 | ... M50: =M46/M24 -> 0.21982921
A51: Google Services 營業利益率 | B51: % | C51: =C32/C17 -> 0.39767488 | D51: =D32/D17 -> 0.40675652 | E51: =E32/E17 -> 0.4350869 | F51: =F32/F17 -> 0.4128435 | G51: =G32/G17 -> 0.42323752 | H51: =H32/H17 -> 0.38958884 | I51: =I32/I17 -> 0.37447031 | J51: =J32/J17 -> 0.37066738 | ... M51: =M32/M17 -> 0.36464841
A52: Google Cloud 營業利益率 | B52: % | C52: =C35/C21 -> 0.14138657 | D52: =D35/D21 -> 0.23694745 | E52: =E35/E21 -> 0.34404858 | F52: =F35/F21 -> 0.32521026 | G52: =G35/G21 -> 0.33354492 | H52: =H35/H21 -> 0.31098928 | I52: =I35/I21 -> 0.30383043 | J52: =J35/J21 -> 0.29414585 | ... M52: =M35/M21 -> 0.24402099
A53: 利息收入（期初現金 × r_cash） | B53: US$B | F53: =r_cash*CF!F31*0.5 -> 2.952809 | G53: =F53 -> 2.952809 | H53: =r_cash*CF!H31*1 -> 6.3995636 | I53: =r_cash*CF!I31*1 -> 5.4983865 | J53: =r_cash*CF!J31*1 -> 5.658351 | K53: =r_cash*CF!K31*1 -> 8.3889579 | L53: =r_cash*CF!L31*1 -> 12.950529 | M53: =r_cash*CF!M31*1 -> 18.774842
A54: 利息費用（期初債務 × r_debt） | B54: US$B | F54: =r_debt*CF!F38*0.5 -> 2.42604 | G54: =F54 -> 2.42604 | H54: =r_debt*CF!H38*1 -> 5.95608 | I54: =r_debt*CF!I38*1 -> 5.90808 | J54: =r_debt*CF!J38*1 -> 5.779632 | K54: =r_debt*CF!K38*1 -> 5.69496 | L54: =r_debt*CF!L38*1 -> 5.350032 | M54: =r_debt*CF!M38*1 -> 5.110032
A55: 權益證券淨損益（預測期設 0） | B55: US$B | D55: =SUM(Q!D33:G33) -> 24.08 | E55: =Q!L33 -> 135.946 | F55: 0 | G55: =E55+F55 -> 135.946 | H55: 0 | I55: 0 | J55: 0 | K55: 0 | L55: 0 | M55: 0 | N55: 2026H1 135.9 主要為 SpaceX 上市與 Anthropic 重估（非營業）；預測期 0（工作單第 2 節 PL）
A56: 業外收益合計 | B56: US$B | C56: =Q!J32 -> 7.425 | D56: =Q!K32 -> 29.787 | E56: =Q!L32 -> 135.699 | F56: =F53-F54+F55 -> 0.526769 | G56: =E56+F56 -> 136.22577 | H56: =H53-H54+H55 -> 0.44348355 | I56: =I53-I54+I55 -> -0.4096935 | J56: =J53-J54+J55 -> -0.12128103 | K56: =K53-K54+K55 -> 2.6939979 | L56: =L53-L54+L55 -> 7.6004967 | M56: =M53-M54+M55 -> 13.66481
A57: 稅前利益 | B57: US$B | C57: =C46+C56 -> 119.815 | D57: =D46+D56 -> 158.826 | E57: =E46+E56 -> 216.165 | F57: =F46+F56 -> 84.776662 | G57: =G46+G56 -> 300.94166 | H57: =H46+H56 -> 172.32625 | I57: =I46+I56 -> 186.79388 | J57: =J46+J56 -> 206.33345 | ... M57: =M46+M56 -> 249.50379
A58: 所得稅 | B58: US$B | C58: =Q!J36 -> 19.697 | D58: =Q!K36 -> 26.656 | E58: =Q!L36 -> 41.394 | F58: =F57*tax -> 14.242479 | G58: =E58+F58 -> 55.636479 | H58: =H57*tax -> 28.95081 | I58: =I57*tax -> 31.381373 | J58: =J57*tax -> 34.664019 | K58: =K57*tax -> 38.21564 | L58: =L57*tax -> 40.285211 | M58: =M57*tax -> 41.916638
A59: 淨利 | B59: US$B | C59: =C57-C58 -> 100.118 | D59: =D57-D58 -> 132.17 | E59: =E57-E58 -> 174.771 | F59: =F57-F58 -> 70.534182 | G59: =G57-G58 -> 245.30518 | H59: =H57-H58 -> 143.37544 | I59: =I57-I58 -> 155.41251 | J59: =J57-J58 -> 171.66943 | ... M59: =M57-M58 -> 207.58716
A60: 檢查：實績淨利 − Q 頁 | B60: US$B | C60: =C59-Q!J37 -> 0 | D60: =D59-Q!K37 -> 0 | E60: =E59-Q!L37 -> 0
A61: 特別股股利 | B61: US$B | E61: 0 | F61: =pref_2H -> 0.535 | G61: =E61+F61 -> 0.535 | H61: =pref_27 -> 1.203 | I61: =pref_28 -> 1.203 | J61: =pref_29 -> 0.602 | K61: 0 | L61: 0 | M61: 0
A62: 歸屬普通股淨利 | B62: US$B | E62: =E59-E61 -> 174.771 | F62: =F59-F61 -> 69.999182 | G62: =G59-G61 -> 244.77018 | H62: =H59-H61 -> 142.17244 | I62: =I59-I61 -> 154.20951 | J62: =J59-J61 -> 171.06743 | K62: =K59-K61 -> 189.25841 | L62: =L59-L61 -> 199.50771 | M62: =M59-M61 -> 207.58716
A63: 期末稀釋股數（十億股） | B63: 十億股 | E63: =sh_dil_q2+(sh_out-sh_basic_q2) -> 12.388 | F63: =E63*(1+dil*0.5)-CF!F34/CF!F41 -> 12.44994 | H63: =F63*(1+dil*1)-CF!H34/CF!H41 -> 12.52452 | I63: =H63*(1+dil*1)-CF!I34/CF!I41 -> 12.604893 | J63: =I63*(1+dil*1)-CF!J34/CF!J41+conv_sh -> 12.745206 | K63: =J63*(1+dil*1)-CF!K34/CF!K41 -> 12.836399 | L63: =K63*(1+dil*1)-CF!L34/CF!L41 -> 12.93217 | M63: =L63*(1+dil*1)-CF!M34/CF!M41 -> 13.032194 | N63: 1H26 期末＝Q2 稀釋加權＋(7/15 流通股 − Q2 基本加權)；之後 ×(1＋dil) − 回購 ÷ 回購均價；2029 強制轉換特別股 +conv_sh
A64: 平均稀釋股數（十億股） | B64: 十億股 | C64: =Q!J39 -> 12.447 | D64: =Q!K39 -> 12.23 | E64: =Q!L39 -> 12.2735 | F64: =E63*(1+dil*0.25) -> 12.41897 | G64: =(E64+F64)/2 -> 12.346235 | H64: =(F63+H63)/2 -> 12.48723 | I64: =(H63+I63)/2 -> 12.564707 | J64: =(I63+J63)/2 -> 12.675049 | K64: =(J63+K63)/2 -> 12.790803 | L64: =(K63+L63)/2 -> 12.884285 | M64: =(L63+M63)/2 -> 12.982182
A65: EPS（GAAP 稀釋，美元） | B65: US$ | C65: =C59/C64 -> 8.0435446 | D65: =D59/D64 -> 10.807032 | E65: =E62/E64 -> 14.239703 | F65: =F62/F64 -> 5.6364725 | G65: =G62/G64 -> 19.825492 | H65: =H62/H64 -> 11.385426 | I65: =I62/I64 -> 12.273228 | J65: =J62/J64 -> 13.496392 | K65: =K62/K64 -> 14.796445 | L65: =L62/L64 -> 15.484578 | M65: =M62/M64 -> 15.990159
A66: EPS（不含權益證券損益，美元） | B66: US$ | E66: =(E62-E55*(1-tax_eq))/E64 -> 5.48936 | F66: =(F62-F55*(1-tax_eq))/F64 -> 5.6364725 | G66: =(G62-G55*(1-tax_eq))/G64 -> 11.126699 | H66: =(H62-H55*(1-tax_eq))/H64 -> 11.385426 | I66: =(I62-I55*(1-tax_eq))/I64 -> 12.273228 | J66: =(J62-J55*(1-tax_eq))/J64 -> 13.496392 | K66: =(K62-K55*(1-tax_eq))/K64 -> 14.796445 | L66: =(L62-L55*(1-tax_eq))/L64 -> 15.484578 | M66: =(M62-M55*(1-tax_eq))/M64 -> 15.990159 | N66: 權益證券損益以 tax_eq 21% 稅後扣除；可與共識 non-GAAP EPS 比較
A67: EPS（評價口徑；讀法 2 含稅後影子效益，美元） | B67: US$ | F67: =(F62+(internal_ai_reading=2)*F48*(1-tax))/F64 -> 5.9019265 | G67: =(G62+(internal_ai_reading=2)*G48*(1-tax))/G64 -> 20.09251 | H67: =(H62+(internal_ai_reading=2)*H48*(1-tax))/H64 -> 13.562396 | I67: =(I62+(internal_ai_reading=2)*I48*(1-tax))/I64 -> 16.729413 | J67: =(J62+(internal_ai_reading=2)*J48*(1-tax))/J64 -> 19.993619 | K67: =(K62+(internal_ai_reading=2)*K48*(1-tax))/K64 -> 22.80043 | L67: =(L62+(internal_ai_reading=2)*L48*(1-tax))/L64 -> 24.514343 | M67: =(M62+(internal_ai_reading=2)*M48*(1-tax))/M64 -> 25.571627 | N67: 評價口徑；財報口徑見上兩列
A68: 股權報酬（已含在分部營業利益內） | B68: US$B | C68: =Q!J44 -> 22.785 | D68: =Q!K44 -> 24.953 | E68: =Q!L44 -> 14.708 | F68: =F24*sbc_r -> 16.858366 | G68: =E68+F68 -> 31.566366 | H68: =H24*sbc_r -> 38.917756 | I68: =I24*sbc_r -> 46.011838 | J68: =J24*sbc_r -> 52.682857 | K68: =K24*sbc_r -> 58.222048 | L68: =L24*sbc_r -> 62.903518 | M68: =M24*sbc_r -> 67.695462
A70: 情境 B（近四季成長收斂；基準）
A71: 項目 | B71: 單位 | C71: FY2024A | D71: FY2025A | E71: 1H26A | F71: 2H26E | G71: FY2026E | H71: FY2027E | I71: FY2028E | J71: FY2029E | K71: FY2030E | L71: FY2031E | M71: FY2032E | N71: 說明
A72: Google Search & other | B72: US$B | C72: =Seg!C47 -> 198.084 | D72: =Seg!D47 -> 224.532 | E72: =Seg!E47 -> 123.67 | F72: =Seg!F47 -> 139.7411 | G72: =Seg!G47 -> 263.4111 | H72: =Seg!H47 -> 301.87173 | I72: =Seg!I47 -> 339.30582 | J72: =Seg!J47 -> 373.91613 | ... M72: =Seg!M47 -> 471.02664
A73: YouTube ads | B73: US$B | C73: =Seg!C49 -> 36.147 | D73: =Seg!D49 -> 40.367 | E73: =Seg!E49 -> 20.938 | F73: =Seg!F49 -> 24.179364 | G73: =Seg!G49 -> 45.117364 | H73: =Seg!H49 -> 49.983474 | I73: =Seg!I49 -> 54.910329 | J73: =Seg!J49 -> 59.812989 | ... M73: =Seg!M49 -> 75.347139
A74: Google Network | B74: US$B | C74: =Seg!C51 -> 30.359 | D74: =Seg!D51 -> 29.792 | E74: =Seg!E51 -> 14.274 | F74: =Seg!F51 -> 14.851255 | G74: =Seg!G51 -> 29.125255 | H74: =Seg!H51 -> 28.649377 | I74: =Seg!I51 -> 28.337309 | J74: =Seg!J51 -> 28.182975 | ... M74: =Seg!M51 -> 28.182975
A75: Google subscriptions, platforms, and devices | B75: US$B | C75: =Seg!C53 -> 40.34 | D75: =Seg!D53 -> 48.03 | E75: =Seg!E53 -> 25.295 | F75: =Seg!F53 -> 31.193701 | G75: =Seg!G53 -> 56.488701 | H75: =Seg!H53 -> 65.502963 | I75: =Seg!I53 -> 74.654879 | J75: =Seg!J53 -> 83.602922 | ... M75: =Seg!M53 -> 111.27549
A76: Google Services | B76: US$B | C76: =Seg!C54 -> 304.93 | D76: =Seg!D54 -> 342.721 | E76: =Seg!E54 -> 184.177 | F76: =Seg!F54 -> 209.96542 | G76: =Seg!G54 -> 394.14242 | H76: =Seg!H54 -> 446.00755 | I76: =Seg!I54 -> 497.20834 | J76: =Seg!J54 -> 545.51502 | ... M76: =Seg!M54 -> 685.83224
A77: Cloud AI（命題子列） | B77: US$B | E77: =Seg!E55 -> 9.7583729 | F77: =Seg!F55 -> 13.072238 | G77: =Seg!G55 -> 22.830611 | H77: =Seg!H55 -> 38.882858 | I77: =Seg!I55 -> 56.703559 | J77: =Seg!J55 -> 73.012119 | K77: =Seg!K55 -> 85.400179 | L77: =Seg!L55 -> 94.03926 | M77: =Seg!M55 -> 99.017013
A78: TPU 系統銷售（命題子列） | B78: US$B | E78: =Seg!E56 -> 0 | F78: =Seg!F56 -> 1 | G78: =Seg!G56 -> 1 | H78: =Seg!H56 -> 13 | I78: =Seg!I56 -> 13 | J78: =Seg!J56 -> 13 | K78: =Seg!K56 -> 13 | L78: =Seg!L56 -> 13 | M78: =Seg!M56 -> 13
A79: Cloud 其他（命題子列） | B79: US$B | E79: =Seg!E58 -> 35.037627 | F79: =Seg!F58 -> 42.381373 | G79: =Seg!G58 -> 77.419 | H79: =Seg!H58 -> 105.85824 | I79: =Seg!I58 -> 134.60523 | J79: =Seg!J58 -> 158.26622 | K79: =Seg!K58 -> 170.92752 | L79: =Seg!L58 -> 184.60172 | M79: =Seg!M58 -> 199.36986
A80: Google Cloud | B80: US$B | C80: =Seg!C59 -> 43.229 | D80: =Seg!D59 -> 58.705 | E80: =Seg!E59 -> 44.796 | F80: =Seg!F59 -> 56.453611 | G80: =Seg!G59 -> 101.24961 | H80: =Seg!H59 -> 157.7411 | I80: =Seg!I59 -> 204.30879 | J80: =Seg!J59 -> 244.27834 | ... M80: =Seg!M59 -> 311.38687
A81: Other Bets | B81: US$B | C81: =Seg!C60 -> 1.648 | D81: =Seg!D60 -> 1.537 | E81: =Seg!E60 -> 0.793 | F81: =Seg!F60 -> 0.75 | G81: =Seg!G60 -> 1.543 | H81: =Seg!H60 -> 1.6 | I81: =Seg!I60 -> 1.8 | J81: =Seg!J60 -> 2 | ... M81: =Seg!M60 -> 2.6
A82: Hedging gains (losses) | B82: US$B | C82: =Seg!C61 -> 0.211 | D82: =Seg!D61 -> -0.127 | E82: =Seg!E61 -> -0.074 | F82: =Seg!F61 -> 0 | G82: =Seg!G61 -> -0.074 | H82: =Seg!H61 -> 0 | I82: =Seg!I61 -> 0 | J82: =Seg!J61 -> 0 | ... M82: =Seg!M61 -> 0
A83: 合併營收 | B83: US$B | C83: =Seg!C62 -> 350.018 | D83: =Seg!D62 -> 402.836 | E83: =Seg!E62 -> 229.692 | F83: =Seg!F62 -> 267.16903 | G83: =Seg!G62 -> 496.86103 | H83: =Seg!H62 -> 605.34864 | I83: =Seg!I62 -> 703.31713 | J83: =Seg!J62 -> 791.79336 | ... M83: =Seg!M62 -> 999.81912
A84: 合併營收年增 | B84: % | D84: =D83/C83-1 -> 0.15090081 | G84: =G83/D83-1 -> 0.23340772 | H84: =H83/G83-1 -> 0.21834598 | I84: =I83/H83-1 -> 0.16183812 | J84: =J83/I83-1 -> 0.12579849 | K84: =K83/J83-1 -> 0.086269958 | L84: =L83/K83-1 -> 0.080436801 | M84: =M83/L83-1 -> 0.075901328
A85: 檢查：產品線合計 − Google Services | B85: US$B | C85: =C72+C73+C74+C75-C76 -> 0 | D85: =D72+D73+D74+D75-D76 -> 0 | E85: =E72+E73+E74+E75-E76 -> 0 | F85: =F72+F73+F74+F75-F76 -> 0 | G85: =G72+G73+G74+G75-G76 -> 0 | H85: =H72+H73+H74+H75-H76 -> 0 | I85: =I72+I73+I74+I75-I76 -> 0 | J85: =J72+J73+J74+J75-J76 -> 0 | ... M85: =M72+M73+M74+M75-M76 -> 0
A86: 檢查：Cloud 子列合計 − Google Cloud | B86: US$B | E86: =E77+E78+E79-E80 -> 0 | F86: =F77+F78+F79-F80 -> 0 | G86: =G77+G78+G79-G80 -> 0 | H86: =H77+H78+H79-H80 -> 0 | I86: =I77+I78+I79-I80 -> 0 | J86: =J77+J78+J79-J80 -> 0 | K86: =K77+K78+K79-K80 -> 0 | L86: =L77+L78+L79-L80 -> 0 | M86: =M77+M78+M79-M80 -> 0
A87: 檢查：分部合計＋避險 − 合併營收 | B87: US$B | C87: =C76+C80+C81+C82-C83 -> 0 | D87: =D76+D80+D81+D82-D83 -> 0 | E87: =E76+E80+E81+E82-E83 -> 0 | F87: =F76+F80+F81+F82-F83 -> 0 | G87: =G76+G80+G81+G82-G83 -> 0 | H87: =H76+H80+H81+H82-H83 -> 0 | I87: =I76+I80+I81+I82-I83 -> 0 | J87: =J76+J80+J81+J82-J83 -> 0 | ... M87: =M76+M80+M81+M82-M83 -> 0
A88: Search 情境差額（相對 B 路徑） | B88: US$B | F88: =Seg!F47-Seg!F43 -> 0 | G88: =F88 -> 0 | H88: =Seg!H47-Seg!H43 -> 0 | I88: =Seg!I47-Seg!I43 -> 0 | J88: =Seg!J47-Seg!J43 -> 0 | K88: =Seg!K47-Seg!K43 -> 0 | L88: =Seg!L47-Seg!L43 -> 0 | M88: =Seg!M47-Seg!M43 -> 0
A89: Google Services EBITDA | B89: US$B | F89: =m_svc*(F76-F88)+inc_m*F88-svc_sh*(Thesis!F68+Thesis!F69) -> 101.67943 | H89: =m_svc*(H76-H88)+inc_m*H88-svc_sh*(Thesis!H68+Thesis!H69) -> 210.28814 | I89: =m_svc*(I76-I88)+inc_m*I88-svc_sh*(Thesis!I68+Thesis!I69) -> 231.98338 | J89: =m_svc*(J76-J88)+inc_m*J88-svc_sh*(Thesis!J68+Thesis!J69) -> 255.91388 | K89: =m_svc*(K76-K88)+inc_m*K88-svc_sh*(Thesis!K68+Thesis!K69) -> 278.0333 | L89: =m_svc*(L76-L88)+inc_m*L88-svc_sh*(Thesis!L68+Thesis!L69) -> 299.37413 | M89: =m_svc*(M76-M88)+inc_m*M88-svc_sh*(Thesis!M68+Thesis!M69) -> 323.38196 | N89: B 路徑營收 × m_svc（Q 頁；預設 1H26 49.4%，mb_ttm＝1 時近四季 47.6%）＋Search 差額 × inc_m − 自用 AI 增量營運與租金 × svc_sh
A90: Google Services 折舊（基礎分攤＋新增非 AI＋自用 AI × svc_sh） | B90: US$B | F90: =Thesis!F77*sh_svc+Seg!F71+Thesis!F65*svc_sh -> 14.996569 | H90: =Thesis!H77*sh_svc+Seg!H71+Thesis!H65*svc_sh -> 40.05465 | I90: =Thesis!I77*sh_svc+Seg!I71+Thesis!I65*svc_sh -> 54.108444 | J90: =Thesis!J77*sh_svc+Seg!J71+Thesis!J65*svc_sh -> 67.620756 | K90: =Thesis!K77*sh_svc+Seg!K71+Thesis!K65*svc_sh -> 77.840291 | L90: =Thesis!L77*sh_svc+Seg!L71+Thesis!L65*svc_sh -> 84.466778 | M90: =Thesis!M77*sh_svc+Seg!M71+Thesis!M65*svc_sh -> 96.404947
A91: Google Services 營業利益 | B91: US$B | C91: =Q!J18 -> 121.263 | D91: =Q!K18 -> 139.404 | E91: =Q!L18 -> 80.133 | F91: =F89-F90 -> 86.682859 | G91: =E91+F91 -> 166.81586 | H91: =H89-H90 -> 170.23349 | I91: =I89-I90 -> 177.87493 | J91: =J89-J90 -> 188.29312 | K91: =K89-K90 -> 200.193 | L91: =L89-L90 -> 214.90736 | M91: =M89-M90 -> 226.97702
A92: Google Cloud EBITDA | B92: US$B | F92: =Thesis!F41+F78*tpu_m+F79*m_co -> 23.180487 | H92: =Thesis!H41+H78*tpu_m+H79*m_co -> 65.910285 | I92: =Thesis!I41+I78*tpu_m+I79*m_co -> 89.262727 | J92: =Thesis!J41+J78*tpu_m+J79*m_co -> 109.92081 | K92: =Thesis!K41+K78*tpu_m+K79*m_co -> 124.11433 | L92: =Thesis!L41+L78*tpu_m+L79*m_co -> 135.37916 | M92: =Thesis!M41+M78*tpu_m+M79*m_co -> 143.81331 | N92: Cloud AI EBITDA（Tokenomics 營運成本）＋TPU × tpu_m＋Cloud 其他 × m_co
A93: Google Cloud 折舊（基礎分攤＋對外 AI＋新增非 AI） | B93: US$B | F93: =Thesis!F77*sh_cloud+Thesis!F64+Seg!F72 -> 4.8211933 | H93: =Thesis!H77*sh_cloud+Thesis!H64+Seg!H72 -> 16.854495 | I93: =Thesis!I77*sh_cloud+Thesis!I64+Seg!I72 -> 27.1875 | J93: =Thesis!J77*sh_cloud+Thesis!J64+Seg!J72 -> 38.067345 | K93: =Thesis!K77*sh_cloud+Thesis!K64+Seg!K72 -> 48.232805 | L93: =Thesis!L77*sh_cloud+Thesis!L64+Seg!L72 -> 57.875471 | M93: =Thesis!M77*sh_cloud+Thesis!M64+Seg!M72 -> 67.828382
A94: Google Cloud 營業利益 | B94: US$B | C94: =Q!J19 -> 6.112 | D94: =Q!K19 -> 13.91 | E94: =Q!L19 -> 15.412 | F94: =F92-F93 -> 18.359293 | G94: =E94+F94 -> 33.771293 | H94: =H92-H93 -> 49.05579 | I94: =I92-I93 -> 62.075227 | J94: =J92-J93 -> 71.853461 | K94: =K92-K93 -> 75.881525 | L94: =L92-L93 -> 77.503691 | M94: =M92-M93 -> 75.984932
A95: Other Bets 折舊（基礎分攤＋新增非 AI） | B95: US$B | F95: =Thesis!F77*sh_ob+Seg!F73 -> 0.049109617 | H95: =Thesis!H77*sh_ob+Seg!H73 -> 0.10286923 | I95: =Thesis!I77*sh_ob+Seg!I73 -> 0.11276923 | J95: =Thesis!J77*sh_ob+Seg!J73 -> 0.11896729 | K95: =Thesis!K77*sh_ob+Seg!K73 -> 0.11476607 | L95: =Thesis!L77*sh_ob+Seg!L73 -> 0.095650871 | M95: =Thesis!M77*sh_ob+Seg!M73 -> 0.10678769
A96: Other Bets 營業利益 | B96: US$B | C96: =Q!J20 -> -4.444 | D96: =Q!K20 -> -7.515 | E96: =Q!L20 -> -3.899 | F96: =ob_oi*0.5 -> -4.5 | G96: =E96+F96 -> -8.399 | H96: =ob_oi*1 -> -9 | I96: =ob_oi*1 -> -9 | J96: =ob_oi*1 -> -9 | K96: =ob_oi*1 -> -9 | L96: =ob_oi*1 -> -9 | M96: =ob_oi*1 -> -9
A97: Other Bets EBITDA | B97: US$B | F97: =F96+F95 -> -4.4508904 | H97: =H96+H95 -> -8.8971308 | I97: =I96+I95 -> -8.8872308 | J97: =J96+J95 -> -8.8810327 | K97: =K96+K95 -> -8.8852339 | L97: =L96+L95 -> -8.9043491 | M97: =M96+M95 -> -8.8932123
A98: Alphabet-level 折舊（自用 AI × (1 − svc_sh)） | B98: US$B | F98: =Thesis!F65*(1-svc_sh) -> 1.9953469 | H98: =Thesis!H65*(1-svc_sh) -> 9.83243 | I98: =Thesis!I65*(1-svc_sh) -> 17.366395 | J98: =Thesis!J65*(1-svc_sh) -> 25.133508 | K98: =Thesis!K65*(1-svc_sh) -> 32.401108 | L98: =Thesis!L65*(1-svc_sh) -> 39.714304 | M98: =Thesis!M65*(1-svc_sh) -> 45.660155
A99: Alphabet-level activities（避險營收 − 未分攤費用 − 自用 AI 增量成本 × (1 − svc_sh)） | B99: US$B | C99: =Q!J21 -> -10.541 | D99: =Q!K21 -> -16.76 | E99: =Q!L21 -> -11.18 | F99: =F82-abc_rate*F83-Thesis!F72 -> -16.29226 | G99: =E99+F99 -> -27.47226 | H99: =H82-abc_rate*H83-Thesis!H72 -> -45.828239 | I99: =I82-abc_rate*I83-Thesis!I72 -> -60.500113 | J99: =J82-abc_rate*J83-Thesis!J72 -> -72.502938 | K99: =K82-abc_rate*K83-Thesis!K72 -> -82.510391 | L99: =L82-abc_rate*L83-Thesis!L72 -> -94.314836 | M99: =M82-abc_rate*M83-Thesis!M72 -> -104.32991
A100: Alphabet-level EBITDA | B100: US$B | F100: =F99+F98 -> -14.296913 | H100: =H99+H98 -> -35.995809 | I100: =I99+I98 -> -43.133717 | J100: =J99+J98 -> -47.36943 | K100: =K99+K98 -> -50.109283 | L100: =L99+L98 -> -54.600532 | M100: =M99+M98 -> -58.669753
A101: 分部營業利益合計 | B101: US$B | C101: =C91+C94+C96+C99 -> 112.39 | D101: =D91+D94+D96+D99 -> 129.039 | E101: =E91+E94+E96+E99 -> 80.466 | F101: =F91+F94+F96+F99 -> 84.249893 | G101: =G91+G94+G96+G99 -> 164.71589 | H101: =H91+H94+H96+H99 -> 164.46104 | I101: =I91+I94+I96+I99 -> 170.45005 | J101: =J91+J94+J96+J99 -> 178.64364 | ... M101: =M91+M94+M96+M99 -> 189.63204
A102: 合併 EBITDA（分部 EBITDA 合計） | B102: US$B | F102: =F89+F92+F97+F100 -> 106.11211 | H102: =H89+H92+H97+H100 -> 231.30548 | I102: =I89+I92+I97+I100 -> 269.22515 | J102: =J89+J92+J97+J100 -> 309.58422 | K102: =K89+K92+K97+K100 -> 343.15311 | L102: =L89+L92+L97+L100 -> 371.24841 | M102: =M89+M92+M97+M100 -> 399.63231
A103: 折舊合計（基礎＋新增 AI＋新增非 AI） | B103: US$B | C103: =Q!J43 -> 15.311 | D103: =Q!K43 -> 21.136 | E103: =Q!L43 -> 13.586 | F103: =Thesis!F77+Thesis!F63+Seg!F74 -> 21.862219 | G103: =E103+F103 -> 35.448219 | H103: =Thesis!H77+Thesis!H63+Seg!H74 -> 66.844444 | I103: =Thesis!I77+Thesis!I63+Seg!I74 -> 98.775109 | J103: =Thesis!J77+Thesis!J63+Seg!J74 -> 130.94058 | K103: =Thesis!K77+Thesis!K63+Seg!K74 -> 158.58897 | L103: =Thesis!L77+Thesis!L63+Seg!L74 -> 182.1522 | M103: =Thesis!M77+Thesis!M63+Seg!M74 -> 210.00027 | N103: 1H26 與以前為現金流量表實績
...

Sheet CF
A1: CF — 現金流（US$B）。營運現金＝淨利＋折舊＋股權報酬＋營運資金；資本支出＝AI（Thesis）＋非 AI（Seg）；自由現金流＝營運現金 − 資本支出 − 融資租賃本金。融資順序：現金 → 減少回購 → 新債（最低現金 50）
A2: 2026 年：上半年發行普通股 30.5B（承銷＋Berkshire）與強制轉換特別股 19.1B、暫停回購（C4：現金牛最強，但 2026 已轉向外部融資）；2H26 回購 0；FY2027 起回購目標 17.0／年（現金不足時先減回購）
A4: 收支關卡（地圖讀這兩列；模型期間 FY2026–FY2030，FY2026 含上半年實績）
A5: 項目 | B5: 情境 A | C5: 情境 B | D5: 情境 C | E5: 說明
A6: 收支關卡：自由現金流扣股利（五年合計） | B6: =SUM(G26:K26) -> 261.21839 | C6: =SUM(G58:K58) -> 180.04925 | D6: =SUM(G90:K90) -> 29.846864 | E6: FY2026–FY2030 自由現金流（扣融資租賃本金）− 普通股與特別股股利；FY2026 含上半年實績。負值＝入不敷出
A7: 其中：五年新增舉債 | B7: =SUM(G35:K35) -> 0 | C7: =SUM(G67:K67) -> 0 | D7: =SUM(G99:K99) -> 0
A8: 其中：五年回購合計（FY2027–FY2030 目標 4 × bb_t） | B8: =SUM(G34:K34) -> 68.012 | C8: =SUM(G66:K66) -> 68.012 | D8: =SUM(G98:K98) -> 68.012
A9: 是否需要舉債或停止回購 | B9: =IF(B7>0.001,"需要舉債"&IF(B8<4*bb_t-0.001,"且減少回購",""),IF(B8<4*bb_t-0.001,"不需舉債，但須減少回購","不需舉債，回購照目標")) -> 不需舉債，回購照目標 | C9: =IF(C7>0.001,"需要舉債"&IF(C8<4*bb_t-0.001,"且減少回購",""),IF(C8<4*bb_t-0.001,"不需舉債，但須減少回購","不需舉債，回購照目標")) -> 不需舉債，回購照目標 | D9: =IF(D7>0.001,"需要舉債"&IF(D8<4*bb_t-0.001,"且減少回購",""),IF(D8<4*bb_t-0.001,"不需舉債，但須減少回購","不需舉債，回購照目標")) -> 不需舉債，回購照目標 | E9: 依現金瀑布：現金 → 減少回購 → 新債（最低現金 50）；2026 上半年已發行股權 49.6、2H26 起新債 25.0 為已發生事件
A10: 檢查：收支關卡 − 首年起五年逐欄加總（FY2026＋…＋FY2030） | B10: =B6-(G26+H26+I26+J26+K26) -> 0 | C10: =C6-(G58+H58+I58+J58+K58) -> 0 | D10: =D6-(G90+H90+I90+J90+K90) -> 0
A11: 情境 A（AI 搜尋擴大變現）
A12: 項目 | B12: 單位 | C12: FY2024A | D12: FY2025A | E12: 1H26A | F12: 2H26E | G12: FY2026E | H12: FY2027E | I12: FY2028E | J12: FY2029E | K12: FY2030E | L12: FY2031E | M12: FY2032E | N12: 說明
A13: 淨利 | B13: US$B | C13: =PL!C59 -> 100.118 | D13: =PL!D59 -> 132.17 | E13: =PL!E59 -> 174.771 | F13: =PL!F59 -> 70.534182 | G13: =PL!G59 -> 245.30518 | H13: =PL!H59 -> 143.37544 | I13: =PL!I59 -> 155.41251 | J13: =PL!J59 -> 171.66943 | ... M13: =PL!M59 -> 207.58716
A14: 折舊 | B14: US$B | C14: =PL!C44 -> 15.311 | D14: =PL!D44 -> 21.136 | E14: =PL!E44 -> 13.586 | F14: =PL!F44 -> 21.862219 | G14: =PL!G44 -> 35.448219 | H14: =PL!H44 -> 66.861566 | I14: =PL!I44 -> 98.882404 | J14: =PL!J44 -> 131.22897 | ... M14: =PL!M44 -> 211.37338
A15: 股權報酬（非現金） | B15: US$B | C15: =PL!C68 -> 22.785 | D15: =PL!D68 -> 24.953 | E15: =PL!E68 -> 14.708 | F15: =PL!F68 -> 16.858366 | G15: =PL!G68 -> 31.566366 | H15: =PL!H68 -> 38.917756 | I15: =PL!I68 -> 46.011838 | J15: =PL!J68 -> 52.682857 | ... M15: =PL!M68 -> 67.695462
A16: 營運資金變動（流入＋） | B16: US$B | F16: =wc_2h -> 8.49 | G16: =F16 -> 8.49 | H16: =wc_k*(PL!H24-PL!G24) -> 1.402855 | I16: =wc_k*(PL!I24-PL!H24) -> 1.3153845 | J16: =wc_k*(PL!J24-PL!I24) -> 1.23694 | K16: =wc_k*(PL!K24-PL!J24) -> 1.0270767 | L16: =wc_k*(PL!L24-PL!K24) -> 0.86803803 | M16: =wc_k*(PL!M24-PL!L24) -> 0.8885221 | N16: 2H26＝上一年度同期實際（C14）；之後＝營收增量 × wc_k
A17: 其他非現金調整（實績差額：權益證券利益迴轉、遞延稅等） | B17: US$B | C17: =Q!J45-C13-C14-C15 -> -12.915 | D17: =Q!K45-D13-D14-D15 -> -13.546 | E17: =Q!L45-E13-E14-E15 -> -118.206 | F17: 0 | G17: =E17+F17 -> -118.206 | H17: 0 | I17: 0 | J17: 0 | K17: 0 | L17: 0 | M17: 0
A18: 營運現金流 | B18: US$B | C18: =C13+C14+C15+C16+C17 -> 125.299 | D18: =D13+D14+D15+D16+D17 -> 164.713 | E18: =E13+E14+E15+E16+E17 -> 84.859 | F18: =F13+F14+F15+F16+F17 -> 117.74477 | G18: =G13+G14+G15+G16+G17 -> 202.60377 | H18: =H13+H14+H15+H16+H17 -> 250.55761 | I18: =I13+I14+I15+I16+I17 -> 301.62214 | J18: =J13+J14+J15+J16+J17 -> 356.8182 | ... M18: =M13+M14+M15+M16+M17 -> 487.54452
A19: 資本支出：AI（Thesis；首期含指引下限補足） | B19: US$B | F19: =Thesis!F52 -> 98.2828 | G19: =F19 -> 98.2828 | H19: =Thesis!H52 -> 190.01908 | I19: =Thesis!I52 -> 201.14439 | J19: =Thesis!J52 -> 180.85921 | K19: =Thesis!K52 -> 171.69309 | L19: =Thesis!L52 -> 177.21448 | M19: =Thesis!M52 -> 167.87684
A20: 資本支出：非 AI（Seg） | B20: US$B | F20: =Seg!F34 -> 21.1192 | G20: =F20 -> 21.1192 | H20: =Seg!H34 -> 48.712972 | I20: =Seg!I34 -> 58.413871 | J20: =Seg!J34 -> 67.091178 | K20: =Seg!K34 -> 73.387536 | L20: =Seg!L34 -> 79.235057 | M20: =Seg!M34 -> 85.560454
A21: 資本支出合計 | B21: US$B | C21: =Q!J46 -> 52.535 | D21: =Q!K46 -> 91.447 | E21: =Q!L46 -> 80.598 | F21: =F19+F20 -> 119.402 | G21: =E21+F21 -> 200 | H21: =H19+H20 -> 238.73206 | I21: =I19+I20 -> 259.55826 | J21: =J19+J20 -> 247.95039 | K21: =K19+K20 -> 245.08063 | L21: =L19+L20 -> 256.44954 | M21: =M19+M20 -> 253.4373
A22: 融資租賃本金 | B22: US$B | E22: =lease_1H -> 0.84 | F22: =lease_2H -> 0.206 | G22: =E22+F22 -> 1.046 | H22: =lease_27 -> 0.387 | I22: =lease_28 -> 0.377 | J22: =lease_29 -> 0.356 | K22: =lease_30 -> 0.285 | L22: =lease_31 -> 0.25 | M22: =lease_32 -> 0.25 | N22: 1H26：10-Q 附註 4 補充資訊 0.840 [Interested-party]；FY2024–25 未列（公司 FCF 定義不扣）
A23: 自由現金流（營運現金 − 資本支出 − 融資租賃本金） | B23: US$B | C23: =C18-C21-N(C22) -> 72.764 | D23: =D18-D21-N(D22) -> 73.266 | E23: =E18-E21-N(E22) -> 3.421 | F23: =F18-F21-N(F22) -> -1.8632328 | G23: =G18-G21-N(G22) -> 1.5577672 | H23: =H18-H21-N(H22) -> 11.438559 | I23: =I18-I21-N(I22) -> 41.686881 | J23: =J18-J21-N(J22) -> 108.51181 | ... M23: =M18-M21-N(M22) -> 233.85722
A24: 普通股股利 | B24: US$B | C24: =Q!J50 -> 7.363 | D24: =Q!K50 -> 10.049 | E24: =Q!L50 -> 5.231 | F24: =dps/2*sh_out -> 5.3812 | G24: =E24+F24 -> 10.6122 | H24: =dps*(1+dps_g)^(2027-2026)*PL!F63 -> 11.503745 | I24: =dps*(1+dps_g)^(2028-2026)*PL!H63 -> 12.15129 | J24: =dps*(1+dps_g)^(2029-2026)*PL!I63 -> 12.840731 | K24: =dps*(1+dps_g)^(2030-2026)*PL!J63 -> 13.632852 | L24: =dps*(1+dps_g)^(2031-2026)*PL!K63 -> 14.416917 | M24: =dps*(1+dps_g)^(2032-2026)*PL!L63 -> 15.250704 | N24: 2H26＝0.22 × 2 × 流通股；之後每股 +5%／年 × 期初稀釋股數（避免與回購循環）
A25: 特別股股利 | B25: US$B | E25: =PL!E61 -> 0 | F25: =PL!F61 -> 0.535 | G25: =PL!G61 -> 0.535 | H25: =PL!H61 -> 1.203 | I25: =PL!I61 -> 1.203 | J25: =PL!J61 -> 0.602 | K25: =PL!K61 -> 0 | L25: =PL!L61 -> 0 | M25: =PL!M61 -> 0
A26: 自由現金流扣股利 | B26: US$B | C26: =C23-C24-N(C25) -> 65.401 | D26: =D23-D24-N(D25) -> 63.217 | E26: =E23-E24-N(E25) -> -1.81 | F26: =F23-F24-N(F25) -> -7.7794328 | G26: =G23-G24-N(G25) -> -9.5894328 | H26: =H23-H24-N(H25) -> -1.2681856 | I26: =I23-I24-N(I25) -> 28.332591 | J26: =J23-J24-N(J25) -> 95.069078 | ... M26: =M23-M24-N(M25) -> 218.60652
A27: 策略投資（Anthropic 出資；1H26 含 Wiz、Intersect 收購） | B27: US$B | E27: =anth_1H -> 55.44 | F27: =anth_2H -> 2.222 | G27: =E27+F27 -> 57.662 | H27: =anth_27 -> 4.444 | I27: =anth_28 -> 4.444 | J27: =anth_29 -> 4.444 | K27: =anth_30 -> 4.444 | L27: =anth_31 -> 0 | M27: =anth_32 -> 0 | N27: 1H26：非上市證券 22.1＋收購 33.7＋其他 − 出售（legacy_v0.2/company.json ytdActual.jv）[Derived]；投資活動，不在自由現金流
A28: 債務到期償還 | B28: US$B | E28: =mat_1H -> 5.253 | F28: =mat_2H -> 2 | G28: =E28+F28 -> 7.253 | H28: =mat_27 -> 1 | I28: =mat_28 -> 2.676 | J28: =mat_29 -> 1.764 | K28: =mat_30 -> 7.186 | L28: =mat_31 -> 5 | M28: =mat_32 -> 5 | N28: 1H26：10-Q 償還債務 [Interested-party]
A29: 已發行新債 | B29: US$B | E29: =newd_1H -> 56.226 | F29: =debt_new_2h -> 25 | G29: =E29+F29 -> 81.226 | H29: 0 | I29: 0 | J29: 0 | K29: 0 | L29: 0 | M29: 0 | N29: 1H26：發債淨額（10-Q）；2H26：2026-08 美元票據 25.0
A30: 股權發行（普通股＋強制轉換特別股，淨額） | B30: US$B | E30: =eq_1H -> 49.562 | F30: 0 | G30: =E30+F30 -> 49.562 | H30: 0 | I30: 0 | J30: 0 | K30: 0 | L30: 0 | M30: 0 | N30: C4：2026-06 普通股 30.5（承銷 20.5＋Berkshire 10.0）＋特別股 19.1 [Interested-party]；ATM 40B 與代扣稅不建模
A31: 期初現金（現金＋債權類有價證券） | B31: US$B | E31: =cash_ye25 -> 120.53 | F31: =E36 -> 155.411 | H31: =F36 -> 168.40957 | I31: =H36 -> 144.69438 | J31: =I36 -> 148.90397 | K31: =J36 -> 220.76205 | L31: =K36 -> 340.80339 | M31: =L36 -> 494.07479
A32: 其他（1H26 實績差額：代扣稅、capped call、匯率；預測期 0） | B32: US$B | E32: =cash_0-(E31+E23-E24-E25-E27-E28+E29+E30) -> -8.404 | F32: 0 | H32: 0 | I32: 0 | J32: 0 | K32: 0 | L32: 0 | M32: 0
A33: 回購前現金 | B33: US$B | E33: =E31+E23-E24-E25-E27-E28+E29+E30+E32 -> 155.411 | F33: =F31+F23-F24-F25-F27-F28+F29+F30+F32 -> 168.40957 | H33: =H31+H23-H24-H25-H27-H28+H29+H30+H32 -> 161.69738 | I33: =I31+I23-I24-I25-I27-I28+I29+I30+I32 -> 165.90697 | J33: =J31+J23-J24-J25-J27-J28+J29+J30+J32 -> 237.76505 | K33: =K31+K23-K24-K25-K27-K28+K29+K30+K32 -> 357.80639 | L33: =L31+L23-L24-L25-L27-L28+L29+L30+L32 -> 511.07779 | M33: =M31+M23-M24-M25-M27-M28+M29+M30+M32 -> 707.6813
A34: 回購 | B34: US$B | E34: =Q!L49 -> 0 | F34: 0 | G34: =E34+F34 -> 0 | H34: =MAX(0,MIN(bb_t,H33-min_cash)) -> 17.003 | I34: =MAX(0,MIN(bb_t,I33-min_cash)) -> 17.003 | J34: =MAX(0,MIN(bb_t,J33-min_cash)) -> 17.003 | K34: =MAX(0,MIN(bb_t,K33-min_cash)) -> 17.003 | L34: =MAX(0,MIN(bb_t,L33-min_cash)) -> 17.003 | M34: =MAX(0,MIN(bb_t,M33-min_cash)) -> 17.003 | N34: 2H26＝0（暫停，C4）；之後＝MIN(回購目標, 回購前現金 − 最低現金)
A35: 新增舉債（現金低於最低現金時） | B35: US$B | E35: 0 | F35: =MAX(0,min_cash-(F33-F34)) -> 0 | G35: =E35+F35 -> 0 | H35: =MAX(0,min_cash-(H33-H34)) -> 0 | I35: =MAX(0,min_cash-(I33-I34)) -> 0 | J35: =MAX(0,min_cash-(J33-J34)) -> 0 | K35: =MAX(0,min_cash-(K33-K34)) -> 0 | L35: =MAX(0,min_cash-(L33-L34)) -> 0 | M35: =MAX(0,min_cash-(M33-M34)) -> 0
A36: 期末現金（現金＋債權類有價證券） | B36: US$B | E36: =E33-E34+E35 -> 155.411 | F36: =F33-F34+F35 -> 168.40957 | H36: =H33-H34+H35 -> 144.69438 | I36: =I33-I34+I35 -> 148.90397 | J36: =J33-J34+J35 -> 220.76205 | K36: =K33-K34+K35 -> 340.80339 | L36: =L33-L34+L35 -> 494.07479 | M36: =M33-M34+M35 -> 690.6783
A37: 檢查：1H26 期末現金 − 10-Q（應為 0） | B37: US$B | E37: =E36-cash_0 -> 0
A38: 期初債務 | B38: US$B | E38: =debt_ye25 -> 49.085 | F38: =E39 -> 101.085 | H38: =F39 -> 124.085 | I38: =H39 -> 123.085 | J38: =I39 -> 120.409 | K38: =J39 -> 118.645 | L38: =K39 -> 111.459 | M38: =L39 -> 106.459 | N38: 2025-12-31 面額 49.085（事實總帳 debt.face.fy2025）
A39: 期末債務 | B39: US$B | E39: =debt_0 -> 101.085 | F39: =F38-F28+F29+F35 -> 124.085 | H39: =H38-H28+H29+H35 -> 123.085 | I39: =I38-I28+I29+I35 -> 120.409 | J39: =J38-J28+J29+J35 -> 118.645 | K39: =K38-K28+K29+K35 -> 111.459 | L39: =L38-L28+L29+L35 -> 106.459 | M39: =M38-M28+M29+M35 -> 101.459 | N39: 1H26＝10-Q 面額（含匯率變動）
A40: 淨現金（現金 − 債務） | B40: US$B | E40: =E36-E39 -> 54.326 | F40: =F36-F39 -> 44.324567 | H40: =H36-H39 -> 21.609382 | I40: =I36-I39 -> 28.494973 | J40: =J36-J39 -> 102.11705 | K40: =K36-K39 -> 229.34439 | L40: =L36-L39 -> 387.61579 | M40: =M36-M39 -> 589.2193
A41: 回購均價（現價 × (1＋ke)^年數） | B41: US$ | F41: =px -> 316.8 | H41: =px*(1+ke)^(2027+mid-t_px0) -> 340.61156 | I41: =px*(1+ke)^(2028+mid-t_px0) -> 378.91778 | J41: =px*(1+ke)^(2029+mid-t_px0) -> 421.53204 | K41: =px*(1+ke)^(2030+mid-t_px0) -> 468.93883 | L41: =px*(1+ke)^(2031+mid-t_px0) -> 521.67714 | M41: =px*(1+ke)^(2032+mid-t_px0) -> 580.34655
A43: 情境 B（近四季成長收斂；基準）
A44: 項目 | B44: 單位 | C44: FY2024A | D44: FY2025A | E44: 1H26A | F44: 2H26E | G44: FY2026E | H44: FY2027E | I44: FY2028E | J44: FY2029E | K44: FY2030E | L44: FY2031E | M44: FY2032E | N44: 說明
A45: 淨利 | B45: US$B | C45: =PL!C118 -> 100.118 | D45: =PL!D118 -> 132.17 | E45: =PL!E118 -> 174.771 | F45: =PL!F118 -> 70.534182 | G45: =PL!G118 -> 245.30518 | H45: =PL!H118 -> 137.20056 | I45: =PL!I118 -> 141.27247 | J45: =PL!J118 -> 147.87117 | ... M45: =PL!M118 -> 165.32317
A46: 折舊 | B46: US$B | C46: =PL!C103 -> 15.311 | D46: =PL!D103 -> 21.136 | E46: =PL!E103 -> 13.586 | F46: =PL!F103 -> 21.862219 | G46: =PL!G103 -> 35.448219 | H46: =PL!H103 -> 66.844444 | I46: =PL!I103 -> 98.775109 | J46: =PL!J103 -> 130.94058 | ... M46: =PL!M103 -> 210.00027
A47: 股權報酬（非現金） | B47: US$B | C47: =PL!C127 -> 22.785 | D47: =PL!D127 -> 24.953 | E47: =PL!E127 -> 14.708 | F47: =PL!F127 -> 16.858366 | G47: =PL!G127 -> 31.566366 | H47: =PL!H127 -> 38.197499 | I47: =PL!I127 -> 44.379311 | J47: =PL!J127 -> 49.962161 | ... M47: =PL!M127 -> 63.088586
A48: 營運資金變動（流入＋） | B48: US$B | F48: =wc_2h -> 8.49 | G48: =F48 -> 8.49 | H48: =wc_k*(PL!H83-PL!G83) -> 1.269305 | I48: =wc_k*(PL!I83-PL!H83) -> 1.1462313 | J48: =wc_k*(PL!J83-PL!I83) -> 1.0351719 | K48: =wc_k*(PL!K83-PL!J83) -> 0.79920337 | L48: =wc_k*(PL!L83-PL!K83) -> 0.80945046 | M48: =wc_k*(PL!M83-PL!L83) -> 0.82524752 | N48: 2H26＝上一年度同期實際（C14）；之後＝營收增量 × wc_k
A49: 其他非現金調整（實績差額：權益證券利益迴轉、遞延稅等） | B49: US$B | C49: =Q!J45-C45-C46-C47 -> -12.915 | D49: =Q!K45-D45-D46-D47 -> -13.546 | E49: =Q!L45-E45-E46-E47 -> -118.206 | F49: 0 | G49: =E49+F49 -> -118.206 | H49: 0 | I49: 0 | J49: 0 | K49: 0 | L49: 0 | M49: 0
A50: 營運現金流 | B50: US$B | C50: =C45+C46+C47+C48+C49 -> 125.299 | D50: =D45+D46+D47+D48+D49 -> 164.713 | E50: =E45+E46+E47+E48+E49 -> 84.859 | F50: =F45+F46+F47+F48+F49 -> 117.74477 | G50: =G45+G46+G47+G48+G49 -> 202.60377 | H50: =H45+H46+H47+H48+H49 -> 243.51181 | I50: =I45+I46+I47+I48+I49 -> 285.57312 | J50: =J45+J46+J47+J48+J49 -> 329.80908 | ... M50: =M45+M46+M47+M48+M49 -> 439.23727
A51: 資本支出：AI（Thesis；首期含指引下限補足） | B51: US$B | F51: =Thesis!F52 -> 98.2828 | G51: =F51 -> 98.2828 | H51: =Thesis!H52 -> 190.01908 | I51: =Thesis!I52 -> 201.14439 | J51: =Thesis!J52 -> 180.85921 | K51: =Thesis!K52 -> 171.69309 | L51: =Thesis!L52 -> 177.21448 | M51: =Thesis!M52 -> 167.87684
A52: 資本支出：非 AI（Seg） | B52: US$B | F52: =Seg!F70 -> 21.1192 | G52: =F52 -> 21.1192 | H52: =Seg!H70 -> 48.028101 | I52: =Seg!I70 -> 56.861547 | J52: =Seg!J70 -> 64.504146 | K52: =Seg!K70 -> 69.631923 | L52: =Seg!L70 -> 75.178994 | M52: =Seg!M70 -> 81.179907
A53: 資本支出合計 | B53: US$B | C53: =Q!J46 -> 52.535 | D53: =Q!K46 -> 91.447 | E53: =Q!L46 -> 80.598 | F53: =F51+F52 -> 119.402 | G53: =E53+F53 -> 200 | H53: =H51+H52 -> 238.04718 | I53: =I51+I52 -> 258.00593 | J53: =J51+J52 -> 245.36336 | K53: =K51+K52 -> 241.32501 | L53: =L51+L52 -> 252.39348 | M53: =M51+M52 -> 249.05675
A54: 融資租賃本金 | B54: US$B | E54: =lease_1H -> 0.84 | F54: =lease_2H -> 0.206 | G54: =E54+F54 -> 1.046 | H54: =lease_27 -> 0.387 | I54: =lease_28 -> 0.377 | J54: =lease_29 -> 0.356 | K54: =lease_30 -> 0.285 | L54: =lease_31 -> 0.25 | M54: =lease_32 -> 0.25 | N54: 1H26：10-Q 附註 4 補充資訊 0.840 [Interested-party]；FY2024–25 未列（公司 FCF 定義不扣）
A55: 自由現金流（營運現金 − 資本支出 − 融資租賃本金） | B55: US$B | C55: =C50-C53-N(C54) -> 72.764 | D55: =D50-D53-N(D54) -> 73.266 | E55: =E50-E53-N(E54) -> 3.421 | F55: =F50-F53-N(F54) -> -1.8632328 | G55: =G50-G53-N(G54) -> 1.5577672 | H55: =H50-H53-N(H54) -> 5.0776278 | I55: =I50-I53-N(I54) -> 27.190183 | J55: =J50-J53-N(J54) -> 84.089723 | ... M55: =M50-M53-N(M54) -> 189.93052
A56: 普通股股利 | B56: US$B | C56: =Q!J50 -> 7.363 | D56: =Q!K50 -> 10.049 | E56: =Q!L50 -> 5.231 | F56: =dps/2*sh_out -> 5.3812 | G56: =E56+F56 -> 10.6122 | H56: =dps*(1+dps_g)^(2027-2026)*PL!F122 -> 11.503745 | I56: =dps*(1+dps_g)^(2028-2026)*PL!H122 -> 12.15129 | J56: =dps*(1+dps_g)^(2029-2026)*PL!I122 -> 12.840731 | K56: =dps*(1+dps_g)^(2030-2026)*PL!J122 -> 13.632852 | L56: =dps*(1+dps_g)^(2031-2026)*PL!K122 -> 14.416917 | M56: =dps*(1+dps_g)^(2032-2026)*PL!L122 -> 15.250704 | N56: 2H26＝0.22 × 2 × 流通股；之後每股 +5%／年 × 期初稀釋股數（避免與回購循環）
A57: 特別股股利 | B57: US$B | E57: =PL!E120 -> 0 | F57: =PL!F120 -> 0.535 | G57: =PL!G120 -> 0.535 | H57: =PL!H120 -> 1.203 | I57: =PL!I120 -> 1.203 | J57: =PL!J120 -> 0.602 | K57: =PL!K120 -> 0 | L57: =PL!L120 -> 0 | M57: =PL!M120 -> 0
A58: 自由現金流扣股利 | B58: US$B | C58: =C55-C56-N(C57) -> 65.401 | D58: =D55-D56-N(D57) -> 63.217 | E58: =E55-E56-N(E57) -> -1.81 | F58: =F55-F56-N(F57) -> -7.7794328 | G58: =G55-G56-N(G57) -> -9.5894328 | H58: =H55-H56-N(H57) -> -7.6291168 | I58: =I55-I56-N(I57) -> 13.835893 | J58: =J55-J56-N(J57) -> 70.646993 | ... M58: =M55-M56-N(M57) -> 174.67982
A59: 策略投資（Anthropic 出資；1H26 含 Wiz、Intersect 收購） | B59: US$B | E59: =anth_1H -> 55.44 | F59: =anth_2H -> 2.222 | G59: =E59+F59 -> 57.662 | H59: =anth_27 -> 4.444 | I59: =anth_28 -> 4.444 | J59: =anth_29 -> 4.444 | K59: =anth_30 -> 4.444 | L59: =anth_31 -> 0 | M59: =anth_32 -> 0 | N59: 1H26：非上市證券 22.1＋收購 33.7＋其他 − 出售（legacy_v0.2/company.json ytdActual.jv）[Derived]；投資活動，不在自由現金流
A60: 債務到期償還 | B60: US$B | E60: =mat_1H -> 5.253 | F60: =mat_2H -> 2 | G60: =E60+F60 -> 7.253 | H60: =mat_27 -> 1 | I60: =mat_28 -> 2.676 | J60: =mat_29 -> 1.764 | K60: =mat_30 -> 7.186 | L60: =mat_31 -> 5 | M60: =mat_32 -> 5 | N60: 1H26：10-Q 償還債務 [Interested-party]
A61: 已發行新債 | B61: US$B | E61: =newd_1H -> 56.226 | F61: =debt_new_2h -> 25 | G61: =E61+F61 -> 81.226 | H61: 0 | I61: 0 | J61: 0 | K61: 0 | L61: 0 | M61: 0 | N61: 1H26：發債淨額（10-Q）；2H26：2026-08 美元票據 25.0
A62: 股權發行（普通股＋強制轉換特別股，淨額） | B62: US$B | E62: =eq_1H -> 49.562 | F62: 0 | G62: =E62+F62 -> 49.562 | H62: 0 | I62: 0 | J62: 0 | K62: 0 | L62: 0 | M62: 0 | N62: C4：2026-06 普通股 30.5（承銷 20.5＋Berkshire 10.0）＋特別股 19.1 [Interested-party]；ATM 40B 與代扣稅不建模
A63: 期初現金（現金＋債權類有價證券） | B63: US$B | E63: =cash_ye25 -> 120.53 | F63: =E68 -> 155.411 | H63: =F68 -> 168.40957 | I63: =H68 -> 138.33345 | J63: =I68 -> 128.04634 | K63: =J68 -> 175.48234 | L63: =K68 -> 259.63425 | M63: =L68 -> 373.25581
A64: 其他（1H26 實績差額：代扣稅、capped call、匯率；預測期 0） | B64: US$B | E64: =cash_0-(E63+E55-E56-E57-E59-E60+E61+E62) -> -8.404 | F64: 0 | H64: 0 | I64: 0 | J64: 0 | K64: 0 | L64: 0 | M64: 0
A65: 回購前現金 | B65: US$B | E65: =E63+E55-E56-E57-E59-E60+E61+E62+E64 -> 155.411 | F65: =F63+F55-F56-F57-F59-F60+F61+F62+F64 -> 168.40957 | H65: =H63+H55-H56-H57-H59-H60+H61+H62+H64 -> 155.33645 | I65: =I63+I55-I56-I57-I59-I60+I61+I62+I64 -> 145.04934 | J65: =J63+J55-J56-J57-J59-J60+J61+J62+J64 -> 192.48534 | K65: =K63+K55-K56-K57-K59-K60+K61+K62+K64 -> 276.63725 | L65: =L63+L55-L56-L57-L59-L60+L61+L62+L64 -> 390.25881 | M65: =M63+M55-M56-M57-M59-M60+M61+M62+M64 -> 542.93563
A66: 回購 | B66: US$B | E66: =Q!L49 -> 0 | F66: 0 | G66: =E66+F66 -> 0 | H66: =MAX(0,MIN(bb_t,H65-min_cash)) -> 17.003 | I66: =MAX(0,MIN(bb_t,I65-min_cash)) -> 17.003 | J66: =MAX(0,MIN(bb_t,J65-min_cash)) -> 17.003 | K66: =MAX(0,MIN(bb_t,K65-min_cash)) -> 17.003 | L66: =MAX(0,MIN(bb_t,L65-min_cash)) -> 17.003 | M66: =MAX(0,MIN(bb_t,M65-min_cash)) -> 17.003 | N66: 2H26＝0（暫停，C4）；之後＝MIN(回購目標, 回購前現金 − 最低現金)
A67: 新增舉債（現金低於最低現金時） | B67: US$B | E67: 0 | F67: =MAX(0,min_cash-(F65-F66)) -> 0 | G67: =E67+F67 -> 0 | H67: =MAX(0,min_cash-(H65-H66)) -> 0 | I67: =MAX(0,min_cash-(I65-I66)) -> 0 | J67: =MAX(0,min_cash-(J65-J66)) -> 0 | K67: =MAX(0,min_cash-(K65-K66)) -> 0 | L67: =MAX(0,min_cash-(L65-L66)) -> 0 | M67: =MAX(0,min_cash-(M65-M66)) -> 0
A68: 期末現金（現金＋債權類有價證券） | B68: US$B | E68: =E65-E66+E67 -> 155.411 | F68: =F65-F66+F67 -> 168.40957 | H68: =H65-H66+H67 -> 138.33345 | I68: =I65-I66+I67 -> 128.04634 | J68: =J65-J66+J67 -> 175.48234 | K68: =K65-K66+K67 -> 259.63425 | L68: =L65-L66+L67 -> 373.25581 | M68: =M65-M66+M67 -> 525.93263
A69: 檢查：1H26 期末現金 − 10-Q（應為 0） | B69: US$B | E69: =E68-cash_0 -> 0
A70: 期初債務 | B70: US$B | E70: =debt_ye25 -> 49.085 | F70: =E71 -> 101.085 | H70: =F71 -> 124.085 | I70: =H71 -> 123.085 | J70: =I71 -> 120.409 | K70: =J71 -> 118.645 | L70: =K71 -> 111.459 | M70: =L71 -> 106.459 | N70: 2025-12-31 面額 49.085（事實總帳 debt.face.fy2025）
A71: 期末債務 | B71: US$B | E71: =debt_0 -> 101.085 | F71: =F70-F60+F61+F67 -> 124.085 | H71: =H70-H60+H61+H67 -> 123.085 | I71: =I70-I60+I61+I67 -> 120.409 | J71: =J70-J60+J61+J67 -> 118.645 | K71: =K70-K60+K61+K67 -> 111.459 | L71: =L70-L60+L61+L67 -> 106.459 | M71: =M70-M60+M61+M67 -> 101.459 | N71: 1H26＝10-Q 面額（含匯率變動）
A72: 淨現金（現金 − 債務） | B72: US$B | E72: =E68-E71 -> 54.326 | F72: =F68-F71 -> 44.324567 | H72: =H68-H71 -> 15.24845 | I72: =I68-I71 -> 7.6373439 | J72: =J68-J71 -> 56.837337 | K72: =K68-K71 -> 148.17525 | L72: =L68-L71 -> 266.79681 | M72: =M68-M71 -> 424.47363
A73: 回購均價（現價 × (1＋ke)^年數） | B73: US$ | F73: =px -> 316.8 | H73: =px*(1+ke)^(2027+mid-t_px0) -> 340.61156 | I73: =px*(1+ke)^(2028+mid-t_px0) -> 378.91778 | J73: =px*(1+ke)^(2029+mid-t_px0) -> 421.53204 | K73: =px*(1+ke)^(2030+mid-t_px0) -> 468.93883 | L73: =px*(1+ke)^(2031+mid-t_px0) -> 521.67714 | M73: =px*(1+ke)^(2032+mid-t_px0) -> 580.34655
A75: 情境 C（查詢被 AI 助理分流、每次查詢變現下降）
A76: 項目 | B76: 單位 | C76: FY2024A | D76: FY2025A | E76: 1H26A | F76: 2H26E | G76: FY2026E | H76: FY2027E | I76: FY2028E | J76: FY2029E | K76: FY2030E | L76: FY2031E | M76: FY2032E | N76: 說明
A77: 淨利 | B77: US$B | C77: =PL!C177 -> 100.118 | D77: =PL!D177 -> 132.17 | E77: =PL!E177 -> 174.771 | F77: =PL!F177 -> 70.534182 | G77: =PL!G177 -> 245.30518 | H77: =PL!H177 -> 125.15701 | I77: =PL!I177 -> 114.37617 | J77: =PL!J177 -> 103.72746 | ... M77: =PL!M177 -> 88.889197
A78: 折舊 | B78: US$B | C78: =PL!C162 -> 15.311 | D78: =PL!D162 -> 21.136 | E78: =PL!E162 -> 13.586 | F78: =PL!F162 -> 21.862219 | G78: =PL!G162 -> 35.448219 | H78: =PL!H162 -> 66.811049 | I78: =PL!I162 -> 98.567732 | J78: =PL!J162 -> 130.39192 | ... M78: =PL!M162 -> 207.48298
A79: 股權報酬（非現金） | B79: US$B | C79: =PL!C186 -> 22.785 | D79: =PL!D186 -> 24.953 | E79: =PL!E186 -> 14.708 | F79: =PL!F186 -> 16.858366 | G79: =PL!G186 -> 31.566366 | H79: =PL!H186 -> 36.792702 | I79: =PL!I186 -> 41.274832 | J79: =PL!J186 -> 44.918921 | ... M79: =PL!M186 -> 54.766488
A80: 營運資金變動（流入＋） | B80: US$B | F80: =wc_2h -> 8.49 | G80: =F80 -> 8.49 | H80: =wc_k*(PL!H142-PL!G142) -> 1.0088275 | I80: =wc_k*(PL!I142-PL!H142) -> 0.83107652 | J80: =wc_k*(PL!J142-PL!I142) -> 0.67568675 | K80: =wc_k*(PL!K142-PL!J142) -> 0.41137568 | L80: =wc_k*(PL!L142-PL!K142) -> 0.70361485 | M80: =wc_k*(PL!M142-PL!L142) -> 0.71094506 | N80: 2H26＝上一年度同期實際（C14）；之後＝營收增量 × wc_k
A81: 其他非現金調整（實績差額：權益證券利益迴轉、遞延稅等） | B81: US$B | C81: =Q!J45-C77-C78-C79 -> -12.915 | D81: =Q!K45-D77-D78-D79 -> -13.546 | E81: =Q!L45-E77-E78-E79 -> -118.206 | F81: 0 | G81: =E81+F81 -> -118.206 | H81: 0 | I81: 0 | J81: 0 | K81: 0 | L81: 0 | M81: 0
A82: 營運現金流 | B82: US$B | C82: =C77+C78+C79+C80+C81 -> 125.299 | D82: =D77+D78+D79+D80+D81 -> 164.713 | E82: =E77+E78+E79+E80+E81 -> 84.859 | F82: =F77+F78+F79+F80+F81 -> 117.74477 | G82: =G77+G78+G79+G80+G81 -> 202.60377 | H82: =H77+H78+H79+H80+H81 -> 229.76958 | I82: =I77+I78+I79+I80+I81 -> 255.04981 | J82: =J77+J78+J79+J80+J81 -> 279.71399 | ... M82: =M77+M78+M79+M80+M81 -> 351.84961
A83: 資本支出：AI（Thesis；首期含指引下限補足） | B83: US$B | F83: =Thesis!F52 -> 98.2828 | G83: =F83 -> 98.2828 | H83: =Thesis!H52 -> 190.01908 | I83: =Thesis!I52 -> 201.14439 | J83: =Thesis!J52 -> 180.85921 | K83: =Thesis!K52 -> 171.69309 | L83: =Thesis!L52 -> 177.21448 | M83: =Thesis!M52 -> 167.87684
A84: 資本支出：非 AI（Seg） | B84: US$B | F84: =Seg!F106 -> 21.1192 | G84: =F84 -> 21.1192 | H84: =Seg!H106 -> 46.692318 | I84: =Seg!I106 -> 53.909586 | J84: =Seg!J106 -> 59.708671 | K84: =Seg!K106 -> 62.847588 | L84: =Seg!L106 -> 67.851913 | M84: =Seg!M106 -> 73.266659
A85: 資本支出合計 | B85: US$B | C85: =Q!J46 -> 52.535 | D85: =Q!K46 -> 91.447 | E85: =Q!L46 -> 80.598 | F85: =F83+F84 -> 119.402 | G85: =E85+F85 -> 200 | H85: =H83+H84 -> 236.7114 | I85: =I83+I84 -> 255.05397 | J85: =J83+J84 -> 240.56788 | K85: =K83+K84 -> 234.54068 | L85: =L83+L84 -> 245.0664 | M85: =M83+M84 -> 241.1435
A86: 融資租賃本金 | B86: US$B | E86: =lease_1H -> 0.84 | F86: =lease_2H -> 0.206 | G86: =E86+F86 -> 1.046 | H86: =lease_27 -> 0.387 | I86: =lease_28 -> 0.377 | J86: =lease_29 -> 0.356 | K86: =lease_30 -> 0.285 | L86: =lease_31 -> 0.25 | M86: =lease_32 -> 0.25 | N86: 1H26：10-Q 附註 4 補充資訊 0.840 [Interested-party]；FY2024–25 未列（公司 FCF 定義不扣）
A87: 自由現金流（營運現金 − 資本支出 − 融資租賃本金） | B87: US$B | C87: =C82-C85-N(C86) -> 72.764 | D87: =D82-D85-N(D86) -> 73.266 | E87: =E82-E85-N(E86) -> 3.421 | F87: =F82-F85-N(F86) -> -1.8632328 | G87: =G82-G85-N(G86) -> 1.5577672 | H87: =H82-H85-N(H86) -> -7.3288165 | I87: =I82-I85-N(I86) -> -0.38116385 | J87: =J82-J85-N(J86) -> 38.790104 | ... M87: =M82-M85-N(M86) -> 110.4561
A88: 普通股股利 | B88: US$B | C88: =Q!J50 -> 7.363 | D88: =Q!K50 -> 10.049 | E88: =Q!L50 -> 5.231 | F88: =dps/2*sh_out -> 5.3812 | G88: =E88+F88 -> 10.6122 | H88: =dps*(1+dps_g)^(2027-2026)*PL!F181 -> 11.503745 | I88: =dps*(1+dps_g)^(2028-2026)*PL!H181 -> 12.15129 | J88: =dps*(1+dps_g)^(2029-2026)*PL!I181 -> 12.840731 | K88: =dps*(1+dps_g)^(2030-2026)*PL!J181 -> 13.632852 | L88: =dps*(1+dps_g)^(2031-2026)*PL!K181 -> 14.416917 | M88: =dps*(1+dps_g)^(2032-2026)*PL!L181 -> 15.250704 | N88: 2H26＝0.22 × 2 × 流通股；之後每股 +5%／年 × 期初稀釋股數（避免與回購循環）
A89: 特別股股利 | B89: US$B | E89: =PL!E179 -> 0 | F89: =PL!F179 -> 0.535 | G89: =PL!G179 -> 0.535 | H89: =PL!H179 -> 1.203 | I89: =PL!I179 -> 1.203 | J89: =PL!J179 -> 0.602 | K89: =PL!K179 -> 0 | L89: =PL!L179 -> 0 | M89: =PL!M179 -> 0
A90: 自由現金流扣股利 | B90: US$B | C90: =C87-C88-N(C89) -> 65.401 | D90: =D87-D88-N(D89) -> 63.217 | E90: =E87-E88-N(E89) -> -1.81 | F90: =F87-F88-N(F89) -> -7.7794328 | G90: =G87-G88-N(G89) -> -9.5894328 | H90: =H87-H88-N(H89) -> -20.035561 | I90: =I87-I88-N(I89) -> -13.735454 | J90: =J87-J88-N(J89) -> 25.347374 | ... M90: =M87-M88-N(M89) -> 95.2054
A91: 策略投資（Anthropic 出資；1H26 含 Wiz、Intersect 收購） | B91: US$B | E91: =anth_1H -> 55.44 | F91: =anth_2H -> 2.222 | G91: =E91+F91 -> 57.662 | H91: =anth_27 -> 4.444 | I91: =anth_28 -> 4.444 | J91: =anth_29 -> 4.444 | K91: =anth_30 -> 4.444 | L91: =anth_31 -> 0 | M91: =anth_32 -> 0 | N91: 1H26：非上市證券 22.1＋收購 33.7＋其他 − 出售（legacy_v0.2/company.json ytdActual.jv）[Derived]；投資活動，不在自由現金流
A92: 債務到期償還 | B92: US$B | E92: =mat_1H -> 5.253 | F92: =mat_2H -> 2 | G92: =E92+F92 -> 7.253 | H92: =mat_27 -> 1 | I92: =mat_28 -> 2.676 | J92: =mat_29 -> 1.764 | K92: =mat_30 -> 7.186 | L92: =mat_31 -> 5 | M92: =mat_32 -> 5 | N92: 1H26：10-Q 償還債務 [Interested-party]
A93: 已發行新債 | B93: US$B | E93: =newd_1H -> 56.226 | F93: =debt_new_2h -> 25 | G93: =E93+F93 -> 81.226 | H93: 0 | I93: 0 | J93: 0 | K93: 0 | L93: 0 | M93: 0 | N93: 1H26：發債淨額（10-Q）；2H26：2026-08 美元票據 25.0
A94: 股權發行（普通股＋強制轉換特別股，淨額） | B94: US$B | E94: =eq_1H -> 49.562 | F94: 0 | G94: =E94+F94 -> 49.562 | H94: 0 | I94: 0 | J94: 0 | K94: 0 | L94: 0 | M94: 0 | N94: C4：2026-06 普通股 30.5（承銷 20.5＋Berkshire 10.0）＋特別股 19.1 [Interested-party]；ATM 40B 與代扣稅不建模
A95: 期初現金（現金＋債權類有價證券） | B95: US$B | E95: =cash_ye25 -> 120.53 | F95: =E100 -> 155.411 | H95: =F100 -> 168.40957 | I95: =H100 -> 125.92701 | J95: =I100 -> 88.068553 | K95: =J100 -> 90.204926 | L95: =K100 -> 109.43186 | M95: =L100 -> 151.30874
A96: 其他（1H26 實績差額：代扣稅、capped call、匯率；預測期 0） | B96: US$B | E96: =cash_0-(E95+E87-E88-E89-E91-E92+E93+E94) -> -8.404 | F96: 0 | H96: 0 | I96: 0 | J96: 0 | K96: 0 | L96: 0 | M96: 0
A97: 回購前現金 | B97: US$B | E97: =E95+E87-E88-E89-E91-E92+E93+E94+E96 -> 155.411 | F97: =F95+F87-F88-F89-F91-F92+F93+F94+F96 -> 168.40957 | H97: =H95+H87-H88-H89-H91-H92+H93+H94+H96 -> 142.93001 | I97: =I95+I87-I88-I89-I91-I92+I93+I94+I96 -> 105.07155 | J97: =J95+J87-J88-J89-J91-J92+J93+J94+J96 -> 107.20793 | K97: =K95+K87-K88-K89-K91-K92+K93+K94+K96 -> 126.43486 | L97: =L95+L87-L88-L89-L91-L92+L93+L94+L96 -> 168.31174 | M97: =M95+M87-M88-M89-M91-M92+M93+M94+M96 -> 241.51414
A98: 回購 | B98: US$B | E98: =Q!L49 -> 0 | F98: 0 | G98: =E98+F98 -> 0 | H98: =MAX(0,MIN(bb_t,H97-min_cash)) -> 17.003 | I98: =MAX(0,MIN(bb_t,I97-min_cash)) -> 17.003 | J98: =MAX(0,MIN(bb_t,J97-min_cash)) -> 17.003 | K98: =MAX(0,MIN(bb_t,K97-min_cash)) -> 17.003 | L98: =MAX(0,MIN(bb_t,L97-min_cash)) -> 17.003 | M98: =MAX(0,MIN(bb_t,M97-min_cash)) -> 17.003 | N98: 2H26＝0（暫停，C4）；之後＝MIN(回購目標, 回購前現金 − 最低現金)
A99: 新增舉債（現金低於最低現金時） | B99: US$B | E99: 0 | F99: =MAX(0,min_cash-(F97-F98)) -> 0 | G99: =E99+F99 -> 0 | H99: =MAX(0,min_cash-(H97-H98)) -> 0 | I99: =MAX(0,min_cash-(I97-I98)) -> 0 | J99: =MAX(0,min_cash-(J97-J98)) -> 0 | K99: =MAX(0,min_cash-(K97-K98)) -> 0 | L99: =MAX(0,min_cash-(L97-L98)) -> 0 | M99: =MAX(0,min_cash-(M97-M98)) -> 0
A100: 期末現金（現金＋債權類有價證券） | B100: US$B | E100: =E97-E98+E99 -> 155.411 | F100: =F97-F98+F99 -> 168.40957 | H100: =H97-H98+H99 -> 125.92701 | I100: =I97-I98+I99 -> 88.068553 | J100: =J97-J98+J99 -> 90.204926 | K100: =K97-K98+K99 -> 109.43186 | L100: =L97-L98+L99 -> 151.30874 | M100: =M97-M98+M99 -> 224.51114
A101: 檢查：1H26 期末現金 − 10-Q（應為 0） | B101: US$B | E101: =E100-cash_0 -> 0
A102: 期初債務 | B102: US$B | E102: =debt_ye25 -> 49.085 | F102: =E103 -> 101.085 | H102: =F103 -> 124.085 | I102: =H103 -> 123.085 | J102: =I103 -> 120.409 | K102: =J103 -> 118.645 | L102: =K103 -> 111.459 | M102: =L103 -> 106.459 | N102: 2025-12-31 面額 49.085（事實總帳 debt.face.fy2025）
A103: 期末債務 | B103: US$B | E103: =debt_0 -> 101.085 | F103: =F102-F92+F93+F99 -> 124.085 | H103: =H102-H92+H93+H99 -> 123.085 | I103: =I102-I92+I93+I99 -> 120.409 | J103: =J102-J92+J93+J99 -> 118.645 | K103: =K102-K92+K93+K99 -> 111.459 | L103: =L102-L92+L93+L99 -> 106.459 | M103: =M102-M92+M93+M99 -> 101.459 | N103: 1H26＝10-Q 面額（含匯率變動）
...

Sheet Val
A1: Val — 目標價（約 12 個月後，2027-10-27）＝DCF 50%＋分部加總（SOTP）50%；情境權重 A 25%／B 50%／C 25%（In 頁，黃底＝判斷題）。分部加總即本模型的 Comparable（在分部層做）。主值＝自用 AI 讀法 2（In 頁 internal_ai_reading），讀法 1 並列
A2: DCF：無槓桿自由現金流（NOPAT＋折舊 − 資本支出＋營運資金；股權報酬視為現金成本、不加回）以 WACC 折現到評價日 2026-06-30（期中慣例），終值＝NOPAT(FY2033) ×(1 − g ÷ RONIC) ÷ (WACC − g)，RONIC＝WACC；以 ke 推到目標時點並扣期間股利。SOTP：目標時點 NTM EBITDA（股權報酬加回，與同業倍數同口徑）× 同業 NTM EV/EBITDA；Cloud AI 用自身 DCF（F3）
A4: 0.3 結論
A5: 項目 | B5: 數值 | C5: 對照 | D5: 對照 | E5: 說明
A6: DCF 目標價（情境加權） | B6: =tp_wA*B102+tp_wB*C102+tp_wC*D102 -> 179.63304
A7: Comparable 目標價（市場主流同業法） | B7: =tp_wA*B145+tp_wB*C145+tp_wC*D145 -> 318.24061 | E7: ＝分部加總（SOTP）情境加權；各分部用各自同業倍數，Cloud AI 用自身 DCF
A8: 目標價（DCF 與 Comparable 加權） | B8: =w_dcf*B6+(1-w_dcf)*B7 -> 248.93682 | E8: ="DCF 權重 "&TEXT(w_dcf,"0%")&"、分部加總 "&TEXT(1-w_dcf,"0%")&"；自用 AI 讀法 "&internal_ai_reading -> DCF 權重 50%、分部加總 50%；自用 AI 讀法 2
A9: 現價（2026-10-26 收盤） | B9: =px -> 316.8 | E9: StockAnalysis 歷史股價（In 頁 px）
A10: 市場共識目標價 | B10: =cons_tp -> 429.12 | E10: StockAnalysis 61 位分析師平均（2026-10-26）；只作對照
A11: 上檔空間：加權目標價 | B11: =B8/px-1 -> -0.21421457
A12: 上檔空間：Comparable 目標價 | B12: =B7/px-1 -> 0.0045473761
A13: 上檔空間級距 | B13: =IF(B11>0.5,"大於 50%",IF(B11>0.25,"25%–50%",IF(B11>=0,"0%–25%",IF(B11>=-0.25,"0%～−25%",IF(B11>=-0.5,"−25%～−50%","小於 −50%"))))) -> 0%～−25% | E13: 以「上檔空間：加權目標價」分六級（Andy 2026-10-25 14:00）
A14: 投資建議 | B14: =IF(B11>=0.5,"強力買進",IF(B11>=0.25,"買進",IF(B11>-0.25,"中立",IF(B11>-0.5,"放空","強力放空")))) -> 中立 | E14: 五級固定規則：≥ +50% 強力買進、+25%～+50% 買進、−25%～+25% 中立、−50%～−25% 放空、≤ −50% 強力放空
A15: 價格帶（DCF 不如預期～順利） | B15: =D102 -> 139.44745 | C15: =B102 -> 209.65628 | E15: B＝C 情境 DCF、C＝A 情境 DCF（皆推到 12 個月後）
A16: 悲觀情境價（C 情境 DCF） | B16: =D102 -> 139.44745 | E16: 地圖「悲觀情境空間」＝本列 ÷ 現價 − 1
A17: 情境目標價（A／B／C；DCF 與分部加總加權） | B17: =w_dcf*B102+(1-w_dcf)*B145 -> 273.02102 | C17: =w_dcf*C102+(1-w_dcf)*C145 -> 253.15499 | D17: =w_dcf*D102+(1-w_dcf)*D145 -> 216.41628
A18: 情境上檔空間（A／B／C） | B18: =B17/px-1 -> -0.13819122 | C18: =C17/px-1 -> -0.20089964 | D18: =D17/px-1 -> -0.31686779
A19: DCF 終值占 EV（A／B／C） | B19: =B94 -> 0.73190605 | C19: =C94 -> 0.74129404 | D19: =D94 -> 0.7695741
A20: 讀法 2（自用 AI 價值中性）：目標價／上檔空間／投資建議 | B20: =w_dcf*(tp_wA*B101+tp_wB*C101+tp_wC*D101)+(1-w_dcf)*(tp_wA*B144+tp_wB*C144+tp_wC*D144) -> 248.93682 | C20: =B20/px-1 -> -0.21421457 | D20: =IF(C20>=0.5,"強力買進",IF(C20>=0.25,"買進",IF(C20>-0.25,"中立",IF(C20>-0.5,"放空","強力放空")))) -> 中立 | E20: 活公式（修正一 F1；主值）
A21: 讀法 1（自用 AI 只計成本）：目標價／上檔空間／投資建議 | B21: =w_dcf*(tp_wA*B100+tp_wB*C100+tp_wC*D100)+(1-w_dcf)*(tp_wA*B143+tp_wB*C143+tp_wC*D143) -> 180.17862 | C21: =B21/px-1 -> -0.43125437 | D21: =IF(C21>=0.5,"強力買進",IF(C21>=0.25,"買進",IF(C21>-0.25,"中立",IF(C21>-0.5,"放空","強力放空")))) -> 放空 | E21: 活公式（敏感度；v0.2.2 與 v0.3 修正前的主值）
A22: 讀法 1／2 的 DCF 目標價（情境加權） | B22: =tp_wA*B100+tp_wB*C100+tp_wC*D100 -> 94.552232 | C22: =tp_wA*B101+tp_wB*C101+tp_wC*D101 -> 179.63304
A23: 讀法 1／2 的分部加總目標價（情境加權） | B23: =tp_wA*B143+tp_wB*C143+tp_wC*D143 -> 265.805 | C23: =tp_wA*B144+tp_wB*C144+tp_wC*D144 -> 318.24061
A24: 目標價方法 | B24: DCF（無槓桿 FCF、WACC、RONIC＝WACC）50%＋分部加總（各分部同業 NTM EV/EBITDA、Cloud AI 自身 DCF）50%；情境 25／50／25；自用 AI 讀法 2
A25: 檢查：情境權重合計（應為 1） | B25: =ROUND(tp_wA+tp_wB+tp_wC,6) -> 1
A26: 檢查：主值目標價 − 所選讀法的目標價（應為 0） | B26: =B8-IF(internal_ai_reading=2,B20,B21) -> 0
A32: 0.0 折現率（CAPM；修正一 F4：Blume β、約 10 年期 kd、負債含融資租賃）
A33: 項目 | B33: 數值 | E33: 說明
A34: 股權市值 E＝現價 × 流通股 | B34: =px*sh_out -> 3874.464
A35: 負債 D（債務面額＋融資租賃） | B35: =debt_0+fin_lease -> 103.675
A36: 股東權益成本 ke＝rf＋β × ERP | B36: =rf+beta*erp -> 0.11246307 | E36: ="β（Blume 調整、兩來源中位數）"&TEXT(beta,"0.000") -> β（Blume 調整、兩來源中位數）1.193
A37: 稅後債務成本（約 10 年期） | B37: =kd*(1-tax_w) -> 0.0489216
A38: WACC（＋wacc_adj，Sens 用） | B38: =(B34*ke+B35*B37)/(B34+B35)+wacc_adj -> 0.11080711 | E38: 修正前 11.56%（原始 β 1.288、kd 6.527%）
A39: 永續期新投資報酬 RONIC＝WACC＋ronic_sp | B39: =wacc+ronic_sp -> 0.11080711 | E39: 修正一 F5：RONIC＝WACC（Sens：＋5pt）
A41: 0.1 DCF（無槓桿自由現金流；三情境各一區塊；欄 F＝2H26、H–M＝FY2027–FY2032；不含影子效益的「財報口徑」與影子效益分開列）
A42: 情境 A（AI 搜尋擴大變現）
A43: 項目 | E43: 說明 | F43: 2H26E | H43: FY2027E | I43: FY2028E | J43: FY2029E | K43: FY2030E | L43: FY2031E | M43: FY2032E
A44: 營業利益（財報口徑 EBIT） | F44: =PL!F46 -> 84.249893 | H44: =PL!H46 -> 171.88276 | I44: =PL!I46 -> 187.20358 | J44: =PL!J46 -> 206.45473 | K44: =PL!K46 -> 224.78005 | L44: =PL!L46 -> 232.19243 | M44: =PL!M46 -> 235.83899
A45: NOPAT＝(EBIT＋sbc_add × 股權報酬) ×(1 − 稅率) | F45: =(F44+sbc_add*PL!F68)*(1-tax) -> 70.095911 | H45: =(H44+sbc_add*PL!H68)*(1-tax) -> 143.00646 | I45: =(I44+sbc_add*PL!I68)*(1-tax) -> 155.75338 | J45: =(J44+sbc_add*PL!J68)*(1-tax) -> 171.77034 | K45: =(K44+sbc_add*PL!K68)*(1-tax) -> 187.017 | L45: =(L44+sbc_add*PL!L68)*(1-tax) -> 193.1841 | M45: =(M44+sbc_add*PL!M68)*(1-tax) -> 196.21804
A46: ＋折舊 | F46: =PL!F44 -> 21.862219 | H46: =PL!H44 -> 66.861566 | I46: =PL!I44 -> 98.882404 | J46: =PL!J44 -> 131.22897 | K46: =PL!K44 -> 159.16528 | L46: =PL!L44 -> 183.11159 | M46: =PL!M44 -> 211.37338
A47: − 資本支出 | F47: =CF!F21 -> 119.402 | H47: =CF!H21 -> 238.73206 | I47: =CF!I21 -> 259.55826 | J47: =CF!J21 -> 247.95039 | K47: =CF!K21 -> 245.08063 | L47: =CF!L21 -> 256.44954 | M47: =CF!M21 -> 253.4373
A48: ＋營運資金變動 | F48: =CF!F16 -> 8.49 | H48: =CF!H16 -> 1.402855 | I48: =CF!I16 -> 1.3153845 | J48: =CF!J16 -> 1.23694 | K48: =CF!K16 -> 1.0270767 | L48: =CF!L16 -> 0.86803803 | M48: =CF!M16 -> 0.8885221
A49: 無槓桿自由現金流（財報口徑） | E49: 股權報酬視為現金成本（修正一 F2） | F49: =F45+F46-F47+F48 -> -18.953871 | H49: =H45+H46-H47+H48 -> -27.461175 | I49: =I45+I46-I47+I48 -> -3.6070925 | J49: =J45+J46-J47+J48 -> 56.285858 | K49: =K45+K46-K47+K48 -> 102.12873 | L49: =L45+L46-L47+L48 -> 120.71418 | M49: =M45+M46-M47+M48 -> 155.04264
A50: 自用 AI 影子效益（稅後；讀法 2 加入） | F50: =PL!F48*(1-tax) -> 3.2966663 | H50: =PL!H48*(1-tax) -> 27.184329 | I50: =PL!I48*(1-tax) -> 55.990656 | J50: =PL!J48*(1-tax) -> 82.352679 | K50: =PL!K48*(1-tax) -> 102.3774 | L50: =PL!L48*(1-tax) -> 116.34207 | M50: =PL!M48*(1-tax) -> 124.38837
A51: 折現年數（評價日 2026-06-30 起，期中） | F51: =t_2h -> 0.25 | H51: =2027-2026 -> 1 | I51: =2028-2026 -> 2 | J51: =2029-2026 -> 3 | K51: =2030-2026 -> 4 | L51: =2031-2026 -> 5 | M51: =2032-2026 -> 6
A52: 折現因子 1 ÷ (1＋WACC)^年數 | F52: =1/(1+wacc)^F51 -> 0.97407038 | H52: =1/(1+wacc)^H51 -> 0.90024631 | I52: =1/(1+wacc)^I51 -> 0.81044342 | J52: =1/(1+wacc)^J51 -> 0.72959869 | K52: =1/(1+wacc)^K51 -> 0.65681853 | L52: =1/(1+wacc)^L51 -> 0.59129846 | M52: =1/(1+wacc)^M51 -> 0.53231426
A53: 現值（財報口徑） | F53: =F49*F52 -> -18.462404 | H53: =H49*H52 -> -24.721822 | I53: =I49*I52 -> -2.9233443 | J53: =J49*J52 -> 41.066089 | K53: =K49*K52 -> 67.080045 | L53: =L49*L52 -> 71.378111 | M53: =M49*M52 -> 82.531405
A54: 現值（影子效益） | F54: =F50*F52 -> 3.211185 | H54: =H50*H52 -> 24.472592 | I54: =I50*I52 -> 45.377259 | J54: =J50*J52 -> 60.084407 | K54: =K50*K52 -> 67.243372 | L54: =L50*L52 -> 68.792885 | M54: =M50*M52 -> 66.213703
A56: 情境 B（近四季成長收斂；基準）
A57: 項目 | E57: 說明 | F57: 2H26E | H57: FY2027E | I57: FY2028E | J57: FY2029E | K57: FY2030E | L57: FY2031E | M57: FY2032E
A58: 營業利益（財報口徑 EBIT） | F58: =PL!F105 -> 84.249893 | H58: =PL!H105 -> 164.46104 | I58: =PL!I105 -> 170.45005 | J58: =PL!J105 -> 178.64364 | K58: =PL!K105 -> 184.56414 | L58: =PL!L105 -> 189.09621 | M58: =PL!M105 -> 189.63204
A59: NOPAT＝(EBIT＋sbc_add × 股權報酬) ×(1 − 稅率) | F59: =(F58+sbc_add*PL!F127)*(1-tax) -> 70.095911 | H59: =(H58+sbc_add*PL!H127)*(1-tax) -> 136.83158 | I59: =(I58+sbc_add*PL!I127)*(1-tax) -> 141.81444 | J59: =(J58+sbc_add*PL!J127)*(1-tax) -> 148.63151 | K59: =(K58+sbc_add*PL!K127)*(1-tax) -> 153.55736 | L59: =(L58+sbc_add*PL!L127)*(1-tax) -> 157.32805 | M59: =(M58+sbc_add*PL!M127)*(1-tax) -> 157.77386
A60: ＋折舊 | F60: =PL!F103 -> 21.862219 | H60: =PL!H103 -> 66.844444 | I60: =PL!I103 -> 98.775109 | J60: =PL!J103 -> 130.94058 | K60: =PL!K103 -> 158.58897 | L60: =PL!L103 -> 182.1522 | M60: =PL!M103 -> 210.00027
A61: − 資本支出 | F61: =CF!F53 -> 119.402 | H61: =CF!H53 -> 238.04718 | I61: =CF!I53 -> 258.00593 | J61: =CF!J53 -> 245.36336 | K61: =CF!K53 -> 241.32501 | L61: =CF!L53 -> 252.39348 | M61: =CF!M53 -> 249.05675
A62: ＋營運資金變動 | F62: =CF!F48 -> 8.49 | H62: =CF!H48 -> 1.269305 | I62: =CF!I48 -> 1.1462313 | J62: =CF!J48 -> 1.0351719 | K62: =CF!K48 -> 0.79920337 | L62: =CF!L48 -> 0.80945046 | M62: =CF!M48 -> 0.82524752
A63: 無槓桿自由現金流（財報口徑） | E63: 股權報酬視為現金成本（修正一 F2） | F63: =F59+F60-F61+F62 -> -18.953871 | H63: =H59+H60-H61+H62 -> -33.10185 | I63: =I59+I60-I61+I62 -> -16.270155 | J63: =J59+J60-J61+J62 -> 35.243903 | K63: =K59+K60-K61+K62 -> 71.620523 | L63: =L59+L60-L61+L62 -> 87.896223 | M63: =M59+M60-M61+M62 -> 119.54263
A64: 自用 AI 影子效益（稅後；讀法 2 加入） | F64: =PL!F107*(1-tax) -> 3.2966663 | H64: =PL!H107*(1-tax) -> 27.184329 | I64: =PL!I107*(1-tax) -> 55.990656 | J64: =PL!J107*(1-tax) -> 82.352679 | K64: =PL!K107*(1-tax) -> 102.3774 | L64: =PL!L107*(1-tax) -> 116.34207 | M64: =PL!M107*(1-tax) -> 124.38837
A65: 折現年數（評價日 2026-06-30 起，期中） | F65: =t_2h -> 0.25 | H65: =2027-2026 -> 1 | I65: =2028-2026 -> 2 | J65: =2029-2026 -> 3 | K65: =2030-2026 -> 4 | L65: =2031-2026 -> 5 | M65: =2032-2026 -> 6
A66: 折現因子 1 ÷ (1＋WACC)^年數 | F66: =1/(1+wacc)^F65 -> 0.97407038 | H66: =1/(1+wacc)^H65 -> 0.90024631 | I66: =1/(1+wacc)^I65 -> 0.81044342 | J66: =1/(1+wacc)^J65 -> 0.72959869 | K66: =1/(1+wacc)^K65 -> 0.65681853 | L66: =1/(1+wacc)^L65 -> 0.59129846 | M66: =1/(1+wacc)^M65 -> 0.53231426
A67: 現值（財報口徑） | F67: =F63*F66 -> -18.462404 | H67: =H63*H66 -> -29.799818 | I67: =I63*I66 -> -13.18604 | J67: =J63*J66 -> 25.713906 | K67: =K63*K66 -> 47.041687 | L67: =L63*L66 -> 51.972901 | M67: =M63*M66 -> 63.634244
A68: 現值（影子效益） | F68: =F64*F66 -> 3.211185 | H68: =H64*H66 -> 24.472592 | I68: =I64*I66 -> 45.377259 | J68: =J64*J66 -> 60.084407 | K68: =K64*K66 -> 67.243372 | L68: =L64*L66 -> 68.792885 | M68: =M64*M66 -> 66.213703
A70: 情境 C（查詢被 AI 助理分流、每次查詢變現下降）
A71: 項目 | E71: 說明 | F71: 2H26E | H71: FY2027E | I71: FY2028E | J71: FY2029E | K71: FY2030E | L71: FY2031E | M71: FY2032E
A72: 營業利益（財報口徑 EBIT） | F72: =PL!F164 -> 84.249893 | H72: =PL!H164 -> 149.98561 | I72: =PL!I164 -> 138.59421 | J72: =PL!J164 -> 127.10546 | K72: =PL!K164 -> 111.95289 | L72: =PL!L164 -> 111.28183 | M72: =PL!M164 -> 106.19828
A73: NOPAT＝(EBIT＋sbc_add × 股權報酬) ×(1 − 稅率) | F73: =(F72+sbc_add*PL!F186)*(1-tax) -> 70.095911 | H73: =(H72+sbc_add*PL!H186)*(1-tax) -> 124.78803 | I73: =(I72+sbc_add*PL!I186)*(1-tax) -> 115.31038 | J73: =(J72+sbc_add*PL!J186)*(1-tax) -> 105.75174 | K73: =(K72+sbc_add*PL!K186)*(1-tax) -> 93.144805 | L73: =(L72+sbc_add*PL!L186)*(1-tax) -> 92.586483 | M73: =(M72+sbc_add*PL!M186)*(1-tax) -> 88.356966
A74: ＋折舊 | F74: =PL!F162 -> 21.862219 | H74: =PL!H162 -> 66.811049 | I74: =PL!I162 -> 98.567732 | J74: =PL!J162 -> 130.39192 | K74: =PL!K162 -> 157.51104 | L74: =PL!L162 -> 180.38227 | M74: =PL!M162 -> 207.48298
A75: − 資本支出 | F75: =CF!F85 -> 119.402 | H75: =CF!H85 -> 236.7114 | I75: =CF!I85 -> 255.05397 | J75: =CF!J85 -> 240.56788 | K75: =CF!K85 -> 234.54068 | L75: =CF!L85 -> 245.0664 | M75: =CF!M85 -> 241.1435
A76: ＋營運資金變動 | F76: =CF!F80 -> 8.49 | H76: =CF!H80 -> 1.0088275 | I76: =CF!I80 -> 0.83107652 | J76: =CF!J80 -> 0.67568675 | K76: =CF!K80 -> 0.41137568 | L76: =CF!L80 -> 0.70361485 | M76: =CF!M80 -> 0.71094506
A77: 無槓桿自由現金流（財報口徑） | E77: 股權報酬視為現金成本（修正一 F2） | F77: =F73+F74-F75+F76 -> -18.953871 | H77: =H73+H74-H75+H76 -> -44.103496 | I77: =I73+I74-I75+I76 -> -40.344782 | J77: =J73+J74-J75+J76 -> -3.7485377 | K77: =K73+K74-K75+K76 -> 16.526541 | L77: =L73+L74-L75+L76 -> 28.605972 | M77: =M73+M74-M75+M76 -> 55.407386
A78: 自用 AI 影子效益（稅後；讀法 2 加入） | F78: =PL!F166*(1-tax) -> 3.2966663 | H78: =PL!H166*(1-tax) -> 27.184329 | I78: =PL!I166*(1-tax) -> 55.990656 | J78: =PL!J166*(1-tax) -> 82.352679 | K78: =PL!K166*(1-tax) -> 102.3774 | L78: =PL!L166*(1-tax) -> 116.34207 | M78: =PL!M166*(1-tax) -> 124.38837
A79: 折現年數（評價日 2026-06-30 起，期中） | F79: =t_2h -> 0.25 | H79: =2027-2026 -> 1 | I79: =2028-2026 -> 2 | J79: =2029-2026 -> 3 | K79: =2030-2026 -> 4 | L79: =2031-2026 -> 5 | M79: =2032-2026 -> 6
A80: 折現因子 1 ÷ (1＋WACC)^年數 | F80: =1/(1+wacc)^F79 -> 0.97407038 | H80: =1/(1+wacc)^H79 -> 0.90024631 | I80: =1/(1+wacc)^I79 -> 0.81044342 | J80: =1/(1+wacc)^J79 -> 0.72959869 | K80: =1/(1+wacc)^K79 -> 0.65681853 | L80: =1/(1+wacc)^L79 -> 0.59129846 | M80: =1/(1+wacc)^M79 -> 0.53231426
A81: 現值（財報口徑） | F81: =F77*F80 -> -18.462404 | H81: =H77*H80 -> -39.70401 | I81: =I77*I80 -> -32.697163 | J81: =J77*J80 -> -2.7349282 | K81: =K77*K80 -> 10.854938 | L81: =L77*L80 -> 16.914667 | M81: =M77*M80 -> 29.494141
A82: 現值（影子效益） | F82: =F78*F80 -> 3.211185 | H82: =H78*H80 -> 24.472592 | I82: =I78*I80 -> 45.377259 | J82: =J78*J80 -> 60.084407 | K82: =K78*K80 -> 67.243372 | L82: =L78*L80 -> 68.792885 | M82: =M78*M80 -> 66.213703
A84: DCF 彙總
A85: 項目 | B85: 情境 A | C85: 情境 B | D85: 情境 C | E85: 說明
A86: 明確期現值合計（財報口徑） | B86: =SUM(F53:M53) -> 215.94808 | C86: =SUM(F67:M67) -> 126.91447 | D86: =SUM(F81:M81) -> -36.334758
A87: 終值（FY2032 年底，財報口徑） | B87: =IF(tv_alt=1,M49*(1+g_tv)/(wacc-g_tv),M45*(1+g_tv)*(1-g_tv/ronic)/(wacc-g_tv)) -> 1823.9315 | C87: =IF(tv_alt=1,M63*(1+g_tv)/(wacc-g_tv),M59*(1+g_tv)*(1-g_tv/ronic)/(wacc-g_tv)) -> 1466.5762 | D87: =IF(tv_alt=1,M77*(1+g_tv)/(wacc-g_tv),M73*(1+g_tv)*(1-g_tv/ronic)/(wacc-g_tv)) -> 821.31621 | E87: 價值驅動：NOPAT(FY2033) ×(1 − g ÷ RONIC) ÷ (WACC − g)；tv_alt＝1 時改用 FY2032 無槓桿自由現金流 ×(1＋g)
A88: 終值現值（折現年數＝FY2032 期中＋mid） | B88: =B87/(1+wacc)^($M$51+mid) -> 921.20714 | C88: =C87/(1+wacc)^($M$65+mid) -> 740.71888 | D88: =D87/(1+wacc)^($M$79+mid) -> 414.8195
A89: 企業價值 EV（讀法 1：只計自用 AI 成本） | B89: =B86+B88 -> 1137.1552 | C89: =C86+C88 -> 867.63335 | D89: =D86+D88 -> 378.48475
A90: ＋自用 AI 影子效益現值：明確期 | B90: =SUM(F54:M54) -> 335.3954 | C90: =SUM(F68:M68) -> 335.3954 | D90: =SUM(F82:M82) -> 335.3954
A91: ＋自用 AI 影子效益現值：終值 | B91: =IF(tv_alt=1,M50*(1+g_tv)/(wacc-g_tv),M50*(1+g_tv)*(1-g_tv/ronic)/(wacc-g_tv))/(1+wacc)^($M$51+mid) -> 583.98024 | C91: =IF(tv_alt=1,M64*(1+g_tv)/(wacc-g_tv),M64*(1+g_tv)*(1-g_tv/ronic)/(wacc-g_tv))/(1+wacc)^($M$65+mid) -> 583.98024 | D91: =IF(tv_alt=1,M78*(1+g_tv)/(wacc-g_tv),M78*(1+g_tv)*(1-g_tv/ronic)/(wacc-g_tv))/(1+wacc)^($M$79+mid) -> 583.98024
A92: 企業價值 EV（讀法 2：自用 AI 價值中性） | B92: =B89+B90+B91 -> 2056.5309 | C92: =C89+C90+C91 -> 1787.009 | D92: =D89+D90+D91 -> 1297.8604
A93: 企業價值 EV（主值，依 internal_ai_reading） | B93: =IF(internal_ai_reading=2,B92,B89) -> 2056.5309 | C93: =IF(internal_ai_reading=2,C92,C89) -> 1787.009 | D93: =IF(internal_ai_reading=2,D92,D89) -> 1297.8604
A94: 其中：終值占 EV（主值） | B94: =(B88+(internal_ai_reading=2)*B91)/B93 -> 0.73190605 | C94: =(C88+(internal_ai_reading=2)*C91)/C93 -> 0.74129404 | D94: =(D88+(internal_ai_reading=2)*D91)/D93 -> 0.7695741
A95: ＋淨現金（評價日：現金 − 債務 − 融資租賃） | B95: =cash_0-debt_0-fin_lease -> 51.736 | C95: =cash_0-debt_0-fin_lease -> 51.736 | D95: =cash_0-debt_0-fin_lease -> 51.736
A96: ＋持股（Anthropic × 比例 ×(1 − 折價)＋SpaceX＋其他上市權益證券） | B96: =ant_val*ant_stake*(1-illiq)+spacex+oth_eq -> 197.689 | C96: =ant_val*ant_stake*(1-illiq)+spacex+oth_eq -> 197.689 | D96: =ant_val*ant_stake*(1-illiq)+spacex+oth_eq -> 197.689
A97: − 類債（應計罰款＋非控制權益） | B97: =fines+nci -> 24.456 | C97: =fines+nci -> 24.456 | D97: =fines+nci -> 24.456
A98: − 特別股股利現值（轉換前，以 ke 折現） | B98: =pref_2H/(1+ke)^$F$51+pref_27/(1+ke)^$H$51+pref_28/(1+ke)^$I$51+pref_29/(1+ke)^$J$51 -> 3.0116408 | C98: =pref_2H/(1+ke)^$F$51+pref_27/(1+ke)^$H$51+pref_28/(1+ke)^$I$51+pref_29/(1+ke)^$J$51 -> 3.0116408 | D98: =pref_2H/(1+ke)^$F$51+pref_27/(1+ke)^$H$51+pref_28/(1+ke)^$I$51+pref_29/(1+ke)^$J$51 -> 3.0116408 | E98: 修正一：強制轉換特別股 2029-05 轉股前的股利屬特別股股東
A99: 股數（評價日期末稀釋＋強制轉換特別股） | B99: =PL!E63+conv_sh -> 12.4426 | C99: =PL!E122+conv_sh -> 12.4426 | D99: =PL!E181+conv_sh -> 12.4426
A100: DCF 每股價值推到目標時點（讀法 1） | B100: =MAX(0,(B89+B95+B96-B97-B98)/B99*(1+ke)^t_tgt-dps_tgt) -> 124.57548 | C100: =MAX(0,(C89+C95+C96-C97-C98)/C99*(1+ke)^t_tgt-dps_tgt) -> 99.633403 | D100: =MAX(0,(D89+D95+D96-D97-D98)/D99*(1+ke)^t_tgt-dps_tgt) -> 54.366642 | E100: (EV＋淨現金＋持股 − 類債 − 特別股股利) ÷ 股數 ×(1＋ke)^t_tgt − 期間每股股利
A101: DCF 每股價值推到目標時點（讀法 2） | B101: =MAX(0,(B92+B95+B96-B97-B98)/B99*(1+ke)^t_tgt-dps_tgt) -> 209.65628 | C101: =MAX(0,(C92+C95+C96-C97-C98)/C99*(1+ke)^t_tgt-dps_tgt) -> 184.71421 | D101: =MAX(0,(D92+D95+D96-D97-D98)/D99*(1+ke)^t_tgt-dps_tgt) -> 139.44745
A102: DCF 情境價值推到 12 個月後（主值） | B102: =IF(internal_ai_reading=2,B101,B100) -> 209.65628 | C102: =IF(internal_ai_reading=2,C101,C100) -> 184.71421 | D102: =IF(internal_ai_reading=2,D101,D100) -> 139.44745
A104: 0.15 Cloud AI 模組自身 DCF（修正一 F3：分部加總的 AI 腿；FCF＝AI EBITDA − 稅 − 對外 AI 資本支出〔含汰換〕；三情境相同）
A105: 項目 | E105: 說明 | F105: 2H26E | H105: FY2027E | I105: FY2028E | J105: FY2029E | K105: FY2030E | L105: FY2031E | M105: FY2032E
A106: Cloud AI EBITDA（Thesis） | F106: =Thesis!F41 -> 10.974548 | H106: =Thesis!H41 -> 32.797293 | I106: =Thesis!I41 -> 48.040104 | J106: =Thesis!J41 -> 62.023332 | K106: =Thesis!K41 -> 72.645058 | L106: =Thesis!L41 -> 80.052348 | M106: =Thesis!M41 -> 84.320356
A107: 對外 AI 新增折舊（Thesis） | F107: =Thesis!F64 -> 2.1378716 | H107: =Thesis!H64 -> 10.534746 | I107: =Thesis!I64 -> 18.606852 | J107: =Thesis!J64 -> 26.928758 | K107: =Thesis!K64 -> 34.715472 | L107: =Thesis!L64 -> 42.55104 | M107: =Thesis!M64 -> 48.921595
A108: AI NOPAT＝(EBITDA − 折舊) ×(1 − 稅率) | F108: =(F106-F107)*(1-tax) -> 7.3521147 | H108: =(H106-H107)*(1-tax) -> 18.522439 | I108: =(I106-I107)*(1-tax) -> 24.488466 | J108: =(J106-J107)*(1-tax) -> 29.198685 | K108: =(K106-K107)*(1-tax) -> 31.557416 | L108: =(L106-L107)*(1-tax) -> 31.201089 | M108: =(M106-M107)*(1-tax) -> 29.451769
A109: 對外 AI 資本支出＝AI 資本支出 × 對外比例 | F109: =Thesis!F52*ext_sh -> 29.48484 | H109: =Thesis!H52*ext_sh -> 57.005725 | I109: =Thesis!I52*ext_sh -> 60.343316 | J109: =Thesis!J52*ext_sh -> 54.257763 | K109: =Thesis!K52*ext_sh -> 51.507927 | L109: =Thesis!L52*ext_sh -> 53.164345 | M109: =Thesis!M52*ext_sh -> 50.363053
A110: AI 自由現金流＝NOPAT＋折舊 − 資本支出 | F110: =F108+F107-F109 -> -19.994854 | H110: =H108+H107-H109 -> -27.94854 | I110: =I108+I107-I109 -> -17.247998 | J110: =J108+J107-J109 -> 1.8696804 | K110: =K108+K107-K109 -> 14.764961 | L110: =L108+L107-L109 -> 20.587783 | M110: =M108+M107-M109 -> 28.01031
A111: 現值 | F111: =F110*F52 -> -19.476395 | H111: =H110*H52 -> -25.16057 | I111: =I110*I52 -> -13.978527 | J111: =J110*J52 -> 1.3641164 | K111: =K110*K52 -> 9.6978998 | L111: =L110*L52 -> 12.173524 | M111: =M110*M52 -> 14.910288
...

Sheet Recon
A1: Recon — 口徑對照：合併層對市場共識（MarketScreener，2026-10-26）、逐分部對共識與公司指引、v0.3 對 v0.2.2。只作對照，不作校準（工作單第 4 節）
A3: 1. 合併層：本模型 vs 市場共識
A4: 項目 | B4: 年度 | C4: 情境 A | D4: 情境 B | E4: 情境 C | F4: 共識 | G4: B ÷ 共識 − 1 | H4: 說明
A5: 營收 | B5: FY2026 | C5: =PL!G24 -> 496.86103 | D5: =PL!G83 -> 496.86103 | E5: =PL!G142 -> 496.86103 | F5: =c_rev_26 -> 500.142 | G5: =D5/F5-1 -> -0.006560073
A6: 營收 | B6: FY2027 | C6: =PL!H24 -> 616.76317 | D6: =PL!H83 -> 605.34864 | E6: =PL!H142 -> 583.0856 | F6: =c_rev_27 -> 626.817 | G6: =D6/F6-1 -> -0.0342498
A7: 營收 | B7: FY2028 | C7: =PL!I24 -> 729.1892 | D7: =PL!I83 -> 703.31713 | E7: =PL!I142 -> 654.11778 | F7: =c_rev_28 -> 754.762 | G7: =D7/F7-1 -> -0.06816039
A8: 營業利益 | B8: FY2026 | C8: =PL!G46 -> 164.71589 | D8: =PL!G105 -> 164.71589 | E8: =PL!G164 -> 164.71589 | F8: =c_ebit_26 -> 172.033 | G8: =D8/F8-1 -> -0.042533162
A9: 營業利益 | B9: FY2027 | C9: =PL!H46 -> 171.88276 | D9: =PL!H105 -> 164.46104 | E9: =PL!H164 -> 149.98561 | F9: =c_ebit_27 -> 220.967 | G9: =D9/F9-1 -> -0.25572126
A10: 營業利益 | B10: FY2028 | C10: =PL!I46 -> 187.20358 | D10: =PL!I105 -> 170.45005 | E10: =PL!I164 -> 138.59421 | F10: =c_ebit_28 -> 268.322 | G10: =D10/F10-1 -> -0.36475561
A11: EPS（GAAP，含權益證券損益） | B11: FY2026 | C11: =PL!G65 -> 19.825492 | D11: =PL!G124 -> 19.825492 | E11: =PL!G183 -> 19.825492 | F11: =c_eps_26 -> 20.6 | G11: =D11/F11-1 -> -0.037597479 | H11: 含上半年權益證券利益 135.9；StockAnalysis 排除後的共識 11.89（In 頁 c_eps26_sa）
A12: EPS（GAAP，含權益證券損益） | B12: FY2027 | C12: =PL!H65 -> 11.385426 | D12: =PL!H124 -> 10.890931 | E12: =PL!H183 -> 9.9264612 | F12: =c_eps_27 -> 15.12 | G12: =D12/F12-1 -> -0.27970033
A13: EPS（GAAP，含權益證券損益） | B13: FY2028 | C13: =PL!I65 -> 12.273228 | D13: =PL!I124 -> 11.14785 | E13: =PL!I183 -> 9.0072273 | F13: =c_eps_28 -> 18.21 | G13: =D13/F13-1 -> -0.38781713
A14: 資本支出 | B14: FY2026 | C14: =CF!G21 -> 200 | D14: =CF!G53 -> 200 | E14: =CF!G85 -> 200 | F14: =c_capex_26 -> 202.078 | G14: =D14/F14-1 -> -0.010283158
A15: 資本支出 | B15: FY2027 | C15: =CF!H21 -> 238.73206 | D15: =CF!H53 -> 238.04718 | E15: =CF!H85 -> 236.7114 | F15: =c_capex_27 -> 308.024 | G15: =D15/F15-1 -> -0.22717975
A16: 資本支出 | B16: FY2028 | C16: =CF!I21 -> 259.55826 | D16: =CF!I53 -> 258.00593 | E16: =CF!I85 -> 255.05397 | F16: =c_capex_28 -> 352.387 | G16: =D16/F16-1 -> -0.26783356
A17: 自由現金流 | B17: FY2026 | C17: =CF!G23 -> 1.5577672 | D17: =CF!G55 -> 1.5577672 | E17: =CF!G87 -> 1.5577672 | F17: =c_fcf_26 -> 7.069 | G17: =D17/F17-1 -> -0.77963401 | H17: 本模型扣融資租賃本金；共識＝營運現金 − 資本支出
A18: 自由現金流 | B18: FY2027 | C18: =CF!H23 -> 11.438559 | D18: =CF!H55 -> 5.0776278 | E18: =CF!H87 -> -7.3288165 | F18: =c_fcf_27 -> -37.207 | G18: =D18/F18-1 -> -1.1364697 | H18: 本模型扣融資租賃本金；共識＝營運現金 − 資本支出
A19: 自由現金流 | B19: FY2028 | C19: =CF!I23 -> 41.686881 | D19: =CF!I55 -> 27.190183 | E19: =CF!I87 -> -0.38116385 | F19: =c_fcf_28 -> 6.132 | G19: =D19/F19-1 -> 3.434146 | H19: 本模型扣融資租賃本金；共識＝營運現金 − 資本支出
A20: EPS（不含權益證券損益）FY2026 vs StockAnalysis 共識 | B20: FY2026 | C20: =PL!G66 -> 11.126699 | D20: =PL!G125 -> 11.126699 | E20: =PL!G184 -> 11.126699 | F20: =c_eps26_sa -> 11.89 | G20: =D20/F20-1 -> -0.064196876
A22: 2. 逐分部、逐產品線：本模型（情境 B）vs 共識與公司指引
A23: 分部／產品線 | B23: FY2026E | C23: FY2027E | D23: FY2028E | E23: 共識 | F23: 公司指引 | G23: 說明
A24: Google Search & other | B24: =PL!G72 -> 263.4111 | C24: =PL!H72 -> 301.87173 | D24: =PL!I72 -> 339.30582 | E24: 未找到 | F24: 無（公司不給營收指引） | G24: StockAnalysis、MarketScreener 免費頁只有合併層；分部共識需付費資料，本次網路搜尋額度用盡，未能補（資料缺口：未找到）
A25: YouTube ads | B25: =PL!G73 -> 45.117364 | C25: =PL!H73 -> 49.983474 | D25: =PL!I73 -> 54.910329 | E25: 未找到 | F25: 無（公司不給營收指引）
A26: Google Network | B26: =PL!G74 -> 29.125255 | C26: =PL!H74 -> 28.649377 | D26: =PL!I74 -> 28.337309 | E26: 未找到 | F26: 無（公司不給營收指引）
A27: Google subscriptions, platforms, and devices | B27: =PL!G75 -> 56.488701 | C27: =PL!H75 -> 65.502963 | D27: =PL!I75 -> 74.654879 | E27: 未找到 | F27: 無（公司不給營收指引）
A28: Google Services | B28: =PL!G76 -> 394.14242 | C28: =PL!H76 -> 446.00755 | D28: =PL!I76 -> 497.20834 | E28: 未找到 | F28: 無（公司不給營收指引）
A29: Google Cloud | B29: =PL!G80 -> 101.24961 | C29: =PL!H80 -> 157.7411 | D29: =PL!I80 -> 204.30879 | E29: 未找到 | F29: 仍供不應求（2026Q2）；無營收指引
A30: Cloud AI（命題子列） | B30: =PL!G77 -> 22.830611 | C30: =PL!H77 -> 38.882858 | D30: =PL!I77 -> 56.703559 | E30: 未找到 | F30: 無（公司不給營收指引）
A31: TPU 系統銷售 | B31: =PL!G78 -> 1 | C31: =PL!H78 -> 13 | D31: =PL!I78 -> 13 | E31: 未找到 | F31: 2026 認列一小部分、大部分在 2027（2026Q2 法說，事實總帳 guid.tpuRev）
A32: Cloud 其他 | B32: =PL!G79 -> 77.419 | C32: =PL!H79 -> 105.85824 | D32: =PL!I79 -> 134.60523 | E32: 未找到 | F32: 無（公司不給營收指引）
A33: Other Bets | B33: =PL!G81 -> 1.543 | C33: =PL!H81 -> 1.6 | D33: =PL!I81 -> 1.8 | E33: 未找到 | F33: 無（公司不給營收指引）
A34: Google Cloud 積壓（RPO）約 50% 在 24 個月內認列 → 2026H2–2028H1 至少可認列 | B34: =rpo_cloud*rpo_24m -> 256.95 | G34: 10-Q 2026Q2：Cloud RPO 513.9、約 50% 於 24 個月內（事實總帳 rpo.cloud、rpo.share24m）[Interested-party]；只作驗證列，不反推 k 或 MW
A35: 本模型 Google Cloud 營收 2026H2–2028H1（情境 B） | B35: =PL!F80+PL!H80+0.5*PL!I80 -> 316.3491 | C35: =B35/B34 -> 1.2311699 | G35: C 欄＝本模型 ÷ 積壓可認列（> 1 表示模型營收高於積壓可支撐的下限，差額需新簽約）
A36: FY2026 資本支出：本模型 vs 公司指引 195–205 | B36: =CF!G53 -> 200 | C36: =capex_g -> 200 | G36: C10：首期＝MAX(公式, 指引)
A37: FY2027 資本支出：本模型 vs 公司「顯著增加」（無數字）vs 共識 | B37: =CF!H53 -> 238.04718 | C37: =c_capex_27 -> 308.024 | G37: 本模型 FY2027 由 MW 路徑推導（C10 基準速度 = 2026 指引隱含量延續）；低於共識是已知差異（v0.2.2 同）
A39: 3. v0.3 vs v0.2.2：目標價與主要差異來源
A40: 項目 | B40: 數值 | C40: 說明
A41: v0.2.2 加權目標價（讀法 1；25／50／25） | B41: =tpw_v022 -> 147.54 | C41: v0.2.2：保守 175.08／基準 146.09／積極 122.89（容量情境；讀法 2 為 218.79）
A42: v0.3 加權目標價 | B42: =Val!B8 -> 248.93682
A43: 差額 | B43: =B42-B41 -> 101.39682
A44: 拆解（以改輸入重算；make_v03.sh）
A45: 評價法權重：DCF 50% → v0.2.2 的 45%（其餘不變） | B45: =Val!B8-255.867201633057 -> -6.9303786 | C45: v0.3 − 改成 w_dcf=0.45 後的目標價（正值＝本版設定使目標價較高）
A46: 現價回到 v0.2.2 的 350.50（只影響 WACC 的權益權重與回購價） | B46: =Val!B8-248.710588733203 -> 0.22623433 | C46: v0.3 − 改成 px=350.5 後的目標價（正值＝本版設定使目標價較高）
A47: 其餘：營收結構（分部＋Search 情境軸）、AI 折舊與自用 AI 成本進分部損益、DCF 終值口徑（價值驅動）、SOTP 以各分部同業倍數取代 EV/EBITDA 錨定 2029、情境定義改為 Search | B47: =B43-N(B45)-N(B46) -> 108.10097 | C47: 兩版引擎不同，無法逐項以同一引擎重算；本列為殘差（報告第 6 節逐項說明方向）

Sheet Sens
A1: Sens — 一次改一個輸入（In 頁低／高值），整本活頁簿以 LibreOffice 重算後的加權目標價（Val 頁「目標價（DCF 與 Comparable 加權）」）；由 alphabet/make_v03.sh 產生，建置時寫入（數值）
A2: 相對基準＝情境目標價 ÷ 基準加權目標價 − 1；龍捲風依絕對值排序（HTML）。基準與各案例的其他輸入相同
A3: 驅動 | B3: 設定 | C3: 方向 | D3: 加權目標價 | E3: 相對基準 | F3: 鍵 | G3: 說明
A4: 自用 AI 讀法 1（只計成本；C16）：低 | B4: 讀法 2 → 讀法 1 | C4: 低 | D4: 180.17862 | E4: =D4/Val!$B$8-1 -> -0.27620746 | F4: internal_ai_reading | G4: 重算值（make_v03.sh）
A5: 對外比例（C23）：低 | B5: 10%／50%（±20pt；總 MW 不變） | C5: 低 | D5: 264.84545 | E5: =D5/Val!$B$8-1 -> 0.063906273 | F5: ext_sh | G5: 重算值（make_v03.sh）
A6: 對外比例（C23）：高 | B6: 10%／50%（±20pt；總 MW 不變） | C6: 高 | D6: 232.98963 | E6: =D6/Val!$B$8-1 -> -0.064061187 | F6: ext_sh | G6: 重算值（make_v03.sh）
A7: AI MW 新增速度：低 | B7: v0.2.2 保守／積極速度 | C7: 低 | D7: 240.98474 | E7: =D7/Val!$B$8-1 -> -0.031944178 | F7: pace | G7: 重算值（make_v03.sh）
A8: AI MW 新增速度：高 | B8: v0.2.2 保守／積極速度 | C8: 高 | D8: 257.115 | E8: =D8/Val!$B$8-1 -> 0.032852415 | F8: pace | G8: 重算值（make_v03.sh）
A9: k：長約價格（低＝判斷倍數 0.60）：低 | B9: 長約 0.75 → 0.60 | C9: 低 | D9: 247.51165 | E9: =D9/Val!$B$8-1 -> -0.0057250583 | F9: kl_px | G9: 重算值（make_v03.sh）
A10: k：現貨價格（高＝GCP 牌價）：高 | B10: 2.82 → 4.858 US$/GPU-hr | C10: 高 | D10: 258.13157 | E10: =D10/Val!$B$8-1 -> 0.036936066 | F10: ks_px | G10: 重算值（make_v03.sh）
A11: TPU 係數（收入與資本支出雙邊 × 0.7）：低 | B11: C2 敏感度；同時改 tpu_cf | C11: 低 | D11: 245.84282 | E11: =D11/Val!$B$8-1 -> -0.012428853 | F11: tpu_f | G11: 重算值（make_v03.sh）
A12: AI IT 折舊年限：低 | B12: 5／7 年 | C12: 低 | D12: 249.39846 | E12: =D12/Val!$B$8-1 -> 0.0018544158 | F12: life_it | G12: 重算值（make_v03.sh）
A13: AI IT 折舊年限：高 | B13: 5／7 年 | C13: 高 | D13: 252.20799 | E13: =D13/Val!$B$8-1 -> 0.013140557 | F13: life_it | G13: 重算值（make_v03.sh）
A14: Search 情境 C 分流幅度：低 | B14: 10%／30%（只影響 C 情境） | C14: 低 | D14: 251.91523 | E14: =D14/Val!$B$8-1 -> 0.011964525 | F14: dC | G14: 重算值（make_v03.sh）
A15: Search 情境 C 分流幅度：高 | B15: 10%／30%（只影響 C 情境） | C15: 高 | D15: 245.95841 | E15: =D15/Val!$B$8-1 -> -0.011964525 | F15: dC | G15: 重算值（make_v03.sh）
... A45: DCF 加回股權報酬：高 | B45: 不加回 → 加回（稅後） | C45: 高 | D45: 268.82295 | E45: =D45/Val!$B$8-1 -> 0.079884214 | F45: sbc_add | G45: 重算值（make_v03.sh）
A47: 基準加權目標價（Val 頁） | D47: =Val!B8 -> 248.93682
