Workbook

Sheet README
A1: Fabrinet（FN，NYSE）收支與估值模型 v0.1.2（AI 半導體 Project：網通次產業內複製——光模組與光元件代工，樣板 Coherent） 2026-10-26
A2: 版本：v0.1.1（2026-10-25：補上檔空間級距、投資建議、重點觀察，數值不變）；v0.1（2026-10-25 初版；三情境延伸到 FY2032、目標價＝DCF 與 Comparable 加權）。Fabrinet 的光模組有效份額口徑與中際旭創、Coherent 模型一致（光模組營收 ÷ 可插拔市場），Units 頁檢查與中際旭創相加低於 100%。
A3: 模型命題：Fabrinet 的資料中心營收＝AI 可插拔光模組市場（本專案網通模型）× Fabrinet 光模組有效份額（NVIDIA 等客戶代工）× 單價係數＋CPO 光學 × CPO 份額＋DCI＋HPC（乘同字母 AI 情境係數）；通訊基礎設施、車用工業另依成長率推。股價自 52 週高點 749 跌到約 315（−58%），只約 17 倍共識未來 12 月 EPS：市場在問 NVIDIA 光模組份額流失（占營收 27.6% → 16.3%）後，DCI、HPC 與新客戶能否接上成長。
A4: 核心問題：NVIDIA 份額下滑而 DCI、HPC 高成長——市場隱含的 FY2028 EPS 要多低，光模組份額、AI 市場、毛利率三條路徑各要不利到什麼程度？
A6: 會計年度：FY(t)＝t−1 年 7 月～t 年 6 月（6 月最後一個星期五結束）；FY2026＝2025-06～2026-06-26（實績）、FY2027＝2026-06～2027-06。日曆年市場以「上半年比重 hw」換算：FY(t)＝（1 − hw）× CY(t−1)＋hw × CY(t)，FY2027 的 CY2026 下半年用 Q1 指引推導＋Q2 假設。口徑：non-GAAP（排除股票薪酬、Pillar Two 補充稅、非上市股權重估等）。
A8: 驅動因子 → 推導量（全部唯讀上游，不修改）
A9: 光模組與其他：markets/network 的 AI 可插拔光模組市場 × 同字母顆數係數 × Fabrinet 有效份額（CY2026 校準）× 份額相對值（Assumed）× 單價係數（基準 1）＋ CPO 光學市場 × CPO 份額（Assumed）。DCI、HPC：FY2027 上半年推導 × 下半年成長，FY2028 起年增，乘同字母 AI 情境係數。
A10: 通訊基礎設施（電信系統、衛星通訊、電信元件）、車用工業與其他（EV 充電、LiDAR、工業雷射）：FY2027 上半年 × 下半年成長，FY2028 起年增（Assumed；各情境相同）。毛利率：FY2027 起輸入路徑（情境 A 高、C 低）。營業費用：彈性 phi（Derived）。稅率 5%（不含 Pillar Two）。
A11: 校準：FY2026 全年實績；資料中心內光模組、DCI、HPC 由法說會金額推導（Q 頁）。不用共識（只在 Recon 對帳）。
A12: 估值：目標價（Val 第 0 節）＝0.5 × DCF（股東現金流＝EPS ×（1 − g／ROE），FY2027–32 明確期＋永續，r 10%、g 4%，情境權重 0.3／0.5／0.2；情境價值下限 0）＋0.5 × Comparable（市場主流同業前瞻 P/E 中位數 × 12 個月後前瞻 EPS）。舊法規則值情境加權保留參考（不是目標價）；現價 ÷ FY2027、FY2028 EPS；市場隱含 FY2028 EPS（Val 第 4 節）；十年 GAAP P/E 規則值（兩個資料商）× FY2027 EPS。本版未做先驗，無 Andy 合理 P/E 對照。
A13: 標記：Verified、Interested-party、Analogy、Assumed、Derived。SemiAnalysis 未使用。
A15: 已知限制：(1) 光模組份額相對值、CPO 份額、毛利率路徑皆為 Assumed，是 FY2028 EPS 最敏感的輸入（Sens）；(2) 資料中心內光模組、DCI、HPC 金額為法說會轉述與推導，FY2027 Q1 季報（預估 2026-11-02）後更新；(3) 代工營收含料件轉嫁，有效份額與模組廠出貨份額口徑不同；(4) non-GAAP 排除 Pillar Two 補充稅（約每股 1.6 美元／年），DCF 偏高估；(5) Building 10 等資本支出使 FY2026 自由現金流近 0，DCF 以 g／ROE 再投資率近似，未建資本支出；(6) R4 產業部署路徑未建（Recon 預留列）。
... A17: v0.1.1（2026-10-25）：補上檔空間級距、投資建議、重點觀察（Val 頁 0.3 結論加「上檔空間級距」「投資建議」兩列、README 頁加重點觀察三點；數值不變，既有儲存格位置不變）。
A18: ="投資建議："&Val!B50&"（依上檔空間固定規則）" -> 投資建議：中立（依上檔空間固定規則）
A19: 重點觀察 1：目標價 US$373（DCF 350、Comparable 396 各半），比現價 314.94（2026-10-23）高 18.5%，級距 0%–25%；Comparable 單獨為 +25.9%。本模型 12 個月後前瞻 EPS 23.81 比共識前瞻 EPS 21.27 高 11.9%，但同業（Coherent、Lumentum、Jabil、Celestica、Flex）前瞻 P/E 中位數 16.7 倍，遠低於共識目標價 687.78 隱含的 32.3 倍（高 94.2%）；共識目標價比現價高 118.4%，與本模型的差距幾乎全在倍數。
A20: 重點觀察 2：情境分歧大：情境 A／C（含網通 CPO 情境、份額、CPO 份額、毛利率）FY2028 EPS 比 B 高 26.2%／低 20.7%，DCF 價格帶 164～564；單一變數中計入 Pillar Two 補充稅 −9.5%、光模組份額流失 −7.7%、毛利率低（新廠爬坡）−6.9%。
A21: 重點觀察 3：追蹤 FY2027 Q1 財報（預估 2026-11-02）：資料中心內光模組、DCI、HPC 金額為推導值，NVIDIA 光模組營收未揭露。網通 CPO 已改三情境（v0.1.2；A＝替代快、C＝慢）：Fabrinet 同時代工可插拔與 CPO（情境 A 取 CPO 份額高值），CPO 快淨為加分——情境 A FY2028 EPS 由 26.89 升到 27.81（+3.4%）、C 由 17.44 升到 17.48（+0.2%）、B 不變；CPO 份額低／高時 FY2028 EPS −2.0%／+3.0%。
A22: v0.1.2（2026-10-26）：網通模型 v0.2.3 的 CPO 滲透改三情境（A＝替代快、B＝平平、C＝慢），本模型 A／B／C 改讀同字母的可插拔與 CPO 市場（In 頁末新增 B、C 兩組；情境 A 沿用 A 節 mpl_／mcp_，數值改為網通情境 A）；FY2027 起三情境不再相同。其他輸入不變。

Sheet In
A1: In — 輸入（藍字；基準欄 E，低 D、高 F）。金額：十億美元（US$B）；比例：%。每個輸入附兩個來源（找不到者寫「未找到」）；公司原文算一個
A2: 標記：Verified／Interested-party／Analogy／Assumed／Derived；Analogy、Assumed 給低／高區間。情境 A 取公司特有變數的高值、B 取基準、C 取低值。SemiAnalysis 未使用。公司原文＝SEC 8-K 新聞稿與 10-K；資料中心內的光模組、DCI、HPC 拆分以法說會揭露金額推導
A3: 鍵 | B3: 項目 | C3: 單位 | D3: 低 | E3: 基準 | F3: 高 | G3: 標記 | H3: 來源1 | I3: 來源2／說明
A4: A. AI 光模組市場（讀 markets/network 成品；日曆年；情境 A 基準，B／C 依同字母顆數係數縮放）
A5: mpl_26 | B5: AI 可插拔光模組市場 CY2026 | C5: US$B | E5: 29.753262 | G5: Derived | H5: markets/network/dist/20261026_AI網通市場模型_v0.2.3.xlsx｜Mkt!C45:F45 | I5: 加速器顆數 × 每顆光學內容（scale-out 為主；2029 含 scale-up 光學）− CPO
A6: mpl_27 | B6: AI 可插拔光模組市場 CY2027 | C6: US$B | E6: 53.560715 | G6: Derived | H6: markets/network/dist/20261026_AI網通市場模型_v0.2.3.xlsx｜Mkt!C45:F45 | I6: 同上
A7: mpl_28 | B7: AI 可插拔光模組市場 CY2028 | C7: US$B | E7: 57.9915 | G7: Derived | H7: markets/network/dist/20261026_AI網通市場模型_v0.2.3.xlsx｜Mkt!C45:F45 | I7: 同上
A8: mpl_29 | B8: AI 可插拔光模組市場 CY2029 | C8: US$B | E8: 72.9348 | G8: Derived | H8: markets/network/dist/20261026_AI網通市場模型_v0.2.3.xlsx｜Mkt!C45:F45 | I8: 同上
A9: mcp_26 | B9: AI CPO 光學市場 CY2026 | C9: US$B | E9: 0.300538 | G9: Derived | H9: markets/network/dist/20261026_AI網通市場模型_v0.2.3.xlsx｜Mkt!C44:F44 | I9: 共同封裝光學；情境 A 列（網通 v0.2.3 起 CPO 滲透分三情境，替代速度為行業變數，B、C 見 In 頁末，各 × 同字母顆數係數，不自訂）
A10: mcp_27 | B10: AI CPO 光學市場 CY2027 | C10: US$B | E10: 2.818985 | G10: Derived | H10: markets/network/dist/20261026_AI網通市場模型_v0.2.3.xlsx｜Mkt!C44:F44 | I10: 同上
A11: mcp_28 | B11: AI CPO 光學市場 CY2028 | C11: US$B | E11: 6.4435 | G11: Derived | H11: markets/network/dist/20261026_AI網通市場模型_v0.2.3.xlsx｜Mkt!C44:F44 | I11: 同上
A12: mcp_29 | B12: AI CPO 光學市場 CY2029 | C12: US$B | E12: 11.74736 | G12: Derived | H12: markets/network/dist/20261026_AI網通市場模型_v0.2.3.xlsx｜Mkt!C44:F44 | I12: 同上
A13: itc_26 | B13: AI IT 資本支出 CY2026 | C13: US$B | E13: 781.87292 | G13: Derived | H13: markets/network/dist/20261026_AI網通市場模型_v0.2.3.xlsx｜Mkt!C27:F27 | I13: Recon 用：Fabrinet 資料中心營收 ÷ AI IT 資本支出
A14: itc_27 | B14: AI IT 資本支出 CY2027 | C14: US$B | E14: 1565.35 | G14: Derived | H14: markets/network/dist/20261026_AI網通市場模型_v0.2.3.xlsx｜Mkt!C27:F27 | I14: 同上
A15: itc_28 | B15: AI IT 資本支出 CY2028 | C15: US$B | E15: 1984.2639 | G15: Derived | H15: markets/network/dist/20261026_AI網通市場模型_v0.2.3.xlsx｜Mkt!C27:F27 | I15: 同上
A16: itc_29 | B16: AI IT 資本支出 CY2029 | C16: US$B | E16: 2260.3903 | G16: Derived | H16: markets/network/dist/20261026_AI網通市場模型_v0.2.3.xlsx｜Mkt!C27:F27 | I16: 同上
... A26: um29_C | B26: 情境 C：2029 顆數 ÷ 基準 | C26: x | E26: 0.6 | G26: Assumed | H26: tsmc/dist/20261028_台積電個股模型_v0.4.xlsx｜In!E42 | I26: 同上
A27: B. Fabrinet 光模組份額與單價（光模組有效份額＝資料中心光模組與其他營收 ÷ 可插拔市場；代工營收含客供以外的料件；低＝情境 C、基準＝B、高＝A）
A28: rel_27 | B28: 光模組有效份額 CY2027 ÷ CY2026（相對值） | C28: x | D28: 0.8 | E28: 1 | F28: 1.15 | G28: Assumed | H28: https://www.webull.com/news/15420495044125696：數個新光模組專案最快 FY2027 Q1 起量，一個商用（merchant）專案 12 月季開始、其他 CY2027 初（公司，Interested-party） | I28: https://www.sec.gov/Archives/edgar/data/0001408710/000140871026000028/fn-20260626.htm：NVIDIA 占營收 FY2025 27.6% → FY2026 16.3%（客戶自建與多供應商分散；高值＝新客戶專案、低值＝NVIDIA 份額續降）
A29: rel_28 | B29: 光模組有效份額 CY2028 ÷ CY2026 | C29: x | D29: 0.7 | E29: 1 | F29: 1.25 | G29: Assumed | H29: 同上；Building 10（約 200 萬平方呎）2027 年初完工，產能由約 55–58 億美元增至 85–93 億美元（公司） | I29: —
A30: rel_29 | B30: 光模組有效份額 CY2029 ÷ CY2026 | C30: x | D30: 0.6 | E30: 0.95 | F30: 1.3 | G30: Assumed | H30: 同上 | I30: —
A31: cpo_27 | B31: Fabrinet 占 CPO 光學金額 CY2027 | C31: % | D31: 0 | E31: 0.05 | F31: 0.15 | G31: Assumed | H31: Webull 法說會逐字稿（網址見 Sources）：與少數客戶開發 CPO 並已在生產元件，尚未全量；NPO 比 CPO 更近（公司） | I31: Fabrinet CPO 營收：未找到
A32: cpo_28 | B32: Fabrinet 占 CPO 光學金額 CY2028 | C32: % | D32: 0.02 | E32: 0.1 | F32: 0.2 | G32: Assumed | H32: 同上 | I32: 中際旭創、Coherent 模型同期 15%；代工與模組廠份額有重疊
A33: cpo_29 | B33: Fabrinet 占 CPO 光學金額 CY2029 | C33: % | D33: 0.05 | E33: 0.15 | F33: 0.25 | G33: Assumed | H33: 同上 | I33: —
A34: pxr_27 | B34: 單價係數 CY2027（相對網通模型每顆內容；基準 1） | C34: x | D34: 0.9 | E34: 1 | F34: 1.05 | G34: Assumed | H34: 網通模型每顆光學內容已含世代單價；本係數只在 Sens 動（降價快於模型） | I34: 代工價格為成本加成；料件降價直接降營收（公司未揭露價格）
A35: pxr_28 | B35: 單價係數 CY2028 | C35: x | D35: 0.8 | E35: 1 | F35: 1.05 | G35: Assumed | H35: 同上（與中際旭創、Coherent 模型相同） | I35: —
A36: pxr_29 | B36: 單價係數 CY2029 | C36: x | D36: 0.72 | E36: 1 | F36: 1.05 | G36: Assumed | H36: 同上 | I36: —
A37: hw | B37: 日曆年上半年占全年比重（光模組；會計年度換算用） | C37: % | D37: 0.42 | E37: 0.46 | F37: 0.5 | G37: Assumed | H37: CY2026 推導：上半年（FY2026 Q3＋Q4）÷ 全年約 46%（Q 頁） | I37: 與 Coherent 模型相同；Sens 動 42%／50%
A38: q2_tg | B38: FY2027 Q2（2026-12 季）光模組季增 | C38: % | D38: 0.03 | E38: 0.08 | F38: 0.15 | G38: Assumed | H38: https://www.webull.com/news/15420495044125696：商用光模組專案 12 月季開始（公司） | I38: https://www.nasdaq.com/articles/fabrinet-q4-earnings-call-highlights：資料中心 FY2027 Q1 預期光模組、DCI、HPC 全面成長
A39: C. FY2026 實績與新營收類別（公司 FY2026 起改報資料中心、通訊基礎設施、車用工業與其他三類）
A40: q3_rev | B40: FY2026 Q3（2026-03 季）營收 | C40: US$B | E40: 1.2143 | G40: Verified | H40: https://www.sec.gov/Archives/edgar/data/0001408710/000140871026000014/fn-2026504xex991q326.htm：1,214.3 百萬美元 | I40: https://www.tradingview.com/news/zacks:01f406102094b:0-fn-q3-earnings-beat-estimates-revenues-up-on-strong-telecom-hpc/：12.14 億美元（年增 39.3%）
A41: q4_rev | B41: FY2026 Q4（2026-06 季）營收 | C41: US$B | E41: 1.315788 | G41: Verified | H41: https://www.sec.gov/Archives/edgar/data/0001408710/000140871026000026/fn-2026811xex991q426.htm：1,315,788 千美元（年增 45%） | I41: https://www.nasdaq.com/articles/fabrinet-q4-earnings-call-highlights：13.16 億美元
A42: q3_dc | B42: FY2026 Q3 資料中心營收（新分類） | C42: US$B | E42: 0.592 | G42: Interested-party | H42: https://pulse2.com/fabrinet-data-center-revenue-jumps-68-to-669-million-and-becomes-51-of-quarterly-sales-as-dci-more-than-doubles/：5.920 億美元（Q4 季增 13% 的基期；公司簡報經媒體轉述） | I42: https://www.nasdaq.com/articles/fabrinet-q4-earnings-call-highlights：Q4 季增 13%（669 ÷ 1.13 ≈ 592）
A43: q4_dc | B43: FY2026 Q4 資料中心營收 | C43: US$B | E43: 0.6693 | G43: Interested-party | H43: https://pulse2.com/fabrinet-data-center-revenue-jumps-68-to-669-million-and-becomes-51-of-quarterly-sales-as-dci-more-than-doubles/：6.693 億美元（年增 68%、占 51%） | I43: https://www.webull.com/news/15420495044125696：6.69 億美元
A44: q4_ci | B44: FY2026 Q4 通訊基礎設施營收 | C44: US$B | E44: 0.4129 | G44: Interested-party | H44: https://pulse2.com/fabrinet-data-center-revenue-jumps-68-to-669-million-and-becomes-51-of-quarterly-sales-as-dci-more-than-doubles/：4.129 億美元（年增約 40%） | I44: https://www.nasdaq.com/articles/fabrinet-q4-earnings-call-highlights：4.13 億美元，季增 1%
A45: q4_aio | B45: FY2026 Q4 車用、工業與其他營收 | C45: US$B | E45: 0.2336 | G45: Interested-party | H45: https://pulse2.com/fabrinet-data-center-revenue-jumps-68-to-669-million-and-becomes-51-of-quarterly-sales-as-dci-more-than-doubles/：2.336 億美元（年增約 8%） | I45: https://www.nasdaq.com/articles/fabrinet-q4-earnings-call-highlights：2.34 億美元，季增 9%（EV 充電、LiDAR）
A46: q4_cig | B46: FY2026 Q4 通訊基礎設施季增（Q3 回推用） | C46: % | E46: 0.01 | G46: Interested-party | H46: https://www.nasdaq.com/articles/fabrinet-q4-earnings-call-highlights：季增 1%（公司） | I46: https://www.webull.com/news/15420495044125696：同值
A47: dci_q1 | B47: FY2026 Q1 DCI（資料中心互連）營收 | C47: US$B | E47: 0.1381 | G47: Interested-party | H47: https://pulse2.com/fabrinet-data-center-revenue-jumps-68-to-669-million-and-becomes-51-of-quarterly-sales-as-dci-more-than-doubles/：1.381 億美元（法說會） | I47: —
A48: dci_q2 | B48: FY2026 Q2 DCI（資料中心互連）營收 | C48: US$B | E48: 0.1422 | G48: Interested-party | H48: https://pulse2.com/fabrinet-data-center-revenue-jumps-68-to-669-million-and-becomes-51-of-quarterly-sales-as-dci-more-than-doubles/：1.422 億美元（法說會） | I48: https://www.aol.com/articles/fabrinet-fn-q2-2026-earnings-232305108.html：1.42 億美元，年增 42%
A49: dci_q3 | B49: FY2026 Q3 DCI（資料中心互連）營收 | C49: US$B | E49: 0.1969 | G49: Interested-party | H49: https://pulse2.com/fabrinet-data-center-revenue-jumps-68-to-669-million-and-becomes-51-of-quarterly-sales-as-dci-more-than-doubles/：1.969 億美元（法說會） | I49: https://www.tradingview.com/news/zacks:01f406102094b:0-fn-q3-earnings-beat-estimates-revenues-up-on-strong-telecom-hpc/：1.969 億美元，年增 90.4%
A50: dci_q4 | B50: FY2026 Q4 DCI（資料中心互連）營收 | C50: US$B | E50: 0.2559 | G50: Interested-party | H50: https://pulse2.com/fabrinet-data-center-revenue-jumps-68-to-669-million-and-becomes-51-of-quarterly-sales-as-dci-more-than-doubles/：2.559 億美元（法說會） | I50: https://www.webull.com/news/15420495044125696：DCI 年化約 10 億美元
A51: hpc_q1 | B51: FY2026 Q1 HPC（高效能運算）營收 | C51: US$B | E51: 0.0154 | G51: Interested-party | H51: Pulse 2.0（網址見 Sources）：0.154 億美元 | I51: https://www.aol.com/articles/fabrinet-fn-q2-2026-earnings-232305108.html：Q1 約 0.15 億美元
... A57: dci_q4_25 | B57: FY2025 Q4 DCI 營收 | C57: US$B | E57: 0.107 | G57: Interested-party | H57: https://pulse2.com/fabrinet-data-center-revenue-jumps-68-to-669-million-and-becomes-51-of-quarterly-sales-as-dci-more-than-doubles/：1.07 億美元 | I57: —
A58: dci_q1_25 | B58: FY2025 Q1 DCI 營收 | C58: US$B | D58: 0.08 | E58: 0.1 | F58: 0.11 | G58: Assumed | H58: 未找到；假設與 FY2025 Q2 回推值（約 1.0 億）相近 | I58: 只影響 FY2025 拆分
A59: nv26 | B59: NVIDIA 占營收 FY2026 | C59: % | E59: 0.163 | G59: Verified | H59: https://www.sec.gov/Archives/edgar/data/0001408710/000140871026000028/fn-20260626.htm：16.3%（FY2025 27.6%） | I59: https://www.webull.com/news/15420495044125696：16%（Cisco 20%、Nokia 11%、Amazon 11%）
A60: D. FY2027 Q1 指引與 Q2 假設（＝CY2026 下半年）
A61: q1_rev | B61: FY2027 Q1（2026-09 季）營收指引中點 | C61: US$B | D61: 1.375 | E61: 1.4 | F61: 1.425 | G61: Interested-party | H61: https://www.sec.gov/Archives/edgar/data/0001408710/000140871026000026/fn-2026811xex991q426.htm：13.75–14.25 億美元（公司指引） | I61: https://www.webull.com/news/15420495044125696：中點年增 43%
A62: q1_eps | B62: FY2027 Q1 non-GAAP EPS 指引中點 | C62: US$ | D62: 4.1 | E62: 4.175 | F62: 4.25 | G62: Interested-party | H62: https://www.sec.gov/Archives/edgar/data/0001408710/000140871026000026/fn-2026811xex991q426.htm：4.10–4.25 美元（公司指引） | I62: GAAP 3.39–3.54；差額含 Pillar Two 0.40 美元
A63: q1_gm | B63: FY2027 Q1 non-GAAP 毛利率 | C63: % | D63: 0.12 | E63: 0.122 | F63: 0.124 | G63: Assumed | H63: https://www.sec.gov/Archives/edgar/data/0001408710/000140871026000026/fn-2026811xex991q426.htm：FY2026 Q4 12.2%、全年 12.2%（公司不指引毛利率） | I63: https://www.webull.com/news/15420495044125696：Q1 季節性費用增加，短暫壓利潤率（公司）
A64: q1_opx | B64: FY2027 Q1 non-GAAP 營業費用 | C64: US$B | D64: 0.018 | E64: 0.0195 | F64: 0.021 | G64: Assumed | H64: FY2026 Q4 非 GAAP 營業費用約 0.175 億美元（毛利 − 營業利益） | I64: Q1 調薪季節性上升（公司）
A65: q_dcig | B65: DCI 季增（FY2027 Q1、Q2） | C65: % | D65: 0.05 | E65: 0.1 | F65: 0.15 | G65: Assumed | H65: FY2026 Q4 DCI 季增 30%（推導） | I65: https://www.nasdaq.com/articles/fabrinet-q4-earnings-call-highlights：DCI 是 Q4 最大成長來源
A66: q_hpg | B66: HPC 季增（FY2027 Q1、Q2） | C66: % | D66: 0 | E66: 0.1 | F66: 0.2 | G66: Assumed | H66: FY2026 Q4 季增約 11%（推導） | I66: https://www.aol.com/articles/fabrinet-fn-q2-2026-earnings-232305108.html：Fabrinet 在 AWS 專案是第二供應商，非獨家（公司）
A67: q_cig | B67: 通訊基礎設施季增（FY2027 Q1、Q2） | C67: % | D67: 0 | E67: 0.03 | F67: 0.05 | G67: Assumed | H67: https://www.nasdaq.com/articles/fabrinet-q4-earnings-call-highlights：預期健康成長（公司） | I67: —
A68: q_aig | B68: 車用、工業與其他季增（FY2027 Q1、Q2） | C68: % | D68: 0 | E68: 0.02 | F68: 0.05 | G68: Assumed | H68: https://www.nasdaq.com/articles/fabrinet-q4-earnings-call-highlights：預期成長，未給數字（公司） | I68: —
A69: E. DCI、HPC、通訊基礎設施、車用工業（FY2027＝上半年 ×（2＋下半年 ÷ 上半年 − 1）；FY2028 起年增；DCI、HPC 另乘同字母 AI 情境係數）
A70: h2_dci | B70: DCI 下半年 ÷ 上半年 − 1（FY2027） | C70: % | D70: 0 | E70: 0.12 | F70: 0.25 | G70: Assumed | H70: https://www.webull.com/news/15420495044125696：DCI 年化約 10 億美元（Q4） | I70: —
A71: g_dci_28 | B71: DCI 年增 FY2028（基準路徑） | C71: % | D71: 0.05 | E71: 0.2 | F71: 0.3 | G71: Assumed | H71: scale-across 資料中心互連（800G ZR／ZR+） | I71: —
A72: g_dci_29 | B72: DCI 年增 FY2029（基準路徑） | C72: % | D72: 0 | E72: 0.1 | F72: 0.2 | G72: Assumed | H72: 同上 | I72: —
A73: h2_hpc | B73: HPC 下半年 ÷ 上半年 − 1（FY2027） | C73: % | D73: -0.1 | E73: 0.08 | F73: 0.2 | G73: Assumed | H73: AWS 專案（公司未具名）第二供應商；量能波動大 | I73: —
A74: g_hpc_28 | B74: HPC 年增 FY2028（基準路徑） | C74: % | D74: -0.1 | E74: 0.15 | F74: 0.3 | G74: Assumed | H74: 同上 | I74: —
A75: g_hpc_29 | B75: HPC 年增 FY2029（基準路徑） | C75: % | D75: -0.1 | E75: 0.1 | F75: 0.2 | G75: Assumed | H75: 同上 | I75: —
A76: h2_ci | B76: 通訊基礎設施下半年 ÷ 上半年 − 1（FY2027） | C76: % | D76: 0 | E76: 0.04 | F76: 0.06 | G76: Assumed | H76: https://www.nasdaq.com/articles/fabrinet-q4-earnings-call-highlights：電信系統、衛星通訊、電信元件全面成長（公司） | I76: —
A77: g_ci_28 | B77: 通訊基礎設施年增 FY2028 | C77: % | D77: 0 | E77: 0.06 | F77: 0.1 | G77: Assumed | H77: FY2026 年增約 47%（10-K 比重推導）；高基期後放緩 | I77: —
A78: g_ci_29 | B78: 通訊基礎設施年增 FY2029 | C78: % | D78: -0.03 | E78: 0.05 | F78: 0.08 | G78: Assumed | H78: 同上 | I78: —
A79: h2_aio | B79: 車用、工業與其他下半年 ÷ 上半年 − 1（FY2027） | C79: % | D79: -0.02 | E79: 0.02 | F79: 0.05 | G79: Assumed | H79: https://www.nasdaq.com/articles/fabrinet-q4-earnings-call-highlights：EV 充電與 LiDAR（公司） | I79: —
A80: g_aio_28 | B80: 車用、工業與其他年增 FY2028 | C80: % | D80: 0 | E80: 0.05 | F80: 0.08 | G80: Assumed | H80: FY2026 年增約 10%（10-K 比重推導） | I80: —
A81: g_aio_29 | B81: 車用、工業與其他年增 FY2029 | C81: % | D81: 0 | E81: 0.05 | F81: 0.08 | G81: Assumed | H81: 同上 | I81: —
A82: F. 毛利率、費用、稅率、股數（non-GAAP；毛利率低＝情境 C、基準＝B、高＝A）
A83: gm_27 | B83: non-GAAP 毛利率 FY2027 | C83: % | D83: 0.118 | E83: 0.123 | F83: 0.127 | G83: Assumed | H83: https://www.sec.gov/Archives/edgar/data/0001408710/000140871026000026/fn-2026811xex991q426.htm：FY2026 12.2%、FY2025 12.4% | I83: https://www.webull.com/news/15420495044125696：Q4 12.2%（季增 10bp、年減 30bp）；規模帶來營業槓桿（公司）
A84: gm_28 | B84: non-GAAP 毛利率 FY2028 | C84: % | D84: 0.115 | E84: 0.123 | F84: 0.128 | G84: Assumed | H84: 同上；新廠爬坡期壓毛利（低值） | I84: —
A85: gm_29 | B85: non-GAAP 毛利率 FY2029 | C85: % | D85: 0.113 | E85: 0.123 | F85: 0.128 | G85: Assumed | H85: 同上 | I85: —
A86: phi | B86: 營業費用成長對營收成長的彈性 | C86: x | D86: 0.1 | E86: =Q!B24 -> 0.21353845 | F86: 0.6 | G86: Derived | H86: FY2026 non-GAAP 營業費用年增 ÷ 營收年增（Q 頁） | I86: https://www.webull.com/news/15420495044125696：營業費用約占營收 1.3%（Q4）
A87: opx_adj | B87: 營業費用額外占營收比（Sens 用；基準 0） | C87: pt | D87: -0.002 | E87: 0 | F87: 0.005 | G87: Assumed | H87: 無 | I87: Sens 用 +0.5 個百分點
A88: int_f | B88: non-GAAP 業外淨收益（利息、匯兌、其他；FY2027 起，每年） | C88: US$B | D88: 0.02 | E88: 0.03 | F88: 0.04 | G88: Assumed | H88: https://www.sec.gov/Archives/edgar/data/0001408710/000140871026000026/fn-2026811xex991q426.htm：FY2026 利息收入 3,240 萬美元；現金與短期投資 8.75 億美元（2026-06） | I88: 資本支出（FY2026 2.53 億美元）使現金下降
A89: tx | B89: non-GAAP 稅率（不含 Pillar Two 補充稅） | C89: % | D89: 0.04 | E89: 0.05 | F89: 0.06 | G89: Assumed | H89: FY2026 non-GAAP 約 4.6%（Q 頁推導：GAAP 稅 8,209 萬 − Pillar Two 5,745 萬） | I89: 泰國 BOI 租稅優惠；明細：未找到
A90: p2 | B90: Pillar Two 補充稅占稅前（Sens 用；non-GAAP 排除） | C90: pt | E90: 0.09 | G90: Derived | H90: https://www.sec.gov/Archives/edgar/data/0001408710/000140871026000026/fn-2026811xex991q426.htm：FY2027 Q1 指引排除 Pillar Two 每股 0.40 美元（約 1,450 萬美元／季） | I90: https://www.sec.gov/Archives/edgar/data/0001408710/000140871026000028/fn-20260626.htm：泰國 UTPR 已立法；FY2026 認列 5,745 萬美元（現金尚未支付）
A91: sh_q1 | B91: FY2027 Q1 稀釋股數（指引） | C91: 十億股 | E91: 0.0363 | G91: Interested-party | H91: https://www.sec.gov/Archives/edgar/data/0001408710/000140871026000026/fn-2026811xex991q426.htm：約 3,630 萬股（公司指引） | I91: https://www.sec.gov/Archives/edgar/data/0001408710/000140871026000028/fn-20260626.htm：普通股 35,834,864 股（2026-08-07）
A92: sh_g | B92: 股數年變動 | C92: % | D92: -0.01 | E92: 0 | F92: 0.01 | G92: Assumed | H92: https://www.sec.gov/Archives/edgar/data/0001408710/000140871026000026/fn-2026811xex991q426.htm：FY2026 回購 520 萬美元（FY2025 1.26 億）；剩餘授權約 1.69 億 | I92: 股票薪酬稀釋約抵回購
A93: mf | B93: AI 市場係數（Sens 用；CY2027 起） | C93: x | D93: 0.8 | E93: 1 | F93: 1.2 | G93: Assumed | H93: 網通模型 CY2027 可插拔光模組 +84% | I93: ±20%
A94: G. FY2025、FY2026 實績（non-GAAP；US$B）
A95: a25_rev_in | B95: FY2025 營收 | C95: US$B | E95: 3.419327 | G95: Verified | H95: https://www.sec.gov/Archives/edgar/data/0001408710/000140871026000026/fn-2026811xex991q426.htm：3,419,327 | I95: https://stockanalysis.com/stocks/fn/financials/：營收 3,419 百萬美元（stockanalysis）
A96: a26_rev_in | B96: FY2026 營收 | C96: US$B | E96: 4.641097 | G96: Verified | H96: https://www.sec.gov/Archives/edgar/data/0001408710/000140871026000026/fn-2026811xex991q426.htm：4,641,097 千美元 | I96: https://stockanalysis.com/stocks/fn/financials/：營收 4,641 百萬美元
A97: a25_dcp_in | B97: FY2025 資料中心占營收（新分類） | C97: % | E97: 0.462 | G97: Verified | H97: https://www.sec.gov/Archives/edgar/data/0001408710/000140871026000028/fn-20260626.htm：46.2% | I97: —
A98: a26_dcp_in | B98: FY2026 資料中心占營收（新分類） | C98: % | E98: 0.479 | G98: Verified | H98: https://www.sec.gov/Archives/edgar/data/0001408710/000140871026000028/fn-20260626.htm：47.9%（10-K） | I98: https://www.nasdaq.com/articles/fabrinet-q4-earnings-call-highlights：Q4 資料中心 51%
A99: a25_cip_in | B99: FY2025 通訊基礎設施占營收 | C99: % | E99: 0.307 | G99: Verified | H99: https://www.sec.gov/Archives/edgar/data/0001408710/000140871026000028/fn-20260626.htm：30.7% | I99: —
A100: a26_cip_in | B100: FY2026 通訊基礎設施占營收 | C100: % | E100: 0.333 | G100: Verified | H100: https://www.sec.gov/Archives/edgar/data/0001408710/000140871026000028/fn-20260626.htm：33.3%（10-K） | I100: —
A101: a25_aiop_in | B101: FY2025 車用、工業與其他占營收 | C101: % | E101: 0.231 | G101: Verified | H101: https://www.sec.gov/Archives/edgar/data/0001408710/000140871026000028/fn-20260626.htm：23.1% | I101: —
A102: a26_aiop_in | B102: FY2026 車用、工業與其他占營收 | C102: % | E102: 0.188 | G102: Verified | H102: https://www.sec.gov/Archives/edgar/data/0001408710/000140871026000028/fn-20260626.htm：18.8%（10-K） | I102: —
A103: a25_gp_in | B103: FY2025 non-GAAP 毛利 | C103: % | E103: 0.423805 | G103: Verified | H103: https://www.sec.gov/Archives/edgar/data/0001408710/000140871026000028/fn-20260626.htm：423,805 | I103: —
A104: a26_gp_in | B104: FY2026 non-GAAP 毛利 | C104: % | E104: 0.56797 | G104: Verified | H104: https://www.sec.gov/Archives/edgar/data/0001408710/000140871026000028/fn-20260626.htm：567,970 | I104: —
A105: a25_op_in | B105: FY2025 non-GAAP 營業利益 | C105: % | E105: 0.360712 | G105: Verified | H105: https://www.sec.gov/Archives/edgar/data/0001408710/000140871026000028/fn-20260626.htm：360,712 | I105: —
A106: a26_op_in | B106: FY2026 non-GAAP 營業利益 | C106: % | E106: 0.500063 | G106: Verified | H106: https://www.sec.gov/Archives/edgar/data/0001408710/000140871026000028/fn-20260626.htm：500,063 | I106: —
A107: a25_tax_in | B107: FY2025 non-GAAP 所得稅（GAAP 稅 − Pillar Two） | C107: US$B | E107: 0.022653 | G107: Verified | H107: https://www.sec.gov/Archives/edgar/data/0001408710/000140871026000026/fn-2026811xex991q426.htm：22,653 | I107: —
A108: a26_tax_in | B108: FY2026 non-GAAP 所得稅（GAAP 稅 − Pillar Two） | C108: US$B | E108: =0.082086-0.057447 -> 0.024639 | G108: Verified | H108: https://www.sec.gov/Archives/edgar/data/0001408710/000140871026000026/fn-2026811xex991q426.htm：82,086 − 57,447 | I108: —
A109: a25_ni_in | B109: FY2025 non-GAAP 淨利 | C109: US$B | E109: 0.368792 | G109: Verified | H109: https://www.sec.gov/Archives/edgar/data/0001408710/000140871026000026/fn-2026811xex991q426.htm：368,792 | I109: —
A110: a26_ni_in | B110: FY2026 non-GAAP 淨利 | C110: US$B | E110: 0.510907 | G110: Verified | H110: https://www.sec.gov/Archives/edgar/data/0001408710/000140871026000026/fn-2026811xex991q426.htm：510,907 | I110: —
A111: a25_eps_in | B111: FY2025 non-GAAP 稀釋 EPS | C111: US$ | E111: 10.17 | G111: Verified | H111: https://www.sec.gov/Archives/edgar/data/0001408710/000140871026000026/fn-2026811xex991q426.htm：10.17 | I111: —
A112: a26_eps_in | B112: FY2026 non-GAAP 稀釋 EPS | C112: US$ | E112: 14.09 | G112: Verified | H112: https://www.sec.gov/Archives/edgar/data/0001408710/000140871026000026/fn-2026811xex991q426.htm：14.09 美元 | I112: https://www.webull.com/news/15420495044125696：14.09 美元（法說會）
A113: a25_sh_in | B113: FY2025 稀釋股數 | C113: 十億股 | E113: 0.036267 | G113: Verified | H113: https://www.sec.gov/Archives/edgar/data/0001408710/000140871026000026/fn-2026811xex991q426.htm：36,267 | I113: —
A114: a26_sh_in | B114: FY2026 稀釋股數 | C114: 十億股 | E114: 0.036252 | G114: Verified | H114: https://www.sec.gov/Archives/edgar/data/0001408710/000140871026000026/fn-2026811xex991q426.htm：36,252 千股 | I114: —
...

Sheet Q
A1: Q — 實績與季度拆分（十億美元；EPS 為美元；股數為十億股；non-GAAP）。藍字＝輸入（In 頁）；黑字＝公式。FY(t)＝t−1 年 7 月～t 年 6 月
A2: 資料中心內的光模組、DCI、HPC 金額只在法說會揭露：光模組與其他＝資料中心 − DCI − HPC。FY2026 Q3 通訊基礎設施＝Q4 ÷（1＋季增 1%），車用工業＝營收 − 其他兩類。FY2027 Q1：各類別依季增假設，資料中心＝營收指引中點 − 通訊 − 車用工業；Q2 依季增假設。FY2027 Q1 季報（預估 2026-11-02）公布後以實績取代
A3: 項目 | B3: FY2025A | C3: FY2026A | D3: FY2026 Q3 | E3: FY2026 Q4 | F3: FY2027 Q1（指引） | G3: FY2027 Q2（假設） | H3: 標記 | I3: 說明
A4: 營收 | B4: =a25_rev_in -> 3.419327 | C4: =a26_rev_in -> 4.641097 | D4: =q3_rev -> 1.2143 | E4: =q4_rev -> 1.315788 | F4: =q1_rev -> 1.4 | G4: =G5+G9+G10 -> 1.4846651 | H4: Verified／Interested-party（指引）
A5: 資料中心 | B5: =a25_rev_in*a25_dcp_in -> 1.5797291 | C5: =a26_rev_in*a26_dcp_in -> 2.2230855 | D5: =q3_dc -> 0.592 | E5: =q4_dc -> 0.6693 | F5: =F4-F9-F10 -> 0.736441 | G5: =G6+G7+G8 -> 0.80358208 | H5: Verified（比重）／Interested-party（季） | I5: FY2025、FY2026＝營收 × 10-K 比重；FY2027 Q1＝指引中點 − 通訊 − 車用工業
A6: 光模組與其他（資料中心 − DCI − HPC） | B6: =B5-B7-B8 -> 1.1691744 | C6: =C5-C7-C8 -> 1.1638855 | D6: =D5-D7-D8 -> 0.2884 | E6: =E5-E7-E8 -> 0.2954 | F6: =F5-F7-F8 -> 0.325151 | G6: =F6*(1+q2_tg) -> 0.35116308 | H6: Derived／Assumed | I6: NVIDIA 光模組代工與其他客戶光模組；Q2 依季增假設
A7: DCI（資料中心互連） | B7: =dci_q1_25+dci_q2/(1+dci_y2)+dci_q3/(1+dci_y3)+dci_q4_25 -> 0.41055471 | C7: =dci_q1+dci_q2+dci_q3+dci_q4 -> 0.7331 | D7: =dci_q3 -> 0.1969 | E7: =dci_q4 -> 0.2559 | F7: =E7*(1+q_dcig) -> 0.28149 | G7: =F7*(1+q_dcig) -> 0.309639 | H7: Interested-party／Assumed | I7: FY2025＝Q1 假設＋Q2、Q3 由年增率回推＋Q4 實績
A8: HPC（高效能運算） | B8: =0 -> 0 | C8: =hpc_q1+hpc_q2+hpc_q3+hpc_q4 -> 0.3261 | D8: =hpc_q3 -> 0.1067 | E8: =hpc_q4 -> 0.118 | F8: =E8*(1+q_hpg) -> 0.1298 | G8: =F8*(1+q_hpg) -> 0.14278 | H8: Interested-party／Assumed | I8: FY2025 視為 0（HPC 自 FY2026 Q1 起量，約 0.15 億美元）
A9: 通訊基礎設施（電信系統、衛星通訊、電信元件） | B9: =a25_rev_in*a25_cip_in -> 1.0497334 | C9: =a26_rev_in*a26_cip_in -> 1.5454853 | D9: =q4_ci/(1+q4_cig) -> 0.40881188 | E9: =q4_ci -> 0.4129 | F9: =E9*(1+q_cig) -> 0.425287 | G9: =F9*(1+q_cig) -> 0.43804561 | H9: Verified／Derived
A10: 車用、工業與其他（EV 充電、LiDAR、工業雷射、醫療） | B10: =a25_rev_in*a25_aiop_in -> 0.78986454 | C10: =a26_rev_in*a26_aiop_in -> 0.87252624 | D10: =D4-D5-D9 -> 0.21348812 | E10: =q4_aio -> 0.2336 | F10: =E10*(1+q_aig) -> 0.238272 | G10: =F10*(1+q_aig) -> 0.24303744 | H10: Verified／Derived
A11: non-GAAP 毛利 | B11: =a25_gp_in -> 0.423805 | C11: =a26_gp_in -> 0.56797 | F11: =F4*q1_gm -> 0.1708 | H11: Verified
A12: non-GAAP 毛利率 | B12: =B11/B4 -> 0.12394398 | C12: =C11/C4 -> 0.12237839 | F12: =F11/F4 -> 0.122 | H12: Derived
A13: non-GAAP 營業費用（毛利 − 營業利益） | B13: =a25_gp_in-a25_op_in -> 0.063093 | C13: =a26_gp_in-a26_op_in -> 0.067907 | F13: =q1_opx -> 0.0195 | H13: Derived
A14: non-GAAP 營業利益 | B14: =B11-B13 -> 0.360712 | C14: =C11-C13 -> 0.500063 | F14: =F11-F13 -> 0.1513 | H14: Derived
A15: non-GAAP 業外淨收益（淨利＋稅 − 營業利益） | B15: =a25_ni_in+a25_tax_in-a25_op_in -> 0.030733 | C15: =a26_ni_in+a26_tax_in-a26_op_in -> 0.035483 | F15: =int_f/4 -> 0.0075 | H15: Derived | I15: 利息收入、匯兌、其他；FY2026 排除非上市股權重估利益 5,674 萬美元
A16: non-GAAP 稅率 | B16: =a25_tax_in/(B14+B15) -> 0.057870199 | C16: =a26_tax_in/(C14+C15) -> 0.046007252 | F16: =tx -> 0.05 | H16: Derived
A17: non-GAAP 淨利 | B17: =a25_ni_in -> 0.368792 | C17: =a26_ni_in -> 0.510907 | F17: =(F14+F15)*(1-F16) -> 0.15086 | H17: Verified／Derived
A18: 稀釋股數 | B18: =a25_sh_in -> 0.036267 | C18: =a26_sh_in -> 0.036252 | F18: =sh_q1 -> 0.0363 | H18: Verified
A19: non-GAAP 稀釋 EPS | B19: =B17/B18 -> 10.168804 | C19: =C17/C18 -> 14.093209 | F19: =F17/F18 -> 4.1559229 | H19: Derived | I19: FY2027 Q1 指引中點 4.175
A21: 推導量
A22: FY2026 營收年增 | B22: =C4/B4-1 -> 0.357313
A23: FY2026 營業費用年增 | B23: =C13/B13-1 -> 0.076300065
A24: 營業費用彈性（營業費用年增 ÷ 營收年增；In 頁 phi 的依據） | B24: =B23/B22 -> 0.21353845
A25: CY2026 光模組與其他（FY2026 Q3＋Q4＋FY2027 Q1＋Q2；份額校準基礎） | B25: =D6+E6+F6+G6 -> 1.2601141
A26: CY2026 下半年光模組與其他（＝FY2027 上半年） | B26: =F6+G6 -> 0.67631408
A27: CY2026 上半年光模組 ÷ 全年（hw 的依據） | B27: =(D6+E6)/B25 -> 0.46329139
A28: FY2027 Q1 EPS（模型，指引中點）÷ 公司 EPS 指引中點 − 1 | B28: =F19/q1_eps-1 -> -0.0045693736
A29: FY2026 NVIDIA 營收（16.3% × 營收）÷ 光模組與其他 | B29: =nv26*C4/C6 -> 0.64997703
A30: FY2026 資料中心 ÷ 營收 | B30: =C5/C4 -> 0.479
A31: FY2027 上半年 DCI（Q1＋Q2） | B31: =F7+G7 -> 0.591129
A32: FY2027 上半年 HPC | B32: =F8+G8 -> 0.27258
A33: FY2027 上半年通訊基礎設施 | B33: =F9+G9 -> 0.86333261
A34: FY2027 上半年車用、工業與其他 | B34: =F10+G10 -> 0.48130944

Sheet Units
A1: Units — Fabrinet 在 AI 光模組的有效份額（日曆年）。市場取自 markets/network（加速器顆數 × 每顆光學內容；美元）；份額口徑與中際旭創、Coherent 模型一致（光模組營收 ÷ 可插拔市場），與中際旭創相加須低於 100%
A3: 項目 | B3: 單位 | C3: CY2026 | D3: CY2027 | E3: CY2028 | F3: CY2029 | G3: 說明
A4: AI 可插拔光模組市場（情境 A） | B4: US$B | C4: =PL!D63 -> 29.753262 | D4: =PL!E63 -> 53.560715 | E4: =PL!F63 -> 57.9915 | F4: =PL!G63 -> 72.9348 | G4: markets/network Mkt 頁
A5: AI CPO 光學市場（情境 A） | B5: US$B | C5: =PL!D64 -> 0.300538 | D5: =PL!E64 -> 2.818985 | E5: =PL!F64 -> 6.4435 | F5: =PL!G64 -> 11.74736 | G5: 同上
A6: Fabrinet 光模組有效份額（情境 A） | B6: % | C6: =PL!D67 -> 0.042352132 | D6: =PL!E67 -> 0.048704952 | E6: =PL!F67 -> 0.052940165 | F6: =PL!G67 -> 0.055057772 | G6: CY2026 以 FY2026 下半年實績推導＋FY2027 Q1 指引推導＋Q2 假設校準；情境 A 份額取高值
A7: 中際旭創可插拔有效份額（innolight/dist） | B7: % | C7: =inl_26 -> 0.42183339 | D7: =inl_27 -> 0.40074172 | E7: =inl_28 -> 0.37965005 | F7: =inl_29 -> 0.35855838 | G7: 唯讀上游
A8: 兩者合計 | B8: % | C8: =C6+C7 -> 0.46418552 | D8: =D6+D7 -> 0.44944667 | E8: =E6+E7 -> 0.43259021 | F8: =F6+F7 -> 0.41361615 | G8: 須低於 100%；其餘由新易盛、Coherent、Lumentum 等分配
A9: Fabrinet 光模組與其他營收（情境 A；日曆年） | B9: US$B | C9: =PL!D70 -> 1.2601141 | D9: =PL!E70 -> 3.0315198 | E9: =PL!F70 -> 4.3587796 | F9: =PL!G70 -> 6.9524676
A10: 其他廠商＝ 可插拔＋CPO − 中際旭創 − Fabrinet | B10: US$B | C10: =C4+C5-C7*C4-C9 -> 16.242767 | D10: =D4+D5-D7*D4-D9 -> 31.884167 | E10: =E4+E5-E7*E4-E9 -> 38.059745 | F10: =F4+F5-F7*F4-F9 -> 51.578309 | G10: 中際旭創以可插拔份額近似（其 CPO 份額不扣）
A11: Fabrinet 資料中心光模組營收 ÷ AI IT 資本支出 | B11: % | C11: =PL!D70/itc_26 -> 0.001611661 | D11: =PL!E70/itc_27 -> 0.0019366402 | E11: =PL!F70/itc_28 -> 0.0021966733 | F11: =PL!G70/itc_29 -> 0.0030757819 | G11: markets/network 的 AI IT 資本支出
A12: 核對：兩者合計最大值 < 100%（1＝通過） | C12: =IF(MAX(C8:F8)<1,1,0) -> 1
A14: 讀法：Fabrinet 是代工廠，光模組營收含 NVIDIA 等客戶自有品牌的模組，與中際旭創、Coherent 的出貨口徑不同，所以是「有效」份額；NVIDIA 占營收由 27.6% 降到 16.3%，份額相對值與 CPO 份額是 Assumed，是最需要每季檢查的輸入。

Sheet PL
A1: PL — Fabrinet 損益（US$B；non-GAAP）。FY2025A、FY2026A（錨點）為實績，FY2027 起為模型。FY(t)＝t−1 年 7 月～t 年 6 月。三情境各一個完整推導區塊（本頁下方），頂端為摘要。顆數係數從 CY2028 開始；FY2027 的情境差異只來自公司特有變數（份額、CPO 份額、毛利率）
A2: 灰底＝FY2030–FY2032 收斂法，非驅動因子推導（上游市場層只到 2029）：營收年增由 FY2029 線性收斂到 fade_g（A＝tp_g＋2pt、B＝tp_g、C＝tp_g−2pt），淨利率由 FY2029 線性收斂到 fade_m（A＝FY2029、B＝FY2029 與十年平均的中點、C＝十年平均；In 頁 K 節），FY2032 達到；股數依 sh_g
A3: 情境／項目 | B3: 單位 | C3: FY2025A | D3: FY2026A（錨點） | E3: FY2027 | F3: FY2028 | G3: FY2029 | H3: FY2030（收斂） | I3: FY2031（收斂） | J3: FY2032（收斂） | K3: 說明
A4: 情境 A
A5: 營收 | B5: US$B | C5: =C81 -> 3.419327 | D5: =D81 -> 4.641097 | E5: =E81 -> 6.6244167 | F5: =F81 -> 8.6856306 | G5: =G81 -> 10.955418 | H5: =H81 -> 13.083156 | I5: =I81 -> 14.746141 | J5: =J81 -> 15.63091
A6: 營收年增 | B6: % | D6: =D82 -> 0.357313 | E6: =E82 -> 0.42733855 | F6: =F82 -> 0.31115403 | G6: =G82 -> 0.26132674 | H6: =H82 -> 0.19421782 | I6: =I82 -> 0.12710891 | J6: =J82 -> 0.06
A7: 資料中心 | B7: US$B | C7: =C78 -> 1.5797291 | D7: =D78 -> 2.2230855 | E7: =E78 -> 3.8909731 | F7: =F78 -> 5.7979028 | G7: =G78 -> 7.9233039
A8: 光模組與其他 | B8: US$B | C8: =C73 -> 1.1691744 | D8: =D73 -> 1.1638855 | E8: =E73 -> 2.0708132 | F8: =F73 -> 3.6420593 | G8: =G73 -> 5.5518761
A9: DCI | B9: US$B | C9: =C75 -> 0.41055471 | D9: =D75 -> 0.7331 | E9: =E75 -> 1.2531935 | F9: =F75 -> 1.5038322 | G9: =G75 -> 1.6542154
A10: HPC | B10: US$B | C10: =C77 -> 0 | D10: =D77 -> 0.3261 | E10: =E77 -> 0.5669664 | F10: =F77 -> 0.65201136 | G10: =G77 -> 0.7172125
A11: 通訊基礎設施 | B11: US$B | C11: =C79 -> 1.0497334 | D11: =D79 -> 1.5454853 | E11: =E79 -> 1.7611985 | F11: =F79 -> 1.8668704 | G11: =G79 -> 1.960214
A12: 車用、工業與其他 | B12: US$B | C12: =C80 -> 0.78986454 | D12: =D80 -> 0.87252624 | E12: =E80 -> 0.97224507 | F12: =F80 -> 1.0208573 | G12: =G80 -> 1.0719002
A13: 毛利率 | B13: % | C13: =C85 -> 0.12394398 | D13: =D85 -> 0.12237839 | E13: =E85 -> 0.127 | F13: =F85 -> 0.128 | G13: =G85 -> 0.128
A14: 營業利益率 | B14: % | C14: =C90 -> 0.1054921 | D14: =D90 -> 0.10774672 | E14: =E90 -> 0.11581355 | F14: =F90 -> 0.11890136 | G14: =G90 -> 0.12038391
A15: 淨利 | B15: US$B | C15: =C93 -> 0.368792 | D15: =D93 -> 0.510907 | E15: =E93 -> 0.75733732 | F15: =F93 -> 1.0095966 | G15: =G93 -> 1.2814133 | H15: =H93 -> 1.5302866 | I15: =I93 -> 1.7247997 | J15: =J93 -> 1.8282876
A16: EPS | B16: US$ | C16: =C96 -> 10.168804 | D16: =D96 -> 14.093209 | E16: =E96 -> 20.863287 | F16: =F96 -> 27.812579 | G16: =G96 -> 35.300642 | H16: =H96 -> 42.156655 | I16: =I96 -> 47.515142 | J16: =J96 -> 50.36605
A17: EPS 年增 | B17: % | D17: =D97 -> 0.38592594 | E17: =E97 -> 0.48037879 | F17: =F97 -> 0.3330871 | G17: =G97 -> 0.26923294 | H17: =H97 -> 0.19421782 | I17: =I97 -> 0.12710891 | J17: =J97 -> 0.06
A19: 情境 B
A20: 營收 | B20: US$B | C20: =C121 -> 3.419327 | D20: =D121 -> 4.641097 | E20: =E121 -> 6.3342561 | F20: =F121 -> 7.2142358 | G20: =G121 -> 7.8272266 | H20: =H121 -> 8.3749738 | I20: =I121 -> 8.8355125 | J20: =J121 -> 9.188933
A21: 營收年增 | B21: % | D21: =D122 -> 0.357313 | E21: =E122 -> 0.36481873 | F21: =F122 -> 0.13892392 | G21: =G122 -> 0.084969602 | H21: =H122 -> 0.069979735 | I21: =I122 -> 0.054989867 | J21: =J122 -> 0.04
A22: 資料中心 | B22: US$B | C22: =C118 -> 1.5797291 | D22: =D118 -> 2.2230855 | E22: =E118 -> 3.6008125 | F22: =F118 -> 4.3265081 | G22: =G118 -> 4.7951124
A23: 光模組與其他 | B23: US$B | C23: =C113 -> 1.1691744 | D23: =D113 -> 1.1638855 | E23: =E113 -> 1.7806527 | F23: =F113 -> 2.3690021 | G23: =G113 -> 2.8434273
A24: DCI | B24: US$B | C24: =C115 -> 0.41055471 | D24: =D115 -> 0.7331 | E24: =E115 -> 1.2531935 | F24: =F115 -> 1.3654796 | G24: =G115 -> 1.3614193
A25: HPC | B25: US$B | C25: =C117 -> 0 | D25: =D117 -> 0.3261 | E25: =E117 -> 0.5669664 | F25: =F117 -> 0.59202631 | G25: =G117 -> 0.59026588
A26: 通訊基礎設施 | B26: US$B | C26: =C119 -> 1.0497334 | D26: =D119 -> 1.5454853 | E26: =E119 -> 1.7611985 | F26: =F119 -> 1.8668704 | G26: =G119 -> 1.960214
A27: 車用、工業與其他 | B27: US$B | C27: =C120 -> 0.78986454 | D27: =D120 -> 0.87252624 | E27: =E120 -> 0.97224507 | F27: =F120 -> 1.0208573 | G27: =G120 -> 1.0719002
A28: 毛利率 | B28: % | C28: =C125 -> 0.12394398 | D28: =D125 -> 0.12237839 | E28: =E125 -> 0.123 | F28: =F125 -> 0.123 | G28: =G125 -> 0.123
A29: 營業利益率 | B29: % | C29: =C130 -> 0.1054921 | D29: =D130 -> 0.10774672 | E29: =E130 -> 0.11144424 | F29: =F130 -> 0.1125528 | G29: =G130 -> 0.11319626
A30: 淨利 | B30: US$B | C30: =C133 -> 0.368792 | D30: =D133 -> 0.510907 | E30: =E133 -> 0.69912054 | F30: =F133 -> 0.7998833 | G30: =G133 -> 0.87021214 | H30: =H133 -> 0.89087098 | I30: =I133 -> 0.89740877 | J30: =J133 -> 0.889156
A31: EPS | B31: US$ | C31: =C136 -> 10.168804 | D31: =D136 -> 14.093209 | E31: =E136 -> 19.259519 | F31: =F136 -> 22.035353 | G31: =G136 -> 23.972786 | H31: =H136 -> 24.5419 | I31: =I136 -> 24.722005 | J31: =J136 -> 24.494656
A32: EPS 年增 | B32: % | D32: =D137 -> 0.38592594 | E32: =E137 -> 0.36658155 | F32: =F137 -> 0.14412788 | G32: =G137 -> 0.087923871 | H32: =H137 -> 0.023740003 | I32: =I137 -> 0.0073386582 | J32: =J137 -> -0.0091962234
A34: 情境 C
A35: 營收 | B35: US$B | C35: =C161 -> 3.419327 | D35: =D161 -> 4.641097 | E35: =E161 -> 6.0910539 | F35: =F161 -> 6.1798837 | G35: =G161 -> 5.6866902 | H35: =H161 -> 5.4220458 | I35: =I161 -> 5.350102 | J35: =J161 -> 5.457104
A36: 營收年增 | B36: % | D36: =D162 -> 0.357313 | E36: =E162 -> 0.31241685 | F36: =F162 -> 0.014583644 | G36: =G162 -> -0.079806271 | H36: =H162 -> -0.046537514 | I36: =I162 -> -0.013268757 | J36: =J162 -> 0.02
A37: 資料中心 | B37: US$B | C37: =C158 -> 1.5797291 | D37: =D158 -> 2.2230855 | E37: =E158 -> 3.3576103 | F37: =F158 -> 3.2921559 | G37: =G158 -> 2.6545761
A38: 光模組與其他 | B38: US$B | C38: =C153 -> 1.1691744 | D38: =D153 -> 1.1638855 | E38: =E153 -> 1.5374505 | F38: =F153 -> 1.5329876 | G38: =G153 -> 1.2317193
A39: DCI | B39: US$B | C39: =C155 -> 0.41055471 | D39: =D155 -> 0.7331 | E39: =E155 -> 1.2531935 | F39: =F155 -> 1.2271271 | G39: =G155 -> 0.99252924
A40: HPC | B40: US$B | C40: =C157 -> 0 | D40: =D157 -> 0.3261 | E40: =E157 -> 0.5669664 | F40: =F157 -> 0.53204127 | G40: =G157 -> 0.4303275
A41: 通訊基礎設施 | B41: US$B | C41: =C159 -> 1.0497334 | D41: =D159 -> 1.5454853 | E41: =E159 -> 1.7611985 | F41: =F159 -> 1.8668704 | G41: =G159 -> 1.960214
A42: 車用、工業與其他 | B42: US$B | C42: =C160 -> 0.78986454 | D42: =D160 -> 0.87252624 | E42: =E160 -> 0.97224507 | F42: =F160 -> 1.0208573 | G42: =G160 -> 1.0719002
A43: 毛利率 | B43: % | C43: =C165 -> 0.12394398 | D43: =D165 -> 0.12237839 | E43: =E165 -> 0.118 | F43: =F165 -> 0.115 | G43: =G165 -> 0.113
A44: 營業利益率 | B44: % | C44: =C170 -> 0.1054921 | D44: =D170 -> 0.10774672 | E44: =E170 -> 0.10610759 | F44: =F170 -> 0.10324203 | G44: =G170 -> 0.10022229
A45: 淨利 | B45: US$B | C45: =C173 -> 0.368792 | D45: =D173 -> 0.510907 | E45: =E173 -> 0.64249173 | F45: =F173 -> 0.63462257 | G45: =G173 -> 0.56993648 | H45: =H173 -> 0.51111052 | I45: =I173 -> 0.47245481 | J45: =J173 -> 0.44939252
A46: EPS | B46: US$ | C46: =C176 -> 10.168804 | D46: =D176 -> 14.093209 | E46: =E176 -> 17.699497 | F46: =F176 -> 17.482716 | G46: =G176 -> 15.700729 | H46: =H176 -> 14.08018 | I46: =I176 -> 13.015284 | J46: =J176 -> 12.379959
A47: EPS 年增 | B47: % | D47: =D177 -> 0.38592594 | E47: =E177 -> 0.25588836 | F47: =F177 -> -0.01224787 | G47: =G177 -> -0.10192845 | H47: =H177 -> -0.10321493 | I47: =I177 -> -0.07563083 | J47: =J177 -> -0.048813756
A49: 核對（應為 0）：FY2026 模型與實績（校準恆等式）
A50: 情境 B：營收差（US$B） | D50: =D121-a26_rev_in -> 0
A51: 情境 B：營業利益差（US$B；公司揭露 0.500063） | D51: =D129-0.500063 -> 0
A52: 情境 B：EPS 差（公司揭露 14.09；四捨五入差應小於 0.01） | D52: =D136-a26_eps_in -> 0.0032086506
A53: 情境 B：CY2026 光模組 − 可插拔市場 × 有效份額 | D53: =D110-D103*D107 -> 0
A60: 情境 A（順利）：顆數係數 1.0、網通 CPO 情境 A（替代快）；份額、CPO 份額、毛利率取高值
A61: 項目 | B61: 單位 | C61: FY2025A | D61: FY2026A（錨點） | E61: FY2027 | F61: FY2028 | G61: FY2029 | H61: FY2030（收斂） | I61: FY2031（收斂） | J61: FY2032（收斂） | K61: 說明
A62: A. 日曆年 AI 光學（本節 D–G 欄＝CY2026–CY2029；D 欄＝CY2026 校準年）
A63: AI 可插拔光模組市場 × 情境顆數係數（日曆年） | B63: US$B | D63: =mpl_26*1 -> 29.753262 | E63: =mpl_27*1*1 -> 53.560715 | F63: =mpl_28*um28_A*1 -> 57.9915 | G63: =mpl_29*um29_A*1 -> 72.9348 | K63: 本節欄位為日曆年
A64: AI CPO 光學市場 × 情境顆數係數（日曆年） | B64: US$B | D64: =mcp_26*1 -> 0.300538 | E64: =mcp_27*1 -> 2.818985 | F64: =mcp_28*um28_A -> 6.4435 | G64: =mcp_29*um29_A -> 11.74736
A65: Fabrinet 光模組有效份額（CY2026 校準）＝ CY2026 光模組與其他 ÷ 可插拔市場 | B65: % | D65: =tr_cy26/D63 -> 0.042352132 | K65: Derived：CY2026 CPO 營收視為 0；代工營收含料件，屬「有效」份額
A66: 份額相對值（÷ CY2026） | B66: x | D66: =1 -> 1 | E66: =RHI_27 -> 1.15 | F66: =RHI_28 -> 1.25 | G66: =RHI_29 -> 1.3
A67: 光模組有效份額（日曆年） | B67: % | D67: =$D$65*D66 -> 0.042352132 | E67: =$D$65*E66 -> 0.048704952 | F67: =$D$65*F66 -> 0.052940165 | G67: =$D$65*G66 -> 0.055057772
A68: 單價係數（相對網通模型） | B68: x | D68: =1 -> 1 | E68: =pxr_27 -> 1 | F68: =pxr_28 -> 1 | G68: =pxr_29 -> 1
A69: Fabrinet 占 CPO 光學金額 | B69: % | D69: =0 -> 0 | E69: =CPHI_27 -> 0.15 | F69: =CPHI_28 -> 0.2 | G69: =CPHI_29 -> 0.25
A70: 光模組與其他營收（日曆年） | B70: US$B | D70: =tr_cy26 -> 1.2601141 | E70: =E63*E67*E68+E64*E69 -> 3.0315198 | F70: =F63*F67*F68+F64*F69 -> 4.3587796 | G70: =G63*G67*G68+G64*G69 -> 6.9524676
A71: B. 會計年度營收（本節起 C–G 欄＝FY2025–FY2029）
A72: AI 情境係數（會計年度；DCI、HPC 用） | B72: x | C72: =1 -> 1 | D72: =1 -> 1 | E72: =1 -> 1 | F72: =(1-hw)+hw*um28_A -> 1 | G72: =(1-hw)*um28_A+hw*um29_A -> 1 | K72: 同字母顆數係數依日曆年上半年比重換算；FY2027 為 1
A73: 光模組與其他 | B73: US$B | C73: =a25_tr -> 1.1691744 | D73: =a26_tr -> 1.1638855 | E73: =h1_27+hw*E70 -> 2.0708132 | F73: =(1-hw)*E70+hw*F70 -> 3.6420593 | G73: =(1-hw)*F70+hw*G70 -> 5.5518761 | K73: FY2027＝CY2026 下半年（Q 頁）＋ hw × CY2027；FY2028＝（1 − hw）× CY2027 ＋ hw × CY2028
A74: DCI 基準路徑（未乘情境係數） | B74: US$B | C74: =a25_dci -> 0.41055471 | D74: =a26_dci -> 0.7331 | E74: =h1dci*(2+h2_dci) -> 1.2531935 | F74: =E74*(1+g_dci_28) -> 1.5038322 | G74: =F74*(1+g_dci_29) -> 1.6542154
A75: DCI（資料中心互連） | B75: US$B | C75: =C74*C72 -> 0.41055471 | D75: =D74*D72 -> 0.7331 | E75: =E74*E72 -> 1.2531935 | F75: =F74*F72 -> 1.5038322 | G75: =G74*G72 -> 1.6542154
A76: HPC 基準路徑（未乘情境係數） | B76: US$B | C76: =a25_hpc -> 0 | D76: =a26_hpc -> 0.3261 | E76: =h1hpc*(2+h2_hpc) -> 0.5669664 | F76: =E76*(1+g_hpc_28) -> 0.65201136 | G76: =F76*(1+g_hpc_29) -> 0.7172125
A77: HPC（高效能運算） | B77: US$B | C77: =C76*C72 -> 0 | D77: =D76*D72 -> 0.3261 | E77: =E76*E72 -> 0.5669664 | F77: =F76*F72 -> 0.65201136 | G77: =G76*G72 -> 0.7172125
A78: 資料中心 | B78: US$B | C78: =C73+C75+C77 -> 1.5797291 | D78: =D73+D75+D77 -> 2.2230855 | E78: =E73+E75+E77 -> 3.8909731 | F78: =F73+F75+F77 -> 5.7979028 | G78: =G73+G75+G77 -> 7.9233039
A79: 通訊基礎設施 | B79: US$B | C79: =a25_ci -> 1.0497334 | D79: =a26_ci -> 1.5454853 | E79: =h1ci*(2+h2_ci) -> 1.7611985 | F79: =E79*(1+g_ci_28) -> 1.8668704 | G79: =F79*(1+g_ci_29) -> 1.960214
A80: 車用、工業與其他 | B80: US$B | C80: =a25_aio -> 0.78986454 | D80: =a26_aio -> 0.87252624 | E80: =h1aio*(2+h2_aio) -> 0.97224507 | F80: =E80*(1+g_aio_28) -> 1.0208573 | G80: =F80*(1+g_aio_29) -> 1.0719002
A81: 營收 | B81: US$B | C81: =C78+C79+C80 -> 3.419327 | D81: =D78+D79+D80 -> 4.641097 | E81: =E78+E79+E80 -> 6.6244167 | F81: =F78+F79+F80 -> 8.6856306 | G81: =G78+G79+G80 -> 10.955418 | H81: =G81*(1+H82) -> 13.083156 | I81: =H81*(1+I82) -> 14.746141 | J81: =I81*(1+J82) -> 15.63091
A82: 營收年增 | B82: % | D82: =D81/C81-1 -> 0.357313 | E82: =E81/D81-1 -> 0.42733855 | F82: =F81/E81-1 -> 0.31115403 | G82: =G81/F81-1 -> 0.26132674 | H82: =$G82+(fade_gA-$G82)*1/3 -> 0.19421782 | I82: =$G82+(fade_gA-$G82)*2/3 -> 0.12710891 | J82: =$G82+(fade_gA-$G82)*3/3 -> 0.06
A83: 資料中心 ÷ 營收 | B83: % | C83: =C78/C81 -> 0.462 | D83: =D78/D81 -> 0.479 | E83: =E78/E81 -> 0.58736841 | F83: =F78/F81 -> 0.66752814 | G83: =G78/G81 -> 0.72323154
A84: C. 損益（non-GAAP）
A85: 毛利率 | B85: % | C85: =a25_gp/a25_rev -> 0.12394398 | D85: =a26_gp/a26_rev -> 0.12237839 | E85: =GMHI_27 -> 0.127 | F85: =GMHI_28 -> 0.128 | G85: =GMHI_29 -> 0.128 | K85: FY2027 起為輸入路徑（成本加成代工；新廠爬坡與料件占比）
A86: 毛利 | B86: US$B | C86: =C81*C85 -> 0.423805 | D86: =D81*D85 -> 0.56797 | E86: =E81*E85 -> 0.84130092 | F86: =F81*F85 -> 1.1117607 | G86: =G81*G85 -> 1.4022935
A87: 營業費用（基準路徑） | B87: US$B | C87: =a25_opx -> 0.063093 | D87: =a26_opx -> 0.067907 | E87: =D87*(1+MAX(0,phi*E82)) -> 0.074103732 | F87: =E87*(1+MAX(0,phi*F82)) -> 0.079027432 | G87: =F87*(1+MAX(0,phi*G82)) -> 0.083437424
A88: 營業費用 | B88: US$B | C88: =C87 -> 0.063093 | D88: =D87 -> 0.067907 | E88: =E87+0*E81 -> 0.074103732 | F88: =F87+0*F81 -> 0.079027432 | G88: =G87+0*G81 -> 0.083437424
A89: 營業利益 | B89: US$B | C89: =C86-C88 -> 0.360712 | D89: =D86-D88 -> 0.500063 | E89: =E86-E88 -> 0.76719718 | F89: =F86-F88 -> 1.0327333 | G89: =G86-G88 -> 1.3188561
A90: 營業利益率 | B90: % | C90: =C89/C81 -> 0.1054921 | D90: =D89/D81 -> 0.10774672 | E90: =E89/E81 -> 0.11581355 | F90: =F89/F81 -> 0.11890136 | G90: =G89/G81 -> 0.12038391
A91: 業外淨收益（利息、匯兌、其他） | B91: US$B | C91: =a25_oth -> 0.030733 | D91: =a26_oth -> 0.035483 | E91: =int_f -> 0.03 | F91: =int_f -> 0.03 | G91: =int_f -> 0.03
A92: 稅前利益 | B92: US$B | C92: =C89+C91 -> 0.391445 | D92: =D89+D91 -> 0.535546 | E92: =E89+E91 -> 0.79719718 | F92: =F89+F91 -> 1.0627333 | G92: =G89+G91 -> 1.3488561
A93: 淨利 | B93: US$B | C93: =a25_ni -> 0.368792 | D93: =a26_ni -> 0.510907 | E93: =E92*(1-(tx)) -> 0.75733732 | F93: =F92*(1-(tx)) -> 1.0095966 | G93: =G92*(1-(tx)) -> 1.2814133 | H93: =H81*H94 -> 1.5302866 | I93: =I81*I94 -> 1.7247997 | J93: =J81*J94 -> 1.8282876
A94: 淨利率 | B94: % | C94: =C93/C81 -> 0.10785514 | D94: =D93/D81 -> 0.11008324 | E94: =E93/E81 -> 0.11432513 | F94: =F93/F81 -> 0.11623757 | G94: =G93/G81 -> 0.11696617 | H94: =$G94+(fade_mA-$G94)*1/3 -> 0.11696617 | I94: =$G94+(fade_mA-$G94)*2/3 -> 0.11696617 | J94: =$G94+(fade_mA-$G94)*3/3 -> 0.11696617
A95: 稀釋股數 | B95: 十億股 | C95: =a25_sh -> 0.036267 | D95: =a26_sh -> 0.036252 | E95: =sh_q1*(1+sh_g) -> 0.0363 | F95: =E95*(1+sh_g) -> 0.0363 | G95: =F95*(1+sh_g) -> 0.0363 | H95: =G95*(1+sh_g) -> 0.0363 | I95: =H95*(1+sh_g) -> 0.0363 | J95: =I95*(1+sh_g) -> 0.0363
A96: EPS | B96: US$ | C96: =C93/C95 -> 10.168804 | D96: =D93/D95 -> 14.093209 | E96: =E93/E95 -> 20.863287 | F96: =F93/F95 -> 27.812579 | G96: =G93/G95 -> 35.300642 | H96: =H93/H95 -> 42.156655 | I96: =I93/I95 -> 47.515142 | J96: =J93/J95 -> 50.36605
A97: EPS 年增 | B97: % | D97: =D96/C96-1 -> 0.38592594 | E97: =E96/D96-1 -> 0.48037879 | F97: =F96/E96-1 -> 0.3330871 | G97: =G96/F96-1 -> 0.26923294 | H97: =H96/G96-1 -> 0.19421782 | I97: =I96/H96-1 -> 0.12710891 | J97: =J96/I96-1 -> 0.06
A100: 情境 B（平平）：CY2028 顆數 ×0.8、CY2029 ×0.85、網通 CPO 情境 B；公司變數取基準
A101: 項目 | B101: 單位 | C101: FY2025A | D101: FY2026A（錨點） | E101: FY2027 | F101: FY2028 | G101: FY2029 | H101: FY2030（收斂） | I101: FY2031（收斂） | J101: FY2032（收斂） | K101: 說明
A102: A. 日曆年 AI 光學（本節 D–G 欄＝CY2026–CY2029；D 欄＝CY2026 校準年）
A103: AI 可插拔光模組市場 × 情境顆數係數（日曆年） | B103: US$B | D103: =mplB_26*1 -> 29.753262 | E103: =mplB_27*1*1 -> 54.688309 | F103: =mplB_28*um28_B*1 -> 48.9706 | G103: =mplB_29*um29_B*1 -> 66.987208 | K103: 本節欄位為日曆年
A104: AI CPO 光學市場 × 情境顆數係數（日曆年） | B104: US$B | D104: =mcpB_26*1 -> 0.300538 | E104: =mcpB_27*1 -> 1.691391 | F104: =mcpB_28*um28_B -> 2.5774 | G104: =mcpB_29*um29_B -> 4.992628
A105: Fabrinet 光模組有效份額（CY2026 校準）＝ CY2026 光模組與其他 ÷ 可插拔市場 | B105: % | D105: =tr_cy26/D103 -> 0.042352132 | K105: Derived：CY2026 CPO 營收視為 0；代工營收含料件，屬「有效」份額
A106: 份額相對值（÷ CY2026） | B106: x | D106: =1 -> 1 | E106: =rel_27 -> 1 | F106: =rel_28 -> 1 | G106: =rel_29 -> 0.95
A107: 光模組有效份額（日曆年） | B107: % | D107: =$D$105*D106 -> 0.042352132 | E107: =$D$105*E106 -> 0.042352132 | F107: =$D$105*F106 -> 0.042352132 | G107: =$D$105*G106 -> 0.040234525
A108: 單價係數（相對網通模型） | B108: x | D108: =1 -> 1 | E108: =pxr_27 -> 1 | F108: =pxr_28 -> 1 | G108: =pxr_29 -> 1
A109: Fabrinet 占 CPO 光學金額 | B109: % | D109: =0 -> 0 | E109: =cpo_27 -> 0.05 | F109: =cpo_28 -> 0.1 | G109: =cpo_29 -> 0.15
A110: 光模組與其他營收（日曆年） | B110: US$B | D110: =tr_cy26 -> 1.2601141 | E110: =E103*E107*E108+E104*E109 -> 2.400736 | F110: =F103*F107*F108+F104*F109 -> 2.3317493 | G110: =G103*G107*G108+G104*G109 -> 3.4440927
A111: B. 會計年度營收（本節起 C–G 欄＝FY2025–FY2029）
...

Sheet Val
A1: Val — P/E 估值（美元；non-GAAP EPS）。目標價＝DCF 與 Comparable 加權（第 0 節）；舊法規則值情境加權保留參考；另列「現價 ÷ FY2027、FY2028 EPS（模型）」、市場隱含 EPS 與十年 P/E 規則值。十年 P/E 為 GAAP 年底 P/E（Fabrinet 每年皆獲利，十年皆列入）
A2: 循環位置：Fabrinet 不是設備股，不套設備市場見頂年；以本模型營收最高的會計年度為見頂年（比照 Coherent、中際旭創）。營收到 FY2029 仍在增加時，見頂年未知，判為中段
A4: 0. 目標價
A5: 0.1 DCF（股東權益現金流，FY2027–FY2032 明確期＋FY2032 後永續）
A6: 項目 | B6: A（順利） | C6: B（平平） | D6: C（不如預期） | E6: 說明
A7: 情境 EPS（FY2027–FY2032） | E7: PL 頁各情境；FY2030 起為收斂法（PL 頁灰底）
A8: FY2027 | B8: =PL!E16 -> 20.863287 | C8: =PL!E31 -> 19.259519 | D8: =PL!E46 -> 17.699497
A9: FY2028 | B9: =PL!F16 -> 27.812579 | C9: =PL!F31 -> 22.035353 | D9: =PL!F46 -> 17.482716
A10: FY2029 | B10: =PL!G16 -> 35.300642 | C10: =PL!G31 -> 23.972786 | D10: =PL!G46 -> 15.700729
A11: FY2030 | B11: =PL!H16 -> 42.156655 | C11: =PL!H31 -> 24.5419 | D11: =PL!H46 -> 14.08018
A12: FY2031 | B12: =PL!I16 -> 47.515142 | C12: =PL!I31 -> 24.722005 | D12: =PL!I46 -> 13.015284
A13: FY2032 | B13: =PL!J16 -> 50.36605 | C13: =PL!J31 -> 24.494656 | D13: =PL!J46 -> 12.379959
A14: 股東現金流＝EPS ×（1 − tp_g ÷ tp_roe）
A15: 再投資率（tp_g ÷ tp_roe，上限 0.8） | B15: =IF(tp_roe<=tp_g,0.8,MIN(tp_g/tp_roe,0.8)) -> 0.20836364 | E15: ROE＝In 頁 tp_roe；tp_roe ≤ tp_g 時取上限 0.8
A16: FY2027 | B16: =B8*(1-$B$15) -> 16.516137 | C16: =C8*(1-$B$15) -> 15.246536 | D16: =D8*(1-$B$15) -> 14.011565
A17: FY2028 | B17: =B9*(1-$B$15) -> 22.017449 | C17: =C9*(1-$B$15) -> 17.443986 | D17: =D9*(1-$B$15) -> 13.839953
A18: FY2029 | B18: =B10*(1-$B$15) -> 27.945272 | C18: =C10*(1-$B$15) -> 18.977729 | D18: =D10*(1-$B$15) -> 12.429268
A19: FY2030 | B19: =B11*(1-$B$15) -> 33.372741 | C19: =C11*(1-$B$15) -> 19.428261 | D19: =D11*(1-$B$15) -> 11.146382
A20: FY2031 | B20: =B12*(1-$B$15) -> 37.614714 | C20: =C12*(1-$B$15) -> 19.570838 | D20: =D12*(1-$B$15) -> 10.303372
A21: FY2032 | B21: =B13*(1-$B$15) -> 39.871597 | C21: =C13*(1-$B$15) -> 19.39086 | D21: =D13*(1-$B$15) -> 9.8004258
A22: DCF 情境每股價值（折現率 tp_r） | B22: =MAX(0,SUMPRODUCT(B16:B21,1/(1+tp_r)^{1;2;3;4;5;6})+B21*(1+tp_g)/(tp_r-tp_g)/(1+tp_r)^6) -> 512.97516 | C22: =MAX(0,SUMPRODUCT(C16:C21,1/(1+tp_r)^{1;2;3;4;5;6})+C21*(1+tp_g)/(tp_r-tp_g)/(1+tp_r)^6) -> 268.62694 | D22: =MAX(0,SUMPRODUCT(D16:D21,1/(1+tp_r)^{1;2;3;4;5;6})+D21*(1+tp_g)/(tp_r-tp_g)/(1+tp_r)^6) -> 148.94633 | E22: Σ 明確期現金流 ÷ (1＋r)^t ＋ 永續價值 ÷ (1＋r)^6；永續價值＝FY2032 現金流 ×(1＋g)÷(r−g)；基準日 2026 年底，t＝1 對 FY2027；小於 0 時取 0（股東有限責任）
A23: DCF 情境價值推到 12 個月後（×(1＋tp_r)） | B23: =B22*(1+tp_r) -> 564.27268 | C23: =C22*(1+tp_r) -> 295.48964 | D23: =D22*(1+tp_r) -> 163.84096
A24: DCF 目標價（情境加權） | B24: =tp_wA*B23+tp_wB*C23+tp_wC*D23 -> 349.79481 | E24: Σ 權重 × 情境價值 ×(1＋r)；權重見 In 頁
A26: 0.2 Comparable（市場主流同業前瞻 P/E）
A27: 同業與前瞻 P/E | B27: 代號 | C27: 前瞻 12 月 P/E | D27: 日期 | E27: 來源 | F27: 標記
A28: Coherent | B28: COHR | C28: 22.3 | D28: 2026-10-23 | E28: stockanalysis forward PE（分析師共識；價格日期如左） | F28: Interested-party
A29: Lumentum | B29: LITE | C29: 34.71 | D29: 2026-10-23 | E29: stockanalysis forward PE（分析師共識；價格日期如左） | F29: Interested-party
A30: Jabil | B30: JBL | C30: 15.49 | D30: 2026-10-23 | E30: stockanalysis forward PE（分析師共識；價格日期如左） | F30: Interested-party
A31: Celestica | B31: CLS | C31: 16.65 | D31: 2026-10-23 | E31: stockanalysis forward PE（分析師共識；價格日期如左） | F31: Interested-party
A32: Flex | B32: FLEX | C32: 14.74 | D32: 2026-10-23 | E32: stockanalysis forward PE（分析師共識；價格日期如左） | F32: Interested-party
A33: 同業前瞻 P/E 中位數 | B33: =MEDIAN(C28:C32) -> 16.65 | E33: 美股光通訊（Coherent、Lumentum）與電子代工（Jabil、Celestica、Flex）同業；不放 A 股（中際旭創、新易盛另見各自模型）
A34: 12 個月後的前瞻 EPS（情境加權） | B34: =tp_wA*(8/12*B9+4/12*B10)+tp_wB*(8/12*C9+4/12*C10)+tp_wC*(8/12*D9+4/12*D10) -> 23.810906 | E34: 約 2027-10 時的未來 12 月（2027-11～2028-10）≈ 8／12 × FY2028＋4／12 × FY2029（會計年度 6 月底結束）
A35: Comparable 目標價 | B35: =B33*B34 -> 396.45158 | E35: 同業中位數 × 前瞻 EPS
A37: 0.3 結論
A38: 項目 | B38: 數值 | E38: 說明
A39: 目標價（DCF 與 Comparable 加權） | B39: =tp_w_dcf*B24+(1-tp_w_dcf)*B35 -> 373.1232 | E39: tp_w_dcf × DCF＋（1 − tp_w_dcf）× Comparable；tp_w_dcf 見 In 頁
A40: Comparable 目標價（市場主流同業法） | B40: =B35 -> 396.45158
A41: 市場共識目標價 | B41: =cons_tp -> 687.78 | E41: stockanalysis：9 位分析師平均 687.78（2026-10-21 更新；MarketBeat 10 位平均 650.63）
A42: 上檔空間：加權目標價 | B42: =B39/px-1 -> 0.18474376 | E42: 現價＝In 頁 px
A43: 上檔空間：Comparable 目標價 | B43: =B40/px-1 -> 0.25881623
A44: 與市場共識目標價的差距：EPS 因素 | B44: =B34/cons_feps-1 -> 0.11945961 | E44: 本模型前瞻 EPS ÷ 共識前瞻 EPS − 1；共識前瞻 EPS＝In 頁 cons_feps
A45: 與市場共識目標價的差距：倍數因素 | B45: =(cons_tp/cons_feps)/B33-1 -> 0.94208313 | E45: ="共識目標價隱含 "&TEXT(cons_tp/cons_feps,"0.0")&"x，同業中位數 "&TEXT(B33,"0.0")&"x" -> 共識目標價隱含 32.3x，同業中位數 16.7x
A46: 價格帶（DCF 不如預期～順利） | B46: =TEXT(D23,"#,##0.00")&"～"&TEXT(B23,"#,##0.00") -> 163.84～564.27 | E46: C 情境價值～A 情境價值（推到 12 個月後）
A47: 歷史倍數檢查：現價隱含 P/E 的十年分位（A／B／C） | B47: =IF(px/B9>MAX($B$102:$C$111),1,IF(px/B9<MIN($B$102:$C$111),0,PERCENTRANK($B$102:$C$111,px/B9))) -> 0 | C47: =IF(px/C9>MAX($B$102:$C$111),1,IF(px/C9<MIN($B$102:$C$111),0,PERCENTRANK($B$102:$C$111,px/C9))) -> 0.0881 | D47: =IF(px/D9>MAX($B$102:$C$111),1,IF(px/D9<MIN($B$102:$C$111),0,PERCENTRANK($B$102:$C$111,px/D9))) -> 0.222 | E47: 現價 ÷ 各情境 FY2028 EPS 在 2016–2025 年底 P/E（第 6 節採用來源）的分位；高於十年最大值＝100%；只作檢查，不進目標價
A48: 目標價方法 | B48: DCF：股東現金流＝EPS ×（1 − g／ROE），r＝10%、g＝4%、ROE＝近三年 GAAP 平均（再投資率約兩成），FY2027–32 明確期＋永續，FY2030 起為收斂法，情境價值下限 0。Comparable：Coherent、Lumentum、Jabil、Celestica、Flex 前瞻 P/E 中位數 × 12 個月後前瞻 EPS（non-GAAP）。偏誤：會計年度 6 月底結束，DCF 的 t＝1 對 FY2027，比基準日早半年（偏高估）；non-GAAP 排除 Pillar Two 補充稅（偏高估約 9%）；資本支出高於折舊、未建模（偏高估）。情境對應：A＝順利、B＝平平、C＝不如預期。
A49: 上檔空間級距 | B49: =IF(B42>0.5,"大於 50%",IF(B42>0.25,"25%–50%",IF(B42>=0,"0%–25%",IF(B42>=-0.25,"0%～−25%",IF(B42>=-0.5,"−25%～−50%","小於 −50%"))))) -> 0%–25% | E49: 以「上檔空間：加權目標價」分六級（Andy 2026-10-25 14:00）
A50: 投資建議 | B50: =IF(B42>0.5,"強力買進",IF(B42>0.25,"買進",IF(B42>=-0.25,"中立",IF(B42>=-0.5,"放空","強力放空")))) -> 中立 | E50: 依上檔空間固定規則（Andy 2026-10-25 14:17）：大於 +50% 強力買進、+25%～+50% 買進、−25%～+25% 中立、−50%～−25% 放空、小於 −50% 強力放空
A51: 舊法：規則值情境加權（參考）
A52: 項目 | B52: 數值 | E52: 說明
A53: 規則值情境加權價（參考，非目標價） | B53: =tp_wA*D81+tp_wB*D82+tp_wC*D83 -> 408.00154 | E53: 權重 × 各情境隱含價（第 3 節規則值）
A54: 規則值情境加權價 ÷ 現價 − 1（參考） | B54: =B53/px-1 -> 0.29548976 | E54: 現價＝In 頁 px（2026-10-23 收盤）
A55: 情境 A 隱含價（順利） | B55: =D81 -> 438.12903 | E55: ="FY2027 EPS "&TEXT(B81,"0.00")&" × "&C75&" 判定倍數 "&TEXT(C81,"0.0")&"x" -> FY2027 EPS 20.86 × 中段 判定倍數 21.0x
A56: 情境 B 隱含價（平平） | B56: =D82 -> 404.4499 | E56: ="FY2027 EPS "&TEXT(B82,"0.00")&" × "&C76&" 判定倍數 "&TEXT(C82,"0.0")&"x" -> FY2027 EPS 19.26 × 中段 判定倍數 21.0x
A57: 情境 C 隱含價（不如預期） | B57: =D83 -> 371.68943 | E57: ="FY2027 EPS "&TEXT(B83,"0.00")&" × "&C77&" 判定倍數 "&TEXT(C83,"0.0")&"x" -> FY2027 EPS 17.70 × 中段 判定倍數 21.0x
A58: 情境權重 A／B／C | B58: =tp_wA -> 0.3 | C58: =tp_wB -> 0.5 | D58: =tp_wC -> 0.2 | E58: ="合計 "&TEXT(B58+C58+D58,"0%")&"；In 頁 tp_wA／tp_wB／tp_wC（Assumed，Andy 可改）" -> 合計 100%；In 頁 tp_wA／tp_wB／tp_wC（Assumed，Andy 可改）
A59: 舊法說明 | B59: P/E：各情境 FY2027（2027-06 結束）non-GAAP EPS × 十年（2016–2025 年底）GAAP P/E 依循環位置取分位（營收最高年規則：仍成長＝中段＝中位數；見頂＝25 分位）。偏誤方向為小幅高估：GAAP 倍數套在較高的 non-GAAP EPS 上；隱含價約為 2027 年中的價格、未折現。
A62: 1. 價格與市場隱含倍數
A63: 項目 | B63: A | C63: B | D63: C | E63: 說明
A64: 現價（2026-10-23 收盤） | B64: =px -> 314.94
A65: 現價 ÷ FY2026 EPS（實績） | B65: =px/PL!D16 -> 22.346934 | C65: =px/PL!D31 -> 22.346934 | D65: =px/PL!D46 -> 22.346934
A66: 現價 ÷ FY2027 EPS（模型） | B66: =px/PL!E16 -> 15.095416 | C66: =px/PL!E31 -> 16.352433 | D66: =px/PL!E46 -> 17.793726 | E66: FY2027 三情境差異來自公司特有變數與網通 CPO 情境（顆數係數從 CY2028 開始）
A67: 現價 ÷ FY2028 EPS（模型） | B67: =px/PL!F16 -> 11.323653 | C67: =px/PL!F31 -> 14.292487 | D67: =px/PL!F46 -> 18.014364
A68: 現價 ÷ FY2029 EPS（模型） | B68: =px/PL!G16 -> 8.9216509 | C68: =px/PL!G31 -> 13.137397 | D68: =px/PL!G46 -> 20.058941
A69: 現價 ÷ 共識未來 12 月 EPS（9/12 × FY2027＋3/12 × FY2028） | B69: =px/(cons_eps27*9/12+cons_eps28*3/12) -> 16.584518
A70: 現價 ÷ 52 週高點 − 1 | B70: =px/px_hi-1 -> -0.5794576
A71: 現價 ÷ FY2027 Q1 EPS 指引中點年化 | B71: =px/(q1_eps*4) -> 18.858683 | E71: 4.175 × 4
A73: 2. 循環位置（本模型營收最高的會計年度）
A74: 情境 | B74: 營收最高年（FY2026–FY2029） | C74: FY2027 判定 | D74: 規則倍數（P/E） | E74: 見頂年是否未知 | F74: 說明
A75: A | B75: =INDEX({2026,2027,2028,2029},MATCH(MAX(PL!D81:G81),PL!D81:G81,0)) -> 2029 | C75: =IF(B75=2029,"中段",IF(2027<B75,"中段",IF(2027=B75,"見頂","谷底"))) -> 中段 | D75: =IF(C75="見頂",pe_peak,IF(C75="谷底",pe_trough,pe_mid)) -> 21 | E75: =IF(B75=2029,"是：營收到觀測期末仍在增加","否") -> 是：營收到觀測期末仍在增加 | F75: tools/cycle_position.py excel_rule；營收最高年取代設備市場見頂年
A76: B | B76: =INDEX({2026,2027,2028,2029},MATCH(MAX(PL!D121:G121),PL!D121:G121,0)) -> 2029 | C76: =IF(B76=2029,"中段",IF(2027<B76,"中段",IF(2027=B76,"見頂","谷底"))) -> 中段 | D76: =IF(C76="見頂",pe_peak,IF(C76="谷底",pe_trough,pe_mid)) -> 21 | E76: =IF(B76=2029,"是：營收到觀測期末仍在增加","否") -> 是：營收到觀測期末仍在增加 | F76: 同上
A77: C | B77: =INDEX({2026,2027,2028,2029},MATCH(MAX(PL!D161:G161),PL!D161:G161,0)) -> 2028 | C77: =IF(B77=2029,"中段",IF(2027<B77,"中段",IF(2027=B77,"見頂","谷底"))) -> 中段 | D77: =IF(C77="見頂",pe_peak,IF(C77="谷底",pe_trough,pe_mid)) -> 21 | E77: =IF(B77=2029,"是：營收到觀測期末仍在增加","否") -> 否 | F77: 同上
A79: 3. 規則值隱含股價（美元；約 FY2027 年底＝2027-06，未折現）＝ FY2027 EPS × 規則倍數
A80: 情境 | B80: FY2027 EPS | C80: 規則倍數 | D80: 隱含股價 | E80: 相對現價 | F80: 現價 ÷ FY2027 EPS
A81: A | B81: =PL!E16 -> 20.863287 | C81: =D75 -> 21 | D81: =B81*C81 -> 438.12903 | E81: =D81/px-1 -> 0.39115079 | F81: =px/B81 -> 15.095416
A82: B | B82: =PL!E31 -> 19.259519 | C82: =D76 -> 21 | D82: =B82*C82 -> 404.4499 | E82: =D82/px-1 -> 0.28421254 | F82: =px/B82 -> 16.352433
A83: C | B83: =PL!E46 -> 17.699497 | C83: =D77 -> 21 | D83: =B83*C83 -> 371.68943 | E83: =D83/px-1 -> 0.18019124 | F83: =px/B83 -> 17.793726
A85: 4. 核心問題：市場隱含的 FY2028 EPS（＝現價 ÷ 假設倍數）與模型的距離
A86: 假設倍數（÷ FY2028 EPS） | B86: 市場隱含 FY2028 EPS | C86: 模型 FY2028 EPS（B） | D86: 隱含 ÷ 模型 B − 1 | E86: 模型 FY2028 EPS（C） | F86: 隱含 ÷ 模型 C − 1
A87: 10 | B87: =px/A87 -> 31.494 | C87: =PL!F31 -> 22.035353 | D87: =B87/C87-1 -> 0.42924874 | E87: =PL!F46 -> 17.482716 | F87: =B87/E87-1 -> 0.80143639
A88: 15 | B88: =px/A88 -> 20.996 | C88: =PL!F31 -> 22.035353 | D88: =B88/C88-1 -> -0.047167508 | E88: =PL!F46 -> 17.482716 | F88: =B88/E88-1 -> 0.2009576
A89: 20 | B89: =px/A89 -> 15.747 | C89: =PL!F31 -> 22.035353 | D89: =B89/C89-1 -> -0.28537563 | E89: =PL!F46 -> 17.482716 | F89: =B89/E89-1 -> -0.099281804
A90: =pe_peak -> 18.51 | B90: =px/A90 -> 17.014587 | C90: =PL!F31 -> 22.035353 | D90: =B90/C90-1 -> -0.22785049 | E90: =PL!F46 -> 17.482716 | F90: =B90/E90-1 -> -0.026776665
A91: 讀法：第四列＝十年 P/E 25 分位（見頂倍數）。現價約 14 倍模型 FY2028 EPS（B）；若市場對 FY2028 給見頂倍數，隱含 FY2028 EPS 約等於情境 C（顆數 ×0.6、光模組份額與毛利率低值）——市場定價接近「NVIDIA 光模組份額續降、AI 部署下修」的組合。
A93: 本版未做先驗：無 Andy 合理 P/E 對照。
A97: 6. 十年倍數與規則值（2016–2025 年底；見頂年 25 分位、中段中位數、谷底 75 分位）
A98: 規則（Andy 2026-10-13）：合理倍數＝年底 P/E 依循環位置取分位。兩個資料商來源（GAAP 落後 P/E）；GAAP 倍數套在 non-GAAP EPS 上（non-GAAP 約高 7%），偏誤方向為小幅高估；2025 年 43x 為 AI 光模組題材溢價；前瞻 P/E 歷史待 Bloomberg。
A100: P/E：十年歷史倍數
A101: 年底 | B101: companiesmarketcap（年底 P/E） | C101: macrotrends（12 月底 P/E） | D101: 標記／說明
A102: 2016 | B102: 16.4 | C102: 17 | D102: companiesmarketcap（年底 P/E）：Interested-party（資料商；GAAP TTM）；macrotrends（12 月底 P/E）：Interested-party（資料商；GAAP TTM；2024、2025 年底未列，未找到）
A103: 2017 | B103: 12 | C103: 12.21
A104: 2018 | B104: 18.3 | C104: 18.73
A105: 2019 | B105: 20.2 | C105: 20.52
A106: 2020 | B106: 23 | C106: 23.37
A107: 2021 | B107: 25.2 | C107: 25.59
A108: 2022 | B108: 20 | C108: 20.26
A109: 2023 | B109: 27.2 | C109: 27.5
A110: 2024 | B110: 24.4
A111: 2025 | B111: 43.3
A112: 25 分位（各來源） | B112: =PERCENTILE(B102:B111,0.25) -> 18.725 | C112: =PERCENTILE(C102:C111,0.25) -> 18.2975
A113: 中位數（各來源） | B113: =MEDIAN(B102:B111) -> 21.6 | C113: =MEDIAN(C102:C111) -> 20.39
...

Sheet Recon
A1: Recon — 本模型 vs 共識、公司指引與產能。只作事後對照，不為對上數字而調參數。共識來自彙整網站（stockanalysis、MarketBeat、tickflow），各家年度與更新日不一
A3: 項目 | B3: 對照值 | C3: 模型 A | D3: 差距 A | E3: 模型 B | F3: 差距 B | G3: 模型 C | H3: 差距 C | I3: 對照來源 | J3: 說明
A4: A. 共識（校準未使用）
A5: FY2027 營收 vs 共識 | B5: =cons_rev27 -> 6.11 | C5: =PL!E81 -> 6.6244167 | D5: =C5/B5-1 -> 0.084192579 | E5: =PL!E121 -> 6.3342561 | F5: =E5/B5-1 -> 0.036703131 | G5: =PL!E161 -> 6.0910539 | H5: =G5/B5-1 -> -0.0031008307 | I5: stockanalysis（2026-10-21）
A6: FY2027 EPS vs 共識 | B6: =cons_eps27 -> 18.23 | C6: =PL!E96 -> 20.863287 | D6: =C6/B6-1 -> 0.14444801 | E6: =PL!E136 -> 19.259519 | F6: =E6/B6-1 -> 0.056473888 | G6: =PL!E176 -> 17.699497 | H6: =G6/B6-1 -> -0.029100568 | I6: stockanalysis（7 位）
A7: FY2027 EPS vs 共識（第二來源） | B7: =cons_eps27b -> 17.5 | C7: =PL!E96 -> 20.863287 | D7: =C7/B7-1 -> 0.19218784 | E7: =PL!E136 -> 19.259519 | F7: =E7/B7-1 -> 0.10054394 | G7: =PL!E176 -> 17.699497 | H7: =G7/B7-1 -> 0.011399809 | I7: MarketBeat（2026-10-23）
A8: FY2028 營收 vs 共識 | B8: =cons_rev28 -> 6.58 | C8: =PL!F81 -> 8.6856306 | D8: =C8/B8-1 -> 0.32000465 | E8: =PL!F121 -> 7.2142358 | F8: =E8/B8-1 -> 0.096388424 | G8: =PL!F161 -> 6.1798837 | H8: =G8/B8-1 -> -0.06080795 | I8: tickflow（3 位；疑似未更新）
A9: FY2028 EPS vs 共識 | B9: =cons_eps28 -> 21.27 | C9: =PL!F96 -> 27.812579 | D9: =C9/B9-1 -> 0.30759657 | E9: =PL!F136 -> 22.035353 | F9: =E9/B9-1 -> 0.03598273 | G9: =PL!F176 -> 17.482716 | H9: =G9/B9-1 -> -0.17805757 | I9: MarketBeat（2026-10-23）
A10: FY2028 EPS vs 共識（第二來源） | B10: =cons_eps28b -> 20.14 | C10: =PL!F96 -> 27.812579 | D10: =C10/B10-1 -> 0.38096222 | E10: =PL!F136 -> 22.035353 | F10: =E10/B10-1 -> 0.094108871 | G10: =PL!F176 -> 17.482716 | H10: =G10/B10-1 -> -0.13194064 | I10: tickflow（2 位）
A11: B. 公司指引與校準
A12: FY2027 Q1 EPS（模型，營收指引中點、毛利率與費用假設）vs 公司 EPS 指引中點 | B12: =q1_eps -> 4.175 | C12: =Q!F19 -> 4.1559229 | D12: =C12/B12-1 -> -0.0045693736 | E12: =Q!F19 -> 4.1559229 | F12: =E12/B12-1 -> -0.0045693736 | G12: =Q!F19 -> 4.1559229 | H12: =G12/B12-1 -> -0.0045693736 | I12: 公司指引（2026-08-17） | J12: 毛利率、費用、稅率為假設；股數取指引
A13: FY2026 Q3 營收：資料中心＋通訊（回推）＋車用工業（推導）vs 實績 | B13: =q3_rev -> 1.2143 | C13: =Q!D5+Q!D9+Q!D10 -> 1.2143 | D13: =C13/B13-1 -> 0 | E13: =Q!D5+Q!D9+Q!D10 -> 1.2143 | F13: =E13/B13-1 -> 0 | G13: =Q!D5+Q!D9+Q!D10 -> 1.2143 | H13: =G13/B13-1 -> 0 | I13: 公司 | J13: 恆等（車用工業為差額）；僅確認拆分加總
A14: FY2026 NVIDIA 營收（10-K 16.3%）vs 光模組與其他 | B14: =nv26*a26_rev_in -> 0.75649881 | C14: =PL!D73 -> 1.1638855 | D14: =C14/B14-1 -> 0.53851592 | E14: =PL!D113 -> 1.1638855 | F14: =E14/B14-1 -> 0.53851592 | G14: =PL!D153 -> 1.1638855 | H14: =G14/B14-1 -> 0.53851592 | I14: 10-K | J14: NVIDIA 營收低於光模組與其他：其餘為其他客戶光模組與資料中心零組件
A15: C. 份額、市場與產能
A16: CY2026 Fabrinet＋中際旭創可插拔有效份額 | C16: =Units!C8 -> 0.46418552 | E16: =Units!C8 -> 0.46418552 | G16: =Units!C8 -> 0.46418552 | I16: Units 頁 | J16: 須低於 100%
A17: CY2028 Fabrinet＋中際旭創可插拔有效份額 | C17: =Units!E8 -> 0.43259021 | E17: =Units!E8 -> 0.43259021 | G17: =Units!E8 -> 0.43259021 | I17: Units 頁（情境 A）
A18: FY2027 資料中心 ÷ CY2027 AI IT 資本支出 | C18: =PL!E78/itc_27 -> 0.0024856889 | E18: =PL!E118/itc_27 -> 0.0023003242 | G18: =PL!E158/itc_27 -> 0.0021449582 | I18: markets/network | J18: 每 1 美元 AI IT 資本支出分到的 Fabrinet 資料中心營收
A19: FY2028 營收 vs 產能（現有＋Building 10） | B19: =cap_b10 -> 8.9 | C19: =PL!F81 -> 8.6856306 | D19: =C19/B19-1 -> -0.024086451 | E19: =PL!F121 -> 7.2142358 | F19: =E19/B19-1 -> -0.1894117 | G19: =PL!F161 -> 6.1798837 | H19: =G19/B19-1 -> -0.30563105 | I19: 公司（法說會） | J19: 差距 > 0 表示需要 Building 10 以外的新產能
A20: FY2029 營收 vs 長期產能目標 | B20: =cap_tot -> 13.25 | C20: =PL!G81 -> 10.955418 | D20: =C20/B20-1 -> -0.17317599 | E20: =PL!G121 -> 7.8272266 | F20: =E20/B20-1 -> -0.40926592 | G20: =PL!G161 -> 5.6866902 | H20: =G20/B20-1 -> -0.57081583 | I20: 公司（法說會） | J20: 長期目標 125–140 億美元的中點
A21: D. 預留
A22: R4 產業部署路徑（markets/deploy_path/，尚未建立）：上線後以資料中心營收 ÷ 部署 GW 計算每 GW 營收 | J22: 預留列：本版無數值
A23: FY2027 Q1 季報（預估 2026-11-02 盤後）：公布後以實績取代 Q 頁 Q1 指引推導，並更新資料中心內光模組、DCI、HPC 拆分 | J23: 預留列：本版無數值

Sheet Sens
A1: Sens — 一次動一個輸入（以情境 B 為基準；有效份額在每個案例內依 CY2026 重算，FY2026 恆等於實績）：對 FY2027、FY2028 的營收、資料中心營收、毛利率與 EPS 的影響。每個案例是一個完整推導區塊（本頁下方）
A3: 案例 | B3: 設定 | C3: FY2027 營收 | D3: FY2027 資料中心 | E3: FY2027 毛利率 | F3: FY2027 EPS | G3: FY2027 EPS 相對基準 | H3: FY2028 營收 | I3: FY2028 資料中心 | J3: FY2028 毛利率 | K3: FY2028 EPS | L3: FY2028 EPS 相對基準
A4: 基準（情境 B） | B4: PL 區塊 B | C4: =PL!E121 -> 6.3342561 | D4: =PL!E118 -> 3.6008125 | E4: =PL!E125 -> 0.123 | F4: =PL!E136 -> 19.259519 | G4: =F4/F$4-1 -> 0 | H4: =PL!F121 -> 7.2142358 | I4: =PL!F118 -> 4.3265081 | J4: =PL!F125 -> 0.123 | K4: =PL!F136 -> 22.035353 | L4: =K4/K$4-1 -> 0
A5: 份額流失（低） | B5: 光模組份額相對值 CY2027 0.80、CY2028 0.70、CY2029 0.60（NVIDIA 份額續降） | C5: =E61 -> 6.1211688 | D5: =E58 -> 3.3877252 | E5: =E65 -> 0.123 | F5: =E76 -> 18.591013 | G5: =F5/F$4-1 -> -0.034710419 | H5: =F61 -> 6.6778766 | I5: =F58 -> 3.7901488 | J5: =F65 -> 0.123 | K5: =F76 -> 20.346195 | L5: =K5/K$4-1 -> -0.076656708
A6: 份額大增（高） | B6: 份額相對值 1.15／1.25／1.30（新客戶光模組專案、Building 10 產能） | C6: =E101 -> 6.4940716 | D6: =E98 -> 3.760628 | E6: =E105 -> 0.123 | F6: =E116 -> 19.760898 | G6: =F6/F$4-1 -> 0.026032814 | H6: =F101 -> 7.6403564 | I6: =F98 -> 4.7526286 | J6: =F105 -> 0.123 | K6: =F116 -> 23.378102 | L6: =K6/K$4-1 -> 0.060936131
A7: 降價快於模型 | B7: 單價係數 CY2027 0.90、CY2028 0.80、CY2029 0.72 | C7: =E141 -> 6.2277125 | D7: =E138 -> 3.4942689 | E7: =E145 -> 0.123 | F7: =E156 -> 18.925266 | G7: =F7/F$4-1 -> -0.017355209 | H7: =F141 -> 6.898354 | I7: =F138 -> 4.0106262 | J7: =F145 -> 0.123 | K7: =F156 -> 21.040217 | L7: =K7/K$4-1 -> -0.045160888
A8: 毛利率 低（新廠爬坡） | B8: 毛利率 FY2027 11.8%、FY2028 11.5%、FY2029 11.3% | C8: =E181 -> 6.3342561 | D8: =E178 -> 3.6008125 | E8: =E185 -> 0.118 | F8: =E196 -> 18.430656 | G8: =F8/F$4-1 -> -0.043036522 | H8: =F181 -> 7.2142358 | I8: =F178 -> 4.3265081 | J8: =F185 -> 0.115 | K8: =F196 -> 20.524934 | L8: =K8/K$4-1 -> -0.068545239
A9: 毛利率 高 | B9: 毛利率 12.7%／12.8%／12.8% | C9: =E221 -> 6.3342561 | D9: =E218 -> 3.6008125 | E9: =E225 -> 0.127 | F9: =E236 -> 19.922609 | G9: =F9/F$4-1 -> 0.034429218 | H9: =F221 -> 7.2142358 | I9: =F218 -> 4.3265081 | J9: =F225 -> 0.128 | K9: =F236 -> 22.979364 | L9: =K9/K$4-1 -> 0.042840775
A10: CPO 份額 低 | B10: CY2027 0%、CY2028 2%、CY2029 5% | C10: =E261 -> 6.2953541 | D10: =E258 -> 3.5619105 | E10: =E265 -> 0.123 | F10: =E276 -> 19.137474 | G10: =F10/F$4-1 -> -0.0063368599 | H10: =F261 -> 7.07372 | I10: =F258 -> 4.1859922 | J10: =F265 -> 0.123 | K10: =F276 -> 21.592547 | L10: =K10/K$4-1 -> -0.020095222
A11: CPO 份額 高 | B11: CY2027 15%、CY2028 20%、CY2029 25% | C11: =E301 -> 6.4120601 | D11: =E298 -> 3.6786165 | E11: =E305 -> 0.123 | F11: =E316 -> 19.503609 | G11: =F11/F$4-1 -> 0.01267372 | H11: =F301 -> 7.4241313 | I11: =F298 -> 4.5364036 | J11: =F305 -> 0.123 | K11: =F316 -> 22.696694 | L11: =K11/K$4-1 -> 0.03001276
A12: AI 市場 ×0.8 | B12: CY2027 起可插拔光模組市場 ×0.8 | C12: =E341 -> 6.1211688 | D12: =E338 -> 3.3877252 | E12: =E345 -> 0.123 | F12: =E356 -> 18.591013 | G12: =F12/F$4-1 -> -0.034710419 | H12: =F341 -> 6.773281 | I12: =F338 -> 3.8855532 | J12: =F345 -> 0.123 | K12: =F356 -> 20.646985 | L12: =K12/K$4-1 -> -0.063006369
A13: AI 市場 ×1.2 | B13: ×1.2 | C13: =E381 -> 6.5473434 | D13: =E378 -> 3.8138999 | E13: =E385 -> 0.123 | F13: =E396 -> 19.928025 | G13: =F13/F$4-1 -> 0.034710419 | H13: =F381 -> 7.6551907 | I13: =F378 -> 4.7674629 | J13: =F385 -> 0.123 | K13: =F396 -> 23.424349 | L13: =K13/K$4-1 -> 0.063034925
A14: 上半年比重 42% | B14: 日曆年上半年占 42%（FY 認列較晚） | C14: =E421 -> 6.2382267 | D14: =E418 -> 3.5047831 | E14: =E425 -> 0.123 | F14: =E436 -> 18.958252 | G14: =F14/F$4-1 -> -0.015642518 | H14: =F421 -> 7.234242 | I14: =F418 -> 4.3465143 | J14: =F425 -> 0.123 | K14: =F436 -> 22.099389 | L14: =K14/K$4-1 -> 0.0029060788
A15: 上半年比重 50% | B15: 50% | C15: =E461 -> 6.4302856 | D15: =E458 -> 3.696842 | E15: =E465 -> 0.123 | F15: =E476 -> 19.560786 | G15: =F15/F$4-1 -> 0.015642518 | H15: =F461 -> 7.1942296 | I15: =F458 -> 4.3065019 | J15: =F465 -> 0.123 | K15: =F476 -> 21.971131 | L15: =K15/K$4-1 -> -0.0029144688
A16: DCI 成長 低 | B16: FY2027 下半年 ÷ 上半年 +0%；FY2028 +5%、FY2029 0% | C16: =E501 -> 6.2633206 | D16: =E498 -> 3.5298771 | E16: =E505 -> 0.123 | F16: =E516 -> 19.036977 | G16: =F16/F$4-1 -> -0.011554889 | H16: =F501 -> 6.975921 | I16: =F498 -> 4.0881932 | J16: =F505 -> 0.123 | K16: =F516 -> 21.284444 | L16: =K16/K$4-1 -> -0.034077431
A17: HPC 成長 低（AWS 專案流失） | B17: FY2027 下半年 ÷ 上半年 −10%；FY2028、FY2029 各 −10% | C17: =E541 -> 6.2851917 | D17: =E538 -> 3.5517481 | E17: =E545 -> 0.123 | F17: =E556 -> 19.105592 | G17: =F17/F$4-1 -> -0.0079922442 | H17: =F541 -> 7.045439 | I17: =F538 -> 4.1577113 | J17: =F545 -> 0.123 | K17: =F556 -> 21.503459 | L17: =K17/K$4-1 -> -0.024138202
A18: 營業費用率 +0.5pt | B18: 營業費用額外 +0.5% × 營收 | C18: =E581 -> 6.3342561 | D18: =E578 -> 3.6008125 | E18: =E585 -> 0.123 | F18: =E596 -> 18.430656 | G18: =F18/F$4-1 -> -0.043036522 | H18: =F581 -> 7.2142358 | I18: =F578 -> 4.3265081 | J18: =F585 -> 0.123 | K18: =F596 -> 21.091341 | L18: =K18/K$4-1 -> -0.042840775
A19: 計入 Pillar Two 補充稅 | B19: 稅率 +9pt（non-GAAP 排除、但為實際稅負） | C19: =E621 -> 6.3342561 | D19: =E618 -> 3.6008125 | E19: =E625 -> 0.123 | F19: =E636 -> 17.434933 | G19: =F19/F$4-1 -> -0.094736842 | H19: =F621 -> 7.2142358 | I19: =F618 -> 4.3265081 | J19: =F625 -> 0.123 | K19: =F636 -> 19.947793 | L19: =K19/K$4-1 -> -0.094736842
A20: 情境 A（全部） | B20: 顆數 1.0＋CPO 情境 A＋份額、CPO 份額、毛利率高值 | C20: =PL!E81 -> 6.6244167 | D20: =PL!E78 -> 3.8909731 | E20: =PL!E85 -> 0.127 | F20: =PL!E96 -> 20.863287 | G20: =F20/F$4-1 -> 0.083271457 | H20: =PL!F81 -> 8.6856306 | I20: =PL!F78 -> 5.7979028 | J20: =PL!F85 -> 0.128 | K20: =PL!F96 -> 27.812579 | L20: =K20/K$4-1 -> 0.26217989
A21: 情境 C（全部） | B21: CY2028–29 顆數 ×0.6＋CPO 情境 C＋公司變數低值 | C21: =PL!E161 -> 6.0910539 | D21: =PL!E158 -> 3.3576103 | E21: =PL!E165 -> 0.118 | F21: =PL!E176 -> 17.699497 | G21: =F21/F$4-1 -> -0.081000067 | H21: =PL!F161 -> 6.1798837 | I21: =PL!F158 -> 3.2921559 | J21: =PL!F165 -> 0.115 | K21: =PL!F176 -> 17.482716 | L21: =K21/K$4-1 -> -0.20660605
A23: 讀法：顆數係數從 CY2028 起作用，FY2028 只含半年 CY2028。FY2027 上半年＝指引推導＋假設，所以份額、市場等案例對 FY2027 只影響下半年；「計入 Pillar Two」顯示 non-GAAP 口徑排除的實際稅負。
A25: 目標價參數（只改 DCF 參數與權重；PL 收斂法的 fade_g 不隨 tp_g 變動）
A26: 案例 | B26: 設定 | C26: DCF 目標價 | D26: Comparable 目標價 | E26: 加權目標價 | F26: 相對基準
A27: 基準 | B27: r 10%、g 4%、DCF 權重 0.5 | C27: =(tp_wA*MAX(0,Val!B8*(1-IF(tp_roe<=tp_g,0.8,MIN(tp_g/tp_roe,0.8)))/(1+tp_r)^1+Val!B9*(1-IF(tp_roe<=tp_g,0.8,MIN(tp_g/tp_roe,0.8)))/(1+tp_r)^2+Val!B10*(1-IF(tp_roe<=tp_g,0.8,MIN(tp_g/tp_roe,0.8)))/(1+tp_r)^3+Val!B11*(1-IF(tp_roe<=tp_g,0.8,MIN(tp_g/tp_roe,0.8)))/(1+tp_r)^4+Val!B12*(1-IF(tp_roe<=tp_g,0.8,MIN(tp_g/tp_roe,0.8)))/(1+tp_r)^5+Val!B13*(1-IF(tp_roe<=tp_g,0.8,MIN(tp_g/tp_roe,0.8)))/(1+tp_r)^6+Val!B13*(1-IF(tp_roe<=tp_g,0.8,MIN(tp_g/tp_roe,0.8)))*(1+tp_g)/(tp_r-tp_g)/(1+tp_r)^6)+tp_wB*MAX(0,Val!C8*(1-IF(tp_roe<=tp_g,0.8,MIN(tp_g/tp_roe,0.8)))/(1+tp_r)^1+Val!C9*(1-IF(tp_roe<=tp_g,0.8,MIN(tp_g/tp_roe,0.8)))/(1+tp_r)^2+Val!C10*(1-IF(tp_roe<=tp_g,0.8,MIN(tp_g/tp_roe,0.8)))/(1+tp_r)^3+Val!C11*(1-IF(tp_roe<=tp_g,0.8,MIN(tp_g/tp_roe,0.8)))/(1+tp_r)^4+Val!C12*(1-IF(tp_roe<=tp_g,0.8,MIN(tp_g/tp_roe,0.8)))/(1+tp_r)^5+Val!C13*(1-IF(tp_roe<=tp_g,0.8,MIN(tp_g/tp_roe,0.8)))/(1+tp_r)^6+Val!C13*(1-IF(tp_roe<=tp_g,0.8,MIN(tp_g/tp_roe,0.8)))*(1+tp_g)/(tp_r-tp_g)/(1+tp_r)^6)+tp_wC*MAX(0,Val!D8*(1-IF(tp_roe<=tp_g,0.8,MIN(tp_g/tp_roe,0.8)))/(1+tp_r)^1+Val!D9*(1-IF(tp_roe<=tp_g,0.8,MIN(tp_g/tp_roe,0.8)))/(1+tp_r)^2+Val!D10*(1-IF(tp_roe<=tp_g,0.8,MIN(tp_g/tp_roe,0.8)))/(1+tp_r)^3+Val!D11*(1-IF(tp_roe<=tp_g,0.8,MIN(tp_g/tp_roe,0.8)))/(1+tp_r)^4+Val!D12*(1-IF(tp_roe<=tp_g,0.8,MIN(tp_g/tp_roe,0.8)))/(1+tp_r)^5+Val!D13*(1-IF(tp_roe<=tp_g,0.8,MIN(tp_g/tp_roe,0.8)))/(1+tp_r)^6+Val!D13*(1-IF(tp_roe<=tp_g,0.8,MIN(tp_g/tp_roe,0.8)))*(1+tp_g)/(tp_r-tp_g)/(1+tp_r)^6))*(1+tp_r) -> 349.79481 | D27: =Val!B35 -> 396.45158 | E27: =tp_w_dcf*C27+(1-tp_w_dcf)*D27 -> 373.1232 | F27: =E27/E$27-1 -> 0
A28: 折現率 +1pt | B28: r 11% | C28: =(tp_wA*MAX(0,Val!B8*(1-IF(tp_roe<=tp_g,0.8,MIN(tp_g/tp_roe,0.8)))/(1+(tp_r+0.01))^1+Val!B9*(1-IF(tp_roe<=tp_g,0.8,MIN(tp_g/tp_roe,0.8)))/(1+(tp_r+0.01))^2+Val!B10*(1-IF(tp_roe<=tp_g,0.8,MIN(tp_g/tp_roe,0.8)))/(1+(tp_r+0.01))^3+Val!B11*(1-IF(tp_roe<=tp_g,0.8,MIN(tp_g/tp_roe,0.8)))/(1+(tp_r+0.01))^4+Val!B12*(1-IF(tp_roe<=tp_g,0.8,MIN(tp_g/tp_roe,0.8)))/(1+(tp_r+0.01))^5+Val!B13*(1-IF(tp_roe<=tp_g,0.8,MIN(tp_g/tp_roe,0.8)))/(1+(tp_r+0.01))^6+Val!B13*(1-IF(tp_roe<=tp_g,0.8,MIN(tp_g/tp_roe,0.8)))*(1+tp_g)/((tp_r+0.01)-tp_g)/(1+(tp_r+0.01))^6)+tp_wB*MAX(0,Val!C8*(1-IF(tp_roe<=tp_g,0.8,MIN(tp_g/tp_roe,0.8)))/(1+(tp_r+0.01))^1+Val!C9*(1-IF(tp_roe<=tp_g,0.8,MIN(tp_g/tp_roe,0.8)))/(1+(tp_r+0.01))^2+Val!C10*(1-IF(tp_roe<=tp_g,0.8,MIN(tp_g/tp_roe,0.8)))/(1+(tp_r+0.01))^3+Val!C11*(1-IF(tp_roe<=tp_g,0.8,MIN(tp_g/tp_roe,0.8)))/(1+(tp_r+0.01))^4+Val!C12*(1-IF(tp_roe<=tp_g,0.8,MIN(tp_g/tp_roe,0.8)))/(1+(tp_r+0.01))^5+Val!C13*(1-IF(tp_roe<=tp_g,0.8,MIN(tp_g/tp_roe,0.8)))/(1+(tp_r+0.01))^6+Val!C13*(1-IF(tp_roe<=tp_g,0.8,MIN(tp_g/tp_roe,0.8)))*(1+tp_g)/((tp_r+0.01)-tp_g)/(1+(tp_r+0.01))^6)+tp_wC*MAX(0,Val!D8*(1-IF(tp_roe<=tp_g,0.8,MIN(tp_g/tp_roe,0.8)))/(1+(tp_r+0.01))^1+Val!D9*(1-IF(tp_roe<=tp_g,0.8,MIN(tp_g/tp_roe,0.8)))/(1+(tp_r+0.01))^2+Val!D10*(1-IF(tp_roe<=tp_g,0.8,MIN(tp_g/tp_roe,0.8)))/(1+(tp_r+0.01))^3+Val!D11*(1-IF(tp_roe<=tp_g,0.8,MIN(tp_g/tp_roe,0.8)))/(1+(tp_r+0.01))^4+Val!D12*(1-IF(tp_roe<=tp_g,0.8,MIN(tp_g/tp_roe,0.8)))/(1+(tp_r+0.01))^5+Val!D13*(1-IF(tp_roe<=tp_g,0.8,MIN(tp_g/tp_roe,0.8)))/(1+(tp_r+0.01))^6+Val!D13*(1-IF(tp_roe<=tp_g,0.8,MIN(tp_g/tp_roe,0.8)))*(1+tp_g)/((tp_r+0.01)-tp_g)/(1+(tp_r+0.01))^6))*(1+(tp_r+0.01)) -> 301.7423 | D28: =Val!B35 -> 396.45158 | E28: =tp_w_dcf*C28+(1-tp_w_dcf)*D28 -> 349.09694 | F28: =E28/E$27-1 -> -0.064392293
A29: 折現率 −1pt | B29: r 9% | C29: =(tp_wA*MAX(0,Val!B8*(1-IF(tp_roe<=tp_g,0.8,MIN(tp_g/tp_roe,0.8)))/(1+(tp_r-0.01))^1+Val!B9*(1-IF(tp_roe<=tp_g,0.8,MIN(tp_g/tp_roe,0.8)))/(1+(tp_r-0.01))^2+Val!B10*(1-IF(tp_roe<=tp_g,0.8,MIN(tp_g/tp_roe,0.8)))/(1+(tp_r-0.01))^3+Val!B11*(1-IF(tp_roe<=tp_g,0.8,MIN(tp_g/tp_roe,0.8)))/(1+(tp_r-0.01))^4+Val!B12*(1-IF(tp_roe<=tp_g,0.8,MIN(tp_g/tp_roe,0.8)))/(1+(tp_r-0.01))^5+Val!B13*(1-IF(tp_roe<=tp_g,0.8,MIN(tp_g/tp_roe,0.8)))/(1+(tp_r-0.01))^6+Val!B13*(1-IF(tp_roe<=tp_g,0.8,MIN(tp_g/tp_roe,0.8)))*(1+tp_g)/((tp_r-0.01)-tp_g)/(1+(tp_r-0.01))^6)+tp_wB*MAX(0,Val!C8*(1-IF(tp_roe<=tp_g,0.8,MIN(tp_g/tp_roe,0.8)))/(1+(tp_r-0.01))^1+Val!C9*(1-IF(tp_roe<=tp_g,0.8,MIN(tp_g/tp_roe,0.8)))/(1+(tp_r-0.01))^2+Val!C10*(1-IF(tp_roe<=tp_g,0.8,MIN(tp_g/tp_roe,0.8)))/(1+(tp_r-0.01))^3+Val!C11*(1-IF(tp_roe<=tp_g,0.8,MIN(tp_g/tp_roe,0.8)))/(1+(tp_r-0.01))^4+Val!C12*(1-IF(tp_roe<=tp_g,0.8,MIN(tp_g/tp_roe,0.8)))/(1+(tp_r-0.01))^5+Val!C13*(1-IF(tp_roe<=tp_g,0.8,MIN(tp_g/tp_roe,0.8)))/(1+(tp_r-0.01))^6+Val!C13*(1-IF(tp_roe<=tp_g,0.8,MIN(tp_g/tp_roe,0.8)))*(1+tp_g)/((tp_r-0.01)-tp_g)/(1+(tp_r-0.01))^6)+tp_wC*MAX(0,Val!D8*(1-IF(tp_roe<=tp_g,0.8,MIN(tp_g/tp_roe,0.8)))/(1+(tp_r-0.01))^1+Val!D9*(1-IF(tp_roe<=tp_g,0.8,MIN(tp_g/tp_roe,0.8)))/(1+(tp_r-0.01))^2+Val!D10*(1-IF(tp_roe<=tp_g,0.8,MIN(tp_g/tp_roe,0.8)))/(1+(tp_r-0.01))^3+Val!D11*(1-IF(tp_roe<=tp_g,0.8,MIN(tp_g/tp_roe,0.8)))/(1+(tp_r-0.01))^4+Val!D12*(1-IF(tp_roe<=tp_g,0.8,MIN(tp_g/tp_roe,0.8)))/(1+(tp_r-0.01))^5+Val!D13*(1-IF(tp_roe<=tp_g,0.8,MIN(tp_g/tp_roe,0.8)))/(1+(tp_r-0.01))^6+Val!D13*(1-IF(tp_roe<=tp_g,0.8,MIN(tp_g/tp_roe,0.8)))*(1+tp_g)/((tp_r-0.01)-tp_g)/(1+(tp_r-0.01))^6))*(1+(tp_r-0.01)) -> 417.0739 | D29: =Val!B35 -> 396.45158 | E29: =tp_w_dcf*C29+(1-tp_w_dcf)*D29 -> 406.76274 | F29: =E29/E$27-1 -> 0.090156662
A30: 長期成長 +1pt | B30: g 5% | C30: =(tp_wA*MAX(0,Val!B8*(1-IF(tp_roe<=(tp_g+0.01),0.8,MIN((tp_g+0.01)/tp_roe,0.8)))/(1+tp_r)^1+Val!B9*(1-IF(tp_roe<=(tp_g+0.01),0.8,MIN((tp_g+0.01)/tp_roe,0.8)))/(1+tp_r)^2+Val!B10*(1-IF(tp_roe<=(tp_g+0.01),0.8,MIN((tp_g+0.01)/tp_roe,0.8)))/(1+tp_r)^3+Val!B11*(1-IF(tp_roe<=(tp_g+0.01),0.8,MIN((tp_g+0.01)/tp_roe,0.8)))/(1+tp_r)^4+Val!B12*(1-IF(tp_roe<=(tp_g+0.01),0.8,MIN((tp_g+0.01)/tp_roe,0.8)))/(1+tp_r)^5+Val!B13*(1-IF(tp_roe<=(tp_g+0.01),0.8,MIN((tp_g+0.01)/tp_roe,0.8)))/(1+tp_r)^6+Val!B13*(1-IF(tp_roe<=(tp_g+0.01),0.8,MIN((tp_g+0.01)/tp_roe,0.8)))*(1+(tp_g+0.01))/(tp_r-(tp_g+0.01))/(1+tp_r)^6)+tp_wB*MAX(0,Val!C8*(1-IF(tp_roe<=(tp_g+0.01),0.8,MIN((tp_g+0.01)/tp_roe,0.8)))/(1+tp_r)^1+Val!C9*(1-IF(tp_roe<=(tp_g+0.01),0.8,MIN((tp_g+0.01)/tp_roe,0.8)))/(1+tp_r)^2+Val!C10*(1-IF(tp_roe<=(tp_g+0.01),0.8,MIN((tp_g+0.01)/tp_roe,0.8)))/(1+tp_r)^3+Val!C11*(1-IF(tp_roe<=(tp_g+0.01),0.8,MIN((tp_g+0.01)/tp_roe,0.8)))/(1+tp_r)^4+Val!C12*(1-IF(tp_roe<=(tp_g+0.01),0.8,MIN((tp_g+0.01)/tp_roe,0.8)))/(1+tp_r)^5+Val!C13*(1-IF(tp_roe<=(tp_g+0.01),0.8,MIN((tp_g+0.01)/tp_roe,0.8)))/(1+tp_r)^6+Val!C13*(1-IF(tp_roe<=(tp_g+0.01),0.8,MIN((tp_g+0.01)/tp_roe,0.8)))*(1+(tp_g+0.01))/(tp_r-(tp_g+0.01))/(1+tp_r)^6)+tp_wC*MAX(0,Val!D8*(1-IF(tp_roe<=(tp_g+0.01),0.8,MIN((tp_g+0.01)/tp_roe,0.8)))/(1+tp_r)^1+Val!D9*(1-IF(tp_roe<=(tp_g+0.01),0.8,MIN((tp_g+0.01)/tp_roe,0.8)))/(1+tp_r)^2+Val!D10*(1-IF(tp_roe<=(tp_g+0.01),0.8,MIN((tp_g+0.01)/tp_roe,0.8)))/(1+tp_r)^3+Val!D11*(1-IF(tp_roe<=(tp_g+0.01),0.8,MIN((tp_g+0.01)/tp_roe,0.8)))/(1+tp_r)^4+Val!D12*(1-IF(tp_roe<=(tp_g+0.01),0.8,MIN((tp_g+0.01)/tp_roe,0.8)))/(1+tp_r)^5+Val!D13*(1-IF(tp_roe<=(tp_g+0.01),0.8,MIN((tp_g+0.01)/tp_roe,0.8)))/(1+tp_r)^6+Val!D13*(1-IF(tp_roe<=(tp_g+0.01),0.8,MIN((tp_g+0.01)/tp_roe,0.8)))*(1+(tp_g+0.01))/(tp_r-(tp_g+0.01))/(1+tp_r)^6))*(1+tp_r) -> 377.00876 | D30: =Val!B35 -> 396.45158 | E30: =tp_w_dcf*C30+(1-tp_w_dcf)*D30 -> 386.73017 | F30: =E30/E$27-1 -> 0.036467779
A31: 長期成長 −1pt | B31: g 3% | C31: =(tp_wA*MAX(0,Val!B8*(1-IF(tp_roe<=(tp_g-0.01),0.8,MIN((tp_g-0.01)/tp_roe,0.8)))/(1+tp_r)^1+Val!B9*(1-IF(tp_roe<=(tp_g-0.01),0.8,MIN((tp_g-0.01)/tp_roe,0.8)))/(1+tp_r)^2+Val!B10*(1-IF(tp_roe<=(tp_g-0.01),0.8,MIN((tp_g-0.01)/tp_roe,0.8)))/(1+tp_r)^3+Val!B11*(1-IF(tp_roe<=(tp_g-0.01),0.8,MIN((tp_g-0.01)/tp_roe,0.8)))/(1+tp_r)^4+Val!B12*(1-IF(tp_roe<=(tp_g-0.01),0.8,MIN((tp_g-0.01)/tp_roe,0.8)))/(1+tp_r)^5+Val!B13*(1-IF(tp_roe<=(tp_g-0.01),0.8,MIN((tp_g-0.01)/tp_roe,0.8)))/(1+tp_r)^6+Val!B13*(1-IF(tp_roe<=(tp_g-0.01),0.8,MIN((tp_g-0.01)/tp_roe,0.8)))*(1+(tp_g-0.01))/(tp_r-(tp_g-0.01))/(1+tp_r)^6)+tp_wB*MAX(0,Val!C8*(1-IF(tp_roe<=(tp_g-0.01),0.8,MIN((tp_g-0.01)/tp_roe,0.8)))/(1+tp_r)^1+Val!C9*(1-IF(tp_roe<=(tp_g-0.01),0.8,MIN((tp_g-0.01)/tp_roe,0.8)))/(1+tp_r)^2+Val!C10*(1-IF(tp_roe<=(tp_g-0.01),0.8,MIN((tp_g-0.01)/tp_roe,0.8)))/(1+tp_r)^3+Val!C11*(1-IF(tp_roe<=(tp_g-0.01),0.8,MIN((tp_g-0.01)/tp_roe,0.8)))/(1+tp_r)^4+Val!C12*(1-IF(tp_roe<=(tp_g-0.01),0.8,MIN((tp_g-0.01)/tp_roe,0.8)))/(1+tp_r)^5+Val!C13*(1-IF(tp_roe<=(tp_g-0.01),0.8,MIN((tp_g-0.01)/tp_roe,0.8)))/(1+tp_r)^6+Val!C13*(1-IF(tp_roe<=(tp_g-0.01),0.8,MIN((tp_g-0.01)/tp_roe,0.8)))*(1+(tp_g-0.01))/(tp_r-(tp_g-0.01))/(1+tp_r)^6)+tp_wC*MAX(0,Val!D8*(1-IF(tp_roe<=(tp_g-0.01),0.8,MIN((tp_g-0.01)/tp_roe,0.8)))/(1+tp_r)^1+Val!D9*(1-IF(tp_roe<=(tp_g-0.01),0.8,MIN((tp_g-0.01)/tp_roe,0.8)))/(1+tp_r)^2+Val!D10*(1-IF(tp_roe<=(tp_g-0.01),0.8,MIN((tp_g-0.01)/tp_roe,0.8)))/(1+tp_r)^3+Val!D11*(1-IF(tp_roe<=(tp_g-0.01),0.8,MIN((tp_g-0.01)/tp_roe,0.8)))/(1+tp_r)^4+Val!D12*(1-IF(tp_roe<=(tp_g-0.01),0.8,MIN((tp_g-0.01)/tp_roe,0.8)))/(1+tp_r)^5+Val!D13*(1-IF(tp_roe<=(tp_g-0.01),0.8,MIN((tp_g-0.01)/tp_roe,0.8)))/(1+tp_r)^6+Val!D13*(1-IF(tp_roe<=(tp_g-0.01),0.8,MIN((tp_g-0.01)/tp_roe,0.8)))*(1+(tp_g-0.01))/(tp_r-(tp_g-0.01))/(1+tp_r)^6))*(1+tp_r) -> 331.87816 | D31: =Val!B35 -> 396.45158 | E31: =tp_w_dcf*C31+(1-tp_w_dcf)*D31 -> 364.16487 | F31: =E31/E$27-1 -> -0.024009027
A32: DCF 權重 0.3 | B32: Comparable 0.7 | C32: =(tp_wA*MAX(0,Val!B8*(1-IF(tp_roe<=tp_g,0.8,MIN(tp_g/tp_roe,0.8)))/(1+tp_r)^1+Val!B9*(1-IF(tp_roe<=tp_g,0.8,MIN(tp_g/tp_roe,0.8)))/(1+tp_r)^2+Val!B10*(1-IF(tp_roe<=tp_g,0.8,MIN(tp_g/tp_roe,0.8)))/(1+tp_r)^3+Val!B11*(1-IF(tp_roe<=tp_g,0.8,MIN(tp_g/tp_roe,0.8)))/(1+tp_r)^4+Val!B12*(1-IF(tp_roe<=tp_g,0.8,MIN(tp_g/tp_roe,0.8)))/(1+tp_r)^5+Val!B13*(1-IF(tp_roe<=tp_g,0.8,MIN(tp_g/tp_roe,0.8)))/(1+tp_r)^6+Val!B13*(1-IF(tp_roe<=tp_g,0.8,MIN(tp_g/tp_roe,0.8)))*(1+tp_g)/(tp_r-tp_g)/(1+tp_r)^6)+tp_wB*MAX(0,Val!C8*(1-IF(tp_roe<=tp_g,0.8,MIN(tp_g/tp_roe,0.8)))/(1+tp_r)^1+Val!C9*(1-IF(tp_roe<=tp_g,0.8,MIN(tp_g/tp_roe,0.8)))/(1+tp_r)^2+Val!C10*(1-IF(tp_roe<=tp_g,0.8,MIN(tp_g/tp_roe,0.8)))/(1+tp_r)^3+Val!C11*(1-IF(tp_roe<=tp_g,0.8,MIN(tp_g/tp_roe,0.8)))/(1+tp_r)^4+Val!C12*(1-IF(tp_roe<=tp_g,0.8,MIN(tp_g/tp_roe,0.8)))/(1+tp_r)^5+Val!C13*(1-IF(tp_roe<=tp_g,0.8,MIN(tp_g/tp_roe,0.8)))/(1+tp_r)^6+Val!C13*(1-IF(tp_roe<=tp_g,0.8,MIN(tp_g/tp_roe,0.8)))*(1+tp_g)/(tp_r-tp_g)/(1+tp_r)^6)+tp_wC*MAX(0,Val!D8*(1-IF(tp_roe<=tp_g,0.8,MIN(tp_g/tp_roe,0.8)))/(1+tp_r)^1+Val!D9*(1-IF(tp_roe<=tp_g,0.8,MIN(tp_g/tp_roe,0.8)))/(1+tp_r)^2+Val!D10*(1-IF(tp_roe<=tp_g,0.8,MIN(tp_g/tp_roe,0.8)))/(1+tp_r)^3+Val!D11*(1-IF(tp_roe<=tp_g,0.8,MIN(tp_g/tp_roe,0.8)))/(1+tp_r)^4+Val!D12*(1-IF(tp_roe<=tp_g,0.8,MIN(tp_g/tp_roe,0.8)))/(1+tp_r)^5+Val!D13*(1-IF(tp_roe<=tp_g,0.8,MIN(tp_g/tp_roe,0.8)))/(1+tp_r)^6+Val!D13*(1-IF(tp_roe<=tp_g,0.8,MIN(tp_g/tp_roe,0.8)))*(1+tp_g)/(tp_r-tp_g)/(1+tp_r)^6))*(1+tp_r) -> 349.79481 | D32: =Val!B35 -> 396.45158 | E32: =0.3*C32+(1-0.3)*D32 -> 382.45455 | F32: =E32/E$27-1 -> 0.025008774
A33: DCF 權重 0.7 | B33: Comparable 0.3 | C33: =(tp_wA*MAX(0,Val!B8*(1-IF(tp_roe<=tp_g,0.8,MIN(tp_g/tp_roe,0.8)))/(1+tp_r)^1+Val!B9*(1-IF(tp_roe<=tp_g,0.8,MIN(tp_g/tp_roe,0.8)))/(1+tp_r)^2+Val!B10*(1-IF(tp_roe<=tp_g,0.8,MIN(tp_g/tp_roe,0.8)))/(1+tp_r)^3+Val!B11*(1-IF(tp_roe<=tp_g,0.8,MIN(tp_g/tp_roe,0.8)))/(1+tp_r)^4+Val!B12*(1-IF(tp_roe<=tp_g,0.8,MIN(tp_g/tp_roe,0.8)))/(1+tp_r)^5+Val!B13*(1-IF(tp_roe<=tp_g,0.8,MIN(tp_g/tp_roe,0.8)))/(1+tp_r)^6+Val!B13*(1-IF(tp_roe<=tp_g,0.8,MIN(tp_g/tp_roe,0.8)))*(1+tp_g)/(tp_r-tp_g)/(1+tp_r)^6)+tp_wB*MAX(0,Val!C8*(1-IF(tp_roe<=tp_g,0.8,MIN(tp_g/tp_roe,0.8)))/(1+tp_r)^1+Val!C9*(1-IF(tp_roe<=tp_g,0.8,MIN(tp_g/tp_roe,0.8)))/(1+tp_r)^2+Val!C10*(1-IF(tp_roe<=tp_g,0.8,MIN(tp_g/tp_roe,0.8)))/(1+tp_r)^3+Val!C11*(1-IF(tp_roe<=tp_g,0.8,MIN(tp_g/tp_roe,0.8)))/(1+tp_r)^4+Val!C12*(1-IF(tp_roe<=tp_g,0.8,MIN(tp_g/tp_roe,0.8)))/(1+tp_r)^5+Val!C13*(1-IF(tp_roe<=tp_g,0.8,MIN(tp_g/tp_roe,0.8)))/(1+tp_r)^6+Val!C13*(1-IF(tp_roe<=tp_g,0.8,MIN(tp_g/tp_roe,0.8)))*(1+tp_g)/(tp_r-tp_g)/(1+tp_r)^6)+tp_wC*MAX(0,Val!D8*(1-IF(tp_roe<=tp_g,0.8,MIN(tp_g/tp_roe,0.8)))/(1+tp_r)^1+Val!D9*(1-IF(tp_roe<=tp_g,0.8,MIN(tp_g/tp_roe,0.8)))/(1+tp_r)^2+Val!D10*(1-IF(tp_roe<=tp_g,0.8,MIN(tp_g/tp_roe,0.8)))/(1+tp_r)^3+Val!D11*(1-IF(tp_roe<=tp_g,0.8,MIN(tp_g/tp_roe,0.8)))/(1+tp_r)^4+Val!D12*(1-IF(tp_roe<=tp_g,0.8,MIN(tp_g/tp_roe,0.8)))/(1+tp_r)^5+Val!D13*(1-IF(tp_roe<=tp_g,0.8,MIN(tp_g/tp_roe,0.8)))/(1+tp_r)^6+Val!D13*(1-IF(tp_roe<=tp_g,0.8,MIN(tp_g/tp_roe,0.8)))*(1+tp_g)/(tp_r-tp_g)/(1+tp_r)^6))*(1+tp_r) -> 349.79481 | D33: =Val!B35 -> 396.45158 | E33: =0.7*C33+(1-0.7)*D33 -> 363.79184 | F33: =E33/E$27-1 -> -0.025008774
A40: 案例區塊：份額流失（低）（情境 B）
A41: 項目 | B41: 單位 | C41: FY2025A | D41: FY2026A（錨點） | E41: FY2027 | F41: FY2028 | G41: FY2029 | H41: 說明
A42: A. 日曆年 AI 光學（本節 D–G 欄＝CY2026–CY2029；D 欄＝CY2026 校準年）
A43: AI 可插拔光模組市場 × 情境顆數係數（日曆年） | B43: US$B | D43: =mplB_26*1 -> 29.753262 | E43: =mplB_27*1*1 -> 54.688309 | F43: =mplB_28*um28_B*1 -> 48.9706 | G43: =mplB_29*um29_B*1 -> 66.987208 | H43: 本節欄位為日曆年
A44: AI CPO 光學市場 × 情境顆數係數（日曆年） | B44: US$B | D44: =mcpB_26*1 -> 0.300538 | E44: =mcpB_27*1 -> 1.691391 | F44: =mcpB_28*um28_B -> 2.5774 | G44: =mcpB_29*um29_B -> 4.992628
A45: Fabrinet 光模組有效份額（CY2026 校準）＝ CY2026 光模組與其他 ÷ 可插拔市場 | B45: % | D45: =tr_cy26/D43 -> 0.042352132 | H45: Derived：CY2026 CPO 營收視為 0；代工營收含料件，屬「有效」份額
A46: 份額相對值（÷ CY2026） | B46: x | D46: =1 -> 1 | E46: =RLO_27 -> 0.8 | F46: =RLO_28 -> 0.7 | G46: =RLO_29 -> 0.6
A47: 光模組有效份額（日曆年） | B47: % | D47: =$D$45*D46 -> 0.042352132 | E47: =$D$45*E46 -> 0.033881706 | F47: =$D$45*F46 -> 0.029646492 | G47: =$D$45*G46 -> 0.025411279
A48: 單價係數（相對網通模型） | B48: x | D48: =1 -> 1 | E48: =pxr_27 -> 1 | F48: =pxr_28 -> 1 | G48: =pxr_29 -> 1
A49: Fabrinet 占 CPO 光學金額 | B49: % | D49: =0 -> 0 | E49: =cpo_27 -> 0.05 | F49: =cpo_28 -> 0.1 | G49: =cpo_29 -> 0.15
A50: 光模組與其他營收（日曆年） | B50: US$B | D50: =tr_cy26 -> 1.2601141 | E50: =E43*E47*E48+E44*E49 -> 1.9375027 | F50: =F43*F47*F48+F44*F49 -> 1.7095465 | G50: =G43*G47*G48+G44*G49 -> 2.4511248
A51: B. 會計年度營收（本節起 C–G 欄＝FY2025–FY2029）
A52: AI 情境係數（會計年度；DCI、HPC 用） | B52: x | C52: =1 -> 1 | D52: =1 -> 1 | E52: =1 -> 1 | F52: =(1-hw)+hw*um28_B -> 0.908 | G52: =(1-hw)*um28_B+hw*um29_B -> 0.823 | H52: 同字母顆數係數依日曆年上半年比重換算；FY2027 為 1
A53: 光模組與其他 | B53: US$B | C53: =a25_tr -> 1.1691744 | D53: =a26_tr -> 1.1638855 | E53: =h1_27+hw*E50 -> 1.5675653 | F53: =(1-hw)*E50+hw*F50 -> 1.8326429 | G53: =(1-hw)*F50+hw*G50 -> 2.0506726 | H53: FY2027＝CY2026 下半年（Q 頁）＋ hw × CY2027；FY2028＝（1 − hw）× CY2027 ＋ hw × CY2028
A54: DCI 基準路徑（未乘情境係數） | B54: US$B | C54: =a25_dci -> 0.41055471 | D54: =a26_dci -> 0.7331 | E54: =h1dci*(2+h2_dci) -> 1.2531935 | F54: =E54*(1+g_dci_28) -> 1.5038322 | G54: =F54*(1+g_dci_29) -> 1.6542154
A55: DCI（資料中心互連） | B55: US$B | C55: =C54*C52 -> 0.41055471 | D55: =D54*D52 -> 0.7331 | E55: =E54*E52 -> 1.2531935 | F55: =F54*F52 -> 1.3654796 | G55: =G54*G52 -> 1.3614193
A56: HPC 基準路徑（未乘情境係數） | B56: US$B | C56: =a25_hpc -> 0 | D56: =a26_hpc -> 0.3261 | E56: =h1hpc*(2+h2_hpc) -> 0.5669664 | F56: =E56*(1+g_hpc_28) -> 0.65201136 | G56: =F56*(1+g_hpc_29) -> 0.7172125
A57: HPC（高效能運算） | B57: US$B | C57: =C56*C52 -> 0 | D57: =D56*D52 -> 0.3261 | E57: =E56*E52 -> 0.5669664 | F57: =F56*F52 -> 0.59202631 | G57: =G56*G52 -> 0.59026588
A58: 資料中心 | B58: US$B | C58: =C53+C55+C57 -> 1.5797291 | D58: =D53+D55+D57 -> 2.2230855 | E58: =E53+E55+E57 -> 3.3877252 | F58: =F53+F55+F57 -> 3.7901488 | G58: =G53+G55+G57 -> 4.0023577
A59: 通訊基礎設施 | B59: US$B | C59: =a25_ci -> 1.0497334 | D59: =a26_ci -> 1.5454853 | E59: =h1ci*(2+h2_ci) -> 1.7611985 | F59: =E59*(1+g_ci_28) -> 1.8668704 | G59: =F59*(1+g_ci_29) -> 1.960214
A60: 車用、工業與其他 | B60: US$B | C60: =a25_aio -> 0.78986454 | D60: =a26_aio -> 0.87252624 | E60: =h1aio*(2+h2_aio) -> 0.97224507 | F60: =E60*(1+g_aio_28) -> 1.0208573 | G60: =F60*(1+g_aio_29) -> 1.0719002
A61: 營收 | B61: US$B | C61: =C58+C59+C60 -> 3.419327 | D61: =D58+D59+D60 -> 4.641097 | E61: =E58+E59+E60 -> 6.1211688 | F61: =F58+F59+F60 -> 6.6778766 | G61: =G58+G59+G60 -> 7.0344718
A62: 營收年增 | B62: % | D62: =D61/C61-1 -> 0.357313 | E62: =E61/D61-1 -> 0.3189056 | F62: =F61/E61-1 -> 0.09094795 | G62: =G61/F61-1 -> 0.053399502
A63: 資料中心 ÷ 營收 | B63: % | C63: =C58/C61 -> 0.462 | D63: =D58/D61 -> 0.479 | E63: =E58/E61 -> 0.55344417 | F63: =F58/F61 -> 0.56756796 | G63: =G58/G61 -> 0.5689635
A64: C. 損益（non-GAAP）
A65: 毛利率 | B65: % | C65: =a25_gp/a25_rev -> 0.12394398 | D65: =a26_gp/a26_rev -> 0.12237839 | E65: =gm_27 -> 0.123 | F65: =gm_28 -> 0.123 | G65: =gm_29 -> 0.123 | H65: FY2027 起為輸入路徑（成本加成代工；新廠爬坡與料件占比）
A66: 毛利 | B66: US$B | C66: =C61*C65 -> 0.423805 | D66: =D61*D65 -> 0.56797 | E66: =E61*E65 -> 0.75290376 | F66: =F61*F65 -> 0.82137882 | G66: =G61*G65 -> 0.86524004
A67: 營業費用（基準路徑） | B67: US$B | C67: =a25_opx -> 0.063093 | D67: =a26_opx -> 0.067907 | E67: =D67*(1+MAX(0,phi*E62)) -> 0.072531372 | F67: =E67*(1+MAX(0,phi*F62)) -> 0.073939995 | G67: =F67*(1+MAX(0,phi*G62)) -> 0.074783122
A68: 營業費用 | B68: US$B | C68: =C67 -> 0.063093 | D68: =D67 -> 0.067907 | E68: =E67+0*E61 -> 0.072531372 | F68: =F67+0*F61 -> 0.073939995 | G68: =G67+0*G61 -> 0.074783122
A69: 營業利益 | B69: US$B | C69: =C66-C68 -> 0.360712 | D69: =D66-D68 -> 0.500063 | E69: =E66-E68 -> 0.68037239 | F69: =F66-F68 -> 0.74743882 | G69: =G66-G68 -> 0.79045692
A70: 營業利益率 | B70: % | C70: =C69/C61 -> 0.1054921 | D70: =D69/D61 -> 0.10774672 | E70: =E69/E61 -> 0.11115073 | F70: =F69/F61 -> 0.11192762 | G70: =G69/G61 -> 0.11236905
A71: 業外淨收益（利息、匯兌、其他） | B71: US$B | C71: =a25_oth -> 0.030733 | D71: =a26_oth -> 0.035483 | E71: =int_f -> 0.03 | F71: =int_f -> 0.03 | G71: =int_f -> 0.03
A72: 稅前利益 | B72: US$B | C72: =C69+C71 -> 0.391445 | D72: =D69+D71 -> 0.535546 | E72: =E69+E71 -> 0.71037239 | F72: =F69+F71 -> 0.77743882 | G72: =G69+G71 -> 0.82045692
A73: 淨利 | B73: US$B | C73: =a25_ni -> 0.368792 | D73: =a26_ni -> 0.510907 | E73: =E72*(1-(tx)) -> 0.67485377 | F73: =F72*(1-(tx)) -> 0.73856688 | G73: =G72*(1-(tx)) -> 0.77943407
A74: 淨利率 | B74: % | C74: =C73/C61 -> 0.10785514 | D74: =D73/D61 -> 0.11008324 | E74: =E73/E61 -> 0.11024917 | F74: =F73/F61 -> 0.11059906 | G74: =G73/G61 -> 0.11080207
A75: 稀釋股數 | B75: 十億股 | C75: =a25_sh -> 0.036267 | D75: =a26_sh -> 0.036252 | E75: =sh_q1*(1+sh_g) -> 0.0363 | F75: =E75*(1+sh_g) -> 0.0363 | G75: =F75*(1+sh_g) -> 0.0363
A76: EPS | B76: US$ | C76: =C73/C75 -> 10.168804 | D76: =D73/D75 -> 14.093209 | E76: =E73/E75 -> 18.591013 | F76: =F73/F75 -> 20.346195 | G76: =G73/G75 -> 21.472013
A77: EPS 年增 | B77: % | D77: =D76/C76-1 -> 0.38592594 | E77: =E76/D76-1 -> 0.31914694 | F77: =F76/E76-1 -> 0.094410243 | G77: =G76/F76-1 -> 0.055333091
A80: 案例區塊：份額大增（高）（情境 B）
A81: 項目 | B81: 單位 | C81: FY2025A | D81: FY2026A（錨點） | E81: FY2027 | F81: FY2028 | G81: FY2029 | H81: 說明
A82: A. 日曆年 AI 光學（本節 D–G 欄＝CY2026–CY2029；D 欄＝CY2026 校準年）
A83: AI 可插拔光模組市場 × 情境顆數係數（日曆年） | B83: US$B | D83: =mplB_26*1 -> 29.753262 | E83: =mplB_27*1*1 -> 54.688309 | F83: =mplB_28*um28_B*1 -> 48.9706 | G83: =mplB_29*um29_B*1 -> 66.987208 | H83: 本節欄位為日曆年
A84: AI CPO 光學市場 × 情境顆數係數（日曆年） | B84: US$B | D84: =mcpB_26*1 -> 0.300538 | E84: =mcpB_27*1 -> 1.691391 | F84: =mcpB_28*um28_B -> 2.5774 | G84: =mcpB_29*um29_B -> 4.992628
A85: Fabrinet 光模組有效份額（CY2026 校準）＝ CY2026 光模組與其他 ÷ 可插拔市場 | B85: % | D85: =tr_cy26/D83 -> 0.042352132 | H85: Derived：CY2026 CPO 營收視為 0；代工營收含料件，屬「有效」份額
A86: 份額相對值（÷ CY2026） | B86: x | D86: =1 -> 1 | E86: =RHI_27 -> 1.15 | F86: =RHI_28 -> 1.25 | G86: =RHI_29 -> 1.3
A87: 光模組有效份額（日曆年） | B87: % | D87: =$D$85*D86 -> 0.042352132 | E87: =$D$85*E86 -> 0.048704952 | F87: =$D$85*F86 -> 0.052940165 | G87: =$D$85*G86 -> 0.055057772
A88: 單價係數（相對網通模型） | B88: x | D88: =1 -> 1 | E88: =pxr_27 -> 1 | F88: =pxr_28 -> 1 | G88: =pxr_29 -> 1
A89: Fabrinet 占 CPO 光學金額 | B89: % | D89: =0 -> 0 | E89: =cpo_27 -> 0.05 | F89: =cpo_28 -> 0.1 | G89: =cpo_29 -> 0.15
A90: 光模組與其他營收（日曆年） | B90: US$B | D90: =tr_cy26 -> 1.2601141 | E90: =E83*E87*E88+E84*E89 -> 2.748161 | F90: =F83*F87*F88+F84*F89 -> 2.8502516 | G90: =G83*G87*G88+G84*G89 -> 4.4370606
A91: B. 會計年度營收（本節起 C–G 欄＝FY2025–FY2029）
A92: AI 情境係數（會計年度；DCI、HPC 用） | B92: x | C92: =1 -> 1 | D92: =1 -> 1 | E92: =1 -> 1 | F92: =(1-hw)+hw*um28_B -> 0.908 | G92: =(1-hw)*um28_B+hw*um29_B -> 0.823 | H92: 同字母顆數係數依日曆年上半年比重換算；FY2027 為 1
A93: 光模組與其他 | B93: US$B | C93: =a25_tr -> 1.1691744 | D93: =a26_tr -> 1.1638855 | E93: =h1_27+hw*E90 -> 1.9404681 | F93: =(1-hw)*E90+hw*F90 -> 2.7951227 | G93: =(1-hw)*F90+hw*G90 -> 3.5801838 | H93: FY2027＝CY2026 下半年（Q 頁）＋ hw × CY2027；FY2028＝（1 − hw）× CY2027 ＋ hw × CY2028
A94: DCI 基準路徑（未乘情境係數） | B94: US$B | C94: =a25_dci -> 0.41055471 | D94: =a26_dci -> 0.7331 | E94: =h1dci*(2+h2_dci) -> 1.2531935 | F94: =E94*(1+g_dci_28) -> 1.5038322 | G94: =F94*(1+g_dci_29) -> 1.6542154
A95: DCI（資料中心互連） | B95: US$B | C95: =C94*C92 -> 0.41055471 | D95: =D94*D92 -> 0.7331 | E95: =E94*E92 -> 1.2531935 | F95: =F94*F92 -> 1.3654796 | G95: =G94*G92 -> 1.3614193
A96: HPC 基準路徑（未乘情境係數） | B96: US$B | C96: =a25_hpc -> 0 | D96: =a26_hpc -> 0.3261 | E96: =h1hpc*(2+h2_hpc) -> 0.5669664 | F96: =E96*(1+g_hpc_28) -> 0.65201136 | G96: =F96*(1+g_hpc_29) -> 0.7172125
A97: HPC（高效能運算） | B97: US$B | C97: =C96*C92 -> 0 | D97: =D96*D92 -> 0.3261 | E97: =E96*E92 -> 0.5669664 | F97: =F96*F92 -> 0.59202631 | G97: =G96*G92 -> 0.59026588
A98: 資料中心 | B98: US$B | C98: =C93+C95+C97 -> 1.5797291 | D98: =D93+D95+D97 -> 2.2230855 | E98: =E93+E95+E97 -> 3.760628 | F98: =F93+F95+F97 -> 4.7526286 | G98: =G93+G95+G97 -> 5.5318689
A99: 通訊基礎設施 | B99: US$B | C99: =a25_ci -> 1.0497334 | D99: =a26_ci -> 1.5454853 | E99: =h1ci*(2+h2_ci) -> 1.7611985 | F99: =E99*(1+g_ci_28) -> 1.8668704 | G99: =F99*(1+g_ci_29) -> 1.960214
A100: 車用、工業與其他 | B100: US$B | C100: =a25_aio -> 0.78986454 | D100: =a26_aio -> 0.87252624 | E100: =h1aio*(2+h2_aio) -> 0.97224507 | F100: =E100*(1+g_aio_28) -> 1.0208573 | G100: =F100*(1+g_aio_29) -> 1.0719002
A101: 營收 | B101: US$B | C101: =C98+C99+C100 -> 3.419327 | D101: =D98+D99+D100 -> 4.641097 | E101: =E98+E99+E100 -> 6.4940716 | F101: =F98+F99+F100 -> 7.6403564 | G101: =G98+G99+G100 -> 8.5639831
A102: 營收年增 | B102: % | D102: =D101/C101-1 -> 0.357313 | E102: =E101/D101-1 -> 0.39925358 | F102: =F101/E101-1 -> 0.17651249 | G102: =G101/F101-1 -> 0.1208879
A103: 資料中心 ÷ 營收 | B103: % | C103: =C98/C101 -> 0.462 | D103: =D98/D101 -> 0.479 | E103: =E98/E101 -> 0.57908632 | F103: =F98/F101 -> 0.62204279 | G103: =G98/G101 -> 0.6459458
A104: C. 損益（non-GAAP）
A105: 毛利率 | B105: % | C105: =a25_gp/a25_rev -> 0.12394398 | D105: =a26_gp/a26_rev -> 0.12237839 | E105: =gm_27 -> 0.123 | F105: =gm_28 -> 0.123 | G105: =gm_29 -> 0.123 | H105: FY2027 起為輸入路徑（成本加成代工；新廠爬坡與料件占比）
A106: 毛利 | B106: US$B | C106: =C101*C105 -> 0.423805 | D106: =D101*D105 -> 0.56797 | E106: =E101*E105 -> 0.79877081 | F106: =F101*F105 -> 0.93976384 | G106: =G101*G105 -> 1.0533699
A107: 營業費用（基準路徑） | B107: US$B | C107: =a25_opx -> 0.063093 | D107: =a26_opx -> 0.067907 | E107: =D107*(1+MAX(0,phi*E102)) -> 0.073696479 | F107: =E107*(1+MAX(0,phi*F102)) -> 0.076474261 | G107: =F107*(1+MAX(0,phi*G102)) -> 0.078448384
A108: 營業費用 | B108: US$B | C108: =C107 -> 0.063093 | D108: =D107 -> 0.067907 | E108: =E107+0*E101 -> 0.073696479 | F108: =F107+0*F101 -> 0.076474261 | G108: =G107+0*G101 -> 0.078448384
A109: 營業利益 | B109: US$B | C109: =C106-C108 -> 0.360712 | D109: =D106-D108 -> 0.500063 | E109: =E106-E108 -> 0.72507433 | F109: =F106-F108 -> 0.86328957 | G109: =G106-G108 -> 0.97492153
A110: 營業利益率 | B110: % | C110: =C109/C101 -> 0.1054921 | D110: =D109/D101 -> 0.10774672 | E110: =E109/E101 -> 0.11165173 | F110: =F109/F101 -> 0.11299075 | G110: =G109/G101 -> 0.11383973
A111: 業外淨收益（利息、匯兌、其他） | B111: US$B | C111: =a25_oth -> 0.030733 | D111: =a26_oth -> 0.035483 | E111: =int_f -> 0.03 | F111: =int_f -> 0.03 | G111: =int_f -> 0.03
...

Sheet Sources
A1: 來源（公司原文＝SEC 8-K 新聞稿與 10-K；法說會內容經第三方轉述，待人工複核）
A2: 公司：FY2026 第四季與全年財報新聞稿（8-K Exhibit 99.1；損益、non-GAAP 調節、Pillar Two、Q1 指引、資產負債表） | B2: https://www.sec.gov/Archives/edgar/data/0001408710/000140871026000026/fn-2026811xex991q426.htm
A3: 公司：FY2026 第三季財報新聞稿（8-K Exhibit 99.1） | B3: https://www.sec.gov/Archives/edgar/data/0001408710/000140871026000014/fn-2026504xex991q326.htm
A4: 公司：FY2026 10-K（三類營收比重、客戶集中度、Pillar Two、股數） | B4: https://www.sec.gov/Archives/edgar/data/0001408710/000140871026000028/fn-20260626.htm
A5: 二手：Webull 法說會逐字稿（FY2026 Q4；類別營收、產能、CPO／NPO、客戶） | B5: https://www.webull.com/news/15420495044125696
A6: 二手：Nasdaq 法說會重點（類別定義：DCI、HPC 屬資料中心） | B6: https://www.nasdaq.com/articles/fabrinet-q4-earnings-call-highlights
A7: 二手：Pulse 2.0（Q4 類別營收、DCI 與 HPC 各季） | B7: https://pulse2.com/fabrinet-data-center-revenue-jumps-68-to-669-million-and-becomes-51-of-quarterly-sales-as-dci-more-than-doubles/
A8: 二手：Zacks（TradingView；FY2026 Q3 舊分類營收：datacom、telecom、DCI、HPC） | B8: https://www.tradingview.com/news/zacks:01f406102094b:0-fn-q3-earnings-beat-estimates-revenues-up-on-strong-telecom-hpc/
A9: 二手：AOL／Motley Fool 法說會逐字稿（FY2026 Q2；HPC、DCI、AWS 第二供應商） | B9: https://www.aol.com/articles/fabrinet-fn-q2-2026-earnings-232305108.html
A10: 共識：stockanalysis（股價 10-23、forward PE、FY2027 共識、目標價、ROE） | B10: https://stockanalysis.com/stocks/fn/statistics/；https://stockanalysis.com/stocks/fn/forecast/
A11: 共識：MarketBeat（FY2027／FY2028 EPS、52 週區間、目標價、下次財報估計日 2026-11-02） | B11: https://www.marketbeat.com/stocks/NYSE/FN/
A12: 共識：tickflow（FY2028 營收與 EPS） | B12: https://www.tickflow.io/stock/FN/forecast
A13: 資料商：stockanalysis 損益表與資產負債表（FY2022–FY2026；ROE、淨利率） | B13: https://stockanalysis.com/stocks/fn/financials/；https://stockanalysis.com/stocks/fn/financials/balance-sheet/
... A16: 同業：stockanalysis forward PE（COHR、LITE、JBL、CLS、FLEX；2026-10-23） | B16: https://stockanalysis.com/stocks/cohr/statistics/；https://stockanalysis.com/stocks/lite/statistics/；https://stockanalysis.com/stocks/jbl/statistics/；https://stockanalysis.com/stocks/cls/statistics/；https://stockanalysis.com/stocks/flex/statistics/
A17: 市場層：markets/network、tsmc、innolight 成品（本 repo，唯讀）；markets/memory SCEN_UNITS（核對）
A18: 待補（人工）：光模組（datacom）新分類金額；NVIDIA 光模組營收；CPO 營收；泰國 BOI 稅率明細；共識家數與 FY2028 營收第二來源；前瞻 P/E 歷史（Bloomberg）；FY2027 Q1 財報日期公司公告 | B18: 未找到
A19: SemiAnalysis | B19: 未使用
