Workbook

Sheet README
A1: 世界先進（5347.TWO；VIS）個股模型 v0.1（AI 半導體 Project：代工層，8 吋成熟製程與特殊製程晶圓代工；樣板 guc/、營收結構參考 tsmc/） 2026-10-31
A2: 版本：v0.1（初版）。營收＝8 吋晶圓（產能 × 稼動率 × 美元售價 × 匯率）＋VSMC 新加坡 12 吋廠（FY2027 第一季量產；產能 × 稼動率 × 售價）。滾入 3Q26 營收實績（月營收）與 3Q26 毛利率指引；3Q26 財報 2026-11-05 公布後更新。本版未做先驗。
A3: 模型命題：世界先進以 8 吋成熟與特殊製程為主（2Q26 電源管理 IC 77%、面板驅動 IC 約 19%），獲利由 8 吋稼動率與價格循環決定；AI 伺服器電源帶動電源管理 IC 與分離式元件，稼動率回到 90% 以上，AI 相關占營收由上半年個位數升到下半年雙位數。新加坡 VSMC 12 吋廠（與 NXP 合資，持股 60%）2027 年第一季量產，初期折舊重；中國成熟製程擴產是價格的下行風險。
A4: 核心問題：8 吋稼動率與售價回升能走多遠（情境 A 稼動率 95%、售價 +6%），VSMC 量產初期的毛利率與非控制權益讓 EPS 增加多少；現價約 25 倍 FY2026 EPS、24 倍未來 12 月 EPS（模型 B），與同業前瞻 P/E 中位數 27.4 倍差多少。
A6: 會計年度＝日曆年，FY(t)＝CY(t)，不平移。FY2025A 實績、FY2026 錨點（1Q、2Q26 實績＋3Q26 營收實績與毛利率指引＋4Q26 假設）、FY2027–FY2029 驅動因子推導、FY2030–FY2032 收斂法。金額：十億新台幣；EPS：新台幣（基本）；口徑：歸屬母公司淨利（TIFRS）。晶圓：千片 8 吋；VSMC：千片 12 吋。
A8: 驅動因子 → 推導量（行業變數讀 Siliconomics；8 吋稼動率與售價為公司層級，待併入 Siliconomics）
A9: 8 吋晶圓：產能（FY2026 330.6 萬片，公司；FY2027–29 持平，粗線寬轉細線寬）× 稼動率（A／B／C：FY2027 95%／90%／80%、FY2028 94%／86%／74%、FY2029 93%／87%／78%）× 美元售價（FY2026 約 643 美元／片；FY2027 +6%／+3%／−3%、FY2028 +2%／0／−5%、FY2029 +1%／0／−2%）× 匯率 32（Siliconomics fx_twd）。
A10: VSMC 12 吋：產能 FY2027 144、FY2028 360、FY2029 504 千片（2029 年滿載月產能約 4.4 萬片）× 稼動率 90%／80%／65% × 售價 1,800 美元（Assumed）；毛利率 FY2027 5%／−5%／−20%、FY2028 20%／12%／0、FY2029 25%／18%／5%（Assumed，含折舊）；NXP 非控制權益 40%。AI 相關占營收只作記憶列（FY2026 10%、FY2027 起 25%／20%／15%），不進營收加總。
A11: 成本：8 吋銷貨成本內折舊（FY2026 約 86.6 億元＝公司預估折舊 96.2 億 × 0.9；年增 3%／2%／0）＋每片現金成本（FY2026 殘差，年增 2%）；營業費用彈性 0.5、年增下限 3%；營業外每年 15 億元、稅率 15%、股數 19.07 億股。
A12: 校準：FY2026 ＝ 1Q、2Q26 實績＋3Q26 營收實績（月營收 157.0 億元）與毛利率指引中點 33.5%＋4Q26 假設（營收季增 3%、毛利率 34%）。8 吋售價與每片現金成本以 FY2026 校準；不用券商數字（只在 Recon 對帳）。
A13: 估值：Val 第 0 節目標價＝0.5 × DCF 目標價（股東現金流＝EPS ×（1 − g／ROE），FY2027–32 明確期＋永續，r 10%、g 4%，三情境權重 0.3／0.5／0.2，情境價值負值取 0）＋0.5 × Comparable 目標價（聯電、格芯、中芯港股、高塔前瞻 P/E 中位數 × 12 個月後前瞻 EPS；不含 A 股；世界先進本身 Bloomberg 前瞻倍數待取，相對倍數調整係數自動取 1.0）；另列 Comparable 單獨目標價、市場共識目標價與差距拆解。十年 P/E 規則值 × FY2027 EPS 保留為參考（不是目標價）。本版未做先驗，無 Andy 合理 P/E 對照。
A14: 預估期間：FY2027–FY2029 由驅動因子推導；FY2030 起為收斂法，非驅動因子推導（營收年增由 FY2029 線性收斂到 fade_g、淨利率收斂到 fade_m，FY2032 達到；PL 頁灰底）。十年平均淨利率未找到，B、C 依工作單以 FY2029 × 0.8 代替。
... A21: 公司特有：8 吋稼動率 FY2027 95%／90%／80%、FY2028 94%／86%／74%、FY2029 93%／87%／78%；售價 FY2027 +6%／+3%／−3%、FY2028 +2%／0／−5%、FY2029 +1%／0／−2%（C＝中國成熟製程擴產的價格壓力）；VSMC 稼動率 90%／80%／65%、毛利率 FY2027 5%／−5%／−20%；AI 相關占比（記憶列）25%／20%／15%。
A23: ="投資建議："&Val!B135&"（依上檔空間固定規則）" -> 投資建議：中立（依上檔空間固定規則）
A24: ="重點觀察 1：目標價 NT$"&TEXT(Val!$B$39,"#,##0.00")&"（DCF "&TEXT(Val!$B$24,"#,##0.00")&"、Comparable（相對倍數調整後）"&TEXT(tp_comp_adj,"#,##0.00")&"；DCF 權重 "&TEXT(tp_w_dcf,"0%")&"），比現價 "&TEXT(px,"#,##0.00")&"（2026-10-22）"&IF(Val!$B$42>=0,"高 "&TEXT(Val!$B$42,"0.0%"),"低 "&TEXT(-Val!$B$42,"0.0%"))&"，級距 "&Val!$B$134&"、投資建議 "&Val!$B$135&"。相對倍數調整係數 "&TEXT(rm_factor,"0.00")&"（本公司 10 年前瞻倍數中位數 ÷ 同業的中位數，夾在 0.5–2.0；Val 第 0.5 節），調整前加權上檔空間 "&TEXT((tp_w_dcf*Val!$B$24+(1-tp_w_dcf)*Val!$B$35)/px-1,"+0.0%;−0.0%")&"；Comparable 單獨（市場主流同業法、未調整）為 "&TEXT(Val!$B$43,"+0.0%;−0.0%")&"。" -> 重點觀察 1：目標價 NT$126.59（DCF 77.48、Comparable（相對倍數調整後）175.69；DCF 權重 50%），比現價 161.00（2026-10-22）低 21.4%，級距 0%～−25%、投資建議 中立。相對倍數調整係數 1.00（本公司 10 年前瞻倍數中位數 ÷ 同業的中位數，夾在 0.5–2.0；Val 第 0.5 節），調整前加權上檔空間 −21.4%；Comparable 單獨（市場主流同業法、未調整）為 +9.1%。
A25: 重點觀察 2：DCF 與 Comparable 差距大：DCF 77.5 只有現價的 48%，因 ROE 近三年平均 12.9%、再投資率 31%，且情境 B 的 FY2028 EPS 6.37 低於 FY2027 的 6.88（8 吋稼動率 86%、售價持平，VSMC 量產初期毛利率 12%）；Comparable 用同業前瞻 P/E 中位數 27.4 倍，世界先進本身 Bloomberg 前瞻倍數待取，未做相對倍數調整。DCF 權重 0.3／0.7 使加權目標價 +15.5%／−15.5%，是最大的單一敏感度；上檔空間 −21.4% 距放空門檻 −25% 只差 3.6 個百分點。
A26: 重點觀察 3：VSMC 新加坡 12 吋廠 2027 年第一季量產：模型 FY2027 12 吋占營收 9.8%（情境 A；研究機構 12%）、FY2029 27%；8 吋售價 ±3% 使加權目標價 ±11.9%、匯率 30.5 使 −18.8%，VSMC 產能 ±20% 只有 ±1.2%。下一個檢驗點是 2026-11-05 的 3Q26 財報與法說（3Q26 毛利率 vs 指引 32.5–34.5%、4Q26 指引、VSMC 認證與量產時程）。
A28: 相對倍數調整（tools/relative_multiple.py；Val 第 0.5 節）已含在加權目標價：Comparable（相對倍數調整後）＝同業前瞻倍數中位數 × 本公司 10 年相對同業的倍數比（Bloomberg 前瞻倍數）。「Comparable 目標價（市場主流同業法）」維持不調整。重點觀察的數字以本版重算值撰寫（第 1 點第一句為公式）。
A30: v0.1（2026-10-31）：依個股模型原則第 8 節調整 In 頁呈現（數值不變）。In 頁 D／F 欄名改「敏感度低」「敏感度高」（只用於 Sens 頁、不進目標價）；In 頁最後新增「情境驅動對照」一節，把上方各情境專屬輸入三情境並排（只引用上方各列，純展示）；HTML 驅動因子一節分「情境驅動」與「單一參數」兩張表。

Sheet In
A1: In — 輸入（藍字；基準欄 E，低 D、高 F）。金額：十億新台幣（NT$B）；晶圓：千片（8 吋）；售價：美元／片；匯率：新台幣／美元。公司財報與法說為 Interested-party（公司說法）或 Verified（財報數字）；券商、資料商、媒體為 Interested-party。【v0.1】基準欄 E 進主模型；D／F＝敏感度低／高，只用於 Sens 頁（一次動一個參數）、不進目標價；情境 A／B／C 的驅動見本頁最後一節「情境驅動對照」。
A2: 標記：Verified／Interested-party／Analogy／Assumed／Derived；Analogy、Assumed 以情境或 Sens 區間呈現，不當點估計。行業變數讀 Siliconomics v0.10（siliconomics/data/siliconomics_snapshot_v0.10.json）；成熟製程稼動率與售價屬公司層級，說明欄標「待併入 Siliconomics」。SemiAnalysis 未使用
A3: 鍵 | B3: 項目 | C3: 單位 | D3: 敏感度低 | E3: 基準 | F3: 敏感度高 | G3: 標記 | H3: 來源1 | I3: 來源2／說明
A4: A. 行業變數（Siliconomics v0.10（siliconomics/data/siliconomics_snapshot_v0.10.json）；A／B／C 讀同字母上游，不自訂行業路徑）
A5: fx | B5: 匯率（FY2027 起；美元售價換算） | C5: NT$/US$ | D5: 30.5 | E5: 32 | F5: 33 | G5: Assumed | H5: Siliconomics v0.10（siliconomics/data/siliconomics_snapshot_v0.10.json）｜fx_twd | I5: Siliconomics 共用匯率（2026–2029）；與台積電、聯發科等台股模型同值
A6: B. 產能與稼動率（8 吋；公司層級，待併入 Siliconomics：Siliconomics 尚無成熟製程稼動率）
A7: cap_26 | B7: FY2026 產能（8 吋，千片／年） | C7: 千片 | E7: =Q!G7 -> 3306 | G7: Derived | H7: 科技新報 2026-05-05（1Q26 法說）：2026 年 8 吋產能約 330.6 萬片、年減約 4%（粗線寬淘汰並升級為細線寬） | I7: 季度產能以全年 ÷ 4 計（1Q26 歲修使月產能季減 9%，未拆分）
A8: capg27 | B8: FY2027 產能年增 | C8: % | E8: 0 | G8: Assumed | H8: Assumed：8 吋不新建廠；粗線寬轉細線寬、去瓶頸（公司 2Q26 法說） | I8: 三情境相同（產能為公司已核准的擴產；待併入 Siliconomics）
A9: capg28 | B9: FY2028 產能年增 | C9: % | E9: 0 | G9: Assumed | H9: 同上 | I9: 三情境相同（產能為公司已核准的擴產；待併入 Siliconomics）
A10: capg29 | B10: FY2029 產能年增 | C10: % | E10: 0 | G10: Assumed | H10: 同上 | I10: 三情境相同（產能為公司已核准的擴產；待併入 Siliconomics）
A11: cap_adj | B11: 產能係數（Sens 用；FY2027 起各年同乘） | C11: x | D11: 0.95 | E11: 1 | F11: 1.05 | G11: Assumed | H11: 無 | I11: ±5%：擴產時程提前或延後
A12: ut27_A | B12: FY2027 平均稼動率（情境 A） | C12: % | E12: 0.95 | G12: Assumed | H12: 優分析 2026-08-04（2Q26 法說轉述）：3Q26 稼動率約 90%、4Q26 可能超過 90%；出貨受設備與產能瓶頸限制 | I12: A 最有利、C 最不利（C＝中國成熟製程擴產的價格與份額壓力）；待併入 Siliconomics
A13: ut27_B | B13: FY2027 平均稼動率（情境 B） | C13: % | E13: 0.9 | G13: Assumed | H13: 同上 | I13: 待併入 Siliconomics
A14: ut27_C | B14: FY2027 平均稼動率（情境 C） | C14: % | E14: 0.8 | G14: Assumed | H14: 同上 | I14: 待併入 Siliconomics
A15: ut28_A | B15: FY2028 平均稼動率（情境 A） | C15: % | E15: 0.94 | G15: Assumed | H15: 同上 | I15: A 最有利、C 最不利（C＝中國成熟製程擴產的價格與份額壓力）；待併入 Siliconomics
A16: ut28_B | B16: FY2028 平均稼動率（情境 B） | C16: % | E16: 0.86 | G16: Assumed | H16: 同上 | I16: 待併入 Siliconomics
A17: ut28_C | B17: FY2028 平均稼動率（情境 C） | C17: % | E17: 0.74 | G17: Assumed | H17: 同上 | I17: 待併入 Siliconomics
A18: ut29_A | B18: FY2029 平均稼動率（情境 A） | C18: % | E18: 0.93 | G18: Assumed | H18: 同上 | I18: A 最有利、C 最不利（C＝中國成熟製程擴產的價格與份額壓力）；待併入 Siliconomics
A19: ut29_B | B19: FY2029 平均稼動率（情境 B） | C19: % | E19: 0.87 | G19: Assumed | H19: 同上 | I19: 待併入 Siliconomics
A20: ut29_C | B20: FY2029 平均稼動率（情境 C） | C20: % | E20: 0.78 | G20: Assumed | H20: 同上 | I20: 待併入 Siliconomics
A21: ut_adj | B21: 稼動率調整（Sens 用；FY2027 起各年加減，上限 98%） | C21: pt | D21: -0.03 | E21: 0 | F21: 0.03 | G21: Assumed | H21: 無 | I21: ±3 個百分點
A22: C. 平均售價（美元，每片 8 吋；公司層級，待併入 Siliconomics：Siliconomics 尚無成熟製程價格）
A23: asp_26 | B23: FY2026 平均售價（8 吋晶圓；美元／片） | C23: US$/片 | E23: =a26_rev/a26_ship/fx_26*1000000 -> 643.46941 | G23: Derived | H23: FY2026 營收 ÷ 出貨 ÷ 匯率（VSMC 尚未量產） | I23: 校準年；FY2027 起依情境年增
A24: asp27_A | B24: FY2027 平均售價年增（美元；情境 A） | C24: % | E24: 0.06 | G24: Assumed | H24: 工商時報 2026-08-06（法人）：花旗：產能吃緊、漲價空間增加；公司 2026 年長約到期影響低個位數（NOWnews 2026-02-03） | I24: A＝漲價延續；C＝中國成熟製程擴產造成價格壓力；待併入 Siliconomics
A25: asp27_B | B25: FY2027 平均售價年增（美元；情境 B） | C25: % | E25: 0.03 | G25: Assumed | H25: 同上 | I25: 待併入 Siliconomics
A26: asp27_C | B26: FY2027 平均售價年增（美元；情境 C） | C26: % | E26: -0.03 | G26: Assumed | H26: 同上 | I26: 待併入 Siliconomics
A27: asp28_A | B27: FY2028 平均售價年增（美元；情境 A） | C27: % | E27: 0.02 | G27: Assumed | H27: 同上 | I27: A＝漲價延續；C＝中國成熟製程擴產造成價格壓力；待併入 Siliconomics
A28: asp28_B | B28: FY2028 平均售價年增（美元；情境 B） | C28: % | E28: 0 | G28: Assumed | H28: 同上 | I28: 待併入 Siliconomics
A29: asp28_C | B29: FY2028 平均售價年增（美元；情境 C） | C29: % | E29: -0.05 | G29: Assumed | H29: 同上 | I29: 待併入 Siliconomics
A30: asp29_A | B30: FY2029 平均售價年增（美元；情境 A） | C30: % | E30: 0.01 | G30: Assumed | H30: 同上 | I30: A＝漲價延續；C＝中國成熟製程擴產造成價格壓力；待併入 Siliconomics
A31: asp29_B | B31: FY2029 平均售價年增（美元；情境 B） | C31: % | E31: 0 | G31: Assumed | H31: 同上 | I31: 待併入 Siliconomics
A32: asp29_C | B32: FY2029 平均售價年增（美元；情境 C） | C32: % | E32: -0.02 | G32: Assumed | H32: 同上 | I32: 待併入 Siliconomics
A33: asp_adj | B33: 售價水準調整（Sens 用；FY2027 起各年同乘 1＋x） | C33: % | D33: -0.03 | E33: 0 | F33: 0.03 | G33: Assumed | H33: 無 | I33: ±3%
A34: D. VSMC（新加坡 12 吋廠，與 NXP 合資，世界先進持股 60%、合併報表）：產能 × 稼動率 × 售價；毛利率路徑；非控制權益 40%
A35: vcap27 | B35: FY2027 VSMC 產能（12 吋，千片／年） | C35: 千片 | E35: 144 | G35: Assumed | H35: 公司：VSMC 2027 年第一季量產、良率 99%（工商時報 2026-08-06 轉述） | I35: 三情境相同（產能為公司規劃）
A36: vcap28 | B36: FY2028 VSMC 產能（12 吋，千片／年） | C36: 千片 | E36: 360 | G36: Assumed | H36: Assumed：月產能爬坡到約 3 萬片 | I36: 三情境相同（產能為公司規劃）
A37: vcap29 | B37: FY2029 VSMC 產能（12 吋，千片／年） | C37: 千片 | E37: 504 | G37: Assumed | H37: 公司：2029 年滿載月產能約 4.4 萬片（原 5.5 萬片；科技新報 2026-05-05） | I37: 三情境相同（產能為公司規劃）
A38: vcap_adj | B38: VSMC 產能係數（Sens 用） | C38: x | D38: 0.8 | E38: 1 | F38: 1.2 | G38: Assumed | H38: 無 | I38: ±20%：量產爬坡快慢
A39: vut_A | B39: VSMC 稼動率（FY2027 起；情境 A） | C39: % | E39: 0.9 | G39: Assumed | H39: 公司：2027 年量產時稼動率「會令人滿意」（NOWnews 2026-02-03） | I39: A 最有利、C 最不利
A40: vut_B | B40: VSMC 稼動率（FY2027 起；情境 B） | C40: % | E40: 0.8 | G40: Assumed | H40: 同上 | I40: —
A41: vut_C | B41: VSMC 稼動率（FY2027 起；情境 C） | C41: % | E41: 0.65 | G41: Assumed | H41: 同上 | I41: —
A42: vasp | B42: VSMC 平均售價（美元／12 吋片） | C42: US$ | D42: 1500 | E42: 1800 | F42: 2100 | G42: Assumed | H42: Assumed：VSMC 製程 130–40 奈米；公司未揭露售價 | I42: 130–40 奈米特殊製程 12 吋；公司未揭露
A43: vgm27_A | B43: FY2027 VSMC 毛利率（含折舊；情境 A） | C43: % | E43: 0.05 | G43: Assumed | H43: Assumed：總投資 67 億美元（科技新報 2026-05-05），量產初期折舊重；法人：2027 年 12 吋占營收 12%、全公司毛利率 35%（工商時報 2026-08-06） | I43: 量產初期折舊重；A 最有利、C 最不利
A44: vgm27_B | B44: FY2027 VSMC 毛利率（含折舊；情境 B） | C44: % | E44: -0.05 | G44: Assumed | H44: 同上 | I44: —
A45: vgm27_C | B45: FY2027 VSMC 毛利率（含折舊；情境 C） | C45: % | E45: -0.2 | G45: Assumed | H45: 同上 | I45: —
A46: vgm28_A | B46: FY2028 VSMC 毛利率（含折舊；情境 A） | C46: % | E46: 0.2 | G46: Assumed | H46: 同上 | I46: 量產初期折舊重；A 最有利、C 最不利
A47: vgm28_B | B47: FY2028 VSMC 毛利率（含折舊；情境 B） | C47: % | E47: 0.12 | G47: Assumed | H47: 同上 | I47: —
A48: vgm28_C | B48: FY2028 VSMC 毛利率（含折舊；情境 C） | C48: % | E48: 0 | G48: Assumed | H48: 同上 | I48: —
A49: vgm29_A | B49: FY2029 VSMC 毛利率（含折舊；情境 A） | C49: % | E49: 0.25 | G49: Assumed | H49: 同上 | I49: 量產初期折舊重；A 最有利、C 最不利
A50: vgm29_B | B50: FY2029 VSMC 毛利率（含折舊；情境 B） | C50: % | E50: 0.18 | G50: Assumed | H50: 同上 | I50: —
A51: vgm29_C | B51: FY2029 VSMC 毛利率（含折舊；情境 C） | C51: % | E51: 0.05 | G51: Assumed | H51: 同上 | I51: —
A52: vmi | B52: VSMC 非控制權益比例（NXP 持股） | C52: % | E52: 0.4 | G52: Verified | H52: 公司：世界先進出資 24 億美元持股 60%、NXP 出資 16 億美元持股 40%（科技新報 2026-05-05） | I52: 非控制權益＝VSMC 毛利 ×（1 − 稅率）× 40%（簡化：VSMC 營業費用未另計）
A53: ai_sh26 | B53: FY2026 AI 相關 ÷ 營收（記憶列） | C53: % | E53: 0.1 | G53: Interested-party | H53: 優分析 2026-08-04（2Q26 法說轉述）：AI 相關占營收上半年個位數、下半年雙位數、全年雙位數；全年 AI 營收約翻倍 | I53: 公司：全年雙位數；只作記憶列，不進營收加總
A54: ai_sh27_A | B54: FY2027 起 AI 相關 ÷ 營收（記憶列；情境 A） | C54: % | E54: 0.25 | G54: Assumed | H54: 工商時報 2026-08-06（法人）：法人：AI 相關占比由今年 10–15% 升到 30%（中介層、電源管理 IC、分離式元件供不應求） | I54: AI 需求已反映在稼動率與售價情境；本列不進營收加總
... A56: ai_sh27_C | B56: FY2027 起 AI 相關 ÷ 營收（記憶列；情境 C） | C56: % | E56: 0.15 | G56: Assumed | H56: 同上 | I56: —
A57: E. 成本：折舊（銷貨成本內）、每片現金成本、營業費用、營業外、稅、股數
A58: da_tot26 | B58: FY2026 折舊與攤銷（全公司） | C58: NT$B | E58: 9.62 | G58: Interested-party | H58: 優分析 2026-02（資本支出、折舊）：公司預估 2026 年折舊約 96.2 億元（2025 年 85.5 億元） | I58: 8 吋廠；VSMC 折舊放在 VSMC 毛利率內
A59: da_sh | B59: 折舊中計入銷貨成本的比例 | C59: % | E59: 0.9 | G59: Assumed | H59: 公司未揭露拆分；晶圓廠折舊多數計入銷貨成本 | I59: —
A60: dag_27 | B60: FY2027 銷貨成本內折舊年增 | C60: % | E60: 0.03 | G60: Assumed | H60: Assumed：8 吋去瓶頸與升級 | I60: 三情境相同（擴產已核准）
A61: dag_28 | B61: FY2028 銷貨成本內折舊年增 | C61: % | E61: 0.02 | G61: Assumed | H61: 同上 | I61: 三情境相同（擴產已核准）
A62: dag_29 | B62: FY2029 銷貨成本內折舊年增 | C62: % | E62: 0 | G62: Assumed | H62: 同上 | I62: 三情境相同（擴產已核准）
A63: dag_adj | B63: 折舊年增調整（Sens 用；FY2027 起各年加減） | C63: pt | D63: -0.05 | E63: 0 | F63: 0.05 | G63: Assumed | H63: 無 | I63: ±5 個百分點
A64: cc_g | B64: 每片現金成本年增（FY2027 起） | C64: % | D64: 0 | E64: 0.02 | F64: 0.04 | G64: Assumed | H64: 原物料、電價、人力（Assumed） | I64: 每片現金成本為 FY2026 殘差（Derived），之後依本列成長
A65: phi | B65: 營業費用成長對營收成長的彈性 | C65: x | D65: 0.3 | E65: 0.5 | F65: 0.8 | G65: Assumed | H65: FY2025 營業費用 58.8 億、1H26 約 32.7 億（Q 頁） | I65: —
A66: g_opx_min | B66: 營業費用年增下限 | C66: % | E66: 0.03 | G66: Assumed | H66: 研發、新業務投入 | I66: —
A67: nonop_f | B67: 營業外淨額（FY2027 起每年） | C67: NT$B | D67: 0.5 | E67: 1.5 | F67: 2.5 | G67: Assumed | H67: FY2025 約 14.8 億、1H26 約 11.1 億（Q 頁 Derived） | I67: VSMC 借款利息與政府補助：未找到
A68: tax | B68: 有效稅率（FY2027 起） | C68: % | D68: 0.12 | E68: 0.15 | F68: 0.2 | G68: Assumed | H68: FY2025 約 14.5%（Q 頁 Derived） | I68: —
A69: sh_g | B69: 加權股數年變動 | C69: % | E69: 0 | G69: Assumed | H69: 2Q26 淨利 ÷ EPS 推得約 19.07 億股（Q 頁） | I69: stockanalysis 流通股數 18.8 億股
A70: F. FY2026 錨點（1Q、2Q26 實績＋3Q26＋4Q26 指引或假設）
A71: fx_26 | B71: FY2026 平均匯率 | C71: NT$/US$ | E71: 31.6 | G71: Assumed | H71: 公司指引匯率：1Q26 31.3、3Q26 32（法說） | I71: 實際平均匯率：未找到
A72: ut_q1 | B72: 1Q26 稼動率 | C72: % | E72: 0.8 | G72: Assumed | H72: 公司未揭露；1Q26 月產能因歲修季減 9% | I72: —
A73: q3_gm | B73: 3Q26 毛利率（公司指引中點） | C73: % | E73: 0.335 | G73: Interested-party | H73: 優分析 2026-08-04（2Q26 法說轉述）：3Q26 指引 32.5–34.5%（匯率 32） | I73: 3Q26 財報 2026-11-05 公布後更新
A74: q3_opx | B74: 3Q26 營業費用 | C74: NT$B | E74: 1.75 | G74: Assumed | H74: 2Q26 約 16.95 億（Q 頁） | I74: —
A75: q3_nonop | B75: 3Q26 營業外淨額 | C75: NT$B | E75: 0.5 | G75: Assumed | H75: 1Q26 約 5.4 億、2Q26 約 5.8 億（Q 頁） | I75: —
A76: q3_tax | B76: 3Q26 有效稅率 | C76: % | E76: =t_h1 -> 0.14526589 | G76: Derived | H76: FY2025 有效稅率 | I76: —
A77: q4_g | B77: 4Q26 營收季增 | C77: % | E77: 0.03 | G77: Assumed | H77: 優分析 2026-08-04（2Q26 法說轉述）：第四季有機會優於第三季 | I77: —
A78: q4_ut | B78: 4Q26 稼動率 | C78: % | E78: 0.92 | G78: Interested-party | H78: 優分析 2026-08-04（2Q26 法說轉述）：4Q26 稼動率可能超過 90% | I78: 取 92%
A79: q4_gm | B79: 4Q26 毛利率 | C79: % | E79: 0.34 | G79: Assumed | H79: 3Q26 指引上半段 | I79: —
A80: q4_opx | B80: 4Q26 營業費用 | C80: NT$B | E80: 1.8 | G80: Assumed | H80: 同上 | I80: —
A81: q4_nonop | B81: 4Q26 營業外淨額 | C81: NT$B | E81: 0.5 | G81: Assumed | H81: 同上 | I81: —
A82: q4_tax | B82: 4Q26 有效稅率 | C82: % | E82: =t_h1 -> 0.14526589 | G82: Derived | H82: FY2025 有效稅率 | I82: —
A83: t_h1 | B83: FY2025 有效稅率（1H26 推估稅前利益用） | C83: % | E83: =1-7.908/9.252 -> 0.14526589 | G83: Derived | H83: stockanalysis.comfinancials/：FY2025 淨利 79.08 億 ÷ 稅前約 92.52 億 | I83: 1Q、2Q26 稅前利益與所得稅：未找到
A84: q_sh | B84: 加權股數（2Q26） | C84: 十億股 | E84: =Q!D19 -> 1.9070513 | G84: Derived | H84: 2Q26 淨利 ÷ EPS | I84: stockanalysis 流通股數 18.8 億股
A85: G. 公司說法、共識與券商（只作 Recon 對帳，不作校準）
A86: cons_rev26 | B86: 共識營收 FY2026（只作對照，不進模型） | C86: NT$B | E86: 58.5 | G86: Interested-party | H86: stockanalysis.comforecast/（15 位；2026-09-21 擷取） | I86: 區間 56.8–59.7；FY2027 起共識為付費資料：未找到
A87: cons_eps26 | B87: 共識 EPS FY2026（只作對照，不進模型） | C87: NT$ | E87: 6.05 | G87: Interested-party | H87: stockanalysis.comforecast/（2026-09-21 擷取） | I87: 區間 5.46–6.50
A88: an_eps27 | B88: 研究機構 FY2027 EPS（約 8 元） | C88: NT$ | E88: 8 | G88: Interested-party | H88: 工商時報 2026-08-06（法人） | I88: FY2028 超過一個股本（未給數字）
A89: an_gm27 | B89: 研究機構 FY2027 毛利率 | C89: % | E89: 0.35 | G89: Interested-party | H89: 工商時報 2026-08-06（法人） | I89: 今年 32.8%
A90: an_12sh27 | B90: 研究機構 FY2027 12 吋占營收 | C90: % | E90: 0.12 | G90: Interested-party | H90: 工商時報 2026-08-06（法人） | I90: —
A91: co_q3_gm | B91: 公司：3Q26 毛利率指引中點 | C91: % | E91: 0.335 | G91: Interested-party | H91: 優分析 2026-08-04（2Q26 法說轉述） | I91: 32.5–34.5%
A92: H. 價格與市場倍數
A93: px | B93: 股價（2026-10-22 收盤） | C93: NT$ | E93: 161 | G93: Interested-party | H93: stockanalysis.comhistory/：10-22 收盤 161.00 | I93: 10-23 以後收盤：未找到（stockanalysis 歷史頁只到 10-22）
A94: pe_ttm | B94: 近 12 月 P/E（現價 ÷ 近 12 月 EPS 4.57） | C94: x | E94: =px/4.57 -> 35.229759 | G94: Derived | H94: stockanalysis 近 12 月 EPS（至 2026-06） | I94: —
A95: fpe | B95: 前瞻 P/E（stockanalysis，2026-09-11；股價 157.5） | C95: x | E95: 23.41 | G95: Interested-party | H95: stockanalysis.com | I95: —
A96: cons_feps | B96: 共識前瞻 12 月 EPS（2026-09-11 股價 ÷ 前瞻 P/E） | C96: NT$ | E96: =157.5/fpe -> 6.7278941 | G96: Derived | H96: stockanalysis 前瞻 P/E 23.41（股價 157.5） | I96: 共識前瞻 EPS 的直接數字：未找到
A97: cons_tp | B97: 市場共識目標價（賣方平均） | C97: NT$ | E97: 183.18 | G97: Interested-party | H97: stockanalysis：17 位分析師平均 183.18（2026-09-21 擷取；中位數 187、區間 89–220） | I97: 工商時報 2026-08-06：花旗 185、法人最高 220
A98: nim_5 | B98: 近五年平均淨利率（FY2021–25；對照用） | C98: % | E98: =AVERAGE(11.82/43.951,15.28/51.694,7.37/38.273,7.046/44.055,7.908/48.591) -> 0.2159536 | G98: Derived | H98: stockanalysis 財報頁：FY2021–25 營收與淨利 | I98: 十年平均（2016–2025）：未找到（2016–2020 未取得）；收斂法依工作單改用最後一年 × 0.8
A99: I. 目標價與收斂法參數（黃底；Assumed，Andy 可改）
A100: tp_wA | B100: 目標價情境權重 A（A 順利／B 平平／C 不如預期） | C100: % | E100: 0.3 | G100: Assumed | H100: Andy 可改（工作單 2026-10-25 預設 A 0.3／B 0.5／C 0.2） | I100: 三者合計應為 100%
A101: tp_wB | B101: 目標價情境權重 B（A 順利／B 平平／C 不如預期） | C101: % | E101: 0.5 | G101: Assumed | H101: Andy 可改（工作單 2026-10-25 預設 A 0.3／B 0.5／C 0.2） | I101: 三者合計應為 100%
...

Sheet Q
A1: Q — 實績與 FY2026 錨點（十億新台幣；EPS 為新台幣、基本；股數為十億股；晶圓為千片 8 吋）。藍字＝輸入（公司法說、媒體轉述、stockanalysis）；黑字＝公式
A2: FY2026 錨點＝1Q、2Q26 實績＋3Q26 營收實績（月營收）與公司指引（毛利率 32.5–34.5% 中點）＋4Q26 假設；3Q26 財報與法說 2026-11-05（stockanalysis），公布後更新
A3: 項目 | B3: FY2025A | C3: 1Q26（實績） | D3: 2Q26（實績） | E3: 3Q26（營收實績＋指引） | F3: 4Q26（模型） | G3: FY2026 錨點 | H3: 標記 | I3: 來源1 | J3: 來源2／說明
A4: 營收 | B4: 48.591 | C4: 12.532 | D4: 14.245 | E4: =42.479-26.777 -> 15.702 | F4: =E4*(1+q4_g) -> 16.17306 | G4: =SUM(C4:F4) -> 58.65206 | H4: Verified／Assumed（4Q） | I4: FY2025：stockanalysis 財報頁、科技新報 2026-02-03；1Q26：科技新報 2026-05-05；2Q26：優分析 2026-08-04；3Q26 營收：科技新報 2026-10-08（月營收） | J4: 3Q26：前 9 月 424.79 億 − 1H26 267.77 億（月營收）；4Q26＝3Q26 ×（1＋季增）
A5: 晶圓出貨（千片，8 吋） | C5: =C7*C6 -> 661.2 | D5: =D7*D6 -> 719.055 | E5: =E7*E6 -> 743.85 | F5: =F7*F6 -> 760.38 | G5: =SUM(C5:F5) -> 2884.485 | H5: Derived | I5: 產能 × 稼動率 | J5: 公司只揭露出貨季增率（1Q26 約 +3%、2Q26 指引 +11–13%）
A6: 稼動率 | C6: =ut_q1 -> 0.8 | D6: 0.87 | E6: 0.9 | F6: =q4_ut -> 0.92 | G6: =G5/G7 -> 0.8725 | H6: Interested-party／Assumed | I6: https://www.ctee.com.tw/news/20260806700216-430201：2Q26 約 87%；公司：3Q26 約 90%（指引） | J6: FY2026 欄＝出貨合計 ÷ 產能合計
A7: 產能（千片，8 吋） | C7: =3306/4 -> 826.5 | D7: =3306/4 -> 826.5 | E7: =3306/4 -> 826.5 | F7: =3306/4 -> 826.5 | G7: =SUM(C7:F7) -> 3306 | H7: Derived | I7: 公司：2026 年 8 吋產能約 330.6 萬片 ÷ 4 | J7: 季度產能未揭露（Assumed 平均分配）
A8: 平均售價（全部營收 ÷ 出貨；美元／片） | C8: =C4/C5/fx_26*1000000 -> 599.79171 | D8: =D4/D5/fx_26*1000000 -> 626.92164 | E8: =E4/E5/fx_26*1000000 -> 668.00932 | F8: =F4/F5/fx_26*1000000 -> 673.092 | G8: =G4/G5/fx_26*1000000 -> 643.46941 | H8: Derived | I8: 營收 ÷ 出貨 ÷ 匯率 | J8: 公司：1Q26 平均售價季減約 4%；2Q26、3Q26 指引季增 2–4%
A9: 毛利 | B9: 13.654 | C9: =C4*0.293 -> 3.671876 | D9: =D4*0.323 -> 4.601135 | E9: =E4*q3_gm -> 5.26017 | F9: =F4*q4_gm -> 5.4988404 | G9: =SUM(C9:F9) -> 19.032021 | H9: Verified（毛利率 × 營收）／Interested-party（3Q 指引）／Assumed（4Q） | I9: FY2025：stockanalysis 財報頁、科技新報 2026-02-03；1Q26：科技新報 2026-05-05；2Q26：優分析 2026-08-04；3Q26 營收：科技新報 2026-10-08（月營收） | J9: 毛利率 1Q26 29.3%、2Q26 32.3%（公司法說）
A10: 毛利率 | B10: =B9/B4 -> 0.28099854 | C10: =C9/C4 -> 0.293 | D10: =D9/D4 -> 0.323 | E10: =E9/E4 -> 0.335 | F10: =F9/F4 -> 0.34 | G10: =G9/G4 -> 0.32449025 | H10: Derived | I10: — | J10: 公司：4Q25 27.5%、1Q26 29.3%、2Q26 32.3%
A11: 營業費用 | B11: =B9-B12 -> 5.881 | C11: =C9-C12 -> 1.579032 | D11: =D9-D12 -> 1.695155 | E11: =q3_opx -> 1.75 | F11: =q4_opx -> 1.8 | G11: =SUM(C11:F11) -> 6.824187 | H11: Derived／Assumed | I11: FY2025：stockanalysis 財報頁、科技新報 2026-02-03；1Q26：科技新報 2026-05-05；2Q26：優分析 2026-08-04；3Q26 營收：科技新報 2026-10-08（月營收） | J11: 毛利 − 營業利益
A12: 營業利益 | B12: 7.773 | C12: =C4*0.167 -> 2.092844 | D12: =D4*0.204 -> 2.90598 | E12: =E9-E11 -> 3.51017 | F12: =F9-F11 -> 3.6988404 | G12: =SUM(C12:F12) -> 12.207834 | H12: Verified（營業利益率 × 營收）／Derived | I12: FY2025：stockanalysis 財報頁、科技新報 2026-02-03；1Q26：科技新報 2026-05-05；2Q26：優分析 2026-08-04；3Q26 營收：科技新報 2026-10-08（月營收） | J12: 營業利益率 1Q26 16.7%、2Q26 20.4%
A13: 營業外淨額 | B13: =B14-B12 -> 1.479 | C13: =C14-C12 -> 0.53487375 | D13: =D14-D12 -> 0.57463457 | E13: =q3_nonop -> 0.5 | F13: =q4_nonop -> 0.5 | G13: =SUM(C13:F13) -> 2.1095083 | H13: Derived／Assumed | I13: FY2025：stockanalysis 財報頁、科技新報 2026-02-03；1Q26：科技新報 2026-05-05；2Q26：優分析 2026-08-04；3Q26 營收：科技新報 2026-10-08（月營收） | J13: 稅前 − 營業利益
A14: 稅前利益 | B14: 9.252 | C14: =C17/(1-t_h1) -> 2.6277178 | D14: =D17/(1-t_h1) -> 3.4806146 | E14: =E12+E13 -> 4.01017 | F14: =F12+F13 -> 4.1988404 | G14: =SUM(C14:F14) -> 14.317343 | H14: Derived | I14: FY2025：stockanalysis 財報頁、科技新報 2026-02-03；1Q26：科技新報 2026-05-05；2Q26：優分析 2026-08-04；3Q26 營收：科技新報 2026-10-08（月營收） | J14: FY2025 由 stockanalysis 稅前淨利率推得；1Q、2Q26＝淨利 ÷（1 − FY2025 稅率）
A15: 所得稅 | B15: =B14-B17-B18 -> 1.344 | C15: =C14-C17-C18 -> 0.38171775 | D15: =D14-D17-D18 -> 0.50561457 | E15: =E14*q3_tax -> 0.58254091 | F15: =F14*q4_tax -> 0.60994828 | G15: =SUM(C15:F15) -> 2.0798215 | H15: Derived／Assumed | I15: FY2025：stockanalysis 財報頁、科技新報 2026-02-03；1Q26：科技新報 2026-05-05；2Q26：優分析 2026-08-04；3Q26 營收：科技新報 2026-10-08（月營收） | J15: 稅前 −（歸屬母公司淨利＋非控制權益）
A16: 有效稅率 | B16: =B15/B14 -> 0.14526589 | C16: =C15/C14 -> 0.14526589 | D16: =D15/D14 -> 0.14526589 | E16: =E15/E14 -> 0.14526589 | F16: =F15/F14 -> 0.14526589 | G16: =G15/G14 -> 0.14526589 | H16: Derived | I16: — | J16: —
A17: 歸屬母公司淨利 | B17: 7.908 | C17: 2.246 | D17: 2.975 | E17: =E14-E15-E18 -> 3.4276291 | F17: =F14-F15-F18 -> 3.5888921 | G17: =SUM(C17:F17) -> 12.237521 | H17: Verified／Derived | I17: FY2025：stockanalysis 財報頁、科技新報 2026-02-03；1Q26：科技新報 2026-05-05；2Q26：優分析 2026-08-04；3Q26 營收：科技新報 2026-10-08（月營收） | J17: 公司：1Q26 22.46 億、2Q26 29.75 億
A18: 非控制權益 | B18: 0 | C18: 0 | D18: 0 | E18: 0 | F18: 0 | G18: =SUM(C18:F18) -> 0 | H18: Derived／Assumed | I18: FY2025：stockanalysis 財報頁、科技新報 2026-02-03；1Q26：科技新報 2026-05-05；2Q26：優分析 2026-08-04；3Q26 營收：科技新報 2026-10-08（月營收） | J18: VSMC 量產前費用的非控制權益：未拆分（取 0）
A19: 加權股數（十億股） | B19: =7.908/4.22 -> 1.8739336 | C19: =2.246/1.18 -> 1.9033898 | D19: =2.975/1.56 -> 1.9070513 | E19: =q_sh -> 1.9070513 | F19: =q_sh -> 1.9070513 | G19: =AVERAGE(C19:F19) -> 1.9061359 | H19: Derived | I19: 淨利 ÷ EPS（公司） | J19: —
A20: EPS（基本） | B20: =B17/B19 -> 4.22 | C20: =C17/C19 -> 1.18 | D20: =D17/D19 -> 1.56 | E20: =E17/E19 -> 1.797345 | F20: =F17/F19 -> 1.8819065 | G20: =G17/G19 -> 6.4200675 | H20: Derived | I20: 淨利 ÷ 股數 | J20: —
A21: 公司揭露 EPS | B21: 4.22 | C21: 1.18 | D21: 1.56 | H21: Verified | I21: 公司：FY2025 4.22（stockanalysis）、1Q26 1.18、2Q26 1.56 | J21: 3Q26 EPS：2026-11-05 公布
A23: FY2026 錨點的檢查（參考；校準未使用券商數字）
A24: FY2026 營收年增 | B24: =G4/B4-1 -> 0.20705604
A25: 3Q26 營收季增 | B25: =E4/D4-1 -> 0.1022815
A26: FY2026 毛利率 | B26: =G10 -> 0.32449025
A27: FY2026 營業利益率 | B27: =G12/G4 -> 0.20813991
A28: 檢查：1H26 營收 自算 − 公司 267.77（應約為 0） | B28: =C4+D4-26.777 -> 0
A29: 檢查：1H26 EPS 自算 − 公司 2.74（應約為 0） | B29: =C20+D20-2.74 -> 0
A30: FY2026 平均售價（美元／8 吋片） | B30: =G8 -> 643.46941
A34: 官方報告分部與產品別（最近完整年度＋最近四季 3Q25–2Q26；分部原則第 3 條）
A35: 項目 | B35: FY2025A | C35: 3Q25 | D35: 4Q25 | E35: 1Q26 | F35: 2Q26 | G35: 最近四季合計 | H35: 標記 | I35: 來源1 | J35: 來源2／說明
A36: 晶圓代工營收（單一營運部門） | B36: 48.591 | C36: =12.594/1.02 -> 12.347059 | D36: 12.594 | E36: =C4 -> 12.532 | F36: =D4 -> 14.245 | G36: =SUM(C36:F36) -> 51.718059 | H36: Verified | I36: 公司：單一營運部門（晶圓代工）；4Q25 125.94 億（季增 2%） | J36: 3Q25＝4Q25 ÷ 1.02（Derived，四捨五入誤差另註）
A37: 電源管理 IC | F37: =F36*0.77 -> 10.96865 | H37: Interested-party | I37: https://uanalyze.com.tw/articles/8378052767：2Q26 電源管理 IC 77% | J37: 其他季比重：未找到
A38: 大尺寸面板驅動 IC | F38: =F36*0.12 -> 1.7094 | H38: Interested-party | I38: https://uanalyze.com.tw/articles/8378052767：2Q26 12% | J38: —
A39: 中小尺寸面板驅動 IC | F39: =F36*0.07 -> 0.99715 | H39: Interested-party | I39: https://uanalyze.com.tw/articles/8378052767：2Q26 約 7% | J39: —
A40: 其他（含分離式元件） | F40: =F36-F37-F38-F39 -> 0.5698 | H40: Derived | I40: 差額（公司：其他約 4%） | J40: 分離式元件未單獨揭露
A41: 檢查：分部合計 − 合併營收 | B41: =B36-B4 -> 0 | D41: =D36-12.594 -> 0 | E41: =E36-C4 -> 0 | F41: =F36-D4 -> 0 | H41: Derived | I41: — | J41: 應為 0（3Q25 為推得，不列核對）
A42: 檢查：子列合計 − 分部（2Q26） | F42: =F37+F38+F39+F40-F36 -> 0 | H42: Derived | I42: — | J42: 應為 0

Sheet Units
A1: Units — 世界先進 8 吋晶圓（千片）、稼動率、售價，與 VSMC 12 吋廠（三情境）。8 吋產能 FY2026 為公司揭露；VSMC 產能為公司規劃與 Assumed 爬坡
A3: 項目 | B3: 單位 | C3: FY2026 | D3: FY2027 | E3: FY2028 | F3: FY2029 | G3: 說明
A4: 1. 8 吋晶圓：三情境稼動率、出貨與售價
A5: 稼動率（情境 A） | B5: % | C5: =PL!D64 -> 0.8725 | D5: =PL!E64 -> 0.95 | E5: =PL!F64 -> 0.94 | F5: =PL!G64 -> 0.93 | G5: PL 頁各情境推導區塊
A6: 稼動率（情境 B） | B6: % | C6: =PL!D105 -> 0.8725 | D6: =PL!E105 -> 0.9 | E6: =PL!F105 -> 0.86 | F6: =PL!G105 -> 0.87 | G6: 同上
A7: 稼動率（情境 C） | B7: % | C7: =PL!D146 -> 0.8725 | D7: =PL!E146 -> 0.8 | E7: =PL!F146 -> 0.74 | F7: =PL!G146 -> 0.78 | G7: 同上
A8: 晶圓出貨（情境 A） | B8: 千片 | C8: =PL!D65 -> 2884.485 | D8: =PL!E65 -> 3140.7 | E8: =PL!F65 -> 3107.64 | F8: =PL!G65 -> 3074.58 | G8: PL 頁各情境推導區塊
A9: 晶圓出貨（情境 B） | B9: 千片 | C9: =PL!D106 -> 2884.485 | D9: =PL!E106 -> 2975.4 | E9: =PL!F106 -> 2843.16 | F9: =PL!G106 -> 2876.22 | G9: 同上
A10: 晶圓出貨（情境 C） | B10: 千片 | C10: =PL!D147 -> 2884.485 | D10: =PL!E147 -> 2644.8 | E10: =PL!F147 -> 2446.44 | F10: =PL!G147 -> 2578.68 | G10: 同上
A11: 平均售價（美元）（情境 A） | B11: US$/片 | C11: =PL!D66 -> 643.46941 | D11: =PL!E66 -> 682.07757 | E11: =PL!F66 -> 695.71912 | F11: =PL!G66 -> 702.67631 | G11: PL 頁各情境推導區塊
A12: 平均售價（美元）（情境 B） | B12: US$/片 | C12: =PL!D107 -> 643.46941 | D12: =PL!E107 -> 662.77349 | E12: =PL!F107 -> 662.77349 | F12: =PL!G107 -> 662.77349 | G12: 同上
A13: 平均售價（美元）（情境 C） | B13: US$/片 | C13: =PL!D148 -> 643.46941 | D13: =PL!E148 -> 624.16532 | E13: =PL!F148 -> 592.95706 | F13: =PL!G148 -> 581.09792 | G13: 同上
A14: 晶圓營收（情境 A） | B14: NT$B | C14: =PL!D69 -> 58.65206 | D14: =PL!E69 -> 68.550433 | E14: =PL!F69 -> 69.185426 | F14: =PL!G69 -> 69.133905 | G14: PL 頁各情境推導區塊
A15: 晶圓營收（情境 B） | B15: NT$B | C15: =PL!D110 -> 58.65206 | D15: =PL!E110 -> 63.10452 | E15: =PL!F110 -> 60.299874 | F15: =PL!G110 -> 61.001036 | G15: 同上
A16: 晶圓營收（情境 C） | B16: NT$B | C16: =PL!D151 -> 58.65206 | D16: =PL!E151 -> 52.825358 | E16: =PL!F151 -> 46.420284 | F16: =PL!G151 -> 47.950898 | G16: 同上
A18: 2. VSMC 12 吋廠與 AI 相關（三情境）
A19: VSMC 出貨（12 吋）（情境 A） | B19: 千片 | C19: =PL!D73 -> 0 | D19: =PL!E73 -> 129.6 | E19: =PL!F73 -> 324 | F19: =PL!G73 -> 453.6 | G19: PL 頁各情境推導區塊
A20: VSMC 出貨（12 吋）（情境 B） | B20: 千片 | C20: =PL!D114 -> 0 | D20: =PL!E114 -> 115.2 | E20: =PL!F114 -> 288 | F20: =PL!G114 -> 403.2 | G20: 同上
A21: VSMC 出貨（12 吋）（情境 C） | B21: 千片 | C21: =PL!D155 -> 0 | D21: =PL!E155 -> 93.6 | E21: =PL!F155 -> 234 | F21: =PL!G155 -> 327.6 | G21: 同上
A22: VSMC 營收（情境 A） | B22: NT$B | C22: =PL!D74 -> 0 | D22: =PL!E74 -> 7.46496 | E22: =PL!F74 -> 18.6624 | F22: =PL!G74 -> 26.12736 | G22: PL 頁各情境推導區塊
A23: VSMC 營收（情境 B） | B23: NT$B | C23: =PL!D115 -> 0 | D23: =PL!E115 -> 6.63552 | E23: =PL!F115 -> 16.5888 | F23: =PL!G115 -> 23.22432 | G23: 同上
A24: VSMC 營收（情境 C） | B24: NT$B | C24: =PL!D156 -> 0 | D24: =PL!E156 -> 5.39136 | E24: =PL!F156 -> 13.4784 | F24: =PL!G156 -> 18.86976 | G24: 同上
A25: 12 吋（VSMC）÷ 營收（情境 A） | B25: % | C25: =PL!D76 -> 0 | D25: =PL!E76 -> 0.098203268 | E25: =PL!F76 -> 0.21244009 | F25: =PL!G76 -> 0.27427055 | G25: PL 頁各情境推導區塊
A26: 12 吋（VSMC）÷ 營收（情境 B） | B26: % | C26: =PL!D117 -> 0 | D26: =PL!E117 -> 0.09514649 | E26: =PL!F117 -> 0.21575089 | F26: =PL!G117 -> 0.27574024 | G26: 同上
A27: 12 吋（VSMC）÷ 營收（情境 C） | B27: % | C27: =PL!D158 -> 0 | D27: =PL!E158 -> 0.092608449 | E27: =PL!F158 -> 0.22501997 | F27: =PL!G158 -> 0.2823941 | G27: 同上
A28: AI 相關 ÷ 營收（記憶列）（情境 A） | B28: % | C28: =PL!D77 -> 0.1 | D28: =PL!E77 -> 0.25 | E28: =PL!F77 -> 0.25 | F28: =PL!G77 -> 0.25 | G28: PL 頁各情境推導區塊
A29: AI 相關 ÷ 營收（記憶列）（情境 B） | B29: % | C29: =PL!D118 -> 0.1 | D29: =PL!E118 -> 0.2 | E29: =PL!F118 -> 0.2 | F29: =PL!G118 -> 0.2 | G29: 同上
A30: AI 相關 ÷ 營收（記憶列）（情境 C） | B30: % | C30: =PL!D159 -> 0.1 | D30: =PL!E159 -> 0.15 | E30: =PL!F159 -> 0.15 | F30: =PL!G159 -> 0.15 | G30: 同上
A32: 3. 校準值（只用 FY2026 已發生的實績與錨點；不用共識、不用 FY2027 起的目標）
A33: FY2026 平均售價（美元／片） | C33: =PL!D66 -> 643.46941 | G33: 晶圓營收 ÷ 出貨 ÷ 匯率
A34: FY2026 每片現金成本（NT$K） | C34: =PL!D81 -> 10.733992 | G34: 讓 FY2026 毛利等於錨點
A35: FY2026 銷貨成本內折舊（NT$B） | C35: =PL!D80 -> 8.658 | G35: 全公司折舊 × da_sh
A37: 讀法：8 吋稼動率與售價決定 FY2027 的大部分 EPS；VSMC 從 FY2027 起放量，量產初期毛利率為負（折舊重），FY2028 起的毛利率是 C 情境下修的主因之一。

Sheet PL
A1: PL — 世界先進損益（十億新台幣；EPS 新台幣、基本；歸屬母公司）。FY2025A 實績、FY2026 錨點（三情境相同），FY2027–FY2029 由驅動因子推導，FY2030–FY2032 為收斂法。FY(t)＝CY(t)。三情境各一個完整推導區塊（本頁下方），頂端為摘要
A2: 灰底＝FY2030–FY2032 收斂法（上游顆數只到 CY2029）：營收年增線性收斂到 fade_g、淨利率線性收斂到 fade_m（In 頁 I 節），非驅動因子推導
A3: 情境／項目 | B3: 單位 | C3: FY2025A | D3: FY2026（錨點） | E3: FY2027 | F3: FY2028 | G3: FY2029 | H3: FY2030（收斂） | I3: FY2031（收斂） | J3: FY2032（收斂） | K3: 說明
A4: 情境 A
A5: 營收 | B5: NT$B | C5: =C75 -> 48.591 | D5: =D75 -> 58.65206 | E5: =E75 -> 76.015393 | F5: =F75 -> 87.847826 | G5: =G75 -> 95.261265 | H5: =H75 -> 102.52586 | I5: =I75 -> 109.51093 | J5: =J75 -> 116.08159
A6: 營收年增 | B6: % | D6: =D78 -> 0.20705604 | E6: =E78 -> 0.29603961 | F6: =F78 -> 0.15565839 | G6: =G78 -> 0.084389555 | H6: =H78 -> 0.076259703 | I6: =I78 -> 0.068129852 | J6: =J78 -> 0.06
A7: 8 吋晶圓營收 | B7: NT$B | D7: =D69 -> 58.65206 | E7: =E69 -> 68.550433 | F7: =F69 -> 69.185426 | G7: =G69 -> 69.133905
A8: VSMC 營收（12 吋） | B8: NT$B | D8: =D74 -> 0 | E8: =E74 -> 7.46496 | F8: =F74 -> 18.6624 | G8: =G74 -> 26.12736
A9: AI 相關 ÷ 營收（記憶列） | B9: % | D9: =D77 -> 0.1 | E9: =E77 -> 0.25 | F9: =F77 -> 0.25 | G9: =G77 -> 0.25
A10: 稼動率 | B10: % | D10: =D64 -> 0.8725 | E10: =E64 -> 0.95 | F10: =F64 -> 0.94 | G10: =G64 -> 0.93
A11: 平均售價（美元） | B11: US$/片 | D11: =D66 -> 643.46941 | E11: =E66 -> 682.07757 | F11: =F66 -> 695.71912 | G11: =G66 -> 702.67631
A12: 毛利率 | B12: % | C12: =C86 -> 0.28099854 | D12: =D86 -> 0.32449025 | E12: =E86 -> 0.33702973 | F12: =F86 -> 0.33144577 | G12: =G86 -> 0.33116415
A13: 營業利益率 | B13: % | C13: =C89 -> 0.1599679 | D13: =D89 -> 0.20813991 | E13: =E89 -> 0.23396769 | F13: =F89 -> 0.23532456 | G13: =G89 -> 0.23878312
A14: 歸屬母公司淨利 | B14: NT$B | C14: =C94 -> 7.908 | D14: =D94 -> 12.237521 | E14: =E94 -> 16.265469 | F14: =F94 -> 17.577795 | G14: =G94 -> 18.388939 | H14: =H94 -> 19.791274 | I14: =I94 -> 21.139651 | J14: =J94 -> 22.40803
A15: 淨利率 | B15: % | C15: =C98 -> 0.16274619 | D15: =D98 -> 0.20864606 | E15: =E98 -> 0.213976 | F15: =F98 -> 0.20009369 | G15: =G98 -> 0.1930369 | H15: =H98 -> 0.1930369 | I15: =I98 -> 0.1930369 | J15: =J98 -> 0.1930369
A16: EPS | B16: NT$ | C16: =C96 -> 4.22 | D16: =D96 -> 6.4200675 | E16: =E96 -> 8.5291201 | F16: =F96 -> 9.2172642 | G16: =G96 -> 9.6426033 | H16: =H96 -> 10.377945 | I16: =I96 -> 11.084993 | J16: =J96 -> 11.750093
A17: EPS 年增 | B17: % | D17: =D97 -> 0.521343 | E17: =E97 -> 0.32850942 | F17: =F97 -> 0.080681718 | G17: =G97 -> 0.046145922 | H17: =H97 -> 0.076259703 | I17: =I97 -> 0.068129852 | J17: =J97 -> 0.06
A19: 情境 B
A20: 營收 | B20: NT$B | C20: =C116 -> 48.591 | D20: =D116 -> 58.65206 | E20: =E116 -> 69.74004 | F20: =F116 -> 76.888674 | G20: =G116 -> 84.225356 | H20: =H116 -> 90.70619 | I20: =I116 -> 96.010069 | J20: =J116 -> 99.850472
A21: 營收年增 | B21: % | D21: =D119 -> 0.20705604 | E21: =E119 -> 0.18904672 | F21: =F119 -> 0.10250402 | G21: =G119 -> 0.095419532 | H21: =H119 -> 0.076946355 | I21: =I119 -> 0.058473177 | J21: =J119 -> 0.04
A22: 8 吋晶圓營收 | B22: NT$B | D22: =D110 -> 58.65206 | E22: =E110 -> 63.10452 | F22: =F110 -> 60.299874 | G22: =G110 -> 61.001036
A23: VSMC 營收（12 吋） | B23: NT$B | D23: =D115 -> 0 | E23: =E115 -> 6.63552 | F23: =F115 -> 16.5888 | G23: =G115 -> 23.22432
A24: AI 相關 ÷ 營收（記憶列） | B24: % | D24: =D118 -> 0.1 | E24: =E118 -> 0.2 | F24: =F118 -> 0.2 | G24: =G118 -> 0.2
A25: 稼動率 | B25: % | D25: =D105 -> 0.8725 | E25: =E105 -> 0.9 | F25: =F105 -> 0.86 | G25: =G105 -> 0.87
A26: 平均售價（美元） | B26: US$/片 | D26: =D107 -> 643.46941 | E26: =E107 -> 662.77349 | F26: =F107 -> 662.77349 | G26: =G107 -> 662.77349
A27: 毛利率 | B27: % | C27: =C127 -> 0.28099854 | D27: =D127 -> 0.32449025 | E27: =E127 -> 0.30510917 | F27: =F127 -> 0.27888416 | G27: =G127 -> 0.27690357
A28: 營業利益率 | B28: % | C28: =C130 -> 0.1599679 | D28: =D130 -> 0.20813991 | E28: =E130 -> 0.19800811 | F28: =F130 -> 0.1767619 | G28: =G130 -> 0.17922913
A29: 歸屬母公司淨利 | B29: NT$B | C29: =C135 -> 7.908 | D29: =D135 -> 12.237521 | E29: =E135 -> 13.125533 | F29: =F135 -> 12.150517 | G29: =G135 -> 12.684963 | H29: =H135 -> 13.205658 | I29: =I135 -> 13.49584 | J29: =J135 -> 13.5344
A30: 淨利率 | B30: % | C30: =C139 -> 0.16274619 | D30: =D139 -> 0.20864606 | E30: =E139 -> 0.18820657 | F30: =F139 -> 0.15802739 | G30: =G139 -> 0.15060742 | H30: =H139 -> 0.14558717 | I30: =I139 -> 0.14056692 | J30: =J139 -> 0.13554668
A31: EPS | B31: NT$ | C31: =C137 -> 4.22 | D31: =D137 -> 6.4200675 | E31: =E137 -> 6.8826326 | F31: =F137 -> 6.3713635 | G31: =G137 -> 6.6516111 | H31: =H137 -> 6.9246473 | I31: =I137 -> 7.0768102 | J31: =J137 -> 7.0970297
A32: EPS 年增 | B32: % | D32: =D138 -> 0.521343 | E32: =E138 -> 0.072049891 | F32: =F138 -> -0.074283953 | G32: =G138 -> 0.043985497 | H32: =H138 -> 0.041048143 | I32: =I138 -> 0.021974102 | J32: =J138 -> 0.0028571429
A34: 情境 C
A35: 營收 | B35: NT$B | C35: =C157 -> 48.591 | D35: =D157 -> 58.65206 | E35: =E157 -> 58.216718 | F35: =F157 -> 59.898684 | G35: =G157 -> 66.820658 | H35: =H157 -> 72.414055 | I35: =I157 -> 76.168998 | J35: =J157 -> 77.692378
A36: 營收年增 | B36: % | D36: =D160 -> 0.20705604 | E36: =E160 -> -0.007422445 | F36: =F160 -> 0.028891448 | G36: =G160 -> 0.11556138 | H36: =H160 -> 0.083707589 | I36: =I160 -> 0.051853795 | J36: =J160 -> 0.02
A37: 8 吋晶圓營收 | B37: NT$B | D37: =D151 -> 58.65206 | E37: =E151 -> 52.825358 | F37: =F151 -> 46.420284 | G37: =G151 -> 47.950898
A38: VSMC 營收（12 吋） | B38: NT$B | D38: =D156 -> 0 | E38: =E156 -> 5.39136 | F38: =F156 -> 13.4784 | G38: =G156 -> 18.86976
A39: AI 相關 ÷ 營收（記憶列） | B39: % | D39: =D159 -> 0.1 | E39: =E159 -> 0.15 | F39: =F159 -> 0.15 | G39: =G159 -> 0.15
A40: 稼動率 | B40: % | D40: =D146 -> 0.8725 | E40: =E146 -> 0.8 | F40: =F146 -> 0.74 | G40: =G146 -> 0.78
A41: 平均售價（美元） | B41: US$/片 | D41: =D148 -> 643.46941 | E41: =E148 -> 624.16532 | F41: =F148 -> 592.95706 | G41: =G148 -> 581.09792
A42: 毛利率 | B42: % | C42: =C168 -> 0.28099854 | D42: =D168 -> 0.32449025 | E42: =E168 -> 0.23828721 | F42: =F168 -> 0.16700225 | G42: =G168 -> 0.15600793
A43: 營業利益率 | B43: % | C43: =C171 -> 0.1599679 | D43: =D171 -> 0.20813991 | E43: =E171 -> 0.1175502 | F43: =F171 -> 0.046135154 | G43: =G171 -> 0.041401166
A44: 歸屬母公司淨利 | B44: NT$B | C44: =C176 -> 7.908 | D44: =D176 -> 12.237521 | E44: =E176 -> 7.4584912 | F44: =F176 -> 3.6239197 | G44: =G176 -> 3.3056993 | H44: =H176 -> 3.343584 | I44: =I176 -> 3.26575 | J44: =J176 -> 3.0748292
A45: 淨利率 | B45: % | C45: =C180 -> 0.16274619 | D45: =D180 -> 0.20864606 | E45: =E180 -> 0.12811597 | F45: =F180 -> 0.060500824 | G45: =G180 -> 0.049471217 | H45: =H180 -> 0.046173136 | I45: =I180 -> 0.042875055 | J45: =J180 -> 0.039576974
A46: EPS | B46: NT$ | C46: =C178 -> 4.22 | D46: =D178 -> 6.4200675 | E46: =E178 -> 3.9110071 | F46: =F178 -> 1.9002739 | G46: =G178 -> 1.7334087 | H46: =H178 -> 1.7532743 | I46: =I178 -> 1.7124605 | J46: =J178 -> 1.6123474
A47: EPS 年增 | B47: % | D47: =D179 -> 0.521343 | E47: =E179 -> -0.39081526 | F47: =F179 -> -0.5141216 | G47: =G179 -> -0.08781112 | H47: =H179 -> 0.011460416 | I47: =I179 -> -0.023278619 | J47: =J179 -> -0.058461538
A49: 核對（應為 0）：FY2026 模型 − 錨點
A50: 三情境：營收差（NT$B） | D50: =ABS(D75-a26_rev)+ABS(D116-a26_rev)+ABS(D157-a26_rev) -> 0
A51: 三情境：毛利差（NT$B） | D51: =ABS(D85-a26_gp)+ABS(D126-a26_gp)+ABS(D167-a26_gp) -> 0
A52: 三情境：EPS 差（NT$） | D52: =ABS(D96-a26_eps)+ABS(D137-a26_eps)+ABS(D178-a26_eps) -> 0
A60: 情境 A（順利）：8 吋稼動率 95%／94%／93%；售價 +6%／+2%／+1%；VSMC 稼動率 90%、毛利率 5%／20%／25%
A61: 項目 | B61: 單位 | C61: FY2025A | D61: FY2026（錨點） | E61: FY2027 | F61: FY2028 | G61: FY2029 | H61: FY2030（收斂） | I61: FY2031（收斂） | J61: FY2032（收斂） | K61: 說明
A62: A. 8 吋晶圓：產能 × 稼動率 × 平均售價（D 欄＝FY2026 校準年）
A63: 產能（8 吋） | B63: 千片 | D63: =cap_26 -> 3306 | E63: =D63*(1+capg27)*cap_adj -> 3306 | F63: =E63*(1+capg28) -> 3306 | G63: =F63*(1+capg29) -> 3306
A64: 平均稼動率 | B64: % | D64: =a26_ship/cap_26 -> 0.8725 | E64: =MIN(0.98,ut27_A+ut_adj) -> 0.95 | F64: =MIN(0.98,ut28_A+ut_adj) -> 0.94 | G64: =MIN(0.98,ut29_A+ut_adj) -> 0.93
A65: 晶圓出貨（8 吋） | B65: 千片 | D65: =D63*D64 -> 2884.485 | E65: =E63*E64 -> 3140.7 | F65: =F63*F64 -> 3107.64 | G65: =G63*G64 -> 3074.58
A66: 平均售價（8 吋晶圓） | B66: US$/片 | D66: =asp_26 -> 643.46941 | E66: =D66*(1+asp27_A)*(1+asp_adj) -> 682.07757 | F66: =E66*(1+asp28_A) -> 695.71912 | G66: =F66*(1+asp29_A) -> 702.67631
A67: 平均售價年增（美元） | B67: % | E67: =E66/D66-1 -> 0.06 | F67: =F66/E66-1 -> 0.02 | G67: =G66/F66-1 -> 0.01
A68: 匯率 | B68: NT$/US$ | D68: =fx_26 -> 31.6 | E68: =fx -> 32 | F68: =fx -> 32 | G68: =fx -> 32
A69: 8 吋晶圓營收 | B69: NT$B | D69: =D65*D66*D68/1000000 -> 58.65206 | E69: =E65*E66*E68/1000000 -> 68.550433 | F69: =F65*F66*F68/1000000 -> 69.185426 | G69: =G65*G66*G68/1000000 -> 69.133905
A70: B. VSMC（新加坡 12 吋廠；FY2027 第一季量產）
A71: VSMC 產能（12 吋） | B71: 千片 | D71: =0 -> 0 | E71: =vcap27*vcap_adj -> 144 | F71: =vcap28*vcap_adj -> 360 | G71: =vcap29*vcap_adj -> 504
A72: VSMC 稼動率 | B72: % | E72: =vut_A -> 0.9 | F72: =vut_A -> 0.9 | G72: =vut_A -> 0.9
A73: VSMC 出貨（12 吋） | B73: 千片 | D73: =0 -> 0 | E73: =E71*E72 -> 129.6 | F73: =F71*F72 -> 324 | G73: =G71*G72 -> 453.6
A74: VSMC 營收（12 吋） | B74: NT$B | D74: =0 -> 0 | E74: =E73*vasp*E68/1000000 -> 7.46496 | F74: =F73*vasp*F68/1000000 -> 18.6624 | G74: =G73*vasp*G68/1000000 -> 26.12736
A75: 營收 | B75: NT$B | C75: =a25_rev -> 48.591 | D75: =D69+D74 -> 58.65206 | E75: =E69+E74 -> 76.015393 | F75: =F69+F74 -> 87.847826 | G75: =G69+G74 -> 95.261265 | H75: =G75*(1+H78) -> 102.52586 | I75: =H75*(1+I78) -> 109.51093 | J75: =I75*(1+J78) -> 116.08159 | K75: FY2030 起為收斂法：營收年增由 FY2029 線性收斂到 fade_g、淨利率收斂到 fade_m（FY2032 達到），非驅動因子推導
A76: 12 吋（VSMC）÷ 營收 | B76: % | D76: =D74/D75 -> 0 | E76: =E74/E75 -> 0.098203268 | F76: =F74/F75 -> 0.21244009 | G76: =G74/G75 -> 0.27427055
A77: AI 相關 ÷ 營收（記憶列，不進營收加總） | B77: % | D77: =ai_sh26 -> 0.1 | E77: =ai_sh27_A -> 0.25 | F77: =ai_sh27_A -> 0.25 | G77: =ai_sh27_A -> 0.25
A78: 營收年增 | B78: % | D78: =D75/C75-1 -> 0.20705604 | E78: =E75/D75-1 -> 0.29603961 | F78: =F75/E75-1 -> 0.15565839 | G78: =G75/F75-1 -> 0.084389555 | H78: =$G78+(fade_gA-$G78)*1/3 -> 0.076259703 | I78: =$G78+(fade_gA-$G78)*2/3 -> 0.068129852 | J78: =$G78+(fade_gA-$G78)*3/3 -> 0.06
A79: C. 成本與損益
A80: 銷貨成本內折舊 | B80: NT$B | D80: =da_tot26*da_sh -> 8.658 | E80: =D80*(1+dag_27+dag_adj) -> 8.91774 | F80: =E80*(1+dag_28+dag_adj) -> 9.0960948 | G80: =F80*(1+dag_29+dag_adj) -> 9.0960948
A81: 每片現金成本（FY2026 殘差，之後年增 cc_g） | B81: NT$K/片 | D81: =(D69-a26_gp-D80)/D65*1000 -> 10.733992 | E81: =D81*(1+cc_g) -> 10.948672 | F81: =E81*(1+cc_g) -> 11.167645 | G81: =F81*(1+cc_g) -> 11.390998 | K81: Derived：讓 FY2026 毛利等於錨點；含原物料、人力、電力等變動與固定現金成本
A82: 現金成本合計（每片 × 出貨） | B82: NT$B | D82: =D81*D65/1000 -> 30.962039 | E82: =E81*E65/1000 -> 34.386493 | F82: =F81*F65/1000 -> 34.705021 | G82: =G81*G65/1000 -> 35.022535
A83: VSMC 毛利率 | B83: % | E83: =vgm27_A -> 0.05 | F83: =vgm28_A -> 0.2 | G83: =vgm29_A -> 0.25
A84: VSMC 毛利 | B84: NT$B | D84: =0 -> 0 | E84: =E74*E83 -> 0.373248 | F84: =F74*F83 -> 3.73248 | G84: =G74*G83 -> 6.53184
A85: 毛利 | B85: NT$B | C85: =a25_gp -> 13.654 | D85: =D69-D80-D82+D84 -> 19.032021 | E85: =E69-E80-E82+E84 -> 25.619447 | F85: =F69-F80-F82+F84 -> 29.116791 | G85: =G69-G80-G82+G84 -> 31.547116
A86: 毛利率 | B86: % | C86: =C85/C75 -> 0.28099854 | D86: =D85/D75 -> 0.32449025 | E86: =E85/E75 -> 0.33702973 | F86: =F85/F75 -> 0.33144577 | G86: =G85/G75 -> 0.33116415
A87: 營業費用 | B87: NT$B | C87: =a25_opx -> 5.881 | D87: =a26_opx -> 6.824187 | E87: =D87*(1+MAX(g_opx_min,phi*E78)) -> 7.8343018 | F87: =E87*(1+MAX(g_opx_min,phi*F78)) -> 8.4440392 | G87: =F87*(1+MAX(g_opx_min,phi*G78)) -> 8.8003336
A88: 營業利益 | B88: NT$B | C88: =C85-C87 -> 7.773 | D88: =D85-D87 -> 12.207834 | E88: =E85-E87 -> 17.785146 | F88: =F85-F87 -> 20.672751 | G88: =G85-G87 -> 22.746782
A89: 營業利益率 | B89: % | C89: =C88/C75 -> 0.1599679 | D89: =D88/D75 -> 0.20813991 | E89: =E88/E75 -> 0.23396769 | F89: =F88/F75 -> 0.23532456 | G89: =G88/G75 -> 0.23878312
A90: 營業外淨額 | B90: NT$B | C90: =a25_nonop -> 1.479 | D90: =a26_nonop -> 2.1095083 | E90: =nonop_f -> 1.5 | F90: =nonop_f -> 1.5 | G90: =nonop_f -> 1.5
A91: 稅前利益 | B91: NT$B | C91: =C88+C90 -> 9.252 | D91: =D88+D90 -> 14.317343 | E91: =E88+E90 -> 19.285146 | F91: =F88+F90 -> 22.172751 | G91: =G88+G90 -> 24.246782
A92: 所得稅 | B92: NT$B | C92: =a25_tax -> 1.344 | D92: =a26_tax -> 2.0798215 | E92: =E91*tax -> 2.8927718 | F92: =F91*tax -> 3.3259127 | G92: =G91*tax -> 3.6370173
A93: 非控制權益（NXP 占 VSMC 40%） | B93: NT$B | C93: =a25_mi -> 0 | D93: =a26_mi -> 0 | E93: =vmi*E84*(1-tax) -> 0.12690432 | F93: =vmi*F84*(1-tax) -> 1.2690432 | G93: =vmi*G84*(1-tax) -> 2.2208256 | K93: VSMC 虧損時為負值（母公司淨利少扣）
A94: 歸屬母公司淨利 | B94: NT$B | C94: =C91-C92-C93 -> 7.908 | D94: =D91-D92-D93 -> 12.237521 | E94: =E91-E92-E93 -> 16.265469 | F94: =F91-F92-F93 -> 17.577795 | G94: =G91-G92-G93 -> 18.388939 | H94: =H75*H98 -> 19.791274 | I94: =I75*I98 -> 21.139651 | J94: =J75*J98 -> 22.40803
A95: 加權股數 | B95: 十億股 | C95: =a25_sh -> 1.8739336 | D95: =a26_sh -> 1.9061359 | E95: =q_sh*(1+sh_g) -> 1.9070513 | F95: =E95*(1+sh_g) -> 1.9070513 | G95: =F95*(1+sh_g) -> 1.9070513 | H95: =G95*(1+sh_g) -> 1.9070513 | I95: =H95*(1+sh_g) -> 1.9070513 | J95: =I95*(1+sh_g) -> 1.9070513
A96: EPS（基本） | B96: NT$ | C96: =C94/C95 -> 4.22 | D96: =D94/D95 -> 6.4200675 | E96: =E94/E95 -> 8.5291201 | F96: =F94/F95 -> 9.2172642 | G96: =G94/G95 -> 9.6426033 | H96: =H94/H95 -> 10.377945 | I96: =I94/I95 -> 11.084993 | J96: =J94/J95 -> 11.750093
A97: EPS 年增 | B97: % | D97: =D96/C96-1 -> 0.521343 | E97: =E96/D96-1 -> 0.32850942 | F97: =F96/E96-1 -> 0.080681718 | G97: =G96/F96-1 -> 0.046145922 | H97: =H96/G96-1 -> 0.076259703 | I97: =I96/H96-1 -> 0.068129852 | J97: =J96/I96-1 -> 0.06
A98: 淨利率（歸屬母公司淨利 ÷ 營收） | B98: % | C98: =C94/C75 -> 0.16274619 | D98: =D94/D75 -> 0.20864606 | E98: =E94/E75 -> 0.213976 | F98: =F94/F75 -> 0.20009369 | G98: =G94/G75 -> 0.1930369 | H98: =$G98+(fade_mA-$G98)*1/3 -> 0.1930369 | I98: =$G98+(fade_mA-$G98)*2/3 -> 0.1930369 | J98: =$G98+(fade_mA-$G98)*3/3 -> 0.1930369
A101: 情境 B（平平）：8 吋稼動率 90%／86%／87%；售價 +3%／0／0；VSMC 稼動率 80%、毛利率 −5%／12%／18%
A102: 項目 | B102: 單位 | C102: FY2025A | D102: FY2026（錨點） | E102: FY2027 | F102: FY2028 | G102: FY2029 | H102: FY2030（收斂） | I102: FY2031（收斂） | J102: FY2032（收斂） | K102: 說明
A103: A. 8 吋晶圓：產能 × 稼動率 × 平均售價（D 欄＝FY2026 校準年）
A104: 產能（8 吋） | B104: 千片 | D104: =cap_26 -> 3306 | E104: =D104*(1+capg27)*cap_adj -> 3306 | F104: =E104*(1+capg28) -> 3306 | G104: =F104*(1+capg29) -> 3306
A105: 平均稼動率 | B105: % | D105: =a26_ship/cap_26 -> 0.8725 | E105: =MIN(0.98,ut27_B+ut_adj) -> 0.9 | F105: =MIN(0.98,ut28_B+ut_adj) -> 0.86 | G105: =MIN(0.98,ut29_B+ut_adj) -> 0.87
A106: 晶圓出貨（8 吋） | B106: 千片 | D106: =D104*D105 -> 2884.485 | E106: =E104*E105 -> 2975.4 | F106: =F104*F105 -> 2843.16 | G106: =G104*G105 -> 2876.22
A107: 平均售價（8 吋晶圓） | B107: US$/片 | D107: =asp_26 -> 643.46941 | E107: =D107*(1+asp27_B)*(1+asp_adj) -> 662.77349 | F107: =E107*(1+asp28_B) -> 662.77349 | G107: =F107*(1+asp29_B) -> 662.77349
A108: 平均售價年增（美元） | B108: % | E108: =E107/D107-1 -> 0.03 | F108: =F107/E107-1 -> 0 | G108: =G107/F107-1 -> 0
A109: 匯率 | B109: NT$/US$ | D109: =fx_26 -> 31.6 | E109: =fx -> 32 | F109: =fx -> 32 | G109: =fx -> 32
A110: 8 吋晶圓營收 | B110: NT$B | D110: =D106*D107*D109/1000000 -> 58.65206 | E110: =E106*E107*E109/1000000 -> 63.10452 | F110: =F106*F107*F109/1000000 -> 60.299874 | G110: =G106*G107*G109/1000000 -> 61.001036
A111: B. VSMC（新加坡 12 吋廠；FY2027 第一季量產）
A112: VSMC 產能（12 吋） | B112: 千片 | D112: =0 -> 0 | E112: =vcap27*vcap_adj -> 144 | F112: =vcap28*vcap_adj -> 360 | G112: =vcap29*vcap_adj -> 504
...

Sheet Val
A1: Val — P/E 估值（新台幣）。結論用「現價 ÷ FY2027、FY2028 EPS（模型）」；目標價＝DCF 與 Comparable 加權（第 0 節）；十年 P/E 規則值（第 3 節，年底落後 P/E）只作參考
A2: 循環位置：世界先進不是設備股，不套設備市場見頂年；以本模型營收最高的會計年度為見頂年（比照創意、聯發科；FY(t)＝CY(t)）。營收到 FY2029 仍在增加時，見頂年未知，判為中段
A4: 0. 目標價
A5: 0.1 DCF（股東權益現金流，FY2027–FY2032 明確期＋FY2032 後永續）
A6: 項目 | B6: A（順利） | C6: B（平平） | D6: C（不如預期） | E6: 說明
A7: 情境 EPS（FY2027–FY2032） | E7: PL 頁各情境；FY2030 起為收斂法
A8: FY2027 | B8: =PL!E16 -> 8.5291201 | C8: =PL!E31 -> 6.8826326 | D8: =PL!E46 -> 3.9110071
A9: FY2028 | B9: =PL!F16 -> 9.2172642 | C9: =PL!F31 -> 6.3713635 | D9: =PL!F46 -> 1.9002739
A10: FY2029 | B10: =PL!G16 -> 9.6426033 | C10: =PL!G31 -> 6.6516111 | D10: =PL!G46 -> 1.7334087
A11: FY2030 | B11: =PL!H16 -> 10.377945 | C11: =PL!H31 -> 6.9246473 | D11: =PL!H46 -> 1.7532743
A12: FY2031 | B12: =PL!I16 -> 11.084993 | C12: =PL!I31 -> 7.0768102 | D12: =PL!I46 -> 1.7124605
A13: FY2032 | B13: =PL!J16 -> 11.750093 | C13: =PL!J31 -> 7.0970297 | D13: =PL!J46 -> 1.6123474
A14: 股東現金流＝EPS ×（1 − tp_g ÷ tp_roe）
A15: 再投資率（tp_g ÷ tp_roe，上限 0.8） | B15: =MIN(tp_g/tp_roe,0.8) -> 0.30991736 | E15: ROE 為近三年平均（In 頁 tp_roe）
A16: FY2027 | B16: =B8*(1-$B$15) -> 5.8857978 | C16: =C8*(1-$B$15) -> 4.7495853 | D16: =D8*(1-$B$15) -> 2.6989182
A17: FY2028 | B17: =B9*(1-$B$15) -> 6.3606741 | C17: =C9*(1-$B$15) -> 4.3967674 | D17: =D9*(1-$B$15) -> 1.311346
A18: FY2029 | B18: =B10*(1-$B$15) -> 6.6541932 | C18: =C10*(1-$B$15) -> 4.5901613 | D18: =D10*(1-$B$15) -> 1.1961953
A19: FY2030 | B19: =B11*(1-$B$15) -> 7.16164 | C19: =C11*(1-$B$15) -> 4.7785789 | D19: =D11*(1-$B$15) -> 1.2099042
A20: FY2031 | B20: =B12*(1-$B$15) -> 7.6495615 | C20: =C12*(1-$B$15) -> 4.8835839 | D20: =D12*(1-$B$15) -> 1.1817393
A21: FY2032 | B21: =B13*(1-$B$15) -> 8.1085352 | C21: =C13*(1-$B$15) -> 4.897537 | D21: =D13*(1-$B$15) -> 1.112653
A22: DCF 情境每股價值（折現率 tp_r） | B22: =MAX(0,SUMPRODUCT(B16:B21,1/(1+tp_r)^{1;2;3;4;5;6})+B21*(1+tp_g)/(tp_r-tp_g)/(1+tp_r)^6) -> 109.16085 | C22: =MAX(0,SUMPRODUCT(C16:C21,1/(1+tp_r)^{1;2;3;4;5;6})+C21*(1+tp_g)/(tp_r-tp_g)/(1+tp_r)^6) -> 68.379394 | D22: =MAX(0,SUMPRODUCT(D16:D21,1/(1+tp_r)^{1;2;3;4;5;6})+D21*(1+tp_g)/(tp_r-tp_g)/(1+tp_r)^6) -> 17.510685 | E22: Σ 明確期現金流 ÷ (1＋r)^t ＋ 永續價值 ÷ (1＋r)^6；永續價值＝FY2032 現金流 ×(1＋g)÷(r−g)；基準日 2026 年底；負值取 0
A23: DCF 情境價值推到 12 個月後（×(1＋tp_r)） | B23: =B22*(1+tp_r) -> 120.07694 | C23: =C22*(1+tp_r) -> 75.217334 | D23: =D22*(1+tp_r) -> 19.261754
A24: DCF 目標價（情境加權） | B24: =tp_wA*B23+tp_wB*C23+tp_wC*D23 -> 77.484099 | E24: Σ 權重 × 情境價值 ×(1＋r)；權重見 In 頁
A26: 0.2 Comparable（市場主流同業前瞻 P/E）
A27: 同業與前瞻 P/E | B27: 代號 | C27: 前瞻 12 月 P/E | D27: 日期 | E27: 來源 | F27: 標記
A28: 聯電（UMC） | B28: 2303.TW | C28: 20.22 | D28: 2026-10-22 | E28: stockanalysis.com forward PE（分析師共識；價格日期如左） | F28: Interested-party
A29: 格芯（GlobalFoundries） | B29: GFS | C29: 20.04 | D29: 2026-10-22 | E29: stockanalysis.com forward PE（抄自台積電模型 Val 頁同業表） | F29: Interested-party
A30: 中芯國際（SMIC，港股） | B30: 0981.HK | C30: 37.14 | D30: 2026-10-16 | E30: stockanalysis.com forward PE（抄自台積電模型 Val 頁同業表） | F30: Interested-party
A31: 高塔半導體（Tower） | B31: TSEM | C31: 34.63 | D31: 2026-10-26 | E31: stockanalysis.com forward PE（分析師共識；價格日期如左） | F31: Interested-party
A33: 同業前瞻 P/E 中位數 | B33: =MEDIAN(C28:C31) -> 27.425 | E33: 成熟與特殊製程晶圓代工同業（聯電、格芯、中芯港股、高塔）；不含 A 股（非 A 股公司，Andy 2026-10-25 11:53）；力積電、華虹前瞻 P/E 未取得或資料日過舊，未列
A34: 12 個月後的前瞻 EPS（情境加權） | B34: =tp_wA*(2/12*B8+10/12*B9)+tp_wB*(2/12*C8+10/12*C9)+tp_wC*(2/12*D8+10/12*D9) -> 6.4061388 | E34: 約 2027-10 時的未來 12 月 EPS ≈ 2／12 × FY2027＋10／12 × FY2028（會計年度＝日曆年）
A35: Comparable 目標價 | B35: =B33*B34 -> 175.68836 | E35: 同業中位數 × 前瞻 EPS
A37: 0.3 結論
A38: 項目 | B38: 數值 | E38: 說明
A39: 目標價（DCF 與 Comparable 加權） | B39: =tp_w_dcf*B24+(1-tp_w_dcf)*tp_comp_adj -> 126.58623 | E39: tp_w_dcf × DCF＋（1 − tp_w_dcf）× Comparable（相對倍數調整後，見第 0.5 節）
A40: Comparable 目標價（市場主流同業法） | B40: =B35 -> 175.68836
A41: 市場共識目標價 | B41: =cons_tp -> 183.18 | E41: stockanalysis：17 位分析師平均 183.18（2026-09-21 擷取；中位數 187、區間 89–220）
A42: 上檔空間：加權目標價 | B42: =B39/px-1 -> -0.21375014 | E42: 現價＝In 頁 px（2026-10-22 收盤）
A43: 上檔空間：Comparable 目標價 | B43: =B40/px-1 -> 0.091232024
A44: 與市場共識目標價的差距：EPS 因素 | B44: =B34/cons_feps-1 -> -0.047824072 | E44: 本模型前瞻 EPS ÷ 共識前瞻 EPS − 1；共識前瞻 EPS 見 In 頁 cons_feps
A45: 與市場共識目標價的差距：倍數因素 | B45: =(cons_tp/cons_feps)/B33-1 -> -0.0072217042 | E45: ="共識目標價隱含 "&TEXT(cons_tp/cons_feps,"0.0")&"x，同業中位數 "&TEXT(B33,"0.0")&"x" -> 共識目標價隱含 27.2x，同業中位數 27.4x
A46: 價格帶（DCF 不如預期～順利） | B46: =TEXT(D23,"#,##0")&"～"&TEXT(B23,"#,##0") -> 19～120 | E46: C 情境價值～A 情境價值（推到 12 個月後）
A47: 歷史倍數檢查：現價隱含 P/E 的十年分位（A／B／C） | B47: =IF(px/B9>=MAX($B$86:$B$95),1,IF(px/B9<=MIN($B$86:$B$95),0,PERCENTRANK($B$86:$B$95,px/B9))) -> 0.515 | C47: =IF(px/C9>=MAX($B$86:$B$95),1,IF(px/C9<=MIN($B$86:$B$95),0,PERCENTRANK($B$86:$B$95,px/C9))) -> 1 | D47: =IF(px/D9>=MAX($B$86:$B$95),1,IF(px/D9<=MIN($B$86:$B$95),0,PERCENTRANK($B$86:$B$95,px/D9))) -> 1 | E47: 現價 ÷ 各情境 FY2028 EPS 在 2016–2025 年底 P/E（第 5 節兩來源平均）的分位；高於十年最大值記為 100%、低於最小值記為 0%；只作檢查，不進目標價
A48: 目標價方法 | B48: DCF：股東現金流＝EPS ×（1 − g／ROE），r＝10%、g＝4%、ROE 為近三年平均約 12.9%（再投資率約 31%），FY2027–32 明確期＋永續；VSMC 建廠期（2025–2027）資本支出每年 600–700 億元，遠高於淨利，本模型沒有資本支出推導，未改用淨利＋折舊－資本支出，DCF 偏高估；情境價值負值取 0。Comparable：聯電、格芯、中芯（港股）、高塔前瞻 P/E 中位數；世界先進本身 Bloomberg 前瞻倍數待取，相對倍數調整係數取 1.0（不調整）。主要偏誤：8 吋稼動率、售價與 VSMC 毛利率屬公司層級假設（待併入 Siliconomics）；FY2030 起只用收斂法。情境對應：A＝順利（8 吋稼動率 95%、VSMC 稼動率 90%）、B＝平平、C＝不如預期（中國成熟製程擴產、8 吋稼動率 74–80%、VSMC 毛利率為負）
A51: 1. 價格與市場隱含倍數
A52: 項目 | B52: A | C52: B | D52: C | E52: 說明
A53: 現價（2026-10-22 收盤） | B53: =px -> 161
A54: 現價 ÷ FY2026 EPS（錨點） | B54: =px/PL!D16 -> 25.077618 | C54: =px/PL!D31 -> 25.077618 | D54: =px/PL!D46 -> 25.077618 | E54: FY2026 三情境相同（錨點）
A55: 現價 ÷ FY2027 EPS（模型） | B55: =px/PL!E16 -> 18.876507 | C55: =px/PL!E31 -> 23.392212 | D55: =px/PL!E46 -> 41.165867 | E55: FY2027 三情境差在稼動率、售價與新業務；顆數情境係數從 CY2028 開始
A56: 現價 ÷ FY2028 EPS（模型） | B56: =px/PL!F16 -> 17.467222 | C56: =px/PL!F31 -> 25.269316 | D56: =px/PL!F46 -> 84.724629
A57: 現價 ÷ FY2029 EPS（模型） | B57: =px/PL!G16 -> 16.696736 | C57: =px/PL!G31 -> 24.204662 | D57: =px/PL!G46 -> 92.880577
A58: 未來 12 月 EPS（模型 B）≈ 0.2 × FY2026＋0.8 × FY2027 | B58: =0.2*PL!D31+0.8*PL!E31 -> 6.7901196
A59: 現價 ÷ 未來 12 月 EPS（模型 B） | B59: =px/B58 -> 23.710923
A60: 近 12 月 P/E（現價 ÷ 近 12 月 EPS） | B60: =pe_ttm -> 35.229759
A61: 前瞻 P/E（stockanalysis，2026-09-11；股價 157.5） | B61: =fpe -> 23.41
A63: 2. 循環位置（本模型營收最高年；FY(t)＝CY(t)）
A64: 情境 | B64: 營收最高年（FY2026–FY2029） | C64: FY2027 判定 | D64: 規則倍數（P/E） | E64: 見頂年是否未知 | F64: 說明
A65: A | B65: =INDEX({2026,2027,2028,2029},MATCH(MAX(PL!D75:G75),PL!D75:G75,0)) -> 2029 | C65: =IF(B65=2029,"中段",IF(2027<B65,"中段",IF(2027=B65,"見頂","谷底"))) -> 中段 | D65: =IF(C65="見頂",pe_peak,IF(C65="谷底",pe_trough,pe_mid)) -> 19.5 | E65: =IF(B65=2029,"是：營收到觀測期末仍在增加","否") -> 是：營收到觀測期末仍在增加 | F65: tools/cycle_position.py excel_rule；營收最高年取代設備市場見頂年
A66: B | B66: =INDEX({2026,2027,2028,2029},MATCH(MAX(PL!D116:G116),PL!D116:G116,0)) -> 2029 | C66: =IF(B66=2029,"中段",IF(2027<B66,"中段",IF(2027=B66,"見頂","谷底"))) -> 中段 | D66: =IF(C66="見頂",pe_peak,IF(C66="谷底",pe_trough,pe_mid)) -> 19.5 | E66: =IF(B66=2029,"是：營收到觀測期末仍在增加","否") -> 是：營收到觀測期末仍在增加 | F66: 同上
A67: C | B67: =INDEX({2026,2027,2028,2029},MATCH(MAX(PL!D157:G157),PL!D157:G157,0)) -> 2029 | C67: =IF(B67=2029,"中段",IF(2027<B67,"中段",IF(2027=B67,"見頂","谷底"))) -> 中段 | D67: =IF(C67="見頂",pe_peak,IF(C67="谷底",pe_trough,pe_mid)) -> 19.5 | E67: =IF(B67=2029,"是：營收到觀測期末仍在增加","否") -> 是：營收到觀測期末仍在增加 | F67: 同上
A69: 3. 規則值隱含股價（新台幣；約 FY2027 年底，未折現）＝ FY2027 EPS × 規則倍數
A70: 情境 | B70: FY2027 EPS | C70: （同左） | D70: 規則倍數 | E70: 隱含股價 | F70: 相對現價 | G70: 現價 ÷ FY2027 EPS
A71: A | B71: =PL!E16 -> 8.5291201 | C71: =B71 -> 8.5291201 | D71: =D65 -> 19.5 | E71: =C71*D71 -> 166.31784 | F71: =E71/px-1 -> 0.033030077 | G71: =px/C71 -> 18.876507
A72: B | B72: =PL!E31 -> 6.8826326 | C72: =B72 -> 6.8826326 | D72: =D66 -> 19.5 | E72: =C72*D72 -> 134.21134 | F72: =E72/px-1 -> -0.16638922 | G72: =px/C72 -> 23.392212
A73: C | B73: =PL!E46 -> 3.9110071 | C73: =B73 -> 3.9110071 | D73: =D67 -> 19.5 | E73: =C73*D73 -> 76.264639 | F73: =E73/px-1 -> -0.52630659 | G73: =px/C73 -> 41.165867
A75: 4. What must be true：FY2027 年底價 ＝ 現價 ×（1＋報酬）所需的倍數（FY2028 EPS；約 2027 年底的價格看下一年 EPS）
A76: FY2027 年底價 ÷ 現價 | B76: 所需倍數（÷ FY2028 EPS，A） | C76: 所需倍數（÷ FY2028 EPS，B） | D76: 所需倍數（÷ FY2028 EPS，C） | E76: 對照：十年中位數
A77: 1 | B77: =px*A77/PL!F16 -> 17.467222 | C77: =px*A77/PL!F31 -> 25.269316 | D77: =px*A77/PL!F46 -> 84.724629 | E77: =pe_mid -> 19.5
A78: 1.1 | B78: =px*A78/PL!F16 -> 19.213944 | C78: =px*A78/PL!F31 -> 27.796248 | D78: =px*A78/PL!F46 -> 93.197092 | E78: =pe_mid -> 19.5
A79: 1.21 | B79: =px*A79/PL!F16 -> 21.135339 | C79: =px*A79/PL!F31 -> 30.575873 | D79: =px*A79/PL!F46 -> 102.5168 | E79: =pe_mid -> 19.5
A80: 1.5 | B80: =px*A80/PL!F16 -> 26.200833 | C80: =px*A80/PL!F31 -> 37.903975 | D80: =px*A80/PL!F46 -> 127.08694 | E80: =pe_mid -> 19.5
A81: 2 | B81: =px*A81/PL!F16 -> 34.934444 | C81: =px*A81/PL!F31 -> 50.538633 | D81: =px*A81/PL!F46 -> 169.44926 | E81: =pe_mid -> 19.5
A82: 讀法：1.00＝價格不變、1.21＝一年約 21%。所需倍數低於歷史中位數時，現價相對便宜；倍數是否合理，另看前瞻 P/E 歷史（Bloomberg）。本版未做先驗，無 Andy 合理 P/E 對照。
A84: 5. 十年 P/E（2016–2025 年底；兩來源平均，分位排名用；無負值或 >200 需剔除）
A85: 年底 | B85: 兩來源平均 P/E | C85: companiesmarketcap | D85: stockanalysis
A86: 2016 | B86: =IF(COUNT(C86:D86)=0,"",AVERAGE(C86:D86)) -> 11.2 | C86: =IF(B105="","",B105) -> 11.2 | D86: =IF(C105="","",C105)
A87: 2017 | B87: =IF(COUNT(C87:D87)=0,"",AVERAGE(C87:D87)) -> 17 | C87: =IF(B106="","",B106) -> 17 | D87: =IF(C106="","",C106)
A88: 2018 | B88: =IF(COUNT(C88:D88)=0,"",AVERAGE(C88:D88)) -> 12.5 | C88: =IF(B107="","",B107) -> 12.5 | D88: =IF(C107="","",C107)
A89: 2019 | B89: =IF(COUNT(C89:D89)=0,"",AVERAGE(C89:D89)) -> 17.5 | C89: =IF(B108="","",B108) -> 17.5 | D89: =IF(C108="","",C108)
A90: 2020 | B90: =IF(COUNT(C90:D90)=0,"",AVERAGE(C90:D90)) -> 24 | C90: =IF(B109="","",B109) -> 24 | D90: =IF(C109="","",C109)
A91: 2021 | B91: =IF(COUNT(C91:D91)=0,"",AVERAGE(C91:D91)) -> 20.105 | C91: =IF(B110="","",B110) -> 18.3 | D91: =IF(C110="","",C110) -> 21.91
A92: 2022 | B92: =IF(COUNT(C92:D92)=0,"",AVERAGE(C92:D92)) -> 7.85 | C92: =IF(B111="","",B111) -> 7.39 | D92: =IF(C111="","",C111) -> 8.31
A93: 2023 | B93: =IF(COUNT(C93:D93)=0,"",AVERAGE(C93:D93)) -> 17.41 | C93: =IF(B112="","",B112) -> 16.7 | D93: =IF(C112="","",C112) -> 18.12
A94: 2024 | B94: =IF(COUNT(C94:D94)=0,"",AVERAGE(C94:D94)) -> 24.58 | C94: =IF(B113="","",B113) -> 22.7 | D94: =IF(C113="","",C113) -> 26.46
A95: 2025 | B95: =IF(COUNT(C95:D95)=0,"",AVERAGE(C95:D95)) -> 21.875 | C95: =IF(B114="","",B114) -> 22 | D95: =IF(C114="","",C114) -> 21.75
A96: 年數 | B96: =COUNT($B$86:$B$95) -> 10
A100: 6. 十年倍數與規則值（2016–2025 年底；見頂年 25 分位、中段中位數、谷底 75 分位）
A101: 規則（Andy 2026-10-13）：合理倍數＝2016–2025 年底 P/E 依循環位置取分位，兩個來源分別取分位再平均。stockanalysis 年度 P/E 只有 FY2021–25。十年中位數約 17–18 倍；2022 年 EPS 高峰時 P/E 只有 7–8 倍。
A103: P/E：十年歷史倍數
A104: 年底 | B104: companiesmarketcap（年底 P/E） | C104: stockanalysis（年度 P/E） | D104: 標記／說明
A105: 2016 | B105: 11.2 | D105: companiesmarketcap（年底 P/E）：Interested-party（資料商；2016–2025 共 10 年）；stockanalysis（年度 P/E）：Interested-party（資料商；只有 FY2021–25，2016–2020 未找到）
A106: 2017 | B106: 17
A107: 2018 | B107: 12.5
A108: 2019 | B108: 17.5
A109: 2020 | B109: 24
A110: 2021 | B110: 18.3 | C110: 21.91
A111: 2022 | B111: 7.39 | C111: 8.31
A112: 2023 | B112: 16.7 | C112: 18.12
A113: 2024 | B113: 22.7 | C113: 26.46
A114: 2025 | B114: 22 | C114: 21.75
...

Sheet Recon
A1: Recon — 本模型 vs 公司說法、共識、券商。只作事後對照，不為對上數字而調參數。券商與資料商數字為 Interested-party，不用於校準
A3: 項目 | B3: 對照值 | C3: 模型 A | D3: 差距 A | E3: 模型 B | F3: 差距 B | G3: 模型 C | H3: 差距 C | I3: 對照來源 | J3: 說明
A4: A. FY2026 錨點 vs 共識
A5: FY2026 營收 vs 共識 | B5: =cons_rev26 -> 58.5 | C5: =PL!D75 -> 58.65206 | D5: =C5/B5-1 -> 0.0025993162 | E5: =PL!D116 -> 58.65206 | F5: =E5/B5-1 -> 0.0025993162 | G5: =PL!D157 -> 58.65206 | H5: =G5/B5-1 -> 0.0025993162 | I5: stockanalysis（15 位；2026-09-21） | J5: 共識資料日早於 3Q26 營收公布
A6: FY2026 EPS vs 共識 | B6: =cons_eps26 -> 6.05 | C6: =PL!D96 -> 6.4200675 | D6: =C6/B6-1 -> 0.061168177 | E6: =PL!D137 -> 6.4200675 | F6: =E6/B6-1 -> 0.061168177 | G6: =PL!D178 -> 6.4200675 | H6: =G6/B6-1 -> 0.061168177 | I6: stockanalysis（2026-09-21） | J6: 共識區間 5.46–6.50
A7: 3Q26 毛利率 vs 公司指引中點（百分點） | B7: =co_q3_gm -> 0.335 | C7: =Q!E10 -> 0.335 | D7: =C7-B7 -> 0 | E7: =Q!E10 -> 0.335 | F7: =E7-B7 -> 0 | G7: =Q!E10 -> 0.335 | H7: =G7-B7 -> 0 | I7: 優分析 2026-08-04（法說） | J7: 三欄同值（FY2026 錨點）；3Q26 財報 2026-11-05
A8: B. FY2027 vs 研究機構（校準未使用）
A9: FY2027 EPS vs 研究機構約 8 元 | B9: =an_eps27 -> 8 | C9: =PL!E96 -> 8.5291201 | D9: =C9/B9-1 -> 0.066140016 | E9: =PL!E137 -> 6.8826326 | F9: =E9/B9-1 -> -0.13967092 | G9: =PL!E178 -> 3.9110071 | H9: =G9/B9-1 -> -0.51112411 | I9: 工商時報 2026-08-06 | J9: FY2027 共識：未找到
A10: FY2027 毛利率 vs 研究機構 35%（百分點） | B10: =an_gm27 -> 0.35 | C10: =PL!E86 -> 0.33702973 | D10: =C10-B10 -> -0.012970268 | E10: =PL!E127 -> 0.30510917 | F10: =E10-B10 -> -0.044890829 | G10: =PL!E168 -> 0.23828721 | H10: =G10-B10 -> -0.11171279 | I10: 工商時報 2026-08-06
A11: FY2027 12 吋（VSMC）占營收 vs 研究機構 12%（百分點） | B11: =an_12sh27 -> 0.12 | C11: =PL!E76 -> 0.098203268 | D11: =C11-B11 -> -0.021796732 | E11: =PL!E117 -> 0.09514649 | F11: =E11-B11 -> -0.02485351 | G11: =PL!E158 -> 0.092608449 | H11: =G11-B11 -> -0.027391551 | I11: 工商時報 2026-08-06
A12: 共識前瞻 12 月 EPS vs 模型（情境加權 2／12 × FY2027＋10／12 × FY2028） | B12: =cons_feps -> 6.7278941 | C12: =Val!B34 -> 6.4061388 | D12: =C12/B12-1 -> -0.047824072 | E12: =Val!B34 -> 6.4061388 | F12: =E12/B12-1 -> -0.047824072 | G12: =Val!B34 -> 6.4061388 | H12: =G12/B12-1 -> -0.047824072 | I12: stockanalysis 前瞻 P/E 推得 | J12: 三欄同值（情境加權）
A13: 預留
A14: 成熟製程稼動率與價格的行業層（Siliconomics）尚未建立：上線後以本模型稼動率、售價情境對照行業路徑 | J14: 預留列：本版無數值

Sheet Sens
A1: Sens — 一次動一個輸入（In 頁敏感度低／高值），三情境都在本頁下方逐案重算（FY2026 恆等於錨點，每片現金成本在每個案例內重算），表內為情境加權後的 DCF、Comparable（相對倍數調整後）與加權目標價；另列 FY2027、FY2028 情境 A 的 EPS
A2: 相對基準＝案例加權目標價 ÷ 基準加權目標價 − 1。目標價參數（tp_r、tp_g、tp_w_dcf）三案只改 DCF 參數，PL 收斂法的 fade_g 不隨 tp_g 變動
A3: 案例 | B3: 設定 | C3: 鍵 | D3: FY2027 EPS（A） | E3: FY2028 EPS（A） | F3: FY2028 EPS 相對基準（A） | G3: DCF 目標價 | H3: Comparable（調整後）目標價 | I3: 加權目標價 | J3: 相對基準
A4: 基準（三情境加權） | B4: PL 頁三個推導區塊 | C4: — | D4: =PL!E96 -> 8.5291201 | E4: =PL!F96 -> 9.2172642 | F4: =E4/E$4-1 -> 0 | G4: =(tp_wA*MAX(0,PL!E96*(1-MIN(tp_g/tp_roe,0.8))/(1+tp_r)^1+PL!F96*(1-MIN(tp_g/tp_roe,0.8))/(1+tp_r)^2+PL!G96*(1-MIN(tp_g/tp_roe,0.8))/(1+tp_r)^3+PL!H96*(1-MIN(tp_g/tp_roe,0.8))/(1+tp_r)^4+PL!I96*(1-MIN(tp_g/tp_roe,0.8))/(1+tp_r)^5+PL!J96*(1-MIN(tp_g/tp_roe,0.8))/(1+tp_r)^6+PL!J96*(1-MIN(tp_g/tp_roe,0.8))*(1+tp_g)/(tp_r-tp_g)/(1+tp_r)^6)+tp_wB*MAX(0,PL!E137*(1-MIN(tp_g/tp_roe,0.8))/(1+tp_r)^1+PL!F137*(1-MIN(tp_g/tp_roe,0.8))/(1+tp_r)^2+PL!G137*(1-MIN(tp_g/tp_roe,0.8))/(1+tp_r)^3+PL!H137*(1-MIN(tp_g/tp_roe,0.8))/(1+tp_r)^4+PL!I137*(1-MIN(tp_g/tp_roe,0.8))/(1+tp_r)^5+PL!J137*(1-MIN(tp_g/tp_roe,0.8))/(1+tp_r)^6+PL!J137*(1-MIN(tp_g/tp_roe,0.8))*(1+tp_g)/(tp_r-tp_g)/(1+tp_r)^6)+tp_wC*MAX(0,PL!E178*(1-MIN(tp_g/tp_roe,0.8))/(1+tp_r)^1+PL!F178*(1-MIN(tp_g/tp_roe,0.8))/(1+tp_r)^2+PL!G178*(1-MIN(tp_g/tp_roe,0.8))/(1+tp_r)^3+PL!H178*(1-MIN(tp_g/tp_roe,0.8))/(1+tp_r)^4+PL!I178*(1-MIN(tp_g/tp_roe,0.8))/(1+tp_r)^5+PL!J178*(1-MIN(tp_g/tp_roe,0.8))/(1+tp_r)^6+PL!J178*(1-MIN(tp_g/tp_roe,0.8))*(1+tp_g)/(tp_r-tp_g)/(1+tp_r)^6))*(1+tp_r) -> 77.484099 | H4: =Val!$B$33*(tp_wA*(2/12*PL!E96+10/12*PL!F96)+tp_wB*(2/12*PL!E137+10/12*PL!F137)+tp_wC*(2/12*PL!E178+10/12*PL!F178))*rm_factor -> 175.68836 | I4: =tp_w_dcf*G4+(1-tp_w_dcf)*H4 -> 126.58623 | J4: =I4/I$4-1 -> 0
A5: 匯率：低 | B5: =TEXT(fx_lo,"0.0")&"（基準 "&TEXT(fx,"0.0")&"）" -> 30.5（基準 32.0） | C5: fx | D5: =E74 -> 7.1846194 | E5: =F74 -> 7.8245771 | F5: =E5/E$4-1 -> -0.1510955 | G5: =(tp_wA*MAX(0,E74*(1-MIN(tp_g/tp_roe,0.8))/(1+tp_r)^1+F74*(1-MIN(tp_g/tp_roe,0.8))/(1+tp_r)^2+G74*(1-MIN(tp_g/tp_roe,0.8))/(1+tp_r)^3+H74*(1-MIN(tp_g/tp_roe,0.8))/(1+tp_r)^4+I74*(1-MIN(tp_g/tp_roe,0.8))/(1+tp_r)^5+J74*(1-MIN(tp_g/tp_roe,0.8))/(1+tp_r)^6+J74*(1-MIN(tp_g/tp_roe,0.8))*(1+tp_g)/(tp_r-tp_g)/(1+tp_r)^6)+tp_wB*MAX(0,E115*(1-MIN(tp_g/tp_roe,0.8))/(1+tp_r)^1+F115*(1-MIN(tp_g/tp_roe,0.8))/(1+tp_r)^2+G115*(1-MIN(tp_g/tp_roe,0.8))/(1+tp_r)^3+H115*(1-MIN(tp_g/tp_roe,0.8))/(1+tp_r)^4+I115*(1-MIN(tp_g/tp_roe,0.8))/(1+tp_r)^5+J115*(1-MIN(tp_g/tp_roe,0.8))/(1+tp_r)^6+J115*(1-MIN(tp_g/tp_roe,0.8))*(1+tp_g)/(tp_r-tp_g)/(1+tp_r)^6)+tp_wC*MAX(0,E156*(1-MIN(tp_g/tp_roe,0.8))/(1+tp_r)^1+F156*(1-MIN(tp_g/tp_roe,0.8))/(1+tp_r)^2+G156*(1-MIN(tp_g/tp_roe,0.8))/(1+tp_r)^3+H156*(1-MIN(tp_g/tp_roe,0.8))/(1+tp_r)^4+I156*(1-MIN(tp_g/tp_roe,0.8))/(1+tp_r)^5+J156*(1-MIN(tp_g/tp_roe,0.8))/(1+tp_r)^6+J156*(1-MIN(tp_g/tp_roe,0.8))*(1+tp_g)/(tp_r-tp_g)/(1+tp_r)^6))*(1+tp_r) -> 63.113274 | H5: =Val!$B$33*(tp_wA*(2/12*E74+10/12*F74)+tp_wB*(2/12*E115+10/12*F115)+tp_wC*(2/12*E156+10/12*F156))*rm_factor -> 142.39339 | I5: =tp_w_dcf*G5+(1-tp_w_dcf)*H5 -> 102.75333 | J5: =I5/I$4-1 -> -0.188274
A6: 匯率：高 | B6: =TEXT(fx_hi,"0.0")&"（基準 "&TEXT(fx,"0.0")&"）" -> 33.0（基準 32.0） | C6: fx | D6: =E197 -> 9.425454 | E6: =F197 -> 10.145722 | F6: =E6/E$4-1 -> 0.10073033 | G6: =(tp_wA*MAX(0,E197*(1-MIN(tp_g/tp_roe,0.8))/(1+tp_r)^1+F197*(1-MIN(tp_g/tp_roe,0.8))/(1+tp_r)^2+G197*(1-MIN(tp_g/tp_roe,0.8))/(1+tp_r)^3+H197*(1-MIN(tp_g/tp_roe,0.8))/(1+tp_r)^4+I197*(1-MIN(tp_g/tp_roe,0.8))/(1+tp_r)^5+J197*(1-MIN(tp_g/tp_roe,0.8))/(1+tp_r)^6+J197*(1-MIN(tp_g/tp_roe,0.8))*(1+tp_g)/(tp_r-tp_g)/(1+tp_r)^6)+tp_wB*MAX(0,E238*(1-MIN(tp_g/tp_roe,0.8))/(1+tp_r)^1+F238*(1-MIN(tp_g/tp_roe,0.8))/(1+tp_r)^2+G238*(1-MIN(tp_g/tp_roe,0.8))/(1+tp_r)^3+H238*(1-MIN(tp_g/tp_roe,0.8))/(1+tp_r)^4+I238*(1-MIN(tp_g/tp_roe,0.8))/(1+tp_r)^5+J238*(1-MIN(tp_g/tp_roe,0.8))/(1+tp_r)^6+J238*(1-MIN(tp_g/tp_roe,0.8))*(1+tp_g)/(tp_r-tp_g)/(1+tp_r)^6)+tp_wC*MAX(0,E279*(1-MIN(tp_g/tp_roe,0.8))/(1+tp_r)^1+F279*(1-MIN(tp_g/tp_roe,0.8))/(1+tp_r)^2+G279*(1-MIN(tp_g/tp_roe,0.8))/(1+tp_r)^3+H279*(1-MIN(tp_g/tp_roe,0.8))/(1+tp_r)^4+I279*(1-MIN(tp_g/tp_roe,0.8))/(1+tp_r)^5+J279*(1-MIN(tp_g/tp_roe,0.8))/(1+tp_r)^6+J279*(1-MIN(tp_g/tp_roe,0.8))*(1+tp_g)/(tp_r-tp_g)/(1+tp_r)^6))*(1+tp_r) -> 87.064649 | H6: =Val!$B$33*(tp_wA*(2/12*E197+10/12*F197)+tp_wB*(2/12*E238+10/12*F238)+tp_wC*(2/12*E279+10/12*F279))*rm_factor -> 197.885 | I6: =tp_w_dcf*G6+(1-tp_w_dcf)*H6 -> 142.47482 | J6: =I6/I$4-1 -> 0.125516
A7: 8 吋產能係數：低 | B7: =TEXT(cap_adj_lo,"0.00")&"（基準 "&TEXT(cap_adj,"0.00")&"）" -> 0.95（基準 1.00） | C7: cap_adj | D7: =E320 -> 7.8566263 | E7: =F320 -> 8.5328729 | F7: =E7/E$4-1 -> -0.074251026 | G7: =(tp_wA*MAX(0,E320*(1-MIN(tp_g/tp_roe,0.8))/(1+tp_r)^1+F320*(1-MIN(tp_g/tp_roe,0.8))/(1+tp_r)^2+G320*(1-MIN(tp_g/tp_roe,0.8))/(1+tp_r)^3+H320*(1-MIN(tp_g/tp_roe,0.8))/(1+tp_r)^4+I320*(1-MIN(tp_g/tp_roe,0.8))/(1+tp_r)^5+J320*(1-MIN(tp_g/tp_roe,0.8))/(1+tp_r)^6+J320*(1-MIN(tp_g/tp_roe,0.8))*(1+tp_g)/(tp_r-tp_g)/(1+tp_r)^6)+tp_wB*MAX(0,E361*(1-MIN(tp_g/tp_roe,0.8))/(1+tp_r)^1+F361*(1-MIN(tp_g/tp_roe,0.8))/(1+tp_r)^2+G361*(1-MIN(tp_g/tp_roe,0.8))/(1+tp_r)^3+H361*(1-MIN(tp_g/tp_roe,0.8))/(1+tp_r)^4+I361*(1-MIN(tp_g/tp_roe,0.8))/(1+tp_r)^5+J361*(1-MIN(tp_g/tp_roe,0.8))/(1+tp_r)^6+J361*(1-MIN(tp_g/tp_roe,0.8))*(1+tp_g)/(tp_r-tp_g)/(1+tp_r)^6)+tp_wC*MAX(0,E402*(1-MIN(tp_g/tp_roe,0.8))/(1+tp_r)^1+F402*(1-MIN(tp_g/tp_roe,0.8))/(1+tp_r)^2+G402*(1-MIN(tp_g/tp_roe,0.8))/(1+tp_r)^3+H402*(1-MIN(tp_g/tp_roe,0.8))/(1+tp_r)^4+I402*(1-MIN(tp_g/tp_roe,0.8))/(1+tp_r)^5+J402*(1-MIN(tp_g/tp_roe,0.8))/(1+tp_r)^6+J402*(1-MIN(tp_g/tp_roe,0.8))*(1+tp_g)/(tp_r-tp_g)/(1+tp_r)^6))*(1+tp_r) -> 71.078346 | H7: =Val!$B$33*(tp_wA*(2/12*E320+10/12*F320)+tp_wB*(2/12*E361+10/12*F361)+tp_wC*(2/12*E402+10/12*F402))*rm_factor -> 159.8576 | I7: =tp_w_dcf*G7+(1-tp_w_dcf)*H7 -> 115.46797 | J7: =I7/I$4-1 -> -0.087831475
A8: 8 吋產能係數：高 | B8: =TEXT(cap_adj_hi,"0.00")&"（基準 "&TEXT(cap_adj,"0.00")&"）" -> 1.05（基準 1.00） | C8: cap_adj | D8: =E443 -> 9.201614 | E8: =F443 -> 9.9012019 | F8: =E8/E$4-1 -> 0.074201818 | G8: =(tp_wA*MAX(0,E443*(1-MIN(tp_g/tp_roe,0.8))/(1+tp_r)^1+F443*(1-MIN(tp_g/tp_roe,0.8))/(1+tp_r)^2+G443*(1-MIN(tp_g/tp_roe,0.8))/(1+tp_r)^3+H443*(1-MIN(tp_g/tp_roe,0.8))/(1+tp_r)^4+I443*(1-MIN(tp_g/tp_roe,0.8))/(1+tp_r)^5+J443*(1-MIN(tp_g/tp_roe,0.8))/(1+tp_r)^6+J443*(1-MIN(tp_g/tp_roe,0.8))*(1+tp_g)/(tp_r-tp_g)/(1+tp_r)^6)+tp_wB*MAX(0,E484*(1-MIN(tp_g/tp_roe,0.8))/(1+tp_r)^1+F484*(1-MIN(tp_g/tp_roe,0.8))/(1+tp_r)^2+G484*(1-MIN(tp_g/tp_roe,0.8))/(1+tp_r)^3+H484*(1-MIN(tp_g/tp_roe,0.8))/(1+tp_r)^4+I484*(1-MIN(tp_g/tp_roe,0.8))/(1+tp_r)^5+J484*(1-MIN(tp_g/tp_roe,0.8))/(1+tp_r)^6+J484*(1-MIN(tp_g/tp_roe,0.8))*(1+tp_g)/(tp_r-tp_g)/(1+tp_r)^6)+tp_wC*MAX(0,E525*(1-MIN(tp_g/tp_roe,0.8))/(1+tp_r)^1+F525*(1-MIN(tp_g/tp_roe,0.8))/(1+tp_r)^2+G525*(1-MIN(tp_g/tp_roe,0.8))/(1+tp_r)^3+H525*(1-MIN(tp_g/tp_roe,0.8))/(1+tp_r)^4+I525*(1-MIN(tp_g/tp_roe,0.8))/(1+tp_r)^5+J525*(1-MIN(tp_g/tp_roe,0.8))/(1+tp_r)^6+J525*(1-MIN(tp_g/tp_roe,0.8))*(1+tp_g)/(tp_r-tp_g)/(1+tp_r)^6))*(1+tp_r) -> 83.865734 | H8: =Val!$B$33*(tp_wA*(2/12*E443+10/12*F443)+tp_wB*(2/12*E484+10/12*F484)+tp_wC*(2/12*E525+10/12*F525))*rm_factor -> 191.51076 | I8: =tp_w_dcf*G8+(1-tp_w_dcf)*H8 -> 137.68825 | J8: =I8/I$4-1 -> 0.087703236
A9: 8 吋稼動率調整：低 | B9: =TEXT(ut_adj_lo,"0.0%")&"（基準 "&TEXT(ut_adj,"0.0%")&"）" -> -3.0%（基準 0.0%） | C9: ut_adj | D9: =E566 -> 8.1043872 | E9: =F566 -> 8.7804515 | F9: =E9/E$4-1 -> -0.04739071 | G9: =(tp_wA*MAX(0,E566*(1-MIN(tp_g/tp_roe,0.8))/(1+tp_r)^1+F566*(1-MIN(tp_g/tp_roe,0.8))/(1+tp_r)^2+G566*(1-MIN(tp_g/tp_roe,0.8))/(1+tp_r)^3+H566*(1-MIN(tp_g/tp_roe,0.8))/(1+tp_r)^4+I566*(1-MIN(tp_g/tp_roe,0.8))/(1+tp_r)^5+J566*(1-MIN(tp_g/tp_roe,0.8))/(1+tp_r)^6+J566*(1-MIN(tp_g/tp_roe,0.8))*(1+tp_g)/(tp_r-tp_g)/(1+tp_r)^6)+tp_wB*MAX(0,E607*(1-MIN(tp_g/tp_roe,0.8))/(1+tp_r)^1+F607*(1-MIN(tp_g/tp_roe,0.8))/(1+tp_r)^2+G607*(1-MIN(tp_g/tp_roe,0.8))/(1+tp_r)^3+H607*(1-MIN(tp_g/tp_roe,0.8))/(1+tp_r)^4+I607*(1-MIN(tp_g/tp_roe,0.8))/(1+tp_r)^5+J607*(1-MIN(tp_g/tp_roe,0.8))/(1+tp_r)^6+J607*(1-MIN(tp_g/tp_roe,0.8))*(1+tp_g)/(tp_r-tp_g)/(1+tp_r)^6)+tp_wC*MAX(0,E648*(1-MIN(tp_g/tp_roe,0.8))/(1+tp_r)^1+F648*(1-MIN(tp_g/tp_roe,0.8))/(1+tp_r)^2+G648*(1-MIN(tp_g/tp_roe,0.8))/(1+tp_r)^3+H648*(1-MIN(tp_g/tp_roe,0.8))/(1+tp_r)^4+I648*(1-MIN(tp_g/tp_roe,0.8))/(1+tp_r)^5+J648*(1-MIN(tp_g/tp_roe,0.8))/(1+tp_r)^6+J648*(1-MIN(tp_g/tp_roe,0.8))*(1+tp_g)/(tp_r-tp_g)/(1+tp_r)^6))*(1+tp_r) -> 73.11507 | H9: =Val!$B$33*(tp_wA*(2/12*E566+10/12*F566)+tp_wB*(2/12*E607+10/12*F607)+tp_wC*(2/12*E648+10/12*F648))*rm_factor -> 164.78031 | I9: =tp_w_dcf*G9+(1-tp_w_dcf)*H9 -> 118.94769 | J9: =I9/I$4-1 -> -0.060342555
A10: 8 吋稼動率調整：高 | B10: =TEXT(ut_adj_hi,"0.0%")&"（基準 "&TEXT(ut_adj,"0.0%")&"）" -> 3.0%（基準 0.0%） | C10: ut_adj | D10: =E689 -> 8.9538531 | E10: =F689 -> 9.6539094 | F10: =E10/E$4-1 -> 0.047372543 | G10: =(tp_wA*MAX(0,E689*(1-MIN(tp_g/tp_roe,0.8))/(1+tp_r)^1+F689*(1-MIN(tp_g/tp_roe,0.8))/(1+tp_r)^2+G689*(1-MIN(tp_g/tp_roe,0.8))/(1+tp_r)^3+H689*(1-MIN(tp_g/tp_roe,0.8))/(1+tp_r)^4+I689*(1-MIN(tp_g/tp_roe,0.8))/(1+tp_r)^5+J689*(1-MIN(tp_g/tp_roe,0.8))/(1+tp_r)^6+J689*(1-MIN(tp_g/tp_roe,0.8))*(1+tp_g)/(tp_r-tp_g)/(1+tp_r)^6)+tp_wB*MAX(0,E730*(1-MIN(tp_g/tp_roe,0.8))/(1+tp_r)^1+F730*(1-MIN(tp_g/tp_roe,0.8))/(1+tp_r)^2+G730*(1-MIN(tp_g/tp_roe,0.8))/(1+tp_r)^3+H730*(1-MIN(tp_g/tp_roe,0.8))/(1+tp_r)^4+I730*(1-MIN(tp_g/tp_roe,0.8))/(1+tp_r)^5+J730*(1-MIN(tp_g/tp_roe,0.8))/(1+tp_r)^6+J730*(1-MIN(tp_g/tp_roe,0.8))*(1+tp_g)/(tp_r-tp_g)/(1+tp_r)^6)+tp_wC*MAX(0,E771*(1-MIN(tp_g/tp_roe,0.8))/(1+tp_r)^1+F771*(1-MIN(tp_g/tp_roe,0.8))/(1+tp_r)^2+G771*(1-MIN(tp_g/tp_roe,0.8))/(1+tp_r)^3+H771*(1-MIN(tp_g/tp_roe,0.8))/(1+tp_r)^4+I771*(1-MIN(tp_g/tp_roe,0.8))/(1+tp_r)^5+J771*(1-MIN(tp_g/tp_roe,0.8))/(1+tp_r)^6+J771*(1-MIN(tp_g/tp_roe,0.8))*(1+tp_g)/(tp_r-tp_g)/(1+tp_r)^6))*(1+tp_r) -> 81.840072 | H10: =Val!$B$33*(tp_wA*(2/12*E689+10/12*F689)+tp_wB*(2/12*E730+10/12*F730)+tp_wC*(2/12*E771+10/12*F771))*rm_factor -> 186.59363 | I10: =tp_w_dcf*G10+(1-tp_w_dcf)*H10 -> 134.21685 | J10: =I10/I$4-1 -> 0.060280041
A11: 8 吋售價水準調整：低 | B11: =TEXT(asp_adj_lo,"0.0%")&"（基準 "&TEXT(asp_adj,"0.0%")&"）" -> -3.0%（基準 0.0%） | C11: asp_adj | D11: =E812 -> 7.6658273 | E11: =F812 -> 8.3426322 | F11: =E11/E$4-1 -> -0.094890634 | G11: =(tp_wA*MAX(0,E812*(1-MIN(tp_g/tp_roe,0.8))/(1+tp_r)^1+F812*(1-MIN(tp_g/tp_roe,0.8))/(1+tp_r)^2+G812*(1-MIN(tp_g/tp_roe,0.8))/(1+tp_r)^3+H812*(1-MIN(tp_g/tp_roe,0.8))/(1+tp_r)^4+I812*(1-MIN(tp_g/tp_roe,0.8))/(1+tp_r)^5+J812*(1-MIN(tp_g/tp_roe,0.8))/(1+tp_r)^6+J812*(1-MIN(tp_g/tp_roe,0.8))*(1+tp_g)/(tp_r-tp_g)/(1+tp_r)^6)+tp_wB*MAX(0,E853*(1-MIN(tp_g/tp_roe,0.8))/(1+tp_r)^1+F853*(1-MIN(tp_g/tp_roe,0.8))/(1+tp_r)^2+G853*(1-MIN(tp_g/tp_roe,0.8))/(1+tp_r)^3+H853*(1-MIN(tp_g/tp_roe,0.8))/(1+tp_r)^4+I853*(1-MIN(tp_g/tp_roe,0.8))/(1+tp_r)^5+J853*(1-MIN(tp_g/tp_roe,0.8))/(1+tp_r)^6+J853*(1-MIN(tp_g/tp_roe,0.8))*(1+tp_g)/(tp_r-tp_g)/(1+tp_r)^6)+tp_wC*MAX(0,E894*(1-MIN(tp_g/tp_roe,0.8))/(1+tp_r)^1+F894*(1-MIN(tp_g/tp_roe,0.8))/(1+tp_r)^2+G894*(1-MIN(tp_g/tp_roe,0.8))/(1+tp_r)^3+H894*(1-MIN(tp_g/tp_roe,0.8))/(1+tp_r)^4+I894*(1-MIN(tp_g/tp_roe,0.8))/(1+tp_r)^5+J894*(1-MIN(tp_g/tp_roe,0.8))/(1+tp_r)^6+J894*(1-MIN(tp_g/tp_roe,0.8))*(1+tp_g)/(tp_r-tp_g)/(1+tp_r)^6))*(1+tp_r) -> 68.605652 | H11: =Val!$B$33*(tp_wA*(2/12*E812+10/12*F812)+tp_wB*(2/12*E853+10/12*F853)+tp_wC*(2/12*E894+10/12*F894))*rm_factor -> 154.508 | I11: =tp_w_dcf*G11+(1-tp_w_dcf)*H11 -> 111.55682 | J11: =I11/I$4-1 -> -0.11872858
A12: 8 吋售價水準調整：高 | B12: =TEXT(asp_adj_hi,"0.0%")&"（基準 "&TEXT(asp_adj,"0.0%")&"）" -> 3.0%（基準 0.0%） | C12: asp_adj | D12: =E935 -> 9.392413 | E12: =F935 -> 10.091733 | F12: =E12/E$4-1 -> 0.094872941 | G12: =(tp_wA*MAX(0,E935*(1-MIN(tp_g/tp_roe,0.8))/(1+tp_r)^1+F935*(1-MIN(tp_g/tp_roe,0.8))/(1+tp_r)^2+G935*(1-MIN(tp_g/tp_roe,0.8))/(1+tp_r)^3+H935*(1-MIN(tp_g/tp_roe,0.8))/(1+tp_r)^4+I935*(1-MIN(tp_g/tp_roe,0.8))/(1+tp_r)^5+J935*(1-MIN(tp_g/tp_roe,0.8))/(1+tp_r)^6+J935*(1-MIN(tp_g/tp_roe,0.8))*(1+tp_g)/(tp_r-tp_g)/(1+tp_r)^6)+tp_wB*MAX(0,E976*(1-MIN(tp_g/tp_roe,0.8))/(1+tp_r)^1+F976*(1-MIN(tp_g/tp_roe,0.8))/(1+tp_r)^2+G976*(1-MIN(tp_g/tp_roe,0.8))/(1+tp_r)^3+H976*(1-MIN(tp_g/tp_roe,0.8))/(1+tp_r)^4+I976*(1-MIN(tp_g/tp_roe,0.8))/(1+tp_r)^5+J976*(1-MIN(tp_g/tp_roe,0.8))/(1+tp_r)^6+J976*(1-MIN(tp_g/tp_roe,0.8))*(1+tp_g)/(tp_r-tp_g)/(1+tp_r)^6)+tp_wC*MAX(0,E1017*(1-MIN(tp_g/tp_roe,0.8))/(1+tp_r)^1+F1017*(1-MIN(tp_g/tp_roe,0.8))/(1+tp_r)^2+G1017*(1-MIN(tp_g/tp_roe,0.8))/(1+tp_r)^3+H1017*(1-MIN(tp_g/tp_roe,0.8))/(1+tp_r)^4+I1017*(1-MIN(tp_g/tp_roe,0.8))/(1+tp_r)^5+J1017*(1-MIN(tp_g/tp_roe,0.8))/(1+tp_r)^6+J1017*(1-MIN(tp_g/tp_roe,0.8))*(1+tp_g)/(tp_r-tp_g)/(1+tp_r)^6))*(1+tp_r) -> 86.338608 | H12: =Val!$B$33*(tp_wA*(2/12*E935+10/12*F935)+tp_wB*(2/12*E976+10/12*F976)+tp_wC*(2/12*E1017+10/12*F1017))*rm_factor -> 196.86571 | I12: =tp_w_dcf*G12+(1-tp_w_dcf)*H12 -> 141.60216 | J12: =I12/I$4-1 -> 0.11862217
A13: 折舊年增調整：低 | B13: =TEXT(dag_adj_lo,"0.0%")&"（基準 "&TEXT(dag_adj,"0.0%")&"）" -> -5.0%（基準 0.0%） | C13: dag_adj | D13: =E1058 -> 8.7220698 | E13: =F1058 -> 9.6031636 | F13: =E13/E$4-1 -> 0.041867025 | G13: =(tp_wA*MAX(0,E1058*(1-MIN(tp_g/tp_roe,0.8))/(1+tp_r)^1+F1058*(1-MIN(tp_g/tp_roe,0.8))/(1+tp_r)^2+G1058*(1-MIN(tp_g/tp_roe,0.8))/(1+tp_r)^3+H1058*(1-MIN(tp_g/tp_roe,0.8))/(1+tp_r)^4+I1058*(1-MIN(tp_g/tp_roe,0.8))/(1+tp_r)^5+J1058*(1-MIN(tp_g/tp_roe,0.8))/(1+tp_r)^6+J1058*(1-MIN(tp_g/tp_roe,0.8))*(1+tp_g)/(tp_r-tp_g)/(1+tp_r)^6)+tp_wB*MAX(0,E1099*(1-MIN(tp_g/tp_roe,0.8))/(1+tp_r)^1+F1099*(1-MIN(tp_g/tp_roe,0.8))/(1+tp_r)^2+G1099*(1-MIN(tp_g/tp_roe,0.8))/(1+tp_r)^3+H1099*(1-MIN(tp_g/tp_roe,0.8))/(1+tp_r)^4+I1099*(1-MIN(tp_g/tp_roe,0.8))/(1+tp_r)^5+J1099*(1-MIN(tp_g/tp_roe,0.8))/(1+tp_r)^6+J1099*(1-MIN(tp_g/tp_roe,0.8))*(1+tp_g)/(tp_r-tp_g)/(1+tp_r)^6)+tp_wC*MAX(0,E1140*(1-MIN(tp_g/tp_roe,0.8))/(1+tp_r)^1+F1140*(1-MIN(tp_g/tp_roe,0.8))/(1+tp_r)^2+G1140*(1-MIN(tp_g/tp_roe,0.8))/(1+tp_r)^3+H1140*(1-MIN(tp_g/tp_roe,0.8))/(1+tp_r)^4+I1140*(1-MIN(tp_g/tp_roe,0.8))/(1+tp_r)^5+J1140*(1-MIN(tp_g/tp_roe,0.8))/(1+tp_r)^6+J1140*(1-MIN(tp_g/tp_roe,0.8))*(1+tp_g)/(tp_r-tp_g)/(1+tp_r)^6))*(1+tp_r) -> 83.633848 | H13: =Val!$B$33*(tp_wA*(2/12*E1058+10/12*F1058)+tp_wB*(2/12*E1099+10/12*F1099)+tp_wC*(2/12*E1140+10/12*F1140))*rm_factor -> 185.38971 | I13: =tp_w_dcf*G13+(1-tp_w_dcf)*H13 -> 134.51178 | J13: =I13/I$4-1 -> 0.06260989
A14: 折舊年增調整：高 | B14: =TEXT(dag_adj_hi,"0.0%")&"（基準 "&TEXT(dag_adj,"0.0%")&"）" -> 5.0%（基準 0.0%） | C14: dag_adj | D14: =E1181 -> 8.3361704 | E14: =F1181 -> 8.8120698 | F14: =E14/E$4-1 -> -0.043960376 | G14: =(tp_wA*MAX(0,E1181*(1-MIN(tp_g/tp_roe,0.8))/(1+tp_r)^1+F1181*(1-MIN(tp_g/tp_roe,0.8))/(1+tp_r)^2+G1181*(1-MIN(tp_g/tp_roe,0.8))/(1+tp_r)^3+H1181*(1-MIN(tp_g/tp_roe,0.8))/(1+tp_r)^4+I1181*(1-MIN(tp_g/tp_roe,0.8))/(1+tp_r)^5+J1181*(1-MIN(tp_g/tp_roe,0.8))/(1+tp_r)^6+J1181*(1-MIN(tp_g/tp_roe,0.8))*(1+tp_g)/(tp_r-tp_g)/(1+tp_r)^6)+tp_wB*MAX(0,E1222*(1-MIN(tp_g/tp_roe,0.8))/(1+tp_r)^1+F1222*(1-MIN(tp_g/tp_roe,0.8))/(1+tp_r)^2+G1222*(1-MIN(tp_g/tp_roe,0.8))/(1+tp_r)^3+H1222*(1-MIN(tp_g/tp_roe,0.8))/(1+tp_r)^4+I1222*(1-MIN(tp_g/tp_roe,0.8))/(1+tp_r)^5+J1222*(1-MIN(tp_g/tp_roe,0.8))/(1+tp_r)^6+J1222*(1-MIN(tp_g/tp_roe,0.8))*(1+tp_g)/(tp_r-tp_g)/(1+tp_r)^6)+tp_wC*MAX(0,E1263*(1-MIN(tp_g/tp_roe,0.8))/(1+tp_r)^1+F1263*(1-MIN(tp_g/tp_roe,0.8))/(1+tp_r)^2+G1263*(1-MIN(tp_g/tp_roe,0.8))/(1+tp_r)^3+H1263*(1-MIN(tp_g/tp_roe,0.8))/(1+tp_r)^4+I1263*(1-MIN(tp_g/tp_roe,0.8))/(1+tp_r)^5+J1263*(1-MIN(tp_g/tp_roe,0.8))/(1+tp_r)^6+J1263*(1-MIN(tp_g/tp_roe,0.8))*(1+tp_g)/(tp_r-tp_g)/(1+tp_r)^6))*(1+tp_r) -> 70.725342 | H14: =Val!$B$33*(tp_wA*(2/12*E1181+10/12*F1181)+tp_wB*(2/12*E1222+10/12*F1222)+tp_wC*(2/12*E1263+10/12*F1263))*rm_factor -> 165.54603 | I14: =tp_w_dcf*G14+(1-tp_w_dcf)*H14 -> 118.13569 | J14: =I14/I$4-1 -> -0.066757177
A15: 每片現金成本年增：低 | B15: =TEXT(cc_g_lo,"0.0%")&"（基準 "&TEXT(cc_g,"0.0%")&"）" -> 0.0%（基準 2.0%） | C15: cc_g | D15: =E1304 -> 8.8296407 | E15: =F1304 -> 9.8179258 | F15: =E15/E$4-1 -> 0.065167018 | G15: =(tp_wA*MAX(0,E1304*(1-MIN(tp_g/tp_roe,0.8))/(1+tp_r)^1+F1304*(1-MIN(tp_g/tp_roe,0.8))/(1+tp_r)^2+G1304*(1-MIN(tp_g/tp_roe,0.8))/(1+tp_r)^3+H1304*(1-MIN(tp_g/tp_roe,0.8))/(1+tp_r)^4+I1304*(1-MIN(tp_g/tp_roe,0.8))/(1+tp_r)^5+J1304*(1-MIN(tp_g/tp_roe,0.8))/(1+tp_r)^6+J1304*(1-MIN(tp_g/tp_roe,0.8))*(1+tp_g)/(tp_r-tp_g)/(1+tp_r)^6)+tp_wB*MAX(0,E1345*(1-MIN(tp_g/tp_roe,0.8))/(1+tp_r)^1+F1345*(1-MIN(tp_g/tp_roe,0.8))/(1+tp_r)^2+G1345*(1-MIN(tp_g/tp_roe,0.8))/(1+tp_r)^3+H1345*(1-MIN(tp_g/tp_roe,0.8))/(1+tp_r)^4+I1345*(1-MIN(tp_g/tp_roe,0.8))/(1+tp_r)^5+J1345*(1-MIN(tp_g/tp_roe,0.8))/(1+tp_r)^6+J1345*(1-MIN(tp_g/tp_roe,0.8))*(1+tp_g)/(tp_r-tp_g)/(1+tp_r)^6)+tp_wC*MAX(0,E1386*(1-MIN(tp_g/tp_roe,0.8))/(1+tp_r)^1+F1386*(1-MIN(tp_g/tp_roe,0.8))/(1+tp_r)^2+G1386*(1-MIN(tp_g/tp_roe,0.8))/(1+tp_r)^3+H1386*(1-MIN(tp_g/tp_roe,0.8))/(1+tp_r)^4+I1386*(1-MIN(tp_g/tp_roe,0.8))/(1+tp_r)^5+J1386*(1-MIN(tp_g/tp_roe,0.8))/(1+tp_r)^6+J1386*(1-MIN(tp_g/tp_roe,0.8))*(1+tp_g)/(tp_r-tp_g)/(1+tp_r)^6))*(1+tp_r) -> 86.608583 | H15: =Val!$B$33*(tp_wA*(2/12*E1304+10/12*F1304)+tp_wB*(2/12*E1345+10/12*F1345)+tp_wC*(2/12*E1386+10/12*F1386))*rm_factor -> 189.54177 | I15: =tp_w_dcf*G15+(1-tp_w_dcf)*H15 -> 138.07518 | J15: =I15/I$4-1 -> 0.090759874
A16: 每片現金成本年增：高 | B16: =TEXT(cc_g_hi,"0.0%")&"（基準 "&TEXT(cc_g,"0.0%")&"）" -> 4.0%（基準 2.0%） | C16: cc_g | D16: =E1427 -> 8.2285995 | E16: =F1427 -> 8.6047083 | F16: =E16/E$4-1 -> -0.066457454 | G16: =(tp_wA*MAX(0,E1427*(1-MIN(tp_g/tp_roe,0.8))/(1+tp_r)^1+F1427*(1-MIN(tp_g/tp_roe,0.8))/(1+tp_r)^2+G1427*(1-MIN(tp_g/tp_roe,0.8))/(1+tp_r)^3+H1427*(1-MIN(tp_g/tp_roe,0.8))/(1+tp_r)^4+I1427*(1-MIN(tp_g/tp_roe,0.8))/(1+tp_r)^5+J1427*(1-MIN(tp_g/tp_roe,0.8))/(1+tp_r)^6+J1427*(1-MIN(tp_g/tp_roe,0.8))*(1+tp_g)/(tp_r-tp_g)/(1+tp_r)^6)+tp_wB*MAX(0,E1468*(1-MIN(tp_g/tp_roe,0.8))/(1+tp_r)^1+F1468*(1-MIN(tp_g/tp_roe,0.8))/(1+tp_r)^2+G1468*(1-MIN(tp_g/tp_roe,0.8))/(1+tp_r)^3+H1468*(1-MIN(tp_g/tp_roe,0.8))/(1+tp_r)^4+I1468*(1-MIN(tp_g/tp_roe,0.8))/(1+tp_r)^5+J1468*(1-MIN(tp_g/tp_roe,0.8))/(1+tp_r)^6+J1468*(1-MIN(tp_g/tp_roe,0.8))*(1+tp_g)/(tp_r-tp_g)/(1+tp_r)^6)+tp_wC*MAX(0,E1509*(1-MIN(tp_g/tp_roe,0.8))/(1+tp_r)^1+F1509*(1-MIN(tp_g/tp_roe,0.8))/(1+tp_r)^2+G1509*(1-MIN(tp_g/tp_roe,0.8))/(1+tp_r)^3+H1509*(1-MIN(tp_g/tp_roe,0.8))/(1+tp_r)^4+I1509*(1-MIN(tp_g/tp_roe,0.8))/(1+tp_r)^5+J1509*(1-MIN(tp_g/tp_roe,0.8))/(1+tp_r)^6+J1509*(1-MIN(tp_g/tp_roe,0.8))*(1+tp_g)/(tp_r-tp_g)/(1+tp_r)^6))*(1+tp_r) -> 68.009459 | H16: =Val!$B$33*(tp_wA*(2/12*E1427+10/12*F1427)+tp_wB*(2/12*E1468+10/12*F1468)+tp_wC*(2/12*E1509+10/12*F1509))*rm_factor -> 161.58624 | I16: =tp_w_dcf*G16+(1-tp_w_dcf)*H16 -> 114.79785 | J16: =I16/I$4-1 -> -0.093125279
A17: 營業費用彈性：低 | B17: =TEXT(phi_lo,"0.00")&"（基準 "&TEXT(phi,"0.00")&"）" -> 0.30（基準 0.50） | C17: phi | D17: =E1550 -> 8.7092092 | E17: =F1550 -> 9.5144704 | F17: =E17/E$4-1 -> 0.032244516 | G17: =(tp_wA*MAX(0,E1550*(1-MIN(tp_g/tp_roe,0.8))/(1+tp_r)^1+F1550*(1-MIN(tp_g/tp_roe,0.8))/(1+tp_r)^2+G1550*(1-MIN(tp_g/tp_roe,0.8))/(1+tp_r)^3+H1550*(1-MIN(tp_g/tp_roe,0.8))/(1+tp_r)^4+I1550*(1-MIN(tp_g/tp_roe,0.8))/(1+tp_r)^5+J1550*(1-MIN(tp_g/tp_roe,0.8))/(1+tp_r)^6+J1550*(1-MIN(tp_g/tp_roe,0.8))*(1+tp_g)/(tp_r-tp_g)/(1+tp_r)^6)+tp_wB*MAX(0,E1591*(1-MIN(tp_g/tp_roe,0.8))/(1+tp_r)^1+F1591*(1-MIN(tp_g/tp_roe,0.8))/(1+tp_r)^2+G1591*(1-MIN(tp_g/tp_roe,0.8))/(1+tp_r)^3+H1591*(1-MIN(tp_g/tp_roe,0.8))/(1+tp_r)^4+I1591*(1-MIN(tp_g/tp_roe,0.8))/(1+tp_r)^5+J1591*(1-MIN(tp_g/tp_roe,0.8))/(1+tp_r)^6+J1591*(1-MIN(tp_g/tp_roe,0.8))*(1+tp_g)/(tp_r-tp_g)/(1+tp_r)^6)+tp_wC*MAX(0,E1632*(1-MIN(tp_g/tp_roe,0.8))/(1+tp_r)^1+F1632*(1-MIN(tp_g/tp_roe,0.8))/(1+tp_r)^2+G1632*(1-MIN(tp_g/tp_roe,0.8))/(1+tp_r)^3+H1632*(1-MIN(tp_g/tp_roe,0.8))/(1+tp_r)^4+I1632*(1-MIN(tp_g/tp_roe,0.8))/(1+tp_r)^5+J1632*(1-MIN(tp_g/tp_roe,0.8))/(1+tp_r)^6+J1632*(1-MIN(tp_g/tp_roe,0.8))*(1+tp_g)/(tp_r-tp_g)/(1+tp_r)^6))*(1+tp_r) -> 80.266141 | H17: =Val!$B$33*(tp_wA*(2/12*E1550+10/12*F1550)+tp_wB*(2/12*E1591+10/12*F1591)+tp_wC*(2/12*E1632+10/12*F1632))*rm_factor -> 180.3703 | I17: =tp_w_dcf*G17+(1-tp_w_dcf)*H17 -> 130.31822 | J17: =I17/I$4-1 -> 0.029481838
A18: 營業費用彈性：高 | B18: =TEXT(phi_hi,"0.00")&"（基準 "&TEXT(phi,"0.00")&"）" -> 0.80（基準 0.50） | C18: phi | D18: =E1673 -> 8.2589866 | E18: =F1673 -> 8.7504306 | F18: =E18/E$4-1 -> -0.050647741 | G18: =(tp_wA*MAX(0,E1673*(1-MIN(tp_g/tp_roe,0.8))/(1+tp_r)^1+F1673*(1-MIN(tp_g/tp_roe,0.8))/(1+tp_r)^2+G1673*(1-MIN(tp_g/tp_roe,0.8))/(1+tp_r)^3+H1673*(1-MIN(tp_g/tp_roe,0.8))/(1+tp_r)^4+I1673*(1-MIN(tp_g/tp_roe,0.8))/(1+tp_r)^5+J1673*(1-MIN(tp_g/tp_roe,0.8))/(1+tp_r)^6+J1673*(1-MIN(tp_g/tp_roe,0.8))*(1+tp_g)/(tp_r-tp_g)/(1+tp_r)^6)+tp_wB*MAX(0,E1714*(1-MIN(tp_g/tp_roe,0.8))/(1+tp_r)^1+F1714*(1-MIN(tp_g/tp_roe,0.8))/(1+tp_r)^2+G1714*(1-MIN(tp_g/tp_roe,0.8))/(1+tp_r)^3+H1714*(1-MIN(tp_g/tp_roe,0.8))/(1+tp_r)^4+I1714*(1-MIN(tp_g/tp_roe,0.8))/(1+tp_r)^5+J1714*(1-MIN(tp_g/tp_roe,0.8))/(1+tp_r)^6+J1714*(1-MIN(tp_g/tp_roe,0.8))*(1+tp_g)/(tp_r-tp_g)/(1+tp_r)^6)+tp_wC*MAX(0,E1755*(1-MIN(tp_g/tp_roe,0.8))/(1+tp_r)^1+F1755*(1-MIN(tp_g/tp_roe,0.8))/(1+tp_r)^2+G1755*(1-MIN(tp_g/tp_roe,0.8))/(1+tp_r)^3+H1755*(1-MIN(tp_g/tp_roe,0.8))/(1+tp_r)^4+I1755*(1-MIN(tp_g/tp_roe,0.8))/(1+tp_r)^5+J1755*(1-MIN(tp_g/tp_roe,0.8))/(1+tp_r)^6+J1755*(1-MIN(tp_g/tp_roe,0.8))*(1+tp_g)/(tp_r-tp_g)/(1+tp_r)^6))*(1+tp_r) -> 72.934574 | H18: =Val!$B$33*(tp_wA*(2/12*E1673+10/12*F1673)+tp_wB*(2/12*E1714+10/12*F1714)+tp_wC*(2/12*E1755+10/12*F1755))*rm_factor -> 168.42026 | I18: =tp_w_dcf*G18+(1-tp_w_dcf)*H18 -> 120.67742 | J18: =I18/I$4-1 -> -0.046678156
A19: 營業外淨額：低 | B19: =TEXT(nonop_f_lo,"0.0")&"（基準 "&TEXT(nonop_f,"0.0")&"）" -> 0.5（基準 1.5） | C19: nonop_f | D19: =E1796 -> 8.0834058 | E19: =F1796 -> 8.7715499 | F19: =E19/E$4-1 -> -0.048356462 | G19: =(tp_wA*MAX(0,E1796*(1-MIN(tp_g/tp_roe,0.8))/(1+tp_r)^1+F1796*(1-MIN(tp_g/tp_roe,0.8))/(1+tp_r)^2+G1796*(1-MIN(tp_g/tp_roe,0.8))/(1+tp_r)^3+H1796*(1-MIN(tp_g/tp_roe,0.8))/(1+tp_r)^4+I1796*(1-MIN(tp_g/tp_roe,0.8))/(1+tp_r)^5+J1796*(1-MIN(tp_g/tp_roe,0.8))/(1+tp_r)^6+J1796*(1-MIN(tp_g/tp_roe,0.8))*(1+tp_g)/(tp_r-tp_g)/(1+tp_r)^6)+tp_wB*MAX(0,E1837*(1-MIN(tp_g/tp_roe,0.8))/(1+tp_r)^1+F1837*(1-MIN(tp_g/tp_roe,0.8))/(1+tp_r)^2+G1837*(1-MIN(tp_g/tp_roe,0.8))/(1+tp_r)^3+H1837*(1-MIN(tp_g/tp_roe,0.8))/(1+tp_r)^4+I1837*(1-MIN(tp_g/tp_roe,0.8))/(1+tp_r)^5+J1837*(1-MIN(tp_g/tp_roe,0.8))/(1+tp_r)^6+J1837*(1-MIN(tp_g/tp_roe,0.8))*(1+tp_g)/(tp_r-tp_g)/(1+tp_r)^6)+tp_wC*MAX(0,E1878*(1-MIN(tp_g/tp_roe,0.8))/(1+tp_r)^1+F1878*(1-MIN(tp_g/tp_roe,0.8))/(1+tp_r)^2+G1878*(1-MIN(tp_g/tp_roe,0.8))/(1+tp_r)^3+H1878*(1-MIN(tp_g/tp_roe,0.8))/(1+tp_r)^4+I1878*(1-MIN(tp_g/tp_roe,0.8))/(1+tp_r)^5+J1878*(1-MIN(tp_g/tp_roe,0.8))/(1+tp_r)^6+J1878*(1-MIN(tp_g/tp_roe,0.8))*(1+tp_g)/(tp_r-tp_g)/(1+tp_r)^6))*(1+tp_r) -> 72.376086 | H19: =Val!$B$33*(tp_wA*(2/12*E1796+10/12*F1796)+tp_wB*(2/12*E1837+10/12*F1837)+tp_wC*(2/12*E1878+10/12*F1878))*rm_factor -> 163.46464 | I19: =tp_w_dcf*G19+(1-tp_w_dcf)*H19 -> 117.92036 | J19: =I19/I$4-1 -> -0.068458187
A20: 營業外淨額：高 | B20: =TEXT(nonop_f_hi,"0.0")&"（基準 "&TEXT(nonop_f,"0.0")&"）" -> 2.5（基準 1.5） | C20: nonop_f | D20: =E1919 -> 8.9748344 | E20: =F1919 -> 9.6629785 | F20: =E20/E$4-1 -> 0.048356462 | G20: =(tp_wA*MAX(0,E1919*(1-MIN(tp_g/tp_roe,0.8))/(1+tp_r)^1+F1919*(1-MIN(tp_g/tp_roe,0.8))/(1+tp_r)^2+G1919*(1-MIN(tp_g/tp_roe,0.8))/(1+tp_r)^3+H1919*(1-MIN(tp_g/tp_roe,0.8))/(1+tp_r)^4+I1919*(1-MIN(tp_g/tp_roe,0.8))/(1+tp_r)^5+J1919*(1-MIN(tp_g/tp_roe,0.8))/(1+tp_r)^6+J1919*(1-MIN(tp_g/tp_roe,0.8))*(1+tp_g)/(tp_r-tp_g)/(1+tp_r)^6)+tp_wB*MAX(0,E1960*(1-MIN(tp_g/tp_roe,0.8))/(1+tp_r)^1+F1960*(1-MIN(tp_g/tp_roe,0.8))/(1+tp_r)^2+G1960*(1-MIN(tp_g/tp_roe,0.8))/(1+tp_r)^3+H1960*(1-MIN(tp_g/tp_roe,0.8))/(1+tp_r)^4+I1960*(1-MIN(tp_g/tp_roe,0.8))/(1+tp_r)^5+J1960*(1-MIN(tp_g/tp_roe,0.8))/(1+tp_r)^6+J1960*(1-MIN(tp_g/tp_roe,0.8))*(1+tp_g)/(tp_r-tp_g)/(1+tp_r)^6)+tp_wC*MAX(0,E2001*(1-MIN(tp_g/tp_roe,0.8))/(1+tp_r)^1+F2001*(1-MIN(tp_g/tp_roe,0.8))/(1+tp_r)^2+G2001*(1-MIN(tp_g/tp_roe,0.8))/(1+tp_r)^3+H2001*(1-MIN(tp_g/tp_roe,0.8))/(1+tp_r)^4+I2001*(1-MIN(tp_g/tp_roe,0.8))/(1+tp_r)^5+J2001*(1-MIN(tp_g/tp_roe,0.8))/(1+tp_r)^6+J2001*(1-MIN(tp_g/tp_roe,0.8))*(1+tp_g)/(tp_r-tp_g)/(1+tp_r)^6))*(1+tp_r) -> 82.592112 | H20: =Val!$B$33*(tp_wA*(2/12*E1919+10/12*F1919)+tp_wB*(2/12*E1960+10/12*F1960)+tp_wC*(2/12*E2001+10/12*F2001))*rm_factor -> 187.91207 | I20: =tp_w_dcf*G20+(1-tp_w_dcf)*H20 -> 135.25209 | J20: =I20/I$4-1 -> 0.068458187
A21: 稅率：低 | B21: =TEXT(tax_lo,"0%")&"（基準 "&TEXT(tax,"0%")&"）" -> 12%（基準 15%） | C21: tax | D21: =E2042 -> 8.8301479 | E21: =F2042 -> 9.5425794 | F21: =E21/E$4-1 -> 0.035294118 | G21: =(tp_wA*MAX(0,E2042*(1-MIN(tp_g/tp_roe,0.8))/(1+tp_r)^1+F2042*(1-MIN(tp_g/tp_roe,0.8))/(1+tp_r)^2+G2042*(1-MIN(tp_g/tp_roe,0.8))/(1+tp_r)^3+H2042*(1-MIN(tp_g/tp_roe,0.8))/(1+tp_r)^4+I2042*(1-MIN(tp_g/tp_roe,0.8))/(1+tp_r)^5+J2042*(1-MIN(tp_g/tp_roe,0.8))/(1+tp_r)^6+J2042*(1-MIN(tp_g/tp_roe,0.8))*(1+tp_g)/(tp_r-tp_g)/(1+tp_r)^6)+tp_wB*MAX(0,E2083*(1-MIN(tp_g/tp_roe,0.8))/(1+tp_r)^1+F2083*(1-MIN(tp_g/tp_roe,0.8))/(1+tp_r)^2+G2083*(1-MIN(tp_g/tp_roe,0.8))/(1+tp_r)^3+H2083*(1-MIN(tp_g/tp_roe,0.8))/(1+tp_r)^4+I2083*(1-MIN(tp_g/tp_roe,0.8))/(1+tp_r)^5+J2083*(1-MIN(tp_g/tp_roe,0.8))/(1+tp_r)^6+J2083*(1-MIN(tp_g/tp_roe,0.8))*(1+tp_g)/(tp_r-tp_g)/(1+tp_r)^6)+tp_wC*MAX(0,E2124*(1-MIN(tp_g/tp_roe,0.8))/(1+tp_r)^1+F2124*(1-MIN(tp_g/tp_roe,0.8))/(1+tp_r)^2+G2124*(1-MIN(tp_g/tp_roe,0.8))/(1+tp_r)^3+H2124*(1-MIN(tp_g/tp_roe,0.8))/(1+tp_r)^4+I2124*(1-MIN(tp_g/tp_roe,0.8))/(1+tp_r)^5+J2124*(1-MIN(tp_g/tp_roe,0.8))/(1+tp_r)^6+J2124*(1-MIN(tp_g/tp_roe,0.8))*(1+tp_g)/(tp_r-tp_g)/(1+tp_r)^6))*(1+tp_r) -> 80.218832 | H21: =Val!$B$33*(tp_wA*(2/12*E2042+10/12*F2042)+tp_wB*(2/12*E2083+10/12*F2083)+tp_wC*(2/12*E2124+10/12*F2124))*rm_factor -> 181.88912 | I21: =tp_w_dcf*G21+(1-tp_w_dcf)*H21 -> 131.05398 | J21: =I21/I$4-1 -> 0.035294118
A22: 稅率：高 | B22: =TEXT(tax_hi,"0%")&"（基準 "&TEXT(tax,"0%")&"）" -> 20%（基準 15%） | C22: tax | D22: =E2165 -> 8.0274072 | E22: =F2165 -> 8.6750722 | F22: =E22/E$4-1 -> -0.058823529 | G22: =(tp_wA*MAX(0,E2165*(1-MIN(tp_g/tp_roe,0.8))/(1+tp_r)^1+F2165*(1-MIN(tp_g/tp_roe,0.8))/(1+tp_r)^2+G2165*(1-MIN(tp_g/tp_roe,0.8))/(1+tp_r)^3+H2165*(1-MIN(tp_g/tp_roe,0.8))/(1+tp_r)^4+I2165*(1-MIN(tp_g/tp_roe,0.8))/(1+tp_r)^5+J2165*(1-MIN(tp_g/tp_roe,0.8))/(1+tp_r)^6+J2165*(1-MIN(tp_g/tp_roe,0.8))*(1+tp_g)/(tp_r-tp_g)/(1+tp_r)^6)+tp_wB*MAX(0,E2206*(1-MIN(tp_g/tp_roe,0.8))/(1+tp_r)^1+F2206*(1-MIN(tp_g/tp_roe,0.8))/(1+tp_r)^2+G2206*(1-MIN(tp_g/tp_roe,0.8))/(1+tp_r)^3+H2206*(1-MIN(tp_g/tp_roe,0.8))/(1+tp_r)^4+I2206*(1-MIN(tp_g/tp_roe,0.8))/(1+tp_r)^5+J2206*(1-MIN(tp_g/tp_roe,0.8))/(1+tp_r)^6+J2206*(1-MIN(tp_g/tp_roe,0.8))*(1+tp_g)/(tp_r-tp_g)/(1+tp_r)^6)+tp_wC*MAX(0,E2247*(1-MIN(tp_g/tp_roe,0.8))/(1+tp_r)^1+F2247*(1-MIN(tp_g/tp_roe,0.8))/(1+tp_r)^2+G2247*(1-MIN(tp_g/tp_roe,0.8))/(1+tp_r)^3+H2247*(1-MIN(tp_g/tp_roe,0.8))/(1+tp_r)^4+I2247*(1-MIN(tp_g/tp_roe,0.8))/(1+tp_r)^5+J2247*(1-MIN(tp_g/tp_roe,0.8))/(1+tp_r)^6+J2247*(1-MIN(tp_g/tp_roe,0.8))*(1+tp_g)/(tp_r-tp_g)/(1+tp_r)^6))*(1+tp_r) -> 72.926211 | H22: =Val!$B$33*(tp_wA*(2/12*E2165+10/12*F2165)+tp_wB*(2/12*E2206+10/12*F2206)+tp_wC*(2/12*E2247+10/12*F2247))*rm_factor -> 165.35375 | I22: =tp_w_dcf*G22+(1-tp_w_dcf)*H22 -> 119.13998 | J22: =I22/I$4-1 -> -0.058823529
A23: VSMC 產能係數：低 | B23: =TEXT(vcap_adj_lo,"0.00")&"（基準 "&TEXT(vcap_adj,"0.00")&"）" -> 0.80（基準 1.00） | C23: vcap_adj | D23: =E2288 -> 8.5478692 | E23: =F2288 -> 9.1058567 | F23: =E23/E$4-1 -> -0.012086831 | G23: =(tp_wA*MAX(0,E2288*(1-MIN(tp_g/tp_roe,0.8))/(1+tp_r)^1+F2288*(1-MIN(tp_g/tp_roe,0.8))/(1+tp_r)^2+G2288*(1-MIN(tp_g/tp_roe,0.8))/(1+tp_r)^3+H2288*(1-MIN(tp_g/tp_roe,0.8))/(1+tp_r)^4+I2288*(1-MIN(tp_g/tp_roe,0.8))/(1+tp_r)^5+J2288*(1-MIN(tp_g/tp_roe,0.8))/(1+tp_r)^6+J2288*(1-MIN(tp_g/tp_roe,0.8))*(1+tp_g)/(tp_r-tp_g)/(1+tp_r)^6)+tp_wB*MAX(0,E2329*(1-MIN(tp_g/tp_roe,0.8))/(1+tp_r)^1+F2329*(1-MIN(tp_g/tp_roe,0.8))/(1+tp_r)^2+G2329*(1-MIN(tp_g/tp_roe,0.8))/(1+tp_r)^3+H2329*(1-MIN(tp_g/tp_roe,0.8))/(1+tp_r)^4+I2329*(1-MIN(tp_g/tp_roe,0.8))/(1+tp_r)^5+J2329*(1-MIN(tp_g/tp_roe,0.8))/(1+tp_r)^6+J2329*(1-MIN(tp_g/tp_roe,0.8))*(1+tp_g)/(tp_r-tp_g)/(1+tp_r)^6)+tp_wC*MAX(0,E2370*(1-MIN(tp_g/tp_roe,0.8))/(1+tp_r)^1+F2370*(1-MIN(tp_g/tp_roe,0.8))/(1+tp_r)^2+G2370*(1-MIN(tp_g/tp_roe,0.8))/(1+tp_r)^3+H2370*(1-MIN(tp_g/tp_roe,0.8))/(1+tp_r)^4+I2370*(1-MIN(tp_g/tp_roe,0.8))/(1+tp_r)^5+J2370*(1-MIN(tp_g/tp_roe,0.8))/(1+tp_r)^6+J2370*(1-MIN(tp_g/tp_roe,0.8))*(1+tp_g)/(tp_r-tp_g)/(1+tp_r)^6))*(1+tp_r) -> 75.269754 | H23: =Val!$B$33*(tp_wA*(2/12*E2288+10/12*F2288)+tp_wB*(2/12*E2329+10/12*F2329)+tp_wC*(2/12*E2370+10/12*F2370))*rm_factor -> 174.82918 | I23: =tp_w_dcf*G23+(1-tp_w_dcf)*H23 -> 125.04947 | J23: =I23/I$4-1 -> -0.012140024
A24: VSMC 產能係數：高 | B24: =TEXT(vcap_adj_hi,"0.00")&"（基準 "&TEXT(vcap_adj,"0.00")&"）" -> 1.20（基準 1.00） | C24: vcap_adj | D24: =E2411 -> 8.510371 | E24: =F2411 -> 9.3294607 | F24: =E24/E$4-1 -> 0.012172429 | G24: =(tp_wA*MAX(0,E2411*(1-MIN(tp_g/tp_roe,0.8))/(1+tp_r)^1+F2411*(1-MIN(tp_g/tp_roe,0.8))/(1+tp_r)^2+G2411*(1-MIN(tp_g/tp_roe,0.8))/(1+tp_r)^3+H2411*(1-MIN(tp_g/tp_roe,0.8))/(1+tp_r)^4+I2411*(1-MIN(tp_g/tp_roe,0.8))/(1+tp_r)^5+J2411*(1-MIN(tp_g/tp_roe,0.8))/(1+tp_r)^6+J2411*(1-MIN(tp_g/tp_roe,0.8))*(1+tp_g)/(tp_r-tp_g)/(1+tp_r)^6)+tp_wB*MAX(0,E2452*(1-MIN(tp_g/tp_roe,0.8))/(1+tp_r)^1+F2452*(1-MIN(tp_g/tp_roe,0.8))/(1+tp_r)^2+G2452*(1-MIN(tp_g/tp_roe,0.8))/(1+tp_r)^3+H2452*(1-MIN(tp_g/tp_roe,0.8))/(1+tp_r)^4+I2452*(1-MIN(tp_g/tp_roe,0.8))/(1+tp_r)^5+J2452*(1-MIN(tp_g/tp_roe,0.8))/(1+tp_r)^6+J2452*(1-MIN(tp_g/tp_roe,0.8))*(1+tp_g)/(tp_r-tp_g)/(1+tp_r)^6)+tp_wC*MAX(0,E2493*(1-MIN(tp_g/tp_roe,0.8))/(1+tp_r)^1+F2493*(1-MIN(tp_g/tp_roe,0.8))/(1+tp_r)^2+G2493*(1-MIN(tp_g/tp_roe,0.8))/(1+tp_r)^3+H2493*(1-MIN(tp_g/tp_roe,0.8))/(1+tp_r)^4+I2493*(1-MIN(tp_g/tp_roe,0.8))/(1+tp_r)^5+J2493*(1-MIN(tp_g/tp_roe,0.8))/(1+tp_r)^6+J2493*(1-MIN(tp_g/tp_roe,0.8))*(1+tp_g)/(tp_r-tp_g)/(1+tp_r)^6))*(1+tp_r) -> 79.685832 | H24: =Val!$B$33*(tp_wA*(2/12*E2411+10/12*F2411)+tp_wB*(2/12*E2452+10/12*F2452)+tp_wC*(2/12*E2493+10/12*F2493))*rm_factor -> 176.56174 | I24: =tp_w_dcf*G24+(1-tp_w_dcf)*H24 -> 128.12378 | J24: =I24/I$4-1 -> 0.012146323
A25: VSMC 售價：低 | B25: =TEXT(vasp_lo,"#,##0")&"（基準 "&TEXT(vasp,"#,##0")&"）" -> 1,500（基準 1,800） | C25: vasp | D25: =E2534 -> 8.5447444 | E25: =F2534 -> 9.1243678 | F25: =E25/E$4-1 -> -0.010078521 | G25: =(tp_wA*MAX(0,E2534*(1-MIN(tp_g/tp_roe,0.8))/(1+tp_r)^1+F2534*(1-MIN(tp_g/tp_roe,0.8))/(1+tp_r)^2+G2534*(1-MIN(tp_g/tp_roe,0.8))/(1+tp_r)^3+H2534*(1-MIN(tp_g/tp_roe,0.8))/(1+tp_r)^4+I2534*(1-MIN(tp_g/tp_roe,0.8))/(1+tp_r)^5+J2534*(1-MIN(tp_g/tp_roe,0.8))/(1+tp_r)^6+J2534*(1-MIN(tp_g/tp_roe,0.8))*(1+tp_g)/(tp_r-tp_g)/(1+tp_r)^6)+tp_wB*MAX(0,E2575*(1-MIN(tp_g/tp_roe,0.8))/(1+tp_r)^1+F2575*(1-MIN(tp_g/tp_roe,0.8))/(1+tp_r)^2+G2575*(1-MIN(tp_g/tp_roe,0.8))/(1+tp_r)^3+H2575*(1-MIN(tp_g/tp_roe,0.8))/(1+tp_r)^4+I2575*(1-MIN(tp_g/tp_roe,0.8))/(1+tp_r)^5+J2575*(1-MIN(tp_g/tp_roe,0.8))/(1+tp_r)^6+J2575*(1-MIN(tp_g/tp_roe,0.8))*(1+tp_g)/(tp_r-tp_g)/(1+tp_r)^6)+tp_wC*MAX(0,E2616*(1-MIN(tp_g/tp_roe,0.8))/(1+tp_r)^1+F2616*(1-MIN(tp_g/tp_roe,0.8))/(1+tp_r)^2+G2616*(1-MIN(tp_g/tp_roe,0.8))/(1+tp_r)^3+H2616*(1-MIN(tp_g/tp_roe,0.8))/(1+tp_r)^4+I2616*(1-MIN(tp_g/tp_roe,0.8))/(1+tp_r)^5+J2616*(1-MIN(tp_g/tp_roe,0.8))/(1+tp_r)^6+J2616*(1-MIN(tp_g/tp_roe,0.8))*(1+tp_g)/(tp_r-tp_g)/(1+tp_r)^6))*(1+tp_r) -> 75.639802 | H25: =Val!$B$33*(tp_wA*(2/12*E2534+10/12*F2534)+tp_wB*(2/12*E2575+10/12*F2575)+tp_wC*(2/12*E2616+10/12*F2616))*rm_factor -> 174.97135 | I25: =tp_w_dcf*G25+(1-tp_w_dcf)*H25 -> 125.30558 | J25: =I25/I$4-1 -> -0.010116812
A26: VSMC 售價：高 | B26: =TEXT(vasp_hi,"#,##0")&"（基準 "&TEXT(vasp,"#,##0")&"）" -> 2,100（基準 1,800） | C26: vasp | D26: =E2657 -> 8.5134959 | E26: =F2657 -> 9.3107084 | F26: =E26/E$4-1 -> 0.010137957 | G26: =(tp_wA*MAX(0,E2657*(1-MIN(tp_g/tp_roe,0.8))/(1+tp_r)^1+F2657*(1-MIN(tp_g/tp_roe,0.8))/(1+tp_r)^2+G2657*(1-MIN(tp_g/tp_roe,0.8))/(1+tp_r)^3+H2657*(1-MIN(tp_g/tp_roe,0.8))/(1+tp_r)^4+I2657*(1-MIN(tp_g/tp_roe,0.8))/(1+tp_r)^5+J2657*(1-MIN(tp_g/tp_roe,0.8))/(1+tp_r)^6+J2657*(1-MIN(tp_g/tp_roe,0.8))*(1+tp_g)/(tp_r-tp_g)/(1+tp_r)^6)+tp_wB*MAX(0,E2698*(1-MIN(tp_g/tp_roe,0.8))/(1+tp_r)^1+F2698*(1-MIN(tp_g/tp_roe,0.8))/(1+tp_r)^2+G2698*(1-MIN(tp_g/tp_roe,0.8))/(1+tp_r)^3+H2698*(1-MIN(tp_g/tp_roe,0.8))/(1+tp_r)^4+I2698*(1-MIN(tp_g/tp_roe,0.8))/(1+tp_r)^5+J2698*(1-MIN(tp_g/tp_roe,0.8))/(1+tp_r)^6+J2698*(1-MIN(tp_g/tp_roe,0.8))*(1+tp_g)/(tp_r-tp_g)/(1+tp_r)^6)+tp_wC*MAX(0,E2739*(1-MIN(tp_g/tp_roe,0.8))/(1+tp_r)^1+F2739*(1-MIN(tp_g/tp_roe,0.8))/(1+tp_r)^2+G2739*(1-MIN(tp_g/tp_roe,0.8))/(1+tp_r)^3+H2739*(1-MIN(tp_g/tp_roe,0.8))/(1+tp_r)^4+I2739*(1-MIN(tp_g/tp_roe,0.8))/(1+tp_r)^5+J2739*(1-MIN(tp_g/tp_roe,0.8))/(1+tp_r)^6+J2739*(1-MIN(tp_g/tp_roe,0.8))*(1+tp_g)/(tp_r-tp_g)/(1+tp_r)^6))*(1+tp_r) -> 79.319647 | H26: =Val!$B$33*(tp_wA*(2/12*E2657+10/12*F2657)+tp_wB*(2/12*E2698+10/12*F2698)+tp_wC*(2/12*E2739+10/12*F2739))*rm_factor -> 176.41522 | I26: =tp_w_dcf*G26+(1-tp_w_dcf)*H26 -> 127.86743 | J26: =I26/I$4-1 -> 0.010121218
A27: 折現率 +1pt | B27: r 11% | C27: tp_r | D27: =PL!E96 -> 8.5291201 | E27: =PL!F96 -> 9.2172642 | F27: =E27/E$4-1 -> 0 | G27: =(tp_wA*MAX(0,PL!E96*(1-MIN(tp_g/tp_roe,0.8))/(1+(tp_r+0.01))^1+PL!F96*(1-MIN(tp_g/tp_roe,0.8))/(1+(tp_r+0.01))^2+PL!G96*(1-MIN(tp_g/tp_roe,0.8))/(1+(tp_r+0.01))^3+PL!H96*(1-MIN(tp_g/tp_roe,0.8))/(1+(tp_r+0.01))^4+PL!I96*(1-MIN(tp_g/tp_roe,0.8))/(1+(tp_r+0.01))^5+PL!J96*(1-MIN(tp_g/tp_roe,0.8))/(1+(tp_r+0.01))^6+PL!J96*(1-MIN(tp_g/tp_roe,0.8))*(1+tp_g)/((tp_r+0.01)-tp_g)/(1+(tp_r+0.01))^6)+tp_wB*MAX(0,PL!E137*(1-MIN(tp_g/tp_roe,0.8))/(1+(tp_r+0.01))^1+PL!F137*(1-MIN(tp_g/tp_roe,0.8))/(1+(tp_r+0.01))^2+PL!G137*(1-MIN(tp_g/tp_roe,0.8))/(1+(tp_r+0.01))^3+PL!H137*(1-MIN(tp_g/tp_roe,0.8))/(1+(tp_r+0.01))^4+PL!I137*(1-MIN(tp_g/tp_roe,0.8))/(1+(tp_r+0.01))^5+PL!J137*(1-MIN(tp_g/tp_roe,0.8))/(1+(tp_r+0.01))^6+PL!J137*(1-MIN(tp_g/tp_roe,0.8))*(1+tp_g)/((tp_r+0.01)-tp_g)/(1+(tp_r+0.01))^6)+tp_wC*MAX(0,PL!E178*(1-MIN(tp_g/tp_roe,0.8))/(1+(tp_r+0.01))^1+PL!F178*(1-MIN(tp_g/tp_roe,0.8))/(1+(tp_r+0.01))^2+PL!G178*(1-MIN(tp_g/tp_roe,0.8))/(1+(tp_r+0.01))^3+PL!H178*(1-MIN(tp_g/tp_roe,0.8))/(1+(tp_r+0.01))^4+PL!I178*(1-MIN(tp_g/tp_roe,0.8))/(1+(tp_r+0.01))^5+PL!J178*(1-MIN(tp_g/tp_roe,0.8))/(1+(tp_r+0.01))^6+PL!J178*(1-MIN(tp_g/tp_roe,0.8))*(1+tp_g)/((tp_r+0.01)-tp_g)/(1+(tp_r+0.01))^6))*(1+(tp_r+0.01)) -> 67.093713 | H27: =Val!$B$33*(tp_wA*(2/12*PL!E96+10/12*PL!F96)+tp_wB*(2/12*PL!E137+10/12*PL!F137)+tp_wC*(2/12*PL!E178+10/12*PL!F178))*rm_factor -> 175.68836 | I27: =tp_w_dcf*G27+(1-tp_w_dcf)*H27 -> 121.39103 | J27: =I27/I$4-1 -> -0.041040745
A28: 折現率 −1pt | B28: r 9% | C28: tp_r | D28: =PL!E96 -> 8.5291201 | E28: =PL!F96 -> 9.2172642 | F28: =E28/E$4-1 -> 0 | G28: =(tp_wA*MAX(0,PL!E96*(1-MIN(tp_g/tp_roe,0.8))/(1+(tp_r-0.01))^1+PL!F96*(1-MIN(tp_g/tp_roe,0.8))/(1+(tp_r-0.01))^2+PL!G96*(1-MIN(tp_g/tp_roe,0.8))/(1+(tp_r-0.01))^3+PL!H96*(1-MIN(tp_g/tp_roe,0.8))/(1+(tp_r-0.01))^4+PL!I96*(1-MIN(tp_g/tp_roe,0.8))/(1+(tp_r-0.01))^5+PL!J96*(1-MIN(tp_g/tp_roe,0.8))/(1+(tp_r-0.01))^6+PL!J96*(1-MIN(tp_g/tp_roe,0.8))*(1+tp_g)/((tp_r-0.01)-tp_g)/(1+(tp_r-0.01))^6)+tp_wB*MAX(0,PL!E137*(1-MIN(tp_g/tp_roe,0.8))/(1+(tp_r-0.01))^1+PL!F137*(1-MIN(tp_g/tp_roe,0.8))/(1+(tp_r-0.01))^2+PL!G137*(1-MIN(tp_g/tp_roe,0.8))/(1+(tp_r-0.01))^3+PL!H137*(1-MIN(tp_g/tp_roe,0.8))/(1+(tp_r-0.01))^4+PL!I137*(1-MIN(tp_g/tp_roe,0.8))/(1+(tp_r-0.01))^5+PL!J137*(1-MIN(tp_g/tp_roe,0.8))/(1+(tp_r-0.01))^6+PL!J137*(1-MIN(tp_g/tp_roe,0.8))*(1+tp_g)/((tp_r-0.01)-tp_g)/(1+(tp_r-0.01))^6)+tp_wC*MAX(0,PL!E178*(1-MIN(tp_g/tp_roe,0.8))/(1+(tp_r-0.01))^1+PL!F178*(1-MIN(tp_g/tp_roe,0.8))/(1+(tp_r-0.01))^2+PL!G178*(1-MIN(tp_g/tp_roe,0.8))/(1+(tp_r-0.01))^3+PL!H178*(1-MIN(tp_g/tp_roe,0.8))/(1+(tp_r-0.01))^4+PL!I178*(1-MIN(tp_g/tp_roe,0.8))/(1+(tp_r-0.01))^5+PL!J178*(1-MIN(tp_g/tp_roe,0.8))/(1+(tp_r-0.01))^6+PL!J178*(1-MIN(tp_g/tp_roe,0.8))*(1+tp_g)/((tp_r-0.01)-tp_g)/(1+(tp_r-0.01))^6))*(1+(tp_r-0.01)) -> 92.029651 | H28: =Val!$B$33*(tp_wA*(2/12*PL!E96+10/12*PL!F96)+tp_wB*(2/12*PL!E137+10/12*PL!F137)+tp_wC*(2/12*PL!E178+10/12*PL!F178))*rm_factor -> 175.68836 | I28: =tp_w_dcf*G28+(1-tp_w_dcf)*H28 -> 133.859 | J28: =I28/I$4-1 -> 0.057453138
A29: 長期成長 +1pt | B29: g 5% | C29: tp_g | D29: =PL!E96 -> 8.5291201 | E29: =PL!F96 -> 9.2172642 | F29: =E29/E$4-1 -> 0 | G29: =(tp_wA*MAX(0,PL!E96*(1-MIN((tp_g+0.01)/tp_roe,0.8))/(1+tp_r)^1+PL!F96*(1-MIN((tp_g+0.01)/tp_roe,0.8))/(1+tp_r)^2+PL!G96*(1-MIN((tp_g+0.01)/tp_roe,0.8))/(1+tp_r)^3+PL!H96*(1-MIN((tp_g+0.01)/tp_roe,0.8))/(1+tp_r)^4+PL!I96*(1-MIN((tp_g+0.01)/tp_roe,0.8))/(1+tp_r)^5+PL!J96*(1-MIN((tp_g+0.01)/tp_roe,0.8))/(1+tp_r)^6+PL!J96*(1-MIN((tp_g+0.01)/tp_roe,0.8))*(1+(tp_g+0.01))/(tp_r-(tp_g+0.01))/(1+tp_r)^6)+tp_wB*MAX(0,PL!E137*(1-MIN((tp_g+0.01)/tp_roe,0.8))/(1+tp_r)^1+PL!F137*(1-MIN((tp_g+0.01)/tp_roe,0.8))/(1+tp_r)^2+PL!G137*(1-MIN((tp_g+0.01)/tp_roe,0.8))/(1+tp_r)^3+PL!H137*(1-MIN((tp_g+0.01)/tp_roe,0.8))/(1+tp_r)^4+PL!I137*(1-MIN((tp_g+0.01)/tp_roe,0.8))/(1+tp_r)^5+PL!J137*(1-MIN((tp_g+0.01)/tp_roe,0.8))/(1+tp_r)^6+PL!J137*(1-MIN((tp_g+0.01)/tp_roe,0.8))*(1+(tp_g+0.01))/(tp_r-(tp_g+0.01))/(1+tp_r)^6)+tp_wC*MAX(0,PL!E178*(1-MIN((tp_g+0.01)/tp_roe,0.8))/(1+tp_r)^1+PL!F178*(1-MIN((tp_g+0.01)/tp_roe,0.8))/(1+tp_r)^2+PL!G178*(1-MIN((tp_g+0.01)/tp_roe,0.8))/(1+tp_r)^3+PL!H178*(1-MIN((tp_g+0.01)/tp_roe,0.8))/(1+tp_r)^4+PL!I178*(1-MIN((tp_g+0.01)/tp_roe,0.8))/(1+tp_r)^5+PL!J178*(1-MIN((tp_g+0.01)/tp_roe,0.8))/(1+tp_r)^6+PL!J178*(1-MIN((tp_g+0.01)/tp_roe,0.8))*(1+(tp_g+0.01))/(tp_r-(tp_g+0.01))/(1+tp_r)^6))*(1+tp_r) -> 79.099911 | H29: =Val!$B$33*(tp_wA*(2/12*PL!E96+10/12*PL!F96)+tp_wB*(2/12*PL!E137+10/12*PL!F137)+tp_wC*(2/12*PL!E178+10/12*PL!F178))*rm_factor -> 175.68836 | I29: =tp_w_dcf*G29+(1-tp_w_dcf)*H29 -> 127.39413 | J29: =I29/I$4-1 -> 0.0063822563
A30: 長期成長 −1pt | B30: g 3% | C30: tp_g | D30: =PL!E96 -> 8.5291201 | E30: =PL!F96 -> 9.2172642 | F30: =E30/E$4-1 -> 0 | G30: =(tp_wA*MAX(0,PL!E96*(1-MIN((tp_g-0.01)/tp_roe,0.8))/(1+tp_r)^1+PL!F96*(1-MIN((tp_g-0.01)/tp_roe,0.8))/(1+tp_r)^2+PL!G96*(1-MIN((tp_g-0.01)/tp_roe,0.8))/(1+tp_r)^3+PL!H96*(1-MIN((tp_g-0.01)/tp_roe,0.8))/(1+tp_r)^4+PL!I96*(1-MIN((tp_g-0.01)/tp_roe,0.8))/(1+tp_r)^5+PL!J96*(1-MIN((tp_g-0.01)/tp_roe,0.8))/(1+tp_r)^6+PL!J96*(1-MIN((tp_g-0.01)/tp_roe,0.8))*(1+(tp_g-0.01))/(tp_r-(tp_g-0.01))/(1+tp_r)^6)+tp_wB*MAX(0,PL!E137*(1-MIN((tp_g-0.01)/tp_roe,0.8))/(1+tp_r)^1+PL!F137*(1-MIN((tp_g-0.01)/tp_roe,0.8))/(1+tp_r)^2+PL!G137*(1-MIN((tp_g-0.01)/tp_roe,0.8))/(1+tp_r)^3+PL!H137*(1-MIN((tp_g-0.01)/tp_roe,0.8))/(1+tp_r)^4+PL!I137*(1-MIN((tp_g-0.01)/tp_roe,0.8))/(1+tp_r)^5+PL!J137*(1-MIN((tp_g-0.01)/tp_roe,0.8))/(1+tp_r)^6+PL!J137*(1-MIN((tp_g-0.01)/tp_roe,0.8))*(1+(tp_g-0.01))/(tp_r-(tp_g-0.01))/(1+tp_r)^6)+tp_wC*MAX(0,PL!E178*(1-MIN((tp_g-0.01)/tp_roe,0.8))/(1+tp_r)^1+PL!F178*(1-MIN((tp_g-0.01)/tp_roe,0.8))/(1+tp_r)^2+PL!G178*(1-MIN((tp_g-0.01)/tp_roe,0.8))/(1+tp_r)^3+PL!H178*(1-MIN((tp_g-0.01)/tp_roe,0.8))/(1+tp_r)^4+PL!I178*(1-MIN((tp_g-0.01)/tp_roe,0.8))/(1+tp_r)^5+PL!J178*(1-MIN((tp_g-0.01)/tp_roe,0.8))/(1+tp_r)^6+PL!J178*(1-MIN((tp_g-0.01)/tp_roe,0.8))*(1+(tp_g-0.01))/(tp_r-(tp_g-0.01))/(1+tp_r)^6))*(1+tp_r) -> 76.951762 | H30: =Val!$B$33*(tp_wA*(2/12*PL!E96+10/12*PL!F96)+tp_wB*(2/12*PL!E137+10/12*PL!F137)+tp_wC*(2/12*PL!E178+10/12*PL!F178))*rm_factor -> 175.68836 | I30: =tp_w_dcf*G30+(1-tp_w_dcf)*H30 -> 126.32006 | J30: =I30/I$4-1 -> -0.0021026654
A31: DCF 權重 0.3 | B31: Comparable 0.7 | C31: tp_w_dcf | D31: =PL!E96 -> 8.5291201 | E31: =PL!F96 -> 9.2172642 | F31: =E31/E$4-1 -> 0 | G31: =(tp_wA*MAX(0,PL!E96*(1-MIN(tp_g/tp_roe,0.8))/(1+tp_r)^1+PL!F96*(1-MIN(tp_g/tp_roe,0.8))/(1+tp_r)^2+PL!G96*(1-MIN(tp_g/tp_roe,0.8))/(1+tp_r)^3+PL!H96*(1-MIN(tp_g/tp_roe,0.8))/(1+tp_r)^4+PL!I96*(1-MIN(tp_g/tp_roe,0.8))/(1+tp_r)^5+PL!J96*(1-MIN(tp_g/tp_roe,0.8))/(1+tp_r)^6+PL!J96*(1-MIN(tp_g/tp_roe,0.8))*(1+tp_g)/(tp_r-tp_g)/(1+tp_r)^6)+tp_wB*MAX(0,PL!E137*(1-MIN(tp_g/tp_roe,0.8))/(1+tp_r)^1+PL!F137*(1-MIN(tp_g/tp_roe,0.8))/(1+tp_r)^2+PL!G137*(1-MIN(tp_g/tp_roe,0.8))/(1+tp_r)^3+PL!H137*(1-MIN(tp_g/tp_roe,0.8))/(1+tp_r)^4+PL!I137*(1-MIN(tp_g/tp_roe,0.8))/(1+tp_r)^5+PL!J137*(1-MIN(tp_g/tp_roe,0.8))/(1+tp_r)^6+PL!J137*(1-MIN(tp_g/tp_roe,0.8))*(1+tp_g)/(tp_r-tp_g)/(1+tp_r)^6)+tp_wC*MAX(0,PL!E178*(1-MIN(tp_g/tp_roe,0.8))/(1+tp_r)^1+PL!F178*(1-MIN(tp_g/tp_roe,0.8))/(1+tp_r)^2+PL!G178*(1-MIN(tp_g/tp_roe,0.8))/(1+tp_r)^3+PL!H178*(1-MIN(tp_g/tp_roe,0.8))/(1+tp_r)^4+PL!I178*(1-MIN(tp_g/tp_roe,0.8))/(1+tp_r)^5+PL!J178*(1-MIN(tp_g/tp_roe,0.8))/(1+tp_r)^6+PL!J178*(1-MIN(tp_g/tp_roe,0.8))*(1+tp_g)/(tp_r-tp_g)/(1+tp_r)^6))*(1+tp_r) -> 77.484099 | H31: =Val!$B$33*(tp_wA*(2/12*PL!E96+10/12*PL!F96)+tp_wB*(2/12*PL!E137+10/12*PL!F137)+tp_wC*(2/12*PL!E178+10/12*PL!F178))*rm_factor -> 175.68836 | I31: =0.3*G31+(1-0.3)*H31 -> 146.22708 | J31: =I31/I$4-1 -> 0.15515788
A32: DCF 權重 0.7 | B32: Comparable 0.3 | C32: tp_w_dcf | D32: =PL!E96 -> 8.5291201 | E32: =PL!F96 -> 9.2172642 | F32: =E32/E$4-1 -> 0 | G32: =(tp_wA*MAX(0,PL!E96*(1-MIN(tp_g/tp_roe,0.8))/(1+tp_r)^1+PL!F96*(1-MIN(tp_g/tp_roe,0.8))/(1+tp_r)^2+PL!G96*(1-MIN(tp_g/tp_roe,0.8))/(1+tp_r)^3+PL!H96*(1-MIN(tp_g/tp_roe,0.8))/(1+tp_r)^4+PL!I96*(1-MIN(tp_g/tp_roe,0.8))/(1+tp_r)^5+PL!J96*(1-MIN(tp_g/tp_roe,0.8))/(1+tp_r)^6+PL!J96*(1-MIN(tp_g/tp_roe,0.8))*(1+tp_g)/(tp_r-tp_g)/(1+tp_r)^6)+tp_wB*MAX(0,PL!E137*(1-MIN(tp_g/tp_roe,0.8))/(1+tp_r)^1+PL!F137*(1-MIN(tp_g/tp_roe,0.8))/(1+tp_r)^2+PL!G137*(1-MIN(tp_g/tp_roe,0.8))/(1+tp_r)^3+PL!H137*(1-MIN(tp_g/tp_roe,0.8))/(1+tp_r)^4+PL!I137*(1-MIN(tp_g/tp_roe,0.8))/(1+tp_r)^5+PL!J137*(1-MIN(tp_g/tp_roe,0.8))/(1+tp_r)^6+PL!J137*(1-MIN(tp_g/tp_roe,0.8))*(1+tp_g)/(tp_r-tp_g)/(1+tp_r)^6)+tp_wC*MAX(0,PL!E178*(1-MIN(tp_g/tp_roe,0.8))/(1+tp_r)^1+PL!F178*(1-MIN(tp_g/tp_roe,0.8))/(1+tp_r)^2+PL!G178*(1-MIN(tp_g/tp_roe,0.8))/(1+tp_r)^3+PL!H178*(1-MIN(tp_g/tp_roe,0.8))/(1+tp_r)^4+PL!I178*(1-MIN(tp_g/tp_roe,0.8))/(1+tp_r)^5+PL!J178*(1-MIN(tp_g/tp_roe,0.8))/(1+tp_r)^6+PL!J178*(1-MIN(tp_g/tp_roe,0.8))*(1+tp_g)/(tp_r-tp_g)/(1+tp_r)^6))*(1+tp_r) -> 77.484099 | H32: =Val!$B$33*(tp_wA*(2/12*PL!E96+10/12*PL!F96)+tp_wB*(2/12*PL!E137+10/12*PL!F137)+tp_wC*(2/12*PL!E178+10/12*PL!F178))*rm_factor -> 175.68836 | I32: =0.7*G32+(1-0.7)*H32 -> 106.94538 | J32: =I32/I$4-1 -> -0.15515788
A34: 讀法：8 吋稼動率與售價最敏感；VSMC 的產能與售價影響 FY2028 起的 EPS，但因非控制權益 40% 與量產初期毛利率低，對加權目標價的影響小於 8 吋售價。
A36: 敏感度「逐案推導區塊」：以下每個案例三個情境各一個完整推導區塊（不是案例列）
A38: 案例區塊：匯率：低（情境 A）
A39: 項目 | B39: 單位 | C39: FY2025A | D39: FY2026（錨點） | E39: FY2027 | F39: FY2028 | G39: FY2029 | H39: FY2030（收斂） | I39: FY2031（收斂） | J39: FY2032（收斂） | K39: 說明
A40: A. 8 吋晶圓：產能 × 稼動率 × 平均售價（D 欄＝FY2026 校準年）
A41: 產能（8 吋） | B41: 千片 | D41: =cap_26 -> 3306 | E41: =D41*(1+capg27)*cap_adj -> 3306 | F41: =E41*(1+capg28) -> 3306 | G41: =F41*(1+capg29) -> 3306
A42: 平均稼動率 | B42: % | D42: =a26_ship/cap_26 -> 0.8725 | E42: =MIN(0.98,ut27_A+ut_adj) -> 0.95 | F42: =MIN(0.98,ut28_A+ut_adj) -> 0.94 | G42: =MIN(0.98,ut29_A+ut_adj) -> 0.93
A43: 晶圓出貨（8 吋） | B43: 千片 | D43: =D41*D42 -> 2884.485 | E43: =E41*E42 -> 3140.7 | F43: =F41*F42 -> 3107.64 | G43: =G41*G42 -> 3074.58
A44: 平均售價（8 吋晶圓） | B44: US$/片 | D44: =asp_26 -> 643.46941 | E44: =D44*(1+asp27_A)*(1+asp_adj) -> 682.07757 | F44: =E44*(1+asp28_A) -> 695.71912 | G44: =F44*(1+asp29_A) -> 702.67631
A45: 平均售價年增（美元） | B45: % | E45: =E44/D44-1 -> 0.06 | F45: =F44/E44-1 -> 0.02 | G45: =G44/F44-1 -> 0.01
A46: 匯率 | B46: NT$/US$ | D46: =fx_26 -> 31.6 | E46: =fx_lo -> 30.5 | F46: =fx_lo -> 30.5 | G46: =fx_lo -> 30.5
A47: 8 吋晶圓營收 | B47: NT$B | D47: =D43*D44*D46/1000000 -> 58.65206 | E47: =E43*E44*E46/1000000 -> 65.337131 | F47: =F43*F44*F46/1000000 -> 65.942359 | G47: =G43*G44*G46/1000000 -> 65.893253
A48: B. VSMC（新加坡 12 吋廠；FY2027 第一季量產）
A49: VSMC 產能（12 吋） | B49: 千片 | D49: =0 -> 0 | E49: =vcap27*vcap_adj -> 144 | F49: =vcap28*vcap_adj -> 360 | G49: =vcap29*vcap_adj -> 504
A50: VSMC 稼動率 | B50: % | E50: =vut_A -> 0.9 | F50: =vut_A -> 0.9 | G50: =vut_A -> 0.9
A51: VSMC 出貨（12 吋） | B51: 千片 | D51: =0 -> 0 | E51: =E49*E50 -> 129.6 | F51: =F49*F50 -> 324 | G51: =G49*G50 -> 453.6
A52: VSMC 營收（12 吋） | B52: NT$B | D52: =0 -> 0 | E52: =E51*vasp*E46/1000000 -> 7.11504 | F52: =F51*vasp*F46/1000000 -> 17.7876 | G52: =G51*vasp*G46/1000000 -> 24.90264
A53: 營收 | B53: NT$B | C53: =a25_rev -> 48.591 | D53: =D47+D52 -> 58.65206 | E53: =E47+E52 -> 72.452171 | F53: =F47+F52 -> 83.729959 | G53: =G47+G52 -> 90.795893 | H53: =G53*(1+H56) -> 97.719961 | I53: =H53*(1+I56) -> 104.37761 | J53: =I53*(1+J56) -> 110.64026 | K53: FY2030 起為收斂法：營收年增由 FY2029 線性收斂到 fade_g、淨利率收斂到 fade_m（FY2032 達到），非驅動因子推導
A54: 12 吋（VSMC）÷ 營收 | B54: % | D54: =D52/D53 -> 0 | E54: =E52/E53 -> 0.098203268 | F54: =F52/F53 -> 0.21244009 | G54: =G52/G53 -> 0.27427055
A55: AI 相關 ÷ 營收（記憶列，不進營收加總） | B55: % | D55: =ai_sh26 -> 0.1 | E55: =ai_sh27_A -> 0.25 | F55: =ai_sh27_A -> 0.25 | G55: =ai_sh27_A -> 0.25
A56: 營收年增 | B56: % | D56: =D53/C53-1 -> 0.20705604 | E56: =E53/D53-1 -> 0.23528775 | F56: =F53/E53-1 -> 0.15565839 | G56: =G53/F53-1 -> 0.084389555 | H56: =$G56+(fade_gA-$G56)*1/3 -> 0.076259703 | I56: =$G56+(fade_gA-$G56)*2/3 -> 0.068129852 | J56: =$G56+(fade_gA-$G56)*3/3 -> 0.06
A57: C. 成本與損益
A58: 銷貨成本內折舊 | B58: NT$B | D58: =da_tot26*da_sh -> 8.658 | E58: =D58*(1+dag_27+dag_adj) -> 8.91774 | F58: =E58*(1+dag_28+dag_adj) -> 9.0960948 | G58: =F58*(1+dag_29+dag_adj) -> 9.0960948
A59: 每片現金成本（FY2026 殘差，之後年增 cc_g） | B59: NT$K/片 | D59: =(D47-a26_gp-D58)/D43*1000 -> 10.733992 | E59: =D59*(1+cc_g) -> 10.948672 | F59: =E59*(1+cc_g) -> 11.167645 | G59: =F59*(1+cc_g) -> 11.390998 | K59: Derived：讓 FY2026 毛利等於錨點；含原物料、人力、電力等變動與固定現金成本
A60: 現金成本合計（每片 × 出貨） | B60: NT$B | D60: =D59*D43/1000 -> 30.962039 | E60: =E59*E43/1000 -> 34.386493 | F60: =F59*F43/1000 -> 34.705021 | G60: =G59*G43/1000 -> 35.022535
A61: VSMC 毛利率 | B61: % | E61: =vgm27_A -> 0.05 | F61: =vgm28_A -> 0.2 | G61: =vgm29_A -> 0.25
A62: VSMC 毛利 | B62: NT$B | D62: =0 -> 0 | E62: =E52*E61 -> 0.355752 | F62: =F52*F61 -> 3.55752 | G62: =G52*G61 -> 6.22566
A63: 毛利 | B63: NT$B | C63: =a25_gp -> 13.654 | D63: =D47-D58-D60+D62 -> 19.032021 | E63: =E47-E58-E60+E62 -> 22.38865 | F63: =F47-F58-F60+F62 -> 25.698764 | G63: =G47-G58-G60+G62 -> 28.000284
A64: 毛利率 | B64: % | C64: =C63/C53 -> 0.28099854 | D64: =D63/D53 -> 0.32449025 | E64: =E63/E53 -> 0.30901282 | F64: =F63/F53 -> 0.30692435 | G64: =G63/G53 -> 0.30838712
A65: 營業費用 | B65: NT$B | C65: =a25_opx -> 5.881 | D65: =a26_opx -> 6.824187 | E65: =D65*(1+MAX(g_opx_min,phi*E56)) -> 7.6270108 | F65: =E65*(1+MAX(g_opx_min,phi*F56)) -> 8.2206149 | G65: =F65*(1+MAX(g_opx_min,phi*G56)) -> 8.5674819
A66: 營業利益 | B66: NT$B | C66: =C63-C65 -> 7.773 | D66: =D63-D65 -> 12.207834 | E66: =E63-E65 -> 14.761639 | F66: =F63-F65 -> 17.478149 | G66: =G63-G65 -> 19.432802
A67: 營業利益率 | B67: % | C67: =C66/C53 -> 0.1599679 | D67: =D66/D53 -> 0.20813991 | E67: =E66/E53 -> 0.20374323 | F67: =F66/F53 -> 0.20874427 | G67: =G66/G53 -> 0.21402732
A68: 營業外淨額 | B68: NT$B | C68: =a25_nonop -> 1.479 | D68: =a26_nonop -> 2.1095083 | E68: =nonop_f -> 1.5 | F68: =nonop_f -> 1.5 | G68: =nonop_f -> 1.5
A69: 稅前利益 | B69: NT$B | C69: =C66+C68 -> 9.252 | D69: =D66+D68 -> 14.317343 | E69: =E66+E68 -> 16.261639 | F69: =F66+F68 -> 18.978149 | G69: =G66+G68 -> 20.932802
A70: 所得稅 | B70: NT$B | C70: =a25_tax -> 1.344 | D70: =a26_tax -> 2.0798215 | E70: =E69*tax -> 2.4392459 | F70: =F69*tax -> 2.8467223 | G70: =G69*tax -> 3.1399203
A71: 非控制權益（NXP 占 VSMC 40%） | B71: NT$B | C71: =a25_mi -> 0 | D71: =a26_mi -> 0 | E71: =vmi*E62*(1-tax) -> 0.12095568 | F71: =vmi*F62*(1-tax) -> 1.2095568 | G71: =vmi*G62*(1-tax) -> 2.1167244 | K71: VSMC 虧損時為負值（母公司淨利少扣）
A72: 歸屬母公司淨利 | B72: NT$B | C72: =C69-C70-C71 -> 7.908 | D72: =D69-D70-D71 -> 12.237521 | E72: =E69-E70-E71 -> 13.701438 | F72: =F69-F70-F71 -> 14.92187 | G72: =G69-G70-G71 -> 15.676157 | H72: =H53*H76 -> 16.871616 | I72: =I53*I76 -> 18.021077 | J72: =J53*J76 -> 19.102342
A73: 加權股數 | B73: 十億股 | C73: =a25_sh -> 1.8739336 | D73: =a26_sh -> 1.9061359 | E73: =q_sh*(1+sh_g) -> 1.9070513 | F73: =E73*(1+sh_g) -> 1.9070513 | G73: =F73*(1+sh_g) -> 1.9070513 | H73: =G73*(1+sh_g) -> 1.9070513 | I73: =H73*(1+sh_g) -> 1.9070513 | J73: =I73*(1+sh_g) -> 1.9070513
A74: EPS（基本） | B74: NT$ | C74: =C72/C73 -> 4.22 | D74: =D72/D73 -> 6.4200675 | E74: =E72/E73 -> 7.1846194 | F74: =F72/F73 -> 7.8245771 | G74: =G72/G73 -> 8.2201026 | H74: =H72/H73 -> 8.8469651 | I74: =I72/I73 -> 9.4497076 | J74: =J72/J73 -> 10.01669
A75: EPS 年增 | B75: % | D75: =D74/C74-1 -> 0.521343 | E75: =E74/D74-1 -> 0.11908783 | F75: =F74/E74-1 -> 0.089073293 | G75: =G74/F74-1 -> 0.050549122 | H75: =H74/G74-1 -> 0.076259703 | I75: =I74/H74-1 -> 0.068129852 | J75: =J74/I74-1 -> 0.06
A76: 淨利率（歸屬母公司淨利 ÷ 營收） | B76: % | C76: =C72/C53 -> 0.16274619 | D76: =D72/D53 -> 0.20864606 | E76: =E72/E53 -> 0.1891101 | F76: =F72/F53 -> 0.17821422 | G76: =G72/G53 -> 0.17265271 | H76: =$G76+($G$76*1-$G76)*1/3 -> 0.17265271 | I76: =$G76+($G$76*1-$G76)*2/3 -> 0.17265271 | J76: =$G76+($G$76*1-$G76)*3/3 -> 0.17265271
A79: 案例區塊：匯率：低（情境 B）
A80: 項目 | B80: 單位 | C80: FY2025A | D80: FY2026（錨點） | E80: FY2027 | F80: FY2028 | G80: FY2029 | H80: FY2030（收斂） | I80: FY2031（收斂） | J80: FY2032（收斂） | K80: 說明
A81: A. 8 吋晶圓：產能 × 稼動率 × 平均售價（D 欄＝FY2026 校準年）
A82: 產能（8 吋） | B82: 千片 | D82: =cap_26 -> 3306 | E82: =D82*(1+capg27)*cap_adj -> 3306 | F82: =E82*(1+capg28) -> 3306 | G82: =F82*(1+capg29) -> 3306
A83: 平均稼動率 | B83: % | D83: =a26_ship/cap_26 -> 0.8725 | E83: =MIN(0.98,ut27_B+ut_adj) -> 0.9 | F83: =MIN(0.98,ut28_B+ut_adj) -> 0.86 | G83: =MIN(0.98,ut29_B+ut_adj) -> 0.87
A84: 晶圓出貨（8 吋） | B84: 千片 | D84: =D82*D83 -> 2884.485 | E84: =E82*E83 -> 2975.4 | F84: =F82*F83 -> 2843.16 | G84: =G82*G83 -> 2876.22
A85: 平均售價（8 吋晶圓） | B85: US$/片 | D85: =asp_26 -> 643.46941 | E85: =D85*(1+asp27_B)*(1+asp_adj) -> 662.77349 | F85: =E85*(1+asp28_B) -> 662.77349 | G85: =F85*(1+asp29_B) -> 662.77349
A86: 平均售價年增（美元） | B86: % | E86: =E85/D85-1 -> 0.03 | F86: =F85/E85-1 -> 0 | G86: =G85/F85-1 -> 0
A87: 匯率 | B87: NT$/US$ | D87: =fx_26 -> 31.6 | E87: =fx_lo -> 30.5 | F87: =fx_lo -> 30.5 | G87: =fx_lo -> 30.5
A88: 8 吋晶圓營收 | B88: NT$B | D88: =D84*D85*D87/1000000 -> 58.65206 | E88: =E84*E85*E87/1000000 -> 60.146495 | F88: =F84*F85*F87/1000000 -> 57.473318 | G88: =G84*G85*G87/1000000 -> 58.141612
A89: B. VSMC（新加坡 12 吋廠；FY2027 第一季量產）
A90: VSMC 產能（12 吋） | B90: 千片 | D90: =0 -> 0 | E90: =vcap27*vcap_adj -> 144 | F90: =vcap28*vcap_adj -> 360 | G90: =vcap29*vcap_adj -> 504
A91: VSMC 稼動率 | B91: % | E91: =vut_B -> 0.8 | F91: =vut_B -> 0.8 | G91: =vut_B -> 0.8
A92: VSMC 出貨（12 吋） | B92: 千片 | D92: =0 -> 0 | E92: =E90*E91 -> 115.2 | F92: =F90*F91 -> 288 | G92: =G90*G91 -> 403.2
A93: VSMC 營收（12 吋） | B93: NT$B | D93: =0 -> 0 | E93: =E92*vasp*E87/1000000 -> 6.32448 | F93: =F92*vasp*F87/1000000 -> 15.8112 | G93: =G92*vasp*G87/1000000 -> 22.13568
A94: 營收 | B94: NT$B | C94: =a25_rev -> 48.591 | D94: =D88+D93 -> 58.65206 | E94: =E88+E93 -> 66.470975 | F94: =F88+F93 -> 73.284518 | G94: =G88+G93 -> 80.277292 | H94: =G94*(1+H97) -> 86.454337 | I94: =H94*(1+I97) -> 91.509597 | J94: =I94*(1+J97) -> 95.169981 | K94: FY2030 起為收斂法：營收年增由 FY2029 線性收斂到 fade_g、淨利率收斂到 fade_m（FY2032 達到），非驅動因子推導
A95: 12 吋（VSMC）÷ 營收 | B95: % | D95: =D93/D94 -> 0 | E95: =E93/E94 -> 0.09514649 | F95: =F93/F94 -> 0.21575089 | G95: =G93/G94 -> 0.27574024
A96: AI 相關 ÷ 營收（記憶列，不進營收加總） | B96: % | D96: =ai_sh26 -> 0.1 | E96: =ai_sh27_B -> 0.2 | F96: =ai_sh27_B -> 0.2 | G96: =ai_sh27_B -> 0.2
A97: 營收年增 | B97: % | D97: =D94/C94-1 -> 0.20705604 | E97: =E94/D94-1 -> 0.13331015 | F97: =F94/E94-1 -> 0.10250402 | G97: =G94/F94-1 -> 0.095419532 | H97: =$G97+(fade_gB-$G97)*1/3 -> 0.076946355 | I97: =$G97+(fade_gB-$G97)*2/3 -> 0.058473177 | J97: =$G97+(fade_gB-$G97)*3/3 -> 0.04
A98: C. 成本與損益
A99: 銷貨成本內折舊 | B99: NT$B | D99: =da_tot26*da_sh -> 8.658 | E99: =D99*(1+dag_27+dag_adj) -> 8.91774 | F99: =E99*(1+dag_28+dag_adj) -> 9.0960948 | G99: =F99*(1+dag_29+dag_adj) -> 9.0960948
A100: 每片現金成本（FY2026 殘差，之後年增 cc_g） | B100: NT$K/片 | D100: =(D88-a26_gp-D99)/D84*1000 -> 10.733992 | E100: =D100*(1+cc_g) -> 10.948672 | F100: =E100*(1+cc_g) -> 11.167645 | G100: =F100*(1+cc_g) -> 11.390998 | K100: Derived：讓 FY2026 毛利等於錨點；含原物料、人力、電力等變動與固定現金成本
A101: 現金成本合計（每片 × 出貨） | B101: NT$B | D101: =D100*D84/1000 -> 30.962039 | E101: =E100*E84/1000 -> 32.576678 | F101: =F100*F84/1000 -> 31.751402 | G101: =G100*G84/1000 -> 32.763016
A102: VSMC 毛利率 | B102: % | E102: =vgm27_B -> -0.05 | F102: =vgm28_B -> 0.12 | G102: =vgm29_B -> 0.18
A103: VSMC 毛利 | B103: NT$B | D103: =0 -> 0 | E103: =E93*E102 -> -0.316224 | F103: =F93*F102 -> 1.897344 | G103: =G93*G102 -> 3.9844224
A104: 毛利 | B104: NT$B | C104: =a25_gp -> 13.654 | D104: =D88-D99-D101+D103 -> 19.032021 | E104: =E88-E99-E101+E103 -> 18.335853 | F104: =F88-F99-F101+F103 -> 18.523165 | G104: =G88-G99-G101+G103 -> 20.266923
A105: 毛利率 | B105: % | C105: =C104/C94 -> 0.28099854 | D105: =D104/D94 -> 0.32449025 | E105: =E104/E94 -> 0.27584751 | F105: =F104/F94 -> 0.25275686 | G105: =G104/G94 -> 0.25246147
...

Sheet Sources
A1: 來源（公司財報與法說內容部分為媒體轉述；券商、資料商、媒體皆為 Interested-party）
A2: 媒體：優分析 2026-08-04（2Q26 法說：營收、毛利率、營業利益率、EPS、3Q26 指引、AI 占比、產品組合） | B2: https://uanalyze.com.tw/articles/8378052767
A3: 媒體：科技新報 2026-05-05（1Q26：營收、毛利率、EPS、出貨與售價；2026 年 8 吋產能 330.6 萬片；VSMC 總投資 67 億美元、2029 年月產能 4.4 萬片） | B3: https://finance.technews.tw/2026/05/05/vis-2026-q1-financial-report/
A4: 媒體：科技新報 2026-02-03（4Q25：營收 125.94 億、毛利率 27.5%、EPS 0.93；FY2025 營業利益、淨利） | B4: https://technews.tw/2026/02/03/vis-2025-q4-financial-report/
A5: 媒體：NOWnews 2026-02-03（4Q25 法說：長約到期、價格堅挺、VSMC 時程） | B5: https://www.nownews.com/news/6782793
A6: 媒體：優分析 2026-02（2026 資本支出 600–700 億、折舊 96.2 億） | B6: https://uanalyze.com.tw/articles/8174247250
A7: 媒體：科技新報 2026-10-08（9 月營收 59.04 億、前 9 月 424.79 億） | B7: https://finance.technews.tw/2026/10/08/vis-5347-202609-financial-report/
A8: 媒體：工商時報 2026-08-06（法人目標價、FY2026–27 EPS、2Q 稼動率約 87%、AI 占比、12 吋占 2027 營收 12%、毛利率 35%） | B8: https://www.ctee.com.tw/news/20260806700216-430201
A9: 資料商：stockanalysis（股價、前瞻 P/E、共識、FY2021–25 損益、ROE、年度 P/E） | B9: https://stockanalysis.com/quote/tpex/5347/；https://stockanalysis.com/quote/tpex/5347/forecast/；https://stockanalysis.com/quote/tpex/5347/financials/；https://stockanalysis.com/quote/tpex/5347/financials/ratios/；https://stockanalysis.com/quote/tpex/5347/history/
A10: 資料商：stockanalysis 同業前瞻 P/E（2303、GFS、0981、TSEM） | B10: https://stockanalysis.com/quote/tpe/2303/；https://stockanalysis.com/stocks/gfs/；https://stockanalysis.com/quote/hkg/0981/；https://stockanalysis.com/stocks/tsem/
A11: 資料商：companiesmarketcap 年底 P/E | B11: https://companiesmarketcap.com/vanguard-international-semiconductor/pe-ratio/
A12: 行業層：Siliconomics 快照（匯率 fx_twd；本 repo，唯讀） | B12: siliconomics/data/CURRENT_SNAPSHOT；siliconomics/reader.py
A13: 待補（人工）：3Q26 財報與法說（2026-11-05）；出貨片數與售價絕對值、各季產能與稼動率（1Q26）；產品別比重（2Q26 以外各季）；VSMC 售價、毛利率、借款與補助；1Q、2Q26 稅前利益；FY2027 起共識；2016–2020 淨利率（十年平均）；Bloomberg 前瞻倍數；10-23 以後收盤價 | B13: 未找到
A14: SemiAnalysis | B14: 未使用
