Workbook

Sheet README
A1: Microsoft（MSFT）個股模型 v0.3.1 — 命題＋官方營收分部 → 損益表（2026-10-29；資料截至 FY27Q1〔2026-09-30〕；評價日 2026-09-30、目標價時點 2027-10-29）
A2: 工作表：README → In → Q → Thesis → Seg → PL → CF → Val → Recon → Sens → Sources。金額十億美元；財年 6 月結束（FY2027＝2026-07～2027-06）
A3: 命題：AI 能否同時在 Azure（算力）與 Microsoft 365（Copilot 應用）變現，撐住翻倍的資本支出。
A4: 核心問題：FY2029 的 AI 增量營業利益能否覆蓋 AI 資本支出的資金成本（AI 增量 ROIC 對 WACC），且自由現金流不需停止回購。
A5: ="① 命題答案（FY2029，基準情境 B）：讀法 2（主值；自用 AI 價值中性）AI 增量 ROIC "&TEXT(Thesis!H102,"0.0%")&"，讀法 1（自用 AI 只計成本）"&TEXT(Thesis!H103,"0.0%")&"，WACC "&TEXT(wacc,"0.0%")&"；對外 Azure AI 本身 "&TEXT(Thesis!H105,"0.0%")&"。讀法 1 下 AI 容量越大、目標價越低（自用算力只有成本）；讀法 2 下容量增加對目標價中性偏正（敏感度：MW 速度改 Epoch 可辨識站點 "&TEXT(Sens!D9,"+0.0;-0.0")&"、+20% "&TEXT(Sens!D10,"+0.0;-0.0")&"）。AI 折舊 FY2026 "&TEXT(Thesis!E95,"0.0")&" → FY2029 "&TEXT(Thesis!H95,"0.0")&" 十億美元，財報口徑營業利益率 FY2029 "&TEXT(PL!H76,"0.0%")&"（FY2026 "&TEXT(PL!E76,"0.0%")&"）。" -> ① 命題答案（FY2029，基準情境 B）：讀法 2（主值；自用 AI 價值中性）AI 增量 ROIC 8.6%，讀法 1（自用 AI 只計成本）1.0%，WACC 10.3%；對外 Azure AI 本身 13.1%。讀法 1 下 AI 容量越大、目標價越低（自用算力只有成本）；讀法 2 下容量增加對目標價中性偏正（敏感度：MW 速度改 Epoch 可辨識站點 -28.5、+20% +2.8）。AI 折舊 FY2026 16.3 → FY2029 89.1 十億美元，財報口徑營業利益率 FY2029 39.1%（FY2026 46.8%）。
A6: ="② 收支關卡：基準情境首年起五年（FY2027–FY2031）自由現金流扣股利合計 "&TEXT(CF!C5,"#,##0.0")&" 十億美元（樂觀 "&TEXT(CF!B5,"#,##0.0")&"、保守 "&TEXT(CF!D5,"#,##0.0")&"）；"&CF!C6&"。" -> ② 收支關卡：基準情境首年起五年（FY2027–FY2031）自由現金流扣股利合計 259.6 十億美元（樂觀 363.2、保守 137.9）；需要舉債 8.1 十億美元；回購較每年 22.3 的目標少 44.3 十億美元（2 年減少）。
A7: ="③ 評價：加權目標價 "&TEXT(Val!$B$36,"#,##0")&" 美元（讀法 2），較現價 "&TEXT(px,"#,##0.00")&" "&TEXT(Val!$B$40,"+0.0%;-0.0%")&"；DCF "&TEXT(Val!$B$14,"#,##0")&"、分部加總 "&TEXT(Val!$B$31,"#,##0")&"；讀法 1 目標價 "&TEXT(Val!$B$47,"#,##0")&"（"&Val!$B$49&"）；市場共識 "&TEXT(cons_tp,"#,##0")&"。WACC "&TEXT(wacc,"0.0%")&"（−1pt 時目標價 "&TEXT(Sens!C27,"#,##0")&"）；非 AI 各線改用 Microsoft 自身 NTM EV/EBITDA "&TEXT(m_own,"0.0")&"× 時目標價 "&TEXT(Sens!C94,"#,##0")&"。" -> ③ 評價：加權目標價 384 美元（讀法 2），較現價 531.01 -27.7%；DCF 324、分部加總 444；讀法 1 目標價 311（放空）；市場共識 605。WACC 10.3%（−1pt 時目標價 406）；非 AI 各線改用 Microsoft 自身 NTM EV/EBITDA 15.7× 時目標價 450。
A8: ="投資建議："&Val!$B$43&"（讀法 2 主值；上檔空間 "&TEXT(Val!$B$40,"+0.0%;-0.0%")&"；讀法 1："&Val!$B$49&"；五級固定規則：≥ +50% 強力買進、+25%～+50% 買進、−25%～+25% 中立、−50%～−25% 放空、≤ −50% 強力放空）" -> 投資建議：放空（讀法 2 主值；上檔空間 -27.7%；讀法 1：放空；五級固定規則：≥ +50% 強力買進、+25%～+50% 買進、−25%～+25% 中立、−50%～−25% 放空、≤ −50% 強力放空）
A9: ="收支關卡（地圖）：CF 頁「收支關卡：自由現金流扣股利（五年合計）」基準 "&TEXT(CF!C5,"#,##0.0")&" 十億美元（財報現金，不含影子效益）" -> 收支關卡（地圖）：CF 頁「收支關卡：自由現金流扣股利（五年合計）」基準 259.6 十億美元（財報現金，不含影子效益）
A11: 驅動 → 推導對照表（每頁輸入、推導量、因果方向）
A12: 頁 | B12: 輸入（In 頁鍵） | C12: 推導量 | D12: 因果方向 | E12: 基準值（FY2029，情境 B）
A13: Thesis | B13: pace、mw_ext_26、ext_sh、rent_ext_f | C13: 在役對外 AI MW、自有 AI MW（含自用） | D13: MW 越多 → Azure AI 營收↑、AI 資本支出與折舊↑ | E13: =Thesis!H60 -> 11429.605
A14: Thesis | B14: tk_hold_*、p_long、p_spot、ls_*（k） | C14: 每 MW 年收入（US$M/MW-年） | D14: k 越高 → Azure AI 營收與 EBITDA↑（三情境主要差異） | E14: =Thesis!H76 -> 12.735046
A15: Thesis | B15: tk_cxit_*、tk_cxfac、self_build、capex_floor27、life_it | C15: AI 資本支出、AI 折舊 | D15: 資本支出 → 折舊 → Agents and Infra 營業利益↓；→ 自由現金流↓ | E15: =Thesis!H95 -> 89.100091
A16: Seg | B16: cop_s26、cop_add_*、cop_px | C16: Copilot 營收（M365 cloud 子列） | D16: 座席 × 月費 → M365 cloud↑ | E16: =Seg!H38 -> 24
A17: Seg | B17: glt_*、n_conv | C17: 非命題產品線營收 | D17: 近一年年增收斂到長期值 | E17: =Seg!H56 -> 555.72683
A18: PL | B18: （FY2026 校準）、dm_seg | C18: Agents and Infra 核心利益率、分部營業利益 | D18: 核心利益率 ×（分部 − Azure AI）＋ Azure AI − AI 成本 − AI 折舊 | E18: =PL!H71 -> 196.76369
A19: PL | B19: internal_ai_reading、tax_f、oie_f | C19: 自用 AI 影子效益、淨利、EPS（評價口徑） | D19: 讀法 2：自用 MW × 持有成本（扣 Copilot）進評價口徑營業利益 | E19: =PL!H88 -> 27.37464
A20: CF | B20: sbc_r、wc27、cx_*、fl_pay_*、bb_target、dps_* | C20: 自由現金流、回購、舉債、股數 | D20: 自由現金流扣股利 → 回購（不足先減）→ 舉債 | E20: =CF!H62 -> 62.211875
A21: Val | B21: rf、beta、erp、kd、g_tv、m_*、al_*、w_* | C21: DCF、SOTP（AI 模組 DCF）、加權目標價 | D21: WACC↑ → DCF↓；倍數↑ → SOTP↑ | E21: =Val!$B$36 -> 384.10456
A23: 結果摘要（三情境）
A24: 項目 | B24: 情境 A（樂觀） | C24: 情境 B（基準） | D24: 情境 C（保守） | E24: 說明
A25: 營收 FY2029（US$B） | B25: =Seg!H29 -> 587.29479 | C25: =Seg!H56 -> 555.72683 | D25: =Seg!H83 -> 519.25825
A26: Azure AI 營收 FY2029 | B26: =Thesis!H25 -> 153.81672 | C26: =Thesis!H77 -> 128.19527 | D26: =Thesis!H129 -> 97.449538
A27: Copilot 營收 FY2029 | B27: =Seg!H11 -> 31.5 | C27: =Seg!H38 -> 24 | D27: =Seg!H65 -> 16.5
A28: 營業利益率 FY2029（財報口徑） | B28: =PL!H37 -> 0.41909125 | C28: =PL!H76 -> 0.39069071 | D28: =PL!H115 -> 0.35262622
A29: EPS FY2029（財報口徑，US$） | B29: =PL!H47 -> 26.005415 | C29: =PL!H86 -> 22.891665 | D29: =PL!H125 -> 19.240201
A30: EPS FY2029（評價口徑，US$） | B30: =PL!H49 -> 30.040255 | C30: =PL!H88 -> 27.37464 | D30: =PL!H127 -> 24.165561
A31: 自由現金流 FY2029（財報現金） | B31: =CF!H30 -> 86.187278 | C31: =CF!H62 -> 62.211875 | D31: =CF!H94 -> 34.022608
A32: AI 增量 ROIC FY2029（讀法 2） | B32: =Thesis!H50 -> 0.13195104 | C32: =Thesis!H102 -> 0.08595571 | D32: =Thesis!H154 -> 0.030761308
A33: AI 增量 ROIC FY2029（讀法 1） | B33: =Thesis!H51 -> 0.063730556 | C33: =Thesis!H103 -> 0.010047899 | D33: =Thesis!H155 -> -0.052833824
A35: 情境目標價（US$；讀法 2） | B35: =Val!B44 -> 423.24787 | C35: =Val!C44 -> 386.05217 | D35: =Val!D44 -> 341.06603
A37: 與 v0.2.2 的差異：v0.2.2 沿用 CoreWeave 架構（對外 AI MW × 每 MW 收入＋其餘業務成長率線、融資瀑布）；v0.3 改為官方兩分部、八條產品線，命題只驅動 Azure AI 與 Copilot 兩條子列，AI 資本支出經折舊進分部營業利益；評價改 DCF 50%＋SOTP 50%、情境 25／50／25。拆解見 Recon 第 5 節。
A38: 已知限制：AI 在役 MW、對外比例、Copilot 營收與座席歷史、產品線利潤、Maia 部署量公司皆未揭露（Assumed，給區間）；非命題產品線依 FY2026 年增收斂，未套用 FY27Q2 季度指引（Windows 指引 mid-thirties 衰退，只列 Recon 對照）；共識為財報前（2026-10-27）。
A39: 建置：bash microsoft/make_v03.sh（build_microsoft.py → LibreOffice 重算 → check_v03.py → segment_check → HTML）；變動拆解與 C10 重解：python3 microsoft/attrib_v031.py
A40: v0.3.1（2026-10-29，季度滾動）：Q 頁加入 FY27Q1（八季 FY25Q2–FY27Q1）；FY2027＝Q1 實績＋Q2–Q4 模型（首期營運資金依 C14 用 FY2026 同期）；評價日 2026-09-30、目標價時點 2027-10-29；C10 依新的資本支出指引重解 MW 速度；Tokenomics v21.4 → v21.7，Maia 改讀 IF_NonNV_*；現價、共識、OpenAI 持股 24% 更新。變動拆解見 Recon 第 5 節。v0.3 修正一（2026-10-27，獨立核對後）：收支關卡範圍公式誤加 FY2032（改為首年起五年並加核對列）；自用 AI 讀法 2 為主值；DCF 扣股票薪酬、減融資租賃負債、扣期間股利；SOTP 的 AI 腿改用模組 DCF；WACC 改 Blume β、10 年期 kd、負債含融資租賃；FY2029 後 MW 新增速度收斂；汰換時更新在役世代。修正二（2026-10-27，第二次核對後；Andy 2026-10-27 15:03 決定讀法 2 為主值）：影子效益只計評價日後新增的自用 MW、只扣 Copilot 增量；SOTP 的 AI 模組改以 FY2028 起現金流折到 FY2027 年底（避免與 FY2027 年底淨現金重複）並扣 FY2028 第一季股利、改用稀釋股數；FY2027 補足到指引下限的資本支出改列其他資本支出（不增 AI MW）；FY2032 MW 增量＝g × 前一年在役 MW；加 ERP 敏感度。修正三（第三次核對後）：影子效益基準改 FY2026 平均自用 MW；SOTP 補加 FY2027 年底到目標價時點的非 AI 自由現金流；FY2027 補足差額的折舊由營業利益扣除。前後對照見報告第 9、10、11 節。

Sheet In
A1: In — 輸入（v0.3.1：FY27Q1 實績滾入；v0.3.2：加「情境驅動對照」、欄名改敏感度低／高；v0.3.3：IF_HoldEcon 四列補低／高、Sens 頁補鍵欄與案例；數值不變）（藍字＝輸入、黑字＝由其他輸入推得）。基準欄 E 進主模型；D／F＝敏感度低／高，只用於 Sens 頁、不進目標價；情境 A／B／C 的驅動見本頁最後一節「情境驅動對照」；金額十億美元（US$B），MW＝IT 關鍵電力。標記：Verified／Interested-party／Analogy／Assumed／Derived；Analogy、Assumed 一律給區間
A2: 「沿用 v0.2.2」＝MAG v0.2.2（2026-10-25，PR #105）已核准的參數與證據，原出處見來源欄；SEC 一手數字取自 microsoft/data/microsoft_facts_20261008.json（v0.1a 起的事實總帳）；FY27Q1 取自 microsoft/data/microsoft_facts_FY27Q1_20261029.json（財報新聞稿與 IR 財務報表兩次讀取核對）
A3: 鍵 | B3: 項目 | C3: 單位 | D3: 敏感度低 | E3: 基準 | F3: 敏感度高 | G3: 標記 | H3: 來源1 | I3: 來源2／說明
A4: A. 股價、股數與資本結構（評價日 2026-09-30＝FY27Q1 季底〔v0.3：2026-06-30〕；目標價時點＝今日 2026-10-29 後 12 個月）
A5: px | B5: 現價（2026-10-28 收盤） | C5: US$ | E5: 531.01 | G5: Verified | H5: https://www.marketbeat.com/stocks/nasdaq/msft/chart（2026-10-28 收盤 531.01，−0.32／−0.06%；前日 531.33；擷取 2026-10-29） | I5: https://247wallst.com/investing/2026/10/28/live-will-microsoft-crush-q1-earnings-tonight-after-the-bell/（報價 531.01，−0.06%）兩來源一致；財報後盤後 544.93（+2.6%）不採用
A6: sh_dil26 | B6: FY2026 稀釋加權股數 | C6: 十億股 | E6: 7.453 | G6: Verified | H6: 事實總帳 microsoft/data/microsoft_facts_20261008.json｜is.sharesDilW.fy2026（10-K FY2026） | I6: v0.3 DCF 每股的分母（評價日 2026-06-30）
A7: sh_basic26 | B7: FY2026 基本加權股數 | C7: 十億股 | E7: 7.429 | G7: Verified | H7: 事實總帳 microsoft/data/microsoft_facts_20261008.json｜is.sharesBasicW.fy2026 | I7: —
A8: dil_gap | B8: 稀釋與基本股數差 | C8: 十億股 | E8: =sh_dil26-sh_basic26 -> 0.024 | G8: Derived | H8: FY2026 稀釋 − 基本 | I8: 預測期稀釋股數＝期間平均流通股數＋此差額
A9: sh_out26 | B9: 流通股數（2026-06-30） | C9: 十億股 | E9: 7.427 | G9: Verified | H9: 事實總帳 microsoft/data/microsoft_facts_20261008.json｜sh.out.fy2026（10-K 附註 15） | I9: —
A10: cash_open | B10: 現金與短期投資（2026-06-30） | C10: US$B | E10: 76.843 | G10: Verified | H10: 事實總帳 microsoft/data/microsoft_facts_20261008.json｜bs.cashSti.fy2026 | I10: CF 頁 FY2027 期初
A11: debt_face | B11: 債務面額（2026-06-30） | C11: US$B | E11: 46.136 | G11: Verified | H11: 事實總帳 microsoft/data/microsoft_facts_20261008.json｜debt.face.fy2026（附註 10） | I11: 帳面值 40.294；CF 頁 FY2027 期初
A12: sh_dil_q1 | B12: FY27Q1 稀釋加權股數 | C12: 十億股 | E12: 7.446 | G12: Interested-party | H12: 事實總帳 microsoft/data/microsoft_facts_FY27Q1_20261029.json｜q.sharesDilW.fy27q1（新聞稿損益表；10-Q 同值） | I12: v0.3.1 DCF 每股的分母（評價日 2026-09-30）
A13: sh_out_q1 | B13: 流通股數（2026-09-30） | C13: 十億股 | E13: 7.427 | G13: Interested-party | H13: 事實總帳 microsoft/data/microsoft_facts_FY27Q1_20261029.json｜sh.out.fy27q1（資產負債表；10-Q 同值） | I13: WACC 股權市值
A14: cash_q1 | B14: 現金與短期投資（2026-09-30） | C14: US$B | E14: 64.509 | G14: Interested-party | H14: 事實總帳 microsoft/data/microsoft_facts_FY27Q1_20261029.json｜bs.cashSti.fy27q1（新聞稿與 IR 財務報表兩讀一致） | I14: DCF 權益橋（評價日）
A15: debt_q1 | B15: 債務面額（2026-09-30） | C15: US$B | E15: 41.269 | G15: Interested-party | H15: 事實總帳 microsoft/data/microsoft_facts_FY27Q1_20261029.json｜debt.face.fy27q1（10-Q 附註 9 到期表合計） | I15: 帳面值 35.481；FY2026 面額 − 本季償還 4.850＝41.286（差 0.017 推定匯率）
A16: fl_liab_q1 | B16: 融資租賃負債（2026-09-30，在帳） | C16: US$B | E16: 70.973 | G16: Interested-party | H16: 事實總帳 microsoft/data/microsoft_facts_FY27Q1_20261029.json｜lease.finLiab.fy27q1（10-Q 附註 12；付款 95.246 − 設算利息 24.273 核對） | I16: 含本季新起租；DCF 權益橋（評價日）
A17: sh_val | B17: 評價日流通股數（WACC） | C17: 十億股 | E17: =sh_out_q1 -> 7.427 | G17: Derived | H17: ＝sh_out_q1（v0.3.1：評價日 2026-09-30） | I17: —
A18: shd_val | B18: 評價日稀釋股數（DCF 每股分母） | C18: 十億股 | E18: =sh_dil_q1 -> 7.446 | G18: Derived | H18: ＝sh_dil_q1（v0.3.1：評價日 2026-09-30） | I18: —
A19: cash_val | B19: 評價日現金與短期投資 | C19: US$B | E19: =cash_q1 -> 64.509 | G19: Derived | H19: ＝cash_q1（v0.3.1：評價日 2026-09-30） | I19: —
A20: debt_val | B20: 評價日債務面額 | C20: US$B | E20: =debt_q1 -> 41.269 | G20: Derived | H20: ＝debt_q1（v0.3.1：評價日 2026-09-30） | I20: —
A21: fl_val | B21: 評價日在帳融資租賃負債 | C21: US$B | E21: =fl_liab_q1 -> 70.973 | G21: Derived | H21: ＝fl_liab_q1（v0.3.1：評價日 2026-09-30） | I21: —
A22: debt_mat_27 | B22: 債務到期 FY2027 | C22: US$B | E22: 9.25 | G22: Verified | H22: 事實總帳 microsoft/data/microsoft_facts_20261008.json｜debt.maturity.fy2027（附註 10 到期表） | I22: FY2027：Q1 已還 4.850＋10-Q 剩餘三季 4.400＝9.250（10-K 9.227）
A23: debt_mat_28 | B23: 債務到期 FY2028 | C23: US$B | E23: 0 | G23: Verified | H23: 事實總帳 microsoft/data/microsoft_facts_20261008.json｜debt.maturity.fy2028（附註 10 到期表） | I23: 10-Q 2026-09-30 到期表同值
A24: debt_mat_29 | B24: 債務到期 FY2029 | C24: US$B | E24: 2.001 | G24: Verified | H24: 事實總帳 microsoft/data/microsoft_facts_20261008.json｜debt.maturity.fy2029（附註 10 到期表） | I24: 10-Q 2026-09-30 到期表同值
A25: debt_mat_30 | B25: 債務到期 FY2030 | C25: US$B | E25: 0 | G25: Verified | H25: 事實總帳 microsoft/data/microsoft_facts_20261008.json｜debt.maturity.fy2030（附註 10 到期表） | I25: 10-Q 2026-09-30 到期表同值
A26: debt_mat_31 | B26: 債務到期 FY2031 | C26: US$B | E26: 0.5 | G26: Verified | H26: 事實總帳 microsoft/data/microsoft_facts_20261008.json｜debt.maturity.fy2031（附註 10 到期表） | I26: 10-Q 2026-09-30 到期表同值
A27: debt_mat_32 | B27: 債務到期 FY2032 | C27: US$B | E27: 0 | G27: Assumed | H27: 事實總帳 microsoft/data/microsoft_facts_20261008.json｜到期表只列 FY2031 以後合計 34.385；FY2032 取 0 | I27: —
A28: fl_liab | B28: 融資租賃負債（2026-06-30，在帳） | C28: US$B | E28: 66.594 | G28: Verified | H28: 事實總帳 microsoft/data/microsoft_facts_20261008.json｜lease.finLiab.fy2026（附註 13） | I28: 在帳融資租賃的資產已在過去的資本支出（公司口徑）內，其本金在預測期照付（CF 頁）
A29: fl_rate | B29: 融資租賃加權利率 | C29: % | E29: 0.045 | G29: Verified | H29: 事實總帳 microsoft/data/microsoft_facts_20261008.json｜lease.wtdRate.fin | I29: 10-Q 2026-09-30 同為 4.5%
A30: fl_pay_27 | B30: 在帳融資租賃付款 FY2027（未折現，含息） | C30: US$B | E30: 7.121 | G30: Verified | H30: 事實總帳 microsoft/data/microsoft_facts_20261008.json｜lease.maturity.fin.fy2027 | I30: 2026-06-30 在帳租賃的付款表（收支關卡用；FY27Q1 新起租者已在資本支出內）
A31: fl_pay_28 | B31: 在帳融資租賃付款 FY2028（未折現，含息） | C31: US$B | E31: 7.294 | G31: Verified | H31: 事實總帳 microsoft/data/microsoft_facts_20261008.json｜lease.maturity.fin.fy2028 | I31: 2026-06-30 在帳租賃的付款表（收支關卡用；FY27Q1 新起租者已在資本支出內）
A32: fl_pay_29 | B32: 在帳融資租賃付款 FY2029（未折現，含息） | C32: US$B | E32: 6.668 | G32: Verified | H32: 事實總帳 microsoft/data/microsoft_facts_20261008.json｜lease.maturity.fin.fy2029 | I32: 2026-06-30 在帳租賃的付款表（收支關卡用；FY27Q1 新起租者已在資本支出內）
A33: fl_pay_30 | B33: 在帳融資租賃付款 FY2030（未折現，含息） | C33: US$B | E33: 6.57 | G33: Verified | H33: 事實總帳 microsoft/data/microsoft_facts_20261008.json｜lease.maturity.fin.fy2030 | I33: 2026-06-30 在帳租賃的付款表（收支關卡用；FY27Q1 新起租者已在資本支出內）
A34: fl_pay_31 | B34: 在帳融資租賃付款 FY2031（未折現，含息） | C34: US$B | E34: 6.543 | G34: Verified | H34: 事實總帳 microsoft/data/microsoft_facts_20261008.json｜lease.maturity.fin.fy2031 | I34: 2026-06-30 在帳租賃的付款表（收支關卡用；FY27Q1 新起租者已在資本支出內）
A35: fl_pay_32 | B35: 在帳融資租賃付款 FY2032（未折現，含息） | C35: US$B | E35: =fl_pay_31 -> 6.543 | G35: Assumed | H35: 事實總帳 microsoft/data/microsoft_facts_20261008.json｜FY2032 比照 FY2031（之後合計 55.490 分多年） | I35: 2026-06-30 在帳租賃的付款表（收支關卡用；FY27Q1 新起租者已在資本支出內）
A36: min_cash | B36: 最低現金 | C36: US$B | D36: 30 | E36: 50 | F36: 70 | G36: Assumed | H36: 沿用 v0.2.2（microsoft/legacy_v0.2/company.json；交接檔 docs/handoff/20261025_Microsoft收支模型_交接檔_v0_2_2.md）（defaults.minCash 50） | I36: 低於此水準先停回購、再舉債
A37: bb_target | B37: 回購目標（每年） | C37: US$B | E37: 22.271 | G37: Verified | H37: 事實總帳 microsoft/data/microsoft_facts_20261008.json｜cf.buyback.fy2026（含員工扣稅買回 5.6） | I37: 現金不足時先減回購
A38: bb_g | B38: 回購價格年增（以現價起算） | C38: % | D38: 0 | E38: 0.08 | F38: 0.12 | G38: Assumed | H38: 無：約等於股東權益成本扣股利率 | I38: 只影響股數
A39: sh_iss | B39: 員工股票發行（每年） | C39: 十億股 | D39: 0.035 | E39: 0.045 | F39: 0.055 | G39: Derived | H39: 事實總帳 microsoft/data/microsoft_facts_20261008.json｜FY2026 回購約 0.048 十億股（計畫 0.036＋扣稅買回 5.6 ÷ 約 470 美元），基本加權股數 7.433 → 7.429 幾乎不變 → 發行約 0.045 | I39: 低／高 Assumed
A40: dps_q0 | B40: 每季股利（FY2027 第一季付，舊額） | C40: US$ | E40: 0.91 | G40: Verified | H40: 事實總帳 microsoft/data/microsoft_facts_20261008.json｜sh.dps.fy2026（每季 0.91） | I40: —
A41: dps_q1 | B41: 每季股利（2026-09-15 宣告，新額） | C41: US$ | E41: 0.98 | G41: Interested-party | H41: 事實總帳 microsoft/data/microsoft_facts_20261008.json｜sh.dpsQ.fy27q1 | I41: —
A42: dps_27 | B42: FY2027 每股股利（付現） | C42: US$ | E42: =dps_q0+3*dps_q1 -> 3.85 | G42: Derived | H42: 第一季付舊額（FY27Q1 現金流量表付現 6.757＝0.91 × 7.427）、其後三季付新額 | I42: —
A43: div_rem27 | B43: 評價日後 FY2027 尚待支付的每股股利 | C43: US$ | E43: =3*dps_q1 -> 2.94 | G43: Derived | H43: v0.3.1：評價日 2026-09-30 後的 FY27 第二至第四季（新額 × 3） | I43: DCF 推到目標價時點時扣除
A44: dps_g | B44: 每股股利年增（FY2028 起） | C44: % | D44: 0.05 | E44: 0.08 | F44: 0.1 | G44: Interested-party | H44: 沿用 v0.2.2（microsoft/legacy_v0.2/company.json；交接檔 docs/handoff/20261025_Microsoft收支模型_交接檔_v0_2_2.md）（defaults.dividend.growth；2026-09 宣告 +8%） | I44: —
A45: B. 折現率與評價參數（WACC 沿用 v0.2.2 的 CAPM 輸入；權重為 [判斷] 預設，Andy 可改）
A46: rf | B46: 無風險利率（10 年美債，2026-10-26） | C46: % | E46: 0.05 | G46: Verified | H46: U.S. Treasury 10 年期殖利率 2026-10-26：5.00%（修正一：chat 端統一 MAG＋Oracle 個股模型的同一輸入，與 Amazon v0.3 相同） | I46: 事實總帳 microsoft/data/microsoft_facts_20261008.json｜val.ust10：2026-10-07 為 5.28%（v0.2.2 與 v0.3 初版）
A47: beta_sa | B47: 原始 β：StockAnalysis（5 年月資料；Yahoo 同值，推測同源，算 1 個） | C47: x | E47: 1.1 | G47: Verified | H47: 事實總帳 microsoft/data/microsoft_facts_20261008.json｜val.beta.sa（2026-10-08） | I47: C13：獨立來源
A48: beta_gf | B48: 原始 β：GuruFocus（3 年） | C48: x | E48: 1.1741 | G48: Verified | H48: 事實總帳 microsoft/data/microsoft_facts_20261008.json｜val.beta.gurufocus（2026-10-08） | I48: C13：獨立來源
A49: blume_w | B49: Blume 調整：原始 β 權重（其餘向 1 收斂） | C49: x | E49: 0.67 | G49: Assumed | H49: 共同修正工作單 F4（2026-10-27）：0.67 × 原始 β＋0.33 | I49: —
A50: beta | B50: β（兩個獨立來源 Blume 調整後的中位數） | C50: x | D50: 0.95 | E50: =MEDIAN(blume_w*beta_sa+(1-blume_w),blume_w*beta_gf+(1-blume_w)) -> 1.0918235 | F50: 1.174 | G50: Derived | H50: Blume：1.10 → 1.067、1.1741 → 1.117；中位數 1.092（修正一；v0.3 初版用原始平均 1.137） | I50: 低 0.95＝獨立核對建議區間下緣；高＝原始 GuruFocus
A51: erp | B51: 股權風險溢酬 | C51: % | D51: 0.045 | E51: 0.05 | F51: 0.06 | G51: Assumed | H51: MAG 對照表 r1 5.10（判斷，列敏感度） | I51: 沿用 v0.2.2（microsoft/legacy_v0.2/company.json；交接檔 docs/handoff/20261025_Microsoft收支模型_交接檔_v0_2_2.md）
A52: kd_aaa | B52: 對照：Moody's Aaa 公司債殖利率（長天期） | C52: % | E52: 0.0626 | G52: Analogy | H52: 事實總帳 microsoft/data/microsoft_facts_20261008.json｜val.kd.aaa（FRED DAAA 2026-10-06） | I52: v0.3 初版 kd；Aaa 指數為 20 年以上長債，修正一改用約 10 年期
A53: kd_spread | B53: 約 10 年期 AAA 公司債對美債利差 | C53: pt | D53: 0.003 | E53: 0.006 | F53: 0.009 | G53: Assumed | H53: 無：MSFT 個別債券殖利率找不到；AAA 10 年期利差歷史約 0.3–0.9 個百分點 | I53: kd＝rf＋利差（修正一 F4）
A54: kd | B54: 稅前債務成本（約 10 年期公司債） | C54: % | E54: =rf+kd_spread -> 0.056 | G54: Derived | H54: rf（10 年美債）＋利差 | I54: —
A55: tax_w | B55: WACC 用稅率 | C55: % | E55: 0.2 | G55: Interested-party | H55: 事實總帳 microsoft/data/microsoft_facts_20261008.json｜guid.fy27.etr（FY2027 指引約 20%） | I55: —
A56: ke | B56: 股東權益成本（CAPM） | C56: % | E56: =rf+beta*erp -> 0.10459117 | G56: Derived | H56: rf ＋ β × ERP | I56: —
A57: wacc | B57: WACC | C57: % | E57: =(px*sh_val*ke+(debt_val+fl_val)*kd*(1-tax_w))/(px*sh_val+debt_val+fl_val) -> 0.10293659 | G57: Derived | H57: E／(D＋E) × ke ＋ D／(D＋E) × kd ×（1 − 稅率）；E＝現價 × 評價日流通股數、D＝評價日債務面額＋在帳融資租賃負債（修正一 F4；v0.3.1 改用 2026-09-30 值） | I57: v0.2.2 10.90%；v0.3 10.29%
A58: g_tv | B58: 永續成長率（FY2032 後） | C58: % | D58: 0.02 | E58: 0.03 | F58: 0.04 | G58: Assumed | H58: 工作單 20261027 第 2 節：g 3% | I58: Sens ±1pt
A59: ronic_prem | B59: 永續期新投資報酬 − WACC | C59: pt | D59: -0.02 | E59: 0 | F59: 0.05 | G59: Assumed | H59: 無：永續期新投資只賺資金成本（成長不創造價值） | I59: 永續期自由現金流＝NOPAT ×（1 − g ÷ 新投資報酬）；替代口徑（FY2032 自由現金流 ×（1＋g））見 Sens 判斷預設表
A60: base_fy | B60: 評價日所屬會計年度（最新已申報年度） | C60: 年 | E60: 2026 | G60: Verified | H60: FY2026 10-K（期末 2026-06-30） | I60: 公式中的年數以「年度列 − base_fy」計算（修正一 F6：不寫死）
A61: mid_yr | B61: 期中折現：年中偏移 | C61: 年 | E61: 0.5 | G61: Assumed | H61: 現金流平均發生在年中 | I61: —
A62: val_d0 | B62: 最新會計年度年底（FY2026，2026-06-30） | C62: 日期 | E62: =DATE(2026,6,30) -> 46203 | G62: Verified | H62: FY2026 10-K 期末 | I62: 折現年數的起點；評價日與此日的差＝v_off
A63: roll_d1 | B63: 評價日（FY27Q1 季底 2026-09-30） | C63: 日期 | E63: =DATE(2026,9,30) -> 46295 | G63: Verified | H63: v0.3.1：最新已申報季（FY27Q1 10-Q，期末 2026-09-30）；v0.3 為 2026-06-30 | I63: —
A64: roll_d2 | B64: 目標價時點（今日 2026-10-29 後 12 個月） | C64: 日期 | E64: =DATE(2027,10,29) -> 46689 | G64: Assumed | H64: 工作單：目標價約 12 個月後（v0.3：2027-10-27） | I64: 工作單字面「目標價日 +1 季」（2028-01-27）列 Sens 判斷替代與報告「需 Andy 決定」
A65: days_yr | B65: 每年天數 | C65: 天 | E65: 365 | G65: Assumed | H65: — | I65: —
A66: v_off | B66: 評價日距 FY2026 年底（年） | C66: 年 | E66: =(roll_d1-val_d0)/days_yr -> 0.25205479 | G66: Derived | H66: 2026-06-30 → 評價日 | I66: FY2027 只折現評價日後的剩餘期間；之後各年折現年數減 v_off
A67: t_roll | B67: 評價日 → 目標價時點（年） | C67: 年 | E67: =(roll_d2-roll_d1)/days_yr -> 1.0794521 | G67: Derived | H67: 評價日 → 目標價時點 | I67: DCF 每股以 WACC 推到目標價時點（已決定事項 12 沿用），並扣除期間股利（修正一 F6）
A68: roll_div_q | B68: 評價日到目標價時點之間、FY2028 已付的股利季數 | C68: 季 | E68: 1 | G68: Derived | H68: FY2028 第一季股利約 2027-09 支付，早於目標價時點 | I68: —
A69: q_per_yr | B69: 每年季數 | C69: 季 | E69: 4 | G69: Verified | H69: — | I69: —
A70: stub_d0 | B70: SOTP 淨現金日（FY2027 年底 2027-06-30） | C70: 日期 | E70: =DATE(2027,6,30) -> 46568 | G70: Verified | H70: FY2027 年底 | I70: —
A71: t_stub | B71: SOTP 淨現金日 → 目標價時點（年） | C71: 年 | E71: =(roll_d2-stub_d0)/days_yr -> 0.33150685 | G71: Derived | H71: 2027-06-30 → 目標價時點 | I71: 修正三：此期間的非 AI 自由現金流既不在 FY2027 年底淨現金、也不在目標價時點 NTM EBITDA 倍數內，SOTP 補加
A72: fy28_end | B72: FY2028 年底 | C72: 日期 | E72: =DATE(2028,6,30) -> 46934 | G72: Verified | H72: 財年 6 月結束 | I72: —
A73: w_ntm28 | B73: 目標價時點的未來 12 個月中 FY2028 的比重 | C73: x | E73: =(fy28_end-roll_d2)/days_yr -> 0.67123288 | G73: Derived | H73: 目標價時點起 12 個月：FY2028 約 0.67、FY2029 約 0.33 | I73: SOTP 用 NTM EBITDA
A74: w_dcf | B74: 目標價中 DCF 的權重（其餘為分部加總 SOTP） | C74: % | D74: 0.3 | E74: 0.5 | F74: 0.7 | G74: Assumed | H74: [判斷] 預設：工作單 20261027 第 2 節（與 AI半導體 DCF＋Comparable 各半一致；Comparable 在分部層做） | I74: Andy 可改
A75: w_A | B75: 情境權重 A | C75: % | E75: 0.25 | G75: Assumed | H75: [判斷] 預設：工作單 20261027 第 2 節 A 25%／B 50%／C 25% | I75: Andy 可改
A76: w_B | B76: 情境權重 B | C76: % | E76: 0.5 | G76: Assumed | H76: [判斷] 預設：工作單 20261027 第 2 節 A 25%／B 50%／C 25% | I76: Andy 可改
A77: w_C | B77: 情境權重 C | C77: % | E77: 0.25 | G77: Assumed | H77: [判斷] 預設：工作單 20261027 第 2 節 A 25%／B 50%／C 25% | I77: Andy 可改
A78: oai_stake | B78: OpenAI 持股比例 | C78: % | E78: 0.24 | F78: 0.27 | G78: Interested-party | H78: 事實總帳 microsoft/data/microsoft_facts_FY27Q1_20261029.json｜oai.stake.fy27q1（10-Q FY27Q1 附註 1：approximate 24% interest on an as-converted basis，最新） | I78: FY2026 10-K 約 25%（oai.stake.fy2026，v0.3 主值）；重組時（2025-10-28）約 27%，列判斷替代
A79: oai_stake26 | B79: 對照：OpenAI 持股（FY2026 10-K） | C79: % | E79: 0.25 | G79: Verified | H79: 事實總帳 microsoft/data/microsoft_facts_20261008.json｜oai.stake.fy2026（10-K 附註 1：approximate 25%） | I79: v0.3 主值；Sens 判斷替代
A80: oai_val | B80: OpenAI 最近一輪投後估值 | C80: US$B | E80: 852 | G80: Interested-party | H80: 事實總帳 microsoft/data/microsoft_facts_20261008.json｜oai.valuation（2026-03 結案，募資 122） | I80: 新創自報估值；2026-09-30 報導洽談 300 億美元、估值 1.4 兆（未結案，不採用；https://propakistani.pk/2026/09/30/openai-reportedly-seeks-30-billion-at-1-4-trillion-valuation/）
A81: liq_disc | B81: 未上市持股流動性折價 | C81: % | D81: 0 | E81: 0.2 | F81: 0.4 | G81: Assumed | H81: 工作單 20261027：20% | I81: 沿用 v0.2.2（microsoft/legacy_v0.2/company.json；交接檔 docs/handoff/20261025_Microsoft收支模型_交接檔_v0_2_2.md）
A82: oai_v | B82: OpenAI 持股價值（扣折價） | C82: US$B | E82: =oai_stake*oai_val*(1-liq_disc) -> 163.584 | G82: Derived | H82: 比例 × 估值 ×（1 − 折價） | I82: Anthropic 持股比例未揭露 → 不估值（資料缺口）
A83: m_ai | B83: Azure AI 倍數（EV／NTM EBITDA） | C83: x | D83: 4 | E83: 6 | F83: 10 | G83: Assumed | H83: 沿用 v0.2.2（microsoft/legacy_v0.2/company.json；交接檔 docs/handoff/20261025_Microsoft收支模型_交接檔_v0_2_2.md）（valuation.evEbitda 6×） | I83: AI 基礎設施租賃同業（CRWV TTM 25×、NBIS 不具意義、ORCL NTM 9.5×）口徑不一，沿用 v0.2.2
A84: m_cloud | B84: 非 AI 雲端倍數（Azure 其他） | C84: x | E84: 13.82 | G84: Derived | H84: microsoft/data/peers_cloud_20261008.json：ORCL、IBM、SAP、CRM、NOW、AKAM、EQIX、DOCN 中位數（C12） | I84: 2026-10-07 收盤
A85: m_sw | B85: 企業軟體倍數（M365 cloud、授權、產業、Frontier） | C85: x | E85: 10.8 | G85: Derived | H85: 事實總帳 microsoft/data/microsoft_facts_20261008.json｜val.peer.sw.*：ORCL 9.54、SAP 15.02、CRM 10.80、ADBE 6.60、NOW 20.65 中位數（不含 MSFT） | I85: 2026-10-07
A86: m_ads | B86: 數位廣告倍數（Search and advertising） | C86: x | E86: 9.11 | G86: Derived | H86: microsoft/data/peers_ads_20261009.json：META、PINS、TTD、APP、RDDT、SNAP 中位數（C18） | I86: 2026-10-07
A87: m_game | B87: 遊戲倍數（XBOX） | C87: x | E87: 12.63 | G87: Derived | H87: 事實總帳 microsoft/data/microsoft_facts_20261008.json｜val.peer.game.*：TTWO 50.9、NTDOY 12.63、NTES 8.23 中位數（TTM；NTM 找不到） | I87: 2026-10-08
A88: m_pc | B88: PC／裝置倍數（Windows OEM and devices） | C88: x | E88: 14.47 | G88: Derived | H88: 事實總帳 microsoft/data/microsoft_facts_20261008.json｜val.peer.pc.*：HPQ 7.6、DELL 22.1、Lenovo 14.47 中位數（TTM） | I88: 2026-10-08
A89: m_own | B89: Microsoft 自身 NTM EV／EBITDA（對照） | C89: x | E89: 15.67 | G89: Derived | H89: 事實總帳 microsoft/data/microsoft_facts_20261008.json｜val.msft.ownNtm（2026-10-07） | I89: 只用於判斷預設替代（非 AI 各線改用自身倍數）
A90: al_m365 | B90: 產品線營業利益率分配：Microsoft 365 cloud（SOTP 用） | C90: % | D90: 0.5 | E90: 0.6 | F90: 0.7 | G90: Assumed | H90: 事實總帳 microsoft/data/microsoft_facts_20261008.json｜alloc.oiMargin（公司不揭露產品線利潤）；沿用 v0.2.2（microsoft/legacy_v0.2/company.json；交接檔 docs/handoff/20261025_Microsoft收支模型_交接檔_v0_2_2.md） | I90: 舊 PBP 分部 FY2026 59.9% 類比；Azure 其他、XBOX＋Windows 為分部殘差
A91: al_lic | B91: 產品線營業利益率分配：Productivity and server licensing（SOTP 用） | C91: % | D91: 0.65 | E91: 0.75 | F91: 0.85 | G91: Assumed | H91: 事實總帳 microsoft/data/microsoft_facts_20261008.json｜alloc.oiMargin（公司不揭露產品線利潤）；沿用 v0.2.2（microsoft/legacy_v0.2/company.json；交接檔 docs/handoff/20261025_Microsoft收支模型_交接檔_v0_2_2.md） | I91: 地端授權毛利高、銷售費用低；Azure 其他、XBOX＋Windows 為分部殘差
A92: al_ind | B92: 產品線營業利益率分配：Industry solutions（SOTP 用） | C92: % | D92: 0.2 | E92: 0.3 | F92: 0.4 | G92: Assumed | H92: 事實總帳 microsoft/data/microsoft_facts_20261008.json｜alloc.oiMargin（公司不揭露產品線利潤）；沿用 v0.2.2（microsoft/legacy_v0.2/company.json；交接檔 docs/handoff/20261025_Microsoft收支模型_交接檔_v0_2_2.md） | I92: 含 Dynamics、LinkedIn 等；Azure 其他、XBOX＋Windows 為分部殘差
A93: al_fro | B93: 產品線營業利益率分配：Frontier and support services（SOTP 用） | C93: % | D93: 0.2 | E93: 0.3 | F93: 0.4 | G93: Assumed | H93: 事實總帳 microsoft/data/microsoft_facts_20261008.json｜alloc.oiMargin（公司不揭露產品線利潤）；沿用 v0.2.2（microsoft/legacy_v0.2/company.json；交接檔 docs/handoff/20261025_Microsoft收支模型_交接檔_v0_2_2.md） | I93: 含支援服務；Azure 其他、XBOX＋Windows 為分部殘差
A94: al_srch | B94: 產品線營業利益率分配：Search and advertising（SOTP 用） | C94: % | D94: 0.2 | E94: 0.3 | F94: 0.4 | G94: Assumed | H94: 事實總帳 microsoft/data/microsoft_facts_20261008.json｜alloc.oiMargin（公司不揭露產品線利潤）；沿用 v0.2.2（microsoft/legacy_v0.2/company.json；交接檔 docs/handoff/20261025_Microsoft收支模型_交接檔_v0_2_2.md） | I94: —；Azure 其他、XBOX＋Windows 為分部殘差
A95: C. Tokenomics v21.7 快照（microsoft/data/tokenomics_snapshot_v21.7.json；基準成本欄；每 GW＝IT 關鍵電力；v0.3.1 由 v21.4 升級，契約名稱值逐一比對無差異）
A96: tk_hold_h100 | B96: IF_HoldEcon｜Hopper H100（每 MW 年持有成本，WACC 10% 打平） | C96: US$M/MW-年 | D96: 6.7910747 | E96: 9.7030873 | F96: 16.66377 | G96: Derived | H96: Tokenomics v21.7（20261025_Tokenomics_v21.7.xlsx，master 6621bc5） | I96: 基準成本欄；低／高＝同一快照的低成本／高成本欄（Interface!C13／Interface!E13，v0.3.3 補區間，只用於 Sens 頁 he_all 案例）
A97: tk_hold_gb200 | B97: IF_HoldEcon｜GB200 NVL72（每 MW 年持有成本，WACC 10% 打平） | C97: US$M/MW-年 | D97: 6.6118163 | E97: 8.8281656 | F97: 14.318575 | G97: Derived | H97: Tokenomics v21.7（20261025_Tokenomics_v21.7.xlsx，master 6621bc5） | I97: 基準成本欄；低／高＝同一快照的低成本／高成本欄（Interface!F13／Interface!H13，v0.3.3 補區間，只用於 Sens 頁 he_all 案例）
A98: tk_hold_gb300 | B98: IF_HoldEcon｜GB300 NVL72（每 MW 年持有成本，WACC 10% 打平） | C98: US$M/MW-年 | D98: 8.4288991 | E98: 10.886411 | F98: 18.534646 | G98: Derived | H98: Tokenomics v21.7（20261025_Tokenomics_v21.7.xlsx，master 6621bc5） | I98: 基準成本欄；低／高＝同一快照的低成本／高成本欄（Interface!I13／Interface!K13，v0.3.3 補區間，只用於 Sens 頁 he_all 案例）
A99: tk_hold_vr200 | B99: IF_HoldEcon｜VR200 NVL72（每 MW 年持有成本，WACC 10% 打平） | C99: US$M/MW-年 | D99: 9.2190715 | E99: 12.225471 | F99: 19.750627 | G99: Derived | H99: Tokenomics v21.7（20261025_Tokenomics_v21.7.xlsx，master 6621bc5） | I99: 基準成本欄；低／高＝同一快照的低成本／高成本欄（Interface!L13／Interface!N13，v0.3.3 補區間，只用於 Sens 頁 he_all 案例）
A100: tk_cxit_h100 | B100: IF_CapexIT｜Hopper H100（每 MW IT 資本支出） | C100: US$M/MW | E100: 27.510214 | G100: Derived | H100: Tokenomics v21.7（20261025_Tokenomics_v21.7.xlsx，master 6621bc5） | I100: —
...

Sheet Q
A1: Q — 實績（十億美元）。分部與產品線為 FY2027 起的報導口徑（FY25Q2–FY26Q4：8-K 2026-09-02「Segment History／Products and Service Offerings — As Restated」，未經查核；FY27Q1：2026-10-28 財報新聞稿與 IR 財務報表，兩次讀取核對一致）；合併損益、現金流量取自 10-K／財報新聞稿（事實總帳）
A2: 最近八季 FY25Q2–FY27Q1（v0.3.1 加入 FY27Q1、移出 FY25Q1）；J 欄＝FY2026 四季合計（公式）、K 欄＝FY2027 年初至今（Q1）；L、M 欄＝公司揭露的年度值（輸入）；核對列實績必須為 0。舊三分部（PBP／IC／MPC）列在下方對照（FY2026 以前口徑）
A3: 項目 | B3: FY25Q2（～2024-12） | C3: FY25Q3（～2025-03） | D3: FY25Q4（～06） | E3: FY26Q1（～2025-09） | F3: FY26Q2（～12） | G3: FY26Q3（～2026-03） | H3: FY26Q4（～06） | I3: FY27Q1（～2026-09） | J3: FY2026（四季合計） | K3: FY2027 年初至今（Q1） | L3: FY2025（公司年度值） | M3: FY2026（公司年度值） | N3: 標記 | O3: 來源（事實總帳 id）
A4: 1. 官方分部與產品線營收（FY2027 起報導口徑）
A5: Agents and Infra | B5: 52.766 | C5: 54.763 | D5: 60.778 | E5: 61.672 | F5: 64.441 | G5: 67.438 | H5: 74.576 | I5: 76.795 | J5: =SUM(E5:H5) -> 268.127 | K5: =I5 -> 76.795 | L5: 218.783 | M5: 268.127 | N5: Verified | O5: 8-K 2026-09-02 附件 99.1（As Restated）；FY27Q1：2026-10-28 新聞稿／IR 財務報表｜q.seg27.ai.rev.*、seg27.ai.rev.*
A6: Azure | B6: 17.337 | C6: 18.54 | D6: 20.712 | E6: 22.384 | F6: 24.129 | G6: 26.008 | H6: 29.417 | I6: 33.165 | J6: =SUM(E6:H6) -> 101.938 | K6: =I6 -> 33.165 | L6: 72.61 | M6: 101.938 | N6: Verified | O6: 8-K 2026-09-02 附件 99.1（As Restated）；FY27Q1：2026-10-28 新聞稿／IR 財務報表｜q.prod27.azure.*
A7: Microsoft 365 cloud | B7: 20.686 | C7: 20.967 | D7: 22.935 | E7: 23.694 | F7: 24.466 | G7: 25.418 | H7: 26.721 | I7: 27.778 | J7: =SUM(E7:H7) -> 100.299 | K7: =I7 -> 27.778 | L7: 84.605 | M7: 100.299 | N7: Verified | O7: 8-K 2026-09-02 附件 99.1（As Restated）；FY27Q1：2026-10-28 新聞稿／IR 財務報表｜q.prod27.m365cloud.*
A8: Productivity and server licensing | B8: 8.307 | C8: 8.731 | D8: 10.302 | E8: 8.678 | F8: 8.814 | G8: 8.76 | H8: 11.033 | I8: 8.407 | J8: =SUM(E8:H8) -> 37.285 | K8: =I8 -> 8.407 | L8: 35.391 | M8: 37.285 | N8: Verified | O8: 8-K 2026-09-02 附件 99.1（As Restated）；FY27Q1：2026-10-28 新聞稿／IR 財務報表｜q.prod27.licensing.*
A9: Industry solutions | B9: 4.544 | C9: 4.579 | D9: 4.835 | E9: 4.894 | F9: 4.994 | G9: 5.165 | H9: 5.292 | I9: 5.337 | J9: =SUM(E9:H9) -> 20.345 | K9: =I9 -> 5.337 | L9: 18.417 | M9: 20.345 | N9: Verified | O9: 8-K 2026-09-02 附件 99.1（As Restated）；FY27Q1：2026-10-28 新聞稿／IR 財務報表｜q.prod27.industry.*
A10: Frontier and support services | B10: 1.892 | C10: 1.946 | D10: 1.994 | E10: 2.022 | F10: 2.038 | G10: 2.087 | H10: 2.113 | I10: 2.108 | J10: =SUM(E10:H10) -> 8.26 | K10: =I10 -> 2.108 | L10: 7.76 | M10: 8.26 | N10: Verified | O10: 8-K 2026-09-02 附件 99.1（As Restated）；FY27Q1：2026-10-28 新聞稿／IR 財務報表｜q.prod27.frontier.*
A11: 檢查：Agents and Infra 產品線合計 − 分部 | B11: =SUM(B6:B10)-B5 -> 0 | C11: =SUM(C6:C10)-C5 -> 0 | D11: =SUM(D6:D10)-D5 -> 0 | E11: =SUM(E6:E10)-E5 -> 0 | F11: =SUM(F6:F10)-F5 -> 0 | G11: =SUM(G6:G10)-G5 -> 0 | H11: =SUM(H6:H10)-H5 -> 0 | I11: =SUM(I6:I10)-I5 -> 0 | ... M11: =SUM(M6:M10)-M5 -> 0 | N11: 核對
A12: Devices and Consumer | B12: 16.866 | C12: 15.303 | D12: 15.663 | E12: 16.001 | F12: 16.832 | G12: 15.448 | H12: 15.431 | I12: 15.484 | J12: =SUM(E12:H12) -> 63.712 | K12: =I12 -> 15.484 | L12: 62.941 | M12: 63.712 | N12: Verified | O12: 8-K 2026-09-02 附件 99.1（As Restated）；FY27Q1：2026-10-28 新聞稿／IR 財務報表｜q.seg27.dc.rev.*
A13: Search and advertising | B13: 5.773 | C13: 5.437 | D13: 5.802 | E13: 5.942 | F13: 6.393 | G13: 6.065 | H13: 6.435 | I13: 6.554 | J13: =SUM(E13:H13) -> 24.835 | K13: =I13 -> 6.554 | L13: 22.171 | M13: 24.835 | N13: Verified | O13: 8-K 2026-09-02 附件 99.1（As Restated）；FY27Q1：2026-10-28 新聞稿／IR 財務報表｜q.prod27.searchads.*
A14: XBOX | B14: 6.581 | C14: 5.721 | D14: 5.532 | E14: 5.508 | F14: 5.958 | G14: 5.341 | H14: 4.983 | I14: 5.379 | J14: =SUM(E14:H14) -> 21.79 | K14: =I14 -> 5.379 | L14: 23.455 | M14: 21.79 | N14: Verified | O14: 8-K 2026-09-02 附件 99.1（As Restated）；FY27Q1：2026-10-28 新聞稿／IR 財務報表｜q.prod27.xbox.*
A15: Windows OEM and devices | B15: 4.512 | C15: 4.145 | D15: 4.329 | E15: 4.551 | F15: 4.481 | G15: 4.042 | H15: 4.013 | I15: 3.551 | J15: =SUM(E15:H15) -> 17.087 | K15: =I15 -> 3.551 | L15: 17.315 | M15: 17.087 | N15: Verified | O15: 8-K 2026-09-02 附件 99.1（As Restated）；FY27Q1：2026-10-28 新聞稿／IR 財務報表｜q.prod27.windows.*
A16: 檢查：Devices and Consumer 產品線合計 − 分部 | B16: =SUM(B13:B15)-B12 -> 0 | C16: =SUM(C13:C15)-C12 -> 0 | D16: =SUM(D13:D15)-D12 -> 0 | E16: =SUM(E13:E15)-E12 -> 0 | F16: =SUM(F13:F15)-F12 -> 0 | G16: =SUM(G13:G15)-G12 -> 0 | H16: =SUM(H13:H15)-H12 -> 0 | I16: =SUM(I13:I15)-I12 -> 0 | ... M16: =SUM(M13:M15)-M12 -> 0 | N16: 核對
A17: 分部合計（營收） | B17: =B5+B12 -> 69.632 | C17: =C5+C12 -> 70.066 | D17: =D5+D12 -> 76.441 | E17: =E5+E12 -> 77.673 | F17: =F5+F12 -> 81.273 | G17: =G5+G12 -> 82.886 | H17: =H5+H12 -> 90.007 | I17: =I5+I12 -> 92.279 | J17: =SUM(E17:H17) -> 331.839 | K17: =I17 -> 92.279 | L17: =L5+L12 -> 281.724 | M17: =M5+M12 -> 331.839 | N17: Derived
A18: 合併營收（公司損益表） | B18: 69.632 | C18: 70.066 | D18: 76.441 | E18: 77.673 | F18: 81.273 | G18: 82.886 | H18: 90.007 | I18: 92.279 | J18: =SUM(E18:H18) -> 331.839 | K18: =I18 -> 92.279 | L18: 281.724 | M18: 331.839 | N18: Verified | O18: 財報新聞稿／10-K｜q.rev.*、is.rev.*
A19: 檢查：分部合計 − 合併營收 | B19: =B17-B18 -> 0 | C19: =C17-C18 -> 0 | D19: =D17-D18 -> 0 | E19: =E17-E18 -> 0 | F19: =F17-F18 -> 0 | G19: =G17-G18 -> 0 | H19: =H17-H18 -> 0 | I19: =I17-I18 -> 0 | ... M19: =M17-M18 -> 0 | N19: 核對
A20: 2. 分部營業利益（Microsoft 無未分攤項：分部合計＝合併營業利益）
A21: Agents and Infra 營業利益 | B21: 26.718 | C21: 27.704 | D21: 30.221 | E21: 32.718 | F21: 33.167 | G21: 33.748 | H21: 36.732 | I21: 40.558 | J21: =SUM(E21:H21) -> 136.365 | K21: =I21 -> 40.558 | L21: 110.814 | M21: 136.365 | N21: Verified | O21: 8-K 2026-09-02 附件 99.1（As Restated）；FY27Q1：2026-10-28 新聞稿／IR 財務報表｜q.seg27.ai.oi.*
A22: Devices and Consumer 營業利益 | B22: 4.935 | C22: 4.296 | D22: 4.102 | E22: 5.243 | F22: 5.108 | G22: 4.65 | H22: 3.871 | I22: 5.357 | J22: =SUM(E22:H22) -> 18.872 | K22: =I22 -> 5.357 | L22: 17.714 | M22: 18.872 | N22: Verified | O22: 8-K 2026-09-02 附件 99.1（As Restated）；FY27Q1：2026-10-28 新聞稿／IR 財務報表｜q.seg27.dc.oi.*
A23: 合併營業利益（公司損益表） | B23: 31.653 | C23: 32 | D23: 34.323 | E23: 37.961 | F23: 38.275 | G23: 38.398 | H23: 40.603 | I23: 45.915 | J23: =SUM(E23:H23) -> 155.237 | K23: =I23 -> 45.915 | L23: 128.528 | M23: 155.237 | N23: Verified | O23: 財報新聞稿／10-K｜q.oi.*、is.oi.*
A24: 檢查：分部營業利益合計 − 合併營業利益（未分攤＝0） | B24: =B21+B22-B23 -> 0 | C24: =C21+C22-C23 -> 0 | D24: =D21+D22-D23 -> 0 | E24: =E21+E22-E23 -> 0 | F24: =F21+F22-F23 -> 0 | G24: =G21+G22-G23 -> 0 | H24: =H21+H22-H23 -> 0 | I24: =I21+I22-I23 -> 0 | ... M24: =M21+M22-M23 -> 0 | N24: 核對
A25: 3. 合併損益主要列（年度值；淨利另列各季；FY27Q1 單季另填 I 欄）
A26: 淨利（GAAP，含 OpenAI 等持股損益） | B26: 24.108 | C26: 25.824 | D26: 27.233 | E26: 27.747 | F26: 38.458 | G26: 31.778 | H26: 35.766 | I26: 36.629 | J26: =SUM(E26:H26) -> 133.749 | K26: =I26 -> 36.629 | L26: 101.832 | M26: 133.749 | N26: Verified | O26: 財報新聞稿／10-K｜q.ni.*、is.ni.*
A27: 業外收支（other income (expense), net） | I27: 0.038 | K27: =I27 -> 0.038 | L27: -4.901 | M27: 10.697 | N27: Verified | O27: 10-K｜is.oie.*；FY27Q1：q.oie.fy27q1
A28: 稅前淨利 | I28: 45.953 | K28: =I28 -> 45.953 | L28: 123.627 | M28: 165.934 | N28: Verified | O28: 10-K｜is.pretax.*；FY27Q1：q.pretax.fy27q1
A29: 所得稅 | I29: 9.324 | K29: =I29 -> 9.324 | L29: 21.795 | M29: 32.185 | N29: Verified | O29: 10-K｜is.tax.*；FY27Q1：q.tax.fy27q1
A30: 其中：OpenAI 等持股損益（公司非 GAAP 調節；FY27Q1 為稅前 OpenAI 淨利得） | I30: 0.272 | K30: =I30 -> 0.272 | L30: -4.763 | M30: 6.53 | N30: Verified | O30: 10-K｜is.openaiGain.*；FY27Q1：q.openaiGain.fy27q1
A31: 稀釋加權股數（十億股） | I31: 7.446 | K31: =I31 -> 7.446 | L31: 7.465 | M31: 7.453 | N31: Verified | O31: 10-K｜is.sharesDilW.*；FY27Q1：q.sharesDilW.fy27q1
A32: 稀釋 EPS（US$） | I32: 4.92 | K32: =I32 -> 4.92 | L32: 13.64 | M32: 17.95 | N32: Verified | O32: 10-K｜is.epsDil.*；FY27Q1：q.epsDil.fy27q1
A33: 檢查：營業利益＋業外 − 稅前；稅前 − 稅 − 淨利（年度與 FY27Q1，應為 0） | I33: =(I23+I27-I28)+(I28-I29-I26) -> 0 | L33: =(L23+L27-L28)+(L28-L29-L26) -> 0 | M33: =(M23+M27-M28)+(M28-M29-M26) -> 0 | N33: 核對
A34: 4. 現金流量（各季為新聞稿單季值；資本支出為現金 PP&E）
A35: 營業現金流 | B35: 22.291 | C35: 37.044 | D35: 42.647 | E35: 45.057 | F35: 35.758 | G35: 46.679 | H35: 55.441 | I35: 58 | J35: =SUM(E35:H35) -> 182.935 | K35: =I35 -> 58 | L35: 136.162 | M35: 182.935 | N35: Verified | O35: 新聞稿現金流量表｜q.cf.ocf.*
A36: 資本支出（現金 PP&E，正值） | B36: 15.804 | C36: 16.745 | D36: 17.079 | E36: 19.394 | F36: 29.876 | G36: 30.876 | H36: 35.802 | I36: 39.367 | J36: =SUM(E36:H36) -> 115.948 | K36: =I36 -> 39.367 | L36: 64.551 | M36: 115.948 | N36: Verified | O36: 新聞稿現金流量表｜q.cf.capex.*
A37: 自由現金流（營業現金流 − 現金資本支出） | B37: =B35-B36 -> 6.487 | C37: =C35-C36 -> 20.299 | D37: =D35-D36 -> 25.568 | E37: =E35-E36 -> 25.663 | F37: =F35-F36 -> 5.882 | G37: =G35-G36 -> 15.803 | H37: =H35-H36 -> 19.639 | I37: =I35-I36 -> 18.633 | J37: =SUM(E37:H37) -> 66.987 | K37: =I37 -> 18.633 | L37: =L35-L36 -> 71.611 | M37: =M35-M36 -> 66.987 | N37: Derived
A38: 折舊、攤銷及其他（現金流量表） | B38: 5.667 | C38: 7.734 | D38: 9.317 | E38: 8.147 | F38: 9.198 | G38: 10.167 | H38: 11.022 | I38: 11.744 | J38: =SUM(E38:H38) -> 38.534 | K38: =I38 -> 11.744 | L38: 29.433 | M38: 38.534 | N38: Verified | O38: 新聞稿現金流量表｜q.cf.da.*（Q1 由年初至今推得）
A39: 股票薪酬 | B39: 3.089 | C39: 2.98 | D39: 3.073 | E39: 2.983 | F39: 3.219 | G39: 3.081 | H39: 3.122 | I39: 3.134 | J39: =SUM(E39:H39) -> 12.405 | K39: =I39 -> 3.134 | L39: 11.974 | M39: 12.405 | N39: Verified | O39: 新聞稿現金流量表｜q.cf.sbc.*
A40: 回購（正值） | B40: 4.986 | C40: 4.781 | D40: 4.546 | E40: 5.65 | F40: 7.415 | G40: 4.627 | H40: 4.579 | I40: 4.379 | J40: =SUM(E40:H40) -> 22.271 | K40: =I40 -> 4.379 | L40: 18.42 | M40: 22.271 | N40: Verified | O40: 新聞稿現金流量表｜q.cf.buyback.*
A41: 股利（正值） | B41: 6.17 | C41: 6.169 | D41: 6.169 | E41: 6.169 | F41: 6.762 | G41: 6.756 | H41: 6.758 | I41: 6.757 | J41: =SUM(E41:H41) -> 26.445 | K41: =I41 -> 6.757 | L41: 24.082 | M41: 26.445 | N41: Verified | O41: 新聞稿現金流量表｜q.cf.div.*
A42: 營運資產與負債變動（九項合計） | E42: -0.218 | I42: 2.115 | K42: =I42 -> 2.115 | M42: -4.895 | N42: Interested-party | O42: 新聞稿現金流量表｜q.cf.wc.fy26q1、q.cf.wc.fy27q1；FY2026：cf.wc.total.fy2026
A43: 資本支出（公司口徑：含融資租賃，法說值） | B43: 22.6 | C43: 21.4 | D43: 24.2 | E43: 34.9 | F43: 37.5 | G43: 31.9 | H43: 41 | I43: 45.2 | J43: =SUM(E43:H43) -> 145.3 | K43: =I43 -> 45.2 | M43: 145.3 | N43: Interested-party | O43: 法說／IR 財務報表 CapEx 工作表｜capexFL.*（公司口徑≠現金＋融資租賃）
A44: 融資租賃本金（正值） | I44: 1 | K44: =I44 -> 1 | L44: 2.283 | M44: 3.101 | N44: Verified | O44: 10-K 附註 13｜lease.finPrincipal.*；FY27Q1：10-Q 附註 12 q.cf.flPrincipal.fy27q1
A45: 檢查：FY2026 四季合計 − 公司年度值（以上各列絕對值合計） | J45: =SUMPRODUCT(ABS(J5:J23-M5:M23))+ABS(J26-M26)+SUMPRODUCT(ABS(J35:J41-M35:M41))+ABS(J43-M43) -> 0 | N45: 核對
A46: 5. 對照：舊三分部（FY2026 以前口徑；10-K／各季新聞稿；FY27Q1 起不再揭露）與 Azure 年增
A47: Productivity and Business Processes（舊） 營收 | B47: 29.437 | C47: 29.944 | D47: 33.112 | E47: 33.02 | F47: 34.116 | G47: 35.013 | H47: 37.847 | J47: =SUM(E47:H47) -> 139.996 | L47: 120.81 | M47: 139.996 | N47: Verified | O47: 10-K／新聞稿｜q.seg.pbp.rev.*
A48: Intelligent Cloud（舊） 營收 | B48: 25.544 | C48: 26.751 | D48: 29.878 | E48: 30.897 | F48: 32.907 | G48: 34.681 | H48: 39.306 | J48: =SUM(E48:H48) -> 137.791 | L48: 106.265 | M48: 137.791 | N48: Verified | O48: 10-K／新聞稿｜q.seg.ic.rev.*
A49: More Personal Computing（舊） 營收 | B49: 14.651 | C49: 13.371 | D49: 13.451 | E49: 13.756 | F49: 14.25 | G49: 13.192 | H49: 12.854 | J49: =SUM(E49:H49) -> 54.052 | L49: 54.649 | M49: 54.052 | N49: Verified | O49: 10-K／新聞稿｜q.seg.mpc.rev.*
A50: 檢查：舊三分部合計 − 合併營收（FY2026 以前） | B50: =B47+B48+B49-B18 -> 0 | C50: =C47+C48+C49-C18 -> 0 | D50: =D47+D48+D49-D18 -> 0 | E50: =E47+E48+E49-E18 -> 0 | F50: =F47+F48+F49-F18 -> 0 | G50: =G47+G48+G49-G18 -> 0 | H50: =H47+H48+H49-H18 -> 0 | J50: =J47+J48+J49-J18 -> 0 | L50: =L47+L48+L49-L18 -> 0 | M50: =M47+M48+M49-M18 -> 0 | N50: 核對
A51: Azure 年增（重編口徑，公司揭露） | E51: 0.4 | F51: 0.39 | G51: 0.4 | H51: 0.42 | I51: 0.48 | N51: Interested-party | O51: 8-K 2026-09-02 Investor Metrics｜q.azure27.growth.*；FY27Q1 新聞稿

Sheet Thesis
A1: Thesis — 命題模組：AI 在役 MW → Azure AI 營收（MW × Tokenomics 每 MW 持有成本 × k）；AI 資本支出（MW × Tokenomics 每 MW 成本）→ AI 折舊與營運成本 → Agents and Infra 營業利益；AI 增量 ROIC 對 WACC
A2: 三情境的 MW 路徑相同（資本支出依公司指引），差在變現：k（長約／現貨組合）與 Copilot 座席。命題模組只驅動 Azure 的「Azure AI」子列與 M365 cloud 的「Copilot」子列，不取代官方分部
A3: 核心問題的答案列：「AI 增量 ROIC − WACC」（FY2029 欄）
A4: 情境 A（樂觀）｜命題模組（Thesis）
A5: 項目 | B5: 單位 | C5: FY2024A | D5: FY2025A | E5: FY2026A | F5: FY2027 | G5: FY2028 | H5: FY2029 | I5: FY2030 | J5: FY2031 | K5: FY2032 | L5: 說明
A6: 會計年度（數值；公式以「年度 − base_fy」計年數） | B6: 年 | C6: 2024 | D6: 2025 | E6: 2026 | F6: 2027 | G6: 2028 | H6: 2029 | I6: 2030 | J6: 2031 | K6: 2032
A7: 在役對外 AI MW 每年新增 | B7: MW | F7: =pace -> 2726.5351 | G7: =pace -> 2726.5351 | H7: =pace -> 2726.5351 | I7: =pace+(g_tv*Thesis!H8-pace)*MIN(1,(Thesis!I6-pace_y0)/(pace_y1-pace_y0)) -> 1931.9861 | J7: =pace+(g_tv*Thesis!I8-pace)*MIN(1,(Thesis!J6-pace_y0)/(pace_y1-pace_y0)) -> 1176.0769 | K7: =pace+(g_tv*Thesis!J8-pace)*MIN(1,(Thesis!K6-pace_y0)/(pace_y1-pace_y0)) -> 436.13005 | L7: FY2029 以前＝依資本支出指引的速度；之後逐年線性收斂到 g_tv × 前一年在役 MW，FY2032 的在役 MW 年增＝g（修正二 F5）
A8: 在役對外 AI MW（年底，含租用） | B8: MW | C8: =mw_ext_24 -> 640 | D8: =mw_ext_25 -> 1630 | E8: =mw_ext_26 -> 3250 | F8: =Thesis!E8+Thesis!F7 -> 5976.5351 | G8: =Thesis!F8+Thesis!G7 -> 8703.0702 | H8: =Thesis!G8+Thesis!H7 -> 11429.605 | I8: =Thesis!H8+Thesis!I7 -> 13361.591 | J8: =Thesis!I8+Thesis!J7 -> 14537.668 | K8: =Thesis!J8+Thesis!K7 -> 14973.798 | L8: 三情境速度相同（變現驅動不同）
A9: 其中租用 neocloud 的對外 MW | B9: MW | C9: =rent_ext_24 -> 150 | D9: =rent_ext_25 -> 400 | E9: =rent_ext_26 -> 550 | F9: =rent_ext_f -> 756 | G9: =rent_ext_f -> 756 | H9: =rent_ext_f -> 756 | I9: =rent_ext_f -> 756 | J9: =rent_ext_f -> 756 | K9: =rent_ext_f -> 756 | L9: 收入照算，不計資本支出與折舊（C20）
A10: 自有對外 MW | B10: MW | C10: =Thesis!C8-Thesis!C9 -> 490 | D10: =Thesis!D8-Thesis!D9 -> 1230 | E10: =Thesis!E8-Thesis!E9 -> 2700 | F10: =Thesis!F8-Thesis!F9 -> 5220.5351 | G10: =Thesis!G8-Thesis!G9 -> 7947.0702 | H10: =Thesis!H8-Thesis!H9 -> 10673.605 | I10: =Thesis!I8-Thesis!I9 -> 12605.591 | J10: =Thesis!J8-Thesis!J9 -> 13781.668 | K10: =Thesis!K8-Thesis!K9 -> 14217.798
A11: 自有 AI MW（對外 ÷ 對外比例） | B11: MW | C11: =Thesis!C10/ext_sh -> 816.66667 | D11: =Thesis!D10/ext_sh -> 2050 | E11: =Thesis!E10/ext_sh -> 4500 | F11: =Thesis!F10/ext_sh -> 8700.8918 | G11: =Thesis!G10/ext_sh -> 13245.117 | H11: =Thesis!H10/ext_sh -> 17789.342 | I11: =Thesis!I10/ext_sh -> 21009.319 | J11: =Thesis!J10/ext_sh -> 22969.447 | K11: =Thesis!K10/ext_sh -> 23696.331 | L11: 含自用（M365／GitHub Copilot、MAI 研發）
A12: 其中自用 AI MW | B12: MW | C12: =Thesis!C11-Thesis!C10 -> 326.66667 | D12: =Thesis!D11-Thesis!D10 -> 820 | E12: =Thesis!E11-Thesis!E10 -> 1800 | F12: =Thesis!F11-Thesis!F10 -> 3480.3567 | G12: =Thesis!G11-Thesis!G10 -> 5298.0468 | H12: =Thesis!H11-Thesis!H10 -> 7115.7369 | I12: =Thesis!I11-Thesis!I10 -> 8403.7276 | J12: =Thesis!J11-Thesis!J10 -> 9187.7789 | K12: =Thesis!K11-Thesis!K10 -> 9478.5322
A13: 自有 AI MW 新增（FY2024 欄含以前全部） | B13: MW | C13: =Thesis!C11 -> 816.66667 | D13: =Thesis!D11-Thesis!C11 -> 1233.3333 | E13: =Thesis!E11-Thesis!D11 -> 2450 | F13: =Thesis!F11-Thesis!E11 -> 4200.8918 | G13: =Thesis!G11-Thesis!F11 -> 4544.2252 | H13: =Thesis!H11-Thesis!G11 -> 4544.2252 | I13: =Thesis!I11-Thesis!H11 -> 3219.9769 | J13: =Thesis!J11-Thesis!I11 -> 1960.1281 | K13: =Thesis!K11-Thesis!J11 -> 726.88341
A14: 在役對外 MW 新增 | B14: MW | D14: =Thesis!D8-Thesis!C8 -> 990 | E14: =Thesis!E8-Thesis!D8 -> 1620 | F14: =Thesis!F8-Thesis!E8 -> 2726.5351 | G14: =Thesis!G8-Thesis!F8 -> 2726.5351 | H14: =Thesis!H8-Thesis!G8 -> 2726.5351 | I14: =Thesis!I8-Thesis!H8 -> 1931.9861 | J14: =Thesis!J8-Thesis!I8 -> 1176.0769 | K14: =Thesis!K8-Thesis!J8 -> 436.13005
A15: 其中汰換為新世代的對外 MW（汰換 MW × 對外比例） | B15: MW | F15: =Thesis!F34*ext_sh -> 0 | G15: =Thesis!G34*ext_sh -> 0 | H15: =Thesis!H34*ext_sh -> 0 | I15: =Thesis!I34*ext_sh -> 490 | J15: =Thesis!J34*ext_sh -> 740 | K15: =Thesis!K34*ext_sh -> 1470 | L15: 修正一：汰換時在役世代占比同步更新（舊世代依期初占比移出、新世代依當年新增占比移入）
A16: 在役對外 MW：Hopper | B16: MW | C16: =mix_h*Thesis!C8 -> 128 | D16: =mix_h*Thesis!D8 -> 326 | E16: =mix_h*Thesis!E8 -> 650 | F16: =Thesis!E16-Thesis!F15*mix_h -> 650 | G16: =Thesis!F16-Thesis!G15*mix_h -> 650 | H16: =Thesis!G16-Thesis!H15*mix_h -> 650 | I16: =Thesis!H16-Thesis!I15*mix_h -> 552 | J16: =Thesis!I16-Thesis!J15*mix_h -> 404 | K16: =Thesis!J16-Thesis!K15*mix_h -> 110
A17: 在役對外 MW：GB200 | B17: MW | C17: =mix_g2*Thesis!C8 -> 288 | D17: =mix_g2*Thesis!D8 -> 733.5 | E17: =mix_g2*Thesis!E8 -> 1462.5 | F17: =Thesis!E17-Thesis!F15*mix_g2 -> 1462.5 | G17: =Thesis!F17-Thesis!G15*mix_g2 -> 1462.5 | H17: =Thesis!G17-Thesis!H15*mix_g2 -> 1462.5 | I17: =Thesis!H17-Thesis!I15*mix_g2 -> 1242 | J17: =Thesis!I17-Thesis!J15*mix_g2 -> 909 | K17: =Thesis!J17-Thesis!K15*mix_g2 -> 247.5
A18: 在役對外 MW：GB300（nonnv＝0 時含 Maia 200） | B18: MW | C18: =mix_g3*Thesis!C8 -> 224 | D18: =mix_g3*Thesis!D8 -> 570.5 | E18: =mix_g3*Thesis!E8 -> 1137.5 | F18: =Thesis!E18+(Thesis!F14+Thesis!F15)*(a_g3_27-nonnv*a_mai)-Thesis!F15*mix_g3 -> 2773.4211 | G18: =Thesis!F18+(Thesis!G14+Thesis!G15)*(a_g3_28-nonnv*a_mai)-Thesis!G15*mix_g3 -> 3318.7281 | H18: =Thesis!G18+(Thesis!H14+Thesis!H15)*(a_g3_29-nonnv*a_mai)-Thesis!H15*mix_g3 -> 3318.7281 | I18: =Thesis!H18+(Thesis!I14+Thesis!I15)*(a_g3_29-nonnv*a_mai)-Thesis!I15*mix_g3 -> 3147.2281 | J18: =Thesis!I18+(Thesis!J14+Thesis!J15)*(a_g3_29-nonnv*a_mai)-Thesis!J15*mix_g3 -> 2888.2281 | K18: =Thesis!J18+(Thesis!K14+Thesis!K15)*(a_g3_29-nonnv*a_mai)-Thesis!K15*mix_g3 -> 2373.7281
A19: 在役對外 MW：Maia 200（nonnv＝1；Tokenomics IF_NonNV_*） | B19: MW | C19: 0 | D19: 0 | E19: 0 | F19: =Thesis!E19+(Thesis!F14+Thesis!F15)*nonnv*a_mai -> 272.65351 | G19: =Thesis!F19+(Thesis!G14+Thesis!G15)*nonnv*a_mai -> 545.30702 | H19: =Thesis!G19+(Thesis!H14+Thesis!H15)*nonnv*a_mai -> 817.96053 | I19: =Thesis!H19+(Thesis!I14+Thesis!I15)*nonnv*a_mai -> 1060.1591 | J19: =Thesis!I19+(Thesis!J14+Thesis!J15)*nonnv*a_mai -> 1251.7668 | K19: =Thesis!J19+(Thesis!K14+Thesis!K15)*nonnv*a_mai -> 1442.3798 | L19: v0.3.1：Maia 改讀 Tokenomics 產出比與持有成本比（÷ VR200）；v0.3 以 GB300 × 1.0 計
A20: 在役對外 MW：VR200 | B20: MW | C20: 0 | D20: 0 | E20: 0 | F20: =Thesis!E20+(Thesis!F14+Thesis!F15)*(1-a_g3_27) -> 817.96053 | G20: =Thesis!F20+(Thesis!G14+Thesis!G15)*(1-a_g3_28) -> 2726.5351 | H20: =Thesis!G20+(Thesis!H14+Thesis!H15)*(1-a_g3_29) -> 5180.4167 | I20: =Thesis!H20+(Thesis!I14+Thesis!I15)*(1-a_g3_29) -> 7360.2042 | J20: =Thesis!I20+(Thesis!J14+Thesis!J15)*(1-a_g3_29) -> 9084.6734 | K20: =Thesis!J20+(Thesis!K14+Thesis!K15)*(1-a_g3_29) -> 10800.19
A21: 在役世代加權持有成本（IF_HoldEcon；Maia＝持有成本比 × VR200） | B21: US$M/MW-年 | C21: =(Thesis!C16*tk_hold_h100+Thesis!C17*tk_hold_gb200+Thesis!C18*tk_hold_gb300+Thesis!C20*tk_hold_vr200+Thesis!C19*nv_hold_mai*tk_hold_vr200)/Thesis!C8 -> 9.7235358 | D21: =(Thesis!D16*tk_hold_h100+Thesis!D17*tk_hold_gb200+Thesis!D18*tk_hold_gb300+Thesis!D20*tk_hold_vr200+Thesis!D19*nv_hold_mai*tk_hold_vr200)/Thesis!D8 -> 9.7235358 | E21: =(Thesis!E16*tk_hold_h100+Thesis!E17*tk_hold_gb200+Thesis!E18*tk_hold_gb300+Thesis!E20*tk_hold_vr200+Thesis!E19*nv_hold_mai*tk_hold_vr200)/Thesis!E8 -> 9.7235358 | F21: =(Thesis!F16*tk_hold_h100+Thesis!F17*tk_hold_gb200+Thesis!F18*tk_hold_gb300+Thesis!F20*tk_hold_vr200+Thesis!F19*nv_hold_mai*tk_hold_vr200)/Thesis!F8 -> 10.219535 | G21: =(Thesis!G16*tk_hold_h100+Thesis!G17*tk_hold_gb200+Thesis!G18*tk_hold_gb300+Thesis!G20*tk_hold_vr200+Thesis!G19*nv_hold_mai*tk_hold_vr200)/Thesis!G8 -> 10.57256 | H21: =(Thesis!H16*tk_hold_h100+Thesis!H17*tk_hold_gb200+Thesis!H18*tk_hold_gb300+Thesis!H20*tk_hold_vr200+Thesis!H19*nv_hold_mai*tk_hold_vr200)/Thesis!H8 -> 10.821043 | I21: =(Thesis!I16*tk_hold_h100+Thesis!I17*tk_hold_gb200+Thesis!I18*tk_hold_gb300+Thesis!I20*tk_hold_vr200+Thesis!I19*nv_hold_mai*tk_hold_vr200)/Thesis!I8 -> 11.005062 | J21: =(Thesis!J16*tk_hold_h100+Thesis!J17*tk_hold_gb200+Thesis!J18*tk_hold_gb300+Thesis!J20*tk_hold_vr200+Thesis!J19*nv_hold_mai*tk_hold_vr200)/Thesis!J8 -> 11.150579 | K21: =(Thesis!K16*tk_hold_h100+Thesis!K17*tk_hold_gb200+Thesis!K18*tk_hold_gb300+Thesis!K20*tk_hold_vr200+Thesis!K19*nv_hold_mai*tk_hold_vr200)/Thesis!K8 -> 11.349691 | L21: 影子效益（k＝1）用此成本口徑
A22: 在役世代加權收入錨（IF_HoldEcon；Maia＝產出比 × VR200） | B22: US$M/MW-年 | C22: =(Thesis!C16*tk_hold_h100+Thesis!C17*tk_hold_gb200+Thesis!C18*tk_hold_gb300+Thesis!C20*tk_hold_vr200+Thesis!C19*nv_out_mai*tk_hold_vr200)/Thesis!C8 -> 9.7235358 | D22: =(Thesis!D16*tk_hold_h100+Thesis!D17*tk_hold_gb200+Thesis!D18*tk_hold_gb300+Thesis!D20*tk_hold_vr200+Thesis!D19*nv_out_mai*tk_hold_vr200)/Thesis!D8 -> 9.7235358 | E22: =(Thesis!E16*tk_hold_h100+Thesis!E17*tk_hold_gb200+Thesis!E18*tk_hold_gb300+Thesis!E20*tk_hold_vr200+Thesis!E19*nv_out_mai*tk_hold_vr200)/Thesis!E8 -> 9.7235358 | F22: =(Thesis!F16*tk_hold_h100+Thesis!F17*tk_hold_gb200+Thesis!F18*tk_hold_gb300+Thesis!F20*tk_hold_vr200+Thesis!F19*nv_out_mai*tk_hold_vr200)/Thesis!F8 -> 10.247422 | G22: =(Thesis!G16*tk_hold_h100+Thesis!G17*tk_hold_gb200+Thesis!G18*tk_hold_gb300+Thesis!G20*tk_hold_vr200+Thesis!G19*nv_out_mai*tk_hold_vr200)/Thesis!G8 -> 10.61086 | H22: =(Thesis!H16*tk_hold_h100+Thesis!H17*tk_hold_gb200+Thesis!H18*tk_hold_gb300+Thesis!H20*tk_hold_vr200+Thesis!H19*nv_out_mai*tk_hold_vr200)/Thesis!H8 -> 10.864789 | I22: =(Thesis!I16*tk_hold_h100+Thesis!I17*tk_hold_gb200+Thesis!I18*tk_hold_gb300+Thesis!I20*tk_hold_vr200+Thesis!I19*nv_out_mai*tk_hold_vr200)/Thesis!I8 -> 11.053563 | J22: =(Thesis!J16*tk_hold_h100+Thesis!J17*tk_hold_gb200+Thesis!J18*tk_hold_gb300+Thesis!J20*tk_hold_vr200+Thesis!J19*nv_out_mai*tk_hold_vr200)/Thesis!J8 -> 11.203213 | K22: =(Thesis!K16*tk_hold_h100+Thesis!K17*tk_hold_gb200+Thesis!K18*tk_hold_gb300+Thesis!K20*tk_hold_vr200+Thesis!K19*nv_out_mai*tk_hold_vr200)/Thesis!K8 -> 11.408574 | L22: nonnv＝0 時與持有成本列相同
A23: k（長約占比 × k_長約＋其餘 × k_現貨） | B23: x | C23: =k_B -> 1.1721393 | D23: =k_B -> 1.1721393 | E23: =k_B -> 1.1721393 | F23: =(k_B+((ls_A*k_long+(1-ls_A)*k_spot)-k_B)*MIN(1,(Thesis!F6-base_fy)/k_ramp)) -> 1.2502283 | G23: =(k_B+((ls_A*k_long+(1-ls_A)*k_spot)-k_B)*MIN(1,(Thesis!G6-base_fy)/k_ramp)) -> 1.3283172 | H23: =(k_B+((ls_A*k_long+(1-ls_A)*k_spot)-k_B)*MIN(1,(Thesis!H6-base_fy)/k_ramp)) -> 1.4064062 | I23: =(k_B+((ls_A*k_long+(1-ls_A)*k_spot)-k_B)*MIN(1,(Thesis!I6-base_fy)/k_ramp)) -> 1.4064062 | J23: =(k_B+((ls_A*k_long+(1-ls_A)*k_spot)-k_B)*MIN(1,(Thesis!J6-base_fy)/k_ramp)) -> 1.4064062 | K23: =(k_B+((ls_A*k_long+(1-ls_A)*k_spot)-k_B)*MIN(1,(Thesis!K6-base_fy)/k_ramp)) -> 1.4064062 | L23: 實績期三情境同用基準 k（拆分是估計，不是情境）；FY2027 起 k_ramp 年線性移到情境 k
A24: 每 MW 年收入（對外） | B24: US$M/MW-年 | C24: =Thesis!C22*Thesis!C23*chip_f -> 11.397339 | D24: =Thesis!D22*Thesis!D23*chip_f -> 11.397339 | E24: =Thesis!E22*Thesis!E23*chip_f -> 11.397339 | F24: =Thesis!F22*Thesis!F23*chip_f -> 12.811617 | G24: =Thesis!G22*Thesis!G23*chip_f -> 14.094589 | H24: =Thesis!H22*Thesis!H23*chip_f -> 15.280306 | I24: =Thesis!I22*Thesis!I23*chip_f -> 15.545799 | J24: =Thesis!J22*Thesis!J23*chip_f -> 15.756268 | K24: =Thesis!K22*Thesis!K23*chip_f -> 16.045089 | L24: 按 MW-year 計價，不乘利用率（v0.2.2 口徑）
A25: Azure AI 營收（期間平均在役對外 MW × 每 MW 年收入） | B25: US$B | D25: =(Thesis!C8+Thesis!D8)/2*Thesis!D24/1000 -> 12.935979 | E25: =(Thesis!D8+Thesis!E8)/2*Thesis!E24/1000 -> 27.809506 | F25: =(Thesis!E8+Thesis!F8)/2*Thesis!F24/1000 -> 59.103417 | G25: =(Thesis!F8+Thesis!G8)/2*Thesis!G24/1000 -> 103.4515 | H25: =(Thesis!G8+Thesis!H8)/2*Thesis!H24/1000 -> 153.81672 | I25: =(Thesis!H8+Thesis!I8)/2*Thesis!I24/1000 -> 192.69948 | J25: =(Thesis!I8+Thesis!J8)/2*Thesis!J24/1000 -> 219.7941 | K25: =(Thesis!J8+Thesis!K8)/2*Thesis!K24/1000 -> 236.75705 | L25: FY2025、FY2026 為模型估計（用於拆出 Azure 其他）
A26: 在役世代加權 IF_OpexGW | B26: US$M/MW-年 | C26: =(Thesis!C16*tk_opex_h100+Thesis!C17*tk_opex_gb200+Thesis!C18*tk_opex_gb300+(Thesis!C20+Thesis!C19)*tk_opex_vr200)/Thesis!C8 -> 1.8863604 | D26: =(Thesis!D16*tk_opex_h100+Thesis!D17*tk_opex_gb200+Thesis!D18*tk_opex_gb300+(Thesis!D20+Thesis!D19)*tk_opex_vr200)/Thesis!D8 -> 1.8863604 | E26: =(Thesis!E16*tk_opex_h100+Thesis!E17*tk_opex_gb200+Thesis!E18*tk_opex_gb300+(Thesis!E20+Thesis!E19)*tk_opex_vr200)/Thesis!E8 -> 1.8863604 | F26: =(Thesis!F16*tk_opex_h100+Thesis!F17*tk_opex_gb200+Thesis!F18*tk_opex_gb300+(Thesis!F20+Thesis!F19)*tk_opex_vr200)/Thesis!F8 -> 1.9505116 | G26: =(Thesis!G16*tk_opex_h100+Thesis!G17*tk_opex_gb200+Thesis!G18*tk_opex_gb300+(Thesis!G20+Thesis!G19)*tk_opex_vr200)/Thesis!G8 -> 1.98836 | H26: =(Thesis!H16*tk_opex_h100+Thesis!H17*tk_opex_gb200+Thesis!H18*tk_opex_gb300+(Thesis!H20+Thesis!H19)*tk_opex_vr200)/Thesis!H8 -> 2.0134401 | I26: =(Thesis!I16*tk_opex_h100+Thesis!I17*tk_opex_gb200+Thesis!I18*tk_opex_gb300+(Thesis!I20+Thesis!I19)*tk_opex_vr200)/Thesis!I8 -> 2.0326117 | J26: =(Thesis!J16*tk_opex_h100+Thesis!J17*tk_opex_gb200+Thesis!J18*tk_opex_gb300+(Thesis!J20+Thesis!J19)*tk_opex_vr200)/Thesis!J8 -> 2.0480807 | K26: =(Thesis!K16*tk_opex_h100+Thesis!K17*tk_opex_gb200+Thesis!K18*tk_opex_gb300+(Thesis!K20+Thesis!K19)*tk_opex_vr200)/Thesis!K8 -> 2.0697383 | L26: Maia 的每 MW 營運成本以 VR200 計（電力相同；Assumed）
A27: AI 營運成本：自有 AI MW（平均 × IF_OpexGW） | B27: US$B | D27: =(Thesis!C11+Thesis!D11)/2*Thesis!D26/1000 -> 2.7037833 | E27: =(Thesis!D11+Thesis!E11)/2*Thesis!E26/1000 -> 6.1778304 | F27: =(Thesis!E11+Thesis!F11)/2*Thesis!F26/1000 -> 12.874246 | G27: =(Thesis!F11+Thesis!G11)/2*Thesis!G26/1000 -> 21.818283 | H27: =(Thesis!G11+Thesis!H11)/2*Thesis!H26/1000 -> 31.243013 | I27: =(Thesis!H11+Thesis!I11)/2*Thesis!I26/1000 -> 39.431306 | J27: =(Thesis!I11+Thesis!J11)/2*Thesis!J26/1000 -> 45.036032 | K27: =(Thesis!J11+Thesis!K11)/2*Thesis!K26/1000 -> 48.292973
A28: AI 營運成本：租用 neocloud 租金 | B28: US$B | D28: =(Thesis!C9+Thesis!D9)/2*rent_mw/1000 -> 2.44475 | E28: =(Thesis!D9+Thesis!E9)/2*rent_mw/1000 -> 4.22275 | F28: =(Thesis!E9+Thesis!F9)/2*rent_mw/1000 -> 5.80517 | G28: =(Thesis!F9+Thesis!G9)/2*rent_mw/1000 -> 6.72084 | H28: =(Thesis!G9+Thesis!H9)/2*rent_mw/1000 -> 6.72084 | I28: =(Thesis!H9+Thesis!I9)/2*rent_mw/1000 -> 6.72084 | J28: =(Thesis!I9+Thesis!J9)/2*rent_mw/1000 -> 6.72084 | K28: =(Thesis!J9+Thesis!K9)/2*rent_mw/1000 -> 6.72084
A29: AI 營運成本：租用機房租金（1 − 自建比例） | B29: US$B | D29: =(Thesis!C11+Thesis!D11)/2*(1-self_build)*fac_rent/1000 -> 0.85324238 | E29: =(Thesis!D11+Thesis!E11)/2*(1-self_build)*fac_rent/1000 -> 1.9495596 | F29: =(Thesis!E11+Thesis!F11)/2*(1-self_build)*fac_rent/1000 -> 3.9291489 | G29: =(Thesis!F11+Thesis!G11)/2*(1-self_build)*fac_rent/1000 -> 6.5320691 | H29: =(Thesis!G11+Thesis!H11)/2*(1-self_build)*fac_rent/1000 -> 9.2371799 | I29: =(Thesis!H11+Thesis!I11)/2*(1-self_build)*fac_rent/1000 -> 11.548138 | J29: =(Thesis!I11+Thesis!J11)/2*(1-self_build)*fac_rent/1000 -> 13.089958 | K29: =(Thesis!J11+Thesis!K11)/2*(1-self_build)*fac_rent/1000 -> 13.889728 | L29: C22
A30: 自有 AI 中對外的比重（期間平均） | B30: % | D30: =(Thesis!C10+Thesis!D10)/(Thesis!C11+Thesis!D11) -> 0.6 | E30: =(Thesis!D10+Thesis!E10)/(Thesis!D11+Thesis!E11) -> 0.6 | F30: =(Thesis!E10+Thesis!F10)/(Thesis!E11+Thesis!F11) -> 0.6 | G30: =(Thesis!F10+Thesis!G10)/(Thesis!F11+Thesis!G11) -> 0.6 | H30: =(Thesis!G10+Thesis!H10)/(Thesis!G11+Thesis!H11) -> 0.6 | I30: =(Thesis!H10+Thesis!I10)/(Thesis!H11+Thesis!I11) -> 0.6 | J30: =(Thesis!I10+Thesis!J10)/(Thesis!I11+Thesis!J11) -> 0.6 | K30: =(Thesis!J10+Thesis!K10)/(Thesis!J11+Thesis!K11) -> 0.6
A31: Azure AI EBITDA（營收 − 對外營運成本 − 租金） | B31: US$B | D31: =Thesis!D25-Thesis!D30*(Thesis!D27+Thesis!D29)-Thesis!D28 -> 8.3570141 | E31: =Thesis!E25-Thesis!E30*(Thesis!E27+Thesis!E29)-Thesis!E28 -> 18.710322 | F31: =Thesis!F25-Thesis!F30*(Thesis!F27+Thesis!F29)-Thesis!F28 -> 43.216209 | G31: =Thesis!G25-Thesis!G30*(Thesis!G27+Thesis!G29)-Thesis!G28 -> 79.720447 | H31: =Thesis!H25-Thesis!H30*(Thesis!H27+Thesis!H29)-Thesis!H28 -> 122.80776 | I31: =Thesis!I25-Thesis!I30*(Thesis!I27+Thesis!I29)-Thesis!I28 -> 155.39097 | J31: =Thesis!J25-Thesis!J30*(Thesis!J27+Thesis!J29)-Thesis!J28 -> 178.19767 | K31: =Thesis!K25-Thesis!K30*(Thesis!K27+Thesis!K29)-Thesis!K28 -> 192.72659
A32: 自用 AI 營運成本（服務 Copilot 等自有產品） | B32: US$B | D32: =(1-Thesis!D30)*(Thesis!D27+Thesis!D29) -> 1.4228103 | E32: =(1-Thesis!E30)*(Thesis!E27+Thesis!E29) -> 3.250956 | F32: =(1-Thesis!F30)*(Thesis!F27+Thesis!F29) -> 6.7213581 | G32: =(1-Thesis!G30)*(Thesis!G27+Thesis!G29) -> 11.340141 | H32: =(1-Thesis!H30)*(Thesis!H27+Thesis!H29) -> 16.192077 | I32: =(1-Thesis!I30)*(Thesis!I27+Thesis!I29) -> 20.391777 | J32: =(1-Thesis!J30)*(Thesis!J27+Thesis!J29) -> 23.250396 | K32: =(1-Thesis!K30)*(Thesis!K27+Thesis!K29) -> 24.87308
A33: 新增與汰換 MW 的 IT 資本支出（世代加權） | B33: US$M/MW | C33: =cxit_open -> 27.5919 | D33: =cxit_open -> 27.5919 | E33: =cxit_open -> 27.5919 | F33: =((a_g3_27-nonnv*a_mai)*tk_cxit_gb300+nonnv*a_mai*nv_hold_mai*tk_cxit_vr200+(1-a_g3_27)*tk_cxit_vr200) -> 32.497558 | G33: =((a_g3_28-nonnv*a_mai)*tk_cxit_gb300+nonnv*a_mai*nv_hold_mai*tk_cxit_vr200+(1-a_g3_28)*tk_cxit_vr200) -> 34.637209 | H33: =((a_g3_29-nonnv*a_mai)*tk_cxit_gb300+nonnv*a_mai*nv_hold_mai*tk_cxit_vr200+(1-a_g3_29)*tk_cxit_vr200) -> 35.707034 | I33: =((a_g3_29-nonnv*a_mai)*tk_cxit_gb300+nonnv*a_mai*nv_hold_mai*tk_cxit_vr200+(1-a_g3_29)*tk_cxit_vr200) -> 35.707034 | J33: =((a_g3_29-nonnv*a_mai)*tk_cxit_gb300+nonnv*a_mai*nv_hold_mai*tk_cxit_vr200+(1-a_g3_29)*tk_cxit_vr200) -> 35.707034 | K33: =((a_g3_29-nonnv*a_mai)*tk_cxit_gb300+nonnv*a_mai*nv_hold_mai*tk_cxit_vr200+(1-a_g3_29)*tk_cxit_vr200) -> 35.707034 | L33: FY2026 以前用期初世代加權（估計）
A34: GPU 汰換 MW（自有 AI MW 滿 IT 年限者） | B34: MW | F34: =Thesis!C13*IF(Thesis!F6-Thesis!C6=life_it,1,0)+Thesis!D13*IF(Thesis!F6-Thesis!D6=life_it,1,0)+Thesis!E13*IF(Thesis!F6-Thesis!E6=life_it,1,0) -> 0 | G34: =Thesis!C13*IF(Thesis!G6-Thesis!C6=life_it,1,0)+Thesis!D13*IF(Thesis!G6-Thesis!D6=life_it,1,0)+Thesis!E13*IF(Thesis!G6-Thesis!E6=life_it,1,0)+Thesis!F13*IF(Thesis!G6-Thesis!F6=life_it,1,0) -> 0 | H34: =Thesis!C13*IF(Thesis!H6-Thesis!C6=life_it,1,0)+Thesis!D13*IF(Thesis!H6-Thesis!D6=life_it,1,0)+Thesis!E13*IF(Thesis!H6-Thesis!E6=life_it,1,0)+Thesis!F13*IF(Thesis!H6-Thesis!F6=life_it,1,0)+Thesis!G13*IF(Thesis!H6-Thesis!G6=life_it,1,0) -> 0 | I34: =Thesis!C13*IF(Thesis!I6-Thesis!C6=life_it,1,0)+Thesis!D13*IF(Thesis!I6-Thesis!D6=life_it,1,0)+Thesis!E13*IF(Thesis!I6-Thesis!E6=life_it,1,0)+Thesis!F13*IF(Thesis!I6-Thesis!F6=life_it,1,0)+Thesis!G13*IF(Thesis!I6-Thesis!G6=life_it,1,0)+Thesis!H13*IF(Thesis!I6-Thesis!H6=life_it,1,0) -> 816.66667 | J34: =Thesis!C13*IF(Thesis!J6-Thesis!C6=life_it,1,0)+Thesis!D13*IF(Thesis!J6-Thesis!D6=life_it,1,0)+Thesis!E13*IF(Thesis!J6-Thesis!E6=life_it,1,0)+Thesis!F13*IF(Thesis!J6-Thesis!F6=life_it,1,0)+Thesis!G13*IF(Thesis!J6-Thesis!G6=life_it,1,0)+Thesis!H13*IF(Thesis!J6-Thesis!H6=life_it,1,0)+Thesis!I13*IF(Thesis!J6-Thesis!I6=life_it,1,0) -> 1233.3333 | K34: =Thesis!C13*IF(Thesis!K6-Thesis!C6=life_it,1,0)+Thesis!D13*IF(Thesis!K6-Thesis!D6=life_it,1,0)+Thesis!E13*IF(Thesis!K6-Thesis!E6=life_it,1,0)+Thesis!F13*IF(Thesis!K6-Thesis!F6=life_it,1,0)+Thesis!G13*IF(Thesis!K6-Thesis!G6=life_it,1,0)+Thesis!H13*IF(Thesis!K6-Thesis!H6=life_it,1,0)+Thesis!I13*IF(Thesis!K6-Thesis!I6=life_it,1,0)+Thesis!J13*IF(Thesis!K6-Thesis!J6=life_it,1,0) -> 2450 | L34: 只換 IT、機房不換；FY2024 欄含 FY2024 以前全部（視同 FY2024 投入）；舊機隊在年限到期後停止折舊，汰換後的新 IT 另計折舊（不重複）
A35: AI IT 資本支出（公式） | B35: US$B | C35: =Thesis!C13*Thesis!C33/1000 -> 22.533385 | D35: =Thesis!D13*Thesis!D33/1000 -> 34.030009 | E35: =Thesis!E13*Thesis!E33/1000 -> 67.600154 | F35: =(Thesis!F13+Thesis!F34)*Thesis!F33/1000 -> 136.51872 | G35: =(Thesis!G13+Thesis!G34)*Thesis!G33/1000 -> 157.39928 | H35: =(Thesis!H13+Thesis!H34)*Thesis!H33/1000 -> 162.2608 | I35: =(Thesis!I13+Thesis!I34)*Thesis!I33/1000 -> 144.13657 | J35: =(Thesis!J13+Thesis!J34)*Thesis!J33/1000 -> 114.02904 | K35: =(Thesis!K13+Thesis!K34)*Thesis!K33/1000 -> 113.43709
A36: AI 機房資本支出（自建比例 × IF_CapexFacility） | B36: US$B | C36: =Thesis!C13*self_build*tk_cxfac/1000 -> 6.2083 | D36: =Thesis!D13*self_build*tk_cxfac/1000 -> 9.3758 | E36: =Thesis!E13*self_build*tk_cxfac/1000 -> 18.6249 | F36: =Thesis!F13*self_build*tk_cxfac/1000 -> 31.93518 | G36: =Thesis!G13*self_build*tk_cxfac/1000 -> 34.5452 | H36: =Thesis!H13*self_build*tk_cxfac/1000 -> 34.5452 | I36: =Thesis!I13*self_build*tk_cxfac/1000 -> 24.478264 | J36: =Thesis!J13*self_build*tk_cxfac/1000 -> 14.900894 | K36: =Thesis!K13*self_build*tk_cxfac/1000 -> 5.5257677
A37: C10 對帳落差：FY2027 公司指引推估 − 模型資本支出（AI IT＋AI 機房＋非 AI；正負） | B37: US$B | F37: =capex_floor27-Thesis!F35-Thesis!F36-CF!F25 -> 0.047577445 | L37: v0.3.1：基準情境以 MW 速度重解使此列 ≈ 0（A、C 情境 Azure 其他略有不同，殘差見報告）
A38: FY2027 補足到公司指引的差額（落差為正時補足） | B38: US$B | F38: =MAX(0,Thesis!F37) -> 0.047577445
A39: AI IT 資本支出 | B39: US$B | C39: =Thesis!C35 -> 22.533385 | D39: =Thesis!D35 -> 34.030009 | E39: =Thesis!E35 -> 67.600154 | F39: =Thesis!F35 -> 136.51872 | G39: =Thesis!G35 -> 157.39928 | H39: =Thesis!H35 -> 162.2608 | I39: =Thesis!I35 -> 144.13657 | J39: =Thesis!J35 -> 114.02904 | K39: =Thesis!K35 -> 113.43709
A40: AI 資本支出合計 | B40: US$B | C40: =Thesis!C39+Thesis!C36 -> 28.741685 | D40: =Thesis!D39+Thesis!D36 -> 43.405809 | E40: =Thesis!E39+Thesis!E36 -> 86.225054 | F40: =Thesis!F39+Thesis!F36 -> 168.4539 | G40: =Thesis!G39+Thesis!G36 -> 191.94448 | H40: =Thesis!H39+Thesis!H36 -> 196.806 | I40: =Thesis!I39+Thesis!I36 -> 168.61483 | J40: =Thesis!J39+Thesis!J36 -> 128.92993 | K40: =Thesis!K39+Thesis!K36 -> 118.96285 | L40: FY2026 以前為依 MW 估計的值（非公司揭露）
A41: AI IT 折舊（半年慣例、年限 life_it） | B41: US$B | E41: =(Thesis!C39*IF(2<life_it,1,IF(2=life_it,0.5,0))+Thesis!D39*IF(1<life_it,1,IF(1=life_it,0.5,0))+Thesis!E39*0.5)/life_it -> 15.060578 | F41: =(Thesis!C39*IF(3<life_it,1,IF(3=life_it,0.5,0))+Thesis!D39*IF(2<life_it,1,IF(2=life_it,0.5,0))+Thesis!E39*IF(1<life_it,1,IF(1=life_it,0.5,0))+Thesis!F39*0.5)/life_it -> 32.070485 | G41: =(Thesis!C39*IF(4<life_it,1,IF(4=life_it,0.5,0))+Thesis!D39*IF(3<life_it,1,IF(3=life_it,0.5,0))+Thesis!E39*IF(2<life_it,1,IF(2=life_it,0.5,0))+Thesis!F39*IF(1<life_it,1,IF(1=life_it,0.5,0))+Thesis!G39*0.5)/life_it -> 56.563652 | H41: =(Thesis!C39*IF(5<life_it,1,IF(5=life_it,0.5,0))+Thesis!D39*IF(4<life_it,1,IF(4=life_it,0.5,0))+Thesis!E39*IF(3<life_it,1,IF(3=life_it,0.5,0))+Thesis!F39*IF(2<life_it,1,IF(2=life_it,0.5,0))+Thesis!G39*IF(1<life_it,1,IF(1=life_it,0.5,0))+Thesis!H39*0.5)/life_it -> 83.201992 | I41: =(Thesis!C39*IF(6<life_it,1,IF(6=life_it,0.5,0))+Thesis!D39*IF(5<life_it,1,IF(5=life_it,0.5,0))+Thesis!E39*IF(4<life_it,1,IF(4=life_it,0.5,0))+Thesis!F39*IF(3<life_it,1,IF(3=life_it,0.5,0))+Thesis!G39*IF(2<life_it,1,IF(2=life_it,0.5,0))+Thesis!H39*IF(1<life_it,1,IF(1=life_it,0.5,0))+Thesis!I39*0.5)/life_it -> 106.85732 | J41: =(Thesis!C39*IF(7<life_it,1,IF(7=life_it,0.5,0))+Thesis!D39*IF(6<life_it,1,IF(6=life_it,0.5,0))+Thesis!E39*IF(5<life_it,1,IF(5=life_it,0.5,0))+Thesis!F39*IF(4<life_it,1,IF(4=life_it,0.5,0))+Thesis!G39*IF(3<life_it,1,IF(3=life_it,0.5,0))+Thesis!H39*IF(2<life_it,1,IF(2=life_it,0.5,0))+Thesis!I39*IF(1<life_it,1,IF(1=life_it,0.5,0))+Thesis!J39*0.5)/life_it -> 123.65751 | K41: =(Thesis!C39*IF(8<life_it,1,IF(8=life_it,0.5,0))+Thesis!D39*IF(7<life_it,1,IF(7=life_it,0.5,0))+Thesis!E39*IF(6<life_it,1,IF(6=life_it,0.5,0))+Thesis!F39*IF(5<life_it,1,IF(5=life_it,0.5,0))+Thesis!G39*IF(4<life_it,1,IF(4=life_it,0.5,0))+Thesis!H39*IF(3<life_it,1,IF(3=life_it,0.5,0))+Thesis!I39*IF(2<life_it,1,IF(2=life_it,0.5,0))+Thesis!J39*IF(1<life_it,1,IF(1=life_it,0.5,0))+Thesis!K39*0.5)/life_it -> 134.14384
A42: AI 機房折舊（年限 life_fac） | B42: US$B | E42: =(Thesis!C36*IF(2<life_fac,1,IF(2=life_fac,0.5,0))+Thesis!D36*IF(1<life_fac,1,IF(1=life_fac,0.5,0))+Thesis!E36*0.5)/life_fac -> 1.2448275 | F42: =(Thesis!C36*IF(3<life_fac,1,IF(3=life_fac,0.5,0))+Thesis!D36*IF(2<life_fac,1,IF(2=life_fac,0.5,0))+Thesis!E36*IF(1<life_fac,1,IF(1=life_fac,0.5,0))+Thesis!F36*0.5)/life_fac -> 2.5088295 | G42: =(Thesis!C36*IF(4<life_fac,1,IF(4=life_fac,0.5,0))+Thesis!D36*IF(3<life_fac,1,IF(3=life_fac,0.5,0))+Thesis!E36*IF(2<life_fac,1,IF(2=life_fac,0.5,0))+Thesis!F36*IF(1<life_fac,1,IF(1=life_fac,0.5,0))+Thesis!G36*0.5)/life_fac -> 4.170839 | H42: =(Thesis!C36*IF(5<life_fac,1,IF(5=life_fac,0.5,0))+Thesis!D36*IF(4<life_fac,1,IF(4=life_fac,0.5,0))+Thesis!E36*IF(3<life_fac,1,IF(3=life_fac,0.5,0))+Thesis!F36*IF(2<life_fac,1,IF(2=life_fac,0.5,0))+Thesis!G36*IF(1<life_fac,1,IF(1=life_fac,0.5,0))+Thesis!H36*0.5)/life_fac -> 5.898099 | I42: =(Thesis!C36*IF(6<life_fac,1,IF(6=life_fac,0.5,0))+Thesis!D36*IF(5<life_fac,1,IF(5=life_fac,0.5,0))+Thesis!E36*IF(4<life_fac,1,IF(4=life_fac,0.5,0))+Thesis!F36*IF(3<life_fac,1,IF(3=life_fac,0.5,0))+Thesis!G36*IF(2<life_fac,1,IF(2=life_fac,0.5,0))+Thesis!H36*IF(1<life_fac,1,IF(1=life_fac,0.5,0))+Thesis!I36*0.5)/life_fac -> 7.3736856 | J42: =(Thesis!C36*IF(7<life_fac,1,IF(7=life_fac,0.5,0))+Thesis!D36*IF(6<life_fac,1,IF(6=life_fac,0.5,0))+Thesis!E36*IF(5<life_fac,1,IF(5=life_fac,0.5,0))+Thesis!F36*IF(4<life_fac,1,IF(4=life_fac,0.5,0))+Thesis!G36*IF(3<life_fac,1,IF(3=life_fac,0.5,0))+Thesis!H36*IF(2<life_fac,1,IF(2=life_fac,0.5,0))+Thesis!I36*IF(1<life_fac,1,IF(1=life_fac,0.5,0))+Thesis!J36*0.5)/life_fac -> 8.3581645 | K42: =(Thesis!C36*IF(8<life_fac,1,IF(8=life_fac,0.5,0))+Thesis!D36*IF(7<life_fac,1,IF(7=life_fac,0.5,0))+Thesis!E36*IF(6<life_fac,1,IF(6=life_fac,0.5,0))+Thesis!F36*IF(5<life_fac,1,IF(5=life_fac,0.5,0))+Thesis!G36*IF(4<life_fac,1,IF(4=life_fac,0.5,0))+Thesis!H36*IF(3<life_fac,1,IF(3=life_fac,0.5,0))+Thesis!I36*IF(2<life_fac,1,IF(2=life_fac,0.5,0))+Thesis!J36*IF(1<life_fac,1,IF(1=life_fac,0.5,0))+Thesis!K36*0.5)/life_fac -> 8.868831
A43: AI 折舊合計（進 Agents and Infra 營業利益） | B43: US$B | E43: =Thesis!E41+Thesis!E42 -> 16.305406 | F43: =Thesis!F41+Thesis!F42 -> 34.579314 | G43: =Thesis!G41+Thesis!G42 -> 60.734491 | H43: =Thesis!H41+Thesis!H42 -> 89.100091 | I43: =Thesis!I41+Thesis!I42 -> 114.23101 | J43: =Thesis!J41+Thesis!J42 -> 132.01567 | K43: =Thesis!K41+Thesis!K42 -> 143.01267
A44: Azure AI 營業利益（EBITDA − 對外分攤折舊） | B44: US$B | E44: =Thesis!E31-Thesis!E30*Thesis!E43 -> 8.9270789 | F44: =Thesis!F31-Thesis!F30*Thesis!F43 -> 22.468621 | G44: =Thesis!G31-Thesis!G30*Thesis!G43 -> 43.279753 | H44: =Thesis!H31-Thesis!H30*Thesis!H43 -> 69.34771 | I44: =Thesis!I31-Thesis!I30*Thesis!I43 -> 86.852367 | J44: =Thesis!J31-Thesis!J30*Thesis!J43 -> 98.988265 | K44: =Thesis!K31-Thesis!K30*Thesis!K43 -> 106.91899
A45: Copilot 營收（Seg） | B45: US$B | E45: =Seg!E11 -> 5.25 | F45: =Seg!F11 -> 13.5 | G45: =Seg!G11 -> 22.5 | H45: =Seg!H11 -> 31.5 | I45: =Seg!I11 -> 38.25 | J45: =Seg!J11 -> 42.75 | K45: =Seg!K11 -> 47.25
A46: 自用 AI 影子效益（讀法 2 金額）＝MAX(0,（當年平均自用 MW − FY2026 平均自用 MW）× 持有成本（k＝1）− Copilot 增量 × 核心利益率) | B46: US$B | F46: =MAX(0,((Thesis!E12+Thesis!F12)/2-(shadow_base*(Thesis!$D$12+Thesis!$E$12)/2+(1-shadow_base)*Thesis!$E$12))*Thesis!F21/1000-(Thesis!F45-Thesis!$E$45)*PL!F31) -> 8.8834067 | G46: =MAX(0,((Thesis!F12+Thesis!G12)/2-(shadow_base*(Thesis!$D$12+Thesis!$E$12)/2+(1-shadow_base)*Thesis!$E$12))*Thesis!G21/1000-(Thesis!G45-Thesis!$E$45)*PL!G31) -> 22.706031 | H46: =MAX(0,((Thesis!G12+Thesis!H12)/2-(shadow_base*(Thesis!$D$12+Thesis!$E$12)/2+(1-shadow_base)*Thesis!$E$12))*Thesis!H21/1000-(Thesis!H45-Thesis!$E$45)*PL!H31) -> 38.001845 | I46: =MAX(0,((Thesis!H12+Thesis!I12)/2-(shadow_base*(Thesis!$D$12+Thesis!$E$12)/2+(1-shadow_base)*Thesis!$E$12))*Thesis!I21/1000-(Thesis!I45-Thesis!$E$45)*PL!I31) -> 52.138109 | J46: =MAX(0,((Thesis!I12+Thesis!J12)/2-(shadow_base*(Thesis!$D$12+Thesis!$E$12)/2+(1-shadow_base)*Thesis!$E$12))*Thesis!J21/1000-(Thesis!J45-Thesis!$E$45)*PL!J31) -> 62.059582 | K46: =MAX(0,((Thesis!J12+Thesis!K12)/2-(shadow_base*(Thesis!$D$12+Thesis!$E$12)/2+(1-shadow_base)*Thesis!$E$12))*Thesis!K21/1000-(Thesis!K45-Thesis!$E$45)*PL!K31) -> 67.080131 | L46: 修正二：FY2026 已反映在核心利益率內的自用 MW 不再計；修正三：基準改 FY2026 平均自用 MW（核心利益率以 FY2026 全年校準）；Copilot 只扣高於 FY2026 的增量
A47: 自用 AI 影子效益（依讀法開關 internal_ai_reading） | B47: US$B | F47: =IF(internal_ai_reading=2,1,0)*Thesis!F46 -> 8.8834067 | G47: =IF(internal_ai_reading=2,1,0)*Thesis!G46 -> 22.706031 | H47: =IF(internal_ai_reading=2,1,0)*Thesis!H46 -> 38.001845 | I47: =IF(internal_ai_reading=2,1,0)*Thesis!I46 -> 52.138109 | J47: =IF(internal_ai_reading=2,1,0)*Thesis!J46 -> 62.059582 | K47: =IF(internal_ai_reading=2,1,0)*Thesis!K46 -> 67.080131
A48: AI 增量營業利益（評價口徑）＝Azure AI EBITDA＋Copilot × 核心利益率＋影子效益 − 自用 AI 營運成本 − AI 折舊 | B48: US$B | F48: =Thesis!F31+Thesis!F45*PL!F31+Thesis!F47-Thesis!F32-Thesis!F43 -> 18.506868 | G48: =Thesis!G31+Thesis!G45*PL!G31+Thesis!G47-Thesis!G32-Thesis!G43 -> 43.198386 | H48: =Thesis!H31+Thesis!H45*PL!H31+Thesis!H47-Thesis!H32-Thesis!H43 -> 73.502598 | I48: =Thesis!I31+Thesis!I45*PL!I31+Thesis!I47-Thesis!I32-Thesis!I43 -> 94.745414 | J48: =Thesis!J31+Thesis!J45*PL!J31+Thesis!J47-Thesis!J32-Thesis!J43 -> 109.39961 | K48: =Thesis!K31+Thesis!K45*PL!K31+Thesis!K47-Thesis!K32-Thesis!K43 -> 118.8987
A49: AI PP&E 淨額（年底） | B49: US$B | E49: =Thesis!E11*(cxit_open+self_build*tk_cxfac)/1000*ai_net_open -> 126.69804 | F49: =Thesis!E49+Thesis!F40-Thesis!F43 -> 260.57263 | G49: =Thesis!F49+Thesis!G40-Thesis!G43 -> 391.78261 | H49: =Thesis!G49+Thesis!H40-Thesis!H43 -> 499.48853 | I49: =Thesis!H49+Thesis!I40-Thesis!I43 -> 553.87235 | J49: =Thesis!I49+Thesis!J40-Thesis!J43 -> 550.78661 | K49: =Thesis!J49+Thesis!K40-Thesis!K43 -> 526.73679 | L49: 期初＝自有 AI MW × 每 MW 全成本 × 淨額比（v0.2.2）
A50: AI 增量 ROIC（評價口徑；稅後營業利益 ÷ 平均 AI PP&E 淨額） | B50: % | F50: =Thesis!F48*(1-tax_f)/((Thesis!E49+Thesis!F49)/2) -> 0.076460706 | G50: =Thesis!G48*(1-tax_f)/((Thesis!F49+Thesis!G49)/2) -> 0.10595058 | H50: =Thesis!H48*(1-tax_f)/((Thesis!G49+Thesis!H49)/2) -> 0.13195104 | I50: =Thesis!I48*(1-tax_f)/((Thesis!H49+Thesis!I49)/2) -> 0.14391332 | J50: =Thesis!J48*(1-tax_f)/((Thesis!I49+Thesis!J49)/2) -> 0.15845558 | K50: =Thesis!K48*(1-tax_f)/((Thesis!J49+Thesis!K49)/2) -> 0.17655108
A51: 讀法 1（自用 AI 只計成本）的 AI 增量 ROIC | B51: % | F51: =(Thesis!F48-Thesis!F47)*(1-tax_f)/((Thesis!E49+Thesis!F49)/2) -> 0.039759112 | G51: =(Thesis!G48-Thesis!G47)*(1-tax_f)/((Thesis!F49+Thesis!G49)/2) -> 0.050260606 | H51: =(Thesis!H48-Thesis!H47)*(1-tax_f)/((Thesis!G49+Thesis!H49)/2) -> 0.063730556 | I51: =(Thesis!I48-Thesis!I47)*(1-tax_f)/((Thesis!H49+Thesis!I49)/2) -> 0.064718263 | J51: =(Thesis!J48-Thesis!J47)*(1-tax_f)/((Thesis!I49+Thesis!J49)/2) -> 0.068567807 | K51: =(Thesis!K48-Thesis!K47)*(1-tax_f)/((Thesis!J49+Thesis!K49)/2) -> 0.0769447
A52: 讀法 2（自用 AI 價值中性）的 AI 增量 ROIC | B52: % | F52: =(Thesis!F48-Thesis!F47+Thesis!F46)*(1-tax_f)/((Thesis!E49+Thesis!F49)/2) -> 0.076460706 | G52: =(Thesis!G48-Thesis!G47+Thesis!G46)*(1-tax_f)/((Thesis!F49+Thesis!G49)/2) -> 0.10595058 | H52: =(Thesis!H48-Thesis!H47+Thesis!H46)*(1-tax_f)/((Thesis!G49+Thesis!H49)/2) -> 0.13195104 | I52: =(Thesis!I48-Thesis!I47+Thesis!I46)*(1-tax_f)/((Thesis!H49+Thesis!I49)/2) -> 0.14391332 | J52: =(Thesis!J48-Thesis!J47+Thesis!J46)*(1-tax_f)/((Thesis!I49+Thesis!J49)/2) -> 0.15845558 | K52: =(Thesis!K48-Thesis!K47+Thesis!K46)*(1-tax_f)/((Thesis!J49+Thesis!K49)/2) -> 0.17655108
A53: 對外 AI ROIC（Azure AI 營業利益 ÷ 對外分攤的 PP&E；C11 口徑） | B53: % | F53: =Thesis!F44*(1-tax_f)/(Thesis!F30*(Thesis!E49+Thesis!F49)/2) -> 0.15471433 | G53: =Thesis!G44*(1-tax_f)/(Thesis!G30*(Thesis!F49+Thesis!G49)/2) -> 0.17691691 | H53: =Thesis!H44*(1-tax_f)/(Thesis!H30*(Thesis!G49+Thesis!H49)/2) -> 0.20748706 | I53: =Thesis!I44*(1-tax_f)/(Thesis!I30*(Thesis!H49+Thesis!I49)/2) -> 0.21987366 | J53: =Thesis!J44*(1-tax_f)/(Thesis!J30*(Thesis!I49+Thesis!J49)/2) -> 0.23895946 | K53: =Thesis!K44*(1-tax_f)/(Thesis!K30*(Thesis!J49+Thesis!K49)/2) -> 0.26460427
A54: AI 增量 ROIC − WACC | B54: pt | F54: =Thesis!F50-wacc -> -0.026475885 | G54: =Thesis!G50-wacc -> 0.0030139926 | H54: =Thesis!H50-wacc -> 0.029014453 | I54: =Thesis!I50-wacc -> 0.04097673 | J54: =Thesis!J50-wacc -> 0.055518986 | K54: =Thesis!K50-wacc -> 0.073614494
A55: AI 經濟利潤＝稅後 AI 營業利益 − WACC × 平均 AI PP&E 淨額 | B55: US$B | F55: =Thesis!F48*(1-tax_f)-wacc*(Thesis!E49+Thesis!F49)/2 -> -5.1266668 | G55: =Thesis!G48*(1-tax_f)-wacc*(Thesis!F49+Thesis!G49)/2 -> 0.98309693 | H55: =Thesis!H48*(1-tax_f)-wacc*(Thesis!G49+Thesis!H49)/2 -> 12.929872 | I55: =Thesis!I48*(1-tax_f)-wacc*(Thesis!H49+Thesis!I49)/2 -> 21.581642 | J55: =Thesis!J48*(1-tax_f)-wacc*(Thesis!I49+Thesis!J49)/2 -> 30.664773 | K55: =Thesis!K48*(1-tax_f)-wacc*(Thesis!J49+Thesis!K49)/2 -> 39.66067
A56: 情境 B（基準）｜命題模組（Thesis）
A57: 項目 | B57: 單位 | C57: FY2024A | D57: FY2025A | E57: FY2026A | F57: FY2027 | G57: FY2028 | H57: FY2029 | I57: FY2030 | J57: FY2031 | K57: FY2032 | L57: 說明
A58: 會計年度（數值；公式以「年度 − base_fy」計年數） | B58: 年 | C58: 2024 | D58: 2025 | E58: 2026 | F58: 2027 | G58: 2028 | H58: 2029 | I58: 2030 | J58: 2031 | K58: 2032
A59: 在役對外 AI MW 每年新增 | B59: MW | F59: =pace -> 2726.5351 | G59: =pace -> 2726.5351 | H59: =pace -> 2726.5351 | I59: =pace+(g_tv*Thesis!H60-pace)*MIN(1,(Thesis!I58-pace_y0)/(pace_y1-pace_y0)) -> 1931.9861 | J59: =pace+(g_tv*Thesis!I60-pace)*MIN(1,(Thesis!J58-pace_y0)/(pace_y1-pace_y0)) -> 1176.0769 | K59: =pace+(g_tv*Thesis!J60-pace)*MIN(1,(Thesis!K58-pace_y0)/(pace_y1-pace_y0)) -> 436.13005 | L59: FY2029 以前＝依資本支出指引的速度；之後逐年線性收斂到 g_tv × 前一年在役 MW，FY2032 的在役 MW 年增＝g（修正二 F5）
A60: 在役對外 AI MW（年底，含租用） | B60: MW | C60: =mw_ext_24 -> 640 | D60: =mw_ext_25 -> 1630 | E60: =mw_ext_26 -> 3250 | F60: =Thesis!E60+Thesis!F59 -> 5976.5351 | G60: =Thesis!F60+Thesis!G59 -> 8703.0702 | H60: =Thesis!G60+Thesis!H59 -> 11429.605 | I60: =Thesis!H60+Thesis!I59 -> 13361.591 | J60: =Thesis!I60+Thesis!J59 -> 14537.668 | K60: =Thesis!J60+Thesis!K59 -> 14973.798 | L60: 三情境速度相同（變現驅動不同）
A61: 其中租用 neocloud 的對外 MW | B61: MW | C61: =rent_ext_24 -> 150 | D61: =rent_ext_25 -> 400 | E61: =rent_ext_26 -> 550 | F61: =rent_ext_f -> 756 | G61: =rent_ext_f -> 756 | H61: =rent_ext_f -> 756 | I61: =rent_ext_f -> 756 | J61: =rent_ext_f -> 756 | K61: =rent_ext_f -> 756 | L61: 收入照算，不計資本支出與折舊（C20）
A62: 自有對外 MW | B62: MW | C62: =Thesis!C60-Thesis!C61 -> 490 | D62: =Thesis!D60-Thesis!D61 -> 1230 | E62: =Thesis!E60-Thesis!E61 -> 2700 | F62: =Thesis!F60-Thesis!F61 -> 5220.5351 | G62: =Thesis!G60-Thesis!G61 -> 7947.0702 | H62: =Thesis!H60-Thesis!H61 -> 10673.605 | I62: =Thesis!I60-Thesis!I61 -> 12605.591 | J62: =Thesis!J60-Thesis!J61 -> 13781.668 | K62: =Thesis!K60-Thesis!K61 -> 14217.798
A63: 自有 AI MW（對外 ÷ 對外比例） | B63: MW | C63: =Thesis!C62/ext_sh -> 816.66667 | D63: =Thesis!D62/ext_sh -> 2050 | E63: =Thesis!E62/ext_sh -> 4500 | F63: =Thesis!F62/ext_sh -> 8700.8918 | G63: =Thesis!G62/ext_sh -> 13245.117 | H63: =Thesis!H62/ext_sh -> 17789.342 | I63: =Thesis!I62/ext_sh -> 21009.319 | J63: =Thesis!J62/ext_sh -> 22969.447 | K63: =Thesis!K62/ext_sh -> 23696.331 | L63: 含自用（M365／GitHub Copilot、MAI 研發）
A64: 其中自用 AI MW | B64: MW | C64: =Thesis!C63-Thesis!C62 -> 326.66667 | D64: =Thesis!D63-Thesis!D62 -> 820 | E64: =Thesis!E63-Thesis!E62 -> 1800 | F64: =Thesis!F63-Thesis!F62 -> 3480.3567 | G64: =Thesis!G63-Thesis!G62 -> 5298.0468 | H64: =Thesis!H63-Thesis!H62 -> 7115.7369 | I64: =Thesis!I63-Thesis!I62 -> 8403.7276 | J64: =Thesis!J63-Thesis!J62 -> 9187.7789 | K64: =Thesis!K63-Thesis!K62 -> 9478.5322
A65: 自有 AI MW 新增（FY2024 欄含以前全部） | B65: MW | C65: =Thesis!C63 -> 816.66667 | D65: =Thesis!D63-Thesis!C63 -> 1233.3333 | E65: =Thesis!E63-Thesis!D63 -> 2450 | F65: =Thesis!F63-Thesis!E63 -> 4200.8918 | G65: =Thesis!G63-Thesis!F63 -> 4544.2252 | H65: =Thesis!H63-Thesis!G63 -> 4544.2252 | I65: =Thesis!I63-Thesis!H63 -> 3219.9769 | J65: =Thesis!J63-Thesis!I63 -> 1960.1281 | K65: =Thesis!K63-Thesis!J63 -> 726.88341
A66: 在役對外 MW 新增 | B66: MW | D66: =Thesis!D60-Thesis!C60 -> 990 | E66: =Thesis!E60-Thesis!D60 -> 1620 | F66: =Thesis!F60-Thesis!E60 -> 2726.5351 | G66: =Thesis!G60-Thesis!F60 -> 2726.5351 | H66: =Thesis!H60-Thesis!G60 -> 2726.5351 | I66: =Thesis!I60-Thesis!H60 -> 1931.9861 | J66: =Thesis!J60-Thesis!I60 -> 1176.0769 | K66: =Thesis!K60-Thesis!J60 -> 436.13005
A67: 其中汰換為新世代的對外 MW（汰換 MW × 對外比例） | B67: MW | F67: =Thesis!F86*ext_sh -> 0 | G67: =Thesis!G86*ext_sh -> 0 | H67: =Thesis!H86*ext_sh -> 0 | I67: =Thesis!I86*ext_sh -> 490 | J67: =Thesis!J86*ext_sh -> 740 | K67: =Thesis!K86*ext_sh -> 1470 | L67: 修正一：汰換時在役世代占比同步更新（舊世代依期初占比移出、新世代依當年新增占比移入）
A68: 在役對外 MW：Hopper | B68: MW | C68: =mix_h*Thesis!C60 -> 128 | D68: =mix_h*Thesis!D60 -> 326 | E68: =mix_h*Thesis!E60 -> 650 | F68: =Thesis!E68-Thesis!F67*mix_h -> 650 | G68: =Thesis!F68-Thesis!G67*mix_h -> 650 | H68: =Thesis!G68-Thesis!H67*mix_h -> 650 | I68: =Thesis!H68-Thesis!I67*mix_h -> 552 | J68: =Thesis!I68-Thesis!J67*mix_h -> 404 | K68: =Thesis!J68-Thesis!K67*mix_h -> 110
A69: 在役對外 MW：GB200 | B69: MW | C69: =mix_g2*Thesis!C60 -> 288 | D69: =mix_g2*Thesis!D60 -> 733.5 | E69: =mix_g2*Thesis!E60 -> 1462.5 | F69: =Thesis!E69-Thesis!F67*mix_g2 -> 1462.5 | G69: =Thesis!F69-Thesis!G67*mix_g2 -> 1462.5 | H69: =Thesis!G69-Thesis!H67*mix_g2 -> 1462.5 | I69: =Thesis!H69-Thesis!I67*mix_g2 -> 1242 | J69: =Thesis!I69-Thesis!J67*mix_g2 -> 909 | K69: =Thesis!J69-Thesis!K67*mix_g2 -> 247.5
A70: 在役對外 MW：GB300（nonnv＝0 時含 Maia 200） | B70: MW | C70: =mix_g3*Thesis!C60 -> 224 | D70: =mix_g3*Thesis!D60 -> 570.5 | E70: =mix_g3*Thesis!E60 -> 1137.5 | F70: =Thesis!E70+(Thesis!F66+Thesis!F67)*(a_g3_27-nonnv*a_mai)-Thesis!F67*mix_g3 -> 2773.4211 | G70: =Thesis!F70+(Thesis!G66+Thesis!G67)*(a_g3_28-nonnv*a_mai)-Thesis!G67*mix_g3 -> 3318.7281 | H70: =Thesis!G70+(Thesis!H66+Thesis!H67)*(a_g3_29-nonnv*a_mai)-Thesis!H67*mix_g3 -> 3318.7281 | I70: =Thesis!H70+(Thesis!I66+Thesis!I67)*(a_g3_29-nonnv*a_mai)-Thesis!I67*mix_g3 -> 3147.2281 | J70: =Thesis!I70+(Thesis!J66+Thesis!J67)*(a_g3_29-nonnv*a_mai)-Thesis!J67*mix_g3 -> 2888.2281 | K70: =Thesis!J70+(Thesis!K66+Thesis!K67)*(a_g3_29-nonnv*a_mai)-Thesis!K67*mix_g3 -> 2373.7281
A71: 在役對外 MW：Maia 200（nonnv＝1；Tokenomics IF_NonNV_*） | B71: MW | C71: 0 | D71: 0 | E71: 0 | F71: =Thesis!E71+(Thesis!F66+Thesis!F67)*nonnv*a_mai -> 272.65351 | G71: =Thesis!F71+(Thesis!G66+Thesis!G67)*nonnv*a_mai -> 545.30702 | H71: =Thesis!G71+(Thesis!H66+Thesis!H67)*nonnv*a_mai -> 817.96053 | I71: =Thesis!H71+(Thesis!I66+Thesis!I67)*nonnv*a_mai -> 1060.1591 | J71: =Thesis!I71+(Thesis!J66+Thesis!J67)*nonnv*a_mai -> 1251.7668 | K71: =Thesis!J71+(Thesis!K66+Thesis!K67)*nonnv*a_mai -> 1442.3798 | L71: v0.3.1：Maia 改讀 Tokenomics 產出比與持有成本比（÷ VR200）；v0.3 以 GB300 × 1.0 計
A72: 在役對外 MW：VR200 | B72: MW | C72: 0 | D72: 0 | E72: 0 | F72: =Thesis!E72+(Thesis!F66+Thesis!F67)*(1-a_g3_27) -> 817.96053 | G72: =Thesis!F72+(Thesis!G66+Thesis!G67)*(1-a_g3_28) -> 2726.5351 | H72: =Thesis!G72+(Thesis!H66+Thesis!H67)*(1-a_g3_29) -> 5180.4167 | I72: =Thesis!H72+(Thesis!I66+Thesis!I67)*(1-a_g3_29) -> 7360.2042 | J72: =Thesis!I72+(Thesis!J66+Thesis!J67)*(1-a_g3_29) -> 9084.6734 | K72: =Thesis!J72+(Thesis!K66+Thesis!K67)*(1-a_g3_29) -> 10800.19
A73: 在役世代加權持有成本（IF_HoldEcon；Maia＝持有成本比 × VR200） | B73: US$M/MW-年 | C73: =(Thesis!C68*tk_hold_h100+Thesis!C69*tk_hold_gb200+Thesis!C70*tk_hold_gb300+Thesis!C72*tk_hold_vr200+Thesis!C71*nv_hold_mai*tk_hold_vr200)/Thesis!C60 -> 9.7235358 | D73: =(Thesis!D68*tk_hold_h100+Thesis!D69*tk_hold_gb200+Thesis!D70*tk_hold_gb300+Thesis!D72*tk_hold_vr200+Thesis!D71*nv_hold_mai*tk_hold_vr200)/Thesis!D60 -> 9.7235358 | E73: =(Thesis!E68*tk_hold_h100+Thesis!E69*tk_hold_gb200+Thesis!E70*tk_hold_gb300+Thesis!E72*tk_hold_vr200+Thesis!E71*nv_hold_mai*tk_hold_vr200)/Thesis!E60 -> 9.7235358 | F73: =(Thesis!F68*tk_hold_h100+Thesis!F69*tk_hold_gb200+Thesis!F70*tk_hold_gb300+Thesis!F72*tk_hold_vr200+Thesis!F71*nv_hold_mai*tk_hold_vr200)/Thesis!F60 -> 10.219535 | G73: =(Thesis!G68*tk_hold_h100+Thesis!G69*tk_hold_gb200+Thesis!G70*tk_hold_gb300+Thesis!G72*tk_hold_vr200+Thesis!G71*nv_hold_mai*tk_hold_vr200)/Thesis!G60 -> 10.57256 | H73: =(Thesis!H68*tk_hold_h100+Thesis!H69*tk_hold_gb200+Thesis!H70*tk_hold_gb300+Thesis!H72*tk_hold_vr200+Thesis!H71*nv_hold_mai*tk_hold_vr200)/Thesis!H60 -> 10.821043 | I73: =(Thesis!I68*tk_hold_h100+Thesis!I69*tk_hold_gb200+Thesis!I70*tk_hold_gb300+Thesis!I72*tk_hold_vr200+Thesis!I71*nv_hold_mai*tk_hold_vr200)/Thesis!I60 -> 11.005062 | J73: =(Thesis!J68*tk_hold_h100+Thesis!J69*tk_hold_gb200+Thesis!J70*tk_hold_gb300+Thesis!J72*tk_hold_vr200+Thesis!J71*nv_hold_mai*tk_hold_vr200)/Thesis!J60 -> 11.150579 | K73: =(Thesis!K68*tk_hold_h100+Thesis!K69*tk_hold_gb200+Thesis!K70*tk_hold_gb300+Thesis!K72*tk_hold_vr200+Thesis!K71*nv_hold_mai*tk_hold_vr200)/Thesis!K60 -> 11.349691 | L73: 影子效益（k＝1）用此成本口徑
A74: 在役世代加權收入錨（IF_HoldEcon；Maia＝產出比 × VR200） | B74: US$M/MW-年 | C74: =(Thesis!C68*tk_hold_h100+Thesis!C69*tk_hold_gb200+Thesis!C70*tk_hold_gb300+Thesis!C72*tk_hold_vr200+Thesis!C71*nv_out_mai*tk_hold_vr200)/Thesis!C60 -> 9.7235358 | D74: =(Thesis!D68*tk_hold_h100+Thesis!D69*tk_hold_gb200+Thesis!D70*tk_hold_gb300+Thesis!D72*tk_hold_vr200+Thesis!D71*nv_out_mai*tk_hold_vr200)/Thesis!D60 -> 9.7235358 | E74: =(Thesis!E68*tk_hold_h100+Thesis!E69*tk_hold_gb200+Thesis!E70*tk_hold_gb300+Thesis!E72*tk_hold_vr200+Thesis!E71*nv_out_mai*tk_hold_vr200)/Thesis!E60 -> 9.7235358 | F74: =(Thesis!F68*tk_hold_h100+Thesis!F69*tk_hold_gb200+Thesis!F70*tk_hold_gb300+Thesis!F72*tk_hold_vr200+Thesis!F71*nv_out_mai*tk_hold_vr200)/Thesis!F60 -> 10.247422 | G74: =(Thesis!G68*tk_hold_h100+Thesis!G69*tk_hold_gb200+Thesis!G70*tk_hold_gb300+Thesis!G72*tk_hold_vr200+Thesis!G71*nv_out_mai*tk_hold_vr200)/Thesis!G60 -> 10.61086 | H74: =(Thesis!H68*tk_hold_h100+Thesis!H69*tk_hold_gb200+Thesis!H70*tk_hold_gb300+Thesis!H72*tk_hold_vr200+Thesis!H71*nv_out_mai*tk_hold_vr200)/Thesis!H60 -> 10.864789 | I74: =(Thesis!I68*tk_hold_h100+Thesis!I69*tk_hold_gb200+Thesis!I70*tk_hold_gb300+Thesis!I72*tk_hold_vr200+Thesis!I71*nv_out_mai*tk_hold_vr200)/Thesis!I60 -> 11.053563 | J74: =(Thesis!J68*tk_hold_h100+Thesis!J69*tk_hold_gb200+Thesis!J70*tk_hold_gb300+Thesis!J72*tk_hold_vr200+Thesis!J71*nv_out_mai*tk_hold_vr200)/Thesis!J60 -> 11.203213 | K74: =(Thesis!K68*tk_hold_h100+Thesis!K69*tk_hold_gb200+Thesis!K70*tk_hold_gb300+Thesis!K72*tk_hold_vr200+Thesis!K71*nv_out_mai*tk_hold_vr200)/Thesis!K60 -> 11.408574 | L74: nonnv＝0 時與持有成本列相同
A75: k（長約占比 × k_長約＋其餘 × k_現貨） | B75: x | C75: =k_B -> 1.1721393 | D75: =k_B -> 1.1721393 | E75: =k_B -> 1.1721393 | F75: =(k_B+((ls_B*k_long+(1-ls_B)*k_spot)-k_B)*MIN(1,(Thesis!F58-base_fy)/k_ramp)) -> 1.1721393 | G75: =(k_B+((ls_B*k_long+(1-ls_B)*k_spot)-k_B)*MIN(1,(Thesis!G58-base_fy)/k_ramp)) -> 1.1721393 | H75: =(k_B+((ls_B*k_long+(1-ls_B)*k_spot)-k_B)*MIN(1,(Thesis!H58-base_fy)/k_ramp)) -> 1.1721393 | I75: =(k_B+((ls_B*k_long+(1-ls_B)*k_spot)-k_B)*MIN(1,(Thesis!I58-base_fy)/k_ramp)) -> 1.1721393 | J75: =(k_B+((ls_B*k_long+(1-ls_B)*k_spot)-k_B)*MIN(1,(Thesis!J58-base_fy)/k_ramp)) -> 1.1721393 | K75: =(k_B+((ls_B*k_long+(1-ls_B)*k_spot)-k_B)*MIN(1,(Thesis!K58-base_fy)/k_ramp)) -> 1.1721393 | L75: 實績期三情境同用基準 k（拆分是估計，不是情境）；FY2027 起 k_ramp 年線性移到情境 k
A76: 每 MW 年收入（對外） | B76: US$M/MW-年 | C76: =Thesis!C74*Thesis!C75*chip_f -> 11.397339 | D76: =Thesis!D74*Thesis!D75*chip_f -> 11.397339 | E76: =Thesis!E74*Thesis!E75*chip_f -> 11.397339 | F76: =Thesis!F74*Thesis!F75*chip_f -> 12.011406 | G76: =Thesis!G74*Thesis!G75*chip_f -> 12.437407 | H76: =Thesis!H74*Thesis!H75*chip_f -> 12.735046 | I76: =Thesis!I74*Thesis!I75*chip_f -> 12.956315 | J76: =Thesis!J74*Thesis!J75*chip_f -> 13.131726 | K76: =Thesis!K74*Thesis!K75*chip_f -> 13.372438 | L76: 按 MW-year 計價，不乘利用率（v0.2.2 口徑）
A77: Azure AI 營收（期間平均在役對外 MW × 每 MW 年收入） | B77: US$B | D77: =(Thesis!C60+Thesis!D60)/2*Thesis!D76/1000 -> 12.935979 | E77: =(Thesis!D60+Thesis!E60)/2*Thesis!E76/1000 -> 27.809506 | F77: =(Thesis!E60+Thesis!F60)/2*Thesis!F76/1000 -> 55.411832 | G77: =(Thesis!F60+Thesis!G60)/2*Thesis!G76/1000 -> 91.28811 | H77: =(Thesis!G60+Thesis!H60)/2*Thesis!H76/1000 -> 128.19527 | I77: =(Thesis!H60+Thesis!I60)/2*Thesis!I76/1000 -> 160.60128 | J77: =(Thesis!I60+Thesis!J60)/2*Thesis!J76/1000 -> 183.18272 | K77: =(Thesis!J60+Thesis!K60)/2*Thesis!K76/1000 -> 197.32012 | L77: FY2025、FY2026 為模型估計（用於拆出 Azure 其他）
A78: 在役世代加權 IF_OpexGW | B78: US$M/MW-年 | C78: =(Thesis!C68*tk_opex_h100+Thesis!C69*tk_opex_gb200+Thesis!C70*tk_opex_gb300+(Thesis!C72+Thesis!C71)*tk_opex_vr200)/Thesis!C60 -> 1.8863604 | D78: =(Thesis!D68*tk_opex_h100+Thesis!D69*tk_opex_gb200+Thesis!D70*tk_opex_gb300+(Thesis!D72+Thesis!D71)*tk_opex_vr200)/Thesis!D60 -> 1.8863604 | E78: =(Thesis!E68*tk_opex_h100+Thesis!E69*tk_opex_gb200+Thesis!E70*tk_opex_gb300+(Thesis!E72+Thesis!E71)*tk_opex_vr200)/Thesis!E60 -> 1.8863604 | F78: =(Thesis!F68*tk_opex_h100+Thesis!F69*tk_opex_gb200+Thesis!F70*tk_opex_gb300+(Thesis!F72+Thesis!F71)*tk_opex_vr200)/Thesis!F60 -> 1.9505116 | G78: =(Thesis!G68*tk_opex_h100+Thesis!G69*tk_opex_gb200+Thesis!G70*tk_opex_gb300+(Thesis!G72+Thesis!G71)*tk_opex_vr200)/Thesis!G60 -> 1.98836 | H78: =(Thesis!H68*tk_opex_h100+Thesis!H69*tk_opex_gb200+Thesis!H70*tk_opex_gb300+(Thesis!H72+Thesis!H71)*tk_opex_vr200)/Thesis!H60 -> 2.0134401 | I78: =(Thesis!I68*tk_opex_h100+Thesis!I69*tk_opex_gb200+Thesis!I70*tk_opex_gb300+(Thesis!I72+Thesis!I71)*tk_opex_vr200)/Thesis!I60 -> 2.0326117 | J78: =(Thesis!J68*tk_opex_h100+Thesis!J69*tk_opex_gb200+Thesis!J70*tk_opex_gb300+(Thesis!J72+Thesis!J71)*tk_opex_vr200)/Thesis!J60 -> 2.0480807 | K78: =(Thesis!K68*tk_opex_h100+Thesis!K69*tk_opex_gb200+Thesis!K70*tk_opex_gb300+(Thesis!K72+Thesis!K71)*tk_opex_vr200)/Thesis!K60 -> 2.0697383 | L78: Maia 的每 MW 營運成本以 VR200 計（電力相同；Assumed）
A79: AI 營運成本：自有 AI MW（平均 × IF_OpexGW） | B79: US$B | D79: =(Thesis!C63+Thesis!D63)/2*Thesis!D78/1000 -> 2.7037833 | E79: =(Thesis!D63+Thesis!E63)/2*Thesis!E78/1000 -> 6.1778304 | F79: =(Thesis!E63+Thesis!F63)/2*Thesis!F78/1000 -> 12.874246 | G79: =(Thesis!F63+Thesis!G63)/2*Thesis!G78/1000 -> 21.818283 | H79: =(Thesis!G63+Thesis!H63)/2*Thesis!H78/1000 -> 31.243013 | I79: =(Thesis!H63+Thesis!I63)/2*Thesis!I78/1000 -> 39.431306 | J79: =(Thesis!I63+Thesis!J63)/2*Thesis!J78/1000 -> 45.036032 | K79: =(Thesis!J63+Thesis!K63)/2*Thesis!K78/1000 -> 48.292973
A80: AI 營運成本：租用 neocloud 租金 | B80: US$B | D80: =(Thesis!C61+Thesis!D61)/2*rent_mw/1000 -> 2.44475 | E80: =(Thesis!D61+Thesis!E61)/2*rent_mw/1000 -> 4.22275 | F80: =(Thesis!E61+Thesis!F61)/2*rent_mw/1000 -> 5.80517 | G80: =(Thesis!F61+Thesis!G61)/2*rent_mw/1000 -> 6.72084 | H80: =(Thesis!G61+Thesis!H61)/2*rent_mw/1000 -> 6.72084 | I80: =(Thesis!H61+Thesis!I61)/2*rent_mw/1000 -> 6.72084 | J80: =(Thesis!I61+Thesis!J61)/2*rent_mw/1000 -> 6.72084 | K80: =(Thesis!J61+Thesis!K61)/2*rent_mw/1000 -> 6.72084
A81: AI 營運成本：租用機房租金（1 − 自建比例） | B81: US$B | D81: =(Thesis!C63+Thesis!D63)/2*(1-self_build)*fac_rent/1000 -> 0.85324238 | E81: =(Thesis!D63+Thesis!E63)/2*(1-self_build)*fac_rent/1000 -> 1.9495596 | F81: =(Thesis!E63+Thesis!F63)/2*(1-self_build)*fac_rent/1000 -> 3.9291489 | G81: =(Thesis!F63+Thesis!G63)/2*(1-self_build)*fac_rent/1000 -> 6.5320691 | H81: =(Thesis!G63+Thesis!H63)/2*(1-self_build)*fac_rent/1000 -> 9.2371799 | I81: =(Thesis!H63+Thesis!I63)/2*(1-self_build)*fac_rent/1000 -> 11.548138 | J81: =(Thesis!I63+Thesis!J63)/2*(1-self_build)*fac_rent/1000 -> 13.089958 | K81: =(Thesis!J63+Thesis!K63)/2*(1-self_build)*fac_rent/1000 -> 13.889728 | L81: C22
A82: 自有 AI 中對外的比重（期間平均） | B82: % | D82: =(Thesis!C62+Thesis!D62)/(Thesis!C63+Thesis!D63) -> 0.6 | E82: =(Thesis!D62+Thesis!E62)/(Thesis!D63+Thesis!E63) -> 0.6 | F82: =(Thesis!E62+Thesis!F62)/(Thesis!E63+Thesis!F63) -> 0.6 | G82: =(Thesis!F62+Thesis!G62)/(Thesis!F63+Thesis!G63) -> 0.6 | H82: =(Thesis!G62+Thesis!H62)/(Thesis!G63+Thesis!H63) -> 0.6 | I82: =(Thesis!H62+Thesis!I62)/(Thesis!H63+Thesis!I63) -> 0.6 | J82: =(Thesis!I62+Thesis!J62)/(Thesis!I63+Thesis!J63) -> 0.6 | K82: =(Thesis!J62+Thesis!K62)/(Thesis!J63+Thesis!K63) -> 0.6
A83: Azure AI EBITDA（營收 − 對外營運成本 − 租金） | B83: US$B | D83: =Thesis!D77-Thesis!D82*(Thesis!D79+Thesis!D81)-Thesis!D80 -> 8.3570141 | E83: =Thesis!E77-Thesis!E82*(Thesis!E79+Thesis!E81)-Thesis!E80 -> 18.710322 | F83: =Thesis!F77-Thesis!F82*(Thesis!F79+Thesis!F81)-Thesis!F80 -> 39.524624 | G83: =Thesis!G77-Thesis!G82*(Thesis!G79+Thesis!G81)-Thesis!G80 -> 67.557059 | H83: =Thesis!H77-Thesis!H82*(Thesis!H79+Thesis!H81)-Thesis!H80 -> 97.186318 | I83: =Thesis!I77-Thesis!I82*(Thesis!I79+Thesis!I81)-Thesis!I80 -> 123.29278 | J83: =Thesis!J77-Thesis!J82*(Thesis!J79+Thesis!J81)-Thesis!J80 -> 141.58629 | K83: =Thesis!K77-Thesis!K82*(Thesis!K79+Thesis!K81)-Thesis!K80 -> 153.28966
A84: 自用 AI 營運成本（服務 Copilot 等自有產品） | B84: US$B | D84: =(1-Thesis!D82)*(Thesis!D79+Thesis!D81) -> 1.4228103 | E84: =(1-Thesis!E82)*(Thesis!E79+Thesis!E81) -> 3.250956 | F84: =(1-Thesis!F82)*(Thesis!F79+Thesis!F81) -> 6.7213581 | G84: =(1-Thesis!G82)*(Thesis!G79+Thesis!G81) -> 11.340141 | H84: =(1-Thesis!H82)*(Thesis!H79+Thesis!H81) -> 16.192077 | I84: =(1-Thesis!I82)*(Thesis!I79+Thesis!I81) -> 20.391777 | J84: =(1-Thesis!J82)*(Thesis!J79+Thesis!J81) -> 23.250396 | K84: =(1-Thesis!K82)*(Thesis!K79+Thesis!K81) -> 24.87308
A85: 新增與汰換 MW 的 IT 資本支出（世代加權） | B85: US$M/MW | C85: =cxit_open -> 27.5919 | D85: =cxit_open -> 27.5919 | E85: =cxit_open -> 27.5919 | F85: =((a_g3_27-nonnv*a_mai)*tk_cxit_gb300+nonnv*a_mai*nv_hold_mai*tk_cxit_vr200+(1-a_g3_27)*tk_cxit_vr200) -> 32.497558 | G85: =((a_g3_28-nonnv*a_mai)*tk_cxit_gb300+nonnv*a_mai*nv_hold_mai*tk_cxit_vr200+(1-a_g3_28)*tk_cxit_vr200) -> 34.637209 | H85: =((a_g3_29-nonnv*a_mai)*tk_cxit_gb300+nonnv*a_mai*nv_hold_mai*tk_cxit_vr200+(1-a_g3_29)*tk_cxit_vr200) -> 35.707034 | I85: =((a_g3_29-nonnv*a_mai)*tk_cxit_gb300+nonnv*a_mai*nv_hold_mai*tk_cxit_vr200+(1-a_g3_29)*tk_cxit_vr200) -> 35.707034 | J85: =((a_g3_29-nonnv*a_mai)*tk_cxit_gb300+nonnv*a_mai*nv_hold_mai*tk_cxit_vr200+(1-a_g3_29)*tk_cxit_vr200) -> 35.707034 | K85: =((a_g3_29-nonnv*a_mai)*tk_cxit_gb300+nonnv*a_mai*nv_hold_mai*tk_cxit_vr200+(1-a_g3_29)*tk_cxit_vr200) -> 35.707034 | L85: FY2026 以前用期初世代加權（估計）
A86: GPU 汰換 MW（自有 AI MW 滿 IT 年限者） | B86: MW | F86: =Thesis!C65*IF(Thesis!F58-Thesis!C58=life_it,1,0)+Thesis!D65*IF(Thesis!F58-Thesis!D58=life_it,1,0)+Thesis!E65*IF(Thesis!F58-Thesis!E58=life_it,1,0) -> 0 | G86: =Thesis!C65*IF(Thesis!G58-Thesis!C58=life_it,1,0)+Thesis!D65*IF(Thesis!G58-Thesis!D58=life_it,1,0)+Thesis!E65*IF(Thesis!G58-Thesis!E58=life_it,1,0)+Thesis!F65*IF(Thesis!G58-Thesis!F58=life_it,1,0) -> 0 | H86: =Thesis!C65*IF(Thesis!H58-Thesis!C58=life_it,1,0)+Thesis!D65*IF(Thesis!H58-Thesis!D58=life_it,1,0)+Thesis!E65*IF(Thesis!H58-Thesis!E58=life_it,1,0)+Thesis!F65*IF(Thesis!H58-Thesis!F58=life_it,1,0)+Thesis!G65*IF(Thesis!H58-Thesis!G58=life_it,1,0) -> 0 | I86: =Thesis!C65*IF(Thesis!I58-Thesis!C58=life_it,1,0)+Thesis!D65*IF(Thesis!I58-Thesis!D58=life_it,1,0)+Thesis!E65*IF(Thesis!I58-Thesis!E58=life_it,1,0)+Thesis!F65*IF(Thesis!I58-Thesis!F58=life_it,1,0)+Thesis!G65*IF(Thesis!I58-Thesis!G58=life_it,1,0)+Thesis!H65*IF(Thesis!I58-Thesis!H58=life_it,1,0) -> 816.66667 | J86: =Thesis!C65*IF(Thesis!J58-Thesis!C58=life_it,1,0)+Thesis!D65*IF(Thesis!J58-Thesis!D58=life_it,1,0)+Thesis!E65*IF(Thesis!J58-Thesis!E58=life_it,1,0)+Thesis!F65*IF(Thesis!J58-Thesis!F58=life_it,1,0)+Thesis!G65*IF(Thesis!J58-Thesis!G58=life_it,1,0)+Thesis!H65*IF(Thesis!J58-Thesis!H58=life_it,1,0)+Thesis!I65*IF(Thesis!J58-Thesis!I58=life_it,1,0) -> 1233.3333 | K86: =Thesis!C65*IF(Thesis!K58-Thesis!C58=life_it,1,0)+Thesis!D65*IF(Thesis!K58-Thesis!D58=life_it,1,0)+Thesis!E65*IF(Thesis!K58-Thesis!E58=life_it,1,0)+Thesis!F65*IF(Thesis!K58-Thesis!F58=life_it,1,0)+Thesis!G65*IF(Thesis!K58-Thesis!G58=life_it,1,0)+Thesis!H65*IF(Thesis!K58-Thesis!H58=life_it,1,0)+Thesis!I65*IF(Thesis!K58-Thesis!I58=life_it,1,0)+Thesis!J65*IF(Thesis!K58-Thesis!J58=life_it,1,0) -> 2450 | L86: 只換 IT、機房不換；FY2024 欄含 FY2024 以前全部（視同 FY2024 投入）；舊機隊在年限到期後停止折舊，汰換後的新 IT 另計折舊（不重複）
A87: AI IT 資本支出（公式） | B87: US$B | C87: =Thesis!C65*Thesis!C85/1000 -> 22.533385 | D87: =Thesis!D65*Thesis!D85/1000 -> 34.030009 | E87: =Thesis!E65*Thesis!E85/1000 -> 67.600154 | F87: =(Thesis!F65+Thesis!F86)*Thesis!F85/1000 -> 136.51872 | G87: =(Thesis!G65+Thesis!G86)*Thesis!G85/1000 -> 157.39928 | H87: =(Thesis!H65+Thesis!H86)*Thesis!H85/1000 -> 162.2608 | I87: =(Thesis!I65+Thesis!I86)*Thesis!I85/1000 -> 144.13657 | J87: =(Thesis!J65+Thesis!J86)*Thesis!J85/1000 -> 114.02904 | K87: =(Thesis!K65+Thesis!K86)*Thesis!K85/1000 -> 113.43709
A88: AI 機房資本支出（自建比例 × IF_CapexFacility） | B88: US$B | C88: =Thesis!C65*self_build*tk_cxfac/1000 -> 6.2083 | D88: =Thesis!D65*self_build*tk_cxfac/1000 -> 9.3758 | E88: =Thesis!E65*self_build*tk_cxfac/1000 -> 18.6249 | F88: =Thesis!F65*self_build*tk_cxfac/1000 -> 31.93518 | G88: =Thesis!G65*self_build*tk_cxfac/1000 -> 34.5452 | H88: =Thesis!H65*self_build*tk_cxfac/1000 -> 34.5452 | I88: =Thesis!I65*self_build*tk_cxfac/1000 -> 24.478264 | J88: =Thesis!J65*self_build*tk_cxfac/1000 -> 14.900894 | K88: =Thesis!K65*self_build*tk_cxfac/1000 -> 5.5257677
A89: C10 對帳落差：FY2027 公司指引推估 − 模型資本支出（AI IT＋AI 機房＋非 AI；正負） | B89: US$B | F89: =capex_floor27-Thesis!F87-Thesis!F88-CF!F57 -> 1.9458658e-05 | L89: v0.3.1：基準情境以 MW 速度重解使此列 ≈ 0（A、C 情境 Azure 其他略有不同，殘差見報告）
A90: FY2027 補足到公司指引的差額（落差為正時補足） | B90: US$B | F90: =MAX(0,Thesis!F89) -> 1.9458658e-05
A91: AI IT 資本支出 | B91: US$B | C91: =Thesis!C87 -> 22.533385 | D91: =Thesis!D87 -> 34.030009 | E91: =Thesis!E87 -> 67.600154 | F91: =Thesis!F87 -> 136.51872 | G91: =Thesis!G87 -> 157.39928 | H91: =Thesis!H87 -> 162.2608 | I91: =Thesis!I87 -> 144.13657 | J91: =Thesis!J87 -> 114.02904 | K91: =Thesis!K87 -> 113.43709
A92: AI 資本支出合計 | B92: US$B | C92: =Thesis!C91+Thesis!C88 -> 28.741685 | D92: =Thesis!D91+Thesis!D88 -> 43.405809 | E92: =Thesis!E91+Thesis!E88 -> 86.225054 | F92: =Thesis!F91+Thesis!F88 -> 168.4539 | G92: =Thesis!G91+Thesis!G88 -> 191.94448 | H92: =Thesis!H91+Thesis!H88 -> 196.806 | I92: =Thesis!I91+Thesis!I88 -> 168.61483 | J92: =Thesis!J91+Thesis!J88 -> 128.92993 | K92: =Thesis!K91+Thesis!K88 -> 118.96285 | L92: FY2026 以前為依 MW 估計的值（非公司揭露）
A93: AI IT 折舊（半年慣例、年限 life_it） | B93: US$B | E93: =(Thesis!C91*IF(2<life_it,1,IF(2=life_it,0.5,0))+Thesis!D91*IF(1<life_it,1,IF(1=life_it,0.5,0))+Thesis!E91*0.5)/life_it -> 15.060578 | F93: =(Thesis!C91*IF(3<life_it,1,IF(3=life_it,0.5,0))+Thesis!D91*IF(2<life_it,1,IF(2=life_it,0.5,0))+Thesis!E91*IF(1<life_it,1,IF(1=life_it,0.5,0))+Thesis!F91*0.5)/life_it -> 32.070485 | G93: =(Thesis!C91*IF(4<life_it,1,IF(4=life_it,0.5,0))+Thesis!D91*IF(3<life_it,1,IF(3=life_it,0.5,0))+Thesis!E91*IF(2<life_it,1,IF(2=life_it,0.5,0))+Thesis!F91*IF(1<life_it,1,IF(1=life_it,0.5,0))+Thesis!G91*0.5)/life_it -> 56.563652 | H93: =(Thesis!C91*IF(5<life_it,1,IF(5=life_it,0.5,0))+Thesis!D91*IF(4<life_it,1,IF(4=life_it,0.5,0))+Thesis!E91*IF(3<life_it,1,IF(3=life_it,0.5,0))+Thesis!F91*IF(2<life_it,1,IF(2=life_it,0.5,0))+Thesis!G91*IF(1<life_it,1,IF(1=life_it,0.5,0))+Thesis!H91*0.5)/life_it -> 83.201992 | I93: =(Thesis!C91*IF(6<life_it,1,IF(6=life_it,0.5,0))+Thesis!D91*IF(5<life_it,1,IF(5=life_it,0.5,0))+Thesis!E91*IF(4<life_it,1,IF(4=life_it,0.5,0))+Thesis!F91*IF(3<life_it,1,IF(3=life_it,0.5,0))+Thesis!G91*IF(2<life_it,1,IF(2=life_it,0.5,0))+Thesis!H91*IF(1<life_it,1,IF(1=life_it,0.5,0))+Thesis!I91*0.5)/life_it -> 106.85732 | J93: =(Thesis!C91*IF(7<life_it,1,IF(7=life_it,0.5,0))+Thesis!D91*IF(6<life_it,1,IF(6=life_it,0.5,0))+Thesis!E91*IF(5<life_it,1,IF(5=life_it,0.5,0))+Thesis!F91*IF(4<life_it,1,IF(4=life_it,0.5,0))+Thesis!G91*IF(3<life_it,1,IF(3=life_it,0.5,0))+Thesis!H91*IF(2<life_it,1,IF(2=life_it,0.5,0))+Thesis!I91*IF(1<life_it,1,IF(1=life_it,0.5,0))+Thesis!J91*0.5)/life_it -> 123.65751 | K93: =(Thesis!C91*IF(8<life_it,1,IF(8=life_it,0.5,0))+Thesis!D91*IF(7<life_it,1,IF(7=life_it,0.5,0))+Thesis!E91*IF(6<life_it,1,IF(6=life_it,0.5,0))+Thesis!F91*IF(5<life_it,1,IF(5=life_it,0.5,0))+Thesis!G91*IF(4<life_it,1,IF(4=life_it,0.5,0))+Thesis!H91*IF(3<life_it,1,IF(3=life_it,0.5,0))+Thesis!I91*IF(2<life_it,1,IF(2=life_it,0.5,0))+Thesis!J91*IF(1<life_it,1,IF(1=life_it,0.5,0))+Thesis!K91*0.5)/life_it -> 134.14384
A94: AI 機房折舊（年限 life_fac） | B94: US$B | E94: =(Thesis!C88*IF(2<life_fac,1,IF(2=life_fac,0.5,0))+Thesis!D88*IF(1<life_fac,1,IF(1=life_fac,0.5,0))+Thesis!E88*0.5)/life_fac -> 1.2448275 | F94: =(Thesis!C88*IF(3<life_fac,1,IF(3=life_fac,0.5,0))+Thesis!D88*IF(2<life_fac,1,IF(2=life_fac,0.5,0))+Thesis!E88*IF(1<life_fac,1,IF(1=life_fac,0.5,0))+Thesis!F88*0.5)/life_fac -> 2.5088295 | G94: =(Thesis!C88*IF(4<life_fac,1,IF(4=life_fac,0.5,0))+Thesis!D88*IF(3<life_fac,1,IF(3=life_fac,0.5,0))+Thesis!E88*IF(2<life_fac,1,IF(2=life_fac,0.5,0))+Thesis!F88*IF(1<life_fac,1,IF(1=life_fac,0.5,0))+Thesis!G88*0.5)/life_fac -> 4.170839 | H94: =(Thesis!C88*IF(5<life_fac,1,IF(5=life_fac,0.5,0))+Thesis!D88*IF(4<life_fac,1,IF(4=life_fac,0.5,0))+Thesis!E88*IF(3<life_fac,1,IF(3=life_fac,0.5,0))+Thesis!F88*IF(2<life_fac,1,IF(2=life_fac,0.5,0))+Thesis!G88*IF(1<life_fac,1,IF(1=life_fac,0.5,0))+Thesis!H88*0.5)/life_fac -> 5.898099 | I94: =(Thesis!C88*IF(6<life_fac,1,IF(6=life_fac,0.5,0))+Thesis!D88*IF(5<life_fac,1,IF(5=life_fac,0.5,0))+Thesis!E88*IF(4<life_fac,1,IF(4=life_fac,0.5,0))+Thesis!F88*IF(3<life_fac,1,IF(3=life_fac,0.5,0))+Thesis!G88*IF(2<life_fac,1,IF(2=life_fac,0.5,0))+Thesis!H88*IF(1<life_fac,1,IF(1=life_fac,0.5,0))+Thesis!I88*0.5)/life_fac -> 7.3736856 | J94: =(Thesis!C88*IF(7<life_fac,1,IF(7=life_fac,0.5,0))+Thesis!D88*IF(6<life_fac,1,IF(6=life_fac,0.5,0))+Thesis!E88*IF(5<life_fac,1,IF(5=life_fac,0.5,0))+Thesis!F88*IF(4<life_fac,1,IF(4=life_fac,0.5,0))+Thesis!G88*IF(3<life_fac,1,IF(3=life_fac,0.5,0))+Thesis!H88*IF(2<life_fac,1,IF(2=life_fac,0.5,0))+Thesis!I88*IF(1<life_fac,1,IF(1=life_fac,0.5,0))+Thesis!J88*0.5)/life_fac -> 8.3581645 | K94: =(Thesis!C88*IF(8<life_fac,1,IF(8=life_fac,0.5,0))+Thesis!D88*IF(7<life_fac,1,IF(7=life_fac,0.5,0))+Thesis!E88*IF(6<life_fac,1,IF(6=life_fac,0.5,0))+Thesis!F88*IF(5<life_fac,1,IF(5=life_fac,0.5,0))+Thesis!G88*IF(4<life_fac,1,IF(4=life_fac,0.5,0))+Thesis!H88*IF(3<life_fac,1,IF(3=life_fac,0.5,0))+Thesis!I88*IF(2<life_fac,1,IF(2=life_fac,0.5,0))+Thesis!J88*IF(1<life_fac,1,IF(1=life_fac,0.5,0))+Thesis!K88*0.5)/life_fac -> 8.868831
A95: AI 折舊合計（進 Agents and Infra 營業利益） | B95: US$B | E95: =Thesis!E93+Thesis!E94 -> 16.305406 | F95: =Thesis!F93+Thesis!F94 -> 34.579314 | G95: =Thesis!G93+Thesis!G94 -> 60.734491 | H95: =Thesis!H93+Thesis!H94 -> 89.100091 | I95: =Thesis!I93+Thesis!I94 -> 114.23101 | J95: =Thesis!J93+Thesis!J94 -> 132.01567 | K95: =Thesis!K93+Thesis!K94 -> 143.01267
A96: Azure AI 營業利益（EBITDA − 對外分攤折舊） | B96: US$B | E96: =Thesis!E83-Thesis!E82*Thesis!E95 -> 8.9270789 | F96: =Thesis!F83-Thesis!F82*Thesis!F95 -> 18.777036 | G96: =Thesis!G83-Thesis!G82*Thesis!G95 -> 31.116364 | H96: =Thesis!H83-Thesis!H82*Thesis!H95 -> 43.726264 | I96: =Thesis!I83-Thesis!I82*Thesis!I95 -> 54.75417 | J96: =Thesis!J83-Thesis!J82*Thesis!J95 -> 62.376882 | K96: =Thesis!K83-Thesis!K82*Thesis!K95 -> 67.482063
A97: Copilot 營收（Seg） | B97: US$B | E97: =Seg!E38 -> 5.25 | F97: =Seg!F38 -> 12 | G97: =Seg!G38 -> 18 | H97: =Seg!H38 -> 24 | I97: =Seg!I38 -> 28.5 | J97: =Seg!J38 -> 31.5 | K97: =Seg!K38 -> 34.5
A98: 自用 AI 影子效益（讀法 2 金額）＝MAX(0,（當年平均自用 MW − FY2026 平均自用 MW）× 持有成本（k＝1）− Copilot 增量 × 核心利益率) | B98: US$B | F98: =MAX(0,((Thesis!E64+Thesis!F64)/2-(shadow_base*(Thesis!$D$64+Thesis!$E$64)/2+(1-shadow_base)*Thesis!$E$64))*Thesis!F73/1000-(Thesis!F97-Thesis!$E$97)*PL!F70) -> 9.7398428 | G98: =MAX(0,((Thesis!F64+Thesis!G64)/2-(shadow_base*(Thesis!$D$64+Thesis!$E$64)/2+(1-shadow_base)*Thesis!$E$64))*Thesis!G73/1000-(Thesis!G97-Thesis!$E$97)*PL!G70) -> 25.275339 | H98: =MAX(0,((Thesis!G64+Thesis!H64)/2-(shadow_base*(Thesis!$D$64+Thesis!$E$64)/2+(1-shadow_base)*Thesis!$E$64))*Thesis!H73/1000-(Thesis!H97-Thesis!$E$97)*PL!H70) -> 42.284025 | I98: =MAX(0,((Thesis!H64+Thesis!I64)/2-(shadow_base*(Thesis!$D$64+Thesis!$E$64)/2+(1-shadow_base)*Thesis!$E$64))*Thesis!I73/1000-(Thesis!I97-Thesis!$E$97)*PL!I70) -> 57.704944 | J98: =MAX(0,((Thesis!I64+Thesis!J64)/2-(shadow_base*(Thesis!$D$64+Thesis!$E$64)/2+(1-shadow_base)*Thesis!$E$64))*Thesis!J73/1000-(Thesis!J97-Thesis!$E$97)*PL!J70) -> 68.482852 | K98: =MAX(0,((Thesis!J64+Thesis!K64)/2-(shadow_base*(Thesis!$D$64+Thesis!$E$64)/2+(1-shadow_base)*Thesis!$E$64))*Thesis!K73/1000-(Thesis!K97-Thesis!$E$97)*PL!K70) -> 74.359837 | L98: 修正二：FY2026 已反映在核心利益率內的自用 MW 不再計；修正三：基準改 FY2026 平均自用 MW（核心利益率以 FY2026 全年校準）；Copilot 只扣高於 FY2026 的增量
A99: 自用 AI 影子效益（依讀法開關 internal_ai_reading） | B99: US$B | F99: =IF(internal_ai_reading=2,1,0)*Thesis!F98 -> 9.7398428 | G99: =IF(internal_ai_reading=2,1,0)*Thesis!G98 -> 25.275339 | H99: =IF(internal_ai_reading=2,1,0)*Thesis!H98 -> 42.284025 | I99: =IF(internal_ai_reading=2,1,0)*Thesis!I98 -> 57.704944 | J99: =IF(internal_ai_reading=2,1,0)*Thesis!J98 -> 68.482852 | K99: =IF(internal_ai_reading=2,1,0)*Thesis!K98 -> 74.359837
A100: AI 增量營業利益（評價口徑）＝Azure AI EBITDA＋Copilot × 核心利益率＋影子效益 − 自用 AI 營運成本 − AI 折舊 | B100: US$B | F100: =Thesis!F83+Thesis!F97*PL!F70+Thesis!F99-Thesis!F84-Thesis!F95 -> 14.815283 | G100: =Thesis!G83+Thesis!G97*PL!G70+Thesis!G99-Thesis!G84-Thesis!G95 -> 31.034998 | H100: =Thesis!H83+Thesis!H97*PL!H70+Thesis!H99-Thesis!H84-Thesis!H95 -> 47.881152 | I100: =Thesis!I83+Thesis!I97*PL!I70+Thesis!I99-Thesis!I84-Thesis!I95 -> 62.647217 | J100: =Thesis!J83+Thesis!J97*PL!J70+Thesis!J99-Thesis!J84-Thesis!J95 -> 72.788225 | K100: =Thesis!K83+Thesis!K97*PL!K70+Thesis!K99-Thesis!K84-Thesis!K95 -> 79.461781
...

Sheet Seg
A1: Seg — 營收分部層：官方分部 Agents and Infra、Devices and Consumer（8-K 2026-09-02 重編）→ 八條產品線；Azure ＝ Azure AI（命題）＋ Azure 其他；Microsoft 365 cloud ＝ 基礎 ＋ Copilot（命題）
A2: 非命題產品線：FY2026 對 FY2025 年增線性收斂到長期值（FY2032 到達；In 頁 F 節）；三情境相同。FY2025、FY2026 欄為實績（Azure、M365 cloud 的子列為模型拆分）
A4: 情境 A（樂觀）｜營收分部層（Seg）
A5: 項目 | B5: 單位 | C5: FY2024A | D5: FY2025A | E5: FY2026A | F5: FY2027 | G5: FY2028 | H5: FY2029 | I5: FY2030 | J5: FY2031 | K5: FY2032 | L5: 說明
A6: Azure AI（命題子列） | B6: US$B | D6: =Thesis!D25 -> 12.935979 | E6: =Thesis!E25 -> 27.809506 | F6: =Thesis!F25 -> 59.103417 | G6: =Thesis!G25 -> 103.4515 | H6: =Thesis!H25 -> 153.81672 | I6: =Thesis!I25 -> 192.69948 | J6: =Thesis!J25 -> 219.7941 | K6: =Thesis!K25 -> 236.75705
A7: Azure 其他（非 AI 雲端；FY2025–26＝Azure 實績 − Azure AI 估計；FY2027＝Azure（Q1 實績＋Q2–Q4 模型）− Azure AI） | B7: US$B | D7: =Q!L6-Seg!D6 -> 59.674021 | E7: =Q!M6-Seg!E6 -> 74.128494 | F7: =Q!$I$6+(Seg!F6+Seg!E7*(1+Seg!F8))*(1-Q!$E$6/Q!M6)-Seg!F6 -> 90.486602 | G7: =Seg!F7*(1+Seg!G8) -> 107.51159 | H7: =Seg!G7*(1+Seg!H8) -> 124.83299 | I7: =Seg!H7*(1+Seg!I8) -> 141.56993 | J7: =Seg!I7*(1+Seg!J8) -> 156.72319 | K7: =Seg!J7*(1+Seg!K8) -> 169.26105 | L7: v0.3.1：FY2027 Azure＝Q1 實績＋（Azure AI＋Azure 其他的全年模型）×（1 − FY26Q1 占 FY2026 比重）；Q1 實績與模型的差額歸 Azure 其他（不回推 k，C3）
A8: 年增（近一年 → 長期值） | B8: % | E8: =Seg!E7/Seg!D7-1 -> 0.24222388 | F8: =Seg!$E$8+(glt_azo-Seg!$E$8)*MIN(1,(Thesis!F6-base_fy)/n_conv) -> 0.21518657 | G8: =Seg!$E$8+(glt_azo-Seg!$E$8)*MIN(1,(Thesis!G6-base_fy)/n_conv) -> 0.18814926 | H8: =Seg!$E$8+(glt_azo-Seg!$E$8)*MIN(1,(Thesis!H6-base_fy)/n_conv) -> 0.16111194 | I8: =Seg!$E$8+(glt_azo-Seg!$E$8)*MIN(1,(Thesis!I6-base_fy)/n_conv) -> 0.13407463 | J8: =Seg!$E$8+(glt_azo-Seg!$E$8)*MIN(1,(Thesis!J6-base_fy)/n_conv) -> 0.10703731 | K8: =Seg!$E$8+(glt_azo-Seg!$E$8)*MIN(1,(Thesis!K6-base_fy)/n_conv) -> 0.08
A9: Azure | B9: US$B | D9: =Seg!D6+Seg!D7 -> 72.61 | E9: =Seg!E6+Seg!E7 -> 101.938 | F9: =Seg!F6+Seg!F7 -> 149.59002 | G9: =Seg!G6+Seg!G7 -> 210.96309 | H9: =Seg!H6+Seg!H7 -> 278.64971 | I9: =Seg!I6+Seg!I7 -> 334.2694 | J9: =Seg!J6+Seg!J7 -> 376.51729 | K9: =Seg!K6+Seg!K7 -> 406.01809
A10: Copilot 付費座席（年底） | B10: 百萬席 | C10: =cop_s24 -> 1 | D10: =cop_s25 -> 5 | E10: =cop_s26 -> 30 | F10: =Seg!E10+cop_add_A -> 60 | G10: =Seg!F10+cop_add_A -> 90 | H10: =Seg!G10+cop_add_A -> 120 | I10: =Seg!H10+cop_add_A*cop_tail -> 135 | J10: =Seg!I10+cop_add_A*cop_tail -> 150 | K10: =Seg!J10+cop_add_A*cop_tail -> 165 | L10: FY2027–FY2029 每年淨增 cop_add；FY2030 起 × cop_tail
A11: Copilot（命題子列：平均座席 × 月費 × 12） | B11: US$B | D11: =(Seg!C10+Seg!D10)/2*cop_px*12/1000 -> 0.9 | E11: =(Seg!D10+Seg!E10)/2*cop_px*12/1000 -> 5.25 | F11: =(Seg!E10+Seg!F10)/2*cop_px*12/1000 -> 13.5 | G11: =(Seg!F10+Seg!G10)/2*cop_px*12/1000 -> 22.5 | H11: =(Seg!G10+Seg!H10)/2*cop_px*12/1000 -> 31.5 | I11: =(Seg!H10+Seg!I10)/2*cop_px*12/1000 -> 38.25 | J11: =(Seg!I10+Seg!J10)/2*cop_px*12/1000 -> 42.75 | K11: =(Seg!J10+Seg!K10)/2*cop_px*12/1000 -> 47.25 | L11: 實績期用基準月費（拆分是估計）；敏感度只改預測期
A12: M365 基礎（不含 Copilot；FY2025–26＝實績 − Copilot 估計；FY2027＝M365 cloud（Q1 實績＋Q2–Q4 模型）− Copilot） | B12: US$B | D12: =Q!L7-Seg!D11 -> 83.705 | E12: =Q!M7-Seg!E11 -> 95.049 | F12: =Q!$I$7+(Seg!E12*(1+Seg!F13)+Seg!F11)*(1-Q!$E$7/Q!M7)-Seg!F11 -> 106.22965 | G12: =Seg!F12*(1+Seg!G13) -> 118.30609 | H12: =Seg!G12*(1+Seg!H13) -> 130.46344 | I12: =Seg!H12*(1+Seg!I13) -> 142.44535 | J12: =Seg!I12*(1+Seg!J13) -> 153.97212 | K12: =Seg!J12*(1+Seg!K13) -> 164.75017 | L12: Q1 實績與模型的差額歸 M365 基礎
A13: 年增（近一年 → 長期值） | B13: % | E13: =Seg!E12/Seg!D12-1 -> 0.13552356 | F13: =Seg!$E$13+(glt_m365b-Seg!$E$13)*MIN(1,(Thesis!F6-base_fy)/n_conv) -> 0.12460297 | G13: =Seg!$E$13+(glt_m365b-Seg!$E$13)*MIN(1,(Thesis!G6-base_fy)/n_conv) -> 0.11368238 | H13: =Seg!$E$13+(glt_m365b-Seg!$E$13)*MIN(1,(Thesis!H6-base_fy)/n_conv) -> 0.10276178 | I13: =Seg!$E$13+(glt_m365b-Seg!$E$13)*MIN(1,(Thesis!I6-base_fy)/n_conv) -> 0.091841188 | J13: =Seg!$E$13+(glt_m365b-Seg!$E$13)*MIN(1,(Thesis!J6-base_fy)/n_conv) -> 0.080920594 | K13: =Seg!$E$13+(glt_m365b-Seg!$E$13)*MIN(1,(Thesis!K6-base_fy)/n_conv) -> 0.07
A14: Microsoft 365 cloud | B14: US$B | D14: =Seg!D12+Seg!D11 -> 84.605 | E14: =Seg!E12+Seg!E11 -> 100.299 | F14: =Seg!F12+Seg!F11 -> 119.72965 | G14: =Seg!G12+Seg!G11 -> 140.80609 | H14: =Seg!H12+Seg!H11 -> 161.96344 | I14: =Seg!I12+Seg!I11 -> 180.69535 | J14: =Seg!J12+Seg!J11 -> 196.72212 | K14: =Seg!K12+Seg!K11 -> 212.00017
A15: Productivity and server licensing | B15: US$B | D15: =Q!L8 -> 35.391 | E15: =Q!M8 -> 37.285 | F15: =Q!$I$8+(Q!M8-Q!$E$8)*(1+Seg!F16) -> 38.385144 | G15: =Seg!F15*(1+Seg!G16) -> 40.010535 | H15: =Seg!G15*(1+Seg!H16) -> 41.481251 | I15: =Seg!H15*(1+Seg!I16) -> 42.774311 | J15: =Seg!I15*(1+Seg!J16) -> 43.868737 | K15: =Seg!J15*(1+Seg!K16) -> 44.746112 | L15: FY2027＝Q1 實績＋FY2026 第二至第四季 ×（1＋年增）
A16: 年增（近一年 → 長期值） | B16: % | E16: =Seg!E15/Seg!D15-1 -> 0.053516431 | F16: =Seg!$E$16+(glt_lic-Seg!$E$16)*MIN(1,(Thesis!F6-base_fy)/n_conv) -> 0.047930359 | G16: =Seg!$E$16+(glt_lic-Seg!$E$16)*MIN(1,(Thesis!G6-base_fy)/n_conv) -> 0.042344287 | H16: =Seg!$E$16+(glt_lic-Seg!$E$16)*MIN(1,(Thesis!H6-base_fy)/n_conv) -> 0.036758215 | I16: =Seg!$E$16+(glt_lic-Seg!$E$16)*MIN(1,(Thesis!I6-base_fy)/n_conv) -> 0.031172144 | J16: =Seg!$E$16+(glt_lic-Seg!$E$16)*MIN(1,(Thesis!J6-base_fy)/n_conv) -> 0.025586072 | K16: =Seg!$E$16+(glt_lic-Seg!$E$16)*MIN(1,(Thesis!K6-base_fy)/n_conv) -> 0.02
A17: Industry solutions | B17: US$B | D17: =Q!L9 -> 18.417 | E17: =Q!M9 -> 20.345 | F17: =Q!$I$9+(Q!M9-Q!$E$9)*(1+Seg!F18) -> 22.31618 | G17: =Seg!F17*(1+Seg!G18) -> 24.39435 | H17: =Seg!G17*(1+Seg!H18) -> 26.525024 | I17: =Seg!H17*(1+Seg!I18) -> 28.688457 | J17: =Seg!I17*(1+Seg!J18) -> 30.862497 | K17: =Seg!J17*(1+Seg!K18) -> 33.022872 | L17: FY2027＝Q1 實績＋FY2026 第二至第四季 ×（1＋年增）
A18: 年增（近一年 → 長期值） | B18: % | E18: =Seg!E17/Seg!D17-1 -> 0.10468589 | F18: =Seg!$E$18+(glt_ind-Seg!$E$18)*MIN(1,(Thesis!F6-base_fy)/n_conv) -> 0.098904907 | G18: =Seg!$E$18+(glt_ind-Seg!$E$18)*MIN(1,(Thesis!G6-base_fy)/n_conv) -> 0.093123925 | H18: =Seg!$E$18+(glt_ind-Seg!$E$18)*MIN(1,(Thesis!H6-base_fy)/n_conv) -> 0.087342944 | I18: =Seg!$E$18+(glt_ind-Seg!$E$18)*MIN(1,(Thesis!I6-base_fy)/n_conv) -> 0.081561963 | J18: =Seg!$E$18+(glt_ind-Seg!$E$18)*MIN(1,(Thesis!J6-base_fy)/n_conv) -> 0.075780981 | K18: =Seg!$E$18+(glt_ind-Seg!$E$18)*MIN(1,(Thesis!K6-base_fy)/n_conv) -> 0.07
A19: Frontier and support services | B19: US$B | D19: =Q!L10 -> 7.76 | E19: =Q!M10 -> 8.26 | F19: =Q!$I$10+(Q!M10-Q!$E$10)*(1+Seg!F20) -> 8.7537208 | G19: =Seg!F19*(1+Seg!G20) -> 9.3339932 | H19: =Seg!G19*(1+Seg!H20) -> 9.9613916 | I19: =Seg!H19*(1+Seg!I20) -> 10.640204 | J19: =Seg!I19*(1+Seg!J20) -> 11.375146 | K19: =Seg!J19*(1+Seg!K20) -> 12.171406 | L19: FY2027＝Q1 實績＋FY2026 第二至第四季 ×（1＋年增）
A20: 年增（近一年 → 長期值） | B20: % | E20: =Seg!E19/Seg!D19-1 -> 0.06443299 | F20: =Seg!$E$20+(glt_fro-Seg!$E$20)*MIN(1,(Thesis!F6-base_fy)/n_conv) -> 0.065360825 | G20: =Seg!$E$20+(glt_fro-Seg!$E$20)*MIN(1,(Thesis!G6-base_fy)/n_conv) -> 0.06628866 | H20: =Seg!$E$20+(glt_fro-Seg!$E$20)*MIN(1,(Thesis!H6-base_fy)/n_conv) -> 0.067216495 | I20: =Seg!$E$20+(glt_fro-Seg!$E$20)*MIN(1,(Thesis!I6-base_fy)/n_conv) -> 0.06814433 | J20: =Seg!$E$20+(glt_fro-Seg!$E$20)*MIN(1,(Thesis!J6-base_fy)/n_conv) -> 0.069072165 | K20: =Seg!$E$20+(glt_fro-Seg!$E$20)*MIN(1,(Thesis!K6-base_fy)/n_conv) -> 0.07
A21: Agents and Infra | B21: US$B | D21: =Seg!D9+Seg!D14+Seg!D15+Seg!D17+Seg!D19 -> 218.783 | E21: =Seg!E9+Seg!E14+Seg!E15+Seg!E17+Seg!E19 -> 268.127 | F21: =Seg!F9+Seg!F14+Seg!F15+Seg!F17+Seg!F19 -> 338.77472 | G21: =Seg!G9+Seg!G14+Seg!G15+Seg!G17+Seg!G19 -> 425.50806 | H21: =Seg!H9+Seg!H14+Seg!H15+Seg!H17+Seg!H19 -> 518.58081 | I21: =Seg!I9+Seg!I14+Seg!I15+Seg!I17+Seg!I19 -> 597.06773 | J21: =Seg!J9+Seg!J14+Seg!J15+Seg!J17+Seg!J19 -> 659.34579 | K21: =Seg!K9+Seg!K14+Seg!K15+Seg!K17+Seg!K19 -> 707.95865
A22: Search and advertising | B22: US$B | D22: =Q!L13 -> 22.171 | E22: =Q!M13 -> 24.835 | F22: =Q!$I$13+(Q!M13-Q!$E$13)*(1+Seg!F23) -> 27.55919 | G22: =Seg!F22*(1+Seg!G23) -> 30.409856 | H22: =Seg!G22*(1+Seg!H23) -> 33.301179 | I22: =Seg!H22*(1+Seg!I23) -> 36.189024 | J22: =Seg!I22*(1+Seg!J23) -> 39.024777 | K22: =Seg!J22*(1+Seg!K23) -> 41.756512 | L22: FY2027＝Q1 實績＋FY2026 第二至第四季 ×（1＋年增）
A23: 年增（近一年 → 長期值） | B23: % | E23: =Seg!E22/Seg!D22-1 -> 0.12015696 | F23: =Seg!$E$23+(glt_srch-Seg!$E$23)*MIN(1,(Thesis!F6-base_fy)/n_conv) -> 0.11179747 | G23: =Seg!$E$23+(glt_srch-Seg!$E$23)*MIN(1,(Thesis!G6-base_fy)/n_conv) -> 0.10343797 | H23: =Seg!$E$23+(glt_srch-Seg!$E$23)*MIN(1,(Thesis!H6-base_fy)/n_conv) -> 0.095078481 | I23: =Seg!$E$23+(glt_srch-Seg!$E$23)*MIN(1,(Thesis!I6-base_fy)/n_conv) -> 0.086718987 | J23: =Seg!$E$23+(glt_srch-Seg!$E$23)*MIN(1,(Thesis!J6-base_fy)/n_conv) -> 0.078359494 | K23: =Seg!$E$23+(glt_srch-Seg!$E$23)*MIN(1,(Thesis!K6-base_fy)/n_conv) -> 0.07
A24: XBOX | B24: US$B | D24: =Q!L14 -> 23.455 | E24: =Q!M14 -> 21.79 | F24: =Q!$I$14+(Q!M14-Q!$E$14)*(1+Seg!F25) -> 20.752098 | G24: =Seg!F24*(1+Seg!G25) -> 19.908359 | H24: =Seg!G24*(1+Seg!H25) -> 19.400826 | I24: =Seg!H24*(1+Seg!I25) -> 19.200435 | J24: =Seg!I24*(1+Seg!J25) -> 19.293278 | K24: =Seg!J24*(1+Seg!K25) -> 19.679144 | L24: FY2027＝Q1 實績＋FY2026 第二至第四季 ×（1＋年增）
A25: 年增（近一年 → 長期值） | B25: % | E25: =Seg!E24/Seg!D24-1 -> -0.070986996 | F25: =Seg!$E$25+(glt_xbox-Seg!$E$25)*MIN(1,(Thesis!F6-base_fy)/n_conv) -> -0.055822497 | G25: =Seg!$E$25+(glt_xbox-Seg!$E$25)*MIN(1,(Thesis!G6-base_fy)/n_conv) -> -0.040657998 | H25: =Seg!$E$25+(glt_xbox-Seg!$E$25)*MIN(1,(Thesis!H6-base_fy)/n_conv) -> -0.025493498 | I25: =Seg!$E$25+(glt_xbox-Seg!$E$25)*MIN(1,(Thesis!I6-base_fy)/n_conv) -> -0.010328999 | J25: =Seg!$E$25+(glt_xbox-Seg!$E$25)*MIN(1,(Thesis!J6-base_fy)/n_conv) -> 0.0048355006 | K25: =Seg!$E$25+(glt_xbox-Seg!$E$25)*MIN(1,(Thesis!K6-base_fy)/n_conv) -> 0.02
A26: Windows OEM and devices | B26: US$B | D26: =Q!L15 -> 17.315 | E26: =Q!M15 -> 17.087 | F26: =Q!$I$15+(Q!M15-Q!$E$15)*(1+Seg!F27) -> 15.991227 | G26: =Seg!F26*(1+Seg!G27) -> 15.957456 | H26: =Seg!G26*(1+Seg!H27) -> 16.011969 | I26: =Seg!H26*(1+Seg!I27) -> 16.155181 | J26: =Seg!I26*(1+Seg!J27) -> 16.388979 | K26: =Seg!J26*(1+Seg!K27) -> 16.716759 | L26: FY2027＝Q1 實績＋FY2026 第二至第四季 ×（1＋年增）
A27: 年增（近一年 → 長期值） | B27: % | E27: =Seg!E26/Seg!D26-1 -> -0.013167774 | F27: =Seg!$E$27+(glt_win-Seg!$E$27)*MIN(1,(Thesis!F6-base_fy)/n_conv) -> -0.0076398113 | G27: =Seg!$E$27+(glt_win-Seg!$E$27)*MIN(1,(Thesis!G6-base_fy)/n_conv) -> -0.0021118491 | H27: =Seg!$E$27+(glt_win-Seg!$E$27)*MIN(1,(Thesis!H6-base_fy)/n_conv) -> 0.0034161132 | I27: =Seg!$E$27+(glt_win-Seg!$E$27)*MIN(1,(Thesis!I6-base_fy)/n_conv) -> 0.0089440755 | J27: =Seg!$E$27+(glt_win-Seg!$E$27)*MIN(1,(Thesis!J6-base_fy)/n_conv) -> 0.014472038 | K27: =Seg!$E$27+(glt_win-Seg!$E$27)*MIN(1,(Thesis!K6-base_fy)/n_conv) -> 0.02
A28: Devices and Consumer | B28: US$B | D28: =Seg!D22+Seg!D24+Seg!D26 -> 62.941 | E28: =Seg!E22+Seg!E24+Seg!E26 -> 63.712 | F28: =Seg!F22+Seg!F24+Seg!F26 -> 64.302515 | G28: =Seg!G22+Seg!G24+Seg!G26 -> 66.275672 | H28: =Seg!H22+Seg!H24+Seg!H26 -> 68.713974 | I28: =Seg!I22+Seg!I24+Seg!I26 -> 71.544639 | J28: =Seg!J22+Seg!J24+Seg!J26 -> 74.707035 | K28: =Seg!K22+Seg!K24+Seg!K26 -> 78.152415
A29: 合併營收（分部合計） | B29: US$B | D29: =Seg!D21+Seg!D28 -> 281.724 | E29: =Seg!E21+Seg!E28 -> 331.839 | F29: =Seg!F21+Seg!F28 -> 403.07723 | G29: =Seg!G21+Seg!G28 -> 491.78373 | H29: =Seg!H21+Seg!H28 -> 587.29479 | I29: =Seg!I21+Seg!I28 -> 668.61237 | J29: =Seg!J21+Seg!J28 -> 734.05283 | K29: =Seg!K21+Seg!K28 -> 786.11106
A30: 檢查：產品線合計 − 分部；實績期另比對公司分部值 | B30: US$B | D30: =(Seg!D9+Seg!D14+Seg!D15+Seg!D17+Seg!D19-Seg!D21)+(Seg!D22+Seg!D24+Seg!D26-Seg!D28)+(Seg!D21-Q!L5)+(Seg!D28-Q!L12)+(Seg!D9-Q!L6)+(Seg!D14-Q!L7) -> 0 | E30: =(Seg!E9+Seg!E14+Seg!E15+Seg!E17+Seg!E19-Seg!E21)+(Seg!E22+Seg!E24+Seg!E26-Seg!E28)+(Seg!E21-Q!M5)+(Seg!E28-Q!M12)+(Seg!E9-Q!M6)+(Seg!E14-Q!M7) -> 0 | F30: =(Seg!F9+Seg!F14+Seg!F15+Seg!F17+Seg!F19-Seg!F21)+(Seg!F22+Seg!F24+Seg!F26-Seg!F28) -> 0 | G30: =(Seg!G9+Seg!G14+Seg!G15+Seg!G17+Seg!G19-Seg!G21)+(Seg!G22+Seg!G24+Seg!G26-Seg!G28) -> 0 | H30: =(Seg!H9+Seg!H14+Seg!H15+Seg!H17+Seg!H19-Seg!H21)+(Seg!H22+Seg!H24+Seg!H26-Seg!H28) -> 0 | I30: =(Seg!I9+Seg!I14+Seg!I15+Seg!I17+Seg!I19-Seg!I21)+(Seg!I22+Seg!I24+Seg!I26-Seg!I28) -> 0 | J30: =(Seg!J9+Seg!J14+Seg!J15+Seg!J17+Seg!J19-Seg!J21)+(Seg!J22+Seg!J24+Seg!J26-Seg!J28) -> 0 | K30: =(Seg!K9+Seg!K14+Seg!K15+Seg!K17+Seg!K19-Seg!K21)+(Seg!K22+Seg!K24+Seg!K26-Seg!K28) -> 0
A31: 情境 B（基準）｜營收分部層（Seg）
A32: 項目 | B32: 單位 | C32: FY2024A | D32: FY2025A | E32: FY2026A | F32: FY2027 | G32: FY2028 | H32: FY2029 | I32: FY2030 | J32: FY2031 | K32: FY2032 | L32: 說明
A33: Azure AI（命題子列） | B33: US$B | D33: =Thesis!D77 -> 12.935979 | E33: =Thesis!E77 -> 27.809506 | F33: =Thesis!F77 -> 55.411832 | G33: =Thesis!G77 -> 91.28811 | H33: =Thesis!H77 -> 128.19527 | I33: =Thesis!I77 -> 160.60128 | J33: =Thesis!J77 -> 183.18272 | K33: =Thesis!K77 -> 197.32012
A34: Azure 其他（非 AI 雲端；FY2025–26＝Azure 實績 − Azure AI 估計；FY2027＝Azure（Q1 實績＋Q2–Q4 模型）− Azure AI） | B34: US$B | D34: =Q!L6-Seg!D33 -> 59.674021 | E34: =Q!M6-Seg!E33 -> 74.128494 | F34: =Q!$I$6+(Seg!F33+Seg!E34*(1+Seg!F35))*(1-Q!$E$6/Q!M6)-Seg!F33 -> 91.297216 | G34: =Seg!F34*(1+Seg!G35) -> 108.47472 | H34: =Seg!G34*(1+Seg!H35) -> 125.95129 | I34: =Seg!H34*(1+Seg!I35) -> 142.83817 | J34: =Seg!I34*(1+Seg!J35) -> 158.12718 | K34: =Seg!J34*(1+Seg!K35) -> 170.77735 | L34: v0.3.1：FY2027 Azure＝Q1 實績＋（Azure AI＋Azure 其他的全年模型）×（1 − FY26Q1 占 FY2026 比重）；Q1 實績與模型的差額歸 Azure 其他（不回推 k，C3）
A35: 年增（近一年 → 長期值） | B35: % | E35: =Seg!E34/Seg!D34-1 -> 0.24222388 | F35: =Seg!$E$35+(glt_azo-Seg!$E$35)*MIN(1,(Thesis!F58-base_fy)/n_conv) -> 0.21518657 | G35: =Seg!$E$35+(glt_azo-Seg!$E$35)*MIN(1,(Thesis!G58-base_fy)/n_conv) -> 0.18814926 | H35: =Seg!$E$35+(glt_azo-Seg!$E$35)*MIN(1,(Thesis!H58-base_fy)/n_conv) -> 0.16111194 | I35: =Seg!$E$35+(glt_azo-Seg!$E$35)*MIN(1,(Thesis!I58-base_fy)/n_conv) -> 0.13407463 | J35: =Seg!$E$35+(glt_azo-Seg!$E$35)*MIN(1,(Thesis!J58-base_fy)/n_conv) -> 0.10703731 | K35: =Seg!$E$35+(glt_azo-Seg!$E$35)*MIN(1,(Thesis!K58-base_fy)/n_conv) -> 0.08
A36: Azure | B36: US$B | D36: =Seg!D33+Seg!D34 -> 72.61 | E36: =Seg!E33+Seg!E34 -> 101.938 | F36: =Seg!F33+Seg!F34 -> 146.70905 | G36: =Seg!G33+Seg!G34 -> 199.76283 | H36: =Seg!H33+Seg!H34 -> 254.14657 | I36: =Seg!I33+Seg!I34 -> 303.43945 | J36: =Seg!J33+Seg!J34 -> 341.3099 | K36: =Seg!K33+Seg!K34 -> 368.09748
A37: Copilot 付費座席（年底） | B37: 百萬席 | C37: =cop_s24 -> 1 | D37: =cop_s25 -> 5 | E37: =cop_s26 -> 30 | F37: =Seg!E37+cop_add_B -> 50 | G37: =Seg!F37+cop_add_B -> 70 | H37: =Seg!G37+cop_add_B -> 90 | I37: =Seg!H37+cop_add_B*cop_tail -> 100 | J37: =Seg!I37+cop_add_B*cop_tail -> 110 | K37: =Seg!J37+cop_add_B*cop_tail -> 120 | L37: FY2027–FY2029 每年淨增 cop_add；FY2030 起 × cop_tail
A38: Copilot（命題子列：平均座席 × 月費 × 12） | B38: US$B | D38: =(Seg!C37+Seg!D37)/2*cop_px*12/1000 -> 0.9 | E38: =(Seg!D37+Seg!E37)/2*cop_px*12/1000 -> 5.25 | F38: =(Seg!E37+Seg!F37)/2*cop_px*12/1000 -> 12 | G38: =(Seg!F37+Seg!G37)/2*cop_px*12/1000 -> 18 | H38: =(Seg!G37+Seg!H37)/2*cop_px*12/1000 -> 24 | I38: =(Seg!H37+Seg!I37)/2*cop_px*12/1000 -> 28.5 | J38: =(Seg!I37+Seg!J37)/2*cop_px*12/1000 -> 31.5 | K38: =(Seg!J37+Seg!K37)/2*cop_px*12/1000 -> 34.5 | L38: 實績期用基準月費（拆分是估計）；敏感度只改預測期
A39: M365 基礎（不含 Copilot；FY2025–26＝實績 − Copilot 估計；FY2027＝M365 cloud（Q1 實績＋Q2–Q4 模型）− Copilot） | B39: US$B | D39: =Q!L7-Seg!D38 -> 83.705 | E39: =Q!M7-Seg!E38 -> 95.049 | F39: =Q!$I$7+(Seg!E39*(1+Seg!F40)+Seg!F38)*(1-Q!$E$7/Q!M7)-Seg!F38 -> 106.584 | G39: =Seg!F39*(1+Seg!G40) -> 118.70073 | H39: =Seg!G39*(1+Seg!H40) -> 130.89862 | I39: =Seg!H39*(1+Seg!I40) -> 142.92051 | J39: =Seg!I39*(1+Seg!J40) -> 154.48572 | K39: =Seg!J39*(1+Seg!K40) -> 165.29972 | L39: Q1 實績與模型的差額歸 M365 基礎
A40: 年增（近一年 → 長期值） | B40: % | E40: =Seg!E39/Seg!D39-1 -> 0.13552356 | F40: =Seg!$E$40+(glt_m365b-Seg!$E$40)*MIN(1,(Thesis!F58-base_fy)/n_conv) -> 0.12460297 | G40: =Seg!$E$40+(glt_m365b-Seg!$E$40)*MIN(1,(Thesis!G58-base_fy)/n_conv) -> 0.11368238 | H40: =Seg!$E$40+(glt_m365b-Seg!$E$40)*MIN(1,(Thesis!H58-base_fy)/n_conv) -> 0.10276178 | I40: =Seg!$E$40+(glt_m365b-Seg!$E$40)*MIN(1,(Thesis!I58-base_fy)/n_conv) -> 0.091841188 | J40: =Seg!$E$40+(glt_m365b-Seg!$E$40)*MIN(1,(Thesis!J58-base_fy)/n_conv) -> 0.080920594 | K40: =Seg!$E$40+(glt_m365b-Seg!$E$40)*MIN(1,(Thesis!K58-base_fy)/n_conv) -> 0.07
A41: Microsoft 365 cloud | B41: US$B | D41: =Seg!D39+Seg!D38 -> 84.605 | E41: =Seg!E39+Seg!E38 -> 100.299 | F41: =Seg!F39+Seg!F38 -> 118.584 | G41: =Seg!G39+Seg!G38 -> 136.70073 | H41: =Seg!H39+Seg!H38 -> 154.89862 | I41: =Seg!I39+Seg!I38 -> 171.42051 | J41: =Seg!J39+Seg!J38 -> 185.98572 | K41: =Seg!K39+Seg!K38 -> 199.79972
A42: Productivity and server licensing | B42: US$B | D42: =Q!L8 -> 35.391 | E42: =Q!M8 -> 37.285 | F42: =Q!$I$8+(Q!M8-Q!$E$8)*(1+Seg!F43) -> 38.385144 | G42: =Seg!F42*(1+Seg!G43) -> 40.010535 | H42: =Seg!G42*(1+Seg!H43) -> 41.481251 | I42: =Seg!H42*(1+Seg!I43) -> 42.774311 | J42: =Seg!I42*(1+Seg!J43) -> 43.868737 | K42: =Seg!J42*(1+Seg!K43) -> 44.746112 | L42: FY2027＝Q1 實績＋FY2026 第二至第四季 ×（1＋年增）
A43: 年增（近一年 → 長期值） | B43: % | E43: =Seg!E42/Seg!D42-1 -> 0.053516431 | F43: =Seg!$E$43+(glt_lic-Seg!$E$43)*MIN(1,(Thesis!F58-base_fy)/n_conv) -> 0.047930359 | G43: =Seg!$E$43+(glt_lic-Seg!$E$43)*MIN(1,(Thesis!G58-base_fy)/n_conv) -> 0.042344287 | H43: =Seg!$E$43+(glt_lic-Seg!$E$43)*MIN(1,(Thesis!H58-base_fy)/n_conv) -> 0.036758215 | I43: =Seg!$E$43+(glt_lic-Seg!$E$43)*MIN(1,(Thesis!I58-base_fy)/n_conv) -> 0.031172144 | J43: =Seg!$E$43+(glt_lic-Seg!$E$43)*MIN(1,(Thesis!J58-base_fy)/n_conv) -> 0.025586072 | K43: =Seg!$E$43+(glt_lic-Seg!$E$43)*MIN(1,(Thesis!K58-base_fy)/n_conv) -> 0.02
A44: Industry solutions | B44: US$B | D44: =Q!L9 -> 18.417 | E44: =Q!M9 -> 20.345 | F44: =Q!$I$9+(Q!M9-Q!$E$9)*(1+Seg!F45) -> 22.31618 | G44: =Seg!F44*(1+Seg!G45) -> 24.39435 | H44: =Seg!G44*(1+Seg!H45) -> 26.525024 | I44: =Seg!H44*(1+Seg!I45) -> 28.688457 | J44: =Seg!I44*(1+Seg!J45) -> 30.862497 | K44: =Seg!J44*(1+Seg!K45) -> 33.022872 | L44: FY2027＝Q1 實績＋FY2026 第二至第四季 ×（1＋年增）
A45: 年增（近一年 → 長期值） | B45: % | E45: =Seg!E44/Seg!D44-1 -> 0.10468589 | F45: =Seg!$E$45+(glt_ind-Seg!$E$45)*MIN(1,(Thesis!F58-base_fy)/n_conv) -> 0.098904907 | G45: =Seg!$E$45+(glt_ind-Seg!$E$45)*MIN(1,(Thesis!G58-base_fy)/n_conv) -> 0.093123925 | H45: =Seg!$E$45+(glt_ind-Seg!$E$45)*MIN(1,(Thesis!H58-base_fy)/n_conv) -> 0.087342944 | I45: =Seg!$E$45+(glt_ind-Seg!$E$45)*MIN(1,(Thesis!I58-base_fy)/n_conv) -> 0.081561963 | J45: =Seg!$E$45+(glt_ind-Seg!$E$45)*MIN(1,(Thesis!J58-base_fy)/n_conv) -> 0.075780981 | K45: =Seg!$E$45+(glt_ind-Seg!$E$45)*MIN(1,(Thesis!K58-base_fy)/n_conv) -> 0.07
A46: Frontier and support services | B46: US$B | D46: =Q!L10 -> 7.76 | E46: =Q!M10 -> 8.26 | F46: =Q!$I$10+(Q!M10-Q!$E$10)*(1+Seg!F47) -> 8.7537208 | G46: =Seg!F46*(1+Seg!G47) -> 9.3339932 | H46: =Seg!G46*(1+Seg!H47) -> 9.9613916 | I46: =Seg!H46*(1+Seg!I47) -> 10.640204 | J46: =Seg!I46*(1+Seg!J47) -> 11.375146 | K46: =Seg!J46*(1+Seg!K47) -> 12.171406 | L46: FY2027＝Q1 實績＋FY2026 第二至第四季 ×（1＋年增）
A47: 年增（近一年 → 長期值） | B47: % | E47: =Seg!E46/Seg!D46-1 -> 0.06443299 | F47: =Seg!$E$47+(glt_fro-Seg!$E$47)*MIN(1,(Thesis!F58-base_fy)/n_conv) -> 0.065360825 | G47: =Seg!$E$47+(glt_fro-Seg!$E$47)*MIN(1,(Thesis!G58-base_fy)/n_conv) -> 0.06628866 | H47: =Seg!$E$47+(glt_fro-Seg!$E$47)*MIN(1,(Thesis!H58-base_fy)/n_conv) -> 0.067216495 | I47: =Seg!$E$47+(glt_fro-Seg!$E$47)*MIN(1,(Thesis!I58-base_fy)/n_conv) -> 0.06814433 | J47: =Seg!$E$47+(glt_fro-Seg!$E$47)*MIN(1,(Thesis!J58-base_fy)/n_conv) -> 0.069072165 | K47: =Seg!$E$47+(glt_fro-Seg!$E$47)*MIN(1,(Thesis!K58-base_fy)/n_conv) -> 0.07
A48: Agents and Infra | B48: US$B | D48: =Seg!D36+Seg!D41+Seg!D42+Seg!D44+Seg!D46 -> 218.783 | E48: =Seg!E36+Seg!E41+Seg!E42+Seg!E44+Seg!E46 -> 268.127 | F48: =Seg!F36+Seg!F41+Seg!F42+Seg!F44+Seg!F46 -> 334.7481 | G48: =Seg!G36+Seg!G41+Seg!G42+Seg!G44+Seg!G46 -> 410.20243 | H48: =Seg!H36+Seg!H41+Seg!H42+Seg!H44+Seg!H46 -> 487.01286 | I48: =Seg!I36+Seg!I41+Seg!I42+Seg!I44+Seg!I46 -> 556.96293 | J48: =Seg!J36+Seg!J41+Seg!J42+Seg!J44+Seg!J46 -> 613.402 | K48: =Seg!K36+Seg!K41+Seg!K42+Seg!K44+Seg!K46 -> 657.83759
A49: Search and advertising | B49: US$B | D49: =Q!L13 -> 22.171 | E49: =Q!M13 -> 24.835 | F49: =Q!$I$13+(Q!M13-Q!$E$13)*(1+Seg!F50) -> 27.55919 | G49: =Seg!F49*(1+Seg!G50) -> 30.409856 | H49: =Seg!G49*(1+Seg!H50) -> 33.301179 | I49: =Seg!H49*(1+Seg!I50) -> 36.189024 | J49: =Seg!I49*(1+Seg!J50) -> 39.024777 | K49: =Seg!J49*(1+Seg!K50) -> 41.756512 | L49: FY2027＝Q1 實績＋FY2026 第二至第四季 ×（1＋年增）
A50: 年增（近一年 → 長期值） | B50: % | E50: =Seg!E49/Seg!D49-1 -> 0.12015696 | F50: =Seg!$E$50+(glt_srch-Seg!$E$50)*MIN(1,(Thesis!F58-base_fy)/n_conv) -> 0.11179747 | G50: =Seg!$E$50+(glt_srch-Seg!$E$50)*MIN(1,(Thesis!G58-base_fy)/n_conv) -> 0.10343797 | H50: =Seg!$E$50+(glt_srch-Seg!$E$50)*MIN(1,(Thesis!H58-base_fy)/n_conv) -> 0.095078481 | I50: =Seg!$E$50+(glt_srch-Seg!$E$50)*MIN(1,(Thesis!I58-base_fy)/n_conv) -> 0.086718987 | J50: =Seg!$E$50+(glt_srch-Seg!$E$50)*MIN(1,(Thesis!J58-base_fy)/n_conv) -> 0.078359494 | K50: =Seg!$E$50+(glt_srch-Seg!$E$50)*MIN(1,(Thesis!K58-base_fy)/n_conv) -> 0.07
A51: XBOX | B51: US$B | D51: =Q!L14 -> 23.455 | E51: =Q!M14 -> 21.79 | F51: =Q!$I$14+(Q!M14-Q!$E$14)*(1+Seg!F52) -> 20.752098 | G51: =Seg!F51*(1+Seg!G52) -> 19.908359 | H51: =Seg!G51*(1+Seg!H52) -> 19.400826 | I51: =Seg!H51*(1+Seg!I52) -> 19.200435 | J51: =Seg!I51*(1+Seg!J52) -> 19.293278 | K51: =Seg!J51*(1+Seg!K52) -> 19.679144 | L51: FY2027＝Q1 實績＋FY2026 第二至第四季 ×（1＋年增）
A52: 年增（近一年 → 長期值） | B52: % | E52: =Seg!E51/Seg!D51-1 -> -0.070986996 | F52: =Seg!$E$52+(glt_xbox-Seg!$E$52)*MIN(1,(Thesis!F58-base_fy)/n_conv) -> -0.055822497 | G52: =Seg!$E$52+(glt_xbox-Seg!$E$52)*MIN(1,(Thesis!G58-base_fy)/n_conv) -> -0.040657998 | H52: =Seg!$E$52+(glt_xbox-Seg!$E$52)*MIN(1,(Thesis!H58-base_fy)/n_conv) -> -0.025493498 | I52: =Seg!$E$52+(glt_xbox-Seg!$E$52)*MIN(1,(Thesis!I58-base_fy)/n_conv) -> -0.010328999 | J52: =Seg!$E$52+(glt_xbox-Seg!$E$52)*MIN(1,(Thesis!J58-base_fy)/n_conv) -> 0.0048355006 | K52: =Seg!$E$52+(glt_xbox-Seg!$E$52)*MIN(1,(Thesis!K58-base_fy)/n_conv) -> 0.02
A53: Windows OEM and devices | B53: US$B | D53: =Q!L15 -> 17.315 | E53: =Q!M15 -> 17.087 | F53: =Q!$I$15+(Q!M15-Q!$E$15)*(1+Seg!F54) -> 15.991227 | G53: =Seg!F53*(1+Seg!G54) -> 15.957456 | H53: =Seg!G53*(1+Seg!H54) -> 16.011969 | I53: =Seg!H53*(1+Seg!I54) -> 16.155181 | J53: =Seg!I53*(1+Seg!J54) -> 16.388979 | K53: =Seg!J53*(1+Seg!K54) -> 16.716759 | L53: FY2027＝Q1 實績＋FY2026 第二至第四季 ×（1＋年增）
A54: 年增（近一年 → 長期值） | B54: % | E54: =Seg!E53/Seg!D53-1 -> -0.013167774 | F54: =Seg!$E$54+(glt_win-Seg!$E$54)*MIN(1,(Thesis!F58-base_fy)/n_conv) -> -0.0076398113 | G54: =Seg!$E$54+(glt_win-Seg!$E$54)*MIN(1,(Thesis!G58-base_fy)/n_conv) -> -0.0021118491 | H54: =Seg!$E$54+(glt_win-Seg!$E$54)*MIN(1,(Thesis!H58-base_fy)/n_conv) -> 0.0034161132 | I54: =Seg!$E$54+(glt_win-Seg!$E$54)*MIN(1,(Thesis!I58-base_fy)/n_conv) -> 0.0089440755 | J54: =Seg!$E$54+(glt_win-Seg!$E$54)*MIN(1,(Thesis!J58-base_fy)/n_conv) -> 0.014472038 | K54: =Seg!$E$54+(glt_win-Seg!$E$54)*MIN(1,(Thesis!K58-base_fy)/n_conv) -> 0.02
A55: Devices and Consumer | B55: US$B | D55: =Seg!D49+Seg!D51+Seg!D53 -> 62.941 | E55: =Seg!E49+Seg!E51+Seg!E53 -> 63.712 | F55: =Seg!F49+Seg!F51+Seg!F53 -> 64.302515 | G55: =Seg!G49+Seg!G51+Seg!G53 -> 66.275672 | H55: =Seg!H49+Seg!H51+Seg!H53 -> 68.713974 | I55: =Seg!I49+Seg!I51+Seg!I53 -> 71.544639 | J55: =Seg!J49+Seg!J51+Seg!J53 -> 74.707035 | K55: =Seg!K49+Seg!K51+Seg!K53 -> 78.152415
A56: 合併營收（分部合計） | B56: US$B | D56: =Seg!D48+Seg!D55 -> 281.724 | E56: =Seg!E48+Seg!E55 -> 331.839 | F56: =Seg!F48+Seg!F55 -> 399.05061 | G56: =Seg!G48+Seg!G55 -> 476.47811 | H56: =Seg!H48+Seg!H55 -> 555.72683 | I56: =Seg!I48+Seg!I55 -> 628.50757 | J56: =Seg!J48+Seg!J55 -> 688.10904 | K56: =Seg!K48+Seg!K55 -> 735.99001
A57: 檢查：產品線合計 − 分部；實績期另比對公司分部值 | B57: US$B | D57: =(Seg!D36+Seg!D41+Seg!D42+Seg!D44+Seg!D46-Seg!D48)+(Seg!D49+Seg!D51+Seg!D53-Seg!D55)+(Seg!D48-Q!L5)+(Seg!D55-Q!L12)+(Seg!D36-Q!L6)+(Seg!D41-Q!L7) -> 0 | E57: =(Seg!E36+Seg!E41+Seg!E42+Seg!E44+Seg!E46-Seg!E48)+(Seg!E49+Seg!E51+Seg!E53-Seg!E55)+(Seg!E48-Q!M5)+(Seg!E55-Q!M12)+(Seg!E36-Q!M6)+(Seg!E41-Q!M7) -> 0 | F57: =(Seg!F36+Seg!F41+Seg!F42+Seg!F44+Seg!F46-Seg!F48)+(Seg!F49+Seg!F51+Seg!F53-Seg!F55) -> 0 | G57: =(Seg!G36+Seg!G41+Seg!G42+Seg!G44+Seg!G46-Seg!G48)+(Seg!G49+Seg!G51+Seg!G53-Seg!G55) -> 0 | H57: =(Seg!H36+Seg!H41+Seg!H42+Seg!H44+Seg!H46-Seg!H48)+(Seg!H49+Seg!H51+Seg!H53-Seg!H55) -> 0 | I57: =(Seg!I36+Seg!I41+Seg!I42+Seg!I44+Seg!I46-Seg!I48)+(Seg!I49+Seg!I51+Seg!I53-Seg!I55) -> 0 | J57: =(Seg!J36+Seg!J41+Seg!J42+Seg!J44+Seg!J46-Seg!J48)+(Seg!J49+Seg!J51+Seg!J53-Seg!J55) -> 0 | K57: =(Seg!K36+Seg!K41+Seg!K42+Seg!K44+Seg!K46-Seg!K48)+(Seg!K49+Seg!K51+Seg!K53-Seg!K55) -> 0
A58: 情境 C（保守）｜營收分部層（Seg）
A59: 項目 | B59: 單位 | C59: FY2024A | D59: FY2025A | E59: FY2026A | F59: FY2027 | G59: FY2028 | H59: FY2029 | I59: FY2030 | J59: FY2031 | K59: FY2032 | L59: 說明
A60: Azure AI（命題子列） | B60: US$B | D60: =Thesis!D129 -> 12.935979 | E60: =Thesis!E129 -> 27.809506 | F60: =Thesis!F129 -> 50.981929 | G60: =Thesis!G129 -> 76.692044 | H60: =Thesis!H129 -> 97.449538 | I60: =Thesis!I129 -> 122.08345 | J60: =Thesis!J129 -> 139.24906 | K60: =Thesis!K129 -> 149.99582
A61: Azure 其他（非 AI 雲端；FY2025–26＝Azure 實績 − Azure AI 估計；FY2027＝Azure（Q1 實績＋Q2–Q4 模型）− Azure AI） | B61: US$B | D61: =Q!L6-Seg!D60 -> 59.674021 | E61: =Q!M6-Seg!E60 -> 74.128494 | F61: =Q!$I$6+(Seg!F60+Seg!E61*(1+Seg!F62))*(1-Q!$E$6/Q!M6)-Seg!F60 -> 92.269954 | G61: =Seg!F61*(1+Seg!G62) -> 109.63048 | H61: =Seg!G61*(1+Seg!H62) -> 127.29326 | I61: =Seg!H61*(1+Seg!I62) -> 144.36005 | J61: =Seg!I61*(1+Seg!J62) -> 159.81196 | K61: =Seg!J61*(1+Seg!K62) -> 172.59692 | L61: v0.3.1：FY2027 Azure＝Q1 實績＋（Azure AI＋Azure 其他的全年模型）×（1 − FY26Q1 占 FY2026 比重）；Q1 實績與模型的差額歸 Azure 其他（不回推 k，C3）
A62: 年增（近一年 → 長期值） | B62: % | E62: =Seg!E61/Seg!D61-1 -> 0.24222388 | F62: =Seg!$E$62+(glt_azo-Seg!$E$62)*MIN(1,(Thesis!F110-base_fy)/n_conv) -> 0.21518657 | G62: =Seg!$E$62+(glt_azo-Seg!$E$62)*MIN(1,(Thesis!G110-base_fy)/n_conv) -> 0.18814926 | H62: =Seg!$E$62+(glt_azo-Seg!$E$62)*MIN(1,(Thesis!H110-base_fy)/n_conv) -> 0.16111194 | I62: =Seg!$E$62+(glt_azo-Seg!$E$62)*MIN(1,(Thesis!I110-base_fy)/n_conv) -> 0.13407463 | J62: =Seg!$E$62+(glt_azo-Seg!$E$62)*MIN(1,(Thesis!J110-base_fy)/n_conv) -> 0.10703731 | K62: =Seg!$E$62+(glt_azo-Seg!$E$62)*MIN(1,(Thesis!K110-base_fy)/n_conv) -> 0.08
A63: Azure | B63: US$B | D63: =Seg!D60+Seg!D61 -> 72.61 | E63: =Seg!E60+Seg!E61 -> 101.938 | F63: =Seg!F60+Seg!F61 -> 143.25188 | G63: =Seg!G60+Seg!G61 -> 186.32252 | H63: =Seg!H60+Seg!H61 -> 224.74279 | I63: =Seg!I60+Seg!I61 -> 266.4435 | J63: =Seg!J60+Seg!J61 -> 299.06102 | K63: =Seg!K60+Seg!K61 -> 322.59274
A64: Copilot 付費座席（年底） | B64: 百萬席 | C64: =cop_s24 -> 1 | D64: =cop_s25 -> 5 | E64: =cop_s26 -> 30 | F64: =Seg!E64+cop_add_C -> 40 | G64: =Seg!F64+cop_add_C -> 50 | H64: =Seg!G64+cop_add_C -> 60 | I64: =Seg!H64+cop_add_C*cop_tail -> 65 | J64: =Seg!I64+cop_add_C*cop_tail -> 70 | K64: =Seg!J64+cop_add_C*cop_tail -> 75 | L64: FY2027–FY2029 每年淨增 cop_add；FY2030 起 × cop_tail
A65: Copilot（命題子列：平均座席 × 月費 × 12） | B65: US$B | D65: =(Seg!C64+Seg!D64)/2*cop_px*12/1000 -> 0.9 | E65: =(Seg!D64+Seg!E64)/2*cop_px*12/1000 -> 5.25 | F65: =(Seg!E64+Seg!F64)/2*cop_px*12/1000 -> 10.5 | G65: =(Seg!F64+Seg!G64)/2*cop_px*12/1000 -> 13.5 | H65: =(Seg!G64+Seg!H64)/2*cop_px*12/1000 -> 16.5 | I65: =(Seg!H64+Seg!I64)/2*cop_px*12/1000 -> 18.75 | J65: =(Seg!I64+Seg!J64)/2*cop_px*12/1000 -> 20.25 | K65: =(Seg!J64+Seg!K64)/2*cop_px*12/1000 -> 21.75 | L65: 實績期用基準月費（拆分是估計）；敏感度只改預測期
A66: M365 基礎（不含 Copilot；FY2025–26＝實績 − Copilot 估計；FY2027＝M365 cloud（Q1 實績＋Q2–Q4 模型）− Copilot） | B66: US$B | D66: =Q!L7-Seg!D65 -> 83.705 | E66: =Q!M7-Seg!E65 -> 95.049 | F66: =Q!$I$7+(Seg!E66*(1+Seg!F67)+Seg!F65)*(1-Q!$E$7/Q!M7)-Seg!F65 -> 106.93835 | G66: =Seg!F66*(1+Seg!G67) -> 119.09536 | H66: =Seg!G66*(1+Seg!H67) -> 131.33381 | I66: =Seg!H66*(1+Seg!I67) -> 143.39567 | J66: =Seg!I66*(1+Seg!J67) -> 154.99933 | K66: =Seg!J66*(1+Seg!K67) -> 165.84928 | L66: Q1 實績與模型的差額歸 M365 基礎
A67: 年增（近一年 → 長期值） | B67: % | E67: =Seg!E66/Seg!D66-1 -> 0.13552356 | F67: =Seg!$E$67+(glt_m365b-Seg!$E$67)*MIN(1,(Thesis!F110-base_fy)/n_conv) -> 0.12460297 | G67: =Seg!$E$67+(glt_m365b-Seg!$E$67)*MIN(1,(Thesis!G110-base_fy)/n_conv) -> 0.11368238 | H67: =Seg!$E$67+(glt_m365b-Seg!$E$67)*MIN(1,(Thesis!H110-base_fy)/n_conv) -> 0.10276178 | I67: =Seg!$E$67+(glt_m365b-Seg!$E$67)*MIN(1,(Thesis!I110-base_fy)/n_conv) -> 0.091841188 | J67: =Seg!$E$67+(glt_m365b-Seg!$E$67)*MIN(1,(Thesis!J110-base_fy)/n_conv) -> 0.080920594 | K67: =Seg!$E$67+(glt_m365b-Seg!$E$67)*MIN(1,(Thesis!K110-base_fy)/n_conv) -> 0.07
A68: Microsoft 365 cloud | B68: US$B | D68: =Seg!D66+Seg!D65 -> 84.605 | E68: =Seg!E66+Seg!E65 -> 100.299 | F68: =Seg!F66+Seg!F65 -> 117.43835 | G68: =Seg!G66+Seg!G65 -> 132.59536 | H68: =Seg!H66+Seg!H65 -> 147.83381 | I68: =Seg!I66+Seg!I65 -> 162.14567 | J68: =Seg!J66+Seg!J65 -> 175.24933 | K68: =Seg!K66+Seg!K65 -> 187.59928
A69: Productivity and server licensing | B69: US$B | D69: =Q!L8 -> 35.391 | E69: =Q!M8 -> 37.285 | F69: =Q!$I$8+(Q!M8-Q!$E$8)*(1+Seg!F70) -> 38.385144 | G69: =Seg!F69*(1+Seg!G70) -> 40.010535 | H69: =Seg!G69*(1+Seg!H70) -> 41.481251 | I69: =Seg!H69*(1+Seg!I70) -> 42.774311 | J69: =Seg!I69*(1+Seg!J70) -> 43.868737 | K69: =Seg!J69*(1+Seg!K70) -> 44.746112 | L69: FY2027＝Q1 實績＋FY2026 第二至第四季 ×（1＋年增）
A70: 年增（近一年 → 長期值） | B70: % | E70: =Seg!E69/Seg!D69-1 -> 0.053516431 | F70: =Seg!$E$70+(glt_lic-Seg!$E$70)*MIN(1,(Thesis!F110-base_fy)/n_conv) -> 0.047930359 | G70: =Seg!$E$70+(glt_lic-Seg!$E$70)*MIN(1,(Thesis!G110-base_fy)/n_conv) -> 0.042344287 | H70: =Seg!$E$70+(glt_lic-Seg!$E$70)*MIN(1,(Thesis!H110-base_fy)/n_conv) -> 0.036758215 | I70: =Seg!$E$70+(glt_lic-Seg!$E$70)*MIN(1,(Thesis!I110-base_fy)/n_conv) -> 0.031172144 | J70: =Seg!$E$70+(glt_lic-Seg!$E$70)*MIN(1,(Thesis!J110-base_fy)/n_conv) -> 0.025586072 | K70: =Seg!$E$70+(glt_lic-Seg!$E$70)*MIN(1,(Thesis!K110-base_fy)/n_conv) -> 0.02
A71: Industry solutions | B71: US$B | D71: =Q!L9 -> 18.417 | E71: =Q!M9 -> 20.345 | F71: =Q!$I$9+(Q!M9-Q!$E$9)*(1+Seg!F72) -> 22.31618 | G71: =Seg!F71*(1+Seg!G72) -> 24.39435 | H71: =Seg!G71*(1+Seg!H72) -> 26.525024 | I71: =Seg!H71*(1+Seg!I72) -> 28.688457 | J71: =Seg!I71*(1+Seg!J72) -> 30.862497 | K71: =Seg!J71*(1+Seg!K72) -> 33.022872 | L71: FY2027＝Q1 實績＋FY2026 第二至第四季 ×（1＋年增）
A72: 年增（近一年 → 長期值） | B72: % | E72: =Seg!E71/Seg!D71-1 -> 0.10468589 | F72: =Seg!$E$72+(glt_ind-Seg!$E$72)*MIN(1,(Thesis!F110-base_fy)/n_conv) -> 0.098904907 | G72: =Seg!$E$72+(glt_ind-Seg!$E$72)*MIN(1,(Thesis!G110-base_fy)/n_conv) -> 0.093123925 | H72: =Seg!$E$72+(glt_ind-Seg!$E$72)*MIN(1,(Thesis!H110-base_fy)/n_conv) -> 0.087342944 | I72: =Seg!$E$72+(glt_ind-Seg!$E$72)*MIN(1,(Thesis!I110-base_fy)/n_conv) -> 0.081561963 | J72: =Seg!$E$72+(glt_ind-Seg!$E$72)*MIN(1,(Thesis!J110-base_fy)/n_conv) -> 0.075780981 | K72: =Seg!$E$72+(glt_ind-Seg!$E$72)*MIN(1,(Thesis!K110-base_fy)/n_conv) -> 0.07
A73: Frontier and support services | B73: US$B | D73: =Q!L10 -> 7.76 | E73: =Q!M10 -> 8.26 | F73: =Q!$I$10+(Q!M10-Q!$E$10)*(1+Seg!F74) -> 8.7537208 | G73: =Seg!F73*(1+Seg!G74) -> 9.3339932 | H73: =Seg!G73*(1+Seg!H74) -> 9.9613916 | I73: =Seg!H73*(1+Seg!I74) -> 10.640204 | J73: =Seg!I73*(1+Seg!J74) -> 11.375146 | K73: =Seg!J73*(1+Seg!K74) -> 12.171406 | L73: FY2027＝Q1 實績＋FY2026 第二至第四季 ×（1＋年增）
A74: 年增（近一年 → 長期值） | B74: % | E74: =Seg!E73/Seg!D73-1 -> 0.06443299 | F74: =Seg!$E$74+(glt_fro-Seg!$E$74)*MIN(1,(Thesis!F110-base_fy)/n_conv) -> 0.065360825 | G74: =Seg!$E$74+(glt_fro-Seg!$E$74)*MIN(1,(Thesis!G110-base_fy)/n_conv) -> 0.06628866 | H74: =Seg!$E$74+(glt_fro-Seg!$E$74)*MIN(1,(Thesis!H110-base_fy)/n_conv) -> 0.067216495 | I74: =Seg!$E$74+(glt_fro-Seg!$E$74)*MIN(1,(Thesis!I110-base_fy)/n_conv) -> 0.06814433 | J74: =Seg!$E$74+(glt_fro-Seg!$E$74)*MIN(1,(Thesis!J110-base_fy)/n_conv) -> 0.069072165 | K74: =Seg!$E$74+(glt_fro-Seg!$E$74)*MIN(1,(Thesis!K110-base_fy)/n_conv) -> 0.07
A75: Agents and Infra | B75: US$B | D75: =Seg!D63+Seg!D68+Seg!D69+Seg!D71+Seg!D73 -> 218.783 | E75: =Seg!E63+Seg!E68+Seg!E69+Seg!E71+Seg!E73 -> 268.127 | F75: =Seg!F63+Seg!F68+Seg!F69+Seg!F71+Seg!F73 -> 330.14528 | G75: =Seg!G63+Seg!G68+Seg!G69+Seg!G71+Seg!G73 -> 392.65676 | H75: =Seg!H63+Seg!H68+Seg!H69+Seg!H71+Seg!H73 -> 450.54427 | I75: =Seg!I63+Seg!I68+Seg!I69+Seg!I71+Seg!I73 -> 510.69214 | J75: =Seg!J63+Seg!J68+Seg!J69+Seg!J71+Seg!J73 -> 560.41673 | K75: =Seg!K63+Seg!K68+Seg!K69+Seg!K71+Seg!K73 -> 600.13241
A76: Search and advertising | B76: US$B | D76: =Q!L13 -> 22.171 | E76: =Q!M13 -> 24.835 | F76: =Q!$I$13+(Q!M13-Q!$E$13)*(1+Seg!F77) -> 27.55919 | G76: =Seg!F76*(1+Seg!G77) -> 30.409856 | H76: =Seg!G76*(1+Seg!H77) -> 33.301179 | I76: =Seg!H76*(1+Seg!I77) -> 36.189024 | J76: =Seg!I76*(1+Seg!J77) -> 39.024777 | K76: =Seg!J76*(1+Seg!K77) -> 41.756512 | L76: FY2027＝Q1 實績＋FY2026 第二至第四季 ×（1＋年增）
A77: 年增（近一年 → 長期值） | B77: % | E77: =Seg!E76/Seg!D76-1 -> 0.12015696 | F77: =Seg!$E$77+(glt_srch-Seg!$E$77)*MIN(1,(Thesis!F110-base_fy)/n_conv) -> 0.11179747 | G77: =Seg!$E$77+(glt_srch-Seg!$E$77)*MIN(1,(Thesis!G110-base_fy)/n_conv) -> 0.10343797 | H77: =Seg!$E$77+(glt_srch-Seg!$E$77)*MIN(1,(Thesis!H110-base_fy)/n_conv) -> 0.095078481 | I77: =Seg!$E$77+(glt_srch-Seg!$E$77)*MIN(1,(Thesis!I110-base_fy)/n_conv) -> 0.086718987 | J77: =Seg!$E$77+(glt_srch-Seg!$E$77)*MIN(1,(Thesis!J110-base_fy)/n_conv) -> 0.078359494 | K77: =Seg!$E$77+(glt_srch-Seg!$E$77)*MIN(1,(Thesis!K110-base_fy)/n_conv) -> 0.07
A78: XBOX | B78: US$B | D78: =Q!L14 -> 23.455 | E78: =Q!M14 -> 21.79 | F78: =Q!$I$14+(Q!M14-Q!$E$14)*(1+Seg!F79) -> 20.752098 | G78: =Seg!F78*(1+Seg!G79) -> 19.908359 | H78: =Seg!G78*(1+Seg!H79) -> 19.400826 | I78: =Seg!H78*(1+Seg!I79) -> 19.200435 | J78: =Seg!I78*(1+Seg!J79) -> 19.293278 | K78: =Seg!J78*(1+Seg!K79) -> 19.679144 | L78: FY2027＝Q1 實績＋FY2026 第二至第四季 ×（1＋年增）
A79: 年增（近一年 → 長期值） | B79: % | E79: =Seg!E78/Seg!D78-1 -> -0.070986996 | F79: =Seg!$E$79+(glt_xbox-Seg!$E$79)*MIN(1,(Thesis!F110-base_fy)/n_conv) -> -0.055822497 | G79: =Seg!$E$79+(glt_xbox-Seg!$E$79)*MIN(1,(Thesis!G110-base_fy)/n_conv) -> -0.040657998 | H79: =Seg!$E$79+(glt_xbox-Seg!$E$79)*MIN(1,(Thesis!H110-base_fy)/n_conv) -> -0.025493498 | I79: =Seg!$E$79+(glt_xbox-Seg!$E$79)*MIN(1,(Thesis!I110-base_fy)/n_conv) -> -0.010328999 | J79: =Seg!$E$79+(glt_xbox-Seg!$E$79)*MIN(1,(Thesis!J110-base_fy)/n_conv) -> 0.0048355006 | K79: =Seg!$E$79+(glt_xbox-Seg!$E$79)*MIN(1,(Thesis!K110-base_fy)/n_conv) -> 0.02
A80: Windows OEM and devices | B80: US$B | D80: =Q!L15 -> 17.315 | E80: =Q!M15 -> 17.087 | F80: =Q!$I$15+(Q!M15-Q!$E$15)*(1+Seg!F81) -> 15.991227 | G80: =Seg!F80*(1+Seg!G81) -> 15.957456 | H80: =Seg!G80*(1+Seg!H81) -> 16.011969 | I80: =Seg!H80*(1+Seg!I81) -> 16.155181 | J80: =Seg!I80*(1+Seg!J81) -> 16.388979 | K80: =Seg!J80*(1+Seg!K81) -> 16.716759 | L80: FY2027＝Q1 實績＋FY2026 第二至第四季 ×（1＋年增）
A81: 年增（近一年 → 長期值） | B81: % | E81: =Seg!E80/Seg!D80-1 -> -0.013167774 | F81: =Seg!$E$81+(glt_win-Seg!$E$81)*MIN(1,(Thesis!F110-base_fy)/n_conv) -> -0.0076398113 | G81: =Seg!$E$81+(glt_win-Seg!$E$81)*MIN(1,(Thesis!G110-base_fy)/n_conv) -> -0.0021118491 | H81: =Seg!$E$81+(glt_win-Seg!$E$81)*MIN(1,(Thesis!H110-base_fy)/n_conv) -> 0.0034161132 | I81: =Seg!$E$81+(glt_win-Seg!$E$81)*MIN(1,(Thesis!I110-base_fy)/n_conv) -> 0.0089440755 | J81: =Seg!$E$81+(glt_win-Seg!$E$81)*MIN(1,(Thesis!J110-base_fy)/n_conv) -> 0.014472038 | K81: =Seg!$E$81+(glt_win-Seg!$E$81)*MIN(1,(Thesis!K110-base_fy)/n_conv) -> 0.02
A82: Devices and Consumer | B82: US$B | D82: =Seg!D76+Seg!D78+Seg!D80 -> 62.941 | E82: =Seg!E76+Seg!E78+Seg!E80 -> 63.712 | F82: =Seg!F76+Seg!F78+Seg!F80 -> 64.302515 | G82: =Seg!G76+Seg!G78+Seg!G80 -> 66.275672 | H82: =Seg!H76+Seg!H78+Seg!H80 -> 68.713974 | I82: =Seg!I76+Seg!I78+Seg!I80 -> 71.544639 | J82: =Seg!J76+Seg!J78+Seg!J80 -> 74.707035 | K82: =Seg!K76+Seg!K78+Seg!K80 -> 78.152415
A83: 合併營收（分部合計） | B83: US$B | D83: =Seg!D75+Seg!D82 -> 281.724 | E83: =Seg!E75+Seg!E82 -> 331.839 | F83: =Seg!F75+Seg!F82 -> 394.4478 | G83: =Seg!G75+Seg!G82 -> 458.93243 | H83: =Seg!H75+Seg!H82 -> 519.25825 | I83: =Seg!I75+Seg!I82 -> 582.23677 | J83: =Seg!J75+Seg!J82 -> 635.12377 | K83: =Seg!K75+Seg!K82 -> 678.28483
A84: 檢查：產品線合計 − 分部；實績期另比對公司分部值 | B84: US$B | D84: =(Seg!D63+Seg!D68+Seg!D69+Seg!D71+Seg!D73-Seg!D75)+(Seg!D76+Seg!D78+Seg!D80-Seg!D82)+(Seg!D75-Q!L5)+(Seg!D82-Q!L12)+(Seg!D63-Q!L6)+(Seg!D68-Q!L7) -> 0 | E84: =(Seg!E63+Seg!E68+Seg!E69+Seg!E71+Seg!E73-Seg!E75)+(Seg!E76+Seg!E78+Seg!E80-Seg!E82)+(Seg!E75-Q!M5)+(Seg!E82-Q!M12)+(Seg!E63-Q!M6)+(Seg!E68-Q!M7) -> 0 | F84: =(Seg!F63+Seg!F68+Seg!F69+Seg!F71+Seg!F73-Seg!F75)+(Seg!F76+Seg!F78+Seg!F80-Seg!F82) -> 0 | G84: =(Seg!G63+Seg!G68+Seg!G69+Seg!G71+Seg!G73-Seg!G75)+(Seg!G76+Seg!G78+Seg!G80-Seg!G82) -> 0 | H84: =(Seg!H63+Seg!H68+Seg!H69+Seg!H71+Seg!H73-Seg!H75)+(Seg!H76+Seg!H78+Seg!H80-Seg!H82) -> 0 | I84: =(Seg!I63+Seg!I68+Seg!I69+Seg!I71+Seg!I73-Seg!I75)+(Seg!I76+Seg!I78+Seg!I80-Seg!I82) -> 0 | J84: =(Seg!J63+Seg!J68+Seg!J69+Seg!J71+Seg!J73-Seg!J75)+(Seg!J76+Seg!J78+Seg!J80-Seg!J82) -> 0 | K84: =(Seg!K63+Seg!K68+Seg!K69+Seg!K71+Seg!K73-Seg!K75)+(Seg!K76+Seg!K78+Seg!K80-Seg!K82) -> 0

Sheet PL
A1: PL — 分部營收 → 分部營業利益（Agents and Infra 由核心利益率扣 AI 營運成本與 AI 折舊；Devices and Consumer 依實績利益率）→ 合併營業利益 → 業外 → 稅 → 淨利 → EPS
A2: 核對列（三情境、全部年度合計，應為 0；segments.json 與 tools/segment_check 讀這三列）
A3: 項目 | B3: 單位 | C3: FY2024A | D3: FY2025A | E3: FY2026A | F3: FY2027 | G3: FY2028 | H3: FY2029 | I3: FY2030 | J3: FY2031 | K3: FY2032 | L3: 說明
A4: 檢查：分部合計 − 合併營收（三情境，實績期另比對公司值） | B4: US$B | D4: =ABS(PL!D23+PL!D27-PL!D28)+ABS(PL!D28-Q!L18)+ABS(PL!D62+PL!D66-PL!D67)+ABS(PL!D67-Q!L18)+ABS(PL!D101+PL!D105-PL!D106)+ABS(PL!D106-Q!L18) -> 0 | E4: =ABS(PL!E23+PL!E27-PL!E28)+ABS(PL!E28-Q!M18)+ABS(PL!E62+PL!E66-PL!E67)+ABS(PL!E67-Q!M18)+ABS(PL!E101+PL!E105-PL!E106)+ABS(PL!E106-Q!M18) -> 0 | F4: =ABS(PL!F23+PL!F27-PL!F28)+ABS(PL!F62+PL!F66-PL!F67)+ABS(PL!F101+PL!F105-PL!F106) -> 0 | G4: =ABS(PL!G23+PL!G27-PL!G28)+ABS(PL!G62+PL!G66-PL!G67)+ABS(PL!G101+PL!G105-PL!G106) -> 0 | H4: =ABS(PL!H23+PL!H27-PL!H28)+ABS(PL!H62+PL!H66-PL!H67)+ABS(PL!H101+PL!H105-PL!H106) -> 0 | I4: =ABS(PL!I23+PL!I27-PL!I28)+ABS(PL!I62+PL!I66-PL!I67)+ABS(PL!I101+PL!I105-PL!I106) -> 0 | J4: =ABS(PL!J23+PL!J27-PL!J28)+ABS(PL!J62+PL!J66-PL!J67)+ABS(PL!J101+PL!J105-PL!J106) -> 0 | K4: =ABS(PL!K23+PL!K27-PL!K28)+ABS(PL!K62+PL!K66-PL!K67)+ABS(PL!K101+PL!K105-PL!K106) -> 0
A5: 檢查：產品線合計 − 分部（三情境，實績期另比對公司值） | B5: US$B | D5: =ABS(Seg!D30)+ABS(Seg!D57)+ABS(Seg!D84) -> 0 | E5: =ABS(Seg!E30)+ABS(Seg!E57)+ABS(Seg!E84) -> 0 | F5: =ABS(Seg!F30)+ABS(Seg!F57)+ABS(Seg!F84) -> 0 | G5: =ABS(Seg!G30)+ABS(Seg!G57)+ABS(Seg!G84) -> 0 | H5: =ABS(Seg!H30)+ABS(Seg!H57)+ABS(Seg!H84) -> 0 | I5: =ABS(Seg!I30)+ABS(Seg!I57)+ABS(Seg!I84) -> 0 | J5: =ABS(Seg!J30)+ABS(Seg!J57)+ABS(Seg!J84) -> 0 | K5: =ABS(Seg!K30)+ABS(Seg!K57)+ABS(Seg!K84) -> 0
A6: 檢查：命題子列合計 − 母列（Azure、Microsoft 365 cloud；三情境） | B6: US$B | D6: =ABS(PL!D15+PL!D16-PL!D14)+ABS(PL!D18+PL!D19-PL!D17)+ABS(PL!D54+PL!D55-PL!D53)+ABS(PL!D57+PL!D58-PL!D56)+ABS(PL!D93+PL!D94-PL!D92)+ABS(PL!D96+PL!D97-PL!D95) -> 0 | E6: =ABS(PL!E15+PL!E16-PL!E14)+ABS(PL!E18+PL!E19-PL!E17)+ABS(PL!E54+PL!E55-PL!E53)+ABS(PL!E57+PL!E58-PL!E56)+ABS(PL!E93+PL!E94-PL!E92)+ABS(PL!E96+PL!E97-PL!E95) -> 0 | F6: =ABS(PL!F15+PL!F16-PL!F14)+ABS(PL!F18+PL!F19-PL!F17)+ABS(PL!F54+PL!F55-PL!F53)+ABS(PL!F57+PL!F58-PL!F56)+ABS(PL!F93+PL!F94-PL!F92)+ABS(PL!F96+PL!F97-PL!F95) -> 0 | G6: =ABS(PL!G15+PL!G16-PL!G14)+ABS(PL!G18+PL!G19-PL!G17)+ABS(PL!G54+PL!G55-PL!G53)+ABS(PL!G57+PL!G58-PL!G56)+ABS(PL!G93+PL!G94-PL!G92)+ABS(PL!G96+PL!G97-PL!G95) -> 0 | H6: =ABS(PL!H15+PL!H16-PL!H14)+ABS(PL!H18+PL!H19-PL!H17)+ABS(PL!H54+PL!H55-PL!H53)+ABS(PL!H57+PL!H58-PL!H56)+ABS(PL!H93+PL!H94-PL!H92)+ABS(PL!H96+PL!H97-PL!H95) -> 0 | I6: =ABS(PL!I15+PL!I16-PL!I14)+ABS(PL!I18+PL!I19-PL!I17)+ABS(PL!I54+PL!I55-PL!I53)+ABS(PL!I57+PL!I58-PL!I56)+ABS(PL!I93+PL!I94-PL!I92)+ABS(PL!I96+PL!I97-PL!I95) -> 0 | J6: =ABS(PL!J15+PL!J16-PL!J14)+ABS(PL!J18+PL!J19-PL!J17)+ABS(PL!J54+PL!J55-PL!J53)+ABS(PL!J57+PL!J58-PL!J56)+ABS(PL!J93+PL!J94-PL!J92)+ABS(PL!J96+PL!J97-PL!J95) -> 0 | K6: =ABS(PL!K15+PL!K16-PL!K14)+ABS(PL!K18+PL!K19-PL!K17)+ABS(PL!K54+PL!K55-PL!K53)+ABS(PL!K57+PL!K58-PL!K56)+ABS(PL!K93+PL!K94-PL!K92)+ABS(PL!K96+PL!K97-PL!K95) -> 0
A7: 檢查：分部營業利益合計 − 合併營業利益（三情境；實績期比對公司值） | B7: US$B | D7: =ABS(PL!D32+PL!D34-PL!D35)+ABS(PL!D36)+ABS(PL!D71+PL!D73-PL!D74)+ABS(PL!D75)+ABS(PL!D110+PL!D112-PL!D113)+ABS(PL!D114) -> 0 | E7: =ABS(PL!E32+PL!E34-PL!E35)+ABS(PL!E36)+ABS(PL!E71+PL!E73-PL!E74)+ABS(PL!E75)+ABS(PL!E110+PL!E112-PL!E113)+ABS(PL!E114) -> 0 | F7: =ABS(PL!F32+PL!F34-PL!F35)+ABS(PL!F71+PL!F73-PL!F74)+ABS(PL!F110+PL!F112-PL!F113) -> 0 | G7: =ABS(PL!G32+PL!G34-PL!G35)+ABS(PL!G71+PL!G73-PL!G74)+ABS(PL!G110+PL!G112-PL!G113) -> 0 | H7: =ABS(PL!H32+PL!H34-PL!H35)+ABS(PL!H71+PL!H73-PL!H74)+ABS(PL!H110+PL!H112-PL!H113) -> 0 | I7: =ABS(PL!I32+PL!I34-PL!I35)+ABS(PL!I71+PL!I73-PL!I74)+ABS(PL!I110+PL!I112-PL!I113) -> 0 | J7: =ABS(PL!J32+PL!J34-PL!J35)+ABS(PL!J71+PL!J73-PL!J74)+ABS(PL!J110+PL!J112-PL!J113) -> 0 | K7: =ABS(PL!K32+PL!K34-PL!K35)+ABS(PL!K71+PL!K73-PL!K74)+ABS(PL!K110+PL!K112-PL!K113) -> 0
A9: 以下三個區塊依序為情境 A、B、C；分部與產品線列標籤與 8-K 相同（segments.json 對應）
A12: 情境 A（樂觀）｜損益（PL）
A13: 項目 | B13: 單位 | C13: FY2024A | D13: FY2025A | E13: FY2026A | F13: FY2027 | G13: FY2028 | H13: FY2029 | I13: FY2030 | J13: FY2031 | K13: FY2032 | L13: 說明
A14: Azure | B14: US$B | D14: =Seg!D9 -> 72.61 | E14: =Seg!E9 -> 101.938 | F14: =Seg!F9 -> 149.59002 | G14: =Seg!G9 -> 210.96309 | H14: =Seg!H9 -> 278.64971 | I14: =Seg!I9 -> 334.2694 | J14: =Seg!J9 -> 376.51729 | K14: =Seg!K9 -> 406.01809
A15: Azure AI（命題子列） | B15: US$B | D15: =Seg!D6 -> 12.935979 | E15: =Seg!E6 -> 27.809506 | F15: =Seg!F6 -> 59.103417 | G15: =Seg!G6 -> 103.4515 | H15: =Seg!H6 -> 153.81672 | I15: =Seg!I6 -> 192.69948 | J15: =Seg!J6 -> 219.7941 | K15: =Seg!K6 -> 236.75705
A16: Azure 其他 | B16: US$B | D16: =Seg!D7 -> 59.674021 | E16: =Seg!E7 -> 74.128494 | F16: =Seg!F7 -> 90.486602 | G16: =Seg!G7 -> 107.51159 | H16: =Seg!H7 -> 124.83299 | I16: =Seg!I7 -> 141.56993 | J16: =Seg!J7 -> 156.72319 | K16: =Seg!K7 -> 169.26105
A17: Microsoft 365 cloud | B17: US$B | D17: =Seg!D14 -> 84.605 | E17: =Seg!E14 -> 100.299 | F17: =Seg!F14 -> 119.72965 | G17: =Seg!G14 -> 140.80609 | H17: =Seg!H14 -> 161.96344 | I17: =Seg!I14 -> 180.69535 | J17: =Seg!J14 -> 196.72212 | K17: =Seg!K14 -> 212.00017
A18: M365 基礎（不含 Copilot） | B18: US$B | D18: =Seg!D12 -> 83.705 | E18: =Seg!E12 -> 95.049 | F18: =Seg!F12 -> 106.22965 | G18: =Seg!G12 -> 118.30609 | H18: =Seg!H12 -> 130.46344 | I18: =Seg!I12 -> 142.44535 | J18: =Seg!J12 -> 153.97212 | K18: =Seg!K12 -> 164.75017
A19: Copilot（命題子列） | B19: US$B | D19: =Seg!D11 -> 0.9 | E19: =Seg!E11 -> 5.25 | F19: =Seg!F11 -> 13.5 | G19: =Seg!G11 -> 22.5 | H19: =Seg!H11 -> 31.5 | I19: =Seg!I11 -> 38.25 | J19: =Seg!J11 -> 42.75 | K19: =Seg!K11 -> 47.25
A20: Productivity and server licensing | B20: US$B | D20: =Seg!D15 -> 35.391 | E20: =Seg!E15 -> 37.285 | F20: =Seg!F15 -> 38.385144 | G20: =Seg!G15 -> 40.010535 | H20: =Seg!H15 -> 41.481251 | I20: =Seg!I15 -> 42.774311 | J20: =Seg!J15 -> 43.868737 | K20: =Seg!K15 -> 44.746112
A21: Industry solutions | B21: US$B | D21: =Seg!D17 -> 18.417 | E21: =Seg!E17 -> 20.345 | F21: =Seg!F17 -> 22.31618 | G21: =Seg!G17 -> 24.39435 | H21: =Seg!H17 -> 26.525024 | I21: =Seg!I17 -> 28.688457 | J21: =Seg!J17 -> 30.862497 | K21: =Seg!K17 -> 33.022872
A22: Frontier and support services | B22: US$B | D22: =Seg!D19 -> 7.76 | E22: =Seg!E19 -> 8.26 | F22: =Seg!F19 -> 8.7537208 | G22: =Seg!G19 -> 9.3339932 | H22: =Seg!H19 -> 9.9613916 | I22: =Seg!I19 -> 10.640204 | J22: =Seg!J19 -> 11.375146 | K22: =Seg!K19 -> 12.171406
A23: Agents and Infra | B23: US$B | D23: =Seg!D21 -> 218.783 | E23: =Seg!E21 -> 268.127 | F23: =Seg!F21 -> 338.77472 | G23: =Seg!G21 -> 425.50806 | H23: =Seg!H21 -> 518.58081 | I23: =Seg!I21 -> 597.06773 | J23: =Seg!J21 -> 659.34579 | K23: =Seg!K21 -> 707.95865
A24: Search and advertising | B24: US$B | D24: =Seg!D22 -> 22.171 | E24: =Seg!E22 -> 24.835 | F24: =Seg!F22 -> 27.55919 | G24: =Seg!G22 -> 30.409856 | H24: =Seg!H22 -> 33.301179 | I24: =Seg!I22 -> 36.189024 | J24: =Seg!J22 -> 39.024777 | K24: =Seg!K22 -> 41.756512
A25: XBOX | B25: US$B | D25: =Seg!D24 -> 23.455 | E25: =Seg!E24 -> 21.79 | F25: =Seg!F24 -> 20.752098 | G25: =Seg!G24 -> 19.908359 | H25: =Seg!H24 -> 19.400826 | I25: =Seg!I24 -> 19.200435 | J25: =Seg!J24 -> 19.293278 | K25: =Seg!K24 -> 19.679144
A26: Windows OEM and devices | B26: US$B | D26: =Seg!D26 -> 17.315 | E26: =Seg!E26 -> 17.087 | F26: =Seg!F26 -> 15.991227 | G26: =Seg!G26 -> 15.957456 | H26: =Seg!H26 -> 16.011969 | I26: =Seg!I26 -> 16.155181 | J26: =Seg!J26 -> 16.388979 | K26: =Seg!K26 -> 16.716759
A27: Devices and Consumer | B27: US$B | D27: =Seg!D28 -> 62.941 | E27: =Seg!E28 -> 63.712 | F27: =Seg!F28 -> 64.302515 | G27: =Seg!G28 -> 66.275672 | H27: =Seg!H28 -> 68.713974 | I27: =Seg!I28 -> 71.544639 | J27: =Seg!J28 -> 74.707035 | K27: =Seg!K28 -> 78.152415
A28: 合併營收 | B28: US$B | D28: =Seg!D29 -> 281.724 | E28: =Seg!E29 -> 331.839 | F28: =Seg!F29 -> 403.07723 | G28: =Seg!G29 -> 491.78373 | H28: =Seg!H29 -> 587.29479 | I28: =Seg!I29 -> 668.61237 | J28: =Seg!J29 -> 734.05283 | K28: =Seg!K29 -> 786.11106
A29: 營收年增 | B29: % | E29: =PL!E28/PL!D28-1 -> 0.17788687 | F29: =PL!F28/PL!E28-1 -> 0.21467709 | G29: =PL!G28/PL!F28-1 -> 0.22007321 | H29: =PL!H28/PL!G28-1 -> 0.19421354 | I29: =PL!I28/PL!H28-1 -> 0.13846127 | J29: =PL!J28/PL!I28-1 -> 0.097875029 | K29: =PL!K28/PL!J28-1 -> 0.070918925
A30: 檢查：分部合計 − 合併營收；子列合計 − 母列（Azure、M365 cloud） | B30: US$B | D30: =(PL!D23+PL!D27-PL!D28)+(PL!D15+PL!D16-PL!D14)+(PL!D18+PL!D19-PL!D17)+(PL!D28-Q!L18) -> 0 | E30: =(PL!E23+PL!E27-PL!E28)+(PL!E15+PL!E16-PL!E14)+(PL!E18+PL!E19-PL!E17)+(PL!E28-Q!M18) -> 0 | F30: =(PL!F23+PL!F27-PL!F28)+(PL!F15+PL!F16-PL!F14)+(PL!F18+PL!F19-PL!F17) -> 0 | G30: =(PL!G23+PL!G27-PL!G28)+(PL!G15+PL!G16-PL!G14)+(PL!G18+PL!G19-PL!G17) -> 0 | H30: =(PL!H23+PL!H27-PL!H28)+(PL!H15+PL!H16-PL!H14)+(PL!H18+PL!H19-PL!H17) -> 0 | I30: =(PL!I23+PL!I27-PL!I28)+(PL!I15+PL!I16-PL!I14)+(PL!I18+PL!I19-PL!I17) -> 0 | J30: =(PL!J23+PL!J27-PL!J28)+(PL!J15+PL!J16-PL!J14)+(PL!J18+PL!J19-PL!J17) -> 0 | K30: =(PL!K23+PL!K27-PL!K28)+(PL!K15+PL!K16-PL!K14)+(PL!K18+PL!K19-PL!K17) -> 0
A31: Agents and Infra 核心利益率（扣 AI 營運成本與 AI 折舊前；FY2026 校準） | B31: % | E31: =(Q!M21+Thesis!E27+Thesis!E28+Thesis!E29+Thesis!E43-Thesis!E25)/(Q!M5-Thesis!E25) -> 0.57095735 | F31: =PL!$E$31+dm_seg -> 0.57095735 | G31: =PL!$E$31+dm_seg -> 0.57095735 | H31: =PL!$E$31+dm_seg -> 0.57095735 | I31: =PL!$E$31+dm_seg -> 0.57095735 | J31: =PL!$E$31+dm_seg -> 0.57095735 | K31: =PL!$E$31+dm_seg -> 0.57095735 | L31: FY2026：(分部營業利益＋AI 營運成本＋AI 折舊 − Azure AI 營收) ÷ (分部營收 − Azure AI 營收)；之後固定（＋dm_seg）
A32: Agents and Infra 營業利益 | B32: US$B | D32: =Q!L21 -> 110.814 | E32: =Q!M21 -> 136.365 | F32: =Q!$I$21+(PL!F31*(Seg!F21-Thesis!F25)+Thesis!F25-(Thesis!F27+Thesis!F28+Thesis!F29)-Thesis!F43-CF!F18)*(Seg!F21-Q!$I$5)/Seg!F21 -> 165.51894 | G32: =(PL!G31*(Seg!G21-Thesis!G25)+Thesis!G25-(Thesis!G27+Thesis!G28+Thesis!G29)-Thesis!G43-CF!G18) -> 191.52209 | H32: =(PL!H31*(Seg!H21-Thesis!H25)+Thesis!H25-(Thesis!H27+Thesis!H28+Thesis!H29)-Thesis!H43-CF!H18) -> 225.77648 | I32: =(PL!I31*(Seg!I21-Thesis!I25)+Thesis!I25-(Thesis!I27+Thesis!I28+Thesis!I29)-Thesis!I43-CF!I18) -> 251.64174 | J32: =(PL!J31*(Seg!J21-Thesis!J25)+Thesis!J25-(Thesis!J27+Thesis!J28+Thesis!J29)-Thesis!J43-CF!J18) -> 273.89375 | K32: =(PL!K31*(Seg!K21-Thesis!K25)+Thesis!K25-(Thesis!K27+Thesis!K28+Thesis!K29)-Thesis!K43-CF!K18) -> 293.87405 | L32: 修正三：另扣 FY2027 補足差額的折舊；＝核心利益率 ×（分部營收 − Azure AI）＋ Azure AI 營收 − AI 營運成本 − AI 折舊：AI 資本支出經折舊進分部營業利益；v0.3.1：FY2027＝Q1 實績＋全年模型 × 第二至第四季營收占比
A33: Devices and Consumer 營業利益率 | B33: % | E33: =Q!M22/Q!M12 -> 0.29620794 | F33: =PL!$E$33+dm_seg -> 0.29620794 | G33: =PL!$E$33+dm_seg -> 0.29620794 | H33: =PL!$E$33+dm_seg -> 0.29620794 | I33: =PL!$E$33+dm_seg -> 0.29620794 | J33: =PL!$E$33+dm_seg -> 0.29620794 | K33: =PL!$E$33+dm_seg -> 0.29620794 | L33: FY2026 實績後固定（＋dm_seg）
A34: Devices and Consumer 營業利益 | B34: US$B | D34: =Q!L22 -> 17.714 | E34: =Q!M22 -> 18.872 | F34: =Q!$I$22+(Seg!F28-Q!$I$12)*PL!F33 -> 19.817432 | G34: =Seg!G28*PL!G33 -> 19.63138 | H34: =Seg!H28*PL!H33 -> 20.353624 | I34: =Seg!I28*PL!I33 -> 21.19209 | J34: =Seg!J28*PL!J33 -> 22.128817 | K34: =Seg!K28*PL!K33 -> 23.149365 | L34: FY2027＝Q1 實績＋第二至第四季營收 × 利益率
A35: 合併營業利益（財報口徑；分部合計，無未分攤項） | B35: US$B | D35: =PL!D32+PL!D34 -> 128.528 | E35: =PL!E32+PL!E34 -> 155.237 | F35: =PL!F32+PL!F34 -> 185.33637 | G35: =PL!G32+PL!G34 -> 211.15347 | H35: =PL!H32+PL!H34 -> 246.13011 | I35: =PL!I32+PL!I34 -> 272.83383 | J35: =PL!J32+PL!J34 -> 296.02256 | K35: =PL!K32+PL!K34 -> 317.02341
A36: 檢查：分部營業利益合計 − 公司合併營業利益（實績） | B36: US$B | D36: =PL!D35-Q!L23 -> 0 | E36: =PL!E35-Q!M23 -> 0
A37: 營業利益率（財報口徑） | B37: % | D37: =PL!D35/PL!D28 -> 0.45621956 | E37: =PL!E35/PL!E28 -> 0.46780818 | F37: =PL!F35/PL!F28 -> 0.45980362 | G37: =PL!G35/PL!G28 -> 0.42936246 | H37: =PL!H35/PL!H28 -> 0.41909125 | I37: =PL!I35/PL!I28 -> 0.4080598 | J37: =PL!J35/PL!J28 -> 0.40327147 | K37: =PL!K35/PL!K28 -> 0.40328069
A38: 自用 AI 影子效益（讀法 2；非財報營收；分攤到 Agents and Infra） | B38: US$B | F38: =Thesis!F47 -> 8.8834067 | G38: =Thesis!G47 -> 22.706031 | H38: =Thesis!H47 -> 38.001845 | I38: =Thesis!I47 -> 52.138109 | J38: =Thesis!J47 -> 62.059582 | K38: =Thesis!K47 -> 67.080131 | L38: 修正一 F1：營收與分部對帳不動；只進評價口徑的營業利益、淨利、EPS 與 DCF
A39: 營業利益（評價口徑＝財報＋自用 AI 影子效益） | B39: US$B | D39: =PL!D35 -> 128.528 | E39: =PL!E35 -> 155.237 | F39: =PL!F35+PL!F38 -> 194.21978 | G39: =PL!G35+PL!G38 -> 233.8595 | H39: =PL!H35+PL!H38 -> 284.13195 | I39: =PL!I35+PL!I38 -> 324.97194 | J39: =PL!J35+PL!J38 -> 358.08214 | K39: =PL!K35+PL!K38 -> 384.10354
A40: 備忘：AI 折舊（Thesis） | B40: US$B | E40: =Thesis!E43 -> 16.305406 | F40: =Thesis!F43 -> 34.579314 | G40: =Thesis!G43 -> 60.734491 | H40: =Thesis!H43 -> 89.100091 | I40: =Thesis!I43 -> 114.23101 | J40: =Thesis!J43 -> 132.01567 | K40: =Thesis!K43 -> 143.01267
A41: 備忘：非 AI 折舊攤銷（CF） | B41: US$B | E41: =CF!E17 -> 22.228594 | F41: =CF!F17 -> 23.580344 | G41: =CF!G17 -> 25.380142 | H41: =CF!H17 -> 27.596464 | I41: =CF!I17 -> 30.152941 | J41: =CF!J17 -> 32.957502 | K41: =CF!K17 -> 35.925678
A42: 業外收支（預測期不含持股評價損益＝0） | B42: US$B | D42: =Q!L27 -> -4.901 | E42: =Q!M27 -> 10.697 | F42: =Q!$I$27+oie_f*(q_per_yr-1)/q_per_yr -> -0.862 | G42: =oie_f -> -1.2 | H42: =oie_f -> -1.2 | I42: =oie_f -> -1.2 | J42: =oie_f -> -1.2 | K42: =oie_f -> -1.2 | L42: FY2026 含 OpenAI 重組利得等 +6.5；FY2027 Q1 實績 +0.038（含 OpenAI 稅前利得 0.272）＋其餘三季 × oie_f
A43: 稅前淨利（財報口徑） | B43: US$B | D43: =PL!D35+PL!D42 -> 123.627 | E43: =PL!E35+PL!E42 -> 165.934 | F43: =PL!F35+PL!F42 -> 184.47437 | G43: =PL!G35+PL!G42 -> 209.95347 | H43: =PL!H35+PL!H42 -> 244.93011 | I43: =PL!I35+PL!I42 -> 271.63383 | J43: =PL!J35+PL!J42 -> 294.82256 | K43: =PL!K35+PL!K42 -> 315.82341
A44: 所得稅（財報口徑） | B44: US$B | D44: =Q!L29 -> 21.795 | E44: =Q!M29 -> 32.185 | F44: =Q!$I$29+(PL!F43-Q!$I$28)*tax_f -> 37.028274 | G44: =PL!G43*tax_f -> 41.990695 | H44: =PL!H43*tax_f -> 48.986022 | I44: =PL!I43*tax_f -> 54.326767 | J44: =PL!J43*tax_f -> 58.964512 | K44: =PL!K43*tax_f -> 63.164682
A45: 淨利（財報口徑） | B45: US$B | D45: =PL!D43-PL!D44 -> 101.832 | E45: =PL!E43-PL!E44 -> 133.749 | F45: =PL!F43-PL!F44 -> 147.4461 | G45: =PL!G43-PL!G44 -> 167.96278 | H45: =PL!H43-PL!H44 -> 195.94409 | I45: =PL!I43-PL!I44 -> 217.30707 | J45: =PL!J43-PL!J44 -> 235.85805 | K45: =PL!K43-PL!K44 -> 252.65873
A46: 稀釋股數（十億股；回購依 CF 頁） | B46: 十億股 | D46: =Q!L31 -> 7.465 | E46: =Q!M31 -> 7.453 | F46: =CF!F42 -> 7.4706327 | G46: =CF!G42 -> 7.5099036 | H46: =CF!H42 -> 7.5347418 | I46: =CF!I42 -> 7.5464231 | J46: =CF!J42 -> 7.5605725 | K46: =CF!K42 -> 7.5770072
A47: EPS（財報口徑，US$） | B47: US$ | D47: =PL!D45/PL!D46 -> 13.641259 | E47: =PL!E45/PL!E46 -> 17.945659 | F47: =PL!F45/PL!F46 -> 19.736762 | G47: =PL!G45/PL!G46 -> 22.365504 | H47: =PL!H45/PL!H46 -> 26.005415 | I47: =PL!I45/PL!I46 -> 28.796035 | J47: =PL!J45/PL!J46 -> 31.195792 | K47: =PL!K45/PL!K46 -> 33.345452 | L47: 實績期與公司 EPS 差 < 0.01（四捨五入）
A48: 淨利（評價口徑＝財報＋影子效益 ×（1 − 稅率）） | B48: US$B | D48: =PL!D45 -> 101.832 | E48: =PL!E45 -> 133.749 | F48: =PL!F45+PL!F38*(1-tax_f) -> 154.55282 | G48: =PL!G45+PL!G38*(1-tax_f) -> 186.1276 | H48: =PL!H45+PL!H38*(1-tax_f) -> 226.34556 | I48: =PL!I45+PL!I38*(1-tax_f) -> 259.01755 | J48: =PL!J45+PL!J38*(1-tax_f) -> 285.50571 | K48: =PL!K45+PL!K38*(1-tax_f) -> 306.32283
A49: EPS（評價口徑，US$） | B49: US$ | D49: =PL!D48/PL!D46 -> 13.641259 | E49: =PL!E48/PL!E46 -> 17.945659 | F49: =PL!F48/PL!F46 -> 20.68805 | G49: =PL!G48/PL!G46 -> 24.784287 | H49: =PL!H48/PL!H46 -> 30.040255 | I49: =PL!I48/PL!I46 -> 34.323222 | J49: =PL!J48/PL!J46 -> 37.762446 | K49: =PL!K48/PL!K46 -> 40.427946 | L49: 讀法 2 主值；讀法 1 時＝財報口徑
A50: EPS 年增（評價口徑） | B50: % | E50: =PL!E49/PL!D49-1 -> 0.31554274 | F50: =PL!F49/PL!E49-1 -> 0.15281637 | G50: =PL!G49/PL!F49-1 -> 0.19800013 | H50: =PL!H49/PL!G49-1 -> 0.21206857 | I50: =PL!I49/PL!H49-1 -> 0.14257425 | J50: =PL!J49/PL!I49-1 -> 0.1002011 | K50: =PL!K49/PL!J49-1 -> 0.070585978
A51: 情境 B（基準）｜損益（PL）
A52: 項目 | B52: 單位 | C52: FY2024A | D52: FY2025A | E52: FY2026A | F52: FY2027 | G52: FY2028 | H52: FY2029 | I52: FY2030 | J52: FY2031 | K52: FY2032 | L52: 說明
A53: Azure | B53: US$B | D53: =Seg!D36 -> 72.61 | E53: =Seg!E36 -> 101.938 | F53: =Seg!F36 -> 146.70905 | G53: =Seg!G36 -> 199.76283 | H53: =Seg!H36 -> 254.14657 | I53: =Seg!I36 -> 303.43945 | J53: =Seg!J36 -> 341.3099 | K53: =Seg!K36 -> 368.09748
A54: Azure AI（命題子列） | B54: US$B | D54: =Seg!D33 -> 12.935979 | E54: =Seg!E33 -> 27.809506 | F54: =Seg!F33 -> 55.411832 | G54: =Seg!G33 -> 91.28811 | H54: =Seg!H33 -> 128.19527 | I54: =Seg!I33 -> 160.60128 | J54: =Seg!J33 -> 183.18272 | K54: =Seg!K33 -> 197.32012
A55: Azure 其他 | B55: US$B | D55: =Seg!D34 -> 59.674021 | E55: =Seg!E34 -> 74.128494 | F55: =Seg!F34 -> 91.297216 | G55: =Seg!G34 -> 108.47472 | H55: =Seg!H34 -> 125.95129 | I55: =Seg!I34 -> 142.83817 | J55: =Seg!J34 -> 158.12718 | K55: =Seg!K34 -> 170.77735
A56: Microsoft 365 cloud | B56: US$B | D56: =Seg!D41 -> 84.605 | E56: =Seg!E41 -> 100.299 | F56: =Seg!F41 -> 118.584 | G56: =Seg!G41 -> 136.70073 | H56: =Seg!H41 -> 154.89862 | I56: =Seg!I41 -> 171.42051 | J56: =Seg!J41 -> 185.98572 | K56: =Seg!K41 -> 199.79972
A57: M365 基礎（不含 Copilot） | B57: US$B | D57: =Seg!D39 -> 83.705 | E57: =Seg!E39 -> 95.049 | F57: =Seg!F39 -> 106.584 | G57: =Seg!G39 -> 118.70073 | H57: =Seg!H39 -> 130.89862 | I57: =Seg!I39 -> 142.92051 | J57: =Seg!J39 -> 154.48572 | K57: =Seg!K39 -> 165.29972
A58: Copilot（命題子列） | B58: US$B | D58: =Seg!D38 -> 0.9 | E58: =Seg!E38 -> 5.25 | F58: =Seg!F38 -> 12 | G58: =Seg!G38 -> 18 | H58: =Seg!H38 -> 24 | I58: =Seg!I38 -> 28.5 | J58: =Seg!J38 -> 31.5 | K58: =Seg!K38 -> 34.5
A59: Productivity and server licensing | B59: US$B | D59: =Seg!D42 -> 35.391 | E59: =Seg!E42 -> 37.285 | F59: =Seg!F42 -> 38.385144 | G59: =Seg!G42 -> 40.010535 | H59: =Seg!H42 -> 41.481251 | I59: =Seg!I42 -> 42.774311 | J59: =Seg!J42 -> 43.868737 | K59: =Seg!K42 -> 44.746112
A60: Industry solutions | B60: US$B | D60: =Seg!D44 -> 18.417 | E60: =Seg!E44 -> 20.345 | F60: =Seg!F44 -> 22.31618 | G60: =Seg!G44 -> 24.39435 | H60: =Seg!H44 -> 26.525024 | I60: =Seg!I44 -> 28.688457 | J60: =Seg!J44 -> 30.862497 | K60: =Seg!K44 -> 33.022872
A61: Frontier and support services | B61: US$B | D61: =Seg!D46 -> 7.76 | E61: =Seg!E46 -> 8.26 | F61: =Seg!F46 -> 8.7537208 | G61: =Seg!G46 -> 9.3339932 | H61: =Seg!H46 -> 9.9613916 | I61: =Seg!I46 -> 10.640204 | J61: =Seg!J46 -> 11.375146 | K61: =Seg!K46 -> 12.171406
A62: Agents and Infra | B62: US$B | D62: =Seg!D48 -> 218.783 | E62: =Seg!E48 -> 268.127 | F62: =Seg!F48 -> 334.7481 | G62: =Seg!G48 -> 410.20243 | H62: =Seg!H48 -> 487.01286 | I62: =Seg!I48 -> 556.96293 | J62: =Seg!J48 -> 613.402 | K62: =Seg!K48 -> 657.83759
A63: Search and advertising | B63: US$B | D63: =Seg!D49 -> 22.171 | E63: =Seg!E49 -> 24.835 | F63: =Seg!F49 -> 27.55919 | G63: =Seg!G49 -> 30.409856 | H63: =Seg!H49 -> 33.301179 | I63: =Seg!I49 -> 36.189024 | J63: =Seg!J49 -> 39.024777 | K63: =Seg!K49 -> 41.756512
A64: XBOX | B64: US$B | D64: =Seg!D51 -> 23.455 | E64: =Seg!E51 -> 21.79 | F64: =Seg!F51 -> 20.752098 | G64: =Seg!G51 -> 19.908359 | H64: =Seg!H51 -> 19.400826 | I64: =Seg!I51 -> 19.200435 | J64: =Seg!J51 -> 19.293278 | K64: =Seg!K51 -> 19.679144
A65: Windows OEM and devices | B65: US$B | D65: =Seg!D53 -> 17.315 | E65: =Seg!E53 -> 17.087 | F65: =Seg!F53 -> 15.991227 | G65: =Seg!G53 -> 15.957456 | H65: =Seg!H53 -> 16.011969 | I65: =Seg!I53 -> 16.155181 | J65: =Seg!J53 -> 16.388979 | K65: =Seg!K53 -> 16.716759
A66: Devices and Consumer | B66: US$B | D66: =Seg!D55 -> 62.941 | E66: =Seg!E55 -> 63.712 | F66: =Seg!F55 -> 64.302515 | G66: =Seg!G55 -> 66.275672 | H66: =Seg!H55 -> 68.713974 | I66: =Seg!I55 -> 71.544639 | J66: =Seg!J55 -> 74.707035 | K66: =Seg!K55 -> 78.152415
A67: 合併營收 | B67: US$B | D67: =Seg!D56 -> 281.724 | E67: =Seg!E56 -> 331.839 | F67: =Seg!F56 -> 399.05061 | G67: =Seg!G56 -> 476.47811 | H67: =Seg!H56 -> 555.72683 | I67: =Seg!I56 -> 628.50757 | J67: =Seg!J56 -> 688.10904 | K67: =Seg!K56 -> 735.99001
A68: 營收年增 | B68: % | E68: =PL!E67/PL!D67-1 -> 0.17788687 | F68: =PL!F67/PL!E67-1 -> 0.20254283 | G68: =PL!G67/PL!F67-1 -> 0.19402926 | H68: =PL!H67/PL!G67-1 -> 0.16632186 | I68: =PL!I67/PL!H67-1 -> 0.13096495 | J68: =PL!J67/PL!I67-1 -> 0.094830151 | K68: =PL!K67/PL!J67-1 -> 0.069583404
A69: 檢查：分部合計 − 合併營收；子列合計 − 母列（Azure、M365 cloud） | B69: US$B | D69: =(PL!D62+PL!D66-PL!D67)+(PL!D54+PL!D55-PL!D53)+(PL!D57+PL!D58-PL!D56)+(PL!D67-Q!L18) -> 0 | E69: =(PL!E62+PL!E66-PL!E67)+(PL!E54+PL!E55-PL!E53)+(PL!E57+PL!E58-PL!E56)+(PL!E67-Q!M18) -> 0 | F69: =(PL!F62+PL!F66-PL!F67)+(PL!F54+PL!F55-PL!F53)+(PL!F57+PL!F58-PL!F56) -> 0 | G69: =(PL!G62+PL!G66-PL!G67)+(PL!G54+PL!G55-PL!G53)+(PL!G57+PL!G58-PL!G56) -> 0 | H69: =(PL!H62+PL!H66-PL!H67)+(PL!H54+PL!H55-PL!H53)+(PL!H57+PL!H58-PL!H56) -> 0 | I69: =(PL!I62+PL!I66-PL!I67)+(PL!I54+PL!I55-PL!I53)+(PL!I57+PL!I58-PL!I56) -> 0 | J69: =(PL!J62+PL!J66-PL!J67)+(PL!J54+PL!J55-PL!J53)+(PL!J57+PL!J58-PL!J56) -> 0 | K69: =(PL!K62+PL!K66-PL!K67)+(PL!K54+PL!K55-PL!K53)+(PL!K57+PL!K58-PL!K56) -> 0
A70: Agents and Infra 核心利益率（扣 AI 營運成本與 AI 折舊前；FY2026 校準） | B70: % | E70: =(Q!M21+Thesis!E79+Thesis!E80+Thesis!E81+Thesis!E95-Thesis!E77)/(Q!M5-Thesis!E77) -> 0.57095735 | F70: =PL!$E$70+dm_seg -> 0.57095735 | G70: =PL!$E$70+dm_seg -> 0.57095735 | H70: =PL!$E$70+dm_seg -> 0.57095735 | I70: =PL!$E$70+dm_seg -> 0.57095735 | J70: =PL!$E$70+dm_seg -> 0.57095735 | K70: =PL!$E$70+dm_seg -> 0.57095735 | L70: FY2026：(分部營業利益＋AI 營運成本＋AI 折舊 − Azure AI 營收) ÷ (分部營收 − Azure AI 營收)；之後固定（＋dm_seg）
A71: Agents and Infra 營業利益 | B71: US$B | D71: =Q!L21 -> 110.814 | E71: =Q!M21 -> 136.365 | F71: =Q!$I$21+(PL!F70*(Seg!F48-Thesis!F77)+Thesis!F77-(Thesis!F79+Thesis!F80+Thesis!F81)-Thesis!F95-CF!F50)*(Seg!F48-Q!$I$5)/Seg!F48 -> 162.08989 | G71: =(PL!G70*(Seg!G48-Thesis!G77)+Thesis!G77-(Thesis!G79+Thesis!G80+Thesis!G81)-Thesis!G95-CF!G50) -> 177.5689 | H71: =(PL!H70*(Seg!H48-Thesis!H77)+Thesis!H77-(Thesis!H79+Thesis!H80+Thesis!H81)-Thesis!H95-CF!H50) -> 196.76369 | I71: =(PL!I70*(Seg!I48-Thesis!I77)+Thesis!I77-(Thesis!I79+Thesis!I80+Thesis!I81)-Thesis!I95-CF!I50) -> 214.97558 | J71: =(PL!J70*(Seg!J48-Thesis!J77)+Thesis!J77-(Thesis!J79+Thesis!J80+Thesis!J81)-Thesis!J95-CF!J50) -> 231.95708 | K71: =(PL!K70*(Seg!K48-Thesis!K77)+Thesis!K77-(Thesis!K79+Thesis!K80+Thesis!K81)-Thesis!K95-CF!K50) -> 248.33975 | L71: 修正三：另扣 FY2027 補足差額的折舊；＝核心利益率 ×（分部營收 − Azure AI）＋ Azure AI 營收 − AI 營運成本 − AI 折舊：AI 資本支出經折舊進分部營業利益；v0.3.1：FY2027＝Q1 實績＋全年模型 × 第二至第四季營收占比
A72: Devices and Consumer 營業利益率 | B72: % | E72: =Q!M22/Q!M12 -> 0.29620794 | F72: =PL!$E$72+dm_seg -> 0.29620794 | G72: =PL!$E$72+dm_seg -> 0.29620794 | H72: =PL!$E$72+dm_seg -> 0.29620794 | I72: =PL!$E$72+dm_seg -> 0.29620794 | J72: =PL!$E$72+dm_seg -> 0.29620794 | K72: =PL!$E$72+dm_seg -> 0.29620794 | L72: FY2026 實績後固定（＋dm_seg）
A73: Devices and Consumer 營業利益 | B73: US$B | D73: =Q!L22 -> 17.714 | E73: =Q!M22 -> 18.872 | F73: =Q!$I$22+(Seg!F55-Q!$I$12)*PL!F72 -> 19.817432 | G73: =Seg!G55*PL!G72 -> 19.63138 | H73: =Seg!H55*PL!H72 -> 20.353624 | I73: =Seg!I55*PL!I72 -> 21.19209 | J73: =Seg!J55*PL!J72 -> 22.128817 | K73: =Seg!K55*PL!K72 -> 23.149365 | L73: FY2027＝Q1 實績＋第二至第四季營收 × 利益率
A74: 合併營業利益（財報口徑；分部合計，無未分攤項） | B74: US$B | D74: =PL!D71+PL!D73 -> 128.528 | E74: =PL!E71+PL!E73 -> 155.237 | F74: =PL!F71+PL!F73 -> 181.90732 | G74: =PL!G71+PL!G73 -> 197.20028 | H74: =PL!H71+PL!H73 -> 217.11731 | I74: =PL!I71+PL!I73 -> 236.16767 | J74: =PL!J71+PL!J73 -> 254.08589 | K74: =PL!K71+PL!K73 -> 271.48911
A75: 檢查：分部營業利益合計 − 公司合併營業利益（實績） | B75: US$B | D75: =PL!D74-Q!L23 -> 0 | E75: =PL!E74-Q!M23 -> 0
A76: 營業利益率（財報口徑） | B76: % | D76: =PL!D74/PL!D67 -> 0.45621956 | E76: =PL!E74/PL!E67 -> 0.46780818 | F76: =PL!F74/PL!F67 -> 0.45585024 | G76: =PL!G74/PL!G67 -> 0.41387061 | H76: =PL!H74/PL!H67 -> 0.39069071 | I76: =PL!I74/PL!I67 -> 0.37575947 | J76: =PL!J74/PL!J67 -> 0.36925237 | K76: =PL!K74/PL!K67 -> 0.36887608
A77: 自用 AI 影子效益（讀法 2；非財報營收；分攤到 Agents and Infra） | B77: US$B | F77: =Thesis!F99 -> 9.7398428 | G77: =Thesis!G99 -> 25.275339 | H77: =Thesis!H99 -> 42.284025 | I77: =Thesis!I99 -> 57.704944 | J77: =Thesis!J99 -> 68.482852 | K77: =Thesis!K99 -> 74.359837 | L77: 修正一 F1：營收與分部對帳不動；只進評價口徑的營業利益、淨利、EPS 與 DCF
A78: 營業利益（評價口徑＝財報＋自用 AI 影子效益） | B78: US$B | D78: =PL!D74 -> 128.528 | E78: =PL!E74 -> 155.237 | F78: =PL!F74+PL!F77 -> 191.64716 | G78: =PL!G74+PL!G77 -> 222.47562 | H78: =PL!H74+PL!H77 -> 259.40134 | I78: =PL!I74+PL!I77 -> 293.87262 | J78: =PL!J74+PL!J77 -> 322.56875 | K78: =PL!K74+PL!K77 -> 345.84895
A79: 備忘：AI 折舊（Thesis） | B79: US$B | E79: =Thesis!E95 -> 16.305406 | F79: =Thesis!F95 -> 34.579314 | G79: =Thesis!G95 -> 60.734491 | H79: =Thesis!H95 -> 89.100091 | I79: =Thesis!I95 -> 114.23101 | J79: =Thesis!J95 -> 132.01567 | K79: =Thesis!K95 -> 143.01267
A80: 備忘：非 AI 折舊攤銷（CF） | B80: US$B | E80: =CF!E49 -> 22.228594 | F80: =CF!F49 -> 23.580344 | G80: =CF!G49 -> 25.358351 | H80: =CF!H49 -> 27.52857 | I80: =CF!I49 -> 30.024452 | J80: =CF!J49 -> 32.762579 | K80: =CF!K49 -> 35.658568
A81: 業外收支（預測期不含持股評價損益＝0） | B81: US$B | D81: =Q!L27 -> -4.901 | E81: =Q!M27 -> 10.697 | F81: =Q!$I$27+oie_f*(q_per_yr-1)/q_per_yr -> -0.862 | G81: =oie_f -> -1.2 | H81: =oie_f -> -1.2 | I81: =oie_f -> -1.2 | J81: =oie_f -> -1.2 | K81: =oie_f -> -1.2 | L81: FY2026 含 OpenAI 重組利得等 +6.5；FY2027 Q1 實績 +0.038（含 OpenAI 稅前利得 0.272）＋其餘三季 × oie_f
A82: 稅前淨利（財報口徑） | B82: US$B | D82: =PL!D74+PL!D81 -> 123.627 | E82: =PL!E74+PL!E81 -> 165.934 | F82: =PL!F74+PL!F81 -> 181.04532 | G82: =PL!G74+PL!G81 -> 196.00028 | H82: =PL!H74+PL!H81 -> 215.91731 | I82: =PL!I74+PL!I81 -> 234.96767 | J82: =PL!J74+PL!J81 -> 252.88589 | K82: =PL!K74+PL!K81 -> 270.28911
A83: 所得稅（財報口徑） | B83: US$B | D83: =Q!L29 -> 21.795 | E83: =Q!M29 -> 32.185 | F83: =Q!$I$29+(PL!F82-Q!$I$28)*tax_f -> 36.342464 | G83: =PL!G82*tax_f -> 39.200057 | H83: =PL!H82*tax_f -> 43.183462 | I83: =PL!I82*tax_f -> 46.993535 | J83: =PL!J82*tax_f -> 50.577179 | K83: =PL!K82*tax_f -> 54.057822
A84: 淨利（財報口徑） | B84: US$B | D84: =PL!D82-PL!D83 -> 101.832 | E84: =PL!E82-PL!E83 -> 133.749 | F84: =PL!F82-PL!F83 -> 144.70285 | G84: =PL!G82-PL!G83 -> 156.80023 | H84: =PL!H82-PL!H83 -> 172.73385 | I84: =PL!I82-PL!I83 -> 187.97414 | J84: =PL!J82-PL!J83 -> 202.30871 | K84: =PL!K82-PL!K83 -> 216.23129
A85: 稀釋股數（十億股；回購依 CF 頁） | B85: 十億股 | D85: =Q!L31 -> 7.465 | E85: =Q!M31 -> 7.453 | F85: =CF!F74 -> 7.4732546 | G85: =CF!G74 -> 7.5180092 | H85: =CF!H74 -> 7.5457092 | I85: =CF!I74 -> 7.5573905 | J85: =CF!J74 -> 7.5715399 | K85: =CF!K74 -> 7.5879746
A86: EPS（財報口徑，US$） | B86: US$ | D86: =PL!D84/PL!D85 -> 13.641259 | E86: =PL!E84/PL!E85 -> 17.945659 | F86: =PL!F84/PL!F85 -> 19.362763 | G86: =PL!G84/PL!G85 -> 20.856615 | H86: =PL!H84/PL!H85 -> 22.891665 | I86: =PL!I84/PL!I85 -> 24.872889 | J86: =PL!J84/PL!J85 -> 26.719626 | K86: =PL!K84/PL!K85 -> 28.496575 | L86: 實績期與公司 EPS 差 < 0.01（四捨五入）
A87: 淨利（評價口徑＝財報＋影子效益 ×（1 − 稅率）） | B87: US$B | D87: =PL!D84 -> 101.832 | E87: =PL!E84 -> 133.749 | F87: =PL!F84+PL!F77*(1-tax_f) -> 152.49473 | G87: =PL!G84+PL!G77*(1-tax_f) -> 177.0205 | H87: =PL!H84+PL!H77*(1-tax_f) -> 206.56107 | I87: =PL!I84+PL!I77*(1-tax_f) -> 234.13809 | J87: =PL!J84+PL!J77*(1-tax_f) -> 257.095 | K87: =PL!K84+PL!K77*(1-tax_f) -> 275.71916
A88: EPS（評價口徑，US$） | B88: US$ | D88: =PL!D87/PL!D85 -> 13.641259 | E88: =PL!E87/PL!E85 -> 17.945659 | F88: =PL!F87/PL!F85 -> 20.405397 | G88: =PL!G87/PL!G85 -> 23.546193 | H88: =PL!H87/PL!H85 -> 27.37464 | I88: =PL!I87/PL!I85 -> 30.981341 | J88: =PL!J87/PL!J85 -> 33.955444 | K88: =PL!K87/PL!K85 -> 36.336332 | L88: 讀法 2 主值；讀法 1 時＝財報口徑
A89: EPS 年增（評價口徑） | B89: % | E89: =PL!E88/PL!D88-1 -> 0.31554274 | F89: =PL!F88/PL!E88-1 -> 0.13706589 | G89: =PL!G88/PL!F88-1 -> 0.15391986 | H89: =PL!H88/PL!G88-1 -> 0.16259301 | I89: =PL!I88/PL!H88-1 -> 0.13175339 | J89: =PL!J88/PL!I88-1 -> 0.095996567 | K89: =PL!K88/PL!J88-1 -> 0.070118007
A90: 情境 C（保守）｜損益（PL）
A91: 項目 | B91: 單位 | C91: FY2024A | D91: FY2025A | E91: FY2026A | F91: FY2027 | G91: FY2028 | H91: FY2029 | I91: FY2030 | J91: FY2031 | K91: FY2032 | L91: 說明
A92: Azure | B92: US$B | D92: =Seg!D63 -> 72.61 | E92: =Seg!E63 -> 101.938 | F92: =Seg!F63 -> 143.25188 | G92: =Seg!G63 -> 186.32252 | H92: =Seg!H63 -> 224.74279 | I92: =Seg!I63 -> 266.4435 | J92: =Seg!J63 -> 299.06102 | K92: =Seg!K63 -> 322.59274
A93: Azure AI（命題子列） | B93: US$B | D93: =Seg!D60 -> 12.935979 | E93: =Seg!E60 -> 27.809506 | F93: =Seg!F60 -> 50.981929 | G93: =Seg!G60 -> 76.692044 | H93: =Seg!H60 -> 97.449538 | I93: =Seg!I60 -> 122.08345 | J93: =Seg!J60 -> 139.24906 | K93: =Seg!K60 -> 149.99582
A94: Azure 其他 | B94: US$B | D94: =Seg!D61 -> 59.674021 | E94: =Seg!E61 -> 74.128494 | F94: =Seg!F61 -> 92.269954 | G94: =Seg!G61 -> 109.63048 | H94: =Seg!H61 -> 127.29326 | I94: =Seg!I61 -> 144.36005 | J94: =Seg!J61 -> 159.81196 | K94: =Seg!K61 -> 172.59692
A95: Microsoft 365 cloud | B95: US$B | D95: =Seg!D68 -> 84.605 | E95: =Seg!E68 -> 100.299 | F95: =Seg!F68 -> 117.43835 | G95: =Seg!G68 -> 132.59536 | H95: =Seg!H68 -> 147.83381 | I95: =Seg!I68 -> 162.14567 | J95: =Seg!J68 -> 175.24933 | K95: =Seg!K68 -> 187.59928
A96: M365 基礎（不含 Copilot） | B96: US$B | D96: =Seg!D66 -> 83.705 | E96: =Seg!E66 -> 95.049 | F96: =Seg!F66 -> 106.93835 | G96: =Seg!G66 -> 119.09536 | H96: =Seg!H66 -> 131.33381 | I96: =Seg!I66 -> 143.39567 | J96: =Seg!J66 -> 154.99933 | K96: =Seg!K66 -> 165.84928
A97: Copilot（命題子列） | B97: US$B | D97: =Seg!D65 -> 0.9 | E97: =Seg!E65 -> 5.25 | F97: =Seg!F65 -> 10.5 | G97: =Seg!G65 -> 13.5 | H97: =Seg!H65 -> 16.5 | I97: =Seg!I65 -> 18.75 | J97: =Seg!J65 -> 20.25 | K97: =Seg!K65 -> 21.75
A98: Productivity and server licensing | B98: US$B | D98: =Seg!D69 -> 35.391 | E98: =Seg!E69 -> 37.285 | F98: =Seg!F69 -> 38.385144 | G98: =Seg!G69 -> 40.010535 | H98: =Seg!H69 -> 41.481251 | I98: =Seg!I69 -> 42.774311 | J98: =Seg!J69 -> 43.868737 | K98: =Seg!K69 -> 44.746112
A99: Industry solutions | B99: US$B | D99: =Seg!D71 -> 18.417 | E99: =Seg!E71 -> 20.345 | F99: =Seg!F71 -> 22.31618 | G99: =Seg!G71 -> 24.39435 | H99: =Seg!H71 -> 26.525024 | I99: =Seg!I71 -> 28.688457 | J99: =Seg!J71 -> 30.862497 | K99: =Seg!K71 -> 33.022872
A100: Frontier and support services | B100: US$B | D100: =Seg!D73 -> 7.76 | E100: =Seg!E73 -> 8.26 | F100: =Seg!F73 -> 8.7537208 | G100: =Seg!G73 -> 9.3339932 | H100: =Seg!H73 -> 9.9613916 | I100: =Seg!I73 -> 10.640204 | J100: =Seg!J73 -> 11.375146 | K100: =Seg!K73 -> 12.171406
A101: Agents and Infra | B101: US$B | D101: =Seg!D75 -> 218.783 | E101: =Seg!E75 -> 268.127 | F101: =Seg!F75 -> 330.14528 | G101: =Seg!G75 -> 392.65676 | H101: =Seg!H75 -> 450.54427 | I101: =Seg!I75 -> 510.69214 | J101: =Seg!J75 -> 560.41673 | K101: =Seg!K75 -> 600.13241
A102: Search and advertising | B102: US$B | D102: =Seg!D76 -> 22.171 | E102: =Seg!E76 -> 24.835 | F102: =Seg!F76 -> 27.55919 | G102: =Seg!G76 -> 30.409856 | H102: =Seg!H76 -> 33.301179 | I102: =Seg!I76 -> 36.189024 | J102: =Seg!J76 -> 39.024777 | K102: =Seg!K76 -> 41.756512
A103: XBOX | B103: US$B | D103: =Seg!D78 -> 23.455 | E103: =Seg!E78 -> 21.79 | F103: =Seg!F78 -> 20.752098 | G103: =Seg!G78 -> 19.908359 | H103: =Seg!H78 -> 19.400826 | I103: =Seg!I78 -> 19.200435 | J103: =Seg!J78 -> 19.293278 | K103: =Seg!K78 -> 19.679144
...

Sheet CF
A1: CF — 營業現金流（淨利＋AI 與非 AI 折舊＋股票薪酬＋營運資金）− 資本支出（AI＝Thesis；非 AI＝營收 × 比例）− 融資租賃本金 → 自由現金流（財報現金）；股利、回購、舉債（最低現金）
A2: 收支關卡（地圖讀此表）：模型期間首年起五年（FY2027–FY2031）自由現金流扣股利後合計（財報現金，不含自用 AI 影子效益）；並判斷是否需要舉債或停止回購
A4: 項目 | B4: 情境 A（樂觀） | C4: 情境 B（基準） | D4: 情境 C（保守） | E4: 說明
A5: 收支關卡：自由現金流扣股利（五年合計） | B5: =CF!$C$43 -> 363.18539 | C5: =CF!$C$75 -> 259.64022 | D5: =CF!$C$107 -> 137.88246 | E5: US$B；為正＝五年自由現金流足以支付股利（地圖收支關卡讀 C 欄＝基準情境）。修正一：v0.3 初版的範圍公式被讀成 F 欄到 CF 欄，誤加了 FY2032
A6: 是否需要舉債或停止回購（FY2027–FY2031） | B6: =CF!$C$45 -> 不需舉債；回購較每年 22.3 的目標少 38.0 十億美元（2 年減少） | C6: =CF!$C$77 -> 需要舉債 8.1 十億美元；回購較每年 22.3 的目標少 44.3 十億美元（2 年減少） | D6: =CF!$C$109 -> 需要舉債 26.6 十億美元；回購較每年 22.3 的目標少 66.8 十億美元（3 年減少）
A7: 自由現金流 FY2027（參考） | B7: =CF!F30 -> 14.165555 | C7: =CF!F62 -> 11.271787 | D7: =CF!F94 -> 7.8440332
A8: 自由現金流 FY2029（參考） | B8: =CF!H30 -> 86.187278 | C8: =CF!H62 -> 62.211875 | D8: =CF!H94 -> 34.022608
A9: 資本支出 FY2027（公司口徑，參考） | B9: =CF!F27 -> 204.2 | C9: =CF!F59 -> 204.2 | D9: =CF!F91 -> 204.27996
A10: 回購合計 FY2027–FY2031 | B10: =SUM(CF!F35:J35) -> 73.388777 | C10: =SUM(CF!F67:J67) -> 67.083837 | D10: =SUM(CF!F99:J99) -> 44.542
A11: 新增舉債合計 FY2027–FY2031 | B11: =SUM(CF!F36:J36) -> 0 | C11: =SUM(CF!F68:J68) -> 8.149229 | D11: =SUM(CF!F100:J100) -> 26.554111
A12: 檢查：收支關卡＝首年起五年自由現金流扣股利（逐欄加總） | B12: =B5-(CF!F33+CF!G33+CF!H33+CF!I33+CF!J33) -> 0 | C12: =C5-(CF!F65+CF!G65+CF!H65+CF!I65+CF!J65) -> 0 | D12: =D5-(CF!F97+CF!G97+CF!H97+CF!I97+CF!J97) -> 0
A14: 情境 A（樂觀）｜現金流與資金（CF）
A15: 項目 | B15: 單位 | C15: FY2024A | D15: FY2025A | E15: FY2026A | F15: FY2027 | G15: FY2028 | H15: FY2029 | I15: FY2030 | J15: FY2031 | K15: FY2032 | L15: 說明
A16: 淨利（財報口徑） | B16: US$B | F16: =PL!F45 -> 147.4461 | G16: =PL!G45 -> 167.96278 | H16: =PL!H45 -> 195.94409 | I16: =PL!I45 -> 217.30707 | J16: =PL!J45 -> 235.85805 | K16: =PL!K45 -> 252.65873
A17: 非 AI 折舊攤銷 | B17: US$B | E17: =Q!M38-Thesis!E43 -> 22.228594 | F17: =CF!E17*(1-1/life_nonai)+(CF!F25+CF!F26)/life_nonai -> 23.580344 | G17: =CF!F17*(1-1/life_nonai)+(CF!G25)/life_nonai -> 25.380142 | H17: =CF!G17*(1-1/life_nonai)+(CF!H25)/life_nonai -> 27.596464 | I17: =CF!H17*(1-1/life_nonai)+(CF!I25)/life_nonai -> 30.152941 | J17: =CF!I17*(1-1/life_nonai)+(CF!J25)/life_nonai -> 32.957502 | K17: =CF!J17*(1-1/life_nonai)+(CF!K25)/life_nonai -> 35.925678 | L17: FY2026＝公司 D&A − AI 折舊估計（C17）
A18: 其中 FY2027 補足差額的折舊（非 AI 遞減法：差額 ÷ 年限 ×（1 − 1／年限）^（年度 − 2027）） | B18: US$B | F18: =CF!$F$26/life_nonai*(1-1/life_nonai)^(Thesis!F6-2027) -> 0.0047577445 | G18: =CF!$F$26/life_nonai*(1-1/life_nonai)^(Thesis!G6-2027) -> 0.0042819701 | H18: =CF!$F$26/life_nonai*(1-1/life_nonai)^(Thesis!H6-2027) -> 0.0038537731 | I18: =CF!$F$26/life_nonai*(1-1/life_nonai)^(Thesis!I6-2027) -> 0.0034683958 | J18: =CF!$F$26/life_nonai*(1-1/life_nonai)^(Thesis!J6-2027) -> 0.0031215562 | K18: =CF!$F$26/life_nonai*(1-1/life_nonai)^(Thesis!K6-2027) -> 0.0028094006 | L18: 修正三：核心利益率固定，補足差額的折舊須另由 Agents and Infra 營業利益扣除
A19: 折舊攤銷合計（AI＋非 AI） | B19: US$B | E19: =Thesis!E43+CF!E17 -> 38.534 | F19: =Thesis!F43+CF!F17 -> 58.159659 | G19: =Thesis!G43+CF!G17 -> 86.114632 | H19: =Thesis!H43+CF!H17 -> 116.69655 | I19: =Thesis!I43+CF!I17 -> 144.38395 | J19: =Thesis!J43+CF!J17 -> 164.97318 | K19: =Thesis!K43+CF!K17 -> 178.93835
A20: 股票薪酬（現金流量表加回；DCF 視為現金成本） | B20: US$B | F20: =Seg!F29*sbc_r -> 15.068069 | G20: =Seg!G29*sbc_r -> 18.384148 | H20: =Seg!H29*sbc_r -> 21.954598 | I20: =Seg!I29*sbc_r -> 24.99446 | J20: =Seg!J29*sbc_r -> 27.440793 | K20: =Seg!K29*sbc_r -> 29.386865
A21: 營運資金變動（FY2027 為第二至第四季） | B21: US$B | F21: =wc27-wc26q1 -> -4.677 | G21: =wc_f -> 0 | H21: =wc_f -> 0 | I21: =wc_f -> 0 | J21: =wc_f -> 0 | K21: =wc_f -> 0 | L21: C14：首期＝上一年度同期實績（v0.3.1：FY2026 全年 − FY26Q1）；之後 wc_f
A22: FY27Q1 實績的營運資金與其他項目（營業現金流 − 淨利 − 折舊 − 股票薪酬） | B22: US$B | F22: =Q!$I$35-Q!$I$26-Q!$I$38-Q!$I$39 -> 6.493 | L22: 含遞延稅 +4.6、應收帳款回收等；FY2027 營業現金流＝全年淨利＋折舊＋股票薪酬＋本列＋第二至第四季營運資金
A23: 營業現金流 | B23: US$B | E23: =Q!M35 -> 182.935 | F23: =CF!F16+CF!F19+CF!F20+CF!F21+CF!F22 -> 222.48983 | G23: =CF!G16+CF!G19+CF!G20+CF!G21 -> 272.46156 | H23: =CF!H16+CF!H19+CF!H20+CF!H21 -> 334.59524 | I23: =CF!I16+CF!I19+CF!I20+CF!I21 -> 386.68548 | J23: =CF!J16+CF!J19+CF!J20+CF!J21 -> 428.27202 | K23: =CF!K16+CF!K19+CF!K20+CF!K21 -> 460.98394
A24: AI 資本支出（Thesis） | B24: US$B | F24: =Thesis!F40 -> 168.4539 | G24: =Thesis!G40 -> 191.94448 | H24: =Thesis!H40 -> 196.806 | I24: =Thesis!I40 -> 168.61483 | J24: =Thesis!J40 -> 128.92993 | K24: =Thesis!K40 -> 118.96285
A25: 非 AI 資本支出（各線營收 × 比例） | B25: US$B | E25: =Seg!E7*cx_azo+Seg!E14*cx_m365+Seg!E15*cx_lic+(Seg!E17+Seg!E19)*cx_ind+Seg!E22*cx_srch+(Seg!E24+Seg!E26)*cx_dev -> 30.184659 | F25: =Seg!F7*cx_azo+Seg!F14*cx_m365+Seg!F15*cx_lic+(Seg!F17+Seg!F19)*cx_ind+Seg!F22*cx_srch+(Seg!F24+Seg!F26)*cx_dev -> 35.698519 | G25: =Seg!G7*cx_azo+Seg!G14*cx_m365+Seg!G15*cx_lic+(Seg!G17+Seg!G19)*cx_ind+Seg!G22*cx_srch+(Seg!G24+Seg!G26)*cx_dev -> 41.578318 | H25: =Seg!H7*cx_azo+Seg!H14*cx_m365+Seg!H15*cx_lic+(Seg!H17+Seg!H19)*cx_ind+Seg!H22*cx_srch+(Seg!H24+Seg!H26)*cx_dev -> 47.543366 | I25: =Seg!I7*cx_azo+Seg!I14*cx_m365+Seg!I15*cx_lic+(Seg!I17+Seg!I19)*cx_ind+Seg!I22*cx_srch+(Seg!I24+Seg!I26)*cx_dev -> 53.16123 | J25: =Seg!J7*cx_azo+Seg!J14*cx_m365+Seg!J15*cx_lic+(Seg!J17+Seg!J19)*cx_ind+Seg!J22*cx_srch+(Seg!J24+Seg!J26)*cx_dev -> 58.198557 | K25: =Seg!K7*cx_azo+Seg!K14*cx_m365+Seg!K15*cx_lic+(Seg!K17+Seg!K19)*cx_ind+Seg!K22*cx_srch+(Seg!K24+Seg!K26)*cx_dev -> 62.63926
A26: FY2027 補足到公司指引下限的其他資本支出（不增 AI MW；非 AI 遞減法每年 1／年限折舊，折舊由 Agents and Infra 營業利益扣除） | B26: US$B | F26: =Thesis!F38 -> 0.047577445 | L26: 修正二：補足差額不再當 AI IT（v0.3 修正一有折舊卻無 MW 與收入）；FY2026 公司口徑 145.3 比模型估計 116.4 多 28.9，推定含 AI 以外的資料中心與未拆分項目
A27: 資本支出合計（公司口徑，含融資租賃） | B27: US$B | E27: =Q!M43 -> 145.3 | F27: =CF!F24+CF!F25+CF!F26 -> 204.2 | G27: =CF!G24+CF!G25 -> 233.52279 | H27: =CF!H24+CF!H25 -> 244.34937 | I27: =CF!I24+CF!I25 -> 221.77606 | J27: =CF!J24+CF!J25 -> 187.12849 | K27: =CF!K24+CF!K25 -> 181.60211 | L27: 新的融資租賃在取得時視同現金（偏保守，v0.2.2 口徑）；FY2026 為公司法說值
A28: 在帳融資租賃負債（年底） | B28: US$B | E28: =fl_liab -> 66.594 | F28: =CF!E28-CF!F29 -> 62.46973 | G28: =CF!F28-CF!G29 -> 57.986868 | H28: =CF!G28-CF!H29 -> 53.928277 | I28: =CF!H28-CF!I29 -> 49.785049 | J28: =CF!I28-CF!J29 -> 45.482377 | K28: =CF!J28-CF!K29 -> 40.986084
A29: 在帳融資租賃本金（付款 − 利息） | B29: US$B | F29: =fl_pay_27-CF!E28*fl_rate -> 4.12427 | G29: =fl_pay_28-CF!F28*fl_rate -> 4.4828621 | H29: =fl_pay_29-CF!G28*fl_rate -> 4.0585909 | I29: =fl_pay_30-CF!H28*fl_rate -> 4.1432275 | J29: =fl_pay_31-CF!I28*fl_rate -> 4.3026728 | K29: =fl_pay_32-CF!J28*fl_rate -> 4.4962931
A30: 自由現金流（財報現金：營業現金流 − 資本支出 − 融資租賃本金） | B30: US$B | E30: =Q!M35-Q!M36-Q!M44 -> 63.886 | F30: =CF!F23-CF!F27-CF!F29 -> 14.165555 | G30: =CF!G23-CF!G27-CF!G29 -> 34.455903 | H30: =CF!H23-CF!H27-CF!H29 -> 86.187278 | I30: =CF!I23-CF!I27-CF!I29 -> 160.76618 | J30: =CF!J23-CF!J27-CF!J29 -> 236.84086 | K30: =CF!K23-CF!K27-CF!K29 -> 274.88553 | L30: FY2026 為實績（現金資本支出口徑）；收支關卡用此列（不含影子效益）
A31: 每股股利 | B31: US$ | F31: =dps_27 -> 3.85 | G31: =CF!F31*(1+dps_g) -> 4.158 | H31: =CF!G31*(1+dps_g) -> 4.49064 | I31: =CF!H31*(1+dps_g) -> 4.8498912 | J31: =CF!I31*(1+dps_g) -> 5.2378825 | K31: =CF!J31*(1+dps_g) -> 5.6569131
A32: 股利 | B32: US$B | E32: =Q!M41 -> 26.445 | F32: =CF!F31*CF!E41 -> 28.59395 | G32: =CF!G31*CF!F41 -> 31.044731 | H32: =CF!H31*CF!G41 -> 33.704686 | I32: =CF!I31*CF!H41 -> 36.4515 | J32: =CF!J31*CF!I41 -> 39.435517 | K32: =CF!K31*CF!J41 -> 42.677113 | L32: 每股股利 × 期初流通股數（避免與回購循環）
A33: 自由現金流扣股利 | B33: US$B | E33: =CF!E30-CF!E32 -> 37.441 | F33: =CF!F30-CF!F32 -> -14.428395 | G33: =CF!G30-CF!G32 -> 3.4111719 | H33: =CF!H30-CF!H32 -> 52.482592 | I33: =CF!I30-CF!I32 -> 124.31469 | J33: =CF!J30-CF!J32 -> 197.40534 | K33: =CF!K30-CF!K32 -> 232.20842
A34: 債務到期償還 | B34: US$B | F34: =debt_mat_27 -> 9.25 | G34: =debt_mat_28 -> 0 | H34: =debt_mat_29 -> 2.001 | I34: =debt_mat_30 -> 0 | J34: =debt_mat_31 -> 0.5 | K34: =debt_mat_32 -> 0
A35: 回購（現金不足時先減） | B35: US$B | E35: =Q!M40 -> 22.271 | F35: =MAX(0,MIN(bb_target,CF!E37+CF!F33-CF!F34-min_cash)) -> 3.1646055 | G35: =MAX(0,MIN(bb_target,CF!F37+CF!G33-CF!G34-min_cash)) -> 3.4111719 | H35: =MAX(0,MIN(bb_target,CF!G37+CF!H33-CF!H34-min_cash)) -> 22.271 | I35: =MAX(0,MIN(bb_target,CF!H37+CF!I33-CF!I34-min_cash)) -> 22.271 | J35: =MAX(0,MIN(bb_target,CF!I37+CF!J33-CF!J34-min_cash)) -> 22.271 | K35: =MAX(0,MIN(bb_target,CF!J37+CF!K33-CF!K34-min_cash)) -> 22.271
A36: 新增舉債（維持最低現金） | B36: US$B | F36: =MAX(0,min_cash-(CF!E37+CF!F33-CF!F34-CF!F35)) -> 0 | G36: =MAX(0,min_cash-(CF!F37+CF!G33-CF!G34-CF!G35)) -> 0 | H36: =MAX(0,min_cash-(CF!G37+CF!H33-CF!H34-CF!H35)) -> 0 | I36: =MAX(0,min_cash-(CF!H37+CF!I33-CF!I34-CF!I35)) -> 0 | J36: =MAX(0,min_cash-(CF!I37+CF!J33-CF!J34-CF!J35)) -> 0 | K36: =MAX(0,min_cash-(CF!J37+CF!K33-CF!K34-CF!K35)) -> 0
A37: 現金與短期投資（年底） | B37: US$B | E37: =cash_open -> 76.843 | F37: =CF!E37+CF!F33-CF!F34-CF!F35+CF!F36 -> 50 | G37: =CF!F37+CF!G33-CF!G34-CF!G35+CF!G36 -> 50 | H37: =CF!G37+CF!H33-CF!H34-CF!H35+CF!H36 -> 78.210592 | I37: =CF!H37+CF!I33-CF!I34-CF!I35+CF!I36 -> 180.25428 | J37: =CF!I37+CF!J33-CF!J34-CF!J35+CF!J36 -> 354.88862 | K37: =CF!J37+CF!K33-CF!K34-CF!K35+CF!K36 -> 564.82604
A38: 債務（年底，面額） | B38: US$B | E38: =debt_face -> 46.136 | F38: =CF!E38-CF!F34+CF!F36 -> 36.886 | G38: =CF!F38-CF!G34+CF!G36 -> 36.886 | H38: =CF!G38-CF!H34+CF!H36 -> 34.885 | I38: =CF!H38-CF!I34+CF!I36 -> 34.885 | J38: =CF!I38-CF!J34+CF!J36 -> 34.385 | K38: =CF!J38-CF!K34+CF!K36 -> 34.385
A39: 淨現金（不含租賃） | B39: US$B | E39: =CF!E37-CF!E38 -> 30.707 | F39: =CF!F37-CF!F38 -> 13.114 | G39: =CF!G37-CF!G38 -> 13.114 | H39: =CF!H37-CF!H38 -> 43.325592 | I39: =CF!I37-CF!I38 -> 145.36928 | J39: =CF!J37-CF!J38 -> 320.50362 | K39: =CF!K37-CF!K38 -> 530.44104
A40: 回購均價 | B40: US$ | F40: =px*(1+bb_g)^(Thesis!F6-base_fy-mid_yr) -> 551.84178 | G40: =px*(1+bb_g)^(Thesis!G6-base_fy-mid_yr) -> 595.98912 | H40: =px*(1+bb_g)^(Thesis!H6-base_fy-mid_yr) -> 643.66825 | I40: =px*(1+bb_g)^(Thesis!I6-base_fy-mid_yr) -> 695.16171 | J40: =px*(1+bb_g)^(Thesis!J6-base_fy-mid_yr) -> 750.77465 | K40: =px*(1+bb_g)^(Thesis!K6-base_fy-mid_yr) -> 810.83662
A41: 流通股數（年底） | B41: 十億股 | E41: =sh_out26 -> 7.427 | F41: =CF!E41+sh_iss-CF!F35/CF!F40 -> 7.4662654 | G41: =CF!F41+sh_iss-CF!G35/CF!G40 -> 7.5055418 | H41: =CF!G41+sh_iss-CF!H35/CF!H40 -> 7.5159417 | I41: =CF!H41+sh_iss-CF!I35/CF!I40 -> 7.5289046 | J41: =CF!I41+sh_iss-CF!J35/CF!J40 -> 7.5442405 | K41: =CF!J41+sh_iss-CF!K35/CF!K40 -> 7.5617738
A42: 稀釋加權股數 | B42: 十億股 | E42: =sh_dil26 -> 7.453 | F42: =(CF!E41+CF!F41)/2+dil_gap -> 7.4706327 | G42: =(CF!F41+CF!G41)/2+dil_gap -> 7.5099036 | H42: =(CF!G41+CF!H41)/2+dil_gap -> 7.5347418 | I42: =(CF!H41+CF!I41)/2+dil_gap -> 7.5464231 | J42: =(CF!I41+CF!J41)/2+dil_gap -> 7.5605725 | K42: =(CF!J41+CF!K41)/2+dil_gap -> 7.5770072
A43: 自由現金流扣股利（FY2027–FY2031 合計，本情境） | B43: US$B | C43: =SUM(CF!F33:J33) -> 363.18539
A44: 檢查：收支關卡＝首年起五年自由現金流扣股利（逐欄加總） | B44: US$B | C44: =CF!$C$43-(CF!F33+CF!G33+CF!H33+CF!I33+CF!J33) -> 0
A45: 是否需要舉債或停止回購（FY2027–FY2031） | B45: 文字 | C45: =IF(SUM(CF!F36:J36)>0.05,"需要舉債 "&TEXT(SUM(CF!F36:J36),"0.0")&" 十億美元","不需舉債")&"；"&IF(SUM(CF!F35:J35)<COUNT(CF!F35:J35)*bb_target-0.05,"回購較每年 "&TEXT(bb_target,"0.0")&" 的目標少 "&TEXT(COUNT(CF!F35:J35)*bb_target-SUM(CF!F35:J35),"0.0")&" 十億美元（"&TEXT(COUNTIF(CF!F35:J35,"<"&(bb_target-0.05)),"0")&" 年減少）","回購不減") -> 不需舉債；回購較每年 22.3 的目標少 38.0 十億美元（2 年減少）
A46: 情境 B（基準）｜現金流與資金（CF）
A47: 項目 | B47: 單位 | C47: FY2024A | D47: FY2025A | E47: FY2026A | F47: FY2027 | G47: FY2028 | H47: FY2029 | I47: FY2030 | J47: FY2031 | K47: FY2032 | L47: 說明
A48: 淨利（財報口徑） | B48: US$B | F48: =PL!F84 -> 144.70285 | G48: =PL!G84 -> 156.80023 | H48: =PL!H84 -> 172.73385 | I48: =PL!I84 -> 187.97414 | J48: =PL!J84 -> 202.30871 | K48: =PL!K84 -> 216.23129
A49: 非 AI 折舊攤銷 | B49: US$B | E49: =Q!M38-Thesis!E95 -> 22.228594 | F49: =CF!E49*(1-1/life_nonai)+(CF!F57+CF!F58)/life_nonai -> 23.580344 | G49: =CF!F49*(1-1/life_nonai)+(CF!G57)/life_nonai -> 25.358351 | H49: =CF!G49*(1-1/life_nonai)+(CF!H57)/life_nonai -> 27.52857 | I49: =CF!H49*(1-1/life_nonai)+(CF!I57)/life_nonai -> 30.024452 | J49: =CF!I49*(1-1/life_nonai)+(CF!J57)/life_nonai -> 32.762579 | K49: =CF!J49*(1-1/life_nonai)+(CF!K57)/life_nonai -> 35.658568 | L49: FY2026＝公司 D&A − AI 折舊估計（C17）
A50: 其中 FY2027 補足差額的折舊（非 AI 遞減法：差額 ÷ 年限 ×（1 − 1／年限）^（年度 − 2027）） | B50: US$B | F50: =CF!$F$58/life_nonai*(1-1/life_nonai)^(Thesis!F58-2027) -> 1.9458658e-06 | G50: =CF!$F$58/life_nonai*(1-1/life_nonai)^(Thesis!G58-2027) -> 1.7512792e-06 | H50: =CF!$F$58/life_nonai*(1-1/life_nonai)^(Thesis!H58-2027) -> 1.5761513e-06 | I50: =CF!$F$58/life_nonai*(1-1/life_nonai)^(Thesis!I58-2027) -> 1.4185361e-06 | J50: =CF!$F$58/life_nonai*(1-1/life_nonai)^(Thesis!J58-2027) -> 1.2766825e-06 | K50: =CF!$F$58/life_nonai*(1-1/life_nonai)^(Thesis!K58-2027) -> 1.1490143e-06 | L50: 修正三：核心利益率固定，補足差額的折舊須另由 Agents and Infra 營業利益扣除
A51: 折舊攤銷合計（AI＋非 AI） | B51: US$B | E51: =Thesis!E95+CF!E49 -> 38.534 | F51: =Thesis!F95+CF!F49 -> 58.159659 | G51: =Thesis!G95+CF!G49 -> 86.092841 | H51: =Thesis!H95+CF!H49 -> 116.62866 | I51: =Thesis!I95+CF!I49 -> 144.25546 | J51: =Thesis!J95+CF!J49 -> 164.77825 | K51: =Thesis!K95+CF!K49 -> 178.67124
A52: 股票薪酬（現金流量表加回；DCF 視為現金成本） | B52: US$B | F52: =Seg!F56*sbc_r -> 14.917544 | G52: =Seg!G56*sbc_r -> 17.811984 | H52: =Seg!H56*sbc_r -> 20.774506 | I52: =Seg!I56*sbc_r -> 23.495238 | J52: =Seg!J56*sbc_r -> 25.723295 | K52: =Seg!K56*sbc_r -> 27.51321
A53: 營運資金變動（FY2027 為第二至第四季） | B53: US$B | F53: =wc27-wc26q1 -> -4.677 | G53: =wc_f -> 0 | H53: =wc_f -> 0 | I53: =wc_f -> 0 | J53: =wc_f -> 0 | K53: =wc_f -> 0 | L53: C14：首期＝上一年度同期實績（v0.3.1：FY2026 全年 − FY26Q1）；之後 wc_f
A54: FY27Q1 實績的營運資金與其他項目（營業現金流 − 淨利 − 折舊 − 股票薪酬） | B54: US$B | F54: =Q!$I$35-Q!$I$26-Q!$I$38-Q!$I$39 -> 6.493 | L54: 含遞延稅 +4.6、應收帳款回收等；FY2027 營業現金流＝全年淨利＋折舊＋股票薪酬＋本列＋第二至第四季營運資金
A55: 營業現金流 | B55: US$B | E55: =Q!M35 -> 182.935 | F55: =CF!F48+CF!F51+CF!F52+CF!F53+CF!F54 -> 219.59606 | G55: =CF!G48+CF!G51+CF!G52+CF!G53 -> 260.70505 | H55: =CF!H48+CF!H51+CF!H52+CF!H53 -> 310.13702 | I55: =CF!I48+CF!I51+CF!I52+CF!I53 -> 355.72484 | J55: =CF!J48+CF!J51+CF!J52+CF!J53 -> 392.81026 | K55: =CF!K48+CF!K51+CF!K52+CF!K53 -> 422.41574
A56: AI 資本支出（Thesis） | B56: US$B | F56: =Thesis!F92 -> 168.4539 | G56: =Thesis!G92 -> 191.94448 | H56: =Thesis!H92 -> 196.806 | I56: =Thesis!I92 -> 168.61483 | J56: =Thesis!J92 -> 128.92993 | K56: =Thesis!K92 -> 118.96285
A57: 非 AI 資本支出（各線營收 × 比例） | B57: US$B | E57: =Seg!E34*cx_azo+Seg!E41*cx_m365+Seg!E42*cx_lic+(Seg!E44+Seg!E46)*cx_ind+Seg!E49*cx_srch+(Seg!E51+Seg!E53)*cx_dev -> 30.184659 | F57: =Seg!F34*cx_azo+Seg!F41*cx_m365+Seg!F42*cx_lic+(Seg!F44+Seg!F46)*cx_ind+Seg!F49*cx_srch+(Seg!F51+Seg!F53)*cx_dev -> 35.746076 | G57: =Seg!G34*cx_azo+Seg!G41*cx_m365+Seg!G42*cx_lic+(Seg!G44+Seg!G46)*cx_ind+Seg!G49*cx_srch+(Seg!G51+Seg!G53)*cx_dev -> 41.360407 | H57: =Seg!H34*cx_azo+Seg!H41*cx_m365+Seg!H42*cx_lic+(Seg!H44+Seg!H46)*cx_ind+Seg!H49*cx_srch+(Seg!H51+Seg!H53)*cx_dev -> 47.060545 | I57: =Seg!I34*cx_azo+Seg!I41*cx_m365+Seg!I42*cx_lic+(Seg!I44+Seg!I46)*cx_ind+Seg!I49*cx_srch+(Seg!I51+Seg!I53)*cx_dev -> 52.487394 | J57: =Seg!J34*cx_azo+Seg!J41*cx_m365+Seg!J42*cx_lic+(Seg!J44+Seg!J46)*cx_ind+Seg!J49*cx_srch+(Seg!J51+Seg!J53)*cx_dev -> 57.405715 | K57: =Seg!K34*cx_azo+Seg!K41*cx_m365+Seg!K42*cx_lic+(Seg!K44+Seg!K46)*cx_ind+Seg!K49*cx_srch+(Seg!K51+Seg!K53)*cx_dev -> 61.722477
A58: FY2027 補足到公司指引下限的其他資本支出（不增 AI MW；非 AI 遞減法每年 1／年限折舊，折舊由 Agents and Infra 營業利益扣除） | B58: US$B | F58: =Thesis!F90 -> 1.9458658e-05 | L58: 修正二：補足差額不再當 AI IT（v0.3 修正一有折舊卻無 MW 與收入）；FY2026 公司口徑 145.3 比模型估計 116.4 多 28.9，推定含 AI 以外的資料中心與未拆分項目
A59: 資本支出合計（公司口徑，含融資租賃） | B59: US$B | E59: =Q!M43 -> 145.3 | F59: =CF!F56+CF!F57+CF!F58 -> 204.2 | G59: =CF!G56+CF!G57 -> 233.30488 | H59: =CF!H56+CF!H57 -> 243.86655 | I59: =CF!I56+CF!I57 -> 221.10223 | J59: =CF!J56+CF!J57 -> 186.33565 | K59: =CF!K56+CF!K57 -> 180.68533 | L59: 新的融資租賃在取得時視同現金（偏保守，v0.2.2 口徑）；FY2026 為公司法說值
A60: 在帳融資租賃負債（年底） | B60: US$B | E60: =fl_liab -> 66.594 | F60: =CF!E60-CF!F61 -> 62.46973 | G60: =CF!F60-CF!G61 -> 57.986868 | H60: =CF!G60-CF!H61 -> 53.928277 | I60: =CF!H60-CF!I61 -> 49.785049 | J60: =CF!I60-CF!J61 -> 45.482377 | K60: =CF!J60-CF!K61 -> 40.986084
A61: 在帳融資租賃本金（付款 − 利息） | B61: US$B | F61: =fl_pay_27-CF!E60*fl_rate -> 4.12427 | G61: =fl_pay_28-CF!F60*fl_rate -> 4.4828621 | H61: =fl_pay_29-CF!G60*fl_rate -> 4.0585909 | I61: =fl_pay_30-CF!H60*fl_rate -> 4.1432275 | J61: =fl_pay_31-CF!I60*fl_rate -> 4.3026728 | K61: =fl_pay_32-CF!J60*fl_rate -> 4.4962931
A62: 自由現金流（財報現金：營業現金流 − 資本支出 − 融資租賃本金） | B62: US$B | E62: =Q!M35-Q!M36-Q!M44 -> 63.886 | F62: =CF!F55-CF!F59-CF!F61 -> 11.271787 | G62: =CF!G55-CF!G59-CF!G61 -> 22.917306 | H62: =CF!H55-CF!H59-CF!H61 -> 62.211875 | I62: =CF!I55-CF!I59-CF!I61 -> 130.47938 | J62: =CF!J55-CF!J59-CF!J61 -> 202.17194 | K62: =CF!K55-CF!K59-CF!K61 -> 237.23411 | L62: FY2026 為實績（現金資本支出口徑）；收支關卡用此列（不含影子效益）
A63: 每股股利 | B63: US$ | F63: =dps_27 -> 3.85 | G63: =CF!F63*(1+dps_g) -> 4.158 | H63: =CF!G63*(1+dps_g) -> 4.49064 | I63: =CF!H63*(1+dps_g) -> 4.8498912 | J63: =CF!I63*(1+dps_g) -> 5.2378825 | K63: =CF!J63*(1+dps_g) -> 5.6569131
A64: 股利 | B64: US$B | E64: =Q!M41 -> 26.445 | F64: =CF!F63*CF!E73 -> 28.59395 | G64: =CF!G63*CF!F73 -> 31.066535 | H64: =CF!H63*CF!G73 -> 33.753937 | I64: =CF!I63*CF!H73 -> 36.50469 | J64: =CF!J63*CF!I73 -> 39.492963 | K64: =CF!K63*CF!J73 -> 42.739155 | L64: 每股股利 × 期初流通股數（避免與回購循環）
A65: 自由現金流扣股利 | B65: US$B | E65: =CF!E62-CF!E64 -> 37.441 | F65: =CF!F62-CF!F64 -> -17.322163 | G65: =CF!G62-CF!G64 -> -8.149229 | H65: =CF!H62-CF!H64 -> 28.457938 | I65: =CF!I62-CF!I64 -> 93.974694 | J65: =CF!J62-CF!J64 -> 162.67898 | K65: =CF!K62-CF!K64 -> 194.49496
A66: 債務到期償還 | B66: US$B | F66: =debt_mat_27 -> 9.25 | G66: =debt_mat_28 -> 0 | H66: =debt_mat_29 -> 2.001 | I66: =debt_mat_30 -> 0 | J66: =debt_mat_31 -> 0.5 | K66: =debt_mat_32 -> 0
A67: 回購（現金不足時先減） | B67: US$B | E67: =Q!M40 -> 22.271 | F67: =MAX(0,MIN(bb_target,CF!E69+CF!F65-CF!F66-min_cash)) -> 0.2708375 | G67: =MAX(0,MIN(bb_target,CF!F69+CF!G65-CF!G66-min_cash)) -> 0 | H67: =MAX(0,MIN(bb_target,CF!G69+CF!H65-CF!H66-min_cash)) -> 22.271 | I67: =MAX(0,MIN(bb_target,CF!H69+CF!I65-CF!I66-min_cash)) -> 22.271 | J67: =MAX(0,MIN(bb_target,CF!I69+CF!J65-CF!J66-min_cash)) -> 22.271 | K67: =MAX(0,MIN(bb_target,CF!J69+CF!K65-CF!K66-min_cash)) -> 22.271
A68: 新增舉債（維持最低現金） | B68: US$B | F68: =MAX(0,min_cash-(CF!E69+CF!F65-CF!F66-CF!F67)) -> 0 | G68: =MAX(0,min_cash-(CF!F69+CF!G65-CF!G66-CF!G67)) -> 8.149229 | H68: =MAX(0,min_cash-(CF!G69+CF!H65-CF!H66-CF!H67)) -> 0 | I68: =MAX(0,min_cash-(CF!H69+CF!I65-CF!I66-CF!I67)) -> 0 | J68: =MAX(0,min_cash-(CF!I69+CF!J65-CF!J66-CF!J67)) -> 0 | K68: =MAX(0,min_cash-(CF!J69+CF!K65-CF!K66-CF!K67)) -> 0
A69: 現金與短期投資（年底） | B69: US$B | E69: =cash_open -> 76.843 | F69: =CF!E69+CF!F65-CF!F66-CF!F67+CF!F68 -> 50 | G69: =CF!F69+CF!G65-CF!G66-CF!G67+CF!G68 -> 50 | H69: =CF!G69+CF!H65-CF!H66-CF!H67+CF!H68 -> 54.185938 | I69: =CF!H69+CF!I65-CF!I66-CF!I67+CF!I68 -> 125.88963 | J69: =CF!I69+CF!J65-CF!J66-CF!J67+CF!J68 -> 265.79761 | K69: =CF!J69+CF!K65-CF!K66-CF!K67+CF!K68 -> 438.02157
A70: 債務（年底，面額） | B70: US$B | E70: =debt_face -> 46.136 | F70: =CF!E70-CF!F66+CF!F68 -> 36.886 | G70: =CF!F70-CF!G66+CF!G68 -> 45.035229 | H70: =CF!G70-CF!H66+CF!H68 -> 43.034229 | I70: =CF!H70-CF!I66+CF!I68 -> 43.034229 | J70: =CF!I70-CF!J66+CF!J68 -> 42.534229 | K70: =CF!J70-CF!K66+CF!K68 -> 42.534229
A71: 淨現金（不含租賃） | B71: US$B | E71: =CF!E69-CF!E70 -> 30.707 | F71: =CF!F69-CF!F70 -> 13.114 | G71: =CF!G69-CF!G70 -> 4.964771 | H71: =CF!H69-CF!H70 -> 11.151709 | I71: =CF!I69-CF!I70 -> 82.855403 | J71: =CF!J69-CF!J70 -> 223.26338 | K71: =CF!K69-CF!K70 -> 395.48734
A72: 回購均價 | B72: US$ | F72: =px*(1+bb_g)^(Thesis!F58-base_fy-mid_yr) -> 551.84178 | G72: =px*(1+bb_g)^(Thesis!G58-base_fy-mid_yr) -> 595.98912 | H72: =px*(1+bb_g)^(Thesis!H58-base_fy-mid_yr) -> 643.66825 | I72: =px*(1+bb_g)^(Thesis!I58-base_fy-mid_yr) -> 695.16171 | J72: =px*(1+bb_g)^(Thesis!J58-base_fy-mid_yr) -> 750.77465 | K72: =px*(1+bb_g)^(Thesis!K58-base_fy-mid_yr) -> 810.83662
A73: 流通股數（年底） | B73: 十億股 | E73: =sh_out26 -> 7.427 | F73: =CF!E73+sh_iss-CF!F67/CF!F72 -> 7.4715092 | G73: =CF!F73+sh_iss-CF!G67/CF!G72 -> 7.5165092 | H73: =CF!G73+sh_iss-CF!H67/CF!H72 -> 7.5269091 | I73: =CF!H73+sh_iss-CF!I67/CF!I72 -> 7.5398719 | J73: =CF!I73+sh_iss-CF!J67/CF!J72 -> 7.5552079 | K73: =CF!J73+sh_iss-CF!K67/CF!K72 -> 7.5727412
A74: 稀釋加權股數 | B74: 十億股 | E74: =sh_dil26 -> 7.453 | F74: =(CF!E73+CF!F73)/2+dil_gap -> 7.4732546 | G74: =(CF!F73+CF!G73)/2+dil_gap -> 7.5180092 | H74: =(CF!G73+CF!H73)/2+dil_gap -> 7.5457092 | I74: =(CF!H73+CF!I73)/2+dil_gap -> 7.5573905 | J74: =(CF!I73+CF!J73)/2+dil_gap -> 7.5715399 | K74: =(CF!J73+CF!K73)/2+dil_gap -> 7.5879746
A75: 自由現金流扣股利（FY2027–FY2031 合計，本情境） | B75: US$B | C75: =SUM(CF!F65:J65) -> 259.64022
A76: 檢查：收支關卡＝首年起五年自由現金流扣股利（逐欄加總） | B76: US$B | C76: =CF!$C$75-(CF!F65+CF!G65+CF!H65+CF!I65+CF!J65) -> 0
A77: 是否需要舉債或停止回購（FY2027–FY2031） | B77: 文字 | C77: =IF(SUM(CF!F68:J68)>0.05,"需要舉債 "&TEXT(SUM(CF!F68:J68),"0.0")&" 十億美元","不需舉債")&"；"&IF(SUM(CF!F67:J67)<COUNT(CF!F67:J67)*bb_target-0.05,"回購較每年 "&TEXT(bb_target,"0.0")&" 的目標少 "&TEXT(COUNT(CF!F67:J67)*bb_target-SUM(CF!F67:J67),"0.0")&" 十億美元（"&TEXT(COUNTIF(CF!F67:J67,"<"&(bb_target-0.05)),"0")&" 年減少）","回購不減") -> 需要舉債 8.1 十億美元；回購較每年 22.3 的目標少 44.3 十億美元（2 年減少）
A78: 情境 C（保守）｜現金流與資金（CF）
A79: 項目 | B79: 單位 | C79: FY2024A | D79: FY2025A | E79: FY2026A | F79: FY2027 | G79: FY2028 | H79: FY2029 | I79: FY2030 | J79: FY2031 | K79: FY2032 | L79: 說明
A80: 淨利（財報口徑） | B80: US$B | F80: =PL!F123 -> 141.51913 | G80: =PL!G123 -> 143.77609 | H80: =PL!H123 -> 145.52326 | I80: =PL!I123 -> 153.61858 | J80: =PL!J123 -> 163.02732 | K80: =PL!K123 -> 173.63022
A81: 非 AI 折舊攤銷 | B81: US$B | E81: =Q!M38-Thesis!E147 -> 22.228594 | F81: =CF!E81*(1-1/life_nonai)+(CF!F89+CF!F90)/life_nonai -> 23.588341 | G81: =CF!F81*(1-1/life_nonai)+(CF!G89)/life_nonai -> 25.347609 | H81: =CF!G81*(1-1/life_nonai)+(CF!H89)/life_nonai -> 27.475093 | I81: =CF!H81*(1-1/life_nonai)+(CF!I89)/life_nonai -> 29.914013 | J81: =CF!I81*(1-1/life_nonai)+(CF!J89)/life_nonai -> 32.589515 | K81: =CF!J81*(1-1/life_nonai)+(CF!K89)/life_nonai -> 35.417198 | L81: FY2026＝公司 D&A − AI 折舊估計（C17）
A82: 其中 FY2027 補足差額的折舊（非 AI 遞減法：差額 ÷ 年限 ×（1 − 1／年限）^（年度 − 2027）） | B82: US$B | F82: =CF!$F$90/life_nonai*(1-1/life_nonai)^(Thesis!F110-2027) -> 0 | G82: =CF!$F$90/life_nonai*(1-1/life_nonai)^(Thesis!G110-2027) -> 0 | H82: =CF!$F$90/life_nonai*(1-1/life_nonai)^(Thesis!H110-2027) -> 0 | I82: =CF!$F$90/life_nonai*(1-1/life_nonai)^(Thesis!I110-2027) -> 0 | J82: =CF!$F$90/life_nonai*(1-1/life_nonai)^(Thesis!J110-2027) -> 0 | K82: =CF!$F$90/life_nonai*(1-1/life_nonai)^(Thesis!K110-2027) -> 0 | L82: 修正三：核心利益率固定，補足差額的折舊須另由 Agents and Infra 營業利益扣除
A83: 折舊攤銷合計（AI＋非 AI） | B83: US$B | E83: =Thesis!E147+CF!E81 -> 38.534 | F83: =Thesis!F147+CF!F81 -> 58.167655 | G83: =Thesis!G147+CF!G81 -> 86.082099 | H83: =Thesis!H147+CF!H81 -> 116.57518 | I83: =Thesis!I147+CF!I81 -> 144.14502 | J83: =Thesis!J147+CF!J81 -> 164.60519 | K83: =Thesis!K147+CF!K81 -> 178.42987
A84: 股票薪酬（現金流量表加回；DCF 視為現金成本） | B84: US$B | F84: =Seg!F83*sbc_r -> 14.745479 | G84: =Seg!G83*sbc_r -> 17.156081 | H84: =Seg!H83*sbc_r -> 19.411216 | I84: =Seg!I83*sbc_r -> 21.765516 | J84: =Seg!J83*sbc_r -> 23.742569 | K84: =Seg!K83*sbc_r -> 25.356041
A85: 營運資金變動（FY2027 為第二至第四季） | B85: US$B | F85: =wc27-wc26q1 -> -4.677 | G85: =wc_f -> 0 | H85: =wc_f -> 0 | I85: =wc_f -> 0 | J85: =wc_f -> 0 | K85: =wc_f -> 0 | L85: C14：首期＝上一年度同期實績（v0.3.1：FY2026 全年 − FY26Q1）；之後 wc_f
A86: FY27Q1 實績的營運資金與其他項目（營業現金流 − 淨利 − 折舊 − 股票薪酬） | B86: US$B | F86: =Q!$I$35-Q!$I$26-Q!$I$38-Q!$I$39 -> 6.493 | L86: 含遞延稅 +4.6、應收帳款回收等；FY2027 營業現金流＝全年淨利＋折舊＋股票薪酬＋本列＋第二至第四季營運資金
A87: 營業現金流 | B87: US$B | E87: =Q!M35 -> 182.935 | F87: =CF!F80+CF!F83+CF!F84+CF!F85+CF!F86 -> 216.24827 | G87: =CF!G80+CF!G83+CF!G84+CF!G85 -> 247.01427 | H87: =CF!H80+CF!H83+CF!H84+CF!H85 -> 281.50966 | I87: =CF!I80+CF!I83+CF!I84+CF!I85 -> 319.52912 | J87: =CF!J80+CF!J83+CF!J84+CF!J85 -> 351.37508 | K87: =CF!K80+CF!K83+CF!K84+CF!K85 -> 377.41612
A88: AI 資本支出（Thesis） | B88: US$B | F88: =Thesis!F144 -> 168.4539 | G88: =Thesis!G144 -> 191.94448 | H88: =Thesis!H144 -> 196.806 | I88: =Thesis!I144 -> 168.61483 | J88: =Thesis!J144 -> 128.92993 | K88: =Thesis!K144 -> 118.96285
A89: 非 AI 資本支出（各線營收 × 比例） | B89: US$B | E89: =Seg!E61*cx_azo+Seg!E68*cx_m365+Seg!E69*cx_lic+(Seg!E71+Seg!E73)*cx_ind+Seg!E76*cx_srch+(Seg!E78+Seg!E80)*cx_dev -> 30.184659 | F89: =Seg!F61*cx_azo+Seg!F68*cx_m365+Seg!F69*cx_lic+(Seg!F71+Seg!F73)*cx_ind+Seg!F76*cx_srch+(Seg!F78+Seg!F80)*cx_dev -> 35.826059 | G89: =Seg!G61*cx_azo+Seg!G68*cx_m365+Seg!G69*cx_lic+(Seg!G71+Seg!G73)*cx_ind+Seg!G76*cx_srch+(Seg!G78+Seg!G80)*cx_dev -> 41.181022 | H89: =Seg!H61*cx_azo+Seg!H68*cx_m365+Seg!H69*cx_lic+(Seg!H71+Seg!H73)*cx_ind+Seg!H76*cx_srch+(Seg!H78+Seg!H80)*cx_dev -> 46.622456 | I89: =Seg!I61*cx_azo+Seg!I68*cx_m365+Seg!I69*cx_lic+(Seg!I71+Seg!I73)*cx_ind+Seg!I76*cx_srch+(Seg!I78+Seg!I80)*cx_dev -> 51.864287 | J89: =Seg!J61*cx_azo+Seg!J68*cx_m365+Seg!J69*cx_lic+(Seg!J71+Seg!J73)*cx_ind+Seg!J76*cx_srch+(Seg!J78+Seg!J80)*cx_dev -> 56.669032 | K89: =Seg!K61*cx_azo+Seg!K68*cx_m365+Seg!K69*cx_lic+(Seg!K71+Seg!K73)*cx_ind+Seg!K76*cx_srch+(Seg!K78+Seg!K80)*cx_dev -> 60.866347
A90: FY2027 補足到公司指引下限的其他資本支出（不增 AI MW；非 AI 遞減法每年 1／年限折舊，折舊由 Agents and Infra 營業利益扣除） | B90: US$B | F90: =Thesis!F142 -> 0 | L90: 修正二：補足差額不再當 AI IT（v0.3 修正一有折舊卻無 MW 與收入）；FY2026 公司口徑 145.3 比模型估計 116.4 多 28.9，推定含 AI 以外的資料中心與未拆分項目
A91: 資本支出合計（公司口徑，含融資租賃） | B91: US$B | E91: =Q!M43 -> 145.3 | F91: =CF!F88+CF!F89+CF!F90 -> 204.27996 | G91: =CF!G88+CF!G89 -> 233.1255 | H91: =CF!H88+CF!H89 -> 243.42846 | I91: =CF!I88+CF!I89 -> 220.47912 | J91: =CF!J88+CF!J89 -> 185.59896 | K91: =CF!K88+CF!K89 -> 179.8292 | L91: 新的融資租賃在取得時視同現金（偏保守，v0.2.2 口徑）；FY2026 為公司法說值
A92: 在帳融資租賃負債（年底） | B92: US$B | E92: =fl_liab -> 66.594 | F92: =CF!E92-CF!F93 -> 62.46973 | G92: =CF!F92-CF!G93 -> 57.986868 | H92: =CF!G92-CF!H93 -> 53.928277 | I92: =CF!H92-CF!I93 -> 49.785049 | J92: =CF!I92-CF!J93 -> 45.482377 | K92: =CF!J92-CF!K93 -> 40.986084
A93: 在帳融資租賃本金（付款 − 利息） | B93: US$B | F93: =fl_pay_27-CF!E92*fl_rate -> 4.12427 | G93: =fl_pay_28-CF!F92*fl_rate -> 4.4828621 | H93: =fl_pay_29-CF!G92*fl_rate -> 4.0585909 | I93: =fl_pay_30-CF!H92*fl_rate -> 4.1432275 | J93: =fl_pay_31-CF!I92*fl_rate -> 4.3026728 | K93: =fl_pay_32-CF!J92*fl_rate -> 4.4962931
A94: 自由現金流（財報現金：營業現金流 − 資本支出 − 融資租賃本金） | B94: US$B | E94: =Q!M35-Q!M36-Q!M44 -> 63.886 | F94: =CF!F87-CF!F91-CF!F93 -> 7.8440332 | G94: =CF!G87-CF!G91-CF!G93 -> 9.4059146 | H94: =CF!H87-CF!H91-CF!H93 -> 34.022608 | I94: =CF!I87-CF!I91-CF!I93 -> 94.906775 | J94: =CF!J87-CF!J91-CF!J93 -> 161.47344 | K94: =CF!K87-CF!K91-CF!K93 -> 193.09063 | L94: FY2026 為實績（現金資本支出口徑）；收支關卡用此列（不含影子效益）
A95: 每股股利 | B95: US$ | F95: =dps_27 -> 3.85 | G95: =CF!F95*(1+dps_g) -> 4.158 | H95: =CF!G95*(1+dps_g) -> 4.49064 | I95: =CF!H95*(1+dps_g) -> 4.8498912 | J95: =CF!I95*(1+dps_g) -> 5.2378825 | K95: =CF!J95*(1+dps_g) -> 5.6569131
A96: 股利 | B96: US$B | E96: =Q!M41 -> 26.445 | F96: =CF!F95*CF!E105 -> 28.59395 | G96: =CF!G95*CF!F105 -> 31.068576 | H96: =CF!H95*CF!G105 -> 33.756141 | I96: =CF!I95*CF!H105 -> 36.674877 | J96: =CF!J95*CF!I105 -> 39.676765 | K96: =CF!K95*CF!J105 -> 42.937661 | L96: 每股股利 × 期初流通股數（避免與回購循環）
A97: 自由現金流扣股利 | B97: US$B | E97: =CF!E94-CF!E96 -> 37.441 | F97: =CF!F94-CF!F96 -> -20.749917 | G97: =CF!G94-CF!G96 -> -21.662661 | H97: =CF!H94-CF!H96 -> 0.26646675 | I97: =CF!I94-CF!I96 -> 58.231898 | J97: =CF!J94-CF!J96 -> 121.79668 | K97: =CF!K94-CF!K96 -> 150.15297
A98: 債務到期償還 | B98: US$B | F98: =debt_mat_27 -> 9.25 | G98: =debt_mat_28 -> 0 | H98: =debt_mat_29 -> 2.001 | I98: =debt_mat_30 -> 0 | J98: =debt_mat_31 -> 0.5 | K98: =debt_mat_32 -> 0
A99: 回購（現金不足時先減） | B99: US$B | E99: =Q!M40 -> 22.271 | F99: =MAX(0,MIN(bb_target,CF!E101+CF!F97-CF!F98-min_cash)) -> 0 | G99: =MAX(0,MIN(bb_target,CF!F101+CF!G97-CF!G98-min_cash)) -> 0 | H99: =MAX(0,MIN(bb_target,CF!G101+CF!H97-CF!H98-min_cash)) -> 0 | I99: =MAX(0,MIN(bb_target,CF!H101+CF!I97-CF!I98-min_cash)) -> 22.271 | J99: =MAX(0,MIN(bb_target,CF!I101+CF!J97-CF!J98-min_cash)) -> 22.271 | K99: =MAX(0,MIN(bb_target,CF!J101+CF!K97-CF!K98-min_cash)) -> 22.271
A100: 新增舉債（維持最低現金） | B100: US$B | F100: =MAX(0,min_cash-(CF!E101+CF!F97-CF!F98-CF!F99)) -> 3.1569168 | G100: =MAX(0,min_cash-(CF!F101+CF!G97-CF!G98-CF!G99)) -> 21.662661 | H100: =MAX(0,min_cash-(CF!G101+CF!H97-CF!H98-CF!H99)) -> 1.7345332 | I100: =MAX(0,min_cash-(CF!H101+CF!I97-CF!I98-CF!I99)) -> 0 | J100: =MAX(0,min_cash-(CF!I101+CF!J97-CF!J98-CF!J99)) -> 0 | K100: =MAX(0,min_cash-(CF!J101+CF!K97-CF!K98-CF!K99)) -> 0
A101: 現金與短期投資（年底） | B101: US$B | E101: =cash_open -> 76.843 | F101: =CF!E101+CF!F97-CF!F98-CF!F99+CF!F100 -> 50 | G101: =CF!F101+CF!G97-CF!G98-CF!G99+CF!G100 -> 50 | H101: =CF!G101+CF!H97-CF!H98-CF!H99+CF!H100 -> 50 | I101: =CF!H101+CF!I97-CF!I98-CF!I99+CF!I100 -> 85.960898 | J101: =CF!I101+CF!J97-CF!J98-CF!J99+CF!J100 -> 184.98657 | K101: =CF!J101+CF!K97-CF!K98-CF!K99+CF!K100 -> 312.86855
A102: 債務（年底，面額） | B102: US$B | E102: =debt_face -> 46.136 | F102: =CF!E102-CF!F98+CF!F100 -> 40.042917 | G102: =CF!F102-CF!G98+CF!G100 -> 61.705578 | H102: =CF!G102-CF!H98+CF!H100 -> 61.439111 | I102: =CF!H102-CF!I98+CF!I100 -> 61.439111 | J102: =CF!I102-CF!J98+CF!J100 -> 60.939111 | K102: =CF!J102-CF!K98+CF!K100 -> 60.939111
...

Sheet Val
A1: Val — 目標價（約 12 個月後，2027-10-29；評價日 2026-09-30）＝DCF 50%＋分部加總 SOTP 50%（Comparable 在分部層做）；情境權重 A 25%／B 50%／C 25%（皆 [判斷] 預設，Andy 可改，In 頁黃底）。主值＝讀法 2（自用 AI 價值中性），讀法 1 並列
A2: 口徑（修正一）：DCF 的自由現金流扣股票薪酬（視為現金成本）、加自用 AI 影子效益（稅後），在帳融資租賃負債自權益橋扣除，推到目標價時點後扣期間股利；SOTP 的產品線 EBITDA 為股票薪酬加回口徑（與同業倍數同口徑），AI 基礎設施模組以自身 DCF（含資本支出與汰換）計價，同業倍數版列對照
A4: 0. 目標價
A5: 0.1 DCF（評價用自由現金流折現；WACC：Blume β、約 10 年期 kd、負債含融資租賃；g 3%）
A6: 項目 | B6: 情境 A（樂觀） | C6: 情境 B（基準） | D6: 情境 C（保守） | E6: 說明
A7: DCF 企業價值（評價日 2026-09-30） | B7: =Val!$C$83 -> 2350.5232 | C7: =Val!$C$132 -> 2096.6223 | D7: =Val!$C$181 -> 1790.9538 | E7: US$B；FY2027 只計第二至第四季
A8: 永續價值占比 | B8: =Val!$C$84 -> 0.74484002 | C8: =Val!$C$133 -> 0.75187474 | D8: =Val!$C$182 -> 0.76320015 | E8: 永續價值現值 ÷ EV
A9: 加：淨現金（評價日 2026-09-30） | B9: =cash_val-debt_val -> 23.24 | C9: =cash_val-debt_val -> 23.24 | D9: =cash_val-debt_val -> 23.24 | E9: 現金與短期投資 64.509 − 債務面額 41.269（10-Q）
A10: 減：在帳融資租賃負債（評價日 2026-09-30） | B10: =fl_val -> 70.973 | C10: =fl_val -> 70.973 | D10: =fl_val -> 70.973 | E10: 修正一 F6：融資租賃列入淨負債；10-Q 70.973（含本季新起租）
A11: 加：OpenAI 持股（比例 × 估值 ×（1 − 流動性折價）） | B11: =oai_v -> 163.584 | C11: =oai_v -> 163.584 | D11: =oai_v -> 163.584 | E11: Anthropic 比例未揭露，不估值
A12: DCF 每股價值（評價日） | B12: =Val!$C$86 -> 331.23478 | C12: =Val!$C$135 -> 297.13581 | D12: =Val!$C$184 -> 256.08445 | E12: ÷ FY27Q1 稀釋加權股數
A13: DCF 情境價值推到 12 個月後（×（1＋WACC）^t − 期間股利） | B13: =Val!$C$88 -> 364.20644 | C13: =Val!$C$137 -> 326.30354 | D13: =Val!$C$186 -> 280.67266 | E13: t＝2026-09-30 → 2027-10-29；扣 FY2027 第二至第四季與 FY2028 第一季股利
A14: DCF 目標價（情境加權） | B14: =w_A*B13+w_B*C13+w_C*D13 -> 324.37155 | E14: Σ 情境權重 × 情境價值
A15: WACC／永續成長率 | B15: =wacc -> 0.10293659 | C15: =g_tv -> 0.03 | E15: WACC＝In 頁（CAPM，Blume β）；g＝In 頁
A17: 0.2 分部加總（SOTP；Comparable 在分部層做：非 AI 產品線＝目標價時點 NTM EBITDA × 同業 NTM EV/EBITDA 中位數；AI 基礎設施＝模組 DCF）
A18: 項目 | B18: 情境 A（樂觀） | C18: 情境 B（基準） | D18: 情境 C（保守） | E18: 倍數（x）
A19: EV：AI 基礎設施模組（Azure AI＋自用 AI；模組 DCF） | B19: =Val!$C$104 -> 424.25974 | C19: =Val!$C$153 -> 186.59213 | D19: =Val!$C$202 -> -109.24883
A20: EV：Azure 其他（非 AI 雲端同業） | B20: =Val!$C$106 -> 1085.1796 | C20: =Val!$C$155 -> 1089.0344 | D20: =Val!$C$204 -> 1093.0388 | E20: =m_cloud -> 13.82
A21: EV：Microsoft 365 cloud（企業軟體同業） | B21: =Val!$C$107 -> 1120.4776 | C21: =Val!$C$156 -> 1082.8496 | D21: =Val!$C$205 -> 1045.1706 | E21: =m_sw -> 10.8
A22: EV：Productivity and server licensing（企業軟體） | B22: =Val!$C$108 -> 372.68399 | C22: =Val!$C$157 -> 372.92925 | D22: =Val!$C$206 -> 373.17844 | E22: =m_sw -> 10.8
A23: EV：Industry solutions（企業軟體） | B23: =Val!$C$109 -> 108.99263 | C23: =Val!$C$158 -> 109.14535 | D23: =Val!$C$207 -> 109.30056 | E23: =m_sw -> 10.8
A24: EV：Frontier and support services（企業軟體） | B24: =Val!$C$110 -> 41.436265 | C24: =Val!$C$159 -> 41.494216 | D24: =Val!$C$208 -> 41.553104 | E24: =m_sw -> 10.8
A25: EV：Search and advertising（數位廣告同業） | B25: =Val!$C$111 -> 114.89107 | C25: =Val!$C$160 -> 115.05217 | D25: =Val!$C$209 -> 115.2159 | E25: =m_ads -> 9.11
A26: EV：XBOX（遊戲同業） | B26: =Val!$C$112 -> 98.505199 | C26: =Val!$C$161 -> 98.644176 | D26: =Val!$C$210 -> 98.785336 | E26: =m_game -> 12.63
A27: EV：Windows OEM and devices（PC／裝置同業） | B27: =Val!$C$113 -> 91.323156 | C27: =Val!$C$162 -> 91.452375 | D27: =Val!$C$211 -> 91.583645 | E27: =m_pc -> 14.47
A28: 分部加總 EV | B28: =Val!$C$114 -> 3457.7493 | C28: =Val!$C$163 -> 3187.1937 | D28: =Val!$C$212 -> 2858.5775 | E28: US$B
A29: 加：淨現金（FY2027 年底）＋OpenAI 持股 − 在帳融資租賃負債＋期間非 AI 自由現金流 | B29: =Val!$C$116 -> 162.51156 | C29: =Val!$C$165 -> 162.10191 | D29: =Val!$C$214 -> 158.55427 | E29: 期間＝FY2027 年底 → 目標價時點（修正三）
A30: 分部加總每股價值（目標價時點） | B30: =Val!$C$117 -> 482.28929 | C30: =Val!$C$166 -> 445.8008 | D30: =Val!$C$215 -> 401.4594 | E30: ÷ FY2027 年底稀釋股數；扣 FY2028 第一季股利（修正二）
