Workbook

Sheet README
A1: 廣達電腦（2382）收支與估值模型 v0.2（AI 半導體 Project：伺服器組裝次產業樣板） 2026-10-25
A2: 版本：v0.2（2026-10-25：目標價改為 DCF 與 Comparable 加權、三情境延伸到 FY2032；FY2025–FY2029 數值不變）。前版：v0.1.1（2026-10-25：Val 新增第 0 節「目標價與上檔空間」、In 新增情境權重 tp_wA／tp_wB／tp_wC；其餘數值與 v0.1 相同）。v0.1（初版）：AI 伺服器組裝市場、廣達有效份額、ODM 每櫃價格與客供比例在本模型 Units 頁建立，為本專案權威資料（規則第 13 條）；鴻海、緯創之後讀這條組裝線。
A3: 模型命題：廣達的 AI 伺服器營收＝部署 GW（AI IT 資本支出 ÷ 每 GW IT 資本支出）× 每 GW ODM 整櫃價值 × 廣達有效份額 ×（1 − 客供比例）。組裝營收含轉手的 GPU，營收大、毛利率約 5%；客供比例上升時營收成長放慢、毛利率回升，毛利金額大致不變。市場約 10 倍未來 12 月 EPS。
A4: 核心問題：客供比例上升與 VR 每櫃價格上升之下，每櫃毛利金額能不能撐住 EPS 成長；約 10 倍未來 12 月 P/E 隱含什麼路徑。
A6: 會計年度＝日曆年，FY(t)＝CY(t)，不平移。預測期 FY2027–FY2029（三年）。金額：十億新台幣；整櫃價格與市場以美元計、以匯率換算。口徑：歸屬母公司淨利。
A8: 驅動因子 → 推導量（全部唯讀上游，不修改）
A9: AI 伺服器營收：markets/network 的 AI IT 資本支出 × 情境顆數係數 ÷ 每 GW IT 資本支出（Tokenomics，經橋接表）＝部署 GW；× 每 GW 架數（Tokenomics）× ODM 每櫃價格（法人）＝組裝市場；× 廣達有效份額（FY2026 以公司伺服器與 AI 占比校準）× 份額相對值（Assumed）×（1 − 客供比例，Assumed）。
A10: 非 AI：FY2026 殘差 × 成長率（Assumed）。毛利率：AI 伺服器（毛額基礎）比其他營收低 d_ai（Assumed），FY2027 起再加 VR 稀釋 vrd（Assumed），其他毛利率為 FY2026 殘差（Derived）；客供部分不計營收、保留 keep 比例的毛利。營業費用：彈性 phi（Derived）。淨利：營業利益 × 淨利係數（業外與稅前未找到）。
A11: 校準：FY2026 ＝ 1H26 實績＋3Q26 營收實績＋假設（4Q 季增、毛利率、營業費用率）。不用券商數字（只在 Recon 對帳）。
A12: 估值：Val 第 0 節目標價＝0.5 × DCF 目標價（股東現金流＝EPS ×（1 − tp_g ÷ tp_roe），FY2027–FY2032 明確期＋永續，r 10%、g 4%，三情境權重 0.3／0.5／0.2，推到 12 個月後）＋0.5 × Comparable 目標價（緯創、緯穎、鴻海、英業達、Super Micro 前瞻 P/E 中位數 × 12 個月後前瞻 EPS）；另列 Comparable 單獨目標價、市場共識目標價與差距拆解（EPS 因素、倍數因素）、DCF 價格帶、十年 P/E 分位檢查（只作檢查）。（v0.1.1 原估值說明，保留作參考：現價 ÷ FY2027、FY2028 EPS；十年 P/E 規則值（兩個資料商來源）× FY2027 EPS；循環位置以本模型營收最高年判定（不套設備股見頂年）。）
A13: 標記：Verified、Interested-party、Analogy、Assumed、Derived。SemiAnalysis 未使用。公司原文只經法說摘要與新聞；券商多未具名或單一來源。
A15: 已知限制：(1) 客供比例與保留毛利比例是 Assumed，公司只說「比重仍低」；(2) 份額只有一個量化來源（單月櫃數調查），且有效份額的分母含 ASIC、HGX 與其他廠，與櫃數份額不同口徑；(3) 2028 年起每 GW ODM 價值（Rubin Ultra）是 Assumed；(4) 部署 GW 以 VR200 每 GW IT 資本支出換算，ASIC 機架每 GW 資本支出較低，GW 可能低估；(5) 業外與稅前利益未找到，以淨利 ÷ 營業利益涵蓋；(6) 十年 P/E 兩來源在 2016–2021 年差距大，且 AI 前為低倍數；(7) 3Q26 法說（11 月中）後更新錨點；R4 產業部署路徑未建。
... A18: 先驗：v0.1 的 Andy 合理 P/E 對照保留不動，不進目標價；本版未新增先驗。

Sheet In
A1: In — 輸入（藍字；基準欄 E，低 D、高 F）。金額：十億新台幣（NT$B），整櫃價格與市場為美元；比例：%。每個輸入附兩個來源（找不到者寫「未找到」）；公司原文算一個
A2: 標記：Verified／Interested-party／Analogy／Assumed／Derived；Analogy、Assumed 給低／高區間。SemiAnalysis 未使用。公司原文＝廣達法說（經富果、優分析、Taipei Times 摘要）、月營收公告；公司的 AI 占比與展望為 Interested-party；券商估計皆為 Interested-party
A3: 鍵 | B3: 項目 | C3: 單位 | D3: 低 | E3: 基準 | F3: 高 | G3: 標記 | H3: 來源1 | I3: 來源2／說明
A4: A. AI 部署規模（讀 markets/network、markets/chip_bridge、tsmc 成品；情境 A 基準，B／C 依顆數係數縮放）
A5: itc_26 | B5: AI IT 資本支出 2026 | C5: US$B | E5: 781.87292 | G5: Derived | H5: markets/network/dist/20261023_AI網通市場模型_v0.2.2.xlsx｜Mkt!C27:F27 | I5: 加速器顆數 × 每顆 IT capex（含 ASIC）；本模型以此除以每 GW IT 資本支出得到部署 GW（與台達電模型同口徑）
A6: itc_27 | B6: AI IT 資本支出 2027 | C6: US$B | E6: 1565.35 | G6: Derived | H6: markets/network/dist/20261023_AI網通市場模型_v0.2.2.xlsx｜Mkt!C27:F27 | I6: 同上
A7: itc_28 | B7: AI IT 資本支出 2028 | C7: US$B | E7: 1984.2639 | G7: Derived | H7: markets/network/dist/20261023_AI網通市場模型_v0.2.2.xlsx｜Mkt!C27:F27 | I7: 同上
A8: itc_29 | B8: AI IT 資本支出 2029 | C8: US$B | E8: 2260.3903 | G8: Derived | H8: markets/network/dist/20261023_AI網通市場模型_v0.2.2.xlsx｜Mkt!C27:F27 | I8: 同上
A9: itpg_gb | B9: 每 GW IT 資本支出（GB300） | C9: US$B | E9: 32.237224 | G9: Derived | H9: markets/chip_bridge/dist/20261023_晶片內容橋接表_v0.2.1.xlsx｜In!E10（GB300）、H10（VR200） | I9: Tokenomics v20.1 IF_CapexIT（經橋接表；唯讀）
A10: itpg_vr | B10: 每 GW IT 資本支出（VR200；2027 起） | C10: US$B | E10: 37.586352 | G10: Derived | H10: markets/chip_bridge/dist/20261023_晶片內容橋接表_v0.2.1.xlsx｜In!E10（GB300）、H10（VR200） | I10: 同上；Rubin Ultra 與 ASIC 機架未另訂（Assumed：同 VR200）
A11: vr26 | B11: 2026 年部署中 Rubin 世代占比（混合用） | C11: % | D11: 0.15 | E11: 0.22 | F11: 0.3 | G11: Interested-party | H11: TrendForce 2026 組合 Rubin 22%（經 markets/memory） | I11: 廣達：Vera Rubin 4Q26 小量、1Q27 放量（財報狗 2026-10-08）
A12: racks_gb | B12: 每 GW 機架數（GB300） | C12: 架 | E12: 6764 | G12: Derived | H12: markets/chip_bridge/dist/20261023_晶片內容橋接表_v0.2.1.xlsx｜In!E6（GB300）、H6（VR200） | I12: Tokenomics IF_RacksPerGW（經橋接表）
A13: racks_vr | B13: 每 GW 機架數（VR200） | C13: 架 | E13: 4052 | G13: Derived | H13: markets/chip_bridge/dist/20261023_晶片內容橋接表_v0.2.1.xlsx｜In!E6（GB300）、H6（VR200） | I13: 同上
A14: rack_gb | B14: 整櫃買方價格（GB300，Tokenomics） | C14: US$M/架 | E14: 4.3 | G14: Derived | H14: markets/chip_bridge/dist/20261023_晶片內容橋接表_v0.2.1.xlsx｜In!E5（GB300）、H5（VR200） | I14: Recon 用：ODM 價 ÷ 買方價
A15: rack_vr | B15: 整櫃買方價格（VR200，Tokenomics） | C15: US$M/架 | E15: 8.4 | G15: Derived | H15: markets/chip_bridge/dist/20261023_晶片內容橋接表_v0.2.1.xlsx｜In!E5（GB300）、H5（VR200） | I15: 同上
A16: um28_A | B16: 情境 A：2028 顆數 ÷ 基準 | C16: x | E16: 1 | G16: Assumed | H16: tsmc/dist/20261025_台積電模型_v0.2.2.xlsx｜In!E37 | I16: A＝基準；B＝AI 資本支出消化；C＝明顯下修（與台積電、NVIDIA、Arista、台達電模型相同）
A17: um29_A | B17: 情境 A：2029 顆數 ÷ 基準 | C17: x | E17: 1 | G17: Assumed | H17: tsmc/dist/20261025_台積電模型_v0.2.2.xlsx｜In!E38 | I17: 同上
A18: um28_B | B18: 情境 B：2028 顆數 ÷ 基準 | C18: x | E18: 0.8 | G18: Assumed | H18: tsmc/dist/20261025_台積電模型_v0.2.2.xlsx｜In!E39 | I18: A＝基準；B＝AI 資本支出消化；C＝明顯下修（與台積電、NVIDIA、Arista、台達電模型相同）
A19: um29_B | B19: 情境 B：2029 顆數 ÷ 基準 | C19: x | E19: 0.85 | G19: Assumed | H19: tsmc/dist/20261025_台積電模型_v0.2.2.xlsx｜In!E40 | I19: 同上
A20: um28_C | B20: 情境 C：2028 顆數 ÷ 基準 | C20: x | E20: 0.6 | G20: Assumed | H20: tsmc/dist/20261025_台積電模型_v0.2.2.xlsx｜In!E41 | I20: A＝基準；B＝AI 資本支出消化；C＝明顯下修（與台積電、NVIDIA、Arista、台達電模型相同）
A21: um29_C | B21: 情境 C：2029 顆數 ÷ 基準 | C21: x | E21: 0.6 | G21: Assumed | H21: tsmc/dist/20261025_台積電模型_v0.2.2.xlsx｜In!E42 | I21: 同上
A22: fx | B22: 匯率（新台幣 ÷ 美元） | C22: NT$/US$ | D22: 30.5 | E22: 32 | F22: 33 | G22: Derived | H22: 與台達電模型相同（公司換算隱含約 32.7） | I22: 先驗比對用 32.7（只影響美元換算的市場與每 GW）
A23: B. 組裝價格、廣達份額與客供（本專案為權威：NVIDIA 整櫃組裝份額、每櫃 ODM 價格、客供比例，規則第 13 條）
A24: odm_gb | B24: ODM 每櫃價格 GB300 | C24: US$M/架 | D24: 3.6 | E24: 4 | F24: 4.3 | G24: Interested-party | H24: https://www.ctee.com.tw/news/20261008700747-430201：GB300 ASP 約 US$4M（法人，未具名） | I24: FTNN 2026-10-09 同值；上限＝Tokenomics 買方價 4.3
A25: odm_vr | B25: ODM 每櫃價格 VR200 | C25: US$M/架 | D25: 6.5 | E25: 6.75 | F25: 7 | G25: Interested-party | H25: https://www.ctee.com.tw/news/20261008700747-430201：VR ASP 估 US$6.5–7M（法人） | I25: FTNN 2026-10-09 同值；Tokenomics 買方價 8.4
A26: vpg_28 | B26: 每 GW ODM 整櫃價值 2028 ÷ 2027（Rubin Ultra） | C26: x | D26: 0.85 | E26: 1 | F26: 1.2 | G26: Assumed | H26: Rubin Ultra（Kyber）每櫃價格與每 GW 架數：未找到 | I26: 每 GW 價值 GB300 約 27.1B → VR200 約 27.4B（4.0 × 6,764 vs 6.75 × 4,052）：換世代時每 GW 大致持平
A27: vpg_29 | B27: 每 GW ODM 整櫃價值 2029 ÷ 2027 | C27: x | D27: 0.85 | E27: 1 | F27: 1.2 | G27: Assumed | H27: 同上 | I27: —
A28: rel_27 | B28: 廣達 AI 伺服器有效份額 2027 ÷ 2026（相對值） | C28: x | D28: 0.85 | E28: 1 | F28: 1.1 | G28: Assumed | H28: https://money.udn.com/money/amp/story/5607/9745501：美系券商 8 月調查 鴻海約 2,600 櫃、廣達 2,500–2,550、緯創 2,300–2,400（Interested-party，單一來源） | I28: 公司：前五大 CSP 為主，Neocloud GPU 與 CSP ASIC 專案小量出貨（2Q26 法說）；Neocloud 繞過 OEM 找 ODM（FTNN 2026-10-09）
A29: rel_28 | B29: 廣達份額 2028 ÷ 2026 | C29: x | D29: 0.75 | E29: 0.95 | F29: 1.1 | G29: Assumed | H29: 同上；台灣組裝產能 2028 再翻倍（公司） | I29: —
A30: rel_29 | B30: 廣達份額 2029 ÷ 2026 | C30: x | D30: 0.7 | E30: 0.9 | F30: 1.1 | G30: Assumed | H30: 同上 | I30: —
A31: cs_27 | B31: 客供比例 2027（AI 毛額價值中改為客戶供料、不計營收的比例） | C31: % | D31: 0 | E31: 0.1 | F31: 0.25 | G31: Assumed | H31: https://blog.fugle.tw/post/earnings-call-2382-2026-08-13：3Q26 起部分高價關鍵料件改客供，GPU 與 ASIC 客戶都有；比重仍低（公司） | I31: https://www.kgi.com.hk/zh-cn/-/media/files/kgishk/research-reports/tw-reports/quanta-computer-2382-tt-20260813en.pdf：2H26 客供比重小，營益率持平 1H26
A32: cs_28 | B32: 客供比例 2028 | C32: % | D32: 0 | E32: 0.2 | F32: 0.4 | G32: Assumed | H32: 同上；公司與客戶協商轉換以提高利潤率（Taipei Times 2026-05-15） | I32: —
A33: cs_29 | B33: 客供比例 2029 | C33: % | D33: 0 | E33: 0.25 | F33: 0.5 | G33: Assumed | H33: 同上 | I33: —
A34: keep | B34: 客供部分保留的毛利比例（相對買賣模式） | C34: x | D34: 0.7 | E34: 0.9 | F34: 1 | G34: Assumed | H34: 公司：客供可減輕毛利率稀釋與營運資金壓力（2Q26 法說） | I34: 買賣模式下轉手 GPU 的加價很薄；客供後少掉這部分加價：未找到量化
A35: C. 營收結構錨點（公司揭露比例 × 營收）
A36: srv_26 | B36: 2026 年伺服器營收 ÷ 營收 | C36: % | D36: 0.82 | E36: 0.85 | F36: 0.88 | G36: Interested-party | H36: https://blog.fugle.tw/post/earnings-call-2382-2026-08-13：伺服器自 1Q26 起超過 80%（公司） | I36: https://www.kgi.com.hk/zh-cn/-/media/files/kgishk/research-reports/tw-reports/quanta-computer-2382-tt-20260813en.pdf：雲端伺服器 2026F 85%、2027F 88%
A37: ais_26 | B37: 2026 年 AI 伺服器 ÷ 伺服器營收 | C37: % | D37: 0.75 | E37: 0.8 | F37: 0.82 | G37: Interested-party | H37: https://uanalyze.com.tw/articles/5252953366：1H26 75–80%，全年約 80%（公司） | I37: https://www.kgi.com.hk/zh-cn/-/media/files/kgishk/research-reports/tw-reports/quanta-computer-2382-tt-20260813en.pdf：同
A38: g_nai26 | B38: 2026 年非 AI 營收年增（反推 FY2025 AI 營收） | C38: % | D38: -0.05 | E38: 0.05 | F38: 0.15 | G38: Assumed | H38: 公司：筆電雙位數衰退、一般伺服器雙位數成長（2Q26 法說、財報狗 10-08） | I38: https://statementdog.com/news/17848：公司維持 AI 伺服器「三位數年增」；若只倍增，非 AI 須 +67%，與筆電衰退不符，所以倍增讀為下限
A39: g_nai27 | B39: 非 AI 營收年增 2027 | C39: % | D39: -0.05 | E39: 0.03 | F39: 0.08 | G39: Assumed | H39: 筆電 2026 年雙位數衰退、低於 20%（公司，財報狗 10-08）；一般伺服器雙位數成長（公司） | I39: 筆電約占 2026 營收 11–13%
A40: g_nai28 | B40: 非 AI 營收年增 2028 | C40: % | D40: -0.05 | E40: 0.02 | F40: 0.06 | G40: Assumed | H40: 同上 | I40: —
A41: g_nai29 | B41: 非 AI 營收年增 2029 | C41: % | D41: -0.05 | E41: 0.02 | F41: 0.06 | G41: Assumed | H41: 同上 | I41: —
A42: D. 毛利率
A43: d_ai | B43: AI 伺服器毛利率（毛額基礎）減其他營收毛利率 | C43: pt | D43: -0.035 | E43: -0.02 | F43: -0.005 | G43: Assumed | H43: 公司：高價 AI 機櫃稀釋毛利率；FY2025 6.98% → 1H26 4.92%（AI 占比上升） | I43: 部門別毛利率未揭露：未找到
A44: vrd | B44: VR 世代起 AI 毛利率（毛額基礎）變動（FY2027 起） | C44: pt | D44: -0.006 | E44: -0.003 | F44: 0 | G44: Assumed | H44: 凱基 2026-08-13（網址見 Sources）：VR 每櫃價格較高，毛利金額增加、毛利率可能被稀釋；凱基毛利率 2026F 4.9% → 2027F 4.7% | I44: 每櫃加工費與每櫃價格不同比例上升：未找到量化
A45: E. FY2026 錨點（1H26 實績＋3Q26 營收實績＋假設）
A46: q3_rev | B46: 3Q26 營收（月營收合計） | C46: NT$B | E46: 1115.5 | G46: Verified | H46: https://statementdog.com/news/17848：3Q26 1.1155 兆、前三季 2.9614 兆 | I46: TechNews 2026-10-08：前 9 月 2.96 兆
A47: q4g | B47: 4Q26 營收季增 | C47: % | D47: -0.15 | E47: -0.07 | F47: 0.05 | G47: Interested-party | H47: https://statementdog.com/news/17848：法人估全年接近 4 兆（4Q 約 1.04 兆，季減約 7%） | I47: 公司：GB300 為 4Q 主要動能、VR 4Q 小量；9 月月減 23%（出貨時點）
A48: q_gm | B48: 3Q、4Q26 毛利率 | C48: % | D48: 0.047 | E48: 0.05 | F48: 0.053 | G48: Interested-party | H48: https://blog.fugle.tw/post/earnings-call-2382-2026-08-13：全年利潤率維持 1H26 水準；2Q26 5.02%（公司） | I48: https://www.kgi.com.hk/zh-cn/-/media/files/kgishk/research-reports/tw-reports/quanta-computer-2382-tt-20260813en.pdf：2026F 4.9%
A49: q_opx | B49: 3Q、4Q26 營業費用 ÷ 營收 | C49: % | D49: 0.0165 | E49: 0.0175 | F49: 0.019 | G49: Assumed | H49: 2Q26 1.72%（新低）、1H26 1.81%（公司） | I49: —
A50: q_nio | B50: 3Q、4Q26 淨利 ÷ 營業利益 | C50: % | D50: 0.84 | E50: 0.87 | F50: 0.89 | G50: Derived | H50: 1H26 49.84 ÷ 57.3＝0.870；FY2025 74.98 ÷ 87.5＝0.857（公司） | I50: 業外收益與稅前利益：未找到（公開摘要未列）
A51: q_sh | B51: 股數（十億股；EPS 換算） | C51: 十億股 | E51: =49.84/12.93 -> 3.8546017 | G51: Derived | H51: 1H26 淨利 49.84 ÷ EPS 12.93（公司） | I51: FY2025 74.98 ÷ 19.45＝3.855
A52: F. 營業費用、淨利係數、股數（FY2027 起）
A53: phi | B53: 營業費用成長對營收成長的彈性 | C53: x | D53: 0.2 | E53: 0.4 | F53: 0.7 | G53: Derived | H53: FY2026 錨點實測（Q 頁 B26） | I53: 營業費用率 FY2025 2.9% → 2Q26 1.72%
A54: opx_adj | B54: 營業費用額外占營收比（Sens 用；基準 0） | C54: pt | D54: -0.002 | E54: 0 | F54: 0.002 | G54: Assumed | H54: 無 | I54: 營益率約 3%，±0.2 個百分點已是約 ±7% 的營業利益
A55: nio_f | B55: 淨利 ÷ 營業利益 | C55: % | D55: 0.75 | E55: 0.865 | F55: 0.89 | G55: Derived | H55: 同 q_nio（1H26 0.870、FY2025 0.857） | I55: 低值＝券商隱含：凱基 FY2026 EPS 27.06 × 3.855 ÷（3.2% × 4,219）≈ 0.77、FY2027 ≈ 0.73（原因未找到）
A56: sh_g | B56: 股數年變動 | C56: % | D56: 0 | E56: 0 | F56: 0.005 | G56: Assumed | H56: FY2025 3.855 → 1H26 3.855（公司 EPS 與淨利） | I56: —
A57: mf | B57: AI 部署係數（Sens 用；FY2027 起） | C57: x | D57: 0.8 | E57: 1 | F57: 1.2 | G57: Assumed | H57: 網通模型 2027 年 AI IT 資本支出約 2 倍 | I57: ±20%
A58: G. 共識、市場資料（只作 Recon 對帳，不作校準）
A59: b_rev26 | B59: 券商 FY2026 營收（凱基 08-13，3Q 前） | C59: NT$B | E59: 4219.196 | G59: Interested-party | H59: https://www.kgi.com.hk/zh-cn/-/media/files/kgishk/research-reports/tw-reports/quanta-computer-2382-tt-20260813en.pdf | I59: 3Q 只達法人預期 92%（工商時報 10-08）
A60: b_eps26 | B60: 券商 FY2026 EPS（凱基 08-13） | C60: NT$ | E60: 27.06 | G60: Interested-party | H60: https://www.kgi.com.hk/zh-cn/-/media/files/kgishk/research-reports/tw-reports/quanta-computer-2382-tt-20260813en.pdf | I60: —
A61: b_rev27a | B61: 券商 FY2027 營收（凱基 08-13） | C61: NT$B | E61: 5220.407 | G61: Interested-party | H61: https://www.kgi.com.hk/zh-cn/-/media/files/kgishk/research-reports/tw-reports/quanta-computer-2382-tt-20260813en.pdf | I61: —
A62: b_rev27b | B62: 券商 FY2027 營收（法人，10-08） | C62: NT$B | E62: 5300 | G62: Interested-party | H62: https://www.ctee.com.tw/news/20261008700747-430201（未具名） | I62: —
A63: b_eps27a | B63: 券商 FY2027 EPS（凱基 08-13） | C63: NT$ | E63: 31.75 | G63: Interested-party | H63: https://www.kgi.com.hk/zh-cn/-/media/files/kgishk/research-reports/tw-reports/quanta-computer-2382-tt-20260813en.pdf | I63: —
A64: b_eps27b | B64: 券商 FY2027 EPS（法人，10-08） | C64: NT$ | E64: 32.09 | G64: Interested-party | H64: https://www.ctee.com.tw/news/20261008700747-430201（未具名；目標價 400＝12.5x） | I64: FTNN 2026-10-09 同值
A65: b_gm27 | B65: 券商 FY2027 毛利率（凱基） | C65: % | E65: 0.047 | G65: Interested-party | H65: https://www.kgi.com.hk/zh-cn/-/media/files/kgishk/research-reports/tw-reports/quanta-computer-2382-tt-20260813en.pdf | I65: 營益率 3.2%
A66: rk_sh | B66: 三家 ODM 中廣達的 NVL72 櫃數份額（8 月調查） | C66: % | E66: =2525/(2600+2525+2350) -> 0.33779264 | G66: Interested-party | H66: 經濟日報 2026-09-10 引述美系券商（網址見 Sources） | I66: 單月、三家合計（不含 Dell、Supermicro 等）；第二個量化來源：未找到
A67: pe_fair_andy | B67: Andy 先驗：合理 P/E | C67: x | E67: 15 | G67: Assumed | H67: 先驗_Andy_廣達_20261024 Q9b（Drive；不在本 repo） | I67: 只作對照
A68: H. 價格與估值
A69: px | B69: 股價（2026-10-22 收盤） | C69: NT$ | E69: 322 | G69: Interested-party | H69: Yahoo 股市 2382（10-22 收盤 322、前收 328.5） | I69: 財報狗：10-13 收盤 323
A70: pe_ttm | B70: 近 12 月 P/E（10-22） | C70: x | E70: 14.31 | G70: Interested-party | H70: Yahoo 股市 2382 | I70: —
A71: I. 目標價情境權重（Val 第 0 節用；Andy 可改）
A72: tp_wA | B72: 目標價情境權重：情境 A（順利） | C72: 權重 | E72: 0.3 | G72: Assumed | H72: Andy 可改（2026-10-25 目標價規格預設 A／B／C＝0.3／0.5／0.2） | I72: 三個權重合計應為 1；v0.2 起用於 DCF 與 Comparable 的情境加權（Val 第 0 節）
A73: tp_wB | B73: 目標價情境權重：情境 B（平平） | C73: 權重 | E73: 0.5 | G73: Assumed | H73: Andy 可改（2026-10-25 目標價規格預設 A／B／C＝0.3／0.5／0.2） | I73: 三個權重合計應為 1；v0.2 起用於 DCF 與 Comparable 的情境加權（Val 第 0 節）
A74: tp_wC | B74: 目標價情境權重：情境 C（不如預期） | C74: 權重 | E74: 0.2 | G74: Assumed | H74: Andy 可改（2026-10-25 目標價規格預設 A／B／C＝0.3／0.5／0.2） | I74: 三個權重合計應為 1；v0.2 起用於 DCF 與 Comparable 的情境加權（Val 第 0 節）
A75: J. 目標價（DCF 與 Comparable 加權）與收斂法參數（v0.2 新增；黃底＝Assumed，Andy 可改）
A76: tp_r | B76: 折現率／要求報酬（DCF） | C76: % | E76: 0.1 | G76: Assumed | H76: Andy 可改（工作單 2026-10-25 預設 10%；美、台、日、韓同一值） | I76: Sens 頁 ±1pt
A77: tp_g | B77: 長期成長率（DCF 永續；情境 B 的 FY2032 營收年增收斂目標） | C77: % | E77: 0.04 | G77: Assumed | H77: Andy 可改（工作單預設 4%） | I77: Sens 頁 ±1pt（只動 DCF，PL 收斂目標不隨之變動）
A78: tp_roe | B78: ROE（近三年平均） | C78: % | E78: =AVERAGE(0.2186,0.2842,0.3119) -> 0.27156667 | G78: Derived | H78: stockanalysis 比率頁（Return on Equity）：FY2023 21.86%、FY2024 28.42%、FY2025 31.19% | I78: 單一來源；近 12 月 39.48%（同站）
A79: tp_w_dcf | B79: 目標價中 DCF 的權重；其餘為 Comparable | C79: % | E79: 0.5 | G79: Assumed | H79: Andy 可改（2026-10-25 11:53 改為 0.5：DCF／Comparable 各半） | I79: Sens 頁 0.4／0.8
A80: fade_gA | B80: 情境 A（順利）：FY2032 營收年增收斂目標（tp_g＋2pt） | C80: % | E80: =tp_g+0.02 -> 0.06 | G80: Assumed | H80: 工作單 2026-10-25 11:20 收斂法 | I80: FY2030 起由 FY2029 年增線性收斂，FY2032 達到
A81: fade_gB | B81: 情境 B（平平）：FY2032 營收年增收斂目標（＝tp_g） | C81: % | E81: =tp_g -> 0.04 | G81: Assumed | H81: 同上 | I81: —
A82: fade_gC | B82: 情境 C（不如預期）：FY2032 營收年增收斂目標（tp_g−2pt） | C82: % | E82: =tp_g-0.02 -> 0.02 | G82: Assumed | H82: 同上 | I82: —
A83: nim10_f | B83: 十年平均淨利率的替代：最後一年（FY2029）淨利率 ×（本值） | C83: x | E83: 0.8 | G83: Assumed | H83: 十年（2016–2025）平均淨利率：未找到（免費資料商只到近五年）；依工作單以最後一年 × 0.8 替代 | I83: 淨利率收斂目標：A＝FY2029、B＝FY2029 與替代值的中點、C＝替代值（PL 延伸表）
A84: cons_tp | B84: 市場共識目標價（賣方平均） | C84: NT$ | E84: 427.84 | G84: Interested-party | H84: stockanalysis 個股頁（S&P Global）19 位分析師平均 427.84，頁面時間 2026-10-14 | I84: 第二來源：未找到
A85: cons_feps | B85: 共識前瞻 12 月 EPS（＝價格 ÷ 前瞻 P/E） | C85: NT$ | E85: =323/11.31 -> 28.558798 | G85: Interested-party | H85: stockanalysis 個股頁 2026-10-14：價格 323 ÷ Forward PE 11.31 | I85: 賣方共識，只作對帳與差距拆解，不作校準

Sheet Q
A1: Q — 實績與 FY2026 錨點（十億新台幣；EPS 為新台幣；股數為十億股）。藍字＝輸入；黑字＝公式。實績取自廣達法說摘要、財報新聞與月營收
A2: FY2026 錨點＝1H26 實績＋3Q26 營收實績（月營收）＋3Q、4Q 假設（毛利率、營業費用率、淨利 ÷ 營業利益；4Q 營收＝3Q × (1＋季增)）。FY2025 與 1H26 毛利由公司揭露的毛利率 × 營收推得；FY2025 營業利益同。業外與稅前：未找到
A3: 項目 | B3: FY2025A | C3: 1H26（實績） | D3: 3Q26（營收實績） | E3: 4Q26（模型） | F3: FY2026 錨點 | G3: 標記 | H3: 來源1（公司） | I3: 來源2／說明
A4: 營收 | B4: 2123.689 | C4: 1845.8 | D4: =q3_rev -> 1115.5 | E4: =D4*(1+q4g) -> 1037.415 | F4: =SUM(C4:E4) -> 3998.715 | G4: Verified／Interested-party（4Q 季增） | H4: FY2025：https://uanalyze.com.tw/articles/3341848159；1H26：https://blog.fugle.tw/post/earnings-call-2382-2026-08-13 | I4: FY2025 2,123.689（凱基）；1H26 1.8458 兆（公司）
A5: 毛利 | B5: =B4*0.0698 -> 148.23349 | C5: =C4*0.0492 -> 90.81336 | D5: =D4*q_gm -> 55.775 | E5: =E4*q_gm -> 51.87075 | F5: =SUM(C5:E5) -> 198.45911 | G5: Derived（毛利率 × 營收）／Interested-party | H5: FY2025：https://uanalyze.com.tw/articles/3341848159；1H26：https://blog.fugle.tw/post/earnings-call-2382-2026-08-13 | I5: FY2025 毛利率 6.98%；1H26 4.92%（公司）
A6: 毛利率 | B6: =B5/B4 -> 0.0698 | C6: =C5/C4 -> 0.0492 | D6: =D5/D4 -> 0.05 | E6: =E5/E4 -> 0.05 | F6: =F5/F4 -> 0.049630721 | G6: Derived | H6: — | I6: —
A7: 營業費用 | B7: =B5-B8 -> 60.737505 | C7: =C5-C8 -> 33.51336 | D7: =D4*q_opx -> 19.52125 | E7: =E4*q_opx -> 18.154763 | F7: =SUM(C7:E7) -> 71.189373 | G7: Derived（毛利 − 營業利益）／Assumed | H7: FY2025：https://uanalyze.com.tw/articles/3341848159；1H26：https://blog.fugle.tw/post/earnings-call-2382-2026-08-13 | I7: 3Q26 營收：月營收公告（財報狗 2026-10-08）
A8: 營業利益 | B8: =B4*0.0412 -> 87.495987 | C8: 57.3 | D8: =D5-D7 -> 36.25375 | E8: =E5-E7 -> 33.715987 | F8: =SUM(C8:E8) -> 127.26974 | G8: Derived／Verified | H8: FY2025：https://uanalyze.com.tw/articles/3341848159；1H26：https://blog.fugle.tw/post/earnings-call-2382-2026-08-13 | I8: FY2025 營益率 4.12%；1H26 573 億、營益率 3.1%（公司）
A9: 營業利益率 | B9: =B8/B4 -> 0.0412 | C9: =C8/C4 -> 0.03104345 | D9: =D8/D4 -> 0.0325 | E9: =E8/E4 -> 0.0325 | F9: =F8/F4 -> 0.031827659 | G9: Derived | H9: — | I9: —
A10: 歸屬母公司淨利 | B10: 74.98 | C10: 49.84 | D10: =D8*q_nio -> 31.540762 | E10: =E8*q_nio -> 29.332909 | F10: =SUM(C10:E10) -> 110.71367 | G10: Verified／Derived（3Q、4Q） | H10: FY2025：https://uanalyze.com.tw/articles/3341848159；1H26：https://blog.fugle.tw/post/earnings-call-2382-2026-08-13 | I10: 2Q26 28.65、2Q26 EPS 7.43
A11: 淨利 ÷ 營業利益（含業外、稅、非控制權益） | B11: =B10/B8 -> 0.85695359 | C11: =C10/C8 -> 0.86980803 | D11: =D10/D8 -> 0.87 | E11: =E10/E8 -> 0.87 | F11: =F10/F8 -> 0.86991357 | G11: Derived | H11: — | I11: —
A12: 股數（十億股） | B12: =74.98/19.45 -> 3.8550129 | C12: =q_sh -> 3.8546017 | D12: =q_sh -> 3.8546017 | E12: =q_sh -> 3.8546017 | F12: =q_sh -> 3.8546017 | G12: Derived | H12: FY2025：https://uanalyze.com.tw/articles/3341848159；1H26：https://blog.fugle.tw/post/earnings-call-2382-2026-08-13 | I12: 淨利 ÷ EPS
A13: EPS | B13: =B10/B12 -> 19.45 | C13: =C10/C12 -> 12.93 | D13: =D10/D12 -> 8.1826256 | E13: =E10/E12 -> 7.6098418 | F13: =F10/F12 -> 28.722467 | G13: Derived | H13: 淨利 ÷ 股數 | I13: —
A14: 公司揭露 EPS | B14: 19.45 | C14: 12.93 | G14: Verified | H14: FY2025：https://uanalyze.com.tw/articles/3341848159；1H26：https://blog.fugle.tw/post/earnings-call-2382-2026-08-13 | I14: 2Q26 7.43
A15: AI 伺服器營收（＝營收 × 伺服器占比 × AI 占伺服器） | B15: =B4-F16/(1+g_nai26) -> 905.033 | F15: =F4*srv_26*ais_26 -> 2719.1262 | G15: Derived／Interested-party | H15: 公司比例（In 頁 C 節）；FY2025＝營收 − FY2026 非 AI ÷（1＋非 AI 年增） | I15: 各季與年度 AI 營收金額未揭露：未找到
A16: 非 AI 營收（一般伺服器、筆電、其他） | B16: =F16/(1+g_nai26) -> 1218.656 | F16: =F4-F15 -> 1279.5888 | G16: Derived／Assumed（FY2025） | H16: — | I16: —
A18: FY2026 錨點的檢查（參考；校準未使用券商數字）
A19: FY2026 營收年增 | B19: =F4/B4-1 -> 0.88290988
A20: FY2026 營業費用年增 | B20: =F7/B7-1 -> 0.17208259
A21: 營業費用彈性（營業費用年增 ÷ 營收年增；In 頁 phi 的依據） | B21: =B20/B19 -> 0.19490391
A22: FY2026 營收 ÷ 凱基（08-13，3Q 前）− 1 | B22: =F4/b_rev26-1 -> -0.052256638
A23: FY2026 EPS ÷ 凱基 − 1 | B23: =F13/b_eps26-1 -> 0.061436341
A24: AI 伺服器營收 FY2026 年增（隱含；公司說三位數） | B24: =F15/B15-1 -> 2.0044498

Sheet Units
A1: Units — AI 伺服器組裝市場、廣達份額、客供比例（本專案權威，規則第 13 條）。部署 GW＝AI IT 資本支出（markets/network）÷ 每 GW IT 資本支出（Tokenomics，經橋接表）
A3: 項目 | B3: 單位 | C3: CY2026 | D3: CY2027 | E3: CY2028 | F3: CY2029 | G3: 說明
A4: 部署 GW（情境 A） | B4: GW | C4: =PL!D65 -> 23.399538 | D4: =PL!E65 -> 41.646766 | E4: =PL!F65 -> 52.792138 | F4: =PL!G65 -> 60.138592 | G4: AI IT 資本支出 ÷ 每 GW IT 資本支出
A5: 每 GW ODM 整櫃價值 | B5: US$B/GW | C5: =PL!D66 -> 27.1209 | D5: =PL!E66 -> 27.351 | E5: =PL!F66 -> 27.351 | F5: =PL!G66 -> 27.351 | G5: 架數 × ODM 每櫃價格（GB300 4.0、VR200 6.75 百萬美元）
A6: AI 伺服器組裝市場（ODM 價） | B6: US$B | C6: =PL!D67 -> 634.61653 | D6: =PL!E67 -> 1139.0807 | E6: =PL!F67 -> 1443.9178 | F6: =PL!G67 -> 1644.8506 | G6: 含 ASIC 機架（假設每 GW 價值相同）
A7: 廣達有效份額 | B7: % | C7: =PL!D71 -> 0.13389612 | D7: =PL!E71 -> 0.13389612 | E7: =PL!F71 -> 0.12720132 | F7: =PL!G71 -> 0.12050651 | G7: FY2026 以公司伺服器與 AI 占比校準
A8: 廣達 AI 伺服器毛額價值 | B8: US$B | C8: =PL!D72/fx -> 84.972694 | D8: =PL!E72/fx -> 152.51849 | E8: =PL!F72/fx -> 183.66824 | F8: =PL!G72/fx -> 198.21521 | G8: 買賣模式下的營收
A9: 客供比例 | B9: % | C9: =PL!D73 -> 0 | D9: =PL!E73 -> 0.1 | E9: =PL!F73 -> 0.2 | F9: =PL!G73 -> 0.25 | G9: Assumed（FY2027 起）
A10: 廣達 AI 伺服器營收 | B10: US$B | C10: =PL!D74/fx -> 84.972694 | D10: =PL!E74/fx -> 137.26664 | E10: =PL!F74/fx -> 146.93459 | F10: =PL!G74/fx -> 148.66141
A11: 隱含廣達出貨櫃數（NVL72 等值） | B11: 千櫃 | C11: =PL!D81 -> 18.452268 | D11: =PL!E81 -> 22.595332 | E11: =PL!F81 -> 27.21011 | F11: =PL!G81 -> 29.365216 | G11: 毛額價值 ÷ ODM 每櫃價格
A12: 每 GW 廣達 AI 伺服器營收 | B12: US$B/GW | C12: =PL!D80 -> 3.6313834 | D12: =PL!E80 -> 3.2959736 | E12: =PL!F80 -> 2.7832666 | F12: =PL!G80 -> 2.4719802 | G12: 先驗比對推導 2026 約 3.4–4.2
A13: 廣達 AI 伺服器毛利率（營收基礎） | B13: % | C13: =PL!D87 -> 0.043230721 | D13: =PL!E87 -> 0.044253794 | E13: =PL!F87 -> 0.049282634 | F13: =PL!G87 -> 0.052299938 | G13: 客供上升 → 毛利率上升、毛利金額大致不變
A14: 其他廠商（鴻海、緯創、英業達、Dell、Supermicro 等）＝ 市場 − 廣達毛額 | B14: US$B | C14: =PL!D67-PL!D72/fx -> 549.64384 | D14: =PL!E67-PL!E72/fx -> 986.5622 | E14: =PL!F67-PL!F72/fx -> 1260.2495 | F14: =PL!G67-PL!G72/fx -> 1446.6354
A16: 讀法：FY2026 有效份額遠低於整櫃櫃數份額（三家中約三分之一），因為本模型分母是全部 AI IT 資本支出換算的組裝市場（含 ASIC、HGX 與其他組裝廠），且公司部分出貨為運算托盤而非整櫃。客供比例與份額相對值是 Assumed，是最需要每季檢查的輸入。

Sheet PL
A1: PL — 廣達損益（十億新台幣；EPS 新台幣；歸屬母公司）。FY2025A 實績、FY2026 錨點（1H26 實績＋3Q26 營收實績＋假設），FY2027 起為模型。FY(t)＝CY(t)。三情境各一個完整推導區塊（本頁下方），頂端為摘要。FY2026–FY2027 三情境相同（顆數係數從 CY2028 開始）
A3: 情境／項目 | B3: 單位 | C3: FY2025A | D3: FY2026（錨點） | E3: FY2027 | F3: FY2028 | G3: FY2029 | H3: 說明
A4: 情境 A
A5: 營收 | B5: NT$B | C5: =C77 -> 2123.689 | D5: =D77 -> 3998.715 | E5: =E77 -> 5710.509 | F5: =F77 -> 6046.243 | G5: =G77 -> 6128.3878
A6: 營收年增 | B6: % | D6: =D78 -> 0.88290988 | E6: =E78 -> 0.42808601 | F6: =F78 -> 0.058792318 | G6: =G78 -> 0.013586081
A7: AI 伺服器營收 | B7: NT$B | C7: =C74 -> 905.033 | D7: =D74 -> 2719.1262 | E7: =E74 -> 4392.5325 | F7: =F74 -> 4701.907 | G7: =G74 -> 4757.1651
A8: 非 AI 營收 | B8: NT$B | C8: =C76 -> 1218.656 | D8: =D76 -> 1279.5888 | E8: =E76 -> 1317.9765 | F8: =F76 -> 1344.336 | G8: =G76 -> 1371.2227
A9: AI 伺服器 ÷ 營收 | B9: % | C9: =C79 -> 0.4261608 | D9: =D79 -> 0.68 | E9: =E79 -> 0.76920158 | F9: =F79 -> 0.77765763 | G9: =G79 -> 0.77625066
A10: 毛利 | B10: NT$B | C10: =C85 -> 148.23349 | D10: =D85 -> 198.45911 | E10: =E85 -> 277.72283 | F10: =F85 -> 316.7257 | G10: =G85 -> 335.50284
A11: 毛利率 | B11: % | C11: =C86 -> 0.0698 | D11: =D86 -> 0.049630721 | E11: =E86 -> 0.048633639 | F11: =F86 -> 0.052383885 | G11: =G86 -> 0.054745693
A12: 營業利益率 | B12: % | C12: =C91 -> 0.0412 | D12: =D91 -> 0.031827659 | E12: =E91 -> 0.034032586 | F12: =F91 -> 0.03826929 | G12: =G91 -> 0.040744614
A13: 歸屬母公司淨利 | B13: NT$B | C13: =C93 -> 74.98 | D13: =D93 -> 110.71367 | E13: =E93 -> 168.10703 | F13: =F93 -> 200.14839 | G13: =G93 -> 215.98945
A14: EPS | B14: NT$ | C14: =C95 -> 19.45 | D14: =D95 -> 28.722467 | E14: =E95 -> 43.612036 | F14: =F95 -> 51.924533 | G14: =G95 -> 56.034182
A15: EPS 年增 | B15: % | D15: =D96 -> 0.47673354 | E15: =E96 -> 0.51839449 | F15: =F96 -> 0.19060098 | G15: =G96 -> 0.079146581
A17: 情境 B
A18: 營收 | B18: NT$B | C18: =C116 -> 2123.689 | D18: =D116 -> 3998.715 | E18: =E116 -> 5710.509 | F18: =F116 -> 5105.8616 | G18: =G116 -> 5414.813
A19: 營收年增 | B19: % | D19: =D117 -> 0.88290988 | E19: =E117 -> 0.42808601 | F19: =F117 -> -0.10588327 | G19: =G117 -> 0.060509159
A20: AI 伺服器營收 | B20: NT$B | C20: =C113 -> 905.033 | D20: =D113 -> 2719.1262 | E20: =E113 -> 4392.5325 | F20: =F113 -> 3761.5256 | G20: =G113 -> 4043.5903
A21: 非 AI 營收 | B21: NT$B | C21: =C115 -> 1218.656 | D21: =D115 -> 1279.5888 | E21: =E115 -> 1317.9765 | F21: =F115 -> 1344.336 | G21: =G115 -> 1371.2227
A22: AI 伺服器 ÷ 營收 | B22: % | C22: =C118 -> 0.4261608 | D22: =D118 -> 0.68 | E22: =E118 -> 0.76920158 | F22: =F118 -> 0.73670732 | G22: =G118 -> 0.74676453
A23: 毛利 | B23: NT$B | C23: =C124 -> 148.23349 | D23: =D124 -> 198.45911 | E23: =E124 -> 277.72283 | F23: =F124 -> 270.38122 | G23: =G124 -> 298.18292
A24: 毛利率 | B24: % | C24: =C125 -> 0.0698 | D24: =D125 -> 0.049630721 | E24: =E125 -> 0.048633639 | F24: =F125 -> 0.052955063 | G24: =G125 -> 0.055068
A25: 營業利益率 | B25: % | C25: =C130 -> 0.0412 | D25: =D130 -> 0.031827659 | E25: =E130 -> 0.034032586 | F25: =F130 -> 0.036624922 | G25: =G130 -> 0.039296905
A26: 歸屬母公司淨利 | B26: NT$B | C26: =C132 -> 74.98 | D26: =D132 -> 110.71367 | E26: =E132 -> 168.10703 | F26: =F132 -> 161.75654 | G26: =G132 -> 184.05936
A27: EPS | B27: NT$ | C27: =C134 -> 19.45 | D27: =D134 -> 28.722467 | E27: =E134 -> 43.612036 | F27: =F134 -> 41.964528 | G27: =G134 -> 47.750553
A28: EPS 年增 | B28: % | D28: =D135 -> 0.47673354 | E28: =E135 -> 0.51839449 | F28: =F135 -> -0.037776458 | G28: =G135 -> 0.13787896
A30: 情境 C
A31: 營收 | B31: NT$B | C31: =C155 -> 2123.689 | D31: =D155 -> 3998.715 | E31: =E155 -> 5710.509 | F31: =F155 -> 4165.4802 | G31: =G155 -> 4225.5217
A32: 營收年增 | B32: % | D32: =D156 -> 0.88290988 | E32: =E156 -> 0.42808601 | F32: =F156 -> -0.27055885 | G32: =G156 -> 0.014414073
A33: AI 伺服器營收 | B33: NT$B | C33: =C152 -> 905.033 | D33: =D152 -> 2719.1262 | E33: =E152 -> 4392.5325 | F33: =F152 -> 2821.1442 | G33: =G152 -> 2854.299
A34: 非 AI 營收 | B34: NT$B | C34: =C154 -> 1218.656 | D34: =D154 -> 1279.5888 | E34: =E154 -> 1317.9765 | F34: =F154 -> 1344.336 | G34: =G154 -> 1371.2227
A35: AI 伺服器 ÷ 營收 | B35: % | C35: =C157 -> 0.4261608 | D35: =D157 -> 0.68 | E35: =E157 -> 0.76920158 | F35: =F157 -> 0.67726746 | G35: =G157 -> 0.67549032
A36: 毛利 | B36: NT$B | C36: =C163 -> 148.23349 | D36: =D163 -> 198.45911 | E36: =E163 -> 277.72283 | F36: =F163 -> 224.03675 | G36: =G163 -> 235.98306
A37: 毛利率 | B37: % | C37: =C164 -> 0.0698 | D37: =D164 -> 0.049630721 | E37: =E164 -> 0.048633639 | F37: =F164 -> 0.053784135 | G37: =G164 -> 0.055847083
A38: 營業利益率 | B38: % | C38: =C169 -> 0.0412 | D38: =D169 -> 0.031827659 | E38: =E169 -> 0.034032586 | F38: =F169 -> 0.033767369 | G38: =G169 -> 0.036000971
A39: 歸屬母公司淨利 | B39: NT$B | C39: =C171 -> 74.98 | D39: =D171 -> 110.71367 | E39: =E171 -> 168.10703 | F39: =F171 -> 121.66857 | G39: =G171 -> 131.5863
A40: EPS | B40: NT$ | C40: =C173 -> 19.45 | D40: =D173 -> 28.722467 | E40: =E173 -> 43.612036 | F40: =F173 -> 31.564499 | G40: =G173 -> 34.137456
A41: EPS 年增 | B41: % | D41: =D174 -> 0.47673354 | E41: =E174 -> 0.51839449 | F41: =F174 -> -0.2762434 | G41: =G174 -> 0.08151426
A43: 核對（應為 0）：FY2026 模型營收 − 錨點；FY2026 模型 AI 伺服器 − 錨點；FY2026 毛利 − 錨點
A44: 情境 A：營收差（NT$B） | D44: =D77-a26_rev -> 0
A45: 情境 A：AI 伺服器差（NT$B） | D45: =D74-a26_ai -> 0
A46: 情境 A：毛利差（NT$B；以 FY2027 公式套用 FY2026） | D46: =D83*D76+D84-a26_gp -> 0
A60: 情境 A：基準（顆數係數 1.0）
A61: 項目 | B61: 單位 | C61: FY2025A | D61: FY2026（錨點） | E61: FY2027 | F61: FY2028 | G61: FY2029 | H61: 說明
A62: A. AI 部署與整櫃組裝市場（D 欄＝FY2026 校準年；E–G＝FY2027–FY2029）
A63: AI IT 資本支出 × 情境顆數係數 | B63: US$B | D63: =itc_26*1 -> 781.87292 | E63: =itc_27*1*1 -> 1565.35 | F63: =itc_28*um28_A*1 -> 1984.2639 | G63: =itc_29*um29_A*1 -> 2260.3903
A64: 每 GW IT 資本支出 | B64: US$B | D64: =itpg_gb*(1-vr26)+itpg_vr*vr26 -> 33.414032 | E64: =itpg_vr -> 37.586352 | F64: =itpg_vr -> 37.586352 | G64: =itpg_vr -> 37.586352
A65: 部署 GW（IT 電力） | B65: GW | D65: =D63/D64 -> 23.399538 | E65: =E63/E64 -> 41.646766 | F65: =F63/F64 -> 52.792138 | G65: =G63/G64 -> 60.138592
A66: 每 GW ODM 整櫃價值 | B66: US$B/GW | D66: =(racks_gb*odm_gb*(1-vr26)+racks_vr*odm_vr*vr26)/1000 -> 27.1209 | E66: =racks_vr*odm_vr/1000 -> 27.351 | F66: =$E66*vpg_28 -> 27.351 | G66: =$E66*vpg_29 -> 27.351 | H66: 架數 × ODM 每櫃價格；含 ASIC 機架（Assumed：每 GW 價值相同）
A67: AI 伺服器組裝市場（ODM 價，美元） | B67: US$B | D67: =D65*D66 -> 634.61653 | E67: =E65*E66 -> 1139.0807 | F67: =F65*F66 -> 1443.9178 | G67: =G65*G66 -> 1644.8506
A68: AI 伺服器組裝市場（新台幣） | B68: NT$B | D68: =D67*fx -> 20307.729 | E68: =E67*fx -> 36450.582 | F68: =F67*fx -> 46205.369 | G68: =G67*fx -> 52635.22
A69: 廣達有效份額（FY2026 校準）＝ AI 伺服器營收 ÷ 市場 | B69: % | D69: =a26_ai/D68 -> 0.13389612 | H69: Derived：分子為公司伺服器占比 × AI 占比 × 營收；分母含 ASIC、HGX 機架，所以低於整櫃櫃數份額
A70: 份額相對值（÷ FY2026） | B70: x | D70: =1 -> 1 | E70: =rel_27 -> 1 | F70: =rel_28 -> 0.95 | G70: =rel_29 -> 0.9
A71: 廣達有效份額 | B71: % | D71: =$D$69*D70 -> 0.13389612 | E71: =$D$69*E70 -> 0.13389612 | F71: =$D$69*F70 -> 0.12720132 | G71: =$D$69*G70 -> 0.12050651
A72: AI 伺服器毛額價值（買賣模式下的營收） | B72: NT$B | D72: =D68*D71 -> 2719.1262 | E72: =E68*E71 -> 4880.5917 | F72: =F68*F71 -> 5877.3838 | G72: =G68*G71 -> 6342.8867
A73: 客供比例 | B73: % | D73: =0 -> 0 | E73: =cs_27 -> 0.1 | F73: =cs_28 -> 0.2 | G73: =cs_29 -> 0.25 | H73: FY2026 的少量客供已含在錨點與校準份額內，記為 0
A74: AI 伺服器營收 | B74: NT$B | C74: =a25_ai -> 905.033 | D74: =D72*(1-D73) -> 2719.1262 | E74: =E72*(1-E73) -> 4392.5325 | F74: =F72*(1-F73) -> 4701.907 | G74: =G72*(1-G73) -> 4757.1651
A75: B. 非 AI 與合計
A76: 非 AI 營收（一般伺服器、筆電、其他） | B76: NT$B | C76: =a25_nai -> 1218.656 | D76: =a26_nai -> 1279.5888 | E76: =D76*(1+g_nai27) -> 1317.9765 | F76: =E76*(1+g_nai28) -> 1344.336 | G76: =F76*(1+g_nai29) -> 1371.2227
A77: 營收 | B77: NT$B | C77: =C74+C76 -> 2123.689 | D77: =D74+D76 -> 3998.715 | E77: =E74+E76 -> 5710.509 | F77: =F74+F76 -> 6046.243 | G77: =G74+G76 -> 6128.3878
A78: 營收年增 | B78: % | D78: =D77/C77-1 -> 0.88290988 | E78: =E77/D77-1 -> 0.42808601 | F78: =F77/E77-1 -> 0.058792318 | G78: =G77/F77-1 -> 0.013586081
A79: AI 伺服器 ÷ 營收 | B79: % | C79: =C74/C77 -> 0.4261608 | D79: =D74/D77 -> 0.68 | E79: =E74/E77 -> 0.76920158 | F79: =F74/F77 -> 0.77765763 | G79: =G74/G77 -> 0.77625066
A80: 每 GW 廣達 AI 伺服器營收 | B80: US$B/GW | D80: =D74/fx/D65 -> 3.6313834 | E80: =E74/fx/E65 -> 3.2959736 | F80: =F74/fx/F65 -> 2.7832666 | G80: =G74/fx/G65 -> 2.4719802
A81: 隱含廣達出貨櫃數（毛額價值 ÷ ODM 每櫃價格；NVL72 等值） | B81: 千櫃 | D81: =D72/fx/(odm_gb*(1-vr26)+odm_vr*vr26) -> 18.452268 | E81: =E72/fx/odm_vr -> 22.595332 | F81: =F72/fx/odm_vr -> 27.21011 | G81: =G72/fx/odm_vr -> 29.365216 | H81: 十億美元 ÷ 百萬美元 ＝ 千櫃；FY2028 起若每 GW 價值改變，每櫃價格仍以 VR200 換算（參考）
A82: C. 損益
A83: 其他營收毛利率 ＝ 錨點毛利率 − 差距 × AI 占比（FY2026 校準） | B83: % | D83: =a26_gp/D77-d_ai*D79 -> 0.063230721 | H83: Derived：讓 FY2026 毛利率等於錨點；AI 毛利率（毛額基礎）＝其他 + 差距（差距為負）
A84: AI 伺服器毛利 ＝ AI 毛利率 × 毛額價值 ×（1 − 客供 ×（1 − 保留比例）） | B84: NT$B | D84: =($D$83+d_ai)*D72*(1-D73*(1-keep)) -> 117.54979 | E84: =($D$83+d_ai+vrd)*E72*(1-E73*(1-keep)) -> 194.38623 | F84: =($D$83+d_ai+vrd)*F72*(1-F73*(1-keep)) -> 231.72236 | G84: =($D$83+d_ai+vrd)*G72*(1-G73*(1-keep)) -> 248.79944 | H84: 客供部分不計營收，但大部分毛利金額保留（keep）；FY2027 起加 VR 稀釋 vrd
A85: 毛利 | B85: NT$B | C85: =a25_gp -> 148.23349 | D85: =a26_gp -> 198.45911 | E85: =$D$83*E76+E84 -> 277.72283 | F85: =$D$83*F76+F84 -> 316.7257 | G85: =$D$83*G76+G84 -> 335.50284
A86: 毛利率 | B86: % | C86: =C85/C77 -> 0.0698 | D86: =D85/D77 -> 0.049630721 | E86: =E85/E77 -> 0.048633639 | F86: =F85/F77 -> 0.052383885 | G86: =G85/G77 -> 0.054745693
A87: AI 伺服器毛利率（營收基礎） | B87: % | D87: =D84/D74 -> 0.043230721 | E87: =E84/E74 -> 0.044253794 | F87: =F84/F74 -> 0.049282634 | G87: =G84/G74 -> 0.052299938 | H87: 客供比例上升 → 營收基礎毛利率上升
A88: 營業費用（基準路徑） | B88: NT$B | C88: =a25_opx -> 60.737505 | D88: =a26_opx -> 71.189373 | E88: =D88*(1+MAX(0,phi*E78)) -> 83.379442 | F88: =E88*(1+MAX(0,phi*F78)) -> 85.340271 | G88: =F88*(1+MAX(0,phi*G78)) -> 85.804047
A89: 營業費用 | B89: NT$B | C89: =C88 -> 60.737505 | D89: =D88 -> 71.189373 | E89: =E88+0*E77 -> 83.379442 | F89: =F88+0*F77 -> 85.340271 | G89: =G88+0*G77 -> 85.804047
A90: 營業利益 | B90: NT$B | C90: =C85-C89 -> 87.495987 | D90: =D85-D89 -> 127.26974 | E90: =E85-E89 -> 194.34339 | F90: =F85-F89 -> 231.38543 | G90: =G85-G89 -> 249.69879
A91: 營業利益率 | B91: % | C91: =C90/C77 -> 0.0412 | D91: =D90/D77 -> 0.031827659 | E91: =E90/E77 -> 0.034032586 | F91: =F90/F77 -> 0.03826929 | G91: =G90/G77 -> 0.040744614
A92: 淨利 ÷ 營業利益 | B92: % | C92: =a25_ni/a25_oi -> 0.85695359 | D92: =a26_ni/a26_oi -> 0.86991357 | E92: =nio_f -> 0.865 | F92: =nio_f -> 0.865 | G92: =nio_f -> 0.865
A93: 歸屬母公司淨利 | B93: NT$B | C93: =a25_ni -> 74.98 | D93: =a26_ni -> 110.71367 | E93: =E90*E92 -> 168.10703 | F93: =F90*F92 -> 200.14839 | G93: =G90*G92 -> 215.98945
A94: 股數 | B94: 十億股 | C94: =a25_sh -> 3.8550129 | D94: =a26_sh -> 3.8546017 | E94: =D94*(1+sh_g) -> 3.8546017 | F94: =E94*(1+sh_g) -> 3.8546017 | G94: =F94*(1+sh_g) -> 3.8546017
A95: EPS | B95: NT$ | C95: =C93/C94 -> 19.45 | D95: =D93/D94 -> 28.722467 | E95: =E93/E94 -> 43.612036 | F95: =F93/F94 -> 51.924533 | G95: =G93/G94 -> 56.034182
A96: EPS 年增 | B96: % | D96: =D95/C95-1 -> 0.47673354 | E96: =E95/D95-1 -> 0.51839449 | F96: =F95/E95-1 -> 0.19060098 | G96: =G95/F95-1 -> 0.079146581
A99: 情境 B：CY2028 顆數 ×0.8、CY2029 ×0.85
A100: 項目 | B100: 單位 | C100: FY2025A | D100: FY2026（錨點） | E100: FY2027 | F100: FY2028 | G100: FY2029 | H100: 說明
A101: A. AI 部署與整櫃組裝市場（D 欄＝FY2026 校準年；E–G＝FY2027–FY2029）
A102: AI IT 資本支出 × 情境顆數係數 | B102: US$B | D102: =itc_26*1 -> 781.87292 | E102: =itc_27*1*1 -> 1565.35 | F102: =itc_28*um28_B*1 -> 1587.4111 | G102: =itc_29*um29_B*1 -> 1921.3317
A103: 每 GW IT 資本支出 | B103: US$B | D103: =itpg_gb*(1-vr26)+itpg_vr*vr26 -> 33.414032 | E103: =itpg_vr -> 37.586352 | F103: =itpg_vr -> 37.586352 | G103: =itpg_vr -> 37.586352
A104: 部署 GW（IT 電力） | B104: GW | D104: =D102/D103 -> 23.399538 | E104: =E102/E103 -> 41.646766 | F104: =F102/F103 -> 42.233711 | G104: =G102/G103 -> 51.117803
A105: 每 GW ODM 整櫃價值 | B105: US$B/GW | D105: =(racks_gb*odm_gb*(1-vr26)+racks_vr*odm_vr*vr26)/1000 -> 27.1209 | E105: =racks_vr*odm_vr/1000 -> 27.351 | F105: =$E105*vpg_28 -> 27.351 | G105: =$E105*vpg_29 -> 27.351 | H105: 架數 × ODM 每櫃價格；含 ASIC 機架（Assumed：每 GW 價值相同）
A106: AI 伺服器組裝市場（ODM 價，美元） | B106: US$B | D106: =D104*D105 -> 634.61653 | E106: =E104*E105 -> 1139.0807 | F106: =F104*F105 -> 1155.1342 | G106: =G104*G105 -> 1398.123
A107: AI 伺服器組裝市場（新台幣） | B107: NT$B | D107: =D106*fx -> 20307.729 | E107: =E106*fx -> 36450.582 | F107: =F106*fx -> 36964.295 | G107: =G106*fx -> 44739.937
A108: 廣達有效份額（FY2026 校準）＝ AI 伺服器營收 ÷ 市場 | B108: % | D108: =a26_ai/D107 -> 0.13389612 | H108: Derived：分子為公司伺服器占比 × AI 占比 × 營收；分母含 ASIC、HGX 機架，所以低於整櫃櫃數份額
A109: 份額相對值（÷ FY2026） | B109: x | D109: =1 -> 1 | E109: =rel_27 -> 1 | F109: =rel_28 -> 0.95 | G109: =rel_29 -> 0.9
A110: 廣達有效份額 | B110: % | D110: =$D$108*D109 -> 0.13389612 | E110: =$D$108*E109 -> 0.13389612 | F110: =$D$108*F109 -> 0.12720132 | G110: =$D$108*G109 -> 0.12050651
A111: AI 伺服器毛額價值（買賣模式下的營收） | B111: NT$B | D111: =D107*D110 -> 2719.1262 | E111: =E107*E110 -> 4880.5917 | F111: =F107*F110 -> 4701.907 | G111: =G107*G110 -> 5391.4537
A112: 客供比例 | B112: % | D112: =0 -> 0 | E112: =cs_27 -> 0.1 | F112: =cs_28 -> 0.2 | G112: =cs_29 -> 0.25 | H112: FY2026 的少量客供已含在錨點與校準份額內，記為 0
A113: AI 伺服器營收 | B113: NT$B | C113: =a25_ai -> 905.033 | D113: =D111*(1-D112) -> 2719.1262 | E113: =E111*(1-E112) -> 4392.5325 | F113: =F111*(1-F112) -> 3761.5256 | G113: =G111*(1-G112) -> 4043.5903
A114: B. 非 AI 與合計
A115: 非 AI 營收（一般伺服器、筆電、其他） | B115: NT$B | C115: =a25_nai -> 1218.656 | D115: =a26_nai -> 1279.5888 | E115: =D115*(1+g_nai27) -> 1317.9765 | F115: =E115*(1+g_nai28) -> 1344.336 | G115: =F115*(1+g_nai29) -> 1371.2227
A116: 營收 | B116: NT$B | C116: =C113+C115 -> 2123.689 | D116: =D113+D115 -> 3998.715 | E116: =E113+E115 -> 5710.509 | F116: =F113+F115 -> 5105.8616 | G116: =G113+G115 -> 5414.813
A117: 營收年增 | B117: % | D117: =D116/C116-1 -> 0.88290988 | E117: =E116/D116-1 -> 0.42808601 | F117: =F116/E116-1 -> -0.10588327 | G117: =G116/F116-1 -> 0.060509159
A118: AI 伺服器 ÷ 營收 | B118: % | C118: =C113/C116 -> 0.4261608 | D118: =D113/D116 -> 0.68 | E118: =E113/E116 -> 0.76920158 | F118: =F113/F116 -> 0.73670732 | G118: =G113/G116 -> 0.74676453
A119: 每 GW 廣達 AI 伺服器營收 | B119: US$B/GW | D119: =D113/fx/D104 -> 3.6313834 | E119: =E113/fx/E104 -> 3.2959736 | F119: =F113/fx/F104 -> 2.7832666 | G119: =G113/fx/G104 -> 2.4719802
...

Sheet Val
A1: Val — P/E 估值（新台幣）。結論用「現價 ÷ FY2027、FY2028 EPS（模型）」與十年 P/E 規則值（年底落後 P/E，基準為 FY2027 EPS）
A2: 循環位置：廣達不是設備股，不套設備市場見頂年；以本模型營收最高的會計年度為見頂年（比照 NVIDIA、Arista、台達電；FY(t)＝CY(t)）。營收到 FY2029 仍在增加時，見頂年未知，判為中段
A3: 目標價：見第 0 節（本頁第 85 列；v0.2 新增，DCF 與 Comparable 加權）。第 41 列「舊法：規則值情境加權（參考）」不再是目標價，只作參考
A4: 1. 價格與市場隱含倍數
A5: 項目 | B5: A | C5: B | D5: C | E5: 說明
A6: 現價（2026-10-22 收盤） | B6: =px -> 322
A7: 現價 ÷ FY2026 EPS（錨點） | B7: =px/PL!D14 -> 11.210736 | C7: =px/PL!D27 -> 11.210736 | D7: =px/PL!D40 -> 11.210736
A8: 現價 ÷ FY2027 EPS（模型） | B8: =px/PL!E14 -> 7.3832829 | C8: =px/PL!E27 -> 7.3832829 | D8: =px/PL!E40 -> 7.3832829 | E8: FY2027 三情境相同（顆數係數從 CY2028 開始）
A9: 現價 ÷ FY2028 EPS（模型） | B9: =px/PL!F14 -> 6.2013076 | C9: =px/PL!F27 -> 7.6731472 | D9: =px/PL!F40 -> 10.201334
A10: 現價 ÷ FY2029 EPS（模型） | B10: =px/PL!G14 -> 5.7464924 | C10: =px/PL!G27 -> 6.7433774 | D10: =px/PL!G40 -> 9.4324545
A11: 未來 12 月 EPS（模型 A）≈ 0.2 × FY2026＋0.8 × FY2027 | B11: =0.2*PL!D14+0.8*PL!E14 -> 40.634122
A12: 現價 ÷ 未來 12 月 EPS（模型 A） | B12: =px/B11 -> 7.9243744 | E12: Andy 先驗 Q9a 答 20x（未來 12 月）
A13: 近 12 月 P/E（Yahoo，10-22） | B13: =pe_ttm -> 14.31
A15: 2. 循環位置（本模型營收最高年；FY(t)＝CY(t)）
A16: 情境 | B16: 營收最高年（FY2026–FY2029） | C16: FY2027 判定 | D16: 規則倍數（P/E） | E16: 見頂年是否未知 | F16: 說明
A17: A | B17: =INDEX({2026,2027,2028,2029},MATCH(MAX(PL!D77:G77),PL!D77:G77,0)) -> 2029 | C17: =IF(B17=2029,"中段",IF(2027<B17,"中段",IF(2027=B17,"見頂","谷底"))) -> 中段 | D17: =IF(C17="見頂",pe_peak,IF(C17="谷底",pe_trough,pe_mid)) -> 12.27 | E17: =IF(B17=2029,"是：營收到觀測期末仍在增加","否") -> 是：營收到觀測期末仍在增加 | F17: tools/cycle_position.py excel_rule；營收最高年取代設備市場見頂年
A18: B | B18: =INDEX({2026,2027,2028,2029},MATCH(MAX(PL!D116:G116),PL!D116:G116,0)) -> 2027 | C18: =IF(B18=2029,"中段",IF(2027<B18,"中段",IF(2027=B18,"見頂","谷底"))) -> 見頂 | D18: =IF(C18="見頂",pe_peak,IF(C18="谷底",pe_trough,pe_mid)) -> 10.81 | E18: =IF(B18=2029,"是：營收到觀測期末仍在增加","否") -> 否 | F18: 同上
A19: C | B19: =INDEX({2026,2027,2028,2029},MATCH(MAX(PL!D155:G155),PL!D155:G155,0)) -> 2027 | C19: =IF(B19=2029,"中段",IF(2027<B19,"中段",IF(2027=B19,"見頂","谷底"))) -> 見頂 | D19: =IF(C19="見頂",pe_peak,IF(C19="谷底",pe_trough,pe_mid)) -> 10.81 | E19: =IF(B19=2029,"是：營收到觀測期末仍在增加","否") -> 否 | F19: 同上
A21: 3. 規則值隱含股價（新台幣；約 FY2027 年底，未折現）＝ FY2027 EPS × 規則倍數
A22: 情境 | B22: FY2027 EPS | C22: （同左） | D22: 規則倍數 | E22: 隱含股價 | F22: 相對現價 | G22: 現價 ÷ FY2027 EPS
A23: A | B23: =PL!E14 -> 43.612036 | C23: =B23 -> 43.612036 | D23: =D17 -> 12.27 | E23: =C23*D23 -> 535.11969 | F23: =E23/px-1 -> 0.66186238 | G23: =px/C23 -> 7.3832829
A24: B | B24: =PL!E27 -> 43.612036 | C24: =B24 -> 43.612036 | D24: =D18 -> 10.81 | E24: =C24*D24 -> 471.44611 | F24: =E24/px-1 -> 0.46411836 | G24: =px/C24 -> 7.3832829
A25: C | B25: =PL!E40 -> 43.612036 | C25: =B25 -> 43.612036 | D25: =D19 -> 10.81 | E25: =C25*D25 -> 471.44611 | F25: =E25/px-1 -> 0.46411836 | G25: =px/C25 -> 7.3832829
A26: 4. What must be true：FY2027 年底價 ＝ 現價 ×（1＋報酬）所需的倍數（FY2028 EPS；約 2027 年底的價格看下一年 EPS）
A27: FY2027 年底價 ÷ 現價 | B27: 所需倍數（÷ FY2028 EPS，A） | C27: 所需倍數（÷ FY2028 EPS，C） | D27: 對照：Andy 合理 P/E | E27: 對照：十年中位數
A28: 1 | B28: =px*A28/PL!F14 -> 6.2013076 | C28: =px*A28/PL!F40 -> 10.201334 | D28: =pe_fair_andy -> 15 | E28: =pe_mid -> 12.27
A29: 1.1 | B29: =px*A29/PL!F14 -> 6.8214383 | C29: =px*A29/PL!F40 -> 11.221467 | D29: =pe_fair_andy -> 15 | E29: =pe_mid -> 12.27
A30: 1.21 | B30: =px*A30/PL!F14 -> 7.5035822 | C30: =px*A30/PL!F40 -> 12.343614 | D30: =pe_fair_andy -> 15 | E30: =pe_mid -> 12.27
A31: 1.5 | B31: =px*A31/PL!F14 -> 9.3019614 | C31: =px*A31/PL!F40 -> 15.302001 | D31: =pe_fair_andy -> 15 | E31: =pe_mid -> 12.27
A32: 2 | B32: =px*A32/PL!F14 -> 12.402615 | C32: =px*A32/PL!F40 -> 20.402668 | D32: =pe_fair_andy -> 15 | E32: =pe_mid -> 12.27
A33: 讀法：1.00＝價格不變、1.21＝一年約 21%。所需倍數低於歷史中位數時，現價相對便宜；倍數是否合理，另看前瞻 P/E 歷史（Bloomberg）。
A35: 5. 對照：以 Andy 合理 P/E 15x 計算的隱含價（只作對照，非規則值）
A36: 情境 | B36: FY2027 EPS | C36: × 15x | D36: 相對現價 | E36: FY2028 EPS | F36: × 15x | G36: 相對現價
A37: A | B37: =PL!E14 -> 43.612036 | C37: =B37*pe_fair_andy -> 654.18054 | D37: =C37/px-1 -> 1.0316166 | E37: =PL!F14 -> 51.924533 | F37: =E37*pe_fair_andy -> 778.86799 | G37: =F37/px-1 -> 1.4188447
A38: B | B38: =PL!E27 -> 43.612036 | C38: =B38*pe_fair_andy -> 654.18054 | D38: =C38/px-1 -> 1.0316166 | E38: =PL!F27 -> 41.964528 | F38: =E38*pe_fair_andy -> 629.46792 | G38: =F38/px-1 -> 0.95486932
A39: C | B39: =PL!E40 -> 43.612036 | C39: =B39*pe_fair_andy -> 654.18054 | D39: =C39/px-1 -> 1.0316166 | E39: =PL!F40 -> 31.564499 | F39: =E39*pe_fair_andy -> 473.46749 | G39: =F39/px-1 -> 0.47039593
A41: 舊法：規則值情境加權（參考；v0.1.1 的「0. 目標價與上檔空間」改名，不再是目標價；權重為 In 頁 tp_wA／tp_wB／tp_wC）
A42: 舊法隱含價（情境加權，參考） | B42: =tp_wA*B44+tp_wB*B45+tp_wC*B46 -> 490.54818 | E42: ＝權重 A × 情境 A 隱含價＋權重 B × 情境 B 隱含價＋權重 C × 情境 C 隱含價（NT$）
A43: 舊法隱含價相對現價（÷ 現價 − 1） | B43: =B42/px-1 -> 0.52344157 | E43: 相對「現價（2026-10-22 收盤）」
A44: 情境 A 隱含價（樂觀） | B44: =E23 -> 535.11969 | E44: ＝規則值隱含股價 E23（情境 A：基準（顆數係數 1.0））
A45: 情境 B 隱含價（基準） | B45: =E24 -> 471.44611 | E45: ＝規則值隱含股價 E24（情境 B：CY2028 顆數 ×0.8、CY2029 ×0.85）
A46: 情境 C 隱含價（下檔） | B46: =E25 -> 471.44611 | E46: ＝規則值隱含股價 E25（情境 C：CY2028–29 顆數 ×0.6）
A47: 情境權重 A／B／C | B47: =tp_wA -> 0.3 | C47: =tp_wB -> 0.5 | D47: =tp_wC -> 0.2 | E47: In 頁輸入（Assumed，Andy 可改）：B 欄＝情境 A、C 欄＝情境 B、D 欄＝情境 C
A48: 舊法說明 | B48: P/E 規則值：各情境 FY2027 EPS × 2016–2025 年底 P/E 依循環位置取分位（見頂＝25 分位、中段＝中位數、谷底＝75 分位；companiesmarketcap 與 Goodinfo 兩來源分別取分位再平均）。隱含價約為 FY2027 年底價、未折現，作 12 個月目標價的近似；情境 A／B／C 即本模型三個顆數情境（A 最高、C 最低）。偏誤：十年倍數含 2016–2022 年筆電代工期低倍數（約 8–17x），目標價可能偏低。
A50: 6. 十年倍數與規則值（2016–2025 年底；見頂年 25 分位、中段中位數、谷底 75 分位）
A51: 規則（Andy 2026-10-13）：合理倍數＝2016–2025 年底 P/E 依循環位置取分位，兩個來源分別取分位再平均。兩來源 2016–2021 年相差約 3–6 個倍數點（companiesmarketcap 疑用還原股價，數字較低）；Goodinfo 多年加權平均 P/E 區間 12.02–20.7 只作量級核對。2016–2022 年廣達為筆電代工為主的低成長公司（約 8–17x），2023 年起 AI 伺服器重新定價，規則值可能低估 AI 期的合理倍數。
A53: P/E：十年歷史倍數
A54: 年底 | B54: companiesmarketcap（年底 P/E） | C54: Goodinfo（年底收盤 ÷ EPS） | D54: 標記／說明
A55: 2016 | B55: 9.26 | C55: =60.3/3.93 -> 15.343511 | D55: companiesmarketcap（年底 P/E）：Interested-party（資料商；2016–2025 共 10 年；價格可能為還原股價）；Goodinfo（年底收盤 ÷ EPS）：Derived（資料商收盤價與 EPS；未還原除息）
A56: 2017 | B56: 10.5 | C56: =61.9/3.73 -> 16.595174
A57: 2018 | B57: 8.95 | C57: =52.7/3.92 -> 13.443878
A58: 2019 | B58: 11.1 | C58: =64.3/4.14 -> 15.531401
A59: 2020 | B59: 9.23 | C59: =80.9/6.57 -> 12.313546
A60: 2021 | B60: 8.62 | C60: =94.7/8.73 -> 10.847652
A61: 2022 | B61: 8.3 | C61: =72.3/7.51 -> 9.6271638
A62: 2023 | B62: 20.2 | C62: =224.5/10.29 -> 21.817298
A63: 2024 | B63: 17.7 | C63: =287/15.49 -> 18.528083
A64: 2025 | B64: 13.5 | C64: =272/19.45 -> 13.984576
A65: 25 分位（各來源） | B65: =PERCENTILE(B55:B64,0.25) -> 9.02 | C65: =PERCENTILE(C55:C64,0.25) -> 12.596129
A66: 中位數（各來源） | B66: =MEDIAN(B55:B64) -> 9.88 | C66: =MEDIAN(C55:C64) -> 14.664044
A67: 75 分位（各來源） | B67: =PERCENTILE(B55:B64,0.75) -> 12.9 | C67: =PERCENTILE(C55:C64,0.75) -> 16.329231
A68: 最小（各來源） | B68: =MIN(B55:B64) -> 8.3 | C68: =MIN(C55:C64) -> 9.6271638
A69: 最大（各來源） | B69: =MAX(B55:B64) -> 20.2 | C69: =MAX(C55:C64) -> 21.817298
A70: 採用 25 分位（P/E） | B70: =ROUND(AVERAGE(B65,C65),2) -> 10.81
A71: 採用 中位數（P/E） | B71: =ROUND(AVERAGE(B66,C66),2) -> 12.27
A72: 採用 75 分位（P/E） | B72: =ROUND(AVERAGE(B67,C67),2) -> 14.61
A73: 採用 最小（P/E） | B73: =ROUND(MIN(B68,C68),2) -> 8.3
A74: 採用 最大（P/E） | B74: =ROUND(MAX(B69,C69),2) -> 21.82
A76: P/E：規則值
A77: 情形 | B77: 循環位置 | C77: 倍數 | D77: 基準 | E77: 每股基準 | F77: 隱含股價 | G77: 相對目前 | H77: 現價 ÷ 基準
A78: 規則值：見頂（P/E） | B78: 25 分位 | C78: =B70 -> 10.81 | D78: FY2027 EPS（A） | E78: =C23 -> 43.612036 | F78: =C78*E78 -> 471.44611 | G78: =F78/px-1 -> 0.46411836 | H78: =px/E78 -> 7.3832829
A79: 規則值：中段（P/E） | B79: 中位數 | C79: =B71 -> 12.27 | D79: FY2027 EPS（A） | E79: =C23 -> 43.612036 | F79: =C79*E79 -> 535.11969 | G79: =F79/px-1 -> 0.66186238 | H79: =px/E79 -> 7.3832829
A80: 規則值：谷底（P/E） | B80: 75 分位 | C80: =B72 -> 14.61 | D80: FY2027 EPS（A） | E80: =C23 -> 43.612036 | F80: =C80*E80 -> 637.17185 | G80: =F80/px-1 -> 0.97879457 | H80: =px/E80 -> 7.3832829
A85: 0. 目標價（DCF 與 Comparable 加權；v0.2 新增，放在本頁既有內容之後以免位移既有儲存格；三情境欄 B／C／D＝A 順利／B 平平／C 不如預期）
A86: 0.1 DCF（股東權益現金流，FY2027–FY2032 明確期＋FY2032 後永續）
A87: 項目 | B87: A（順利） | C87: B（平平） | D87: C（不如預期） | E87: 說明
A88: 情境 EPS（FY2027–FY2032） | E88: PL 頁延伸表；FY2030 起為收斂法
A89: FY2027 | B89: =PL!E185 -> 43.612036 | C89: =PL!E197 -> 43.612036 | D89: =PL!E209 -> 43.612036
A90: FY2028 | B90: =PL!F185 -> 51.924533 | C90: =PL!F197 -> 41.964528 | D90: =PL!F209 -> 31.564499
A91: FY2029 | B91: =PL!G185 -> 56.034182 | C91: =PL!G197 -> 47.750553 | D91: =PL!G209 -> 34.137456
A92: FY2030 | B92: =PL!H185 -> 57.662389 | C92: =PL!H197 -> 48.636343 | D92: =PL!H209 -> 32.380207
A93: FY2031 | B93: =PL!I185 -> 60.23002 | C93: =PL!I197 -> 49.158628 | D93: =PL!I209 -> 30.612697
A94: FY2032 | B94: =PL!J185 -> 63.843821 | C94: =PL!J197 -> 49.299081 | D94: =PL!J209 -> 28.823032
A95: 股東現金流＝EPS ×（1 − tp_g ÷ tp_roe）
A96: 再投資率（tp_g ÷ tp_roe，上限 0.8） | B96: =MIN(tp_g/tp_roe,0.8) -> 0.14729348 | E96: ROE 為近三年平均（In 頁 tp_roe）
A97: FY2027 | B97: =B89*(1-$B$96) -> 37.188268 | C97: =C89*(1-$B$96) -> 37.188268 | D97: =D89*(1-$B$96) -> 37.188268
A98: FY2028 | B98: =B90*(1-$B$96) -> 44.276388 | C98: =C90*(1-$B$96) -> 35.783427 | D98: =D90*(1-$B$96) -> 26.915254
A99: FY2029 | B99: =B91*(1-$B$96) -> 47.780712 | C99: =C91*(1-$B$96) -> 40.717208 | D99: =D91*(1-$B$96) -> 29.109231
A100: FY2030 | B100: =B92*(1-$B$96) -> 49.169095 | C100: =C92*(1-$B$96) -> 41.472526 | D100: =D92*(1-$B$96) -> 27.610814
A101: FY2031 | B101: =B93*(1-$B$96) -> 51.358531 | C101: =C93*(1-$B$96) -> 41.917882 | D101: =D93*(1-$B$96) -> 26.103646
A102: FY2032 | B102: =B94*(1-$B$96) -> 54.440042 | C102: =C94*(1-$B$96) -> 42.037648 | D102: =D94*(1-$B$96) -> 24.577587
A103: DCF 情境每股價值（折現率 tp_r） | B103: =SUMPRODUCT(B97:B102,1/(1+tp_r)^{1;2;3;4;5;6})+B102*(1+tp_g)/(tp_r-tp_g)/(1+tp_r)^6 -> 735.15374 | C103: =SUMPRODUCT(C97:C102,1/(1+tp_r)^{1;2;3;4;5;6})+C102*(1+tp_g)/(tp_r-tp_g)/(1+tp_r)^6 -> 583.36057 | D103: =SUMPRODUCT(D97:D102,1/(1+tp_r)^{1;2;3;4;5;6})+D102*(1+tp_g)/(tp_r-tp_g)/(1+tp_r)^6 -> 367.33439 | E103: Σ 明確期現金流 ÷ (1＋r)^t ＋ 永續價值 ÷ (1＋r)^6；永續價值＝FY2032 現金流 ×(1＋g)÷(r−g)；基準日 2026 年底，t＝1 對 FY2027
A104: DCF 情境價值推到 12 個月後（×(1＋tp_r)） | B104: =B103*(1+tp_r) -> 808.66912 | C104: =C103*(1+tp_r) -> 641.69663 | D104: =D103*(1+tp_r) -> 404.06783
A105: DCF 目標價（情境加權） | B105: =tp_wA*B104+tp_wB*C104+tp_wC*D104 -> 644.26261 | E105: Σ tp_wA／wB／wC × 情境價值 ×(1＋tp_r)；權重見 In 頁
A107: 0.2 Comparable（市場主流同業前瞻 P/E）
A108: 同業與前瞻 P/E | B108: 代號 | C108: 前瞻 12 月 P/E | D108: 日期 | E108: 來源 | F108: 標記
A109: 緯創（Wistron） | B109: 3231.TW | C109: 9.93 | D109: 2026-09-29 | E109: stockanalysis.com 個股頁 Forward PE（分析師共識；價格日期如左） | F109: Interested-party（賣方共識）
A110: 緯穎（Wiwynn） | B110: 6669.TW | C110: 13.87 | D110: 2026-10-02 | E110: stockanalysis.com 個股頁 Forward PE（分析師共識；價格日期如左） | F110: Interested-party（賣方共識）
A111: 鴻海（Hon Hai） | B111: 2317.TW | C111: 11.37 | D111: 2026-10-19 | E111: stockanalysis.com 個股頁 Forward PE（分析師共識；價格日期如左） | F111: Interested-party（賣方共識）
A112: 英業達（Inventec） | B112: 2356.TW | C112: 18 | D112: 2026-08-14 | E112: stockanalysis.com 個股頁 Forward PE（分析師共識；價格日期如左） | F112: Interested-party（賣方共識）
...

Sheet Recon
A1: Recon — 本模型 vs 券商估計與櫃數份額。只作事後對照，不為對上數字而調參數。券商多未具名或單一來源；2027 共識（付費）未找到
A3: 項目 | B3: 對照值 | C3: 模型 A | D3: 差距 A | E3: 模型 B | F3: 差距 B | G3: 模型 C | H3: 差距 C | I3: 對照來源 | J3: 說明
A4: A. 券商估計（校準未使用）
A5: FY2026 營收 vs 凱基（08-13，3Q 前） | B5: =b_rev26 -> 4219.196 | C5: =PL!D77 -> 3998.715 | D5: =C5/B5-1 -> -0.052256638 | E5: =PL!D116 -> 3998.715 | F5: =E5/B5-1 -> -0.052256638 | G5: =PL!D155 -> 3998.715 | H5: =G5/B5-1 -> -0.052256638 | I5: 凱基 2026-08-13 | J5: 3Q 只達法人預期 92%
A6: FY2026 EPS vs 凱基 | B6: =b_eps26 -> 27.06 | C6: =PL!D95 -> 28.722467 | D6: =C6/B6-1 -> 0.061436341 | E6: =PL!D134 -> 28.722467 | F6: =E6/B6-1 -> 0.061436341 | G6: =PL!D173 -> 28.722467 | H6: =G6/B6-1 -> 0.061436341 | I6: 凱基 2026-08-13
A7: FY2027 營收 vs 凱基 | B7: =b_rev27a -> 5220.407 | C7: =PL!E77 -> 5710.509 | D7: =C7/B7-1 -> 0.093881945 | E7: =PL!E116 -> 5710.509 | F7: =E7/B7-1 -> 0.093881945 | G7: =PL!E155 -> 5710.509 | H7: =G7/B7-1 -> 0.093881945 | I7: 凱基 2026-08-13
A8: FY2027 營收 vs 法人（10-08） | B8: =b_rev27b -> 5300 | C8: =PL!E77 -> 5710.509 | D8: =C8/B8-1 -> 0.077454521 | E8: =PL!E116 -> 5710.509 | F8: =E8/B8-1 -> 0.077454521 | G8: =PL!E155 -> 5710.509 | H8: =G8/B8-1 -> 0.077454521 | I8: 工商時報 2026-10-08
A9: FY2027 EPS vs 凱基 | B9: =b_eps27a -> 31.75 | C9: =PL!E95 -> 43.612036 | D9: =C9/B9-1 -> 0.37360744 | E9: =PL!E134 -> 43.612036 | F9: =E9/B9-1 -> 0.37360744 | G9: =PL!E173 -> 43.612036 | H9: =G9/B9-1 -> 0.37360744 | I9: 凱基 2026-08-13
A10: FY2027 EPS vs 法人（10-08） | B10: =b_eps27b -> 32.09 | C10: =PL!E95 -> 43.612036 | D10: =C10/B10-1 -> 0.35905379 | E10: =PL!E134 -> 43.612036 | F10: =E10/B10-1 -> 0.35905379 | G10: =PL!E173 -> 43.612036 | H10: =G10/B10-1 -> 0.35905379 | I10: 工商時報 2026-10-08 | J10: 兩家區間 31.75–32.09
A11: FY2027 毛利率 vs 凱基（百分點） | B11: =b_gm27 -> 0.047 | C11: =PL!E86 -> 0.048633639 | D11: =C11-B11 -> 0.0016336385 | E11: =PL!E125 -> 0.048633639 | F11: =E11-B11 -> 0.0016336385 | G11: =PL!E164 -> 0.048633639 | H11: =G11-B11 -> 0.0016336385 | I11: 凱基 2026-08-13 | J11: 模型含客供 10%，毛利率較高
A12: FY2027 營收年增（模型） | C12: =PL!E78 -> 0.42808601 | E12: =PL!E117 -> 0.42808601 | G12: =PL!E156 -> 0.42808601 | I12: —
A13: B. 份額與每 GW（先驗比對的機制檢查）
A14: FY2026 有效份額 vs 三家 ODM 中的 NVL72 櫃數份額 | B14: =rk_sh -> 0.33779264 | C14: =PL!D69 -> 0.13389612 | D14: =C14-B14 -> -0.20389652 | E14: =PL!D108 -> 0.13389612 | F14: =E14-B14 -> -0.20389652 | G14: =PL!D147 -> 0.13389612 | H14: =G14-B14 -> -0.20389652 | I14: 經濟日報 2026-09-10（美系券商） | J14: 口徑不同：本模型分母為全部 AI 組裝市場（含 ASIC、HGX、其他廠）
A15: FY2026 每 GW 廣達 AI 伺服器營收（US$B） | C15: =PL!D80 -> 3.6313834 | E15: =PL!D119 -> 3.6313834 | G15: =PL!D158 -> 3.6313834 | I15: — | J15: 先驗比對推導約 3.4–4.2
A16: FY2026 隱含廣達出貨櫃數（千櫃，NVL72 等值） | C16: =PL!D81 -> 18.452268 | E16: =PL!D120 -> 18.452268 | G16: =PL!D159 -> 18.452268 | I16: — | J16: 三家調查單月約 2.5 千櫃 × 12 ≈ 30 千櫃（Interested-party；含運算托盤口徑不明）
A17: FY2027 AI 伺服器 ÷ 營收 | C17: =PL!E79 -> 0.76920158 | E17: =PL!E118 -> 0.76920158 | G17: =PL!E157 -> 0.76920158 | I17: —
A18: C. 校準
A19: 其他營收毛利率（Derived） | C19: =PL!D83 -> 0.063230721 | E19: =PL!D122 -> 0.063230721 | G19: =PL!D161 -> 0.063230721 | I19: FY2026 錨點 | J19: AI 毛利率（毛額基礎）＝此值＋d_ai
A20: FY2027 毛利率 vs FY2026（百分點） | B20: =a26_gp/a26_rev -> 0.049630721 | C20: =PL!E86 -> 0.048633639 | D20: =C20-B20 -> -0.00099708284 | E20: =PL!E125 -> 0.048633639 | F20: =E20-B20 -> -0.00099708284 | G20: =PL!E164 -> 0.048633639 | H20: =G20-B20 -> -0.00099708284 | I20: 錨點 | J20: 客供使毛利率上升
A21: 4Q26 EPS（模型） | C21: =Q!E13 -> 7.6098418 | E21: =Q!E13 -> 7.6098418 | G21: =Q!E13 -> 7.6098418 | I21: —
A22: D. 預留
A23: R4 產業部署路徑（markets/deploy_path/，尚未建立）：上線後以部署路徑取代「AI IT 資本支出 ÷ 每 GW IT 資本支出」 | J23: 預留列：本版無數值
A25: E. 目標價對帳（v0.2；模型欄為情境加權值，非情境 A）
A26: 12 個月後的前瞻 EPS（情境加權）vs 共識前瞻 EPS | B26: =cons_feps -> 28.558798 | C26: =Val!B115 -> 42.995776 | D26: =C26/B26-1 -> 0.50551772 | I26: stockanalysis 個股頁 2026-10-14：價格 323 ÷ Forward PE 11.31 | J26: 共識只作對帳，不作校準
A27: 目標價（DCF 與 Comparable 加權）vs 市場共識目標價 | B27: =cons_tp -> 427.84 | C27: =Val!B120 -> 566.56229 | D27: =C27/B27-1 -> 0.32423872 | I27: stockanalysis 個股頁（S&P Global）19 位分析師平均 427.84，頁面時間 2026-10-14 | J27: 共識只作對帳，不作校準
A28: Comparable 目標價 vs 市場共識目標價 | B28: =cons_tp -> 427.84 | C28: =Val!B116 -> 488.86197 | D28: =C28/B28-1 -> 0.14262802 | I28: 同上 | J28: 共識只作對帳，不作校準

Sheet Sens
A1: Sens — 一次動一個輸入（情境 A；有效份額、其他營收毛利率在每個案例內依 FY2026 錨點重算，FY2026 恆等於錨點）：對 FY2027、FY2028 的營收、AI 伺服器營收、毛利率與 EPS 的影響。每個案例是一個完整推導區塊（本頁下方）
A3: 案例 | B3: 設定 | C3: FY2027 營收 | D3: FY2027 AI 伺服器營收 | E3: FY2027 毛利率 | F3: FY2027 EPS | G3: FY2027 EPS 相對基準 | H3: FY2028 營收 | I3: FY2028 AI 伺服器營收 | J3: FY2028 毛利率 | K3: FY2028 EPS | L3: FY2028 EPS 相對基準
A4: 基準（情境 A） | B4: PL 區塊 A | C4: =PL!E77 -> 5710.509 | D4: =PL!E74 -> 4392.5325 | E4: =PL!E86 -> 0.048633639 | F4: =PL!E95 -> 43.612036 | G4: =F4/F$4-1 -> 0 | H4: =PL!F77 -> 6046.243 | I4: =PL!F74 -> 4701.907 | J4: =PL!F86 -> 0.052383885 | K4: =PL!F95 -> 51.924533 | L4: =K4/K$4-1 -> 0
A5: 份額流失（低） | B5: 份額相對值 2027 0.85、2028 0.75、2029 0.70（鴻海、緯創搶單） | C5: =E57 -> 5051.6291 | D5: =E54 -> 3733.6526 | E5: =E66 -> 0.049204898 | F5: =E75 -> 38.121714 | G5: =F5/F$4-1 -> -0.12589007 | H5: =F57 -> 5056.3679 | I5: =F54 -> 3712.0319 | J5: =F66 -> 0.05299101 | K5: =F75 -> 42.463458 | L5: =K5/K$4-1 -> -0.18220819
A6: 份額上升（高） | B6: 份額相對值 1.1（Neocloud、ASIC 專案） | C6: =E96 -> 6149.7622 | D6: =E93 -> 4831.7857 | E6: =E105 -> 0.048320803 | F6: =E114 -> 47.272251 | G6: =F6/F$4-1 -> 0.083926712 | H6: =F96 -> 6788.6494 | I6: =F93 -> 5444.3134 | J6: =F105 -> 0.052044732 | K6: =F114 -> 59.066448 | L6: =K6/K$4-1 -> 0.13754414
A7: 客供 0（維持買賣） | B7: 客供比例 2027–29 皆 0 | C7: =E135 -> 6198.5681 | D7: =E132 -> 4880.5917 | E7: =E144 -> 0.045121118 | F7: =E153 -> 43.272714 | G7: =F7/F$4-1 -> -0.0077804648 | H7: =F135 -> 7221.7198 | I7: =F132 -> 5877.3838 | J7: =F144 -> 0.044512212 | K7: =F153 -> 51.358953 | L7: =K7/K$4-1 -> -0.01089234
A8: 客供 高 | B8: 客供比例 25%／40%／50% | C8: =E174 -> 4978.4202 | D8: =E171 -> 3660.4437 | E8: =E183 -> 0.05519373 | F8: =E192 -> 44.121019 | G8: =F8/F$4-1 -> 0.011670697 | H8: =F174 -> 4870.7663 | I8: =F171 -> 3526.4303 | J8: =F183 -> 0.064054946 | K8: =F192 -> 52.473246 | L8: =K8/K$4-1 -> 0.010567516
A9: 客供保留毛利 0.7 | B9: 客供部分只保留 70% 毛利 | C9: =E213 -> 5710.509 | D9: =E210 -> 4392.5325 | E9: =E222 -> 0.04794596 | F9: =E231 -> 42.730791 | G9: =F9/F$4-1 -> -0.020206473 | H9: =F213 -> 6046.243 | I9: =F210 -> 4701.907 | J9: =F222 -> 0.050819598 | K9: =F231 -> 49.802078 | L9: =K9/K$4-1 -> -0.040875762
A10: 客供保留毛利 1.0 | B10: 毛利金額完全保留 | C10: =E252 -> 5710.509 | D10: =E249 -> 4392.5325 | E10: =E261 -> 0.048977478 | F10: =E270 -> 44.052659 | G10: =F10/F$4-1 -> 0.010103237 | H10: =F252 -> 6046.243 | I10: =F249 -> 4701.907 | J10: =F261 -> 0.053166028 | K10: =F270 -> 52.98576 | L10: =K10/K$4-1 -> 0.020437881
A11: 每 GW 價值 低 | B11: 2028–29 每 GW ODM 價值 ×0.85（Rubin Ultra 降價或客供更深） | C11: =E291 -> 5710.509 | D11: =E288 -> 4392.5325 | E11: =E300 -> 0.048633639 | F11: =E309 -> 43.612036 | G11: =F11/F$4-1 -> 0 | H11: =F291 -> 5340.957 | I11: =F288 -> 3996.621 | J11: =F300 -> 0.052793412 | K11: =F309 -> 44.564535 | L11: =K11/K$4-1 -> -0.14174413
A12: 每 GW 價值 高 | B12: ×1.2 | C12: =E330 -> 5710.509 | D12: =E327 -> 4392.5325 | E12: =E339 -> 0.048633639 | F12: =E348 -> 43.612036 | G12: =F12/F$4-1 -> 0 | H12: =F330 -> 6986.6244 | I12: =F327 -> 5642.2884 | J12: =F339 -> 0.051966464 | K12: =F348 -> 61.092068 | L12: =K12/K$4-1 -> 0.17655498
A13: AI 部署 ×0.8 | B13: FY2027 起 AI IT 資本支出 ×0.8 | C13: =E369 -> 4832.0025 | D13: =E366 -> 3514.026 | E13: =E378 -> 0.049429938 | F13: =E387 -> 36.291607 | G13: =F13/F$4-1 -> -0.16785342 | H13: =F369 -> 5105.8616 | I13: =F366 -> 3761.5256 | J13: =F378 -> 0.052955063 | K13: =F387 -> 42.97607 | L13: =K13/K$4-1 -> -0.17233594
A14: AI 部署 ×1.2 | B14: ×1.2 | C14: =E408 -> 6589.0155 | D14: =E405 -> 5271.039 | E14: =E417 -> 0.048049678 | F14: =E426 -> 50.932466 | G14: =F14/F$4-1 -> 0.16785342 | H14: =F408 -> 6986.6244 | I14: =F405 -> 5642.2884 | J14: =F417 -> 0.051966464 | K14: =F426 -> 60.87516 | L14: =K14/K$4-1 -> 0.1723776
A15: 非 AI 成長 低 | B15: 2027–29 −5% | C15: =E447 -> 5608.1419 | D15: =E444 -> 4392.5325 | E15: =E456 -> 0.048367194 | F15: =E465 -> 42.323094 | G15: =F15/F$4-1 -> -0.029554732 | H15: =F447 -> 5856.7359 | I15: =F444 -> 4701.907 | J15: =F456 -> 0.052032912 | K15: =F465 -> 49.510287 | L15: =K15/K$4-1 -> -0.046495295
A16: 非 AI 成長 高 | B16: 2027 +8%、2028–29 +6% | C16: =E486 -> 5774.4884 | D16: =E483 -> 4392.5325 | E16: =E495 -> 0.048795369 | F16: =E504 -> 44.417625 | G16: =F16/F$4-1 -> 0.018471707 | H16: =F486 -> 6166.7803 | I16: =F483 -> 4701.907 | J16: =F495 -> 0.052595899 | K16: =F504 -> 53.461436 | L16: =K16/K$4-1 -> 0.029598792
A17: AI 毛利率差距 −3.5pt | B17: AI 毛利率（毛額基礎）比其他低 3.5 個百分點 | C17: =E525 -> 5710.509 | D17: =E522 -> 4392.5325 | E17: =E534 -> 0.046926398 | F17: =E543 -> 41.424244 | G17: =F17/F$4-1 -> -0.050164875 | H17: =F525 -> 6046.243 | I17: =F522 -> 4701.907 | J17: =F534 -> 0.05007915 | K17: =F543 -> 48.797423 | L17: =K17/K$4-1 -> -0.060224131
A18: AI 毛利率差距 −0.5pt | B18: 只低 0.5 個百分點 | C18: =E564 -> 5710.509 | D18: =E561 -> 4392.5325 | E18: =E573 -> 0.050340879 | F18: =E582 -> 45.799829 | G18: =F18/F$4-1 -> 0.050164875 | H18: =F564 -> 6046.243 | I18: =F561 -> 4701.907 | J18: =F573 -> 0.054688619 | K18: =F582 -> 55.051643 | L18: =K18/K$4-1 -> 0.060224131
A19: VR 稀釋 −0.6pt | B19: FY2027 起 AI 毛利率（毛額基礎）−0.6 個百分點 | C19: =E603 -> 5710.509 | D19: =E600 -> 4392.5325 | E19: =E612 -> 0.046095273 | F19: =E621 -> 40.359175 | G19: =F19/F$4-1 -> -0.074586316 | H19: =F603 -> 6046.243 | I19: =F600 -> 4701.907 | J19: =F612 -> 0.049525993 | K19: =F621 -> 48.046889 | L19: =K19/K$4-1 -> -0.074678465
A20: VR 不稀釋 | B20: FY2027 起不變 | C20: =E642 -> 5710.509 | D20: =E639 -> 4392.5325 | E20: =E651 -> 0.051172004 | F20: =E660 -> 46.864897 | G20: =F20/F$4-1 -> 0.074586316 | H20: =F642 -> 6046.243 | I20: =F639 -> 4701.907 | J20: =F651 -> 0.055241776 | K20: =F660 -> 55.802177 | L20: =K20/K$4-1 -> 0.074678465
A21: 營業費用率 +0.2pt | B21: 營業費用額外 +0.2% × 營收 | C21: =E681 -> 5710.509 | D21: =E678 -> 4392.5325 | E21: =E690 -> 0.048633639 | F21: =E699 -> 41.049079 | G21: =F21/F$4-1 -> -0.058767207 | H21: =F681 -> 6046.243 | I21: =F678 -> 4701.907 | J21: =F690 -> 0.052383885 | K21: =F699 -> 49.210893 | L21: =K21/K$4-1 -> -0.052261226
A22: 淨利 ÷ 營業利益 0.75 | B22: FY2027 起 0.75（券商隱含約 0.73–0.77） | C22: =E720 -> 5710.509 | D22: =E717 -> 4392.5325 | E22: =E729 -> 0.048633639 | F22: =E738 -> 37.813904 | G22: =F22/F$4-1 -> -0.13294798 | H22: =F720 -> 6046.243 | I22: =F717 -> 4701.907 | J22: =F729 -> 0.052383885 | K22: =F738 -> 45.021271 | L22: =K22/K$4-1 -> -0.13294798
A23: 顆數情境 B | B23: CY2028 ×0.8、CY2029 ×0.85 | C23: =PL!E116 -> 5710.509 | D23: =PL!E113 -> 4392.5325 | E23: =PL!E125 -> 0.048633639 | F23: =PL!E134 -> 43.612036 | G23: =F23/F$4-1 -> 0 | H23: =PL!F116 -> 5105.8616 | I23: =PL!F113 -> 3761.5256 | J23: =PL!F125 -> 0.052955063 | K23: =PL!F134 -> 41.964528 | L23: =K23/K$4-1 -> -0.19181694
A24: 顆數情境 C | B24: CY2028–29 ×0.6 | C24: =PL!E155 -> 5710.509 | D24: =PL!E152 -> 4392.5325 | E24: =PL!E164 -> 0.048633639 | F24: =PL!E173 -> 43.612036 | G24: =F24/F$4-1 -> 0 | H24: =PL!F155 -> 4165.4802 | I24: =PL!F152 -> 2821.1442 | J24: =PL!F164 -> 0.053784135 | K24: =PL!F173 -> 31.564499 | L24: =K24/K$4-1 -> -0.39210817
A26: 讀法：FY2027 三情境相同；顆數情境 B、C 的差異從 FY2028 起。每個案例的 FY2026 有效份額與其他營收毛利率依該案例重算，所以 FY2026 恆等於錨點。「客供」案例同時改變營收與毛利率，EPS 只受保留毛利比例影響：客供比例高、保留比例低時 EPS 才明顯下降。
A40: 案例區塊：份額流失（低）（情境 A）
A41: 項目 | B41: 單位 | C41: FY2025A | D41: FY2026（錨點） | E41: FY2027 | F41: FY2028 | G41: FY2029 | H41: 說明
A42: A. AI 部署與整櫃組裝市場（D 欄＝FY2026 校準年；E–G＝FY2027–FY2029）
A43: AI IT 資本支出 × 情境顆數係數 | B43: US$B | D43: =itc_26*1 -> 781.87292 | E43: =itc_27*1*1 -> 1565.35 | F43: =itc_28*um28_A*1 -> 1984.2639 | G43: =itc_29*um29_A*1 -> 2260.3903
A44: 每 GW IT 資本支出 | B44: US$B | D44: =itpg_gb*(1-vr26)+itpg_vr*vr26 -> 33.414032 | E44: =itpg_vr -> 37.586352 | F44: =itpg_vr -> 37.586352 | G44: =itpg_vr -> 37.586352
A45: 部署 GW（IT 電力） | B45: GW | D45: =D43/D44 -> 23.399538 | E45: =E43/E44 -> 41.646766 | F45: =F43/F44 -> 52.792138 | G45: =G43/G44 -> 60.138592
A46: 每 GW ODM 整櫃價值 | B46: US$B/GW | D46: =(racks_gb*odm_gb*(1-vr26)+racks_vr*odm_vr*vr26)/1000 -> 27.1209 | E46: =racks_vr*odm_vr/1000 -> 27.351 | F46: =$E46*vpg_28 -> 27.351 | G46: =$E46*vpg_29 -> 27.351 | H46: 架數 × ODM 每櫃價格；含 ASIC 機架（Assumed：每 GW 價值相同）
A47: AI 伺服器組裝市場（ODM 價，美元） | B47: US$B | D47: =D45*D46 -> 634.61653 | E47: =E45*E46 -> 1139.0807 | F47: =F45*F46 -> 1443.9178 | G47: =G45*G46 -> 1644.8506
A48: AI 伺服器組裝市場（新台幣） | B48: NT$B | D48: =D47*fx -> 20307.729 | E48: =E47*fx -> 36450.582 | F48: =F47*fx -> 46205.369 | G48: =G47*fx -> 52635.22
A49: 廣達有效份額（FY2026 校準）＝ AI 伺服器營收 ÷ 市場 | B49: % | D49: =a26_ai/D48 -> 0.13389612 | H49: Derived：分子為公司伺服器占比 × AI 占比 × 營收；分母含 ASIC、HGX 機架，所以低於整櫃櫃數份額
A50: 份額相對值（÷ FY2026） | B50: x | D50: =1 -> 1 | E50: =RLO_27 -> 0.85 | F50: =RLO_28 -> 0.75 | G50: =RLO_29 -> 0.7
A51: 廣達有效份額 | B51: % | D51: =$D$49*D50 -> 0.13389612 | E51: =$D$49*E50 -> 0.11381171 | F51: =$D$49*F50 -> 0.10042209 | G51: =$D$49*G50 -> 0.093727287
A52: AI 伺服器毛額價值（買賣模式下的營收） | B52: NT$B | D52: =D48*D51 -> 2719.1262 | E52: =E48*E51 -> 4148.5029 | F52: =F48*F51 -> 4640.0398 | G52: =G48*G51 -> 4933.3564
A53: 客供比例 | B53: % | D53: =0 -> 0 | E53: =cs_27 -> 0.1 | F53: =cs_28 -> 0.2 | G53: =cs_29 -> 0.25 | H53: FY2026 的少量客供已含在錨點與校準份額內，記為 0
A54: AI 伺服器營收 | B54: NT$B | C54: =a25_ai -> 905.033 | D54: =D52*(1-D53) -> 2719.1262 | E54: =E52*(1-E53) -> 3733.6526 | F54: =F52*(1-F53) -> 3712.0319 | G54: =G52*(1-G53) -> 3700.0173
A55: B. 非 AI 與合計
A56: 非 AI 營收（一般伺服器、筆電、其他） | B56: NT$B | C56: =a25_nai -> 1218.656 | D56: =a26_nai -> 1279.5888 | E56: =D56*(1+g_nai27) -> 1317.9765 | F56: =E56*(1+g_nai28) -> 1344.336 | G56: =F56*(1+g_nai29) -> 1371.2227
A57: 營收 | B57: NT$B | C57: =C54+C56 -> 2123.689 | D57: =D54+D56 -> 3998.715 | E57: =E54+E56 -> 5051.6291 | F57: =F54+F56 -> 5056.3679 | G57: =G54+G56 -> 5071.24
A58: 營收年增 | B58: % | D58: =D57/C57-1 -> 0.88290988 | E58: =E57/D57-1 -> 0.26331311 | F58: =F57/E57-1 -> 0.0009380676 | G58: =G57/F57-1 -> 0.0029412653
A59: AI 伺服器 ÷ 營收 | B59: % | C59: =C54/C57 -> 0.4261608 | D59: =D54/D57 -> 0.68 | E59: =E54/E57 -> 0.73909873 | F59: =F54/F57 -> 0.7341301 | G59: =G54/G57 -> 0.729608
A60: 每 GW 廣達 AI 伺服器營收 | B60: US$B/GW | D60: =D54/fx/D45 -> 3.6313834 | E60: =E54/fx/E45 -> 2.8015776 | F60: =F54/fx/F45 -> 2.1973157 | G60: =G54/fx/G45 -> 1.9226513
A61: 隱含廣達出貨櫃數（毛額價值 ÷ ODM 每櫃價格；NVL72 等值） | B61: 千櫃 | D61: =D52/fx/(odm_gb*(1-vr26)+odm_vr*vr26) -> 18.452268 | E61: =E52/fx/odm_vr -> 19.206032 | F61: =F52/fx/odm_vr -> 21.481666 | G61: =G52/fx/odm_vr -> 22.839613 | H61: 十億美元 ÷ 百萬美元 ＝ 千櫃；FY2028 起若每 GW 價值改變，每櫃價格仍以 VR200 換算（參考）
A62: C. 損益
A63: 其他營收毛利率 ＝ 錨點毛利率 − 差距 × AI 占比（FY2026 校準） | B63: % | D63: =a26_gp/D57-d_ai*D59 -> 0.063230721 | H63: Derived：讓 FY2026 毛利率等於錨點；AI 毛利率（毛額基礎）＝其他 + 差距（差距為負）
A64: AI 伺服器毛利 ＝ AI 毛利率 × 毛額價值 ×（1 − 客供 ×（1 − 保留比例）） | B64: NT$B | D64: =($D$63+d_ai)*D52*(1-D53*(1-keep)) -> 117.54979 | E64: =($D$63+d_ai+vrd)*E52*(1-E53*(1-keep)) -> 165.22829 | F64: =($D$63+d_ai+vrd)*F52*(1-F53*(1-keep)) -> 182.93871 | G64: =($D$63+d_ai+vrd)*G52*(1-G53*(1-keep)) -> 193.51067 | H64: 客供部分不計營收，但大部分毛利金額保留（keep）；FY2027 起加 VR 稀釋 vrd
A65: 毛利 | B65: NT$B | C65: =a25_gp -> 148.23349 | D65: =a26_gp -> 198.45911 | E65: =$D$63*E56+E64 -> 248.56489 | F65: =$D$63*F56+F64 -> 267.94204 | G65: =$D$63*G56+G64 -> 280.21407
A66: 毛利率 | B66: % | C66: =C65/C57 -> 0.0698 | D66: =D65/D57 -> 0.049630721 | E66: =E65/E57 -> 0.049204898 | F66: =F65/F57 -> 0.05299101 | G66: =G65/G57 -> 0.055255534
A67: AI 伺服器毛利率（營收基礎） | B67: % | D67: =D64/D54 -> 0.043230721 | E67: =E64/E54 -> 0.044253794 | F67: =F64/F54 -> 0.049282634 | G67: =G64/G54 -> 0.052299938 | H67: 客供比例上升 → 營收基礎毛利率上升
A68: 營業費用（基準路徑） | B68: NT$B | C68: =a25_opx -> 60.737505 | D68: =a26_opx -> 71.189373 | E68: =D68*(1+MAX(0,phi*E58)) -> 78.687411 | F68: =E68*(1+MAX(0,phi*F58)) -> 78.716936 | G68: =F68*(1+MAX(0,phi*G58)) -> 78.809547
A69: 營業費用 | B69: NT$B | C69: =C68 -> 60.737505 | D69: =D68 -> 71.189373 | E69: =E68+0*E57 -> 78.687411 | F69: =F68+0*F57 -> 78.716936 | G69: =G68+0*G57 -> 78.809547
A70: 營業利益 | B70: NT$B | C70: =C65-C69 -> 87.495987 | D70: =D65-D69 -> 127.26974 | E70: =E65-E69 -> 169.87748 | F70: =F65-F69 -> 189.22511 | G70: =G65-G69 -> 201.40453
A71: 營業利益率 | B71: % | C71: =C70/C57 -> 0.0412 | D71: =D70/D57 -> 0.031827659 | E71: =E70/E57 -> 0.033628258 | F71: =F70/F57 -> 0.037423129 | G71: =G70/G57 -> 0.039715046
A72: 淨利 ÷ 營業利益 | B72: % | C72: =a25_ni/a25_oi -> 0.85695359 | D72: =a26_ni/a26_oi -> 0.86991357 | E72: =nio_f -> 0.865 | F72: =nio_f -> 0.865 | G72: =nio_f -> 0.865
A73: 歸屬母公司淨利 | B73: NT$B | C73: =a25_ni -> 74.98 | D73: =a26_ni -> 110.71367 | E73: =E70*E72 -> 146.94402 | F73: =F70*F72 -> 163.67972 | G73: =G70*G72 -> 174.21492
A74: 股數 | B74: 十億股 | C74: =a25_sh -> 3.8550129 | D74: =a26_sh -> 3.8546017 | E74: =D74*(1+sh_g) -> 3.8546017 | F74: =E74*(1+sh_g) -> 3.8546017 | G74: =F74*(1+sh_g) -> 3.8546017
A75: EPS | B75: NT$ | C75: =C73/C74 -> 19.45 | D75: =D73/D74 -> 28.722467 | E75: =E73/E74 -> 38.121714 | F75: =F73/F74 -> 42.463458 | G75: =G73/G74 -> 45.196606
A76: EPS 年增 | B76: % | D76: =D75/C75-1 -> 0.47673354 | E76: =E75/D75-1 -> 0.32724371 | F76: =F75/E75-1 -> 0.11389161 | G76: =G75/F75-1 -> 0.064364725
A79: 案例區塊：份額上升（高）（情境 A）
A80: 項目 | B80: 單位 | C80: FY2025A | D80: FY2026（錨點） | E80: FY2027 | F80: FY2028 | G80: FY2029 | H80: 說明
A81: A. AI 部署與整櫃組裝市場（D 欄＝FY2026 校準年；E–G＝FY2027–FY2029）
A82: AI IT 資本支出 × 情境顆數係數 | B82: US$B | D82: =itc_26*1 -> 781.87292 | E82: =itc_27*1*1 -> 1565.35 | F82: =itc_28*um28_A*1 -> 1984.2639 | G82: =itc_29*um29_A*1 -> 2260.3903
A83: 每 GW IT 資本支出 | B83: US$B | D83: =itpg_gb*(1-vr26)+itpg_vr*vr26 -> 33.414032 | E83: =itpg_vr -> 37.586352 | F83: =itpg_vr -> 37.586352 | G83: =itpg_vr -> 37.586352
A84: 部署 GW（IT 電力） | B84: GW | D84: =D82/D83 -> 23.399538 | E84: =E82/E83 -> 41.646766 | F84: =F82/F83 -> 52.792138 | G84: =G82/G83 -> 60.138592
A85: 每 GW ODM 整櫃價值 | B85: US$B/GW | D85: =(racks_gb*odm_gb*(1-vr26)+racks_vr*odm_vr*vr26)/1000 -> 27.1209 | E85: =racks_vr*odm_vr/1000 -> 27.351 | F85: =$E85*vpg_28 -> 27.351 | G85: =$E85*vpg_29 -> 27.351 | H85: 架數 × ODM 每櫃價格；含 ASIC 機架（Assumed：每 GW 價值相同）
A86: AI 伺服器組裝市場（ODM 價，美元） | B86: US$B | D86: =D84*D85 -> 634.61653 | E86: =E84*E85 -> 1139.0807 | F86: =F84*F85 -> 1443.9178 | G86: =G84*G85 -> 1644.8506
A87: AI 伺服器組裝市場（新台幣） | B87: NT$B | D87: =D86*fx -> 20307.729 | E87: =E86*fx -> 36450.582 | F87: =F86*fx -> 46205.369 | G87: =G86*fx -> 52635.22
A88: 廣達有效份額（FY2026 校準）＝ AI 伺服器營收 ÷ 市場 | B88: % | D88: =a26_ai/D87 -> 0.13389612 | H88: Derived：分子為公司伺服器占比 × AI 占比 × 營收；分母含 ASIC、HGX 機架，所以低於整櫃櫃數份額
A89: 份額相對值（÷ FY2026） | B89: x | D89: =1 -> 1 | E89: =RHI_27 -> 1.1 | F89: =RHI_28 -> 1.1 | G89: =RHI_29 -> 1.1
A90: 廣達有效份額 | B90: % | D90: =$D$88*D89 -> 0.13389612 | E90: =$D$88*E89 -> 0.14728574 | F90: =$D$88*F89 -> 0.14728574 | G90: =$D$88*G89 -> 0.14728574
A91: AI 伺服器毛額價值（買賣模式下的營收） | B91: NT$B | D91: =D87*D90 -> 2719.1262 | E91: =E87*E90 -> 5368.6508 | F91: =F87*F90 -> 6805.3918 | G91: =G87*G90 -> 7752.4171
A92: 客供比例 | B92: % | D92: =0 -> 0 | E92: =cs_27 -> 0.1 | F92: =cs_28 -> 0.2 | G92: =cs_29 -> 0.25 | H92: FY2026 的少量客供已含在錨點與校準份額內，記為 0
A93: AI 伺服器營收 | B93: NT$B | C93: =a25_ai -> 905.033 | D93: =D91*(1-D92) -> 2719.1262 | E93: =E91*(1-E92) -> 4831.7857 | F93: =F91*(1-F92) -> 5444.3134 | G93: =G91*(1-G92) -> 5814.3128
A94: B. 非 AI 與合計
A95: 非 AI 營收（一般伺服器、筆電、其他） | B95: NT$B | C95: =a25_nai -> 1218.656 | D95: =a26_nai -> 1279.5888 | E95: =D95*(1+g_nai27) -> 1317.9765 | F95: =E95*(1+g_nai28) -> 1344.336 | G95: =F95*(1+g_nai29) -> 1371.2227
A96: 營收 | B96: NT$B | C96: =C93+C95 -> 2123.689 | D96: =D93+D95 -> 3998.715 | E96: =E93+E95 -> 6149.7622 | F96: =F93+F95 -> 6788.6494 | G96: =G93+G95 -> 7185.5356
A97: 營收年增 | B97: % | D97: =D96/C96-1 -> 0.88290988 | E97: =E96/D96-1 -> 0.53793461 | F97: =F96/E96-1 -> 0.10388811 | G97: =G96/F96-1 -> 0.058463199
A98: AI 伺服器 ÷ 營收 | B98: % | C98: =C93/C96 -> 0.4261608 | D98: =D93/D96 -> 0.68 | E98: =E93/E96 -> 0.7856866 | F98: =F93/F96 -> 0.80197298 | G98: =G93/G96 -> 0.80916903
A99: 每 GW 廣達 AI 伺服器營收 | B99: US$B/GW | D99: =D93/fx/D84 -> 3.6313834 | E99: =E93/fx/E84 -> 3.625571 | F99: =F93/fx/F84 -> 3.2227297 | G99: =G93/fx/G84 -> 3.0213091
A100: 隱含廣達出貨櫃數（毛額價值 ÷ ODM 每櫃價格；NVL72 等值） | B100: 千櫃 | D100: =D91/fx/(odm_gb*(1-vr26)+odm_vr*vr26) -> 18.452268 | E100: =E91/fx/odm_vr -> 24.854865 | F100: =F91/fx/odm_vr -> 31.506443 | G100: =G91/fx/odm_vr -> 35.89082 | H100: 十億美元 ÷ 百萬美元 ＝ 千櫃；FY2028 起若每 GW 價值改變，每櫃價格仍以 VR200 換算（參考）
A101: C. 損益
A102: 其他營收毛利率 ＝ 錨點毛利率 − 差距 × AI 占比（FY2026 校準） | B102: % | D102: =a26_gp/D96-d_ai*D98 -> 0.063230721 | H102: Derived：讓 FY2026 毛利率等於錨點；AI 毛利率（毛額基礎）＝其他 + 差距（差距為負）
A103: AI 伺服器毛利 ＝ AI 毛利率 × 毛額價值 ×（1 − 客供 ×（1 − 保留比例）） | B103: NT$B | D103: =($D$102+d_ai)*D91*(1-D92*(1-keep)) -> 117.54979 | E103: =($D$102+d_ai+vrd)*E91*(1-E92*(1-keep)) -> 213.82485 | F103: =($D$102+d_ai+vrd)*F91*(1-F92*(1-keep)) -> 268.3101 | G103: =($D$102+d_ai+vrd)*G91*(1-G92*(1-keep)) -> 304.0882 | H103: 客供部分不計營收，但大部分毛利金額保留（keep）；FY2027 起加 VR 稀釋 vrd
A104: 毛利 | B104: NT$B | C104: =a25_gp -> 148.23349 | D104: =a26_gp -> 198.45911 | E104: =$D$102*E95+E103 -> 297.16145 | F104: =$D$102*F95+F103 -> 353.31344 | G104: =$D$102*G95+G103 -> 390.7916
A105: 毛利率 | B105: % | C105: =C104/C96 -> 0.0698 | D105: =D104/D96 -> 0.049630721 | E105: =E104/E96 -> 0.048320803 | F105: =F104/F96 -> 0.052044732 | G105: =G104/G96 -> 0.05438587
A106: AI 伺服器毛利率（營收基礎） | B106: % | D106: =D103/D93 -> 0.043230721 | E106: =E103/E93 -> 0.044253794 | F106: =F103/F93 -> 0.049282634 | G106: =G103/G93 -> 0.052299938 | H106: 客供比例上升 → 營收基礎毛利率上升
A107: 營業費用（基準路徑） | B107: NT$B | C107: =a25_opx -> 60.737505 | D107: =a26_opx -> 71.189373 | E107: =D107*(1+MAX(0,phi*E97)) -> 86.507464 | F107: =E107*(1+MAX(0,phi*F97)) -> 90.102302 | G107: =F107*(1+MAX(0,phi*G97)) -> 92.20937
A108: 營業費用 | B108: NT$B | C108: =C107 -> 60.737505 | D108: =D107 -> 71.189373 | E108: =E107+0*E96 -> 86.507464 | F108: =F107+0*F96 -> 90.102302 | G108: =G107+0*G96 -> 92.20937
A109: 營業利益 | B109: NT$B | C109: =C104-C108 -> 87.495987 | D109: =D104-D108 -> 127.26974 | E109: =E104-E108 -> 210.65399 | F109: =F104-F108 -> 263.21114 | G109: =G104-G108 -> 298.58223
A110: 營業利益率 | B110: % | C110: =C109/C96 -> 0.0412 | D110: =D109/D96 -> 0.031827659 | E110: =E109/E96 -> 0.034254005 | F110: =F109/F96 -> 0.038772239 | G110: =G109/G96 -> 0.041553233
A111: 淨利 ÷ 營業利益 | B111: % | C111: =a25_ni/a25_oi -> 0.85695359 | D111: =a26_ni/a26_oi -> 0.86991357 | E111: =nio_f -> 0.865 | F111: =nio_f -> 0.865 | G111: =nio_f -> 0.865
A112: 歸屬母公司淨利 | B112: NT$B | C112: =a25_ni -> 74.98 | D112: =a26_ni -> 110.71367 | E112: =E109*E111 -> 182.2157 | F112: =F109*F111 -> 227.67763 | G112: =G109*G111 -> 258.27363
A113: 股數 | B113: 十億股 | C113: =a25_sh -> 3.8550129 | D113: =a26_sh -> 3.8546017 | E113: =D113*(1+sh_g) -> 3.8546017 | F113: =E113*(1+sh_g) -> 3.8546017 | G113: =F113*(1+sh_g) -> 3.8546017
A114: EPS | B114: NT$ | C114: =C112/C113 -> 19.45 | D114: =D112/D113 -> 28.722467 | E114: =E112/E113 -> 47.272251 | F114: =F112/F113 -> 59.066448 | G114: =G112/G113 -> 67.003973
A115: EPS 年增 | B115: % | D115: =D114/C114-1 -> 0.47673354 | E115: =E114/D114-1 -> 0.64582835 | F115: =F114/E114-1 -> 0.24949515 | G115: =G114/F114-1 -> 0.13438298
A118: 案例區塊：客供 0（維持買賣）（情境 A）
A119: 項目 | B119: 單位 | C119: FY2025A | D119: FY2026（錨點） | E119: FY2027 | F119: FY2028 | G119: FY2029 | H119: 說明
...

Sheet Sources
A1: 來源（公司原文只經法說摘要與新聞轉述，原始簡報待人工複核；券商與資料商皆為 Interested-party）
A2: 公司（摘要）：富果 2Q26 法說摘要 2026-08-13（1H26 損益、伺服器與 AI 占比、客供、產能、資本支出） | B2: https://blog.fugle.tw/post/earnings-call-2382-2026-08-13
A3: 公司（摘要）：優分析 2Q26 法說（AI 占伺服器 75–80%、全年約 80%、毛利率、能見度至 2028） | B3: https://uanalyze.com.tw/articles/5252953366
A4: 公司（摘要）：Taipei Times 2026-05-15（1Q26 毛利率 4.78%、客供轉換協商） | B4: https://www.taipeitimes.com/News/biz/archives/2026/05/15/2003857345
A5: 二手：優分析 2025 年財報（毛利率 6.98%、營益率 4.12%、淨利 749.8 億、EPS 19.45） | B5: https://uanalyze.com.tw/articles/3341848159
A6: 二手：財報狗 2026-10-08（3Q26 營收 1.1155 兆、前三季 2.9614 兆、VR 時程、筆電占比） | B6: https://statementdog.com/news/17848
A7: 券商：凱基 2026-08-13（2025A–2027F 營收、EPS、毛利率、營益率） | B7: https://www.kgi.com.hk/zh-cn/-/media/files/kgishk/research-reports/tw-reports/quanta-computer-2382-tt-20260813en.pdf
A8: 券商：工商時報 2026-10-08（法人 2027 營收 5.3 兆、EPS 32.09、GB300 與 VR 每櫃價格） | B8: https://www.ctee.com.tw/news/20261008700747-430201
A9: 券商：FTNN 2026-10-09（同上；Neocloud 繞過 OEM） | B9: https://www.ftnn.com.tw/news/585951
A10: 券商：經濟日報 2026-09-10（美系券商 NVL72 櫃數調查） | B10: https://money.udn.com/money/amp/story/5607/9745501
A11: 資料商：Yahoo 股市（10-22 收盤、近 12 月 P/E） | B11: https://tw.stock.yahoo.com/quote/2382.TW
A12: 資料商：companiesmarketcap 年底 P/E | B12: https://companiesmarketcap.com/quanta-computer/pe-ratio/
A13: 資料商：Goodinfo 歷年經營績效（年底收盤、EPS） | B13: https://goodinfo.tw/tw/StockBzPerformance.asp?STOCK_ID=2382&RPT_CAT=M_YEAR
A14: 市場層：markets/network、markets/chip_bridge、tsmc 成品（本 repo，唯讀）
A15: 待補（人工）：3Q26 法說（11 月中）；客戶占比（年報 10% 以上客戶，MOPS）；業外與稅前利益；客供比例的量化；前瞻 P/E 十年歷史（Bloomberg）；券商共識（付費） | B15: 未找到
A16: SemiAnalysis | B16: 未使用
