Workbook

Sheet README
A1: 緯穎科技（6669）收支與估值模型 v0.1（AI 半導體 Project：伺服器組裝次產業，樣板＝quanta/） 2026-10-25
A2: 版本：v0.1（初版）。緯穎是雲端客戶（AWS、Microsoft、Meta）的伺服器 ODM，AI 伺服器約九成是 ASIC 機架（Trainium 為主），另一半營收是通用伺服器。組裝市場與 ODM 每櫃價格讀廣達模型（規則第 13 條），本模型只決定緯穎的份額、ASIC 傾斜、客供與通用伺服器。
A3: 模型命題：緯穎的 AI 伺服器營收＝部署 GW × 每 GW ODM 整櫃價值 × 緯穎有效份額（FY2026 校準）× ASIC 傾斜係數（客戶 ASIC 顆數相對全部加速器的成長）×（1 − 客供比例）；通用伺服器另以成長率推。毛利率約 8%，高於 GPU 整櫃組裝廠，因為 ASIC 機架不含轉手 GPU。
A4: 核心問題：客戶 ASIC（Trainium、MTIA、Maia）放量能不能讓 AI 營收在 FY2027 翻倍以上、同時守住約 8% 毛利率；除權後約 1,840 元、約 12 倍前瞻 P/E 隱含什麼路徑。
A6: 會計年度＝日曆年，FY(t)＝CY(t)，不平移。金額：十億新台幣；整櫃價格與市場以美元計、以匯率換算。口徑：歸屬母公司淨利。2026-09-02 除權（每股配約 1.98 股）：所有 EPS 與股數為除權還原後（除權前 EPS ÷ 2.9828），現價為除權後價格；年底 P/E 不受除權影響。
A8: 驅動因子 → 推導量（全部唯讀上游，不修改）
A9: AI 伺服器營收：markets/network 的 AI IT 資本支出 × 情境顆數係數 ÷ 每 GW IT 資本支出（Tokenomics，經橋接表）＝部署 GW；× 每 GW 架數 × ODM 每櫃價格（廣達模型）＝組裝市場；× 緯穎有效份額（FY2026 以公司 AI 占比校準）× 份額相對值（Assumed）× ASIC 傾斜係數（tsmc 成品顆數，Derived）×（1 − 客供比例，Assumed）。
A10: 通用伺服器：FY2026 殘差 × 成長率（Assumed）。毛利率：AI 伺服器（毛額基礎）比通用低 d_ai（Assumed），FY2027 起再加 GPU 機櫃稀釋 vrd；通用毛利率為 FY2026 殘差（Derived）。營業費用彈性 phi（Assumed）。淨利：營業利益 × 淨利係數（業外與稅前未找到）。
A11: 校準：FY2026 ＝ 1H26 實績＋3Q26 營收實績＋假設（4Q 季增、毛利率、營業費用率）。不用券商數字（只在 Recon 對帳）。
A12: 估值：Val 第 0 節目標價＝0.5 × DCF 目標價（股東現金流＝EPS ×（1 − g／ROE），FY2027–32 明確期＋永續，r 10%、g 4%，三情境權重 0.3／0.5／0.2）＋0.5 × Comparable 目標價（廣達、緯創、鴻海、Supermicro、Celestica 前瞻 P/E 中位數 × 12 個月後前瞻 EPS；不含 A 股）；另列 Comparable 單獨目標價、市場共識目標價與差距拆解。十年 P/E 規則值 × FY2027 EPS 保留為參考（不是目標價）。情境對應：A＝順利、B＝平平、C＝不如預期（原為顆數情境）。本版未做先驗，無 Andy 合理 P/E 對照。
A13: 預估期間：FY2027–FY2029 由驅動因子推導；FY2030 起為收斂法，非驅動因子推導（營收年增由 FY2029 線性收斂到 fade_g、淨利率收斂到 fade_m，FY2032 達到；PL 頁灰底）。
A14: 標記：Verified、Interested-party、Analogy、Assumed、Derived。SemiAnalysis 未使用。公司原文只經財報摘要與新聞；券商與資料商為 Interested-party。
A16: 已知限制：(1) ASIC 傾斜係數用 tsmc 成品的「Trainium＋其他 ASIC」顆數，「其他 ASIC」含華為 Ascend（非緯穎客戶）；ASIC 機架每 GW 價值假設與 NVIDIA 整櫃相同；(2) 份額相對值與客供比例是 Assumed；(3) 客戶集中：前三大客戶約 96%（凱基，標籤順序不明），單一客戶轉單風險未建；(4) 業外與稅前利益未找到；(5) 十年 P/E 只有 2019–2025 七年；(6) 共識 FY2027–28 EPS 由共識淨利 ÷ 除權後股數推得；(7) 3Q26 財報（約 11 月上旬）後更新錨點；R4 產業部署路徑未建。

Sheet In
A1: In — 輸入（藍字；基準欄 E，低 D、高 F）。金額：十億新台幣（NT$B），整櫃價格與市場為美元；比例：%。每個輸入附兩個來源（找不到者寫「未找到」）；公司原文算一個。EPS 與股數皆為除權還原後
A2: 標記：Verified／Interested-party／Analogy／Assumed／Derived；Analogy、Assumed 給低／高區間，不當點估計（放情境或 Sens）。SemiAnalysis 未使用。公司原文＝緯穎財報與法說（經優分析、理財周刊、口袋學堂摘要）、月營收公告；公司的 AI 占比與展望為 Interested-party；券商與資料商估計皆為 Interested-party。組裝市場與 ODM 每櫃價格讀廣達模型（唯讀），口徑一致
A3: 鍵 | B3: 項目 | C3: 單位 | D3: 低 | E3: 基準 | F3: 高 | G3: 標記 | H3: 來源1 | I3: 來源2／說明
A4: A. AI 部署規模（讀 markets/network、markets/chip_bridge、tsmc 成品；情境 A 基準，B／C 依顆數係數縮放）
A5: itc_26 | B5: AI IT 資本支出 2026 | C5: US$B | E5: 781.87292 | G5: Derived | H5: markets/network/dist/20261023_AI網通市場模型_v0.2.2.xlsx｜Mkt!C27:F27 | I5: 加速器顆數 × 每顆 IT capex（含 ASIC）；除以每 GW IT 資本支出得到部署 GW（與廣達、鴻海模型同口徑）
A6: itc_27 | B6: AI IT 資本支出 2027 | C6: US$B | E6: 1565.35 | G6: Derived | H6: markets/network/dist/20261023_AI網通市場模型_v0.2.2.xlsx｜Mkt!C27:F27 | I6: 同上
A7: itc_28 | B7: AI IT 資本支出 2028 | C7: US$B | E7: 1984.2639 | G7: Derived | H7: markets/network/dist/20261023_AI網通市場模型_v0.2.2.xlsx｜Mkt!C27:F27 | I7: 同上
A8: itc_29 | B8: AI IT 資本支出 2029 | C8: US$B | E8: 2260.3903 | G8: Derived | H8: markets/network/dist/20261023_AI網通市場模型_v0.2.2.xlsx｜Mkt!C27:F27 | I8: 同上
A9: itpg_gb | B9: 每 GW IT 資本支出（GB300） | C9: US$B | E9: 32.237224 | G9: Derived | H9: markets/chip_bridge/dist/20261023_晶片內容橋接表_v0.2.1.xlsx｜In!E10（GB300）、H10（VR200） | I9: Tokenomics v20.1 IF_CapexIT（經橋接表；唯讀）
A10: itpg_vr | B10: 每 GW IT 資本支出（VR200；2027 起） | C10: US$B | E10: 37.586352 | G10: Derived | H10: markets/chip_bridge/dist/20261023_晶片內容橋接表_v0.2.1.xlsx｜In!E10（GB300）、H10（VR200） | I10: 同上；ASIC 機架未另訂（Assumed：同 VR200）
A11: vr26 | B11: 2026 年部署中 Rubin 世代占比（混合用） | C11: % | D11: 0.15 | E11: 0.22 | F11: 0.3 | G11: Derived | H11: quanta/dist/20261025_廣達模型_v0.2.xlsx｜In!D11:F11 | I11: 廣達模型輸入（TrendForce 2026 組合 Rubin 22%）
A12: racks_gb | B12: 每 GW 機架數（GB300） | C12: 架 | E12: 6764 | G12: Derived | H12: markets/chip_bridge/dist/20261023_晶片內容橋接表_v0.2.1.xlsx｜In!E6（GB300）、H6（VR200） | I12: Tokenomics IF_RacksPerGW（經橋接表）
A13: racks_vr | B13: 每 GW 機架數（VR200） | C13: 架 | E13: 4052 | G13: Derived | H13: markets/chip_bridge/dist/20261023_晶片內容橋接表_v0.2.1.xlsx｜In!E6（GB300）、H6（VR200） | I13: 同上
A14: um28_A | B14: 情境 A：2028 顆數 ÷ 基準 | C14: x | E14: 1 | G14: Assumed | H14: tsmc/dist/20261025_台積電模型_v0.2.2.xlsx｜In!E37 | I14: A＝順利（基準）；B＝平平（AI 資本支出消化）；C＝不如預期（明顯下修）；與台積電、廣達、鴻海模型相同
A15: um29_A | B15: 情境 A：2029 顆數 ÷ 基準 | C15: x | E15: 1 | G15: Assumed | H15: tsmc/dist/20261025_台積電模型_v0.2.2.xlsx｜In!E38 | I15: 同上
A16: um28_B | B16: 情境 B：2028 顆數 ÷ 基準 | C16: x | E16: 0.8 | G16: Assumed | H16: tsmc/dist/20261025_台積電模型_v0.2.2.xlsx｜In!E39 | I16: A＝順利（基準）；B＝平平（AI 資本支出消化）；C＝不如預期（明顯下修）；與台積電、廣達、鴻海模型相同
A17: um29_B | B17: 情境 B：2029 顆數 ÷ 基準 | C17: x | E17: 0.85 | G17: Assumed | H17: tsmc/dist/20261025_台積電模型_v0.2.2.xlsx｜In!E40 | I17: 同上
A18: um28_C | B18: 情境 C：2028 顆數 ÷ 基準 | C18: x | E18: 0.6 | G18: Assumed | H18: tsmc/dist/20261025_台積電模型_v0.2.2.xlsx｜In!E41 | I18: A＝順利（基準）；B＝平平（AI 資本支出消化）；C＝不如預期（明顯下修）；與台積電、廣達、鴻海模型相同
A19: um29_C | B19: 情境 C：2029 顆數 ÷ 基準 | C19: x | E19: 0.6 | G19: Assumed | H19: tsmc/dist/20261025_台積電模型_v0.2.2.xlsx｜In!E42 | I19: 同上
A20: fx | B20: 匯率（新台幣 ÷ 美元） | C20: NT$/US$ | D20: 30.5 | E20: 32 | F20: 33 | G20: Derived | H20: quanta/dist/20261025_廣達模型_v0.2.xlsx｜In!D22:F22 | I20: 與廣達、鴻海模型相同
A21: ua_26 | B21: 緯穎客戶 ASIC 顆數 2026（AWS Trainium＋其他 ASIC） | C21: 百萬顆 | E21: 3 | G21: Derived | H21: tsmc/dist/20261025_台積電模型_v0.2.2.xlsx｜In!E5:E36 | I21: Trainium＋「其他 ASIC（MTIA、Maia、Ascend 等）」；Google TPU 不含（非緯穎主要客戶）；2029＝2028 × (1＋各類成長)
A22: ua_27 | B22: 緯穎客戶 ASIC 顆數 2027（AWS Trainium＋其他 ASIC） | C22: 百萬顆 | E22: 7 | G22: Derived | H22: 同上 | I22: 同上；「其他 ASIC」含華為 Ascend，非緯穎客戶（限制）
A23: ua_28 | B23: 緯穎客戶 ASIC 顆數 2028（AWS Trainium＋其他 ASIC） | C23: 百萬顆 | E23: 8 | G23: Derived | H23: 同上 | I23: 同上；「其他 ASIC」含華為 Ascend，非緯穎客戶（限制）
A24: ua_29 | B24: 緯穎客戶 ASIC 顆數 2029（AWS Trainium＋其他 ASIC） | C24: 百萬顆 | E24: 9.2 | G24: Derived | H24: 同上 | I24: 同上；「其他 ASIC」含華為 Ascend，非緯穎客戶（限制）
A25: ut_26 | B25: 全部 AI 加速器顆數 2026 | C25: 百萬顆 | E25: 15.2 | G25: Derived | H25: tsmc/dist/20261025_台積電模型_v0.2.2.xlsx｜In!E5:E36 | I25: 八類加速器合計（與 Amkor 模型同口徑）
A26: ut_27 | B26: 全部 AI 加速器顆數 2027 | C26: 百萬顆 | E26: 23.7 | G26: Derived | H26: 同上 | I26: 同上
A27: ut_28 | B27: 全部 AI 加速器顆數 2028 | C27: 百萬顆 | E27: 26.5 | G27: Derived | H27: 同上 | I27: 同上
A28: ut_29 | B28: 全部 AI 加速器顆數 2029 | C28: 百萬顆 | E28: 30.15 | G28: Derived | H28: 同上 | I28: 同上
A29: B. 組裝價格（讀廣達模型，唯讀）、緯穎份額、ASIC 比重與客供
A30: odm_gb | B30: ODM 每櫃價格 GB300（廣達模型） | C30: US$M/架 | D30: 3.6 | E30: 4 | F30: 4.3 | G30: Derived | H30: quanta/dist/20261025_廣達模型_v0.2.xlsx｜In!D24:F24 | I30: 廣達模型標記 Interested-party（法人）；本模型不另訂；ASIC 機架每 GW 價值假設相同（Assumed）
A31: odm_vr | B31: ODM 每櫃價格 VR200（廣達模型） | C31: US$M/架 | D31: 6.5 | E31: 6.75 | F31: 7 | G31: Derived | H31: quanta/dist/20261025_廣達模型_v0.2.xlsx｜In!D25:F25 | I31: 同上
A32: vpg_28 | B32: 每 GW ODM 整櫃價值 2028 ÷ 2027（廣達模型） | C32: x | D32: 0.85 | E32: 1 | F32: 1.2 | G32: Assumed | H32: quanta/dist/20261025_廣達模型_v0.2.xlsx｜In!D26:F26 | I32: 廣達模型的 Assumed
A33: vpg_29 | B33: 每 GW ODM 整櫃價值 2029 ÷ 2027（廣達模型） | C33: x | D33: 0.85 | E33: 1 | F33: 1.2 | G33: Assumed | H33: quanta/dist/20261025_廣達模型_v0.2.xlsx｜In!D27:F27 | I33: 同上
A34: asic_mix | B34: 2026 年 ASIC 占緯穎 AI 伺服器營收 | C34: % | D34: 0.85 | E34: 0.9 | F34: 0.95 | G34: Interested-party | H34: 優分析 2026-02-26（4Q25 法說）：ASIC 約占 AI 伺服器九成（公司，4Q25 法說） | I34: 凱基 2026-07-28 報告：2026F ASIC 91%、2027F 88%（凱基）
A35: rel_27 | B35: 緯穎有效份額 2027 ÷ 2026（相對值，ASIC 傾斜之外） | C35: x | D35: 0.85 | E35: 1 | F35: 1.1 | G35: Assumed | H35: 優分析 2026-09-10（公司說明）：4Q26 ASIC 出貨超越通用伺服器、GPU 機櫃季底開始出貨（公司） | I35: 經濟日報 2026-09-21（高盛）：AWS 新一代氣冷、液冷 ASIC 伺服器放量；NVIDIA、AMD 新 GPU 機櫃 4Q26 量產（高盛）
A36: rel_28 | B36: 緯穎有效份額 2028 ÷ 2026 | C36: x | D36: 0.75 | E36: 1 | F36: 1.1 | G36: Assumed | H36: 同上；客戶自行分散 ODM（Celestica、廣達等）為下檔 | I36: —
A37: rel_29 | B37: 緯穎有效份額 2029 ÷ 2026 | C37: x | D37: 0.7 | E37: 0.95 | F37: 1.1 | G37: Assumed | H37: 同上 | I37: —
A38: cs_27 | B38: 客供比例 2027（AI 毛額價值中改為客戶供料、不計營收的比例） | C38: % | D38: 0 | E38: 0.05 | F38: 0.15 | G38: Assumed | H38: 優分析 2026-08-07（2Q26 財報）：自 4 月起部分客戶記憶體改代採購，不計營收與成本（公司） | I38: 凱基 2026-07-28 報告：AMD Helios 機櫃的客供條件仍在協商（凱基）；量化：未找到
A39: cs_28 | B39: 客供比例 2028 | C39: % | D39: 0 | E39: 0.1 | F39: 0.25 | G39: Assumed | H39: 同上；廣達模型 20%（GPU 機櫃為主） | I39: —
A40: cs_29 | B40: 客供比例 2029 | C40: % | D40: 0 | E40: 0.15 | F40: 0.35 | G40: Assumed | H40: 同上；廣達模型 25% | I40: —
A41: keep | B41: 客供部分保留的毛利比例（相對買賣模式） | C41: x | D41: 0.7 | E41: 0.9 | F41: 1 | G41: Assumed | H41: 公司：代採購使營收與成本同步減少（2Q26 財報） | I41: 與廣達模型同值；量化：未找到
A42: C. 營收結構錨點（公司揭露比例 × 營收）
A43: ais_25 | B43: 2025 年 AI 伺服器 ÷ 營收 | C43: % | D43: 0.48 | E43: 0.5 | F43: 0.52 | G43: Interested-party | H43: 優分析 2026-02-26（4Q25 法說）：2025 AI 約占五成，AI 與通用伺服器各半（公司） | I43: 凱基 2026-07-28 報告：2025 52%（凱基）
A44: ais_26 | B44: 2026 年 AI 伺服器 ÷ 營收 | C44: % | D44: 0.45 | E44: 0.48 | F44: 0.52 | G44: Interested-party | H44: 優分析 2026-09-10（公司說明）：3Q26 ASIC 與通用伺服器出貨各半、4Q26 ASIC 超越（公司）；2026 年 AI 比重「超過 50%」（公司，2026-02） | I44: 凱基 2026-07-28 報告：2026F 46%（凱基 07-28；3Q 營收實績前）
A45: g_nai27 | B45: 通用伺服器（非 AI）年增 2027 | C45: % | D45: -0.1 | E45: 0.05 | F45: 0.15 | G45: Assumed | H45: 經濟日報 2026-09-21（高盛）：北美 CSP 通用伺服器需求強、Agentic AI 帶動（高盛） | I45: 理財周刊 2026-09-09：記憶體代採購使通用伺服器營收縮小（理財周刊）
A46: g_nai28 | B46: 通用伺服器年增 2028 | C46: % | D46: -0.05 | E46: 0.03 | F46: 0.1 | G46: Assumed | H46: 同上 | I46: —
A47: g_nai29 | B47: 通用伺服器年增 2029 | C47: % | D47: -0.05 | E47: 0.03 | F47: 0.08 | G47: Assumed | H47: 同上 | I47: —
A48: D. 毛利率
A49: d_ai | B49: AI 伺服器毛利率（毛額基礎）減通用伺服器毛利率 | C49: pt | D49: -0.02 | E49: -0.01 | F49: 0 | G49: Assumed | H49: 優分析 2026-09-10（公司說明）：下半年 ASIC 比重上升，毛利率變化不大（公司） | I49: 凱基 2026-07-28 報告：毛利率 2026F 7.9% → 2027F 7.0%（AI 比重 46% → 61%）；部門別毛利率：未找到
A50: vrd | B50: FY2027 起 AI 毛利率（毛額基礎）變動（GPU 機櫃比重上升） | C50: pt | D50: -0.005 | E50: -0.002 | F50: 0 | G50: Assumed | H50: GPU 機櫃含轉手 GPU，毛利率較低（公司：先前 GB200 專案拉低毛利率，4Q25 法說） | I50: 廣達模型 VR 稀釋 −0.3 個百分點
A51: E. FY2026 錨點（1H26 實績＋3Q26 營收實績＋假設）
A52: adj | B52: 除權還原係數（1＋每股配股數） | C52: x | E52: 2.9827946 | G52: Verified | H52: 口袋學堂（除權）：2026-09-02 除權，每股配發 1.98279460 股，參考價 7,800 ÷ 2.9828 ＝ 2,615 | I52: 數位時代（除權）：每千股配 1,982.7946 股（可轉債轉換使配股率調整）
A53: q3_rev | B53: 3Q26 營收（月營收合計） | C53: NT$B | E53: 434.618 | G53: Verified | H53: 優分析 2026-10-15：3Q26 4,346.18 億、季增 56.25%；前三季 9,892.78 億 | I53: TechNews 2026-10-08（9 月營收）：9 月 1,726.20 億、前 9 月 9,892.78 億（7 月 1,176.86、8 月 1,443.12，理財周刊）
A54: q4g | B54: 4Q26 營收季增 | C54: % | D54: -0.05 | E54: 0.08 | F54: 0.15 | G54: Assumed | H54: 優分析 2026-10-15：4Q26 ASIC 出貨超越通用伺服器、GPU 機櫃季底出貨（公司） | I54: 9 月單月 1,726 億 × 3 ＝ 5,179 億（季增 19%）；凱基 07-28 估 4Q26 季增 15%（以 3Q 估值為基）
A55: q_gm | B55: 3Q、4Q26 毛利率 | C55: % | D55: 0.076 | E55: 0.083 | F55: 0.088 | G55: Interested-party | H55: 優分析 2026-09-10（公司說明）：下半年毛利率變化不大，NRE 貢獻待觀察（公司）；1H26 8.41%、2Q26 9.26%（含 NRE） | I55: 凱基 2026-07-28 報告：3Q26F 8.2%、4Q26F 7.4%
A56: q_opx | B56: 3Q、4Q26 營業費用 ÷ 營收 | C56: % | D56: 0.013 | E56: 0.015 | F56: 0.018 | G56: Assumed | H56: 1Q26 1.24%、2Q26 1.99%、1H26 1.62%（公司毛利率與營益率推得） | I56: 凱基 2026-07-28 報告：3Q26F 1.4%（8.2% − 6.8%）
A57: q_nio | B57: 3Q、4Q26 淨利 ÷ 營業利益 | C57: % | D57: 0.75 | E57: 0.78 | F57: 0.8 | G57: Derived | H57: 1H26 290.84 ÷ 376.8＝0.772；FY2025 511.18 ÷ 639.18＝0.800（公司） | I57: 業外與稅前利益：未找到（摘要未列）
A58: q_sh | B58: 除權後股數（3Q、4Q26） | C58: 十億股 | E58: 0.55736 | G58: Interested-party | H58: stockanalysis.com：流通股數 557.36 百萬股（2026-10-21） | I58: 2Q26 加權股數 0.1861 × 還原係數 2.9828 ＝ 0.5551（Derived）
A59: F. 營業費用、淨利係數、股數（FY2027 起）
A60: phi | B60: 營業費用成長對營收成長的彈性 | C60: x | D60: 0.5 | E60: 0.8 | F60: 1 | G60: Assumed | H60: FY2026 錨點實測見 Q 頁（約 1.0，含美國廠與研發擴編） | I60: 廣達模型 0.4；營業費用率 FY2025 1.53%
A61: opx_adj | B61: 營業費用額外占營收比（Sens 用；基準 0） | C61: pt | D61: -0.002 | E61: 0 | F61: 0.002 | G61: Assumed | H61: 無 | I61: 營益率約 7%，±0.2 個百分點約 ±3% 的營業利益
A62: nio_f | B62: 淨利 ÷ 營業利益 | C62: % | D62: 0.72 | E62: 0.78 | F62: 0.8 | G62: Derived | H62: 同 q_nio（1H26 0.772、FY2025 0.800） | I62: 低值：銀行聯貸 15 億美元與可轉債使利息費用上升（Assumed）
A63: sh_g | B63: 股數年變動 | C63: % | D63: 0 | E63: 0.005 | F63: 0.02 | G63: Assumed | H63: 優分析 2026-08-07（2Q26 財報）：董事會通過發行國內無擔保可轉債上限 150 億元（公司） | I63: 150 億 ÷ 市值約 1 兆 ≈ 1.5%（轉換價：未找到）
A64: mf | B64: AI 部署係數（Sens 用；FY2027 起） | C64: x | D64: 0.8 | E64: 1 | F64: 1.2 | G64: Assumed | H64: 網通模型 2027 年 AI IT 資本支出約 1.8 倍 | I64: ±20%
A65: G. 券商、共識（只作 Recon 對帳，不作校準；除權前 EPS 已 ÷ 還原係數）
A66: b_rev26 | B66: 凱基 FY2026 營收（07-28，3Q 前） | C66: NT$B | E66: 1361.998 | G66: Interested-party | H66: 凱基 2026-07-28 報告 | I66: —
A67: b_eps26 | B67: 凱基 FY2026 EPS（還原） | C67: NT$ | E67: =370.69/adj -> 124.27607 | G67: Interested-party | H67: 凱基 2026-07-28 報告：370.69（除權前） | I67: —
A68: b_rev27 | B68: 凱基 FY2027 營收 | C68: NT$B | E68: 2368.079 | G68: Interested-party | H68: 凱基 2026-07-28 報告 | I68: AI 伺服器 FY2027F 1,442（凱基）
A69: b_eps27 | B69: 凱基 FY2027 EPS（還原） | C69: NT$ | E69: =566.42/adj -> 189.89574 | G69: Interested-party | H69: 凱基 2026-07-28 報告：566.42（除權前） | I69: —
A70: b_gm27 | B70: 凱基 FY2027 毛利率 | C70: % | E70: 0.07 | G70: Interested-party | H70: 凱基 2026-07-28 報告 | I70: 營益率 5.8%
A71: c_rev26 | B71: 共識 FY2026 營收（18 位） | C71: NT$B | E71: 1403.066 | G71: Interested-party | H71: Simply Wall St（2026-10-22） | I71: 鉅亨 2026-06-15（FactSet）：FactSet 06-15 中位數 1,304（21 位）
A72: c_rev27 | B72: 共識 FY2027 營收（19 位） | C72: NT$B | E72: 2488.718 | G72: Interested-party | H72: Simply Wall St（2026-10-22） | I72: 鉅亨 2026-06-15（FactSet）：FactSet 06-15 中位數 1,943
A73: c_ni26 | B73: 共識 FY2026 淨利（18 位） | C73: NT$B | E73: 73.089 | G73: Interested-party | H73: Simply Wall St（2026-10-22） | I73: —
A74: c_ni27 | B74: 共識 FY2027 淨利（19 位） | C74: NT$B | E74: 109.35 | G74: Interested-party | H74: Simply Wall St（2026-10-22） | I74: —
A75: c_ni28 | B75: 共識 FY2028 淨利（13 位） | C75: NT$B | E75: 130.798 | G75: Interested-party | H75: Simply Wall St（2026-10-22） | I75: —
A76: c_eps26 | B76: 共識 FY2026 EPS（還原；Simply Wall St 10-20） | C76: NT$ | E76: 138 | G76: Interested-party | H76: Simply Wall St：FY2026 EPS 估計由 123 上修至 138（2026-10-20） | I76: FactSet 09-02 中位數 361.05（除權前，18 位；數位時代）÷ 還原係數 ≈ 121
A77: c_eps27 | B77: 共識 FY2027 EPS（還原；共識淨利 ÷ 除權後股數） | C77: NT$ | E77: =c_ni27/q_sh -> 196.19277 | G77: Derived | H77: Simply Wall St 共識淨利 ÷ 557.36 百萬股 | I77: FactSet 06-15 中位數 463.51（除權前）÷ 還原係數 ≈ 155
A78: c_eps28 | B78: 共識 FY2028 EPS（還原；共識淨利 ÷ 除權後股數） | C78: NT$ | E78: =c_ni28/q_sh -> 234.67418 | G78: Derived | H78: 同上 | I78: FactSet 06-15 中位數 534.87（除權前）÷ 還原係數 ≈ 179
A79: H. 價格與市場倍數
A80: px | B80: 股價（2026-10-22 收盤，除權後） | C80: NT$ | E80: 1840 | G80: Interested-party | H80: 聚財網（wearn）日線：10-22 收盤 1,840（開 1,940、低 1,830） | I80: aktien.guide：10-22 1,840；除權前 9-01 收盤 7,800、9-02 除權參考價 2,615
A81: pe_ttm | B81: 近 12 月 P/E（stockanalysis，10-21） | C81: x | E81: 19.2 | G81: Interested-party | H81: stockanalysis.com | I81: companiesmarketcap 5.74（未還原除權，不採用）
A82: fpe | B82: 前瞻 P/E（stockanalysis，10-21 價格 1,880） | C82: x | E82: 11.73 | G82: Interested-party | H82: stockanalysis.com | I82: —
A83: cons_feps | B83: 共識前瞻 12 月 EPS（10-21 價格 1,880 ÷ 前瞻 P/E） | C83: NT$ | E83: =1880/fpe -> 160.2728 | G83: Derived | H83: stockanalysis 前瞻 P/E 11.73（2026-10-21） | I83: 共識前瞻 EPS 的直接數字：未找到
A84: cons_tp | B84: 市場共識目標價（賣方平均，除權後） | C84: NT$ | D84: 2262.98 | E84: 2845.66 | F84: 4000 | G84: Interested-party | H84: Investing.com：19 位平均 2,845.66、最高 4,000（高盛）、最低 2,262.98（2026-10-23 擷取） | I84: aktien.guide：20 位平均 3,060（10-22）；Simply Wall St 10-20：2,821
A85: nim10 | B85: 十年平均淨利率（2016–2025，稅後淨利 ÷ 營收） | C85: % | E85: =AVERAGE(3.11/317,12.1/857,55.8/1811,61.7/1636,86.1/1869,86.5/1926,142/2929,120/2419,228/3605,511/9507) -> 0.039851788 | G85: Derived | H85: Goodinfo 經營績效：各年營收與稅後淨利（億元；2016 317／3.11 … 2025 9,507／511） | I85: 凱基 07-28：FY2025 營收 950,663、淨利 51,118 百萬元（同）；2016–2017 為初期低利潤率年
A86: I. 目標價與收斂法參數（黃底；Assumed，Andy 可改）
A87: tp_wA | B87: 目標價情境權重 A（A 順利／B 平平／C 不如預期） | C87: % | E87: 0.3 | G87: Assumed | H87: Andy 可改（工作單 2026-10-25 預設 A 0.3／B 0.5／C 0.2） | I87: 三者合計應為 100%（Val 頁第 0 節列示）
A88: tp_wB | B88: 目標價情境權重 B（A 順利／B 平平／C 不如預期） | C88: % | E88: 0.5 | G88: Assumed | H88: Andy 可改（工作單 2026-10-25 預設 A 0.3／B 0.5／C 0.2） | I88: 三者合計應為 100%（Val 頁第 0 節列示）
A89: tp_wC | B89: 目標價情境權重 C（A 順利／B 平平／C 不如預期） | C89: % | E89: 0.2 | G89: Assumed | H89: Andy 可改（工作單 2026-10-25 預設 A 0.3／B 0.5／C 0.2） | I89: 三者合計應為 100%（Val 頁第 0 節列示）
A90: tp_r | B90: 折現率／要求報酬 | C90: % | E90: 0.1 | G90: Assumed | H90: Andy 可改（工作單預設 10%；美、台、日、韓同一值） | I90: DCF 折現率；DCF 情境價值 ×(1＋r) 推到 12 個月後
A91: tp_g | B91: 長期成長率 | C91: % | E91: 0.04 | G91: Assumed | H91: Andy 可改（工作單預設 4%） | I91: DCF 永續成長率；FY2032 收斂目標（情境 B）
A92: tp_roe | B92: ROE（近三年平均，FY2023–25） | C92: % | E92: =AVERAGE(0.297,0.349,0.48) -> 0.37533333 | G92: Derived | H92: Goodinfo 經營績效：ROE FY2023 29.7%、FY2024 34.9%、FY2025 48% | I92: 單一來源；stockanalysis 近 12 月 51.08%
A93: tp_w_dcf | B93: 目標價中 DCF 的權重；其餘為 Comparable | C93: % | E93: 0.5 | G93: Assumed | H93: Andy 可改（Andy 2026-10-25 11:53 定 DCF／Comparable 各半） | I93: —
A94: fade_gA | B94: 情境 A：FY2032 營收年增收斂目標（tp_g＋2pt） | C94: % | E94: =tp_g+0.02 -> 0.06 | G94: Assumed | H94: 工作單 2026-10-25 11:20 收斂法 | I94: FY2030 起由 FY2029 年增線性收斂
A95: fade_gB | B95: 情境 B：FY2032 營收年增收斂目標（＝tp_g） | C95: % | E95: =tp_g -> 0.04 | G95: Assumed | H95: 同上 | I95: —
A96: fade_gC | B96: 情境 C：FY2032 營收年增收斂目標（tp_g−2pt） | C96: % | E96: =tp_g-0.02 -> 0.02 | G96: Assumed | H96: 同上 | I96: —
A97: fade_mA | B97: 情境 A：FY2032 淨利率收斂目標（＝情境 A FY2029 淨利率） | C97: % | E97: =PL!G13 -> 0.058215425 | G97: Derived | H97: PL 頁情境 A FY2029（公式於建置時連結） | I97: —
A98: fade_mB | B98: 情境 B：FY2032 淨利率收斂目標（情境 B FY2029 與十年平均的中點） | C98: % | E98: =(PL!G26+nim10)/2 -> 0.048899828 | G98: Derived | H98: PL 頁情境 B FY2029、In 頁 nim10 | I98: —
A99: fade_mC | B99: 情境 C：FY2032 淨利率收斂目標（＝十年平均淨利率） | C99: % | E99: =nim10 -> 0.039851788 | G99: Derived | H99: In 頁 nim10 | I99: —

Sheet Q
A1: Q — 實績與 FY2026 錨點（十億新台幣；EPS 為新台幣、除權還原後；股數為十億股、除權還原後）。藍字＝輸入；黑字＝公式。實績取自緯穎財報摘要與月營收
A2: FY2026 錨點＝1H26 實績＋3Q26 營收實績（月營收）＋3Q、4Q 假設（毛利率、營業費用率、淨利 ÷ 營業利益；4Q 營收＝3Q × (1＋季增)）。2Q26 毛利與營業利益由公司揭露的毛利率、營益率 × 營收推得。EPS 還原：除權前 EPS ÷ 2.9828（2026-09-02 除權）
A3: 項目 | B3: FY2025A | C3: 1H26（實績） | D3: 3Q26（營收實績） | E3: 4Q26（模型） | F3: FY2026 錨點 | G3: 標記 | H3: 來源1（公司） | I3: 來源2／說明
A4: 營收 | B4: 950.663 | C4: 554.661 | D4: =q3_rev -> 434.618 | E4: =D4*(1+q4g) -> 469.38744 | F4: =SUM(C4:E4) -> 1458.6664 | G4: Verified／Assumed（4Q 季增） | H4: FY2025：凱基 2026-07-28（公司年報數字）；1H26：優分析 2026-08-07（2Q26 財報） | I4: 1Q26 2,765.08 億、2Q26 2,781.53 億（公司）
A5: 毛利 | B5: 78.454 | C5: =20.881+278.153*0.0926 -> 46.637968 | D5: =D4*q_gm -> 36.073294 | E5: =E4*q_gm -> 38.959158 | F5: =SUM(C5:E5) -> 121.67042 | G5: Verified／Derived（2Q26 毛利率 × 營收） | H5: FY2025：凱基 2026-07-28（公司年報數字）；1H26：優分析 2026-08-07（2Q26 財報） | I5: 1Q26 毛利 208.81 億；2Q26 毛利率 9.26%；1H26 毛利率 8.41%（公司）
A6: 毛利率 | B6: =B5/B4 -> 0.082525564 | C6: =C5/C4 -> 0.084083734 | D6: =D5/D4 -> 0.083 | E6: =E5/E4 -> 0.083 | F6: =F5/F4 -> 0.083412092 | G6: Derived | H6: — | I6: —
A7: 營業費用 | B7: =B5-B8 -> 14.536 | C7: =C5-C8 -> 8.9582447 | D7: =D4*q_opx -> 6.51927 | E7: =E4*q_opx -> 7.0408116 | F7: =SUM(C7:E7) -> 22.518326 | G7: Derived（毛利 − 營業利益）／Assumed | H7: FY2025：凱基 2026-07-28（公司年報數字）；1H26：優分析 2026-08-07（2Q26 財報） | I7: Goodinfo：FY2025 營收 9,507 億、毛利率 8.25%、淨利 511 億、EPS 275.06
A8: 營業利益 | B8: 63.918 | C8: =17.458+278.153*0.0727 -> 37.679723 | D8: =D5-D7 -> 29.554024 | E8: =E5-E7 -> 31.918346 | F8: =SUM(C8:E8) -> 99.152093 | G8: Verified／Derived | H8: FY2025：凱基 2026-07-28（公司年報數字）；1H26：優分析 2026-08-07（2Q26 財報） | I8: 1Q26 營業利益 174.58 億；2Q26 營益率 7.27%；1H26 營益率 6.79%（公司）
A9: 營業利益率 | B9: =B8/B4 -> 0.067235182 | C9: =C8/C4 -> 0.067932887 | D9: =D8/D4 -> 0.068 | E9: =E8/E4 -> 0.068 | F9: =F8/F4 -> 0.06797448 | G9: Derived | H9: — | I9: —
A10: 歸屬母公司淨利 | B10: 51.118 | C10: 29.084 | D10: =D8*q_nio -> 23.052139 | E10: =E8*q_nio -> 24.89631 | F10: =SUM(C10:E10) -> 77.032449 | G10: Verified／Derived（3Q、4Q） | H10: FY2025：凱基 2026-07-28（公司年報數字）；1H26：優分析 2026-08-07（2Q26 財報） | I10: 2Q26 149.69 億、1Q26 141.15 億（公司）
A11: 淨利 ÷ 營業利益（含業外、稅） | B11: =B10/B8 -> 0.79974342 | C11: =C10/C8 -> 0.77187404 | D11: =D10/D8 -> 0.78 | E11: =E10/E8 -> 0.78 | F11: =F10/F8 -> 0.77691198 | G11: Derived | H11: — | I11: —
A12: 股數（十億股，除權還原後） | B12: =51.118/275.06*adj -> 0.55433176 | C12: =29.084/156.38*adj -> 0.55474868 | D12: =q_sh -> 0.55736 | E12: =q_sh -> 0.55736 | F12: =(2*C12+D12+E12)/4 -> 0.55605434 | G12: Derived | H12: FY2025：凱基 2026-07-28（公司年報數字）；1H26：優分析 2026-08-07（2Q26 財報） | I12: 淨利 ÷ 除權前 EPS × 還原係數；FY2026＝半年加權（1H 兩季、3Q、4Q 各一季）
A13: EPS（除權還原後） | B13: =B10/B12 -> 92.215535 | C13: =C10/C12 -> 52.427344 | D13: =D10/D12 -> 41.359514 | E13: =E10/E12 -> 44.668275 | F13: =F10/F12 -> 138.53403 | G13: Derived | H13: 淨利 ÷ 還原股數 | I13: —
A14: 公司揭露 EPS（除權前） | B14: 275.06 | C14: 156.38 | G14: Verified | H14: FY2025：凱基 2026-07-28（公司年報數字）；1H26：優分析 2026-08-07（2Q26 財報） | I14: 2Q26 80.43、1Q26 75.95（Yahoo 股市 EPS 頁同）
A15: 公司揭露 EPS ÷ 還原係數 | B15: =B14/adj -> 92.215535 | C15: =C14/adj -> 52.427344 | G15: Derived | H15: — | I15: 應等於第 13 列
A16: AI 伺服器營收（＝營收 × AI 占比） | B16: =B4*ais_25 -> 475.3315 | F16: =F4*ais_26 -> 700.15989 | G16: Derived／Interested-party | H16: 公司比例（In 頁 C 節） | I16: 各季 AI 營收金額未揭露：未找到
A17: 通用伺服器與其他（非 AI） | B17: =B4-B16 -> 475.3315 | F17: =F4-F16 -> 758.50655 | G17: Derived | H17: — | I17: —
A19: FY2026 錨點的檢查（參考；校準未使用券商數字）
A20: FY2026 營收年增 | B20: =F4/B4-1 -> 0.53436753
A21: FY2026 營業費用年增 | B21: =F7/B7-1 -> 0.54914188
A22: 營業費用彈性（營業費用年增 ÷ 營收年增；In 頁 phi 的對照） | B22: =B21/B20 -> 1.0276483
A23: FY2026 營收 ÷ 共識（Simply Wall St 10-22）− 1 | B23: =F4/c_rev26-1 -> 0.039627815
A24: FY2026 EPS ÷ 共識（還原 138）− 1 | B24: =F13/c_eps26-1 -> 0.003869784
A25: AI 伺服器營收 FY2026 年增（隱含） | B25: =F16/B16-1 -> 0.47299283
A26: 1H26 EPS 自算 − 公司揭露還原（應約為 0） | B26: =C13-C15 -> 0

Sheet Units
A1: Units — AI 伺服器組裝市場（讀廣達模型口徑）、緯穎份額、ASIC 傾斜與客供（情境 A）。部署 GW＝AI IT 資本支出（markets/network）÷ 每 GW IT 資本支出（Tokenomics，經橋接表）
A3: 項目 | B3: 單位 | C3: CY2026 | D3: CY2027 | E3: CY2028 | F3: CY2029 | G3: 說明
A4: 部署 GW（情境 A） | B4: GW | C4: =PL!D65 -> 23.399538 | D4: =PL!E65 -> 41.646766 | E4: =PL!F65 -> 52.792138 | F4: =PL!G65 -> 60.138592 | G4: AI IT 資本支出 ÷ 每 GW IT 資本支出
A5: AI 伺服器組裝市場（ODM 價） | B5: US$B | C5: =PL!D67 -> 634.61653 | D5: =PL!E67 -> 1139.0807 | E5: =PL!F67 -> 1443.9178 | F5: =PL!G67 -> 1644.8506 | G5: 與廣達、鴻海模型同口徑
A6: 緯穎客戶 ASIC 顆數（Trainium＋其他 ASIC） | B6: 百萬顆 | C6: =ua_26 -> 3 | D6: =ua_27 -> 7 | E6: =ua_28 -> 8 | F6: =ua_29 -> 9.2 | G6: tsmc 成品
A7: 全部 AI 加速器顆數 | B7: 百萬顆 | C7: =ut_26 -> 15.2 | D7: =ut_27 -> 23.7 | E7: =ut_28 -> 26.5 | F7: =ut_29 -> 30.15 | G7: tsmc 成品
A8: ASIC 傾斜係數 | B8: x | C8: =PL!D71 -> 1 | D8: =PL!E71 -> 1.4468354 | E8: =PL!F71 -> 1.4766038 | F8: =PL!G71 -> 1.4914428 | G8: ASIC 比重 90% × 相對顆數指數＋10%
A9: 緯穎有效份額 | B9: % | C9: =PL!D72 -> 0.034477508 | D9: =PL!E72 -> 0.049883281 | E9: =PL!F72 -> 0.050909619 | F9: =PL!G72 -> 0.048850169 | G9: FY2026 以公司 AI 占比校準
A10: 對照：廣達有效份額（廣達模型） | B10: % | C10: 0.13389612 | D10: 0.13389612 | E10: 0.12720132 | F10: 0.12050651 | G10: quanta/dist/20261025_廣達模型_v0.2.xlsx｜Units!C7:F7
A11: 緯穎 AI 伺服器毛額價值 | B11: US$B | C11: =PL!D73/fx -> 21.879997 | D11: =PL!E73/fx -> 56.821082 | E11: =PL!F73/fx -> 73.509303 | F11: =PL!G73/fx -> 80.351231 | G11: 買賣模式下的營收
A12: 客供比例 | B12: % | C12: =PL!D74 -> 0 | D12: =PL!E74 -> 0.05 | E12: =PL!F74 -> 0.1 | F12: =PL!G74 -> 0.15 | G12: Assumed（FY2027 起）
A13: 緯穎 AI 伺服器營收 | B13: US$B | C13: =PL!D75/fx -> 21.879997 | D13: =PL!E75/fx -> 53.980028 | E13: =PL!F75/fx -> 66.158373 | F13: =PL!G75/fx -> 68.298547
A14: 每 GW 緯穎 AI 伺服器營收 | B14: US$B/GW | C14: =PL!D81 -> 0.93506105 | D14: =PL!E81 -> 1.2961397 | E14: =PL!F81 -> 1.2531861 | F14: =PL!G81 -> 1.1356858
A15: 緯穎 AI 伺服器毛利率（營收基礎） | B15: % | C15: =PL!D87 -> 0.078212092 | D15: =PL!E87 -> 0.079822138 | E15: =PL!F87 -> 0.083833301 | F15: =PL!G87 -> 0.088316365 | G15: 客供上升 → 毛利率上升
A17: 讀法：緯穎 AI 伺服器約九成是 ASIC 機架（AWS Trainium 為主，另有 Meta、Microsoft 自研晶片），所以份額隨「客戶 ASIC 顆數 ÷ 全部加速器顆數」上升；FY2026 有效份額只有約 3%，因為分母是全部 AI 組裝市場（含 NVIDIA 整櫃、Google TPU 與其他組裝廠）。份額相對值與客供比例是 Assumed。

Sheet PL
A1: PL — 緯穎損益（十億新台幣；EPS 新台幣、除權還原後；歸屬母公司）。FY2025A 實績、FY2026 錨點（1H26 實績＋3Q26 營收實績＋假設；三情境相同），FY2027 起為模型。FY(t)＝CY(t)。三情境各一個完整推導區塊（本頁下方），頂端為摘要。FY2027 三情境相同（顆數係數從 CY2028 開始）
A2: 灰底＝FY2030–FY2032 收斂法（上游只到 2029）：營收年增線性收斂到 fade_g、淨利率線性收斂到 fade_m（In 頁 I 節），非驅動因子推導
A3: 情境／項目 | B3: 單位 | C3: FY2025A | D3: FY2026（錨點） | E3: FY2027 | F3: FY2028 | G3: FY2029 | H3: FY2030（收斂） | I3: FY2031（收斂） | J3: FY2032（收斂） | K3: 說明
A4: 情境 A
A5: 營收 | B5: NT$B | C5: =C78 -> 950.663 | D5: =D78 -> 1458.6664 | E5: =E78 -> 2523.7928 | F5: =F78 -> 2937.3928 | G5: =G78 -> 3030.4881 | H5: =H78 -> 3155.1284 | I5: =I78 -> 3314.6655 | J5: =J78 -> 3513.5454
A6: 營收年增 | B6: % | D6: =D79 -> 0.53436753 | E6: =E79 -> 0.73020555 | F6: =F79 -> 0.16388033 | G6: =G79 -> 0.031693177 | H6: =H79 -> 0.041128785 | I6: =I79 -> 0.050564392 | J6: =J79 -> 0.06
A7: AI 伺服器營收 | B7: NT$B | C7: =C75 -> 475.3315 | D7: =D75 -> 700.15989 | E7: =E75 -> 1727.3609 | F7: =F75 -> 2117.0679 | G7: =G75 -> 2185.5535
A8: 通用伺服器與其他 | B8: NT$B | C8: =C77 -> 475.3315 | D8: =D77 -> 758.50655 | E8: =E77 -> 796.43188 | F8: =F77 -> 820.32483 | G8: =G77 -> 844.93458
A9: AI 伺服器 ÷ 營收 | B9: % | C9: =C80 -> 0.5 | D9: =D80 -> 0.48 | E9: =E80 -> 0.68443056 | F9: =F80 -> 0.72073029 | G9: =G80 -> 0.72118861
A10: 毛利率 | B10: % | C10: =C86 -> 0.082525564 | D10: =D86 -> 0.083412092 | E10: =E86 -> 0.082469751 | F10: =F86 -> 0.085056165 | G10: =G86 -> 0.088287293
A11: 營業利益率 | B11: % | C11: =C91 -> 0.067235182 | D11: =D91 -> 0.06797448 | E11: =E91 -> 0.068335179 | F11: =F91 -> 0.071319636 | G11: =G91 -> 0.074635161
A12: 歸屬母公司淨利 | B12: NT$B | C12: =C93 -> 51.118 | D12: =D93 -> 77.032449 | E12: =E93 -> 134.52179 | F12: =F93 -> 163.40515 | G12: =G93 -> 176.42115 | H12: =H93 -> 183.67714 | I12: =I93 -> 192.96466 | J12: =J93 -> 204.54254
A13: 淨利率 | B13: % | C13: =C97 -> 0.053770895 | D13: =D97 -> 0.052810188 | E13: =E97 -> 0.05330144 | F13: =F97 -> 0.055629316 | G13: =G97 -> 0.058215425 | H13: =H97 -> 0.058215425 | I13: =I97 -> 0.058215425 | J13: =J97 -> 0.058215425
A14: EPS | B14: NT$ | C14: =C95 -> 92.215535 | D14: =D95 -> 138.53403 | E14: =E95 -> 240.71843 | F14: =F95 -> 290.94868 | G14: =G95 -> 312.56132 | H14: =H95 -> 323.7976 | I14: =I95 -> 338.47784 | J14: =J95 -> 357.0015
A15: EPS 年增 | B15: % | D15: =D96 -> 0.50228516 | E15: =E96 -> 0.73761224 | F15: =F96 -> 0.20866808 | G15: =G96 -> 0.074283355 | H15: =H96 -> 0.035949039 | I15: =I96 -> 0.045337704 | J15: =J96 -> 0.054726368
A17: 情境 B
A18: 營收 | B18: NT$B | C18: =C118 -> 950.663 | D18: =D118 -> 1458.6664 | E18: =E118 -> 2523.7928 | F18: =F118 -> 2513.9792 | G18: =G118 -> 2702.655 | H18: =H118 -> 2873.9145 | I18: =I118 -> 3022.4487 | J18: =J118 -> 3143.3466
A19: 營收年增 | B19: % | D19: =D119 -> 0.53436753 | E19: =E119 -> 0.73020555 | F19: =F119 -> -0.0038884305 | G19: =G119 -> 0.075050689 | H19: =H119 -> 0.063367126 | I19: =I119 -> 0.051683563 | J19: =J119 -> 0.04
A20: AI 伺服器營收 | B20: NT$B | C20: =C115 -> 475.3315 | D20: =D115 -> 700.15989 | E20: =E115 -> 1727.3609 | F20: =F115 -> 1693.6543 | G20: =G115 -> 1857.7205
A21: 通用伺服器與其他 | B21: NT$B | C21: =C117 -> 475.3315 | D21: =D117 -> 758.50655 | E21: =E117 -> 796.43188 | F21: =F117 -> 820.32483 | G21: =G117 -> 844.93458
A22: AI 伺服器 ÷ 營收 | B22: % | C22: =C120 -> 0.5 | D22: =D120 -> 0.48 | E22: =E120 -> 0.68443056 | F22: =F120 -> 0.67369466 | G22: =G120 -> 0.68736869
A23: 毛利率 | B23: % | C23: =C126 -> 0.082525564 | D23: =D126 -> 0.083412092 | E23: =E126 -> 0.082469751 | F23: =F126 -> 0.085262124 | G23: =G126 -> 0.088283766
A24: 營業利益率 | B24: % | C24: =C131 -> 0.067235182 | D24: =D131 -> 0.06797448 | E24: =E131 -> 0.068335179 | F24: =F131 -> 0.071072376 | G24: =G131 -> 0.074292139
A25: 歸屬母公司淨利 | B25: NT$B | C25: =C133 -> 51.118 | D25: =D133 -> 77.032449 | E25: =E133 -> 134.52179 | F25: =F133 -> 139.36609 | G25: =G133 -> 156.6131 | H25: =H133 -> 157.86946 | I25: =I133 -> 156.91297 | J25: =J133 -> 153.70911
A26: 淨利率 | B26: % | C26: =C137 -> 0.053770895 | D26: =D137 -> 0.052810188 | E26: =E137 -> 0.05330144 | F26: =F137 -> 0.055436453 | G26: =G137 -> 0.057947868 | H26: =H137 -> 0.054931855 | I26: =I137 -> 0.051915842 | J26: =J137 -> 0.048899828
A27: EPS | B27: NT$ | C27: =C135 -> 92.215535 | D27: =D135 -> 138.53403 | E27: =E135 -> 240.71843 | F27: =F135 -> 248.14627 | G27: =G135 -> 277.46785 | H27: =H135 -> 278.3022 | I27: =I135 -> 275.23984 | J27: =J135 -> 268.27858
A28: EPS 年增 | B28: % | D28: =D136 -> 0.50228516 | E28: =E136 -> 0.73761224 | F28: =F136 -> 0.030856988 | G28: =G136 -> 0.11816247 | H28: =H136 -> 0.0030070111 | I28: =I136 -> -0.011003718 | J28: =J136 -> -0.025291591
A30: 情境 C
A31: 營收 | B31: NT$B | C31: =C158 -> 950.663 | D31: =D158 -> 1458.6664 | E31: =E158 -> 2523.7928 | F31: =F158 -> 2090.5656 | G31: =G158 -> 2156.2667 | H31: =H158 -> 2215.819 | I31: =I158 -> 2268.5758 | J31: =J158 -> 2313.9473
A32: 營收年增 | B32: % | D32: =D159 -> 0.53436753 | E32: =E159 -> 0.73020555 | F32: =F159 -> -0.17165719 | G32: =G159 -> 0.03142742 | H32: =H159 -> 0.02761828 | I32: =I159 -> 0.02380914 | J32: =J159 -> 0.02
A33: AI 伺服器營收 | B33: NT$B | C33: =C155 -> 475.3315 | D33: =D155 -> 700.15989 | E33: =E155 -> 1727.3609 | F33: =F155 -> 1270.2408 | G33: =G155 -> 1311.3321
A34: 通用伺服器與其他 | B34: NT$B | C34: =C157 -> 475.3315 | D34: =D157 -> 758.50655 | E34: =E157 -> 796.43188 | F34: =F157 -> 820.32483 | G34: =G157 -> 844.93458
A35: AI 伺服器 ÷ 營收 | B35: % | C35: =C160 -> 0.5 | D35: =D160 -> 0.48 | E35: =E160 -> 0.68443056 | F35: =F160 -> 0.60760627 | G35: =G160 -> 0.60814931
A36: 毛利率 | B36: % | C36: =C166 -> 0.082525564 | D36: =D166 -> 0.083412092 | E36: =E166 -> 0.082469751 | F36: =F166 -> 0.085551511 | G36: =G166 -> 0.088275506
A37: 營業利益率 | B37: % | C37: =C171 -> 0.067235182 | D37: =D171 -> 0.06797448 | E37: =E171 -> 0.068335179 | F37: =F171 -> 0.068487836 | G37: =G171 -> 0.071315816
A38: 歸屬母公司淨利 | B38: NT$B | C38: =C173 -> 51.118 | D38: =D173 -> 77.032449 | E38: =E173 -> 134.52179 | F38: =F173 -> 111.67908 | G38: =G173 -> 119.94522 | H38: =H173 -> 111.60671 | I38: =I173 -> 102.33539 | J38: =J173 -> 92.214939
A39: 淨利率 | B39: % | C39: =C177 -> 0.053770895 | D39: =D177 -> 0.052810188 | E39: =E177 -> 0.05330144 | F39: =F177 -> 0.053420512 | G39: =G177 -> 0.055626337 | H39: =H177 -> 0.050368154 | I39: =I177 -> 0.045109971 | J39: =J177 -> 0.039851788
A40: EPS | B40: NT$ | C40: =C175 -> 92.215535 | D40: =D175 -> 138.53403 | E40: =E175 -> 240.71843 | F40: =F175 -> 198.84858 | G40: =G175 -> 212.5042 | H40: =H175 -> 196.74733 | I40: =I175 -> 179.50572 | J40: =J175 -> 160.94878
A41: EPS 年增 | B41: % | D41: =D176 -> 0.50228516 | E41: =E176 -> 0.73761224 | F41: =F176 -> -0.17393703 | G41: =G176 -> 0.068673457 | H41: =H176 -> -0.074148503 | I41: =I176 -> -0.087633235 | J41: =J176 -> -0.10337803
A43: 核對（應為 0）：FY2026 模型 − 錨點
A44: 三情境：營收差（NT$B） | D44: =ABS(D78-a26_rev)+ABS(D118-a26_rev)+ABS(D158-a26_rev) -> 0
A45: 三情境：EPS 差（NT$） | D45: =ABS(D95-a26_eps)+ABS(D135-a26_eps)+ABS(D175-a26_eps) -> 0
A46: 情境 A：毛利差（NT$B；以 FY2027 公式套用 FY2026） | D46: =D83*D77+D84-a26_gp -> 0
A60: 情境 A（順利）：顆數係數 1.0
A61: 項目 | B61: 單位 | C61: FY2025A | D61: FY2026（錨點） | E61: FY2027 | F61: FY2028 | G61: FY2029 | H61: FY2030（收斂） | I61: FY2031（收斂） | J61: FY2032（收斂） | K61: 說明
A62: A. AI 部署與整櫃組裝市場（D 欄＝FY2026 校準年；E–G＝FY2027–FY2029）
A63: AI IT 資本支出 × 情境顆數係數 | B63: US$B | D63: =itc_26 -> 781.87292 | E63: =itc_27*1 -> 1565.35 | F63: =itc_28*um28_A*1 -> 1984.2639 | G63: =itc_29*um29_A*1 -> 2260.3903
A64: 每 GW IT 資本支出 | B64: US$B | D64: =itpg_gb*(1-vr26)+itpg_vr*vr26 -> 33.414032 | E64: =itpg_vr -> 37.586352 | F64: =itpg_vr -> 37.586352 | G64: =itpg_vr -> 37.586352
A65: 部署 GW（IT 電力） | B65: GW | D65: =D63/D64 -> 23.399538 | E65: =E63/E64 -> 41.646766 | F65: =F63/F64 -> 52.792138 | G65: =G63/G64 -> 60.138592
A66: 每 GW ODM 整櫃價值（廣達模型口徑） | B66: US$B/GW | D66: =(racks_gb*odm_gb*(1-vr26)+racks_vr*odm_vr*vr26)/1000 -> 27.1209 | E66: =racks_vr*odm_vr/1000 -> 27.351 | F66: =$E66*vpg_28 -> 27.351 | G66: =$E66*vpg_29 -> 27.351 | K66: 架數 × ODM 每櫃價格；ASIC 機架每 GW 價值假設相同（Assumed）
A67: AI 伺服器組裝市場（ODM 價，美元） | B67: US$B | D67: =D65*D66 -> 634.61653 | E67: =E65*E66 -> 1139.0807 | F67: =F65*F66 -> 1443.9178 | G67: =G65*G66 -> 1644.8506
A68: AI 伺服器組裝市場（新台幣） | B68: NT$B | D68: =D67*fx -> 20307.729 | E68: =E67*fx -> 36450.582 | F68: =F67*fx -> 46205.369 | G68: =G67*fx -> 52635.22
A69: 緯穎有效份額（FY2026 校準）＝ AI 伺服器營收 ÷ 市場 | B69: % | D69: =a26_ai/D68 -> 0.034477508 | K69: Derived：分子為公司 AI 占比 × 營收；分母為全部 AI 組裝市場（含 NVIDIA、Google TPU 與其他組裝廠）
A70: 份額相對值（÷ FY2026；ASIC 傾斜之外） | B70: x | D70: =1 -> 1 | E70: =rel_27 -> 1 | F70: =rel_28 -> 1 | G70: =rel_29 -> 0.95
A71: ASIC 傾斜係數 ＝ ASIC 比重 ×（客戶 ASIC 顆數指數 ÷ 全部顆數指數）＋（1 − ASIC 比重） | B71: x | D71: =1 -> 1 | E71: =asic_mix*((ua_27/ua_26)/(ut_27/ut_26))+(1-asic_mix) -> 1.4468354 | F71: =asic_mix*((ua_28/ua_26)/(ut_28/ut_26))+(1-asic_mix) -> 1.4766038 | G71: =asic_mix*((ua_29/ua_26)/(ut_29/ut_26))+(1-asic_mix) -> 1.4914428 | K71: Trainium＋其他 ASIC 成長快於全部加速器時，緯穎占 AI 組裝市場的份額上升；情境係數對兩者相同、互相抵銷
A72: 緯穎有效份額 | B72: % | D72: =$D$69*D70*D71 -> 0.034477508 | E72: =$D$69*E70*E71 -> 0.049883281 | F72: =$D$69*F70*F71 -> 0.050909619 | G72: =$D$69*G70*G71 -> 0.048850169
A73: AI 伺服器毛額價值（買賣模式下的營收） | B73: NT$B | D73: =D68*D72 -> 700.15989 | E73: =E68*E72 -> 1818.2746 | F73: =F68*F72 -> 2352.2977 | G73: =G68*G72 -> 2571.2394
A74: 客供比例 | B74: % | D74: =0 -> 0 | E74: =cs_27 -> 0.05 | F74: =cs_28 -> 0.1 | G74: =cs_29 -> 0.15 | K74: FY2026 的記憶體代採購已含在錨點與校準份額內，記為 0
A75: AI 伺服器營收 | B75: NT$B | C75: =a25_ai -> 475.3315 | D75: =D73*(1-D74) -> 700.15989 | E75: =E73*(1-E74) -> 1727.3609 | F75: =F73*(1-F74) -> 2117.0679 | G75: =G73*(1-G74) -> 2185.5535
A76: B. 通用伺服器與合計
A77: 通用伺服器與其他（非 AI） | B77: NT$B | C77: =a25_nai -> 475.3315 | D77: =a26_nai -> 758.50655 | E77: =D77*(1+g_nai27) -> 796.43188 | F77: =E77*(1+g_nai28) -> 820.32483 | G77: =F77*(1+g_nai29) -> 844.93458
A78: 營收 | B78: NT$B | C78: =C75+C77 -> 950.663 | D78: =D75+D77 -> 1458.6664 | E78: =E75+E77 -> 2523.7928 | F78: =F75+F77 -> 2937.3928 | G78: =G75+G77 -> 3030.4881 | H78: =G78*(1+H79) -> 3155.1284 | I78: =H78*(1+I79) -> 3314.6655 | J78: =I78*(1+J79) -> 3513.5454 | K78: FY2030 起為收斂法：營收年增由 FY2029 線性收斂到 fade_g、淨利率收斂到 fade_m（FY2032 達到），非驅動因子推導
A79: 營收年增 | B79: % | D79: =D78/C78-1 -> 0.53436753 | E79: =E78/D78-1 -> 0.73020555 | F79: =F78/E78-1 -> 0.16388033 | G79: =G78/F78-1 -> 0.031693177 | H79: =$G79+(fade_gA-$G79)*1/3 -> 0.041128785 | I79: =$G79+(fade_gA-$G79)*2/3 -> 0.050564392 | J79: =$G79+(fade_gA-$G79)*3/3 -> 0.06
A80: AI 伺服器 ÷ 營收 | B80: % | C80: =C75/C78 -> 0.5 | D80: =D75/D78 -> 0.48 | E80: =E75/E78 -> 0.68443056 | F80: =F75/F78 -> 0.72073029 | G80: =G75/G78 -> 0.72118861
A81: 每 GW 緯穎 AI 伺服器營收 | B81: US$B/GW | D81: =D75/fx/D65 -> 0.93506105 | E81: =E75/fx/E65 -> 1.2961397 | F81: =F75/fx/F65 -> 1.2531861 | G81: =G75/fx/G65 -> 1.1356858
A82: C. 損益
A83: 通用伺服器毛利率 ＝ 錨點毛利率 − 差距 × AI 占比（FY2026 校準） | B83: % | D83: =a26_gp/D78-d_ai*D80 -> 0.088212092 | K83: Derived：讓 FY2026 毛利率等於錨點；AI 毛利率（毛額基礎）＝通用 + 差距（差距為負）
A84: AI 伺服器毛利 ＝ AI 毛利率 × 毛額價值 ×（1 − 客供 ×（1 − 保留比例）） | B84: NT$B | D84: =($D$83+d_ai)*D73*(1-D74*(1-keep)) -> 54.76097 | E84: =($D$83+d_ai+vrd)*E73*(1-E74*(1-keep)) -> 137.88164 | F84: =($D$83+d_ai+vrd)*F73*(1-F74*(1-keep)) -> 177.48079 | G84: =($D$83+d_ai+vrd)*G73*(1-G74*(1-keep)) -> 193.02014 | K84: 客供部分不計營收，但大部分毛利金額保留（keep）；FY2027 起加 GPU 機櫃稀釋 vrd
A85: 毛利 | B85: NT$B | C85: =a25_gp -> 78.454 | D85: =a26_gp -> 121.67042 | E85: =$D$83*E77+E84 -> 208.13656 | F85: =$D$83*F77+F84 -> 249.84336 | G85: =$D$83*G77+G84 -> 267.55359
A86: 毛利率 | B86: % | C86: =C85/C78 -> 0.082525564 | D86: =D85/D78 -> 0.083412092 | E86: =E85/E78 -> 0.082469751 | F86: =F85/F78 -> 0.085056165 | G86: =G85/G78 -> 0.088287293
A87: AI 伺服器毛利率（營收基礎） | B87: % | D87: =D84/D75 -> 0.078212092 | E87: =E84/E75 -> 0.079822138 | F87: =F84/F75 -> 0.083833301 | G87: =G84/G75 -> 0.088316365 | K87: 客供比例上升 → 營收基礎毛利率上升
A88: 營業費用（基準路徑） | B88: NT$B | C88: =a25_opx -> 14.536 | D88: =a26_opx -> 22.518326 | E88: =D88*(1+MAX(0,phi*E79)) -> 35.672732 | F88: =E88*(1+MAX(0,phi*F79)) -> 40.349579 | G88: =F88*(1+MAX(0,phi*G79)) -> 41.372624
A89: 營業費用 | B89: NT$B | C89: =C88 -> 14.536 | D89: =D88 -> 22.518326 | E89: =E88+0*E78 -> 35.672732 | F89: =F88+0*F78 -> 40.349579 | G89: =G88+0*G78 -> 41.372624
A90: 營業利益 | B90: NT$B | C90: =C85-C89 -> 63.918 | D90: =D85-D89 -> 99.152093 | E90: =E85-E89 -> 172.46383 | F90: =F85-F89 -> 209.49378 | G90: =G85-G89 -> 226.18096
A91: 營業利益率 | B91: % | C91: =C90/C78 -> 0.067235182 | D91: =D90/D78 -> 0.06797448 | E91: =E90/E78 -> 0.068335179 | F91: =F90/F78 -> 0.071319636 | G91: =G90/G78 -> 0.074635161
A92: 淨利 ÷ 營業利益 | B92: % | C92: =a25_ni/a25_oi -> 0.79974342 | D92: =a26_ni/a26_oi -> 0.77691198 | E92: =nio_f -> 0.78 | F92: =nio_f -> 0.78 | G92: =nio_f -> 0.78
A93: 歸屬母公司淨利 | B93: NT$B | C93: =a25_ni -> 51.118 | D93: =a26_ni -> 77.032449 | E93: =E90*E92 -> 134.52179 | F93: =F90*F92 -> 163.40515 | G93: =G90*G92 -> 176.42115 | H93: =H78*H97 -> 183.67714 | I93: =I78*I97 -> 192.96466 | J93: =J78*J97 -> 204.54254
A94: 股數（除權還原後） | B94: 十億股 | C94: =a25_sh -> 0.55433176 | D94: =a26_sh -> 0.55605434 | E94: =D94*(1+sh_g) -> 0.55883461 | F94: =E94*(1+sh_g) -> 0.56162878 | G94: =F94*(1+sh_g) -> 0.56443693 | H94: =G94*(1+sh_g) -> 0.56725911 | I94: =H94*(1+sh_g) -> 0.57009541 | J94: =I94*(1+sh_g) -> 0.57294588
A95: EPS（除權還原後） | B95: NT$ | C95: =C93/C94 -> 92.215535 | D95: =D93/D94 -> 138.53403 | E95: =E93/E94 -> 240.71843 | F95: =F93/F94 -> 290.94868 | G95: =G93/G94 -> 312.56132 | H95: =H93/H94 -> 323.7976 | I95: =I93/I94 -> 338.47784 | J95: =J93/J94 -> 357.0015
A96: EPS 年增 | B96: % | D96: =D95/C95-1 -> 0.50228516 | E96: =E95/D95-1 -> 0.73761224 | F96: =F95/E95-1 -> 0.20866808 | G96: =G95/F95-1 -> 0.074283355 | H96: =H95/G95-1 -> 0.035949039 | I96: =I95/H95-1 -> 0.045337704 | J96: =J95/I95-1 -> 0.054726368
A97: 淨利率（歸屬母公司淨利 ÷ 營收） | B97: % | C97: =C93/C78 -> 0.053770895 | D97: =D93/D78 -> 0.052810188 | E97: =E93/E78 -> 0.05330144 | F97: =F93/F78 -> 0.055629316 | G97: =G93/G78 -> 0.058215425 | H97: =$G97+(fade_mA-$G97)*1/3 -> 0.058215425 | I97: =$G97+(fade_mA-$G97)*2/3 -> 0.058215425 | J97: =$G97+(fade_mA-$G97)*3/3 -> 0.058215425
A100: 情境 B（平平）：CY2028 顆數 ×0.8、CY2029 ×0.85
A101: 項目 | B101: 單位 | C101: FY2025A | D101: FY2026（錨點） | E101: FY2027 | F101: FY2028 | G101: FY2029 | H101: FY2030（收斂） | I101: FY2031（收斂） | J101: FY2032（收斂） | K101: 說明
A102: A. AI 部署與整櫃組裝市場（D 欄＝FY2026 校準年；E–G＝FY2027–FY2029）
A103: AI IT 資本支出 × 情境顆數係數 | B103: US$B | D103: =itc_26 -> 781.87292 | E103: =itc_27*1 -> 1565.35 | F103: =itc_28*um28_B*1 -> 1587.4111 | G103: =itc_29*um29_B*1 -> 1921.3317
A104: 每 GW IT 資本支出 | B104: US$B | D104: =itpg_gb*(1-vr26)+itpg_vr*vr26 -> 33.414032 | E104: =itpg_vr -> 37.586352 | F104: =itpg_vr -> 37.586352 | G104: =itpg_vr -> 37.586352
A105: 部署 GW（IT 電力） | B105: GW | D105: =D103/D104 -> 23.399538 | E105: =E103/E104 -> 41.646766 | F105: =F103/F104 -> 42.233711 | G105: =G103/G104 -> 51.117803
A106: 每 GW ODM 整櫃價值（廣達模型口徑） | B106: US$B/GW | D106: =(racks_gb*odm_gb*(1-vr26)+racks_vr*odm_vr*vr26)/1000 -> 27.1209 | E106: =racks_vr*odm_vr/1000 -> 27.351 | F106: =$E106*vpg_28 -> 27.351 | G106: =$E106*vpg_29 -> 27.351 | K106: 架數 × ODM 每櫃價格；ASIC 機架每 GW 價值假設相同（Assumed）
A107: AI 伺服器組裝市場（ODM 價，美元） | B107: US$B | D107: =D105*D106 -> 634.61653 | E107: =E105*E106 -> 1139.0807 | F107: =F105*F106 -> 1155.1342 | G107: =G105*G106 -> 1398.123
A108: AI 伺服器組裝市場（新台幣） | B108: NT$B | D108: =D107*fx -> 20307.729 | E108: =E107*fx -> 36450.582 | F108: =F107*fx -> 36964.295 | G108: =G107*fx -> 44739.937
A109: 緯穎有效份額（FY2026 校準）＝ AI 伺服器營收 ÷ 市場 | B109: % | D109: =a26_ai/D108 -> 0.034477508 | K109: Derived：分子為公司 AI 占比 × 營收；分母為全部 AI 組裝市場（含 NVIDIA、Google TPU 與其他組裝廠）
A110: 份額相對值（÷ FY2026；ASIC 傾斜之外） | B110: x | D110: =1 -> 1 | E110: =rel_27 -> 1 | F110: =rel_28 -> 1 | G110: =rel_29 -> 0.95
A111: ASIC 傾斜係數 ＝ ASIC 比重 ×（客戶 ASIC 顆數指數 ÷ 全部顆數指數）＋（1 − ASIC 比重） | B111: x | D111: =1 -> 1 | E111: =asic_mix*((ua_27/ua_26)/(ut_27/ut_26))+(1-asic_mix) -> 1.4468354 | F111: =asic_mix*((ua_28/ua_26)/(ut_28/ut_26))+(1-asic_mix) -> 1.4766038 | G111: =asic_mix*((ua_29/ua_26)/(ut_29/ut_26))+(1-asic_mix) -> 1.4914428 | K111: Trainium＋其他 ASIC 成長快於全部加速器時，緯穎占 AI 組裝市場的份額上升；情境係數對兩者相同、互相抵銷
A112: 緯穎有效份額 | B112: % | D112: =$D$109*D110*D111 -> 0.034477508 | E112: =$D$109*E110*E111 -> 0.049883281 | F112: =$D$109*F110*F111 -> 0.050909619 | G112: =$D$109*G110*G111 -> 0.048850169
A113: AI 伺服器毛額價值（買賣模式下的營收） | B113: NT$B | D113: =D108*D112 -> 700.15989 | E113: =E108*E112 -> 1818.2746 | F113: =F108*F112 -> 1881.8382 | G113: =G108*G112 -> 2185.5535
A114: 客供比例 | B114: % | D114: =0 -> 0 | E114: =cs_27 -> 0.05 | F114: =cs_28 -> 0.1 | G114: =cs_29 -> 0.15 | K114: FY2026 的記憶體代採購已含在錨點與校準份額內，記為 0
A115: AI 伺服器營收 | B115: NT$B | C115: =a25_ai -> 475.3315 | D115: =D113*(1-D114) -> 700.15989 | E115: =E113*(1-E114) -> 1727.3609 | F115: =F113*(1-F114) -> 1693.6543 | G115: =G113*(1-G114) -> 1857.7205
A116: B. 通用伺服器與合計
A117: 通用伺服器與其他（非 AI） | B117: NT$B | C117: =a25_nai -> 475.3315 | D117: =a26_nai -> 758.50655 | E117: =D117*(1+g_nai27) -> 796.43188 | F117: =E117*(1+g_nai28) -> 820.32483 | G117: =F117*(1+g_nai29) -> 844.93458
A118: 營收 | B118: NT$B | C118: =C115+C117 -> 950.663 | D118: =D115+D117 -> 1458.6664 | E118: =E115+E117 -> 2523.7928 | F118: =F115+F117 -> 2513.9792 | G118: =G115+G117 -> 2702.655 | H118: =G118*(1+H119) -> 2873.9145 | I118: =H118*(1+I119) -> 3022.4487 | J118: =I118*(1+J119) -> 3143.3466 | K118: FY2030 起為收斂法：營收年增由 FY2029 線性收斂到 fade_g、淨利率收斂到 fade_m（FY2032 達到），非驅動因子推導
...

Sheet Val
A1: Val — P/E 估值（新台幣，除權後）。結論用「現價 ÷ FY2027、FY2028 EPS（模型）」；目標價＝DCF 與 Comparable 加權（第 0 節）；十年 P/E 規則值（第 3 節，年底落後 P/E）只作參考
A2: 循環位置：緯穎不是設備股，不套設備市場見頂年；以本模型營收最高的會計年度為見頂年（比照廣達、鴻海；FY(t)＝CY(t)）。營收到 FY2029 仍在增加時，見頂年未知，判為中段
A4: 0. 目標價
A5: 0.1 DCF（股東權益現金流，FY2027–FY2032 明確期＋FY2032 後永續）
A6: 項目 | B6: A（順利） | C6: B（平平） | D6: C（不如預期） | E6: 說明
A7: 情境 EPS（FY2027–FY2032） | E7: PL 頁各情境（除權還原後）；FY2030 起為收斂法
A8: FY2027 | B8: =PL!E14 -> 240.71843 | C8: =PL!E27 -> 240.71843 | D8: =PL!E40 -> 240.71843
A9: FY2028 | B9: =PL!F14 -> 290.94868 | C9: =PL!F27 -> 248.14627 | D9: =PL!F40 -> 198.84858
A10: FY2029 | B10: =PL!G14 -> 312.56132 | C10: =PL!G27 -> 277.46785 | D10: =PL!G40 -> 212.5042
A11: FY2030 | B11: =PL!H14 -> 323.7976 | C11: =PL!H27 -> 278.3022 | D11: =PL!H40 -> 196.74733
A12: FY2031 | B12: =PL!I14 -> 338.47784 | C12: =PL!I27 -> 275.23984 | D12: =PL!I40 -> 179.50572
A13: FY2032 | B13: =PL!J14 -> 357.0015 | C13: =PL!J27 -> 268.27858 | D13: =PL!J40 -> 160.94878
A14: 股東現金流＝EPS ×（1 − tp_g ÷ tp_roe）
A15: 再投資率（tp_g ÷ tp_roe，上限 0.8） | B15: =MIN(tp_g/tp_roe,0.8) -> 0.10657194 | E15: ROE 為近三年平均（In 頁 tp_roe）
A16: FY2027 | B16: =B8*(1-$B$15) -> 215.0646 | C16: =C8*(1-$B$15) -> 215.0646 | D16: =D8*(1-$B$15) -> 215.0646
A17: FY2028 | B17: =B9*(1-$B$15) -> 259.94171 | C17: =C9*(1-$B$15) -> 221.70084 | D17: =D9*(1-$B$15) -> 177.6569
A18: FY2029 | B18: =B10*(1-$B$15) -> 279.25106 | C18: =C10*(1-$B$15) -> 247.89756 | D18: =D10*(1-$B$15) -> 189.85721
A19: FY2030 | B19: =B11*(1-$B$15) -> 289.28986 | C19: =C11*(1-$B$15) -> 248.64299 | D19: =D11*(1-$B$15) -> 175.77959
A20: FY2031 | B20: =B12*(1-$B$15) -> 302.4056 | C20: =C12*(1-$B$15) -> 245.90699 | D20: =D12*(1-$B$15) -> 160.37545
A21: FY2032 | B21: =B13*(1-$B$15) -> 318.95516 | C21: =C13*(1-$B$15) -> 239.68762 | D21: =D13*(1-$B$15) -> 143.79615
A22: DCF 情境每股價值（折現率 tp_r） | B22: =SUMPRODUCT(B16:B21,1/(1+tp_r)^{1;2;3;4;5;6})+B21*(1+tp_g)/(tp_r-tp_g)/(1+tp_r)^6 -> 4306.2732 | C22: =SUMPRODUCT(C16:C21,1/(1+tp_r)^{1;2;3;4;5;6})+C21*(1+tp_g)/(tp_r-tp_g)/(1+tp_r)^6 -> 3367.9541 | D22: =SUMPRODUCT(D16:D21,1/(1+tp_r)^{1;2;3;4;5;6})+D21*(1+tp_g)/(tp_r-tp_g)/(1+tp_r)^6 -> 2192.7217 | E22: Σ 明確期現金流 ÷ (1＋r)^t ＋ 永續價值 ÷ (1＋r)^6；永續價值＝FY2032 現金流 ×(1＋g)÷(r−g)；基準日 2026 年底
A23: DCF 情境價值推到 12 個月後（×(1＋tp_r)） | B23: =B22*(1+tp_r) -> 4736.9005 | C23: =C22*(1+tp_r) -> 3704.7496 | D23: =D22*(1+tp_r) -> 2411.9938
A24: DCF 目標價（情境加權） | B24: =tp_wA*B23+tp_wB*C23+tp_wC*D23 -> 3755.8437 | E24: Σ 權重 × 情境價值 ×(1＋r)；權重見 In 頁
A26: 0.2 Comparable（市場主流同業前瞻 P/E）
A27: 同業與前瞻 P/E | B27: 代號 | C27: 前瞻 12 月 P/E | D27: 日期 | E27: 來源 | F27: 標記
A28: 廣達（Quanta） | B28: 2382.TW | C28: 11.52 | D28: 2026-10-21 | E28: stockanalysis.com forward PE（分析師共識；價格日期如左） | F28: Interested-party
A29: 緯創（Wistron） | B29: 3231.TW | C29: 9.21 | D29: 2026-10-19 | E29: stockanalysis.com forward PE（分析師共識；價格日期如左） | F29: Interested-party
A30: 鴻海（Hon Hai） | B30: 2317.TW | C30: 11.94 | D30: 2026-10-21 | E30: stockanalysis.com forward PE（分析師共識；價格日期如左） | F30: Interested-party
A31: Super Micro Computer | B31: SMCI | C31: 7.06 | D31: 2026-10-23 | E31: stockanalysis.com forward PE（分析師共識；價格日期如左） | F31: Interested-party
A32: Celestica | B32: CLS | C32: 16.65 | D32: 2026-10-23 | E32: stockanalysis.com forward PE（分析師共識；價格日期如左） | F32: Interested-party
A33: 同業前瞻 P/E 中位數 | B33: =MEDIAN(C28:C32) -> 11.52 | E33: 雲端伺服器 ODM／EMS 同業：廣達、緯創、鴻海、Supermicro、Celestica（不含 A 股）
A34: 12 個月後的前瞻 EPS（情境加權） | B34: =tp_wA*(2/12*B8+10/12*B9)+tp_wB*(2/12*C8+10/12*C9)+tp_wC*(2/12*D8+10/12*D9) -> 249.39262 | E34: 約 2027-10 時的未來 12 月 EPS ≈ 2／12 × FY2027＋10／12 × FY2028（會計年度＝日曆年）
A35: Comparable 目標價 | B35: =B33*B34 -> 2873.0029 | E35: 同業中位數 × 前瞻 EPS
A37: 0.3 結論
A38: 項目 | B38: 數值 | E38: 說明
A39: 目標價（DCF 與 Comparable 加權） | B39: =tp_w_dcf*B24+(1-tp_w_dcf)*B35 -> 3314.4233 | E39: tp_w_dcf × DCF＋（1 − tp_w_dcf）× Comparable；tp_w_dcf 見 In 頁（0.5）
A40: Comparable 目標價（市場主流同業法） | B40: =B35 -> 2873.0029
A41: 市場共識目標價 | B41: =cons_tp -> 2845.66 | E41: Investing.com：19 位分析師平均 2,845.66（最高 4,000、最低 2,262.98），2026-10-23 擷取；aktien.guide 20 位 3,060
A42: 上檔空間：加權目標價 | B42: =B39/px-1 -> 0.80131702 | E42: 現價＝In 頁 px（2026-10-22 收盤）
A43: 上檔空間：Comparable 目標價 | B43: =B40/px-1 -> 0.56141464
A44: 與市場共識目標價的差距：EPS 因素 | B44: =B34/cons_feps-1 -> 0.55605074 | E44: 本模型前瞻 EPS ÷ 共識前瞻 EPS − 1；共識前瞻 EPS＝價格 ÷ 前瞻 P/E（In 頁 cons_feps）
A45: 與市場共識目標價的差距：倍數因素 | B45: =(cons_tp/cons_feps)/B33-1 -> 0.54124149 | E45: ="共識目標價隱含 "&TEXT(cons_tp/cons_feps,"0.0")&"x，同業中位數 "&TEXT(B33,"0.0")&"x" -> 共識目標價隱含 17.8x，同業中位數 11.5x
A46: 價格帶（DCF 不如預期～順利） | B46: =TEXT(D23,"0")&"～"&TEXT(B23,"0") -> 2412～4737 | E46: C 情境價值～A 情境價值（推到 12 個月後）
A47: 歷史倍數檢查：現價隱含 P/E 的十年分位（A／B／C） | B47: =IF(px/B9<=MIN($B$86:$B$95),0,IF(px/B9>=MAX($B$86:$B$95),1,PERCENTRANK($B$86:$B$95,px/B9))) -> 0 | C47: =IF(px/C9<=MIN($B$86:$B$95),0,IF(px/C9>=MAX($B$86:$B$95),1,PERCENTRANK($B$86:$B$95,px/C9))) -> 0 | D47: =IF(px/D9<=MIN($B$86:$B$95),0,IF(px/D9>=MAX($B$86:$B$95),1,PERCENTRANK($B$86:$B$95,px/D9))) -> 0 | E47: 現價 ÷ 各情境 FY2028 EPS 在 2019–2025 年底 P/E（第 5 節兩來源平均）的分位；低於歷史最小值記 0%、高於最大值記 100%；只作檢查，不進目標價
A48: 目標價方法 | B48: DCF：股東現金流＝除權還原 EPS ×（1 − g／ROE），r＝10%、g＝4%、ROE 為近三年平均約 37.5%（再投資率約 11%），FY2027–32 明確期＋永續；組裝廠資本支出低於淨利（2026 年約 13 億美元），未改用淨利＋折舊－資本支出。Comparable：廣達、緯創、鴻海、Supermicro、Celestica 前瞻 P/E 中位數（不含 A 股；英業達的 stockanalysis 價格停在 08-07，未列入）；Supermicro 倍數低（會計與毛利率疑慮）、Celestica 高（ASIC 與網通），中位數為廣達。偏誤：FY2030 起只有收斂法，淨利率高於十年平均時 DCF 偏高估；客戶集中（前三大約 96%）未在折現率反映。情境對應：A＝順利（顆數基準）、B＝平平（顆數 ×0.8／0.85）、C＝不如預期（顆數 ×0.6）
A51: 1. 價格與市場隱含倍數
A52: 項目 | B52: A | C52: B | D52: C | E52: 說明
A53: 現價（2026-10-22 收盤） | B53: =px -> 1840
A54: 現價 ÷ FY2026 EPS（錨點） | B54: =px/PL!D14 -> 13.281935 | C54: =px/PL!D27 -> 13.281935 | D54: =px/PL!D40 -> 13.281935 | E54: FY2026 三情境相同（錨點）
A55: 現價 ÷ FY2027 EPS（模型） | B55: =px/PL!E14 -> 7.6437854 | C55: =px/PL!E27 -> 7.6437854 | D55: =px/PL!E40 -> 7.6437854 | E55: FY2027 三情境相同（顆數係數從 CY2028 開始）
A56: 現價 ÷ FY2028 EPS（模型） | B56: =px/PL!F14 -> 6.3241394 | C56: =px/PL!F27 -> 7.4149815 | D56: =px/PL!F40 -> 9.2532721
A57: 現價 ÷ FY2029 EPS（模型） | B57: =px/PL!G14 -> 5.8868448 | C57: =px/PL!G27 -> 6.631399 | D57: =px/PL!G40 -> 8.6586525
A58: 未來 12 月 EPS（模型 B）≈ 0.2 × FY2026＋0.8 × FY2027 | B58: =0.2*PL!D27+0.8*PL!E27 -> 220.28155
A59: 現價 ÷ 未來 12 月 EPS（模型 B） | B59: =px/B58 -> 8.3529466
A60: 近 12 月 P/E（stockanalysis，10-21） | B60: =pe_ttm -> 19.2
A61: 前瞻 P/E（stockanalysis，10-21） | B61: =fpe -> 11.73
A63: 2. 循環位置（本模型營收最高年；FY(t)＝CY(t)）
A64: 情境 | B64: 營收最高年（FY2026–FY2029） | C64: FY2027 判定 | D64: 規則倍數（P/E） | E64: 見頂年是否未知 | F64: 說明
A65: A | B65: =INDEX({2026,2027,2028,2029},MATCH(MAX(PL!D78:G78),PL!D78:G78,0)) -> 2029 | C65: =IF(B65=2029,"中段",IF(2027<B65,"中段",IF(2027=B65,"見頂","谷底"))) -> 中段 | D65: =IF(C65="見頂",pe_peak,IF(C65="谷底",pe_trough,pe_mid)) -> 16.72 | E65: =IF(B65=2029,"是：營收到觀測期末仍在增加","否") -> 是：營收到觀測期末仍在增加 | F65: tools/cycle_position.py excel_rule；營收最高年取代設備市場見頂年
A66: B | B66: =INDEX({2026,2027,2028,2029},MATCH(MAX(PL!D118:G118),PL!D118:G118,0)) -> 2029 | C66: =IF(B66=2029,"中段",IF(2027<B66,"中段",IF(2027=B66,"見頂","谷底"))) -> 中段 | D66: =IF(C66="見頂",pe_peak,IF(C66="谷底",pe_trough,pe_mid)) -> 16.72 | E66: =IF(B66=2029,"是：營收到觀測期末仍在增加","否") -> 是：營收到觀測期末仍在增加 | F66: 同上
A67: C | B67: =INDEX({2026,2027,2028,2029},MATCH(MAX(PL!D158:G158),PL!D158:G158,0)) -> 2027 | C67: =IF(B67=2029,"中段",IF(2027<B67,"中段",IF(2027=B67,"見頂","谷底"))) -> 見頂 | D67: =IF(C67="見頂",pe_peak,IF(C67="谷底",pe_trough,pe_mid)) -> 14.37 | E67: =IF(B67=2029,"是：營收到觀測期末仍在增加","否") -> 否 | F67: 同上
A69: 3. 規則值隱含股價（新台幣；約 FY2027 年底，未折現）＝ FY2027 EPS × 規則倍數
A70: 情境 | B70: FY2027 EPS | C70: （同左） | D70: 規則倍數 | E70: 隱含股價 | F70: 相對現價 | G70: 現價 ÷ FY2027 EPS
A71: A | B71: =PL!E14 -> 240.71843 | C71: =B71 -> 240.71843 | D71: =D65 -> 16.72 | E71: =C71*D71 -> 4024.8121 | F71: =E71/px-1 -> 1.1873979 | G71: =px/C71 -> 7.6437854
A72: B | B72: =PL!E27 -> 240.71843 | C72: =B72 -> 240.71843 | D72: =D66 -> 16.72 | E72: =C72*D72 -> 4024.8121 | F72: =E72/px-1 -> 1.1873979 | G72: =px/C72 -> 7.6437854
A73: C | B73: =PL!E40 -> 240.71843 | C73: =B73 -> 240.71843 | D73: =D67 -> 14.37 | E73: =C73*D73 -> 3459.1238 | F73: =E73/px-1 -> 0.87995858 | G73: =px/C73 -> 7.6437854
A75: 4. What must be true：FY2027 年底價 ＝ 現價 ×（1＋報酬）所需的倍數（FY2028 EPS；約 2027 年底的價格看下一年 EPS）
A76: FY2027 年底價 ÷ 現價 | B76: 所需倍數（÷ FY2028 EPS，A） | C76: 所需倍數（÷ FY2028 EPS，B） | D76: 所需倍數（÷ FY2028 EPS，C） | E76: 對照：十年中位數
A77: 1 | B77: =px*A77/PL!F14 -> 6.3241394 | C77: =px*A77/PL!F27 -> 7.4149815 | D77: =px*A77/PL!F40 -> 9.2532721 | E77: =pe_mid -> 16.72
A78: 1.1 | B78: =px*A78/PL!F14 -> 6.9565534 | C78: =px*A78/PL!F27 -> 8.1564796 | D78: =px*A78/PL!F40 -> 10.178599 | E78: =pe_mid -> 16.72
A79: 1.21 | B79: =px*A79/PL!F14 -> 7.6522087 | C79: =px*A79/PL!F27 -> 8.9721276 | D79: =px*A79/PL!F40 -> 11.196459 | E79: =pe_mid -> 16.72
A80: 1.5 | B80: =px*A80/PL!F14 -> 9.4862091 | C80: =px*A80/PL!F27 -> 11.122472 | D80: =px*A80/PL!F40 -> 13.879908 | E80: =pe_mid -> 16.72
A81: 2 | B81: =px*A81/PL!F14 -> 12.648279 | C81: =px*A81/PL!F27 -> 14.829963 | D81: =px*A81/PL!F40 -> 18.506544 | E81: =pe_mid -> 16.72
A82: 讀法：1.00＝價格不變、1.21＝一年約 21%。所需倍數低於歷史中位數時，現價相對便宜；倍數是否合理，另看前瞻 P/E 歷史（Bloomberg）。本版未做先驗，無 Andy 合理 P/E 對照。
A84: 5. 十年 P/E（2016–2025 年底；兩來源平均，分位排名用；2019 年上市，2016–2018 無市價）
A85: 年底 | B85: 兩來源平均 P/E | C85: companiesmarketcap | D85: Goodinfo
A86: 2016
A87: 2017
A88: 2018
A89: 2019 | B89: =AVERAGE(C89:D89) -> 16.017738 | C89: =B108 -> 14.6 | D89: =C108 -> 17.435475
A90: 2020 | B90: =AVERAGE(C90:D90) -> 13.297208 | C90: =B109 -> 12.3 | D90: =C109 -> 14.294416
A91: 2021 | B91: =AVERAGE(C91:D91) -> 21.271735 | C91: =B110 -> 20 | D91: =C110 -> 22.543469
A92: 2022 | B92: =AVERAGE(C92:D92) -> 9.4105051 | C92: =B111 -> 8.99 | D92: =C111 -> 9.8310102
A93: 2023 | B93: =AVERAGE(C93:D93) -> 25.897677 | C93: =B112 -> 25.3 | D93: =C112 -> 26.495354
A94: 2024 | B94: =AVERAGE(C94:D94) -> 20.150004 | C94: =B113 -> 19.6 | D94: =C113 -> 20.700008
A95: 2025 | B95: =AVERAGE(C95:D95) -> 16.152767 | C95: =B114 -> 16 | D95: =C114 -> 16.305533
A96: 年數 | B96: =COUNT($B$86:$B$95) -> 7
A100: 6. 十年倍數與規則值（2016–2025 年底；見頂年 25 分位、中段中位數、谷底 75 分位）
A101: 規則（Andy 2026-10-13）：合理倍數＝2016–2025 年底 P/E 依循環位置取分位，兩個來源分別取分位再平均。緯穎 2019 年上市，只有 7 年（2019–2025）。兩來源相差 1–3 個倍數點（companiesmarketcap 可能用近 12 月 EPS）。2023 年 EPS 低谷時 P/E 25–26x，偏高。
A103: P/E：十年歷史倍數
A104: 年底 | B104: companiesmarketcap（年底 P/E） | C104: Goodinfo（年底收盤 ÷ EPS） | D104: 標記／說明
A105: 2016 | D105: companiesmarketcap（年底 P/E）：Interested-party（資料商；2019–2025 共 7 年；2017–2018 為上市前數字，不採用）；Goodinfo（年底收盤 ÷ EPS）：Derived（資料商年底收盤與 EPS；除權前價格與 EPS，比值不受除權影響）
A106: 2017
A107: 2018
A108: 2019 | B108: 14.6 | C108: =635/36.42 -> 17.435475
A109: 2020 | B109: 12.3 | C109: =704/49.25 -> 14.294416
A110: 2021 | B110: 20 | C110: =1115/49.46 -> 22.543469
A111: 2022 | B111: 8.99 | C111: =797/81.07 -> 9.8310102
A112: 2023 | B112: 25.3 | C112: =1825/68.88 -> 26.495354
A113: 2024 | B113: 19.6 | C113: =2620/126.57 -> 20.700008
...

Sheet Recon
A1: Recon — 本模型 vs 券商估計、共識與份額口徑。只作事後對照，不為對上數字而調參數。除權前的券商 EPS 已 ÷ 還原係數 2.9828
A3: 項目 | B3: 對照值 | C3: 模型 A | D3: 差距 A | E3: 模型 B | F3: 差距 B | G3: 模型 C | H3: 差距 C | I3: 對照來源 | J3: 說明
A4: A. 共識與券商（校準未使用）
A5: FY2026 營收 vs 共識 | B5: =c_rev26 -> 1403.066 | C5: =PL!D78 -> 1458.6664 | D5: =C5/B5-1 -> 0.039627815 | E5: =PL!D118 -> 1458.6664 | F5: =E5/B5-1 -> 0.039627815 | G5: =PL!D158 -> 1458.6664 | H5: =G5/B5-1 -> 0.039627815 | I5: Simply Wall St（18 位，10-22）
A6: FY2026 EPS vs 共識（還原） | B6: =c_eps26 -> 138 | C6: =PL!D95 -> 138.53403 | D6: =C6/B6-1 -> 0.003869784 | E6: =PL!D135 -> 138.53403 | F6: =E6/B6-1 -> 0.003869784 | G6: =PL!D175 -> 138.53403 | H6: =G6/B6-1 -> 0.003869784 | I6: Simply Wall St（10-20 上修至 138） | J6: FactSet 09-02 中位數約 121（還原）
A7: FY2027 營收 vs 共識 | B7: =c_rev27 -> 2488.718 | C7: =PL!E78 -> 2523.7928 | D7: =C7/B7-1 -> 0.014093508 | E7: =PL!E118 -> 2523.7928 | F7: =E7/B7-1 -> 0.014093508 | G7: =PL!E158 -> 2523.7928 | H7: =G7/B7-1 -> 0.014093508 | I7: Simply Wall St（19 位）
A8: FY2027 EPS vs 共識（共識淨利 ÷ 除權後股數） | B8: =c_eps27 -> 196.19277 | C8: =PL!E95 -> 240.71843 | D8: =C8/B8-1 -> 0.22694853 | E8: =PL!E135 -> 240.71843 | F8: =E8/B8-1 -> 0.22694853 | G8: =PL!E175 -> 240.71843 | H8: =G8/B8-1 -> 0.22694853 | I8: Simply Wall St（19 位）
A9: FY2028 EPS vs 共識（共識淨利 ÷ 除權後股數） | B9: =c_eps28 -> 234.67418 | C9: =PL!F95 -> 290.94868 | D9: =C9/B9-1 -> 0.23979843 | E9: =PL!F135 -> 248.14627 | F9: =E9/B9-1 -> 0.05740765 | G9: =PL!F175 -> 198.84858 | H9: =G9/B9-1 -> -0.15266102 | I9: Simply Wall St（13 位）
A10: FY2026 營收 vs 凱基（07-28，3Q 前） | B10: =b_rev26 -> 1361.998 | C10: =PL!D78 -> 1458.6664 | D10: =C10/B10-1 -> 0.070975464 | E10: =PL!D118 -> 1458.6664 | F10: =E10/B10-1 -> 0.070975464 | G10: =PL!D158 -> 1458.6664 | H10: =G10/B10-1 -> 0.070975464 | I10: 凱基 2026-07-28 | J10: 3Q26 營收 4,346 億高於凱基估 3,755 億
A11: FY2027 營收 vs 凱基 | B11: =b_rev27 -> 2368.079 | C11: =PL!E78 -> 2523.7928 | D11: =C11/B11-1 -> 0.065755309 | E11: =PL!E118 -> 2523.7928 | F11: =E11/B11-1 -> 0.065755309 | G11: =PL!E158 -> 2523.7928 | H11: =G11/B11-1 -> 0.065755309 | I11: 凱基 2026-07-28
A12: FY2027 EPS vs 凱基（還原） | B12: =b_eps27 -> 189.89574 | C12: =PL!E95 -> 240.71843 | D12: =C12/B12-1 -> 0.26763465 | E12: =PL!E135 -> 240.71843 | F12: =E12/B12-1 -> 0.26763465 | G12: =PL!E175 -> 240.71843 | H12: =G12/B12-1 -> 0.26763465 | I12: 凱基 2026-07-28
A13: FY2027 毛利率 vs 凱基（百分點） | B13: =b_gm27 -> 0.07 | C13: =PL!E86 -> 0.082469751 | D13: =C13-B13 -> 0.012469751 | E13: =PL!E126 -> 0.082469751 | F13: =E13-B13 -> 0.012469751 | G13: =PL!E166 -> 0.082469751 | H13: =G13-B13 -> 0.012469751 | I13: 凱基 2026-07-28
A14: FY2027 AI 伺服器 ÷ 營收 vs 凱基 61%（百分點） | B14: 0.61 | C14: =PL!E80 -> 0.68443056 | D14: =C14-B14 -> 0.074430558 | E14: =PL!E120 -> 0.68443056 | F14: =E14-B14 -> 0.074430558 | G14: =PL!E160 -> 0.68443056 | H14: =G14-B14 -> 0.074430558 | I14: 凱基 2026-07-28
A15: B. 份額與每 GW
A16: FY2026 緯穎有效份額 ÷ 廣達有效份額（廣達模型） | C16: =PL!D69/Units!C10 -> 0.25749444 | E16: =PL!D109/Units!C10 -> 0.25749444 | G16: =PL!D149/Units!C10 -> 0.25749444 | I16: 廣達模型 Units 頁 | J16: 同口徑（全部 AI 組裝市場）；緯穎約為廣達的四分之一
A17: FY2026 每 GW 緯穎 AI 伺服器營收（US$B） | C17: =PL!D81 -> 0.93506105 | E17: =PL!D121 -> 0.93506105 | G17: =PL!D161 -> 0.93506105 | I17: —
A18: FY2027 ASIC 傾斜係數 | C18: =PL!E71 -> 1.4468354 | E18: =PL!E111 -> 1.4468354 | G18: =PL!E151 -> 1.4468354 | I18: tsmc 成品顆數 | J18: 大於 1：客戶 ASIC 顆數成長快於全部加速器
A19: FY2027 AI 伺服器營收（NT$B）vs 凱基 1,442 | B19: 1442 | C19: =PL!E75 -> 1727.3609 | D19: =C19/B19-1 -> 0.19789243 | E19: =PL!E115 -> 1727.3609 | F19: =E19/B19-1 -> 0.19789243 | G19: =PL!E155 -> 1727.3609 | H19: =G19/B19-1 -> 0.19789243 | I19: 凱基 2026-07-28
A20: C. 校準
A21: 通用伺服器毛利率（Derived） | C21: =PL!D83 -> 0.088212092 | E21: =PL!D123 -> 0.088212092 | G21: =PL!D163 -> 0.088212092 | I21: FY2026 錨點 | J21: AI 毛利率（毛額基礎）＝此值＋d_ai
A22: 4Q26 EPS（模型，還原） | C22: =Q!E13 -> 44.668275 | E22: =Q!E13 -> 44.668275 | G22: =Q!E13 -> 44.668275 | I22: —
A23: D. 預留
A24: R4 產業部署路徑（markets/deploy_path/，尚未建立）：上線後以部署路徑取代「AI IT 資本支出 ÷ 每 GW IT 資本支出」 | J24: 預留列：本版無數值

Sheet Sens
A1: Sens — 一次動一個輸入（情境 A；有效份額、通用伺服器毛利率在每個案例內依 FY2026 錨點重算，FY2026 恆等於錨點）：對 FY2027、FY2028 營收、毛利率與 EPS 的影響。每個案例是一個完整推導區塊（本頁下方）
A3: 案例 | B3: 設定 | C3: FY2027 營收 | D3: FY2027 毛利率 | E3: FY2027 EPS | F3: FY2027 EPS 相對基準 | G3: FY2028 營收 | H3: FY2028 毛利率 | I3: FY2028 EPS | J3: FY2028 EPS 相對基準
A4: 基準（情境 A） | B4: PL 區塊 A | C4: =PL!E78 -> 2523.7928 | D4: =PL!E86 -> 0.082469751 | E4: =PL!E95 -> 240.71843 | F4: =E4/E$4-1 -> 0 | G4: =PL!F78 -> 2937.3928 | H4: =PL!F86 -> 0.085056165 | I4: =PL!F95 -> 290.94868 | J4: =I4/I$4-1 -> 0
A5: AI 部署 ×0.8 | B5: FY2027 起 AI IT 資本支出 ×0.8 | C5: =E58 -> 2178.3206 | D5: =E66 -> 0.082889651 | E5: =E75 -> 208.18362 | F5: =E5/E$4-1 -> -0.13515713 | G5: =F58 -> 2513.9792 | H5: =F66 -> 0.085262124 | I5: =F75 -> 248.695 | J5: =I5/I$4-1 -> -0.14522726
A6: AI 部署 ×1.2 | B6: ×1.2 | C6: =E98 -> 2869.2649 | D6: =E106 -> 0.082150967 | E6: =E115 -> 273.25324 | F6: =E6/E$4-1 -> 0.13515713 | G6: =F98 -> 3360.8063 | H6: =F106 -> 0.084902102 | I6: =F115 -> 333.21415 | J6: =I6/I$4-1 -> 0.1452678
A7: 份額流失（低） | B7: 份額相對值 2027 0.85、2028 0.75、2029 0.70（客戶分散 ODM） | C7: =E138 -> 2264.6886 | D7: =E146 -> 0.082772666 | E7: =E155 -> 216.31732 | F7: =E7/E$4-1 -> -0.10136784 | G7: =F138 -> 2408.1258 | H7: =F146 -> 0.08532493 | I7: =F155 -> 237.98089 | J7: =I7/I$4-1 -> -0.18205198
A8: 份額上升（高） | B8: 份額相對值 1.1 | C8: =E178 -> 2696.5289 | D8: =E186 -> 0.082300149 | E8: =E195 -> 256.98583 | F8: =E8/E$4-1 -> 0.067578563 | G8: =F178 -> 3149.0996 | H8: =F186 -> 0.084973955 | I8: =F195 -> 312.08022 | J8: =I8/I$4-1 -> 0.072629807
A9: 無 ASIC 傾斜 | B9: 緯穎份額只隨全部加速器成長（ASIC 比重設 0） | C9: =E218 -> 1990.3209 | D9: =E226 -> 0.083179399 | E9: =E235 -> 190.47876 | F9: =E9/E$4-1 -> -0.2087072 | G9: =F218 -> 2254.0662 | H9: =F226 -> 0.085426879 | I9: =F235 -> 222.75285 | J9: =I9/I$4-1 -> -0.23439125
A10: ASIC 比重 85% | B10: 基準 90% | C10: =E258 -> 2494.1554 | D10: =E266 -> 0.082501212 | E10: =E275 -> 237.92733 | F10: =E10/E$4-1 -> -0.011594844 | G10: =F258 -> 2899.4302 | H10: =F266 -> 0.085072176 | I10: =F275 -> 287.15826 | J10: =I10/I$4-1 -> -0.01302779
A11: 客供 0（維持買賣） | B11: 客供比例 2027–29 皆 0 | C11: =E298 -> 2614.7065 | D11: =E306 -> 0.079867257 | E11: =E315 -> 240.11836 | F11: =E11/E$4-1 -> -0.0024928134 | G11: =F298 -> 3172.6225 | H11: =F306 -> 0.079314856 | I11: =F315 -> 289.65119 | J11: =I11/I$4-1 -> -0.0044595134
A12: 客供 高 | B12: 客供比例 15%／25%／35% | C12: =E338 -> 2341.9653 | D12: =E346 -> 0.088280905 | E12: =E355 -> 241.91856 | F12: =E12/E$4-1 -> 0.0049856268 | G12: =F338 -> 2584.5481 | H12: =F346 -> 0.095627649 | I12: =F355 -> 292.98107 | J12: =I12/I$4-1 -> 0.0069854076
A13: 客供保留毛利 0.7 | B13: 客供部分只保留 70% 毛利 | C13: =E378 -> 2523.7928 | D13: =E386 -> 0.081920679 | E13: =E395 -> 238.78426 | F13: =E13/E$4-1 -> -0.0080349899 | G13: =F378 -> 2937.3928 | H13: =F386 -> 0.083835535 | I13: =F395 -> 285.96911 | J13: =I13/I$4-1 -> -0.017114926
A14: 每 GW 價值 低 | B14: 2028–29 每 GW ODM 價值 ×0.85 | C14: =E418 -> 2523.7928 | D14: =E426 -> 0.082469751 | E14: =E435 -> 240.71843 | F14: =E14/E$4-1 -> 0 | G14: =F418 -> 2619.8326 | H14: =F426 -> 0.085204393 | I14: =F435 -> 258.96246 | J14: =I14/I$4-1 -> -0.10993766
A15: 每 GW 價值 高 | B15: ×1.2 | C15: =E458 -> 2523.7928 | D15: =E466 -> 0.082469751 | E15: =E475 -> 240.71843 | F15: =E15/E$4-1 -> 0 | G15: =F458 -> 3360.8063 | H15: =F466 -> 0.084902102 | I15: =F475 -> 333.59697 | J15: =I15/I$4-1 -> 0.14658355
A16: 通用伺服器成長 低 | B16: 2027 −10%、2028–29 −5% | C16: =E498 -> 2410.0168 | D16: =E506 -> 0.082198658 | E16: =E515 -> 228.67122 | F16: =E16/E$4-1 -> -0.050046864 | G16: =F498 -> 2765.591 | H16: =F506 -> 0.084860115 | I16: =F515 -> 272.73062 | J16: =I16/I$4-1 -> -0.062616061
A17: 通用伺服器成長 高 | B17: 2027 +15%、2028 +10%、2029 +8% | C17: =E538 -> 2599.6434 | D17: =E546 -> 0.082637298 | E17: =E555 -> 248.74989 | F17: =E17/E$4-1 -> 0.033364576 | G17: =F538 -> 3076.5787 | H17: =F546 -> 0.085198941 | I17: =F555 -> 305.73238 | J17: =I17/I$4-1 -> 0.050812074
A18: AI 毛利率差距 −2pt | B18: AI 毛利率（毛額基礎）比通用低 2 個百分點 | C18: =E578 -> 2523.7928 | D18: =E586 -> 0.08025686 | E18: =E595 -> 232.92326 | F18: =E18/E$4-1 -> -0.032382905 | G18: =F578 -> 2937.3928 | H18: =F586 -> 0.082274082 | I18: =F595 -> 279.59916 | J18: =I18/I$4-1 -> -0.039008648
A19: AI 毛利率差距 0 | B19: 與通用相同 | C19: =E618 -> 2523.7928 | D19: =E626 -> 0.084682643 | E19: =E635 -> 248.51359 | F19: =E19/E$4-1 -> 0.032382905 | G19: =F618 -> 2937.3928 | H19: =F626 -> 0.087838247 | I19: =F635 -> 302.29819 | J19: =I19/I$4-1 -> 0.039008648
A20: GPU 稀釋 −0.5pt | B20: FY2027 起 AI 毛利率 −0.5 個百分點 | C20: =E658 -> 2523.7928 | D20: =E666 -> 0.080319199 | E20: =E675 -> 233.14286 | F20: =E20/E$4-1 -> -0.031470655 | G20: =F658 -> 2937.3928 | H20: =F666 -> 0.082677755 | I20: =F675 -> 281.24595 | J20: =I20/I$4-1 -> -0.033348599
A21: 營業費用率 +0.2pt | B21: 營業費用額外 +0.2% × 營收 | C21: =E698 -> 2523.7928 | D21: =E706 -> 0.082469751 | E21: =E715 -> 233.6732 | F21: =E21/E$4-1 -> -0.029267502 | G21: =F698 -> 2937.3928 | H21: =F706 -> 0.085056165 | I21: =F715 -> 282.78967 | J21: =I21/I$4-1 -> -0.028042768
A22: 營業費用彈性 1.0 | B22: 基準 0.8（FY2026 實測約 1.0） | C22: =E738 -> 2523.7928 | D22: =E746 -> 0.082469751 | E22: =E755 -> 236.12832 | F22: =E22/E$4-1 -> -0.019068354 | G22: =F738 -> 2937.3928 | H22: =F746 -> 0.085056165 | I22: =F755 -> 284.0091 | J22: =I22/I$4-1 -> -0.023851544
A23: 淨利 ÷ 營業利益 0.72 | B23: FY2027 起 0.72（利息費用上升） | C23: =E778 -> 2523.7928 | D23: =E786 -> 0.082469751 | E23: =E795 -> 222.20162 | F23: =E23/E$4-1 -> -0.076923077 | G23: =F778 -> 2937.3928 | H23: =F786 -> 0.085056165 | I23: =F795 -> 268.56801 | J23: =I23/I$4-1 -> -0.076923077
A24: 情境 B | B24: CY2028 顆數 ×0.8、CY2029 ×0.85 | C24: =PL!E118 -> 2523.7928 | D24: =PL!E126 -> 0.082469751 | E24: =PL!E135 -> 240.71843 | F24: =E24/E$4-1 -> 0 | G24: =PL!F118 -> 2513.9792 | H24: =PL!F126 -> 0.085262124 | I24: =PL!F135 -> 248.14627 | J24: =I24/I$4-1 -> -0.14711325
A25: 情境 C | B25: CY2028–29 顆數 ×0.6 | C25: =PL!E158 -> 2523.7928 | D25: =PL!E166 -> 0.082469751 | E25: =PL!E175 -> 240.71843 | F25: =E25/E$4-1 -> 0 | G25: =PL!F158 -> 2090.5656 | H25: =PL!F166 -> 0.085551511 | I25: =PL!F175 -> 198.84858 | J25: =I25/I$4-1 -> -0.31655102
A27: 讀法：顆數情境 B、C 的差異從 FY2028 起。緯穎的 AI 營收由部署 GW 與 ASIC 傾斜係數共同決定；「無 ASIC 傾斜」案例顯示上游 Trainium 與其他 ASIC 顆數假設對 EPS 的貢獻。客供只在保留毛利比例低時明顯影響 EPS。
A29: 目標價參數（只改 DCF 參數；PL 收斂法的 fade_g 不隨 tp_g 變動）
A30: 案例 | B30: 設定 | C30: DCF 目標價 | D30: Comparable 目標價 | E30: 加權目標價 | F30: 相對基準
A31: 基準 | B31: r 10%、g 4%、DCF 權重 0.5 | C31: =(tp_wA*(Val!B8*(1-MIN(tp_g/tp_roe,0.8))/(1+tp_r)^1+Val!B9*(1-MIN(tp_g/tp_roe,0.8))/(1+tp_r)^2+Val!B10*(1-MIN(tp_g/tp_roe,0.8))/(1+tp_r)^3+Val!B11*(1-MIN(tp_g/tp_roe,0.8))/(1+tp_r)^4+Val!B12*(1-MIN(tp_g/tp_roe,0.8))/(1+tp_r)^5+Val!B13*(1-MIN(tp_g/tp_roe,0.8))/(1+tp_r)^6+Val!B13*(1-MIN(tp_g/tp_roe,0.8))*(1+tp_g)/(tp_r-tp_g)/(1+tp_r)^6)+tp_wB*(Val!C8*(1-MIN(tp_g/tp_roe,0.8))/(1+tp_r)^1+Val!C9*(1-MIN(tp_g/tp_roe,0.8))/(1+tp_r)^2+Val!C10*(1-MIN(tp_g/tp_roe,0.8))/(1+tp_r)^3+Val!C11*(1-MIN(tp_g/tp_roe,0.8))/(1+tp_r)^4+Val!C12*(1-MIN(tp_g/tp_roe,0.8))/(1+tp_r)^5+Val!C13*(1-MIN(tp_g/tp_roe,0.8))/(1+tp_r)^6+Val!C13*(1-MIN(tp_g/tp_roe,0.8))*(1+tp_g)/(tp_r-tp_g)/(1+tp_r)^6)+tp_wC*(Val!D8*(1-MIN(tp_g/tp_roe,0.8))/(1+tp_r)^1+Val!D9*(1-MIN(tp_g/tp_roe,0.8))/(1+tp_r)^2+Val!D10*(1-MIN(tp_g/tp_roe,0.8))/(1+tp_r)^3+Val!D11*(1-MIN(tp_g/tp_roe,0.8))/(1+tp_r)^4+Val!D12*(1-MIN(tp_g/tp_roe,0.8))/(1+tp_r)^5+Val!D13*(1-MIN(tp_g/tp_roe,0.8))/(1+tp_r)^6+Val!D13*(1-MIN(tp_g/tp_roe,0.8))*(1+tp_g)/(tp_r-tp_g)/(1+tp_r)^6))*(1+tp_r) -> 3755.8437 | D31: =Val!B35 -> 2873.0029 | E31: =tp_w_dcf*C31+(1-tp_w_dcf)*D31 -> 3314.4233 | F31: =E31/E$31-1 -> 0
A32: 折現率 +1pt | B32: r 11% | C32: =(tp_wA*(Val!B8*(1-MIN(tp_g/tp_roe,0.8))/(1+(tp_r+0.01))^1+Val!B9*(1-MIN(tp_g/tp_roe,0.8))/(1+(tp_r+0.01))^2+Val!B10*(1-MIN(tp_g/tp_roe,0.8))/(1+(tp_r+0.01))^3+Val!B11*(1-MIN(tp_g/tp_roe,0.8))/(1+(tp_r+0.01))^4+Val!B12*(1-MIN(tp_g/tp_roe,0.8))/(1+(tp_r+0.01))^5+Val!B13*(1-MIN(tp_g/tp_roe,0.8))/(1+(tp_r+0.01))^6+Val!B13*(1-MIN(tp_g/tp_roe,0.8))*(1+tp_g)/((tp_r+0.01)-tp_g)/(1+(tp_r+0.01))^6)+tp_wB*(Val!C8*(1-MIN(tp_g/tp_roe,0.8))/(1+(tp_r+0.01))^1+Val!C9*(1-MIN(tp_g/tp_roe,0.8))/(1+(tp_r+0.01))^2+Val!C10*(1-MIN(tp_g/tp_roe,0.8))/(1+(tp_r+0.01))^3+Val!C11*(1-MIN(tp_g/tp_roe,0.8))/(1+(tp_r+0.01))^4+Val!C12*(1-MIN(tp_g/tp_roe,0.8))/(1+(tp_r+0.01))^5+Val!C13*(1-MIN(tp_g/tp_roe,0.8))/(1+(tp_r+0.01))^6+Val!C13*(1-MIN(tp_g/tp_roe,0.8))*(1+tp_g)/((tp_r+0.01)-tp_g)/(1+(tp_r+0.01))^6)+tp_wC*(Val!D8*(1-MIN(tp_g/tp_roe,0.8))/(1+(tp_r+0.01))^1+Val!D9*(1-MIN(tp_g/tp_roe,0.8))/(1+(tp_r+0.01))^2+Val!D10*(1-MIN(tp_g/tp_roe,0.8))/(1+(tp_r+0.01))^3+Val!D11*(1-MIN(tp_g/tp_roe,0.8))/(1+(tp_r+0.01))^4+Val!D12*(1-MIN(tp_g/tp_roe,0.8))/(1+(tp_r+0.01))^5+Val!D13*(1-MIN(tp_g/tp_roe,0.8))/(1+(tp_r+0.01))^6+Val!D13*(1-MIN(tp_g/tp_roe,0.8))*(1+tp_g)/((tp_r+0.01)-tp_g)/(1+(tp_r+0.01))^6))*(1+(tp_r+0.01)) -> 3257.4294 | D32: =Val!B35 -> 2873.0029 | E32: =tp_w_dcf*C32+(1-tp_w_dcf)*D32 -> 3065.2162 | F32: =E32/E$31-1 -> -0.075188688
A33: 折現率 −1pt | B33: r 9% | C33: =(tp_wA*(Val!B8*(1-MIN(tp_g/tp_roe,0.8))/(1+(tp_r-0.01))^1+Val!B9*(1-MIN(tp_g/tp_roe,0.8))/(1+(tp_r-0.01))^2+Val!B10*(1-MIN(tp_g/tp_roe,0.8))/(1+(tp_r-0.01))^3+Val!B11*(1-MIN(tp_g/tp_roe,0.8))/(1+(tp_r-0.01))^4+Val!B12*(1-MIN(tp_g/tp_roe,0.8))/(1+(tp_r-0.01))^5+Val!B13*(1-MIN(tp_g/tp_roe,0.8))/(1+(tp_r-0.01))^6+Val!B13*(1-MIN(tp_g/tp_roe,0.8))*(1+tp_g)/((tp_r-0.01)-tp_g)/(1+(tp_r-0.01))^6)+tp_wB*(Val!C8*(1-MIN(tp_g/tp_roe,0.8))/(1+(tp_r-0.01))^1+Val!C9*(1-MIN(tp_g/tp_roe,0.8))/(1+(tp_r-0.01))^2+Val!C10*(1-MIN(tp_g/tp_roe,0.8))/(1+(tp_r-0.01))^3+Val!C11*(1-MIN(tp_g/tp_roe,0.8))/(1+(tp_r-0.01))^4+Val!C12*(1-MIN(tp_g/tp_roe,0.8))/(1+(tp_r-0.01))^5+Val!C13*(1-MIN(tp_g/tp_roe,0.8))/(1+(tp_r-0.01))^6+Val!C13*(1-MIN(tp_g/tp_roe,0.8))*(1+tp_g)/((tp_r-0.01)-tp_g)/(1+(tp_r-0.01))^6)+tp_wC*(Val!D8*(1-MIN(tp_g/tp_roe,0.8))/(1+(tp_r-0.01))^1+Val!D9*(1-MIN(tp_g/tp_roe,0.8))/(1+(tp_r-0.01))^2+Val!D10*(1-MIN(tp_g/tp_roe,0.8))/(1+(tp_r-0.01))^3+Val!D11*(1-MIN(tp_g/tp_roe,0.8))/(1+(tp_r-0.01))^4+Val!D12*(1-MIN(tp_g/tp_roe,0.8))/(1+(tp_r-0.01))^5+Val!D13*(1-MIN(tp_g/tp_roe,0.8))/(1+(tp_r-0.01))^6+Val!D13*(1-MIN(tp_g/tp_roe,0.8))*(1+tp_g)/((tp_r-0.01)-tp_g)/(1+(tp_r-0.01))^6))*(1+(tp_r-0.01)) -> 4453.1754 | D33: =Val!B35 -> 2873.0029 | E33: =tp_w_dcf*C33+(1-tp_w_dcf)*D33 -> 3663.0892 | F33: =E33/E$31-1 -> 0.10519654
A34: 長期成長 +1pt | B34: g 5% | C34: =(tp_wA*(Val!B8*(1-MIN((tp_g+0.01)/tp_roe,0.8))/(1+tp_r)^1+Val!B9*(1-MIN((tp_g+0.01)/tp_roe,0.8))/(1+tp_r)^2+Val!B10*(1-MIN((tp_g+0.01)/tp_roe,0.8))/(1+tp_r)^3+Val!B11*(1-MIN((tp_g+0.01)/tp_roe,0.8))/(1+tp_r)^4+Val!B12*(1-MIN((tp_g+0.01)/tp_roe,0.8))/(1+tp_r)^5+Val!B13*(1-MIN((tp_g+0.01)/tp_roe,0.8))/(1+tp_r)^6+Val!B13*(1-MIN((tp_g+0.01)/tp_roe,0.8))*(1+(tp_g+0.01))/(tp_r-(tp_g+0.01))/(1+tp_r)^6)+tp_wB*(Val!C8*(1-MIN((tp_g+0.01)/tp_roe,0.8))/(1+tp_r)^1+Val!C9*(1-MIN((tp_g+0.01)/tp_roe,0.8))/(1+tp_r)^2+Val!C10*(1-MIN((tp_g+0.01)/tp_roe,0.8))/(1+tp_r)^3+Val!C11*(1-MIN((tp_g+0.01)/tp_roe,0.8))/(1+tp_r)^4+Val!C12*(1-MIN((tp_g+0.01)/tp_roe,0.8))/(1+tp_r)^5+Val!C13*(1-MIN((tp_g+0.01)/tp_roe,0.8))/(1+tp_r)^6+Val!C13*(1-MIN((tp_g+0.01)/tp_roe,0.8))*(1+(tp_g+0.01))/(tp_r-(tp_g+0.01))/(1+tp_r)^6)+tp_wC*(Val!D8*(1-MIN((tp_g+0.01)/tp_roe,0.8))/(1+tp_r)^1+Val!D9*(1-MIN((tp_g+0.01)/tp_roe,0.8))/(1+tp_r)^2+Val!D10*(1-MIN((tp_g+0.01)/tp_roe,0.8))/(1+tp_r)^3+Val!D11*(1-MIN((tp_g+0.01)/tp_roe,0.8))/(1+tp_r)^4+Val!D12*(1-MIN((tp_g+0.01)/tp_roe,0.8))/(1+tp_r)^5+Val!D13*(1-MIN((tp_g+0.01)/tp_roe,0.8))/(1+tp_r)^6+Val!D13*(1-MIN((tp_g+0.01)/tp_roe,0.8))*(1+(tp_g+0.01))/(tp_r-(tp_g+0.01))/(1+tp_r)^6))*(1+tp_r) -> 4183.4315 | D34: =Val!B35 -> 2873.0029 | E34: =tp_w_dcf*C34+(1-tp_w_dcf)*D34 -> 3528.2172 | F34: =E34/E$31-1 -> 0.064504107
A35: 長期成長 −1pt | B35: g 3% | C35: =(tp_wA*(Val!B8*(1-MIN((tp_g-0.01)/tp_roe,0.8))/(1+tp_r)^1+Val!B9*(1-MIN((tp_g-0.01)/tp_roe,0.8))/(1+tp_r)^2+Val!B10*(1-MIN((tp_g-0.01)/tp_roe,0.8))/(1+tp_r)^3+Val!B11*(1-MIN((tp_g-0.01)/tp_roe,0.8))/(1+tp_r)^4+Val!B12*(1-MIN((tp_g-0.01)/tp_roe,0.8))/(1+tp_r)^5+Val!B13*(1-MIN((tp_g-0.01)/tp_roe,0.8))/(1+tp_r)^6+Val!B13*(1-MIN((tp_g-0.01)/tp_roe,0.8))*(1+(tp_g-0.01))/(tp_r-(tp_g-0.01))/(1+tp_r)^6)+tp_wB*(Val!C8*(1-MIN((tp_g-0.01)/tp_roe,0.8))/(1+tp_r)^1+Val!C9*(1-MIN((tp_g-0.01)/tp_roe,0.8))/(1+tp_r)^2+Val!C10*(1-MIN((tp_g-0.01)/tp_roe,0.8))/(1+tp_r)^3+Val!C11*(1-MIN((tp_g-0.01)/tp_roe,0.8))/(1+tp_r)^4+Val!C12*(1-MIN((tp_g-0.01)/tp_roe,0.8))/(1+tp_r)^5+Val!C13*(1-MIN((tp_g-0.01)/tp_roe,0.8))/(1+tp_r)^6+Val!C13*(1-MIN((tp_g-0.01)/tp_roe,0.8))*(1+(tp_g-0.01))/(tp_r-(tp_g-0.01))/(1+tp_r)^6)+tp_wC*(Val!D8*(1-MIN((tp_g-0.01)/tp_roe,0.8))/(1+tp_r)^1+Val!D9*(1-MIN((tp_g-0.01)/tp_roe,0.8))/(1+tp_r)^2+Val!D10*(1-MIN((tp_g-0.01)/tp_roe,0.8))/(1+tp_r)^3+Val!D11*(1-MIN((tp_g-0.01)/tp_roe,0.8))/(1+tp_r)^4+Val!D12*(1-MIN((tp_g-0.01)/tp_roe,0.8))/(1+tp_r)^5+Val!D13*(1-MIN((tp_g-0.01)/tp_roe,0.8))/(1+tp_r)^6+Val!D13*(1-MIN((tp_g-0.01)/tp_roe,0.8))*(1+(tp_g-0.01))/(tp_r-(tp_g-0.01))/(1+tp_r)^6))*(1+tp_r) -> 3458.7308 | D35: =Val!B35 -> 2873.0029 | E35: =tp_w_dcf*C35+(1-tp_w_dcf)*D35 -> 3165.8669 | F35: =E35/E$31-1 -> -0.04482121
A36: DCF 權重 0.3 | C36: =(tp_wA*(Val!B8*(1-MIN(tp_g/tp_roe,0.8))/(1+tp_r)^1+Val!B9*(1-MIN(tp_g/tp_roe,0.8))/(1+tp_r)^2+Val!B10*(1-MIN(tp_g/tp_roe,0.8))/(1+tp_r)^3+Val!B11*(1-MIN(tp_g/tp_roe,0.8))/(1+tp_r)^4+Val!B12*(1-MIN(tp_g/tp_roe,0.8))/(1+tp_r)^5+Val!B13*(1-MIN(tp_g/tp_roe,0.8))/(1+tp_r)^6+Val!B13*(1-MIN(tp_g/tp_roe,0.8))*(1+tp_g)/(tp_r-tp_g)/(1+tp_r)^6)+tp_wB*(Val!C8*(1-MIN(tp_g/tp_roe,0.8))/(1+tp_r)^1+Val!C9*(1-MIN(tp_g/tp_roe,0.8))/(1+tp_r)^2+Val!C10*(1-MIN(tp_g/tp_roe,0.8))/(1+tp_r)^3+Val!C11*(1-MIN(tp_g/tp_roe,0.8))/(1+tp_r)^4+Val!C12*(1-MIN(tp_g/tp_roe,0.8))/(1+tp_r)^5+Val!C13*(1-MIN(tp_g/tp_roe,0.8))/(1+tp_r)^6+Val!C13*(1-MIN(tp_g/tp_roe,0.8))*(1+tp_g)/(tp_r-tp_g)/(1+tp_r)^6)+tp_wC*(Val!D8*(1-MIN(tp_g/tp_roe,0.8))/(1+tp_r)^1+Val!D9*(1-MIN(tp_g/tp_roe,0.8))/(1+tp_r)^2+Val!D10*(1-MIN(tp_g/tp_roe,0.8))/(1+tp_r)^3+Val!D11*(1-MIN(tp_g/tp_roe,0.8))/(1+tp_r)^4+Val!D12*(1-MIN(tp_g/tp_roe,0.8))/(1+tp_r)^5+Val!D13*(1-MIN(tp_g/tp_roe,0.8))/(1+tp_r)^6+Val!D13*(1-MIN(tp_g/tp_roe,0.8))*(1+tp_g)/(tp_r-tp_g)/(1+tp_r)^6))*(1+tp_r) -> 3755.8437 | D36: =Val!B35 -> 2873.0029 | E36: =0.3*C36+(1-0.3)*D36 -> 3137.8552 | F36: =E36/E$31-1 -> -0.053272662
A37: DCF 權重 0.7 | C37: =(tp_wA*(Val!B8*(1-MIN(tp_g/tp_roe,0.8))/(1+tp_r)^1+Val!B9*(1-MIN(tp_g/tp_roe,0.8))/(1+tp_r)^2+Val!B10*(1-MIN(tp_g/tp_roe,0.8))/(1+tp_r)^3+Val!B11*(1-MIN(tp_g/tp_roe,0.8))/(1+tp_r)^4+Val!B12*(1-MIN(tp_g/tp_roe,0.8))/(1+tp_r)^5+Val!B13*(1-MIN(tp_g/tp_roe,0.8))/(1+tp_r)^6+Val!B13*(1-MIN(tp_g/tp_roe,0.8))*(1+tp_g)/(tp_r-tp_g)/(1+tp_r)^6)+tp_wB*(Val!C8*(1-MIN(tp_g/tp_roe,0.8))/(1+tp_r)^1+Val!C9*(1-MIN(tp_g/tp_roe,0.8))/(1+tp_r)^2+Val!C10*(1-MIN(tp_g/tp_roe,0.8))/(1+tp_r)^3+Val!C11*(1-MIN(tp_g/tp_roe,0.8))/(1+tp_r)^4+Val!C12*(1-MIN(tp_g/tp_roe,0.8))/(1+tp_r)^5+Val!C13*(1-MIN(tp_g/tp_roe,0.8))/(1+tp_r)^6+Val!C13*(1-MIN(tp_g/tp_roe,0.8))*(1+tp_g)/(tp_r-tp_g)/(1+tp_r)^6)+tp_wC*(Val!D8*(1-MIN(tp_g/tp_roe,0.8))/(1+tp_r)^1+Val!D9*(1-MIN(tp_g/tp_roe,0.8))/(1+tp_r)^2+Val!D10*(1-MIN(tp_g/tp_roe,0.8))/(1+tp_r)^3+Val!D11*(1-MIN(tp_g/tp_roe,0.8))/(1+tp_r)^4+Val!D12*(1-MIN(tp_g/tp_roe,0.8))/(1+tp_r)^5+Val!D13*(1-MIN(tp_g/tp_roe,0.8))/(1+tp_r)^6+Val!D13*(1-MIN(tp_g/tp_roe,0.8))*(1+tp_g)/(tp_r-tp_g)/(1+tp_r)^6))*(1+tp_r) -> 3755.8437 | D37: =Val!B35 -> 2873.0029 | E37: =0.7*C37+(1-0.7)*D37 -> 3490.9915 | F37: =E37/E$31-1 -> 0.053272662
A40: 案例區塊：AI 部署 ×0.8（情境 A）
A41: 項目 | B41: 單位 | C41: FY2025A | D41: FY2026（錨點） | E41: FY2027 | F41: FY2028 | G41: FY2029 | H41: FY2030（收斂） | I41: FY2031（收斂） | J41: FY2032（收斂） | K41: 說明
A42: A. AI 部署與整櫃組裝市場（D 欄＝FY2026 校準年；E–G＝FY2027–FY2029）
A43: AI IT 資本支出 × 情境顆數係數 | B43: US$B | D43: =itc_26 -> 781.87292 | E43: =itc_27*mf_lo -> 1252.28 | F43: =itc_28*um28_A*mf_lo -> 1587.4111 | G43: =itc_29*um29_A*mf_lo -> 1808.3122
A44: 每 GW IT 資本支出 | B44: US$B | D44: =itpg_gb*(1-vr26)+itpg_vr*vr26 -> 33.414032 | E44: =itpg_vr -> 37.586352 | F44: =itpg_vr -> 37.586352 | G44: =itpg_vr -> 37.586352
A45: 部署 GW（IT 電力） | B45: GW | D45: =D43/D44 -> 23.399538 | E45: =E43/E44 -> 33.317413 | F45: =F43/F44 -> 42.233711 | G45: =G43/G44 -> 48.110873
A46: 每 GW ODM 整櫃價值（廣達模型口徑） | B46: US$B/GW | D46: =(racks_gb*odm_gb*(1-vr26)+racks_vr*odm_vr*vr26)/1000 -> 27.1209 | E46: =racks_vr*odm_vr/1000 -> 27.351 | F46: =$E46*vpg_28 -> 27.351 | G46: =$E46*vpg_29 -> 27.351 | K46: 架數 × ODM 每櫃價格；ASIC 機架每 GW 價值假設相同（Assumed）
A47: AI 伺服器組裝市場（ODM 價，美元） | B47: US$B | D47: =D45*D46 -> 634.61653 | E47: =E45*E46 -> 911.26455 | F47: =F45*F46 -> 1155.1342 | G47: =G45*G46 -> 1315.8805
A48: AI 伺服器組裝市場（新台幣） | B48: NT$B | D48: =D47*fx -> 20307.729 | E48: =E47*fx -> 29160.466 | F48: =F47*fx -> 36964.295 | G48: =G47*fx -> 42108.176
A49: 緯穎有效份額（FY2026 校準）＝ AI 伺服器營收 ÷ 市場 | B49: % | D49: =a26_ai/D48 -> 0.034477508 | K49: Derived：分子為公司 AI 占比 × 營收；分母為全部 AI 組裝市場（含 NVIDIA、Google TPU 與其他組裝廠）
A50: 份額相對值（÷ FY2026；ASIC 傾斜之外） | B50: x | D50: =1 -> 1 | E50: =rel_27 -> 1 | F50: =rel_28 -> 1 | G50: =rel_29 -> 0.95
A51: ASIC 傾斜係數 ＝ ASIC 比重 ×（客戶 ASIC 顆數指數 ÷ 全部顆數指數）＋（1 − ASIC 比重） | B51: x | D51: =1 -> 1 | E51: =asic_mix*((ua_27/ua_26)/(ut_27/ut_26))+(1-asic_mix) -> 1.4468354 | F51: =asic_mix*((ua_28/ua_26)/(ut_28/ut_26))+(1-asic_mix) -> 1.4766038 | G51: =asic_mix*((ua_29/ua_26)/(ut_29/ut_26))+(1-asic_mix) -> 1.4914428 | K51: Trainium＋其他 ASIC 成長快於全部加速器時，緯穎占 AI 組裝市場的份額上升；情境係數對兩者相同、互相抵銷
A52: 緯穎有效份額 | B52: % | D52: =$D$49*D50*D51 -> 0.034477508 | E52: =$D$49*E50*E51 -> 0.049883281 | F52: =$D$49*F50*F51 -> 0.050909619 | G52: =$D$49*G50*G51 -> 0.048850169
A53: AI 伺服器毛額價值（買賣模式下的營收） | B53: NT$B | D53: =D48*D52 -> 700.15989 | E53: =E48*E52 -> 1454.6197 | F53: =F48*F52 -> 1881.8382 | G53: =G48*G52 -> 2056.9915
A54: 客供比例 | B54: % | D54: =0 -> 0 | E54: =cs_27 -> 0.05 | F54: =cs_28 -> 0.1 | G54: =cs_29 -> 0.15 | K54: FY2026 的記憶體代採購已含在錨點與校準份額內，記為 0
A55: AI 伺服器營收 | B55: NT$B | C55: =a25_ai -> 475.3315 | D55: =D53*(1-D54) -> 700.15989 | E55: =E53*(1-E54) -> 1381.8887 | F55: =F53*(1-F54) -> 1693.6543 | G55: =G53*(1-G54) -> 1748.4428
A56: B. 通用伺服器與合計
A57: 通用伺服器與其他（非 AI） | B57: NT$B | C57: =a25_nai -> 475.3315 | D57: =a26_nai -> 758.50655 | E57: =D57*(1+g_nai27) -> 796.43188 | F57: =E57*(1+g_nai28) -> 820.32483 | G57: =F57*(1+g_nai29) -> 844.93458
A58: 營收 | B58: NT$B | C58: =C55+C57 -> 950.663 | D58: =D55+D57 -> 1458.6664 | E58: =E55+E57 -> 2178.3206 | F58: =F55+F57 -> 2513.9792 | G58: =G55+G57 -> 2593.3774 | H58: =G58*(1+H59) -> 2699.8488 | I58: =H58*(1+I59) -> 2836.2656 | J58: =I58*(1+J59) -> 3006.4415 | K58: FY2030 起為收斂法：營收年增由 FY2029 線性收斂到 fade_g、淨利率收斂到 fade_m（FY2032 達到），非驅動因子推導
A59: 營收年增 | B59: % | D59: =D58/C58-1 -> 0.53436753 | E59: =E58/D58-1 -> 0.49336444 | F59: =F58/E58-1 -> 0.15409054 | G59: =G58/F58-1 -> 0.031582678 | H59: =$G59+(fade_gA-$G59)*1/3 -> 0.041055119 | I59: =$G59+(fade_gA-$G59)*2/3 -> 0.050527559 | J59: =$G59+(fade_gA-$G59)*3/3 -> 0.06
A60: AI 伺服器 ÷ 營收 | B60: % | C60: =C55/C58 -> 0.5 | D60: =D55/D58 -> 0.48 | E60: =E55/E58 -> 0.63438262 | F60: =F55/F58 -> 0.67369466 | G60: =G55/G58 -> 0.67419528
A61: 每 GW 緯穎 AI 伺服器營收 | B61: US$B/GW | D61: =D55/fx/D45 -> 0.93506105 | E61: =E55/fx/E45 -> 1.2961397 | F61: =F55/fx/F45 -> 1.2531861 | G61: =G55/fx/G45 -> 1.1356858
A62: C. 損益
A63: 通用伺服器毛利率 ＝ 錨點毛利率 − 差距 × AI 占比（FY2026 校準） | B63: % | D63: =a26_gp/D58-d_ai*D60 -> 0.088212092 | K63: Derived：讓 FY2026 毛利率等於錨點；AI 毛利率（毛額基礎）＝通用 + 差距（差距為負）
A64: AI 伺服器毛利 ＝ AI 毛利率 × 毛額價值 ×（1 − 客供 ×（1 − 保留比例）） | B64: NT$B | D64: =($D$63+d_ai)*D53*(1-D54*(1-keep)) -> 54.76097 | E64: =($D$63+d_ai+vrd)*E53*(1-E54*(1-keep)) -> 110.30531 | F64: =($D$63+d_ai+vrd)*F53*(1-F54*(1-keep)) -> 141.98463 | G64: =($D$63+d_ai+vrd)*G53*(1-G54*(1-keep)) -> 154.41611 | K64: 客供部分不計營收，但大部分毛利金額保留（keep）；FY2027 起加 GPU 機櫃稀釋 vrd
A65: 毛利 | B65: NT$B | C65: =a25_gp -> 78.454 | D65: =a26_gp -> 121.67042 | E65: =$D$63*E57+E64 -> 180.56023 | F65: =$D$63*F57+F64 -> 214.3472 | G65: =$D$63*G57+G64 -> 228.94956
A66: 毛利率 | B66: % | C66: =C65/C58 -> 0.082525564 | D66: =D65/D58 -> 0.083412092 | E66: =E65/E58 -> 0.082889651 | F66: =F65/F58 -> 0.085262124 | G66: =G65/G58 -> 0.088282393
A67: AI 伺服器毛利率（營收基礎） | B67: % | D67: =D64/D55 -> 0.078212092 | E67: =E64/E55 -> 0.079822138 | F67: =F64/F55 -> 0.083833301 | G67: =G64/G55 -> 0.088316365 | K67: 客供比例上升 → 營收基礎毛利率上升
A68: 營業費用（基準路徑） | B68: NT$B | C68: =a25_opx -> 14.536 | D68: =a26_opx -> 22.518326 | E68: =D68*(1+MAX(0,phi*E59)) -> 31.406119 | F68: =E68*(1+MAX(0,phi*F59)) -> 35.277628 | G68: =F68*(1+MAX(0,phi*G59)) -> 36.168958
A69: 營業費用 | B69: NT$B | C69: =C68 -> 14.536 | D69: =D68 -> 22.518326 | E69: =E68+0*E58 -> 31.406119 | F69: =F68+0*F58 -> 35.277628 | G69: =G68+0*G58 -> 36.168958
A70: 營業利益 | B70: NT$B | C70: =C65-C69 -> 63.918 | D70: =D65-D69 -> 99.152093 | E70: =E65-E69 -> 149.15411 | F70: =F65-F69 -> 179.06958 | G70: =G65-G69 -> 192.7806
A71: 營業利益率 | B71: % | C71: =C70/C58 -> 0.067235182 | D71: =D70/D58 -> 0.06797448 | E71: =E70/E58 -> 0.068472068 | F71: =F70/F58 -> 0.071229538 | G71: =G70/G58 -> 0.074335731
A72: 淨利 ÷ 營業利益 | B72: % | C72: =a25_ni/a25_oi -> 0.79974342 | D72: =a26_ni/a26_oi -> 0.77691198 | E72: =nio_f -> 0.78 | F72: =nio_f -> 0.78 | G72: =nio_f -> 0.78
A73: 歸屬母公司淨利 | B73: NT$B | C73: =a25_ni -> 51.118 | D73: =a26_ni -> 77.032449 | E73: =E70*E72 -> 116.34021 | F73: =F70*F72 -> 139.67427 | G73: =G70*G72 -> 150.36887 | H73: =H58*H77 -> 156.75247 | I73: =I58*I77 -> 164.8936 | J73: =J58*J77 -> 175.02127
A74: 股數（除權還原後） | B74: 十億股 | C74: =a25_sh -> 0.55433176 | D74: =a26_sh -> 0.55605434 | E74: =D74*(1+sh_g) -> 0.55883461 | F74: =E74*(1+sh_g) -> 0.56162878 | G74: =F74*(1+sh_g) -> 0.56443693 | H74: =G74*(1+sh_g) -> 0.56725911 | I74: =H74*(1+sh_g) -> 0.57009541 | J74: =I74*(1+sh_g) -> 0.57294588
A75: EPS（除權還原後） | B75: NT$ | C75: =C73/C74 -> 92.215535 | D75: =D73/D74 -> 138.53403 | E75: =E73/E74 -> 208.18362 | F75: =F73/F74 -> 248.695 | G75: =G73/G74 -> 266.40509 | H75: =H73/H74 -> 276.3331 | I75: =I73/I74 -> 289.2386 | J75: =J73/J74 -> 305.47609
A76: EPS 年增 | B76: % | D76: =D75/C75-1 -> 0.50228516 | E76: =E75/D75-1 -> 0.50276156 | F76: =F75/E75-1 -> 0.19459448 | G76: =G75/F75-1 -> 0.071212086 | H76: =H75/G75-1 -> 0.037266602 | I76: =I75/H75-1 -> 0.046702689 | J76: =J75/I75-1 -> 0.056138747
A77: 淨利率（歸屬母公司淨利 ÷ 營收） | B77: % | C77: =C73/C58 -> 0.053770895 | D77: =D73/D58 -> 0.052810188 | E77: =E73/E58 -> 0.053408213 | F77: =F73/F58 -> 0.05555904 | G77: =G73/G58 -> 0.05798187 | H77: =$G77+(fade_mA-$G77)*1/3 -> 0.058059722 | I77: =$G77+(fade_mA-$G77)*2/3 -> 0.058137573 | J77: =$G77+(fade_mA-$G77)*3/3 -> 0.058215425
A80: 案例區塊：AI 部署 ×1.2（情境 A）
A81: 項目 | B81: 單位 | C81: FY2025A | D81: FY2026（錨點） | E81: FY2027 | F81: FY2028 | G81: FY2029 | H81: FY2030（收斂） | I81: FY2031（收斂） | J81: FY2032（收斂） | K81: 說明
A82: A. AI 部署與整櫃組裝市場（D 欄＝FY2026 校準年；E–G＝FY2027–FY2029）
A83: AI IT 資本支出 × 情境顆數係數 | B83: US$B | D83: =itc_26 -> 781.87292 | E83: =itc_27*mf_hi -> 1878.42 | F83: =itc_28*um28_A*mf_hi -> 2381.1167 | G83: =itc_29*um29_A*mf_hi -> 2712.4683
A84: 每 GW IT 資本支出 | B84: US$B | D84: =itpg_gb*(1-vr26)+itpg_vr*vr26 -> 33.414032 | E84: =itpg_vr -> 37.586352 | F84: =itpg_vr -> 37.586352 | G84: =itpg_vr -> 37.586352
A85: 部署 GW（IT 電力） | B85: GW | D85: =D83/D84 -> 23.399538 | E85: =E83/E84 -> 49.976119 | F85: =F83/F84 -> 63.350566 | G85: =G83/G84 -> 72.16631
A86: 每 GW ODM 整櫃價值（廣達模型口徑） | B86: US$B/GW | D86: =(racks_gb*odm_gb*(1-vr26)+racks_vr*odm_vr*vr26)/1000 -> 27.1209 | E86: =racks_vr*odm_vr/1000 -> 27.351 | F86: =$E86*vpg_28 -> 27.351 | G86: =$E86*vpg_29 -> 27.351 | K86: 架數 × ODM 每櫃價格；ASIC 機架每 GW 價值假設相同（Assumed）
A87: AI 伺服器組裝市場（ODM 價，美元） | B87: US$B | D87: =D85*D86 -> 634.61653 | E87: =E85*E86 -> 1366.8968 | F87: =F85*F86 -> 1732.7013 | G87: =G85*G86 -> 1973.8207
A88: AI 伺服器組裝市場（新台幣） | B88: NT$B | D88: =D87*fx -> 20307.729 | E88: =E87*fx -> 43740.699 | F88: =F87*fx -> 55446.442 | G88: =G87*fx -> 63162.264
A89: 緯穎有效份額（FY2026 校準）＝ AI 伺服器營收 ÷ 市場 | B89: % | D89: =a26_ai/D88 -> 0.034477508 | K89: Derived：分子為公司 AI 占比 × 營收；分母為全部 AI 組裝市場（含 NVIDIA、Google TPU 與其他組裝廠）
A90: 份額相對值（÷ FY2026；ASIC 傾斜之外） | B90: x | D90: =1 -> 1 | E90: =rel_27 -> 1 | F90: =rel_28 -> 1 | G90: =rel_29 -> 0.95
A91: ASIC 傾斜係數 ＝ ASIC 比重 ×（客戶 ASIC 顆數指數 ÷ 全部顆數指數）＋（1 − ASIC 比重） | B91: x | D91: =1 -> 1 | E91: =asic_mix*((ua_27/ua_26)/(ut_27/ut_26))+(1-asic_mix) -> 1.4468354 | F91: =asic_mix*((ua_28/ua_26)/(ut_28/ut_26))+(1-asic_mix) -> 1.4766038 | G91: =asic_mix*((ua_29/ua_26)/(ut_29/ut_26))+(1-asic_mix) -> 1.4914428 | K91: Trainium＋其他 ASIC 成長快於全部加速器時，緯穎占 AI 組裝市場的份額上升；情境係數對兩者相同、互相抵銷
A92: 緯穎有效份額 | B92: % | D92: =$D$89*D90*D91 -> 0.034477508 | E92: =$D$89*E90*E91 -> 0.049883281 | F92: =$D$89*F90*F91 -> 0.050909619 | G92: =$D$89*G90*G91 -> 0.048850169
A93: AI 伺服器毛額價值（買賣模式下的營收） | B93: NT$B | D93: =D88*D92 -> 700.15989 | E93: =E88*E92 -> 2181.9295 | F93: =F88*F92 -> 2822.7572 | G93: =G88*G92 -> 3085.4873
A94: 客供比例 | B94: % | D94: =0 -> 0 | E94: =cs_27 -> 0.05 | F94: =cs_28 -> 0.1 | G94: =cs_29 -> 0.15 | K94: FY2026 的記憶體代採購已含在錨點與校準份額內，記為 0
A95: AI 伺服器營收 | B95: NT$B | C95: =a25_ai -> 475.3315 | D95: =D93*(1-D94) -> 700.15989 | E95: =E93*(1-E94) -> 2072.8331 | F95: =F93*(1-F94) -> 2540.4815 | G95: =G93*(1-G94) -> 2622.6642
A96: B. 通用伺服器與合計
A97: 通用伺服器與其他（非 AI） | B97: NT$B | C97: =a25_nai -> 475.3315 | D97: =a26_nai -> 758.50655 | E97: =D97*(1+g_nai27) -> 796.43188 | F97: =E97*(1+g_nai28) -> 820.32483 | G97: =F97*(1+g_nai29) -> 844.93458
A98: 營收 | B98: NT$B | C98: =C95+C97 -> 950.663 | D98: =D95+D97 -> 1458.6664 | E98: =E95+E97 -> 2869.2649 | F98: =F95+F97 -> 3360.8063 | G98: =G95+G97 -> 3467.5988 | H98: =G98*(1+H99) -> 3610.408 | I98: =H98*(1+I99) -> 3793.0655 | J98: =I98*(1+J99) -> 4020.6495 | K98: FY2030 起為收斂法：營收年增由 FY2029 線性收斂到 fade_g、淨利率收斂到 fade_m（FY2032 達到），非驅動因子推導
A99: 營收年增 | B99: % | D99: =D98/C98-1 -> 0.53436753 | E99: =E98/D98-1 -> 0.96704666 | F99: =F98/E98-1 -> 0.17131266 | G99: =G98/F98-1 -> 0.031775833 | H99: =$G99+(fade_gA-$G99)*1/3 -> 0.041183889 | I99: =$G99+(fade_gA-$G99)*2/3 -> 0.050591944 | J99: =$G99+(fade_gA-$G99)*3/3 -> 0.06
A100: AI 伺服器 ÷ 營收 | B100: % | C100: =C95/C98 -> 0.5 | D100: =D95/D98 -> 0.48 | E100: =E95/E98 -> 0.72242651 | F100: =F95/F98 -> 0.75591428 | G100: =G95/G98 -> 0.75633439
A101: 每 GW 緯穎 AI 伺服器營收 | B101: US$B/GW | D101: =D95/fx/D85 -> 0.93506105 | E101: =E95/fx/E85 -> 1.2961397 | F101: =F95/fx/F85 -> 1.2531861 | G101: =G95/fx/G85 -> 1.1356858
A102: C. 損益
A103: 通用伺服器毛利率 ＝ 錨點毛利率 − 差距 × AI 占比（FY2026 校準） | B103: % | D103: =a26_gp/D98-d_ai*D100 -> 0.088212092 | K103: Derived：讓 FY2026 毛利率等於錨點；AI 毛利率（毛額基礎）＝通用 + 差距（差距為負）
A104: AI 伺服器毛利 ＝ AI 毛利率 × 毛額價值 ×（1 − 客供 ×（1 − 保留比例）） | B104: NT$B | D104: =($D$103+d_ai)*D93*(1-D94*(1-keep)) -> 54.76097 | E104: =($D$103+d_ai+vrd)*E93*(1-E94*(1-keep)) -> 165.45797 | F104: =($D$103+d_ai+vrd)*F93*(1-F94*(1-keep)) -> 212.97695 | G104: =($D$103+d_ai+vrd)*G93*(1-G94*(1-keep)) -> 231.62417 | K104: 客供部分不計營收，但大部分毛利金額保留（keep）；FY2027 起加 GPU 機櫃稀釋 vrd
A105: 毛利 | B105: NT$B | C105: =a25_gp -> 78.454 | D105: =a26_gp -> 121.67042 | E105: =$D$103*E97+E104 -> 235.71289 | F105: =$D$103*F97+F104 -> 285.33952 | G105: =$D$103*G97+G104 -> 306.15762
A106: 毛利率 | B106: % | C106: =C105/C98 -> 0.082525564 | D106: =D105/D98 -> 0.083412092 | E106: =E105/E98 -> 0.082150967 | F106: =F105/F98 -> 0.084902102 | G106: =G105/G98 -> 0.088290958
A107: AI 伺服器毛利率（營收基礎） | B107: % | D107: =D104/D95 -> 0.078212092 | E107: =E104/E95 -> 0.079822138 | F107: =F104/F95 -> 0.083833301 | G107: =G104/G95 -> 0.088316365 | K107: 客供比例上升 → 營收基礎毛利率上升
...

Sheet Sources
A1: 來源（公司原文只經財報摘要與新聞轉述，原始簡報待人工複核；券商與資料商皆為 Interested-party）
A2: 公司（摘要）：優分析 2026-08-07（2Q26、1H26 營收、毛利率、營益率、淨利、EPS；記憶體代採購；資本支出 9.42 億美元） | B2: https://uanalyze.com.tw/articles/3734153022
A3: 公司（摘要）：優分析 2026-09-10（3Q 通用與 ASIC 各半、4Q ASIC 超越、GPU 季底出貨、產能配置） | B3: https://uanalyze.com.tw/articles/9272255032
A4: 公司（摘要）：優分析 2026-02-26（4Q25 法說：AI 約五成、ASIC 約九成） | B4: https://uanalyze.com.tw/articles/4033848176
A5: 公司（摘要）：優分析 2026-10-15（3Q26 營收 4,346.18 億、前三季 9,892.78 億） | B5: https://uanalyze.com.tw/articles/4794857151
A6: 公司：月營收（TechNews 2026-10-08，9 月 1,726.20 億） | B6: https://finance.technews.tw/2026/10/08/wiwynn-6669-202609-financial-report/
A7: 公司（摘要）：理財周刊 2026-09-09（7、8 月營收；代採購說明） | B7: https://www.moneyweekly.com.tw/_Article?AID=247745
A8: 公司：除權（口袋學堂；配股率 1.98279460、參考價 2,615） | B8: https://www.pocket.tw/school/articles/7853/
A9: 公司：除權（數位時代；配股率調整原因、FactSet 2026 EPS 中位數 361.05） | B9: https://www.bnext.com.tw/article/92119/wiwynn-stock-dividend-1-to-3
A10: 券商：凱基 2026-07-28（FY2025 實績、2026F–2027F、客戶與 AI 占比、ASIC 比重） | B10: https://www.kgi.com.hk/zh-hk/-/media/files/kgishk/research-reports/tw-reports/wiwynn-6669-tt20260728en.pdf
A11: 券商：工商時報 2026-08-03（美系券商 EPS 2026–28 估計、目標價） | B11: https://www.ctee.com.tw/news/20260803700886-430201
A12: 券商：經濟日報 2026-09-21（高盛目標價 3,777、資本支出、ASIC 與 GPU 機櫃） | B12: https://money.udn.com/money/amp/story/5607/9768749
A13: 資料商：鉅亨 2026-06-15（FactSet 共識） | B13: https://news.cnyes.com/news/id/6498877
... A24: SemiAnalysis | B24: 未使用
