Workbook

Sheet 導覽
A1: WhiteFiber 收支與評價模型 — Excel 版 v0.1（更新 2026-10-08；與 HTML v0.1 同步；市價截至 2026-10-07 收盤）
A3: 這個活頁簿在回答什麼
A4: 一句話：長約託管能否成為可融資的現金流底座，撐住雲端 GPU 擴張而不反覆稀釋——WhiteFiber 用客戶預付款支應多少擴張資本支出，剩下的缺口要靠多少債務與新股。
A5: 所有分頁用同一組數字，改任何一個輸入，後面全部會跟著動。
A7: 分頁結構（依模組分組，分頁標籤顏色相同者為同一模組）
A8: 摘要 一頁摘要：結論、與市場共識的差異、現價隱含什麼、驗證點（全部活公式）。
A9: 輸入與假設 所有可調參數（A 情境 → B 產能與收入 → C 利潤率 → D 支出 → E 融資 → F 評價 → G 1H 實際 → H 情境區間運算表 → I 市場共識 → J 季度追蹤輸入）。
A10: 各期收支 類現金流量：來源（含客戶預付）、用途、融資前缺口、期前融資瀑布。
A11: 季度追蹤 焦點季的模型／共識／指引／實際與差距（由年度模型拆分，只用於追蹤；實際數填在輸入與假設 J 區）。
A12: 運營_產能與收入 已連網 MW → 在役 MW → 營收（MW × 每 MW 年收入 × 利用率）；RPO 排程只作對照與產能瓶頸旗標。
A13: 資產負債_既有債務／新債與新股／租賃承諾 類資產負債表：季報債務明細、每期現金與總債務與股數、租賃承諾。
A14: 損益 類損益表（FY26＝1H 實際＋下半年模型）。
... A42: DCF 以融資後股數計每股，並加回新股募得現金的現值；EV/EBITDA 用錨定年末淨負債與錨定年末股數。

Sheet 摘要
A1: 一頁摘要 — 結論、與市場的差異、現價隱含什麼、驗證點（全部依輸入連動）
A2: ="模型端＝目前情境：" & CHOOSE(輸入與假設!$C$5,"保守 只有已簽約","基準 加 NC-1 下一批","積極 NC-2／3 與 Krambu") & "（預設＝基準）；共識＝data/consensus_wyfi_20261008.json（2026-10-08）" -> 模型端＝目前情境：基準 加 NC-1 下一批（預設＝基準）；共識＝data/consensus_wyfi_20261008.json（2026-10-08）
A4: 1｜結論
A5: 結論｜評等代碼（1＝買進、0＝中立、−1＝賣出） | C5: =評價_DCF與目標價!C78 -> 0
A6: 結論｜評等 | C6: =CHOOSE(C5+2,"賣出","中立","買進") -> 中立
A7: 結論｜點位（加權目標價） | B7: US$ | C7: =評價_DCF與目標價!C51 -> 16.838649
A8: 結論｜現價 | B8: US$ | C8: =輸入與假設!$C$228 -> 16.83
A9: 結論｜空間 | B9: % | C9: =C7/C8-1 -> 0.00051390791
A10: 結論｜情境區間（下緣／上緣） | B10: US$ | C10: =評價_DCF與目標價!C83 -> 10.044175 | D10: =評價_DCF與目標價!D83 -> 34.655938
A11: 結論｜方法區間（下緣／上緣） | B11: US$ | C11: =評價_DCF與目標價!C85 -> 16.428437 | D11: =評價_DCF與目標價!D85 -> 16.838649
A12: 結論｜賣出門檻價 | B12: US$ | C12: =評價_DCF與目標價!$C$79 -> 14.3055
A13: 結論｜點位 − 賣出門檻 | B13: US$ | C13: =C7-C12 -> 2.5331491
A14: 結論｜結論句 | C14: =C6&"：點位 $"&TEXT(C7,"0.0")&"，較現價 $"&TEXT(C8,"0.00")&" "&IF(C9>=0,"高","低")&" "&TEXT(ABS(C9)*100,"0")&"%；情境區間 $"&TEXT(C10,"0.0")&"–$"&TEXT(D10,"0.0")&"，方法區間 $"&TEXT(C11,"0.0")&"–$"&TEXT(D11,"0.0")&"；點位"&IF(C13<0,"低於","高於")&"賣出門檻 $"&TEXT(C12,"0.0")&" 達 $"&TEXT(ABS(C13),"0.0")&"。" -> 中立：點位 $16.8，較現價 $16.83 高 0%；情境區間 $10.0–$34.7，方法區間 $16.4–$16.8；點位高於賣出門檻 $14.3 達 $2.5。
A15: 結論｜情境判斷句 | C15: =評價_DCF與目標價!C91 -> 情境區間上緣 $34.7 不低於現價 $16.83：賣出並非在三個擴張情境下都成立。
A16: 結論｜融資上限句 | C16: =IF(OR(輸入與假設!$C$199="ebitda",輸入與假設!$C$199="leaseAdj"),"超出可融資上限、需高息債的金額："&IF(SUM(各期收支!C87:G87)>50,"$"&TEXT(SUM(各期收支!C87:G87),"#,##0.0")&"m（五期高息債溢出）","$0")&"；債務上限＝"&IF(輸入與假設!$C$199="leaseAdj","(總債務＋租賃負債) ≤ "&IF(輸入與假設!$C$200=INT(輸入與假設!$C$200),TEXT(輸入與假設!$C$200,"0"),TEXT(輸入與假設!$C$200,"0.0"))&"×(EBITDA＋租金)","總債務 ≤ "&IF(輸入與假設!$C$200=INT(輸入與假設!$C$200),TEXT(輸入與假設!$C$200,"0"),TEXT(輸入與假設!$C$200,"0.0"))&"× 當期 EBITDA")&"，股權每年 ≤ 現市值 "&IF(ROUND(ABS(輸入與假設!$C$207)*100,4)=INT(ROUND(ABS(輸入與假設!$C$207)*100,4)),TEXT(ROUND(ABS(輸入與假設!$C$207)*100,4),"0"),TEXT(ROUND(ABS(輸入與假設!$C$207)*100,4),"0.0"))&"%"&"。","") -> 超出可融資上限、需高息債的金額：$0；債務上限＝總債務 ≤ 5× 當期 EBITDA，股權每年 ≤ 現市值 10%。
A17: 結論｜調整後槓桿句 | C17: =IF(輸入與假設!$C$199="leaseAdj","調整後槓桿（(債務＋租賃負債) ÷ (EBITDA＋租金)）路徑 "&TEXT(資產負債_新債與新股!C38,"0.0")&"／"&TEXT(資產負債_新債與新股!D38,"0.0")&"／"&TEXT(資產負債_新債與新股!E38,"0.0")&"／"&TEXT(資產負債_新債與新股!F38,"0.0")&"／"&TEXT(資產負債_新債與新股!G38,"0.0")&"×；上限 "&IF(輸入與假設!$C$200=INT(輸入與假設!$C$200),TEXT(輸入與假設!$C$200,"0"),TEXT(輸入與假設!$C$200,"0.0"))&"×，"&IF(MAX(資產負債_新債與新股!$C$38:$G$38)>輸入與假設!$C$200+0.000000001,CHOOSE(MATCH(MAX(資產負債_新債與新股!$C$38:$G$38),資產負債_新債與新股!$C$38:$G$38,0),"FY26","FY27","FY28","FY29","FY30")&" 超過 "&TEXT(MAX(資產負債_新債與新股!$C$38:$G$38)-輸入與假設!$C$200,"0.0")&"×：需股權或高息債。","最小空間 "&TEXT(輸入與假設!$C$200-MAX(資產負債_新債與新股!$C$38:$G$38),"0.0")&"×（"&CHOOSE(MATCH(MAX(資產負債_新債與新股!$C$38:$G$38),資產負債_新債與新股!$C$38:$G$38,0),"FY26","FY27","FY28","FY29","FY30")&"）。"),"總債務 ÷ EBITDA（年化）路徑 "&TEXT(資產負債_新債與新股!C40,"0.0")&"／"&TEXT(資產負債_新債與新股!D40,"0.0")&"／"&TEXT(資產負債_新債與新股!E40,"0.0")&"／"&TEXT(資產負債_新債與新股!F40,"0.0")&"／"&TEXT(資產負債_新債與新股!G40,"0.0")&"×；上限 "&IF(輸入與假設!$C$200=INT(輸入與假設!$C$200),TEXT(輸入與假設!$C$200,"0"),TEXT(輸入與假設!$C$200,"0.0"))&"×，"&IF(MAX(資產負債_新債與新股!$C$40:$G$40)>輸入與假設!$C$200+0.000000001,CHOOSE(MATCH(MAX(資產負債_新債與新股!$C$40:$G$40),資產負債_新債與新股!$C$40:$G$40,0),"FY26","FY27","FY28","FY29","FY30")&" 最高超過 "&TEXT(MAX(資產負債_新債與新股!$C$40:$G$40)-輸入與假設!$C$200,"0.0")&"×：超過期間新債只能動用已承諾額度，其餘靠可轉債、股權或高息債。","最小空間 "&TEXT(輸入與假設!$C$200-MAX(資產負債_新債與新股!$C$40:$G$40),"0.0")&"×（"&CHOOSE(MATCH(MAX(資產負債_新債與新股!$C$40:$G$40),資產負債_新債與新股!$C$40:$G$40,0),"FY26","FY27","FY28","FY29","FY30")&"）。")) -> 總債務 ÷ EBITDA（年化）路徑 37.1／29.2／8.6／5.1／3.6×；上限 5×，FY26 最高超過 32.1×：超過期間新債只能動用已承諾額度，其餘靠可轉債、股權或高息債。
A18: 結論｜延誤句 | C18: =IF(運營_產能與收入!$C$62>0,"建設延誤 "&IF(運營_產能與收入!$C$62=INT(運營_產能與收入!$C$62),TEXT(運營_產能與收入!$C$62,"0"),TEXT(運營_產能與收入!$C$62,"0.0"))&" 個月（GPU 資本支出照原時程）：閒置資本（已支出、尚未產生收入）峰值 $"&TEXT(MAX(運營_產能與收入!$C$67:$G$67),"#,##0.0")&"m（"&CHOOSE(MATCH(MAX(運營_產能與收入!$C$67:$G$67),運營_產能與收入!$C$67:$G$67,0),"FY26","FY27","FY28","FY29","FY30")&" 末）。","建設延誤：本情境 0 個月（無閒置資本）。") -> 建設延誤 3 個月（GPU 資本支出照原時程）：閒置資本（已支出、尚未產生收入）峰值 $61.7m（FY26 末）。
A20: 2｜與市場的差異（模型：目前情境 vs 共識；FY26–FY28）
A21: 項目 | B21: 單位 | C21: FY26 | D21: FY27 | E21: FY28
A22: 差異｜營收｜模型 | B22: US$m | C22: =損益!C29 -> 129.87243 | D22: =損益!D29 -> 278.16958 | E22: =損益!E29 -> 417.41242
A23: 差異｜營收｜共識 | B23: US$m | C23: =輸入與假設!$C$344 -> 137 | D23: =輸入與假設!$D$344 -> 296 | E23: =輸入與假設!$E$344 -> 530
A24: 差異｜營收｜差距 | B24: % | C24: =IFERROR(C22/C23-1,"—") -> -0.052026049 | D24: =IFERROR(D22/D23-1,"—") -> -0.060237895 | E24: =IFERROR(E22/E23-1,"—") -> -0.21242939
A25: 差異｜調整後 EBITDA｜模型 | B25: US$m | C25: =輸入與假設!$C$310+損益!C22 -> 14.748729 | D25: =損益!D34 -> 25.404783 | E25: =損益!E34 -> 90.266499
A26: 差異｜調整後 EBITDA｜共識 | B26: US$m | C26: ="—" -> — | D26: ="—" -> — | E26: ="—" -> —
A27: 差異｜調整後 EBITDA｜差距 | B27: % | C27: =IFERROR(C25/C26-1,"—") -> — | D27: =IFERROR(D25/D26-1,"—") -> — | E27: =IFERROR(E25/E26-1,"—") -> — | I27: FY26 模型＝1H 實際調整後 EBITDA（輸入與假設 G 區，報導轉述 [Verified]）＋2H 模型
A28: 差異｜調整後 EBITDA｜差距（金額） | B28: US$m | C28: =IFERROR(C25-C26,"—") -> — | D28: =IFERROR(D25-D26,"—") -> — | E28: =IFERROR(E25-E26,"—") -> — | I28: 與 HTML 一頁摘要、市場共識分頁同一呈現；判斷門檻仍用上一列比例
A29: 差異｜EBITDA 率｜模型 | B29: % | C29: =C25/C22 -> 0.1135632 | D29: =D25/D22 -> 0.091328401 | E29: =E25/E22 -> 0.21625254
A30: 差異｜EBITDA 率｜共識 | B30: % | C30: ="—" -> — | D30: ="—" -> — | E30: ="—" -> —
A31: 差異｜EBITDA 率｜差距（百分點） | B31: pt | C31: =IFERROR(C29-C30,"—") -> — | D31: =IFERROR(D29-D30,"—") -> — | E31: =IFERROR(E29-E30,"—") -> — | I31: EBITDA 率以百分點列差距，不納入判斷
A32: 差異｜CapEx（毛額）｜模型 | B32: US$m | C32: =輸入與假設!$C$293+輸入與假設!C$175 -> 491.69103 | D32: =輸入與假設!D$175 -> 427.14561 | E32: =輸入與假設!E$175 -> 56.385
A33: 差異｜CapEx（毛額）｜共識 | B33: US$m | C33: ="—" -> — | D33: ="—" -> — | E33: ="—" -> —
A34: 差異｜CapEx（毛額）｜差距 | B34: % | C34: =IFERROR(C32/C33-1,"—") -> — | D34: =IFERROR(D32/D33-1,"—") -> — | E34: =IFERROR(E32/E33-1,"—") -> — | I34: 共識 CapEx 口徑未揭露；FY26＝1H 實際毛額＋2H 模型毛額
A35: 差異｜淨負債｜模型 | B35: US$m | C35: =資產負債_新債與新股!C26 -> 324.46042 | D35: =資產負債_新債與新股!D26 -> 712.5112 | E35: =資產負債_新債與新股!E26 -> 749.1855
A36: 差異｜淨負債｜共識 | B36: US$m | C36: ="—" -> — | D36: ="—" -> — | E36: ="—" -> —
A37: 差異｜淨負債｜差距 | B37: % | C37: =IFERROR(C35/C36-1,"—") -> — | D37: =IFERROR(D35/D36-1,"—") -> — | E37: =IFERROR(E35/E36-1,"—") -> — | I37: 共識淨負債不含租賃、口徑未揭露：只列不判斷
A38: 差異｜淨負債｜差距（金額） | B38: US$m | C38: =IFERROR(C35-C36,"—") -> — | D38: =IFERROR(D35-D36,"—") -> — | E38: =IFERROR(E35-E36,"—") -> — | I38: 與 HTML 一頁摘要、市場共識分頁同一呈現；判斷門檻仍用上一列比例
A39: 差異｜分歧項目（超過門檻者） | C39: =MID(IF(ABS(C24)>輸入與假設!$C$367,"、營收 "&IF(C24<0,"−","+")&TEXT(ABS(C24)*100,"0.0")&"%",""),2,999) -> 營收 −5.2% | D39: =MID(IF(ABS(D24)>輸入與假設!$C$367,"、營收 "&IF(D24<0,"−","+")&TEXT(ABS(D24)*100,"0.0")&"%",""),2,999) -> 營收 −6.0% | E39: =MID(IF(ABS(E24)>輸入與假設!$C$367,"、營收 "&IF(E24<0,"−","+")&TEXT(ABS(E24)*100,"0.0")&"%",""),2,999) -> 營收 −21.2% | I39: 營收、EBITDA、CapEx 任一項差距絕對值超過門檻即列出（與 HTML 判斷句同一規則）
A40: 差異｜分歧起始年（1＝FY26…3＝FY28；0＝無） | C40: =IF(C39<>"",1,IF(D39<>"",2,IF(E39<>"",3,0))) -> 1
A41: 差異｜判斷句 | C41: =CHOOSE(C40+1,"FY26–FY28 營收 與共識差距皆在 "&IF(ROUND(ABS(輸入與假設!$C$367)*100,4)=INT(ROUND(ABS(輸入與假設!$C$367)*100,4)),TEXT(ROUND(ABS(輸入與假設!$C$367)*100,4),"0"),TEXT(ROUND(ABS(輸入與假設!$C$367)*100,4),"0.0"))&"%"&" 以內。","分歧始於 FY26（"&C39&"）"&"；FY27 "&IF(D39="","回到 "&IF(ROUND(ABS(輸入與假設!$C$367)*100,4)=INT(ROUND(ABS(輸入與假設!$C$367)*100,4)),TEXT(ROUND(ABS(輸入與假設!$C$367)*100,4),"0"),TEXT(ROUND(ABS(輸入與假設!$C$367)*100,4),"0.0"))&"%"&" 以內",D39)&"；FY28 "&IF(E39="","回到 "&IF(ROUND(ABS(輸入與假設!$C$367)*100,4)=INT(ROUND(ABS(輸入與假設!$C$367)*100,4)),TEXT(ROUND(ABS(輸入與假設!$C$367)*100,4),"0"),TEXT(ROUND(ABS(輸入與假設!$C$367)*100,4),"0.0"))&"%"&" 以內",E39)&"。","FY26 營收 與共識差距在 "&IF(ROUND(ABS(輸入與假設!$C$367)*100,4)=INT(ROUND(ABS(輸入與假設!$C$367)*100,4)),TEXT(ROUND(ABS(輸入與假設!$C$367)*100,4),"0"),TEXT(ROUND(ABS(輸入與假設!$C$367)*100,4),"0.0"))&"%"&" 以內；分歧始於 FY27（"&D39&"）"&"；FY28 "&IF(E39="","回到 "&IF(ROUND(ABS(輸入與假設!$C$367)*100,4)=INT(ROUND(ABS(輸入與假設!$C$367)*100,4)),TEXT(ROUND(ABS(輸入與假設!$C$367)*100,4),"0"),TEXT(ROUND(ABS(輸入與假設!$C$367)*100,4),"0.0"))&"%"&" 以內",E39)&"。","FY26–FY27 營收 與共識差距在 "&IF(ROUND(ABS(輸入與假設!$C$367)*100,4)=INT(ROUND(ABS(輸入與假設!$C$367)*100,4)),TEXT(ROUND(ABS(輸入與假設!$C$367)*100,4),"0"),TEXT(ROUND(ABS(輸入與假設!$C$367)*100,4),"0.0"))&"%"&" 以內；分歧始於 FY28（"&E39&"）。") -> 分歧始於 FY26（營收 −5.2%）；FY27 營收 −6.0%；FY28 營收 −21.2%。
A42: 差異原因｜FY26｜營收 | C42: =IF(ABS(C24)>輸入與假設!$C$367,"觀點","") -> 觀點 | D42: =IF(ABS(C24)>輸入與假設!$C$367,"營收＝雲端（在役 MW × 每 MW 年收入，Tokenomics 正向推導；年底已連網 "&IF((輸入與假設!C$43)<0,"−","")&TEXT(ABS((輸入與假設!C$43)),"#,##0.0")&" MW-IT）＋託管（已簽約合約排程與擴建）；共識未揭露 MW 與單價假設","") -> 營收＝雲端（在役 MW × 每 MW 年收入，Tokenomics 正向推導；年底已連網 14.6 MW-IT）＋託管（已簽約合約排程與擴建）；共識未揭露 MW 與單價假設 | I42: C＝類型、D＝原因（需附原因時顯示；EBITDA 以利潤率差、其餘以比例門檻判斷）
A43: 差異原因｜FY27｜營收 | C43: =IF(ABS(D24)>輸入與假設!$C$367,"觀點","") -> 觀點 | D43: =IF(ABS(D24)>輸入與假設!$C$367,"營收＝雲端（在役 MW × 每 MW 年收入，Tokenomics 正向推導；年底已連網 "&IF((輸入與假設!D$43)<0,"−","")&TEXT(ABS((輸入與假設!D$43)),"#,##0.0")&" MW-IT）＋託管（已簽約合約排程與擴建）；共識未揭露 MW 與單價假設","") -> 營收＝雲端（在役 MW × 每 MW 年收入，Tokenomics 正向推導；年底已連網 16.5 MW-IT）＋託管（已簽約合約排程與擴建）；共識未揭露 MW 與單價假設
A44: 差異原因｜FY28｜營收 | C44: =IF(ABS(E24)>輸入與假設!$C$367,"觀點","") -> 觀點 | D44: =IF(ABS(E24)>輸入與假設!$C$367,"營收＝雲端（在役 MW × 每 MW 年收入，Tokenomics 正向推導；年底已連網 "&IF((輸入與假設!E$43)<0,"−","")&TEXT(ABS((輸入與假設!E$43)),"#,##0.0")&" MW-IT）＋託管（已簽約合約排程與擴建）；共識未揭露 MW 與單價假設","") -> 營收＝雲端（在役 MW × 每 MW 年收入，Tokenomics 正向推導；年底已連網 19.5 MW-IT）＋託管（已簽約合約排程與擴建）；共識未揭露 MW 與單價假設
A45: 差異｜需附原因項數 | C45: =SUMPRODUCT(--(ABS(C24:E24)>輸入與假設!$C$367)) -> 3 | I45: 營收、EBITDA（利潤率差）、CapEx、淨負債 × FY26–FY28
A46: 差異｜差異原因摘要 | C46: =IF(C45=0,"","需附原因的 "&C45&" 項差距："&MID(IF((COUNTIF(C42,"觀點")+COUNTIF(C43,"觀點")+COUNTIF(C44,"觀點"))>0,"、觀點 "&(COUNTIF(C42,"觀點")+COUNTIF(C43,"觀點")+COUNTIF(C44,"觀點"))&" 項","")&IF((COUNTIF(C42,"拆法")+COUNTIF(C43,"拆法")+COUNTIF(C44,"拆法"))>0,"、拆法 "&(COUNTIF(C42,"拆法")+COUNTIF(C43,"拆法")+COUNTIF(C44,"拆法"))&" 項","")&IF((COUNTIF(C42,"已知限制")+COUNTIF(C43,"已知限制")+COUNTIF(C44,"已知限制"))>0,"、已知限制 "&(COUNTIF(C42,"已知限制")+COUNTIF(C43,"已知限制")+COUNTIF(C44,"已知限制"))&" 項","")&IF((C45-((COUNTIF(C42,"觀點")+COUNTIF(C43,"觀點")+COUNTIF(C44,"觀點"))+(COUNTIF(C42,"拆法")+COUNTIF(C43,"拆法")+COUNTIF(C44,"拆法"))+(COUNTIF(C42,"已知限制")+COUNTIF(C43,"已知限制")+COUNTIF(C44,"已知限制"))))>0,"、未歸類 "&(C45-((COUNTIF(C42,"觀點")+COUNTIF(C43,"觀點")+COUNTIF(C44,"觀點"))+(COUNTIF(C42,"拆法")+COUNTIF(C43,"拆法")+COUNTIF(C44,"拆法"))+(COUNTIF(C42,"已知限制")+COUNTIF(C43,"已知限制")+COUNTIF(C44,"已知限制"))))&" 項",""),2,999)&"；原因見「損益與評價 → 市場共識」。") -> 需附原因的 3 項差距：觀點 3 項；原因見「損益與評價 → 市場共識」。 | I46: 與 HTML 一頁摘要同一句
A48: 3｜現價隱含什麼
A49: 隱含｜共識平均目標價隱含 FY28 EV/EBITDA | B49: x | C49: ="—" -> — | I49: ＝（共識平均目標價 × 股數＋共識 FY28 淨負債）÷ 共識 FY28 調整後 EBITDA
A50: 隱含｜現價隱含 FY28 EV/EBITDA | B50: x | C50: ="—" -> — | I50: 同一共識 FY28 數字，價格換成現價
A51: 隱含｜模型方法區間上緣 | B51: x | C51: =MAX(輸入與假設!$C$258,輸入與假設!$C$259) -> 6 | I51: 模型 EV/EBITDA 腿（雲端 倍數）錨定 FY29 並折回 2027-06-30，錨定年度與此不同
A52: 隱含｜模型 FY28 託管 EBITDA | B52: US$m | C52: =輸入與假設!E$117 -> 88.573269 | I52: × 託管 EV/EBITDA 倍數，自共識隱含 EV 扣除
A53: 隱含｜共識平均目標價隱含 FY28 雲端 EV/EBITDA | B53: x | C53: ="—" -> — | I53: ＝（隱含 EV − 託管 EBITDA × 託管倍數）÷（共識 EBITDA − 託管 EBITDA）
A54: 隱含｜現價隱含 FY28 雲端 EV/EBITDA | B54: x | C54: ="—" -> — | I54: 同上，價格換成現價
A55: 隱含｜隱含倍數句 | C55: ="共識 FY28 調整後 EBITDA 未列：隱含倍數不適用（共識平均目標價 $"&TEXT(輸入與假設!$C$322,"0.00")&"、現價 $"&TEXT(輸入與假設!$C$228,"0.00")&"）。" -> 共識 FY28 調整後 EBITDA 未列：隱含倍數不適用（共識平均目標價 $38.00、現價 $16.83）。
A56: 反向 DCF｜FY30 每 MW 年收入（目前／隱含／變動） | C56: =評價_反向DCF!B18 -> 17.4 | D56: =評價_反向DCF!C18 -> 31.5283 | E56: =評價_反向DCF!D18 -> 0.812 | I56: 快照（預設輸入）：見『評價_反向DCF』；改輸入後請以目標搜尋重算
A57: 反向 DCF｜每 MW 建置成本（目前／隱含／變動） | C57: =評價_反向DCF!B19 -> 37.59 | D57: =評價_反向DCF!C19 -> 12.8425 | E57: =評價_反向DCF!D19 -> -0.6584
A58: 反向 DCF｜穩態 EBITDA 率（目前／隱含／變動 pt） | C58: =評價_反向DCF!B20 -> 0.47 | D58: =評價_反向DCF!C20 -> 0.8566 | E58: =評價_反向DCF!D20 -> 0.3866
A59: 反向 DCF｜加權目標價＝現價所需每 MW 年收入（目前／隱含／變動） | C59: =評價_反向DCF!B21 -> 17.4 | D59: =評價_反向DCF!C21 -> 17.3821 | E59: =評價_反向DCF!D21 -> -0.001
A61: 4｜驗證點與市場看法（賣方與管理層數字標記 Interested-party）
A62: 驗證｜焦點季 | C62: =季度追蹤!C12 -> Q3 2026 | I62: 『輸入與假設』J 區選擇；季度層由年度模型拆分，只用於追蹤
A63: 驗證｜營收（模型／共識／指引低／指引高／實際） | B63: US$m | C63: =季度追蹤!C6 -> 31.883144 | D63: =季度追蹤!D6 -> 不適用 | E63: =季度追蹤!F6 -> 不適用 | F63: =季度追蹤!G6 -> 不適用 | G63: =季度追蹤!I6 -> 待公布 | I63: 共識、指引為 Interested-party
A64: 驗證｜營收｜句 | C64: =INDEX(季度追蹤!$C$123:$H$123,輸入與假設!$C$373) -> 營收：模型 $31.9m
A65: 驗證｜調整後 EBITDA（模型／共識／指引低／指引高／實際） | B65: US$m | C65: =季度追蹤!C7 -> 2.4255511 | D65: =季度追蹤!D7 -> 不適用 | E65: =季度追蹤!F7 -> 不適用 | F65: =季度追蹤!G7 -> 不適用 | G65: =季度追蹤!I7 -> 待公布 | I65: 共識、指引為 Interested-party
A66: 驗證｜調整後 EBITDA｜句 | C66: =INDEX(季度追蹤!$C$124:$H$124,輸入與假設!$C$373) -> 調整後 EBITDA：模型 $2.4m
A67: 驗證｜CapEx（毛額）（模型／共識／指引低／指引高／實際） | B67: US$m | C67: =季度追蹤!C10 -> 73.489513 | D67: =季度追蹤!D10 -> 不適用 | E67: =季度追蹤!F10 -> 不適用 | F67: =季度追蹤!G10 -> 不適用 | G67: =季度追蹤!I10 -> 待公布 | I67: 共識、指引為 Interested-party
A68: 驗證｜CapEx（毛額）｜句 | C68: =INDEX(季度追蹤!$C$127:$H$127,輸入與假設!$C$373) -> CapEx（毛額）：模型 $73.5m
A69: 驗證｜評等分布（強力買進／買進／持有／賣出／強力賣出） | B69: 家 | C69: =輸入與假設!$C$337 -> 0 | D69: =輸入與假設!$C$338 -> 9 | E69: =輸入與假設!$C$339 -> 1 | F69: =輸入與假設!$C$340 -> 1 | G69: =輸入與假設!$C$341 -> 0 | I69: 2026-10，合計 11 家 [Interested-party]
A70: 驗證｜目標價（平均／中位數／最低／最高） | B70: US$ | C70: =輸入與假設!$C$322 -> 38 | D70: ="—" -> — | E70: =輸入與假設!$C$323 -> 32 | F70: =輸入與假設!$C$324 -> 50 | I70: 11 家；MarketBeat（自行彙整），擷取 2026-10-08 [Interested-party]
A72: 來源獨立性：Simply Wall St 的預估來自 S&P Global Market Intelligence；MarketBeat 目標價與評等為自行彙整（獨立於 S&P）；Investing.com 自行彙整；Yahoo 1 年目標價屬 LSEG 系；Tickflow 未具名來源。目標價四個呈現（MarketBeat 38.00、Investing 40.50、Yahoo 40.45、S&P 40.89）可視為至少三個獨立來源；營收預估只有 S&P（Simply Wall St）與 Tickflow 兩個呈現，FY2026 一致（137 vs 138），FY2027–28 差距大（296 vs 約 261；530 vs 約 381，Tickflow 為季度預估加總、家數 2–3），不算一致。
A73: 共識來源：Simply Wall St（S&P Global Market Intelligence）、MarketBeat（自行彙整）；擷取 2026-10-08。逐筆來源、日期與標記見『輸入與假設』I 區。

Sheet 輸入與假設
A1: 輸入（依類別排序；點左側 ＋／− 展開或收合。藍字可改；黃底為最關鍵假設）
A2: A 情境 → B 產能與收入 → C 利潤率 → D 支出（CapEx／折舊／租賃／JV）→ E 融資 → F 評價 → G 參考：1H26 實際 → H 情境區間運算表 → I 市場共識 → J 季度追蹤輸入。灰底『▸』為明細子區，預設收合
A4: A｜情境與規模（管理層擴張力道）
A5: 情境選擇（1＝保守 只有已簽約、2＝基準 加 NC-1 下一批、3＝積極 NC-2／3 與 Krambu） | C5: 2 | D5: =CHOOSE(C5,"保守 只有已簽約","基準 加 NC-1 下一批","積極 NC-2／3 與 Krambu") -> 基準 加 NC-1 下一批 | I5: 三情境改變擴張力道（已連網 MW 路徑）與每 MW 年收入（Tokenomics 正向推導三情境值）；其餘假設相同（對照表 r1 第 4 節第 1 條）
A6: ▸ 情境路徑明細（已連網 MW、在役比例、表外租金基準）
A7: 已連網 MW 路徑 | B7: 單位 | C7: FY26 | D7: FY27 | E7: FY28 | F7: FY29 | G7: FY30 | I7: FY31 新增 MW
A8: 首期期末已連網 MW（三情境共用） | B8: MW | C8: 14.574 | I8: 首期期末＝評價日已連網＋首期剩餘季度依最新季交付速度；推導與來源見 company.json → scenarios.mwPath.note [Derived]
A9: 保守 只有已簽約｜合約 MW 上限 | B9: MW | C9: 12.074 | D9: 14.048 | E9: 14.048 | F9: 14.048 | G9: 14.048 | I9: company.json → scenarios.mwPath.contracted
A10: 保守 只有已簽約｜併網速度 | B10: MW／年 | C10: 100 | I10: company.json → scenarios.mwPath.pace
A11: 保守 只有已簽約 | B11: MW | C11: =MIN(C9,輸入與假設!$C$8) -> 12.074 | D11: =MIN(D9,C11+輸入與假設!$C$10*D$41) -> 14.048 | E11: =MIN(E9,D11+輸入與假設!$C$10*E$41) -> 14.048 | F11: =MIN(F9,E11+輸入與假設!$C$10*F$41) -> 14.048 | G11: =MIN(G9,F11+輸入與假設!$C$10*G$41) -> 14.048 | I11: 0 | J11: 雲端只計已簽約 GPU 合約（不含尚無客戶的雪梨 2.5 MW）、合約到期以 Tokenomics 每 MW 續作；託管只有 NC-1 40 MW 與 MTL 現有站點；NC-1 專案融資未完成；延誤 6 個月；I 欄＝FY31 新增 MW
A12: 基準 加 NC-1 下一批｜合約 MW 上限 | B12: MW | C12: 14.574 | D12: 16.548 | E12: 19.548 | F12: 22.548 | G12: 25.548 | I12: company.json → scenarios.mwPath.contracted
A13: 基準 加 NC-1 下一批｜併網速度 | B13: MW／年 | C13: 100 | I13: company.json → scenarios.mwPath.pace
A14: 基準 加 NC-1 下一批 | B14: MW | C14: =MIN(C12,輸入與假設!$C$8) -> 14.574 | D14: =MIN(D12,C14+輸入與假設!$C$13*D$41) -> 16.548 | E14: =MIN(E12,D14+輸入與假設!$C$13*E$41) -> 19.548 | F14: =MIN(F12,E14+輸入與假設!$C$13*F$41) -> 22.548 | G14: =MIN(G12,F14+輸入與假設!$C$13*G$41) -> 25.548 | I14: 0 | J14: 雲端加雪梨 2.5 MW 與每年新增 3 MW-IT（2026 年新簽約約 8.6 MW-IT 的四分之一強）；託管加 NC-1 下一批 45 毛 MW（÷1.35 約 33 MW-IT）；NC-1 專案融資完成；延誤 3 個月；I 欄＝FY31 新增 MW
A15: 積極 NC-2／3 與 Krambu｜合約 MW 上限 | B15: MW | C15: 14.574 | D15: 16.548 | E15: 22.548 | F15: 28.548 | G15: 34.548 | I15: company.json → scenarios.mwPath.contracted
A16: 積極 NC-2／3 與 Krambu｜併網速度 | B16: MW／年 | C16: 100 | I16: company.json → scenarios.mwPath.pace
A17: 積極 NC-2／3 與 Krambu | B17: MW | C17: =MIN(C15,輸入與假設!$C$8) -> 14.574 | D17: =MIN(D15,C17+輸入與假設!$C$16*D$41) -> 16.548 | E17: =MIN(E15,D17+輸入與假設!$C$16*E$41) -> 22.548 | F17: =MIN(F15,E17+輸入與假設!$C$16*F$41) -> 28.548 | G17: =MIN(G15,F17+輸入與假設!$C$16*G$41) -> 34.548 | I17: 0 | J17: 雲端每年新增 6 MW-IT；託管再加 NC-2／3（60 毛 MW 起，2027 Q3）、NC-1 擴至長期毛容量、Krambu 100 MW（二手、口徑不明）；NC-1 專案融資完成；延誤 0；I 欄＝FY31 新增 MW
A18: 每 MW 年收入｜保守 只有已簽約 | B18: US$m/MW | C18: 11.62 | D18: 11.62 | E18: 11.62 | F18: 11.62 | G18: 11.62 | I18: Tokenomics 正向推導三情境（data/permw_tokenomics_20261008.json）；不用公司 ACV [Derived]
A19: 每 MW 年收入｜基準 加 NC-1 下一批 | B19: US$m/MW | C19: 17.4 | D19: 17.4 | E19: 17.4 | F19: 17.4 | G19: 17.4 | I19: Tokenomics 正向推導三情境（data/permw_tokenomics_20261008.json）；不用公司 ACV [Derived]
A20: 每 MW 年收入｜積極 NC-2／3 與 Krambu | B20: US$m/MW | C20: 24.2 | D20: 24.2 | E20: 24.2 | F20: 24.2 | G20: 24.2 | I20: Tokenomics 正向推導三情境（data/permw_tokenomics_20261008.json）；不用公司 ACV [Derived]
A21: 在役 MW 收斂比例（期初校準值 → 已連網） | B21: % | C21: 0.7 | D21: 0.85 | E21: 0.9 | F21: 0.9 | G21: 0.9 | I21: 期初可計費 MW＝2026 Q2 經常性雲端營收 11.506（23.806 扣終止費 12.3）× 4＝46.02 ÷ 各情境每 MW 年收入（保守 3.96／基準 2.65／積極 1.9 MW-IT），是對齊已實現實際數的校準，不是以公司目標反推（評價日已連網 5.5 MW 中實際計費當量較低：舊世代 H100 機隊單價低於 Tokenomics）。各期末可計費 MW＝期初校準值＋(已連網 − 期初校準值)× 收斂比例 70%／85%／90%／90%／90%（新合約 2026-07 至 2027 Q2 陸續起算，首期 70% [Assumed]）；小數 2 位（roundDp）。
A22: 期初可計費 MW 校準：Q2 2026 實際營收年化 | B22: US$m | C22: 46.024 | I22: 最新季實際營收 × 4（company.json → scenarios.billableRatio.openAnnualRevenue）[Derived]
A23: 期初可計費 MW｜保守 只有已簽約 | B23: MW | C23: =ROUND(輸入與假設!$C$22/C18,2) -> 3.96 | I23: ＝實際營收年化 ÷ 該情境每 MW 年收入（對齊已實現實際數的校準）
A24: 期初可計費 MW｜基準 加 NC-1 下一批 | B24: MW | C24: =ROUND(輸入與假設!$C$22/C19,2) -> 2.65 | I24: ＝實際營收年化 ÷ 該情境每 MW 年收入（對齊已實現實際數的校準）
A25: 期初可計費 MW｜積極 NC-2／3 與 Krambu | B25: MW | C25: =ROUND(輸入與假設!$C$22/C20,2) -> 1.9 | I25: ＝實際營收年化 ÷ 該情境每 MW 年收入（對齊已實現實際數的校準）
A26: 未起租租賃總額（未折現） | B26: US$m | C26: 20.296 | I26: 季報附註已簽約未起租租賃（company.json → leases.facts.notCommenced）[Interested-party]
A27: 未起租：評價日後第幾季開始起租（0＝首期第一季） | B27: 季 | C27: 1 | I27: company.json → leases.uncommenced.startQ
A28: 未起租：平均分攤起租的季數 | B28: 季 | C28: 1 | I28: 季報：FY27Q2 至 FY2029 起租 → 11 季 [Assumed]
A29: 未起租：每筆租期 | B29: 年 | C29: 4.916667 | I29: 季報 15–19 年取中點；敏感度 15／19 年見報告 [Assumed]
A30: B｜產能與收入（MW、每 MW 年收入、利用率、信用；RPO 只作對照）
A31: 6/30 RPO | B31: US$m | C31: 75.146 | I31: 季報 RPO 75.146（只作對照與債務上限的 backlog）[Interested-party]
A32: 評價日後新增承諾 | B32: US$m | C32: 0 | I32: 評價日後新簽、尚未進 RPO 的承諾；未揭露，取 0 [Assumed]
A33: 五期認列比例（至 2030 末） | B33: % | C33: 1 | I33: 季報 RPO 桶線性分攤後五期合計 100% [Derived]
A34: RPO 桶權重合計 | B34: % | C34: 1 | I34: 下方權重列的合計，用於歸一化
A35: 2025-12-31 主動電力 | B35: MW | C35: 5.5 | I35: 2025 年底雲端已連網 MW-IT：冰島第三方機房 5.5（10-Q；亞特蘭大 2026-02 起承租、加拿大 MW 未揭露）[Interested-party]
A36: 6/30 Billable MW | B36: MW | C36: =CHOOSE(輸入與假設!$C$5,輸入與假設!$C$23,輸入與假設!$C$24,輸入與假設!$C$25) -> 2.65 | I36: ＝依 A 區情境選擇器（以實際營收校準）
A37: 收入用平均在役 MW（1=是） | C37: 1 | I37: 0＝用期末存量全期化；建議 1
A38: 營收驅動（mw＝MW × 每 MW 年收入；rpo＝RPO 排程） | C38: mw | I38: mw：新產能簽約率固定 100%，營收＝容量上限；RPO 只作對照與產能瓶頸旗標（company.json → defaults.revenueDriver）
A39: 每 MW 年收入倍數（整體） | B39: % | C39: 1 | I39: 反向 DCF 與壓力測試用；預設 100%。以『目標搜尋』調整此格即可反解市價隱含單價
A40: 項目 | B40: 單位 | C40: FY26 | D40: FY27 | E40: FY28 | F40: FY29 | G40: FY30 | I40: 來源／標籤
A41: 模型期長度（年） | C41: 0.5 | D41: 1 | E41: 1 | F41: 1 | G41: 1 | I41: 勿改。由 calendar_q.py 推算；只用於容量上限、電力、維護等年率換算 [Derived]
A42: RPO 桶權重 | B42: % | C42: 0.2878 | D42: 0.575599 | E42: 0.136601 | F42: 0 | G42: 0 | H42: =SUM(C42:G42) -> 1 | I42: 季報 RPO 桶（雲端 RPO 75.1：2026 下半年 21.6、2027 43.3、2028 10.3（不含 7–8 月簽約的 Baseten、Prime VR200、冰島 B300 與巴黎）；託管 RPO 932.9 另列於託管分部；只作對照）桶內線性分攤 [Derived]
A43: Accepted MW（期末主動電力） | B43: MW | C43: =CHOOSE(輸入與假設!$C$5,C11,C14,C17) -> 14.574 | D43: =CHOOSE(輸入與假設!$C$5,D11,D14,D17) -> 16.548 | E43: =CHOOSE(輸入與假設!$C$5,E11,E14,E17) -> 19.548 | F43: =CHOOSE(輸入與假設!$C$5,F11,F14,F17) -> 22.548 | G43: =CHOOSE(輸入與假設!$C$5,G11,G14,G17) -> 25.548 | I43: ＝依 A 區情境選擇器（已連網 MW-IT）
A44: Billable MW | B44: MW | C44: =ROUND(輸入與假設!$C$36+(C43-輸入與假設!$C$36)*C21,2) -> 11 | D44: =ROUND(輸入與假設!$C$36+(D43-輸入與假設!$C$36)*D21,2) -> 14.46 | E44: =ROUND(輸入與假設!$C$36+(E43-輸入與假設!$C$36)*E21,2) -> 17.86 | F44: =ROUND(輸入與假設!$C$36+(F43-輸入與假設!$C$36)*F21,2) -> 20.56 | G44: =ROUND(輸入與假設!$C$36+(G43-輸入與假設!$C$36)*G21,2) -> 23.26 | I44: ＝期初校準值＋(已連網 − 期初校準值)× 收斂比例（A 區）
A45: 利用率 | B45: % | C45: 1 | D45: 1 | E45: 1 | F45: 1 | G45: 1 | I45: 100%：每 MW 年收入已含可計費利用率（路徑 B 80／85／90%），不重複扣除 [Derived]
A46: 每 MW 年收入 | B46: US$m/MW | C46: =CHOOSE(輸入與假設!$C$5,C18,C19,C20) -> 17.4 | D46: =CHOOSE(輸入與假設!$C$5,D18,D19,D20) -> 17.4 | E46: =CHOOSE(輸入與假設!$C$5,E18,E19,E20) -> 17.4 | F46: =CHOOSE(輸入與假設!$C$5,F18,F19,F20) -> 17.4 | G46: =CHOOSE(輸入與假設!$C$5,G18,G19,G20) -> 17.4 | I46: ＝依 A 區情境選擇器（Tokenomics 正向推導三情境）
A47: 新產能簽約率 | B47: % | C47: 1 | D47: 1 | E47: 1 | F47: 1 | G47: 1 | I47: MW 驅動：100%（RPO 只作對照）
A48: 客戶違約率 | B48: % | C48: 0.005 | D48: 0.01 | E48: 0.015 | F48: 0.02 | G48: 0.025 | I48: 客戶集中度的定價（company.json → texts.concentration），非預測 [Assumed]
A49: 回收率 | B49: % | C49: 0.5 | D49: 0.5 | E49: 0.5 | F49: 0.5 | G49: 0.5 | I49: [Assumed]
A50: 非算力服務營收 | B50: US$m | C50: 0 | D50: 0 | E50: 0 | F50: 0 | G50: 0 | I50: 預設 0：AI cloud 軟體已含在每 MW 年收入；其他事業另列 [Assumed]
A51: 其他事業 EBITDA | B51: US$m | C51: 0 | D51: 0 | E51: 0 | F51: 0 | G51: 0 | I51: 不適用（其他營收＝設備銷售型租賃利息，每季約 0.3，未建模；託管另列於託管分部）
A52: ▸ B2｜託管（各線全年營收＝上一財年 ×(1＋年增率)，年增率自起點線性收斂到長期值；FY26 模型期＝全年 − 1H 實際）
A53: ▸ 託管站點（MW 驅動：IT MW × 第一年租金 ×(1＋年調)^(期中點 − 起租) × 在租年數；建置 CapEx 依建置起訖分攤；建物 D&A 另列） | I53: 託管分部（v0.1b 步驟 3；另建 MW 驅動區塊，營收與 EBITDA 經由第二分部〔模板「託管」〕列進入損益、營運來源與分部 EV/EBITDA）：各站點營收＝IT MW × 第一年租金（US$m/MW-IT·年）×(1＋年調)^(期中點 − 起租) × 期間內在租年數；未簽約站點的起租時點隨建設延誤月數後移（delay＝1）；建置 CapEx 在建置起訖期間平均分攤（不隨延誤後移），進類現金流量與託管 PP&E；建物 D&A＝(期初託管 PP&E＋本期建置 × ½) ÷ 年限 × 期間長度，與 GPU 折舊分列。轉嫁電費以淨額處理（Nscale 合約 TCV 不含電費，不計入營收與成本；對照表 r1 第 4 節第 4 條）。期初託管 PP&E＝10-Q 託管設備帳面淨額（含 NC-1 在建）556.3；建物折舊 20 年（區間 15–30：10-K 30 年 vs 10-Q 20–25 年）[Assumed]。客戶預付覆蓋比同樣適用於託管建置 CapEx（coverPrepay；1H26 預付 72.6 ÷ 資本支出 344.7 的口徑含託管）。
A54: 託管｜期初時點（評價日起，年） | B54: 年 | C54: 0 | D54: 0.5 | E54: 1.5 | F54: 2.5 | G54: 3.5 | I54: 由 calendar_q.py 推算（勿改）
A55: 託管｜期末時點（評價日起，年） | B55: 年 | C55: 0.5 | D55: 1.5 | E55: 2.5 | F55: 3.5 | G55: 4.5 | I55: 由 calendar_q.py 推算（勿改）
A56: 託管｜NC-1 第一期 A（Nscale 20 MW）｜IT MW／起租（年）／第一年租金（US$m/MW）／年調／建置 CapEx（US$m） | C56: 20 | D56: 0.0833 | E56: 1.886 | F56: 0.03 | G56: 0 | I56: Nscale 10 年約 865／40 MW-IT／年調 3%：第 1 年等值 1.886 US$m/MW-IT·年（865 ÷ (40 × Σ1.03^t) [Derived]；NRC 未揭露，若 NRC>0 第 1 年更低）；2026 Q3 開始計費，前 20 MW 以 2026-08-01 起算（評價日後 0.083 年）[Interested-party／Assumed]；建置已完成（6/30 在建工程 484.6 含於託管期初 PP&E）
A57: 託管｜NC-1 第一期 A（Nscale 20 MW）｜建置起（年）／建置訖（年）／隨延誤後移／已簽約 | C57: 0 | D57: 0 | E57: 0 | F57: 1 | I57: 時點為評價日起的年數；隨延誤後移＝1 時起租加上建設延誤月數 ÷ 12（建置不後移）
A58: 託管｜NC-1 第一期 A（Nscale 20 MW）｜情境（保守／基準／積極；1＝納入） | C58: 1 | D58: 1 | E58: 1 | I58: 依『輸入與假設』A 區情境選擇器
A59: 託管｜NC-1 第一期 A（Nscale 20 MW）｜營收（模型期） | B59: US$m | C59: =CHOOSE(輸入與假設!$C$5,$C$58,$D$58,$E$58)*IF(C$55>MAX(C$54,($D$56+$E$57*運營_產能與收入!$C$62/12)),$C$56*$E$56*(1+$F$56)^((MAX(C$54,($D$56+$E$57*運營_產能與收入!$C$62/12))+C$55)/2-($D$56+$E$57*運營_產能與收入!$C$62/12))*(C$55-MAX(C$54,($D$56+$E$57*運營_產能與收入!$C$62/12))),0) -> 15.815023 | D59: =CHOOSE(輸入與假設!$C$5,$C$58,$D$58,$E$58)*IF(D$55>MAX(D$54,($D$56+$E$57*運營_產能與收入!$C$62/12)),$C$56*$E$56*(1+$F$56)^((MAX(D$54,($D$56+$E$57*運營_產能與收入!$C$62/12))+D$55)/2-($D$56+$E$57*運營_產能與收入!$C$62/12))*(D$55-MAX(D$54,($D$56+$E$57*運營_產能與收入!$C$62/12))),0) -> 38.756055 | E59: =CHOOSE(輸入與假設!$C$5,$C$58,$D$58,$E$58)*IF(E$55>MAX(E$54,($D$56+$E$57*運營_產能與收入!$C$62/12)),$C$56*$E$56*(1+$F$56)^((MAX(E$54,($D$56+$E$57*運營_產能與收入!$C$62/12))+E$55)/2-($D$56+$E$57*運營_產能與收入!$C$62/12))*(E$55-MAX(E$54,($D$56+$E$57*運營_產能與收入!$C$62/12))),0) -> 39.918737 | F59: =CHOOSE(輸入與假設!$C$5,$C$58,$D$58,$E$58)*IF(F$55>MAX(F$54,($D$56+$E$57*運營_產能與收入!$C$62/12)),$C$56*$E$56*(1+$F$56)^((MAX(F$54,($D$56+$E$57*運營_產能與收入!$C$62/12))+F$55)/2-($D$56+$E$57*運營_產能與收入!$C$62/12))*(F$55-MAX(F$54,($D$56+$E$57*運營_產能與收入!$C$62/12))),0) -> 41.116299 | G59: =CHOOSE(輸入與假設!$C$5,$C$58,$D$58,$E$58)*IF(G$55>MAX(G$54,($D$56+$E$57*運營_產能與收入!$C$62/12)),$C$56*$E$56*(1+$F$56)^((MAX(G$54,($D$56+$E$57*運營_產能與收入!$C$62/12))+G$55)/2-($D$56+$E$57*運營_產能與收入!$C$62/12))*(G$55-MAX(G$54,($D$56+$E$57*運營_產能與收入!$C$62/12))),0) -> 42.349788 | I59: ＝情境旗標 × MW × 第一年租金 ×(1＋年調)^(期中點 − 起租) × 期間內在租年數
A60: 託管｜NC-1 第一期 A（Nscale 20 MW）｜建置 CapEx（模型期） | B60: US$m | C60: =CHOOSE(輸入與假設!$C$5,$C$58,$D$58,$E$58)*IF($D$57>$C$57,$G$56*MAX(0,MIN(C$55,$D$57)-MAX(C$54,$C$57))/($D$57-$C$57),IF(OR(AND($C$57>=C$54,$C$57<C$55),$C$57<C$54),$G$56,0)) -> 0 | D60: =CHOOSE(輸入與假設!$C$5,$C$58,$D$58,$E$58)*IF($D$57>$C$57,$G$56*MAX(0,MIN(D$55,$D$57)-MAX(D$54,$C$57))/($D$57-$C$57),IF(OR(AND($C$57>=D$54,$C$57<D$55)),$G$56,0)) -> 0 | E60: =CHOOSE(輸入與假設!$C$5,$C$58,$D$58,$E$58)*IF($D$57>$C$57,$G$56*MAX(0,MIN(E$55,$D$57)-MAX(E$54,$C$57))/($D$57-$C$57),IF(OR(AND($C$57>=E$54,$C$57<E$55)),$G$56,0)) -> 0 | F60: =CHOOSE(輸入與假設!$C$5,$C$58,$D$58,$E$58)*IF($D$57>$C$57,$G$56*MAX(0,MIN(F$55,$D$57)-MAX(F$54,$C$57))/($D$57-$C$57),IF(OR(AND($C$57>=F$54,$C$57<F$55)),$G$56,0)) -> 0 | G60: =CHOOSE(輸入與假設!$C$5,$C$58,$D$58,$E$58)*IF($D$57>$C$57,$G$56*MAX(0,MIN(G$55,$D$57)-MAX(G$54,$C$57))/($D$57-$C$57),IF(OR(AND($C$57>=G$54,$C$57<G$55)),$G$56,0)) -> 0 | I60: ＝建置總額 × 建置期間落在本期的比例（不隨延誤後移）
A61: 託管｜NC-1 第一期 B（Nscale 20 MW）｜IT MW／起租（年）／第一年租金（US$m/MW）／年調／建置 CapEx（US$m） | C61: 20 | D61: 0.1667 | E61: 1.886 | F61: 0.03 | G61: 0 | I61: 同上；後 20 MW 於 8 月底全額計費（2026-09-01 起算，評價日後 0.167 年）[Interested-party]
A62: 託管｜NC-1 第一期 B（Nscale 20 MW）｜建置起（年）／建置訖（年）／隨延誤後移／已簽約 | C62: 0 | D62: 0 | E62: 0 | F62: 1 | I62: 時點為評價日起的年數；隨延誤後移＝1 時起租加上建設延誤月數 ÷ 12（建置不後移）
A63: 託管｜NC-1 第一期 B（Nscale 20 MW）｜情境（保守／基準／積極；1＝納入） | C63: 1 | D63: 1 | E63: 1 | I63: 依『輸入與假設』A 區情境選擇器
A64: 託管｜NC-1 第一期 B（Nscale 20 MW）｜營收（模型期） | B64: US$m | C64: =CHOOSE(輸入與假設!$C$5,$C$63,$D$63,$E$63)*IF(C$55>MAX(C$54,($D$61+$E$62*運營_產能與收入!$C$62/12)),$C$61*$E$61*(1+$F$61)^((MAX(C$54,($D$61+$E$62*運營_產能與收入!$C$62/12))+C$55)/2-($D$61+$E$62*運營_產能與收入!$C$62/12))*(C$55-MAX(C$54,($D$61+$E$62*運營_產能與收入!$C$62/12))),0) -> 12.634159 | D64: =CHOOSE(輸入與假設!$C$5,$C$63,$D$63,$E$63)*IF(D$55>MAX(D$54,($D$61+$E$62*運營_產能與收入!$C$62/12)),$C$61*$E$61*(1+$F$61)^((MAX(D$54,($D$61+$E$62*運營_產能與收入!$C$62/12))+D$55)/2-($D$61+$E$62*運營_產能與收入!$C$62/12))*(D$55-MAX(D$54,($D$61+$E$62*運營_產能與收入!$C$62/12))),0) -> 38.660631 | E64: =CHOOSE(輸入與假設!$C$5,$C$63,$D$63,$E$63)*IF(E$55>MAX(E$54,($D$61+$E$62*運營_產能與收入!$C$62/12)),$C$61*$E$61*(1+$F$61)^((MAX(E$54,($D$61+$E$62*運營_產能與收入!$C$62/12))+E$55)/2-($D$61+$E$62*運營_產能與收入!$C$62/12))*(E$55-MAX(E$54,($D$61+$E$62*運營_產能與收入!$C$62/12))),0) -> 39.82045 | F64: =CHOOSE(輸入與假設!$C$5,$C$63,$D$63,$E$63)*IF(F$55>MAX(F$54,($D$61+$E$62*運營_產能與收入!$C$62/12)),$C$61*$E$61*(1+$F$61)^((MAX(F$54,($D$61+$E$62*運營_產能與收入!$C$62/12))+F$55)/2-($D$61+$E$62*運營_產能與收入!$C$62/12))*(F$55-MAX(F$54,($D$61+$E$62*運營_產能與收入!$C$62/12))),0) -> 41.015064 | G64: =CHOOSE(輸入與假設!$C$5,$C$63,$D$63,$E$63)*IF(G$55>MAX(G$54,($D$61+$E$62*運營_產能與收入!$C$62/12)),$C$61*$E$61*(1+$F$61)^((MAX(G$54,($D$61+$E$62*運營_產能與收入!$C$62/12))+G$55)/2-($D$61+$E$62*運營_產能與收入!$C$62/12))*(G$55-MAX(G$54,($D$61+$E$62*運營_產能與收入!$C$62/12))),0) -> 42.245516 | I64: ＝情境旗標 × MW × 第一年租金 ×(1＋年調)^(期中點 − 起租) × 期間內在租年數
A65: 託管｜NC-1 第一期 B（Nscale 20 MW）｜建置 CapEx（模型期） | B65: US$m | C65: =CHOOSE(輸入與假設!$C$5,$C$63,$D$63,$E$63)*IF($D$62>$C$62,$G$61*MAX(0,MIN(C$55,$D$62)-MAX(C$54,$C$62))/($D$62-$C$62),IF(OR(AND($C$62>=C$54,$C$62<C$55),$C$62<C$54),$G$61,0)) -> 0 | D65: =CHOOSE(輸入與假設!$C$5,$C$63,$D$63,$E$63)*IF($D$62>$C$62,$G$61*MAX(0,MIN(D$55,$D$62)-MAX(D$54,$C$62))/($D$62-$C$62),IF(OR(AND($C$62>=D$54,$C$62<D$55)),$G$61,0)) -> 0 | E65: =CHOOSE(輸入與假設!$C$5,$C$63,$D$63,$E$63)*IF($D$62>$C$62,$G$61*MAX(0,MIN(E$55,$D$62)-MAX(E$54,$C$62))/($D$62-$C$62),IF(OR(AND($C$62>=E$54,$C$62<E$55)),$G$61,0)) -> 0 | F65: =CHOOSE(輸入與假設!$C$5,$C$63,$D$63,$E$63)*IF($D$62>$C$62,$G$61*MAX(0,MIN(F$55,$D$62)-MAX(F$54,$C$62))/($D$62-$C$62),IF(OR(AND($C$62>=F$54,$C$62<F$55)),$G$61,0)) -> 0 | G65: =CHOOSE(輸入與假設!$C$5,$C$63,$D$63,$E$63)*IF($D$62>$C$62,$G$61*MAX(0,MIN(G$55,$D$62)-MAX(G$54,$C$62))/($D$62-$C$62),IF(OR(AND($C$62>=G$54,$C$62<G$55)),$G$61,0)) -> 0 | I65: ＝建置總額 × 建置期間落在本期的比例（不隨延誤後移）
A66: 託管｜MTL-3（Cerebras 5 MW）｜IT MW／起租（年）／第一年租金（US$m/MW）／年調／建置 CapEx（US$m） | C66: 5 | D66: -0.6667 | E66: 2.35 | F66: 0 | G66: 0 | I66: Cerebras 5 年約、每月 CAD 1.4（約 USD 0.979）＝11.75／年 ÷ 5 MW-IT＝2.35；2025-11 起計費；年調未揭露，取 0 [Interested-party]
A67: 託管｜MTL-3（Cerebras 5 MW）｜建置起（年）／建置訖（年）／隨延誤後移／已簽約 | C67: 0 | D67: 0 | E67: 0 | F67: 1 | I67: 時點為評價日起的年數；隨延誤後移＝1 時起租加上建設延誤月數 ÷ 12（建置不後移）
A68: 託管｜MTL-3（Cerebras 5 MW）｜情境（保守／基準／積極；1＝納入） | C68: 1 | D68: 1 | E68: 1 | I68: 依『輸入與假設』A 區情境選擇器
A69: 託管｜MTL-3（Cerebras 5 MW）｜營收（模型期） | B69: US$m | C69: =CHOOSE(輸入與假設!$C$5,$C$68,$D$68,$E$68)*IF(C$55>MAX(C$54,($D$66+$E$67*運營_產能與收入!$C$62/12)),$C$66*$E$66*(1+$F$66)^((MAX(C$54,($D$66+$E$67*運營_產能與收入!$C$62/12))+C$55)/2-($D$66+$E$67*運營_產能與收入!$C$62/12))*(C$55-MAX(C$54,($D$66+$E$67*運營_產能與收入!$C$62/12))),0) -> 5.875 | D69: =CHOOSE(輸入與假設!$C$5,$C$68,$D$68,$E$68)*IF(D$55>MAX(D$54,($D$66+$E$67*運營_產能與收入!$C$62/12)),$C$66*$E$66*(1+$F$66)^((MAX(D$54,($D$66+$E$67*運營_產能與收入!$C$62/12))+D$55)/2-($D$66+$E$67*運營_產能與收入!$C$62/12))*(D$55-MAX(D$54,($D$66+$E$67*運營_產能與收入!$C$62/12))),0) -> 11.75 | E69: =CHOOSE(輸入與假設!$C$5,$C$68,$D$68,$E$68)*IF(E$55>MAX(E$54,($D$66+$E$67*運營_產能與收入!$C$62/12)),$C$66*$E$66*(1+$F$66)^((MAX(E$54,($D$66+$E$67*運營_產能與收入!$C$62/12))+E$55)/2-($D$66+$E$67*運營_產能與收入!$C$62/12))*(E$55-MAX(E$54,($D$66+$E$67*運營_產能與收入!$C$62/12))),0) -> 11.75 | F69: =CHOOSE(輸入與假設!$C$5,$C$68,$D$68,$E$68)*IF(F$55>MAX(F$54,($D$66+$E$67*運營_產能與收入!$C$62/12)),$C$66*$E$66*(1+$F$66)^((MAX(F$54,($D$66+$E$67*運營_產能與收入!$C$62/12))+F$55)/2-($D$66+$E$67*運營_產能與收入!$C$62/12))*(F$55-MAX(F$54,($D$66+$E$67*運營_產能與收入!$C$62/12))),0) -> 11.75 | G69: =CHOOSE(輸入與假設!$C$5,$C$68,$D$68,$E$68)*IF(G$55>MAX(G$54,($D$66+$E$67*運營_產能與收入!$C$62/12)),$C$66*$E$66*(1+$F$66)^((MAX(G$54,($D$66+$E$67*運營_產能與收入!$C$62/12))+G$55)/2-($D$66+$E$67*運營_產能與收入!$C$62/12))*(G$55-MAX(G$54,($D$66+$E$67*運營_產能與收入!$C$62/12))),0) -> 11.75 | I69: ＝情境旗標 × MW × 第一年租金 ×(1＋年調)^(期中點 − 起租) × 期間內在租年數
A70: 託管｜MTL-3（Cerebras 5 MW）｜建置 CapEx（模型期） | B70: US$m | C70: =CHOOSE(輸入與假設!$C$5,$C$68,$D$68,$E$68)*IF($D$67>$C$67,$G$66*MAX(0,MIN(C$55,$D$67)-MAX(C$54,$C$67))/($D$67-$C$67),IF(OR(AND($C$67>=C$54,$C$67<C$55),$C$67<C$54),$G$66,0)) -> 0 | D70: =CHOOSE(輸入與假設!$C$5,$C$68,$D$68,$E$68)*IF($D$67>$C$67,$G$66*MAX(0,MIN(D$55,$D$67)-MAX(D$54,$C$67))/($D$67-$C$67),IF(OR(AND($C$67>=D$54,$C$67<D$55)),$G$66,0)) -> 0 | E70: =CHOOSE(輸入與假設!$C$5,$C$68,$D$68,$E$68)*IF($D$67>$C$67,$G$66*MAX(0,MIN(E$55,$D$67)-MAX(E$54,$C$67))/($D$67-$C$67),IF(OR(AND($C$67>=E$54,$C$67<E$55)),$G$66,0)) -> 0 | F70: =CHOOSE(輸入與假設!$C$5,$C$68,$D$68,$E$68)*IF($D$67>$C$67,$G$66*MAX(0,MIN(F$55,$D$67)-MAX(F$54,$C$67))/($D$67-$C$67),IF(OR(AND($C$67>=F$54,$C$67<F$55)),$G$66,0)) -> 0 | G70: =CHOOSE(輸入與假設!$C$5,$C$68,$D$68,$E$68)*IF($D$67>$C$67,$G$66*MAX(0,MIN(G$55,$D$67)-MAX(G$54,$C$67))/($D$67-$C$67),IF(OR(AND($C$67>=G$54,$C$67<G$55)),$G$66,0)) -> 0 | I70: ＝建置總額 × 建置期間落在本期的比例（不隨延誤後移）
A71: 託管｜MTL-1（3 MW，14 家客戶）｜IT MW／起租（年）／第一年租金（US$m/MW）／年調／建置 CapEx（US$m） | C71: 3 | D71: -5.5 | E71: 2.38 | F71: 0 | G71: 0 | I71: 100% 已簽約、平均合約約 2.5 年；每 MW 2.38＝(Q2 託管營收 4.726 − MTL-3 2.94) × 4 ÷ 3 [Derived]；到期以同價續約 [Assumed]
A72: 託管｜MTL-1（3 MW，14 家客戶）｜建置起（年）／建置訖（年）／隨延誤後移／已簽約 | C72: 0 | D72: 0 | E72: 0 | F72: 1 | I72: 時點為評價日起的年數；隨延誤後移＝1 時起租加上建設延誤月數 ÷ 12（建置不後移）
A73: 託管｜MTL-1（3 MW，14 家客戶）｜情境（保守／基準／積極；1＝納入） | C73: 1 | D73: 1 | E73: 1 | I73: 依『輸入與假設』A 區情境選擇器
A74: 託管｜MTL-1（3 MW，14 家客戶）｜營收（模型期） | B74: US$m | C74: =CHOOSE(輸入與假設!$C$5,$C$73,$D$73,$E$73)*IF(C$55>MAX(C$54,($D$71+$E$72*運營_產能與收入!$C$62/12)),$C$71*$E$71*(1+$F$71)^((MAX(C$54,($D$71+$E$72*運營_產能與收入!$C$62/12))+C$55)/2-($D$71+$E$72*運營_產能與收入!$C$62/12))*(C$55-MAX(C$54,($D$71+$E$72*運營_產能與收入!$C$62/12))),0) -> 3.57 | D74: =CHOOSE(輸入與假設!$C$5,$C$73,$D$73,$E$73)*IF(D$55>MAX(D$54,($D$71+$E$72*運營_產能與收入!$C$62/12)),$C$71*$E$71*(1+$F$71)^((MAX(D$54,($D$71+$E$72*運營_產能與收入!$C$62/12))+D$55)/2-($D$71+$E$72*運營_產能與收入!$C$62/12))*(D$55-MAX(D$54,($D$71+$E$72*運營_產能與收入!$C$62/12))),0) -> 7.14 | E74: =CHOOSE(輸入與假設!$C$5,$C$73,$D$73,$E$73)*IF(E$55>MAX(E$54,($D$71+$E$72*運營_產能與收入!$C$62/12)),$C$71*$E$71*(1+$F$71)^((MAX(E$54,($D$71+$E$72*運營_產能與收入!$C$62/12))+E$55)/2-($D$71+$E$72*運營_產能與收入!$C$62/12))*(E$55-MAX(E$54,($D$71+$E$72*運營_產能與收入!$C$62/12))),0) -> 7.14 | F74: =CHOOSE(輸入與假設!$C$5,$C$73,$D$73,$E$73)*IF(F$55>MAX(F$54,($D$71+$E$72*運營_產能與收入!$C$62/12)),$C$71*$E$71*(1+$F$71)^((MAX(F$54,($D$71+$E$72*運營_產能與收入!$C$62/12))+F$55)/2-($D$71+$E$72*運營_產能與收入!$C$62/12))*(F$55-MAX(F$54,($D$71+$E$72*運營_產能與收入!$C$62/12))),0) -> 7.14 | G74: =CHOOSE(輸入與假設!$C$5,$C$73,$D$73,$E$73)*IF(G$55>MAX(G$54,($D$71+$E$72*運營_產能與收入!$C$62/12)),$C$71*$E$71*(1+$F$71)^((MAX(G$54,($D$71+$E$72*運營_產能與收入!$C$62/12))+G$55)/2-($D$71+$E$72*運營_產能與收入!$C$62/12))*(G$55-MAX(G$54,($D$71+$E$72*運營_產能與收入!$C$62/12))),0) -> 7.14 | I74: ＝情境旗標 × MW × 第一年租金 ×(1＋年調)^(期中點 − 起租) × 期間內在租年數
A75: 託管｜MTL-1（3 MW，14 家客戶）｜建置 CapEx（模型期） | B75: US$m | C75: =CHOOSE(輸入與假設!$C$5,$C$73,$D$73,$E$73)*IF($D$72>$C$72,$G$71*MAX(0,MIN(C$55,$D$72)-MAX(C$54,$C$72))/($D$72-$C$72),IF(OR(AND($C$72>=C$54,$C$72<C$55),$C$72<C$54),$G$71,0)) -> 0 | D75: =CHOOSE(輸入與假設!$C$5,$C$73,$D$73,$E$73)*IF($D$72>$C$72,$G$71*MAX(0,MIN(D$55,$D$72)-MAX(D$54,$C$72))/($D$72-$C$72),IF(OR(AND($C$72>=D$54,$C$72<D$55)),$G$71,0)) -> 0 | E75: =CHOOSE(輸入與假設!$C$5,$C$73,$D$73,$E$73)*IF($D$72>$C$72,$G$71*MAX(0,MIN(E$55,$D$72)-MAX(E$54,$C$72))/($D$72-$C$72),IF(OR(AND($C$72>=E$54,$C$72<E$55)),$G$71,0)) -> 0 | F75: =CHOOSE(輸入與假設!$C$5,$C$73,$D$73,$E$73)*IF($D$72>$C$72,$G$71*MAX(0,MIN(F$55,$D$72)-MAX(F$54,$C$72))/($D$72-$C$72),IF(OR(AND($C$72>=F$54,$C$72<F$55)),$G$71,0)) -> 0 | G75: =CHOOSE(輸入與假設!$C$5,$C$73,$D$73,$E$73)*IF($D$72>$C$72,$G$71*MAX(0,MIN(G$55,$D$72)-MAX(G$54,$C$72))/($D$72-$C$72),IF(OR(AND($C$72>=G$54,$C$72<G$55)),$G$71,0)) -> 0 | I75: ＝建置總額 × 建置期間落在本期的比例（不隨延誤後移）
A76: 託管｜MTL-2（3 MW-IT，2026 年底）｜IT MW／起租（年）／第一年租金（US$m/MW）／年調／建置 CapEx（US$m） | C76: 3 | D76: 0.5 | E76: 1.85 | F76: 0.03 | G76: 23.6 | I76: 5 毛／3 IT；2026 Q3 啟動初期施工、目標 2026 年底完工；建置估 23.6（10-Q）；客戶未定 → 租金取可比區間中點 1.85 [Analogy]；保守情境不納入（未簽約）
A77: 託管｜MTL-2（3 MW-IT，2026 年底）｜建置起（年）／建置訖（年）／隨延誤後移／已簽約 | C77: 0 | D77: 0.5 | E77: 1 | F77: 0 | I77: 時點為評價日起的年數；隨延誤後移＝1 時起租加上建設延誤月數 ÷ 12（建置不後移）
A78: 託管｜MTL-2（3 MW-IT，2026 年底）｜情境（保守／基準／積極；1＝納入） | C78: 0 | D78: 1 | E78: 1 | I78: 依『輸入與假設』A 區情境選擇器
A79: 託管｜MTL-2（3 MW-IT，2026 年底）｜營收（模型期） | B79: US$m | C79: =CHOOSE(輸入與假設!$C$5,$C$78,$D$78,$E$78)*IF(C$55>MAX(C$54,($D$76+$E$77*運營_產能與收入!$C$62/12)),$C$76*$E$76*(1+$F$76)^((MAX(C$54,($D$76+$E$77*運營_產能與收入!$C$62/12))+C$55)/2-($D$76+$E$77*運營_產能與收入!$C$62/12))*(C$55-MAX(C$54,($D$76+$E$77*運營_產能與收入!$C$62/12))),0) -> 0 | D79: =CHOOSE(輸入與假設!$C$5,$C$78,$D$78,$E$78)*IF(D$55>MAX(D$54,($D$76+$E$77*運營_產能與收入!$C$62/12)),$C$76*$E$76*(1+$F$76)^((MAX(D$54,($D$76+$E$77*運營_產能與收入!$C$62/12))+D$55)/2-($D$76+$E$77*運營_產能與收入!$C$62/12))*(D$55-MAX(D$54,($D$76+$E$77*運營_產能與收入!$C$62/12))),0) -> 4.2088961 | E79: =CHOOSE(輸入與假設!$C$5,$C$78,$D$78,$E$78)*IF(E$55>MAX(E$54,($D$76+$E$77*運營_產能與收入!$C$62/12)),$C$76*$E$76*(1+$F$76)^((MAX(E$54,($D$76+$E$77*運營_產能與收入!$C$62/12))+E$55)/2-($D$76+$E$77*運營_產能與收入!$C$62/12))*(E$55-MAX(E$54,($D$76+$E$77*運營_產能與收入!$C$62/12))),0) -> 5.7588997 | F79: =CHOOSE(輸入與假設!$C$5,$C$78,$D$78,$E$78)*IF(F$55>MAX(F$54,($D$76+$E$77*運營_產能與收入!$C$62/12)),$C$76*$E$76*(1+$F$76)^((MAX(F$54,($D$76+$E$77*運營_產能與收入!$C$62/12))+F$55)/2-($D$76+$E$77*運營_產能與收入!$C$62/12))*(F$55-MAX(F$54,($D$76+$E$77*運營_產能與收入!$C$62/12))),0) -> 5.9316667 | G79: =CHOOSE(輸入與假設!$C$5,$C$78,$D$78,$E$78)*IF(G$55>MAX(G$54,($D$76+$E$77*運營_產能與收入!$C$62/12)),$C$76*$E$76*(1+$F$76)^((MAX(G$54,($D$76+$E$77*運營_產能與收入!$C$62/12))+G$55)/2-($D$76+$E$77*運營_產能與收入!$C$62/12))*(G$55-MAX(G$54,($D$76+$E$77*運營_產能與收入!$C$62/12))),0) -> 6.1096167 | I79: ＝情境旗標 × MW × 第一年租金 ×(1＋年調)^(期中點 − 起租) × 期間內在租年數
A80: 託管｜MTL-2（3 MW-IT，2026 年底）｜建置 CapEx（模型期） | B80: US$m | C80: =CHOOSE(輸入與假設!$C$5,$C$78,$D$78,$E$78)*IF($D$77>$C$77,$G$76*MAX(0,MIN(C$55,$D$77)-MAX(C$54,$C$77))/($D$77-$C$77),IF(OR(AND($C$77>=C$54,$C$77<C$55),$C$77<C$54),$G$76,0)) -> 23.6 | D80: =CHOOSE(輸入與假設!$C$5,$C$78,$D$78,$E$78)*IF($D$77>$C$77,$G$76*MAX(0,MIN(D$55,$D$77)-MAX(D$54,$C$77))/($D$77-$C$77),IF(OR(AND($C$77>=D$54,$C$77<D$55)),$G$76,0)) -> 0 | E80: =CHOOSE(輸入與假設!$C$5,$C$78,$D$78,$E$78)*IF($D$77>$C$77,$G$76*MAX(0,MIN(E$55,$D$77)-MAX(E$54,$C$77))/($D$77-$C$77),IF(OR(AND($C$77>=E$54,$C$77<E$55)),$G$76,0)) -> 0 | F80: =CHOOSE(輸入與假設!$C$5,$C$78,$D$78,$E$78)*IF($D$77>$C$77,$G$76*MAX(0,MIN(F$55,$D$77)-MAX(F$54,$C$77))/($D$77-$C$77),IF(OR(AND($C$77>=F$54,$C$77<F$55)),$G$76,0)) -> 0 | G80: =CHOOSE(輸入與假設!$C$5,$C$78,$D$78,$E$78)*IF($D$77>$C$77,$G$76*MAX(0,MIN(G$55,$D$77)-MAX(G$54,$C$77))/($D$77-$C$77),IF(OR(AND($C$77>=G$54,$C$77<G$55)),$G$76,0)) -> 0 | I80: ＝建置總額 × 建置期間落在本期的比例（不隨延誤後移）
A81: 託管｜NC-1 下一批（45 毛 MW ÷ 1.35）｜IT MW／起租（年）／第一年租金（US$m/MW）／年調／建置 CapEx（US$m） | C81: 33.33 | D81: 1.5 | E81: 1.85 | F81: 0.03 | G81: 383.295 | I81: Duke 容量協議下一批 45 毛 MW（÷1.35＝33.33 MW-IT；Nscale 有優先權）；2028-01 起租（評價日後 1.5 年，對照表「2027–28 起租」）；租金 1.85（可比區間中點 [Analogy]）；建置 11.5／MW-IT（區間 9.0–13.5 [Analogy]）於 2027 年支出
A82: 託管｜NC-1 下一批（45 毛 MW ÷ 1.35）｜建置起（年）／建置訖（年）／隨延誤後移／已簽約 | C82: 0.5 | D82: 1.5 | E82: 1 | F82: 0 | I82: 時點為評價日起的年數；隨延誤後移＝1 時起租加上建設延誤月數 ÷ 12（建置不後移）
A83: 託管｜NC-1 下一批（45 毛 MW ÷ 1.35）｜情境（保守／基準／積極；1＝納入） | C83: 0 | D83: 1 | E83: 1 | I83: 依『輸入與假設』A 區情境選擇器
A84: 託管｜NC-1 下一批（45 毛 MW ÷ 1.35）｜營收（模型期） | B84: US$m | C84: =CHOOSE(輸入與假設!$C$5,$C$83,$D$83,$E$83)*IF(C$55>MAX(C$54,($D$81+$E$82*運營_產能與收入!$C$62/12)),$C$81*$E$81*(1+$F$81)^((MAX(C$54,($D$81+$E$82*運營_產能與收入!$C$62/12))+C$55)/2-($D$81+$E$82*運營_產能與收入!$C$62/12))*(C$55-MAX(C$54,($D$81+$E$82*運營_產能與收入!$C$62/12))),0) -> 0 | D84: =CHOOSE(輸入與假設!$C$5,$C$83,$D$83,$E$83)*IF(D$55>MAX(D$54,($D$81+$E$82*運營_產能與收入!$C$62/12)),$C$81*$E$81*(1+$F$81)^((MAX(D$54,($D$81+$E$82*運營_產能與收入!$C$62/12))+D$55)/2-($D$81+$E$82*運營_產能與收入!$C$62/12))*(D$55-MAX(D$54,($D$81+$E$82*運營_產能與收入!$C$62/12))),0) -> 0 | E84: =CHOOSE(輸入與假設!$C$5,$C$83,$D$83,$E$83)*IF(E$55>MAX(E$54,($D$81+$E$82*運營_產能與收入!$C$62/12)),$C$81*$E$81*(1+$F$81)^((MAX(E$54,($D$81+$E$82*運營_產能與收入!$C$62/12))+E$55)/2-($D$81+$E$82*運營_產能與收入!$C$62/12))*(E$55-MAX(E$54,($D$81+$E$82*運營_產能與收入!$C$62/12))),0) -> 46.760836 | F84: =CHOOSE(輸入與假設!$C$5,$C$83,$D$83,$E$83)*IF(F$55>MAX(F$54,($D$81+$E$82*運營_產能與收入!$C$62/12)),$C$81*$E$81*(1+$F$81)^((MAX(F$54,($D$81+$E$82*運營_產能與收入!$C$62/12))+F$55)/2-($D$81+$E$82*運營_產能與收入!$C$62/12))*(F$55-MAX(F$54,($D$81+$E$82*運營_產能與收入!$C$62/12))),0) -> 63.981376 | G84: =CHOOSE(輸入與假設!$C$5,$C$83,$D$83,$E$83)*IF(G$55>MAX(G$54,($D$81+$E$82*運營_產能與收入!$C$62/12)),$C$81*$E$81*(1+$F$81)^((MAX(G$54,($D$81+$E$82*運營_產能與收入!$C$62/12))+G$55)/2-($D$81+$E$82*運營_產能與收入!$C$62/12))*(G$55-MAX(G$54,($D$81+$E$82*運營_產能與收入!$C$62/12))),0) -> 65.900817 | I84: ＝情境旗標 × MW × 第一年租金 ×(1＋年調)^(期中點 − 起租) × 期間內在租年數
A85: 託管｜NC-1 下一批（45 毛 MW ÷ 1.35）｜建置 CapEx（模型期） | B85: US$m | C85: =CHOOSE(輸入與假設!$C$5,$C$83,$D$83,$E$83)*IF($D$82>$C$82,$G$81*MAX(0,MIN(C$55,$D$82)-MAX(C$54,$C$82))/($D$82-$C$82),IF(OR(AND($C$82>=C$54,$C$82<C$55),$C$82<C$54),$G$81,0)) -> 0 | D85: =CHOOSE(輸入與假設!$C$5,$C$83,$D$83,$E$83)*IF($D$82>$C$82,$G$81*MAX(0,MIN(D$55,$D$82)-MAX(D$54,$C$82))/($D$82-$C$82),IF(OR(AND($C$82>=D$54,$C$82<D$55)),$G$81,0)) -> 383.295 | E85: =CHOOSE(輸入與假設!$C$5,$C$83,$D$83,$E$83)*IF($D$82>$C$82,$G$81*MAX(0,MIN(E$55,$D$82)-MAX(E$54,$C$82))/($D$82-$C$82),IF(OR(AND($C$82>=E$54,$C$82<E$55)),$G$81,0)) -> 0 | F85: =CHOOSE(輸入與假設!$C$5,$C$83,$D$83,$E$83)*IF($D$82>$C$82,$G$81*MAX(0,MIN(F$55,$D$82)-MAX(F$54,$C$82))/($D$82-$C$82),IF(OR(AND($C$82>=F$54,$C$82<F$55)),$G$81,0)) -> 0 | G85: =CHOOSE(輸入與假設!$C$5,$C$83,$D$83,$E$83)*IF($D$82>$C$82,$G$81*MAX(0,MIN(G$55,$D$82)-MAX(G$54,$C$82))/($D$82-$C$82),IF(OR(AND($C$82>=G$54,$C$82<G$55)),$G$81,0)) -> 0 | I85: ＝建置總額 × 建置期間落在本期的比例（不隨延誤後移）
A86: 託管｜NC-2／3（60 毛 MW 起 ÷ 1.35）｜IT MW／起租（年）／第一年租金（US$m/MW）／年調／建置 CapEx（US$m） | C86: 44.44 | D86: 1.25 | E86: 1.85 | F86: 0.03 | G86: 571.06 | I86: 北卡 Yadkin County 兩處（買賣協議 60.0，2026 Q4 交割、2027 Q3 RFS；60 毛 MW 起、最多 198）；44.44 MW-IT；租金 1.85 [Analogy]；資本支出＝土地 60.0＋建置 11.5／MW-IT；只放積極（審查留言第 6 條）
A87: 託管｜NC-2／3（60 毛 MW 起 ÷ 1.35）｜建置起（年）／建置訖（年）／隨延誤後移／已簽約 | C87: 0.375 | D87: 1.25 | E87: 1 | F87: 0 | I87: 時點為評價日起的年數；隨延誤後移＝1 時起租加上建設延誤月數 ÷ 12（建置不後移）
A88: 託管｜NC-2／3（60 毛 MW 起 ÷ 1.35）｜情境（保守／基準／積極；1＝納入） | C88: 0 | D88: 0 | E88: 1 | I88: 依『輸入與假設』A 區情境選擇器
A89: 託管｜NC-2／3（60 毛 MW 起 ÷ 1.35）｜營收（模型期） | B89: US$m | C89: =CHOOSE(輸入與假設!$C$5,$C$88,$D$88,$E$88)*IF(C$55>MAX(C$54,($D$86+$E$87*運營_產能與收入!$C$62/12)),$C$86*$E$86*(1+$F$86)^((MAX(C$54,($D$86+$E$87*運營_產能與收入!$C$62/12))+C$55)/2-($D$86+$E$87*運營_產能與收入!$C$62/12))*(C$55-MAX(C$54,($D$86+$E$87*運營_產能與收入!$C$62/12))),0) -> 0 | D89: =CHOOSE(輸入與假設!$C$5,$C$88,$D$88,$E$88)*IF(D$55>MAX(D$54,($D$86+$E$87*運營_產能與收入!$C$62/12)),$C$86*$E$86*(1+$F$86)^((MAX(D$54,($D$86+$E$87*運營_產能與收入!$C$62/12))+D$55)/2-($D$86+$E$87*運營_產能與收入!$C$62/12))*(D$55-MAX(D$54,($D$86+$E$87*運營_產能與收入!$C$62/12))),0) -> 0 | E89: =CHOOSE(輸入與假設!$C$5,$C$88,$D$88,$E$88)*IF(E$55>MAX(E$54,($D$86+$E$87*運營_產能與收入!$C$62/12)),$C$86*$E$86*(1+$F$86)^((MAX(E$54,($D$86+$E$87*運營_產能與收入!$C$62/12))+E$55)/2-($D$86+$E$87*運營_產能與收入!$C$62/12))*(E$55-MAX(E$54,($D$86+$E$87*運營_產能與收入!$C$62/12))),0) -> 0 | F89: =CHOOSE(輸入與假設!$C$5,$C$88,$D$88,$E$88)*IF(F$55>MAX(F$54,($D$86+$E$87*運營_產能與收入!$C$62/12)),$C$86*$E$86*(1+$F$86)^((MAX(F$54,($D$86+$E$87*運營_產能與收入!$C$62/12))+F$55)/2-($D$86+$E$87*運營_產能與收入!$C$62/12))*(F$55-MAX(F$54,($D$86+$E$87*運營_產能與收入!$C$62/12))),0) -> 0 | G89: =CHOOSE(輸入與假設!$C$5,$C$88,$D$88,$E$88)*IF(G$55>MAX(G$54,($D$86+$E$87*運營_產能與收入!$C$62/12)),$C$86*$E$86*(1+$F$86)^((MAX(G$54,($D$86+$E$87*運營_產能與收入!$C$62/12))+G$55)/2-($D$86+$E$87*運營_產能與收入!$C$62/12))*(G$55-MAX(G$54,($D$86+$E$87*運營_產能與收入!$C$62/12))),0) -> 0 | I89: ＝情境旗標 × MW × 第一年租金 ×(1＋年調)^(期中點 − 起租) × 期間內在租年數
A90: 託管｜NC-2／3（60 毛 MW 起 ÷ 1.35）｜建置 CapEx（模型期） | B90: US$m | C90: =CHOOSE(輸入與假設!$C$5,$C$88,$D$88,$E$88)*IF($D$87>$C$87,$G$86*MAX(0,MIN(C$55,$D$87)-MAX(C$54,$C$87))/($D$87-$C$87),IF(OR(AND($C$87>=C$54,$C$87<C$55),$C$87<C$54),$G$86,0)) -> 0 | D90: =CHOOSE(輸入與假設!$C$5,$C$88,$D$88,$E$88)*IF($D$87>$C$87,$G$86*MAX(0,MIN(D$55,$D$87)-MAX(D$54,$C$87))/($D$87-$C$87),IF(OR(AND($C$87>=D$54,$C$87<D$55)),$G$86,0)) -> 0 | E90: =CHOOSE(輸入與假設!$C$5,$C$88,$D$88,$E$88)*IF($D$87>$C$87,$G$86*MAX(0,MIN(E$55,$D$87)-MAX(E$54,$C$87))/($D$87-$C$87),IF(OR(AND($C$87>=E$54,$C$87<E$55)),$G$86,0)) -> 0 | F90: =CHOOSE(輸入與假設!$C$5,$C$88,$D$88,$E$88)*IF($D$87>$C$87,$G$86*MAX(0,MIN(F$55,$D$87)-MAX(F$54,$C$87))/($D$87-$C$87),IF(OR(AND($C$87>=F$54,$C$87<F$55)),$G$86,0)) -> 0 | G90: =CHOOSE(輸入與假設!$C$5,$C$88,$D$88,$E$88)*IF($D$87>$C$87,$G$86*MAX(0,MIN(G$55,$D$87)-MAX(G$54,$C$87))/($D$87-$C$87),IF(OR(AND($C$87>=G$54,$C$87<G$55)),$G$86,0)) -> 0 | I90: ＝建置總額 × 建置期間落在本期的比例（不隨延誤後移）
A91: 託管｜NC-1 擴建 A（＋100 毛 MW）｜IT MW／起租（年）／第一年租金（US$m/MW）／年調／建置 CapEx（US$m） | C91: 74.07 | D91: 2.5 | E91: 1.85 | F91: 0.03 | G91: 851.805 | I91: NC-1 長期毛容量約 200（10-Q）／約 300（法說）：積極情境擴至約 300 毛 MW 的第一段（＋100 毛，2029-01 起租）[Interested-party 目標／Assumed 時程]；只放積極
A92: 託管｜NC-1 擴建 A（＋100 毛 MW）｜建置起（年）／建置訖（年）／隨延誤後移／已簽約 | C92: 1.5 | D92: 2.5 | E92: 1 | F92: 0 | I92: 時點為評價日起的年數；隨延誤後移＝1 時起租加上建設延誤月數 ÷ 12（建置不後移）
A93: 託管｜NC-1 擴建 A（＋100 毛 MW）｜情境（保守／基準／積極；1＝納入） | C93: 0 | D93: 0 | E93: 1 | I93: 依『輸入與假設』A 區情境選擇器
A94: 託管｜NC-1 擴建 A（＋100 毛 MW）｜營收（模型期） | B94: US$m | C94: =CHOOSE(輸入與假設!$C$5,$C$93,$D$93,$E$93)*IF(C$55>MAX(C$54,($D$91+$E$92*運營_產能與收入!$C$62/12)),$C$91*$E$91*(1+$F$91)^((MAX(C$54,($D$91+$E$92*運營_產能與收入!$C$62/12))+C$55)/2-($D$91+$E$92*運營_產能與收入!$C$62/12))*(C$55-MAX(C$54,($D$91+$E$92*運營_產能與收入!$C$62/12))),0) -> 0 | D94: =CHOOSE(輸入與假設!$C$5,$C$93,$D$93,$E$93)*IF(D$55>MAX(D$54,($D$91+$E$92*運營_產能與收入!$C$62/12)),$C$91*$E$91*(1+$F$91)^((MAX(D$54,($D$91+$E$92*運營_產能與收入!$C$62/12))+D$55)/2-($D$91+$E$92*運營_產能與收入!$C$62/12))*(D$55-MAX(D$54,($D$91+$E$92*運營_產能與收入!$C$62/12))),0) -> 0 | E94: =CHOOSE(輸入與假設!$C$5,$C$93,$D$93,$E$93)*IF(E$55>MAX(E$54,($D$91+$E$92*運營_產能與收入!$C$62/12)),$C$91*$E$91*(1+$F$91)^((MAX(E$54,($D$91+$E$92*運營_產能與收入!$C$62/12))+E$55)/2-($D$91+$E$92*運營_產能與收入!$C$62/12))*(E$55-MAX(E$54,($D$91+$E$92*運營_產能與收入!$C$62/12))),0) -> 0 | F94: =CHOOSE(輸入與假設!$C$5,$C$93,$D$93,$E$93)*IF(F$55>MAX(F$54,($D$91+$E$92*運營_產能與收入!$C$62/12)),$C$91*$E$91*(1+$F$91)^((MAX(F$54,($D$91+$E$92*運營_產能與收入!$C$62/12))+F$55)/2-($D$91+$E$92*運營_產能與收入!$C$62/12))*(F$55-MAX(F$54,($D$91+$E$92*運營_產能與收入!$C$62/12))),0) -> 0 | G94: =CHOOSE(輸入與假設!$C$5,$C$93,$D$93,$E$93)*IF(G$55>MAX(G$54,($D$91+$E$92*運營_產能與收入!$C$62/12)),$C$91*$E$91*(1+$F$91)^((MAX(G$54,($D$91+$E$92*運營_產能與收入!$C$62/12))+G$55)/2-($D$91+$E$92*運營_產能與收入!$C$62/12))*(G$55-MAX(G$54,($D$91+$E$92*運營_產能與收入!$C$62/12))),0) -> 0 | I94: ＝情境旗標 × MW × 第一年租金 ×(1＋年調)^(期中點 − 起租) × 期間內在租年數
A95: 託管｜NC-1 擴建 A（＋100 毛 MW）｜建置 CapEx（模型期） | B95: US$m | C95: =CHOOSE(輸入與假設!$C$5,$C$93,$D$93,$E$93)*IF($D$92>$C$92,$G$91*MAX(0,MIN(C$55,$D$92)-MAX(C$54,$C$92))/($D$92-$C$92),IF(OR(AND($C$92>=C$54,$C$92<C$55),$C$92<C$54),$G$91,0)) -> 0 | D95: =CHOOSE(輸入與假設!$C$5,$C$93,$D$93,$E$93)*IF($D$92>$C$92,$G$91*MAX(0,MIN(D$55,$D$92)-MAX(D$54,$C$92))/($D$92-$C$92),IF(OR(AND($C$92>=D$54,$C$92<D$55)),$G$91,0)) -> 0 | E95: =CHOOSE(輸入與假設!$C$5,$C$93,$D$93,$E$93)*IF($D$92>$C$92,$G$91*MAX(0,MIN(E$55,$D$92)-MAX(E$54,$C$92))/($D$92-$C$92),IF(OR(AND($C$92>=E$54,$C$92<E$55)),$G$91,0)) -> 0 | F95: =CHOOSE(輸入與假設!$C$5,$C$93,$D$93,$E$93)*IF($D$92>$C$92,$G$91*MAX(0,MIN(F$55,$D$92)-MAX(F$54,$C$92))/($D$92-$C$92),IF(OR(AND($C$92>=F$54,$C$92<F$55)),$G$91,0)) -> 0 | G95: =CHOOSE(輸入與假設!$C$5,$C$93,$D$93,$E$93)*IF($D$92>$C$92,$G$91*MAX(0,MIN(G$55,$D$92)-MAX(G$54,$C$92))/($D$92-$C$92),IF(OR(AND($C$92>=G$54,$C$92<G$55)),$G$91,0)) -> 0 | I95: ＝建置總額 × 建置期間落在本期的比例（不隨延誤後移）
A96: 託管｜NC-1 擴建 B（＋101 毛 MW，至約 300 毛）｜IT MW／起租（年）／第一年租金（US$m/MW）／年調／建置 CapEx（US$m） | C96: 74.81 | D96: 3.5 | E96: 1.85 | F96: 0.03 | G96: 860.315 | I96: 同上第二段（＋101 毛，2030-01 起租）；只放積極
A97: 託管｜NC-1 擴建 B（＋101 毛 MW，至約 300 毛）｜建置起（年）／建置訖（年）／隨延誤後移／已簽約 | C97: 2.5 | D97: 3.5 | E97: 1 | F97: 0 | I97: 時點為評價日起的年數；隨延誤後移＝1 時起租加上建設延誤月數 ÷ 12（建置不後移）
A98: 託管｜NC-1 擴建 B（＋101 毛 MW，至約 300 毛）｜情境（保守／基準／積極；1＝納入） | C98: 0 | D98: 0 | E98: 1 | I98: 依『輸入與假設』A 區情境選擇器
A99: 託管｜NC-1 擴建 B（＋101 毛 MW，至約 300 毛）｜營收（模型期） | B99: US$m | C99: =CHOOSE(輸入與假設!$C$5,$C$98,$D$98,$E$98)*IF(C$55>MAX(C$54,($D$96+$E$97*運營_產能與收入!$C$62/12)),$C$96*$E$96*(1+$F$96)^((MAX(C$54,($D$96+$E$97*運營_產能與收入!$C$62/12))+C$55)/2-($D$96+$E$97*運營_產能與收入!$C$62/12))*(C$55-MAX(C$54,($D$96+$E$97*運營_產能與收入!$C$62/12))),0) -> 0 | D99: =CHOOSE(輸入與假設!$C$5,$C$98,$D$98,$E$98)*IF(D$55>MAX(D$54,($D$96+$E$97*運營_產能與收入!$C$62/12)),$C$96*$E$96*(1+$F$96)^((MAX(D$54,($D$96+$E$97*運營_產能與收入!$C$62/12))+D$55)/2-($D$96+$E$97*運營_產能與收入!$C$62/12))*(D$55-MAX(D$54,($D$96+$E$97*運營_產能與收入!$C$62/12))),0) -> 0 | E99: =CHOOSE(輸入與假設!$C$5,$C$98,$D$98,$E$98)*IF(E$55>MAX(E$54,($D$96+$E$97*運營_產能與收入!$C$62/12)),$C$96*$E$96*(1+$F$96)^((MAX(E$54,($D$96+$E$97*運營_產能與收入!$C$62/12))+E$55)/2-($D$96+$E$97*運營_產能與收入!$C$62/12))*(E$55-MAX(E$54,($D$96+$E$97*運營_產能與收入!$C$62/12))),0) -> 0 | F99: =CHOOSE(輸入與假設!$C$5,$C$98,$D$98,$E$98)*IF(F$55>MAX(F$54,($D$96+$E$97*運營_產能與收入!$C$62/12)),$C$96*$E$96*(1+$F$96)^((MAX(F$54,($D$96+$E$97*運營_產能與收入!$C$62/12))+F$55)/2-($D$96+$E$97*運營_產能與收入!$C$62/12))*(F$55-MAX(F$54,($D$96+$E$97*運營_產能與收入!$C$62/12))),0) -> 0 | G99: =CHOOSE(輸入與假設!$C$5,$C$98,$D$98,$E$98)*IF(G$55>MAX(G$54,($D$96+$E$97*運營_產能與收入!$C$62/12)),$C$96*$E$96*(1+$F$96)^((MAX(G$54,($D$96+$E$97*運營_產能與收入!$C$62/12))+G$55)/2-($D$96+$E$97*運營_產能與收入!$C$62/12))*(G$55-MAX(G$54,($D$96+$E$97*運營_產能與收入!$C$62/12))),0) -> 0 | I99: ＝情境旗標 × MW × 第一年租金 ×(1＋年調)^(期中點 − 起租) × 期間內在租年數
A100: 託管｜NC-1 擴建 B（＋101 毛 MW，至約 300 毛）｜建置 CapEx（模型期） | B100: US$m | C100: =CHOOSE(輸入與假設!$C$5,$C$98,$D$98,$E$98)*IF($D$97>$C$97,$G$96*MAX(0,MIN(C$55,$D$97)-MAX(C$54,$C$97))/($D$97-$C$97),IF(OR(AND($C$97>=C$54,$C$97<C$55),$C$97<C$54),$G$96,0)) -> 0 | D100: =CHOOSE(輸入與假設!$C$5,$C$98,$D$98,$E$98)*IF($D$97>$C$97,$G$96*MAX(0,MIN(D$55,$D$97)-MAX(D$54,$C$97))/($D$97-$C$97),IF(OR(AND($C$97>=D$54,$C$97<D$55)),$G$96,0)) -> 0 | E100: =CHOOSE(輸入與假設!$C$5,$C$98,$D$98,$E$98)*IF($D$97>$C$97,$G$96*MAX(0,MIN(E$55,$D$97)-MAX(E$54,$C$97))/($D$97-$C$97),IF(OR(AND($C$97>=E$54,$C$97<E$55)),$G$96,0)) -> 0 | F100: =CHOOSE(輸入與假設!$C$5,$C$98,$D$98,$E$98)*IF($D$97>$C$97,$G$96*MAX(0,MIN(F$55,$D$97)-MAX(F$54,$C$97))/($D$97-$C$97),IF(OR(AND($C$97>=F$54,$C$97<F$55)),$G$96,0)) -> 0 | G100: =CHOOSE(輸入與假設!$C$5,$C$98,$D$98,$E$98)*IF($D$97>$C$97,$G$96*MAX(0,MIN(G$55,$D$97)-MAX(G$54,$C$97))/($D$97-$C$97),IF(OR(AND($C$97>=G$54,$C$97<G$55)),$G$96,0)) -> 0 | I100: ＝建置總額 × 建置期間落在本期的比例（不隨延誤後移）
A101: 託管｜Krambu（100 MW，口徑不明）｜IT MW／起租（年）／第一年租金（US$m/MW）／年調／建置 CapEx（US$m） | C101: 74.07 | D101: 1.5 | E101: 1.85 | F101: 0.03 | G101: 851.805 | I101: 法說二手摘要：Krambu 100 MW 液冷託管獨家使用權（2027 起）；10-Q 與簡報未提、條件與價格未揭露、口徑不明 → 以 100 毛 MW ÷1.35、自建同口徑（租金 1.85、建置 11.5／MW-IT）建模 [Assumed]；只放積極並標註（審查留言第 6 條）
...

Sheet 各期收支
A1: 支出與資金 — 五層支出、四層來源、現金橋
A2: FY26 欄＝1H 實際（季報現金流量表口徑）＋下半年模型；FY27 以後為純模型。瀑布以「融資前現金」決定需求並直接由各支出列加總，因此沒有循環參照
A4: 項目 | B4: 單位 | C4: FY26 | D4: FY27 | E4: FY28 | F4: FY29 | G4: FY30 | I4: 公式／來源說明
A5: 支出（五層）
A6: ① 毛 CapEx（認列，備忘） | B6: US$m | C6: =輸入與假設!$C$293+輸入與假設!C$175 -> 491.69103 | D6: =輸入與假設!D$175 -> 427.14561 | E6: =輸入與假設!E$175 -> 56.385 | F6: =輸入與假設!F$175 -> 56.385 | G6: =輸入與假設!G$175 -> 127.04668 | I6: FY26＝1H 實際認列 344.712＋2H 模型；對照公司全年指引 不適用（公司未給指引）。備忘列：用途合計採現金口徑，不用這一列
A7: 客戶預付率 | B7: % | C7: =輸入與假設!C$152 -> 0.21 | D7: =輸入與假設!D$152 -> 0.21 | E7: =輸入與假設!E$152 -> 0.21 | F7: =輸入與假設!F$152 -> 0.21 | G7: =輸入與假設!G$152 -> 0.21
A8: 客戶預付金額（抵減，2H 起） | B8: US$m | C8: =(輸入與假設!C$165+輸入與假設!C$107)*C7 -> 30.865595 | D8: =(輸入與假設!D$165+輸入與假設!D$107)*D7 -> 89.700579 | E8: =(輸入與假設!E$165+輸入與假設!E$107)*E7 -> 11.84085 | F8: =(輸入與假設!F$165+輸入與假設!F$107)*F7 -> 11.84085 | G8: =(輸入與假設!G$165+輸入與假設!G$107)*G7 -> 7.6965525 | I8: ＝成長型 CapEx × 預付比率（汰換 CapEx 不計）；含託管建置（WhiteFiber v0.1b：defaults.colo.coverPrepay）；1H 的預付已含在實際 CFO 內，不重複計入
A9: 合約負債期初（客戶預付餘額） | B9: US$m | C9: =輸入與假設!$C$149 -> 143.11 | D9: =C12 -> 165.03122 | E9: =D12 -> 234.1029 | F9: =E12 -> 216.68088 | G9: =F12 -> 201.43662 | I9: FY26 期初＝6/30 季報遞延營收
A10: 合約負債利息累積（重大財務組成，非現金） | B10: US$m | C10: =輸入與假設!$C$150*(C9+0.5*C8)*運營_產能與收入!C7 -> 0 | D10: =輸入與假設!$C$150*(D9+0.5*D8)*運營_產能與收入!D7 -> 0 | E10: =輸入與假設!$C$150*(E9+0.5*E8)*運營_產能與收入!E7 -> 0 | F10: =輸入與假設!$C$150*(F9+0.5*F8)*運營_產能與收入!F7 -> 0 | G10: =輸入與假設!$C$150*(G9+0.5*G8)*運營_產能與收入!G7 -> 0 | I10: ＝隱含利率 ×(期初合約負債＋本期預付流入 × ½)× 期間長度；進損益利息、不進現金（v0.1b）
A11: 預付認列（非現金營收） | B11: US$m | C11: =MIN(C9+C10,(C9+C10)/輸入與假設!$C$148*運營_產能與收入!C7) -> 8.944375 | D11: =MIN(D9+D10,(D9+D10)/輸入與假設!$C$148*運營_產能與收入!D7) -> 20.628903 | E11: =MIN(E9+E10,(E9+E10)/輸入與假設!$C$148*運營_產能與收入!E7) -> 29.262862 | F11: =MIN(F9+F10,(F9+F10)/輸入與假設!$C$148*運營_產能與收入!F7) -> 27.085111 | G11: =MIN(G9+G10,(G9+G10)/輸入與假設!$C$148*運營_產能與收入!G7) -> 25.179578 | I11: ＝(期初合約負債＋累積利息) ÷ 認列年數 × 期間長度；這部分營收已在預付時收現，自營運來源扣除
A12: 合約負債期末 | B12: US$m | C12: =C9+C8+C10-C11 -> 165.03122 | D12: =D9+D8+D10-D11 -> 234.1029 | E12: =E9+E8+E10-E11 -> 216.68088 | F12: =F9+F8+F10-F11 -> 201.43662 | G12: =G9+G8+G10-G11 -> 183.9536 | I12: ＝期初＋預付流入＋累積利息−認列
A13: ① CapEx（用途用：1H 現金／2H 毛額） | B13: US$m | C13: =輸入與假設!$C$292+輸入與假設!C$175 -> 491.69103 | D13: =輸入與假設!D$175 -> 427.14561 | E13: =輸入與假設!E$175 -> 56.385 | F13: =輸入與假設!F$175 -> 56.385 | G13: =輸入與假設!G$175 -> 127.04668 | I13: 1H 採現金流量表的現金購置 344.712；2H 起採毛額，客戶預付在來源端抵回（避免重複計入）
A14: ② 在帳現金租金（備忘，1H 已含在 CFO） | B14: US$m | C14: =輸入與假設!C$153 -> 3.268 | D14: =輸入與假設!D$153 -> 4.28 | E14: =輸入與假設!E$153 -> 2.465 | F14: =輸入與假設!F$153 -> 2.304 | G14: =輸入與假設!G$153 -> 2.358 | I14: 見『租賃與承諾』頁；2030 後尚有 5.76。FY26 欄僅 2H：1H 租金 13.044 已含在實際 CFO 內
A15: ② 表外現金租金（未起租） | B15: US$m | C15: =運營_產能與收入!C71 -> 0.51599997 | D15: =運營_產能與收入!D71 -> 4.1279997 | E15: =運營_產能與收入!E71 -> 4.1279997 | F15: =運營_產能與收入!F71 -> 4.1279997 | G15: =運營_產能與收入!G71 -> 4.1279997 | I15: 已簽約未起租租賃 20.296 的現金路徑
A16: ② GPU 租金（租賃設備） | B16: US$m | C16: =輸入與假設!C$172 -> 8.0330849 | D16: =輸入與假設!D$172 -> 37.842479 | E16: =輸入與假設!E$172 -> 50.89496 | F16: =輸入與假設!F$172 -> 65.579644 | G16: =輸入與假設!G$172 -> 77.694508 | I16: 新增 GPU 租賃部分的固定租金（『輸入與假設』D 區；WhiteFiber v0.1b）
A17: 租金合計 | B17: US$m | C17: =C14+C15+C16 -> 11.817085 | D17: =D14+D15+D16 -> 46.250479 | E17: =E14+E15+E16 -> 57.48796 | F17: =F14+F15+F16 -> 72.011644 | G17: =G14+G15+G16 -> 84.180508 | I17: 租金已含在 EBITDA 率內（GAAP 營業租賃費用屬營業費用）：營運來源以 EBITDA 率＋租金÷營收計（租前），此列再扣，淨效果中性
A18: ③ 存量債務利息（備忘，1H 已含在 CFO） | B18: US$m | C18: =輸入與假設!C$225 -> 13.586726 | D18: =輸入與假設!D$225 -> 51.128959 | E18: =輸入與假設!E$225 -> 43.836731 | F18: =輸入與假設!F$225 -> 40.079815 | G18: =輸入與假設!G$225 -> 36.586123 | I18: ="6/30 債務餘額的利息。FY26 全年利息＝1H 實際 8.011＋2H "&TEXT(C18,"0.0")&"＝"&TEXT(8.011+C18,"0.00")&"（見下方備忘）" -> 6/30 債務餘額的利息。FY26 全年利息＝1H 實際 8.011＋2H 13.6＝21.60（見下方備忘）
A19: 期初累積現金 | B19: US$m | C19: =輸入與假設!$C$290 -> 114.441 | D19: =C54 -> 136.21658 | E19: =D54 -> 30 | F19: =E54 -> 30 | G19: =F54 -> 30 | I19: FY26 自 2025-12-31 起算；之後＝前期期末累積現金
A20: 新債利率 | B20: % | C20: =IF(輸入與假設!$C$218=1,輸入與假設!C$224+MAX(0,輸入與假設!$C$217-450)/100*0.004,輸入與假設!C$224) -> 0.095 | D20: =IF(輸入與假設!$C$218=1,輸入與假設!D$224+MAX(0,輸入與假設!$C$217-450)/100*0.004,輸入與假設!D$224) -> 0.095 | E20: =IF(輸入與假設!$C$218=1,輸入與假設!E$224+MAX(0,輸入與假設!$C$217-450)/100*0.004,輸入與假設!E$224) -> 0.095 | F20: =IF(輸入與假設!$C$218=1,輸入與假設!F$224+MAX(0,輸入與假設!$C$217-450)/100*0.004,輸入與假設!F$224) -> 0.095 | G20: =IF(輸入與假設!$C$218=1,輸入與假設!G$224+MAX(0,輸入與假設!$C$217-450)/100*0.004,輸入與假設!G$224) -> 0.095 | I20: CDS 開關：＋MAX(0,CDS−450)×0.4bp/bp
A21: ③ 新債利息（瀑布） | B21: US$m | C21: =C88 -> 0 | D21: =D88 -> 4.1728098 | E21: =E88 -> 8.8531983 | F21: =F88 -> 11.573231 | G21: =G88 -> 14.23471 | I21: ＝新債利率×期間長度×(期初新債＋本期舉借)；見下方「期前融資瀑布」
A22: 利息合計 | B22: US$m | C22: =C18+C21 -> 13.586726 | D22: =D18+D21 -> 55.301769 | E22: =E18+E21 -> 52.68993 | F22: =F18+F21 -> 51.653046 | G22: =G18+G21 -> 50.820832
A23: ④ JV／策略投資出資 | B23: US$m | C23: =輸入與假設!$C$294+輸入與假設!C$158 -> 0 | D23: =輸入與假設!D$158 -> 0 | E23: =輸入與假設!E$158 -> 0 | F23: =輸入與假設!F$158 -> 0 | G23: =輸入與假設!G$158 -> 0 | I23: FY26＝1H 實際 0.0（JV 0.000＋策略投資 0.000）＋2H 模型。WYFI 不發股息
A24: ⑧ 股利（普通股＋特別股） | B24: US$m | C24: =輸入與假設!$C$309+4*輸入與假設!$C$202*運營_產能與收入!C7*(輸入與假設!$C$203+0+SUMPRODUCT(資產負債_既有債務!$D$20:$D$21*資產負債_既有債務!$H$15:$H$16*(資產負債_既有債務!$G$15:$G$16<0)))+輸入與假設!C$222 -> 0 | D24: =4*輸入與假設!$C$202*運營_產能與收入!D7*(輸入與假設!$C$203+C91+SUMPRODUCT(資產負債_既有債務!$D$20:$D$21*資產負債_既有債務!$H$15:$H$16*(資產負債_既有債務!$G$15:$G$16<1)))+輸入與假設!D$222 -> 0 | E24: =4*輸入與假設!$C$202*運營_產能與收入!E7*(輸入與假設!$C$203+D91+SUMPRODUCT(資產負債_既有債務!$D$20:$D$21*資產負債_既有債務!$H$15:$H$16*(資產負債_既有債務!$G$15:$G$16<2)))+輸入與假設!E$222 -> 0 | F24: =4*輸入與假設!$C$202*運營_產能與收入!F7*(輸入與假設!$C$203+E91+SUMPRODUCT(資產負債_既有債務!$D$20:$D$21*資產負債_既有債務!$H$15:$H$16*(資產負債_既有債務!$G$15:$G$16<3)))+輸入與假設!F$222 -> 0 | G24: =4*輸入與假設!$C$202*運營_產能與收入!G7*(輸入與假設!$C$203+F91+SUMPRODUCT(資產負債_既有債務!$D$20:$D$21*資產負債_既有債務!$H$15:$H$16*(資產負債_既有債務!$G$15:$G$16<4)))+輸入與假設!G$222 -> 0 | I24: 普通股＝每股每季 × 4 × 期間長度 ×(基礎股數＋前期累計瀑布新股＋已強制轉換特別股)＋特別股股利；FY26＝1H 實際＋2H 模型（v0.1b）
A25: 電力（overlay） | B25: US$m | C25: =IF(輸入與假設!$C$130=1,運營_產能與收入!C9*8760*輸入與假設!C$132*輸入與假設!C$131/1000000*運營_產能與收入!C7,0) -> 0 | D25: =IF(輸入與假設!$C$130=1,運營_產能與收入!D9*8760*輸入與假設!D$132*輸入與假設!D$131/1000000*運營_產能與收入!D7,0) -> 0 | E25: =IF(輸入與假設!$C$130=1,運營_產能與收入!E9*8760*輸入與假設!E$132*輸入與假設!E$131/1000000*運營_產能與收入!E7,0) -> 0 | F25: =IF(輸入與假設!$C$130=1,運營_產能與收入!F9*8760*輸入與假設!F$132*輸入與假設!F$131/1000000*運營_產能與收入!F7,0) -> 0 | G25: =IF(輸入與假設!$C$130=1,運營_產能與收入!G9*8760*輸入與假設!G$132*輸入與假設!G$131/1000000*運營_產能與收入!G7,0) -> 0 | I25: ＝已連網 MW×8760×PUE×電價÷1e9×期間係數。EBITDA 率已含電費，預設關閉
A26: 維護（overlay） | B26: US$m | C26: =IF(輸入與假設!$C$130=1,運營_產能與收入!C9*輸入與假設!C$133*運營_產能與收入!C7,0) -> 0 | D26: =IF(輸入與假設!$C$130=1,運營_產能與收入!D9*輸入與假設!D$133*運營_產能與收入!D7,0) -> 0 | E26: =IF(輸入與假設!$C$130=1,運營_產能與收入!E9*輸入與假設!E$133*運營_產能與收入!E7,0) -> 0 | F26: =IF(輸入與假設!$C$130=1,運營_產能與收入!F9*輸入與假設!F$133*運營_產能與收入!F7,0) -> 0 | G26: =IF(輸入與假設!$C$130=1,運營_產能與收入!G9*輸入與假設!G$133*運營_產能與收入!G7,0) -> 0
A27: ⑤ 排程還本（季報到期表） | B27: US$m | C27: =輸入與假設!$C$296+IF(輸入與假設!$C$197=1,輸入與假設!C$223,0)+資產負債_既有債務!C32+資產負債_既有債務!C43 -> 17.972 | D27: =IF(輸入與假設!$C$197=1,輸入與假設!D$223,0)+資產負債_既有債務!D32+資產負債_既有債務!D43 -> 90.747 | E27: =IF(輸入與假設!$C$197=1,輸入與假設!E$223,0)+資產負債_既有債務!E32+資產負債_既有債務!E43 -> 36.9595 | F27: =IF(輸入與假設!$C$197=1,輸入與假設!F$223,0)+資產負債_既有債務!F32+資產負債_既有債務!F43 -> 51.6715 | G27: =IF(輸入與假設!$C$197=1,輸入與假設!G$223,0)+資產負債_既有債務!G32+資產負債_既有債務!G43 -> 30.7125 | I27: FY26＝1H 實際還款 12.599＋2H 到期表 5.373
A28: ⑥ capped call 支出（1H 實際） | B28: US$m | C28: =輸入與假設!$C$297 -> 120 | D28: =0 -> 0 | E28: =0 -> 0 | F28: =0 -> 0 | G28: =0 -> 0 | I28: 可轉債配套 capped call 現金支出（未見揭露，0）
A29: ⑦ 現金稅（2H 起） | B29: US$m | C29: =輸入與假設!$C$216*MAX(0,運營_產能與收入!C50*輸入與假設!C$127+輸入與假設!C$51+輸入與假設!C$117-運營_產能與收入!C74-輸入與假設!C$176-輸入與假設!C$225) -> 0 | D29: =輸入與假設!$C$216*MAX(0,運營_產能與收入!D50*輸入與假設!D$127+輸入與假設!D$51+輸入與假設!D$117-運營_產能與收入!D74-輸入與假設!D$176-輸入與假設!D$225) -> 0 | E29: =輸入與假設!$C$216*MAX(0,運營_產能與收入!E50*輸入與假設!E$127+輸入與假設!E$51+輸入與假設!E$117-運營_產能與收入!E74-輸入與假設!E$176-輸入與假設!E$225) -> 0 | F29: =輸入與假設!$C$216*MAX(0,運營_產能與收入!F50*輸入與假設!F$127+輸入與假設!F$51+輸入與假設!F$117-運營_產能與收入!F74-輸入與假設!F$176-輸入與假設!F$225) -> 0 | G29: =輸入與假設!$C$216*MAX(0,運營_產能與收入!G50*輸入與假設!G$127+輸入與假設!G$51+輸入與假設!G$117-運營_產能與收入!G74-輸入與假設!G$176-輸入與假設!G$225) -> 9.5408719 | I29: ＝稅率 × MAX(0, 損益 EBITDA − 車隊 D&A − 存量利息)；1H 的稅已含在 CFO 內（v0.1b）
A30: 用途合計（現金口徑） | B30: US$m | C30: =C13+C17+C22+C23+C25+C26+C27+C28+C29+C24 -> 655.06684 | D30: =D13+D17+D22+D23+D25+D26+D27+D28+D29+D24 -> 619.44486 | E30: =E13+E17+E22+E23+E25+E26+E27+E28+E29+E24 -> 203.52239 | F30: =F13+F17+F22+F23+F25+F26+F27+F28+F29+F24 -> 231.72119 | G30: =G13+G17+G22+G23+G25+G26+G27+G28+G29+G24 -> 302.30139 | I30: FY26 的 1H 部分採季報現金流量表口徑（現金購置、還款、JV、capped call）；1H 的利息與租金已含在 CFO 內，不重複列
A31: 來源（四層）
A32: Ⓐ0 1H26 實際營運現金流（CFO） | B32: US$m | C32: =輸入與假設!$C$291 -> 89.105 | D32: =0 -> 0 | E32: =0 -> 0 | F32: =0 -> 0 | G32: =0 -> 0 | I32: 季報實際值，取代模型推算；已含 1H 的利息、租金與客戶預付
A33: Ⓐ RPO 現金（2H 起） | B33: US$m | C33: =運營_產能與收入!C52 -> -0.91646212 | D33: =運營_產能與收入!D52 -> 3.8687335 | E33: =運營_產能與收入!E52 -> 2.2644478 | F33: =運營_產能與收入!F52 -> 0 | G33: =運營_產能與收入!G52 -> 0
A34: Ⓑ 新簽約現金 | B34: US$m | C34: =運營_產能與收入!C53 -> -0.83010925 | D34: =運營_產能與收入!D53 -> 12.021047 | E34: =運營_產能與收入!E53 -> 56.472883 | F34: =運營_產能與收入!F53 -> 112.69607 | G34: =運營_產能與收入!G53 -> 177.69662
A35: Ⓒ 非算力服務現金 | B35: US$m | C35: =輸入與假設!C$128 -> 0 | D35: =輸入與假設!D$128 -> 0 | E35: =輸入與假設!E$128 -> 0 | F35: =輸入與假設!F$128 -> 0 | G35: =輸入與假設!G$128 -> 0
A36: Ⓒ2 其他事業 EBITDA（2H 起） | B36: US$m | C36: =輸入與假設!C$51 -> 0 | D36: =輸入與假設!D$51 -> 0 | E36: =輸入與假設!E$51 -> 0 | F36: =輸入與假設!F$51 -> 0 | G36: =輸入與假設!G$51 -> 0 | I36: 非核心事業 EBITDA（負值＝燒錢），視為現金（v0.1b）
A37: Ⓒ3 託管 EBITDA（2H 起） | B37: US$m | C37: =輸入與假設!C$117 -> 19.780763 | D37: =輸入與假設!D$117 -> 55.685633 | E37: =輸入與假設!E$117 -> 88.573269 | F37: =輸入與假設!F$117 -> 105.63746 | G37: =輸入與假設!G$117 -> 114.07223 | I37: SaaS、軟體、硬體、服務四線 EBITDA，視為現金（現金稅另列於用途；v0.1b）
A38: Ⓒ4 減：延誤罰則（營業費用） | B38: US$m | C38: =-運營_產能與收入!C74 -> 0 | D38: =-運營_產能與收入!D74 -> 0 | E38: =-運營_產能與收入!E74 -> 0 | F38: =-運營_產能與收入!F74 -> 0 | G38: =-運營_產能與收入!G74 -> 0 | I38: 建設延誤期間應計費而未計費營收 × 罰則比例（預設 0；v0.2）
A39: Ⓓ 客戶預付（2H 起） | B39: US$m | C39: =C8 -> 30.865595 | D39: =D8 -> 89.700579 | E39: =E8 -> 11.84085 | F39: =F8 -> 11.84085 | G39: =G8 -> 7.6965525
A40: Ⓓ2 減：預付認列（非現金營收） | B40: US$m | C40: =-C11 -> -8.944375 | D40: =-D11 -> -20.628903 | E40: =-E11 -> -29.262862 | F40: =-F11 -> -27.085111 | G40: =-G11 -> -25.179578 | I40: 營收中由合約負債轉入的部分已在預付時收現，不重複計入服務現金（v0.1b）
A41: 營運來源合計 | B41: US$m | C41: =C32+C33+C34+C35+C36+C37+C38+C39+C40 -> 129.06041 | D41: =D32+D33+D34+D35+D36+D37+D38+D39+D40 -> 140.64709 | E41: =E32+E33+E34+E35+E36+E37+E38+E39+E40 -> 129.88859 | F41: =F32+F33+F34+F35+F36+F37+F38+F39+F40 -> 203.08927 | G41: =G32+G33+G34+G35+G36+G37+G38+G39+G40 -> 274.28583
A42: Ⓔ 股權／可轉債（融資） | B42: US$m | C42: =輸入與假設!$C$298+IF(輸入與假設!$C$187=1,輸入與假設!$C$186,0)+SUM(輸入與假設!$C$181:$C$184) -> 217.961 | D42: =0 -> 0 | E42: =0 -> 0 | F42: =0 -> 0 | G42: =0 -> 0 | I42: FY26＝1H 未發行普通股（0）＋2H 期後股權 0（2031 可轉債交換發行約 6.3M 股為以股換債，列於期後事件）；另含期後事件現金淨額（『輸入與假設』E 區，WhiteFiber v0.1b）
A43: Ⓕ 1H26 實際借款（融資） | B43: US$m | C43: =輸入與假設!$C$295 -> 304.526 | D43: =0 -> 0 | E43: =0 -> 0 | F43: =0 -> 0 | G43: =0 -> 0 | I43: 季報：H1 借款 304.526（2026-03 可轉債）
A44: Ⓕ2 NC-1 專案貸款動用（融資） | B44: US$m | C44: =資產負債_既有債務!C42 -> 0 | D44: =資產負債_既有債務!D42 -> 307.125 | E44: =資產負債_既有債務!E42 -> 0 | F44: =資產負債_既有債務!F42 -> 0 | G44: =資產負債_既有債務!G42 -> 0 | I44: 排程貸款：動用期期初一次到位，先於瀑布（見『資產負債_既有債務』NC-1 專案貸款；WhiteFiber v0.1c）
A45: Ⓖ 瀑布：新債（額度＋資產層） | B45: US$m | C45: =C80 -> 0 | D45: =D80 -> 20 | E45: =E80 -> 22.193297 | F45: =F80 -> 28.63192 | G45: =G80 -> 28.015568 | I45: 見下方「期前融資瀑布」
A46: Ⓖ2 瀑布：可轉債 | B46: US$m | C46: =C83 -> 0 | D46: =D83 -> 45.456196 | E46: =E83 -> 51.440505 | F46: =F83 -> 0 | G46: =G83 -> 0 | I46: 資產擔保融資用罄後、股權之前；每年不超過可轉債上限（v0.1b）
A47: Ⓗ 瀑布：股權募資 | B47: US$m | C47: =C86 -> 0 | D47: =D86 -> 0 | E47: =E86 -> 0 | F47: =F86 -> 0 | G47: =G86 -> 0 | I47: 債務與可轉債用罄後的殘差；每年不超過股權吸收上限
A48: Ⓘ 瀑布：高息債（股權上限溢出） | B48: US$m | C48: =C87 -> 0 | D48: =D87 -> 0 | E48: =E87 -> 0 | F48: =F87 -> 0 | G48: =G87 -> 0 | I48: 股權超過每年上限的部分；不受 backlog 上限約束
A49: 總來源（含融資） | B49: US$m | C49: =C41+C42+C43+C44+C45+C46+C47+C48 -> 651.54741 | D49: =D41+D42+D43+D44+D45+D46+D47+D48 -> 513.22829 | E49: =E41+E42+E43+E44+E45+E46+E47+E48 -> 203.52239 | F49: =F41+F42+F43+F44+F45+F46+F47+F48 -> 231.72119 | G49: =G41+G42+G43+G44+G45+G46+G47+G48 -> 302.30139
A50: 缺口與現金橋
A51: 1H 其他／受限現金調節 | B51: US$m | C51: =輸入與假設!$C$185-(輸入與假設!$C$290+輸入與假設!$C$291+輸入與假設!$C$295+輸入與假設!$C$298-輸入與假設!$C$292-輸入與假設!$C$294-輸入與假設!$C$296-輸入與假設!$C$297-輸入與假設!$C$309) -> 25.295 | D51: =0 -> 0 | E51: =0 -> 0 | F51: =0 -> 0 | G51: =0 -> 0 | I51: 使 1H 實際流量接回 6/30 現金餘額；差額來自受限現金重分類與未逐項列出的項目
A52: 營運缺口（不含融資、不含還本） | B52: US$m | C52: =C41-(C30-C27-C28) -> -388.03442 | D52: =D41-(D30-D27-D28) -> -388.05077 | E52: =E41-(E30-E27-E28) -> -36.674302 | F52: =F41-(F30-F27-F28) -> 23.03958 | G52: =G41-(G30-G27-G28) -> 2.6969316 | I52: 本業能不能自給：營運來源 −（用途 − 排程還本 − capped call）
A53: 期間缺口（含融資） | B53: US$m | C53: =C49-C30+C51 -> 21.775575 | D53: =D49-D30+D51 -> -106.21658 | E53: =E49-E30+E51 -> 0 | F53: =F49-F30+F51 -> 0 | G53: =G49-G30+G51 -> 0
A54: 期末累積現金 | B54: US$m | C54: =C19+C53 -> 136.21658 | D54: =D19+D53 -> 30 | E54: =E19+E53 -> 30 | F54: =F19+F53 -> 30 | G54: =G19+G53 -> 30 | I54: 期前融資：每期末不低於最低現金
A56: 租賃負債（期末剩餘租金現值；調整後槓桿用，v0.2）
A57: 租賃折現率（加權平均） | B57: % | C57: 0.083 | I57: 10-K FY2026 營業／融資租賃加權平均折現率（事實總帳 lease.discRate.fy26）[Verified]；company.json → leases.liability.discRate
A58: 在帳租約：模型期後尾端年數 | B58: 年 | C58: 3 | I58: 到期表 2030 後的未折現付款平均分攤年數（10-K 營業租賃加權平均剩餘期限 12 年）[Derived]
A59: 在帳租賃負債（期末） | B59: US$m | C59: =輸入與假設!D$153*(1+各期收支!$C$57)^(-(運營_產能與收入!$D$63-運營_產能與收入!$D$7/2-運營_產能與收入!$C$63))+輸入與假設!E$153*(1+各期收支!$C$57)^(-(運營_產能與收入!$E$63-運營_產能與收入!$E$7/2-運營_產能與收入!$C$63))+輸入與假設!F$153*(1+各期收支!$C$57)^(-(運營_產能與收入!$F$63-運營_產能與收入!$F$7/2-運營_產能與收入!$C$63))+輸入與假設!G$153*(1+各期收支!$C$57)^(-(運營_產能與收入!$G$63-運營_產能與收入!$G$7/2-運營_產能與收入!$C$63))+5.76/各期收支!$C$58*(1+各期收支!$C$57)^0.5*(1-(1+各期收支!$C$57)^(-各期收支!$C$58))/各期收支!$C$57*(1+各期收支!$C$57)^(-(運營_產能與收入!$G$63-運營_產能與收入!$C$63)) -> 13.694188 | D59: =輸入與假設!E$153*(1+各期收支!$C$57)^(-(運營_產能與收入!$E$63-運營_產能與收入!$E$7/2-運營_產能與收入!$D$63))+輸入與假設!F$153*(1+各期收支!$C$57)^(-(運營_產能與收入!$F$63-運營_產能與收入!$F$7/2-運營_產能與收入!$D$63))+輸入與假設!G$153*(1+各期收支!$C$57)^(-(運營_產能與收入!$G$63-運營_產能與收入!$G$7/2-運營_產能與收入!$D$63))+5.76/各期收支!$C$58*(1+各期收支!$C$57)^0.5*(1-(1+各期收支!$C$57)^(-各期收支!$C$58))/各期收支!$C$57*(1+各期收支!$C$57)^(-(運營_產能與收入!$G$63-運營_產能與收入!$D$63)) -> 10.376726 | E59: =輸入與假設!F$153*(1+各期收支!$C$57)^(-(運營_產能與收入!$F$63-運營_產能與收入!$F$7/2-運營_產能與收入!$E$63))+輸入與假設!G$153*(1+各期收支!$C$57)^(-(運營_產能與收入!$G$63-運營_產能與收入!$G$7/2-運營_產能與收入!$E$63))+5.76/各期收支!$C$58*(1+各期收支!$C$57)^0.5*(1-(1+各期收支!$C$57)^(-各期收支!$C$58))/各期收支!$C$57*(1+各期收支!$C$57)^(-(運營_產能與收入!$G$63-運營_產能與收入!$E$63)) -> 8.6727357 | F59: =輸入與假設!G$153*(1+各期收支!$C$57)^(-(運營_產能與收入!$G$63-運營_產能與收入!$G$7/2-運營_產能與收入!$F$63))+5.76/各期收支!$C$58*(1+各期收支!$C$57)^0.5*(1-(1+各期收支!$C$57)^(-各期收支!$C$58))/各期收支!$C$57*(1+各期收支!$C$57)^(-(運營_產能與收入!$G$63-運營_產能與收入!$F$63)) -> 6.9948625 | G59: =5.76/各期收支!$C$58*(1+各期收支!$C$57)^0.5*(1-(1+各期收支!$C$57)^(-各期收支!$C$58))/各期收支!$C$57*(1+各期收支!$C$57)^(-(運營_產能與收入!$G$63-運營_產能與收入!$G$63)) -> 5.1215295 | I59: ＝期末之後各期到期表現金（期中付款）＋模型期後尾端 5.76（平均分攤、年中付款）的現值
A60: 未起租租約已起租部分的租賃負債（期末） | B60: US$m | C60: =IF(OR(運營_產能與收入!$C$62<=0,運營_產能與收入!$C$68<=0),1*輸入與假設!$C$26/輸入與假設!$C$28/輸入與假設!$C$29/4/((1+各期收支!$C$57)^0.25-1)*(MIN(MAX(0,輸入與假設!C$154-(輸入與假設!$C$27)),輸入與假設!$C$28)-(1+各期收支!$C$57)^(-(4*輸入與假設!$C$29-MAX(0,輸入與假設!C$154-(輸入與假設!$C$27)))/4)*(1-(1+各期收支!$C$57)^(-MIN(MAX(0,輸入與假設!C$154-(輸入與假設!$C$27)),輸入與假設!$C$28)/4))/(1-(1+各期收支!$C$57)^(-0.25))),(1-運營_產能與收入!$C$68)*輸入與假設!$C$26/輸入與假設!$C$28/輸入與假設!$C$29/4/((1+各期收支!$C$57)^0.25-1)*(MIN(MAX(0,輸入與假設!C$154-(輸入與假設!$C$27)),輸入與假設!$C$28)-(1+各期收支!$C$57)^(-(4*輸入與假設!$C$29-MAX(0,輸入與假設!C$154-(輸入與假設!$C$27)))/4)*(1-(1+各期收支!$C$57)^(-MIN(MAX(0,輸入與假設!C$154-(輸入與假設!$C$27)),輸入與假設!$C$28)/4))/(1-(1+各期收支!$C$57)^(-0.25)))+運營_產能與收入!$C$68*輸入與假設!$C$26/輸入與假設!$C$28/輸入與假設!$C$29/4/((1+各期收支!$C$57)^0.25-1)*(MIN(MAX(0,輸入與假設!C$154-(輸入與假設!$C$27+運營_產能與收入!$C$62/3)),輸入與假設!$C$28)-(1+各期收支!$C$57)^(-(4*輸入與假設!$C$29-MAX(0,輸入與假設!C$154-(輸入與假設!$C$27+運營_產能與收入!$C$62/3)))/4)*(1-(1+各期收支!$C$57)^(-MIN(MAX(0,輸入與假設!C$154-(輸入與假設!$C$27+運營_產能與收入!$C$62/3)),輸入與假設!$C$28)/4))/(1-(1+各期收支!$C$57)^(-0.25)))) -> 7.9631253 | D60: =IF(OR(運營_產能與收入!$C$62<=0,運營_產能與收入!$C$68<=0),1*輸入與假設!$C$26/輸入與假設!$C$28/輸入與假設!$C$29/4/((1+各期收支!$C$57)^0.25-1)*(MIN(MAX(0,輸入與假設!D$154-(輸入與假設!$C$27)),輸入與假設!$C$28)-(1+各期收支!$C$57)^(-(4*輸入與假設!$C$29-MAX(0,輸入與假設!D$154-(輸入與假設!$C$27)))/4)*(1-(1+各期收支!$C$57)^(-MIN(MAX(0,輸入與假設!D$154-(輸入與假設!$C$27)),輸入與假設!$C$28)/4))/(1-(1+各期收支!$C$57)^(-0.25))),(1-運營_產能與收入!$C$68)*輸入與假設!$C$26/輸入與假設!$C$28/輸入與假設!$C$29/4/((1+各期收支!$C$57)^0.25-1)*(MIN(MAX(0,輸入與假設!D$154-(輸入與假設!$C$27)),輸入與假設!$C$28)-(1+各期收支!$C$57)^(-(4*輸入與假設!$C$29-MAX(0,輸入與假設!D$154-(輸入與假設!$C$27)))/4)*(1-(1+各期收支!$C$57)^(-MIN(MAX(0,輸入與假設!D$154-(輸入與假設!$C$27)),輸入與假設!$C$28)/4))/(1-(1+各期收支!$C$57)^(-0.25)))+運營_產能與收入!$C$68*輸入與假設!$C$26/輸入與假設!$C$28/輸入與假設!$C$29/4/((1+各期收支!$C$57)^0.25-1)*(MIN(MAX(0,輸入與假設!D$154-(輸入與假設!$C$27+運營_產能與收入!$C$62/3)),輸入與假設!$C$28)-(1+各期收支!$C$57)^(-(4*輸入與假設!$C$29-MAX(0,輸入與假設!D$154-(輸入與假設!$C$27+運營_產能與收入!$C$62/3)))/4)*(1-(1+各期收支!$C$57)^(-MIN(MAX(0,輸入與假設!D$154-(輸入與假設!$C$27+運營_產能與收入!$C$62/3)),輸入與假設!$C$28)/4))/(1-(1+各期收支!$C$57)^(-0.25)))) -> 13.371371 | E60: =IF(OR(運營_產能與收入!$C$62<=0,運營_產能與收入!$C$68<=0),1*輸入與假設!$C$26/輸入與假設!$C$28/輸入與假設!$C$29/4/((1+各期收支!$C$57)^0.25-1)*(MIN(MAX(0,輸入與假設!E$154-(輸入與假設!$C$27)),輸入與假設!$C$28)-(1+各期收支!$C$57)^(-(4*輸入與假設!$C$29-MAX(0,輸入與假設!E$154-(輸入與假設!$C$27)))/4)*(1-(1+各期收支!$C$57)^(-MIN(MAX(0,輸入與假設!E$154-(輸入與假設!$C$27)),輸入與假設!$C$28)/4))/(1-(1+各期收支!$C$57)^(-0.25))),(1-運營_產能與收入!$C$68)*輸入與假設!$C$26/輸入與假設!$C$28/輸入與假設!$C$29/4/((1+各期收支!$C$57)^0.25-1)*(MIN(MAX(0,輸入與假設!E$154-(輸入與假設!$C$27)),輸入與假設!$C$28)-(1+各期收支!$C$57)^(-(4*輸入與假設!$C$29-MAX(0,輸入與假設!E$154-(輸入與假設!$C$27)))/4)*(1-(1+各期收支!$C$57)^(-MIN(MAX(0,輸入與假設!E$154-(輸入與假設!$C$27)),輸入與假設!$C$28)/4))/(1-(1+各期收支!$C$57)^(-0.25)))+運營_產能與收入!$C$68*輸入與假設!$C$26/輸入與假設!$C$28/輸入與假設!$C$29/4/((1+各期收支!$C$57)^0.25-1)*(MIN(MAX(0,輸入與假設!E$154-(輸入與假設!$C$27+運營_產能與收入!$C$62/3)),輸入與假設!$C$28)-(1+各期收支!$C$57)^(-(4*輸入與假設!$C$29-MAX(0,輸入與假設!E$154-(輸入與假設!$C$27+運營_產能與收入!$C$62/3)))/4)*(1-(1+各期收支!$C$57)^(-MIN(MAX(0,輸入與假設!E$154-(輸入與假設!$C$27+運營_產能與收入!$C$62/3)),輸入與假設!$C$28)/4))/(1-(1+各期收支!$C$57)^(-0.25)))) -> 10.226845 | F60: =IF(OR(運營_產能與收入!$C$62<=0,運營_產能與收入!$C$68<=0),1*輸入與假設!$C$26/輸入與假設!$C$28/輸入與假設!$C$29/4/((1+各期收支!$C$57)^0.25-1)*(MIN(MAX(0,輸入與假設!F$154-(輸入與假設!$C$27)),輸入與假設!$C$28)-(1+各期收支!$C$57)^(-(4*輸入與假設!$C$29-MAX(0,輸入與假設!F$154-(輸入與假設!$C$27)))/4)*(1-(1+各期收支!$C$57)^(-MIN(MAX(0,輸入與假設!F$154-(輸入與假設!$C$27)),輸入與假設!$C$28)/4))/(1-(1+各期收支!$C$57)^(-0.25))),(1-運營_產能與收入!$C$68)*輸入與假設!$C$26/輸入與假設!$C$28/輸入與假設!$C$29/4/((1+各期收支!$C$57)^0.25-1)*(MIN(MAX(0,輸入與假設!F$154-(輸入與假設!$C$27)),輸入與假設!$C$28)-(1+各期收支!$C$57)^(-(4*輸入與假設!$C$29-MAX(0,輸入與假設!F$154-(輸入與假設!$C$27)))/4)*(1-(1+各期收支!$C$57)^(-MIN(MAX(0,輸入與假設!F$154-(輸入與假設!$C$27)),輸入與假設!$C$28)/4))/(1-(1+各期收支!$C$57)^(-0.25)))+運營_產能與收入!$C$68*輸入與假設!$C$26/輸入與假設!$C$28/輸入與假設!$C$29/4/((1+各期收支!$C$57)^0.25-1)*(MIN(MAX(0,輸入與假設!F$154-(輸入與假設!$C$27+運營_產能與收入!$C$62/3)),輸入與假設!$C$28)-(1+各期收支!$C$57)^(-(4*輸入與假設!$C$29-MAX(0,輸入與假設!F$154-(輸入與假設!$C$27+運營_產能與收入!$C$62/3)))/4)*(1-(1+各期收支!$C$57)^(-MIN(MAX(0,輸入與假設!F$154-(輸入與假設!$C$27+運營_產能與收入!$C$62/3)),輸入與假設!$C$28)/4))/(1-(1+各期收支!$C$57)^(-0.25)))) -> 6.8213232 | G60: =IF(OR(運營_產能與收入!$C$62<=0,運營_產能與收入!$C$68<=0),1*輸入與假設!$C$26/輸入與假設!$C$28/輸入與假設!$C$29/4/((1+各期收支!$C$57)^0.25-1)*(MIN(MAX(0,輸入與假設!G$154-(輸入與假設!$C$27)),輸入與假設!$C$28)-(1+各期收支!$C$57)^(-(4*輸入與假設!$C$29-MAX(0,輸入與假設!G$154-(輸入與假設!$C$27)))/4)*(1-(1+各期收支!$C$57)^(-MIN(MAX(0,輸入與假設!G$154-(輸入與假設!$C$27)),輸入與假設!$C$28)/4))/(1-(1+各期收支!$C$57)^(-0.25))),(1-運營_產能與收入!$C$68)*輸入與假設!$C$26/輸入與假設!$C$28/輸入與假設!$C$29/4/((1+各期收支!$C$57)^0.25-1)*(MIN(MAX(0,輸入與假設!G$154-(輸入與假設!$C$27)),輸入與假設!$C$28)-(1+各期收支!$C$57)^(-(4*輸入與假設!$C$29-MAX(0,輸入與假設!G$154-(輸入與假設!$C$27)))/4)*(1-(1+各期收支!$C$57)^(-MIN(MAX(0,輸入與假設!G$154-(輸入與假設!$C$27)),輸入與假設!$C$28)/4))/(1-(1+各期收支!$C$57)^(-0.25)))+運營_產能與收入!$C$68*輸入與假設!$C$26/輸入與假設!$C$28/輸入與假設!$C$29/4/((1+各期收支!$C$57)^0.25-1)*(MIN(MAX(0,輸入與假設!G$154-(輸入與假設!$C$27+運營_產能與收入!$C$62/3)),輸入與假設!$C$28)-(1+各期收支!$C$57)^(-(4*輸入與假設!$C$29-MAX(0,輸入與假設!G$154-(輸入與假設!$C$27+運營_產能與收入!$C$62/3)))/4)*(1-(1+各期收支!$C$57)^(-MIN(MAX(0,輸入與假設!G$154-(輸入與假設!$C$27+運營_產能與收入!$C$62/3)),輸入與假設!$C$28)/4))/(1-(1+各期收支!$C$57)^(-0.25)))) -> 3.1331434 | I60: 每季起租 總額 ÷ 季數、每筆季末付租：已起租各筆剩餘租金現值合計（延誤連動部分起算季延後 延誤月數 ÷ 3）
A61: 租賃負債合計（期末） | B61: US$m | C61: =C59+C60 -> 21.657314 | D61: =D59+D60 -> 23.748097 | E61: =E59+E60 -> 18.89958 | F61: =F59+F60 -> 13.816186 | G61: =G59+G60 -> 8.2546728
A63: 期前融資瀑布（缺口在需要前一期先融好：額度 → 資產層新債 → 股權）
A64: 用途（不含新債利息） | B64: US$m | C64: =C13+C17+C18+C23+C25+C26+C27+C28+C29+C24 -> 655.06684 | D64: =D13+D17+D18+D23+D25+D26+D27+D28+D29+D24 -> 615.27205 | E64: =E13+E17+E18+E23+E25+E26+E27+E28+E29+E24 -> 194.66919 | F64: =F13+F17+F18+F23+F25+F26+F27+F28+F29+F24 -> 220.14796 | G64: =G13+G17+G18+G23+G25+G26+G27+G28+G29+G24 -> 288.06668 | I64: 避免循環參照：直接由各支出列加總
A65: 新債期初餘額 | B65: US$m | C65: =0 -> 0 | D65: =C92 -> 0 | E65: =D92 -> 20 | F65: =E92 -> 42.193297 | G65: =F92 -> 70.825218
A66: 新債利率 × 期間長度 | B66: % | C66: =C20*運營_產能與收入!C7 -> 0.0475 | D66: =D20*運營_產能與收入!D7 -> 0.095 | E66: =E20*運營_產能與收入!E7 -> 0.095 | F66: =F20*運營_產能與收入!F7 -> 0.095 | G66: =G20*運營_產能與收入!G7 -> 0.095
A67: 高息債期初餘額 | B67: US$m | C67: =0 -> 0 | D67: =C94 -> 0 | E67: =D94 -> 0 | F67: =E94 -> 0 | G67: =F94 -> 0
A68: 可轉債（瀑布）期初餘額 | B68: US$m | C68: =0 -> 0 | D68: =C95 -> 0 | E68: =D95 -> 45.456196 | F68: =E95 -> 96.896701 | G68: =F95 -> 96.896701
A69: 可轉債票息 × 期間長度 | B69: % | C69: =輸入與假設!$C$213*運營_產能與收入!C7 -> 0.025 | D69: =輸入與假設!$C$213*運營_產能與收入!D7 -> 0.05 | E69: =輸入與假設!$C$213*運營_產能與收入!E7 -> 0.05 | F69: =輸入與假設!$C$213*運營_產能與收入!F7 -> 0.05 | G69: =輸入與假設!$C$213*運營_產能與收入!G7 -> 0.05
A70: 高息債利率 × 期間長度 | B70: % | C70: =(輸入與假設!$C$215+IF(輸入與假設!$C$218=1,MAX(0,輸入與假設!$C$217-輸入與假設!$C$219)/10000*輸入與假設!$C$220,0))*運營_產能與收入!C7 -> 0.06 | D70: =(輸入與假設!$C$215+IF(輸入與假設!$C$218=1,MAX(0,輸入與假設!$C$217-輸入與假設!$C$219)/10000*輸入與假設!$C$220,0))*運營_產能與收入!D7 -> 0.12 | E70: =(輸入與假設!$C$215+IF(輸入與假設!$C$218=1,MAX(0,輸入與假設!$C$217-輸入與假設!$C$219)/10000*輸入與假設!$C$220,0))*運營_產能與收入!E7 -> 0.12 | F70: =(輸入與假設!$C$215+IF(輸入與假設!$C$218=1,MAX(0,輸入與假設!$C$217-輸入與假設!$C$219)/10000*輸入與假設!$C$220,0))*運營_產能與收入!F7 -> 0.12 | G70: =(輸入與假設!$C$215+IF(輸入與假設!$C$218=1,MAX(0,輸入與假設!$C$217-輸入與假設!$C$219)/10000*輸入與假設!$C$220,0))*運營_產能與收入!G7 -> 0.12
A71: 融資前現金（扣既有新債利息） | B71: US$m | C71: =C19+C41+C42+C43+C44+C51-C64-C66*C65-C70*C67-C69*C68 -> 136.21658 | D71: =D19+D41+D42+D43+D44+D51-D64-D66*D65-D70*D67-D69*D68 -> -31.283387 | E71: =E19+E41+E42+E43+E44+E51-E64-E66*E65-E70*E67-E69*E68 -> -38.953414 | F71: =F19+F41+F42+F43+F44+F51-F64-F66*F65-F70*F67-F69*F68 -> 4.0881122 | G71: =G19+G41+G42+G43+G44+G51-G64-G66*G65-G70*G67-G69*G68 -> 4.6459106
A72: 融資需求（補足至最低現金） | B72: US$m | C72: =MAX(0,輸入與假設!$C$204-C71) -> 0 | D72: =MAX(0,輸入與假設!$C$204-D71) -> 61.283387 | E72: =MAX(0,輸入與假設!$C$204-E71) -> 68.953414 | F72: =MAX(0,輸入與假設!$C$204-F71) -> 25.911888 | G72: =MAX(0,輸入與假設!$C$204-G71) -> 25.354089
A73: 期初 backlog | B73: US$m | C73: =輸入與假設!$C$31+輸入與假設!$C$32 -> 75.146 | D73: =C75 -> 151.46514 | E73: =D75 -> 259.47586 | F73: =E75 -> 358.00769 | G73: =F75 -> 231.98525 | I73: FY26 期初＝6/30 RPO 75.146＋期後新增 0.0
A74: 新簽合約增量（年化增量×年期） | B74: US$m | C74: =MAX(0,運營_產能與收入!C24/運營_產能與收入!C7-0)*輸入與假設!$C$201 -> 117.53539 | D74: =MAX(0,運營_產能與收入!D24/運營_產能與收入!D7-運營_產能與收入!C24/運營_產能與收入!C7)*輸入與假設!$C$201 -> 285.66473 | E74: =MAX(0,運營_產能與收入!E24/運營_產能與收入!E7-運營_產能與收入!D24/運營_產能與收入!D7)*輸入與假設!$C$201 -> 364.79533 | F74: =MAX(0,運營_產能與收入!F24/運營_產能與收入!F7-運營_產能與收入!E24/運營_產能與收入!E7)*輸入與假設!$C$201 -> 194.96406 | G74: =MAX(0,運營_產能與收入!G24/運營_產能與收入!G7-運營_產能與收入!F24/運營_產能與收入!F7)*輸入與假設!$C$201 -> 145.5075
A75: 期末 backlog | B75: US$m | C75: =C73-運營_產能與收入!C18-運營_產能與收入!C24+C74 -> 151.46514 | D75: =D73-運營_產能與收入!D18-運營_產能與收入!D24+D74 -> 259.47586 | E75: =E73-運營_產能與收入!E18-運營_產能與收入!E24+E74 -> 358.00769 | F75: =F73-運營_產能與收入!F18-運營_產能與收入!F24+F74 -> 231.98525 | G75: =G73-運營_產能與收入!G18-運營_產能與收入!G24+G74 -> 8.00375 | I75: ＝期初 − 排程認列 − 新簽約認列 ＋ 新簽合約增量
A76: 既有債務＋期後可轉債（期末） | B76: US$m | C76: =IF(輸入與假設!$C$197=1,資產負債_既有債務!C28,資產負債_既有債務!$E$8)+資產負債_既有債務!$E$11+資產負債_既有債務!C33+資產負債_既有債務!C44 -> 460.677 | D76: =IF(輸入與假設!$C$197=1,資產負債_既有債務!D28,資產負債_既有債務!$E$8)+資產負債_既有債務!$E$11+資產負債_既有債務!D33+資產負債_既有債務!D44 -> 677.055 | E76: =IF(輸入與假設!$C$197=1,資產負債_既有債務!E28,資產負債_既有債務!$E$8)+資產負債_既有債務!$E$11+資產負債_既有債務!E33+資產負債_既有債務!E44 -> 640.0955 | F76: =IF(輸入與假設!$C$197=1,資產負債_既有債務!F28,資產負債_既有債務!$E$8)+資產負債_既有債務!$E$11+資產負債_既有債務!F33+資產負債_既有債務!F44 -> 588.424 | G76: =IF(輸入與假設!$C$197=1,資產負債_既有債務!G28,資產負債_既有債務!$E$8)+資產負債_既有債務!$E$11+資產負債_既有債務!G33+資產負債_既有債務!G44 -> 557.7115 | I76: ＝(依到期表遞減的既有本金，若關閉攤還則維持 315.339)＋期後新發可轉債 0＋NC-1 專案貸款期末餘額（v0.1c）
A77: 債務上限（倍數 × 當期 EBITDA；或債務／backlog） | B77: US$m | C77: =IF(輸入與假設!$C$199="leaseAdj",輸入與假設!$C$200*(損益!C22+C17)/運營_產能與收入!C7-C61,IF(輸入與假設!$C$199="ebitda",輸入與假設!$C$200*損益!C22/運營_產能與收入!C7,輸入與假設!$C$198*C75)) -> 62.12729 | D77: =IF(輸入與假設!$C$199="leaseAdj",輸入與假設!$C$200*(損益!D22+D17)/運營_產能與收入!D7-D61,IF(輸入與假設!$C$199="ebitda",輸入與假設!$C$200*損益!D22/運營_產能與收入!D7,輸入與假設!$C$198*D75)) -> 127.02392 | E77: =IF(輸入與假設!$C$199="leaseAdj",輸入與假設!$C$200*(損益!E22+E17)/運營_產能與收入!E7-E61,IF(輸入與假設!$C$199="ebitda",輸入與假設!$C$200*損益!E22/運營_產能與收入!E7,輸入與假設!$C$198*E75)) -> 451.33249 | F77: =IF(輸入與假設!$C$199="leaseAdj",輸入與假設!$C$200*(損益!F22+F17)/運營_產能與收入!F7-F61,IF(輸入與假設!$C$199="ebitda",輸入與假設!$C$200*損益!F22/運營_產能與收入!F7,輸入與假設!$C$198*F75)) -> 737.30115 | G77: =IF(輸入與假設!$C$199="leaseAdj",輸入與假設!$C$200*(損益!G22+G17)/運營_產能與收入!G7-G61,IF(輸入與假設!$C$199="ebitda",輸入與假設!$C$200*損益!G22/運營_產能與收入!G7,輸入與假設!$C$198*G75)) -> 1049.1883 | I77: leaseAdj：總債務 ≤ 倍數 ×(損益 EBITDA＋租金)（年化）− 租賃負債（v0.2）；ebitda：總債務 ≤ 倍數 × 損益 EBITDA（年化）；backlog：總債務 ≤ 倍數 × 期末 backlog（模板）
A78: 未動用額度（期初） | B78: US$m | C78: =IF(輸入與假設!$C$189=1,輸入與假設!$C$188,0) -> 20 | D78: =C93 -> 20 | E78: =D93 -> 0 | F78: =E93 -> 0 | G78: =F93 -> 0 | I78: ＝前期期末未動用（NC-1 專案貸款改為排程貸款，不在額度內；WhiteFiber v0.1c）
A79: 新債可借上限 | B79: US$m | C79: =MAX(0,C77-(C76-資產負債_既有債務!C44+C65+C68),C78) -> 20 | D79: =MAX(0,D77-(D76-資產負債_既有債務!D44+D65+D68),D78) -> 20 | E79: =MAX(0,E77-(E76-資產負債_既有債務!E44+E65+E68),E78) -> 22.193297 | F79: =MAX(0,F77-(F76-資產負債_既有債務!F44+F65+F68),F78) -> 255.48715 | G79: =MAX(0,G77-(G76-資產負債_既有債務!G44+G65+G68),G78) -> 538.74242 | I79: ＝MAX(上限 −（既有債務 − NC-1 專案貸款）− 期初新債 − 期初瀑布可轉債, 未動用額度)；專案貸款以 NC-1 合約現金流與資產獨立核貸，不占公司層級上限（v0.1c）
A80: 新債舉借 | B80: US$m | C80: =MIN(C79,C72/(1-C66)) -> 0 | D80: =MIN(D79,D72/(1-D66)) -> 20 | E80: =MIN(E79,E72/(1-E66)) -> 22.193297 | F80: =MIN(F79,F72/(1-F66)) -> 28.63192 | G80: =MIN(G79,G72/(1-G66)) -> 28.015568 | I80: 期前融資：期初到位，當期全額計息，所以需求要除以 (1−利率×期間)
A81: 債務後剩餘需求 | B81: US$m | C81: =MAX(0,C72+C66*C80-C80) -> 0 | D81: =MAX(0,D72+D66*D80-D80) -> 43.183387 | E81: =MAX(0,E72+E66*E80-E80) -> 48.868479 | F81: =MAX(0,F72+F66*F80-F80) -> 0 | G81: =MAX(0,G72+G66*G80-G80) -> 0
A82: 可轉債可發行上限 | B82: US$m | C82: =MAX(0,輸入與假設!$C$212)*運營_產能與收入!C7 -> 37.95 | D82: =MAX(0,輸入與假設!$C$212)*運營_產能與收入!D7 -> 75.9 | E82: =MAX(0,輸入與假設!$C$212)*運營_產能與收入!E7 -> 75.9 | F82: =MAX(0,輸入與假設!$C$212)*運營_產能與收入!F7 -> 75.9 | G82: =MAX(0,輸入與假設!$C$212)*運營_產能與收入!G7 -> 75.9 | I82: ＝每年上限（隨情境）× 期間長度
A83: 可轉債發行 | B83: US$m | C83: =MIN(C82,C81/(1-C69)) -> 0 | D83: =MIN(D82,D81/(1-D69)) -> 45.456196 | E83: =MIN(E82,E81/(1-E69)) -> 51.440505 | F83: =MIN(F82,F81/(1-F69)) -> 0 | G83: =MIN(G82,G81/(1-G69)) -> 0 | I83: 期前融資：期初到位、當期全額計息
A84: 可轉債後剩餘需求 | B84: US$m | C84: =MAX(0,C81+C69*C83-C83) -> 0 | D84: =MAX(0,D81+D69*D83-D83) -> 0 | E84: =MAX(0,E81+E69*E83-E83) -> 0 | F84: =MAX(0,F81+F69*F83-F83) -> 0 | G84: =MAX(0,G81+G69*G83-G83) -> 0
A85: 每年股權吸收上限 | B85: US$m | C85: =IF(輸入與假設!$C$207>=9,1E+099,輸入與假設!$C$207*輸入與假設!$C$205*輸入與假設!$C$208*運營_產能與收入!C7) -> 37.968187 | D85: =IF(輸入與假設!$C$207>=9,1E+099,輸入與假設!$C$207*輸入與假設!$C$205*輸入與假設!$C$208*運營_產能與收入!D7) -> 75.936374 | E85: =IF(輸入與假設!$C$207>=9,1E+099,輸入與假設!$C$207*輸入與假設!$C$205*輸入與假設!$C$208*運營_產能與收入!E7) -> 75.936374 | F85: =IF(輸入與假設!$C$207>=9,1E+099,輸入與假設!$C$207*輸入與假設!$C$205*輸入與假設!$C$208*運營_產能與收入!F7) -> 75.936374 | G85: =IF(輸入與假設!$C$207>=9,1E+099,輸入與假設!$C$207*輸入與假設!$C$205*輸入與假設!$C$208*運營_產能與收入!G7) -> 75.936374 | I85: ＝現市值（發行參考價 × 45.1197m 股）× 上限 % × 期間長度
A86: 股權募資 | B86: US$m | C86: =MIN(C84,C85) -> 0 | D86: =MIN(D84,D85) -> 0 | E86: =MIN(E84,E85) -> 0 | F86: =MIN(F84,F85) -> 0 | G86: =MIN(G84,G85) -> 0
A87: 高息債舉借（溢出） | B87: US$m | C87: =(C84-C86)/(1-C70) -> 0 | D87: =(D84-D86)/(1-D70) -> 0 | E87: =(E84-E86)/(1-E70) -> 0 | F87: =(F84-F86)/(1-F70) -> 0 | G87: =(G84-G86)/(1-G70) -> 0
A88: 新債＋高息債利息（期初餘額＋本期舉借） | B88: US$m | C88: =C66*(C65+C80)+C70*(C67+C87)+C69*(C68+C83) -> 0 | D88: =D66*(D65+D80)+D70*(D67+D87)+D69*(D68+D83) -> 4.1728098 | E88: =E66*(E65+E80)+E70*(E67+E87)+E69*(E68+E83) -> 8.8531983 | F88: =F66*(F65+F80)+F70*(F67+F87)+F69*(F68+F83) -> 11.573231 | G88: =G66*(G65+G80)+G70*(G67+G87)+G69*(G68+G83) -> 14.23471 | I88: 含瀑布可轉債票息（v0.1b）
A89: 發行價（現價×(1−折價)） | B89: US$ | C89: =輸入與假設!$C$205*(1-輸入與假設!$C$206) -> 15.147 | D89: =輸入與假設!$C$205*(1-輸入與假設!$C$206) -> 15.147 | E89: =輸入與假設!$C$205*(1-輸入與假設!$C$206) -> 15.147 | F89: =輸入與假設!$C$205*(1-輸入與假設!$C$206) -> 15.147 | G89: =輸入與假設!$C$205*(1-輸入與假設!$C$206) -> 15.147
A90: 新發行股數 | B90: m | C90: =C86/C89 -> 0 | D90: =D86/D89 -> 0 | E90: =E86/E89 -> 0 | F90: =F86/F89 -> 0 | G90: =G86/G89 -> 0
A91: 累計新股 | B91: m | C91: =C90 -> 0 | D91: =C91+D90 -> 0 | E91: =D91+E90 -> 0 | F91: =E91+F90 -> 0 | G91: =F91+G90 -> 0
A92: 新債期末餘額 | B92: US$m | C92: =C65+C80 -> 0 | D92: =D65+D80 -> 20 | E92: =E65+E80 -> 42.193297 | F92: =F65+F80 -> 70.825218 | G92: =G65+G80 -> 98.840786
A93: 未動用額度（期末） | B93: US$m | C93: =C78-MIN(C78,C80) -> 20 | D93: =D78-MIN(D78,D80) -> 0 | E93: =E78-MIN(E78,E80) -> 0 | F93: =F78-MIN(F78,F80) -> 0 | G93: =G78-MIN(G78,G80) -> 0
A94: 高息債期末餘額 | B94: US$m | C94: =C67+C87 -> 0 | D94: =D67+D87 -> 0 | E94: =E67+E87 -> 0 | F94: =F67+F87 -> 0 | G94: =G67+G87 -> 0
A95: 可轉債（瀑布）期末餘額 | B95: US$m | C95: =C68+C83 -> 0 | D95: =D68+D83 -> 45.456196 | E95: =E68+E83 -> 96.896701 | F95: =F68+F83 -> 96.896701 | G95: =G68+G83 -> 96.896701
A96: 期末總債務（既有＋可轉債＋新債＋高息債） | B96: US$m | C96: =C76+C92+C95+C94 -> 460.677 | D96: =D76+D92+D95+D94 -> 742.5112 | E96: =E76+E92+E95+E94 -> 779.1855 | F96: =F76+F92+F95+F94 -> 756.14592 | G96: =G76+G92+G95+G94 -> 753.44899
A97: 融資前累積現金 | B97: US$m | C97: =C19+C41+C42+C43+C51-C64 -> 136.21658 | D97: =C97+D41+D42-D64 -> -338.40839 | E97: =D97+E41+E42-E64 -> -403.18899 | F97: =E97+F41+F42-F64 -> -420.24768 | G97: =F97+G41+G42-G64 -> -434.02854 | I97: 若不做任何新融資的累積現金；負值＝外部資金需求
A99: 四層橋（驗算）
A100: 期初現金（2025-12-31） | C100: =輸入與假設!$C$290 -> 114.441
A101: ＋ 營運缺口合計 | C101: =SUM(C52:G52) -> -787.02299
A102: ＋ 股權／可轉債合計 | C102: =SUM(C42:G42) -> 217.961
A103: ＋ 1H 實際借款 | C103: =SUM(C43:G43) -> 304.526
A104: − capped call（1H） | C104: =-SUM(C28:G28) -> -120
...

Sheet 季度追蹤
A1: 季度追蹤 — 焦點季的模型／共識／指引／實際與差距（由年度模型拆分；只用於追蹤，不影響年度數字與目標價）
A2: 設定與實際數在『輸入與假設』J 區，共識在 I 區；缺資料顯示「不適用」，實際數空白＝待公布。差距超過門檻的項目附差異原因（拆法＝所屬期間合計差距在門檻內）。第 2 區為 6 季路徑與拆分明細（預設收合）。
A4: 1｜焦點季（『輸入與假設』J 區選擇）：模型／共識／指引／實際與差距
A5: 指標 | B5: 單位 | C5: 模型 | D5: 共識 | E5: 模型 vs 共識 | F5: 指引（低） | G5: 指引（高） | H5: 模型 vs 指引中點 | I5: 實際 | J5: 實際 vs 模型 | K5: 實際 vs 共識 | L5: 實際 vs 指引中點 | M5: 利潤率 pt：模型 vs 共識 | N5: 模型 vs 指引 | O5: 實際 vs 模型 | P5: 實際 vs 共識 | Q5: 實際 vs 指引
A6: 焦點｜營收 | B6: US$m | C6: =INDEX($C$22:$H$22,輸入與假設!$C$373) -> 31.883144 | D6: =INDEX($C$32:$H$32,輸入與假設!$C$373) -> 不適用 | E6: =INDEX($C$41:$H$41,輸入與假設!$C$373) -> 不適用 | F6: 不適用 | G6: 不適用 | H6: =INDEX($C$42:$H$42,輸入與假設!$C$373) -> 不適用 | I6: =IF(ISNUMBER(INDEX($C$35:$H$35,輸入與假設!$C$373)),INDEX($C$35:$H$35,輸入與假設!$C$373),"待公布") -> 待公布 | J6: =INDEX($C$43:$H$43,輸入與假設!$C$373) | K6: =INDEX($C$44:$H$44,輸入與假設!$C$373) | L6: =INDEX($C$45:$H$45,輸入與假設!$C$373)
A7: 焦點｜調整後 EBITDA | B7: US$m | C7: =INDEX($C$28:$H$28,輸入與假設!$C$373) -> 2.4255511 | D7: =INDEX($C$33:$H$33,輸入與假設!$C$373) -> 不適用 | E7: =INDEX($C$46:$H$46,輸入與假設!$C$373) -> 不適用 | F7: 不適用 | G7: 不適用 | H7: =INDEX($C$47:$H$47,輸入與假設!$C$373) -> 不適用 | I7: =IF(ISNUMBER(INDEX($C$36:$H$36,輸入與假設!$C$373)),INDEX($C$36:$H$36,輸入與假設!$C$373),"待公布") -> 待公布 | J7: =INDEX($C$48:$H$48,輸入與假設!$C$373) | K7: =INDEX($C$49:$H$49,輸入與假設!$C$373) | L7: =INDEX($C$50:$H$50,輸入與假設!$C$373) | M7: =INDEX($C$51:$H$51,輸入與假設!$C$373) -> 不適用 | N7: =INDEX($C$52:$H$52,輸入與假設!$C$373) -> 不適用 | O7: =INDEX($C$53:$H$53,輸入與假設!$C$373) | P7: =INDEX($C$54:$H$54,輸入與假設!$C$373) | Q7: =INDEX($C$55:$H$55,輸入與假設!$C$373)
A8: 焦點｜EBITDA 率 | B8: % | C8: =INDEX($C$27:$H$27,輸入與假設!$C$373) -> 0.076076284 | D8: =INDEX($C$34:$H$34,輸入與假設!$C$373) -> 不適用 | E8: =INDEX($C$56:$H$56,輸入與假設!$C$373) -> 不適用 | F8: 不適用 | G8: 不適用 | H8: =INDEX($C$57:$H$57,輸入與假設!$C$373) -> 不適用 | I8: =IF(ISNUMBER(INDEX($C$37:$H$37,輸入與假設!$C$373)),INDEX($C$37:$H$37,輸入與假設!$C$373),"待公布") -> 待公布 | J8: =INDEX($C$58:$H$58,輸入與假設!$C$373) | K8: =INDEX($C$59:$H$59,輸入與假設!$C$373) | L8: =INDEX($C$60:$H$60,輸入與假設!$C$373)
A9: 焦點｜調整後營業利益 | B9: US$m | C9: =INDEX($C$30:$H$30,輸入與假設!$C$373) -> -10.953068 | D9: 不適用 | E9: =INDEX($C$61:$H$61,輸入與假設!$C$373) -> 不適用 | F9: 不適用 | G9: 不適用 | H9: =INDEX($C$62:$H$62,輸入與假設!$C$373) -> 不適用 | I9: =IF(ISNUMBER(INDEX($C$38:$H$38,輸入與假設!$C$373)),INDEX($C$38:$H$38,輸入與假設!$C$373),"待公布") -> 待公布 | J9: =INDEX($C$63:$H$63,輸入與假設!$C$373) | K9: =INDEX($C$64:$H$64,輸入與假設!$C$373) | L9: =INDEX($C$65:$H$65,輸入與假設!$C$373) | M9: =INDEX($C$66:$H$66,輸入與假設!$C$373) -> 不適用 | N9: =INDEX($C$67:$H$67,輸入與假設!$C$373) -> 不適用 | O9: =INDEX($C$68:$H$68,輸入與假設!$C$373) | P9: =INDEX($C$69:$H$69,輸入與假設!$C$373) | Q9: =INDEX($C$70:$H$70,輸入與假設!$C$373)
A10: 焦點｜CapEx（毛額） | B10: US$m | C10: =INDEX($C$31:$H$31,輸入與假設!$C$373) -> 73.489513 | D10: 不適用 | E10: =INDEX($C$71:$H$71,輸入與假設!$C$373) -> 不適用 | F10: 不適用 | G10: 不適用 | H10: =INDEX($C$72:$H$72,輸入與假設!$C$373) -> 不適用 | I10: =IF(ISNUMBER(INDEX($C$39:$H$39,輸入與假設!$C$373)),INDEX($C$39:$H$39,輸入與假設!$C$373),"待公布") -> 待公布 | J10: =INDEX($C$73:$H$73,輸入與假設!$C$373) | K10: =INDEX($C$74:$H$74,輸入與假設!$C$373) | L10: =INDEX($C$75:$H$75,輸入與假設!$C$373)
A11: 焦點｜季末雲端已連網 MW-IT | B11: MW | C11: =INDEX($C$19:$H$19,輸入與假設!$C$373) -> 10.037 | D11: 不適用 | E11: =INDEX($C$76:$H$76,輸入與假設!$C$373) -> 不適用 | F11: 不適用 | G11: 不適用 | H11: =INDEX($C$77:$H$77,輸入與假設!$C$373) -> 不適用 | I11: =IF(ISNUMBER(INDEX($C$40:$H$40,輸入與假設!$C$373)),INDEX($C$40:$H$40,輸入與假設!$C$373),"待公布") -> 待公布 | J11: =INDEX($C$78:$H$78,輸入與假設!$C$373) | K11: =INDEX($C$79:$H$79,輸入與假設!$C$373) | L11: =INDEX($C$80:$H$80,輸入與假設!$C$373)
A12: 焦點｜季度 | C12: =INDEX($C$16:$H$16,輸入與假設!$C$373) -> Q3 2026
A13: 焦點｜差異原因 | C13: =IF(INDEX($C$117:$H$117,輸入與假設!$C$373)="","無（差距皆在 "&IF(ROUND(ABS(輸入與假設!$C$367)*100,4)=INT(ROUND(ABS(輸入與假設!$C$367)*100,4)),TEXT(ROUND(ABS(輸入與假設!$C$367)*100,4),"0"),TEXT(ROUND(ABS(輸入與假設!$C$367)*100,4),"0.0"))&"%"&" 以內）",INDEX($C$117:$H$117,輸入與假設!$C$373)) -> 無（差距皆在 5% 以內）
A15: 2｜6 季路徑、共識、指引、實際與差距（明細；第 1 區以焦點季引用本區）
A16: 項目 | B16: 單位 | C16: Q3 2026 | D16: Q4 2026 | E16: Q1 2027 | F16: Q2 2027 | G16: Q3 2027 | H16: Q4 2027
A17: 所屬期間 | C17: =輸入與假設!C$372 -> 1 | D17: =輸入與假設!D$372 -> 1 | E17: =輸入與假設!E$372 -> 2 | F17: =輸入與假設!F$372 -> 2 | G17: =輸入與假設!G$372 -> 2 | H17: =輸入與假設!H$372 -> 2 | J17: 1＝2H26、2＝FY27
A18: 季序 | C18: 1 | D18: 2 | E18: 3 | F18: 4 | G18: 5 | H18: 6 | J18: EBITDA 率直線的 x 軸
A19: 季末雲端已連網 MW-IT（模型） | B19: MW | C19: =輸入與假設!$C$375+(輸入與假設!C$43-輸入與假設!$C$375)*1/2 -> 10.037 | D19: =輸入與假設!$C$375+(輸入與假設!C$43-輸入與假設!$C$375)*2/2 -> 14.574 | E19: =輸入與假設!C$43+(輸入與假設!D$43-輸入與假設!C$43)*1/4 -> 15.0675 | F19: =輸入與假設!C$43+(輸入與假設!D$43-輸入與假設!C$43)*2/4 -> 15.561 | G19: =輸入與假設!C$43+(輸入與假設!D$43-輸入與假設!C$43)*3/4 -> 16.0545 | H19: =輸入與假設!C$43+(輸入與假設!D$43-輸入與假設!C$43)*4/4 -> 16.548 | J19: 期初與期末 Accepted 之間線性內插；第 1 期起點見 J 區
A20: 平均在役 MW（Billable，拆分依據） | B20: MW | C20: =輸入與假設!$C$36+(運營_產能與收入!C$11-輸入與假設!$C$36)*1/4 -> 3.69375 | D20: =輸入與假設!$C$36+(運營_產能與收入!C$11-輸入與假設!$C$36)*3/4 -> 5.78125 | E20: =運營_產能與收入!C$11+(運營_產能與收入!D$11-運營_產能與收入!C$11)*1/8 -> 7.67125 | F20: =運營_產能與收入!C$11+(運營_產能與收入!D$11-運營_產能與收入!C$11)*3/8 -> 9.36375 | G20: =運營_產能與收入!C$11+(運營_產能與收入!D$11-運營_產能與收入!C$11)*5/8 -> 11.05625 | H20: =運營_產能與收入!C$11+(運營_產能與收入!D$11-運營_產能與收入!C$11)*7/8 -> 12.74875 | J20: 期初與期末 Billable 之間線性內插的季平均
A21: 季內新增 Accepted MW | B21: MW | C21: =C19-輸入與假設!$C$375 -> 4.537 | D21: =D19-C19 -> 4.537 | E21: =E19-輸入與假設!C$43 -> 0.4935 | F21: =F19-E19 -> 0.4935 | G21: =G19-F19 -> 0.4935 | H21: =H19-G19 -> 0.4935 | J21: CapEx 拆分依據
A22: 營收（模型） | B22: US$m | C22: =輸入與假設!$C$374+1*(損益!C9-2*輸入與假設!$C$374)/3 -> 31.883144 | D22: =輸入與假設!$C$374+2*(損益!C9-2*輸入與假設!$C$374)/3 -> 47.227287 | E22: =損益!D9*E20/(E20+F20+G20+H20) -> 52.250451 | F22: =損益!D9*F20/(E20+F20+G20+H20) -> 63.778414 | G22: =損益!D9*G20/(E20+F20+G20+H20) -> 75.306377 | H22: =損益!D9*H20/(E20+F20+G20+H20) -> 86.834341 | J22: 拆分方法見『輸入與假設』J 區與 HTML「拆分方法」
A23: EBITDA 率直線｜各期營收合計 S | C23: =C22+D22 -> 79.110431 | D23: =E22+F22+G22+H22 -> 278.16958 | J23: 欄＝期間（2H26、FY27）
A24: EBITDA 率直線｜營收 × 季序合計 T | C24: =C22*C18+D22*D18 -> 126.33772 | D24: =E22*E18+F22*F18+G22*G18+H22*H18 -> 1309.4029 | J24: 欄＝期間（2H26、FY27）
A25: EBITDA 率直線｜年度 EBITDA E | C25: =損益!C22 -> 6.212729 | D25: =損益!D22 -> 25.404783 | J25: 欄＝期間（2H26、FY27）
A26: EBITDA 率直線｜截距 a／斜率 b | C26: =(C25*D24-C24*D25)/(C23*D24-C24*D23) -> 0.071962108 | D26: =(C23*D25-D23*C25)/(C23*D24-C24*D23) -> 0.0041141755 | J26: 解兩式：Σ營收×(a＋b×季序)＝各期年度 EBITDA
A27: EBITDA 率（模型） | B27: % | C27: =$C$26+$D$26*C18 -> 0.076076284 | D27: =$C$26+$D$26*D18 -> 0.080190459 | E27: =$C$26+$D$26*E18 -> 0.084304635 | F27: =$C$26+$D$26*F18 -> 0.08841881 | G27: =$C$26+$D$26*G18 -> 0.092532986 | H27: =$C$26+$D$26*H18 -> 0.096647161 | J27: 跨季一條直線，季度 EBITDA 加總＝年度
A28: 調整後 EBITDA（模型） | B28: US$m | C28: =C22*C27 -> 2.4255511 | D28: =D22*D27 -> 3.7871779 | E28: =E22*E27 -> 4.4049552 | F28: =F22*F27 -> 5.6392115 | G28: =G22*G27 -> 6.9683239 | H28: =H22*H27 -> 8.3922925
A29: 車隊折舊（模型） | B29: US$m | C29: =(輸入與假設!C$173+運營_產能與收入!C$66*1/4)/輸入與假設!$C$139*輸入與假設!C$41/2+(輸入與假設!C$110+輸入與假設!C$107*1/4)/輸入與假設!$C$109*輸入與假設!C$41/2 -> 13.378619 | D29: =(輸入與假設!C$173+運營_產能與收入!C$66*3/4)/輸入與假設!$C$139*輸入與假設!C$41/2+(輸入與假設!C$110+輸入與假設!C$107*3/4)/輸入與假設!$C$109*輸入與假設!C$41/2 -> 15.068357 | E29: =(輸入與假設!D$173+運營_產能與收入!D$66*1/8)/輸入與假設!$C$139*輸入與假設!D$41/4+(輸入與假設!D$110+輸入與假設!D$107*1/8)/輸入與假設!$C$109*輸入與假設!D$41/4 -> 17.103233 | F29: =(輸入與假設!D$173+運營_產能與收入!D$66*3/8)/輸入與假設!$C$139*輸入與假設!D$41/4+(輸入與假設!D$110+輸入與假設!D$107*3/8)/輸入與假設!$C$109*輸入與假設!D$41/4 -> 19.483249 | G29: =(輸入與假設!D$173+運營_產能與收入!D$66*5/8)/輸入與假設!$C$139*輸入與假設!D$41/4+(輸入與假設!D$110+輸入與假設!D$107*5/8)/輸入與假設!$C$109*輸入與假設!D$41/4 -> 21.863264 | H29: =(輸入與假設!D$173+運營_產能與收入!D$66*7/8)/輸入與假設!$C$139*輸入與假設!D$41/4+(輸入與假設!D$110+輸入與假設!D$107*7/8)/輸入與假設!$C$109*輸入與假設!D$41/4 -> 24.243279 | J29: 依期內平均 PP&E（與年度車隊折舊公式相同；含託管建物 D&A）
A30: 調整後營業利益（模型） | B30: US$m | C30: =C28-C29 -> -10.953068 | D30: =D28-D29 -> -11.281179 | E30: =E28-E29 -> -12.698278 | F30: =F28-F29 -> -13.844037 | G30: =G28-G29 -> -14.89494 | H30: =H28-H29 -> -15.850987 | J30: ＝調整後 EBITDA − 車隊折舊（未扣 SBC）
A31: CapEx（毛額）（模型） | B31: US$m | C31: =IF((C21+D21)>0,輸入與假設!C$175*C21/(C21+D21),輸入與假設!C$175/2) -> 73.489513 | D31: =IF((C21+D21)>0,輸入與假設!C$175*D21/(C21+D21),輸入與假設!C$175/2) -> 73.489513 | E31: =IF((E21+F21+G21+H21)>0,輸入與假設!D$175*E21/(E21+F21+G21+H21),輸入與假設!D$175/4) -> 106.7864 | F31: =IF((E21+F21+G21+H21)>0,輸入與假設!D$175*F21/(E21+F21+G21+H21),輸入與假設!D$175/4) -> 106.7864 | G31: =IF((E21+F21+G21+H21)>0,輸入與假設!D$175*G21/(E21+F21+G21+H21),輸入與假設!D$175/4) -> 106.7864 | H31: =IF((E21+F21+G21+H21)>0,輸入與假設!D$175*H21/(E21+F21+G21+H21),輸入與假設!D$175/4) -> 106.7864 | J31: 依季內新增 Accepted MW
A32: 共識｜營收 | B32: US$m | C32: 不適用 | D32: 不適用 | E32: 不適用 | F32: 不適用 | G32: 不適用 | H32: 不適用 | J32: I 區季度共識 [Interested-party]
A33: 共識｜調整後 EBITDA | B33: US$m | C33: 不適用 | D33: 不適用 | E33: 不適用 | F33: 不適用 | G33: 不適用 | H33: 不適用 | J33: I 區季度共識 [Interested-party]
A34: 共識｜EBITDA 率 [Derived] | B34: % | C34: 不適用 | D34: 不適用 | E34: 不適用 | F34: 不適用 | G34: 不適用 | H34: 不適用 | J34: ＝共識 EBITDA ÷ 共識營收
A35: 實際｜營收 | B35: US$m | C35: =IF(ISNUMBER(輸入與假設!C$376),輸入與假設!C$376,"") | D35: =IF(ISNUMBER(輸入與假設!D$376),輸入與假設!D$376,"") | E35: =IF(ISNUMBER(輸入與假設!E$376),輸入與假設!E$376,"") | F35: =IF(ISNUMBER(輸入與假設!F$376),輸入與假設!F$376,"") | G35: =IF(ISNUMBER(輸入與假設!G$376),輸入與假設!G$376,"") | H35: =IF(ISNUMBER(輸入與假設!H$376),輸入與假設!H$376,"")
A36: 實際｜調整後 EBITDA | B36: US$m | C36: =IF(ISNUMBER(輸入與假設!C$377),輸入與假設!C$377,"") | D36: =IF(ISNUMBER(輸入與假設!D$377),輸入與假設!D$377,"") | E36: =IF(ISNUMBER(輸入與假設!E$377),輸入與假設!E$377,"") | F36: =IF(ISNUMBER(輸入與假設!F$377),輸入與假設!F$377,"") | G36: =IF(ISNUMBER(輸入與假設!G$377),輸入與假設!G$377,"") | H36: =IF(ISNUMBER(輸入與假設!H$377),輸入與假設!H$377,"")
A37: 實際｜EBITDA 率 | B37: % | C37: =IF(AND(ISNUMBER(輸入與假設!C$377),ISNUMBER(輸入與假設!C$376)),輸入與假設!C$377/輸入與假設!C$376,"") | D37: =IF(AND(ISNUMBER(輸入與假設!D$377),ISNUMBER(輸入與假設!D$376)),輸入與假設!D$377/輸入與假設!D$376,"") | E37: =IF(AND(ISNUMBER(輸入與假設!E$377),ISNUMBER(輸入與假設!E$376)),輸入與假設!E$377/輸入與假設!E$376,"") | F37: =IF(AND(ISNUMBER(輸入與假設!F$377),ISNUMBER(輸入與假設!F$376)),輸入與假設!F$377/輸入與假設!F$376,"") | G37: =IF(AND(ISNUMBER(輸入與假設!G$377),ISNUMBER(輸入與假設!G$376)),輸入與假設!G$377/輸入與假設!G$376,"") | H37: =IF(AND(ISNUMBER(輸入與假設!H$377),ISNUMBER(輸入與假設!H$376)),輸入與假設!H$377/輸入與假設!H$376,"") | J37: ＝實際 EBITDA ÷ 實際營收
A38: 實際｜調整後營業利益 | B38: US$m | C38: =IF(ISNUMBER(輸入與假設!C$378),輸入與假設!C$378,"") | D38: =IF(ISNUMBER(輸入與假設!D$378),輸入與假設!D$378,"") | E38: =IF(ISNUMBER(輸入與假設!E$378),輸入與假設!E$378,"") | F38: =IF(ISNUMBER(輸入與假設!F$378),輸入與假設!F$378,"") | G38: =IF(ISNUMBER(輸入與假設!G$378),輸入與假設!G$378,"") | H38: =IF(ISNUMBER(輸入與假設!H$378),輸入與假設!H$378,"")
A39: 實際｜CapEx（毛額） | B39: US$m | C39: =IF(ISNUMBER(輸入與假設!C$379),輸入與假設!C$379,"") | D39: =IF(ISNUMBER(輸入與假設!D$379),輸入與假設!D$379,"") | E39: =IF(ISNUMBER(輸入與假設!E$379),輸入與假設!E$379,"") | F39: =IF(ISNUMBER(輸入與假設!F$379),輸入與假設!F$379,"") | G39: =IF(ISNUMBER(輸入與假設!G$379),輸入與假設!G$379,"") | H39: =IF(ISNUMBER(輸入與假設!H$379),輸入與假設!H$379,"")
A40: 實際｜季末雲端 MW（口徑不明） | B40: MW | C40: =IF(ISNUMBER(輸入與假設!C$380),輸入與假設!C$380,"") | D40: =IF(ISNUMBER(輸入與假設!D$380),輸入與假設!D$380,"") | E40: =IF(ISNUMBER(輸入與假設!E$380),輸入與假設!E$380,"") | F40: =IF(ISNUMBER(輸入與假設!F$380),輸入與假設!F$380,"") | G40: =IF(ISNUMBER(輸入與假設!G$380),輸入與假設!G$380,"") | H40: =IF(ISNUMBER(輸入與假設!H$380),輸入與假設!H$380,"")
A41: 差距｜營收｜模型 vs 共識 | B41: % | C41: =IF(AND(ISNUMBER(C22),ISNUMBER(C32),C32<>0),C22/(C32)-1,"不適用") -> 不適用 | D41: =IF(AND(ISNUMBER(D22),ISNUMBER(D32),D32<>0),D22/(D32)-1,"不適用") -> 不適用 | E41: =IF(AND(ISNUMBER(E22),ISNUMBER(E32),E32<>0),E22/(E32)-1,"不適用") -> 不適用 | F41: =IF(AND(ISNUMBER(F22),ISNUMBER(F32),F32<>0),F22/(F32)-1,"不適用") -> 不適用 | G41: =IF(AND(ISNUMBER(G22),ISNUMBER(G32),G32<>0),G22/(G32)-1,"不適用") -> 不適用 | H41: =IF(AND(ISNUMBER(H22),ISNUMBER(H32),H32<>0),H22/(H32)-1,"不適用") -> 不適用
A42: 差距｜營收｜模型 vs 指引中點 | B42: % | C42: 不適用 | D42: 不適用 | E42: 不適用 | F42: 不適用 | G42: 不適用 | H42: 不適用
A43: 差距｜營收｜實際 vs 模型 | B43: % | C43: =IF(ISNUMBER(C35),IF(AND(ISNUMBER(C22),C22<>0),C35/(C22)-1,"不適用"),"") | D43: =IF(ISNUMBER(D35),IF(AND(ISNUMBER(D22),D22<>0),D35/(D22)-1,"不適用"),"") | E43: =IF(ISNUMBER(E35),IF(AND(ISNUMBER(E22),E22<>0),E35/(E22)-1,"不適用"),"") | F43: =IF(ISNUMBER(F35),IF(AND(ISNUMBER(F22),F22<>0),F35/(F22)-1,"不適用"),"") | G43: =IF(ISNUMBER(G35),IF(AND(ISNUMBER(G22),G22<>0),G35/(G22)-1,"不適用"),"") | H43: =IF(ISNUMBER(H35),IF(AND(ISNUMBER(H22),H22<>0),H35/(H22)-1,"不適用"),"")
A44: 差距｜營收｜實際 vs 共識 | B44: % | C44: =IF(ISNUMBER(C35),IF(AND(ISNUMBER(C32),C32<>0),C35/(C32)-1,"不適用"),"") | D44: =IF(ISNUMBER(D35),IF(AND(ISNUMBER(D32),D32<>0),D35/(D32)-1,"不適用"),"") | E44: =IF(ISNUMBER(E35),IF(AND(ISNUMBER(E32),E32<>0),E35/(E32)-1,"不適用"),"") | F44: =IF(ISNUMBER(F35),IF(AND(ISNUMBER(F32),F32<>0),F35/(F32)-1,"不適用"),"") | G44: =IF(ISNUMBER(G35),IF(AND(ISNUMBER(G32),G32<>0),G35/(G32)-1,"不適用"),"") | H44: =IF(ISNUMBER(H35),IF(AND(ISNUMBER(H32),H32<>0),H35/(H32)-1,"不適用"),"")
A45: 差距｜營收｜實際 vs 指引中點 | B45: % | C45: =IF(ISNUMBER(C35),"不適用","") | D45: =IF(ISNUMBER(D35),"不適用","") | E45: =IF(ISNUMBER(E35),"不適用","") | F45: =IF(ISNUMBER(F35),"不適用","") | G45: =IF(ISNUMBER(G35),"不適用","") | H45: =IF(ISNUMBER(H35),"不適用","")
A46: 差距｜調整後 EBITDA｜模型 vs 共識 | B46: US$m | C46: =IF(AND(ISNUMBER(C28),ISNUMBER(C33)),C28-(C33),"不適用") -> 不適用 | D46: =IF(AND(ISNUMBER(D28),ISNUMBER(D33)),D28-(D33),"不適用") -> 不適用 | E46: =IF(AND(ISNUMBER(E28),ISNUMBER(E33)),E28-(E33),"不適用") -> 不適用 | F46: =IF(AND(ISNUMBER(F28),ISNUMBER(F33)),F28-(F33),"不適用") -> 不適用 | G46: =IF(AND(ISNUMBER(G28),ISNUMBER(G33)),G28-(G33),"不適用") -> 不適用 | H46: =IF(AND(ISNUMBER(H28),ISNUMBER(H33)),H28-(H33),"不適用") -> 不適用
A47: 差距｜調整後 EBITDA｜模型 vs 指引中點 | B47: US$m | C47: 不適用 | D47: 不適用 | E47: 不適用 | F47: 不適用 | G47: 不適用 | H47: 不適用
A48: 差距｜調整後 EBITDA｜實際 vs 模型 | B48: US$m | C48: =IF(ISNUMBER(C36),IF(AND(ISNUMBER(C28)),C36-(C28),"不適用"),"") | D48: =IF(ISNUMBER(D36),IF(AND(ISNUMBER(D28)),D36-(D28),"不適用"),"") | E48: =IF(ISNUMBER(E36),IF(AND(ISNUMBER(E28)),E36-(E28),"不適用"),"") | F48: =IF(ISNUMBER(F36),IF(AND(ISNUMBER(F28)),F36-(F28),"不適用"),"") | G48: =IF(ISNUMBER(G36),IF(AND(ISNUMBER(G28)),G36-(G28),"不適用"),"") | H48: =IF(ISNUMBER(H36),IF(AND(ISNUMBER(H28)),H36-(H28),"不適用"),"")
A49: 差距｜調整後 EBITDA｜實際 vs 共識 | B49: US$m | C49: =IF(ISNUMBER(C36),IF(AND(ISNUMBER(C33)),C36-(C33),"不適用"),"") | D49: =IF(ISNUMBER(D36),IF(AND(ISNUMBER(D33)),D36-(D33),"不適用"),"") | E49: =IF(ISNUMBER(E36),IF(AND(ISNUMBER(E33)),E36-(E33),"不適用"),"") | F49: =IF(ISNUMBER(F36),IF(AND(ISNUMBER(F33)),F36-(F33),"不適用"),"") | G49: =IF(ISNUMBER(G36),IF(AND(ISNUMBER(G33)),G36-(G33),"不適用"),"") | H49: =IF(ISNUMBER(H36),IF(AND(ISNUMBER(H33)),H36-(H33),"不適用"),"")
A50: 差距｜調整後 EBITDA｜實際 vs 指引中點 | B50: US$m | C50: =IF(ISNUMBER(C36),"不適用","") | D50: =IF(ISNUMBER(D36),"不適用","") | E50: =IF(ISNUMBER(E36),"不適用","") | F50: =IF(ISNUMBER(F36),"不適用","") | G50: =IF(ISNUMBER(G36),"不適用","") | H50: =IF(ISNUMBER(H36),"不適用","")
A51: 差距｜調整後 EBITDA｜模型 vs 共識（利潤率 pt） | B51: pt | C51: =IF(AND(ISNUMBER(C28),ISNUMBER(C22),C22<>0,ISNUMBER(C33),ISNUMBER(C32),C32<>0),C28/C22-C33/C32,"不適用") -> 不適用 | D51: =IF(AND(ISNUMBER(D28),ISNUMBER(D22),D22<>0,ISNUMBER(D33),ISNUMBER(D32),D32<>0),D28/D22-D33/D32,"不適用") -> 不適用 | E51: =IF(AND(ISNUMBER(E28),ISNUMBER(E22),E22<>0,ISNUMBER(E33),ISNUMBER(E32),E32<>0),E28/E22-E33/E32,"不適用") -> 不適用 | F51: =IF(AND(ISNUMBER(F28),ISNUMBER(F22),F22<>0,ISNUMBER(F33),ISNUMBER(F32),F32<>0),F28/F22-F33/F32,"不適用") -> 不適用 | G51: =IF(AND(ISNUMBER(G28),ISNUMBER(G22),G22<>0,ISNUMBER(G33),ISNUMBER(G32),G32<>0),G28/G22-G33/G32,"不適用") -> 不適用 | H51: =IF(AND(ISNUMBER(H28),ISNUMBER(H22),H22<>0,ISNUMBER(H33),ISNUMBER(H32),H32<>0),H28/H22-H33/H32,"不適用") -> 不適用
A52: 差距｜調整後 EBITDA｜模型 vs 指引中點（利潤率 pt） | B52: pt | C52: 不適用 | D52: 不適用 | E52: 不適用 | F52: 不適用 | G52: 不適用 | H52: 不適用
A53: 差距｜調整後 EBITDA｜實際 vs 模型（利潤率 pt） | B53: pt | C53: =IF(ISNUMBER(C36),IF(AND(ISNUMBER(C36),ISNUMBER(C35),C35<>0,ISNUMBER(C28),ISNUMBER(C22),C22<>0),C36/C35-C28/C22,"不適用"),"") | D53: =IF(ISNUMBER(D36),IF(AND(ISNUMBER(D36),ISNUMBER(D35),D35<>0,ISNUMBER(D28),ISNUMBER(D22),D22<>0),D36/D35-D28/D22,"不適用"),"") | E53: =IF(ISNUMBER(E36),IF(AND(ISNUMBER(E36),ISNUMBER(E35),E35<>0,ISNUMBER(E28),ISNUMBER(E22),E22<>0),E36/E35-E28/E22,"不適用"),"") | F53: =IF(ISNUMBER(F36),IF(AND(ISNUMBER(F36),ISNUMBER(F35),F35<>0,ISNUMBER(F28),ISNUMBER(F22),F22<>0),F36/F35-F28/F22,"不適用"),"") | G53: =IF(ISNUMBER(G36),IF(AND(ISNUMBER(G36),ISNUMBER(G35),G35<>0,ISNUMBER(G28),ISNUMBER(G22),G22<>0),G36/G35-G28/G22,"不適用"),"") | H53: =IF(ISNUMBER(H36),IF(AND(ISNUMBER(H36),ISNUMBER(H35),H35<>0,ISNUMBER(H28),ISNUMBER(H22),H22<>0),H36/H35-H28/H22,"不適用"),"")
A54: 差距｜調整後 EBITDA｜實際 vs 共識（利潤率 pt） | B54: pt | C54: =IF(ISNUMBER(C36),IF(AND(ISNUMBER(C36),ISNUMBER(C35),C35<>0,ISNUMBER(C33),ISNUMBER(C32),C32<>0),C36/C35-C33/C32,"不適用"),"") | D54: =IF(ISNUMBER(D36),IF(AND(ISNUMBER(D36),ISNUMBER(D35),D35<>0,ISNUMBER(D33),ISNUMBER(D32),D32<>0),D36/D35-D33/D32,"不適用"),"") | E54: =IF(ISNUMBER(E36),IF(AND(ISNUMBER(E36),ISNUMBER(E35),E35<>0,ISNUMBER(E33),ISNUMBER(E32),E32<>0),E36/E35-E33/E32,"不適用"),"") | F54: =IF(ISNUMBER(F36),IF(AND(ISNUMBER(F36),ISNUMBER(F35),F35<>0,ISNUMBER(F33),ISNUMBER(F32),F32<>0),F36/F35-F33/F32,"不適用"),"") | G54: =IF(ISNUMBER(G36),IF(AND(ISNUMBER(G36),ISNUMBER(G35),G35<>0,ISNUMBER(G33),ISNUMBER(G32),G32<>0),G36/G35-G33/G32,"不適用"),"") | H54: =IF(ISNUMBER(H36),IF(AND(ISNUMBER(H36),ISNUMBER(H35),H35<>0,ISNUMBER(H33),ISNUMBER(H32),H32<>0),H36/H35-H33/H32,"不適用"),"")
A55: 差距｜調整後 EBITDA｜實際 vs 指引中點（利潤率 pt） | B55: pt | C55: =IF(ISNUMBER(C36),"不適用","") | D55: =IF(ISNUMBER(D36),"不適用","") | E55: =IF(ISNUMBER(E36),"不適用","") | F55: =IF(ISNUMBER(F36),"不適用","") | G55: =IF(ISNUMBER(G36),"不適用","") | H55: =IF(ISNUMBER(H36),"不適用","")
A56: 差距｜EBITDA 率｜模型 vs 共識 | B56: pt | C56: =IF(AND(ISNUMBER(C27),ISNUMBER(C34)),C27-(C34),"不適用") -> 不適用 | D56: =IF(AND(ISNUMBER(D27),ISNUMBER(D34)),D27-(D34),"不適用") -> 不適用 | E56: =IF(AND(ISNUMBER(E27),ISNUMBER(E34)),E27-(E34),"不適用") -> 不適用 | F56: =IF(AND(ISNUMBER(F27),ISNUMBER(F34)),F27-(F34),"不適用") -> 不適用 | G56: =IF(AND(ISNUMBER(G27),ISNUMBER(G34)),G27-(G34),"不適用") -> 不適用 | H56: =IF(AND(ISNUMBER(H27),ISNUMBER(H34)),H27-(H34),"不適用") -> 不適用
A57: 差距｜EBITDA 率｜模型 vs 指引中點 | B57: pt | C57: 不適用 | D57: 不適用 | E57: 不適用 | F57: 不適用 | G57: 不適用 | H57: 不適用
A58: 差距｜EBITDA 率｜實際 vs 模型 | B58: pt | C58: =IF(ISNUMBER(C37),IF(AND(ISNUMBER(C27)),C37-(C27),"不適用"),"") | D58: =IF(ISNUMBER(D37),IF(AND(ISNUMBER(D27)),D37-(D27),"不適用"),"") | E58: =IF(ISNUMBER(E37),IF(AND(ISNUMBER(E27)),E37-(E27),"不適用"),"") | F58: =IF(ISNUMBER(F37),IF(AND(ISNUMBER(F27)),F37-(F27),"不適用"),"") | G58: =IF(ISNUMBER(G37),IF(AND(ISNUMBER(G27)),G37-(G27),"不適用"),"") | H58: =IF(ISNUMBER(H37),IF(AND(ISNUMBER(H27)),H37-(H27),"不適用"),"")
A59: 差距｜EBITDA 率｜實際 vs 共識 | B59: pt | C59: =IF(ISNUMBER(C37),IF(AND(ISNUMBER(C34)),C37-(C34),"不適用"),"") | D59: =IF(ISNUMBER(D37),IF(AND(ISNUMBER(D34)),D37-(D34),"不適用"),"") | E59: =IF(ISNUMBER(E37),IF(AND(ISNUMBER(E34)),E37-(E34),"不適用"),"") | F59: =IF(ISNUMBER(F37),IF(AND(ISNUMBER(F34)),F37-(F34),"不適用"),"") | G59: =IF(ISNUMBER(G37),IF(AND(ISNUMBER(G34)),G37-(G34),"不適用"),"") | H59: =IF(ISNUMBER(H37),IF(AND(ISNUMBER(H34)),H37-(H34),"不適用"),"")
A60: 差距｜EBITDA 率｜實際 vs 指引中點 | B60: pt | C60: =IF(ISNUMBER(C37),"不適用","") | D60: =IF(ISNUMBER(D37),"不適用","") | E60: =IF(ISNUMBER(E37),"不適用","") | F60: =IF(ISNUMBER(F37),"不適用","") | G60: =IF(ISNUMBER(G37),"不適用","") | H60: =IF(ISNUMBER(H37),"不適用","")
A61: 差距｜調整後營業利益｜模型 vs 共識 | B61: US$m | C61: 不適用 | D61: 不適用 | E61: 不適用 | F61: 不適用 | G61: 不適用 | H61: 不適用
A62: 差距｜調整後營業利益｜模型 vs 指引中點 | B62: US$m | C62: 不適用 | D62: 不適用 | E62: 不適用 | F62: 不適用 | G62: 不適用 | H62: 不適用
A63: 差距｜調整後營業利益｜實際 vs 模型 | B63: US$m | C63: =IF(ISNUMBER(C38),IF(AND(ISNUMBER(C30)),C38-(C30),"不適用"),"") | D63: =IF(ISNUMBER(D38),IF(AND(ISNUMBER(D30)),D38-(D30),"不適用"),"") | E63: =IF(ISNUMBER(E38),IF(AND(ISNUMBER(E30)),E38-(E30),"不適用"),"") | F63: =IF(ISNUMBER(F38),IF(AND(ISNUMBER(F30)),F38-(F30),"不適用"),"") | G63: =IF(ISNUMBER(G38),IF(AND(ISNUMBER(G30)),G38-(G30),"不適用"),"") | H63: =IF(ISNUMBER(H38),IF(AND(ISNUMBER(H30)),H38-(H30),"不適用"),"")
A64: 差距｜調整後營業利益｜實際 vs 共識 | B64: US$m | C64: =IF(ISNUMBER(C38),"不適用","") | D64: =IF(ISNUMBER(D38),"不適用","") | E64: =IF(ISNUMBER(E38),"不適用","") | F64: =IF(ISNUMBER(F38),"不適用","") | G64: =IF(ISNUMBER(G38),"不適用","") | H64: =IF(ISNUMBER(H38),"不適用","")
A65: 差距｜調整後營業利益｜實際 vs 指引中點 | B65: US$m | C65: =IF(ISNUMBER(C38),"不適用","") | D65: =IF(ISNUMBER(D38),"不適用","") | E65: =IF(ISNUMBER(E38),"不適用","") | F65: =IF(ISNUMBER(F38),"不適用","") | G65: =IF(ISNUMBER(G38),"不適用","") | H65: =IF(ISNUMBER(H38),"不適用","")
A66: 差距｜調整後營業利益｜模型 vs 共識（利潤率 pt） | B66: pt | C66: 不適用 | D66: 不適用 | E66: 不適用 | F66: 不適用 | G66: 不適用 | H66: 不適用
A67: 差距｜調整後營業利益｜模型 vs 指引中點（利潤率 pt） | B67: pt | C67: 不適用 | D67: 不適用 | E67: 不適用 | F67: 不適用 | G67: 不適用 | H67: 不適用
A68: 差距｜調整後營業利益｜實際 vs 模型（利潤率 pt） | B68: pt | C68: =IF(ISNUMBER(C38),IF(AND(ISNUMBER(C38),ISNUMBER(C35),C35<>0,ISNUMBER(C30),ISNUMBER(C22),C22<>0),C38/C35-C30/C22,"不適用"),"") | D68: =IF(ISNUMBER(D38),IF(AND(ISNUMBER(D38),ISNUMBER(D35),D35<>0,ISNUMBER(D30),ISNUMBER(D22),D22<>0),D38/D35-D30/D22,"不適用"),"") | E68: =IF(ISNUMBER(E38),IF(AND(ISNUMBER(E38),ISNUMBER(E35),E35<>0,ISNUMBER(E30),ISNUMBER(E22),E22<>0),E38/E35-E30/E22,"不適用"),"") | F68: =IF(ISNUMBER(F38),IF(AND(ISNUMBER(F38),ISNUMBER(F35),F35<>0,ISNUMBER(F30),ISNUMBER(F22),F22<>0),F38/F35-F30/F22,"不適用"),"") | G68: =IF(ISNUMBER(G38),IF(AND(ISNUMBER(G38),ISNUMBER(G35),G35<>0,ISNUMBER(G30),ISNUMBER(G22),G22<>0),G38/G35-G30/G22,"不適用"),"") | H68: =IF(ISNUMBER(H38),IF(AND(ISNUMBER(H38),ISNUMBER(H35),H35<>0,ISNUMBER(H30),ISNUMBER(H22),H22<>0),H38/H35-H30/H22,"不適用"),"")
A69: 差距｜調整後營業利益｜實際 vs 共識（利潤率 pt） | B69: pt | C69: =IF(ISNUMBER(C38),"不適用","") | D69: =IF(ISNUMBER(D38),"不適用","") | E69: =IF(ISNUMBER(E38),"不適用","") | F69: =IF(ISNUMBER(F38),"不適用","") | G69: =IF(ISNUMBER(G38),"不適用","") | H69: =IF(ISNUMBER(H38),"不適用","")
A70: 差距｜調整後營業利益｜實際 vs 指引中點（利潤率 pt） | B70: pt | C70: =IF(ISNUMBER(C38),"不適用","") | D70: =IF(ISNUMBER(D38),"不適用","") | E70: =IF(ISNUMBER(E38),"不適用","") | F70: =IF(ISNUMBER(F38),"不適用","") | G70: =IF(ISNUMBER(G38),"不適用","") | H70: =IF(ISNUMBER(H38),"不適用","")
A71: 差距｜CapEx（毛額）｜模型 vs 共識 | B71: % | C71: 不適用 | D71: 不適用 | E71: 不適用 | F71: 不適用 | G71: 不適用 | H71: 不適用
A72: 差距｜CapEx（毛額）｜模型 vs 指引中點 | B72: % | C72: 不適用 | D72: 不適用 | E72: 不適用 | F72: 不適用 | G72: 不適用 | H72: 不適用
A73: 差距｜CapEx（毛額）｜實際 vs 模型 | B73: % | C73: =IF(ISNUMBER(C39),IF(AND(ISNUMBER(C31),C31<>0),C39/(C31)-1,"不適用"),"") | D73: =IF(ISNUMBER(D39),IF(AND(ISNUMBER(D31),D31<>0),D39/(D31)-1,"不適用"),"") | E73: =IF(ISNUMBER(E39),IF(AND(ISNUMBER(E31),E31<>0),E39/(E31)-1,"不適用"),"") | F73: =IF(ISNUMBER(F39),IF(AND(ISNUMBER(F31),F31<>0),F39/(F31)-1,"不適用"),"") | G73: =IF(ISNUMBER(G39),IF(AND(ISNUMBER(G31),G31<>0),G39/(G31)-1,"不適用"),"") | H73: =IF(ISNUMBER(H39),IF(AND(ISNUMBER(H31),H31<>0),H39/(H31)-1,"不適用"),"")
A74: 差距｜CapEx（毛額）｜實際 vs 共識 | B74: % | C74: =IF(ISNUMBER(C39),"不適用","") | D74: =IF(ISNUMBER(D39),"不適用","") | E74: =IF(ISNUMBER(E39),"不適用","") | F74: =IF(ISNUMBER(F39),"不適用","") | G74: =IF(ISNUMBER(G39),"不適用","") | H74: =IF(ISNUMBER(H39),"不適用","")
A75: 差距｜CapEx（毛額）｜實際 vs 指引中點 | B75: % | C75: =IF(ISNUMBER(C39),"不適用","") | D75: =IF(ISNUMBER(D39),"不適用","") | E75: =IF(ISNUMBER(E39),"不適用","") | F75: =IF(ISNUMBER(F39),"不適用","") | G75: =IF(ISNUMBER(G39),"不適用","") | H75: =IF(ISNUMBER(H39),"不適用","")
A76: 差距｜季末雲端已連網 MW-IT｜模型 vs 共識 | B76: MW | C76: 不適用 | D76: 不適用 | E76: 不適用 | F76: 不適用 | G76: 不適用 | H76: 不適用
A77: 差距｜季末雲端已連網 MW-IT｜模型 vs 指引中點 | B77: MW | C77: 不適用 | D77: 不適用 | E77: 不適用 | F77: 不適用 | G77: 不適用 | H77: 不適用
A78: 差距｜季末雲端已連網 MW-IT｜實際 vs 模型 | B78: MW | C78: =IF(ISNUMBER(C40),IF(AND(ISNUMBER(C19)),C40-(C19),"不適用"),"") | D78: =IF(ISNUMBER(D40),IF(AND(ISNUMBER(D19)),D40-(D19),"不適用"),"") | E78: =IF(ISNUMBER(E40),IF(AND(ISNUMBER(E19)),E40-(E19),"不適用"),"") | F78: =IF(ISNUMBER(F40),IF(AND(ISNUMBER(F19)),F40-(F19),"不適用"),"") | G78: =IF(ISNUMBER(G40),IF(AND(ISNUMBER(G19)),G40-(G19),"不適用"),"") | H78: =IF(ISNUMBER(H40),IF(AND(ISNUMBER(H19)),H40-(H19),"不適用"),"")
A79: 差距｜季末雲端已連網 MW-IT｜實際 vs 共識 | B79: MW | C79: =IF(ISNUMBER(C40),"不適用","") | D79: =IF(ISNUMBER(D40),"不適用","") | E79: =IF(ISNUMBER(E40),"不適用","") | F79: =IF(ISNUMBER(F40),"不適用","") | G79: =IF(ISNUMBER(G40),"不適用","") | H79: =IF(ISNUMBER(H40),"不適用","")
A80: 差距｜季末雲端已連網 MW-IT｜實際 vs 指引中點 | B80: MW | C80: =IF(ISNUMBER(C40),"不適用","") | D80: =IF(ISNUMBER(D40),"不適用","") | E80: =IF(ISNUMBER(E40),"不適用","") | F80: =IF(ISNUMBER(F40),"不適用","") | G80: =IF(ISNUMBER(G40),"不適用","") | H80: =IF(ISNUMBER(H40),"不適用","")
A81: 合計基準｜營收｜vs 共識 | B81: US$m | C81: =IF(COUNT(C32,D32)=2,C32+D32,"不適用") -> 不適用 | D81: =IF(COUNT(C32,D32)=2,C32+D32,"不適用") -> 不適用 | E81: =IF(COUNT(E32,F32,G32,H32)=4,E32+F32+G32+H32,"不適用") -> 不適用 | F81: =IF(COUNT(E32,F32,G32,H32)=4,E32+F32+G32+H32,"不適用") -> 不適用 | G81: =IF(COUNT(E32,F32,G32,H32)=4,E32+F32+G32+H32,"不適用") -> 不適用 | H81: =IF(COUNT(E32,F32,G32,H32)=4,E32+F32+G32+H32,"不適用") -> 不適用 | J81: 所屬期間的季度共識合計
A82: 拆解｜營收｜vs 共識｜水準 | B82: US$m | C82: =IF(AND(ISNUMBER(C81),C81<>0,ISNUMBER(C32),ISNUMBER(C22)),(損益!C9-C81)*(C32)/C81,"不適用") -> 不適用 | D82: =IF(AND(ISNUMBER(D81),D81<>0,ISNUMBER(D32),ISNUMBER(D22)),(損益!C9-D81)*(D32)/D81,"不適用") -> 不適用 | E82: =IF(AND(ISNUMBER(E81),E81<>0,ISNUMBER(E32),ISNUMBER(E22)),(損益!D9-E81)*(E32)/E81,"不適用") -> 不適用 | F82: =IF(AND(ISNUMBER(F81),F81<>0,ISNUMBER(F32),ISNUMBER(F22)),(損益!D9-F81)*(F32)/F81,"不適用") -> 不適用 | G82: =IF(AND(ISNUMBER(G81),G81<>0,ISNUMBER(G32),ISNUMBER(G22)),(損益!D9-G81)*(G32)/G81,"不適用") -> 不適用 | H82: =IF(AND(ISNUMBER(H81),H81<>0,ISNUMBER(H32),ISNUMBER(H22)),(損益!D9-H81)*(H32)/H81,"不適用") -> 不適用 | J82: (模型期間 − 比較期間) × 比較的季占比
A83: 拆解｜營收｜vs 共識｜分配 | B83: US$m | C83: =IF(AND(ISNUMBER(C81),C81<>0,ISNUMBER(C32),ISNUMBER(C22)),(C22/損益!C9-(C32)/C81)*損益!C9,"不適用") -> 不適用 | D83: =IF(AND(ISNUMBER(D81),D81<>0,ISNUMBER(D32),ISNUMBER(D22)),(D22/損益!C9-(D32)/D81)*損益!C9,"不適用") -> 不適用 | E83: =IF(AND(ISNUMBER(E81),E81<>0,ISNUMBER(E32),ISNUMBER(E22)),(E22/損益!D9-(E32)/E81)*損益!D9,"不適用") -> 不適用 | F83: =IF(AND(ISNUMBER(F81),F81<>0,ISNUMBER(F32),ISNUMBER(F22)),(F22/損益!D9-(F32)/F81)*損益!D9,"不適用") -> 不適用 | G83: =IF(AND(ISNUMBER(G81),G81<>0,ISNUMBER(G32),ISNUMBER(G22)),(G22/損益!D9-(G32)/G81)*損益!D9,"不適用") -> 不適用 | H83: =IF(AND(ISNUMBER(H81),H81<>0,ISNUMBER(H32),ISNUMBER(H22)),(H22/損益!D9-(H32)/H81)*損益!D9,"不適用") -> 不適用 | J83: (模型季占比 − 比較季占比) × 模型期間；水準＋分配＝季度差距
A84: 原因｜營收｜vs 共識 | C84: =IF(ISNUMBER(C41),IF(ABS(C41)>輸入與假設!$C$367,IF(ISNUMBER(C82),IF(ABS(C83)>ABS(C82),"營收 vs 共識 "&IF(C41<0,"−","+")&TEXT(ABS(C41)*100,"#,##0.0")&"%"&"：拆法（分配 "&IF(C83<0,"−","+")&IF(ABS(C83)<0,"−","")&"$"&TEXT(ABS(ABS(C83)),"#,##0.0")&"m"&"（Q3 2026 占 2H26 "&TEXT((C22/損益!C9)*100,"#,##0.0")&"%"&"，共識合計 "&TEXT(((C32)/C81)*100,"#,##0.0")&"%"&"）；水準 "&IF(C82<0,"−","+")&IF(ABS(C82)<0,"−","")&"$"&TEXT(ABS(ABS(C82)),"#,##0.0")&"m"&"）","營收 vs 共識 "&IF(C41<0,"−","+")&TEXT(ABS(C41)*100,"#,##0.0")&"%"&"：觀點（水準 "&IF(C82<0,"−","+")&IF(ABS(C82)<0,"−","")&"$"&TEXT(ABS(ABS(C82)),"#,##0.0")&"m"&"（2H26 模型 "&IF(損益!C9<0,"−","")&"$"&TEXT(ABS(損益!C9),"#,##0.0")&"m"&"，共識合計 "&IF(C81<0,"−","")&"$"&TEXT(ABS(C81),"#,##0.0")&"m"&"）；分配 "&IF(C83<0,"−","+")&IF(ABS(C83)<0,"−","")&"$"&TEXT(ABS(ABS(C83)),"#,##0.0")&"m"&"；"&"雲端營收＝在役 MW × 每 MW 年收入（Tokenomics 正向推導），期初可計費 MW 以 Q2 經常性雲端營收年化校準；託管營收照已簽約合約排程；共識未揭露 MW 與單價假設"&"）"),"營收 vs 共識 "&IF(C41<0,"−","+")&TEXT(ABS(C41)*100,"#,##0.0")&"%"&"：觀點（"&"雲端營收＝在役 MW × 每 MW 年收入（Tokenomics 正向推導），期初可計費 MW 以 Q2 經常性雲端營收年化校準；託管營收照已簽約合約排程；共識未揭露 MW 與單價假設"&"）"),""),"") | D84: =IF(ISNUMBER(D41),IF(ABS(D41)>輸入與假設!$C$367,IF(ISNUMBER(D82),IF(ABS(D83)>ABS(D82),"營收 vs 共識 "&IF(D41<0,"−","+")&TEXT(ABS(D41)*100,"#,##0.0")&"%"&"：拆法（分配 "&IF(D83<0,"−","+")&IF(ABS(D83)<0,"−","")&"$"&TEXT(ABS(ABS(D83)),"#,##0.0")&"m"&"（Q4 2026 占 2H26 "&TEXT((D22/損益!C9)*100,"#,##0.0")&"%"&"，共識合計 "&TEXT(((D32)/D81)*100,"#,##0.0")&"%"&"）；水準 "&IF(D82<0,"−","+")&IF(ABS(D82)<0,"−","")&"$"&TEXT(ABS(ABS(D82)),"#,##0.0")&"m"&"）","營收 vs 共識 "&IF(D41<0,"−","+")&TEXT(ABS(D41)*100,"#,##0.0")&"%"&"：觀點（水準 "&IF(D82<0,"−","+")&IF(ABS(D82)<0,"−","")&"$"&TEXT(ABS(ABS(D82)),"#,##0.0")&"m"&"（2H26 模型 "&IF(損益!C9<0,"−","")&"$"&TEXT(ABS(損益!C9),"#,##0.0")&"m"&"，共識合計 "&IF(D81<0,"−","")&"$"&TEXT(ABS(D81),"#,##0.0")&"m"&"）；分配 "&IF(D83<0,"−","+")&IF(ABS(D83)<0,"−","")&"$"&TEXT(ABS(ABS(D83)),"#,##0.0")&"m"&"；"&"雲端營收＝在役 MW × 每 MW 年收入（Tokenomics 正向推導），期初可計費 MW 以 Q2 經常性雲端營收年化校準；託管營收照已簽約合約排程；共識未揭露 MW 與單價假設"&"）"),"營收 vs 共識 "&IF(D41<0,"−","+")&TEXT(ABS(D41)*100,"#,##0.0")&"%"&"：觀點（"&"雲端營收＝在役 MW × 每 MW 年收入（Tokenomics 正向推導），期初可計費 MW 以 Q2 經常性雲端營收年化校準；託管營收照已簽約合約排程；共識未揭露 MW 與單價假設"&"）"),""),"") | E84: =IF(ISNUMBER(E41),IF(ABS(E41)>輸入與假設!$C$367,IF(ISNUMBER(E82),IF(ABS(E83)>ABS(E82),"營收 vs 共識 "&IF(E41<0,"−","+")&TEXT(ABS(E41)*100,"#,##0.0")&"%"&"：拆法（分配 "&IF(E83<0,"−","+")&IF(ABS(E83)<0,"−","")&"$"&TEXT(ABS(ABS(E83)),"#,##0.0")&"m"&"（Q1 2027 占 FY27 "&TEXT((E22/損益!D9)*100,"#,##0.0")&"%"&"，共識合計 "&TEXT(((E32)/E81)*100,"#,##0.0")&"%"&"）；水準 "&IF(E82<0,"−","+")&IF(ABS(E82)<0,"−","")&"$"&TEXT(ABS(ABS(E82)),"#,##0.0")&"m"&"）","營收 vs 共識 "&IF(E41<0,"−","+")&TEXT(ABS(E41)*100,"#,##0.0")&"%"&"：觀點（水準 "&IF(E82<0,"−","+")&IF(ABS(E82)<0,"−","")&"$"&TEXT(ABS(ABS(E82)),"#,##0.0")&"m"&"（FY27 模型 "&IF(損益!D9<0,"−","")&"$"&TEXT(ABS(損益!D9),"#,##0.0")&"m"&"，共識合計 "&IF(E81<0,"−","")&"$"&TEXT(ABS(E81),"#,##0.0")&"m"&"）；分配 "&IF(E83<0,"−","+")&IF(ABS(E83)<0,"−","")&"$"&TEXT(ABS(ABS(E83)),"#,##0.0")&"m"&"；"&"雲端營收＝在役 MW × 每 MW 年收入（Tokenomics 正向推導），期初可計費 MW 以 Q2 經常性雲端營收年化校準；託管營收照已簽約合約排程；共識未揭露 MW 與單價假設"&"）"),"營收 vs 共識 "&IF(E41<0,"−","+")&TEXT(ABS(E41)*100,"#,##0.0")&"%"&"：觀點（"&"雲端營收＝在役 MW × 每 MW 年收入（Tokenomics 正向推導），期初可計費 MW 以 Q2 經常性雲端營收年化校準；託管營收照已簽約合約排程；共識未揭露 MW 與單價假設"&"）"),""),"") | F84: =IF(ISNUMBER(F41),IF(ABS(F41)>輸入與假設!$C$367,IF(ISNUMBER(F82),IF(ABS(F83)>ABS(F82),"營收 vs 共識 "&IF(F41<0,"−","+")&TEXT(ABS(F41)*100,"#,##0.0")&"%"&"：拆法（分配 "&IF(F83<0,"−","+")&IF(ABS(F83)<0,"−","")&"$"&TEXT(ABS(ABS(F83)),"#,##0.0")&"m"&"（Q2 2027 占 FY27 "&TEXT((F22/損益!D9)*100,"#,##0.0")&"%"&"，共識合計 "&TEXT(((F32)/F81)*100,"#,##0.0")&"%"&"）；水準 "&IF(F82<0,"−","+")&IF(ABS(F82)<0,"−","")&"$"&TEXT(ABS(ABS(F82)),"#,##0.0")&"m"&"）","營收 vs 共識 "&IF(F41<0,"−","+")&TEXT(ABS(F41)*100,"#,##0.0")&"%"&"：觀點（水準 "&IF(F82<0,"−","+")&IF(ABS(F82)<0,"−","")&"$"&TEXT(ABS(ABS(F82)),"#,##0.0")&"m"&"（FY27 模型 "&IF(損益!D9<0,"−","")&"$"&TEXT(ABS(損益!D9),"#,##0.0")&"m"&"，共識合計 "&IF(F81<0,"−","")&"$"&TEXT(ABS(F81),"#,##0.0")&"m"&"）；分配 "&IF(F83<0,"−","+")&IF(ABS(F83)<0,"−","")&"$"&TEXT(ABS(ABS(F83)),"#,##0.0")&"m"&"；"&"雲端營收＝在役 MW × 每 MW 年收入（Tokenomics 正向推導），期初可計費 MW 以 Q2 經常性雲端營收年化校準；託管營收照已簽約合約排程；共識未揭露 MW 與單價假設"&"）"),"營收 vs 共識 "&IF(F41<0,"−","+")&TEXT(ABS(F41)*100,"#,##0.0")&"%"&"：觀點（"&"雲端營收＝在役 MW × 每 MW 年收入（Tokenomics 正向推導），期初可計費 MW 以 Q2 經常性雲端營收年化校準；託管營收照已簽約合約排程；共識未揭露 MW 與單價假設"&"）"),""),"") | G84: =IF(ISNUMBER(G41),IF(ABS(G41)>輸入與假設!$C$367,IF(ISNUMBER(G82),IF(ABS(G83)>ABS(G82),"營收 vs 共識 "&IF(G41<0,"−","+")&TEXT(ABS(G41)*100,"#,##0.0")&"%"&"：拆法（分配 "&IF(G83<0,"−","+")&IF(ABS(G83)<0,"−","")&"$"&TEXT(ABS(ABS(G83)),"#,##0.0")&"m"&"（Q3 2027 占 FY27 "&TEXT((G22/損益!D9)*100,"#,##0.0")&"%"&"，共識合計 "&TEXT(((G32)/G81)*100,"#,##0.0")&"%"&"）；水準 "&IF(G82<0,"−","+")&IF(ABS(G82)<0,"−","")&"$"&TEXT(ABS(ABS(G82)),"#,##0.0")&"m"&"）","營收 vs 共識 "&IF(G41<0,"−","+")&TEXT(ABS(G41)*100,"#,##0.0")&"%"&"：觀點（水準 "&IF(G82<0,"−","+")&IF(ABS(G82)<0,"−","")&"$"&TEXT(ABS(ABS(G82)),"#,##0.0")&"m"&"（FY27 模型 "&IF(損益!D9<0,"−","")&"$"&TEXT(ABS(損益!D9),"#,##0.0")&"m"&"，共識合計 "&IF(G81<0,"−","")&"$"&TEXT(ABS(G81),"#,##0.0")&"m"&"）；分配 "&IF(G83<0,"−","+")&IF(ABS(G83)<0,"−","")&"$"&TEXT(ABS(ABS(G83)),"#,##0.0")&"m"&"；"&"雲端營收＝在役 MW × 每 MW 年收入（Tokenomics 正向推導），期初可計費 MW 以 Q2 經常性雲端營收年化校準；託管營收照已簽約合約排程；共識未揭露 MW 與單價假設"&"）"),"營收 vs 共識 "&IF(G41<0,"−","+")&TEXT(ABS(G41)*100,"#,##0.0")&"%"&"：觀點（"&"雲端營收＝在役 MW × 每 MW 年收入（Tokenomics 正向推導），期初可計費 MW 以 Q2 經常性雲端營收年化校準；託管營收照已簽約合約排程；共識未揭露 MW 與單價假設"&"）"),""),"") | H84: =IF(ISNUMBER(H41),IF(ABS(H41)>輸入與假設!$C$367,IF(ISNUMBER(H82),IF(ABS(H83)>ABS(H82),"營收 vs 共識 "&IF(H41<0,"−","+")&TEXT(ABS(H41)*100,"#,##0.0")&"%"&"：拆法（分配 "&IF(H83<0,"−","+")&IF(ABS(H83)<0,"−","")&"$"&TEXT(ABS(ABS(H83)),"#,##0.0")&"m"&"（Q4 2027 占 FY27 "&TEXT((H22/損益!D9)*100,"#,##0.0")&"%"&"，共識合計 "&TEXT(((H32)/H81)*100,"#,##0.0")&"%"&"）；水準 "&IF(H82<0,"−","+")&IF(ABS(H82)<0,"−","")&"$"&TEXT(ABS(ABS(H82)),"#,##0.0")&"m"&"）","營收 vs 共識 "&IF(H41<0,"−","+")&TEXT(ABS(H41)*100,"#,##0.0")&"%"&"：觀點（水準 "&IF(H82<0,"−","+")&IF(ABS(H82)<0,"−","")&"$"&TEXT(ABS(ABS(H82)),"#,##0.0")&"m"&"（FY27 模型 "&IF(損益!D9<0,"−","")&"$"&TEXT(ABS(損益!D9),"#,##0.0")&"m"&"，共識合計 "&IF(H81<0,"−","")&"$"&TEXT(ABS(H81),"#,##0.0")&"m"&"）；分配 "&IF(H83<0,"−","+")&IF(ABS(H83)<0,"−","")&"$"&TEXT(ABS(ABS(H83)),"#,##0.0")&"m"&"；"&"雲端營收＝在役 MW × 每 MW 年收入（Tokenomics 正向推導），期初可計費 MW 以 Q2 經常性雲端營收年化校準；託管營收照已簽約合約排程；共識未揭露 MW 與單價假設"&"）"),"營收 vs 共識 "&IF(H41<0,"−","+")&TEXT(ABS(H41)*100,"#,##0.0")&"%"&"：觀點（"&"雲端營收＝在役 MW × 每 MW 年收入（Tokenomics 正向推導），期初可計費 MW 以 Q2 經常性雲端營收年化校準；託管營收照已簽約合約排程；共識未揭露 MW 與單價假設"&"）"),""),"")
A85: 原因類型｜營收｜vs 共識 | C85: =IF(ISNUMBER(C41),IF(ABS(C41)>輸入與假設!$C$367,IF(ISNUMBER(C82),IF(ABS(C83)>ABS(C82),"拆法","觀點"),"觀點"),""),"") | D85: =IF(ISNUMBER(D41),IF(ABS(D41)>輸入與假設!$C$367,IF(ISNUMBER(D82),IF(ABS(D83)>ABS(D82),"拆法","觀點"),"觀點"),""),"") | E85: =IF(ISNUMBER(E41),IF(ABS(E41)>輸入與假設!$C$367,IF(ISNUMBER(E82),IF(ABS(E83)>ABS(E82),"拆法","觀點"),"觀點"),""),"") | F85: =IF(ISNUMBER(F41),IF(ABS(F41)>輸入與假設!$C$367,IF(ISNUMBER(F82),IF(ABS(F83)>ABS(F82),"拆法","觀點"),"觀點"),""),"") | G85: =IF(ISNUMBER(G41),IF(ABS(G41)>輸入與假設!$C$367,IF(ISNUMBER(G82),IF(ABS(G83)>ABS(G82),"拆法","觀點"),"觀點"),""),"") | H85: =IF(ISNUMBER(H41),IF(ABS(H41)>輸入與假設!$C$367,IF(ISNUMBER(H82),IF(ABS(H83)>ABS(H82),"拆法","觀點"),"觀點"),""),"")
A86: 原因｜營收｜vs 指引中點
A87: 原因類型｜營收｜vs 指引中點
A88: 原因｜營收｜實際 vs 模型 | C88: =IF(ISNUMBER(C43),IF(ABS(C43)>輸入與假設!$C$367,"營收 實際 vs 模型 "&IF(C43<0,"−","+")&TEXT(ABS(C43)*100,"#,##0.0")&"%"&"：觀點（"&"雲端營收＝在役 MW × 每 MW 年收入（Tokenomics 正向推導），期初可計費 MW 以 Q2 經常性雲端營收年化校準；託管營收照已簽約合約排程；共識未揭露 MW 與單價假設"&"）",""),"") | D88: =IF(ISNUMBER(D43),IF(ABS(D43)>輸入與假設!$C$367,"營收 實際 vs 模型 "&IF(D43<0,"−","+")&TEXT(ABS(D43)*100,"#,##0.0")&"%"&"：觀點（"&"雲端營收＝在役 MW × 每 MW 年收入（Tokenomics 正向推導），期初可計費 MW 以 Q2 經常性雲端營收年化校準；託管營收照已簽約合約排程；共識未揭露 MW 與單價假設"&"）",""),"") | E88: =IF(ISNUMBER(E43),IF(ABS(E43)>輸入與假設!$C$367,"營收 實際 vs 模型 "&IF(E43<0,"−","+")&TEXT(ABS(E43)*100,"#,##0.0")&"%"&"：觀點（"&"雲端營收＝在役 MW × 每 MW 年收入（Tokenomics 正向推導），期初可計費 MW 以 Q2 經常性雲端營收年化校準；託管營收照已簽約合約排程；共識未揭露 MW 與單價假設"&"）",""),"") | F88: =IF(ISNUMBER(F43),IF(ABS(F43)>輸入與假設!$C$367,"營收 實際 vs 模型 "&IF(F43<0,"−","+")&TEXT(ABS(F43)*100,"#,##0.0")&"%"&"：觀點（"&"雲端營收＝在役 MW × 每 MW 年收入（Tokenomics 正向推導），期初可計費 MW 以 Q2 經常性雲端營收年化校準；託管營收照已簽約合約排程；共識未揭露 MW 與單價假設"&"）",""),"") | G88: =IF(ISNUMBER(G43),IF(ABS(G43)>輸入與假設!$C$367,"營收 實際 vs 模型 "&IF(G43<0,"−","+")&TEXT(ABS(G43)*100,"#,##0.0")&"%"&"：觀點（"&"雲端營收＝在役 MW × 每 MW 年收入（Tokenomics 正向推導），期初可計費 MW 以 Q2 經常性雲端營收年化校準；託管營收照已簽約合約排程；共識未揭露 MW 與單價假設"&"）",""),"") | H88: =IF(ISNUMBER(H43),IF(ABS(H43)>輸入與假設!$C$367,"營收 實際 vs 模型 "&IF(H43<0,"−","+")&TEXT(ABS(H43)*100,"#,##0.0")&"%"&"：觀點（"&"雲端營收＝在役 MW × 每 MW 年收入（Tokenomics 正向推導），期初可計費 MW 以 Q2 經常性雲端營收年化校準；託管營收照已簽約合約排程；共識未揭露 MW 與單價假設"&"）",""),"")
A89: 原因類型｜營收｜實際 vs 模型 | C89: =IF(ISNUMBER(C43),IF(ABS(C43)>輸入與假設!$C$367,"觀點",""),"") | D89: =IF(ISNUMBER(D43),IF(ABS(D43)>輸入與假設!$C$367,"觀點",""),"") | E89: =IF(ISNUMBER(E43),IF(ABS(E43)>輸入與假設!$C$367,"觀點",""),"") | F89: =IF(ISNUMBER(F43),IF(ABS(F43)>輸入與假設!$C$367,"觀點",""),"") | G89: =IF(ISNUMBER(G43),IF(ABS(G43)>輸入與假設!$C$367,"觀點",""),"") | H89: =IF(ISNUMBER(H43),IF(ABS(H43)>輸入與假設!$C$367,"觀點",""),"")
A90: 合計基準｜調整後 EBITDA｜vs 共識 | B90: US$m | C90: =IF(COUNT(C33,D33)=2,C33+D33,"不適用") -> 不適用 | D90: =IF(COUNT(C33,D33)=2,C33+D33,"不適用") -> 不適用 | E90: =IF(COUNT(E33,F33,G33,H33)=4,E33+F33+G33+H33,"不適用") -> 不適用 | F90: =IF(COUNT(E33,F33,G33,H33)=4,E33+F33+G33+H33,"不適用") -> 不適用 | G90: =IF(COUNT(E33,F33,G33,H33)=4,E33+F33+G33+H33,"不適用") -> 不適用 | H90: =IF(COUNT(E33,F33,G33,H33)=4,E33+F33+G33+H33,"不適用") -> 不適用 | J90: 所屬期間的季度共識合計
A91: 拆解｜調整後 EBITDA｜vs 共識｜水準 | B91: US$m | C91: =IF(AND(ISNUMBER(C90),C90<>0,ISNUMBER(C33),ISNUMBER(C28)),(損益!C22-C90)*(C33)/C90,"不適用") -> 不適用 | D91: =IF(AND(ISNUMBER(D90),D90<>0,ISNUMBER(D33),ISNUMBER(D28)),(損益!C22-D90)*(D33)/D90,"不適用") -> 不適用 | E91: =IF(AND(ISNUMBER(E90),E90<>0,ISNUMBER(E33),ISNUMBER(E28)),(損益!D22-E90)*(E33)/E90,"不適用") -> 不適用 | F91: =IF(AND(ISNUMBER(F90),F90<>0,ISNUMBER(F33),ISNUMBER(F28)),(損益!D22-F90)*(F33)/F90,"不適用") -> 不適用 | G91: =IF(AND(ISNUMBER(G90),G90<>0,ISNUMBER(G33),ISNUMBER(G28)),(損益!D22-G90)*(G33)/G90,"不適用") -> 不適用 | H91: =IF(AND(ISNUMBER(H90),H90<>0,ISNUMBER(H33),ISNUMBER(H28)),(損益!D22-H90)*(H33)/H90,"不適用") -> 不適用 | J91: (模型期間 − 比較期間) × 比較的季占比
A92: 拆解｜調整後 EBITDA｜vs 共識｜分配 | B92: US$m | C92: =IF(AND(ISNUMBER(C90),C90<>0,ISNUMBER(C33),ISNUMBER(C28)),(C28/損益!C22-(C33)/C90)*損益!C22,"不適用") -> 不適用 | D92: =IF(AND(ISNUMBER(D90),D90<>0,ISNUMBER(D33),ISNUMBER(D28)),(D28/損益!C22-(D33)/D90)*損益!C22,"不適用") -> 不適用 | E92: =IF(AND(ISNUMBER(E90),E90<>0,ISNUMBER(E33),ISNUMBER(E28)),(E28/損益!D22-(E33)/E90)*損益!D22,"不適用") -> 不適用 | F92: =IF(AND(ISNUMBER(F90),F90<>0,ISNUMBER(F33),ISNUMBER(F28)),(F28/損益!D22-(F33)/F90)*損益!D22,"不適用") -> 不適用 | G92: =IF(AND(ISNUMBER(G90),G90<>0,ISNUMBER(G33),ISNUMBER(G28)),(G28/損益!D22-(G33)/G90)*損益!D22,"不適用") -> 不適用 | H92: =IF(AND(ISNUMBER(H90),H90<>0,ISNUMBER(H33),ISNUMBER(H28)),(H28/損益!D22-(H33)/H90)*損益!D22,"不適用") -> 不適用 | J92: (模型季占比 − 比較季占比) × 模型期間；水準＋分配＝季度差距
A93: 原因｜調整後 EBITDA｜vs 共識 | C93: =IF(ISNUMBER(C46),IF(IF(ISNUMBER(C51),ABS(C51)>輸入與假設!$C$368,OR(AND(C33<>0,ABS(C46)>輸入與假設!$C$367*ABS(C33)),AND(C33=0,C46<>0))),IF(ISNUMBER(C91),IF(ABS(C92)>ABS(C91),"調整後 EBITDA vs 共識 "&IF(C46<0,"−","+")&IF(ABS(C46)<0,"−","")&"$"&TEXT(ABS(ABS(C46)),"#,##0.0")&"m"&IF(ISNUMBER(C51),"／"&IF(C51<0,"−","+")&TEXT(ABS(C51)*100,"#,##0.0")&"pt","")&"：拆法（分配 "&IF(C92<0,"−","+")&IF(ABS(C92)<0,"−","")&"$"&TEXT(ABS(ABS(C92)),"#,##0.0")&"m"&"（Q3 2026 占 2H26 "&TEXT((C28/損益!C22)*100,"#,##0.0")&"%"&"，共識合計 "&TEXT(((C33)/C90)*100,"#,##0.0")&"%"&"）；水準 "&IF(C91<0,"−","+")&IF(ABS(C91)<0,"−","")&"$"&TEXT(ABS(ABS(C91)),"#,##0.0")&"m"&"）","調整後 EBITDA vs 共識 "&IF(C46<0,"−","+")&IF(ABS(C46)<0,"−","")&"$"&TEXT(ABS(ABS(C46)),"#,##0.0")&"m"&IF(ISNUMBER(C51),"／"&IF(C51<0,"−","+")&TEXT(ABS(C51)*100,"#,##0.0")&"pt","")&"：觀點（水準 "&IF(C91<0,"−","+")&IF(ABS(C91)<0,"−","")&"$"&TEXT(ABS(ABS(C91)),"#,##0.0")&"m"&"（2H26 模型 "&IF(損益!C22<0,"−","")&"$"&TEXT(ABS(損益!C22),"#,##0.0")&"m"&"，共識合計 "&IF(C90<0,"−","")&"$"&TEXT(ABS(C90),"#,##0.0")&"m"&"）；分配 "&IF(C92<0,"−","+")&IF(ABS(C92)<0,"−","")&"$"&TEXT(ABS(ABS(C92)),"#,##0.0")&"m"&"；"&"模型 EBITDA 率 "&IF((C27)<0,"−","")&TEXT(ABS((C27))*100,"#,##0.0")&"%"&"（雲端起點以扣一次性後的經常性數字校準）"&"）"),"調整後 EBITDA vs 共識 "&IF(C46<0,"−","+")&IF(ABS(C46)<0,"−","")&"$"&TEXT(ABS(ABS(C46)),"#,##0.0")&"m"&IF(ISNUMBER(C51),"／"&IF(C51<0,"−","+")&TEXT(ABS(C51)*100,"#,##0.0")&"pt","")&"：觀點（"&"模型 EBITDA 率 "&IF((C27)<0,"−","")&TEXT(ABS((C27))*100,"#,##0.0")&"%"&"（雲端起點以扣一次性後的經常性數字校準）"&"）"),""),"") | D93: =IF(ISNUMBER(D46),IF(IF(ISNUMBER(D51),ABS(D51)>輸入與假設!$C$368,OR(AND(D33<>0,ABS(D46)>輸入與假設!$C$367*ABS(D33)),AND(D33=0,D46<>0))),IF(ISNUMBER(D91),IF(ABS(D92)>ABS(D91),"調整後 EBITDA vs 共識 "&IF(D46<0,"−","+")&IF(ABS(D46)<0,"−","")&"$"&TEXT(ABS(ABS(D46)),"#,##0.0")&"m"&IF(ISNUMBER(D51),"／"&IF(D51<0,"−","+")&TEXT(ABS(D51)*100,"#,##0.0")&"pt","")&"：拆法（分配 "&IF(D92<0,"−","+")&IF(ABS(D92)<0,"−","")&"$"&TEXT(ABS(ABS(D92)),"#,##0.0")&"m"&"（Q4 2026 占 2H26 "&TEXT((D28/損益!C22)*100,"#,##0.0")&"%"&"，共識合計 "&TEXT(((D33)/D90)*100,"#,##0.0")&"%"&"）；水準 "&IF(D91<0,"−","+")&IF(ABS(D91)<0,"−","")&"$"&TEXT(ABS(ABS(D91)),"#,##0.0")&"m"&"）","調整後 EBITDA vs 共識 "&IF(D46<0,"−","+")&IF(ABS(D46)<0,"−","")&"$"&TEXT(ABS(ABS(D46)),"#,##0.0")&"m"&IF(ISNUMBER(D51),"／"&IF(D51<0,"−","+")&TEXT(ABS(D51)*100,"#,##0.0")&"pt","")&"：觀點（水準 "&IF(D91<0,"−","+")&IF(ABS(D91)<0,"−","")&"$"&TEXT(ABS(ABS(D91)),"#,##0.0")&"m"&"（2H26 模型 "&IF(損益!C22<0,"−","")&"$"&TEXT(ABS(損益!C22),"#,##0.0")&"m"&"，共識合計 "&IF(D90<0,"−","")&"$"&TEXT(ABS(D90),"#,##0.0")&"m"&"）；分配 "&IF(D92<0,"−","+")&IF(ABS(D92)<0,"−","")&"$"&TEXT(ABS(ABS(D92)),"#,##0.0")&"m"&"；"&"模型 EBITDA 率 "&IF((D27)<0,"−","")&TEXT(ABS((D27))*100,"#,##0.0")&"%"&"（雲端起點以扣一次性後的經常性數字校準）"&"）"),"調整後 EBITDA vs 共識 "&IF(D46<0,"−","+")&IF(ABS(D46)<0,"−","")&"$"&TEXT(ABS(ABS(D46)),"#,##0.0")&"m"&IF(ISNUMBER(D51),"／"&IF(D51<0,"−","+")&TEXT(ABS(D51)*100,"#,##0.0")&"pt","")&"：觀點（"&"模型 EBITDA 率 "&IF((D27)<0,"−","")&TEXT(ABS((D27))*100,"#,##0.0")&"%"&"（雲端起點以扣一次性後的經常性數字校準）"&"）"),""),"") | E93: =IF(ISNUMBER(E46),IF(IF(ISNUMBER(E51),ABS(E51)>輸入與假設!$C$368,OR(AND(E33<>0,ABS(E46)>輸入與假設!$C$367*ABS(E33)),AND(E33=0,E46<>0))),IF(ISNUMBER(E91),IF(ABS(E92)>ABS(E91),"調整後 EBITDA vs 共識 "&IF(E46<0,"−","+")&IF(ABS(E46)<0,"−","")&"$"&TEXT(ABS(ABS(E46)),"#,##0.0")&"m"&IF(ISNUMBER(E51),"／"&IF(E51<0,"−","+")&TEXT(ABS(E51)*100,"#,##0.0")&"pt","")&"：拆法（分配 "&IF(E92<0,"−","+")&IF(ABS(E92)<0,"−","")&"$"&TEXT(ABS(ABS(E92)),"#,##0.0")&"m"&"（Q1 2027 占 FY27 "&TEXT((E28/損益!D22)*100,"#,##0.0")&"%"&"，共識合計 "&TEXT(((E33)/E90)*100,"#,##0.0")&"%"&"）；水準 "&IF(E91<0,"−","+")&IF(ABS(E91)<0,"−","")&"$"&TEXT(ABS(ABS(E91)),"#,##0.0")&"m"&"）","調整後 EBITDA vs 共識 "&IF(E46<0,"−","+")&IF(ABS(E46)<0,"−","")&"$"&TEXT(ABS(ABS(E46)),"#,##0.0")&"m"&IF(ISNUMBER(E51),"／"&IF(E51<0,"−","+")&TEXT(ABS(E51)*100,"#,##0.0")&"pt","")&"：觀點（水準 "&IF(E91<0,"−","+")&IF(ABS(E91)<0,"−","")&"$"&TEXT(ABS(ABS(E91)),"#,##0.0")&"m"&"（FY27 模型 "&IF(損益!D22<0,"−","")&"$"&TEXT(ABS(損益!D22),"#,##0.0")&"m"&"，共識合計 "&IF(E90<0,"−","")&"$"&TEXT(ABS(E90),"#,##0.0")&"m"&"）；分配 "&IF(E92<0,"−","+")&IF(ABS(E92)<0,"−","")&"$"&TEXT(ABS(ABS(E92)),"#,##0.0")&"m"&"；"&"模型 EBITDA 率 "&IF((E27)<0,"−","")&TEXT(ABS((E27))*100,"#,##0.0")&"%"&"（雲端起點以扣一次性後的經常性數字校準）"&"）"),"調整後 EBITDA vs 共識 "&IF(E46<0,"−","+")&IF(ABS(E46)<0,"−","")&"$"&TEXT(ABS(ABS(E46)),"#,##0.0")&"m"&IF(ISNUMBER(E51),"／"&IF(E51<0,"−","+")&TEXT(ABS(E51)*100,"#,##0.0")&"pt","")&"：觀點（"&"模型 EBITDA 率 "&IF((E27)<0,"−","")&TEXT(ABS((E27))*100,"#,##0.0")&"%"&"（雲端起點以扣一次性後的經常性數字校準）"&"）"),""),"") | F93: =IF(ISNUMBER(F46),IF(IF(ISNUMBER(F51),ABS(F51)>輸入與假設!$C$368,OR(AND(F33<>0,ABS(F46)>輸入與假設!$C$367*ABS(F33)),AND(F33=0,F46<>0))),IF(ISNUMBER(F91),IF(ABS(F92)>ABS(F91),"調整後 EBITDA vs 共識 "&IF(F46<0,"−","+")&IF(ABS(F46)<0,"−","")&"$"&TEXT(ABS(ABS(F46)),"#,##0.0")&"m"&IF(ISNUMBER(F51),"／"&IF(F51<0,"−","+")&TEXT(ABS(F51)*100,"#,##0.0")&"pt","")&"：拆法（分配 "&IF(F92<0,"−","+")&IF(ABS(F92)<0,"−","")&"$"&TEXT(ABS(ABS(F92)),"#,##0.0")&"m"&"（Q2 2027 占 FY27 "&TEXT((F28/損益!D22)*100,"#,##0.0")&"%"&"，共識合計 "&TEXT(((F33)/F90)*100,"#,##0.0")&"%"&"）；水準 "&IF(F91<0,"−","+")&IF(ABS(F91)<0,"−","")&"$"&TEXT(ABS(ABS(F91)),"#,##0.0")&"m"&"）","調整後 EBITDA vs 共識 "&IF(F46<0,"−","+")&IF(ABS(F46)<0,"−","")&"$"&TEXT(ABS(ABS(F46)),"#,##0.0")&"m"&IF(ISNUMBER(F51),"／"&IF(F51<0,"−","+")&TEXT(ABS(F51)*100,"#,##0.0")&"pt","")&"：觀點（水準 "&IF(F91<0,"−","+")&IF(ABS(F91)<0,"−","")&"$"&TEXT(ABS(ABS(F91)),"#,##0.0")&"m"&"（FY27 模型 "&IF(損益!D22<0,"−","")&"$"&TEXT(ABS(損益!D22),"#,##0.0")&"m"&"，共識合計 "&IF(F90<0,"−","")&"$"&TEXT(ABS(F90),"#,##0.0")&"m"&"）；分配 "&IF(F92<0,"−","+")&IF(ABS(F92)<0,"−","")&"$"&TEXT(ABS(ABS(F92)),"#,##0.0")&"m"&"；"&"模型 EBITDA 率 "&IF((F27)<0,"−","")&TEXT(ABS((F27))*100,"#,##0.0")&"%"&"（雲端起點以扣一次性後的經常性數字校準）"&"）"),"調整後 EBITDA vs 共識 "&IF(F46<0,"−","+")&IF(ABS(F46)<0,"−","")&"$"&TEXT(ABS(ABS(F46)),"#,##0.0")&"m"&IF(ISNUMBER(F51),"／"&IF(F51<0,"−","+")&TEXT(ABS(F51)*100,"#,##0.0")&"pt","")&"：觀點（"&"模型 EBITDA 率 "&IF((F27)<0,"−","")&TEXT(ABS((F27))*100,"#,##0.0")&"%"&"（雲端起點以扣一次性後的經常性數字校準）"&"）"),""),"") | G93: =IF(ISNUMBER(G46),IF(IF(ISNUMBER(G51),ABS(G51)>輸入與假設!$C$368,OR(AND(G33<>0,ABS(G46)>輸入與假設!$C$367*ABS(G33)),AND(G33=0,G46<>0))),IF(ISNUMBER(G91),IF(ABS(G92)>ABS(G91),"調整後 EBITDA vs 共識 "&IF(G46<0,"−","+")&IF(ABS(G46)<0,"−","")&"$"&TEXT(ABS(ABS(G46)),"#,##0.0")&"m"&IF(ISNUMBER(G51),"／"&IF(G51<0,"−","+")&TEXT(ABS(G51)*100,"#,##0.0")&"pt","")&"：拆法（分配 "&IF(G92<0,"−","+")&IF(ABS(G92)<0,"−","")&"$"&TEXT(ABS(ABS(G92)),"#,##0.0")&"m"&"（Q3 2027 占 FY27 "&TEXT((G28/損益!D22)*100,"#,##0.0")&"%"&"，共識合計 "&TEXT(((G33)/G90)*100,"#,##0.0")&"%"&"）；水準 "&IF(G91<0,"−","+")&IF(ABS(G91)<0,"−","")&"$"&TEXT(ABS(ABS(G91)),"#,##0.0")&"m"&"）","調整後 EBITDA vs 共識 "&IF(G46<0,"−","+")&IF(ABS(G46)<0,"−","")&"$"&TEXT(ABS(ABS(G46)),"#,##0.0")&"m"&IF(ISNUMBER(G51),"／"&IF(G51<0,"−","+")&TEXT(ABS(G51)*100,"#,##0.0")&"pt","")&"：觀點（水準 "&IF(G91<0,"−","+")&IF(ABS(G91)<0,"−","")&"$"&TEXT(ABS(ABS(G91)),"#,##0.0")&"m"&"（FY27 模型 "&IF(損益!D22<0,"−","")&"$"&TEXT(ABS(損益!D22),"#,##0.0")&"m"&"，共識合計 "&IF(G90<0,"−","")&"$"&TEXT(ABS(G90),"#,##0.0")&"m"&"）；分配 "&IF(G92<0,"−","+")&IF(ABS(G92)<0,"−","")&"$"&TEXT(ABS(ABS(G92)),"#,##0.0")&"m"&"；"&"模型 EBITDA 率 "&IF((G27)<0,"−","")&TEXT(ABS((G27))*100,"#,##0.0")&"%"&"（雲端起點以扣一次性後的經常性數字校準）"&"）"),"調整後 EBITDA vs 共識 "&IF(G46<0,"−","+")&IF(ABS(G46)<0,"−","")&"$"&TEXT(ABS(ABS(G46)),"#,##0.0")&"m"&IF(ISNUMBER(G51),"／"&IF(G51<0,"−","+")&TEXT(ABS(G51)*100,"#,##0.0")&"pt","")&"：觀點（"&"模型 EBITDA 率 "&IF((G27)<0,"−","")&TEXT(ABS((G27))*100,"#,##0.0")&"%"&"（雲端起點以扣一次性後的經常性數字校準）"&"）"),""),"") | H93: =IF(ISNUMBER(H46),IF(IF(ISNUMBER(H51),ABS(H51)>輸入與假設!$C$368,OR(AND(H33<>0,ABS(H46)>輸入與假設!$C$367*ABS(H33)),AND(H33=0,H46<>0))),IF(ISNUMBER(H91),IF(ABS(H92)>ABS(H91),"調整後 EBITDA vs 共識 "&IF(H46<0,"−","+")&IF(ABS(H46)<0,"−","")&"$"&TEXT(ABS(ABS(H46)),"#,##0.0")&"m"&IF(ISNUMBER(H51),"／"&IF(H51<0,"−","+")&TEXT(ABS(H51)*100,"#,##0.0")&"pt","")&"：拆法（分配 "&IF(H92<0,"−","+")&IF(ABS(H92)<0,"−","")&"$"&TEXT(ABS(ABS(H92)),"#,##0.0")&"m"&"（Q4 2027 占 FY27 "&TEXT((H28/損益!D22)*100,"#,##0.0")&"%"&"，共識合計 "&TEXT(((H33)/H90)*100,"#,##0.0")&"%"&"）；水準 "&IF(H91<0,"−","+")&IF(ABS(H91)<0,"−","")&"$"&TEXT(ABS(ABS(H91)),"#,##0.0")&"m"&"）","調整後 EBITDA vs 共識 "&IF(H46<0,"−","+")&IF(ABS(H46)<0,"−","")&"$"&TEXT(ABS(ABS(H46)),"#,##0.0")&"m"&IF(ISNUMBER(H51),"／"&IF(H51<0,"−","+")&TEXT(ABS(H51)*100,"#,##0.0")&"pt","")&"：觀點（水準 "&IF(H91<0,"−","+")&IF(ABS(H91)<0,"−","")&"$"&TEXT(ABS(ABS(H91)),"#,##0.0")&"m"&"（FY27 模型 "&IF(損益!D22<0,"−","")&"$"&TEXT(ABS(損益!D22),"#,##0.0")&"m"&"，共識合計 "&IF(H90<0,"−","")&"$"&TEXT(ABS(H90),"#,##0.0")&"m"&"）；分配 "&IF(H92<0,"−","+")&IF(ABS(H92)<0,"−","")&"$"&TEXT(ABS(ABS(H92)),"#,##0.0")&"m"&"；"&"模型 EBITDA 率 "&IF((H27)<0,"−","")&TEXT(ABS((H27))*100,"#,##0.0")&"%"&"（雲端起點以扣一次性後的經常性數字校準）"&"）"),"調整後 EBITDA vs 共識 "&IF(H46<0,"−","+")&IF(ABS(H46)<0,"−","")&"$"&TEXT(ABS(ABS(H46)),"#,##0.0")&"m"&IF(ISNUMBER(H51),"／"&IF(H51<0,"−","+")&TEXT(ABS(H51)*100,"#,##0.0")&"pt","")&"：觀點（"&"模型 EBITDA 率 "&IF((H27)<0,"−","")&TEXT(ABS((H27))*100,"#,##0.0")&"%"&"（雲端起點以扣一次性後的經常性數字校準）"&"）"),""),"")
A94: 原因類型｜調整後 EBITDA｜vs 共識 | C94: =IF(ISNUMBER(C46),IF(IF(ISNUMBER(C51),ABS(C51)>輸入與假設!$C$368,OR(AND(C33<>0,ABS(C46)>輸入與假設!$C$367*ABS(C33)),AND(C33=0,C46<>0))),IF(ISNUMBER(C91),IF(ABS(C92)>ABS(C91),"拆法","觀點"),"觀點"),""),"") | D94: =IF(ISNUMBER(D46),IF(IF(ISNUMBER(D51),ABS(D51)>輸入與假設!$C$368,OR(AND(D33<>0,ABS(D46)>輸入與假設!$C$367*ABS(D33)),AND(D33=0,D46<>0))),IF(ISNUMBER(D91),IF(ABS(D92)>ABS(D91),"拆法","觀點"),"觀點"),""),"") | E94: =IF(ISNUMBER(E46),IF(IF(ISNUMBER(E51),ABS(E51)>輸入與假設!$C$368,OR(AND(E33<>0,ABS(E46)>輸入與假設!$C$367*ABS(E33)),AND(E33=0,E46<>0))),IF(ISNUMBER(E91),IF(ABS(E92)>ABS(E91),"拆法","觀點"),"觀點"),""),"") | F94: =IF(ISNUMBER(F46),IF(IF(ISNUMBER(F51),ABS(F51)>輸入與假設!$C$368,OR(AND(F33<>0,ABS(F46)>輸入與假設!$C$367*ABS(F33)),AND(F33=0,F46<>0))),IF(ISNUMBER(F91),IF(ABS(F92)>ABS(F91),"拆法","觀點"),"觀點"),""),"") | G94: =IF(ISNUMBER(G46),IF(IF(ISNUMBER(G51),ABS(G51)>輸入與假設!$C$368,OR(AND(G33<>0,ABS(G46)>輸入與假設!$C$367*ABS(G33)),AND(G33=0,G46<>0))),IF(ISNUMBER(G91),IF(ABS(G92)>ABS(G91),"拆法","觀點"),"觀點"),""),"") | H94: =IF(ISNUMBER(H46),IF(IF(ISNUMBER(H51),ABS(H51)>輸入與假設!$C$368,OR(AND(H33<>0,ABS(H46)>輸入與假設!$C$367*ABS(H33)),AND(H33=0,H46<>0))),IF(ISNUMBER(H91),IF(ABS(H92)>ABS(H91),"拆法","觀點"),"觀點"),""),"")
A95: 原因｜調整後 EBITDA｜vs 指引中點
A96: 原因類型｜調整後 EBITDA｜vs 指引中點
A97: 原因｜調整後 EBITDA｜實際 vs 模型 | C97: =IF(ISNUMBER(C48),IF(IF(ISNUMBER(C53),ABS(C53)>輸入與假設!$C$368,OR(AND(C28<>0,ABS(C48)>輸入與假設!$C$367*ABS(C28)),AND(C28=0,C48<>0))),"調整後 EBITDA 實際 vs 模型 "&IF(C48<0,"−","+")&IF(ABS(C48)<0,"−","")&"$"&TEXT(ABS(ABS(C48)),"#,##0.0")&"m"&IF(ISNUMBER(C53),"／"&IF(C53<0,"−","+")&TEXT(ABS(C53)*100,"#,##0.0")&"pt","")&"：觀點（"&"模型 EBITDA 率 "&IF((C27)<0,"−","")&TEXT(ABS((C27))*100,"#,##0.0")&"%"&"（雲端起點以扣一次性後的經常性數字校準）"&"）",""),"") | D97: =IF(ISNUMBER(D48),IF(IF(ISNUMBER(D53),ABS(D53)>輸入與假設!$C$368,OR(AND(D28<>0,ABS(D48)>輸入與假設!$C$367*ABS(D28)),AND(D28=0,D48<>0))),"調整後 EBITDA 實際 vs 模型 "&IF(D48<0,"−","+")&IF(ABS(D48)<0,"−","")&"$"&TEXT(ABS(ABS(D48)),"#,##0.0")&"m"&IF(ISNUMBER(D53),"／"&IF(D53<0,"−","+")&TEXT(ABS(D53)*100,"#,##0.0")&"pt","")&"：觀點（"&"模型 EBITDA 率 "&IF((D27)<0,"−","")&TEXT(ABS((D27))*100,"#,##0.0")&"%"&"（雲端起點以扣一次性後的經常性數字校準）"&"）",""),"") | E97: =IF(ISNUMBER(E48),IF(IF(ISNUMBER(E53),ABS(E53)>輸入與假設!$C$368,OR(AND(E28<>0,ABS(E48)>輸入與假設!$C$367*ABS(E28)),AND(E28=0,E48<>0))),"調整後 EBITDA 實際 vs 模型 "&IF(E48<0,"−","+")&IF(ABS(E48)<0,"−","")&"$"&TEXT(ABS(ABS(E48)),"#,##0.0")&"m"&IF(ISNUMBER(E53),"／"&IF(E53<0,"−","+")&TEXT(ABS(E53)*100,"#,##0.0")&"pt","")&"：觀點（"&"模型 EBITDA 率 "&IF((E27)<0,"−","")&TEXT(ABS((E27))*100,"#,##0.0")&"%"&"（雲端起點以扣一次性後的經常性數字校準）"&"）",""),"") | F97: =IF(ISNUMBER(F48),IF(IF(ISNUMBER(F53),ABS(F53)>輸入與假設!$C$368,OR(AND(F28<>0,ABS(F48)>輸入與假設!$C$367*ABS(F28)),AND(F28=0,F48<>0))),"調整後 EBITDA 實際 vs 模型 "&IF(F48<0,"−","+")&IF(ABS(F48)<0,"−","")&"$"&TEXT(ABS(ABS(F48)),"#,##0.0")&"m"&IF(ISNUMBER(F53),"／"&IF(F53<0,"−","+")&TEXT(ABS(F53)*100,"#,##0.0")&"pt","")&"：觀點（"&"模型 EBITDA 率 "&IF((F27)<0,"−","")&TEXT(ABS((F27))*100,"#,##0.0")&"%"&"（雲端起點以扣一次性後的經常性數字校準）"&"）",""),"") | G97: =IF(ISNUMBER(G48),IF(IF(ISNUMBER(G53),ABS(G53)>輸入與假設!$C$368,OR(AND(G28<>0,ABS(G48)>輸入與假設!$C$367*ABS(G28)),AND(G28=0,G48<>0))),"調整後 EBITDA 實際 vs 模型 "&IF(G48<0,"−","+")&IF(ABS(G48)<0,"−","")&"$"&TEXT(ABS(ABS(G48)),"#,##0.0")&"m"&IF(ISNUMBER(G53),"／"&IF(G53<0,"−","+")&TEXT(ABS(G53)*100,"#,##0.0")&"pt","")&"：觀點（"&"模型 EBITDA 率 "&IF((G27)<0,"−","")&TEXT(ABS((G27))*100,"#,##0.0")&"%"&"（雲端起點以扣一次性後的經常性數字校準）"&"）",""),"") | H97: =IF(ISNUMBER(H48),IF(IF(ISNUMBER(H53),ABS(H53)>輸入與假設!$C$368,OR(AND(H28<>0,ABS(H48)>輸入與假設!$C$367*ABS(H28)),AND(H28=0,H48<>0))),"調整後 EBITDA 實際 vs 模型 "&IF(H48<0,"−","+")&IF(ABS(H48)<0,"−","")&"$"&TEXT(ABS(ABS(H48)),"#,##0.0")&"m"&IF(ISNUMBER(H53),"／"&IF(H53<0,"−","+")&TEXT(ABS(H53)*100,"#,##0.0")&"pt","")&"：觀點（"&"模型 EBITDA 率 "&IF((H27)<0,"−","")&TEXT(ABS((H27))*100,"#,##0.0")&"%"&"（雲端起點以扣一次性後的經常性數字校準）"&"）",""),"")
A98: 原因類型｜調整後 EBITDA｜實際 vs 模型 | C98: =IF(ISNUMBER(C48),IF(IF(ISNUMBER(C53),ABS(C53)>輸入與假設!$C$368,OR(AND(C28<>0,ABS(C48)>輸入與假設!$C$367*ABS(C28)),AND(C28=0,C48<>0))),"觀點",""),"") | D98: =IF(ISNUMBER(D48),IF(IF(ISNUMBER(D53),ABS(D53)>輸入與假設!$C$368,OR(AND(D28<>0,ABS(D48)>輸入與假設!$C$367*ABS(D28)),AND(D28=0,D48<>0))),"觀點",""),"") | E98: =IF(ISNUMBER(E48),IF(IF(ISNUMBER(E53),ABS(E53)>輸入與假設!$C$368,OR(AND(E28<>0,ABS(E48)>輸入與假設!$C$367*ABS(E28)),AND(E28=0,E48<>0))),"觀點",""),"") | F98: =IF(ISNUMBER(F48),IF(IF(ISNUMBER(F53),ABS(F53)>輸入與假設!$C$368,OR(AND(F28<>0,ABS(F48)>輸入與假設!$C$367*ABS(F28)),AND(F28=0,F48<>0))),"觀點",""),"") | G98: =IF(ISNUMBER(G48),IF(IF(ISNUMBER(G53),ABS(G53)>輸入與假設!$C$368,OR(AND(G28<>0,ABS(G48)>輸入與假設!$C$367*ABS(G28)),AND(G28=0,G48<>0))),"觀點",""),"") | H98: =IF(ISNUMBER(H48),IF(IF(ISNUMBER(H53),ABS(H53)>輸入與假設!$C$368,OR(AND(H28<>0,ABS(H48)>輸入與假設!$C$367*ABS(H28)),AND(H28=0,H48<>0))),"觀點",""),"")
A99: 原因｜調整後營業利益｜vs 共識
A100: 原因類型｜調整後營業利益｜vs 共識
A101: 原因｜調整後營業利益｜vs 指引中點
A102: 原因類型｜調整後營業利益｜vs 指引中點
...

Sheet 運營_產能與收入
A1: 產能與收入 — 合約排程 vs 機房產能
A2: 兩條線獨立產生後相減：排程>容量→瓶頸（收不到）；容量>排程→剩餘產能（要靠新簽約賣掉）
A3: FY26 欄口徑：MW 為年底存量；標示「（模型期）」的收入列只含 2026 下半年——RPO 桶自 2026-06-30 起算，1H 收入已實現、不再受產能約束。1H 實際單列，兩者相加即 FY26 全年（見本頁「FY26 全年」列）。
A5: 項目 | B5: 單位 | C5: FY26 | D5: FY27 | E5: FY28 | F5: FY29 | G5: FY30 | I5: 公式／來源說明
A6: 模型期間 | C6: ="2026-07-01~12-31" -> 2026-07-01~12-31 | D6: ="2027 全年" -> 2027 全年 | E6: ="2028 全年" -> 2028 全年 | F6: ="2029 全年" -> 2029 全年 | G6: ="2030 全年" -> 2030 全年 | I6: FY26 的模型期只有下半年；1H 已實現的營收單列於下方
A7: 模型期長度（年） | C7: =輸入與假設!C$41 -> 0.5 | D7: =輸入與假設!D$41 -> 1 | E7: =輸入與假設!E$41 -> 1 | F7: =輸入與假設!F$41 -> 1 | G7: =輸入與假設!G$41 -> 1 | I7: 只用於下方三處：容量上限、電力、維護——把年率換算成該期金額
A8: （A）機房：容量上限
A9: Accepted MW（已驗收，單調不減） | B9: MW | C9: =MAX(0,輸入與假設!C$43) -> 14.574 | D9: =MAX(輸入與假設!D$43,C9) -> 16.548 | E9: =MAX(輸入與假設!E$43,D9) -> 19.548 | F9: =MAX(輸入與假設!F$43,E9) -> 22.548 | G9: =MAX(輸入與假設!G$43,F9) -> 25.548 | I9: 引擎規則：不得低於前期（產能不會消失）
A10: Billable MW（上限為 Accepted） | B10: MW | C10: =MIN(MAX(0,輸入與假設!C$44),C9) -> 11 | D10: =MIN(MAX(0,輸入與假設!D$44),D9) -> 14.46 | E10: =MIN(MAX(0,輸入與假設!E$44),E9) -> 17.86 | F10: =MIN(MAX(0,輸入與假設!F$44),F9) -> 20.56 | G10: =MIN(MAX(0,輸入與假設!G$44),G9) -> 23.26 | I10: 引擎規則：可計費不得超過已驗收
A11: Billable MW（延誤後，計費用） | B11: MW | C11: =IF($C$62<=0,$C$10,輸入與假設!$C$36+($C$10-輸入與假設!$C$36)*MAX(0,MIN(1,($C$63-$C$62/12-0)/$C$7))+($D$10-$C$10)*MAX(0,MIN(1,($C$63-$C$62/12-$C$63)/$D$7))+($E$10-$D$10)*MAX(0,MIN(1,($C$63-$C$62/12-$D$63)/$E$7))+($F$10-$E$10)*MAX(0,MIN(1,($C$63-$C$62/12-$E$63)/$F$7))+($G$10-$F$10)*MAX(0,MIN(1,($C$63-$C$62/12-$F$63)/$G$7))) -> 6.825 | D11: =IF($C$62<=0,$D$10,輸入與假設!$C$36+($C$10-輸入與假設!$C$36)*MAX(0,MIN(1,($D$63-$C$62/12-0)/$C$7))+($D$10-$C$10)*MAX(0,MIN(1,($D$63-$C$62/12-$C$63)/$D$7))+($E$10-$D$10)*MAX(0,MIN(1,($D$63-$C$62/12-$D$63)/$E$7))+($F$10-$E$10)*MAX(0,MIN(1,($D$63-$C$62/12-$E$63)/$F$7))+($G$10-$F$10)*MAX(0,MIN(1,($D$63-$C$62/12-$F$63)/$G$7))) -> 13.595 | E11: =IF($C$62<=0,$E$10,輸入與假設!$C$36+($C$10-輸入與假設!$C$36)*MAX(0,MIN(1,($E$63-$C$62/12-0)/$C$7))+($D$10-$C$10)*MAX(0,MIN(1,($E$63-$C$62/12-$C$63)/$D$7))+($E$10-$D$10)*MAX(0,MIN(1,($E$63-$C$62/12-$D$63)/$E$7))+($F$10-$E$10)*MAX(0,MIN(1,($E$63-$C$62/12-$E$63)/$F$7))+($G$10-$F$10)*MAX(0,MIN(1,($E$63-$C$62/12-$F$63)/$G$7))) -> 17.01 | F11: =IF($C$62<=0,$F$10,輸入與假設!$C$36+($C$10-輸入與假設!$C$36)*MAX(0,MIN(1,($F$63-$C$62/12-0)/$C$7))+($D$10-$C$10)*MAX(0,MIN(1,($F$63-$C$62/12-$C$63)/$D$7))+($E$10-$D$10)*MAX(0,MIN(1,($F$63-$C$62/12-$D$63)/$E$7))+($F$10-$E$10)*MAX(0,MIN(1,($F$63-$C$62/12-$E$63)/$F$7))+($G$10-$F$10)*MAX(0,MIN(1,($F$63-$C$62/12-$F$63)/$G$7))) -> 19.885 | G11: =IF($C$62<=0,$G$10,輸入與假設!$C$36+($C$10-輸入與假設!$C$36)*MAX(0,MIN(1,($G$63-$C$62/12-0)/$C$7))+($D$10-$C$10)*MAX(0,MIN(1,($G$63-$C$62/12-$C$63)/$D$7))+($E$10-$D$10)*MAX(0,MIN(1,($G$63-$C$62/12-$D$63)/$E$7))+($F$10-$E$10)*MAX(0,MIN(1,($G$63-$C$62/12-$E$63)/$F$7))+($G$10-$F$10)*MAX(0,MIN(1,($G$63-$C$62/12-$F$63)/$G$7))) -> 22.585 | I11: ＝上列往後平移建設延誤月數（以期間長度線性內插；評價日之前取期初校準值）；延誤 0 時＝上列；見（E）區（v0.2）
A12: 期初在役 MW | B12: MW | C12: =輸入與假設!$C$36 -> 2.65 | D12: =C11 -> 6.825 | E12: =D11 -> 13.595 | F12: =E11 -> 17.01 | G12: =F11 -> 19.885 | I12: 前期期末＝本期期初（延誤後）
A13: 平均在役 MW（FY26 欄為下半年平均） | B13: MW | C13: =IF(輸入與假設!$C$37=1,(C12+C11)/2,C11) -> 4.7375 | D13: =IF(輸入與假設!$C$37=1,(D12+D11)/2,D11) -> 10.21 | E13: =IF(輸入與假設!$C$37=1,(E12+E11)/2,E11) -> 15.3025 | F13: =IF(輸入與假設!$C$37=1,(F12+F11)/2,F11) -> 18.4475 | G13: =IF(輸入與假設!$C$37=1,(G12+G11)/2,G11) -> 21.235 | I13: 開關在輸入頁：1＝(期初+期末)/2，0＝期末全期化
A14: 利用率 | B14: % | C14: =輸入與假設!C$45 -> 1 | D14: =輸入與假設!D$45 -> 1 | E14: =輸入與假設!E$45 -> 1 | F14: =輸入與假設!F$45 -> 1 | G14: =輸入與假設!G$45 -> 1
A15: 每 MW 年收入 | B15: US$m/MW | C15: =輸入與假設!C$46 -> 17.4 | D15: =輸入與假設!D$46 -> 17.4 | E15: =輸入與假設!E$46 -> 17.4 | F15: =輸入與假設!F$46 -> 17.4 | G15: =輸入與假設!G$46 -> 17.4
A16: 容量上限（模型期最多能交付的收入） | B16: US$m | C16: =C13*輸入與假設!C$46*輸入與假設!$C$39*輸入與假設!C$45*C7 -> 41.21625 | D16: =D13*輸入與假設!D$46*輸入與假設!$C$39*輸入與假設!D$45*D7 -> 177.654 | E16: =E13*輸入與假設!E$46*輸入與假設!$C$39*輸入與假設!E$45*E7 -> 266.2635 | F16: =F13*輸入與假設!F$46*輸入與假設!$C$39*輸入與假設!F$45*F7 -> 320.9865 | G16: =G13*輸入與假設!G$46*輸入與假設!$C$39*輸入與假設!G$45*G7 -> 369.489 | I16: ＝平均在役 MW × 每 MW 年收入 × 利用率 × 期間係數。只看機房，不看合約
A17: （B）合約：排程 RPO
A18: 排程 RPO（模型期，依季報桶分攤） | B18: US$m | C18: =(輸入與假設!$C$31+輸入與假設!$C$32)*(輸入與假設!C$42/輸入與假設!$C$34)*輸入與假設!$C$33 -> 21.627019 | D18: =(輸入與假設!$C$31+輸入與假設!$C$32)*(輸入與假設!D$42/輸入與假設!$C$34)*輸入與假設!$C$33 -> 43.253962 | E18: =(輸入與假設!$C$31+輸入與假設!$C$32)*(輸入與假設!E$42/輸入與假設!$C$34)*輸入與假設!$C$33 -> 10.265019 | F18: =(輸入與假設!$C$31+輸入與假設!$C$32)*(輸入與假設!F$42/輸入與假設!$C$34)*輸入與假設!$C$33 -> 0 | G18: =(輸入與假設!$C$31+輸入與假設!$C$32)*(輸入與假設!G$42/輸入與假設!$C$34)*輸入與假設!$C$33 -> 0 | I18: ＝(6/30 RPO＋評價日後新增)×本期權重÷權重合計×五期認列比例。只看合約，不看機房
A19: （C）兩條線相減
A20: 產能瓶頸（模型期：排程 − 容量） | B20: US$m | C20: =MAX(0,C18-C16) -> 0 | D20: =MAX(0,D18-D16) -> 0 | E20: =MAX(0,E18-E16) -> 0 | F20: =MAX(0,F18-F16) -> 0 | G20: =MAX(0,G18-G16) -> 0 | I20: 合約有、機房沒有 → 本期收不到，且不遞延到下期（保守處理）
A21: 期初 RPO 轉換收入（模型期） | B21: US$m | C21: =C18-C20 -> 21.627019 | D21: =D18-D20 -> 43.253962 | E21: =E18-E20 -> 10.265019 | F21: =F18-F20 -> 0 | G21: =G18-G20 -> 0 | I21: ＝排程 − 瓶頸。當瓶頸>0 時，此值恆等於容量上限
A22: 未被期初 RPO 占用的產能 | B22: US$m | C22: =MAX(0,C16-C18) -> 19.589231 | D22: =MAX(0,D16-D18) -> 134.40004 | E22: =MAX(0,E16-E18) -> 255.99848 | F22: =MAX(0,F16-F18) -> 320.9865 | G22: =MAX(0,G16-G18) -> 369.489 | I22: 容量 − 排程。機房有、期初合約沒占滿 → 要靠新簽約
A23: 新產能簽約率 | B23: % | C23: =IF(輸入與假設!$C$38="mw",1,輸入與假設!C$47) -> 1 | D23: =IF(輸入與假設!$C$38="mw",1,輸入與假設!D$47) -> 1 | E23: =IF(輸入與假設!$C$38="mw",1,輸入與假設!E$47) -> 1 | F23: =IF(輸入與假設!$C$38="mw",1,輸入與假設!F$47) -> 1 | G23: =IF(輸入與假設!$C$38="mw",1,輸入與假設!G$47) -> 1 | I23: MW 驅動時固定 100%
A24: 新簽約收入 | B24: US$m | C24: =C22*C23 -> 19.589231 | D24: =D22*D23 -> 134.40004 | E24: =E22*E23 -> 255.99848 | F24: =F22*F23 -> 320.9865 | G24: =G22*G23 -> 369.489 | I24: 超出期初 RPO 的產能收入（MW 驅動，簽約率 100%）
A25: 未售產能（浪費） | B25: US$m | C25: =MAX(0,C16-C21-C24) -> 0 | D25: =MAX(0,D16-D21-D24) -> 0 | E25: =MAX(0,E16-E21-E24) -> 0 | F25: =MAX(0,F16-F21-F24) -> 0 | G25: =MAX(0,G16-G21-G24) -> 0 | I25: 蓋好但賣不掉（MW 驅動時為 0）
A26: 損益用算力收入（模型期＝RPO 轉換＋新簽約） | B26: US$m | C26: =C21+C24 -> 41.21625 | D26: =D21+D24 -> 177.654 | E26: =E21+E24 -> 266.2635 | F26: =F21+F24 -> 320.9865 | G26: =G21+G24 -> 369.489 | I26: 損益與評價頁的算力收入由此連結，確保現金與損益同一組數字
A27: 核對：算力收入 − 平均在役 MW × 每 MW × 利用率 × 期間 | B27: US$m | C27: =C26-C13*輸入與假設!C$46*輸入與假設!$C$39*輸入與假設!C$45*C7 -> 0 | D27: =D26-D13*輸入與假設!D$46*輸入與假設!$C$39*輸入與假設!D$45*D7 -> 0 | E27: =E26-E13*輸入與假設!E$46*輸入與假設!$C$39*輸入與假設!E$45*E7 -> 0 | F27: =F26-F13*輸入與假設!F$46*輸入與假設!$C$39*輸入與假設!F$45*F7 -> 0 | G27: =G26-G13*輸入與假設!G$46*輸入與假設!$C$39*輸入與假設!G$45*G7 -> 0 | I27: MW 驅動時應為 0：營收可追溯為 MW × 每 MW 年收入 × 利用率（v0.1b）
A28: 對照：評價日起 36 個月營收權重 | B28: % | C28: 1 | D28: 1 | E28: 1 | F28: 0.5 | G28: 0 | I28: RPO 36 個月內轉換的對照用（只作對照，不驅動營收）
A29: 對照：評價日起 36 個月 MW 驅動營收 | B29: US$m | C29: =C26*C28 -> 41.21625 | D29: =D26*D28 -> 177.654 | E29: =E26*E28 -> 266.2635 | F29: =F26*F28 -> 160.49325 | G29: =G26*G28 -> 0 | I29: 合計對照季報 RPO 75.146 × 36 個月內 100%（含託管 RPO）；差額不回推每 MW 單價
A30: 1H26 實際營收（季報，已實現） | B30: US$m | C30: =輸入與假設!$C$301 -> 50.762 | D30: =0 -> 0 | E30: =0 -> 0 | F30: =0 -> 0 | G30: =0 -> 0 | I30: 2026-01-01 至 06-30 已認列營收。已實現，不受下半年產能約束，故不進入上方的瓶頸計算
A31: FY26 全年總營收（1H 實際＋模型期算力＋服務＋託管） | B31: US$m | C31: =C30+C26+輸入與假設!C$50+輸入與假設!C$115 -> 129.87243 | D31: =D30+D26+輸入與假設!D$50+輸入與假設!D$115 -> 278.16958 | E31: =E30+E26+輸入與假設!E$50+輸入與假設!E$115 -> 417.41242 | F31: =F30+F26+輸入與假設!F$50+輸入與假設!F$115 -> 491.92091 | G31: =G30+G26+輸入與假設!G$50+輸入與假設!G$115 -> 544.98474 | I31: FY26 欄對照公司全年指引 不適用（公司未給指引）；FY27 以後即為該年度總營收
A33: ▸ 對照：合約隱含每 MW-IT 年收入 vs Tokenomics（只作對照，不作輸入）
A34: 合約 | B34: 單位 | C34: 合約隱含 | D34: Tokenomics（FY26） | E34: 合約 ÷ Tokenomics | I34: 合約隱含每 MW-IT 年營收 [Derived]：TCV ÷ 年數 ÷（GPU 數 × 每顆 IT kW ÷ 1000），每顆 IT kW 取 Tokenomics v5.26（B300／B200 以 GB300／GB200 近似，HGX 氣冷機實際約低 0–12%，使隱含單價略為低估）；只作對照與敏感度，不作輸入（共同規則第 4 節）
A35: 對照｜合約隱含每 MW｜Baseten（1,392 顆 B300，3 年） | B35: US$m/MW-IT·年 | C35: 19.27 | D35: =輸入與假設!C46*輸入與假設!$C$39 -> 17.4 | E35: =C35/D35 -> 1.1074713 | I35: TCV 165.2 ÷ 3 ÷ 2.858 MW-IT（$4.52／GPU·時）
A36: 對照｜合約隱含每 MW｜Prime Intellect（576 顆 VR200，3 年） | B36: US$m/MW-IT·年 | C36: 18.27 | D36: =輸入與假設!C46*輸入與假設!$C$39 -> 17.4 | E36: =C36/D36 -> 1.05 | I36: TCV 108.2 ÷ 3 ÷ 1.974 MW-IT（$7.15）
A37: 對照｜合約隱含每 MW｜冰島 B300（576 顆，5 年） | B37: US$m/MW-IT·年 | C37: 14.8 | D37: =輸入與假設!C46*輸入與假設!$C$39 -> 17.4 | E37: =C37/D37 -> 0.85057471 | I37: TCV 87.5 ÷ 5 ÷ 1.183 MW-IT（$3.47；另有營收分成）
A38: 對照｜合約隱含每 MW｜128 顆 B300（3 年） | B38: US$m/MW-IT·年 | C38: 20.29 | D38: =輸入與假設!C46*輸入與假設!$C$39 -> 17.4 | E38: =C38/D38 -> 1.166092 | I38: TCV 16.0 ÷ 3 ÷ 0.263 MW-IT（$4.76）
A39: 對照｜合約隱含每 MW｜B200 384 顆（2 年） | B39: US$m/MW-IT·年 | C39: 11.83 | D39: =輸入與假設!C46*輸入與假設!$C$39 -> 17.4 | E39: =C39/D39 -> 0.67988506 | I39: TCV 18.1 ÷ 2 ÷ 0.765 MW-IT
A40: 對照｜合約隱含每 MW｜Prime GB200 216 顆（1 年） | B40: US$m/MW-IT·年 | C40: 15.8 | D40: =輸入與假設!C46*輸入與假設!$C$39 -> 17.4 | E40: =C40/D40 -> 0.90804598 | I40: TCV 6.8 ÷ 0.43 MW-IT
A41: 對照｜合約隱含每 MW｜H100 2,048 顆（2 年；8 卡／台 [Assumed]） | B41: US$m/MW-IT·年 | C41: 8.8 | D41: =輸入與假設!C46*輸入與假設!$C$39 -> 17.4 | E41: =C41/D41 -> 0.50574713 | I41: TCV 50.2 ÷ 2 ÷ 2.852 MW-IT（舊世代）
A42: 對照｜合約隱含每 MW｜新簽 B300／VR200 長約平均（前四筆） | B42: US$m/MW-IT·年 | C42: 18.16 | D42: =輸入與假設!C46*輸入與假設!$C$39 -> 17.4 | E42: =C42/D42 -> 1.0436782 | I42: Baseten、Prime VR200、冰島 B300、128 顆 B300 簡單平均 [Derived]
A43: 對照｜合約隱含每 MW｜Q2 經常性雲端年化 ÷ 冰島 5.5 MW（上限） | B43: US$m/MW-IT·年 | C43: 8.37 | D43: =輸入與假設!C46*輸入與假設!$C$39 -> 17.4 | E43: =C43/D43 -> 0.48103448 | I43: 46.02 ÷ 5.5；亞特蘭大與加拿大 MW 未揭露，分母偏小
A44: （D）收入 → 現金：三道折扣
A45: 客戶違約率 | B45: % | C45: =輸入與假設!C$48 -> 0.005 | D45: =輸入與假設!D$48 -> 0.01 | E45: =輸入與假設!E$48 -> 0.015 | F45: =輸入與假設!F$48 -> 0.02 | G45: =輸入與假設!G$48 -> 0.025
A46: 回收率 | B46: % | C46: =輸入與假設!C$49 -> 0.5 | D46: =輸入與假設!D$49 -> 0.5 | E46: =輸入與假設!E$49 -> 0.5 | F46: =輸入與假設!F$49 -> 0.5 | G46: =輸入與假設!G$49 -> 0.5
A47: 信用損失（期初 RPO 部分） | B47: US$m | C47: =C21*輸入與假設!C$48*(1-輸入與假設!C$49) -> 0.054067547 | D47: =D21*輸入與假設!D$48*(1-輸入與假設!D$49) -> 0.21626981 | E47: =E21*輸入與假設!E$48*(1-輸入與假設!E$49) -> 0.076987641 | F47: =F21*輸入與假設!F$48*(1-輸入與假設!F$49) -> 0 | G47: =G21*輸入與假設!G$48*(1-輸入與假設!G$49) -> 0 | I47: ＝收入 × 違約率 × (1−回收率)
A48: 收現（期初 RPO 部分） | B48: US$m | C48: =C21-C47 -> 21.572951 | D48: =D21-D47 -> 43.037693 | E48: =E21-E47 -> 10.188031 | F48: =F21-F47 -> 0 | G48: =G21-G47 -> 0
A49: EBITDA 率（損益與資金共用） | B49: % | C49: =輸入與假設!C$127 -> -0.32919137 | D49: =輸入與假設!D$127 -> -0.17044846 | E49: =輸入與假設!E$127 -> 0.0063592265 | F49: =輸入與假設!F$127 -> 0.13029448 | G49: =輸入與假設!G$127 -> 0.25918346 | I49: 起始→穩態線性爬升
A50: 模型期總營收（算力＋服務） | B50: US$m | C50: =C26+輸入與假設!C$50 -> 41.21625 | D50: =D26+輸入與假設!D$50 -> 177.654 | E50: =E26+輸入與假設!E$50 -> 266.2635 | F50: =F26+輸入與假設!F$50 -> 320.9865 | G50: =G26+輸入與假設!G$50 -> 369.489
A51: EBITDAR 率（EBITDA 率＋租金÷營收） | B51: % | C51: =輸入與假設!C$127+各期收支!C17/MAX(10,C50) -> -0.042482 | D51: =輸入與假設!D$127+各期收支!D17/MAX(10,D50) -> 0.08989175 | E51: =輸入與假設!E$127+各期收支!E17/MAX(10,E50) -> 0.2222655 | F51: =輸入與假設!F$127+各期收支!F17/MAX(10,F50) -> 0.35463925 | G51: =輸入與假設!G$127+各期收支!G17/MAX(10,G50) -> 0.487013 | I51: 租金前的 EBITDA 率。EBITDA 已扣租金，而資金模型把租金列在支出端，所以要加回，避免重複扣除
A52: RPO 現金（可支應資本用途） | B52: US$m | C52: =C48*C51 -> -0.91646212 | D52: =D48*D51 -> 3.8687335 | E52: =E48*E51 -> 2.2644478 | F52: =F48*F51 -> 0 | G52: =G48*G51 -> 0 | I52: ×EBITDAR 率。租金與利息在支出頁單獨列示
A53: 新簽約現金 | B53: US$m | C53: =C24*(1-輸入與假設!C$48*(1-輸入與假設!C$49))*C51 -> -0.83010925 | D53: =D24*(1-輸入與假設!D$48*(1-輸入與假設!D$49))*D51 -> 12.021047 | E53: =E24*(1-輸入與假設!E$48*(1-輸入與假設!E$49))*E51 -> 56.472883 | F53: =F24*(1-輸入與假設!F$48*(1-輸入與假設!F$49))*F51 -> 112.69607 | G53: =G24*(1-輸入與假設!G$48*(1-輸入與假設!G$49))*G51 -> 177.69662 | I53: 同樣扣信用損失、乘 EBITDAR 率
A55: 讀法：FY26（2H）與 FY27 瓶頸>0，合約多於機房；FY28 起反轉，收入愈來愈靠『新簽約收入』這一列。
A56: 把『新產能簽約率』調到 0，就能看到只靠期初 RPO 的資金缺口有多大——這是最重要的一個壓力測試。
A58: （E）建設延誤（v0.2）：計費 MW 往後平移；GPU 資本支出與客戶出資照原時程；折舊自投入使用時點起算
A59: 建設延誤月數｜保守 只有已簽約 | B59: 月 | C59: 6 | I59: company.json → scenarios.delayMonths；依據見該欄 note [Assumed]
A60: 建設延誤月數｜基準 加 NC-1 下一批 | B60: 月 | C60: 3 | I60: company.json → scenarios.delayMonths；依據見該欄 note [Assumed]
A61: 建設延誤月數｜積極 NC-2／3 與 Krambu | B61: 月 | C61: 0 | I61: company.json → scenarios.delayMonths；依據見該欄 note [Assumed]
A62: 建設延誤月數（目前情境） | B62: 月 | C62: =CHOOSE(輸入與假設!$C$5,運營_產能與收入!$C$59,運營_產能與收入!$C$60,運營_產能與收入!$C$61) -> 3 | I62: ＝依『輸入與假設』A 區情境選擇器；0＝不延誤（＝v0.1）
A63: 期末時點（評價日起，年） | B63: 年 | C63: =SUM($C$7:C7) -> 0.5 | D63: =SUM($C$7:D7) -> 1.5 | E63: =SUM($C$7:E7) -> 2.5 | F63: =SUM($C$7:F7) -> 3.5 | G63: =SUM($C$7:G7) -> 4.5 | I63: ＝累計期間長度
A64: 成長型 CapEx 累計（原時程，評價日起） | B64: US$m | C64: =SUM(輸入與假設!$C$165:C$165) -> 123.37902 | D64: =SUM(輸入與假設!$C$165:D$165) -> 167.22964 | E64: =SUM(輸入與假設!$C$165:E$165) -> 223.61464 | F64: =SUM(輸入與假設!$C$165:F$165) -> 279.99964 | G64: =SUM(輸入與假設!$C$165:G$165) -> 316.64989 | I64: GPU 與網通照原併網時程採購、交貨等電（客戶出資覆蓋比同樣依原時程）
A65: 已投入使用累計（延誤後） | B65: US$m | C65: =IF($C$62<=0,$C$64,0+($C$64-0)*MAX(0,MIN(1,($C$63-$C$62/12-0)/$C$7))+($D$64-$C$64)*MAX(0,MIN(1,($C$63-$C$62/12-$C$63)/$D$7))+($E$64-$D$64)*MAX(0,MIN(1,($C$63-$C$62/12-$D$63)/$E$7))+($F$64-$E$64)*MAX(0,MIN(1,($C$63-$C$62/12-$E$63)/$F$7))+($G$64-$F$64)*MAX(0,MIN(1,($C$63-$C$62/12-$F$63)/$G$7))) -> 61.689512 | D65: =IF($C$62<=0,$D$64,0+($C$64-0)*MAX(0,MIN(1,($D$63-$C$62/12-0)/$C$7))+($D$64-$C$64)*MAX(0,MIN(1,($D$63-$C$62/12-$C$63)/$D$7))+($E$64-$D$64)*MAX(0,MIN(1,($D$63-$C$62/12-$D$63)/$E$7))+($F$64-$E$64)*MAX(0,MIN(1,($D$63-$C$62/12-$E$63)/$F$7))+($G$64-$F$64)*MAX(0,MIN(1,($D$63-$C$62/12-$F$63)/$G$7))) -> 156.26699 | E65: =IF($C$62<=0,$E$64,0+($C$64-0)*MAX(0,MIN(1,($E$63-$C$62/12-0)/$C$7))+($D$64-$C$64)*MAX(0,MIN(1,($E$63-$C$62/12-$C$63)/$D$7))+($E$64-$D$64)*MAX(0,MIN(1,($E$63-$C$62/12-$D$63)/$E$7))+($F$64-$E$64)*MAX(0,MIN(1,($E$63-$C$62/12-$E$63)/$F$7))+($G$64-$F$64)*MAX(0,MIN(1,($E$63-$C$62/12-$F$63)/$G$7))) -> 209.51839 | F65: =IF($C$62<=0,$F$64,0+($C$64-0)*MAX(0,MIN(1,($F$63-$C$62/12-0)/$C$7))+($D$64-$C$64)*MAX(0,MIN(1,($F$63-$C$62/12-$C$63)/$D$7))+($E$64-$D$64)*MAX(0,MIN(1,($F$63-$C$62/12-$D$63)/$E$7))+($F$64-$E$64)*MAX(0,MIN(1,($F$63-$C$62/12-$E$63)/$F$7))+($G$64-$F$64)*MAX(0,MIN(1,($F$63-$C$62/12-$F$63)/$G$7))) -> 265.90339 | G65: =IF($C$62<=0,$G$64,0+($C$64-0)*MAX(0,MIN(1,($G$63-$C$62/12-0)/$C$7))+($D$64-$C$64)*MAX(0,MIN(1,($G$63-$C$62/12-$C$63)/$D$7))+($E$64-$D$64)*MAX(0,MIN(1,($G$63-$C$62/12-$D$63)/$E$7))+($F$64-$E$64)*MAX(0,MIN(1,($G$63-$C$62/12-$E$63)/$F$7))+($G$64-$F$64)*MAX(0,MIN(1,($G$63-$C$62/12-$F$63)/$G$7))) -> 307.48733 | I65: ＝上列往後平移建設延誤月數（線性內插）；延誤 0 時＝上列
A66: 本期投入使用的成長型 CapEx（折舊基礎） | B66: US$m | C66: =C65 -> 61.689512 | D66: =D65-C65 -> 94.577473 | E66: =E65-D65 -> 53.251404 | F66: =F65-E65 -> 56.385 | G66: =G65-F65 -> 41.583938 | I66: 車隊折舊自投入使用時點起算（『輸入與假設』期初毛 PP&E 與 D&A 引用此列）
A67: 閒置資本（已支出未產生收入，期末） | B67: US$m | C67: =C64-C65 -> 61.689512 | D67: =D64-D65 -> 10.962654 | E67: =E64-E65 -> 14.09625 | F67: =F64-F65 -> 14.09625 | G67: =G64-G65 -> 9.1625625 | I67: ＝原時程累計 − 已投入使用累計；延誤 0 時為 0。一頁摘要以一句呈現峰值
A68: 未起租租約起租連動比例（delayLink） | B68: % | C68: 0.5 | I68: 未起租租金中此比例的起租時點隨延誤月數後移（開發商交付晚），其餘照原時程（company.json → leases.uncommenced.delayLink）[Assumed]；替代 0／1
A69: 延誤罰則（應計費而未計費營收的 %） | B69: % | C69: 0 | I69: 公司未揭露合約條款：預設 0（不存在／未揭露）；敏感度 5%／10%（company.json → defaults.delayPenalty）[Assumed]
A70: 表外現金租金：全部隨延誤平移（對照） | B70: US$m | C70: =輸入與假設!$C$26/輸入與假設!$C$28/輸入與假設!$C$29/4*((MIN(MAX(0,輸入與假設!C$154-(輸入與假設!$C$27+運營_產能與收入!$C$62/3)),輸入與假設!$C$28)*(MIN(MAX(0,輸入與假設!C$154-(輸入與假設!$C$27+運營_產能與收入!$C$62/3)),輸入與假設!$C$28)+1)/2+輸入與假設!$C$28*MAX(0,MAX(0,輸入與假設!C$154-(輸入與假設!$C$27+運營_產能與收入!$C$62/3))-輸入與假設!$C$28))-(MIN(MAX(0,0-(輸入與假設!$C$27+運營_產能與收入!$C$62/3)),輸入與假設!$C$28)*(MIN(MAX(0,0-(輸入與假設!$C$27+運營_產能與收入!$C$62/3)),輸入與假設!$C$28)+1)/2+輸入與假設!$C$28*MAX(0,MAX(0,0-(輸入與假設!$C$27+運營_產能與收入!$C$62/3))-輸入與假設!$C$28))) -> 0 | D70: =輸入與假設!$C$26/輸入與假設!$C$28/輸入與假設!$C$29/4*((MIN(MAX(0,輸入與假設!D$154-(輸入與假設!$C$27+運營_產能與收入!$C$62/3)),輸入與假設!$C$28)*(MIN(MAX(0,輸入與假設!D$154-(輸入與假設!$C$27+運營_產能與收入!$C$62/3)),輸入與假設!$C$28)+1)/2+輸入與假設!$C$28*MAX(0,MAX(0,輸入與假設!D$154-(輸入與假設!$C$27+運營_產能與收入!$C$62/3))-輸入與假設!$C$28))-(MIN(MAX(0,輸入與假設!C$154-(輸入與假設!$C$27+運營_產能與收入!$C$62/3)),輸入與假設!$C$28)*(MIN(MAX(0,輸入與假設!C$154-(輸入與假設!$C$27+運營_產能與收入!$C$62/3)),輸入與假設!$C$28)+1)/2+輸入與假設!$C$28*MAX(0,MAX(0,輸入與假設!C$154-(輸入與假設!$C$27+運營_產能與收入!$C$62/3))-輸入與假設!$C$28))) -> 4.1279997 | E70: =輸入與假設!$C$26/輸入與假設!$C$28/輸入與假設!$C$29/4*((MIN(MAX(0,輸入與假設!E$154-(輸入與假設!$C$27+運營_產能與收入!$C$62/3)),輸入與假設!$C$28)*(MIN(MAX(0,輸入與假設!E$154-(輸入與假設!$C$27+運營_產能與收入!$C$62/3)),輸入與假設!$C$28)+1)/2+輸入與假設!$C$28*MAX(0,MAX(0,輸入與假設!E$154-(輸入與假設!$C$27+運營_產能與收入!$C$62/3))-輸入與假設!$C$28))-(MIN(MAX(0,輸入與假設!D$154-(輸入與假設!$C$27+運營_產能與收入!$C$62/3)),輸入與假設!$C$28)*(MIN(MAX(0,輸入與假設!D$154-(輸入與假設!$C$27+運營_產能與收入!$C$62/3)),輸入與假設!$C$28)+1)/2+輸入與假設!$C$28*MAX(0,MAX(0,輸入與假設!D$154-(輸入與假設!$C$27+運營_產能與收入!$C$62/3))-輸入與假設!$C$28))) -> 4.1279997 | F70: =輸入與假設!$C$26/輸入與假設!$C$28/輸入與假設!$C$29/4*((MIN(MAX(0,輸入與假設!F$154-(輸入與假設!$C$27+運營_產能與收入!$C$62/3)),輸入與假設!$C$28)*(MIN(MAX(0,輸入與假設!F$154-(輸入與假設!$C$27+運營_產能與收入!$C$62/3)),輸入與假設!$C$28)+1)/2+輸入與假設!$C$28*MAX(0,MAX(0,輸入與假設!F$154-(輸入與假設!$C$27+運營_產能與收入!$C$62/3))-輸入與假設!$C$28))-(MIN(MAX(0,輸入與假設!E$154-(輸入與假設!$C$27+運營_產能與收入!$C$62/3)),輸入與假設!$C$28)*(MIN(MAX(0,輸入與假設!E$154-(輸入與假設!$C$27+運營_產能與收入!$C$62/3)),輸入與假設!$C$28)+1)/2+輸入與假設!$C$28*MAX(0,MAX(0,輸入與假設!E$154-(輸入與假設!$C$27+運營_產能與收入!$C$62/3))-輸入與假設!$C$28))) -> 4.1279997 | G70: =輸入與假設!$C$26/輸入與假設!$C$28/輸入與假設!$C$29/4*((MIN(MAX(0,輸入與假設!G$154-(輸入與假設!$C$27+運營_產能與收入!$C$62/3)),輸入與假設!$C$28)*(MIN(MAX(0,輸入與假設!G$154-(輸入與假設!$C$27+運營_產能與收入!$C$62/3)),輸入與假設!$C$28)+1)/2+輸入與假設!$C$28*MAX(0,MAX(0,輸入與假設!G$154-(輸入與假設!$C$27+運營_產能與收入!$C$62/3))-輸入與假設!$C$28))-(MIN(MAX(0,輸入與假設!F$154-(輸入與假設!$C$27+運營_產能與收入!$C$62/3)),輸入與假設!$C$28)*(MIN(MAX(0,輸入與假設!F$154-(輸入與假設!$C$27+運營_產能與收入!$C$62/3)),輸入與假設!$C$28)+1)/2+輸入與假設!$C$28*MAX(0,MAX(0,輸入與假設!F$154-(輸入與假設!$C$27+運營_產能與收入!$C$62/3))-輸入與假設!$C$28))) -> 4.1279997 | I70: ＝未起租排程的起算季延後 延誤月數 ÷ 3 季（其餘同『輸入與假設』表外現金租金）
A71: 表外現金租金（未起租，延誤連動後） | B71: US$m | C71: =IF(OR(運營_產能與收入!$C$62<=0,運營_產能與收入!$C$68<=0),輸入與假設!C$155,(1-運營_產能與收入!$C$68)*輸入與假設!C$155+運營_產能與收入!$C$68*C70) -> 0.51599997 | D71: =IF(OR(運營_產能與收入!$C$62<=0,運營_產能與收入!$C$68<=0),輸入與假設!D$155,(1-運營_產能與收入!$C$68)*輸入與假設!D$155+運營_產能與收入!$C$68*D70) -> 4.1279997 | E71: =IF(OR(運營_產能與收入!$C$62<=0,運營_產能與收入!$C$68<=0),輸入與假設!E$155,(1-運營_產能與收入!$C$68)*輸入與假設!E$155+運營_產能與收入!$C$68*E70) -> 4.1279997 | F71: =IF(OR(運營_產能與收入!$C$62<=0,運營_產能與收入!$C$68<=0),輸入與假設!F$155,(1-運營_產能與收入!$C$68)*輸入與假設!F$155+運營_產能與收入!$C$68*F70) -> 4.1279997 | G71: =IF(OR(運營_產能與收入!$C$62<=0,運營_產能與收入!$C$68<=0),輸入與假設!G$155,(1-運營_產能與收入!$C$68)*輸入與假設!G$155+運營_產能與收入!$C$68*G70) -> 4.1279997 | I71: ＝(1 − 連動比例)× 原排程＋連動比例 × 平移後排程；延誤 0 時＝原排程（『各期收支』租金引用此列）
A72: 容量上限（未延誤，對照） | B72: US$m | C72: =IF(輸入與假設!$C$37=1,(輸入與假設!$C$36+C10)/2,C10)*輸入與假設!C$46*輸入與假設!$C$39*輸入與假設!C$45*C7 -> 59.3775 | D72: =IF(輸入與假設!$C$37=1,(C10+D10)/2,D10)*輸入與假設!D$46*輸入與假設!$C$39*輸入與假設!D$45*D7 -> 221.502 | E72: =IF(輸入與假設!$C$37=1,(D10+E10)/2,E10)*輸入與假設!E$46*輸入與假設!$C$39*輸入與假設!E$45*E7 -> 281.184 | F72: =IF(輸入與假設!$C$37=1,(E10+F10)/2,F10)*輸入與假設!F$46*輸入與假設!$C$39*輸入與假設!F$45*F7 -> 334.254 | G72: =IF(輸入與假設!$C$37=1,(F10+G10)/2,G10)*輸入與假設!G$46*輸入與假設!$C$39*輸入與假設!G$45*G7 -> 381.234 | I72: ＝未延誤的平均可計費 MW × 每 MW 年收入 × 利用率 × 期間長度
A73: 應計費而未計費營收（延誤造成） | B73: US$m | C73: =IF(運營_產能與收入!$C$62<=0,0,MAX(0,C72-C16)) -> 18.16125 | D73: =IF(運營_產能與收入!$C$62<=0,0,MAX(0,D72-D16)) -> 43.848 | E73: =IF(運營_產能與收入!$C$62<=0,0,MAX(0,E72-E16)) -> 14.9205 | F73: =IF(運營_產能與收入!$C$62<=0,0,MAX(0,F72-F16)) -> 13.2675 | G73: =IF(運營_產能與收入!$C$62<=0,0,MAX(0,G72-G16)) -> 11.745 | I73: ＝未延誤容量上限 − 延誤後容量上限
A74: 延誤罰則（營業費用） | B74: US$m | C74: =運營_產能與收入!$C$69*C73 -> 0 | D74: =運營_產能與收入!$C$69*D73 -> 0 | E74: =運營_產能與收入!$C$69*E73 -> 0 | F74: =運營_產能與收入!$C$69*F73 -> 0 | G74: =運營_產能與收入!$C$69*G73 -> 0 | I74: ＝罰則比例 × 應計費而未計費營收；扣 EBITDA、營運來源、稅基與債務上限。客戶預付不因延誤退還（已知限制）

Sheet 運營_站點
A1: 站點租賃 — 公司揭露 vs 季報總額（檢驗租金路徑用）
A2: 季報不揭露逐站租金；下表為具名站點（company.json → defaults.sites），有租約金額者用來檢驗『每 MW 年租金』與模型租金路徑是否一致
A4: 站點 | B4: 營運方 | C4: 契約 MW | D4: 已驗收 MW | E4: 合約總值 $m | F4: 年期 | G4: 年租金 $m | H4: 每 MW 年租金 $m | I4: 時程 | J4: 季報對應 | K4: 說明
A5: 冰島 Blönduós（第三方機房） | B5: 承租容量（雲端） | C5: 5.5 | D5: 5.5 | E5: 未揭露 | F5: 未揭露 | I5: 營運中 | J5: — | K5: 10-Q：已簽 5.5 MW-IT（6 毛 MW）；目前雲端營收主要來自冰島 [Interested-party]
A6: 安大略第三方機房（Baseten） | B6: 第三方機房、WhiteFiber GPU | C6: 2.858 | D6: 0 | E6: 未揭露 | F6: 未揭露 | I6: 2026-11 | J6: — | K6: 1,392 顆 B300 依 Tokenomics 換算 2.858 MW-IT；MW 未揭露 [Derived]
A7: 巴黎第三方機房 | B7: 第三方機房、專案層級融資（未完成） | C7: 1.84 | D7: 0 | E7: 未揭露 | F7: 未揭露 | I7: 2026-09-30 | J7: — | K7: GPU 數與 MW 未揭露；年額 >32 ÷ 17.40 推得 1.84 MW-IT [Derived]
A8: 雪梨第三方機房 | B8: 承租（WhiteFiber, Inc. 保證） | C8: 2.5 | D8: 0 | E8: 未揭露 | F8: 未揭露 | I8: 2026 Q4 | J8: — | K8: 10-Q：2.5 MW-IT、59 個月租約；客戶未揭露 [Interested-party]
A9: 加拿大（Prime Intellect VR200） | B9: 第三方機房 | C9: 1.974 | D9: 0 | E9: 未揭露 | F9: 未揭露 | I9: 2027 Q2 | J9: — | K9: 576 顆 VR200 依 Tokenomics 換算 1.974 MW-IT [Derived]
A10: 具名站點合計 | C10: =SUM(C5:C9) -> 14.672 | D10: =SUM(D5:D9) -> 5.5 | E10: =SUM(E5:E9) -> 0 | G10: =SUM(G5:G9) -> 0 | H10: =IF(I10>0,G10/I10,0) -> 0 | I10: =SUMPRODUCT(ISNUMBER(G5:G9)*C5:C9) -> 0 | K10: 加權每 MW 年租金＝具名站點的市場基準（I 欄＝有租約金額站點的契約 MW；沒有時為 0，不適用）
A12: 對帳：具名站點 vs 季報租賃承諾總額
A13: 季報在帳租賃（未折現，已起租） | E13: 20.435 | K13: company.json → leases.facts.onBal
A14: 季報未起租租賃（未折現） | E14: 20.296 | K14: company.json → leases.facts.notCommenced
A15: 季報單站按造價計租上限 | E15: 0 | K15: company.json → leases.facts.singleCap（無則 0）
A16: 季報已揭露租賃承諾合計 | E16: =SUM(E13:E15) -> 40.731 | K16: 未折現金額
A17: 減：具名站點合約總值 | E17: =-E10 -> 0
A18: ＝ 未具名站點（殘差） | E18: =E16+E17 -> 40.731 | K18: 未具名站點；公司不揭露逐站租金，殘差大是必然
A19: 殘差占季報總額 | E19: =IF(E16<>0,E18/E16,0) -> 1
A21: 檢驗：模型租金路徑 ÷ 在役 MW vs 市場基準
A22: 項目 | B22: 單位 | C22: FY26 | D22: FY27 | E22: FY28 | F22: FY29 | G22: FY30
A23: 模型租金（在帳＋表外） | B23: US$m | C23: =各期收支!C17 -> 11.817085 | D23: =各期收支!D17 -> 46.250479 | E23: =各期收支!E17 -> 57.48796 | F23: =各期收支!F17 -> 72.011644 | G23: =各期收支!G17 -> 84.180508
A24: 平均在役 MW（已連網） | B24: MW | C24: =(輸入與假設!C$160+輸入與假設!C$43)/2 -> 10.037 | D24: =(輸入與假設!D$160+輸入與假設!D$43)/2 -> 15.561 | E24: =(輸入與假設!E$160+輸入與假設!E$43)/2 -> 18.048 | F24: =(輸入與假設!F$160+輸入與假設!F$43)/2 -> 21.048 | G24: =(輸入與假設!G$160+輸入與假設!G$43)/2 -> 24.048
A25: 模型期長度（年） | B25: 年 | C25: =輸入與假設!C$41 -> 0.5 | D25: =輸入與假設!D$41 -> 1 | E25: =輸入與假設!E$41 -> 1 | F25: =輸入與假設!F$41 -> 1 | G25: =輸入與假設!G$41 -> 1
A26: 模型每 MW 年租金 | B26: US$m/MW | C26: =C23/C25/C24 -> 2.3547046 | D26: =D23/D25/D24 -> 2.9722048 | E26: =E23/E25/E24 -> 3.1852815 | F26: =F23/F25/F24 -> 3.4213058 | G26: =G23/G25/G24 -> 3.5005201 | K26: FY26 欄只含下半年租金、MW 取全期平均，略有低估
A27: 第三方租賃占比 | C27: 1 | K27: 其餘為自建，成本走 CapEx（company.json → leases.facts.share）[Assumed]
A28: 基準租金（MW×市場基準×占比） | B28: US$m | C28: =C24*運營_站點!$H$10*$C$27*C25 -> 0 | D28: =D24*運營_站點!$H$10*$C$27*D25 -> 0 | E28: =E24*運營_站點!$H$10*$C$27*E25 -> 0 | F28: =F24*運營_站點!$H$10*$C$27*F25 -> 0 | G28: =G24*運營_站點!$H$10*$C$27*G25 -> 0 | K28: 具名站點有租約金額時才有意義；否則為 0
A29: 差額（基準 − 模型） | B29: US$m | C29: =C28-C23 -> -11.817085 | D29: =D28-D23 -> -46.250479 | E29: =E28-E23 -> -57.48796 | F29: =F28-F23 -> -72.011644 | G29: =G28-G23 -> -84.180508 | K29: 正值＝模型租金可能低估的金額
A30: 五期差額合計 | C30: =SUM(C29:G29) -> -271.74768

Sheet 資產負債_既有債務
A1: 債務明細 — 季報（2026-06-30）逐筆＋存量利息推導
A2: 有效利率為現金票息口徑（可轉債＝票息 ÷ 到期累積倍數，本金以到期累積本金計）。本頁算出的存量利息連回『輸入』頁，再進入支出與資金頁
A4: 工具 | B4: 類別 | C4: 到期 | D4: 有效利率 | E4: 6/30 本金 | F4: 年化利息 | I4: 備註
A5: Bit Digital DDTL（含 B. Riley 持有票據） | B5: 擔保（NC-1 Topco 股權） | C5: 2027-03 | D5: 0.095 | E5: 80 | F5: =D5*E5 -> 7.6 | I5: 已動用 80（6/30 50＋7/27、7/31 共 30）；票面 9.5%（NC-1 完工且 ≥80% 出租後 8.0%）；另有 1.1× MOIC，以 debt.extraCost 加付計入融資成本；到期假設 2027-03（可動用期 9 個月，由 NC-1 專案融資或再融資償還）[Interested-party／Assumed]
A6: Landsbankinn 冰島擔保定期貸款 | B6: 擔保（冰島子公司股權與 GPU） | C6: 2028-06 | D6: 0.0792 | E6: 18 | F6: =D6*E6 -> 1.4256 | I6: SOFR＋4.25%（6/30 票面 7.92%、有效 10.64%）；2 年、季攤還（流動 9.0）[Interested-party]
A7: RBC 聯貸（Enovum，不可循環） | B7: 擔保（MTL-2／MTL-3 不動產） | C7: 2029-07 | D7: 0.055 | E7: 26.2 | F7: =D7*E7 -> 1.441 | I7: 2026-07-15 動用 CAD 36.8（10-Q 換算 USD 26.2；匯率依 10-Q 附註 19）並全額再融資 RBC 17.339；首次動用起 3 年、15 年攤還季付；利率 CORRA＋2.45%＋CSA，以 5.5% 計 [Interested-party／Assumed 區間 5.0–6.5%]
A8: 合計（6/30） | E8: =SUM(E5:E7) -> 124.2 | F8: =SUM(F5:F7) -> 10.4666 | I8: 應等於最新季報本金合計 315.339（company.json → latestQuarter.debtPrincipal）
A9: 加權有效利率 | D9: =F8/E8 -> 0.084272142 | I9: ＝年化利息 ÷ 本金（company.json → debt.instruments 的有效利率）
A11: 評價日後新發可轉債 | D11: 0 | E11: 0 | F11: =D11*E11 -> 0 | I11: company.json → debt.convertible（期後新發；不在五期還本表內，只計利息）
A13: 可轉債逐檔（若轉換法：有效轉換價 < 判斷價 → 視為轉股，不計利息與還本）
A14: 可轉債 | B14: 到期 | C14: 票息 | D14: 原始本金 | E14: 到期累積倍數 | F14: 轉換價 | G14: 到期所屬模型期 | H14: 強制轉換（1＝是） | I14: 備註
A15: 4.50% 2031 可轉債（交換後剩餘） | B15: 2031-02 | C15: 0.045 | D15: 31.85 | E15: 1 | F15: 25.91 | G15: 5 | H15: 0 | I15: 原始 230（2026-01）；2026-08 以現金約 118.5＋約 6.3M 股交換 198.15，剩 31.85；轉換價 25.91（38.5981 股／千元）；2029-02 起可賣回／可贖回 [Interested-party]
A16: 5.00% 2032 可轉債（2026-08） | B16: 2032-09 | C16: 0.05 | D16: 310 | E16: 1 | F16: 33.84 | G16: 5 | H16: 0 | I16: 310（含超額配售 40）；轉換價 33.84（29.5530 股／千元，9.161M 股）；2030-09-06 起可賣回／可贖回；無上限買權（8-K 與新聞稿未提）；淨收入 298.5 [Interested-party 8-K]
I17: 到期所屬模型期：0＝首期 … 4＝末期、5＝模型期後（建置時依期末日推算）
A19: 可轉債（推導） | C19: 到期本金 | D19: 若轉換股數 | E19: 有效轉換價 | F19: 融資分類 | G19: 評價第一輪 | H19: 評價第二輪 | I19: 說明
A20: =A15 -> 4.50% 2031 可轉債（交換後剩餘） | C20: =D15*E15 -> 31.85 | D20: =D15/F15 -> 1.2292551 | E20: =F15*E15 -> 25.91 | F20: =IF(OR(H15=1,E20<輸入與假設!$C$205),1,0) -> 0 | G20: =IF(OR(H15=1,E20<輸入與假設!$C$228),1,0) -> 0 | H20: =IF(OR(H15=1,E20<評價_DCF與目標價!$C$66),1,0) -> 0
A21: =A16 -> 5.00% 2032 可轉債（2026-08） | C21: =D16*E16 -> 310 | D21: =D16/F16 -> 9.1607565 | E21: =F16*E16 -> 33.84 | F21: =IF(OR(H16=1,E21<輸入與假設!$C$205),1,0) -> 0 | G21: =IF(OR(H16=1,E21<輸入與假設!$C$228),1,0) -> 0 | H21: =IF(OR(H16=1,E21<評價_DCF與目標價!$C$66),1,0) -> 0
A22: 合計 | C22: =SUM(C20:C21) -> 341.85 | D22: =SUM(D20:D21) -> 10.390012 | I22: 分類 1＝轉股（若轉換法）、0＝債務。強制轉換者一律為 1。融資分類判斷價＝股權發行價；評價第一輪＝現價；第二輪＝MIN(現價, 第一輪加權目標價)
A24: 存量利息推導（本金依季報到期表遞減）
A25: 項目 | B25: 單位 | C25: FY26 | D25: FY27 | E25: FY28 | F25: FY29 | G25: FY30 | I25: 公式／來源說明
A26: 期初本金 | B26: US$m | C26: =E8 -> 124.2 | D26: =C28 -> 118.827 | E26: =D28 -> 28.08 | F26: =E28 -> 21.833 | G26: =F28 -> 0.874 | I26: FY26 期初為 6/30 本金（模型期起點）
A27: 排程還本 | B27: US$m | C27: =輸入與假設!C$223 -> 5.373 | D27: =輸入與假設!D$223 -> 90.747 | E27: =輸入與假設!E$223 -> 6.247 | F27: =輸入與假設!F$223 -> 20.959 | G27: =輸入與假設!G$223 -> 0 | I27: 季報到期表
A28: 期末本金 | B28: US$m | C28: =C26-C27 -> 118.827 | D28: =D26-D27 -> 28.08 | E28: =E26-E27 -> 21.833 | F28: =F26-F27 -> 0.874 | G28: =G26-G27 -> 0.874
A29: 平均本金 | B29: US$m | C29: =(C26+C28)/2 -> 121.5135 | D29: =(D26+D28)/2 -> 73.4535 | E29: =(E26+E28)/2 -> 24.9565 | F29: =(F26+F28)/2 -> 11.3535 | G29: =(G26+G28)/2 -> 0.874
A30: 存量債務利息 | B30: US$m | C30: =C29*資產負債_既有債務!$D$9*輸入與假設!C$41 -> 5.1201014 | D30: =D29*資產負債_既有債務!$D$9*輸入與假設!D$41 -> 6.1900838 | E30: =E29*資產負債_既有債務!$D$9*輸入與假設!E$41 -> 2.1031377 | F30: =F29*資產負債_既有債務!$D$9*輸入與假設!F$41 -> 0.95678376 | G30: =G29*資產負債_既有債務!$D$9*輸入與假設!G$41 -> 0.073653852 | I30: ＝平均本金×加權有效利率×期間長度。限制：假設利率組合不變；可轉債折價攤銷（非現金）不計
A31: 期後新發可轉債利息 | B31: US$m | C31: =資產負債_既有債務!$F$11*輸入與假設!C$41 -> 0 | D31: =資產負債_既有債務!$F$11*輸入與假設!D$41 -> 0 | E31: =資產負債_既有債務!$F$11*輸入與假設!E$41 -> 0 | F31: =資產負債_既有債務!$F$11*輸入與假設!F$41 -> 0 | G31: =資產負債_既有債務!$F$11*輸入與假設!G$41 -> 0
A32: 可轉債到期還本（債務處理） | B32: US$m | C32: =IF(輸入與假設!$C$197=1,SUMPRODUCT((1-資產負債_既有債務!$F$20:$F$21)*資產負債_既有債務!$C$20:$C$21*(資產負債_既有債務!$G$15:$G$16=0)),0) -> 0 | D32: =IF(輸入與假設!$C$197=1,SUMPRODUCT((1-資產負債_既有債務!$F$20:$F$21)*資產負債_既有債務!$C$20:$C$21*(資產負債_既有債務!$G$15:$G$16=1)),0) -> 0 | E32: =IF(輸入與假設!$C$197=1,SUMPRODUCT((1-資產負債_既有債務!$F$20:$F$21)*資產負債_既有債務!$C$20:$C$21*(資產負債_既有債務!$G$15:$G$16=2)),0) -> 0 | F32: =IF(輸入與假設!$C$197=1,SUMPRODUCT((1-資產負債_既有債務!$F$20:$F$21)*資產負債_既有債務!$C$20:$C$21*(資產負債_既有債務!$G$15:$G$16=3)),0) -> 0 | G32: =IF(輸入與假設!$C$197=1,SUMPRODUCT((1-資產負債_既有債務!$F$20:$F$21)*資產負債_既有債務!$C$20:$C$21*(資產負債_既有債務!$G$15:$G$16=4)),0) -> 0 | I32: 融資分類為債務的可轉債，到期當期以到期累積本金現金還本
A33: 可轉債期末餘額（債務處理） | B33: US$m | C33: =IF(輸入與假設!$C$197=1,SUMPRODUCT((1-資產負債_既有債務!$F$20:$F$21)*資產負債_既有債務!$C$20:$C$21*(資產負債_既有債務!$G$15:$G$16>0)),SUMPRODUCT((1-資產負債_既有債務!$F$20:$F$21)*資產負債_既有債務!$C$20:$C$21)) -> 341.85 | D33: =IF(輸入與假設!$C$197=1,SUMPRODUCT((1-資產負債_既有債務!$F$20:$F$21)*資產負債_既有債務!$C$20:$C$21*(資產負債_既有債務!$G$15:$G$16>1)),SUMPRODUCT((1-資產負債_既有債務!$F$20:$F$21)*資產負債_既有債務!$C$20:$C$21)) -> 341.85 | E33: =IF(輸入與假設!$C$197=1,SUMPRODUCT((1-資產負債_既有債務!$F$20:$F$21)*資產負債_既有債務!$C$20:$C$21*(資產負債_既有債務!$G$15:$G$16>2)),SUMPRODUCT((1-資產負債_既有債務!$F$20:$F$21)*資產負債_既有債務!$C$20:$C$21)) -> 341.85 | F33: =IF(輸入與假設!$C$197=1,SUMPRODUCT((1-資產負債_既有債務!$F$20:$F$21)*資產負債_既有債務!$C$20:$C$21*(資產負債_既有債務!$G$15:$G$16>3)),SUMPRODUCT((1-資產負債_既有債務!$F$20:$F$21)*資產負債_既有債務!$C$20:$C$21)) -> 341.85 | G33: =IF(輸入與假設!$C$197=1,SUMPRODUCT((1-資產負債_既有債務!$F$20:$F$21)*資產負債_既有債務!$C$20:$C$21*(資產負債_既有債務!$G$15:$G$16>4)),SUMPRODUCT((1-資產負債_既有債務!$F$20:$F$21)*資產負債_既有債務!$C$20:$C$21)) -> 341.85 | I33: 到期累積本金；關閉攤還時維持全額
A34: 可轉債票息（債務處理） | B34: US$m | C34: =IF(輸入與假設!$C$197=1,SUMPRODUCT((1-資產負債_既有債務!$F$20:$F$21)*資產負債_既有債務!$D$15:$D$16*資產負債_既有債務!$C$15:$C$16*((資產負債_既有債務!$G$15:$G$16>0)+0.5*(資產負債_既有債務!$G$15:$G$16=0))),SUMPRODUCT((1-資產負債_既有債務!$F$20:$F$21)*資產負債_既有債務!$D$15:$D$16*資產負債_既有債務!$C$15:$C$16))*輸入與假設!C$41 -> 8.466625 | D34: =IF(輸入與假設!$C$197=1,SUMPRODUCT((1-資產負債_既有債務!$F$20:$F$21)*資產負債_既有債務!$D$15:$D$16*資產負債_既有債務!$C$15:$C$16*((資產負債_既有債務!$G$15:$G$16>1)+0.5*(資產負債_既有債務!$G$15:$G$16=1))),SUMPRODUCT((1-資產負債_既有債務!$F$20:$F$21)*資產負債_既有債務!$D$15:$D$16*資產負債_既有債務!$C$15:$C$16))*輸入與假設!D$41 -> 16.93325 | E34: =IF(輸入與假設!$C$197=1,SUMPRODUCT((1-資產負債_既有債務!$F$20:$F$21)*資產負債_既有債務!$D$15:$D$16*資產負債_既有債務!$C$15:$C$16*((資產負債_既有債務!$G$15:$G$16>2)+0.5*(資產負債_既有債務!$G$15:$G$16=2))),SUMPRODUCT((1-資產負債_既有債務!$F$20:$F$21)*資產負債_既有債務!$D$15:$D$16*資產負債_既有債務!$C$15:$C$16))*輸入與假設!E$41 -> 16.93325 | F34: =IF(輸入與假設!$C$197=1,SUMPRODUCT((1-資產負債_既有債務!$F$20:$F$21)*資產負債_既有債務!$D$15:$D$16*資產負債_既有債務!$C$15:$C$16*((資產負債_既有債務!$G$15:$G$16>3)+0.5*(資產負債_既有債務!$G$15:$G$16=3))),SUMPRODUCT((1-資產負債_既有債務!$F$20:$F$21)*資產負債_既有債務!$D$15:$D$16*資產負債_既有債務!$C$15:$C$16))*輸入與假設!F$41 -> 16.93325 | G34: =IF(輸入與假設!$C$197=1,SUMPRODUCT((1-資產負債_既有債務!$F$20:$F$21)*資產負債_既有債務!$D$15:$D$16*資產負債_既有債務!$C$15:$C$16*((資產負債_既有債務!$G$15:$G$16>4)+0.5*(資產負債_既有債務!$G$15:$G$16=4))),SUMPRODUCT((1-資產負債_既有債務!$F$20:$F$21)*資產負債_既有債務!$D$15:$D$16*資產負債_既有債務!$C$15:$C$16))*輸入與假設!G$41 -> 16.93325 | I34: ＝原始本金 × 票息 × 期間長度；到期當期計半期
A35: FY26 新增借款利息校準 | B35: US$m | C35: =0 -> 0 | D35: =0 -> 0 | E35: =0 -> 0 | F35: =0 -> 0 | G35: =0 -> 0 | I35: 讓首期模型利息對上公司季度利息指引的校準值（company.json → defaults.intCal）；無指引時為 0
A36: 額外融資成本｜DDTL 1.1× MOIC 到期加付 | B36: US$m | C36: =0 -> 0 | D36: =1.9 -> 1.9 | E36: =0 -> 0 | F36: =0 -> 0 | G36: =0 -> 0 | I36: MOIC：到期時貸方累計收款至少為本金 1.1 倍＝8.0；評價日後至假設到期 2027-03 的票息約 6.1（50 × 9.5% × 0.75 年＋30 × 9.5% × 約 0.67 年）→ 到期加付約 1.9，列為 FY27 融資成本（非經常利息；審查留言第 2 條）[Derived]；WACC 稅前債務成本仍 9.5%
A37: 存量利息合計（連回輸入頁） | B37: US$m | C37: =C30+C31+C34+C35+C36+C45 -> 13.586726 | D37: =D30+D31+D34+D35+D36+D45 -> 51.128959 | E37: =E30+E31+E34+E35+E36+E45 -> 43.836731 | F37: =F30+F31+F34+F35+F36+F45 -> 40.079815 | G37: =G30+G31+G34+G35+G36+G45 -> 36.586123 | I37: ＝存量債務利息＋期後新發可轉債利息＋可轉債票息＋首期校準＋額外融資成本＋NC-1 專案貸款利息（v0.1c）
A39: NC-1 專案貸款（排程：動用期期初一次動用 × 自有利率 × 次期起直線攤還；WhiteFiber v0.1c）
A40: 項目 | B40: 單位 | C40: FY26 | D40: FY27 | E40: FY28 | F40: FY29 | G40: FY30 | I40: 公式／來源說明
A41: 專案貸款期初餘額 | B41: US$m | C41: =0 -> 0 | D41: =C44 -> 0 | E41: =D44 -> 307.125 | F41: =E44 -> 276.4125 | G41: =F44 -> 245.7
A42: 專案貸款動用 | B42: US$m | C42: =IF(輸入與假設!$C$194=0,輸入與假設!$C$193,0) -> 0 | D42: =IF(輸入與假設!$C$194=1,輸入與假設!$C$193,0) -> 307.125 | E42: =IF(輸入與假設!$C$194=2,輸入與假設!$C$193,0) -> 0 | F42: =IF(輸入與假設!$C$194=3,輸入與假設!$C$193,0) -> 0 | G42: =IF(輸入與假設!$C$194=4,輸入與假設!$C$193,0) -> 0 | I42: ＝NC-1 專案貸款金額（『輸入與假設』E 區），於動用期期初一次到位
A43: 專案貸款攤還 | B43: US$m | C43: =IF(輸入與假設!$C$194<0,MIN(C41,輸入與假設!$C$193/輸入與假設!$C$196*輸入與假設!C$41),0) -> 0 | D43: =IF(輸入與假設!$C$194<1,MIN(D41,輸入與假設!$C$193/輸入與假設!$C$196*輸入與假設!D$41),0) -> 0 | E43: =IF(輸入與假設!$C$194<2,MIN(E41,輸入與假設!$C$193/輸入與假設!$C$196*輸入與假設!E$41),0) -> 30.7125 | F43: =IF(輸入與假設!$C$194<3,MIN(F41,輸入與假設!$C$193/輸入與假設!$C$196*輸入與假設!F$41),0) -> 30.7125 | G43: =IF(輸入與假設!$C$194<4,MIN(G41,輸入與假設!$C$193/輸入與假設!$C$196*輸入與假設!G$41),0) -> 30.7125 | I43: ＝金額 ÷ 攤還年數 × 期間長度（動用次期起；不超過期初餘額）
A44: 專案貸款期末餘額 | B44: US$m | C44: =C41+C42-C43 -> 0 | D44: =D41+D42-D43 -> 307.125 | E44: =E41+E42-E43 -> 276.4125 | F44: =F41+F42-F43 -> 245.7 | G44: =G41+G42-G43 -> 214.9875
A45: 專案貸款利息 | B45: US$m | C45: =輸入與假設!$C$195*(C41+C42+C44)/2*輸入與假設!C$41 -> 0 | D45: =輸入與假設!$C$195*(D41+D42+D44)/2*輸入與假設!D$41 -> 26.105625 | E45: =輸入與假設!$C$195*(E41+E42+E44)/2*輸入與假設!E$41 -> 24.800344 | F45: =輸入與假設!$C$195*(F41+F42+F44)/2*輸入與假設!F$41 -> 22.189781 | G45: =輸入與假設!$C$195*(G41+G42+G44)/2*輸入與假設!G$41 -> 19.579219 | I45: ＝利率 ×(期初＋動用＋期末)÷ 2 × 期間長度（動用當期全期計息）；併入存量利息合計

Sheet 資產負債_新債與新股
A1: 新債與新股（類資產負債表：現金、債務、股本、槓桿）
A2: 全部為連結公式。FY26 欄的現金自 2026-06-30 起算（模型期），與 HTML『資產與負債 → 新債與新股』同口徑
A4: 項目 | B4: 單位 | C4: FY26 | D4: FY27 | E4: FY28 | F4: FY29 | G4: FY30 | I4: 公式／來源說明
A5: 現金
A6: 期初現金 | B6: US$m | C6: =輸入與假設!$C$185 -> 56.056 | D6: =各期收支!C54 -> 136.21658 | E6: =各期收支!D54 -> 30 | F6: =各期收支!E54 -> 30 | G6: =各期收支!F54 -> 30 | I6: FY26＝6/30 現金（模型期起點）
A7: 營運收支淨額（含期後股權／可轉債，不含瀑布） | B7: US$m | C7: =各期收支!C97-輸入與假設!$C$185 -> 80.160575 | D7: =各期收支!D97-各期收支!C97 -> -474.62496 | E7: =各期收支!E97-各期收支!D97 -> -64.780604 | F7: =各期收支!F97-各期收支!E97 -> -17.058689 | G7: =各期收支!G97-各期收支!F97 -> -13.780859 | I7: ＝融資前累積現金的當期變動；負值即當期外部資金需求
A8: ＋ 瀑布：新債（額度＋資產層） | B8: US$m | C8: =各期收支!C80 -> 0 | D8: =各期收支!D80 -> 20 | E8: =各期收支!E80 -> 22.193297 | F8: =各期收支!F80 -> 28.63192 | G8: =各期收支!G80 -> 28.015568
A9: ＋ 瀑布：可轉債 | B9: US$m | C9: =各期收支!C83 -> 0 | D9: =各期收支!D83 -> 45.456196 | E9: =各期收支!E83 -> 51.440505 | F9: =各期收支!F83 -> 0 | G9: =各期收支!G83 -> 0
A10: ＋ 瀑布：高息債 | B10: US$m | C10: =各期收支!C87 -> 0 | D10: =各期收支!D87 -> 0 | E10: =各期收支!E87 -> 0 | F10: =各期收支!F87 -> 0 | G10: =各期收支!G87 -> 0
A11: ＋ 瀑布：股權募資 | B11: US$m | C11: =各期收支!C86 -> 0 | D11: =各期收支!D86 -> 0 | E11: =各期收支!E86 -> 0 | F11: =各期收支!F86 -> 0 | G11: =各期收支!G86 -> 0
A12: ＋ NC-1 專案貸款動用 | B12: US$m | C12: =各期收支!C44 -> 0 | D12: =各期收支!D44 -> 307.125 | E12: =各期收支!E44 -> 0 | F12: =各期收支!F44 -> 0 | G12: =各期收支!G44 -> 0
A13: − 新融資利息（新債＋可轉債＋高息債） | B13: US$m | C13: =-各期收支!C88 -> 0 | D13: =-各期收支!D88 -> -4.1728098 | E13: =-各期收支!E88 -> -8.8531983 | F13: =-各期收支!F88 -> -11.573231 | G13: =-各期收支!G88 -> -14.23471
A14: 期末現金 | B14: US$m | C14: =SUM(C6:C13) -> 136.21658 | D14: =SUM(D6:D13) -> 30 | E14: =SUM(E6:E13) -> 30 | F14: =SUM(F6:F13) -> 30 | G14: =SUM(G6:G13) -> 30 | I14: 應等於『各期收支』期末累積現金（見下列驗算）
A15: 驗算：與各期收支期末現金差異 | B15: US$m | C15: =C14-各期收支!C54 -> 0 | D15: =D14-各期收支!D54 -> 0 | E15: =E14-各期收支!E54 -> 0 | F15: =F14-各期收支!F54 -> 0 | G15: =G14-各期收支!G54 -> 0 | I15: 應為 0
A16: 債務
A17: 既有債務期初（季報本金） | B17: US$m | C17: =資產負債_既有債務!$E$8+SUMPRODUCT((1-資產負債_既有債務!$F$20:$F$21)*資產負債_既有債務!$C$20:$C$21) -> 466.05 | D17: =C20 -> 460.677 | E17: =D20 -> 677.055 | F17: =E20 -> 640.0955 | G17: =F20 -> 588.424 | I17: FY26＝其他借款＋債務處理可轉債到期本金（轉股處理者不列）
A18: − 排程還本（模型期） | B18: US$m | C18: =-IF(輸入與假設!$C$197=1,輸入與假設!C$223,0)-資產負債_既有債務!C32 -> -5.373 | D18: =-IF(輸入與假設!$C$197=1,輸入與假設!D$223,0)-資產負債_既有債務!D32 -> -90.747 | E18: =-IF(輸入與假設!$C$197=1,輸入與假設!E$223,0)-資產負債_既有債務!E32 -> -6.247 | F18: =-IF(輸入與假設!$C$197=1,輸入與假設!F$223,0)-資產負債_既有債務!F32 -> -20.959 | G18: =-IF(輸入與假設!$C$197=1,輸入與假設!G$223,0)-資產負債_既有債務!G32 -> 0
A19: ＋ NC-1 專案貸款動用 − 攤還 | B19: US$m | C19: =資產負債_既有債務!C42-資產負債_既有債務!C43 -> 0 | D19: =資產負債_既有債務!D42-資產負債_既有債務!D43 -> 307.125 | E19: =資產負債_既有債務!E42-資產負債_既有債務!E43 -> -30.7125 | F19: =資產負債_既有債務!F42-資產負債_既有債務!F43 -> -30.7125 | G19: =資產負債_既有債務!G42-資產負債_既有債務!G43 -> -30.7125 | I19: 排程貸款（WhiteFiber v0.1c）
A20: 既有債務期末 | B20: US$m | C20: =各期收支!C76-0 -> 460.677 | D20: =各期收支!D76-0 -> 677.055 | E20: =各期收支!E76-0 -> 640.0955 | F20: =各期收支!F76-0 -> 588.424 | G20: =各期收支!G76-0 -> 557.7115 | I20: ＝依到期表遞減（關閉攤還時維持期初）；含 NC-1 專案貸款餘額
A21: ＋ 期後新發可轉債 | B21: US$m | C21: =0 -> 0 | D21: =0 -> 0 | E21: =0 -> 0 | F21: =0 -> 0 | G21: =0 -> 0
A22: ＋ 瀑布新債餘額 | B22: US$m | C22: =各期收支!C92 -> 0 | D22: =各期收支!D92 -> 20 | E22: =各期收支!E92 -> 42.193297 | F22: =各期收支!F92 -> 70.825218 | G22: =各期收支!G92 -> 98.840786
A23: ＋ 瀑布可轉債餘額 | B23: US$m | C23: =各期收支!C95 -> 0 | D23: =各期收支!D95 -> 45.456196 | E23: =各期收支!E95 -> 96.896701 | F23: =各期收支!F95 -> 96.896701 | G23: =各期收支!G95 -> 96.896701
A24: ＋ 高息債餘額 | B24: US$m | C24: =各期收支!C94 -> 0 | D24: =各期收支!D94 -> 0 | E24: =各期收支!E94 -> 0 | F24: =各期收支!F94 -> 0 | G24: =各期收支!G94 -> 0
A25: 總債務 | B25: US$m | C25: =SUM(C20:C24) -> 460.677 | D25: =SUM(D20:D24) -> 742.5112 | E25: =SUM(E20:E24) -> 779.1855 | F25: =SUM(F20:F24) -> 756.14592 | G25: =SUM(G20:G24) -> 753.44899 | I25: 應等於『各期收支』期末總債務
A26: 淨負債（總債務 − 期末現金） | B26: US$m | C26: =C25-C14 -> 324.46042 | D26: =D25-D14 -> 712.5112 | E26: =E25-E14 -> 749.1855 | F26: =F25-F14 -> 726.14592 | G26: =G25-G14 -> 723.44899
A27: 股本
A28: 基礎股數（含 ATM 上限、SBC 稀釋） | B28: m | C28: =損益!C23 -> 39.33849 | D28: =損益!D23 -> 39.731875 | E28: =損益!E23 -> 40.129194 | F28: =損益!F23 -> 40.530486 | G28: =損益!G23 -> 40.93579
A29: ＋ 本期新股 | B29: m | C29: =各期收支!C90 -> 0 | D29: =各期收支!D90 -> 0 | E29: =各期收支!E90 -> 0 | F29: =各期收支!F90 -> 0 | G29: =各期收支!G90 -> 0
A30: 總股數（期末） | B30: m | C30: =損益!C24 -> 39.33849 | D30: =損益!D24 -> 39.731875 | E30: =損益!E24 -> 40.129194 | F30: =損益!F24 -> 40.530486 | G30: =損益!G24 -> 40.93579 | I30: ＝基礎股數＋累計新股
A31: 槓桿
A32: 期末 backlog | B32: US$m | C32: =各期收支!C75 -> 151.46514 | D32: =各期收支!D75 -> 259.47586 | E32: =各期收支!E75 -> 358.00769 | F32: =各期收支!F75 -> 231.98525 | G32: =各期收支!G75 -> 8.00375
A33: 債務上限（債務／backlog × 期末 backlog） | B33: US$m | C33: =各期收支!C77 -> 62.12729 | D33: =各期收支!D77 -> 127.02392 | E33: =各期收支!E77 -> 451.33249 | F33: =各期收支!F77 -> 737.30115 | G33: =各期收支!G77 -> 1049.1883
A34: 總債務 ÷ 期末 backlog | B34: x | C34: =C25/MAX(10,C32) -> 3.0414722 | D34: =D25/MAX(10,D32) -> 2.861581 | E34: =E25/MAX(10,E32) -> 2.176449 | F34: =F25/MAX(10,F32) -> 3.2594569 | G34: =G25/MAX(10,G32) -> 75.344899 | I34: 高息債不受 backlog 上限約束
A35: 總債務 ÷ EBITDA（年化） | B35: x | C35: =C25/MAX(10,損益!C22/輸入與假設!C$41) -> 37.075253 | D35: =D25/MAX(10,損益!D22/輸入與假設!D$41) -> 29.22722 | E35: =E25/MAX(10,損益!E22/輸入與假設!E$41) -> 8.6320563 | F35: =F25/MAX(10,損益!F22/輸入與假設!F$41) -> 5.1277956 | G35: =G25/MAX(10,損益!G22/輸入與假設!G$41) -> 3.5906279 | I35: FY26 模型期 EBITDA 以半年×2 年化
A36: 租賃負債（期末） | B36: US$m | C36: =各期收支!C61 -> 21.657314 | D36: =各期收支!D61 -> 23.748097 | E36: =各期收支!E61 -> 18.89958 | F36: =各期收支!F61 -> 13.816186 | G36: =各期收支!G61 -> 8.2546728 | I36: 見『各期收支』租賃負債（期末剩餘租金現值，5.7%）
A37: EBITDAR（年化＝(EBITDA＋租金) ÷ 期間長度） | B37: US$m | C37: =(損益!C22+各期收支!C17)/輸入與假設!C$41 -> 36.059628 | D37: =(損益!D22+各期收支!D17)/輸入與假設!D$41 -> 71.655262 | E37: =(損益!E22+各期收支!E17)/輸入與假設!E$41 -> 147.75446 | F37: =(損益!F22+各期收支!F17)/輸入與假設!F$41 -> 219.47187 | G37: =(損益!G22+各期收支!G17)/輸入與假設!G$41 -> 294.01818
A38: 調整後槓桿（(總債務＋租賃負債) ÷ EBITDAR） | B38: x | C38: =(C25+C36)/MAX(10,C37) -> 13.37602 | D38: =(D25+D36)/MAX(10,D37) -> 10.693692 | E38: =(E25+E36)/MAX(10,E37) -> 5.4014281 | F38: =(F25+F36)/MAX(10,F37) -> 3.5082496 | G38: =(G25+G36)/MAX(10,G37) -> 2.5906686 | I38: S&P 降評門檻 >4.5×（[Interested-party] 二手轉述）；S&P 自身口徑另含全部未起租承諾與無條件採購義務，較本列高（見報告）
A39: 距債務上限的空間（上限 − 調整後槓桿） | B39: x | C39: =輸入與假設!$C$200-C38 -> -8.3760203 | D39: =輸入與假設!$C$200-D38 -> -5.6936919 | E39: =輸入與假設!$C$200-E38 -> -0.40142805 | F39: =輸入與假設!$C$200-F38 -> 1.4917504 | G39: =輸入與假設!$C$200-G38 -> 2.4093314 | I39: 負值＝超過上限：需股權或高息債
A40: 總債務 ÷ EBITDA（年化） | B40: x | C40: =C25/MAX(10,C37-各期收支!C17/運營_產能與收入!C7) -> 37.075253 | D40: =D25/MAX(10,D37-各期收支!D17/運營_產能與收入!D7) -> 29.22722 | E40: =E25/MAX(10,E37-各期收支!E17/運營_產能與收入!E7) -> 8.6320563 | F40: =F25/MAX(10,F37-各期收支!F17/運營_產能與收入!F7) -> 5.1277956 | G40: =G25/MAX(10,G37-各期收支!G17/運營_產能與收入!G7) -> 3.5906279 | I40: 債務上限基準為 ebitda 時的槓桿（總債務含可轉債；EBITDA 為負或極小時以 US$10m 為下限）；WhiteFiber v0.1b

Sheet 資產負債_租賃承諾
A1: 租賃與承諾 — 季報（2026-06-30）原始揭露
A2: 本頁為硬編碼的申報數字（藍字），支出與資金頁的租金與還本列由此而來
A4: 在帳租賃到期表（未折現）
A5: 項目 | B5: 單位 | C5: 2026 下半 | D5: 2027 | E5: 2028 | F5: 2029 | G5: 2030 | H5: 其後
A6: 營業租賃付款 | B6: US$m | C6: 3.268 | D6: 4.28 | E6: 2.465 | F6: 2.304 | G6: 2.358 | H6: 5.76
A7: 融資租賃付款 | B7: US$m | C7: 0 | D7: 0 | E7: 0 | F7: 0 | G7: 0 | H7: 0
A8: 合計（＝支出頁「在帳現金租金」） | C8: =SUM(C6:C7) -> 3.268 | D8: =SUM(D6:D7) -> 4.28 | E8: =SUM(E6:E7) -> 2.465 | F8: =SUM(F6:F7) -> 2.304 | G8: =SUM(G6:G7) -> 2.358 | H8: =SUM(H6:H7) -> 5.76 | I8: 營業租賃負債現值 15.376、融資租賃 0.0；年報加權剩餘租期 12／14 年、折現率 5.7% [Verified]
A10: 債務本金到期表
A11: 項目 | B11: 單位 | C11: 2026 下半 | D11: 2027 | E11: 2028 | F11: 2029 | G11: 2030 | H11: 其後
A12: 本金（＝支出頁「排程還本」） | B12: US$m | C12: 5.373 | D12: 90.747 | E12: 6.247 | F12: 20.959 | G12: 0 | H12: 0 | I12: 其他借款到期表（company.json → debt.amortization）；可轉債到期還本依融資分類另計，見『資產負債_既有債務』逐檔表
A13: 合計 | C13: =SUM(C12:H12) -> 123.326
A15: 表外與契約性承諾（未入表）
A16: 項目 | B16: 單位 | C16: 金額 | D16: 時程 | E16: 入表？ | F16: 模型位置
A17: 未起租租賃（未折現） | B17: US$m | C17: 20.296 | D17: 季報揭露之已簽約未起租租賃 | E17: 否 | F17: 表外現金租金
A18: 單站按造價計租，上限 | B18: US$m | C18: 0 | D18: 無此類揭露時為 0 | E18: 否 | F18: 表外現金租金
A19: 未動用信用額度 | B19: US$m | C19: 20 | D19: company.json → defaults.facility（Bit Digital DDTL 未動用額度 20（額度 100、已動用 80；可增至 150 未承諾，不計）） | E19: 否（來源） | F19: 瀑布：未動用額度
A20: 已揭露金額之承諾合計（未起租＋單站上限） | C20: =C17+C18 -> 20.296
A21: 模型表外租金五期合計 | C21: =SUM(各期收支!C15:G15) -> 17.027999
A22: 模型表外租金尾端（模型期後未付＝總額 − 五期） | C22: =MAX(0,輸入與假設!$C$26-C21) -> 3.2680012
A23: 模型路徑合計 ÷ 已承諾（≥0.8 為合理） | C23: =(C21+C22)/C20 -> 1 | I23: 起租排程依季報附註（起租期間與期限）平均分攤；五期＋尾端＝未起租總額

Sheet 損益
A1: 損益（類損益表）— 與資金模型同一組收入
A2: 算力收入、Cash CapEx、利息皆由前面分頁連結而來；改資金假設，此頁會跟著動
A4: 項目 | B4: 單位 | C4: FY26 | D4: FY27 | E4: FY28 | F4: FY29 | G4: FY30 | I4: 公式／來源說明
A5: 損益表
A6: 算力收入 | B6: US$m | C6: =運營_產能與收入!C26 -> 41.21625 | D6: =運營_產能與收入!D26 -> 177.654 | E6: =運營_產能與收入!E26 -> 266.2635 | F6: =運營_產能與收入!F26 -> 320.9865 | G6: =運營_產能與收入!G26 -> 369.489 | I6: ＝RPO 轉換＋新簽約
A7: 非算力服務 | B7: US$m | C7: =輸入與假設!C$50 -> 0 | D7: =輸入與假設!D$50 -> 0 | E7: =輸入與假設!E$50 -> 0 | F7: =輸入與假設!F$50 -> 0 | G7: =輸入與假設!G$50 -> 0
A8: 託管 | B8: US$m | C8: =輸入與假設!C$115 -> 37.894181 | D8: =輸入與假設!D$115 -> 100.51558 | E8: =輸入與假設!E$115 -> 151.14892 | F8: =輸入與假設!F$115 -> 170.93441 | G8: =輸入與假設!G$115 -> 175.49574 | I8: SaaS、軟體、硬體、服務（v0.1b）
A9: 總營收 | B9: US$m | C9: =C6+C7+C8 -> 79.110431 | D9: =D6+D7+D8 -> 278.16958 | E9: =E6+E7+E8 -> 417.41242 | F9: =F6+F7+F8 -> 491.92091 | G9: =G6+G7+G8 -> 544.98474
A10: EBITDA 率 | B10: % | C10: =輸入與假設!C$127 -> -0.32919137 | D10: =輸入與假設!D$127 -> -0.17044846 | E10: =輸入與假設!E$127 -> 0.0063592265 | F10: =輸入與假設!F$127 -> 0.13029448 | G10: =輸入與假設!G$127 -> 0.25918346
A11: 延誤罰則（服務抵減，營業費用） | B11: US$m | C11: =運營_產能與收入!C74 -> 0 | D11: =運營_產能與收入!D74 -> 0 | E11: =運營_產能與收入!E74 -> 0 | F11: =運營_產能與收入!F74 -> 0 | G11: =運營_產能與收入!G74 -> 0 | I11: 建設延誤期間應計費而未計費營收 × 罰則比例（預設 0；v0.2）
A12: 營業利益（EBIT） | B12: US$m | C12: =(C6+C7)*輸入與假設!C$127+輸入與假設!C$51+輸入與假設!C$117-C11-輸入與假設!C$176 -> -22.234247 | D12: =(D6+D7)*輸入與假設!D$127+輸入與假設!D$51+輸入與假設!D$117-D11-輸入與假設!D$176 -> -57.288242 | E12: =(E6+E7)*輸入與假設!E$127+輸入與假設!E$51+輸入與假設!E$117-E11-輸入與假設!E$176 -> -16.791789 | F12: =(F6+F7)*輸入與假設!F$127+輸入與假設!F$51+輸入與假設!F$117-F11-輸入與假設!F$176 -> 29.438302 | G12: =(G6+G7)*輸入與假設!G$127+輸入與假設!G$51+輸入與假設!G$117-G11-輸入與假設!G$176 -> 82.018846 | I12: ＝(算力＋服務營收)×EBITDA 率＋其他事業 EBITDA＋託管 EBITDA − 延誤罰則 − 車隊 D&A
A13: 利息（含瀑布新債） | B13: US$m | C13: =各期收支!C22 -> 13.586726 | D13: =各期收支!D22 -> 55.301769 | E13: =各期收支!E22 -> 52.68993 | F13: =各期收支!F22 -> 51.653046 | G13: =各期收支!G22 -> 50.820832
A14: 預付財務組成利息（非現金） | B14: US$m | C14: =各期收支!C10 -> 0 | D14: =各期收支!D10 -> 0 | E14: =各期收支!E10 -> 0 | F14: =各期收支!F10 -> 0 | G14: =各期收支!G10 -> 0 | I14: 客戶預付的重大財務組成：合約負債以隱含利率累積的利息（v0.1b）
A15: 稅前損益 | B15: US$m | C15: =C12-C13-C14 -> -35.820973 | D15: =D12-D13-D14 -> -112.59001 | E15: =E12-E13-E14 -> -69.481719 | F15: =F12-F13-F14 -> -22.214743 | G15: =G12-G13-G14 -> 31.198014
A16: NOL 期初餘額 | B16: US$m | C16: =輸入與假設!$C$246 -> 0 | D16: =C18 -> 35.820973 | E16: =D18 -> 148.41098 | F16: =E18 -> 217.8927 | G16: =F18 -> 240.10745 | I16: 6/30 累積虧損約 0.0
A17: 本期動用 NOL | B17: US$m | C17: =MIN(C16,MAX(0,C15)*輸入與假設!$C$247) -> 0 | D17: =MIN(D16,MAX(0,D15)*輸入與假設!$C$247) -> 0 | E17: =MIN(E16,MAX(0,E15)*輸入與假設!$C$247) -> 0 | F17: =MIN(F16,MAX(0,F15)*輸入與假設!$C$247) -> 0 | G17: =MIN(G16,MAX(0,G15)*輸入與假設!$C$247) -> 24.958411 | I17: 美國規定：抵扣上限為應稅所得 80%
A18: NOL 期末餘額 | B18: US$m | C18: =C16-C17+MAX(0,-C15) -> 35.820973 | D18: =D16-D17+MAX(0,-D15) -> 148.41098 | E18: =E16-E17+MAX(0,-E15) -> 217.8927 | F18: =F16-F17+MAX(0,-F15) -> 240.10745 | G18: =G16-G17+MAX(0,-G15) -> 215.14903
A19: 所得稅 | B19: US$m | C19: =MAX(0,C15-C17)*輸入與假設!$C$233 -> 0 | D19: =MAX(0,D15-D17)*輸入與假設!$C$233 -> 0 | E19: =MAX(0,E15-E17)*輸入與假設!$C$233 -> 0 | F19: =MAX(0,F15-F17)*輸入與假設!$C$233 -> 0 | G19: =MAX(0,G15-G17)*輸入與假設!$C$233 -> 1.3103166 | I19: 虧損年不認列稅盾（與公司評價備抵一致）
A20: 淨利 | B20: US$m | C20: =C15-C19 -> -35.820973 | D20: =D15-D19 -> -112.59001 | E20: =E15-E19 -> -69.481719 | F20: =F15-F19 -> -22.214743 | G20: =G15-G19 -> 29.887697
A21: D&A | B21: US$m | C21: =輸入與假設!C$176 -> 28.446976 | D21: =輸入與假設!D$176 -> 82.693025 | E21: =輸入與假設!E$176 -> 107.05829 | F21: =輸入與假設!F$176 -> 118.02193 | G21: =輸入與假設!G$176 -> 127.81882 | I21: 車隊折舊，見輸入頁
A22: EBITDA | B22: US$m | C22: =C12+C21 -> 6.212729 | D22: =D12+D21 -> 25.404783 | E22: =E12+E21 -> 90.266499 | F22: =F12+F21 -> 147.46023 | G22: =G12+G21 -> 209.83767
A23: 基礎股數（每年 +SBC 稀釋） | B23: m | C23: =評價_DCF與目標價!$C$69 -> 39.33849 | D23: =C23*(1+輸入與假設!$C$260) -> 39.731875 | E23: =D23*(1+輸入與假設!$C$260) -> 40.129194 | F23: =E23*(1+輸入與假設!$C$260) -> 40.530486 | G23: =F23*(1+輸入與假設!$C$260) -> 40.93579 | I23: FY26＝評價股數（含價內可轉債轉股，見『評價_DCF與目標價』可轉債區）；之後每年 ×(1＋股數年增)
A24: 股數（含瀑布新股） | B24: m | C24: =C23+各期收支!C91 -> 39.33849 | D24: =D23+各期收支!D91 -> 39.731875 | E24: =E23+各期收支!E91 -> 40.129194 | F24: =F23+各期收支!F91 -> 40.530486 | G24: =G23+各期收支!G91 -> 40.93579 | I24: ＝基礎股數＋累計瀑布新股
A25: 每股盈餘（EPS，模型期） | B25: US$ | C25: =C20/C24 -> -0.91058333 | D25: =D20/D24 -> -2.8337452 | E25: =E20/E24 -> -1.7314507 | F25: =F20/F24 -> -0.54809961 | G25: =G20/G24 -> 0.73011164 | I25: FY26 欄只含下半年；全年口徑見下方
A27: 損益表（全年口徑；FY26＝1H 實際＋下半年模型；與 HTML 損益簡表一致）
A28: 1H26 實際營收（已實現） | B28: US$m | C28: =輸入與假設!$C$301 -> 50.762 | D28: =0 -> 0 | E28: =0 -> 0 | F28: =0 -> 0 | G28: =0 -> 0
A29: 全年總營收 | B29: US$m | C29: =C28+C9 -> 129.87243 | D29: =D28+D9 -> 278.16958 | E29: =E28+E9 -> 417.41242 | F29: =F28+F9 -> 491.92091 | G29: =G28+G9 -> 544.98474 | I29: FY26 可對照指引 不適用（公司未給指引）
A30: 營收 YoY | B30: % | C30: =C29/79.164-1 -> 0.64054913 | D30: =D29/C29-1 -> 1.1418678 | E30: =E29/D29-1 -> 0.50056817 | F30: =F29/E29-1 -> 0.17850087 | G30: =G29/F29-1 -> 0.10787066 | I30: FY25 實際 79.164
A31: 全年 GAAP 營業利益 | B31: US$m | C31: =輸入與假設!$C$302+C12 -> -42.509247 | D31: =D12 -> -57.288242 | E31: =E12 -> -16.791789 | F31: =F12 -> 29.438302 | G31: =G12 -> 82.018846
A32: 營利率 | B32: % | C32: =C31/C29 -> -0.3273154 | D32: =D31/D29 -> -0.20594718 | E32: =E31/E29 -> -0.040228292 | F32: =F31/F29 -> 0.059843568 | G32: =G31/G29 -> 0.15049751
A33: 全年 D&A | B33: US$m | C33: =輸入與假設!$C$305+C21 -> 41.454976 | D33: =D21 -> 82.693025 | E33: =E21 -> 107.05829 | F33: =F21 -> 118.02193 | G33: =G21 -> 127.81882 | I33: 1H 實際 13.008
A34: 全年 EBITDA | B34: US$m | C34: =C31+C33 -> -1.054271 | D34: =D31+D33 -> 25.404783 | E34: =E31+E33 -> 90.266499 | F34: =F31+F33 -> 147.46023 | G34: =G31+G33 -> 209.83767
A35: 全年利息（含瀑布新債） | B35: US$m | C35: =輸入與假設!$C$299+C13 -> 21.597726 | D35: =D13 -> 55.301769 | E35: =E13 -> 52.68993 | F35: =F13 -> 51.653046 | G35: =G13 -> 50.820832 | I35: FY27 起瀑布新債利息（9%）與新股同時影響 EPS
A36: 全年淨利 | B36: US$m | C36: =輸入與假設!$C$303+C20 -> -62.838973 | D36: =D20 -> -112.59001 | E36: =E20 -> -69.481719 | F36: =F20 -> -22.214743 | G36: =G20 -> 29.887697
A37: 淨利率 | B37: % | C37: =C36/C29 -> -0.48385152 | D37: =D36/D29 -> -0.40475313 | E37: =E36/E29 -> -0.1664582 | F37: =F36/F29 -> -0.045159177 | G37: =G36/G29 -> 0.054841347
A38: 全年 GAAP EPS | B38: US$ | C38: =輸入與假設!$C$307+C20/C24 -> -1.6105833 | D38: =D20/D24 -> -2.8337452 | E38: =E20/E24 -> -1.7314507 | F38: =F20/F24 -> -0.54809961 | G38: =G20/G24 -> 0.73011164 | I38: FY26＝1H 實際 EPS −0.70＋下半年淨利÷股數
A39: 全年 EPS（加回 SBC） | B39: US$ | C39: =輸入與假設!$C$308+(C20+輸入與假設!$C$261*輸入與假設!C$41)/C24 -> -1.0405268 | D39: =(D20+輸入與假設!$C$261*輸入與假設!D$41)/D24 -> -2.2791779 | E39: =(E20+輸入與假設!$C$261*輸入與假設!E$41)/E24 -> -1.1823741 | F39: =(F20+輸入與假設!$C$261*輸入與假設!F$41)/F24 -> -0.0044594436 | G39: =(G20+輸入與假設!$C$261*輸入與假設!G$41)/G24 -> 1.2683692 | I39: ＝(淨利＋SBC)÷股數；NOL 狀態無現金稅，SBC 全額加回

Sheet 評價_DCF與目標價
A1: 評價 — DCF、EV/EBITDA、加權目標價
A2: 營收、營業利益、D&A、EBITDA、股數引用『損益』頁；Cash CapEx 與融資引用『各期收支』頁
A4: 項目 | B4: 單位 | C4: FY26 | D4: FY27 | E4: FY28 | F4: FY29 | G4: FY30 | I4: 公式／來源說明
A5: DCF（無槓桿自由現金流；起點為 2026-06-30）
A6: 現金 CapEx（2026-06-30 之後） | B6: US$m | C6: =輸入與假設!C$175-各期收支!C8 -> 116.11343 | D6: =輸入與假設!D$175-各期收支!D8 -> 337.44504 | E6: =輸入與假設!E$175-各期收支!E8 -> 44.54415 | F6: =輸入與假設!F$175-各期收支!F8 -> 44.54415 | G6: =輸入與假設!G$175-各期收支!G8 -> 119.35013 | I6: DCF 起點為 6/30，故 FY26 欄只含 2H 的建置支出，不含 1H 已發生的 344.712
A7: 比較基期營收 | B7: US$m | C7: =79.164 -> 79.164 | D7: =50.762+損益!C9 -> 129.87243 | E7: =損益!D9 -> 278.16958 | F7: =損益!E9 -> 417.41242 | G7: =損益!F9 -> 491.92091 | I7: FY25 實際 79.164；FY27 基期＝1H 實際 50.762＋FY26 模型期營收
A8: 預付認列（非現金營收，扣除） | B8: US$m | C8: =各期收支!C11 -> 8.944375 | D8: =各期收支!D11 -> 20.628903 | E8: =各期收支!E11 -> 29.262862 | F8: =各期收支!F11 -> 27.085111 | G8: =各期收支!G11 -> 25.179578 | I8: 營收中由合約負債轉入的部分已在預付時收現（預付流入已自現金 CapEx 抵減），UFCF 扣除以免重複（v0.1b）
A9: 營運資金變動 | B9: US$m | C9: =輸入與假設!$C$248*MAX(0,損益!C9-C7) -> 0 | D9: =輸入與假設!$C$248*MAX(0,損益!D9-D7) -> 2.965943 | E9: =輸入與假設!$C$248*MAX(0,損益!E9-E7) -> 2.7848568 | F9: =輸入與假設!$C$248*MAX(0,損益!F9-F7) -> 1.4901696 | G9: =輸入與假設!$C$248*MAX(0,損益!G9-G7) -> 1.0612766 | I9: 營收增量的 2%
A10: 無槓桿 NOL 期初 | B10: US$m | C10: =輸入與假設!$C$246 -> 0 | D10: =C12 -> 22.234247 | E10: =D12 -> 79.522488 | F10: =E12 -> 96.314277 | G10: =F12 -> 72.763635 | I10: DCF 用無槓桿稅（利息不可抵稅，否則稅盾被計兩次：一次在 UFCF、一次在 WACC）
A11: 本期動用（無槓桿） | B11: US$m | C11: =MIN(C10,MAX(0,損益!C12)*輸入與假設!$C$247) -> 0 | D11: =MIN(D10,MAX(0,損益!D12)*輸入與假設!$C$247) -> 0 | E11: =MIN(E10,MAX(0,損益!E12)*輸入與假設!$C$247) -> 0 | F11: =MIN(F10,MAX(0,損益!F12)*輸入與假設!$C$247) -> 23.550642 | G11: =MIN(G10,MAX(0,損益!G12)*輸入與假設!$C$247) -> 65.615077
A12: 無槓桿 NOL 期末 | B12: US$m | C12: =C10-C11+MAX(0,-損益!C12) -> 22.234247 | D12: =D10-D11+MAX(0,-損益!D12) -> 79.522488 | E12: =E10-E11+MAX(0,-損益!E12) -> 96.314277 | F12: =F10-F11+MAX(0,-損益!F12) -> 72.763635 | G12: =G10-G11+MAX(0,-損益!G12) -> 7.1485585
A13: 無槓桿所得稅（DCF 用） | B13: US$m | C13: =MAX(0,損益!C12-C11)*輸入與假設!$C$233 -> 0 | D13: =MAX(0,損益!D12-D11)*輸入與假設!$C$233 -> 0 | E13: =MAX(0,損益!E12-E11)*輸入與假設!$C$233 -> 0 | F13: =MAX(0,損益!F12-F11)*輸入與假設!$C$233 -> 1.2364087 | G13: =MAX(0,損益!G12-G11)*輸入與假設!$C$233 -> 3.4447915 | I13: 與損益表的所得稅不同：此處不扣利息，數字較高，這是 DCF 的正確口徑
A14: UFCF | B14: US$m | C14: =損益!C12-C13+損益!C21-C6-C9-C8 -> -118.84508 | D14: =損益!D12-D13+損益!D21-D6-D9-D8 -> -335.6351 | E14: =損益!E12-E13+損益!E21-E6-E9-E8 -> 13.67463 | F14: =損益!F12-F13+損益!F21-F6-F9-F8 -> 73.104391 | G14: =損益!G12-G13+損益!G21-G6-G9-G8 -> 60.801892 | I14: ＝EBIT−無槓桿稅＋D&A−現金 CapEx（已扣客戶預付）−營運資金−預付認列。建置期全為負是正常的
A15: 折現期數 | B15: 年 | C15: =輸入與假設!$C$278 -> 0.5 | D15: =輸入與假設!$D$278 -> 1.5 | E15: =輸入與假設!$E$278 -> 2.5 | F15: =輸入與假設!$F$278 -> 3.5 | G15: =輸入與假設!$G$278 -> 4.5 | I15: 自 2026-06-30 起算；FY26 模型期（下半年）的現金流平均落在 0.5 年
A16: 折現因子 | C16: =1/(1+輸入與假設!$C$243)^C15 -> 0.93713671 | D16: =1/(1+輸入與假設!$C$243)^D15 -> 0.82301708 | E16: =1/(1+輸入與假設!$C$243)^E15 -> 0.72279434 | F16: =1/(1+輸入與假設!$C$243)^F15 -> 0.63477621 | G16: =1/(1+輸入與假設!$C$243)^G15 -> 0.55747647
A17: UFCF 現值 | B17: US$m | C17: =C14*C16 -> -111.37408 | D17: =D14*D16 -> -276.23342 | E17: =E14*E16 -> 9.8839451 | F17: =F14*F16 -> 46.404929 | G17: =G14*G16 -> 33.895624
A19: 五期 UFCF 現值合計 | C19: =SUM(C17:G17) -> -297.423 | I19: 建置期現金流現值
A20: 終值基準 FCF（FY30 UFCF，含汰換 CapEx） | C20: =G14+輸入與假設!G165*(1-各期收支!G7)+輸入與假設!G107*(1-各期收支!G7) -> 89.755589 | I20: v0.1c：終值基準＝末期 UFCF（含穩態汰換 CapEx，已扣客戶預付覆蓋）＋加回末期成長型 CapEx（扣預付後；成長由 g 表達，預設情境為 0）；GPU 不是永續資產，終值年須持續再投資
A21: 終值（Gordon） | C21: =IF(C30=1,0,C20*(1+輸入與假設!$C$244)/(輸入與假設!$C$243-輸入與假設!$C$244)) -> 850.80226 | I21: ＝常態化 FCF×(1+g)÷(WACC−g)
A22: 終值現值 | C22: =C21*G16 -> 474.30224
A23: 企業價值 EV | C23: =C19+C22 -> 176.87924
A24: 減：淨負債 | C24: =-評價_DCF與目標價!$C$70 -> -192.033 | I24: ＝評價淨負債（不含可轉債的淨負債＋債務處理可轉債到期本金＋調整項；見下方可轉債區）
A25: 股權價值 | C25: =C23+C24 -> -15.153761
A26: DCF 每股 | C26: =IF(C30=1,0,IF(輸入與假設!$C$263=2,C32,C31)) -> 0 | I26: 採用值：失效時為 0 且權重歸零；否則依「DCF 下限方式」取 0 截斷或選擇權
A27: 終值占 EV 比重 | C27: =C22/C23 -> 2.6815032 | I27: ="超過 "&IF(ROUND(ABS(輸入與假設!$C$287)*100,4)=INT(ROUND(ABS(輸入與假設!$C$287)*100,4)),TEXT(ROUND(ABS(輸入與假設!$C$287)*100,4),"0"),TEXT(ROUND(ABS(輸入與假設!$C$287)*100,4),"0.0"))&"%"&" 表示結論由終值假設決定，不由現金流決定" -> 超過 85% 表示結論由終值假設決定，不由現金流決定
A28: 新股募得現金（現值） | C28: =各期收支!C86/(1+輸入與假設!$C$243)^輸入與假設!$C$279+各期收支!D86/(1+輸入與假設!$C$243)^輸入與假設!$D$279+各期收支!E86/(1+輸入與假設!$C$243)^輸入與假設!$E$279+各期收支!F86/(1+輸入與假設!$C$243)^輸入與假設!$F$279+各期收支!G86/(1+輸入與假設!$C$243)^輸入與假設!$G$279 -> 0 | I28: 期初到位，折現期數 0／0.5／1.5／2.5／3.5 年
A29: 融資後股數（含瀑布新股） | C29: =評價_DCF與目標價!$C$69+各期收支!G91 -> 39.33849
A30: DCF 失效？（WACC ≤ g 或常態化 FCF ≤ 0） | C30: =IF(OR(輸入與假設!$C$243<=輸入與假設!$C$244,C20<=0),1,0) -> 0 | I30: 1＝失效：DCF 權重歸零、EV/EBITDA 100%。股權為負不算失效
A31: DCF 每股：0 截斷 | C31: =MAX(0,(C25+C28)/C29) -> 0
A32: DCF 每股：選擇權（Merton） | C32: =IF((C23+C28)<=0,0,IF(評價_DCF與目標價!$C$70<=0,(C23+C28),(C23+C28)*NORMSDIST(C33)-評價_DCF與目標價!$C$70*EXP(-輸入與假設!$C$234*輸入與假設!$C$265)*NORMSDIST(C34))/C29) -> 2.0256459 | I32: Black-Scholes：S＝企業價值＋新股現值、K＝淨負債
A33: d1 | C33: =IF(OR((C23+C28)<=0,評價_DCF與目標價!$C$70<=0),0,(LN((C23+C28)/評價_DCF與目標價!$C$70)+(輸入與假設!$C$234+輸入與假設!$C$264^2/2)*輸入與假設!$C$265)/(輸入與假設!$C$264*SQRT(輸入與假設!$C$265))) -> 0.67641835
A34: d2 | C34: =C33-輸入與假設!$C$264*SQRT(輸入與假設!$C$265) -> -0.38424182
A36: 倍數法（錨定年度，預設 FY29；折回 2027-06-30）
A37: 錨定年度 | C37: =CHOOSE(輸入與假設!$C$255,"FY27","FY28","FY29","FY30") -> FY29 | I37: 輸入與假設 F 區可改
A38: 錨定年度 EBITDA | C38: =INDEX(損益!$D$22:$G$22,1,輸入與假設!$C$255) -> 147.46023
A39: 錨定年度企業價值（倍數 × EBITDA） | C39: =C45*輸入與假設!$C$249+C44*輸入與假設!$C$254 -> 2442.914 | I39: 分部加總：雲端 EBITDA × EV/EBITDA 倍數＋託管 EBITDA × 託管倍數（下方兩列）
A40: 錨定年度末淨負債（總債務 − 現金） | C40: =INDEX(各期收支!$D$96:$G$96,1,輸入與假設!$C$255)-INDEX(各期收支!$D$54:$G$54,1,輸入與假設!$C$255)+評價_DCF與目標價!$C$71 -> 726.14592 | I40: 含瀑布新債；加可轉債分類調整與淨負債調整項（見下方可轉債區）
A41: 錨定年度末股數（含瀑布新股） | C41: =INDEX(損益!$D$24:$G$24,1,輸入與假設!$C$255) -> 40.530486 | I41: 損益股數：SBC 逐年稀釋＋瀑布新股
A42: 折回 2027-06-30 的折現因子 | C42: =1/(1+輸入與假設!$C$243)^(輸入與假設!$C$255-輸入與假設!$C$275) -> 0.72279434 | I42: 以 WACC 折現 [Assumed]
A43: EV/EBITDA 每股（融資後） | C43: =MAX(0,(C39-C40)/C41)*C42 -> 30.615726 | I43: 以 0 為下限
A44: 錨定年度託管 EBITDA | C44: =INDEX(輸入與假設!$D$117:$G$117,1,輸入與假設!$C$255) -> 105.63746 | I44: × 託管 EV/EBITDA 倍數（託管同業 NTM 中位數）
A45: 錨定年度 雲端 EBITDA（算力＋服務＋其他） | C45: =C38-C44 -> 41.822768 | I45: ＝錨定年度 EBITDA − 託管；× EV/EBITDA 倍數
A47: 加權目標價
A48: DCF 每股（推到目標價時點） | C48: =C26*(1+輸入與假設!$C$243)^輸入與假設!$C$271 -> 0 | I48: ＝DCF 每股 ×（1＋WACC）^（評價日至目標價時點的年數）
A49: DCF 每股 × 有效權重 | C49: =C48*IF(C30=1,0,輸入與假設!$C$256) -> 0
A50: EV/EBITDA（融資後）× 有效權重 | C50: =C43*IF(C30=1,1,1-輸入與假設!$C$256) -> 16.838649
A51: 加權目標價 | C51: =SUM(C49:C50) -> 16.838649 | I51: 期前融資瀑布：缺口先由額度與資產層新債支應，殘差以股權募足；估值不再扣缺口本金
A52: 現價 | C52: =輸入與假設!$C$228 -> 16.83
A53: 潛在空間 | C53: =C51/C52-1 -> 0.00051390791
A55: 可轉債稀釋（若轉換法；第一輪判斷價＝現價，第二輪＝MIN(現價, 第一輪目標價)）
A56: 第一輪：轉股股數 | C56: =SUMPRODUCT(資產負債_既有債務!$D$20:$D$21*資產負債_既有債務!$G$20:$G$21) -> 0 | I56: 有效轉換價 < 現價的可轉債：原始本金 ÷ 轉換價
A57: 第一輪：評價股數 | C57: =輸入與假設!$C$229+C56 -> 39.33849
A58: 第一輪：評價淨負債 | C58: =輸入與假設!$C$230+SUMPRODUCT(資產負債_既有債務!$C$20:$C$21*(1-資產負債_既有債務!$G$20:$G$21))+輸入與假設!$C$232 -> 192.033 | I58: ＝不含可轉債的淨負債＋債務處理可轉債到期本金＋調整項
A59: 第一輪：DCF 融資後股數 | C59: =C57+各期收支!G91 -> 39.33849
A60: 第一輪：d1 | C60: =IF(OR((C23+C28)<=0,C58<=0),0,(LN((C23+C28)/C58)+(輸入與假設!$C$234+輸入與假設!$C$264^2/2)*輸入與假設!$C$265)/(輸入與假設!$C$264*SQRT(輸入與假設!$C$265))) -> 0.67641835
A61: 第一輪：DCF 每股（評價日） | C61: =IF(C30=1,0,IF(輸入與假設!$C$263=2,IF((C23+C28)<=0,0,IF(C58<=0,(C23+C28),(C23+C28)*NORMSDIST(C60)-C58*EXP(-輸入與假設!$C$234*輸入與假設!$C$265)*NORMSDIST(C60-輸入與假設!$C$264*SQRT(輸入與假設!$C$265)))/C59),MAX(0,(C23-C58+C28)/C59))) -> 0 | I61: 與上方 DCF 同算法，只換股數與淨負債
A62: 第一輪：錨定年末淨負債 | C62: =INDEX(各期收支!$D$96:$G$96,1,輸入與假設!$C$255)-INDEX(各期收支!$D$54:$G$54,1,輸入與假設!$C$255)+SUMPRODUCT(資產負債_既有債務!$C$20:$C$21*(資產負債_既有債務!$F$20:$F$21-資產負債_既有債務!$G$20:$G$21))+輸入與假設!$C$232 -> 726.14592 | I62: ＝融資表錨定年末淨負債＋（融資分類為轉股、評價分類為債務的到期本金）＋調整項
A63: 第一輪：錨定年末股數 | C63: =C57*(1+輸入與假設!$C$260)^輸入與假設!$C$255+INDEX(各期收支!$D$91:$G$91,1,輸入與假設!$C$255) -> 40.530486
A64: 第一輪：EV/EBITDA 每股 | C64: =MAX(0,(C39-C62)/C63)*C42 -> 30.615726
A65: 第一輪：加權目標價 | C65: =C61*(1+輸入與假設!$C$243)^輸入與假設!$C$271*IF(C30=1,0,輸入與假設!$C$256)+C64*IF(C30=1,1,1-輸入與假設!$C$256) -> 16.838649
A66: 第二輪判斷價 | C66: =MIN(輸入與假設!$C$228,C65) -> 16.83 | I66: ＝MIN(現價, 第一輪加權目標價)：以較保守者判斷是否價內
A67: 第二輪：轉股股數 | C67: =SUMPRODUCT(資產負債_既有債務!$D$20:$D$21*資產負債_既有債務!$H$20:$H$21) -> 0 | I67: 有效轉換價 < 第二輪判斷價的可轉債
A68: 第二輪：債務處理到期本金 | C68: =SUMPRODUCT(資產負債_既有債務!$C$20:$C$21*(1-資產負債_既有債務!$H$20:$H$21)) -> 341.85
A69: 評價股數（含可轉債轉股） | C69: =輸入與假設!$C$229+C67 -> 39.33849 | I69: DCF、損益股數與錨定年末股數的起點
A70: 評價淨負債（含可轉債與調整項） | C70: =輸入與假設!$C$230+C68+輸入與假設!$C$232 -> 192.033 | I70: DCF 減項與 Merton 履約價
A71: 錨定年末淨負債調整（可轉債分類差＋調整項） | C71: =SUMPRODUCT(資產負債_既有債務!$C$20:$C$21*(資產負債_既有債務!$F$20:$F$21-資產負債_既有債務!$H$20:$H$21))+輸入與假設!$C$232 -> 0 | I71: 融資現金流依『融資分類』（判斷價＝股權發行價）；評價依第二輪分類，差額在錨定年末淨負債補回
A72: DCF 權重說明 | C72: =IF(C30=1,"DCF 失效，已以 EV/EBITDA 100% 計。",IF(AND(輸入與假設!$C$263<>2,C87<0),"DCF 為 $0 仍計 "&TEXT(輸入與假設!$C$256,"0%")&" 權重的原因：DCF 沒有失效，而是算出的股權價值為負（每股約 −$"&TEXT(ABS(C87),"0.0")&"），代表自由現金流折現後的企業價值不足以償還淨負債。EV/EBITDA 沒有扣除 GPU 汰換與擴張支出，保留 DCF 權重，是為了讓目標價反映「EBITDA 付不起資本成本」。若不計 DCF，目標價為 $"&TEXT(C43,"0.0")&"（"&CHOOSE(D86+2,"賣出","中立","買進")&"）；"&TEXT(輸入與假設!$C$256,"0%")&"／"&TEXT(1-輸入與假設!$C$256,"0%")&" 為判斷值。","")) -> DCF 為 $0 仍計 45% 權重的原因：DCF 沒有失效，而是算出的股權價值為負（每股約 −$0.4），代表自由現金流折現後的企業價值不足以償還淨負債。EV/EBITDA 沒有扣除 GPU 汰換與擴張支出，保留 DCF 權重，是為了讓目標價反映「EBITDA 付不起資本成本」。若不計 DCF，目標價為 $30.6（中立）；45%／55% 為判斷值。 | I72: 只在 DCF 被 0 截斷時顯示；DCF 失效時改為一句；DCF 為正時空白（與 HTML 同一字串）
A74: 目標價區間（情境區間、方法區間；評等仍依點位）
A75: 目標價區間｜點位（目前輸入的加權目標價） | C75: =C51 -> 16.838649 | I75: ="評等規則不變：空間 ≥"&IF(ROUND(ABS(輸入與假設!$C$281)*100,4)=INT(ROUND(ABS(輸入與假設!$C$281)*100,4)),TEXT(ROUND(ABS(輸入與假設!$C$281)*100,4),"0"),TEXT(ROUND(ABS(輸入與假設!$C$281)*100,4),"0.0"))&"%"&" 且終值占比 <"&IF(ROUND(ABS(輸入與假設!$C$282)*100,4)=INT(ROUND(ABS(輸入與假設!$C$282)*100,4)),TEXT(ROUND(ABS(輸入與假設!$C$282)*100,4),"0"),TEXT(ROUND(ABS(輸入與假設!$C$282)*100,4),"0.0"))&"%"&"、股權募資 ≤"&IF(輸入與假設!$C$284=INT(輸入與假設!$C$284),TEXT(輸入與假設!$C$284,"0"),TEXT(輸入與假設!$C$284,"0.0"))&" 倍現市值 → 買進；空間 ≤−"&IF(ROUND(ABS(輸入與假設!$C$283)*100,4)=INT(ROUND(ABS(輸入與假設!$C$283)*100,4)),TEXT(ROUND(ABS(輸入與假設!$C$283)*100,4),"0"),TEXT(ROUND(ABS(輸入與假設!$C$283)*100,4),"0.0"))&"%"&"，或股權募資 >"&IF(輸入與假設!$C$284=INT(輸入與假設!$C$284),TEXT(輸入與假設!$C$284,"0"),TEXT(輸入與假設!$C$284,"0.0"))&" 倍且空間 ≤−"&IF(ROUND(ABS(輸入與假設!$C$285)*100,4)=INT(ROUND(ABS(輸入與假設!$C$285)*100,4)),TEXT(ROUND(ABS(輸入與假設!$C$285)*100,4),"0"),TEXT(ROUND(ABS(輸入與假設!$C$285)*100,4),"0.0"))&"%"&" → 賣出；其餘中立" -> 評等規則不變：空間 ≥25% 且終值占比 <90%、股權募資 ≤1.5 倍現市值 → 買進；空間 ≤−15%，或股權募資 >1.5 倍且空間 ≤−8% → 賣出；其餘中立
A76: 目標價區間｜終值占 EV（評等用） | C76: =C22/MAX(ABS(C23),1)*IF(C23=0,1,SIGN(C23)) -> 2.6815032
A77: 目標價區間｜股權募資 ÷ 現市值（評等用） | C77: =SUM(各期收支!C86:G86)/(輸入與假設!$C$228*輸入與假設!$C$229) -> 0
A78: 目標價區間｜點位評等代碼（1＝買進、0＝中立、−1＝賣出） | C78: =IF(AND((C51/MAX(輸入與假設!$C$228,0.01)-1)>=輸入與假設!$C$281,$C$76<輸入與假設!$C$282,$C$77<=輸入與假設!$C$284),1,IF(OR((C51/MAX(輸入與假設!$C$228,0.01)-1)<=輸入與假設!$C$283,AND($C$77>輸入與假設!$C$284,(C51/MAX(輸入與假設!$C$228,0.01)-1)<=輸入與假設!$C$285)),-1,0)) -> 0 | D78: =CHOOSE(C78+2,"賣出","中立","買進") -> 中立
A79: 目標價區間｜賣出門檻價（現價 × (1 − 15%)） | C79: =輸入與假設!$C$228*(1+輸入與假設!$C$283) -> 14.3055
A80: 目標價區間｜保守 只有已簽約（加權目標價／評等代碼／距賣出門檻） | C80: =輸入與假設!D315 -> 10.044175 | D80: =輸入與假設!E315 -> -1 | E80: =C80-$C$79 -> -4.2613254 | I80: 引用『輸入與假設』底部模擬運算表（情境選擇 1／2／3），保留其餘手動輸入
A81: 目標價區間｜基準 加 NC-1 下一批（加權目標價／評等代碼／距賣出門檻） | C81: =輸入與假設!D316 -> 16.838649 | D81: =輸入與假設!E316 -> 0 | E81: =C81-$C$79 -> 2.5331491
A82: 目標價區間｜積極 NC-2／3 與 Krambu（加權目標價／評等代碼／距賣出門檻） | C82: =輸入與假設!D317 -> 34.655938 | D82: =輸入與假設!E317 -> 0 | E82: =C82-$C$79 -> 20.350438
A83: 目標價區間｜情境區間（下緣／上緣） | C83: =MIN(C80,C82) -> 10.044175 | D83: =MAX(C80,C82) -> 34.655938
A84: 目標價區間｜方法區間倍數（下端／上端） | C84: =MIN(輸入與假設!$C$258,輸入與假設!$C$259) -> 5 | D84: =MAX(輸入與假設!$C$258,輸入與假設!$C$259) -> 6
A85: 目標價區間｜方法區間（下緣／上緣） | C85: =MIN(C48*IF(C30=1,0,輸入與假設!$C$256)+MAX(0,(C45*C84+C44*輸入與假設!$C$254-C40)/C41)*C42*IF(C30=1,1,1-輸入與假設!$C$256),C48*IF(C30=1,0,輸入與假設!$C$256)+MAX(0,(C45*D84+C44*輸入與假設!$C$254-C40)/C41)*C42*IF(C30=1,1,1-輸入與假設!$C$256)) -> 16.428437 | D85: =MAX(C48*IF(C30=1,0,輸入與假設!$C$256)+MAX(0,(C45*C84+C44*輸入與假設!$C$254-C40)/C41)*C42*IF(C30=1,1,1-輸入與假設!$C$256),C48*IF(C30=1,0,輸入與假設!$C$256)+MAX(0,(C45*D84+C44*輸入與假設!$C$254-C40)/C41)*C42*IF(C30=1,1,1-輸入與假設!$C$256)) -> 16.838649 | I85: ＝DCF 採用值 × 有效權重 ＋ EV/EBITDA 腿（倍數換成兩端）× 有效權重
A86: 目標價區間｜100% EV/EBITDA 目標價（價位／評等代碼） | C86: =C43 -> 30.615726 | D86: =IF(AND((C43/MAX(輸入與假設!$C$228,0.01)-1)>=輸入與假設!$C$281,$C$76<輸入與假設!$C$282,$C$77<=輸入與假設!$C$284),1,IF(OR((C43/MAX(輸入與假設!$C$228,0.01)-1)<=輸入與假設!$C$283,AND($C$77>輸入與假設!$C$284,(C43/MAX(輸入與假設!$C$228,0.01)-1)<=輸入與假設!$C$285)),-1,0)) -> 0 | E86: =CHOOSE(D86+2,"賣出","中立","買進") -> 中立
A87: 目標價區間｜未截斷 DCF 每股 | C87: =(C25+C28)/C29 -> -0.38521461
A88: 目標價區間｜點位摘要 | C88: ="目標價 $"&TEXT(C51,"0.0")&"（情境區間 $"&TEXT(C83,"0.0")&"–$"&TEXT(D83,"0.0")&"）" -> 目標價 $16.8（情境區間 $10.0–$34.7）
A89: 目標價區間｜方法區間標籤 | C89: ="方法區間（目前情境，"&IF(C84=INT(C84),TEXT(C84,"0"),TEXT(C84,"0.0"))&"–"&IF(D84=INT(D84),TEXT(D84,"0"),TEXT(D84,"0.0"))&"x）" -> 方法區間（目前情境，5–6x）
A90: 目標價區間｜點位位置 | C90: =IF(ABS(輸入與假設!$C$249-D84)<0.000000001,"目前點位位於方法區間上緣（"&IF(D84=INT(D84),TEXT(D84,"0"),TEXT(D84,"0.0"))&"x 為穩態倍數上緣）",IF(ABS(輸入與假設!$C$249-C84)<0.000000001,"目前點位位於方法區間下緣（"&IF(C84=INT(C84),TEXT(C84,"0"),TEXT(C84,"0.0"))&"x）","目前點位"&IF(AND(輸入與假設!$C$249>C84,輸入與假設!$C$249<D84),"位於方法區間內",IF(輸入與假設!$C$249>D84,"高於方法區間上緣","低於方法區間下緣"))&"（目前倍數 "&IF(輸入與假設!$C$249=INT(輸入與假設!$C$249),TEXT(輸入與假設!$C$249,"0"),TEXT(輸入與假設!$C$249,"0.0"))&"x）")) -> 目前點位位於方法區間上緣（6x 為穩態倍數上緣）
A91: 目標價區間｜判斷句 | C91: =IF(D83<輸入與假設!$C$228,"情境區間上緣 $"&TEXT(D83,"0.0")&" 低於現價 $"&TEXT(輸入與假設!$C$228,"0.00")&IF((D80<>-1)+(D81<>-1)+(D82<>-1)>0,"，但"&SUBSTITUTE(TRIM(IF(D80<>-1,"保守","")&" "&IF(D81<>-1,"基準","")&" "&IF(D82<>-1,"積極",""))," ","、")&"情境未達賣出門檻 $"&TEXT($C$79,"0.0"),"：賣出在三個擴張情境下都成立"),"情境區間上緣 $"&TEXT(D83,"0.0")&" 不低於現價 $"&TEXT(輸入與假設!$C$228,"0.00")&"：賣出並非在三個擴張情境下都成立")&"。"&IF(ABS(E80)<輸入與假設!$C$286*輸入與假設!$C$228,"保守情境 $"&TEXT(C80,"0.0")&"，"&IF(E80<0,"距賣出門檻","高於賣出門檻")&" $"&TEXT($C$79,"0.0")&" 僅 $"&TEXT(ABS(E80),"0.0")&"。","")&IF(ABS(E81)<輸入與假設!$C$286*輸入與假設!$C$228,"基準情境 $"&TEXT(C81,"0.0")&"，"&IF(E81<0,"距賣出門檻","高於賣出門檻")&" $"&TEXT($C$79,"0.0")&" 僅 $"&TEXT(ABS(E81),"0.0")&"。","")&IF(ABS(E82)<輸入與假設!$C$286*輸入與假設!$C$228,"積極情境 $"&TEXT(C82,"0.0")&"，"&IF(E82<0,"距賣出門檻","高於賣出門檻")&" $"&TEXT($C$79,"0.0")&" 僅 $"&TEXT(ABS(E82),"0.0")&"。","") -> 情境區間上緣 $34.7 不低於現價 $16.83：賣出並非在三個擴張情境下都成立。
A93: 錨定年度 × 倍數矩陣（每股；以 WACC 折回 2027-06-30）
A94: 雲端 倍數 ＼ 錨定（EV/EBITDA 腿） | B94: 倍數 | C94: FY27 | D94: FY28 | E94: FY29 | F94: FY30 | I94: EV/EBITDA 腿＝(雲端 EBITDA × 倍數＋託管 EBITDA × 託管倍數 − 錨定年末淨負債) ÷ 錨定年末股數 × 折現因子；加權＝DCF 採用值 × 有效權重 ＋ 腿 × 有效權重。綠底＝不低於現價
A95: 錨定×倍數｜EV/EBITDA 腿｜3.4x | B95: 3.4 | C95: =MAX(0,((INDEX(損益!$D$22:$G$22,1,1)-INDEX(輸入與假設!$D$117:$G$117,1,1))*$B95+INDEX(輸入與假設!$D$117:$G$117,1,1)*輸入與假設!$C$254-(INDEX(各期收支!$D$96:$G$96,1,1)-INDEX(各期收支!$D$54:$G$54,1,1)+評價_DCF與目標價!$C$71))/INDEX(損益!$D$24:$G$24,1,1))/(1+輸入與假設!$C$243)^(1-輸入與假設!$C$275) -> 8.0196719 | D95: =MAX(0,((INDEX(損益!$D$22:$G$22,1,2)-INDEX(輸入與假設!$D$117:$G$117,1,2))*$B95+INDEX(輸入與假設!$D$117:$G$117,1,2)*輸入與假設!$C$254-(INDEX(各期收支!$D$96:$G$96,1,2)-INDEX(各期收支!$D$54:$G$54,1,2)+評價_DCF與目標價!$C$71))/INDEX(損益!$D$24:$G$24,1,2))/(1+輸入與假設!$C$243)^(2-輸入與假設!$C$275) -> 22.446623 | E95: =MAX(0,((INDEX(損益!$D$22:$G$22,1,3)-INDEX(輸入與假設!$D$117:$G$117,1,3))*$B95+INDEX(輸入與假設!$D$117:$G$117,1,3)*輸入與假設!$C$254-(INDEX(各期收支!$D$96:$G$96,1,3)-INDEX(各期收支!$D$54:$G$54,1,3)+評價_DCF與目標價!$C$71))/INDEX(損益!$D$24:$G$24,1,3))/(1+輸入與假設!$C$243)^(3-輸入與假設!$C$275) -> 28.676541 | F95: =MAX(0,((INDEX(損益!$D$22:$G$22,1,4)-INDEX(輸入與假設!$D$117:$G$117,1,4))*$B95+INDEX(輸入與假設!$D$117:$G$117,1,4)*輸入與假設!$C$254-(INDEX(各期收支!$D$96:$G$96,1,4)-INDEX(各期收支!$D$54:$G$54,1,4)+評價_DCF與目標價!$C$71))/INDEX(損益!$D$24:$G$24,1,4))/(1+輸入與假設!$C$243)^(4-輸入與假設!$C$275) -> 30.534918
A96: 錨定×倍數｜EV/EBITDA 腿｜4.5x | B96: 4.5 | C96: =MAX(0,((INDEX(損益!$D$22:$G$22,1,1)-INDEX(輸入與假設!$D$117:$G$117,1,1))*$B96+INDEX(輸入與假設!$D$117:$G$117,1,1)*輸入與假設!$C$254-(INDEX(各期收支!$D$96:$G$96,1,1)-INDEX(各期收支!$D$54:$G$54,1,1)+評價_DCF與目標價!$C$71))/INDEX(損益!$D$24:$G$24,1,1))/(1+輸入與假設!$C$243)^(1-輸入與假設!$C$275) -> 7.23403 | D96: =MAX(0,((INDEX(損益!$D$22:$G$22,1,2)-INDEX(輸入與假設!$D$117:$G$117,1,2))*$B96+INDEX(輸入與假設!$D$117:$G$117,1,2)*輸入與假設!$C$254-(INDEX(各期收支!$D$96:$G$96,1,2)-INDEX(各期收支!$D$54:$G$54,1,2)+評價_DCF與目標價!$C$71))/INDEX(損益!$D$24:$G$24,1,2))/(1+輸入與假設!$C$243)^(2-輸入與假設!$C$275) -> 22.484822 | E96: =MAX(0,((INDEX(損益!$D$22:$G$22,1,3)-INDEX(輸入與假設!$D$117:$G$117,1,3))*$B96+INDEX(輸入與假設!$D$117:$G$117,1,3)*輸入與假設!$C$254-(INDEX(各期收支!$D$96:$G$96,1,3)-INDEX(各期收支!$D$54:$G$54,1,3)+評價_DCF與目標價!$C$71))/INDEX(損益!$D$24:$G$24,1,3))/(1+輸入與假設!$C$243)^(3-輸入與假設!$C$275) -> 29.496965 | F96: =MAX(0,((INDEX(損益!$D$22:$G$22,1,4)-INDEX(輸入與假設!$D$117:$G$117,1,4))*$B96+INDEX(輸入與假設!$D$117:$G$117,1,4)*輸入與假設!$C$254-(INDEX(各期收支!$D$96:$G$96,1,4)-INDEX(各期收支!$D$54:$G$54,1,4)+評價_DCF與目標價!$C$71))/INDEX(損益!$D$24:$G$24,1,4))/(1+輸入與假設!$C$243)^(4-輸入與假設!$C$275) -> 32.168418
A97: 錨定×倍數｜EV/EBITDA 腿｜5.0x | B97: 5 | C97: =MAX(0,((INDEX(損益!$D$22:$G$22,1,1)-INDEX(輸入與假設!$D$117:$G$117,1,1))*$B97+INDEX(輸入與假設!$D$117:$G$117,1,1)*輸入與假設!$C$254-(INDEX(各期收支!$D$96:$G$96,1,1)-INDEX(各期收支!$D$54:$G$54,1,1)+評價_DCF與目標價!$C$71))/INDEX(損益!$D$24:$G$24,1,1))/(1+輸入與假設!$C$243)^(1-輸入與假設!$C$275) -> 6.87692 | D97: =MAX(0,((INDEX(損益!$D$22:$G$22,1,2)-INDEX(輸入與假設!$D$117:$G$117,1,2))*$B97+INDEX(輸入與假設!$D$117:$G$117,1,2)*輸入與假設!$C$254-(INDEX(各期收支!$D$96:$G$96,1,2)-INDEX(各期收支!$D$54:$G$54,1,2)+評價_DCF與目標價!$C$71))/INDEX(損益!$D$24:$G$24,1,2))/(1+輸入與假設!$C$243)^(2-輸入與假設!$C$275) -> 22.502186 | E97: =MAX(0,((INDEX(損益!$D$22:$G$22,1,3)-INDEX(輸入與假設!$D$117:$G$117,1,3))*$B97+INDEX(輸入與假設!$D$117:$G$117,1,3)*輸入與假設!$C$254-(INDEX(各期收支!$D$96:$G$96,1,3)-INDEX(各期收支!$D$54:$G$54,1,3)+評價_DCF與目標價!$C$71))/INDEX(損益!$D$24:$G$24,1,3))/(1+輸入與假設!$C$243)^(3-輸入與假設!$C$275) -> 29.869886 | F97: =MAX(0,((INDEX(損益!$D$22:$G$22,1,4)-INDEX(輸入與假設!$D$117:$G$117,1,4))*$B97+INDEX(輸入與假設!$D$117:$G$117,1,4)*輸入與假設!$C$254-(INDEX(各期收支!$D$96:$G$96,1,4)-INDEX(各期收支!$D$54:$G$54,1,4)+評價_DCF與目標價!$C$71))/INDEX(損益!$D$24:$G$24,1,4))/(1+輸入與假設!$C$243)^(4-輸入與假設!$C$275) -> 32.910917
A98: 錨定×倍數｜EV/EBITDA 腿｜6.0x | B98: 6 | C98: =MAX(0,((INDEX(損益!$D$22:$G$22,1,1)-INDEX(輸入與假設!$D$117:$G$117,1,1))*$B98+INDEX(輸入與假設!$D$117:$G$117,1,1)*輸入與假設!$C$254-(INDEX(各期收支!$D$96:$G$96,1,1)-INDEX(各期收支!$D$54:$G$54,1,1)+評價_DCF與目標價!$C$71))/INDEX(損益!$D$24:$G$24,1,1))/(1+輸入與假設!$C$243)^(1-輸入與假設!$C$275) -> 6.1627001 | D98: =MAX(0,((INDEX(損益!$D$22:$G$22,1,2)-INDEX(輸入與假設!$D$117:$G$117,1,2))*$B98+INDEX(輸入與假設!$D$117:$G$117,1,2)*輸入與假設!$C$254-(INDEX(各期收支!$D$96:$G$96,1,2)-INDEX(各期收支!$D$54:$G$54,1,2)+評價_DCF與目標價!$C$71))/INDEX(損益!$D$24:$G$24,1,2))/(1+輸入與假設!$C$243)^(2-輸入與假設!$C$275) -> 22.536912 | E98: =MAX(0,((INDEX(損益!$D$22:$G$22,1,3)-INDEX(輸入與假設!$D$117:$G$117,1,3))*$B98+INDEX(輸入與假設!$D$117:$G$117,1,3)*輸入與假設!$C$254-(INDEX(各期收支!$D$96:$G$96,1,3)-INDEX(各期收支!$D$54:$G$54,1,3)+評價_DCF與目標價!$C$71))/INDEX(損益!$D$24:$G$24,1,3))/(1+輸入與假設!$C$243)^(3-輸入與假設!$C$275) -> 30.615726 | F98: =MAX(0,((INDEX(損益!$D$22:$G$22,1,4)-INDEX(輸入與假設!$D$117:$G$117,1,4))*$B98+INDEX(輸入與假設!$D$117:$G$117,1,4)*輸入與假設!$C$254-(INDEX(各期收支!$D$96:$G$96,1,4)-INDEX(各期收支!$D$54:$G$54,1,4)+評價_DCF與目標價!$C$71))/INDEX(損益!$D$24:$G$24,1,4))/(1+輸入與假設!$C$243)^(4-輸入與假設!$C$275) -> 34.395917
A99: 錨定×倍數｜EV/EBITDA 腿｜7.0x | B99: 7 | C99: =MAX(0,((INDEX(損益!$D$22:$G$22,1,1)-INDEX(輸入與假設!$D$117:$G$117,1,1))*$B99+INDEX(輸入與假設!$D$117:$G$117,1,1)*輸入與假設!$C$254-(INDEX(各期收支!$D$96:$G$96,1,1)-INDEX(各期收支!$D$54:$G$54,1,1)+評價_DCF與目標價!$C$71))/INDEX(損益!$D$24:$G$24,1,1))/(1+輸入與假設!$C$243)^(1-輸入與假設!$C$275) -> 5.4484802 | D99: =MAX(0,((INDEX(損益!$D$22:$G$22,1,2)-INDEX(輸入與假設!$D$117:$G$117,1,2))*$B99+INDEX(輸入與假設!$D$117:$G$117,1,2)*輸入與假設!$C$254-(INDEX(各期收支!$D$96:$G$96,1,2)-INDEX(各期收支!$D$54:$G$54,1,2)+評價_DCF與目標價!$C$71))/INDEX(損益!$D$24:$G$24,1,2))/(1+輸入與假設!$C$243)^(2-輸入與假設!$C$275) -> 22.571639 | E99: =MAX(0,((INDEX(損益!$D$22:$G$22,1,3)-INDEX(輸入與假設!$D$117:$G$117,1,3))*$B99+INDEX(輸入與假設!$D$117:$G$117,1,3)*輸入與假設!$C$254-(INDEX(各期收支!$D$96:$G$96,1,3)-INDEX(各期收支!$D$54:$G$54,1,3)+評價_DCF與目標價!$C$71))/INDEX(損益!$D$24:$G$24,1,3))/(1+輸入與假設!$C$243)^(3-輸入與假設!$C$275) -> 31.361566 | F99: =MAX(0,((INDEX(損益!$D$22:$G$22,1,4)-INDEX(輸入與假設!$D$117:$G$117,1,4))*$B99+INDEX(輸入與假設!$D$117:$G$117,1,4)*輸入與假設!$C$254-(INDEX(各期收支!$D$96:$G$96,1,4)-INDEX(各期收支!$D$54:$G$54,1,4)+評價_DCF與目標價!$C$71))/INDEX(損益!$D$24:$G$24,1,4))/(1+輸入與假設!$C$243)^(4-輸入與假設!$C$275) -> 35.880916
A101: 雲端 倍數 ＼ 錨定（加權目標價） | B101: 倍數 | C101: FY27 | D101: FY28 | E101: FY29 | F101: FY30
A102: 錨定×倍數｜加權目標價｜3.4x | B102: 3.4 | C102: =C48*IF(C30=1,0,輸入與假設!$C$256)+C95*IF(C30=1,1,1-輸入與假設!$C$256) -> 4.4108195 | D102: =C48*IF(C30=1,0,輸入與假設!$C$256)+D95*IF(C30=1,1,1-輸入與假設!$C$256) -> 12.345643 | E102: =C48*IF(C30=1,0,輸入與假設!$C$256)+E95*IF(C30=1,1,1-輸入與假設!$C$256) -> 15.772098 | F102: =C48*IF(C30=1,0,輸入與假設!$C$256)+F95*IF(C30=1,1,1-輸入與假設!$C$256) -> 16.794205
A103: 錨定×倍數｜加權目標價｜4.5x | B103: 4.5 | C103: =C48*IF(C30=1,0,輸入與假設!$C$256)+C96*IF(C30=1,1,1-輸入與假設!$C$256) -> 3.9787165 | D103: =C48*IF(C30=1,0,輸入與假設!$C$256)+D96*IF(C30=1,1,1-輸入與假設!$C$256) -> 12.366652 | E103: =C48*IF(C30=1,0,輸入與假設!$C$256)+E96*IF(C30=1,1,1-輸入與假設!$C$256) -> 16.223331 | F103: =C48*IF(C30=1,0,輸入與假設!$C$256)+F96*IF(C30=1,1,1-輸入與假設!$C$256) -> 17.69263
A104: 錨定×倍數｜加權目標價｜5.0x | B104: 5 | C104: =C48*IF(C30=1,0,輸入與假設!$C$256)+C97*IF(C30=1,1,1-輸入與假設!$C$256) -> 3.782306 | D104: =C48*IF(C30=1,0,輸入與假設!$C$256)+D97*IF(C30=1,1,1-輸入與假設!$C$256) -> 12.376202 | E104: =C48*IF(C30=1,0,輸入與假設!$C$256)+E97*IF(C30=1,1,1-輸入與假設!$C$256) -> 16.428437 | F104: =C48*IF(C30=1,0,輸入與假設!$C$256)+F97*IF(C30=1,1,1-輸入與假設!$C$256) -> 18.101004
A105: 錨定×倍數｜加權目標價｜6.0x | B105: 6 | C105: =C48*IF(C30=1,0,輸入與假設!$C$256)+C98*IF(C30=1,1,1-輸入與假設!$C$256) -> 3.3894851 | D105: =C48*IF(C30=1,0,輸入與假設!$C$256)+D98*IF(C30=1,1,1-輸入與假設!$C$256) -> 12.395302 | E105: =C48*IF(C30=1,0,輸入與假設!$C$256)+E98*IF(C30=1,1,1-輸入與假設!$C$256) -> 16.838649 | F105: =C48*IF(C30=1,0,輸入與假設!$C$256)+F98*IF(C30=1,1,1-輸入與假設!$C$256) -> 18.917754
A106: 錨定×倍數｜加權目標價｜7.0x | B106: 7 | C106: =C48*IF(C30=1,0,輸入與假設!$C$256)+C99*IF(C30=1,1,1-輸入與假設!$C$256) -> 2.9966641 | D106: =C48*IF(C30=1,0,輸入與假設!$C$256)+D99*IF(C30=1,1,1-輸入與假設!$C$256) -> 12.414402 | E106: =C48*IF(C30=1,0,輸入與假設!$C$256)+E99*IF(C30=1,1,1-輸入與假設!$C$256) -> 17.248861 | F106: =C48*IF(C30=1,0,輸入與假設!$C$256)+F99*IF(C30=1,1,1-輸入與假設!$C$256) -> 19.734504

Sheet 評價_反向DCF
A1: 反向 DCF — 現價隱含什麼樣的收入與成本
