Workbook

Sheet 導覽
A1: CoreWeave 收支與評價模型 — Excel 版 v4.6（更新 2026-09-25；與 HTML v4.6 同步；市價截至 2026-09-24 收盤）
A3: 這個活頁簿在回答什麼
A4: 一句話：CoreWeave 手上 $103.7bn 的合約（RPO）在 2030 年前能變成多少現金，而同一段時間要付出多少現金——
A5: 差額就是必須向外籌措的金額。所有分頁用同一組數字，改任何一個輸入，後面全部會跟著動。
A7: 分頁結構（依模組分組，分頁標籤顏色相同者為同一模組）
A8: 摘要 一頁摘要：結論、與市場共識的差異、現價隱含什麼、驗證點（v4.3；全部活公式）。
A9: 輸入與假設 所有可調參數（A 情境 → B 產能與收入 → C 利潤率 → D 支出 → E 融資 → F 評價 → G 1H 實際 → H 情境區間運算表 → I 市場共識 → J 季度追蹤輸入）。
A10: 各期收支 類現金流量：來源、用途、融資前缺口、期前融資瀑布。
A11: 季度追蹤 焦點季的模型／共識／指引／實際與差距（v4.4；由年度模型拆分，只用於追蹤；實際數填在輸入與假設 J 區）。
A12: 運營_產能與收入 合約排程 vs 機房產能 → 收入 → 現金；運營_站點：房東揭露與租金檢驗。
A13: 資產負債_既有債務／新債與新股／租賃承諾 類資產負債表：10-Q 債務明細、每期現金與總債務與股數、租賃承諾。
A14: 損益 類損益表（FY26＝1H 實際＋下半年模型）。
... A83: 舊版的透支利息（借款利息）與扣 NTM 缺口（借款本金）並非重複計費；v2.0 的差別是新債設上限、超出部分改以股權支應。瀑布位於「支出與資金」頁下方。

Sheet 摘要
A1: 一頁摘要 — 結論、與市場的差異、現價隱含什麼、驗證點（全部依輸入連動）
A2: ="模型端＝目前情境：" & CHOOSE(輸入與假設!$C$5,"保守 4.2 GW","基準 5.6 GW","積極 8 GW") & "（預設＝基準）；共識＝data/consensus_crwv_20260925.json（2026-09-25）" -> 模型端＝目前情境：基準 5.6 GW（預設＝基準）；共識＝data/consensus_crwv_20260925.json（2026-09-25）
A4: 1｜結論
A5: 結論｜評等代碼（1＝買進、0＝中立、−1＝賣出） | C5: =評價_DCF與目標價!C57 -> -1
A6: 結論｜評等 | C6: =CHOOSE(C5+2,"賣出","中立","買進") -> 賣出
A7: 結論｜點位（加權目標價） | B7: US$ | C7: =評價_DCF與目標價!C48 -> 29.678472
A8: 結論｜現價 | B8: US$ | C8: =輸入與假設!$C$165 -> 90.13
A9: 結論｜空間 | B9: % | C9: =C7/C8-1 -> -0.67071483
A10: 結論｜情境區間（下緣／上緣） | B10: US$ | C10: =評價_DCF與目標價!C62 -> 19.94892 | D10: =評價_DCF與目標價!D62 -> 43.992773
A11: 結論｜方法區間（下緣／上緣） | B11: US$ | C11: =評價_DCF與目標價!C64 -> 15.210032 | D11: =評價_DCF與目標價!D64 -> 29.678472
A12: 結論｜賣出門檻價 | B12: US$ | C12: =評價_DCF與目標價!$C$58 -> 76.6105
A13: 結論｜點位 − 賣出門檻 | B13: US$ | C13: =C7-C12 -> -46.932028
A14: 結論｜結論句 | C14: =C6&"：點位 $"&TEXT(C7,"0.0")&"，較現價 $"&TEXT(C8,"0.00")&" "&IF(C9>=0,"高","低")&" "&TEXT(ABS(C9)*100,"0")&"%；情境區間 $"&TEXT(C10,"0.0")&"–$"&TEXT(D10,"0.0")&"，方法區間 $"&TEXT(C11,"0.0")&"–$"&TEXT(D11,"0.0")&"；點位"&IF(C13<0,"低於","高於")&"賣出門檻 $"&TEXT(C12,"0.0")&" 達 $"&TEXT(ABS(C13),"0.0")&"。" -> 賣出：點位 $29.7，較現價 $90.13 低 67%；情境區間 $19.9–$44.0，方法區間 $15.2–$29.7；點位低於賣出門檻 $76.6 達 $46.9。
A15: 結論｜情境判斷句 | C15: =評價_DCF與目標價!C70 -> 情境區間上緣 $44.0 低於現價 $90.13：賣出在三個擴張情境下都成立。
A16: 結論｜每 MW 經濟性句 | C16: ="每 MW（FY27）：年收入 $"&TEXT(每MW經濟性!D8,"0.0")&"m、現金成本 $"&TEXT(每MW經濟性!D16,"0.0")&"m（含租金 $"&TEXT(每MW經濟性!D15,"0.0")&"m）、EBITDA $"&TEXT(每MW經濟性!D17,"0.0")&"m；計費單價為 Tokenomics 經濟持有成本（含廠房資本回收的打平線）$"&TEXT(每MW經濟性!D83,"0.0")&"m 的 "&TEXT(每MW經濟性!D84,"0.00")&" 倍"&IF(每MW經濟性!D84<1,"，未回收全部持有成本","")&"。" -> 每 MW（FY27）：年收入 $10.6m、現金成本 $4.3m（含租金 $1.6m）、EBITDA $6.2m；計費單價為 Tokenomics 經濟持有成本（含廠房資本回收的打平線）$11.6m 的 0.99 倍，未回收全部持有成本。 | I16: 首個完整財年、目前情境；數字取自『每MW經濟性』彙總表與每 MW 收入對照（持有成本＝Tokenomics IF_HoldEcon 世代加權）
A18: 2｜與市場的差異（模型：目前情境 vs 共識；FY26–FY28）
A19: 項目 | B19: 單位 | C19: FY26 | D19: FY27 | E19: FY28
A20: 差異｜營收｜模型 | B20: US$bn | C20: =損益!C26 -> 13.066 | D20: =損益!D26 -> 26.1275 | E20: =損益!E26 -> 36.669415
A21: 差異｜營收｜共識 | B21: US$bn | C21: =輸入與假設!$C$259 -> 12.882 | D21: =輸入與假設!$D$259 -> 26.376 | E21: =輸入與假設!$E$259 -> 42.55
A22: 差異｜營收｜差距 | B22: % | C22: =C20/C21-1 -> 0.014283496 | D22: =D20/D21-1 -> -0.0094214437 | E22: =E20/E21-1 -> -0.1382041
A23: 差異｜調整後 EBITDA｜模型 | B23: US$bn | C23: =輸入與假設!$C$231+損益!C19 -> 7.5256769 | D23: =損益!D31 -> 15.41514 | E23: =損益!E31 -> 22.104113
A24: 差異｜調整後 EBITDA｜共識 | B24: US$bn | C24: =輸入與假設!$C$260 -> 7.574 | D24: =輸入與假設!$D$260 -> 16.656 | E24: =輸入與假設!$E$260 -> 28.857
A25: 差異｜調整後 EBITDA｜差距 | B25: % | C25: =C23/C24-1 -> -0.0063801233 | D25: =D23/D24-1 -> -0.074499284 | E25: =E23/E24-1 -> -0.23401208 | I25: FY26 模型＝1H 實際調整後 EBITDA（輸入與假設 G 區，報導轉述 [Verified]）＋2H 模型
A26: 差異｜調整後 EBITDA｜差距（金額） | B26: US$bn | C26: =C23-C24 -> -0.048323054 | D26: =D23-D24 -> -1.2408601 | E26: =E23-E24 -> -6.7528866 | I26: 與 HTML 一頁摘要、市場共識分頁同一呈現；判斷門檻仍用上一列比例
A27: 差異｜EBITDA 率｜模型 | B27: % | C27: =C23/C20 -> 0.57597405 | D27: =D23/D20 -> 0.58999674 | E27: =E23/E20 -> 0.60279427
A28: 差異｜EBITDA 率｜共識 | B28: % | C28: =輸入與假設!$C$261 -> 0.588 | D28: =輸入與假設!$D$261 -> 0.632 | E28: =輸入與假設!$E$261 -> 0.678
A29: 差異｜EBITDA 率｜差距（百分點） | B29: pt | C29: =C27-C28 -> -0.012025949 | D29: =D27-D28 -> -0.042003256 | E29: =E27-E28 -> -0.075205733 | I29: EBITDA 率以百分點列差距，不納入判斷
A30: 差異｜CapEx（毛額）｜模型 | B30: US$bn | C30: =輸入與假設!$C$215+輸入與假設!C$137 -> 37.800889 | D30: =輸入與假設!D$137 -> 42.299209 | E30: =輸入與假設!E$137 -> 32.512194
A31: 差異｜CapEx（毛額）｜共識 | B31: US$bn | C31: =輸入與假設!$C$266 -> 35.953 | D31: =輸入與假設!$D$266 -> 46.476 | E31: =輸入與假設!$E$266 -> 50.129
A32: 差異｜CapEx（毛額）｜差距 | B32: % | C32: =C30/C31-1 -> 0.051397347 | D32: =D30/D31-1 -> -0.089869851 | E32: =E30/E31-1 -> -0.35142942 | I32: 共識 CapEx 口徑未揭露；FY26＝1H 實際毛額＋2H 模型毛額
A33: 差異｜淨負債｜模型 | B33: US$bn | C33: =資產負債_新債與新股!C22 -> 46.297792 | D33: =資產負債_新債與新股!D22 -> 77.316635 | E33: =資產負債_新債與新股!E22 -> 94.103031
A34: 差異｜淨負債｜共識 | B34: US$bn | C34: =輸入與假設!$C$268 -> 46.442 | D34: =輸入與假設!$D$268 -> 74.707 | E34: =輸入與假設!$E$268 -> 96.039
A35: 差異｜淨負債｜差距 | B35: % | C35: =C33/C34-1 -> -0.003105125 | D35: =D33/D34-1 -> 0.034931597 | E35: =E33/E34-1 -> -0.020158149 | I35: 共識淨負債不含租賃、口徑未揭露：只列不判斷
A36: 差異｜淨負債｜差距（金額） | B36: US$bn | C36: =C33-C34 -> -0.14420822 | D36: =D33-D34 -> 2.6096348 | E36: =E33-E34 -> -1.9359685 | I36: 與 HTML 一頁摘要、市場共識分頁同一呈現；判斷門檻仍用上一列比例
A37: 差異｜分歧項目（超過門檻者） | C37: =MID(IF(ABS(C22)>輸入與假設!$C$301,"、營收 "&IF(C22<0,"−","+")&TEXT(ABS(C22)*100,"0.0")&"%","")&IF(ABS(C25)>輸入與假設!$C$301,"、EBITDA "&IF(C26<0,"−","+")&"$"&TEXT(ABS(C26),"#,##0.00")&"bn"&"／"&IF(C29<0,"−","+")&TEXT(ABS(C29)*100,"0.0")&"pt","")&IF(ABS(C32)>輸入與假設!$C$301,"、CapEx "&IF(C32<0,"−","+")&TEXT(ABS(C32)*100,"0.0")&"%",""),2,999) -> CapEx +5.1% | D37: =MID(IF(ABS(D22)>輸入與假設!$C$301,"、營收 "&IF(D22<0,"−","+")&TEXT(ABS(D22)*100,"0.0")&"%","")&IF(ABS(D25)>輸入與假設!$C$301,"、EBITDA "&IF(D26<0,"−","+")&"$"&TEXT(ABS(D26),"#,##0.00")&"bn"&"／"&IF(D29<0,"−","+")&TEXT(ABS(D29)*100,"0.0")&"pt","")&IF(ABS(D32)>輸入與假設!$C$301,"、CapEx "&IF(D32<0,"−","+")&TEXT(ABS(D32)*100,"0.0")&"%",""),2,999) -> EBITDA −$1.24bn／−4.2pt、CapEx −9.0% | E37: =MID(IF(ABS(E22)>輸入與假設!$C$301,"、營收 "&IF(E22<0,"−","+")&TEXT(ABS(E22)*100,"0.0")&"%","")&IF(ABS(E25)>輸入與假設!$C$301,"、EBITDA "&IF(E26<0,"−","+")&"$"&TEXT(ABS(E26),"#,##0.00")&"bn"&"／"&IF(E29<0,"−","+")&TEXT(ABS(E29)*100,"0.0")&"pt","")&IF(ABS(E32)>輸入與假設!$C$301,"、CapEx "&IF(E32<0,"−","+")&TEXT(ABS(E32)*100,"0.0")&"%",""),2,999) -> 營收 −13.8%、EBITDA −$6.75bn／−7.5pt、CapEx −35.1% | I37: 營收、EBITDA、CapEx 任一項差距絕對值超過門檻即列出（與 HTML 判斷句同一規則）
A38: 差異｜分歧起始年（1＝FY26…3＝FY28；0＝無） | C38: =IF(C37<>"",1,IF(D37<>"",2,IF(E37<>"",3,0))) -> 1
A39: 差異｜判斷句 | C39: =CHOOSE(C38+1,"FY26–FY28 營收、EBITDA、CapEx 與共識差距皆在 "&IF(ROUND(ABS(輸入與假設!$C$301)*100,4)=INT(ROUND(ABS(輸入與假設!$C$301)*100,4)),TEXT(ROUND(ABS(輸入與假設!$C$301)*100,4),"0"),TEXT(ROUND(ABS(輸入與假設!$C$301)*100,4),"0.0"))&"%"&" 以內。","分歧始於 FY26（"&C37&"）"&"；FY27 "&IF(D37="","回到 "&IF(ROUND(ABS(輸入與假設!$C$301)*100,4)=INT(ROUND(ABS(輸入與假設!$C$301)*100,4)),TEXT(ROUND(ABS(輸入與假設!$C$301)*100,4),"0"),TEXT(ROUND(ABS(輸入與假設!$C$301)*100,4),"0.0"))&"%"&" 以內",D37)&"；FY28 "&IF(E37="","回到 "&IF(ROUND(ABS(輸入與假設!$C$301)*100,4)=INT(ROUND(ABS(輸入與假設!$C$301)*100,4)),TEXT(ROUND(ABS(輸入與假設!$C$301)*100,4),"0"),TEXT(ROUND(ABS(輸入與假設!$C$301)*100,4),"0.0"))&"%"&" 以內",E37)&"。","FY26 營收、EBITDA、CapEx 與共識差距在 "&IF(ROUND(ABS(輸入與假設!$C$301)*100,4)=INT(ROUND(ABS(輸入與假設!$C$301)*100,4)),TEXT(ROUND(ABS(輸入與假設!$C$301)*100,4),"0"),TEXT(ROUND(ABS(輸入與假設!$C$301)*100,4),"0.0"))&"%"&" 以內；分歧始於 FY27（"&D37&"）"&"；FY28 "&IF(E37="","回到 "&IF(ROUND(ABS(輸入與假設!$C$301)*100,4)=INT(ROUND(ABS(輸入與假設!$C$301)*100,4)),TEXT(ROUND(ABS(輸入與假設!$C$301)*100,4),"0"),TEXT(ROUND(ABS(輸入與假設!$C$301)*100,4),"0.0"))&"%"&" 以內",E37)&"。","FY26–FY27 營收、EBITDA、CapEx 與共識差距在 "&IF(ROUND(ABS(輸入與假設!$C$301)*100,4)=INT(ROUND(ABS(輸入與假設!$C$301)*100,4)),TEXT(ROUND(ABS(輸入與假設!$C$301)*100,4),"0"),TEXT(ROUND(ABS(輸入與假設!$C$301)*100,4),"0.0"))&"%"&" 以內；分歧始於 FY28（"&E37&"）。") -> 分歧始於 FY26（CapEx +5.1%）；FY27 EBITDA −$1.24bn／−4.2pt、CapEx −9.0%；FY28 營收 −13.8%、EBITDA −$6.75bn／−7.5pt、CapEx −35.1%。
A40: 差異原因｜FY26｜EBITDA | C40: =IF(ABS(C29)>輸入與假設!$C$302,"觀點","") | D40: =IF(ABS(C29)>輸入與假設!$C$302,"EBITDA 率 "&IF((C27)<0,"−","")&TEXT(ABS((C27))*100,"#,##0.0")&"%"&" 對共識 "&IF((C28)<0,"−","")&TEXT(ABS((C28))*100,"#,##0.0")&"%"&"：模型改為由下而上（Tokenomics 電費與維護 × 平均在役 MW＋管銷率，再扣租金），不含爬坡期閒置產能與未揭露成本；營收差距 "&IF((C22)<0,"−","+")&TEXT(ABS((C22))*100,"#,##0.0")&"%","") | I40: C＝類型、D＝原因（需附原因時顯示；EBITDA 以利潤率差、其餘以比例門檻判斷）
A41: 差異原因｜FY26｜CapEx | C41: =IF(ABS(C32)>輸入與假設!$C$301,"觀點","") -> 觀點 | D41: =IF(ABS(C32)>輸入與假設!$C$301,"CapEx 依新增 MW 計算：新增 "&IF((輸入與假設!C$130)<0,"−","")&TEXT(ABS((輸入與假設!C$130)),"#,##0")&" MW × Tokenomics 每 MW $"&IF((輸入與假設!C$120)<0,"−","")&TEXT(ABS((輸入與假設!C$120)),"#,##0")&"m（IF_CapexIT × 新增世代，含次年預建）；共識口徑未揭露","") -> CapEx 依新增 MW 計算：新增 1,000 MW × Tokenomics 每 MW $35m（IF_CapexIT × 新增世代，含次年預建）；共識口徑未揭露
A42: 差異原因｜FY26｜淨負債 | C42: =IF(ABS(C35)>輸入與假設!$C$301,"觀點","") | D42: =IF(ABS(C35)>輸入與假設!$C$301,"淨負債隨 CapEx 與融資需求而定（模型 CapEx 差距 "&IF((C32)<0,"−","+")&TEXT(ABS((C32))*100,"#,##0.0")&"%"&"）；共識淨負債不含租賃、口徑未揭露","")
A43: 差異原因｜FY27｜EBITDA | C43: =IF(ABS(D29)>輸入與假設!$C$302,"觀點","") -> 觀點 | D43: =IF(ABS(D29)>輸入與假設!$C$302,"EBITDA 率 "&IF((D27)<0,"−","")&TEXT(ABS((D27))*100,"#,##0.0")&"%"&" 對共識 "&IF((D28)<0,"−","")&TEXT(ABS((D28))*100,"#,##0.0")&"%"&"：模型改為由下而上（Tokenomics 電費與維護 × 平均在役 MW＋管銷率，再扣租金），不含爬坡期閒置產能與未揭露成本；營收差距 "&IF((D22)<0,"−","+")&TEXT(ABS((D22))*100,"#,##0.0")&"%","") -> EBITDA 率 59.0% 對共識 63.2%：模型改為由下而上（Tokenomics 電費與維護 × 平均在役 MW＋管銷率，再扣租金），不含爬坡期閒置產能與未揭露成本；營收差距 −0.9%
A44: 差異原因｜FY27｜CapEx | C44: =IF(ABS(D32)>輸入與假設!$C$301,"觀點","") -> 觀點 | D44: =IF(ABS(D32)>輸入與假設!$C$301,"CapEx 依新增 MW 計算：新增 "&IF((輸入與假設!D$130)<0,"−","")&TEXT(ABS((輸入與假設!D$130)),"#,##0")&" MW × 每 MW $"&IF((輸入與假設!D$120)<0,"−","")&TEXT(ABS((輸入與假設!D$120)),"#,##0")&"m（含次年預建）；共識口徑未揭露","") -> CapEx 依新增 MW 計算：新增 1,250 MW × 每 MW $38m（含次年預建）；共識口徑未揭露
A45: 差異原因｜FY27｜淨負債 | C45: =IF(ABS(D35)>輸入與假設!$C$301,"觀點","") | D45: =IF(ABS(D35)>輸入與假設!$C$301,"淨負債隨 CapEx 與融資需求而定（模型 CapEx 差距 "&IF((D32)<0,"−","+")&TEXT(ABS((D32))*100,"#,##0.0")&"%"&"）；共識淨負債不含租賃、口徑未揭露","")
A46: 差異原因｜FY28｜營收 | C46: =IF(ABS(E22)>輸入與假設!$C$301,"觀點","") -> 觀點 | D46: =IF(ABS(E22)>輸入與假設!$C$301,"營收由模型 MW 路徑決定：FY28 年底 Accepted "&IF((輸入與假設!E$26)<0,"−","")&TEXT(ABS((輸入與假設!E$26)),"#,##0")&" MW（目前情境）；共識未揭露 MW 假設","") -> 營收由模型 MW 路徑決定：FY28 年底 Accepted 4,000 MW（目前情境）；共識未揭露 MW 假設
A47: 差異原因｜FY28｜EBITDA | C47: =IF(ABS(E29)>輸入與假設!$C$302,"觀點","") -> 觀點 | D47: =IF(ABS(E29)>輸入與假設!$C$302,"EBITDA 率 "&IF((E27)<0,"−","")&TEXT(ABS((E27))*100,"#,##0.0")&"%"&" 對共識 "&IF((E28)<0,"−","")&TEXT(ABS((E28))*100,"#,##0.0")&"%"&"：模型改為由下而上（Tokenomics 電費與維護 × 平均在役 MW＋管銷率，再扣租金），不含爬坡期閒置產能與未揭露成本；營收差距 "&IF((E22)<0,"−","+")&TEXT(ABS((E22))*100,"#,##0.0")&"%","") -> EBITDA 率 60.3% 對共識 67.8%：模型改為由下而上（Tokenomics 電費與維護 × 平均在役 MW＋管銷率，再扣租金），不含爬坡期閒置產能與未揭露成本；營收差距 −13.8%
A48: 差異原因｜FY28｜CapEx | C48: =IF(ABS(E32)>輸入與假設!$C$301,"觀點","") -> 觀點 | D48: =IF(ABS(E32)>輸入與假設!$C$301,"CapEx 依新增 MW 計算：新增 "&IF((輸入與假設!E$130)<0,"−","")&TEXT(ABS((輸入與假設!E$130)),"#,##0")&" MW × 每 MW $"&IF((輸入與假設!E$120)<0,"−","")&TEXT(ABS((輸入與假設!E$120)),"#,##0")&"m（含次年預建）；共識口徑未揭露","") -> CapEx 依新增 MW 計算：新增 900 MW × 每 MW $38m（含次年預建）；共識口徑未揭露
A49: 差異原因｜FY28｜淨負債 | C49: =IF(ABS(E35)>輸入與假設!$C$301,"觀點","") | D49: =IF(ABS(E35)>輸入與假設!$C$301,"淨負債隨 CapEx 與融資需求而定（模型 CapEx 差距 "&IF((E32)<0,"−","+")&TEXT(ABS((E32))*100,"#,##0.0")&"%"&"）；共識淨負債不含租賃、口徑未揭露","")
A50: 差異｜需附原因項數 | C50: =SUMPRODUCT(--(ABS(C22:E22)>輸入與假設!$C$301))+SUMPRODUCT(--(ABS(C29:E29)>輸入與假設!$C$302))+SUMPRODUCT(--(ABS(C32:E32)>輸入與假設!$C$301))+SUMPRODUCT(--(ABS(C35:E35)>輸入與假設!$C$301)) -> 6 | I50: 營收、EBITDA（利潤率差）、CapEx、淨負債 × FY26–FY28
A51: 差異｜差異原因摘要 | C51: =IF(C50=0,"","需附原因的 "&C50&" 項差距："&MID(IF((COUNTIF(C40,"觀點")+COUNTIF(C41,"觀點")+COUNTIF(C42,"觀點")+COUNTIF(C43,"觀點")+COUNTIF(C44,"觀點")+COUNTIF(C45,"觀點")+COUNTIF(C46,"觀點")+COUNTIF(C47,"觀點")+COUNTIF(C48,"觀點")+COUNTIF(C49,"觀點"))>0,"、觀點 "&(COUNTIF(C40,"觀點")+COUNTIF(C41,"觀點")+COUNTIF(C42,"觀點")+COUNTIF(C43,"觀點")+COUNTIF(C44,"觀點")+COUNTIF(C45,"觀點")+COUNTIF(C46,"觀點")+COUNTIF(C47,"觀點")+COUNTIF(C48,"觀點")+COUNTIF(C49,"觀點"))&" 項","")&IF((COUNTIF(C40,"拆法")+COUNTIF(C41,"拆法")+COUNTIF(C42,"拆法")+COUNTIF(C43,"拆法")+COUNTIF(C44,"拆法")+COUNTIF(C45,"拆法")+COUNTIF(C46,"拆法")+COUNTIF(C47,"拆法")+COUNTIF(C48,"拆法")+COUNTIF(C49,"拆法"))>0,"、拆法 "&(COUNTIF(C40,"拆法")+COUNTIF(C41,"拆法")+COUNTIF(C42,"拆法")+COUNTIF(C43,"拆法")+COUNTIF(C44,"拆法")+COUNTIF(C45,"拆法")+COUNTIF(C46,"拆法")+COUNTIF(C47,"拆法")+COUNTIF(C48,"拆法")+COUNTIF(C49,"拆法"))&" 項","")&IF((COUNTIF(C40,"已知限制")+COUNTIF(C41,"已知限制")+COUNTIF(C42,"已知限制")+COUNTIF(C43,"已知限制")+COUNTIF(C44,"已知限制")+COUNTIF(C45,"已知限制")+COUNTIF(C46,"已知限制")+COUNTIF(C47,"已知限制")+COUNTIF(C48,"已知限制")+COUNTIF(C49,"已知限制"))>0,"、已知限制 "&(COUNTIF(C40,"已知限制")+COUNTIF(C41,"已知限制")+COUNTIF(C42,"已知限制")+COUNTIF(C43,"已知限制")+COUNTIF(C44,"已知限制")+COUNTIF(C45,"已知限制")+COUNTIF(C46,"已知限制")+COUNTIF(C47,"已知限制")+COUNTIF(C48,"已知限制")+COUNTIF(C49,"已知限制"))&" 項","")&IF((C50-((COUNTIF(C40,"觀點")+COUNTIF(C41,"觀點")+COUNTIF(C42,"觀點")+COUNTIF(C43,"觀點")+COUNTIF(C44,"觀點")+COUNTIF(C45,"觀點")+COUNTIF(C46,"觀點")+COUNTIF(C47,"觀點")+COUNTIF(C48,"觀點")+COUNTIF(C49,"觀點"))+(COUNTIF(C40,"拆法")+COUNTIF(C41,"拆法")+COUNTIF(C42,"拆法")+COUNTIF(C43,"拆法")+COUNTIF(C44,"拆法")+COUNTIF(C45,"拆法")+COUNTIF(C46,"拆法")+COUNTIF(C47,"拆法")+COUNTIF(C48,"拆法")+COUNTIF(C49,"拆法"))+(COUNTIF(C40,"已知限制")+COUNTIF(C41,"已知限制")+COUNTIF(C42,"已知限制")+COUNTIF(C43,"已知限制")+COUNTIF(C44,"已知限制")+COUNTIF(C45,"已知限制")+COUNTIF(C46,"已知限制")+COUNTIF(C47,"已知限制")+COUNTIF(C48,"已知限制")+COUNTIF(C49,"已知限制"))))>0,"、未歸類 "&(C50-((COUNTIF(C40,"觀點")+COUNTIF(C41,"觀點")+COUNTIF(C42,"觀點")+COUNTIF(C43,"觀點")+COUNTIF(C44,"觀點")+COUNTIF(C45,"觀點")+COUNTIF(C46,"觀點")+COUNTIF(C47,"觀點")+COUNTIF(C48,"觀點")+COUNTIF(C49,"觀點"))+(COUNTIF(C40,"拆法")+COUNTIF(C41,"拆法")+COUNTIF(C42,"拆法")+COUNTIF(C43,"拆法")+COUNTIF(C44,"拆法")+COUNTIF(C45,"拆法")+COUNTIF(C46,"拆法")+COUNTIF(C47,"拆法")+COUNTIF(C48,"拆法")+COUNTIF(C49,"拆法"))+(COUNTIF(C40,"已知限制")+COUNTIF(C41,"已知限制")+COUNTIF(C42,"已知限制")+COUNTIF(C43,"已知限制")+COUNTIF(C44,"已知限制")+COUNTIF(C45,"已知限制")+COUNTIF(C46,"已知限制")+COUNTIF(C47,"已知限制")+COUNTIF(C48,"已知限制")+COUNTIF(C49,"已知限制"))))&" 項",""),2,999)&"；原因見「損益與評價 → 市場共識」。") -> 需附原因的 6 項差距：觀點 6 項；原因見「損益與評價 → 市場共識」。 | I51: 與 HTML 一頁摘要同一句
A53: 3｜現價隱含什麼
A54: 隱含｜共識平均目標價隱含 FY28 EV/EBITDA | B54: x | C54: =(輸入與假設!$C$242*輸入與假設!$C$166+輸入與假設!$E$268)/輸入與假設!$E$260 -> 6.1924133 | I54: ＝（共識平均目標價 × 股數＋共識 FY28 淨負債）÷ 共識 FY28 調整後 EBITDA
A55: 隱含｜現價隱含 FY28 EV/EBITDA | B55: x | C55: =(輸入與假設!$C$165*輸入與假設!$C$166+輸入與假設!$E$268)/輸入與假設!$E$260 -> 5.1614967 | I55: 同一共識 FY28 數字，價格換成現價
A56: 隱含｜模型方法區間上緣 | B56: x | C56: =MAX(輸入與假設!$C$179,輸入與假設!$C$180) -> 6 | I56: 模型 EV/EBITDA 腿錨定 FY29 並折回 2027-06-30，錨定年度與此不同
A57: 隱含｜隱含倍數句 | C57: ="共識平均目標價 $"&TEXT(輸入與假設!$C$242,"0.00")&" 隱含 FY28 EV/EBITDA "&TEXT(C54,"0.0")&"x，"&IF(ROUND(C54,1)>C56,"高於",IF(ROUND(C54,1)<C56,"低於","等於"))&"模型方法區間上緣 "&IF(C56=INT(C56),TEXT(C56,"0"),TEXT(C56,"0.0"))&"x；現價 $"&TEXT(輸入與假設!$C$165,"0.00")&" 隱含 "&TEXT(C55,"0.0")&"x。" -> 共識平均目標價 $140.81 隱含 FY28 EV/EBITDA 6.2x，高於模型方法區間上緣 6x；現價 $90.13 隱含 5.2x。
A58: 反向 DCF｜FY30 每 MW 年收入（目前／隱含／變動） | C58: =評價_反向DCF!B18 -> 10.5 | D58: =評價_反向DCF!C18 -> 16.7538 | E58: =評價_反向DCF!D18 -> 0.5956 | I58: 快照（預設輸入）：見『評價_反向DCF』；改輸入後請以目標搜尋重算
A59: 反向 DCF｜每 MW 建置成本（目前／隱含／變動） | C59: =評價_反向DCF!B19 -> 37.5864 | D59: =評價_反向DCF!C19 -> 14.8946 | E59: =評價_反向DCF!D19 -> -0.6037
A60: 反向 DCF｜穩態 EBITDA 率（目前／隱含／變動 pt） | C60: =評價_反向DCF!B20 -> 0.5691 | D60: =評價_反向DCF!C20 -> 0.9118 | E60: =評價_反向DCF!D20 -> 0.3427
A61: 反向 DCF｜加權目標價＝現價所需每 MW 年收入（目前／隱含／變動） | C61: =評價_反向DCF!B21 -> 10.5 | D61: =評價_反向DCF!C21 -> 14.1575 | E61: =評價_反向DCF!D21 -> 0.3483
A63: 4｜驗證點與市場看法（賣方與管理層數字標記 Interested-party）
A64: 驗證｜焦點季 | C64: =季度追蹤!C12 -> Q3'26 | I64: 『輸入與假設』J 區選擇；季度層由年度模型拆分，只用於追蹤
A65: 驗證｜營收（模型／共識／指引低／指引高／實際） | B65: US$bn | C65: =季度追蹤!C6 -> 3.6626667 | D65: =季度追蹤!D6 -> 3.541 | E65: =季度追蹤!F6 -> 3.45 | F65: =季度追蹤!G6 -> 3.6 | G65: =季度追蹤!I6 -> 待公布 | I65: 共識、指引為 Interested-party
A66: 驗證｜營收｜句 | C66: =INDEX(季度追蹤!$C$139:$H$139,輸入與假設!$C$307) -> 營收：模型 $3.66bn｜共識 $3.54bn（+3.4%）｜指引 $3.45–3.60bn（中點 +3.9%，高於上緣）〔觀點〕
A67: 驗證｜調整後營業利益（模型／共識／指引低／指引高／實際） | B67: US$bn | C67: =季度追蹤!C9 -> -0.066042019 | D67: =季度追蹤!D9 -> 不適用 | E67: =季度追蹤!F9 -> 0.2 | F67: =季度追蹤!G9 -> 0.26 | G67: =季度追蹤!I9 -> 待公布 | I67: 共識、指引為 Interested-party
A68: 驗證｜調整後營業利益｜句 | C68: =INDEX(季度追蹤!$C$142:$H$142,輸入與假設!$C$307) -> 調整後營業利益：模型 −$0.07bn｜指引 $0.20–0.26bn（中點 −$0.30bn／−8.3pt，低於下緣）〔已知限制〕
A69: 驗證｜CapEx（毛額）（模型／共識／指引低／指引高／實際） | B69: US$bn | C69: =季度追蹤!C10 -> 12.5 | D69: =季度追蹤!D10 -> 不適用 | E69: =季度追蹤!F10 -> 11.5 | F69: =季度追蹤!G10 -> 13.5 | G69: =季度追蹤!I10 -> 待公布 | I69: 共識、指引為 Interested-party
A70: 驗證｜CapEx（毛額）｜句 | C70: =INDEX(季度追蹤!$C$143:$H$143,輸入與假設!$C$307) -> CapEx（毛額）：模型 $12.50bn｜指引 $11.50–13.50bn（中點 +0.0%，區間上半部）
A71: 驗證｜評等分布（強力買進／買進／持有／賣出／強力賣出） | B71: 家 | C71: =輸入與假設!$C$252 -> 21 | D71: =輸入與假設!$C$253 -> 7 | E71: =輸入與假設!$C$254 -> 9 | F71: =輸入與假設!$C$255 -> 1 | G71: =輸入與假設!$C$256 -> 2 | I71: 2026-09，合計 40 家 [Interested-party]
A72: 驗證｜目標價（平均／中位數／最低／最高） | B72: US$ | C72: =輸入與假設!$C$242 -> 140.81 | D72: =輸入與假設!$C$243 -> 140 | E72: =輸入與假設!$C$244 -> 39 | F72: =輸入與假設!$C$245 -> 317 | I72: 40 家；S&P Global Market Intelligence（經 StockAnalysis.com），擷取 2026-09-25 [Interested-party]
A74: 來源獨立性：StockAnalysis.com 與 MarketScreener 的營收預估完全相同（12.882／26.376），兩者皆引用 S&P Global／Capital IQ，屬同一來源的兩個呈現，不是獨立交叉驗證。獨立來源僅有 LSEG（CNBC 引用，日期較舊）。
A75: 共識來源：MarketScreener（S&P Capital IQ／FactSet 共識）、S&P Global Market Intelligence（經 StockAnalysis.com）；擷取 2026-09-25。逐筆來源、日期與標記見『輸入與假設』I 區。

Sheet 輸入與假設
A1: 輸入（依類別排序；點左側 ＋／− 展開或收合。藍字可改；黃底為最關鍵假設）
A2: A 情境 → B 產能與收入 → C 利潤率 → D 支出（CapEx／折舊／租賃／JV）→ E 融資 → F 評價 → G 參考：1H26 實際 → H 情境區間運算表 → I 市場共識 → J 季度追蹤輸入。灰底『▸』為明細子區，預設收合
A4: A｜情境與規模（管理層擴張力道）
A5: 情境選擇（1＝保守 4.2 GW、2＝基準 5.6 GW、3＝積極 8 GW） | C5: 2 | D5: =CHOOSE(C5,"保守 4.2 GW","基準 5.6 GW","積極 8 GW") -> 基準 5.6 GW | I5: 三情境只改變管理層的擴張力道；其餘假設相同。FY26–FY27 三者相同（年底 1,850／3,100 MW），FY28 起分歧
A6: ▸ 情境路徑明細（Accepted MW、爬坡比例、表外租金基準）
A7: Accepted MW 路徑 | B7: 單位 | C7: FY26 | D7: FY27 | E7: FY28 | F7: FY29 | G7: FY30 | I7: FY31 新增 MW
A8: 保守 4.2 GW | B8: MW | C8: 1850 | D8: 3100 | E8: 3800 | F8: 4200 | G8: 4200 | I8: 0 | J8: 只交付已簽約電力 4.2 GW（8/11 法說），不再新簽
A9: 基準 5.6 GW | B9: MW | C9: 1850 | D9: 3100 | E9: 4000 | F9: 4800 | G9: 5600 | I9: 500 | J9: 2027 年後每年約 +800 MW
A10: 積極 8 GW | B10: MW | C10: 1850 | D10: 3100 | E10: 4600 | F10: 6300 | G10: 8000 | I10: 1000 | J10: 公司目標 2030 ≥8 GW
A11: Billable／Accepted 爬坡比例 | B11: % | C11: 0.91891892 | D11: 0.93548387 | E11: 0.93478261 | F11: 0.93650794 | G11: 0.9375 | I11: 三情境共用
A12: 表外現金租金（積極路徑） | B12: US$bn | C12: 0.3 | D12: 1.6 | E12: 3 | F12: 4 | G12: 4.6 | I12: 其他情境依「新增 MW（相對 6/30 的 1,500 MW）」等比例縮放
A13: 表外租金起算 MW | B13: MW | C13: 1500 | I13: 6/30 主動電力；表外租金依超過此值的新增 MW 等比例縮放（company.json → scenarios.leaseRampFloorMw）
A14: B｜產能與收入（RPO、MW、利用率、單價、簽約、信用）
A15: 6/30 RPO | B15: US$bn | C15: 103.7 | I15: 10-Q 103.7（backlog 104.2 含 0.5 其他）[Verified]
A16: Q3 初新增承諾 | B16: US$bn | C16: 25 | I16: 法說「>25」，尚未入 RPO [Interested-party]
A17: 五期認列比例（至 2030 末） | B17: % | C17: 0.84 | I17: 10-Q 桶 41／39／20 線性分攤後五期合計 84% [Derived]
A18: RPO 桶權重合計 | B18: % | C18: 0.84 | I18: 下方權重列的合計，用於歸一化
A19: 2025-12-31 主動電力 | B19: MW | C19: 850 | I19: Q4 2025 法說：年底 >850 MW、43 座資料中心 [Verified]
A20: 6/30 Billable MW | B20: MW | C20: 1350 | I20: 主動電力 1.5 GW 扣爬坡中 [Assumed]
A21: 收入用平均在役 MW（1=是） | C21: 1 | I21: 0＝用期末存量全期化。CRWV 交付後載（6 月 +300MW），建議 1
A22: 每 MW 年收入倍數（整體） | B22: % | C22: 1 | I22: 反向 DCF 與壓力測試用；預設 100%。以『目標搜尋』調整此格即可反解市價隱含單價
A23: 項目 | B23: 單位 | C23: FY26 | D23: FY27 | E23: FY28 | F23: FY29 | G23: FY30 | I23: 來源／標籤
A24: 模型期長度（年） | C24: 0.5 | D24: 1 | E24: 1 | F24: 1 | G24: 1 | I24: 勿改。FY26 模型期為 2026-07-01～12-31（0.5 年）。只用於容量上限、電力、維護三處年率換算 [Derived]
A25: RPO 桶權重 | B25: % | C25: 0.1025 | D25: 0.205 | E25: 0.2 | F25: 0.195 | G25: 0.1375 | H25: =SUM(C25:G25) -> 0.84 | I25: 10-Q 41%／24m、39%／25-48m、20%／49-78m 桶內線性分攤 [Derived]
A26: Accepted MW（期末主動電力） | B26: MW | C26: =CHOOSE(輸入與假設!$C$5,C8,C9,C10) -> 1850 | D26: =CHOOSE(輸入與假設!$C$5,D8,D9,D10) -> 3100 | E26: =CHOOSE(輸入與假設!$C$5,E8,E9,E10) -> 4000 | F26: =CHOOSE(輸入與假設!$C$5,F8,F9,F10) -> 4800 | G26: =CHOOSE(輸入與假設!$C$5,G8,G9,G10) -> 5600 | I26: ＝依 A 區情境選擇器
A27: Billable MW | B27: MW | C27: =ROUND(C26*C11,0) -> 1700 | D27: =ROUND(D26*D11,0) -> 2900 | E27: =ROUND(E26*E11,0) -> 3739 | F27: =ROUND(F26*F11,0) -> 4495 | G27: =ROUND(G26*G11,0) -> 5250 | I27: ＝Accepted × 爬坡比例（A 區）
A28: 利用率 | B28: % | C28: 0.95 | D28: 0.95 | E28: 0.94 | F28: 0.93 | G28: 0.92 | I28: 法說「近期產能實質售罄」，不擬合 100% [Assumed]
A29: 每 MW 年收入 | B29: US$bn/MW | C29: 0.0112 | D29: 0.0115 | E29: 0.0115 | F29: 0.011 | G29: 0.0105 | I29: 期末 ARR 18.5–19.5÷1.85GW≈10.0–10.5M/MW；7 月漲價 25% 只影響新約 [Derived]
A30: 新產能簽約率 | B30: % | C30: 1 | D30: 1 | E30: 0.9 | F30: 0.85 | G30: 0.8 | I30: 未被期初 RPO 占用的產能能賣掉的比例 [Assumed]
A31: 客戶違約率 | B31: % | C31: 0.005 | D31: 0.01 | E31: 0.015 | F31: 0.02 | G31: 0.025 | I31: 前三大客戶 72% 營收的定價，非預測 [Assumed]
A32: 回收率 | B32: % | C32: 0.5 | D32: 0.5 | E32: 0.5 | F32: 0.5 | G32: 0.5 | I32: [Assumed]
A33: 非算力服務營收 | B33: US$bn | C33: 0.3 | D33: 1 | E33: 1.8 | F33: 2.8 | G33: 3.8 | I33: 軟體／儲存／CPU／managed inference；損益營收與資金現金共用 [Derived]
A35: ▸ 世代組合（W2；公司專屬，世代與 Tokenomics 同名；每 MW 資本支出、成本、收入依此加權）
A36: 每 MW 方法（資本支出／營運成本／收入） | C36: tokenomics／bottomUp／legacy | I36: company.json → methodology.perMw（建置時決定公式）：tokenomics｜legacy、bottomUp｜ebitdaPct、gpuHr｜legacy；全為舊方法時與 v4.5 相同
A37: MW 口徑（1＝IT 關鍵電力、2＝設施） | C37: 1 | I37: company.json → meta.mwBasis。Tokenomics 每 GW＝IT 關鍵電力；設施口徑時 IT MW＝設施 MW ÷ IF_FacilityGW（各 Tokenomics 每 MW 值 × 換算係數）[Assumed，見 W1 第 6a 步]
A38: Tokenomics 成本情境（1＝低成本、2＝基準、3＝高成本） | C38: 2 | I38: 模型主值取基準；低／高只作敏感度（每MW經濟性頁「敏感度」）
A39: 世代組合敏感度（0＝基準、1＝Rubin Ultra 版） | C39: 0 | I39: Rubin Ultra 版（FY29–FY30 新增 100% Rubin Ultra）；只作敏感度
A40: GPU 小時價格情境（1＝低、2＝基準、3＝高） | C40: 2 | I40: 只在 revenue=gpuHr 時影響收入；價格讀 company.json → pricing.gpuHr
A41: 期初在役 MW（2026-06-30，世代組合起點） | B41: MW | C41: 1500 | I41: company.json → fleet.openMix.activeMW（最新已申報季末主動電力）[Verified]
A42: 期初在役占比｜Hopper H100 | B42: % | C42: 0.272667 | I42: [Assumed]；W1 第 6b 步（coreweave/data/permw_inputs_20261007.json → fleetMix.openMix）：依年份分層——2024 年底前 360 MW＝Hopper；2025 年新增 490 MW＝GB200 70%／GB300 20%／H200 10%；2026 上半年新增 650 MW＝GB300 85%／GB200 15%。MW 錨點 [Verified]、各層占比 [Assumed]；W1 回報 27／29／43% 為四捨五入（區間 Hopper 24–31%、GB200 20–42%、GB300 30–53%）
A43: 期初在役占比｜GB200 NVL72 | B43: % | C43: 0.293667 | I43: [Assumed]；同上
A44: 期初在役占比｜GB300 NVL72 | B44: % | C44: 0.433666 | I44: [Assumed]；同上
A45: 期初在役占比｜VR200 NVL72 | B45: % | C45: 0 | I45: [Assumed]；同上
A46: 期初在役占比｜Rubin Ultra（MGX NVL 單架，72 GPU） | B46: % | C46: 0 | I46: [Assumed]；同上
A47: 新增 MW 的世代占比 | B47: 單位 | C47: FY26 | D47: FY27 | E47: FY28 | F47: FY29 | G47: FY30 | I47: 來源／標籤
A48: 新增占比（基準）｜Hopper H100 | B48: % | C48: 0 | D48: 0 | E48: 0 | F48: 0 | G48: 0 | I48: 工作單 W2 預設 [Assumed]：2H26 GB300 80%／GB200 20%；FY27 GB300 50%／VR200 50%；FY28–FY30 VR200 100%。W1 第 6b 步：GB300 為 2026 主力、Vera Rubin Q2 2026 才完成首套驗證、Meta 2026-04-09 擴約含首批 Vera Rubin，方向一致
A49: 新增占比（基準）｜GB200 NVL72 | B49: % | C49: 0.2 | D49: 0 | E49: 0 | F49: 0 | G49: 0
A50: 新增占比（基準）｜GB300 NVL72 | B50: % | C50: 0.8 | D50: 0.5 | E50: 0 | F50: 0 | G50: 0
A51: 新增占比（基準）｜VR200 NVL72 | B51: % | C51: 0 | D51: 0.5 | E51: 1 | F51: 1 | G51: 1
A52: 新增占比（基準）｜Rubin Ultra（MGX NVL 單架，72 GPU） | B52: % | C52: 0 | D52: 0 | E52: 0 | F52: 0 | G52: 0
A53: 新增占比（Rubin Ultra 版）｜Hopper H100 | B53: % | C53: 0 | D53: 0 | E53: 0 | F53: 0 | G53: 0 | I53: [Assumed]（只作敏感度）
A54: 新增占比（Rubin Ultra 版）｜GB200 NVL72 | B54: % | C54: 0.2 | D54: 0 | E54: 0 | F54: 0 | G54: 0
A55: 新增占比（Rubin Ultra 版）｜GB300 NVL72 | B55: % | C55: 0.8 | D55: 0.5 | E55: 0 | F55: 0 | G55: 0
A56: 新增占比（Rubin Ultra 版）｜VR200 NVL72 | B56: % | C56: 0 | D56: 0.5 | E56: 1 | F56: 0 | G56: 0
A57: 新增占比（Rubin Ultra 版）｜Rubin Ultra（MGX NVL 單架，72 GPU） | B57: % | C57: 0 | D57: 0 | E57: 0 | F57: 1 | G57: 1
A58: 新增占比（採用）｜Hopper H100 | B58: % | C58: =IF(輸入與假設!$C$39=1,C53,C48) -> 0 | D58: =IF(輸入與假設!$C$39=1,D53,D48) -> 0 | E58: =IF(輸入與假設!$C$39=1,E53,E48) -> 0 | F58: =IF(輸入與假設!$C$39=1,F53,F48) -> 0 | G58: =IF(輸入與假設!$C$39=1,G53,G48) -> 0 | I58: ＝依「世代組合敏感度」選擇基準或 Rubin Ultra 版
A59: 新增占比（採用）｜GB200 NVL72 | B59: % | C59: =IF(輸入與假設!$C$39=1,C54,C49) -> 0.2 | D59: =IF(輸入與假設!$C$39=1,D54,D49) -> 0 | E59: =IF(輸入與假設!$C$39=1,E54,E49) -> 0 | F59: =IF(輸入與假設!$C$39=1,F54,F49) -> 0 | G59: =IF(輸入與假設!$C$39=1,G54,G49) -> 0
A60: 新增占比（採用）｜GB300 NVL72 | B60: % | C60: =IF(輸入與假設!$C$39=1,C55,C50) -> 0.8 | D60: =IF(輸入與假設!$C$39=1,D55,D50) -> 0.5 | E60: =IF(輸入與假設!$C$39=1,E55,E50) -> 0 | F60: =IF(輸入與假設!$C$39=1,F55,F50) -> 0 | G60: =IF(輸入與假設!$C$39=1,G55,G50) -> 0
A61: 新增占比（採用）｜VR200 NVL72 | B61: % | C61: =IF(輸入與假設!$C$39=1,C56,C51) -> 0 | D61: =IF(輸入與假設!$C$39=1,D56,D51) -> 0.5 | E61: =IF(輸入與假設!$C$39=1,E56,E51) -> 1 | F61: =IF(輸入與假設!$C$39=1,F56,F51) -> 1 | G61: =IF(輸入與假設!$C$39=1,G56,G51) -> 1
A62: 新增占比（採用）｜Rubin Ultra（MGX NVL 單架，72 GPU） | B62: % | C62: =IF(輸入與假設!$C$39=1,C57,C52) -> 0 | D62: =IF(輸入與假設!$C$39=1,D57,D52) -> 0 | E62: =IF(輸入與假設!$C$39=1,E57,E52) -> 0 | F62: =IF(輸入與假設!$C$39=1,F57,F52) -> 0 | G62: =IF(輸入與假設!$C$39=1,G57,G52) -> 0
A63: 新增占比合計（須為 100%） | B63: % | C63: =SUM(C58:C62) -> 1 | D63: =SUM(D58:D62) -> 1 | E63: =SUM(E58:E62) -> 1 | F63: =SUM(F58:F62) -> 1 | G63: =SUM(G58:G62) -> 1 | I63: 檢查頁核對
A64: TK 資本與口徑（IT 設備、合計、設施／IT、MW 換算、折舊年限） | B64: 世代 | C64: IT 設備 | D64: 合計 | E64: 設施／IT | F64: MW 換算 | G64: 折舊年限 | I64: US$m／公司 MW（IF_CapexIT、IF_CapexTotal 每 GW＝每 MW 百萬美元，× MW 換算）；設施／IT＝IF_FacilityGW（基準）；MW 換算＝IT 口徑 1、設施口徑 1÷設施／IT；折舊年限＝IF_DeprLifeIT（v5.26 前空白，暫代 D 區 GPU 經濟壽命）
A65: TK 資本與口徑｜Hopper H100 | B65: H100 | C65: =OFFSET(TK_CapexIT_H100,0,輸入與假設!$C$38-2)*F65 -> 27.510214 | D65: =OFFSET(TK_CapexTotal_H100,0,輸入與假設!$C$38-2)*F65 -> 40.180214 | E65: =TK_FacilityGW_H100 -> 1.2 | F65: =IF(輸入與假設!$C$37=2,1/E65,1) -> 1 | G65: =TK_DeprLifeIT_H100 -> 6
A66: TK 資本與口徑｜GB200 NVL72 | B66: GB200 | C66: =OFFSET(TK_CapexIT_GB200,0,輸入與假設!$C$38-2)*F66 -> 24.015174 | D66: =OFFSET(TK_CapexTotal_GB200,0,輸入與假設!$C$38-2)*F66 -> 36.685174 | E66: =TK_FacilityGW_GB200 -> 1.2 | F66: =IF(輸入與假設!$C$37=2,1/E66,1) -> 1 | G66: =TK_DeprLifeIT_GB200 -> 6
A67: TK 資本與口徑｜GB300 NVL72 | B67: GB300 | C67: =OFFSET(TK_CapexIT_GB300,0,輸入與假設!$C$38-2)*F67 -> 37.445504 | D67: =OFFSET(TK_CapexTotal_GB300,0,輸入與假設!$C$38-2)*F67 -> 50.115504 | E67: =TK_FacilityGW_GB300 -> 1.2 | F67: =IF(輸入與假設!$C$37=2,1/E67,1) -> 1 | G67: =TK_DeprLifeIT_GB300 -> 6
A68: TK 資本與口徑｜VR200 NVL72 | B68: VR200 | C68: =OFFSET(TK_CapexIT_VR200,0,輸入與假設!$C$38-2)*F68 -> 37.586352 | D68: =OFFSET(TK_CapexTotal_VR200,0,輸入與假設!$C$38-2)*F68 -> 50.256352 | E68: =TK_FacilityGW_VR200 -> 1.2 | F68: =IF(輸入與假設!$C$37=2,1/E68,1) -> 1 | G68: =TK_DeprLifeIT_VR200 -> 6
A69: TK 資本與口徑｜Rubin Ultra（MGX NVL 單架，72 GPU） | B69: RU | C69: =OFFSET(TK_CapexIT_RU,0,輸入與假設!$C$38-2)*F69 -> 50.08578 | D69: =OFFSET(TK_CapexTotal_RU,0,輸入與假設!$C$38-2)*F69 -> 62.75578 | E69: =TK_FacilityGW_RU -> 1.2 | F69: =IF(輸入與假設!$C$37=2,1/E69,1) -> 1 | G69: =TK_DeprLifeIT_RU -> 6
A70: TK 營運成本（電費、IT 維護、人員軟體、稅險） | B70: 世代 | C70: 電費 | D70: IT 維護 | E70: 人員軟體 | F70: 稅險×IT占比 | I70: US$m／公司 MW／年。電費＝IF_PowerCost（已含平均用電比與 PUE）；IT 維護 IF_MaintIT、人員軟體 IF_StaffSW、稅險 IF_TaxIns × IT 資本占總資本比（v5.26 前空白：IT 維護暫代 C 區『維護成本』、人員軟體與稅險暫代 0）
A71: TK 營運成本｜Hopper H100 | B71: H100 | C71: =OFFSET(TK_PowerCost_H100,0,輸入與假設!$C$38-2)*F65 -> 0.672768 | D71: =OFFSET(TK_MaintIT_H100,0,輸入與假設!$C$38-2)*F65 -> 0.82530642 | E71: =OFFSET(TK_StaffSW_H100,0,輸入與假設!$C$38-2)*F65 -> 0.325 | F71: =OFFSET(TK_TaxIns_H100,0,輸入與假設!$C$38-2)*F65*C65/D65 -> 0.13755107
A72: TK 營運成本｜GB200 NVL72 | B72: GB200 | C72: =OFFSET(TK_PowerCost_GB200,0,輸入與假設!$C$38-2)*F66 -> 0.672768 | D72: =OFFSET(TK_MaintIT_GB200,0,輸入與假設!$C$38-2)*F66 -> 0.72045522 | E72: =OFFSET(TK_StaffSW_GB200,0,輸入與假設!$C$38-2)*F66 -> 0.325 | F72: =OFFSET(TK_TaxIns_GB200,0,輸入與假設!$C$38-2)*F66*C66/D66 -> 0.12007587
A73: TK 營運成本｜GB300 NVL72 | B73: GB300 | C73: =OFFSET(TK_PowerCost_GB300,0,輸入與假設!$C$38-2)*F67 -> 0.672768 | D73: =OFFSET(TK_MaintIT_GB300,0,輸入與假設!$C$38-2)*F67 -> 1.1233651 | E73: =OFFSET(TK_StaffSW_GB300,0,輸入與假設!$C$38-2)*F67 -> 0.325 | F73: =OFFSET(TK_TaxIns_GB300,0,輸入與假設!$C$38-2)*F67*C67/D67 -> 0.18722752
A74: TK 營運成本｜VR200 NVL72 | B74: VR200 | C74: =OFFSET(TK_PowerCost_VR200,0,輸入與假設!$C$38-2)*F68 -> 0.672768 | D74: =OFFSET(TK_MaintIT_VR200,0,輸入與假設!$C$38-2)*F68 -> 1.1275906 | E74: =OFFSET(TK_StaffSW_VR200,0,輸入與假設!$C$38-2)*F68 -> 0.325 | F74: =OFFSET(TK_TaxIns_VR200,0,輸入與假設!$C$38-2)*F68*C68/D68 -> 0.18793176
A75: TK 營運成本｜Rubin Ultra（MGX NVL 單架，72 GPU） | B75: RU | C75: =OFFSET(TK_PowerCost_RU,0,輸入與假設!$C$38-2)*F69 -> 0.672768 | D75: =OFFSET(TK_MaintIT_RU,0,輸入與假設!$C$38-2)*F69 -> 1.5025734 | E75: =OFFSET(TK_StaffSW_RU,0,輸入與假設!$C$38-2)*F69 -> 0.325 | F75: =OFFSET(TK_TaxIns_RU,0,輸入與假設!$C$38-2)*F69*C69/D69 -> 0.2504289
A76: TK 收入參考（GPU 數、GPU 小時持有成本、經濟持有成本、GPU 小時合約價） | B76: 世代 | C76: GPU／MW | D76: GPU 時成本 | E76: 持有成本 | F76: 合約價 | I76: GPU／MW＝IF_GPUsPerGW ÷ 1000 × MW 換算（顆）；GPU 時成本＝IF_GPUhrEcon（US$/GPU-hr，100% 時數、不含利潤）；持有成本＝IF_HoldEcon（US$m／MW／年，含廠房資本回收）；合約價＝company.json → pricing.gpuHr（空白＝不適用）
A77: TK 收入參考｜Hopper H100 | B77: H100 | C77: =TK_GPUsPerGW_H100*F65/1000 -> 718.048 | D77: =OFFSET(TK_GPUhrEcon_H100,0,輸入與假設!$C$38-2) -> 1.6050293 | E77: =OFFSET(TK_HoldEcon_H100,0,輸入與假設!$C$38-2)*F65 -> 10.095795
A78: TK 收入參考｜GB200 NVL72 | B78: GB200 | C78: =TK_GPUsPerGW_GB200*F66/1000 -> 501.768 | D78: =OFFSET(TK_GPUhrEcon_GB200,0,輸入與假設!$C$38-2) -> 2.0864538 | E78: =OFFSET(TK_HoldEcon_GB200,0,輸入與假設!$C$38-2)*F66 -> 9.1709819
A79: TK 收入參考｜GB300 NVL72 | B79: GB300 | C79: =TK_GPUsPerGW_GB300*F67/1000 -> 487.008 | D79: =OFFSET(TK_GPUhrEcon_GB300,0,輸入與假設!$C$38-2) -> 2.9826956 | E79: =OFFSET(TK_HoldEcon_GB300,0,輸入與假設!$C$38-2)*F67 -> 12.724746
A80: TK 收入參考｜VR200 NVL72 | B80: VR200 | C80: =TK_GPUsPerGW_VR200*F68/1000 -> 291.744 | D80: =OFFSET(TK_GPUhrEcon_VR200,0,輸入與假設!$C$38-2) -> 4.9935941 | E80: =OFFSET(TK_HoldEcon_VR200,0,輸入與假設!$C$38-2)*F68 -> 12.762016
A81: TK 收入參考｜Rubin Ultra（MGX NVL 單架，72 GPU） | B81: RU | C81: =TK_GPUsPerGW_RU*F69/1000 -> 194.76 | D81: =OFFSET(TK_GPUhrEcon_RU,0,輸入與假設!$C$38-2) -> 9.4188379 | E81: =OFFSET(TK_HoldEcon_RU,0,輸入與假設!$C$38-2)*F69 -> 16.069457
A83: C｜利潤率（EBITDA 率單一來源；損益與資金共用）
A84: 起始 EBITDA 率（FY26） | B84: % | C84: 0.59 | I84: W2 由下而上模式下不使用（保留為舊方法對照）
A85: 穩態 EBITDA 率（FY30） | B85: % | C85: =每MW經濟性!G71 -> 0.56910658 | I85: W2 由下而上：預設＝由下而上 FY30 EBITDA 率（公式）；改成數值即為 FY30 目標，差額線性分攤到各期（反向 DCF、敏感度用）
A86: 項目 | B86: 單位 | C86: FY26 | D86: FY27 | E86: FY28 | F86: FY29 | G86: FY30 | I86: 來源／標籤
A87: EBITDA 率 | B87: % | C87: =每MW經濟性!C71+(輸入與假設!$C$85-每MW經濟性!$G$71)*0/4 -> 0.57752014 | D87: =每MW經濟性!D71+(輸入與假設!$C$85-每MW經濟性!$G$71)*1/4 -> 0.58999674 | E87: =每MW經濟性!E71+(輸入與假設!$C$85-每MW經濟性!$G$71)*2/4 -> 0.60279427 | F87: =每MW經濟性!F71+(輸入與假設!$C$85-每MW經濟性!$G$71)*3/4 -> 0.59255589 | G87: =每MW經濟性!G71+(輸入與假設!$C$85-每MW經濟性!$G$71)*4/4 -> 0.56910658 | I87: W2 由下而上：＝『每MW經濟性』由下而上 EBITDA 率＋（穩態 − 由下而上 FY30）× 期數 ÷ 4（公式）
A88: 非算力服務現金 | B88: US$bn | C88: =輸入與假設!C$33*運營_產能與收入!C35 -> 0.22103923 | D88: =輸入與假設!D$33*運營_產能與收入!D35 -> 0.74075744 | E88: =輸入與假設!E$33*運營_產能與收入!E35 -> 1.3169843 | F88: =輸入與假設!F$33*運營_產能與收入!F35 -> 1.9977565 | G88: =輸入與假設!G$33*運營_產能與收入!G35 -> 2.6009763 | I88: ＝服務營收 × EBITDAR 率（公式）
A89: ▸ 電力／維護 overlay（預設關閉；EBITDA 已含電費）
A90: 電力／維護 overlay（1=開） | C90: 0 | I90: EBITDA 率已含電費，開啟會重複扣除，僅供壓力測試
A91: 電價 | B91: $/MWh | C91: 60 | D91: 62 | E91: 64 | F91: 66 | G91: 68 | I91: overlay 用 [Assumed]
A92: PUE | C92: 1.25 | D92: 1.24 | E92: 1.22 | F92: 1.2 | G92: 1.2 | I92: overlay 用 [Assumed]
A93: 維護成本 | B93: US$m/MW | C93: 0.15 | D93: 0.15 | E93: 0.16 | F93: 0.16 | G93: 0.17 | I93: overlay 用 [Assumed]
A94: ▸ 由下而上營運成本輸入（W2；最近一季 10-Q，公司專屬）
A95: 最近一季營收 | B95: US$bn | C95: 2.575 | I95: 10-Q 損益表 [Verified]
A96: 最近一季營收成本 | B96: US$bn | C96: 0.879 | I96: 10-Q 損益表 [Verified]
A97: 最近一季技術與基礎設施 | B97: US$bn | C97: 1.507 | I97: 10-Q 損益表；D&A 主要在此列 [Verified]
A98: 最近一季銷售行銷 | B98: US$bn | C98: 0.06 | I98: 10-Q 損益表 [Verified]
A99: 其中 SBC（銷售行銷） | B99: US$bn | C99: 0.012 | I99: 10-Q SBC 附註 [Verified]
A100: 最近一季一般管理 | B100: US$bn | C100: 0.178 | I100: 10-Q 損益表 [Verified]
A101: 其中 SBC（一般管理） | B101: US$bn | C101: 0.084 | I101: 10-Q SBC 附註 [Verified]
A102: 最近一季 D&A 合計 | B102: US$bn | C102: 1.393 | I102: 10-Q 現金流量表（未依列別揭露，視為全在營收成本與技術基礎設施）[Verified]
A103: SBC（營收成本＋技術與基礎設施） | B103: US$bn | C103: 0.069 | I103: 10-Q SBC 附註：技術與基礎設施 0.060＋營收成本 0.009 [Verified]
...

Sheet 各期收支
A1: 支出與資金 — 五層支出、四層來源、現金橋
A2: FY26 欄＝1H 實際（10-Q 現金流量表口徑）＋下半年模型；FY27 以後為純模型。瀑布以「融資前現金」決定需求並直接由各支出列加總，因此沒有循環參照
A4: 項目 | B4: 單位 | C4: FY26 | D4: FY27 | E4: FY28 | F4: FY29 | G4: FY30 | I4: 公式／來源說明
A5: 支出（五層）
A6: ① 毛 CapEx（認列，備忘） | B6: US$bn | C6: =輸入與假設!$C$215+輸入與假設!C$137 -> 37.800889 | D6: =輸入與假設!D$137 -> 42.299209 | E6: =輸入與假設!E$137 -> 32.512194 | F6: =輸入與假設!F$137 -> 33.827717 | G6: =輸入與假設!G$137 -> 35.894966 | I6: FY26＝1H 實際認列 16.139＋2H 模型；對照公司全年指引 35–39。備忘列：用途合計採現金口徑，不用這一列
A7: 客戶預付率 | B7: % | C7: =輸入與假設!C$122 -> 0.08 | D7: =輸入與假設!D$122 -> 0.08 | E7: =輸入與假設!E$122 -> 0.08 | F7: =輸入與假設!F$122 -> 0.08 | G7: =輸入與假設!G$122 -> 0.08
A8: 客戶預付金額（抵減，2H 起） | B8: US$bn | C8: =輸入與假設!C$137*C7 -> 1.7329511 | D8: =輸入與假設!D$137*D7 -> 3.3839367 | E8: =輸入與假設!E$137*E7 -> 2.6009756 | F8: =輸入與假設!F$137*F7 -> 2.7062173 | G8: =輸入與假設!G$137*G7 -> 2.8715973 | I8: 1H 的預付已含在實際 CFO 內，不重複計入
A9: ① CapEx（用途用：1H 現金／2H 毛額） | B9: US$bn | C9: =輸入與假設!$C$214+輸入與假設!C$137 -> 35.778889 | D9: =輸入與假設!D$137 -> 42.299209 | E9: =輸入與假設!E$137 -> 32.512194 | F9: =輸入與假設!F$137 -> 33.827717 | G9: =輸入與假設!G$137 -> 35.894966 | I9: 1H 採現金流量表的現金購置 14.117；2H 起採毛額，客戶預付在來源端抵回（避免重複計入）
A10: ② 在帳現金租金（備忘，1H 已含在 CFO） | B10: US$bn | C10: =輸入與假設!C$123 -> 1.04 | D10: =輸入與假設!D$123 -> 2.339 | E10: =輸入與假設!E$123 -> 2.306 | F10: =輸入與假設!F$123 -> 2.373 | G10: =輸入與假設!G$123 -> 2.289 | I10: 見『租賃與承諾』頁；2030 後尚有 19.023。FY26 欄僅 2H：1H 租金 0.748 已含在實際 CFO 內
A11: ② 表外現金租金（未起租） | B11: US$bn | C11: =輸入與假設!C$124 -> 0.3 | D11: =輸入與假設!D$124 -> 1.6 | E11: =輸入與假設!E$124 -> 2.4193548 | F11: =輸入與假設!F$124 -> 2.75 | G11: =輸入與假設!G$124 -> 2.9015385 | I11: 未起租 35.5＋單站上限 14.7＋355MW 造價計租的現金路徑
A12: 租金合計 | B12: US$bn | C12: =C10+C11 -> 1.34 | D12: =D10+D11 -> 3.939 | E12: =E10+E11 -> 4.7253548 | F12: =F10+F11 -> 5.123 | G12: =G10+G11 -> 5.1905385
A13: ③ 存量債務利息（備忘，1H 已含在 CFO） | B13: US$bn | C13: =輸入與假設!C$162 -> 1.8058963 | D13: =輸入與假設!D$162 -> 2.4660068 | E13: =輸入與假設!E$162 -> 2.0200947 | F13: =輸入與假設!F$162 -> 1.7324815 | G13: =輸入與假設!G$162 -> 1.4951385 | I13: ="6/30 債務餘額的利息。FY26 全年利息＝1H 實際 1.176＋2H "&TEXT(C13,"0.0")&"＝"&TEXT(1.176+C13,"0.00")&"（見下方備忘）" -> 6/30 債務餘額的利息。FY26 全年利息＝1H 實際 1.176＋2H 1.8＝2.98（見下方備忘）
A14: 期初累積現金 | B14: US$bn | C14: =輸入與假設!$C$212 -> 3.127 | D14: =C41 -> 2 | E14: =D41 -> 2 | F14: =E41 -> 2 | G14: =F41 -> 2 | I14: FY26 自 2025-12-31 的 3.127 起算；之後＝前期期末累積現金
A15: 新債利率 | B15: % | C15: =IF(輸入與假設!$C$156=1,輸入與假設!C$161+MAX(0,輸入與假設!$C$155-450)/100*0.004,輸入與假設!C$161) -> 0.09 | D15: =IF(輸入與假設!$C$156=1,輸入與假設!D$161+MAX(0,輸入與假設!$C$155-450)/100*0.004,輸入與假設!D$161) -> 0.09 | E15: =IF(輸入與假設!$C$156=1,輸入與假設!E$161+MAX(0,輸入與假設!$C$155-450)/100*0.004,輸入與假設!E$161) -> 0.09 | F15: =IF(輸入與假設!$C$156=1,輸入與假設!F$161+MAX(0,輸入與假設!$C$155-450)/100*0.004,輸入與假設!F$161) -> 0.09 | G15: =IF(輸入與假設!$C$156=1,輸入與假設!G$161+MAX(0,輸入與假設!$C$155-450)/100*0.004,輸入與假設!G$161) -> 0.09 | I15: CDS 開關：＋MAX(0,CDS−450)×0.4bp/bp
A16: ③ 新債利息（瀑布） | B16: US$bn | C16: =C63 -> 0.60569063 | D16: =D63 -> 4.5596371 | E16: =E63 -> 6.4678528 | F16: =F63 -> 7.3610235 | G16: =G63 -> 8.6350905 | I16: ＝新債利率×期間長度×(期初新債＋本期舉借)；見下方「期前融資瀑布」
A17: 利息合計 | B17: US$bn | C17: =C13+C16 -> 2.4115869 | D17: =D13+D16 -> 7.0256439 | E17: =E13+E16 -> 8.4879476 | F17: =F13+F16 -> 9.093505 | G17: =G13+G16 -> 10.130229
A18: ④ JV／策略投資出資 | B18: US$bn | C18: =輸入與假設!$C$216+輸入與假設!C$127 -> 1.938 | D18: =輸入與假設!D$127 -> 0.4 | E18: =輸入與假設!E$127 -> 0.3 | F18: =輸入與假設!F$127 -> 0.2 | G18: =輸入與假設!G$127 -> 0.2 | I18: FY26＝1H 實際 0.688（JV 0.550＋策略投資 0.138）＋2H 模型。10-Q 已承諾 1.7bn。CRWV 不發股息
A19: 電力（overlay） | B19: US$bn | C19: =0 -> 0 | D19: =0 -> 0 | E19: =0 -> 0 | F19: =0 -> 0 | G19: =0 -> 0 | I19: W2 由下而上：電費與維護已含在營運成本，overlay 自動停用（避免重複扣）
A20: 維護（overlay） | B20: US$bn | C20: =0 -> 0 | D20: =0 -> 0 | E20: =0 -> 0 | F20: =0 -> 0 | G20: =0 -> 0
A21: ⑤ 排程還本（10-Q 本金表） | B21: US$bn | C21: =輸入與假設!$C$218+IF(輸入與假設!$C$146=1,輸入與假設!C$160,0) -> 9.632 | D21: =IF(輸入與假設!$C$146=1,輸入與假設!D$160,0) -> 6.184 | E21: =IF(輸入與假設!$C$146=1,輸入與假設!E$160,0) -> 4.416 | F21: =IF(輸入與假設!$C$146=1,輸入與假設!F$160,0) -> 2.421 | G21: =IF(輸入與假設!$C$146=1,輸入與假設!G$160,0) -> 3.221 | I21: FY26＝1H 實際還款 5.219＋2H 到期表 4.413
A22: ⑥ capped call 支出（1H 實際） | B22: US$bn | C22: =輸入與假設!$C$219 -> 0.492 | D22: =0 -> 0 | E22: =0 -> 0 | F22: =0 -> 0 | G22: =0 -> 0 | I22: Q2 4.0bn 可轉債的 capped call 現金支出
A23: 用途合計（現金口徑） | B23: US$bn | C23: =C9+C12+C17+C18+C19+C20+C21+C22 -> 51.592476 | D23: =D9+D12+D17+D18+D19+D20+D21+D22 -> 59.847853 | E23: =E9+E12+E17+E18+E19+E20+E21+E22 -> 50.441497 | F23: =F9+F12+F17+F18+F19+F20+F21+F22 -> 50.665222 | G23: =G9+G12+G17+G18+G19+G20+G21+G22 -> 54.636734 | I23: FY26 的 1H 部分採 10-Q 現金流量表口徑（現金購置、還款、JV、capped call）；1H 的利息與租金已含在 CFO 內，不重複列
A24: 來源（四層）
A25: Ⓐ0 1H26 實際營運現金流（CFO） | B25: US$bn | C25: =輸入與假設!$C$213 -> 3.663 | D25: =0 -> 0 | E25: =0 -> 0 | F25: =0 -> 0 | G25: =0 -> 0 | I25: 10-Q 實際值，取代模型推算；已含 1H 的利息、租金與客戶預付
A26: Ⓐ RPO 現金（2H 起） | B26: US$bn | C26: =運營_產能與收入!C36 -> 5.9626936 | D26: =運營_產能與收入!D36 -> 18.520316 | E26: =運營_產能與收入!E36 -> 18.691628 | F26: =運營_產能與收入!F36 -> 17.726903 | G26: =運營_產能與收入!G36 -> 11.961101
A27: Ⓑ 新簽約現金 | B27: US$bn | C27: =運營_產能與收入!C37 -> 0 | D27: =運營_產能與收入!D37 -> 0 | E27: =運營_產能與收入!E37 -> 6.6295121 | F27: =運營_產能與收入!F37 -> 10.219006 | G27: =運營_產能與收入!G37 -> 15.882354
A28: Ⓒ 非算力服務現金 | B28: US$bn | C28: =輸入與假設!C$88 -> 0.22103923 | D28: =輸入與假設!D$88 -> 0.74075744 | E28: =輸入與假設!E$88 -> 1.3169843 | F28: =輸入與假設!F$88 -> 1.9977565 | G28: =輸入與假設!G$88 -> 2.6009763
A29: Ⓓ 客戶預付（2H 起） | B29: US$bn | C29: =C8 -> 1.7329511 | D29: =D8 -> 3.3839367 | E29: =E8 -> 2.6009756 | F29: =F8 -> 2.7062173 | G29: =G8 -> 2.8715973
A30: 營運來源合計 | B30: US$bn | C30: =C25+C26+C27+C28+C29 -> 11.579684 | D30: =D25+D26+D27+D28+D29 -> 22.64501 | E30: =E25+E26+E27+E28+E29 -> 29.2391 | F30: =F25+F26+F27+F28+F29 -> 32.649884 | G30: =G25+G26+G27+G28+G29 -> 33.316029
A31: Ⓔ 股權／可轉債（融資） | B31: US$bn | C31: =輸入與假設!$C$220+IF(輸入與假設!$C$143=1,輸入與假設!$C$142,0) -> 9.182 | D31: =0 -> 0 | E31: =0 -> 0 | F31: =0 -> 0 | G31: =0 -> 0 | I31: FY26＝1H 私募股權 2.982＋2H 可轉債淨現金 3.2＋ATM 上限 3.0
A32: Ⓕ 1H26 實際借款（融資） | B32: US$bn | C32: =輸入與假設!$C$217 -> 16.747 | D32: =0 -> 0 | E32: =0 -> 0 | F32: =0 -> 0 | G32: =0 -> 0 | I32: 10-Q：H1 借款 16.747。1H 的缺口實際上就是靠舉債填補的
A33: Ⓖ 瀑布：新債（額度＋資產層） | B33: US$bn | C33: =C58 -> 13.459792 | D33: =D58 -> 37.202843 | E33: =E58 -> 21.202397 | F33: =F58 -> 0 | G33: =G58 -> 0.52492452 | I33: 見下方「期前融資瀑布」
A34: Ⓗ 瀑布：股權募資 | B34: US$bn | C34: =C61 -> 0 | D34: =D61 -> 0 | E34: =E61 -> 0 | F34: =F61 -> 10.572249 | G34: =G61 -> 10.572249 | I34: 債務用罄後的殘差；每年不超過股權吸收上限
A35: Ⓘ 瀑布：高息債（股權上限溢出） | B35: US$bn | C35: =C62 -> 0 | D35: =D62 -> 0 | E35: =E62 -> 0 | F35: =F62 -> 7.4430893 | G35: =G62 -> 10.223531 | I35: 股權超過每年上限的部分；不受 backlog 上限約束
A36: 總來源（含融資） | B36: US$bn | C36: =C30+C31+C32+C33+C34+C35 -> 50.968476 | D36: =D30+D31+D32+D33+D34+D35 -> 59.847853 | E36: =E30+E31+E32+E33+E34+E35 -> 50.441497 | F36: =F30+F31+F32+F33+F34+F35 -> 50.665222 | G36: =G30+G31+G32+G33+G34+G35 -> 54.636734
A37: 缺口與現金橋
A38: 1H 其他／受限現金調節 | B38: US$bn | C38: =輸入與假設!$C$141-(輸入與假設!$C$212+輸入與假設!$C$213+輸入與假設!$C$217+輸入與假設!$C$220-輸入與假設!$C$214-輸入與假設!$C$216-輸入與假設!$C$218-輸入與假設!$C$219) -> -0.503 | D38: =0 -> 0 | E38: =0 -> 0 | F38: =0 -> 0 | G38: =0 -> 0 | I38: 使 1H 實際流量接回 6/30 現金餘額；差額來自受限現金重分類與未逐項列出的項目
A39: 營運缺口（不含融資、不含還本） | B39: US$bn | C39: =C30-(C23-C21-C22) -> -29.888792 | D39: =D30-(D23-D21-D22) -> -31.018843 | E39: =E30-(E23-E21-E22) -> -16.786397 | F39: =F30-(F23-F21-F22) -> -15.594338 | G39: =G30-(G23-G21-G22) -> -18.099705 | I39: 本業能不能自給：營運來源 −（用途 − 排程還本 − capped call）
A40: 期間缺口（含融資） | B40: US$bn | C40: =C36-C23+C38 -> -1.127 | D40: =D36-D23+D38 -> 0 | E40: =E36-E23+E38 -> 0 | F40: =F36-F23+F38 -> 0 | G40: =G36-G23+G38 -> 0
A41: 期末累積現金 | B41: US$bn | C41: =C14+C40 -> 2 | D41: =D14+D40 -> 2 | E41: =E14+E40 -> 2 | F41: =F14+F40 -> 2 | G41: =G14+G40 -> 2 | I41: 期前融資：每期末不低於最低現金
A43: 期前融資瀑布（缺口在需要前一期先融好：額度 → 資產層新債 → 股權）
A44: 用途（不含新債利息） | B44: US$bn | C44: =C9+C12+C13+C18+C19+C20+C21+C22 -> 50.986785 | D44: =D9+D12+D13+D18+D19+D20+D21+D22 -> 55.288216 | E44: =E9+E12+E13+E18+E19+E20+E21+E22 -> 43.973644 | F44: =F9+F12+F13+F18+F19+F20+F21+F22 -> 43.304198 | G44: =G9+G12+G13+G18+G19+G20+G21+G22 -> 46.001643 | I44: 避免循環參照：直接由各支出列加總
A45: 新債期初餘額 | B45: US$bn | C45: =0 -> 0 | D45: =C67 -> 13.459792 | E45: =D67 -> 50.662635 | F45: =E67 -> 71.865031 | G45: =F67 -> 71.865031
A46: 新債利率 × 期間長度 | B46: % | C46: =C15*運營_產能與收入!C7 -> 0.045 | D46: =D15*運營_產能與收入!D7 -> 0.09 | E46: =E15*運營_產能與收入!E7 -> 0.09 | F46: =F15*運營_產能與收入!F7 -> 0.09 | G46: =G15*運營_產能與收入!G7 -> 0.09
A47: 高息債期初餘額 | B47: US$bn | C47: =0 -> 0 | D47: =C69 -> 0 | E47: =D69 -> 0 | F47: =E69 -> 0 | G47: =F69 -> 7.4430893
A48: 高息債利率 × 期間長度 | B48: % | C48: =(輸入與假設!$C$154+IF(輸入與假設!$C$156=1,MAX(0,輸入與假設!$C$155-輸入與假設!$C$157)/10000*輸入與假設!$C$158,0))*運營_產能與收入!C7 -> 0.06 | D48: =(輸入與假設!$C$154+IF(輸入與假設!$C$156=1,MAX(0,輸入與假設!$C$155-輸入與假設!$C$157)/10000*輸入與假設!$C$158,0))*運營_產能與收入!D7 -> 0.12 | E48: =(輸入與假設!$C$154+IF(輸入與假設!$C$156=1,MAX(0,輸入與假設!$C$155-輸入與假設!$C$157)/10000*輸入與假設!$C$158,0))*運營_產能與收入!E7 -> 0.12 | F48: =(輸入與假設!$C$154+IF(輸入與假設!$C$156=1,MAX(0,輸入與假設!$C$155-輸入與假設!$C$157)/10000*輸入與假設!$C$158,0))*運營_產能與收入!F7 -> 0.12 | G48: =(輸入與假設!$C$154+IF(輸入與假設!$C$156=1,MAX(0,輸入與假設!$C$155-輸入與假設!$C$157)/10000*輸入與假設!$C$158,0))*運營_產能與收入!G7 -> 0.12
A49: 融資前現金（扣既有新債利息） | B49: US$bn | C49: =C14+C30+C31+C32+C38-C44-C46*C45-C48*C47 -> -10.854101 | D49: =D14+D30+D31+D32+D38-D44-D46*D45-D48*D47 -> -31.854587 | E49: =E14+E30+E31+E32+E38-E44-E46*E45-E48*E47 -> -17.294181 | F49: =F14+F30+F31+F32+F38-F44-F46*F45-F48*F47 -> -15.122168 | G49: =G14+G30+G31+G32+G38-G44-G46*G45-G48*G47 -> -18.046638
A50: 融資需求（補足至最低現金） | B50: US$bn | C50: =MAX(0,輸入與假設!$C$149-C49) -> 12.854101 | D50: =MAX(0,輸入與假設!$C$149-D49) -> 33.854587 | E50: =MAX(0,輸入與假設!$C$149-E49) -> 19.294181 | F50: =MAX(0,輸入與假設!$C$149-F49) -> 17.122168 | G50: =MAX(0,輸入與假設!$C$149-G49) -> 20.046638
A51: 期初 backlog | B51: US$bn | C51: =輸入與假設!$C$15+輸入與假設!$C$16 -> 128.7 | D51: =C53 -> 115.50825 | E51: =D53 -> 89.12475 | F51: =E53 -> 99.902412 | G51: =F53 -> 87.028228 | I51: FY26 期初＝6/30 RPO 103.7＋Q3 新增 25
A52: 新簽合約增量（年化增量×年期） | B52: US$bn | C52: =MAX(0,運營_產能與收入!C23/運營_產能與收入!C7-0)*輸入與假設!$C$148 -> 0 | D52: =MAX(0,運營_產能與收入!D23/運營_產能與收入!D7-運營_產能與收入!C23/運營_產能與收入!C7)*輸入與假設!$C$148 -> 0 | E52: =MAX(0,運營_產能與收入!E23/運營_產能與收入!E7-運營_產能與收入!D23/運營_產能與收入!D7)*輸入與假設!$C$148 -> 45.647078 | F52: =MAX(0,運營_產能與收入!F23/運營_產能與收入!F7-運營_產能與收入!E23/運營_產能與收入!E7)*輸入與假設!$C$148 -> 26.689665 | G52: =MAX(0,運營_產能與收入!G23/運營_產能與收入!G7-運營_產能與收入!F23/運營_產能與收入!F7)*輸入與假設!$C$148 -> 45.151657
A53: 期末 backlog | B53: US$bn | C53: =C51-運營_產能與收入!C17-運營_產能與收入!C23+C52 -> 115.50825 | D53: =D51-運營_產能與收入!D17-運營_產能與收入!D23+D52 -> 89.12475 | E53: =E51-運營_產能與收入!E17-運營_產能與收入!E23+E52 -> 99.902412 | F53: =F51-運營_產能與收入!F17-運營_產能與收入!F23+F52 -> 87.028228 | G53: =G51-運營_產能與收入!G17-運營_產能與收入!G23+G52 -> 90.985956 | I53: ＝期初 − 排程認列 − 新簽約認列 ＋ 新簽合約增量
A54: 既有債務＋9/17 可轉債（期末） | B54: US$bn | C54: =IF(輸入與假設!$C$146=1,資產負債_既有債務!C30,35.551)+3.7 -> 34.838 | D54: =IF(輸入與假設!$C$146=1,資產負債_既有債務!D30,35.551)+3.7 -> 28.654 | E54: =IF(輸入與假設!$C$146=1,資產負債_既有債務!E30,35.551)+3.7 -> 24.238 | F54: =IF(輸入與假設!$C$146=1,資產負債_既有債務!F30,35.551)+3.7 -> 21.817 | G54: =IF(輸入與假設!$C$146=1,資產負債_既有債務!G30,35.551)+3.7 -> 18.596 | I54: ＝(依到期表遞減的既有本金，若關閉攤還則維持 35.551)＋9/17 可轉債 3.7
A55: 債務上限（債務／backlog × 期末 backlog） | B55: US$bn | C55: =輸入與假設!$C$147*C53 -> 115.50825 | D55: =輸入與假設!$C$147*D53 -> 89.12475 | E55: =輸入與假設!$C$147*E53 -> 99.902412 | F55: =輸入與假設!$C$147*F53 -> 87.028228 | G55: =輸入與假設!$C$147*G53 -> 90.985956
A56: 未動用額度（期初） | B56: US$bn | C56: =IF(輸入與假設!$C$145=1,輸入與假設!$C$144,0) -> 10 | D56: =C68 -> 0 | E56: =D68 -> 0 | F56: =E68 -> 0 | G56: =F68 -> 0
A57: 新債可借上限 | B57: US$bn | C57: =MAX(0,C55-(C54+C45),C56) -> 80.67025 | D57: =MAX(0,D55-(D54+D45),D56) -> 47.010958 | E57: =MAX(0,E55-(E54+E45),E56) -> 25.001777 | F57: =MAX(0,F55-(F54+F45),F56) -> 0 | G57: =MAX(0,G55-(G54+G45),G56) -> 0.52492452 | I57: ＝MAX(上限 − 既有債務 − 期初新債, 未動用額度)
A58: 新債舉借 | B58: US$bn | C58: =MIN(C57,C50/(1-C46)) -> 13.459792 | D58: =MIN(D57,D50/(1-D46)) -> 37.202843 | E58: =MIN(E57,E50/(1-E46)) -> 21.202397 | F58: =MIN(F57,F50/(1-F46)) -> 0 | G58: =MIN(G57,G50/(1-G46)) -> 0.52492452 | I58: 期前融資：期初到位，當期全額計息，所以需求要除以 (1−利率×期間)
A59: 債務後剩餘需求 | B59: US$bn | C59: =MAX(0,C50+C46*C58-C58) -> 0 | D59: =MAX(0,D50+D46*D58-D58) -> 0 | E59: =MAX(0,E50+E46*E58-E58) -> 0 | F59: =MAX(0,F50+F46*F58-F58) -> 17.122168 | G59: =MAX(0,G50+G46*G58-G58) -> 19.568957
A60: 每年股權吸收上限 | B60: US$bn | C60: =IF(輸入與假設!$C$152>=9,1E+099,輸入與假設!$C$152*輸入與假設!$C$150*輸入與假設!$C$153*運營_產能與收入!C7) -> 5.2861245 | D60: =IF(輸入與假設!$C$152>=9,1E+099,輸入與假設!$C$152*輸入與假設!$C$150*輸入與假設!$C$153*運營_產能與收入!D7) -> 10.572249 | E60: =IF(輸入與假設!$C$152>=9,1E+099,輸入與假設!$C$152*輸入與假設!$C$150*輸入與假設!$C$153*運營_產能與收入!E7) -> 10.572249 | F60: =IF(輸入與假設!$C$152>=9,1E+099,輸入與假設!$C$152*輸入與假設!$C$150*輸入與假設!$C$153*運營_產能與收入!F7) -> 10.572249 | G60: =IF(輸入與假設!$C$152>=9,1E+099,輸入與假設!$C$152*輸入與假設!$C$150*輸入與假設!$C$153*運營_產能與收入!G7) -> 10.572249 | I60: ＝現市值（發行參考價 × 0.5865bn 股）× 上限 % × 期間長度
A61: 股權募資 | B61: US$bn | C61: =MIN(C59,C60) -> 0 | D61: =MIN(D59,D60) -> 0 | E61: =MIN(E59,E60) -> 0 | F61: =MIN(F59,F60) -> 10.572249 | G61: =MIN(G59,G60) -> 10.572249
A62: 高息債舉借（溢出） | B62: US$bn | C62: =(C59-C61)/(1-C48) -> 0 | D62: =(D59-D61)/(1-D48) -> 0 | E62: =(E59-E61)/(1-E48) -> 0 | F62: =(F59-F61)/(1-F48) -> 7.4430893 | G62: =(G59-G61)/(1-G48) -> 10.223531
A63: 新債＋高息債利息（期初餘額＋本期舉借） | B63: US$bn | C63: =C46*(C45+C58)+C48*(C47+C62) -> 0.60569063 | D63: =D46*(D45+D58)+D48*(D47+D62) -> 4.5596371 | E63: =E46*(E45+E58)+E48*(E47+E62) -> 6.4678528 | F63: =F46*(F45+F58)+F48*(F47+F62) -> 7.3610235 | G63: =G46*(G45+G58)+G48*(G47+G62) -> 8.6350905
A64: 發行價（現價×(1−折價)） | B64: US$ | C64: =輸入與假設!$C$150*(1-輸入與假設!$C$151) -> 81.117 | D64: =輸入與假設!$C$150*(1-輸入與假設!$C$151) -> 81.117 | E64: =輸入與假設!$C$150*(1-輸入與假設!$C$151) -> 81.117 | F64: =輸入與假設!$C$150*(1-輸入與假設!$C$151) -> 81.117 | G64: =輸入與假設!$C$150*(1-輸入與假設!$C$151) -> 81.117
A65: 新發行股數 | B65: bn | C65: =C61/C64 -> 0 | D65: =D61/D64 -> 0 | E65: =E61/E64 -> 0 | F65: =F61/F64 -> 0.13033333 | G65: =G61/G64 -> 0.13033333
A66: 累計新股 | B66: bn | C66: =C65 -> 0 | D66: =C66+D65 -> 0 | E66: =D66+E65 -> 0 | F66: =E66+F65 -> 0.13033333 | G66: =F66+G65 -> 0.26066667
A67: 新債期末餘額 | B67: US$bn | C67: =C45+C58 -> 13.459792 | D67: =D45+D58 -> 50.662635 | E67: =E45+E58 -> 71.865031 | F67: =F45+F58 -> 71.865031 | G67: =G45+G58 -> 72.389956
A68: 未動用額度（期末） | B68: US$bn | C68: =C56-MIN(C56,C58) -> 0 | D68: =D56-MIN(D56,D58) -> 0 | E68: =E56-MIN(E56,E58) -> 0 | F68: =F56-MIN(F56,F58) -> 0 | G68: =G56-MIN(G56,G58) -> 0
A69: 高息債期末餘額 | B69: US$bn | C69: =C47+C62 -> 0 | D69: =D47+D62 -> 0 | E69: =E47+E62 -> 0 | F69: =F47+F62 -> 7.4430893 | G69: =G47+G62 -> 17.666621
A70: 期末總債務（既有＋可轉債＋新債＋高息債） | B70: US$bn | C70: =C54+C67+C69 -> 48.297792 | D70: =D54+D67+D69 -> 79.316635 | E70: =E54+E67+E69 -> 96.103031 | F70: =F54+F67+F69 -> 101.12512 | G70: =G54+G67+G69 -> 108.65258
A71: 融資前累積現金 | B71: US$bn | C71: =C14+C30+C31+C32+C38-C44 -> -10.854101 | D71: =C71+D30+D31-D44 -> -43.497307 | E71: =D71+E30+E31-E44 -> -58.231851 | F71: =E71+F30+F31-F44 -> -68.886166 | G71: =F71+G30+G31-G44 -> -81.57178 | I71: 若不做任何新融資的累積現金；負值＝外部資金需求
A73: 四層橋（驗算）
A74: 期初現金（2025-12-31） | C74: =輸入與假設!$C$212 -> 3.127
A75: ＋ 營運缺口合計 | C75: =SUM(C39:G39) -> -111.38807
A76: ＋ 股權／可轉債合計 | C76: =SUM(C31:G31) -> 9.182
A77: ＋ 1H 實際借款 | C77: =SUM(C32:G32) -> 16.747
A78: − capped call（1H） | C78: =-SUM(C22:G22) -> -0.492
A79: ＋ 1H 其他／受限現金調節 | C79: =SUM(C38:G38) -> -0.503
A80: ＋ 瀑布新債＋股權＋高息債合計 | C80: =SUM(C33:G33)+SUM(C34:G34)+SUM(C35:G35) -> 111.20107
A81: − 排程還本合計 | C81: =-SUM(C21:G21) -> -25.874
A82: ＝ 期末現金（橋算） | C82: =SUM(C74:C81) -> 2
A83: 對照：期末累積現金（表算） | C83: =G41 -> 2
A84: 差異（應為 0） | C84: =C82-C83 -> 3.8191672e-14 | I84: 若不為 0，表示公式鏈被改壞
A86: FY26 全年備忘（對照公司指引）
A87: FY26 總營收（1H 實際＋2H 模型） | C87: =運營_產能與收入!C27 -> 13.066 | I87: 公司指引 12.4–13.2
A88: FY26 CapEx 認列（1H＋2H） | C88: =C6 -> 37.800889 | I88: 公司指引 35–39
A89: FY26 利息（1H 實際＋2H 模型） | C89: =輸入與假設!$C$221+輸入與假設!C$162+C16 -> 3.5875869 | I89: Q3 指引 0.86–0.94／季
A90: FY26 租賃現金（1H 實際＋2H 模型） | C90: =輸入與假設!$C$222+C12 -> 2.088 | I90: 1H 實際支付 0.748
A91: FY26 排程還本（1H 實際＋2H） | C91: =C21 -> 9.632 | I91: 1H 實際還款 5.219＋2H 到期表 4.413

Sheet 季度追蹤
A1: 季度追蹤 — 焦點季的模型／共識／指引／實際與差距（由年度模型拆分；只用於追蹤，不影響年度數字與目標價）
A2: 設定與實際數在『輸入與假設』J 區，共識在 I 區；缺資料顯示「不適用」，實際數空白＝待公布。差距超過門檻的項目附差異原因（拆法＝所屬期間合計差距在門檻內）。第 2 區為 6 季路徑與拆分明細（預設收合）。
A4: 1｜焦點季（『輸入與假設』J 區選擇）：模型／共識／指引／實際與差距
A5: 指標 | B5: 單位 | C5: 模型 | D5: 共識 | E5: 模型 vs 共識 | F5: 指引（低） | G5: 指引（高） | H5: 模型 vs 指引中點 | I5: 實際 | J5: 實際 vs 模型 | K5: 實際 vs 共識 | L5: 實際 vs 指引中點 | M5: 利潤率 pt：模型 vs 共識 | N5: 模型 vs 指引 | O5: 實際 vs 模型 | P5: 實際 vs 共識 | Q5: 實際 vs 指引
A6: 焦點｜營收 | B6: US$bn | C6: =INDEX($C$22:$H$22,輸入與假設!$C$307) -> 3.6626667 | D6: =INDEX($C$41:$H$41,輸入與假設!$C$307) -> 3.541 | E6: =INDEX($C$51:$H$51,輸入與假設!$C$307) -> 0.034359409 | F6: =IF(ISNUMBER(INDEX($C$31:$H$31,輸入與假設!$C$307)),INDEX($C$31:$H$31,輸入與假設!$C$307),"不適用") -> 3.45 | G6: =INDEX($C$32:$H$32,輸入與假設!$C$307) -> 3.6 | H6: =INDEX($C$52:$H$52,輸入與假設!$C$307) -> 0.039054374 | I6: =IF(ISNUMBER(INDEX($C$45:$H$45,輸入與假設!$C$307)),INDEX($C$45:$H$45,輸入與假設!$C$307),"待公布") -> 待公布 | J6: =INDEX($C$53:$H$53,輸入與假設!$C$307) | K6: =INDEX($C$54:$H$54,輸入與假設!$C$307) | L6: =INDEX($C$55:$H$55,輸入與假設!$C$307)
A7: 焦點｜調整後 EBITDA | B7: US$bn | C7: =INDEX($C$28:$H$28,輸入與假設!$C$307) -> 2.106936 | D7: =INDEX($C$42:$H$42,輸入與假設!$C$307) -> 2.047 | E7: =INDEX($C$56:$H$56,輸入與假設!$C$307) -> 0.059935989 | F7: 不適用 | G7: 不適用 | H7: =INDEX($C$57:$H$57,輸入與假設!$C$307) -> 不適用 | I7: =IF(ISNUMBER(INDEX($C$46:$H$46,輸入與假設!$C$307)),INDEX($C$46:$H$46,輸入與假設!$C$307),"待公布") -> 待公布 | J7: =INDEX($C$58:$H$58,輸入與假設!$C$307) | K7: =INDEX($C$59:$H$59,輸入與假設!$C$307) | L7: =INDEX($C$60:$H$60,輸入與假設!$C$307) | M7: =INDEX($C$61:$H$61,輸入與假設!$C$307) -> -0.0028388388 | N7: =INDEX($C$62:$H$62,輸入與假設!$C$307) -> 不適用 | O7: =INDEX($C$63:$H$63,輸入與假設!$C$307) | P7: =INDEX($C$64:$H$64,輸入與假設!$C$307) | Q7: =INDEX($C$65:$H$65,輸入與假設!$C$307)
A8: 焦點｜EBITDA 率 | B8: % | C8: =INDEX($C$27:$H$27,輸入與假設!$C$307) -> 0.57524645 | D8: =INDEX($C$43:$H$43,輸入與假設!$C$307) -> 0.57808529 | E8: =INDEX($C$66:$H$66,輸入與假設!$C$307) -> -0.0028388388 | F8: 不適用 | G8: 不適用 | H8: =INDEX($C$67:$H$67,輸入與假設!$C$307) -> 不適用 | I8: =IF(ISNUMBER(INDEX($C$47:$H$47,輸入與假設!$C$307)),INDEX($C$47:$H$47,輸入與假設!$C$307),"待公布") -> 待公布 | J8: =INDEX($C$68:$H$68,輸入與假設!$C$307) | K8: =INDEX($C$69:$H$69,輸入與假設!$C$307) | L8: =INDEX($C$70:$H$70,輸入與假設!$C$307)
A9: 焦點｜調整後營業利益 | B9: US$bn | C9: =INDEX($C$30:$H$30,輸入與假設!$C$307) -> -0.066042019 | D9: 不適用 | E9: =INDEX($C$71:$H$71,輸入與假設!$C$307) -> 不適用 | F9: =IF(ISNUMBER(INDEX($C$33:$H$33,輸入與假設!$C$307)),INDEX($C$33:$H$33,輸入與假設!$C$307),IF(INDEX($C$35:$H$35,輸入與假設!$C$307)<>"",INDEX($C$35:$H$35,輸入與假設!$C$307),"不適用")) -> 0.2 | G9: =INDEX($C$34:$H$34,輸入與假設!$C$307) -> 0.26 | H9: =INDEX($C$72:$H$72,輸入與假設!$C$307) -> -0.29604202 | I9: =IF(ISNUMBER(INDEX($C$48:$H$48,輸入與假設!$C$307)),INDEX($C$48:$H$48,輸入與假設!$C$307),"待公布") -> 待公布 | J9: =INDEX($C$73:$H$73,輸入與假設!$C$307) | K9: =INDEX($C$74:$H$74,輸入與假設!$C$307) | L9: =INDEX($C$75:$H$75,輸入與假設!$C$307) | M9: =INDEX($C$76:$H$76,輸入與假設!$C$307) -> 不適用 | N9: =INDEX($C$77:$H$77,輸入與假設!$C$307) -> -0.083279357 | O9: =INDEX($C$78:$H$78,輸入與假設!$C$307) | P9: =INDEX($C$79:$H$79,輸入與假設!$C$307) | Q9: =INDEX($C$80:$H$80,輸入與假設!$C$307)
A10: 焦點｜CapEx（毛額） | B10: US$bn | C10: =INDEX($C$40:$H$40,輸入與假設!$C$307) -> 12.5 | D10: 不適用 | E10: =INDEX($C$81:$H$81,輸入與假設!$C$307) -> 不適用 | F10: =IF(ISNUMBER(INDEX($C$36:$H$36,輸入與假設!$C$307)),INDEX($C$36:$H$36,輸入與假設!$C$307),"不適用") -> 11.5 | G10: =INDEX($C$37:$H$37,輸入與假設!$C$307) -> 13.5 | H10: =INDEX($C$82:$H$82,輸入與假設!$C$307) -> 0 | I10: =IF(ISNUMBER(INDEX($C$49:$H$49,輸入與假設!$C$307)),INDEX($C$49:$H$49,輸入與假設!$C$307),"待公布") -> 待公布 | J10: =INDEX($C$83:$H$83,輸入與假設!$C$307) | K10: =INDEX($C$84:$H$84,輸入與假設!$C$307) | L10: =INDEX($C$85:$H$85,輸入與假設!$C$307)
A11: 焦點｜季末 Accepted MW | B11: MW | C11: =INDEX($C$19:$H$19,輸入與假設!$C$307) -> 1675 | D11: 不適用 | E11: =INDEX($C$86:$H$86,輸入與假設!$C$307) -> 不適用 | F11: 不適用 | G11: 不適用 | H11: =INDEX($C$87:$H$87,輸入與假設!$C$307) -> 不適用 | I11: =IF(ISNUMBER(INDEX($C$50:$H$50,輸入與假設!$C$307)),INDEX($C$50:$H$50,輸入與假設!$C$307),"待公布") -> 待公布 | J11: =INDEX($C$88:$H$88,輸入與假設!$C$307) | K11: =INDEX($C$89:$H$89,輸入與假設!$C$307) | L11: =INDEX($C$90:$H$90,輸入與假設!$C$307)
A12: 焦點｜季度 | C12: =INDEX($C$16:$H$16,輸入與假設!$C$307) -> Q3'26
A13: 焦點｜差異原因 | C13: =IF(INDEX($C$133:$H$133,輸入與假設!$C$307)="","無（差距皆在 "&IF(ROUND(ABS(輸入與假設!$C$301)*100,4)=INT(ROUND(ABS(輸入與假設!$C$301)*100,4)),TEXT(ROUND(ABS(輸入與假設!$C$301)*100,4),"0"),TEXT(ROUND(ABS(輸入與假設!$C$301)*100,4),"0.0"))&"%"&" 以內）",INDEX($C$133:$H$133,輸入與假設!$C$307)) -> 營收 vs 指引中點 +3.9%：觀點（水準 +$0.115bn（2H26 模型 $8.413bn，指引隱含 $8.147bn）；分配 +$0.023bn）；調整後營業利益 vs 指引中點 −$0.30bn／−8.3pt：已知限制（對照指引隱含折舊 1.82（＝共識 EBITDA 2.05 − 指引中點 0.23，Derived），模型折舊 2.17；缺口 −0.30 ≈ 折舊 −0.36 ＋ EBITDA +0.06；待辦 6 修正折舊）
A15: 2｜6 季路徑、共識、指引、實際與差距（明細；第 1 區以焦點季引用本區）
A16: 項目 | B16: 單位 | C16: Q3'26 | D16: Q4'26 | E16: Q1'27 | F16: Q2'27 | G16: Q3'27 | H16: Q4'27
A17: 所屬期間 | C17: =輸入與假設!C$306 -> 1 | D17: =輸入與假設!D$306 -> 1 | E17: =輸入與假設!E$306 -> 2 | F17: =輸入與假設!F$306 -> 2 | G17: =輸入與假設!G$306 -> 2 | H17: =輸入與假設!H$306 -> 2 | J17: 1＝2H26、2＝FY27
A18: 季序 | C18: 1 | D18: 2 | E18: 3 | F18: 4 | G18: 5 | H18: 6 | J18: EBITDA 率直線的 x 軸
A19: 季末 Accepted MW（模型） | B19: MW | C19: =輸入與假設!$C$309+(輸入與假設!C$26-輸入與假設!$C$309)*1/2 -> 1675 | D19: =輸入與假設!$C$309+(輸入與假設!C$26-輸入與假設!$C$309)*2/2 -> 1850 | E19: =輸入與假設!C$26+(輸入與假設!D$26-輸入與假設!C$26)*1/4 -> 2162.5 | F19: =輸入與假設!C$26+(輸入與假設!D$26-輸入與假設!C$26)*2/4 -> 2475 | G19: =輸入與假設!C$26+(輸入與假設!D$26-輸入與假設!C$26)*3/4 -> 2787.5 | H19: =輸入與假設!C$26+(輸入與假設!D$26-輸入與假設!C$26)*4/4 -> 3100 | J19: 期初與期末 Accepted 之間線性內插；第 1 期起點見 J 區
A20: 平均在役 MW（Billable，拆分依據） | B20: MW | C20: =輸入與假設!$C$20+(輸入與假設!C$27-輸入與假設!$C$20)*1/4 -> 1437.5 | D20: =輸入與假設!$C$20+(輸入與假設!C$27-輸入與假設!$C$20)*3/4 -> 1612.5 | E20: =輸入與假設!C$27+(輸入與假設!D$27-輸入與假設!C$27)*1/8 -> 1850 | F20: =輸入與假設!C$27+(輸入與假設!D$27-輸入與假設!C$27)*3/8 -> 2150 | G20: =輸入與假設!C$27+(輸入與假設!D$27-輸入與假設!C$27)*5/8 -> 2450 | H20: =輸入與假設!C$27+(輸入與假設!D$27-輸入與假設!C$27)*7/8 -> 2750 | J20: 期初與期末 Billable 之間線性內插的季平均
A21: 季內新增 Accepted MW | B21: MW | C21: =C19-輸入與假設!$C$309 -> 175 | D21: =D19-C19 -> 175 | E21: =E19-輸入與假設!C$26 -> 312.5 | F21: =F19-E19 -> 312.5 | G21: =G19-F19 -> 312.5 | H21: =H19-G19 -> 312.5 | J21: CapEx 拆分依據
A22: 營收（模型） | B22: US$bn | C22: =輸入與假設!$C$308+1*(損益!C8-2*輸入與假設!$C$308)/3 -> 3.6626667 | D22: =輸入與假設!$C$308+2*(損益!C8-2*輸入與假設!$C$308)/3 -> 4.7503333 | E22: =損益!D8*E20/(E20+F20+G20+H20) -> 5.2538995 | F22: =損益!D8*F20/(E20+F20+G20+H20) -> 6.1058832 | G22: =損益!D8*G20/(E20+F20+G20+H20) -> 6.9578668 | H22: =損益!D8*H20/(E20+F20+G20+H20) -> 7.8098505 | J22: 拆分方法見『輸入與假設』J 區與 HTML「拆分方法」
A23: EBITDA 率直線｜各期營收合計 S | C23: =C22+D22 -> 8.413 | D23: =E22+F22+G22+H22 -> 26.1275 | J23: 欄＝期間（2H26、FY27）
A24: EBITDA 率直線｜營收 × 季序合計 T | C24: =C22*C18+D22*D18 -> 13.163333 | D24: =E22*E18+F22*F18+G22*G18+H22*H18 -> 121.83367 | J24: 欄＝期間（2H26、FY27）
A25: EBITDA 率直線｜年度 EBITDA E | C25: =損益!C19 -> 4.8586769 | D25: =損益!D19 -> 15.41514 | J25: 欄＝期間（2H26、FY27）
A26: EBITDA 率直線｜截距 a／斜率 b | C26: =(C25*D24-C24*D25)/(C23*D24-C24*D23) -> 0.57121966 | D26: =(C23*D25-D23*C25)/(C23*D24-C24*D23) -> 0.004026787 | J26: 解兩式：Σ營收×(a＋b×季序)＝各期年度 EBITDA
A27: EBITDA 率（模型） | B27: % | C27: =$C$26+$D$26*C18 -> 0.57524645 | D27: =$C$26+$D$26*D18 -> 0.57927323 | E27: =$C$26+$D$26*E18 -> 0.58330002 | F27: =$C$26+$D$26*F18 -> 0.58732681 | G27: =$C$26+$D$26*G18 -> 0.5913536 | H27: =$C$26+$D$26*H18 -> 0.59538038 | J27: 跨季一條直線，季度 EBITDA 加總＝年度
A28: 調整後 EBITDA（模型） | B28: US$bn | C28: =C22*C27 -> 2.106936 | D28: =D22*D27 -> 2.751741 | E28: =E22*E27 -> 3.0645997 | F28: =F22*F27 -> 3.5861489 | G28: =G22*G27 -> 4.1145596 | H28: =H22*H27 -> 4.6498318
A29: 車隊折舊（模型） | B29: US$bn | C29: =(輸入與假設!C$135+輸入與假設!C$133*1/4)/輸入與假設!$C$114*輸入與假設!C$24/2 -> 2.172978 | D29: =(輸入與假設!C$135+輸入與假設!C$133*3/4)/輸入與假設!$C$114*輸入與假設!C$24/2 -> 2.6242674 | E29: =(輸入與假設!D$135+輸入與假設!D$133*1/8)/輸入與假設!$C$114*輸入與假設!D$24/4 -> 3.0702204 | F29: =(輸入與假設!D$135+輸入與假設!D$133*3/8)/輸入與假設!$C$114*輸入與假設!D$24/4 -> 3.5108372 | G29: =(輸入與假設!D$135+輸入與假設!D$133*5/8)/輸入與假設!$C$114*輸入與假設!D$24/4 -> 3.9514539 | H29: =(輸入與假設!D$135+輸入與假設!D$133*7/8)/輸入與假設!$C$114*輸入與假設!D$24/4 -> 4.3920707 | J29: 依期內平均 PP&E（與年度車隊折舊公式相同）
A30: 調整後營業利益（模型） | B30: US$bn | C30: =C28-C29 -> -0.066042019 | D30: =D28-D29 -> 0.1274736 | E30: =E28-E29 -> -0.0056207459 | F30: =F28-F29 -> 0.075311695 | G30: =G28-G29 -> 0.16310565 | H30: =H28-H29 -> 0.25776112 | J30: ＝調整後 EBITDA − 車隊折舊（未扣 SBC）
A31: 指引｜營收（低） | B31: US$bn | C31: =IF(ISNUMBER(輸入與假設!C$318),輸入與假設!C$318,"不適用") -> 3.45 | D31: =IF(ISNUMBER(輸入與假設!D$318),輸入與假設!D$318,"不適用") -> 不適用 | E31: =IF(ISNUMBER(輸入與假設!E$318),輸入與假設!E$318,"不適用") -> 不適用 | F31: =IF(ISNUMBER(輸入與假設!F$318),輸入與假設!F$318,"不適用") -> 不適用 | G31: =IF(ISNUMBER(輸入與假設!G$318),輸入與假設!G$318,"不適用") -> 不適用 | H31: =IF(ISNUMBER(輸入與假設!H$318),輸入與假設!H$318,"不適用") -> 不適用
A32: 指引｜營收（高） | B32: US$bn | C32: =IF(ISNUMBER(輸入與假設!C$319),輸入與假設!C$319,"不適用") -> 3.6 | D32: =IF(ISNUMBER(輸入與假設!D$319),輸入與假設!D$319,"不適用") -> 不適用 | E32: =IF(ISNUMBER(輸入與假設!E$319),輸入與假設!E$319,"不適用") -> 不適用 | F32: =IF(ISNUMBER(輸入與假設!F$319),輸入與假設!F$319,"不適用") -> 不適用 | G32: =IF(ISNUMBER(輸入與假設!G$319),輸入與假設!G$319,"不適用") -> 不適用 | H32: =IF(ISNUMBER(輸入與假設!H$319),輸入與假設!H$319,"不適用") -> 不適用
A33: 指引｜調整後營業利益（低） | B33: US$bn | C33: =IF(ISNUMBER(輸入與假設!C$320),輸入與假設!C$320,"不適用") -> 0.2 | D33: =IF(ISNUMBER(輸入與假設!D$320),輸入與假設!D$320,"不適用") -> 不適用 | E33: =IF(ISNUMBER(輸入與假設!E$320),輸入與假設!E$320,"不適用") -> 不適用 | F33: =IF(ISNUMBER(輸入與假設!F$320),輸入與假設!F$320,"不適用") -> 不適用 | G33: =IF(ISNUMBER(輸入與假設!G$320),輸入與假設!G$320,"不適用") -> 不適用 | H33: =IF(ISNUMBER(輸入與假設!H$320),輸入與假設!H$320,"不適用") -> 不適用
A34: 指引｜調整後營業利益（高） | B34: US$bn | C34: =IF(ISNUMBER(輸入與假設!C$321),輸入與假設!C$321,"不適用") -> 0.26 | D34: =IF(ISNUMBER(輸入與假設!D$321),輸入與假設!D$321,"不適用") -> 不適用 | E34: =IF(ISNUMBER(輸入與假設!E$321),輸入與假設!E$321,"不適用") -> 不適用 | F34: =IF(ISNUMBER(輸入與假設!F$321),輸入與假設!F$321,"不適用") -> 不適用 | G34: =IF(ISNUMBER(輸入與假設!G$321),輸入與假設!G$321,"不適用") -> 不適用 | H34: =IF(ISNUMBER(輸入與假設!H$321),輸入與假設!H$321,"不適用") -> 不適用
A35: 指引（文字）｜調整後營業利益 | C35: =IF(ISTEXT(輸入與假設!C$324),輸入與假設!C$324,"") | D35: =IF(ISTEXT(輸入與假設!D$324),輸入與假設!D$324,"") -> 調整後營業利益率 low teens | E35: =IF(ISTEXT(輸入與假設!E$324),輸入與假設!E$324,"") | F35: =IF(ISTEXT(輸入與假設!F$324),輸入與假設!F$324,"") | G35: =IF(ISTEXT(輸入與假設!G$324),輸入與假設!G$324,"") | H35: =IF(ISTEXT(輸入與假設!H$324),輸入與假設!H$324,"") | J35: 文字指引：只列不計差距
A36: 指引｜CapEx（毛額）（低） | B36: US$bn | C36: =IF(ISNUMBER(輸入與假設!C$322),輸入與假設!C$322,"不適用") -> 11.5 | D36: =IF(ISNUMBER(輸入與假設!D$322),輸入與假設!D$322,"不適用") -> 不適用 | E36: =IF(ISNUMBER(輸入與假設!E$322),輸入與假設!E$322,"不適用") -> 不適用 | F36: =IF(ISNUMBER(輸入與假設!F$322),輸入與假設!F$322,"不適用") -> 不適用 | G36: =IF(ISNUMBER(輸入與假設!G$322),輸入與假設!G$322,"不適用") -> 不適用 | H36: =IF(ISNUMBER(輸入與假設!H$322),輸入與假設!H$322,"不適用") -> 不適用
A37: 指引｜CapEx（毛額）（高） | B37: US$bn | C37: =IF(ISNUMBER(輸入與假設!C$323),輸入與假設!C$323,"不適用") -> 13.5 | D37: =IF(ISNUMBER(輸入與假設!D$323),輸入與假設!D$323,"不適用") -> 不適用 | E37: =IF(ISNUMBER(輸入與假設!E$323),輸入與假設!E$323,"不適用") -> 不適用 | F37: =IF(ISNUMBER(輸入與假設!F$323),輸入與假設!F$323,"不適用") -> 不適用 | G37: =IF(ISNUMBER(輸入與假設!G$323),輸入與假設!G$323,"不適用") -> 不適用 | H37: =IF(ISNUMBER(輸入與假設!H$323),輸入與假設!H$323,"不適用") -> 不適用
A38: CapEx 指引錨定值 | B38: US$bn | C38: =IF(AND(ISNUMBER(C36),ISNUMBER(C37)),((C36+C37)/2),"") -> 12.5 | D38: =IF(AND(ISNUMBER(D36),ISNUMBER(D37)),((D36+D37)/2),"") | E38: =IF(AND(ISNUMBER(E36),ISNUMBER(E37)),((E36+E37)/2),"") | F38: =IF(AND(ISNUMBER(F36),ISNUMBER(F37)),((F36+F37)/2),"") | G38: =IF(AND(ISNUMBER(G36),ISNUMBER(G37)),((G36+G37)/2),"") | H38: =IF(AND(ISNUMBER(H36),ISNUMBER(H37)),((H36+H37)/2),"") | J38: 有季度指引的季取指引中點（capexSplit＝guidanceAnchor）
A39: CapEx 未錨定季的新增 MW | B39: MW | C39: =IF(ISNUMBER(C38),0,C21) -> 0 | D39: =IF(ISNUMBER(D38),0,D21) -> 175 | E39: =IF(ISNUMBER(E38),0,E21) -> 312.5 | F39: =IF(ISNUMBER(F38),0,F21) -> 312.5 | G39: =IF(ISNUMBER(G38),0,G21) -> 312.5 | H39: =IF(ISNUMBER(H38),0,H21) -> 312.5 | J39: 期間餘數依此分配
A40: CapEx（毛額）（模型） | B40: US$bn | C40: =IF(ISNUMBER(C38),C38,IF((C39+D39)>0,(輸入與假設!C$137-SUM(C38,D38))*C39/(C39+D39),(輸入與假設!C$137-SUM(C38,D38))/(2-COUNT(C38,D38)))) -> 12.5 | D40: =IF(ISNUMBER(D38),D38,IF((C39+D39)>0,(輸入與假設!C$137-SUM(C38,D38))*D39/(C39+D39),(輸入與假設!C$137-SUM(C38,D38))/(2-COUNT(C38,D38)))) -> 9.1618888 | E40: =IF(ISNUMBER(E38),E38,IF((E39+F39+G39+H39)>0,(輸入與假設!D$137-SUM(E38,F38,G38,H38))*E39/(E39+F39+G39+H39),(輸入與假設!D$137-SUM(E38,F38,G38,H38))/(4-COUNT(E38,F38,G38,H38)))) -> 10.574802 | F40: =IF(ISNUMBER(F38),F38,IF((E39+F39+G39+H39)>0,(輸入與假設!D$137-SUM(E38,F38,G38,H38))*F39/(E39+F39+G39+H39),(輸入與假設!D$137-SUM(E38,F38,G38,H38))/(4-COUNT(E38,F38,G38,H38)))) -> 10.574802 | G40: =IF(ISNUMBER(G38),G38,IF((E39+F39+G39+H39)>0,(輸入與假設!D$137-SUM(E38,F38,G38,H38))*G39/(E39+F39+G39+H39),(輸入與假設!D$137-SUM(E38,F38,G38,H38))/(4-COUNT(E38,F38,G38,H38)))) -> 10.574802 | H40: =IF(ISNUMBER(H38),H38,IF((E39+F39+G39+H39)>0,(輸入與假設!D$137-SUM(E38,F38,G38,H38))*H39/(E39+F39+G39+H39),(輸入與假設!D$137-SUM(E38,F38,G38,H38))/(4-COUNT(E38,F38,G38,H38)))) -> 10.574802 | J40: 有季度指引的季＝指引中點；其餘季＝期間餘數依新增 Accepted MW 分配
A41: 共識｜營收 | B41: US$bn | C41: =IF(ISNUMBER(輸入與假設!$C$277),輸入與假設!$C$277,"不適用") -> 3.541 | D41: =IF(ISNUMBER(輸入與假設!$D$277),輸入與假設!$D$277,"不適用") -> 4.706 | E41: 不適用 | F41: 不適用 | G41: 不適用 | H41: 不適用 | J41: I 區季度共識 [Interested-party]
A42: 共識｜調整後 EBITDA | B42: US$bn | C42: =IF(ISNUMBER(輸入與假設!$C$278),輸入與假設!$C$278,"不適用") -> 2.047 | D42: =IF(ISNUMBER(輸入與假設!$D$278),輸入與假設!$D$278,"不適用") -> 2.897 | E42: 不適用 | F42: 不適用 | G42: 不適用 | H42: 不適用 | J42: I 區季度共識 [Interested-party]
A43: 共識｜EBITDA 率 [Derived] | B43: % | C43: =IF(AND(ISNUMBER(輸入與假設!$C$278),ISNUMBER(輸入與假設!$C$277)),輸入與假設!$C$278/輸入與假設!$C$277,"不適用") -> 0.57808529 | D43: =IF(AND(ISNUMBER(輸入與假設!$D$278),ISNUMBER(輸入與假設!$D$277)),輸入與假設!$D$278/輸入與假設!$D$277,"不適用") -> 0.61559711 | E43: 不適用 | F43: 不適用 | G43: 不適用 | H43: 不適用 | J43: ＝共識 EBITDA ÷ 共識營收
A44: 共識 EBIT（口徑未揭露） | B44: US$bn | C44: =IF(ISNUMBER(輸入與假設!$C$279),輸入與假設!$C$279,"不適用") -> 0.2408 | D44: =IF(ISNUMBER(輸入與假設!$D$279),輸入與假設!$D$279,"不適用") -> 0.6805 | E44: 不適用 | F44: 不適用 | G44: 不適用 | H44: 不適用 | J44: 口徑未揭露：只列不比較
A45: 實際｜營收 | B45: US$bn | C45: =IF(ISNUMBER(輸入與假設!C$310),輸入與假設!C$310,"") | D45: =IF(ISNUMBER(輸入與假設!D$310),輸入與假設!D$310,"") | E45: =IF(ISNUMBER(輸入與假設!E$310),輸入與假設!E$310,"") | F45: =IF(ISNUMBER(輸入與假設!F$310),輸入與假設!F$310,"") | G45: =IF(ISNUMBER(輸入與假設!G$310),輸入與假設!G$310,"") | H45: =IF(ISNUMBER(輸入與假設!H$310),輸入與假設!H$310,"")
A46: 實際｜調整後 EBITDA | B46: US$bn | C46: =IF(ISNUMBER(輸入與假設!C$311),輸入與假設!C$311,"") | D46: =IF(ISNUMBER(輸入與假設!D$311),輸入與假設!D$311,"") | E46: =IF(ISNUMBER(輸入與假設!E$311),輸入與假設!E$311,"") | F46: =IF(ISNUMBER(輸入與假設!F$311),輸入與假設!F$311,"") | G46: =IF(ISNUMBER(輸入與假設!G$311),輸入與假設!G$311,"") | H46: =IF(ISNUMBER(輸入與假設!H$311),輸入與假設!H$311,"")
A47: 實際｜EBITDA 率 | B47: % | C47: =IF(AND(ISNUMBER(輸入與假設!C$311),ISNUMBER(輸入與假設!C$310)),輸入與假設!C$311/輸入與假設!C$310,"") | D47: =IF(AND(ISNUMBER(輸入與假設!D$311),ISNUMBER(輸入與假設!D$310)),輸入與假設!D$311/輸入與假設!D$310,"") | E47: =IF(AND(ISNUMBER(輸入與假設!E$311),ISNUMBER(輸入與假設!E$310)),輸入與假設!E$311/輸入與假設!E$310,"") | F47: =IF(AND(ISNUMBER(輸入與假設!F$311),ISNUMBER(輸入與假設!F$310)),輸入與假設!F$311/輸入與假設!F$310,"") | G47: =IF(AND(ISNUMBER(輸入與假設!G$311),ISNUMBER(輸入與假設!G$310)),輸入與假設!G$311/輸入與假設!G$310,"") | H47: =IF(AND(ISNUMBER(輸入與假設!H$311),ISNUMBER(輸入與假設!H$310)),輸入與假設!H$311/輸入與假設!H$310,"") | J47: ＝實際 EBITDA ÷ 實際營收
A48: 實際｜調整後營業利益 | B48: US$bn | C48: =IF(ISNUMBER(輸入與假設!C$312),輸入與假設!C$312,"") | D48: =IF(ISNUMBER(輸入與假設!D$312),輸入與假設!D$312,"") | E48: =IF(ISNUMBER(輸入與假設!E$312),輸入與假設!E$312,"") | F48: =IF(ISNUMBER(輸入與假設!F$312),輸入與假設!F$312,"") | G48: =IF(ISNUMBER(輸入與假設!G$312),輸入與假設!G$312,"") | H48: =IF(ISNUMBER(輸入與假設!H$312),輸入與假設!H$312,"")
A49: 實際｜CapEx（毛額） | B49: US$bn | C49: =IF(ISNUMBER(輸入與假設!C$313),輸入與假設!C$313,"") | D49: =IF(ISNUMBER(輸入與假設!D$313),輸入與假設!D$313,"") | E49: =IF(ISNUMBER(輸入與假設!E$313),輸入與假設!E$313,"") | F49: =IF(ISNUMBER(輸入與假設!F$313),輸入與假設!F$313,"") | G49: =IF(ISNUMBER(輸入與假設!G$313),輸入與假設!G$313,"") | H49: =IF(ISNUMBER(輸入與假設!H$313),輸入與假設!H$313,"")
A50: 實際｜季末 active power | B50: MW | C50: =IF(ISNUMBER(輸入與假設!C$314),輸入與假設!C$314,"") | D50: =IF(ISNUMBER(輸入與假設!D$314),輸入與假設!D$314,"") | E50: =IF(ISNUMBER(輸入與假設!E$314),輸入與假設!E$314,"") | F50: =IF(ISNUMBER(輸入與假設!F$314),輸入與假設!F$314,"") | G50: =IF(ISNUMBER(輸入與假設!G$314),輸入與假設!G$314,"") | H50: =IF(ISNUMBER(輸入與假設!H$314),輸入與假設!H$314,"")
A51: 差距｜營收｜模型 vs 共識 | B51: % | C51: =IF(AND(ISNUMBER(C22),ISNUMBER(C41),C41<>0),C22/(C41)-1,"不適用") -> 0.034359409 | D51: =IF(AND(ISNUMBER(D22),ISNUMBER(D41),D41<>0),D22/(D41)-1,"不適用") -> 0.0094205978 | E51: =IF(AND(ISNUMBER(E22),ISNUMBER(E41),E41<>0),E22/(E41)-1,"不適用") -> 不適用 | F51: =IF(AND(ISNUMBER(F22),ISNUMBER(F41),F41<>0),F22/(F41)-1,"不適用") -> 不適用 | G51: =IF(AND(ISNUMBER(G22),ISNUMBER(G41),G41<>0),G22/(G41)-1,"不適用") -> 不適用 | H51: =IF(AND(ISNUMBER(H22),ISNUMBER(H41),H41<>0),H22/(H41)-1,"不適用") -> 不適用
A52: 差距｜營收｜模型 vs 指引中點 | B52: % | C52: =IF(AND(ISNUMBER(C22),ISNUMBER(C31),ISNUMBER(C32)),C22/(((C31+C32)/2))-1,"不適用") -> 0.039054374 | D52: =IF(AND(ISNUMBER(D22),ISNUMBER(D31),ISNUMBER(D32)),D22/(((D31+D32)/2))-1,"不適用") -> 不適用 | E52: =IF(AND(ISNUMBER(E22),ISNUMBER(E31),ISNUMBER(E32)),E22/(((E31+E32)/2))-1,"不適用") -> 不適用 | F52: =IF(AND(ISNUMBER(F22),ISNUMBER(F31),ISNUMBER(F32)),F22/(((F31+F32)/2))-1,"不適用") -> 不適用 | G52: =IF(AND(ISNUMBER(G22),ISNUMBER(G31),ISNUMBER(G32)),G22/(((G31+G32)/2))-1,"不適用") -> 不適用 | H52: =IF(AND(ISNUMBER(H22),ISNUMBER(H31),ISNUMBER(H32)),H22/(((H31+H32)/2))-1,"不適用") -> 不適用
A53: 差距｜營收｜實際 vs 模型 | B53: % | C53: =IF(ISNUMBER(C45),IF(AND(ISNUMBER(C22),C22<>0),C45/(C22)-1,"不適用"),"") | D53: =IF(ISNUMBER(D45),IF(AND(ISNUMBER(D22),D22<>0),D45/(D22)-1,"不適用"),"") | E53: =IF(ISNUMBER(E45),IF(AND(ISNUMBER(E22),E22<>0),E45/(E22)-1,"不適用"),"") | F53: =IF(ISNUMBER(F45),IF(AND(ISNUMBER(F22),F22<>0),F45/(F22)-1,"不適用"),"") | G53: =IF(ISNUMBER(G45),IF(AND(ISNUMBER(G22),G22<>0),G45/(G22)-1,"不適用"),"") | H53: =IF(ISNUMBER(H45),IF(AND(ISNUMBER(H22),H22<>0),H45/(H22)-1,"不適用"),"")
A54: 差距｜營收｜實際 vs 共識 | B54: % | C54: =IF(ISNUMBER(C45),IF(AND(ISNUMBER(C41),C41<>0),C45/(C41)-1,"不適用"),"") | D54: =IF(ISNUMBER(D45),IF(AND(ISNUMBER(D41),D41<>0),D45/(D41)-1,"不適用"),"") | E54: =IF(ISNUMBER(E45),IF(AND(ISNUMBER(E41),E41<>0),E45/(E41)-1,"不適用"),"") | F54: =IF(ISNUMBER(F45),IF(AND(ISNUMBER(F41),F41<>0),F45/(F41)-1,"不適用"),"") | G54: =IF(ISNUMBER(G45),IF(AND(ISNUMBER(G41),G41<>0),G45/(G41)-1,"不適用"),"") | H54: =IF(ISNUMBER(H45),IF(AND(ISNUMBER(H41),H41<>0),H45/(H41)-1,"不適用"),"")
A55: 差距｜營收｜實際 vs 指引中點 | B55: % | C55: =IF(ISNUMBER(C45),IF(AND(ISNUMBER(C31),ISNUMBER(C32)),C45/(((C31+C32)/2))-1,"不適用"),"") | D55: =IF(ISNUMBER(D45),IF(AND(ISNUMBER(D31),ISNUMBER(D32)),D45/(((D31+D32)/2))-1,"不適用"),"") | E55: =IF(ISNUMBER(E45),IF(AND(ISNUMBER(E31),ISNUMBER(E32)),E45/(((E31+E32)/2))-1,"不適用"),"") | F55: =IF(ISNUMBER(F45),IF(AND(ISNUMBER(F31),ISNUMBER(F32)),F45/(((F31+F32)/2))-1,"不適用"),"") | G55: =IF(ISNUMBER(G45),IF(AND(ISNUMBER(G31),ISNUMBER(G32)),G45/(((G31+G32)/2))-1,"不適用"),"") | H55: =IF(ISNUMBER(H45),IF(AND(ISNUMBER(H31),ISNUMBER(H32)),H45/(((H31+H32)/2))-1,"不適用"),"")
A56: 差距｜調整後 EBITDA｜模型 vs 共識 | B56: US$bn | C56: =IF(AND(ISNUMBER(C28),ISNUMBER(C42)),C28-(C42),"不適用") -> 0.059935989 | D56: =IF(AND(ISNUMBER(D28),ISNUMBER(D42)),D28-(D42),"不適用") -> -0.14525904 | E56: =IF(AND(ISNUMBER(E28),ISNUMBER(E42)),E28-(E42),"不適用") -> 不適用 | F56: =IF(AND(ISNUMBER(F28),ISNUMBER(F42)),F28-(F42),"不適用") -> 不適用 | G56: =IF(AND(ISNUMBER(G28),ISNUMBER(G42)),G28-(G42),"不適用") -> 不適用 | H56: =IF(AND(ISNUMBER(H28),ISNUMBER(H42)),H28-(H42),"不適用") -> 不適用
A57: 差距｜調整後 EBITDA｜模型 vs 指引中點 | B57: US$bn | C57: 不適用 | D57: 不適用 | E57: 不適用 | F57: 不適用 | G57: 不適用 | H57: 不適用
A58: 差距｜調整後 EBITDA｜實際 vs 模型 | B58: US$bn | C58: =IF(ISNUMBER(C46),IF(AND(ISNUMBER(C28)),C46-(C28),"不適用"),"") | D58: =IF(ISNUMBER(D46),IF(AND(ISNUMBER(D28)),D46-(D28),"不適用"),"") | E58: =IF(ISNUMBER(E46),IF(AND(ISNUMBER(E28)),E46-(E28),"不適用"),"") | F58: =IF(ISNUMBER(F46),IF(AND(ISNUMBER(F28)),F46-(F28),"不適用"),"") | G58: =IF(ISNUMBER(G46),IF(AND(ISNUMBER(G28)),G46-(G28),"不適用"),"") | H58: =IF(ISNUMBER(H46),IF(AND(ISNUMBER(H28)),H46-(H28),"不適用"),"")
A59: 差距｜調整後 EBITDA｜實際 vs 共識 | B59: US$bn | C59: =IF(ISNUMBER(C46),IF(AND(ISNUMBER(C42)),C46-(C42),"不適用"),"") | D59: =IF(ISNUMBER(D46),IF(AND(ISNUMBER(D42)),D46-(D42),"不適用"),"") | E59: =IF(ISNUMBER(E46),IF(AND(ISNUMBER(E42)),E46-(E42),"不適用"),"") | F59: =IF(ISNUMBER(F46),IF(AND(ISNUMBER(F42)),F46-(F42),"不適用"),"") | G59: =IF(ISNUMBER(G46),IF(AND(ISNUMBER(G42)),G46-(G42),"不適用"),"") | H59: =IF(ISNUMBER(H46),IF(AND(ISNUMBER(H42)),H46-(H42),"不適用"),"")
A60: 差距｜調整後 EBITDA｜實際 vs 指引中點 | B60: US$bn | C60: =IF(ISNUMBER(C46),"不適用","") | D60: =IF(ISNUMBER(D46),"不適用","") | E60: =IF(ISNUMBER(E46),"不適用","") | F60: =IF(ISNUMBER(F46),"不適用","") | G60: =IF(ISNUMBER(G46),"不適用","") | H60: =IF(ISNUMBER(H46),"不適用","")
A61: 差距｜調整後 EBITDA｜模型 vs 共識（利潤率 pt） | B61: pt | C61: =IF(AND(ISNUMBER(C28),ISNUMBER(C22),C22<>0,ISNUMBER(C42),ISNUMBER(C41),C41<>0),C28/C22-C42/C41,"不適用") -> -0.0028388388 | D61: =IF(AND(ISNUMBER(D28),ISNUMBER(D22),D22<>0,ISNUMBER(D42),ISNUMBER(D41),D41<>0),D28/D22-D42/D41,"不適用") -> -0.036323875 | E61: =IF(AND(ISNUMBER(E28),ISNUMBER(E22),E22<>0,ISNUMBER(E42),ISNUMBER(E41),E41<>0),E28/E22-E42/E41,"不適用") -> 不適用 | F61: =IF(AND(ISNUMBER(F28),ISNUMBER(F22),F22<>0,ISNUMBER(F42),ISNUMBER(F41),F41<>0),F28/F22-F42/F41,"不適用") -> 不適用 | G61: =IF(AND(ISNUMBER(G28),ISNUMBER(G22),G22<>0,ISNUMBER(G42),ISNUMBER(G41),G41<>0),G28/G22-G42/G41,"不適用") -> 不適用 | H61: =IF(AND(ISNUMBER(H28),ISNUMBER(H22),H22<>0,ISNUMBER(H42),ISNUMBER(H41),H41<>0),H28/H22-H42/H41,"不適用") -> 不適用
A62: 差距｜調整後 EBITDA｜模型 vs 指引中點（利潤率 pt） | B62: pt | C62: 不適用 | D62: 不適用 | E62: 不適用 | F62: 不適用 | G62: 不適用 | H62: 不適用
A63: 差距｜調整後 EBITDA｜實際 vs 模型（利潤率 pt） | B63: pt | C63: =IF(ISNUMBER(C46),IF(AND(ISNUMBER(C46),ISNUMBER(C45),C45<>0,ISNUMBER(C28),ISNUMBER(C22),C22<>0),C46/C45-C28/C22,"不適用"),"") | D63: =IF(ISNUMBER(D46),IF(AND(ISNUMBER(D46),ISNUMBER(D45),D45<>0,ISNUMBER(D28),ISNUMBER(D22),D22<>0),D46/D45-D28/D22,"不適用"),"") | E63: =IF(ISNUMBER(E46),IF(AND(ISNUMBER(E46),ISNUMBER(E45),E45<>0,ISNUMBER(E28),ISNUMBER(E22),E22<>0),E46/E45-E28/E22,"不適用"),"") | F63: =IF(ISNUMBER(F46),IF(AND(ISNUMBER(F46),ISNUMBER(F45),F45<>0,ISNUMBER(F28),ISNUMBER(F22),F22<>0),F46/F45-F28/F22,"不適用"),"") | G63: =IF(ISNUMBER(G46),IF(AND(ISNUMBER(G46),ISNUMBER(G45),G45<>0,ISNUMBER(G28),ISNUMBER(G22),G22<>0),G46/G45-G28/G22,"不適用"),"") | H63: =IF(ISNUMBER(H46),IF(AND(ISNUMBER(H46),ISNUMBER(H45),H45<>0,ISNUMBER(H28),ISNUMBER(H22),H22<>0),H46/H45-H28/H22,"不適用"),"")
A64: 差距｜調整後 EBITDA｜實際 vs 共識（利潤率 pt） | B64: pt | C64: =IF(ISNUMBER(C46),IF(AND(ISNUMBER(C46),ISNUMBER(C45),C45<>0,ISNUMBER(C42),ISNUMBER(C41),C41<>0),C46/C45-C42/C41,"不適用"),"") | D64: =IF(ISNUMBER(D46),IF(AND(ISNUMBER(D46),ISNUMBER(D45),D45<>0,ISNUMBER(D42),ISNUMBER(D41),D41<>0),D46/D45-D42/D41,"不適用"),"") | E64: =IF(ISNUMBER(E46),IF(AND(ISNUMBER(E46),ISNUMBER(E45),E45<>0,ISNUMBER(E42),ISNUMBER(E41),E41<>0),E46/E45-E42/E41,"不適用"),"") | F64: =IF(ISNUMBER(F46),IF(AND(ISNUMBER(F46),ISNUMBER(F45),F45<>0,ISNUMBER(F42),ISNUMBER(F41),F41<>0),F46/F45-F42/F41,"不適用"),"") | G64: =IF(ISNUMBER(G46),IF(AND(ISNUMBER(G46),ISNUMBER(G45),G45<>0,ISNUMBER(G42),ISNUMBER(G41),G41<>0),G46/G45-G42/G41,"不適用"),"") | H64: =IF(ISNUMBER(H46),IF(AND(ISNUMBER(H46),ISNUMBER(H45),H45<>0,ISNUMBER(H42),ISNUMBER(H41),H41<>0),H46/H45-H42/H41,"不適用"),"")
A65: 差距｜調整後 EBITDA｜實際 vs 指引中點（利潤率 pt） | B65: pt | C65: =IF(ISNUMBER(C46),"不適用","") | D65: =IF(ISNUMBER(D46),"不適用","") | E65: =IF(ISNUMBER(E46),"不適用","") | F65: =IF(ISNUMBER(F46),"不適用","") | G65: =IF(ISNUMBER(G46),"不適用","") | H65: =IF(ISNUMBER(H46),"不適用","")
A66: 差距｜EBITDA 率｜模型 vs 共識 | B66: pt | C66: =IF(AND(ISNUMBER(C27),ISNUMBER(C43)),C27-(C43),"不適用") -> -0.0028388388 | D66: =IF(AND(ISNUMBER(D27),ISNUMBER(D43)),D27-(D43),"不適用") -> -0.036323875 | E66: =IF(AND(ISNUMBER(E27),ISNUMBER(E43)),E27-(E43),"不適用") -> 不適用 | F66: =IF(AND(ISNUMBER(F27),ISNUMBER(F43)),F27-(F43),"不適用") -> 不適用 | G66: =IF(AND(ISNUMBER(G27),ISNUMBER(G43)),G27-(G43),"不適用") -> 不適用 | H66: =IF(AND(ISNUMBER(H27),ISNUMBER(H43)),H27-(H43),"不適用") -> 不適用
A67: 差距｜EBITDA 率｜模型 vs 指引中點 | B67: pt | C67: 不適用 | D67: 不適用 | E67: 不適用 | F67: 不適用 | G67: 不適用 | H67: 不適用
A68: 差距｜EBITDA 率｜實際 vs 模型 | B68: pt | C68: =IF(ISNUMBER(C47),IF(AND(ISNUMBER(C27)),C47-(C27),"不適用"),"") | D68: =IF(ISNUMBER(D47),IF(AND(ISNUMBER(D27)),D47-(D27),"不適用"),"") | E68: =IF(ISNUMBER(E47),IF(AND(ISNUMBER(E27)),E47-(E27),"不適用"),"") | F68: =IF(ISNUMBER(F47),IF(AND(ISNUMBER(F27)),F47-(F27),"不適用"),"") | G68: =IF(ISNUMBER(G47),IF(AND(ISNUMBER(G27)),G47-(G27),"不適用"),"") | H68: =IF(ISNUMBER(H47),IF(AND(ISNUMBER(H27)),H47-(H27),"不適用"),"")
A69: 差距｜EBITDA 率｜實際 vs 共識 | B69: pt | C69: =IF(ISNUMBER(C47),IF(AND(ISNUMBER(C43)),C47-(C43),"不適用"),"") | D69: =IF(ISNUMBER(D47),IF(AND(ISNUMBER(D43)),D47-(D43),"不適用"),"") | E69: =IF(ISNUMBER(E47),IF(AND(ISNUMBER(E43)),E47-(E43),"不適用"),"") | F69: =IF(ISNUMBER(F47),IF(AND(ISNUMBER(F43)),F47-(F43),"不適用"),"") | G69: =IF(ISNUMBER(G47),IF(AND(ISNUMBER(G43)),G47-(G43),"不適用"),"") | H69: =IF(ISNUMBER(H47),IF(AND(ISNUMBER(H43)),H47-(H43),"不適用"),"")
A70: 差距｜EBITDA 率｜實際 vs 指引中點 | B70: pt | C70: =IF(ISNUMBER(C47),"不適用","") | D70: =IF(ISNUMBER(D47),"不適用","") | E70: =IF(ISNUMBER(E47),"不適用","") | F70: =IF(ISNUMBER(F47),"不適用","") | G70: =IF(ISNUMBER(G47),"不適用","") | H70: =IF(ISNUMBER(H47),"不適用","")
A71: 差距｜調整後營業利益｜模型 vs 共識 | B71: US$bn | C71: 不適用 | D71: 不適用 | E71: 不適用 | F71: 不適用 | G71: 不適用 | H71: 不適用
A72: 差距｜調整後營業利益｜模型 vs 指引中點 | B72: US$bn | C72: =IF(AND(ISNUMBER(C30),ISNUMBER(C33),ISNUMBER(C34)),C30-(((C33+C34)/2)),"不適用") -> -0.29604202 | D72: =IF(AND(ISNUMBER(D30),ISNUMBER(D33),ISNUMBER(D34)),D30-(((D33+D34)/2)),"不適用") -> 不適用 | E72: =IF(AND(ISNUMBER(E30),ISNUMBER(E33),ISNUMBER(E34)),E30-(((E33+E34)/2)),"不適用") -> 不適用 | F72: =IF(AND(ISNUMBER(F30),ISNUMBER(F33),ISNUMBER(F34)),F30-(((F33+F34)/2)),"不適用") -> 不適用 | G72: =IF(AND(ISNUMBER(G30),ISNUMBER(G33),ISNUMBER(G34)),G30-(((G33+G34)/2)),"不適用") -> 不適用 | H72: =IF(AND(ISNUMBER(H30),ISNUMBER(H33),ISNUMBER(H34)),H30-(((H33+H34)/2)),"不適用") -> 不適用
A73: 差距｜調整後營業利益｜實際 vs 模型 | B73: US$bn | C73: =IF(ISNUMBER(C48),IF(AND(ISNUMBER(C30)),C48-(C30),"不適用"),"") | D73: =IF(ISNUMBER(D48),IF(AND(ISNUMBER(D30)),D48-(D30),"不適用"),"") | E73: =IF(ISNUMBER(E48),IF(AND(ISNUMBER(E30)),E48-(E30),"不適用"),"") | F73: =IF(ISNUMBER(F48),IF(AND(ISNUMBER(F30)),F48-(F30),"不適用"),"") | G73: =IF(ISNUMBER(G48),IF(AND(ISNUMBER(G30)),G48-(G30),"不適用"),"") | H73: =IF(ISNUMBER(H48),IF(AND(ISNUMBER(H30)),H48-(H30),"不適用"),"")
A74: 差距｜調整後營業利益｜實際 vs 共識 | B74: US$bn | C74: =IF(ISNUMBER(C48),"不適用","") | D74: =IF(ISNUMBER(D48),"不適用","") | E74: =IF(ISNUMBER(E48),"不適用","") | F74: =IF(ISNUMBER(F48),"不適用","") | G74: =IF(ISNUMBER(G48),"不適用","") | H74: =IF(ISNUMBER(H48),"不適用","")
A75: 差距｜調整後營業利益｜實際 vs 指引中點 | B75: US$bn | C75: =IF(ISNUMBER(C48),IF(AND(ISNUMBER(C33),ISNUMBER(C34)),C48-(((C33+C34)/2)),"不適用"),"") | D75: =IF(ISNUMBER(D48),IF(AND(ISNUMBER(D33),ISNUMBER(D34)),D48-(((D33+D34)/2)),"不適用"),"") | E75: =IF(ISNUMBER(E48),IF(AND(ISNUMBER(E33),ISNUMBER(E34)),E48-(((E33+E34)/2)),"不適用"),"") | F75: =IF(ISNUMBER(F48),IF(AND(ISNUMBER(F33),ISNUMBER(F34)),F48-(((F33+F34)/2)),"不適用"),"") | G75: =IF(ISNUMBER(G48),IF(AND(ISNUMBER(G33),ISNUMBER(G34)),G48-(((G33+G34)/2)),"不適用"),"") | H75: =IF(ISNUMBER(H48),IF(AND(ISNUMBER(H33),ISNUMBER(H34)),H48-(((H33+H34)/2)),"不適用"),"")
A76: 差距｜調整後營業利益｜模型 vs 共識（利潤率 pt） | B76: pt | C76: 不適用 | D76: 不適用 | E76: 不適用 | F76: 不適用 | G76: 不適用 | H76: 不適用
A77: 差距｜調整後營業利益｜模型 vs 指引中點（利潤率 pt） | B77: pt | C77: =IF(AND(ISNUMBER(C30),ISNUMBER(C22),C22<>0,ISNUMBER(C33),ISNUMBER(C34),ISNUMBER(C31),ISNUMBER(C32)),C30/C22-((C33+C34)/2)/((C31+C32)/2),"不適用") -> -0.083279357 | D77: =IF(AND(ISNUMBER(D30),ISNUMBER(D22),D22<>0,ISNUMBER(D33),ISNUMBER(D34),ISNUMBER(D31),ISNUMBER(D32)),D30/D22-((D33+D34)/2)/((D31+D32)/2),"不適用") -> 不適用 | E77: =IF(AND(ISNUMBER(E30),ISNUMBER(E22),E22<>0,ISNUMBER(E33),ISNUMBER(E34),ISNUMBER(E31),ISNUMBER(E32)),E30/E22-((E33+E34)/2)/((E31+E32)/2),"不適用") -> 不適用 | F77: =IF(AND(ISNUMBER(F30),ISNUMBER(F22),F22<>0,ISNUMBER(F33),ISNUMBER(F34),ISNUMBER(F31),ISNUMBER(F32)),F30/F22-((F33+F34)/2)/((F31+F32)/2),"不適用") -> 不適用 | G77: =IF(AND(ISNUMBER(G30),ISNUMBER(G22),G22<>0,ISNUMBER(G33),ISNUMBER(G34),ISNUMBER(G31),ISNUMBER(G32)),G30/G22-((G33+G34)/2)/((G31+G32)/2),"不適用") -> 不適用 | H77: =IF(AND(ISNUMBER(H30),ISNUMBER(H22),H22<>0,ISNUMBER(H33),ISNUMBER(H34),ISNUMBER(H31),ISNUMBER(H32)),H30/H22-((H33+H34)/2)/((H31+H32)/2),"不適用") -> 不適用
A78: 差距｜調整後營業利益｜實際 vs 模型（利潤率 pt） | B78: pt | C78: =IF(ISNUMBER(C48),IF(AND(ISNUMBER(C48),ISNUMBER(C45),C45<>0,ISNUMBER(C30),ISNUMBER(C22),C22<>0),C48/C45-C30/C22,"不適用"),"") | D78: =IF(ISNUMBER(D48),IF(AND(ISNUMBER(D48),ISNUMBER(D45),D45<>0,ISNUMBER(D30),ISNUMBER(D22),D22<>0),D48/D45-D30/D22,"不適用"),"") | E78: =IF(ISNUMBER(E48),IF(AND(ISNUMBER(E48),ISNUMBER(E45),E45<>0,ISNUMBER(E30),ISNUMBER(E22),E22<>0),E48/E45-E30/E22,"不適用"),"") | F78: =IF(ISNUMBER(F48),IF(AND(ISNUMBER(F48),ISNUMBER(F45),F45<>0,ISNUMBER(F30),ISNUMBER(F22),F22<>0),F48/F45-F30/F22,"不適用"),"") | G78: =IF(ISNUMBER(G48),IF(AND(ISNUMBER(G48),ISNUMBER(G45),G45<>0,ISNUMBER(G30),ISNUMBER(G22),G22<>0),G48/G45-G30/G22,"不適用"),"") | H78: =IF(ISNUMBER(H48),IF(AND(ISNUMBER(H48),ISNUMBER(H45),H45<>0,ISNUMBER(H30),ISNUMBER(H22),H22<>0),H48/H45-H30/H22,"不適用"),"")
A79: 差距｜調整後營業利益｜實際 vs 共識（利潤率 pt） | B79: pt | C79: =IF(ISNUMBER(C48),"不適用","") | D79: =IF(ISNUMBER(D48),"不適用","") | E79: =IF(ISNUMBER(E48),"不適用","") | F79: =IF(ISNUMBER(F48),"不適用","") | G79: =IF(ISNUMBER(G48),"不適用","") | H79: =IF(ISNUMBER(H48),"不適用","")
A80: 差距｜調整後營業利益｜實際 vs 指引中點（利潤率 pt） | B80: pt | C80: =IF(ISNUMBER(C48),IF(AND(ISNUMBER(C48),ISNUMBER(C45),C45<>0,ISNUMBER(C33),ISNUMBER(C34),ISNUMBER(C31),ISNUMBER(C32)),C48/C45-((C33+C34)/2)/((C31+C32)/2),"不適用"),"") | D80: =IF(ISNUMBER(D48),IF(AND(ISNUMBER(D48),ISNUMBER(D45),D45<>0,ISNUMBER(D33),ISNUMBER(D34),ISNUMBER(D31),ISNUMBER(D32)),D48/D45-((D33+D34)/2)/((D31+D32)/2),"不適用"),"") | E80: =IF(ISNUMBER(E48),IF(AND(ISNUMBER(E48),ISNUMBER(E45),E45<>0,ISNUMBER(E33),ISNUMBER(E34),ISNUMBER(E31),ISNUMBER(E32)),E48/E45-((E33+E34)/2)/((E31+E32)/2),"不適用"),"") | F80: =IF(ISNUMBER(F48),IF(AND(ISNUMBER(F48),ISNUMBER(F45),F45<>0,ISNUMBER(F33),ISNUMBER(F34),ISNUMBER(F31),ISNUMBER(F32)),F48/F45-((F33+F34)/2)/((F31+F32)/2),"不適用"),"") | G80: =IF(ISNUMBER(G48),IF(AND(ISNUMBER(G48),ISNUMBER(G45),G45<>0,ISNUMBER(G33),ISNUMBER(G34),ISNUMBER(G31),ISNUMBER(G32)),G48/G45-((G33+G34)/2)/((G31+G32)/2),"不適用"),"") | H80: =IF(ISNUMBER(H48),IF(AND(ISNUMBER(H48),ISNUMBER(H45),H45<>0,ISNUMBER(H33),ISNUMBER(H34),ISNUMBER(H31),ISNUMBER(H32)),H48/H45-((H33+H34)/2)/((H31+H32)/2),"不適用"),"")
A81: 差距｜CapEx（毛額）｜模型 vs 共識 | B81: % | C81: 不適用 | D81: 不適用 | E81: 不適用 | F81: 不適用 | G81: 不適用 | H81: 不適用
A82: 差距｜CapEx（毛額）｜模型 vs 指引中點 | B82: % | C82: =IF(AND(ISNUMBER(C40),ISNUMBER(C36),ISNUMBER(C37)),C40/(((C36+C37)/2))-1,"不適用") -> 0 | D82: =IF(AND(ISNUMBER(D40),ISNUMBER(D36),ISNUMBER(D37)),D40/(((D36+D37)/2))-1,"不適用") -> 不適用 | E82: =IF(AND(ISNUMBER(E40),ISNUMBER(E36),ISNUMBER(E37)),E40/(((E36+E37)/2))-1,"不適用") -> 不適用 | F82: =IF(AND(ISNUMBER(F40),ISNUMBER(F36),ISNUMBER(F37)),F40/(((F36+F37)/2))-1,"不適用") -> 不適用 | G82: =IF(AND(ISNUMBER(G40),ISNUMBER(G36),ISNUMBER(G37)),G40/(((G36+G37)/2))-1,"不適用") -> 不適用 | H82: =IF(AND(ISNUMBER(H40),ISNUMBER(H36),ISNUMBER(H37)),H40/(((H36+H37)/2))-1,"不適用") -> 不適用
A83: 差距｜CapEx（毛額）｜實際 vs 模型 | B83: % | C83: =IF(ISNUMBER(C49),IF(AND(ISNUMBER(C40),C40<>0),C49/(C40)-1,"不適用"),"") | D83: =IF(ISNUMBER(D49),IF(AND(ISNUMBER(D40),D40<>0),D49/(D40)-1,"不適用"),"") | E83: =IF(ISNUMBER(E49),IF(AND(ISNUMBER(E40),E40<>0),E49/(E40)-1,"不適用"),"") | F83: =IF(ISNUMBER(F49),IF(AND(ISNUMBER(F40),F40<>0),F49/(F40)-1,"不適用"),"") | G83: =IF(ISNUMBER(G49),IF(AND(ISNUMBER(G40),G40<>0),G49/(G40)-1,"不適用"),"") | H83: =IF(ISNUMBER(H49),IF(AND(ISNUMBER(H40),H40<>0),H49/(H40)-1,"不適用"),"")
A84: 差距｜CapEx（毛額）｜實際 vs 共識 | B84: % | C84: =IF(ISNUMBER(C49),"不適用","") | D84: =IF(ISNUMBER(D49),"不適用","") | E84: =IF(ISNUMBER(E49),"不適用","") | F84: =IF(ISNUMBER(F49),"不適用","") | G84: =IF(ISNUMBER(G49),"不適用","") | H84: =IF(ISNUMBER(H49),"不適用","")
A85: 差距｜CapEx（毛額）｜實際 vs 指引中點 | B85: % | C85: =IF(ISNUMBER(C49),IF(AND(ISNUMBER(C36),ISNUMBER(C37)),C49/(((C36+C37)/2))-1,"不適用"),"") | D85: =IF(ISNUMBER(D49),IF(AND(ISNUMBER(D36),ISNUMBER(D37)),D49/(((D36+D37)/2))-1,"不適用"),"") | E85: =IF(ISNUMBER(E49),IF(AND(ISNUMBER(E36),ISNUMBER(E37)),E49/(((E36+E37)/2))-1,"不適用"),"") | F85: =IF(ISNUMBER(F49),IF(AND(ISNUMBER(F36),ISNUMBER(F37)),F49/(((F36+F37)/2))-1,"不適用"),"") | G85: =IF(ISNUMBER(G49),IF(AND(ISNUMBER(G36),ISNUMBER(G37)),G49/(((G36+G37)/2))-1,"不適用"),"") | H85: =IF(ISNUMBER(H49),IF(AND(ISNUMBER(H36),ISNUMBER(H37)),H49/(((H36+H37)/2))-1,"不適用"),"")
A86: 差距｜季末 Accepted MW｜模型 vs 共識 | B86: MW | C86: 不適用 | D86: 不適用 | E86: 不適用 | F86: 不適用 | G86: 不適用 | H86: 不適用
A87: 差距｜季末 Accepted MW｜模型 vs 指引中點 | B87: MW | C87: 不適用 | D87: 不適用 | E87: 不適用 | F87: 不適用 | G87: 不適用 | H87: 不適用
A88: 差距｜季末 Accepted MW｜實際 vs 模型 | B88: MW | C88: =IF(ISNUMBER(C50),IF(AND(ISNUMBER(C19)),C50-(C19),"不適用"),"") | D88: =IF(ISNUMBER(D50),IF(AND(ISNUMBER(D19)),D50-(D19),"不適用"),"") | E88: =IF(ISNUMBER(E50),IF(AND(ISNUMBER(E19)),E50-(E19),"不適用"),"") | F88: =IF(ISNUMBER(F50),IF(AND(ISNUMBER(F19)),F50-(F19),"不適用"),"") | G88: =IF(ISNUMBER(G50),IF(AND(ISNUMBER(G19)),G50-(G19),"不適用"),"") | H88: =IF(ISNUMBER(H50),IF(AND(ISNUMBER(H19)),H50-(H19),"不適用"),"")
A89: 差距｜季末 Accepted MW｜實際 vs 共識 | B89: MW | C89: =IF(ISNUMBER(C50),"不適用","") | D89: =IF(ISNUMBER(D50),"不適用","") | E89: =IF(ISNUMBER(E50),"不適用","") | F89: =IF(ISNUMBER(F50),"不適用","") | G89: =IF(ISNUMBER(G50),"不適用","") | H89: =IF(ISNUMBER(H50),"不適用","")
A90: 差距｜季末 Accepted MW｜實際 vs 指引中點 | B90: MW | C90: =IF(ISNUMBER(C50),"不適用","") | D90: =IF(ISNUMBER(D50),"不適用","") | E90: =IF(ISNUMBER(E50),"不適用","") | F90: =IF(ISNUMBER(F50),"不適用","") | G90: =IF(ISNUMBER(G50),"不適用","") | H90: =IF(ISNUMBER(H50),"不適用","")
A91: 合計基準｜營收｜vs 共識 | B91: US$bn | C91: =IF(COUNT(C41,D41)=2,C41+D41,"不適用") -> 8.247 | D91: =IF(COUNT(C41,D41)=2,C41+D41,"不適用") -> 8.247 | E91: =IF(COUNT(E41,F41,G41,H41)=4,E41+F41+G41+H41,"不適用") -> 不適用 | F91: =IF(COUNT(E41,F41,G41,H41)=4,E41+F41+G41+H41,"不適用") -> 不適用 | G91: =IF(COUNT(E41,F41,G41,H41)=4,E41+F41+G41+H41,"不適用") -> 不適用 | H91: =IF(COUNT(E41,F41,G41,H41)=4,E41+F41+G41+H41,"不適用") -> 不適用 | J91: 所屬期間的季度共識合計
A92: 拆解｜營收｜vs 共識｜水準 | B92: US$bn | C92: =IF(AND(ISNUMBER(C91),C91<>0,ISNUMBER(C41),ISNUMBER(C22)),(損益!C8-C91)*(C41)/C91,"不適用") -> 0.07127513 | D92: =IF(AND(ISNUMBER(D91),D91<>0,ISNUMBER(D41),ISNUMBER(D22)),(損益!C8-D91)*(D41)/D91,"不適用") -> 0.09472487 | E92: =IF(AND(ISNUMBER(E91),E91<>0,ISNUMBER(E41),ISNUMBER(E22)),(損益!D8-E91)*(E41)/E91,"不適用") -> 不適用 | F92: =IF(AND(ISNUMBER(F91),F91<>0,ISNUMBER(F41),ISNUMBER(F22)),(損益!D8-F91)*(F41)/F91,"不適用") -> 不適用 | G92: =IF(AND(ISNUMBER(G91),G91<>0,ISNUMBER(G41),ISNUMBER(G22)),(損益!D8-G91)*(G41)/G91,"不適用") -> 不適用 | H92: =IF(AND(ISNUMBER(H91),H91<>0,ISNUMBER(H41),ISNUMBER(H22)),(損益!D8-H91)*(H41)/H91,"不適用") -> 不適用 | J92: (模型期間 − 比較期間) × 比較的季占比
A93: 拆解｜營收｜vs 共識｜分配 | B93: US$bn | C93: =IF(AND(ISNUMBER(C91),C91<>0,ISNUMBER(C41),ISNUMBER(C22)),(C22/損益!C8-(C41)/C91)*損益!C8,"不適用") -> 0.050391536 | D93: =IF(AND(ISNUMBER(D91),D91<>0,ISNUMBER(D41),ISNUMBER(D22)),(D22/損益!C8-(D41)/D91)*損益!C8,"不適用") -> -0.050391536 | E93: =IF(AND(ISNUMBER(E91),E91<>0,ISNUMBER(E41),ISNUMBER(E22)),(E22/損益!D8-(E41)/E91)*損益!D8,"不適用") -> 不適用 | F93: =IF(AND(ISNUMBER(F91),F91<>0,ISNUMBER(F41),ISNUMBER(F22)),(F22/損益!D8-(F41)/F91)*損益!D8,"不適用") -> 不適用 | G93: =IF(AND(ISNUMBER(G91),G91<>0,ISNUMBER(G41),ISNUMBER(G22)),(G22/損益!D8-(G41)/G91)*損益!D8,"不適用") -> 不適用 | H93: =IF(AND(ISNUMBER(H91),H91<>0,ISNUMBER(H41),ISNUMBER(H22)),(H22/損益!D8-(H41)/H91)*損益!D8,"不適用") -> 不適用 | J93: (模型季占比 − 比較季占比) × 模型期間；水準＋分配＝季度差距
A94: 合計基準｜營收｜vs 指引 | B94: US$bn | C94: =(輸入與假設!$C$325+輸入與假設!$D$325)/2-輸入與假設!$E$325 -> 8.147 | D94: =(輸入與假設!$C$325+輸入與假設!$D$325)/2-輸入與假設!$E$325 -> 8.147 | E94: 不適用 | F94: 不適用 | G94: 不適用 | H94: 不適用 | J94: 所屬期間的隱含指引中點（全年指引中點 − 1H 實際）
A95: 拆解｜營收｜vs 指引｜水準 | B95: US$bn | C95: =IF(AND(ISNUMBER(C94),C94<>0,ISNUMBER(((C31+C32)/2)),ISNUMBER(C22)),(損益!C8-C94)*(((C31+C32)/2))/C94,"不適用") -> 0.11509144 | D95: =IF(AND(ISNUMBER(D94),D94<>0,ISNUMBER(((D31+D32)/2)),ISNUMBER(D22)),(損益!C8-D94)*(((D31+D32)/2))/D94,"不適用") -> 不適用 | E95: =IF(AND(ISNUMBER(E94),E94<>0,ISNUMBER(((E31+E32)/2)),ISNUMBER(E22)),(損益!D8-E94)*(((E31+E32)/2))/E94,"不適用") -> 不適用 | F95: =IF(AND(ISNUMBER(F94),F94<>0,ISNUMBER(((F31+F32)/2)),ISNUMBER(F22)),(損益!D8-F94)*(((F31+F32)/2))/F94,"不適用") -> 不適用 | G95: =IF(AND(ISNUMBER(G94),G94<>0,ISNUMBER(((G31+G32)/2)),ISNUMBER(G22)),(損益!D8-G94)*(((G31+G32)/2))/G94,"不適用") -> 不適用 | H95: =IF(AND(ISNUMBER(H94),H94<>0,ISNUMBER(((H31+H32)/2)),ISNUMBER(H22)),(損益!D8-H94)*(((H31+H32)/2))/H94,"不適用") -> 不適用 | J95: (模型期間 − 比較期間) × 比較的季占比
A96: 拆解｜營收｜vs 指引｜分配 | B96: US$bn | C96: =IF(AND(ISNUMBER(C94),C94<>0,ISNUMBER(((C31+C32)/2)),ISNUMBER(C22)),(C22/損益!C8-(((C31+C32)/2))/C94)*損益!C8,"不適用") -> 0.022575222 | D96: =IF(AND(ISNUMBER(D94),D94<>0,ISNUMBER(((D31+D32)/2)),ISNUMBER(D22)),(D22/損益!C8-(((D31+D32)/2))/D94)*損益!C8,"不適用") -> 不適用 | E96: =IF(AND(ISNUMBER(E94),E94<>0,ISNUMBER(((E31+E32)/2)),ISNUMBER(E22)),(E22/損益!D8-(((E31+E32)/2))/E94)*損益!D8,"不適用") -> 不適用 | F96: =IF(AND(ISNUMBER(F94),F94<>0,ISNUMBER(((F31+F32)/2)),ISNUMBER(F22)),(F22/損益!D8-(((F31+F32)/2))/F94)*損益!D8,"不適用") -> 不適用 | G96: =IF(AND(ISNUMBER(G94),G94<>0,ISNUMBER(((G31+G32)/2)),ISNUMBER(G22)),(G22/損益!D8-(((G31+G32)/2))/G94)*損益!D8,"不適用") -> 不適用 | H96: =IF(AND(ISNUMBER(H94),H94<>0,ISNUMBER(((H31+H32)/2)),ISNUMBER(H22)),(H22/損益!D8-(((H31+H32)/2))/H94)*損益!D8,"不適用") -> 不適用 | J96: (模型季占比 − 比較季占比) × 模型期間；水準＋分配＝季度差距
A97: 原因｜營收｜vs 共識 | C97: =IF(ISNUMBER(C51),IF(ABS(C51)>輸入與假設!$C$301,IF(ISNUMBER(C92),IF(ABS(C93)>ABS(C92),"營收 vs 共識 "&IF(C51<0,"−","+")&TEXT(ABS(C51)*100,"#,##0.0")&"%"&"：拆法（分配 "&IF(C93<0,"−","+")&IF(ABS(C93)<0,"−","")&"$"&TEXT(ABS(ABS(C93)),"#,##0.000")&"bn"&"（Q3'26 占 2H26 "&TEXT((C22/損益!C8)*100,"#,##0.0")&"%"&"，共識合計 "&TEXT(((C41)/C91)*100,"#,##0.0")&"%"&"）；水準 "&IF(C92<0,"−","+")&IF(ABS(C92)<0,"−","")&"$"&TEXT(ABS(ABS(C92)),"#,##0.000")&"bn"&"）","營收 vs 共識 "&IF(C51<0,"−","+")&TEXT(ABS(C51)*100,"#,##0.0")&"%"&"：觀點（水準 "&IF(C92<0,"−","+")&IF(ABS(C92)<0,"−","")&"$"&TEXT(ABS(ABS(C92)),"#,##0.000")&"bn"&"（2H26 模型 "&IF(損益!C8<0,"−","")&"$"&TEXT(ABS(損益!C8),"#,##0.000")&"bn"&"，共識合計 "&IF(C91<0,"−","")&"$"&TEXT(ABS(C91),"#,##0.000")&"bn"&"）；分配 "&IF(C93<0,"−","+")&IF(ABS(C93)<0,"−","")&"$"&TEXT(ABS(ABS(C93)),"#,##0.000")&"bn"&"）"),"營收 vs 共識 "&IF(C51<0,"−","+")&TEXT(ABS(C51)*100,"#,##0.0")&"%"&"：未歸類（差異原因待補）"),""),"") | D97: =IF(ISNUMBER(D51),IF(ABS(D51)>輸入與假設!$C$301,IF(ISNUMBER(D92),IF(ABS(D93)>ABS(D92),"營收 vs 共識 "&IF(D51<0,"−","+")&TEXT(ABS(D51)*100,"#,##0.0")&"%"&"：拆法（分配 "&IF(D93<0,"−","+")&IF(ABS(D93)<0,"−","")&"$"&TEXT(ABS(ABS(D93)),"#,##0.000")&"bn"&"（Q4'26 占 2H26 "&TEXT((D22/損益!C8)*100,"#,##0.0")&"%"&"，共識合計 "&TEXT(((D41)/D91)*100,"#,##0.0")&"%"&"）；水準 "&IF(D92<0,"−","+")&IF(ABS(D92)<0,"−","")&"$"&TEXT(ABS(ABS(D92)),"#,##0.000")&"bn"&"）","營收 vs 共識 "&IF(D51<0,"−","+")&TEXT(ABS(D51)*100,"#,##0.0")&"%"&"：觀點（水準 "&IF(D92<0,"−","+")&IF(ABS(D92)<0,"−","")&"$"&TEXT(ABS(ABS(D92)),"#,##0.000")&"bn"&"（2H26 模型 "&IF(損益!C8<0,"−","")&"$"&TEXT(ABS(損益!C8),"#,##0.000")&"bn"&"，共識合計 "&IF(D91<0,"−","")&"$"&TEXT(ABS(D91),"#,##0.000")&"bn"&"）；分配 "&IF(D93<0,"−","+")&IF(ABS(D93)<0,"−","")&"$"&TEXT(ABS(ABS(D93)),"#,##0.000")&"bn"&"）"),"營收 vs 共識 "&IF(D51<0,"−","+")&TEXT(ABS(D51)*100,"#,##0.0")&"%"&"：未歸類（差異原因待補）"),""),"") | E97: =IF(ISNUMBER(E51),IF(ABS(E51)>輸入與假設!$C$301,IF(ISNUMBER(E92),IF(ABS(E93)>ABS(E92),"營收 vs 共識 "&IF(E51<0,"−","+")&TEXT(ABS(E51)*100,"#,##0.0")&"%"&"：拆法（分配 "&IF(E93<0,"−","+")&IF(ABS(E93)<0,"−","")&"$"&TEXT(ABS(ABS(E93)),"#,##0.000")&"bn"&"（Q1'27 占 FY27 "&TEXT((E22/損益!D8)*100,"#,##0.0")&"%"&"，共識合計 "&TEXT(((E41)/E91)*100,"#,##0.0")&"%"&"）；水準 "&IF(E92<0,"−","+")&IF(ABS(E92)<0,"−","")&"$"&TEXT(ABS(ABS(E92)),"#,##0.000")&"bn"&"）","營收 vs 共識 "&IF(E51<0,"−","+")&TEXT(ABS(E51)*100,"#,##0.0")&"%"&"：觀點（水準 "&IF(E92<0,"−","+")&IF(ABS(E92)<0,"−","")&"$"&TEXT(ABS(ABS(E92)),"#,##0.000")&"bn"&"（FY27 模型 "&IF(損益!D8<0,"−","")&"$"&TEXT(ABS(損益!D8),"#,##0.000")&"bn"&"，共識合計 "&IF(E91<0,"−","")&"$"&TEXT(ABS(E91),"#,##0.000")&"bn"&"）；分配 "&IF(E93<0,"−","+")&IF(ABS(E93)<0,"−","")&"$"&TEXT(ABS(ABS(E93)),"#,##0.000")&"bn"&"）"),"營收 vs 共識 "&IF(E51<0,"−","+")&TEXT(ABS(E51)*100,"#,##0.0")&"%"&"：未歸類（差異原因待補）"),""),"") | F97: =IF(ISNUMBER(F51),IF(ABS(F51)>輸入與假設!$C$301,IF(ISNUMBER(F92),IF(ABS(F93)>ABS(F92),"營收 vs 共識 "&IF(F51<0,"−","+")&TEXT(ABS(F51)*100,"#,##0.0")&"%"&"：拆法（分配 "&IF(F93<0,"−","+")&IF(ABS(F93)<0,"−","")&"$"&TEXT(ABS(ABS(F93)),"#,##0.000")&"bn"&"（Q2'27 占 FY27 "&TEXT((F22/損益!D8)*100,"#,##0.0")&"%"&"，共識合計 "&TEXT(((F41)/F91)*100,"#,##0.0")&"%"&"）；水準 "&IF(F92<0,"−","+")&IF(ABS(F92)<0,"−","")&"$"&TEXT(ABS(ABS(F92)),"#,##0.000")&"bn"&"）","營收 vs 共識 "&IF(F51<0,"−","+")&TEXT(ABS(F51)*100,"#,##0.0")&"%"&"：觀點（水準 "&IF(F92<0,"−","+")&IF(ABS(F92)<0,"−","")&"$"&TEXT(ABS(ABS(F92)),"#,##0.000")&"bn"&"（FY27 模型 "&IF(損益!D8<0,"−","")&"$"&TEXT(ABS(損益!D8),"#,##0.000")&"bn"&"，共識合計 "&IF(F91<0,"−","")&"$"&TEXT(ABS(F91),"#,##0.000")&"bn"&"）；分配 "&IF(F93<0,"−","+")&IF(ABS(F93)<0,"−","")&"$"&TEXT(ABS(ABS(F93)),"#,##0.000")&"bn"&"）"),"營收 vs 共識 "&IF(F51<0,"−","+")&TEXT(ABS(F51)*100,"#,##0.0")&"%"&"：未歸類（差異原因待補）"),""),"") | G97: =IF(ISNUMBER(G51),IF(ABS(G51)>輸入與假設!$C$301,IF(ISNUMBER(G92),IF(ABS(G93)>ABS(G92),"營收 vs 共識 "&IF(G51<0,"−","+")&TEXT(ABS(G51)*100,"#,##0.0")&"%"&"：拆法（分配 "&IF(G93<0,"−","+")&IF(ABS(G93)<0,"−","")&"$"&TEXT(ABS(ABS(G93)),"#,##0.000")&"bn"&"（Q3'27 占 FY27 "&TEXT((G22/損益!D8)*100,"#,##0.0")&"%"&"，共識合計 "&TEXT(((G41)/G91)*100,"#,##0.0")&"%"&"）；水準 "&IF(G92<0,"−","+")&IF(ABS(G92)<0,"−","")&"$"&TEXT(ABS(ABS(G92)),"#,##0.000")&"bn"&"）","營收 vs 共識 "&IF(G51<0,"−","+")&TEXT(ABS(G51)*100,"#,##0.0")&"%"&"：觀點（水準 "&IF(G92<0,"−","+")&IF(ABS(G92)<0,"−","")&"$"&TEXT(ABS(ABS(G92)),"#,##0.000")&"bn"&"（FY27 模型 "&IF(損益!D8<0,"−","")&"$"&TEXT(ABS(損益!D8),"#,##0.000")&"bn"&"，共識合計 "&IF(G91<0,"−","")&"$"&TEXT(ABS(G91),"#,##0.000")&"bn"&"）；分配 "&IF(G93<0,"−","+")&IF(ABS(G93)<0,"−","")&"$"&TEXT(ABS(ABS(G93)),"#,##0.000")&"bn"&"）"),"營收 vs 共識 "&IF(G51<0,"−","+")&TEXT(ABS(G51)*100,"#,##0.0")&"%"&"：未歸類（差異原因待補）"),""),"") | H97: =IF(ISNUMBER(H51),IF(ABS(H51)>輸入與假設!$C$301,IF(ISNUMBER(H92),IF(ABS(H93)>ABS(H92),"營收 vs 共識 "&IF(H51<0,"−","+")&TEXT(ABS(H51)*100,"#,##0.0")&"%"&"：拆法（分配 "&IF(H93<0,"−","+")&IF(ABS(H93)<0,"−","")&"$"&TEXT(ABS(ABS(H93)),"#,##0.000")&"bn"&"（Q4'27 占 FY27 "&TEXT((H22/損益!D8)*100,"#,##0.0")&"%"&"，共識合計 "&TEXT(((H41)/H91)*100,"#,##0.0")&"%"&"）；水準 "&IF(H92<0,"−","+")&IF(ABS(H92)<0,"−","")&"$"&TEXT(ABS(ABS(H92)),"#,##0.000")&"bn"&"）","營收 vs 共識 "&IF(H51<0,"−","+")&TEXT(ABS(H51)*100,"#,##0.0")&"%"&"：觀點（水準 "&IF(H92<0,"−","+")&IF(ABS(H92)<0,"−","")&"$"&TEXT(ABS(ABS(H92)),"#,##0.000")&"bn"&"（FY27 模型 "&IF(損益!D8<0,"−","")&"$"&TEXT(ABS(損益!D8),"#,##0.000")&"bn"&"，共識合計 "&IF(H91<0,"−","")&"$"&TEXT(ABS(H91),"#,##0.000")&"bn"&"）；分配 "&IF(H93<0,"−","+")&IF(ABS(H93)<0,"−","")&"$"&TEXT(ABS(ABS(H93)),"#,##0.000")&"bn"&"）"),"營收 vs 共識 "&IF(H51<0,"−","+")&TEXT(ABS(H51)*100,"#,##0.0")&"%"&"：未歸類（差異原因待補）"),""),"")
A98: 原因類型｜營收｜vs 共識 | C98: =IF(ISNUMBER(C51),IF(ABS(C51)>輸入與假設!$C$301,IF(ISNUMBER(C92),IF(ABS(C93)>ABS(C92),"拆法","觀點"),"未歸類"),""),"") | D98: =IF(ISNUMBER(D51),IF(ABS(D51)>輸入與假設!$C$301,IF(ISNUMBER(D92),IF(ABS(D93)>ABS(D92),"拆法","觀點"),"未歸類"),""),"") | E98: =IF(ISNUMBER(E51),IF(ABS(E51)>輸入與假設!$C$301,IF(ISNUMBER(E92),IF(ABS(E93)>ABS(E92),"拆法","觀點"),"未歸類"),""),"") | F98: =IF(ISNUMBER(F51),IF(ABS(F51)>輸入與假設!$C$301,IF(ISNUMBER(F92),IF(ABS(F93)>ABS(F92),"拆法","觀點"),"未歸類"),""),"") | G98: =IF(ISNUMBER(G51),IF(ABS(G51)>輸入與假設!$C$301,IF(ISNUMBER(G92),IF(ABS(G93)>ABS(G92),"拆法","觀點"),"未歸類"),""),"") | H98: =IF(ISNUMBER(H51),IF(ABS(H51)>輸入與假設!$C$301,IF(ISNUMBER(H92),IF(ABS(H93)>ABS(H92),"拆法","觀點"),"未歸類"),""),"")
A99: 原因｜營收｜vs 指引中點 | C99: =IF(ISNUMBER(C52),IF(OR(ABS(C52)>輸入與假設!$C$301,C22>C32,C22<C31),IF(ISNUMBER(C95),IF(ABS(C96)>ABS(C95),"營收 vs 指引中點 "&IF(C52<0,"−","+")&TEXT(ABS(C52)*100,"#,##0.0")&"%"&"：拆法（分配 "&IF(C96<0,"−","+")&IF(ABS(C96)<0,"−","")&"$"&TEXT(ABS(ABS(C96)),"#,##0.000")&"bn"&"（Q3'26 占 2H26 "&TEXT((C22/損益!C8)*100,"#,##0.0")&"%"&"，指引隱含 "&TEXT(((((C31+C32)/2))/C94)*100,"#,##0.0")&"%"&"）；水準 "&IF(C95<0,"−","+")&IF(ABS(C95)<0,"−","")&"$"&TEXT(ABS(ABS(C95)),"#,##0.000")&"bn"&"）","營收 vs 指引中點 "&IF(C52<0,"−","+")&TEXT(ABS(C52)*100,"#,##0.0")&"%"&"：觀點（水準 "&IF(C95<0,"−","+")&IF(ABS(C95)<0,"−","")&"$"&TEXT(ABS(ABS(C95)),"#,##0.000")&"bn"&"（2H26 模型 "&IF(損益!C8<0,"−","")&"$"&TEXT(ABS(損益!C8),"#,##0.000")&"bn"&"，指引隱含 "&IF(C94<0,"−","")&"$"&TEXT(ABS(C94),"#,##0.000")&"bn"&"）；分配 "&IF(C96<0,"−","+")&IF(ABS(C96)<0,"−","")&"$"&TEXT(ABS(ABS(C96)),"#,##0.000")&"bn"&"）"),"營收 vs 指引中點 "&IF(C52<0,"−","+")&TEXT(ABS(C52)*100,"#,##0.0")&"%"&"：未歸類（差異原因待補）"),""),"") -> 營收 vs 指引中點 +3.9%：觀點（水準 +$0.115bn（2H26 模型 $8.413bn，指引隱含 $8.147bn）；分配 +$0.023bn） | D99: =IF(ISNUMBER(D52),IF(OR(ABS(D52)>輸入與假設!$C$301,D22>D32,D22<D31),IF(ISNUMBER(D95),IF(ABS(D96)>ABS(D95),"營收 vs 指引中點 "&IF(D52<0,"−","+")&TEXT(ABS(D52)*100,"#,##0.0")&"%"&"：拆法（分配 "&IF(D96<0,"−","+")&IF(ABS(D96)<0,"−","")&"$"&TEXT(ABS(ABS(D96)),"#,##0.000")&"bn"&"（Q4'26 占 2H26 "&TEXT((D22/損益!C8)*100,"#,##0.0")&"%"&"，指引隱含 "&TEXT(((((D31+D32)/2))/D94)*100,"#,##0.0")&"%"&"）；水準 "&IF(D95<0,"−","+")&IF(ABS(D95)<0,"−","")&"$"&TEXT(ABS(ABS(D95)),"#,##0.000")&"bn"&"）","營收 vs 指引中點 "&IF(D52<0,"−","+")&TEXT(ABS(D52)*100,"#,##0.0")&"%"&"：觀點（水準 "&IF(D95<0,"−","+")&IF(ABS(D95)<0,"−","")&"$"&TEXT(ABS(ABS(D95)),"#,##0.000")&"bn"&"（2H26 模型 "&IF(損益!C8<0,"−","")&"$"&TEXT(ABS(損益!C8),"#,##0.000")&"bn"&"，指引隱含 "&IF(D94<0,"−","")&"$"&TEXT(ABS(D94),"#,##0.000")&"bn"&"）；分配 "&IF(D96<0,"−","+")&IF(ABS(D96)<0,"−","")&"$"&TEXT(ABS(ABS(D96)),"#,##0.000")&"bn"&"）"),"營收 vs 指引中點 "&IF(D52<0,"−","+")&TEXT(ABS(D52)*100,"#,##0.0")&"%"&"：未歸類（差異原因待補）"),""),"") | E99: =IF(ISNUMBER(E52),IF(OR(ABS(E52)>輸入與假設!$C$301,E22>E32,E22<E31),IF(ISNUMBER(E95),IF(ABS(E96)>ABS(E95),"營收 vs 指引中點 "&IF(E52<0,"−","+")&TEXT(ABS(E52)*100,"#,##0.0")&"%"&"：拆法（分配 "&IF(E96<0,"−","+")&IF(ABS(E96)<0,"−","")&"$"&TEXT(ABS(ABS(E96)),"#,##0.000")&"bn"&"（Q1'27 占 FY27 "&TEXT((E22/損益!D8)*100,"#,##0.0")&"%"&"，指引隱含 "&TEXT(((((E31+E32)/2))/E94)*100,"#,##0.0")&"%"&"）；水準 "&IF(E95<0,"−","+")&IF(ABS(E95)<0,"−","")&"$"&TEXT(ABS(ABS(E95)),"#,##0.000")&"bn"&"）","營收 vs 指引中點 "&IF(E52<0,"−","+")&TEXT(ABS(E52)*100,"#,##0.0")&"%"&"：觀點（水準 "&IF(E95<0,"−","+")&IF(ABS(E95)<0,"−","")&"$"&TEXT(ABS(ABS(E95)),"#,##0.000")&"bn"&"（FY27 模型 "&IF(損益!D8<0,"−","")&"$"&TEXT(ABS(損益!D8),"#,##0.000")&"bn"&"，指引隱含 "&IF(E94<0,"−","")&"$"&TEXT(ABS(E94),"#,##0.000")&"bn"&"）；分配 "&IF(E96<0,"−","+")&IF(ABS(E96)<0,"−","")&"$"&TEXT(ABS(ABS(E96)),"#,##0.000")&"bn"&"）"),"營收 vs 指引中點 "&IF(E52<0,"−","+")&TEXT(ABS(E52)*100,"#,##0.0")&"%"&"：未歸類（差異原因待補）"),""),"") | F99: =IF(ISNUMBER(F52),IF(OR(ABS(F52)>輸入與假設!$C$301,F22>F32,F22<F31),IF(ISNUMBER(F95),IF(ABS(F96)>ABS(F95),"營收 vs 指引中點 "&IF(F52<0,"−","+")&TEXT(ABS(F52)*100,"#,##0.0")&"%"&"：拆法（分配 "&IF(F96<0,"−","+")&IF(ABS(F96)<0,"−","")&"$"&TEXT(ABS(ABS(F96)),"#,##0.000")&"bn"&"（Q2'27 占 FY27 "&TEXT((F22/損益!D8)*100,"#,##0.0")&"%"&"，指引隱含 "&TEXT(((((F31+F32)/2))/F94)*100,"#,##0.0")&"%"&"）；水準 "&IF(F95<0,"−","+")&IF(ABS(F95)<0,"−","")&"$"&TEXT(ABS(ABS(F95)),"#,##0.000")&"bn"&"）","營收 vs 指引中點 "&IF(F52<0,"−","+")&TEXT(ABS(F52)*100,"#,##0.0")&"%"&"：觀點（水準 "&IF(F95<0,"−","+")&IF(ABS(F95)<0,"−","")&"$"&TEXT(ABS(ABS(F95)),"#,##0.000")&"bn"&"（FY27 模型 "&IF(損益!D8<0,"−","")&"$"&TEXT(ABS(損益!D8),"#,##0.000")&"bn"&"，指引隱含 "&IF(F94<0,"−","")&"$"&TEXT(ABS(F94),"#,##0.000")&"bn"&"）；分配 "&IF(F96<0,"−","+")&IF(ABS(F96)<0,"−","")&"$"&TEXT(ABS(ABS(F96)),"#,##0.000")&"bn"&"）"),"營收 vs 指引中點 "&IF(F52<0,"−","+")&TEXT(ABS(F52)*100,"#,##0.0")&"%"&"：未歸類（差異原因待補）"),""),"") | G99: =IF(ISNUMBER(G52),IF(OR(ABS(G52)>輸入與假設!$C$301,G22>G32,G22<G31),IF(ISNUMBER(G95),IF(ABS(G96)>ABS(G95),"營收 vs 指引中點 "&IF(G52<0,"−","+")&TEXT(ABS(G52)*100,"#,##0.0")&"%"&"：拆法（分配 "&IF(G96<0,"−","+")&IF(ABS(G96)<0,"−","")&"$"&TEXT(ABS(ABS(G96)),"#,##0.000")&"bn"&"（Q3'27 占 FY27 "&TEXT((G22/損益!D8)*100,"#,##0.0")&"%"&"，指引隱含 "&TEXT(((((G31+G32)/2))/G94)*100,"#,##0.0")&"%"&"）；水準 "&IF(G95<0,"−","+")&IF(ABS(G95)<0,"−","")&"$"&TEXT(ABS(ABS(G95)),"#,##0.000")&"bn"&"）","營收 vs 指引中點 "&IF(G52<0,"−","+")&TEXT(ABS(G52)*100,"#,##0.0")&"%"&"：觀點（水準 "&IF(G95<0,"−","+")&IF(ABS(G95)<0,"−","")&"$"&TEXT(ABS(ABS(G95)),"#,##0.000")&"bn"&"（FY27 模型 "&IF(損益!D8<0,"−","")&"$"&TEXT(ABS(損益!D8),"#,##0.000")&"bn"&"，指引隱含 "&IF(G94<0,"−","")&"$"&TEXT(ABS(G94),"#,##0.000")&"bn"&"）；分配 "&IF(G96<0,"−","+")&IF(ABS(G96)<0,"−","")&"$"&TEXT(ABS(ABS(G96)),"#,##0.000")&"bn"&"）"),"營收 vs 指引中點 "&IF(G52<0,"−","+")&TEXT(ABS(G52)*100,"#,##0.0")&"%"&"：未歸類（差異原因待補）"),""),"") | H99: =IF(ISNUMBER(H52),IF(OR(ABS(H52)>輸入與假設!$C$301,H22>H32,H22<H31),IF(ISNUMBER(H95),IF(ABS(H96)>ABS(H95),"營收 vs 指引中點 "&IF(H52<0,"−","+")&TEXT(ABS(H52)*100,"#,##0.0")&"%"&"：拆法（分配 "&IF(H96<0,"−","+")&IF(ABS(H96)<0,"−","")&"$"&TEXT(ABS(ABS(H96)),"#,##0.000")&"bn"&"（Q4'27 占 FY27 "&TEXT((H22/損益!D8)*100,"#,##0.0")&"%"&"，指引隱含 "&TEXT(((((H31+H32)/2))/H94)*100,"#,##0.0")&"%"&"）；水準 "&IF(H95<0,"−","+")&IF(ABS(H95)<0,"−","")&"$"&TEXT(ABS(ABS(H95)),"#,##0.000")&"bn"&"）","營收 vs 指引中點 "&IF(H52<0,"−","+")&TEXT(ABS(H52)*100,"#,##0.0")&"%"&"：觀點（水準 "&IF(H95<0,"−","+")&IF(ABS(H95)<0,"−","")&"$"&TEXT(ABS(ABS(H95)),"#,##0.000")&"bn"&"（FY27 模型 "&IF(損益!D8<0,"−","")&"$"&TEXT(ABS(損益!D8),"#,##0.000")&"bn"&"，指引隱含 "&IF(H94<0,"−","")&"$"&TEXT(ABS(H94),"#,##0.000")&"bn"&"）；分配 "&IF(H96<0,"−","+")&IF(ABS(H96)<0,"−","")&"$"&TEXT(ABS(ABS(H96)),"#,##0.000")&"bn"&"）"),"營收 vs 指引中點 "&IF(H52<0,"−","+")&TEXT(ABS(H52)*100,"#,##0.0")&"%"&"：未歸類（差異原因待補）"),""),"")
A100: 原因類型｜營收｜vs 指引中點 | C100: =IF(ISNUMBER(C52),IF(OR(ABS(C52)>輸入與假設!$C$301,C22>C32,C22<C31),IF(ISNUMBER(C95),IF(ABS(C96)>ABS(C95),"拆法","觀點"),"未歸類"),""),"") -> 觀點 | D100: =IF(ISNUMBER(D52),IF(OR(ABS(D52)>輸入與假設!$C$301,D22>D32,D22<D31),IF(ISNUMBER(D95),IF(ABS(D96)>ABS(D95),"拆法","觀點"),"未歸類"),""),"") | E100: =IF(ISNUMBER(E52),IF(OR(ABS(E52)>輸入與假設!$C$301,E22>E32,E22<E31),IF(ISNUMBER(E95),IF(ABS(E96)>ABS(E95),"拆法","觀點"),"未歸類"),""),"") | F100: =IF(ISNUMBER(F52),IF(OR(ABS(F52)>輸入與假設!$C$301,F22>F32,F22<F31),IF(ISNUMBER(F95),IF(ABS(F96)>ABS(F95),"拆法","觀點"),"未歸類"),""),"") | G100: =IF(ISNUMBER(G52),IF(OR(ABS(G52)>輸入與假設!$C$301,G22>G32,G22<G31),IF(ISNUMBER(G95),IF(ABS(G96)>ABS(G95),"拆法","觀點"),"未歸類"),""),"") | H100: =IF(ISNUMBER(H52),IF(OR(ABS(H52)>輸入與假設!$C$301,H22>H32,H22<H31),IF(ISNUMBER(H95),IF(ABS(H96)>ABS(H95),"拆法","觀點"),"未歸類"),""),"")
A101: 原因｜營收｜實際 vs 模型
A102: 原因類型｜營收｜實際 vs 模型
...

Sheet 運營_產能與收入
A1: 產能與收入 — 合約排程 vs 機房產能
A2: 兩條線獨立產生後相減：排程>容量→瓶頸（收不到）；容量>排程→剩餘產能（要靠新簽約賣掉）
A3: FY26 欄口徑：MW 為年底存量；標示「（模型期）」的收入列只含 2026 下半年——RPO 桶自 2026-06-30 起算，1H 收入已實現、不再受產能約束。1H 實際單列，兩者相加即 FY26 全年（見本頁「FY26 全年」列）。
A5: 項目 | B5: 單位 | C5: FY26 | D5: FY27 | E5: FY28 | F5: FY29 | G5: FY30 | I5: 公式／來源說明
A6: 模型期間 | C6: ="2026-07-01~12-31" -> 2026-07-01~12-31 | D6: ="2027 全年" -> 2027 全年 | E6: ="2028 全年" -> 2028 全年 | F6: ="2029 全年" -> 2029 全年 | G6: ="2030 全年" -> 2030 全年 | I6: FY26 的模型期只有下半年；1H 已實現的營收單列於下方
A7: 模型期長度（年） | C7: =輸入與假設!C$24 -> 0.5 | D7: =輸入與假設!D$24 -> 1 | E7: =輸入與假設!E$24 -> 1 | F7: =輸入與假設!F$24 -> 1 | G7: =輸入與假設!G$24 -> 1 | I7: 只用於下方三處：容量上限、電力、維護——把年率換算成該期金額
A8: （A）機房：容量上限
A9: Accepted MW（已驗收，單調不減） | B9: MW | C9: =MAX(0,輸入與假設!C$26) -> 1850 | D9: =MAX(輸入與假設!D$26,C9) -> 3100 | E9: =MAX(輸入與假設!E$26,D9) -> 4000 | F9: =MAX(輸入與假設!F$26,E9) -> 4800 | G9: =MAX(輸入與假設!G$26,F9) -> 5600 | I9: 引擎規則：不得低於前期（產能不會消失）
A10: Billable MW（上限為 Accepted） | B10: MW | C10: =MIN(MAX(0,輸入與假設!C$27),C9) -> 1700 | D10: =MIN(MAX(0,輸入與假設!D$27),D9) -> 2900 | E10: =MIN(MAX(0,輸入與假設!E$27),E9) -> 3739 | F10: =MIN(MAX(0,輸入與假設!F$27),F9) -> 4495 | G10: =MIN(MAX(0,輸入與假設!G$27),G9) -> 5250 | I10: 引擎規則：可計費不得超過已驗收
A11: 期初在役 MW | B11: MW | C11: =輸入與假設!$C$20 -> 1350 | D11: =C10 -> 1700 | E11: =D10 -> 2900 | F11: =E10 -> 3739 | G11: =F10 -> 4495 | I11: 前期期末＝本期期初
A12: 平均在役 MW（FY26 欄為下半年平均） | B12: MW | C12: =IF(輸入與假設!$C$21=1,(C11+C10)/2,C10) -> 1525 | D12: =IF(輸入與假設!$C$21=1,(D11+D10)/2,D10) -> 2300 | E12: =IF(輸入與假設!$C$21=1,(E11+E10)/2,E10) -> 3319.5 | F12: =IF(輸入與假設!$C$21=1,(F11+F10)/2,F10) -> 4117 | G12: =IF(輸入與假設!$C$21=1,(G11+G10)/2,G10) -> 4872.5 | I12: 開關在輸入頁：1＝(期初+期末)/2，0＝期末全期化
A13: 利用率 | B13: % | C13: =輸入與假設!C$28 -> 0.95 | D13: =輸入與假設!D$28 -> 0.95 | E13: =輸入與假設!E$28 -> 0.94 | F13: =輸入與假設!F$28 -> 0.93 | G13: =輸入與假設!G$28 -> 0.92
A14: 每 MW 年收入 | B14: US$bn/MW | C14: =輸入與假設!C$29 -> 0.0112 | D14: =輸入與假設!D$29 -> 0.0115 | E14: =輸入與假設!E$29 -> 0.0115 | F14: =輸入與假設!F$29 -> 0.011 | G14: =輸入與假設!G$29 -> 0.0105
A15: 容量上限（模型期最多能交付的收入） | B15: US$bn | C15: =C12*輸入與假設!C$29*輸入與假設!$C$22*輸入與假設!C$28*C7 -> 8.113 | D15: =D12*輸入與假設!D$29*輸入與假設!$C$22*輸入與假設!D$28*D7 -> 25.1275 | E15: =E12*輸入與假設!E$29*輸入與假設!$C$22*輸入與假設!E$28*E7 -> 35.883795 | F15: =F12*輸入與假設!F$29*輸入與假設!$C$22*輸入與假設!F$28*F7 -> 42.11691 | G15: =G12*輸入與假設!G$29*輸入與假設!$C$22*輸入與假設!G$28*G7 -> 47.06835 | I15: ＝平均在役 MW × 每 MW 年收入 × 利用率 × 期間係數。只看機房，不看合約
A16: （B）合約：排程 RPO
A17: 排程 RPO（模型期，依 10-Q 桶分攤） | B17: US$bn | C17: =(輸入與假設!$C$15+輸入與假設!$C$16)*(輸入與假設!C$25/輸入與假設!$C$18)*輸入與假設!$C$17 -> 13.19175 | D17: =(輸入與假設!$C$15+輸入與假設!$C$16)*(輸入與假設!D$25/輸入與假設!$C$18)*輸入與假設!$C$17 -> 26.3835 | E17: =(輸入與假設!$C$15+輸入與假設!$C$16)*(輸入與假設!E$25/輸入與假設!$C$18)*輸入與假設!$C$17 -> 25.74 | F17: =(輸入與假設!$C$15+輸入與假設!$C$16)*(輸入與假設!F$25/輸入與假設!$C$18)*輸入與假設!$C$17 -> 25.0965 | G17: =(輸入與假設!$C$15+輸入與假設!$C$16)*(輸入與假設!G$25/輸入與假設!$C$18)*輸入與假設!$C$17 -> 17.69625 | I17: ＝(6/30 RPO＋Q3 新增)×本期權重÷權重合計×五期認列比例。只看合約，不看機房
A18: （C）兩條線相減
A19: 產能瓶頸（模型期：排程 − 容量） | B19: US$bn | C19: =MAX(0,C17-C15) -> 5.07875 | D19: =MAX(0,D17-D15) -> 1.256 | E19: =MAX(0,E17-E15) -> 0 | F19: =MAX(0,F17-F15) -> 0 | G19: =MAX(0,G17-G15) -> 0 | I19: 合約有、機房沒有 → 本期收不到，且不遞延到下期（保守處理）
A20: 期初 RPO 轉換收入（模型期） | B20: US$bn | C20: =C17-C19 -> 8.113 | D20: =D17-D19 -> 25.1275 | E20: =E17-E19 -> 25.74 | F20: =F17-F19 -> 25.0965 | G20: =G17-G19 -> 17.69625 | I20: ＝排程 − 瓶頸。當瓶頸>0 時，此值恆等於容量上限
A21: 未被期初 RPO 占用的產能 | B21: US$bn | C21: =MAX(0,C15-C17) -> 0 | D21: =MAX(0,D15-D17) -> 0 | E21: =MAX(0,E15-E17) -> 10.143795 | F21: =MAX(0,F15-F17) -> 17.02041 | G21: =MAX(0,G15-G17) -> 29.3721 | I21: 容量 − 排程。機房有、期初合約沒占滿 → 要靠新簽約
A22: 新產能簽約率 | B22: % | C22: =輸入與假設!C$30 -> 1 | D22: =輸入與假設!D$30 -> 1 | E22: =輸入與假設!E$30 -> 0.9 | F22: =輸入與假設!F$30 -> 0.85 | G22: =輸入與假設!G$30 -> 0.8
A23: 新簽約收入 | B23: US$bn | C23: =C21*輸入與假設!C$30 -> 0 | D23: =D21*輸入與假設!D$30 -> 0 | E23: =E21*輸入與假設!E$30 -> 9.1294155 | F23: =F21*輸入與假設!F$30 -> 14.467348 | G23: =G21*輸入與假設!G$30 -> 23.49768 | I23: 尚未簽署的合約。FY28 起模型收入主要來自此列——8 GW 敘事的風險集中點
A24: 未售產能（浪費） | B24: US$bn | C24: =MAX(0,C15-C20-C23) -> 0 | D24: =MAX(0,D15-D20-D23) -> 0 | E24: =MAX(0,E15-E20-E23) -> 1.0143795 | F24: =MAX(0,F15-F20-F23) -> 2.5530615 | G24: =MAX(0,G15-G20-G23) -> 5.87442 | I24: 蓋好但賣不掉。Bernstein：簽約電力 74% 位於 Tier 3/4 市場
A25: 損益用算力收入（模型期＝RPO 轉換＋新簽約） | B25: US$bn | C25: =C20+C23 -> 8.113 | D25: =D20+D23 -> 25.1275 | E25: =E20+E23 -> 34.869416 | F25: =F20+F23 -> 39.563848 | G25: =G20+G23 -> 41.19393 | I25: 損益與評價頁的算力收入由此連結，確保現金與損益同一組數字
A26: 1H26 實際營收（10-Q，已實現） | B26: US$bn | C26: =輸入與假設!$C$223 -> 4.653 | D26: =0 -> 0 | E26: =0 -> 0 | F26: =0 -> 0 | G26: =0 -> 0 | I26: 2026-01-01 至 06-30 已認列營收。已實現，不受下半年產能約束，故不進入上方的瓶頸計算
A27: FY26 全年總營收（1H 實際＋模型期算力＋服務） | B27: US$bn | C27: =C26+C25+輸入與假設!C$33 -> 13.066 | D27: =D26+D25+輸入與假設!D$33 -> 26.1275 | E27: =E26+E25+輸入與假設!E$33 -> 36.669415 | F27: =F26+F25+輸入與假設!F$33 -> 42.363849 | G27: =G26+G25+輸入與假設!G$33 -> 44.99393 | I27: FY26 欄可直接對照公司全年指引 12.4–13.2；FY27 以後即為該年度總營收
A28: （D）收入 → 現金：三道折扣
A29: 客戶違約率 | B29: % | C29: =輸入與假設!C$31 -> 0.005 | D29: =輸入與假設!D$31 -> 0.01 | E29: =輸入與假設!E$31 -> 0.015 | F29: =輸入與假設!F$31 -> 0.02 | G29: =輸入與假設!G$31 -> 0.025
A30: 回收率 | B30: % | C30: =輸入與假設!C$32 -> 0.5 | D30: =輸入與假設!D$32 -> 0.5 | E30: =輸入與假設!E$32 -> 0.5 | F30: =輸入與假設!F$32 -> 0.5 | G30: =輸入與假設!G$32 -> 0.5
A31: 信用損失（期初 RPO 部分） | B31: US$bn | C31: =C20*輸入與假設!C$31*(1-輸入與假設!C$32) -> 0.0202825 | D31: =D20*輸入與假設!D$31*(1-輸入與假設!D$32) -> 0.1256375 | E31: =E20*輸入與假設!E$31*(1-輸入與假設!E$32) -> 0.19305 | F31: =F20*輸入與假設!F$31*(1-輸入與假設!F$32) -> 0.250965 | G31: =G20*輸入與假設!G$31*(1-輸入與假設!G$32) -> 0.22120313 | I31: ＝收入 × 違約率 × (1−回收率)
A32: 收現（期初 RPO 部分） | B32: US$bn | C32: =C20-C31 -> 8.0927175 | D32: =D20-D31 -> 25.001863 | E32: =E20-E31 -> 25.54695 | F32: =F20-F31 -> 24.845535 | G32: =G20-G31 -> 17.475047
A33: EBITDA 率（損益與資金共用） | B33: % | C33: =輸入與假設!C$87 -> 0.57752014 | D33: =輸入與假設!D$87 -> 0.58999674 | E33: =輸入與假設!E$87 -> 0.60279427 | F33: =輸入與假設!F$87 -> 0.59255589 | G33: =輸入與假設!G$87 -> 0.56910658 | I33: 起始→穩態線性爬升
A34: 模型期總營收（算力＋服務） | B34: US$bn | C34: =C25+輸入與假設!C$33 -> 8.413 | D34: =D25+輸入與假設!D$33 -> 26.1275 | E34: =E25+輸入與假設!E$33 -> 36.669415 | F34: =F25+輸入與假設!F$33 -> 42.363849 | G34: =G25+輸入與假設!G$33 -> 44.99393
A35: EBITDAR 率（EBITDA 率＋租金÷營收） | B35: % | C35: =輸入與假設!C$87+各期收支!C12/MAX(0.01,C34) -> 0.73679745 | D35: =輸入與假設!D$87+各期收支!D12/MAX(0.01,D34) -> 0.74075744 | E35: =輸入與假設!E$87+各期收支!E12/MAX(0.01,E34) -> 0.73165792 | F35: =輸入與假設!F$87+各期收支!F12/MAX(0.01,F34) -> 0.71348447 | G35: =輸入與假設!G$87+各期收支!G12/MAX(0.01,G34) -> 0.68446744 | I35: 租金前的 EBITDA 率。EBITDA 已扣租金，而資金模型把租金列在支出端，所以要加回，避免重複扣除
A36: RPO 現金（可支應資本用途） | B36: US$bn | C36: =C32*C35 -> 5.9626936 | D36: =D32*D35 -> 18.520316 | E36: =E32*E35 -> 18.691628 | F36: =F32*F35 -> 17.726903 | G36: =G32*G35 -> 11.961101 | I36: ×EBITDAR 率。租金與利息在支出頁單獨列示
A37: 新簽約現金 | B37: US$bn | C37: =C23*(1-輸入與假設!C$31*(1-輸入與假設!C$32))*C35 -> 0 | D37: =D23*(1-輸入與假設!D$31*(1-輸入與假設!D$32))*D35 -> 0 | E37: =E23*(1-輸入與假設!E$31*(1-輸入與假設!E$32))*E35 -> 6.6295121 | F37: =F23*(1-輸入與假設!F$31*(1-輸入與假設!F$32))*F35 -> 10.219006 | G37: =G23*(1-輸入與假設!G$31*(1-輸入與假設!G$32))*G35 -> 15.882354 | I37: 同樣扣信用損失、乘 EBITDAR 率
A39: 讀法：FY26（2H）與 FY27 瓶頸>0，合約多於機房；FY28 起反轉，收入愈來愈靠『新簽約收入』這一列。
A40: 把『新產能簽約率』調到 0，就能看到只靠期初 RPO 的資金缺口有多大——這是最重要的一個壓力測試。

Sheet 運營_站點
A1: 站點租賃 — 房東揭露 vs 10-Q 總額（檢驗租金路徑用）
A2: 10-Q 不揭露逐站租金；下表為房東公告的合約值（Interested-party），用來檢驗『每 MW 年租金』與模型租金路徑是否一致
A4: 站點 | B4: 房東 | C4: 契約 MW | D4: 已起租 MW | E4: 合約總值 $bn | F4: 年期 | G4: 年租金 $bn | H4: 每 MW 年租金 $m | I4: 起租時程 | J4: 10-Q 對應 | K4: 來源
A5: Helios（德州 Dickens） | B5: Galaxy (GLXY) | C5: 526 | D5: 133 | E5: 15 | F5: 15 | G5: =E5/F5 -> 1 | H5: =G5/C5*1000 -> 1.9011407 | I5: Ph I 133 MW 2026Q2 起租；Ph II 260 MW 2027H1 起；Ph III 133 MW | J5: 未交付 393 MW＝10-Q「單站上限 14.7／16 年」 | K5: Galaxy 2026-07-06：526 MW、年均租金 >$1bn、15 年＋2×5 年延長 [Interested-party]
A6: Polaris Forge 1（北達科他 Ellendale） | B6: Applied Digital (APLD) | C6: 400 | D6: 250 | E6: 11 | F6: 15 | G6: =E6/F6 -> 0.73333333 | H6: =G6/C6*1000 -> 1.8333333 | I6: 100 MW 2025Q4；150 MW 2026 年中；150 MW 2027 | J6: 大致落在未起租 35.5 內 | K6: APLD 2025-08-29／FQ2 法說：400 MW、約 $11bn、約 15 年 [Interested-party]
A7: Core Scientific 六站（Denton 等） | B7: Core Scientific (CORZ) | C7: 590 | D7: 250 | E7: 10.2 | F7: 12 | G7: =E7/F7 -> 0.85 | H7: =G7/C7*1000 -> 1.440678 | I7: 2026 年約 250 MW；2027 年初全數 590 MW | J7: 部分在帳、部分未起租；「按造價計租」355 MW 可能含部分 | K7: CORZ 2025-02-26：約 590 MW、$10.2bn、12 年；年均約 $850m [Interested-party]
A8: Kenilworth（新澤西 JV） | B8: JV（CRWV 持股 35%） | C8: 未揭露 | D8: 0 | E8: 未揭露 | F8: 15 | I8: 施工中；完工後起租 | J8: 10-Q：租金＝建造成本的一定比例，推定屬「按造價計租」355 MW | K8: 10-Q Note 3：15 年租約、租金依建造成本計；MW 與金額未揭露 [Verified]
A9: 具名站點合計 | C9: =SUM(C5:C8) -> 1516 | D9: =SUM(D5:D8) -> 633 | E9: =SUM(E5:E8) -> 36.2 | G9: =SUM(G5:G8) -> 2.5833333 | H9: =G9/C9*1000 -> 1.7040457 | K9: 加權每 MW 年租金＝具名站點的市場基準
A11: 對帳：具名站點 vs 10-Q 租賃承諾總額
A12: 10-Q 在帳租賃（未折現，已起租） | E12: 29.37 | K12: 營業 29.135＋融資 0.235 [Verified]
A13: 10-Q 未起租租賃（未折現） | E13: 35.5 | K13: 2026–2029 起租、7–16 年 [Verified]
A14: 10-Q 單站按造價計租上限 | E14: 14.7 | K14: 即 Helios 未交付 393 MW [Verified]
A15: 10-Q 已揭露租賃承諾合計 | E15: =SUM(E12:E14) -> 79.57 | K15: 另有 355 MW 按造價計租，金額未定，未含
A16: 減：具名站點合約總值 | E16: =-E9 -> -36.2
A17: ＝ 未具名站點（殘差） | E17: =E15+E16 -> 43.37 | K17: 43 座以上資料中心中未具名者（Equinix、Switch 等託管，以及其他房東）。殘差大是必然——公司不揭露逐站
A18: 殘差占 10-Q 總額 | E18: =E17/E15 -> 0.54505467
A20: 檢驗：模型租金路徑 ÷ 在役 MW vs 市場基準
A21: 項目 | B21: 單位 | C21: FY26 | D21: FY27 | E21: FY28 | F21: FY29 | G21: FY30
A22: 模型租金（在帳＋表外） | B22: US$bn | C22: =各期收支!C12 -> 1.34 | D22: =各期收支!D12 -> 3.939 | E22: =各期收支!E12 -> 4.7253548 | F22: =各期收支!F12 -> 5.123 | G22: =各期收支!G12 -> 5.1905385
A23: 平均在役 MW（Accepted） | B23: MW | C23: =(輸入與假設!C$129+輸入與假設!C$26)/2 -> 1350 | D23: =(輸入與假設!D$129+輸入與假設!D$26)/2 -> 2475 | E23: =(輸入與假設!E$129+輸入與假設!E$26)/2 -> 3550 | F23: =(輸入與假設!F$129+輸入與假設!F$26)/2 -> 4400 | G23: =(輸入與假設!G$129+輸入與假設!G$26)/2 -> 5200
A24: 模型期長度（年） | B24: 年 | C24: =輸入與假設!C$24 -> 0.5 | D24: =輸入與假設!D$24 -> 1 | E24: =輸入與假設!E$24 -> 1 | F24: =輸入與假設!F$24 -> 1 | G24: =輸入與假設!G$24 -> 1
A25: 模型每 MW 年租金 | B25: US$m/MW | C25: =C22/C24/C23*1000 -> 1.9851852 | D25: =D22/D24/D23*1000 -> 1.5915152 | E25: =E22/E24/E23*1000 -> 1.3310859 | F25: =F22/F24/F23*1000 -> 1.1643182 | G25: =G22/G24/G23*1000 -> 0.99818047 | K25: FY26 欄只含下半年租金、MW 取全年平均，略有低估
A26: 第三方租賃占比 | C26: 0.85 | K26: 其餘為自建／JV（Kenilworth、Lancaster），成本走 CapEx 或 JV 出資 [Assumed]
A27: 基準租金（MW×市場基準×占比） | B27: US$bn | C27: =C23*運營_站點!$H$9/1000*$C$26*C24 -> 0.97769624 | D27: =D23*運營_站點!$H$9/1000*$C$26*D24 -> 3.5848862 | E27: =E23*運營_站點!$H$9/1000*$C$26*E24 -> 5.141958 | F27: =F23*運營_站點!$H$9/1000*$C$26*F24 -> 6.373131 | G27: =G23*運營_站點!$H$9/1000*$C$26*G24 -> 7.5318821 | K27: 若 8 GW 多數比照 Helios／APLD／CORZ 的租金水準
A28: 差額（基準 − 模型） | B28: US$bn | C28: =C27-C22 -> -0.36230376 | D28: =D27-D22 -> -0.35411379 | E28: =E27-E22 -> 0.41660316 | F28: =F27-F22 -> 1.250131 | G28: =G27-G22 -> 2.3413437 | K28: 正值＝模型租金可能低估的金額
A29: 五期差額合計 | C29: =SUM(C28:G28) -> 3.2916603

Sheet 每MW經濟性
A1: 每 MW 經濟性（W2：Tokenomics 物理與產業數據 × 公司專屬輸入）
A2: 方法：資本支出 tokenomics／營運成本 bottomUp／收入 legacy（company.json → methodology.perMw）。MW 口徑：IT 關鍵電力。每 MW 值＝期間金額 ÷ 平均在役 MW ÷ 期間長度（年化）。
A4: 項目 | B4: 單位 | C4: FY26 | D4: FY27 | E4: FY28 | F4: FY29 | G4: FY30 | I4: 公式／來源說明
A5: 每 MW 經濟性彙總（每平均在役 MW、年化；US$m／MW／年；目前情境）
A6: 平均在役 MW（IT 關鍵電力） | B6: MW | C6: =IF(輸入與假設!$C$37=2,C50/SUMPRODUCT(C51:C55,輸入與假設!$E$65:$E$69),C50) -> 1675 | D6: =IF(輸入與假設!$C$37=2,D50/SUMPRODUCT(D51:D55,輸入與假設!$E$65:$E$69),D50) -> 2475 | E6: =IF(輸入與假設!$C$37=2,E50/SUMPRODUCT(E51:E55,輸入與假設!$E$65:$E$69),E50) -> 3550 | F6: =IF(輸入與假設!$C$37=2,F50/SUMPRODUCT(F51:F55,輸入與假設!$E$65:$E$69),F50) -> 4400 | G6: =IF(輸入與假設!$C$37=2,G50/SUMPRODUCT(G51:G55,輸入與假設!$E$65:$E$69),G50) -> 5200 | I6: 公司 MW 口徑＝IT 時同上；設施口徑時 ÷ IF_FacilityGW
A7: 平均在役 MW（設施＝IT × IF_FacilityGW） | B7: MW | C7: =IF(輸入與假設!$C$37=2,C50/SUMPRODUCT(C51:C55,輸入與假設!$E$65:$E$69),C50)*SUMPRODUCT(C51:C55,輸入與假設!$E$65:$E$69) -> 2010 | D7: =IF(輸入與假設!$C$37=2,D50/SUMPRODUCT(D51:D55,輸入與假設!$E$65:$E$69),D50)*SUMPRODUCT(D51:D55,輸入與假設!$E$65:$E$69) -> 2970 | E7: =IF(輸入與假設!$C$37=2,E50/SUMPRODUCT(E51:E55,輸入與假設!$E$65:$E$69),E50)*SUMPRODUCT(E51:E55,輸入與假設!$E$65:$E$69) -> 4260 | F7: =IF(輸入與假設!$C$37=2,F50/SUMPRODUCT(F51:F55,輸入與假設!$E$65:$E$69),F50)*SUMPRODUCT(F51:F55,輸入與假設!$E$65:$E$69) -> 5280 | G7: =IF(輸入與假設!$C$37=2,G50/SUMPRODUCT(G51:G55,輸入與假設!$E$65:$E$69),G50)*SUMPRODUCT(G51:G55,輸入與假設!$E$65:$E$69) -> 6240 | I7: IF_FacilityGW 依在役世代加權（基準 1.2）
A8: 每 MW 年收入（算力＋服務） | B8: US$m/MW | C8: =運營_產能與收入!C34/MAX(0.000000001,C50)/輸入與假設!C$24*1000 -> 10.045373 | D8: =運營_產能與收入!D34/MAX(0.000000001,D50)/輸入與假設!D$24*1000 -> 10.556566 | E8: =運營_產能與收入!E34/MAX(0.000000001,E50)/輸入與假設!E$24*1000 -> 10.329413 | F8: =運營_產能與收入!F34/MAX(0.000000001,F50)/輸入與假設!F$24*1000 -> 9.6281474 | G8: =運營_產能與收入!G34/MAX(0.000000001,G50)/輸入與假設!G$24*1000 -> 8.6526788 | I8: 模型期總營收 ÷ 平均在役 MW ÷ 期間長度
A9: 其中：算力收入 | B9: US$m/MW | C9: =運營_產能與收入!C25/MAX(0.000000001,C50)/輸入與假設!C$24*1000 -> 9.6871642 | D9: =運營_產能與收入!D25/MAX(0.000000001,D50)/輸入與假設!D$24*1000 -> 10.152525 | E9: =運營_產能與收入!E25/MAX(0.000000001,E50)/輸入與假設!E$24*1000 -> 9.8223706 | F9: =運營_產能與收入!F25/MAX(0.000000001,F50)/輸入與假設!F$24*1000 -> 8.9917837 | G9: =運營_產能與收入!G25/MAX(0.000000001,G50)/輸入與假設!G$24*1000 -> 7.9219096
A10: 電費 | B10: US$m/MW | C10: =C61/MAX(0.000000001,C50)/輸入與假設!C$24*1000 -> 0.672768 | D10: =D61/MAX(0.000000001,D50)/輸入與假設!D$24*1000 -> 0.672768 | E10: =E61/MAX(0.000000001,E50)/輸入與假設!E$24*1000 -> 0.672768 | F10: =F61/MAX(0.000000001,F50)/輸入與假設!F$24*1000 -> 0.672768 | G10: =G61/MAX(0.000000001,G50)/輸入與假設!G$24*1000 -> 0.672768 | I10: 由下而上明細（下方）
A11: IT 維護 | B11: US$m/MW | C11: =C62/MAX(0.000000001,C50)/輸入與假設!C$24*1000 -> 0.9362069 | D11: =D62/MAX(0.000000001,D50)/輸入與假設!D$24*1000 -> 0.99153829 | E11: =E62/MAX(0.000000001,E50)/輸入與假設!E$24*1000 -> 1.0323653 | F11: =F62/MAX(0.000000001,F50)/輸入與假設!F$24*1000 -> 1.0541961 | G11: =G62/MAX(0.000000001,G50)/輸入與假設!G$24*1000 -> 1.0759512
A12: 人員、軟體、水與耗材 | B12: US$m/MW | C12: =C63/MAX(0.000000001,C50)/輸入與假設!C$24*1000 -> 0.325 | D12: =D63/MAX(0.000000001,D50)/輸入與假設!D$24*1000 -> 0.325 | E12: =E63/MAX(0.000000001,E50)/輸入與假設!E$24*1000 -> 0.325 | F12: =F63/MAX(0.000000001,F50)/輸入與假設!F$24*1000 -> 0.325 | G12: =G63/MAX(0.000000001,G50)/輸入與假設!G$24*1000 -> 0.325
A13: 財產稅與保險 | B13: US$m/MW | C13: =C64/MAX(0.000000001,C50)/輸入與假設!C$24*1000 -> 0.15603448 | D13: =D64/MAX(0.000000001,D50)/輸入與假設!D$24*1000 -> 0.16525638 | E13: =E64/MAX(0.000000001,E50)/輸入與假設!E$24*1000 -> 0.17206088 | F13: =F64/MAX(0.000000001,F50)/輸入與假設!F$24*1000 -> 0.17569935 | G13: =G64/MAX(0.000000001,G50)/輸入與假設!G$24*1000 -> 0.17932521
A14: 公司管銷與其他 | B14: US$m/MW | C14: =C67/MAX(0.000000001,C50)/輸入與假設!C$24*1000 -> 0.55395844 | D14: =D67/MAX(0.000000001,D50)/輸入與假設!D$24*1000 -> 0.58214848 | E14: =E67/MAX(0.000000001,E50)/輸入與假設!E$24*1000 -> 0.56962199 | F14: =F67/MAX(0.000000001,F50)/輸入與假設!F$24*1000 -> 0.53095026 | G14: =G67/MAX(0.000000001,G50)/輸入與假設!G$24*1000 -> 0.47715744
A15: 租金 | B15: US$m/MW | C15: =C70/MAX(0.000000001,C50)/輸入與假設!C$24*1000 -> 1.6 | D15: =D70/MAX(0.000000001,D50)/輸入與假設!D$24*1000 -> 1.5915152 | E15: =E70/MAX(0.000000001,E50)/輸入與假設!E$24*1000 -> 1.3310859 | F15: =F70/MAX(0.000000001,F50)/輸入與假設!F$24*1000 -> 1.1643182 | G15: =G70/MAX(0.000000001,G50)/輸入與假設!G$24*1000 -> 0.99818047
A16: 現金成本合計（含租金） | B16: US$m/MW | C16: =(運營_產能與收入!C34-運營_產能與收入!C34*輸入與假設!C$87)/MAX(0.000000001,C50)/輸入與假設!C$24*1000 -> 4.2439678 | D16: =(運營_產能與收入!D34-運營_產能與收入!D34*輸入與假設!D$87)/MAX(0.000000001,D50)/輸入與假設!D$24*1000 -> 4.3282263 | E16: =(運營_產能與收入!E34-運營_產能與收入!E34*輸入與假設!E$87)/MAX(0.000000001,E50)/輸入與假設!E$24*1000 -> 4.102902 | F16: =(運營_產能與收入!F34-運營_產能與收入!F34*輸入與假設!F$87)/MAX(0.000000001,F50)/輸入與假設!F$24*1000 -> 3.9229319 | G16: =(運營_產能與收入!G34-運營_產能與收入!G34*輸入與假設!G$87)/MAX(0.000000001,G50)/輸入與假設!G$24*1000 -> 3.7283824 | I16: ＝收入 − EBITDA（模型採用的 EBITDA 率；由下而上時＝上列各項合計）
A17: EBITDA | B17: US$m/MW | C17: =運營_產能與收入!C34*輸入與假設!C$87/MAX(0.000000001,C50)/輸入與假設!C$24*1000 -> 5.8014053 | D17: =運營_產能與收入!D34*輸入與假設!D$87/MAX(0.000000001,D50)/輸入與假設!D$24*1000 -> 6.2283394 | E17: =運營_產能與收入!E34*輸入與假設!E$87/MAX(0.000000001,E50)/輸入與假設!E$24*1000 -> 6.2265108 | F17: =運營_產能與收入!F34*輸入與假設!F$87/MAX(0.000000001,F50)/輸入與假設!F$24*1000 -> 5.7052155 | G17: =運營_產能與收入!G34*輸入與假設!G$87/MAX(0.000000001,G50)/輸入與假設!G$24*1000 -> 4.9242965 | I17: ＝營收 × EBITDA 率（損益與資金共用）
A18: D&A（模型車隊折舊） | B18: US$m/MW | C18: =輸入與假設!C$138/MAX(0.000000001,C50)/輸入與假設!C$24*1000 -> 5.7280542 | D18: =輸入與假設!D$138/MAX(0.000000001,D50)/輸入與假設!D$24*1000 -> 6.0301342 | E18: =輸入與假設!E$138/MAX(0.000000001,E50)/輸入與假設!E$24*1000 -> 5.9602439 | F18: =輸入與假設!F$138/MAX(0.000000001,F50)/輸入與假設!F$24*1000 -> 5.9940846 | G18: =輸入與假設!G$138/MAX(0.000000001,G50)/輸入與假設!G$24*1000 -> 5.9724241 | I18: 模型車隊折舊（期初毛 PP&E＋本期成長型×½）÷ 壽命；在役世代加權的建置成本 ÷ 壽命見『資本支出對照』
A19: 利息 | B19: US$m/MW | C19: =各期收支!C17/MAX(0.000000001,C50)/輸入與假設!C$24*1000 -> 2.8795068 | D19: =各期收支!D17/MAX(0.000000001,D50)/輸入與假設!D$24*1000 -> 2.838644 | E19: =各期收支!E17/MAX(0.000000001,E50)/輸入與假設!E$24*1000 -> 2.3909711 | F19: =各期收支!F17/MAX(0.000000001,F50)/輸入與假設!F$24*1000 -> 2.0667057 | G19: =各期收支!G17/MAX(0.000000001,G50)/輸入與假設!G$24*1000 -> 1.948121 | I19: 存量債務＋瀑布新債利息
A20: 稅前 | B20: US$m/MW | C20: =C17-C18-C19 -> -2.8061556 | D20: =D17-D18-D19 -> -2.6404389 | E20: =E17-E18-E19 -> -2.1247042 | F20: =F17-F18-F19 -> -2.3555748 | G20: =G17-G18-G19 -> -2.9962485 | I20: ＝EBITDA − D&A − 利息
A21: 每 MW 資本支出（新增 MW 的建置成本） | B21: US$m/MW | C21: =輸入與假設!C$120*輸入與假設!$C$118 -> 34.759438 | D21: =輸入與假設!D$120*輸入與假設!$C$118 -> 37.515928 | E21: =輸入與假設!E$120*輸入與假設!$C$118 -> 37.586352 | F21: =輸入與假設!F$120*輸入與假設!$C$118 -> 37.586352 | G21: =輸入與假設!G$120*輸入與假設!$C$118 -> 37.586352 | I21: 存量概念（每新增 MW 一次性），與上列年化數字不同
A22: 每設施 MW 年收入 | B22: US$m/MW | C22: =C8*C6/C7 -> 8.3711443 | D22: =D8*D6/D7 -> 8.797138 | E22: =E8*E6/E7 -> 8.607844 | F22: =F8*F6/F7 -> 8.0234562 | G22: =G8*G6/G7 -> 7.2105657
A23: 每設施 MW EBITDA | B23: US$m/MW | C23: =C17*C6/C7 -> 4.8345044 | D23: =D17*D6/D7 -> 5.1902828 | E23: =E17*E6/E7 -> 5.188759 | F23: =F17*F6/F7 -> 4.7543462 | G23: =G17*G6/G7 -> 4.1035804
A24: 讀法：每 MW 收入 − 現金成本（含租金）＝EBITDA；再扣 D&A 與利息＝稅前。W3 前後對照報告直接讀本表。
A25: ▸ 世代結構推導（期初在役 → 汰換 → 新增 → 期末／平均在役；MW，公司口徑）
A26: 期初在役 MW 合計 | B26: MW | C26: =輸入與假設!$C$41 -> 1500 | D26: =C44 -> 1850 | E26: =D44 -> 3100 | F26: =E44 -> 4000 | G26: =F44 -> 4800 | I26: FY26 期初＝2026-06-30 在役（世代組合起點）；之後＝前期期末
A27: 期初在役 MW｜Hopper H100 | B27: MW | C27: =輸入與假設!$C$41*輸入與假設!$C$42 -> 409.0005 | D27: =C39 -> 409.0005 | E27: =D39 -> 409.0005 | F27: =E39 -> 409.0005 | G27: =F39 -> 309.0005
A28: 期初在役 MW｜GB200 NVL72 | B28: MW | C28: =輸入與假設!$C$41*輸入與假設!$C$43 -> 440.5005 | D28: =C40 -> 510.5005 | E28: =D40 -> 510.5005 | F28: =E40 -> 510.5005 | G28: =F40 -> 510.5005
A29: 期初在役 MW｜GB300 NVL72 | B29: MW | C29: =輸入與假設!$C$41*輸入與假設!$C$44 -> 650.499 | D29: =C41 -> 930.499 | E29: =D41 -> 1555.499 | F29: =E41 -> 1555.499 | G29: =F41 -> 1555.499
A30: 期初在役 MW｜VR200 NVL72 | B30: MW | C30: =輸入與假設!$C$41*輸入與假設!$C$45 -> 0 | D30: =C42 -> 0 | E30: =D42 -> 625 | F30: =E42 -> 1525 | G30: =F42 -> 2425
A31: 期初在役 MW｜Rubin Ultra（MGX NVL 單架，72 GPU） | B31: MW | C31: =輸入與假設!$C$41*輸入與假設!$C$46 -> 0 | D31: =C43 -> 0 | E31: =D43 -> 0 | F31: =E43 -> 0 | G31: =F43 -> 0
A32: 汰換 MW（壽命到期批次，最舊世代先出） | B32: MW | C32: =MIN(IF(2026-輸入與假設!$C$114=2023,輸入與假設!$C$115,IF(2026-輸入與假設!$C$114=2024,輸入與假設!$C$116-輸入與假設!$C$115,IF(2026-輸入與假設!$C$114=2025,輸入與假設!$C$19-輸入與假設!$C$116,0))),C26) -> 0 | D32: =MIN(IF(2027-輸入與假設!$C$114=2023,輸入與假設!$C$115,IF(2027-輸入與假設!$C$114=2024,輸入與假設!$C$116-輸入與假設!$C$115,IF(2027-輸入與假設!$C$114=2025,輸入與假設!$C$19-輸入與假設!$C$116,0))),D26) -> 0 | E32: =MIN(IF(2028-輸入與假設!$C$114=2023,輸入與假設!$C$115,IF(2028-輸入與假設!$C$114=2024,輸入與假設!$C$116-輸入與假設!$C$115,IF(2028-輸入與假設!$C$114=2025,輸入與假設!$C$19-輸入與假設!$C$116,0))),E26) -> 0 | F32: =MIN(IF(2029-輸入與假設!$C$114=2023,輸入與假設!$C$115,IF(2029-輸入與假設!$C$114=2024,輸入與假設!$C$116-輸入與假設!$C$115,IF(2029-輸入與假設!$C$114=2025,輸入與假設!$C$19-輸入與假設!$C$116,0))),F26) -> 100 | G32: =MIN(IF(2030-輸入與假設!$C$114=2023,輸入與假設!$C$115,IF(2030-輸入與假設!$C$114=2024,輸入與假設!$C$116-輸入與假設!$C$115,IF(2030-輸入與假設!$C$114=2025,輸入與假設!$C$19-輸入與假設!$C$116,0))),G26) -> 260 | I32: ＝(本年 − GPU 經濟壽命) 那年新增的 MW（與『GPU 汰換 CapEx』同一批次），由世代清單中最舊的世代先出，以當期新增世代補回
A33: 汰換出｜Hopper H100 | B33: MW | C33: =MIN(C27,C32) -> 0 | D33: =MIN(D27,D32) -> 0 | E33: =MIN(E27,E32) -> 0 | F33: =MIN(F27,F32) -> 100 | G33: =MIN(G27,G32) -> 260
A34: 汰換出｜GB200 NVL72 | B34: MW | C34: =MIN(C28,MAX(0,C32-SUM(C27:C27))) -> 0 | D34: =MIN(D28,MAX(0,D32-SUM(D27:D27))) -> 0 | E34: =MIN(E28,MAX(0,E32-SUM(E27:E27))) -> 0 | F34: =MIN(F28,MAX(0,F32-SUM(F27:F27))) -> 0 | G34: =MIN(G28,MAX(0,G32-SUM(G27:G27))) -> 0
A35: 汰換出｜GB300 NVL72 | B35: MW | C35: =MIN(C29,MAX(0,C32-SUM(C27:C28))) -> 0 | D35: =MIN(D29,MAX(0,D32-SUM(D27:D28))) -> 0 | E35: =MIN(E29,MAX(0,E32-SUM(E27:E28))) -> 0 | F35: =MIN(F29,MAX(0,F32-SUM(F27:F28))) -> 0 | G35: =MIN(G29,MAX(0,G32-SUM(G27:G28))) -> 0
A36: 汰換出｜VR200 NVL72 | B36: MW | C36: =MIN(C30,MAX(0,C32-SUM(C27:C29))) -> 0 | D36: =MIN(D30,MAX(0,D32-SUM(D27:D29))) -> 0 | E36: =MIN(E30,MAX(0,E32-SUM(E27:E29))) -> 0 | F36: =MIN(F30,MAX(0,F32-SUM(F27:F29))) -> 0 | G36: =MIN(G30,MAX(0,G32-SUM(G27:G29))) -> 0
A37: 汰換出｜Rubin Ultra（MGX NVL 單架，72 GPU） | B37: MW | C37: =MIN(C31,MAX(0,C32-SUM(C27:C30))) -> 0 | D37: =MIN(D31,MAX(0,D32-SUM(D27:D30))) -> 0 | E37: =MIN(E31,MAX(0,E32-SUM(E27:E30))) -> 0 | F37: =MIN(F31,MAX(0,F32-SUM(F27:F30))) -> 0 | G37: =MIN(G31,MAX(0,G32-SUM(G27:G30))) -> 0
A38: 新增 MW（期末 Accepted − 期初，不為負） | B38: MW | C38: =MAX(0,運營_產能與收入!C9-C26) -> 350 | D38: =MAX(0,運營_產能與收入!D9-D26) -> 1250 | E38: =MAX(0,運營_產能與收入!E9-E26) -> 900 | F38: =MAX(0,運營_產能與收入!F9-F26) -> 800 | G38: =MAX(0,運營_產能與收入!G9-G26) -> 800
A39: 期末在役 MW｜Hopper H100 | B39: MW | C39: =C27-C33+輸入與假設!C58*(C38+C32) -> 409.0005 | D39: =D27-D33+輸入與假設!D58*(D38+D32) -> 409.0005 | E39: =E27-E33+輸入與假設!E58*(E38+E32) -> 409.0005 | F39: =F27-F33+輸入與假設!F58*(F38+F32) -> 309.0005 | G39: =G27-G33+輸入與假設!G58*(G38+G32) -> 49.0005
A40: 期末在役 MW｜GB200 NVL72 | B40: MW | C40: =C28-C34+輸入與假設!C59*(C38+C32) -> 510.5005 | D40: =D28-D34+輸入與假設!D59*(D38+D32) -> 510.5005 | E40: =E28-E34+輸入與假設!E59*(E38+E32) -> 510.5005 | F40: =F28-F34+輸入與假設!F59*(F38+F32) -> 510.5005 | G40: =G28-G34+輸入與假設!G59*(G38+G32) -> 510.5005
A41: 期末在役 MW｜GB300 NVL72 | B41: MW | C41: =C29-C35+輸入與假設!C60*(C38+C32) -> 930.499 | D41: =D29-D35+輸入與假設!D60*(D38+D32) -> 1555.499 | E41: =E29-E35+輸入與假設!E60*(E38+E32) -> 1555.499 | F41: =F29-F35+輸入與假設!F60*(F38+F32) -> 1555.499 | G41: =G29-G35+輸入與假設!G60*(G38+G32) -> 1555.499
A42: 期末在役 MW｜VR200 NVL72 | B42: MW | C42: =C30-C36+輸入與假設!C61*(C38+C32) -> 0 | D42: =D30-D36+輸入與假設!D61*(D38+D32) -> 625 | E42: =E30-E36+輸入與假設!E61*(E38+E32) -> 1525 | F42: =F30-F36+輸入與假設!F61*(F38+F32) -> 2425 | G42: =G30-G36+輸入與假設!G61*(G38+G32) -> 3485
A43: 期末在役 MW｜Rubin Ultra（MGX NVL 單架，72 GPU） | B43: MW | C43: =C31-C37+輸入與假設!C62*(C38+C32) -> 0 | D43: =D31-D37+輸入與假設!D62*(D38+D32) -> 0 | E43: =E31-E37+輸入與假設!E62*(E38+E32) -> 0 | F43: =F31-F37+輸入與假設!F62*(F38+F32) -> 0 | G43: =G31-G37+輸入與假設!G62*(G38+G32) -> 0
A44: 期末在役 MW 合計 | B44: MW | C44: =SUM(C39:C43) -> 1850 | D44: =SUM(D39:D43) -> 3100 | E44: =SUM(E39:E43) -> 4000 | F44: =SUM(F39:F43) -> 4800 | G44: =SUM(G39:G43) -> 5600
A45: 平均在役 MW｜Hopper H100 | B45: MW | C45: =(C27+C39)/2 -> 409.0005 | D45: =(D27+D39)/2 -> 409.0005 | E45: =(E27+E39)/2 -> 409.0005 | F45: =(F27+F39)/2 -> 359.0005 | G45: =(G27+G39)/2 -> 179.0005
A46: 平均在役 MW｜GB200 NVL72 | B46: MW | C46: =(C28+C40)/2 -> 475.5005 | D46: =(D28+D40)/2 -> 510.5005 | E46: =(E28+E40)/2 -> 510.5005 | F46: =(F28+F40)/2 -> 510.5005 | G46: =(G28+G40)/2 -> 510.5005
A47: 平均在役 MW｜GB300 NVL72 | B47: MW | C47: =(C29+C41)/2 -> 790.499 | D47: =(D29+D41)/2 -> 1242.999 | E47: =(E29+E41)/2 -> 1555.499 | F47: =(F29+F41)/2 -> 1555.499 | G47: =(G29+G41)/2 -> 1555.499
A48: 平均在役 MW｜VR200 NVL72 | B48: MW | C48: =(C30+C42)/2 -> 0 | D48: =(D30+D42)/2 -> 312.5 | E48: =(E30+E42)/2 -> 1075 | F48: =(F30+F42)/2 -> 1975 | G48: =(G30+G42)/2 -> 2955
A49: 平均在役 MW｜Rubin Ultra（MGX NVL 單架，72 GPU） | B49: MW | C49: =(C31+C43)/2 -> 0 | D49: =(D31+D43)/2 -> 0 | E49: =(E31+E43)/2 -> 0 | F49: =(F31+F43)/2 -> 0 | G49: =(G31+G43)/2 -> 0
A50: 平均在役 MW 合計 | B50: MW | C50: =SUM(C45:C49) -> 1675 | D50: =SUM(D45:D49) -> 2475 | E50: =SUM(E45:E49) -> 3550 | F50: =SUM(F45:F49) -> 4400 | G50: =SUM(G45:G49) -> 5200 | I50: 公司 MW 口徑（Accepted）；每 MW 值的分母
A51: 平均在役占比｜Hopper H100 | B51: % | C51: =C45/MAX(C50,0.000000001) -> 0.2441794 | D51: =D45/MAX(D50,0.000000001) -> 0.16525273 | E51: =E45/MAX(E50,0.000000001) -> 0.11521141 | F51: =F45/MAX(F50,0.000000001) -> 0.081591023 | G51: =G45/MAX(G50,0.000000001) -> 0.034423173
A52: 平均在役占比｜GB200 NVL72 | B52: % | C52: =C46/MAX(C50,0.000000001) -> 0.2838809 | D52: =D46/MAX(D50,0.000000001) -> 0.20626283 | E52: =E46/MAX(E50,0.000000001) -> 0.14380296 | F52: =F46/MAX(F50,0.000000001) -> 0.11602284 | G52: =G46/MAX(G50,0.000000001) -> 0.098173173
A53: 平均在役占比｜GB300 NVL72 | B53: % | C53: =C47/MAX(C50,0.000000001) -> 0.4719397 | D53: =D47/MAX(D50,0.000000001) -> 0.50222182 | E53: =E47/MAX(E50,0.000000001) -> 0.43816873 | F53: =F47/MAX(F50,0.000000001) -> 0.3535225 | G53: =G47/MAX(G50,0.000000001) -> 0.29913442
A54: 平均在役占比｜VR200 NVL72 | B54: % | C54: =C48/MAX(C50,0.000000001) -> 0 | D54: =D48/MAX(D50,0.000000001) -> 0.12626263 | E54: =E48/MAX(E50,0.000000001) -> 0.3028169 | F54: =F48/MAX(F50,0.000000001) -> 0.44886364 | G54: =G48/MAX(G50,0.000000001) -> 0.56826923
A55: 平均在役占比｜Rubin Ultra（MGX NVL 單架，72 GPU） | B55: % | C55: =C49/MAX(C50,0.000000001) -> 0 | D55: =D49/MAX(D50,0.000000001) -> 0 | E55: =E49/MAX(E50,0.000000001) -> 0 | F55: =F49/MAX(F50,0.000000001) -> 0 | G55: =G49/MAX(G50,0.000000001) -> 0
A56: ▸ 由下而上營運成本（租金前；US$bn，模型期）——模型採用
A57: 每 MW 電費（世代加權） | B57: US$m/MW | C57: =SUMPRODUCT(C51:C55,輸入與假設!$C$71:$C$75) -> 0.672768 | D57: =SUMPRODUCT(D51:D55,輸入與假設!$C$71:$C$75) -> 0.672768 | E57: =SUMPRODUCT(E51:E55,輸入與假設!$C$71:$C$75) -> 0.672768 | F57: =SUMPRODUCT(F51:F55,輸入與假設!$C$71:$C$75) -> 0.672768 | G57: =SUMPRODUCT(G51:G55,輸入與假設!$C$71:$C$75) -> 0.672768 | I57: Tokenomics IF_PowerCost（每 IT GW 年電費，已含平均用電比與 PUE）
A58: 每 MW IT 維護（世代加權） | B58: US$m/MW | C58: =SUMPRODUCT(C51:C55,輸入與假設!$D$71:$D$75) -> 0.9362069 | D58: =SUMPRODUCT(D51:D55,輸入與假設!$D$71:$D$75) -> 0.99153829 | E58: =SUMPRODUCT(E51:E55,輸入與假設!$D$71:$D$75) -> 1.0323653 | F58: =SUMPRODUCT(F51:F55,輸入與假設!$D$71:$D$75) -> 1.0541961 | G58: =SUMPRODUCT(G51:G55,輸入與假設!$D$71:$D$75) -> 1.0759512 | I58: Tokenomics IF_MaintIT
A59: 每 MW 人員、軟體、水與耗材 | B59: US$m/MW | C59: =SUMPRODUCT(C51:C55,輸入與假設!$E$71:$E$75) -> 0.325 | D59: =SUMPRODUCT(D51:D55,輸入與假設!$E$71:$E$75) -> 0.325 | E59: =SUMPRODUCT(E51:E55,輸入與假設!$E$71:$E$75) -> 0.325 | F59: =SUMPRODUCT(F51:F55,輸入與假設!$E$71:$E$75) -> 0.325 | G59: =SUMPRODUCT(G51:G55,輸入與假設!$E$71:$E$75) -> 0.325 | I59: Tokenomics IF_StaffSW
A60: 每 MW 財產稅與保險（只算 IT 部分） | B60: US$m/MW | C60: =SUMPRODUCT(C51:C55,輸入與假設!$F$71:$F$75) -> 0.15603448 | D60: =SUMPRODUCT(D51:D55,輸入與假設!$F$71:$F$75) -> 0.16525638 | E60: =SUMPRODUCT(E51:E55,輸入與假設!$F$71:$F$75) -> 0.17206088 | F60: =SUMPRODUCT(F51:F55,輸入與假設!$F$71:$F$75) -> 0.17569935 | G60: =SUMPRODUCT(G51:G55,輸入與假設!$F$71:$F$75) -> 0.17932521 | I60: Tokenomics IF_TaxIns × IT 資本占總資本比（廠房屬房東）
A61: 電費（金額） | B61: US$bn | C61: =C50*C57/1000*輸入與假設!C$24 -> 0.5634432 | D61: =D50*D57/1000*輸入與假設!D$24 -> 1.6651008 | E61: =E50*E57/1000*輸入與假設!E$24 -> 2.3883264 | F61: =F50*F57/1000*輸入與假設!F$24 -> 2.9601792 | G61: =G50*G57/1000*輸入與假設!G$24 -> 3.4983936 | I61: ＝平均在役 MW × 每 MW 值 ÷ 1000 × 期間長度
A62: IT 維護（金額） | B62: US$bn | C62: =C50*C58/1000*輸入與假設!C$24 -> 0.78407328 | D62: =D50*D58/1000*輸入與假設!D$24 -> 2.4540573 | E62: =E50*E58/1000*輸入與假設!E$24 -> 3.6648967 | F62: =F50*F58/1000*輸入與假設!F$24 -> 4.6384628 | G62: =G50*G58/1000*輸入與假設!G$24 -> 5.5949464
A63: 人員、軟體、水與耗材（金額） | B63: US$bn | C63: =C50*C59/1000*輸入與假設!C$24 -> 0.2721875 | D63: =D50*D59/1000*輸入與假設!D$24 -> 0.804375 | E63: =E50*E59/1000*輸入與假設!E$24 -> 1.15375 | F63: =F50*F59/1000*輸入與假設!F$24 -> 1.43 | G63: =G50*G59/1000*輸入與假設!G$24 -> 1.69
A64: 財產稅與保險（金額） | B64: US$bn | C64: =C50*C60/1000*輸入與假設!C$24 -> 0.13067888 | D64: =D50*D60/1000*輸入與假設!D$24 -> 0.40900954 | E64: =E50*E60/1000*輸入與假設!E$24 -> 0.61081611 | F64: =F50*F60/1000*輸入與假設!F$24 -> 0.77307714 | G64: =G50*G60/1000*輸入與假設!G$24 -> 0.93249107
A65: 模型期總營收（算力＋服務） | B65: US$bn | C65: =運營_產能與收入!C34 -> 8.413 | D65: =運營_產能與收入!D34 -> 26.1275 | E65: =運營_產能與收入!E34 -> 36.669415 | F65: =運營_產能與收入!F34 -> 42.363849 | G65: =運營_產能與收入!G34 -> 44.99393
A66: 管銷率 | B66: % | C66: =輸入與假設!$C$107 -> 0.055145631 | D66: =輸入與假設!$C$107 -> 0.055145631 | E66: =輸入與假設!$C$107 -> 0.055145631 | F66: =輸入與假設!$C$107 -> 0.055145631 | G66: =輸入與假設!$C$107 -> 0.055145631 | I66: C 區『由下而上營運成本輸入』：最近一季實際，各期持平 [Derived]
A67: 公司管銷與其他（金額） | B67: US$bn | C67: =C65*C66 -> 0.46394019 | D67: =D65*D66 -> 1.4408175 | E67: =E65*E66 -> 2.0221581 | F67: =F65*F66 -> 2.3361812 | G67: =G65*G66 -> 2.4812187
A68: 現金營運成本合計（租金前） | B68: US$bn | C68: =C61+C62+C63+C64+C67 -> 2.2143231 | D68: =D61+D62+D63+D64+D67 -> 6.7733601 | E68: =E61+E62+E63+E64+E67 -> 9.8399472 | F68: =F61+F62+F63+F64+F67 -> 12.1379 | G68: =G61+G62+G63+G64+G67 -> 14.19705 | I68: 廠房維護與廠房折舊不計（房東負擔，含在租金）
A69: 由下而上 EBITDAR 率 | B69: % | C69: =1-C68/MAX(0.01,C65) -> 0.73679745 | D69: =1-D68/MAX(0.01,D65) -> 0.74075744 | E69: =1-E68/MAX(0.01,E65) -> 0.73165792 | F69: =1-F68/MAX(0.01,F65) -> 0.71348447 | G69: =1-G68/MAX(0.01,G65) -> 0.68446744 | I69: ＝1 −（現金營運成本 ÷ 營收）
A70: 租金合計 | B70: US$bn | C70: =各期收支!C12 -> 1.34 | D70: =各期收支!D12 -> 3.939 | E70: =各期收支!E12 -> 4.7253548 | F70: =各期收支!F12 -> 5.123 | G70: =各期收支!G12 -> 5.1905385 | I70: 在帳＋表外現金租金（只扣一次：EBITDA 率＝EBITDAR 率 − 租金 ÷ 營收）
A71: 由下而上 EBITDA 率 | B71: % | C71: =C69-C70/MAX(0.01,C65) -> 0.57752014 | D71: =D69-D70/MAX(0.01,D65) -> 0.58999674 | E71: =E69-E70/MAX(0.01,E65) -> 0.60279427 | F71: =F69-F70/MAX(0.01,F65) -> 0.59255589 | G71: =G69-G70/MAX(0.01,G65) -> 0.56910658
A72: EBITDA 率（模型採用） | B72: % | C72: =輸入與假設!C$87 -> 0.57752014 | D72: =輸入與假設!D$87 -> 0.58999674 | E72: =輸入與假設!E$87 -> 0.60279427 | F72: =輸入與假設!F$87 -> 0.59255589 | G72: =輸入與假設!G$87 -> 0.56910658 | I72: ＝由下而上 EBITDA 率＋（穩態輸入 − 由下而上 FY30）× 期數 ÷ 4（穩態輸入預設＝由下而上 FY30，差額 0）
A73: ▸ 每 MW 收入對照（收入方法：備案 legacy——每 MW 年收入為輸入，以下為對照列，不入損益）
A74: 每 MW 年收入（模型採用，100% 計費時數） | B74: US$m/MW | C74: =輸入與假設!C$29*輸入與假設!$C$22*1000 -> 11.2 | D74: =輸入與假設!D$29*輸入與假設!$C$22*1000 -> 11.5 | E74: =輸入與假設!E$29*輸入與假設!$C$22*1000 -> 11.5 | F74: =輸入與假設!F$29*輸入與假設!$C$22*1000 -> 11 | G74: =輸入與假設!G$29*輸入與假設!$C$22*1000 -> 10.5 | I74: ＝B 區『每 MW 年收入』× 倍數；收入端另乘利用率
A75: 每 MW 年收入（計費後＝× 利用率） | B75: US$m/MW | C75: =C74*輸入與假設!C$28 -> 10.64 | D75: =D74*輸入與假設!D$28 -> 10.925 | E75: =E74*輸入與假設!E$28 -> 10.81 | F75: =F74*輸入與假設!F$28 -> 10.23 | G75: =G74*輸入與假設!G$28 -> 9.66
A76: 每 MW 年收入（v4.5 舊值，對照） | B76: US$m/MW | C76: 11.2 | D76: 11.5 | E76: 11.5 | F76: 11 | G76: 10.5 | I76: company.json → defaults.m.revMW（舊方法以期末 ARR 指引回推，只作對照）
A77: 期末 ARR 指引 ÷ 年底主動電力（公司數字，只作對照） | B77: US$m/MW | C77: =(18.5+19.5)/2/1.85 -> 10.27027 | I77: 法說：期末 ARR 18.5–19.5 ÷ 年底 1.85 GW [Derived]；公司數字不作參數（共同規則第 4 節）
A78: 每 MW GPU 數（世代加權） | B78: 顆/MW | C78: =SUMPRODUCT(C51:C55,輸入與假設!$C$77:$C$81) -> 547.61329 | D78: =SUMPRODUCT(D51:D55,輸入與假設!$C$77:$C$81) -> 503.57788 | E78: =SUMPRODUCT(E51:E55,輸入與假設!$C$77:$C$81) -> 456.61974 | F78: =SUMPRODUCT(F51:F55,輸入與假設!$C$77:$C$81) -> 419.92438 | G78: =SUMPRODUCT(G51:G55,輸入與假設!$C$77:$C$81) -> 385.44764 | I78: Tokenomics IF_GPUsPerGW ÷ 1000（× MW 換算）
A79: GPU 小時價格路線：每 MW 年收入 | B79: US$m/MW | C79: 不適用 | D79: 不適用 | E79: 不適用 | F79: 不適用 | G79: 不適用 | I79: ＝Σ 平均在役占比 × 每 MW GPU 數 × GPU 小時合約價 × 8,760 ÷ 10⁶（100% 計費時數）；company.json → pricing.gpuHr 未填（W1：長約價不足兩個獨立來源）→ 不適用
A80: 隱含每 GPU 小時價格（反算對照，不是輸入） | B80: US$/GPU-hr | C80: =C74*1000000/MAX(0.000000001,C78*8760) -> 2.3347476 | D80: =D74*1000000/MAX(0.000000001,D78*8760) -> 2.6069163 | E80: =E74*1000000/MAX(0.000000001,E78*8760) -> 2.875008 | F80: =F74*1000000/MAX(0.000000001,F78*8760) -> 2.9903188 | G80: =G74*1000000/MAX(0.000000001,G78*8760) -> 3.1097093 | I80: ＝每 MW 年收入 ÷（每 MW GPU 數 × 8,760）；利用率在收入端另乘，故不再除以利用率
A81: 每 GPU 小時經濟持有成本（GPU 數加權） | B81: US$/GPU-hr | C81: =SUMPRODUCT(C51:C55,輸入與假設!$C$77:$C$81,輸入與假設!$D$77:$D$81)/MAX(0.000000001,C78) -> 2.3084743 | D81: =SUMPRODUCT(D51:D55,輸入與假設!$C$77:$C$81,輸入與假設!$D$77:$D$81)/MAX(0.000000001,D78) -> 2.6209713 | E81: =SUMPRODUCT(E51:E55,輸入與假設!$C$77:$C$81,輸入與假設!$D$77:$D$81)/MAX(0.000000001,E78) -> 2.9805346 | F81: =SUMPRODUCT(F51:F55,輸入與假設!$C$77:$C$81,輸入與假設!$D$77:$D$81)/MAX(0.000000001,F78) -> 3.2933356 | G81: =SUMPRODUCT(G51:G55,輸入與假設!$C$77:$C$81,輸入與假設!$D$77:$D$81)/MAX(0.000000001,G78) -> 3.6447405 | I81: Tokenomics IF_GPUhrEcon（100% 時數、不含利潤）
A82: 隱含價格 ÷ GPU 小時持有成本 | B82: 倍 | C82: =C80/MAX(0.000000001,C81) -> 1.0113812 | D82: =D80/MAX(0.000000001,D81) -> 0.9946375 | E82: =E80/MAX(0.000000001,E81) -> 0.96459474 | F82: =F80/MAX(0.000000001,F81) -> 0.90799092 | G82: =G80/MAX(0.000000001,G81) -> 0.85320459
A83: 每 MW 經濟持有成本（不賠錢下限） | B83: US$m/MW | C83: =SUMPRODUCT(C51:C55,輸入與假設!$E$77:$E$81) -> 11.073965 | D83: =SUMPRODUCT(D51:D55,輸入與假設!$E$77:$E$81) -> 11.562001 | E83: =SUMPRODUCT(E51:E55,輸入與假設!$E$77:$E$81) -> 11.922105 | F83: =SUMPRODUCT(F51:F55,輸入與假設!$E$77:$E$81) -> 12.114659 | G83: =SUMPRODUCT(G51:G55,輸入與假設!$E$77:$E$81) -> 12.306544 | I83: Tokenomics IF_HoldEcon 依在役世代加權（100% 時數、含廠房資本回收；CRWV 廠房走租金，故此線高於 CRWV 的 IT 持有成本）
A84: 每 MW 年收入 ÷ 經濟持有成本 | B84: 倍 | C84: =C74/MAX(0.000000001,C83) -> 1.0113812 | D84: =D74/MAX(0.000000001,D83) -> 0.9946375 | E84: =E74/MAX(0.000000001,E83) -> 0.96459474 | F84: =F74/MAX(0.000000001,F83) -> 0.90799092 | G84: =G74/MAX(0.000000001,G83) -> 0.85320459
A85: 同業｜IREN–Microsoft 每 MW 年收入（GB300，5 年合約） | B85: US$m/MW | C85: 9.7 | D85: 9.7 | E85: 9.7 | F85: 9.7 | G85: 9.7 | I85: IREN Secures $9.7bn AI Cloud Contract with Microsoft（IREN 新聞稿）（2025-11-03）[Derived]；$9.7bn ÷ 5 年 ÷ 200 MW critical IT；同業合約（非 CoreWeave），含 20% 預付
A86: 市場價格｜H100 Silicon Data 租金指數 | B86: US$/GPU-hr | C86: 2.82 | I86: Hopper H100；市場現行租金指數（非長約）；Silicon Data H100 Index 頁面（含 B200、B300 指數）（2026-10-06）[Verified]
A87: 市場價格｜H100 CoreWeave 隨需牌價 | B87: US$/GPU-hr | C87: 6.155 | I87: Hopper H100；隨需牌價（長約最多 −60%）；CoreWeave Pricing（官網價目，頁面無日期）（2026-10-07）[Interested-party]
A88: 市場價格｜GB200 CoreWeave 隨需牌價 | B88: US$/GPU-hr | C88: 10.5 | I88: GB200 NVL72；隨需牌價（長約最多 −60%；與 Tokenomics L1_GPUhr_GB200_vsCW 同一底層來源）；CoreWeave Pricing（官網價目，頁面無日期）（2026-10-07）[Interested-party]
A89: 市場價格｜B200 Silicon Data 租金指數（GB200 類比） | B89: US$/GPU-hr | C89: 5.87 | I89: GB200 NVL72；市場指數；HGX B200 類比，區間 4.08–6.11；Silicon Data H100 Index 頁面（含 B200、B300 指數）（2026-10-06）[Analogy]
A90: 市場價格｜B300 Silicon Data 租金指數（GB300 類比） | B90: US$/GPU-hr | C90: 6.82 | I90: GB300 NVL72；市場指數；HGX B300 類比，區間 6.82–7.85；Silicon Data H100 Index 頁面（含 B200、B300 指數）（2026-10-06）[Analogy]
A91: 市場價格｜B300 Nebius 隨需牌價（GB300 類比） | B91: US$/GPU-hr | C91: 7.85 | I91: GB300 NVL72；隨需牌價（10/1 起 9.50）；Nebius NVIDIA GPU Pricing（官網價目）（2026-10-07）[Analogy]
A92: ▸ 每 MW 資本支出對照（US$m／MW；新增 MW 的世代加權）
A93: 每 MW 建置成本（模型採用） | B93: US$m/MW | C93: =輸入與假設!C$120 -> 34.759438 | D93: =輸入與假設!D$120 -> 37.515928 | E93: =輸入與假設!E$120 -> 37.586352 | F93: =輸入與假設!F$120 -> 37.586352 | G93: =輸入與假設!G$120 -> 37.586352
A94: Tokenomics IT 設備（IF_CapexIT） | B94: US$m/MW | C94: =SUMPRODUCT(輸入與假設!C$58:C$62,輸入與假設!$C$65:$C$69) -> 34.759438 | D94: =SUMPRODUCT(輸入與假設!D$58:D$62,輸入與假設!$C$65:$C$69) -> 37.515928 | E94: =SUMPRODUCT(輸入與假設!E$58:E$62,輸入與假設!$C$65:$C$69) -> 37.586352 | F94: =SUMPRODUCT(輸入與假設!F$58:F$62,輸入與假設!$C$65:$C$69) -> 37.586352 | G94: =SUMPRODUCT(輸入與假設!G$58:G$62,輸入與假設!$C$65:$C$69) -> 37.586352
A95: Tokenomics 含廠房合計（IF_CapexTotal；對照） | B95: US$m/MW | C95: =SUMPRODUCT(輸入與假設!C$58:C$62,輸入與假設!$D$65:$D$69) -> 47.429438 | D95: =SUMPRODUCT(輸入與假設!D$58:D$62,輸入與假設!$D$65:$D$69) -> 50.185928 | E95: =SUMPRODUCT(輸入與假設!E$58:E$62,輸入與假設!$D$65:$D$69) -> 50.256352 | F95: =SUMPRODUCT(輸入與假設!F$58:F$62,輸入與假設!$D$65:$D$69) -> 50.256352 | G95: =SUMPRODUCT(輸入與假設!G$58:G$62,輸入與假設!$D$65:$D$69) -> 50.256352 | I95: CRWV 機房以租約取得、不含廠房；合計只作對照
A96: v4.5 舊值（以 FY26 CapEx 指引校準） | B96: US$m/MW | C96: 34 | D96: 34 | E96: 34 | F96: 34 | G96: 34 | I96: 舊方法，只作對照
A97: 每 MW 建置成本 ÷ 壽命（在役世代加權；D&A 參考） | B97: US$m/MW | C97: =SUMPRODUCT(C51:C55,輸入與假設!$C$65:$C$69)/輸入與假設!$C$114 -> 5.2011495 | D97: =SUMPRODUCT(D51:D55,輸入與假設!$C$65:$C$69)/輸入與假設!$C$114 -> 5.508546 | E97: =SUMPRODUCT(E51:E55,輸入與假設!$C$65:$C$69)/輸入與假設!$C$114 -> 5.7353625 | F97: =SUMPRODUCT(F51:F55,輸入與假設!$C$65:$C$69)/輸入與假設!$C$114 -> 5.856645 | G97: =SUMPRODUCT(G51:G55,輸入與假設!$C$65:$C$69)/輸入與假設!$C$114 -> 5.9775069
A98: ▸ 最近一季實際對照（10-Q；不強制平衡）
A99: 最近一季平均在役 MW | B99: MW | C99: =輸入與假設!$C$41-輸入與假設!$C$108/2 -> 1250 | I99: ＝季末主動電力 − 當季新增 ÷ 2
A100: 最近一季現金營運成本（租金前，不含管銷） | B100: US$bn | C100: =輸入與假設!$C$96+輸入與假設!$C$97-輸入與假設!$C$102-輸入與假設!$C$103-輸入與假設!$C$104-輸入與假設!$C$105 -> 0.274 | I100: ＝營收成本＋技術與基礎設施 − D&A − SBC − 營業租賃成本 − 變動租賃成本
A101: 最近一季每 MW 現金營運成本（年化，不含管銷） | B101: US$m/MW | C101: =C100*4/C99*1000 -> 0.8768
...

Sheet 資產負債_既有債務
A1: 債務明細 — 10-Q Note 10（2026-06-30）逐筆＋存量利息推導
A2: 有效利率為 10-Q 揭露值（含折價攤銷，四捨五入至整數 %）。本頁算出的存量利息連回『輸入』頁，再進入支出與資金頁
A4: 工具 | B4: 類別 | C4: 到期 | D4: 有效利率 | E4: 6/30 本金 | F4: 年化利息 | I4: 備註
A5: DDTL 1.0 | B5: 追索 | C5: 2028-03 | D5: 0.15 | E5: 1.3 | F5: =D5*E5 -> 0.195 | I5: 資產層、隨客戶付款攤還 [Verified]
A6: DDTL 2.0 | B6: 追索 | C6: 2030-08 | D6: 0.11 | E6: 3.19 | F6: =D6*E6 -> 0.3509 | I6: [Verified]
A7: DDTL 2.1 | B7: 追索 | C7: 2031-03 | D7: 0.09 | E7: 3 | F7: =D7*E7 -> 0.27 | I7: [Verified]
A8: DDTL 3.0 | B8: 追索 | C8: 2030-08 | D8: 0.09 | E8: 2.215 | F8: =D8*E8 -> 0.19935 | I8: [Verified]
A9: DDTL 5.0 | B9: 追索 | C9: 2031-11 | D9: 0.09 | E9: 1.101 | F9: =D9*E9 -> 0.09909 | I9: SOFR+4.50%；額度 3.1 [Verified]
A10: 2030 Senior Notes | B10: 追索 | C10: 2030-06 | D10: 0.1 | E10: 2 | F10: =D10*E10 -> 0.2 | I10: 到期一次還本 [Verified]
A11: 2031 9.00% Senior Notes | B11: 追索 | C11: 2031-02 | D11: 0.1 | E11: 1.75 | F11: =D11*E11 -> 0.175 | I11: [Verified]
A12: 2031 9.75% Senior Notes | B12: 追索 | C12: 2031-10 | D12: 0.1 | E12: 2.75 | F12: =D12*E12 -> 0.275 | I12: 2026-04 發行 [Verified]
A13: 2032 9.625% Senior Notes | B13: 追索 | C13: 2032-07 | D13: 0.1 | E13: 1.25 | F13: =D13*E13 -> 0.125 | I13: 2026-06 發行 [Verified]
A14: 2032 EUR Senior Notes（€2.0bn） | B14: 追索 | C14: 2032-07 | D14: 0.09 | E14: 2.279 | F14: =D14*E14 -> 0.20511 | I14: 票面 8.50%；已做換匯換利避險 [Verified]
A15: 2031 可轉債 | B15: 追索 | C15: 2031-12 | D15: 0.02 | E15: 2.588 | F15: =D15*E15 -> 0.05176 | I15: [Verified]
A16: 2032 可轉債 | B16: 追索 | C16: 2032-10 | D16: 0.02 | E16: 4 | F16: =D16*E16 -> 0.08 | I16: 票面 1.75%；2026-04 發行 [Verified]
... A20: OEM 融資（非追索） | B20: 非追索 | C20: 2026-08～2028-08 | D20: 0.09 | E20: 0.882 | F20: =D20*E20 -> 0.07938 | I20: [Verified]
A21: 合計（6/30） | E21: =SUM(E5:E20) -> 35.551 | F21: =SUM(F5:F20) -> 2.99106 | I21: 應等於 10-Q 本金合計 35.551
A22: 加權有效利率 | D22: =F21/E21 -> 0.084134342 | I22: 公司 9/17 簡報：Q2 加權 8.3%、含新可轉債 pro forma 7.8%（該口徑用票面，本頁用有效利率）
A24: 9/17 期後：2033 可轉債 | D24: 0.02875 | E24: 3.7 | F24: =D24*E24 -> 0.106375 | I24: 轉換價 $97.85；2033 到期，不在五期還本表內 [Verified]
A26: 存量利息推導（本金依 10-Q 到期表遞減）
A27: 項目 | B27: 單位 | C27: FY26 | D27: FY27 | E27: FY28 | F27: FY29 | G27: FY30 | I27: 公式／來源說明
A28: 期初本金 | B28: US$bn | C28: =E21 -> 35.551 | D28: =C30 -> 31.138 | E28: =D30 -> 24.954 | F28: =E30 -> 20.538 | G28: =F30 -> 18.117 | I28: FY26 期初為 6/30 本金（模型期起點）
A29: 排程還本 | B29: US$bn | C29: =輸入與假設!C$160 -> 4.413 | D29: =輸入與假設!D$160 -> 6.184 | E29: =輸入與假設!E$160 -> 4.416 | F29: =輸入與假設!F$160 -> 2.421 | G29: =輸入與假設!G$160 -> 3.221 | I29: 10-Q 到期表
A30: 期末本金 | B30: US$bn | C30: =C28-C29 -> 31.138 | D30: =D28-D29 -> 24.954 | E30: =E28-E29 -> 20.538 | F30: =F28-F29 -> 18.117 | G30: =G28-G29 -> 14.896
A31: 平均本金 | B31: US$bn | C31: =(C28+C30)/2 -> 33.3445 | D31: =(D28+D30)/2 -> 28.046 | E31: =(E28+E30)/2 -> 22.746 | F31: =(F28+F30)/2 -> 19.3275 | G31: =(G28+G30)/2 -> 16.5065
A32: 存量債務利息 | B32: US$bn | C32: =C31*資產負債_既有債務!$D$22*輸入與假設!C$24 -> 1.4027088 | D32: =D31*資產負債_既有債務!$D$22*輸入與假設!D$24 -> 2.3596318 | E32: =E31*資產負債_既有債務!$D$22*輸入與假設!E$24 -> 1.9137197 | F32: =F31*資產負債_既有債務!$D$22*輸入與假設!F$24 -> 1.6261065 | G32: =G31*資產負債_既有債務!$D$22*輸入與假設!G$24 -> 1.3887635 | I32: ＝平均本金×加權有效利率×期間長度。限制：假設利率組合不變（實際上 15% 的 DDTL 1.0 先到期，後期利率會略降）
A33: 9/17 可轉債利息 | B33: US$bn | C33: =資產負債_既有債務!$F$24*輸入與假設!C$24 -> 0.0531875 | D33: =資產負債_既有債務!$F$24*輸入與假設!D$24 -> 0.106375 | E33: =資產負債_既有債務!$F$24*輸入與假設!E$24 -> 0.106375 | F33: =資產負債_既有債務!$F$24*輸入與假設!F$24 -> 0.106375 | G33: =資產負債_既有債務!$F$24*輸入與假設!G$24 -> 0.106375
A34: FY26 新增借款利息校準 | B34: US$bn | C34: =0.35 -> 0.35 | D34: =0 -> 0 | E34: =0 -> 0 | F34: =0 -> 0 | G34: =0 -> 0 | I34: Q3 指引 0.86–0.94／季含 Q3 新動用的 DDTL；存量推算約 0.73／季，差額×2 季≈0.35。FY27 起新增借款改由瀑布新債利息承接 [Derived]
A35: 存量利息合計（連回輸入頁） | B35: US$bn | C35: =C32+C33+C34 -> 1.8058963 | D35: =D32+D33+D34 -> 2.4660068 | E35: =E32+E33+E34 -> 2.0200947 | F35: =F32+F33+F34 -> 1.7324815 | G35: =G32+G33+G34 -> 1.4951385 | I35: v1.4 手動值為 1.8／2.7／2.3／2.0／1.8

Sheet 資產負債_新債與新股
A1: 新債與新股（類資產負債表：現金、債務、股本、槓桿）
A2: 全部為連結公式。FY26 欄的現金自 2026-06-30 起算（模型期），與 HTML『資產與負債 → 新債與新股』同口徑
A4: 項目 | B4: 單位 | C4: FY26 | D4: FY27 | E4: FY28 | F4: FY29 | G4: FY30 | I4: 公式／來源說明
A5: 現金
A6: 期初現金 | B6: US$bn | C6: =輸入與假設!$C$141 -> 5.5 | D6: =各期收支!C41 -> 2 | E6: =各期收支!D41 -> 2 | F6: =各期收支!E41 -> 2 | G6: =各期收支!F41 -> 2 | I6: FY26＝6/30 現金（模型期起點）
A7: 營運收支淨額（含 9/17 可轉債／ATM，不含瀑布） | B7: US$bn | C7: =各期收支!C71-輸入與假設!$C$141 -> -16.354101 | D7: =各期收支!D71-各期收支!C71 -> -32.643206 | E7: =各期收支!E71-各期收支!D71 -> -14.734544 | F7: =各期收支!F71-各期收支!E71 -> -10.654315 | G7: =各期收支!G71-各期收支!F71 -> -12.685614 | I7: ＝融資前累積現金的當期變動；負值即當期外部資金需求
A8: ＋ 瀑布：新債（額度＋資產層） | B8: US$bn | C8: =各期收支!C58 -> 13.459792 | D8: =各期收支!D58 -> 37.202843 | E8: =各期收支!E58 -> 21.202397 | F8: =各期收支!F58 -> 0 | G8: =各期收支!G58 -> 0.52492452
A9: ＋ 瀑布：高息債 | B9: US$bn | C9: =各期收支!C62 -> 0 | D9: =各期收支!D62 -> 0 | E9: =各期收支!E62 -> 0 | F9: =各期收支!F62 -> 7.4430893 | G9: =各期收支!G62 -> 10.223531
A10: ＋ 瀑布：股權募資 | B10: US$bn | C10: =各期收支!C61 -> 0 | D10: =各期收支!D61 -> 0 | E10: =各期收支!E61 -> 0 | F10: =各期收支!F61 -> 10.572249 | G10: =各期收支!G61 -> 10.572249
A11: − 新融資利息（新債＋高息債） | B11: US$bn | C11: =-各期收支!C63 -> -0.60569063 | D11: =-各期收支!D63 -> -4.5596371 | E11: =-各期收支!E63 -> -6.4678528 | F11: =-各期收支!F63 -> -7.3610235 | G11: =-各期收支!G63 -> -8.6350905
A12: 期末現金 | B12: US$bn | C12: =SUM(C6:C11) -> 2 | D12: =SUM(D6:D11) -> 2 | E12: =SUM(E6:E11) -> 2 | F12: =SUM(F6:F11) -> 2 | G12: =SUM(G6:G11) -> 2 | I12: 應等於『各期收支』期末累積現金（見下列驗算）
A13: 驗算：與各期收支期末現金差異 | B13: US$bn | C13: =C12-各期收支!C41 -> 0 | D13: =D12-各期收支!D41 -> 0 | E13: =E12-各期收支!E41 -> 7.1054274e-15 | F13: =F12-各期收支!F41 -> 7.1054274e-15 | G13: =G12-各期收支!G41 -> 1.8651747e-14 | I13: 應為 0
A14: 債務
A15: 既有債務期初（10-Q 本金） | B15: US$bn | C15: =35.551 -> 35.551 | D15: =C17 -> 31.138 | E15: =D17 -> 24.954 | F15: =E17 -> 20.538 | G15: =F17 -> 18.117
A16: − 排程還本（模型期） | B16: US$bn | C16: =-IF(輸入與假設!$C$146=1,輸入與假設!C$160,0) -> -4.413 | D16: =-IF(輸入與假設!$C$146=1,輸入與假設!D$160,0) -> -6.184 | E16: =-IF(輸入與假設!$C$146=1,輸入與假設!E$160,0) -> -4.416 | F16: =-IF(輸入與假設!$C$146=1,輸入與假設!F$160,0) -> -2.421 | G16: =-IF(輸入與假設!$C$146=1,輸入與假設!G$160,0) -> -3.221
A17: 既有債務期末 | B17: US$bn | C17: =各期收支!C54-3.7 -> 31.138 | D17: =各期收支!D54-3.7 -> 24.954 | E17: =各期收支!E54-3.7 -> 20.538 | F17: =各期收支!F54-3.7 -> 18.117 | G17: =各期收支!G54-3.7 -> 14.896 | I17: ＝依到期表遞減（關閉攤還時維持 35.551）
A18: ＋ 9/17 可轉債（2033 到期） | B18: US$bn | C18: =3.7 -> 3.7 | D18: =3.7 -> 3.7 | E18: =3.7 -> 3.7 | F18: =3.7 -> 3.7 | G18: =3.7 -> 3.7
A19: ＋ 瀑布新債餘額 | B19: US$bn | C19: =各期收支!C67 -> 13.459792 | D19: =各期收支!D67 -> 50.662635 | E19: =各期收支!E67 -> 71.865031 | F19: =各期收支!F67 -> 71.865031 | G19: =各期收支!G67 -> 72.389956
A20: ＋ 高息債餘額 | B20: US$bn | C20: =各期收支!C69 -> 0 | D20: =各期收支!D69 -> 0 | E20: =各期收支!E69 -> 0 | F20: =各期收支!F69 -> 7.4430893 | G20: =各期收支!G69 -> 17.666621
A21: 總債務 | B21: US$bn | C21: =SUM(C17:C20) -> 48.297792 | D21: =SUM(D17:D20) -> 79.316635 | E21: =SUM(E17:E20) -> 96.103031 | F21: =SUM(F17:F20) -> 101.12512 | G21: =SUM(G17:G20) -> 108.65258 | I21: 應等於『各期收支』期末總債務
A22: 淨負債（總債務 − 期末現金） | B22: US$bn | C22: =C21-C12 -> 46.297792 | D22: =D21-D12 -> 77.316635 | E22: =E21-E12 -> 94.103031 | F22: =F21-F12 -> 99.125121 | G22: =G21-G12 -> 106.65258
A23: 股本
A24: 基礎股數（含 ATM 上限、SBC 稀釋） | B24: bn | C24: =損益!C20 -> 0.587 | D24: =損益!D20 -> 0.59287 | E24: =損益!E20 -> 0.5987987 | F24: =損益!F20 -> 0.60478669 | G24: =損益!G20 -> 0.61083455
A25: ＋ 本期新股 | B25: bn | C25: =各期收支!C65 -> 0 | D25: =各期收支!D65 -> 0 | E25: =各期收支!E65 -> 0 | F25: =各期收支!F65 -> 0.13033333 | G25: =各期收支!G65 -> 0.13033333
A26: 總股數（期末） | B26: bn | C26: =損益!C21 -> 0.587 | D26: =損益!D21 -> 0.59287 | E26: =損益!E21 -> 0.5987987 | F26: =損益!F21 -> 0.73512002 | G26: =損益!G21 -> 0.87150122 | I26: ＝基礎股數＋累計新股
A27: 槓桿
A28: 期末 backlog | B28: US$bn | C28: =各期收支!C53 -> 115.50825 | D28: =各期收支!D53 -> 89.12475 | E28: =各期收支!E53 -> 99.902412 | F28: =各期收支!F53 -> 87.028228 | G28: =各期收支!G53 -> 90.985956
A29: 債務上限（債務／backlog × 期末 backlog） | B29: US$bn | C29: =各期收支!C55 -> 115.50825 | D29: =各期收支!D55 -> 89.12475 | E29: =各期收支!E55 -> 99.902412 | F29: =各期收支!F55 -> 87.028228 | G29: =各期收支!G55 -> 90.985956
A30: 總債務 ÷ 期末 backlog | B30: x | C30: =C21/MAX(0.01,C28) -> 0.41813283 | D30: =D21/MAX(0.01,D28) -> 0.88995071 | E30: =E21/MAX(0.01,E28) -> 0.96196908 | F30: =F21/MAX(0.01,F28) -> 1.1619807 | G30: =G21/MAX(0.01,G28) -> 1.1941687 | I30: 高息債不受 backlog 上限約束
A31: 總債務 ÷ EBITDA（年化） | B31: x | C31: =C21/MAX(0.01,損益!C19/輸入與假設!C$24) -> 4.9702617 | D31: =D21/MAX(0.01,損益!D19/輸入與假設!D$24) -> 5.1453724 | E31: =E21/MAX(0.01,損益!E19/輸入與假設!E$24) -> 4.3477442 | F31: =F21/MAX(0.01,損益!F19/輸入與假設!F$24) -> 4.0284161 | G31: =G21/MAX(0.01,損益!G19/輸入與假設!G$24) -> 4.2431901 | I31: FY26 模型期 EBITDA 以半年×2 年化

Sheet 資產負債_租賃承諾
A1: 租賃與承諾 — 10-Q（2026-06-30）原始揭露
A2: 本頁為硬編碼的申報數字（藍字），支出與資金頁的租金與還本列由此而來
A4: 在帳租賃到期表（未折現）
A5: 項目 | B5: 單位 | C5: 2026 下半 | D5: 2027 | E5: 2028 | F5: 2029 | G5: 2030 | H5: 其後
A6: 營業租賃付款 | B6: US$bn | C6: 1.028 | D6: 2.116 | E6: 2.306 | F6: 2.373 | G6: 2.289 | H6: 19.023
A7: 融資租賃付款 | B7: US$bn | C7: 0.012 | D7: 0.223 | E7: 0 | F7: 0 | G7: 0 | H7: 0
A8: 合計（＝支出頁「在帳現金租金」） | C8: =SUM(C6:C7) -> 1.04 | D8: =SUM(D6:D7) -> 2.339 | E8: =SUM(E6:E7) -> 2.306 | F8: =SUM(F6:F7) -> 2.373 | G8: =SUM(G6:G7) -> 2.289 | H8: =SUM(H6:H7) -> 19.023 | I8: 營業租賃負債現值 16.319、融資租賃 0.221；加權剩餘租期 12 年、折現率 10% [Verified]
A10: 債務本金到期表
A11: 項目 | B11: 單位 | C11: 2026 下半 | D11: 2027 | E11: 2028 | F11: 2029 | G11: 2030 | H11: 其後
A12: 本金（＝支出頁「排程還本」） | B12: US$bn | C12: 4.413 | D12: 6.184 | E12: 4.416 | F12: 2.421 | G12: 3.221 | H12: 14.896 | I12: 本金合計 35.551（DDTL 13.6、票據 16.6、OEM 5.1 等）[Verified]
A13: 合計 | C13: =SUM(C12:H12) -> 35.551
A15: 表外與契約性承諾（未入表）
A16: 項目 | B16: 單位 | C16: 金額 | D16: 時程 | E16: 入表？ | F16: 模型位置
A17: 未起租租賃（未折現） | B17: US$bn | C17: 35.5 | D17: 2026–2029 起租，7–16 年 | E17: 否 | F17: 表外現金租金
A18: 單站按造價計租，上限 | B18: US$bn | C18: 14.7 | D18: 393 MW 未交付，16 年 | E18: 否 | F18: 表外現金租金
A19: 按造價計租，355 MW | B19: US$bn | C19: 未定 | D19: 2026–2028 分期，金額未定 | E19: 否 | F19: 表外現金租金
A20: 承租人自備設備承諾 | B20: US$bn | C20: 1.2 | D20: 0.5–1.2，分期至 2028 | E20: 否 | F20: 併入毛 CapEx
A21: JV 出資承諾 | B21: US$bn | C21: 1.7 | D21: 已付 0.55 | E21: 否 | F21: JV／策略投資出資
A22: VIE 最大損失暴露 | B22: US$bn | C22: 0.108 | D22: — | E22: 否 | F22: 不另列
A23: 可用信用額度（RCF＋DDTL 未動用） | B23: US$bn | C23: 10.014 | D23: DDTL 4.0 可動用至 2027-06 | E23: 否（來源） | F23: 選用開關
A24: 已揭露金額之承諾合計（未起租＋單站上限） | C24: =C17+C18 -> 50.2
A25: 模型表外租金五期合計 | C25: =SUM(各期收支!C11:G11) -> 9.9708933
A26: 模型表外租金尾端（FY30×12 年） | C26: =各期收支!G11*12 -> 34.818462
A27: 模型路徑合計 ÷ 已承諾（≥0.8 為合理） | C27: =(C25+C26)/C24 -> 0.89221822 | I27: 8 GW 路徑所需新租約多數尚未簽署，路徑高於已承諾屬假設而非錯誤

Sheet 損益
A1: 損益（類損益表）— 與資金模型同一組收入
A2: 算力收入、Cash CapEx、利息皆由前面分頁連結而來；改資金假設，此頁會跟著動
A4: 項目 | B4: 單位 | C4: FY26 | D4: FY27 | E4: FY28 | F4: FY29 | G4: FY30 | I4: 公式／來源說明
A5: 損益表
A6: 算力收入 | B6: US$bn | C6: =運營_產能與收入!C25 -> 8.113 | D6: =運營_產能與收入!D25 -> 25.1275 | E6: =運營_產能與收入!E25 -> 34.869416 | F6: =運營_產能與收入!F25 -> 39.563848 | G6: =運營_產能與收入!G25 -> 41.19393 | I6: ＝RPO 轉換＋新簽約
A7: 非算力服務 | B7: US$bn | C7: =輸入與假設!C$33 -> 0.3 | D7: =輸入與假設!D$33 -> 1 | E7: =輸入與假設!E$33 -> 1.8 | F7: =輸入與假設!F$33 -> 2.8 | G7: =輸入與假設!G$33 -> 3.8
A8: 總營收 | B8: US$bn | C8: =C6+C7 -> 8.413 | D8: =D6+D7 -> 26.1275 | E8: =E6+E7 -> 36.669415 | F8: =F6+F7 -> 42.363849 | G8: =G6+G7 -> 44.99393
A9: EBITDA 率 | B9: % | C9: =輸入與假設!C$87 -> 0.57752014 | D9: =輸入與假設!D$87 -> 0.58999674 | E9: =輸入與假設!E$87 -> 0.60279427 | F9: =輸入與假設!F$87 -> 0.59255589 | G9: =輸入與假設!G$87 -> 0.56910658
A10: 營業利益（EBIT） | B10: US$bn | C10: =C8*輸入與假設!C$87-輸入與假設!C$138 -> 0.061431578 | D10: =D8*輸入與假設!D$87-輸入與假設!D$138 -> 0.49055772 | E10: =E8*輸入與假設!E$87-輸入與假設!E$138 -> 0.94524762 | F10: =F8*輸入與假設!F$87-輸入與假設!F$138 -> -1.271024 | G10: =G8*輸入與假設!G$87-輸入與假設!G$138 -> -5.4502634 | I10: ＝營收×EBITDA 率 − 車隊 D&A
A11: 利息（含瀑布新債） | B11: US$bn | C11: =各期收支!C17 -> 2.4115869 | D11: =各期收支!D17 -> 7.0256439 | E11: =各期收支!E17 -> 8.4879476 | F11: =各期收支!F17 -> 9.093505 | G11: =各期收支!G17 -> 10.130229
A12: 稅前損益 | B12: US$bn | C12: =C10-C11 -> -2.3501553 | D12: =D10-D11 -> -6.5350862 | E12: =E10-E11 -> -7.5427 | F12: =F10-F11 -> -10.364529 | G12: =G10-G11 -> -15.580492
A13: NOL 期初餘額 | B13: US$bn | C13: =輸入與假設!$C$172 -> 4 | D13: =C15 -> 6.3501553 | E13: =D15 -> 12.885242 | F13: =E15 -> 20.427941 | G13: =F15 -> 30.792471 | I13: 6/30 累積虧損約 4.0
A14: 本期動用 NOL | B14: US$bn | C14: =MIN(C13,MAX(0,C12)*輸入與假設!$C$173) -> 0 | D14: =MIN(D13,MAX(0,D12)*輸入與假設!$C$173) -> 0 | E14: =MIN(E13,MAX(0,E12)*輸入與假設!$C$173) -> 0 | F14: =MIN(F13,MAX(0,F12)*輸入與假設!$C$173) -> 0 | G14: =MIN(G13,MAX(0,G12)*輸入與假設!$C$173) -> 0 | I14: 美國規定：抵扣上限為應稅所得 80%
A15: NOL 期末餘額 | B15: US$bn | C15: =C13-C14+MAX(0,-C12) -> 6.3501553 | D15: =D13-D14+MAX(0,-D12) -> 12.885242 | E15: =E13-E14+MAX(0,-E12) -> 20.427941 | F15: =F13-F14+MAX(0,-F12) -> 30.792471 | G15: =G13-G14+MAX(0,-G12) -> 46.372963
A16: 所得稅 | B16: US$bn | C16: =MAX(0,C12-C14)*輸入與假設!$C$171 -> 0 | D16: =MAX(0,D12-D14)*輸入與假設!$C$171 -> 0 | E16: =MAX(0,E12-E14)*輸入與假設!$C$171 -> 0 | F16: =MAX(0,F12-F14)*輸入與假設!$C$171 -> 0 | G16: =MAX(0,G12-G14)*輸入與假設!$C$171 -> 0 | I16: 虧損年不認列稅盾（與公司評價備抵一致）
A17: 淨利 | B17: US$bn | C17: =C12-C16 -> -2.3501553 | D17: =D12-D16 -> -6.5350862 | E17: =E12-E16 -> -7.5427 | F17: =F12-F16 -> -10.364529 | G17: =G12-G16 -> -15.580492
A18: D&A | B18: US$bn | C18: =輸入與假設!C$138 -> 4.7972454 | D18: =輸入與假設!D$138 -> 14.924582 | E18: =輸入與假設!E$138 -> 21.158866 | F18: =輸入與假設!F$138 -> 26.373972 | G18: =輸入與假設!G$138 -> 31.056605 | I18: 車隊折舊，見輸入頁
A19: EBITDA | B19: US$bn | C19: =C10+C18 -> 4.8586769 | D19: =D10+D18 -> 15.41514 | E19: =E10+E18 -> 22.104113 | F19: =F10+F18 -> 25.102948 | G19: =G10+G18 -> 25.606342
A20: 基礎股數（每年 +SBC 稀釋） | B20: bn | C20: =輸入與假設!$C$166 -> 0.587 | D20: =C20*(1+輸入與假設!$C$181) -> 0.59287 | E20: =D20*(1+輸入與假設!$C$181) -> 0.5987987 | F20: =E20*(1+輸入與假設!$C$181) -> 0.60478669 | G20: =F20*(1+輸入與假設!$C$181) -> 0.61083455 | I20: FY26＝含 ATM 上限 0.587；之後每年 ×(1＋股數年增)
A21: 股數（含瀑布新股） | B21: bn | C21: =C20+各期收支!C66 -> 0.587 | D21: =D20+各期收支!D66 -> 0.59287 | E21: =E20+各期收支!E66 -> 0.5987987 | F21: =F20+各期收支!F66 -> 0.73512002 | G21: =G20+各期收支!G66 -> 0.87150122 | I21: ＝基礎股數＋累計瀑布新股
A22: 每股盈餘（EPS，模型期） | B22: US$ | C22: =C17/C21 -> -4.0036718 | D22: =D17/D21 -> -11.022798 | E22: =E17/E21 -> -12.596387 | F22: =F17/F21 -> -14.099098 | G22: =G17/G21 -> -17.877763 | I22: FY26 欄只含下半年；全年口徑見下方
A24: 損益表（全年口徑；FY26＝1H 實際＋下半年模型；與 HTML 損益簡表一致）
A25: 1H26 實際營收（已實現） | B25: US$bn | C25: =輸入與假設!$C$223 -> 4.653 | D25: =0 -> 0 | E25: =0 -> 0 | F25: =0 -> 0 | G25: =0 -> 0
A26: 全年總營收 | B26: US$bn | C26: =C25+C8 -> 13.066 | D26: =D25+D8 -> 26.1275 | E26: =E25+E8 -> 36.669415 | F26: =F25+F8 -> 42.363849 | G26: =G25+G8 -> 44.99393 | I26: FY26 可對照指引 12.4–13.2
A27: 營收 YoY | B27: % | C27: =C26/5.131-1 -> 1.5464822 | D27: =D26/C26-1 -> 0.99965559 | E27: =E26/D26-1 -> 0.40347969 | F27: =F26/E26-1 -> 0.15529108 | G27: =G26/F26-1 -> 0.062083158 | I27: FY25 實際 5.131
A28: 全年 GAAP 營業利益 | B28: US$bn | C28: =輸入與假設!$C$224+C10 -> -0.13156842 | D28: =D10 -> 0.49055772 | E28: =E10 -> 0.94524762 | F28: =F10 -> -1.271024 | G28: =G10 -> -5.4502634
A29: 營利率 | B29: % | C29: =C28/C26 -> -0.010069526 | D29: =D28/D26 -> 0.018775532 | E29: =E28/E26 -> 0.025777548 | F29: =F28/F26 -> -0.030002562 | G29: =G28/G26 -> -0.1211333
A30: 全年 D&A | B30: US$bn | C30: =輸入與假設!$C$227+C18 -> 7.3372454 | D30: =D18 -> 14.924582 | E30: =E18 -> 21.158866 | F30: =F18 -> 26.373972 | G30: =G18 -> 31.056605 | I30: 1H 實際 2.540
A31: 全年 EBITDA | B31: US$bn | C31: =C28+C30 -> 7.2056769 | D31: =D28+D30 -> 15.41514 | E31: =E28+E30 -> 22.104113 | F31: =F28+F30 -> 25.102948 | G31: =G28+G30 -> 25.606342
A32: 全年利息（含瀑布新債） | B32: US$bn | C32: =輸入與假設!$C$221+C11 -> 3.5875869 | D32: =D11 -> 7.0256439 | E32: =E11 -> 8.4879476 | F32: =F11 -> 9.093505 | G32: =G11 -> 10.130229 | I32: FY27 起瀑布新債利息（9%）與新股同時影響 EPS
A33: 全年淨利 | B33: US$bn | C33: =輸入與假設!$C$225+C17 -> -3.7161553 | D33: =D17 -> -6.5350862 | E33: =E17 -> -7.5427 | F33: =F17 -> -10.364529 | G33: =G17 -> -15.580492
A34: 淨利率 | B34: % | C34: =C33/C26 -> -0.28441415 | D34: =D33/D26 -> -0.2501229 | E34: =E33/E26 -> -0.20569458 | F34: =F33/F26 -> -0.24465504 | G34: =G33/G26 -> -0.34627987
A35: 全年 GAAP EPS | B35: US$ | C35: =輸入與假設!$C$229+C17/C21 -> -6.5336718 | D35: =D17/D21 -> -11.022798 | E35: =E17/E21 -> -12.596387 | F35: =F17/F21 -> -14.099098 | G35: =G17/G21 -> -17.877763 | I35: FY26＝1H 實際 EPS −2.53＋下半年淨利÷股數
A36: 全年 EPS（加回 SBC） | B36: US$ | C36: =輸入與假設!$C$230+(C17+輸入與假設!$C$182*輸入與假設!C$24)/C21 -> -5.3474197 | D36: =(D17+輸入與假設!$C$182*輸入與假設!D$24)/D21 -> -9.8421006 | E36: =(E17+輸入與假設!$C$182*輸入與假設!E$24)/E21 -> -11.427379 | F36: =(F17+輸入與假設!$C$182*輸入與假設!F$24)/F21 -> -13.146872 | G36: =(G17+輸入與假設!$C$182*輸入與假設!G$24)/G21 -> -17.074551 | I36: ＝(淨利＋SBC)÷股數；NOL 狀態無現金稅，SBC 全額加回

Sheet 評價_DCF與目標價
A1: 評價 — DCF、EV/EBITDA、加權目標價
A2: 營收、營業利益、D&A、EBITDA、股數引用『損益』頁；Cash CapEx 與融資引用『各期收支』頁
A4: 項目 | B4: 單位 | C4: FY26 | D4: FY27 | E4: FY28 | F4: FY29 | G4: FY30 | I4: 公式／來源說明
A5: DCF（無槓桿自由現金流；起點為 2026-06-30）
A6: 現金 CapEx（2026-06-30 之後） | B6: US$bn | C6: =輸入與假設!C$137-各期收支!C8 -> 19.928938 | D6: =輸入與假設!D$137-各期收支!D8 -> 38.915272 | E6: =輸入與假設!E$137-各期收支!E8 -> 29.911219 | F6: =輸入與假設!F$137-各期收支!F8 -> 31.121499 | G6: =輸入與假設!G$137-各期收支!G8 -> 33.023369 | I6: DCF 起點為 6/30，故 FY26 欄只含 2H 的建置支出，不含 1H 已發生的 14.117
A7: 比較基期營收 | B7: US$bn | C7: =5.131 -> 5.131 | D7: =4.653+損益!C8 -> 13.066 | E7: =損益!D8 -> 26.1275 | F7: =損益!E8 -> 36.669415 | G7: =損益!F8 -> 42.363849 | I7: FY25 實際 5.131；FY27 基期＝1H 實際 4.653＋FY26 模型期營收
A8: 營運資金變動 | B8: US$bn | C8: =輸入與假設!$C$174*MAX(0,損益!C8-C7) -> 0.06564 | D8: =輸入與假設!$C$174*MAX(0,損益!D8-D7) -> 0.26123 | E8: =輸入與假設!$C$174*MAX(0,損益!E8-E7) -> 0.21083831 | F8: =輸入與假設!$C$174*MAX(0,損益!F8-F7) -> 0.11388866 | G8: =輸入與假設!$C$174*MAX(0,損益!G8-G7) -> 0.05260163 | I8: 營收增量的 2%
A9: 無槓桿 NOL 期初 | B9: US$bn | C9: =輸入與假設!$C$172 -> 4 | D9: =C11 -> 3.9508547 | E9: =D11 -> 3.5584086 | F9: =E11 -> 2.8022105 | G9: =F11 -> 4.0732345 | I9: DCF 用無槓桿稅（利息不可抵稅，否則稅盾被計兩次：一次在 UFCF、一次在 WACC）
A10: 本期動用（無槓桿） | B10: US$bn | C10: =MIN(C9,MAX(0,損益!C10)*輸入與假設!$C$173) -> 0.049145263 | D10: =MIN(D9,MAX(0,損益!D10)*輸入與假設!$C$173) -> 0.39244617 | E10: =MIN(E9,MAX(0,損益!E10)*輸入與假設!$C$173) -> 0.75619809 | F10: =MIN(F9,MAX(0,損益!F10)*輸入與假設!$C$173) -> 0 | G10: =MIN(G9,MAX(0,損益!G10)*輸入與假設!$C$173) -> 0
A11: 無槓桿 NOL 期末 | B11: US$bn | C11: =C9-C10+MAX(0,-損益!C10) -> 3.9508547 | D11: =D9-D10+MAX(0,-損益!D10) -> 3.5584086 | E11: =E9-E10+MAX(0,-損益!E10) -> 2.8022105 | F11: =F9-F10+MAX(0,-損益!F10) -> 4.0732345 | G11: =G9-G10+MAX(0,-損益!G10) -> 9.5234979
A12: 無槓桿所得稅（DCF 用） | B12: US$bn | C12: =MAX(0,損益!C10-C10)*輸入與假設!$C$171 -> 0.0025801263 | D12: =MAX(0,損益!D10-D10)*輸入與假設!$C$171 -> 0.020603424 | E12: =MAX(0,損益!E10-E10)*輸入與假設!$C$171 -> 0.0397004 | F12: =MAX(0,損益!F10-F10)*輸入與假設!$C$171 -> 0 | G12: =MAX(0,損益!G10-G10)*輸入與假設!$C$171 -> 0 | I12: 與損益表的所得稅不同：此處不扣利息，數字較高，這是 DCF 的正確口徑
A13: UFCF | B13: US$bn | C13: =損益!C10-C12+損益!C18-C6-C8 -> -15.138481 | D13: =損益!D10-D12+損益!D18-D6-D8 -> -23.781966 | E13: =損益!E10-E12+損益!E18-E6-E8 -> -8.0576442 | F13: =損益!F10-F12+損益!F18-F6-F8 -> -6.13244 | G13: =損益!G10-G12+損益!G18-G6-G8 -> -7.4696287 | I13: ＝EBIT−無槓桿稅＋D&A−現金 CapEx−營運資金。建置期全為負是正常的
A14: 折現期數 | B14: 年 | C14: =輸入與假設!$C$200 -> 0.5 | D14: =輸入與假設!$D$200 -> 1.5 | E14: =輸入與假設!$E$200 -> 2.5 | F14: =輸入與假設!$F$200 -> 3.5 | G14: =輸入與假設!$G$200 -> 4.5 | I14: 自 2026-06-30 起算；FY26 模型期（下半年）的現金流平均落在 0.5 年
A15: 折現因子 | C15: =1/(1+輸入與假設!$C$168)^C14 -> 0.949158 | D15: =1/(1+輸入與假設!$C$168)^D14 -> 0.85509729 | E15: =1/(1+輸入與假設!$C$168)^E14 -> 0.77035792 | F15: =1/(1+輸入與假設!$C$168)^F14 -> 0.69401615 | G15: =1/(1+輸入與假設!$C$168)^G14 -> 0.62523977
A16: UFCF 現值 | B16: US$bn | C16: =C13*C15 -> -14.36881 | D16: =D13*D15 -> -20.335894 | E16: =E13*E15 -> -6.20727 | F16: =F13*F15 -> -4.2560123 | G16: =G13*G15 -> -4.670309
A18: 五期 UFCF 現值合計 | C18: =SUM(C16:G16) -> -49.838296 | I18: 建置期現金流現值
A19: 常態化 FCF（FY30） | C19: =損益!G10*(1-輸入與假設!$C$171)+損益!G18-損益!G18*輸入與假設!$C$170 -> 1.9056129 | I19: ＝EBIT×(1−稅)＋D&A−維持性 CapEx(D&A×比率)。不讓成長性 CapEx 偽裝成永續 FCF
A20: 終值（Gordon） | C20: =IF(C29=1,0,C19*(1+輸入與假設!$C$169)/(輸入與假設!$C$168-輸入與假設!$C$169)) -> 24.534767 | I20: ＝常態化 FCF×(1+g)÷(WACC−g)
A21: 終值現值 | C21: =C20*G15 -> 15.340112
A22: 企業價值 EV | C22: =C18+C21 -> -34.498184
A23: 減：淨負債 | C23: =-輸入與假設!$C$167 -> -30 | I23: 6/30 本金 35.551 − 現金 5.524
A24: 股權價值 | C24: =C22+C23 -> -64.498184
A25: DCF 每股 | C25: =IF(C29=1,0,IF(輸入與假設!$C$184=2,C31,C30)) -> 0 | I25: 採用值：失效時為 0 且權重歸零；否則依「DCF 下限方式」取 0 截斷或選擇權
A26: 終值占 EV 比重 | C26: =C21/C22 -> -0.44466433 | I26: ="超過 "&IF(ROUND(ABS(輸入與假設!$C$209)*100,4)=INT(ROUND(ABS(輸入與假設!$C$209)*100,4)),TEXT(ROUND(ABS(輸入與假設!$C$209)*100,4),"0"),TEXT(ROUND(ABS(輸入與假設!$C$209)*100,4),"0.0"))&"%"&" 表示結論由終值假設決定，不由現金流決定" -> 超過 85% 表示結論由終值假設決定，不由現金流決定
A27: 新股募得現金（現值） | C27: =各期收支!C61/(1+輸入與假設!$C$168)^輸入與假設!$C$201+各期收支!D61/(1+輸入與假設!$C$168)^輸入與假設!$D$201+各期收支!E61/(1+輸入與假設!$C$168)^輸入與假設!$E$201+各期收支!F61/(1+輸入與假設!$C$168)^輸入與假設!$F$201+各期收支!G61/(1+輸入與假設!$C$168)^輸入與假設!$G$201 -> 15.481727 | I27: 期初到位，折現期數 0／0.5／1.5／2.5／3.5 年
A28: 融資後股數（含瀑布新股） | C28: =輸入與假設!$C$166+各期收支!G66 -> 0.84766667
A29: DCF 失效？（WACC ≤ g 或常態化 FCF ≤ 0） | C29: =IF(OR(輸入與假設!$C$168<=輸入與假設!$C$169,C19<=0),1,0) -> 0 | I29: 1＝失效：DCF 權重歸零、EV/EBITDA 100%。股權為負不算失效
A30: DCF 每股：0 截斷 | C30: =MAX(0,(C24+C27)/C28) -> 0
A31: DCF 每股：選擇權（Merton） | C31: =IF((C22+C27)<=0,0,((C22+C27)*NORMSDIST(C32)-輸入與假設!$C$167*EXP(-輸入與假設!$C$186*輸入與假設!$C$187)*NORMSDIST(C33))/C28) -> 0 | I31: Black-Scholes：S＝企業價值＋新股現值、K＝淨負債
A32: d1 | C32: =IF((C22+C27)<=0,0,(LN((C22+C27)/輸入與假設!$C$167)+(輸入與假設!$C$186+輸入與假設!$C$185^2/2)*輸入與假設!$C$187)/(輸入與假設!$C$185*SQRT(輸入與假設!$C$187))) -> 0
A33: d2 | C33: =C32-輸入與假設!$C$185*SQRT(輸入與假設!$C$187) -> -1.0606602
A35: 倍數法（錨定年度，預設 FY29；折回 2027-06-30）
A36: 錨定年度 | C36: =CHOOSE(輸入與假設!$C$176,"FY27","FY28","FY29","FY30") -> FY29 | I36: 輸入與假設 F 區可改
A37: 錨定年度 EBITDA | C37: =INDEX(損益!$D$19:$G$19,1,輸入與假設!$C$176) -> 25.102948
A38: 錨定年度企業價值（倍數 × EBITDA） | C38: =C37*輸入與假設!$C$175 -> 150.61769
A39: 錨定年度末淨負債（總債務 − 現金） | C39: =INDEX(各期收支!$D$70:$G$70,1,輸入與假設!$C$176)-INDEX(各期收支!$D$41:$G$41,1,輸入與假設!$C$176) -> 99.125121 | I39: 含瀑布新債
A40: 錨定年度末股數（含瀑布新股） | C40: =INDEX(損益!$D$21:$G$21,1,輸入與假設!$C$176) -> 0.73512002 | I40: 損益股數：SBC 逐年稀釋＋瀑布新股
A41: 折回 2027-06-30 的折現因子 | C41: =1/(1+輸入與假設!$C$168)^(輸入與假設!$C$176-輸入與假設!$C$197) -> 0.77035792 | I41: 以 WACC 折現 [Assumed]
A42: EV/EBITDA 每股（融資後） | C42: =MAX(0,(C38-C39)/C40)*C41 -> 53.960859 | I42: 以 0 為下限
A44: 加權目標價
A45: DCF 每股（推到目標價時點） | C45: =C25*(1+輸入與假設!$C$168)^輸入與假設!$C$193 -> 0 | I45: ＝DCF 每股 ×（1＋WACC）^（評價日至目標價時點的年數）
A46: DCF 每股 × 有效權重 | C46: =C45*IF(C29=1,0,輸入與假設!$C$177) -> 0
A47: EV/EBITDA（融資後）× 有效權重 | C47: =C42*IF(C29=1,1,1-輸入與假設!$C$177) -> 29.678472
A48: 加權目標價 | C48: =SUM(C46:C47) -> 29.678472 | I48: 期前融資瀑布：缺口先由額度與資產層新債支應，殘差以股權募足；估值不再扣缺口本金
A49: 現價 | C49: =輸入與假設!$C$165 -> 90.13
A50: 潛在空間 | C50: =C48/C49-1 -> -0.67071483
A51: DCF 權重說明 | C51: =IF(C29=1,"DCF 失效，已以 EV/EBITDA 100% 計。",IF(AND(輸入與假設!$C$184<>2,C66<0),"DCF 為 $0 仍計 "&TEXT(輸入與假設!$C$177,"0%")&" 權重的原因：DCF 沒有失效，而是算出的股權價值為負（每股約 −$"&TEXT(ABS(C66),"0.0")&"），代表自由現金流折現後的企業價值不足以償還淨負債。EV/EBITDA 沒有扣除 GPU 汰換與擴張支出，保留 DCF 權重，是為了讓目標價反映「EBITDA 付不起資本成本」。若不計 DCF，目標價為 $"&TEXT(C42,"0.0")&"（"&CHOOSE(D65+2,"賣出","中立","買進")&"）；"&TEXT(輸入與假設!$C$177,"0%")&"／"&TEXT(1-輸入與假設!$C$177,"0%")&" 為判斷值。","")) -> DCF 為 $0 仍計 45% 權重的原因：DCF 沒有失效，而是算出的股權價值為負（每股約 −$57.8），代表自由現金流折現後的企業價值不足以償還淨負債。EV/EBITDA 沒有扣除 GPU 汰換與擴張支出，保留 DCF 權重，是為了讓目標價反映「EBITDA 付不起資本成本」。若不計 DCF，目標價為 $54.0（賣出）；45%／55% 為判斷值。 | I51: 只在 DCF 被 0 截斷時顯示；DCF 失效時改為一句；DCF 為正時空白（與 HTML 同一字串）
A53: 目標價區間（情境區間、方法區間；評等仍依點位）
A54: 目標價區間｜點位（目前輸入的加權目標價） | C54: =C48 -> 29.678472 | I54: ="評等規則不變：空間 ≥"&IF(ROUND(ABS(輸入與假設!$C$203)*100,4)=INT(ROUND(ABS(輸入與假設!$C$203)*100,4)),TEXT(ROUND(ABS(輸入與假設!$C$203)*100,4),"0"),TEXT(ROUND(ABS(輸入與假設!$C$203)*100,4),"0.0"))&"%"&" 且終值占比 <"&IF(ROUND(ABS(輸入與假設!$C$204)*100,4)=INT(ROUND(ABS(輸入與假設!$C$204)*100,4)),TEXT(ROUND(ABS(輸入與假設!$C$204)*100,4),"0"),TEXT(ROUND(ABS(輸入與假設!$C$204)*100,4),"0.0"))&"%"&"、股權募資 ≤"&IF(輸入與假設!$C$206=INT(輸入與假設!$C$206),TEXT(輸入與假設!$C$206,"0"),TEXT(輸入與假設!$C$206,"0.0"))&" 倍現市值 → 買進；空間 ≤−"&IF(ROUND(ABS(輸入與假設!$C$205)*100,4)=INT(ROUND(ABS(輸入與假設!$C$205)*100,4)),TEXT(ROUND(ABS(輸入與假設!$C$205)*100,4),"0"),TEXT(ROUND(ABS(輸入與假設!$C$205)*100,4),"0.0"))&"%"&"，或股權募資 >"&IF(輸入與假設!$C$206=INT(輸入與假設!$C$206),TEXT(輸入與假設!$C$206,"0"),TEXT(輸入與假設!$C$206,"0.0"))&" 倍且空間 ≤−"&IF(ROUND(ABS(輸入與假設!$C$207)*100,4)=INT(ROUND(ABS(輸入與假設!$C$207)*100,4)),TEXT(ROUND(ABS(輸入與假設!$C$207)*100,4),"0"),TEXT(ROUND(ABS(輸入與假設!$C$207)*100,4),"0.0"))&"%"&" → 賣出；其餘中立" -> 評等規則不變：空間 ≥25% 且終值占比 <90%、股權募資 ≤1.5 倍現市值 → 買進；空間 ≤−15%，或股權募資 >1.5 倍且空間 ≤−8% → 賣出；其餘中立
A55: 目標價區間｜終值占 EV（評等用） | C55: =C21/MAX(ABS(C22),1)*IF(C22=0,1,SIGN(C22)) -> -0.44466433
A56: 目標價區間｜股權募資 ÷ 現市值（評等用） | C56: =SUM(各期收支!C61:G61)/(輸入與假設!$C$165*輸入與假設!$C$166) -> 0.39965928
A57: 目標價區間｜點位評等代碼（1＝買進、0＝中立、−1＝賣出） | C57: =IF(AND((C48/MAX(輸入與假設!$C$165,0.01)-1)>=輸入與假設!$C$203,$C$55<輸入與假設!$C$204,$C$56<=輸入與假設!$C$206),1,IF(OR((C48/MAX(輸入與假設!$C$165,0.01)-1)<=輸入與假設!$C$205,AND($C$56>輸入與假設!$C$206,(C48/MAX(輸入與假設!$C$165,0.01)-1)<=輸入與假設!$C$207)),-1,0)) -> -1 | D57: =CHOOSE(C57+2,"賣出","中立","買進") -> 賣出
A58: 目標價區間｜賣出門檻價（現價 × (1 − 15%)） | C58: =輸入與假設!$C$165*(1+輸入與假設!$C$205) -> 76.6105
A59: 目標價區間｜保守 4.2 GW（加權目標價／評等代碼／距賣出門檻） | C59: =輸入與假設!D235 -> 43.992773 | D59: =輸入與假設!E235 -> -1 | E59: =C59-$C$58 -> -32.617727 | I59: 引用『輸入與假設』底部模擬運算表（情境選擇 1／2／3），保留其餘手動輸入
A60: 目標價區間｜基準 5.6 GW（加權目標價／評等代碼／距賣出門檻） | C60: =輸入與假設!D236 -> 29.678472 | D60: =輸入與假設!E236 -> -1 | E60: =C60-$C$58 -> -46.932028
A61: 目標價區間｜積極 8 GW（加權目標價／評等代碼／距賣出門檻） | C61: =輸入與假設!D237 -> 19.94892 | D61: =輸入與假設!E237 -> -1 | E61: =C61-$C$58 -> -56.66158
A62: 目標價區間｜情境區間（下緣／上緣） | C62: =MIN(C59,C61) -> 19.94892 | D62: =MAX(C59,C61) -> 43.992773
A63: 目標價區間｜方法區間倍數（下端／上端） | C63: =MIN(輸入與假設!$C$179,輸入與假設!$C$180) -> 5 | D63: =MAX(輸入與假設!$C$179,輸入與假設!$C$180) -> 6
A64: 目標價區間｜方法區間（下緣／上緣） | C64: =MIN(C45*IF(C29=1,0,輸入與假設!$C$177)+MAX(0,(C37*C63-C39)/C40)*C41*IF(C29=1,1,1-輸入與假設!$C$177),C45*IF(C29=1,0,輸入與假設!$C$177)+MAX(0,(C37*D63-C39)/C40)*C41*IF(C29=1,1,1-輸入與假設!$C$177)) -> 15.210032 | D64: =MAX(C45*IF(C29=1,0,輸入與假設!$C$177)+MAX(0,(C37*C63-C39)/C40)*C41*IF(C29=1,1,1-輸入與假設!$C$177),C45*IF(C29=1,0,輸入與假設!$C$177)+MAX(0,(C37*D63-C39)/C40)*C41*IF(C29=1,1,1-輸入與假設!$C$177)) -> 29.678472 | I64: ＝DCF 採用值 × 有效權重 ＋ EV/EBITDA 腿（倍數換成兩端）× 有效權重
A65: 目標價區間｜100% EV/EBITDA 目標價（價位／評等代碼） | C65: =C42 -> 53.960859 | D65: =IF(AND((C42/MAX(輸入與假設!$C$165,0.01)-1)>=輸入與假設!$C$203,$C$55<輸入與假設!$C$204,$C$56<=輸入與假設!$C$206),1,IF(OR((C42/MAX(輸入與假設!$C$165,0.01)-1)<=輸入與假設!$C$205,AND($C$56>輸入與假設!$C$206,(C42/MAX(輸入與假設!$C$165,0.01)-1)<=輸入與假設!$C$207)),-1,0)) -> -1 | E65: =CHOOSE(D65+2,"賣出","中立","買進") -> 賣出
A66: 目標價區間｜未截斷 DCF 每股 | C66: =(C24+C27)/C28 -> -57.825156
A67: 目標價區間｜點位摘要 | C67: ="目標價 $"&TEXT(C48,"0.0")&"（情境區間 $"&TEXT(C62,"0.0")&"–$"&TEXT(D62,"0.0")&"）" -> 目標價 $29.7（情境區間 $19.9–$44.0）
A68: 目標價區間｜方法區間標籤 | C68: ="方法區間（目前情境，"&IF(C63=INT(C63),TEXT(C63,"0"),TEXT(C63,"0.0"))&"–"&IF(D63=INT(D63),TEXT(D63,"0"),TEXT(D63,"0.0"))&"x）" -> 方法區間（目前情境，5–6x）
A69: 目標價區間｜點位位置 | C69: =IF(ABS(輸入與假設!$C$175-D63)<0.000000001,"目前點位位於方法區間上緣（"&IF(D63=INT(D63),TEXT(D63,"0"),TEXT(D63,"0.0"))&"x 為穩態倍數上緣）",IF(ABS(輸入與假設!$C$175-C63)<0.000000001,"目前點位位於方法區間下緣（"&IF(C63=INT(C63),TEXT(C63,"0"),TEXT(C63,"0.0"))&"x）","目前點位"&IF(AND(輸入與假設!$C$175>C63,輸入與假設!$C$175<D63),"位於方法區間內",IF(輸入與假設!$C$175>D63,"高於方法區間上緣","低於方法區間下緣"))&"（目前倍數 "&IF(輸入與假設!$C$175=INT(輸入與假設!$C$175),TEXT(輸入與假設!$C$175,"0"),TEXT(輸入與假設!$C$175,"0.0"))&"x）")) -> 目前點位位於方法區間上緣（6x 為穩態倍數上緣）
A70: 目標價區間｜判斷句 | C70: =IF(D62<輸入與假設!$C$165,"情境區間上緣 $"&TEXT(D62,"0.0")&" 低於現價 $"&TEXT(輸入與假設!$C$165,"0.00")&IF((D59<>-1)+(D60<>-1)+(D61<>-1)>0,"，但"&SUBSTITUTE(TRIM(IF(D59<>-1,"保守","")&" "&IF(D60<>-1,"基準","")&" "&IF(D61<>-1,"積極",""))," ","、")&"情境未達賣出門檻 $"&TEXT($C$58,"0.0"),"：賣出在三個擴張情境下都成立"),"情境區間上緣 $"&TEXT(D62,"0.0")&" 不低於現價 $"&TEXT(輸入與假設!$C$165,"0.00")&"：賣出並非在三個擴張情境下都成立")&"。"&IF(ABS(E59)<輸入與假設!$C$208*輸入與假設!$C$165,"保守情境 $"&TEXT(C59,"0.0")&"，"&IF(E59<0,"距賣出門檻","高於賣出門檻")&" $"&TEXT($C$58,"0.0")&" 僅 $"&TEXT(ABS(E59),"0.0")&"。","")&IF(ABS(E60)<輸入與假設!$C$208*輸入與假設!$C$165,"基準情境 $"&TEXT(C60,"0.0")&"，"&IF(E60<0,"距賣出門檻","高於賣出門檻")&" $"&TEXT($C$58,"0.0")&" 僅 $"&TEXT(ABS(E60),"0.0")&"。","")&IF(ABS(E61)<輸入與假設!$C$208*輸入與假設!$C$165,"積極情境 $"&TEXT(C61,"0.0")&"，"&IF(E61<0,"距賣出門檻","高於賣出門檻")&" $"&TEXT($C$58,"0.0")&" 僅 $"&TEXT(ABS(E61),"0.0")&"。","") -> 情境區間上緣 $44.0 低於現價 $90.13：賣出在三個擴張情境下都成立。
A72: 錨定年度 × 倍數矩陣（每股；以 WACC 折回 2027-06-30）
A73: 倍數 ＼ 錨定（EV/EBITDA 腿） | B73: 倍數 | C73: FY27 | D73: FY28 | E73: FY29 | F73: FY30 | I73: EV/EBITDA 腿＝(錨定年 EBITDA × 倍數 − 錨定年末淨負債) ÷ 錨定年末股數 × 折現因子；加權＝DCF 採用值 × 有效權重 ＋ 腿 × 有效權重。綠底＝不低於現價
A74: 錨定×倍數｜EV/EBITDA 腿｜3.4x | B74: 3.4 | C74: =MAX(0,(INDEX(損益!$D$19:$G$19,1,1)*$B74-(INDEX(各期收支!$D$70:$G$70,1,1)-INDEX(各期收支!$D$41:$G$41,1,1)))/INDEX(損益!$D$21:$G$21,1,1))/(1+輸入與假設!$C$168)^(1-輸入與假設!$C$197) -> 0 | D74: =MAX(0,(INDEX(損益!$D$19:$G$19,1,2)*$B74-(INDEX(各期收支!$D$70:$G$70,1,2)-INDEX(各期收支!$D$41:$G$41,1,2)))/INDEX(損益!$D$21:$G$21,1,2))/(1+輸入與假設!$C$168)^(2-輸入與假設!$C$197) -> 0 | E74: =MAX(0,(INDEX(損益!$D$19:$G$19,1,3)*$B74-(INDEX(各期收支!$D$70:$G$70,1,3)-INDEX(各期收支!$D$41:$G$41,1,3)))/INDEX(損益!$D$21:$G$21,1,3))/(1+輸入與假設!$C$168)^(3-輸入與假設!$C$197) -> 0 | F74: =MAX(0,(INDEX(損益!$D$19:$G$19,1,4)*$B74-(INDEX(各期收支!$D$70:$G$70,1,4)-INDEX(各期收支!$D$41:$G$41,1,4)))/INDEX(損益!$D$21:$G$21,1,4))/(1+輸入與假設!$C$168)^(4-輸入與假設!$C$197) -> 0
A75: 錨定×倍數｜EV/EBITDA 腿｜4.5x | B75: 4.5 | C75: =MAX(0,(INDEX(損益!$D$19:$G$19,1,1)*$B75-(INDEX(各期收支!$D$70:$G$70,1,1)-INDEX(各期收支!$D$41:$G$41,1,1)))/INDEX(損益!$D$21:$G$21,1,1))/(1+輸入與假設!$C$168)^(1-輸入與假設!$C$197) -> 0 | D75: =MAX(0,(INDEX(損益!$D$19:$G$19,1,2)*$B75-(INDEX(各期收支!$D$70:$G$70,1,2)-INDEX(各期收支!$D$41:$G$41,1,2)))/INDEX(損益!$D$21:$G$21,1,2))/(1+輸入與假設!$C$168)^(2-輸入與假設!$C$197) -> 7.6620182 | E75: =MAX(0,(INDEX(損益!$D$19:$G$19,1,3)*$B75-(INDEX(各期收支!$D$70:$G$70,1,3)-INDEX(各期收支!$D$41:$G$41,1,3)))/INDEX(損益!$D$21:$G$21,1,3))/(1+輸入與假設!$C$168)^(3-輸入與假設!$C$197) -> 14.501476 | F75: =MAX(0,(INDEX(損益!$D$19:$G$19,1,4)*$B75-(INDEX(各期收支!$D$70:$G$70,1,4)-INDEX(各期收支!$D$41:$G$41,1,4)))/INDEX(損益!$D$21:$G$21,1,4))/(1+輸入與假設!$C$168)^(4-輸入與假設!$C$197) -> 6.8294288
A76: 錨定×倍數｜EV/EBITDA 腿｜5.0x | B76: 5 | C76: =MAX(0,(INDEX(損益!$D$19:$G$19,1,1)*$B76-(INDEX(各期收支!$D$70:$G$70,1,1)-INDEX(各期收支!$D$41:$G$41,1,1)))/INDEX(損益!$D$21:$G$21,1,1))/(1+輸入與假設!$C$168)^(1-輸入與假設!$C$197) -> 0 | D76: =MAX(0,(INDEX(損益!$D$19:$G$19,1,2)*$B76-(INDEX(各期收支!$D$70:$G$70,1,2)-INDEX(各期收支!$D$41:$G$41,1,2)))/INDEX(損益!$D$21:$G$21,1,2))/(1+輸入與假設!$C$168)^(2-輸入與假設!$C$197) -> 23.444591 | E76: =MAX(0,(INDEX(損益!$D$19:$G$19,1,3)*$B76-(INDEX(各期收支!$D$70:$G$70,1,3)-INDEX(各期收支!$D$41:$G$41,1,3)))/INDEX(損益!$D$21:$G$21,1,3))/(1+輸入與假設!$C$168)^(3-輸入與假設!$C$197) -> 27.654604 | F76: =MAX(0,(INDEX(損益!$D$19:$G$19,1,4)*$B76-(INDEX(各期收支!$D$70:$G$70,1,4)-INDEX(各期收支!$D$41:$G$41,1,4)))/INDEX(損益!$D$21:$G$21,1,4))/(1+輸入與假設!$C$168)^(4-輸入與假設!$C$197) -> 17.025177
A77: 錨定×倍數｜EV/EBITDA 腿｜6.0x | B77: 6 | C77: =MAX(0,(INDEX(損益!$D$19:$G$19,1,1)*$B77-(INDEX(各期收支!$D$70:$G$70,1,1)-INDEX(各期收支!$D$41:$G$41,1,1)))/INDEX(損益!$D$21:$G$21,1,1))/(1+輸入與假設!$C$168)^(1-輸入與假設!$C$197) -> 24.293214 | D77: =MAX(0,(INDEX(損益!$D$19:$G$19,1,2)*$B77-(INDEX(各期收支!$D$70:$G$70,1,2)-INDEX(各期收支!$D$41:$G$41,1,2)))/INDEX(損益!$D$21:$G$21,1,2))/(1+輸入與假設!$C$168)^(2-輸入與假設!$C$197) -> 55.009735 | E77: =MAX(0,(INDEX(損益!$D$19:$G$19,1,3)*$B77-(INDEX(各期收支!$D$70:$G$70,1,3)-INDEX(各期收支!$D$41:$G$41,1,3)))/INDEX(損益!$D$21:$G$21,1,3))/(1+輸入與假設!$C$168)^(3-輸入與假設!$C$197) -> 53.960859 | F77: =MAX(0,(INDEX(損益!$D$19:$G$19,1,4)*$B77-(INDEX(各期收支!$D$70:$G$70,1,4)-INDEX(各期收支!$D$41:$G$41,1,4)))/INDEX(損益!$D$21:$G$21,1,4))/(1+輸入與假設!$C$168)^(4-輸入與假設!$C$197) -> 37.416675
A78: 錨定×倍數｜EV/EBITDA 腿｜7.0x | B78: 7 | C78: =MAX(0,(INDEX(損益!$D$19:$G$19,1,1)*$B78-(INDEX(各期收支!$D$70:$G$70,1,1)-INDEX(各期收支!$D$41:$G$41,1,1)))/INDEX(損益!$D$21:$G$21,1,1))/(1+輸入與假設!$C$168)^(1-輸入與假設!$C$197) -> 48.972154 | D78: =MAX(0,(INDEX(損益!$D$19:$G$19,1,2)*$B78-(INDEX(各期收支!$D$70:$G$70,1,2)-INDEX(各期收支!$D$41:$G$41,1,2)))/INDEX(損益!$D$21:$G$21,1,2))/(1+輸入與假設!$C$168)^(2-輸入與假設!$C$197) -> 86.57488 | E78: =MAX(0,(INDEX(損益!$D$19:$G$19,1,3)*$B78-(INDEX(各期收支!$D$70:$G$70,1,3)-INDEX(各期收支!$D$41:$G$41,1,3)))/INDEX(損益!$D$21:$G$21,1,3))/(1+輸入與假設!$C$168)^(3-輸入與假設!$C$197) -> 80.267114 | F78: =MAX(0,(INDEX(損益!$D$19:$G$19,1,4)*$B78-(INDEX(各期收支!$D$70:$G$70,1,4)-INDEX(各期收支!$D$41:$G$41,1,4)))/INDEX(損益!$D$21:$G$21,1,4))/(1+輸入與假設!$C$168)^(4-輸入與假設!$C$197) -> 57.808172
A80: 倍數 ＼ 錨定（加權目標價） | B80: 倍數 | C80: FY27 | D80: FY28 | E80: FY29 | F80: FY30
A81: 錨定×倍數｜加權目標價｜3.4x | B81: 3.4 | C81: =C45*IF(C29=1,0,輸入與假設!$C$177)+C74*IF(C29=1,1,1-輸入與假設!$C$177) -> 0 | D81: =C45*IF(C29=1,0,輸入與假設!$C$177)+D74*IF(C29=1,1,1-輸入與假設!$C$177) -> 0 | E81: =C45*IF(C29=1,0,輸入與假設!$C$177)+E74*IF(C29=1,1,1-輸入與假設!$C$177) -> 0 | F81: =C45*IF(C29=1,0,輸入與假設!$C$177)+F74*IF(C29=1,1,1-輸入與假設!$C$177) -> 0
A82: 錨定×倍數｜加權目標價｜4.5x | B82: 4.5 | C82: =C45*IF(C29=1,0,輸入與假設!$C$177)+C75*IF(C29=1,1,1-輸入與假設!$C$177) -> 0 | D82: =C45*IF(C29=1,0,輸入與假設!$C$177)+D75*IF(C29=1,1,1-輸入與假設!$C$177) -> 4.21411 | E82: =C45*IF(C29=1,0,輸入與假設!$C$177)+E75*IF(C29=1,1,1-輸入與假設!$C$177) -> 7.9758118 | F82: =C45*IF(C29=1,0,輸入與假設!$C$177)+F75*IF(C29=1,1,1-輸入與假設!$C$177) -> 3.7561859
A83: 錨定×倍數｜加權目標價｜5.0x | B83: 5 | C83: =C45*IF(C29=1,0,輸入與假設!$C$177)+C76*IF(C29=1,1,1-輸入與假設!$C$177) -> 0 | D83: =C45*IF(C29=1,0,輸入與假設!$C$177)+D76*IF(C29=1,1,1-輸入與假設!$C$177) -> 12.894525 | E83: =C45*IF(C29=1,0,輸入與假設!$C$177)+E76*IF(C29=1,1,1-輸入與假設!$C$177) -> 15.210032 | F83: =C45*IF(C29=1,0,輸入與假設!$C$177)+F76*IF(C29=1,1,1-輸入與假設!$C$177) -> 9.3638476
A84: 錨定×倍數｜加權目標價｜6.0x | B84: 6 | C84: =C45*IF(C29=1,0,輸入與假設!$C$177)+C77*IF(C29=1,1,1-輸入與假設!$C$177) -> 13.361268 | D84: =C45*IF(C29=1,0,輸入與假設!$C$177)+D77*IF(C29=1,1,1-輸入與假設!$C$177) -> 30.255354 | E84: =C45*IF(C29=1,0,輸入與假設!$C$177)+E77*IF(C29=1,1,1-輸入與假設!$C$177) -> 29.678472 | F84: =C45*IF(C29=1,0,輸入與假設!$C$177)+F77*IF(C29=1,1,1-輸入與假設!$C$177) -> 20.579171
A85: 錨定×倍數｜加權目標價｜7.0x | B85: 7 | C85: =C45*IF(C29=1,0,輸入與假設!$C$177)+C78*IF(C29=1,1,1-輸入與假設!$C$177) -> 26.934685 | D85: =C45*IF(C29=1,0,輸入與假設!$C$177)+D78*IF(C29=1,1,1-輸入與假設!$C$177) -> 47.616184 | E85: =C45*IF(C29=1,0,輸入與假設!$C$177)+E78*IF(C29=1,1,1-輸入與假設!$C$177) -> 44.146913 | F85: =C45*IF(C29=1,0,輸入與假設!$C$177)+F78*IF(C29=1,1,1-輸入與假設!$C$177) -> 31.794494

Sheet 評價_反向DCF
A1: 反向 DCF — 現價隱含什麼樣的收入與成本
A2: 不是問「值多少」，而是問「要值現價，營運要長什麼樣」。Excel 以『目標搜尋』反解；下方另附 HTML 即時計算結果的快照（v4.0 預設輸入）
A4: 即時：目前 DCF 與現價的差距
A5: 現價 | B5: =輸入與假設!$C$165 -> 90.13
A6: 目前 DCF 每股（依下限方式） | B6: =評價_DCF與目標價!C25 -> 0
A7: 差距（DCF − 現價）＝目標搜尋的『設定儲存格』 | B7: =B6-B5 -> -90.13
A8: 目前每 MW 年收入倍數／建置成本倍數 | B8: =輸入與假設!$C$22 -> 1 | C8: =輸入與假設!$C$118 -> 1
A10: 操作：用『目標搜尋』反解（資料 → 模擬分析 → 目標搜尋）
A11: ① 設定儲存格：本頁 B7；目標值：0
A12: ② 變數儲存格（擇一）：輸入與假設 B 區『每 MW 年收入倍數』→ 市價隱含單價；或 D 區『每 MW 建置成本倍數』→ 市價隱含建置成本；或 C 區『穩態 EBITDA 率』
A13: ③ 解完請記下結果，再把倍數改回 100%（或按 Ctrl+Z）。DCF 以 0 截斷時，負值區域斜率為 0，請從 100% 以上開始搜尋
A14: ④ 組合分析：先把 D 區建置成本倍數與 C 區穩態 EBITDA 率設為想測的值，再對『每 MW 年收入倍數』做目標搜尋，即得下方矩陣中的一格
A16: 快照：單一槓桿（HTML v4.0 預設輸入，DCF 0 截斷）
A17: 單一槓桿（其他不變） | B17: 目前 | C17: 市價隱含 | D17: 變動 | G17: 對照
A18: FY30 每 MW 年收入（US$m） | B18: 10.5 | C18: 16.7538 | D18: 0.5956 | G18: 期末 ARR 指引隱含約 $10.0–10.5m；7 月新約漲價約 25%
A19: 每 MW 建置成本（US$m） | B19: 37.5864 | C19: 14.8946 | D19: -0.6037 | G19: FY26 指引隱含約 $32–37m
A20: 穩態 EBITDA 率（FY30） | B20: 0.5691 | C20: 0.9118 | D20: 0.3427 | G20: Q2 實際 59%；由下而上上緣約 67–71%（變動為百分點）
A21: （對照）加權目標價＝現價所需每 MW 年收入 | B21: 10.5 | C21: 14.1575 | D21: 0.3483 | G21: 含 EV/EBITDA 6x（FY29 錨定） 腿；非純反向 DCF
A23: 快照：收入與成本的綜合影響——要值現價，FY30 每 MW 年收入需要多少（US$m）
A24: 建置成本 ＼ 穩態 EBITDA 率 | B24: 0.59 | C24: 0.65 | D24: 0.7 | E24: 0.75
A25: $26.3m（-30%） | B25: 13.06 | C25: 11.87 | D25: 11.02 | E25: 10.26
A26: $30.1m（-20%） | B26: 14.03 | C26: 12.77 | D26: 11.85 | E26: 11.05
A27: $33.8m（-10%） | B27: 15 | C27: 13.66 | D27: 12.69 | E27: 11.84
A28: $37.6m（目前） | B28: 16.19 | C28: 14.76 | D28: 13.72 | E28: 12.81
A29: $41.3m（+10%） | B29: 17.47 | C29: 15.93 | D29: 14.82 | E29: 13.85
A30: 快照為靜態數值（HTML 以同一引擎即時計算）；改變輸入後請以目標搜尋重算，或參考 HTML『評價 → 反向 DCF』

Sheet 評價_可比公司
A1: 可比公司 — 以 EV/Sales 為主（市值：2026-09-21 收盤）
A2: EV＝市值＋（有息負債−非受限現金）；含租賃＝EV＋營業租賃負債。EV/EBITDA 僅供參考（同業 GAAP EBITDA 皆為負，顯示 n/m）。此表不進入目標價。與 HTML Comps 分頁同一組數字
A4: 公司 | B4: 市值 | C4: 淨負債 | D4: EV | E4: TTM 營收 | F4: EV/Sales（TTM） | G4: 含租賃 EV/Sales | H4: TTM EBITDA | I4: EV/EBITDA | J4: 資料期 | K4: 備註
A5: NBIS Nebius | B5: 63.81 | C5: 2.16 | D5: =B5+C5 -> 65.97 | E5: 1.36 | F5: =D5/E5 -> 48.507353 | G5: =(D5+0)/E5 -> 48.507353 | H5: =-0.612+0.418 -> -0.194 | I5: =IF(H5>0,D5/H5,"n/m") -> n/m | J5: EBITDA：FY25 20-F | K5: 營業租賃負債 0.0；GAAP 營業損益 -0.612＋D&A 0.418。季報未 XBRL 標註，EBITDA 用 FY2025；營收為 TTM。前瞻 EV/Sales 約 9.3x（由 9/18 forward PS 8.46 推算 [Derived]）
A6: IREN | B6: 18.61 | C6: 1.7 | D6: =B6+C6 -> 20.31 | E6: 0.707 | F6: =D6/E6 -> 28.727016 | G6: =(D6+0.003)/E6 -> 28.731259 | H6: =-1.047+0.418 -> -0.629 | I6: =IF(H6>0,D6/H6,"n/m") -> n/m | J6: FY26 10-K（6/30） | K6: 營業租賃負債 0.003；GAAP 營業損益 -1.047＋D&A 0.418。自有電廠、營業租賃負債僅 0.003bn；FY26 合約 ARR 4.0bn
A7: APLD Applied Digital | B7: 8.22 | C7: 3.37 | D7: =B7+C7 -> 11.59 | E7: 0.6113 | F7: =D7/E7 -> 18.959594 | G7: =(D7+0.066)/E7 -> 19.067561 | H7: =-0.236+0.067 -> -0.169 | I7: =IF(H7>0,D7/H7,"n/m") -> n/m | J7: FY26 10-K（5/31） | K7: 營業租賃負債 0.066；GAAP 營業損益 -0.236＋D&A 0.067。租約多未起租，營收尚未反映約 36bn 合約
A8: CORZ Core Scientific | B8: 5.9 | C8: 2.53 | D8: =B8+C8 -> 8.43 | E8: 0.4403 | F8: =D8/E8 -> 19.146037 | G8: =(D8+0.109)/E8 -> 19.393595 | H8: =-0.561+0.063 -> -0.498 | I8: =IF(H8>0,D8/H8,"n/m") -> n/m | J8: TTM 至 Q2（6/30） | K8: 營業租賃負債 0.109；GAAP 營業損益 -0.561＋D&A 0.063。託管轉型期
A9: 同業中位數 | F9: =MEDIAN(F5:F8) -> 23.936526 | G9: =MEDIAN(G5:G8) -> 24.062427
A10: CRWV（TTM 至 Q2） | B10: 47.12 | C10: =輸入與假設!$C$167 -> 30 | D10: =B10+C10 -> 77.12 | E10: 7.59 | F10: =D10/E10 -> 10.160738 | G10: =(D10+16.319)/E10 -> 12.310804 | H10: =-0.231+3.991 -> 3.76 | I10: =IF(H10>0,D10/H10,"n/m") -> 20.510638 | J10: TTM 至 Q2 | K10: EV 用 9/21 市值與 6/30 淨負債；含租賃再加營業租賃負債 16.319
A11: CRWV 模型 FY27E | B11: =輸入與假設!$C$165*輸入與假設!$C$166 -> 52.90631 | C11: =輸入與假設!$C$167 -> 30 | D11: =B11+C11 -> 82.90631 | E11: =損益!D8 -> 26.1275 | F11: =D11/E11 -> 3.1731436 | G11: =(D11+16.319)/E11 -> 3.7977346 | H11: =損益!D19 -> 15.41514 | I11: =D11/H11 -> 5.3782392 | K11: 市值用模型股數（含 ATM 上限）；分母為模型 FY27 營收
A13: 讀法：CRWV 的 TTM EV/Sales 約為同業中位數的四成。折價來源有三，不能全部解讀為便宜：(1) 同業仍在爬坡，TTM 營收遠小於已簽約規模，TTM 倍數偏高；
A14: (2) CRWV 用租約取得機房，加入營業租賃負債後倍數升至約 12x，同業加與不加差別很小；(3) 客戶集中（前三大 72%）與五期外部資金需求。
A15: 前瞻：NBIS 前瞻 EV/Sales 約 9.3x（由 9/18 forward PS 推算 [Derived]），CRWV 模型 FY27E 約 3x。此表為市場比較用，不進入目標價（DCF 45%＋EV/EBITDA 55%）。

Sheet 檢查_連動
A1: 連動檢查 — 恆等式與口徑
A3: 檢查項目 | B3: 實際值 | C3: 標準 | D3: 結果 | E3: 說明
A4: RPO 桶權重合計 | B4: =SUM(輸入與假設!C25:G25) -> 0.84 | C4: =輸入與假設!$C$18 -> 0.84 | D4: =IF(ABS(B4-C4)<0.0001,"通過","不一致") -> 通過 | E4: 10-Q 桶 41／39／20 線性分攤後應為 84%
A5: 現金橋差異 | B5: =各期收支!C84 -> 3.8191672e-14 | C5: =0 -> 0 | D5: =IF(ABS(B5)<0.01,"通過","不一致") -> 通過 | E5: 期初＋營運缺口＋股權＋額度−還本 ＝ 期末
A6: Billable ≤ Accepted（FY30） | B6: =運營_產能與收入!G9-運營_產能與收入!G10 -> 350 | C6: ≥0 | D6: =IF(B6>=0,"通過","不一致") -> 通過 | E6: 引擎已以 MIN 截斷；此列驗證截斷有效
A7: FY26 CapEx 認列 vs 指引 | B7: =各期收支!C88 -> 37.800889 | C7: 35–39 | D7: =IF(AND(B7>=35,B7<=39),"通過","觀察") -> 通過 | E7: 1H 實際認列 16.139＋2H 模型；公司 8/11 上修全年 35–39
A8: FY26 營收 vs 指引 | B8: =各期收支!C87 -> 13.066 | C8: 12.4–13.2 | D8: =IF(AND(B8>=12.4,B8<=13.2),"通過","觀察") -> 通過 | E8: 1H 實際 4.653＋2H 模型（算力＋非算力服務）
A9: CapEx 強度（模型期合計） | B9: =SUM(各期收支!C6:G6)/((運營_產能與收入!G9-輸入與假設!$C$20)/1000)/1000*1000 -> 42.902347 | C9: $28–34m/MW | D9: =IF(AND(B9>=20,B9<=45),"通過","觀察") -> 通過 | E9: 公司自身比率：2026 CapEx 35–39bn 對應約 +1.25 GW ＝ $28–34m/MW
A10: 表外租金路徑 ÷ 已承諾 | B10: =資產負債_租賃承諾!C27 -> 0.89221822 | C10: ≥0.8x | D10: =IF(B10>=0.8,"通過","不一致") -> 通過 | E10: 8 GW 路徑所需新租約多數未簽，路徑高於承諾屬假設
A11: FY26 利息（1H 實際＋2H） | B11: =各期收支!C89 -> 3.5875869 | C11: ≥2.9 | D11: =IF(B11>=2.9,"通過","觀察") -> 通過 | E11: ="1H 實際 1.176＋2H 模型 "&TEXT(各期收支!C13,"0.0")&"；Q3 指引 0.86–0.94／季" -> 1H 實際 1.176＋2H 模型 1.8；Q3 指引 0.86–0.94／季
A12: FY28 起收入是否依賴未簽約 | B12: =SUM(運營_產能與收入!E23:G23)/SUM(運營_產能與收入!E25:G25) -> 0.40729557 | C12: <50% 較穩健 | D12: =IF(B12<0.5,"通過","觀察") -> 通過 | E12: FY28–30 新簽約收入 ÷ 同期總算力收入。高＝8 GW 敘事的風險集中點
A13: 損益營收＝資金營收 | B13: =損益!D6-運營_產能與收入!D25 -> 0 | C13: =0 -> 0 | D13: =IF(ABS(B13)<0.001,"通過","不一致") -> 通過 | E13: FY27 損益算力收入 − 產能頁 isRev。兩邊必須同一組數字
A14: 終值占 EV 比重 | B14: =評價_DCF與目標價!C26 -> -0.44466433 | C14: ="<"&IF(ROUND(ABS(輸入與假設!$C$209)*100,4)=INT(ROUND(ABS(輸入與假設!$C$209)*100,4)),TEXT(ROUND(ABS(輸入與假設!$C$209)*100,4),"0"),TEXT(ROUND(ABS(輸入與假設!$C$209)*100,4),"0.0"))&"%" -> <85% | D14: =IF(B14<輸入與假設!$C$209,"通過","觀察") -> 通過 | E14: 過高表示結論由終值假設決定
A15: EBITDA 單一來源（FY27 損益 EBITDA÷營收 − 輸入 EBITDA 率） | B15: =損益!D19/損益!D8-輸入與假設!D87 -> 0 | C15: =0 -> 0 | D15: =IF(ABS(B15)<0.0001,"通過","不一致") -> 通過 | E15: 損益與資金引用同一列 EBITDA 率
A16: 現金 EBITDA ＋ 信用調整 − 損益 EBITDA（FY27） | B16: =(運營_產能與收入!D36+運營_產能與收入!D37+輸入與假設!D88-各期收支!D12)+(運營_產能與收入!D31+運營_產能與收入!D23*輸入與假設!D31*(1-輸入與假設!D32))*運營_產能與收入!D35-損益!D19 -> 0 | C16: =0 -> 0 | D16: =IF(ABS(B16)<0.001,"通過","不一致") -> 通過 | E16: 現金 EBITDA＝RPO 現金＋新簽約現金＋服務現金−租金；信用調整＝信用損失×EBITDAR 率
A17: DCF 有效性（1＝失效） | B17: =評價_DCF與目標價!C29 -> 0 | C17: 0 | D17: =IF(B17=0,"通過","觀察") -> 通過 | E17: 失效只定義為 WACC ≤ g 或常態化 FCF ≤ 0；股權為負不算失效
A18: 期末現金 ≥ 最低現金（期前融資） | B18: =MIN(各期收支!C41:G41) -> 2 | C18: ≥2.0 | D18: =IF(B18>=1.999,"通過","不一致") -> 通過 | E18: 瀑布每期補足至最低現金；最小值應等於最低現金
A19: 股權募資 ÷ 現市值 | B19: =SUM(各期收支!C61:G61)/(輸入與假設!$C$165*輸入與假設!$C$166) -> 0.39965928 | C19: ="≤"&IF(輸入與假設!$C$206=INT(輸入與假設!$C$206),TEXT(輸入與假設!$C$206,"0"),TEXT(輸入與假設!$C$206,"0.0"))&"x" -> ≤1.5x | D19: =IF(B19<=輸入與假設!$C$206,"通過","觀察") -> 通過 | E19: ="超過 "&IF(輸入與假設!$C$206=INT(輸入與假設!$C$206),TEXT(輸入與假設!$C$206,"0"),TEXT(輸入與假設!$C$206,"0.0"))&" 倍：市場吸收能力存疑，結論不得為買進" -> 超過 1.5 倍：市場吸收能力存疑，結論不得為買進
A20: 債務明細合計 = 10-Q 本金 35.551 | B20: =資產負債_既有債務!E21 -> 35.551 | C20: 35.551 | D20: =IF(ABS(B20-35.551)<0.01,"通過","不一致") -> 通過 | E20: 16 筆工具逐筆加總
A21: FY26 全年 CapEx（MW 公式） | B21: =輸入與假設!C132 -> 37.800889 | C21: 35–39 | D21: =IF(AND(B21>=35,B21<=39),"通過","觀察") -> 通過 | E21: 由 YE25 850→YE26 1,850 MW 與預建 FY27 推得；應重現公司全年指引
A22: JV 已承諾餘額於 2026 年內履行 | B22: =SUM(輸入與假設!C125:G125) -> 1.15 | C22: =1.15 -> 1.15 | D22: =IF(ABS(B22-1.15)<0.01,"通過","不一致") -> 通過 | E22: 10-Q：1.7 承諾預計 2026 年內履行，H1 已付 0.55
A23: 模型每 MW 年租金（FY30） | B23: =運營_站點!G25 -> 0.99818047 | C23: ≥ 市場基準×占比 | D23: =IF(B23>=運營_站點!$H$9*運營_站點!$C$26*0.8,"通過","觀察") -> 觀察 | E23: 低於基準×占比的八成即標示：模型租金路徑可能低估
A24: 站點租賃：五期租金可能低估 | B24: =運營_站點!$C$29 -> 3.2916603 | C24: <10 | D24: =IF(B24<10,"通過","觀察") -> 通過 | E24: ＝Σ(在役 MW×市場基準×第三方占比 − 模型租金)
A26: 關鍵輸出（快照；「模型期」＝2026-07-01～2030，與 HTML 頂部 KPI 同口徑）
A27: 模型期排程 RPO | B27: =SUM(運營_產能與收入!C17:G17) -> 108.108
A28: 模型期產能瓶頸 | B28: =SUM(運營_產能與收入!C19:G19) -> 6.33475
A29: 模型期新簽約收入 | B29: =SUM(運營_產能與收入!C23:G23) -> 47.094444
A30: 模型期毛 CapEx（6/30 起） | B30: =SUM(輸入與假設!C137:G137) -> 166.19598
A31: 模型期租金（6/30 起） | B31: =SUM(各期收支!C12:G12) -> 20.317893
A32: 模型期利息（6/30 起，含瀑布新債） | B32: =SUM(各期收支!C17:G17) -> 37.148912
A33: 模型期排程還本（6/30 起） | B33: =SUM(輸入與假設!C160:G160)*輸入與假設!$C$146 -> 20.655
A34: 模型期營運缺口（6/30 起） | B34: =SUM(各期收支!C39:G39)-(輸入與假設!$C$213-輸入與假設!$C$214-輸入與假設!$C$216) -> -100.24607
A35: FY26 全年口徑營運缺口（含 1H 實際） | B35: =SUM(各期收支!C39:G39) -> -111.38807
A36: 期末現金 | B36: =各期收支!G41 -> 2
A37: DCF 每股 | B37: =評價_DCF與目標價!C25 -> 0
A38: 加權目標價 | B38: =評價_DCF與目標價!C48 -> 29.678472

Sheet 檢查_版本紀錄
A1: 版本紀錄（基準情境目標價變化與原因）
A2: v2.9 以前檔名日期統一沿用 20260918，此處日期為實際修改日。v1.7 以前基準為 8 GW、v1.7 為 5 GW、v1.8 起為 5.6 GW；情境定義改變的版本不可直接比較。目標價以當版預設輸入計算（DCF 0 截斷）
A4: 版本 | B4: 日期 | C4: 主要變更 | D4: 基準目標價 | E4: 變動原因
A5: v4.6 | B5: 10-08 | C5: 每 MW 經濟性改接 Tokenomics v5.26（YinchenChang/Tokenomics，快照版本固定）：每 MW 資本支出＝新增世代占比 × IF_CapexIT（不含廠房，廠房在租金）、營運成本改由下而上（電費、IT 維護、人員軟體、稅險 × 平均在役 MW＋管銷率 5.5%）、折舊年限 IF_DeprLifeIT；收入採備案（每 MW 年收入仍為輸入，另列隱含 GPU 小時價格與 Tokenomics 持有成本對照）；世代組合（期初 1.5 GW：Hopper 27%／GB200 29%／GB300 43%；新增 GB300 → VR200）；方法開關 methodology.perMw（全設舊方法＝v4.5）；新增「每MW經濟性」頁、一頁摘要每 MW 一句 | D5: $29.7 | E5: 基準 $45.5→$29.7、保守 $69.7→$44.0、積極 $31.0→$19.9，三者皆賣出。拆解：(a) 時間推移 0、(b) 實際數更新 0、(c) 假設變更 0、(d) 方法變更 −$15.8（① 每 MW 資本支出 −$7.6、② 折舊年限 0、③ 營運成本由下而上 −$8.2、④ 收入 0（備案）、⑤ MW 口徑 0）；保守 −$25.7（−$16.6／0／−$9.2）、積極 −$11.0（−$9.1／0／−$1.9）
A6: v4.5 | B6: 09-26 | C6: 期間滾動＋反向 DCF：company.json 新增 calendar（財年結束月份、最新已申報／已公布季度），期間、評價日（最新已申報季末）與折現年數由日曆推算（首期 0.25／0.5／0.75／1 年、5 月財年、無實際數皆可）；actual1H 改為 ytdActual；目標價時點改為「評價日＋12 個月」（2027-06-30），EV/EBITDA 腿折回、DCF 腿（0 截斷與選擇權）以 WACC 推到同一時點；反向 DCF 改由 Excel 求解；一頁摘要與各分頁第一屏的日期與期間文字依日曆產生 | D6: $45.5 | E6: 基準 $47.9→$45.5、保守 $71.7→$69.7、積極 $32.6→$31.0，三者皆賣出。拆解：(a) 時間推移 0（評價日仍為 6/30）、(b) 實際數更新 0、(c) 假設變更 0、(d) 方法變更（目標價時點改為評價日＋12 個月、DCF 腿推到同一時點）−$2.4（保守 −$1.9、積極 −$1.7）
A7: v4.4 | B7: 09-26 | C7: 季度層：資金模型新增「季度追蹤」分頁，Excel 新增「季度追蹤」分頁與「輸入與假設」J 區（2026 Q3–2027 Q4，由年度模型拆分、只用於追蹤；實際數輸入格預設空白）；差距超過門檻（營收等 5%、利潤類利潤率 2pt）或落在指引區間外的項目附差異原因（觀點／拆法／已知限制；拆法以水準／分配拆解判定）；差距寫法：營收、CapEx 為比例，利潤類為金額差＋利潤率百分點；一頁摘要驗證點改為焦點季 3 個指標，方法註腳與最新分析師動作移至市場共識分頁 | D7: $47.9 | E7: 無變動（季度層不影響年度數字與目標價）
A8: v4.3 | B8: 09-25 | C8: 一頁摘要＋市場共識對照：總結頁新增一頁摘要（原 9 頁改為附錄，共 10 頁）；損益與評價新增「市場共識」分頁，Excel 新增「摘要」分頁與「輸入與假設」I 區（逐筆附來源、擷取日期、標記）；移除 Street 參考欄位；現價更新至 9/24 收盤 $90.13（股權發行價同步） | D8: $47.9 | E8: 現價 $85.43→$90.13：發行價提高、新股減少，基準 $47.5→$47.9；保守 −16%→−20%，距賣出門檻 $0.9→$4.9
A9: v4.2 | B9: 09-25 | C9: 設定集中：同業 Comps（數字、名稱、備註、說明文字）與評等門檻移入 company.json（peers、methodology.rating）；Excel「輸入與假設」F 區新增「評等門檻」7 格，評等代碼、賣出門檻價、判斷句與檢查頁改為引用；評等規則說明改為活公式；數字與畫面與 v4.1 相同 | D9: $47.5 | E9: 無變動（純結構）
A10: v4.1 | B10: 09-25 | C10: 目標價改為區間呈現：情境區間（保守與積極情境，保留手動調整）與方法區間（目前情境，EV/EBITDA 5–6x）；判斷句揭露與賣出門檻的餘裕；DCF 權重說明；刪除評價頁舊的下檔／上檔與操作區間；Excel 情境區間以模擬運算表計算（活公式） | D10: $47.5 | E10: 點位無變動；情境區間 $32.1–$71.7、方法區間 $30.8–$47.5
A11: v4.0 | B11: 09-24 | C11: 結構重整：公司資料集中到 company.json（HTML 與 Excel 共用，Excel 75 項輸入改讀此檔）；資料常數與引擎主函式改為可讀名稱；數字與畫面與 v3.6 完全相同 | D11: $47.5 | E11: 無變動（純結構）
A12: v3.6 | B12: 09-24 | C12: EV/EBITDA 錨定年度預設改為 FY29（接近穩態利潤率，與 6x 穩態倍數一致） | D12: $47.5 | E12: 錨定 FY27→FY29：EV/EBITDA 腿 $38.7→$86.4；保守情境 $71.7（−16%）接近賣出門檻
A13: v3.5 | B13: 09-24 | C13: EV/EBITDA 錨定年度可選（FY27–FY30，FY28 起以 WACC 折回 FY27 末）；評價頁與總結頁新增「錨定年度 × 倍數」矩陣；總結頁新增評價方法頁（9 頁） | D13: $21.3 | E13: 預設仍錨定 FY27，無變動；FY29 × 6x 為 $47.5
A14: v3.4 | B14: 09-24 | C14: 新增「總結」簡報頁（8 頁、即時連動、簡報模式、列印 16:9）；股權敏感度表加註融資組合與自動說明；更正融資瀑布說明的股權年度；修正 Excel 無法開啟（sheetPr 子元素順序，v3.3 起即存在） | D14: $21.3 | E14: 無變動
A15: v3.3 | B15: 09-23 | C15: 反向 DCF（收入 × 成本組合）；版本變更紀錄；每 MW 年收入／建置成本倍數 | D15: $21.3 | E15: 倍數預設 100%，無變動
... A36: v1.0 | B36: 09-18 | C36: Oracle 模板改寫為 CoreWeave：2H26–FY30、10-Q／法說／8-K 數據 | D36: $19 | E36: 基準當時為 8 GW

Sheet 來源
A1: 來源與標籤
A3: 標籤 | B3: 內容
A4: Verified | B4: Q2 2026 10-Q（期末 2026-06-30，2026-08-12 申報，Non-accelerated filer，Q3 期限 11/16）：營收 2.575bn +112%（H1 4.653）；GAAP 營損 −0.049；利息費用 0.640（H1 1.176，現金 0.806、資本化 0.176）；淨損 −0.626；Adj. EBITDA 1.510（59%）；SBC 0.165；D&A 1.393；營業租賃成本 0.500、變動租賃 0.150。
A5: Verified | B5: 資產負債：現金 5.524、受限 1.380、有價證券 0.015、可用額度 10.014；PP&E 46.736（CIP 11.9）；營業 ROU 16.595；遞延收入 9.692；債務本金 35.551（追索淨 31.405／非追索 3.663）；股東權益 5.024。
A6: Verified | B6: RPO 103.7bn（backlog 104.2）：41% 於 2028-06 前、39% 於 25–48 月、20% 於 49–78 月。客戶集中：A 36%、B 26%、C 10%；OpenAI 最高 6.5bn 至 2031-05；Meta 最高 21.0bn；Jane Street 約 6.0bn。
A7: Verified | B7: 租賃與承諾：在帳未折現 29.135（營業）＋0.235（融資），2030 後 19.023；未起租租賃 35.5；單站 393 MW 按造價計租上限 14.7／16 年；355 MW 按造價計租（未定）；自備設備 0.5–1.2；JV 承諾 1.7（已付 0.55）；VIE 0.108。
A8: Verified | B8: 現金流（H1）：CFO 3.663；現金購置 PP&E 14.117；借款 16.747、還款 5.219；capped call 0.492；私募股權 2.982。CapEx 認列口徑 Q2 9.352、H1 16.139。
A9: Verified | B9: 9/17 8-K：2033 可轉債 3.7bn、2.875%、轉換價 $97.85、capped call 上限 $199.70；股權分銷最多 35m 股；9/17 收盤 $79.88。
A10: Verified | B10: 市值（2026-09-21 收盤，S&P Global via stockanalysis.com）：CRWV 現價 $90.13（2026-09-24 收盤）、市值 47.12bn（2026-09-21）、流通 551.54m；NBIS 63.81；IREN 18.61；APLD 8.22；CORZ 5.90。淨負債取各公司最新申報：NBIS 2.16、IREN 1.70、APLD 3.37、CORZ 2.53。
A11: Interested-party | B11: 賣方目標價（S&P Global Market Intelligence（經 StockAnalysis.com），擷取 2026-09-25）：平均 $140.81、中位數 $140.00、區間 $39.00–$317.00（40 家）；共識評等 Buy。對照 MarketScreener（同為 S&P／FactSet 資料，非獨立）：平均 $140.95（40 家，Outperform）。數字為賣方意見；逐筆來源與日期見『輸入與假設』I 區。
A12: Interested-party | B12: 法說（8/11）：主動電力 1.5 GW（Q2 +近 500 MW，6 月 +300 MW）；簽約 4.2 GW；2030 ≥8 GW；近期產能實質售罄；7 月 SKU 漲價約 25%；全年營收 12.4–13.2、調整後營益 0.96–1.15、CapEx 35–39、期末 ARR 18.5–19.5；Q3 營收 3.45–3.6、利息 0.86–0.94、CapEx 11.5–13.5。
A13: Interested-party | B13: 9/17 投資人簡報：Q2 pro forma 總債務 38.6bn；加權利率 FY23 14.9% → Q2 8.3% → pro forma 7.8%；總債務／backlog 0.4x；歷年 backlog 9.9／15.1／66.8／104.2。
A14: User-provided | B14: 5Y CDS（2026-09）：中價 720bps、Bid/Ask 690／750、近期區間 680–855（對照 7/28 峰值 855、6 月低點 452）。
... A19: 方法 | B19: v2.0 期前融資瀑布：額度→資產層新債（總債務 ≤ 債務/backlog 上限）→股權殘差；舊版假設缺口全額舉債且無上限（透支利息＝利息、扣缺口＝本金），v2.0 改為債務設上限、殘差以股權支應。

Sheet Tokenomics_取數
A1: Tokenomics 取數（算力相關的產業與物理層資料）
A2: 來源：YinchenChang/Tokenomics 20261007_Tokenomics_v5.26.xlsx（v5.26，commit 4074684，擷取 2026-10-07）。只引用 IF_（不含 IF_Hdr*）與 L1_ 名稱；模型主值取「基準」，低／高只作敏感度；Tokenomics 每 GW＝IT 關鍵電力。
A3: 本分頁目前只顯示、尚未被任何公式引用（W1）；值為快照的藍字輸入格，更新方式見 repo 根目錄 README「共用工具：Tokenomics 取數」。
A4: 具名範圍（基準） | B4: 名稱 | C4: 中文標籤 | D4: 單位 | E4: 世代 | F4: 低成本 | G4: 基準 | H4: 高成本 | I4: Tokenomics 位置 | J4: 版本與 commit
A5: TK_RacksPerGW_H100 | B5: IF_RacksPerGW | C5: 每 GW 機架數 | D5: 架 | E5: Hopper H100 | F5: 22439 | G5: 22439 | H5: 22439 | I5: Interface!C6:E6 | J5: v5.26 · 4074684
A6: TK_RacksPerGW_GB200 | B6: IF_RacksPerGW | C6: 每 GW 機架數 | D6: 架 | E6: GB200 NVL72 | F6: 6969 | G6: 6969 | H6: 6969 | I6: Interface!F6:H6 | J6: v5.26 · 4074684
A7: TK_RacksPerGW_GB300 | B7: IF_RacksPerGW | C7: 每 GW 機架數 | D7: 架 | E7: GB300 NVL72 | F7: 6764 | G7: 6764 | H7: 6764 | I7: Interface!I6:K6 | J7: v5.26 · 4074684
A8: TK_RacksPerGW_VR200 | B8: IF_RacksPerGW | C8: 每 GW 機架數 | D8: 架 | E8: VR200 NVL72 | F8: 4052 | G8: 4052 | H8: 4052 | I8: Interface!L6:N6 | J8: v5.26 · 4074684
A9: TK_RacksPerGW_RU | B9: IF_RacksPerGW | C9: 每 GW 機架數 | D9: 架 | E9: Rubin Ultra（MGX NVL 單架，72 GPU） | F9: 2705 | G9: 2705 | H9: 2705 | I9: Interface!O6:Q6 | J9: v5.26 · 4074684
A10: TK_GPUsPerGW_H100 | B10: IF_GPUsPerGW | C10: 每 GW GPU 數 | D10: 顆 | E10: Hopper H100 | F10: 718048 | G10: 718048 | H10: 718048 | I10: Interface!C7:E7 | J10: v5.26 · 4074684
A11: TK_GPUsPerGW_GB200 | B11: IF_GPUsPerGW | C11: 每 GW GPU 數 | D11: 顆 | E11: GB200 NVL72 | F11: 501768 | G11: 501768 | H11: 501768 | I11: Interface!F7:H7 | J11: v5.26 · 4074684
A12: TK_GPUsPerGW_GB300 | B12: IF_GPUsPerGW | C12: 每 GW GPU 數 | D12: 顆 | E12: GB300 NVL72 | F12: 487008 | G12: 487008 | H12: 487008 | I12: Interface!I7:K7 | J12: v5.26 · 4074684
A13: TK_GPUsPerGW_VR200 | B13: IF_GPUsPerGW | C13: 每 GW GPU 數 | D13: 顆 | E13: VR200 NVL72 | F13: 291744 | G13: 291744 | H13: 291744 | I13: Interface!L7:N7 | J13: v5.26 · 4074684
A14: TK_GPUsPerGW_RU | B14: IF_GPUsPerGW | C14: 每 GW GPU 數 | D14: 顆 | E14: Rubin Ultra（MGX NVL 單架，72 GPU） | F14: 194760 | G14: 194760 | H14: 194760 | I14: Interface!O7:Q7 | J14: v5.26 · 4074684
A15: TK_FacilityGW_H100 | B15: IF_FacilityGW | C15: 每 IT GW 對應設施電力 | D15: GW | E15: Hopper H100 | F15: 1.1 | G15: 1.2 | H15: 1.3 | I15: Interface!C8:E8 | J15: v5.26 · 4074684
A16: TK_FacilityGW_GB200 | B16: IF_FacilityGW | C16: 每 IT GW 對應設施電力 | D16: GW | E16: GB200 NVL72 | F16: 1.1 | G16: 1.2 | H16: 1.3 | I16: Interface!F8:H8 | J16: v5.26 · 4074684
... A54: TK_PowerCost_RU | B54: IF_PowerCost | C54: 其中：每 GW 年電費 | D54: $B/年 | E54: Rubin Ultra（MGX NVL 單架，72 GPU） | F54: 0.404712 | G54: 0.672768 | H54: 1.02492 | I54: Interface!O15:Q15 | J54: v5.26 · 4074684
A55: TK_Util | B55: IF_Util | C55: 基準利用率（第 0 層；下游可覆寫） | D55: % | E55: — | G55: 0.6 | I55: Interface!C48 | J55: v5.26 · 4074684
A56: TK_FacCapexMW | B56: L1_FacCapexMW | C56: 每 MW IT 廠房資本支出 | D56: $M/MW | E56: — | F56: 10.212 | G56: 12.67 | H56: 16.186 | I56: L1!D10（低／高＝E10／F10；成本角落情境（低成本／高成本欄）） | J56: v5.26 · 4074684
A57: TK_GPUhr_GB200_vsCW | B57: L1_GPUhr_GB200_vsCW | C57: 每 GPU 小時持有成本 — 經濟（GB200）對 CoreWeave 隨需牌價 | D57: $/GPU-hr | E57: — | F57: 1.5500366 | G57: 2.0864538 | H57: 3.3943966 | I57: L1!D30（低／高＝E30／F30；成本角落情境（低成本／高成本欄）） | J57: v5.26 · 4074684
A58: TK_GPUhr_GB300_vsBE | B58: L1_GPUhr_GB300_vsBE | C58: 每 GPU 小時持有成本 — 經濟（GB300）對新雲損益兩平租金 | D58: $/GPU-hr | E58: — | F58: 2.0410414 | G58: 2.9826956 | H58: 5.5955944 | I58: L1!D31（低／高＝E31／F31；成本角落情境（低成本／高成本欄）） | J58: v5.26 · 4074684
A59: TK_RevGW_Fleet_VR200 | B59: L1_RevGW_Fleet_VR200 | C59: 1 GW 參考機隊付費營收（理想上限，VR200） | D59: $B/GW/年 | E59: — | F59: 32.482468 | G59: 48.723702 | H59: 64.964936 | I59: L1!D29（低／高＝E29／F29；利用率 40–80%（Sens_Rev 情境值；J6 區間）） | J59: v5.26 · 4074684
A60: TK_DeprLifeIT_H100 | B60: IF_DeprLifeIT | C60: IT 折舊年限 | D60: 年 | E60: Hopper H100 | F60: 6 | G60: 6 | H60: 4 | I60: Interface!C219:E219 | J60: v5.26 · 4074684
A61: TK_DeprLifeIT_GB200 | B61: IF_DeprLifeIT | C61: IT 折舊年限 | D61: 年 | E61: GB200 NVL72 | F61: 6 | G61: 6 | H61: 4 | I61: Interface!F219:H219 | J61: v5.26 · 4074684
A62: TK_DeprLifeIT_GB300 | B62: IF_DeprLifeIT | C62: IT 折舊年限 | D62: 年 | E62: GB300 NVL72 | F62: 6 | G62: 6 | H62: 4 | I62: Interface!I219:K219 | J62: v5.26 · 4074684
A63: TK_DeprLifeIT_VR200 | B63: IF_DeprLifeIT | C63: IT 折舊年限 | D63: 年 | E63: VR200 NVL72 | F63: 6 | G63: 6 | H63: 4 | I63: Interface!L219:N219 | J63: v5.26 · 4074684
A64: TK_DeprLifeIT_RU | B64: IF_DeprLifeIT | C64: IT 折舊年限 | D64: 年 | E64: Rubin Ultra（MGX NVL 單架，72 GPU） | F64: 6 | G64: 6 | H64: 4 | I64: Interface!O219:Q219 | J64: v5.26 · 4074684
A65: TK_DeprIT_H100 | B65: IF_DeprIT | C65: 每 GW IT 折舊 | D65: $B/年 | E65: Hopper H100 | F65: 3.5700449 | G65: 4.5850357 | H65: 8.5301859 | I65: Interface!C220:E220 | J65: v5.26 · 4074684
A66: TK_DeprIT_GB200 | B66: IF_DeprIT | C66: 每 GW IT 折舊 | D66: $B/年 | E66: GB200 NVL72 | F66: 3.4398984 | G66: 4.002529 | H66: 6.9125511 | I66: Interface!F220:H220 | J66: v5.26 · 4074684
A67: TK_DeprIT_GB300 | B67: IF_DeprIT | C67: 每 GW IT 折舊 | D67: $B/年 | E67: GB300 NVL72 | F67: 4.7591504 | G67: 6.2409173 | H67: 12.737627 | I67: Interface!I220:K220 | J67: v5.26 · 4074684
... A109: TK_OpexGW_RU | B109: IF_OpexGW | C109: 每 GW 營運費用小計（不含折舊；含電費） | D109: $B/年 | E109: Rubin Ultra（MGX NVL 單架，72 GPU） | F109: 1.6529763 | G109: 3.0675203 | H109: 5.1121728 | I109: Interface!O228:Q228 | J109: v5.26 · 4074684
