Workbook

Sheet README
A1: 韓美半導體 Hanmi Semiconductor（042700.KS）收支與估值模型 v0.2.3（AI 半導體 Project 步驟 5：設備與材料） 2026-10-25
A2: v0.1（2026-10-25）：首版。樣板 advantest/（設備股，統一循環規則）。本版未做先驗，無 Andy 合理 P/E 對照。
A3: 模型命題：韓美的盈餘由 HBM 的 TC 鍵合需求決定——需求來自記憶體廠下一年的鍵合產能增量（HBM 位元 ÷ 晶粒容量 × 層數加權），韓美的份額集中在 SK 海力士與美光。股價取決於 HBM 位元成長在 2028 之後放緩、晶粒容量提高與混合鍵合導入時，TC 鍵合機的新機需求與韓美在 SK 海力士的份額能否守住。
A5: 會計年度＝日曆年。金額以億韓元（₩億）為主；EPS 為韓元。FY2026 為錨點：上半年實績（509＋2,511）＋下半年假設（h2f、m_h2）；第三季預定 2026-11 公布，建置日未納入。
A7: 驅動因子 → 推導量
A8: HBM 出貨位元（markets/memory，情境別）÷ 晶粒容量 → 核心晶粒數 × 層數加權 ×（1 − 混合鍵合占比）→ TC 鍵合產能需求；新機需求＝下一年產能增量＋汰換
A9: × 各記憶體廠占產能增量（t＋1 年 HBM 市占，讀三家記憶體模型）× 韓美在該廠份額 → 韓美可得需求 × 校準係數 k（FY2025–26 兩年營收）→ HBM TC 鍵合機營收；其他業務＝前一年 × 成長率
A10: 毛利率：FY2026 由錨點營業利益反推，之後沿用（C 扣價格競爭）；營業費用＝固定＋變動 × 營收；不寫死利益率
A11: 情境 A／B／C：HBM 位元讀 markets/memory（2028 ×1.0／0.8／0.6，2029 ×1.0／0.85／0.6）；混合鍵合為行業技術變數、與 Disco 同字母（v0.2.1：CY2028 起 A 取高值、B 基準、C 低值）；公司特有變數（份額、其他業務成長）CY2028 起分情境、A 最有利；C 另加韓華、ASMPT 搶份額與毛利率下調。Val：十年 P/E 分位，循環位置依設備股共用規則（見頂年 A 2029、B 2028、C 2027 → FY2027：A 中段、B 中段、C 見頂）；目標價＝三情境 0.3／0.5／0.2 加權
A13: 標記：Verified、Interested-party、Analogy、Assumed、Derived。SemiAnalysis 未使用。DART 原文未開啟，實績取自新聞稿報導與財務資料頁，原文待人工複核。
A14: 已知限制：(1) 公司不揭露產品別與 2025 客戶別營收，TC 鍵合機占比（60%）與中國比重（17%）取自 CGSI（賣方）；(2) 韓美在 SK 海力士、美光的份額為 Assumed，模型對它們最敏感；(3) 以 HBM 營收市占代替各廠產能增量占比（Analogy）；(4) 晶粒容量、層數、混合鍵合比例沿用 Disco 模型的 Assumed；(5) 鍵合機假設比產能早一年購入，實際交期可能更短，會讓模型的轉折早於實際；(6) 韓美自家混合鍵合機（2027 量產工廠）的營收不建模；(7) 十年 P/E 2016–2017 只有一個來源，companiesmarketcap 2021 年值與他源差異大。
A15: v0.2（2026-10-25）估值 v2：Val 頁新增「0. 目標價」（放在既有內容之後，不位移既有列）＝0.5 × DCF 目標價（股東現金流＝EPS ×（1 − g／ROE），FY2027–32 明確期＋永續，r 10%、g 4%，情境權重 A 0.3／B 0.5／C 0.2）＋0.5 × Comparable 目標價（同業前瞻 P/E 中位數 × 12 個月後前瞻 EPS）；另列 Comparable 單獨目標價、市場共識目標價與差距拆解、歷史分位檢查。原「0. 目標價與上檔空間」改名「舊法：規則值情境加權（參考）」，不再叫目標價。
... A18: v0.2.2（2026-10-25）：補上檔空間級距、投資建議、重點觀察（數值不變）。Val 頁最後新增「上檔空間級距」「投資建議」兩列（依「上檔空間：加權目標價」固定規則）；README 頁最後新增投資建議與重點觀察三點。
A19: ="投資建議："&Val!B123&"（依上檔空間固定規則）" -> 投資建議：強力放空（依上檔空間固定規則）
A20: ="重點觀察 1：目標價 ₩"&TEXT(Val!$B$111,"#,##0")&"（DCF "&TEXT(Val!$B$97,"#,##0")&"、Comparable（相對倍數調整後）"&TEXT(tp_comp_adj,"#,##0")&"；DCF 權重 "&TEXT(tp_w_dcf,"0%")&"），比現價 "&TEXT(px,"#,##0")&"（2026-10-23）"&IF(Val!$B$114>=0,"高 "&TEXT(Val!$B$114,"0.0%"),"低 "&TEXT(-Val!$B$114,"0.0%"))&"，級距 "&Val!$B$122&"、投資建議 "&Val!$B$123&"。相對倍數調整係數 "&TEXT(rm_factor,"0.00")&"（本公司 10 年前瞻倍數中位數 ÷ 同業的中位數，夾在 0.5–2.0；Val 第 0.5 節），調整前加權上檔空間 "&TEXT((tp_w_dcf*Val!$B$97+(1-tp_w_dcf)*Val!$B$107)/px-1,"+0.0%;−0.0%")&"；Comparable 單獨（市場主流同業法、未調整）為 "&TEXT(Val!$B$115,"+0.0%;−0.0%")&"。"&"以下為 2026-10-29 相對倍數調整前撰寫的說明，其中數字為調整前：主因 EPS 與倍數都有：本模型 12 個月後前瞻 EPS 2,662 比共識前瞻 EPS 約 5,000 低 46.8%；現價隱含 70.8 倍前瞻 EPS，同業（BESI、ASMPT、Kulicke & Soffa、Disco）中位數 25.9 倍、共識目標價 271,429 隱含 54.3 倍（比同業高 109%）。D"&"CF 低不是 ROE（39.2%）造成，而是 FY2028 起 TC 鍵合需求回落（FY2027 EPS 3,098 → A 情境 FY2028 2,363）。" -> 重點觀察 1：目標價 ₩36,848（DCF 27,780、Comparable（相對倍數調整後）45,916；DCF 權重 50%），比現價 188,500（2026-10-23）低 80.5%，級距 小於 −50%、投資建議 強力放空。相對倍數調整係數 0.67（本公司 10 年前瞻倍數中位數 ÷ 同業的中位數，夾在 0.5–2.0；Val 第 0.5 節），調整前加權上檔空間 −74.3%；Comparable 單獨（市場主流同業法、未調整）為 −63.4%。以下為 2026-10-29 相對倍數調整前撰寫的說明，其中數字為調整前：主因 EPS 與倍數都有：本模型 12 個月後前瞻 EPS 2,662 比共識前瞻 EPS 約 5,000 低 46.8%；現價隱含 70.8 倍前瞻 EPS，同業（BESI、ASMPT、Kulicke & Soffa、Disco）中位數 25.9 倍、共識目標價 271,429 隱含 54.3 倍（比同業高 109%）。DCF 低不是 ROE（39.2%）造成，而是 FY2028 起 TC 鍵合需求回落（FY2027 EPS 3,098 → A 情境 FY2028 2,363）。
A21: 重點觀察 2：混合鍵合替代是最大變數：不納入混合鍵合時 FY2028 EPS 3,782（基準 2,363，+60.0%）、FY2027 +9.1%；晶粒容量取低值 FY2027 +15.1%，淨利 ÷ 營業利益 0.72 則 −15.4%。
A22: 重點觀察 3：三情境的現價隱含 P/E 都高於十年最大值（分位 100%）；共識前瞻 EPS 只顯示到千位（約 5,000），差距待第三季財報（預定 2026-11-06 前後）的 TC 鍵合出貨與 2027 年訂單檢驗。
A23: v0.2.3（2026-10-28）：分部原則重建（數值不變）。Q 頁最後追加核對列「檢查：分部合計 − 合併營收」；官方分部與子列宣告見 segments.json。
A25: 2026-10-29：加權目標價中的 Comparable 改用相對倍數調整後的值（Val 第 0.5 節：同業前瞻倍數中位數 × 本公司 10 年相對同業的倍數比，Bloomberg 前瞻倍數；Andy 2026-10-27「照建議做」、10-29 資料取回）。「Comparable 目標價（市場主流同業法）」維持不調整。重點觀察 1 的第一句已改為公式；重點觀察 2、3 與其他說明中的目標價與上檔空間數字為調整前撰寫，以 Val 頁為準。
A27: 2026-10-31：依個股模型原則第 8 節第 3 點，主模型的情境 A／C 改讀 In 頁「情境專屬列」一節（由原敏感度高／低欄拆出、數值不變）；敏感度低／高欄只留給 Sens 頁。
A29: v0.2.4（2026-10-31）：依個股模型原則第 8 節調整 In 頁呈現（數值不變）。In 頁 D／F 欄名改「敏感度低」「敏感度高」（只用於 Sens 頁、不進目標價）；In 頁最後新增「情境驅動對照」一節，把上方各情境專屬輸入三情境並排（只引用上方各列，純展示）；HTML 驅動因子一節分「情境驅動」與「單一參數」兩張表。

Sheet In
A1: In — 輸入（藍字；基準欄 E，低 D、高 F）。金額：億韓元（₩億）；HBM 位元：EB；晶粒：百萬顆。每個輸入附兩個來源（來源2 找不到者寫「未找到」）。【v0.2.4】基準欄 E 進主模型；D／F＝敏感度低／高，只用於 Sens 頁（一次動一個參數）、不進目標價；情境 A／B／C 的驅動見本頁最後一節「情境驅動對照」。
A2: 標記：Verified／Interested-party／Analogy／Assumed／Derived；Analogy、Assumed 給低／高區間，不當點估計（放情境或 Sens）。SemiAnalysis 未使用。公司（hanmisemi.com）不出具年度指引；DART 原文在建置環境無法開啟，實績取自 DART 轉載的財務資料頁（valueline、stockanalysis）與新聞稿報導，原文待人工複核
A3: 鍵 | B3: 項目 | C3: 單位 | D3: 敏感度低 | E3: 基準 | F3: 敏感度高 | G3: 標記 | H3: 來源1 | I3: 來源2／說明
A4: A. HBM 出貨位元（markets/memory，經 SK 海力士模型成品 Mkt 頁；情境 A／B／C 各一列；唯讀）
A5: hsA_25 | B5: HBM 出貨位元 2025（EB；A） | C5: EB | E5: 2.2251147 | G5: Derived | H5: skhynix/dist/20261030_SK海力士個股模型_v0.6.1.xlsx｜Mkt!C24:G24 | I5: markets/memory v0.4：出貨＝MIN(需求 × 情境顆數係數, 供給)；2028–29 隨情境，2025–27 三情境相同
A6: hsA_26 | B6: HBM 出貨位元 2026（EB；A） | C6: EB | E6: 3.782695 | G6: Derived | H6: skhynix/dist/20261030_SK海力士個股模型_v0.6.1.xlsx｜Mkt!C24:G24 | I6: 同上
A7: hsA_27 | B7: HBM 出貨位元 2027（EB；A） | C7: EB | E7: 5.8631772 | G7: Derived | H7: skhynix/dist/20261030_SK海力士個股模型_v0.6.1.xlsx｜Mkt!C24:G24 | I7: 同上
A8: hsA_28 | B8: HBM 出貨位元 2028（EB；A） | C8: EB | E8: 8.501607 | G8: Derived | H8: skhynix/dist/20261030_SK海力士個股模型_v0.6.1.xlsx｜Mkt!C24:G24 | I8: 同上
A9: hsA_29 | B9: HBM 出貨位元 2029（EB；A） | C9: EB | E9: 11.477169 | G9: Derived | H9: skhynix/dist/20261030_SK海力士個股模型_v0.6.1.xlsx｜Mkt!C24:G24 | I9: 同上
A10: hsB_25 | B10: HBM 出貨位元 2025（EB；B） | C10: EB | E10: 2.2251147 | G10: Derived | H10: skhynix/dist/20261030_SK海力士個股模型_v0.6.1.xlsx｜Mkt!C25:G25 | I10: markets/memory v0.4：出貨＝MIN(需求 × 情境顆數係數, 供給)；2028–29 隨情境，2025–27 三情境相同
A11: hsB_26 | B11: HBM 出貨位元 2026（EB；B） | C11: EB | E11: 3.782695 | G11: Derived | H11: skhynix/dist/20261030_SK海力士個股模型_v0.6.1.xlsx｜Mkt!C25:G25 | I11: 同上
A12: hsB_27 | B12: HBM 出貨位元 2027（EB；B） | C12: EB | E12: 5.8631772 | G12: Derived | H12: skhynix/dist/20261030_SK海力士個股模型_v0.6.1.xlsx｜Mkt!C25:G25 | I12: 同上
A13: hsB_28 | B13: HBM 出貨位元 2028（EB；B） | C13: EB | E13: 8.22296 | G13: Derived | H13: skhynix/dist/20261030_SK海力士個股模型_v0.6.1.xlsx｜Mkt!C25:G25 | I13: 同上
A14: hsB_29 | B14: HBM 出貨位元 2029（EB；B） | C14: EB | E14: 11.357964 | G14: Derived | H14: skhynix/dist/20261030_SK海力士個股模型_v0.6.1.xlsx｜Mkt!C25:G25 | I14: 同上
A15: hsC_25 | B15: HBM 出貨位元 2025（EB；C） | C15: EB | E15: 2.2251147 | G15: Derived | H15: skhynix/dist/20261030_SK海力士個股模型_v0.6.1.xlsx｜Mkt!C26:G26 | I15: markets/memory v0.4：出貨＝MIN(需求 × 情境顆數係數, 供給)；2028–29 隨情境，2025–27 三情境相同
A16: hsC_26 | B16: HBM 出貨位元 2026（EB；C） | C16: EB | E16: 3.782695 | G16: Derived | H16: skhynix/dist/20261030_SK海力士個股模型_v0.6.1.xlsx｜Mkt!C26:G26 | I16: 同上
... A19: hsC_29 | B19: HBM 出貨位元 2029（EB；C） | C19: EB | E19: 8.017386 | G19: Derived | H19: skhynix/dist/20261030_SK海力士個股模型_v0.6.1.xlsx｜Mkt!C26:G26 | I19: 同上
A20: g_tail | B20: CY2030 HBM 出貨位元相對 2029 的年增（市場層只到 2029；只用於 CY2029 的鍵合機購買） | C20: % | D20: 0 | E20: 0.1 | F20: 0.2 | G20: Assumed | H20: 無：市場層只到 2029；鍵合機在產能需要前一年購入，CY2029 的購買要看 CY2030 | I20: 與 Disco 模型的 g_tail 同值（Assumed）
A21: B. 晶粒、堆疊層數與混合鍵合（與 Disco 模型同一組假設，讀其成品；唯讀）
A22: den_25 | B22: DRAM 核心晶粒容量（組合平均）2025 | C22: Gb／顆 | D22: 22 | E22: 24 | F22: 24 | G22: Assumed | H22: siliconomics｜SIF_hbm_den_25 | I22: JEDEC HBM4：24Gb 或 32Gb 晶粒；容量愈大，同樣位元需要的晶粒（＝TC 鍵合次數）愈少
A23: den_26 | B23: DRAM 核心晶粒容量（組合平均）2026 | C23: Gb／顆 | D23: 24 | E23: 24 | F23: 26 | G23: Assumed | H23: siliconomics｜SIF_hbm_den_26 | I23: 同上
A24: den_27 | B24: DRAM 核心晶粒容量（組合平均）2027 | C24: Gb／顆 | D24: 24 | E24: 26 | F24: 28 | G24: Assumed | H24: siliconomics｜SIF_hbm_den_27 | I24: 同上
A25: den_28 | B25: DRAM 核心晶粒容量（組合平均）2028 | C25: Gb／顆 | D25: 24 | E25: 28 | F25: 32 | G25: Assumed | H25: siliconomics｜SIF_hbm_den_28 | I25: 同上
A26: den_29 | B26: DRAM 核心晶粒容量（組合平均）2029 | C26: Gb／顆 | D26: 26 | E26: 30 | F26: 32 | G26: Assumed | H26: siliconomics｜SIF_hbm_den_29 | I26: 同上
A27: den_30 | B27: DRAM 核心晶粒容量（組合平均）2030 | C27: Gb／顆 | D27: 28 | E27: 32 | F27: 32 | G27: Assumed | H27: siliconomics｜SIF_hbm_den_30 | I27: 同上
A28: stk_25 | B28: HBM 平均堆疊層數 2025 | C28: 層 | D28: 8 | E28: 10 | F28: 12 | G28: Assumed | H28: siliconomics｜SIF_hbm_stk_25 | I28: 層數愈高，每顆晶粒的鍵合精度要求與時間愈高（見 beta）
A29: stk_26 | B29: HBM 平均堆疊層數 2026 | C29: 層 | D29: 10 | E29: 12 | F29: 12 | G29: Assumed | H29: siliconomics｜SIF_hbm_stk_26 | I29: 同上
A30: stk_27 | B30: HBM 平均堆疊層數 2027 | C30: 層 | D30: 12 | E30: 12.5 | F30: 14 | G30: Assumed | H30: siliconomics｜SIF_hbm_stk_27 | I30: 同上
A31: stk_28 | B31: HBM 平均堆疊層數 2028 | C31: 層 | D31: 12 | E31: 14 | F31: 16 | G31: Assumed | H31: siliconomics｜SIF_hbm_stk_28 | I31: 同上
A32: stk_29 | B32: HBM 平均堆疊層數 2029 | C32: 層 | D32: 12 | E32: 15 | F32: 16 | G32: Assumed | H32: siliconomics｜SIF_hbm_stk_29 | I32: 同上
A33: stk_30 | B33: HBM 平均堆疊層數 2030 | C33: 層 | D33: 14 | E33: 16 | F33: 16 | G33: Assumed | H33: siliconomics｜SIF_hbm_stk_30 | I33: 同上
... A41: dlt | B41: 已裝機鍵合產能每年汰換／升級比例（新機需求＝產能增量＋汰換） | C41: %/年 | D41: 0.05 | E41: 0.1 | F41: 0.15 | G41: Assumed | H41: 無：公司不揭露裝機量與機齡；HBM3E→HBM4→HBM4E 換代需新機（TC BONDER 4、4.5） | I41: 與 Disco 模型的 dlt 同值（Assumed）
A42: C. 三家記憶體廠的 HBM 營收市占（讀 SK 海力士、三星、美光模型成品 In 頁；以營收市占代替產能增量占比，Analogy）
A43: ms_sk_25 | B43: SK 海力士 HBM 營收市占 2025 | C43: % | E43: 0.58 | G43: Interested-party | H43: skhynix/dist/20261030_SK海力士個股模型_v0.6.1.xlsx｜In!D21:F21 | I43: 各記憶體模型的 HBM 市占（賣方與公司說法）；本模型以 t＋1 年的市占（三家正規化）當 t 年鍵合產能增量的分配（Analogy：營收市占≈位元市占≈產能增量占比）
A44: ms_sk_26 | B44: SK 海力士 HBM 營收市占 2026 | C44: % | E44: 0.52 | G44: Interested-party | H44: skhynix/dist/20261030_SK海力士個股模型_v0.6.1.xlsx｜In!D22:F22 | I44: 同上
A45: ms_sk_27 | B45: SK 海力士 HBM 營收市占 2027 | C45: % | E45: 0.42 | G45: Interested-party | H45: skhynix/dist/20261030_SK海力士個股模型_v0.6.1.xlsx｜In!D23:F23 | I45: 同上
A46: ms_sk_28 | B46: SK 海力士 HBM 營收市占 2028 | C46: % | E46: 0.4 | G46: Interested-party | H46: skhynix/dist/20261030_SK海力士個股模型_v0.6.1.xlsx｜In!D24:F24 | I46: 同上
A47: ms_sk_29 | B47: SK 海力士 HBM 營收市占 2029 | C47: % | E47: 0.4 | G47: Interested-party | H47: skhynix/dist/20261030_SK海力士個股模型_v0.6.1.xlsx｜In!D42:F42 | I47: 同上
A48: ms_ss_25 | B48: 三星 HBM 營收市占 2025 | C48: % | E48: 0.17 | G48: Interested-party | H48: samsung/dist/20261030_三星電子個股模型_v0.4.xlsx｜In!D29:F29 | I48: 各記憶體模型的 HBM 市占（賣方與公司說法）；本模型以 t＋1 年的市占（三家正規化）當 t 年鍵合產能增量的分配（Analogy：營收市占≈位元市占≈產能增量占比）
A49: ms_ss_26 | B49: 三星 HBM 營收市占 2026 | C49: % | E49: 0.29 | G49: Interested-party | H49: samsung/dist/20261030_三星電子個股模型_v0.4.xlsx｜In!D30:F30 | I49: 同上
A50: ms_ss_27 | B50: 三星 HBM 營收市占 2027 | C50: % | E50: 0.38 | G50: Interested-party | H50: samsung/dist/20261030_三星電子個股模型_v0.4.xlsx｜In!D31:F31 | I50: 同上
A51: ms_ss_28 | B51: 三星 HBM 營收市占 2028 | C51: % | E51: 0.4 | G51: Interested-party | H51: samsung/dist/20261030_三星電子個股模型_v0.4.xlsx｜In!D32:F32 | I51: 同上
A52: ms_ss_29 | B52: 三星 HBM 營收市占 2029 | C52: % | E52: 0.4 | G52: Interested-party | H52: samsung/dist/20261030_三星電子個股模型_v0.4.xlsx｜In!D33:F33 | I52: 同上
A53: ms_mu_25 | B53: 美光 HBM 營收市占 2025 | C53: % | E53: 0.21 | G53: Interested-party | H53: micron/dist/20261030_美光個股模型_v0.4.3.xlsx｜In!D16:F16 | I53: 各記憶體模型的 HBM 市占（賣方與公司說法）；本模型以 t＋1 年的市占（三家正規化）當 t 年鍵合產能增量的分配（Analogy：營收市占≈位元市占≈產能增量占比）
A54: ms_mu_26 | B54: 美光 HBM 營收市占 2026 | C54: % | E54: 0.19 | G54: Interested-party | H54: micron/dist/20261030_美光個股模型_v0.4.3.xlsx｜In!D17:F17 | I54: 同上
... A57: ms_mu_29 | B57: 美光 HBM 營收市占 2029 | C57: % | E57: 0.2 | G57: Interested-party | H57: micron/dist/20261030_美光個股模型_v0.4.3.xlsx｜In!D37:F37 | I57: 同上
A58: D. 韓美在各記憶體廠的 TC 鍵合機份額（份額是本模型的關鍵，皆為 Assumed／Interested-party，給區間）
A59: hsk_25 | B59: 韓美占 SK 海力士 TC 鍵合機採購 2025 | C59: % | D59: 0.4 | E59: 0.5 | F59: 0.65 | G59: Interested-party | H59: TrendForce（2025-12-12，引 The Elec，匿名來源）：韓美 2024 年前為 SK 海力士 HBM 獨家供應商；ASMPT 2024 年底加入，HBM4 約 50 套中約半數為 ASMPT；韓華 Semitech 2025 年初加入 | I59: LS 證券（Interested-party，dealsite 2025-07-25）：2025 年韓美 TC 鍵合機營收中 SK 海力士占 40%、海外 60%
A60: hsk_A | B60: 韓美占 SK 海力士 TC 鍵合機採購（A；v0.2.1：2026–27 三情境共用 A 值，2028 起分情境） | C60: % | D60: 0.35 | E60: 0.45 | F60: 0.55 | G60: Assumed | H60: 韓美 2025-05（₩428 億）、2026-06（₩442 億，約 15 台）接 SK 海力士 HBM4 訂單；SK 海力士 2026-03 預計下約 100 台 HBM4 鍵合機，三家分配未公開（TrendForce 2025-12-12） | I60: A、B：ASMPT 約四成、韓華約一成（Assumed）
A61: hsk_B | B61: 韓美占 SK 海力士 TC 鍵合機採購（B；v0.2.1：2026–27 三情境共用 A 值，2028 起分情境） | C61: % | D61: 0.35 | E61: 0.45 | F61: 0.55 | G61: Assumed | H61: 韓美 2025-05（₩428 億）、2026-06（₩442 億，約 15 台）接 SK 海力士 HBM4 訂單；SK 海力士 2026-03 預計下約 100 台 HBM4 鍵合機，三家分配未公開（TrendForce 2025-12-12） | I61: A、B：ASMPT 約四成、韓華約一成（Assumed）
A62: hsk_C | B62: 韓美占 SK 海力士 TC 鍵合機採購（C；v0.2.1：2026–27 三情境共用 A 值，2028 起分情境） | C62: % | D62: 0.25 | E62: 0.35 | F62: 0.45 | G62: Assumed | H62: 韓美 2025-05（₩428 億）、2026-06（₩442 億，約 15 台）接 SK 海力士 HBM4 訂單；SK 海力士 2026-03 預計下約 100 台 HBM4 鍵合機，三家分配未公開（TrendForce 2025-12-12） | I62: C：韓華 Semitech 與 ASMPT 擴大份額（Assumed）
A63: hmu_25 | B63: 韓美占美光 TC 鍵合機採購 2025 | C63: % | D63: 0.7 | E63: 0.8 | F63: 0.9 | G63: Interested-party | H63: 美光 2025 年選韓美為「Top Supplier」（公司新聞稿 2026-02-09）；美光為 2024 年第二大客戶 ₩1,111 億（事業報告，newdaily 2025-04-02） | I63: TechInvestments（2026，引 CGSI）：美光以韓美為主，測試 ASMPT 與 BESI；BofA（dealsite 2026-07-22）：Q2 2026 主要來自美光加單
A64: hmu_A | B64: 韓美占美光 TC 鍵合機採購（A；v0.2.1：2026–27 三情境共用 A 值，2028 起分情境） | C64: % | D64: 0.65 | E64: 0.75 | F64: 0.85 | G64: Assumed | H64: 同上；美光擴大 HBM 後段產能（買下 AUO、力積電廠房；2026-07） | I64: —
A65: hmu_B | B65: 韓美占美光 TC 鍵合機採購（B；v0.2.1：2026–27 三情境共用 A 值，2028 起分情境） | C65: % | D65: 0.6 | E65: 0.7 | F65: 0.8 | G65: Assumed | H65: 同上；美光擴大 HBM 後段產能（買下 AUO、力積電廠房；2026-07） | I65: —
A66: hmu_C | B66: 韓美占美光 TC 鍵合機採購（C；v0.2.1：2026–27 三情境共用 A 值，2028 起分情境） | C66: % | D66: 0.45 | E66: 0.55 | F66: 0.65 | G66: Assumed | H66: 同上；美光擴大 HBM 後段產能（買下 AUO、力積電廠房；2026-07） | I66: C：ASMPT、BESI 進入美光（Assumed）
A67: hss | B67: 韓美占三星 TC 鍵合機採購（各年） | C67: % | D67: 0 | E67: 0 | F67: 0.1 | G67: Assumed | H67: 三星主要採用自家 SEMES（TechInvestments 2026，引 CGSI）；韓美被視為可能但份額有限的供應商 | I67: Sens 列 10%
A68: E. FY2025 構成（校準錨）與其他業務
A69: tcb_sh25 | B69: TC 鍵合機（含中國）占 FY2025 營收 | C69: % | D69: 0.5 | E69: 0.6 | F69: 0.7 | G69: Interested-party | H69: CGSI（TechInvestments 引用）：FY25F 中國出口 ₩589 億＝TC 鍵合機營收 17% → TC 鍵合機約 ₩3,460 億（Derived）÷ 營收 5,767 ≈ 60% | I69: 公司不揭露產品別營收；第二來源：未找到
A70: cn_sh25 | B70: 中國客戶占 FY2025 TC 鍵合機營收 | C70: % | D70: 0.1 | E70: 0.17 | F70: 0.25 | G70: Interested-party | H70: CGSI（TechInvestments 引用）：FY25F 17%、FY26F 38%、FY27F 40% | I70: 第二來源：未找到
A71: a25_hbm | B71: FY2025 對三大記憶體廠的 HBM TC 鍵合機營收（Derived） | C71: ₩億 | E71: =a25_rev*tcb_sh25*(1-cn_sh25) -> 2871.966 | G71: Derived | H71: 營收 × TC 鍵合機占比 ×（1 − 中國占比） | I71: 其餘（中國 TC 鍵合機、MSVP、EMI Shield、2.5D／FC 鍵合機、零件服務）歸「其他」
A72: g_o26 | B72: 其他業務 FY2026 成長 | C72: % | D72: 0 | E72: 0.15 | F72: 0.35 | G72: Assumed | H72: 無：CGSI 預估中國 TC 鍵合機 FY26 約 2.8 倍（Interested-party，不採作點估計）；MSVP 訂單增加（dealsite 2026-07-14，無數字） | I72: AI 前（2019–2022）公司總營收 1,204–3,732（Analogy：其他業務的量級）
A73: g_o_A | B73: 其他業務年成長（A；v0.2.1：FY2027 三情境共用 A 值，FY2028–29 分情境） | C73: % | D73: 0.07 | E73: 0.12 | F73: 0.17 | G73: Assumed | H73: 無：2.5D 封裝機（2026 推出三款）、HBF 用鍵合機、北美客戶 | I73: —
A74: g_o_B | B74: 其他業務年成長（B；v0.2.1：FY2027 三情境共用 A 值，FY2028–29 分情境） | C74: % | D74: 0.03 | E74: 0.08 | F74: 0.13 | G74: Assumed | H74: 無：2.5D 封裝機（2026 推出三款）、HBF 用鍵合機、北美客戶 | I74: —
A75: g_o_C | B75: 其他業務年成長（C；v0.2.1：FY2027 三情境共用 A 值，FY2028–29 分情境） | C75: % | D75: -0.1 | E75: -0.05 | F75: 0 | G75: Assumed | H75: 無：2.5D 封裝機（2026 推出三款）、HBF 用鍵合機、北美客戶 | I75: C：中國出口受管制（Assumed）
A76: F. FY2026 錨點（上半年實績＋下半年假設；第三季 2026-11 才公布）
A77: h2f | B77: FY2026 下半年營收 ÷（2 × 第二季營收） | C77: x | D77: 0.7 | E77: 0.9 | F77: 1.1 | G77: Assumed | H77: 第二季含美光超常加單（BofA，dealsite 2026-07-22）；SK 海力士 2026-03 預計約 100 台 HBM4 訂單（TrendForce） | I77: Interested-party 對照（不校準）：BofA 下半年約 ₩5,200 億＝1.04；共識全年 ₩7,280 億隱含 0.85
A78: m_h2 | B78: FY2026 下半年營業利益率 | C78: % | D78: 0.42 | E78: 0.48 | F78: 0.52 | G78: Assumed | H78: 第二季 51.9%（創高）；FY2025 43.6% | I78: 基準取兩者之間
A79: rev26 | B79: FY2026 營收錨點（Derived） | C79: ₩億 | E79: =q1_rev+q2_rev+h2f*2*q2_rev -> 7539.8 | G79: Derived | H79: 上半年實績 ＋ h2f × 2 × 第二季 | I79: —
A80: oi26 | B80: FY2026 營業利益錨點（Derived） | C80: ₩億 | E80: =q1_oi+q2_oi+h2f*2*q2_rev*m_h2 -> 3557.504 | G80: Derived | H80: 上半年實績 ＋ 下半年營收 × m_h2 | I80: —
A81: G. 毛利、營業費用、淨利、股數
A82: phi | B82: FY2025 營業費用中變動部分占比 | C82: % | D82: 0.3 | E82: 0.5 | F82: 0.7 | G82: Assumed | H82: 無：公司不揭露費用結構；FY2024 營業費用 589、FY2025 807，營收只增 3%（兩點推導不可用：費用增加非由營收驅動） | I82: 營業費用＝固定（1−phi）× FY2025 ＋ 變動 phi × FY2025 ÷ FY2025 營收 × 營收
A83: opex25 | B83: 營業費用 FY2025（毛利 − 營業利益） | C83: ₩億 | E83: =a25_gp-a25_oi -> 806.7 | G83: Derived | H83: Q 頁 | I83: —
A84: opex_fix | B84: 營業費用固定部分 | C84: ₩億 | E84: =(1-phi)*opex25 -> 403.35 | G84: Derived | H84: — | I84: —
A85: opex_var | B85: 營業費用變動部分占營收 | C85: % | E85: =phi*opex25/a25_rev -> 0.069941044 | G85: Derived | H85: — | I85: —
A86: gm_adj_C28 | B86: 情境 C：FY2028 毛利率額外調整（韓華、ASMPT 價格競爭） | C86: pt | D86: -0.06 | E86: -0.03 | F86: 0 | G86: Assumed | H86: 無：韓美 2025-04 起 TC 鍵合機漲價 25%（newdaily 2025-04-02）；競爭加劇時可能回吐 | I86: —
A87: gm_adj_C29 | B87: 情境 C：FY2029 毛利率額外調整 | C87: pt | D87: -0.08 | E87: -0.05 | F87: 0 | G87: Assumed | H87: 無 | I87: —
A88: nioi | B88: 淨利 ÷ 營業利益 | C88: x | D88: 0.72 | E88: =a25_ni/a25_oi -> 0.85126696 | F88: 0.95 | G88: Derived | H88: 基準＝FY2025 實績 0.851；低＝FY2024–25 平均 0.72（FY2024 有金融資產評價損失）；高＝近 12 月（2026-06）0.95（含 SpaceX 等投資評價益，一次性） | I88: valueline 近 12 月：淨利 2,220、營業利益 2,342
A89: shares | B89: 股數（FY2025 淨利 ÷ FY2025 EPS，加權平均） | C89: 百萬股 | E89: =a25_ni/a25_eps*100 -> 95.891025 | G89: Derived | H89: 2,140.0 億 ÷ 2,231.7 ≈ 95.9M | I89: 流通股：stockanalysis 94.85M（2026-10-02）、etfshopping 95.31M（2025）；庫藏股註銷使股數略降，本版不建模
A90: fx | B90: 匯率（只用於對帳的美元換算） | C90: ₩/US$ | D90: 1350 | E90: 1420 | F90: 1500 | G90: Assumed | H90: 無：本模型以韓元建模，匯率不進損益 | I90: —
A91: H. 估值、共識與對帳來源
A92: pk_A | B92: 情境 A：設備市場見頂年度（日曆年；循環位置規則用） | C92: 年 | E92: 2029 | G92: Derived | H92: markets/equipment/dist/20261023_半導體設備市場模型_v0.1.3.xlsx｜Mkt!C12 | I92: 設備股共用規則（tools/cycle_position.py）：FY(t) 早於見頂年＝中段、等於＝見頂、晚於＝谷底；本公司會計年度＝日曆年
A93: pk_B | B93: 情境 B：設備市場見頂年度（日曆年；循環位置規則用） | C93: 年 | E93: 2028 | G93: Derived | H93: markets/equipment/dist/20261023_半導體設備市場模型_v0.1.3.xlsx｜Mkt!C20 | I93: 同上
A94: pk_C | B94: 情境 C：設備市場見頂年度（日曆年；循環位置規則用） | C94: 年 | E94: 2027 | G94: Derived | H94: markets/equipment/dist/20261023_半導體設備市場模型_v0.1.3.xlsx｜Mkt!C28 | I94: 同上
A95: px | B95: 股價（etfshopping 2026-10-23 收盤） | C95: ₩ | E95: 188500 | G95: Verified | H95: etfshopping.com/stock/042700：2026-10-23 收盤 188,500 | I95: Daum 新聞頁股價欄 188,500（−1.41%）；valueline 10/23 16:55 顯示 189,500（可能含盤後），差 0.5%
A96: tp_wA | B96: 目標價情境權重：情境 A | C96: % | E96: 0.3 | G96: Assumed | H96: Andy 可改（AI 半導體 Project 共用設定 0.3／0.5／0.2） | I96: —
A97: tp_wB | B97: 目標價情境權重：情境 B | C97: % | E97: 0.5 | G97: Assumed | H97: Andy 可改（AI 半導體 Project 共用設定 0.3／0.5／0.2） | I97: —
A98: tp_wC | B98: 目標價情境權重：情境 C | C98: % | E98: 0.2 | G98: Assumed | H98: Andy 可改（AI 半導體 Project 共用設定 0.3／0.5／0.2） | I98: —
A99: cons_rev26 | B99: 共識營收 FY2026 | C99: ₩億 | E99: 7280 | G99: Interested-party | H99: etfshopping 證券商共識（2026-10-19 更新頁面）：₩7,280 億 | I99: 上上人證券 7,850（heraldcorp 2026-06-09）；BofA 上半年＋下半年 ≈ 8,221
A100: cons_oi26 | B100: 賣方營業利益 FY2026（上上人證券） | C100: ₩億 | E100: 3694 | G100: Interested-party | H100: 上上人證券（heraldcorp 2026-06-09） | I100: 共識營業利益：未找到
A101: cons_eps26 | B101: 第三方預估 EPS FY2026（alphadistill） | C101: ₩ | E101: 3400 | G101: Interested-party | H101: alphadistill 2026-10-12（自家估計，非券商共識） | I101: stockanalysis 遠期 P/E 67.90 @ ₩272,000（2026-10-02）隱含遠期 EPS 約 4,006；FnGuide／Naver 共識頁無法開啟：未找到
A102: cons_rev27 | B102: 第三方預估營收 FY2027（alphadistill） | C102: ₩億 | E102: 9900 | G102: Interested-party | H102: alphadistill 2026-10-12 | I102: 共識：未找到
A103: cons_eps27 | B103: 第三方預估 EPS FY2027（alphadistill） | C103: ₩ | E103: 4650 | G103: Interested-party | H103: alphadistill 2026-10-12 | I103: 共識：未找到
... A108: semi_pkg28 | B108: SEMI 組裝與封裝設備 2028 | C108: US$B | E108: 8.6 | G108: Interested-party | H108: markets/equipment/dist/20261023_半導體設備市場模型_v0.1.3.xlsx｜Mkt!C46:G46 | I108: SEMI 2026-07 年中預測（設備商協會，傾向樂觀）
A109: asp | B109: TC 鍵合機單價 | C109: ₩億／台 | D109: 25 | E109: 30 | F109: 40 | G109: Interested-party | H109: 韓經（heraldcorp 2026-06-09 引）：約 ₩30 億／台（₩442 億約 15 台） | I109: TrendForce（2025-12-12）：ASMPT 雙頭機約 ₩40 億／台；只用於台數換算顯示
A111: J. 目標價（DCF 與 Comparable 加權）與 FY2030–32 收斂法參數（v2 新增；黃底＝Assumed，Andy 可改）
A112: tp_r | B112: 折現率（股東權益要求報酬；美、台、日、韓同一值） | C112: % | E112: 0.1 | G112: Assumed | H112: Andy 可改（工作單 2026-10-25 預設 10%） | I112: —
A113: tp_g | B113: 長期成長率（永續成長；收斂法 FY2032 營收年增的基準） | C113: % | E113: 0.04 | G113: Assumed | H113: Andy 可改（工作單預設 4%） | I113: 情境 A＝tp_g＋2pt、B＝tp_g、C＝tp_g−2pt（PL 頁延伸區塊）
A114: tp_roe | B114: ROE（近三年平均，FY2023–FY2025） | C114: % | E114: =AVERAGE(0.5554,0.2743,0.3476) -> 0.39243333 | G114: Derived | H114: stockanalysis 比率頁（2026-10-25 讀取）：FY2023 55.54%、FY2024 27.43%、FY2025 34.76% | I114: 單一來源；近 12 月 33.24%（同站）
A115: tp_w_dcf | B115: 目標價中 DCF 的權重；其餘為 Comparable | C115: % | E115: 0.5 | G115: Assumed | H115: Andy 可改（2026-10-25 11:53：DCF／Comparable 各半） | I115: —
A116: nim10 | B116: 十年平均淨利率 | C116: % | E116: 未找到 | G116: Assumed | H116: 十年淨利資料未找到（韓文券商報告為 PDF 片段，未能逐年核對） | I116: 依工作單：找不到十年平均時用最後一年（FY2029）淨利率 × 0.8；PL 延伸區塊逐情境計算
...

Sheet Q
A1: Q — 實績（億韓元；EPS 為韓元）。會計年度＝日曆年。藍字＝輸入；黑字＝公式（Derived）。公司只公布初步營收與營業利益（DART 公平揭露）；淨利與 EPS 取自財務資料頁的近 12 月數字
A2: FY2026 第三季（2026-07～09）：建置日 2026-10-25 尚未公布（去年第三季於 2025-10-31 公布；mydailybyte 列 2026-11-06，stockanalysis 估 2026-11-13）。公布後更新本頁 J 欄與 In 頁 h2f、m_h2
A3: 項目 | B3: FY2024 | C3: 25Q1 | D3: 25Q2 | E3: 25Q3 | F3: 25Q4 | G3: FY2025 | H3: 26Q1 | I3: 26Q2 | J3: 26Q3（未公布） | K3: 標記 | L3: 來源1 | M3: 來源2／說明
A4: 營收 | B4: 5589 | C4: =G4-D4-E4-F4 -> 1475 | D4: 1800 | E4: 1662 | F4: 830 | G4: 5767 | H4: 509 | I4: 2511 | J4: 未公布 | K4: Verified（25Q1 Derived） | L4: 公司初步實績（DART）：FY2025 5,767（亞洲經濟 2026-02-09）；25Q2 1,800（dealsite 2025-07-25）；26Q1 509（−65.5%）、26Q2 2,511（+39.5%；ddaily 2026-07-14） | M4: etfshopping 各季（DART 初步）：25Q3 1,662、25Q4 830、26Q2 2,512；butler.works：FY2024 5,589、FY2025 5,767；25Q1＝全年 − 其他三季（＝上半年 3,274 − 1,800）
A5: 毛利 | B5: 3143 | G5: 3320.6 | K5: Verified | L5: valueline（DART 轉載）FY2025：營收 5,766.8、銷貨成本 2,446.1、毛利 3,320.6 | M5: stockanalysis：FY2025 毛利 3,319.4、FY2024 3,143.0（季度毛利未找到）
A6: 營業利益 | B6: 2554 | C6: =G6-D6-E6-F6 -> 696.9 | D6: 863 | E6: 678 | F6: 276 | G6: 2513.9 | H6: 85 | I6: 1303 | J6: 未公布 | K6: Verified（25Q1 Derived） | L6: 公司初步實績：FY2025 營益率 43.6%；26Q1 85（−87.9%）、26Q2 1,303（+51.0%，營益率 51.9%） | M6: valueline FY2025 2,513.9；stockanalysis 2,511.8；etfshopping 各季；25Q1＝上半年 1,559 − 863
A7: 營業利益率 | B7: =B6/B4 -> 0.45696905 | C7: =C6/C4 -> 0.47247458 | D7: =D6/D4 -> 0.47944444 | E7: =E6/E4 -> 0.40794224 | F7: =F6/F4 -> 0.33253012 | G7: =G6/G4 -> 0.43591122 | H7: =H6/H4 -> 0.16699411 | I7: =I6/I4 -> 0.51891677 | K7: Derived | L7: — | M7: 公司：FY2025 43.6%、26Q2 51.9%
A8: 營業費用（毛利 − 營業利益） | B8: =B5-B6 -> 589 | G8: =G5-G6 -> 806.7 | K8: Derived | L8: — | M8: valueline FY2025 銷管費 806.7
A9: 淨利（歸屬母公司） | B9: 1526 | G9: 2140 | H9: 190 | K9: Verified | L9: valueline（近 12 月表）FY2025 2,140.0；26Q1 190（etfshopping） | M9: butler.works：FY2024 1,526、FY2025 2,140；stockanalysis FY2025 2,140.1；25 各季、26Q2 單季未找到（近 12 月 2026-06 為 2,220.3）
A10: EPS（韓元） | B10: 1584 | G10: 2231.7 | K10: Verified（來源不一致） | L10: valueline FY2025 2,231.7（DART 轉載） | M10: stockanalysis 2,248、etfshopping 2,256（差 0.7–1.1%，口徑未解：基本／稀釋或加權股數）；FY2024 stockanalysis 1,584、etfshopping 1,589
A11: 檢查：四季合計 − 全年（營收、營業利益；B、C 欄） | B11: =SUM(C4:F4)-G4 -> 0 | C11: =SUM(C6:F6)-G6 -> 0 | K11: — | L11: — | M11: —
A13: 客戶別營收（事業報告）
A14: 客戶 | B14: FY2024 | C14: 占營收 | G14: FY2025 | K14: 標記 | L14: 來源1 | M14: 來源2／說明
A15: SK 海力士 | B15: 2996 | C15: =B15/B4 -> 0.53605296 | G15: LS 證券估：TC 鍵合機營收的 40%（Interested-party） | K15: Verified | L15: 公司 2024 事業報告（newdaily 2025-04-02 報導）
A16: 美光 | B16: 1111 | C16: =B16/B4 -> 0.19878332 | G16: 未找到 | K16: Verified | L16: 公司 2024 事業報告（newdaily 2025-04-02 報導）
A17: 其他（中國、OSAT 等） | B17: =B4-B15-B16 -> 1482 | C17: =B17/B4 -> 0.26516371 | G17: CGSI 估中國 ₩589 億（Interested-party） | K17: Derived | L17: 營收 − 上兩列
A19: 檢查：分部合計 − 合併營收 | B19: =ROUND(B15+B16+B17-B4,3) -> 0
A20: 分部原則第 3 條（2026-10-28 追加）：客戶別營收（FY2024 事業報告）；分部宣告見 segments.json

Sheet Units
A1: Units — HBM 位元 → 核心晶粒 → TC 鍵合產能需求 → 新機需求 → 韓美可得需求（日曆年；三情境，引用 PL 區塊）
A3: 項目 | B3: 單位 | C3: 2025 | D3: 2026 | E3: 2027 | F3: 2028 | G3: 2029 | H3: 2030 | I3: 說明
A4: 情境 A
A5: HBM 出貨位元 | B5: EB | C5: =PL!C43 -> 2.2251147 | D5: =PL!D43 -> 3.782695 | E5: =PL!E43 -> 5.8631772 | F5: =PL!F43 -> 8.501607 | G5: =PL!G43 -> 11.477169 | H5: =PL!H43 -> 12.624886
A6: 核心晶粒數 | B6: 百萬顆 | C6: =PL!C45 -> 741.7049 | D6: =PL!D45 -> 1260.8983 | E6: =PL!E45 -> 1804.0545 | F6: =PL!F45 -> 2429.0306 | G6: =PL!G45 -> 3060.5785 | H6: =PL!H45 -> 3156.2216
A7: TC 鍵合產能需求 | B7: 百萬顆當量 | C7: =PL!C49 -> 741.7049 | D7: =PL!D49 -> 1323.9433 | E7: =PL!E49 -> 1916.8079 | F7: =PL!F49 -> 2271.1436 | G7: =PL!G49 -> 2410.2056 | H7: =PL!H49 -> 2177.7929
A8: 新機需求 | B8: 百萬顆當量 | C8: =PL!C50 -> 656.40884 | D8: =PL!D50 -> 725.25902 | E8: =PL!E50 -> 813.2098 | F8: =PL!F50 -> 366.17636 | G8: =PL!G50 -> 241.02056
A9: 韓美加權份額 | B9: % | C9: =PL!C54 -> 0.412 | D9: =PL!D54 -> 0.339 | E9: =PL!E54 -> 0.33 | F9: =PL!F54 -> 0.33 | G9: =PL!G54 -> 0.33
A10: 韓美可得新機需求 | B10: 百萬顆當量 | C10: =PL!C55 -> 270.44044 | D10: =PL!D55 -> 245.86281 | E10: =PL!E55 -> 268.35923 | F10: =PL!F55 -> 120.8382 | G10: =PL!G55 -> 79.536784
A11: 三大廠 HBM TC 鍵合機市場 | B11: ₩億 | C11: =PL!C69 -> 9004.3989 | D11: =PL!D69 -> 9948.8629 | E11: =PL!E69 -> 11155.343 | F11: =PL!F69 -> 5023.086 | G11: =PL!G69 -> 3306.2402
A13: 情境 B
A14: HBM 出貨位元 | B14: EB | C14: =PL!C76 -> 2.2251147 | D14: =PL!D76 -> 3.782695 | E14: =PL!E76 -> 5.8631772 | F14: =PL!F76 -> 8.22296 | G14: =PL!G76 -> 11.357964 | H14: =PL!H76 -> 12.49376
A15: 核心晶粒數 | B15: 百萬顆 | C15: =PL!C78 -> 741.7049 | D15: =PL!D78 -> 1260.8983 | E15: =PL!E78 -> 1804.0545 | F15: =PL!F78 -> 2349.4171 | G15: =PL!G78 -> 3028.7903 | H15: =PL!H78 -> 3123.44
A16: TC 鍵合產能需求 | B16: 百萬顆當量 | C16: =PL!C82 -> 741.7049 | D16: =PL!D82 -> 1323.9433 | E16: =PL!E82 -> 1916.8079 | F16: =PL!F82 -> 2455.1409 | G16: =PL!G82 -> 2896.2807 | H16: =PL!H82 -> 2693.967
A17: 新機需求 | B17: 百萬顆當量 | C17: =PL!C83 -> 656.40884 | D17: =PL!D83 -> 725.25902 | E17: =PL!E83 -> 813.2098 | F17: =PL!F83 -> 686.65387 | G17: =PL!G83 -> 289.62807
A18: 韓美加權份額 | B18: % | C18: =PL!C87 -> 0.412 | D18: =PL!D87 -> 0.339 | E18: =PL!E87 -> 0.33 | F18: =PL!F87 -> 0.32 | G18: =PL!G87 -> 0.32
A19: 韓美可得新機需求 | B19: 百萬顆當量 | C19: =PL!C88 -> 270.44044 | D19: =PL!D88 -> 245.86281 | E19: =PL!E88 -> 268.35923 | F19: =PL!F88 -> 219.72924 | G19: =PL!G88 -> 92.680982
A20: 三大廠 HBM TC 鍵合機市場 | B20: ₩億 | C20: =PL!C102 -> 9004.3989 | D20: =PL!D102 -> 9948.8629 | E20: =PL!E102 -> 11155.343 | F20: =PL!F102 -> 9419.2903 | G20: =PL!G102 -> 3973.0219
A22: 情境 C
A23: HBM 出貨位元 | B23: EB | C23: =PL!C109 -> 2.2251147 | D23: =PL!D109 -> 3.782695 | E23: =PL!E109 -> 5.8631772 | F23: =PL!F109 -> 6.16722 | G23: =PL!G109 -> 8.017386 | H23: =PL!H109 -> 8.8191246
A24: 核心晶粒數 | B24: 百萬顆 | C24: =PL!C111 -> 741.7049 | D24: =PL!D111 -> 1260.8983 | E24: =PL!E111 -> 1804.0545 | F24: =PL!F111 -> 1762.0629 | G24: =PL!G111 -> 2137.9696 | H24: =PL!H111 -> 2204.7811
A25: TC 鍵合產能需求 | B25: 百萬顆當量 | C25: =PL!C115 -> 741.7049 | D25: =PL!D115 -> 1323.9433 | E25: =PL!E115 -> 1916.8079 | F25: =PL!F115 -> 1938.2691 | G25: =PL!G115 -> 2284.955 | H25: =PL!H115 -> 2281.9485
A26: 新機需求 | B26: 百萬顆當量 | C26: =PL!C116 -> 656.40884 | D26: =PL!D116 -> 725.25902 | E26: =PL!E116 -> 813.2098 | F26: =PL!F116 -> 540.51278 | G26: =PL!G116 -> 228.4955
A27: 韓美加權份額 | B27: % | C27: =PL!C120 -> 0.412 | D27: =PL!D120 -> 0.339 | E27: =PL!E120 -> 0.33 | F27: =PL!F120 -> 0.25 | G27: =PL!G120 -> 0.25
A28: 韓美可得新機需求 | B28: 百萬顆當量 | C28: =PL!C121 -> 270.44044 | D28: =PL!D121 -> 245.86281 | E28: =PL!E121 -> 268.35923 | F28: =PL!F121 -> 135.1282 | G28: =PL!G121 -> 57.123875
A29: 三大廠 HBM TC 鍵合機市場 | B29: ₩億 | C29: =PL!C135 -> 9004.3989 | D29: =PL!D135 -> 9948.8629 | E29: =PL!E135 -> 11155.343 | F29: =PL!F135 -> 7414.5752 | G29: =PL!G135 -> 3134.4256
A31: 台數換算（顯示用；單價為 Interested-party，只影響台數，不影響營收）
A32: 情境 A：三大廠 TC 鍵合機台數＝市場 ÷ 單價 | B32: 台 | C32: =C11/asp -> 300.14663 | D32: =D11/asp -> 331.62876 | E32: =E11/asp -> 371.84475 | F32: =F11/asp -> 167.4362 | G32: =G11/asp -> 110.20801
A33: 情境 B：三大廠 TC 鍵合機台數＝市場 ÷ 單價 | B33: 台 | C33: =C20/asp -> 300.14663 | D33: =D20/asp -> 331.62876 | E33: =E20/asp -> 371.84475 | F33: =F20/asp -> 313.97634 | G33: =G20/asp -> 132.43406
A34: 情境 C：三大廠 TC 鍵合機台數＝市場 ÷ 單價 | B34: 台 | C34: =C29/asp -> 300.14663 | D34: =D29/asp -> 331.62876 | E34: =E29/asp -> 371.84475 | F34: =F29/asp -> 247.15251 | G34: =G29/asp -> 104.48085
I35: 對照：SK 海力士 2026-03 預計下約 100 台 HBM4 鍵合機（TrendForce 引 The Elec）

Sheet PL
A1: PL — 韓美半導體損益（₩億；FY2025 實績，FY2026 錨點＝上半年實績＋下半年假設，FY2027–FY2029 為模型）。三情境各一個完整推導區塊（見下方），本頁頂端為摘要
A3: 情境／項目 | B3: 單位 | C3: FY2025A | D3: FY2026（錨點） | E3: FY2027 | F3: FY2028 | G3: FY2029 | H3: 說明
A4: 情境 A
A5: 營收 | B5: ₩億 | C5: =C60 -> 5767 | D5: =D60 -> 7539.8 | E5: =E60 -> 7410.0668 | F5: =F60 -> 5833.8786 | G5: =G60 -> 5768.4707 | H5: FY2026 為錨點（上半年實績＋下半年 h2f、m_h2），三情境相同；情境差異從 FY2027 起
A6: HBM TC 鍵合機 | B6: ₩億 | C6: =C58 -> 2871.966 | D6: =D58 -> 4210.5109 | E6: =E58 -> 3681.263 | F6: =F58 -> 1657.6184 | G6: =G58 -> 1091.0593
A7: 其他業務 | B7: ₩億 | C7: =C57 -> 2895.034 | D7: =D57 -> 3329.2891 | E7: =E57 -> 3728.8038 | F7: =F57 -> 4176.2602 | G7: =G57 -> 4677.4115
A8: 毛利率 | B8: % | C8: =C63 -> 0.57579331 | D8: =D63 -> 0.59526718 | E8: =E63 -> 0.59526718 | F8: =F63 -> 0.59526718 | G8: =G63 -> 0.59526718
A9: 營業利益 | B9: ₩億 | C9: =C65 -> 2513.9 | D9: =D65 -> 3557.504 | E9: =E65 -> 3489.3518 | F9: =F65 -> 2661.3389 | G9: =G65 -> 2626.9784
A10: 營業利益率 | B10: % | C10: =C66 -> 0.43591122 | D10: =D66 -> 0.47183002 | E10: =E66 -> 0.47089343 | F10: =F66 -> 0.45618688 | G10: =G66 -> 0.45540292
A11: 淨利 | B11: ₩億 | C11: =C67 -> 2140 | D11: =D67 -> 3028.3856 | E11: =E67 -> 2970.3699 | F11: =F67 -> 2265.5099 | G11: =G67 -> 2236.2599
A12: EPS | B12: ₩ | C12: =C68 -> 2231.7 | D12: =D68 -> 3158.1533 | E12: =E68 -> 3097.6516 | F12: =F68 -> 2362.588 | G12: =G68 -> 2332.0847
A14: 情境 B
A15: 營收 | B15: ₩億 | C15: =C93 -> 5767 | D15: =D93 -> 7539.8 | E15: =E93 -> 7410.0668 | F15: =F93 -> 7041.281 | G15: =G93 -> 5620.6437
A16: HBM TC 鍵合機 | B16: ₩億 | C16: =C91 -> 2871.966 | D16: =D91 -> 4210.5109 | E16: =E91 -> 3681.263 | F16: =F91 -> 3014.1729 | G16: =G91 -> 1271.367
A17: 其他業務 | B17: ₩億 | C17: =C90 -> 2895.034 | D17: =D90 -> 3329.2891 | E17: =E90 -> 3728.8038 | F17: =F90 -> 4027.1081 | G17: =G90 -> 4349.2767
A18: 毛利率 | B18: % | C18: =C96 -> 0.57579331 | D18: =D96 -> 0.59526718 | E18: =E96 -> 0.59526718 | F18: =F96 -> 0.59526718 | G18: =G96 -> 0.59526718
A19: 營業利益 | B19: ₩億 | C19: =C98 -> 2513.9 | D19: =D98 -> 3557.504 | E19: =E98 -> 3489.3518 | F19: =F98 -> 3295.6189 | G19: =G98 -> 2549.3211
A20: 營業利益率 | B20: % | C20: =C99 -> 0.43591122 | D20: =D99 -> 0.47183002 | E20: =E99 -> 0.47089343 | F20: =F99 -> 0.46804253 | G20: =G99 -> 0.45356389
A21: 淨利 | B21: ₩億 | C21: =C100 -> 2140 | D21: =D100 -> 3028.3856 | E21: =E100 -> 2970.3699 | F21: =F100 -> 2805.4515 | G21: =G100 -> 2170.1528
A22: EPS | B22: ₩ | C22: =C101 -> 2231.7 | D22: =D101 -> 3158.1533 | E22: =E101 -> 3097.6516 | F22: =F101 -> 2925.6664 | G22: =G101 -> 2263.1448
A24: 情境 C
A25: 營收 | B25: ₩億 | C25: =C126 -> 5767 | D25: =D126 -> 7539.8 | E25: =E126 -> 7410.0668 | F25: =F126 -> 5396.0074 | G25: =G126 -> 4148.8518
A26: HBM TC 鍵合機 | B26: ₩億 | C26: =C124 -> 2871.966 | D26: =D124 -> 4210.5109 | E26: =E124 -> 3681.263 | F26: =F124 -> 1853.6438 | G26: =G124 -> 783.60639
A27: 其他業務 | B27: ₩億 | C27: =C123 -> 2895.034 | D27: =D123 -> 3329.2891 | E27: =E123 -> 3728.8038 | F27: =F123 -> 3542.3636 | G27: =G123 -> 3365.2454
A28: 毛利率 | B28: % | C28: =C129 -> 0.57579331 | D28: =D129 -> 0.59526718 | E28: =E129 -> 0.59526718 | F28: =F129 -> 0.56526718 | G28: =G129 -> 0.54526718
A29: 營業利益 | B29: ₩億 | C29: =C131 -> 2513.9 | D29: =D131 -> 3557.504 | E29: =E131 -> 3489.3518 | F29: =F131 -> 2269.4335 | G29: =G131 -> 1568.7077
A30: 營業利益率 | B30: % | C30: =C132 -> 0.43591122 | D30: =D132 -> 0.47183002 | E30: =E132 -> 0.47089343 | F30: =F132 -> 0.42057642 | G30: =G132 -> 0.37810647
A31: 淨利 | B31: ₩億 | C31: =C133 -> 2140 | D31: =D133 -> 3028.3856 | E31: =E133 -> 2970.3699 | F31: =F133 -> 1931.8937 | G31: =G133 -> 1335.389
A32: EPS | B32: ₩ | C32: =C134 -> 2231.7 | D32: =D134 -> 3158.1533 | E32: =E134 -> 3097.6516 | F32: =F134 -> 2014.6763 | G32: =G134 -> 1392.6111
A34: 核對：FY2026 三情境相同（營收、EPS 差額合計，應為 0） | C34: =ABS(D5-D15)+ABS(D5-D25)+ABS(D12-D32) -> 0
A40: 情境 A：基準顆數；混合鍵合導入快（CY2028 起 Disco 高值）
A41: 項目 | B41: 單位 | C41: 2025 | D41: 2026 | E41: 2027 | F41: 2028 | G41: 2029 | H41: 2030 | I41: 說明
A42: A. 日曆年鍵合產能需求（本公司會計年度＝日曆年）
A43: HBM 出貨位元 | B43: EB | C43: =hsA_25 -> 2.2251147 | D43: =hsA_26 -> 3.782695 | E43: =hsA_27 -> 5.8631772 | F43: =hsA_28 -> 8.501607 | G43: =hsA_29 -> 11.477169 | H43: =G43*(1+g_tail) -> 12.624886 | I43: markets/memory；2030＝2029 ×（1＋g_tail）
A44: DRAM 晶粒容量 | B44: Gb | C44: =den_25 -> 24 | D44: =den_26 -> 24 | E44: =den_27 -> 26 | F44: =den_28 -> 28 | G44: =den_29 -> 30 | H44: =den_30 -> 32
A45: 核心晶粒數＝位元 × 8000 ÷ 容量 | B45: 百萬顆 | C45: =C43*8000/C44 -> 741.7049 | D45: =D43*8000/D44 -> 1260.8983 | E45: =E43*8000/E44 -> 1804.0545 | F45: =F43*8000/F44 -> 2429.0306 | G45: =G43*8000/G44 -> 3060.5785 | H45: =H43*8000/H44 -> 3156.2216 | I45: 1 EB＝8×10⁹ Gb；每顆核心晶粒鍵合一次
A46: 平均堆疊層數 | B46: 層 | C46: =stk_25 -> 10 | D46: =stk_26 -> 12 | E46: =stk_27 -> 12.5 | F46: =stk_28 -> 14 | G46: =stk_29 -> 15 | H46: =stk_30 -> 16
A47: 層數加權（每顆晶粒鍵合時間） | B47: x | C47: =1+beta*(C46-$C46)/4 -> 1 | D47: =1+beta*(D46-$C46)/4 -> 1.05 | E47: =1+beta*(E46-$C46)/4 -> 1.0625 | F47: =1+beta*(F46-$C46)/4 -> 1.1 | G47: =1+beta*(G46-$C46)/4 -> 1.125 | H47: =1+beta*(H46-$C46)/4 -> 1.15
A48: 混合鍵合占比 | B48: % | C48: =hbp_25 -> 0 | D48: =hbp_26 -> 0 | E48: =hbp_27 -> 0 | F48: =hbp_28_A -> 0.15 | G48: =hbp_29_A -> 0.3 | H48: =hbp_30_A -> 0.4 | I48: 情境 A：CY2028 起 Disco 模型高值（導入快）
A49: TC 鍵合產能需求（晶粒 × 層數加權 ×（1 − 混合鍵合）） | B49: 百萬顆當量 | C49: =C45*C47*(1-C48) -> 741.7049 | D49: =D45*D47*(1-D48) -> 1323.9433 | E49: =E45*E47*(1-E48) -> 1916.8079 | F49: =F45*F47*(1-F48) -> 2271.1436 | G49: =G45*G47*(1-G48) -> 2410.2056 | H49: =H45*H47*(1-H48) -> 2177.7929
A50: 新機需求＝MAX(0, 下一年產能 − 本年)＋汰換 × 本年（CY2027 的下一年產能用三情境共同前提） | B50: 百萬顆當量 | C50: =MAX(0,D49-C49)+dlt*C49 -> 656.40884 | D50: =MAX(0,E49-D49)+dlt*D49 -> 725.25902 | E50: =MAX(0,hsA_28*8000/F44*F47*(1-hbp_28)-E49)+dlt*E49 -> 813.2098 | F50: =MAX(0,G49-F49)+dlt*F49 -> 366.17636 | G50: =MAX(0,H49-G49)+dlt*G49 -> 241.02056 | I50: 鍵合機在產能需要前一年購入；v0.2.1：CY2027 購機的 CY2028 產能＝情境 A 的 HBM 位元（hsA_28）× 混合鍵合基準，三情境相同（與 markets/equipment 2027 三情境相同、記憶體供給三情境相同一致）；CY2028 起照讀本情境
A51: SK 海力士 占產能增量（t＋1 年 HBM 市占，三家正規化） | B51: % | C51: =ms_sk_26/(ms_sk_26+ms_ss_26+ms_mu_26) -> 0.52 | D51: =ms_sk_27/(ms_sk_27+ms_ss_27+ms_mu_27) -> 0.42 | E51: =ms_sk_28/(ms_sk_28+ms_ss_28+ms_mu_28) -> 0.4 | F51: =ms_sk_29/(ms_sk_29+ms_ss_29+ms_mu_29) -> 0.4 | G51: =ms_sk_29/(ms_sk_29+ms_ss_29+ms_mu_29) -> 0.4
A52: 三星 占產能增量（t＋1 年 HBM 市占，三家正規化） | B52: % | C52: =ms_ss_26/(ms_sk_26+ms_ss_26+ms_mu_26) -> 0.29 | D52: =ms_ss_27/(ms_sk_27+ms_ss_27+ms_mu_27) -> 0.38 | E52: =ms_ss_28/(ms_sk_28+ms_ss_28+ms_mu_28) -> 0.4 | F52: =ms_ss_29/(ms_sk_29+ms_ss_29+ms_mu_29) -> 0.4 | G52: =ms_ss_29/(ms_sk_29+ms_ss_29+ms_mu_29) -> 0.4
A53: 美光 占產能增量（t＋1 年 HBM 市占，三家正規化） | B53: % | C53: =ms_mu_26/(ms_sk_26+ms_ss_26+ms_mu_26) -> 0.19 | D53: =ms_mu_27/(ms_sk_27+ms_ss_27+ms_mu_27) -> 0.2 | E53: =ms_mu_28/(ms_sk_28+ms_ss_28+ms_mu_28) -> 0.2 | F53: =ms_mu_29/(ms_sk_29+ms_ss_29+ms_mu_29) -> 0.2 | G53: =ms_mu_29/(ms_sk_29+ms_ss_29+ms_mu_29) -> 0.2
A54: 韓美加權份額＝Σ 占比 × 韓美在該廠份額 | B54: % | C54: =C51*hsk_25+C52*hss+C53*hmu_25 -> 0.412 | D54: =D51*hsk_A+D52*hss+D53*hmu_A -> 0.339 | E54: =E51*hsk_A+E52*hss+E53*hmu_A -> 0.33 | F54: =F51*hsk_A+F52*hss+F53*hmu_A -> 0.33 | G54: =G51*hsk_A+G52*hss+G53*hmu_A -> 0.33
A55: 韓美可得新機需求＝新機需求 × 加權份額 | B55: 百萬顆當量 | C55: =C50*C54 -> 270.44044 | D55: =D50*D54 -> 245.86281 | E55: =E50*E54 -> 268.35923 | F55: =F50*F54 -> 120.8382 | G55: =G50*G54 -> 79.536784
A56: B. 損益（會計年度；FY2026＝錨點）
A57: 其他業務營收（中國 TC 鍵合機、MSVP、EMI、2.5D 等） | B57: ₩億 | C57: =a25_rev-a25_hbm -> 2895.034 | D57: =C57*(1+g_o26) -> 3329.2891 | E57: =D57*(1+g_o_A) -> 3728.8038 | F57: =E57*(1+g_o_A) -> 4176.2602 | G57: =F57*(1+g_o_A) -> 4677.4115 | I57: v0.2.1：FY2027 三情境共用 g_o_A，FY2028 起讀 g_o_{情境}
A58: HBM TC 鍵合機營收（三大記憶體廠） | B58: ₩億 | C58: =a25_hbm -> 2871.966 | D58: =rev26-D57 -> 4210.5109 | E58: =$C59*E55 -> 3681.263 | F58: =$C59*F55 -> 1657.6184 | G58: =$C59*G55 -> 1091.0593 | I58: FY2026＝錨點營收 − 其他；FY2027 起＝k × 可得新機需求
A59: 校準係數 k＝(FY2025＋FY2026 HBM 營收) ÷ (兩年可得新機需求) | B59: ₩億／百萬顆 | C59: =(C58+D58)/(C55+D55) -> 13.717669 | I59: 兩年平均，平滑訂單的季節與交期波動；不使用共識
A60: 營收 | B60: ₩億 | C60: =a25_rev -> 5767 | D60: =D57+D58 -> 7539.8 | E60: =E57+E58 -> 7410.0668 | F60: =F57+F58 -> 5833.8786 | G60: =G57+G58 -> 5768.4707
A61: HBM TC 鍵合機占營收 | B61: % | C61: =C58/C60 -> 0.498 | D61: =D58/D60 -> 0.55843801 | E61: =E58/E60 -> 0.49679215 | F61: =F58/F60 -> 0.28413659 | G61: =G58/G60 -> 0.18914185
A62: 營業費用 | B62: ₩億 | C62: =opex25 -> 806.7 | D62: =opex_fix+opex_var*D60 -> 930.69148 | E62: =opex_fix+opex_var*E60 -> 921.61781 | F62: =opex_fix+opex_var*F60 -> 811.37756 | G62: =opex_fix+opex_var*G60 -> 806.80286 | I62: 固定＋變動 × 營收
A63: 毛利率 | B63: % | C63: =a25_gp/a25_rev -> 0.57579331 | D63: =(oi26+D62)/D60 -> 0.59526718 | E63: =$D63+0 -> 0.59526718 | F63: =$D63+0 -> 0.59526718 | G63: =$D63+0 -> 0.59526718 | I63: FY2026＝錨點營業利益反推（Derived）；FY2027 起沿用（情境 C 另扣價格競爭）
A64: 毛利 | B64: ₩億 | C64: =C60*C63 -> 3320.6 | D64: =D60*D63 -> 4488.1955 | E64: =E60*E63 -> 4410.9696 | F64: =F60*F63 -> 3472.7165 | G64: =G60*G63 -> 3433.7813
A65: 營業利益 | B65: ₩億 | C65: =a25_oi -> 2513.9 | D65: =oi26 -> 3557.504 | E65: =E64-E62 -> 3489.3518 | F65: =F64-F62 -> 2661.3389 | G65: =G64-G62 -> 2626.9784
A66: 營業利益率 | B66: % | C66: =C65/C60 -> 0.43591122 | D66: =D65/D60 -> 0.47183002 | E66: =E65/E60 -> 0.47089343 | F66: =F65/F60 -> 0.45618688 | G66: =G65/G60 -> 0.45540292
A67: 淨利 | B67: ₩億 | C67: =a25_ni -> 2140 | D67: =D65*nioi -> 3028.3856 | E67: =E65*nioi -> 2970.3699 | F67: =F65*nioi -> 2265.5099 | G67: =G65*nioi -> 2236.2599
A68: EPS | B68: ₩ | C68: =a25_eps -> 2231.7 | D68: =D67*100/shares -> 3158.1533 | E68: =E67*100/shares -> 3097.6516 | F68: =F67*100/shares -> 2362.588 | G68: =G67*100/shares -> 2332.0847
A69: 三大廠 HBM TC 鍵合機市場（全部供應商）＝k × 新機需求 | B69: ₩億 | C69: =$C59*C50 -> 9004.3989 | D69: =$C59*D50 -> 9948.8629 | E69: =$C59*E50 -> 11155.343 | F69: =$C59*F50 -> 5023.086 | G69: =$C59*G50 -> 3306.2402 | I69: 對帳用
A70: 同上（美元） | B70: US$M | C70: =C69/fx*100 -> 634.1126 | D70: =D69/fx*100 -> 700.62415 | E70: =E69/fx*100 -> 785.5875 | F70: =F69/fx*100 -> 353.73845 | G70: =G69/fx*100 -> 232.83381
A73: 情境 B：2028 顆數 ×0.8、2029 ×0.85；混合鍵合取 Disco 基準
A74: 項目 | B74: 單位 | C74: 2025 | D74: 2026 | E74: 2027 | F74: 2028 | G74: 2029 | H74: 2030 | I74: 說明
A75: A. 日曆年鍵合產能需求（本公司會計年度＝日曆年）
A76: HBM 出貨位元 | B76: EB | C76: =hsB_25 -> 2.2251147 | D76: =hsB_26 -> 3.782695 | E76: =hsB_27 -> 5.8631772 | F76: =hsB_28 -> 8.22296 | G76: =hsB_29 -> 11.357964 | H76: =G76*(1+g_tail) -> 12.49376 | I76: markets/memory；2030＝2029 ×（1＋g_tail）
A77: DRAM 晶粒容量 | B77: Gb | C77: =den_25 -> 24 | D77: =den_26 -> 24 | E77: =den_27 -> 26 | F77: =den_28 -> 28 | G77: =den_29 -> 30 | H77: =den_30 -> 32
A78: 核心晶粒數＝位元 × 8000 ÷ 容量 | B78: 百萬顆 | C78: =C76*8000/C77 -> 741.7049 | D78: =D76*8000/D77 -> 1260.8983 | E78: =E76*8000/E77 -> 1804.0545 | F78: =F76*8000/F77 -> 2349.4171 | G78: =G76*8000/G77 -> 3028.7903 | H78: =H76*8000/H77 -> 3123.44 | I78: 1 EB＝8×10⁹ Gb；每顆核心晶粒鍵合一次
A79: 平均堆疊層數 | B79: 層 | C79: =stk_25 -> 10 | D79: =stk_26 -> 12 | E79: =stk_27 -> 12.5 | F79: =stk_28 -> 14 | G79: =stk_29 -> 15 | H79: =stk_30 -> 16
A80: 層數加權（每顆晶粒鍵合時間） | B80: x | C80: =1+beta*(C79-$C79)/4 -> 1 | D80: =1+beta*(D79-$C79)/4 -> 1.05 | E80: =1+beta*(E79-$C79)/4 -> 1.0625 | F80: =1+beta*(F79-$C79)/4 -> 1.1 | G80: =1+beta*(G79-$C79)/4 -> 1.125 | H80: =1+beta*(H79-$C79)/4 -> 1.15
A81: 混合鍵合占比 | B81: % | C81: =hbp_25 -> 0 | D81: =hbp_26 -> 0 | E81: =hbp_27 -> 0 | F81: =hbp_28 -> 0.05 | G81: =hbp_29 -> 0.15 | H81: =hbp_30 -> 0.25 | I81: 情境 B：Disco 模型基準值
A82: TC 鍵合產能需求（晶粒 × 層數加權 ×（1 − 混合鍵合）） | B82: 百萬顆當量 | C82: =C78*C80*(1-C81) -> 741.7049 | D82: =D78*D80*(1-D81) -> 1323.9433 | E82: =E78*E80*(1-E81) -> 1916.8079 | F82: =F78*F80*(1-F81) -> 2455.1409 | G82: =G78*G80*(1-G81) -> 2896.2807 | H82: =H78*H80*(1-H81) -> 2693.967
A83: 新機需求＝MAX(0, 下一年產能 − 本年)＋汰換 × 本年（CY2027 的下一年產能用三情境共同前提） | B83: 百萬顆當量 | C83: =MAX(0,D82-C82)+dlt*C82 -> 656.40884 | D83: =MAX(0,E82-D82)+dlt*D82 -> 725.25902 | E83: =MAX(0,hsA_28*8000/F77*F80*(1-hbp_28)-E82)+dlt*E82 -> 813.2098 | F83: =MAX(0,G82-F82)+dlt*F82 -> 686.65387 | G83: =MAX(0,H82-G82)+dlt*G82 -> 289.62807 | I83: 鍵合機在產能需要前一年購入；v0.2.1：CY2027 購機的 CY2028 產能＝情境 A 的 HBM 位元（hsA_28）× 混合鍵合基準，三情境相同（與 markets/equipment 2027 三情境相同、記憶體供給三情境相同一致）；CY2028 起照讀本情境
A84: SK 海力士 占產能增量（t＋1 年 HBM 市占，三家正規化） | B84: % | C84: =ms_sk_26/(ms_sk_26+ms_ss_26+ms_mu_26) -> 0.52 | D84: =ms_sk_27/(ms_sk_27+ms_ss_27+ms_mu_27) -> 0.42 | E84: =ms_sk_28/(ms_sk_28+ms_ss_28+ms_mu_28) -> 0.4 | F84: =ms_sk_29/(ms_sk_29+ms_ss_29+ms_mu_29) -> 0.4 | G84: =ms_sk_29/(ms_sk_29+ms_ss_29+ms_mu_29) -> 0.4
A85: 三星 占產能增量（t＋1 年 HBM 市占，三家正規化） | B85: % | C85: =ms_ss_26/(ms_sk_26+ms_ss_26+ms_mu_26) -> 0.29 | D85: =ms_ss_27/(ms_sk_27+ms_ss_27+ms_mu_27) -> 0.38 | E85: =ms_ss_28/(ms_sk_28+ms_ss_28+ms_mu_28) -> 0.4 | F85: =ms_ss_29/(ms_sk_29+ms_ss_29+ms_mu_29) -> 0.4 | G85: =ms_ss_29/(ms_sk_29+ms_ss_29+ms_mu_29) -> 0.4
A86: 美光 占產能增量（t＋1 年 HBM 市占，三家正規化） | B86: % | C86: =ms_mu_26/(ms_sk_26+ms_ss_26+ms_mu_26) -> 0.19 | D86: =ms_mu_27/(ms_sk_27+ms_ss_27+ms_mu_27) -> 0.2 | E86: =ms_mu_28/(ms_sk_28+ms_ss_28+ms_mu_28) -> 0.2 | F86: =ms_mu_29/(ms_sk_29+ms_ss_29+ms_mu_29) -> 0.2 | G86: =ms_mu_29/(ms_sk_29+ms_ss_29+ms_mu_29) -> 0.2
A87: 韓美加權份額＝Σ 占比 × 韓美在該廠份額 | B87: % | C87: =C84*hsk_25+C85*hss+C86*hmu_25 -> 0.412 | D87: =D84*hsk_A+D85*hss+D86*hmu_A -> 0.339 | E87: =E84*hsk_A+E85*hss+E86*hmu_A -> 0.33 | F87: =F84*hsk_B+F85*hss+F86*hmu_B -> 0.32 | G87: =G84*hsk_B+G85*hss+G86*hmu_B -> 0.32
A88: 韓美可得新機需求＝新機需求 × 加權份額 | B88: 百萬顆當量 | C88: =C83*C87 -> 270.44044 | D88: =D83*D87 -> 245.86281 | E88: =E83*E87 -> 268.35923 | F88: =F83*F87 -> 219.72924 | G88: =G83*G87 -> 92.680982
A89: B. 損益（會計年度；FY2026＝錨點）
A90: 其他業務營收（中國 TC 鍵合機、MSVP、EMI、2.5D 等） | B90: ₩億 | C90: =a25_rev-a25_hbm -> 2895.034 | D90: =C90*(1+g_o26) -> 3329.2891 | E90: =D90*(1+g_o_A) -> 3728.8038 | F90: =E90*(1+g_o_B) -> 4027.1081 | G90: =F90*(1+g_o_B) -> 4349.2767 | I90: v0.2.1：FY2027 三情境共用 g_o_A，FY2028 起讀 g_o_{情境}
A91: HBM TC 鍵合機營收（三大記憶體廠） | B91: ₩億 | C91: =a25_hbm -> 2871.966 | D91: =rev26-D90 -> 4210.5109 | E91: =$C92*E88 -> 3681.263 | F91: =$C92*F88 -> 3014.1729 | G91: =$C92*G88 -> 1271.367 | I91: FY2026＝錨點營收 − 其他；FY2027 起＝k × 可得新機需求
A92: 校準係數 k＝(FY2025＋FY2026 HBM 營收) ÷ (兩年可得新機需求) | B92: ₩億／百萬顆 | C92: =(C91+D91)/(C88+D88) -> 13.717669 | I92: 兩年平均，平滑訂單的季節與交期波動；不使用共識
A93: 營收 | B93: ₩億 | C93: =a25_rev -> 5767 | D93: =D90+D91 -> 7539.8 | E93: =E90+E91 -> 7410.0668 | F93: =F90+F91 -> 7041.281 | G93: =G90+G91 -> 5620.6437
A94: HBM TC 鍵合機占營收 | B94: % | C94: =C91/C93 -> 0.498 | D94: =D91/D93 -> 0.55843801 | E94: =E91/E93 -> 0.49679215 | F94: =F91/F93 -> 0.42807167 | G94: =G91/G93 -> 0.22619598
A95: 營業費用 | B95: ₩億 | C95: =opex25 -> 806.7 | D95: =opex_fix+opex_var*D93 -> 930.69148 | E95: =opex_fix+opex_var*E93 -> 921.61781 | F95: =opex_fix+opex_var*F93 -> 895.82454 | G95: =opex_fix+opex_var*G93 -> 796.46369 | I95: 固定＋變動 × 營收
A96: 毛利率 | B96: % | C96: =a25_gp/a25_rev -> 0.57579331 | D96: =(oi26+D95)/D93 -> 0.59526718 | E96: =$D96+0 -> 0.59526718 | F96: =$D96+0 -> 0.59526718 | G96: =$D96+0 -> 0.59526718 | I96: FY2026＝錨點營業利益反推（Derived）；FY2027 起沿用（情境 C 另扣價格競爭）
A97: 毛利 | B97: ₩億 | C97: =C93*C96 -> 3320.6 | D97: =D93*D96 -> 4488.1955 | E97: =E93*E96 -> 4410.9696 | F97: =F93*F96 -> 4191.4435 | G97: =G93*G96 -> 3345.7848
A98: 營業利益 | B98: ₩億 | C98: =a25_oi -> 2513.9 | D98: =oi26 -> 3557.504 | E98: =E97-E95 -> 3489.3518 | F98: =F97-F95 -> 3295.6189 | G98: =G97-G95 -> 2549.3211
A99: 營業利益率 | B99: % | C99: =C98/C93 -> 0.43591122 | D99: =D98/D93 -> 0.47183002 | E99: =E98/E93 -> 0.47089343 | F99: =F98/F93 -> 0.46804253 | G99: =G98/G93 -> 0.45356389
A100: 淨利 | B100: ₩億 | C100: =a25_ni -> 2140 | D100: =D98*nioi -> 3028.3856 | E100: =E98*nioi -> 2970.3699 | F100: =F98*nioi -> 2805.4515 | G100: =G98*nioi -> 2170.1528
A101: EPS | B101: ₩ | C101: =a25_eps -> 2231.7 | D101: =D100*100/shares -> 3158.1533 | E101: =E100*100/shares -> 3097.6516 | F101: =F100*100/shares -> 2925.6664 | G101: =G100*100/shares -> 2263.1448
A102: 三大廠 HBM TC 鍵合機市場（全部供應商）＝k × 新機需求 | B102: ₩億 | C102: =$C92*C83 -> 9004.3989 | D102: =$C92*D83 -> 9948.8629 | E102: =$C92*E83 -> 11155.343 | F102: =$C92*F83 -> 9419.2903 | G102: =$C92*G83 -> 3973.0219 | I102: 對帳用
A103: 同上（美元） | B103: US$M | C103: =C102/fx*100 -> 634.1126 | D103: =D102/fx*100 -> 700.62415 | E103: =E102/fx*100 -> 785.5875 | F103: =F102/fx*100 -> 663.3303 | G103: =G102/fx*100 -> 279.79027
A106: 情境 C：2028–29 顆數 ×0.6；混合鍵合導入慢（CY2028 起 Disco 低值）；韓華、ASMPT 搶份額與價格壓力
A107: 項目 | B107: 單位 | C107: 2025 | D107: 2026 | E107: 2027 | F107: 2028 | G107: 2029 | H107: 2030 | I107: 說明
A108: A. 日曆年鍵合產能需求（本公司會計年度＝日曆年）
A109: HBM 出貨位元 | B109: EB | C109: =hsC_25 -> 2.2251147 | D109: =hsC_26 -> 3.782695 | E109: =hsC_27 -> 5.8631772 | F109: =hsC_28 -> 6.16722 | G109: =hsC_29 -> 8.017386 | H109: =G109*(1+g_tail) -> 8.8191246 | I109: markets/memory；2030＝2029 ×（1＋g_tail）
A110: DRAM 晶粒容量 | B110: Gb | C110: =den_25 -> 24 | D110: =den_26 -> 24 | E110: =den_27 -> 26 | F110: =den_28 -> 28 | G110: =den_29 -> 30 | H110: =den_30 -> 32
A111: 核心晶粒數＝位元 × 8000 ÷ 容量 | B111: 百萬顆 | C111: =C109*8000/C110 -> 741.7049 | D111: =D109*8000/D110 -> 1260.8983 | E111: =E109*8000/E110 -> 1804.0545 | F111: =F109*8000/F110 -> 1762.0629 | G111: =G109*8000/G110 -> 2137.9696 | H111: =H109*8000/H110 -> 2204.7811 | I111: 1 EB＝8×10⁹ Gb；每顆核心晶粒鍵合一次
A112: 平均堆疊層數 | B112: 層 | C112: =stk_25 -> 10 | D112: =stk_26 -> 12 | E112: =stk_27 -> 12.5 | F112: =stk_28 -> 14 | G112: =stk_29 -> 15 | H112: =stk_30 -> 16
A113: 層數加權（每顆晶粒鍵合時間） | B113: x | C113: =1+beta*(C112-$C112)/4 -> 1 | D113: =1+beta*(D112-$C112)/4 -> 1.05 | E113: =1+beta*(E112-$C112)/4 -> 1.0625 | F113: =1+beta*(F112-$C112)/4 -> 1.1 | G113: =1+beta*(G112-$C112)/4 -> 1.125 | H113: =1+beta*(H112-$C112)/4 -> 1.15
...

Sheet Val
A1: Val — P/E 估值。跨公司規則：合理倍數＝10 年（2016–2025 年底）P/E 的分位，依循環位置：見頂年 25 分位、中段中位數、谷底 75 分位。循環位置依設備股共用規則（第 4 節）。本版未做先驗，無 Andy 合理 P/E 對照
A2: P/E 定義：日曆年底收盤價 ÷ 當年 EPS（本公司會計年度＝日曆年）。兩個來源各自取分位再平均（tools/valuation_rule.py 的多來源慣例）
A3: 目標價（DCF 與 Comparable 加權）：見本頁第 77 列起「0. 目標價」（估值 v2 新增，放在既有內容之後以免位移既有列）；原「0. 目標價與上檔空間」改名為「舊法：規則值情境加權（參考）」
A4: 舊法：規則值情境加權（參考）
A5: 項目 | B5: 數值 | E5: 說明
A6: 規則值情境加權價（12 個月；參考） | B6: =tp_wA*B8+tp_wB*B9+tp_wC*B10 -> 64078.021 | E6: 權重 × 三情境隱含價
A7: 相對現價（規則值情境加權價 ÷ 現價 − 1） | B7: =B6/px-1 -> -0.66006355 | E7: 現價見第 6 節
A8: 情境 A 隱含價（樂觀） | B8: =F44 -> 66816.345 | E8: Val!F44：FY2027 EPS × 規則倍數
A9: 情境 B 隱含價（基準） | B9: =F51 -> 66816.345 | E9: Val!F51：FY2027 EPS × 規則倍數
A10: 情境 C 隱含價（下檔） | B10: =F58 -> 53124.725 | E10: Val!F58：FY2027 EPS × 規則倍數
A11: 情境權重 A／B／C | B11: =tp_wA -> 0.3 | C11: =tp_wB -> 0.5 | D11: =tp_wC -> 0.2 | E11: In 頁 tp_wA／tp_wB／tp_wC（Assumed，Andy 可改）
A12: 規則值方法 | B12: P/E：各情境 FY2027 EPS（模型）× 依循環位置的十年（2016–2025 年底）P/E 分位（設備股共用規則：A、B 中段＝中位數，C 見頂＝25 分位），再以 0.3／0.5／0.2 加權。偏誤：十年樣本有 7 年在 HBM 需求出現前（2016–2022，倍數 7–35 倍），會把分位往下拉；2024–25 年 50 倍以上的高成長期只占兩年。照規則計算，不另換倍數
A14: 1. 十年 P/E（年底）— 兩個來源
A15: 年底 | B15: 來源1：companiesmarketcap | C15: 來源2：stockanalysis／券商報告 | D15: 兩者差距 | E15: 標記 | F15: 來源2 出處
A16: 2016-12 | B16: 23.2 | D16: =IF(C16="","",B16-C16) | E16: Interested-party（資料商／券商） | F16: 未找到（2016–2017 年的券商報告與財務頁未取得）
A17: 2017-12 | B17: 55 | D17: =IF(C17="","",B17-C17) | E17: Interested-party（資料商／券商） | F17: 未找到
A18: 2018-12 | B18: 7.16 | C18: 9.7 | D18: =IF(C18="","",B18-C18) -> -2.54 | E18: Interested-party（資料商／券商） | F18: SK 證券 2021-12-22 報告（年底 P/E 9.7）
A19: 2019-12 | B19: 19.7 | C19: 24.1 | D19: =IF(C19="","",B19-C19) -> -4.4 | E19: Interested-party（資料商／券商） | F19: SK 證券 2021-12-22 報告（24.1）
A20: 2020-12 | B20: 17.2 | C20: 18.78 | D20: =IF(C20="","",B20-C20) -> -1.58 | E20: Interested-party（資料商／券商） | F20: Hana 證券 2023-02-13 報告（18.78；SK 證券 18.8）
A21: 2021-12 | B21: 34.8 | C21: 17.93 | D21: =IF(C21="","",B21-C21) -> 16.87 | E21: Interested-party（資料商／券商） | F21: stockanalysis（年底市值 ÷ 淨利；Hana 18.06）
A22: 2022-12 | B22: 12.1 | C22: 12.13 | D22: =IF(C22="","",B22-C22) -> -0.03 | E22: Interested-party（資料商／券商） | F22: stockanalysis（Hana 11.59）
A23: 2023-12 | B23: 21.8 | C23: 22.48 | D23: =IF(C23="","",B23-C23) -> -0.68 | E23: Interested-party（資料商／券商） | F23: stockanalysis
A24: 2024-12 | B24: 51.5 | C24: 51.76 | D24: =IF(C24="","",B24-C24) -> -0.26 | E24: Interested-party（資料商／券商） | F24: stockanalysis
A25: 2025-12 | B25: 56.5 | C25: 56.47 | D25: =IF(C25="","",B25-C25) -> 0.03 | E25: Interested-party（資料商／券商） | F25: stockanalysis
A26: 說明：companiesmarketcap 以美元計價的年底股價 ÷ EPS；2021 年 34.8 與另兩個來源（17.9、18.1）差異大，原因未解（該站 2021 年 EPS 疑有口徑問題），照列不剔除。2022 年 1 比 1 無償配股，各來源 EPS 皆為調整後
A28: 2. 分位
A29: 統計 | B29: 採用（兩來源平均） | C29: 來源1 | D29: 來源2 | E29: 用途
A30: 25 分位 | B30: =ROUND(AVERAGE(C30,D30),2) -> 17.15 | C30: =PERCENTILE(B16:B25,0.25) -> 17.825 | D30: =PERCENTILE(C16:C25,0.25) -> 16.48 | E30: 見頂年
A31: 中位數 | B31: =ROUND(AVERAGE(C31,D31),2) -> 21.57 | C31: =PERCENTILE(B16:B25,0.5) -> 22.5 | D31: =PERCENTILE(C16:C25,0.5) -> 20.63 | E31: 中段
A32: 75 分位 | B32: =ROUND(AVERAGE(C32,D32),2) -> 39.17 | C32: =PERCENTILE(B16:B25,0.75) -> 47.325 | D32: =PERCENTILE(C16:C25,0.75) -> 31.015 | E32: 谷底
A33: 年數 | C33: =COUNT(B16:B25) -> 10 | D33: =COUNT(C16:C25) -> 8
A35: 4. 循環位置（設備股共用規則；見頂年度讀設備市場模型，不在本模型另訂）
A36: 循環位置（設備股共用規則）：各情境的見頂年度取自設備市場模型（markets/equipment 的 Mkt 頁「見頂年度」：A 2029、B 2028、C 2027）；會計年度 FY(t) 對照日曆年 t（FY(t) 有 3/4 落在 t 年）：t 早於見頂年＝中段（中位數）、等於＝見頂（25 分位）、晚於＝谷底（75 分位）。本公司會計年度＝日曆年，FY(t) 直接對照日曆年 t
A37: 情境 | B37: 設備市場見頂年度 | C37: FY2027 對照日曆年 | D37: 判定 | E37: 倍數 | F37: 規則
A38: A | B38: =pk_A -> 2029 | C38: 2027 | D38: =IF(C38<pk_A,"中段",IF(C38=pk_A,"見頂","谷底")) -> 中段 | E38: =IF(D38="見頂",pe_peak,IF(D38="谷底",pe_trough,pe_mid)) -> 21.57 | F38: tools/cycle_position.py
A39: B | B39: =pk_B -> 2028 | C39: 2027 | D39: =IF(C39<pk_B,"中段",IF(C39=pk_B,"見頂","谷底")) -> 中段 | E39: =IF(D39="見頂",pe_peak,IF(D39="谷底",pe_trough,pe_mid)) -> 21.57 | F39: tools/cycle_position.py
A40: C | B40: =pk_C -> 2027 | C40: 2027 | D40: =IF(C40<pk_C,"中段",IF(C40=pk_C,"見頂","谷底")) -> 見頂 | E40: =IF(D40="見頂",pe_peak,IF(D40="谷底",pe_trough,pe_mid)) -> 17.15 | F40: tools/cycle_position.py
A42: 5. 隱含股價（韓元）：規則值＝FY2027 EPS × 依循環位置的倍數；其餘倍數僅供參考
A43: 情境 | B43: EPS 年度 | C43: EPS | D43: 倍數類型 | E43: 倍數 | F43: 隱含股價 | G43: 相對現價 | H43: 備註
A44: A | B44: FY2027 | C44: =PL!E12 -> 3097.6516 | D44: ="規則值："&D38 -> 規則值：中段 | E44: =E38 -> 21.57 | F44: =C44*E44 -> 66816.345 | G44: =F44/px-1 -> -0.64553663
A45: A | B45: FY2027 | C45: =PL!E12 -> 3097.6516 | D45: 參考：25 分位 | E45: =pe_peak -> 17.15 | F45: =C45*E45 -> 53124.725 | G45: =F45/px-1 -> -0.71817122
A46: A | B46: FY2027 | C46: =PL!E12 -> 3097.6516 | D46: 參考：中位數 | E46: =pe_mid -> 21.57 | F46: =C46*E46 -> 66816.345 | G46: =F46/px-1 -> -0.64553663
A47: A | B47: FY2027 | C47: =PL!E12 -> 3097.6516 | D47: 參考：75 分位 | E47: =pe_trough -> 39.17 | F47: =C47*E47 -> 121335.01 | G47: =F47/px-1 -> -0.35631293
A48: A | B48: FY2028 | C48: =PL!F12 -> 2362.588 | D48: 參考：25 分位 | E48: =pe_peak -> 17.15 | F48: =C48*E48 -> 40518.385 | G48: =F48/px-1 -> -0.78504836
A49: A | B49: FY2028 | C49: =PL!F12 -> 2362.588 | D49: 參考：中位數 | E49: =pe_mid -> 21.57 | F49: =C49*E49 -> 50961.024 | G49: =F49/px-1 -> -0.72964974
A50: A | B50: FY2028 | C50: =PL!F12 -> 2362.588 | D50: 參考：75 分位 | E50: =pe_trough -> 39.17 | F50: =C50*E50 -> 92542.573 | G50: =F50/px-1 -> -0.50905797
A51: B | B51: FY2027 | C51: =PL!E22 -> 3097.6516 | D51: ="規則值："&D39 -> 規則值：中段 | E51: =E39 -> 21.57 | F51: =C51*E51 -> 66816.345 | G51: =F51/px-1 -> -0.64553663
A52: B | B52: FY2027 | C52: =PL!E22 -> 3097.6516 | D52: 參考：25 分位 | E52: =pe_peak -> 17.15 | F52: =C52*E52 -> 53124.725 | G52: =F52/px-1 -> -0.71817122
A53: B | B53: FY2027 | C53: =PL!E22 -> 3097.6516 | D53: 參考：中位數 | E53: =pe_mid -> 21.57 | F53: =C53*E53 -> 66816.345 | G53: =F53/px-1 -> -0.64553663
A54: B | B54: FY2027 | C54: =PL!E22 -> 3097.6516 | D54: 參考：75 分位 | E54: =pe_trough -> 39.17 | F54: =C54*E54 -> 121335.01 | G54: =F54/px-1 -> -0.35631293
A55: B | B55: FY2028 | C55: =PL!F22 -> 2925.6664 | D55: 參考：25 分位 | E55: =pe_peak -> 17.15 | F55: =C55*E55 -> 50175.179 | G55: =F55/px-1 -> -0.73381868
A56: B | B56: FY2028 | C56: =PL!F22 -> 2925.6664 | D56: 參考：中位數 | E56: =pe_mid -> 21.57 | F56: =C56*E56 -> 63106.624 | G56: =F56/px-1 -> -0.66521685
A57: B | B57: FY2028 | C57: =PL!F22 -> 2925.6664 | D57: 參考：75 分位 | E57: =pe_trough -> 39.17 | F57: =C57*E57 -> 114598.35 | G57: =F57/px-1 -> -0.39205118
A58: C | B58: FY2027 | C58: =PL!E32 -> 3097.6516 | D58: ="規則值："&D40 -> 規則值：見頂 | E58: =E40 -> 17.15 | F58: =C58*E58 -> 53124.725 | G58: =F58/px-1 -> -0.71817122
A59: C | B59: FY2027 | C59: =PL!E32 -> 3097.6516 | D59: 參考：25 分位 | E59: =pe_peak -> 17.15 | F59: =C59*E59 -> 53124.725 | G59: =F59/px-1 -> -0.71817122
A60: C | B60: FY2027 | C60: =PL!E32 -> 3097.6516 | D60: 參考：中位數 | E60: =pe_mid -> 21.57 | F60: =C60*E60 -> 66816.345 | G60: =F60/px-1 -> -0.64553663
A61: C | B61: FY2027 | C61: =PL!E32 -> 3097.6516 | D61: 參考：75 分位 | E61: =pe_trough -> 39.17 | F61: =C61*E61 -> 121335.01 | G61: =F61/px-1 -> -0.35631293
A62: C | B62: FY2028 | C62: =PL!F32 -> 2014.6763 | D62: 參考：25 分位 | E62: =pe_peak -> 17.15 | F62: =C62*E62 -> 34551.698 | G62: =F62/px-1 -> -0.81670186
A63: C | B63: FY2028 | C63: =PL!F32 -> 2014.6763 | D63: 參考：中位數 | E63: =pe_mid -> 21.57 | F63: =C63*E63 -> 43456.568 | G63: =F63/px-1 -> -0.76946118
A64: C | B64: FY2028 | C64: =PL!F32 -> 2014.6763 | D64: 參考：75 分位 | E64: =pe_trough -> 39.17 | F64: =C64*E64 -> 78914.871 | G64: =F64/px-1 -> -0.58135347
A66: 6. 目前倍數
A67: 項目 | B67: A | C67: B | D67: C | E67: 備註
A68: 現價（etfshopping 2026-10-23 收盤） | B68: =px -> 188500
A69: 現價 ÷ FY2026 EPS（模型） | B69: =px/PL!D12 -> 59.686779 | C69: =px/PL!D22 -> 59.686779 | D69: =px/PL!D32 -> 59.686779
A70: 現價 ÷ FY2027 EPS（模型） | B70: =px/PL!E12 -> 60.85255 | C70: =px/PL!E22 -> 60.85255 | D70: =px/PL!E32 -> 60.85255
A71: 現價 ÷ FY2028 EPS（模型） | B71: =px/PL!F12 -> 79.785387 | C71: =px/PL!F22 -> 64.429765 | D71: =px/PL!F32 -> 93.563418
A72: 近 12 月 P/E（stockanalysis，2026-10-02 @ ₩272,000） | B72: 116.68 | E72: 現價 ÷ 近 12 月 EPS 2,331＝ | F72: =px/2331.18 -> 80.860337
A73: 現價 ÷ 第三方預估 FY2026 EPS（alphadistill 3,400） | B73: =px/cons_eps26 -> 55.441176
A74: 現價隱含倍數 ÷ 規則倍數（情境 A，FY2027） | B74: =B70/E38 -> 2.821166 | E74: >1＝現價高於規則給的倍數
A77: 0. 目標價
A78: 0.1 DCF（股東權益現金流，FY2027–FY2032 明確期＋FY2032 後永續）
A79: 項目 | B79: A（順利） | C79: B（平平） | D79: C（不如預期） | E79: 說明
A80: 情境 EPS（FY2027–FY2032） | E80: PL 頁延伸區塊；FY2030 起為收斂法
A81: FY2027 | B81: =PL!E147 -> 3097.6516 | C81: =PL!E154 -> 3097.6516 | D81: =PL!E161 -> 3097.6516
A82: FY2028 | B82: =PL!F147 -> 2362.588 | C82: =PL!F154 -> 2925.6664 | D82: =PL!F161 -> 2014.6763
A83: FY2029 | B83: =PL!G147 -> 2332.0847 | C83: =PL!G154 -> 2263.1448 | D83: =PL!G161 -> 1392.6111
A84: FY2030 | B84: =PL!H147 -> 2361.2953 | C84: =PL!H154 -> 1922.6174 | D84: =PL!H161 -> 1108.162
A85: FY2031 | B85: =PL!I147 -> 2446.9224 | C85: =PL!I154 -> 1780.9794 | D85: =PL!I161 -> 963.45098
A86: FY2032 | B86: =PL!J147 -> 2593.7377 | C86: =PL!J154 -> 1786.0679 | D86: =PL!J161 -> 907.12616
A87: 股東現金流＝EPS ×（1 − tp_g ÷ tp_roe） | E87: 模型無折舊與資本支出項目，故不用（淨利＋折舊－資本支出）；設備股資本支出低（輕資產），此式偏誤小
A88: 再投資率（tp_g ÷ tp_roe，上限 0.8） | B88: =MIN(tp_g/tp_roe,0.8) -> 0.10192814 | E88: ROE 為近三年平均（In 頁 tp_roe）
A89: FY2027 | B89: =B81*(1-$B$88) -> 2781.9137 | C89: =C81*(1-$B$88) -> 2781.9137 | D89: =D81*(1-$B$88) -> 2781.9137
A90: FY2028 | B90: =B82*(1-$B$88) -> 2121.7738 | C90: =C82*(1-$B$88) -> 2627.4587 | D90: =D82*(1-$B$88) -> 1809.3241
A91: FY2029 | B91: =B83*(1-$B$88) -> 2094.3797 | C91: =C83*(1-$B$88) -> 2032.4667 | D91: =D83*(1-$B$88) -> 1250.6648
A92: FY2030 | B92: =B84*(1-$B$88) -> 2120.6128 | C92: =C84*(1-$B$88) -> 1726.6486 | D92: =D84*(1-$B$88) -> 995.20909
A93: FY2031 | B93: =B85*(1-$B$88) -> 2197.5121 | C93: =C85*(1-$B$88) -> 1599.4475 | D93: =D85*(1-$B$88) -> 865.24822
A94: FY2032 | B94: =B86*(1-$B$88) -> 2329.3628 | C94: =C86*(1-$B$88) -> 1604.0173 | D94: =D86*(1-$B$88) -> 814.66447
A95: DCF 情境每股價值（折現率 tp_r） | B95: =SUMPRODUCT(B89:B94,1/(1+tp_r)^{1;2;3;4;5;6})+B94*(1+tp_g)/(tp_r-tp_g)/(1+tp_r)^6 -> 32774.823 | C95: =SUMPRODUCT(C89:C94,1/(1+tp_r)^{1;2;3;4;5;6})+C94*(1+tp_g)/(tp_r-tp_g)/(1+tp_r)^6 -> 24999.419 | D95: =SUMPRODUCT(D89:D94,1/(1+tp_r)^{1;2;3;4;5;6})+D94*(1+tp_g)/(tp_r-tp_g)/(1+tp_r)^6 -> 14611.666 | E95: Σ 明確期現金流 ÷ (1＋r)^t ＋ 永續價值 ÷ (1＋r)^6；永續價值＝FY2032 現金流 ×(1＋g)÷(r−g)；基準日 2026 年底，t＝1 對 FY2027
A96: DCF 情境價值推到 12 個月後（×(1＋tp_r)） | B96: =B95*(1+tp_r) -> 36052.305 | C96: =C95*(1+tp_r) -> 27499.361 | D96: =D95*(1+tp_r) -> 16072.833
A97: DCF 目標價（情境加權） | B97: =tp_wA*B96+tp_wB*C96+tp_wC*D96 -> 27779.939 | E97: Σ 權重 × 情境價值 ×(1＋r)；權重見 In 頁 tp_wA／tp_wB／tp_wC
A99: 0.2 Comparable（市場主流同業前瞻 P/E）
A100: 同業與前瞻 P/E | B100: 代號 | C100: 前瞻 12 月 P/E | D100: 日期 | E100: 來源 | F100: 標記
A101: BE Semiconductor（BESI） | B101: BESI.AS | C101: 25.82 | D101: 2026-10-23 | E101: stockanalysis.com statistics：Forward PE（分析師共識；價格日期如左） | F101: Interested-party
A102: ASMPT | B102: 0522.HK | C102: 30.26 | D102: 2026-09-23 | E102: stockanalysis.com statistics：Forward PE（分析師共識；價格日期如左） | F102: Interested-party
A103: Kulicke & Soffa | B103: KLIC | C103: 12.61 | D103: 2026-10-23 | E103: stockanalysis.com statistics：Forward PE（分析師共識；價格日期如左） | F103: Interested-party
A104: Disco | B104: 6146.T | C104: 26.01 | D104: 2026-10-23 | E104: stockanalysis.com statistics：Forward PE（分析師共識；價格日期如左） | F104: Interested-party
A105: 同業前瞻 P/E 中位數 | B105: =MEDIAN(C101:C104) -> 25.915 | E105: 後段封裝設備同業：BESI（混合鍵合）、ASMPT（TC 鍵合）、Kulicke & Soffa、Disco；韓華 Semitech 未上市，無法列入
A106: 12 個月後的前瞻 EPS（情境加權） | B106: =tp_wA*(2/12*B81+10/12*B82)+tp_wB*(2/12*C81+10/12*C82)+tp_wC*(2/12*D81+10/12*D82) -> 2661.7293 | E106: 約 2027-10 時的未來 12 月 ≈ 2／12 × FY2027＋10／12 × FY2028（會計年度＝日曆年）
A107: Comparable 目標價 | B107: =B105*B106 -> 68978.715 | E107: 同業中位數 × 上列 EPS
A109: 0.3 結論
...

Sheet Recon
A1: Recon — 本模型 vs 共識、賣方、競爭者估的市場規模、SEMI。只作事後對照，不為對上數字而調整參數。差距 > 10% 的原因見 README
A3: 項目 | B3: 對照值 | C3: 模型 A | D3: 差距 A | E3: 模型 B | F3: 差距 B | G3: 模型 C | H3: 差距 C | I3: 對照來源 | J3: 說明
A4: A. FY2026 vs 共識與賣方（校準未使用）
A5: 營收 | B5: =cons_rev26 -> 7280 | C5: =PL!D5 -> 7539.8 | D5: =C5/B5-1 -> 0.035686813 | E5: =PL!D15 -> 7539.8 | F5: =E5/B5-1 -> 0.035686813 | G5: =PL!D25 -> 7539.8 | H5: =G5/B5-1 -> 0.035686813 | I5: etfshopping 共識 ₩7,280 億 | J5: 錨點＝上半年 3,020 ＋ 0.9 × 2 × 第二季
A6: 營業利益 | B6: =cons_oi26 -> 3694 | C6: =PL!D9 -> 3557.504 | D6: =C6/B6-1 -> -0.036950731 | E6: =PL!D19 -> 3557.504 | F6: =E6/B6-1 -> -0.036950731 | G6: =PL!D29 -> 3557.504 | H6: =G6/B6-1 -> -0.036950731 | I6: 上上人證券（2026-06-09）
A7: EPS（韓元） | B7: =cons_eps26 -> 3400 | C7: =PL!D12 -> 3158.1533 | D7: =C7/B7-1 -> -0.071131371 | E7: =PL!D22 -> 3158.1533 | F7: =E7/B7-1 -> -0.071131371 | G7: =PL!D32 -> 3158.1533 | H7: =G7/B7-1 -> -0.071131371 | I7: alphadistill（2026-10-12，非券商共識） | J7: stockanalysis 遠期 EPS 約 4,006（隱含）
A8: B. FY2027 vs 第三方預估
A9: 營收 | B9: =cons_rev27 -> 9900 | C9: =PL!E5 -> 7410.0668 | D9: =C9/B9-1 -> -0.2515084 | E9: =PL!E15 -> 7410.0668 | F9: =E9/B9-1 -> -0.2515084 | G9: =PL!E25 -> 7410.0668 | H9: =G9/B9-1 -> -0.2515084 | I9: alphadistill
A10: EPS（韓元） | B10: =cons_eps27 -> 4650 | C10: =PL!E12 -> 3097.6516 | D10: =C10/B10-1 -> -0.33383837 | E10: =PL!E22 -> 3097.6516 | F10: =E10/B10-1 -> -0.33383837 | G10: =PL!E32 -> 3097.6516 | H10: =G10/B10-1 -> -0.33383837 | I10: alphadistill
A11: C. 市場規模與市占
A12: TC 鍵合機市場 CY2025（US$M；模型＝三大廠 HBM，不含邏輯與中國） | B12: =tam25 -> 759 | C12: =PL!C70 -> 634.1126 | D12: =C12/B12-1 -> -0.16454203 | E12: =PL!C103 -> 634.1126 | F12: =E12/B12-1 -> -0.16454203 | G12: =PL!C136 -> 634.1126 | H12: =G12/B12-1 -> -0.16454203 | I12: ASMPT 估（含邏輯用 TCB） | J12: 口徑：模型只含三大記憶體廠的 HBM 鍵合
A13: TC 鍵合機市場 CY2028（US$M） | B13: =tam28 -> 1600 | C13: =PL!F70 -> 353.73845 | D13: =C13/B13-1 -> -0.77891347 | E13: =PL!F103 -> 663.3303 | F13: =E13/B13-1 -> -0.58541856 | G13: =PL!F136 -> 522.15319 | H13: =G13/B13-1 -> -0.67365426 | I13: ASMPT 估
A14: 韓美 HBM TC 鍵合機市占 CY2025（模型＝加權份額） | B14: =sh_claim -> 0.712 | C14: =PL!C54 -> 0.412 | D14: =C14-B14 -> -0.3 | E14: =PL!C87 -> 0.412 | F14: =E14-B14 -> -0.3 | G14: =PL!C120 -> 0.412 | H14: =G14-B14 -> -0.3 | I14: 公司引 TechInsights 71.2% | J14: 差距以百分點計
A15: D. 三大廠 HBM TC 鍵合機市場 vs SEMI 組裝與封裝設備（markets/equipment）
A16: CY2025：模型市場（US$B）vs SEMI 組裝與封裝 | B16: =semi_pkg25 -> 6.1131387 | C16: =PL!C70/1000 -> 0.6341126 | D16: =C16/B16-1 -> -0.89627054 | E16: =PL!C103/1000 -> 0.6341126 | F16: =E16/B16-1 -> -0.89627054 | G16: =PL!C136/1000 -> 0.6341126 | H16: =G16/B16-1 -> -0.89627054 | I16: SEMI（equipment 成品） | J16: 差距＝占 SEMI 組裝封裝的比例 − 1
A17: CY2028：同上 | B17: =semi_pkg28 -> 8.6 | C17: =PL!F70/1000 -> 0.35373845 | D17: =C17/B17-1 -> -0.95886762 | E17: =PL!F103/1000 -> 0.6633303 | F17: =E17/B17-1 -> -0.92286857 | G17: =PL!F136/1000 -> 0.52215319 | H17: =G17/B17-1 -> -0.93928451 | I17: SEMI 2026-07
A18: E. 其他資訊（非對帳）
A19: FY2026 上半年營收 ÷ 錨點全年 | C19: =(q1_rev+q2_rev)/PL!D5 -> 0.40054113
A20: CY2026 三大廠 TC 鍵合機台數（模型 A，市場 ÷ 單價） | C20: =Units!D32 -> 331.62876 | J20: 對照：SK 海力士 2026-03 預計約 100 台（The Elec）；HBM4 現有約 50 套

Sheet Sens
A1: Sens — 一次動一個輸入（情境 A）：對 FY2027、FY2028 營收與 EPS 的影響。每個案例是一個完整的推導區塊（本頁下方，與 PL 同一引擎；校準係數 k 在各區塊內重算）
A3: 案例 | B3: 設定 | C3: FY2027 營收 ₩億 | D3: FY2027 EPS ₩ | E3: 相對基準 | F3: FY2028 營收 ₩億 | G3: FY2028 EPS ₩ | H3: 相對基準
A4: 基準（情境 A） | B4: PL 區塊 A | C4: =PL!E60 -> 7410.0668 | D4: =PL!E68 -> 3097.6516 | E4: =D4/D$4-1 -> 0 | F4: =PL!F60 -> 5833.8786 | G4: =PL!F68 -> 2362.588 | H4: =G4/G$4-1 -> 0
A5: SK 海力士份額 −10pt | B5: 35% | C5: =E80 -> 7166.6812 | D5: =E88 -> 2984.1474 | E5: =D5/D$4-1 -> -0.036642009 | F5: =F80 -> 5724.2856 | G5: =F88 -> 2311.4788 | H5: =G5/G$4-1 -> -0.021632741
A6: SK 海力士份額 +10pt | B6: 55% | C6: =E120 -> 7626.3339 | D6: =E128 -> 3198.5089 | E6: =D6/D$4-1 -> 0.032559269 | F6: =F120 -> 5931.2605 | G6: =F128 -> 2408.0026 | H6: =G6/G$4-1 -> 0.01922237
A7: 美光份額 −10pt | B7: 65% | C7: =E160 -> 7286.9229 | D7: =E168 -> 3040.2228 | E7: =D7/D$4-1 -> -0.018539474 | F7: =F160 -> 5778.4287 | G7: =F168 -> 2336.7287 | H7: =G7/G$4-1 -> -0.010945351
A8: 美光份額 +10pt | B8: 85% | C8: =E200 -> 7526.4806 | D8: =E208 -> 3151.9418 | E8: =D8/D$4-1 -> 0.017526233 | F8: =F200 -> 5886.298 | G8: =F208 -> 2387.0341 | H8: =G8/G$4-1 -> 0.010347153
A9: 三星份額 10% | B9: 韓美打進三星 | C9: =E240 -> 7514.6159 | D9: =E248 -> 3146.4086 | E9: =D9/D$4-1 -> 0.015739988 | F9: =F240 -> 5880.9555 | G9: =F248 -> 2384.5426 | H9: =G9/G$4-1 -> 0.009292588
A10: 混合鍵合 不納入 | B10: 各年 0% | C10: =E280 -> 8014.8364 | D10: =E288 -> 3379.689 | E10: =D10/D$4-1 -> 0.091048789 | F10: =F280 -> 8876.969 | G10: =F288 -> 3781.7491 | H10: =G10/G$4-1 -> 0.60068071
A11: 混合鍵合 Disco 基準 | B11: 2028 5%、2029 15%、2030 25% | C11: =E320 -> 7410.0668 | D11: =E328 -> 3097.6516 | E11: =D11/D$4-1 -> 0 | F11: =F320 -> 7083.2775 | G11: =F328 -> 2945.2517 | H11: =G11/G$4-1 -> 0.24662094
A12: 晶粒容量 低 | B12: 各年取低值（晶粒較多） | C12: =E360 -> 8410.1099 | D12: =E368 -> 3564.0269 | E12: =D12/D$4-1 -> 0.15055769 | F12: =F360 -> 5874.4013 | G12: =F368 -> 2381.486 | H12: =G12/G$4-1 -> 0.0079988401
A13: 晶粒容量 高 | B13: 各年取高值（晶粒較少） | C13: =E400 -> 6881.4404 | D13: =E408 -> 2851.1239 | E13: =D13/D$4-1 -> -0.079585353 | F13: =F400 -> 6574.7844 | G13: =F408 -> 2708.1133 | H13: =G13/G$4-1 -> 0.14624863
A14: 堆疊層數 低 | C14: =E440 -> 6989.5988 | D14: =E448 -> 2901.5642 | E14: =D14/D$4-1 -> -0.063301967 | F14: =F440 -> 5531.2335 | G14: =F448 -> 2221.4479 | H14: =G14/G$4-1 -> -0.059739629
A15: 堆疊層數 高 | C15: =E480 -> 7610.0736 | D15: =E488 -> 3190.9258 | E15: =D15/D$4-1 -> 0.030111264 | F15: =F480 -> 5631.9772 | G15: =F488 -> 2268.4303 | H15: =G15/G$4-1 -> -0.039853657
A16: 層數對鍵合時間 0 | B16: beta＝0 | C16: =E520 -> 7120.1812 | D16: =E528 -> 2962.4619 | E16: =D16/D$4-1 -> -0.043642633 | F16: =F520 -> 5585.495 | G16: =F528 -> 2246.753 | H16: =G16/G$4-1 -> -0.049028862
A17: 層數對鍵合時間 0.25 | B17: beta＝0.25 | C17: =E560 -> 7761.1641 | D17: =E568 -> 3261.3876 | E17: =D17/D$4-1 -> 0.052858118 | F17: =F560 -> 6134.7104 | G17: =F568 -> 2502.8825 | H17: =G17/G$4-1 -> 0.059381692
A18: 汰換比例 5% | C18: =E600 -> 7232.161 | D18: =E608 -> 3014.6843 | E18: =D18/D$4-1 -> -0.026783936 | F18: =F600 -> 5409.9555 | G18: =F608 -> 2164.8893 | H18: =G18/G$4-1 -> -0.083678891
A19: 汰換比例 15% | C19: =E640 -> 7563.7477 | D19: =E648 -> 3169.3215 | E19: =D19/D$4-1 -> 0.023136836 | F19: =F640 -> 6200.0772 | G19: =F648 -> 2533.3666 | H19: =G19/G$4-1 -> 0.072284551
A20: FY2026 下半年 ×0.7 | B20: 錨點營收較低 → k 較低 | C20: =E680 -> 6888.0093 | D20: =E688 -> 2896.7829 | E20: =D20/D$4-1 -> -0.064845464 | F20: =F680 -> 5598.8038 | G20: =F688 -> 2287.5828 | H20: =G20/G$4-1 -> -0.031747063
A21: FY2026 下半年 ×1.1 | B21: 錨點營收較高 → k 較高 | C21: =E720 -> 7932.1244 | D21: =E728 -> 3303.596 | E21: =D21/D$4-1 -> 0.066484038 | F21: =F720 -> 6068.9534 | G21: =F728 -> 2443.5095 | H21: =G21/G$4-1 -> 0.034251212
A22: 下半年營益率 42% | B22: 毛利率基準隨之下降 | C22: =E760 -> 7410.0668 | D22: =E768 -> 2861.0484 | E22: =D22/D$4-1 -> -0.07638147 | F22: =F760 -> 5833.8786 | G22: =F768 -> 2176.3125 | H22: =G22/G$4-1 -> -0.078843854
A23: 下半年營益率 52% | C23: =E800 -> 7410.0668 | D23: =E808 -> 3255.3871 | E23: =D23/D$4-1 -> 0.05092098 | F23: =F800 -> 5833.8786 | G23: =F808 -> 2486.7717 | H23: =G23/G$4-1 -> 0.05256257
A24: TC 鍵合機占 FY2025 營收 50% | B24: HBM 基期較低、其他較高 | C24: =E840 -> 7491.6753 | D24: =E848 -> 3135.7101 | E24: =D24/D$4-1 -> 0.012286256 | F24: =F840 -> 6283.5152 | G24: =F848 -> 2572.2784 | H24: =G24/G$4-1 -> 0.088754509
A25: TC 鍵合機占 FY2025 營收 70% | C25: =E880 -> 7328.4584 | D25: =E888 -> 3059.5931 | E25: =D25/D$4-1 -> -0.012286256 | F25: =F880 -> 5384.2421 | G25: =F888 -> 2152.8977 | H25: =G25/G$4-1 -> -0.088754509
A26: 其他業務成長 低 | B26: 7% | C26: =E920 -> 7243.6024 | D26: =E928 -> 3020.02 | E26: =D26/D$4-1 -> -0.025061425 | F26: =F920 -> 5469.3215 | G26: =F928 -> 2192.5749 | H26: =G26/G$4-1 -> -0.071960546
A27: 其他業務成長 高 | B27: 17% | C27: =E960 -> 7576.5313 | D27: =E968 -> 3175.2832 | E27: =D27/D$4-1 -> 0.025061425 | F27: =F960 -> 6215.0822 | G27: =F968 -> 2540.3643 | H27: =G27/G$4-1 -> 0.075246416
A28: 營業費用變動比例 30% | C28: =E1000 -> 7410.0668 | D28: =E1008 -> 3095.1871 | E28: =D28/D$4-1 -> -0.00079558848 | F28: =F1000 -> 5833.8786 | G28: =F1008 -> 2330.1818 | H28: =G28/G$4-1 -> -0.013716429
A29: 營業費用變動比例 70% | C29: =E1040 -> 7410.0668 | D29: =E1048 -> 3100.1161 | E29: =D29/D$4-1 -> 0.00079558848 | F29: =F1040 -> 5833.8786 | G29: =F1048 -> 2394.9943 | H29: =G29/G$4-1 -> 0.013716429
A30: 淨利÷營業利益 0.72 | C30: =E1080 -> 7410.0668 | D30: =E1088 -> 2619.9879 | E30: =D30/D$4-1 -> -0.15420187 | F30: =F1080 -> 5833.8786 | G30: =F1088 -> 1998.2725 | H30: =G30/G$4-1 -> -0.15420187
A31: 淨利÷營業利益 0.95 | B31: 含一次性投資評價益，不當基準 | C31: =E1120 -> 7410.0668 | D31: =E1128 -> 3456.9285 | E31: =D31/D$4-1 -> 0.11598364 | F31: =F1120 -> 5833.8786 | G31: =F1128 -> 2636.6096 | H31: =G31/G$4-1 -> 0.11598364
A32: 顆數情境 B | B32: 2028 ×0.8、2029 ×0.85；混合鍵合基準；份額與其他成長 B | C32: =PL!E93 -> 7410.0668 | D32: =PL!E101 -> 3097.6516 | E32: =D32/D$4-1 -> 0 | F32: =PL!F93 -> 7041.281 | G32: =PL!F101 -> 2925.6664 | H32: =G32/G$4-1 -> 0.23833117
A33: 顆數情境 C | B33: 2028–29 ×0.6；混合鍵合低值（導入慢）；份額回落、毛利率下調 | C33: =PL!E126 -> 7410.0668 | D33: =PL!E134 -> 3097.6516 | E33: =D33/D$4-1 -> 0 | F33: =PL!F126 -> 5396.0074 | G33: =PL!F134 -> 2014.6763 | H33: =G33/G$4-1 -> -0.14725874
A35: 讀法：鍵合機比產能早一年買，FY2027 的需求看 CY2027→2028 的產能增量，所以顆數情境（2028 起）直接影響 FY2027。晶粒容量的影響大，是因為同樣位元下，容量提高會減少需要鍵合的晶粒數；校準係數 k 由 FY2025–26 兩年營收推得，各案例內重算。
A60: 案例區塊：SK 海力士份額 −10pt（情境 A）
A61: 項目 | B61: 單位 | C61: 2025 | D61: 2026 | E61: 2027 | F61: 2028 | G61: 2029 | H61: 2030 | I61: 說明
A62: A. 日曆年鍵合產能需求（本公司會計年度＝日曆年）
A63: HBM 出貨位元 | B63: EB | C63: =hsA_25 -> 2.2251147 | D63: =hsA_26 -> 3.782695 | E63: =hsA_27 -> 5.8631772 | F63: =hsA_28 -> 8.501607 | G63: =hsA_29 -> 11.477169 | H63: =G63*(1+g_tail) -> 12.624886 | I63: markets/memory；2030＝2029 ×（1＋g_tail）
A64: DRAM 晶粒容量 | B64: Gb | C64: =den_25 -> 24 | D64: =den_26 -> 24 | E64: =den_27 -> 26 | F64: =den_28 -> 28 | G64: =den_29 -> 30 | H64: =den_30 -> 32
A65: 核心晶粒數＝位元 × 8000 ÷ 容量 | B65: 百萬顆 | C65: =C63*8000/C64 -> 741.7049 | D65: =D63*8000/D64 -> 1260.8983 | E65: =E63*8000/E64 -> 1804.0545 | F65: =F63*8000/F64 -> 2429.0306 | G65: =G63*8000/G64 -> 3060.5785 | H65: =H63*8000/H64 -> 3156.2216 | I65: 1 EB＝8×10⁹ Gb；每顆核心晶粒鍵合一次
A66: 平均堆疊層數 | B66: 層 | C66: =stk_25 -> 10 | D66: =stk_26 -> 12 | E66: =stk_27 -> 12.5 | F66: =stk_28 -> 14 | G66: =stk_29 -> 15 | H66: =stk_30 -> 16
A67: 層數加權（每顆晶粒鍵合時間） | B67: x | C67: =1+beta*(C66-$C66)/4 -> 1 | D67: =1+beta*(D66-$C66)/4 -> 1.05 | E67: =1+beta*(E66-$C66)/4 -> 1.0625 | F67: =1+beta*(F66-$C66)/4 -> 1.1 | G67: =1+beta*(G66-$C66)/4 -> 1.125 | H67: =1+beta*(H66-$C66)/4 -> 1.15
A68: 混合鍵合占比 | B68: % | C68: =hbp_25 -> 0 | D68: =hbp_26 -> 0 | E68: =hbp_27 -> 0 | F68: =hbp_28_hi -> 0.15 | G68: =hbp_29_hi -> 0.3 | H68: =hbp_30_hi -> 0.4 | I68: 情境 A：CY2028 起 Disco 模型高值（導入快）
A69: TC 鍵合產能需求（晶粒 × 層數加權 ×（1 − 混合鍵合）） | B69: 百萬顆當量 | C69: =C65*C67*(1-C68) -> 741.7049 | D69: =D65*D67*(1-D68) -> 1323.9433 | E69: =E65*E67*(1-E68) -> 1916.8079 | F69: =F65*F67*(1-F68) -> 2271.1436 | G69: =G65*G67*(1-G68) -> 2410.2056 | H69: =H65*H67*(1-H68) -> 2177.7929
A70: 新機需求＝MAX(0, 下一年產能 − 本年)＋汰換 × 本年（CY2027 的下一年產能用三情境共同前提） | B70: 百萬顆當量 | C70: =MAX(0,D69-C69)+dlt*C69 -> 656.40884 | D70: =MAX(0,E69-D69)+dlt*D69 -> 725.25902 | E70: =MAX(0,hsA_28*8000/F64*F67*(1-hbp_28)-E69)+dlt*E69 -> 813.2098 | F70: =MAX(0,G69-F69)+dlt*F69 -> 366.17636 | G70: =MAX(0,H69-G69)+dlt*G69 -> 241.02056 | I70: 鍵合機在產能需要前一年購入；v0.2.1：CY2027 購機的 CY2028 產能＝情境 A 的 HBM 位元（hsA_28）× 混合鍵合基準，三情境相同（與 markets/equipment 2027 三情境相同、記憶體供給三情境相同一致）；CY2028 起照讀本情境
A71: SK 海力士 占產能增量（t＋1 年 HBM 市占，三家正規化） | B71: % | C71: =ms_sk_26/(ms_sk_26+ms_ss_26+ms_mu_26) -> 0.52 | D71: =ms_sk_27/(ms_sk_27+ms_ss_27+ms_mu_27) -> 0.42 | E71: =ms_sk_28/(ms_sk_28+ms_ss_28+ms_mu_28) -> 0.4 | F71: =ms_sk_29/(ms_sk_29+ms_ss_29+ms_mu_29) -> 0.4 | G71: =ms_sk_29/(ms_sk_29+ms_ss_29+ms_mu_29) -> 0.4
A72: 三星 占產能增量（t＋1 年 HBM 市占，三家正規化） | B72: % | C72: =ms_ss_26/(ms_sk_26+ms_ss_26+ms_mu_26) -> 0.29 | D72: =ms_ss_27/(ms_sk_27+ms_ss_27+ms_mu_27) -> 0.38 | E72: =ms_ss_28/(ms_sk_28+ms_ss_28+ms_mu_28) -> 0.4 | F72: =ms_ss_29/(ms_sk_29+ms_ss_29+ms_mu_29) -> 0.4 | G72: =ms_ss_29/(ms_sk_29+ms_ss_29+ms_mu_29) -> 0.4
A73: 美光 占產能增量（t＋1 年 HBM 市占，三家正規化） | B73: % | C73: =ms_mu_26/(ms_sk_26+ms_ss_26+ms_mu_26) -> 0.19 | D73: =ms_mu_27/(ms_sk_27+ms_ss_27+ms_mu_27) -> 0.2 | E73: =ms_mu_28/(ms_sk_28+ms_ss_28+ms_mu_28) -> 0.2 | F73: =ms_mu_29/(ms_sk_29+ms_ss_29+ms_mu_29) -> 0.2 | G73: =ms_mu_29/(ms_sk_29+ms_ss_29+ms_mu_29) -> 0.2
A74: 韓美加權份額＝Σ 占比 × 韓美在該廠份額 | B74: % | C74: =C71*hsk_25+C72*hss+C73*hmu_25 -> 0.412 | D74: =D71*hsk_A_lo+D72*hss+D73*hmu_A -> 0.297 | E74: =E71*hsk_A_lo+E72*hss+E73*hmu_A -> 0.29 | F74: =F71*hsk_A_lo+F72*hss+F73*hmu_A -> 0.29 | G74: =G71*hsk_A_lo+G72*hss+G73*hmu_A -> 0.29
A75: 韓美可得新機需求＝新機需求 × 加權份額 | B75: 百萬顆當量 | C75: =C70*C74 -> 270.44044 | D75: =D70*D74 -> 215.40193 | E75: =E70*E74 -> 235.83084 | F75: =F70*F74 -> 106.19114 | G75: =G70*G74 -> 69.895962
A76: B. 損益（會計年度；FY2026＝錨點）
A77: 其他業務營收（中國 TC 鍵合機、MSVP、EMI、2.5D 等） | B77: ₩億 | C77: =a25_rev-a25_hbm -> 2895.034 | D77: =C77*(1+g_o26) -> 3329.2891 | E77: =D77*(1+g_o_A) -> 3728.8038 | F77: =E77*(1+g_o_A) -> 4176.2602 | G77: =F77*(1+g_o_A) -> 4677.4115 | I77: v0.2.1：FY2027 三情境共用 g_o_A，FY2028 起讀 g_o_{情境}
A78: HBM TC 鍵合機營收（三大記憶體廠） | B78: ₩億 | C78: =a25_hbm -> 2871.966 | D78: =rev26-D77 -> 4210.5109 | E78: =$C79*E75 -> 3437.8774 | F78: =$C79*F75 -> 1548.0254 | G78: =$C79*G75 -> 1018.9242 | I78: FY2026＝錨點營收 − 其他；FY2027 起＝k × 可得新機需求
A79: 校準係數 k＝(FY2025＋FY2026 HBM 營收) ÷ (兩年可得新機需求) | B79: ₩億／百萬顆 | C79: =(C78+D78)/(C75+D75) -> 14.577726 | I79: 兩年平均，平滑訂單的季節與交期波動；不使用共識
A80: 營收 | B80: ₩億 | C80: =a25_rev -> 5767 | D80: =D77+D78 -> 7539.8 | E80: =E77+E78 -> 7166.6812 | F80: =F77+F78 -> 5724.2856 | G80: =G77+G78 -> 5696.3357
A81: HBM TC 鍵合機占營收 | B81: % | C81: =C78/C80 -> 0.498 | D81: =D78/D80 -> 0.55843801 | E81: =E78/E80 -> 0.47970285 | F81: =F78/F80 -> 0.27043119 | G81: =G78/G80 -> 0.17887362
A82: 營業費用 | B82: ₩億 | C82: =opex25 -> 806.7 | D82: =opex_fix+opex_var*D80 -> 930.69148 | E82: =opex_fix+opex_var*E80 -> 904.59516 | F82: =opex_fix+opex_var*F80 -> 803.71251 | G82: =opex_fix+opex_var*G80 -> 801.75766 | I82: 固定＋變動 × 營收
A83: 毛利率 | B83: % | C83: =a25_gp/a25_rev -> 0.57579331 | D83: =(oi26+D82)/D80 -> 0.59526718 | E83: =$D83+0 -> 0.59526718 | F83: =$D83+0 -> 0.59526718 | G83: =$D83+0 -> 0.59526718 | I83: FY2026＝錨點營業利益反推（Derived）；FY2027 起沿用（情境 C 另扣價格競爭）
A84: 毛利 | B84: ₩億 | C84: =C80*C83 -> 3320.6 | D84: =D80*D83 -> 4488.1955 | E84: =E80*E83 -> 4266.0901 | F84: =F80*F83 -> 3407.4794 | G84: =G80*G83 -> 3390.8417
A85: 營業利益 | B85: ₩億 | C85: =a25_oi -> 2513.9 | D85: =oi26 -> 3557.504 | E85: =E84-E82 -> 3361.4949 | F85: =F84-F82 -> 2603.7669 | G85: =G84-G82 -> 2589.084
A86: 營業利益率 | B86: % | C86: =C85/C80 -> 0.43591122 | D86: =D85/D80 -> 0.47183002 | E86: =E85/E80 -> 0.46904485 | F86: =F85/F80 -> 0.4548632 | G86: =G85/G80 -> 0.45451746
A87: 淨利 | B87: ₩億 | C87: =a25_ni -> 2140 | D87: =D85*nioi -> 3028.3856 | E87: =E85*nioi -> 2861.5295 | F87: =F85*nioi -> 2216.5007 | G87: =G85*nioi -> 2204.0017
A88: EPS | B88: ₩ | C88: =a25_eps -> 2231.7 | D88: =D87*100/shares -> 3158.1533 | E88: =E87*100/shares -> 2984.1474 | F88: =F87*100/shares -> 2311.4788 | G88: =G87*100/shares -> 2298.4442
A89: 三大廠 HBM TC 鍵合機市場（全部供應商）＝k × 新機需求 | B89: ₩億 | C89: =$C79*C70 -> 9568.9481 | D89: =$C79*D70 -> 10572.627 | E89: =$C79*E70 -> 11854.75 | F89: =$C79*F70 -> 5338.0186 | G89: =$C79*G70 -> 3513.5316 | I89: 對帳用
A90: 同上（美元） | B90: US$M | C90: =C89/fx*100 -> 673.86958 | D90: =D89/fx*100 -> 744.55121 | E90: =E89/fx*100 -> 834.84152 | F90: =F89/fx*100 -> 375.9168 | G90: =G89/fx*100 -> 247.43181
A100: 案例區塊：SK 海力士份額 +10pt（情境 A）
A101: 項目 | B101: 單位 | C101: 2025 | D101: 2026 | E101: 2027 | F101: 2028 | G101: 2029 | H101: 2030 | I101: 說明
A102: A. 日曆年鍵合產能需求（本公司會計年度＝日曆年）
A103: HBM 出貨位元 | B103: EB | C103: =hsA_25 -> 2.2251147 | D103: =hsA_26 -> 3.782695 | E103: =hsA_27 -> 5.8631772 | F103: =hsA_28 -> 8.501607 | G103: =hsA_29 -> 11.477169 | H103: =G103*(1+g_tail) -> 12.624886 | I103: markets/memory；2030＝2029 ×（1＋g_tail）
A104: DRAM 晶粒容量 | B104: Gb | C104: =den_25 -> 24 | D104: =den_26 -> 24 | E104: =den_27 -> 26 | F104: =den_28 -> 28 | G104: =den_29 -> 30 | H104: =den_30 -> 32
A105: 核心晶粒數＝位元 × 8000 ÷ 容量 | B105: 百萬顆 | C105: =C103*8000/C104 -> 741.7049 | D105: =D103*8000/D104 -> 1260.8983 | E105: =E103*8000/E104 -> 1804.0545 | F105: =F103*8000/F104 -> 2429.0306 | G105: =G103*8000/G104 -> 3060.5785 | H105: =H103*8000/H104 -> 3156.2216 | I105: 1 EB＝8×10⁹ Gb；每顆核心晶粒鍵合一次
A106: 平均堆疊層數 | B106: 層 | C106: =stk_25 -> 10 | D106: =stk_26 -> 12 | E106: =stk_27 -> 12.5 | F106: =stk_28 -> 14 | G106: =stk_29 -> 15 | H106: =stk_30 -> 16
A107: 層數加權（每顆晶粒鍵合時間） | B107: x | C107: =1+beta*(C106-$C106)/4 -> 1 | D107: =1+beta*(D106-$C106)/4 -> 1.05 | E107: =1+beta*(E106-$C106)/4 -> 1.0625 | F107: =1+beta*(F106-$C106)/4 -> 1.1 | G107: =1+beta*(G106-$C106)/4 -> 1.125 | H107: =1+beta*(H106-$C106)/4 -> 1.15
A108: 混合鍵合占比 | B108: % | C108: =hbp_25 -> 0 | D108: =hbp_26 -> 0 | E108: =hbp_27 -> 0 | F108: =hbp_28_hi -> 0.15 | G108: =hbp_29_hi -> 0.3 | H108: =hbp_30_hi -> 0.4 | I108: 情境 A：CY2028 起 Disco 模型高值（導入快）
A109: TC 鍵合產能需求（晶粒 × 層數加權 ×（1 − 混合鍵合）） | B109: 百萬顆當量 | C109: =C105*C107*(1-C108) -> 741.7049 | D109: =D105*D107*(1-D108) -> 1323.9433 | E109: =E105*E107*(1-E108) -> 1916.8079 | F109: =F105*F107*(1-F108) -> 2271.1436 | G109: =G105*G107*(1-G108) -> 2410.2056 | H109: =H105*H107*(1-H108) -> 2177.7929
A110: 新機需求＝MAX(0, 下一年產能 − 本年)＋汰換 × 本年（CY2027 的下一年產能用三情境共同前提） | B110: 百萬顆當量 | C110: =MAX(0,D109-C109)+dlt*C109 -> 656.40884 | D110: =MAX(0,E109-D109)+dlt*D109 -> 725.25902 | E110: =MAX(0,hsA_28*8000/F104*F107*(1-hbp_28)-E109)+dlt*E109 -> 813.2098 | F110: =MAX(0,G109-F109)+dlt*F109 -> 366.17636 | G110: =MAX(0,H109-G109)+dlt*G109 -> 241.02056 | I110: 鍵合機在產能需要前一年購入；v0.2.1：CY2027 購機的 CY2028 產能＝情境 A 的 HBM 位元（hsA_28）× 混合鍵合基準，三情境相同（與 markets/equipment 2027 三情境相同、記憶體供給三情境相同一致）；CY2028 起照讀本情境
A111: SK 海力士 占產能增量（t＋1 年 HBM 市占，三家正規化） | B111: % | C111: =ms_sk_26/(ms_sk_26+ms_ss_26+ms_mu_26) -> 0.52 | D111: =ms_sk_27/(ms_sk_27+ms_ss_27+ms_mu_27) -> 0.42 | E111: =ms_sk_28/(ms_sk_28+ms_ss_28+ms_mu_28) -> 0.4 | F111: =ms_sk_29/(ms_sk_29+ms_ss_29+ms_mu_29) -> 0.4 | G111: =ms_sk_29/(ms_sk_29+ms_ss_29+ms_mu_29) -> 0.4
A112: 三星 占產能增量（t＋1 年 HBM 市占，三家正規化） | B112: % | C112: =ms_ss_26/(ms_sk_26+ms_ss_26+ms_mu_26) -> 0.29 | D112: =ms_ss_27/(ms_sk_27+ms_ss_27+ms_mu_27) -> 0.38 | E112: =ms_ss_28/(ms_sk_28+ms_ss_28+ms_mu_28) -> 0.4 | F112: =ms_ss_29/(ms_sk_29+ms_ss_29+ms_mu_29) -> 0.4 | G112: =ms_ss_29/(ms_sk_29+ms_ss_29+ms_mu_29) -> 0.4
A113: 美光 占產能增量（t＋1 年 HBM 市占，三家正規化） | B113: % | C113: =ms_mu_26/(ms_sk_26+ms_ss_26+ms_mu_26) -> 0.19 | D113: =ms_mu_27/(ms_sk_27+ms_ss_27+ms_mu_27) -> 0.2 | E113: =ms_mu_28/(ms_sk_28+ms_ss_28+ms_mu_28) -> 0.2 | F113: =ms_mu_29/(ms_sk_29+ms_ss_29+ms_mu_29) -> 0.2 | G113: =ms_mu_29/(ms_sk_29+ms_ss_29+ms_mu_29) -> 0.2
A114: 韓美加權份額＝Σ 占比 × 韓美在該廠份額 | B114: % | C114: =C111*hsk_25+C112*hss+C113*hmu_25 -> 0.412 | D114: =D111*hsk_A_hi+D112*hss+D113*hmu_A -> 0.381 | E114: =E111*hsk_A_hi+E112*hss+E113*hmu_A -> 0.37 | F114: =F111*hsk_A_hi+F112*hss+F113*hmu_A -> 0.37 | G114: =G111*hsk_A_hi+G112*hss+G113*hmu_A -> 0.37
A115: 韓美可得新機需求＝新機需求 × 加權份額 | B115: 百萬顆當量 | C115: =C110*C114 -> 270.44044 | D115: =D110*D114 -> 276.32369 | E115: =E110*E114 -> 300.88763 | F115: =F110*F114 -> 135.48525 | G115: =G110*G114 -> 89.177607
A116: B. 損益（會計年度；FY2026＝錨點）
A117: 其他業務營收（中國 TC 鍵合機、MSVP、EMI、2.5D 等） | B117: ₩億 | C117: =a25_rev-a25_hbm -> 2895.034 | D117: =C117*(1+g_o26) -> 3329.2891 | E117: =D117*(1+g_o_A) -> 3728.8038 | F117: =E117*(1+g_o_A) -> 4176.2602 | G117: =F117*(1+g_o_A) -> 4677.4115 | I117: v0.2.1：FY2027 三情境共用 g_o_A，FY2028 起讀 g_o_{情境}
A118: HBM TC 鍵合機營收（三大記憶體廠） | B118: ₩億 | C118: =a25_hbm -> 2871.966 | D118: =rev26-D117 -> 4210.5109 | E118: =$C119*E115 -> 3897.5301 | F118: =$C119*F115 -> 1755.0002 | G118: =$C119*G115 -> 1155.1569 | I118: FY2026＝錨點營收 − 其他；FY2027 起＝k × 可得新機需求
A119: 校準係數 k＝(FY2025＋FY2026 HBM 營收) ÷ (兩年可得新機需求) | B119: ₩億／百萬顆 | C119: =(C118+D118)/(C115+D115) -> 12.953441 | I119: 兩年平均，平滑訂單的季節與交期波動；不使用共識
A120: 營收 | B120: ₩億 | C120: =a25_rev -> 5767 | D120: =D117+D118 -> 7539.8 | E120: =E117+E118 -> 7626.3339 | F120: =F117+F118 -> 5931.2605 | G120: =G117+G118 -> 5832.5683
A121: HBM TC 鍵合機占營收 | B121: % | C121: =C118/C120 -> 0.498 | D121: =D118/D120 -> 0.55843801 | E121: =E118/E120 -> 0.51106209 | F121: =F118/F120 -> 0.29588993 | G121: =G118/G120 -> 0.19805286
A122: 營業費用 | B122: ₩億 | C122: =opex25 -> 806.7 | D122: =opex_fix+opex_var*D120 -> 930.69148 | E122: =opex_fix+opex_var*E120 -> 936.74375 | F122: =opex_fix+opex_var*F120 -> 818.18855 | G122: =opex_fix+opex_var*G120 -> 811.28592 | I122: 固定＋變動 × 營收
A123: 毛利率 | B123: % | C123: =a25_gp/a25_rev -> 0.57579331 | D123: =(oi26+D122)/D120 -> 0.59526718 | E123: =$D123+0 -> 0.59526718 | F123: =$D123+0 -> 0.59526718 | G123: =$D123+0 -> 0.59526718 | I123: FY2026＝錨點營業利益反推（Derived）；FY2027 起沿用（情境 C 另扣價格競爭）
A124: 毛利 | B124: ₩億 | C124: =C120*C123 -> 3320.6 | D124: =D120*D123 -> 4488.1955 | E124: =E120*E123 -> 4539.7063 | F124: =F120*F123 -> 3530.6847 | G124: =G120*G123 -> 3471.9365
A125: 營業利益 | B125: ₩億 | C125: =a25_oi -> 2513.9 | D125: =oi26 -> 3557.504 | E125: =E124-E122 -> 3602.9625 | F125: =F124-F122 -> 2712.4961 | G125: =G124-G122 -> 2660.6506
A126: 營業利益率 | B126: % | C126: =C125/C120 -> 0.43591122 | D126: =D125/D120 -> 0.47183002 | E126: =E125/E120 -> 0.47243703 | F126: =F125/F120 -> 0.45732204 | G126: =G125/G120 -> 0.45617135
A127: 淨利 | B127: ₩億 | C127: =a25_ni -> 2140 | D127: =D125*nioi -> 3028.3856 | E127: =E125*nioi -> 3067.0829 | F127: =F125*nioi -> 2309.0583 | G127: =G125*nioi -> 2264.9239
A128: EPS | B128: ₩ | C128: =a25_eps -> 2231.7 | D128: =D127*100/shares -> 3158.1533 | E128: =E127*100/shares -> 3198.5089 | F128: =F127*100/shares -> 2408.0026 | G128: =G127*100/shares -> 2361.977
A129: 三大廠 HBM TC 鍵合機市場（全部供應商）＝k × 新機需求 | B129: ₩億 | C129: =$C119*C110 -> 8502.7532 | D129: =$C119*D110 -> 9394.6 | E129: =$C119*E110 -> 10533.865 | F129: =$C119*F110 -> 4743.2439 | G129: =$C119*G110 -> 3122.0456 | I129: 對帳用
A130: 同上（美元） | B130: US$M | C130: =C129/fx*100 -> 598.78544 | D130: =D129/fx*100 -> 661.59155 | E130: =E129/fx*100 -> 741.82149 | F130: =F129/fx*100 -> 334.03126 | G130: =G129/fx*100 -> 219.86237
A140: 案例區塊：美光份額 −10pt（情境 A）
A141: 項目 | B141: 單位 | C141: 2025 | D141: 2026 | E141: 2027 | F141: 2028 | G141: 2029 | H141: 2030 | I141: 說明
A142: A. 日曆年鍵合產能需求（本公司會計年度＝日曆年）
A143: HBM 出貨位元 | B143: EB | C143: =hsA_25 -> 2.2251147 | D143: =hsA_26 -> 3.782695 | E143: =hsA_27 -> 5.8631772 | F143: =hsA_28 -> 8.501607 | G143: =hsA_29 -> 11.477169 | H143: =G143*(1+g_tail) -> 12.624886 | I143: markets/memory；2030＝2029 ×（1＋g_tail）
A144: DRAM 晶粒容量 | B144: Gb | C144: =den_25 -> 24 | D144: =den_26 -> 24 | E144: =den_27 -> 26 | F144: =den_28 -> 28 | G144: =den_29 -> 30 | H144: =den_30 -> 32
...

Sheet Sources
A1: 來源（DART 原文在建置環境無法開啟；Naver、FnGuide 頁面被擋；數字取自新聞稿報導與財務資料頁，原文待人工複核）
A2: 亞洲經濟：2025 年創社最大營收 5,767、營益率 43.6%、TC 鍵合機市占 71.2%（2026-02-09） | B2: https://view.asiae.co.kr/en/article/2026020908430125470
A3: ddaily：2026 第二季營收 2,511、營業利益 1,303（2026-07-14） | B3: https://www.ddaily.co.kr/page/view/2026071411214300568
A4: THE FACT：第一季 509／85、目標營收撤回（2026-08） | B4: https://news.tf.co.kr/read/economy/2350287.htm
A5: dealsite：BofA 下半年約 ₩5,200 億、美光加單（2026-07-22） | B5: https://dealsite.co.kr/articles/165650
A6: dealsite：2025 第二季、LS 證券客戶比重（2025-07-25） | B6: https://dealsite.co.kr/articles/145326
A7: heraldcorp：SK 海力士 ₩442 億訂單、上上人證券預估（2026-06-09） | B7: https://biz.heraldcorp.com/article/10778245
A8: newdaily：2024 客戶別營收（SK 海力士 2,996、美光 1,111）、漲價 25%（2025-04-02） | B8: https://biz.newdaily.co.kr/site/data/html/2025/04/02/2025040200057.html
A9: etfshopping：各季初步實績、共識營收、2026-10-23 收盤 | B9: https://etfshopping.com/stock/042700/earnings
A10: valueline：近 12 月損益（毛利、銷管費、淨利、EPS） | B10: https://www.valueline.co.kr/finance/income/042700
A11: stockanalysis：年度損益、年底市值 P/E（2021–2025） | B11: https://stockanalysis.com/quote/krx/042700/financials/ratios/
A12: butler.works：年度營收、營業利益、淨利 | B12: https://www.butler.works/ko/companies/00161383
A13: companiesmarketcap：年底 P/E（2016–2025） | B13: https://companiesmarketcap.com/hanmi-semiconductor/pe-ratio/
... A20: mydailybyte：週報（第三季 2026-11-06 公布） | B20: https://www.mydailybyte.com/littlebit/plus/weekly-report-042700-2026-10-19
A21: 市場層與上游成品：skhynix／samsung／micron／disco／markets/equipment 的 dist（本 repo）
A22: SemiAnalysis | B22: 未使用
