Workbook

Sheet 導覽
A1: Microsoft 收支與評價模型 — Excel 版 v0.1（更新 2026-10-09；與 HTML v0.1 同步；市價截至 2026-10-07 收盤）
A3: 這個活頁簿在回答什麼
A4: 一句話：AI 資本支出有沒有賺到資金成本：每 MW 收入能否覆蓋每 MW 全成本——Microsoft 用客戶預付款支應多少擴張資本支出，剩下的缺口要靠多少債務與新股。
A5: 所有分頁用同一組數字，改任何一個輸入，後面全部會跟著動。
A7: 分頁結構（依模組分組，分頁標籤顏色相同者為同一模組）
A8: 摘要 一頁摘要：結論、與市場共識的差異、現價隱含什麼、驗證點（全部活公式）。
A9: 輸入與假設 所有可調參數（A 情境 → B 產能與收入 → C 利潤率 → D 支出 → E 融資 → F 評價 → G 年初至今 實際 → H 情境區間運算表 → I 市場共識 → J 季度追蹤輸入）。
A10: 各期收支 類現金流量：來源（含客戶預付）、用途、融資前缺口、期前融資瀑布。
A11: 季度追蹤 焦點季的模型／共識／指引／實際與差距（由年度模型拆分，只用於追蹤；實際數填在輸入與假設 J 區）。
A12: 運營_產能與收入 已連網 MW → 在役 MW → 營收（MW × 每 MW 年收入 × 利用率）；RPO 排程只作對照與產能瓶頸旗標。
A13: 資產負債_既有債務／新債與新股／租賃承諾 類資產負債表：季報債務明細、每期現金與總債務與股數、租賃承諾。
A14: 損益 類損益表（FY27＝全年模型）。
... A42: DCF 以融資後股數計每股，並加回新股募得現金的現值；EV/EBITDA 用錨定年末淨負債與錨定年末股數。

Sheet 摘要
A1: 一頁摘要 — 結論、與市場的差異、現價隱含什麼、驗證點（全部依輸入連動）
A2: ="模型端＝目前情境：" & CHOOSE(輸入與假設!$C$5,"保守 第三方可辨識站點","基準 依資本支出指引","積極 依公司容量目標") & "（預設＝基準）；共識＝data/consensus_msft_20261008.json（2026-10-08）" -> 模型端＝目前情境：基準 依資本支出指引（預設＝基準）；共識＝data/consensus_msft_20261008.json（2026-10-08）
A4: 1｜結論
A5: 結論｜評等代碼（1＝買進、0＝中立、−1＝賣出） | C5: =評價_DCF與目標價!C99 -> -1
A6: 結論｜評等 | C6: =CHOOSE(C5+2,"賣出","中立","買進") -> 賣出
A7: 結論｜點位（加權目標價） | B7: US$ | C7: =評價_DCF與目標價!C51 -> 353.55323
A8: 結論｜現價 | B8: US$ | C8: =輸入與假設!$C$330 -> 529.76
A9: 結論｜空間 | B9: % | C9: =C7/C8-1 -> -0.33261623
A10: 結論｜情境區間（下緣／上緣） | B10: US$ | C10: =評價_DCF與目標價!C104 -> 351.96385 | D10: =評價_DCF與目標價!D104 -> 382.25279
A11: 結論｜方法區間（下緣／上緣） | B11: US$ | C11: =評價_DCF與目標價!C106 -> 348.77232 | D11: =評價_DCF與目標價!D106 -> 353.55323
A12: 結論｜賣出門檻價 | B12: US$ | C12: =評價_DCF與目標價!$C$100 -> 450.296
A13: 結論｜點位 − 賣出門檻 | B13: US$ | C13: =C7-C12 -> -96.742773
A14: 結論｜結論句 | C14: =C6&"：點位 $"&TEXT(C7,"0.0")&"，較現價 $"&TEXT(C8,"0.00")&" "&IF(C9>=0,"高","低")&" "&TEXT(ABS(C9)*100,"0")&"%；情境區間 $"&TEXT(C10,"0.0")&"–$"&TEXT(D10,"0.0")&"，方法區間 $"&TEXT(C11,"0.0")&"–$"&TEXT(D11,"0.0")&"；點位"&IF(C13<0,"低於","高於")&"賣出門檻 $"&TEXT(C12,"0.0")&" 達 $"&TEXT(ABS(C13),"0.0")&"。" -> 賣出：點位 $353.6，較現價 $529.76 低 33%；情境區間 $352.0–$382.3，方法區間 $348.8–$353.6；點位低於賣出門檻 $450.3 達 $96.7。
A15: 結論｜情境判斷句 | C15: =評價_DCF與目標價!C129 -> 情境區間上緣 $382.3 低於現價 $529.76：賣出在三個擴張情境下都成立。
A16: 結論｜投資級句 | C16: =IF(OR(輸入與假設!$C$298="ebitda",輸入與假設!$C$298="leaseAdj"),"需失去投資級才能融資的金額："&IF(SUM(各期收支!C93:G93)>0.05,"$"&TEXT(SUM(各期收支!C93:G93),"0.0")&"bn（五期高息債溢出）","$0")&"；投資級上限＝"&IF(輸入與假設!$C$298="leaseAdj","(總債務＋租賃負債) ≤ "&IF(輸入與假設!$C$299=INT(輸入與假設!$C$299),TEXT(輸入與假設!$C$299,"0"),TEXT(輸入與假設!$C$299,"0.0"))&"×(EBITDA＋租金)","總債務 ≤ "&IF(輸入與假設!$C$299=INT(輸入與假設!$C$299),TEXT(輸入與假設!$C$299,"0"),TEXT(輸入與假設!$C$299,"0.0"))&"× 當期 EBITDA")&"，股權每年 ≤ 現市值 "&IF(ROUND(ABS(輸入與假設!$C$309)*100,4)=INT(ROUND(ABS(輸入與假設!$C$309)*100,4)),TEXT(ROUND(ABS(輸入與假設!$C$309)*100,4),"0"),TEXT(ROUND(ABS(輸入與假設!$C$309)*100,4),"0.0"))&"%"&"。","") -> 需失去投資級才能融資的金額：$0；投資級上限＝(總債務＋租賃負債) ≤ 3×(EBITDA＋租金)，股權每年 ≤ 現市值 5%。
A17: 結論｜調整後槓桿句 | C17: ="調整後槓桿（(債務＋租賃負債) ÷ (EBITDA＋租金)）路徑 "&TEXT(資產負債_新債與新股!C37,"0.0")&"／"&TEXT(資產負債_新債與新股!D37,"0.0")&"／"&TEXT(資產負債_新債與新股!E37,"0.0")&"／"&TEXT(資產負債_新債與新股!F37,"0.0")&"／"&TEXT(資產負債_新債與新股!G37,"0.0")&"×；上限 "&IF(輸入與假設!$C$299=INT(輸入與假設!$C$299),TEXT(輸入與假設!$C$299,"0"),TEXT(輸入與假設!$C$299,"0.0"))&"×，"&IF(MAX(資產負債_新債與新股!$C$37:$G$37)>輸入與假設!$C$299+0.000000001,CHOOSE(MATCH(MAX(資產負債_新債與新股!$C$37:$G$37),資產負債_新債與新股!$C$37:$G$37,0),"FY27","FY28","FY29","FY30","FY31")&" 超過 "&TEXT(MAX(資產負債_新債與新股!$C$37:$G$37)-輸入與假設!$C$299,"0.0")&"×：需股權或失去投資級。","最小空間 "&TEXT(輸入與假設!$C$299-MAX(資產負債_新債與新股!$C$37:$G$37),"0.0")&"×（"&CHOOSE(MATCH(MAX(資產負債_新債與新股!$C$37:$G$37),資產負債_新債與新股!$C$37:$G$37,0),"FY27","FY28","FY29","FY30","FY31")&"）。") -> 調整後槓桿（(債務＋租賃負債) ÷ (EBITDA＋租金)）路徑 0.8／0.8／0.8／0.8／0.7×；上限 3×，最小空間 2.2×（FY30）。
A18: 結論｜評價口徑敏感度句 | C18: ="評價口徑敏感度："&"WACC 9% $"&TEXT(評價_DCF與目標價!C114,"0.00")&"（"&CHOOSE(評價_DCF與目標價!D114+2,"賣出","中立","買進")&"）"&"、"&"WACC 10% $"&TEXT(評價_DCF與目標價!C115,"0.00")&"（"&CHOOSE(評價_DCF與目標價!D115+2,"賣出","中立","買進")&"）"&"、"&"WACC 11% $"&TEXT(評價_DCF與目標價!C116,"0.00")&"（"&CHOOSE(評價_DCF與目標價!D116+2,"賣出","中立","買進")&"）"&"；"&"非 AI 分部改用公司自身 NTM EV/EBITDA 15.67× $"&TEXT(評價_DCF與目標價!C119,"0.00")&"（"&CHOOSE(評價_DCF與目標價!D119+2,"賣出","中立","買進")&"）"&"、"&"AI 雲端 15× $"&TEXT(評價_DCF與目標價!C120,"0.00")&"（"&CHOOSE(評價_DCF與目標價!D120+2,"賣出","中立","買進")&"）"&"、"&"組合：WACC 9%＋非 AI 自身倍數＋AI 15× $"&TEXT(評價_DCF與目標價!C121,"0.00")&"（"&CHOOSE(評價_DCF與目標價!D121+2,"賣出","中立","買進")&"）"&"；評等翻轉點："&"WACC 約 "&TEXT(評價_DCF與目標價!C122*100,"0.0")&"%（ERP "&TEXT(評價_DCF與目標價!D122*100,"0.00")&"%）以下由「賣出」轉為「中立」"&"。" -> 評價口徑敏感度：WACC 9% $411.72（賣出）、WACC 10% $377.46（賣出）、WACC 11% $351.09（賣出）；非 AI 分部改用公司自身 NTM EV/EBITDA 15.67× $414.84（賣出）、AI 雲端 15× $396.58（賣出）、組合：WACC 9%＋非 AI 自身倍數＋AI 15× $519.69（中立）；評等翻轉點：WACC 約 8.2%（ERP 2.56%）以下由「賣出」轉為「中立」。
A19: 結論｜終值占比規則句 | C19: ="評等規則：買進須空間 ≥ +"&IF(ROUND(ABS(輸入與假設!$C$419)*100,4)=INT(ROUND(ABS(輸入與假設!$C$419)*100,4)),TEXT(ROUND(ABS(輸入與假設!$C$419)*100,4),"0"),TEXT(ROUND(ABS(輸入與假設!$C$419)*100,4),"0.0"))&"%"&" 且終值占 EV < "&IF(ROUND(ABS(輸入與假設!$C$420)*100,4)=INT(ROUND(ABS(輸入與假設!$C$420)*100,4)),TEXT(ROUND(ABS(輸入與假設!$C$420)*100,4),"0"),TEXT(ROUND(ABS(輸入與假設!$C$420)*100,4),"0.0"))&"%"&"；目前終值占 EV "&TEXT(評價_DCF與目標價!C97*100,"0")&"%"&IF(評價_DCF與目標價!C97>=輸入與假設!$C$420,"，此規則下只可能「賣出」或「中立」","")&"（規則是否修改待 Andy 決定）。" -> 評等規則：買進須空間 ≥ +25% 且終值占 EV < 90%；目前終值占 EV 95%，此規則下只可能「賣出」或「中立」（規則是否修改待 Andy 決定）。
A20: 結論｜兩種讀法句 | C20: ="兩種讀法（自用 AI）：讀法 1（影子收入不進評價）$"&TEXT(評價_DCF與目標價!C51,"0.00")&"；讀法 2（自用 AI 價值中性：自用 MW 以 k＝1 計影子收入並進評價）$"&TEXT(評價_DCF與目標價!C73,"0.00")&"；差額 "&IF(評價_DCF與目標價!C73-評價_DCF與目標價!C51<0,"−","+")&"$"&TEXT(ABS(評價_DCF與目標價!C73-評價_DCF與目標價!C51),"0.00")&"。主值取哪一個是 Andy 的判斷（待決）。" -> 兩種讀法（自用 AI）：讀法 1（影子收入不進評價）$353.55；讀法 2（自用 AI 價值中性：自用 MW 以 k＝1 計影子收入並進評價）$422.48；差額 +$68.93。主值取哪一個是 Andy 的判斷（待決）。
A21: 結論｜對外比例句 | C21: ="對外比例無揭露（目前 "&TEXT(輸入與假設!$C$227*100,"0")&"%，[Assumed]），是最大不確定："&TEXT(評價_DCF與目標價!C112*100,"0")&"% → $"&TEXT(評價_DCF與目標價!D112,"0.00")&"、"&TEXT(評價_DCF與目標價!C113*100,"0")&"% → $"&TEXT(評價_DCF與目標價!D113,"0.00")&"（基準 $"&TEXT(評價_DCF與目標價!C51,"0.00")&"）。" -> 對外比例無揭露（目前 60%，[Assumed]），是最大不確定：40% → $283.83、80% → $383.95（基準 $353.55）。
A22: 結論｜主命題句 | C22: ="主命題（AI 資本支出有沒有賺到資金成本）：FY29 對外 AI ROIC "&TEXT(AI增量報酬!E23*100,"0.0")&"% vs WACC "&TEXT(輸入與假設!$C$349*100,"0.0")&"%（"&IF(AI增量報酬!E25<0,"−","+")&TEXT(ABS(AI增量報酬!E25)*100,"0.0")&"pt）；打平 k "&TEXT(AI增量報酬!C29,"0.00")&"（目前 "&TEXT(輸入與假設!$C$66,"0.00")&"）；全 AI（含影子收入）"&TEXT(AI增量報酬!E27*100,"0.0")&"%。" -> 主命題（AI 資本支出有沒有賺到資金成本）：FY29 對外 AI ROIC 10.1% vs WACC 10.9%（−0.8pt）；打平 k 1.08（目前 1.06）；全 AI（含影子收入）9.7%。
A23: 結論｜股東回饋與 FCF 句 | C23: ="股東回饋與 FCF：FCF "&IF(各期收支!C44<0,"首次為負 FY27（−$"&TEXT(-各期收支!C44,"0.0")&"bn）",IF(各期收支!D44<0,"首次為負 FY28（−$"&TEXT(-各期收支!D44,"0.0")&"bn）",IF(各期收支!E44<0,"首次為負 FY29（−$"&TEXT(-各期收支!E44,"0.0")&"bn）",IF(各期收支!F44<0,"首次為負 FY30（−$"&TEXT(-各期收支!F44,"0.0")&"bn）",IF(各期收支!G44<0,"首次為負 FY31（−$"&TEXT(-各期收支!G44,"0.0")&"bn）","五期皆為正")))))&"；"&IF(SUM(各期收支!C75:G75)<=0.05,"無回購計畫（減少回購步驟不適用）",IF(SUM(各期收支!C77:G77)>0,"回購被迫減少："&MID(IF(各期收支!C77>0.05,"、FY27 $"&TEXT(各期收支!C77,"0.0"),"")&IF(各期收支!D77>0.05,"、FY28 $"&TEXT(各期收支!D77,"0.0"),"")&IF(各期收支!E77>0.05,"、FY29 $"&TEXT(各期收支!E77,"0.0"),"")&IF(各期收支!F77>0.05,"、FY30 $"&TEXT(各期收支!F77,"0.0"),"")&IF(各期收支!G77>0.05,"、FY31 $"&TEXT(各期收支!G77,"0.0"),""),2,999)&"bn","回購未被迫減少"))&"；五期新債 $"&TEXT(SUM(各期收支!C86:G86)+SUM(各期收支!C93:G93),"0.0")&"bn、股權 $"&TEXT(SUM(各期收支!C92:G92),"0.0")&"bn。" -> 股東回饋與 FCF：FCF 五期皆為正；回購被迫減少：FY27 $22.3、FY28 $21.5、FY31 $12.7bn；五期新債 $19.9bn、股權 $0.0bn。
A24: 結論｜延誤句 | C24: =IF(運營_產能與收入!$C$50>0,"建設延誤 "&IF(運營_產能與收入!$C$50=INT(運營_產能與收入!$C$50),TEXT(運營_產能與收入!$C$50,"0"),TEXT(運營_產能與收入!$C$50,"0.0"))&" 個月（GPU 資本支出照原時程）：閒置資本（已支出、尚未產生收入）峰值 $"&TEXT(MAX(運營_產能與收入!$C$55:$G$55),"0.0")&"bn（"&CHOOSE(MATCH(MAX(運營_產能與收入!$C$55:$G$55),運營_產能與收入!$C$55:$G$55,0),"FY27","FY28","FY29","FY30","FY31")&" 末）。","建設延誤：本情境 0 個月（無閒置資本）。") -> 建設延誤：本情境 0 個月（無閒置資本）。
A26: 2｜與市場的差異（模型：目前情境 vs 共識；FY27–FY29）
A27: 項目 | B27: 單位 | C27: FY27 | D27: FY28 | E27: FY29
A28: 差異｜營收｜模型 | B28: US$bn | C28: =損益!C29 -> 397.44559 | D28: =損益!D29 -> 471.42433 | E28: =損益!E29 -> 545.53771
A29: 差異｜營收｜共識 | B29: US$bn | C29: =輸入與假設!$C$478 -> 391.271 | D29: =輸入與假設!$D$478 -> 467.955 | E29: =輸入與假設!$E$478 -> 569.502
A30: 差異｜營收｜差距 | B30: % | C30: =C28/C29-1 -> 0.015780847 | D30: =D28/D29-1 -> 0.0074138152 | E30: =E28/E29-1 -> -0.042079377
A31: 差異｜調整後 EBITDA｜模型 | B31: US$bn | C31: =輸入與假設!$C$448+損益!C22 -> 232.86728 | D31: =損益!D34 -> 282.29401 | E31: =損益!E34 -> 332.79101
A32: 差異｜調整後 EBITDA｜共識 | B32: US$bn | C32: =輸入與假設!$C$479 -> 239.452 | D32: =輸入與假設!$D$479 -> 295.606 | E32: =輸入與假設!$E$479 -> 372.456
A33: 差異｜調整後 EBITDA｜差距 | B33: % | C33: =C31/C32-1 -> -0.027499109 | D33: =D31/D32-1 -> -0.045032873 | E33: =E31/E32-1 -> -0.10649577 | I33: FY27 模型＝年初至今 實際調整後 EBITDA（輸入與假設 G 區，報導轉述 [Verified]）＋全年 模型
A34: 差異｜調整後 EBITDA｜差距（金額） | B34: US$bn | C34: =C31-C32 -> -6.5847167 | D34: =D31-D32 -> -13.311987 | E34: =E31-E32 -> -39.664987 | I34: 與 HTML 一頁摘要、市場共識分頁同一呈現；判斷門檻仍用上一列比例
A35: 差異｜EBITDA 率｜模型 | B35: % | C35: =C31/C28 -> 0.58590985 | D35: =D31/D28 -> 0.59881087 | E35: =E31/E28 -> 0.61002385
A36: 差異｜EBITDA 率｜共識 | B36: % | C36: =輸入與假設!$C$480 -> 0.61198504 | D36: =輸入與假設!$D$480 -> 0.63169749 | E36: =輸入與假設!$E$480 -> 0.65400297
A37: 差異｜EBITDA 率｜差距（百分點） | B37: pt | C37: =C35-C36 -> -0.026075197 | D37: =D35-D36 -> -0.032886626 | E37: =E35-E36 -> -0.043979124 | I37: EBITDA 率以百分點列差距，不納入判斷
A38: 差異｜CapEx（毛額）｜模型 | B38: US$bn | C38: =輸入與假設!$C$431+輸入與假設!C$287 -> 204.20173 | D38: =輸入與假設!D$287 -> 216.20736 | E38: =輸入與假設!E$287 -> 221.96544
A39: 差異｜CapEx（毛額）｜共識 | B39: US$bn | C39: =輸入與假設!$C$484 -> 192.827 | D39: =輸入與假設!$D$484 -> 216.787 | E39: =輸入與假設!$E$484 -> 251.173
A40: 差異｜CapEx（毛額）｜差距 | B40: % | C40: =C38/C39-1 -> 0.058989304 | D40: =D38/D39-1 -> -0.0026737764 | E40: =E38/E39-1 -> -0.11628462 | I40: 共識 CapEx 口徑未揭露；FY27＝年初至今 實際毛額＋全年 模型毛額
A41: 差異｜淨負債｜模型 | B41: US$bn | C41: =資產負債_新債與新股!C25 -> 6.8316593 | D41: =資產負債_新債與新股!D25 -> 6.8316593 | E41: =資產負債_新債與新股!E25 -> -11.928351
A42: 差異｜淨負債｜共識 | B42: US$bn | C42: =輸入與假設!$C$486 -> -51.842 | D42: =輸入與假設!$D$486 -> -38.829 | E42: =輸入與假設!$E$486 -> 99.57
A43: 差異｜淨負債｜差距 | B43: % | C43: =C41/C42-1 -> -1.1317785 | D43: =D41/D42-1 -> -1.1759422 | E43: =E41/E42-1 -> -1.1197986 | I43: 共識淨負債不含租賃、口徑未揭露：只列不判斷
A44: 差異｜淨負債｜差距（金額） | B44: US$bn | C44: =C41-C42 -> 58.673659 | D44: =D41-D42 -> 45.660659 | E44: =E41-E42 -> -111.49835 | I44: 與 HTML 一頁摘要、市場共識分頁同一呈現；判斷門檻仍用上一列比例
A45: 差異｜分歧項目（超過門檻者） | C45: =MID(IF(ABS(C30)>輸入與假設!$C$509,"、營收 "&IF(C30<0,"−","+")&TEXT(ABS(C30)*100,"0.0")&"%","")&IF(ABS(C33)>輸入與假設!$C$509,"、EBITDA "&IF(C34<0,"−","+")&"$"&TEXT(ABS(C34),"#,##0.00")&"bn"&"／"&IF(C37<0,"−","+")&TEXT(ABS(C37)*100,"0.0")&"pt","")&IF(ABS(C40)>輸入與假設!$C$509,"、CapEx "&IF(C40<0,"−","+")&TEXT(ABS(C40)*100,"0.0")&"%",""),2,999) -> CapEx +5.9% | D45: =MID(IF(ABS(D30)>輸入與假設!$C$509,"、營收 "&IF(D30<0,"−","+")&TEXT(ABS(D30)*100,"0.0")&"%","")&IF(ABS(D33)>輸入與假設!$C$509,"、EBITDA "&IF(D34<0,"−","+")&"$"&TEXT(ABS(D34),"#,##0.00")&"bn"&"／"&IF(D37<0,"−","+")&TEXT(ABS(D37)*100,"0.0")&"pt","")&IF(ABS(D40)>輸入與假設!$C$509,"、CapEx "&IF(D40<0,"−","+")&TEXT(ABS(D40)*100,"0.0")&"%",""),2,999) | E45: =MID(IF(ABS(E30)>輸入與假設!$C$509,"、營收 "&IF(E30<0,"−","+")&TEXT(ABS(E30)*100,"0.0")&"%","")&IF(ABS(E33)>輸入與假設!$C$509,"、EBITDA "&IF(E34<0,"−","+")&"$"&TEXT(ABS(E34),"#,##0.00")&"bn"&"／"&IF(E37<0,"−","+")&TEXT(ABS(E37)*100,"0.0")&"pt","")&IF(ABS(E40)>輸入與假設!$C$509,"、CapEx "&IF(E40<0,"−","+")&TEXT(ABS(E40)*100,"0.0")&"%",""),2,999) -> EBITDA −$39.66bn／−4.4pt、CapEx −11.6% | I45: 營收、EBITDA、CapEx 任一項差距絕對值超過門檻即列出（與 HTML 判斷句同一規則）
A46: 差異｜分歧起始年（1＝FY27…3＝FY29；0＝無） | C46: =IF(C45<>"",1,IF(D45<>"",2,IF(E45<>"",3,0))) -> 1
A47: 差異｜判斷句 | C47: =CHOOSE(C46+1,"FY27–FY29 營收、EBITDA、CapEx 與共識差距皆在 "&IF(ROUND(ABS(輸入與假設!$C$509)*100,4)=INT(ROUND(ABS(輸入與假設!$C$509)*100,4)),TEXT(ROUND(ABS(輸入與假設!$C$509)*100,4),"0"),TEXT(ROUND(ABS(輸入與假設!$C$509)*100,4),"0.0"))&"%"&" 以內。","分歧始於 FY27（"&C45&"）"&"；FY28 "&IF(D45="","回到 "&IF(ROUND(ABS(輸入與假設!$C$509)*100,4)=INT(ROUND(ABS(輸入與假設!$C$509)*100,4)),TEXT(ROUND(ABS(輸入與假設!$C$509)*100,4),"0"),TEXT(ROUND(ABS(輸入與假設!$C$509)*100,4),"0.0"))&"%"&" 以內",D45)&"；FY29 "&IF(E45="","回到 "&IF(ROUND(ABS(輸入與假設!$C$509)*100,4)=INT(ROUND(ABS(輸入與假設!$C$509)*100,4)),TEXT(ROUND(ABS(輸入與假設!$C$509)*100,4),"0"),TEXT(ROUND(ABS(輸入與假設!$C$509)*100,4),"0.0"))&"%"&" 以內",E45)&"。","FY27 營收、EBITDA、CapEx 與共識差距在 "&IF(ROUND(ABS(輸入與假設!$C$509)*100,4)=INT(ROUND(ABS(輸入與假設!$C$509)*100,4)),TEXT(ROUND(ABS(輸入與假設!$C$509)*100,4),"0"),TEXT(ROUND(ABS(輸入與假設!$C$509)*100,4),"0.0"))&"%"&" 以內；分歧始於 FY28（"&D45&"）"&"；FY29 "&IF(E45="","回到 "&IF(ROUND(ABS(輸入與假設!$C$509)*100,4)=INT(ROUND(ABS(輸入與假設!$C$509)*100,4)),TEXT(ROUND(ABS(輸入與假設!$C$509)*100,4),"0"),TEXT(ROUND(ABS(輸入與假設!$C$509)*100,4),"0.0"))&"%"&" 以內",E45)&"。","FY27–FY28 營收、EBITDA、CapEx 與共識差距在 "&IF(ROUND(ABS(輸入與假設!$C$509)*100,4)=INT(ROUND(ABS(輸入與假設!$C$509)*100,4)),TEXT(ROUND(ABS(輸入與假設!$C$509)*100,4),"0"),TEXT(ROUND(ABS(輸入與假設!$C$509)*100,4),"0.0"))&"%"&" 以內；分歧始於 FY29（"&E45&"）。") -> 分歧始於 FY27（CapEx +5.9%）；FY28 回到 5% 以內；FY29 EBITDA −$39.66bn／−4.4pt、CapEx −11.6%。
A48: 差異原因｜FY27｜營收 | C48: =IF(ABS(C30)>輸入與假設!$C$509,"觀點","") | D48: =IF(ABS(C30)>輸入與假設!$C$509,"營收＝對外 AI 雲端（年底 "&IF((輸入與假設!C$36)<0,"−","")&TEXT(ABS((輸入與假設!C$36)),"#,##0")&" MW-IT × 每 MW 年收入，Tokenomics × k）＋M365 雲端／授權／產業＋Frontier／搜尋與廣告／Windows＋XBOX／Azure 非 AI（近四季年增率收斂到長期值）；共識未揭露 MW 與單價假設","") | I48: C＝類型、D＝原因（需附原因時顯示；EBITDA 以利潤率差、其餘以比例門檻判斷）
A49: 差異原因｜FY27｜EBITDA | C49: =IF(ABS(C37)>輸入與假設!$C$510,"觀點","") -> 觀點 | D49: =IF(ABS(C37)>輸入與假設!$C$510,"營收差距 "&IF((C30)<0,"−","+")&TEXT(ABS((C30))*100,"#,##0.0")&"%"&"；EBITDA 率 "&IF((C35)<0,"−","")&TEXT(ABS((C35))*100,"#,##0.0")&"%"&" 對共識 "&IF((C36)<0,"−","")&TEXT(ABS((C36))*100,"#,##0.0")&"%"&"（各線 EBITDA 率＝分配營業利益率＋D&A 按營收分攤，五期固定；AI 雲端以 Tokenomics 營運成本推得；共識 EBITDA 口徑未揭露是否扣 SBC）","") -> 營收差距 +1.6%；EBITDA 率 58.6% 對共識 61.2%（各線 EBITDA 率＝分配營業利益率＋D&A 按營收分攤，五期固定；AI 雲端以 Tokenomics 營運成本推得；共識 EBITDA 口徑未揭露是否扣 SBC）
A50: 差異原因｜FY27｜CapEx | C50: =IF(ABS(C40)>輸入與假設!$C$509,"觀點","") -> 觀點 | D50: =IF(ABS(C40)>輸入與假設!$C$509,"CapEx：首期取 FY27 推估 204.2（公司口徑含融資租賃；共識推定現金口徑）；公司未給 FY28 以後指引 → 依新增 AI MW（"&IF((輸入與假設!C$254)<0,"−","")&TEXT(ABS((輸入與假設!C$254)),"#,##0")&" MW-IT 對外）÷ 對外比例 × 每 MW $"&IF((輸入與假設!C$235)<0,"−","")&TEXT(ABS((輸入與假設!C$235)),"#,##0")&"m＋非 AI 強度推導；基準情境 MW 速度由首期資本支出解出（對帳落差 0）","") -> CapEx：首期取 FY27 推估 204.2（公司口徑含融資租賃；共識推定現金口徑）；公司未給 FY28 以後指引 → 依新增 AI MW（2,326 MW-IT 對外）÷ 對外比例 × 每 MW $45m＋非 AI 強度推導；基準情境 MW 速度由首期資本支出解出（對帳落差 0）
A51: 差異原因｜FY27｜淨負債 | C51: =IF(ABS(C43)>輸入與假設!$C$509,"觀點","") -> 觀點 | D51: =IF(ABS(C43)>輸入與假設!$C$509,"淨負債隨 CapEx、投資與融資瀑布而定（模型 CapEx 差距 "&IF((C40)<0,"−","+")&TEXT(ABS((C40))*100,"#,##0.0")&"%"&"）；共識淨負債不含租賃","") -> 淨負債隨 CapEx、投資與融資瀑布而定（模型 CapEx 差距 +5.9%）；共識淨負債不含租賃
A52: 差異原因｜FY28｜營收 | C52: =IF(ABS(D30)>輸入與假設!$C$509,"觀點","") | D52: =IF(ABS(D30)>輸入與假設!$C$509,"營收＝對外 AI 雲端（年底 "&IF((輸入與假設!D$36)<0,"−","")&TEXT(ABS((輸入與假設!D$36)),"#,##0")&" MW-IT × 每 MW 年收入，Tokenomics × k）＋M365 雲端／授權／產業＋Frontier／搜尋與廣告／Windows＋XBOX／Azure 非 AI（近四季年增率收斂到長期值）；共識未揭露 MW 與單價假設","")
A53: 差異原因｜FY28｜EBITDA | C53: =IF(ABS(D37)>輸入與假設!$C$510,"觀點","") -> 觀點 | D53: =IF(ABS(D37)>輸入與假設!$C$510,"營收差距 "&IF((D30)<0,"−","+")&TEXT(ABS((D30))*100,"#,##0.0")&"%"&"；EBITDA 率 "&IF((D35)<0,"−","")&TEXT(ABS((D35))*100,"#,##0.0")&"%"&" 對共識 "&IF((D36)<0,"−","")&TEXT(ABS((D36))*100,"#,##0.0")&"%"&"（各線 EBITDA 率＝分配營業利益率＋D&A 按營收分攤，五期固定；AI 雲端以 Tokenomics 營運成本推得；共識 EBITDA 口徑未揭露是否扣 SBC）","") -> 營收差距 +0.7%；EBITDA 率 59.9% 對共識 63.2%（各線 EBITDA 率＝分配營業利益率＋D&A 按營收分攤，五期固定；AI 雲端以 Tokenomics 營運成本推得；共識 EBITDA 口徑未揭露是否扣 SBC）
A54: 差異原因｜FY28｜CapEx | C54: =IF(ABS(D40)>輸入與假設!$C$509,"觀點","") | D54: =IF(ABS(D40)>輸入與假設!$C$509,"CapEx：首期取 FY27 推估 204.2（公司口徑含融資租賃；共識推定現金口徑）；公司未給 FY28 以後指引 → 依新增 AI MW（"&IF((輸入與假設!D$254)<0,"−","")&TEXT(ABS((輸入與假設!D$254)),"#,##0")&" MW-IT 對外）÷ 對外比例 × 每 MW $"&IF((輸入與假設!D$235)<0,"−","")&TEXT(ABS((輸入與假設!D$235)),"#,##0")&"m＋非 AI 強度推導；基準情境 MW 速度由首期資本支出解出（對帳落差 0）","")
A55: 差異原因｜FY28｜淨負債 | C55: =IF(ABS(D43)>輸入與假設!$C$509,"觀點","") -> 觀點 | D55: =IF(ABS(D43)>輸入與假設!$C$509,"淨負債隨 CapEx、投資與融資瀑布而定（模型 CapEx 差距 "&IF((D40)<0,"−","+")&TEXT(ABS((D40))*100,"#,##0.0")&"%"&"）；共識淨負債不含租賃","") -> 淨負債隨 CapEx、投資與融資瀑布而定（模型 CapEx 差距 −0.3%）；共識淨負債不含租賃
A56: 差異原因｜FY29｜營收 | C56: =IF(ABS(E30)>輸入與假設!$C$509,"觀點","") | D56: =IF(ABS(E30)>輸入與假設!$C$509,"營收＝對外 AI 雲端（年底 "&IF((輸入與假設!E$36)<0,"−","")&TEXT(ABS((輸入與假設!E$36)),"#,##0")&" MW-IT × 每 MW 年收入，Tokenomics × k）＋M365 雲端／授權／產業＋Frontier／搜尋與廣告／Windows＋XBOX／Azure 非 AI（近四季年增率收斂到長期值）；共識未揭露 MW 與單價假設","")
A57: 差異原因｜FY29｜EBITDA | C57: =IF(ABS(E37)>輸入與假設!$C$510,"觀點","") -> 觀點 | D57: =IF(ABS(E37)>輸入與假設!$C$510,"營收差距 "&IF((E30)<0,"−","+")&TEXT(ABS((E30))*100,"#,##0.0")&"%"&"；EBITDA 率 "&IF((E35)<0,"−","")&TEXT(ABS((E35))*100,"#,##0.0")&"%"&" 對共識 "&IF((E36)<0,"−","")&TEXT(ABS((E36))*100,"#,##0.0")&"%"&"（各線 EBITDA 率＝分配營業利益率＋D&A 按營收分攤，五期固定；AI 雲端以 Tokenomics 營運成本推得；共識 EBITDA 口徑未揭露是否扣 SBC）","") -> 營收差距 −4.2%；EBITDA 率 61.0% 對共識 65.4%（各線 EBITDA 率＝分配營業利益率＋D&A 按營收分攤，五期固定；AI 雲端以 Tokenomics 營運成本推得；共識 EBITDA 口徑未揭露是否扣 SBC）
A58: 差異原因｜FY29｜CapEx | C58: =IF(ABS(E40)>輸入與假設!$C$509,"觀點","") -> 觀點 | D58: =IF(ABS(E40)>輸入與假設!$C$509,"CapEx：首期取 FY27 推估 204.2（公司口徑含融資租賃；共識推定現金口徑）；公司未給 FY28 以後指引 → 依新增 AI MW（"&IF((輸入與假設!E$254)<0,"−","")&TEXT(ABS((輸入與假設!E$254)),"#,##0")&" MW-IT 對外）÷ 對外比例 × 每 MW $"&IF((輸入與假設!E$235)<0,"−","")&TEXT(ABS((輸入與假設!E$235)),"#,##0")&"m＋非 AI 強度推導；基準情境 MW 速度由首期資本支出解出（對帳落差 0）","") -> CapEx：首期取 FY27 推估 204.2（公司口徑含融資租賃；共識推定現金口徑）；公司未給 FY28 以後指引 → 依新增 AI MW（2,326 MW-IT 對外）÷ 對外比例 × 每 MW $45m＋非 AI 強度推導；基準情境 MW 速度由首期資本支出解出（對帳落差 0）
A59: 差異原因｜FY29｜淨負債 | C59: =IF(ABS(E43)>輸入與假設!$C$509,"觀點","") -> 觀點 | D59: =IF(ABS(E43)>輸入與假設!$C$509,"淨負債隨 CapEx、投資與融資瀑布而定（模型 CapEx 差距 "&IF((E40)<0,"−","+")&TEXT(ABS((E40))*100,"#,##0.0")&"%"&"）；共識淨負債不含租賃","") -> 淨負債隨 CapEx、投資與融資瀑布而定（模型 CapEx 差距 −11.6%）；共識淨負債不含租賃
A60: 差異｜需附原因項數 | C60: =SUMPRODUCT(--(ABS(C30:E30)>輸入與假設!$C$509))+SUMPRODUCT(--(ABS(C37:E37)>輸入與假設!$C$510))+SUMPRODUCT(--(ABS(C40:E40)>輸入與假設!$C$509))+SUMPRODUCT(--(ABS(C43:E43)>輸入與假設!$C$509)) -> 8 | I60: 營收、EBITDA（利潤率差）、CapEx、淨負債 × FY27–FY29
A61: 差異｜差異原因摘要 | C61: =IF(C60=0,"","需附原因的 "&C60&" 項差距："&MID(IF((COUNTIF(C48,"觀點")+COUNTIF(C49,"觀點")+COUNTIF(C50,"觀點")+COUNTIF(C51,"觀點")+COUNTIF(C52,"觀點")+COUNTIF(C53,"觀點")+COUNTIF(C54,"觀點")+COUNTIF(C55,"觀點")+COUNTIF(C56,"觀點")+COUNTIF(C57,"觀點")+COUNTIF(C58,"觀點")+COUNTIF(C59,"觀點"))>0,"、觀點 "&(COUNTIF(C48,"觀點")+COUNTIF(C49,"觀點")+COUNTIF(C50,"觀點")+COUNTIF(C51,"觀點")+COUNTIF(C52,"觀點")+COUNTIF(C53,"觀點")+COUNTIF(C54,"觀點")+COUNTIF(C55,"觀點")+COUNTIF(C56,"觀點")+COUNTIF(C57,"觀點")+COUNTIF(C58,"觀點")+COUNTIF(C59,"觀點"))&" 項","")&IF((COUNTIF(C48,"拆法")+COUNTIF(C49,"拆法")+COUNTIF(C50,"拆法")+COUNTIF(C51,"拆法")+COUNTIF(C52,"拆法")+COUNTIF(C53,"拆法")+COUNTIF(C54,"拆法")+COUNTIF(C55,"拆法")+COUNTIF(C56,"拆法")+COUNTIF(C57,"拆法")+COUNTIF(C58,"拆法")+COUNTIF(C59,"拆法"))>0,"、拆法 "&(COUNTIF(C48,"拆法")+COUNTIF(C49,"拆法")+COUNTIF(C50,"拆法")+COUNTIF(C51,"拆法")+COUNTIF(C52,"拆法")+COUNTIF(C53,"拆法")+COUNTIF(C54,"拆法")+COUNTIF(C55,"拆法")+COUNTIF(C56,"拆法")+COUNTIF(C57,"拆法")+COUNTIF(C58,"拆法")+COUNTIF(C59,"拆法"))&" 項","")&IF((COUNTIF(C48,"已知限制")+COUNTIF(C49,"已知限制")+COUNTIF(C50,"已知限制")+COUNTIF(C51,"已知限制")+COUNTIF(C52,"已知限制")+COUNTIF(C53,"已知限制")+COUNTIF(C54,"已知限制")+COUNTIF(C55,"已知限制")+COUNTIF(C56,"已知限制")+COUNTIF(C57,"已知限制")+COUNTIF(C58,"已知限制")+COUNTIF(C59,"已知限制"))>0,"、已知限制 "&(COUNTIF(C48,"已知限制")+COUNTIF(C49,"已知限制")+COUNTIF(C50,"已知限制")+COUNTIF(C51,"已知限制")+COUNTIF(C52,"已知限制")+COUNTIF(C53,"已知限制")+COUNTIF(C54,"已知限制")+COUNTIF(C55,"已知限制")+COUNTIF(C56,"已知限制")+COUNTIF(C57,"已知限制")+COUNTIF(C58,"已知限制")+COUNTIF(C59,"已知限制"))&" 項","")&IF((C60-((COUNTIF(C48,"觀點")+COUNTIF(C49,"觀點")+COUNTIF(C50,"觀點")+COUNTIF(C51,"觀點")+COUNTIF(C52,"觀點")+COUNTIF(C53,"觀點")+COUNTIF(C54,"觀點")+COUNTIF(C55,"觀點")+COUNTIF(C56,"觀點")+COUNTIF(C57,"觀點")+COUNTIF(C58,"觀點")+COUNTIF(C59,"觀點"))+(COUNTIF(C48,"拆法")+COUNTIF(C49,"拆法")+COUNTIF(C50,"拆法")+COUNTIF(C51,"拆法")+COUNTIF(C52,"拆法")+COUNTIF(C53,"拆法")+COUNTIF(C54,"拆法")+COUNTIF(C55,"拆法")+COUNTIF(C56,"拆法")+COUNTIF(C57,"拆法")+COUNTIF(C58,"拆法")+COUNTIF(C59,"拆法"))+(COUNTIF(C48,"已知限制")+COUNTIF(C49,"已知限制")+COUNTIF(C50,"已知限制")+COUNTIF(C51,"已知限制")+COUNTIF(C52,"已知限制")+COUNTIF(C53,"已知限制")+COUNTIF(C54,"已知限制")+COUNTIF(C55,"已知限制")+COUNTIF(C56,"已知限制")+COUNTIF(C57,"已知限制")+COUNTIF(C58,"已知限制")+COUNTIF(C59,"已知限制"))))>0,"、未歸類 "&(C60-((COUNTIF(C48,"觀點")+COUNTIF(C49,"觀點")+COUNTIF(C50,"觀點")+COUNTIF(C51,"觀點")+COUNTIF(C52,"觀點")+COUNTIF(C53,"觀點")+COUNTIF(C54,"觀點")+COUNTIF(C55,"觀點")+COUNTIF(C56,"觀點")+COUNTIF(C57,"觀點")+COUNTIF(C58,"觀點")+COUNTIF(C59,"觀點"))+(COUNTIF(C48,"拆法")+COUNTIF(C49,"拆法")+COUNTIF(C50,"拆法")+COUNTIF(C51,"拆法")+COUNTIF(C52,"拆法")+COUNTIF(C53,"拆法")+COUNTIF(C54,"拆法")+COUNTIF(C55,"拆法")+COUNTIF(C56,"拆法")+COUNTIF(C57,"拆法")+COUNTIF(C58,"拆法")+COUNTIF(C59,"拆法"))+(COUNTIF(C48,"已知限制")+COUNTIF(C49,"已知限制")+COUNTIF(C50,"已知限制")+COUNTIF(C51,"已知限制")+COUNTIF(C52,"已知限制")+COUNTIF(C53,"已知限制")+COUNTIF(C54,"已知限制")+COUNTIF(C55,"已知限制")+COUNTIF(C56,"已知限制")+COUNTIF(C57,"已知限制")+COUNTIF(C58,"已知限制")+COUNTIF(C59,"已知限制"))))&" 項",""),2,999)&"；原因見「損益與評價 → 市場共識」。") -> 需附原因的 8 項差距：觀點 8 項；原因見「損益與評價 → 市場共識」。 | I61: 與 HTML 一頁摘要同一句
A63: 3｜現價隱含什麼
A64: 隱含｜共識平均目標價隱含 FY29 EV/EBITDA | B64: x | C64: =(輸入與假設!$C$460*輸入與假設!$C$331+輸入與假設!$E$486)/輸入與假設!$E$479 -> 12.026055 | I64: ＝（共識平均目標價 × 股數＋共識 FY29 淨負債）÷ 共識 FY29 調整後 EBITDA
A65: 隱含｜現價隱含 FY29 EV/EBITDA | B65: x | C65: =(輸入與假設!$C$330*輸入與假設!$C$331+輸入與假設!$E$486)/輸入與假設!$E$479 -> 10.868052 | I65: 同一共識 FY29 數字，價格換成現價
A66: 隱含｜模型方法區間上緣 | B66: x | C66: =MAX(輸入與假設!$C$396,輸入與假設!$C$397) -> 6 | I66: 模型 EV/EBITDA 腿（AI 雲端 倍數）錨定 FY29 並折回 2027-06-30，錨定年度與此不同
A67: 隱含｜模型 FY29 非 AI 事業 EBITDA | B67: US$bn | C67: =輸入與假設!E$205 -> 251.98267 | I67: × 非 AI 事業 EV/EBITDA 倍數，自共識隱含 EV 扣除
A68: 隱含｜共識平均目標價隱含 FY29 AI 雲端 EV/EBITDA | B68: x | C68: =IF(ABS((輸入與假設!$C$460*輸入與假設!$C$331+輸入與假設!$E$486-輸入與假設!E$205*輸入與假設!$C$392)/MAX(輸入與假設!$E$479-輸入與假設!E$205,0.01))<0.05,0,(輸入與假設!$C$460*輸入與假設!$C$331+輸入與假設!$E$486-輸入與假設!E$205*輸入與假設!$C$392)/MAX(輸入與假設!$E$479-輸入與假設!E$205,0.01)) -> 13.002336 | I68: ＝（隱含 EV − 非 AI 事業 EBITDA × 非 AI 事業倍數）÷（共識 EBITDA − 非 AI 事業 EBITDA）
A69: 隱含｜現價隱含 FY29 AI 雲端 EV/EBITDA | B69: x | C69: =IF(ABS((輸入與假設!$C$330*輸入與假設!$C$331+輸入與假設!$E$486-輸入與假設!E$205*輸入與假設!$C$392)/MAX(輸入與假設!$E$479-輸入與假設!E$205,0.01))<0.05,0,(輸入與假設!$C$330*輸入與假設!$C$331+輸入與假設!$E$486-輸入與假設!E$205*輸入與假設!$C$392)/MAX(輸入與假設!$E$479-輸入與假設!E$205,0.01)) -> 9.4222485 | I69: 同上，價格換成現價
A70: 隱含｜隱含倍數句 | C70: ="共識平均目標價 $"&TEXT(輸入與假設!$C$460,"0.00")&" 隱含 FY29 EV/EBITDA "&TEXT(C64,"0.0")&"x（扣除非 AI 事業 "&TEXT(輸入與假設!$C$392,"0.0")&"x × 模型 EBITDA $"&TEXT(C67,"0.0")&"bn 後，AI 雲端 "&TEXT(C68,"0.0")&"x），AI 雲端 倍數"&IF(ROUND(C68,1)>C66,"高於",IF(ROUND(C68,1)<C66,"低於","等於"))&"模型方法區間上緣 "&IF(C66=INT(C66),TEXT(C66,"0"),TEXT(C66,"0.0"))&"x；現價 $"&TEXT(輸入與假設!$C$330,"0.00")&" 隱含 "&TEXT(C65,"0.0")&"x（AI 雲端 "&TEXT(C69,"0.0")&"x）。" -> 共識平均目標價 $587.63 隱含 FY29 EV/EBITDA 12.0x（扣除非 AI 事業 11.6x × 模型 EBITDA $252.0bn 後，AI 雲端 13.0x），AI 雲端 倍數高於模型方法區間上緣 6x；現價 $529.76 隱含 10.9x（AI 雲端 9.4x）。
A71: 反向 DCF｜FY31 每 MW 年收入（目前／隱含／變動） | C71: =評價_反向DCF!B18 -> 13.0191 | D71: =評價_反向DCF!C18 -> 34.3118 | E71: =評價_反向DCF!D18 -> 1.6355 | I71: 快照（預設輸入）：見『評價_反向DCF』；改輸入後請以目標搜尋重算
A72: 反向 DCF｜每 MW 建置成本（目前／隱含／變動） | C72: =評價_反向DCF!B19 -> 45.1743 | D72: =評價_反向DCF!C19 -> 無解 | E72: =評價_反向DCF!D19 -> 無解
A73: 反向 DCF｜穩態 EBITDA 率（目前／隱含／變動 pt） | C73: =評價_反向DCF!B20 -> 0.79 | D73: =評價_反向DCF!C20 -> 無解 | E73: =評價_反向DCF!D20 -> 無解
A74: 反向 DCF｜加權目標價＝現價所需每 MW 年收入（目前／隱含／變動） | C74: =評價_反向DCF!B21 -> 13.0191 | D74: =評價_反向DCF!C21 -> 35.5259 | E74: =評價_反向DCF!D21 -> 1.7288
A76: 4｜驗證點與市場看法（賣方與管理層數字標記 Interested-party）
A77: 驗證｜焦點季 | C77: =季度追蹤!C12 -> Q1 FY27 | I77: 『輸入與假設』J 區選擇；季度層由年度模型拆分，只用於追蹤
A78: 驗證｜營收（模型／共識／指引低／指引高／實際） | B78: US$bn | C78: =季度追蹤!C6 -> 93.748759 | D78: =季度追蹤!D6 -> 90.685 | E78: =季度追蹤!F6 -> 89.85 | F78: =季度追蹤!G6 -> 90.95 | G78: =季度追蹤!I6 -> 待公布 | I78: 共識、指引為 Interested-party
A79: 驗證｜營收｜句 | C79: =INDEX(季度追蹤!$C$129:$H$129,輸入與假設!$C$515) -> 營收：模型 $93.75bn｜共識 $90.69bn（+3.4%）｜指引 $89.85–90.95bn（中點 +3.7%，高於上緣）〔觀點〕
A80: 驗證｜調整後營業利益（模型／共識／指引低／指引高／實際） | B80: US$bn | C80: =季度追蹤!C9 -> 41.008678 | D80: =季度追蹤!D9 -> 不適用 | E80: =季度追蹤!F9 -> 43.15 | F80: =季度追蹤!G9 -> 44.55 | G80: =季度追蹤!I9 -> 待公布 | I80: 共識、指引為 Interested-party
A81: 驗證｜調整後營業利益｜句 | C81: =INDEX(季度追蹤!$C$132:$H$132,輸入與假設!$C$515) -> 調整後營業利益：模型 $41.01bn｜指引 $43.15–44.55bn（中點 −$2.84bn／−4.8pt，低於下緣）〔觀點〕
A82: 驗證｜CapEx（毛額）（模型／共識／指引低／指引高／實際） | B82: US$bn | C82: =季度追蹤!C10 -> 51.050433 | D82: =季度追蹤!D10 -> 不適用 | E82: =季度追蹤!F10 -> 不適用 | F82: =季度追蹤!G10 -> 不適用 | G82: =季度追蹤!I10 -> 待公布 | I82: 共識、指引為 Interested-party
A83: 驗證｜CapEx（毛額）｜句 | C83: =INDEX(季度追蹤!$C$133:$H$133,輸入與假設!$C$515) -> CapEx（毛額）：模型 $51.05bn
A84: 驗證｜評等分布（強力買進／買進／持有／賣出／強力賣出） | B84: 家 | C84: =輸入與假設!$C$471 -> 41 | D84: =輸入與假設!$C$472 -> 14 | E84: =輸入與假設!$C$473 -> 1 | F84: =輸入與假設!$C$474 -> 0 | G84: =輸入與假設!$C$475 -> 0 | I84: 2026-10，合計 56 家 [Interested-party]
A85: 驗證｜目標價（平均／中位數／最低／最高） | B85: US$ | C85: =輸入與假設!$C$460 -> 587.63 | D85: =輸入與假設!$C$461 -> 586 | E85: =輸入與假設!$C$462 -> 440 | F85: =輸入與假設!$C$463 -> 870 | I85: 56 家；S&P Global Market Intelligence（經 StockAnalysis.com），擷取 2026-10-08 [Interested-party]
A87: 來源獨立性：StockAnalysis.com 的目標價、評等、FY27 營收與 EPS 引用 S&P Global Market Intelligence；MarketScreener 年度預估一般屬 S&P Capital IQ 系（與 ORCL、CRWV、NBIS 共識檔同一判斷），FY27 營收 391.271 對 S&P 391.3 一致，視為同一底層來源。Yahoo Finance 營收與 EPS 預估通常來自 LSEG：FY27 391.04（50 家）、FY28 467.31（51 家），與 MarketScreener 391.27／467.96 一致；但 Yahoo FY27 高低值（402.72／380.0）與 S&P 完全相同、分析師數同為 50 → 獨立性存疑，不視為強獨立交叉。MarketBeat 目標價與評等為自行彙整（獨立於 S&P），可作目標價的獨立交叉；Yahoo 目標價 587.63 與 S&P 相同，推測同源。
A88: 共識來源：MarketScreener（S&P Capital IQ 系共識）、S&P Global Market Intelligence（經 StockAnalysis.com）；擷取 2026-10-08。逐筆來源、日期與標記見『輸入與假設』I 區。

Sheet 輸入與假設
A1: 輸入（依類別排序；點左側 ＋／− 展開或收合。藍字可改；黃底為最關鍵假設）
A2: A 情境 → B 產能與收入 → C 利潤率 → D 支出（CapEx／折舊／租賃／JV）→ E 融資 → F 評價 → G 參考：年初至今 實際 → H 情境區間運算表 → I 市場共識 → J 季度追蹤輸入。灰底『▸』為明細子區，預設收合
A4: A｜情境與規模（管理層擴張力道）
A5: 情境選擇（1＝保守 第三方可辨識站點、2＝基準 依資本支出指引、3＝積極 依公司容量目標） | C5: 2 | D5: =CHOOSE(C5,"保守 第三方可辨識站點","基準 依資本支出指引","積極 依公司容量目標") -> 基準 依資本支出指引 | I5: 三情境只改容量軸（對外 AI MW 路徑；世代組合隨新增 MW 改變每 MW 年收入）；價格軸另見 B0（對照表 r1 第 5 節第 1 條）
A6: ▸ 情境路徑明細（已連網 MW、在役比例、表外租金基準）
A7: 已連網 MW 路徑 | B7: 單位 | C7: FY27 | D7: FY28 | E7: FY29 | F7: FY30 | G7: FY31 | I7: FY32 新增 MW
A8: 評價日在役 MW（期初計費，三情境共用） | B8: MW | C8: 3250 | I8: company.json → defaults.billableOpen；來源見 scenarios.mwPath.note（第三方估計，不以營收校準）[Derived／Assumed]
A9: 保守 第三方可辨識站點｜合約 MW 上限 | B9: MW | C9: 4386 | D9: 4386 | E9: 4386 | F9: 4386 | G9: 4386 | I9: company.json → scenarios.mwPath.contracted
A10: 保守 第三方可辨識站點｜併網速度 | B10: MW／年 | C10: 650 | I10: company.json → scenarios.mwPath.pace
A11: 保守 第三方可辨識站點 | B11: MW | C11: =MIN(C9,輸入與假設!$C$8+輸入與假設!$C$10*C$34) -> 3900 | D11: =MIN(D9,C11+輸入與假設!$C$10*D$34) -> 4386 | E11: =MIN(E9,D11+輸入與假設!$C$10*E$34) -> 4386 | F11: =MIN(F9,E11+輸入與假設!$C$10*F$34) -> 4386 | G11: =MIN(G9,F11+輸入與假設!$C$10*G$34) -> 4386 | I11: 0 | J11: 對外 AI MW-IT 只計 Epoch AI 可辨識站點的已交付＋在建：Fairwater Wisconsin 369 → 2028Q2 預測 2,263（+1,894，約 1.75 年）× 對外 60% → 每年 +650、上限 4,386（Atlanta 636 已全數運轉）[Derived]；I 欄＝FY32 新增 MW
A12: 基準 依資本支出指引｜合約 MW 上限 | B12: MW | C12: 99999 | D12: 99999 | E12: 99999 | F12: 99999 | G12: 99999 | I12: company.json → scenarios.mwPath.contracted
A13: 基準 依資本支出指引｜併網速度 | B13: MW／年 | C13: 2325.9 | I13: company.json → scenarios.mwPath.pace
A14: 基準 依資本支出指引 | B14: MW | C14: =MIN(C12,輸入與假設!$C$8+輸入與假設!$C$13*C$34) -> 5575.9 | D14: =MIN(D12,C14+輸入與假設!$C$13*D$34) -> 7901.8 | E14: =MIN(E12,D14+輸入與假設!$C$13*E$34) -> 10227.7 | F14: =MIN(F12,E14+輸入與假設!$C$13*F$34) -> 12553.6 | G14: =MIN(G12,F14+輸入與假設!$C$13*G$34) -> 14879.5 | I14: 2325.9 | J14: 對外 AI MW 新增速度＝近端資本支出隱含的建置量：FY27 資本支出（公司口徑含融資租賃）204.2 −（非 AI 公式值＋GPU 汰換）÷ 每 MW 全成本（Tokenomics IT＋自建比例 × 機房）× 對外 60%，依 λ 遞延上線（scripts/calib_pace.js 解，對帳落差＝0）；之後各年資本支出＝MW 路徑 × 每 MW 成本（同一套數字）[Derived]。FY27 資本支出＝2 ×（曆年 2026 約 175 − FY26 下半年實際 72.9）＝204.2（下半年＝上半年；FY27Q1 指引 >50 吻合）；I 欄＝FY32 新增 MW
A15: 積極 依公司容量目標｜合約 MW 上限 | B15: MW | C15: 99999 | D15: 99999 | E15: 99999 | F15: 99999 | G15: 99999 | I15: company.json → scenarios.mwPath.contracted
A16: 積極 依公司容量目標｜併網速度 | B16: MW／年 | C16: 2400 | I16: company.json → scenarios.mwPath.pace
A17: 積極 依公司容量目標 | B17: MW | C17: =MIN(C15,輸入與假設!$C$8+輸入與假設!$C$16*C$34) -> 5650 | D17: =MIN(D15,C17+輸入與假設!$C$16*D$34) -> 8050 | E17: =MIN(E15,D17+輸入與假設!$C$16*E$34) -> 10450 | F17: =MIN(F15,E17+輸入與假設!$C$16*F$34) -> 12850 | G17: =MIN(G15,F17+輸入與假設!$C$16*G$34) -> 15250 | I17: 2400 | J17: 公司目標：總產能約兩年翻倍（FY26 起多次重申）。以 Bloomberg 總容量約 12 GW（2026-09，口徑不明）為基數 → 每年 +6 GW（設施）× AI 占新增 80%（70%–90% 中點）÷ PUE 1.2 × 對外 60%＝每年 +2,400 MW-IT [Derived；總容量為第三方報導，非公司揭露]；I 欄＝FY32 新增 MW
A18: 在役／已連網比例 | B18: % | C18: 1 | D18: 1 | E18: 1 | F18: 1 | G18: 1 | I18: 對外 AI MW 依 MW-year 計價：已連網即計費（在役比例 100%）；期初計費 MW＝三法交叉估計 3,250，不以 Azure 營收校準 [Assumed]
A19: 未起租租賃總額（未折現） | B19: US$bn | C19: 329.1 | I19: 季報附註已簽約未起租租賃（company.json → leases.facts.notCommenced）[Interested-party]
A20: 未起租：評價日後第幾季開始起租（0＝首期第一季） | B20: 季 | C20: 0 | I20: company.json → leases.uncommenced.startQ
A21: 未起租：平均分攤起租的季數 | B21: 季 | C21: 16 | I21: company.json → leases.uncommenced.quarters（起租時程見該欄說明）[Assumed]
A22: 未起租：每筆租期 | B22: 年 | C22: 15 | I22: 季報 15–19 年取中點；敏感度 15／19 年見報告 [Assumed]
A23: B｜產能與收入（MW、每 MW 年收入、利用率、信用；RPO 只作對照）
A24: 6/30 RPO | B24: US$bn | C24: 0 | I24: 季報 RPO 684.0（只作對照與債務上限的 backlog）[Interested-party]
A25: 評價日後新增承諾 | B25: US$bn | C25: 0 | I25: 評價日後新簽、尚未進 RPO 的承諾；未揭露，取 0 [Assumed]
A26: 五期認列比例（至 2030 末） | B26: % | C26: 0 | I26: 季報 RPO 桶線性分攤後五期合計 0% [Derived]
A27: RPO 桶權重合計 | B27: % | C27: 0.9 | I27: 下方權重列的合計，用於歸一化
A28: 2026-06-30 主動電力 | B28: MW | C28: 3250 | I28: FY26 末（評價日）對外 AI MW-IT 3,250（自有 4,500 × 60%＋租用 1,100 × 50%；三法交叉，事實總帳 split.extMW）[Derived／Assumed]
A29: 6/30 Billable MW | B29: MW | C29: =輸入與假設!$C$8 -> 3250 | I29: 季末在役 MW 未揭露 [Derived]
A30: 收入用平均在役 MW（1=是） | C30: 1 | I30: 0＝用期末存量全期化；建議 1
A31: 營收驅動（mw＝MW × 每 MW 年收入；rpo＝RPO 排程） | C31: mw | I31: mw：新產能簽約率固定 100%，營收＝容量上限；RPO 只作對照與產能瓶頸旗標（company.json → defaults.revenueDriver）
A32: 每 MW 年收入倍數（整體） | B32: % | C32: 1 | I32: 反向 DCF 與壓力測試用；預設 100%。以『目標搜尋』調整此格即可反解市價隱含單價
A33: 項目 | B33: 單位 | C33: FY27 | D33: FY28 | E33: FY29 | F33: FY30 | G33: FY31 | I33: 來源／標籤
A34: 模型期長度（年） | C34: 1 | D34: 1 | E34: 1 | F34: 1 | G34: 1 | I34: 勿改。由 calendar_q.py 推算；只用於容量上限、電力、維護等年率換算 [Derived]
A35: RPO 桶權重 | B35: % | C35: 0.3 | D35: 0.25 | E35: 0.2 | F35: 0.1 | G35: 0.05 | H35: =SUM(C35:G35) -> 0.9 | I35: 季報 RPO 桶（商用 RPO 678B（約 30% 於 12 個月內、加權平均 2.3 年；約 45% 來自 OpenAI，FY26Q2）含 M365 與非 AI 雲端，只作對照（模型排程歸 0：AI 雲端收入＝MW × 每 MW））桶內線性分攤 [Derived]
A36: Accepted MW（期末主動電力） | B36: MW | C36: =CHOOSE(輸入與假設!$C$5,C11,C14,C17) -> 5575.9 | D36: =CHOOSE(輸入與假設!$C$5,D11,D14,D17) -> 7901.8 | E36: =CHOOSE(輸入與假設!$C$5,E11,E14,E17) -> 10227.7 | F36: =CHOOSE(輸入與假設!$C$5,F11,F14,F17) -> 12553.6 | G36: =CHOOSE(輸入與假設!$C$5,G11,G14,G17) -> 14879.5 | I36: ＝依 A 區情境選擇器（已連網 MW-IT）
A37: Billable MW | B37: MW | C37: =ROUND(C36*C18,0) -> 5576 | D37: =ROUND(D36*D18,0) -> 7902 | E37: =ROUND(E36*E18,0) -> 10228 | F37: =ROUND(F36*F18,0) -> 12554 | G37: =ROUND(G36*G18,0) -> 14879 | I37: ＝已連網 × 在役比例（A 區）
A38: 利用率 | B38: % | C38: 1 | D38: 1 | E38: 1 | F38: 1 | G38: 1 | I38: 100%：按 MW-year 計價，收入端不乘 IF_Util（Tokenomics 下游契約第 3 條）
A39: 每 MW 年收入 | B39: US$bn/MW | C39: =C102*輸入與假設!$C$66/1000 -> 0.01218028 | D39: =D102*輸入與假設!$C$66/1000 -> 0.012573416 | E39: =E102*輸入與假設!$C$66/1000 -> 0.012789542 | F39: =F102*輸入與假設!$C$66/1000 -> 0.012925581 | G39: =G102*輸入與假設!$C$66/1000 -> 0.01301909 | I39: ＝加權每 MW 年持有成本 × 採用 k ÷ 1000（B0；Tokenomics × k，不以公司營收反推）
A40: 新產能簽約率 | B40: % | C40: 1 | D40: 1 | E40: 1 | F40: 1 | G40: 1 | I40: MW 驅動：100%（RPO 只作對照）
A41: 客戶違約率 | B41: % | C41: 0 | D41: 0 | E41: 0 | F41: 0 | G41: 0 | I41: 前三大客戶約 59% 營收的定價，非預測 [Assumed]
A42: 回收率 | B42: % | C42: 0.5 | D42: 0.5 | E42: 0.5 | F42: 0.5 | G42: 0.5 | I42: [Assumed]
A43: 非算力服務營收 | B43: US$bn | C43: 0 | D43: 0 | E43: 0 | F43: 0 | G43: 0 | I43: 預設 0：AI cloud 軟體已含在每 MW 年收入；其他事業另列 [Assumed]
A44: 其他事業 EBITDA（輸入） | B44: US$bn | C44: 0 | D44: 0 | E44: 0 | F44: 0 | G44: 0 | I44: 未分攤公司層費用：Microsoft 分部營業利益合計＝合併營業利益（無未分攤項）→ 0；租用算力租金另由 leases.rentedCompute 自本列扣除
A45: 租用算力｜CoreWeave｜年租金 | B45: US$bn／年 | C45: 2.985 | I45: 起租 2025-07、10 年、700 MW（自用 50%／對外 50%）；company.json → leases.rentedCompute
A46: 租用算力｜CoreWeave｜在租年數 | B46: 年 | C46: 1 | D46: 1 | E46: 1 | F46: 1 | G46: 1 | I46: ＝各期與租約期間重疊的月數 ÷ 12（建置時由日曆推算）
A47: 租用算力｜Nebius｜年租金 | B47: US$bn／年 | C47: 3.022 | I47: 起租 2025-11、10 年、205 MW（自用 50%／對外 50%）；company.json → leases.rentedCompute
A48: 租用算力｜Nebius｜在租年數 | B48: 年 | C48: 1 | D48: 1 | E48: 1 | F48: 1 | G48: 1 | I48: ＝各期與租約期間重疊的月數 ÷ 12（建置時由日曆推算）
A49: 租用算力｜IREN｜年租金 | B49: US$bn／年 | C49: 1.685 | I49: 起租 2026-06、10 年、200 MW（自用 50%／對外 50%）；company.json → leases.rentedCompute
A50: 租用算力｜IREN｜在租年數 | B50: 年 | C50: 1 | D50: 1 | E50: 1 | F50: 1 | G50: 1 | I50: ＝各期與租約期間重疊的月數 ÷ 12（建置時由日曆推算）
A51: 租用算力｜Nscale｜年租金 | B51: US$bn／年 | C51: 3.994 | I51: 起租 2026-10、10 年、411 MW（自用 50%／對外 50%）；company.json → leases.rentedCompute
A52: 租用算力｜Nscale｜在租年數 | B52: 年 | C52: 0.75 | D52: 1 | E52: 1 | F52: 1 | G52: 1 | I52: ＝各期與租約期間重疊的月數 ÷ 12（建置時由日曆推算）
A53: 租用算力｜Lambda｜年租金 | B53: US$bn／年 | C53: 0.434 | I53: 起租 2026-01、10 年、55 MW（自用 50%／對外 50%）；company.json → leases.rentedCompute
A54: 租用算力｜Lambda｜在租年數 | B54: 年 | C54: 1 | D54: 1 | E54: 1 | F54: 1 | G54: 1 | I54: ＝各期與租約期間重疊的月數 ÷ 12（建置時由日曆推算）
A55: 租用算力租金（營運成本） | B55: US$bn | C55: =輸入與假設!$C$45*C46+輸入與假設!$C$47*C48+輸入與假設!$C$49*C50+輸入與假設!$C$51*C52+輸入與假設!$C$53*C54 -> 11.1215 | D55: =輸入與假設!$C$45*D46+輸入與假設!$C$47*D48+輸入與假設!$C$49*D50+輸入與假設!$C$51*D52+輸入與假設!$C$53*D54 -> 12.12 | E55: =輸入與假設!$C$45*E46+輸入與假設!$C$47*E48+輸入與假設!$C$49*E50+輸入與假設!$C$51*E52+輸入與假設!$C$53*E54 -> 12.12 | F55: =輸入與假設!$C$45*F46+輸入與假設!$C$47*F48+輸入與假設!$C$49*F50+輸入與假設!$C$51*F52+輸入與假設!$C$53*F54 -> 12.12 | G55: =輸入與假設!$C$45*G46+輸入與假設!$C$47*G48+輸入與假設!$C$49*G50+輸入與假設!$C$51*G52+輸入與假設!$C$53*G54 -> 12.12 | I55: ＝Σ 年租金 × 在租年數（扣 EBITDA 與營運現金；不是資本支出）
A56: 其他事業 EBITDA | B56: US$bn | C56: =C44-C55 -> -11.1215 | D56: =D44-D55 -> -12.12 | E56: =E44-E55 -> -12.12 | F56: =F44-F55 -> -12.12 | G56: =G44-G55 -> -12.12 | I56: ＝輸入 − 租用算力租金（下游引用此列）
A57: 股權報酬占營收（SBC，非現金加回） | B57: % | C57: 0.037383 | I57: 股權報酬（SBC）為非現金費用：分部營業利益已扣除，營運現金加回＝SBC 占營收 × 模型期總營收；FY26 SBC 12.405 ÷ 營收 331.839＝3.74%（現金流量表；[Derived]）。股數稀釋沿用模板每年 1%
A58: FY27 剩餘季度營運資金變動（上年同期實際，流入為正） | B58: US$bn | C58: -4.895 | I58: 首期（FY27 全年）營運資金變動＝上一年度同期實際：FY26 營運資產與負債變動合計 −4.895（應收 −12.737、存貨 −0.461、其他流動資產 −2.627、其他長期資產 −3.964、應付 +5.268、遞延收入 +9.361、所得稅 −1.875、其他流動負債 +6.847、其他長期負債 −4.707；10-K 現金流量表，SEC XBRL）[Derived]；之後年度沿用營收增量比例（MAG 對照表 r1 C14；首期為全年，季節性不適用，照字面套用上一年度全年）
A59: ▸ B0｜對外 AI 雲端定價：每 MW 年收入＝Σ 在役世代占比 × Tokenomics 持有成本 × 晶片係數 × k（收入端不乘 IF_Util）
A60: 價格軸選擇（1＝低 長約下緣、2＝基準 C1 混合、3＝高 現貨改用 Azure 牌價） | C60: 2 | D60: =CHOOSE(C60,"低 長約下緣","基準 C1 混合","高 現貨改用 Azure 牌價") -> 基準 C1 混合 | I60: 價格軸與容量軸（A 區情境）分離；三容量情境預設都用基準 k，3 × 3 目標價矩陣見「評價_DCF與目標價」（對照表 r1 第 5 節第 1 條）
A61: k 組成（價格軸） | B61: 單位 | C61: 低 | D61: 基準 | E61: 高
A62: k｜長約 | B62: 倍 | C62: 0.45 | D62: 0.76 | E62: 0.76 | I62: 長約 k：IREN–Microsoft 0.76（一手 MW）、Nscale 約 0.88（金額二手）、Anthropic–Azure 0.39–0.71（年期假設）、Nebius ≤1.33 → 基準 0.76；低＝長約區間下緣 0.45（Anthropic 隱含）[Assumed]（kevidence longContracts）
A63: k｜現貨 | B63: 倍 | C63: 1.76 | D63: 1.76 | E63: 7.66 | I63: 現貨 k：基準 1.76＝與 Nebius／CRWV 同一市場現貨指數（對照表 r1 C1）；高＝Azure 牌價換算（H100 隨需 12.29 ÷ IF_GPUhrEcon H100 1.605＝7.66，kevidence az.h100.od；與 Amazon 同取隨需層；牌價不是大客戶成交價，只作上限；替代：3 年預留 3.36 → 混合 1.54）
A64: 長約占比 | B64: % | C64: 0.7 | D64: 0.7 | E64: 0.7 | I64: 長約占比 70%（OpenAI 約占商用 RPO 45%＋Anthropic 等長約；45%–100% [Assumed]）
A65: 混合 k | B65: 倍 | C65: =C64*C62+(1-C64)*C63 -> 0.843 | D65: =D64*D62+(1-D64)*D63 -> 1.06 | E65: =E64*E62+(1-E64)*E63 -> 2.83 | I65: ＝長約占比 × k_長約＋(1 − 長約占比) × k_現貨
A66: 採用 k（依價格軸） | B66: 倍 | C66: =CHOOSE(輸入與假設!$C$60,C65,D65,E65) -> 1.06 | I66: ＝依上方價格軸選擇
A67: 自研晶片持有成本係數 | B67: 倍 | C67: 1 | I67: 自研晶片每 MW 錨＝同期 NVIDIA 世代 IF_HoldEcon × 1.0（對照表 r1 C2）：Maia 100 → Hopper（期初未列，部署量不存在）、Maia 200（2026 起量產）→ GB300（v0.1 交付前修訂，查核 b；原 v0.1 誤對 Hopper）；敏感度 × 0.7（收入端單邊與收入＋資本支出雙邊兩版）。Tokenomics 無 NonNV 具名範圍（IF_NonNVRatio、IF_NonNVCostRatio、IF_NonNV_Maia 為 missing），已列缺口回報。
A68: 自研晶片 IT 資本支出係數 | B68: 倍 | C68: 1 | I68: 自研晶片每 MW IT 資本支出係數：預設 1（Maia 200 的資本支出以同期 NVIDIA GB300 的 TK_CapexIT 計）；雙邊敏感度時與 customFactor 同乘 0.7（收入錨與資本支出同降）；機房成本不變 [Assumed]
A69: 上限檢查門檻（每 MW 年收入 ÷ 參考付費營收） | B69: % | C69: 0.5 | I69: 上限檢查：每 MW 年收入 ÷（Σ 世代占比 × IF_RevGWFleet／1000）> 50% 時示警（工作單 v0.1b 第 2 步）
A70: 項目 | B70: 單位 | C70: FY27 | D70: FY28 | E70: FY29 | F70: FY30 | G70: FY31 | I70: 來源／標籤
A71: 世代｜Hopper（H100／H200）｜每 MW 年持有成本 | B71: US$m/MW | C71: =TK_HoldEcon_H100 -> 10.095795 | I71: Tokenomics IF_HoldEcon（H100）；US$B/GW＝US$m/MW
A72: 世代｜Hopper（H100／H200）｜每 MW 年營運成本 | B72: US$m/MW | C72: =TK_OpexGW_H100 -> 2.2773755 | I72: Tokenomics IF_OpexGW（H100；不含折舊，含電費）
A73: 世代｜Hopper（H100／H200）｜每 MW 參考付費營收 | B73: US$m/MW | C73: =TK_RevGWFleet_H100 -> 4.0048877 | I73: Tokenomics IF_RevGWFleet（H100；理論上限，只作檢查）
A74: 世代｜Hopper（H100／H200）｜期初在役占比 | B74: % | C74: 0.2 | I74: 期初在役（評價日 2026-06-30）：Hopper 20%、GB200 45%、GB300 35%（v0.1a mw.genMix.open，[Assumed]；Maia 部署量未揭露，期初不另列）。新增 MW：Maia 200 10%（對應 GB300；「continues to scale」，部署量不存在，[Assumed] 0%–20%）；NVIDIA 部分 FY27 GB300 60%／VR200 30%、FY28 GB300 20%／VR200 70%、FY29 起 VR200 90% [Assumed]（VR200 2026 下半年起出貨）。在役占比＝各世代累計 MW ÷ 對外 AI MW。
A75: 世代｜Hopper（H100／H200）｜新增 MW 占比 | B75: % | C75: 0 | D75: 0 | E75: 0 | F75: 0 | G75: 0 | I75: 各期新增在役 MW 的世代組合 [Assumed]
A76: 世代｜Hopper（H100／H200）｜在役 MW | B76: MW | C76: =輸入與假設!$C$74*輸入與假設!$C$29+MAX(0,C36-輸入與假設!$C$29)*C75 -> 650 | D76: =C76+MAX(0,D36-C36)*D75 -> 650 | E76: =D76+MAX(0,E36-D36)*E75 -> 650 | F76: =E76+MAX(0,F36-E36)*F75 -> 650 | G76: =F76+MAX(0,G36-F36)*G75 -> 650 | I76: ＝前期＋本期新增 × 新增占比（首期＝評價日在役 × 期初占比＋新增）
A77: 世代｜GB200｜每 MW 年持有成本 | B77: US$m/MW | C77: =TK_HoldEcon_GB200 -> 9.1709819 | I77: Tokenomics IF_HoldEcon（GB200）；US$B/GW＝US$m/MW
A78: 世代｜GB200｜每 MW 年營運成本 | B78: US$m/MW | C78: =TK_OpexGW_GB200 -> 2.1550491 | I78: Tokenomics IF_OpexGW（GB200；不含折舊，含電費）
A79: 世代｜GB200｜每 MW 參考付費營收 | B79: US$m/MW | C79: =TK_RevGWFleet_GB200 -> 20.174616 | I79: Tokenomics IF_RevGWFleet（GB200；理論上限，只作檢查）
A80: 世代｜GB200｜期初在役占比 | B80: % | C80: 0.45 | I80: 見第一個世代的說明 [Assumed]
A81: 世代｜GB200｜新增 MW 占比 | B81: % | C81: 0 | D81: 0 | E81: 0 | F81: 0 | G81: 0 | I81: 各期新增在役 MW 的世代組合 [Assumed]
A82: 世代｜GB200｜在役 MW | B82: MW | C82: =輸入與假設!$C$80*輸入與假設!$C$29+MAX(0,C36-輸入與假設!$C$29)*C81 -> 1462.5 | D82: =C82+MAX(0,D36-C36)*D81 -> 1462.5 | E82: =D82+MAX(0,E36-D36)*E81 -> 1462.5 | F82: =E82+MAX(0,F36-E36)*F81 -> 1462.5 | G82: =F82+MAX(0,G36-F36)*G81 -> 1462.5 | I82: ＝前期＋本期新增 × 新增占比（首期＝評價日在役 × 期初占比＋新增）
A83: 世代｜GB300｜每 MW 年持有成本 | B83: US$m/MW | C83: =TK_HoldEcon_GB300 -> 12.724746 | I83: Tokenomics IF_HoldEcon（GB300）；US$B/GW＝US$m/MW
A84: 世代｜GB300｜每 MW 年營運成本 | B84: US$m/MW | C84: =TK_OpexGW_GB300 -> 2.6251106 | I84: Tokenomics IF_OpexGW（GB300；不含折舊，含電費）
A85: 世代｜GB300｜每 MW 參考付費營收 | B85: US$m/MW | C85: =TK_RevGWFleet_GB300 -> 26.265236 | I85: Tokenomics IF_RevGWFleet（GB300；理論上限，只作檢查）
A86: 世代｜GB300｜期初在役占比 | B86: % | C86: 0.35 | I86: 見第一個世代的說明 [Assumed]
A87: 世代｜GB300｜新增 MW 占比 | B87: % | C87: 0.6 | D87: 0.2 | E87: 0 | F87: 0 | G87: 0 | I87: 各期新增在役 MW 的世代組合 [Assumed]
A88: 世代｜GB300｜在役 MW | B88: MW | C88: =輸入與假設!$C$86*輸入與假設!$C$29+MAX(0,C36-輸入與假設!$C$29)*C87 -> 2533.04 | D88: =C88+MAX(0,D36-C36)*D87 -> 2998.22 | E88: =D88+MAX(0,E36-D36)*E87 -> 2998.22 | F88: =E88+MAX(0,F36-E36)*F87 -> 2998.22 | G88: =F88+MAX(0,G36-F36)*G87 -> 2998.22 | I88: ＝前期＋本期新增 × 新增占比（首期＝評價日在役 × 期初占比＋新增）
A89: 世代｜Maia 200｜每 MW 年持有成本 | B89: US$m/MW | C89: =TK_HoldEcon_GB300*輸入與假設!$C$67 -> 12.724746 | I89: Tokenomics IF_HoldEcon（GB300）× 自研晶片係數（對照表 r1 C2）；US$B/GW＝US$m/MW
A90: 世代｜Maia 200｜每 MW 年營運成本 | B90: US$m/MW | C90: =TK_OpexGW_GB300 -> 2.6251106 | I90: Tokenomics IF_OpexGW（GB300；不含折舊，含電費）
A91: 世代｜Maia 200｜每 MW 參考付費營收 | B91: US$m/MW | C91: =TK_RevGWFleet_GB300 -> 26.265236 | I91: Tokenomics IF_RevGWFleet（GB300；理論上限，只作檢查）
A92: 世代｜Maia 200｜期初在役占比 | B92: % | C92: 0 | I92: 見第一個世代的說明 [Assumed]
A93: 世代｜Maia 200｜新增 MW 占比 | B93: % | C93: 0.1 | D93: 0.1 | E93: 0.1 | F93: 0.1 | G93: 0.1 | I93: 各期新增在役 MW 的世代組合 [Assumed]
A94: 世代｜Maia 200｜在役 MW | B94: MW | C94: =輸入與假設!$C$92*輸入與假設!$C$29+MAX(0,C36-輸入與假設!$C$29)*C93 -> 232.59 | D94: =C94+MAX(0,D36-C36)*D93 -> 465.18 | E94: =D94+MAX(0,E36-D36)*E93 -> 697.77 | F94: =E94+MAX(0,F36-E36)*F93 -> 930.36 | G94: =F94+MAX(0,G36-F36)*G93 -> 1162.95 | I94: ＝前期＋本期新增 × 新增占比（首期＝評價日在役 × 期初占比＋新增）
A95: 世代｜Vera Rubin（VR200）｜每 MW 年持有成本 | B95: US$m/MW | C95: =TK_HoldEcon_VR200 -> 12.762016 | I95: Tokenomics IF_HoldEcon（VR200）；US$B/GW＝US$m/MW
A96: 世代｜Vera Rubin（VR200）｜每 MW 年營運成本 | B96: US$m/MW | C96: =TK_OpexGW_VR200 -> 2.6300403 | I96: Tokenomics IF_OpexGW（VR200；不含折舊，含電費）
A97: 世代｜Vera Rubin（VR200）｜每 MW 參考付費營收 | B97: US$m/MW | C97: =TK_RevGWFleet_VR200 -> 48.723702 | I97: Tokenomics IF_RevGWFleet（VR200；理論上限，只作檢查）
A98: 世代｜Vera Rubin（VR200）｜期初在役占比 | B98: % | C98: 0 | I98: 見第一個世代的說明 [Assumed]
A99: 世代｜Vera Rubin（VR200）｜新增 MW 占比 | B99: % | C99: 0.3 | D99: 0.7 | E99: 0.9 | F99: 0.9 | G99: 0.9 | I99: 各期新增在役 MW 的世代組合 [Assumed]
A100: 世代｜Vera Rubin（VR200）｜在役 MW | B100: MW | C100: =輸入與假設!$C$98*輸入與假設!$C$29+MAX(0,C36-輸入與假設!$C$29)*C99 -> 697.77 | D100: =C100+MAX(0,D36-C36)*D99 -> 2325.9 | E100: =D100+MAX(0,E36-D36)*E99 -> 4419.21 | F100: =E100+MAX(0,F36-E36)*F99 -> 6512.52 | G100: =F100+MAX(0,G36-F36)*G99 -> 8605.83 | I100: ＝前期＋本期新增 × 新增占比（首期＝評價日在役 × 期初占比＋新增）
A101: 在役 MW 合計（世代加總） | B101: MW | C101: =C76+C82+C88+C94+C100 -> 5575.9 | D101: =D76+D82+D88+D94+D100 -> 7901.8 | E101: =E76+E82+E88+E94+E100 -> 10227.7 | F101: =F76+F82+F88+F94+F100 -> 12553.6 | G101: =G76+G82+G88+G94+G100 -> 14879.5 | I101: 應＝Accepted MW（核對見檢查頁）
...

Sheet 各期收支
A1: 支出與資金 — 五層支出、四層來源、現金橋
A2: FY27 欄＝年初至今 實際（季報現金流量表口徑）＋全年模型；FY28 以後為純模型。瀑布以「融資前現金」決定需求並直接由各支出列加總，因此沒有循環參照
A4: 項目 | B4: 單位 | C4: FY27 | D4: FY28 | E4: FY29 | F4: FY30 | G4: FY31 | I4: 公式／來源說明
A5: 支出（五層）
A6: ① 毛 CapEx（認列，備忘） | B6: US$bn | C6: =輸入與假設!$C$431+輸入與假設!C$287 -> 204.20173 | D6: =輸入與假設!D$287 -> 216.20736 | E6: =輸入與假設!E$287 -> 221.96544 | F6: =輸入與假設!F$287 -> 267.23064 | G6: =輸入與假設!G$287 -> 374.66162 | I6: FY27＝年初至今 實際認列 0.0＋全年 模型；對照公司全年指引 204.2–204.2。備忘列：用途合計採現金口徑，不用這一列
A7: 客戶預付率 | B7: % | C7: =輸入與假設!C$243 -> 0 | D7: =輸入與假設!D$243 -> 0 | E7: =輸入與假設!E$243 -> 0 | F7: =輸入與假設!F$243 -> 0 | G7: =輸入與假設!G$243 -> 0
A8: 客戶預付金額（抵減，全年 起） | B8: US$bn | C8: =輸入與假設!C$263*C7 -> 0 | D8: =輸入與假設!D$263*D7 -> 0 | E8: =輸入與假設!E$263*E7 -> 0 | F8: =輸入與假設!F$263*F7 -> 0 | G8: =輸入與假設!G$263*G7 -> 0 | I8: ＝成長型 CapEx × 預付比率（汰換 CapEx 不計）；年初至今 的預付已含在實際 CFO 內，不重複計入
A9: 合約負債期初（客戶預付餘額） | B9: US$bn | C9: =輸入與假設!$C$240 -> 0 | D9: =C12 -> 0 | E9: =D12 -> 0 | F9: =E12 -> 0 | G9: =F12 -> 0 | I9: FY27 期初＝6/30 季報遞延營收
A10: 合約負債利息累積（重大財務組成，非現金） | B10: US$bn | C10: =輸入與假設!$C$241*(C9+0.5*C8)*運營_產能與收入!C7 -> 0 | D10: =輸入與假設!$C$241*(D9+0.5*D8)*運營_產能與收入!D7 -> 0 | E10: =輸入與假設!$C$241*(E9+0.5*E8)*運營_產能與收入!E7 -> 0 | F10: =輸入與假設!$C$241*(F9+0.5*F8)*運營_產能與收入!F7 -> 0 | G10: =輸入與假設!$C$241*(G9+0.5*G8)*運營_產能與收入!G7 -> 0 | I10: ＝隱含利率 ×(期初合約負債＋本期預付流入 × ½)× 期間長度；進損益利息、不進現金（v0.1b）
A11: 預付認列（非現金營收） | B11: US$bn | C11: =MIN(C9+C10,(C9+C10)/輸入與假設!$C$239*運營_產能與收入!C7) -> 0 | D11: =MIN(D9+D10,(D9+D10)/輸入與假設!$C$239*運營_產能與收入!D7) -> 0 | E11: =MIN(E9+E10,(E9+E10)/輸入與假設!$C$239*運營_產能與收入!E7) -> 0 | F11: =MIN(F9+F10,(F9+F10)/輸入與假設!$C$239*運營_產能與收入!F7) -> 0 | G11: =MIN(G9+G10,(G9+G10)/輸入與假設!$C$239*運營_產能與收入!G7) -> 0 | I11: ＝(期初合約負債＋累積利息) ÷ 認列年數 × 期間長度；這部分營收已在預付時收現，自營運來源扣除
A12: 合約負債期末 | B12: US$bn | C12: =C9+C8+C10-C11 -> 0 | D12: =D9+D8+D10-D11 -> 0 | E12: =E9+E8+E10-E11 -> 0 | F12: =F9+F8+F10-F11 -> 0 | G12: =G9+G8+G10-G11 -> 0 | I12: ＝期初＋預付流入＋累積利息−認列
A13: ① CapEx（用途用：年初至今 現金／全年 毛額） | B13: US$bn | C13: =輸入與假設!$C$430+輸入與假設!C$287 -> 204.20173 | D13: =輸入與假設!D$287 -> 216.20736 | E13: =輸入與假設!E$287 -> 221.96544 | F13: =輸入與假設!F$287 -> 267.23064 | G13: =輸入與假設!G$287 -> 374.66162 | I13: 年初至今 採現金流量表的現金購置 0.0；全年 起採毛額，客戶預付在來源端抵回（避免重複計入）
A14: ② 在帳現金租金（備忘，年初至今 已含在 CFO） | B14: US$bn | C14: =輸入與假設!C$244 -> 13.203 | D14: =輸入與假設!D$244 -> 11.628 | E14: =輸入與假設!E$244 -> 9.814 | F14: =輸入與假設!F$244 -> 9.182 | G14: =輸入與假設!G$244 -> 8.859 | I14: 見『租賃與承諾』頁；2031 後尚有 61.706。FY27 欄僅 全年：年初至今 租金 0.0 已含在實際 CFO 內
A15: ② 表外現金租金（未起租） | B15: US$bn | C15: =運營_產能與收入!C59 -> 3.428125 | D15: =運營_產能與收入!D59 -> 8.913125 | E15: =運營_產能與收入!E59 -> 14.398125 | F15: =運營_產能與收入!F59 -> 19.883125 | G15: =運營_產能與收入!G59 -> 21.94 | I15: 已簽約未起租租賃 329.1 的現金路徑
A16: 租金合計 | B16: US$bn | C16: =輸入與假設!C$247+C15*輸入與假設!$C$248 -> 7.9780312 | D16: =輸入與假設!D$247+D15*輸入與假設!$C$248 -> 9.5222813 | E16: =輸入與假設!E$247+E15*輸入與假設!$C$248 -> 10.267531 | F16: =輸入與假設!F$247+F15*輸入與假設!$C$248 -> 11.540781 | G16: =輸入與假設!G$247+G15*輸入與假設!$C$248 -> 12.028 | I16: ＝在帳融資租賃現金＋未起租 × 融資部分比例（MAG v0.1b：營業租賃已含在分部 EBITDA，不重複扣除；AI 雲端 EBITDA 由 Tokenomics 推得、未扣租金）
A17: ③ 存量債務利息（備忘，年初至今 已含在 CFO） | B17: US$bn | C17: =輸入與假設!C$327 -> 1.3005073 | D17: =輸入與假設!D$327 -> 1.1556097 | E17: =輸入與假設!E$327 -> 1.1242648 | F17: =輸入與假設!F$327 -> 1.0929199 | G17: =輸入與假設!G$327 -> 1.0850876 | I17: ="6/30 債務餘額的利息。FY27 全年利息＝年初至今 實際 0.0＋全年 "&TEXT(C17,"0.0")&"＝"&TEXT(0+C17,"0.00")&"（見下方備忘）" -> 6/30 債務餘額的利息。FY27 全年利息＝年初至今 實際 0.0＋全年 1.3＝1.30（見下方備忘）
A18: 期初累積現金 | B18: US$bn | C18: =輸入與假設!$C$428 -> 76.843 | D18: =C56 -> 50 | E18: =D56 -> 50 | F18: =E56 -> 66.75901 | G18: =F56 -> 84.639491 | I18: FY27 自 2026-06-30 起算；之後＝前期期末累積現金
A19: 新債利率 | B19: % | C19: =IF(輸入與假設!$C$320=1,輸入與假設!C$326+MAX(0,輸入與假設!$C$319-450)/100*0.004,輸入與假設!C$326) -> 0.05 | D19: =IF(輸入與假設!$C$320=1,輸入與假設!D$326+MAX(0,輸入與假設!$C$319-450)/100*0.004,輸入與假設!D$326) -> 0.05 | E19: =IF(輸入與假設!$C$320=1,輸入與假設!E$326+MAX(0,輸入與假設!$C$319-450)/100*0.004,輸入與假設!E$326) -> 0.05 | F19: =IF(輸入與假設!$C$320=1,輸入與假設!F$326+MAX(0,輸入與假設!$C$319-450)/100*0.004,輸入與假設!F$326) -> 0.05 | G19: =IF(輸入與假設!$C$320=1,輸入與假設!G$326+MAX(0,輸入與假設!$C$319-450)/100*0.004,輸入與假設!G$326) -> 0.05 | I19: CDS 開關：＋MAX(0,CDS−450)×0.4bp/bp
A20: ③ 新債利息（瀑布） | B20: US$bn | C20: =C94 -> 0.99728296 | D20: =D94 -> 0.99728296 | E20: =E94 -> 0.99728296 | F20: =F94 -> 0.99728296 | G20: =G94 -> 0.99728296 | I20: ＝新債利率×期間長度×(期初新債＋本期舉借)；見下方「期前融資瀑布」
A21: 利息合計 | B21: US$bn | C21: =C17+C20 -> 2.2977903 | D21: =D17+D20 -> 2.1528927 | E21: =E17+E20 -> 2.1215478 | F21: =F17+F20 -> 2.0902029 | G21: =G17+G20 -> 2.0823706
A22: ④ JV／策略投資出資 | B22: US$bn | C22: =輸入與假設!$C$432+輸入與假設!C$251 -> 1.1 | D22: =輸入與假設!D$251 -> 0 | E22: =輸入與假設!E$251 -> 0 | F22: =輸入與假設!F$251 -> 0 | G22: =輸入與假設!G$251 -> 0 | I22: FY27＝年初至今 實際 0.0（JV 0.000＋策略投資 0.000）＋全年 模型。MSFT 不發股息
A23: ⑧ 股利（普通股＋特別股） | B23: US$bn | C23: =輸入與假設!$C$447+4*輸入與假設!$C$301*(1+輸入與假設!$C$302)^0*運營_產能與收入!C7*(輸入與假設!$C$303+0+SUMPRODUCT(資產負債_既有債務!$D$29:$D$29*資產負債_既有債務!$H$25:$H$25*(資產負債_既有債務!$G$25:$G$25<0)))+輸入與假設!C$324 -> 29.11384 | D23: =4*輸入與假設!$C$301*(1+輸入與假設!$C$302)^1*運營_產能與收入!D7*(輸入與假設!$C$303+C97+SUMPRODUCT(資產負債_既有債務!$D$29:$D$29*資產負債_既有債務!$H$25:$H$25*(資產負債_既有債務!$G$25:$G$25<1)))+輸入與假設!D$324 -> 31.442947 | E23: =4*輸入與假設!$C$301*(1+輸入與假設!$C$302)^2*運營_產能與收入!E7*(輸入與假設!$C$303+D97+SUMPRODUCT(資產負債_既有債務!$D$29:$D$29*資產負債_既有債務!$H$25:$H$25*(資產負債_既有債務!$G$25:$G$25<2)))+輸入與假設!E$324 -> 33.951299 | F23: =4*輸入與假設!$C$301*(1+輸入與假設!$C$302)^3*運營_產能與收入!F7*(輸入與假設!$C$303+E97+SUMPRODUCT(資產負債_既有債務!$D$29:$D$29*資產負債_既有債務!$H$25:$H$25*(資產負債_既有債務!$G$25:$G$25<3)))+輸入與假設!F$324 -> 36.459808 | G23: =4*輸入與假設!$C$301*(1+輸入與假設!$C$302)^4*運營_產能與收入!G7*(輸入與假設!$C$303+F97+SUMPRODUCT(資產負債_既有債務!$D$29:$D$29*資產負債_既有債務!$H$25:$H$25*(資產負債_既有債務!$G$25:$G$25<4)))+輸入與假設!G$324 -> 39.152389 | I23: 普通股＝每股每季 × 4 × 期間長度 ×(基礎股數＋前期累計瀑布新股＋已強制轉換特別股)＋特別股股利；FY27＝年初至今 實際＋全年 模型（v0.1b）
A24: ⑨ 回購（瀑布：現金不足時先減） | B24: US$bn | C24: =輸入與假設!$C$449+C76 -> 0 | D24: =D76 -> 0.8207201 | E24: =E76 -> 22.271 | F24: =F76 -> 22.271 | G24: =G76 -> 9.535849 | I24: FY27＝年初至今 實際＋全年 瀑布後實際回購；計畫與被迫減少見下方「期前融資瀑布」（MAG v0.1b）
A25: 電力（overlay） | B25: US$bn | C25: =IF(輸入與假設!$C$217=1,運營_產能與收入!C9*8760*輸入與假設!C$219*輸入與假設!C$218/1000000000*運營_產能與收入!C7,0) -> 0 | D25: =IF(輸入與假設!$C$217=1,運營_產能與收入!D9*8760*輸入與假設!D$219*輸入與假設!D$218/1000000000*運營_產能與收入!D7,0) -> 0 | E25: =IF(輸入與假設!$C$217=1,運營_產能與收入!E9*8760*輸入與假設!E$219*輸入與假設!E$218/1000000000*運營_產能與收入!E7,0) -> 0 | F25: =IF(輸入與假設!$C$217=1,運營_產能與收入!F9*8760*輸入與假設!F$219*輸入與假設!F$218/1000000000*運營_產能與收入!F7,0) -> 0 | G25: =IF(輸入與假設!$C$217=1,運營_產能與收入!G9*8760*輸入與假設!G$219*輸入與假設!G$218/1000000000*運營_產能與收入!G7,0) -> 0 | I25: ＝已連網 MW×8760×PUE×電價÷1e9×期間係數。EBITDA 率已含電費，預設關閉
A26: 維護（overlay） | B26: US$bn | C26: =IF(輸入與假設!$C$217=1,運營_產能與收入!C9*輸入與假設!C$220/1000*運營_產能與收入!C7,0) -> 0 | D26: =IF(輸入與假設!$C$217=1,運營_產能與收入!D9*輸入與假設!D$220/1000*運營_產能與收入!D7,0) -> 0 | E26: =IF(輸入與假設!$C$217=1,運營_產能與收入!E9*輸入與假設!E$220/1000*運營_產能與收入!E7,0) -> 0 | F26: =IF(輸入與假設!$C$217=1,運營_產能與收入!F9*輸入與假設!F$220/1000*運營_產能與收入!F7,0) -> 0 | G26: =IF(輸入與假設!$C$217=1,運營_產能與收入!G9*輸入與假設!G$220/1000*運營_產能與收入!G7,0) -> 0
A27: ⑤ 排程還本（季報到期表） | B27: US$bn | C27: =輸入與假設!$C$434+IF(輸入與假設!$C$296=1,輸入與假設!C$325,0)+資產負債_既有債務!C40 -> 9.25 | D27: =IF(輸入與假設!$C$296=1,輸入與假設!D$325,0)+資產負債_既有債務!D40 -> 0 | E27: =IF(輸入與假設!$C$296=1,輸入與假設!E$325,0)+資產負債_既有債務!E40 -> 2.001 | F27: =IF(輸入與假設!$C$296=1,輸入與假設!F$325,0)+資產負債_既有債務!F40 -> 0 | G27: =IF(輸入與假設!$C$296=1,輸入與假設!G$325,0)+資產負債_既有債務!G40 -> 0.5 | I27: FY27＝年初至今 實際還款 0.0＋全年 到期表 9.25
A28: ⑥ capped call 支出（年初至今 實際） | B28: US$bn | C28: =輸入與假設!$C$435 -> 0 | D28: =0 -> 0 | E28: =0 -> 0 | F28: =0 -> 0 | G28: =0 -> 0 | I28: 可轉債配套 capped call 現金支出（未見揭露，0）
A29: ⑦ 現金稅（全年 起） | B29: US$bn | C29: =輸入與假設!$C$318*MAX(0,運營_產能與收入!C38*輸入與假設!C$214+輸入與假設!C$56+輸入與假設!C$205-輸入與假設!C$206-運營_產能與收入!C62-輸入與假設!C$288-輸入與假設!C$327) -> 35.677259 | D29: =輸入與假設!$C$318*MAX(0,運營_產能與收入!D38*輸入與假設!D$214+輸入與假設!D$56+輸入與假設!D$205-輸入與假設!D$206-運營_產能與收入!D62-輸入與假設!D$288-輸入與假設!D$327) -> 39.771067 | E29: =輸入與假設!$C$318*MAX(0,運營_產能與收入!E38*輸入與假設!E$214+輸入與假設!E$56+輸入與假設!E$205-輸入與假設!E$206-運營_產能與收入!E62-輸入與假設!E$288-輸入與假設!E$327) -> 43.848016 | F29: =輸入與假設!$C$318*MAX(0,運營_產能與收入!F38*輸入與假設!F$214+輸入與假設!F$56+輸入與假設!F$205-輸入與假設!F$206-運營_產能與收入!F62-輸入與假設!F$288-輸入與假設!F$327) -> 47.545369 | G29: =輸入與假設!$C$318*MAX(0,運營_產能與收入!G38*輸入與假設!G$214+輸入與假設!G$56+輸入與假設!G$205-輸入與假設!G$206-運營_產能與收入!G62-輸入與假設!G$288-輸入與假設!G$327) -> 50.590469 | I29: ＝稅率 × MAX(0, 損益 EBITDA − 車隊 D&A − 存量利息)；年初至今 的稅已含在 CFO 內（v0.1b）
A30: 用途合計（現金口徑） | B30: US$bn | C30: =C13+C16+C21+C22+C25+C26+C27+C28+C29+C23+C24 -> 289.61865 | D30: =D13+D16+D21+D22+D25+D26+D27+D28+D29+D23+D24 -> 299.91727 | E30: =E13+E16+E21+E22+E25+E26+E27+E28+E29+E23+E24 -> 336.42584 | F30: =F13+F16+F21+F22+F25+F26+F27+F28+F29+F23+F24 -> 387.1378 | G30: =G13+G16+G21+G22+G25+G26+G27+G28+G29+G23+G24 -> 488.5507 | I30: FY27 的 年初至今 部分採季報現金流量表口徑（現金購置、還款、JV、capped call）；年初至今 的利息與租金已含在 CFO 內，不重複列
A31: 來源（四層）
A32: Ⓐ0 年初至今 實際營運現金流（CFO） | B32: US$bn | C32: =輸入與假設!$C$429 -> 0 | D32: =0 -> 0 | E32: =0 -> 0 | F32: =0 -> 0 | G32: =0 -> 0 | I32: 季報實際值，取代模型推算；已含 年初至今 的利息、租金與客戶預付
A33: Ⓐ RPO 現金（全年 起） | B33: US$bn | C33: =運營_產能與收入!C40 -> 0 | D33: =運營_產能與收入!D40 -> 0 | E33: =運營_產能與收入!E40 -> 0 | F33: =運營_產能與收入!F40 -> 0 | G33: =運營_產能與收入!G40 -> 0
A34: Ⓑ 新簽約現金 | B34: US$bn | C34: =運營_產能與收入!C41 -> 42.88673 | D34: =運營_產能與收入!D41 -> 67.80941 | E34: =運營_產能與收入!E41 -> 92.928341 | F34: =運營_產能與收入!F41 -> 118.12879 | G34: =運營_產能與收入!G41 -> 143.36991
A35: Ⓒ 非算力服務現金 | B35: US$bn | C35: =輸入與假設!C$215 -> 0 | D35: =輸入與假設!D$215 -> 0 | E35: =輸入與假設!E$215 -> 0 | F35: =輸入與假設!F$215 -> 0 | G35: =輸入與假設!G$215 -> 0
A36: Ⓒ2 其他事業 EBITDA（全年 起） | B36: US$bn | C36: =輸入與假設!C$56 -> -11.1215 | D36: =輸入與假設!D$56 -> -12.12 | E36: =輸入與假設!E$56 -> -12.12 | F36: =輸入與假設!F$56 -> -12.12 | G36: =輸入與假設!G$56 -> -12.12 | I36: 非核心事業 EBITDA（負值＝燒錢），視為現金（v0.1b）
A37: Ⓒ3 非 AI 事業 EBITDA（全年 起） | B37: US$bn | C37: =輸入與假設!C$205-輸入與假設!C$206 -> 201.10205 | D37: =輸入與假設!D$205-輸入與假設!D$206 -> 226.6046 | E37: =輸入與假設!E$205-輸入與假設!E$206 -> 251.98267 | F37: =輸入與假設!F$205-輸入與假設!F$206 -> 275.9322 | G37: =輸入與假設!G$205-輸入與假設!G$206 -> 297.0803 | I37: 各線 EBITDA − 其他攤銷（視為等額現金支出），視為現金（現金稅另列於用途；MAG v0.1b）
A38: Ⓒ4 減：延誤罰則（營業費用） | B38: US$bn | C38: =-運營_產能與收入!C62 -> 0 | D38: =-運營_產能與收入!D62 -> 0 | E38: =-運營_產能與收入!E62 -> 0 | F38: =-運營_產能與收入!F62 -> 0 | G38: =-運營_產能與收入!G62 -> 0 | I38: 建設延誤期間應計費而未計費營收 × 罰則比例（預設 0；v0.2）
A39: Ⓒ5 加回：股權報酬（非現金） | B39: US$bn | C39: =輸入與假設!$C$57*(運營_產能與收入!C38+輸入與假設!C$204) -> 14.857708 | D39: =輸入與假設!$C$57*(運營_產能與收入!D38+輸入與假設!D$204) -> 17.623256 | E39: =輸入與假設!$C$57*(運營_產能與收入!E38+輸入與假設!E$204) -> 20.393836 | F39: =輸入與假設!$C$57*(運營_產能與收入!F38+輸入與假設!F$204) -> 23.077302 | G39: =輸入與假設!$C$57*(運營_產能與收入!G38+輸入與假設!G$204) -> 25.581002 | I39: ＝SBC 占營收 × 模型期總營收（分部營業利益已扣 SBC；年初至今 已含在實際 CFO；MAG v0.1b）
A40: Ⓒ6 首期營運資金變動（上年同期實際） | B40: US$bn | C40: =IF(ISBLANK(輸入與假設!$C$58),0,輸入與假設!$C$58) -> -4.895 | D40: =0 -> 0 | E40: =0 -> 0 | F40: =0 -> 0 | G40: =0 -> 0 | I40: FY27 剩餘季度＝上一年度同期實際（流入為正；10-Q／10-K 現金流量表 [Derived]）；之後年度資金模型不計營運資金（MAG v0.1b r2 C14）
A41: Ⓓ 客戶預付（全年 起） | B41: US$bn | C41: =C8 -> 0 | D41: =D8 -> 0 | E41: =E8 -> 0 | F41: =F8 -> 0 | G41: =G8 -> 0
A42: Ⓓ2 減：預付認列（非現金營收） | B42: US$bn | C42: =-C11 -> 0 | D42: =-D11 -> 0 | E42: =-E11 -> 0 | F42: =-F11 -> 0 | G42: =-G11 -> 0 | I42: 營收中由合約負債轉入的部分已在預付時收現，不重複計入服務現金（v0.1b）
A43: 營運來源合計 | B43: US$bn | C43: =C32+C33+C34+C35+C36+C37+C38+C39+C40+C41+C42 -> 242.82999 | D43: =D32+D33+D34+D35+D36+D37+D38+D39+D40+D41+D42 -> 299.91727 | E43: =E32+E33+E34+E35+E36+E37+E38+E39+E40+E41+E42 -> 353.18485 | F43: =F32+F33+F34+F35+F36+F37+F38+F39+F40+F41+F42 -> 405.01828 | G43: =G32+G33+G34+G35+G36+G37+G38+G39+G40+G41+G42 -> 453.91121
A44: 自由現金流（FCF＝營運現金 − 現金資本支出） | B44: US$bn | C44: =C43-C29-C21-C13 -> 0.65321196 | D44: =D43-D29-D21-D13 -> 41.785949 | E44: =E43-E29-E21-E13 -> 85.249841 | F44: =F43-F29-F21-F13 -> 88.15207 | G44: =G43-G29-G21-G13 -> 26.576747 | I44: 公司定義近似：營運來源（FY27 含 年初至今 實際 CFO）− 現金稅 − 利息 − 現金資本支出（不扣融資租賃本金）；一頁摘要「FCF 首次為負的年份」（MAG v0.1b）
A45: Ⓔ 股權／可轉債（融資） | B45: US$bn | C45: =輸入與假設!$C$436+IF(輸入與假設!$C$293=1,輸入與假設!$C$292,0) -> 0 | D45: =0 -> 0 | E45: =0 -> 0 | F45: =0 -> 0 | G45: =0 -> 0 | I45: FY27＝全年模型（年初至今 0）：不發股；股利每季 0.98、回購基準 22.3／年
A46: Ⓕ 年初至今 實際借款（融資） | B46: US$bn | C46: =輸入與假設!$C$433 -> 0 | D46: =0 -> 0 | E46: =0 -> 0 | F46: =0 -> 0 | G46: =0 -> 0 | I46: 季報：年初至今 借款 0.0（2026-03 可轉債）
A47: Ⓖ 瀑布：新債（額度＋資產層） | B47: US$bn | C47: =C86 -> 19.945659 | D47: =D86 -> 0 | E47: =E86 -> 0 | F47: =F86 -> 0 | G47: =G86 -> 0 | I47: 見下方「期前融資瀑布」
A48: Ⓖ2 瀑布：可轉債 | B48: US$bn | C48: =C89 -> 0 | D48: =D89 -> 0 | E48: =E89 -> 0 | F48: =F89 -> 0 | G48: =G89 -> 0 | I48: 資產擔保融資用罄後、股權之前；每年不超過可轉債上限（v0.1b）
A49: Ⓗ 瀑布：股權募資 | B49: US$bn | C49: =C92 -> 0 | D49: =D92 -> 0 | E49: =E92 -> 0 | F49: =F92 -> 0 | G49: =G92 -> 0 | I49: 債務與可轉債用罄後的殘差；每年不超過股權吸收上限
A50: Ⓘ 瀑布：高息債（股權上限溢出） | B50: US$bn | C50: =C93 -> 0 | D50: =D93 -> 0 | E50: =E93 -> 0 | F50: =F93 -> 0 | G50: =G93 -> 0 | I50: 股權超過每年上限的部分；不受 backlog 上限約束
A51: 總來源（含融資） | B51: US$bn | C51: =C43+C45+C46+C47+C48+C49+C50 -> 262.77565 | D51: =D43+D45+D46+D47+D48+D49+D50 -> 299.91727 | E51: =E43+E45+E46+E47+E48+E49+E50 -> 353.18485 | F51: =F43+F45+F46+F47+F48+F49+F50 -> 405.01828 | G51: =G43+G45+G46+G47+G48+G49+G50 -> 453.91121
A52: 缺口與現金橋
A53: 年初至今 其他／受限現金調節 | B53: US$bn | C53: =輸入與假設!$C$291-(輸入與假設!$C$428+輸入與假設!$C$429+輸入與假設!$C$433+輸入與假設!$C$436-輸入與假設!$C$430-輸入與假設!$C$432-輸入與假設!$C$434-輸入與假設!$C$435-輸入與假設!$C$447-輸入與假設!$C$449) -> 0 | D53: =0 -> 0 | E53: =0 -> 0 | F53: =0 -> 0 | G53: =0 -> 0 | I53: 使 年初至今 實際流量接回 6/30 現金餘額；差額來自受限現金重分類與未逐項列出的項目
A54: 營運缺口（不含融資、不含還本） | B54: US$bn | C54: =C43-(C30-C27-C28) -> -37.538659 | D54: =D43-(D30-D27-D28) -> 0 | E54: =E43-(E30-E27-E28) -> 18.76001 | F54: =F43-(F30-F27-F28) -> 17.880481 | G54: =G43-(G30-G27-G28) -> -34.139491 | I54: 本業能不能自給：營運來源 −（用途 − 排程還本 − capped call）
A55: 期間缺口（含融資） | B55: US$bn | C55: =C51-C30+C53 -> -26.843 | D55: =D51-D30+D53 -> 0 | E55: =E51-E30+E53 -> 16.75901 | F55: =F51-F30+F53 -> 17.880481 | G55: =G51-G30+G53 -> -34.639491
A56: 期末累積現金 | B56: US$bn | C56: =C18+C55 -> 50 | D56: =D18+D55 -> 50 | E56: =E18+E55 -> 66.75901 | F56: =F18+F55 -> 84.639491 | G56: =G18+G55 -> 50 | I56: 期前融資：每期末不低於最低現金
A58: 租賃負債（期末剩餘租金現值；調整後槓桿用，v0.2）
A59: 租賃折現率（加權平均） | B59: % | C59: 0.043 | I59: 10-K FY2026 營業／融資租賃加權平均折現率（事實總帳 lease.discRate.fy26）[Verified]；company.json → leases.liability.discRate
A60: 在帳租約：模型期後尾端年數 | B60: 年 | C60: 10 | I60: 到期表 2031 後的未折現付款平均分攤年數（10-K 營業租賃加權平均剩餘期限 12 年）[Derived]
A61: 在帳租賃負債（期末） | B61: US$bn | C61: =輸入與假設!D$244*(1+各期收支!$C$59)^(-(運營_產能與收入!$D$51-運營_產能與收入!$D$7/2-運營_產能與收入!$C$51))+輸入與假設!E$244*(1+各期收支!$C$59)^(-(運營_產能與收入!$E$51-運營_產能與收入!$E$7/2-運營_產能與收入!$C$51))+輸入與假設!F$244*(1+各期收支!$C$59)^(-(運營_產能與收入!$F$51-運營_產能與收入!$F$7/2-運營_產能與收入!$C$51))+輸入與假設!G$244*(1+各期收支!$C$59)^(-(運營_產能與收入!$G$51-運營_產能與收入!$G$7/2-運營_產能與收入!$C$51))+61.706/各期收支!$C$60*(1+各期收支!$C$59)^0.5*(1-(1+各期收支!$C$59)^(-各期收支!$C$60))/各期收支!$C$59*(1+各期收支!$C$59)^(-(運營_產能與收入!$G$51-運營_產能與收入!$C$51)) -> 79.062969 | D61: =輸入與假設!E$244*(1+各期收支!$C$59)^(-(運營_產能與收入!$E$51-運營_產能與收入!$E$7/2-運營_產能與收入!$D$51))+輸入與假設!F$244*(1+各期收支!$C$59)^(-(運營_產能與收入!$F$51-運營_產能與收入!$F$7/2-運營_產能與收入!$D$51))+輸入與假設!G$244*(1+各期收支!$C$59)^(-(運營_產能與收入!$G$51-運營_產能與收入!$G$7/2-運營_產能與收入!$D$51))+61.706/各期收支!$C$60*(1+各期收支!$C$59)^0.5*(1-(1+各期收支!$C$59)^(-各期收支!$C$60))/各期收支!$C$59*(1+各期收支!$C$59)^(-(運營_產能與收入!$G$51-運營_產能與收入!$D$51)) -> 70.587306 | E61: =輸入與假設!F$244*(1+各期收支!$C$59)^(-(運營_產能與收入!$F$51-運營_產能與收入!$F$7/2-運營_產能與收入!$E$51))+輸入與假設!G$244*(1+各期收支!$C$59)^(-(運營_產能與收入!$G$51-運營_產能與收入!$G$7/2-運營_產能與收入!$E$51))+61.706/各期收支!$C$60*(1+各期收支!$C$59)^0.5*(1-(1+各期收支!$C$59)^(-各期收支!$C$60))/各期收支!$C$59*(1+各期收支!$C$59)^(-(運營_產能與收入!$G$51-運營_產能與收入!$E$51)) -> 63.59978 | F61: =輸入與假設!G$244*(1+各期收支!$C$59)^(-(運營_產能與收入!$G$51-運營_產能與收入!$G$7/2-運營_產能與收入!$F$51))+61.706/各期收支!$C$60*(1+各期收支!$C$59)^0.5*(1-(1+各期收支!$C$59)^(-各期收支!$C$60))/各期收支!$C$59*(1+各期收支!$C$59)^(-(運營_產能與收入!$G$51-運營_產能與收入!$F$51)) -> 56.957235 | G61: =61.706/各期收支!$C$60*(1+各期收支!$C$59)^0.5*(1-(1+各期收支!$C$59)^(-各期收支!$C$60))/各期收支!$C$59*(1+各期收支!$C$59)^(-(運營_產能與收入!$G$51-運營_產能與收入!$G$51)) -> 50.358933 | I61: ＝期末之後各期到期表現金（期中付款）＋模型期後尾端 61.706（平均分攤、年中付款）的現值
A62: 未起租租約已起租部分的租賃負債（期末） | B62: US$bn | C62: =IF(OR(運營_產能與收入!$C$50<=0,運營_產能與收入!$C$56<=0),1*輸入與假設!$C$19/輸入與假設!$C$21/輸入與假設!$C$22/4/((1+各期收支!$C$59)^0.25-1)*(MIN(MAX(0,輸入與假設!C$245-(輸入與假設!$C$20)),輸入與假設!$C$21)-(1+各期收支!$C$59)^(-(4*輸入與假設!$C$22-MAX(0,輸入與假設!C$245-(輸入與假設!$C$20)))/4)*(1-(1+各期收支!$C$59)^(-MIN(MAX(0,輸入與假設!C$245-(輸入與假設!$C$20)),輸入與假設!$C$21)/4))/(1-(1+各期收支!$C$59)^(-0.25))),(1-運營_產能與收入!$C$56)*輸入與假設!$C$19/輸入與假設!$C$21/輸入與假設!$C$22/4/((1+各期收支!$C$59)^0.25-1)*(MIN(MAX(0,輸入與假設!C$245-(輸入與假設!$C$20)),輸入與假設!$C$21)-(1+各期收支!$C$59)^(-(4*輸入與假設!$C$22-MAX(0,輸入與假設!C$245-(輸入與假設!$C$20)))/4)*(1-(1+各期收支!$C$59)^(-MIN(MAX(0,輸入與假設!C$245-(輸入與假設!$C$20)),輸入與假設!$C$21)/4))/(1-(1+各期收支!$C$59)^(-0.25)))+運營_產能與收入!$C$56*輸入與假設!$C$19/輸入與假設!$C$21/輸入與假設!$C$22/4/((1+各期收支!$C$59)^0.25-1)*(MIN(MAX(0,輸入與假設!C$245-(輸入與假設!$C$20+運營_產能與收入!$C$50/3)),輸入與假設!$C$21)-(1+各期收支!$C$59)^(-(4*輸入與假設!$C$22-MAX(0,輸入與假設!C$245-(輸入與假設!$C$20+運營_產能與收入!$C$50/3)))/4)*(1-(1+各期收支!$C$59)^(-MIN(MAX(0,輸入與假設!C$245-(輸入與假設!$C$20+運營_產能與收入!$C$50/3)),輸入與假設!$C$21)/4))/(1-(1+各期收支!$C$59)^(-0.25)))) -> 58.836946 | D62: =IF(OR(運營_產能與收入!$C$50<=0,運營_產能與收入!$C$56<=0),1*輸入與假設!$C$19/輸入與假設!$C$21/輸入與假設!$C$22/4/((1+各期收支!$C$59)^0.25-1)*(MIN(MAX(0,輸入與假設!D$245-(輸入與假設!$C$20)),輸入與假設!$C$21)-(1+各期收支!$C$59)^(-(4*輸入與假設!$C$22-MAX(0,輸入與假設!D$245-(輸入與假設!$C$20)))/4)*(1-(1+各期收支!$C$59)^(-MIN(MAX(0,輸入與假設!D$245-(輸入與假設!$C$20)),輸入與假設!$C$21)/4))/(1-(1+各期收支!$C$59)^(-0.25))),(1-運營_產能與收入!$C$56)*輸入與假設!$C$19/輸入與假設!$C$21/輸入與假設!$C$22/4/((1+各期收支!$C$59)^0.25-1)*(MIN(MAX(0,輸入與假設!D$245-(輸入與假設!$C$20)),輸入與假設!$C$21)-(1+各期收支!$C$59)^(-(4*輸入與假設!$C$22-MAX(0,輸入與假設!D$245-(輸入與假設!$C$20)))/4)*(1-(1+各期收支!$C$59)^(-MIN(MAX(0,輸入與假設!D$245-(輸入與假設!$C$20)),輸入與假設!$C$21)/4))/(1-(1+各期收支!$C$59)^(-0.25)))+運營_產能與收入!$C$56*輸入與假設!$C$19/輸入與假設!$C$21/輸入與假設!$C$22/4/((1+各期收支!$C$59)^0.25-1)*(MIN(MAX(0,輸入與假設!D$245-(輸入與假設!$C$20+運營_產能與收入!$C$50/3)),輸入與假設!$C$21)-(1+各期收支!$C$59)^(-(4*輸入與假設!$C$22-MAX(0,輸入與假設!D$245-(輸入與假設!$C$20+運營_產能與收入!$C$50/3)))/4)*(1-(1+各期收支!$C$59)^(-MIN(MAX(0,輸入與假設!D$245-(輸入與假設!$C$20+運營_產能與收入!$C$50/3)),輸入與假設!$C$21)/4))/(1-(1+各期收支!$C$59)^(-0.25)))) -> 114.63121 | E62: =IF(OR(運營_產能與收入!$C$50<=0,運營_產能與收入!$C$56<=0),1*輸入與假設!$C$19/輸入與假設!$C$21/輸入與假設!$C$22/4/((1+各期收支!$C$59)^0.25-1)*(MIN(MAX(0,輸入與假設!E$245-(輸入與假設!$C$20)),輸入與假設!$C$21)-(1+各期收支!$C$59)^(-(4*輸入與假設!$C$22-MAX(0,輸入與假設!E$245-(輸入與假設!$C$20)))/4)*(1-(1+各期收支!$C$59)^(-MIN(MAX(0,輸入與假設!E$245-(輸入與假設!$C$20)),輸入與假設!$C$21)/4))/(1-(1+各期收支!$C$59)^(-0.25))),(1-運營_產能與收入!$C$56)*輸入與假設!$C$19/輸入與假設!$C$21/輸入與假設!$C$22/4/((1+各期收支!$C$59)^0.25-1)*(MIN(MAX(0,輸入與假設!E$245-(輸入與假設!$C$20)),輸入與假設!$C$21)-(1+各期收支!$C$59)^(-(4*輸入與假設!$C$22-MAX(0,輸入與假設!E$245-(輸入與假設!$C$20)))/4)*(1-(1+各期收支!$C$59)^(-MIN(MAX(0,輸入與假設!E$245-(輸入與假設!$C$20)),輸入與假設!$C$21)/4))/(1-(1+各期收支!$C$59)^(-0.25)))+運營_產能與收入!$C$56*輸入與假設!$C$19/輸入與假設!$C$21/輸入與假設!$C$22/4/((1+各期收支!$C$59)^0.25-1)*(MIN(MAX(0,輸入與假設!E$245-(輸入與假設!$C$20+運營_產能與收入!$C$50/3)),輸入與假設!$C$21)-(1+各期收支!$C$59)^(-(4*輸入與假設!$C$22-MAX(0,輸入與假設!E$245-(輸入與假設!$C$20+運營_產能與收入!$C$50/3)))/4)*(1-(1+各期收支!$C$59)^(-MIN(MAX(0,輸入與假設!E$245-(輸入與假設!$C$20+運營_產能與收入!$C$50/3)),輸入與假設!$C$21)/4))/(1-(1+各期收支!$C$59)^(-0.25)))) -> 167.25196 | F62: =IF(OR(運營_產能與收入!$C$50<=0,運營_產能與收入!$C$56<=0),1*輸入與假設!$C$19/輸入與假設!$C$21/輸入與假設!$C$22/4/((1+各期收支!$C$59)^0.25-1)*(MIN(MAX(0,輸入與假設!F$245-(輸入與假設!$C$20)),輸入與假設!$C$21)-(1+各期收支!$C$59)^(-(4*輸入與假設!$C$22-MAX(0,輸入與假設!F$245-(輸入與假設!$C$20)))/4)*(1-(1+各期收支!$C$59)^(-MIN(MAX(0,輸入與假設!F$245-(輸入與假設!$C$20)),輸入與假設!$C$21)/4))/(1-(1+各期收支!$C$59)^(-0.25))),(1-運營_產能與收入!$C$56)*輸入與假設!$C$19/輸入與假設!$C$21/輸入與假設!$C$22/4/((1+各期收支!$C$59)^0.25-1)*(MIN(MAX(0,輸入與假設!F$245-(輸入與假設!$C$20)),輸入與假設!$C$21)-(1+各期收支!$C$59)^(-(4*輸入與假設!$C$22-MAX(0,輸入與假設!F$245-(輸入與假設!$C$20)))/4)*(1-(1+各期收支!$C$59)^(-MIN(MAX(0,輸入與假設!F$245-(輸入與假設!$C$20)),輸入與假設!$C$21)/4))/(1-(1+各期收支!$C$59)^(-0.25)))+運營_產能與收入!$C$56*輸入與假設!$C$19/輸入與假設!$C$21/輸入與假設!$C$22/4/((1+各期收支!$C$59)^0.25-1)*(MIN(MAX(0,輸入與假設!F$245-(輸入與假設!$C$20+運營_產能與收入!$C$50/3)),輸入與假設!$C$21)-(1+各期收支!$C$59)^(-(4*輸入與假設!$C$22-MAX(0,輸入與假設!F$245-(輸入與假設!$C$20+運營_產能與收入!$C$50/3)))/4)*(1-(1+各期收支!$C$59)^(-MIN(MAX(0,輸入與假設!F$245-(輸入與假設!$C$20+運營_產能與收入!$C$50/3)),輸入與假設!$C$21)/4))/(1-(1+各期收支!$C$59)^(-0.25)))) -> 216.56273 | G62: =IF(OR(運營_產能與收入!$C$50<=0,運營_產能與收入!$C$56<=0),1*輸入與假設!$C$19/輸入與假設!$C$21/輸入與假設!$C$22/4/((1+各期收支!$C$59)^0.25-1)*(MIN(MAX(0,輸入與假設!G$245-(輸入與假設!$C$20)),輸入與假設!$C$21)-(1+各期收支!$C$59)^(-(4*輸入與假設!$C$22-MAX(0,輸入與假設!G$245-(輸入與假設!$C$20)))/4)*(1-(1+各期收支!$C$59)^(-MIN(MAX(0,輸入與假設!G$245-(輸入與假設!$C$20)),輸入與假設!$C$21)/4))/(1-(1+各期收支!$C$59)^(-0.25))),(1-運營_產能與收入!$C$56)*輸入與假設!$C$19/輸入與假設!$C$21/輸入與假設!$C$22/4/((1+各期收支!$C$59)^0.25-1)*(MIN(MAX(0,輸入與假設!G$245-(輸入與假設!$C$20)),輸入與假設!$C$21)-(1+各期收支!$C$59)^(-(4*輸入與假設!$C$22-MAX(0,輸入與假設!G$245-(輸入與假設!$C$20)))/4)*(1-(1+各期收支!$C$59)^(-MIN(MAX(0,輸入與假設!G$245-(輸入與假設!$C$20)),輸入與假設!$C$21)/4))/(1-(1+各期收支!$C$59)^(-0.25)))+運營_產能與收入!$C$56*輸入與假設!$C$19/輸入與假設!$C$21/輸入與假設!$C$22/4/((1+各期收支!$C$59)^0.25-1)*(MIN(MAX(0,輸入與假設!G$245-(輸入與假設!$C$20+運營_產能與收入!$C$50/3)),輸入與假設!$C$21)-(1+各期收支!$C$59)^(-(4*輸入與假設!$C$22-MAX(0,輸入與假設!G$245-(輸入與假設!$C$20+運營_產能與收入!$C$50/3)))/4)*(1-(1+各期收支!$C$59)^(-MIN(MAX(0,輸入與假設!G$245-(輸入與假設!$C$20+運營_產能與收入!$C$50/3)),輸入與假設!$C$21)/4))/(1-(1+各期收支!$C$59)^(-0.25)))) -> 203.58425 | I62: 每季起租 總額 ÷ 季數、每筆季末付租：已起租各筆剩餘租金現值合計（延誤連動部分起算季延後 延誤月數 ÷ 3）
A63: 租賃負債合計（期末） | B63: US$bn | C63: =C61+C62 -> 137.89992 | D63: =D61+D62 -> 185.21852 | E63: =E61+E62 -> 230.85174 | F63: =F61+F62 -> 273.51996 | G63: =G61+G62 -> 253.94318
A65: 期前融資瀑布（缺口在需要前一期先融好：額度 → 資產層新債 → 股權）
A66: 用途（不含新債利息） | B66: US$bn | C66: =C13+C16+C17+C22+C25+C26+C27+C28+C29+C23 -> 288.62137 | D66: =D13+D16+D17+D22+D25+D26+D27+D28+D29+D23 -> 298.09927 | E66: =E13+E16+E17+E22+E25+E26+E27+E28+E29+E23 -> 313.15756 | F66: =F13+F16+F17+F22+F25+F26+F27+F28+F29+F23 -> 363.86952 | G66: =G13+G16+G17+G22+G25+G26+G27+G28+G29+G23 -> 478.01757 | I66: 避免循環參照：直接由各支出列加總
A67: 新債期初餘額 | B67: US$bn | C67: =0 -> 0 | D67: =C98 -> 19.945659 | E67: =D98 -> 19.945659 | F67: =E98 -> 19.945659 | G67: =F98 -> 19.945659
A68: 新債利率 × 期間長度 | B68: % | C68: =C19*運營_產能與收入!C7 -> 0.05 | D68: =D19*運營_產能與收入!D7 -> 0.05 | E68: =E19*運營_產能與收入!E7 -> 0.05 | F68: =F19*運營_產能與收入!F7 -> 0.05 | G68: =G19*運營_產能與收入!G7 -> 0.05
A69: 高息債期初餘額 | B69: US$bn | C69: =0 -> 0 | D69: =C100 -> 0 | E69: =D100 -> 0 | F69: =E100 -> 0 | G69: =F100 -> 0
A70: 可轉債（瀑布）期初餘額 | B70: US$bn | C70: =0 -> 0 | D70: =C101 -> 0 | E70: =D101 -> 0 | F70: =E101 -> 0 | G70: =F101 -> 0
A71: 可轉債票息 × 期間長度 | B71: % | C71: =輸入與假設!$C$315*運營_產能與收入!C7 -> 0 | D71: =輸入與假設!$C$315*運營_產能與收入!D7 -> 0 | E71: =輸入與假設!$C$315*運營_產能與收入!E7 -> 0 | F71: =輸入與假設!$C$315*運營_產能與收入!F7 -> 0 | G71: =輸入與假設!$C$315*運營_產能與收入!G7 -> 0
A72: 高息債利率 × 期間長度 | B72: % | C72: =(輸入與假設!$C$317+IF(輸入與假設!$C$320=1,MAX(0,輸入與假設!$C$319-輸入與假設!$C$321)/10000*輸入與假設!$C$322,0))*運營_產能與收入!C7 -> 0.12 | D72: =(輸入與假設!$C$317+IF(輸入與假設!$C$320=1,MAX(0,輸入與假設!$C$319-輸入與假設!$C$321)/10000*輸入與假設!$C$322,0))*運營_產能與收入!D7 -> 0.12 | E72: =(輸入與假設!$C$317+IF(輸入與假設!$C$320=1,MAX(0,輸入與假設!$C$319-輸入與假設!$C$321)/10000*輸入與假設!$C$322,0))*運營_產能與收入!E7 -> 0.12 | F72: =(輸入與假設!$C$317+IF(輸入與假設!$C$320=1,MAX(0,輸入與假設!$C$319-輸入與假設!$C$321)/10000*輸入與假設!$C$322,0))*運營_產能與收入!F7 -> 0.12 | G72: =(輸入與假設!$C$317+IF(輸入與假設!$C$320=1,MAX(0,輸入與假設!$C$319-輸入與假設!$C$321)/10000*輸入與假設!$C$322,0))*運營_產能與收入!G7 -> 0.12
A73: 融資前現金（扣既有新債利息） | B73: US$bn | C73: =C18+C43+C45+C46+C53-C66-C68*C67-C72*C69-C71*C70 -> 31.051624 | D73: =D18+D43+D45+D46+D53-D66-D68*D67-D72*D69-D71*D70 -> 50.82072 | E73: =E18+E43+E45+E46+E53-E66-E68*E67-E72*E69-E71*E70 -> 89.03001 | F73: =F18+F43+F45+F46+F53-F66-F68*F67-F72*F69-F71*F70 -> 106.91049 | G73: =G18+G43+G45+G46+G53-G66-G68*G67-G72*G69-G71*G70 -> 59.535849
A74: 融資需求（補足至最低現金） | B74: US$bn | C74: =MAX(0,輸入與假設!$C$304-(C73-C76)) -> 18.948376 | D74: =MAX(0,輸入與假設!$C$304-(D73-D76)) -> 0 | E74: =MAX(0,輸入與假設!$C$304-(E73-E76)) -> 0 | F74: =MAX(0,輸入與假設!$C$304-(F73-F76)) -> 0 | G74: =MAX(0,輸入與假設!$C$304-(G73-G76)) -> 0 | I74: ＝MAX(0, 最低現金 −(融資前現金 − 實際回購))
A75: 回購計畫（基準年額 × 期間長度） | B75: US$bn | C75: =輸入與假設!$C$305*運營_產能與收入!C7 -> 22.271 | D75: =輸入與假設!$C$305*運營_產能與收入!D7 -> 22.271 | E75: =輸入與假設!$C$305*運營_產能與收入!E7 -> 22.271 | F75: =輸入與假設!$C$305*運營_產能與收入!F7 -> 22.271 | G75: =輸入與假設!$C$305*運營_產能與收入!G7 -> 22.271 | I75: MAG v0.1b：瀑布第二步（現金之後、新債之前）
A76: 回購（實際，減少後） | B76: US$bn | C76: =MIN(C75,MAX(C75*輸入與假設!$C$306,C73-輸入與假設!$C$304)) -> 0 | D76: =MIN(D75,MAX(D75*輸入與假設!$C$306,D73-輸入與假設!$C$304)) -> 0.8207201 | E76: =MIN(E75,MAX(E75*輸入與假設!$C$306,E73-輸入與假設!$C$304)) -> 22.271 | F76: =MIN(F75,MAX(F75*輸入與假設!$C$306,F73-輸入與假設!$C$304)) -> 22.271 | G76: =MIN(G75,MAX(G75*輸入與假設!$C$306,G73-輸入與假設!$C$304)) -> 9.535849 | I76: ＝MIN(計畫, MAX(下限, 融資前現金 − 最低現金))
A77: 回購被迫減少 | B77: US$bn | C77: =C75-C76 -> 22.271 | D77: =D75-D76 -> 21.45028 | E77: =E75-E76 -> 0 | F77: =F75-F76 -> 0 | G77: =G75-G76 -> 12.735151 | I77: ＝計畫 − 實際（一頁摘要「回購被迫減少的年份與金額」）
A78: 回購股數 | B78: bn | C78: =C76/MAX(0.01,輸入與假設!$C$307) -> 0 | D78: =D76/MAX(0.01,輸入與假設!$C$307) -> 0.00154923 | E78: =E76/MAX(0.01,輸入與假設!$C$307) -> 0.042039792 | F78: =F76/MAX(0.01,輸入與假設!$C$307) -> 0.042039792 | G78: =G76/MAX(0.01,輸入與假設!$C$307) -> 0.018000319 | I78: ＝實際回購 ÷ 發行參考價（現價）
A79: 期初 backlog | B79: US$bn | C79: =輸入與假設!$C$24+輸入與假設!$C$25 -> 0 | D79: =C81 -> 107.50193 | E79: =D81 -> 115.70977 | F79: =E81 -> 93.386662 | G79: =F81 -> 40.0462 | I79: FY27 期初＝6/30 RPO 0.0＋期後新增 0.0
A80: 新簽合約增量（年化增量×年期） | B80: US$bn | C80: =MAX(0,運營_產能與收入!C24/運營_產能與收入!C7-0)*輸入與假設!$C$300 -> 161.2529 | D80: =MAX(0,運營_產能與收入!D24/運營_產能與收入!D7-運營_產能與收入!C24/運營_產能與收入!C7)*輸入與假設!$C$300 -> 92.938198 | E80: =MAX(0,運營_產能與收入!E24/運營_產能與收入!E7-運營_產能與收入!D24/運營_產能與收入!D7)*輸入與假設!$C$300 -> 93.610894 | F80: =MAX(0,運營_產能與收入!F24/運營_產能與收入!F7-運營_產能與收入!E24/運營_產能與收入!E7)*輸入與假設!$C$300 -> 93.890303 | G80: =MAX(0,運營_產能與收入!G24/運營_產能與收入!G7-運營_產能與收入!F24/運營_產能與收入!F7)*輸入與假設!$C$300 -> 94.02892
A81: 期末 backlog | B81: US$bn | C81: =C79-運營_產能與收入!C18-運營_產能與收入!C24+C80 -> 107.50193 | D81: =D79-運營_產能與收入!D18-運營_產能與收入!D24+D80 -> 115.70977 | E81: =E79-運營_產能與收入!E18-運營_產能與收入!E24+E80 -> 93.386662 | F81: =F79-運營_產能與收入!F18-運營_產能與收入!F24+F80 -> 40.0462 | G81: =G79-運營_產能與收入!G18-運營_產能與收入!G24+G80 -> -44.498618 | I81: ＝期初 − 排程認列 − 新簽約認列 ＋ 新簽合約增量
A82: 既有債務＋期後可轉債（期末） | B82: US$bn | C82: =IF(輸入與假設!$C$296=1,資產負債_既有債務!C36,資產負債_既有債務!$E$18)+資產負債_既有債務!$E$21+資產負債_既有債務!C41 -> 36.886 | D82: =IF(輸入與假設!$C$296=1,資產負債_既有債務!D36,資產負債_既有債務!$E$18)+資產負債_既有債務!$E$21+資產負債_既有債務!D41 -> 36.886 | E82: =IF(輸入與假設!$C$296=1,資產負債_既有債務!E36,資產負債_既有債務!$E$18)+資產負債_既有債務!$E$21+資產負債_既有債務!E41 -> 34.885 | F82: =IF(輸入與假設!$C$296=1,資產負債_既有債務!F36,資產負債_既有債務!$E$18)+資產負債_既有債務!$E$21+資產負債_既有債務!F41 -> 34.885 | G82: =IF(輸入與假設!$C$296=1,資產負債_既有債務!G36,資產負債_既有債務!$E$18)+資產負債_既有債務!$E$21+資產負債_既有債務!G41 -> 34.385 | I82: ＝(依到期表遞減的既有本金，若關閉攤還則維持 46.136)＋期後新發可轉債 0
A83: 債務上限（投資級：倍數 × 當期 EBITDA；或債務／backlog） | B83: US$bn | C83: =IF(輸入與假設!$C$298="leaseAdj",輸入與假設!$C$299*(損益!C22+C16)/運營_產能與收入!C7-C63,IF(輸入與假設!$C$298="ebitda",輸入與假設!$C$299*損益!C22/運營_產能與收入!C7,輸入與假設!$C$297*C81)) -> 584.63603 | D83: =IF(輸入與假設!$C$298="leaseAdj",輸入與假設!$C$299*(損益!D22+D16)/運營_產能與收入!D7-D63,IF(輸入與假設!$C$298="ebitda",輸入與假設!$C$299*損益!D22/運營_產能與收入!D7,輸入與假設!$C$297*D81)) -> 690.23036 | E83: =IF(輸入與假設!$C$298="leaseAdj",輸入與假設!$C$299*(損益!E22+E16)/運營_產能與收入!E7-E63,IF(輸入與假設!$C$298="ebitda",輸入與假設!$C$299*損益!E22/運營_產能與收入!E7,輸入與假設!$C$297*E81)) -> 798.32389 | F83: =IF(輸入與假設!$C$298="leaseAdj",輸入與假設!$C$299*(損益!F22+F16)/運營_產能與收入!F7-F63,IF(輸入與假設!$C$298="ebitda",輸入與假設!$C$299*損益!F22/運營_產能與收入!F7,輸入與假設!$C$297*F81)) -> 906.92533 | G83: =IF(輸入與假設!$C$298="leaseAdj",輸入與假設!$C$299*(損益!G22+G16)/運營_產能與收入!G7-G63,IF(輸入與假設!$C$298="ebitda",輸入與假設!$C$299*損益!G22/運營_產能與收入!G7,輸入與假設!$C$297*G81)) -> 1067.1314 | I83: leaseAdj：總債務 ≤ 倍數 ×(損益 EBITDA＋租金)（年化）− 租賃負債（v0.2）；ebitda：總債務 ≤ 倍數 × 損益 EBITDA（年化）；backlog：總債務 ≤ 倍數 × 期末 backlog（模板）
A84: 未動用額度（期初） | B84: US$bn | C84: =IF(輸入與假設!$C$295=1,輸入與假設!$C$294,0) -> 0 | D84: =C99 -> 0 | E84: =D99 -> 0 | F84: =E99 -> 0 | G84: =F99 -> 0
A85: 新債可借上限 | B85: US$bn | C85: =MAX(0,C83-(C82+C67+C70),C84) -> 547.75003 | D85: =MAX(0,D83-(D82+D67+D70),D84) -> 633.39871 | E85: =MAX(0,E83-(E82+E67+E70),E84) -> 743.49323 | F85: =MAX(0,F83-(F82+F67+F70),F84) -> 852.09467 | G85: =MAX(0,G83-(G82+G67+G70),G84) -> 1012.8008 | I85: ＝MAX(上限 − 既有債務 − 期初新債 − 期初瀑布可轉債, 未動用額度)
A86: 新債舉借 | B86: US$bn | C86: =MIN(C85,C74/(1-C68)) -> 19.945659 | D86: =MIN(D85,D74/(1-D68)) -> 0 | E86: =MIN(E85,E74/(1-E68)) -> 0 | F86: =MIN(F85,F74/(1-F68)) -> 0 | G86: =MIN(G85,G74/(1-G68)) -> 0 | I86: 期前融資：期初到位，當期全額計息，所以需求要除以 (1−利率×期間)
A87: 債務後剩餘需求 | B87: US$bn | C87: =MAX(0,C74+C68*C86-C86) -> 0 | D87: =MAX(0,D74+D68*D86-D86) -> 0 | E87: =MAX(0,E74+E68*E86-E86) -> 0 | F87: =MAX(0,F74+F68*F86-F86) -> 0 | G87: =MAX(0,G74+G68*G86-G86) -> 0
A88: 可轉債可發行上限 | B88: US$bn | C88: =MAX(0,輸入與假設!$C$314)*運營_產能與收入!C7 -> 0 | D88: =MAX(0,輸入與假設!$C$314)*運營_產能與收入!D7 -> 0 | E88: =MAX(0,輸入與假設!$C$314)*運營_產能與收入!E7 -> 0 | F88: =MAX(0,輸入與假設!$C$314)*運營_產能與收入!F7 -> 0 | G88: =MAX(0,輸入與假設!$C$314)*運營_產能與收入!G7 -> 0 | I88: ＝每年上限（隨情境）× 期間長度
A89: 可轉債發行 | B89: US$bn | C89: =MIN(C88,C87/(1-C71)) -> 0 | D89: =MIN(D88,D87/(1-D71)) -> 0 | E89: =MIN(E88,E87/(1-E71)) -> 0 | F89: =MIN(F88,F87/(1-F71)) -> 0 | G89: =MIN(G88,G87/(1-G71)) -> 0 | I89: 期前融資：期初到位、當期全額計息
A90: 可轉債後剩餘需求 | B90: US$bn | C90: =MAX(0,C87+C71*C89-C89) -> 0 | D90: =MAX(0,D87+D71*D89-D89) -> 0 | E90: =MAX(0,E87+E71*E89-E89) -> 0 | F90: =MAX(0,F87+F71*F89-F89) -> 0 | G90: =MAX(0,G87+G71*G89-G89) -> 0
A91: 每年股權吸收上限 | B91: US$bn | C91: =IF(輸入與假設!$C$309>=9,1E+099,輸入與假設!$C$309*輸入與假設!$C$307*輸入與假設!$C$310*運營_產能與收入!C7) -> 196.72638 | D91: =IF(輸入與假設!$C$309>=9,1E+099,輸入與假設!$C$309*輸入與假設!$C$307*輸入與假設!$C$310*運營_產能與收入!D7) -> 196.72638 | E91: =IF(輸入與假設!$C$309>=9,1E+099,輸入與假設!$C$309*輸入與假設!$C$307*輸入與假設!$C$310*運營_產能與收入!E7) -> 196.72638 | F91: =IF(輸入與假設!$C$309>=9,1E+099,輸入與假設!$C$309*輸入與假設!$C$307*輸入與假設!$C$310*運營_產能與收入!F7) -> 196.72638 | G91: =IF(輸入與假設!$C$309>=9,1E+099,輸入與假設!$C$309*輸入與假設!$C$307*輸入與假設!$C$310*運營_產能與收入!G7) -> 196.72638 | I91: ＝現市值（發行參考價 × 7.427bn 股）× 上限 % × 期間長度
A92: 股權募資 | B92: US$bn | C92: =MIN(C90,C91) -> 0 | D92: =MIN(D90,D91) -> 0 | E92: =MIN(E90,E91) -> 0 | F92: =MIN(F90,F91) -> 0 | G92: =MIN(G90,G91) -> 0
A93: 高息債舉借（溢出） | B93: US$bn | C93: =(C90-C92)/(1-C72) -> 0 | D93: =(D90-D92)/(1-D72) -> 0 | E93: =(E90-E92)/(1-E72) -> 0 | F93: =(F90-F92)/(1-F72) -> 0 | G93: =(G90-G92)/(1-G72) -> 0
A94: 新債＋高息債利息（期初餘額＋本期舉借） | B94: US$bn | C94: =C68*(C67+C86)+C72*(C69+C93)+C71*(C70+C89) -> 0.99728296 | D94: =D68*(D67+D86)+D72*(D69+D93)+D71*(D70+D89) -> 0.99728296 | E94: =E68*(E67+E86)+E72*(E69+E93)+E71*(E70+E89) -> 0.99728296 | F94: =F68*(F67+F86)+F72*(F69+F93)+F71*(F70+F89) -> 0.99728296 | G94: =G68*(G67+G86)+G72*(G69+G93)+G71*(G70+G89) -> 0.99728296 | I94: 含瀑布可轉債票息（v0.1b）
A95: 發行價（現價×(1−折價)） | B95: US$ | C95: =輸入與假設!$C$307*(1-輸入與假設!$C$308) -> 476.784 | D95: =輸入與假設!$C$307*(1-輸入與假設!$C$308) -> 476.784 | E95: =輸入與假設!$C$307*(1-輸入與假設!$C$308) -> 476.784 | F95: =輸入與假設!$C$307*(1-輸入與假設!$C$308) -> 476.784 | G95: =輸入與假設!$C$307*(1-輸入與假設!$C$308) -> 476.784
A96: 新發行股數 | B96: bn | C96: =C92/C95 -> 0 | D96: =D92/D95 -> 0 | E96: =E92/E95 -> 0 | F96: =F92/F95 -> 0 | G96: =G92/G95 -> 0
A97: 累計新股 | B97: bn | C97: =C96-C78 -> 0 | D97: =C97+D96-D78 -> -0.00154923 | E97: =D97+E96-E78 -> -0.043589022 | F97: =E97+F96-F78 -> -0.085628813 | G97: =F97+G96-G78 -> -0.10362913
A98: 新債期末餘額 | B98: US$bn | C98: =C67+C86 -> 19.945659 | D98: =D67+D86 -> 19.945659 | E98: =E67+E86 -> 19.945659 | F98: =F67+F86 -> 19.945659 | G98: =G67+G86 -> 19.945659
A99: 未動用額度（期末） | B99: US$bn | C99: =C84-MIN(C84,C86) -> 0 | D99: =D84-MIN(D84,D86) -> 0 | E99: =E84-MIN(E84,E86) -> 0 | F99: =F84-MIN(F84,F86) -> 0 | G99: =G84-MIN(G84,G86) -> 0
A100: 高息債期末餘額 | B100: US$bn | C100: =C69+C93 -> 0 | D100: =D69+D93 -> 0 | E100: =E69+E93 -> 0 | F100: =F69+F93 -> 0 | G100: =G69+G93 -> 0
A101: 可轉債（瀑布）期末餘額 | B101: US$bn | C101: =C70+C89 -> 0 | D101: =D70+D89 -> 0 | E101: =E70+E89 -> 0 | F101: =F70+F89 -> 0 | G101: =G70+G89 -> 0
A102: 期末總債務（既有＋可轉債＋新債＋高息債） | B102: US$bn | C102: =C82+C98+C101+C100 -> 56.831659 | D102: =D82+D98+D101+D100 -> 56.831659 | E102: =E82+E98+E101+E100 -> 54.830659 | F102: =F82+F98+F101+F100 -> 54.830659 | G102: =G82+G98+G101+G100 -> 54.330659
A103: 融資前累積現金 | B103: US$bn | C103: =C18+C43+C45+C46+C53-C66 -> 31.051624 | D103: =C103+D43+D45-D66 -> 32.869627 | E103: =D103+E43+E45-E66 -> 72.89692 | F103: =E103+F43+F45-F66 -> 114.04568 | G103: =F103+G43+G45-G66 -> 89.939325 | I103: 若不做任何新融資的累積現金；負值＝外部資金需求
...

Sheet 季度追蹤
A1: 季度追蹤 — 焦點季的模型／共識／指引／實際與差距（由年度模型拆分；只用於追蹤，不影響年度數字與目標價）
A2: 設定與實際數在『輸入與假設』J 區，共識在 I 區；缺資料顯示「不適用」，實際數空白＝待公布。差距超過門檻的項目附差異原因（拆法＝所屬期間合計差距在門檻內）。第 2 區為 6 季路徑與拆分明細（預設收合）。
A4: 1｜焦點季（『輸入與假設』J 區選擇）：模型／共識／指引／實際與差距
A5: 指標 | B5: 單位 | C5: 模型 | D5: 共識 | E5: 模型 vs 共識 | F5: 指引（低） | G5: 指引（高） | H5: 模型 vs 指引中點 | I5: 實際 | J5: 實際 vs 模型 | K5: 實際 vs 共識 | L5: 實際 vs 指引中點 | M5: 利潤率 pt：模型 vs 共識 | N5: 模型 vs 指引 | O5: 實際 vs 模型 | P5: 實際 vs 共識 | Q5: 實際 vs 指引
A6: 焦點｜營收 | B6: US$bn | C6: =INDEX($C$22:$H$22,輸入與假設!$C$515) -> 93.748759 | D6: =INDEX($C$37:$H$37,輸入與假設!$C$515) -> 90.685 | E6: =INDEX($C$47:$H$47,輸入與假設!$C$515) -> 0.033784626 | F6: =IF(ISNUMBER(INDEX($C$32:$H$32,輸入與假設!$C$515)),INDEX($C$32:$H$32,輸入與假設!$C$515),"不適用") -> 89.85 | G6: =INDEX($C$33:$H$33,輸入與假設!$C$515) -> 90.95 | H6: =INDEX($C$48:$H$48,輸入與假設!$C$515) -> 0.037043792 | I6: =IF(ISNUMBER(INDEX($C$41:$H$41,輸入與假設!$C$515)),INDEX($C$41:$H$41,輸入與假設!$C$515),"待公布") -> 待公布 | J6: =INDEX($C$49:$H$49,輸入與假設!$C$515) | K6: =INDEX($C$50:$H$50,輸入與假設!$C$515) | L6: =INDEX($C$51:$H$51,輸入與假設!$C$515)
A7: 焦點｜調整後 EBITDA | B7: US$bn | C7: =INDEX($C$28:$H$28,輸入與假設!$C$515) -> 54.303798 | D7: =INDEX($C$38:$H$38,輸入與假設!$C$515) -> 56.56 | E7: =INDEX($C$52:$H$52,輸入與假設!$C$515) -> -2.2562018 | F7: 不適用 | G7: 不適用 | H7: =INDEX($C$53:$H$53,輸入與假設!$C$515) -> 不適用 | I7: =IF(ISNUMBER(INDEX($C$42:$H$42,輸入與假設!$C$515)),INDEX($C$42:$H$42,輸入與假設!$C$515),"待公布") -> 待公布 | J7: =INDEX($C$54:$H$54,輸入與假設!$C$515) | K7: =INDEX($C$55:$H$55,輸入與假設!$C$515) | L7: =INDEX($C$56:$H$56,輸入與假設!$C$515) | M7: =INDEX($C$57:$H$57,輸入與假設!$C$515) -> -0.044449231 | N7: =INDEX($C$58:$H$58,輸入與假設!$C$515) -> 不適用 | O7: =INDEX($C$59:$H$59,輸入與假設!$C$515) | P7: =INDEX($C$60:$H$60,輸入與假設!$C$515) | Q7: =INDEX($C$61:$H$61,輸入與假設!$C$515)
A8: 焦點｜EBITDA 率 | B8: % | C8: =INDEX($C$27:$H$27,輸入與假設!$C$515) -> 0.57924818 | D8: =INDEX($C$39:$H$39,輸入與假設!$C$515) -> 0.62369741 | E8: =INDEX($C$62:$H$62,輸入與假設!$C$515) -> -0.044449231 | F8: 不適用 | G8: 不適用 | H8: =INDEX($C$63:$H$63,輸入與假設!$C$515) -> 不適用 | I8: =IF(ISNUMBER(INDEX($C$43:$H$43,輸入與假設!$C$515)),INDEX($C$43:$H$43,輸入與假設!$C$515),"待公布") -> 待公布 | J8: =INDEX($C$64:$H$64,輸入與假設!$C$515) | K8: =INDEX($C$65:$H$65,輸入與假設!$C$515) | L8: =INDEX($C$66:$H$66,輸入與假設!$C$515)
A9: 焦點｜調整後營業利益 | B9: US$bn | C9: =INDEX($C$31:$H$31,輸入與假設!$C$515) -> 41.008678 | D9: 不適用 | E9: =INDEX($C$67:$H$67,輸入與假設!$C$515) -> 不適用 | F9: =IF(ISNUMBER(INDEX($C$34:$H$34,輸入與假設!$C$515)),INDEX($C$34:$H$34,輸入與假設!$C$515),"不適用") -> 43.15 | G9: =INDEX($C$35:$H$35,輸入與假設!$C$515) -> 44.55 | H9: =INDEX($C$68:$H$68,輸入與假設!$C$515) -> -2.8413222 | I9: =IF(ISNUMBER(INDEX($C$44:$H$44,輸入與假設!$C$515)),INDEX($C$44:$H$44,輸入與假設!$C$515),"待公布") -> 待公布 | J9: =INDEX($C$69:$H$69,輸入與假設!$C$515) | K9: =INDEX($C$70:$H$70,輸入與假設!$C$515) | L9: =INDEX($C$71:$H$71,輸入與假設!$C$515) | M9: =INDEX($C$72:$H$72,輸入與假設!$C$515) -> 不適用 | N9: =INDEX($C$73:$H$73,輸入與假設!$C$515) -> -0.047634684 | O9: =INDEX($C$74:$H$74,輸入與假設!$C$515) | P9: =INDEX($C$75:$H$75,輸入與假設!$C$515) | Q9: =INDEX($C$76:$H$76,輸入與假設!$C$515)
A10: 焦點｜CapEx（毛額） | B10: US$bn | C10: =INDEX($C$36:$H$36,輸入與假設!$C$515) -> 51.050433 | D10: 不適用 | E10: =INDEX($C$77:$H$77,輸入與假設!$C$515) -> 不適用 | F10: 不適用 | G10: 不適用 | H10: =INDEX($C$78:$H$78,輸入與假設!$C$515) -> 不適用 | I10: =IF(ISNUMBER(INDEX($C$45:$H$45,輸入與假設!$C$515)),INDEX($C$45:$H$45,輸入與假設!$C$515),"待公布") -> 待公布 | J10: =INDEX($C$79:$H$79,輸入與假設!$C$515) | K10: =INDEX($C$80:$H$80,輸入與假設!$C$515) | L10: =INDEX($C$81:$H$81,輸入與假設!$C$515)
A11: 焦點｜季末已連網 MW-IT | B11: MW | C11: =INDEX($C$19:$H$19,輸入與假設!$C$515) -> 3831.475 | D11: 不適用 | E11: =INDEX($C$82:$H$82,輸入與假設!$C$515) -> 不適用 | F11: 不適用 | G11: 不適用 | H11: =INDEX($C$83:$H$83,輸入與假設!$C$515) -> 不適用 | I11: =IF(ISNUMBER(INDEX($C$46:$H$46,輸入與假設!$C$515)),INDEX($C$46:$H$46,輸入與假設!$C$515),"待公布") -> 待公布 | J11: =INDEX($C$84:$H$84,輸入與假設!$C$515) | K11: =INDEX($C$85:$H$85,輸入與假設!$C$515) | L11: =INDEX($C$86:$H$86,輸入與假設!$C$515)
A12: 焦點｜季度 | C12: =INDEX($C$16:$H$16,輸入與假設!$C$515) -> Q1 FY27
A13: 焦點｜差異原因 | C13: =IF(INDEX($C$123:$H$123,輸入與假設!$C$515)="","無（差距皆在 "&IF(ROUND(ABS(輸入與假設!$C$509)*100,4)=INT(ROUND(ABS(輸入與假設!$C$509)*100,4)),TEXT(ROUND(ABS(輸入與假設!$C$509)*100,4),"0"),TEXT(ROUND(ABS(輸入與假設!$C$509)*100,4),"0.0"))&"%"&" 以內）",INDEX($C$123:$H$123,輸入與假設!$C$515)) -> 營收 vs 指引中點 +3.7%：觀點（營收＝對外 AI 雲端（在役 MW × 每 MW 年收入，Tokenomics × k）＋各分部依近四季年增率收斂；年度總額線性分到各季，未建模季節性）；調整後 EBITDA vs 共識 −$2.26bn／−4.4pt：觀點（模型 EBITDA 率 57.9%；EBITDA＝分部營業利益＋分攤 D&A 與 AI 雲端 Tokenomics 由下而上營運成本）；調整後營業利益 vs 指引中點 −$2.84bn／−4.8pt：觀點（模型折舊 13.30 依期初 PP&E 與資本支出推算；營業利益＝EBITDA − 折舊，年度總額線性分到各季）
A15: 2｜6 季路徑、共識、指引、實際與差距（明細；第 1 區以焦點季引用本區）
A16: 項目 | B16: 單位 | C16: Q1 FY27 | D16: Q2 FY27 | E16: Q3 FY27 | F16: Q4 FY27 | G16: Q1 FY28 | H16: Q2 FY28
A17: 所屬期間 | C17: =輸入與假設!C$514 -> 1 | D17: =輸入與假設!D$514 -> 1 | E17: =輸入與假設!E$514 -> 1 | F17: =輸入與假設!F$514 -> 1 | G17: =輸入與假設!G$514 -> 2 | H17: =輸入與假設!H$514 -> 2 | J17: 1＝FY27、2＝FY28
A18: 季序 | C18: 1 | D18: 2 | E18: 3 | F18: 4 | G18: 5 | H18: 6 | J18: EBITDA 率直線的 x 軸
A19: 季末已連網 MW-IT（模型） | B19: MW | C19: =輸入與假設!$C$517+(輸入與假設!C$36-輸入與假設!$C$517)*1/4 -> 3831.475 | D19: =輸入與假設!$C$517+(輸入與假設!C$36-輸入與假設!$C$517)*2/4 -> 4412.95 | E19: =輸入與假設!$C$517+(輸入與假設!C$36-輸入與假設!$C$517)*3/4 -> 4994.425 | F19: =輸入與假設!$C$517+(輸入與假設!C$36-輸入與假設!$C$517)*4/4 -> 5575.9 | G19: =輸入與假設!C$36+(輸入與假設!D$36-輸入與假設!C$36)*1/2 -> 6738.85 | H19: =輸入與假設!C$36+(輸入與假設!D$36-輸入與假設!C$36)*2/2 -> 7901.8 | J19: 期初與期末 Accepted 之間線性內插；第 1 期起點見 J 區
A20: 平均在役 MW（Billable，拆分依據） | B20: MW | C20: =輸入與假設!$C$29+(運營_產能與收入!C$11-輸入與假設!$C$29)*1/8 -> 3540.7375 | D20: =輸入與假設!$C$29+(運營_產能與收入!C$11-輸入與假設!$C$29)*3/8 -> 4122.2125 | E20: =輸入與假設!$C$29+(運營_產能與收入!C$11-輸入與假設!$C$29)*5/8 -> 4703.6875 | F20: =輸入與假設!$C$29+(運營_產能與收入!C$11-輸入與假設!$C$29)*7/8 -> 5285.1625 | G20: =運營_產能與收入!C$11+(運營_產能與收入!D$11-運營_產能與收入!C$11)*1/4 -> 6157.375 | H20: =運營_產能與收入!C$11+(運營_產能與收入!D$11-運營_產能與收入!C$11)*3/4 -> 7320.325 | J20: 期初與期末 Billable 之間線性內插的季平均
A21: 季內新增 Accepted MW | B21: MW | C21: =C19-輸入與假設!$C$517 -> 581.475 | D21: =D19-C19 -> 581.475 | E21: =E19-D19 -> 581.475 | F21: =F19-E19 -> 581.475 | G21: =G19-輸入與假設!C$36 -> 1162.95 | H21: =H19-G19 -> 1162.95 | J21: CapEx 拆分依據
A22: 營收（模型） | B22: US$bn | C22: =輸入與假設!$C$516+1*(損益!C9-4*輸入與假設!$C$516)/10 -> 93.748759 | D22: =輸入與假設!$C$516+2*(損益!C9-4*輸入與假設!$C$516)/10 -> 97.490518 | E22: =輸入與假設!$C$516+3*(損益!C9-4*輸入與假設!$C$516)/10 -> 101.23228 | F22: =輸入與假設!$C$516+4*(損益!C9-4*輸入與假設!$C$516)/10 -> 104.97404 | G22: =損益!D9*G20/(G20+H20) -> 215.37328 | H22: =損益!D9*H20/(G20+H20) -> 256.05106 | J22: 拆分方法見『輸入與假設』J 區與 HTML「拆分方法」
A23: EBITDA 率直線｜各期營收合計 S | C23: =C22+D22+E22+F22 -> 397.44559 | D23: =G22+H22 -> 471.42433 | J23: 欄＝期間（FY27、FY28）
A24: EBITDA 率直線｜營收 × 季序合計 T | C24: =C22*C18+D22*D18+E22*E18+F22*F18 -> 1012.3228 | D24: =G22*G18+H22*H18 -> 2613.1727 | J24: 欄＝期間（FY27、FY28）
A25: EBITDA 率直線｜年度 EBITDA E | C25: =損益!C22 -> 232.86728 | D25: =損益!D22 -> 282.29401 | J25: 欄＝期間（FY27、FY28）
A26: EBITDA 率直線｜截距 a／斜率 b | C26: =(C25*D24-C24*D25)/(C23*D24-C24*D23) -> 0.5749422 | D26: =(C23*D25-D23*C25)/(C23*D24-C24*D23) -> 0.0043059795 | J26: 解兩式：Σ營收×(a＋b×季序)＝各期年度 EBITDA
A27: EBITDA 率（模型） | B27: % | C27: =$C$26+$D$26*C18 -> 0.57924818 | D27: =$C$26+$D$26*D18 -> 0.58355416 | E27: =$C$26+$D$26*E18 -> 0.58786014 | F27: =$C$26+$D$26*F18 -> 0.59216612 | G27: =$C$26+$D$26*G18 -> 0.5964721 | H27: =$C$26+$D$26*H18 -> 0.60077808 | J27: 跨季一條直線，季度 EBITDA 加總＝年度
A28: 調整後 EBITDA（模型） | B28: US$bn | C28: =C22*C27 -> 54.303798 | D28: =D22*D27 -> 56.890997 | E28: =E22*E27 -> 59.51042 | F28: =F22*F27 -> 62.162067 | G28: =G22*G27 -> 128.46415 | H28: =H22*H27 -> 153.82986
A29: 車隊折舊（模型） | B29: US$bn | C29: =輸入與假設!C$288/4 -> 13.29512 | D29: =輸入與假設!C$288/4 -> 13.29512 | E29: =輸入與假設!C$288/4 -> 13.29512 | F29: =輸入與假設!C$288/4 -> 13.29512 | G29: =輸入與假設!D$288/2 -> 41.141534 | H29: =輸入與假設!D$288/2 -> 41.141534 | J29: ＝期間 D&A（AI＋非 AI 分池）÷ 期內季數
A30: 其他攤銷（模型） | B30: US$bn | C30: =輸入與假設!C$206*C22/MAX(0.000000001,C23) -> 0 | D30: =輸入與假設!C$206*D22/MAX(0.000000001,C23) -> 0 | E30: =輸入與假設!C$206*E22/MAX(0.000000001,C23) -> 0 | F30: =輸入與假設!C$206*F22/MAX(0.000000001,C23) -> 0 | G30: =輸入與假設!D$206*G22/MAX(0.000000001,D23) -> 0 | H30: =輸入與假設!D$206*H22/MAX(0.000000001,D23) -> 0 | J30: ＝期間非 AI 事業其他攤銷 × 季營收占比（MAG v0.1b）
A31: 調整後營業利益（模型） | B31: US$bn | C31: =C28-C29-C30 -> 41.008678 | D31: =D28-D29-D30 -> 43.595877 | E31: =E28-E29-E30 -> 46.2153 | F31: =F28-F29-F30 -> 48.866947 | G31: =G28-G29-G30 -> 87.322616 | H31: =H28-H29-H30 -> 112.68833 | J31: ＝調整後 EBITDA − 車隊折舊 − 其他攤銷（未扣 SBC）
A32: 指引｜營收（低） | B32: US$bn | C32: =IF(ISNUMBER(輸入與假設!C$526),輸入與假設!C$526,"不適用") -> 89.85 | D32: =IF(ISNUMBER(輸入與假設!D$526),輸入與假設!D$526,"不適用") -> 不適用 | E32: =IF(ISNUMBER(輸入與假設!E$526),輸入與假設!E$526,"不適用") -> 不適用 | F32: =IF(ISNUMBER(輸入與假設!F$526),輸入與假設!F$526,"不適用") -> 不適用 | G32: =IF(ISNUMBER(輸入與假設!G$526),輸入與假設!G$526,"不適用") -> 不適用 | H32: =IF(ISNUMBER(輸入與假設!H$526),輸入與假設!H$526,"不適用") -> 不適用
A33: 指引｜營收（高） | B33: US$bn | C33: =IF(ISNUMBER(輸入與假設!C$527),輸入與假設!C$527,"不適用") -> 90.95 | D33: =IF(ISNUMBER(輸入與假設!D$527),輸入與假設!D$527,"不適用") -> 不適用 | E33: =IF(ISNUMBER(輸入與假設!E$527),輸入與假設!E$527,"不適用") -> 不適用 | F33: =IF(ISNUMBER(輸入與假設!F$527),輸入與假設!F$527,"不適用") -> 不適用 | G33: =IF(ISNUMBER(輸入與假設!G$527),輸入與假設!G$527,"不適用") -> 不適用 | H33: =IF(ISNUMBER(輸入與假設!H$527),輸入與假設!H$527,"不適用") -> 不適用
A34: 指引｜調整後營業利益（低） | B34: US$bn | C34: =IF(ISNUMBER(輸入與假設!C$528),輸入與假設!C$528,"不適用") -> 43.15 | D34: =IF(ISNUMBER(輸入與假設!D$528),輸入與假設!D$528,"不適用") -> 不適用 | E34: =IF(ISNUMBER(輸入與假設!E$528),輸入與假設!E$528,"不適用") -> 不適用 | F34: =IF(ISNUMBER(輸入與假設!F$528),輸入與假設!F$528,"不適用") -> 不適用 | G34: =IF(ISNUMBER(輸入與假設!G$528),輸入與假設!G$528,"不適用") -> 不適用 | H34: =IF(ISNUMBER(輸入與假設!H$528),輸入與假設!H$528,"不適用") -> 不適用
A35: 指引｜調整後營業利益（高） | B35: US$bn | C35: =IF(ISNUMBER(輸入與假設!C$529),輸入與假設!C$529,"不適用") -> 44.55 | D35: =IF(ISNUMBER(輸入與假設!D$529),輸入與假設!D$529,"不適用") -> 不適用 | E35: =IF(ISNUMBER(輸入與假設!E$529),輸入與假設!E$529,"不適用") -> 不適用 | F35: =IF(ISNUMBER(輸入與假設!F$529),輸入與假設!F$529,"不適用") -> 不適用 | G35: =IF(ISNUMBER(輸入與假設!G$529),輸入與假設!G$529,"不適用") -> 不適用 | H35: =IF(ISNUMBER(輸入與假設!H$529),輸入與假設!H$529,"不適用") -> 不適用
A36: CapEx（毛額）（模型） | B36: US$bn | C36: =IF((C21+D21+E21+F21)>0,輸入與假設!C$287*C21/(C21+D21+E21+F21),輸入與假設!C$287/4) -> 51.050433 | D36: =IF((C21+D21+E21+F21)>0,輸入與假設!C$287*D21/(C21+D21+E21+F21),輸入與假設!C$287/4) -> 51.050433 | E36: =IF((C21+D21+E21+F21)>0,輸入與假設!C$287*E21/(C21+D21+E21+F21),輸入與假設!C$287/4) -> 51.050433 | F36: =IF((C21+D21+E21+F21)>0,輸入與假設!C$287*F21/(C21+D21+E21+F21),輸入與假設!C$287/4) -> 51.050433 | G36: =IF((G21+H21)>0,輸入與假設!D$287*G21/(G21+H21),輸入與假設!D$287/2) -> 108.10368 | H36: =IF((G21+H21)>0,輸入與假設!D$287*H21/(G21+H21),輸入與假設!D$287/2) -> 108.10368 | J36: 依季內新增 Accepted MW
A37: 共識｜營收 | B37: US$bn | C37: =IF(ISNUMBER(輸入與假設!$C$495),輸入與假設!$C$495,"不適用") -> 90.685 | D37: 不適用 | E37: 不適用 | F37: 不適用 | G37: 不適用 | H37: 不適用 | J37: I 區季度共識 [Interested-party]
A38: 共識｜調整後 EBITDA | B38: US$bn | C38: =IF(ISNUMBER(輸入與假設!$C$496),輸入與假設!$C$496,"不適用") -> 56.56 | D38: 不適用 | E38: 不適用 | F38: 不適用 | G38: 不適用 | H38: 不適用 | J38: I 區季度共識 [Interested-party]
A39: 共識｜EBITDA 率 [Derived] | B39: % | C39: =IF(AND(ISNUMBER(輸入與假設!$C$496),ISNUMBER(輸入與假設!$C$495)),輸入與假設!$C$496/輸入與假設!$C$495,"不適用") -> 0.62369741 | D39: 不適用 | E39: 不適用 | F39: 不適用 | G39: 不適用 | H39: 不適用 | J39: ＝共識 EBITDA ÷ 共識營收
A40: 共識 EBIT（供應商口徑） | B40: US$bn | C40: =IF(ISNUMBER(輸入與假設!$C$497),輸入與假設!$C$497,"不適用") -> 43.994 | D40: 不適用 | E40: 不適用 | F40: 不適用 | G40: 不適用 | H40: 不適用 | J40: 口徑未揭露：只列不比較
A41: 實際｜營收 | B41: US$bn | C41: =IF(ISNUMBER(輸入與假設!C$518),輸入與假設!C$518,"") | D41: =IF(ISNUMBER(輸入與假設!D$518),輸入與假設!D$518,"") | E41: =IF(ISNUMBER(輸入與假設!E$518),輸入與假設!E$518,"") | F41: =IF(ISNUMBER(輸入與假設!F$518),輸入與假設!F$518,"") | G41: =IF(ISNUMBER(輸入與假設!G$518),輸入與假設!G$518,"") | H41: =IF(ISNUMBER(輸入與假設!H$518),輸入與假設!H$518,"")
A42: 實際｜調整後 EBITDA | B42: US$bn | C42: =IF(ISNUMBER(輸入與假設!C$519),輸入與假設!C$519,"") | D42: =IF(ISNUMBER(輸入與假設!D$519),輸入與假設!D$519,"") | E42: =IF(ISNUMBER(輸入與假設!E$519),輸入與假設!E$519,"") | F42: =IF(ISNUMBER(輸入與假設!F$519),輸入與假設!F$519,"") | G42: =IF(ISNUMBER(輸入與假設!G$519),輸入與假設!G$519,"") | H42: =IF(ISNUMBER(輸入與假設!H$519),輸入與假設!H$519,"")
A43: 實際｜EBITDA 率 | B43: % | C43: =IF(AND(ISNUMBER(輸入與假設!C$519),ISNUMBER(輸入與假設!C$518)),輸入與假設!C$519/輸入與假設!C$518,"") | D43: =IF(AND(ISNUMBER(輸入與假設!D$519),ISNUMBER(輸入與假設!D$518)),輸入與假設!D$519/輸入與假設!D$518,"") | E43: =IF(AND(ISNUMBER(輸入與假設!E$519),ISNUMBER(輸入與假設!E$518)),輸入與假設!E$519/輸入與假設!E$518,"") | F43: =IF(AND(ISNUMBER(輸入與假設!F$519),ISNUMBER(輸入與假設!F$518)),輸入與假設!F$519/輸入與假設!F$518,"") | G43: =IF(AND(ISNUMBER(輸入與假設!G$519),ISNUMBER(輸入與假設!G$518)),輸入與假設!G$519/輸入與假設!G$518,"") | H43: =IF(AND(ISNUMBER(輸入與假設!H$519),ISNUMBER(輸入與假設!H$518)),輸入與假設!H$519/輸入與假設!H$518,"") | J43: ＝實際 EBITDA ÷ 實際營收
A44: 實際｜調整後營業利益 | B44: US$bn | C44: =IF(ISNUMBER(輸入與假設!C$520),輸入與假設!C$520,"") | D44: =IF(ISNUMBER(輸入與假設!D$520),輸入與假設!D$520,"") | E44: =IF(ISNUMBER(輸入與假設!E$520),輸入與假設!E$520,"") | F44: =IF(ISNUMBER(輸入與假設!F$520),輸入與假設!F$520,"") | G44: =IF(ISNUMBER(輸入與假設!G$520),輸入與假設!G$520,"") | H44: =IF(ISNUMBER(輸入與假設!H$520),輸入與假設!H$520,"")
A45: 實際｜CapEx（毛額） | B45: US$bn | C45: =IF(ISNUMBER(輸入與假設!C$521),輸入與假設!C$521,"") | D45: =IF(ISNUMBER(輸入與假設!D$521),輸入與假設!D$521,"") | E45: =IF(ISNUMBER(輸入與假設!E$521),輸入與假設!E$521,"") | F45: =IF(ISNUMBER(輸入與假設!F$521),輸入與假設!F$521,"") | G45: =IF(ISNUMBER(輸入與假設!G$521),輸入與假設!G$521,"") | H45: =IF(ISNUMBER(輸入與假設!H$521),輸入與假設!H$521,"")
A46: 實際｜季末對外 AI MW（未揭露） | B46: MW | C46: =IF(ISNUMBER(輸入與假設!C$522),輸入與假設!C$522,"") | D46: =IF(ISNUMBER(輸入與假設!D$522),輸入與假設!D$522,"") | E46: =IF(ISNUMBER(輸入與假設!E$522),輸入與假設!E$522,"") | F46: =IF(ISNUMBER(輸入與假設!F$522),輸入與假設!F$522,"") | G46: =IF(ISNUMBER(輸入與假設!G$522),輸入與假設!G$522,"") | H46: =IF(ISNUMBER(輸入與假設!H$522),輸入與假設!H$522,"")
A47: 差距｜營收｜模型 vs 共識 | B47: % | C47: =IF(AND(ISNUMBER(C22),ISNUMBER(C37),C37<>0),C22/(C37)-1,"不適用") -> 0.033784626 | D47: =IF(AND(ISNUMBER(D22),ISNUMBER(D37),D37<>0),D22/(D37)-1,"不適用") -> 不適用 | E47: =IF(AND(ISNUMBER(E22),ISNUMBER(E37),E37<>0),E22/(E37)-1,"不適用") -> 不適用 | F47: =IF(AND(ISNUMBER(F22),ISNUMBER(F37),F37<>0),F22/(F37)-1,"不適用") -> 不適用 | G47: =IF(AND(ISNUMBER(G22),ISNUMBER(G37),G37<>0),G22/(G37)-1,"不適用") -> 不適用 | H47: =IF(AND(ISNUMBER(H22),ISNUMBER(H37),H37<>0),H22/(H37)-1,"不適用") -> 不適用
A48: 差距｜營收｜模型 vs 指引中點 | B48: % | C48: =IF(AND(ISNUMBER(C22),ISNUMBER(C32),ISNUMBER(C33)),C22/(((C32+C33)/2))-1,"不適用") -> 0.037043792 | D48: =IF(AND(ISNUMBER(D22),ISNUMBER(D32),ISNUMBER(D33)),D22/(((D32+D33)/2))-1,"不適用") -> 不適用 | E48: =IF(AND(ISNUMBER(E22),ISNUMBER(E32),ISNUMBER(E33)),E22/(((E32+E33)/2))-1,"不適用") -> 不適用 | F48: =IF(AND(ISNUMBER(F22),ISNUMBER(F32),ISNUMBER(F33)),F22/(((F32+F33)/2))-1,"不適用") -> 不適用 | G48: =IF(AND(ISNUMBER(G22),ISNUMBER(G32),ISNUMBER(G33)),G22/(((G32+G33)/2))-1,"不適用") -> 不適用 | H48: =IF(AND(ISNUMBER(H22),ISNUMBER(H32),ISNUMBER(H33)),H22/(((H32+H33)/2))-1,"不適用") -> 不適用
A49: 差距｜營收｜實際 vs 模型 | B49: % | C49: =IF(ISNUMBER(C41),IF(AND(ISNUMBER(C22),C22<>0),C41/(C22)-1,"不適用"),"") | D49: =IF(ISNUMBER(D41),IF(AND(ISNUMBER(D22),D22<>0),D41/(D22)-1,"不適用"),"") | E49: =IF(ISNUMBER(E41),IF(AND(ISNUMBER(E22),E22<>0),E41/(E22)-1,"不適用"),"") | F49: =IF(ISNUMBER(F41),IF(AND(ISNUMBER(F22),F22<>0),F41/(F22)-1,"不適用"),"") | G49: =IF(ISNUMBER(G41),IF(AND(ISNUMBER(G22),G22<>0),G41/(G22)-1,"不適用"),"") | H49: =IF(ISNUMBER(H41),IF(AND(ISNUMBER(H22),H22<>0),H41/(H22)-1,"不適用"),"")
A50: 差距｜營收｜實際 vs 共識 | B50: % | C50: =IF(ISNUMBER(C41),IF(AND(ISNUMBER(C37),C37<>0),C41/(C37)-1,"不適用"),"") | D50: =IF(ISNUMBER(D41),IF(AND(ISNUMBER(D37),D37<>0),D41/(D37)-1,"不適用"),"") | E50: =IF(ISNUMBER(E41),IF(AND(ISNUMBER(E37),E37<>0),E41/(E37)-1,"不適用"),"") | F50: =IF(ISNUMBER(F41),IF(AND(ISNUMBER(F37),F37<>0),F41/(F37)-1,"不適用"),"") | G50: =IF(ISNUMBER(G41),IF(AND(ISNUMBER(G37),G37<>0),G41/(G37)-1,"不適用"),"") | H50: =IF(ISNUMBER(H41),IF(AND(ISNUMBER(H37),H37<>0),H41/(H37)-1,"不適用"),"")
A51: 差距｜營收｜實際 vs 指引中點 | B51: % | C51: =IF(ISNUMBER(C41),IF(AND(ISNUMBER(C32),ISNUMBER(C33)),C41/(((C32+C33)/2))-1,"不適用"),"") | D51: =IF(ISNUMBER(D41),IF(AND(ISNUMBER(D32),ISNUMBER(D33)),D41/(((D32+D33)/2))-1,"不適用"),"") | E51: =IF(ISNUMBER(E41),IF(AND(ISNUMBER(E32),ISNUMBER(E33)),E41/(((E32+E33)/2))-1,"不適用"),"") | F51: =IF(ISNUMBER(F41),IF(AND(ISNUMBER(F32),ISNUMBER(F33)),F41/(((F32+F33)/2))-1,"不適用"),"") | G51: =IF(ISNUMBER(G41),IF(AND(ISNUMBER(G32),ISNUMBER(G33)),G41/(((G32+G33)/2))-1,"不適用"),"") | H51: =IF(ISNUMBER(H41),IF(AND(ISNUMBER(H32),ISNUMBER(H33)),H41/(((H32+H33)/2))-1,"不適用"),"")
A52: 差距｜調整後 EBITDA｜模型 vs 共識 | B52: US$bn | C52: =IF(AND(ISNUMBER(C28),ISNUMBER(C38)),C28-(C38),"不適用") -> -2.2562018 | D52: =IF(AND(ISNUMBER(D28),ISNUMBER(D38)),D28-(D38),"不適用") -> 不適用 | E52: =IF(AND(ISNUMBER(E28),ISNUMBER(E38)),E28-(E38),"不適用") -> 不適用 | F52: =IF(AND(ISNUMBER(F28),ISNUMBER(F38)),F28-(F38),"不適用") -> 不適用 | G52: =IF(AND(ISNUMBER(G28),ISNUMBER(G38)),G28-(G38),"不適用") -> 不適用 | H52: =IF(AND(ISNUMBER(H28),ISNUMBER(H38)),H28-(H38),"不適用") -> 不適用
A53: 差距｜調整後 EBITDA｜模型 vs 指引中點 | B53: US$bn | C53: 不適用 | D53: 不適用 | E53: 不適用 | F53: 不適用 | G53: 不適用 | H53: 不適用
A54: 差距｜調整後 EBITDA｜實際 vs 模型 | B54: US$bn | C54: =IF(ISNUMBER(C42),IF(AND(ISNUMBER(C28)),C42-(C28),"不適用"),"") | D54: =IF(ISNUMBER(D42),IF(AND(ISNUMBER(D28)),D42-(D28),"不適用"),"") | E54: =IF(ISNUMBER(E42),IF(AND(ISNUMBER(E28)),E42-(E28),"不適用"),"") | F54: =IF(ISNUMBER(F42),IF(AND(ISNUMBER(F28)),F42-(F28),"不適用"),"") | G54: =IF(ISNUMBER(G42),IF(AND(ISNUMBER(G28)),G42-(G28),"不適用"),"") | H54: =IF(ISNUMBER(H42),IF(AND(ISNUMBER(H28)),H42-(H28),"不適用"),"")
A55: 差距｜調整後 EBITDA｜實際 vs 共識 | B55: US$bn | C55: =IF(ISNUMBER(C42),IF(AND(ISNUMBER(C38)),C42-(C38),"不適用"),"") | D55: =IF(ISNUMBER(D42),IF(AND(ISNUMBER(D38)),D42-(D38),"不適用"),"") | E55: =IF(ISNUMBER(E42),IF(AND(ISNUMBER(E38)),E42-(E38),"不適用"),"") | F55: =IF(ISNUMBER(F42),IF(AND(ISNUMBER(F38)),F42-(F38),"不適用"),"") | G55: =IF(ISNUMBER(G42),IF(AND(ISNUMBER(G38)),G42-(G38),"不適用"),"") | H55: =IF(ISNUMBER(H42),IF(AND(ISNUMBER(H38)),H42-(H38),"不適用"),"")
A56: 差距｜調整後 EBITDA｜實際 vs 指引中點 | B56: US$bn | C56: =IF(ISNUMBER(C42),"不適用","") | D56: =IF(ISNUMBER(D42),"不適用","") | E56: =IF(ISNUMBER(E42),"不適用","") | F56: =IF(ISNUMBER(F42),"不適用","") | G56: =IF(ISNUMBER(G42),"不適用","") | H56: =IF(ISNUMBER(H42),"不適用","")
A57: 差距｜調整後 EBITDA｜模型 vs 共識（利潤率 pt） | B57: pt | C57: =IF(AND(ISNUMBER(C28),ISNUMBER(C22),C22<>0,ISNUMBER(C38),ISNUMBER(C37),C37<>0),C28/C22-C38/C37,"不適用") -> -0.044449231 | D57: =IF(AND(ISNUMBER(D28),ISNUMBER(D22),D22<>0,ISNUMBER(D38),ISNUMBER(D37),D37<>0),D28/D22-D38/D37,"不適用") -> 不適用 | E57: =IF(AND(ISNUMBER(E28),ISNUMBER(E22),E22<>0,ISNUMBER(E38),ISNUMBER(E37),E37<>0),E28/E22-E38/E37,"不適用") -> 不適用 | F57: =IF(AND(ISNUMBER(F28),ISNUMBER(F22),F22<>0,ISNUMBER(F38),ISNUMBER(F37),F37<>0),F28/F22-F38/F37,"不適用") -> 不適用 | G57: =IF(AND(ISNUMBER(G28),ISNUMBER(G22),G22<>0,ISNUMBER(G38),ISNUMBER(G37),G37<>0),G28/G22-G38/G37,"不適用") -> 不適用 | H57: =IF(AND(ISNUMBER(H28),ISNUMBER(H22),H22<>0,ISNUMBER(H38),ISNUMBER(H37),H37<>0),H28/H22-H38/H37,"不適用") -> 不適用
A58: 差距｜調整後 EBITDA｜模型 vs 指引中點（利潤率 pt） | B58: pt | C58: 不適用 | D58: 不適用 | E58: 不適用 | F58: 不適用 | G58: 不適用 | H58: 不適用
A59: 差距｜調整後 EBITDA｜實際 vs 模型（利潤率 pt） | B59: pt | C59: =IF(ISNUMBER(C42),IF(AND(ISNUMBER(C42),ISNUMBER(C41),C41<>0,ISNUMBER(C28),ISNUMBER(C22),C22<>0),C42/C41-C28/C22,"不適用"),"") | D59: =IF(ISNUMBER(D42),IF(AND(ISNUMBER(D42),ISNUMBER(D41),D41<>0,ISNUMBER(D28),ISNUMBER(D22),D22<>0),D42/D41-D28/D22,"不適用"),"") | E59: =IF(ISNUMBER(E42),IF(AND(ISNUMBER(E42),ISNUMBER(E41),E41<>0,ISNUMBER(E28),ISNUMBER(E22),E22<>0),E42/E41-E28/E22,"不適用"),"") | F59: =IF(ISNUMBER(F42),IF(AND(ISNUMBER(F42),ISNUMBER(F41),F41<>0,ISNUMBER(F28),ISNUMBER(F22),F22<>0),F42/F41-F28/F22,"不適用"),"") | G59: =IF(ISNUMBER(G42),IF(AND(ISNUMBER(G42),ISNUMBER(G41),G41<>0,ISNUMBER(G28),ISNUMBER(G22),G22<>0),G42/G41-G28/G22,"不適用"),"") | H59: =IF(ISNUMBER(H42),IF(AND(ISNUMBER(H42),ISNUMBER(H41),H41<>0,ISNUMBER(H28),ISNUMBER(H22),H22<>0),H42/H41-H28/H22,"不適用"),"")
A60: 差距｜調整後 EBITDA｜實際 vs 共識（利潤率 pt） | B60: pt | C60: =IF(ISNUMBER(C42),IF(AND(ISNUMBER(C42),ISNUMBER(C41),C41<>0,ISNUMBER(C38),ISNUMBER(C37),C37<>0),C42/C41-C38/C37,"不適用"),"") | D60: =IF(ISNUMBER(D42),IF(AND(ISNUMBER(D42),ISNUMBER(D41),D41<>0,ISNUMBER(D38),ISNUMBER(D37),D37<>0),D42/D41-D38/D37,"不適用"),"") | E60: =IF(ISNUMBER(E42),IF(AND(ISNUMBER(E42),ISNUMBER(E41),E41<>0,ISNUMBER(E38),ISNUMBER(E37),E37<>0),E42/E41-E38/E37,"不適用"),"") | F60: =IF(ISNUMBER(F42),IF(AND(ISNUMBER(F42),ISNUMBER(F41),F41<>0,ISNUMBER(F38),ISNUMBER(F37),F37<>0),F42/F41-F38/F37,"不適用"),"") | G60: =IF(ISNUMBER(G42),IF(AND(ISNUMBER(G42),ISNUMBER(G41),G41<>0,ISNUMBER(G38),ISNUMBER(G37),G37<>0),G42/G41-G38/G37,"不適用"),"") | H60: =IF(ISNUMBER(H42),IF(AND(ISNUMBER(H42),ISNUMBER(H41),H41<>0,ISNUMBER(H38),ISNUMBER(H37),H37<>0),H42/H41-H38/H37,"不適用"),"")
A61: 差距｜調整後 EBITDA｜實際 vs 指引中點（利潤率 pt） | B61: pt | C61: =IF(ISNUMBER(C42),"不適用","") | D61: =IF(ISNUMBER(D42),"不適用","") | E61: =IF(ISNUMBER(E42),"不適用","") | F61: =IF(ISNUMBER(F42),"不適用","") | G61: =IF(ISNUMBER(G42),"不適用","") | H61: =IF(ISNUMBER(H42),"不適用","")
A62: 差距｜EBITDA 率｜模型 vs 共識 | B62: pt | C62: =IF(AND(ISNUMBER(C27),ISNUMBER(C39)),C27-(C39),"不適用") -> -0.044449231 | D62: =IF(AND(ISNUMBER(D27),ISNUMBER(D39)),D27-(D39),"不適用") -> 不適用 | E62: =IF(AND(ISNUMBER(E27),ISNUMBER(E39)),E27-(E39),"不適用") -> 不適用 | F62: =IF(AND(ISNUMBER(F27),ISNUMBER(F39)),F27-(F39),"不適用") -> 不適用 | G62: =IF(AND(ISNUMBER(G27),ISNUMBER(G39)),G27-(G39),"不適用") -> 不適用 | H62: =IF(AND(ISNUMBER(H27),ISNUMBER(H39)),H27-(H39),"不適用") -> 不適用
A63: 差距｜EBITDA 率｜模型 vs 指引中點 | B63: pt | C63: 不適用 | D63: 不適用 | E63: 不適用 | F63: 不適用 | G63: 不適用 | H63: 不適用
A64: 差距｜EBITDA 率｜實際 vs 模型 | B64: pt | C64: =IF(ISNUMBER(C43),IF(AND(ISNUMBER(C27)),C43-(C27),"不適用"),"") | D64: =IF(ISNUMBER(D43),IF(AND(ISNUMBER(D27)),D43-(D27),"不適用"),"") | E64: =IF(ISNUMBER(E43),IF(AND(ISNUMBER(E27)),E43-(E27),"不適用"),"") | F64: =IF(ISNUMBER(F43),IF(AND(ISNUMBER(F27)),F43-(F27),"不適用"),"") | G64: =IF(ISNUMBER(G43),IF(AND(ISNUMBER(G27)),G43-(G27),"不適用"),"") | H64: =IF(ISNUMBER(H43),IF(AND(ISNUMBER(H27)),H43-(H27),"不適用"),"")
A65: 差距｜EBITDA 率｜實際 vs 共識 | B65: pt | C65: =IF(ISNUMBER(C43),IF(AND(ISNUMBER(C39)),C43-(C39),"不適用"),"") | D65: =IF(ISNUMBER(D43),IF(AND(ISNUMBER(D39)),D43-(D39),"不適用"),"") | E65: =IF(ISNUMBER(E43),IF(AND(ISNUMBER(E39)),E43-(E39),"不適用"),"") | F65: =IF(ISNUMBER(F43),IF(AND(ISNUMBER(F39)),F43-(F39),"不適用"),"") | G65: =IF(ISNUMBER(G43),IF(AND(ISNUMBER(G39)),G43-(G39),"不適用"),"") | H65: =IF(ISNUMBER(H43),IF(AND(ISNUMBER(H39)),H43-(H39),"不適用"),"")
A66: 差距｜EBITDA 率｜實際 vs 指引中點 | B66: pt | C66: =IF(ISNUMBER(C43),"不適用","") | D66: =IF(ISNUMBER(D43),"不適用","") | E66: =IF(ISNUMBER(E43),"不適用","") | F66: =IF(ISNUMBER(F43),"不適用","") | G66: =IF(ISNUMBER(G43),"不適用","") | H66: =IF(ISNUMBER(H43),"不適用","")
A67: 差距｜調整後營業利益｜模型 vs 共識 | B67: US$bn | C67: 不適用 | D67: 不適用 | E67: 不適用 | F67: 不適用 | G67: 不適用 | H67: 不適用
A68: 差距｜調整後營業利益｜模型 vs 指引中點 | B68: US$bn | C68: =IF(AND(ISNUMBER(C31),ISNUMBER(C34),ISNUMBER(C35)),C31-(((C34+C35)/2)),"不適用") -> -2.8413222 | D68: =IF(AND(ISNUMBER(D31),ISNUMBER(D34),ISNUMBER(D35)),D31-(((D34+D35)/2)),"不適用") -> 不適用 | E68: =IF(AND(ISNUMBER(E31),ISNUMBER(E34),ISNUMBER(E35)),E31-(((E34+E35)/2)),"不適用") -> 不適用 | F68: =IF(AND(ISNUMBER(F31),ISNUMBER(F34),ISNUMBER(F35)),F31-(((F34+F35)/2)),"不適用") -> 不適用 | G68: =IF(AND(ISNUMBER(G31),ISNUMBER(G34),ISNUMBER(G35)),G31-(((G34+G35)/2)),"不適用") -> 不適用 | H68: =IF(AND(ISNUMBER(H31),ISNUMBER(H34),ISNUMBER(H35)),H31-(((H34+H35)/2)),"不適用") -> 不適用
A69: 差距｜調整後營業利益｜實際 vs 模型 | B69: US$bn | C69: =IF(ISNUMBER(C44),IF(AND(ISNUMBER(C31)),C44-(C31),"不適用"),"") | D69: =IF(ISNUMBER(D44),IF(AND(ISNUMBER(D31)),D44-(D31),"不適用"),"") | E69: =IF(ISNUMBER(E44),IF(AND(ISNUMBER(E31)),E44-(E31),"不適用"),"") | F69: =IF(ISNUMBER(F44),IF(AND(ISNUMBER(F31)),F44-(F31),"不適用"),"") | G69: =IF(ISNUMBER(G44),IF(AND(ISNUMBER(G31)),G44-(G31),"不適用"),"") | H69: =IF(ISNUMBER(H44),IF(AND(ISNUMBER(H31)),H44-(H31),"不適用"),"")
A70: 差距｜調整後營業利益｜實際 vs 共識 | B70: US$bn | C70: =IF(ISNUMBER(C44),"不適用","") | D70: =IF(ISNUMBER(D44),"不適用","") | E70: =IF(ISNUMBER(E44),"不適用","") | F70: =IF(ISNUMBER(F44),"不適用","") | G70: =IF(ISNUMBER(G44),"不適用","") | H70: =IF(ISNUMBER(H44),"不適用","")
A71: 差距｜調整後營業利益｜實際 vs 指引中點 | B71: US$bn | C71: =IF(ISNUMBER(C44),IF(AND(ISNUMBER(C34),ISNUMBER(C35)),C44-(((C34+C35)/2)),"不適用"),"") | D71: =IF(ISNUMBER(D44),IF(AND(ISNUMBER(D34),ISNUMBER(D35)),D44-(((D34+D35)/2)),"不適用"),"") | E71: =IF(ISNUMBER(E44),IF(AND(ISNUMBER(E34),ISNUMBER(E35)),E44-(((E34+E35)/2)),"不適用"),"") | F71: =IF(ISNUMBER(F44),IF(AND(ISNUMBER(F34),ISNUMBER(F35)),F44-(((F34+F35)/2)),"不適用"),"") | G71: =IF(ISNUMBER(G44),IF(AND(ISNUMBER(G34),ISNUMBER(G35)),G44-(((G34+G35)/2)),"不適用"),"") | H71: =IF(ISNUMBER(H44),IF(AND(ISNUMBER(H34),ISNUMBER(H35)),H44-(((H34+H35)/2)),"不適用"),"")
A72: 差距｜調整後營業利益｜模型 vs 共識（利潤率 pt） | B72: pt | C72: 不適用 | D72: 不適用 | E72: 不適用 | F72: 不適用 | G72: 不適用 | H72: 不適用
A73: 差距｜調整後營業利益｜模型 vs 指引中點（利潤率 pt） | B73: pt | C73: =IF(AND(ISNUMBER(C31),ISNUMBER(C22),C22<>0,ISNUMBER(C34),ISNUMBER(C35),ISNUMBER(C32),ISNUMBER(C33)),C31/C22-((C34+C35)/2)/((C32+C33)/2),"不適用") -> -0.047634684 | D73: =IF(AND(ISNUMBER(D31),ISNUMBER(D22),D22<>0,ISNUMBER(D34),ISNUMBER(D35),ISNUMBER(D32),ISNUMBER(D33)),D31/D22-((D34+D35)/2)/((D32+D33)/2),"不適用") -> 不適用 | E73: =IF(AND(ISNUMBER(E31),ISNUMBER(E22),E22<>0,ISNUMBER(E34),ISNUMBER(E35),ISNUMBER(E32),ISNUMBER(E33)),E31/E22-((E34+E35)/2)/((E32+E33)/2),"不適用") -> 不適用 | F73: =IF(AND(ISNUMBER(F31),ISNUMBER(F22),F22<>0,ISNUMBER(F34),ISNUMBER(F35),ISNUMBER(F32),ISNUMBER(F33)),F31/F22-((F34+F35)/2)/((F32+F33)/2),"不適用") -> 不適用 | G73: =IF(AND(ISNUMBER(G31),ISNUMBER(G22),G22<>0,ISNUMBER(G34),ISNUMBER(G35),ISNUMBER(G32),ISNUMBER(G33)),G31/G22-((G34+G35)/2)/((G32+G33)/2),"不適用") -> 不適用 | H73: =IF(AND(ISNUMBER(H31),ISNUMBER(H22),H22<>0,ISNUMBER(H34),ISNUMBER(H35),ISNUMBER(H32),ISNUMBER(H33)),H31/H22-((H34+H35)/2)/((H32+H33)/2),"不適用") -> 不適用
A74: 差距｜調整後營業利益｜實際 vs 模型（利潤率 pt） | B74: pt | C74: =IF(ISNUMBER(C44),IF(AND(ISNUMBER(C44),ISNUMBER(C41),C41<>0,ISNUMBER(C31),ISNUMBER(C22),C22<>0),C44/C41-C31/C22,"不適用"),"") | D74: =IF(ISNUMBER(D44),IF(AND(ISNUMBER(D44),ISNUMBER(D41),D41<>0,ISNUMBER(D31),ISNUMBER(D22),D22<>0),D44/D41-D31/D22,"不適用"),"") | E74: =IF(ISNUMBER(E44),IF(AND(ISNUMBER(E44),ISNUMBER(E41),E41<>0,ISNUMBER(E31),ISNUMBER(E22),E22<>0),E44/E41-E31/E22,"不適用"),"") | F74: =IF(ISNUMBER(F44),IF(AND(ISNUMBER(F44),ISNUMBER(F41),F41<>0,ISNUMBER(F31),ISNUMBER(F22),F22<>0),F44/F41-F31/F22,"不適用"),"") | G74: =IF(ISNUMBER(G44),IF(AND(ISNUMBER(G44),ISNUMBER(G41),G41<>0,ISNUMBER(G31),ISNUMBER(G22),G22<>0),G44/G41-G31/G22,"不適用"),"") | H74: =IF(ISNUMBER(H44),IF(AND(ISNUMBER(H44),ISNUMBER(H41),H41<>0,ISNUMBER(H31),ISNUMBER(H22),H22<>0),H44/H41-H31/H22,"不適用"),"")
A75: 差距｜調整後營業利益｜實際 vs 共識（利潤率 pt） | B75: pt | C75: =IF(ISNUMBER(C44),"不適用","") | D75: =IF(ISNUMBER(D44),"不適用","") | E75: =IF(ISNUMBER(E44),"不適用","") | F75: =IF(ISNUMBER(F44),"不適用","") | G75: =IF(ISNUMBER(G44),"不適用","") | H75: =IF(ISNUMBER(H44),"不適用","")
A76: 差距｜調整後營業利益｜實際 vs 指引中點（利潤率 pt） | B76: pt | C76: =IF(ISNUMBER(C44),IF(AND(ISNUMBER(C44),ISNUMBER(C41),C41<>0,ISNUMBER(C34),ISNUMBER(C35),ISNUMBER(C32),ISNUMBER(C33)),C44/C41-((C34+C35)/2)/((C32+C33)/2),"不適用"),"") | D76: =IF(ISNUMBER(D44),IF(AND(ISNUMBER(D44),ISNUMBER(D41),D41<>0,ISNUMBER(D34),ISNUMBER(D35),ISNUMBER(D32),ISNUMBER(D33)),D44/D41-((D34+D35)/2)/((D32+D33)/2),"不適用"),"") | E76: =IF(ISNUMBER(E44),IF(AND(ISNUMBER(E44),ISNUMBER(E41),E41<>0,ISNUMBER(E34),ISNUMBER(E35),ISNUMBER(E32),ISNUMBER(E33)),E44/E41-((E34+E35)/2)/((E32+E33)/2),"不適用"),"") | F76: =IF(ISNUMBER(F44),IF(AND(ISNUMBER(F44),ISNUMBER(F41),F41<>0,ISNUMBER(F34),ISNUMBER(F35),ISNUMBER(F32),ISNUMBER(F33)),F44/F41-((F34+F35)/2)/((F32+F33)/2),"不適用"),"") | G76: =IF(ISNUMBER(G44),IF(AND(ISNUMBER(G44),ISNUMBER(G41),G41<>0,ISNUMBER(G34),ISNUMBER(G35),ISNUMBER(G32),ISNUMBER(G33)),G44/G41-((G34+G35)/2)/((G32+G33)/2),"不適用"),"") | H76: =IF(ISNUMBER(H44),IF(AND(ISNUMBER(H44),ISNUMBER(H41),H41<>0,ISNUMBER(H34),ISNUMBER(H35),ISNUMBER(H32),ISNUMBER(H33)),H44/H41-((H34+H35)/2)/((H32+H33)/2),"不適用"),"")
A77: 差距｜CapEx（毛額）｜模型 vs 共識 | B77: % | C77: 不適用 | D77: 不適用 | E77: 不適用 | F77: 不適用 | G77: 不適用 | H77: 不適用
A78: 差距｜CapEx（毛額）｜模型 vs 指引中點 | B78: % | C78: 不適用 | D78: 不適用 | E78: 不適用 | F78: 不適用 | G78: 不適用 | H78: 不適用
A79: 差距｜CapEx（毛額）｜實際 vs 模型 | B79: % | C79: =IF(ISNUMBER(C45),IF(AND(ISNUMBER(C36),C36<>0),C45/(C36)-1,"不適用"),"") | D79: =IF(ISNUMBER(D45),IF(AND(ISNUMBER(D36),D36<>0),D45/(D36)-1,"不適用"),"") | E79: =IF(ISNUMBER(E45),IF(AND(ISNUMBER(E36),E36<>0),E45/(E36)-1,"不適用"),"") | F79: =IF(ISNUMBER(F45),IF(AND(ISNUMBER(F36),F36<>0),F45/(F36)-1,"不適用"),"") | G79: =IF(ISNUMBER(G45),IF(AND(ISNUMBER(G36),G36<>0),G45/(G36)-1,"不適用"),"") | H79: =IF(ISNUMBER(H45),IF(AND(ISNUMBER(H36),H36<>0),H45/(H36)-1,"不適用"),"")
A80: 差距｜CapEx（毛額）｜實際 vs 共識 | B80: % | C80: =IF(ISNUMBER(C45),"不適用","") | D80: =IF(ISNUMBER(D45),"不適用","") | E80: =IF(ISNUMBER(E45),"不適用","") | F80: =IF(ISNUMBER(F45),"不適用","") | G80: =IF(ISNUMBER(G45),"不適用","") | H80: =IF(ISNUMBER(H45),"不適用","")
A81: 差距｜CapEx（毛額）｜實際 vs 指引中點 | B81: % | C81: =IF(ISNUMBER(C45),"不適用","") | D81: =IF(ISNUMBER(D45),"不適用","") | E81: =IF(ISNUMBER(E45),"不適用","") | F81: =IF(ISNUMBER(F45),"不適用","") | G81: =IF(ISNUMBER(G45),"不適用","") | H81: =IF(ISNUMBER(H45),"不適用","")
A82: 差距｜季末已連網 MW-IT｜模型 vs 共識 | B82: MW | C82: 不適用 | D82: 不適用 | E82: 不適用 | F82: 不適用 | G82: 不適用 | H82: 不適用
A83: 差距｜季末已連網 MW-IT｜模型 vs 指引中點 | B83: MW | C83: 不適用 | D83: 不適用 | E83: 不適用 | F83: 不適用 | G83: 不適用 | H83: 不適用
A84: 差距｜季末已連網 MW-IT｜實際 vs 模型 | B84: MW | C84: =IF(ISNUMBER(C46),IF(AND(ISNUMBER(C19)),C46-(C19),"不適用"),"") | D84: =IF(ISNUMBER(D46),IF(AND(ISNUMBER(D19)),D46-(D19),"不適用"),"") | E84: =IF(ISNUMBER(E46),IF(AND(ISNUMBER(E19)),E46-(E19),"不適用"),"") | F84: =IF(ISNUMBER(F46),IF(AND(ISNUMBER(F19)),F46-(F19),"不適用"),"") | G84: =IF(ISNUMBER(G46),IF(AND(ISNUMBER(G19)),G46-(G19),"不適用"),"") | H84: =IF(ISNUMBER(H46),IF(AND(ISNUMBER(H19)),H46-(H19),"不適用"),"")
A85: 差距｜季末已連網 MW-IT｜實際 vs 共識 | B85: MW | C85: =IF(ISNUMBER(C46),"不適用","") | D85: =IF(ISNUMBER(D46),"不適用","") | E85: =IF(ISNUMBER(E46),"不適用","") | F85: =IF(ISNUMBER(F46),"不適用","") | G85: =IF(ISNUMBER(G46),"不適用","") | H85: =IF(ISNUMBER(H46),"不適用","")
A86: 差距｜季末已連網 MW-IT｜實際 vs 指引中點 | B86: MW | C86: =IF(ISNUMBER(C46),"不適用","") | D86: =IF(ISNUMBER(D46),"不適用","") | E86: =IF(ISNUMBER(E46),"不適用","") | F86: =IF(ISNUMBER(F46),"不適用","") | G86: =IF(ISNUMBER(G46),"不適用","") | H86: =IF(ISNUMBER(H46),"不適用","")
A87: 合計基準｜營收｜vs 共識 | B87: US$bn | C87: =IF(COUNT(C37,D37,E37,F37)=4,C37+D37+E37+F37,"不適用") -> 不適用 | D87: =IF(COUNT(C37,D37,E37,F37)=4,C37+D37+E37+F37,"不適用") -> 不適用 | E87: =IF(COUNT(C37,D37,E37,F37)=4,C37+D37+E37+F37,"不適用") -> 不適用 | F87: =IF(COUNT(C37,D37,E37,F37)=4,C37+D37+E37+F37,"不適用") -> 不適用 | G87: =IF(COUNT(G37,H37)=2,G37+H37,"不適用") -> 不適用 | H87: =IF(COUNT(G37,H37)=2,G37+H37,"不適用") -> 不適用 | J87: 所屬期間的季度共識合計
A88: 拆解｜營收｜vs 共識｜水準 | B88: US$bn | C88: =IF(AND(ISNUMBER(C87),C87<>0,ISNUMBER(C37),ISNUMBER(C22)),(損益!C9-C87)*(C37)/C87,"不適用") -> 不適用 | D88: =IF(AND(ISNUMBER(D87),D87<>0,ISNUMBER(D37),ISNUMBER(D22)),(損益!C9-D87)*(D37)/D87,"不適用") -> 不適用 | E88: =IF(AND(ISNUMBER(E87),E87<>0,ISNUMBER(E37),ISNUMBER(E22)),(損益!C9-E87)*(E37)/E87,"不適用") -> 不適用 | F88: =IF(AND(ISNUMBER(F87),F87<>0,ISNUMBER(F37),ISNUMBER(F22)),(損益!C9-F87)*(F37)/F87,"不適用") -> 不適用 | G88: =IF(AND(ISNUMBER(G87),G87<>0,ISNUMBER(G37),ISNUMBER(G22)),(損益!D9-G87)*(G37)/G87,"不適用") -> 不適用 | H88: =IF(AND(ISNUMBER(H87),H87<>0,ISNUMBER(H37),ISNUMBER(H22)),(損益!D9-H87)*(H37)/H87,"不適用") -> 不適用 | J88: (模型期間 − 比較期間) × 比較的季占比
A89: 拆解｜營收｜vs 共識｜分配 | B89: US$bn | C89: =IF(AND(ISNUMBER(C87),C87<>0,ISNUMBER(C37),ISNUMBER(C22)),(C22/損益!C9-(C37)/C87)*損益!C9,"不適用") -> 不適用 | D89: =IF(AND(ISNUMBER(D87),D87<>0,ISNUMBER(D37),ISNUMBER(D22)),(D22/損益!C9-(D37)/D87)*損益!C9,"不適用") -> 不適用 | E89: =IF(AND(ISNUMBER(E87),E87<>0,ISNUMBER(E37),ISNUMBER(E22)),(E22/損益!C9-(E37)/E87)*損益!C9,"不適用") -> 不適用 | F89: =IF(AND(ISNUMBER(F87),F87<>0,ISNUMBER(F37),ISNUMBER(F22)),(F22/損益!C9-(F37)/F87)*損益!C9,"不適用") -> 不適用 | G89: =IF(AND(ISNUMBER(G87),G87<>0,ISNUMBER(G37),ISNUMBER(G22)),(G22/損益!D9-(G37)/G87)*損益!D9,"不適用") -> 不適用 | H89: =IF(AND(ISNUMBER(H87),H87<>0,ISNUMBER(H37),ISNUMBER(H22)),(H22/損益!D9-(H37)/H87)*損益!D9,"不適用") -> 不適用 | J89: (模型季占比 − 比較季占比) × 模型期間；水準＋分配＝季度差距
A90: 原因｜營收｜vs 共識 | C90: =IF(ISNUMBER(C47),IF(ABS(C47)>輸入與假設!$C$509,IF(ISNUMBER(C88),IF(ABS(C89)>ABS(C88),"營收 vs 共識 "&IF(C47<0,"−","+")&TEXT(ABS(C47)*100,"#,##0.0")&"%"&"：拆法（分配 "&IF(C89<0,"−","+")&IF(ABS(C89)<0,"−","")&"$"&TEXT(ABS(ABS(C89)),"#,##0.000")&"bn"&"（Q1 FY27 占 FY27 "&TEXT((C22/損益!C9)*100,"#,##0.0")&"%"&"，共識合計 "&TEXT(((C37)/C87)*100,"#,##0.0")&"%"&"）；水準 "&IF(C88<0,"−","+")&IF(ABS(C88)<0,"−","")&"$"&TEXT(ABS(ABS(C88)),"#,##0.000")&"bn"&"）","營收 vs 共識 "&IF(C47<0,"−","+")&TEXT(ABS(C47)*100,"#,##0.0")&"%"&"：觀點（水準 "&IF(C88<0,"−","+")&IF(ABS(C88)<0,"−","")&"$"&TEXT(ABS(ABS(C88)),"#,##0.000")&"bn"&"（FY27 模型 "&IF(損益!C9<0,"−","")&"$"&TEXT(ABS(損益!C9),"#,##0.000")&"bn"&"，共識合計 "&IF(C87<0,"−","")&"$"&TEXT(ABS(C87),"#,##0.000")&"bn"&"）；分配 "&IF(C89<0,"−","+")&IF(ABS(C89)<0,"−","")&"$"&TEXT(ABS(ABS(C89)),"#,##0.000")&"bn"&"；"&"營收＝對外 AI 雲端（在役 MW × 每 MW 年收入，Tokenomics × k）＋各分部依近四季年增率收斂；年度總額線性分到各季，未建模季節性"&"）"),"營收 vs 共識 "&IF(C47<0,"−","+")&TEXT(ABS(C47)*100,"#,##0.0")&"%"&"：觀點（"&"營收＝對外 AI 雲端（在役 MW × 每 MW 年收入，Tokenomics × k）＋各分部依近四季年增率收斂；年度總額線性分到各季，未建模季節性"&"）"),""),"") | D90: =IF(ISNUMBER(D47),IF(ABS(D47)>輸入與假設!$C$509,IF(ISNUMBER(D88),IF(ABS(D89)>ABS(D88),"營收 vs 共識 "&IF(D47<0,"−","+")&TEXT(ABS(D47)*100,"#,##0.0")&"%"&"：拆法（分配 "&IF(D89<0,"−","+")&IF(ABS(D89)<0,"−","")&"$"&TEXT(ABS(ABS(D89)),"#,##0.000")&"bn"&"（Q2 FY27 占 FY27 "&TEXT((D22/損益!C9)*100,"#,##0.0")&"%"&"，共識合計 "&TEXT(((D37)/D87)*100,"#,##0.0")&"%"&"）；水準 "&IF(D88<0,"−","+")&IF(ABS(D88)<0,"−","")&"$"&TEXT(ABS(ABS(D88)),"#,##0.000")&"bn"&"）","營收 vs 共識 "&IF(D47<0,"−","+")&TEXT(ABS(D47)*100,"#,##0.0")&"%"&"：觀點（水準 "&IF(D88<0,"−","+")&IF(ABS(D88)<0,"−","")&"$"&TEXT(ABS(ABS(D88)),"#,##0.000")&"bn"&"（FY27 模型 "&IF(損益!C9<0,"−","")&"$"&TEXT(ABS(損益!C9),"#,##0.000")&"bn"&"，共識合計 "&IF(D87<0,"−","")&"$"&TEXT(ABS(D87),"#,##0.000")&"bn"&"）；分配 "&IF(D89<0,"−","+")&IF(ABS(D89)<0,"−","")&"$"&TEXT(ABS(ABS(D89)),"#,##0.000")&"bn"&"；"&"營收＝對外 AI 雲端（在役 MW × 每 MW 年收入，Tokenomics × k）＋各分部依近四季年增率收斂；年度總額線性分到各季，未建模季節性"&"）"),"營收 vs 共識 "&IF(D47<0,"−","+")&TEXT(ABS(D47)*100,"#,##0.0")&"%"&"：觀點（"&"營收＝對外 AI 雲端（在役 MW × 每 MW 年收入，Tokenomics × k）＋各分部依近四季年增率收斂；年度總額線性分到各季，未建模季節性"&"）"),""),"") | E90: =IF(ISNUMBER(E47),IF(ABS(E47)>輸入與假設!$C$509,IF(ISNUMBER(E88),IF(ABS(E89)>ABS(E88),"營收 vs 共識 "&IF(E47<0,"−","+")&TEXT(ABS(E47)*100,"#,##0.0")&"%"&"：拆法（分配 "&IF(E89<0,"−","+")&IF(ABS(E89)<0,"−","")&"$"&TEXT(ABS(ABS(E89)),"#,##0.000")&"bn"&"（Q3 FY27 占 FY27 "&TEXT((E22/損益!C9)*100,"#,##0.0")&"%"&"，共識合計 "&TEXT(((E37)/E87)*100,"#,##0.0")&"%"&"）；水準 "&IF(E88<0,"−","+")&IF(ABS(E88)<0,"−","")&"$"&TEXT(ABS(ABS(E88)),"#,##0.000")&"bn"&"）","營收 vs 共識 "&IF(E47<0,"−","+")&TEXT(ABS(E47)*100,"#,##0.0")&"%"&"：觀點（水準 "&IF(E88<0,"−","+")&IF(ABS(E88)<0,"−","")&"$"&TEXT(ABS(ABS(E88)),"#,##0.000")&"bn"&"（FY27 模型 "&IF(損益!C9<0,"−","")&"$"&TEXT(ABS(損益!C9),"#,##0.000")&"bn"&"，共識合計 "&IF(E87<0,"−","")&"$"&TEXT(ABS(E87),"#,##0.000")&"bn"&"）；分配 "&IF(E89<0,"−","+")&IF(ABS(E89)<0,"−","")&"$"&TEXT(ABS(ABS(E89)),"#,##0.000")&"bn"&"；"&"營收＝對外 AI 雲端（在役 MW × 每 MW 年收入，Tokenomics × k）＋各分部依近四季年增率收斂；年度總額線性分到各季，未建模季節性"&"）"),"營收 vs 共識 "&IF(E47<0,"−","+")&TEXT(ABS(E47)*100,"#,##0.0")&"%"&"：觀點（"&"營收＝對外 AI 雲端（在役 MW × 每 MW 年收入，Tokenomics × k）＋各分部依近四季年增率收斂；年度總額線性分到各季，未建模季節性"&"）"),""),"") | F90: =IF(ISNUMBER(F47),IF(ABS(F47)>輸入與假設!$C$509,IF(ISNUMBER(F88),IF(ABS(F89)>ABS(F88),"營收 vs 共識 "&IF(F47<0,"−","+")&TEXT(ABS(F47)*100,"#,##0.0")&"%"&"：拆法（分配 "&IF(F89<0,"−","+")&IF(ABS(F89)<0,"−","")&"$"&TEXT(ABS(ABS(F89)),"#,##0.000")&"bn"&"（Q4 FY27 占 FY27 "&TEXT((F22/損益!C9)*100,"#,##0.0")&"%"&"，共識合計 "&TEXT(((F37)/F87)*100,"#,##0.0")&"%"&"）；水準 "&IF(F88<0,"−","+")&IF(ABS(F88)<0,"−","")&"$"&TEXT(ABS(ABS(F88)),"#,##0.000")&"bn"&"）","營收 vs 共識 "&IF(F47<0,"−","+")&TEXT(ABS(F47)*100,"#,##0.0")&"%"&"：觀點（水準 "&IF(F88<0,"−","+")&IF(ABS(F88)<0,"−","")&"$"&TEXT(ABS(ABS(F88)),"#,##0.000")&"bn"&"（FY27 模型 "&IF(損益!C9<0,"−","")&"$"&TEXT(ABS(損益!C9),"#,##0.000")&"bn"&"，共識合計 "&IF(F87<0,"−","")&"$"&TEXT(ABS(F87),"#,##0.000")&"bn"&"）；分配 "&IF(F89<0,"−","+")&IF(ABS(F89)<0,"−","")&"$"&TEXT(ABS(ABS(F89)),"#,##0.000")&"bn"&"；"&"營收＝對外 AI 雲端（在役 MW × 每 MW 年收入，Tokenomics × k）＋各分部依近四季年增率收斂；年度總額線性分到各季，未建模季節性"&"）"),"營收 vs 共識 "&IF(F47<0,"−","+")&TEXT(ABS(F47)*100,"#,##0.0")&"%"&"：觀點（"&"營收＝對外 AI 雲端（在役 MW × 每 MW 年收入，Tokenomics × k）＋各分部依近四季年增率收斂；年度總額線性分到各季，未建模季節性"&"）"),""),"") | G90: =IF(ISNUMBER(G47),IF(ABS(G47)>輸入與假設!$C$509,IF(ISNUMBER(G88),IF(ABS(G89)>ABS(G88),"營收 vs 共識 "&IF(G47<0,"−","+")&TEXT(ABS(G47)*100,"#,##0.0")&"%"&"：拆法（分配 "&IF(G89<0,"−","+")&IF(ABS(G89)<0,"−","")&"$"&TEXT(ABS(ABS(G89)),"#,##0.000")&"bn"&"（Q1 FY28 占 FY28 "&TEXT((G22/損益!D9)*100,"#,##0.0")&"%"&"，共識合計 "&TEXT(((G37)/G87)*100,"#,##0.0")&"%"&"）；水準 "&IF(G88<0,"−","+")&IF(ABS(G88)<0,"−","")&"$"&TEXT(ABS(ABS(G88)),"#,##0.000")&"bn"&"）","營收 vs 共識 "&IF(G47<0,"−","+")&TEXT(ABS(G47)*100,"#,##0.0")&"%"&"：觀點（水準 "&IF(G88<0,"−","+")&IF(ABS(G88)<0,"−","")&"$"&TEXT(ABS(ABS(G88)),"#,##0.000")&"bn"&"（FY28 模型 "&IF(損益!D9<0,"−","")&"$"&TEXT(ABS(損益!D9),"#,##0.000")&"bn"&"，共識合計 "&IF(G87<0,"−","")&"$"&TEXT(ABS(G87),"#,##0.000")&"bn"&"）；分配 "&IF(G89<0,"−","+")&IF(ABS(G89)<0,"−","")&"$"&TEXT(ABS(ABS(G89)),"#,##0.000")&"bn"&"；"&"營收＝對外 AI 雲端（在役 MW × 每 MW 年收入，Tokenomics × k）＋各分部依近四季年增率收斂；年度總額線性分到各季，未建模季節性"&"）"),"營收 vs 共識 "&IF(G47<0,"−","+")&TEXT(ABS(G47)*100,"#,##0.0")&"%"&"：觀點（"&"營收＝對外 AI 雲端（在役 MW × 每 MW 年收入，Tokenomics × k）＋各分部依近四季年增率收斂；年度總額線性分到各季，未建模季節性"&"）"),""),"") | H90: =IF(ISNUMBER(H47),IF(ABS(H47)>輸入與假設!$C$509,IF(ISNUMBER(H88),IF(ABS(H89)>ABS(H88),"營收 vs 共識 "&IF(H47<0,"−","+")&TEXT(ABS(H47)*100,"#,##0.0")&"%"&"：拆法（分配 "&IF(H89<0,"−","+")&IF(ABS(H89)<0,"−","")&"$"&TEXT(ABS(ABS(H89)),"#,##0.000")&"bn"&"（Q2 FY28 占 FY28 "&TEXT((H22/損益!D9)*100,"#,##0.0")&"%"&"，共識合計 "&TEXT(((H37)/H87)*100,"#,##0.0")&"%"&"）；水準 "&IF(H88<0,"−","+")&IF(ABS(H88)<0,"−","")&"$"&TEXT(ABS(ABS(H88)),"#,##0.000")&"bn"&"）","營收 vs 共識 "&IF(H47<0,"−","+")&TEXT(ABS(H47)*100,"#,##0.0")&"%"&"：觀點（水準 "&IF(H88<0,"−","+")&IF(ABS(H88)<0,"−","")&"$"&TEXT(ABS(ABS(H88)),"#,##0.000")&"bn"&"（FY28 模型 "&IF(損益!D9<0,"−","")&"$"&TEXT(ABS(損益!D9),"#,##0.000")&"bn"&"，共識合計 "&IF(H87<0,"−","")&"$"&TEXT(ABS(H87),"#,##0.000")&"bn"&"）；分配 "&IF(H89<0,"−","+")&IF(ABS(H89)<0,"−","")&"$"&TEXT(ABS(ABS(H89)),"#,##0.000")&"bn"&"；"&"營收＝對外 AI 雲端（在役 MW × 每 MW 年收入，Tokenomics × k）＋各分部依近四季年增率收斂；年度總額線性分到各季，未建模季節性"&"）"),"營收 vs 共識 "&IF(H47<0,"−","+")&TEXT(ABS(H47)*100,"#,##0.0")&"%"&"：觀點（"&"營收＝對外 AI 雲端（在役 MW × 每 MW 年收入，Tokenomics × k）＋各分部依近四季年增率收斂；年度總額線性分到各季，未建模季節性"&"）"),""),"")
A91: 原因類型｜營收｜vs 共識 | C91: =IF(ISNUMBER(C47),IF(ABS(C47)>輸入與假設!$C$509,IF(ISNUMBER(C88),IF(ABS(C89)>ABS(C88),"拆法","觀點"),"觀點"),""),"") | D91: =IF(ISNUMBER(D47),IF(ABS(D47)>輸入與假設!$C$509,IF(ISNUMBER(D88),IF(ABS(D89)>ABS(D88),"拆法","觀點"),"觀點"),""),"") | E91: =IF(ISNUMBER(E47),IF(ABS(E47)>輸入與假設!$C$509,IF(ISNUMBER(E88),IF(ABS(E89)>ABS(E88),"拆法","觀點"),"觀點"),""),"") | F91: =IF(ISNUMBER(F47),IF(ABS(F47)>輸入與假設!$C$509,IF(ISNUMBER(F88),IF(ABS(F89)>ABS(F88),"拆法","觀點"),"觀點"),""),"") | G91: =IF(ISNUMBER(G47),IF(ABS(G47)>輸入與假設!$C$509,IF(ISNUMBER(G88),IF(ABS(G89)>ABS(G88),"拆法","觀點"),"觀點"),""),"") | H91: =IF(ISNUMBER(H47),IF(ABS(H47)>輸入與假設!$C$509,IF(ISNUMBER(H88),IF(ABS(H89)>ABS(H88),"拆法","觀點"),"觀點"),""),"")
A92: 原因｜營收｜vs 指引中點 | C92: =IF(ISNUMBER(C48),IF(OR(ABS(C48)>輸入與假設!$C$509,C22>C33,C22<C32),"營收 vs 指引中點 "&IF(C48<0,"−","+")&TEXT(ABS(C48)*100,"#,##0.0")&"%"&"：觀點（"&"營收＝對外 AI 雲端（在役 MW × 每 MW 年收入，Tokenomics × k）＋各分部依近四季年增率收斂；年度總額線性分到各季，未建模季節性"&"）",""),"") -> 營收 vs 指引中點 +3.7%：觀點（營收＝對外 AI 雲端（在役 MW × 每 MW 年收入，Tokenomics × k）＋各分部依近四季年增率收斂；年度總額線性分到各季，未建模季節性） | D92: =IF(ISNUMBER(D48),IF(OR(ABS(D48)>輸入與假設!$C$509,D22>D33,D22<D32),"營收 vs 指引中點 "&IF(D48<0,"−","+")&TEXT(ABS(D48)*100,"#,##0.0")&"%"&"：觀點（"&"營收＝對外 AI 雲端（在役 MW × 每 MW 年收入，Tokenomics × k）＋各分部依近四季年增率收斂；年度總額線性分到各季，未建模季節性"&"）",""),"") | E92: =IF(ISNUMBER(E48),IF(OR(ABS(E48)>輸入與假設!$C$509,E22>E33,E22<E32),"營收 vs 指引中點 "&IF(E48<0,"−","+")&TEXT(ABS(E48)*100,"#,##0.0")&"%"&"：觀點（"&"營收＝對外 AI 雲端（在役 MW × 每 MW 年收入，Tokenomics × k）＋各分部依近四季年增率收斂；年度總額線性分到各季，未建模季節性"&"）",""),"") | F92: =IF(ISNUMBER(F48),IF(OR(ABS(F48)>輸入與假設!$C$509,F22>F33,F22<F32),"營收 vs 指引中點 "&IF(F48<0,"−","+")&TEXT(ABS(F48)*100,"#,##0.0")&"%"&"：觀點（"&"營收＝對外 AI 雲端（在役 MW × 每 MW 年收入，Tokenomics × k）＋各分部依近四季年增率收斂；年度總額線性分到各季，未建模季節性"&"）",""),"") | G92: =IF(ISNUMBER(G48),IF(OR(ABS(G48)>輸入與假設!$C$509,G22>G33,G22<G32),"營收 vs 指引中點 "&IF(G48<0,"−","+")&TEXT(ABS(G48)*100,"#,##0.0")&"%"&"：觀點（"&"營收＝對外 AI 雲端（在役 MW × 每 MW 年收入，Tokenomics × k）＋各分部依近四季年增率收斂；年度總額線性分到各季，未建模季節性"&"）",""),"") | H92: =IF(ISNUMBER(H48),IF(OR(ABS(H48)>輸入與假設!$C$509,H22>H33,H22<H32),"營收 vs 指引中點 "&IF(H48<0,"−","+")&TEXT(ABS(H48)*100,"#,##0.0")&"%"&"：觀點（"&"營收＝對外 AI 雲端（在役 MW × 每 MW 年收入，Tokenomics × k）＋各分部依近四季年增率收斂；年度總額線性分到各季，未建模季節性"&"）",""),"")
A93: 原因類型｜營收｜vs 指引中點 | C93: =IF(ISNUMBER(C48),IF(OR(ABS(C48)>輸入與假設!$C$509,C22>C33,C22<C32),"觀點",""),"") -> 觀點 | D93: =IF(ISNUMBER(D48),IF(OR(ABS(D48)>輸入與假設!$C$509,D22>D33,D22<D32),"觀點",""),"") | E93: =IF(ISNUMBER(E48),IF(OR(ABS(E48)>輸入與假設!$C$509,E22>E33,E22<E32),"觀點",""),"") | F93: =IF(ISNUMBER(F48),IF(OR(ABS(F48)>輸入與假設!$C$509,F22>F33,F22<F32),"觀點",""),"") | G93: =IF(ISNUMBER(G48),IF(OR(ABS(G48)>輸入與假設!$C$509,G22>G33,G22<G32),"觀點",""),"") | H93: =IF(ISNUMBER(H48),IF(OR(ABS(H48)>輸入與假設!$C$509,H22>H33,H22<H32),"觀點",""),"")
A94: 原因｜營收｜實際 vs 模型 | C94: =IF(ISNUMBER(C49),IF(ABS(C49)>輸入與假設!$C$509,"營收 實際 vs 模型 "&IF(C49<0,"−","+")&TEXT(ABS(C49)*100,"#,##0.0")&"%"&"：觀點（"&"營收＝對外 AI 雲端（在役 MW × 每 MW 年收入，Tokenomics × k）＋各分部依近四季年增率收斂；年度總額線性分到各季，未建模季節性"&"）",""),"") | D94: =IF(ISNUMBER(D49),IF(ABS(D49)>輸入與假設!$C$509,"營收 實際 vs 模型 "&IF(D49<0,"−","+")&TEXT(ABS(D49)*100,"#,##0.0")&"%"&"：觀點（"&"營收＝對外 AI 雲端（在役 MW × 每 MW 年收入，Tokenomics × k）＋各分部依近四季年增率收斂；年度總額線性分到各季，未建模季節性"&"）",""),"") | E94: =IF(ISNUMBER(E49),IF(ABS(E49)>輸入與假設!$C$509,"營收 實際 vs 模型 "&IF(E49<0,"−","+")&TEXT(ABS(E49)*100,"#,##0.0")&"%"&"：觀點（"&"營收＝對外 AI 雲端（在役 MW × 每 MW 年收入，Tokenomics × k）＋各分部依近四季年增率收斂；年度總額線性分到各季，未建模季節性"&"）",""),"") | F94: =IF(ISNUMBER(F49),IF(ABS(F49)>輸入與假設!$C$509,"營收 實際 vs 模型 "&IF(F49<0,"−","+")&TEXT(ABS(F49)*100,"#,##0.0")&"%"&"：觀點（"&"營收＝對外 AI 雲端（在役 MW × 每 MW 年收入，Tokenomics × k）＋各分部依近四季年增率收斂；年度總額線性分到各季，未建模季節性"&"）",""),"") | G94: =IF(ISNUMBER(G49),IF(ABS(G49)>輸入與假設!$C$509,"營收 實際 vs 模型 "&IF(G49<0,"−","+")&TEXT(ABS(G49)*100,"#,##0.0")&"%"&"：觀點（"&"營收＝對外 AI 雲端（在役 MW × 每 MW 年收入，Tokenomics × k）＋各分部依近四季年增率收斂；年度總額線性分到各季，未建模季節性"&"）",""),"") | H94: =IF(ISNUMBER(H49),IF(ABS(H49)>輸入與假設!$C$509,"營收 實際 vs 模型 "&IF(H49<0,"−","+")&TEXT(ABS(H49)*100,"#,##0.0")&"%"&"：觀點（"&"營收＝對外 AI 雲端（在役 MW × 每 MW 年收入，Tokenomics × k）＋各分部依近四季年增率收斂；年度總額線性分到各季，未建模季節性"&"）",""),"")
A95: 原因類型｜營收｜實際 vs 模型 | C95: =IF(ISNUMBER(C49),IF(ABS(C49)>輸入與假設!$C$509,"觀點",""),"") | D95: =IF(ISNUMBER(D49),IF(ABS(D49)>輸入與假設!$C$509,"觀點",""),"") | E95: =IF(ISNUMBER(E49),IF(ABS(E49)>輸入與假設!$C$509,"觀點",""),"") | F95: =IF(ISNUMBER(F49),IF(ABS(F49)>輸入與假設!$C$509,"觀點",""),"") | G95: =IF(ISNUMBER(G49),IF(ABS(G49)>輸入與假設!$C$509,"觀點",""),"") | H95: =IF(ISNUMBER(H49),IF(ABS(H49)>輸入與假設!$C$509,"觀點",""),"")
A96: 合計基準｜調整後 EBITDA｜vs 共識 | B96: US$bn | C96: =IF(COUNT(C38,D38,E38,F38)=4,C38+D38+E38+F38,"不適用") -> 不適用 | D96: =IF(COUNT(C38,D38,E38,F38)=4,C38+D38+E38+F38,"不適用") -> 不適用 | E96: =IF(COUNT(C38,D38,E38,F38)=4,C38+D38+E38+F38,"不適用") -> 不適用 | F96: =IF(COUNT(C38,D38,E38,F38)=4,C38+D38+E38+F38,"不適用") -> 不適用 | G96: =IF(COUNT(G38,H38)=2,G38+H38,"不適用") -> 不適用 | H96: =IF(COUNT(G38,H38)=2,G38+H38,"不適用") -> 不適用 | J96: 所屬期間的季度共識合計
A97: 拆解｜調整後 EBITDA｜vs 共識｜水準 | B97: US$bn | C97: =IF(AND(ISNUMBER(C96),C96<>0,ISNUMBER(C38),ISNUMBER(C28)),(損益!C22-C96)*(C38)/C96,"不適用") -> 不適用 | D97: =IF(AND(ISNUMBER(D96),D96<>0,ISNUMBER(D38),ISNUMBER(D28)),(損益!C22-D96)*(D38)/D96,"不適用") -> 不適用 | E97: =IF(AND(ISNUMBER(E96),E96<>0,ISNUMBER(E38),ISNUMBER(E28)),(損益!C22-E96)*(E38)/E96,"不適用") -> 不適用 | F97: =IF(AND(ISNUMBER(F96),F96<>0,ISNUMBER(F38),ISNUMBER(F28)),(損益!C22-F96)*(F38)/F96,"不適用") -> 不適用 | G97: =IF(AND(ISNUMBER(G96),G96<>0,ISNUMBER(G38),ISNUMBER(G28)),(損益!D22-G96)*(G38)/G96,"不適用") -> 不適用 | H97: =IF(AND(ISNUMBER(H96),H96<>0,ISNUMBER(H38),ISNUMBER(H28)),(損益!D22-H96)*(H38)/H96,"不適用") -> 不適用 | J97: (模型期間 − 比較期間) × 比較的季占比
A98: 拆解｜調整後 EBITDA｜vs 共識｜分配 | B98: US$bn | C98: =IF(AND(ISNUMBER(C96),C96<>0,ISNUMBER(C38),ISNUMBER(C28)),(C28/損益!C22-(C38)/C96)*損益!C22,"不適用") -> 不適用 | D98: =IF(AND(ISNUMBER(D96),D96<>0,ISNUMBER(D38),ISNUMBER(D28)),(D28/損益!C22-(D38)/D96)*損益!C22,"不適用") -> 不適用 | E98: =IF(AND(ISNUMBER(E96),E96<>0,ISNUMBER(E38),ISNUMBER(E28)),(E28/損益!C22-(E38)/E96)*損益!C22,"不適用") -> 不適用 | F98: =IF(AND(ISNUMBER(F96),F96<>0,ISNUMBER(F38),ISNUMBER(F28)),(F28/損益!C22-(F38)/F96)*損益!C22,"不適用") -> 不適用 | G98: =IF(AND(ISNUMBER(G96),G96<>0,ISNUMBER(G38),ISNUMBER(G28)),(G28/損益!D22-(G38)/G96)*損益!D22,"不適用") -> 不適用 | H98: =IF(AND(ISNUMBER(H96),H96<>0,ISNUMBER(H38),ISNUMBER(H28)),(H28/損益!D22-(H38)/H96)*損益!D22,"不適用") -> 不適用 | J98: (模型季占比 − 比較季占比) × 模型期間；水準＋分配＝季度差距
A99: 原因｜調整後 EBITDA｜vs 共識 | C99: =IF(ISNUMBER(C52),IF(IF(ISNUMBER(C57),ABS(C57)>輸入與假設!$C$510,OR(AND(C38<>0,ABS(C52)>輸入與假設!$C$509*ABS(C38)),AND(C38=0,C52<>0))),IF(ISNUMBER(C97),IF(ABS(C98)>ABS(C97),"調整後 EBITDA vs 共識 "&IF(C52<0,"−","+")&IF(ABS(C52)<0,"−","")&"$"&TEXT(ABS(ABS(C52)),"#,##0.00")&"bn"&IF(ISNUMBER(C57),"／"&IF(C57<0,"−","+")&TEXT(ABS(C57)*100,"#,##0.0")&"pt","")&"：拆法（分配 "&IF(C98<0,"−","+")&IF(ABS(C98)<0,"−","")&"$"&TEXT(ABS(ABS(C98)),"#,##0.000")&"bn"&"（Q1 FY27 占 FY27 "&TEXT((C28/損益!C22)*100,"#,##0.0")&"%"&"，共識合計 "&TEXT(((C38)/C96)*100,"#,##0.0")&"%"&"）；水準 "&IF(C97<0,"−","+")&IF(ABS(C97)<0,"−","")&"$"&TEXT(ABS(ABS(C97)),"#,##0.000")&"bn"&"）","調整後 EBITDA vs 共識 "&IF(C52<0,"−","+")&IF(ABS(C52)<0,"−","")&"$"&TEXT(ABS(ABS(C52)),"#,##0.00")&"bn"&IF(ISNUMBER(C57),"／"&IF(C57<0,"−","+")&TEXT(ABS(C57)*100,"#,##0.0")&"pt","")&"：觀點（水準 "&IF(C97<0,"−","+")&IF(ABS(C97)<0,"−","")&"$"&TEXT(ABS(ABS(C97)),"#,##0.000")&"bn"&"（FY27 模型 "&IF(損益!C22<0,"−","")&"$"&TEXT(ABS(損益!C22),"#,##0.000")&"bn"&"，共識合計 "&IF(C96<0,"−","")&"$"&TEXT(ABS(C96),"#,##0.000")&"bn"&"）；分配 "&IF(C98<0,"−","+")&IF(ABS(C98)<0,"−","")&"$"&TEXT(ABS(ABS(C98)),"#,##0.000")&"bn"&"；"&"模型 EBITDA 率 "&IF((C27)<0,"−","")&TEXT(ABS((C27))*100,"#,##0.0")&"%"&"；EBITDA＝分部營業利益＋分攤 D&A 與 AI 雲端 Tokenomics 由下而上營運成本"&"）"),"調整後 EBITDA vs 共識 "&IF(C52<0,"−","+")&IF(ABS(C52)<0,"−","")&"$"&TEXT(ABS(ABS(C52)),"#,##0.00")&"bn"&IF(ISNUMBER(C57),"／"&IF(C57<0,"−","+")&TEXT(ABS(C57)*100,"#,##0.0")&"pt","")&"：觀點（"&"模型 EBITDA 率 "&IF((C27)<0,"−","")&TEXT(ABS((C27))*100,"#,##0.0")&"%"&"；EBITDA＝分部營業利益＋分攤 D&A 與 AI 雲端 Tokenomics 由下而上營運成本"&"）"),""),"") -> 調整後 EBITDA vs 共識 −$2.26bn／−4.4pt：觀點（模型 EBITDA 率 57.9%；EBITDA＝分部營業利益＋分攤 D&A 與 AI 雲端 Tokenomics 由下而上營運成本） | D99: =IF(ISNUMBER(D52),IF(IF(ISNUMBER(D57),ABS(D57)>輸入與假設!$C$510,OR(AND(D38<>0,ABS(D52)>輸入與假設!$C$509*ABS(D38)),AND(D38=0,D52<>0))),IF(ISNUMBER(D97),IF(ABS(D98)>ABS(D97),"調整後 EBITDA vs 共識 "&IF(D52<0,"−","+")&IF(ABS(D52)<0,"−","")&"$"&TEXT(ABS(ABS(D52)),"#,##0.00")&"bn"&IF(ISNUMBER(D57),"／"&IF(D57<0,"−","+")&TEXT(ABS(D57)*100,"#,##0.0")&"pt","")&"：拆法（分配 "&IF(D98<0,"−","+")&IF(ABS(D98)<0,"−","")&"$"&TEXT(ABS(ABS(D98)),"#,##0.000")&"bn"&"（Q2 FY27 占 FY27 "&TEXT((D28/損益!C22)*100,"#,##0.0")&"%"&"，共識合計 "&TEXT(((D38)/D96)*100,"#,##0.0")&"%"&"）；水準 "&IF(D97<0,"−","+")&IF(ABS(D97)<0,"−","")&"$"&TEXT(ABS(ABS(D97)),"#,##0.000")&"bn"&"）","調整後 EBITDA vs 共識 "&IF(D52<0,"−","+")&IF(ABS(D52)<0,"−","")&"$"&TEXT(ABS(ABS(D52)),"#,##0.00")&"bn"&IF(ISNUMBER(D57),"／"&IF(D57<0,"−","+")&TEXT(ABS(D57)*100,"#,##0.0")&"pt","")&"：觀點（水準 "&IF(D97<0,"−","+")&IF(ABS(D97)<0,"−","")&"$"&TEXT(ABS(ABS(D97)),"#,##0.000")&"bn"&"（FY27 模型 "&IF(損益!C22<0,"−","")&"$"&TEXT(ABS(損益!C22),"#,##0.000")&"bn"&"，共識合計 "&IF(D96<0,"−","")&"$"&TEXT(ABS(D96),"#,##0.000")&"bn"&"）；分配 "&IF(D98<0,"−","+")&IF(ABS(D98)<0,"−","")&"$"&TEXT(ABS(ABS(D98)),"#,##0.000")&"bn"&"；"&"模型 EBITDA 率 "&IF((D27)<0,"−","")&TEXT(ABS((D27))*100,"#,##0.0")&"%"&"；EBITDA＝分部營業利益＋分攤 D&A 與 AI 雲端 Tokenomics 由下而上營運成本"&"）"),"調整後 EBITDA vs 共識 "&IF(D52<0,"−","+")&IF(ABS(D52)<0,"−","")&"$"&TEXT(ABS(ABS(D52)),"#,##0.00")&"bn"&IF(ISNUMBER(D57),"／"&IF(D57<0,"−","+")&TEXT(ABS(D57)*100,"#,##0.0")&"pt","")&"：觀點（"&"模型 EBITDA 率 "&IF((D27)<0,"−","")&TEXT(ABS((D27))*100,"#,##0.0")&"%"&"；EBITDA＝分部營業利益＋分攤 D&A 與 AI 雲端 Tokenomics 由下而上營運成本"&"）"),""),"") | E99: =IF(ISNUMBER(E52),IF(IF(ISNUMBER(E57),ABS(E57)>輸入與假設!$C$510,OR(AND(E38<>0,ABS(E52)>輸入與假設!$C$509*ABS(E38)),AND(E38=0,E52<>0))),IF(ISNUMBER(E97),IF(ABS(E98)>ABS(E97),"調整後 EBITDA vs 共識 "&IF(E52<0,"−","+")&IF(ABS(E52)<0,"−","")&"$"&TEXT(ABS(ABS(E52)),"#,##0.00")&"bn"&IF(ISNUMBER(E57),"／"&IF(E57<0,"−","+")&TEXT(ABS(E57)*100,"#,##0.0")&"pt","")&"：拆法（分配 "&IF(E98<0,"−","+")&IF(ABS(E98)<0,"−","")&"$"&TEXT(ABS(ABS(E98)),"#,##0.000")&"bn"&"（Q3 FY27 占 FY27 "&TEXT((E28/損益!C22)*100,"#,##0.0")&"%"&"，共識合計 "&TEXT(((E38)/E96)*100,"#,##0.0")&"%"&"）；水準 "&IF(E97<0,"−","+")&IF(ABS(E97)<0,"−","")&"$"&TEXT(ABS(ABS(E97)),"#,##0.000")&"bn"&"）","調整後 EBITDA vs 共識 "&IF(E52<0,"−","+")&IF(ABS(E52)<0,"−","")&"$"&TEXT(ABS(ABS(E52)),"#,##0.00")&"bn"&IF(ISNUMBER(E57),"／"&IF(E57<0,"−","+")&TEXT(ABS(E57)*100,"#,##0.0")&"pt","")&"：觀點（水準 "&IF(E97<0,"−","+")&IF(ABS(E97)<0,"−","")&"$"&TEXT(ABS(ABS(E97)),"#,##0.000")&"bn"&"（FY27 模型 "&IF(損益!C22<0,"−","")&"$"&TEXT(ABS(損益!C22),"#,##0.000")&"bn"&"，共識合計 "&IF(E96<0,"−","")&"$"&TEXT(ABS(E96),"#,##0.000")&"bn"&"）；分配 "&IF(E98<0,"−","+")&IF(ABS(E98)<0,"−","")&"$"&TEXT(ABS(ABS(E98)),"#,##0.000")&"bn"&"；"&"模型 EBITDA 率 "&IF((E27)<0,"−","")&TEXT(ABS((E27))*100,"#,##0.0")&"%"&"；EBITDA＝分部營業利益＋分攤 D&A 與 AI 雲端 Tokenomics 由下而上營運成本"&"）"),"調整後 EBITDA vs 共識 "&IF(E52<0,"−","+")&IF(ABS(E52)<0,"−","")&"$"&TEXT(ABS(ABS(E52)),"#,##0.00")&"bn"&IF(ISNUMBER(E57),"／"&IF(E57<0,"−","+")&TEXT(ABS(E57)*100,"#,##0.0")&"pt","")&"：觀點（"&"模型 EBITDA 率 "&IF((E27)<0,"−","")&TEXT(ABS((E27))*100,"#,##0.0")&"%"&"；EBITDA＝分部營業利益＋分攤 D&A 與 AI 雲端 Tokenomics 由下而上營運成本"&"）"),""),"") | F99: =IF(ISNUMBER(F52),IF(IF(ISNUMBER(F57),ABS(F57)>輸入與假設!$C$510,OR(AND(F38<>0,ABS(F52)>輸入與假設!$C$509*ABS(F38)),AND(F38=0,F52<>0))),IF(ISNUMBER(F97),IF(ABS(F98)>ABS(F97),"調整後 EBITDA vs 共識 "&IF(F52<0,"−","+")&IF(ABS(F52)<0,"−","")&"$"&TEXT(ABS(ABS(F52)),"#,##0.00")&"bn"&IF(ISNUMBER(F57),"／"&IF(F57<0,"−","+")&TEXT(ABS(F57)*100,"#,##0.0")&"pt","")&"：拆法（分配 "&IF(F98<0,"−","+")&IF(ABS(F98)<0,"−","")&"$"&TEXT(ABS(ABS(F98)),"#,##0.000")&"bn"&"（Q4 FY27 占 FY27 "&TEXT((F28/損益!C22)*100,"#,##0.0")&"%"&"，共識合計 "&TEXT(((F38)/F96)*100,"#,##0.0")&"%"&"）；水準 "&IF(F97<0,"−","+")&IF(ABS(F97)<0,"−","")&"$"&TEXT(ABS(ABS(F97)),"#,##0.000")&"bn"&"）","調整後 EBITDA vs 共識 "&IF(F52<0,"−","+")&IF(ABS(F52)<0,"−","")&"$"&TEXT(ABS(ABS(F52)),"#,##0.00")&"bn"&IF(ISNUMBER(F57),"／"&IF(F57<0,"−","+")&TEXT(ABS(F57)*100,"#,##0.0")&"pt","")&"：觀點（水準 "&IF(F97<0,"−","+")&IF(ABS(F97)<0,"−","")&"$"&TEXT(ABS(ABS(F97)),"#,##0.000")&"bn"&"（FY27 模型 "&IF(損益!C22<0,"−","")&"$"&TEXT(ABS(損益!C22),"#,##0.000")&"bn"&"，共識合計 "&IF(F96<0,"−","")&"$"&TEXT(ABS(F96),"#,##0.000")&"bn"&"）；分配 "&IF(F98<0,"−","+")&IF(ABS(F98)<0,"−","")&"$"&TEXT(ABS(ABS(F98)),"#,##0.000")&"bn"&"；"&"模型 EBITDA 率 "&IF((F27)<0,"−","")&TEXT(ABS((F27))*100,"#,##0.0")&"%"&"；EBITDA＝分部營業利益＋分攤 D&A 與 AI 雲端 Tokenomics 由下而上營運成本"&"）"),"調整後 EBITDA vs 共識 "&IF(F52<0,"−","+")&IF(ABS(F52)<0,"−","")&"$"&TEXT(ABS(ABS(F52)),"#,##0.00")&"bn"&IF(ISNUMBER(F57),"／"&IF(F57<0,"−","+")&TEXT(ABS(F57)*100,"#,##0.0")&"pt","")&"：觀點（"&"模型 EBITDA 率 "&IF((F27)<0,"−","")&TEXT(ABS((F27))*100,"#,##0.0")&"%"&"；EBITDA＝分部營業利益＋分攤 D&A 與 AI 雲端 Tokenomics 由下而上營運成本"&"）"),""),"") | G99: =IF(ISNUMBER(G52),IF(IF(ISNUMBER(G57),ABS(G57)>輸入與假設!$C$510,OR(AND(G38<>0,ABS(G52)>輸入與假設!$C$509*ABS(G38)),AND(G38=0,G52<>0))),IF(ISNUMBER(G97),IF(ABS(G98)>ABS(G97),"調整後 EBITDA vs 共識 "&IF(G52<0,"−","+")&IF(ABS(G52)<0,"−","")&"$"&TEXT(ABS(ABS(G52)),"#,##0.00")&"bn"&IF(ISNUMBER(G57),"／"&IF(G57<0,"−","+")&TEXT(ABS(G57)*100,"#,##0.0")&"pt","")&"：拆法（分配 "&IF(G98<0,"−","+")&IF(ABS(G98)<0,"−","")&"$"&TEXT(ABS(ABS(G98)),"#,##0.000")&"bn"&"（Q1 FY28 占 FY28 "&TEXT((G28/損益!D22)*100,"#,##0.0")&"%"&"，共識合計 "&TEXT(((G38)/G96)*100,"#,##0.0")&"%"&"）；水準 "&IF(G97<0,"−","+")&IF(ABS(G97)<0,"−","")&"$"&TEXT(ABS(ABS(G97)),"#,##0.000")&"bn"&"）","調整後 EBITDA vs 共識 "&IF(G52<0,"−","+")&IF(ABS(G52)<0,"−","")&"$"&TEXT(ABS(ABS(G52)),"#,##0.00")&"bn"&IF(ISNUMBER(G57),"／"&IF(G57<0,"−","+")&TEXT(ABS(G57)*100,"#,##0.0")&"pt","")&"：觀點（水準 "&IF(G97<0,"−","+")&IF(ABS(G97)<0,"−","")&"$"&TEXT(ABS(ABS(G97)),"#,##0.000")&"bn"&"（FY28 模型 "&IF(損益!D22<0,"−","")&"$"&TEXT(ABS(損益!D22),"#,##0.000")&"bn"&"，共識合計 "&IF(G96<0,"−","")&"$"&TEXT(ABS(G96),"#,##0.000")&"bn"&"）；分配 "&IF(G98<0,"−","+")&IF(ABS(G98)<0,"−","")&"$"&TEXT(ABS(ABS(G98)),"#,##0.000")&"bn"&"；"&"模型 EBITDA 率 "&IF((G27)<0,"−","")&TEXT(ABS((G27))*100,"#,##0.0")&"%"&"；EBITDA＝分部營業利益＋分攤 D&A 與 AI 雲端 Tokenomics 由下而上營運成本"&"）"),"調整後 EBITDA vs 共識 "&IF(G52<0,"−","+")&IF(ABS(G52)<0,"−","")&"$"&TEXT(ABS(ABS(G52)),"#,##0.00")&"bn"&IF(ISNUMBER(G57),"／"&IF(G57<0,"−","+")&TEXT(ABS(G57)*100,"#,##0.0")&"pt","")&"：觀點（"&"模型 EBITDA 率 "&IF((G27)<0,"−","")&TEXT(ABS((G27))*100,"#,##0.0")&"%"&"；EBITDA＝分部營業利益＋分攤 D&A 與 AI 雲端 Tokenomics 由下而上營運成本"&"）"),""),"") | H99: =IF(ISNUMBER(H52),IF(IF(ISNUMBER(H57),ABS(H57)>輸入與假設!$C$510,OR(AND(H38<>0,ABS(H52)>輸入與假設!$C$509*ABS(H38)),AND(H38=0,H52<>0))),IF(ISNUMBER(H97),IF(ABS(H98)>ABS(H97),"調整後 EBITDA vs 共識 "&IF(H52<0,"−","+")&IF(ABS(H52)<0,"−","")&"$"&TEXT(ABS(ABS(H52)),"#,##0.00")&"bn"&IF(ISNUMBER(H57),"／"&IF(H57<0,"−","+")&TEXT(ABS(H57)*100,"#,##0.0")&"pt","")&"：拆法（分配 "&IF(H98<0,"−","+")&IF(ABS(H98)<0,"−","")&"$"&TEXT(ABS(ABS(H98)),"#,##0.000")&"bn"&"（Q2 FY28 占 FY28 "&TEXT((H28/損益!D22)*100,"#,##0.0")&"%"&"，共識合計 "&TEXT(((H38)/H96)*100,"#,##0.0")&"%"&"）；水準 "&IF(H97<0,"−","+")&IF(ABS(H97)<0,"−","")&"$"&TEXT(ABS(ABS(H97)),"#,##0.000")&"bn"&"）","調整後 EBITDA vs 共識 "&IF(H52<0,"−","+")&IF(ABS(H52)<0,"−","")&"$"&TEXT(ABS(ABS(H52)),"#,##0.00")&"bn"&IF(ISNUMBER(H57),"／"&IF(H57<0,"−","+")&TEXT(ABS(H57)*100,"#,##0.0")&"pt","")&"：觀點（水準 "&IF(H97<0,"−","+")&IF(ABS(H97)<0,"−","")&"$"&TEXT(ABS(ABS(H97)),"#,##0.000")&"bn"&"（FY28 模型 "&IF(損益!D22<0,"−","")&"$"&TEXT(ABS(損益!D22),"#,##0.000")&"bn"&"，共識合計 "&IF(H96<0,"−","")&"$"&TEXT(ABS(H96),"#,##0.000")&"bn"&"）；分配 "&IF(H98<0,"−","+")&IF(ABS(H98)<0,"−","")&"$"&TEXT(ABS(ABS(H98)),"#,##0.000")&"bn"&"；"&"模型 EBITDA 率 "&IF((H27)<0,"−","")&TEXT(ABS((H27))*100,"#,##0.0")&"%"&"；EBITDA＝分部營業利益＋分攤 D&A 與 AI 雲端 Tokenomics 由下而上營運成本"&"）"),"調整後 EBITDA vs 共識 "&IF(H52<0,"−","+")&IF(ABS(H52)<0,"−","")&"$"&TEXT(ABS(ABS(H52)),"#,##0.00")&"bn"&IF(ISNUMBER(H57),"／"&IF(H57<0,"−","+")&TEXT(ABS(H57)*100,"#,##0.0")&"pt","")&"：觀點（"&"模型 EBITDA 率 "&IF((H27)<0,"−","")&TEXT(ABS((H27))*100,"#,##0.0")&"%"&"；EBITDA＝分部營業利益＋分攤 D&A 與 AI 雲端 Tokenomics 由下而上營運成本"&"）"),""),"")
A100: 原因類型｜調整後 EBITDA｜vs 共識 | C100: =IF(ISNUMBER(C52),IF(IF(ISNUMBER(C57),ABS(C57)>輸入與假設!$C$510,OR(AND(C38<>0,ABS(C52)>輸入與假設!$C$509*ABS(C38)),AND(C38=0,C52<>0))),IF(ISNUMBER(C97),IF(ABS(C98)>ABS(C97),"拆法","觀點"),"觀點"),""),"") -> 觀點 | D100: =IF(ISNUMBER(D52),IF(IF(ISNUMBER(D57),ABS(D57)>輸入與假設!$C$510,OR(AND(D38<>0,ABS(D52)>輸入與假設!$C$509*ABS(D38)),AND(D38=0,D52<>0))),IF(ISNUMBER(D97),IF(ABS(D98)>ABS(D97),"拆法","觀點"),"觀點"),""),"") | E100: =IF(ISNUMBER(E52),IF(IF(ISNUMBER(E57),ABS(E57)>輸入與假設!$C$510,OR(AND(E38<>0,ABS(E52)>輸入與假設!$C$509*ABS(E38)),AND(E38=0,E52<>0))),IF(ISNUMBER(E97),IF(ABS(E98)>ABS(E97),"拆法","觀點"),"觀點"),""),"") | F100: =IF(ISNUMBER(F52),IF(IF(ISNUMBER(F57),ABS(F57)>輸入與假設!$C$510,OR(AND(F38<>0,ABS(F52)>輸入與假設!$C$509*ABS(F38)),AND(F38=0,F52<>0))),IF(ISNUMBER(F97),IF(ABS(F98)>ABS(F97),"拆法","觀點"),"觀點"),""),"") | G100: =IF(ISNUMBER(G52),IF(IF(ISNUMBER(G57),ABS(G57)>輸入與假設!$C$510,OR(AND(G38<>0,ABS(G52)>輸入與假設!$C$509*ABS(G38)),AND(G38=0,G52<>0))),IF(ISNUMBER(G97),IF(ABS(G98)>ABS(G97),"拆法","觀點"),"觀點"),""),"") | H100: =IF(ISNUMBER(H52),IF(IF(ISNUMBER(H57),ABS(H57)>輸入與假設!$C$510,OR(AND(H38<>0,ABS(H52)>輸入與假設!$C$509*ABS(H38)),AND(H38=0,H52<>0))),IF(ISNUMBER(H97),IF(ABS(H98)>ABS(H97),"拆法","觀點"),"觀點"),""),"")
A101: 原因｜調整後 EBITDA｜vs 指引中點
A102: 原因類型｜調整後 EBITDA｜vs 指引中點
...

Sheet 運營_產能與收入
A1: 產能與收入 — 合約排程 vs 機房產能
A2: 兩條線獨立產生後相減：排程>容量→瓶頸（收不到）；容量>排程→剩餘產能（要靠新簽約賣掉）
A3: FY27 欄口徑：MW 為年底存量；標示「（模型期）」的收入列只含 2027 全年——RPO 桶自 2026-06-30 起算，年初至今 收入已實現、不再受產能約束。年初至今 實際單列，兩者相加即 FY27 全年（見本頁「FY26 全年」列）。
A5: 項目 | B5: 單位 | C5: FY27 | D5: FY28 | E5: FY29 | F5: FY30 | G5: FY31 | I5: 公式／來源說明
A6: 模型期間 | C6: ="2026-07-01~06-30" -> 2026-07-01~06-30 | D6: ="2028 全年" -> 2028 全年 | E6: ="2029 全年" -> 2029 全年 | F6: ="2030 全年" -> 2030 全年 | G6: ="2031 全年" -> 2031 全年 | I6: FY27 的模型期只有全年；年初至今 已實現的營收單列於下方
A7: 模型期長度（年） | C7: =輸入與假設!C$34 -> 1 | D7: =輸入與假設!D$34 -> 1 | E7: =輸入與假設!E$34 -> 1 | F7: =輸入與假設!F$34 -> 1 | G7: =輸入與假設!G$34 -> 1 | I7: 只用於下方三處：容量上限、電力、維護——把年率換算成該期金額
A8: （A）機房：容量上限
A9: Accepted MW（已驗收，單調不減） | B9: MW | C9: =MAX(0,輸入與假設!C$36) -> 5575.9 | D9: =MAX(輸入與假設!D$36,C9) -> 7901.8 | E9: =MAX(輸入與假設!E$36,D9) -> 10227.7 | F9: =MAX(輸入與假設!F$36,E9) -> 12553.6 | G9: =MAX(輸入與假設!G$36,F9) -> 14879.5 | I9: 引擎規則：不得低於前期（產能不會消失）
A10: Billable MW（上限為 Accepted） | B10: MW | C10: =MIN(MAX(0,輸入與假設!C$37),C9) -> 5575.9 | D10: =MIN(MAX(0,輸入與假設!D$37),D9) -> 7901.8 | E10: =MIN(MAX(0,輸入與假設!E$37),E9) -> 10227.7 | F10: =MIN(MAX(0,輸入與假設!F$37),F9) -> 12553.6 | G10: =MIN(MAX(0,輸入與假設!G$37),G9) -> 14879 | I10: 引擎規則：可計費不得超過已驗收
A11: Billable MW（延誤後，計費用） | B11: MW | C11: =IF($C$50<=0,$C$10,輸入與假設!$C$29+($C$10-輸入與假設!$C$29)*MAX(0,MIN(1,($C$51-$C$50/12-0)/$C$7))+($D$10-$C$10)*MAX(0,MIN(1,($C$51-$C$50/12-$C$51)/$D$7))+($E$10-$D$10)*MAX(0,MIN(1,($C$51-$C$50/12-$D$51)/$E$7))+($F$10-$E$10)*MAX(0,MIN(1,($C$51-$C$50/12-$E$51)/$F$7))+($G$10-$F$10)*MAX(0,MIN(1,($C$51-$C$50/12-$F$51)/$G$7))) -> 5575.9 | D11: =IF($C$50<=0,$D$10,輸入與假設!$C$29+($C$10-輸入與假設!$C$29)*MAX(0,MIN(1,($D$51-$C$50/12-0)/$C$7))+($D$10-$C$10)*MAX(0,MIN(1,($D$51-$C$50/12-$C$51)/$D$7))+($E$10-$D$10)*MAX(0,MIN(1,($D$51-$C$50/12-$D$51)/$E$7))+($F$10-$E$10)*MAX(0,MIN(1,($D$51-$C$50/12-$E$51)/$F$7))+($G$10-$F$10)*MAX(0,MIN(1,($D$51-$C$50/12-$F$51)/$G$7))) -> 7901.8 | E11: =IF($C$50<=0,$E$10,輸入與假設!$C$29+($C$10-輸入與假設!$C$29)*MAX(0,MIN(1,($E$51-$C$50/12-0)/$C$7))+($D$10-$C$10)*MAX(0,MIN(1,($E$51-$C$50/12-$C$51)/$D$7))+($E$10-$D$10)*MAX(0,MIN(1,($E$51-$C$50/12-$D$51)/$E$7))+($F$10-$E$10)*MAX(0,MIN(1,($E$51-$C$50/12-$E$51)/$F$7))+($G$10-$F$10)*MAX(0,MIN(1,($E$51-$C$50/12-$F$51)/$G$7))) -> 10227.7 | F11: =IF($C$50<=0,$F$10,輸入與假設!$C$29+($C$10-輸入與假設!$C$29)*MAX(0,MIN(1,($F$51-$C$50/12-0)/$C$7))+($D$10-$C$10)*MAX(0,MIN(1,($F$51-$C$50/12-$C$51)/$D$7))+($E$10-$D$10)*MAX(0,MIN(1,($F$51-$C$50/12-$D$51)/$E$7))+($F$10-$E$10)*MAX(0,MIN(1,($F$51-$C$50/12-$E$51)/$F$7))+($G$10-$F$10)*MAX(0,MIN(1,($F$51-$C$50/12-$F$51)/$G$7))) -> 12553.6 | G11: =IF($C$50<=0,$G$10,輸入與假設!$C$29+($C$10-輸入與假設!$C$29)*MAX(0,MIN(1,($G$51-$C$50/12-0)/$C$7))+($D$10-$C$10)*MAX(0,MIN(1,($G$51-$C$50/12-$C$51)/$D$7))+($E$10-$D$10)*MAX(0,MIN(1,($G$51-$C$50/12-$D$51)/$E$7))+($F$10-$E$10)*MAX(0,MIN(1,($G$51-$C$50/12-$E$51)/$F$7))+($G$10-$F$10)*MAX(0,MIN(1,($G$51-$C$50/12-$F$51)/$G$7))) -> 14879 | I11: ＝上列往後平移建設延誤月數（以期間長度線性內插；評價日之前取期初校準值）；延誤 0 時＝上列；見（E）區（v0.2）
A12: 期初在役 MW | B12: MW | C12: =輸入與假設!$C$29 -> 3250 | D12: =C11 -> 5575.9 | E12: =D11 -> 7901.8 | F12: =E11 -> 10227.7 | G12: =F11 -> 12553.6 | I12: 前期期末＝本期期初（延誤後）
A13: 平均在役 MW（FY27 欄為全年平均） | B13: MW | C13: =IF(輸入與假設!$C$30=1,(C12+C11)/2,C11) -> 4412.95 | D13: =IF(輸入與假設!$C$30=1,(D12+D11)/2,D11) -> 6738.85 | E13: =IF(輸入與假設!$C$30=1,(E12+E11)/2,E11) -> 9064.75 | F13: =IF(輸入與假設!$C$30=1,(F12+F11)/2,F11) -> 11390.65 | G13: =IF(輸入與假設!$C$30=1,(G12+G11)/2,G11) -> 13716.3 | I13: 開關在輸入頁：1＝(期初+期末)/2，0＝期末全期化
A14: 利用率 | B14: % | C14: =輸入與假設!C$38 -> 1 | D14: =輸入與假設!D$38 -> 1 | E14: =輸入與假設!E$38 -> 1 | F14: =輸入與假設!F$38 -> 1 | G14: =輸入與假設!G$38 -> 1
A15: 每 MW 年收入 | B15: US$bn/MW | C15: =輸入與假設!C$39 -> 0.01218028 | D15: =輸入與假設!D$39 -> 0.012573416 | E15: =輸入與假設!E$39 -> 0.012789542 | F15: =輸入與假設!F$39 -> 0.012925581 | G15: =輸入與假設!G$39 -> 0.01301909
A16: 容量上限（模型期最多能交付的收入） | B16: US$bn | C16: =C13*輸入與假設!C$39*輸入與假設!$C$32*輸入與假設!C$38*C7 -> 53.750967 | D16: =D13*輸入與假設!D$39*輸入與假設!$C$32*輸入與假設!D$38*D7 -> 84.730366 | E16: =E13*輸入與假設!E$39*輸入與假設!$C$32*輸入與假設!E$38*E7 -> 115.934 | F16: =F13*輸入與假設!F$39*輸入與假設!$C$32*輸入與假設!F$38*F7 -> 147.23076 | G16: =G13*輸入與假設!G$39*輸入與假設!$C$32*輸入與假設!G$38*G7 -> 178.57374 | I16: ＝平均在役 MW × 每 MW 年收入 × 利用率 × 期間係數。只看機房，不看合約
A17: （B）合約：排程 RPO
A18: 排程 RPO（模型期，依季報桶分攤） | B18: US$bn | C18: =(輸入與假設!$C$24+輸入與假設!$C$25)*(輸入與假設!C$35/輸入與假設!$C$27)*輸入與假設!$C$26 -> 0 | D18: =(輸入與假設!$C$24+輸入與假設!$C$25)*(輸入與假設!D$35/輸入與假設!$C$27)*輸入與假設!$C$26 -> 0 | E18: =(輸入與假設!$C$24+輸入與假設!$C$25)*(輸入與假設!E$35/輸入與假設!$C$27)*輸入與假設!$C$26 -> 0 | F18: =(輸入與假設!$C$24+輸入與假設!$C$25)*(輸入與假設!F$35/輸入與假設!$C$27)*輸入與假設!$C$26 -> 0 | G18: =(輸入與假設!$C$24+輸入與假設!$C$25)*(輸入與假設!G$35/輸入與假設!$C$27)*輸入與假設!$C$26 -> 0 | I18: ＝(6/30 RPO＋評價日後新增)×本期權重÷權重合計×五期認列比例。只看合約，不看機房
A19: （C）兩條線相減
A20: 產能瓶頸（模型期：排程 − 容量） | B20: US$bn | C20: =MAX(0,C18-C16) -> 0 | D20: =MAX(0,D18-D16) -> 0 | E20: =MAX(0,E18-E16) -> 0 | F20: =MAX(0,F18-F16) -> 0 | G20: =MAX(0,G18-G16) -> 0 | I20: 合約有、機房沒有 → 本期收不到，且不遞延到下期（保守處理）
A21: 期初 RPO 轉換收入（模型期） | B21: US$bn | C21: =C18-C20 -> 0 | D21: =D18-D20 -> 0 | E21: =E18-E20 -> 0 | F21: =F18-F20 -> 0 | G21: =G18-G20 -> 0 | I21: ＝排程 − 瓶頸。當瓶頸>0 時，此值恆等於容量上限
A22: 未被期初 RPO 占用的產能 | B22: US$bn | C22: =MAX(0,C16-C18) -> 53.750967 | D22: =MAX(0,D16-D18) -> 84.730366 | E22: =MAX(0,E16-E18) -> 115.934 | F22: =MAX(0,F16-F18) -> 147.23076 | G22: =MAX(0,G16-G18) -> 178.57374 | I22: 容量 − 排程。機房有、期初合約沒占滿 → 要靠新簽約
A23: 新產能簽約率 | B23: % | C23: =IF(輸入與假設!$C$31="mw",1,輸入與假設!C$40) -> 1 | D23: =IF(輸入與假設!$C$31="mw",1,輸入與假設!D$40) -> 1 | E23: =IF(輸入與假設!$C$31="mw",1,輸入與假設!E$40) -> 1 | F23: =IF(輸入與假設!$C$31="mw",1,輸入與假設!F$40) -> 1 | G23: =IF(輸入與假設!$C$31="mw",1,輸入與假設!G$40) -> 1 | I23: MW 驅動時固定 100%
A24: 新簽約收入 | B24: US$bn | C24: =C22*C23 -> 53.750967 | D24: =D22*D23 -> 84.730366 | E24: =E22*E23 -> 115.934 | F24: =F22*F23 -> 147.23076 | G24: =G22*G23 -> 178.57374 | I24: 超出期初 RPO 的產能收入（MW 驅動，簽約率 100%）
A25: 未售產能（浪費） | B25: US$bn | C25: =MAX(0,C16-C21-C24) -> 0 | D25: =MAX(0,D16-D21-D24) -> 0 | E25: =MAX(0,E16-E21-E24) -> 0 | F25: =MAX(0,F16-F21-F24) -> 0 | G25: =MAX(0,G16-G21-G24) -> 0 | I25: 蓋好但賣不掉（MW 驅動時為 0）
A26: 損益用算力收入（模型期＝RPO 轉換＋新簽約） | B26: US$bn | C26: =C21+C24 -> 53.750967 | D26: =D21+D24 -> 84.730366 | E26: =E21+E24 -> 115.934 | F26: =F21+F24 -> 147.23076 | G26: =G21+G24 -> 178.57374 | I26: 損益與評價頁的算力收入由此連結，確保現金與損益同一組數字
A27: 核對：算力收入 − 平均在役 MW × 每 MW × 利用率 × 期間 | B27: US$bn | C27: =C26-C13*輸入與假設!C$39*輸入與假設!$C$32*輸入與假設!C$38*C7 -> 0 | D27: =D26-D13*輸入與假設!D$39*輸入與假設!$C$32*輸入與假設!D$38*D7 -> 0 | E27: =E26-E13*輸入與假設!E$39*輸入與假設!$C$32*輸入與假設!E$38*E7 -> 0 | F27: =F26-F13*輸入與假設!F$39*輸入與假設!$C$32*輸入與假設!F$38*F7 -> 0 | G27: =G26-G13*輸入與假設!G$39*輸入與假設!$C$32*輸入與假設!G$38*G7 -> 0 | I27: MW 驅動時應為 0：營收可追溯為 MW × 每 MW 年收入 × 利用率（v0.1b）
A28: 對照：評價日起 36 個月營收權重 | B28: % | C28: 1 | D28: 1 | E28: 1 | F28: 0 | G28: 0 | I28: RPO 36 個月內轉換的對照用（只作對照，不驅動營收）
A29: 對照：評價日起 36 個月 MW 驅動營收 | B29: US$bn | C29: =C26*C28 -> 53.750967 | D29: =D26*D28 -> 84.730366 | E29: =E26*E28 -> 115.934 | F29: =F26*F28 -> 0 | G29: =G26*G28 -> 0 | I29: 合計對照季報 RPO 684 × 36 個月內 75%（含非 AI 事業 RPO）；差額不回推每 MW 單價
A30: 年初至今 實際營收（季報，已實現） | B30: US$bn | C30: =輸入與假設!$C$439 -> 0 | D30: =0 -> 0 | E30: =0 -> 0 | F30: =0 -> 0 | G30: =0 -> 0 | I30: 2026-07-01 至 06-30 已認列營收。已實現，不受全年產能約束，故不進入上方的瓶頸計算
A31: FY27 全年總營收（年初至今 實際＋模型期算力＋服務＋非 AI 事業） | B31: US$bn | C31: =C30+C26+輸入與假設!C$43+輸入與假設!C$204 -> 397.44559 | D31: =D30+D26+輸入與假設!D$43+輸入與假設!D$204 -> 471.42433 | E31: =E30+E26+輸入與假設!E$43+輸入與假設!E$204 -> 545.53771 | F31: =F30+F26+輸入與假設!F$43+輸入與假設!F$204 -> 617.32077 | G31: =G30+G26+輸入與假設!G$43+輸入與假設!G$204 -> 684.29505 | I31: FY27 欄對照公司全年指引 未給全年營收指引；FY28 以後即為該年度總營收
A32: （D）收入 → 現金：三道折扣
A33: 客戶違約率 | B33: % | C33: =輸入與假設!C$41 -> 0 | D33: =輸入與假設!D$41 -> 0 | E33: =輸入與假設!E$41 -> 0 | F33: =輸入與假設!F$41 -> 0 | G33: =輸入與假設!G$41 -> 0
A34: 回收率 | B34: % | C34: =輸入與假設!C$42 -> 0.5 | D34: =輸入與假設!D$42 -> 0.5 | E34: =輸入與假設!E$42 -> 0.5 | F34: =輸入與假設!F$42 -> 0.5 | G34: =輸入與假設!G$42 -> 0.5
A35: 信用損失（期初 RPO 部分） | B35: US$bn | C35: =C21*輸入與假設!C$41*(1-輸入與假設!C$42) -> 0 | D35: =D21*輸入與假設!D$41*(1-輸入與假設!D$42) -> 0 | E35: =E21*輸入與假設!E$41*(1-輸入與假設!E$42) -> 0 | F35: =F21*輸入與假設!F$41*(1-輸入與假設!F$42) -> 0 | G35: =G21*輸入與假設!G$41*(1-輸入與假設!G$42) -> 0 | I35: ＝收入 × 違約率 × (1−回收率)
A36: 收現（期初 RPO 部分） | B36: US$bn | C36: =C21-C35 -> 0 | D36: =D21-D35 -> 0 | E36: =E21-E35 -> 0 | F36: =F21-F35 -> 0 | G36: =G21-G35 -> 0
A37: EBITDA 率（損益與資金共用） | B37: % | C37: =輸入與假設!C$214 -> 0.79787831 | D37: =輸入與假設!D$214 -> 0.80029644 | E37: =輸入與假設!E$214 -> 0.80156247 | F37: =輸入與假設!F$214 -> 0.80233765 | G37: =輸入與假設!G$214 -> 0.80286109 | I37: 起始→穩態線性爬升
A38: 模型期總營收（算力＋服務） | B38: US$bn | C38: =C26+輸入與假設!C$43 -> 53.750967 | D38: =D26+輸入與假設!D$43 -> 84.730366 | E38: =E26+輸入與假設!E$43 -> 115.934 | F38: =F26+輸入與假設!F$43 -> 147.23076 | G38: =G26+輸入與假設!G$43 -> 178.57374
A39: EBITDAR 率（EBITDA 率＋租金÷營收） | B39: % | C39: =輸入與假設!C$214 -> 0.79787831 | D39: =輸入與假設!D$214 -> 0.80029644 | E39: =輸入與假設!E$214 -> 0.80156247 | F39: =輸入與假設!F$214 -> 0.80233765 | G39: =輸入與假設!G$214 -> 0.80286109 | I39: 租金前的 EBITDA 率。EBITDA 已扣租金，而資金模型把租金列在支出端，所以要加回，避免重複扣除
A40: RPO 現金（可支應資本用途） | B40: US$bn | C40: =C36*C39 -> 0 | D40: =D36*D39 -> 0 | E40: =E36*E39 -> 0 | F40: =F36*F39 -> 0 | G40: =G36*G39 -> 0 | I40: ×EBITDAR 率。租金與利息在支出頁單獨列示
A41: 新簽約現金 | B41: US$bn | C41: =C24*(1-輸入與假設!C$41*(1-輸入與假設!C$42))*C39 -> 42.88673 | D41: =D24*(1-輸入與假設!D$41*(1-輸入與假設!D$42))*D39 -> 67.80941 | E41: =E24*(1-輸入與假設!E$41*(1-輸入與假設!E$42))*E39 -> 92.928341 | F41: =F24*(1-輸入與假設!F$41*(1-輸入與假設!F$42))*F39 -> 118.12879 | G41: =G24*(1-輸入與假設!G$41*(1-輸入與假設!G$42))*G39 -> 143.36991 | I41: 同樣扣信用損失、乘 EBITDAR 率
A43: 讀法：FY27（全年）與 FY28 瓶頸>0，合約多於機房；FY29 起反轉，收入愈來愈靠『新簽約收入』這一列。
A44: 把『新產能簽約率』調到 0，就能看到只靠期初 RPO 的資金缺口有多大——這是最重要的一個壓力測試。
A46: （E）建設延誤（v0.2）：計費 MW 往後平移；GPU 資本支出與客戶出資照原時程；折舊自投入使用時點起算
A47: 建設延誤月數｜保守 第三方可辨識站點 | B47: 月 | C47: 0 | I47: company.json → scenarios.delayMonths；依據見該欄 note [Assumed]
A48: 建設延誤月數｜基準 依資本支出指引 | B48: 月 | C48: 0 | I48: company.json → scenarios.delayMonths；依據見該欄 note [Assumed]
A49: 建設延誤月數｜積極 依公司容量目標 | B49: 月 | C49: 0 | I49: company.json → scenarios.delayMonths；依據見該欄 note [Assumed]
A50: 建設延誤月數（目前情境） | B50: 月 | C50: =CHOOSE(輸入與假設!$C$5,運營_產能與收入!$C$47,運營_產能與收入!$C$48,運營_產能與收入!$C$49) -> 0 | I50: ＝依『輸入與假設』A 區情境選擇器；0＝不延誤（＝v0.1）
A51: 期末時點（評價日起，年） | B51: 年 | C51: =SUM($C$7:C7) -> 1 | D51: =SUM($C$7:D7) -> 2 | E51: =SUM($C$7:E7) -> 3 | F51: =SUM($C$7:F7) -> 4 | G51: =SUM($C$7:G7) -> 5 | I51: ＝累計期間長度
A52: 成長型 CapEx 累計（原時程，評價日起） | B52: US$bn | C52: =SUM(輸入與假設!$C$263:C$263) -> 204.20173 | D52: =SUM(輸入與假設!$C$263:D$263) -> 420.40909 | E52: =SUM(輸入與假設!$C$263:E$263) -> 642.37453 | F52: =SUM(輸入與假設!$C$263:F$263) -> 869.52809 | G52: =SUM(輸入與假設!$C$263:G$263) -> 1101.0336 | I52: GPU 與網通照原併網時程採購、交貨等電（客戶出資覆蓋比同樣依原時程）
A53: 已投入使用累計（延誤後） | B53: US$bn | C53: =IF($C$50<=0,$C$52,0+($C$52-0)*MAX(0,MIN(1,($C$51-$C$50/12-0)/$C$7))+($D$52-$C$52)*MAX(0,MIN(1,($C$51-$C$50/12-$C$51)/$D$7))+($E$52-$D$52)*MAX(0,MIN(1,($C$51-$C$50/12-$D$51)/$E$7))+($F$52-$E$52)*MAX(0,MIN(1,($C$51-$C$50/12-$E$51)/$F$7))+($G$52-$F$52)*MAX(0,MIN(1,($C$51-$C$50/12-$F$51)/$G$7))) -> 204.20173 | D53: =IF($C$50<=0,$D$52,0+($C$52-0)*MAX(0,MIN(1,($D$51-$C$50/12-0)/$C$7))+($D$52-$C$52)*MAX(0,MIN(1,($D$51-$C$50/12-$C$51)/$D$7))+($E$52-$D$52)*MAX(0,MIN(1,($D$51-$C$50/12-$D$51)/$E$7))+($F$52-$E$52)*MAX(0,MIN(1,($D$51-$C$50/12-$E$51)/$F$7))+($G$52-$F$52)*MAX(0,MIN(1,($D$51-$C$50/12-$F$51)/$G$7))) -> 420.40909 | E53: =IF($C$50<=0,$E$52,0+($C$52-0)*MAX(0,MIN(1,($E$51-$C$50/12-0)/$C$7))+($D$52-$C$52)*MAX(0,MIN(1,($E$51-$C$50/12-$C$51)/$D$7))+($E$52-$D$52)*MAX(0,MIN(1,($E$51-$C$50/12-$D$51)/$E$7))+($F$52-$E$52)*MAX(0,MIN(1,($E$51-$C$50/12-$E$51)/$F$7))+($G$52-$F$52)*MAX(0,MIN(1,($E$51-$C$50/12-$F$51)/$G$7))) -> 642.37453 | F53: =IF($C$50<=0,$F$52,0+($C$52-0)*MAX(0,MIN(1,($F$51-$C$50/12-0)/$C$7))+($D$52-$C$52)*MAX(0,MIN(1,($F$51-$C$50/12-$C$51)/$D$7))+($E$52-$D$52)*MAX(0,MIN(1,($F$51-$C$50/12-$D$51)/$E$7))+($F$52-$E$52)*MAX(0,MIN(1,($F$51-$C$50/12-$E$51)/$F$7))+($G$52-$F$52)*MAX(0,MIN(1,($F$51-$C$50/12-$F$51)/$G$7))) -> 869.52809 | G53: =IF($C$50<=0,$G$52,0+($C$52-0)*MAX(0,MIN(1,($G$51-$C$50/12-0)/$C$7))+($D$52-$C$52)*MAX(0,MIN(1,($G$51-$C$50/12-$C$51)/$D$7))+($E$52-$D$52)*MAX(0,MIN(1,($G$51-$C$50/12-$D$51)/$E$7))+($F$52-$E$52)*MAX(0,MIN(1,($G$51-$C$50/12-$E$51)/$F$7))+($G$52-$F$52)*MAX(0,MIN(1,($G$51-$C$50/12-$F$51)/$G$7))) -> 1101.0336 | I53: ＝上列往後平移建設延誤月數（線性內插）；延誤 0 時＝上列
A54: 本期投入使用的成長型 CapEx（折舊基礎） | B54: US$bn | C54: =C53 -> 204.20173 | D54: =D53-C53 -> 216.20736 | E54: =E53-D53 -> 221.96544 | F54: =F53-E53 -> 227.15356 | G54: =G53-F53 -> 231.50554 | I54: 車隊折舊自投入使用時點起算（『輸入與假設』期初毛 PP&E 與 D&A 引用此列）
A55: 閒置資本（已支出未產生收入，期末） | B55: US$bn | C55: =C52-C53 -> 0 | D55: =D52-D53 -> 0 | E55: =E52-E53 -> 0 | F55: =F52-F53 -> 0 | G55: =G52-G53 -> 0 | I55: ＝原時程累計 − 已投入使用累計；延誤 0 時為 0。一頁摘要以一句呈現峰值
A56: 未起租租約起租連動比例（delayLink） | B56: % | C56: 0 | I56: 未起租租金中此比例的起租時點隨延誤月數後移（開發商交付晚），其餘照原時程（company.json → leases.uncommenced.delayLink）[Assumed]；替代 0／1
A57: 延誤罰則（應計費而未計費營收的 %） | B57: % | C57: 0 | I57: 公司未揭露合約條款：預設 0（不存在／未揭露）；敏感度 5%／10%（company.json → defaults.delayPenalty）[Assumed]
A58: 表外現金租金：全部隨延誤平移（對照） | B58: US$bn | C58: =輸入與假設!$C$19/輸入與假設!$C$21/輸入與假設!$C$22/4*((MIN(MAX(0,輸入與假設!C$245-(輸入與假設!$C$20+運營_產能與收入!$C$50/3)),輸入與假設!$C$21)*(MIN(MAX(0,輸入與假設!C$245-(輸入與假設!$C$20+運營_產能與收入!$C$50/3)),輸入與假設!$C$21)+1)/2+輸入與假設!$C$21*MAX(0,MAX(0,輸入與假設!C$245-(輸入與假設!$C$20+運營_產能與收入!$C$50/3))-輸入與假設!$C$21))-(MIN(MAX(0,0-(輸入與假設!$C$20+運營_產能與收入!$C$50/3)),輸入與假設!$C$21)*(MIN(MAX(0,0-(輸入與假設!$C$20+運營_產能與收入!$C$50/3)),輸入與假設!$C$21)+1)/2+輸入與假設!$C$21*MAX(0,MAX(0,0-(輸入與假設!$C$20+運營_產能與收入!$C$50/3))-輸入與假設!$C$21))) -> 3.428125 | D58: =輸入與假設!$C$19/輸入與假設!$C$21/輸入與假設!$C$22/4*((MIN(MAX(0,輸入與假設!D$245-(輸入與假設!$C$20+運營_產能與收入!$C$50/3)),輸入與假設!$C$21)*(MIN(MAX(0,輸入與假設!D$245-(輸入與假設!$C$20+運營_產能與收入!$C$50/3)),輸入與假設!$C$21)+1)/2+輸入與假設!$C$21*MAX(0,MAX(0,輸入與假設!D$245-(輸入與假設!$C$20+運營_產能與收入!$C$50/3))-輸入與假設!$C$21))-(MIN(MAX(0,輸入與假設!C$245-(輸入與假設!$C$20+運營_產能與收入!$C$50/3)),輸入與假設!$C$21)*(MIN(MAX(0,輸入與假設!C$245-(輸入與假設!$C$20+運營_產能與收入!$C$50/3)),輸入與假設!$C$21)+1)/2+輸入與假設!$C$21*MAX(0,MAX(0,輸入與假設!C$245-(輸入與假設!$C$20+運營_產能與收入!$C$50/3))-輸入與假設!$C$21))) -> 8.913125 | E58: =輸入與假設!$C$19/輸入與假設!$C$21/輸入與假設!$C$22/4*((MIN(MAX(0,輸入與假設!E$245-(輸入與假設!$C$20+運營_產能與收入!$C$50/3)),輸入與假設!$C$21)*(MIN(MAX(0,輸入與假設!E$245-(輸入與假設!$C$20+運營_產能與收入!$C$50/3)),輸入與假設!$C$21)+1)/2+輸入與假設!$C$21*MAX(0,MAX(0,輸入與假設!E$245-(輸入與假設!$C$20+運營_產能與收入!$C$50/3))-輸入與假設!$C$21))-(MIN(MAX(0,輸入與假設!D$245-(輸入與假設!$C$20+運營_產能與收入!$C$50/3)),輸入與假設!$C$21)*(MIN(MAX(0,輸入與假設!D$245-(輸入與假設!$C$20+運營_產能與收入!$C$50/3)),輸入與假設!$C$21)+1)/2+輸入與假設!$C$21*MAX(0,MAX(0,輸入與假設!D$245-(輸入與假設!$C$20+運營_產能與收入!$C$50/3))-輸入與假設!$C$21))) -> 14.398125 | F58: =輸入與假設!$C$19/輸入與假設!$C$21/輸入與假設!$C$22/4*((MIN(MAX(0,輸入與假設!F$245-(輸入與假設!$C$20+運營_產能與收入!$C$50/3)),輸入與假設!$C$21)*(MIN(MAX(0,輸入與假設!F$245-(輸入與假設!$C$20+運營_產能與收入!$C$50/3)),輸入與假設!$C$21)+1)/2+輸入與假設!$C$21*MAX(0,MAX(0,輸入與假設!F$245-(輸入與假設!$C$20+運營_產能與收入!$C$50/3))-輸入與假設!$C$21))-(MIN(MAX(0,輸入與假設!E$245-(輸入與假設!$C$20+運營_產能與收入!$C$50/3)),輸入與假設!$C$21)*(MIN(MAX(0,輸入與假設!E$245-(輸入與假設!$C$20+運營_產能與收入!$C$50/3)),輸入與假設!$C$21)+1)/2+輸入與假設!$C$21*MAX(0,MAX(0,輸入與假設!E$245-(輸入與假設!$C$20+運營_產能與收入!$C$50/3))-輸入與假設!$C$21))) -> 19.883125 | G58: =輸入與假設!$C$19/輸入與假設!$C$21/輸入與假設!$C$22/4*((MIN(MAX(0,輸入與假設!G$245-(輸入與假設!$C$20+運營_產能與收入!$C$50/3)),輸入與假設!$C$21)*(MIN(MAX(0,輸入與假設!G$245-(輸入與假設!$C$20+運營_產能與收入!$C$50/3)),輸入與假設!$C$21)+1)/2+輸入與假設!$C$21*MAX(0,MAX(0,輸入與假設!G$245-(輸入與假設!$C$20+運營_產能與收入!$C$50/3))-輸入與假設!$C$21))-(MIN(MAX(0,輸入與假設!F$245-(輸入與假設!$C$20+運營_產能與收入!$C$50/3)),輸入與假設!$C$21)*(MIN(MAX(0,輸入與假設!F$245-(輸入與假設!$C$20+運營_產能與收入!$C$50/3)),輸入與假設!$C$21)+1)/2+輸入與假設!$C$21*MAX(0,MAX(0,輸入與假設!F$245-(輸入與假設!$C$20+運營_產能與收入!$C$50/3))-輸入與假設!$C$21))) -> 21.94 | I58: ＝未起租排程的起算季延後 延誤月數 ÷ 3 季（其餘同『輸入與假設』表外現金租金）
A59: 表外現金租金（未起租，延誤連動後） | B59: US$bn | C59: =IF(OR(運營_產能與收入!$C$50<=0,運營_產能與收入!$C$56<=0),輸入與假設!C$246,(1-運營_產能與收入!$C$56)*輸入與假設!C$246+運營_產能與收入!$C$56*C58) -> 3.428125 | D59: =IF(OR(運營_產能與收入!$C$50<=0,運營_產能與收入!$C$56<=0),輸入與假設!D$246,(1-運營_產能與收入!$C$56)*輸入與假設!D$246+運營_產能與收入!$C$56*D58) -> 8.913125 | E59: =IF(OR(運營_產能與收入!$C$50<=0,運營_產能與收入!$C$56<=0),輸入與假設!E$246,(1-運營_產能與收入!$C$56)*輸入與假設!E$246+運營_產能與收入!$C$56*E58) -> 14.398125 | F59: =IF(OR(運營_產能與收入!$C$50<=0,運營_產能與收入!$C$56<=0),輸入與假設!F$246,(1-運營_產能與收入!$C$56)*輸入與假設!F$246+運營_產能與收入!$C$56*F58) -> 19.883125 | G59: =IF(OR(運營_產能與收入!$C$50<=0,運營_產能與收入!$C$56<=0),輸入與假設!G$246,(1-運營_產能與收入!$C$56)*輸入與假設!G$246+運營_產能與收入!$C$56*G58) -> 21.94 | I59: ＝(1 − 連動比例)× 原排程＋連動比例 × 平移後排程；延誤 0 時＝原排程（『各期收支』租金引用此列）
A60: 容量上限（未延誤，對照） | B60: US$bn | C60: =IF(輸入與假設!$C$30=1,(輸入與假設!$C$29+C10)/2,C10)*輸入與假設!C$39*輸入與假設!$C$32*輸入與假設!C$38*C7 -> 53.750967 | D60: =IF(輸入與假設!$C$30=1,(C10+D10)/2,D10)*輸入與假設!D$39*輸入與假設!$C$32*輸入與假設!D$38*D7 -> 84.730366 | E60: =IF(輸入與假設!$C$30=1,(D10+E10)/2,E10)*輸入與假設!E$39*輸入與假設!$C$32*輸入與假設!E$38*E7 -> 115.934 | F60: =IF(輸入與假設!$C$30=1,(E10+F10)/2,F10)*輸入與假設!F$39*輸入與假設!$C$32*輸入與假設!F$38*F7 -> 147.23076 | G60: =IF(輸入與假設!$C$30=1,(F10+G10)/2,G10)*輸入與假設!G$39*輸入與假設!$C$32*輸入與假設!G$38*G7 -> 178.57374 | I60: ＝未延誤的平均可計費 MW × 每 MW 年收入 × 利用率 × 期間長度
A61: 應計費而未計費營收（延誤造成） | B61: US$bn | C61: =IF(運營_產能與收入!$C$50<=0,0,MAX(0,C60-C16)) -> 0 | D61: =IF(運營_產能與收入!$C$50<=0,0,MAX(0,D60-D16)) -> 0 | E61: =IF(運營_產能與收入!$C$50<=0,0,MAX(0,E60-E16)) -> 0 | F61: =IF(運營_產能與收入!$C$50<=0,0,MAX(0,F60-F16)) -> 0 | G61: =IF(運營_產能與收入!$C$50<=0,0,MAX(0,G60-G16)) -> 0 | I61: ＝未延誤容量上限 − 延誤後容量上限
A62: 延誤罰則（營業費用） | B62: US$bn | C62: =運營_產能與收入!$C$57*C61 -> 0 | D62: =運營_產能與收入!$C$57*D61 -> 0 | E62: =運營_產能與收入!$C$57*E61 -> 0 | F62: =運營_產能與收入!$C$57*F61 -> 0 | G62: =運營_產能與收入!$C$57*G61 -> 0 | I62: ＝罰則比例 × 應計費而未計費營收；扣 EBITDA、營運來源、稅基與債務上限。客戶預付不因延誤退還（已知限制）

Sheet 運營_站點
A1: 站點租賃 — 公司揭露 vs 季報總額（檢驗租金路徑用）
A2: 季報不揭露逐站租金；下表為具名站點（company.json → defaults.sites），有租約金額者用來檢驗『每 MW 年租金』與模型租金路徑是否一致
A4: 站點 | B4: 營運方 | C4: 契約 MW | D4: 已驗收 MW | E4: 合約總值 $bn | F4: 年期 | G4: 年租金 $bn | H4: 每 MW 年租金 $m | I4: 時程 | J4: 季報對應 | K4: 說明
A5: Fairwater Wisconsin（Mount Pleasant） | B5: Microsoft 自建（OpenAI 與 Microsoft，B200） | C5: 2263 | D5: 369 | E5: 未揭露 | F5: 未揭露 | I5: 2026 | J5: — | K5: Epoch AI：目前 IT 電力 369 MW（2026-10-05 更新；2028Q2 預測 2,263；事實總帳 mw.epoch.fairwaterWI）[Analogy／第三方]
A6: Fairwater Atlanta | B6: Microsoft 自建（OpenAI 與 Microsoft，GB200） | C6: 636 | D6: 636 | E6: 未揭露 | F6: 未揭露 | I6: 2026 | J6: — | K6: Epoch AI：Buildings 1–4 已運轉，636 MW-IT（2026-06-14）
A7: 具名站點合計 | C7: =SUM(C5:C6) -> 2899 | D7: =SUM(D5:D6) -> 1005 | E7: =SUM(E5:E6) -> 0 | G7: =SUM(G5:G6) -> 0 | H7: =IF(I7>0,G7/I7*1000,0) -> 0 | I7: =SUMPRODUCT(ISNUMBER(G5:G6)*C5:C6) -> 0 | K7: 加權每 MW 年租金＝具名站點的市場基準（I 欄＝有租約金額站點的契約 MW；沒有時為 0，不適用）
A9: 對帳：具名站點 vs 季報租賃承諾總額
A10: 季報在帳租賃（未折現，已起租） | E10: 114.392 | K10: company.json → leases.facts.onBal
A11: 季報未起租租賃（未折現） | E11: 329.1 | K11: company.json → leases.facts.notCommenced
A12: 季報單站按造價計租上限 | E12: 0 | K12: company.json → leases.facts.singleCap（無則 0）
A13: 季報已揭露租賃承諾合計 | E13: =SUM(E10:E12) -> 443.492 | K13: 未折現金額
A14: 減：具名站點合約總值 | E14: =-E7 -> 0
A15: ＝ 未具名站點（殘差） | E15: =E13+E14 -> 443.492 | K15: 未具名站點；公司不揭露逐站租金，殘差大是必然
A16: 殘差占季報總額 | E16: =IF(E13<>0,E15/E13,0) -> 1
A18: 檢驗：模型租金路徑 ÷ 在役 MW vs 市場基準
A19: 項目 | B19: 單位 | C19: FY27 | D19: FY28 | E19: FY29 | F19: FY30 | G19: FY31
A20: 模型租金（在帳＋表外） | B20: US$bn | C20: =各期收支!C16 -> 7.9780312 | D20: =各期收支!D16 -> 9.5222813 | E20: =各期收支!E16 -> 10.267531 | F20: =各期收支!F16 -> 11.540781 | G20: =各期收支!G16 -> 12.028
A21: 平均在役 MW（已連網） | B21: MW | C21: =(輸入與假設!C$253+輸入與假設!C$36)/2 -> 4412.95 | D21: =(輸入與假設!D$253+輸入與假設!D$36)/2 -> 6738.85 | E21: =(輸入與假設!E$253+輸入與假設!E$36)/2 -> 9064.75 | F21: =(輸入與假設!F$253+輸入與假設!F$36)/2 -> 11390.65 | G21: =(輸入與假設!G$253+輸入與假設!G$36)/2 -> 13716.55
A22: 模型期長度（年） | B22: 年 | C22: =輸入與假設!C$34 -> 1 | D22: =輸入與假設!D$34 -> 1 | E22: =輸入與假設!E$34 -> 1 | F22: =輸入與假設!F$34 -> 1 | G22: =輸入與假設!G$34 -> 1
A23: 模型每 MW 年租金 | B23: US$m/MW | C23: =C20/C22/C21*1000 -> 1.807868 | D23: =D20/D22/D21*1000 -> 1.4130425 | E23: =E20/E22/E21*1000 -> 1.1326877 | F23: =F20/F22/F21*1000 -> 1.0131802 | G23: =G20/G22/G21*1000 -> 0.87689689 | K23: FY27 欄只含全年租金、MW 取全期平均，略有低估
A24: 第三方租賃占比 | C24: 1 | K24: 其餘為自建，成本走 CapEx（company.json → leases.facts.share）[Assumed]
A25: 基準租金（MW×市場基準×占比） | B25: US$bn | C25: =C21*運營_站點!$H$7/1000*$C$24*C22 -> 0 | D25: =D21*運營_站點!$H$7/1000*$C$24*D22 -> 0 | E25: =E21*運營_站點!$H$7/1000*$C$24*E22 -> 0 | F25: =F21*運營_站點!$H$7/1000*$C$24*F22 -> 0 | G25: =G21*運營_站點!$H$7/1000*$C$24*G22 -> 0 | K25: 具名站點有租約金額時才有意義；否則為 0
A26: 差額（基準 − 模型） | B26: US$bn | C26: =C25-C20 -> -7.9780312 | D26: =D25-D20 -> -9.5222813 | E26: =E25-E20 -> -10.267531 | F26: =F25-F20 -> -11.540781 | G26: =G25-G20 -> -12.028 | K26: 正值＝模型租金可能低估的金額
A27: 五期差額合計 | C27: =SUM(C26:G26) -> -51.336625

Sheet 資產負債_既有債務
A1: 債務明細 — 季報（2026-06-30）逐筆＋存量利息推導
A2: 有效利率為現金票息口徑（可轉債＝票息 ÷ 到期累積倍數，本金以到期累積本金計）。本頁算出的存量利息連回『輸入』頁，再進入支出與資金頁
A4: 工具 | B4: 類別 | C4: 到期 | D4: 有效利率 | E4: 6/30 本金 | F4: 年化利息 | I4: 備註
A5: 2009 票據 | B5: 無擔保 | C5: 2039-06 | D5: 0.052 | E5: 0.52 | F5: =D5*E5 -> 0.02704 | I5: 10-K FY26 附註 10：面額 520、票面 5.20%–5.20%（取中點）、到期 2039–2039；到期日取區間中點 [Derived]
A6: 2010 票據 | B6: 無擔保 | C6: 2040-06 | D6: 0.045 | E6: 0.486 | F6: =D6*E6 -> 0.02187 | I6: 10-K FY26 附註 10：面額 486、票面 4.50%–4.50%（取中點）、到期 2040–2040；到期日取區間中點 [Derived]
A7: 2011 票據 | B7: 無擔保 | C7: 2041-06 | D7: 0.053 | E7: 0.718 | F7: =D7*E7 -> 0.038054 | I7: 10-K FY26 附註 10：面額 718、票面 5.30%–5.30%（取中點）、到期 2041–2041；到期日取區間中點 [Derived]
A8: 2012 票據 | B8: 無擔保 | C8: 2042-06 | D8: 0.035 | E8: 0.454 | F8: =D8*E8 -> 0.01589 | I8: 10-K FY26 附註 10：面額 454、票面 3.50%–3.50%（取中點）、到期 2042–2042；到期日取區間中點 [Derived]
A9: 2013 美元票據 | B9: 無擔保 | C9: 2043-06 | D9: 0.04315 | E9: 0.314 | F9: =D9*E9 -> 0.0135491 | I9: 10-K FY26 附註 10：面額 314、票面 3.75%–4.88%（取中點）、到期 2043–2043；到期日取區間中點 [Derived]
A10: 2013 歐元票據 | B10: 無擔保 | C10: 2030-06 | D10: 0.0288 | E10: 2.63 | F10: =D10*E10 -> 0.075744 | I10: 10-K FY26 附註 10：面額 2,630、票面 2.63%–3.13%（取中點）、到期 2028–2033；到期日取區間中點 [Derived]
A11: 2015 票據 | B11: 無擔保 | C11: 2045-06 | D11: 0.04125 | E11: 4.555 | F11: =D11*E11 -> 0.18789375 | I11: 10-K FY26 附註 10：面額 4,555、票面 3.50%–4.75%（取中點）、到期 2035–2055；到期日取區間中點 [Derived]
A12: 2016 票據 | B12: 無擔保 | C12: 2041-06 | D12: 0.03175 | E12: 7.93 | F12: =D12*E12 -> 0.2517775 | I12: 10-K FY26 附註 10：面額 7,930、票面 2.40%–3.95%（取中點）、到期 2026–2056；到期日取區間中點 [Derived]
A13: 2017 票據 | B13: 無擔保 | C13: 2041-06 | D13: 0.039 | E13: 6.833 | F13: =D13*E13 -> 0.266487 | I13: 10-K FY26 附註 10：面額 6,833、票面 3.30%–4.50%（取中點）、到期 2026–2057；到期日取區間中點 [Derived]
A14: 2020 票據（交換） | B14: 無擔保 | C14: 2045-06 | D14: 0.02015 | E14: 10.111 | F14: =D14*E14 -> 0.20373665 | I14: 10-K FY26 附註 10：面額 10,111、票面 1.35%–2.68%（取中點）、到期 2030–2060；到期日取區間中點 [Derived]
A15: 2021 票據（交換） | B15: 無擔保 | C15: 2057-06 | D15: 0.0298 | E15: 8.185 | F15: =D15*E15 -> 0.243913 | I15: 10-K FY26 附註 10：面額 8,185、票面 2.92%–3.04%（取中點）、到期 2052–2062；到期日取區間中點 [Derived]
A16: 2023 票據（Activision 交換） | B16: 無擔保 | C16: 2038-06 | D16: 0.02925 | E16: 0.056 | F16: =D16*E16 -> 0.001638 | I16: 10-K FY26 附註 10：面額 56、票面 1.35%–4.50%（取中點）、到期 2026–2050；到期日取區間中點 [Derived]
A17: 2024 票據（Activision 交換） | B17: 無擔保 | C17: 2038-06 | D17: 0.02925 | E17: 3.344 | F17: =D17*E17 -> 0.097812 | I17: 10-K FY26 附註 10：面額 3,344、票面 1.35%–4.50%（取中點）、到期 2026–2050；到期日取區間中點 [Derived]
A18: 合計（6/30） | E18: =SUM(E5:E17) -> 46.136 | F18: =SUM(F5:F17) -> 1.445405 | I18: 應等於最新季報本金合計 46.136（company.json → latestQuarter.debtPrincipal）
A19: 加權有效利率 | D19: =F18/E18 -> 0.031329222 | I19: ＝年化利息 ÷ 本金（company.json → debt.instruments 的有效利率）
A21: 評價日後新發可轉債 | D21: 0 | E21: 0 | F21: =D21*E21 -> 0 | I21: company.json → debt.convertible（期後新發；不在五期還本表內，只計利息）
A23: 可轉債逐檔（若轉換法：有效轉換價 < 判斷價 → 視為轉股，不計利息與還本）
A24: 可轉債 | B24: 到期 | C24: 票息 | D24: 原始本金 | E24: 到期累積倍數 | F24: 轉換價 | G24: 到期所屬模型期 | H24: 強制轉換（1＝是） | I24: 備註
A25: （無可轉債，不適用） | B25: 2099-12 | C25: 0 | D25: 0 | E25: 1 | F25: 1 | G25: 5 | H25: 0 | I25: company.json → debt.convertibles 為空清單
I26: 到期所屬模型期：0＝首期 … 4＝末期、5＝模型期後（建置時依期末日推算）
A28: 可轉債（推導） | C28: 到期本金 | D28: 若轉換股數 | E28: 有效轉換價 | F28: 融資分類 | G28: 評價第一輪 | H28: 評價第二輪 | I28: 說明
A29: =A25 -> （無可轉債，不適用） | C29: =D25*E25 -> 0 | D29: =D25/F25 -> 0 | E29: =F25*E25 -> 1 | F29: =IF(OR(H25=1,E29<輸入與假設!$C$307),1,0) -> 1 | G29: =IF(OR(H25=1,E29<輸入與假設!$C$330),1,0) -> 1 | H29: =IF(OR(H25=1,E29<評價_DCF與目標價!$C$87),1,0) -> 1
A30: 合計 | C30: =SUM(C29:C29) -> 0 | D30: =SUM(D29:D29) -> 0 | I30: 分類 1＝轉股（若轉換法）、0＝債務。強制轉換者一律為 1。融資分類判斷價＝股權發行價；評價第一輪＝現價；第二輪＝MIN(現價, 第一輪加權目標價)
A32: 存量利息推導（本金依季報到期表遞減）
A33: 項目 | B33: 單位 | C33: FY27 | D33: FY28 | E33: FY29 | F33: FY30 | G33: FY31 | I33: 公式／來源說明
A34: 期初本金 | B34: US$bn | C34: =E18 -> 46.136 | D34: =C36 -> 36.886 | E34: =D36 -> 36.886 | F34: =E36 -> 34.885 | G34: =F36 -> 34.885 | I34: FY27 期初為 6/30 本金（模型期起點）
A35: 排程還本 | B35: US$bn | C35: =輸入與假設!C$325 -> 9.25 | D35: =輸入與假設!D$325 -> 0 | E35: =輸入與假設!E$325 -> 2.001 | F35: =輸入與假設!F$325 -> 0 | G35: =輸入與假設!G$325 -> 0.5 | I35: 季報到期表
A36: 期末本金 | B36: US$bn | C36: =C34-C35 -> 36.886 | D36: =D34-D35 -> 36.886 | E36: =E34-E35 -> 34.885 | F36: =F34-F35 -> 34.885 | G36: =G34-G35 -> 34.385
A37: 平均本金 | B37: US$bn | C37: =(C34+C36)/2 -> 41.511 | D37: =(D34+D36)/2 -> 36.886 | E37: =(E34+E36)/2 -> 35.8855 | F37: =(F34+F36)/2 -> 34.885 | G37: =(G34+G36)/2 -> 34.635
A38: 存量債務利息 | B38: US$bn | C38: =C37*資產負債_既有債務!$D$19*輸入與假設!C$34 -> 1.3005073 | D38: =D37*資產負債_既有債務!$D$19*輸入與假設!D$34 -> 1.1556097 | E38: =E37*資產負債_既有債務!$D$19*輸入與假設!E$34 -> 1.1242648 | F38: =F37*資產負債_既有債務!$D$19*輸入與假設!F$34 -> 1.0929199 | G38: =G37*資產負債_既有債務!$D$19*輸入與假設!G$34 -> 1.0850876 | I38: ＝平均本金×加權有效利率×期間長度。限制：假設利率組合不變；可轉債折價攤銷（非現金）不計
A39: 期後新發可轉債利息 | B39: US$bn | C39: =資產負債_既有債務!$F$21*輸入與假設!C$34 -> 0 | D39: =資產負債_既有債務!$F$21*輸入與假設!D$34 -> 0 | E39: =資產負債_既有債務!$F$21*輸入與假設!E$34 -> 0 | F39: =資產負債_既有債務!$F$21*輸入與假設!F$34 -> 0 | G39: =資產負債_既有債務!$F$21*輸入與假設!G$34 -> 0
A40: 可轉債到期還本（債務處理） | B40: US$bn | C40: =IF(輸入與假設!$C$296=1,SUMPRODUCT((1-資產負債_既有債務!$F$29:$F$29)*資產負債_既有債務!$C$29:$C$29*(資產負債_既有債務!$G$25:$G$25=0)),0) -> 0 | D40: =IF(輸入與假設!$C$296=1,SUMPRODUCT((1-資產負債_既有債務!$F$29:$F$29)*資產負債_既有債務!$C$29:$C$29*(資產負債_既有債務!$G$25:$G$25=1)),0) -> 0 | E40: =IF(輸入與假設!$C$296=1,SUMPRODUCT((1-資產負債_既有債務!$F$29:$F$29)*資產負債_既有債務!$C$29:$C$29*(資產負債_既有債務!$G$25:$G$25=2)),0) -> 0 | F40: =IF(輸入與假設!$C$296=1,SUMPRODUCT((1-資產負債_既有債務!$F$29:$F$29)*資產負債_既有債務!$C$29:$C$29*(資產負債_既有債務!$G$25:$G$25=3)),0) -> 0 | G40: =IF(輸入與假設!$C$296=1,SUMPRODUCT((1-資產負債_既有債務!$F$29:$F$29)*資產負債_既有債務!$C$29:$C$29*(資產負債_既有債務!$G$25:$G$25=4)),0) -> 0 | I40: 融資分類為債務的可轉債，到期當期以到期累積本金現金還本
A41: 可轉債期末餘額（債務處理） | B41: US$bn | C41: =IF(輸入與假設!$C$296=1,SUMPRODUCT((1-資產負債_既有債務!$F$29:$F$29)*資產負債_既有債務!$C$29:$C$29*(資產負債_既有債務!$G$25:$G$25>0)),SUMPRODUCT((1-資產負債_既有債務!$F$29:$F$29)*資產負債_既有債務!$C$29:$C$29)) -> 0 | D41: =IF(輸入與假設!$C$296=1,SUMPRODUCT((1-資產負債_既有債務!$F$29:$F$29)*資產負債_既有債務!$C$29:$C$29*(資產負債_既有債務!$G$25:$G$25>1)),SUMPRODUCT((1-資產負債_既有債務!$F$29:$F$29)*資產負債_既有債務!$C$29:$C$29)) -> 0 | E41: =IF(輸入與假設!$C$296=1,SUMPRODUCT((1-資產負債_既有債務!$F$29:$F$29)*資產負債_既有債務!$C$29:$C$29*(資產負債_既有債務!$G$25:$G$25>2)),SUMPRODUCT((1-資產負債_既有債務!$F$29:$F$29)*資產負債_既有債務!$C$29:$C$29)) -> 0 | F41: =IF(輸入與假設!$C$296=1,SUMPRODUCT((1-資產負債_既有債務!$F$29:$F$29)*資產負債_既有債務!$C$29:$C$29*(資產負債_既有債務!$G$25:$G$25>3)),SUMPRODUCT((1-資產負債_既有債務!$F$29:$F$29)*資產負債_既有債務!$C$29:$C$29)) -> 0 | G41: =IF(輸入與假設!$C$296=1,SUMPRODUCT((1-資產負債_既有債務!$F$29:$F$29)*資產負債_既有債務!$C$29:$C$29*(資產負債_既有債務!$G$25:$G$25>4)),SUMPRODUCT((1-資產負債_既有債務!$F$29:$F$29)*資產負債_既有債務!$C$29:$C$29)) -> 0 | I41: 到期累積本金；關閉攤還時維持全額
A42: 可轉債票息（債務處理） | B42: US$bn | C42: =IF(輸入與假設!$C$296=1,SUMPRODUCT((1-資產負債_既有債務!$F$29:$F$29)*資產負債_既有債務!$D$25:$D$25*資產負債_既有債務!$C$25:$C$25*((資產負債_既有債務!$G$25:$G$25>0)+0.5*(資產負債_既有債務!$G$25:$G$25=0))),SUMPRODUCT((1-資產負債_既有債務!$F$29:$F$29)*資產負債_既有債務!$D$25:$D$25*資產負債_既有債務!$C$25:$C$25))*輸入與假設!C$34 -> 0 | D42: =IF(輸入與假設!$C$296=1,SUMPRODUCT((1-資產負債_既有債務!$F$29:$F$29)*資產負債_既有債務!$D$25:$D$25*資產負債_既有債務!$C$25:$C$25*((資產負債_既有債務!$G$25:$G$25>1)+0.5*(資產負債_既有債務!$G$25:$G$25=1))),SUMPRODUCT((1-資產負債_既有債務!$F$29:$F$29)*資產負債_既有債務!$D$25:$D$25*資產負債_既有債務!$C$25:$C$25))*輸入與假設!D$34 -> 0 | E42: =IF(輸入與假設!$C$296=1,SUMPRODUCT((1-資產負債_既有債務!$F$29:$F$29)*資產負債_既有債務!$D$25:$D$25*資產負債_既有債務!$C$25:$C$25*((資產負債_既有債務!$G$25:$G$25>2)+0.5*(資產負債_既有債務!$G$25:$G$25=2))),SUMPRODUCT((1-資產負債_既有債務!$F$29:$F$29)*資產負債_既有債務!$D$25:$D$25*資產負債_既有債務!$C$25:$C$25))*輸入與假設!E$34 -> 0 | F42: =IF(輸入與假設!$C$296=1,SUMPRODUCT((1-資產負債_既有債務!$F$29:$F$29)*資產負債_既有債務!$D$25:$D$25*資產負債_既有債務!$C$25:$C$25*((資產負債_既有債務!$G$25:$G$25>3)+0.5*(資產負債_既有債務!$G$25:$G$25=3))),SUMPRODUCT((1-資產負債_既有債務!$F$29:$F$29)*資產負債_既有債務!$D$25:$D$25*資產負債_既有債務!$C$25:$C$25))*輸入與假設!F$34 -> 0 | G42: =IF(輸入與假設!$C$296=1,SUMPRODUCT((1-資產負債_既有債務!$F$29:$F$29)*資產負債_既有債務!$D$25:$D$25*資產負債_既有債務!$C$25:$C$25*((資產負債_既有債務!$G$25:$G$25>4)+0.5*(資產負債_既有債務!$G$25:$G$25=4))),SUMPRODUCT((1-資產負債_既有債務!$F$29:$F$29)*資產負債_既有債務!$D$25:$D$25*資產負債_既有債務!$C$25:$C$25))*輸入與假設!G$34 -> 0 | I42: ＝原始本金 × 票息 × 期間長度；到期當期計半期
A43: 首期新增借款利息校準 | B43: US$bn | C43: =0 -> 0 | D43: =0 -> 0 | E43: =0 -> 0 | F43: =0 -> 0 | G43: =0 -> 0 | I43: 讓首期模型利息對上公司季度利息指引的校準值（company.json → defaults.intCal）；無指引時為 0
A44: 存量利息合計（連回輸入頁） | B44: US$bn | C44: =C38+C39+C42+C43 -> 1.3005073 | D44: =D38+D39+D42+D43 -> 1.1556097 | E44: =E38+E39+E42+E43 -> 1.1242648 | F44: =F38+F39+F42+F43 -> 1.0929199 | G44: =G38+G39+G42+G43 -> 1.0850876 | I44: ＝存量債務利息＋期後新發可轉債利息＋可轉債票息＋首期校準

Sheet 資產負債_新債與新股
A1: 新債與新股（類資產負債表：現金、債務、股本、槓桿）
A2: 全部為連結公式。FY27 欄的現金自 2026-06-30 起算（模型期），與 HTML『資產與負債 → 新債與新股』同口徑
A4: 項目 | B4: 單位 | C4: FY27 | D4: FY28 | E4: FY29 | F4: FY30 | G4: FY31 | I4: 公式／來源說明
A5: 現金
A6: 期初現金 | B6: US$bn | C6: =輸入與假設!$C$291 -> 76.843 | D6: =各期收支!C56 -> 50 | E6: =各期收支!D56 -> 50 | F6: =各期收支!E56 -> 66.75901 | G6: =各期收支!F56 -> 84.639491 | I6: FY27＝6/30 現金（模型期起點）
A7: 營運收支淨額（含期後股權／可轉債，不含瀑布） | B7: US$bn | C7: =各期收支!C103-輸入與假設!$C$291 -> -45.791376 | D7: =各期收支!D103-各期收支!C103 -> 1.8180031 | E7: =各期收支!E103-各期收支!D103 -> 40.027293 | F7: =各期收支!F103-各期收支!E103 -> 41.148764 | G7: =各期收支!G103-各期收支!F103 -> -24.106359 | I7: ＝融資前累積現金的當期變動；負值即當期外部資金需求
A8: ＋ 瀑布：新債（額度＋資產層） | B8: US$bn | C8: =各期收支!C86 -> 19.945659 | D8: =各期收支!D86 -> 0 | E8: =各期收支!E86 -> 0 | F8: =各期收支!F86 -> 0 | G8: =各期收支!G86 -> 0
A9: ＋ 瀑布：可轉債 | B9: US$bn | C9: =各期收支!C89 -> 0 | D9: =各期收支!D89 -> 0 | E9: =各期收支!E89 -> 0 | F9: =各期收支!F89 -> 0 | G9: =各期收支!G89 -> 0
A10: ＋ 瀑布：高息債 | B10: US$bn | C10: =各期收支!C93 -> 0 | D10: =各期收支!D93 -> 0 | E10: =各期收支!E93 -> 0 | F10: =各期收支!F93 -> 0 | G10: =各期收支!G93 -> 0
A11: ＋ 瀑布：股權募資 | B11: US$bn | C11: =各期收支!C92 -> 0 | D11: =各期收支!D92 -> 0 | E11: =各期收支!E92 -> 0 | F11: =各期收支!F92 -> 0 | G11: =各期收支!G92 -> 0
A12: − 回購（瀑布第二步） | B12: US$bn | C12: =-各期收支!C76 -> 0 | D12: =-各期收支!D76 -> -0.8207201 | E12: =-各期收支!E76 -> -22.271 | F12: =-各期收支!F76 -> -22.271 | G12: =-各期收支!G76 -> -9.535849
A13: − 新融資利息（新債＋可轉債＋高息債） | B13: US$bn | C13: =-各期收支!C94 -> -0.99728296 | D13: =-各期收支!D94 -> -0.99728296 | E13: =-各期收支!E94 -> -0.99728296 | F13: =-各期收支!F94 -> -0.99728296 | G13: =-各期收支!G94 -> -0.99728296
A14: 期末現金 | B14: US$bn | C14: =SUM(C6:C13) -> 50 | D14: =SUM(D6:D13) -> 50 | E14: =SUM(E6:E13) -> 66.75901 | F14: =SUM(F6:F13) -> 84.639491 | G14: =SUM(G6:G13) -> 50 | I14: 應等於『各期收支』期末累積現金（見下列驗算）
A15: 驗算：與各期收支期末現金差異 | B15: US$bn | C15: =C14-各期收支!C56 -> 0 | D15: =D14-各期收支!D56 -> 0 | E15: =E14-各期收支!E56 -> 0 | F15: =F14-各期收支!F56 -> 0 | G15: =G14-各期收支!G56 -> 0 | I15: 應為 0
A16: 債務
A17: 既有債務期初（季報本金） | B17: US$bn | C17: =資產負債_既有債務!$E$18+SUMPRODUCT((1-資產負債_既有債務!$F$29:$F$29)*資產負債_既有債務!$C$29:$C$29) -> 46.136 | D17: =C19 -> 36.886 | E17: =D19 -> 36.886 | F17: =E19 -> 34.885 | G17: =F19 -> 34.885 | I17: FY27＝其他借款＋債務處理可轉債到期本金（轉股處理者不列）
A18: − 排程還本（模型期） | B18: US$bn | C18: =-IF(輸入與假設!$C$296=1,輸入與假設!C$325,0)-資產負債_既有債務!C40 -> -9.25 | D18: =-IF(輸入與假設!$C$296=1,輸入與假設!D$325,0)-資產負債_既有債務!D40 -> 0 | E18: =-IF(輸入與假設!$C$296=1,輸入與假設!E$325,0)-資產負債_既有債務!E40 -> -2.001 | F18: =-IF(輸入與假設!$C$296=1,輸入與假設!F$325,0)-資產負債_既有債務!F40 -> 0 | G18: =-IF(輸入與假設!$C$296=1,輸入與假設!G$325,0)-資產負債_既有債務!G40 -> -0.5
A19: 既有債務期末 | B19: US$bn | C19: =各期收支!C82-0 -> 36.886 | D19: =各期收支!D82-0 -> 36.886 | E19: =各期收支!E82-0 -> 34.885 | F19: =各期收支!F82-0 -> 34.885 | G19: =各期收支!G82-0 -> 34.385 | I19: ＝依到期表遞減（關閉攤還時維持期初）
A20: ＋ 期後新發可轉債 | B20: US$bn | C20: =0 -> 0 | D20: =0 -> 0 | E20: =0 -> 0 | F20: =0 -> 0 | G20: =0 -> 0
A21: ＋ 瀑布新債餘額 | B21: US$bn | C21: =各期收支!C98 -> 19.945659 | D21: =各期收支!D98 -> 19.945659 | E21: =各期收支!E98 -> 19.945659 | F21: =各期收支!F98 -> 19.945659 | G21: =各期收支!G98 -> 19.945659
A22: ＋ 瀑布可轉債餘額 | B22: US$bn | C22: =各期收支!C101 -> 0 | D22: =各期收支!D101 -> 0 | E22: =各期收支!E101 -> 0 | F22: =各期收支!F101 -> 0 | G22: =各期收支!G101 -> 0
A23: ＋ 高息債餘額 | B23: US$bn | C23: =各期收支!C100 -> 0 | D23: =各期收支!D100 -> 0 | E23: =各期收支!E100 -> 0 | F23: =各期收支!F100 -> 0 | G23: =各期收支!G100 -> 0
A24: 總債務 | B24: US$bn | C24: =SUM(C19:C23) -> 56.831659 | D24: =SUM(D19:D23) -> 56.831659 | E24: =SUM(E19:E23) -> 54.830659 | F24: =SUM(F19:F23) -> 54.830659 | G24: =SUM(G19:G23) -> 54.330659 | I24: 應等於『各期收支』期末總債務
A25: 淨負債（總債務 − 期末現金） | B25: US$bn | C25: =C24-C14 -> 6.8316593 | D25: =D24-D14 -> 6.8316593 | E25: =E24-E14 -> -11.928351 | F25: =F24-F14 -> -29.808832 | G25: =G24-G14 -> 4.3306593
A26: 股本
A27: 基礎股數（含 ATM 上限、SBC 稀釋） | B27: bn | C27: =損益!C23 -> 7.453 | D27: =損益!D23 -> 7.52753 | E27: =損益!E23 -> 7.6028053 | F27: =損益!F23 -> 7.6788334 | G27: =損益!G23 -> 7.7556217
A28: ＋ 本期新股 | B28: bn | C28: =各期收支!C96 -> 0 | D28: =各期收支!D96 -> 0 | E28: =各期收支!E96 -> 0 | F28: =各期收支!F96 -> 0 | G28: =各期收支!G96 -> 0
A29: 總股數（期末） | B29: bn | C29: =損益!C24 -> 7.453 | D29: =損益!D24 -> 7.5259808 | E29: =損益!E24 -> 7.5592163 | F29: =損益!F24 -> 7.5932045 | G29: =損益!G24 -> 7.6519926 | I29: ＝基礎股數＋累計新股
A30: 槓桿
A31: 期末 backlog | B31: US$bn | C31: =各期收支!C81 -> 107.50193 | D31: =各期收支!D81 -> 115.70977 | E31: =各期收支!E81 -> 93.386662 | F31: =各期收支!F81 -> 40.0462 | G31: =各期收支!G81 -> -44.498618
A32: 債務上限（債務／backlog × 期末 backlog） | B32: US$bn | C32: =各期收支!C83 -> 584.63603 | D32: =各期收支!D83 -> 690.23036 | E32: =各期收支!E83 -> 798.32389 | F32: =各期收支!F83 -> 906.92533 | G32: =各期收支!G83 -> 1067.1314
A33: 總債務 ÷ 期末 backlog | B33: x | C33: =C24/MAX(0.01,C31) -> 0.52865709 | D33: =D24/MAX(0.01,D31) -> 0.49115698 | E33: =E24/MAX(0.01,E31) -> 0.58713587 | F33: =F24/MAX(0.01,F31) -> 1.3691851 | G33: =G24/MAX(0.01,G31) -> 5433.0659 | I33: 高息債不受 backlog 上限約束
A34: 總債務 ÷ EBITDA（年化） | B34: x | C34: =C24/MAX(0.01,損益!C22/輸入與假設!C$34) -> 0.24405171 | D34: =D24/MAX(0.01,損益!D22/輸入與假設!D$34) -> 0.20132081 | E34: =E24/MAX(0.01,損益!E22/輸入與假設!E$34) -> 0.16476004 | F34: =F24/MAX(0.01,損益!F22/輸入與假設!F$34) -> 0.14355794 | G34: =G24/MAX(0.01,損益!G22/輸入與假設!G$34) -> 0.12684293 | I34: FY27 模型期 EBITDA 以模型期長度年化
A35: 租賃負債（期末） | B35: US$bn | C35: =各期收支!C63 -> 137.89992 | D35: =各期收支!D63 -> 185.21852 | E35: =各期收支!E63 -> 230.85174 | F35: =各期收支!F63 -> 273.51996 | G35: =各期收支!G63 -> 253.94318 | I35: 見『各期收支』租賃負債（期末剩餘租金現值，5.7%）
A36: EBITDAR（年化＝(EBITDA＋租金) ÷ 期間長度） | B36: US$bn | C36: =(損益!C22+各期收支!C16)/輸入與假設!C$34 -> 240.84531 | D36: =(損益!D22+各期收支!D16)/輸入與假設!D$34 -> 291.81629 | E36: =(損益!E22+各期收支!E16)/輸入與假設!E$34 -> 343.05854 | F36: =(損益!F22+各期收支!F16)/輸入與假設!F$34 -> 393.48176 | G36: =(損益!G22+各期收支!G16)/輸入與假設!G$34 -> 440.35821
A37: 調整後槓桿（(總債務＋租賃負債) ÷ EBITDAR） | B37: x | C37: =(C24+C35)/MAX(0.01,C36) -> 0.80853379 | D37: =(D24+D35)/MAX(0.01,D36) -> 0.8294608 | E37: =(E24+E35)/MAX(0.01,E36) -> 0.83275115 | F37: =(F24+F35)/MAX(0.01,F36) -> 0.83447482 | G37: =(G24+G35)/MAX(0.01,G36) -> 0.70005244 | I37: S&P 降評門檻 >4.5×（[Interested-party] 二手轉述）；S&P 自身口徑另含全部未起租承諾與無條件採購義務，較本列高（見報告）
A38: 距投資級上限的空間（上限 − 調整後槓桿） | B38: x | C38: =輸入與假設!$C$299-C37 -> 2.1914662 | D38: =輸入與假設!$C$299-D37 -> 2.1705392 | E38: =輸入與假設!$C$299-E37 -> 2.1672488 | F38: =輸入與假設!$C$299-F37 -> 2.1655252 | G38: =輸入與假設!$C$299-G37 -> 2.2999476 | I38: 負值＝超過上限：需股權或失去投資級

Sheet 資產負債_租賃承諾
A1: 租賃與承諾 — 季報（2026-06-30）原始揭露
A2: 本頁為硬編碼的申報數字（藍字），支出與資金頁的租金與還本列由此而來
A4: 在帳租賃到期表（未折現）
A5: 項目 | B5: 單位 | C5: 2026 下半 | D5: 2027 | E5: 2028 | F5: 2029 | G5: 2030 | H5: 其後
A6: 營業租賃付款 | B6: US$bn | C6: 6.082 | D6: 4.334 | E6: 3.146 | F6: 2.612 | G6: 2.316 | H6: 6.216
A7: 融資租賃付款 | B7: US$bn | C7: 7.121 | D7: 7.294 | E7: 6.668 | F7: 6.57 | G7: 6.543 | H7: 55.49
A8: 合計（＝支出頁「在帳現金租金」） | C8: =SUM(C6:C7) -> 13.203 | D8: =SUM(D6:D7) -> 11.628 | E8: =SUM(E6:E7) -> 9.814 | F8: =SUM(F6:F7) -> 9.182 | G8: =SUM(G6:G7) -> 8.859 | H8: =SUM(H6:H7) -> 61.706 | I8: 營業租賃負債現值 21.925、融資租賃 66.594；年報加權剩餘租期 12／14 年、折現率 5.7% [Verified]
A10: 債務本金到期表
A11: 項目 | B11: 單位 | C11: 2026 下半 | D11: 2027 | E11: 2028 | F11: 2029 | G11: 2030 | H11: 其後
A12: 本金（＝支出頁「排程還本」） | B12: US$bn | C12: 9.25 | D12: 0 | E12: 2.001 | F12: 0 | G12: 0.5 | H12: 34.385 | I12: 其他借款到期表（company.json → debt.amortization）；可轉債到期還本依融資分類另計，見『資產負債_既有債務』逐檔表
A13: 合計 | C13: =SUM(C12:H12) -> 46.136
A15: 表外與契約性承諾（未入表）
A16: 項目 | B16: 單位 | C16: 金額 | D16: 時程 | E16: 入表？ | F16: 模型位置
A17: 未起租租賃（未折現） | B17: US$bn | C17: 329.1 | D17: 季報揭露之已簽約未起租租賃 | E17: 否 | F17: 表外現金租金
A18: 單站按造價計租，上限 | B18: US$bn | C18: 0 | D18: 無此類揭露時為 0 | E18: 否 | F18: 表外現金租金
A19: 未動用信用額度 | B19: US$bn | C19: 0 | D19: company.json → defaults.facility（無已揭露的循環信用額度（不列入瀑布）） | E19: 否（來源） | F19: 瀑布：未動用額度
A20: 已揭露金額之承諾合計（未起租＋單站上限） | C20: =C17+C18 -> 329.1
A21: 模型表外租金五期合計 | C21: =SUM(各期收支!C15:G15) -> 68.5625
A22: 模型表外租金尾端（模型期後未付＝總額 − 五期） | C22: =MAX(0,輸入與假設!$C$19-C21) -> 260.5375
A23: 模型路徑合計 ÷ 已承諾（≥0.8 為合理） | C23: =(C21+C22)/C20 -> 1 | I23: 起租排程依季報附註（起租期間與期限）平均分攤；五期＋尾端＝未起租總額

Sheet 損益
A1: 損益（類損益表）— 與資金模型同一組收入
A2: 算力收入、Cash CapEx、利息皆由前面分頁連結而來；改資金假設，此頁會跟著動
A4: 項目 | B4: 單位 | C4: FY27 | D4: FY28 | E4: FY29 | F4: FY30 | G4: FY31 | I4: 公式／來源說明
A5: 損益表
A6: 算力收入 | B6: US$bn | C6: =運營_產能與收入!C26 -> 53.750967 | D6: =運營_產能與收入!D26 -> 84.730366 | E6: =運營_產能與收入!E26 -> 115.934 | F6: =運營_產能與收入!F26 -> 147.23076 | G6: =運營_產能與收入!G26 -> 178.57374 | I6: ＝RPO 轉換＋新簽約
A7: 非算力服務 | B7: US$bn | C7: =輸入與假設!C$43 -> 0 | D7: =輸入與假設!D$43 -> 0 | E7: =輸入與假設!E$43 -> 0 | F7: =輸入與假設!F$43 -> 0 | G7: =輸入與假設!G$43 -> 0
A8: 非 AI 事業 | B8: US$bn | C8: =輸入與假設!C$204 -> 343.69462 | D8: =輸入與假設!D$204 -> 386.69397 | E8: =輸入與假設!E$204 -> 429.60371 | F8: =輸入與假設!F$204 -> 470.09 | G8: =輸入與假設!G$204 -> 505.72131 | I8: 非 AI 事業各線合計（B2）
A9: 總營收 | B9: US$bn | C9: =C6+C7+C8 -> 397.44559 | D9: =D6+D7+D8 -> 471.42433 | E9: =E6+E7+E8 -> 545.53771 | F9: =F6+F7+F8 -> 617.32077 | G9: =G6+G7+G8 -> 684.29505
A10: EBITDA 率 | B10: % | C10: =輸入與假設!C$214 -> 0.79787831 | D10: =輸入與假設!D$214 -> 0.80029644 | E10: =輸入與假設!E$214 -> 0.80156247 | F10: =輸入與假設!F$214 -> 0.80233765 | G10: =輸入與假設!G$214 -> 0.80286109
A11: 延誤罰則（服務抵減，營業費用） | B11: US$bn | C11: =運營_產能與收入!C62 -> 0 | D11: =運營_產能與收入!D62 -> 0 | E11: =運營_產能與收入!E62 -> 0 | F11: =運營_產能與收入!F62 -> 0 | G11: =運營_產能與收入!G62 -> 0 | I11: 建設延誤期間應計費而未計費營收 × 罰則比例（預設 0；v0.2）
A12: 營業利益（EBIT） | B12: US$bn | C12: =(C6+C7)*輸入與假設!C$214+輸入與假設!C$56+輸入與假設!C$205-輸入與假設!C$206-C11-輸入與假設!C$288 -> 179.6868 | D12: =(D6+D7)*輸入與假設!D$214+輸入與假設!D$56+輸入與假設!D$205-輸入與假設!D$206-D11-輸入與假設!D$288 -> 200.01094 | E12: =(E6+E7)*輸入與假設!E$214+輸入與假設!E$56+輸入與假設!E$205-輸入與假設!E$206-E11-輸入與假設!E$288 -> 220.36434 | F12: =(F6+F7)*輸入與假設!F$214+輸入與假設!F$56+輸入與假設!F$205-輸入與假設!F$206-F11-輸入與假設!F$288 -> 238.81976 | G12: =(G6+G7)*輸入與假設!G$214+輸入與假設!G$56+輸入與假設!G$205-輸入與假設!G$206-G11-輸入與假設!G$288 -> 254.03743 | I12: ＝(算力＋服務營收)×EBITDA 率＋其他事業 EBITDA＋非 AI 事業 EBITDA − 非 AI 事業其他攤銷 − 延誤罰則 − 車隊 D&A
A13: 利息（含瀑布新債） | B13: US$bn | C13: =各期收支!C21 -> 2.2977903 | D13: =各期收支!D21 -> 2.1528927 | E13: =各期收支!E21 -> 2.1215478 | F13: =各期收支!F21 -> 2.0902029 | G13: =各期收支!G21 -> 2.0823706
A14: 預付財務組成利息（非現金） | B14: US$bn | C14: =各期收支!C10 -> 0 | D14: =各期收支!D10 -> 0 | E14: =各期收支!E10 -> 0 | F14: =各期收支!F10 -> 0 | G14: =各期收支!G10 -> 0 | I14: 客戶預付的重大財務組成：合約負債以隱含利率累積的利息（v0.1b）
A15: 稅前損益 | B15: US$bn | C15: =C12-C13-C14 -> 177.38901 | D15: =D12-D13-D14 -> 197.85805 | E15: =E12-E13-E14 -> 218.2428 | F15: =F12-F13-F14 -> 236.72956 | G15: =G12-G13-G14 -> 251.95506
A16: NOL 期初餘額 | B16: US$bn | C16: =輸入與假設!$C$352 -> 0 | D16: =C18 -> 0 | E16: =D18 -> 0 | F16: =E18 -> 0 | G16: =F18 -> 0 | I16: 6/30 累積虧損約 0.0
A17: 本期動用 NOL | B17: US$bn | C17: =MIN(C16,MAX(0,C15)*輸入與假設!$C$353) -> 0 | D17: =MIN(D16,MAX(0,D15)*輸入與假設!$C$353) -> 0 | E17: =MIN(E16,MAX(0,E15)*輸入與假設!$C$353) -> 0 | F17: =MIN(F16,MAX(0,F15)*輸入與假設!$C$353) -> 0 | G17: =MIN(G16,MAX(0,G15)*輸入與假設!$C$353) -> 0 | I17: 美國規定：抵扣上限為應稅所得 80%
A18: NOL 期末餘額 | B18: US$bn | C18: =C16-C17+MAX(0,-C15) -> 0 | D18: =D16-D17+MAX(0,-D15) -> 0 | E18: =E16-E17+MAX(0,-E15) -> 0 | F18: =F16-F17+MAX(0,-F15) -> 0 | G18: =G16-G17+MAX(0,-G15) -> 0
A19: 所得稅 | B19: US$bn | C19: =MAX(0,C15-C17)*輸入與假設!$C$339 -> 35.477802 | D19: =MAX(0,D15-D17)*輸入與假設!$C$339 -> 39.57161 | E19: =MAX(0,E15-E17)*輸入與假設!$C$339 -> 43.648559 | F19: =MAX(0,F15-F17)*輸入與假設!$C$339 -> 47.345912 | G19: =MAX(0,G15-G17)*輸入與假設!$C$339 -> 50.391012 | I19: 虧損年不認列稅盾（與公司評價備抵一致）
A20: 淨利 | B20: US$bn | C20: =C15-C19 -> 141.91121 | D20: =D15-D19 -> 158.28644 | E20: =E15-E19 -> 174.59424 | F20: =F15-F19 -> 189.38365 | G20: =G15-G19 -> 201.56405
A21: D&A | B21: US$bn | C21: =輸入與假設!C$288+輸入與假設!C$206 -> 53.180482 | D21: =輸入與假設!D$288+輸入與假設!D$206 -> 82.283068 | E21: =輸入與假設!E$288+輸入與假設!E$206 -> 112.42667 | F21: =輸入與假設!F$288+輸入與假設!F$206 -> 143.12122 | G21: =輸入與假設!G$288+輸入與假設!G$206 -> 174.29278 | I21: 車隊折舊＋非 AI 事業其他攤銷，見輸入頁
A22: EBITDA | B22: US$bn | C22: =C12+C21 -> 232.86728 | D22: =D12+D21 -> 282.29401 | E22: =E12+E21 -> 332.79101 | F22: =F12+F21 -> 381.94098 | G22: =G12+G21 -> 428.33021
A23: 基礎股數（每年 +SBC 稀釋） | B23: bn | C23: =評價_DCF與目標價!$C$90 -> 7.453 | D23: =C23*(1+輸入與假設!$C$398) -> 7.52753 | E23: =D23*(1+輸入與假設!$C$398) -> 7.6028053 | F23: =E23*(1+輸入與假設!$C$398) -> 7.6788334 | G23: =F23*(1+輸入與假設!$C$398) -> 7.7556217 | I23: FY27＝評價股數（含價內可轉債轉股，見『評價_DCF與目標價』可轉債區）；之後每年 ×(1＋股數年增)
A24: 股數（含瀑布新股） | B24: bn | C24: =C23+各期收支!C97 -> 7.453 | D24: =D23+各期收支!D97 -> 7.5259808 | E24: =E23+各期收支!E97 -> 7.5592163 | F24: =F23+各期收支!F97 -> 7.5932045 | G24: =G23+各期收支!G97 -> 7.6519926 | I24: ＝基礎股數＋累計瀑布新股
A25: 每股盈餘（EPS，模型期） | B25: US$ | C25: =C20/C24 -> 19.040817 | D25: =D20/D24 -> 21.032002 | E25: =E20/E24 -> 23.09687 | F25: =F20/F24 -> 24.941202 | G25: =G20/G24 -> 26.341381 | I25: FY27 欄只含全年；全年口徑見下方
A27: 損益表（全年口徑；FY27＝全年模型；與 HTML 損益簡表一致）
A28: 年初至今 實際營收（已實現） | B28: US$bn | C28: =輸入與假設!$C$439 -> 0 | D28: =0 -> 0 | E28: =0 -> 0 | F28: =0 -> 0 | G28: =0 -> 0
A29: 全年總營收 | B29: US$bn | C29: =C28+C9 -> 397.44559 | D29: =D28+D9 -> 471.42433 | E29: =E28+E9 -> 545.53771 | F29: =F28+F9 -> 617.32077 | G29: =G28+G9 -> 684.29505 | I29: FY27 可對照指引 未給全年營收指引
A30: 營收 YoY | B30: % | C30: =C29/331.839-1 -> 0.19770608 | D30: =D29/C29-1 -> 0.18613553 | E30: =E29/D29-1 -> 0.15721161 | F30: =F29/E29-1 -> 0.13158221 | G30: =G29/F29-1 -> 0.10849186 | I30: FY26 實際 331.839
A31: 全年 GAAP 營業利益 | B31: US$bn | C31: =輸入與假設!$C$440+C12 -> 179.6868 | D31: =D12 -> 200.01094 | E31: =E12 -> 220.36434 | F31: =F12 -> 238.81976 | G31: =G12 -> 254.03743
A32: 營利率 | B32: % | C32: =C31/C29 -> 0.45210415 | D32: =D31/D29 -> 0.42426946 | E32: =E31/E29 -> 0.40393971 | F32: =F31/F29 -> 0.38686494 | G32: =G31/G29 -> 0.37123962
A33: 全年 D&A | B33: US$bn | C33: =輸入與假設!$C$443+C21 -> 53.180482 | D33: =D21 -> 82.283068 | E33: =E21 -> 112.42667 | F33: =F21 -> 143.12122 | G33: =G21 -> 174.29278 | I33: 年初至今 實際 0.000
A34: 全年 EBITDA | B34: US$bn | C34: =C31+C33 -> 232.86728 | D34: =D31+D33 -> 282.29401 | E34: =E31+E33 -> 332.79101 | F34: =F31+F33 -> 381.94098 | G34: =G31+G33 -> 428.33021
A35: 全年利息（含瀑布新債） | B35: US$bn | C35: =輸入與假設!$C$437+C13 -> 2.2977903 | D35: =D13 -> 2.1528927 | E35: =E13 -> 2.1215478 | F35: =F13 -> 2.0902029 | G35: =G13 -> 2.0823706 | I35: FY28 起瀑布新債利息與新股同時影響 EPS
A36: 全年淨利 | B36: US$bn | C36: =輸入與假設!$C$441+C20 -> 141.91121 | D36: =D20 -> 158.28644 | E36: =E20 -> 174.59424 | F36: =F20 -> 189.38365 | G36: =G20 -> 201.56405
A37: 淨利率 | B37: % | C37: =C36/C29 -> 0.35705821 | D37: =D36/D29 -> 0.33576214 | E37: =E36/E29 -> 0.32004064 | F37: =F36/F29 -> 0.30678321 | G37: =G36/G29 -> 0.29455722
A38: 全年 GAAP EPS | B38: US$ | C38: =輸入與假設!$C$445+C20/C24 -> 19.040817 | D38: =D20/D24 -> 21.032002 | E38: =E20/E24 -> 23.09687 | F38: =F20/F24 -> 24.941202 | G38: =G20/G24 -> 26.341381 | I38: FY27＝年初至今 實際 EPS 0.00＋全年淨利÷股數
A39: 全年 EPS（加回 SBC） | B39: US$ | C39: =輸入與假設!$C$446+(C20+輸入與假設!$C$399*輸入與假設!C$34)/C24 -> 20.705247 | D39: =(D20+輸入與假設!$C$399*輸入與假設!D$34)/D24 -> 22.680292 | E39: =(E20+輸入與假設!$C$399*輸入與假設!E$34)/E24 -> 24.737913 | F39: =(F20+輸入與假設!$C$399*輸入與假設!F$34)/F24 -> 26.5749 | G39: =(G20+輸入與假設!$C$399*輸入與假設!G$34)/G24 -> 27.962527 | I39: ＝(淨利＋SBC)÷股數；NOL 狀態無現金稅，SBC 全額加回

Sheet 評價_DCF與目標價
A1: 評價 — DCF、EV/EBITDA、加權目標價
A2: 營收、營業利益、D&A、EBITDA、股數引用『損益』頁；Cash CapEx 與融資引用『各期收支』頁
A4: 項目 | B4: 單位 | C4: FY27 | D4: FY28 | E4: FY29 | F4: FY30 | G4: FY31 | I4: 公式／來源說明
A5: DCF（無槓桿自由現金流；起點為 2026-06-30）
A6: 現金 CapEx（2026-06-30 之後） | B6: US$bn | C6: =輸入與假設!C$287-各期收支!C8 -> 204.20173 | D6: =輸入與假設!D$287-各期收支!D8 -> 216.20736 | E6: =輸入與假設!E$287-各期收支!E8 -> 221.96544 | F6: =輸入與假設!F$287-各期收支!F8 -> 267.23064 | G6: =輸入與假設!G$287-各期收支!G8 -> 374.66162 | I6: DCF 起點為 6/30，故 FY27 欄只含 全年 的建置支出，不含 年初至今 已發生的 0.0
A7: 比較基期營收 | B7: US$bn | C7: =331.839 -> 331.839 | D7: =0+損益!C9 -> 397.44559 | E7: =損益!D9 -> 471.42433 | F7: =損益!E9 -> 545.53771 | G7: =損益!F9 -> 617.32077 | I7: FY26 實際 331.839；FY28 基期＝年初至今 實際 0.0＋FY27 模型期營收
A8: 預付認列（非現金營收，扣除） | B8: US$bn | C8: =各期收支!C11 -> 0 | D8: =各期收支!D11 -> 0 | E8: =各期收支!E11 -> 0 | F8: =各期收支!F11 -> 0 | G8: =各期收支!G11 -> 0 | I8: 營收中由合約負債轉入的部分已在預付時收現（預付流入已自現金 CapEx 抵減），UFCF 扣除以免重複（v0.1b）
A9: 營運資金變動 | B9: US$bn | C9: =IF(ISBLANK(輸入與假設!$C$58),輸入與假設!$C$354*MAX(0,損益!C9-C7),-輸入與假設!$C$58) -> 4.895 | D9: =輸入與假設!$C$354*MAX(0,損益!D9-D7) -> 0 | E9: =輸入與假設!$C$354*MAX(0,損益!E9-E7) -> 0 | F9: =輸入與假設!$C$354*MAX(0,損益!F9-F7) -> 0 | G9: =輸入與假設!$C$354*MAX(0,損益!G9-G7) -> 0 | I9: FY27＝−上年同期實際（輸入非空白時；MAG v0.1b r2 C14）；之後＝營收增量的 0%
A10: 無槓桿 NOL 期初 | B10: US$bn | C10: =輸入與假設!$C$352 -> 0 | D10: =C12 -> 0 | E10: =D12 -> 0 | F10: =E12 -> 0 | G10: =F12 -> 0 | I10: DCF 用無槓桿稅（利息不可抵稅，否則稅盾被計兩次：一次在 UFCF、一次在 WACC）
A11: 本期動用（無槓桿） | B11: US$bn | C11: =MIN(C10,MAX(0,損益!C12)*輸入與假設!$C$353) -> 0 | D11: =MIN(D10,MAX(0,損益!D12)*輸入與假設!$C$353) -> 0 | E11: =MIN(E10,MAX(0,損益!E12)*輸入與假設!$C$353) -> 0 | F11: =MIN(F10,MAX(0,損益!F12)*輸入與假設!$C$353) -> 0 | G11: =MIN(G10,MAX(0,損益!G12)*輸入與假設!$C$353) -> 0
A12: 無槓桿 NOL 期末 | B12: US$bn | C12: =C10-C11+MAX(0,-損益!C12) -> 0 | D12: =D10-D11+MAX(0,-損益!D12) -> 0 | E12: =E10-E11+MAX(0,-損益!E12) -> 0 | F12: =F10-F11+MAX(0,-損益!F12) -> 0 | G12: =G10-G11+MAX(0,-損益!G12) -> 0
A13: 無槓桿所得稅（DCF 用） | B13: US$bn | C13: =MAX(0,損益!C12-C11)*輸入與假設!$C$339 -> 35.93736 | D13: =MAX(0,損益!D12-D11)*輸入與假設!$C$339 -> 40.002189 | E13: =MAX(0,損益!E12-E11)*輸入與假設!$C$339 -> 44.072869 | F13: =MAX(0,損益!F12-F11)*輸入與假設!$C$339 -> 47.763953 | G13: =MAX(0,損益!G12-G11)*輸入與假設!$C$339 -> 50.807486 | I13: 與損益表的所得稅不同：此處不扣利息，數字較高，這是 DCF 的正確口徑
A14: UFCF | B14: US$bn | C14: =損益!C12-C13+損益!C21-輸入與假設!C$206-C6-C9-C8 -> -12.166808 | D14: =損益!D12-D13+損益!D21-輸入與假設!D$206-D6-D9-D8 -> 26.084463 | E14: =損益!E12-E13+損益!E21-輸入與假設!E$206-E6-E9-E8 -> 66.7527 | F14: =損益!F12-F13+損益!F21-輸入與假設!F$206-F6-F9-F8 -> 66.946386 | G14: =損益!G12-G13+損益!G21-輸入與假設!G$206-G6-G9-G8 -> 2.8610988 | I14: ＝EBIT−無槓桿稅＋D&A−現金 CapEx（已扣客戶預付）−營運資金−預付認列。建置期全為負是正常的
A15: 折現期數 | B15: 年 | C15: =輸入與假設!$C$416 -> 1 | D15: =輸入與假設!$D$416 -> 2 | E15: =輸入與假設!$E$416 -> 3 | F15: =輸入與假設!$F$416 -> 4 | G15: =輸入與假設!$G$416 -> 5 | I15: 自 2026-06-30 起算；FY27 模型期（全年）的現金流平均落在 1 年
A16: 折現因子 | C16: =1/(1+輸入與假設!$C$349)^C15 -> 0.90174612 | D16: =1/(1+輸入與假設!$C$349)^D15 -> 0.81314606 | E16: =1/(1+輸入與假設!$C$349)^E15 -> 0.73325131 | F16: =1/(1+輸入與假設!$C$349)^F15 -> 0.66120652 | G16: =1/(1+輸入與假設!$C$349)^G15 -> 0.59624042
A17: UFCF 現值 | B17: US$bn | C17: =C14*C16 -> -10.971372 | D17: =D14*D16 -> 21.210479 | E17: =E14*E16 -> 48.946504 | F17: =F14*F16 -> 44.265387 | G17: =G14*G16 -> 1.7059028
A19: 五期 UFCF 現值合計 | C19: =SUM(C17:G17) -> 105.1569 | I19: 建置期現金流現值
A20: 終值基準 FCF（FY31 UFCF，含汰換 CapEx） | C20: =G14+輸入與假設!G263*(1-各期收支!G7) -> 234.36664 | I20: v0.1c：終值基準＝末期 UFCF（含穩態汰換 CapEx，已扣客戶預付覆蓋）＋加回末期成長型 CapEx（扣預付後；成長由 g 表達，預設情境為 0）；GPU 不是永續資產，終值年須持續再投資
A21: 終值（Gordon） | C21: =IF(C30=1,0,C20*(1+輸入與假設!$C$350)/(輸入與假設!$C$349-輸入與假設!$C$350)) -> 3057.2305 | I21: ＝常態化 FCF×(1+g)÷(WACC−g)
A22: 終值現值 | C22: =C21*G16 -> 1822.8444
A23: 企業價值 EV | C23: =C19+C22 -> 1928.0013
A24: 減：淨負債 | C24: =-評價_DCF與目標價!$C$91 -> 201.107 | I24: ＝評價淨負債（不含可轉債的淨負債＋債務處理可轉債到期本金＋調整項；見下方可轉債區）
A25: 股權價值 | C25: =C23+C24 -> 2129.1083
A26: DCF 每股 | C26: =IF(C30=1,0,IF(輸入與假設!$C$401=2,C32,C31)) -> 284.05468 | I26: 採用值：失效時為 0 且權重歸零；否則依「DCF 下限方式」取 0 截斷或選擇權
A27: 終值占 EV 比重 | C27: =C22/C23 -> 0.94545807 | I27: ="超過 "&IF(ROUND(ABS(輸入與假設!$C$425)*100,4)=INT(ROUND(ABS(輸入與假設!$C$425)*100,4)),TEXT(ROUND(ABS(輸入與假設!$C$425)*100,4),"0"),TEXT(ROUND(ABS(輸入與假設!$C$425)*100,4),"0.0"))&"%"&" 表示結論由終值假設決定，不由現金流決定" -> 超過 85% 表示結論由終值假設決定，不由現金流決定
A28: 新股募得現金（現值） | C28: =(各期收支!C92-各期收支!C76)/(1+輸入與假設!$C$349)^輸入與假設!$C$417+(各期收支!D92-各期收支!D76)/(1+輸入與假設!$C$349)^輸入與假設!$D$417+(各期收支!E92-各期收支!E76)/(1+輸入與假設!$C$349)^輸入與假設!$E$417+(各期收支!F92-各期收支!F76)/(1+輸入與假設!$C$349)^輸入與假設!$F$417+(各期收支!G92-各期收支!G76)/(1+輸入與假設!$C$349)^輸入與假設!$G$417 -> -41.485063 | I28: 期初到位，折現期數 0／0.5／1.5／2.5／3.5 年；MAG v0.1b：扣瀑布回購現金（淨股權）
A29: 融資後股數（含瀑布新股） | C29: =評價_DCF與目標價!$C$90+各期收支!G97 -> 7.3493709
A30: DCF 失效？（WACC ≤ g 或常態化 FCF ≤ 0） | C30: =IF(OR(輸入與假設!$C$349<=輸入與假設!$C$350,C20<=0),1,0) -> 0 | I30: 1＝失效：DCF 權重歸零、EV/EBITDA 100%。股權為負不算失效
A31: DCF 每股：0 截斷 | C31: =MAX(0,(C25+C28)/C29) -> 284.05468
A32: DCF 每股：選擇權（Merton） | C32: =IF((C23+C28)<=0,0,IF(評價_DCF與目標價!$C$91<=0,(C23+C28),(C23+C28)*NORMSDIST(C33)-評價_DCF與目標價!$C$91*EXP(-輸入與假設!$C$340*輸入與假設!$C$403)*NORMSDIST(C34))/C29) -> 256.69084 | I32: Black-Scholes：S＝企業價值＋新股現值、K＝淨負債
A33: d1 | C33: =IF(OR((C23+C28)<=0,評價_DCF與目標價!$C$91<=0),0,(LN((C23+C28)/評價_DCF與目標價!$C$91)+(輸入與假設!$C$340+輸入與假設!$C$402^2/2)*輸入與假設!$C$403)/(輸入與假設!$C$402*SQRT(輸入與假設!$C$403))) -> 0
A34: d2 | C34: =C33-輸入與假設!$C$402*SQRT(輸入與假設!$C$403) -> -1.118034
A36: 倍數法（錨定年度，預設 FY29；折回 2027-06-30）
A37: 錨定年度 | C37: =CHOOSE(輸入與假設!$C$393,"FY28","FY29","FY30","FY31") -> FY29 | I37: 輸入與假設 F 區可改
A38: 錨定年度 EBITDA | C38: =INDEX(損益!$D$22:$G$22,1,輸入與假設!$C$393) -> 332.79101
A39: 錨定年度企業價值（倍數 × EBITDA） | C39: =C45*輸入與假設!$C$355+C44*輸入與假設!$C$392 -> 3397.5917 | I39: 分部加總：AI 雲端 EBITDA × EV/EBITDA 倍數＋非 AI 事業 EBITDA × 非 AI 事業倍數（下方兩列）
A40: 錨定年度末淨負債（總債務 − 現金） | C40: =INDEX(各期收支!$D$102:$G$102,1,輸入與假設!$C$393)-INDEX(各期收支!$D$56:$G$56,1,輸入與假設!$C$393)+評價_DCF與目標價!$C$92 -> -182.32835 | I40: 含瀑布新債；加可轉債分類調整與淨負債調整項（見下方可轉債區）
A41: 錨定年度末股數（含瀑布新股） | C41: =INDEX(損益!$D$24:$G$24,1,輸入與假設!$C$393) -> 7.5592163 | I41: 損益股數：SBC 逐年稀釋＋瀑布新股
A42: 折回 2027-06-30 的折現因子 | C42: =1/(1+輸入與假設!$C$349)^(輸入與假設!$C$393-輸入與假設!$C$413) -> 0.81314606 | I42: 以 WACC 折現 [Assumed]
A43: EV/EBITDA 每股（融資後） | C43: =MAX(0,(C39-C40)/C41)*C42 -> 385.09255 | I43: 以 0 為下限
A44: 錨定年度非 AI 事業 EBITDA | C44: =INDEX(輸入與假設!$D$205:$G$205,1,輸入與假設!$C$393) -> 251.98267 | I44: × 非 AI 事業 EV/EBITDA 倍數（同業 NTM 中位數）
A45: 錨定年度 AI 雲端 EBITDA（算力＋服務＋其他） | C45: =C38-C44 -> 80.808341 | I45: ＝錨定年度 EBITDA − 非 AI 事業；× EV/EBITDA 倍數
A47: 加權目標價
A48: DCF 每股（推到目標價時點） | C48: =C26*(1+輸入與假設!$C$349)^輸入與假設!$C$409 -> 315.00516 | I48: ＝DCF 每股 ×（1＋WACC）^（評價日至目標價時點的年數）
A49: DCF 每股 × 有效權重 | C49: =C48*IF(C30=1,0,輸入與假設!$C$394) -> 141.75232
A50: EV/EBITDA（融資後）× 有效權重 | C50: =C43*IF(C30=1,1,1-輸入與假設!$C$394) -> 211.8009
A51: 加權目標價 | C51: =SUM(C49:C50) -> 353.55323 | I51: 期前融資瀑布：缺口先由額度與資產層新債支應，殘差以股權募足；估值不再扣缺口本金
A52: 現價 | C52: =輸入與假設!$C$330 -> 529.76
A53: 潛在空間 | C53: =C51/C52-1 -> -0.33261623
A55: 讀法 2｜自用 AI 價值中性（自用 MW 以 k＝1 計影子收入進評價；讀法 1＝影子收入不進評價，主值不變）
A56: 讀法 2｜自用 AI 影子 EBITDA（k＝1） | B56: US$bn | C56: =運營_產能與收入!C26*(1/輸入與假設!$C$66-(1-輸入與假設!C$214))*(1/輸入與假設!$C$227-1) -> 26.562815 | D56: =運營_產能與收入!D26*(1/輸入與假設!$C$66-(1-輸入與假設!D$214))*(1/輸入與假設!$C$227-1) -> 42.008901 | E56: =運營_產能與收入!E26*(1/輸入與假設!$C$66-(1-輸入與假設!E$214))*(1/輸入與假設!$C$227-1) -> 57.577359 | F56: =運營_產能與收入!F26*(1/輸入與假設!$C$66-(1-輸入與假設!F$214))*(1/輸入與假設!$C$227-1) -> 73.196646 | G56: =運營_產能與收入!G26*(1/輸入與假設!$C$66-(1-輸入與假設!G$214))*(1/輸入與假設!$C$227-1) -> 88.841306 | I56: ＝對外 AI 營收 ÷ k ×(1 ÷ 對外比例 − 1) − 同口徑營運成本：自用 AI 剛好回收 Tokenomics 持有成本（不創造也不毀損價值）
A57: 讀法 2｜EBIT | B57: US$bn | C57: =損益!C12+C56 -> 206.24962 | D57: =損益!D12+D56 -> 242.01985 | E57: =損益!E12+E56 -> 277.9417 | F57: =損益!F12+F56 -> 312.01641 | G57: =損益!G12+G56 -> 342.87874
A58: 讀法 2｜無槓桿 NOL 期初 | B58: US$bn | C58: =輸入與假設!$C$352 -> 0 | D58: =C60 -> 0 | E58: =D60 -> 0 | F58: =E60 -> 0 | G58: =F60 -> 0
A59: 讀法 2｜本期動用（無槓桿） | B59: US$bn | C59: =MIN(C58,MAX(0,C57)*輸入與假設!$C$353) -> 0 | D59: =MIN(D58,MAX(0,D57)*輸入與假設!$C$353) -> 0 | E59: =MIN(E58,MAX(0,E57)*輸入與假設!$C$353) -> 0 | F59: =MIN(F58,MAX(0,F57)*輸入與假設!$C$353) -> 0 | G59: =MIN(G58,MAX(0,G57)*輸入與假設!$C$353) -> 0
A60: 讀法 2｜無槓桿 NOL 期末 | B60: US$bn | C60: =C58-C59+MAX(0,-C57) -> 0 | D60: =D58-D59+MAX(0,-D57) -> 0 | E60: =E58-E59+MAX(0,-E57) -> 0 | F60: =F58-F59+MAX(0,-F57) -> 0 | G60: =G58-G59+MAX(0,-G57) -> 0
A61: 讀法 2｜無槓桿所得稅 | B61: US$bn | C61: =MAX(0,C57-C59)*輸入與假設!$C$339 -> 41.249923 | D61: =MAX(0,D57-D59)*輸入與假設!$C$339 -> 48.403969 | E61: =MAX(0,E57-E59)*輸入與假設!$C$339 -> 55.588341 | F61: =MAX(0,F57-F59)*輸入與假設!$C$339 -> 62.403282 | G61: =MAX(0,G57-G59)*輸入與假設!$C$339 -> 68.575748
A62: 讀法 2｜UFCF | B62: US$bn | C62: =C14+C56-(C61-C13) -> 9.0834446 | D62: =D14+D56-(D61-D13) -> 59.691584 | E62: =E14+E56-(E61-E13) -> 112.81459 | F62: =F14+F56-(F61-F13) -> 125.5037 | G62: =G14+G56-(G61-G13) -> 73.934144 | I62: ＝讀法 1 UFCF＋影子 EBITDA − 稅差
A63: 讀法 2｜UFCF 現值 | B63: US$bn | C63: =C62*C16 -> 8.1909609 | D63: =D62*D16 -> 48.537977 | E63: =E62*E16 -> 82.721444 | F63: =F62*F16 -> 82.983867 | G63: =G62*G16 -> 44.082524
A64: 讀法 2｜五期 UFCF 現值合計 | C64: =SUM(C63:G63) -> 266.51677
A65: 讀法 2｜終值基準 FCF | C65: =C20-G14+G62 -> 305.43969 | I65: ＝讀法 1 終值基準＋末期影子現金流差
A66: 讀法 2｜DCF 失效？ | C66: =IF(OR(輸入與假設!$C$349<=輸入與假設!$C$350,C65<=0),1,0) -> 0
A67: 讀法 2｜終值現值 | C67: =IF(C66=1,0,C65*(1+輸入與假設!$C$350)/(輸入與假設!$C$349-輸入與假設!$C$350))*G16 -> 2375.6325
A68: 讀法 2｜企業價值 EV | C68: =C64+C67 -> 2642.1493
A69: 讀法 2｜d1 | C69: =IF(OR((C68+C28)<=0,評價_DCF與目標價!$C$91<=0),0,(LN((C68+C28)/評價_DCF與目標價!$C$91)+(輸入與假設!$C$340+輸入與假設!$C$402^2/2)*輸入與假設!$C$403)/(輸入與假設!$C$402*SQRT(輸入與假設!$C$403))) -> 0
A70: 讀法 2｜DCF 每股（評價日） | C70: =IF(C66=1,0,IF(輸入與假設!$C$401=2,IF((C68+C28)<=0,0,IF(評價_DCF與目標價!$C$91<=0,(C68+C28),(C68+C28)*NORMSDIST(C69)-評價_DCF與目標價!$C$91*EXP(-輸入與假設!$C$340*輸入與假設!$C$403)*NORMSDIST(C69-輸入與假設!$C$402*SQRT(輸入與假設!$C$403)))/C29),MAX(0,(C68-評價_DCF與目標價!$C$91+C28)/C29))) -> 381.226 | I70: 與讀法 1 同股數、同淨負債
A71: 讀法 2｜DCF 每股（推到目標價時點） | C71: =C70*(1+輸入與假設!$C$349)^輸入與假設!$C$409 -> 422.76422
A72: 讀法 2｜EV/EBITDA 每股（融資後） | C72: =MAX(0,(C39+INDEX($D$56:$G$56,1,輸入與假設!$C$393)*輸入與假設!$C$355-C40)/C41)*C42 -> 422.25419 | I72: 錨定年 AI 雲端 EBITDA 加影子 EBITDA × AI 雲端倍數
A73: 讀法 2｜加權目標價 | C73: =C71*IF(C66=1,0,輸入與假設!$C$394)+C72*IF(C66=1,1,1-輸入與假設!$C$394) -> 422.4837 | I73: 只有對外 AI 的超額報酬影響目標價（對照表 r1 C16）
A74: 讀法 2 − 讀法 1（目標價差額） | C74: =C73-C51 -> 68.930474 | I74: 主值取哪一個是 Andy 的判斷（待決）
A76: 可轉債稀釋（若轉換法；第一輪判斷價＝現價，第二輪＝MIN(現價, 第一輪目標價)）
A77: 第一輪：轉股股數 | C77: =SUMPRODUCT(資產負債_既有債務!$D$29:$D$29*資產負債_既有債務!$G$29:$G$29) -> 0 | I77: 有效轉換價 < 現價的可轉債：原始本金 ÷ 轉換價
A78: 第一輪：評價股數 | C78: =輸入與假設!$C$331+C77 -> 7.453
A79: 第一輪：評價淨負債 | C79: =輸入與假設!$C$332+SUMPRODUCT(資產負債_既有債務!$C$29:$C$29*(1-資產負債_既有債務!$G$29:$G$29))+輸入與假設!$C$338 -> -201.107 | I79: ＝不含可轉債的淨負債＋債務處理可轉債到期本金＋調整項
A80: 第一輪：DCF 融資後股數 | C80: =C78+各期收支!G97 -> 7.3493709
A81: 第一輪：d1 | C81: =IF(OR((C23+C28)<=0,C79<=0),0,(LN((C23+C28)/C79)+(輸入與假設!$C$340+輸入與假設!$C$402^2/2)*輸入與假設!$C$403)/(輸入與假設!$C$402*SQRT(輸入與假設!$C$403))) -> 0
A82: 第一輪：DCF 每股（評價日） | C82: =IF(C30=1,0,IF(輸入與假設!$C$401=2,IF((C23+C28)<=0,0,IF(C79<=0,(C23+C28),(C23+C28)*NORMSDIST(C81)-C79*EXP(-輸入與假設!$C$340*輸入與假設!$C$403)*NORMSDIST(C81-輸入與假設!$C$402*SQRT(輸入與假設!$C$403)))/C80),MAX(0,(C23-C79+C28)/C80))) -> 284.05468 | I82: 與上方 DCF 同算法，只換股數與淨負債
A83: 第一輪：錨定年末淨負債 | C83: =INDEX(各期收支!$D$102:$G$102,1,輸入與假設!$C$393)-INDEX(各期收支!$D$56:$G$56,1,輸入與假設!$C$393)+SUMPRODUCT(資產負債_既有債務!$C$29:$C$29*(資產負債_既有債務!$F$29:$F$29-資產負債_既有債務!$G$29:$G$29))+輸入與假設!$C$338 -> -182.32835 | I83: ＝融資表錨定年末淨負債＋（融資分類為轉股、評價分類為債務的到期本金）＋調整項
A84: 第一輪：錨定年末股數 | C84: =C78*(1+輸入與假設!$C$398)^輸入與假設!$C$393+INDEX(各期收支!$D$97:$G$97,1,輸入與假設!$C$393) -> 7.5592163
A85: 第一輪：EV/EBITDA 每股 | C85: =MAX(0,(C39-C83)/C84)*C42 -> 385.09255
A86: 第一輪：加權目標價 | C86: =C82*(1+輸入與假設!$C$349)^輸入與假設!$C$409*IF(C30=1,0,輸入與假設!$C$394)+C85*IF(C30=1,1,1-輸入與假設!$C$394) -> 353.55323
A87: 第二輪判斷價 | C87: =MIN(輸入與假設!$C$330,C86) -> 353.55323 | I87: ＝MIN(現價, 第一輪加權目標價)：以較保守者判斷是否價內
A88: 第二輪：轉股股數 | C88: =SUMPRODUCT(資產負債_既有債務!$D$29:$D$29*資產負債_既有債務!$H$29:$H$29) -> 0 | I88: 有效轉換價 < 第二輪判斷價的可轉債
A89: 第二輪：債務處理到期本金 | C89: =SUMPRODUCT(資產負債_既有債務!$C$29:$C$29*(1-資產負債_既有債務!$H$29:$H$29)) -> 0
A90: 評價股數（含可轉債轉股） | C90: =輸入與假設!$C$331+C88 -> 7.453 | I90: DCF、損益股數與錨定年末股數的起點
A91: 評價淨負債（含可轉債與調整項） | C91: =輸入與假設!$C$332+C89+輸入與假設!$C$338 -> -201.107 | I91: DCF 減項與 Merton 履約價
A92: 錨定年末淨負債調整（可轉債分類差＋調整項） | C92: =SUMPRODUCT(資產負債_既有債務!$C$29:$C$29*(資產負債_既有債務!$F$29:$F$29-資產負債_既有債務!$H$29:$H$29))+輸入與假設!$C$338 -> -170.4 | I92: 融資現金流依『融資分類』（判斷價＝股權發行價）；評價依第二輪分類，差額在錨定年末淨負債補回
A93: DCF 權重說明 | C93: =IF(C30=1,"DCF 失效，已以 EV/EBITDA 100% 計。",IF(AND(輸入與假設!$C$401<>2,C108<0),"DCF 為 $0 仍計 "&TEXT(輸入與假設!$C$394,"0%")&" 權重的原因：DCF 沒有失效，而是算出的股權價值為負（每股約 −$"&TEXT(ABS(C108),"0.0")&"），代表自由現金流折現後的企業價值不足以償還淨負債。EV/EBITDA 沒有扣除 GPU 汰換與擴張支出，保留 DCF 權重，是為了讓目標價反映「EBITDA 付不起資本成本」。若不計 DCF，目標價為 $"&TEXT(C43,"0.0")&"（"&CHOOSE(D107+2,"賣出","中立","買進")&"）；"&TEXT(輸入與假設!$C$394,"0%")&"／"&TEXT(1-輸入與假設!$C$394,"0%")&" 為判斷值。","")) | I93: 只在 DCF 被 0 截斷時顯示；DCF 失效時改為一句；DCF 為正時空白（與 HTML 同一字串）
A95: 目標價區間（情境區間、方法區間；評等仍依點位）
A96: 目標價區間｜點位（目前輸入的加權目標價） | C96: =C51 -> 353.55323 | I96: ="評等規則不變：空間 ≥"&IF(ROUND(ABS(輸入與假設!$C$419)*100,4)=INT(ROUND(ABS(輸入與假設!$C$419)*100,4)),TEXT(ROUND(ABS(輸入與假設!$C$419)*100,4),"0"),TEXT(ROUND(ABS(輸入與假設!$C$419)*100,4),"0.0"))&"%"&" 且終值占比 <"&IF(ROUND(ABS(輸入與假設!$C$420)*100,4)=INT(ROUND(ABS(輸入與假設!$C$420)*100,4)),TEXT(ROUND(ABS(輸入與假設!$C$420)*100,4),"0"),TEXT(ROUND(ABS(輸入與假設!$C$420)*100,4),"0.0"))&"%"&"、股權募資 ≤"&IF(輸入與假設!$C$422=INT(輸入與假設!$C$422),TEXT(輸入與假設!$C$422,"0"),TEXT(輸入與假設!$C$422,"0.0"))&" 倍現市值 → 買進；空間 ≤−"&IF(ROUND(ABS(輸入與假設!$C$421)*100,4)=INT(ROUND(ABS(輸入與假設!$C$421)*100,4)),TEXT(ROUND(ABS(輸入與假設!$C$421)*100,4),"0"),TEXT(ROUND(ABS(輸入與假設!$C$421)*100,4),"0.0"))&"%"&"，或股權募資 >"&IF(輸入與假設!$C$422=INT(輸入與假設!$C$422),TEXT(輸入與假設!$C$422,"0"),TEXT(輸入與假設!$C$422,"0.0"))&" 倍且空間 ≤−"&IF(ROUND(ABS(輸入與假設!$C$423)*100,4)=INT(ROUND(ABS(輸入與假設!$C$423)*100,4)),TEXT(ROUND(ABS(輸入與假設!$C$423)*100,4),"0"),TEXT(ROUND(ABS(輸入與假設!$C$423)*100,4),"0.0"))&"%"&" → 賣出；其餘中立" -> 評等規則不變：空間 ≥25% 且終值占比 <90%、股權募資 ≤1.5 倍現市值 → 買進；空間 ≤−15%，或股權募資 >1.5 倍且空間 ≤−8% → 賣出；其餘中立
A97: 目標價區間｜終值占 EV（評等用） | C97: =C22/MAX(ABS(C23),1)*IF(C23=0,1,SIGN(C23)) -> 0.94545807
A98: 目標價區間｜股權募資 ÷ 現市值（評等用） | C98: =SUM(各期收支!C92:G92)/(輸入與假設!$C$330*輸入與假設!$C$331) -> 0
A99: 目標價區間｜點位評等代碼（1＝買進、0＝中立、−1＝賣出） | C99: =IF(AND((C51/MAX(輸入與假設!$C$330,0.01)-1)>=輸入與假設!$C$419,$C$97<輸入與假設!$C$420,$C$98<=輸入與假設!$C$422),1,IF(OR((C51/MAX(輸入與假設!$C$330,0.01)-1)<=輸入與假設!$C$421,AND($C$98>輸入與假設!$C$422,(C51/MAX(輸入與假設!$C$330,0.01)-1)<=輸入與假設!$C$423)),-1,0)) -> -1 | D99: =CHOOSE(C99+2,"賣出","中立","買進") -> 賣出
A100: 目標價區間｜賣出門檻價（現價 × (1 − 15%)） | C100: =輸入與假設!$C$330*(1+輸入與假設!$C$421) -> 450.296
A101: 目標價區間｜保守 第三方可辨識站點（加權目標價／評等代碼／距賣出門檻） | C101: =輸入與假設!D453 -> 382.25279 | D101: =輸入與假設!E453 -> -1 | E101: =C101-$C$100 -> -68.043215 | I101: 引用『輸入與假設』底部模擬運算表（情境選擇 1／2／3），保留其餘手動輸入
A102: 目標價區間｜基準 依資本支出指引（加權目標價／評等代碼／距賣出門檻） | C102: =輸入與假設!D454 -> 353.55323 | D102: =輸入與假設!E454 -> -1 | E102: =C102-$C$100 -> -96.742773
A103: 目標價區間｜積極 依公司容量目標（加權目標價／評等代碼／距賣出門檻） | C103: =輸入與假設!D455 -> 351.96385 | D103: =輸入與假設!E455 -> -1 | E103: =C103-$C$100 -> -98.332146
A104: 目標價區間｜情境區間（下緣／上緣） | C104: =MIN(C101,C103) -> 351.96385 | D104: =MAX(C101,C103) -> 382.25279
A105: 目標價區間｜方法區間倍數（下端／上端） | C105: =MIN(輸入與假設!$C$396,輸入與假設!$C$397) -> 5 | D105: =MAX(輸入與假設!$C$396,輸入與假設!$C$397) -> 6
A106: 目標價區間｜方法區間（下緣／上緣） | C106: =MIN(C48*IF(C30=1,0,輸入與假設!$C$394)+MAX(0,(C45*C105+C44*輸入與假設!$C$392-C40)/C41)*C42*IF(C30=1,1,1-輸入與假設!$C$394),C48*IF(C30=1,0,輸入與假設!$C$394)+MAX(0,(C45*D105+C44*輸入與假設!$C$392-C40)/C41)*C42*IF(C30=1,1,1-輸入與假設!$C$394)) -> 348.77232 | D106: =MAX(C48*IF(C30=1,0,輸入與假設!$C$394)+MAX(0,(C45*C105+C44*輸入與假設!$C$392-C40)/C41)*C42*IF(C30=1,1,1-輸入與假設!$C$394),C48*IF(C30=1,0,輸入與假設!$C$394)+MAX(0,(C45*D105+C44*輸入與假設!$C$392-C40)/C41)*C42*IF(C30=1,1,1-輸入與假設!$C$394)) -> 353.55323 | I106: ＝DCF 採用值 × 有效權重 ＋ EV/EBITDA 腿（倍數換成兩端）× 有效權重
A107: 目標價區間｜100% EV/EBITDA 目標價（價位／評等代碼） | C107: =C43 -> 385.09255 | D107: =IF(AND((C43/MAX(輸入與假設!$C$330,0.01)-1)>=輸入與假設!$C$419,$C$97<輸入與假設!$C$420,$C$98<=輸入與假設!$C$422),1,IF(OR((C43/MAX(輸入與假設!$C$330,0.01)-1)<=輸入與假設!$C$421,AND($C$98>輸入與假設!$C$422,(C43/MAX(輸入與假設!$C$330,0.01)-1)<=輸入與假設!$C$423)),-1,0)) -> -1 | E107: =CHOOSE(D107+2,"賣出","中立","買進") -> 賣出
...

Sheet 評價_反向DCF
A1: 反向 DCF — 現價隱含什麼樣的收入與成本
A2: 不是問「值多少」，而是問「要值現價，營運要長什麼樣」。Excel 以『目標搜尋』反解；下方另附 HTML 即時計算結果的快照（v4.0 預設輸入）
A4: 即時：目前 DCF 與現價的差距
A5: 現價 | B5: =輸入與假設!$C$330 -> 529.76
A6: 目前 DCF 每股（依下限方式） | B6: =評價_DCF與目標價!C26 -> 284.05468
A7: 差距（DCF − 現價）＝目標搜尋的『設定儲存格』 | B7: =B6-B5 -> -245.70532
A8: 目前每 MW 年收入倍數／建置成本倍數 | B8: =輸入與假設!$C$32 -> 1 | C8: =輸入與假設!$C$233 -> 1
A10: 操作：用『目標搜尋』反解（資料 → 模擬分析 → 目標搜尋）
A11: ① 設定儲存格：本頁 B7；目標值：0
A12: ② 變數儲存格（擇一）：輸入與假設 B 區『每 MW 年收入倍數』→ 市價隱含單價；或 D 區『每 MW 建置成本倍數』→ 市價隱含建置成本；或 C 區『穩態 EBITDA 率』
A13: ③ 解完請記下結果，再把倍數改回 100%（或按 Ctrl+Z）。DCF 以 0 截斷時，負值區域斜率為 0，請從 100% 以上開始搜尋
A14: ④ 組合分析：先把 D 區建置成本倍數與 C 區穩態 EBITDA 率設為想測的值，再對『每 MW 年收入倍數』做目標搜尋，即得下方矩陣中的一格
A16: 快照：單一槓桿（HTML v4.0 預設輸入，DCF 0 截斷）
A17: 單一槓桿（其他不變） | B17: 目前 | C17: 市價隱含 | D17: 變動 | G17: 對照
A18: FY31 每 MW 年收入（US$m） | B18: 13.0191 | C18: 34.3118 | D18: 1.6355 | G18: Microsoft 對照：IREN 合約隱含 9.70（IT）US$m/MW-年
A19: 每 MW 建置成本（US$m） | B19: 45.1743 | C19: 無解 | D19: 無解 | G19: Tokenomics 每 MW 全成本（IT＋自建機房 60%）約 $44m/MW-IT
A20: 穩態 EBITDA 率（FY31） | B20: 0.79 | C20: 無解 | D20: 無解 | G20: AI 雲端（算力）EBITDA 率；非 AI 事業 EBITDA 率固定不動。可觀察 neocloud 區間 IREN 約 35%、CRWV 約 59%（變動為百分點）
A21: （對照）加權目標價＝現價所需每 MW 年收入 | B21: 13.0191 | C21: 35.5259 | D21: 1.7288 | G21: 含 EV/EBITDA 腿（FY29 錨定）；非純反向 DCF
A23: 快照：收入與成本的綜合影響——要值現價，FY31 每 MW 年收入需要多少（US$m）
A24: 建置成本 ＼ 穩態 EBITDA 率 | B24: 0.35 | C24: 0.47 | D24: 0.59 | E24: 0.7 | I24: 矩陣保留 AI 雲端 EBITDA 率維度：非 AI 事業（EBITDA 率與同業倍數）不隨此表變動，表內只測算力業務的單位經濟
A25: $31.6m（-30%） | B25: 30.33 | C25: 30.33 | D25: 30.33 | E25: 30.33
A26: $36.1m（-20%） | B26: 31.73 | C26: 31.73 | D26: 31.73 | E26: 31.73
A27: $40.7m（-10%） | B27: 33.06 | C27: 33.06 | D27: 33.06 | E27: 33.06
A28: $45.2m（目前） | B28: 34.31 | C28: 34.31 | D28: 34.31 | E28: 34.31
A29: $49.7m（+10%） | B29: 35.49 | C29: 35.49 | D29: 35.49 | E29: 35.49
A30: 快照為靜態數值（HTML 以同一引擎即時計算）；改變輸入後請以目標搜尋重算，或參考 HTML『評價 → 反向 DCF』

Sheet 評價_可比公司
A1: 可比公司 — 以 EV/Sales 為主（市值：2026-09-21 收盤）
A2: EV＝市值＋（有息負債−非受限現金）；含租賃＝EV＋營業租賃負債。EV/EBITDA 僅供參考（GAAP EBITDA 為負者顯示 n/m）。此表不進入目標價。與 HTML Comps 分頁同一組數字
A4: 公司 | B4: 市值 | C4: 淨負債 | D4: EV | E4: TTM 營收 | F4: EV/Sales（TTM） | G4: 含租賃 EV/Sales | H4: TTM EBITDA | I4: EV/EBITDA | J4: 資料期 | K4: 備註
A5: CRWV CoreWeave | B5: 49.11 | C5: 46.03 | D5: =B5+C5 -> 95.14 | E5: 7.59 | F5: =D5/E5 -> 12.534914 | G5: =(D5+16.54)/E5 -> 14.714097 | H5: =-0.231+3.991 -> 3.76 | I5: =IF(H5>0,D5/H5,"n/m") -> 25.303191 | J5: TTM 至 Q2（6/30，10-Q）；市值與 EV 2026-10-07 | K5: 營業租賃負債 16.54；GAAP 營業損益 -0.231＋D&A 3.991。CRWV 市值與 EV 2026-10-07；TTM 至 Q2；租賃負債 16.54
A6: NBIS Nebius | B6: 68.49 | C6: 2.15 | D6: =B6+C6 -> 70.64 | E6: 1.36 | F6: =D6/E6 -> 51.941176 | G6: =(D6+1.6253)/E6 -> 53.13625 | H6: =-0.612+0.418 -> -0.194 | I6: =IF(H6>0,D6/H6,"n/m") -> n/m | J6: 營收 TTM 至 Q2；營業損益與 D&A 為 FY2025（20-F）；市值與 EV 2026-10-06 | K6: 營業租賃負債 1.6253；GAAP 營業損益 -0.612＋D&A 0.418。NBIS 市值與 EV 2026-10-06；EBITDA 用 FY2025
A7: IREN | B7: 18.61 | C7: 1.7 | D7: =B7+C7 -> 20.31 | E7: 0.707 | F7: =D7/E7 -> 28.727016 | G7: =(D7+0.003)/E7 -> 28.731259 | H7: =-1.047+0.418 -> -0.629 | I7: =IF(H7>0,D7/H7,"n/m") -> n/m | J7: FY26 10-K（6/30）；未更新，日期 2026-09-21 | K7: 營業租賃負債 0.003；GAAP 營業損益 -1.047＋D&A 0.418。自有電廠、營業租賃負債僅 0.003bn；FY26 合約 ARR 4.0bn
A8: APLD Applied Digital | B8: 8.22 | C8: 3.37 | D8: =B8+C8 -> 11.59 | E8: 0.6113 | F8: =D8/E8 -> 18.959594 | G8: =(D8+0.066)/E8 -> 19.067561 | H8: =-0.236+0.067 -> -0.169 | I8: =IF(H8>0,D8/H8,"n/m") -> n/m | J8: FY26 10-K（5/31）；未更新，日期 2026-09-21 | K8: 營業租賃負債 0.066；GAAP 營業損益 -0.236＋D&A 0.067。租約多未起租，營收尚未反映約 36bn 合約
A9: CORZ Core Scientific | B9: 5.9 | C9: 2.53 | D9: =B9+C9 -> 8.43 | E9: 0.4403 | F9: =D9/E9 -> 19.146037 | G9: =(D9+0.109)/E9 -> 19.393595 | H9: =-0.561+0.063 -> -0.498 | I9: =IF(H9>0,D9/H9,"n/m") -> n/m | J9: TTM 至 Q2（6/30）；未更新，日期 2026-09-21 | K9: 營業租賃負債 0.109；GAAP 營業損益 -0.561＋D&A 0.063。託管轉型期
A10: 同業中位數 | F10: =MEDIAN(F5:F9) -> 19.146037 | G10: =MEDIAN(G5:G9) -> 19.393595
A11: MSFT（TTM 至 Q4 2026） | B11: 3934.5 | C11: =輸入與假設!$C$332+SUMPRODUCT(資產負債_既有債務!$C$29:$C$29*(1-資產負債_既有債務!$H$25:$H$25))+輸入與假設!$C$338 -> -201.107 | D11: =B11+C11 -> 3733.393 | E11: 331.839 | F11: =D11/E11 -> 11.250616 | G11: =(D11+21.925)/E11 -> 11.316687 | H11: =155.237+38.534 -> 193.771 | I11: =IF(H11>0,D11/H11,"n/m") -> 19.267037 | J11: TTM 至 Q4 2026 | K11: EV 用 2026-09-21 市值（基本股）與評價日淨負債（可轉債全數以到期本金計入）；含租賃再加營業租賃負債 21.925
A12: MSFT 模型 FY28E | B12: =輸入與假設!$C$330*評價_DCF與目標價!$C$90 -> 3948.3013 | C12: =評價_DCF與目標價!$C$91 -> -201.107 | D12: =B12+C12 -> 3747.1943 | E12: =損益!D9 -> 471.42433 | F12: =D12/E12 -> 7.9486654 | G12: =(D12+21.925)/E12 -> 7.9951734 | H12: =損益!D22 -> 282.29401 | I12: =D12/H12 -> 13.274083 | K12: 市值用評價股數（含價內可轉債轉股）、淨負債用評價淨負債；分母為模型 FY28 營收
A14: 讀法：MSFT 為整體公司（M365、授權、遊戲、搜尋＋Azure），倍數不可直接與純 AI 基礎設施同業比較；
A15: CRWV 以租約取得機房，加入營業租賃負債後倍數上升；MSFT 自建與租賃並行（另有未起租承諾 329.1B 尚未入表），並向 CoreWeave、Nebius、IREN、Nscale、Lambda 租用 GPU。
A16: 前瞻：見下方 MSFT 模型列。此表為市場比較用，不進入目標價。

Sheet AI增量報酬
A1: AI 增量報酬：對外 AI ROIC ＝(對外 AI 雲端 EBITDA − AI 折舊 × 對外比例)×(1 − 稅率) ÷ (平均 AI 投入資本 × 對外比例)，對 WACC
A2: 年化＝模型期 ÷ 期間長度（FY27 只含 全年）；投入資本（全 AI）＝AI 期初毛額 × 淨額比＋累計 AI 成長型與汰換 − 累計 AI 折舊；對外口徑＝投入資本與折舊 × 對外比例（主值）；全 AI 口徑（含影子收入）只作對照；打平 k＝使錨定期對外 AI ROIC＝WACC 的 k（解出的門檻，不是輸入）
A4: 項目 | B4: 單位 | C4: FY27 | D4: FY28 | E4: FY29 | F4: FY30 | G4: FY31 | I4: 公式／來源說明
A5: 對外 AI 雲端營收（年化） | B5: US$bn | C5: =運營_產能與收入!C26/輸入與假設!C$34 -> 53.750967 | D5: =運營_產能與收入!D26/輸入與假設!D$34 -> 84.730366 | E5: =運營_產能與收入!E26/輸入與假設!E$34 -> 115.934 | F5: =運營_產能與收入!F26/輸入與假設!F$34 -> 147.23076 | G5: =運營_產能與收入!G26/輸入與假設!G$34 -> 178.57374
A6: AI 雲端 EBITDA 率 | B6: % | C6: =輸入與假設!C$214 -> 0.79787831 | D6: =輸入與假設!D$214 -> 0.80029644 | E6: =輸入與假設!E$214 -> 0.80156247 | F6: =輸入與假設!F$214 -> 0.80233765 | G6: =輸入與假設!G$214 -> 0.80286109 | I6: Tokenomics 營運成本推得（輸入與假設 C 區）
A7: AI 雲端 EBITDA（年化） | B7: US$bn | C7: =C5*C6 -> 42.88673 | D7: =D5*D6 -> 67.80941 | E7: =E5*E6 -> 92.928341 | F7: =F5*F6 -> 118.12879 | G7: =G5*G6 -> 143.36991
A8: AI 營運成本（年化） | B8: US$bn | C8: =C5-C7 -> 10.864236 | D8: =D5-D7 -> 16.920956 | E8: =E5-E7 -> 23.005657 | F8: =F5-F7 -> 29.101979 | G8: =G5-G7 -> 35.203832
A9: AI 折舊（年化） | B9: US$bn | C9: =輸入與假設!C$283/輸入與假設!C$34 -> 38.115283 | D9: =輸入與假設!D$283/輸入與假設!D$34 -> 63.385503 | E9: =輸入與假設!E$283/輸入與假設!E$34 -> 89.126809 | F9: =輸入與假設!F$283/輸入與假設!F$34 -> 114.87721 | G9: =輸入與假設!G$283/輸入與假設!G$34 -> 140.62762 | I9: D&A 分池（輸入與假設 D 區）
A10: 有效在役對外 MW（＝營收 ÷ 每 MW 年收入） | B10: MW | C10: =C5/MAX(0.000000000001,輸入與假設!C102*輸入與假設!$C$66/1000) -> 4412.95 | D10: =D5/MAX(0.000000000001,輸入與假設!D102*輸入與假設!$C$66/1000) -> 6738.85 | E10: =E5/MAX(0.000000000001,輸入與假設!E102*輸入與假設!$C$66/1000) -> 9064.75 | F10: =F5/MAX(0.000000000001,輸入與假設!F102*輸入與假設!$C$66/1000) -> 11390.65 | G10: =G5/MAX(0.000000000001,輸入與假設!G102*輸入與假設!$C$66/1000) -> 13716.3
A11: 租用對外 MW（平均） | B11: MW | C11: =(輸入與假設!$C$256+輸入與假設!C$257)/2 -> 653 | D11: =(輸入與假設!C$257+輸入與假設!D$257)/2 -> 756 | E11: =(輸入與假設!D$257+輸入與假設!E$257)/2 -> 756 | F11: =(輸入與假設!E$257+輸入與假設!F$257)/2 -> 756 | G11: =(輸入與假設!F$257+輸入與假設!G$257)/2 -> 756 | I11: capexModel.rentedExt（C20）：收入照算、投入資本與折舊不計
A12: 自有對外占自有 AI MW 比例 | B12: % | C12: =MAX(0,C10-C11)/MAX(0.000000001,C10/輸入與假設!$C$227-C11) -> 0.56102607 | D12: =MAX(0,D10-D11)/MAX(0.000000001,D10/輸入與假設!$C$227-D11) -> 0.57113241 | E12: =MAX(0,E10-E11)/MAX(0.000000001,E10/輸入與假設!$C$227-E11) -> 0.57892964 | F12: =MAX(0,F10-F11)/MAX(0.000000001,F10/輸入與假設!$C$227-F11) -> 0.58341052 | G12: =MAX(0,G10-G11)/MAX(0.000000001,G10/輸入與假設!$C$227-G11) -> 0.58631953 | I12: 投入資本與折舊按此比例分攤（無租用時＝對外比例；C11、C20）
A13: 每 MW 機房年租金（Tokenomics 機房成本 × 資本回收係數） | B13: US$bn/MW | C13: =(輸入與假設!C76*TK_CapexFacility_H100+輸入與假設!C82*TK_CapexFacility_GB200+輸入與假設!C88*TK_CapexFacility_GB300+輸入與假設!C94*TK_CapexFacility_GB300+輸入與假設!C100*TK_CapexFacility_VR200)/MAX(0.000000001,輸入與假設!C101)/1000*0.1/(1-(1+0.1)^(-輸入與假設!$C$274)) -> 0.0014889304 | D13: =(輸入與假設!D76*TK_CapexFacility_H100+輸入與假設!D82*TK_CapexFacility_GB200+輸入與假設!D88*TK_CapexFacility_GB300+輸入與假設!D94*TK_CapexFacility_GB300+輸入與假設!D100*TK_CapexFacility_VR200)/MAX(0.000000001,輸入與假設!D101)/1000*0.1/(1-(1+0.1)^(-輸入與假設!$C$274)) -> 0.0014889304 | E13: =(輸入與假設!E76*TK_CapexFacility_H100+輸入與假設!E82*TK_CapexFacility_GB200+輸入與假設!E88*TK_CapexFacility_GB300+輸入與假設!E94*TK_CapexFacility_GB300+輸入與假設!E100*TK_CapexFacility_VR200)/MAX(0.000000001,輸入與假設!E101)/1000*0.1/(1-(1+0.1)^(-輸入與假設!$C$274)) -> 0.0014889304 | F13: =(輸入與假設!F76*TK_CapexFacility_H100+輸入與假設!F82*TK_CapexFacility_GB200+輸入與假設!F88*TK_CapexFacility_GB300+輸入與假設!F94*TK_CapexFacility_GB300+輸入與假設!F100*TK_CapexFacility_VR200)/MAX(0.000000001,輸入與假設!F101)/1000*0.1/(1-(1+0.1)^(-輸入與假設!$C$274)) -> 0.0014889304 | G13: =(輸入與假設!G76*TK_CapexFacility_H100+輸入與假設!G82*TK_CapexFacility_GB200+輸入與假設!G88*TK_CapexFacility_GB300+輸入與假設!G94*TK_CapexFacility_GB300+輸入與假設!G100*TK_CapexFacility_VR200)/MAX(0.000000001,輸入與假設!G101)/1000*0.1/(1-(1+0.1)^(-輸入與假設!$C$274)) -> 0.0014889304 | I13: 出租方打平租金＝在役世代加權 TK_CapexFacility × 10% 資本回收係數（機房年限）[Derived]（C22）
A14: 機房租金（自有對外 MW ×(1 − 自建比例)） | B14: US$bn | C14: =(1-輸入與假設!$C$228)*MAX(0,C10-C11)*C13 -> 2.2393216 | D14: =(1-輸入與假設!$C$228)*MAX(0,D10-D11)*D13 -> 3.563219 | E14: =(1-輸入與假設!$C$228)*MAX(0,E10-E11)*E13 -> 4.9484603 | F14: =(1-輸入與假設!$C$228)*MAX(0,F10-F11)*F13 -> 6.3337016 | G14: =(1-輸入與假設!$C$228)*MAX(0,G10-G11)*G13 -> 7.7187941 | I14: 只進 AI 增量報酬（資金與評價的租金現金已在租賃承諾內，不重複扣；C22）
A15: 租用對外 MW 租金 | B15: US$bn | C15: =C11*6.54/1000 -> 4.27062 | D15: =D11*6.54/1000 -> 4.94424 | E15: =E11*6.54/1000 -> 4.94424 | F15: =F11*6.54/1000 -> 4.94424 | G15: =G11*6.54/1000 -> 4.94424 | I15: ＝租用對外 MW × 每 MW 年租金（capexModel.rentedExt.rentMW；C20）
A16: 對外 AI EBITDA（扣租金） | B16: US$bn | C16: =C7-C14-C15 -> 36.376789 | D16: =D7-D14-D15 -> 59.301951 | E16: =E7-E14-E15 -> 83.03564 | F16: =F7-F14-F15 -> 106.85084 | G16: =G7-G14-G15 -> 130.70687
A17: 對外 AI 折舊（年化，按對外比例分攤） | B17: US$bn | C17: =C9*C12 -> 21.383668 | D17: =D9*D12 -> 36.201515 | E17: =E9*E12 -> 51.598152 | F17: =F9*F12 -> 67.020575 | G17: =G9*G12 -> 82.452719
A18: 對外 AI NOPAT（年化） | B18: US$bn | C18: =(C16-C17)*(1-輸入與假設!$C$339) -> 11.994497 | D18: =(D16-D17)*(1-輸入與假設!$C$339) -> 18.480348 | E18: =(E16-E17)*(1-輸入與假設!$C$339) -> 25.149991 | F18: =(F16-F17)*(1-輸入與假設!$C$339) -> 31.864215 | G18: =(G16-G17)*(1-輸入與假設!$C$339) -> 38.603322 | I18: ＝(對外 EBITDA − 對外折舊)×(1 − 稅率)
A19: AI 投入資本（期初） | B19: US$bn | C19: =(輸入與假設!$C$272+輸入與假設!$C$273)*輸入與假設!$C$277 -> 144.11873 | D19: =C21 -> 274.75638 | E19: =D21 -> 386.37972 | F19: =E21 -> 472.37096 | G19: =F21 -> 572.68888 | I19: FY27＝AI 期初毛額 × 淨額比；之後＝前期期末
A20: AI 投入（成長型＋汰換，模型期） | B20: US$bn | C20: =輸入與假設!C$264+輸入與假設!C$268 -> 168.75293 | D20: =輸入與假設!D$264+輸入與假設!D$268 -> 175.00885 | E20: =輸入與假設!E$264+輸入與假設!E$268 -> 175.11805 | F20: =輸入與假設!F$264+輸入與假設!F$268 -> 215.19513 | G20: =輸入與假設!G$264+輸入與假設!G$268 -> 318.27413
A21: AI 投入資本（期末） | B21: US$bn | C21: =C19+C20-輸入與假設!C$283 -> 274.75638 | D21: =D19+D20-輸入與假設!D$283 -> 386.37972 | E21: =E19+E20-輸入與假設!E$283 -> 472.37096 | F21: =F19+F20-輸入與假設!F$283 -> 572.68888 | G21: =G19+G20-輸入與假設!G$283 -> 750.33538 | I21: ＝期初＋投入 − AI 折舊
A22: 對外 AI 平均投入資本（按對外比例分攤） | B22: US$bn | C22: =(C19+C21)/2*C12 -> 117.49993 | D22: =(D19+D21)/2*D12 -> 188.79813 | E22: =(E19+E21)/2*E12 -> 248.57811 | F22: =(F19+F21)/2*F12 -> 304.84945 | G22: =(G19+G21)/2*G12 -> 387.85748
A23: 對外 AI ROIC（主值） | B23: % | C23: =C18/MAX(0.000000001,C22) -> 0.10208089 | D23: =D18/MAX(0.000000001,D22) -> 0.097884171 | E23: =E18/MAX(0.000000001,E22) -> 0.1011754 | F23: =F18/MAX(0.000000001,F22) -> 0.10452443 | G23: =G18/MAX(0.000000001,G22) -> 0.099529658 | I23: ＝對外 NOPAT ÷ 對外平均投入資本（對照表 r1 C11）
A24: WACC | B24: % | C24: =輸入與假設!$C$349 -> 0.10895958 | D24: =輸入與假設!$C$349 -> 0.10895958 | E24: =輸入與假設!$C$349 -> 0.10895958 | F24: =輸入與假設!$C$349 -> 0.10895958 | G24: =輸入與假設!$C$349 -> 0.10895958
A25: 對外 AI ROIC − WACC | B25: % | C25: =C23-C24 -> -0.0068786958 | D25: =D23-D24 -> -0.011075411 | E25: =E23-E24 -> -0.0077841784 | F25: =F23-F24 -> -0.004435151 | G25: =G23-G24 -> -0.0094299243 | I25: 負值＝AI 投資未賺到資金成本
A26: 影子收入（自用 AI MW × 每 MW 年收入，年化） | B26: US$bn | C26: =C5*(1/輸入與假設!$C$227-1) -> 35.833978 | D26: =D5*(1/輸入與假設!$C$227-1) -> 56.486911 | E26: =E5*(1/輸入與假設!$C$227-1) -> 77.289331 | F26: =F5*(1/輸入與假設!$C$227-1) -> 98.153843 | G26: =G5*(1/輸入與假設!$C$227-1) -> 119.04916 | I26: 自用 AI MW＝對外 ×(1 ÷ 對外比例 − 1)；只作對照，不進評價（對照表 r1 D2）
