Workbook

Sheet README
A1: Microsoft（MSFT）個股模型 v0.3 — 命題＋官方營收分部 → 損益表（2026-10-27；資料截至 FY26Q4；FY27Q1 財報 2026-10-28 未納入）
A2: 工作表：README → In → Q → Thesis → Seg → PL → CF → Val → Recon → Sens → Sources。金額十億美元；財年 6 月結束（FY2027＝2026-07～2027-06）
A3: 命題：AI 能否同時在 Azure（算力）與 Microsoft 365（Copilot 應用）變現，撐住翻倍的資本支出。
A4: 核心問題：FY2029 的 AI 增量營業利益能否覆蓋 AI 資本支出的資金成本（AI 增量 ROIC 對 WACC），且自由現金流不需停止回購。
A5: ="① 命題答案（FY2029，基準情境 B）：讀法 2（主值；自用 AI 價值中性）AI 增量 ROIC "&TEXT(Thesis!H96,"0.0%")&"，讀法 1（自用 AI 只計成本）"&TEXT(Thesis!H97,"0.0%")&"，WACC "&TEXT(wacc,"0.0%")&"；對外 Azure AI 本身 "&TEXT(Thesis!H99,"0.0%")&"。讀法 1 下 AI 容量越大、目標價越低（自用算力只有成本）；讀法 2 下容量增加對目標價中性偏正（敏感度：MW 速度改 Epoch 可辨識站點 "&TEXT(Sens!D9,"+0.0;-0.0")&"、+20% "&TEXT(Sens!D10,"+0.0;-0.0")&"）。AI 折舊 FY2026 "&TEXT(Thesis!E89,"0.0")&" → FY2029 "&TEXT(Thesis!H89,"0.0")&" 十億美元，財報口徑營業利益率 FY2029 "&TEXT(PL!H76,"0.0%")&"（FY2026 "&TEXT(PL!E76,"0.0%")&"）。" -> ① 命題答案（FY2029，基準情境 B）：讀法 2（主值；自用 AI 價值中性）AI 增量 ROIC 10.6%，讀法 1（自用 AI 只計成本）1.1%，WACC 10.3%；對外 Azure AI 本身 13.1%。讀法 1 下 AI 容量越大、目標價越低（自用算力只有成本）；讀法 2 下容量增加對目標價中性偏正（敏感度：MW 速度改 Epoch 可辨識站點 -48.0、+20% +4.5）。AI 折舊 FY2026 16.3 → FY2029 87.7 十億美元，財報口徑營業利益率 FY2029 39.3%（FY2026 46.8%）。
A6: ="② 收支關卡：基準情境首年起五年（FY2027–FY2031）自由現金流扣股利合計 "&TEXT(CF!C5,"#,##0.0")&" 十億美元（樂觀 "&TEXT(CF!B5,"#,##0.0")&"、保守 "&TEXT(CF!D5,"#,##0.0")&"）；"&CF!C6&"。" -> ② 收支關卡：基準情境首年起五年（FY2027–FY2031）自由現金流扣股利合計 274.0 十億美元（樂觀 378.6、保守 151.4）；需要舉債 9.8 十億美元；回購較每年 22.3 的目標少 43.9 十億美元（2 年減少）。
A7: ="③ 評價：加權目標價 "&TEXT(Val!$B$36,"#,##0")&" 美元（讀法 2），較現價 "&TEXT(px,"#,##0.00")&" "&TEXT(Val!$B$40,"+0.0%;-0.0%")&"；DCF "&TEXT(Val!$B$14,"#,##0")&"、分部加總 "&TEXT(Val!$B$31,"#,##0")&"；讀法 1 目標價 "&TEXT(Val!$B$47,"#,##0")&"（"&Val!$B$49&"）；市場共識 "&TEXT(cons_tp,"#,##0")&"。WACC "&TEXT(wacc,"0.0%")&"（−1pt 時目標價 "&TEXT(Sens!C25,"#,##0")&"）；非 AI 各線改用 Microsoft 自身 NTM EV/EBITDA "&TEXT(m_own,"0.0")&"× 時目標價 "&TEXT(Sens!C38,"#,##0")&"。" -> ③ 評價：加權目標價 389 美元（讀法 2），較現價 532.60 -27.0%；DCF 342、分部加總 436；讀法 1 目標價 304（放空）；市場共識 603。WACC 10.3%（−1pt 時目標價 413）；非 AI 各線改用 Microsoft 自身 NTM EV/EBITDA 15.7× 時目標價 455。
A8: ="投資建議："&Val!$B$43&"（讀法 2 主值；上檔空間 "&TEXT(Val!$B$40,"+0.0%;-0.0%")&"；讀法 1："&Val!$B$49&"；五級固定規則：≥ +50% 強力買進、+25%～+50% 買進、−25%～+25% 中立、−50%～−25% 放空、≤ −50% 強力放空）" -> 投資建議：放空（讀法 2 主值；上檔空間 -27.0%；讀法 1：放空；五級固定規則：≥ +50% 強力買進、+25%～+50% 買進、−25%～+25% 中立、−50%～−25% 放空、≤ −50% 強力放空）
A9: ="收支關卡（地圖）：CF 頁「收支關卡：自由現金流扣股利（五年合計）」基準 "&TEXT(CF!C5,"#,##0.0")&" 十億美元（財報現金，不含影子效益）" -> 收支關卡（地圖）：CF 頁「收支關卡：自由現金流扣股利（五年合計）」基準 274.0 十億美元（財報現金，不含影子效益）
A11: 驅動 → 推導對照表（每頁輸入、推導量、因果方向）
A12: 頁 | B12: 輸入（In 頁鍵） | C12: 推導量 | D12: 因果方向 | E12: 基準值（FY2029，情境 B）
A13: Thesis | B13: pace、mw_ext_26、ext_sh、rent_ext_f | C13: 在役對外 AI MW、自有 AI MW（含自用） | D13: MW 越多 → Azure AI 營收↑、AI 資本支出與折舊↑ | E13: =Thesis!H57 -> 10831.6
A14: Thesis | B14: tk_hold_*、p_long、p_spot、ls_*（k） | C14: 每 MW 年收入（US$M/MW-年） | D14: k 越高 → Azure AI 營收與 EBITDA↑（三情境主要差異） | E14: =Thesis!H71 -> 13.047202
A15: Thesis | B15: tk_cxit_*、tk_cxfac、self_build、capex_floor27、life_it | C15: AI 資本支出、AI 折舊 | D15: 資本支出 → 折舊 → Agents and Infra 營業利益↓；→ 自由現金流↓ | E15: =Thesis!H89 -> 87.742316
A16: Seg | B16: cop_s26、cop_add_*、cop_px | C16: Copilot 營收（M365 cloud 子列） | D16: 座席 × 月費 → M365 cloud↑ | E16: =Seg!H38 -> 24
A17: Seg | B17: glt_*、n_conv | C17: 非命題產品線營收 | D17: 近一年年增收斂到長期值 | E17: =Seg!H56 -> 552.7731
A18: PL | B18: （FY2026 校準）、dm_seg | C18: Agents and Infra 核心利益率、分部營業利益 | D18: 核心利益率 ×（分部 − Azure AI）＋ Azure AI − AI 成本 − AI 折舊 | E18: =PL!H71 -> 196.82255
A19: PL | B19: internal_ai_reading、tax_f、oie_f | C19: 自用 AI 影子效益、淨利、EPS（評價口徑） | D19: 讀法 2：自用 MW × 持有成本（扣 Copilot）進評價口徑營業利益 | E19: =PL!H88 -> 28.491897
A20: CF | B20: sbc_r、wc27、cx_*、fl_pay_*、bb_target、dps_* | C20: 自由現金流、回購、舉債、股數 | D20: 自由現金流扣股利 → 回購（不足先減）→ 舉債 | E20: =CF!H56 -> 70.552903
A21: Val | B21: rf、beta、erp、kd、g_tv、m_*、al_*、w_* | C21: DCF、SOTP（AI 模組 DCF）、加權目標價 | D21: WACC↑ → DCF↓；倍數↑ → SOTP↑ | E21: =Val!$B$36 -> 388.94796
A23: 結果摘要（三情境）
A24: 項目 | B24: 情境 A（樂觀） | C24: 情境 B（基準） | D24: 情境 C（保守） | E24: 說明
A25: 營收 FY2029（US$B） | B25: =Seg!H29 -> 585.22308 | C25: =Seg!H56 -> 552.7731 | D25: =Seg!H83 -> 515.33313
A26: Azure AI 營收 FY2029 | B26: =Thesis!H23 -> 149.78561 | C26: =Thesis!H72 -> 124.83563 | D26: =Thesis!H121 -> 94.895656
A27: Copilot 營收 FY2029 | B27: =Seg!H11 -> 31.5 | C27: =Seg!H38 -> 24 | D27: =Seg!H65 -> 16.5
A28: 營業利益率 FY2029（財報口徑） | B28: =PL!H37 -> 0.42152971 | C28: =PL!H76 -> 0.39334721 | D28: =PL!H115 -> 0.35546832
A29: EPS FY2029（財報口徑，US$） | B29: =PL!H47 -> 26.182083 | C29: =PL!H86 -> 23.011461 | D29: =PL!H125 -> 19.346501
A30: EPS FY2029（評價口徑，US$） | B30: =PL!H49 -> 31.221682 | C30: =PL!H88 -> 28.491897 | D30: =PL!H127 -> 25.270618
A31: 自由現金流 FY2029（財報現金） | B31: =CF!H27 -> 94.524344 | C31: =CF!H56 -> 70.552903 | D31: =CF!H85 -> 42.402925
A32: AI 增量 ROIC FY2029（讀法 2） | B32: =Thesis!H47 -> 0.15232209 | C32: =Thesis!H96 -> 0.10623047 | D32: =Thesis!H145 -> 0.050960142
A33: AI 增量 ROIC FY2029（讀法 1） | B33: =Thesis!H48 -> 0.064879597 | C33: =Thesis!H97 -> 0.010911343 | D33: =Thesis!H146 -> -0.052231994
A35: 情境目標價（US$；讀法 2） | B35: =Val!B44 -> 428.63908 | C35: =Val!C44 -> 390.89987 | D35: =Val!D44 -> 345.353
A37: 與 v0.2.2 的差異：v0.2.2 沿用 CoreWeave 架構（對外 AI MW × 每 MW 收入＋其餘業務成長率線、融資瀑布）；v0.3 改為官方兩分部、八條產品線，命題只驅動 Azure AI 與 Copilot 兩條子列，AI 資本支出經折舊進分部營業利益；評價改 DCF 50%＋SOTP 50%、情境 25／50／25。拆解見 Recon 第 5 節。
A38: 已知限制：AI 在役 MW、對外比例、Copilot 營收與座席歷史、產品線利潤公司皆未揭露（Assumed，給區間）；FY27Q1 財報（2026-10-28）未納入，將以 v0.3.1 滾入；Tokenomics 維持 v21.4。
A39: 建置：python3 microsoft/build_microsoft.py raw.xlsx → soffice --headless --calc --convert-to xlsx → microsoft/dist/；HTML：python3 tools/company_html/build_company_html.py microsoft
A40: 修正一（2026-10-27，獨立核對後）：收支關卡範圍公式誤加 FY2032（改為首年起五年並加核對列）；自用 AI 讀法 2 為主值；DCF 扣股票薪酬、減融資租賃負債、扣期間股利；SOTP 的 AI 腿改用模組 DCF；WACC 改 Blume β、10 年期 kd、負債含融資租賃；FY2029 後 MW 新增速度收斂；汰換時更新在役世代。前後對照見報告「修正一」節。

Sheet In
A1: In — 輸入（藍字＝輸入、黑字＝由其他輸入推得）。基準欄 E，低 D、高 F；金額十億美元（US$B），MW＝IT 關鍵電力。標記：Verified／Interested-party／Analogy／Assumed／Derived；Analogy、Assumed 一律給區間
A2: 「沿用 v0.2.2」＝MAG v0.2.2（2026-10-25，PR #105）已核准的參數與證據，原出處見來源欄；SEC 一手數字取自 microsoft/data/microsoft_facts_20261008.json（v0.1a 起的事實總帳）
A3: 鍵 | B3: 項目 | C3: 單位 | D3: 低 | E3: 基準 | F3: 高 | G3: 標記 | H3: 來源1 | I3: 來源2／說明
A4: A. 股價、股數與資本結構（評價日 2026-06-30＝FY2026 年底；目標價時點＝今日 2026-10-27 後 12 個月）
A5: px | B5: 現價（2026-10-26 收盤） | C5: US$ | E5: 532.6 | G5: Verified | H5: https://stockanalysis.com/stocks/msft/statistics/（2026-10-26 收盤 532.60，+8.09／+1.54%；擷取 2026-10-27） | I5: markets/invest_map/data/prices.csv：2026-10-23 收盤 524.51（stockscan；bullfincher）＋ 10-26 漲 8.09＝532.60，兩來源一致
A6: sh_dil26 | B6: FY2026 稀釋加權股數 | C6: 十億股 | E6: 7.453 | G6: Verified | H6: 事實總帳 microsoft/data/microsoft_facts_20261008.json｜is.sharesDilW.fy2026（10-K FY2026） | I6: DCF 每股（評價日 2026-06-30）的分母
A7: sh_basic26 | B7: FY2026 基本加權股數 | C7: 十億股 | E7: 7.429 | G7: Verified | H7: 事實總帳 microsoft/data/microsoft_facts_20261008.json｜is.sharesBasicW.fy2026 | I7: —
A8: dil_gap | B8: 稀釋與基本股數差 | C8: 十億股 | E8: =sh_dil26-sh_basic26 -> 0.024 | G8: Derived | H8: FY2026 稀釋 − 基本 | I8: 預測期稀釋股數＝期間平均流通股數＋此差額
A9: sh_out26 | B9: 流通股數（2026-06-30） | C9: 十億股 | E9: 7.427 | G9: Verified | H9: 事實總帳 microsoft/data/microsoft_facts_20261008.json｜sh.out.fy2026（10-K 附註 15） | I9: —
A10: cash_open | B10: 現金與短期投資（2026-06-30） | C10: US$B | E10: 76.843 | G10: Verified | H10: 事實總帳 microsoft/data/microsoft_facts_20261008.json｜bs.cashSti.fy2026 | I10: —
A11: debt_face | B11: 債務面額（2026-06-30） | C11: US$B | E11: 46.136 | G11: Verified | H11: 事實總帳 microsoft/data/microsoft_facts_20261008.json｜debt.face.fy2026（附註 10） | I11: 帳面值 40.294；WACC 與淨現金用面額
A12: debt_mat_27 | B12: 債務到期 FY2027 | C12: US$B | E12: 9.25 | G12: Verified | H12: 事實總帳 microsoft/data/microsoft_facts_20261008.json｜debt.maturity.fy2027（附註 10 到期表） | I12: —
A13: debt_mat_28 | B13: 債務到期 FY2028 | C13: US$B | E13: 0 | G13: Verified | H13: 事實總帳 microsoft/data/microsoft_facts_20261008.json｜debt.maturity.fy2028（附註 10 到期表） | I13: —
A14: debt_mat_29 | B14: 債務到期 FY2029 | C14: US$B | E14: 2.001 | G14: Verified | H14: 事實總帳 microsoft/data/microsoft_facts_20261008.json｜debt.maturity.fy2029（附註 10 到期表） | I14: —
A15: debt_mat_30 | B15: 債務到期 FY2030 | C15: US$B | E15: 0 | G15: Verified | H15: 事實總帳 microsoft/data/microsoft_facts_20261008.json｜debt.maturity.fy2030（附註 10 到期表） | I15: —
A16: debt_mat_31 | B16: 債務到期 FY2031 | C16: US$B | E16: 0.5 | G16: Verified | H16: 事實總帳 microsoft/data/microsoft_facts_20261008.json｜debt.maturity.fy2031（附註 10 到期表） | I16: —
A17: debt_mat_32 | B17: 債務到期 FY2032 | C17: US$B | E17: 0 | G17: Assumed | H17: 事實總帳 microsoft/data/microsoft_facts_20261008.json｜到期表只列 FY2031 以後合計 34.385；FY2032 取 0 | I17: —
A18: fl_liab | B18: 融資租賃負債（2026-06-30，在帳） | C18: US$B | E18: 66.594 | G18: Verified | H18: 事實總帳 microsoft/data/microsoft_facts_20261008.json｜lease.finLiab.fy2026（附註 13） | I18: 在帳融資租賃的資產已在過去的資本支出（公司口徑）內，其本金在預測期照付（CF 頁）
A19: fl_rate | B19: 融資租賃加權利率 | C19: % | E19: 0.045 | G19: Verified | H19: 事實總帳 microsoft/data/microsoft_facts_20261008.json｜lease.wtdRate.fin | I19: —
A20: fl_pay_27 | B20: 在帳融資租賃付款 FY2027（未折現，含息） | C20: US$B | E20: 7.121 | G20: Verified | H20: 事實總帳 microsoft/data/microsoft_facts_20261008.json｜lease.maturity.fin.fy2027 | I20: —
... A24: fl_pay_31 | B24: 在帳融資租賃付款 FY2031（未折現，含息） | C24: US$B | E24: 6.543 | G24: Verified | H24: 事實總帳 microsoft/data/microsoft_facts_20261008.json｜lease.maturity.fin.fy2031 | I24: —
A25: fl_pay_32 | B25: 在帳融資租賃付款 FY2032（未折現，含息） | C25: US$B | E25: =fl_pay_31 -> 6.543 | G25: Assumed | H25: 事實總帳 microsoft/data/microsoft_facts_20261008.json｜FY2032 比照 FY2031（之後合計 55.490 分多年） | I25: —
A26: min_cash | B26: 最低現金 | C26: US$B | D26: 30 | E26: 50 | F26: 70 | G26: Assumed | H26: 沿用 v0.2.2（microsoft/legacy_v0.2/company.json；交接檔 docs/handoff/20261025_Microsoft收支模型_交接檔_v0_2_2.md）（defaults.minCash 50） | I26: 低於此水準先停回購、再舉債
A27: bb_target | B27: 回購目標（每年） | C27: US$B | E27: 22.271 | G27: Verified | H27: 事實總帳 microsoft/data/microsoft_facts_20261008.json｜cf.buyback.fy2026（含員工扣稅買回 5.6） | I27: 現金不足時先減回購
A28: bb_g | B28: 回購價格年增（以現價起算） | C28: % | D28: 0 | E28: 0.08 | F28: 0.12 | G28: Assumed | H28: 無：約等於股東權益成本扣股利率 | I28: 只影響股數
A29: sh_iss | B29: 員工股票發行（每年） | C29: 十億股 | D29: 0.035 | E29: 0.045 | F29: 0.055 | G29: Derived | H29: 事實總帳 microsoft/data/microsoft_facts_20261008.json｜FY2026 回購約 0.048 十億股（計畫 0.036＋扣稅買回 5.6 ÷ 約 470 美元），基本加權股數 7.433 → 7.429 幾乎不變 → 發行約 0.045 | I29: 低／高 Assumed
A30: dps_q0 | B30: 每季股利（FY2027 第一季付，舊額） | C30: US$ | E30: 0.91 | G30: Verified | H30: 事實總帳 microsoft/data/microsoft_facts_20261008.json｜sh.dps.fy2026（每季 0.91） | I30: —
A31: dps_q1 | B31: 每季股利（2026-09-15 宣告，新額） | C31: US$ | E31: 0.98 | G31: Interested-party | H31: 事實總帳 microsoft/data/microsoft_facts_20261008.json｜sh.dpsQ.fy27q1 | I31: —
A32: dps_27 | B32: FY2027 每股股利（付現） | C32: US$ | E32: =dps_q0+3*dps_q1 -> 3.85 | G32: Derived | H32: 第一季付舊額、其後三季付新額 | I32: —
A33: dps_g | B33: 每股股利年增（FY2028 起） | C33: % | D33: 0.05 | E33: 0.08 | F33: 0.1 | G33: Interested-party | H33: 沿用 v0.2.2（microsoft/legacy_v0.2/company.json；交接檔 docs/handoff/20261025_Microsoft收支模型_交接檔_v0_2_2.md）（defaults.dividend.growth；2026-09 宣告 +8%） | I33: —
A34: B. 折現率與評價參數（WACC 沿用 v0.2.2 的 CAPM 輸入；權重為 [判斷] 預設，Andy 可改）
A35: rf | B35: 無風險利率（10 年美債，2026-10-26） | C35: % | E35: 0.05 | G35: Verified | H35: U.S. Treasury 10 年期殖利率 2026-10-26：5.00%（修正一：chat 端統一 MAG＋Oracle 個股模型的同一輸入，與 Amazon v0.3 相同） | I35: 事實總帳 microsoft/data/microsoft_facts_20261008.json｜val.ust10：2026-10-07 為 5.28%（v0.2.2 與 v0.3 初版）
A36: beta_sa | B36: 原始 β：StockAnalysis（5 年月資料；Yahoo 同值，推測同源，算 1 個） | C36: x | E36: 1.1 | G36: Verified | H36: 事實總帳 microsoft/data/microsoft_facts_20261008.json｜val.beta.sa（2026-10-08） | I36: C13：獨立來源
A37: beta_gf | B37: 原始 β：GuruFocus（3 年） | C37: x | E37: 1.1741 | G37: Verified | H37: 事實總帳 microsoft/data/microsoft_facts_20261008.json｜val.beta.gurufocus（2026-10-08） | I37: C13：獨立來源
A38: blume_w | B38: Blume 調整：原始 β 權重（其餘向 1 收斂） | C38: x | E38: 0.67 | G38: Assumed | H38: 共同修正工作單 F4（2026-10-27）：0.67 × 原始 β＋0.33 | I38: —
A39: beta | B39: β（兩個獨立來源 Blume 調整後的中位數） | C39: x | D39: 0.95 | E39: =MEDIAN(blume_w*beta_sa+(1-blume_w),blume_w*beta_gf+(1-blume_w)) -> 1.0918235 | F39: 1.174 | G39: Derived | H39: Blume：1.10 → 1.067、1.1741 → 1.117；中位數 1.092（修正一；v0.3 初版用原始平均 1.137） | I39: 低 0.95＝獨立核對建議區間下緣；高＝原始 GuruFocus
A40: erp | B40: 股權風險溢酬 | C40: % | D40: 0.04 | E40: 0.05 | F40: 0.06 | G40: Assumed | H40: MAG 對照表 r1 5.10（判斷，列敏感度） | I40: 沿用 v0.2.2（microsoft/legacy_v0.2/company.json；交接檔 docs/handoff/20261025_Microsoft收支模型_交接檔_v0_2_2.md）
A41: kd_aaa | B41: 對照：Moody's Aaa 公司債殖利率（長天期） | C41: % | E41: 0.0626 | G41: Analogy | H41: 事實總帳 microsoft/data/microsoft_facts_20261008.json｜val.kd.aaa（FRED DAAA 2026-10-06） | I41: v0.3 初版 kd；Aaa 指數為 20 年以上長債，修正一改用約 10 年期
A42: kd_spread | B42: 約 10 年期 AAA 公司債對美債利差 | C42: pt | D42: 0.003 | E42: 0.006 | F42: 0.009 | G42: Assumed | H42: 無：MSFT 個別債券殖利率找不到；AAA 10 年期利差歷史約 0.3–0.9 個百分點 | I42: kd＝rf＋利差（修正一 F4）
A43: kd | B43: 稅前債務成本（約 10 年期公司債） | C43: % | E43: =rf+kd_spread -> 0.056 | G43: Derived | H43: rf（10 年美債）＋利差 | I43: —
A44: tax_w | B44: WACC 用稅率 | C44: % | E44: 0.2 | G44: Interested-party | H44: 事實總帳 microsoft/data/microsoft_facts_20261008.json｜guid.fy27.etr（FY2027 指引約 20%） | I44: —
A45: ke | B45: 股東權益成本（CAPM） | C45: % | E45: =rf+beta*erp -> 0.10459117 | G45: Derived | H45: rf ＋ β × ERP | I45: —
A46: wacc | B46: WACC | C46: % | E46: =(px*sh_out26*ke+(debt_face+fl_liab)*kd*(1-tax_w))/(px*sh_out26+debt_face+fl_liab) -> 0.10293442 | G46: Derived | H46: E／(D＋E) × ke ＋ D／(D＋E) × kd ×（1 − 稅率）；E＝現價 × 流通股數、D＝債務面額＋在帳融資租賃負債（修正一 F4） | I46: v0.2.2 10.90%；v0.3 初版 10.90%
A47: g_tv | B47: 永續成長率（FY2032 後） | C47: % | D47: 0.02 | E47: 0.03 | F47: 0.04 | G47: Assumed | H47: 工作單 20261027 第 2 節：g 3% | I47: Sens ±1pt
A48: ronic_prem | B48: 永續期新投資報酬 − WACC | C48: pt | D48: -0.02 | E48: 0 | F48: 0.05 | G48: Assumed | H48: 無：永續期新投資只賺資金成本（成長不創造價值） | I48: 永續期自由現金流＝NOPAT ×（1 − g ÷ 新投資報酬）；替代口徑（FY2032 自由現金流 ×（1＋g））見 Sens 判斷預設表
A49: base_fy | B49: 評價日所屬會計年度（最新已申報年度） | C49: 年 | E49: 2026 | G49: Verified | H49: FY2026 10-K（期末 2026-06-30） | I49: 公式中的年數以「年度列 − base_fy」計算（修正一 F6：不寫死）
A50: mid_yr | B50: 期中折現：年中偏移 | C50: 年 | E50: 0.5 | G50: Assumed | H50: 現金流平均發生在年中 | I50: —
A51: roll_d1 | B51: 評價日（2026-06-30） | C51: 日期 | E51: =DATE(2026,6,30) -> 46203 | G51: Verified | H51: FY2026 年底 | I51: —
A52: roll_d2 | B52: 目標價時點（今日 2026-10-27 後 12 個月） | C52: 日期 | E52: =DATE(2027,10,27) -> 46687 | G52: Assumed | H52: 工作單：目標價約 12 個月後 | I52: —
A53: days_yr | B53: 每年天數 | C53: 天 | E53: 365 | G53: Assumed | H53: — | I53: —
A54: t_roll | B54: 評價日 → 目標價時點（年） | C54: 年 | E54: =(roll_d2-roll_d1)/days_yr -> 1.3260274 | G54: Derived | H54: 2026-06-30 → 2027-10-27 | I54: DCF 每股以 WACC 推到目標價時點（已決定事項 12 沿用），並扣除期間股利（修正一 F6）
A55: roll_div_q | B55: 評價日到目標價時點之間、FY2028 已付的股利季數 | C55: 季 | E55: 1 | G55: Derived | H55: FY2028 第一季股利約 2027-09 支付，早於 2027-10-27 | I55: —
A56: q_per_yr | B56: 每年季數 | C56: 季 | E56: 4 | G56: Verified | H56: — | I56: —
A57: fy28_end | B57: FY2028 年底 | C57: 日期 | E57: =DATE(2028,6,30) -> 46934 | G57: Verified | H57: 財年 6 月結束 | I57: —
A58: w_ntm28 | B58: 目標價時點的未來 12 個月中 FY2028 的比重 | C58: x | E58: =(fy28_end-roll_d2)/days_yr -> 0.67671233 | G58: Derived | H58: 2027-10-27 起 12 個月：FY2028 約 0.68、FY2029 約 0.32 | I58: SOTP 用 NTM EBITDA
A59: w_dcf | B59: 目標價中 DCF 的權重（其餘為分部加總 SOTP） | C59: % | D59: 0.3 | E59: 0.5 | F59: 0.7 | G59: Assumed | H59: [判斷] 預設：工作單 20261027 第 2 節（與 AI半導體 DCF＋Comparable 各半一致；Comparable 在分部層做） | I59: Andy 可改
A60: w_A | B60: 情境權重 A | C60: % | E60: 0.25 | G60: Assumed | H60: [判斷] 預設：工作單 20261027 第 2 節 A 25%／B 50%／C 25% | I60: Andy 可改
A61: w_B | B61: 情境權重 B | C61: % | E61: 0.5 | G61: Assumed | H61: [判斷] 預設：工作單 20261027 第 2 節 A 25%／B 50%／C 25% | I61: Andy 可改
A62: w_C | B62: 情境權重 C | C62: % | E62: 0.25 | G62: Assumed | H62: [判斷] 預設：工作單 20261027 第 2 節 A 25%／B 50%／C 25% | I62: Andy 可改
A63: oai_stake | B63: OpenAI 持股比例 | C63: % | E63: 0.25 | F63: 0.27 | G63: Verified | H63: 事實總帳 microsoft/data/microsoft_facts_20261008.json｜oai.stake.fy2026（10-K FY2026 附註 1：approximate 25%，經查核，最新） | I63: oai.stake.recap：重組時（2025-10-28）約 27%（10-Q FY26Q1）；10-K 稱其後因其他籌資稀釋降到約 25%。修正一維持最新查核值 25%，27% 列判斷替代
A64: oai_val | B64: OpenAI 最近一輪投後估值 | C64: US$B | E64: 852 | G64: Interested-party | H64: 事實總帳 microsoft/data/microsoft_facts_20261008.json｜oai.valuation（2026-03 結案，募資 122） | I64: 新創自報估值
A65: liq_disc | B65: 未上市持股流動性折價 | C65: % | D65: 0 | E65: 0.2 | F65: 0.4 | G65: Assumed | H65: 工作單 20261027：20% | I65: 沿用 v0.2.2（microsoft/legacy_v0.2/company.json；交接檔 docs/handoff/20261025_Microsoft收支模型_交接檔_v0_2_2.md）
A66: oai_v | B66: OpenAI 持股價值（扣折價） | C66: US$B | E66: =oai_stake*oai_val*(1-liq_disc) -> 170.4 | G66: Derived | H66: 比例 × 估值 ×（1 − 折價） | I66: Anthropic 持股比例未揭露 → 不估值（資料缺口）
A67: m_ai | B67: Azure AI 倍數（EV／NTM EBITDA） | C67: x | D67: 4 | E67: 6 | F67: 10 | G67: Assumed | H67: 沿用 v0.2.2（microsoft/legacy_v0.2/company.json；交接檔 docs/handoff/20261025_Microsoft收支模型_交接檔_v0_2_2.md）（valuation.evEbitda 6×） | I67: AI 基礎設施租賃同業（CRWV TTM 25×、NBIS 不具意義、ORCL NTM 9.5×）口徑不一，沿用 v0.2.2
A68: m_cloud | B68: 非 AI 雲端倍數（Azure 其他） | C68: x | E68: 13.82 | G68: Derived | H68: microsoft/data/peers_cloud_20261008.json：ORCL、IBM、SAP、CRM、NOW、AKAM、EQIX、DOCN 中位數（C12） | I68: 2026-10-07 收盤
A69: m_sw | B69: 企業軟體倍數（M365 cloud、授權、產業、Frontier） | C69: x | E69: 10.8 | G69: Derived | H69: 事實總帳 microsoft/data/microsoft_facts_20261008.json｜val.peer.sw.*：ORCL 9.54、SAP 15.02、CRM 10.80、ADBE 6.60、NOW 20.65 中位數（不含 MSFT） | I69: 2026-10-07
A70: m_ads | B70: 數位廣告倍數（Search and advertising） | C70: x | E70: 9.11 | G70: Derived | H70: microsoft/data/peers_ads_20261009.json：META、PINS、TTD、APP、RDDT、SNAP 中位數（C18） | I70: 2026-10-07
A71: m_game | B71: 遊戲倍數（XBOX） | C71: x | E71: 12.63 | G71: Derived | H71: 事實總帳 microsoft/data/microsoft_facts_20261008.json｜val.peer.game.*：TTWO 50.9、NTDOY 12.63、NTES 8.23 中位數（TTM；NTM 找不到） | I71: 2026-10-08
A72: m_pc | B72: PC／裝置倍數（Windows OEM and devices） | C72: x | E72: 14.47 | G72: Derived | H72: 事實總帳 microsoft/data/microsoft_facts_20261008.json｜val.peer.pc.*：HPQ 7.6、DELL 22.1、Lenovo 14.47 中位數（TTM） | I72: 2026-10-08
A73: m_own | B73: Microsoft 自身 NTM EV／EBITDA（對照） | C73: x | E73: 15.67 | G73: Derived | H73: 事實總帳 microsoft/data/microsoft_facts_20261008.json｜val.msft.ownNtm（2026-10-07） | I73: 只用於判斷預設替代（非 AI 各線改用自身倍數）
A74: al_m365 | B74: 產品線營業利益率分配：Microsoft 365 cloud（SOTP 用） | C74: % | D74: 0.5 | E74: 0.6 | F74: 0.7 | G74: Assumed | H74: 事實總帳 microsoft/data/microsoft_facts_20261008.json｜alloc.oiMargin（公司不揭露產品線利潤）；沿用 v0.2.2（microsoft/legacy_v0.2/company.json；交接檔 docs/handoff/20261025_Microsoft收支模型_交接檔_v0_2_2.md） | I74: 舊 PBP 分部 FY2026 59.9% 類比；Azure 其他、XBOX＋Windows 為分部殘差
A75: al_lic | B75: 產品線營業利益率分配：Productivity and server licensing（SOTP 用） | C75: % | D75: 0.65 | E75: 0.75 | F75: 0.85 | G75: Assumed | H75: 事實總帳 microsoft/data/microsoft_facts_20261008.json｜alloc.oiMargin（公司不揭露產品線利潤）；沿用 v0.2.2（microsoft/legacy_v0.2/company.json；交接檔 docs/handoff/20261025_Microsoft收支模型_交接檔_v0_2_2.md） | I75: 地端授權毛利高、銷售費用低；Azure 其他、XBOX＋Windows 為分部殘差
A76: al_ind | B76: 產品線營業利益率分配：Industry solutions（SOTP 用） | C76: % | D76: 0.2 | E76: 0.3 | F76: 0.4 | G76: Assumed | H76: 事實總帳 microsoft/data/microsoft_facts_20261008.json｜alloc.oiMargin（公司不揭露產品線利潤）；沿用 v0.2.2（microsoft/legacy_v0.2/company.json；交接檔 docs/handoff/20261025_Microsoft收支模型_交接檔_v0_2_2.md） | I76: 含 Dynamics、LinkedIn 等；Azure 其他、XBOX＋Windows 為分部殘差
A77: al_fro | B77: 產品線營業利益率分配：Frontier and support services（SOTP 用） | C77: % | D77: 0.2 | E77: 0.3 | F77: 0.4 | G77: Assumed | H77: 事實總帳 microsoft/data/microsoft_facts_20261008.json｜alloc.oiMargin（公司不揭露產品線利潤）；沿用 v0.2.2（microsoft/legacy_v0.2/company.json；交接檔 docs/handoff/20261025_Microsoft收支模型_交接檔_v0_2_2.md） | I77: 含支援服務；Azure 其他、XBOX＋Windows 為分部殘差
A78: al_srch | B78: 產品線營業利益率分配：Search and advertising（SOTP 用） | C78: % | D78: 0.2 | E78: 0.3 | F78: 0.4 | G78: Assumed | H78: 事實總帳 microsoft/data/microsoft_facts_20261008.json｜alloc.oiMargin（公司不揭露產品線利潤）；沿用 v0.2.2（microsoft/legacy_v0.2/company.json；交接檔 docs/handoff/20261025_Microsoft收支模型_交接檔_v0_2_2.md） | I78: —；Azure 其他、XBOX＋Windows 為分部殘差
A79: C. Tokenomics v21.4 快照（microsoft/data/tokenomics_snapshot_v21.4.json；基準成本欄；每 GW＝IT 關鍵電力；沿用 v0.2.2，本版不升級）
A80: tk_hold_h100 | B80: IF_HoldEcon｜Hopper H100（每 MW 年持有成本，WACC 10% 打平） | C80: US$M/MW-年 | E80: 9.7030873 | G80: Derived | H80: Tokenomics v21.4（20261024_Tokenomics_v21.4.xlsx，master 3ac70ac） | I80: 基準成本欄
A81: tk_hold_gb200 | B81: IF_HoldEcon｜GB200 NVL72（每 MW 年持有成本，WACC 10% 打平） | C81: US$M/MW-年 | E81: 8.8281656 | G81: Derived | H81: Tokenomics v21.4（20261024_Tokenomics_v21.4.xlsx，master 3ac70ac） | I81: 基準成本欄
A82: tk_hold_gb300 | B82: IF_HoldEcon｜GB300 NVL72（每 MW 年持有成本，WACC 10% 打平） | C82: US$M/MW-年 | E82: 10.886411 | G82: Derived | H82: Tokenomics v21.4（20261024_Tokenomics_v21.4.xlsx，master 3ac70ac） | I82: 基準成本欄
A83: tk_hold_vr200 | B83: IF_HoldEcon｜VR200 NVL72（每 MW 年持有成本，WACC 10% 打平） | C83: US$M/MW-年 | E83: 12.225471 | G83: Derived | H83: Tokenomics v21.4（20261024_Tokenomics_v21.4.xlsx，master 3ac70ac） | I83: 基準成本欄
A84: tk_cxit_h100 | B84: IF_CapexIT｜Hopper H100（每 MW IT 資本支出） | C84: US$M/MW | E84: 27.510214 | G84: Derived | H84: Tokenomics v21.4（20261024_Tokenomics_v21.4.xlsx，master 3ac70ac） | I84: —
A85: tk_cxit_gb200 | B85: IF_CapexIT｜GB200 NVL72（每 MW IT 資本支出） | C85: US$M/MW | E85: 24.015174 | G85: Derived | H85: Tokenomics v21.4（20261024_Tokenomics_v21.4.xlsx，master 3ac70ac） | I85: —
A86: tk_cxit_gb300 | B86: IF_CapexIT｜GB300 NVL72（每 MW IT 資本支出） | C86: US$M/MW | E86: 32.237224 | G86: Derived | H86: Tokenomics v21.4（20261024_Tokenomics_v21.4.xlsx，master 3ac70ac） | I86: —
A87: tk_cxit_vr200 | B87: IF_CapexIT｜VR200 NVL72（每 MW IT 資本支出） | C87: US$M/MW | E87: 37.586352 | G87: Derived | H87: Tokenomics v21.4（20261024_Tokenomics_v21.4.xlsx，master 3ac70ac） | I87: —
A88: tk_opex_h100 | B88: IF_OpexGW｜Hopper H100（每 MW 年營運成本） | C88: US$M/MW-年 | E88: 1.8846675 | G88: Derived | H88: Tokenomics v21.4（20261024_Tokenomics_v21.4.xlsx，master 3ac70ac） | I88: 電力、維護、人員、稅保
A89: tk_opex_gb200 | B89: IF_OpexGW｜GB200 NVL72（每 MW 年營運成本） | C89: US$M/MW-年 | E89: 1.8122327 | G89: Derived | H89: Tokenomics v21.4（20261024_Tokenomics_v21.4.xlsx，master 3ac70ac） | I89: 電力、維護、人員、稅保
A90: tk_opex_gb300 | B90: IF_OpexGW｜GB300 NVL72（每 MW 年營運成本） | C90: US$M/MW-年 | E90: 1.9826348 | G90: Derived | H90: Tokenomics v21.4（20261024_Tokenomics_v21.4.xlsx，master 3ac70ac） | I90: 電力、維護、人員、稅保
A91: tk_opex_vr200 | B91: IF_OpexGW｜VR200 NVL72（每 MW 年營運成本） | C91: US$M/MW-年 | E91: 2.0934955 | G91: Derived | H91: Tokenomics v21.4（20261024_Tokenomics_v21.4.xlsx，master 3ac70ac） | I91: 電力、維護、人員、稅保
... A93: tk_gpuhr_h100 | B93: IF_GPUhrEcon｜Hopper H100（每 GPU 小時打平價） | C93: US$/GPU-hr | E93: 1.5425965 | G93: Derived | H93: Tokenomics v21.4（20261024_Tokenomics_v21.4.xlsx，master 3ac70ac） | I93: k_現貨的分母
A94: life_it | B94: AI IT 折舊年限（IF_DeprLifeIT） | C94: 年 | D94: 5 | E94: 6 | F94: 7 | G94: Derived | H94: Tokenomics v21.4（20261024_Tokenomics_v21.4.xlsx，master 3ac70ac）；10-K 伺服器與網路設備 2–6 年（pl.usefulLife.servers） | I94: Sens ±1 年
A95: life_fac | B95: 機房折舊年限 | C95: 年 | E95: 20 | G95: Derived | H95: Tokenomics v21.4（20261024_Tokenomics_v21.4.xlsx，master 3ac70ac）（IF_CapexFacility ÷ IF_DeprFac＝20） | I95: 公司 FY2027 起建物 15 → 25 年（guid.usefulLife）
A96: fac_wacc | B96: 機房租金年金折現率（Tokenomics 經濟 WACC） | C96: % | E96: 0.1 | G96: Derived | H96: 沿用 v0.2.2（microsoft/legacy_v0.2/company.json；交接檔 docs/handoff/20261025_Microsoft收支模型_交接檔_v0_2_2.md）（tokenomics.holdEconWacc：Tokenomics Inputs!E28 基準 10%） | I96: 與 IF_HoldEcon 同一折現率
A97: fac_rent | B97: 租用機房每 MW 年租金（資本回收年金） | C97: US$M/MW-年 | E97: =tk_cxfac*fac_wacc/(1-(1+fac_wacc)^(-life_fac)) -> 1.4882134 | G97: Derived | H97: IF_CapexFacility × 年金因子（fac_wacc、機房年限） | I97: C22：租用機房的租金計入 AI 營運成本
A98: D. 命題模組：AI MW、對外比例、k（沿用 v0.2.2；不以 Azure 營收、RPO、AI run-rate 反推）
A99: mw_ext_24 | B99: 在役對外 AI MW（FY2024 年底，含租用） | C99: MW | E99: 640 | G99: Derived | H99: 沿用 v0.2.2（microsoft/legacy_v0.2/company.json；交接檔 docs/handoff/20261025_Microsoft收支模型_交接檔_v0_2_2.md）｜v0.2.2 defaults.mwYearEnd | I99: 公司未揭露 AI 在役 MW（不存在）
A100: mw_ext_25 | B100: 在役對外 AI MW（FY2025 年底，含租用） | C100: MW | E100: 1630 | G100: Derived | H100: 沿用 v0.2.2（microsoft/legacy_v0.2/company.json；交接檔 docs/handoff/20261025_Microsoft收支模型_交接檔_v0_2_2.md）｜v0.2.2 defaults.mwYearEnd | I100: 公司未揭露 AI 在役 MW（不存在）
A101: mw_ext_26 | B101: 在役對外 AI MW（FY2026 年底，含租用） | C101: MW | D101: 2150 | E101: 3250 | F101: 4875 | G101: Derived | H101: 沿用 v0.2.2（microsoft/legacy_v0.2/company.json；交接檔 docs/handoff/20261025_Microsoft收支模型_交接檔_v0_2_2.md）｜三法交叉：自有在役 AI 4,500 × 對外 60%＋neocloud 租用 1,100 × 50%（split.extMW） | I101: 公司未揭露 AI 在役 MW（不存在）
A102: rent_ext_24 | B102: 其中租用 neocloud 的對外 AI MW（FY2024 年底） | C102: MW | E102: 150 | G102: Assumed | H102: 無：CoreWeave 2024、2025 營收約 62%–67% 來自 Microsoft（nc.crwv.*）推估 | I102: 租用 MW 收入照算，不計資本支出與折舊（C20）
A103: rent_ext_25 | B103: 其中租用 neocloud 的對外 AI MW（FY2025 年底） | C103: MW | E103: 400 | G103: Assumed | H103: 無：CoreWeave 2024、2025 營收約 62%–67% 來自 Microsoft（nc.crwv.*）推估 | I103: 租用 MW 收入照算，不計資本支出與折舊（C20）
A104: rent_ext_26 | B104: 其中租用 neocloud 的對外 AI MW（FY2026 年底） | C104: MW | E104: 550 | G104: Derived | H104: 沿用 v0.2.2（microsoft/legacy_v0.2/company.json；交接檔 docs/handoff/20261025_Microsoft收支模型_交接檔_v0_2_2.md）（capexModel.rentedExt：期初 550＝neocloud 在役 1,100 × 對外 50%） | I104: 租用 MW 收入照算，不計資本支出與折舊（C20）
...

Sheet Q
A1: Q — 實績（十億美元）。分部與產品線為 FY2027 起的報導口徑（8-K 2026-09-02「Segment History／Products and Service Offerings — As Restated」，未經查核）；合併損益、現金流量取自 10-K／財報新聞稿（事實總帳）
A2: J、K 欄＝四季合計（公式）；L、M 欄＝公司揭露的年度值（輸入）；核對列實績必須為 0。舊三分部（PBP／IC／MPC）列在下方對照（FY2026 以前口徑）
A3: 項目 | B3: FY25Q1（～2024-09） | C3: FY25Q2（～12） | D3: FY25Q3（～2025-03） | E3: FY25Q4（～06） | F3: FY26Q1（～2025-09） | G3: FY26Q2（～12） | H3: FY26Q3（～2026-03） | I3: FY26Q4（～06） | J3: FY2025（四季合計） | K3: FY2026（四季合計） | L3: FY2025（公司年度值） | M3: FY2026（公司年度值） | N3: 標記 | O3: 來源（事實總帳 id）
A4: 1. 官方分部與產品線營收（FY2027 起報導口徑）
A5: Agents and Infra | B5: 50.476 | C5: 52.766 | D5: 54.763 | E5: 60.778 | F5: 61.672 | G5: 64.441 | H5: 67.438 | I5: 74.576 | J5: =SUM(B5:E5) -> 218.783 | K5: =SUM(F5:I5) -> 268.127 | L5: 218.783 | M5: 268.127 | N5: Verified | O5: 8-K 2026-09-02 附件 99.1（As Restated）｜q.seg27.ai.rev.*、seg27.ai.rev.*
A6: Azure | B6: 16.021 | C6: 17.337 | D6: 18.54 | E6: 20.712 | F6: 22.384 | G6: 24.129 | H6: 26.008 | I6: 29.417 | J6: =SUM(B6:E6) -> 72.61 | K6: =SUM(F6:I6) -> 101.938 | L6: 72.61 | M6: 101.938 | N6: Verified | O6: 8-K 2026-09-02 附件 99.1（As Restated）｜q.prod27.azure.*
A7: Microsoft 365 cloud | B7: 20.017 | C7: 20.686 | D7: 20.967 | E7: 22.935 | F7: 23.694 | G7: 24.466 | H7: 25.418 | I7: 26.721 | J7: =SUM(B7:E7) -> 84.605 | K7: =SUM(F7:I7) -> 100.299 | L7: 84.605 | M7: 100.299 | N7: Verified | O7: 8-K 2026-09-02 附件 99.1（As Restated）｜q.prod27.m365cloud.*
A8: Productivity and server licensing | B8: 8.051 | C8: 8.307 | D8: 8.731 | E8: 10.302 | F8: 8.678 | G8: 8.814 | H8: 8.76 | I8: 11.033 | J8: =SUM(B8:E8) -> 35.391 | K8: =SUM(F8:I8) -> 37.285 | L8: 35.391 | M8: 37.285 | N8: Verified | O8: 8-K 2026-09-02 附件 99.1（As Restated）｜q.prod27.licensing.*
A9: Industry solutions | B9: 4.459 | C9: 4.544 | D9: 4.579 | E9: 4.835 | F9: 4.894 | G9: 4.994 | H9: 5.165 | I9: 5.292 | J9: =SUM(B9:E9) -> 18.417 | K9: =SUM(F9:I9) -> 20.345 | L9: 18.417 | M9: 20.345 | N9: Verified | O9: 8-K 2026-09-02 附件 99.1（As Restated）｜q.prod27.industry.*
A10: Frontier and support services | B10: 1.928 | C10: 1.892 | D10: 1.946 | E10: 1.994 | F10: 2.022 | G10: 2.038 | H10: 2.087 | I10: 2.113 | J10: =SUM(B10:E10) -> 7.76 | K10: =SUM(F10:I10) -> 8.26 | L10: 7.76 | M10: 8.26 | N10: Verified | O10: 8-K 2026-09-02 附件 99.1（As Restated）｜q.prod27.frontier.*
A11: 檢查：Agents and Infra 產品線合計 − 分部 | B11: =SUM(B6:B10)-B5 -> 0 | C11: =SUM(C6:C10)-C5 -> 0 | D11: =SUM(D6:D10)-D5 -> 0 | E11: =SUM(E6:E10)-E5 -> 0 | F11: =SUM(F6:F10)-F5 -> 0 | G11: =SUM(G6:G10)-G5 -> 0 | H11: =SUM(H6:H10)-H5 -> 0 | I11: =SUM(I6:I10)-I5 -> 0 | ... M11: =SUM(M6:M10)-M5 -> 0 | N11: 核對
A12: Devices and Consumer | B12: 15.109 | C12: 16.866 | D12: 15.303 | E12: 15.663 | F12: 16.001 | G12: 16.832 | H12: 15.448 | I12: 15.431 | J12: =SUM(B12:E12) -> 62.941 | K12: =SUM(F12:I12) -> 63.712 | L12: 62.941 | M12: 63.712 | N12: Verified | O12: 8-K 2026-09-02 附件 99.1（As Restated）｜q.seg27.dc.rev.*
A13: Search and advertising | B13: 5.159 | C13: 5.773 | D13: 5.437 | E13: 5.802 | F13: 5.942 | G13: 6.393 | H13: 6.065 | I13: 6.435 | J13: =SUM(B13:E13) -> 22.171 | K13: =SUM(F13:I13) -> 24.835 | L13: 22.171 | M13: 24.835 | N13: Verified | O13: 8-K 2026-09-02 附件 99.1（As Restated）｜q.prod27.searchads.*
A14: XBOX | B14: 5.621 | C14: 6.581 | D14: 5.721 | E14: 5.532 | F14: 5.508 | G14: 5.958 | H14: 5.341 | I14: 4.983 | J14: =SUM(B14:E14) -> 23.455 | K14: =SUM(F14:I14) -> 21.79 | L14: 23.455 | M14: 21.79 | N14: Verified | O14: 8-K 2026-09-02 附件 99.1（As Restated）｜q.prod27.xbox.*
A15: Windows OEM and devices | B15: 4.329 | C15: 4.512 | D15: 4.145 | E15: 4.329 | F15: 4.551 | G15: 4.481 | H15: 4.042 | I15: 4.013 | J15: =SUM(B15:E15) -> 17.315 | K15: =SUM(F15:I15) -> 17.087 | L15: 17.315 | M15: 17.087 | N15: Verified | O15: 8-K 2026-09-02 附件 99.1（As Restated）｜q.prod27.windows.*
A16: 檢查：Devices and Consumer 產品線合計 − 分部 | B16: =SUM(B13:B15)-B12 -> 0 | C16: =SUM(C13:C15)-C12 -> 0 | D16: =SUM(D13:D15)-D12 -> 0 | E16: =SUM(E13:E15)-E12 -> 0 | F16: =SUM(F13:F15)-F12 -> 0 | G16: =SUM(G13:G15)-G12 -> 0 | H16: =SUM(H13:H15)-H12 -> 0 | I16: =SUM(I13:I15)-I12 -> 0 | ... M16: =SUM(M13:M15)-M12 -> 0 | N16: 核對
A17: 分部合計（營收） | B17: =B5+B12 -> 65.585 | C17: =C5+C12 -> 69.632 | D17: =D5+D12 -> 70.066 | E17: =E5+E12 -> 76.441 | F17: =F5+F12 -> 77.673 | G17: =G5+G12 -> 81.273 | H17: =H5+H12 -> 82.886 | I17: =I5+I12 -> 90.007 | J17: =SUM(B17:E17) -> 281.724 | K17: =SUM(F17:I17) -> 331.839 | L17: =L5+L12 -> 281.724 | M17: =M5+M12 -> 331.839 | N17: Derived
A18: 合併營收（公司損益表） | B18: 65.585 | C18: 69.632 | D18: 70.066 | E18: 76.441 | F18: 77.673 | G18: 81.273 | H18: 82.886 | I18: 90.007 | J18: =SUM(B18:E18) -> 281.724 | K18: =SUM(F18:I18) -> 331.839 | L18: 281.724 | M18: 331.839 | N18: Verified | O18: 財報新聞稿／10-K｜q.rev.*、is.rev.*
A19: 檢查：分部合計 − 合併營收 | B19: =B17-B18 -> 0 | C19: =C17-C18 -> 0 | D19: =D17-D18 -> 0 | E19: =E17-E18 -> 0 | F19: =F17-F18 -> 0 | G19: =G17-G18 -> 0 | H19: =H17-H18 -> 0 | I19: =I17-I18 -> 0 | ... M19: =M17-M18 -> 0 | N19: 核對
A20: 2. 分部營業利益（Microsoft 無未分攤項：分部合計＝合併營業利益）
A21: Agents and Infra 營業利益 | B21: 26.171 | C21: 26.718 | D21: 27.704 | E21: 30.221 | F21: 32.718 | G21: 33.167 | H21: 33.748 | I21: 36.732 | J21: =SUM(B21:E21) -> 110.814 | K21: =SUM(F21:I21) -> 136.365 | L21: 110.814 | M21: 136.365 | N21: Verified | O21: 8-K 2026-09-02 附件 99.1（As Restated）｜q.seg27.ai.oi.*
A22: Devices and Consumer 營業利益 | B22: 4.381 | C22: 4.935 | D22: 4.296 | E22: 4.102 | F22: 5.243 | G22: 5.108 | H22: 4.65 | I22: 3.871 | J22: =SUM(B22:E22) -> 17.714 | K22: =SUM(F22:I22) -> 18.872 | L22: 17.714 | M22: 18.872 | N22: Verified | O22: 8-K 2026-09-02 附件 99.1（As Restated）｜q.seg27.dc.oi.*
A23: 合併營業利益（公司損益表） | B23: 30.552 | C23: 31.653 | D23: 32 | E23: 34.323 | F23: 37.961 | G23: 38.275 | H23: 38.398 | I23: 40.603 | J23: =SUM(B23:E23) -> 128.528 | K23: =SUM(F23:I23) -> 155.237 | L23: 128.528 | M23: 155.237 | N23: Verified | O23: 財報新聞稿／10-K｜q.oi.*、is.oi.*
A24: 檢查：分部營業利益合計 − 合併營業利益（未分攤＝0） | B24: =B21+B22-B23 -> 0 | C24: =C21+C22-C23 -> 0 | D24: =D21+D22-D23 -> 0 | E24: =E21+E22-E23 -> 0 | F24: =F21+F22-F23 -> 0 | G24: =G21+G22-G23 -> 0 | H24: =H21+H22-H23 -> 0 | I24: =I21+I22-I23 -> 0 | ... M24: =M21+M22-M23 -> 0 | N24: 核對
A25: 3. 合併損益主要列（年度值；淨利另列各季）
A26: 淨利（GAAP，含 OpenAI 等持股損益） | B26: 24.667 | C26: 24.108 | D26: 25.824 | E26: 27.233 | F26: 27.747 | G26: 38.458 | H26: 31.778 | I26: 35.766 | J26: =SUM(B26:E26) -> 101.832 | K26: =SUM(F26:I26) -> 133.749 | L26: 101.832 | M26: 133.749 | N26: Verified | O26: 財報新聞稿／10-K｜q.ni.*、is.ni.*
A27: 業外收支（other income (expense), net） | L27: -4.901 | M27: 10.697 | N27: Verified | O27: 10-K｜is.oie.*
A28: 稅前淨利 | L28: 123.627 | M28: 165.934 | N28: Verified | O28: 10-K｜is.pretax.*
A29: 所得稅 | L29: 21.795 | M29: 32.185 | N29: Verified | O29: 10-K｜is.tax.*
A30: 其中：OpenAI 等持股損益（公司非 GAAP 調節） | L30: -4.763 | M30: 6.53 | N30: Verified | O30: 10-K｜is.openaiGain.*
A31: 稀釋加權股數（十億股） | L31: 7.465 | M31: 7.453 | N31: Verified | O31: 10-K｜is.sharesDilW.*
A32: 稀釋 EPS（US$） | L32: 13.64 | M32: 17.95 | N32: Verified | O32: 10-K｜is.epsDil.*
A33: 檢查：營業利益＋業外 − 稅前；稅前 − 稅 − 淨利（年度，應為 0） | L33: =(L23+L27-L28)+(L28-L29-L26) -> 0 | M33: =(M23+M27-M28)+(M28-M29-M26) -> 0 | N33: 核對
A34: 4. 現金流量（各季為新聞稿單季值；資本支出為現金 PP&E）
A35: 營業現金流 | B35: 34.18 | C35: 22.291 | D35: 37.044 | E35: 42.647 | F35: 45.057 | G35: 35.758 | H35: 46.679 | I35: 55.441 | J35: =SUM(B35:E35) -> 136.162 | K35: =SUM(F35:I35) -> 182.935 | L35: 136.162 | M35: 182.935 | N35: Verified | O35: 新聞稿現金流量表｜q.cf.ocf.*
A36: 資本支出（現金 PP&E，正值） | B36: 14.923 | C36: 15.804 | D36: 16.745 | E36: 17.079 | F36: 19.394 | G36: 29.876 | H36: 30.876 | I36: 35.802 | J36: =SUM(B36:E36) -> 64.551 | K36: =SUM(F36:I36) -> 115.948 | L36: 64.551 | M36: 115.948 | N36: Verified | O36: 新聞稿現金流量表｜q.cf.capex.*
A37: 自由現金流（營業現金流 − 現金資本支出） | B37: =B35-B36 -> 19.257 | C37: =C35-C36 -> 6.487 | D37: =D35-D36 -> 20.299 | E37: =E35-E36 -> 25.568 | F37: =F35-F36 -> 25.663 | G37: =G35-G36 -> 5.882 | H37: =H35-H36 -> 15.803 | I37: =I35-I36 -> 19.639 | J37: =SUM(B37:E37) -> 71.611 | K37: =SUM(F37:I37) -> 66.987 | L37: =L35-L36 -> 71.611 | M37: =M35-M36 -> 66.987 | N37: Derived
A38: 折舊、攤銷及其他（現金流量表） | B38: 6.716 | C38: 5.667 | D38: 7.734 | E38: 9.317 | F38: 8.147 | G38: 9.198 | H38: 10.167 | I38: 11.022 | J38: =SUM(B38:E38) -> 29.434 | K38: =SUM(F38:I38) -> 38.534 | L38: 29.433 | M38: 38.534 | N38: Verified | O38: 新聞稿現金流量表｜q.cf.da.*（Q1 由年初至今推得）
A39: 股票薪酬 | B39: 2.832 | C39: 3.089 | D39: 2.98 | E39: 3.073 | F39: 2.983 | G39: 3.219 | H39: 3.081 | I39: 3.122 | J39: =SUM(B39:E39) -> 11.974 | K39: =SUM(F39:I39) -> 12.405 | L39: 11.974 | M39: 12.405 | N39: Verified | O39: 新聞稿現金流量表｜q.cf.sbc.*
A40: 回購（正值） | B40: 4.107 | C40: 4.986 | D40: 4.781 | E40: 4.546 | F40: 5.65 | G40: 7.415 | H40: 4.627 | I40: 4.579 | J40: =SUM(B40:E40) -> 18.42 | K40: =SUM(F40:I40) -> 22.271 | L40: 18.42 | M40: 22.271 | N40: Verified | O40: 新聞稿現金流量表｜q.cf.buyback.*
A41: 股利（正值） | B41: 5.574 | C41: 6.17 | D41: 6.169 | E41: 6.169 | F41: 6.169 | G41: 6.762 | H41: 6.756 | I41: 6.758 | J41: =SUM(B41:E41) -> 24.082 | K41: =SUM(F41:I41) -> 26.445 | L41: 24.082 | M41: 26.445 | N41: Verified | O41: 新聞稿現金流量表｜q.cf.div.*
A42: 資本支出（公司口徑：含融資租賃，法說值） | E42: 24.2 | F42: 34.9 | G42: 37.5 | H42: 31.9 | I42: 41 | K42: =SUM(F42:I42) -> 145.3 | M42: 145.3 | N42: Interested-party | O42: 法說｜capexFL.*（FY25Q4 起；公司口徑≠現金＋融資租賃）
A43: 融資租賃本金（正值） | L43: 2.283 | M43: 3.101 | N43: Verified | O43: 10-K 附註 13｜lease.finPrincipal.*
A44: 檢查：四季合計 − 公司年度值（以上各列絕對值合計） | J44: =SUMPRODUCT(ABS(J5:J23-L5:L23))+ABS(J26-L26)+SUMPRODUCT(ABS(J35:J41-L35:L41)) -> 0.001 | K44: =SUMPRODUCT(ABS(K5:K23-M5:M23))+ABS(K26-M26)+SUMPRODUCT(ABS(K35:K41-M35:M41))+ABS(K42-M42) -> 0 | N44: 核對
A45: 5. 對照：舊三分部（FY2026 以前口徑；10-K／各季新聞稿）與 Azure 年增
A46: Productivity and Business Processes（舊） 營收 | B46: 28.317 | C46: 29.437 | D46: 29.944 | E46: 33.112 | F46: 33.02 | G46: 34.116 | H46: 35.013 | I46: 37.847 | J46: =SUM(B46:E46) -> 120.81 | K46: =SUM(F46:I46) -> 139.996 | L46: 120.81 | M46: 139.996 | N46: Verified | O46: 10-K／新聞稿｜q.seg.pbp.rev.*
A47: Intelligent Cloud（舊） 營收 | B47: 24.092 | C47: 25.544 | D47: 26.751 | E47: 29.878 | F47: 30.897 | G47: 32.907 | H47: 34.681 | I47: 39.306 | J47: =SUM(B47:E47) -> 106.265 | K47: =SUM(F47:I47) -> 137.791 | L47: 106.265 | M47: 137.791 | N47: Verified | O47: 10-K／新聞稿｜q.seg.ic.rev.*
A48: More Personal Computing（舊） 營收 | B48: 13.176 | C48: 14.651 | D48: 13.371 | E48: 13.451 | F48: 13.756 | G48: 14.25 | H48: 13.192 | I48: 12.854 | J48: =SUM(B48:E48) -> 54.649 | K48: =SUM(F48:I48) -> 54.052 | L48: 54.649 | M48: 54.052 | N48: Verified | O48: 10-K／新聞稿｜q.seg.mpc.rev.*
A49: 檢查：舊三分部合計 − 合併營收 | B49: =B46+B47+B48-B18 -> 0 | C49: =C46+C47+C48-C18 -> 0 | D49: =D46+D47+D48-D18 -> 0 | E49: =E46+E47+E48-E18 -> 0 | F49: =F46+F47+F48-F18 -> 0 | G49: =G46+G47+G48-G18 -> 0 | H49: =H46+H47+H48-H18 -> 0 | I49: =I46+I47+I48-I18 -> 0 | ... M49: =M46+M47+M48-M18 -> 0 | N49: 核對
A50: Azure 年增（重編口徑，公司揭露） | F50: 0.4 | G50: 0.39 | H50: 0.4 | I50: 0.42 | N50: Interested-party | O50: 8-K 2026-09-02 Investor Metrics｜q.azure27.growth.*

Sheet Thesis
A1: Thesis — 命題模組：AI 在役 MW → Azure AI 營收（MW × Tokenomics 每 MW 持有成本 × k）；AI 資本支出（MW × Tokenomics 每 MW 成本）→ AI 折舊與營運成本 → Agents and Infra 營業利益；AI 增量 ROIC 對 WACC
A2: 三情境的 MW 路徑相同（資本支出依公司指引），差在變現：k（長約／現貨組合）與 Copilot 座席。命題模組只驅動 Azure 的「Azure AI」子列與 M365 cloud 的「Copilot」子列，不取代官方分部
A3: 核心問題的答案列：「AI 增量 ROIC − WACC」（FY2029 欄）
A4: 情境 A（樂觀）｜命題模組（Thesis）
A5: 項目 | B5: 單位 | C5: FY2024A | D5: FY2025A | E5: FY2026A | F5: FY2027 | G5: FY2028 | H5: FY2029 | I5: FY2030 | J5: FY2031 | K5: FY2032 | L5: 說明
A6: 會計年度（數值；公式以「年度 − base_fy」計年數） | B6: 年 | C6: 2024 | D6: 2025 | E6: 2026 | F6: 2027 | G6: 2028 | H6: 2029 | I6: 2030 | J6: 2031 | K6: 2032
A7: 在役對外 AI MW 每年新增 | B7: MW | F7: =pace -> 2527.2 | G7: =pace -> 2527.2 | H7: =pace -> 2527.2 | I7: =pace+(g_tv*Thesis!H8-pace)*MIN(1,(Thesis!I6-pace_y0)/(pace_y1-pace_y0)) -> 1793.116 | J7: =pace+(g_tv*Thesis!H8-pace)*MIN(1,(Thesis!J6-pace_y0)/(pace_y1-pace_y0)) -> 1059.032 | K7: =pace+(g_tv*Thesis!H8-pace)*MIN(1,(Thesis!K6-pace_y0)/(pace_y1-pace_y0)) -> 324.948 | L7: FY2029 以前＝依資本支出指引的速度；之後逐年線性收斂，FY2032 只剩 g_tv × FY2029 在役 MW（修正一 F5：終值不落在建置高峰）
A8: 在役對外 AI MW（年底，含租用） | B8: MW | C8: =mw_ext_24 -> 640 | D8: =mw_ext_25 -> 1630 | E8: =mw_ext_26 -> 3250 | F8: =Thesis!E8+Thesis!F7 -> 5777.2 | G8: =Thesis!F8+Thesis!G7 -> 8304.4 | H8: =Thesis!G8+Thesis!H7 -> 10831.6 | I8: =Thesis!H8+Thesis!I7 -> 12624.716 | J8: =Thesis!I8+Thesis!J7 -> 13683.748 | K8: =Thesis!J8+Thesis!K7 -> 14008.696 | L8: 三情境速度相同（變現驅動不同）
A9: 其中租用 neocloud 的對外 MW | B9: MW | C9: =rent_ext_24 -> 150 | D9: =rent_ext_25 -> 400 | E9: =rent_ext_26 -> 550 | F9: =rent_ext_f -> 756 | G9: =rent_ext_f -> 756 | H9: =rent_ext_f -> 756 | I9: =rent_ext_f -> 756 | J9: =rent_ext_f -> 756 | K9: =rent_ext_f -> 756 | L9: 收入照算，不計資本支出與折舊（C20）
A10: 自有對外 MW | B10: MW | C10: =Thesis!C8-Thesis!C9 -> 490 | D10: =Thesis!D8-Thesis!D9 -> 1230 | E10: =Thesis!E8-Thesis!E9 -> 2700 | F10: =Thesis!F8-Thesis!F9 -> 5021.2 | G10: =Thesis!G8-Thesis!G9 -> 7548.4 | H10: =Thesis!H8-Thesis!H9 -> 10075.6 | I10: =Thesis!I8-Thesis!I9 -> 11868.716 | J10: =Thesis!J8-Thesis!J9 -> 12927.748 | K10: =Thesis!K8-Thesis!K9 -> 13252.696
A11: 自有 AI MW（對外 ÷ 對外比例） | B11: MW | C11: =Thesis!C10/ext_sh -> 816.66667 | D11: =Thesis!D10/ext_sh -> 2050 | E11: =Thesis!E10/ext_sh -> 4500 | F11: =Thesis!F10/ext_sh -> 8368.6667 | G11: =Thesis!G10/ext_sh -> 12580.667 | H11: =Thesis!H10/ext_sh -> 16792.667 | I11: =Thesis!I10/ext_sh -> 19781.193 | J11: =Thesis!J10/ext_sh -> 21546.247 | K11: =Thesis!K10/ext_sh -> 22087.827 | L11: 含自用（M365／GitHub Copilot、MAI 研發）
A12: 其中自用 AI MW | B12: MW | C12: =Thesis!C11-Thesis!C10 -> 326.66667 | D12: =Thesis!D11-Thesis!D10 -> 820 | E12: =Thesis!E11-Thesis!E10 -> 1800 | F12: =Thesis!F11-Thesis!F10 -> 3347.4667 | G12: =Thesis!G11-Thesis!G10 -> 5032.2667 | H12: =Thesis!H11-Thesis!H10 -> 6717.0667 | I12: =Thesis!I11-Thesis!I10 -> 7912.4773 | J12: =Thesis!J11-Thesis!J10 -> 8618.4987 | K12: =Thesis!K11-Thesis!K10 -> 8835.1307
A13: 自有 AI MW 新增（FY2024 欄含以前全部） | B13: MW | C13: =Thesis!C11 -> 816.66667 | D13: =Thesis!D11-Thesis!C11 -> 1233.3333 | E13: =Thesis!E11-Thesis!D11 -> 2450 | F13: =Thesis!F11-Thesis!E11 -> 3868.6667 | G13: =Thesis!G11-Thesis!F11 -> 4212 | H13: =Thesis!H11-Thesis!G11 -> 4212 | I13: =Thesis!I11-Thesis!H11 -> 2988.5267 | J13: =Thesis!J11-Thesis!I11 -> 1765.0533 | K13: =Thesis!K11-Thesis!J11 -> 541.58
A14: 在役對外 MW 新增 | B14: MW | D14: =Thesis!D8-Thesis!C8 -> 990 | E14: =Thesis!E8-Thesis!D8 -> 1620 | F14: =Thesis!F8-Thesis!E8 -> 2527.2 | G14: =Thesis!G8-Thesis!F8 -> 2527.2 | H14: =Thesis!H8-Thesis!G8 -> 2527.2 | I14: =Thesis!I8-Thesis!H8 -> 1793.116 | J14: =Thesis!J8-Thesis!I8 -> 1059.032 | K14: =Thesis!K8-Thesis!J8 -> 324.948
A15: 其中汰換為新世代的對外 MW（汰換 MW × 對外比例） | B15: MW | F15: =Thesis!F32*ext_sh -> 0 | G15: =Thesis!G32*ext_sh -> 0 | H15: =Thesis!H32*ext_sh -> 0 | I15: =Thesis!I32*ext_sh -> 490 | J15: =Thesis!J32*ext_sh -> 740 | K15: =Thesis!K32*ext_sh -> 1470 | L15: 修正一：汰換時在役世代占比同步更新（舊世代依期初占比移出、新世代依當年新增占比移入）
A16: 在役對外 MW：Hopper | B16: MW | C16: =mix_h*Thesis!C8 -> 128 | D16: =mix_h*Thesis!D8 -> 326 | E16: =mix_h*Thesis!E8 -> 650 | F16: =Thesis!E16-Thesis!F15*mix_h -> 650 | G16: =Thesis!F16-Thesis!G15*mix_h -> 650 | H16: =Thesis!G16-Thesis!H15*mix_h -> 650 | I16: =Thesis!H16-Thesis!I15*mix_h -> 552 | J16: =Thesis!I16-Thesis!J15*mix_h -> 404 | K16: =Thesis!J16-Thesis!K15*mix_h -> 110
A17: 在役對外 MW：GB200 | B17: MW | C17: =mix_g2*Thesis!C8 -> 288 | D17: =mix_g2*Thesis!D8 -> 733.5 | E17: =mix_g2*Thesis!E8 -> 1462.5 | F17: =Thesis!E17-Thesis!F15*mix_g2 -> 1462.5 | G17: =Thesis!F17-Thesis!G15*mix_g2 -> 1462.5 | H17: =Thesis!G17-Thesis!H15*mix_g2 -> 1462.5 | I17: =Thesis!H17-Thesis!I15*mix_g2 -> 1242 | J17: =Thesis!I17-Thesis!J15*mix_g2 -> 909 | K17: =Thesis!J17-Thesis!K15*mix_g2 -> 247.5
A18: 在役對外 MW：GB300（含 Maia 200） | B18: MW | C18: =mix_g3*Thesis!C8 -> 224 | D18: =mix_g3*Thesis!D8 -> 570.5 | E18: =mix_g3*Thesis!E8 -> 1137.5 | F18: =Thesis!E18+(Thesis!F14+Thesis!F15)*a_g3_27-Thesis!F15*mix_g3 -> 2906.54 | G18: =Thesis!F18+(Thesis!G14+Thesis!G15)*a_g3_28-Thesis!G15*mix_g3 -> 3664.7 | H18: =Thesis!G18+(Thesis!H14+Thesis!H15)*a_g3_29-Thesis!H15*mix_g3 -> 3917.42 | I18: =Thesis!H18+(Thesis!I14+Thesis!I15)*a_g3_29-Thesis!I15*mix_g3 -> 3974.2316 | J18: =Thesis!I18+(Thesis!J14+Thesis!J15)*a_g3_29-Thesis!J15*mix_g3 -> 3895.1348 | K18: =Thesis!J18+(Thesis!K14+Thesis!K15)*a_g3_29-Thesis!K15*mix_g3 -> 3560.1296
A19: 在役對外 MW：VR200 | B19: MW | C19: 0 | D19: 0 | E19: 0 | F19: =Thesis!E19+(Thesis!F14+Thesis!F15)*(1-a_g3_27) -> 758.16 | G19: =Thesis!F19+(Thesis!G14+Thesis!G15)*(1-a_g3_28) -> 2527.2 | H19: =Thesis!G19+(Thesis!H14+Thesis!H15)*(1-a_g3_29) -> 4801.68 | I19: =Thesis!H19+(Thesis!I14+Thesis!I15)*(1-a_g3_29) -> 6856.4844 | J19: =Thesis!I19+(Thesis!J14+Thesis!J15)*(1-a_g3_29) -> 8475.6132 | K19: =Thesis!J19+(Thesis!K14+Thesis!K15)*(1-a_g3_29) -> 10091.066
A20: 在役世代加權 IF_HoldEcon | B20: US$M/MW-年 | C20: =(Thesis!C16*tk_hold_h100+Thesis!C17*tk_hold_gb200+Thesis!C18*tk_hold_gb300+Thesis!C19*tk_hold_vr200)/Thesis!C8 -> 9.7235358 | D20: =(Thesis!D16*tk_hold_h100+Thesis!D17*tk_hold_gb200+Thesis!D18*tk_hold_gb300+Thesis!D19*tk_hold_vr200)/Thesis!D8 -> 9.7235358 | E20: =(Thesis!E16*tk_hold_h100+Thesis!E17*tk_hold_gb200+Thesis!E18*tk_hold_gb300+Thesis!E19*tk_hold_vr200)/Thesis!E8 -> 9.7235358 | F20: =(Thesis!F16*tk_hold_h100+Thesis!F17*tk_hold_gb200+Thesis!F18*tk_hold_gb300+Thesis!F19*tk_hold_vr200)/Thesis!F8 -> 10.407957 | G20: =(Thesis!G16*tk_hold_h100+Thesis!G17*tk_hold_gb200+Thesis!G18*tk_hold_gb300+Thesis!G19*tk_hold_vr200)/Thesis!G8 -> 10.838813 | H20: =(Thesis!H16*tk_hold_h100+Thesis!H17*tk_hold_gb200+Thesis!H18*tk_hold_gb300+Thesis!H19*tk_hold_vr200)/Thesis!H8 -> 11.131102 | I20: =(Thesis!I16*tk_hold_h100+Thesis!I17*tk_hold_gb200+Thesis!I18*tk_hold_gb300+Thesis!I19*tk_hold_vr200)/Thesis!I8 -> 11.359428 | J20: =(Thesis!J16*tk_hold_h100+Thesis!J17*tk_hold_gb200+Thesis!J18*tk_hold_gb300+Thesis!J19*tk_hold_vr200)/Thesis!J8 -> 11.544151 | K20: =(Thesis!K16*tk_hold_h100+Thesis!K17*tk_hold_gb200+Thesis!K18*tk_hold_gb300+Thesis!K19*tk_hold_vr200)/Thesis!K8 -> 11.805338
A21: k（長約占比 × k_長約＋其餘 × k_現貨） | B21: x | C21: =k_B -> 1.1721393 | D21: =k_B -> 1.1721393 | E21: =k_B -> 1.1721393 | F21: =(k_B+((ls_A*k_long+(1-ls_A)*k_spot)-k_B)*MIN(1,(Thesis!F6-base_fy)/k_ramp)) -> 1.2502283 | G21: =(k_B+((ls_A*k_long+(1-ls_A)*k_spot)-k_B)*MIN(1,(Thesis!G6-base_fy)/k_ramp)) -> 1.3283172 | H21: =(k_B+((ls_A*k_long+(1-ls_A)*k_spot)-k_B)*MIN(1,(Thesis!H6-base_fy)/k_ramp)) -> 1.4064062 | I21: =(k_B+((ls_A*k_long+(1-ls_A)*k_spot)-k_B)*MIN(1,(Thesis!I6-base_fy)/k_ramp)) -> 1.4064062 | J21: =(k_B+((ls_A*k_long+(1-ls_A)*k_spot)-k_B)*MIN(1,(Thesis!J6-base_fy)/k_ramp)) -> 1.4064062 | K21: =(k_B+((ls_A*k_long+(1-ls_A)*k_spot)-k_B)*MIN(1,(Thesis!K6-base_fy)/k_ramp)) -> 1.4064062 | L21: 實績期三情境同用基準 k（拆分是估計，不是情境）；FY2027 起 k_ramp 年線性移到情境 k
A22: 每 MW 年收入（對外） | B22: US$M/MW-年 | C22: =Thesis!C20*Thesis!C21*chip_f -> 11.397339 | D22: =Thesis!D20*Thesis!D21*chip_f -> 11.397339 | E22: =Thesis!E20*Thesis!E21*chip_f -> 11.397339 | F22: =Thesis!F20*Thesis!F21*chip_f -> 13.012323 | G22: =Thesis!G20*Thesis!G21*chip_f -> 14.397382 | H22: =Thesis!H20*Thesis!H21*chip_f -> 15.654851 | I22: =Thesis!I20*Thesis!I21*chip_f -> 15.97597 | J22: =Thesis!J20*Thesis!J21*chip_f -> 16.235765 | K22: =Thesis!K20*Thesis!K21*chip_f -> 16.6031 | L22: 按 MW-year 計價，不乘利用率（v0.2.2 口徑）
A23: Azure AI 營收（期間平均在役對外 MW × 每 MW 年收入） | B23: US$B | D23: =(Thesis!C8+Thesis!D8)/2*Thesis!D22/1000 -> 12.935979 | E23: =(Thesis!D8+Thesis!E8)/2*Thesis!E22/1000 -> 27.809506 | F23: =(Thesis!E8+Thesis!F8)/2*Thesis!F22/1000 -> 58.732419 | G23: =(Thesis!F8+Thesis!G8)/2*Thesis!G22/1000 -> 101.36909 | H23: =(Thesis!G8+Thesis!H8)/2*Thesis!H22/1000 -> 149.78561 | I23: =(Thesis!H8+Thesis!I8)/2*Thesis!I22/1000 -> 187.3687 | J23: =(Thesis!I8+Thesis!J8)/2*Thesis!J22/1000 -> 213.56902 | K23: =(Thesis!J8+Thesis!K8)/2*Thesis!K22/1000 -> 229.89021 | L23: FY2025、FY2026 為模型估計（用於拆出 Azure 其他）
A24: 在役世代加權 IF_OpexGW | B24: US$M/MW-年 | C24: =(Thesis!C16*tk_opex_h100+Thesis!C17*tk_opex_gb200+Thesis!C18*tk_opex_gb300+Thesis!C19*tk_opex_vr200)/Thesis!C8 -> 1.8863604 | D24: =(Thesis!D16*tk_opex_h100+Thesis!D17*tk_opex_gb200+Thesis!D18*tk_opex_gb300+Thesis!D19*tk_opex_vr200)/Thesis!D8 -> 1.8863604 | E24: =(Thesis!E16*tk_opex_h100+Thesis!E17*tk_opex_gb200+Thesis!E18*tk_opex_gb300+Thesis!E19*tk_opex_vr200)/Thesis!E8 -> 1.8863604 | F24: =(Thesis!F16*tk_opex_h100+Thesis!F17*tk_opex_gb200+Thesis!F18*tk_opex_gb300+Thesis!F19*tk_opex_vr200)/Thesis!F8 -> 1.9430236 | G24: =(Thesis!G16*tk_opex_h100+Thesis!G17*tk_opex_gb200+Thesis!G18*tk_opex_gb300+Thesis!G19*tk_opex_vr200)/Thesis!G8 -> 1.9786942 | H24: =(Thesis!H16*tk_opex_h100+Thesis!H17*tk_opex_gb200+Thesis!H18*tk_opex_gb300+Thesis!H19*tk_opex_vr200)/Thesis!H8 -> 2.0028928 | I24: =(Thesis!I16*tk_opex_h100+Thesis!I17*tk_opex_gb200+Thesis!I18*tk_opex_gb300+Thesis!I19*tk_opex_vr200)/Thesis!I8 -> 2.0217959 | J24: =(Thesis!J16*tk_opex_h100+Thesis!J17*tk_opex_gb200+Thesis!J18*tk_opex_gb300+Thesis!J19*tk_opex_vr200)/Thesis!J8 -> 2.0370891 | K24: =(Thesis!K16*tk_opex_h100+Thesis!K17*tk_opex_gb200+Thesis!K18*tk_opex_gb300+Thesis!K19*tk_opex_vr200)/Thesis!K8 -> 2.0587127
A25: AI 營運成本：自有 AI MW（平均 × IF_OpexGW） | B25: US$B | D25: =(Thesis!C11+Thesis!D11)/2*Thesis!D24/1000 -> 2.7037833 | E25: =(Thesis!D11+Thesis!E11)/2*Thesis!E24/1000 -> 6.1778304 | F25: =(Thesis!E11+Thesis!F11)/2*Thesis!F24/1000 -> 12.502062 | G25: =(Thesis!F11+Thesis!G11)/2*Thesis!G24/1000 -> 20.726162 | H25: =(Thesis!G11+Thesis!H11)/2*Thesis!H24/1000 -> 29.415818 | I25: =(Thesis!H11+Thesis!I11)/2*Thesis!I24/1000 -> 36.97244 | J25: =(Thesis!I11+Thesis!J11)/2*Thesis!J24/1000 -> 42.093838 | K25: =(Thesis!J11+Thesis!K11)/2*Thesis!K24/1000 -> 44.915011
A26: AI 營運成本：租用 neocloud 租金 | B26: US$B | D26: =(Thesis!C9+Thesis!D9)/2*rent_mw/1000 -> 2.44475 | E26: =(Thesis!D9+Thesis!E9)/2*rent_mw/1000 -> 4.22275 | F26: =(Thesis!E9+Thesis!F9)/2*rent_mw/1000 -> 5.80517 | G26: =(Thesis!F9+Thesis!G9)/2*rent_mw/1000 -> 6.72084 | H26: =(Thesis!G9+Thesis!H9)/2*rent_mw/1000 -> 6.72084 | I26: =(Thesis!H9+Thesis!I9)/2*rent_mw/1000 -> 6.72084 | J26: =(Thesis!I9+Thesis!J9)/2*rent_mw/1000 -> 6.72084 | K26: =(Thesis!J9+Thesis!K9)/2*rent_mw/1000 -> 6.72084
A27: AI 營運成本：租用機房租金（1 − 自建比例） | B27: US$B | D27: =(Thesis!C11+Thesis!D11)/2*(1-self_build)*fac_rent/1000 -> 0.85324238 | E27: =(Thesis!D11+Thesis!E11)/2*(1-self_build)*fac_rent/1000 -> 1.9495596 | F27: =(Thesis!E11+Thesis!F11)/2*(1-self_build)*fac_rent/1000 -> 3.8302646 | G27: =(Thesis!F11+Thesis!G11)/2*(1-self_build)*fac_rent/1000 -> 6.2354159 | H27: =(Thesis!G11+Thesis!H11)/2*(1-self_build)*fac_rent/1000 -> 8.7427579 | I27: =(Thesis!H11+Thesis!I11)/2*(1-self_build)*fac_rent/1000 -> 10.885942 | J27: =(Thesis!I11+Thesis!J11)/2*(1-self_build)*fac_rent/1000 -> 12.30081 | K27: =(Thesis!J11+Thesis!K11)/2*(1-self_build)*fac_rent/1000 -> 12.987363 | L27: C22
A28: 自有 AI 中對外的比重（期間平均） | B28: % | D28: =(Thesis!C10+Thesis!D10)/(Thesis!C11+Thesis!D11) -> 0.6 | E28: =(Thesis!D10+Thesis!E10)/(Thesis!D11+Thesis!E11) -> 0.6 | F28: =(Thesis!E10+Thesis!F10)/(Thesis!E11+Thesis!F11) -> 0.6 | G28: =(Thesis!F10+Thesis!G10)/(Thesis!F11+Thesis!G11) -> 0.6 | H28: =(Thesis!G10+Thesis!H10)/(Thesis!G11+Thesis!H11) -> 0.6 | I28: =(Thesis!H10+Thesis!I10)/(Thesis!H11+Thesis!I11) -> 0.6 | J28: =(Thesis!I10+Thesis!J10)/(Thesis!I11+Thesis!J11) -> 0.6 | K28: =(Thesis!J10+Thesis!K10)/(Thesis!J11+Thesis!K11) -> 0.6
A29: Azure AI EBITDA（營收 − 對外營運成本 − 租金） | B29: US$B | D29: =Thesis!D23-Thesis!D28*(Thesis!D25+Thesis!D27)-Thesis!D26 -> 8.3570141 | E29: =Thesis!E23-Thesis!E28*(Thesis!E25+Thesis!E27)-Thesis!E26 -> 18.710322 | F29: =Thesis!F23-Thesis!F28*(Thesis!F25+Thesis!F27)-Thesis!F26 -> 43.127853 | G29: =Thesis!G23-Thesis!G28*(Thesis!G25+Thesis!G27)-Thesis!G26 -> 78.471302 | H29: =Thesis!H23-Thesis!H28*(Thesis!H25+Thesis!H27)-Thesis!H26 -> 120.16962 | I29: =Thesis!I23-Thesis!I28*(Thesis!I25+Thesis!I27)-Thesis!I26 -> 151.93283 | J29: =Thesis!J23-Thesis!J28*(Thesis!J25+Thesis!J27)-Thesis!J26 -> 174.21139 | K29: =Thesis!K23-Thesis!K28*(Thesis!K25+Thesis!K27)-Thesis!K26 -> 188.42794
A30: 自用 AI 營運成本（服務 Copilot 等自有產品） | B30: US$B | D30: =(1-Thesis!D28)*(Thesis!D25+Thesis!D27) -> 1.4228103 | E30: =(1-Thesis!E28)*(Thesis!E25+Thesis!E27) -> 3.250956 | F30: =(1-Thesis!F28)*(Thesis!F25+Thesis!F27) -> 6.5329306 | G30: =(1-Thesis!G28)*(Thesis!G25+Thesis!G27) -> 10.784631 | H30: =(1-Thesis!H28)*(Thesis!H25+Thesis!H27) -> 15.263431 | I30: =(1-Thesis!I28)*(Thesis!I25+Thesis!I27) -> 19.143353 | J30: =(1-Thesis!J28)*(Thesis!J25+Thesis!J27) -> 21.757859 | K30: =(1-Thesis!K28)*(Thesis!K25+Thesis!K27) -> 23.160949
A31: 新增與汰換 MW 的 IT 資本支出（世代加權） | B31: US$M/MW | C31: =cxit_open -> 27.5919 | D31: =cxit_open -> 27.5919 | E31: =cxit_open -> 27.5919 | F31: =(a_g3_27*tk_cxit_gb300+(1-a_g3_27)*tk_cxit_vr200) -> 33.841962 | G31: =(a_g3_28*tk_cxit_gb300+(1-a_g3_28)*tk_cxit_vr200) -> 35.981614 | H31: =(a_g3_29*tk_cxit_gb300+(1-a_g3_29)*tk_cxit_vr200) -> 37.051439 | I31: =(a_g3_29*tk_cxit_gb300+(1-a_g3_29)*tk_cxit_vr200) -> 37.051439 | J31: =(a_g3_29*tk_cxit_gb300+(1-a_g3_29)*tk_cxit_vr200) -> 37.051439 | K31: =(a_g3_29*tk_cxit_gb300+(1-a_g3_29)*tk_cxit_vr200) -> 37.051439 | L31: FY2026 以前用期初世代加權（估計）
A32: GPU 汰換 MW（自有 AI MW 滿 IT 年限者） | B32: MW | F32: =Thesis!C13*IF(Thesis!F6-Thesis!C6=life_it,1,0)+Thesis!D13*IF(Thesis!F6-Thesis!D6=life_it,1,0)+Thesis!E13*IF(Thesis!F6-Thesis!E6=life_it,1,0) -> 0 | G32: =Thesis!C13*IF(Thesis!G6-Thesis!C6=life_it,1,0)+Thesis!D13*IF(Thesis!G6-Thesis!D6=life_it,1,0)+Thesis!E13*IF(Thesis!G6-Thesis!E6=life_it,1,0)+Thesis!F13*IF(Thesis!G6-Thesis!F6=life_it,1,0) -> 0 | H32: =Thesis!C13*IF(Thesis!H6-Thesis!C6=life_it,1,0)+Thesis!D13*IF(Thesis!H6-Thesis!D6=life_it,1,0)+Thesis!E13*IF(Thesis!H6-Thesis!E6=life_it,1,0)+Thesis!F13*IF(Thesis!H6-Thesis!F6=life_it,1,0)+Thesis!G13*IF(Thesis!H6-Thesis!G6=life_it,1,0) -> 0 | I32: =Thesis!C13*IF(Thesis!I6-Thesis!C6=life_it,1,0)+Thesis!D13*IF(Thesis!I6-Thesis!D6=life_it,1,0)+Thesis!E13*IF(Thesis!I6-Thesis!E6=life_it,1,0)+Thesis!F13*IF(Thesis!I6-Thesis!F6=life_it,1,0)+Thesis!G13*IF(Thesis!I6-Thesis!G6=life_it,1,0)+Thesis!H13*IF(Thesis!I6-Thesis!H6=life_it,1,0) -> 816.66667 | J32: =Thesis!C13*IF(Thesis!J6-Thesis!C6=life_it,1,0)+Thesis!D13*IF(Thesis!J6-Thesis!D6=life_it,1,0)+Thesis!E13*IF(Thesis!J6-Thesis!E6=life_it,1,0)+Thesis!F13*IF(Thesis!J6-Thesis!F6=life_it,1,0)+Thesis!G13*IF(Thesis!J6-Thesis!G6=life_it,1,0)+Thesis!H13*IF(Thesis!J6-Thesis!H6=life_it,1,0)+Thesis!I13*IF(Thesis!J6-Thesis!I6=life_it,1,0) -> 1233.3333 | K32: =Thesis!C13*IF(Thesis!K6-Thesis!C6=life_it,1,0)+Thesis!D13*IF(Thesis!K6-Thesis!D6=life_it,1,0)+Thesis!E13*IF(Thesis!K6-Thesis!E6=life_it,1,0)+Thesis!F13*IF(Thesis!K6-Thesis!F6=life_it,1,0)+Thesis!G13*IF(Thesis!K6-Thesis!G6=life_it,1,0)+Thesis!H13*IF(Thesis!K6-Thesis!H6=life_it,1,0)+Thesis!I13*IF(Thesis!K6-Thesis!I6=life_it,1,0)+Thesis!J13*IF(Thesis!K6-Thesis!J6=life_it,1,0) -> 2450 | L32: 只換 IT、機房不換；FY2024 欄含 FY2024 以前全部（視同 FY2024 投入）；舊機隊在年限到期後停止折舊，汰換後的新 IT 另計折舊（不重複）
A33: AI IT 資本支出（公式） | B33: US$B | C33: =Thesis!C13*Thesis!C31/1000 -> 22.533385 | D33: =Thesis!D13*Thesis!D31/1000 -> 34.030009 | E33: =Thesis!E13*Thesis!E31/1000 -> 67.600154 | F33: =(Thesis!F13+Thesis!F32)*Thesis!F31/1000 -> 130.92327 | G33: =(Thesis!G13+Thesis!G32)*Thesis!G31/1000 -> 151.55456 | H33: =(Thesis!H13+Thesis!H32)*Thesis!H31/1000 -> 156.06066 | I33: =(Thesis!I13+Thesis!I32)*Thesis!I31/1000 -> 140.98789 | J33: =(Thesis!J13+Thesis!J32)*Thesis!J31/1000 -> 111.09454 | K33: =(Thesis!K13+Thesis!K32)*Thesis!K31/1000 -> 110.84234
A34: AI 機房資本支出（自建比例 × IF_CapexFacility） | B34: US$B | C34: =Thesis!C13*self_build*tk_cxfac/1000 -> 6.2083 | D34: =Thesis!D13*self_build*tk_cxfac/1000 -> 9.3758 | E34: =Thesis!E13*self_build*tk_cxfac/1000 -> 18.6249 | F34: =Thesis!F13*self_build*tk_cxfac/1000 -> 29.409604 | G34: =Thesis!G13*self_build*tk_cxfac/1000 -> 32.019624 | H34: =Thesis!H13*self_build*tk_cxfac/1000 -> 32.019624 | I34: =Thesis!I13*self_build*tk_cxfac/1000 -> 22.71878 | J34: =Thesis!J13*self_build*tk_cxfac/1000 -> 13.417935 | K34: =Thesis!K13*self_build*tk_cxfac/1000 -> 4.1170912
A35: FY2027 補足到公司資本支出下限的差額（計入 IT） | B35: US$B | F35: =MAX(0,capex_floor27-Thesis!F33-Thesis!F34-CF!F23) -> 8.1377769 | L35: 近期以公司指引為下限（C10 方法沿用）；IT 占約三分之二（法說短期資產）
A36: AI IT 資本支出（含補足差額） | B36: US$B | C36: =Thesis!C33 -> 22.533385 | D36: =Thesis!D33 -> 34.030009 | E36: =Thesis!E33 -> 67.600154 | F36: =Thesis!F33+Thesis!F35 -> 139.06105 | G36: =Thesis!G33 -> 151.55456 | H36: =Thesis!H33 -> 156.06066 | I36: =Thesis!I33 -> 140.98789 | J36: =Thesis!J33 -> 111.09454 | K36: =Thesis!K33 -> 110.84234
A37: AI 資本支出合計 | B37: US$B | C37: =Thesis!C36+Thesis!C34 -> 28.741685 | D37: =Thesis!D36+Thesis!D34 -> 43.405809 | E37: =Thesis!E36+Thesis!E34 -> 86.225054 | F37: =Thesis!F36+Thesis!F34 -> 168.47065 | G37: =Thesis!G36+Thesis!G34 -> 183.57418 | H37: =Thesis!H36+Thesis!H34 -> 188.08029 | I37: =Thesis!I36+Thesis!I34 -> 163.70667 | J37: =Thesis!J36+Thesis!J34 -> 124.51248 | K37: =Thesis!K36+Thesis!K34 -> 114.95944 | L37: FY2026 以前為依 MW 估計的值（非公司揭露）
A38: AI IT 折舊（半年慣例、年限 life_it） | B38: US$B | E38: =(Thesis!C36*IF(2<life_it,1,IF(2=life_it,0.5,0))+Thesis!D36*IF(1<life_it,1,IF(1=life_it,0.5,0))+Thesis!E36*0.5)/life_it -> 15.060578 | F38: =(Thesis!C36*IF(3<life_it,1,IF(3=life_it,0.5,0))+Thesis!D36*IF(2<life_it,1,IF(2=life_it,0.5,0))+Thesis!E36*IF(1<life_it,1,IF(1=life_it,0.5,0))+Thesis!F36*0.5)/life_it -> 32.282345 | G38: =(Thesis!C36*IF(4<life_it,1,IF(4=life_it,0.5,0))+Thesis!D36*IF(3<life_it,1,IF(3=life_it,0.5,0))+Thesis!E36*IF(2<life_it,1,IF(2=life_it,0.5,0))+Thesis!F36*IF(1<life_it,1,IF(1=life_it,0.5,0))+Thesis!G36*0.5)/life_it -> 56.500312 | H38: =(Thesis!C36*IF(5<life_it,1,IF(5=life_it,0.5,0))+Thesis!D36*IF(4<life_it,1,IF(4=life_it,0.5,0))+Thesis!E36*IF(3<life_it,1,IF(3=life_it,0.5,0))+Thesis!F36*IF(2<life_it,1,IF(2=life_it,0.5,0))+Thesis!G36*IF(1<life_it,1,IF(1=life_it,0.5,0))+Thesis!H36*0.5)/life_it -> 82.134914 | I38: =(Thesis!C36*IF(6<life_it,1,IF(6=life_it,0.5,0))+Thesis!D36*IF(5<life_it,1,IF(5=life_it,0.5,0))+Thesis!E36*IF(4<life_it,1,IF(4=life_it,0.5,0))+Thesis!F36*IF(3<life_it,1,IF(3=life_it,0.5,0))+Thesis!G36*IF(2<life_it,1,IF(2=life_it,0.5,0))+Thesis!H36*IF(1<life_it,1,IF(1=life_it,0.5,0))+Thesis!I36*0.5)/life_it -> 105.01118 | J38: =(Thesis!C36*IF(7<life_it,1,IF(7=life_it,0.5,0))+Thesis!D36*IF(6<life_it,1,IF(6=life_it,0.5,0))+Thesis!E36*IF(5<life_it,1,IF(5=life_it,0.5,0))+Thesis!F36*IF(4<life_it,1,IF(4=life_it,0.5,0))+Thesis!G36*IF(3<life_it,1,IF(3=life_it,0.5,0))+Thesis!H36*IF(2<life_it,1,IF(2=life_it,0.5,0))+Thesis!I36*IF(1<life_it,1,IF(1=life_it,0.5,0))+Thesis!J36*0.5)/life_it -> 121.30443 | K38: =(Thesis!C36*IF(8<life_it,1,IF(8=life_it,0.5,0))+Thesis!D36*IF(7<life_it,1,IF(7=life_it,0.5,0))+Thesis!E36*IF(6<life_it,1,IF(6=life_it,0.5,0))+Thesis!F36*IF(5<life_it,1,IF(5=life_it,0.5,0))+Thesis!G36*IF(4<life_it,1,IF(4=life_it,0.5,0))+Thesis!H36*IF(3<life_it,1,IF(3=life_it,0.5,0))+Thesis!I36*IF(2<life_it,1,IF(2=life_it,0.5,0))+Thesis!J36*IF(1<life_it,1,IF(1=life_it,0.5,0))+Thesis!K36*0.5)/life_it -> 131.32999
A39: AI 機房折舊（年限 life_fac） | B39: US$B | E39: =(Thesis!C34*IF(2<life_fac,1,IF(2=life_fac,0.5,0))+Thesis!D34*IF(1<life_fac,1,IF(1=life_fac,0.5,0))+Thesis!E34*0.5)/life_fac -> 1.2448275 | F39: =(Thesis!C34*IF(3<life_fac,1,IF(3=life_fac,0.5,0))+Thesis!D34*IF(2<life_fac,1,IF(2=life_fac,0.5,0))+Thesis!E34*IF(1<life_fac,1,IF(1=life_fac,0.5,0))+Thesis!F34*0.5)/life_fac -> 2.4456901 | G39: =(Thesis!C34*IF(4<life_fac,1,IF(4=life_fac,0.5,0))+Thesis!D34*IF(3<life_fac,1,IF(3=life_fac,0.5,0))+Thesis!E34*IF(2<life_fac,1,IF(2=life_fac,0.5,0))+Thesis!F34*IF(1<life_fac,1,IF(1=life_fac,0.5,0))+Thesis!G34*0.5)/life_fac -> 3.9814208 | H39: =(Thesis!C34*IF(5<life_fac,1,IF(5=life_fac,0.5,0))+Thesis!D34*IF(4<life_fac,1,IF(4=life_fac,0.5,0))+Thesis!E34*IF(3<life_fac,1,IF(3=life_fac,0.5,0))+Thesis!F34*IF(2<life_fac,1,IF(2=life_fac,0.5,0))+Thesis!G34*IF(1<life_fac,1,IF(1=life_fac,0.5,0))+Thesis!H34*0.5)/life_fac -> 5.582402 | I39: =(Thesis!C34*IF(6<life_fac,1,IF(6=life_fac,0.5,0))+Thesis!D34*IF(5<life_fac,1,IF(5=life_fac,0.5,0))+Thesis!E34*IF(4<life_fac,1,IF(4=life_fac,0.5,0))+Thesis!F34*IF(3<life_fac,1,IF(3=life_fac,0.5,0))+Thesis!G34*IF(2<life_fac,1,IF(2=life_fac,0.5,0))+Thesis!H34*IF(1<life_fac,1,IF(1=life_fac,0.5,0))+Thesis!I34*0.5)/life_fac -> 6.9508621 | J39: =(Thesis!C34*IF(7<life_fac,1,IF(7=life_fac,0.5,0))+Thesis!D34*IF(6<life_fac,1,IF(6=life_fac,0.5,0))+Thesis!E34*IF(5<life_fac,1,IF(5=life_fac,0.5,0))+Thesis!F34*IF(4<life_fac,1,IF(4=life_fac,0.5,0))+Thesis!G34*IF(3<life_fac,1,IF(3=life_fac,0.5,0))+Thesis!H34*IF(2<life_fac,1,IF(2=life_fac,0.5,0))+Thesis!I34*IF(1<life_fac,1,IF(1=life_fac,0.5,0))+Thesis!J34*0.5)/life_fac -> 7.85428 | K39: =(Thesis!C34*IF(8<life_fac,1,IF(8=life_fac,0.5,0))+Thesis!D34*IF(7<life_fac,1,IF(7=life_fac,0.5,0))+Thesis!E34*IF(6<life_fac,1,IF(6=life_fac,0.5,0))+Thesis!F34*IF(5<life_fac,1,IF(5=life_fac,0.5,0))+Thesis!G34*IF(4<life_fac,1,IF(4=life_fac,0.5,0))+Thesis!H34*IF(3<life_fac,1,IF(3=life_fac,0.5,0))+Thesis!I34*IF(2<life_fac,1,IF(2=life_fac,0.5,0))+Thesis!J34*IF(1<life_fac,1,IF(1=life_fac,0.5,0))+Thesis!K34*0.5)/life_fac -> 8.2926556
A40: AI 折舊合計（進 Agents and Infra 營業利益） | B40: US$B | E40: =Thesis!E38+Thesis!E39 -> 16.305406 | F40: =Thesis!F38+Thesis!F39 -> 34.728035 | G40: =Thesis!G38+Thesis!G39 -> 60.481733 | H40: =Thesis!H38+Thesis!H39 -> 87.717316 | I40: =Thesis!I38+Thesis!I39 -> 111.96204 | J40: =Thesis!J38+Thesis!J39 -> 129.15871 | K40: =Thesis!K38+Thesis!K39 -> 139.62265
A41: Azure AI 營業利益（EBITDA − 對外分攤折舊） | B41: US$B | E41: =Thesis!E29-Thesis!E28*Thesis!E40 -> 8.9270789 | F41: =Thesis!F29-Thesis!F28*Thesis!F40 -> 22.291032 | G41: =Thesis!G29-Thesis!G28*Thesis!G40 -> 42.182262 | H41: =Thesis!H29-Thesis!H28*Thesis!H40 -> 67.539235 | I41: =Thesis!I29-Thesis!I28*Thesis!I40 -> 84.75561 | J41: =Thesis!J29-Thesis!J28*Thesis!J40 -> 96.716167 | K41: =Thesis!K29-Thesis!K28*Thesis!K40 -> 104.65435
A42: Copilot 營收（Seg） | B42: US$B | E42: =Seg!E11 -> 5.25 | F42: =Seg!F11 -> 13.5 | G42: =Seg!G11 -> 22.5 | H42: =Seg!H11 -> 31.5 | I42: =Seg!I11 -> 38.25 | J42: =Seg!J11 -> 42.75 | K42: =Seg!K11 -> 47.25
A43: 自用 AI 影子效益（讀法 2 金額）＝MAX(0, 平均自用 MW × 持有成本（k＝1）− Copilot × 核心利益率) | B43: US$B | F43: =MAX(0,(Thesis!E12+Thesis!F12)/2*Thesis!F20/1000-Thesis!F42*PL!F31) -> 19.079382 | G43: =MAX(0,(Thesis!F12+Thesis!G12)/2*Thesis!G20/1000-Thesis!G42*PL!G31) -> 32.566641 | H43: =MAX(0,(Thesis!G12+Thesis!H12)/2*Thesis!H20/1000-Thesis!H42*PL!H31) -> 47.406356 | I43: =MAX(0,(Thesis!H12+Thesis!I12)/2*Thesis!I20/1000-Thesis!I42*PL!I31) -> 61.252509 | J43: =MAX(0,(Thesis!I12+Thesis!J12)/2*Thesis!J20/1000-Thesis!J42*PL!J31) -> 71.009614 | K43: =MAX(0,(Thesis!J12+Thesis!K12)/2*Thesis!K20/1000-Thesis!K42*PL!K31) -> 76.045258 | L43: 自用 AI 價值中性：自用算力至少回收 Tokenomics 持有成本；Copilot 已在 M365 營收內計入的部分扣除，避免重複
A44: 自用 AI 影子效益（依讀法開關 internal_ai_reading） | B44: US$B | F44: =IF(internal_ai_reading=2,1,0)*Thesis!F43 -> 19.079382 | G44: =IF(internal_ai_reading=2,1,0)*Thesis!G43 -> 32.566641 | H44: =IF(internal_ai_reading=2,1,0)*Thesis!H43 -> 47.406356 | I44: =IF(internal_ai_reading=2,1,0)*Thesis!I43 -> 61.252509 | J44: =IF(internal_ai_reading=2,1,0)*Thesis!J43 -> 71.009614 | K44: =IF(internal_ai_reading=2,1,0)*Thesis!K43 -> 76.045258
A45: AI 增量營業利益（評價口徑）＝Azure AI EBITDA＋Copilot × 核心利益率＋影子效益 − 自用 AI 營運成本 − AI 折舊 | B45: US$B | F45: =Thesis!F29+Thesis!F42*PL!F31+Thesis!F44-Thesis!F30-Thesis!F40 -> 28.654194 | G45: =Thesis!G29+Thesis!G42*PL!G31+Thesis!G44-Thesis!G30-Thesis!G40 -> 52.61812 | H45: =Thesis!H29+Thesis!H42*PL!H31+Thesis!H44-Thesis!H30-Thesis!H40 -> 82.580391 | I45: =Thesis!I29+Thesis!I42*PL!I31+Thesis!I44-Thesis!I30-Thesis!I40 -> 103.91907 | J45: =Thesis!J29+Thesis!J42*PL!J31+Thesis!J44-Thesis!J30-Thesis!J40 -> 118.71286 | K45: =Thesis!K29+Thesis!K42*PL!K31+Thesis!K44-Thesis!K30-Thesis!K40 -> 128.66734
A46: AI PP&E 淨額（年底） | B46: US$B | E46: =Thesis!E11*(cxit_open+self_build*tk_cxfac)/1000*ai_net_open -> 126.69804 | F46: =Thesis!E46+Thesis!F37-Thesis!F40 -> 260.44066 | G46: =Thesis!F46+Thesis!G37-Thesis!G40 -> 383.5331 | H46: =Thesis!G46+Thesis!H37-Thesis!H40 -> 483.89607 | I46: =Thesis!H46+Thesis!I37-Thesis!I40 -> 535.6407 | J46: =Thesis!I46+Thesis!J37-Thesis!J40 -> 530.99447 | K46: =Thesis!J46+Thesis!K37-Thesis!K40 -> 506.33126 | L46: 期初＝自有 AI MW × 每 MW 全成本 × 淨額比（v0.2.2）
A47: AI 增量 ROIC（評價口徑；稅後營業利益 ÷ 平均 AI PP&E 淨額） | B47: % | F47: =Thesis!F45*(1-tax_f)/((Thesis!E46+Thesis!F46)/2) -> 0.11842451 | G47: =Thesis!G45*(1-tax_f)/((Thesis!F46+Thesis!G46)/2) -> 0.13073357 | H47: =Thesis!H45*(1-tax_f)/((Thesis!G46+Thesis!H46)/2) -> 0.15232209 | I47: =Thesis!I45*(1-tax_f)/((Thesis!H46+Thesis!I46)/2) -> 0.16308437 | J47: =Thesis!J45*(1-tax_f)/((Thesis!I46+Thesis!J46)/2) -> 0.17807455 | K47: =Thesis!K45*(1-tax_f)/((Thesis!J46+Thesis!K46)/2) -> 0.19846007
A48: 讀法 1（自用 AI 只計成本）的 AI 增量 ROIC | B48: % | F48: =(Thesis!F45-Thesis!F44)*(1-tax_f)/((Thesis!E46+Thesis!F46)/2) -> 0.039571603 | G48: =(Thesis!G45-Thesis!G44)*(1-tax_f)/((Thesis!F46+Thesis!G46)/2) -> 0.049819368 | H48: =(Thesis!H45-Thesis!H44)*(1-tax_f)/((Thesis!G46+Thesis!H46)/2) -> 0.064879597 | I48: =(Thesis!I45-Thesis!I44)*(1-tax_f)/((Thesis!H46+Thesis!I46)/2) -> 0.066958345 | J48: =(Thesis!J45-Thesis!J44)*(1-tax_f)/((Thesis!I46+Thesis!J46)/2) -> 0.071556988 | K48: =(Thesis!K45-Thesis!K44)*(1-tax_f)/((Thesis!J46+Thesis!K46)/2) -> 0.081165757
A49: 讀法 2（自用 AI 價值中性）的 AI 增量 ROIC | B49: % | F49: =(Thesis!F45-Thesis!F44+Thesis!F43)*(1-tax_f)/((Thesis!E46+Thesis!F46)/2) -> 0.11842451 | G49: =(Thesis!G45-Thesis!G44+Thesis!G43)*(1-tax_f)/((Thesis!F46+Thesis!G46)/2) -> 0.13073357 | H49: =(Thesis!H45-Thesis!H44+Thesis!H43)*(1-tax_f)/((Thesis!G46+Thesis!H46)/2) -> 0.15232209 | I49: =(Thesis!I45-Thesis!I44+Thesis!I43)*(1-tax_f)/((Thesis!H46+Thesis!I46)/2) -> 0.16308437 | J49: =(Thesis!J45-Thesis!J44+Thesis!J43)*(1-tax_f)/((Thesis!I46+Thesis!J46)/2) -> 0.17807455 | K49: =(Thesis!K45-Thesis!K44+Thesis!K43)*(1-tax_f)/((Thesis!J46+Thesis!K46)/2) -> 0.19846007
A50: 對外 AI ROIC（Azure AI 營業利益 ÷ 對外分攤的 PP&E；C11 口徑） | B50: % | F50: =Thesis!F41*(1-tax_f)/(Thesis!F28*(Thesis!E46+Thesis!F46)/2) -> 0.15354382 | G50: =Thesis!G41*(1-tax_f)/(Thesis!G28*(Thesis!F46+Thesis!G46)/2) -> 0.17467487 | H50: =Thesis!H41*(1-tax_f)/(Thesis!H28*(Thesis!G46+Thesis!H46)/2) -> 0.20763035 | I50: =Thesis!I41*(1-tax_f)/(Thesis!I28*(Thesis!H46+Thesis!I46)/2) -> 0.22168397 | J50: =Thesis!J41*(1-tax_f)/(Thesis!J28*(Thesis!I46+Thesis!J46)/2) -> 0.24179756 | K50: =Thesis!K41*(1-tax_f)/(Thesis!K28*(Thesis!J46+Thesis!K46)/2) -> 0.2690363
A51: AI 增量 ROIC − WACC | B51: pt | F51: =Thesis!F47-wacc -> 0.015490091 | G51: =Thesis!G47-wacc -> 0.027799155 | H51: =Thesis!H47-wacc -> 0.04938767 | I51: =Thesis!I47-wacc -> 0.060149947 | J51: =Thesis!J47-wacc -> 0.075140134 | K51: =Thesis!K47-wacc -> 0.095525654
A52: AI 經濟利潤＝稅後 AI 營業利益 − WACC × 平均 AI PP&E 淨額 | B52: US$B | F52: =Thesis!F45*(1-tax_f)-wacc*(Thesis!E46+Thesis!F46)/2 -> 2.9984068 | G52: =Thesis!G45*(1-tax_f)-wacc*(Thesis!F46+Thesis!G46)/2 -> 8.9509631 | H52: =Thesis!H45*(1-tax_f)-wacc*(Thesis!G46+Thesis!H46)/2 -> 21.420153 | I52: =Thesis!I45*(1-tax_f)-wacc*(Thesis!H46+Thesis!I46)/2 -> 30.662542 | J52: =Thesis!J45*(1-tax_f)-wacc*(Thesis!I46+Thesis!J46)/2 -> 40.073555 | K52: =Thesis!K45*(1-tax_f)-wacc*(Thesis!J46+Thesis!K46)/2 -> 49.545609
A53: 情境 B（基準）｜命題模組（Thesis）
A54: 項目 | B54: 單位 | C54: FY2024A | D54: FY2025A | E54: FY2026A | F54: FY2027 | G54: FY2028 | H54: FY2029 | I54: FY2030 | J54: FY2031 | K54: FY2032 | L54: 說明
A55: 會計年度（數值；公式以「年度 − base_fy」計年數） | B55: 年 | C55: 2024 | D55: 2025 | E55: 2026 | F55: 2027 | G55: 2028 | H55: 2029 | I55: 2030 | J55: 2031 | K55: 2032
A56: 在役對外 AI MW 每年新增 | B56: MW | F56: =pace -> 2527.2 | G56: =pace -> 2527.2 | H56: =pace -> 2527.2 | I56: =pace+(g_tv*Thesis!H57-pace)*MIN(1,(Thesis!I55-pace_y0)/(pace_y1-pace_y0)) -> 1793.116 | J56: =pace+(g_tv*Thesis!H57-pace)*MIN(1,(Thesis!J55-pace_y0)/(pace_y1-pace_y0)) -> 1059.032 | K56: =pace+(g_tv*Thesis!H57-pace)*MIN(1,(Thesis!K55-pace_y0)/(pace_y1-pace_y0)) -> 324.948 | L56: FY2029 以前＝依資本支出指引的速度；之後逐年線性收斂，FY2032 只剩 g_tv × FY2029 在役 MW（修正一 F5：終值不落在建置高峰）
A57: 在役對外 AI MW（年底，含租用） | B57: MW | C57: =mw_ext_24 -> 640 | D57: =mw_ext_25 -> 1630 | E57: =mw_ext_26 -> 3250 | F57: =Thesis!E57+Thesis!F56 -> 5777.2 | G57: =Thesis!F57+Thesis!G56 -> 8304.4 | H57: =Thesis!G57+Thesis!H56 -> 10831.6 | I57: =Thesis!H57+Thesis!I56 -> 12624.716 | J57: =Thesis!I57+Thesis!J56 -> 13683.748 | K57: =Thesis!J57+Thesis!K56 -> 14008.696 | L57: 三情境速度相同（變現驅動不同）
A58: 其中租用 neocloud 的對外 MW | B58: MW | C58: =rent_ext_24 -> 150 | D58: =rent_ext_25 -> 400 | E58: =rent_ext_26 -> 550 | F58: =rent_ext_f -> 756 | G58: =rent_ext_f -> 756 | H58: =rent_ext_f -> 756 | I58: =rent_ext_f -> 756 | J58: =rent_ext_f -> 756 | K58: =rent_ext_f -> 756 | L58: 收入照算，不計資本支出與折舊（C20）
A59: 自有對外 MW | B59: MW | C59: =Thesis!C57-Thesis!C58 -> 490 | D59: =Thesis!D57-Thesis!D58 -> 1230 | E59: =Thesis!E57-Thesis!E58 -> 2700 | F59: =Thesis!F57-Thesis!F58 -> 5021.2 | G59: =Thesis!G57-Thesis!G58 -> 7548.4 | H59: =Thesis!H57-Thesis!H58 -> 10075.6 | I59: =Thesis!I57-Thesis!I58 -> 11868.716 | J59: =Thesis!J57-Thesis!J58 -> 12927.748 | K59: =Thesis!K57-Thesis!K58 -> 13252.696
A60: 自有 AI MW（對外 ÷ 對外比例） | B60: MW | C60: =Thesis!C59/ext_sh -> 816.66667 | D60: =Thesis!D59/ext_sh -> 2050 | E60: =Thesis!E59/ext_sh -> 4500 | F60: =Thesis!F59/ext_sh -> 8368.6667 | G60: =Thesis!G59/ext_sh -> 12580.667 | H60: =Thesis!H59/ext_sh -> 16792.667 | I60: =Thesis!I59/ext_sh -> 19781.193 | J60: =Thesis!J59/ext_sh -> 21546.247 | K60: =Thesis!K59/ext_sh -> 22087.827 | L60: 含自用（M365／GitHub Copilot、MAI 研發）
A61: 其中自用 AI MW | B61: MW | C61: =Thesis!C60-Thesis!C59 -> 326.66667 | D61: =Thesis!D60-Thesis!D59 -> 820 | E61: =Thesis!E60-Thesis!E59 -> 1800 | F61: =Thesis!F60-Thesis!F59 -> 3347.4667 | G61: =Thesis!G60-Thesis!G59 -> 5032.2667 | H61: =Thesis!H60-Thesis!H59 -> 6717.0667 | I61: =Thesis!I60-Thesis!I59 -> 7912.4773 | J61: =Thesis!J60-Thesis!J59 -> 8618.4987 | K61: =Thesis!K60-Thesis!K59 -> 8835.1307
A62: 自有 AI MW 新增（FY2024 欄含以前全部） | B62: MW | C62: =Thesis!C60 -> 816.66667 | D62: =Thesis!D60-Thesis!C60 -> 1233.3333 | E62: =Thesis!E60-Thesis!D60 -> 2450 | F62: =Thesis!F60-Thesis!E60 -> 3868.6667 | G62: =Thesis!G60-Thesis!F60 -> 4212 | H62: =Thesis!H60-Thesis!G60 -> 4212 | I62: =Thesis!I60-Thesis!H60 -> 2988.5267 | J62: =Thesis!J60-Thesis!I60 -> 1765.0533 | K62: =Thesis!K60-Thesis!J60 -> 541.58
A63: 在役對外 MW 新增 | B63: MW | D63: =Thesis!D57-Thesis!C57 -> 990 | E63: =Thesis!E57-Thesis!D57 -> 1620 | F63: =Thesis!F57-Thesis!E57 -> 2527.2 | G63: =Thesis!G57-Thesis!F57 -> 2527.2 | H63: =Thesis!H57-Thesis!G57 -> 2527.2 | I63: =Thesis!I57-Thesis!H57 -> 1793.116 | J63: =Thesis!J57-Thesis!I57 -> 1059.032 | K63: =Thesis!K57-Thesis!J57 -> 324.948
A64: 其中汰換為新世代的對外 MW（汰換 MW × 對外比例） | B64: MW | F64: =Thesis!F81*ext_sh -> 0 | G64: =Thesis!G81*ext_sh -> 0 | H64: =Thesis!H81*ext_sh -> 0 | I64: =Thesis!I81*ext_sh -> 490 | J64: =Thesis!J81*ext_sh -> 740 | K64: =Thesis!K81*ext_sh -> 1470 | L64: 修正一：汰換時在役世代占比同步更新（舊世代依期初占比移出、新世代依當年新增占比移入）
A65: 在役對外 MW：Hopper | B65: MW | C65: =mix_h*Thesis!C57 -> 128 | D65: =mix_h*Thesis!D57 -> 326 | E65: =mix_h*Thesis!E57 -> 650 | F65: =Thesis!E65-Thesis!F64*mix_h -> 650 | G65: =Thesis!F65-Thesis!G64*mix_h -> 650 | H65: =Thesis!G65-Thesis!H64*mix_h -> 650 | I65: =Thesis!H65-Thesis!I64*mix_h -> 552 | J65: =Thesis!I65-Thesis!J64*mix_h -> 404 | K65: =Thesis!J65-Thesis!K64*mix_h -> 110
A66: 在役對外 MW：GB200 | B66: MW | C66: =mix_g2*Thesis!C57 -> 288 | D66: =mix_g2*Thesis!D57 -> 733.5 | E66: =mix_g2*Thesis!E57 -> 1462.5 | F66: =Thesis!E66-Thesis!F64*mix_g2 -> 1462.5 | G66: =Thesis!F66-Thesis!G64*mix_g2 -> 1462.5 | H66: =Thesis!G66-Thesis!H64*mix_g2 -> 1462.5 | I66: =Thesis!H66-Thesis!I64*mix_g2 -> 1242 | J66: =Thesis!I66-Thesis!J64*mix_g2 -> 909 | K66: =Thesis!J66-Thesis!K64*mix_g2 -> 247.5
A67: 在役對外 MW：GB300（含 Maia 200） | B67: MW | C67: =mix_g3*Thesis!C57 -> 224 | D67: =mix_g3*Thesis!D57 -> 570.5 | E67: =mix_g3*Thesis!E57 -> 1137.5 | F67: =Thesis!E67+(Thesis!F63+Thesis!F64)*a_g3_27-Thesis!F64*mix_g3 -> 2906.54 | G67: =Thesis!F67+(Thesis!G63+Thesis!G64)*a_g3_28-Thesis!G64*mix_g3 -> 3664.7 | H67: =Thesis!G67+(Thesis!H63+Thesis!H64)*a_g3_29-Thesis!H64*mix_g3 -> 3917.42 | I67: =Thesis!H67+(Thesis!I63+Thesis!I64)*a_g3_29-Thesis!I64*mix_g3 -> 3974.2316 | J67: =Thesis!I67+(Thesis!J63+Thesis!J64)*a_g3_29-Thesis!J64*mix_g3 -> 3895.1348 | K67: =Thesis!J67+(Thesis!K63+Thesis!K64)*a_g3_29-Thesis!K64*mix_g3 -> 3560.1296
A68: 在役對外 MW：VR200 | B68: MW | C68: 0 | D68: 0 | E68: 0 | F68: =Thesis!E68+(Thesis!F63+Thesis!F64)*(1-a_g3_27) -> 758.16 | G68: =Thesis!F68+(Thesis!G63+Thesis!G64)*(1-a_g3_28) -> 2527.2 | H68: =Thesis!G68+(Thesis!H63+Thesis!H64)*(1-a_g3_29) -> 4801.68 | I68: =Thesis!H68+(Thesis!I63+Thesis!I64)*(1-a_g3_29) -> 6856.4844 | J68: =Thesis!I68+(Thesis!J63+Thesis!J64)*(1-a_g3_29) -> 8475.6132 | K68: =Thesis!J68+(Thesis!K63+Thesis!K64)*(1-a_g3_29) -> 10091.066
A69: 在役世代加權 IF_HoldEcon | B69: US$M/MW-年 | C69: =(Thesis!C65*tk_hold_h100+Thesis!C66*tk_hold_gb200+Thesis!C67*tk_hold_gb300+Thesis!C68*tk_hold_vr200)/Thesis!C57 -> 9.7235358 | D69: =(Thesis!D65*tk_hold_h100+Thesis!D66*tk_hold_gb200+Thesis!D67*tk_hold_gb300+Thesis!D68*tk_hold_vr200)/Thesis!D57 -> 9.7235358 | E69: =(Thesis!E65*tk_hold_h100+Thesis!E66*tk_hold_gb200+Thesis!E67*tk_hold_gb300+Thesis!E68*tk_hold_vr200)/Thesis!E57 -> 9.7235358 | F69: =(Thesis!F65*tk_hold_h100+Thesis!F66*tk_hold_gb200+Thesis!F67*tk_hold_gb300+Thesis!F68*tk_hold_vr200)/Thesis!F57 -> 10.407957 | G69: =(Thesis!G65*tk_hold_h100+Thesis!G66*tk_hold_gb200+Thesis!G67*tk_hold_gb300+Thesis!G68*tk_hold_vr200)/Thesis!G57 -> 10.838813 | H69: =(Thesis!H65*tk_hold_h100+Thesis!H66*tk_hold_gb200+Thesis!H67*tk_hold_gb300+Thesis!H68*tk_hold_vr200)/Thesis!H57 -> 11.131102 | I69: =(Thesis!I65*tk_hold_h100+Thesis!I66*tk_hold_gb200+Thesis!I67*tk_hold_gb300+Thesis!I68*tk_hold_vr200)/Thesis!I57 -> 11.359428 | J69: =(Thesis!J65*tk_hold_h100+Thesis!J66*tk_hold_gb200+Thesis!J67*tk_hold_gb300+Thesis!J68*tk_hold_vr200)/Thesis!J57 -> 11.544151 | K69: =(Thesis!K65*tk_hold_h100+Thesis!K66*tk_hold_gb200+Thesis!K67*tk_hold_gb300+Thesis!K68*tk_hold_vr200)/Thesis!K57 -> 11.805338
A70: k（長約占比 × k_長約＋其餘 × k_現貨） | B70: x | C70: =k_B -> 1.1721393 | D70: =k_B -> 1.1721393 | E70: =k_B -> 1.1721393 | F70: =(k_B+((ls_B*k_long+(1-ls_B)*k_spot)-k_B)*MIN(1,(Thesis!F55-base_fy)/k_ramp)) -> 1.1721393 | G70: =(k_B+((ls_B*k_long+(1-ls_B)*k_spot)-k_B)*MIN(1,(Thesis!G55-base_fy)/k_ramp)) -> 1.1721393 | H70: =(k_B+((ls_B*k_long+(1-ls_B)*k_spot)-k_B)*MIN(1,(Thesis!H55-base_fy)/k_ramp)) -> 1.1721393 | I70: =(k_B+((ls_B*k_long+(1-ls_B)*k_spot)-k_B)*MIN(1,(Thesis!I55-base_fy)/k_ramp)) -> 1.1721393 | J70: =(k_B+((ls_B*k_long+(1-ls_B)*k_spot)-k_B)*MIN(1,(Thesis!J55-base_fy)/k_ramp)) -> 1.1721393 | K70: =(k_B+((ls_B*k_long+(1-ls_B)*k_spot)-k_B)*MIN(1,(Thesis!K55-base_fy)/k_ramp)) -> 1.1721393 | L70: 實績期三情境同用基準 k（拆分是估計，不是情境）；FY2027 起 k_ramp 年線性移到情境 k
A71: 每 MW 年收入（對外） | B71: US$M/MW-年 | C71: =Thesis!C69*Thesis!C70*chip_f -> 11.397339 | D71: =Thesis!D69*Thesis!D70*chip_f -> 11.397339 | E71: =Thesis!E69*Thesis!E70*chip_f -> 11.397339 | F71: =Thesis!F69*Thesis!F70*chip_f -> 12.199576 | G71: =Thesis!G69*Thesis!G70*chip_f -> 12.704599 | H71: =Thesis!H69*Thesis!H70*chip_f -> 13.047202 | I71: =Thesis!I69*Thesis!I70*chip_f -> 13.314833 | J71: =Thesis!J69*Thesis!J70*chip_f -> 13.531353 | K71: =Thesis!K69*Thesis!K70*chip_f -> 13.8375 | L71: 按 MW-year 計價，不乘利用率（v0.2.2 口徑）
A72: Azure AI 營收（期間平均在役對外 MW × 每 MW 年收入） | B72: US$B | D72: =(Thesis!C57+Thesis!D57)/2*Thesis!D71/1000 -> 12.935979 | E72: =(Thesis!D57+Thesis!E57)/2*Thesis!E71/1000 -> 27.809506 | F72: =(Thesis!E57+Thesis!F57)/2*Thesis!F71/1000 -> 55.064007 | G72: =(Thesis!F57+Thesis!G57)/2*Thesis!G71/1000 -> 89.450541 | H72: =(Thesis!G57+Thesis!H57)/2*Thesis!H71/1000 -> 124.83563 | I72: =(Thesis!H57+Thesis!I57)/2*Thesis!I71/1000 -> 156.15846 | J72: =(Thesis!I57+Thesis!J57)/2*Thesis!J71/1000 -> 177.99456 | K72: =(Thesis!J57+Thesis!K57)/2*Thesis!K71/1000 -> 191.5971 | L72: FY2025、FY2026 為模型估計（用於拆出 Azure 其他）
A73: 在役世代加權 IF_OpexGW | B73: US$M/MW-年 | C73: =(Thesis!C65*tk_opex_h100+Thesis!C66*tk_opex_gb200+Thesis!C67*tk_opex_gb300+Thesis!C68*tk_opex_vr200)/Thesis!C57 -> 1.8863604 | D73: =(Thesis!D65*tk_opex_h100+Thesis!D66*tk_opex_gb200+Thesis!D67*tk_opex_gb300+Thesis!D68*tk_opex_vr200)/Thesis!D57 -> 1.8863604 | E73: =(Thesis!E65*tk_opex_h100+Thesis!E66*tk_opex_gb200+Thesis!E67*tk_opex_gb300+Thesis!E68*tk_opex_vr200)/Thesis!E57 -> 1.8863604 | F73: =(Thesis!F65*tk_opex_h100+Thesis!F66*tk_opex_gb200+Thesis!F67*tk_opex_gb300+Thesis!F68*tk_opex_vr200)/Thesis!F57 -> 1.9430236 | G73: =(Thesis!G65*tk_opex_h100+Thesis!G66*tk_opex_gb200+Thesis!G67*tk_opex_gb300+Thesis!G68*tk_opex_vr200)/Thesis!G57 -> 1.9786942 | H73: =(Thesis!H65*tk_opex_h100+Thesis!H66*tk_opex_gb200+Thesis!H67*tk_opex_gb300+Thesis!H68*tk_opex_vr200)/Thesis!H57 -> 2.0028928 | I73: =(Thesis!I65*tk_opex_h100+Thesis!I66*tk_opex_gb200+Thesis!I67*tk_opex_gb300+Thesis!I68*tk_opex_vr200)/Thesis!I57 -> 2.0217959 | J73: =(Thesis!J65*tk_opex_h100+Thesis!J66*tk_opex_gb200+Thesis!J67*tk_opex_gb300+Thesis!J68*tk_opex_vr200)/Thesis!J57 -> 2.0370891 | K73: =(Thesis!K65*tk_opex_h100+Thesis!K66*tk_opex_gb200+Thesis!K67*tk_opex_gb300+Thesis!K68*tk_opex_vr200)/Thesis!K57 -> 2.0587127
A74: AI 營運成本：自有 AI MW（平均 × IF_OpexGW） | B74: US$B | D74: =(Thesis!C60+Thesis!D60)/2*Thesis!D73/1000 -> 2.7037833 | E74: =(Thesis!D60+Thesis!E60)/2*Thesis!E73/1000 -> 6.1778304 | F74: =(Thesis!E60+Thesis!F60)/2*Thesis!F73/1000 -> 12.502062 | G74: =(Thesis!F60+Thesis!G60)/2*Thesis!G73/1000 -> 20.726162 | H74: =(Thesis!G60+Thesis!H60)/2*Thesis!H73/1000 -> 29.415818 | I74: =(Thesis!H60+Thesis!I60)/2*Thesis!I73/1000 -> 36.97244 | J74: =(Thesis!I60+Thesis!J60)/2*Thesis!J73/1000 -> 42.093838 | K74: =(Thesis!J60+Thesis!K60)/2*Thesis!K73/1000 -> 44.915011
A75: AI 營運成本：租用 neocloud 租金 | B75: US$B | D75: =(Thesis!C58+Thesis!D58)/2*rent_mw/1000 -> 2.44475 | E75: =(Thesis!D58+Thesis!E58)/2*rent_mw/1000 -> 4.22275 | F75: =(Thesis!E58+Thesis!F58)/2*rent_mw/1000 -> 5.80517 | G75: =(Thesis!F58+Thesis!G58)/2*rent_mw/1000 -> 6.72084 | H75: =(Thesis!G58+Thesis!H58)/2*rent_mw/1000 -> 6.72084 | I75: =(Thesis!H58+Thesis!I58)/2*rent_mw/1000 -> 6.72084 | J75: =(Thesis!I58+Thesis!J58)/2*rent_mw/1000 -> 6.72084 | K75: =(Thesis!J58+Thesis!K58)/2*rent_mw/1000 -> 6.72084
A76: AI 營運成本：租用機房租金（1 − 自建比例） | B76: US$B | D76: =(Thesis!C60+Thesis!D60)/2*(1-self_build)*fac_rent/1000 -> 0.85324238 | E76: =(Thesis!D60+Thesis!E60)/2*(1-self_build)*fac_rent/1000 -> 1.9495596 | F76: =(Thesis!E60+Thesis!F60)/2*(1-self_build)*fac_rent/1000 -> 3.8302646 | G76: =(Thesis!F60+Thesis!G60)/2*(1-self_build)*fac_rent/1000 -> 6.2354159 | H76: =(Thesis!G60+Thesis!H60)/2*(1-self_build)*fac_rent/1000 -> 8.7427579 | I76: =(Thesis!H60+Thesis!I60)/2*(1-self_build)*fac_rent/1000 -> 10.885942 | J76: =(Thesis!I60+Thesis!J60)/2*(1-self_build)*fac_rent/1000 -> 12.30081 | K76: =(Thesis!J60+Thesis!K60)/2*(1-self_build)*fac_rent/1000 -> 12.987363 | L76: C22
A77: 自有 AI 中對外的比重（期間平均） | B77: % | D77: =(Thesis!C59+Thesis!D59)/(Thesis!C60+Thesis!D60) -> 0.6 | E77: =(Thesis!D59+Thesis!E59)/(Thesis!D60+Thesis!E60) -> 0.6 | F77: =(Thesis!E59+Thesis!F59)/(Thesis!E60+Thesis!F60) -> 0.6 | G77: =(Thesis!F59+Thesis!G59)/(Thesis!F60+Thesis!G60) -> 0.6 | H77: =(Thesis!G59+Thesis!H59)/(Thesis!G60+Thesis!H60) -> 0.6 | I77: =(Thesis!H59+Thesis!I59)/(Thesis!H60+Thesis!I60) -> 0.6 | J77: =(Thesis!I59+Thesis!J59)/(Thesis!I60+Thesis!J60) -> 0.6 | K77: =(Thesis!J59+Thesis!K59)/(Thesis!J60+Thesis!K60) -> 0.6
A78: Azure AI EBITDA（營收 − 對外營運成本 − 租金） | B78: US$B | D78: =Thesis!D72-Thesis!D77*(Thesis!D74+Thesis!D76)-Thesis!D75 -> 8.3570141 | E78: =Thesis!E72-Thesis!E77*(Thesis!E74+Thesis!E76)-Thesis!E75 -> 18.710322 | F78: =Thesis!F72-Thesis!F77*(Thesis!F74+Thesis!F76)-Thesis!F75 -> 39.459441 | G78: =Thesis!G72-Thesis!G77*(Thesis!G74+Thesis!G76)-Thesis!G75 -> 66.552755 | H78: =Thesis!H72-Thesis!H77*(Thesis!H74+Thesis!H76)-Thesis!H75 -> 95.219645 | I78: =Thesis!I72-Thesis!I77*(Thesis!I74+Thesis!I76)-Thesis!I75 -> 120.72259 | J78: =Thesis!J72-Thesis!J77*(Thesis!J74+Thesis!J76)-Thesis!J75 -> 138.63693 | K78: =Thesis!K72-Thesis!K77*(Thesis!K74+Thesis!K76)-Thesis!K75 -> 150.13484
A79: 自用 AI 營運成本（服務 Copilot 等自有產品） | B79: US$B | D79: =(1-Thesis!D77)*(Thesis!D74+Thesis!D76) -> 1.4228103 | E79: =(1-Thesis!E77)*(Thesis!E74+Thesis!E76) -> 3.250956 | F79: =(1-Thesis!F77)*(Thesis!F74+Thesis!F76) -> 6.5329306 | G79: =(1-Thesis!G77)*(Thesis!G74+Thesis!G76) -> 10.784631 | H79: =(1-Thesis!H77)*(Thesis!H74+Thesis!H76) -> 15.263431 | I79: =(1-Thesis!I77)*(Thesis!I74+Thesis!I76) -> 19.143353 | J79: =(1-Thesis!J77)*(Thesis!J74+Thesis!J76) -> 21.757859 | K79: =(1-Thesis!K77)*(Thesis!K74+Thesis!K76) -> 23.160949
A80: 新增與汰換 MW 的 IT 資本支出（世代加權） | B80: US$M/MW | C80: =cxit_open -> 27.5919 | D80: =cxit_open -> 27.5919 | E80: =cxit_open -> 27.5919 | F80: =(a_g3_27*tk_cxit_gb300+(1-a_g3_27)*tk_cxit_vr200) -> 33.841962 | G80: =(a_g3_28*tk_cxit_gb300+(1-a_g3_28)*tk_cxit_vr200) -> 35.981614 | H80: =(a_g3_29*tk_cxit_gb300+(1-a_g3_29)*tk_cxit_vr200) -> 37.051439 | I80: =(a_g3_29*tk_cxit_gb300+(1-a_g3_29)*tk_cxit_vr200) -> 37.051439 | J80: =(a_g3_29*tk_cxit_gb300+(1-a_g3_29)*tk_cxit_vr200) -> 37.051439 | K80: =(a_g3_29*tk_cxit_gb300+(1-a_g3_29)*tk_cxit_vr200) -> 37.051439 | L80: FY2026 以前用期初世代加權（估計）
A81: GPU 汰換 MW（自有 AI MW 滿 IT 年限者） | B81: MW | F81: =Thesis!C62*IF(Thesis!F55-Thesis!C55=life_it,1,0)+Thesis!D62*IF(Thesis!F55-Thesis!D55=life_it,1,0)+Thesis!E62*IF(Thesis!F55-Thesis!E55=life_it,1,0) -> 0 | G81: =Thesis!C62*IF(Thesis!G55-Thesis!C55=life_it,1,0)+Thesis!D62*IF(Thesis!G55-Thesis!D55=life_it,1,0)+Thesis!E62*IF(Thesis!G55-Thesis!E55=life_it,1,0)+Thesis!F62*IF(Thesis!G55-Thesis!F55=life_it,1,0) -> 0 | H81: =Thesis!C62*IF(Thesis!H55-Thesis!C55=life_it,1,0)+Thesis!D62*IF(Thesis!H55-Thesis!D55=life_it,1,0)+Thesis!E62*IF(Thesis!H55-Thesis!E55=life_it,1,0)+Thesis!F62*IF(Thesis!H55-Thesis!F55=life_it,1,0)+Thesis!G62*IF(Thesis!H55-Thesis!G55=life_it,1,0) -> 0 | I81: =Thesis!C62*IF(Thesis!I55-Thesis!C55=life_it,1,0)+Thesis!D62*IF(Thesis!I55-Thesis!D55=life_it,1,0)+Thesis!E62*IF(Thesis!I55-Thesis!E55=life_it,1,0)+Thesis!F62*IF(Thesis!I55-Thesis!F55=life_it,1,0)+Thesis!G62*IF(Thesis!I55-Thesis!G55=life_it,1,0)+Thesis!H62*IF(Thesis!I55-Thesis!H55=life_it,1,0) -> 816.66667 | J81: =Thesis!C62*IF(Thesis!J55-Thesis!C55=life_it,1,0)+Thesis!D62*IF(Thesis!J55-Thesis!D55=life_it,1,0)+Thesis!E62*IF(Thesis!J55-Thesis!E55=life_it,1,0)+Thesis!F62*IF(Thesis!J55-Thesis!F55=life_it,1,0)+Thesis!G62*IF(Thesis!J55-Thesis!G55=life_it,1,0)+Thesis!H62*IF(Thesis!J55-Thesis!H55=life_it,1,0)+Thesis!I62*IF(Thesis!J55-Thesis!I55=life_it,1,0) -> 1233.3333 | K81: =Thesis!C62*IF(Thesis!K55-Thesis!C55=life_it,1,0)+Thesis!D62*IF(Thesis!K55-Thesis!D55=life_it,1,0)+Thesis!E62*IF(Thesis!K55-Thesis!E55=life_it,1,0)+Thesis!F62*IF(Thesis!K55-Thesis!F55=life_it,1,0)+Thesis!G62*IF(Thesis!K55-Thesis!G55=life_it,1,0)+Thesis!H62*IF(Thesis!K55-Thesis!H55=life_it,1,0)+Thesis!I62*IF(Thesis!K55-Thesis!I55=life_it,1,0)+Thesis!J62*IF(Thesis!K55-Thesis!J55=life_it,1,0) -> 2450 | L81: 只換 IT、機房不換；FY2024 欄含 FY2024 以前全部（視同 FY2024 投入）；舊機隊在年限到期後停止折舊，汰換後的新 IT 另計折舊（不重複）
A82: AI IT 資本支出（公式） | B82: US$B | C82: =Thesis!C62*Thesis!C80/1000 -> 22.533385 | D82: =Thesis!D62*Thesis!D80/1000 -> 34.030009 | E82: =Thesis!E62*Thesis!E80/1000 -> 67.600154 | F82: =(Thesis!F62+Thesis!F81)*Thesis!F80/1000 -> 130.92327 | G82: =(Thesis!G62+Thesis!G81)*Thesis!G80/1000 -> 151.55456 | H82: =(Thesis!H62+Thesis!H81)*Thesis!H80/1000 -> 156.06066 | I82: =(Thesis!I62+Thesis!I81)*Thesis!I80/1000 -> 140.98789 | J82: =(Thesis!J62+Thesis!J81)*Thesis!J80/1000 -> 111.09454 | K82: =(Thesis!K62+Thesis!K81)*Thesis!K80/1000 -> 110.84234
A83: AI 機房資本支出（自建比例 × IF_CapexFacility） | B83: US$B | C83: =Thesis!C62*self_build*tk_cxfac/1000 -> 6.2083 | D83: =Thesis!D62*self_build*tk_cxfac/1000 -> 9.3758 | E83: =Thesis!E62*self_build*tk_cxfac/1000 -> 18.6249 | F83: =Thesis!F62*self_build*tk_cxfac/1000 -> 29.409604 | G83: =Thesis!G62*self_build*tk_cxfac/1000 -> 32.019624 | H83: =Thesis!H62*self_build*tk_cxfac/1000 -> 32.019624 | I83: =Thesis!I62*self_build*tk_cxfac/1000 -> 22.71878 | J83: =Thesis!J62*self_build*tk_cxfac/1000 -> 13.417935 | K83: =Thesis!K62*self_build*tk_cxfac/1000 -> 4.1170912
A84: FY2027 補足到公司資本支出下限的差額（計入 IT） | B84: US$B | F84: =MAX(0,capex_floor27-Thesis!F82-Thesis!F83-CF!F52) -> 8.2877769 | L84: 近期以公司指引為下限（C10 方法沿用）；IT 占約三分之二（法說短期資產）
A85: AI IT 資本支出（含補足差額） | B85: US$B | C85: =Thesis!C82 -> 22.533385 | D85: =Thesis!D82 -> 34.030009 | E85: =Thesis!E82 -> 67.600154 | F85: =Thesis!F82+Thesis!F84 -> 139.21105 | G85: =Thesis!G82 -> 151.55456 | H85: =Thesis!H82 -> 156.06066 | I85: =Thesis!I82 -> 140.98789 | J85: =Thesis!J82 -> 111.09454 | K85: =Thesis!K82 -> 110.84234
A86: AI 資本支出合計 | B86: US$B | C86: =Thesis!C85+Thesis!C83 -> 28.741685 | D86: =Thesis!D85+Thesis!D83 -> 43.405809 | E86: =Thesis!E85+Thesis!E83 -> 86.225054 | F86: =Thesis!F85+Thesis!F83 -> 168.62065 | G86: =Thesis!G85+Thesis!G83 -> 183.57418 | H86: =Thesis!H85+Thesis!H83 -> 188.08029 | I86: =Thesis!I85+Thesis!I83 -> 163.70667 | J86: =Thesis!J85+Thesis!J83 -> 124.51248 | K86: =Thesis!K85+Thesis!K83 -> 114.95944 | L86: FY2026 以前為依 MW 估計的值（非公司揭露）
A87: AI IT 折舊（半年慣例、年限 life_it） | B87: US$B | E87: =(Thesis!C85*IF(2<life_it,1,IF(2=life_it,0.5,0))+Thesis!D85*IF(1<life_it,1,IF(1=life_it,0.5,0))+Thesis!E85*0.5)/life_it -> 15.060578 | F87: =(Thesis!C85*IF(3<life_it,1,IF(3=life_it,0.5,0))+Thesis!D85*IF(2<life_it,1,IF(2=life_it,0.5,0))+Thesis!E85*IF(1<life_it,1,IF(1=life_it,0.5,0))+Thesis!F85*0.5)/life_it -> 32.294845 | G87: =(Thesis!C85*IF(4<life_it,1,IF(4=life_it,0.5,0))+Thesis!D85*IF(3<life_it,1,IF(3=life_it,0.5,0))+Thesis!E85*IF(2<life_it,1,IF(2=life_it,0.5,0))+Thesis!F85*IF(1<life_it,1,IF(1=life_it,0.5,0))+Thesis!G85*0.5)/life_it -> 56.525312 | H87: =(Thesis!C85*IF(5<life_it,1,IF(5=life_it,0.5,0))+Thesis!D85*IF(4<life_it,1,IF(4=life_it,0.5,0))+Thesis!E85*IF(3<life_it,1,IF(3=life_it,0.5,0))+Thesis!F85*IF(2<life_it,1,IF(2=life_it,0.5,0))+Thesis!G85*IF(1<life_it,1,IF(1=life_it,0.5,0))+Thesis!H85*0.5)/life_it -> 82.159914 | I87: =(Thesis!C85*IF(6<life_it,1,IF(6=life_it,0.5,0))+Thesis!D85*IF(5<life_it,1,IF(5=life_it,0.5,0))+Thesis!E85*IF(4<life_it,1,IF(4=life_it,0.5,0))+Thesis!F85*IF(3<life_it,1,IF(3=life_it,0.5,0))+Thesis!G85*IF(2<life_it,1,IF(2=life_it,0.5,0))+Thesis!H85*IF(1<life_it,1,IF(1=life_it,0.5,0))+Thesis!I85*0.5)/life_it -> 105.03618 | J87: =(Thesis!C85*IF(7<life_it,1,IF(7=life_it,0.5,0))+Thesis!D85*IF(6<life_it,1,IF(6=life_it,0.5,0))+Thesis!E85*IF(5<life_it,1,IF(5=life_it,0.5,0))+Thesis!F85*IF(4<life_it,1,IF(4=life_it,0.5,0))+Thesis!G85*IF(3<life_it,1,IF(3=life_it,0.5,0))+Thesis!H85*IF(2<life_it,1,IF(2=life_it,0.5,0))+Thesis!I85*IF(1<life_it,1,IF(1=life_it,0.5,0))+Thesis!J85*0.5)/life_it -> 121.32943 | K87: =(Thesis!C85*IF(8<life_it,1,IF(8=life_it,0.5,0))+Thesis!D85*IF(7<life_it,1,IF(7=life_it,0.5,0))+Thesis!E85*IF(6<life_it,1,IF(6=life_it,0.5,0))+Thesis!F85*IF(5<life_it,1,IF(5=life_it,0.5,0))+Thesis!G85*IF(4<life_it,1,IF(4=life_it,0.5,0))+Thesis!H85*IF(3<life_it,1,IF(3=life_it,0.5,0))+Thesis!I85*IF(2<life_it,1,IF(2=life_it,0.5,0))+Thesis!J85*IF(1<life_it,1,IF(1=life_it,0.5,0))+Thesis!K85*0.5)/life_it -> 131.35499
A88: AI 機房折舊（年限 life_fac） | B88: US$B | E88: =(Thesis!C83*IF(2<life_fac,1,IF(2=life_fac,0.5,0))+Thesis!D83*IF(1<life_fac,1,IF(1=life_fac,0.5,0))+Thesis!E83*0.5)/life_fac -> 1.2448275 | F88: =(Thesis!C83*IF(3<life_fac,1,IF(3=life_fac,0.5,0))+Thesis!D83*IF(2<life_fac,1,IF(2=life_fac,0.5,0))+Thesis!E83*IF(1<life_fac,1,IF(1=life_fac,0.5,0))+Thesis!F83*0.5)/life_fac -> 2.4456901 | G88: =(Thesis!C83*IF(4<life_fac,1,IF(4=life_fac,0.5,0))+Thesis!D83*IF(3<life_fac,1,IF(3=life_fac,0.5,0))+Thesis!E83*IF(2<life_fac,1,IF(2=life_fac,0.5,0))+Thesis!F83*IF(1<life_fac,1,IF(1=life_fac,0.5,0))+Thesis!G83*0.5)/life_fac -> 3.9814208 | H88: =(Thesis!C83*IF(5<life_fac,1,IF(5=life_fac,0.5,0))+Thesis!D83*IF(4<life_fac,1,IF(4=life_fac,0.5,0))+Thesis!E83*IF(3<life_fac,1,IF(3=life_fac,0.5,0))+Thesis!F83*IF(2<life_fac,1,IF(2=life_fac,0.5,0))+Thesis!G83*IF(1<life_fac,1,IF(1=life_fac,0.5,0))+Thesis!H83*0.5)/life_fac -> 5.582402 | I88: =(Thesis!C83*IF(6<life_fac,1,IF(6=life_fac,0.5,0))+Thesis!D83*IF(5<life_fac,1,IF(5=life_fac,0.5,0))+Thesis!E83*IF(4<life_fac,1,IF(4=life_fac,0.5,0))+Thesis!F83*IF(3<life_fac,1,IF(3=life_fac,0.5,0))+Thesis!G83*IF(2<life_fac,1,IF(2=life_fac,0.5,0))+Thesis!H83*IF(1<life_fac,1,IF(1=life_fac,0.5,0))+Thesis!I83*0.5)/life_fac -> 6.9508621 | J88: =(Thesis!C83*IF(7<life_fac,1,IF(7=life_fac,0.5,0))+Thesis!D83*IF(6<life_fac,1,IF(6=life_fac,0.5,0))+Thesis!E83*IF(5<life_fac,1,IF(5=life_fac,0.5,0))+Thesis!F83*IF(4<life_fac,1,IF(4=life_fac,0.5,0))+Thesis!G83*IF(3<life_fac,1,IF(3=life_fac,0.5,0))+Thesis!H83*IF(2<life_fac,1,IF(2=life_fac,0.5,0))+Thesis!I83*IF(1<life_fac,1,IF(1=life_fac,0.5,0))+Thesis!J83*0.5)/life_fac -> 7.85428 | K88: =(Thesis!C83*IF(8<life_fac,1,IF(8=life_fac,0.5,0))+Thesis!D83*IF(7<life_fac,1,IF(7=life_fac,0.5,0))+Thesis!E83*IF(6<life_fac,1,IF(6=life_fac,0.5,0))+Thesis!F83*IF(5<life_fac,1,IF(5=life_fac,0.5,0))+Thesis!G83*IF(4<life_fac,1,IF(4=life_fac,0.5,0))+Thesis!H83*IF(3<life_fac,1,IF(3=life_fac,0.5,0))+Thesis!I83*IF(2<life_fac,1,IF(2=life_fac,0.5,0))+Thesis!J83*IF(1<life_fac,1,IF(1=life_fac,0.5,0))+Thesis!K83*0.5)/life_fac -> 8.2926556
A89: AI 折舊合計（進 Agents and Infra 營業利益） | B89: US$B | E89: =Thesis!E87+Thesis!E88 -> 16.305406 | F89: =Thesis!F87+Thesis!F88 -> 34.740535 | G89: =Thesis!G87+Thesis!G88 -> 60.506733 | H89: =Thesis!H87+Thesis!H88 -> 87.742316 | I89: =Thesis!I87+Thesis!I88 -> 111.98704 | J89: =Thesis!J87+Thesis!J88 -> 129.18371 | K89: =Thesis!K87+Thesis!K88 -> 139.64765
A90: Azure AI 營業利益（EBITDA − 對外分攤折舊） | B90: US$B | E90: =Thesis!E78-Thesis!E77*Thesis!E89 -> 8.9270789 | F90: =Thesis!F78-Thesis!F77*Thesis!F89 -> 18.615119 | G90: =Thesis!G78-Thesis!G77*Thesis!G89 -> 30.248715 | H90: =Thesis!H78-Thesis!H77*Thesis!H89 -> 42.574255 | I90: =Thesis!I78-Thesis!I77*Thesis!I89 -> 53.530367 | J90: =Thesis!J78-Thesis!J77*Thesis!J89 -> 61.126704 | K90: =Thesis!K78-Thesis!K77*Thesis!K89 -> 66.34625
A91: Copilot 營收（Seg） | B91: US$B | E91: =Seg!E38 -> 5.25 | F91: =Seg!F38 -> 12 | G91: =Seg!G38 -> 18 | H91: =Seg!H38 -> 24 | I91: =Seg!I38 -> 28.5 | J91: =Seg!J38 -> 31.5 | K91: =Seg!K38 -> 34.5
A92: 自用 AI 影子效益（讀法 2 金額）＝MAX(0, 平均自用 MW × 持有成本（k＝1）− Copilot × 核心利益率) | B92: US$B | F92: =MAX(0,(Thesis!E61+Thesis!F61)/2*Thesis!F69/1000-Thesis!F91*PL!F70) -> 19.935818 | G92: =MAX(0,(Thesis!F61+Thesis!G61)/2*Thesis!G69/1000-Thesis!G91*PL!G70) -> 35.135949 | H92: =MAX(0,(Thesis!G61+Thesis!H61)/2*Thesis!H69/1000-Thesis!H91*PL!H70) -> 51.688537 | I92: =MAX(0,(Thesis!H61+Thesis!I61)/2*Thesis!I69/1000-Thesis!I91*PL!I70) -> 66.819343 | J92: =MAX(0,(Thesis!I61+Thesis!J61)/2*Thesis!J69/1000-Thesis!J91*PL!J70) -> 77.432884 | K92: =MAX(0,(Thesis!J61+Thesis!K61)/2*Thesis!K69/1000-Thesis!K91*PL!K70) -> 83.324964 | L92: 自用 AI 價值中性：自用算力至少回收 Tokenomics 持有成本；Copilot 已在 M365 營收內計入的部分扣除，避免重複
A93: 自用 AI 影子效益（依讀法開關 internal_ai_reading） | B93: US$B | F93: =IF(internal_ai_reading=2,1,0)*Thesis!F92 -> 19.935818 | G93: =IF(internal_ai_reading=2,1,0)*Thesis!G92 -> 35.135949 | H93: =IF(internal_ai_reading=2,1,0)*Thesis!H92 -> 51.688537 | I93: =IF(internal_ai_reading=2,1,0)*Thesis!I92 -> 66.819343 | J93: =IF(internal_ai_reading=2,1,0)*Thesis!J92 -> 77.432884 | K93: =IF(internal_ai_reading=2,1,0)*Thesis!K92 -> 83.324964
A94: AI 增量營業利益（評價口徑）＝Azure AI EBITDA＋Copilot × 核心利益率＋影子效益 − 自用 AI 營運成本 − AI 折舊 | B94: US$B | F94: =Thesis!F78+Thesis!F91*PL!F70+Thesis!F93-Thesis!F79-Thesis!F89 -> 24.973281 | G94: =Thesis!G78+Thesis!G91*PL!G70+Thesis!G93-Thesis!G79-Thesis!G89 -> 40.674572 | H94: =Thesis!H78+Thesis!H91*PL!H70+Thesis!H93-Thesis!H79-Thesis!H89 -> 57.605411 | I94: =Thesis!I78+Thesis!I91*PL!I70+Thesis!I93-Thesis!I79-Thesis!I89 -> 72.683826 | J94: =Thesis!J78+Thesis!J91*PL!J70+Thesis!J93-Thesis!J79-Thesis!J89 -> 83.113401 | K94: =Thesis!K78+Thesis!K91*PL!K70+Thesis!K93-Thesis!K79-Thesis!K89 -> 90.349234
A95: AI PP&E 淨額（年底） | B95: US$B | E95: =Thesis!E60*(cxit_open+self_build*tk_cxfac)/1000*ai_net_open -> 126.69804 | F95: =Thesis!E95+Thesis!F86-Thesis!F89 -> 260.57816 | G95: =Thesis!F95+Thesis!G86-Thesis!G89 -> 383.6456 | H95: =Thesis!G95+Thesis!H86-Thesis!H89 -> 483.98357 | I95: =Thesis!H95+Thesis!I86-Thesis!I89 -> 535.7032 | J95: =Thesis!I95+Thesis!J86-Thesis!J89 -> 531.03197 | K95: =Thesis!J95+Thesis!K86-Thesis!K89 -> 506.34376 | L95: 期初＝自有 AI MW × 每 MW 全成本 × 淨額比（v0.2.2）
A96: AI 增量 ROIC（評價口徑；稅後營業利益 ÷ 平均 AI PP&E 淨額） | B96: % | F96: =Thesis!F94*(1-tax_f)/((Thesis!E95+Thesis!F95)/2) -> 0.10317507 | G96: =Thesis!G94*(1-tax_f)/((Thesis!F95+Thesis!G95)/2) -> 0.10101974 | H96: =Thesis!H94*(1-tax_f)/((Thesis!G95+Thesis!H95)/2) -> 0.10623047 | I96: =Thesis!I94*(1-tax_f)/((Thesis!H95+Thesis!I95)/2) -> 0.11404887 | J96: =Thesis!J94*(1-tax_f)/((Thesis!I95+Thesis!J95)/2) -> 0.1246621 | K96: =Thesis!K94*(1-tax_f)/((Thesis!J95+Thesis!K95)/2) -> 0.13935045
A97: 讀法 1（自用 AI 只計成本）的 AI 增量 ROIC | B97: % | F97: =(Thesis!F94-Thesis!F93)*(1-tax_f)/((Thesis!E95+Thesis!F95)/2) -> 0.020811867 | G97: =(Thesis!G94-Thesis!G93)*(1-tax_f)/((Thesis!F95+Thesis!G95)/2) -> 0.013755773 | H97: =(Thesis!H94-Thesis!H93)*(1-tax_f)/((Thesis!G95+Thesis!H95)/2) -> 0.010911343 | I97: =(Thesis!I94-Thesis!I93)*(1-tax_f)/((Thesis!H95+Thesis!I95)/2) -> 0.0092020143 | J97: =(Thesis!J94-Thesis!J93)*(1-tax_f)/((Thesis!I95+Thesis!J95)/2) -> 0.0085202278 | K97: =(Thesis!K94-Thesis!K93)*(1-tax_f)/((Thesis!J95+Thesis!K95)/2) -> 0.010833907
A98: 讀法 2（自用 AI 價值中性）的 AI 增量 ROIC | B98: % | F98: =(Thesis!F94-Thesis!F93+Thesis!F92)*(1-tax_f)/((Thesis!E95+Thesis!F95)/2) -> 0.10317507 | G98: =(Thesis!G94-Thesis!G93+Thesis!G92)*(1-tax_f)/((Thesis!F95+Thesis!G95)/2) -> 0.10101974 | H98: =(Thesis!H94-Thesis!H93+Thesis!H92)*(1-tax_f)/((Thesis!G95+Thesis!H95)/2) -> 0.10623047 | I98: =(Thesis!I94-Thesis!I93+Thesis!I92)*(1-tax_f)/((Thesis!H95+Thesis!I95)/2) -> 0.11404887 | J98: =(Thesis!J94-Thesis!J93+Thesis!J92)*(1-tax_f)/((Thesis!I95+Thesis!J95)/2) -> 0.1246621 | K98: =(Thesis!K94-Thesis!K93+Thesis!K92)*(1-tax_f)/((Thesis!J95+Thesis!K95)/2) -> 0.13935045
A99: 對外 AI ROIC（Azure AI 營業利益 ÷ 對外分攤的 PP&E；C11 口徑） | B99: % | F99: =Thesis!F90*(1-tax_f)/(Thesis!F77*(Thesis!E95+Thesis!F95)/2) -> 0.12817808 | G99: =Thesis!G90*(1-tax_f)/(Thesis!G77*(Thesis!F95+Thesis!G95)/2) -> 0.12520997 | H99: =Thesis!H90*(1-tax_f)/(Thesis!H77*(Thesis!G95+Thesis!H95)/2) -> 0.13085239 | I99: =Thesis!I90*(1-tax_f)/(Thesis!I77*(Thesis!H95+Thesis!I95)/2) -> 0.13999166 | J99: =Thesis!J90*(1-tax_f)/(Thesis!J77*(Thesis!I95+Thesis!J95)/2) -> 0.15280695 | K99: =Thesis!K90*(1-tax_f)/(Thesis!K77*(Thesis!J95+Thesis!K95)/2) -> 0.17054894
A100: AI 增量 ROIC − WACC | B100: pt | F100: =Thesis!F96-wacc -> 0.00024065475 | G100: =Thesis!G96-wacc -> -0.0019146825 | H100: =Thesis!H96-wacc -> 0.0032960536 | I100: =Thesis!I96-wacc -> 0.011114447 | J100: =Thesis!J96-wacc -> 0.021727675 | K100: =Thesis!K96-wacc -> 0.03641603
...

Sheet Seg
A1: Seg — 營收分部層：官方分部 Agents and Infra、Devices and Consumer（8-K 2026-09-02 重編）→ 八條產品線；Azure ＝ Azure AI（命題）＋ Azure 其他；Microsoft 365 cloud ＝ 基礎 ＋ Copilot（命題）
A2: 非命題產品線：FY2026 對 FY2025 年增線性收斂到長期值（FY2032 到達；In 頁 F 節）；三情境相同。FY2025、FY2026 欄為實績（Azure、M365 cloud 的子列為模型拆分）
A4: 情境 A（樂觀）｜營收分部層（Seg）
A5: 項目 | B5: 單位 | C5: FY2024A | D5: FY2025A | E5: FY2026A | F5: FY2027 | G5: FY2028 | H5: FY2029 | I5: FY2030 | J5: FY2031 | K5: FY2032 | L5: 說明
A6: Azure AI（命題子列） | B6: US$B | D6: =Thesis!D23 -> 12.935979 | E6: =Thesis!E23 -> 27.809506 | F6: =Thesis!F23 -> 58.732419 | G6: =Thesis!G23 -> 101.36909 | H6: =Thesis!H23 -> 149.78561 | I6: =Thesis!I23 -> 187.3687 | J6: =Thesis!J23 -> 213.56902 | K6: =Thesis!K23 -> 229.89021
A7: Azure 其他（非 AI 雲端；FY2025–26＝Azure 實績 − Azure AI 估計） | B7: US$B | D7: =Q!L6-Seg!D6 -> 59.674021 | E7: =Q!M6-Seg!E6 -> 74.128494 | F7: =Seg!E7*(1+Seg!F8) -> 90.07995 | G7: =Seg!F7*(1+Seg!G8) -> 107.02843 | H7: =Seg!G7*(1+Seg!H8) -> 124.27198 | I7: =Seg!H7*(1+Seg!I8) -> 140.9337 | J7: =Seg!I7*(1+Seg!J8) -> 156.01887 | K7: =Seg!J7*(1+Seg!K8) -> 168.50038
A8: 年增（近一年 → 長期值） | B8: % | E8: =Seg!E7/Seg!D7-1 -> 0.24222388 | F8: =Seg!$E$8+(glt_azo-Seg!$E$8)*MIN(1,(Thesis!F6-base_fy)/n_conv) -> 0.21518657 | G8: =Seg!$E$8+(glt_azo-Seg!$E$8)*MIN(1,(Thesis!G6-base_fy)/n_conv) -> 0.18814926 | H8: =Seg!$E$8+(glt_azo-Seg!$E$8)*MIN(1,(Thesis!H6-base_fy)/n_conv) -> 0.16111194 | I8: =Seg!$E$8+(glt_azo-Seg!$E$8)*MIN(1,(Thesis!I6-base_fy)/n_conv) -> 0.13407463 | J8: =Seg!$E$8+(glt_azo-Seg!$E$8)*MIN(1,(Thesis!J6-base_fy)/n_conv) -> 0.10703731 | K8: =Seg!$E$8+(glt_azo-Seg!$E$8)*MIN(1,(Thesis!K6-base_fy)/n_conv) -> 0.08
A9: Azure | B9: US$B | D9: =Seg!D6+Seg!D7 -> 72.61 | E9: =Seg!E6+Seg!E7 -> 101.938 | F9: =Seg!F6+Seg!F7 -> 148.81237 | G9: =Seg!G6+Seg!G7 -> 208.39751 | H9: =Seg!H6+Seg!H7 -> 274.05759 | I9: =Seg!I6+Seg!I7 -> 328.30241 | J9: =Seg!J6+Seg!J7 -> 369.58789 | K9: =Seg!K6+Seg!K7 -> 398.39058
A10: Copilot 付費座席（年底） | B10: 百萬席 | C10: =cop_s24 -> 1 | D10: =cop_s25 -> 5 | E10: =cop_s26 -> 30 | F10: =Seg!E10+cop_add_A -> 60 | G10: =Seg!F10+cop_add_A -> 90 | H10: =Seg!G10+cop_add_A -> 120 | I10: =Seg!H10+cop_add_A*cop_tail -> 135 | J10: =Seg!I10+cop_add_A*cop_tail -> 150 | K10: =Seg!J10+cop_add_A*cop_tail -> 165 | L10: FY2027–FY2029 每年淨增 cop_add；FY2030 起 × cop_tail
A11: Copilot（命題子列：平均座席 × 月費 × 12） | B11: US$B | D11: =(Seg!C10+Seg!D10)/2*cop_px*12/1000 -> 0.9 | E11: =(Seg!D10+Seg!E10)/2*cop_px*12/1000 -> 5.25 | F11: =(Seg!E10+Seg!F10)/2*cop_px*12/1000 -> 13.5 | G11: =(Seg!F10+Seg!G10)/2*cop_px*12/1000 -> 22.5 | H11: =(Seg!G10+Seg!H10)/2*cop_px*12/1000 -> 31.5 | I11: =(Seg!H10+Seg!I10)/2*cop_px*12/1000 -> 38.25 | J11: =(Seg!I10+Seg!J10)/2*cop_px*12/1000 -> 42.75 | K11: =(Seg!J10+Seg!K10)/2*cop_px*12/1000 -> 47.25 | L11: 實績期用基準月費（拆分是估計）；敏感度只改預測期
A12: M365 基礎（不含 Copilot；FY2025–26＝實績 − Copilot 估計） | B12: US$B | D12: =Q!L7-Seg!D11 -> 83.705 | E12: =Q!M7-Seg!E11 -> 95.049 | F12: =Seg!E12*(1+Seg!F13) -> 106.89239 | G12: =Seg!F12*(1+Seg!G13) -> 119.04417 | H12: =Seg!G12*(1+Seg!H13) -> 131.27736 | I12: =Seg!H12*(1+Seg!I13) -> 143.33403 | J12: =Seg!I12*(1+Seg!J13) -> 154.9327 | K12: =Seg!J12*(1+Seg!K13) -> 165.77799
A13: 年增（近一年 → 長期值） | B13: % | E13: =Seg!E12/Seg!D12-1 -> 0.13552356 | F13: =Seg!$E$13+(glt_m365b-Seg!$E$13)*MIN(1,(Thesis!F6-base_fy)/n_conv) -> 0.12460297 | G13: =Seg!$E$13+(glt_m365b-Seg!$E$13)*MIN(1,(Thesis!G6-base_fy)/n_conv) -> 0.11368238 | H13: =Seg!$E$13+(glt_m365b-Seg!$E$13)*MIN(1,(Thesis!H6-base_fy)/n_conv) -> 0.10276178 | I13: =Seg!$E$13+(glt_m365b-Seg!$E$13)*MIN(1,(Thesis!I6-base_fy)/n_conv) -> 0.091841188 | J13: =Seg!$E$13+(glt_m365b-Seg!$E$13)*MIN(1,(Thesis!J6-base_fy)/n_conv) -> 0.080920594 | K13: =Seg!$E$13+(glt_m365b-Seg!$E$13)*MIN(1,(Thesis!K6-base_fy)/n_conv) -> 0.07
A14: Microsoft 365 cloud | B14: US$B | D14: =Seg!D12+Seg!D11 -> 84.605 | E14: =Seg!E12+Seg!E11 -> 100.299 | F14: =Seg!F12+Seg!F11 -> 120.39239 | G14: =Seg!G12+Seg!G11 -> 141.54417 | H14: =Seg!H12+Seg!H11 -> 162.77736 | I14: =Seg!I12+Seg!I11 -> 181.58403 | J14: =Seg!J12+Seg!J11 -> 197.6827 | K14: =Seg!K12+Seg!K11 -> 213.02799
A15: Productivity and server licensing | B15: US$B | D15: =Q!L8 -> 35.391 | E15: =Q!M8 -> 37.285 | F15: =Seg!E15*(1+Seg!F16) -> 39.072083 | G15: =Seg!F15*(1+Seg!G16) -> 40.726563 | H15: =Seg!G15*(1+Seg!H16) -> 42.223599 | I15: =Seg!H15*(1+Seg!I16) -> 43.539799 | J15: =Seg!I15*(1+Seg!J16) -> 44.653811 | K15: =Seg!J15*(1+Seg!K16) -> 45.546887
A16: 年增（近一年 → 長期值） | B16: % | E16: =Seg!E15/Seg!D15-1 -> 0.053516431 | F16: =Seg!$E$16+(glt_lic-Seg!$E$16)*MIN(1,(Thesis!F6-base_fy)/n_conv) -> 0.047930359 | G16: =Seg!$E$16+(glt_lic-Seg!$E$16)*MIN(1,(Thesis!G6-base_fy)/n_conv) -> 0.042344287 | H16: =Seg!$E$16+(glt_lic-Seg!$E$16)*MIN(1,(Thesis!H6-base_fy)/n_conv) -> 0.036758215 | I16: =Seg!$E$16+(glt_lic-Seg!$E$16)*MIN(1,(Thesis!I6-base_fy)/n_conv) -> 0.031172144 | J16: =Seg!$E$16+(glt_lic-Seg!$E$16)*MIN(1,(Thesis!J6-base_fy)/n_conv) -> 0.025586072 | K16: =Seg!$E$16+(glt_lic-Seg!$E$16)*MIN(1,(Thesis!K6-base_fy)/n_conv) -> 0.02
A17: Industry solutions | B17: US$B | D17: =Q!L9 -> 18.417 | E17: =Q!M9 -> 20.345 | F17: =Seg!E17*(1+Seg!F18) -> 22.35722 | G17: =Seg!F17*(1+Seg!G18) -> 24.439212 | H17: =Seg!G17*(1+Seg!H18) -> 26.573805 | I17: =Seg!H17*(1+Seg!I18) -> 28.741217 | J17: =Seg!I17*(1+Seg!J18) -> 30.919255 | K17: =Seg!J17*(1+Seg!K18) -> 33.083602
A18: 年增（近一年 → 長期值） | B18: % | E18: =Seg!E17/Seg!D17-1 -> 0.10468589 | F18: =Seg!$E$18+(glt_ind-Seg!$E$18)*MIN(1,(Thesis!F6-base_fy)/n_conv) -> 0.098904907 | G18: =Seg!$E$18+(glt_ind-Seg!$E$18)*MIN(1,(Thesis!G6-base_fy)/n_conv) -> 0.093123925 | H18: =Seg!$E$18+(glt_ind-Seg!$E$18)*MIN(1,(Thesis!H6-base_fy)/n_conv) -> 0.087342944 | I18: =Seg!$E$18+(glt_ind-Seg!$E$18)*MIN(1,(Thesis!I6-base_fy)/n_conv) -> 0.081561963 | J18: =Seg!$E$18+(glt_ind-Seg!$E$18)*MIN(1,(Thesis!J6-base_fy)/n_conv) -> 0.075780981 | K18: =Seg!$E$18+(glt_ind-Seg!$E$18)*MIN(1,(Thesis!K6-base_fy)/n_conv) -> 0.07
A19: Frontier and support services | B19: US$B | D19: =Q!L10 -> 7.76 | E19: =Q!M10 -> 8.26 | F19: =Seg!E19*(1+Seg!F20) -> 8.7998804 | G19: =Seg!F19*(1+Seg!G20) -> 9.3832127 | H19: =Seg!G19*(1+Seg!H20) -> 10.013919 | I19: =Seg!H19*(1+Seg!I20) -> 10.696311 | J19: =Seg!I19*(1+Seg!J20) -> 11.435129 | K19: =Seg!J19*(1+Seg!K20) -> 12.235588
A20: 年增（近一年 → 長期值） | B20: % | E20: =Seg!E19/Seg!D19-1 -> 0.06443299 | F20: =Seg!$E$20+(glt_fro-Seg!$E$20)*MIN(1,(Thesis!F6-base_fy)/n_conv) -> 0.065360825 | G20: =Seg!$E$20+(glt_fro-Seg!$E$20)*MIN(1,(Thesis!G6-base_fy)/n_conv) -> 0.06628866 | H20: =Seg!$E$20+(glt_fro-Seg!$E$20)*MIN(1,(Thesis!H6-base_fy)/n_conv) -> 0.067216495 | I20: =Seg!$E$20+(glt_fro-Seg!$E$20)*MIN(1,(Thesis!I6-base_fy)/n_conv) -> 0.06814433 | J20: =Seg!$E$20+(glt_fro-Seg!$E$20)*MIN(1,(Thesis!J6-base_fy)/n_conv) -> 0.069072165 | K20: =Seg!$E$20+(glt_fro-Seg!$E$20)*MIN(1,(Thesis!K6-base_fy)/n_conv) -> 0.07
A21: Agents and Infra | B21: US$B | D21: =Seg!D9+Seg!D14+Seg!D15+Seg!D17+Seg!D19 -> 218.783 | E21: =Seg!E9+Seg!E14+Seg!E15+Seg!E17+Seg!E19 -> 268.127 | F21: =Seg!F9+Seg!F14+Seg!F15+Seg!F17+Seg!F19 -> 339.43394 | G21: =Seg!G9+Seg!G14+Seg!G15+Seg!G17+Seg!G19 -> 424.49067 | H21: =Seg!H9+Seg!H14+Seg!H15+Seg!H17+Seg!H19 -> 515.64628 | I21: =Seg!I9+Seg!I14+Seg!I15+Seg!I17+Seg!I19 -> 592.86376 | J21: =Seg!J9+Seg!J14+Seg!J15+Seg!J17+Seg!J19 -> 654.27879 | K21: =Seg!K9+Seg!K14+Seg!K15+Seg!K17+Seg!K19 -> 702.28465
A22: Search and advertising | B22: US$B | D22: =Q!L13 -> 22.171 | E22: =Q!M13 -> 24.835 | F22: =Seg!E22*(1+Seg!F23) -> 27.61149 | G22: =Seg!F22*(1+Seg!G23) -> 30.467567 | H22: =Seg!G22*(1+Seg!H23) -> 33.364377 | I22: =Seg!H22*(1+Seg!I23) -> 36.257702 | J22: =Seg!I22*(1+Seg!J23) -> 39.098837 | K22: =Seg!J22*(1+Seg!K23) -> 41.835755
A23: 年增（近一年 → 長期值） | B23: % | E23: =Seg!E22/Seg!D22-1 -> 0.12015696 | F23: =Seg!$E$23+(glt_srch-Seg!$E$23)*MIN(1,(Thesis!F6-base_fy)/n_conv) -> 0.11179747 | G23: =Seg!$E$23+(glt_srch-Seg!$E$23)*MIN(1,(Thesis!G6-base_fy)/n_conv) -> 0.10343797 | H23: =Seg!$E$23+(glt_srch-Seg!$E$23)*MIN(1,(Thesis!H6-base_fy)/n_conv) -> 0.095078481 | I23: =Seg!$E$23+(glt_srch-Seg!$E$23)*MIN(1,(Thesis!I6-base_fy)/n_conv) -> 0.086718987 | J23: =Seg!$E$23+(glt_srch-Seg!$E$23)*MIN(1,(Thesis!J6-base_fy)/n_conv) -> 0.078359494 | K23: =Seg!$E$23+(glt_srch-Seg!$E$23)*MIN(1,(Thesis!K6-base_fy)/n_conv) -> 0.07
A24: XBOX | B24: US$B | D24: =Q!L14 -> 23.455 | E24: =Q!M14 -> 21.79 | F24: =Seg!E24*(1+Seg!F25) -> 20.573628 | G24: =Seg!F24*(1+Seg!G25) -> 19.737145 | H24: =Seg!G24*(1+Seg!H25) -> 19.233976 | I24: =Seg!H24*(1+Seg!I25) -> 19.035309 | J24: =Seg!I24*(1+Seg!J25) -> 19.127354 | K24: =Seg!J24*(1+Seg!K25) -> 19.509901
A25: 年增（近一年 → 長期值） | B25: % | E25: =Seg!E24/Seg!D24-1 -> -0.070986996 | F25: =Seg!$E$25+(glt_xbox-Seg!$E$25)*MIN(1,(Thesis!F6-base_fy)/n_conv) -> -0.055822497 | G25: =Seg!$E$25+(glt_xbox-Seg!$E$25)*MIN(1,(Thesis!G6-base_fy)/n_conv) -> -0.040657998 | H25: =Seg!$E$25+(glt_xbox-Seg!$E$25)*MIN(1,(Thesis!H6-base_fy)/n_conv) -> -0.025493498 | I25: =Seg!$E$25+(glt_xbox-Seg!$E$25)*MIN(1,(Thesis!I6-base_fy)/n_conv) -> -0.010328999 | J25: =Seg!$E$25+(glt_xbox-Seg!$E$25)*MIN(1,(Thesis!J6-base_fy)/n_conv) -> 0.0048355006 | K25: =Seg!$E$25+(glt_xbox-Seg!$E$25)*MIN(1,(Thesis!K6-base_fy)/n_conv) -> 0.02
A26: Windows OEM and devices | B26: US$B | D26: =Q!L15 -> 17.315 | E26: =Q!M15 -> 17.087 | F26: =Seg!E26*(1+Seg!F27) -> 16.956459 | G26: =Seg!F26*(1+Seg!G27) -> 16.920649 | H26: =Seg!G26*(1+Seg!H27) -> 16.978452 | I26: =Seg!H26*(1+Seg!I27) -> 17.130308 | J26: =Seg!I26*(1+Seg!J27) -> 17.378219 | K26: =Seg!J26*(1+Seg!K27) -> 17.725783
A27: 年增（近一年 → 長期值） | B27: % | E27: =Seg!E26/Seg!D26-1 -> -0.013167774 | F27: =Seg!$E$27+(glt_win-Seg!$E$27)*MIN(1,(Thesis!F6-base_fy)/n_conv) -> -0.0076398113 | G27: =Seg!$E$27+(glt_win-Seg!$E$27)*MIN(1,(Thesis!G6-base_fy)/n_conv) -> -0.0021118491 | H27: =Seg!$E$27+(glt_win-Seg!$E$27)*MIN(1,(Thesis!H6-base_fy)/n_conv) -> 0.0034161132 | I27: =Seg!$E$27+(glt_win-Seg!$E$27)*MIN(1,(Thesis!I6-base_fy)/n_conv) -> 0.0089440755 | J27: =Seg!$E$27+(glt_win-Seg!$E$27)*MIN(1,(Thesis!J6-base_fy)/n_conv) -> 0.014472038 | K27: =Seg!$E$27+(glt_win-Seg!$E$27)*MIN(1,(Thesis!K6-base_fy)/n_conv) -> 0.02
A28: Devices and Consumer | B28: US$B | D28: =Seg!D22+Seg!D24+Seg!D26 -> 62.941 | E28: =Seg!E22+Seg!E24+Seg!E26 -> 63.712 | F28: =Seg!F22+Seg!F24+Seg!F26 -> 65.141576 | G28: =Seg!G22+Seg!G24+Seg!G26 -> 67.125361 | H28: =Seg!H22+Seg!H24+Seg!H26 -> 69.576805 | I28: =Seg!I22+Seg!I24+Seg!I26 -> 72.423319 | J28: =Seg!J22+Seg!J24+Seg!J26 -> 75.60441 | K28: =Seg!K22+Seg!K24+Seg!K26 -> 79.07144
A29: 合併營收（分部合計） | B29: US$B | D29: =Seg!D21+Seg!D28 -> 281.724 | E29: =Seg!E21+Seg!E28 -> 331.839 | F29: =Seg!F21+Seg!F28 -> 404.57552 | G29: =Seg!G21+Seg!G28 -> 491.61603 | H29: =Seg!H21+Seg!H28 -> 585.22308 | I29: =Seg!I21+Seg!I28 -> 665.28708 | J29: =Seg!J21+Seg!J28 -> 729.8832 | K29: =Seg!K21+Seg!K28 -> 781.35609
A30: 檢查：產品線合計 − 分部；實績期另比對公司分部值 | B30: US$B | D30: =(Seg!D9+Seg!D14+Seg!D15+Seg!D17+Seg!D19-Seg!D21)+(Seg!D22+Seg!D24+Seg!D26-Seg!D28)+(Seg!D21-Q!L5)+(Seg!D28-Q!L12)+(Seg!D9-Q!L6)+(Seg!D14-Q!L7) -> 0 | E30: =(Seg!E9+Seg!E14+Seg!E15+Seg!E17+Seg!E19-Seg!E21)+(Seg!E22+Seg!E24+Seg!E26-Seg!E28)+(Seg!E21-Q!M5)+(Seg!E28-Q!M12)+(Seg!E9-Q!M6)+(Seg!E14-Q!M7) -> 0 | F30: =(Seg!F9+Seg!F14+Seg!F15+Seg!F17+Seg!F19-Seg!F21)+(Seg!F22+Seg!F24+Seg!F26-Seg!F28) -> 0 | G30: =(Seg!G9+Seg!G14+Seg!G15+Seg!G17+Seg!G19-Seg!G21)+(Seg!G22+Seg!G24+Seg!G26-Seg!G28) -> 0 | H30: =(Seg!H9+Seg!H14+Seg!H15+Seg!H17+Seg!H19-Seg!H21)+(Seg!H22+Seg!H24+Seg!H26-Seg!H28) -> 0 | I30: =(Seg!I9+Seg!I14+Seg!I15+Seg!I17+Seg!I19-Seg!I21)+(Seg!I22+Seg!I24+Seg!I26-Seg!I28) -> 0 | J30: =(Seg!J9+Seg!J14+Seg!J15+Seg!J17+Seg!J19-Seg!J21)+(Seg!J22+Seg!J24+Seg!J26-Seg!J28) -> 0 | K30: =(Seg!K9+Seg!K14+Seg!K15+Seg!K17+Seg!K19-Seg!K21)+(Seg!K22+Seg!K24+Seg!K26-Seg!K28) -> 0
A31: 情境 B（基準）｜營收分部層（Seg）
A32: 項目 | B32: 單位 | C32: FY2024A | D32: FY2025A | E32: FY2026A | F32: FY2027 | G32: FY2028 | H32: FY2029 | I32: FY2030 | J32: FY2031 | K32: FY2032 | L32: 說明
A33: Azure AI（命題子列） | B33: US$B | D33: =Thesis!D72 -> 12.935979 | E33: =Thesis!E72 -> 27.809506 | F33: =Thesis!F72 -> 55.064007 | G33: =Thesis!G72 -> 89.450541 | H33: =Thesis!H72 -> 124.83563 | I33: =Thesis!I72 -> 156.15846 | J33: =Thesis!J72 -> 177.99456 | K33: =Thesis!K72 -> 191.5971
A34: Azure 其他（非 AI 雲端；FY2025–26＝Azure 實績 − Azure AI 估計） | B34: US$B | D34: =Q!L6-Seg!D33 -> 59.674021 | E34: =Q!M6-Seg!E33 -> 74.128494 | F34: =Seg!E34*(1+Seg!F35) -> 90.07995 | G34: =Seg!F34*(1+Seg!G35) -> 107.02843 | H34: =Seg!G34*(1+Seg!H35) -> 124.27198 | I34: =Seg!H34*(1+Seg!I35) -> 140.9337 | J34: =Seg!I34*(1+Seg!J35) -> 156.01887 | K34: =Seg!J34*(1+Seg!K35) -> 168.50038
A35: 年增（近一年 → 長期值） | B35: % | E35: =Seg!E34/Seg!D34-1 -> 0.24222388 | F35: =Seg!$E$35+(glt_azo-Seg!$E$35)*MIN(1,(Thesis!F55-base_fy)/n_conv) -> 0.21518657 | G35: =Seg!$E$35+(glt_azo-Seg!$E$35)*MIN(1,(Thesis!G55-base_fy)/n_conv) -> 0.18814926 | H35: =Seg!$E$35+(glt_azo-Seg!$E$35)*MIN(1,(Thesis!H55-base_fy)/n_conv) -> 0.16111194 | I35: =Seg!$E$35+(glt_azo-Seg!$E$35)*MIN(1,(Thesis!I55-base_fy)/n_conv) -> 0.13407463 | J35: =Seg!$E$35+(glt_azo-Seg!$E$35)*MIN(1,(Thesis!J55-base_fy)/n_conv) -> 0.10703731 | K35: =Seg!$E$35+(glt_azo-Seg!$E$35)*MIN(1,(Thesis!K55-base_fy)/n_conv) -> 0.08
A36: Azure | B36: US$B | D36: =Seg!D33+Seg!D34 -> 72.61 | E36: =Seg!E33+Seg!E34 -> 101.938 | F36: =Seg!F33+Seg!F34 -> 145.14396 | G36: =Seg!G33+Seg!G34 -> 196.47897 | H36: =Seg!H33+Seg!H34 -> 249.10761 | I36: =Seg!I33+Seg!I34 -> 297.09216 | J36: =Seg!J33+Seg!J34 -> 334.01343 | K36: =Seg!K33+Seg!K34 -> 360.09748
A37: Copilot 付費座席（年底） | B37: 百萬席 | C37: =cop_s24 -> 1 | D37: =cop_s25 -> 5 | E37: =cop_s26 -> 30 | F37: =Seg!E37+cop_add_B -> 50 | G37: =Seg!F37+cop_add_B -> 70 | H37: =Seg!G37+cop_add_B -> 90 | I37: =Seg!H37+cop_add_B*cop_tail -> 100 | J37: =Seg!I37+cop_add_B*cop_tail -> 110 | K37: =Seg!J37+cop_add_B*cop_tail -> 120 | L37: FY2027–FY2029 每年淨增 cop_add；FY2030 起 × cop_tail
A38: Copilot（命題子列：平均座席 × 月費 × 12） | B38: US$B | D38: =(Seg!C37+Seg!D37)/2*cop_px*12/1000 -> 0.9 | E38: =(Seg!D37+Seg!E37)/2*cop_px*12/1000 -> 5.25 | F38: =(Seg!E37+Seg!F37)/2*cop_px*12/1000 -> 12 | G38: =(Seg!F37+Seg!G37)/2*cop_px*12/1000 -> 18 | H38: =(Seg!G37+Seg!H37)/2*cop_px*12/1000 -> 24 | I38: =(Seg!H37+Seg!I37)/2*cop_px*12/1000 -> 28.5 | J38: =(Seg!I37+Seg!J37)/2*cop_px*12/1000 -> 31.5 | K38: =(Seg!J37+Seg!K37)/2*cop_px*12/1000 -> 34.5 | L38: 實績期用基準月費（拆分是估計）；敏感度只改預測期
A39: M365 基礎（不含 Copilot；FY2025–26＝實績 − Copilot 估計） | B39: US$B | D39: =Q!L7-Seg!D38 -> 83.705 | E39: =Q!M7-Seg!E38 -> 95.049 | F39: =Seg!E39*(1+Seg!F40) -> 106.89239 | G39: =Seg!F39*(1+Seg!G40) -> 119.04417 | H39: =Seg!G39*(1+Seg!H40) -> 131.27736 | I39: =Seg!H39*(1+Seg!I40) -> 143.33403 | J39: =Seg!I39*(1+Seg!J40) -> 154.9327 | K39: =Seg!J39*(1+Seg!K40) -> 165.77799
A40: 年增（近一年 → 長期值） | B40: % | E40: =Seg!E39/Seg!D39-1 -> 0.13552356 | F40: =Seg!$E$40+(glt_m365b-Seg!$E$40)*MIN(1,(Thesis!F55-base_fy)/n_conv) -> 0.12460297 | G40: =Seg!$E$40+(glt_m365b-Seg!$E$40)*MIN(1,(Thesis!G55-base_fy)/n_conv) -> 0.11368238 | H40: =Seg!$E$40+(glt_m365b-Seg!$E$40)*MIN(1,(Thesis!H55-base_fy)/n_conv) -> 0.10276178 | I40: =Seg!$E$40+(glt_m365b-Seg!$E$40)*MIN(1,(Thesis!I55-base_fy)/n_conv) -> 0.091841188 | J40: =Seg!$E$40+(glt_m365b-Seg!$E$40)*MIN(1,(Thesis!J55-base_fy)/n_conv) -> 0.080920594 | K40: =Seg!$E$40+(glt_m365b-Seg!$E$40)*MIN(1,(Thesis!K55-base_fy)/n_conv) -> 0.07
A41: Microsoft 365 cloud | B41: US$B | D41: =Seg!D39+Seg!D38 -> 84.605 | E41: =Seg!E39+Seg!E38 -> 100.299 | F41: =Seg!F39+Seg!F38 -> 118.89239 | G41: =Seg!G39+Seg!G38 -> 137.04417 | H41: =Seg!H39+Seg!H38 -> 155.27736 | I41: =Seg!I39+Seg!I38 -> 171.83403 | J41: =Seg!J39+Seg!J38 -> 186.4327 | K41: =Seg!K39+Seg!K38 -> 200.27799
A42: Productivity and server licensing | B42: US$B | D42: =Q!L8 -> 35.391 | E42: =Q!M8 -> 37.285 | F42: =Seg!E42*(1+Seg!F43) -> 39.072083 | G42: =Seg!F42*(1+Seg!G43) -> 40.726563 | H42: =Seg!G42*(1+Seg!H43) -> 42.223599 | I42: =Seg!H42*(1+Seg!I43) -> 43.539799 | J42: =Seg!I42*(1+Seg!J43) -> 44.653811 | K42: =Seg!J42*(1+Seg!K43) -> 45.546887
A43: 年增（近一年 → 長期值） | B43: % | E43: =Seg!E42/Seg!D42-1 -> 0.053516431 | F43: =Seg!$E$43+(glt_lic-Seg!$E$43)*MIN(1,(Thesis!F55-base_fy)/n_conv) -> 0.047930359 | G43: =Seg!$E$43+(glt_lic-Seg!$E$43)*MIN(1,(Thesis!G55-base_fy)/n_conv) -> 0.042344287 | H43: =Seg!$E$43+(glt_lic-Seg!$E$43)*MIN(1,(Thesis!H55-base_fy)/n_conv) -> 0.036758215 | I43: =Seg!$E$43+(glt_lic-Seg!$E$43)*MIN(1,(Thesis!I55-base_fy)/n_conv) -> 0.031172144 | J43: =Seg!$E$43+(glt_lic-Seg!$E$43)*MIN(1,(Thesis!J55-base_fy)/n_conv) -> 0.025586072 | K43: =Seg!$E$43+(glt_lic-Seg!$E$43)*MIN(1,(Thesis!K55-base_fy)/n_conv) -> 0.02
A44: Industry solutions | B44: US$B | D44: =Q!L9 -> 18.417 | E44: =Q!M9 -> 20.345 | F44: =Seg!E44*(1+Seg!F45) -> 22.35722 | G44: =Seg!F44*(1+Seg!G45) -> 24.439212 | H44: =Seg!G44*(1+Seg!H45) -> 26.573805 | I44: =Seg!H44*(1+Seg!I45) -> 28.741217 | J44: =Seg!I44*(1+Seg!J45) -> 30.919255 | K44: =Seg!J44*(1+Seg!K45) -> 33.083602
A45: 年增（近一年 → 長期值） | B45: % | E45: =Seg!E44/Seg!D44-1 -> 0.10468589 | F45: =Seg!$E$45+(glt_ind-Seg!$E$45)*MIN(1,(Thesis!F55-base_fy)/n_conv) -> 0.098904907 | G45: =Seg!$E$45+(glt_ind-Seg!$E$45)*MIN(1,(Thesis!G55-base_fy)/n_conv) -> 0.093123925 | H45: =Seg!$E$45+(glt_ind-Seg!$E$45)*MIN(1,(Thesis!H55-base_fy)/n_conv) -> 0.087342944 | I45: =Seg!$E$45+(glt_ind-Seg!$E$45)*MIN(1,(Thesis!I55-base_fy)/n_conv) -> 0.081561963 | J45: =Seg!$E$45+(glt_ind-Seg!$E$45)*MIN(1,(Thesis!J55-base_fy)/n_conv) -> 0.075780981 | K45: =Seg!$E$45+(glt_ind-Seg!$E$45)*MIN(1,(Thesis!K55-base_fy)/n_conv) -> 0.07
A46: Frontier and support services | B46: US$B | D46: =Q!L10 -> 7.76 | E46: =Q!M10 -> 8.26 | F46: =Seg!E46*(1+Seg!F47) -> 8.7998804 | G46: =Seg!F46*(1+Seg!G47) -> 9.3832127 | H46: =Seg!G46*(1+Seg!H47) -> 10.013919 | I46: =Seg!H46*(1+Seg!I47) -> 10.696311 | J46: =Seg!I46*(1+Seg!J47) -> 11.435129 | K46: =Seg!J46*(1+Seg!K47) -> 12.235588
A47: 年增（近一年 → 長期值） | B47: % | E47: =Seg!E46/Seg!D46-1 -> 0.06443299 | F47: =Seg!$E$47+(glt_fro-Seg!$E$47)*MIN(1,(Thesis!F55-base_fy)/n_conv) -> 0.065360825 | G47: =Seg!$E$47+(glt_fro-Seg!$E$47)*MIN(1,(Thesis!G55-base_fy)/n_conv) -> 0.06628866 | H47: =Seg!$E$47+(glt_fro-Seg!$E$47)*MIN(1,(Thesis!H55-base_fy)/n_conv) -> 0.067216495 | I47: =Seg!$E$47+(glt_fro-Seg!$E$47)*MIN(1,(Thesis!I55-base_fy)/n_conv) -> 0.06814433 | J47: =Seg!$E$47+(glt_fro-Seg!$E$47)*MIN(1,(Thesis!J55-base_fy)/n_conv) -> 0.069072165 | K47: =Seg!$E$47+(glt_fro-Seg!$E$47)*MIN(1,(Thesis!K55-base_fy)/n_conv) -> 0.07
A48: Agents and Infra | B48: US$B | D48: =Seg!D36+Seg!D41+Seg!D42+Seg!D44+Seg!D46 -> 218.783 | E48: =Seg!E36+Seg!E41+Seg!E42+Seg!E44+Seg!E46 -> 268.127 | F48: =Seg!F36+Seg!F41+Seg!F42+Seg!F44+Seg!F46 -> 334.26553 | G48: =Seg!G36+Seg!G41+Seg!G42+Seg!G44+Seg!G46 -> 408.07212 | H48: =Seg!H36+Seg!H41+Seg!H42+Seg!H44+Seg!H46 -> 483.1963 | I48: =Seg!I36+Seg!I41+Seg!I42+Seg!I44+Seg!I46 -> 551.90352 | J48: =Seg!J36+Seg!J41+Seg!J42+Seg!J44+Seg!J46 -> 607.45432 | K48: =Seg!K36+Seg!K41+Seg!K42+Seg!K44+Seg!K46 -> 651.24155
A49: Search and advertising | B49: US$B | D49: =Q!L13 -> 22.171 | E49: =Q!M13 -> 24.835 | F49: =Seg!E49*(1+Seg!F50) -> 27.61149 | G49: =Seg!F49*(1+Seg!G50) -> 30.467567 | H49: =Seg!G49*(1+Seg!H50) -> 33.364377 | I49: =Seg!H49*(1+Seg!I50) -> 36.257702 | J49: =Seg!I49*(1+Seg!J50) -> 39.098837 | K49: =Seg!J49*(1+Seg!K50) -> 41.835755
A50: 年增（近一年 → 長期值） | B50: % | E50: =Seg!E49/Seg!D49-1 -> 0.12015696 | F50: =Seg!$E$50+(glt_srch-Seg!$E$50)*MIN(1,(Thesis!F55-base_fy)/n_conv) -> 0.11179747 | G50: =Seg!$E$50+(glt_srch-Seg!$E$50)*MIN(1,(Thesis!G55-base_fy)/n_conv) -> 0.10343797 | H50: =Seg!$E$50+(glt_srch-Seg!$E$50)*MIN(1,(Thesis!H55-base_fy)/n_conv) -> 0.095078481 | I50: =Seg!$E$50+(glt_srch-Seg!$E$50)*MIN(1,(Thesis!I55-base_fy)/n_conv) -> 0.086718987 | J50: =Seg!$E$50+(glt_srch-Seg!$E$50)*MIN(1,(Thesis!J55-base_fy)/n_conv) -> 0.078359494 | K50: =Seg!$E$50+(glt_srch-Seg!$E$50)*MIN(1,(Thesis!K55-base_fy)/n_conv) -> 0.07
A51: XBOX | B51: US$B | D51: =Q!L14 -> 23.455 | E51: =Q!M14 -> 21.79 | F51: =Seg!E51*(1+Seg!F52) -> 20.573628 | G51: =Seg!F51*(1+Seg!G52) -> 19.737145 | H51: =Seg!G51*(1+Seg!H52) -> 19.233976 | I51: =Seg!H51*(1+Seg!I52) -> 19.035309 | J51: =Seg!I51*(1+Seg!J52) -> 19.127354 | K51: =Seg!J51*(1+Seg!K52) -> 19.509901
A52: 年增（近一年 → 長期值） | B52: % | E52: =Seg!E51/Seg!D51-1 -> -0.070986996 | F52: =Seg!$E$52+(glt_xbox-Seg!$E$52)*MIN(1,(Thesis!F55-base_fy)/n_conv) -> -0.055822497 | G52: =Seg!$E$52+(glt_xbox-Seg!$E$52)*MIN(1,(Thesis!G55-base_fy)/n_conv) -> -0.040657998 | H52: =Seg!$E$52+(glt_xbox-Seg!$E$52)*MIN(1,(Thesis!H55-base_fy)/n_conv) -> -0.025493498 | I52: =Seg!$E$52+(glt_xbox-Seg!$E$52)*MIN(1,(Thesis!I55-base_fy)/n_conv) -> -0.010328999 | J52: =Seg!$E$52+(glt_xbox-Seg!$E$52)*MIN(1,(Thesis!J55-base_fy)/n_conv) -> 0.0048355006 | K52: =Seg!$E$52+(glt_xbox-Seg!$E$52)*MIN(1,(Thesis!K55-base_fy)/n_conv) -> 0.02
A53: Windows OEM and devices | B53: US$B | D53: =Q!L15 -> 17.315 | E53: =Q!M15 -> 17.087 | F53: =Seg!E53*(1+Seg!F54) -> 16.956459 | G53: =Seg!F53*(1+Seg!G54) -> 16.920649 | H53: =Seg!G53*(1+Seg!H54) -> 16.978452 | I53: =Seg!H53*(1+Seg!I54) -> 17.130308 | J53: =Seg!I53*(1+Seg!J54) -> 17.378219 | K53: =Seg!J53*(1+Seg!K54) -> 17.725783
A54: 年增（近一年 → 長期值） | B54: % | E54: =Seg!E53/Seg!D53-1 -> -0.013167774 | F54: =Seg!$E$54+(glt_win-Seg!$E$54)*MIN(1,(Thesis!F55-base_fy)/n_conv) -> -0.0076398113 | G54: =Seg!$E$54+(glt_win-Seg!$E$54)*MIN(1,(Thesis!G55-base_fy)/n_conv) -> -0.0021118491 | H54: =Seg!$E$54+(glt_win-Seg!$E$54)*MIN(1,(Thesis!H55-base_fy)/n_conv) -> 0.0034161132 | I54: =Seg!$E$54+(glt_win-Seg!$E$54)*MIN(1,(Thesis!I55-base_fy)/n_conv) -> 0.0089440755 | J54: =Seg!$E$54+(glt_win-Seg!$E$54)*MIN(1,(Thesis!J55-base_fy)/n_conv) -> 0.014472038 | K54: =Seg!$E$54+(glt_win-Seg!$E$54)*MIN(1,(Thesis!K55-base_fy)/n_conv) -> 0.02
A55: Devices and Consumer | B55: US$B | D55: =Seg!D49+Seg!D51+Seg!D53 -> 62.941 | E55: =Seg!E49+Seg!E51+Seg!E53 -> 63.712 | F55: =Seg!F49+Seg!F51+Seg!F53 -> 65.141576 | G55: =Seg!G49+Seg!G51+Seg!G53 -> 67.125361 | H55: =Seg!H49+Seg!H51+Seg!H53 -> 69.576805 | I55: =Seg!I49+Seg!I51+Seg!I53 -> 72.423319 | J55: =Seg!J49+Seg!J51+Seg!J53 -> 75.60441 | K55: =Seg!K49+Seg!K51+Seg!K53 -> 79.07144
A56: 合併營收（分部合計） | B56: US$B | D56: =Seg!D48+Seg!D55 -> 281.724 | E56: =Seg!E48+Seg!E55 -> 331.839 | F56: =Seg!F48+Seg!F55 -> 399.4071 | G56: =Seg!G48+Seg!G55 -> 475.19748 | H56: =Seg!H48+Seg!H55 -> 552.7731 | I56: =Seg!I48+Seg!I55 -> 624.32684 | J56: =Seg!J48+Seg!J55 -> 683.05873 | K56: =Seg!K48+Seg!K55 -> 730.31299
A57: 檢查：產品線合計 − 分部；實績期另比對公司分部值 | B57: US$B | D57: =(Seg!D36+Seg!D41+Seg!D42+Seg!D44+Seg!D46-Seg!D48)+(Seg!D49+Seg!D51+Seg!D53-Seg!D55)+(Seg!D48-Q!L5)+(Seg!D55-Q!L12)+(Seg!D36-Q!L6)+(Seg!D41-Q!L7) -> 0 | E57: =(Seg!E36+Seg!E41+Seg!E42+Seg!E44+Seg!E46-Seg!E48)+(Seg!E49+Seg!E51+Seg!E53-Seg!E55)+(Seg!E48-Q!M5)+(Seg!E55-Q!M12)+(Seg!E36-Q!M6)+(Seg!E41-Q!M7) -> 0 | F57: =(Seg!F36+Seg!F41+Seg!F42+Seg!F44+Seg!F46-Seg!F48)+(Seg!F49+Seg!F51+Seg!F53-Seg!F55) -> 0 | G57: =(Seg!G36+Seg!G41+Seg!G42+Seg!G44+Seg!G46-Seg!G48)+(Seg!G49+Seg!G51+Seg!G53-Seg!G55) -> 0 | H57: =(Seg!H36+Seg!H41+Seg!H42+Seg!H44+Seg!H46-Seg!H48)+(Seg!H49+Seg!H51+Seg!H53-Seg!H55) -> 0 | I57: =(Seg!I36+Seg!I41+Seg!I42+Seg!I44+Seg!I46-Seg!I48)+(Seg!I49+Seg!I51+Seg!I53-Seg!I55) -> 0 | J57: =(Seg!J36+Seg!J41+Seg!J42+Seg!J44+Seg!J46-Seg!J48)+(Seg!J49+Seg!J51+Seg!J53-Seg!J55) -> 0 | K57: =(Seg!K36+Seg!K41+Seg!K42+Seg!K44+Seg!K46-Seg!K48)+(Seg!K49+Seg!K51+Seg!K53-Seg!K55) -> 0
A58: 情境 C（保守）｜營收分部層（Seg）
A59: 項目 | B59: 單位 | C59: FY2024A | D59: FY2025A | E59: FY2026A | F59: FY2027 | G59: FY2028 | H59: FY2029 | I59: FY2030 | J59: FY2031 | K59: FY2032 | L59: 說明
A60: Azure AI（命題子列） | B60: US$B | D60: =Thesis!D121 -> 12.935979 | E60: =Thesis!E121 -> 27.809506 | F60: =Thesis!F121 -> 50.661911 | G60: =Thesis!G121 -> 75.148284 | H60: =Thesis!H121 -> 94.895656 | I60: =Thesis!I121 -> 118.70617 | J60: =Thesis!J121 -> 135.3052 | K60: =Thesis!K121 -> 145.64538
A61: Azure 其他（非 AI 雲端；FY2025–26＝Azure 實績 − Azure AI 估計） | B61: US$B | D61: =Q!L6-Seg!D60 -> 59.674021 | E61: =Q!M6-Seg!E60 -> 74.128494 | F61: =Seg!E61*(1+Seg!F62) -> 90.07995 | G61: =Seg!F61*(1+Seg!G62) -> 107.02843 | H61: =Seg!G61*(1+Seg!H62) -> 124.27198 | I61: =Seg!H61*(1+Seg!I62) -> 140.9337 | J61: =Seg!I61*(1+Seg!J62) -> 156.01887 | K61: =Seg!J61*(1+Seg!K62) -> 168.50038
A62: 年增（近一年 → 長期值） | B62: % | E62: =Seg!E61/Seg!D61-1 -> 0.24222388 | F62: =Seg!$E$62+(glt_azo-Seg!$E$62)*MIN(1,(Thesis!F104-base_fy)/n_conv) -> 0.21518657 | G62: =Seg!$E$62+(glt_azo-Seg!$E$62)*MIN(1,(Thesis!G104-base_fy)/n_conv) -> 0.18814926 | H62: =Seg!$E$62+(glt_azo-Seg!$E$62)*MIN(1,(Thesis!H104-base_fy)/n_conv) -> 0.16111194 | I62: =Seg!$E$62+(glt_azo-Seg!$E$62)*MIN(1,(Thesis!I104-base_fy)/n_conv) -> 0.13407463 | J62: =Seg!$E$62+(glt_azo-Seg!$E$62)*MIN(1,(Thesis!J104-base_fy)/n_conv) -> 0.10703731 | K62: =Seg!$E$62+(glt_azo-Seg!$E$62)*MIN(1,(Thesis!K104-base_fy)/n_conv) -> 0.08
A63: Azure | B63: US$B | D63: =Seg!D60+Seg!D61 -> 72.61 | E63: =Seg!E60+Seg!E61 -> 101.938 | F63: =Seg!F60+Seg!F61 -> 140.74186 | G63: =Seg!G60+Seg!G61 -> 182.17671 | H63: =Seg!H60+Seg!H61 -> 219.16764 | I63: =Seg!I60+Seg!I61 -> 259.63987 | J63: =Seg!J60+Seg!J61 -> 291.32407 | K63: =Seg!K60+Seg!K61 -> 314.14575
A64: Copilot 付費座席（年底） | B64: 百萬席 | C64: =cop_s24 -> 1 | D64: =cop_s25 -> 5 | E64: =cop_s26 -> 30 | F64: =Seg!E64+cop_add_C -> 40 | G64: =Seg!F64+cop_add_C -> 50 | H64: =Seg!G64+cop_add_C -> 60 | I64: =Seg!H64+cop_add_C*cop_tail -> 65 | J64: =Seg!I64+cop_add_C*cop_tail -> 70 | K64: =Seg!J64+cop_add_C*cop_tail -> 75 | L64: FY2027–FY2029 每年淨增 cop_add；FY2030 起 × cop_tail
A65: Copilot（命題子列：平均座席 × 月費 × 12） | B65: US$B | D65: =(Seg!C64+Seg!D64)/2*cop_px*12/1000 -> 0.9 | E65: =(Seg!D64+Seg!E64)/2*cop_px*12/1000 -> 5.25 | F65: =(Seg!E64+Seg!F64)/2*cop_px*12/1000 -> 10.5 | G65: =(Seg!F64+Seg!G64)/2*cop_px*12/1000 -> 13.5 | H65: =(Seg!G64+Seg!H64)/2*cop_px*12/1000 -> 16.5 | I65: =(Seg!H64+Seg!I64)/2*cop_px*12/1000 -> 18.75 | J65: =(Seg!I64+Seg!J64)/2*cop_px*12/1000 -> 20.25 | K65: =(Seg!J64+Seg!K64)/2*cop_px*12/1000 -> 21.75 | L65: 實績期用基準月費（拆分是估計）；敏感度只改預測期
A66: M365 基礎（不含 Copilot；FY2025–26＝實績 − Copilot 估計） | B66: US$B | D66: =Q!L7-Seg!D65 -> 83.705 | E66: =Q!M7-Seg!E65 -> 95.049 | F66: =Seg!E66*(1+Seg!F67) -> 106.89239 | G66: =Seg!F66*(1+Seg!G67) -> 119.04417 | H66: =Seg!G66*(1+Seg!H67) -> 131.27736 | I66: =Seg!H66*(1+Seg!I67) -> 143.33403 | J66: =Seg!I66*(1+Seg!J67) -> 154.9327 | K66: =Seg!J66*(1+Seg!K67) -> 165.77799
A67: 年增（近一年 → 長期值） | B67: % | E67: =Seg!E66/Seg!D66-1 -> 0.13552356 | F67: =Seg!$E$67+(glt_m365b-Seg!$E$67)*MIN(1,(Thesis!F104-base_fy)/n_conv) -> 0.12460297 | G67: =Seg!$E$67+(glt_m365b-Seg!$E$67)*MIN(1,(Thesis!G104-base_fy)/n_conv) -> 0.11368238 | H67: =Seg!$E$67+(glt_m365b-Seg!$E$67)*MIN(1,(Thesis!H104-base_fy)/n_conv) -> 0.10276178 | I67: =Seg!$E$67+(glt_m365b-Seg!$E$67)*MIN(1,(Thesis!I104-base_fy)/n_conv) -> 0.091841188 | J67: =Seg!$E$67+(glt_m365b-Seg!$E$67)*MIN(1,(Thesis!J104-base_fy)/n_conv) -> 0.080920594 | K67: =Seg!$E$67+(glt_m365b-Seg!$E$67)*MIN(1,(Thesis!K104-base_fy)/n_conv) -> 0.07
A68: Microsoft 365 cloud | B68: US$B | D68: =Seg!D66+Seg!D65 -> 84.605 | E68: =Seg!E66+Seg!E65 -> 100.299 | F68: =Seg!F66+Seg!F65 -> 117.39239 | G68: =Seg!G66+Seg!G65 -> 132.54417 | H68: =Seg!H66+Seg!H65 -> 147.77736 | I68: =Seg!I66+Seg!I65 -> 162.08403 | J68: =Seg!J66+Seg!J65 -> 175.1827 | K68: =Seg!K66+Seg!K65 -> 187.52799
A69: Productivity and server licensing | B69: US$B | D69: =Q!L8 -> 35.391 | E69: =Q!M8 -> 37.285 | F69: =Seg!E69*(1+Seg!F70) -> 39.072083 | G69: =Seg!F69*(1+Seg!G70) -> 40.726563 | H69: =Seg!G69*(1+Seg!H70) -> 42.223599 | I69: =Seg!H69*(1+Seg!I70) -> 43.539799 | J69: =Seg!I69*(1+Seg!J70) -> 44.653811 | K69: =Seg!J69*(1+Seg!K70) -> 45.546887
A70: 年增（近一年 → 長期值） | B70: % | E70: =Seg!E69/Seg!D69-1 -> 0.053516431 | F70: =Seg!$E$70+(glt_lic-Seg!$E$70)*MIN(1,(Thesis!F104-base_fy)/n_conv) -> 0.047930359 | G70: =Seg!$E$70+(glt_lic-Seg!$E$70)*MIN(1,(Thesis!G104-base_fy)/n_conv) -> 0.042344287 | H70: =Seg!$E$70+(glt_lic-Seg!$E$70)*MIN(1,(Thesis!H104-base_fy)/n_conv) -> 0.036758215 | I70: =Seg!$E$70+(glt_lic-Seg!$E$70)*MIN(1,(Thesis!I104-base_fy)/n_conv) -> 0.031172144 | J70: =Seg!$E$70+(glt_lic-Seg!$E$70)*MIN(1,(Thesis!J104-base_fy)/n_conv) -> 0.025586072 | K70: =Seg!$E$70+(glt_lic-Seg!$E$70)*MIN(1,(Thesis!K104-base_fy)/n_conv) -> 0.02
A71: Industry solutions | B71: US$B | D71: =Q!L9 -> 18.417 | E71: =Q!M9 -> 20.345 | F71: =Seg!E71*(1+Seg!F72) -> 22.35722 | G71: =Seg!F71*(1+Seg!G72) -> 24.439212 | H71: =Seg!G71*(1+Seg!H72) -> 26.573805 | I71: =Seg!H71*(1+Seg!I72) -> 28.741217 | J71: =Seg!I71*(1+Seg!J72) -> 30.919255 | K71: =Seg!J71*(1+Seg!K72) -> 33.083602
A72: 年增（近一年 → 長期值） | B72: % | E72: =Seg!E71/Seg!D71-1 -> 0.10468589 | F72: =Seg!$E$72+(glt_ind-Seg!$E$72)*MIN(1,(Thesis!F104-base_fy)/n_conv) -> 0.098904907 | G72: =Seg!$E$72+(glt_ind-Seg!$E$72)*MIN(1,(Thesis!G104-base_fy)/n_conv) -> 0.093123925 | H72: =Seg!$E$72+(glt_ind-Seg!$E$72)*MIN(1,(Thesis!H104-base_fy)/n_conv) -> 0.087342944 | I72: =Seg!$E$72+(glt_ind-Seg!$E$72)*MIN(1,(Thesis!I104-base_fy)/n_conv) -> 0.081561963 | J72: =Seg!$E$72+(glt_ind-Seg!$E$72)*MIN(1,(Thesis!J104-base_fy)/n_conv) -> 0.075780981 | K72: =Seg!$E$72+(glt_ind-Seg!$E$72)*MIN(1,(Thesis!K104-base_fy)/n_conv) -> 0.07
A73: Frontier and support services | B73: US$B | D73: =Q!L10 -> 7.76 | E73: =Q!M10 -> 8.26 | F73: =Seg!E73*(1+Seg!F74) -> 8.7998804 | G73: =Seg!F73*(1+Seg!G74) -> 9.3832127 | H73: =Seg!G73*(1+Seg!H74) -> 10.013919 | I73: =Seg!H73*(1+Seg!I74) -> 10.696311 | J73: =Seg!I73*(1+Seg!J74) -> 11.435129 | K73: =Seg!J73*(1+Seg!K74) -> 12.235588
A74: 年增（近一年 → 長期值） | B74: % | E74: =Seg!E73/Seg!D73-1 -> 0.06443299 | F74: =Seg!$E$74+(glt_fro-Seg!$E$74)*MIN(1,(Thesis!F104-base_fy)/n_conv) -> 0.065360825 | G74: =Seg!$E$74+(glt_fro-Seg!$E$74)*MIN(1,(Thesis!G104-base_fy)/n_conv) -> 0.06628866 | H74: =Seg!$E$74+(glt_fro-Seg!$E$74)*MIN(1,(Thesis!H104-base_fy)/n_conv) -> 0.067216495 | I74: =Seg!$E$74+(glt_fro-Seg!$E$74)*MIN(1,(Thesis!I104-base_fy)/n_conv) -> 0.06814433 | J74: =Seg!$E$74+(glt_fro-Seg!$E$74)*MIN(1,(Thesis!J104-base_fy)/n_conv) -> 0.069072165 | K74: =Seg!$E$74+(glt_fro-Seg!$E$74)*MIN(1,(Thesis!K104-base_fy)/n_conv) -> 0.07
A75: Agents and Infra | B75: US$B | D75: =Seg!D63+Seg!D68+Seg!D69+Seg!D71+Seg!D73 -> 218.783 | E75: =Seg!E63+Seg!E68+Seg!E69+Seg!E71+Seg!E73 -> 268.127 | F75: =Seg!F63+Seg!F68+Seg!F69+Seg!F71+Seg!F73 -> 328.36343 | G75: =Seg!G63+Seg!G68+Seg!G69+Seg!G71+Seg!G73 -> 389.26987 | H75: =Seg!H63+Seg!H68+Seg!H69+Seg!H71+Seg!H73 -> 445.75632 | I75: =Seg!I63+Seg!I68+Seg!I69+Seg!I71+Seg!I73 -> 504.70123 | J75: =Seg!J63+Seg!J68+Seg!J69+Seg!J71+Seg!J73 -> 553.51497 | K75: =Seg!K63+Seg!K68+Seg!K69+Seg!K71+Seg!K73 -> 592.53982
A76: Search and advertising | B76: US$B | D76: =Q!L13 -> 22.171 | E76: =Q!M13 -> 24.835 | F76: =Seg!E76*(1+Seg!F77) -> 27.61149 | G76: =Seg!F76*(1+Seg!G77) -> 30.467567 | H76: =Seg!G76*(1+Seg!H77) -> 33.364377 | I76: =Seg!H76*(1+Seg!I77) -> 36.257702 | J76: =Seg!I76*(1+Seg!J77) -> 39.098837 | K76: =Seg!J76*(1+Seg!K77) -> 41.835755
A77: 年增（近一年 → 長期值） | B77: % | E77: =Seg!E76/Seg!D76-1 -> 0.12015696 | F77: =Seg!$E$77+(glt_srch-Seg!$E$77)*MIN(1,(Thesis!F104-base_fy)/n_conv) -> 0.11179747 | G77: =Seg!$E$77+(glt_srch-Seg!$E$77)*MIN(1,(Thesis!G104-base_fy)/n_conv) -> 0.10343797 | H77: =Seg!$E$77+(glt_srch-Seg!$E$77)*MIN(1,(Thesis!H104-base_fy)/n_conv) -> 0.095078481 | I77: =Seg!$E$77+(glt_srch-Seg!$E$77)*MIN(1,(Thesis!I104-base_fy)/n_conv) -> 0.086718987 | J77: =Seg!$E$77+(glt_srch-Seg!$E$77)*MIN(1,(Thesis!J104-base_fy)/n_conv) -> 0.078359494 | K77: =Seg!$E$77+(glt_srch-Seg!$E$77)*MIN(1,(Thesis!K104-base_fy)/n_conv) -> 0.07
A78: XBOX | B78: US$B | D78: =Q!L14 -> 23.455 | E78: =Q!M14 -> 21.79 | F78: =Seg!E78*(1+Seg!F79) -> 20.573628 | G78: =Seg!F78*(1+Seg!G79) -> 19.737145 | H78: =Seg!G78*(1+Seg!H79) -> 19.233976 | I78: =Seg!H78*(1+Seg!I79) -> 19.035309 | J78: =Seg!I78*(1+Seg!J79) -> 19.127354 | K78: =Seg!J78*(1+Seg!K79) -> 19.509901
A79: 年增（近一年 → 長期值） | B79: % | E79: =Seg!E78/Seg!D78-1 -> -0.070986996 | F79: =Seg!$E$79+(glt_xbox-Seg!$E$79)*MIN(1,(Thesis!F104-base_fy)/n_conv) -> -0.055822497 | G79: =Seg!$E$79+(glt_xbox-Seg!$E$79)*MIN(1,(Thesis!G104-base_fy)/n_conv) -> -0.040657998 | H79: =Seg!$E$79+(glt_xbox-Seg!$E$79)*MIN(1,(Thesis!H104-base_fy)/n_conv) -> -0.025493498 | I79: =Seg!$E$79+(glt_xbox-Seg!$E$79)*MIN(1,(Thesis!I104-base_fy)/n_conv) -> -0.010328999 | J79: =Seg!$E$79+(glt_xbox-Seg!$E$79)*MIN(1,(Thesis!J104-base_fy)/n_conv) -> 0.0048355006 | K79: =Seg!$E$79+(glt_xbox-Seg!$E$79)*MIN(1,(Thesis!K104-base_fy)/n_conv) -> 0.02
A80: Windows OEM and devices | B80: US$B | D80: =Q!L15 -> 17.315 | E80: =Q!M15 -> 17.087 | F80: =Seg!E80*(1+Seg!F81) -> 16.956459 | G80: =Seg!F80*(1+Seg!G81) -> 16.920649 | H80: =Seg!G80*(1+Seg!H81) -> 16.978452 | I80: =Seg!H80*(1+Seg!I81) -> 17.130308 | J80: =Seg!I80*(1+Seg!J81) -> 17.378219 | K80: =Seg!J80*(1+Seg!K81) -> 17.725783
A81: 年增（近一年 → 長期值） | B81: % | E81: =Seg!E80/Seg!D80-1 -> -0.013167774 | F81: =Seg!$E$81+(glt_win-Seg!$E$81)*MIN(1,(Thesis!F104-base_fy)/n_conv) -> -0.0076398113 | G81: =Seg!$E$81+(glt_win-Seg!$E$81)*MIN(1,(Thesis!G104-base_fy)/n_conv) -> -0.0021118491 | H81: =Seg!$E$81+(glt_win-Seg!$E$81)*MIN(1,(Thesis!H104-base_fy)/n_conv) -> 0.0034161132 | I81: =Seg!$E$81+(glt_win-Seg!$E$81)*MIN(1,(Thesis!I104-base_fy)/n_conv) -> 0.0089440755 | J81: =Seg!$E$81+(glt_win-Seg!$E$81)*MIN(1,(Thesis!J104-base_fy)/n_conv) -> 0.014472038 | K81: =Seg!$E$81+(glt_win-Seg!$E$81)*MIN(1,(Thesis!K104-base_fy)/n_conv) -> 0.02
A82: Devices and Consumer | B82: US$B | D82: =Seg!D76+Seg!D78+Seg!D80 -> 62.941 | E82: =Seg!E76+Seg!E78+Seg!E80 -> 63.712 | F82: =Seg!F76+Seg!F78+Seg!F80 -> 65.141576 | G82: =Seg!G76+Seg!G78+Seg!G80 -> 67.125361 | H82: =Seg!H76+Seg!H78+Seg!H80 -> 69.576805 | I82: =Seg!I76+Seg!I78+Seg!I80 -> 72.423319 | J82: =Seg!J76+Seg!J78+Seg!J80 -> 75.60441 | K82: =Seg!K76+Seg!K78+Seg!K80 -> 79.07144
A83: 合併營收（分部合計） | B83: US$B | D83: =Seg!D75+Seg!D82 -> 281.724 | E83: =Seg!E75+Seg!E82 -> 331.839 | F83: =Seg!F75+Seg!F82 -> 393.50501 | G83: =Seg!G75+Seg!G82 -> 456.39523 | H83: =Seg!H75+Seg!H82 -> 515.33313 | I83: =Seg!I75+Seg!I82 -> 577.12455 | J83: =Seg!J75+Seg!J82 -> 629.11938 | K83: =Seg!K75+Seg!K82 -> 671.61126
A84: 檢查：產品線合計 − 分部；實績期另比對公司分部值 | B84: US$B | D84: =(Seg!D63+Seg!D68+Seg!D69+Seg!D71+Seg!D73-Seg!D75)+(Seg!D76+Seg!D78+Seg!D80-Seg!D82)+(Seg!D75-Q!L5)+(Seg!D82-Q!L12)+(Seg!D63-Q!L6)+(Seg!D68-Q!L7) -> 0 | E84: =(Seg!E63+Seg!E68+Seg!E69+Seg!E71+Seg!E73-Seg!E75)+(Seg!E76+Seg!E78+Seg!E80-Seg!E82)+(Seg!E75-Q!M5)+(Seg!E82-Q!M12)+(Seg!E63-Q!M6)+(Seg!E68-Q!M7) -> 0 | F84: =(Seg!F63+Seg!F68+Seg!F69+Seg!F71+Seg!F73-Seg!F75)+(Seg!F76+Seg!F78+Seg!F80-Seg!F82) -> 0 | G84: =(Seg!G63+Seg!G68+Seg!G69+Seg!G71+Seg!G73-Seg!G75)+(Seg!G76+Seg!G78+Seg!G80-Seg!G82) -> 0 | H84: =(Seg!H63+Seg!H68+Seg!H69+Seg!H71+Seg!H73-Seg!H75)+(Seg!H76+Seg!H78+Seg!H80-Seg!H82) -> 0 | I84: =(Seg!I63+Seg!I68+Seg!I69+Seg!I71+Seg!I73-Seg!I75)+(Seg!I76+Seg!I78+Seg!I80-Seg!I82) -> 0 | J84: =(Seg!J63+Seg!J68+Seg!J69+Seg!J71+Seg!J73-Seg!J75)+(Seg!J76+Seg!J78+Seg!J80-Seg!J82) -> 0 | K84: =(Seg!K63+Seg!K68+Seg!K69+Seg!K71+Seg!K73-Seg!K75)+(Seg!K76+Seg!K78+Seg!K80-Seg!K82) -> 0

Sheet PL
A1: PL — 分部營收 → 分部營業利益（Agents and Infra 由核心利益率扣 AI 營運成本與 AI 折舊；Devices and Consumer 依實績利益率）→ 合併營業利益 → 業外 → 稅 → 淨利 → EPS
A2: 核對列（三情境、全部年度合計，應為 0；segments.json 與 tools/segment_check 讀這三列）
A3: 項目 | B3: 單位 | C3: FY2024A | D3: FY2025A | E3: FY2026A | F3: FY2027 | G3: FY2028 | H3: FY2029 | I3: FY2030 | J3: FY2031 | K3: FY2032 | L3: 說明
A4: 檢查：分部合計 − 合併營收（三情境，實績期另比對公司值） | B4: US$B | D4: =ABS(PL!D23+PL!D27-PL!D28)+ABS(PL!D28-Q!L18)+ABS(PL!D62+PL!D66-PL!D67)+ABS(PL!D67-Q!L18)+ABS(PL!D101+PL!D105-PL!D106)+ABS(PL!D106-Q!L18) -> 0 | E4: =ABS(PL!E23+PL!E27-PL!E28)+ABS(PL!E28-Q!M18)+ABS(PL!E62+PL!E66-PL!E67)+ABS(PL!E67-Q!M18)+ABS(PL!E101+PL!E105-PL!E106)+ABS(PL!E106-Q!M18) -> 0 | F4: =ABS(PL!F23+PL!F27-PL!F28)+ABS(PL!F62+PL!F66-PL!F67)+ABS(PL!F101+PL!F105-PL!F106) -> 0 | G4: =ABS(PL!G23+PL!G27-PL!G28)+ABS(PL!G62+PL!G66-PL!G67)+ABS(PL!G101+PL!G105-PL!G106) -> 0 | H4: =ABS(PL!H23+PL!H27-PL!H28)+ABS(PL!H62+PL!H66-PL!H67)+ABS(PL!H101+PL!H105-PL!H106) -> 0 | I4: =ABS(PL!I23+PL!I27-PL!I28)+ABS(PL!I62+PL!I66-PL!I67)+ABS(PL!I101+PL!I105-PL!I106) -> 0 | J4: =ABS(PL!J23+PL!J27-PL!J28)+ABS(PL!J62+PL!J66-PL!J67)+ABS(PL!J101+PL!J105-PL!J106) -> 0 | K4: =ABS(PL!K23+PL!K27-PL!K28)+ABS(PL!K62+PL!K66-PL!K67)+ABS(PL!K101+PL!K105-PL!K106) -> 0
A5: 檢查：產品線合計 − 分部（三情境，實績期另比對公司值） | B5: US$B | D5: =ABS(Seg!D30)+ABS(Seg!D57)+ABS(Seg!D84) -> 0 | E5: =ABS(Seg!E30)+ABS(Seg!E57)+ABS(Seg!E84) -> 0 | F5: =ABS(Seg!F30)+ABS(Seg!F57)+ABS(Seg!F84) -> 0 | G5: =ABS(Seg!G30)+ABS(Seg!G57)+ABS(Seg!G84) -> 0 | H5: =ABS(Seg!H30)+ABS(Seg!H57)+ABS(Seg!H84) -> 0 | I5: =ABS(Seg!I30)+ABS(Seg!I57)+ABS(Seg!I84) -> 0 | J5: =ABS(Seg!J30)+ABS(Seg!J57)+ABS(Seg!J84) -> 0 | K5: =ABS(Seg!K30)+ABS(Seg!K57)+ABS(Seg!K84) -> 0
A6: 檢查：命題子列合計 − 母列（Azure、Microsoft 365 cloud；三情境） | B6: US$B | D6: =ABS(PL!D15+PL!D16-PL!D14)+ABS(PL!D18+PL!D19-PL!D17)+ABS(PL!D54+PL!D55-PL!D53)+ABS(PL!D57+PL!D58-PL!D56)+ABS(PL!D93+PL!D94-PL!D92)+ABS(PL!D96+PL!D97-PL!D95) -> 0 | E6: =ABS(PL!E15+PL!E16-PL!E14)+ABS(PL!E18+PL!E19-PL!E17)+ABS(PL!E54+PL!E55-PL!E53)+ABS(PL!E57+PL!E58-PL!E56)+ABS(PL!E93+PL!E94-PL!E92)+ABS(PL!E96+PL!E97-PL!E95) -> 0 | F6: =ABS(PL!F15+PL!F16-PL!F14)+ABS(PL!F18+PL!F19-PL!F17)+ABS(PL!F54+PL!F55-PL!F53)+ABS(PL!F57+PL!F58-PL!F56)+ABS(PL!F93+PL!F94-PL!F92)+ABS(PL!F96+PL!F97-PL!F95) -> 0 | G6: =ABS(PL!G15+PL!G16-PL!G14)+ABS(PL!G18+PL!G19-PL!G17)+ABS(PL!G54+PL!G55-PL!G53)+ABS(PL!G57+PL!G58-PL!G56)+ABS(PL!G93+PL!G94-PL!G92)+ABS(PL!G96+PL!G97-PL!G95) -> 0 | H6: =ABS(PL!H15+PL!H16-PL!H14)+ABS(PL!H18+PL!H19-PL!H17)+ABS(PL!H54+PL!H55-PL!H53)+ABS(PL!H57+PL!H58-PL!H56)+ABS(PL!H93+PL!H94-PL!H92)+ABS(PL!H96+PL!H97-PL!H95) -> 0 | I6: =ABS(PL!I15+PL!I16-PL!I14)+ABS(PL!I18+PL!I19-PL!I17)+ABS(PL!I54+PL!I55-PL!I53)+ABS(PL!I57+PL!I58-PL!I56)+ABS(PL!I93+PL!I94-PL!I92)+ABS(PL!I96+PL!I97-PL!I95) -> 0 | J6: =ABS(PL!J15+PL!J16-PL!J14)+ABS(PL!J18+PL!J19-PL!J17)+ABS(PL!J54+PL!J55-PL!J53)+ABS(PL!J57+PL!J58-PL!J56)+ABS(PL!J93+PL!J94-PL!J92)+ABS(PL!J96+PL!J97-PL!J95) -> 0 | K6: =ABS(PL!K15+PL!K16-PL!K14)+ABS(PL!K18+PL!K19-PL!K17)+ABS(PL!K54+PL!K55-PL!K53)+ABS(PL!K57+PL!K58-PL!K56)+ABS(PL!K93+PL!K94-PL!K92)+ABS(PL!K96+PL!K97-PL!K95) -> 0
A7: 檢查：分部營業利益合計 − 合併營業利益（三情境；實績期比對公司值） | B7: US$B | D7: =ABS(PL!D32+PL!D34-PL!D35)+ABS(PL!D36)+ABS(PL!D71+PL!D73-PL!D74)+ABS(PL!D75)+ABS(PL!D110+PL!D112-PL!D113)+ABS(PL!D114) -> 0 | E7: =ABS(PL!E32+PL!E34-PL!E35)+ABS(PL!E36)+ABS(PL!E71+PL!E73-PL!E74)+ABS(PL!E75)+ABS(PL!E110+PL!E112-PL!E113)+ABS(PL!E114) -> 0 | F7: =ABS(PL!F32+PL!F34-PL!F35)+ABS(PL!F71+PL!F73-PL!F74)+ABS(PL!F110+PL!F112-PL!F113) -> 0 | G7: =ABS(PL!G32+PL!G34-PL!G35)+ABS(PL!G71+PL!G73-PL!G74)+ABS(PL!G110+PL!G112-PL!G113) -> 0 | H7: =ABS(PL!H32+PL!H34-PL!H35)+ABS(PL!H71+PL!H73-PL!H74)+ABS(PL!H110+PL!H112-PL!H113) -> 0 | I7: =ABS(PL!I32+PL!I34-PL!I35)+ABS(PL!I71+PL!I73-PL!I74)+ABS(PL!I110+PL!I112-PL!I113) -> 0 | J7: =ABS(PL!J32+PL!J34-PL!J35)+ABS(PL!J71+PL!J73-PL!J74)+ABS(PL!J110+PL!J112-PL!J113) -> 0 | K7: =ABS(PL!K32+PL!K34-PL!K35)+ABS(PL!K71+PL!K73-PL!K74)+ABS(PL!K110+PL!K112-PL!K113) -> 0
A9: 以下三個區塊依序為情境 A、B、C；分部與產品線列標籤與 8-K 相同（segments.json 對應）
A12: 情境 A（樂觀）｜損益（PL）
A13: 項目 | B13: 單位 | C13: FY2024A | D13: FY2025A | E13: FY2026A | F13: FY2027 | G13: FY2028 | H13: FY2029 | I13: FY2030 | J13: FY2031 | K13: FY2032 | L13: 說明
A14: Azure | B14: US$B | D14: =Seg!D9 -> 72.61 | E14: =Seg!E9 -> 101.938 | F14: =Seg!F9 -> 148.81237 | G14: =Seg!G9 -> 208.39751 | H14: =Seg!H9 -> 274.05759 | I14: =Seg!I9 -> 328.30241 | J14: =Seg!J9 -> 369.58789 | K14: =Seg!K9 -> 398.39058
A15: Azure AI（命題子列） | B15: US$B | D15: =Seg!D6 -> 12.935979 | E15: =Seg!E6 -> 27.809506 | F15: =Seg!F6 -> 58.732419 | G15: =Seg!G6 -> 101.36909 | H15: =Seg!H6 -> 149.78561 | I15: =Seg!I6 -> 187.3687 | J15: =Seg!J6 -> 213.56902 | K15: =Seg!K6 -> 229.89021
A16: Azure 其他 | B16: US$B | D16: =Seg!D7 -> 59.674021 | E16: =Seg!E7 -> 74.128494 | F16: =Seg!F7 -> 90.07995 | G16: =Seg!G7 -> 107.02843 | H16: =Seg!H7 -> 124.27198 | I16: =Seg!I7 -> 140.9337 | J16: =Seg!J7 -> 156.01887 | K16: =Seg!K7 -> 168.50038
A17: Microsoft 365 cloud | B17: US$B | D17: =Seg!D14 -> 84.605 | E17: =Seg!E14 -> 100.299 | F17: =Seg!F14 -> 120.39239 | G17: =Seg!G14 -> 141.54417 | H17: =Seg!H14 -> 162.77736 | I17: =Seg!I14 -> 181.58403 | J17: =Seg!J14 -> 197.6827 | K17: =Seg!K14 -> 213.02799
A18: M365 基礎（不含 Copilot） | B18: US$B | D18: =Seg!D12 -> 83.705 | E18: =Seg!E12 -> 95.049 | F18: =Seg!F12 -> 106.89239 | G18: =Seg!G12 -> 119.04417 | H18: =Seg!H12 -> 131.27736 | I18: =Seg!I12 -> 143.33403 | J18: =Seg!J12 -> 154.9327 | K18: =Seg!K12 -> 165.77799
A19: Copilot（命題子列） | B19: US$B | D19: =Seg!D11 -> 0.9 | E19: =Seg!E11 -> 5.25 | F19: =Seg!F11 -> 13.5 | G19: =Seg!G11 -> 22.5 | H19: =Seg!H11 -> 31.5 | I19: =Seg!I11 -> 38.25 | J19: =Seg!J11 -> 42.75 | K19: =Seg!K11 -> 47.25
A20: Productivity and server licensing | B20: US$B | D20: =Seg!D15 -> 35.391 | E20: =Seg!E15 -> 37.285 | F20: =Seg!F15 -> 39.072083 | G20: =Seg!G15 -> 40.726563 | H20: =Seg!H15 -> 42.223599 | I20: =Seg!I15 -> 43.539799 | J20: =Seg!J15 -> 44.653811 | K20: =Seg!K15 -> 45.546887
A21: Industry solutions | B21: US$B | D21: =Seg!D17 -> 18.417 | E21: =Seg!E17 -> 20.345 | F21: =Seg!F17 -> 22.35722 | G21: =Seg!G17 -> 24.439212 | H21: =Seg!H17 -> 26.573805 | I21: =Seg!I17 -> 28.741217 | J21: =Seg!J17 -> 30.919255 | K21: =Seg!K17 -> 33.083602
A22: Frontier and support services | B22: US$B | D22: =Seg!D19 -> 7.76 | E22: =Seg!E19 -> 8.26 | F22: =Seg!F19 -> 8.7998804 | G22: =Seg!G19 -> 9.3832127 | H22: =Seg!H19 -> 10.013919 | I22: =Seg!I19 -> 10.696311 | J22: =Seg!J19 -> 11.435129 | K22: =Seg!K19 -> 12.235588
A23: Agents and Infra | B23: US$B | D23: =Seg!D21 -> 218.783 | E23: =Seg!E21 -> 268.127 | F23: =Seg!F21 -> 339.43394 | G23: =Seg!G21 -> 424.49067 | H23: =Seg!H21 -> 515.64628 | I23: =Seg!I21 -> 592.86376 | J23: =Seg!J21 -> 654.27879 | K23: =Seg!K21 -> 702.28465
A24: Search and advertising | B24: US$B | D24: =Seg!D22 -> 22.171 | E24: =Seg!E22 -> 24.835 | F24: =Seg!F22 -> 27.61149 | G24: =Seg!G22 -> 30.467567 | H24: =Seg!H22 -> 33.364377 | I24: =Seg!I22 -> 36.257702 | J24: =Seg!J22 -> 39.098837 | K24: =Seg!K22 -> 41.835755
A25: XBOX | B25: US$B | D25: =Seg!D24 -> 23.455 | E25: =Seg!E24 -> 21.79 | F25: =Seg!F24 -> 20.573628 | G25: =Seg!G24 -> 19.737145 | H25: =Seg!H24 -> 19.233976 | I25: =Seg!I24 -> 19.035309 | J25: =Seg!J24 -> 19.127354 | K25: =Seg!K24 -> 19.509901
A26: Windows OEM and devices | B26: US$B | D26: =Seg!D26 -> 17.315 | E26: =Seg!E26 -> 17.087 | F26: =Seg!F26 -> 16.956459 | G26: =Seg!G26 -> 16.920649 | H26: =Seg!H26 -> 16.978452 | I26: =Seg!I26 -> 17.130308 | J26: =Seg!J26 -> 17.378219 | K26: =Seg!K26 -> 17.725783
A27: Devices and Consumer | B27: US$B | D27: =Seg!D28 -> 62.941 | E27: =Seg!E28 -> 63.712 | F27: =Seg!F28 -> 65.141576 | G27: =Seg!G28 -> 67.125361 | H27: =Seg!H28 -> 69.576805 | I27: =Seg!I28 -> 72.423319 | J27: =Seg!J28 -> 75.60441 | K27: =Seg!K28 -> 79.07144
A28: 合併營收 | B28: US$B | D28: =Seg!D29 -> 281.724 | E28: =Seg!E29 -> 331.839 | F28: =Seg!F29 -> 404.57552 | G28: =Seg!G29 -> 491.61603 | H28: =Seg!H29 -> 585.22308 | I28: =Seg!I29 -> 665.28708 | J28: =Seg!J29 -> 729.8832 | K28: =Seg!K29 -> 781.35609
A29: 營收年增 | B29: % | E29: =PL!E28/PL!D28-1 -> 0.17788687 | F29: =PL!F28/PL!E28-1 -> 0.21919219 | G29: =PL!G28/PL!F28-1 -> 0.21514034 | H29: =PL!H28/PL!G28-1 -> 0.19040683 | I29: =PL!I28/PL!H28-1 -> 0.13680937 | J29: =PL!J28/PL!I28-1 -> 0.097095104 | K29: =PL!K28/PL!J28-1 -> 0.070522097
A30: 檢查：分部合計 − 合併營收；子列合計 − 母列（Azure、M365 cloud） | B30: US$B | D30: =(PL!D23+PL!D27-PL!D28)+(PL!D15+PL!D16-PL!D14)+(PL!D18+PL!D19-PL!D17)+(PL!D28-Q!L18) -> 0 | E30: =(PL!E23+PL!E27-PL!E28)+(PL!E15+PL!E16-PL!E14)+(PL!E18+PL!E19-PL!E17)+(PL!E28-Q!M18) -> 0 | F30: =(PL!F23+PL!F27-PL!F28)+(PL!F15+PL!F16-PL!F14)+(PL!F18+PL!F19-PL!F17) -> 0 | G30: =(PL!G23+PL!G27-PL!G28)+(PL!G15+PL!G16-PL!G14)+(PL!G18+PL!G19-PL!G17) -> 0 | H30: =(PL!H23+PL!H27-PL!H28)+(PL!H15+PL!H16-PL!H14)+(PL!H18+PL!H19-PL!H17) -> 0 | I30: =(PL!I23+PL!I27-PL!I28)+(PL!I15+PL!I16-PL!I14)+(PL!I18+PL!I19-PL!I17) -> 0 | J30: =(PL!J23+PL!J27-PL!J28)+(PL!J15+PL!J16-PL!J14)+(PL!J18+PL!J19-PL!J17) -> 0 | K30: =(PL!K23+PL!K27-PL!K28)+(PL!K15+PL!K16-PL!K14)+(PL!K18+PL!K19-PL!K17) -> 0
A31: Agents and Infra 核心利益率（扣 AI 營運成本與 AI 折舊前；FY2026 校準） | B31: % | E31: =(Q!M21+Thesis!E25+Thesis!E26+Thesis!E27+Thesis!E40-Thesis!E23)/(Q!M5-Thesis!E23) -> 0.57095735 | F31: =PL!$E$31+dm_seg -> 0.57095735 | G31: =PL!$E$31+dm_seg -> 0.57095735 | H31: =PL!$E$31+dm_seg -> 0.57095735 | I31: =PL!$E$31+dm_seg -> 0.57095735 | J31: =PL!$E$31+dm_seg -> 0.57095735 | K31: =PL!$E$31+dm_seg -> 0.57095735 | L31: FY2026：(分部營業利益＋AI 營運成本＋AI 折舊 − Azure AI 營收) ÷ (分部營收 − Azure AI 營收)；之後固定（＋dm_seg）
A32: Agents and Infra 營業利益 | B32: US$B | D32: =Q!L21 -> 110.814 | E32: =Q!M21 -> 136.365 | F32: =PL!F31*(Seg!F21-Thesis!F23)+Thesis!F23-(Thesis!F25+Thesis!F26+Thesis!F27)-Thesis!F40 -> 162.13548 | G32: =PL!G31*(Seg!G21-Thesis!G23)+Thesis!G23-(Thesis!G25+Thesis!G26+Thesis!G27)-Thesis!G40 -> 191.69358 | H32: =PL!H31*(Seg!H21-Thesis!H23)+Thesis!H23-(Thesis!H25+Thesis!H26+Thesis!H27)-Thesis!H40 -> 226.07971 | I32: =PL!I31*(Seg!I21-Thesis!I23)+Thesis!I23-(Thesis!I25+Thesis!I26+Thesis!I27)-Thesis!I40 -> 252.34782 | J32: =PL!J31*(Seg!J21-Thesis!J23)+Thesis!J23-(Thesis!J25+Thesis!J26+Thesis!J27)-Thesis!J40 -> 274.9213 | K32: =PL!K31*(Seg!K21-Thesis!K23)+Thesis!K23-(Thesis!K25+Thesis!K26+Thesis!K27)-Thesis!K40 -> 295.36143 | L32: ＝核心利益率 ×（分部營收 − Azure AI）＋ Azure AI 營收 − AI 營運成本 − AI 折舊：AI 資本支出經折舊進分部營業利益
A33: Devices and Consumer 營業利益率 | B33: % | E33: =Q!M22/Q!M12 -> 0.29620794 | F33: =PL!$E$33+dm_seg -> 0.29620794 | G33: =PL!$E$33+dm_seg -> 0.29620794 | H33: =PL!$E$33+dm_seg -> 0.29620794 | I33: =PL!$E$33+dm_seg -> 0.29620794 | J33: =PL!$E$33+dm_seg -> 0.29620794 | K33: =PL!$E$33+dm_seg -> 0.29620794 | L33: FY2026 實績後固定（＋dm_seg）
A34: Devices and Consumer 營業利益 | B34: US$B | D34: =Q!L22 -> 17.714 | E34: =Q!M22 -> 18.872 | F34: =Seg!F28*PL!F33 -> 19.295452 | G34: =Seg!G28*PL!G33 -> 19.883065 | H34: =Seg!H28*PL!H33 -> 20.609202 | I34: =Seg!I28*PL!I33 -> 21.452362 | J34: =Seg!J28*PL!J33 -> 22.394626 | K34: =Seg!K28*PL!K33 -> 23.421588
A35: 合併營業利益（財報口徑；分部合計，無未分攤項） | B35: US$B | D35: =PL!D32+PL!D34 -> 128.528 | E35: =PL!E32+PL!E34 -> 155.237 | F35: =PL!F32+PL!F34 -> 181.43094 | G35: =PL!G32+PL!G34 -> 211.57664 | H35: =PL!H32+PL!H34 -> 246.68892 | I35: =PL!I32+PL!I34 -> 273.80019 | J35: =PL!J32+PL!J34 -> 297.31593 | K35: =PL!K32+PL!K34 -> 318.78301
A36: 檢查：分部營業利益合計 − 公司合併營業利益（實績） | B36: US$B | D36: =PL!D35-Q!L23 -> 0 | E36: =PL!E35-Q!M23 -> 0
A37: 營業利益率（財報口徑） | B37: % | D37: =PL!D35/PL!D28 -> 0.45621956 | E37: =PL!E35/PL!E28 -> 0.46780818 | F37: =PL!F35/PL!F28 -> 0.44844764 | G37: =PL!G35/PL!G28 -> 0.4303697 | H37: =PL!H35/PL!H28 -> 0.42152971 | I37: =PL!I35/PL!I28 -> 0.41155194 | J37: =PL!J35/PL!J28 -> 0.40734727 | K37: =PL!K35/PL!K28 -> 0.40798686
A38: 自用 AI 影子效益（讀法 2；非財報營收；分攤到 Agents and Infra） | B38: US$B | F38: =Thesis!F44 -> 19.079382 | G38: =Thesis!G44 -> 32.566641 | H38: =Thesis!H44 -> 47.406356 | I38: =Thesis!I44 -> 61.252509 | J38: =Thesis!J44 -> 71.009614 | K38: =Thesis!K44 -> 76.045258 | L38: 修正一 F1：營收與分部對帳不動；只進評價口徑的營業利益、淨利、EPS 與 DCF
A39: 營業利益（評價口徑＝財報＋自用 AI 影子效益） | B39: US$B | D39: =PL!D35 -> 128.528 | E39: =PL!E35 -> 155.237 | F39: =PL!F35+PL!F38 -> 200.51032 | G39: =PL!G35+PL!G38 -> 244.14329 | H39: =PL!H35+PL!H38 -> 294.09527 | I39: =PL!I35+PL!I38 -> 335.0527 | J39: =PL!J35+PL!J38 -> 368.32554 | K39: =PL!K35+PL!K38 -> 394.82827
A40: 備忘：AI 折舊（Thesis） | B40: US$B | E40: =Thesis!E40 -> 16.305406 | F40: =Thesis!F40 -> 34.728035 | G40: =Thesis!G40 -> 60.481733 | H40: =Thesis!H40 -> 87.717316 | I40: =Thesis!I40 -> 111.96204 | J40: =Thesis!J40 -> 129.15871 | K40: =Thesis!K40 -> 139.62265
A41: 備忘：非 AI 折舊攤銷（CF） | B41: US$B | E41: =CF!E17 -> 22.228594 | F41: =CF!F17 -> 23.578669 | G41: =CF!G17 -> 25.381092 | H41: =CF!H17 -> 27.599134 | I41: =CF!I17 -> 30.156561 | J41: =CF!J17 -> 32.961496 | K41: =CF!K17 -> 35.929717
A42: 業外收支（預測期不含持股評價損益＝0） | B42: US$B | D42: =Q!L27 -> -4.901 | E42: =Q!M27 -> 10.697 | F42: =oie_f -> -0.4 | G42: =oie_f -> -0.4 | H42: =oie_f -> -0.4 | I42: =oie_f -> -0.4 | J42: =oie_f -> -0.4 | K42: =oie_f -> -0.4 | L42: FY2026 含 OpenAI 重組利得等 +6.5
A43: 稅前淨利（財報口徑） | B43: US$B | D43: =PL!D35+PL!D42 -> 123.627 | E43: =PL!E35+PL!E42 -> 165.934 | F43: =PL!F35+PL!F42 -> 181.03094 | G43: =PL!G35+PL!G42 -> 211.17664 | H43: =PL!H35+PL!H42 -> 246.28892 | I43: =PL!I35+PL!I42 -> 273.40019 | J43: =PL!J35+PL!J42 -> 296.91593 | K43: =PL!K35+PL!K42 -> 318.38301
A44: 所得稅（財報口徑） | B44: US$B | D44: =Q!L29 -> 21.795 | E44: =Q!M29 -> 32.185 | F44: =PL!F43*tax_f -> 36.206187 | G44: =PL!G43*tax_f -> 42.235329 | H44: =PL!H43*tax_f -> 49.257783 | I44: =PL!I43*tax_f -> 54.680037 | J44: =PL!J43*tax_f -> 59.383186 | K44: =PL!K43*tax_f -> 63.676603
A45: 淨利（財報口徑） | B45: US$B | D45: =PL!D43-PL!D44 -> 101.832 | E45: =PL!E43-PL!E44 -> 133.749 | F45: =PL!F43-PL!F44 -> 144.82475 | G45: =PL!G43-PL!G44 -> 168.94132 | H45: =PL!H43-PL!H44 -> 197.03113 | I45: =PL!I43-PL!I44 -> 218.72015 | J45: =PL!J43-PL!J44 -> 237.53274 | K45: =PL!K43-PL!K44 -> 254.70641
A46: 稀釋股數（十億股；回購依 CF 頁） | B46: 十億股 | D46: =Q!L31 -> 7.465 | E46: =Q!M31 -> 7.453 | F46: =CF!F39 -> 7.4735 | G46: =CF!G39 -> 7.5080834 | H46: =CF!H39 -> 7.5254184 | I46: =CF!I39 -> 7.5371993 | J46: =CF!J39 -> 7.5514408 | K46: =CF!K39 -> 7.5679607
A47: EPS（財報口徑，US$） | B47: US$ | D47: =PL!D45/PL!D46 -> 13.641259 | E47: =PL!E45/PL!E46 -> 17.945659 | F47: =PL!F45/PL!F46 -> 19.378437 | G47: =PL!G45/PL!G46 -> 22.501257 | H47: =PL!H45/PL!H46 -> 26.182083 | I47: =PL!I45/PL!I46 -> 29.018756 | J47: =PL!J45/PL!J46 -> 31.455288 | K47: =PL!K45/PL!K46 -> 33.655885 | L47: 實績期與公司 EPS 差 < 0.01（四捨五入）
A48: 淨利（評價口徑＝財報＋影子效益 ×（1 − 稅率）） | B48: US$B | D48: =PL!D45 -> 101.832 | E48: =PL!E45 -> 133.749 | F48: =PL!F45+PL!F38*(1-tax_f) -> 160.08826 | G48: =PL!G45+PL!G38*(1-tax_f) -> 194.99463 | H48: =PL!H45+PL!H38*(1-tax_f) -> 234.95622 | I48: =PL!I45+PL!I38*(1-tax_f) -> 267.72216 | J48: =PL!J45+PL!J38*(1-tax_f) -> 294.34043 | K48: =PL!K45+PL!K38*(1-tax_f) -> 315.54262
A49: EPS（評價口徑，US$） | B49: US$ | D49: =PL!D48/PL!D46 -> 13.641259 | E49: =PL!E48/PL!E46 -> 17.945659 | F49: =PL!F48/PL!F46 -> 21.420787 | G49: =PL!G48/PL!G46 -> 25.971292 | H49: =PL!H48/PL!H46 -> 31.221682 | I49: =PL!I48/PL!I46 -> 35.520111 | J49: =PL!J48/PL!J46 -> 38.97805 | K49: =PL!K48/PL!K46 -> 41.694537 | L49: 讀法 2 主值；讀法 1 時＝財報口徑
A50: EPS 年增（評價口徑） | B50: % | E50: =PL!E49/PL!D49-1 -> 0.31554274 | F50: =PL!F49/PL!E49-1 -> 0.19364727 | G50: =PL!G49/PL!F49-1 -> 0.21243406 | H50: =PL!H49/PL!G49-1 -> 0.20216126 | I50: =PL!I49/PL!H49-1 -> 0.13767451 | J50: =PL!J49/PL!I49-1 -> 0.097351568 | K50: =PL!K49/PL!J49-1 -> 0.069692745
A51: 情境 B（基準）｜損益（PL）
A52: 項目 | B52: 單位 | C52: FY2024A | D52: FY2025A | E52: FY2026A | F52: FY2027 | G52: FY2028 | H52: FY2029 | I52: FY2030 | J52: FY2031 | K52: FY2032 | L52: 說明
A53: Azure | B53: US$B | D53: =Seg!D36 -> 72.61 | E53: =Seg!E36 -> 101.938 | F53: =Seg!F36 -> 145.14396 | G53: =Seg!G36 -> 196.47897 | H53: =Seg!H36 -> 249.10761 | I53: =Seg!I36 -> 297.09216 | J53: =Seg!J36 -> 334.01343 | K53: =Seg!K36 -> 360.09748
A54: Azure AI（命題子列） | B54: US$B | D54: =Seg!D33 -> 12.935979 | E54: =Seg!E33 -> 27.809506 | F54: =Seg!F33 -> 55.064007 | G54: =Seg!G33 -> 89.450541 | H54: =Seg!H33 -> 124.83563 | I54: =Seg!I33 -> 156.15846 | J54: =Seg!J33 -> 177.99456 | K54: =Seg!K33 -> 191.5971
A55: Azure 其他 | B55: US$B | D55: =Seg!D34 -> 59.674021 | E55: =Seg!E34 -> 74.128494 | F55: =Seg!F34 -> 90.07995 | G55: =Seg!G34 -> 107.02843 | H55: =Seg!H34 -> 124.27198 | I55: =Seg!I34 -> 140.9337 | J55: =Seg!J34 -> 156.01887 | K55: =Seg!K34 -> 168.50038
A56: Microsoft 365 cloud | B56: US$B | D56: =Seg!D41 -> 84.605 | E56: =Seg!E41 -> 100.299 | F56: =Seg!F41 -> 118.89239 | G56: =Seg!G41 -> 137.04417 | H56: =Seg!H41 -> 155.27736 | I56: =Seg!I41 -> 171.83403 | J56: =Seg!J41 -> 186.4327 | K56: =Seg!K41 -> 200.27799
A57: M365 基礎（不含 Copilot） | B57: US$B | D57: =Seg!D39 -> 83.705 | E57: =Seg!E39 -> 95.049 | F57: =Seg!F39 -> 106.89239 | G57: =Seg!G39 -> 119.04417 | H57: =Seg!H39 -> 131.27736 | I57: =Seg!I39 -> 143.33403 | J57: =Seg!J39 -> 154.9327 | K57: =Seg!K39 -> 165.77799
A58: Copilot（命題子列） | B58: US$B | D58: =Seg!D38 -> 0.9 | E58: =Seg!E38 -> 5.25 | F58: =Seg!F38 -> 12 | G58: =Seg!G38 -> 18 | H58: =Seg!H38 -> 24 | I58: =Seg!I38 -> 28.5 | J58: =Seg!J38 -> 31.5 | K58: =Seg!K38 -> 34.5
A59: Productivity and server licensing | B59: US$B | D59: =Seg!D42 -> 35.391 | E59: =Seg!E42 -> 37.285 | F59: =Seg!F42 -> 39.072083 | G59: =Seg!G42 -> 40.726563 | H59: =Seg!H42 -> 42.223599 | I59: =Seg!I42 -> 43.539799 | J59: =Seg!J42 -> 44.653811 | K59: =Seg!K42 -> 45.546887
A60: Industry solutions | B60: US$B | D60: =Seg!D44 -> 18.417 | E60: =Seg!E44 -> 20.345 | F60: =Seg!F44 -> 22.35722 | G60: =Seg!G44 -> 24.439212 | H60: =Seg!H44 -> 26.573805 | I60: =Seg!I44 -> 28.741217 | J60: =Seg!J44 -> 30.919255 | K60: =Seg!K44 -> 33.083602
A61: Frontier and support services | B61: US$B | D61: =Seg!D46 -> 7.76 | E61: =Seg!E46 -> 8.26 | F61: =Seg!F46 -> 8.7998804 | G61: =Seg!G46 -> 9.3832127 | H61: =Seg!H46 -> 10.013919 | I61: =Seg!I46 -> 10.696311 | J61: =Seg!J46 -> 11.435129 | K61: =Seg!K46 -> 12.235588
A62: Agents and Infra | B62: US$B | D62: =Seg!D48 -> 218.783 | E62: =Seg!E48 -> 268.127 | F62: =Seg!F48 -> 334.26553 | G62: =Seg!G48 -> 408.07212 | H62: =Seg!H48 -> 483.1963 | I62: =Seg!I48 -> 551.90352 | J62: =Seg!J48 -> 607.45432 | K62: =Seg!K48 -> 651.24155
A63: Search and advertising | B63: US$B | D63: =Seg!D49 -> 22.171 | E63: =Seg!E49 -> 24.835 | F63: =Seg!F49 -> 27.61149 | G63: =Seg!G49 -> 30.467567 | H63: =Seg!H49 -> 33.364377 | I63: =Seg!I49 -> 36.257702 | J63: =Seg!J49 -> 39.098837 | K63: =Seg!K49 -> 41.835755
A64: XBOX | B64: US$B | D64: =Seg!D51 -> 23.455 | E64: =Seg!E51 -> 21.79 | F64: =Seg!F51 -> 20.573628 | G64: =Seg!G51 -> 19.737145 | H64: =Seg!H51 -> 19.233976 | I64: =Seg!I51 -> 19.035309 | J64: =Seg!J51 -> 19.127354 | K64: =Seg!K51 -> 19.509901
A65: Windows OEM and devices | B65: US$B | D65: =Seg!D53 -> 17.315 | E65: =Seg!E53 -> 17.087 | F65: =Seg!F53 -> 16.956459 | G65: =Seg!G53 -> 16.920649 | H65: =Seg!H53 -> 16.978452 | I65: =Seg!I53 -> 17.130308 | J65: =Seg!J53 -> 17.378219 | K65: =Seg!K53 -> 17.725783
A66: Devices and Consumer | B66: US$B | D66: =Seg!D55 -> 62.941 | E66: =Seg!E55 -> 63.712 | F66: =Seg!F55 -> 65.141576 | G66: =Seg!G55 -> 67.125361 | H66: =Seg!H55 -> 69.576805 | I66: =Seg!I55 -> 72.423319 | J66: =Seg!J55 -> 75.60441 | K66: =Seg!K55 -> 79.07144
A67: 合併營收 | B67: US$B | D67: =Seg!D56 -> 281.724 | E67: =Seg!E56 -> 331.839 | F67: =Seg!F56 -> 399.4071 | G67: =Seg!G56 -> 475.19748 | H67: =Seg!H56 -> 552.7731 | I67: =Seg!I56 -> 624.32684 | J67: =Seg!J56 -> 683.05873 | K67: =Seg!K56 -> 730.31299
A68: 營收年增 | B68: % | E68: =PL!E67/PL!D67-1 -> 0.17788687 | F68: =PL!F67/PL!E67-1 -> 0.20361713 | G68: =PL!G67/PL!F67-1 -> 0.18975721 | H68: =PL!H67/PL!G67-1 -> 0.16324922 | I68: =PL!I67/PL!H67-1 -> 0.12944504 | J68: =PL!J67/PL!I67-1 -> 0.094072358 | K68: =PL!K67/PL!J67-1 -> 0.069180367
A69: 檢查：分部合計 − 合併營收；子列合計 − 母列（Azure、M365 cloud） | B69: US$B | D69: =(PL!D62+PL!D66-PL!D67)+(PL!D54+PL!D55-PL!D53)+(PL!D57+PL!D58-PL!D56)+(PL!D67-Q!L18) -> 0 | E69: =(PL!E62+PL!E66-PL!E67)+(PL!E54+PL!E55-PL!E53)+(PL!E57+PL!E58-PL!E56)+(PL!E67-Q!M18) -> 0 | F69: =(PL!F62+PL!F66-PL!F67)+(PL!F54+PL!F55-PL!F53)+(PL!F57+PL!F58-PL!F56) -> 0 | G69: =(PL!G62+PL!G66-PL!G67)+(PL!G54+PL!G55-PL!G53)+(PL!G57+PL!G58-PL!G56) -> 0 | H69: =(PL!H62+PL!H66-PL!H67)+(PL!H54+PL!H55-PL!H53)+(PL!H57+PL!H58-PL!H56) -> 0 | I69: =(PL!I62+PL!I66-PL!I67)+(PL!I54+PL!I55-PL!I53)+(PL!I57+PL!I58-PL!I56) -> 0 | J69: =(PL!J62+PL!J66-PL!J67)+(PL!J54+PL!J55-PL!J53)+(PL!J57+PL!J58-PL!J56) -> 0 | K69: =(PL!K62+PL!K66-PL!K67)+(PL!K54+PL!K55-PL!K53)+(PL!K57+PL!K58-PL!K56) -> 0
A70: Agents and Infra 核心利益率（扣 AI 營運成本與 AI 折舊前；FY2026 校準） | B70: % | E70: =(Q!M21+Thesis!E74+Thesis!E75+Thesis!E76+Thesis!E89-Thesis!E72)/(Q!M5-Thesis!E72) -> 0.57095735 | F70: =PL!$E$70+dm_seg -> 0.57095735 | G70: =PL!$E$70+dm_seg -> 0.57095735 | H70: =PL!$E$70+dm_seg -> 0.57095735 | I70: =PL!$E$70+dm_seg -> 0.57095735 | J70: =PL!$E$70+dm_seg -> 0.57095735 | K70: =PL!$E$70+dm_seg -> 0.57095735 | L70: FY2026：(分部營業利益＋AI 營運成本＋AI 折舊 − Azure AI 營收) ÷ (分部營收 − Azure AI 營收)；之後固定（＋dm_seg）
A71: Agents and Infra 營業利益 | B71: US$B | D71: =Q!L21 -> 110.814 | E71: =Q!M21 -> 136.365 | F71: =PL!F70*(Seg!F48-Thesis!F72)+Thesis!F72-(Thesis!F74+Thesis!F75+Thesis!F76)-Thesis!F89 -> 157.59814 | G71: =PL!G70*(Seg!G48-Thesis!G72)+Thesis!G72-(Thesis!G74+Thesis!G75+Thesis!G76)-Thesis!G89 -> 177.18072 | H71: =PL!H70*(Seg!H48-Thesis!H72)+Thesis!H72-(Thesis!H74+Thesis!H75+Thesis!H76)-Thesis!H89 -> 196.82255 | I71: =PL!I70*(Seg!I48-Thesis!I72)+Thesis!I72-(Thesis!I74+Thesis!I75+Thesis!I76)-Thesis!I89 -> 215.54575 | J71: =PL!J70*(Seg!J48-Thesis!J72)+Thesis!J72-(Thesis!J74+Thesis!J75+Thesis!J76)-Thesis!J89 -> 232.89857 | K71: =PL!K70*(Seg!K48-Thesis!K72)+Thesis!K72-(Thesis!K74+Thesis!K75+Thesis!K76)-Thesis!K89 -> 249.76362 | L71: ＝核心利益率 ×（分部營收 − Azure AI）＋ Azure AI 營收 − AI 營運成本 − AI 折舊：AI 資本支出經折舊進分部營業利益
A72: Devices and Consumer 營業利益率 | B72: % | E72: =Q!M22/Q!M12 -> 0.29620794 | F72: =PL!$E$72+dm_seg -> 0.29620794 | G72: =PL!$E$72+dm_seg -> 0.29620794 | H72: =PL!$E$72+dm_seg -> 0.29620794 | I72: =PL!$E$72+dm_seg -> 0.29620794 | J72: =PL!$E$72+dm_seg -> 0.29620794 | K72: =PL!$E$72+dm_seg -> 0.29620794 | L72: FY2026 實績後固定（＋dm_seg）
A73: Devices and Consumer 營業利益 | B73: US$B | D73: =Q!L22 -> 17.714 | E73: =Q!M22 -> 18.872 | F73: =Seg!F55*PL!F72 -> 19.295452 | G73: =Seg!G55*PL!G72 -> 19.883065 | H73: =Seg!H55*PL!H72 -> 20.609202 | I73: =Seg!I55*PL!I72 -> 21.452362 | J73: =Seg!J55*PL!J72 -> 22.394626 | K73: =Seg!K55*PL!K72 -> 23.421588
A74: 合併營業利益（財報口徑；分部合計，無未分攤項） | B74: US$B | D74: =PL!D71+PL!D73 -> 128.528 | E74: =PL!E71+PL!E73 -> 155.237 | F74: =PL!F71+PL!F73 -> 176.89359 | G74: =PL!G71+PL!G73 -> 197.06379 | H74: =PL!H71+PL!H73 -> 217.43176 | I74: =PL!I71+PL!I73 -> 236.99811 | J74: =PL!J71+PL!J73 -> 255.2932 | K74: =PL!K71+PL!K73 -> 273.1852
A75: 檢查：分部營業利益合計 − 公司合併營業利益（實績） | B75: US$B | D75: =PL!D74-Q!L23 -> 0 | E75: =PL!E74-Q!M23 -> 0
A76: 營業利益率（財報口徑） | B76: % | D76: =PL!D74/PL!D67 -> 0.45621956 | E76: =PL!E74/PL!E67 -> 0.46780818 | F76: =PL!F74/PL!F67 -> 0.44289044 | G76: =PL!G74/PL!G67 -> 0.41469872 | H76: =PL!H74/PL!H67 -> 0.39334721 | I76: =PL!I74/PL!I67 -> 0.37960583 | J76: =PL!J74/PL!J67 -> 0.37374999 | K76: =PL!K74/PL!K67 -> 0.37406593
A77: 自用 AI 影子效益（讀法 2；非財報營收；分攤到 Agents and Infra） | B77: US$B | F77: =Thesis!F93 -> 19.935818 | G77: =Thesis!G93 -> 35.135949 | H77: =Thesis!H93 -> 51.688537 | I77: =Thesis!I93 -> 66.819343 | J77: =Thesis!J93 -> 77.432884 | K77: =Thesis!K93 -> 83.324964 | L77: 修正一 F1：營收與分部對帳不動；只進評價口徑的營業利益、淨利、EPS 與 DCF
A78: 營業利益（評價口徑＝財報＋自用 AI 影子效益） | B78: US$B | D78: =PL!D74 -> 128.528 | E78: =PL!E74 -> 155.237 | F78: =PL!F74+PL!F77 -> 196.82941 | G78: =PL!G74+PL!G77 -> 232.19974 | H78: =PL!H74+PL!H77 -> 269.12029 | I78: =PL!I74+PL!I77 -> 303.81745 | J78: =PL!J74+PL!J77 -> 332.72608 | K78: =PL!K74+PL!K77 -> 356.51017
A79: 備忘：AI 折舊（Thesis） | B79: US$B | E79: =Thesis!E89 -> 16.305406 | F79: =Thesis!F89 -> 34.740535 | G79: =Thesis!G89 -> 60.506733 | H79: =Thesis!H89 -> 87.742316 | I79: =Thesis!I89 -> 111.98704 | J79: =Thesis!J89 -> 129.18371 | K79: =Thesis!K89 -> 139.64765
A80: 備忘：非 AI 折舊攤銷（CF） | B80: US$B | E80: =CF!E46 -> 22.228594 | F80: =CF!F46 -> 23.563669 | G80: =CF!G46 -> 25.322592 | H80: =CF!H46 -> 27.471484 | I80: =CF!I46 -> 29.944176 | J80: =CF!J46 -> 32.657849 | K80: =CF!K46 -> 35.528935
A81: 業外收支（預測期不含持股評價損益＝0） | B81: US$B | D81: =Q!L27 -> -4.901 | E81: =Q!M27 -> 10.697 | F81: =oie_f -> -0.4 | G81: =oie_f -> -0.4 | H81: =oie_f -> -0.4 | I81: =oie_f -> -0.4 | J81: =oie_f -> -0.4 | K81: =oie_f -> -0.4 | L81: FY2026 含 OpenAI 重組利得等 +6.5
A82: 稅前淨利（財報口徑） | B82: US$B | D82: =PL!D74+PL!D81 -> 123.627 | E82: =PL!E74+PL!E81 -> 165.934 | F82: =PL!F74+PL!F81 -> 176.49359 | G82: =PL!G74+PL!G81 -> 196.66379 | H82: =PL!H74+PL!H81 -> 217.03176 | I82: =PL!I74+PL!I81 -> 236.59811 | J82: =PL!J74+PL!J81 -> 254.8932 | K82: =PL!K74+PL!K81 -> 272.7852
A83: 所得稅（財報口徑） | B83: US$B | D83: =Q!L29 -> 21.795 | E83: =Q!M29 -> 32.185 | F83: =PL!F82*tax_f -> 35.298718 | G83: =PL!G82*tax_f -> 39.332758 | H83: =PL!H82*tax_f -> 43.406351 | I83: =PL!I82*tax_f -> 47.319622 | J83: =PL!J82*tax_f -> 50.978639 | K83: =PL!K82*tax_f -> 54.557041
A84: 淨利（財報口徑） | B84: US$B | D84: =PL!D82-PL!D83 -> 101.832 | E84: =PL!E82-PL!E83 -> 133.749 | F84: =PL!F82-PL!F83 -> 141.19487 | G84: =PL!G82-PL!G83 -> 157.33103 | H84: =PL!H82-PL!H83 -> 173.62541 | I84: =PL!I82-PL!I83 -> 189.27849 | J84: =PL!J82-PL!J83 -> 203.91456 | K84: =PL!K82-PL!K83 -> 218.22816
A85: 稀釋股數（十億股；回購依 CF 頁） | B85: 十億股 | D85: =Q!L31 -> 7.465 | E85: =Q!M31 -> 7.453 | F85: =CF!F68 -> 7.4735 | G85: =CF!G68 -> 7.5179597 | H85: =CF!H68 -> 7.545171 | I85: =CF!I68 -> 7.5569518 | J85: =CF!J68 -> 7.5711933 | K85: =CF!K68 -> 7.5877132
A86: EPS（財報口徑，US$） | B86: US$ | D86: =PL!D84/PL!D85 -> 13.641259 | E86: =PL!E84/PL!E85 -> 17.945659 | F86: =PL!F84/PL!F85 -> 18.892737 | G86: =PL!G84/PL!G85 -> 20.927358 | H86: =PL!H84/PL!H85 -> 23.011461 | I86: =PL!I84/PL!I85 -> 25.046936 | J86: =PL!J84/PL!J85 -> 26.932948 | K86: =PL!K84/PL!K85 -> 28.760729 | L86: 實績期與公司 EPS 差 < 0.01（四捨五入）
A87: 淨利（評價口徑＝財報＋影子效益 ×（1 − 稅率）） | B87: US$B | D87: =PL!D84 -> 101.832 | E87: =PL!E84 -> 133.749 | F87: =PL!F84+PL!F77*(1-tax_f) -> 157.14353 | G87: =PL!G84+PL!G77*(1-tax_f) -> 185.43979 | H87: =PL!H84+PL!H77*(1-tax_f) -> 214.97623 | I87: =PL!I84+PL!I77*(1-tax_f) -> 242.73396 | J87: =PL!J84+PL!J77*(1-tax_f) -> 265.86086 | K87: =PL!K84+PL!K77*(1-tax_f) -> 284.88813
A88: EPS（評價口徑，US$） | B88: US$ | D88: =PL!D87/PL!D85 -> 13.641259 | E88: =PL!E87/PL!E85 -> 17.945659 | F88: =PL!F87/PL!F85 -> 21.026765 | G88: =PL!G87/PL!G85 -> 24.666239 | H88: =PL!H87/PL!H85 -> 28.491897 | I88: =PL!I87/PL!I85 -> 32.120618 | J88: =PL!J87/PL!J85 -> 35.11479 | K88: =PL!K87/PL!K85 -> 37.545981 | L88: 讀法 2 主值；讀法 1 時＝財報口徑
A89: EPS 年增（評價口徑） | B89: % | E89: =PL!E88/PL!D88-1 -> 0.31554274 | F89: =PL!F88/PL!E88-1 -> 0.17169083 | G89: =PL!G88/PL!F88-1 -> 0.17308771 | H89: =PL!H88/PL!G88-1 -> 0.15509693 | I89: =PL!I88/PL!H88-1 -> 0.12735975 | J89: =PL!J88/PL!I88-1 -> 0.093216514 | K89: =PL!K88/PL!J88-1 -> 0.069235518
A90: 情境 C（保守）｜損益（PL）
A91: 項目 | B91: 單位 | C91: FY2024A | D91: FY2025A | E91: FY2026A | F91: FY2027 | G91: FY2028 | H91: FY2029 | I91: FY2030 | J91: FY2031 | K91: FY2032 | L91: 說明
A92: Azure | B92: US$B | D92: =Seg!D63 -> 72.61 | E92: =Seg!E63 -> 101.938 | F92: =Seg!F63 -> 140.74186 | G92: =Seg!G63 -> 182.17671 | H92: =Seg!H63 -> 219.16764 | I92: =Seg!I63 -> 259.63987 | J92: =Seg!J63 -> 291.32407 | K92: =Seg!K63 -> 314.14575
A93: Azure AI（命題子列） | B93: US$B | D93: =Seg!D60 -> 12.935979 | E93: =Seg!E60 -> 27.809506 | F93: =Seg!F60 -> 50.661911 | G93: =Seg!G60 -> 75.148284 | H93: =Seg!H60 -> 94.895656 | I93: =Seg!I60 -> 118.70617 | J93: =Seg!J60 -> 135.3052 | K93: =Seg!K60 -> 145.64538
A94: Azure 其他 | B94: US$B | D94: =Seg!D61 -> 59.674021 | E94: =Seg!E61 -> 74.128494 | F94: =Seg!F61 -> 90.07995 | G94: =Seg!G61 -> 107.02843 | H94: =Seg!H61 -> 124.27198 | I94: =Seg!I61 -> 140.9337 | J94: =Seg!J61 -> 156.01887 | K94: =Seg!K61 -> 168.50038
A95: Microsoft 365 cloud | B95: US$B | D95: =Seg!D68 -> 84.605 | E95: =Seg!E68 -> 100.299 | F95: =Seg!F68 -> 117.39239 | G95: =Seg!G68 -> 132.54417 | H95: =Seg!H68 -> 147.77736 | I95: =Seg!I68 -> 162.08403 | J95: =Seg!J68 -> 175.1827 | K95: =Seg!K68 -> 187.52799
A96: M365 基礎（不含 Copilot） | B96: US$B | D96: =Seg!D66 -> 83.705 | E96: =Seg!E66 -> 95.049 | F96: =Seg!F66 -> 106.89239 | G96: =Seg!G66 -> 119.04417 | H96: =Seg!H66 -> 131.27736 | I96: =Seg!I66 -> 143.33403 | J96: =Seg!J66 -> 154.9327 | K96: =Seg!K66 -> 165.77799
A97: Copilot（命題子列） | B97: US$B | D97: =Seg!D65 -> 0.9 | E97: =Seg!E65 -> 5.25 | F97: =Seg!F65 -> 10.5 | G97: =Seg!G65 -> 13.5 | H97: =Seg!H65 -> 16.5 | I97: =Seg!I65 -> 18.75 | J97: =Seg!J65 -> 20.25 | K97: =Seg!K65 -> 21.75
A98: Productivity and server licensing | B98: US$B | D98: =Seg!D69 -> 35.391 | E98: =Seg!E69 -> 37.285 | F98: =Seg!F69 -> 39.072083 | G98: =Seg!G69 -> 40.726563 | H98: =Seg!H69 -> 42.223599 | I98: =Seg!I69 -> 43.539799 | J98: =Seg!J69 -> 44.653811 | K98: =Seg!K69 -> 45.546887
A99: Industry solutions | B99: US$B | D99: =Seg!D71 -> 18.417 | E99: =Seg!E71 -> 20.345 | F99: =Seg!F71 -> 22.35722 | G99: =Seg!G71 -> 24.439212 | H99: =Seg!H71 -> 26.573805 | I99: =Seg!I71 -> 28.741217 | J99: =Seg!J71 -> 30.919255 | K99: =Seg!K71 -> 33.083602
A100: Frontier and support services | B100: US$B | D100: =Seg!D73 -> 7.76 | E100: =Seg!E73 -> 8.26 | F100: =Seg!F73 -> 8.7998804 | G100: =Seg!G73 -> 9.3832127 | H100: =Seg!H73 -> 10.013919 | I100: =Seg!I73 -> 10.696311 | J100: =Seg!J73 -> 11.435129 | K100: =Seg!K73 -> 12.235588
A101: Agents and Infra | B101: US$B | D101: =Seg!D75 -> 218.783 | E101: =Seg!E75 -> 268.127 | F101: =Seg!F75 -> 328.36343 | G101: =Seg!G75 -> 389.26987 | H101: =Seg!H75 -> 445.75632 | I101: =Seg!I75 -> 504.70123 | J101: =Seg!J75 -> 553.51497 | K101: =Seg!K75 -> 592.53982
A102: Search and advertising | B102: US$B | D102: =Seg!D76 -> 22.171 | E102: =Seg!E76 -> 24.835 | F102: =Seg!F76 -> 27.61149 | G102: =Seg!G76 -> 30.467567 | H102: =Seg!H76 -> 33.364377 | I102: =Seg!I76 -> 36.257702 | J102: =Seg!J76 -> 39.098837 | K102: =Seg!K76 -> 41.835755
A103: XBOX | B103: US$B | D103: =Seg!D78 -> 23.455 | E103: =Seg!E78 -> 21.79 | F103: =Seg!F78 -> 20.573628 | G103: =Seg!G78 -> 19.737145 | H103: =Seg!H78 -> 19.233976 | I103: =Seg!I78 -> 19.035309 | J103: =Seg!J78 -> 19.127354 | K103: =Seg!K78 -> 19.509901
...

Sheet CF
A1: CF — 營業現金流（淨利＋AI 與非 AI 折舊＋股票薪酬＋營運資金）− 資本支出（AI＝Thesis；非 AI＝營收 × 比例）− 融資租賃本金 → 自由現金流（財報現金）；股利、回購、舉債（最低現金）
A2: 收支關卡（地圖讀此表）：模型期間首年起五年（FY2027–FY2031）自由現金流扣股利後合計（財報現金，不含自用 AI 影子效益）；並判斷是否需要舉債或停止回購
A4: 項目 | B4: 情境 A（樂觀） | C4: 情境 B（基準） | D4: 情境 C（保守） | E4: 說明
A5: 收支關卡：自由現金流扣股利（五年合計） | B5: =CF!$C$40 -> 378.566 | C5: =CF!$C$69 -> 273.96596 | D5: =CF!$C$98 -> 151.42012 | E5: US$B；為正＝五年自由現金流足以支付股利（地圖收支關卡讀 C 欄＝基準情境）。修正一：v0.3 初版的範圍公式被讀成 F 欄到 CF 欄，誤加了 FY2032
A6: 是否需要舉債或停止回購（FY2027–FY2031） | B6: =CF!$C$42 -> 需要舉債 6.0 十億美元；回購較每年 22.3 的目標少 32.1 十億美元（2 年減少） | C6: =CF!$C$71 -> 需要舉債 9.8 十億美元；回購較每年 22.3 的目標少 43.9 十億美元（2 年減少） | D6: =CF!$C$100 -> 需要舉債 27.4 十億美元；回購較每年 22.3 的目標少 60.2 十億美元（3 年減少）
A7: 自由現金流 FY2027（參考） | B7: =CF!F27 -> 5.0362631 | C7: =CF!F56 -> 1.2106755 | D7: =CF!F85 -> -3.229285
A8: 自由現金流 FY2029（參考） | B8: =CF!H27 -> 94.524344 | C8: =CF!H56 -> 70.552903 | D8: =CF!H85 -> 42.402925
A9: 資本支出 FY2027（公司口徑，參考） | B9: =CF!F24 -> 204.2 | C9: =CF!F53 -> 204.2 | D9: =CF!F82 -> 204.2
A10: 回購合計 FY2027–FY2031 | B10: =SUM(CF!F32:J32) -> 79.266507 | C10: =SUM(CF!F61:J61) -> 67.458955 | D10: =SUM(CF!F90:J90) -> 51.187784
A11: 新增舉債合計 FY2027–FY2031 | B11: =SUM(CF!F33:J33) -> 5.9646869 | C11: =SUM(CF!F62:J62) -> 9.7902745 | D11: =SUM(CF!F91:J91) -> 27.387909
A12: 檢查：收支關卡＝首年起五年自由現金流扣股利（逐欄加總） | B12: =B5-(CF!F30+CF!G30+CF!H30+CF!I30+CF!J30) -> 0 | C12: =C5-(CF!F59+CF!G59+CF!H59+CF!I59+CF!J59) -> 0 | D12: =D5-(CF!F88+CF!G88+CF!H88+CF!I88+CF!J88) -> 0
A14: 情境 A（樂觀）｜現金流與資金（CF）
A15: 項目 | B15: 單位 | C15: FY2024A | D15: FY2025A | E15: FY2026A | F15: FY2027 | G15: FY2028 | H15: FY2029 | I15: FY2030 | J15: FY2031 | K15: FY2032 | L15: 說明
A16: 淨利（財報口徑） | B16: US$B | F16: =PL!F45 -> 144.82475 | G16: =PL!G45 -> 168.94132 | H16: =PL!H45 -> 197.03113 | I16: =PL!I45 -> 218.72015 | J16: =PL!J45 -> 237.53274 | K16: =PL!K45 -> 254.70641
A17: 非 AI 折舊攤銷 | B17: US$B | E17: =Q!M38-Thesis!E40 -> 22.228594 | F17: =CF!E17*(1-1/life_nonai)+CF!F23/life_nonai -> 23.578669 | G17: =CF!F17*(1-1/life_nonai)+CF!G23/life_nonai -> 25.381092 | H17: =CF!G17*(1-1/life_nonai)+CF!H23/life_nonai -> 27.599134 | I17: =CF!H17*(1-1/life_nonai)+CF!I23/life_nonai -> 30.156561 | J17: =CF!I17*(1-1/life_nonai)+CF!J23/life_nonai -> 32.961496 | K17: =CF!J17*(1-1/life_nonai)+CF!K23/life_nonai -> 35.929717 | L17: FY2026＝公司 D&A − AI 折舊估計（C17）
A18: 折舊攤銷合計（AI＋非 AI） | B18: US$B | E18: =Thesis!E40+CF!E17 -> 38.534 | F18: =Thesis!F40+CF!F17 -> 58.306705 | G18: =Thesis!G40+CF!G17 -> 85.862825 | H18: =Thesis!H40+CF!H17 -> 115.31645 | I18: =Thesis!I40+CF!I17 -> 142.1186 | J18: =Thesis!J40+CF!J17 -> 162.12021 | K18: =Thesis!K40+CF!K17 -> 175.55236
A19: 股票薪酬（現金流量表加回；DCF 視為現金成本） | B19: US$B | F19: =Seg!F29*sbc_r -> 15.124079 | G19: =Seg!G29*sbc_r -> 18.377879 | H19: =Seg!H29*sbc_r -> 21.877152 | I19: =Seg!I29*sbc_r -> 24.870152 | J19: =Seg!J29*sbc_r -> 27.284921 | K19: =Seg!K29*sbc_r -> 29.209111
A20: 營運資金變動 | B20: US$B | F20: =wc27 -> -4.895 | G20: =wc_f -> 0 | H20: =wc_f -> 0 | I20: =wc_f -> 0 | J20: =wc_f -> 0 | K20: =wc_f -> 0 | L20: C14：首期＝上一年度實績；之後 wc_f
A21: 營業現金流 | B21: US$B | E21: =Q!M35 -> 182.935 | F21: =CF!F16+CF!F18+CF!F19+CF!F20 -> 213.36053 | G21: =CF!G16+CF!G18+CF!G19+CF!G20 -> 273.18202 | H21: =CF!H16+CF!H18+CF!H19+CF!H20 -> 334.22473 | I21: =CF!I16+CF!I18+CF!I19+CF!I20 -> 385.7089 | J21: =CF!J16+CF!J18+CF!J19+CF!J20 -> 426.93787 | K21: =CF!K16+CF!K18+CF!K19+CF!K20 -> 459.46789
A22: AI 資本支出（Thesis） | B22: US$B | F22: =Thesis!F37 -> 168.47065 | G22: =Thesis!G37 -> 183.57418 | H22: =Thesis!H37 -> 188.08029 | I22: =Thesis!I37 -> 163.70667 | J22: =Thesis!J37 -> 124.51248 | K22: =Thesis!K37 -> 114.95944
A23: 非 AI 資本支出（各線營收 × 比例） | B23: US$B | E23: =Seg!E7*cx_azo+Seg!E14*cx_m365+Seg!E15*cx_lic+(Seg!E17+Seg!E19)*cx_ind+Seg!E22*cx_srch+(Seg!E24+Seg!E26)*cx_dev -> 30.184659 | F23: =Seg!F7*cx_azo+Seg!F14*cx_m365+Seg!F15*cx_lic+(Seg!F17+Seg!F19)*cx_ind+Seg!F22*cx_srch+(Seg!F24+Seg!F26)*cx_dev -> 35.729347 | G23: =Seg!G7*cx_azo+Seg!G14*cx_m365+Seg!G15*cx_lic+(Seg!G17+Seg!G19)*cx_ind+Seg!G22*cx_srch+(Seg!G24+Seg!G26)*cx_dev -> 41.602894 | H23: =Seg!H7*cx_azo+Seg!H14*cx_m365+Seg!H15*cx_lic+(Seg!H17+Seg!H19)*cx_ind+Seg!H22*cx_srch+(Seg!H24+Seg!H26)*cx_dev -> 47.561514 | I23: =Seg!I7*cx_azo+Seg!I14*cx_m365+Seg!I15*cx_lic+(Seg!I17+Seg!I19)*cx_ind+Seg!I22*cx_srch+(Seg!I24+Seg!I26)*cx_dev -> 53.1734 | J23: =Seg!J7*cx_azo+Seg!J14*cx_m365+Seg!J15*cx_lic+(Seg!J17+Seg!J19)*cx_ind+Seg!J22*cx_srch+(Seg!J24+Seg!J26)*cx_dev -> 58.205913 | K23: =Seg!K7*cx_azo+Seg!K14*cx_m365+Seg!K15*cx_lic+(Seg!K17+Seg!K19)*cx_ind+Seg!K22*cx_srch+(Seg!K24+Seg!K26)*cx_dev -> 62.643703
A24: 資本支出合計（公司口徑，含融資租賃） | B24: US$B | E24: =Q!M42 -> 145.3 | F24: =CF!F22+CF!F23 -> 204.2 | G24: =CF!G22+CF!G23 -> 225.17707 | H24: =CF!H22+CF!H23 -> 235.6418 | I24: =CF!I22+CF!I23 -> 216.88007 | J24: =CF!J22+CF!J23 -> 182.71839 | K24: =CF!K22+CF!K23 -> 177.60314 | L24: 新的融資租賃在取得時視同現金（偏保守，v0.2.2 口徑）；FY2026 為公司法說值
A25: 在帳融資租賃負債（年底） | B25: US$B | E25: =fl_liab -> 66.594 | F25: =CF!E25-CF!F26 -> 62.46973 | G25: =CF!F25-CF!G26 -> 57.986868 | H25: =CF!G25-CF!H26 -> 53.928277 | I25: =CF!H25-CF!I26 -> 49.785049 | J25: =CF!I25-CF!J26 -> 45.482377 | K25: =CF!J25-CF!K26 -> 40.986084
A26: 在帳融資租賃本金（付款 − 利息） | B26: US$B | F26: =fl_pay_27-CF!E25*fl_rate -> 4.12427 | G26: =fl_pay_28-CF!F25*fl_rate -> 4.4828621 | H26: =fl_pay_29-CF!G25*fl_rate -> 4.0585909 | I26: =fl_pay_30-CF!H25*fl_rate -> 4.1432275 | J26: =fl_pay_31-CF!I25*fl_rate -> 4.3026728 | K26: =fl_pay_32-CF!J25*fl_rate -> 4.4962931
A27: 自由現金流（財報現金：營業現金流 − 資本支出 − 融資租賃本金） | B27: US$B | E27: =Q!M35-Q!M36-Q!M43 -> 63.886 | F27: =CF!F21-CF!F24-CF!F26 -> 5.0362631 | G27: =CF!G21-CF!G24-CF!G26 -> 43.522083 | H27: =CF!H21-CF!H24-CF!H26 -> 94.524344 | I27: =CF!I21-CF!I24-CF!I26 -> 164.6856 | J27: =CF!J21-CF!J24-CF!J26 -> 239.91681 | K27: =CF!K21-CF!K24-CF!K26 -> 277.36845 | L27: FY2026 為實績（現金資本支出口徑）；收支關卡用此列（不含影子效益）
A28: 每股股利 | B28: US$ | F28: =dps_27 -> 3.85 | G28: =CF!F28*(1+dps_g) -> 4.158 | H28: =CF!G28*(1+dps_g) -> 4.49064 | I28: =CF!H28*(1+dps_g) -> 4.8498912 | J28: =CF!I28*(1+dps_g) -> 5.2378825 | K28: =CF!J28*(1+dps_g) -> 5.6569131
A29: 股利 | B29: US$B | E29: =Q!M41 -> 26.445 | F29: =CF!F28*CF!E38 -> 28.59395 | G29: =CF!G28*CF!F38 -> 31.068576 | H29: =CF!H28*CF!G38 -> 33.662587 | I29: =CF!I28*CF!H38 -> 36.406533 | J29: =CF!J28*CF!I38 -> 39.387454 | K29: =CF!K28*CF!J38 -> 42.625706 | L29: 每股股利 × 期初流通股數（避免與回購循環）
A30: 自由現金流扣股利 | B30: US$B | E30: =CF!E27-CF!E29 -> 37.441 | F30: =CF!F27-CF!F29 -> -23.557687 | G30: =CF!G27-CF!G29 -> 12.453507 | H30: =CF!H27-CF!H29 -> 60.861758 | I30: =CF!I27-CF!I29 -> 128.27907 | J30: =CF!J27-CF!J29 -> 200.52935 | K30: =CF!K27-CF!K29 -> 234.74275
A31: 債務到期償還 | B31: US$B | F31: =debt_mat_27 -> 9.25 | G31: =debt_mat_28 -> 0 | H31: =debt_mat_29 -> 2.001 | I31: =debt_mat_30 -> 0 | J31: =debt_mat_31 -> 0.5 | K31: =debt_mat_32 -> 0
A32: 回購（現金不足時先減） | B32: US$B | E32: =Q!M40 -> 22.271 | F32: =MAX(0,MIN(bb_target,CF!E34+CF!F30-CF!F31-min_cash)) -> 0 | G32: =MAX(0,MIN(bb_target,CF!F34+CF!G30-CF!G31-min_cash)) -> 12.453507 | H32: =MAX(0,MIN(bb_target,CF!G34+CF!H30-CF!H31-min_cash)) -> 22.271 | I32: =MAX(0,MIN(bb_target,CF!H34+CF!I30-CF!I31-min_cash)) -> 22.271 | J32: =MAX(0,MIN(bb_target,CF!I34+CF!J30-CF!J31-min_cash)) -> 22.271 | K32: =MAX(0,MIN(bb_target,CF!J34+CF!K30-CF!K31-min_cash)) -> 22.271
A33: 新增舉債（維持最低現金） | B33: US$B | F33: =MAX(0,min_cash-(CF!E34+CF!F30-CF!F31-CF!F32)) -> 5.9646869 | G33: =MAX(0,min_cash-(CF!F34+CF!G30-CF!G31-CF!G32)) -> 0 | H33: =MAX(0,min_cash-(CF!G34+CF!H30-CF!H31-CF!H32)) -> 0 | I33: =MAX(0,min_cash-(CF!H34+CF!I30-CF!I31-CF!I32)) -> 0 | J33: =MAX(0,min_cash-(CF!I34+CF!J30-CF!J31-CF!J32)) -> 0 | K33: =MAX(0,min_cash-(CF!J34+CF!K30-CF!K31-CF!K32)) -> 0
A34: 現金與短期投資（年底） | B34: US$B | E34: =cash_open -> 76.843 | F34: =CF!E34+CF!F30-CF!F31-CF!F32+CF!F33 -> 50 | G34: =CF!F34+CF!G30-CF!G31-CF!G32+CF!G33 -> 50 | H34: =CF!G34+CF!H30-CF!H31-CF!H32+CF!H33 -> 86.589758 | I34: =CF!H34+CF!I30-CF!I31-CF!I32+CF!I33 -> 192.59783 | J34: =CF!I34+CF!J30-CF!J31-CF!J32+CF!J33 -> 370.35618 | K34: =CF!J34+CF!K30-CF!K31-CF!K32+CF!K33 -> 582.82793
A35: 債務（年底，面額） | B35: US$B | E35: =debt_face -> 46.136 | F35: =CF!E35-CF!F31+CF!F33 -> 42.850687 | G35: =CF!F35-CF!G31+CF!G33 -> 42.850687 | H35: =CF!G35-CF!H31+CF!H33 -> 40.849687 | I35: =CF!H35-CF!I31+CF!I33 -> 40.849687 | J35: =CF!I35-CF!J31+CF!J33 -> 40.349687 | K35: =CF!J35-CF!K31+CF!K33 -> 40.349687
A36: 淨現金（不含租賃） | B36: US$B | E36: =CF!E34-CF!E35 -> 30.707 | F36: =CF!F34-CF!F35 -> 7.1493131 | G36: =CF!G34-CF!G35 -> 7.1493131 | H36: =CF!H34-CF!H35 -> 45.740071 | I36: =CF!I34-CF!I35 -> 151.74814 | J36: =CF!J34-CF!J35 -> 330.0065 | K36: =CF!K34-CF!K35 -> 542.47825
A37: 回購均價 | B37: US$ | F37: =px*(1+bb_g)^(Thesis!F6-base_fy-mid_yr) -> 553.49416 | G37: =px*(1+bb_g)^(Thesis!G6-base_fy-mid_yr) -> 597.77369 | H37: =px*(1+bb_g)^(Thesis!H6-base_fy-mid_yr) -> 645.59558 | I37: =px*(1+bb_g)^(Thesis!I6-base_fy-mid_yr) -> 697.24323 | J37: =px*(1+bb_g)^(Thesis!J6-base_fy-mid_yr) -> 753.02269 | K37: =px*(1+bb_g)^(Thesis!K6-base_fy-mid_yr) -> 813.2645
A38: 流通股數（年底） | B38: 十億股 | E38: =sh_out26 -> 7.427 | F38: =CF!E38+sh_iss-CF!F32/CF!F37 -> 7.472 | G38: =CF!F38+sh_iss-CF!G32/CF!G37 -> 7.4961669 | H38: =CF!G38+sh_iss-CF!H32/CF!H37 -> 7.50667 | I38: =CF!H38+sh_iss-CF!I32/CF!I37 -> 7.5197285 | J38: =CF!I38+sh_iss-CF!J32/CF!J37 -> 7.535153 | K38: =CF!J38+sh_iss-CF!K32/CF!K37 -> 7.5527684
A39: 稀釋加權股數 | B39: 十億股 | E39: =sh_dil26 -> 7.453 | F39: =(CF!E38+CF!F38)/2+dil_gap -> 7.4735 | G39: =(CF!F38+CF!G38)/2+dil_gap -> 7.5080834 | H39: =(CF!G38+CF!H38)/2+dil_gap -> 7.5254184 | I39: =(CF!H38+CF!I38)/2+dil_gap -> 7.5371993 | J39: =(CF!I38+CF!J38)/2+dil_gap -> 7.5514408 | K39: =(CF!J38+CF!K38)/2+dil_gap -> 7.5679607
A40: 自由現金流扣股利（FY2027–FY2031 合計，本情境） | B40: US$B | C40: =SUM(CF!F30:J30) -> 378.566
A41: 檢查：收支關卡＝首年起五年自由現金流扣股利（逐欄加總） | B41: US$B | C41: =CF!$C$40-(CF!F30+CF!G30+CF!H30+CF!I30+CF!J30) -> 0
A42: 是否需要舉債或停止回購（FY2027–FY2031） | B42: 文字 | C42: =IF(SUM(CF!F33:J33)>0.05,"需要舉債 "&TEXT(SUM(CF!F33:J33),"0.0")&" 十億美元","不需舉債")&"；"&IF(SUM(CF!F32:J32)<COUNT(CF!F32:J32)*bb_target-0.05,"回購較每年 "&TEXT(bb_target,"0.0")&" 的目標少 "&TEXT(COUNT(CF!F32:J32)*bb_target-SUM(CF!F32:J32),"0.0")&" 十億美元（"&TEXT(COUNTIF(CF!F32:J32,"<"&(bb_target-0.05)),"0")&" 年減少）","回購不減") -> 需要舉債 6.0 十億美元；回購較每年 22.3 的目標少 32.1 十億美元（2 年減少）
A43: 情境 B（基準）｜現金流與資金（CF）
A44: 項目 | B44: 單位 | C44: FY2024A | D44: FY2025A | E44: FY2026A | F44: FY2027 | G44: FY2028 | H44: FY2029 | I44: FY2030 | J44: FY2031 | K44: FY2032 | L44: 說明
A45: 淨利（財報口徑） | B45: US$B | F45: =PL!F84 -> 141.19487 | G45: =PL!G84 -> 157.33103 | H45: =PL!H84 -> 173.62541 | I45: =PL!I84 -> 189.27849 | J45: =PL!J84 -> 203.91456 | K45: =PL!K84 -> 218.22816
A46: 非 AI 折舊攤銷 | B46: US$B | E46: =Q!M38-Thesis!E89 -> 22.228594 | F46: =CF!E46*(1-1/life_nonai)+CF!F52/life_nonai -> 23.563669 | G46: =CF!F46*(1-1/life_nonai)+CF!G52/life_nonai -> 25.322592 | H46: =CF!G46*(1-1/life_nonai)+CF!H52/life_nonai -> 27.471484 | I46: =CF!H46*(1-1/life_nonai)+CF!I52/life_nonai -> 29.944176 | J46: =CF!I46*(1-1/life_nonai)+CF!J52/life_nonai -> 32.657849 | K46: =CF!J46*(1-1/life_nonai)+CF!K52/life_nonai -> 35.528935 | L46: FY2026＝公司 D&A − AI 折舊估計（C17）
A47: 折舊攤銷合計（AI＋非 AI） | B47: US$B | E47: =Thesis!E89+CF!E46 -> 38.534 | F47: =Thesis!F89+CF!F46 -> 58.304205 | G47: =Thesis!G89+CF!G46 -> 85.829325 | H47: =Thesis!H89+CF!H46 -> 115.2138 | I47: =Thesis!I89+CF!I46 -> 141.93122 | J47: =Thesis!J89+CF!J46 -> 161.84156 | K47: =Thesis!K89+CF!K46 -> 175.17658
A48: 股票薪酬（現金流量表加回；DCF 視為現金成本） | B48: US$B | F48: =Seg!F56*sbc_r -> 14.93087 | G48: =Seg!G56*sbc_r -> 17.764111 | H48: =Seg!H56*sbc_r -> 20.664088 | I48: =Seg!I56*sbc_r -> 23.338952 | J48: =Seg!J56*sbc_r -> 25.534502 | K48: =Seg!K56*sbc_r -> 27.300988
A49: 營運資金變動 | B49: US$B | F49: =wc27 -> -4.895 | G49: =wc_f -> 0 | H49: =wc_f -> 0 | I49: =wc_f -> 0 | J49: =wc_f -> 0 | K49: =wc_f -> 0 | L49: C14：首期＝上一年度實績；之後 wc_f
A50: 營業現金流 | B50: US$B | E50: =Q!M35 -> 182.935 | F50: =CF!F45+CF!F47+CF!F48+CF!F49 -> 209.53495 | G50: =CF!G45+CF!G47+CF!G48+CF!G49 -> 260.92447 | H50: =CF!H45+CF!H47+CF!H48+CF!H49 -> 309.50329 | I50: =CF!I45+CF!I47+CF!I48+CF!I49 -> 354.54865 | J50: =CF!J45+CF!J47+CF!J48+CF!J49 -> 391.29062 | K50: =CF!K45+CF!K47+CF!K48+CF!K49 -> 420.70573
A51: AI 資本支出（Thesis） | B51: US$B | F51: =Thesis!F86 -> 168.62065 | G51: =Thesis!G86 -> 183.57418 | H51: =Thesis!H86 -> 188.08029 | I51: =Thesis!I86 -> 163.70667 | J51: =Thesis!J86 -> 124.51248 | K51: =Thesis!K86 -> 114.95944
A52: 非 AI 資本支出（各線營收 × 比例） | B52: US$B | E52: =Seg!E34*cx_azo+Seg!E41*cx_m365+Seg!E42*cx_lic+(Seg!E44+Seg!E46)*cx_ind+Seg!E49*cx_srch+(Seg!E51+Seg!E53)*cx_dev -> 30.184659 | F52: =Seg!F34*cx_azo+Seg!F41*cx_m365+Seg!F42*cx_lic+(Seg!F44+Seg!F46)*cx_ind+Seg!F49*cx_srch+(Seg!F51+Seg!F53)*cx_dev -> 35.579347 | G52: =Seg!G34*cx_azo+Seg!G41*cx_m365+Seg!G42*cx_lic+(Seg!G44+Seg!G46)*cx_ind+Seg!G49*cx_srch+(Seg!G51+Seg!G53)*cx_dev -> 41.152894 | H52: =Seg!H34*cx_azo+Seg!H41*cx_m365+Seg!H42*cx_lic+(Seg!H44+Seg!H46)*cx_ind+Seg!H49*cx_srch+(Seg!H51+Seg!H53)*cx_dev -> 46.811514 | I52: =Seg!I34*cx_azo+Seg!I41*cx_m365+Seg!I42*cx_lic+(Seg!I44+Seg!I46)*cx_ind+Seg!I49*cx_srch+(Seg!I51+Seg!I53)*cx_dev -> 52.1984 | J52: =Seg!J34*cx_azo+Seg!J41*cx_m365+Seg!J42*cx_lic+(Seg!J44+Seg!J46)*cx_ind+Seg!J49*cx_srch+(Seg!J51+Seg!J53)*cx_dev -> 57.080913 | K52: =Seg!K34*cx_azo+Seg!K41*cx_m365+Seg!K42*cx_lic+(Seg!K44+Seg!K46)*cx_ind+Seg!K49*cx_srch+(Seg!K51+Seg!K53)*cx_dev -> 61.368703
A53: 資本支出合計（公司口徑，含融資租賃） | B53: US$B | E53: =Q!M42 -> 145.3 | F53: =CF!F51+CF!F52 -> 204.2 | G53: =CF!G51+CF!G52 -> 224.72707 | H53: =CF!H51+CF!H52 -> 234.8918 | I53: =CF!I51+CF!I52 -> 215.90507 | J53: =CF!J51+CF!J52 -> 181.59339 | K53: =CF!K51+CF!K52 -> 176.32814 | L53: 新的融資租賃在取得時視同現金（偏保守，v0.2.2 口徑）；FY2026 為公司法說值
A54: 在帳融資租賃負債（年底） | B54: US$B | E54: =fl_liab -> 66.594 | F54: =CF!E54-CF!F55 -> 62.46973 | G54: =CF!F54-CF!G55 -> 57.986868 | H54: =CF!G54-CF!H55 -> 53.928277 | I54: =CF!H54-CF!I55 -> 49.785049 | J54: =CF!I54-CF!J55 -> 45.482377 | K54: =CF!J54-CF!K55 -> 40.986084
A55: 在帳融資租賃本金（付款 − 利息） | B55: US$B | F55: =fl_pay_27-CF!E54*fl_rate -> 4.12427 | G55: =fl_pay_28-CF!F54*fl_rate -> 4.4828621 | H55: =fl_pay_29-CF!G54*fl_rate -> 4.0585909 | I55: =fl_pay_30-CF!H54*fl_rate -> 4.1432275 | J55: =fl_pay_31-CF!I54*fl_rate -> 4.3026728 | K55: =fl_pay_32-CF!J54*fl_rate -> 4.4962931
A56: 自由現金流（財報現金：營業現金流 − 資本支出 − 融資租賃本金） | B56: US$B | E56: =Q!M35-Q!M36-Q!M43 -> 63.886 | F56: =CF!F50-CF!F53-CF!F55 -> 1.2106755 | G56: =CF!G50-CF!G53-CF!G55 -> 31.714531 | H56: =CF!H50-CF!H53-CF!H55 -> 70.552903 | I56: =CF!I50-CF!I53-CF!I55 -> 134.50036 | J56: =CF!J50-CF!J53-CF!J55 -> 205.39456 | K56: =CF!K50-CF!K53-CF!K55 -> 239.8813 | L56: FY2026 為實績（現金資本支出口徑）；收支關卡用此列（不含影子效益）
A57: 每股股利 | B57: US$ | F57: =dps_27 -> 3.85 | G57: =CF!F57*(1+dps_g) -> 4.158 | H57: =CF!G57*(1+dps_g) -> 4.49064 | I57: =CF!H57*(1+dps_g) -> 4.8498912 | J57: =CF!I57*(1+dps_g) -> 5.2378825 | K57: =CF!J57*(1+dps_g) -> 5.6569131
A58: 股利 | B58: US$B | E58: =Q!M41 -> 26.445 | F58: =CF!F57*CF!E67 -> 28.59395 | G58: =CF!G57*CF!F67 -> 31.068576 | H58: =CF!H57*CF!G67 -> 33.751288 | I58: =CF!I57*CF!H67 -> 36.502331 | J58: =CF!J57*CF!I67 -> 39.490916 | K58: =CF!K57*CF!J67 -> 42.737444 | L58: 每股股利 × 期初流通股數（避免與回購循環）
A59: 自由現金流扣股利 | B59: US$B | E59: =CF!E56-CF!E58 -> 37.441 | F59: =CF!F56-CF!F58 -> -27.383274 | G59: =CF!G56-CF!G58 -> 0.64595491 | H59: =CF!H56-CF!H58 -> 36.801614 | I59: =CF!I56-CF!I58 -> 97.998027 | J59: =CF!J56-CF!J58 -> 165.90364 | K59: =CF!K56-CF!K58 -> 197.14386
A60: 債務到期償還 | B60: US$B | F60: =debt_mat_27 -> 9.25 | G60: =debt_mat_28 -> 0 | H60: =debt_mat_29 -> 2.001 | I60: =debt_mat_30 -> 0 | J60: =debt_mat_31 -> 0.5 | K60: =debt_mat_32 -> 0
A61: 回購（現金不足時先減） | B61: US$B | E61: =Q!M40 -> 22.271 | F61: =MAX(0,MIN(bb_target,CF!E63+CF!F59-CF!F60-min_cash)) -> 0 | G61: =MAX(0,MIN(bb_target,CF!F63+CF!G59-CF!G60-min_cash)) -> 0.64595491 | H61: =MAX(0,MIN(bb_target,CF!G63+CF!H59-CF!H60-min_cash)) -> 22.271 | I61: =MAX(0,MIN(bb_target,CF!H63+CF!I59-CF!I60-min_cash)) -> 22.271 | J61: =MAX(0,MIN(bb_target,CF!I63+CF!J59-CF!J60-min_cash)) -> 22.271 | K61: =MAX(0,MIN(bb_target,CF!J63+CF!K59-CF!K60-min_cash)) -> 22.271
A62: 新增舉債（維持最低現金） | B62: US$B | F62: =MAX(0,min_cash-(CF!E63+CF!F59-CF!F60-CF!F61)) -> 9.7902745 | G62: =MAX(0,min_cash-(CF!F63+CF!G59-CF!G60-CF!G61)) -> 0 | H62: =MAX(0,min_cash-(CF!G63+CF!H59-CF!H60-CF!H61)) -> 0 | I62: =MAX(0,min_cash-(CF!H63+CF!I59-CF!I60-CF!I61)) -> 0 | J62: =MAX(0,min_cash-(CF!I63+CF!J59-CF!J60-CF!J61)) -> 0 | K62: =MAX(0,min_cash-(CF!J63+CF!K59-CF!K60-CF!K61)) -> 0
A63: 現金與短期投資（年底） | B63: US$B | E63: =cash_open -> 76.843 | F63: =CF!E63+CF!F59-CF!F60-CF!F61+CF!F62 -> 50 | G63: =CF!F63+CF!G59-CF!G60-CF!G61+CF!G62 -> 50 | H63: =CF!G63+CF!H59-CF!H60-CF!H61+CF!H62 -> 62.529614 | I63: =CF!H63+CF!I59-CF!I60-CF!I61+CF!I62 -> 138.25664 | J63: =CF!I63+CF!J59-CF!J60-CF!J61+CF!J62 -> 281.38928 | K63: =CF!J63+CF!K59-CF!K60-CF!K61+CF!K62 -> 456.26214
A64: 債務（年底，面額） | B64: US$B | E64: =debt_face -> 46.136 | F64: =CF!E64-CF!F60+CF!F62 -> 46.676274 | G64: =CF!F64-CF!G60+CF!G62 -> 46.676274 | H64: =CF!G64-CF!H60+CF!H62 -> 44.675274 | I64: =CF!H64-CF!I60+CF!I62 -> 44.675274 | J64: =CF!I64-CF!J60+CF!J62 -> 44.175274 | K64: =CF!J64-CF!K60+CF!K62 -> 44.175274
A65: 淨現金（不含租賃） | B65: US$B | E65: =CF!E63-CF!E64 -> 30.707 | F65: =CF!F63-CF!F64 -> 3.3237255 | G65: =CF!G63-CF!G64 -> 3.3237255 | H65: =CF!H63-CF!H64 -> 17.85434 | I65: =CF!I63-CF!I64 -> 93.581367 | J65: =CF!J63-CF!J64 -> 237.21401 | K65: =CF!K63-CF!K64 -> 412.08686
A66: 回購均價 | B66: US$ | F66: =px*(1+bb_g)^(Thesis!F55-base_fy-mid_yr) -> 553.49416 | G66: =px*(1+bb_g)^(Thesis!G55-base_fy-mid_yr) -> 597.77369 | H66: =px*(1+bb_g)^(Thesis!H55-base_fy-mid_yr) -> 645.59558 | I66: =px*(1+bb_g)^(Thesis!I55-base_fy-mid_yr) -> 697.24323 | J66: =px*(1+bb_g)^(Thesis!J55-base_fy-mid_yr) -> 753.02269 | K66: =px*(1+bb_g)^(Thesis!K55-base_fy-mid_yr) -> 813.2645
A67: 流通股數（年底） | B67: 十億股 | E67: =sh_out26 -> 7.427 | F67: =CF!E67+sh_iss-CF!F61/CF!F66 -> 7.472 | G67: =CF!F67+sh_iss-CF!G61/CF!G66 -> 7.5159194 | H67: =CF!G67+sh_iss-CF!H61/CF!H66 -> 7.5264226 | I67: =CF!H67+sh_iss-CF!I61/CF!I66 -> 7.5394811 | J67: =CF!I67+sh_iss-CF!J61/CF!J66 -> 7.5549056 | K67: =CF!J67+sh_iss-CF!K61/CF!K66 -> 7.5725209
A68: 稀釋加權股數 | B68: 十億股 | E68: =sh_dil26 -> 7.453 | F68: =(CF!E67+CF!F67)/2+dil_gap -> 7.4735 | G68: =(CF!F67+CF!G67)/2+dil_gap -> 7.5179597 | H68: =(CF!G67+CF!H67)/2+dil_gap -> 7.545171 | I68: =(CF!H67+CF!I67)/2+dil_gap -> 7.5569518 | J68: =(CF!I67+CF!J67)/2+dil_gap -> 7.5711933 | K68: =(CF!J67+CF!K67)/2+dil_gap -> 7.5877132
A69: 自由現金流扣股利（FY2027–FY2031 合計，本情境） | B69: US$B | C69: =SUM(CF!F59:J59) -> 273.96596
A70: 檢查：收支關卡＝首年起五年自由現金流扣股利（逐欄加總） | B70: US$B | C70: =CF!$C$69-(CF!F59+CF!G59+CF!H59+CF!I59+CF!J59) -> 0
A71: 是否需要舉債或停止回購（FY2027–FY2031） | B71: 文字 | C71: =IF(SUM(CF!F62:J62)>0.05,"需要舉債 "&TEXT(SUM(CF!F62:J62),"0.0")&" 十億美元","不需舉債")&"；"&IF(SUM(CF!F61:J61)<COUNT(CF!F61:J61)*bb_target-0.05,"回購較每年 "&TEXT(bb_target,"0.0")&" 的目標少 "&TEXT(COUNT(CF!F61:J61)*bb_target-SUM(CF!F61:J61),"0.0")&" 十億美元（"&TEXT(COUNTIF(CF!F61:J61,"<"&(bb_target-0.05)),"0")&" 年減少）","回購不減") -> 需要舉債 9.8 十億美元；回購較每年 22.3 的目標少 43.9 十億美元（2 年減少）
A72: 情境 C（保守）｜現金流與資金（CF）
A73: 項目 | B73: 單位 | C73: FY2024A | D73: FY2025A | E73: FY2026A | F73: FY2027 | G73: FY2028 | H73: FY2029 | I73: FY2030 | J73: FY2031 | K73: FY2032 | L73: 說明
A74: 淨利（財報口徑） | B74: US$B | F74: =PL!F123 -> 136.97805 | G74: =PL!G123 -> 143.81378 | H74: =PL!H123 -> 146.22768 | I74: =PL!I123 -> 154.84319 | J74: =PL!J123 -> 164.60446 | K74: =PL!K123 -> 175.62302
A75: 非 AI 折舊攤銷 | B75: US$B | E75: =Q!M38-Thesis!E138 -> 22.228594 | F75: =CF!E75*(1-1/life_nonai)+CF!F81/life_nonai -> 23.548669 | G75: =CF!F75*(1-1/life_nonai)+CF!G81/life_nonai -> 25.264092 | H75: =CF!G75*(1-1/life_nonai)+CF!H81/life_nonai -> 27.343834 | I75: =CF!H75*(1-1/life_nonai)+CF!I81/life_nonai -> 29.731791 | J75: =CF!I75*(1-1/life_nonai)+CF!J81/life_nonai -> 32.354203 | K75: =CF!J75*(1-1/life_nonai)+CF!K81/life_nonai -> 35.128153 | L75: FY2026＝公司 D&A − AI 折舊估計（C17）
A76: 折舊攤銷合計（AI＋非 AI） | B76: US$B | E76: =Thesis!E138+CF!E75 -> 38.534 | F76: =Thesis!F138+CF!F75 -> 58.301705 | G76: =Thesis!G138+CF!G75 -> 85.795825 | H76: =Thesis!H138+CF!H75 -> 115.11115 | I76: =Thesis!I138+CF!I75 -> 141.74383 | J76: =Thesis!J138+CF!J75 -> 161.56291 | K76: =Thesis!K138+CF!K75 -> 174.8008
A77: 股票薪酬（現金流量表加回；DCF 視為現金成本） | B77: US$B | F77: =Seg!F83*sbc_r -> 14.710235 | G77: =Seg!G83*sbc_r -> 17.061234 | H77: =Seg!H83*sbc_r -> 19.264485 | I77: =Seg!I83*sbc_r -> 21.574408 | J77: =Seg!J83*sbc_r -> 23.518109 | K77: =Seg!K83*sbc_r -> 25.106566
A78: 營運資金變動 | B78: US$B | F78: =wc27 -> -4.895 | G78: =wc_f -> 0 | H78: =wc_f -> 0 | I78: =wc_f -> 0 | J78: =wc_f -> 0 | K78: =wc_f -> 0 | L78: C14：首期＝上一年度實績；之後 wc_f
A79: 營業現金流 | B79: US$B | E79: =Q!M35 -> 182.935 | F79: =CF!F74+CF!F76+CF!F77+CF!F78 -> 205.09498 | G79: =CF!G74+CF!G76+CF!G77+CF!G78 -> 246.67084 | H79: =CF!H74+CF!H76+CF!H77+CF!H78 -> 280.60332 | I79: =CF!I74+CF!I76+CF!I77+CF!I78 -> 318.16143 | J79: =CF!J74+CF!J76+CF!J77+CF!J78 -> 349.68548 | K79: =CF!K74+CF!K76+CF!K77+CF!K78 -> 375.53038
A80: AI 資本支出（Thesis） | B80: US$B | F80: =Thesis!F135 -> 168.77065 | G80: =Thesis!G135 -> 183.57418 | H80: =Thesis!H135 -> 188.08029 | I80: =Thesis!I135 -> 163.70667 | J80: =Thesis!J135 -> 124.51248 | K80: =Thesis!K135 -> 114.95944
A81: 非 AI 資本支出（各線營收 × 比例） | B81: US$B | E81: =Seg!E61*cx_azo+Seg!E68*cx_m365+Seg!E69*cx_lic+(Seg!E71+Seg!E73)*cx_ind+Seg!E76*cx_srch+(Seg!E78+Seg!E80)*cx_dev -> 30.184659 | F81: =Seg!F61*cx_azo+Seg!F68*cx_m365+Seg!F69*cx_lic+(Seg!F71+Seg!F73)*cx_ind+Seg!F76*cx_srch+(Seg!F78+Seg!F80)*cx_dev -> 35.429347 | G81: =Seg!G61*cx_azo+Seg!G68*cx_m365+Seg!G69*cx_lic+(Seg!G71+Seg!G73)*cx_ind+Seg!G76*cx_srch+(Seg!G78+Seg!G80)*cx_dev -> 40.702894 | H81: =Seg!H61*cx_azo+Seg!H68*cx_m365+Seg!H69*cx_lic+(Seg!H71+Seg!H73)*cx_ind+Seg!H76*cx_srch+(Seg!H78+Seg!H80)*cx_dev -> 46.061514 | I81: =Seg!I61*cx_azo+Seg!I68*cx_m365+Seg!I69*cx_lic+(Seg!I71+Seg!I73)*cx_ind+Seg!I76*cx_srch+(Seg!I78+Seg!I80)*cx_dev -> 51.2234 | J81: =Seg!J61*cx_azo+Seg!J68*cx_m365+Seg!J69*cx_lic+(Seg!J71+Seg!J73)*cx_ind+Seg!J76*cx_srch+(Seg!J78+Seg!J80)*cx_dev -> 55.955913 | K81: =Seg!K61*cx_azo+Seg!K68*cx_m365+Seg!K69*cx_lic+(Seg!K71+Seg!K73)*cx_ind+Seg!K76*cx_srch+(Seg!K78+Seg!K80)*cx_dev -> 60.093703
A82: 資本支出合計（公司口徑，含融資租賃） | B82: US$B | E82: =Q!M42 -> 145.3 | F82: =CF!F80+CF!F81 -> 204.2 | G82: =CF!G80+CF!G81 -> 224.27707 | H82: =CF!H80+CF!H81 -> 234.1418 | I82: =CF!I80+CF!I81 -> 214.93007 | J82: =CF!J80+CF!J81 -> 180.46839 | K82: =CF!K80+CF!K81 -> 175.05314 | L82: 新的融資租賃在取得時視同現金（偏保守，v0.2.2 口徑）；FY2026 為公司法說值
A83: 在帳融資租賃負債（年底） | B83: US$B | E83: =fl_liab -> 66.594 | F83: =CF!E83-CF!F84 -> 62.46973 | G83: =CF!F83-CF!G84 -> 57.986868 | H83: =CF!G83-CF!H84 -> 53.928277 | I83: =CF!H83-CF!I84 -> 49.785049 | J83: =CF!I83-CF!J84 -> 45.482377 | K83: =CF!J83-CF!K84 -> 40.986084
A84: 在帳融資租賃本金（付款 − 利息） | B84: US$B | F84: =fl_pay_27-CF!E83*fl_rate -> 4.12427 | G84: =fl_pay_28-CF!F83*fl_rate -> 4.4828621 | H84: =fl_pay_29-CF!G83*fl_rate -> 4.0585909 | I84: =fl_pay_30-CF!H83*fl_rate -> 4.1432275 | J84: =fl_pay_31-CF!I83*fl_rate -> 4.3026728 | K84: =fl_pay_32-CF!J83*fl_rate -> 4.4962931
A85: 自由現金流（財報現金：營業現金流 − 資本支出 − 融資租賃本金） | B85: US$B | E85: =Q!M35-Q!M36-Q!M43 -> 63.886 | F85: =CF!F79-CF!F82-CF!F84 -> -3.229285 | G85: =CF!G79-CF!G82-CF!G84 -> 17.910902 | H85: =CF!H79-CF!H82-CF!H84 -> 42.402925 | I85: =CF!I79-CF!I82-CF!I84 -> 99.088129 | J85: =CF!J79-CF!J82-CF!J84 -> 164.91442 | K85: =CF!K79-CF!K82-CF!K84 -> 195.98095 | L85: FY2026 為實績（現金資本支出口徑）；收支關卡用此列（不含影子效益）
A86: 每股股利 | B86: US$ | F86: =dps_27 -> 3.85 | G86: =CF!F86*(1+dps_g) -> 4.158 | H86: =CF!G86*(1+dps_g) -> 4.49064 | I86: =CF!H86*(1+dps_g) -> 4.8498912 | J86: =CF!I86*(1+dps_g) -> 5.2378825 | K86: =CF!J86*(1+dps_g) -> 5.6569131
A87: 股利 | B87: US$B | E87: =Q!M41 -> 26.445 | F87: =CF!F86*CF!E96 -> 28.59395 | G87: =CF!G86*CF!F96 -> 31.068576 | H87: =CF!H86*CF!G96 -> 33.756141 | I87: =CF!I86*CF!H96 -> 36.624952 | J87: =CF!J86*CF!I96 -> 39.623347 | K87: =CF!K86*CF!J96 -> 42.88047 | L87: 每股股利 × 期初流通股數（避免與回購循環）
A88: 自由現金流扣股利 | B88: US$B | E88: =CF!E85-CF!E87 -> 37.441 | F88: =CF!F85-CF!F87 -> -31.823235 | G88: =CF!G85-CF!G87 -> -13.157674 | H88: =CF!H85-CF!H87 -> 8.6467844 | I88: =CF!I85-CF!I87 -> 62.463176 | J88: =CF!J85-CF!J87 -> 125.29107 | K88: =CF!K85-CF!K87 -> 153.10048
A89: 債務到期償還 | B89: US$B | F89: =debt_mat_27 -> 9.25 | G89: =debt_mat_28 -> 0 | H89: =debt_mat_29 -> 2.001 | I89: =debt_mat_30 -> 0 | J89: =debt_mat_31 -> 0.5 | K89: =debt_mat_32 -> 0
A90: 回購（現金不足時先減） | B90: US$B | E90: =Q!M40 -> 22.271 | F90: =MAX(0,MIN(bb_target,CF!E92+CF!F88-CF!F89-min_cash)) -> 0 | G90: =MAX(0,MIN(bb_target,CF!F92+CF!G88-CF!G89-min_cash)) -> 0 | H90: =MAX(0,MIN(bb_target,CF!G92+CF!H88-CF!H89-min_cash)) -> 6.6457844 | I90: =MAX(0,MIN(bb_target,CF!H92+CF!I88-CF!I89-min_cash)) -> 22.271 | J90: =MAX(0,MIN(bb_target,CF!I92+CF!J88-CF!J89-min_cash)) -> 22.271 | K90: =MAX(0,MIN(bb_target,CF!J92+CF!K88-CF!K89-min_cash)) -> 22.271
A91: 新增舉債（維持最低現金） | B91: US$B | F91: =MAX(0,min_cash-(CF!E92+CF!F88-CF!F89-CF!F90)) -> 14.230235 | G91: =MAX(0,min_cash-(CF!F92+CF!G88-CF!G89-CF!G90)) -> 13.157674 | H91: =MAX(0,min_cash-(CF!G92+CF!H88-CF!H89-CF!H90)) -> 0 | I91: =MAX(0,min_cash-(CF!H92+CF!I88-CF!I89-CF!I90)) -> 0 | J91: =MAX(0,min_cash-(CF!I92+CF!J88-CF!J89-CF!J90)) -> 0 | K91: =MAX(0,min_cash-(CF!J92+CF!K88-CF!K89-CF!K90)) -> 0
A92: 現金與短期投資（年底） | B92: US$B | E92: =cash_open -> 76.843 | F92: =CF!E92+CF!F88-CF!F89-CF!F90+CF!F91 -> 50 | G92: =CF!F92+CF!G88-CF!G89-CF!G90+CF!G91 -> 50 | H92: =CF!G92+CF!H88-CF!H89-CF!H90+CF!H91 -> 50 | I92: =CF!H92+CF!I88-CF!I89-CF!I90+CF!I91 -> 90.192176 | J92: =CF!I92+CF!J88-CF!J89-CF!J90+CF!J91 -> 192.71224 | K92: =CF!J92+CF!K88-CF!K89-CF!K90+CF!K91 -> 323.54173
A93: 債務（年底，面額） | B93: US$B | E93: =debt_face -> 46.136 | F93: =CF!E93-CF!F89+CF!F91 -> 51.116235 | G93: =CF!F93-CF!G89+CF!G91 -> 64.273909 | H93: =CF!G93-CF!H89+CF!H91 -> 62.272909 | I93: =CF!H93-CF!I89+CF!I91 -> 62.272909 | J93: =CF!I93-CF!J89+CF!J91 -> 61.772909 | K93: =CF!J93-CF!K89+CF!K91 -> 61.772909
A94: 淨現金（不含租賃） | B94: US$B | E94: =CF!E92-CF!E93 -> 30.707 | F94: =CF!F92-CF!F93 -> -1.116235 | G94: =CF!G92-CF!G93 -> -14.273909 | H94: =CF!H92-CF!H93 -> -12.272909 | I94: =CF!I92-CF!I93 -> 27.919267 | J94: =CF!J92-CF!J93 -> 130.93934 | K94: =CF!K92-CF!K93 -> 261.76882
A95: 回購均價 | B95: US$ | F95: =px*(1+bb_g)^(Thesis!F104-base_fy-mid_yr) -> 553.49416 | G95: =px*(1+bb_g)^(Thesis!G104-base_fy-mid_yr) -> 597.77369 | H95: =px*(1+bb_g)^(Thesis!H104-base_fy-mid_yr) -> 645.59558 | I95: =px*(1+bb_g)^(Thesis!I104-base_fy-mid_yr) -> 697.24323 | J95: =px*(1+bb_g)^(Thesis!J104-base_fy-mid_yr) -> 753.02269 | K95: =px*(1+bb_g)^(Thesis!K104-base_fy-mid_yr) -> 813.2645
A96: 流通股數（年底） | B96: 十億股 | E96: =sh_out26 -> 7.427 | F96: =CF!E96+sh_iss-CF!F90/CF!F95 -> 7.472 | G96: =CF!F96+sh_iss-CF!G90/CF!G95 -> 7.517 | H96: =CF!G96+sh_iss-CF!H90/CF!H95 -> 7.551706 | I96: =CF!H96+sh_iss-CF!I90/CF!I95 -> 7.5647645 | J96: =CF!I96+sh_iss-CF!J90/CF!J95 -> 7.580189 | K96: =CF!J96+sh_iss-CF!K90/CF!K95 -> 7.5978043
A97: 稀釋加權股數 | B97: 十億股 | E97: =sh_dil26 -> 7.453 | F97: =(CF!E96+CF!F96)/2+dil_gap -> 7.4735 | G97: =(CF!F96+CF!G96)/2+dil_gap -> 7.5185 | H97: =(CF!G96+CF!H96)/2+dil_gap -> 7.558353 | I97: =(CF!H96+CF!I96)/2+dil_gap -> 7.5822352 | J97: =(CF!I96+CF!J96)/2+dil_gap -> 7.5964767 | K97: =(CF!J96+CF!K96)/2+dil_gap -> 7.6129966
A98: 自由現金流扣股利（FY2027–FY2031 合計，本情境） | B98: US$B | C98: =SUM(CF!F88:J88) -> 151.42012
A99: 檢查：收支關卡＝首年起五年自由現金流扣股利（逐欄加總） | B99: US$B | C99: =CF!$C$98-(CF!F88+CF!G88+CF!H88+CF!I88+CF!J88) -> 0
A100: 是否需要舉債或停止回購（FY2027–FY2031） | B100: 文字 | C100: =IF(SUM(CF!F91:J91)>0.05,"需要舉債 "&TEXT(SUM(CF!F91:J91),"0.0")&" 十億美元","不需舉債")&"；"&IF(SUM(CF!F90:J90)<COUNT(CF!F90:J90)*bb_target-0.05,"回購較每年 "&TEXT(bb_target,"0.0")&" 的目標少 "&TEXT(COUNT(CF!F90:J90)*bb_target-SUM(CF!F90:J90),"0.0")&" 十億美元（"&TEXT(COUNTIF(CF!F90:J90,"<"&(bb_target-0.05)),"0")&" 年減少）","回購不減") -> 需要舉債 27.4 十億美元；回購較每年 22.3 的目標少 60.2 十億美元（3 年減少）

Sheet Val
A1: Val — 目標價（約 12 個月後，2027-10-27）＝DCF 50%＋分部加總 SOTP 50%（Comparable 在分部層做）；情境權重 A 25%／B 50%／C 25%（皆 [判斷] 預設，Andy 可改，In 頁黃底）。主值＝讀法 2（自用 AI 價值中性），讀法 1 並列
A2: 口徑（修正一）：DCF 的自由現金流扣股票薪酬（視為現金成本）、加自用 AI 影子效益（稅後），在帳融資租賃負債自權益橋扣除，推到目標價時點後扣期間股利；SOTP 的產品線 EBITDA 為股票薪酬加回口徑（與同業倍數同口徑），AI 基礎設施模組以自身 DCF（含資本支出與汰換）計價，同業倍數版列對照
A4: 0. 目標價
A5: 0.1 DCF（評價用自由現金流折現；WACC：Blume β、約 10 年期 kd、負債含融資租賃；g 3%）
A6: 項目 | B6: 情境 A（樂觀） | C6: 情境 B（基準） | D6: 情境 C（保守） | E6: 說明
A7: DCF 企業價值（2026-06-30） | B7: =Val!$C$81 -> 2398.4445 | C7: =Val!$C$127 -> 2149.8991 | D7: =Val!$C$173 -> 1851.1846 | E7: US$B
A8: 永續價值占比 | B8: =Val!$C$82 -> 0.73206057 | C8: =Val!$C$128 -> 0.73743255 | D8: =Val!$C$174 -> 0.74597987 | E8: 永續價值現值 ÷ EV
A9: 加：淨現金（FY2026 年底） | B9: =CF!E36 -> 30.707 | C9: =CF!E65 -> 30.707 | D9: =CF!E94 -> 30.707
A10: 減：在帳融資租賃負債（FY2026 年底） | B10: =CF!E25 -> 66.594 | C10: =CF!E54 -> 66.594 | D10: =CF!E83 -> 66.594 | E10: 修正一 F6：融資租賃列入淨負債
A11: 加：OpenAI 持股（比例 × 估值 ×（1 − 流動性折價）） | B11: =oai_v -> 170.4 | C11: =oai_v -> 170.4 | D11: =oai_v -> 170.4 | E11: Anthropic 比例未揭露，不估值
A12: DCF 每股價值（2026-06-30） | B12: =Val!$C$84 -> 339.85744 | C12: =Val!$C$130 -> 306.50906 | D12: =Val!$C$176 -> 266.4293 | E12: ÷ FY2026 稀釋股數
A13: DCF 情境價值推到 12 個月後（×（1＋WACC）^t − 期間股利） | B13: =Val!$C$86 -> 382.11751 | C13: =Val!$C$132 -> 344.14261 | D13: =Val!$C$178 -> 298.50244 | E13: t＝評價日 → 2027-10-27；扣 FY2027 股利與 FY2028 第一季股利
A14: DCF 目標價（情境加權） | B14: =w_A*B13+w_B*C13+w_C*D13 -> 342.22629 | E14: Σ 情境權重 × 情境價值
A15: WACC／永續成長率 | B15: =wacc -> 0.10293442 | C15: =g_tv -> 0.03 | E15: WACC＝In 頁（CAPM，Blume β）；g＝In 頁
A17: 0.2 分部加總（SOTP；Comparable 在分部層做：非 AI 產品線＝目標價時點 NTM EBITDA × 同業 NTM EV/EBITDA 中位數；AI 基礎設施＝模組 DCF）
A18: 項目 | B18: 情境 A（樂觀） | C18: 情境 B（基準） | D18: 情境 C（保守） | E18: 倍數（x）
A19: EV：AI 基礎設施模組（Azure AI＋自用 AI；模組 DCF） | B19: =Val!$C$102 -> 395.34116 | C19: =Val!$C$148 -> 163.34394 | D19: =Val!$C$194 -> -125.78243
A20: EV：Azure 其他（非 AI 雲端同業） | B20: =Val!$C$104 -> 1075.8947 | C20: =Val!$C$150 -> 1070.815 | D20: =Val!$C$196 -> 1064.0989 | E20: =m_cloud -> 13.82
A21: EV：Microsoft 365 cloud（企業軟體同業） | B21: =Val!$C$105 -> 1124.9084 | C21: =Val!$C$151 -> 1084.5052 | D21: =Val!$C$197 -> 1044.0482 | E21: =m_sw -> 10.8
A22: EV：Productivity and server licensing（企業軟體） | B22: =Val!$C$106 -> 379.14617 | C22: =Val!$C$152 -> 379.44665 | D22: =Val!$C$198 -> 379.75567 | E22: =m_sw -> 10.8
A23: EV：Industry solutions（企業軟體） | B23: =Val!$C$107 -> 109.06201 | C23: =Val!$C$153 -> 109.24583 | D23: =Val!$C$199 -> 109.4349 | E23: =m_sw -> 10.8
A24: EV：Frontier and support services（企業軟體） | B24: =Val!$C$108 -> 41.609111 | C24: =Val!$C$154 -> 41.679152 | D24: =Val!$C$200 -> 41.751188 | E24: =m_sw -> 10.8
A25: EV：Search and advertising（數位廣告同業） | B25: =Val!$C$109 -> 114.96637 | C25: =Val!$C$155 -> 115.16024 | D25: =Val!$C$201 -> 115.35964 | E25: =m_ads -> 9.11
A26: EV：XBOX（遊戲同業） | B26: =Val!$C$110 -> 97.615221 | C26: =Val!$C$156 -> 97.781441 | D26: =Val!$C$202 -> 97.952354 | E26: =m_game -> 12.63
A27: EV：Windows OEM and devices（PC／裝置同業） | B27: =Val!$C$111 -> 96.77762 | C27: =Val!$C$157 -> 96.94274 | D27: =Val!$C$203 -> 97.112536 | E27: =m_pc -> 14.47
A28: 分部加總 EV | B28: =Val!$C$112 -> 3435.3208 | C28: =Val!$C$158 -> 3158.9201 | D28: =Val!$C$204 -> 2823.731 | E28: US$B
A29: 加：淨現金（FY2027 年底）＋OpenAI 持股 − 在帳融資租賃負債 | B29: =Val!$C$113 -> 115.07958 | C29: =Val!$C$159 -> 111.254 | D29: =Val!$C$205 -> 106.81403
A30: 分部加總每股價值（目標價時點） | B30: =Val!$C$114 -> 475.16065 | C30: =Val!$C$160 -> 437.65714 | D30: =Val!$C$206 -> 392.20356 | E30: ÷ FY2027 年底流通股數
A31: Comparable 目標價（市場主流同業法） | B31: =w_A*B30+w_B*C30+w_C*D30 -> 435.66962 | E31: ＝分部加總（SOTP）情境加權；同業倍數見 In 頁 B 節與 E 欄
A32: 對照：Azure AI 以同業倍數計（NTM EBITDA × 6×；v0.3 初版口徑） | B32: =Val!$C$103 -> 551.71113 | C32: =Val!$C$149 -> 454.92244 | D32: =Val!$C$195 -> 338.77601 | E32: F3：AI 腿不再用 EBITDA × 倍數（忽略資本密集度）；差額見報告
A34: 0.3 結論
A35: 項目 | B35: 數值 | C35: 對照 | D35: 對照 | E35: 說明
A36: 目標價（DCF 與 Comparable 加權） | B36: =w_dcf*$B$14+(1-w_dcf)*$B$31 -> 388.94796 | E36: w_dcf × DCF ＋（1 − w_dcf）× 分部加總；[判斷] 預設 50／50；主值＝讀法 2
A37: DCF 目標價（情境加權） | B37: =$B$14 -> 342.22629
A38: 市場共識目標價 | B38: =cons_tp -> 603.43 | C38: =cons_tp_lo -> 440 | D38: =cons_tp_hi -> 870 | E38: S&P（經 StockAnalysis）57 位平均；C、D＝最低、最高（2026-10-26）
A39: 現價（2026-10-26 收盤） | B39: =px -> 532.6 | E39: StockAnalysis（2026-10-26 收盤）
A40: 上檔空間：加權目標價 | B40: =$B$36/px-1 -> -0.26971845 | E40: 目標價 ÷ 現價 − 1
A41: 上檔空間：Comparable 目標價 | B41: =$B$31/px-1 -> -0.1819947
A42: 上檔空間級距 | B42: =IF($B$40>0.5,"大於 50%",IF($B$40>0.25,"25%–50%",IF($B$40>=0,"0%–25%",IF($B$40>=-0.25,"0%～−25%",IF($B$40>=-0.5,"−25%～−50%","小於 −50%"))))) -> −25%～−50% | E42: 以「上檔空間：加權目標價」分六級（Andy 2026-10-25 14:00）
A43: 投資建議 | B43: =IF($B$40>=0.5,"強力買進",IF($B$40>=0.25,"買進",IF($B$40>-0.25,"中立",IF($B$40>-0.5,"放空","強力放空")))) -> 放空 | E43: 五級固定規則：≥ +50% 強力買進、+25%～+50% 買進、−25%～+25% 中立、−50%～−25% 放空、≤ −50% 強力放空
A44: 情境目標價（DCF 50%＋SOTP 50%） | B44: =Val!$C$115 -> 428.63908 | C44: =Val!$C$161 -> 390.89987 | D44: =Val!$C$207 -> 345.353 | E44: A／B／C
A45: 上檔空間：情境目標價 | B45: =B44/px-1 -> -0.19519511 | C45: =C44/px-1 -> -0.26605357 | D45: =D44/px-1 -> -0.35157153
A46: 投資建議（基準情境 B，參考） | C46: =IF(C45>=0.5,"強力買進",IF(C45>=0.25,"買進",IF(C45>-0.25,"中立",IF(C45>-0.5,"放空","強力放空")))) -> 放空 | E46: 地圖與評等用加權目標價
A47: 目標價（讀法 1：自用 AI 只計成本；敏感度） | B47: =Sens!C4 -> 303.63913 | E47: Sens 頁「讀法 1」案例（三情境全部重算）
A48: 上檔空間（讀法 1） | B48: =$B$47/px-1 -> -0.42989273
A49: 投資建議（讀法 1） | B49: =IF($B$48>=0.5,"強力買進",IF($B$48>=0.25,"買進",IF($B$48>-0.25,"中立",IF($B$48>-0.5,"放空","強力放空")))) -> 放空
A50: 悲觀情境價（C 情境 DCF，12 個月後） | B50: =D13 -> 298.50244 | E50: 工作單：悲觀情境價＝C 情境 DCF
A51: 價格帶（DCF 不如預期～順利） | B51: =D13 -> 298.50244 | C51: =B13 -> 382.11751 | E51: B＝C 情境 DCF、C＝A 情境 DCF（皆推到 12 個月後）
A52: 現價 ÷ FY2028 EPS（模型） | B52: =px/PL!G49 -> 20.507258 | C52: =px/PL!G88 -> 21.592266 | D52: =px/PL!G127 -> 23.016436 | E52: A／B／C；評價口徑 EPS（讀法 2）
A53: 加權目標價 ÷ FY2028 EPS（基準） | B53: =$B$36/PL!G88 -> 15.768434
A54: 目標價方法 | B54: DCF：評價用自由現金流（營業現金流 − 股票薪酬 − 公司口徑資本支出＋自用 AI 影子效益稅後），WACC（CAPM：rf 5.00%（2026-10-26）、Blume β、ERP 5%；kd＝rf＋10 年期 AAA 利差；負債含融資租賃），FY2027–FY2032 明確期（FY2029 後 MW 新增速度收斂），永續期 NOPAT ×（1 − g ÷ WACC）÷（WACC − g），g 3%；評價日 2026-06-30，以 WACC 推到 2027-10-27 並扣期間股利。SOTP：AI 基礎設施模組 DCF；Azure 其他 13.82×（非 AI 雲端 8 家）、M365 cloud／授權／產業／Frontier 10.8×（企業軟體 5 家，不含 MSFT）、搜尋與廣告 9.11×（6 家）、XBOX 12.63×（遊戲 3 家 TTM）、Windows 14.47×（PC 3 家 TTM），乘目標價時點 NTM EBITDA（股票薪酬加回）；加淨現金與 OpenAI 持股（25% × 852 ×（1 − 20%））、減在帳融資租賃負債。
A56: 1. 各情境評價明細（引擎輸出；列 70 起）
A70: 情境 A（樂觀）｜評價（Val）
A71: 項目 | B71: 單位 | C71: FY2024A | D71: FY2025A | E71: FY2026A | F71: FY2027 | G71: FY2028 | H71: FY2029 | I71: FY2030 | J71: FY2031 | K71: FY2032 | L71: 說明
A72: 折現年數（期中，自評價日） | B72: 年 | F72: =Thesis!F6-base_fy-mid_yr -> 0.5 | G72: =Thesis!G6-base_fy-mid_yr -> 1.5 | H72: =Thesis!H6-base_fy-mid_yr -> 2.5 | I72: =Thesis!I6-base_fy-mid_yr -> 3.5 | J72: =Thesis!J6-base_fy-mid_yr -> 4.5 | K72: =Thesis!K6-base_fy-mid_yr -> 5.5
A73: 折現因子 | B73: x | F73: =1/(1+wacc)^Val!F72 -> 0.95219337 | G73: =1/(1+wacc)^Val!G72 -> 0.86332728 | H73: =1/(1+wacc)^Val!H72 -> 0.78275486 | I73: =1/(1+wacc)^Val!I72 -> 0.70970209 | J73: =1/(1+wacc)^Val!J72 -> 0.64346717 | K73: =1/(1+wacc)^Val!K72 -> 0.58341381
A74: 評價用自由現金流＝營業現金流 − 股票薪酬 − 資本支出＋影子效益 ×（1 − 稅率） | B74: US$B | F74: =CF!F21-CF!F19-CF!F24+Thesis!F44*(1-tax_f) -> 9.2999599 | G74: =CF!G21-CF!G19-CF!G24+Thesis!G44*(1-tax_f) -> 55.68038 | H74: =CF!H21-CF!H19-CF!H24+Thesis!H44*(1-tax_f) -> 114.63087 | I74: =CF!I21-CF!I19-CF!I24+Thesis!I44*(1-tax_f) -> 192.96069 | J74: =CF!J21-CF!J19-CF!J24+Thesis!J44*(1-tax_f) -> 273.74225 | K74: =CF!K21-CF!K19-CF!K24+Thesis!K44*(1-tax_f) -> 313.49184 | L74: 修正一：F2 股票薪酬視為現金成本；F1 讀法 2 影子效益；在帳融資租賃本金不扣，改在權益橋減負債（F6）
A75: 評價用自由現金流現值 | B75: US$B | F75: =Val!F74*Val!F73 -> 8.8553602 | G75: =Val!G74*Val!G73 -> 48.070391 | H75: =Val!H74*Val!H73 -> 89.727869 | I75: =Val!I74*Val!I73 -> 136.9446 | J75: =Val!J74*Val!J73 -> 176.14415 | K75: =Val!K74*Val!K73 -> 182.89547
A76: 明確期現值合計（FY2027–FY2032） | B76: US$B | C76: =SUM(Val!F75:K75) -> 642.63785
A77: 永續起點 NOPAT（FY2032 評價口徑營業利益 ×（1＋g）×（1 − 稅率）） | B77: US$B | C77: =PL!K39*(1+g_tv)*(1-tax_f) -> 325.3385
A78: 永續期自由現金流（NOPAT ×（1 − g ÷ 新投資報酬）） | B78: US$B | C78: =Val!$C$77*(1-g_tv/(wacc+ronic_prem)) -> 230.51934
A79: 永續價值（FY2032 年底） | B79: US$B | C79: =Val!$C$78/(wacc-g_tv) -> 3160.6385
A80: 永續價值現值 | B80: US$B | C80: =Val!$C$79/(1+wacc)^(Val!K72+mid_yr) -> 1755.8067
A81: DCF 企業價值（2026-06-30） | B81: US$B | C81: =Val!$C$76+Val!$C$80 -> 2398.4445
A82: 永續價值占比 | B82: % | C82: =Val!$C$80/Val!$C$81 -> 0.73206057
A83: 股東權益價值＝EV＋淨現金 − 在帳融資租賃負債（FY2026 年底）＋OpenAI 持股 | B83: US$B | C83: =Val!$C$81+CF!E36-CF!E25+oai_v -> 2532.9575
A84: DCF 每股價值（2026-06-30） | B84: US$ | C84: =Val!$C$83/sh_dil26 -> 339.85744
A85: 評價日到目標價時點已付的每股股利 | B85: US$ | C85: =dps_27+CF!G28*roll_div_q/q_per_yr -> 4.8895
A86: DCF 每股價值推到 12 個月後（×（1＋WACC）^t_roll − 期間股利） | B86: US$ | C86: =Val!$C$84*(1+wacc)^t_roll-Val!$C$85 -> 382.11751
A87: 非 AI 折舊 ÷（營收 − Azure AI） | B87: % | F87: =CF!F17/(Seg!F29-Thesis!F23) -> 0.06817736 | G87: =CF!G17/(Seg!G29-Thesis!G23) -> 0.065038541 | H87: =CF!H17/(Seg!H29-Thesis!H23) -> 0.063382542 | I87: =CF!I17/(Seg!I29-Thesis!I23) -> 0.063099814 | J87: =CF!J17/(Seg!J29-Thesis!J23) -> 0.063839998 | K87: =CF!K17/(Seg!K29-Thesis!K23) -> 0.065153108
A88: EBITDA：Microsoft 365 cloud（營收 ×（分配利益率＋折舊率＋股票薪酬率）） | B88: US$B | F88: =Seg!F14*(al_m365+Val!F87+sbc_r) -> 84.944047 | G88: =Seg!G14*(al_m365+Val!G87+sbc_r) -> 99.423614 | H88: =Seg!H14*(al_m365+Val!H87+sbc_r) -> 114.0687 | I88: =Seg!I14*(al_m365+Val!I87+sbc_r) -> 127.19642 | J88: =Seg!J14*(al_m365+Val!J87+sbc_r) -> 138.61958 | K88: =Seg!K14*(al_m365+Val!K87+sbc_r) -> 149.65977 | L88: F2：同業 EV/EBITDA 多為股票薪酬加回口徑，分部 EBITDA 同口徑
A89: EBITDA：Productivity and server licensing（營收 ×（分配利益率＋折舊率＋股票薪酬率）） | B89: US$B | F89: =Seg!F15*(al_lic+Val!F87+sbc_r) -> 33.42851 | G89: =Seg!G15*(al_lic+Val!G87+sbc_r) -> 34.716183 | H89: =Seg!H15*(al_lic+Val!H87+sbc_r) -> 35.922365 | I89: =Seg!I15*(al_lic+Val!I87+sbc_r) -> 37.029833 | J89: =Seg!J15*(al_lic+Val!J87+sbc_r) -> 38.010333 | K89: =Seg!K15*(al_lic+Val!K87+sbc_r) -> 38.830347
A90: EBITDA：Industry solutions（營收 ×（分配利益率＋折舊率＋股票薪酬率）） | B90: US$B | F90: =Seg!F17*(al_ind+Val!F87+sbc_r) -> 9.0671931 | G90: =Seg!G17*(al_ind+Val!G87+sbc_r) -> 9.8348554 | H90: =Seg!H17*(al_ind+Val!H87+sbc_r) -> 10.649854 | I90: =Seg!I17*(al_ind+Val!I87+sbc_r) -> 11.510352 | J90: =Seg!J17*(al_ind+Val!J87+sbc_r) -> 12.405503 | K90: =Seg!K17*(al_ind+Val!K87+sbc_r) -> 13.317331
A91: EBITDA：Frontier and support services（營收 ×（分配利益率＋折舊率＋股票薪酬率）） | B91: US$B | F91: =Seg!F19*(al_fro+Val!F87+sbc_r) -> 3.568879 | G91: =Seg!G19*(al_fro+Val!G87+sbc_r) -> 3.776003 | H91: =Seg!H19*(al_fro+Val!H87+sbc_r) -> 4.0132297 | I91: =Seg!I19*(al_fro+Val!I87+sbc_r) -> 4.2836844 | J91: =Seg!J19*(al_fro+Val!J87+sbc_r) -> 4.5880318 | K91: =Seg!K19*(al_fro+Val!K87+sbc_r) -> 4.9252607
A92: EBITDA：Search and advertising（營收 ×（分配利益率＋折舊率＋股票薪酬率）） | B92: US$B | F92: =Seg!F22*(al_srch+Val!F87+sbc_r) -> 11.198114 | G92: =Seg!G22*(al_srch+Val!G87+sbc_r) -> 12.260793 | H92: =Seg!H22*(al_srch+Val!H87+sbc_r) -> 13.371279 | I92: =Seg!I22*(al_srch+Val!I87+sbc_r) -> 14.520571 | J92: =Seg!J22*(al_srch+Val!J87+sbc_r) -> 15.687336 | K92: =Seg!K22*(al_srch+Val!K87+sbc_r) -> 16.840385
A93: EBITDA：AI 基礎設施模組（Azure AI EBITDA − 自用 AI 營運成本＋影子效益） | B93: US$B | F93: =Thesis!F29-Thesis!F30+Thesis!F44 -> 55.674305 | G93: =Thesis!G29-Thesis!G30+Thesis!G44 -> 100.25331 | H93: =Thesis!H29-Thesis!H30+Thesis!H44 -> 152.31255 | I93: =Thesis!I29-Thesis!I30+Thesis!I44 -> 194.04199 | J93: =Thesis!J29-Thesis!J30+Thesis!J44 -> 223.46315 | K93: =Thesis!K29-Thesis!K30+Thesis!K44 -> 241.31225
A94: EBITDA：Agents and Infra 合計（評價口徑營業利益＋AI 折舊＋非 AI 折舊與股票薪酬分攤） | B94: US$B | F94: =PL!F32+Thesis!F44+Thesis!F40+Val!F87*(Seg!F21-Thesis!F23)+sbc_r*Seg!F21 -> 247.76931 | G94: =PL!G32+Thesis!G44+Thesis!G40+Val!G87*(Seg!G21-Thesis!G23)+sbc_r*Seg!G21 -> 321.62587 | H94: =PL!H32+Thesis!H44+Thesis!H40+Val!H87*(Seg!H21-Thesis!H23)+sbc_r*Seg!H21 -> 403.66876 | I94: =PL!I32+Thesis!I44+Thesis!I40+Val!I87*(Seg!I21-Thesis!I23)+sbc_r*Seg!I21 -> 473.31182 | J94: =PL!J32+Thesis!J44+Thesis!J40+Val!J87*(Seg!J21-Thesis!J23)+sbc_r*Seg!J21 -> 527.68317 | K94: =PL!K32+Thesis!K44+Thesis!K40+Val!K87*(Seg!K21-Thesis!K23)+sbc_r*Seg!K21 -> 568.06051
A95: EBITDA：Azure 其他（分部殘差；不含 AI 模組） | B95: US$B | F95: =Val!F94-Val!F88-Val!F89-Val!F90-Val!F91-Val!F93 -> 61.086376 | G95: =Val!G94-Val!G88-Val!G89-Val!G90-Val!G91-Val!G93 -> 73.621902 | H95: =Val!H94-Val!H88-Val!H89-Val!H90-Val!H91-Val!H93 -> 86.70206 | I95: =Val!I94-Val!I88-Val!I89-Val!I90-Val!I91-Val!I93 -> 99.249543 | J95: =Val!J94-Val!J88-Val!J89-Val!J90-Val!J91-Val!J93 -> 110.59658 | K95: =Val!K94-Val!K88-Val!K89-Val!K90-Val!K91-Val!K93 -> 120.01556
A96: EBITDA：Devices and Consumer 合計 | B96: US$B | F96: =PL!F34+Val!F87*Seg!F28+sbc_r*Seg!F28 -> 26.171793 | G96: =PL!G34+Val!G87*Seg!G28+sbc_r*Seg!G28 -> 26.75812 | H96: =PL!H34+Val!H87*Seg!H28+sbc_r*Seg!H28 -> 27.620117 | I96: =PL!I34+Val!I87*Seg!I28+sbc_r*Seg!I28 -> 28.729631 | J96: =PL!J34+Val!J87*Seg!J28+sbc_r*Seg!J28 -> 30.0475 | K96: =PL!K34+Val!K87*Seg!K28+sbc_r*Seg!K28 -> 31.529233
A97: EBITDA：XBOX（分部殘差按營收分） | B97: US$B | F97: =(Val!F96-Val!F92)*Seg!F24/(Seg!F24+Seg!F26) -> 8.2084248 | G97: =(Val!G96-Val!G92)*Seg!G24/(Seg!G24+Seg!G26) -> 7.8055938 | H97: =(Val!H96-Val!H92)*Seg!H24/(Seg!H24+Seg!H26) -> 7.5681704 | I97: =(Val!I96-Val!I92)*Seg!I24/(Seg!I24+Seg!I26) -> 7.4787561 | J97: =(Val!J96-Val!J92)*Seg!J24/(Seg!J24+Seg!J26) -> 7.5241096 | K97: =(Val!K96-Val!K92)*Seg!K24/(Seg!K24+Seg!K26) -> 7.6963262
A98: EBITDA：Windows OEM and devices | B98: US$B | F98: =Val!F96-Val!F92-Val!F97 -> 6.7652539 | G98: =Val!G96-Val!G92-Val!G97 -> 6.6917334 | H98: =Val!H96-Val!H92-Val!H97 -> 6.6806684 | I98: =Val!I96-Val!I92-Val!I97 -> 6.7303032 | J98: =Val!J96-Val!J92-Val!J97 -> 6.8360539 | K98: =Val!K96-Val!K92-Val!K97 -> 6.9925219
A99: AI 模組自由現金流＝EBITDA − 稅 ×（EBITDA − AI 折舊）− AI 資本支出（含汰換） | B99: US$B | F99: =Val!F93-tax_f*(Val!F93-Thesis!F40)-Thesis!F37 -> -116.9856 | G99: =Val!G93-tax_f*(Val!G93-Thesis!G40)-Thesis!G37 -> -91.275184 | H99: =Val!H93-tax_f*(Val!H93-Thesis!H40)-Thesis!H37 -> -48.686783 | I99: =Val!I93-tax_f*(Val!I93-Thesis!I40)-Thesis!I37 -> 13.919331 | J99: =Val!J93-tax_f*(Val!J93-Thesis!J40)-Thesis!J37 -> 80.089784 | K99: =Val!K93-tax_f*(Val!K93-Thesis!K40)-Thesis!K37 -> 106.01489
A100: AI 模組自由現金流現值 | B100: US$B | F100: =Val!F99*Val!F73 -> -111.39291 | G100: =Val!G99*Val!G73 -> -78.800356 | H100: =Val!H99*Val!H73 -> -38.109816 | I100: =Val!I99*Val!I73 -> 9.8785782 | J100: =Val!J99*Val!J73 -> 51.535147 | K100: =Val!K99*Val!K73 -> 61.850552
A101: AI 模組永續價值現值（NOPAT ×（1 − g ÷ 新投資報酬）÷（WACC − g）） | B101: US$B | C101: =(Val!K93-Thesis!K40)*(1-tax_f)*(1+g_tv)*(1-g_tv/(wacc+ronic_prem))/(wacc-g_tv)/(1+wacc)^(Val!K72+mid_yr) -> 452.21503
A102: 分部加總：AI 基礎設施模組（模組 DCF，推到目標價時點） | B102: US$B | C102: =(SUM(Val!F100:K100)+Val!$C$101)*(1+wacc)^t_roll -> 395.34116 | L102: F3：AI 腿以自身 DCF 計入資本密集度
