Workbook

Sheet README
A1: NAND 市場層 v0.1（AI 半導體 Project；樣板 markets/memory） 2026-10-25
A2: 命題：NAND 營收由 AI 推論帶動的企業級 SSD 位元需求與合約價循環決定；2026–27 供給受限、價格在高檔，2028 起各情境依加速器顆數係數與價格路徑分歧。
A4: 驅動因子 → 推導量
A5: Mkt A 區｜加速器顆數（markets/memory UNITS × 同字母 SCEN_UNITS）× 每顆企業級 SSD 容量 → AI 企業級 SSD 需求；非 AI 企業級 SSD、手機、PC、消費性以 2025 基期 × 年增 → 位元需求合計
A6: Mkt A 區｜全產業位元供給（2025 基期 ×（1＋美光指引年增），三情境相同）；出貨＝MIN(需求, 供給)
A7: Mkt B 區｜季價指數（markets/memory NAND 路徑，同字母；2030 收斂法）× 季度位元 → 以 2Q26 實績為錨的季度市場營收；份額（2026Q3 由 Kioxia、SanDisk 公司指引推得）→ 各廠營收與位元
A8: Ann｜年度摘要：需求、供給、出貨、平均售價、營收、各廠份額；Kioxia＋SanDisk 合資群份額＝兩家相加（下游公司模型讀同一組列）
A10: 情境：A＝順利、B＝平平、C＝不如預期；價格讀 markets/memory NAND_S 同字母，顆數讀 SCEN_UNITS 同字母（2028–29；CY2030 沿用 2029），不自訂行業路徑。CY2030 價格為收斂法（十年平均年變動 p10，三情境相同）。
A11: 單位：$B、EB、$/GB、百萬顆。2026Q2 以前為 TrendForce 實績；季度位元為年度依年增平滑（近似）。
A12: 已知限制：全產業 EB 基期與各應用占比為 Assumed（只影響 AI 與非 AI 需求的相對大小與 EB 絕對值）；各廠晶圓產能未找到（Sup 頁）；各廠平均售價假設等於市場平均。
A14: v0.3（2026-10-31）：季價指數的口徑改為「實現平均售價」。Siliconomics v0.10：2026Q3 +25%（Kioxia、SK 海力士實績 mid-20%；原合約價 +15%）、2026Q4 +8.1%（兩季累計 1.15 × 1.175 不變；原 +17.5%）；2027 起價格水準不變。SanDisk、Kioxia 的 2026Q3 份額因此由 11.6%／15.8% 降為 10.7%／14.5%。另：兩家 2026Q4 起的份額改為「2026Q3 實績份額與 2026Q4 公司指引份額的平均」（新增輸入 sd_g4、kx_g4、kx_fxg4；三星、SK 海力士、美光本來就用 1H26 兩季平均），以平滑 Kioxia 公司揭露的出貨季別移動：Kioxia 13.9%、SanDisk 10.65%；其他廠（餘額）13.4%。2026Q4 對公司指引：SanDisk +0.4%（原 +9.6%）、Kioxia（美元、TrendForce 口徑）+4.8%（原 +19.2%；日圓口徑另含匯率假設 160 對 157 的 +1.9%；見 Recon）。

Sheet In
A1: In — NAND 市場層輸入（藍字；基準 E 欄，低 D、高 F）。金額：十億美元（$B）；位元：EB（10^18 位元組）；顆數：百萬顆。每個輸入附標記與來源；找不到者寫「未找到」
A2: 標記：Verified／Interested-party（寫明是誰）／Analogy／Assumed（給低／高區間）／Derived（寫明換算）。價格路徑、加速器顆數、情境顆數係數取自 markets/memory/market.py（單一來源，本頁只抄錄並標示來源；改 markets/memory 後重建本檔）。SemiAnalysis 未使用
A3: 鍵 | B3: 項目 | C3: 單位 | D3: 低 | E3: 基準 | F3: 高 | G3: 標記 | H3: 來源1 | I3: 來源2／說明
A4: N1. NAND 合約價季增（共用市場層 markets/memory；情境 A／B／C 同字母）
A5: nq_1 | B5: NAND 合約價季增 2025Q2 | C5: % | E5: 0 | G5: Interested-party | H5: markets/memory/market.py NAND_COMMON[0] | I5: TrendForce：1Q26 +85~90%、2Q26 +70~75%、3Q26 +10~15%（MS 實際約 +20%）、4Q26 +15~20%；2025Q2–Q4 為 Assumed
A6: nq_2 | B6: NAND 合約價季增 2025Q3 | C6: % | E6: 0.05 | G6: Interested-party | H6: markets/memory/market.py NAND_COMMON[1] | I6: 同上
A7: nq_3 | B7: NAND 合約價季增 2025Q4 | C7: % | E7: 0.3 | G7: Interested-party | H7: markets/memory/market.py NAND_COMMON[2] | I7: 同上
A8: nq_4 | B8: NAND 合約價季增 2026Q1 | C8: % | E8: 0.875 | G8: Interested-party | H8: markets/memory/market.py NAND_COMMON[3] | I8: 同上
A9: nq_5 | B9: NAND 合約價季增 2026Q2 | C9: % | E9: 0.725 | G9: Interested-party | H9: markets/memory/market.py NAND_COMMON[4] | I9: 同上
A10: nq_6 | B10: NAND 合約價季增 2026Q3 | C10: % | E10: 0.25 | G10: Interested-party | H10: markets/memory/market.py NAND_COMMON[5] | I10: 同上
A11: nq_7 | B11: NAND 合約價季增 2026Q4 | C11: % | E11: 0.081 | G11: Interested-party | H11: markets/memory/market.py NAND_COMMON[6] | I11: 同上
A12: nqA_8 | B12: NAND 合約價季增 2027Q1（A） | C12: % | E12: 0.03 | G12: Interested-party | H12: markets/memory/market.py NAND_S['A'][0] | I12: 本庫情境路徑，依據：TrendForce：2027 下半年供需平衡、價格面臨下修壓力（2026-10-28 來源複核：來源無逐季數字，逐季值為本庫拆分）
A13: nqA_9 | B13: NAND 合約價季增 2027Q2（A） | C13: % | E13: 0 | G13: Interested-party | H13: markets/memory/market.py NAND_S['A'][1] | I13: 同上
A14: nqA_10 | B14: NAND 合約價季增 2027Q3（A） | C14: % | E14: -0.05 | G14: Interested-party | H14: markets/memory/market.py NAND_S['A'][2] | I14: 同上
A15: nqA_11 | B15: NAND 合約價季增 2027Q4（A） | C15: % | E15: -0.07 | G15: Interested-party | H15: markets/memory/market.py NAND_S['A'][3] | I15: 同上
A16: nqA_12 | B16: NAND 合約價季增 2028Q1（A） | C16: % | E16: -0.05 | G16: Interested-party | H16: markets/memory/market.py NAND_S['A'][4] | I16: 同上
... A47: nqC_19 | B47: NAND 合約價季增 2029Q4（C） | C47: % | E47: 0.1 | G47: Assumed | H47: markets/memory/market.py NAND_S['C'][11] | I47: 同上
A48: p10 | B48: CY2030 NAND 平均售價年變動（收斂法：十年平均；三情境相同） | C48: % | D48: -0.2 | E48: -0.12 | F48: -0.05 | G48: Analogy | H48: 上游 markets/memory 季價只到 2029Q4。收斂法：CY2030 起價格回到長期趨勢＝過去十年 NAND 每 GB 售價的年均變動；可驗證的 2016–2025 年 $/GB 序列未找到，取每位元成本年降 15–20% 減去循環中段的溢價（Analogy：製程每代密度提升、價格長期跟隨成本） | I48: 2030 各季季增＝(1＋p10)^(1/4)−1，自 2029Q4 起算；低 −20%、高 −5%（Sens 列）
A49: N2. 加速器顆數（markets/memory UNITS 合計；2028–29 情境係數 SCEN_UNITS，同字母）
A50: u_26 | B50: 加速器顆數合計 2026（情境 A 基準） | C50: 百萬顆 | E50: 15.2 | G50: Derived | H50: markets/memory/market.py UNITS 各列 2026 合計（NVIDIA、AMD、TPU、Trainium、其他 ASIC） | I50: 與 HBM 需求、台積電 CoWoS、Advantest 同一套顆數
A51: u_27 | B51: 加速器顆數合計 2027（情境 A 基準） | C51: 百萬顆 | E51: 23.7 | G51: Derived | H51: markets/memory/market.py UNITS 各列 2027 合計（NVIDIA、AMD、TPU、Trainium、其他 ASIC） | I51: 同上
A52: u_28 | B52: 加速器顆數合計 2028（情境 A 基準） | C52: 百萬顆 | E52: 26.5 | G52: Derived | H52: markets/memory/market.py UNITS 各列 2028 合計（NVIDIA、AMD、TPU、Trainium、其他 ASIC） | I52: 同上
A53: um28_A | B53: 情境 A：2028 顆數 ÷ 基準 | C53: x | E53: 1 | G53: Derived | H53: markets/memory/market.py SCEN_UNITS['A'][0] | I53: A＝1.0；B、C 為 Assumed（markets/memory）；CY2030 沿用 2029 係數
A54: um29_A | B54: 情境 A：2029 顆數 ÷ 基準 | C54: x | E54: 1 | G54: Derived | H54: markets/memory/market.py SCEN_UNITS['A'][1] | I54: 同上
A55: um28_B | B55: 情境 B：2028 顆數 ÷ 基準 | C55: x | E55: 0.8 | G55: Derived | H55: markets/memory/market.py SCEN_UNITS['B'][0] | I55: 同上
A56: um29_B | B56: 情境 B：2029 顆數 ÷ 基準 | C56: x | E56: 0.85 | G56: Derived | H56: markets/memory/market.py SCEN_UNITS['B'][1] | I56: 同上
A57: um28_C | B57: 情境 C：2028 顆數 ÷ 基準 | C57: x | E57: 0.6 | G57: Derived | H57: markets/memory/market.py SCEN_UNITS['C'][0] | I57: 同上
A58: um29_C | B58: 情境 C：2029 顆數 ÷ 基準 | C58: x | E58: 0.6 | G58: Derived | H58: markets/memory/market.py SCEN_UNITS['C'][1] | I58: 同上
A59: g_u29 | B59: 2029 加速器顆數年增（情境 A 基準；B、C 再乘 um29） | C59: % | D59: 0 | E59: 0.13773585 | F59: 0.25 | G59: Derived | H59: Siliconomics SIF_UnitsGrowth29：平台別 2029 成長率（M5 節）加權，與台積電、網通模型同一路徑（v0.2 起；原 Assumed 10%）；低／高沿用原區間供敏感度 | I59: 三情境同一基準，情境差異只來自 um29（不自訂行業路徑）
A60: g_u30 | B60: 2030 加速器顆數年增（情境 A 基準；B、C 再乘 um29） | C60: % | D60: -0.05 | E60: 0.05 | F60: 0.15 | G60: Assumed | H60: 上游只到 2029；收斂到低個位數成長 | I60: 同上
A61: tb_26 | B61: 每顆加速器帶動的企業級 SSD 容量 2026 | C61: TB／顆 | D61: 24 | E61: 30 | F61: 36 | G61: Assumed | H61: AI 推論的 KV 快取卸載、RAG 向量庫、檢查點與資料湖（伺服器內建＋外接儲存）。2026 值使 2026 企業級 SSD 約占位元需求四成（TrendForce 2026-07：伺服器約 40%；Counterpoint 2Q26：企業級 SSD 占出貨位元 48%） | I61: 低／高 ±20%（Sens 列）；三情境相同（情境差異來自顆數）
A62: tb_27 | B62: 每顆加速器帶動的企業級 SSD 容量 2027 | C62: TB／顆 | D62: 27 | E62: 34 | F62: 41 | G62: Assumed | H62: 每年約 +13–18%：單顆加速器記憶體與脈絡長度增加（Assumed） | I62: 低／高 ±20%（Sens 列）；三情境相同（情境差異來自顆數）
A63: tb_28 | B63: 每顆加速器帶動的企業級 SSD 容量 2028 | C63: TB／顆 | D63: 32 | E63: 40 | F63: 48 | G63: Assumed | H63: 每年約 +13–18%：單顆加速器記憶體與脈絡長度增加（Assumed） | I63: 低／高 ±20%（Sens 列）；三情境相同（情境差異來自顆數）
A64: tb_29 | B64: 每顆加速器帶動的企業級 SSD 容量 2029 | C64: TB／顆 | D64: 37 | E64: 46 | F64: 55 | G64: Assumed | H64: 每年約 +13–18%：單顆加速器記憶體與脈絡長度增加（Assumed） | I64: 低／高 ±20%（Sens 列）；三情境相同（情境差異來自顆數）
A65: tb_30 | B65: 每顆加速器帶動的企業級 SSD 容量 2030 | C65: TB／顆 | D65: 42 | E65: 52 | F65: 62 | G65: Assumed | H65: 每年約 +13–18%：單顆加速器記憶體與脈絡長度增加（Assumed） | I65: 低／高 ±20%（Sens 列）；三情境相同（情境差異來自顆數）
A66: N3. 位元需求（2025 基期與各應用年增；非 AI 應用三情境相同）
A67: bits25 | B67: 2025 NAND 位元出貨（全產業） | C67: EB | D67: 850 | E67: 1000 | F67: 1150 | G67: Assumed | H67: 全產業 EB 的公開數字未找到（TrendForce、Yole 付費）；以 2025 營收約 $72B ÷ 合約均價約 $0.07／GB 粗估約 1 ZB | I67: 只影響 EB 與 $/GB 的絕對值，以及 AI 需求（顆數 × 容量，絕對量）與其他應用（比例 × 基期）的相對大小；營收以 2Q26 實績為錨，不受基期水準影響
A68: g25 | B68: 2025 位元出貨年增（推 2024 位元） | C68: % | D68: 0.08 | E68: 0.12 | F68: 0.16 | G68: Assumed | H68: 2025 上半庫存去化、下半價漲；全年位元成長公開數字未找到 | I68: 只用於 CY2024 欄
A69: sh_essd25 | B69: 2025 企業級 SSD 占位元需求 | C69: % | D69: 0.26 | E69: 0.3 | F69: 0.34 | G69: Interested-party | H69: Counterpoint 2Q25 企業級 SSD 占 NAND 出貨位元 26%、2Q26 48%（capitalandcompute 2026-08 轉載 Counterpoint Q2 2026 Memory & Storage Tracker） | I69: 全年平均取 30%（下半年 AI 伺服器拉貨，Derived／Assumed）
A70: ai25 | B70: 2025 企業級 SSD 中 AI 伺服器的比例 | C70: % | D70: 0.45 | E70: 0.55 | F70: 0.65 | G70: Assumed | H70: 未找到；AI 伺服器（加速器）帶動的企業級 SSD 約過半 | I70: 2026 起 AI 部分改由顆數 × 每顆容量推導
A71: sh_mob25 | B71: 2025 手機占位元需求 | C71: % | D71: 0.28 | E71: 0.32 | F71: 0.36 | G71: Assumed | H71: TrendForce 2026-07：手機與筆電合計約 40%（2026，企業級 SSD 擴大後）；2025 手機約三成
A72: sh_pc25 | B72: 2025 PC（client SSD）占位元需求 | C72: % | D72: 0.2 | E72: 0.23 | F72: 0.26 | G72: Assumed | H72: 同上 | I72: 消費性（記憶卡、USB、遊戲機、車用等）＝1 − 其餘
A73: g_nai | B73: 非 AI 企業級 SSD 位元年增（一般伺服器、儲存陣列取代 HDD） | C73: % | D73: 0.05 | E73: 0.1 | F73: 0.15 | G73: Assumed | H73: QLC 取代近線 HDD（TrendForce 2025-09：HDD 交期逾 52 週） | I73: 三情境相同
A74: g_mob_26 | B74: 手機位元年增 2026 | C74: % | D74: -0.1 | E74: -0.05 | F74: 0 | G74: Assumed | H74: TrendForce 2026-08-18：手機、PC 因 BOM 成本上升需求轉弱；2028 起每機容量回升 | I74: 三情境相同（非 AI 應用不隨加速器情境）
A75: g_mob_27 | B75: 手機位元年增 2027 | C75: % | D75: 0 | E75: 0.03 | F75: 0.06 | G75: Assumed | H75: 同上 | I75: 三情境相同（非 AI 應用不隨加速器情境）
A76: g_mob_28 | B76: 手機位元年增 2028（2029–30 同此值） | C76: % | D76: 0.05 | E76: 0.08 | F76: 0.11 | G76: Assumed | H76: 同上 | I76: 三情境相同（非 AI 應用不隨加速器情境）
A77: g_pc_26 | B77: PC位元年增 2026 | C77: % | D77: -0.1 | E77: -0.05 | F77: 0 | G77: Assumed | H77: 同上 | I77: 三情境相同（非 AI 應用不隨加速器情境）
A78: g_pc_27 | B78: PC位元年增 2027 | C78: % | D78: -0.03 | E78: 0 | F78: 0.03 | G78: Assumed | H78: 同上 | I78: 三情境相同（非 AI 應用不隨加速器情境）
A79: g_pc_28 | B79: PC位元年增 2028（2029–30 同此值） | C79: % | D79: 0.03 | E79: 0.06 | F79: 0.09 | G79: Assumed | H79: 同上 | I79: 三情境相同（非 AI 應用不隨加速器情境）
A80: g_con_26 | B80: 消費性與其他位元年增 2026 | C80: % | D80: -0.15 | E80: -0.1 | F80: -0.05 | G80: Assumed | H80: 微軟、任天堂 2026 年遊戲機漲價（儲存成本上升 2.5 倍） | I80: 三情境相同（非 AI 應用不隨加速器情境）
A81: g_con_27 | B81: 消費性與其他位元年增 2027 | C81: % | D81: -0.03 | E81: 0 | F81: 0.03 | G81: Assumed | H81: 同上 | I81: 三情境相同（非 AI 應用不隨加速器情境）
A82: g_con_28 | B82: 消費性與其他位元年增 2028（2029–30 同此值） | C82: % | D82: 0.02 | E82: 0.05 | F82: 0.08 | G82: Assumed | H82: 同上 | I82: 三情境相同（非 AI 應用不隨加速器情境）
A83: N4. 位元供給（全產業；三情境相同：產能與製程轉換 2027 前已訂定）
A84: gs_26 | B84: 位元供給年增 2026 | C84: % | D84: 0.18 | E84: 0.21 | F84: 0.24 | G84: Interested-party | H84: 美光 FQ4 FY26（2026-09-30）：產業 NAND 位元出貨 CY2026 低 20% 段、CY2027 與 CY2028 約中 20% 段，供給受限至 2028（Guru3D 2026-10-01 轉載） | I84: 三星 2026 晶圓投片約 −4.5%、SK 海力士 −10%（投資轉向 HBM；borecraft 2026-05-26 轉載 DigiTimes、Blocks & Files），位元成長來自層數
A85: gs_27 | B85: 位元供給年增 2027 | C85: % | D85: 0.2 | E85: 0.25 | F85: 0.28 | G85: Interested-party | H85: 同上 | I85: 同上
A86: gs_28 | B86: 位元供給年增 2028 | C86: % | D86: 0.2 | E86: 0.25 | F86: 0.28 | G86: Interested-party | H86: 同上 | I86: 同上
A87: gs_29 | B87: 位元供給年增 2029 | C87: % | D87: 0.15 | E87: 0.22 | F87: 0.28 | G87: Assumed | H87: 上游無 2029；Kioxia 北上 K2（BiCS10，332 層）、三星 V10（430 層以上）2027 起量產 | I87: 同上
A88: gs_30 | B88: 位元供給年增 2030 | C88: % | D88: 0.12 | E88: 0.2 | F88: 0.26 | G88: Assumed | H88: 同上 | I88: 同上
A89: N5. 季度實績（TrendForce 前五大 NAND 營收；$B）與前五大占全市場比例
A90: rv_ss_0 | B90: 三星 NAND 營收 2025Q1 | C90: $B | E90: 4.2 | G90: Derived | H90: 2Q25 營收 ÷（1＋2Q25 季增）（TrendForce 2025-08-28：三星 +23.8%、SK +52.5%、Kioxia +11.4%、美光 +3.7%、SanDisk +12.2%）
A91: rv_ss_1 | B91: 三星 NAND 營收 2025Q2 | C91: $B | E91: 5.2 | G91: Interested-party | H91: TrendForce 2025-08-28（2Q25 前五大 $14.67B）https://www.trendforce.com/presscenter/news/20250828-12688.html
A92: rv_ss_2 | B92: 三星 NAND 營收 2025Q3 | C92: $B | E92: 6 | G92: Interested-party | H92: TrendForce 2025-12-03（3Q25 前五大約 $17.1B）https://www.trendforce.com/presscenter/news/20251203-12813.html
A93: rv_ss_3 | B93: 三星 NAND 營收 2025Q4 | C93: $B | E93: 6.6 | G93: Interested-party | H93: TrendForce（4Q25 前五大 $21.17B，+23.8%；I-Connect007 轉載）
A94: rv_ss_4 | B94: 三星 NAND 營收 2026Q1 | C94: $B | E94: 13.51 | G94: Derived | H94: 2Q26 營收 ÷（1＋2Q26 季增）（TrendForce 2026-08-18：三星 +70.7%、SK +89.5%、美光 +99.2%、Kioxia +79.9%、SanDisk +50.7%）
A95: rv_ss_5 | B95: 三星 NAND 營收 2026Q2 | C95: $B | E95: 23.06 | G95: Interested-party | H95: TrendForce 2026-08-18（2Q26 NAND 前五大營收排名）https://www.trendforce.com/presscenter/news/20260818-13186.html
A96: rv_sk_0 | B96: SK 海力士＋Solidigm NAND 營收 2025Q1 | C96: $B | E96: 2.19 | G96: Derived | H96: 2Q25 營收 ÷（1＋2Q25 季增）（TrendForce 2025-08-28：三星 +23.8%、SK +52.5%、Kioxia +11.4%、美光 +3.7%、SanDisk +12.2%）
A97: rv_sk_1 | B97: SK 海力士＋Solidigm NAND 營收 2025Q2 | C97: $B | E97: 3.34 | G97: Interested-party | H97: TrendForce 2025-08-28（2Q25 前五大 $14.67B）https://www.trendforce.com/presscenter/news/20250828-12688.html
A98: rv_sk_2 | B98: SK 海力士＋Solidigm NAND 營收 2025Q3 | C98: $B | E98: 3.53 | G98: Interested-party | H98: TrendForce 2025-12-03（3Q25 前五大約 $17.1B）https://www.trendforce.com/presscenter/news/20251203-12813.html
A99: rv_sk_3 | B99: SK 海力士＋Solidigm NAND 營收 2025Q4 | C99: $B | E99: 5.21 | G99: Interested-party | H99: TrendForce（4Q25 前五大 $21.17B，+23.8%；I-Connect007 轉載）
A100: rv_sk_4 | B100: SK 海力士＋Solidigm NAND 營收 2026Q1 | C100: $B | E100: 7.53 | G100: Derived | H100: 2Q26 營收 ÷（1＋2Q26 季增）（TrendForce 2026-08-18：三星 +70.7%、SK +89.5%、美光 +99.2%、Kioxia +79.9%、SanDisk +50.7%）
A101: rv_sk_5 | B101: SK 海力士＋Solidigm NAND 營收 2026Q2 | C101: $B | E101: 14.27 | G101: Interested-party | H101: TrendForce 2026-08-18（2Q26 NAND 前五大營收排名）https://www.trendforce.com/presscenter/news/20260818-13186.html
... A118: rv_sd_4 | B118: SanDisk NAND 營收 2026Q1 | C118: $B | E118: 5.95 | G118: Derived | H118: 2Q26 營收 ÷（1＋2Q26 季增）（TrendForce 2026-08-18：三星 +70.7%、SK +89.5%、美光 +99.2%、Kioxia +79.9%、SanDisk +50.7%）
A119: rv_sd_5 | B119: SanDisk NAND 營收 2026Q2 | C119: $B | E119: 8.97 | G119: Interested-party | H119: TrendForce 2026-08-18（2Q26 NAND 前五大營收排名）https://www.trendforce.com/presscenter/news/20260818-13186.html | I119: SanDisk 公司營收：FQ1 FY26 2.308、FQ2 3.025、FQ3 5.950、FQ4 8.965（8-K），與 TrendForce 一致
A120: t5_0 | B120: 前五大占全市場營收 2025Q1 | C120: % | D120: 0.9 | E120: 0.93 | F120: 0.95 | G120: Assumed | H120: 未找到；取 2Q25 值附近 | I120: 其他＝長江存儲、英特爾殘餘、旺宏、華邦等
A121: t5_1 | B121: 前五大占全市場營收 2025Q2 | C121: % | E121: =(rv_ss_1+rv_sk_1+rv_mu_1+rv_kx_1+rv_sd_1)/(rv_ss_1/0.329) -> 0.92879231 | G121: Derived | H121: 全市場＝三星營收 ÷ 三星市占 32.9%（TrendForce 2025-08-28）；前五大 ÷ 全市場 | I121: 其他＝長江存儲、英特爾殘餘、旺宏、華邦等
A122: t5_2 | B122: 前五大占全市場營收 2025Q3 | C122: % | D122: 0.88 | E122: 0.91 | F122: 0.93 | G122: Assumed | H122: 未找到；2Q25 與 4Q25 之間 | I122: 其他＝長江存儲、英特爾殘餘、旺宏、華邦等
A123: t5_3 | B123: 前五大占全市場營收 2025Q4 | C123: % | E123: =(rv_ss_3+rv_sk_3+rv_mu_3+rv_kx_3+rv_sd_3)/(rv_ss_3/0.28) -> 0.89854545 | G123: Derived | H123: 三星市占 28%（TrendForce 4Q25） | I123: 其他＝長江存儲、英特爾殘餘、旺宏、華邦等
A124: t5_4 | B124: 前五大占全市場營收 2026Q1 | C124: % | D124: 0.86 | E124: 0.885 | F124: 0.9 | G124: Assumed | H124: 未找到；4Q25 與 2Q26 之間 | I124: 其他＝長江存儲、英特爾殘餘、旺宏、華邦等
A125: t5_5 | B125: 前五大占全市場營收 2026Q2 | C125: % | E125: =(rv_ss_5+rv_sk_5+rv_mu_5+rv_kx_5+rv_sd_5)/(rv_ss_5/0.293) -> 0.87506114 | G125: Derived | H125: 三星市占 29.3%、Kioxia 13.6%（TrendForce 2026-08-18；兩者推得的全市場一致） | I125: 其他＝長江存儲、英特爾殘餘、旺宏、華邦等
A126: rev24 | B126: 2024 NAND 市場營收 | C126: $B | E126: 67.4 | G126: Interested-party | H126: TrendForce（TelecomLead 轉載）：2024 NAND 營收 $67.4B（+77%） | I126: 第二來源：未找到；只用於 CY2024 欄
A127: N6. 各廠份額（2026Q3 起；Kioxia、SanDisk 由公司 2026Q3 指引推得，其餘沿用 1H26 實績，其他＝餘額）
A128: sd_g | B128: SanDisk FQ1 FY27（2026-07～09）營收實績 | C128: $B | E128: 11.031 | G128: Verified | H128: SanDisk FQ1 FY27 新聞稿與法說（2026-10-29；Benzinga／Motley Fool 逐字稿、Investing.com 簡報摘要）：$11.031B | I128: v0.3 前為公司指引 $10.3–10.8B
A129: sd_k | B129: SanDisk 公司營收 ÷ TrendForce 口徑（2Q26） | C129: x | E129: =8.965/rv_sd_5 -> 0.99944259 | G129: Derived | H129: FQ4 FY26 營收 8.965 ÷ TrendForce 2Q26 8.97
A130: kx_g | B130: Kioxia FY2026 第二季（2026-07～09）營收實績 | C130: ¥B | E130: 2480 | G130: Verified | H130: Kioxia FY2026 第二季財報（2026-10-30；404K Research 法說整理、FourWeekMBA 轉載）：營收 ¥2,480.0B、營業利益 ¥1,994.7B；第三季指引 ¥2,500.0B（假設 157 日圓） | I130: v0.3 前為公司指引 ¥2,390.0B
A131: kx_fxg | B131: Kioxia 第二季平均匯率 | C131: ¥／$ | E131: 161 | G131: Verified | H131: 同上：第二季 161 日圓（第一季 160）
A132: kx_k | B132: Kioxia 公司營收 ÷ TrendForce 口徑（2Q26） | C132: x | E132: =1767.1/160/rv_kx_5 -> 1.0302589 | G132: Derived | H132: 第一季營收 ¥1,767.1B ÷ 平均匯率 160 ÷ TrendForce 2Q26 10.72（公司含其他營收 ¥66.7B）
A133: sd_g4 | B133: SanDisk FQ2 FY27（2026-10～12）營收指引中點 | C133: $B | D133: 12.2 | E133: 12.4 | F133: 12.6 | G133: Interested-party | H133: SanDisk FQ1 FY27 法說（2026-10-29）：FQ2 FY27 營收 12.2–12.6（立場：公司） | I133: v0.3：與 2026Q3 實績平均，推 2026Q4 起份額（平滑公司出貨季別移動；三星、SK 海力士、美光同樣用兩季平均）
A134: kx_g4 | B134: Kioxia FY2026 第三季（2026-10～12）營收指引 | C134: ¥B | E134: 2500 | G134: Interested-party | H134: Kioxia 第二季財報（2026-10-30；Investing.com）：¥2,500B；位元持平（7–9 月提前出貨、部分長交期產品遞延到 1–3 月）、平均售價季增低個位數（產品組合轉差） | I134: 同上
A135: kx_fxg4 | B135: Kioxia 第三季指引的匯率假設 | C135: ¥／$ | E135: 157 | G135: Interested-party | H135: 同上：157 日圓
A136: dr_ss | B136: 三星 營收份額年變動（2027 起，三情境相同） | C136: pt／年 | D136: -1 | E136: -0.5 | F136: 0 | G136: Assumed | H136: 三星：2026 晶圓投片減少、投資轉向 HBM（Blocks & Files 2026-01-20 轉載）；2Q26 市占小降（TrendForce）
A137: dr_sk | B137: SK 海力士＋Solidigm 營收份額年變動（2027 起，三情境相同） | C137: pt／年 | D137: -0.5 | E137: 0 | F137: 0.5 | G137: Assumed | H137: SK 海力士＋Solidigm：投片 −10%，但 QLC 企業級 SSD 接單強（TrendForce 2026-08-18）
A138: dr_mu | B138: 美光 營收份額年變動（2027 起，三情境相同） | C138: pt／年 | D138: -0.3 | E138: 0.2 | F138: 0.6 | G138: Assumed | H138: 美光：2Q26 季增最高（+99.2%）；位元成長低於產業（美光 FQ4 FY26）
A139: dr_jv_A | B139: 情境 A：Kioxia＋SanDisk 合資群營收份額年變動（2027 起） | C139: pt／年 | D139: -0.3 | E139: 0 | F139: 0.3 | G139: Assumed | H139: A：北上 K2 與 BiCS10 如期量產（Kioxia FY26–28 年均資本支出 ¥470B，TrendForce 2026-06-03） | I139: Flash Ventures（四日市、北上）由 Kioxia 50.1%／SanDisk 49.9% 持有（SanDisk FQ4 FY26 簡報），兩家位元成長同步；方向：A 最有利、C 最不利；其他（長江存儲等）吸收差額
A140: dr_jv_B | B140: 情境 B：Kioxia＋SanDisk 合資群營收份額年變動（2027 起） | C140: pt／年 | D140: -0.6 | E140: -0.3 | F140: 0 | G140: Assumed | H140: B：長江存儲（2Q26 位元市占 14%，Counterpoint）持續擴產 | I140: 同上
A141: dr_jv_C | B141: 情境 C：Kioxia＋SanDisk 合資群營收份額年變動（2027 起） | C141: pt／年 | D141: -1 | E141: -0.6 | F141: -0.2 | G141: Assumed | H141: C：AI 需求轉弱時中國廠以價換量 | I141: 同上

Sheet Ann
A1: Ann — NAND 市場年度摘要（三情境；引用 Mkt 頁）。CY2024–2025 為實績（位元為 Assumed 基期）；CY2026 含 1H26 實績；CY2030 價格為收斂法（灰底）
A3: 情境／項目 | B3: 單位 | C3: CY2024 | D3: CY2025 | E3: CY2026 | F3: CY2027 | G3: CY2028 | H3: CY2029 | I3: CY2030 | J3: 說明
A4: 情境 A（順利）
A5: 加速器顆數 | B5: 百萬顆 | E5: =Mkt!E6 -> 15.2 | F5: =Mkt!F6 -> 23.7 | G5: =Mkt!G6 -> 26.5 | H5: =Mkt!H6 -> 30.15 | I5: =Mkt!I6 -> 31.6575
A6: 需求：AI 企業級 SSD | B6: EB | D6: =Mkt!D8 -> 165 | E6: =Mkt!E8 -> 456 | F6: =Mkt!F8 -> 805.8 | G6: =Mkt!G8 -> 1060 | H6: =Mkt!H8 -> 1386.9 | I6: =Mkt!I8 -> 1646.19
A7: 需求：非 AI 企業級 SSD | B7: EB | D7: =Mkt!D9 -> 135 | E7: =Mkt!E9 -> 148.5 | F7: =Mkt!F9 -> 163.35 | G7: =Mkt!G9 -> 179.685 | H7: =Mkt!H9 -> 197.6535 | I7: =Mkt!I9 -> 217.41885
A8: 需求：手機 | B8: EB | D8: =Mkt!D10 -> 320 | E8: =Mkt!E10 -> 304 | F8: =Mkt!F10 -> 313.12 | G8: =Mkt!G10 -> 338.1696 | H8: =Mkt!H10 -> 365.22317 | I8: =Mkt!I10 -> 394.44102
A9: 需求：PC | B9: EB | D9: =Mkt!D11 -> 230 | E9: =Mkt!E11 -> 218.5 | F9: =Mkt!F11 -> 218.5 | G9: =Mkt!G11 -> 231.61 | H9: =Mkt!H11 -> 245.5066 | I9: =Mkt!I11 -> 260.237
A10: 需求：消費性與其他 | B10: EB | D10: =Mkt!D12 -> 150 | E10: =Mkt!E12 -> 135 | F10: =Mkt!F12 -> 135 | G10: =Mkt!G12 -> 141.75 | H10: =Mkt!H12 -> 148.8375 | I10: =Mkt!I12 -> 156.27937
A11: 位元需求合計 | B11: EB | D11: =Mkt!D13 -> 1000 | E11: =Mkt!E13 -> 1262 | F11: =Mkt!F13 -> 1635.77 | G11: =Mkt!G13 -> 1951.2146 | H11: =Mkt!H13 -> 2344.1208 | I11: =Mkt!I13 -> 2674.5662
A12: 企業級 SSD 占需求 | B12: % | D12: =Mkt!D14 -> 0.3 | E12: =Mkt!E14 -> 0.47900158 | F12: =Mkt!F14 -> 0.59247327 | G12: =Mkt!G14 -> 0.63534016 | H12: =Mkt!H14 -> 0.67596923 | I12: =Mkt!I14 -> 0.69678919
A13: 位元供給 | B13: EB | D13: =Mkt!D15 -> 1000 | E13: =Mkt!E15 -> 1210 | F13: =Mkt!F15 -> 1512.5 | G13: =Mkt!G15 -> 1890.625 | H13: =Mkt!H15 -> 2306.5625 | I13: =Mkt!I15 -> 2767.875
A14: 需求 ÷ 供給 − 1 | B14: % | E14: =Mkt!E16 -> 0.042975207 | F14: =Mkt!F16 -> 0.081500826 | G14: =Mkt!G16 -> 0.032047392 | H14: =Mkt!H16 -> 0.016283221 | I14: =Mkt!I16 -> -0.033711334
A15: 位元出貨 | B15: EB | C15: =Mkt!C17 -> 892.85714 | D15: =Mkt!D17 -> 1000 | E15: =Mkt!E17 -> 1210 | F15: =Mkt!F17 -> 1512.5 | G15: =Mkt!G17 -> 1890.625 | H15: =Mkt!H17 -> 2306.5625 | I15: =Mkt!I17 -> 2674.5662
A16: 位元出貨年增 | B16: % | D16: =Mkt!D18 -> 0.12 | E16: =Mkt!E18 -> 0.21 | F16: =Mkt!F18 -> 0.25 | G16: =Mkt!G18 -> 0.25 | H16: =Mkt!H18 -> 0.22 | I16: =Mkt!I18 -> 0.1595464
A17: 平均售價 | B17: $/GB | C17: =Mkt!C21 -> 0.075488 | D17: =Mkt!D21 -> 0.071103592 | E17: =Mkt!E21 -> 0.28332293 | F17: =Mkt!F21 -> 0.3548659 | G17: =Mkt!G21 -> 0.28805826 | H17: =Mkt!H21 -> 0.2473227 | I17: =Mkt!I21 -> 0.21823704
A18: 平均售價年變動 | B18: % | D18: =Mkt!D22 -> -0.058080856 | E18: =Mkt!E22 -> 2.9846501 | F18: =Mkt!F22 -> 0.25251387 | G18: =Mkt!G22 -> -0.18826165 | H18: =Mkt!H22 -> -0.1414143 | I18: =Mkt!I22 -> -0.11760206
A19: NAND 市場營收 | B19: $B | C19: =Mkt!C19 -> 67.4 | D19: =Mkt!D19 -> 71.103592 | E19: =Mkt!E19 -> 342.82075 | F19: =Mkt!F19 -> 536.73468 | G19: =Mkt!G19 -> 544.61015 | H19: =Mkt!H19 -> 570.46528 | I19: =Mkt!I19 -> 583.68943 | J19: CY2026–28 三情境營收與位元成長見 README
A20: 市場營收年增 | B20: % | D20: =Mkt!D20 -> 0.054949442 | E20: =Mkt!E20 -> 3.8214266 | F20: =Mkt!F20 -> 0.56564233 | G20: =Mkt!G20 -> 0.014672931 | H20: =Mkt!H20 -> 0.04747456 | I20: =Mkt!I20 -> 0.023181352
A21: 份額：三星 | B21: % | D21: =Mkt!D23 -> 0.30940771 | E21: =Mkt!E23 -> 0.29814637 | F21: =Mkt!F23 -> 0.29314637 | G21: =Mkt!G23 -> 0.28814637 | H21: =Mkt!H23 -> 0.28314637 | I21: =Mkt!I23 -> 0.27814637
A22: 份額：SK 海力士＋Solidigm | B22: % | D22: =Mkt!D24 -> 0.20069309 | E22: =Mkt!E24 -> 0.17773013 | F22: =Mkt!F24 -> 0.17773013 | G22: =Mkt!G24 -> 0.17773013 | H22: =Mkt!H24 -> 0.17773013 | I22: =Mkt!I24 -> 0.17773013
A23: 份額：美光 | B23: % | D23: =Mkt!D25 -> 0.134733 | E23: =Mkt!E25 -> 0.1451191 | F23: =Mkt!F25 -> 0.1471191 | G23: =Mkt!G25 -> 0.1491191 | H23: =Mkt!H25 -> 0.1511191 | I23: =Mkt!I25 -> 0.1531191
A24: 份額：Kioxia | B24: % | D24: =Mkt!D26 -> 0.14359331 | E24: =Mkt!E26 -> 0.13953322 | F24: =Mkt!F26 -> 0.13851299 | G24: =Mkt!G26 -> 0.13851299 | H24: =Mkt!H26 -> 0.13851299 | I24: =Mkt!I26 -> 0.13851299
A25: 份額：SanDisk | B25: % | D25: =Mkt!D27 -> 0.1255914 | E25: =Mkt!E27 -> 0.11206254 | F25: =Mkt!F27 -> 0.10651367 | G25: =Mkt!G27 -> 0.10651367 | H25: =Mkt!H27 -> 0.10651367 | I25: =Mkt!I27 -> 0.10651367
A26: 份額：其他（長江存儲等） | B26: % | D26: =Mkt!D28 -> 0.085981484 | E26: =Mkt!E28 -> 0.12740864 | F26: =Mkt!F28 -> 0.13697774 | G26: =Mkt!G28 -> 0.13997774 | H26: =Mkt!H28 -> 0.14297774 | I26: =Mkt!I28 -> 0.14597774
A27: Kioxia＋SanDisk（合資群）份額 | B27: % | D27: =D24+D25 -> 0.26918471 | E27: =E24+E25 -> 0.25159576 | F27: =F24+F25 -> 0.24502666 | G27: =G24+g25 -> 0.25851299 | H27: =H24+H25 -> 0.24502666 | I27: =I24+I25 -> 0.24502666
A28: Kioxia 營收（年） | B28: $B | D28: =SUM(Mkt!C43:F43) -> 10.21 | E28: =SUM(Mkt!G43:J43) -> 47.834882 | F28: =SUM(Mkt!K43:N43) -> 74.344724 | G28: =SUM(Mkt!O43:R43) -> 75.435579 | H28: =SUM(Mkt!S43:V43) -> 79.01685 | I28: =SUM(Mkt!W43:Z43) -> 80.848567
A29: SanDisk 營收（年） | B29: $B | D29: =SUM(Mkt!C44:F44) -> 8.93 | E29: =SUM(Mkt!G44:J44) -> 38.417364 | F29: =SUM(Mkt!K44:N44) -> 57.169581 | G29: =SUM(Mkt!O44:R44) -> 58.008426 | H29: =SUM(Mkt!S44:V44) -> 60.76235 | I29: =SUM(Mkt!W44:Z44) -> 62.170904
A31: 情境 B（平平）
A32: 加速器顆數 | B32: 百萬顆 | E32: =Mkt!E54 -> 15.2 | F32: =Mkt!F54 -> 23.7 | G32: =Mkt!G54 -> 21.2 | H32: =Mkt!H54 -> 25.6275 | I32: =Mkt!I54 -> 26.908875
A33: 需求：AI 企業級 SSD | B33: EB | D33: =Mkt!D56 -> 165 | E33: =Mkt!E56 -> 456 | F33: =Mkt!F56 -> 805.8 | G33: =Mkt!G56 -> 848 | H33: =Mkt!H56 -> 1178.865 | I33: =Mkt!I56 -> 1399.2615
A34: 需求：非 AI 企業級 SSD | B34: EB | D34: =Mkt!D57 -> 135 | E34: =Mkt!E57 -> 148.5 | F34: =Mkt!F57 -> 163.35 | G34: =Mkt!G57 -> 179.685 | H34: =Mkt!H57 -> 197.6535 | I34: =Mkt!I57 -> 217.41885
A35: 需求：手機 | B35: EB | D35: =Mkt!D58 -> 320 | E35: =Mkt!E58 -> 304 | F35: =Mkt!F58 -> 313.12 | G35: =Mkt!G58 -> 338.1696 | H35: =Mkt!H58 -> 365.22317 | I35: =Mkt!I58 -> 394.44102
A36: 需求：PC | B36: EB | D36: =Mkt!D59 -> 230 | E36: =Mkt!E59 -> 218.5 | F36: =Mkt!F59 -> 218.5 | G36: =Mkt!G59 -> 231.61 | H36: =Mkt!H59 -> 245.5066 | I36: =Mkt!I59 -> 260.237
A37: 需求：消費性與其他 | B37: EB | D37: =Mkt!D60 -> 150 | E37: =Mkt!E60 -> 135 | F37: =Mkt!F60 -> 135 | G37: =Mkt!G60 -> 141.75 | H37: =Mkt!H60 -> 148.8375 | I37: =Mkt!I60 -> 156.27937
A38: 位元需求合計 | B38: EB | D38: =Mkt!D61 -> 1000 | E38: =Mkt!E61 -> 1262 | F38: =Mkt!F61 -> 1635.77 | G38: =Mkt!G61 -> 1739.2146 | H38: =Mkt!H61 -> 2136.0858 | I38: =Mkt!I61 -> 2427.6377
A39: 企業級 SSD 占需求 | B39: % | D39: =Mkt!D62 -> 0.3 | E39: =Mkt!E62 -> 0.47900158 | F39: =Mkt!F62 -> 0.59247327 | G39: =Mkt!G62 -> 0.59089028 | H39: =Mkt!H62 -> 0.64441162 | I39: =Mkt!I62 -> 0.66594794
A40: 位元供給 | B40: EB | D40: =Mkt!D63 -> 1000 | E40: =Mkt!E63 -> 1210 | F40: =Mkt!F63 -> 1512.5 | G40: =Mkt!G63 -> 1890.625 | H40: =Mkt!H63 -> 2306.5625 | I40: =Mkt!I63 -> 2767.875
A41: 需求 ÷ 供給 − 1 | B41: % | E41: =Mkt!E64 -> 0.042975207 | F41: =Mkt!F64 -> 0.081500826 | G41: =Mkt!G64 -> -0.08008484 | H41: =Mkt!H64 -> -0.073909435 | I41: =Mkt!I64 -> -0.12292364
A42: 位元出貨 | B42: EB | C42: =Mkt!C65 -> 892.85714 | D42: =Mkt!D65 -> 1000 | E42: =Mkt!E65 -> 1210 | F42: =Mkt!F65 -> 1512.5 | G42: =Mkt!G65 -> 1739.2146 | H42: =Mkt!H65 -> 2136.0858 | I42: =Mkt!I65 -> 2427.6377
A43: 位元出貨年增 | B43: % | D43: =Mkt!D66 -> 0.12 | E43: =Mkt!E66 -> 0.21 | F43: =Mkt!F66 -> 0.25 | G43: =Mkt!G66 -> 0.14989395 | H43: =Mkt!H66 -> 0.22818988 | I43: =Mkt!I66 -> 0.13648889
A44: 平均售價 | B44: $/GB | C44: =Mkt!C69 -> 0.075488 | D44: =Mkt!D69 -> 0.071103592 | E44: =Mkt!E69 -> 0.28332293 | F44: =Mkt!F69 -> 0.34517215 | G44: =Mkt!G69 -> 0.13931903 | H44: =Mkt!H69 -> 0.11738423 | I44: =Mkt!I69 -> 0.11341154
A45: 平均售價年變動 | B45: % | D45: =Mkt!D70 -> -0.058080856 | E45: =Mkt!E70 -> 2.9846501 | F45: =Mkt!F70 -> 0.21829938 | G45: =Mkt!G70 -> -0.59637813 | H45: =Mkt!H70 -> -0.15744298 | I45: =Mkt!I70 -> -0.033843479
A46: NAND 市場營收 | B46: $B | C46: =Mkt!C67 -> 67.4 | D46: =Mkt!D67 -> 71.103592 | E46: =Mkt!E67 -> 342.82075 | F46: =Mkt!F67 -> 522.07288 | G46: =Mkt!G67 -> 242.30569 | H46: =Mkt!H67 -> 250.74278 | I46: =Mkt!I67 -> 275.32213
A47: 市場營收年增 | B47: % | D47: =Mkt!D68 -> 0.054949442 | E47: =Mkt!E68 -> 3.8214266 | F47: =Mkt!F68 -> 0.52287423 | G47: =Mkt!G68 -> -0.53587766 | H47: =Mkt!H68 -> 0.034820008 | I47: =Mkt!I68 -> 0.098026152
A48: 份額：三星 | B48: % | D48: =Mkt!D71 -> 0.30940771 | E48: =Mkt!E71 -> 0.29814637 | F48: =Mkt!F71 -> 0.29314637 | G48: =Mkt!G71 -> 0.28814637 | H48: =Mkt!H71 -> 0.28314637 | I48: =Mkt!I71 -> 0.27814637
A49: 份額：SK 海力士＋Solidigm | B49: % | D49: =Mkt!D72 -> 0.20069309 | E49: =Mkt!E72 -> 0.17773013 | F49: =Mkt!F72 -> 0.17773013 | G49: =Mkt!G72 -> 0.17773013 | H49: =Mkt!H72 -> 0.17773013 | I49: =Mkt!I72 -> 0.17773013
A50: 份額：美光 | B50: % | D50: =Mkt!D73 -> 0.134733 | E50: =Mkt!E73 -> 0.1451191 | F50: =Mkt!F73 -> 0.1471191 | G50: =Mkt!G73 -> 0.1491191 | H50: =Mkt!H73 -> 0.1511191 | I50: =Mkt!I73 -> 0.1531191
A51: 份額：Kioxia | B51: % | D51: =Mkt!D74 -> 0.14359331 | E51: =Mkt!E74 -> 0.13953322 | F51: =Mkt!F74 -> 0.13678707 | G51: =Mkt!G74 -> 0.13506115 | H51: =Mkt!H74 -> 0.13333524 | I51: =Mkt!I74 -> 0.13160932
A52: 份額：SanDisk | B52: % | D52: =Mkt!D75 -> 0.1255914 | E52: =Mkt!E75 -> 0.11206254 | F52: =Mkt!F75 -> 0.10523959 | G52: =Mkt!G75 -> 0.10396551 | H52: =Mkt!H75 -> 0.10269142 | I52: =Mkt!I75 -> 0.10141734
A53: 份額：其他（長江存儲等） | B53: % | D53: =Mkt!D76 -> 0.085981484 | E53: =Mkt!E76 -> 0.12740864 | F53: =Mkt!F76 -> 0.13997774 | G53: =Mkt!G76 -> 0.14597774 | H53: =Mkt!H76 -> 0.15197774 | I53: =Mkt!I76 -> 0.15797774
A54: Kioxia＋SanDisk（合資群）份額 | B54: % | D54: =D51+D52 -> 0.26918471 | E54: =E51+E52 -> 0.25159576 | F54: =F51+F52 -> 0.24202666 | G54: =G51+G52 -> 0.23902666 | H54: =H51+H52 -> 0.23602666 | I54: =I51+I52 -> 0.23302666
A55: Kioxia 營收（年） | B55: $B | D55: =SUM(Mkt!C91:F91) -> 10.21 | E55: =SUM(Mkt!G91:J91) -> 47.834882 | F55: =SUM(Mkt!K91:N91) -> 71.41282 | G55: =SUM(Mkt!O91:R91) -> 32.726086 | H55: =SUM(Mkt!S91:V91) -> 33.432847 | I55: =SUM(Mkt!W91:Z91) -> 36.234957
A56: SanDisk 營收（年） | B56: $B | D56: =SUM(Mkt!C92:F92) -> 8.93 | E56: =SUM(Mkt!G92:J92) -> 38.417364 | F56: =SUM(Mkt!K92:N92) -> 54.942735 | G56: =SUM(Mkt!O92:R92) -> 25.191434 | H56: =SUM(Mkt!S92:V92) -> 25.749132 | I56: =SUM(Mkt!W92:Z92) -> 27.922438
A58: 情境 C（不如預期）
A59: 加速器顆數 | B59: 百萬顆 | E59: =Mkt!E102 -> 15.2 | F59: =Mkt!F102 -> 23.7 | G59: =Mkt!G102 -> 15.9 | H59: =Mkt!H102 -> 18.09 | I59: =Mkt!I102 -> 18.9945
A60: 需求：AI 企業級 SSD | B60: EB | D60: =Mkt!D104 -> 165 | E60: =Mkt!E104 -> 456 | F60: =Mkt!F104 -> 805.8 | G60: =Mkt!G104 -> 636 | H60: =Mkt!H104 -> 832.14 | I60: =Mkt!I104 -> 987.714
A61: 需求：非 AI 企業級 SSD | B61: EB | D61: =Mkt!D105 -> 135 | E61: =Mkt!E105 -> 148.5 | F61: =Mkt!F105 -> 163.35 | G61: =Mkt!G105 -> 179.685 | H61: =Mkt!H105 -> 197.6535 | I61: =Mkt!I105 -> 217.41885
A62: 需求：手機 | B62: EB | D62: =Mkt!D106 -> 320 | E62: =Mkt!E106 -> 304 | F62: =Mkt!F106 -> 313.12 | G62: =Mkt!G106 -> 338.1696 | H62: =Mkt!H106 -> 365.22317 | I62: =Mkt!I106 -> 394.44102
A63: 需求：PC | B63: EB | D63: =Mkt!D107 -> 230 | E63: =Mkt!E107 -> 218.5 | F63: =Mkt!F107 -> 218.5 | G63: =Mkt!G107 -> 231.61 | H63: =Mkt!H107 -> 245.5066 | I63: =Mkt!I107 -> 260.237
A64: 需求：消費性與其他 | B64: EB | D64: =Mkt!D108 -> 150 | E64: =Mkt!E108 -> 135 | F64: =Mkt!F108 -> 135 | G64: =Mkt!G108 -> 141.75 | H64: =Mkt!H108 -> 148.8375 | I64: =Mkt!I108 -> 156.27937
A65: 位元需求合計 | B65: EB | D65: =Mkt!D109 -> 1000 | E65: =Mkt!E109 -> 1262 | F65: =Mkt!F109 -> 1635.77 | G65: =Mkt!G109 -> 1527.2146 | H65: =Mkt!H109 -> 1789.3608 | I65: =Mkt!I109 -> 2016.0902
A66: 企業級 SSD 占需求 | B66: % | D66: =Mkt!D110 -> 0.3 | E66: =Mkt!E110 -> 0.47900158 | F66: =Mkt!F110 -> 0.59247327 | G66: =Mkt!G110 -> 0.53409979 | H66: =Mkt!H110 -> 0.57550915 | I66: =Mkt!I110 -> 0.59775739
A67: 位元供給 | B67: EB | D67: =Mkt!D111 -> 1000 | E67: =Mkt!E111 -> 1210 | F67: =Mkt!F111 -> 1512.5 | G67: =Mkt!G111 -> 1890.625 | H67: =Mkt!H111 -> 2306.5625 | I67: =Mkt!I111 -> 2767.875
A68: 需求 ÷ 供給 − 1 | B68: % | E68: =Mkt!E112 -> 0.042975207 | F68: =Mkt!F112 -> 0.081500826 | G68: =Mkt!G112 -> -0.19221707 | H68: =Mkt!H112 -> -0.22423053 | I68: =Mkt!I112 -> -0.27161081
A69: 位元出貨 | B69: EB | C69: =Mkt!C113 -> 892.85714 | D69: =Mkt!D113 -> 1000 | E69: =Mkt!E113 -> 1210 | F69: =Mkt!F113 -> 1512.5 | G69: =Mkt!G113 -> 1527.2146 | H69: =Mkt!H113 -> 1789.3608 | I69: =Mkt!I113 -> 2016.0902
A70: 位元出貨年增 | B70: % | D70: =Mkt!D114 -> 0.12 | E70: =Mkt!E114 -> 0.21 | F70: =Mkt!F114 -> 0.25 | G70: =Mkt!G114 -> 0.0097286612 | H70: =Mkt!H114 -> 0.17164986 | I70: =Mkt!I114 -> 0.12670976
A71: 平均售價 | B71: $/GB | C71: =Mkt!C117 -> 0.075488 | D71: =Mkt!D117 -> 0.071103592 | E71: =Mkt!E117 -> 0.28332293 | F71: =Mkt!F117 -> 0.34517215 | G71: =Mkt!G117 -> 0.11408236 | H71: =Mkt!H117 -> 0.078370361 | I71: =Mkt!I117 -> 0.08112105
A72: 平均售價年變動 | B72: % | D72: =Mkt!D118 -> -0.058080856 | E72: =Mkt!E118 -> 2.9846501 | F72: =Mkt!F118 -> 0.21829938 | G72: =Mkt!G118 -> -0.66949141 | H72: =Mkt!H118 -> -0.31303701 | I72: =Mkt!I118 -> 0.035098589
A73: NAND 市場營收 | B73: $B | C73: =Mkt!C115 -> 67.4 | D73: =Mkt!D115 -> 71.103592 | E73: =Mkt!E115 -> 342.82075 | F73: =Mkt!F115 -> 522.07288 | G73: =Mkt!G115 -> 174.22825 | H73: =Mkt!H115 -> 140.23285 | I73: =Mkt!I115 -> 163.54736
A74: 市場營收年增 | B74: % | D74: =Mkt!D116 -> 0.054949442 | E74: =Mkt!E116 -> 3.8214266 | F74: =Mkt!F116 -> 0.52287423 | G74: =Mkt!G116 -> -0.666276 | H74: =Mkt!H116 -> -0.19511991 | I74: =Mkt!I116 -> 0.16625568
A75: 份額：三星 | B75: % | D75: =Mkt!D119 -> 0.30940771 | E75: =Mkt!E119 -> 0.29814637 | F75: =Mkt!F119 -> 0.29314637 | G75: =Mkt!G119 -> 0.28814637 | H75: =Mkt!H119 -> 0.28314637 | I75: =Mkt!I119 -> 0.27814637
A76: 份額：SK 海力士＋Solidigm | B76: % | D76: =Mkt!D120 -> 0.20069309 | E76: =Mkt!E120 -> 0.17773013 | F76: =Mkt!F120 -> 0.17773013 | G76: =Mkt!G120 -> 0.17773013 | H76: =Mkt!H120 -> 0.17773013 | I76: =Mkt!I120 -> 0.17773013
A77: 份額：美光 | B77: % | D77: =Mkt!D121 -> 0.134733 | E77: =Mkt!E121 -> 0.1451191 | F77: =Mkt!F121 -> 0.1471191 | G77: =Mkt!G121 -> 0.1491191 | H77: =Mkt!H121 -> 0.1511191 | I77: =Mkt!I121 -> 0.1531191
A78: 份額：Kioxia | B78: % | D78: =Mkt!D122 -> 0.14359331 | E78: =Mkt!E122 -> 0.13953322 | F78: =Mkt!F122 -> 0.13506115 | G78: =Mkt!G122 -> 0.13160932 | H78: =Mkt!H122 -> 0.12815748 | I78: =Mkt!I122 -> 0.12470565
A79: 份額：SanDisk | B79: % | D79: =Mkt!D123 -> 0.1255914 | E79: =Mkt!E123 -> 0.11206254 | F79: =Mkt!F123 -> 0.10396551 | G79: =Mkt!G123 -> 0.10141734 | H79: =Mkt!H123 -> 0.098869175 | I79: =Mkt!I123 -> 0.096321009
A80: 份額：其他（長江存儲等） | B80: % | D80: =Mkt!D124 -> 0.085981484 | E80: =Mkt!E124 -> 0.12740864 | F80: =Mkt!F124 -> 0.14297774 | G80: =Mkt!G124 -> 0.15197774 | H80: =Mkt!H124 -> 0.16097774 | I80: =Mkt!I124 -> 0.16997774
A81: Kioxia＋SanDisk（合資群）份額 | B81: % | D81: =D78+D79 -> 0.26918471 | E81: =E78+E79 -> 0.25159576 | F81: =F78+F79 -> 0.23902666 | G81: =G78+G79 -> 0.23302666 | H81: =H78+H79 -> 0.22702666 | I81: =I78+I79 -> 0.22102666
A82: Kioxia 營收（年） | B82: $B | D82: =SUM(Mkt!C139:F139) -> 10.21 | E82: =SUM(Mkt!G139:J139) -> 47.834882 | F82: =SUM(Mkt!K139:N139) -> 70.511765 | G82: =SUM(Mkt!O139:R139) -> 22.930061 | H82: =SUM(Mkt!S139:V139) -> 17.971889 | I82: =SUM(Mkt!W139:Z139) -> 20.395279
A83: SanDisk 營收（年） | B83: $B | D83: =SUM(Mkt!C140:F140) -> 8.93 | E83: =SUM(Mkt!G140:J140) -> 38.417364 | F83: =SUM(Mkt!K140:N140) -> 54.277571 | G83: =SUM(Mkt!O140:R140) -> 17.669766 | H83: =SUM(Mkt!S140:V140) -> 13.864706 | I83: =SUM(Mkt!W140:Z140) -> 15.753047
A85: 核對：三情境份額合計 − 1、實績季重現（應為 0） | C85: =Mkt!C49+Mkt!C97+Mkt!C145 -> 0

Sheet Path
A1: Path — NAND 合約價指數（2025Q1＝1）。2025Q2–2029Q4 季增取自 markets/memory（In 頁 N1）；2030 各季＝(1＋p10)^(1/4)（收斂法，灰底）
A3: 情境 | B3: 說明 | C3: 2025Q1 | D3: 2025Q2 | E3: 2025Q3 | F3: 2025Q4 | G3: 2026Q1 | H3: 2026Q2 | I3: 2026Q3 | J3: 2026Q4 | K3: 2027Q1 | L3: 2027Q2 | M3: 2027Q3 | N3: 2027Q4 | O3: 2028Q1 | P3: 2028Q2 | Q3: 2028Q3 | R3: 2028Q4 | S3: 2029Q1 | T3: 2029Q2 | U3: 2029Q3 | V3: 2029Q4 | W3: 2030Q1 | X3: 2030Q2 | Y3: 2030Q3 | Z3: 2030Q4
A4: A | B4: 情境 A（順利） | C4: 1 | D4: =C4*(1+nq_1) -> 1 | E4: =D4*(1+nq_2) -> 1.05 | F4: =E4*(1+nq_3) -> 1.365 | G4: =F4*(1+nq_4) -> 2.559375 | H4: =G4*(1+nq_5) -> 4.4149219 | I4: =H4*(1+nq_6) -> 5.5186523 | J4: =I4*(1+nq_7) -> 5.9656632 | K4: =J4*(1+nqA_8) -> 6.1446331 | L4: =K4*(1+nqA_9) -> 6.1446331 | M4: =L4*(1+nqA_10) -> 5.8374014 | N4: =M4*(1+nqA_11) -> 5.4287833 | O4: =N4*(1+nqA_12) -> 5.1573442 | P4: =O4*(1+nqA_13) -> 4.899477 | Q4: =P4*(1+nqA_14) -> 4.6545031 | R4: =Q4*(1+nqA_15) -> 4.4217779 | S4: =R4*(1+nqA_16) -> 4.2891246 | T4: =S4*(1+nqA_17) -> 4.1604509 | U4: =T4*(1+nqA_18) -> 4.0356373 | V4: =U4*(1+nqA_19) -> 3.9145682 | W4: =V4*(1+((1+p10)^(1/4)-1)) -> 3.791443 | X4: =W4*(1+((1+p10)^(1/4)-1)) -> 3.6721905 | Y4: =X4*(1+((1+p10)^(1/4)-1)) -> 3.5566888 | Z4: =Y4*(1+((1+p10)^(1/4)-1)) -> 3.44482
A5: B | B5: 情境 B（平平） | C5: 1 | D5: =C5*(1+nq_1) -> 1 | E5: =D5*(1+nq_2) -> 1.05 | F5: =E5*(1+nq_3) -> 1.365 | G5: =F5*(1+nq_4) -> 2.559375 | H5: =G5*(1+nq_5) -> 4.4149219 | I5: =H5*(1+nq_6) -> 5.5186523 | J5: =I5*(1+nq_7) -> 5.9656632 | K5: =J5*(1+nqB_8) -> 6.2639463 | L5: =K5*(1+nqB_9) -> 6.3892253 | M5: =L5*(1+nqB_10) -> 5.7503027 | N5: =M5*(1+nqB_11) -> 4.6002422 | O5: =N5*(1+nqB_12) -> 3.2201695 | P5: =O5*(1+nqB_13) -> 2.4151272 | Q5: =P5*(1+nqB_14) -> 1.9321017 | R5: =Q5*(1+nqB_15) -> 1.7388915 | S5: =R5*(1+nqB_16) -> 1.8258361 | T5: =S5*(1+nqB_17) -> 1.9171279 | U5: =T5*(1+nqB_18) -> 1.9746418 | V5: =U5*(1+nqB_19) -> 2.033881 | W5: =V5*(1+((1+p10)^(1/4)-1)) -> 1.9699092 | X5: =W5*(1+((1+p10)^(1/4)-1)) -> 1.9079495 | Y5: =X5*(1+((1+p10)^(1/4)-1)) -> 1.8479386 | Z5: =Y5*(1+((1+p10)^(1/4)-1)) -> 1.7898153
A6: C | B6: 情境 C（不如預期） | C6: 1 | D6: =C6*(1+nq_1) -> 1 | E6: =D6*(1+nq_2) -> 1.05 | F6: =E6*(1+nq_3) -> 1.365 | G6: =F6*(1+nq_4) -> 2.559375 | H6: =G6*(1+nq_5) -> 4.4149219 | I6: =H6*(1+nq_6) -> 5.5186523 | J6: =I6*(1+nq_7) -> 5.9656632 | K6: =J6*(1+nqC_8) -> 6.2639463 | L6: =K6*(1+nqC_9) -> 6.3892253 | M6: =L6*(1+nqC_10) -> 5.7503027 | N6: =M6*(1+nqC_11) -> 4.6002422 | O6: =N6*(1+nqC_12) -> 2.9901574 | P6: =O6*(1+nqC_13) -> 1.9436023 | Q6: =P6*(1+nqC_14) -> 1.4577017 | R6: =Q6*(1+nqC_15) -> 1.1661614 | S6: =R6*(1+nqC_16) -> 1.1661614 | T6: =S6*(1+nqC_17) -> 1.2244695 | U6: =T6*(1+nqC_18) -> 1.322427 | V6: =U6*(1+nqC_19) -> 1.4546697 | W6: =V6*(1+((1+p10)^(1/4)-1)) -> 1.4089159 | X6: =W6*(1+((1+p10)^(1/4)-1)) -> 1.3646012 | Y6: =X6*(1+((1+p10)^(1/4)-1)) -> 1.3216803 | Z6: =Y6*(1+((1+p10)^(1/4)-1)) -> 1.2801094
A8: 年均指數
A9: 情境 | B9: 說明 | C9: CY2025 | D9: CY2026 | E9: CY2027 | F9: CY2028 | G9: CY2029 | H9: CY2030 | I9: CY2026÷CY2025 | J9: CY2027÷CY2026 | K9: CY2028÷CY2027 | L9: CY2029÷CY2028 | M9: CY2030÷CY2029
A10: A | B10: 四季平均 | C10: =AVERAGE(C4:F4) -> 1.10375 | D10: =AVERAGE(G4:J4) -> 4.6146531 | E10: =AVERAGE(K4:N4) -> 5.8888627 | F10: =AVERAGE(O4:R4) -> 4.7832755 | G10: =AVERAGE(S4:V4) -> 4.0999453 | H10: =AVERAGE(W4:Z4) -> 3.6162856 | I10: =D10/C10-1 -> 3.1808862 | J10: =E10/D10-1 -> 0.27612252 | K10: =F10/E10-1 -> -0.18774205 | L10: =G10/F10-1 -> -0.14285823 | M10: =H10/G10-1 -> -0.11796735
A11: B | B11: 四季平均 | C11: =AVERAGE(C5:F5) -> 1.10375 | D11: =AVERAGE(G5:J5) -> 4.6146531 | E11: =AVERAGE(K5:N5) -> 5.7509291 | F11: =AVERAGE(O5:R5) -> 2.3265725 | G11: =AVERAGE(S5:V5) -> 1.9378717 | H11: =AVERAGE(W5:Z5) -> 1.8789032 | I11: =D11/C11-1 -> 3.1808862 | J11: =E11/D11-1 -> 0.24623217 | K11: =F11/E11-1 -> -0.59544407 | L11: =G11/F11-1 -> -0.16707013 | M11: =H11/G11-1 -> -0.030429538
A12: C | B12: 四季平均 | C12: =AVERAGE(C6:F6) -> 1.10375 | D12: =AVERAGE(G6:J6) -> 4.6146531 | E12: =AVERAGE(K6:N6) -> 5.7509291 | F12: =AVERAGE(O6:R6) -> 1.8894057 | G12: =AVERAGE(S6:V6) -> 1.2919319 | H12: =AVERAGE(W6:Z6) -> 1.3438267 | I12: =D12/C12-1 -> 3.1808862 | J12: =E12/D12-1 -> 0.24623217 | K12: =F12/E12-1 -> -0.67146079 | L12: =G12/F12-1 -> -0.31622315 | M12: =H12/G12-1 -> 0.040168345

Sheet Mkt
A1: Mkt — NAND 市場（三情境各一個完整推導區塊；A 區年度、B 區季度）。需求＝AI 企業級 SSD（加速器顆數 × 每顆容量）＋非 AI；出貨＝MIN(需求, 供給)；營收＝2Q26 實績 × 價格指數比 × 位元比；份額 × 市場＝各廠營收
A2: 下游讀數列：「Kioxia 營收（情境 s）」「SanDisk 營收（情境 s）」「Kioxia 位元（…）」「SanDisk 位元（…）」（C..Z＝2025Q1..2030Q4）。灰底＝2030 收斂法
A4: 情境 A（順利）：價格路徑 A（2027–28 高檔持平、2029 緩降（BofA、TrendForce 型））；2028–29 顆數 × 1.0／1.0；合資群份額年變動 dr_jv_A
A5: A. 年度（日曆年） | B5: 單位 | C5: CY2024 | D5: CY2025 | E5: CY2026 | F5: CY2027 | G5: CY2028 | H5: CY2029 | I5: CY2030 | AB5: 說明
A6: 加速器顆數（同字母情境係數） | B6: 百萬顆 | E6: =(u_26)*1 -> 15.2 | F6: =(u_27)*1 -> 23.7 | G6: =(u_28)*um28_A -> 26.5 | H6: =(u_28*(1+g_u29))*um29_A -> 30.15 | I6: =(u_28*(1+g_u29)*(1+g_u30))*um29_A -> 31.6575 | AB6: markets/memory UNITS × SCEN_UNITS；2029–30 基準以 g_u29、g_u30 外推，CY2030 沿用 um29
A7: 每顆企業級 SSD 容量 | B7: TB | E7: =tb_26 -> 30 | F7: =tb_27 -> 34 | G7: =tb_28 -> 40 | H7: =tb_29 -> 46 | I7: =tb_30 -> 52
A8: 需求：AI 企業級 SSD | B8: EB | D8: =bits25*sh_essd25*ai25 -> 165 | E8: =E6*E7 -> 456 | F8: =F6*F7 -> 805.8 | G8: =G6*G7 -> 1060 | H8: =H6*H7 -> 1386.9 | I8: =I6*I7 -> 1646.19 | AB8: 顆數 × 每顆容量（百萬顆 × TB＝EB）；2025＝基期 × 占比
A9: 需求：非 AI 企業級 SSD | B9: EB | D9: =bits25*sh_essd25*(1-ai25) -> 135 | E9: =D9*(1+g_nai) -> 148.5 | F9: =E9*(1+g_nai) -> 163.35 | G9: =F9*(1+g_nai) -> 179.685 | H9: =G9*(1+g_nai) -> 197.6535 | I9: =H9*(1+g_nai) -> 217.41885
A10: 需求：手機 | B10: EB | D10: =bits25*sh_mob25 -> 320 | E10: =D10*(1+g_mob_26) -> 304 | F10: =E10*(1+g_mob_27) -> 313.12 | G10: =F10*(1+g_mob_28) -> 338.1696 | H10: =G10*(1+g_mob_28) -> 365.22317 | I10: =H10*(1+g_mob_28) -> 394.44102
A11: 需求：PC（client SSD） | B11: EB | D11: =bits25*sh_pc25 -> 230 | E11: =D11*(1+g_pc_26) -> 218.5 | F11: =E11*(1+g_pc_27) -> 218.5 | G11: =F11*(1+g_pc_28) -> 231.61 | H11: =G11*(1+g_pc_28) -> 245.5066 | I11: =H11*(1+g_pc_28) -> 260.237
A12: 需求：消費性與其他 | B12: EB | D12: =bits25*(1-sh_essd25-sh_mob25-sh_pc25) -> 150 | E12: =D12*(1+g_con_26) -> 135 | F12: =E12*(1+g_con_27) -> 135 | G12: =F12*(1+g_con_28) -> 141.75 | H12: =G12*(1+g_con_28) -> 148.8375 | I12: =H12*(1+g_con_28) -> 156.27937
A13: 位元需求合計 | B13: EB | D13: =SUM(D8:D12) -> 1000 | E13: =SUM(E8:E12) -> 1262 | F13: =SUM(F8:F12) -> 1635.77 | G13: =SUM(G8:G12) -> 1951.2146 | H13: =SUM(H8:H12) -> 2344.1208 | I13: =SUM(I8:I12) -> 2674.5662
A14: 企業級 SSD 占位元需求 | B14: % | D14: =(D8+D9)/D13 -> 0.3 | E14: =(E8+E9)/E13 -> 0.47900158 | F14: =(F8+F9)/F13 -> 0.59247327 | G14: =(G8+G9)/G13 -> 0.63534016 | H14: =(H8+H9)/H13 -> 0.67596923 | I14: =(I8+I9)/I13 -> 0.69678919
A15: 位元供給（三情境相同） | B15: EB | D15: =bits25 -> 1000 | E15: =D15*(1+gs_26) -> 1210 | F15: =E15*(1+gs_27) -> 1512.5 | G15: =F15*(1+gs_28) -> 1890.625 | H15: =G15*(1+gs_29) -> 2306.5625 | I15: =H15*(1+gs_30) -> 2767.875 | AB15: 2025＝出貨實績（基期）；供給不隨需求情境變（產能 2027 前已訂定），需求不足的結果是閒置產能與降價
A16: 需求 ÷ 供給 − 1（>0＝短缺） | B16: % | E16: =E13/E15-1 -> 0.042975207 | F16: =F13/F15-1 -> 0.081500826 | G16: =G13/G15-1 -> 0.032047392 | H16: =H13/H15-1 -> 0.016283221 | I16: =I13/I15-1 -> -0.033711334
A17: 位元出貨＝MIN(需求, 供給) | B17: EB | C17: =bits25/(1+g25) -> 892.85714 | D17: =bits25 -> 1000 | E17: =MIN(E13,E15) -> 1210 | F17: =MIN(F13,F15) -> 1512.5 | G17: =MIN(G13,G15) -> 1890.625 | H17: =MIN(H13,H15) -> 2306.5625 | I17: =MIN(I13,I15) -> 2674.5662
A18: 位元出貨年增 | B18: % | D18: =D17/C17-1 -> 0.12 | E18: =E17/D17-1 -> 0.21 | F18: =F17/E17-1 -> 0.25 | G18: =G17/F17-1 -> 0.25 | H18: =H17/G17-1 -> 0.22 | I18: =I17/H17-1 -> 0.1595464
A19: NAND 市場營收（四季合計） | B19: $B | C19: =rev24 -> 67.4 | D19: =SUM(C33:F33) -> 71.103592 | E19: =SUM(G33:J33) -> 342.82075 | F19: =SUM(K33:N33) -> 536.73468 | G19: =SUM(O33:R33) -> 544.61015 | H19: =SUM(S33:V33) -> 570.46528 | I19: =SUM(W33:Z33) -> 583.68943 | AB19: CY2024 為 TrendForce 年度值
A20: 市場營收年增 | B20: % | D20: =D19/C19-1 -> 0.054949442 | E20: =E19/D19-1 -> 3.8214266 | F20: =F19/E19-1 -> 0.56564233 | G20: =G19/F19-1 -> 0.014672931 | H20: =H19/G19-1 -> 0.04747456 | I20: =I19/H19-1 -> 0.023181352
A21: 平均售價（營收 ÷ 位元出貨） | B21: $/GB | C21: =C19/C17 -> 0.075488 | D21: =D19/D17 -> 0.071103592 | E21: =E19/E17 -> 0.28332293 | F21: =F19/F17 -> 0.3548659 | G21: =G19/G17 -> 0.28805826 | H21: =H19/H17 -> 0.2473227 | I21: =I19/I17 -> 0.21823704
A22: 平均售價年變動 | B22: % | D22: =D21/C21-1 -> -0.058080856 | E22: =E21/D21-1 -> 2.9846501 | F22: =F21/E21-1 -> 0.25251387 | G22: =G21/F21-1 -> -0.18826165 | H22: =H21/G21-1 -> -0.1414143 | I22: =I21/H21-1 -> -0.11760206 | AB22: CY2030 為收斂法（p10）＋位元平滑效果
A23: 年度份額：三星 | B23: % | D23: =SUM(C40:F40)/D19 -> 0.30940771 | E23: =SUM(G40:J40)/E19 -> 0.29814637 | F23: =SUM(K40:N40)/F19 -> 0.29314637 | G23: =SUM(O40:R40)/G19 -> 0.28814637 | H23: =SUM(S40:V40)/H19 -> 0.28314637 | I23: =SUM(W40:Z40)/I19 -> 0.27814637
A24: 年度份額：SK 海力士＋Solidigm | B24: % | D24: =SUM(C41:F41)/D19 -> 0.20069309 | E24: =SUM(G41:J41)/E19 -> 0.17773013 | F24: =SUM(K41:N41)/F19 -> 0.17773013 | G24: =SUM(O41:R41)/G19 -> 0.17773013 | H24: =SUM(S41:V41)/H19 -> 0.17773013 | I24: =SUM(W41:Z41)/I19 -> 0.17773013
A25: 年度份額：美光 | B25: % | D25: =SUM(C42:F42)/D19 -> 0.134733 | E25: =SUM(G42:J42)/E19 -> 0.1451191 | F25: =SUM(K42:N42)/F19 -> 0.1471191 | G25: =SUM(O42:R42)/G19 -> 0.1491191 | H25: =SUM(S42:V42)/H19 -> 0.1511191 | I25: =SUM(W42:Z42)/I19 -> 0.1531191
A26: 年度份額：Kioxia | B26: % | D26: =SUM(C43:F43)/D19 -> 0.14359331 | E26: =SUM(G43:J43)/E19 -> 0.13953322 | F26: =SUM(K43:N43)/F19 -> 0.13851299 | G26: =SUM(O43:R43)/G19 -> 0.13851299 | H26: =SUM(S43:V43)/H19 -> 0.13851299 | I26: =SUM(W43:Z43)/I19 -> 0.13851299
A27: 年度份額：SanDisk | B27: % | D27: =SUM(C44:F44)/D19 -> 0.1255914 | E27: =SUM(G44:J44)/E19 -> 0.11206254 | F27: =SUM(K44:N44)/F19 -> 0.10651367 | G27: =SUM(O44:R44)/G19 -> 0.10651367 | H27: =SUM(S44:V44)/H19 -> 0.10651367 | I27: =SUM(W44:Z44)/I19 -> 0.10651367
A28: 年度份額：其他（長江存儲等） | B28: % | D28: =SUM(C45:F45)/D19 -> 0.085981484 | E28: =SUM(G45:J45)/E19 -> 0.12740864 | F28: =SUM(K45:N45)/F19 -> 0.13697774 | G28: =SUM(O45:R45)/G19 -> 0.13997774 | H28: =SUM(S45:V45)/H19 -> 0.14297774 | I28: =SUM(W45:Z45)/I19 -> 0.14597774
A30: B. 季度 | B30: 單位 | C30: 2025Q1 | D30: 2025Q2 | E30: 2025Q3 | F30: 2025Q4 | G30: 2026Q1 | H30: 2026Q2 | I30: 2026Q3 | J30: 2026Q4 | K30: 2027Q1 | L30: 2027Q2 | M30: 2027Q3 | N30: 2027Q4 | O30: 2028Q1 | P30: 2028Q2 | Q30: 2028Q3 | R30: 2028Q4 | S30: 2029Q1 | T30: 2029Q2 | U30: 2029Q3 | V30: 2029Q4 | W30: 2030Q1 | X30: 2030Q2 | Y30: 2030Q3 | Z30: 2030Q4 | AB30: 說明
A31: 合約價指數（同字母路徑） | B31: 2025Q1＝1 | C31: =Path!C4 -> 1 | D31: =Path!D4 -> 1 | E31: =Path!E4 -> 1.05 | F31: =Path!F4 -> 1.365 | G31: =Path!G4 -> 2.559375 | H31: =Path!H4 -> 4.4149219 | I31: =Path!I4 -> 5.5186523 | J31: =Path!J4 -> 5.9656632 | K31: =Path!K4*1 -> 6.1446331 | L31: =Path!L4*1 -> 6.1446331 | M31: =Path!M4*1 -> 5.8374014 | N31: =Path!N4*1 -> 5.4287833 | O31: =Path!O4*1 -> 5.1573442 | P31: =Path!P4*1 -> 4.899477 | Q31: =Path!Q4*1 -> 4.6545031 | R31: =Path!R4*1 -> 4.4217779 | ... V31: =Path!V4*1 -> 3.9145682 | W31: =Path!V4*(1+p10)^(1/4)*1 -> 3.791443 | X31: =Path!V4*(1+p10)^(2/4)*1 -> 3.6721905 | Y31: =Path!V4*(1+p10)^(3/4)*1 -> 3.5566888 | Z31: =Path!V4*(1+p10)^(4/4)*1 -> 3.44482 | AB31: Path 頁；Sens 可對 2027 起的季價乘價格係數
A32: 季度位元出貨（年內依年增平滑；四季合計＝年度） | B32: EB | C32: =D17/4*(D17/C17)^((1-2.5)/4)/(((D17/C17)^(-0.375)+(D17/C17)^(-0.125)+(D17/C17)^(0.125)+(D17/C17)^(0.375))/4) -> 239.47787 | D32: =D17/4*(D17/C17)^((2-2.5)/4)/(((D17/C17)^(-0.375)+(D17/C17)^(-0.125)+(D17/C17)^(0.125)+(D17/C17)^(0.375))/4) -> 246.35983 | E32: =D17/4*(D17/C17)^((3-2.5)/4)/(((D17/C17)^(-0.375)+(D17/C17)^(-0.125)+(D17/C17)^(0.125)+(D17/C17)^(0.375))/4) -> 253.43956 | F32: =D17/4*(D17/C17)^((4-2.5)/4)/(((D17/C17)^(-0.375)+(D17/C17)^(-0.125)+(D17/C17)^(0.125)+(D17/C17)^(0.375))/4) -> 260.72274 | G32: =E17/4*(E17/D17)^((1-2.5)/4)/(((E17/D17)^(-0.375)+(E17/D17)^(-0.125)+(E17/D17)^(0.125)+(E17/D17)^(0.375))/4) -> 281.23193 | H32: =E17/4*(E17/D17)^((2-2.5)/4)/(((E17/D17)^(-0.375)+(E17/D17)^(-0.125)+(E17/D17)^(0.125)+(E17/D17)^(0.375))/4) -> 294.95854 | I32: =E17/4*(E17/D17)^((3-2.5)/4)/(((E17/D17)^(-0.375)+(E17/D17)^(-0.125)+(E17/D17)^(0.125)+(E17/D17)^(0.375))/4) -> 309.35513 | J32: =E17/4*(E17/D17)^((4-2.5)/4)/(((E17/D17)^(-0.375)+(E17/D17)^(-0.125)+(E17/D17)^(0.125)+(E17/D17)^(0.375))/4) -> 324.4544 | K32: =F17/4*(F17/E17)^((1-2.5)/4)/(((F17/E17)^(-0.375)+(F17/E17)^(-0.125)+(F17/E17)^(0.125)+(F17/E17)^(0.375))/4) -> 347.09614 | L32: =F17/4*(F17/E17)^((2-2.5)/4)/(((F17/E17)^(-0.375)+(F17/E17)^(-0.125)+(F17/E17)^(0.125)+(F17/E17)^(0.375))/4) -> 367.00949 | M32: =F17/4*(F17/E17)^((3-2.5)/4)/(((F17/E17)^(-0.375)+(F17/E17)^(-0.125)+(F17/E17)^(0.125)+(F17/E17)^(0.375))/4) -> 388.06529 | N32: =F17/4*(F17/E17)^((4-2.5)/4)/(((F17/E17)^(-0.375)+(F17/E17)^(-0.125)+(F17/E17)^(0.125)+(F17/E17)^(0.375))/4) -> 410.32908 | O32: =G17/4*(G17/F17)^((1-2.5)/4)/(((G17/F17)^(-0.375)+(G17/F17)^(-0.125)+(G17/F17)^(0.125)+(G17/F17)^(0.375))/4) -> 433.87018 | P32: =G17/4*(G17/F17)^((2-2.5)/4)/(((G17/F17)^(-0.375)+(G17/F17)^(-0.125)+(G17/F17)^(0.125)+(G17/F17)^(0.375))/4) -> 458.76186 | Q32: =G17/4*(G17/F17)^((3-2.5)/4)/(((G17/F17)^(-0.375)+(G17/F17)^(-0.125)+(G17/F17)^(0.125)+(G17/F17)^(0.375))/4) -> 485.08161 | R32: =G17/4*(G17/F17)^((4-2.5)/4)/(((G17/F17)^(-0.375)+(G17/F17)^(-0.125)+(G17/F17)^(0.125)+(G17/F17)^(0.375))/4) -> 512.91135 | S32: =H17/4*(H17/G17)^((1-2.5)/4)/(((H17/G17)^(-0.375)+(H17/G17)^(-0.125)+(H17/G17)^(0.125)+(H17/G17)^(0.375))/4) -> 534.37942 | T32: =H17/4*(H17/G17)^((2-2.5)/4)/(((H17/G17)^(-0.375)+(H17/G17)^(-0.125)+(H17/G17)^(0.125)+(H17/G17)^(0.375))/4) -> 561.61627 | U32: =H17/4*(H17/G17)^((3-2.5)/4)/(((H17/G17)^(-0.375)+(H17/G17)^(-0.125)+(H17/G17)^(0.125)+(H17/G17)^(0.375))/4) -> 590.24136 | V32: =H17/4*(H17/G17)^((4-2.5)/4)/(((H17/G17)^(-0.375)+(H17/G17)^(-0.125)+(H17/G17)^(0.125)+(H17/G17)^(0.375))/4) -> 620.32545 | W32: =I17/4*(I17/H17)^((1-2.5)/4)/(((I17/H17)^(-0.375)+(I17/H17)^(-0.125)+(I17/H17)^(0.125)+(I17/H17)^(0.375))/4) -> 631.99501 | X32: =I17/4*(I17/H17)^((2-2.5)/4)/(((I17/H17)^(-0.375)+(I17/H17)^(-0.125)+(I17/H17)^(0.125)+(I17/H17)^(0.375))/4) -> 655.82155 | Y32: =I17/4*(I17/H17)^((3-2.5)/4)/(((I17/H17)^(-0.375)+(I17/H17)^(-0.125)+(I17/H17)^(0.125)+(I17/H17)^(0.375))/4) -> 680.54636 | Z32: =I17/4*(I17/H17)^((4-2.5)/4)/(((I17/H17)^(-0.375)+(I17/H17)^(-0.125)+(I17/H17)^(0.125)+(I17/H17)^(0.375))/4) -> 706.20331 | AB32: 季度＝年度 ÷ 4 ×（1＋年增）^((季−2.5)/4)，再正規化使四季合計等於年度
A33: NAND 市場營收（2026Q2 前實績；之後＝2Q26 實績 × 價格指數比 × 位元比） | B33: $B | C33: =(rv_ss_0+rv_sk_0+rv_mu_0+rv_kx_0+rv_sd_0)/t5_0 -> 12.935484 | D33: =(rv_ss_1+rv_sk_1+rv_mu_1+rv_kx_1+rv_sd_1)/t5_1 -> 15.805471 | E33: =(rv_ss_2+rv_sk_2+rv_mu_2+rv_kx_2+rv_sd_2)/t5_2 -> 18.791209 | F33: =(rv_ss_3+rv_sk_3+rv_mu_3+rv_kx_3+rv_sd_3)/t5_3 -> 23.571429 | G33: =(rv_ss_4+rv_sk_4+rv_mu_4+rv_kx_4+rv_sd_4)/t5_4 -> 43.954802 | H33: =(rv_ss_5+rv_sk_5+rv_mu_5+rv_kx_5+rv_sd_5)/t5_5 -> 78.703072 | I33: =$H33*I31/$H31*I32/$H32 -> 103.1806 | J33: =$H33*J31/$H31*J32/$H32 -> 116.98228 | K33: =$H33*K31/$H31*K32/$H32 -> 128.90015 | L33: =$H33*L31/$H31*L32/$H32 -> 136.29532 | M33: =$H33*M31/$H31*M32/$H32 -> 136.90901 | N33: =$H33*N31/$H31*N32/$H32 -> 134.6302 | O33: =$H33*O31/$H31*O32/$H32 -> 135.2364 | P33: =$H33*P31/$H31*P32/$H32 -> 135.84533 | ... Z33: =$H33*Z31/$H31*Z32/$H32 -> 147.02933 | AB33: 實績＝TrendForce 前五大 ÷ 前五大占比；以 2Q26 為錨
A34: 份額：三星 | B34: % | C34: =rv_ss_0/C33 -> 0.32468828 | D34: =rv_ss_1/D33 -> 0.329 | E34: =rv_ss_2/E33 -> 0.31929825 | F34: =rv_ss_3/F33 -> 0.28 | G34: =rv_ss_4/G33 -> 0.30736118 | H34: =rv_ss_5/H33 -> 0.293 | I34: =(rv_ss_4+rv_ss_5)/($G33+$H33) -> 0.29814637 | J34: =(rv_ss_4+rv_ss_5)/($G33+$H33) -> 0.29814637 | K34: =(rv_ss_4+rv_ss_5)/($G33+$H33)+dr_ss/100*1 -> 0.29314637 | L34: =(rv_ss_4+rv_ss_5)/($G33+$H33)+dr_ss/100*1 -> 0.29314637 | M34: =(rv_ss_4+rv_ss_5)/($G33+$H33)+dr_ss/100*1 -> 0.29314637 | N34: =(rv_ss_4+rv_ss_5)/($G33+$H33)+dr_ss/100*1 -> 0.29314637 | O34: =(rv_ss_4+rv_ss_5)/($G33+$H33)+dr_ss/100*2 -> 0.28814637 | P34: =(rv_ss_4+rv_ss_5)/($G33+$H33)+dr_ss/100*2 -> 0.28814637 | Q34: =(rv_ss_4+rv_ss_5)/($G33+$H33)+dr_ss/100*2 -> 0.28814637 | R34: =(rv_ss_4+rv_ss_5)/($G33+$H33)+dr_ss/100*2 -> 0.28814637 | S34: =(rv_ss_4+rv_ss_5)/($G33+$H33)+dr_ss/100*3 -> 0.28314637 | T34: =(rv_ss_4+rv_ss_5)/($G33+$H33)+dr_ss/100*3 -> 0.28314637 | U34: =(rv_ss_4+rv_ss_5)/($G33+$H33)+dr_ss/100*3 -> 0.28314637 | V34: =(rv_ss_4+rv_ss_5)/($G33+$H33)+dr_ss/100*3 -> 0.28314637 | W34: =(rv_ss_4+rv_ss_5)/($G33+$H33)+dr_ss/100*4 -> 0.27814637 | X34: =(rv_ss_4+rv_ss_5)/($G33+$H33)+dr_ss/100*4 -> 0.27814637 | Y34: =(rv_ss_4+rv_ss_5)/($G33+$H33)+dr_ss/100*4 -> 0.27814637 | Z34: =(rv_ss_4+rv_ss_5)/($G33+$H33)+dr_ss/100*4 -> 0.27814637 | AB34: 2026Q3–Q4＝1H26 實績份額；2027 起每年＋年變動
A35: 份額：SK 海力士＋Solidigm | B35: % | C35: =rv_sk_0/C33 -> 0.16930175 | D35: =rv_sk_1/D33 -> 0.21131923 | E35: =rv_sk_2/E33 -> 0.1878538 | F35: =rv_sk_3/F33 -> 0.2210303 | G35: =rv_sk_4/G33 -> 0.17131234 | H35: =rv_sk_5/H33 -> 0.1813144 | I35: =(rv_sk_4+rv_sk_5)/($G33+$H33) -> 0.17773013 | J35: =(rv_sk_4+rv_sk_5)/($G33+$H33) -> 0.17773013 | K35: =(rv_sk_4+rv_sk_5)/($G33+$H33)+dr_sk/100*1 -> 0.17773013 | L35: =(rv_sk_4+rv_sk_5)/($G33+$H33)+dr_sk/100*1 -> 0.17773013 | M35: =(rv_sk_4+rv_sk_5)/($G33+$H33)+dr_sk/100*1 -> 0.17773013 | N35: =(rv_sk_4+rv_sk_5)/($G33+$H33)+dr_sk/100*1 -> 0.17773013 | O35: =(rv_sk_4+rv_sk_5)/($G33+$H33)+dr_sk/100*2 -> 0.17773013 | P35: =(rv_sk_4+rv_sk_5)/($G33+$H33)+dr_sk/100*2 -> 0.17773013 | Q35: =(rv_sk_4+rv_sk_5)/($G33+$H33)+dr_sk/100*2 -> 0.17773013 | R35: =(rv_sk_4+rv_sk_5)/($G33+$H33)+dr_sk/100*2 -> 0.17773013 | S35: =(rv_sk_4+rv_sk_5)/($G33+$H33)+dr_sk/100*3 -> 0.17773013 | T35: =(rv_sk_4+rv_sk_5)/($G33+$H33)+dr_sk/100*3 -> 0.17773013 | U35: =(rv_sk_4+rv_sk_5)/($G33+$H33)+dr_sk/100*3 -> 0.17773013 | V35: =(rv_sk_4+rv_sk_5)/($G33+$H33)+dr_sk/100*3 -> 0.17773013 | W35: =(rv_sk_4+rv_sk_5)/($G33+$H33)+dr_sk/100*4 -> 0.17773013 | X35: =(rv_sk_4+rv_sk_5)/($G33+$H33)+dr_sk/100*4 -> 0.17773013 | Y35: =(rv_sk_4+rv_sk_5)/($G33+$H33)+dr_sk/100*4 -> 0.17773013 | Z35: =(rv_sk_4+rv_sk_5)/($G33+$H33)+dr_sk/100*4 -> 0.17773013 | AB35: 2026Q3–Q4＝1H26 實績份額；2027 起每年＋年變動
A36: 份額：美光 | B36: % | C36: =rv_mu_0/C33 -> 0.15693267 | D36: =rv_mu_1/D33 -> 0.13286538 | E36: =rv_mu_2/E33 -> 0.12878363 | F36: =rv_mu_3/F33 -> 0.12854545 | G36: =rv_mu_4/G33 -> 0.13536632 | H36: =rv_mu_5/H33 -> 0.15056592 | I36: =(rv_mu_4+rv_mu_5)/($G33+$H33) -> 0.1451191 | J36: =(rv_mu_4+rv_mu_5)/($G33+$H33) -> 0.1451191 | K36: =(rv_mu_4+rv_mu_5)/($G33+$H33)+dr_mu/100*1 -> 0.1471191 | L36: =(rv_mu_4+rv_mu_5)/($G33+$H33)+dr_mu/100*1 -> 0.1471191 | M36: =(rv_mu_4+rv_mu_5)/($G33+$H33)+dr_mu/100*1 -> 0.1471191 | N36: =(rv_mu_4+rv_mu_5)/($G33+$H33)+dr_mu/100*1 -> 0.1471191 | O36: =(rv_mu_4+rv_mu_5)/($G33+$H33)+dr_mu/100*2 -> 0.1491191 | P36: =(rv_mu_4+rv_mu_5)/($G33+$H33)+dr_mu/100*2 -> 0.1491191 | Q36: =(rv_mu_4+rv_mu_5)/($G33+$H33)+dr_mu/100*2 -> 0.1491191 | R36: =(rv_mu_4+rv_mu_5)/($G33+$H33)+dr_mu/100*2 -> 0.1491191 | S36: =(rv_mu_4+rv_mu_5)/($G33+$H33)+dr_mu/100*3 -> 0.1511191 | T36: =(rv_mu_4+rv_mu_5)/($G33+$H33)+dr_mu/100*3 -> 0.1511191 | U36: =(rv_mu_4+rv_mu_5)/($G33+$H33)+dr_mu/100*3 -> 0.1511191 | V36: =(rv_mu_4+rv_mu_5)/($G33+$H33)+dr_mu/100*3 -> 0.1511191 | W36: =(rv_mu_4+rv_mu_5)/($G33+$H33)+dr_mu/100*4 -> 0.1531191 | X36: =(rv_mu_4+rv_mu_5)/($G33+$H33)+dr_mu/100*4 -> 0.1531191 | Y36: =(rv_mu_4+rv_mu_5)/($G33+$H33)+dr_mu/100*4 -> 0.1531191 | Z36: =(rv_mu_4+rv_mu_5)/($G33+$H33)+dr_mu/100*4 -> 0.1531191 | AB36: 2026Q3–Q4＝1H26 實績份額；2027 起每年＋年變動
A37: 份額：Kioxia | B37: % | C37: =rv_kx_0/C33 -> 0.14842893 | D37: =rv_kx_1/D33 -> 0.13539615 | E37: =rv_kx_2/E33 -> 0.1511345 | F37: =rv_kx_3/F33 -> 0.14042424 | G37: =rv_kx_4/G33 -> 0.13559383 | H37: =rv_kx_5/H33 -> 0.13620815 | I37: =kx_g/kx_fxg/kx_k/$I33 -> 0.14490434 | J37: =(kx_g/kx_fxg/kx_k/$I33+kx_g4/kx_fxg4/kx_k/$J33)/2 -> 0.13851299 | K37: =(kx_g/kx_fxg/kx_k/$I33+kx_g4/kx_fxg4/kx_k/$J33)/2+dr_jv_A/100*1*(kx_g/kx_fxg/kx_k)/(kx_g/kx_fxg/kx_k+sd_g/sd_k) -> 0.13851299 | L37: =(kx_g/kx_fxg/kx_k/$I33+kx_g4/kx_fxg4/kx_k/$J33)/2+dr_jv_A/100*1*(kx_g/kx_fxg/kx_k)/(kx_g/kx_fxg/kx_k+sd_g/sd_k) -> 0.13851299 | M37: =(kx_g/kx_fxg/kx_k/$I33+kx_g4/kx_fxg4/kx_k/$J33)/2+dr_jv_A/100*1*(kx_g/kx_fxg/kx_k)/(kx_g/kx_fxg/kx_k+sd_g/sd_k) -> 0.13851299 | N37: =(kx_g/kx_fxg/kx_k/$I33+kx_g4/kx_fxg4/kx_k/$J33)/2+dr_jv_A/100*1*(kx_g/kx_fxg/kx_k)/(kx_g/kx_fxg/kx_k+sd_g/sd_k) -> 0.13851299 | O37: =(kx_g/kx_fxg/kx_k/$I33+kx_g4/kx_fxg4/kx_k/$J33)/2+dr_jv_A/100*2*(kx_g/kx_fxg/kx_k)/(kx_g/kx_fxg/kx_k+sd_g/sd_k) -> 0.13851299 | P37: =(kx_g/kx_fxg/kx_k/$I33+kx_g4/kx_fxg4/kx_k/$J33)/2+dr_jv_A/100*2*(kx_g/kx_fxg/kx_k)/(kx_g/kx_fxg/kx_k+sd_g/sd_k) -> 0.13851299 | Q37: =(kx_g/kx_fxg/kx_k/$I33+kx_g4/kx_fxg4/kx_k/$J33)/2+dr_jv_A/100*2*(kx_g/kx_fxg/kx_k)/(kx_g/kx_fxg/kx_k+sd_g/sd_k) -> 0.13851299 | R37: =(kx_g/kx_fxg/kx_k/$I33+kx_g4/kx_fxg4/kx_k/$J33)/2+dr_jv_A/100*2*(kx_g/kx_fxg/kx_k)/(kx_g/kx_fxg/kx_k+sd_g/sd_k) -> 0.13851299 | S37: =(kx_g/kx_fxg/kx_k/$I33+kx_g4/kx_fxg4/kx_k/$J33)/2+dr_jv_A/100*3*(kx_g/kx_fxg/kx_k)/(kx_g/kx_fxg/kx_k+sd_g/sd_k) -> 0.13851299 | T37: =(kx_g/kx_fxg/kx_k/$I33+kx_g4/kx_fxg4/kx_k/$J33)/2+dr_jv_A/100*3*(kx_g/kx_fxg/kx_k)/(kx_g/kx_fxg/kx_k+sd_g/sd_k) -> 0.13851299 | U37: =(kx_g/kx_fxg/kx_k/$I33+kx_g4/kx_fxg4/kx_k/$J33)/2+dr_jv_A/100*3*(kx_g/kx_fxg/kx_k)/(kx_g/kx_fxg/kx_k+sd_g/sd_k) -> 0.13851299 | V37: =(kx_g/kx_fxg/kx_k/$I33+kx_g4/kx_fxg4/kx_k/$J33)/2+dr_jv_A/100*3*(kx_g/kx_fxg/kx_k)/(kx_g/kx_fxg/kx_k+sd_g/sd_k) -> 0.13851299 | W37: =(kx_g/kx_fxg/kx_k/$I33+kx_g4/kx_fxg4/kx_k/$J33)/2+dr_jv_A/100*4*(kx_g/kx_fxg/kx_k)/(kx_g/kx_fxg/kx_k+sd_g/sd_k) -> 0.13851299 | X37: =(kx_g/kx_fxg/kx_k/$I33+kx_g4/kx_fxg4/kx_k/$J33)/2+dr_jv_A/100*4*(kx_g/kx_fxg/kx_k)/(kx_g/kx_fxg/kx_k+sd_g/sd_k) -> 0.13851299 | Y37: =(kx_g/kx_fxg/kx_k/$I33+kx_g4/kx_fxg4/kx_k/$J33)/2+dr_jv_A/100*4*(kx_g/kx_fxg/kx_k)/(kx_g/kx_fxg/kx_k+sd_g/sd_k) -> 0.13851299 | Z37: =(kx_g/kx_fxg/kx_k/$I33+kx_g4/kx_fxg4/kx_k/$J33)/2+dr_jv_A/100*4*(kx_g/kx_fxg/kx_k)/(kx_g/kx_fxg/kx_k+sd_g/sd_k) -> 0.13851299 | AB37: 2026Q3＝公司第二季實績 ÷ 匯率 ÷ 公司口徑係數 ÷ 市場；2026Q4 起＝2026Q3 實績份額與 2026Q4 指引份額的平均（平滑出貨季別移動）；2027 起＋合資群年變動 × Kioxia 比重
A38: 份額：SanDisk | B38: % | C38: =rv_sd_0/C33 -> 0.13064838 | D38: =rv_sd_1/D33 -> 0.12021154 | E38: =rv_sd_2/E33 -> 0.12292982 | F38: =rv_sd_3/F33 -> 0.12854545 | G38: =rv_sd_4/G33 -> 0.13536632 | H38: =rv_sd_5/H33 -> 0.11397268 | I38: =sd_g/sd_k/$I33 -> 0.10696926 | J38: =(sd_g/sd_k/$I33+sd_g4/sd_k/$J33)/2 -> 0.10651367 | K38: =(sd_g/sd_k/$I33+sd_g4/sd_k/$J33)/2+dr_jv_A/100*1*(sd_g/sd_k)/(kx_g/kx_fxg/kx_k+sd_g/sd_k) -> 0.10651367 | L38: =(sd_g/sd_k/$I33+sd_g4/sd_k/$J33)/2+dr_jv_A/100*1*(sd_g/sd_k)/(kx_g/kx_fxg/kx_k+sd_g/sd_k) -> 0.10651367 | M38: =(sd_g/sd_k/$I33+sd_g4/sd_k/$J33)/2+dr_jv_A/100*1*(sd_g/sd_k)/(kx_g/kx_fxg/kx_k+sd_g/sd_k) -> 0.10651367 | N38: =(sd_g/sd_k/$I33+sd_g4/sd_k/$J33)/2+dr_jv_A/100*1*(sd_g/sd_k)/(kx_g/kx_fxg/kx_k+sd_g/sd_k) -> 0.10651367 | O38: =(sd_g/sd_k/$I33+sd_g4/sd_k/$J33)/2+dr_jv_A/100*2*(sd_g/sd_k)/(kx_g/kx_fxg/kx_k+sd_g/sd_k) -> 0.10651367 | P38: =(sd_g/sd_k/$I33+sd_g4/sd_k/$J33)/2+dr_jv_A/100*2*(sd_g/sd_k)/(kx_g/kx_fxg/kx_k+sd_g/sd_k) -> 0.10651367 | Q38: =(sd_g/sd_k/$I33+sd_g4/sd_k/$J33)/2+dr_jv_A/100*2*(sd_g/sd_k)/(kx_g/kx_fxg/kx_k+sd_g/sd_k) -> 0.10651367 | R38: =(sd_g/sd_k/$I33+sd_g4/sd_k/$J33)/2+dr_jv_A/100*2*(sd_g/sd_k)/(kx_g/kx_fxg/kx_k+sd_g/sd_k) -> 0.10651367 | S38: =(sd_g/sd_k/$I33+sd_g4/sd_k/$J33)/2+dr_jv_A/100*3*(sd_g/sd_k)/(kx_g/kx_fxg/kx_k+sd_g/sd_k) -> 0.10651367 | T38: =(sd_g/sd_k/$I33+sd_g4/sd_k/$J33)/2+dr_jv_A/100*3*(sd_g/sd_k)/(kx_g/kx_fxg/kx_k+sd_g/sd_k) -> 0.10651367 | U38: =(sd_g/sd_k/$I33+sd_g4/sd_k/$J33)/2+dr_jv_A/100*3*(sd_g/sd_k)/(kx_g/kx_fxg/kx_k+sd_g/sd_k) -> 0.10651367 | V38: =(sd_g/sd_k/$I33+sd_g4/sd_k/$J33)/2+dr_jv_A/100*3*(sd_g/sd_k)/(kx_g/kx_fxg/kx_k+sd_g/sd_k) -> 0.10651367 | W38: =(sd_g/sd_k/$I33+sd_g4/sd_k/$J33)/2+dr_jv_A/100*4*(sd_g/sd_k)/(kx_g/kx_fxg/kx_k+sd_g/sd_k) -> 0.10651367 | X38: =(sd_g/sd_k/$I33+sd_g4/sd_k/$J33)/2+dr_jv_A/100*4*(sd_g/sd_k)/(kx_g/kx_fxg/kx_k+sd_g/sd_k) -> 0.10651367 | Y38: =(sd_g/sd_k/$I33+sd_g4/sd_k/$J33)/2+dr_jv_A/100*4*(sd_g/sd_k)/(kx_g/kx_fxg/kx_k+sd_g/sd_k) -> 0.10651367 | Z38: =(sd_g/sd_k/$I33+sd_g4/sd_k/$J33)/2+dr_jv_A/100*4*(sd_g/sd_k)/(kx_g/kx_fxg/kx_k+sd_g/sd_k) -> 0.10651367 | AB38: 2026Q3＝公司 FQ1 FY27 實績 ÷ 口徑係數 ÷ 市場；2026Q4 起＝2026Q3 實績份額與 FQ2 FY27 指引份額的平均；2027 起＋合資群年變動 × SanDisk 比重
A39: 份額：其他（長江存儲等） | B39: % | C39: =1-t5_0 -> 0.07 | D39: =1-t5_1 -> 0.071207692 | E39: =1-t5_2 -> 0.09 | F39: =1-t5_3 -> 0.10145455 | G39: =1-t5_4 -> 0.115 | H39: =1-t5_5 -> 0.12493886 | I39: =1-I34-I35-I36-I37-I38 -> 0.12713079 | J39: =1-J34-J35-J36-J37-J38 -> 0.13397774 | K39: =1-K34-K35-K36-K37-K38 -> 0.13697774 | L39: =1-L34-L35-L36-L37-L38 -> 0.13697774 | M39: =1-M34-M35-M36-M37-M38 -> 0.13697774 | N39: =1-N34-N35-N36-N37-N38 -> 0.13697774 | O39: =1-O34-O35-O36-O37-O38 -> 0.13997774 | P39: =1-P34-P35-P36-P37-P38 -> 0.13997774 | ... Z39: =1-Z34-Z35-Z36-Z37-Z38 -> 0.14597774 | AB39: 餘額（長江存儲等）
A40: 三星 營收（情境 A） | B40: $B | C40: =C33*C34 -> 4.2 | D40: =D33*D34 -> 5.2 | E40: =E33*E34 -> 6 | F40: =F33*F34 -> 6.6 | G40: =G33*G34 -> 13.51 | H40: =H33*H34 -> 23.06 | I40: =I33*I34 -> 30.762921 | J40: =J33*J34 -> 34.877842 | ... Z40: =Z33*Z34 -> 40.895674
A41: SK 海力士＋Solidigm 營收（情境 A） | B41: $B | C41: =C33*C35 -> 2.19 | D41: =D33*D35 -> 3.34 | E41: =E33*E35 -> 3.53 | F41: =F33*F35 -> 5.21 | G41: =G33*G35 -> 7.53 | H41: =H33*H35 -> 14.27 | I41: =I33*I35 -> 18.338301 | J41: =J33*J35 -> 20.791276 | ... Z41: =Z33*Z35 -> 26.131542
A42: 美光 營收（情境 A） | B42: $B | C42: =C33*C36 -> 2.03 | D42: =D33*D36 -> 2.1 | E42: =E33*E36 -> 2.42 | F42: =F33*F36 -> 3.03 | G42: =G33*G36 -> 5.95 | H42: =H33*H36 -> 11.85 | I42: =I33*I36 -> 14.973475 | J42: =J33*J36 -> 16.976363 | ... Z42: =Z33*Z36 -> 22.512998
A43: Kioxia 營收（情境 A） | B43: $B | C43: =C33*C37 -> 1.92 | D43: =D33*D37 -> 2.14 | E43: =E33*E37 -> 2.84 | F43: =F33*F37 -> 3.31 | G43: =G33*G37 -> 5.96 | H43: =H33*H37 -> 10.72 | I43: =I33*I37 -> 14.951317 | J43: =J33*J37 -> 16.203565 | ... Z43: =Z33*Z37 -> 20.365471
A44: SanDisk 營收（情境 A） | B44: $B | C44: =C33*C38 -> 1.69 | D44: =D33*D38 -> 1.9 | E44: =E33*E38 -> 2.31 | F44: =F33*F38 -> 3.03 | G44: =G33*G38 -> 5.95 | H44: =H33*H38 -> 8.97 | I44: =I33*I38 -> 11.037152 | J44: =J33*J38 -> 12.460212 | ... Z44: =Z33*Z38 -> 15.660633
A45: 其他（長江存儲等） 營收（情境 A） | B45: $B | C45: =C33*C39 -> 0.90548387 | D45: =D33*D39 -> 1.1254711 | E45: =E33*E39 -> 1.6912088 | F45: =F33*F39 -> 2.3914286 | G45: =G33*G39 -> 5.0548023 | H45: =H33*H39 -> 9.8330717 | I45: =I33*I39 -> 13.117431 | J45: =J33*J39 -> 15.673022 | ... Z45: =Z33*Z39 -> 21.463009
A46: Kioxia＋SanDisk（合資群）份額（情境 A） | B46: % | C46: =C37+C38 -> 0.27907731 | D46: =D37+D38 -> 0.25560769 | E46: =E37+E38 -> 0.27406433 | F46: =F37+F38 -> 0.2689697 | G46: =G37+G38 -> 0.27096015 | H46: =H37+H38 -> 0.25018083 | I46: =I37+I38 -> 0.25187361 | J46: =J37+J38 -> 0.24502666 | ... Z46: =Z37+Z38 -> 0.24502666
A47: Kioxia 位元（情境 A；季度出貨 × 營收份額） | B47: EB | C47: =C32*C37 -> 35.545444 | D47: =D32*D37 -> 33.356174 | E47: =E32*E37 -> 38.303462 | F47: =F32*F37 -> 36.611793 | G47: =G32*G37 -> 38.133315 | H47: =H32*H37 -> 40.175758 | I47: =I32*I37 -> 44.826902 | J47: =J32*J37 -> 44.941148 | ... Z47: =Z32*Z37 -> 97.818331 | AB47: 假設該廠平均售價＝市場平均（份額以營收計）；公司模型以此列的變動率推單位成本
A48: SanDisk 位元（情境 A；季度出貨 × 營收份額） | B48: EB | C48: =C32*C38 -> 31.287396 | D48: =D32*D38 -> 29.615294 | E48: =E32*E38 -> 31.15528 | F48: =F32*F38 -> 33.514723 | G48: =G32*G38 -> 38.069333 | H48: =H32*H38 -> 33.617215 | I48: =I32*I38 -> 33.091489 | J48: =J32*J38 -> 34.558829 | ... Z48: =Z32*Z38 -> 75.220307
A49: 檢查：份額合計 − 1；實績季營收重現（應為 0） | B49: — | C49: =ABS(SUM(C34:C39)-1)+ABS(SUM(I34:I39)-1)+ABS(SUM(Z34:Z39)-1)+ABS(H44-rv_sd_5) -> 0
A52: 情境 B（平平）：價格路徑 B（2027 Q2 見頂、2028 回落約一半、2029 溫和回升（Citi、Bernstein 型））；2028–29 顆數 × 0.8／0.85；合資群份額年變動 dr_jv_B
A53: A. 年度（日曆年） | B53: 單位 | C53: CY2024 | D53: CY2025 | E53: CY2026 | F53: CY2027 | G53: CY2028 | H53: CY2029 | I53: CY2030 | AB53: 說明
A54: 加速器顆數（同字母情境係數） | B54: 百萬顆 | E54: =(u_26)*1 -> 15.2 | F54: =(u_27)*1 -> 23.7 | G54: =(u_28)*um28_B -> 21.2 | H54: =(u_28*(1+g_u29))*um29_B -> 25.6275 | I54: =(u_28*(1+g_u29)*(1+g_u30))*um29_B -> 26.908875 | AB54: markets/memory UNITS × SCEN_UNITS；2029–30 基準以 g_u29、g_u30 外推，CY2030 沿用 um29
A55: 每顆企業級 SSD 容量 | B55: TB | E55: =tb_26 -> 30 | F55: =tb_27 -> 34 | G55: =tb_28 -> 40 | H55: =tb_29 -> 46 | I55: =tb_30 -> 52
A56: 需求：AI 企業級 SSD | B56: EB | D56: =bits25*sh_essd25*ai25 -> 165 | E56: =E54*E55 -> 456 | F56: =F54*F55 -> 805.8 | G56: =G54*G55 -> 848 | H56: =H54*H55 -> 1178.865 | I56: =I54*I55 -> 1399.2615 | AB56: 顆數 × 每顆容量（百萬顆 × TB＝EB）；2025＝基期 × 占比
A57: 需求：非 AI 企業級 SSD | B57: EB | D57: =bits25*sh_essd25*(1-ai25) -> 135 | E57: =D57*(1+g_nai) -> 148.5 | F57: =E57*(1+g_nai) -> 163.35 | G57: =F57*(1+g_nai) -> 179.685 | H57: =G57*(1+g_nai) -> 197.6535 | I57: =H57*(1+g_nai) -> 217.41885
A58: 需求：手機 | B58: EB | D58: =bits25*sh_mob25 -> 320 | E58: =D58*(1+g_mob_26) -> 304 | F58: =E58*(1+g_mob_27) -> 313.12 | G58: =F58*(1+g_mob_28) -> 338.1696 | H58: =G58*(1+g_mob_28) -> 365.22317 | I58: =H58*(1+g_mob_28) -> 394.44102
A59: 需求：PC（client SSD） | B59: EB | D59: =bits25*sh_pc25 -> 230 | E59: =D59*(1+g_pc_26) -> 218.5 | F59: =E59*(1+g_pc_27) -> 218.5 | G59: =F59*(1+g_pc_28) -> 231.61 | H59: =G59*(1+g_pc_28) -> 245.5066 | I59: =H59*(1+g_pc_28) -> 260.237
A60: 需求：消費性與其他 | B60: EB | D60: =bits25*(1-sh_essd25-sh_mob25-sh_pc25) -> 150 | E60: =D60*(1+g_con_26) -> 135 | F60: =E60*(1+g_con_27) -> 135 | G60: =F60*(1+g_con_28) -> 141.75 | H60: =G60*(1+g_con_28) -> 148.8375 | I60: =H60*(1+g_con_28) -> 156.27937
A61: 位元需求合計 | B61: EB | D61: =SUM(D56:D60) -> 1000 | E61: =SUM(E56:E60) -> 1262 | F61: =SUM(F56:F60) -> 1635.77 | G61: =SUM(G56:G60) -> 1739.2146 | H61: =SUM(H56:H60) -> 2136.0858 | I61: =SUM(I56:I60) -> 2427.6377
A62: 企業級 SSD 占位元需求 | B62: % | D62: =(D56+D57)/D61 -> 0.3 | E62: =(E56+E57)/E61 -> 0.47900158 | F62: =(F56+F57)/F61 -> 0.59247327 | G62: =(G56+G57)/G61 -> 0.59089028 | H62: =(H56+H57)/H61 -> 0.64441162 | I62: =(I56+I57)/I61 -> 0.66594794
A63: 位元供給（三情境相同） | B63: EB | D63: =bits25 -> 1000 | E63: =D63*(1+gs_26) -> 1210 | F63: =E63*(1+gs_27) -> 1512.5 | G63: =F63*(1+gs_28) -> 1890.625 | H63: =G63*(1+gs_29) -> 2306.5625 | I63: =H63*(1+gs_30) -> 2767.875 | AB63: 2025＝出貨實績（基期）；供給不隨需求情境變（產能 2027 前已訂定），需求不足的結果是閒置產能與降價
A64: 需求 ÷ 供給 − 1（>0＝短缺） | B64: % | E64: =E61/E63-1 -> 0.042975207 | F64: =F61/F63-1 -> 0.081500826 | G64: =G61/G63-1 -> -0.08008484 | H64: =H61/H63-1 -> -0.073909435 | I64: =I61/I63-1 -> -0.12292364
A65: 位元出貨＝MIN(需求, 供給) | B65: EB | C65: =bits25/(1+g25) -> 892.85714 | D65: =bits25 -> 1000 | E65: =MIN(E61,E63) -> 1210 | F65: =MIN(F61,F63) -> 1512.5 | G65: =MIN(G61,G63) -> 1739.2146 | H65: =MIN(H61,H63) -> 2136.0858 | I65: =MIN(I61,I63) -> 2427.6377
A66: 位元出貨年增 | B66: % | D66: =D65/C65-1 -> 0.12 | E66: =E65/D65-1 -> 0.21 | F66: =F65/E65-1 -> 0.25 | G66: =G65/F65-1 -> 0.14989395 | H66: =H65/G65-1 -> 0.22818988 | I66: =I65/H65-1 -> 0.13648889
A67: NAND 市場營收（四季合計） | B67: $B | C67: =rev24 -> 67.4 | D67: =SUM(C81:F81) -> 71.103592 | E67: =SUM(G81:J81) -> 342.82075 | F67: =SUM(K81:N81) -> 522.07288 | G67: =SUM(O81:R81) -> 242.30569 | H67: =SUM(S81:V81) -> 250.74278 | I67: =SUM(W81:Z81) -> 275.32213 | AB67: CY2024 為 TrendForce 年度值
A68: 市場營收年增 | B68: % | D68: =D67/C67-1 -> 0.054949442 | E68: =E67/D67-1 -> 3.8214266 | F68: =F67/E67-1 -> 0.52287423 | G68: =G67/F67-1 -> -0.53587766 | H68: =H67/G67-1 -> 0.034820008 | I68: =I67/H67-1 -> 0.098026152
A69: 平均售價（營收 ÷ 位元出貨） | B69: $/GB | C69: =C67/C65 -> 0.075488 | D69: =D67/D65 -> 0.071103592 | E69: =E67/E65 -> 0.28332293 | F69: =F67/F65 -> 0.34517215 | G69: =G67/G65 -> 0.13931903 | H69: =H67/H65 -> 0.11738423 | I69: =I67/I65 -> 0.11341154
A70: 平均售價年變動 | B70: % | D70: =D69/C69-1 -> -0.058080856 | E70: =E69/D69-1 -> 2.9846501 | F70: =F69/E69-1 -> 0.21829938 | G70: =G69/F69-1 -> -0.59637813 | H70: =H69/G69-1 -> -0.15744298 | I70: =I69/H69-1 -> -0.033843479 | AB70: CY2030 為收斂法（p10）＋位元平滑效果
A71: 年度份額：三星 | B71: % | D71: =SUM(C88:F88)/D67 -> 0.30940771 | E71: =SUM(G88:J88)/E67 -> 0.29814637 | F71: =SUM(K88:N88)/F67 -> 0.29314637 | G71: =SUM(O88:R88)/G67 -> 0.28814637 | H71: =SUM(S88:V88)/H67 -> 0.28314637 | I71: =SUM(W88:Z88)/I67 -> 0.27814637
A72: 年度份額：SK 海力士＋Solidigm | B72: % | D72: =SUM(C89:F89)/D67 -> 0.20069309 | E72: =SUM(G89:J89)/E67 -> 0.17773013 | F72: =SUM(K89:N89)/F67 -> 0.17773013 | G72: =SUM(O89:R89)/G67 -> 0.17773013 | H72: =SUM(S89:V89)/H67 -> 0.17773013 | I72: =SUM(W89:Z89)/I67 -> 0.17773013
A73: 年度份額：美光 | B73: % | D73: =SUM(C90:F90)/D67 -> 0.134733 | E73: =SUM(G90:J90)/E67 -> 0.1451191 | F73: =SUM(K90:N90)/F67 -> 0.1471191 | G73: =SUM(O90:R90)/G67 -> 0.1491191 | H73: =SUM(S90:V90)/H67 -> 0.1511191 | I73: =SUM(W90:Z90)/I67 -> 0.1531191
A74: 年度份額：Kioxia | B74: % | D74: =SUM(C91:F91)/D67 -> 0.14359331 | E74: =SUM(G91:J91)/E67 -> 0.13953322 | F74: =SUM(K91:N91)/F67 -> 0.13678707 | G74: =SUM(O91:R91)/G67 -> 0.13506115 | H74: =SUM(S91:V91)/H67 -> 0.13333524 | I74: =SUM(W91:Z91)/I67 -> 0.13160932
A75: 年度份額：SanDisk | B75: % | D75: =SUM(C92:F92)/D67 -> 0.1255914 | E75: =SUM(G92:J92)/E67 -> 0.11206254 | F75: =SUM(K92:N92)/F67 -> 0.10523959 | G75: =SUM(O92:R92)/G67 -> 0.10396551 | H75: =SUM(S92:V92)/H67 -> 0.10269142 | I75: =SUM(W92:Z92)/I67 -> 0.10141734
A76: 年度份額：其他（長江存儲等） | B76: % | D76: =SUM(C93:F93)/D67 -> 0.085981484 | E76: =SUM(G93:J93)/E67 -> 0.12740864 | F76: =SUM(K93:N93)/F67 -> 0.13997774 | G76: =SUM(O93:R93)/G67 -> 0.14597774 | H76: =SUM(S93:V93)/H67 -> 0.15197774 | I76: =SUM(W93:Z93)/I67 -> 0.15797774
A78: B. 季度 | B78: 單位 | C78: 2025Q1 | D78: 2025Q2 | E78: 2025Q3 | F78: 2025Q4 | G78: 2026Q1 | H78: 2026Q2 | I78: 2026Q3 | J78: 2026Q4 | K78: 2027Q1 | L78: 2027Q2 | M78: 2027Q3 | N78: 2027Q4 | O78: 2028Q1 | P78: 2028Q2 | Q78: 2028Q3 | R78: 2028Q4 | S78: 2029Q1 | T78: 2029Q2 | U78: 2029Q3 | V78: 2029Q4 | W78: 2030Q1 | X78: 2030Q2 | Y78: 2030Q3 | Z78: 2030Q4 | AB78: 說明
A79: 合約價指數（同字母路徑） | B79: 2025Q1＝1 | C79: =Path!C5 -> 1 | D79: =Path!D5 -> 1 | E79: =Path!E5 -> 1.05 | F79: =Path!F5 -> 1.365 | G79: =Path!G5 -> 2.559375 | H79: =Path!H5 -> 4.4149219 | I79: =Path!I5 -> 5.5186523 | J79: =Path!J5 -> 5.9656632 | K79: =Path!K5*1 -> 6.2639463 | L79: =Path!L5*1 -> 6.3892253 | M79: =Path!M5*1 -> 5.7503027 | N79: =Path!N5*1 -> 4.6002422 | O79: =Path!O5*1 -> 3.2201695 | P79: =Path!P5*1 -> 2.4151272 | Q79: =Path!Q5*1 -> 1.9321017 | R79: =Path!R5*1 -> 1.7388915 | ... V79: =Path!V5*1 -> 2.033881 | W79: =Path!V5*(1+p10)^(1/4)*1 -> 1.9699092 | X79: =Path!V5*(1+p10)^(2/4)*1 -> 1.9079495 | Y79: =Path!V5*(1+p10)^(3/4)*1 -> 1.8479386 | Z79: =Path!V5*(1+p10)^(4/4)*1 -> 1.7898153 | AB79: Path 頁；Sens 可對 2027 起的季價乘價格係數
A80: 季度位元出貨（年內依年增平滑；四季合計＝年度） | B80: EB | C80: =D65/4*(D65/C65)^((1-2.5)/4)/(((D65/C65)^(-0.375)+(D65/C65)^(-0.125)+(D65/C65)^(0.125)+(D65/C65)^(0.375))/4) -> 239.47787 | D80: =D65/4*(D65/C65)^((2-2.5)/4)/(((D65/C65)^(-0.375)+(D65/C65)^(-0.125)+(D65/C65)^(0.125)+(D65/C65)^(0.375))/4) -> 246.35983 | E80: =D65/4*(D65/C65)^((3-2.5)/4)/(((D65/C65)^(-0.375)+(D65/C65)^(-0.125)+(D65/C65)^(0.125)+(D65/C65)^(0.375))/4) -> 253.43956 | F80: =D65/4*(D65/C65)^((4-2.5)/4)/(((D65/C65)^(-0.375)+(D65/C65)^(-0.125)+(D65/C65)^(0.125)+(D65/C65)^(0.375))/4) -> 260.72274 | G80: =E65/4*(E65/D65)^((1-2.5)/4)/(((E65/D65)^(-0.375)+(E65/D65)^(-0.125)+(E65/D65)^(0.125)+(E65/D65)^(0.375))/4) -> 281.23193 | H80: =E65/4*(E65/D65)^((2-2.5)/4)/(((E65/D65)^(-0.375)+(E65/D65)^(-0.125)+(E65/D65)^(0.125)+(E65/D65)^(0.375))/4) -> 294.95854 | I80: =E65/4*(E65/D65)^((3-2.5)/4)/(((E65/D65)^(-0.375)+(E65/D65)^(-0.125)+(E65/D65)^(0.125)+(E65/D65)^(0.375))/4) -> 309.35513 | J80: =E65/4*(E65/D65)^((4-2.5)/4)/(((E65/D65)^(-0.375)+(E65/D65)^(-0.125)+(E65/D65)^(0.125)+(E65/D65)^(0.375))/4) -> 324.4544 | K80: =F65/4*(F65/E65)^((1-2.5)/4)/(((F65/E65)^(-0.375)+(F65/E65)^(-0.125)+(F65/E65)^(0.125)+(F65/E65)^(0.375))/4) -> 347.09614 | L80: =F65/4*(F65/E65)^((2-2.5)/4)/(((F65/E65)^(-0.375)+(F65/E65)^(-0.125)+(F65/E65)^(0.125)+(F65/E65)^(0.375))/4) -> 367.00949 | M80: =F65/4*(F65/E65)^((3-2.5)/4)/(((F65/E65)^(-0.375)+(F65/E65)^(-0.125)+(F65/E65)^(0.125)+(F65/E65)^(0.375))/4) -> 388.06529 | N80: =F65/4*(F65/E65)^((4-2.5)/4)/(((F65/E65)^(-0.375)+(F65/E65)^(-0.125)+(F65/E65)^(0.125)+(F65/E65)^(0.375))/4) -> 410.32908 | O80: =G65/4*(G65/F65)^((1-2.5)/4)/(((G65/F65)^(-0.375)+(G65/F65)^(-0.125)+(G65/F65)^(0.125)+(G65/F65)^(0.375))/4) -> 412.30218 | P80: =G65/4*(G65/F65)^((2-2.5)/4)/(((G65/F65)^(-0.375)+(G65/F65)^(-0.125)+(G65/F65)^(0.125)+(G65/F65)^(0.375))/4) -> 426.95301 | Q80: =G65/4*(G65/F65)^((3-2.5)/4)/(((G65/F65)^(-0.375)+(G65/F65)^(-0.125)+(G65/F65)^(0.125)+(G65/F65)^(0.375))/4) -> 442.12444 | R80: =G65/4*(G65/F65)^((4-2.5)/4)/(((G65/F65)^(-0.375)+(G65/F65)^(-0.125)+(G65/F65)^(0.125)+(G65/F65)^(0.375))/4) -> 457.83498 | S80: =H65/4*(H65/G65)^((1-2.5)/4)/(((H65/G65)^(-0.375)+(H65/G65)^(-0.125)+(H65/G65)^(0.125)+(H65/G65)^(0.375))/4) -> 493.59152 | T80: =H65/4*(H65/G65)^((2-2.5)/4)/(((H65/G65)^(-0.375)+(H65/G65)^(-0.125)+(H65/G65)^(0.125)+(H65/G65)^(0.375))/4) -> 519.61785 | U80: =H65/4*(H65/G65)^((3-2.5)/4)/(((H65/G65)^(-0.375)+(H65/G65)^(-0.125)+(H65/G65)^(0.125)+(H65/G65)^(0.375))/4) -> 547.01652 | V80: =H65/4*(H65/G65)^((4-2.5)/4)/(((H65/G65)^(-0.375)+(H65/G65)^(-0.125)+(H65/G65)^(0.125)+(H65/G65)^(0.375))/4) -> 575.85988 | W80: =I65/4*(I65/H65)^((1-2.5)/4)/(((I65/H65)^(-0.375)+(I65/H65)^(-0.125)+(I65/H65)^(0.125)+(I65/H65)^(0.375))/4) -> 578.1084 | X80: =I65/4*(I65/H65)^((2-2.5)/4)/(((I65/H65)^(-0.375)+(I65/H65)^(-0.125)+(I65/H65)^(0.125)+(I65/H65)^(0.375))/4) -> 596.89862 | Y80: =I65/4*(I65/H65)^((3-2.5)/4)/(((I65/H65)^(-0.375)+(I65/H65)^(-0.125)+(I65/H65)^(0.125)+(I65/H65)^(0.375))/4) -> 616.29959 | Z80: =I65/4*(I65/H65)^((4-2.5)/4)/(((I65/H65)^(-0.375)+(I65/H65)^(-0.125)+(I65/H65)^(0.125)+(I65/H65)^(0.375))/4) -> 636.33114 | AB80: 季度＝年度 ÷ 4 ×（1＋年增）^((季−2.5)/4)，再正規化使四季合計等於年度
A81: NAND 市場營收（2026Q2 前實績；之後＝2Q26 實績 × 價格指數比 × 位元比） | B81: $B | C81: =(rv_ss_0+rv_sk_0+rv_mu_0+rv_kx_0+rv_sd_0)/t5_0 -> 12.935484 | D81: =(rv_ss_1+rv_sk_1+rv_mu_1+rv_kx_1+rv_sd_1)/t5_1 -> 15.805471 | E81: =(rv_ss_2+rv_sk_2+rv_mu_2+rv_kx_2+rv_sd_2)/t5_2 -> 18.791209 | F81: =(rv_ss_3+rv_sk_3+rv_mu_3+rv_kx_3+rv_sd_3)/t5_3 -> 23.571429 | G81: =(rv_ss_4+rv_sk_4+rv_mu_4+rv_kx_4+rv_sd_4)/t5_4 -> 43.954802 | H81: =(rv_ss_5+rv_sk_5+rv_mu_5+rv_kx_5+rv_sd_5)/t5_5 -> 78.703072 | I81: =$H81*I79/$H79*I80/$H80 -> 103.1806 | J81: =$H81*J79/$H79*J80/$H80 -> 116.98228 | K81: =$H81*K79/$H79*K80/$H80 -> 131.40307 | L81: =$H81*L79/$H79*L80/$H80 -> 141.72066 | M81: =$H81*M79/$H79*M80/$H80 -> 134.86622 | N81: =$H81*N79/$H79*N80/$H80 -> 114.08293 | O81: =$H81*O79/$H79*O80/$H80 -> 80.242056 | P81: =$H81*P79/$H79*P80/$H80 -> 62.320045 | ... Z81: =$H81*Z79/$H79*Z80/$H80 -> 68.833376 | AB81: 實績＝TrendForce 前五大 ÷ 前五大占比；以 2Q26 為錨
A82: 份額：三星 | B82: % | C82: =rv_ss_0/C81 -> 0.32468828 | D82: =rv_ss_1/D81 -> 0.329 | E82: =rv_ss_2/E81 -> 0.31929825 | F82: =rv_ss_3/F81 -> 0.28 | G82: =rv_ss_4/G81 -> 0.30736118 | H82: =rv_ss_5/H81 -> 0.293 | I82: =(rv_ss_4+rv_ss_5)/($G81+$H81) -> 0.29814637 | J82: =(rv_ss_4+rv_ss_5)/($G81+$H81) -> 0.29814637 | K82: =(rv_ss_4+rv_ss_5)/($G81+$H81)+dr_ss/100*1 -> 0.29314637 | L82: =(rv_ss_4+rv_ss_5)/($G81+$H81)+dr_ss/100*1 -> 0.29314637 | M82: =(rv_ss_4+rv_ss_5)/($G81+$H81)+dr_ss/100*1 -> 0.29314637 | N82: =(rv_ss_4+rv_ss_5)/($G81+$H81)+dr_ss/100*1 -> 0.29314637 | O82: =(rv_ss_4+rv_ss_5)/($G81+$H81)+dr_ss/100*2 -> 0.28814637 | P82: =(rv_ss_4+rv_ss_5)/($G81+$H81)+dr_ss/100*2 -> 0.28814637 | Q82: =(rv_ss_4+rv_ss_5)/($G81+$H81)+dr_ss/100*2 -> 0.28814637 | R82: =(rv_ss_4+rv_ss_5)/($G81+$H81)+dr_ss/100*2 -> 0.28814637 | S82: =(rv_ss_4+rv_ss_5)/($G81+$H81)+dr_ss/100*3 -> 0.28314637 | T82: =(rv_ss_4+rv_ss_5)/($G81+$H81)+dr_ss/100*3 -> 0.28314637 | U82: =(rv_ss_4+rv_ss_5)/($G81+$H81)+dr_ss/100*3 -> 0.28314637 | V82: =(rv_ss_4+rv_ss_5)/($G81+$H81)+dr_ss/100*3 -> 0.28314637 | W82: =(rv_ss_4+rv_ss_5)/($G81+$H81)+dr_ss/100*4 -> 0.27814637 | X82: =(rv_ss_4+rv_ss_5)/($G81+$H81)+dr_ss/100*4 -> 0.27814637 | Y82: =(rv_ss_4+rv_ss_5)/($G81+$H81)+dr_ss/100*4 -> 0.27814637 | Z82: =(rv_ss_4+rv_ss_5)/($G81+$H81)+dr_ss/100*4 -> 0.27814637 | AB82: 2026Q3–Q4＝1H26 實績份額；2027 起每年＋年變動
A83: 份額：SK 海力士＋Solidigm | B83: % | C83: =rv_sk_0/C81 -> 0.16930175 | D83: =rv_sk_1/D81 -> 0.21131923 | E83: =rv_sk_2/E81 -> 0.1878538 | F83: =rv_sk_3/F81 -> 0.2210303 | G83: =rv_sk_4/G81 -> 0.17131234 | H83: =rv_sk_5/H81 -> 0.1813144 | I83: =(rv_sk_4+rv_sk_5)/($G81+$H81) -> 0.17773013 | J83: =(rv_sk_4+rv_sk_5)/($G81+$H81) -> 0.17773013 | K83: =(rv_sk_4+rv_sk_5)/($G81+$H81)+dr_sk/100*1 -> 0.17773013 | L83: =(rv_sk_4+rv_sk_5)/($G81+$H81)+dr_sk/100*1 -> 0.17773013 | M83: =(rv_sk_4+rv_sk_5)/($G81+$H81)+dr_sk/100*1 -> 0.17773013 | N83: =(rv_sk_4+rv_sk_5)/($G81+$H81)+dr_sk/100*1 -> 0.17773013 | O83: =(rv_sk_4+rv_sk_5)/($G81+$H81)+dr_sk/100*2 -> 0.17773013 | P83: =(rv_sk_4+rv_sk_5)/($G81+$H81)+dr_sk/100*2 -> 0.17773013 | Q83: =(rv_sk_4+rv_sk_5)/($G81+$H81)+dr_sk/100*2 -> 0.17773013 | R83: =(rv_sk_4+rv_sk_5)/($G81+$H81)+dr_sk/100*2 -> 0.17773013 | S83: =(rv_sk_4+rv_sk_5)/($G81+$H81)+dr_sk/100*3 -> 0.17773013 | T83: =(rv_sk_4+rv_sk_5)/($G81+$H81)+dr_sk/100*3 -> 0.17773013 | U83: =(rv_sk_4+rv_sk_5)/($G81+$H81)+dr_sk/100*3 -> 0.17773013 | V83: =(rv_sk_4+rv_sk_5)/($G81+$H81)+dr_sk/100*3 -> 0.17773013 | W83: =(rv_sk_4+rv_sk_5)/($G81+$H81)+dr_sk/100*4 -> 0.17773013 | X83: =(rv_sk_4+rv_sk_5)/($G81+$H81)+dr_sk/100*4 -> 0.17773013 | Y83: =(rv_sk_4+rv_sk_5)/($G81+$H81)+dr_sk/100*4 -> 0.17773013 | Z83: =(rv_sk_4+rv_sk_5)/($G81+$H81)+dr_sk/100*4 -> 0.17773013 | AB83: 2026Q3–Q4＝1H26 實績份額；2027 起每年＋年變動
A84: 份額：美光 | B84: % | C84: =rv_mu_0/C81 -> 0.15693267 | D84: =rv_mu_1/D81 -> 0.13286538 | E84: =rv_mu_2/E81 -> 0.12878363 | F84: =rv_mu_3/F81 -> 0.12854545 | G84: =rv_mu_4/G81 -> 0.13536632 | H84: =rv_mu_5/H81 -> 0.15056592 | I84: =(rv_mu_4+rv_mu_5)/($G81+$H81) -> 0.1451191 | J84: =(rv_mu_4+rv_mu_5)/($G81+$H81) -> 0.1451191 | K84: =(rv_mu_4+rv_mu_5)/($G81+$H81)+dr_mu/100*1 -> 0.1471191 | L84: =(rv_mu_4+rv_mu_5)/($G81+$H81)+dr_mu/100*1 -> 0.1471191 | M84: =(rv_mu_4+rv_mu_5)/($G81+$H81)+dr_mu/100*1 -> 0.1471191 | N84: =(rv_mu_4+rv_mu_5)/($G81+$H81)+dr_mu/100*1 -> 0.1471191 | O84: =(rv_mu_4+rv_mu_5)/($G81+$H81)+dr_mu/100*2 -> 0.1491191 | P84: =(rv_mu_4+rv_mu_5)/($G81+$H81)+dr_mu/100*2 -> 0.1491191 | Q84: =(rv_mu_4+rv_mu_5)/($G81+$H81)+dr_mu/100*2 -> 0.1491191 | R84: =(rv_mu_4+rv_mu_5)/($G81+$H81)+dr_mu/100*2 -> 0.1491191 | S84: =(rv_mu_4+rv_mu_5)/($G81+$H81)+dr_mu/100*3 -> 0.1511191 | T84: =(rv_mu_4+rv_mu_5)/($G81+$H81)+dr_mu/100*3 -> 0.1511191 | U84: =(rv_mu_4+rv_mu_5)/($G81+$H81)+dr_mu/100*3 -> 0.1511191 | V84: =(rv_mu_4+rv_mu_5)/($G81+$H81)+dr_mu/100*3 -> 0.1511191 | W84: =(rv_mu_4+rv_mu_5)/($G81+$H81)+dr_mu/100*4 -> 0.1531191 | X84: =(rv_mu_4+rv_mu_5)/($G81+$H81)+dr_mu/100*4 -> 0.1531191 | Y84: =(rv_mu_4+rv_mu_5)/($G81+$H81)+dr_mu/100*4 -> 0.1531191 | Z84: =(rv_mu_4+rv_mu_5)/($G81+$H81)+dr_mu/100*4 -> 0.1531191 | AB84: 2026Q3–Q4＝1H26 實績份額；2027 起每年＋年變動
A85: 份額：Kioxia | B85: % | C85: =rv_kx_0/C81 -> 0.14842893 | D85: =rv_kx_1/D81 -> 0.13539615 | E85: =rv_kx_2/E81 -> 0.1511345 | F85: =rv_kx_3/F81 -> 0.14042424 | G85: =rv_kx_4/G81 -> 0.13559383 | H85: =rv_kx_5/H81 -> 0.13620815 | I85: =kx_g/kx_fxg/kx_k/$I81 -> 0.14490434 | J85: =(kx_g/kx_fxg/kx_k/$I81+kx_g4/kx_fxg4/kx_k/$J81)/2 -> 0.13851299 | K85: =(kx_g/kx_fxg/kx_k/$I81+kx_g4/kx_fxg4/kx_k/$J81)/2+dr_jv_B/100*1*(kx_g/kx_fxg/kx_k)/(kx_g/kx_fxg/kx_k+sd_g/sd_k) -> 0.13678707 | L85: =(kx_g/kx_fxg/kx_k/$I81+kx_g4/kx_fxg4/kx_k/$J81)/2+dr_jv_B/100*1*(kx_g/kx_fxg/kx_k)/(kx_g/kx_fxg/kx_k+sd_g/sd_k) -> 0.13678707 | M85: =(kx_g/kx_fxg/kx_k/$I81+kx_g4/kx_fxg4/kx_k/$J81)/2+dr_jv_B/100*1*(kx_g/kx_fxg/kx_k)/(kx_g/kx_fxg/kx_k+sd_g/sd_k) -> 0.13678707 | N85: =(kx_g/kx_fxg/kx_k/$I81+kx_g4/kx_fxg4/kx_k/$J81)/2+dr_jv_B/100*1*(kx_g/kx_fxg/kx_k)/(kx_g/kx_fxg/kx_k+sd_g/sd_k) -> 0.13678707 | O85: =(kx_g/kx_fxg/kx_k/$I81+kx_g4/kx_fxg4/kx_k/$J81)/2+dr_jv_B/100*2*(kx_g/kx_fxg/kx_k)/(kx_g/kx_fxg/kx_k+sd_g/sd_k) -> 0.13506115 | P85: =(kx_g/kx_fxg/kx_k/$I81+kx_g4/kx_fxg4/kx_k/$J81)/2+dr_jv_B/100*2*(kx_g/kx_fxg/kx_k)/(kx_g/kx_fxg/kx_k+sd_g/sd_k) -> 0.13506115 | Q85: =(kx_g/kx_fxg/kx_k/$I81+kx_g4/kx_fxg4/kx_k/$J81)/2+dr_jv_B/100*2*(kx_g/kx_fxg/kx_k)/(kx_g/kx_fxg/kx_k+sd_g/sd_k) -> 0.13506115 | R85: =(kx_g/kx_fxg/kx_k/$I81+kx_g4/kx_fxg4/kx_k/$J81)/2+dr_jv_B/100*2*(kx_g/kx_fxg/kx_k)/(kx_g/kx_fxg/kx_k+sd_g/sd_k) -> 0.13506115 | S85: =(kx_g/kx_fxg/kx_k/$I81+kx_g4/kx_fxg4/kx_k/$J81)/2+dr_jv_B/100*3*(kx_g/kx_fxg/kx_k)/(kx_g/kx_fxg/kx_k+sd_g/sd_k) -> 0.13333524 | T85: =(kx_g/kx_fxg/kx_k/$I81+kx_g4/kx_fxg4/kx_k/$J81)/2+dr_jv_B/100*3*(kx_g/kx_fxg/kx_k)/(kx_g/kx_fxg/kx_k+sd_g/sd_k) -> 0.13333524 | U85: =(kx_g/kx_fxg/kx_k/$I81+kx_g4/kx_fxg4/kx_k/$J81)/2+dr_jv_B/100*3*(kx_g/kx_fxg/kx_k)/(kx_g/kx_fxg/kx_k+sd_g/sd_k) -> 0.13333524 | V85: =(kx_g/kx_fxg/kx_k/$I81+kx_g4/kx_fxg4/kx_k/$J81)/2+dr_jv_B/100*3*(kx_g/kx_fxg/kx_k)/(kx_g/kx_fxg/kx_k+sd_g/sd_k) -> 0.13333524 | W85: =(kx_g/kx_fxg/kx_k/$I81+kx_g4/kx_fxg4/kx_k/$J81)/2+dr_jv_B/100*4*(kx_g/kx_fxg/kx_k)/(kx_g/kx_fxg/kx_k+sd_g/sd_k) -> 0.13160932 | X85: =(kx_g/kx_fxg/kx_k/$I81+kx_g4/kx_fxg4/kx_k/$J81)/2+dr_jv_B/100*4*(kx_g/kx_fxg/kx_k)/(kx_g/kx_fxg/kx_k+sd_g/sd_k) -> 0.13160932 | Y85: =(kx_g/kx_fxg/kx_k/$I81+kx_g4/kx_fxg4/kx_k/$J81)/2+dr_jv_B/100*4*(kx_g/kx_fxg/kx_k)/(kx_g/kx_fxg/kx_k+sd_g/sd_k) -> 0.13160932 | Z85: =(kx_g/kx_fxg/kx_k/$I81+kx_g4/kx_fxg4/kx_k/$J81)/2+dr_jv_B/100*4*(kx_g/kx_fxg/kx_k)/(kx_g/kx_fxg/kx_k+sd_g/sd_k) -> 0.13160932 | AB85: 2026Q3＝公司第二季實績 ÷ 匯率 ÷ 公司口徑係數 ÷ 市場；2026Q4 起＝2026Q3 實績份額與 2026Q4 指引份額的平均（平滑出貨季別移動）；2027 起＋合資群年變動 × Kioxia 比重
A86: 份額：SanDisk | B86: % | C86: =rv_sd_0/C81 -> 0.13064838 | D86: =rv_sd_1/D81 -> 0.12021154 | E86: =rv_sd_2/E81 -> 0.12292982 | F86: =rv_sd_3/F81 -> 0.12854545 | G86: =rv_sd_4/G81 -> 0.13536632 | H86: =rv_sd_5/H81 -> 0.11397268 | I86: =sd_g/sd_k/$I81 -> 0.10696926 | J86: =(sd_g/sd_k/$I81+sd_g4/sd_k/$J81)/2 -> 0.10651367 | K86: =(sd_g/sd_k/$I81+sd_g4/sd_k/$J81)/2+dr_jv_B/100*1*(sd_g/sd_k)/(kx_g/kx_fxg/kx_k+sd_g/sd_k) -> 0.10523959 | L86: =(sd_g/sd_k/$I81+sd_g4/sd_k/$J81)/2+dr_jv_B/100*1*(sd_g/sd_k)/(kx_g/kx_fxg/kx_k+sd_g/sd_k) -> 0.10523959 | M86: =(sd_g/sd_k/$I81+sd_g4/sd_k/$J81)/2+dr_jv_B/100*1*(sd_g/sd_k)/(kx_g/kx_fxg/kx_k+sd_g/sd_k) -> 0.10523959 | N86: =(sd_g/sd_k/$I81+sd_g4/sd_k/$J81)/2+dr_jv_B/100*1*(sd_g/sd_k)/(kx_g/kx_fxg/kx_k+sd_g/sd_k) -> 0.10523959 | O86: =(sd_g/sd_k/$I81+sd_g4/sd_k/$J81)/2+dr_jv_B/100*2*(sd_g/sd_k)/(kx_g/kx_fxg/kx_k+sd_g/sd_k) -> 0.10396551 | P86: =(sd_g/sd_k/$I81+sd_g4/sd_k/$J81)/2+dr_jv_B/100*2*(sd_g/sd_k)/(kx_g/kx_fxg/kx_k+sd_g/sd_k) -> 0.10396551 | Q86: =(sd_g/sd_k/$I81+sd_g4/sd_k/$J81)/2+dr_jv_B/100*2*(sd_g/sd_k)/(kx_g/kx_fxg/kx_k+sd_g/sd_k) -> 0.10396551 | R86: =(sd_g/sd_k/$I81+sd_g4/sd_k/$J81)/2+dr_jv_B/100*2*(sd_g/sd_k)/(kx_g/kx_fxg/kx_k+sd_g/sd_k) -> 0.10396551 | S86: =(sd_g/sd_k/$I81+sd_g4/sd_k/$J81)/2+dr_jv_B/100*3*(sd_g/sd_k)/(kx_g/kx_fxg/kx_k+sd_g/sd_k) -> 0.10269142 | T86: =(sd_g/sd_k/$I81+sd_g4/sd_k/$J81)/2+dr_jv_B/100*3*(sd_g/sd_k)/(kx_g/kx_fxg/kx_k+sd_g/sd_k) -> 0.10269142 | U86: =(sd_g/sd_k/$I81+sd_g4/sd_k/$J81)/2+dr_jv_B/100*3*(sd_g/sd_k)/(kx_g/kx_fxg/kx_k+sd_g/sd_k) -> 0.10269142 | V86: =(sd_g/sd_k/$I81+sd_g4/sd_k/$J81)/2+dr_jv_B/100*3*(sd_g/sd_k)/(kx_g/kx_fxg/kx_k+sd_g/sd_k) -> 0.10269142 | W86: =(sd_g/sd_k/$I81+sd_g4/sd_k/$J81)/2+dr_jv_B/100*4*(sd_g/sd_k)/(kx_g/kx_fxg/kx_k+sd_g/sd_k) -> 0.10141734 | X86: =(sd_g/sd_k/$I81+sd_g4/sd_k/$J81)/2+dr_jv_B/100*4*(sd_g/sd_k)/(kx_g/kx_fxg/kx_k+sd_g/sd_k) -> 0.10141734 | Y86: =(sd_g/sd_k/$I81+sd_g4/sd_k/$J81)/2+dr_jv_B/100*4*(sd_g/sd_k)/(kx_g/kx_fxg/kx_k+sd_g/sd_k) -> 0.10141734 | Z86: =(sd_g/sd_k/$I81+sd_g4/sd_k/$J81)/2+dr_jv_B/100*4*(sd_g/sd_k)/(kx_g/kx_fxg/kx_k+sd_g/sd_k) -> 0.10141734 | AB86: 2026Q3＝公司 FQ1 FY27 實績 ÷ 口徑係數 ÷ 市場；2026Q4 起＝2026Q3 實績份額與 FQ2 FY27 指引份額的平均；2027 起＋合資群年變動 × SanDisk 比重
A87: 份額：其他（長江存儲等） | B87: % | C87: =1-t5_0 -> 0.07 | D87: =1-t5_1 -> 0.071207692 | E87: =1-t5_2 -> 0.09 | F87: =1-t5_3 -> 0.10145455 | G87: =1-t5_4 -> 0.115 | H87: =1-t5_5 -> 0.12493886 | I87: =1-I82-I83-I84-I85-I86 -> 0.12713079 | J87: =1-J82-J83-J84-J85-J86 -> 0.13397774 | K87: =1-K82-K83-K84-K85-K86 -> 0.13997774 | L87: =1-L82-L83-L84-L85-L86 -> 0.13997774 | M87: =1-M82-M83-M84-M85-M86 -> 0.13997774 | N87: =1-N82-N83-N84-N85-N86 -> 0.13997774 | O87: =1-O82-O83-O84-O85-O86 -> 0.14597774 | P87: =1-P82-P83-P84-P85-P86 -> 0.14597774 | ... Z87: =1-Z82-Z83-Z84-Z85-Z86 -> 0.15797774 | AB87: 餘額（長江存儲等）
A88: 三星 營收（情境 B） | B88: $B | C88: =C81*C82 -> 4.2 | D88: =D81*D82 -> 5.2 | E88: =E81*E82 -> 6 | F88: =F81*F82 -> 6.6 | G88: =G81*G82 -> 13.51 | H88: =H81*H82 -> 23.06 | I88: =I81*I82 -> 30.762921 | J88: =J81*J82 -> 34.877842 | ... Z88: =Z81*Z82 -> 19.145754
A89: SK 海力士＋Solidigm 營收（情境 B） | B89: $B | C89: =C81*C83 -> 2.19 | D89: =D81*D83 -> 3.34 | E89: =E81*E83 -> 3.53 | F89: =F81*F83 -> 5.21 | G89: =G81*G83 -> 7.53 | H89: =H81*H83 -> 14.27 | I89: =I81*I83 -> 18.338301 | J89: =J81*J83 -> 20.791276 | ... Z89: =Z81*Z83 -> 12.233765
A90: 美光 營收（情境 B） | B90: $B | C90: =C81*C84 -> 2.03 | D90: =D81*D84 -> 2.1 | E90: =E81*E84 -> 2.42 | F90: =F81*F84 -> 3.03 | G90: =G81*G84 -> 5.95 | H90: =H81*H84 -> 11.85 | I90: =I81*I84 -> 14.973475 | J90: =J81*J84 -> 16.976363 | ... Z90: =Z81*Z84 -> 10.539705
A91: Kioxia 營收（情境 B） | B91: $B | C91: =C81*C85 -> 1.92 | D91: =D81*D85 -> 2.14 | E91: =E81*E85 -> 2.84 | F91: =F81*F85 -> 3.31 | G91: =G81*G85 -> 5.96 | H91: =H81*H85 -> 10.72 | I91: =I81*I85 -> 14.951317 | J91: =J81*J85 -> 16.203565 | ... Z91: =Z81*Z85 -> 9.0591137
A92: SanDisk 營收（情境 B） | B92: $B | C92: =C81*C86 -> 1.69 | D92: =D81*D86 -> 1.9 | E92: =E81*E86 -> 2.31 | F92: =F81*F86 -> 3.03 | G92: =G81*G86 -> 5.95 | H92: =H81*H86 -> 8.97 | I92: =I81*I86 -> 11.037152 | J92: =J81*J86 -> 12.460212 | ... Z92: =Z81*Z86 -> 6.9808979
A93: 其他（長江存儲等） 營收（情境 B） | B93: $B | C93: =C81*C87 -> 0.90548387 | D93: =D81*D87 -> 1.1254711 | E93: =E81*E87 -> 1.6912088 | F93: =F81*F87 -> 2.3914286 | G93: =G81*G87 -> 5.0548023 | H93: =H81*H87 -> 9.8330717 | I93: =I81*I87 -> 13.117431 | J93: =J81*J87 -> 15.673022 | ... Z93: =Z81*Z87 -> 10.874141
A94: Kioxia＋SanDisk（合資群）份額（情境 B） | B94: % | C94: =C85+C86 -> 0.27907731 | D94: =D85+D86 -> 0.25560769 | E94: =E85+E86 -> 0.27406433 | F94: =F85+F86 -> 0.2689697 | G94: =G85+G86 -> 0.27096015 | H94: =H85+H86 -> 0.25018083 | I94: =I85+I86 -> 0.25187361 | J94: =J85+J86 -> 0.24502666 | ... Z94: =Z85+Z86 -> 0.23302666
A95: Kioxia 位元（情境 B；季度出貨 × 營收份額） | B95: EB | C95: =C80*C85 -> 35.545444 | D95: =D80*D85 -> 33.356174 | E95: =E80*E85 -> 38.303462 | F95: =F80*F85 -> 36.611793 | G95: =G80*G85 -> 38.133315 | H95: =H80*H85 -> 40.175758 | I95: =I80*I85 -> 44.826902 | J95: =J80*J85 -> 44.941148 | ... Z95: =Z80*Z85 -> 83.747107 | AB95: 假設該廠平均售價＝市場平均（份額以營收計）；公司模型以此列的變動率推單位成本
A96: SanDisk 位元（情境 B；季度出貨 × 營收份額） | B96: EB | C96: =C80*C86 -> 31.287396 | D96: =D80*D86 -> 29.615294 | E96: =E80*E86 -> 31.15528 | F96: =F80*F86 -> 33.514723 | G96: =G80*G86 -> 38.069333 | H96: =H80*H86 -> 33.617215 | I96: =I80*I86 -> 33.091489 | J96: =J80*J86 -> 34.558829 | ... Z96: =Z80*Z86 -> 64.535011
A97: 檢查：份額合計 − 1；實績季營收重現（應為 0） | B97: — | C97: =ABS(SUM(C82:C87)-1)+ABS(SUM(I82:I87)-1)+ABS(SUM(Z82:Z87)-1)+ABS(H92-rv_sd_5) -> 0
A100: 情境 C（不如預期）：價格路徑 C（2028 回到 2025 年價格水準、2029 自谷底回升（完整循環））；2028–29 顆數 × 0.6／0.6；合資群份額年變動 dr_jv_C
A101: A. 年度（日曆年） | B101: 單位 | C101: CY2024 | D101: CY2025 | E101: CY2026 | F101: CY2027 | G101: CY2028 | H101: CY2029 | I101: CY2030 | AB101: 說明
A102: 加速器顆數（同字母情境係數） | B102: 百萬顆 | E102: =(u_26)*1 -> 15.2 | F102: =(u_27)*1 -> 23.7 | G102: =(u_28)*um28_C -> 15.9 | H102: =(u_28*(1+g_u29))*um29_C -> 18.09 | I102: =(u_28*(1+g_u29)*(1+g_u30))*um29_C -> 18.9945 | AB102: markets/memory UNITS × SCEN_UNITS；2029–30 基準以 g_u29、g_u30 外推，CY2030 沿用 um29
A103: 每顆企業級 SSD 容量 | B103: TB | E103: =tb_26 -> 30 | F103: =tb_27 -> 34 | G103: =tb_28 -> 40 | H103: =tb_29 -> 46 | I103: =tb_30 -> 52
A104: 需求：AI 企業級 SSD | B104: EB | D104: =bits25*sh_essd25*ai25 -> 165 | E104: =E102*E103 -> 456 | F104: =F102*F103 -> 805.8 | G104: =G102*G103 -> 636 | H104: =H102*H103 -> 832.14 | I104: =I102*I103 -> 987.714 | AB104: 顆數 × 每顆容量（百萬顆 × TB＝EB）；2025＝基期 × 占比
A105: 需求：非 AI 企業級 SSD | B105: EB | D105: =bits25*sh_essd25*(1-ai25) -> 135 | E105: =D105*(1+g_nai) -> 148.5 | F105: =E105*(1+g_nai) -> 163.35 | G105: =F105*(1+g_nai) -> 179.685 | H105: =G105*(1+g_nai) -> 197.6535 | I105: =H105*(1+g_nai) -> 217.41885
A106: 需求：手機 | B106: EB | D106: =bits25*sh_mob25 -> 320 | E106: =D106*(1+g_mob_26) -> 304 | F106: =E106*(1+g_mob_27) -> 313.12 | G106: =F106*(1+g_mob_28) -> 338.1696 | H106: =G106*(1+g_mob_28) -> 365.22317 | I106: =H106*(1+g_mob_28) -> 394.44102
A107: 需求：PC（client SSD） | B107: EB | D107: =bits25*sh_pc25 -> 230 | E107: =D107*(1+g_pc_26) -> 218.5 | F107: =E107*(1+g_pc_27) -> 218.5 | G107: =F107*(1+g_pc_28) -> 231.61 | H107: =G107*(1+g_pc_28) -> 245.5066 | I107: =H107*(1+g_pc_28) -> 260.237
...

Sheet Sup
A1: Sup — 主要廠位元供給說明（層數、產能動向；本頁為文字輸入，不進計算：位元供給以全產業年增 gs_ 計，見 In 頁 N4）
A3: 廠商 | B3: 主力世代（2026） | C3: 下一代 | D3: 2026 產能動向 | E3: 2Q26 位元市占 | F3: 標記 | G3: 來源
A4: 三星 | B4: V9（286 層） | C4: V10（430 層以上；大規模投資不早於 1H26） | D4: 晶圓投片約 −4.5%（投資轉向 HBM） | E4: 25% | F4: Interested-party | G4: borecraft 2026-05-26（轉載 DigiTimes 2026-05-25、Blocks & Files 2026-01-20）；Counterpoint 2Q26 位元市占
A5: SK 海力士＋Solidigm | B5: 321 層（V9 世代） | C5: 300 層級新品 2027 年初全面量產 | D5: 晶圓投片約 −10%；Solidigm QLC 企業級 SSD 出貨季增約 40% | E5: 22% | F5: Interested-party | G5: 同上；TrendForce 2026-08-18
A6: Kioxia（合資群） | B6: BiCS8（218 層） | C6: BiCS10（332 層，北上 K2，FY2026 量產；密度高約 59%） | D6: Kioxia＋SanDisk 2026 資本支出 $4.5B（+41%）；Kioxia FY26–28 年均 ¥470B | E6: 未找到 | F6: Interested-party | G6: TrendForce 2025-11-13、2026-06-03；borecraft 2026-05-26
A7: SanDisk（合資群） | B7: BiCS8（218 層；與 Kioxia 共用晶圓廠） | C7: BiCS10 | D7: 位元成長相對保守（TrendForce 2Q26）；Flash Ventures 持股 49.9% | E7: 未找到 | F7: Interested-party | G7: TrendForce 2026-08-18；SanDisk FQ4 FY26 簡報
A8: 美光 | B8: G9（276 層） | C8: 未找到 | D8: 位元成長低於產業（美光 FQ4 FY26） | E8: 未找到 | F8: Interested-party | G8: 美光 FQ4 FY26 法說（Guru3D 2026-10-01）
A9: 長江存儲 | B9: Xtacking 4.0（267 層） | C9: 未找到 | D9: 2Q26 位元市占 14%（第三），年增約 22%；三廠 2026 年底投產 | E9: 14% | F9: Interested-party | G9: Counterpoint 2Q26（hwbusters 轉載）；markets/equipment In 頁
A11: 各廠晶圓月產能（千片）：未找到可驗證的公開數字（TrendForce、Yole 付費）。本版不以各廠產能加總推供給，改用全產業位元年增（美光指引），各廠以營收份額分配。

Sheet Recon
A1: Recon — 本模型 vs 公司指引、公開預測（只作事後對照，不回推參數）。差距＝模型 ÷ 對照 − 1（百分點列為相減）
A3: 項目 | B3: 對照值 | C3: 模型 A | D3: 模型 B | E3: 模型 C | F3: 差距 A | G3: 對照來源 | H3: 說明
A4: 2Q26 SanDisk 營收（實績重現） | B4: =rv_sd_5 -> 8.97 | C4: =Mkt!H44 -> 8.97 | D4: =Mkt!H92 -> 8.97 | E4: =Mkt!H140 -> 8.97 | F4: =C4/B4-1 -> 0 | G4: TrendForce 2026-08-18（2Q26 NAND 前五大營收排名）https://www.trendforce.com/presscenter/news/20260818-13186.html | H4: 恆等式
A5: 2026Q3 SanDisk 營收 vs 公司指引（TrendForce 口徑） | B5: =sd_g/sd_k -> 11.037152 | C5: =Mkt!I44 -> 11.037152 | D5: =Mkt!I92 -> 11.037152 | E5: =Mkt!I140 -> 11.037152 | F5: =C5/B5-1 -> 0 | G5: SanDisk 指引 $10.3–10.8B | H5: 恆等式（份額由指引推得）
A6: 2026Q3 市場營收 vs 2Q26 ×（1＋季價 25%） | B6: =Mkt!H33*1.25 -> 98.37884 | C6: =Mkt!I33 -> 103.1806 | D6: =Mkt!I81 -> 103.1806 | E6: =Mkt!I129 -> 103.1806 | F6: =C6/B6-1 -> 0.048808848 | G6: Siliconomics v0.10 nq_6：2026Q3 實現平均售價 +25%（Kioxia、SK 海力士 mid-20%；TrendForce 合約價 +10~15% 只作對照） | H6: 差額＝位元季增
A7: CY2026 位元出貨年增 vs 美光「低 20% 段」（百分點） | B7: 0.21 | C7: =Mkt!E18 -> 0.21 | D7: =Mkt!E66 -> 0.21 | E7: =Mkt!E114 -> 0.21 | F7: =C7-B7 -> 0 | G7: 美光 FQ4 FY26（Guru3D 2026-10-01） | H7: 供給受限時＝gs_26
A8: CY2027 位元出貨年增 vs 美光「約中 20% 段」（百分點） | B8: 0.25 | C8: =Mkt!F18 -> 0.25 | D8: =Mkt!F66 -> 0.25 | E8: =Mkt!F114 -> 0.25 | F8: =C8-B8 -> 0 | G8: 同上
A9: CY2028 位元出貨年增 vs 美光「約中 20% 段」（百分點） | B9: 0.25 | C9: =Mkt!G18 -> 0.25 | D9: =Mkt!G66 -> 0.14989395 | E9: =Mkt!G114 -> 0.0097286612 | F9: =C9-B9 -> 0 | G9: 同上 | H9: B、C 需求低於供給，出貨＝需求
A10: CY2026 需求 ÷ 供給 − 1 vs TrendForce 供給缺口 4–6%（百分點） | B10: 0.05 | C10: =Mkt!E16 -> 0.042975207 | D10: =Mkt!E64 -> 0.042975207 | E10: =Mkt!E112 -> 0.042975207 | F10: =C10-B10 -> -0.0070247934 | G10: TrendForce 2026-07-21（Guru3D 轉載）：2026 供給低於需求 4–6%；2H27 回到平衡
A11: CY2026 企業級 SSD 占需求 vs Counterpoint 2Q26 48%（百分點） | B11: 0.48 | C11: =Mkt!E14 -> 0.47900158 | D11: =Mkt!E62 -> 0.47900158 | E11: =Mkt!E110 -> 0.47900158 | F11: =C11-B11 -> -0.00099841521 | G11: Counterpoint 2Q26（季度值；全年平均應較低） | H11: TrendForce：2026 伺服器約 40%
A12: CY2025 市場營收（實績）vs 前五大合計 ÷ 0.9 | B12: =(rv_ss_0+rv_ss_1+rv_ss_2+rv_ss_3+rv_sk_0+rv_sk_1+rv_sk_2+rv_sk_3+rv_mu_0+rv_mu_1+rv_mu_2+rv_mu_3+rv_kx_0+rv_kx_1+rv_kx_2+rv_kx_3+rv_sd_0+rv_sd_1+rv_sd_2+rv_sd_3)/0.9 -> 72.211111 | C12: =Mkt!D19 -> 71.103592 | D12: =Mkt!D67 -> 71.103592 | E12: =Mkt!D115 -> 71.103592 | F12: =C12/B12-1 -> -0.015337235 | G12: TrendForce 季度合計
A13: CY2027 Kioxia＋SanDisk 營收 vs 共識（會計年度依月份拼成日曆年：Kioxia ¼ FY2026＋¾ FY2027；SanDisk ½ FY2027＋½ FY2028） | B13: =10071/160/kx_k*0.25+13477/160/kx_k*0.75+49.1/sd_k*0.5+58.4/sd_k*0.5 -> 130.37177 | C13: =Ann!F28+Ann!F29 -> 131.5143 | D13: =Ann!F55+Ann!F56 -> 126.35556 | E13: =Ann!F82+Ann!F83 -> 124.78934 | F13: =C13/B13-1 -> 0.008763647 | G13: MarketScreener 2026-10-23 擷取：Kioxia FY2027（2027-03）營收 ¥10.07 兆、FY2028 ¥13.48 兆；SanDisk FY2027 $49.1B、FY2028 $58.4B | H13: 會計年度依月份拼成日曆年（Derived）；共識只作對照
A14: 2026Q4 SanDisk 營收 vs FQ2 FY27 指引中點 12.4（TrendForce 口徑） | B14: =12.4/sd_k -> 12.406916 | C14: =Mkt!J44 -> 12.460212 | D14: =Mkt!J92 -> 12.460212 | E14: =Mkt!J140 -> 12.460212 | F14: =C14/B14-1 -> 0.0042956712 | G14: SanDisk FQ1 FY27 法說（2026-10-29）：FQ2 FY27 營收指引 12.2–12.6 | H14: v0.3：2026Q4 季價 +8.1%＋份額取兩季平均（v0.2 差距 +9.6%）；公司稱價量皆貢獻、同品項價格溫和上升
A15: 2026Q4 Kioxia 營收 vs 第三季指引 ¥2,500B ÷ 157 日圓（TrendForce 口徑） | B15: =2500/157/kx_k -> 15.455889 | C15: =Mkt!J43 -> 16.203565 | D15: =Mkt!J91 -> 16.203565 | E15: =Mkt!J139 -> 16.203565 | F15: =C15/B15-1 -> 0.0483748 | G15: Kioxia 第二季財報（2026-10-30）：第三季營收指引 ¥2,500B（157 日圓）；位元持平、平均售價季增低個位數 | H15: v0.3：季價 +8.1%＋份額取兩季平均（v0.2 差距 +19.2%）。餘差＝份額平均只平滑一半的出貨季別移動（7–9 月提前、部分遞延到 1–3 月，同一會計年度內）與產品組合

Sheet Sens
A1: Sens — 一次動一個輸入（情境 A）：對 CY2027、CY2028 市場營收與 Kioxia＋SanDisk 營收的影響。每個案例為一個完整推導區塊（本頁下方，與 Mkt 同一引擎）
A3: 案例 | B3: 設定 | C3: CY2027 市場 $B | D3: 相對基準 | E3: CY2028 市場 $B | F3: 相對基準 | G3: CY2028 位元出貨 EB | H3: CY2028 合資群營收 $B | I3: 相對基準 | J3: CY2030 市場 $B | K3: 相對基準
A4: 基準（情境 A） | B4: Mkt 區塊 A | C4: =Mkt!F19 -> 536.73468 | D4: =C4/C$4-1 -> 0 | E4: =Mkt!G19 -> 544.61015 | F4: =E4/E$4-1 -> 0 | G4: =Mkt!G17 -> 1890.625 | H4: =SUM(Mkt!O43:R43)+SUM(Mkt!O44:R44) -> 133.444 | I4: =H4/H$4-1 -> 0 | J4: =Mkt!I19 -> 583.68943 | K4: =J4/J$4-1 -> 0
A5: 每顆容量 −20% | B5: tb 低欄 | C5: =F55 -> 536.58496 | D5: =C5/C$4-1 -> -0.00027894775 | E5: =G55 -> 515.86451 | F5: =E5/E$4-1 -> -0.052782043 | G5: =G53 -> 1739.2146 | H5: =SUM(O79:R79)+SUM(O80:R80) -> 127.95763 | I5: =H5/H$4-1 -> -0.041113648 | J5: =I55 -> 529.50958 | K5: =J5/J$4-1 -> -0.092823077
A6: 每顆容量 +20% | B6: tb 高欄 | C6: =F125 -> 536.73468 | D6: =C6/C$4-1 -> 0 | E6: =G125 -> 544.61015 | F6: =E6/E$4-1 -> 0 | G6: =G123 -> 1890.625 | H6: =SUM(O149:R149)+SUM(O150:R150) -> 133.444 | I6: =H6/H$4-1 -> 0 | J6: =I125 -> 603.84615 | K6: =J6/J$4-1 -> 0.034533288
A7: 位元供給成長 低 | B7: gs 低欄 | C7: =F195 -> 513.74938 | D7: =C7/C$4-1 -> -0.042824321 | E7: =G195 -> 500.49259 | F7: =E7/E$4-1 -> -0.0810076 | G7: =G193 -> 1699.2 | H7: =SUM(O219:R219)+SUM(O220:R220) -> 123.7838 | I7: =H7/H$4-1 -> -0.072391471 | J7: =I195 -> 488.23413 | K7: =J7/J$4-1 -> -0.16353782
A8: 位元供給成長 高 | B8: gs 高欄 | C8: =F265 -> 551.34164 | D8: =C8/C$4-1 -> 0.027214494 | E8: =G265 -> 550.50712 | F8: =E8/E$4-1 -> 0.010827884 | G8: =G263 -> 1951.2146 | H8: =SUM(O289:R289)+SUM(O290:R290) -> 133.66781 | I8: =H8/H$4-1 -> 0.001677183 | J8: =I265 -> 571.62806 | K8: =J8/J$4-1 -> -0.020664033
A9: 2025 位元基期 850 EB | B9: bits25 低 | C9: =F335 -> 536.73468 | D9: =C9/C$4-1 -> 0 | E9: =G335 -> 544.61015 | F9: =E9/E$4-1 -> 0 | G9: =G333 -> 1607.0312 | H9: =SUM(O359:R359)+SUM(O360:R360) -> 133.444 | I9: =H9/H$4-1 -> 0 | J9: =I335 -> 603.84615 | K9: =J9/J$4-1 -> 0.034533288
A10: 2025 位元基期 1,150 EB | B10: bits25 高 | C10: =F405 -> 539.56078 | D10: =C10/C$4-1 -> 0.0052653652 | E10: =G405 -> 525.38218 | F10: =E10/E$4-1 -> -0.035305942 | G10: =G403 -> 2084.8968 | H10: =SUM(O429:R429)+SUM(O430:R430) -> 129.02951 | I10: =H10/H$4-1 -> -0.033081227 | J10: =I405 -> 539.80573 | K10: =J10/J$4-1 -> -0.075183317
A11: 企業級 SSD 2025 占比 26% | B11: sh_essd25 低 | C11: =F475 -> 536.73468 | D11: =C11/C$4-1 -> 0 | E11: =G475 -> 544.61015 | F11: =E11/E$4-1 -> 0 | G11: =G473 -> 1890.625 | H11: =SUM(O499:R499)+SUM(O500:R500) -> 133.444 | I11: =H11/H$4-1 -> 0 | J11: =I475 -> 586.43014 | K11: =J11/J$4-1 -> 0.0046954883
A12: 非 AI 企業級 SSD 年增 5% | B12: g_nai 低 | C12: =F545 -> 536.73468 | D12: =C12/C$4-1 -> 0 | E12: =G545 -> 544.61015 | F12: =E12/E$4-1 -> 0 | G12: =G543 -> 1890.625 | H12: =SUM(O569:R569)+SUM(O570:R570) -> 133.444 | I12: =H12/H$4-1 -> 0 | J12: =I545 -> 573.93987 | K12: =J12/J$4-1 -> -0.016703333
A13: 2029 顆數年增 0% | B13: g_u29 低 | C13: =F615 -> 536.73468 | D13: =C13/C$4-1 -> 0 | E13: =G615 -> 544.61015 | F13: =E13/E$4-1 -> 0 | G13: =G613 -> 1890.625 | H13: =SUM(O639:R639)+SUM(O640:R640) -> 133.444 | I13: =H13/H$4-1 -> 0 | J13: =I615 -> 540.30089 | K13: =J13/J$4-1 -> -0.074334987
A14: CY2030 售價年變動 −20% | B14: p10 低 | C14: =F685 -> 536.73468 | D14: =C14/C$4-1 -> 0 | E14: =G685 -> 544.61015 | F14: =E14/E$4-1 -> 0 | G14: =G683 -> 1890.625 | H14: =SUM(O709:R709)+SUM(O710:R710) -> 133.444 | I14: =H14/H$4-1 -> 0 | J14: =I685 -> 550.0475 | K14: =J14/J$4-1 -> -0.057636697
A15: 2027 起季價水準 ×0.8 | B15: 價格係數 0.8 | C15: =F755 -> 429.38774 | D15: =C15/C$4-1 -> -0.2 | E15: =G755 -> 435.68812 | F15: =E15/E$4-1 -> -0.2 | G15: =G753 -> 1890.625 | H15: =SUM(O779:R779)+SUM(O780:R780) -> 106.7552 | I15: =H15/H$4-1 -> -0.2 | J15: =I755 -> 466.95155 | K15: =J15/J$4-1 -> -0.2
A16: 合資群份額年變動取 C（−0.6pt） | B16: dr_jv_C | C16: =F825 -> 536.73468 | D16: =C16/C$4-1 -> 0 | E16: =G825 -> 544.61015 | F16: =E16/E$4-1 -> 0 | G16: =G823 -> 1890.625 | H16: =SUM(O849:R849)+SUM(O850:R850) -> 126.90868 | I16: =H16/H$4-1 -> -0.048974263 | J16: =I825 -> 583.68943 | K16: =J16/J$4-1 -> 0
A17: 情境 B | B17: Mkt 區塊 B | C17: =Mkt!F67 -> 522.07288 | D17: =C17/C$4-1 -> -0.027316653 | E17: =Mkt!G67 -> 242.30569 | F17: =E17/E$4-1 -> -0.55508414 | G17: =Mkt!G65 -> 1739.2146 | H17: =SUM(Mkt!O91:R91)+SUM(Mkt!O92:R92) -> 57.917519 | I17: =H17/H$4-1 -> -0.56597886 | J17: =Mkt!I67 -> 275.32213 | K17: =J17/J$4-1 -> -0.52830716
A18: 情境 C | B18: Mkt 區塊 C | C18: =Mkt!F115 -> 522.07288 | D18: =C18/C$4-1 -> -0.027316653 | E18: =Mkt!G115 -> 174.22825 | F18: =E18/E$4-1 -> -0.6800863 | G18: =Mkt!G113 -> 1527.2146 | H18: =SUM(Mkt!O139:R139)+SUM(Mkt!O140:R140) -> 40.599827 | I18: =H18/H$4-1 -> -0.69575384 | J18: =Mkt!I115 -> 163.54736 | K18: =J18/J$4-1 -> -0.71980415
A20: 讀法：營收以 2Q26 實績為錨，2026Q3 起的變動＝價格指數比 × 位元比；Kioxia、SanDisk 的 2026Q3 份額由公司指引推得，因此改變市場路徑時兩家 2026Q3 營收不變（份額反向調整）。
A40: 案例區塊：每顆容量 −20%（情境 A）
A41: A. 年度（日曆年） | B41: 單位 | C41: CY2024 | D41: CY2025 | E41: CY2026 | F41: CY2027 | G41: CY2028 | H41: CY2029 | I41: CY2030 | AB41: 說明
A42: 加速器顆數（同字母情境係數） | B42: 百萬顆 | E42: =(u_26)*1 -> 15.2 | F42: =(u_27)*1 -> 23.7 | G42: =(u_28)*um28_A -> 26.5 | H42: =(u_28*(1+g_u29))*um29_A -> 30.15 | I42: =(u_28*(1+g_u29)*(1+g_u30))*um29_A -> 31.6575 | AB42: markets/memory UNITS × SCEN_UNITS；2029–30 基準以 g_u29、g_u30 外推，CY2030 沿用 um29
A43: 每顆企業級 SSD 容量 | B43: TB | E43: =tb_26_lo -> 24 | F43: =tb_27_lo -> 27 | G43: =tb_28_lo -> 32 | H43: =tb_29_lo -> 37 | I43: =tb_30_lo -> 42
A44: 需求：AI 企業級 SSD | B44: EB | D44: =bits25*sh_essd25*ai25 -> 165 | E44: =E42*E43 -> 364.8 | F44: =F42*F43 -> 639.9 | G44: =G42*G43 -> 848 | H44: =H42*H43 -> 1115.55 | I44: =I42*I43 -> 1329.615 | AB44: 顆數 × 每顆容量（百萬顆 × TB＝EB）；2025＝基期 × 占比
A45: 需求：非 AI 企業級 SSD | B45: EB | D45: =bits25*sh_essd25*(1-ai25) -> 135 | E45: =D45*(1+g_nai) -> 148.5 | F45: =E45*(1+g_nai) -> 163.35 | G45: =F45*(1+g_nai) -> 179.685 | H45: =G45*(1+g_nai) -> 197.6535 | I45: =H45*(1+g_nai) -> 217.41885
A46: 需求：手機 | B46: EB | D46: =bits25*sh_mob25 -> 320 | E46: =D46*(1+g_mob_26) -> 304 | F46: =E46*(1+g_mob_27) -> 313.12 | G46: =F46*(1+g_mob_28) -> 338.1696 | H46: =G46*(1+g_mob_28) -> 365.22317 | I46: =H46*(1+g_mob_28) -> 394.44102
A47: 需求：PC（client SSD） | B47: EB | D47: =bits25*sh_pc25 -> 230 | E47: =D47*(1+g_pc_26) -> 218.5 | F47: =E47*(1+g_pc_27) -> 218.5 | G47: =F47*(1+g_pc_28) -> 231.61 | H47: =G47*(1+g_pc_28) -> 245.5066 | I47: =H47*(1+g_pc_28) -> 260.237
A48: 需求：消費性與其他 | B48: EB | D48: =bits25*(1-sh_essd25-sh_mob25-sh_pc25) -> 150 | E48: =D48*(1+g_con_26) -> 135 | F48: =E48*(1+g_con_27) -> 135 | G48: =F48*(1+g_con_28) -> 141.75 | H48: =G48*(1+g_con_28) -> 148.8375 | I48: =H48*(1+g_con_28) -> 156.27937
A49: 位元需求合計 | B49: EB | D49: =SUM(D44:D48) -> 1000 | E49: =SUM(E44:E48) -> 1170.8 | F49: =SUM(F44:F48) -> 1469.87 | G49: =SUM(G44:G48) -> 1739.2146 | H49: =SUM(H44:H48) -> 2072.7708 | I49: =SUM(I44:I48) -> 2357.9912
A50: 企業級 SSD 占位元需求 | B50: % | D50: =(D44+D45)/D49 -> 0.3 | E50: =(E44+E45)/E49 -> 0.43841818 | F50: =(F44+F45)/F49 -> 0.5464769 | G50: =(G44+G45)/G49 -> 0.59089028 | H50: =(H44+H45)/H49 -> 0.6335498 | I50: =(I44+I45)/I49 -> 0.65608125
A51: 位元供給（三情境相同） | B51: EB | D51: =bits25 -> 1000 | E51: =D51*(1+gs_26) -> 1210 | F51: =E51*(1+gs_27) -> 1512.5 | G51: =F51*(1+gs_28) -> 1890.625 | H51: =G51*(1+gs_29) -> 2306.5625 | I51: =H51*(1+gs_30) -> 2767.875 | AB51: 2025＝出貨實績（基期）；供給不隨需求情境變（產能 2027 前已訂定），需求不足的結果是閒置產能與降價
A52: 需求 ÷ 供給 − 1（>0＝短缺） | B52: % | E52: =E49/E51-1 -> -0.032396694 | F52: =F49/F51-1 -> -0.028185124 | G52: =G49/G51-1 -> -0.08008484 | H52: =H49/H51-1 -> -0.10135937 | I52: =I49/I51-1 -> -0.14808608
A53: 位元出貨＝MIN(需求, 供給) | B53: EB | C53: =bits25/(1+g25) -> 892.85714 | D53: =bits25 -> 1000 | E53: =MIN(E49,E51) -> 1170.8 | F53: =MIN(F49,F51) -> 1469.87 | G53: =MIN(G49,G51) -> 1739.2146 | H53: =MIN(H49,H51) -> 2072.7708 | I53: =MIN(I49,I51) -> 2357.9912
A54: 位元出貨年增 | B54: % | D54: =D53/C53-1 -> 0.12 | E54: =E53/D53-1 -> 0.1708 | F54: =F53/E53-1 -> 0.25544072 | G54: =G53/F53-1 -> 0.18324382 | H54: =H53/G53-1 -> 0.19178552 | I54: =I53/H53-1 -> 0.13760348
A55: NAND 市場營收（四季合計） | B55: $B | C55: =rev24 -> 67.4 | D55: =SUM(C69:F69) -> 71.103592 | E55: =SUM(G69:J69) -> 340.0642 | F55: =SUM(K69:N69) -> 536.58496 | G55: =SUM(O69:R69) -> 515.86451 | H55: =SUM(S69:V69) -> 527.51186 | I55: =SUM(W69:Z69) -> 529.50958 | AB55: CY2024 為 TrendForce 年度值
A56: 市場營收年增 | B56: % | D56: =D55/C55-1 -> 0.054949442 | E56: =E55/D55-1 -> 3.7826585 | F56: =F55/E55-1 -> 0.5778931 | G56: =G55/F55-1 -> -0.038615403 | H56: =H55/G55-1 -> 0.022578311 | I56: =I55/H55-1 -> 0.0037870646
A57: 平均售價（營收 ÷ 位元出貨） | B57: $/GB | C57: =C55/C53 -> 0.075488 | D57: =D55/D53 -> 0.071103592 | E57: =E55/E53 -> 0.29045456 | F57: =F55/F53 -> 0.36505606 | G57: =G55/G53 -> 0.29660774 | H57: =H55/H53 -> 0.254496 | I57: =I55/I53 -> 0.22455961
A58: 平均售價年變動 | B58: % | D58: =D57/C57-1 -> -0.058080856 | E58: =E57/D57-1 -> 3.0849492 | F58: =F57/E57-1 -> 0.25684396 | G58: =G57/F57-1 -> -0.18750085 | H58: =H57/G57-1 -> -0.1419779 | I58: =I57/H57-1 -> -0.11763011 | AB58: CY2030 為收斂法（p10）＋位元平滑效果
A59: 年度份額：三星 | B59: % | D59: =SUM(C76:F76)/D55 -> 0.30940771 | E59: =SUM(G76:J76)/E55 -> 0.29814637 | F59: =SUM(K76:N76)/F55 -> 0.29314637 | G59: =SUM(O76:R76)/G55 -> 0.28814637 | H59: =SUM(S76:V76)/H55 -> 0.28314637 | I59: =SUM(W76:Z76)/I55 -> 0.27814637
A60: 年度份額：SK 海力士＋Solidigm | B60: % | D60: =SUM(C77:F77)/D55 -> 0.20069309 | E60: =SUM(G77:J77)/E55 -> 0.17773013 | F60: =SUM(K77:N77)/F55 -> 0.17773013 | G60: =SUM(O77:R77)/G55 -> 0.17773013 | H60: =SUM(S77:V77)/H55 -> 0.17773013 | I60: =SUM(W77:Z77)/I55 -> 0.17773013
A61: 年度份額：美光 | B61: % | D61: =SUM(C78:F78)/D55 -> 0.134733 | E61: =SUM(G78:J78)/E55 -> 0.1451191 | F61: =SUM(K78:N78)/F55 -> 0.1471191 | G61: =SUM(O78:R78)/G55 -> 0.1491191 | H61: =SUM(S78:V78)/H55 -> 0.1511191 | I61: =SUM(W78:Z78)/I55 -> 0.1531191
A62: 年度份額：Kioxia | B62: % | D62: =SUM(C79:F79)/D55 -> 0.14359331 | E62: =SUM(G79:J79)/E55 -> 0.14045991 | F62: =SUM(K79:N79)/F55 -> 0.14020877 | G62: =SUM(O79:R79)/G55 -> 0.14020877 | H62: =SUM(S79:V79)/H55 -> 0.14020877 | I62: =SUM(W79:Z79)/I55 -> 0.14020877
A63: 年度份額：SanDisk | B63: % | D63: =SUM(C80:F80)/D55 -> 0.1255914 | E63: =SUM(G80:J80)/E55 -> 0.11282005 | F63: =SUM(K80:N80)/F55 -> 0.10783628 | G63: =SUM(O80:R80)/G55 -> 0.10783628 | H63: =SUM(S80:V80)/H55 -> 0.10783628 | I63: =SUM(W80:Z80)/I55 -> 0.10783628
A64: 年度份額：其他（長江存儲等） | B64: % | D64: =SUM(C81:F81)/D55 -> 0.085981484 | E64: =SUM(G81:J81)/E55 -> 0.12572444 | F64: =SUM(K81:N81)/F55 -> 0.13395936 | G64: =SUM(O81:R81)/G55 -> 0.13695936 | H64: =SUM(S81:V81)/H55 -> 0.13995936 | I64: =SUM(W81:Z81)/I55 -> 0.14295936
A66: B. 季度 | B66: 單位 | C66: 2025Q1 | D66: 2025Q2 | E66: 2025Q3 | F66: 2025Q4 | G66: 2026Q1 | H66: 2026Q2 | I66: 2026Q3 | J66: 2026Q4 | K66: 2027Q1 | L66: 2027Q2 | M66: 2027Q3 | N66: 2027Q4 | O66: 2028Q1 | P66: 2028Q2 | Q66: 2028Q3 | R66: 2028Q4 | S66: 2029Q1 | T66: 2029Q2 | U66: 2029Q3 | V66: 2029Q4 | W66: 2030Q1 | X66: 2030Q2 | Y66: 2030Q3 | Z66: 2030Q4 | AB66: 說明
A67: 合約價指數（同字母路徑） | B67: 2025Q1＝1 | C67: =Path!C4 -> 1 | D67: =Path!D4 -> 1 | E67: =Path!E4 -> 1.05 | F67: =Path!F4 -> 1.365 | G67: =Path!G4 -> 2.559375 | H67: =Path!H4 -> 4.4149219 | I67: =Path!I4 -> 5.5186523 | J67: =Path!J4 -> 5.9656632 | K67: =Path!K4*1 -> 6.1446331 | L67: =Path!L4*1 -> 6.1446331 | M67: =Path!M4*1 -> 5.8374014 | N67: =Path!N4*1 -> 5.4287833 | O67: =Path!O4*1 -> 5.1573442 | P67: =Path!P4*1 -> 4.899477 | Q67: =Path!Q4*1 -> 4.6545031 | R67: =Path!R4*1 -> 4.4217779 | ... V67: =Path!V4*1 -> 3.9145682 | W67: =Path!V4*(1+p10)^(1/4)*1 -> 3.791443 | X67: =Path!V4*(1+p10)^(2/4)*1 -> 3.6721905 | Y67: =Path!V4*(1+p10)^(3/4)*1 -> 3.5566888 | Z67: =Path!V4*(1+p10)^(4/4)*1 -> 3.44482 | AB67: Path 頁；Sens 可對 2027 起的季價乘價格係數
A68: 季度位元出貨（年內依年增平滑；四季合計＝年度） | B68: EB | C68: =D53/4*(D53/C53)^((1-2.5)/4)/(((D53/C53)^(-0.375)+(D53/C53)^(-0.125)+(D53/C53)^(0.125)+(D53/C53)^(0.375))/4) -> 239.47787 | D68: =D53/4*(D53/C53)^((2-2.5)/4)/(((D53/C53)^(-0.375)+(D53/C53)^(-0.125)+(D53/C53)^(0.125)+(D53/C53)^(0.375))/4) -> 246.35983 | E68: =D53/4*(D53/C53)^((3-2.5)/4)/(((D53/C53)^(-0.375)+(D53/C53)^(-0.125)+(D53/C53)^(0.125)+(D53/C53)^(0.375))/4) -> 253.43956 | F68: =D53/4*(D53/C53)^((4-2.5)/4)/(((D53/C53)^(-0.375)+(D53/C53)^(-0.125)+(D53/C53)^(0.125)+(D53/C53)^(0.375))/4) -> 260.72274 | G68: =E53/4*(E53/D53)^((1-2.5)/4)/(((E53/D53)^(-0.375)+(E53/D53)^(-0.125)+(E53/D53)^(0.125)+(E53/D53)^(0.375))/4) -> 275.62586 | H68: =E53/4*(E53/D53)^((2-2.5)/4)/(((E53/D53)^(-0.375)+(E53/D53)^(-0.125)+(E53/D53)^(0.125)+(E53/D53)^(0.375))/4) -> 286.70855 | I68: =E53/4*(E53/D53)^((3-2.5)/4)/(((E53/D53)^(-0.375)+(E53/D53)^(-0.125)+(E53/D53)^(0.125)+(E53/D53)^(0.375))/4) -> 298.23686 | J68: =E53/4*(E53/D53)^((4-2.5)/4)/(((E53/D53)^(-0.375)+(E53/D53)^(-0.125)+(E53/D53)^(0.125)+(E53/D53)^(0.375))/4) -> 310.22872 | K68: =F53/4*(F53/E53)^((1-2.5)/4)/(((F53/E53)^(-0.375)+(F53/E53)^(-0.125)+(F53/E53)^(0.125)+(F53/E53)^(0.375))/4) -> 336.73855 | L68: =F53/4*(F53/E53)^((2-2.5)/4)/(((F53/E53)^(-0.375)+(F53/E53)^(-0.125)+(F53/E53)^(0.125)+(F53/E53)^(0.375))/4) -> 356.44447 | M68: =F53/4*(F53/E53)^((3-2.5)/4)/(((F53/E53)^(-0.375)+(F53/E53)^(-0.125)+(F53/E53)^(0.125)+(F53/E53)^(0.375))/4) -> 377.30359 | N68: =F53/4*(F53/E53)^((4-2.5)/4)/(((F53/E53)^(-0.375)+(F53/E53)^(-0.125)+(F53/E53)^(0.125)+(F53/E53)^(0.375))/4) -> 399.38338 | O68: =G53/4*(G53/F53)^((1-2.5)/4)/(((G53/F53)^(-0.375)+(G53/F53)^(-0.125)+(G53/F53)^(0.125)+(G53/F53)^(0.375))/4) -> 407.76521 | P68: =G53/4*(G53/F53)^((2-2.5)/4)/(((G53/F53)^(-0.375)+(G53/F53)^(-0.125)+(G53/F53)^(0.125)+(G53/F53)^(0.375))/4) -> 425.28369 | Q68: =G53/4*(G53/F53)^((3-2.5)/4)/(((G53/F53)^(-0.375)+(G53/F53)^(-0.125)+(G53/F53)^(0.125)+(G53/F53)^(0.375))/4) -> 443.55481 | R68: =G53/4*(G53/F53)^((4-2.5)/4)/(((G53/F53)^(-0.375)+(G53/F53)^(-0.125)+(G53/F53)^(0.125)+(G53/F53)^(0.375))/4) -> 462.61089 | S68: =H53/4*(H53/G53)^((1-2.5)/4)/(((H53/G53)^(-0.375)+(H53/G53)^(-0.125)+(H53/G53)^(0.125)+(H53/G53)^(0.375))/4) -> 484.61283 | T68: =H53/4*(H53/G53)^((2-2.5)/4)/(((H53/G53)^(-0.375)+(H53/G53)^(-0.125)+(H53/G53)^(0.125)+(H53/G53)^(0.375))/4) -> 506.34256 | U68: =H53/4*(H53/G53)^((3-2.5)/4)/(((H53/G53)^(-0.375)+(H53/G53)^(-0.125)+(H53/G53)^(0.125)+(H53/G53)^(0.375))/4) -> 529.04663 | V68: =H53/4*(H53/G53)^((4-2.5)/4)/(((H53/G53)^(-0.375)+(H53/G53)^(-0.125)+(H53/G53)^(0.125)+(H53/G53)^(0.375))/4) -> 552.76875 | W68: =I53/4*(I53/H53)^((1-2.5)/4)/(((I53/H53)^(-0.375)+(I53/H53)^(-0.125)+(I53/H53)^(0.125)+(I53/H53)^(0.375))/4) -> 561.31115 | X68: =I53/4*(I53/H53)^((2-2.5)/4)/(((I53/H53)^(-0.375)+(I53/H53)^(-0.125)+(I53/H53)^(0.125)+(I53/H53)^(0.375))/4) -> 579.69746 | Y68: =I53/4*(I53/H53)^((3-2.5)/4)/(((I53/H53)^(-0.375)+(I53/H53)^(-0.125)+(I53/H53)^(0.125)+(I53/H53)^(0.375))/4) -> 598.68603 | Z68: =I53/4*(I53/H53)^((4-2.5)/4)/(((I53/H53)^(-0.375)+(I53/H53)^(-0.125)+(I53/H53)^(0.125)+(I53/H53)^(0.375))/4) -> 618.2966 | AB68: 季度＝年度 ÷ 4 ×（1＋年增）^((季−2.5)/4)，再正規化使四季合計等於年度
A69: NAND 市場營收（2026Q2 前實績；之後＝2Q26 實績 × 價格指數比 × 位元比） | B69: $B | C69: =(rv_ss_0+rv_sk_0+rv_mu_0+rv_kx_0+rv_sd_0)/t5_0 -> 12.935484 | D69: =(rv_ss_1+rv_sk_1+rv_mu_1+rv_kx_1+rv_sd_1)/t5_1 -> 15.805471 | E69: =(rv_ss_2+rv_sk_2+rv_mu_2+rv_kx_2+rv_sd_2)/t5_2 -> 18.791209 | F69: =(rv_ss_3+rv_sk_3+rv_mu_3+rv_kx_3+rv_sd_3)/t5_3 -> 23.571429 | G69: =(rv_ss_4+rv_sk_4+rv_mu_4+rv_kx_4+rv_sd_4)/t5_4 -> 43.954802 | H69: =(rv_ss_5+rv_sk_5+rv_mu_5+rv_kx_5+rv_sd_5)/t5_5 -> 78.703072 | I69: =$H69*I67/$H67*I68/$H68 -> 102.33457 | J69: =$H69*J67/$H67*J68/$H68 -> 115.07176 | K69: =$H69*K67/$H67*K68/$H68 -> 128.65208 | L69: =$H69*L67/$H67*L68/$H68 -> 136.18079 | M69: =$H69*M67/$H67*M68/$H68 -> 136.94258 | N69: =$H69*N67/$H67*N68/$H68 -> 134.80951 | O69: =$H69*O67/$H67*O68/$H68 -> 130.7568 | P69: =$H69*P67/$H67*P68/$H68 -> 129.55568 | ... Z69: =$H69*Z67/$H67*Z68/$H68 -> 132.43153 | AB69: 實績＝TrendForce 前五大 ÷ 前五大占比；以 2Q26 為錨
A70: 份額：三星 | B70: % | C70: =rv_ss_0/C69 -> 0.32468828 | D70: =rv_ss_1/D69 -> 0.329 | E70: =rv_ss_2/E69 -> 0.31929825 | F70: =rv_ss_3/F69 -> 0.28 | G70: =rv_ss_4/G69 -> 0.30736118 | H70: =rv_ss_5/H69 -> 0.293 | I70: =(rv_ss_4+rv_ss_5)/($G69+$H69) -> 0.29814637 | J70: =(rv_ss_4+rv_ss_5)/($G69+$H69) -> 0.29814637 | K70: =(rv_ss_4+rv_ss_5)/($G69+$H69)+dr_ss/100*1 -> 0.29314637 | L70: =(rv_ss_4+rv_ss_5)/($G69+$H69)+dr_ss/100*1 -> 0.29314637 | M70: =(rv_ss_4+rv_ss_5)/($G69+$H69)+dr_ss/100*1 -> 0.29314637 | N70: =(rv_ss_4+rv_ss_5)/($G69+$H69)+dr_ss/100*1 -> 0.29314637 | O70: =(rv_ss_4+rv_ss_5)/($G69+$H69)+dr_ss/100*2 -> 0.28814637 | P70: =(rv_ss_4+rv_ss_5)/($G69+$H69)+dr_ss/100*2 -> 0.28814637 | Q70: =(rv_ss_4+rv_ss_5)/($G69+$H69)+dr_ss/100*2 -> 0.28814637 | R70: =(rv_ss_4+rv_ss_5)/($G69+$H69)+dr_ss/100*2 -> 0.28814637 | S70: =(rv_ss_4+rv_ss_5)/($G69+$H69)+dr_ss/100*3 -> 0.28314637 | T70: =(rv_ss_4+rv_ss_5)/($G69+$H69)+dr_ss/100*3 -> 0.28314637 | U70: =(rv_ss_4+rv_ss_5)/($G69+$H69)+dr_ss/100*3 -> 0.28314637 | V70: =(rv_ss_4+rv_ss_5)/($G69+$H69)+dr_ss/100*3 -> 0.28314637 | W70: =(rv_ss_4+rv_ss_5)/($G69+$H69)+dr_ss/100*4 -> 0.27814637 | X70: =(rv_ss_4+rv_ss_5)/($G69+$H69)+dr_ss/100*4 -> 0.27814637 | Y70: =(rv_ss_4+rv_ss_5)/($G69+$H69)+dr_ss/100*4 -> 0.27814637 | Z70: =(rv_ss_4+rv_ss_5)/($G69+$H69)+dr_ss/100*4 -> 0.27814637 | AB70: 2026Q3–Q4＝1H26 實績份額；2027 起每年＋年變動
A71: 份額：SK 海力士＋Solidigm | B71: % | C71: =rv_sk_0/C69 -> 0.16930175 | D71: =rv_sk_1/D69 -> 0.21131923 | E71: =rv_sk_2/E69 -> 0.1878538 | F71: =rv_sk_3/F69 -> 0.2210303 | G71: =rv_sk_4/G69 -> 0.17131234 | H71: =rv_sk_5/H69 -> 0.1813144 | I71: =(rv_sk_4+rv_sk_5)/($G69+$H69) -> 0.17773013 | J71: =(rv_sk_4+rv_sk_5)/($G69+$H69) -> 0.17773013 | K71: =(rv_sk_4+rv_sk_5)/($G69+$H69)+dr_sk/100*1 -> 0.17773013 | L71: =(rv_sk_4+rv_sk_5)/($G69+$H69)+dr_sk/100*1 -> 0.17773013 | M71: =(rv_sk_4+rv_sk_5)/($G69+$H69)+dr_sk/100*1 -> 0.17773013 | N71: =(rv_sk_4+rv_sk_5)/($G69+$H69)+dr_sk/100*1 -> 0.17773013 | O71: =(rv_sk_4+rv_sk_5)/($G69+$H69)+dr_sk/100*2 -> 0.17773013 | P71: =(rv_sk_4+rv_sk_5)/($G69+$H69)+dr_sk/100*2 -> 0.17773013 | Q71: =(rv_sk_4+rv_sk_5)/($G69+$H69)+dr_sk/100*2 -> 0.17773013 | R71: =(rv_sk_4+rv_sk_5)/($G69+$H69)+dr_sk/100*2 -> 0.17773013 | S71: =(rv_sk_4+rv_sk_5)/($G69+$H69)+dr_sk/100*3 -> 0.17773013 | T71: =(rv_sk_4+rv_sk_5)/($G69+$H69)+dr_sk/100*3 -> 0.17773013 | U71: =(rv_sk_4+rv_sk_5)/($G69+$H69)+dr_sk/100*3 -> 0.17773013 | V71: =(rv_sk_4+rv_sk_5)/($G69+$H69)+dr_sk/100*3 -> 0.17773013 | W71: =(rv_sk_4+rv_sk_5)/($G69+$H69)+dr_sk/100*4 -> 0.17773013 | X71: =(rv_sk_4+rv_sk_5)/($G69+$H69)+dr_sk/100*4 -> 0.17773013 | Y71: =(rv_sk_4+rv_sk_5)/($G69+$H69)+dr_sk/100*4 -> 0.17773013 | Z71: =(rv_sk_4+rv_sk_5)/($G69+$H69)+dr_sk/100*4 -> 0.17773013 | AB71: 2026Q3–Q4＝1H26 實績份額；2027 起每年＋年變動
A72: 份額：美光 | B72: % | C72: =rv_mu_0/C69 -> 0.15693267 | D72: =rv_mu_1/D69 -> 0.13286538 | E72: =rv_mu_2/E69 -> 0.12878363 | F72: =rv_mu_3/F69 -> 0.12854545 | G72: =rv_mu_4/G69 -> 0.13536632 | H72: =rv_mu_5/H69 -> 0.15056592 | I72: =(rv_mu_4+rv_mu_5)/($G69+$H69) -> 0.1451191 | J72: =(rv_mu_4+rv_mu_5)/($G69+$H69) -> 0.1451191 | K72: =(rv_mu_4+rv_mu_5)/($G69+$H69)+dr_mu/100*1 -> 0.1471191 | L72: =(rv_mu_4+rv_mu_5)/($G69+$H69)+dr_mu/100*1 -> 0.1471191 | M72: =(rv_mu_4+rv_mu_5)/($G69+$H69)+dr_mu/100*1 -> 0.1471191 | N72: =(rv_mu_4+rv_mu_5)/($G69+$H69)+dr_mu/100*1 -> 0.1471191 | O72: =(rv_mu_4+rv_mu_5)/($G69+$H69)+dr_mu/100*2 -> 0.1491191 | P72: =(rv_mu_4+rv_mu_5)/($G69+$H69)+dr_mu/100*2 -> 0.1491191 | Q72: =(rv_mu_4+rv_mu_5)/($G69+$H69)+dr_mu/100*2 -> 0.1491191 | R72: =(rv_mu_4+rv_mu_5)/($G69+$H69)+dr_mu/100*2 -> 0.1491191 | S72: =(rv_mu_4+rv_mu_5)/($G69+$H69)+dr_mu/100*3 -> 0.1511191 | T72: =(rv_mu_4+rv_mu_5)/($G69+$H69)+dr_mu/100*3 -> 0.1511191 | U72: =(rv_mu_4+rv_mu_5)/($G69+$H69)+dr_mu/100*3 -> 0.1511191 | V72: =(rv_mu_4+rv_mu_5)/($G69+$H69)+dr_mu/100*3 -> 0.1511191 | W72: =(rv_mu_4+rv_mu_5)/($G69+$H69)+dr_mu/100*4 -> 0.1531191 | X72: =(rv_mu_4+rv_mu_5)/($G69+$H69)+dr_mu/100*4 -> 0.1531191 | Y72: =(rv_mu_4+rv_mu_5)/($G69+$H69)+dr_mu/100*4 -> 0.1531191 | Z72: =(rv_mu_4+rv_mu_5)/($G69+$H69)+dr_mu/100*4 -> 0.1531191 | AB72: 2026Q3–Q4＝1H26 實績份額；2027 起每年＋年變動
A73: 份額：Kioxia | B73: % | C73: =rv_kx_0/C69 -> 0.14842893 | D73: =rv_kx_1/D69 -> 0.13539615 | E73: =rv_kx_2/E69 -> 0.1511345 | F73: =rv_kx_3/F69 -> 0.14042424 | G73: =rv_kx_4/G69 -> 0.13559383 | H73: =rv_kx_5/H69 -> 0.13620815 | I73: =kx_g/kx_fxg/kx_k/$I69 -> 0.14610231 | J73: =(kx_g/kx_fxg/kx_k/$I69+kx_g4/kx_fxg4/kx_k/$J69)/2 -> 0.14020877 | K73: =(kx_g/kx_fxg/kx_k/$I69+kx_g4/kx_fxg4/kx_k/$J69)/2+dr_jv_A/100*1*(kx_g/kx_fxg/kx_k)/(kx_g/kx_fxg/kx_k+sd_g/sd_k) -> 0.14020877 | L73: =(kx_g/kx_fxg/kx_k/$I69+kx_g4/kx_fxg4/kx_k/$J69)/2+dr_jv_A/100*1*(kx_g/kx_fxg/kx_k)/(kx_g/kx_fxg/kx_k+sd_g/sd_k) -> 0.14020877 | M73: =(kx_g/kx_fxg/kx_k/$I69+kx_g4/kx_fxg4/kx_k/$J69)/2+dr_jv_A/100*1*(kx_g/kx_fxg/kx_k)/(kx_g/kx_fxg/kx_k+sd_g/sd_k) -> 0.14020877 | N73: =(kx_g/kx_fxg/kx_k/$I69+kx_g4/kx_fxg4/kx_k/$J69)/2+dr_jv_A/100*1*(kx_g/kx_fxg/kx_k)/(kx_g/kx_fxg/kx_k+sd_g/sd_k) -> 0.14020877 | O73: =(kx_g/kx_fxg/kx_k/$I69+kx_g4/kx_fxg4/kx_k/$J69)/2+dr_jv_A/100*2*(kx_g/kx_fxg/kx_k)/(kx_g/kx_fxg/kx_k+sd_g/sd_k) -> 0.14020877 | P73: =(kx_g/kx_fxg/kx_k/$I69+kx_g4/kx_fxg4/kx_k/$J69)/2+dr_jv_A/100*2*(kx_g/kx_fxg/kx_k)/(kx_g/kx_fxg/kx_k+sd_g/sd_k) -> 0.14020877 | Q73: =(kx_g/kx_fxg/kx_k/$I69+kx_g4/kx_fxg4/kx_k/$J69)/2+dr_jv_A/100*2*(kx_g/kx_fxg/kx_k)/(kx_g/kx_fxg/kx_k+sd_g/sd_k) -> 0.14020877 | R73: =(kx_g/kx_fxg/kx_k/$I69+kx_g4/kx_fxg4/kx_k/$J69)/2+dr_jv_A/100*2*(kx_g/kx_fxg/kx_k)/(kx_g/kx_fxg/kx_k+sd_g/sd_k) -> 0.14020877 | S73: =(kx_g/kx_fxg/kx_k/$I69+kx_g4/kx_fxg4/kx_k/$J69)/2+dr_jv_A/100*3*(kx_g/kx_fxg/kx_k)/(kx_g/kx_fxg/kx_k+sd_g/sd_k) -> 0.14020877 | T73: =(kx_g/kx_fxg/kx_k/$I69+kx_g4/kx_fxg4/kx_k/$J69)/2+dr_jv_A/100*3*(kx_g/kx_fxg/kx_k)/(kx_g/kx_fxg/kx_k+sd_g/sd_k) -> 0.14020877 | U73: =(kx_g/kx_fxg/kx_k/$I69+kx_g4/kx_fxg4/kx_k/$J69)/2+dr_jv_A/100*3*(kx_g/kx_fxg/kx_k)/(kx_g/kx_fxg/kx_k+sd_g/sd_k) -> 0.14020877 | V73: =(kx_g/kx_fxg/kx_k/$I69+kx_g4/kx_fxg4/kx_k/$J69)/2+dr_jv_A/100*3*(kx_g/kx_fxg/kx_k)/(kx_g/kx_fxg/kx_k+sd_g/sd_k) -> 0.14020877 | W73: =(kx_g/kx_fxg/kx_k/$I69+kx_g4/kx_fxg4/kx_k/$J69)/2+dr_jv_A/100*4*(kx_g/kx_fxg/kx_k)/(kx_g/kx_fxg/kx_k+sd_g/sd_k) -> 0.14020877 | X73: =(kx_g/kx_fxg/kx_k/$I69+kx_g4/kx_fxg4/kx_k/$J69)/2+dr_jv_A/100*4*(kx_g/kx_fxg/kx_k)/(kx_g/kx_fxg/kx_k+sd_g/sd_k) -> 0.14020877 | Y73: =(kx_g/kx_fxg/kx_k/$I69+kx_g4/kx_fxg4/kx_k/$J69)/2+dr_jv_A/100*4*(kx_g/kx_fxg/kx_k)/(kx_g/kx_fxg/kx_k+sd_g/sd_k) -> 0.14020877 | Z73: =(kx_g/kx_fxg/kx_k/$I69+kx_g4/kx_fxg4/kx_k/$J69)/2+dr_jv_A/100*4*(kx_g/kx_fxg/kx_k)/(kx_g/kx_fxg/kx_k+sd_g/sd_k) -> 0.14020877 | AB73: 2026Q3＝公司第二季實績 ÷ 匯率 ÷ 公司口徑係數 ÷ 市場；2026Q4 起＝2026Q3 實績份額與 2026Q4 指引份額的平均（平滑出貨季別移動）；2027 起＋合資群年變動 × Kioxia 比重
A74: 份額：SanDisk | B74: % | C74: =rv_sd_0/C69 -> 0.13064838 | D74: =rv_sd_1/D69 -> 0.12021154 | E74: =rv_sd_2/E69 -> 0.12292982 | F74: =rv_sd_3/F69 -> 0.12854545 | G74: =rv_sd_4/G69 -> 0.13536632 | H74: =rv_sd_5/H69 -> 0.11397268 | I74: =sd_g/sd_k/$I69 -> 0.1078536 | J74: =(sd_g/sd_k/$I69+sd_g4/sd_k/$J69)/2 -> 0.10783628 | K74: =(sd_g/sd_k/$I69+sd_g4/sd_k/$J69)/2+dr_jv_A/100*1*(sd_g/sd_k)/(kx_g/kx_fxg/kx_k+sd_g/sd_k) -> 0.10783628 | L74: =(sd_g/sd_k/$I69+sd_g4/sd_k/$J69)/2+dr_jv_A/100*1*(sd_g/sd_k)/(kx_g/kx_fxg/kx_k+sd_g/sd_k) -> 0.10783628 | M74: =(sd_g/sd_k/$I69+sd_g4/sd_k/$J69)/2+dr_jv_A/100*1*(sd_g/sd_k)/(kx_g/kx_fxg/kx_k+sd_g/sd_k) -> 0.10783628 | N74: =(sd_g/sd_k/$I69+sd_g4/sd_k/$J69)/2+dr_jv_A/100*1*(sd_g/sd_k)/(kx_g/kx_fxg/kx_k+sd_g/sd_k) -> 0.10783628 | O74: =(sd_g/sd_k/$I69+sd_g4/sd_k/$J69)/2+dr_jv_A/100*2*(sd_g/sd_k)/(kx_g/kx_fxg/kx_k+sd_g/sd_k) -> 0.10783628 | P74: =(sd_g/sd_k/$I69+sd_g4/sd_k/$J69)/2+dr_jv_A/100*2*(sd_g/sd_k)/(kx_g/kx_fxg/kx_k+sd_g/sd_k) -> 0.10783628 | Q74: =(sd_g/sd_k/$I69+sd_g4/sd_k/$J69)/2+dr_jv_A/100*2*(sd_g/sd_k)/(kx_g/kx_fxg/kx_k+sd_g/sd_k) -> 0.10783628 | R74: =(sd_g/sd_k/$I69+sd_g4/sd_k/$J69)/2+dr_jv_A/100*2*(sd_g/sd_k)/(kx_g/kx_fxg/kx_k+sd_g/sd_k) -> 0.10783628 | S74: =(sd_g/sd_k/$I69+sd_g4/sd_k/$J69)/2+dr_jv_A/100*3*(sd_g/sd_k)/(kx_g/kx_fxg/kx_k+sd_g/sd_k) -> 0.10783628 | T74: =(sd_g/sd_k/$I69+sd_g4/sd_k/$J69)/2+dr_jv_A/100*3*(sd_g/sd_k)/(kx_g/kx_fxg/kx_k+sd_g/sd_k) -> 0.10783628 | U74: =(sd_g/sd_k/$I69+sd_g4/sd_k/$J69)/2+dr_jv_A/100*3*(sd_g/sd_k)/(kx_g/kx_fxg/kx_k+sd_g/sd_k) -> 0.10783628 | V74: =(sd_g/sd_k/$I69+sd_g4/sd_k/$J69)/2+dr_jv_A/100*3*(sd_g/sd_k)/(kx_g/kx_fxg/kx_k+sd_g/sd_k) -> 0.10783628 | W74: =(sd_g/sd_k/$I69+sd_g4/sd_k/$J69)/2+dr_jv_A/100*4*(sd_g/sd_k)/(kx_g/kx_fxg/kx_k+sd_g/sd_k) -> 0.10783628 | X74: =(sd_g/sd_k/$I69+sd_g4/sd_k/$J69)/2+dr_jv_A/100*4*(sd_g/sd_k)/(kx_g/kx_fxg/kx_k+sd_g/sd_k) -> 0.10783628 | Y74: =(sd_g/sd_k/$I69+sd_g4/sd_k/$J69)/2+dr_jv_A/100*4*(sd_g/sd_k)/(kx_g/kx_fxg/kx_k+sd_g/sd_k) -> 0.10783628 | Z74: =(sd_g/sd_k/$I69+sd_g4/sd_k/$J69)/2+dr_jv_A/100*4*(sd_g/sd_k)/(kx_g/kx_fxg/kx_k+sd_g/sd_k) -> 0.10783628 | AB74: 2026Q3＝公司 FQ1 FY27 實績 ÷ 口徑係數 ÷ 市場；2026Q4 起＝2026Q3 實績份額與 FQ2 FY27 指引份額的平均；2027 起＋合資群年變動 × SanDisk 比重
A75: 份額：其他（長江存儲等） | B75: % | C75: =1-t5_0 -> 0.07 | D75: =1-t5_1 -> 0.071207692 | E75: =1-t5_2 -> 0.09 | F75: =1-t5_3 -> 0.10145455 | G75: =1-t5_4 -> 0.115 | H75: =1-t5_5 -> 0.12493886 | I75: =1-I70-I71-I72-I73-I74 -> 0.12504849 | J75: =1-J70-J71-J72-J73-J74 -> 0.13095936 | K75: =1-K70-K71-K72-K73-K74 -> 0.13395936 | L75: =1-L70-L71-L72-L73-L74 -> 0.13395936 | M75: =1-M70-M71-M72-M73-M74 -> 0.13395936 | N75: =1-N70-N71-N72-N73-N74 -> 0.13395936 | O75: =1-O70-O71-O72-O73-O74 -> 0.13695936 | P75: =1-P70-P71-P72-P73-P74 -> 0.13695936 | ... Z75: =1-Z70-Z71-Z72-Z73-Z74 -> 0.14295936 | AB75: 餘額（長江存儲等）
A76: 三星 營收（情境 A） | B76: $B | C76: =C69*C70 -> 4.2 | D76: =D69*D70 -> 5.2 | E76: =E69*E70 -> 6 | F76: =F69*F70 -> 6.6 | G76: =G69*G70 -> 13.51 | H76: =H69*H70 -> 23.06 | I76: =I69*I70 -> 30.510681 | J76: =J69*J70 -> 34.308227 | ... Z76: =Z69*Z70 -> 36.83535
A77: SK 海力士＋Solidigm 營收（情境 A） | B77: $B | C77: =C69*C71 -> 2.19 | D77: =D69*D71 -> 3.34 | E77: =E69*E71 -> 3.53 | F77: =F69*F71 -> 5.21 | G77: =G69*G71 -> 7.53 | H77: =H69*H71 -> 14.27 | I77: =I69*I71 -> 18.187937 | J77: =J69*J71 -> 20.451719 | ... Z77: =Z69*Z71 -> 23.537074
A78: 美光 營收（情境 A） | B78: $B | C78: =C69*C72 -> 2.03 | D78: =D69*D72 -> 2.1 | E78: =E69*E72 -> 2.42 | F78: =F69*F72 -> 3.03 | G78: =G69*G72 -> 5.95 | H78: =H69*H72 -> 11.85 | I78: =I69*I72 -> 14.850701 | J78: =J69*J72 -> 16.69911 | ... Z78: =Z69*Z72 -> 20.277797
A79: Kioxia 營收（情境 A） | B79: $B | C79: =C69*C73 -> 1.92 | D79: =D69*D73 -> 2.14 | E79: =E69*E73 -> 2.84 | F79: =F69*F73 -> 3.31 | G79: =G69*G73 -> 5.96 | H79: =H69*H73 -> 10.72 | I79: =I69*I73 -> 14.951317 | J79: =J69*J73 -> 16.134069 | ... Z79: =Z69*Z73 -> 18.568062
A80: SanDisk 營收（情境 A） | B80: $B | C80: =C69*C74 -> 1.69 | D80: =D69*D74 -> 1.9 | E80: =E69*E74 -> 2.31 | F80: =F69*F74 -> 3.03 | G80: =G69*G74 -> 5.95 | H80: =H69*H74 -> 8.97 | I80: =I69*I74 -> 11.037152 | J80: =J69*J74 -> 12.40891 | ... Z80: =Z69*Z74 -> 14.280923
A81: 其他（長江存儲等） 營收（情境 A） | B81: $B | C81: =C69*C75 -> 0.90548387 | D81: =D69*D75 -> 1.1254711 | E81: =E69*E75 -> 1.6912088 | F81: =F69*F75 -> 2.3914286 | G81: =G69*G75 -> 5.0548023 | H81: =H69*H75 -> 9.8330717 | I81: =I69*I75 -> 12.796784 | J81: =J69*J75 -> 15.069723 | ... Z81: =Z69*Z75 -> 18.932327
A82: Kioxia＋SanDisk（合資群）份額（情境 A） | B82: % | C82: =C73+C74 -> 0.27907731 | D82: =D73+D74 -> 0.25560769 | E82: =E73+E74 -> 0.27406433 | F82: =F73+F74 -> 0.2689697 | G82: =G73+G74 -> 0.27096015 | H82: =H73+H74 -> 0.25018083 | I82: =I73+I74 -> 0.25395591 | J82: =J73+J74 -> 0.24804504 | ... Z82: =Z73+Z74 -> 0.24804504
A83: Kioxia 位元（情境 A；季度出貨 × 營收份額） | B83: EB | C83: =C68*C73 -> 35.545444 | D83: =D68*D73 -> 33.356174 | E83: =E68*E73 -> 38.303462 | F83: =F68*F73 -> 36.611793 | G83: =G68*G73 -> 37.373167 | H83: =H68*H73 -> 39.052042 | I83: =I68*I73 -> 43.573094 | J83: =J68*J73 -> 43.496786 | ... Z83: =Z68*Z73 -> 86.690603 | AB83: 假設該廠平均售價＝市場平均（份額以營收計）；公司模型以此列的變動率推單位成本
A84: SanDisk 位元（情境 A；季度出貨 × 營收份額） | B84: EB | C84: =C68*C74 -> 31.287396 | D84: =D68*D74 -> 29.615294 | E84: =E68*E74 -> 31.15528 | F84: =F68*F74 -> 33.514723 | G84: =G68*G74 -> 37.31046 | H84: =H68*H74 -> 32.676942 | I84: =I68*I74 -> 32.16592 | J84: =J68*J74 -> 33.45391 | ... Z84: =Z68*Z74 -> 66.674802
A85: 檢查：份額合計 − 1；實績季營收重現（應為 0） | B85: — | C85: =ABS(SUM(C70:C75)-1)+ABS(SUM(I70:I75)-1)+ABS(SUM(Z70:Z75)-1)+ABS(H80-rv_sd_5) -> 0
A110: 案例區塊：每顆容量 +20%（情境 A）
A111: A. 年度（日曆年） | B111: 單位 | C111: CY2024 | D111: CY2025 | E111: CY2026 | F111: CY2027 | G111: CY2028 | H111: CY2029 | I111: CY2030 | AB111: 說明
A112: 加速器顆數（同字母情境係數） | B112: 百萬顆 | E112: =(u_26)*1 -> 15.2 | F112: =(u_27)*1 -> 23.7 | G112: =(u_28)*um28_A -> 26.5 | H112: =(u_28*(1+g_u29))*um29_A -> 30.15 | I112: =(u_28*(1+g_u29)*(1+g_u30))*um29_A -> 31.6575 | AB112: markets/memory UNITS × SCEN_UNITS；2029–30 基準以 g_u29、g_u30 外推，CY2030 沿用 um29
A113: 每顆企業級 SSD 容量 | B113: TB | E113: =tb_26_hi -> 36 | F113: =tb_27_hi -> 41 | G113: =tb_28_hi -> 48 | H113: =tb_29_hi -> 55 | I113: =tb_30_hi -> 62
A114: 需求：AI 企業級 SSD | B114: EB | D114: =bits25*sh_essd25*ai25 -> 165 | E114: =E112*E113 -> 547.2 | F114: =F112*F113 -> 971.7 | G114: =G112*G113 -> 1272 | H114: =H112*H113 -> 1658.25 | I114: =I112*I113 -> 1962.765 | AB114: 顆數 × 每顆容量（百萬顆 × TB＝EB）；2025＝基期 × 占比
A115: 需求：非 AI 企業級 SSD | B115: EB | D115: =bits25*sh_essd25*(1-ai25) -> 135 | E115: =D115*(1+g_nai) -> 148.5 | F115: =E115*(1+g_nai) -> 163.35 | G115: =F115*(1+g_nai) -> 179.685 | H115: =G115*(1+g_nai) -> 197.6535 | I115: =H115*(1+g_nai) -> 217.41885
A116: 需求：手機 | B116: EB | D116: =bits25*sh_mob25 -> 320 | E116: =D116*(1+g_mob_26) -> 304 | F116: =E116*(1+g_mob_27) -> 313.12 | G116: =F116*(1+g_mob_28) -> 338.1696 | H116: =G116*(1+g_mob_28) -> 365.22317 | I116: =H116*(1+g_mob_28) -> 394.44102
A117: 需求：PC（client SSD） | B117: EB | D117: =bits25*sh_pc25 -> 230 | E117: =D117*(1+g_pc_26) -> 218.5 | F117: =E117*(1+g_pc_27) -> 218.5 | G117: =F117*(1+g_pc_28) -> 231.61 | H117: =G117*(1+g_pc_28) -> 245.5066 | I117: =H117*(1+g_pc_28) -> 260.237
A118: 需求：消費性與其他 | B118: EB | D118: =bits25*(1-sh_essd25-sh_mob25-sh_pc25) -> 150 | E118: =D118*(1+g_con_26) -> 135 | F118: =E118*(1+g_con_27) -> 135 | G118: =F118*(1+g_con_28) -> 141.75 | H118: =G118*(1+g_con_28) -> 148.8375 | I118: =H118*(1+g_con_28) -> 156.27937
A119: 位元需求合計 | B119: EB | D119: =SUM(D114:D118) -> 1000 | E119: =SUM(E114:E118) -> 1353.2 | F119: =SUM(F114:F118) -> 1801.67 | G119: =SUM(G114:G118) -> 2163.2146 | H119: =SUM(H114:H118) -> 2615.4708 | I119: =SUM(I114:I118) -> 2991.1412
A120: 企業級 SSD 占位元需求 | B120: % | D120: =(D114+D115)/D119 -> 0.3 | E120: =(E114+E115)/E119 -> 0.51411469 | F120: =(F114+F115)/F119 -> 0.62999883 | G120: =(G114+G115)/G119 -> 0.67107766 | H120: =(H114+H115)/H119 -> 0.70958679 | I120: =(I114+I115)/I119 -> 0.72888027
A121: 位元供給（三情境相同） | B121: EB | D121: =bits25 -> 1000 | E121: =D121*(1+gs_26) -> 1210 | F121: =E121*(1+gs_27) -> 1512.5 | G121: =F121*(1+gs_28) -> 1890.625 | H121: =G121*(1+gs_29) -> 2306.5625 | I121: =H121*(1+gs_30) -> 2767.875 | AB121: 2025＝出貨實績（基期）；供給不隨需求情境變（產能 2027 前已訂定），需求不足的結果是閒置產能與降價
A122: 需求 ÷ 供給 − 1（>0＝短缺） | B122: % | E122: =E119/E121-1 -> 0.11834711 | F122: =F119/F121-1 -> 0.19118678 | G122: =G119/G121-1 -> 0.14417962 | H122: =H119/H121-1 -> 0.13392582 | I122: =I119/I121-1 -> 0.080663412
A123: 位元出貨＝MIN(需求, 供給) | B123: EB | C123: =bits25/(1+g25) -> 892.85714 | D123: =bits25 -> 1000 | E123: =MIN(E119,E121) -> 1210 | F123: =MIN(F119,F121) -> 1512.5 | G123: =MIN(G119,G121) -> 1890.625 | H123: =MIN(H119,H121) -> 2306.5625 | I123: =MIN(I119,I121) -> 2767.875
A124: 位元出貨年增 | B124: % | D124: =D123/C123-1 -> 0.12 | E124: =E123/D123-1 -> 0.21 | F124: =F123/E123-1 -> 0.25 | G124: =G123/F123-1 -> 0.25 | H124: =H123/G123-1 -> 0.22 | I124: =I123/H123-1 -> 0.2
A125: NAND 市場營收（四季合計） | B125: $B | C125: =rev24 -> 67.4 | D125: =SUM(C139:F139) -> 71.103592 | E125: =SUM(G139:J139) -> 342.82075 | F125: =SUM(K139:N139) -> 536.73468 | G125: =SUM(O139:R139) -> 544.61015 | H125: =SUM(S139:V139) -> 570.46528 | I125: =SUM(W139:Z139) -> 603.84615 | AB125: CY2024 為 TrendForce 年度值
A126: 市場營收年增 | B126: % | D126: =D125/C125-1 -> 0.054949442 | E126: =E125/D125-1 -> 3.8214266 | F126: =F125/E125-1 -> 0.56564233 | G126: =G125/F125-1 -> 0.014672931 | H126: =H125/G125-1 -> 0.04747456 | I126: =I125/H125-1 -> 0.058515169
A127: 平均售價（營收 ÷ 位元出貨） | B127: $/GB | C127: =C125/C123 -> 0.075488 | D127: =D125/D123 -> 0.071103592 | E127: =E125/E123 -> 0.28332293 | F127: =F125/F123 -> 0.3548659 | G127: =G125/G123 -> 0.28805826 | H127: =H125/H123 -> 0.2473227 | I127: =I125/I123 -> 0.21816236
A128: 平均售價年變動 | B128: % | D128: =D127/C127-1 -> -0.058080856 | E128: =E127/D127-1 -> 2.9846501 | F128: =F127/E127-1 -> 0.25251387 | G128: =G127/F127-1 -> -0.18826165 | H128: =H127/G127-1 -> -0.1414143 | I128: =I127/H127-1 -> -0.11790403 | AB128: CY2030 為收斂法（p10）＋位元平滑效果
A129: 年度份額：三星 | B129: % | D129: =SUM(C146:F146)/D125 -> 0.30940771 | E129: =SUM(G146:J146)/E125 -> 0.29814637 | F129: =SUM(K146:N146)/F125 -> 0.29314637 | G129: =SUM(O146:R146)/G125 -> 0.28814637 | H129: =SUM(S146:V146)/H125 -> 0.28314637 | I129: =SUM(W146:Z146)/I125 -> 0.27814637
A130: 年度份額：SK 海力士＋Solidigm | B130: % | D130: =SUM(C147:F147)/D125 -> 0.20069309 | E130: =SUM(G147:J147)/E125 -> 0.17773013 | F130: =SUM(K147:N147)/F125 -> 0.17773013 | G130: =SUM(O147:R147)/G125 -> 0.17773013 | H130: =SUM(S147:V147)/H125 -> 0.17773013 | I130: =SUM(W147:Z147)/I125 -> 0.17773013
A131: 年度份額：美光 | B131: % | D131: =SUM(C148:F148)/D125 -> 0.134733 | E131: =SUM(G148:J148)/E125 -> 0.1451191 | F131: =SUM(K148:N148)/F125 -> 0.1471191 | G131: =SUM(O148:R148)/G125 -> 0.1491191 | H131: =SUM(S148:V148)/H125 -> 0.1511191 | I131: =SUM(W148:Z148)/I125 -> 0.1531191
A132: 年度份額：Kioxia | B132: % | D132: =SUM(C149:F149)/D125 -> 0.14359331 | E132: =SUM(G149:J149)/E125 -> 0.13953322 | F132: =SUM(K149:N149)/F125 -> 0.13851299 | G132: =SUM(O149:R149)/G125 -> 0.13851299 | H132: =SUM(S149:V149)/H125 -> 0.13851299 | I132: =SUM(W149:Z149)/I125 -> 0.13851299
A133: 年度份額：SanDisk | B133: % | D133: =SUM(C150:F150)/D125 -> 0.1255914 | E133: =SUM(G150:J150)/E125 -> 0.11206254 | F133: =SUM(K150:N150)/F125 -> 0.10651367 | G133: =SUM(O150:R150)/G125 -> 0.10651367 | H133: =SUM(S150:V150)/H125 -> 0.10651367 | I133: =SUM(W150:Z150)/I125 -> 0.10651367
A134: 年度份額：其他（長江存儲等） | B134: % | D134: =SUM(C151:F151)/D125 -> 0.085981484 | E134: =SUM(G151:J151)/E125 -> 0.12740864 | F134: =SUM(K151:N151)/F125 -> 0.13697774 | G134: =SUM(O151:R151)/G125 -> 0.13997774 | H134: =SUM(S151:V151)/H125 -> 0.14297774 | I134: =SUM(W151:Z151)/I125 -> 0.14597774
A136: B. 季度 | B136: 單位 | C136: 2025Q1 | D136: 2025Q2 | E136: 2025Q3 | F136: 2025Q4 | G136: 2026Q1 | H136: 2026Q2 | I136: 2026Q3 | J136: 2026Q4 | K136: 2027Q1 | L136: 2027Q2 | M136: 2027Q3 | N136: 2027Q4 | O136: 2028Q1 | P136: 2028Q2 | Q136: 2028Q3 | R136: 2028Q4 | S136: 2029Q1 | T136: 2029Q2 | U136: 2029Q3 | V136: 2029Q4 | W136: 2030Q1 | X136: 2030Q2 | Y136: 2030Q3 | Z136: 2030Q4 | AB136: 說明
A137: 合約價指數（同字母路徑） | B137: 2025Q1＝1 | C137: =Path!C4 -> 1 | D137: =Path!D4 -> 1 | E137: =Path!E4 -> 1.05 | F137: =Path!F4 -> 1.365 | G137: =Path!G4 -> 2.559375 | H137: =Path!H4 -> 4.4149219 | I137: =Path!I4 -> 5.5186523 | J137: =Path!J4 -> 5.9656632 | K137: =Path!K4*1 -> 6.1446331 | L137: =Path!L4*1 -> 6.1446331 | M137: =Path!M4*1 -> 5.8374014 | N137: =Path!N4*1 -> 5.4287833 | O137: =Path!O4*1 -> 5.1573442 | P137: =Path!P4*1 -> 4.899477 | Q137: =Path!Q4*1 -> 4.6545031 | R137: =Path!R4*1 -> 4.4217779 | ... V137: =Path!V4*1 -> 3.9145682 | W137: =Path!V4*(1+p10)^(1/4)*1 -> 3.791443 | X137: =Path!V4*(1+p10)^(2/4)*1 -> 3.6721905 | Y137: =Path!V4*(1+p10)^(3/4)*1 -> 3.5566888 | Z137: =Path!V4*(1+p10)^(4/4)*1 -> 3.44482 | AB137: Path 頁；Sens 可對 2027 起的季價乘價格係數
A138: 季度位元出貨（年內依年增平滑；四季合計＝年度） | B138: EB | C138: =D123/4*(D123/C123)^((1-2.5)/4)/(((D123/C123)^(-0.375)+(D123/C123)^(-0.125)+(D123/C123)^(0.125)+(D123/C123)^(0.375))/4) -> 239.47787 | D138: =D123/4*(D123/C123)^((2-2.5)/4)/(((D123/C123)^(-0.375)+(D123/C123)^(-0.125)+(D123/C123)^(0.125)+(D123/C123)^(0.375))/4) -> 246.35983 | E138: =D123/4*(D123/C123)^((3-2.5)/4)/(((D123/C123)^(-0.375)+(D123/C123)^(-0.125)+(D123/C123)^(0.125)+(D123/C123)^(0.375))/4) -> 253.43956 | F138: =D123/4*(D123/C123)^((4-2.5)/4)/(((D123/C123)^(-0.375)+(D123/C123)^(-0.125)+(D123/C123)^(0.125)+(D123/C123)^(0.375))/4) -> 260.72274 | G138: =E123/4*(E123/D123)^((1-2.5)/4)/(((E123/D123)^(-0.375)+(E123/D123)^(-0.125)+(E123/D123)^(0.125)+(E123/D123)^(0.375))/4) -> 281.23193 | H138: =E123/4*(E123/D123)^((2-2.5)/4)/(((E123/D123)^(-0.375)+(E123/D123)^(-0.125)+(E123/D123)^(0.125)+(E123/D123)^(0.375))/4) -> 294.95854 | I138: =E123/4*(E123/D123)^((3-2.5)/4)/(((E123/D123)^(-0.375)+(E123/D123)^(-0.125)+(E123/D123)^(0.125)+(E123/D123)^(0.375))/4) -> 309.35513 | J138: =E123/4*(E123/D123)^((4-2.5)/4)/(((E123/D123)^(-0.375)+(E123/D123)^(-0.125)+(E123/D123)^(0.125)+(E123/D123)^(0.375))/4) -> 324.4544 | K138: =F123/4*(F123/E123)^((1-2.5)/4)/(((F123/E123)^(-0.375)+(F123/E123)^(-0.125)+(F123/E123)^(0.125)+(F123/E123)^(0.375))/4) -> 347.09614 | L138: =F123/4*(F123/E123)^((2-2.5)/4)/(((F123/E123)^(-0.375)+(F123/E123)^(-0.125)+(F123/E123)^(0.125)+(F123/E123)^(0.375))/4) -> 367.00949 | M138: =F123/4*(F123/E123)^((3-2.5)/4)/(((F123/E123)^(-0.375)+(F123/E123)^(-0.125)+(F123/E123)^(0.125)+(F123/E123)^(0.375))/4) -> 388.06529 | N138: =F123/4*(F123/E123)^((4-2.5)/4)/(((F123/E123)^(-0.375)+(F123/E123)^(-0.125)+(F123/E123)^(0.125)+(F123/E123)^(0.375))/4) -> 410.32908 | O138: =G123/4*(G123/F123)^((1-2.5)/4)/(((G123/F123)^(-0.375)+(G123/F123)^(-0.125)+(G123/F123)^(0.125)+(G123/F123)^(0.375))/4) -> 433.87018 | P138: =G123/4*(G123/F123)^((2-2.5)/4)/(((G123/F123)^(-0.375)+(G123/F123)^(-0.125)+(G123/F123)^(0.125)+(G123/F123)^(0.375))/4) -> 458.76186 | Q138: =G123/4*(G123/F123)^((3-2.5)/4)/(((G123/F123)^(-0.375)+(G123/F123)^(-0.125)+(G123/F123)^(0.125)+(G123/F123)^(0.375))/4) -> 485.08161 | R138: =G123/4*(G123/F123)^((4-2.5)/4)/(((G123/F123)^(-0.375)+(G123/F123)^(-0.125)+(G123/F123)^(0.125)+(G123/F123)^(0.375))/4) -> 512.91135 | S138: =H123/4*(H123/G123)^((1-2.5)/4)/(((H123/G123)^(-0.375)+(H123/G123)^(-0.125)+(H123/G123)^(0.125)+(H123/G123)^(0.375))/4) -> 534.37942 | T138: =H123/4*(H123/G123)^((2-2.5)/4)/(((H123/G123)^(-0.375)+(H123/G123)^(-0.125)+(H123/G123)^(0.125)+(H123/G123)^(0.375))/4) -> 561.61627 | U138: =H123/4*(H123/G123)^((3-2.5)/4)/(((H123/G123)^(-0.375)+(H123/G123)^(-0.125)+(H123/G123)^(0.125)+(H123/G123)^(0.375))/4) -> 590.24136 | V138: =H123/4*(H123/G123)^((4-2.5)/4)/(((H123/G123)^(-0.375)+(H123/G123)^(-0.125)+(H123/G123)^(0.125)+(H123/G123)^(0.375))/4) -> 620.32545 | W138: =I123/4*(I123/H123)^((1-2.5)/4)/(((I123/H123)^(-0.375)+(I123/H123)^(-0.125)+(I123/H123)^(0.125)+(I123/H123)^(0.375))/4) -> 645.40118 | X138: =I123/4*(I123/H123)^((2-2.5)/4)/(((I123/H123)^(-0.375)+(I123/H123)^(-0.125)+(I123/H123)^(0.125)+(I123/H123)^(0.375))/4) -> 675.49956 | Y138: =I123/4*(I123/H123)^((3-2.5)/4)/(((I123/H123)^(-0.375)+(I123/H123)^(-0.125)+(I123/H123)^(0.125)+(I123/H123)^(0.375))/4) -> 707.00157 | Z138: =I123/4*(I123/H123)^((4-2.5)/4)/(((I123/H123)^(-0.375)+(I123/H123)^(-0.125)+(I123/H123)^(0.125)+(I123/H123)^(0.375))/4) -> 739.97269 | AB138: 季度＝年度 ÷ 4 ×（1＋年增）^((季−2.5)/4)，再正規化使四季合計等於年度
A139: NAND 市場營收（2026Q2 前實績；之後＝2Q26 實績 × 價格指數比 × 位元比） | B139: $B | C139: =(rv_ss_0+rv_sk_0+rv_mu_0+rv_kx_0+rv_sd_0)/t5_0 -> 12.935484 | D139: =(rv_ss_1+rv_sk_1+rv_mu_1+rv_kx_1+rv_sd_1)/t5_1 -> 15.805471 | E139: =(rv_ss_2+rv_sk_2+rv_mu_2+rv_kx_2+rv_sd_2)/t5_2 -> 18.791209 | F139: =(rv_ss_3+rv_sk_3+rv_mu_3+rv_kx_3+rv_sd_3)/t5_3 -> 23.571429 | G139: =(rv_ss_4+rv_sk_4+rv_mu_4+rv_kx_4+rv_sd_4)/t5_4 -> 43.954802 | H139: =(rv_ss_5+rv_sk_5+rv_mu_5+rv_kx_5+rv_sd_5)/t5_5 -> 78.703072 | I139: =$H139*I137/$H137*I138/$H138 -> 103.1806 | J139: =$H139*J137/$H137*J138/$H138 -> 116.98228 | K139: =$H139*K137/$H137*K138/$H138 -> 128.90015 | L139: =$H139*L137/$H137*L138/$H138 -> 136.29532 | M139: =$H139*M137/$H137*M138/$H138 -> 136.90901 | N139: =$H139*N137/$H137*N138/$H138 -> 134.6302 | O139: =$H139*O137/$H137*O138/$H138 -> 135.2364 | P139: =$H139*P137/$H137*P138/$H138 -> 135.84533 | ... Z139: =$H139*Z137/$H137*Z138/$H138 -> 154.06001 | AB139: 實績＝TrendForce 前五大 ÷ 前五大占比；以 2Q26 為錨
A140: 份額：三星 | B140: % | C140: =rv_ss_0/C139 -> 0.32468828 | D140: =rv_ss_1/D139 -> 0.329 | E140: =rv_ss_2/E139 -> 0.31929825 | F140: =rv_ss_3/F139 -> 0.28 | G140: =rv_ss_4/G139 -> 0.30736118 | H140: =rv_ss_5/H139 -> 0.293 | I140: =(rv_ss_4+rv_ss_5)/($G139+$H139) -> 0.29814637 | J140: =(rv_ss_4+rv_ss_5)/($G139+$H139) -> 0.29814637 | K140: =(rv_ss_4+rv_ss_5)/($G139+$H139)+dr_ss/100*1 -> 0.29314637 | L140: =(rv_ss_4+rv_ss_5)/($G139+$H139)+dr_ss/100*1 -> 0.29314637 | M140: =(rv_ss_4+rv_ss_5)/($G139+$H139)+dr_ss/100*1 -> 0.29314637 | N140: =(rv_ss_4+rv_ss_5)/($G139+$H139)+dr_ss/100*1 -> 0.29314637 | O140: =(rv_ss_4+rv_ss_5)/($G139+$H139)+dr_ss/100*2 -> 0.28814637 | P140: =(rv_ss_4+rv_ss_5)/($G139+$H139)+dr_ss/100*2 -> 0.28814637 | Q140: =(rv_ss_4+rv_ss_5)/($G139+$H139)+dr_ss/100*2 -> 0.28814637 | R140: =(rv_ss_4+rv_ss_5)/($G139+$H139)+dr_ss/100*2 -> 0.28814637 | S140: =(rv_ss_4+rv_ss_5)/($G139+$H139)+dr_ss/100*3 -> 0.28314637 | T140: =(rv_ss_4+rv_ss_5)/($G139+$H139)+dr_ss/100*3 -> 0.28314637 | U140: =(rv_ss_4+rv_ss_5)/($G139+$H139)+dr_ss/100*3 -> 0.28314637 | V140: =(rv_ss_4+rv_ss_5)/($G139+$H139)+dr_ss/100*3 -> 0.28314637 | W140: =(rv_ss_4+rv_ss_5)/($G139+$H139)+dr_ss/100*4 -> 0.27814637 | X140: =(rv_ss_4+rv_ss_5)/($G139+$H139)+dr_ss/100*4 -> 0.27814637 | Y140: =(rv_ss_4+rv_ss_5)/($G139+$H139)+dr_ss/100*4 -> 0.27814637 | Z140: =(rv_ss_4+rv_ss_5)/($G139+$H139)+dr_ss/100*4 -> 0.27814637 | AB140: 2026Q3–Q4＝1H26 實績份額；2027 起每年＋年變動
A141: 份額：SK 海力士＋Solidigm | B141: % | C141: =rv_sk_0/C139 -> 0.16930175 | D141: =rv_sk_1/D139 -> 0.21131923 | E141: =rv_sk_2/E139 -> 0.1878538 | F141: =rv_sk_3/F139 -> 0.2210303 | G141: =rv_sk_4/G139 -> 0.17131234 | H141: =rv_sk_5/H139 -> 0.1813144 | I141: =(rv_sk_4+rv_sk_5)/($G139+$H139) -> 0.17773013 | J141: =(rv_sk_4+rv_sk_5)/($G139+$H139) -> 0.17773013 | K141: =(rv_sk_4+rv_sk_5)/($G139+$H139)+dr_sk/100*1 -> 0.17773013 | L141: =(rv_sk_4+rv_sk_5)/($G139+$H139)+dr_sk/100*1 -> 0.17773013 | M141: =(rv_sk_4+rv_sk_5)/($G139+$H139)+dr_sk/100*1 -> 0.17773013 | N141: =(rv_sk_4+rv_sk_5)/($G139+$H139)+dr_sk/100*1 -> 0.17773013 | O141: =(rv_sk_4+rv_sk_5)/($G139+$H139)+dr_sk/100*2 -> 0.17773013 | P141: =(rv_sk_4+rv_sk_5)/($G139+$H139)+dr_sk/100*2 -> 0.17773013 | Q141: =(rv_sk_4+rv_sk_5)/($G139+$H139)+dr_sk/100*2 -> 0.17773013 | R141: =(rv_sk_4+rv_sk_5)/($G139+$H139)+dr_sk/100*2 -> 0.17773013 | S141: =(rv_sk_4+rv_sk_5)/($G139+$H139)+dr_sk/100*3 -> 0.17773013 | T141: =(rv_sk_4+rv_sk_5)/($G139+$H139)+dr_sk/100*3 -> 0.17773013 | U141: =(rv_sk_4+rv_sk_5)/($G139+$H139)+dr_sk/100*3 -> 0.17773013 | V141: =(rv_sk_4+rv_sk_5)/($G139+$H139)+dr_sk/100*3 -> 0.17773013 | W141: =(rv_sk_4+rv_sk_5)/($G139+$H139)+dr_sk/100*4 -> 0.17773013 | X141: =(rv_sk_4+rv_sk_5)/($G139+$H139)+dr_sk/100*4 -> 0.17773013 | Y141: =(rv_sk_4+rv_sk_5)/($G139+$H139)+dr_sk/100*4 -> 0.17773013 | Z141: =(rv_sk_4+rv_sk_5)/($G139+$H139)+dr_sk/100*4 -> 0.17773013 | AB141: 2026Q3–Q4＝1H26 實績份額；2027 起每年＋年變動
A142: 份額：美光 | B142: % | C142: =rv_mu_0/C139 -> 0.15693267 | D142: =rv_mu_1/D139 -> 0.13286538 | E142: =rv_mu_2/E139 -> 0.12878363 | F142: =rv_mu_3/F139 -> 0.12854545 | G142: =rv_mu_4/G139 -> 0.13536632 | H142: =rv_mu_5/H139 -> 0.15056592 | I142: =(rv_mu_4+rv_mu_5)/($G139+$H139) -> 0.1451191 | J142: =(rv_mu_4+rv_mu_5)/($G139+$H139) -> 0.1451191 | K142: =(rv_mu_4+rv_mu_5)/($G139+$H139)+dr_mu/100*1 -> 0.1471191 | L142: =(rv_mu_4+rv_mu_5)/($G139+$H139)+dr_mu/100*1 -> 0.1471191 | M142: =(rv_mu_4+rv_mu_5)/($G139+$H139)+dr_mu/100*1 -> 0.1471191 | N142: =(rv_mu_4+rv_mu_5)/($G139+$H139)+dr_mu/100*1 -> 0.1471191 | O142: =(rv_mu_4+rv_mu_5)/($G139+$H139)+dr_mu/100*2 -> 0.1491191 | P142: =(rv_mu_4+rv_mu_5)/($G139+$H139)+dr_mu/100*2 -> 0.1491191 | Q142: =(rv_mu_4+rv_mu_5)/($G139+$H139)+dr_mu/100*2 -> 0.1491191 | R142: =(rv_mu_4+rv_mu_5)/($G139+$H139)+dr_mu/100*2 -> 0.1491191 | S142: =(rv_mu_4+rv_mu_5)/($G139+$H139)+dr_mu/100*3 -> 0.1511191 | T142: =(rv_mu_4+rv_mu_5)/($G139+$H139)+dr_mu/100*3 -> 0.1511191 | U142: =(rv_mu_4+rv_mu_5)/($G139+$H139)+dr_mu/100*3 -> 0.1511191 | V142: =(rv_mu_4+rv_mu_5)/($G139+$H139)+dr_mu/100*3 -> 0.1511191 | W142: =(rv_mu_4+rv_mu_5)/($G139+$H139)+dr_mu/100*4 -> 0.1531191 | X142: =(rv_mu_4+rv_mu_5)/($G139+$H139)+dr_mu/100*4 -> 0.1531191 | Y142: =(rv_mu_4+rv_mu_5)/($G139+$H139)+dr_mu/100*4 -> 0.1531191 | Z142: =(rv_mu_4+rv_mu_5)/($G139+$H139)+dr_mu/100*4 -> 0.1531191 | AB142: 2026Q3–Q4＝1H26 實績份額；2027 起每年＋年變動
A143: 份額：Kioxia | B143: % | C143: =rv_kx_0/C139 -> 0.14842893 | D143: =rv_kx_1/D139 -> 0.13539615 | E143: =rv_kx_2/E139 -> 0.1511345 | F143: =rv_kx_3/F139 -> 0.14042424 | G143: =rv_kx_4/G139 -> 0.13559383 | H143: =rv_kx_5/H139 -> 0.13620815 | I143: =kx_g/kx_fxg/kx_k/$I139 -> 0.14490434 | J143: =(kx_g/kx_fxg/kx_k/$I139+kx_g4/kx_fxg4/kx_k/$J139)/2 -> 0.13851299 | K143: =(kx_g/kx_fxg/kx_k/$I139+kx_g4/kx_fxg4/kx_k/$J139)/2+dr_jv_A/100*1*(kx_g/kx_fxg/kx_k)/(kx_g/kx_fxg/kx_k+sd_g/sd_k) -> 0.13851299 | L143: =(kx_g/kx_fxg/kx_k/$I139+kx_g4/kx_fxg4/kx_k/$J139)/2+dr_jv_A/100*1*(kx_g/kx_fxg/kx_k)/(kx_g/kx_fxg/kx_k+sd_g/sd_k) -> 0.13851299 | M143: =(kx_g/kx_fxg/kx_k/$I139+kx_g4/kx_fxg4/kx_k/$J139)/2+dr_jv_A/100*1*(kx_g/kx_fxg/kx_k)/(kx_g/kx_fxg/kx_k+sd_g/sd_k) -> 0.13851299 | N143: =(kx_g/kx_fxg/kx_k/$I139+kx_g4/kx_fxg4/kx_k/$J139)/2+dr_jv_A/100*1*(kx_g/kx_fxg/kx_k)/(kx_g/kx_fxg/kx_k+sd_g/sd_k) -> 0.13851299 | O143: =(kx_g/kx_fxg/kx_k/$I139+kx_g4/kx_fxg4/kx_k/$J139)/2+dr_jv_A/100*2*(kx_g/kx_fxg/kx_k)/(kx_g/kx_fxg/kx_k+sd_g/sd_k) -> 0.13851299 | P143: =(kx_g/kx_fxg/kx_k/$I139+kx_g4/kx_fxg4/kx_k/$J139)/2+dr_jv_A/100*2*(kx_g/kx_fxg/kx_k)/(kx_g/kx_fxg/kx_k+sd_g/sd_k) -> 0.13851299 | Q143: =(kx_g/kx_fxg/kx_k/$I139+kx_g4/kx_fxg4/kx_k/$J139)/2+dr_jv_A/100*2*(kx_g/kx_fxg/kx_k)/(kx_g/kx_fxg/kx_k+sd_g/sd_k) -> 0.13851299 | R143: =(kx_g/kx_fxg/kx_k/$I139+kx_g4/kx_fxg4/kx_k/$J139)/2+dr_jv_A/100*2*(kx_g/kx_fxg/kx_k)/(kx_g/kx_fxg/kx_k+sd_g/sd_k) -> 0.13851299 | S143: =(kx_g/kx_fxg/kx_k/$I139+kx_g4/kx_fxg4/kx_k/$J139)/2+dr_jv_A/100*3*(kx_g/kx_fxg/kx_k)/(kx_g/kx_fxg/kx_k+sd_g/sd_k) -> 0.13851299 | T143: =(kx_g/kx_fxg/kx_k/$I139+kx_g4/kx_fxg4/kx_k/$J139)/2+dr_jv_A/100*3*(kx_g/kx_fxg/kx_k)/(kx_g/kx_fxg/kx_k+sd_g/sd_k) -> 0.13851299 | U143: =(kx_g/kx_fxg/kx_k/$I139+kx_g4/kx_fxg4/kx_k/$J139)/2+dr_jv_A/100*3*(kx_g/kx_fxg/kx_k)/(kx_g/kx_fxg/kx_k+sd_g/sd_k) -> 0.13851299 | V143: =(kx_g/kx_fxg/kx_k/$I139+kx_g4/kx_fxg4/kx_k/$J139)/2+dr_jv_A/100*3*(kx_g/kx_fxg/kx_k)/(kx_g/kx_fxg/kx_k+sd_g/sd_k) -> 0.13851299 | W143: =(kx_g/kx_fxg/kx_k/$I139+kx_g4/kx_fxg4/kx_k/$J139)/2+dr_jv_A/100*4*(kx_g/kx_fxg/kx_k)/(kx_g/kx_fxg/kx_k+sd_g/sd_k) -> 0.13851299 | X143: =(kx_g/kx_fxg/kx_k/$I139+kx_g4/kx_fxg4/kx_k/$J139)/2+dr_jv_A/100*4*(kx_g/kx_fxg/kx_k)/(kx_g/kx_fxg/kx_k+sd_g/sd_k) -> 0.13851299 | Y143: =(kx_g/kx_fxg/kx_k/$I139+kx_g4/kx_fxg4/kx_k/$J139)/2+dr_jv_A/100*4*(kx_g/kx_fxg/kx_k)/(kx_g/kx_fxg/kx_k+sd_g/sd_k) -> 0.13851299 | Z143: =(kx_g/kx_fxg/kx_k/$I139+kx_g4/kx_fxg4/kx_k/$J139)/2+dr_jv_A/100*4*(kx_g/kx_fxg/kx_k)/(kx_g/kx_fxg/kx_k+sd_g/sd_k) -> 0.13851299 | AB143: 2026Q3＝公司第二季實績 ÷ 匯率 ÷ 公司口徑係數 ÷ 市場；2026Q4 起＝2026Q3 實績份額與 2026Q4 指引份額的平均（平滑出貨季別移動）；2027 起＋合資群年變動 × Kioxia 比重
A144: 份額：SanDisk | B144: % | C144: =rv_sd_0/C139 -> 0.13064838 | D144: =rv_sd_1/D139 -> 0.12021154 | E144: =rv_sd_2/E139 -> 0.12292982 | F144: =rv_sd_3/F139 -> 0.12854545 | G144: =rv_sd_4/G139 -> 0.13536632 | H144: =rv_sd_5/H139 -> 0.11397268 | I144: =sd_g/sd_k/$I139 -> 0.10696926 | J144: =(sd_g/sd_k/$I139+sd_g4/sd_k/$J139)/2 -> 0.10651367 | K144: =(sd_g/sd_k/$I139+sd_g4/sd_k/$J139)/2+dr_jv_A/100*1*(sd_g/sd_k)/(kx_g/kx_fxg/kx_k+sd_g/sd_k) -> 0.10651367 | L144: =(sd_g/sd_k/$I139+sd_g4/sd_k/$J139)/2+dr_jv_A/100*1*(sd_g/sd_k)/(kx_g/kx_fxg/kx_k+sd_g/sd_k) -> 0.10651367 | M144: =(sd_g/sd_k/$I139+sd_g4/sd_k/$J139)/2+dr_jv_A/100*1*(sd_g/sd_k)/(kx_g/kx_fxg/kx_k+sd_g/sd_k) -> 0.10651367 | N144: =(sd_g/sd_k/$I139+sd_g4/sd_k/$J139)/2+dr_jv_A/100*1*(sd_g/sd_k)/(kx_g/kx_fxg/kx_k+sd_g/sd_k) -> 0.10651367 | O144: =(sd_g/sd_k/$I139+sd_g4/sd_k/$J139)/2+dr_jv_A/100*2*(sd_g/sd_k)/(kx_g/kx_fxg/kx_k+sd_g/sd_k) -> 0.10651367 | P144: =(sd_g/sd_k/$I139+sd_g4/sd_k/$J139)/2+dr_jv_A/100*2*(sd_g/sd_k)/(kx_g/kx_fxg/kx_k+sd_g/sd_k) -> 0.10651367 | Q144: =(sd_g/sd_k/$I139+sd_g4/sd_k/$J139)/2+dr_jv_A/100*2*(sd_g/sd_k)/(kx_g/kx_fxg/kx_k+sd_g/sd_k) -> 0.10651367 | R144: =(sd_g/sd_k/$I139+sd_g4/sd_k/$J139)/2+dr_jv_A/100*2*(sd_g/sd_k)/(kx_g/kx_fxg/kx_k+sd_g/sd_k) -> 0.10651367 | S144: =(sd_g/sd_k/$I139+sd_g4/sd_k/$J139)/2+dr_jv_A/100*3*(sd_g/sd_k)/(kx_g/kx_fxg/kx_k+sd_g/sd_k) -> 0.10651367 | T144: =(sd_g/sd_k/$I139+sd_g4/sd_k/$J139)/2+dr_jv_A/100*3*(sd_g/sd_k)/(kx_g/kx_fxg/kx_k+sd_g/sd_k) -> 0.10651367 | U144: =(sd_g/sd_k/$I139+sd_g4/sd_k/$J139)/2+dr_jv_A/100*3*(sd_g/sd_k)/(kx_g/kx_fxg/kx_k+sd_g/sd_k) -> 0.10651367 | V144: =(sd_g/sd_k/$I139+sd_g4/sd_k/$J139)/2+dr_jv_A/100*3*(sd_g/sd_k)/(kx_g/kx_fxg/kx_k+sd_g/sd_k) -> 0.10651367 | W144: =(sd_g/sd_k/$I139+sd_g4/sd_k/$J139)/2+dr_jv_A/100*4*(sd_g/sd_k)/(kx_g/kx_fxg/kx_k+sd_g/sd_k) -> 0.10651367 | X144: =(sd_g/sd_k/$I139+sd_g4/sd_k/$J139)/2+dr_jv_A/100*4*(sd_g/sd_k)/(kx_g/kx_fxg/kx_k+sd_g/sd_k) -> 0.10651367 | Y144: =(sd_g/sd_k/$I139+sd_g4/sd_k/$J139)/2+dr_jv_A/100*4*(sd_g/sd_k)/(kx_g/kx_fxg/kx_k+sd_g/sd_k) -> 0.10651367 | Z144: =(sd_g/sd_k/$I139+sd_g4/sd_k/$J139)/2+dr_jv_A/100*4*(sd_g/sd_k)/(kx_g/kx_fxg/kx_k+sd_g/sd_k) -> 0.10651367 | AB144: 2026Q3＝公司 FQ1 FY27 實績 ÷ 口徑係數 ÷ 市場；2026Q4 起＝2026Q3 實績份額與 FQ2 FY27 指引份額的平均；2027 起＋合資群年變動 × SanDisk 比重
A145: 份額：其他（長江存儲等） | B145: % | C145: =1-t5_0 -> 0.07 | D145: =1-t5_1 -> 0.071207692 | E145: =1-t5_2 -> 0.09 | F145: =1-t5_3 -> 0.10145455 | G145: =1-t5_4 -> 0.115 | H145: =1-t5_5 -> 0.12493886 | I145: =1-I140-I141-I142-I143-I144 -> 0.12713079 | J145: =1-J140-J141-J142-J143-J144 -> 0.13397774 | K145: =1-K140-K141-K142-K143-K144 -> 0.13697774 | L145: =1-L140-L141-L142-L143-L144 -> 0.13697774 | M145: =1-M140-M141-M142-M143-M144 -> 0.13697774 | N145: =1-N140-N141-N142-N143-N144 -> 0.13697774 | O145: =1-O140-O141-O142-O143-O144 -> 0.13997774 | P145: =1-P140-P141-P142-P143-P144 -> 0.13997774 | ... Z145: =1-Z140-Z141-Z142-Z143-Z144 -> 0.14597774 | AB145: 餘額（長江存儲等）
A146: 三星 營收（情境 A） | B146: $B | C146: =C139*C140 -> 4.2 | D146: =D139*D140 -> 5.2 | E146: =E139*E140 -> 6 | F146: =F139*F140 -> 6.6 | G146: =G139*G140 -> 13.51 | H146: =H139*H140 -> 23.06 | I146: =I139*I140 -> 30.762921 | J146: =J139*J140 -> 34.877842 | ... Z146: =Z139*Z140 -> 42.851232
A147: SK 海力士＋Solidigm 營收（情境 A） | B147: $B | C147: =C139*C141 -> 2.19 | D147: =D139*D141 -> 3.34 | E147: =E139*E141 -> 3.53 | F147: =F139*F141 -> 5.21 | G147: =G139*G141 -> 7.53 | H147: =H139*H141 -> 14.27 | I147: =I139*I141 -> 18.338301 | J147: =J139*J141 -> 20.791276 | ... Z147: =Z139*Z141 -> 27.381105
...

Sheet Sources
A1: 來源
A2: markets/memory/market.py：NAND 季價路徑（NAND_COMMON、NAND_S）、加速器顆數 UNITS、情境顆數係數 SCEN_UNITS | B2: 本 repo（單一來源）
A3: TrendForce：2Q26 NAND 前五大營收（2026-08-18） | B3: https://www.trendforce.com/presscenter/news/20260818-13186.html
A4: TrendForce：2Q25 NAND 營收（2025-08-28） | B4: https://www.trendforce.com/presscenter/news/20250828-12688.html
A5: TrendForce：3Q25 NAND 營收（2025-12-03） | B5: https://www.trendforce.com/presscenter/news/20251203-12813.html
A6: TrendForce：4Q25 NAND 營收（I-Connect007 轉載） | B6: https://iconnect007.com/article/149024/ai-server-storage-demand-surges-top-five-nand-flash-suppliers-post-238-qoq-revenue-growth-in-4q25/149021/pcb
A7: TrendForce：2024 NAND 營收 $67.4B（TelecomLead 轉載） | B7: https://telecomlead.com/semiconductor/memory-industry-to-see-significant-revenue-growth-trendforce-117301
A8: TrendForce：2026 供給缺口 4–6%、2H27 平衡、伺服器約 40%（Guru3D 2026-07-21 轉載） | B8: https://www.guru3d.com/story/nand-flash-supply-expected-to-return-to-market-balance-in-2027/
A9: 美光：產業 NAND 位元出貨 CY2026–28（Guru3D 2026-10-01 轉載 FQ4 FY26） | B9: https://www.guru3d.com/story/micron-expects-dram-and-nand-supply-to-tighten-further-through-2028/
A10: Counterpoint：2Q26 企業級 SSD 占位元 48%、位元市占（capitalandcompute、hwbusters 轉載） | B10: https://capitalandcompute.net/blog/why-are-ssds-so-expensive/
A11: SanDisk FQ4 FY26 新聞稿（8-K，2026-08-05） | B11: https://www.sec.gov/Archives/edgar/data/0002023554/000162828026053346/sndkq4-26ex991xpressrelease.htm
A12: Kioxia FY2026 第一季財報（SGX 轉載，2026-07-31） | B12: https://links.sgx.com/1.0.0/corporate-announcements/DOATO9EIE4EEQ2Y8/898078_Earnings-Release-FY2026-1Q-EN.pdf
A13: borecraft：Kioxia 332 層、三星／SK 投片（2026-05-26，轉載 DigiTimes 等；AI 輔助撰寫，弱） | B13: https://borecraft.com/?p=15672
... A16: SemiAnalysis | B16: 未使用
