Workbook

Sheet README
A1: BESI（BE Semiconductor Industries，BESI.AS）收支與估值模型 v0.1.1（AI 半導體 Project 步驟 5：設備與材料） 2026-10-25
A2: v0.1（2026-10-25）：首版。樣板 hanmi/（鍵合設備，HBM 晶粒與混合鍵合比例口徑相同）與 advantest/（設備股統一循環規則）。本版未做先驗，無 Andy 合理 P/E 對照。
A3: 模型命題：BESI 的盈餘由混合鍵合機的新機需求決定——邏輯（SoIC 類）由 AI 先進封裝晶圓 × 混合鍵合導入比例推得，HBM 由 HBM 晶粒 × 混合鍵合占比（與韓美同一口徑）÷ 機台產能推得；傳統貼合機等主流業務隨設備市場循環。股價取決於 2027 年 CoWoS 增速放緩後，邏輯導入比例與 HBM4E／HBM5 混合鍵合能否接棒，以及 BESI 能否守住份額。
A5: 會計年度＝日曆年。金額以百萬歐元（€M）為主；EPS 為歐元。FY2026 為錨點：前三季實績（184.9＋249.9＋283.4）＋第四季公司指引（營收持平 ±5%、毛利率 63–65%、費用 +5～10%）；第三季已於 2026-10-22 公布並納入。
A7: 驅動因子 → 推導量
A8: HBM：HBM 出貨位元（markets/memory 同字母情境）÷ 晶粒容量 → 核心晶粒數 × 層數加權 × 混合鍵合占比（Disco 模型，韓美用 1 − 此比例）→ 混合鍵合產能 ÷ 每台年產能 → 所需機台；新機＝下一年增量＋汰換；× 單價 × BESI 份額
A9: 邏輯：台積電 CoWoS 需求（基準）× 情境顆數係數（同字母）× 混合鍵合導入比例 → 需求指數；新機需求指數 × 校準係數 k（FY2026 混合鍵合營收）× 相對份額 → 邏輯混合鍵合營收；主流業務＝前一年 ×（1＋彈性 × markets/equipment 同字母設備總額年增）
A10: 毛利率：FY2026 錨點，之後加上混合鍵合占比變化 × 毛利溢價（C 扣價格競爭）；營業費用＝固定＋變動 × 營收；淨利＝（營業利益 − 財務費用）×（1 − 稅率）
A11: 情境 A／B／C＝順利／平平／不如預期：上游全部讀同字母（markets/memory HBM 位元、台積電情境顆數係數 2028 ×1.0／0.8／0.6、2029 ×1.0／0.85／0.6、markets/equipment 設備總額）；公司特有變數 A 最有利、C 最不利（HBM 混合鍵合 Disco 高／基準／低、邏輯導入快／中／慢、份額、C 另扣毛利率）。Val：十年 P/E 分位，循環位置依設備股共用規則（見頂年 A 2029、B 2028、C 2027 → FY2027：A 中段、B 中段、C 見頂）；舊法規則值三情境 0.3／0.5／0.2 加權
A13: 標記：Verified、Interested-party、Analogy、Assumed、Derived。SemiAnalysis 未使用。公司不揭露混合鍵合營收、產品別營收、機台單價與產能，相關輸入皆為 Assumed。
A14: 已知限制：(1) 混合鍵合營收、HBM／邏輯拆分、機台單價與產出皆未揭露（Assumed），FY2026 混合鍵合占比 25% 決定 k 與主流基期；(2) 邏輯導入比例無資料，水準被 k 吸收，只有斜率有作用；(3) 以台積電 CoWoS 需求代表 AI 邏輯先進封裝規模（Analogy），未含英特爾、消費性 CPU、共同封裝光學；(4) HBM 混合鍵合比例與晶粒、層數沿用 Disco 模型 Assumed，與韓美同進同退（方向相反）；(5) 機台假設比產能早一年購入；(6) 十年 P/E 2016–2020 只有一個來源、2025 只有一個來源；(7) 每年 €100M 回購與策略檢討（可能與應用材料合作）未建模。
A15: 估值 v2（2026-10-25）：Val 頁「0. 目標價」＝0.5 × DCF 目標價（股東現金流＝EPS ×（1 − g／ROE），FY2027–32 明確期＋永續，r 10%、g 4%，情境權重 A 0.3／B 0.5／C 0.2；負值取 0）＋0.5 × Comparable 目標價（同業前瞻 P/E 中位數 × 12 個月後前瞻 EPS）；另列 Comparable 單獨目標價、市場共識目標價與差距拆解、歷史分位檢查。「舊法：規則值情境加權（參考）」不是目標價。
... A17: v0.1.1（2026-10-25）：補上檔空間級距、投資建議、重點觀察（數值不變）。Val 頁最後新增「上檔空間級距」「投資建議」兩列（依「上檔空間：加權目標價」固定規則）；README 頁最後新增投資建議與重點觀察三點。
A18: ="投資建議："&Val!B124&"（依上檔空間固定規則）" -> 投資建議：中立（依上檔空間固定規則）
A19: ="重點觀察 1：目標價 €"&TEXT(Val!$B$112,"#,##0.00")&"（DCF "&TEXT(Val!$B$97,"#,##0.00")&"、Comparable（相對倍數調整後）"&TEXT(tp_comp_adj,"#,##0.00")&"；DCF 權重 "&TEXT(tp_w_dcf,"0%")&"），比現價 "&TEXT(px,"#,##0.00")&"（2026-10-23）"&IF(Val!$B$115>=0,"高 "&TEXT(Val!$B$115,"0.0%"),"低 "&TEXT(-Val!$B$115,"0.0%"))&"，級距 "&Val!$B$123&"、投資建議 "&Val!$B$124&"。相對倍數調整係數 "&TEXT(rm_factor,"0.00")&"（本公司 10 年前瞻倍數中位數 ÷ 同業的中位數，夾在 0.5–2.0；Val 第 0.5 節），調整前加權上檔空間 "&TEXT((tp_w_dcf*Val!$B$97+(1-tp_w_dcf)*Val!$B$108)/px-1,"+0.0%;−0.0%")&"；Comparable 單獨（市場主流同業法、未調整）為 "&TEXT(Val!$B$116,"+0.0%;−0.0%")&"。"&"以下為 2026-10-29 相對倍數調整前撰寫的說明，其中數字為調整前：DCF 低是情境分歧造成：DCF 情境價值 A 158.4（現價的 1.09 倍）、B 82.4、C 44.8，B 的 FY2028 EPS 6.59 比 A 的 9.37 低 30%。" -> 重點觀察 1：目標價 €157.28（DCF 96.23、Comparable（相對倍數調整後）218.34；DCF 權重 50%），比現價 145.10（2026-10-23）高 8.4%，級距 0%–25%、投資建議 中立。相對倍數調整係數 1.31（本公司 10 年前瞻倍數中位數 ÷ 同業的中位數，夾在 0.5–2.0；Val 第 0.5 節），調整前加權上檔空間 −9.4%；Comparable 單獨（市場主流同業法、未調整）為 +14.9%。以下為 2026-10-29 相對倍數調整前撰寫的說明，其中數字為調整前：DCF 低是情境分歧造成：DCF 情境價值 A 158.4（現價的 1.09 倍）、B 82.4、C 44.8，B 的 FY2028 EPS 6.59 比 A 的 9.37 低 30%。
A20: 重點觀察 2：本模型 12 個月後前瞻 EPS 6.52 比共識前瞻 EPS 8.14 低 19.9%；共識目標價 270.57 隱含 33.2 倍，同業中位數 26.0 倍（倍數因素 +27.7%）。
A21: 重點觀察 3：最敏感的是邏輯（SoIC 類）混合鍵合導入速度：導入比例 ×0.7／×1.3 使 FY2027 EPS −22.0%／+22.0%，改走情境 B 路徑 −12.2%；HBM 混合鍵合取 Disco 低值 −7.2%。下一個檢驗事件是 Q4-26 財報（約 2027-02 下旬）的混合鍵合訂單（Q3-26 訂單 €342.6M）。
A23: 2026-10-29：加權目標價中的 Comparable 改用相對倍數調整後的值（Val 第 0.5 節：同業前瞻倍數中位數 × 本公司 10 年相對同業的倍數比，Bloomberg 前瞻倍數；Andy 2026-10-27「照建議做」、10-29 資料取回）。「Comparable 目標價（市場主流同業法）」維持不調整。重點觀察 1 的第一句已改為公式；重點觀察 2、3 與其他說明中的目標價與上檔空間數字為調整前撰寫，以 Val 頁為準。
A25: v0.1.2（2026-10-31）：依個股模型原則第 8 節調整 In 頁呈現（數值不變）。In 頁 D／F 欄名改「敏感度低」「敏感度高」（只用於 Sens 頁、不進目標價）；In 頁最後新增「情境驅動對照」一節，把上方各情境專屬輸入三情境並排（只引用上方各列，純展示）；HTML 驅動因子一節分「情境驅動」與「單一參數」兩張表。

Sheet In
A1: In — 輸入（藍字；基準欄 E，低 D、高 F）。金額：百萬歐元（€M）；HBM 位元：EB；晶粒：百萬顆；CoWoS：千片。每個輸入附兩個來源（來源2 找不到者寫「未找到」）。【v0.1.2】基準欄 E 進主模型；D／F＝敏感度低／高，只用於 Sens 頁（一次動一個參數）、不進目標價；情境 A／B／C 的驅動見本頁最後一節「情境驅動對照」。
A2: 標記：Verified／Interested-party／Analogy／Assumed／Derived；Analogy、Assumed 給低／高區間，不當點估計（放情境或 Sens）。SemiAnalysis 未使用。公司（besi.com）只給下一季指引，不揭露混合鍵合營收、產品別營收與機台單價；實績取自公司新聞稿（GlobeNewswire 轉載）與財務資料頁
A3: 鍵 | B3: 項目 | C3: 單位 | D3: 敏感度低 | E3: 基準 | F3: 敏感度高 | G3: 標記 | H3: 來源1 | I3: 來源2／說明
A4: A. HBM 出貨位元（markets/memory，經 SK 海力士模型成品 Mkt 頁；情境 A／B／C 各一列，讀同字母；唯讀）
A5: hsA_25 | B5: HBM 出貨位元 2025（EB；A） | C5: EB | E5: 2.2251147 | G5: Derived | H5: skhynix/dist/20261030_SK海力士個股模型_v0.6.1.xlsx｜Mkt!C24:G24 | I5: markets/memory：出貨＝MIN(需求 × 情境顆數係數 SCEN_UNITS, 供給)；2028–29 隨情境，2025–27 三情境相同
A6: hsA_26 | B6: HBM 出貨位元 2026（EB；A） | C6: EB | E6: 3.782695 | G6: Derived | H6: skhynix/dist/20261030_SK海力士個股模型_v0.6.1.xlsx｜Mkt!C24:G24 | I6: 同上
A7: hsA_27 | B7: HBM 出貨位元 2027（EB；A） | C7: EB | E7: 5.8631772 | G7: Derived | H7: skhynix/dist/20261030_SK海力士個股模型_v0.6.1.xlsx｜Mkt!C24:G24 | I7: 同上
A8: hsA_28 | B8: HBM 出貨位元 2028（EB；A） | C8: EB | E8: 8.501607 | G8: Derived | H8: skhynix/dist/20261030_SK海力士個股模型_v0.6.1.xlsx｜Mkt!C24:G24 | I8: 同上
A9: hsA_29 | B9: HBM 出貨位元 2029（EB；A） | C9: EB | E9: 11.477169 | G9: Derived | H9: skhynix/dist/20261030_SK海力士個股模型_v0.6.1.xlsx｜Mkt!C24:G24 | I9: 同上
A10: hsB_25 | B10: HBM 出貨位元 2025（EB；B） | C10: EB | E10: 2.2251147 | G10: Derived | H10: skhynix/dist/20261030_SK海力士個股模型_v0.6.1.xlsx｜Mkt!C25:G25 | I10: markets/memory：出貨＝MIN(需求 × 情境顆數係數 SCEN_UNITS, 供給)；2028–29 隨情境，2025–27 三情境相同
A11: hsB_26 | B11: HBM 出貨位元 2026（EB；B） | C11: EB | E11: 3.782695 | G11: Derived | H11: skhynix/dist/20261030_SK海力士個股模型_v0.6.1.xlsx｜Mkt!C25:G25 | I11: 同上
A12: hsB_27 | B12: HBM 出貨位元 2027（EB；B） | C12: EB | E12: 5.8631772 | G12: Derived | H12: skhynix/dist/20261030_SK海力士個股模型_v0.6.1.xlsx｜Mkt!C25:G25 | I12: 同上
A13: hsB_28 | B13: HBM 出貨位元 2028（EB；B） | C13: EB | E13: 8.22296 | G13: Derived | H13: skhynix/dist/20261030_SK海力士個股模型_v0.6.1.xlsx｜Mkt!C25:G25 | I13: 同上
A14: hsB_29 | B14: HBM 出貨位元 2029（EB；B） | C14: EB | E14: 11.357964 | G14: Derived | H14: skhynix/dist/20261030_SK海力士個股模型_v0.6.1.xlsx｜Mkt!C25:G25 | I14: 同上
A15: hsC_25 | B15: HBM 出貨位元 2025（EB；C） | C15: EB | E15: 2.2251147 | G15: Derived | H15: skhynix/dist/20261030_SK海力士個股模型_v0.6.1.xlsx｜Mkt!C26:G26 | I15: markets/memory：出貨＝MIN(需求 × 情境顆數係數 SCEN_UNITS, 供給)；2028–29 隨情境，2025–27 三情境相同
A16: hsC_26 | B16: HBM 出貨位元 2026（EB；C） | C16: EB | E16: 3.782695 | G16: Derived | H16: skhynix/dist/20261030_SK海力士個股模型_v0.6.1.xlsx｜Mkt!C26:G26 | I16: 同上
... A19: hsC_29 | B19: HBM 出貨位元 2029（EB；C） | C19: EB | E19: 8.017386 | G19: Derived | H19: skhynix/dist/20261030_SK海力士個股模型_v0.6.1.xlsx｜Mkt!C26:G26 | I19: 同上
A20: g_tail | B20: CY2030 需求相對 2029 的年增（市場層只到 2029；只用於 CY2029 的機台購買） | C20: % | D20: 0 | E20: 0.1 | F20: 0.2 | G20: Assumed | H20: disco/dist/20261031_Disco模型_v0.2.3.xlsx｜In!D51:F51 | I20: 與 Disco、韓美模型的 g_tail 同值（讀 Disco 成品）
A21: B. 晶粒、堆疊層數與混合鍵合比例（與 Disco、韓美模型同一組假設，讀 Disco 成品；唯讀）
A22: den_25 | B22: DRAM 核心晶粒容量（組合平均）2025 | C22: Gb／顆 | D22: 22 | E22: 24 | F22: 24 | G22: Assumed | H22: siliconomics｜SIF_hbm_den_25 | I22: 與韓美同一口徑：每顆核心晶粒鍵合一次；容量愈大，同樣位元的鍵合次數愈少
A23: den_26 | B23: DRAM 核心晶粒容量（組合平均）2026 | C23: Gb／顆 | D23: 24 | E23: 24 | F23: 26 | G23: Assumed | H23: siliconomics｜SIF_hbm_den_26 | I23: 同上
A24: den_27 | B24: DRAM 核心晶粒容量（組合平均）2027 | C24: Gb／顆 | D24: 24 | E24: 26 | F24: 28 | G24: Assumed | H24: siliconomics｜SIF_hbm_den_27 | I24: 同上
A25: den_28 | B25: DRAM 核心晶粒容量（組合平均）2028 | C25: Gb／顆 | D25: 24 | E25: 28 | F25: 32 | G25: Assumed | H25: siliconomics｜SIF_hbm_den_28 | I25: 同上
A26: den_29 | B26: DRAM 核心晶粒容量（組合平均）2029 | C26: Gb／顆 | D26: 26 | E26: 30 | F26: 32 | G26: Assumed | H26: siliconomics｜SIF_hbm_den_29 | I26: 同上
A27: den_30 | B27: DRAM 核心晶粒容量（組合平均）2030 | C27: Gb／顆 | D27: 28 | E27: 32 | F27: 32 | G27: Assumed | H27: siliconomics｜SIF_hbm_den_30 | I27: 同上
A28: stk_25 | B28: HBM 平均堆疊層數 2025 | C28: 層 | D28: 8 | E28: 10 | F28: 12 | G28: Assumed | H28: siliconomics｜SIF_hbm_stk_25 | I28: 層數愈高，每顆晶粒的鍵合精度要求與時間愈高（見 beta）
A29: stk_26 | B29: HBM 平均堆疊層數 2026 | C29: 層 | D29: 10 | E29: 12 | F29: 12 | G29: Assumed | H29: siliconomics｜SIF_hbm_stk_26 | I29: 同上
A30: stk_27 | B30: HBM 平均堆疊層數 2027 | C30: 層 | D30: 12 | E30: 12.5 | F30: 14 | G30: Assumed | H30: siliconomics｜SIF_hbm_stk_27 | I30: 同上
A31: stk_28 | B31: HBM 平均堆疊層數 2028 | C31: 層 | D31: 12 | E31: 14 | F31: 16 | G31: Assumed | H31: siliconomics｜SIF_hbm_stk_28 | I31: 同上
A32: stk_29 | B32: HBM 平均堆疊層數 2029 | C32: 層 | D32: 12 | E32: 15 | F32: 16 | G32: Assumed | H32: siliconomics｜SIF_hbm_stk_29 | I32: 同上
A33: stk_30 | B33: HBM 平均堆疊層數 2030 | C33: 層 | D33: 14 | E33: 16 | F33: 16 | G33: Assumed | H33: siliconomics｜SIF_hbm_stk_30 | I33: 同上
... A41: dlt | B41: 已裝機鍵合產能每年汰換／升級比例（新機需求＝產能增量＋汰換） | C41: %/年 | D41: 0.05 | E41: 0.1 | F41: 0.15 | G41: Assumed | H41: 與 Disco、韓美模型同值（Assumed） | I41: 公司不揭露裝機量與機齡；精度由 100nm→50nm→25nm 換代（Q3-26 法說）
A42: C. 邏輯混合鍵合（SoIC 等）：AI 先進封裝晶圓需求（台積電模型成品，基準路徑 × 同字母情境顆數係數；唯讀）
A43: cow_26 | B43: CoWoS 晶圓需求合計 2026（基準路徑） | C43: 千片 | E43: 1107.8576 | G43: Derived | H43: tsmc/dist/20261030_台積電個股模型_v0.4.1.xlsx｜CoWoS!B13:E13 | I43: 台積電模型：加速器顆數 ÷ 每片封裝數＋其他用途；本模型以此代表 AI 邏輯先進封裝的規模（Analogy：SoIC 晶圓與 CoWoS 同步）
A44: cow_27 | B44: CoWoS 晶圓需求合計 2027（基準路徑） | C44: 千片 | E44: 2096.4286 | G44: Derived | H44: tsmc/dist/20261030_台積電個股模型_v0.4.1.xlsx｜CoWoS!B13:E13 | I44: 同上
A45: cow_28 | B45: CoWoS 晶圓需求合計 2028（基準路徑） | C45: 千片 | E45: 2620.0893 | G45: Derived | H45: tsmc/dist/20261030_台積電個股模型_v0.4.1.xlsx｜CoWoS!B13:E13 | I45: 同上
A46: cow_29 | B46: CoWoS 晶圓需求合計 2029（基準路徑） | C46: 千片 | E46: 3013.3259 | G46: Derived | H46: tsmc/dist/20261030_台積電個股模型_v0.4.1.xlsx｜CoWoS!B13:E13 | I46: 同上
A47: um28_A | B47: 情境 A：2028 顆數 ÷ 基準（台積電模型情境顆數係數） | C47: x | E47: 1 | G47: Derived | H47: tsmc/dist/20261030_台積電個股模型_v0.4.1.xlsx｜In!D37:F37 | I47: 與 markets/memory SCEN_UNITS 同一套；2026–27 無情境差異
A48: um29_A | B48: 情境 A：2029 顆數 ÷ 基準（台積電模型情境顆數係數） | C48: x | E48: 1 | G48: Derived | H48: tsmc/dist/20261030_台積電個股模型_v0.4.1.xlsx｜In!D38:F38 | I48: 同上
A49: um28_B | B49: 情境 B：2028 顆數 ÷ 基準（台積電模型情境顆數係數） | C49: x | E49: 0.8 | G49: Derived | H49: tsmc/dist/20261030_台積電個股模型_v0.4.1.xlsx｜In!D39:F39 | I49: 同上
A50: um29_B | B50: 情境 B：2029 顆數 ÷ 基準（台積電模型情境顆數係數） | C50: x | E50: 0.85 | G50: Derived | H50: tsmc/dist/20261030_台積電個股模型_v0.4.1.xlsx｜In!D40:F40 | I50: 同上
A51: um28_C | B51: 情境 C：2028 顆數 ÷ 基準（台積電模型情境顆數係數） | C51: x | E51: 0.6 | G51: Derived | H51: tsmc/dist/20261030_台積電個股模型_v0.4.1.xlsx｜In!D41:F41 | I51: 同上
A52: um29_C | B52: 情境 C：2029 顆數 ÷ 基準（台積電模型情境顆數係數） | C52: x | E52: 0.6 | G52: Derived | H52: tsmc/dist/20261030_台積電個股模型_v0.4.1.xlsx｜In!D42:F42 | I52: 同上
A53: attA_26 | B53: 混合鍵合（SoIC 類）占 AI 先進封裝晶圓比例 2026（A） | C53: % | D53: 0.08 | E53: 0.08 | F53: 0.08 | G53: Assumed | H53: 無直接資料：公司稱邏輯混合鍵合加速（AMD、資料中心與消費性 CPU 新品，Q2-26 新聞稿；美國邏輯客戶 2025 年裝機、明年擴產，Q3-26 法說；邏輯大客戶 6 條整合產線 30 台，Q4-25 新聞稿） | I53: 2026–27 三情境相同（2027 產能的機台多在 2026 下單，視為已知）；2028 起 A 導入最快、C 最慢；低／高＝2028 起 ×0.7／×1.3。比例的水準被校準係數 k 吸收，只有變化才影響營收
A54: attA_27 | B54: 混合鍵合（SoIC 類）占 AI 先進封裝晶圓比例 2027（A） | C54: % | D54: 0.11 | E54: 0.11 | F54: 0.11 | G54: Assumed | H54: 同上 | I54: —
A55: attA_28 | B55: 混合鍵合（SoIC 類）占 AI 先進封裝晶圓比例 2028（A） | C55: % | D55: 0.126 | E55: 0.18 | F55: 0.234 | G55: Assumed | H55: 同上 | I55: —
A56: attA_29 | B56: 混合鍵合（SoIC 類）占 AI 先進封裝晶圓比例 2029（A） | C56: % | D56: 0.182 | E56: 0.26 | F56: 0.338 | G56: Assumed | H56: 同上 | I56: —
A57: attA_30 | B57: 混合鍵合（SoIC 類）占 AI 先進封裝晶圓比例 2030（A） | C57: % | D57: 0.238 | E57: 0.34 | F57: 0.442 | G57: Assumed | H57: 同上 | I57: —
A58: attB_26 | B58: 混合鍵合（SoIC 類）占 AI 先進封裝晶圓比例 2026（B） | C58: % | D58: 0.08 | E58: 0.08 | F58: 0.08 | G58: Assumed | H58: 同上 | I58: 2026–27 三情境相同（2027 產能的機台多在 2026 下單，視為已知）；2028 起 A 導入最快、C 最慢；低／高＝2028 起 ×0.7／×1.3。比例的水準被校準係數 k 吸收，只有變化才影響營收
A59: attB_27 | B59: 混合鍵合（SoIC 類）占 AI 先進封裝晶圓比例 2027（B） | C59: % | D59: 0.11 | E59: 0.11 | F59: 0.11 | G59: Assumed | H59: 同上 | I59: —
A60: attB_28 | B60: 混合鍵合（SoIC 類）占 AI 先進封裝晶圓比例 2028（B） | C60: % | D60: 0.105 | E60: 0.15 | F60: 0.195 | G60: Assumed | H60: 同上 | I60: —
A61: attB_29 | B61: 混合鍵合（SoIC 類）占 AI 先進封裝晶圓比例 2029（B） | C61: % | D61: 0.14 | E61: 0.2 | F61: 0.26 | G61: Assumed | H61: 同上 | I61: —
A62: attB_30 | B62: 混合鍵合（SoIC 類）占 AI 先進封裝晶圓比例 2030（B） | C62: % | D62: 0.175 | E62: 0.25 | F62: 0.325 | G62: Assumed | H62: 同上 | I62: —
A63: attC_26 | B63: 混合鍵合（SoIC 類）占 AI 先進封裝晶圓比例 2026（C） | C63: % | D63: 0.08 | E63: 0.08 | F63: 0.08 | G63: Assumed | H63: 同上 | I63: 2026–27 三情境相同（2027 產能的機台多在 2026 下單，視為已知）；2028 起 A 導入最快、C 最慢；低／高＝2028 起 ×0.7／×1.3。比例的水準被校準係數 k 吸收，只有變化才影響營收
A64: attC_27 | B64: 混合鍵合（SoIC 類）占 AI 先進封裝晶圓比例 2027（C） | C64: % | D64: 0.11 | E64: 0.11 | F64: 0.11 | G64: Assumed | H64: 同上 | I64: —
... A67: attC_30 | B67: 混合鍵合（SoIC 類）占 AI 先進封裝晶圓比例 2030（C） | C67: % | D67: 0.112 | E67: 0.16 | F67: 0.208 | G67: Assumed | H67: 同上 | I67: —
A68: D. 混合鍵合機台（公司不揭露單價與產能；皆為 Assumed／Interested-party）
A69: uph | B69: 混合鍵合機有效產出（晶粒／小時） | C69: 顆／時 | D69: 600 | E69: 1000 | F69: 1500 | G69: Assumed | H69: 公司產品頁：Datacon 8800 CHAMEO ultra plus AC 乾循環最高 2,000 CPH（Interested-party）；實際產出低於乾循環 | I69: 第二來源：未找到
A70: util | B70: 機台稼動率（全年小時 × 比例） | C70: % | D70: 0.6 | E70: 0.7 | F70: 0.8 | G70: Assumed | H70: 無：後段設備常見 60–80% | I70: —
A71: thr | B71: 每台年產能（百萬顆晶粒）＝uph × 8760 × util ÷ 10⁶（Derived） | C71: 百萬顆／台 | E71: =uph*8760*util/1000000 -> 6.132 | G71: Derived | H71: — | I71: —
A72: asp | B72: 混合鍵合機單價（HBM 用；只用於 HBM 段） | C72: €M／台 | D72: 2 | E72: 2.5 | F72: 3.5 | G72: Assumed | H72: 公司不揭露（Q3-26 法說：未給 ASP）；隱含檢查：FY2026 混合鍵合營收 ÷ 單價 vs 累計訂單 150＋（2025 年底）→ 215＋台（Q3-26），見 Recon | I72: 第二來源：未找到
A73: shm_A | B73: BESI 占 HBM 混合鍵合機採購（A） | C73: % | D73: 0.5 | E73: 0.6 | F73: 0.7 | G73: Assumed | H73: 無份額資料：競爭者韓美（2027 年混合鍵合工廠）、韓華 Semitech、SEMES（三星）、ASMPT；BESI 與應用材料整合方案（Interested-party：公司稱 HBM4E／HBM5 採用混合鍵合） | I73: A 最有利、C 最不利（Assumed）
A74: shm_B | B74: BESI 占 HBM 混合鍵合機採購（B） | C74: % | D74: 0.4 | E74: 0.5 | F74: 0.6 | G74: Assumed | H74: 同上 | I74: A 最有利、C 最不利（Assumed）
A75: shm_C | B75: BESI 占 HBM 混合鍵合機採購（C） | C75: % | D75: 0.25 | E75: 0.35 | F75: 0.45 | G75: Assumed | H75: 同上 | I75: A 最有利、C 最不利（Assumed）
A76: shl_A | B76: BESI 邏輯混合鍵合份額，相對 FY2026（A） | C76: x | D76: 0.9 | E76: 1 | F76: 1.1 | G76: Assumed | H76: FY2026 份額已含在校準係數 k；之後 ASMPT、Kulicke & Soffa、韓美、ASML（公司稱非競爭者，Q3-26 法說，Interested-party）可能搶份額 | I76: A 守住、C 流失兩成（Assumed）
A77: shl_B | B77: BESI 邏輯混合鍵合份額，相對 FY2026（B） | C77: x | D77: 0.85 | E77: 0.95 | F77: 1.05 | G77: Assumed | H77: 同上 | I77: A 守住、C 流失兩成（Assumed）
A78: shl_C | B78: BESI 邏輯混合鍵合份額，相對 FY2026（C） | C78: x | D78: 0.7 | E78: 0.8 | F78: 0.9 | G78: Assumed | H78: 同上 | I78: A 守住、C 流失兩成（Assumed）
A79: E. FY2026 錨點（前三季實績＋第四季公司指引）與混合鍵合營收拆分
A80: q4g | B80: 第四季營收相對第三季（公司指引 −5%～＋5%） | C80: % | D80: -0.05 | E80: 0 | F80: 0.05 | G80: Interested-party | H80: 公司 Q3-26 新聞稿（2026-10-22）：第四季營收持平 ±5%（交貨時點，非需求轉弱） | I80: investing.com 簡報摘要、gurufocus 法說摘要同
A81: q4gm | B81: 第四季毛利率（公司指引 63–65%） | C81: % | D81: 0.63 | E81: 0.64 | F81: 0.65 | G81: Interested-party | H81: 同上 | I81: 第三季 65.2%
A82: q4opx | B82: 第四季營業費用相對第三季（指引 +5%～+10%，含策略檢討顧問費） | C82: % | D82: 0.05 | E82: 0.075 | F82: 0.1 | G82: Interested-party | H82: 同上：16 週策略檢討，2027-01 初結論 | I82: —
A83: q4fin | B83: 第四季財務費用淨額 | C83: €M | D83: 4 | E83: 6 | F83: 8 | G83: Assumed | H83: 前三季 5.2、6.3、約 6.1（第三季由淨利 ÷（1 − 稅率）回推） | I83: 2031 年到期 4.5% 優先票據 €350M
A84: rev26 | B84: FY2026 營收錨點（Derived） | C84: €M | E84: =q1_rev+q2_rev+q3_rev+q3_rev*(1+q4g) -> 1001.6 | G84: Derived | H84: 前三季實績＋第三季 ×（1＋q4g） | I84: 共識 €1,002M（marketscreener）
A85: gp26 | B85: FY2026 毛利錨點（Derived） | C85: €M | E85: =q1_gp+q2_gp+q3_gp+q3_rev*(1+q4g)*q4gm -> 647.676 | G85: Derived | H85: — | I85: —
A86: opx26 | B86: FY2026 營業費用錨點（Derived） | C86: €M | E86: =q1_opx+q2_opx+q3_opx+q3_opx*(1+q4opx) -> 223.1325 | G86: Derived | H86: 公司說法換算 FY2026 營業費用約 €223M（investing.com 簡報摘要） | I86: —
A87: oi26 | B87: FY2026 營業利益錨點（Derived） | C87: €M | E87: =gp26-opx26 -> 424.5435 | G87: Derived | H87: — | I87: —
A88: ni26 | B88: FY2026 淨利錨點（Derived） | C88: €M | E88: =q1_ni+q2_ni+q3_ni+(q3_rev*(1+q4g)*q4gm-q3_opx*(1+q4opx)-q4fin)*(1-tax) -> 348.26413 | G88: Derived | H88: 前三季實績＋第四季（營業利益 − 財務費用）×（1 − 稅率） | I88: —
A89: eps26 | B89: FY2026 EPS 錨點（Derived） | C89: € | E89: =q1_eps+q2_eps+q3_eps+(ni26-q1_ni-q2_ni-q3_ni)/shares -> 4.3364299 | G89: Derived | H89: 前三季 EPS 實績＋第四季淨利 ÷ 股數 | I89: 共識 4.33（marketscreener）／4.42（stockanalysis）
A90: hb25 | B90: FY2025 混合鍵合營收 | C90: €M | D90: 90 | E90: 120 | F90: 160 | G90: Assumed | H90: 公司不揭露。FT（經 tspasemiconductor 轉引）：2023 年 €36M；Morningstar（2025-02-21）：混合鍵合營收自 2023 年三倍（Interested-party） | I90: 2025 年底累計訂單 150＋台（2024 年底未找到）；只用於 FY2025 拆分顯示
A91: hb_sh26 | B91: FY2026 混合鍵合營收占營收 | C91: % | D91: 0.18 | E91: 0.25 | F91: 0.35 | G91: Assumed | H91: 公司：2026 年前三季混合鍵合訂單超過 2025 全年兩倍（Q3-26 法說，Interested-party）；AI 相關占系統訂單約 60%（H1-26） | I91: FT（舊預測）：2026 年 €476M（約三分之一）；Sens 列低／高
A92: hbm26 | B92: FY2026 HBM 用混合鍵合營收（量產前） | C92: €M | E92: 0 | G92: Assumed | H92: 公司：記憶體短缺使 HBM 混合鍵合導入延後（Q3-26 法說）；試產機台併入邏輯與其他（校準係數 k） | I92: —
A93: F. 主流業務（傳統貼合機、封裝、電鍍、TC 鍵合；FY2027 起隨設備市場同字母情境）
A94: eqgA_27 | B94: 設備總額年增 2027（A） | C94: % | E94: 0.19874492 | G94: Derived | H94: markets/equipment/dist/20261023_半導體設備市場模型_v0.1.3.xlsx｜Mkt!E7:G7 | I94: markets/equipment Mkt 頁同字母情境（不自訂行業路徑）
A95: eqgA_28 | B95: 設備總額年增 2028（A） | C95: % | E95: 0.1274053 | G95: Derived | H95: markets/equipment/dist/20261023_半導體設備市場模型_v0.1.3.xlsx｜Mkt!E7:G7 | I95: 同上
A96: eqgA_29 | B96: 設備總額年增 2029（A） | C96: % | E96: 0.059452673 | G96: Derived | H96: markets/equipment/dist/20261023_半導體設備市場模型_v0.1.3.xlsx｜Mkt!E7:G7 | I96: 同上
A97: eqgB_27 | B97: 設備總額年增 2027（B） | C97: % | E97: 0.19874492 | G97: Derived | H97: markets/equipment/dist/20261023_半導體設備市場模型_v0.1.3.xlsx｜Mkt!E15:G15 | I97: 同上
A98: eqgB_28 | B98: 設備總額年增 2028（B） | C98: % | E98: 0 | G98: Derived | H98: markets/equipment/dist/20261023_半導體設備市場模型_v0.1.3.xlsx｜Mkt!E15:G15 | I98: 同上
A99: eqgB_29 | B99: 設備總額年增 2029（B） | C99: % | E99: -0.05 | G99: Derived | H99: markets/equipment/dist/20261023_半導體設備市場模型_v0.1.3.xlsx｜Mkt!E15:G15 | I99: 同上
A100: eqgC_27 | B100: 設備總額年增 2027（C） | C100: % | E100: 0.19874492 | G100: Derived | H100: markets/equipment/dist/20261023_半導體設備市場模型_v0.1.3.xlsx｜Mkt!E23:G23 | I100: 同上
A101: eqgC_28 | B101: 設備總額年增 2028（C） | C101: % | E101: -0.2 | G101: Derived | H101: markets/equipment/dist/20261023_半導體設備市場模型_v0.1.3.xlsx｜Mkt!E23:G23 | I101: 同上
A102: eqgC_29 | B102: 設備總額年增 2029（C） | C102: % | E102: 0 | G102: Derived | H102: markets/equipment/dist/20261023_半導體設備市場模型_v0.1.3.xlsx｜Mkt!E23:G23 | I102: 同上
A103: el | B103: 主流業務營收對設備市場年增的彈性 | C103: x | D103: 0.5 | E103: 1 | F103: 1.5 | G103: Assumed | H103: 無：公司稱主流市場（行動、車用、工業）2026 年復甦；車用約占 10%（Q3-26 法說） | I103: FY2025 主流業務 −7%（設備市場 +）時彈性不穩定，Sens 列 0.5／1.5
A104: G. 毛利、營業費用、稅、股數
A105: gm_prem | B105: 混合鍵合相對主流業務的毛利率溢價（組合效果） | C105: pt | D105: 0 | E105: 0.08 | F105: 0.15 | G105: Assumed | H105: 公司：第三、四季毛利率因產品組合變動（Q2-26、Q3-26 新聞稿）；長期毛利率指引 64–68%（投資人日 2026-06-19，Interested-party） | I105: FY2027 起毛利率＝FY2026 ＋ 溢價 ×（混合鍵合占比 − FY2026 占比）
A106: gm_adj_C | B106: 情境 C：FY2028 起毛利率額外調整（價格競爭） | C106: pt | D106: -0.04 | E106: -0.02 | F106: 0 | G106: Assumed | H106: 無 | I106: —
A107: phi | B107: 營業費用中變動部分占比 | C107: % | D107: 0.25 | E107: 0.4 | F107: 0.6 | G107: Assumed | H107: FY2024 €200M、FY2025 €201M（營收 −3%）、FY2026 約 €223M（營收 +69%）：費用多為固定 | I107: 營業費用＝固定（1−phi）× FY2026 ＋ 變動 phi × FY2026 ÷ FY2026 營收 × 營收
A108: opex_fix | B108: 營業費用固定部分 | C108: €M | E108: =(1-phi)*opx26 -> 133.8795 | G108: Derived | H108: — | I108: —
A109: opex_var | B109: 營業費用變動部分占營收 | C109: % | E109: =phi*opx26/rev26 -> 0.089110423 | G109: Derived | H109: — | I109: —
A110: fin | B110: 財務費用淨額（FY2027 起） | C110: €M | D110: 10 | E110: 20 | F110: 30 | G110: Assumed | H110: FY2025 €19.1M；2026 前三季約 €17.6M；€350M 4.5% 票據利息約 €16M，現金與存款 €592M 利息收入抵銷一部分 | I110: —
A111: tax | B111: 有效稅率 | C111: % | D111: 0.12 | E111: 0.135 | F111: 0.16 | G111: Verified | H111: 公司：Q2-26 13.1%、Q3-26 13.3%（新聞稿；荷蘭創新盒） | I111: FY2025 14.5%（22.3 ÷ 153.9）
...

Sheet Q
A1: Q — 實績（百萬歐元；EPS 為歐元）。會計年度＝日曆年。藍字＝輸入；黑字＝公式（Derived）。季資料取自公司新聞稿（GlobeNewswire 轉載），年資料另以 stockanalysis 核對
A2: FY2026 第三季（2026-07～09）已於 2026-10-22 公布並納入（J 欄）；第四季與全年預定 2027-02-25 公布（公司財務行事曆）。公布後更新本頁與 In 頁 q4g、q4gm、q4opx
A3: 項目 | B3: FY2024 | C3: 25Q1 | D3: 25Q2 | E3: 25Q3 | F3: 25Q4 | G3: FY2025 | H3: 26Q1 | I3: 26Q2 | J3: 26Q3 | K3: 標記 | L3: 來源1 | M3: 來源2／說明
A4: 營收 | B4: 607.5 | C4: 144.1 | D4: 148.1 | E4: 132.7 | F4: 166.4 | G4: 591.3 | H4: 184.9 | I4: 249.9 | J4: 283.4 | K4: Verified | L4: 公司新聞稿：Q4-25／FY2025（2026-02-19）、Q2-26（2026-07-23）、Q3-26（2026-10-22） | M4: stockanalysis 年度：FY2024 607.47、FY2025 591.33；investing.com Q3-26 簡報摘要 283.4
A5: 毛利 | B5: 395.9 | C5: 91.7 | D5: 93.7 | E5: 82.6 | F5: 106.2 | G5: 374.3 | H5: 117.4 | I5: 164.1 | J5: 184.8 | K5: Verified（26Q3 Derived） | L5: 公司新聞稿；26Q3＝營收 283.4 × 毛利率 65.2%（簡報摘要） | M5: stockanalysis：FY2025 374.27、FY2024 395.94
A6: 毛利率 | B6: =B5/B4 -> 0.65168724 | C6: =C5/C4 -> 0.63636364 | D6: =D5/D4 -> 0.63268062 | E6: =E5/E4 -> 0.62245667 | F6: =F5/F4 -> 0.63822115 | G6: =G5/G4 -> 0.63301201 | H6: =H5/H4 -> 0.6349378 | I6: =I5/I4 -> 0.65666267 | J6: =J5/J4 -> 0.65208186 | K6: Derived | L6: — | M6: 公司：FY2025 63.3%、26Q2 65.7%、26Q3 65.2%
A7: 營業費用（銷管＋研發，毛利 − 營業利益） | B7: =B5-B8 -> 200.3 | C7: =C5-C8 -> 52.4 | D7: =D5-D8 -> 50.2 | E7: =E5-E8 -> 48.5 | F7: =F5-F8 -> 50 | G7: =G5-G8 -> 201.2 | H7: =H5-H8 -> 53.5 | I7: =I5-I8 -> 55.3 | J7: =J5-J8 -> 55.1 | K7: Derived | L7: — | M7: 公司：26Q2 55.3、26Q3 55.1
A8: 營業利益 | B8: 195.6 | C8: 39.3 | D8: 43.5 | E8: 34.1 | F8: 56.2 | G8: 173.1 | H8: 63.9 | I8: 108.8 | J8: 129.7 | K8: Verified | L8: 公司新聞稿 | M8: stockanalysis：FY2025 173.06、FY2024 195.59
A9: 財務費用淨額 | B9: 7.1 | C9: 3 | D9: 5.7 | E9: 5.1 | F9: 5.3 | G9: 19.1 | H9: 5.2 | I9: 6.3 | J9: =J8-J10/(1-0.133) -> 6.055248 | K9: Verified（26Q3 Derived） | L9: 公司新聞稿；26Q3＝營業利益 − 淨利 ÷（1 − 13.3%） | M9: —
A10: 淨利 | B10: 182 | C10: 31.5 | D10: 32.1 | E10: 25.3 | F10: 42.8 | G10: 131.6 | H10: 51.6 | I10: 89 | J10: 107.2 | K10: Verified | L10: 公司新聞稿（FY2024 含 €18.2M 稅務利益） | M10: stockanalysis：FY2025 131.64、FY2024 181.99
A11: EPS（基本，歐元） | B11: 2.31 | C11: 0.4 | D11: 0.4 | E11: 0.32 | F11: 0.54 | G11: 1.66 | H11: 0.65 | I11: 1.11 | J11: 1.33 | K11: Verified | L11: 公司新聞稿 | M11: stockanalysis 稀釋 EPS：FY2025 1.66、FY2024 2.30
A12: 訂單 | B12: 586.7 | C12: 131.9 | D12: 128 | E12: 174.7 | F12: 250.4 | G12: 685 | H12: 269.7 | I12: 292.9 | J12: 342.6 | K12: Verified | L12: 公司新聞稿 | M12: 近 12 月訂單 €1.2B（Q3-26）
A13: 檢查：四季合計 − 全年（營收、淨利；B、C 欄） | B13: =SUM(C4:F4)-G4 -> 0 | C13: =SUM(C10:F10)-G10 -> 0.1 | K13: — | L13: — | M13: —

Sheet Units
A1: Units — HBM 晶粒 → 混合鍵合產能 → 機台；AI 先進封裝晶圓 → 邏輯混合鍵合需求指數（日曆年；三情境，引用 PL 區塊）
A3: 項目 | B3: 單位 | C3: 2025 | D3: 2026 | E3: 2027 | F3: 2028 | G3: 2029 | H3: 2030 | I3: 說明
A4: 情境 A
A5: HBM 出貨位元 | B5: EB | C5: =PL!C43 -> 2.2251147 | D5: =PL!D43 -> 3.782695 | E5: =PL!E43 -> 5.8631772 | F5: =PL!F43 -> 8.501607 | G5: =PL!G43 -> 11.477169 | H5: =PL!H43 -> 12.624886
A6: 核心晶粒數 | B6: 百萬顆 | C6: =PL!C45 -> 741.7049 | D6: =PL!D45 -> 1260.8983 | E6: =PL!E45 -> 1804.0545 | F6: =PL!F45 -> 2429.0306 | G6: =PL!G45 -> 3060.5785 | H6: =PL!H45 -> 3156.2216
A7: 混合鍵合占比（HBM） | B7: % | C7: =PL!C48 -> 0 | D7: =PL!D48 -> 0 | E7: =PL!E48 -> 0.05 | F7: =PL!F48 -> 0.15 | G7: =PL!G48 -> 0.3 | H7: =PL!H48 -> 0.4
A8: HBM 混合鍵合所需機台 | B8: 台 | C8: =PL!C50 -> 0 | D8: =PL!D50 -> 0 | E8: =PL!E50 -> 15.629549 | F8: =PL!F50 -> 65.360412 | G8: =PL!G50 -> 168.45161 | H8: =PL!H50 -> 236.76809
A9: HBM 混合鍵合新機需求 | B9: 台 | C9: =PL!C51 -> 0 | D9: =PL!D51 -> 15.629549 | E9: =PL!E51 -> 51.293817 | F9: =PL!F51 -> 109.62724 | G9: =PL!G51 -> 85.161646
A10: AI 先進封裝晶圓需求 | B10: 千片 | D10: =PL!D53 -> 1107.8576 | E10: =PL!E53 -> 2096.4286 | F10: =PL!F53 -> 2620.0893 | G10: =PL!G53 -> 3013.3259 | H10: =PL!H53 -> 3314.6585
A11: 混合鍵合邏輯晶圓（需求指數） | B11: 千片當量 | D11: =PL!D55 -> 88.62861 | E11: =PL!E55 -> 230.60714 | F11: =PL!F55 -> 471.61607 | G11: =PL!G55 -> 783.46473 | H11: =PL!H55 -> 1126.9839
A12: 邏輯新機需求指數 | B12: 千片當量 | D12: =PL!D56 -> 150.84139 | E12: =PL!E56 -> 264.06964 | F12: =PL!F56 -> 359.01027 | G12: =PL!G56 -> 421.86563
A13: 混合鍵合營收隱含機台數 | B13: 台 | C13: =PL!C72 -> 48 | D13: =PL!D72 -> 100.16 | E13: =PL!E72 -> 206.12083 | F13: =PL!F72 -> 304.16229 | G13: =PL!G72 -> 331.21944
A15: 情境 B
A16: HBM 出貨位元 | B16: EB | C16: =PL!C78 -> 2.2251147 | D16: =PL!D78 -> 3.782695 | E16: =PL!E78 -> 5.8631772 | F16: =PL!F78 -> 8.22296 | G16: =PL!G78 -> 11.357964 | H16: =PL!H78 -> 12.49376
A17: 核心晶粒數 | B17: 百萬顆 | C17: =PL!C80 -> 741.7049 | D17: =PL!D80 -> 1260.8983 | E17: =PL!E80 -> 1804.0545 | F17: =PL!F80 -> 2349.4171 | G17: =PL!G80 -> 3028.7903 | H17: =PL!H80 -> 3123.44
A18: 混合鍵合占比（HBM） | B18: % | C18: =PL!C83 -> 0 | D18: =PL!D83 -> 0 | E18: =PL!E83 -> 0 | F18: =PL!F83 -> 0.05 | G18: =PL!G83 -> 0.15 | H18: =PL!H83 -> 0.25
A19: HBM 混合鍵合所需機台 | B19: 台 | C19: =PL!C85 -> 0 | D19: =PL!D85 -> 0 | E19: =PL!E85 -> 0 | F19: =PL!F85 -> 21.072724 | G19: =PL!G85 -> 83.351004 | H19: =PL!H85 -> 146.44308
A20: HBM 混合鍵合新機需求 | B20: 台 | C20: =PL!C86 -> 0 | D20: =PL!D86 -> 0 | E20: =PL!E86 -> 21.072724 | F20: =PL!F86 -> 64.385553 | G20: =PL!G86 -> 71.42718
A21: AI 先進封裝晶圓需求 | B21: 千片 | D21: =PL!D88 -> 1107.8576 | E21: =PL!E88 -> 2096.4286 | F21: =PL!F88 -> 2096.0714 | G21: =PL!G88 -> 2561.327 | H21: =PL!H88 -> 2817.4597
A22: 混合鍵合邏輯晶圓（需求指數） | B22: 千片當量 | D22: =PL!D90 -> 88.62861 | E22: =PL!E90 -> 230.60714 | F22: =PL!F90 -> 314.41071 | G22: =PL!G90 -> 512.2654 | H22: =PL!H90 -> 704.36493
A23: 邏輯新機需求指數 | B23: 千片當量 | D23: =PL!D91 -> 150.84139 | E23: =PL!E91 -> 106.86429 | F23: =PL!F91 -> 229.29576 | G23: =PL!G91 -> 243.32607
A24: 混合鍵合營收隱含機台數 | B24: 台 | C24: =PL!C107 -> 48 | D24: =PL!D107 -> 100.16 | E24: =PL!E107 -> 77.947238 | F24: =PL!F107 -> 176.83444 | G24: =PL!G107 -> 189.20569
A26: 情境 C
A27: HBM 出貨位元 | B27: EB | C27: =PL!C113 -> 2.2251147 | D27: =PL!D113 -> 3.782695 | E27: =PL!E113 -> 5.8631772 | F27: =PL!F113 -> 6.16722 | G27: =PL!G113 -> 8.017386 | H27: =PL!H113 -> 8.8191246
A28: 核心晶粒數 | B28: 百萬顆 | C28: =PL!C115 -> 741.7049 | D28: =PL!D115 -> 1260.8983 | E28: =PL!E115 -> 1804.0545 | F28: =PL!F115 -> 1762.0629 | G28: =PL!G115 -> 2137.9696 | H28: =PL!H115 -> 2204.7811
A29: 混合鍵合占比（HBM） | B29: % | C29: =PL!C118 -> 0 | D29: =PL!D118 -> 0 | E29: =PL!E118 -> 0 | F29: =PL!F118 -> 0 | G29: =PL!G118 -> 0.05 | H29: =PL!H118 -> 0.1
A30: HBM 混合鍵合所需機台 | B30: 台 | C30: =PL!C120 -> 0 | D30: =PL!D120 -> 0 | E30: =PL!E120 -> 0 | F30: =PL!F120 -> 0 | G30: =PL!G120 -> 19.612001 | H30: =PL!H120 -> 41.348635
A31: HBM 混合鍵合新機需求 | B31: 台 | C31: =PL!C121 -> 0 | D31: =PL!D121 -> 0 | E31: =PL!E121 -> 0 | F31: =PL!F121 -> 19.612001 | G31: =PL!G121 -> 23.697835
A32: AI 先進封裝晶圓需求 | B32: 千片 | D32: =PL!D123 -> 1107.8576 | E32: =PL!E123 -> 2096.4286 | F32: =PL!F123 -> 1572.0536 | G32: =PL!G123 -> 1807.9955 | H32: =PL!H123 -> 1988.7951
A33: 混合鍵合邏輯晶圓（需求指數） | B33: 千片當量 | D33: =PL!D125 -> 88.62861 | E33: =PL!E125 -> 230.60714 | F33: =PL!F125 -> 188.64643 | G33: =PL!G125 -> 253.11937 | H33: =PL!H125 -> 318.20721
A34: 邏輯新機需求指數 | B34: 千片當量 | D34: =PL!D126 -> 150.84139 | E34: =PL!E126 -> 23.060714 | F34: =PL!F126 -> 83.337589 | G34: =PL!G126 -> 90.399777
A35: 混合鍵合營收隱含機台數 | B35: 台 | C35: =PL!C142 -> 48 | D35: =PL!D142 -> 100.16 | E35: =PL!E142 -> 12.250012 | F35: =PL!F142 -> 51.133709 | G35: =PL!G142 -> 56.315234
I37: 對照：混合鍵合累計訂單 2025 年底 150＋台、2026 年第三季 215＋台（公司）

Sheet PL
A1: PL — BESI 損益（€M；FY2025 實績，FY2026 錨點＝前三季實績＋第四季指引，FY2027–FY2029 為模型）。三情境各一個完整推導區塊（見下方），本頁頂端為摘要
A3: 情境／項目 | B3: 單位 | C3: FY2025A | D3: FY2026（錨點） | E3: FY2027 | F3: FY2028 | G3: FY2029 | H3: 說明
A4: 情境 A
A5: 營收 | B5: €M | C5: =C63 -> 591.3 | D5: =D63 -> 1001.6 | E5: =E63 -> 1415.7993 | F5: =F63 -> 1775.631 | G5: =G63 -> 1903.6318 | H5: FY2026 為錨點（前三季實績＋第四季指引），三情境相同；情境差異從 FY2027 起
A6: 混合鍵合 | B6: €M | C6: =C61 -> 120 | D6: =D61 -> 250.4 | E6: =E61 -> 515.30209 | F6: =F61 -> 760.40572 | G6: =G61 -> 828.0486
A7: 主流業務 | B7: €M | C7: =C62 -> 471.3 | D7: =D62 -> 751.2 | E7: =E62 -> 900.49718 | F7: =F62 -> 1015.2253 | G7: =G62 -> 1075.5832
A8: 毛利率 | B8: % | C8: =C65 -> 0.63301201 | D8: =D65 -> 0.64664137 | E8: =E65 -> 0.65575861 | F8: =F65 -> 0.660901 | G8: =G65 -> 0.66144006
A9: 營業利益 | B9: €M | C9: =C68 -> 173.1 | D9: =D68 -> 424.5435 | E9: =E68 -> 668.38059 | F9: =F68 -> 881.40959 | G9: =G68 -> 955.62537
A10: 營業利益率 | B10: % | C10: =C69 -> 0.2927448 | D10: =D69 -> 0.42386532 | E10: =E69 -> 0.47208712 | F10: =F69 -> 0.49639231 | G10: =G69 -> 0.50200117
A11: 淨利 | B11: €M | C11: =C70 -> 131.6 | D11: =D70 -> 348.26413 | E11: =E70 -> 560.84921 | F11: =F70 -> 745.11929 | G11: =G70 -> 809.31595
A12: EPS | B12: € | C12: =C71 -> 1.66 | D12: =D71 -> 4.3364299 | E12: =E71 -> 6.9582971 | F12: =F71 -> 9.2444838 | G12: =G71 -> 10.040953
A14: 情境 B
A15: 營收 | B15: €M | C15: =C98 -> 591.3 | D15: =D98 -> 1001.6 | E15: =E98 -> 1095.3653 | F15: =F98 -> 1342.5833 | G15: =G98 -> 1328.4865
A16: 混合鍵合 | B16: €M | C16: =C96 -> 120 | D16: =D96 -> 250.4 | E16: =E96 -> 194.8681 | F16: =F96 -> 442.0861 | G16: =G96 -> 473.01422
A17: 主流業務 | B17: €M | C17: =C97 -> 471.3 | D17: =D97 -> 751.2 | E17: =E97 -> 900.49718 | F17: =F97 -> 900.49718 | G17: =G97 -> 855.47232
A18: 毛利率 | B18: % | C18: =C100 -> 0.63301201 | D18: =D100 -> 0.64664137 | E18: =E100 -> 0.64087356 | F18: =F100 -> 0.65298379 | G18: =G100 -> 0.65512577
A19: 營業利益 | B19: €M | C19: =C103 -> 173.1 | D19: =D103 -> 424.5435 | E19: =E103 -> 470.50269 | F19: =F103 -> 623.16745 | G19: =G103 -> 618.06427
A20: 營業利益率 | B20: % | C20: =C104 -> 0.2927448 | D20: =D104 -> 0.42386532 | E20: =E104 -> 0.42953953 | F20: =F104 -> 0.46415553 | G20: =G104 -> 0.46523939
A21: 淨利 | B21: €M | C21: =C105 -> 131.6 | D21: =D105 -> 348.26413 | E21: =E105 -> 389.68482 | F21: =F105 -> 521.73985 | G21: =G105 -> 517.32559
A22: EPS | B22: € | C22: =C106 -> 1.66 | D22: =D106 -> 4.3364299 | E22: =E106 -> 4.8347091 | F22: =F106 -> 6.4730783 | G22: =G106 -> 6.4183119
A24: 情境 C
A25: 營收 | B25: €M | C25: =C133 -> 591.3 | D25: =D133 -> 1001.6 | E25: =E133 -> 931.12221 | F25: =F133 -> 848.23202 | G25: =G133 -> 861.18583
A26: 混合鍵合 | B26: €M | C26: =C131 -> 120 | D26: =D131 -> 250.4 | E26: =E131 -> 30.62503 | F26: =F131 -> 127.83427 | G26: =G131 -> 140.78808
A27: 主流業務 | B27: €M | C27: =C132 -> 471.3 | D27: =D132 -> 751.2 | E27: =E132 -> 900.49718 | F27: =F132 -> 720.39775 | G27: =G132 -> 720.39775
A28: 毛利率 | B28: % | C28: =C135 -> 0.63301201 | D28: =D135 -> 0.64664137 | E28: =E135 -> 0.62927261 | F28: =F135 -> 0.61869791 | G28: =G135 -> 0.61971991
A29: 營業利益 | B29: €M | C29: =C138 -> 173.1 | D29: =D138 -> 424.5435 | E29: =E138 -> 369.07751 | F29: =F138 -> 315.33356 | G29: =G138 -> 323.07387
A30: 營業利益率 | B30: % | C30: =C139 -> 0.2927448 | D30: =D139 -> 0.42386532 | E30: =E139 -> 0.39637924 | F30: =F139 -> 0.3717539 | G30: =G139 -> 0.37515
A31: 淨利 | B31: €M | C31: =C140 -> 131.6 | D31: =D140 -> 348.26413 | E31: =E140 -> 301.95205 | F31: =F140 -> 255.46353 | G31: =G140 -> 262.1589
A32: EPS | B32: € | C32: =C141 -> 1.66 | D32: =D141 -> 4.3364299 | E32: =E141 -> 3.7462334 | F32: =F141 -> 3.1694636 | G32: =G141 -> 3.2525311
A34: 核對：FY2026 三情境相同（營收、EPS 差額合計，應為 0） | C34: =ABS(D5-D15)+ABS(D5-D25)+ABS(D12-D32) -> 0
A40: 情境 A（順利）：markets/memory、台積電顆數係數、markets/equipment 皆取 A；HBM 混合鍵合取 Disco 高值；邏輯導入快；份額守住
A41: 項目 | B41: 單位 | C41: 2025 | D41: 2026 | E41: 2027 | F41: 2028 | G41: 2029 | H41: 2030 | I41: 說明
A42: A. HBM 混合鍵合（日曆年；與韓美同一晶粒口徑）
A43: HBM 出貨位元 | B43: EB | C43: =hsA_25 -> 2.2251147 | D43: =hsA_26 -> 3.782695 | E43: =hsA_27 -> 5.8631772 | F43: =hsA_28 -> 8.501607 | G43: =hsA_29 -> 11.477169 | H43: =G43*(1+g_tail) -> 12.624886 | I43: markets/memory 同字母情境；2030＝2029 ×（1＋g_tail）
A44: DRAM 晶粒容量 | B44: Gb | C44: =den_25 -> 24 | D44: =den_26 -> 24 | E44: =den_27 -> 26 | F44: =den_28 -> 28 | G44: =den_29 -> 30 | H44: =den_30 -> 32
A45: 核心晶粒數＝位元 × 8000 ÷ 容量 | B45: 百萬顆 | C45: =C43*8000/C44 -> 741.7049 | D45: =D43*8000/D44 -> 1260.8983 | E45: =E43*8000/E44 -> 1804.0545 | F45: =F43*8000/F44 -> 2429.0306 | G45: =G43*8000/G44 -> 3060.5785 | H45: =H43*8000/H44 -> 3156.2216 | I45: 1 EB＝8×10⁹ Gb；每顆核心晶粒鍵合一次
A46: 平均堆疊層數 | B46: 層 | C46: =stk_25 -> 10 | D46: =stk_26 -> 12 | E46: =stk_27 -> 12.5 | F46: =stk_28 -> 14 | G46: =stk_29 -> 15 | H46: =stk_30 -> 16
A47: 層數加權（每顆晶粒鍵合時間） | B47: x | C47: =1+beta*(C46-$C46)/4 -> 1 | D47: =1+beta*(D46-$C46)/4 -> 1.05 | E47: =1+beta*(E46-$C46)/4 -> 1.0625 | F47: =1+beta*(F46-$C46)/4 -> 1.1 | G47: =1+beta*(G46-$C46)/4 -> 1.125 | H47: =1+beta*(H46-$C46)/4 -> 1.15
A48: 混合鍵合占比 | B48: % | C48: =hbp_25_hi -> 0 | D48: =hbp_26_hi -> 0 | E48: =hbp_27_hi -> 0.05 | F48: =hbp_28_hi -> 0.15 | G48: =hbp_29_hi -> 0.3 | H48: =hbp_30_hi -> 0.4 | I48: 情境 A：Disco 模型高值
A49: 混合鍵合產能需求（晶粒 × 層數加權 × 混合鍵合占比） | B49: 百萬顆當量 | C49: =C45*C47*C48 -> 0 | D49: =D45*D47*D48 -> 0 | E49: =E45*E47*E48 -> 95.840397 | F49: =F45*F47*F48 -> 400.79004 | G49: =G45*G47*G48 -> 1032.9453 | H49: =H45*H47*H48 -> 1451.8619
A50: 所需機台＝產能需求 ÷ 每台年產能 | B50: 台 | C50: =C49/thr -> 0 | D50: =D49/thr -> 0 | E50: =E49/thr -> 15.629549 | F50: =F49/thr -> 65.360412 | G50: =G49/thr -> 168.45161 | H50: =H49/thr -> 236.76809
A51: 新機需求＝MAX(0, 下一年 − 本年)＋汰換 × 本年 | B51: 台 | C51: =MAX(0,D50-C50)+dlt*C50 -> 0 | D51: =MAX(0,E50-D50)+dlt*D50 -> 15.629549 | E51: =MAX(0,F50-E50)+dlt*E50 -> 51.293817 | F51: =MAX(0,G50-F50)+dlt*F50 -> 109.62724 | G51: =MAX(0,H50-G50)+dlt*G50 -> 85.161646 | I51: 機台在產能需要前一年購入
A52: B. 邏輯混合鍵合（SoIC 類；日曆年）
A53: AI 先進封裝晶圓需求＝台積電 CoWoS 需求 × 情境顆數係數 | B53: 千片 | D53: =cow_26*1 -> 1107.8576 | E53: =cow_27*1 -> 2096.4286 | F53: =cow_28*um28_A -> 2620.0893 | G53: =cow_29*um29_A -> 3013.3259 | H53: =G53*(1+g_tail) -> 3314.6585 | I53: 2030＝2029 ×（1＋g_tail）
A54: 混合鍵合占 AI 先進封裝晶圓比例 | B54: % | D54: =attA_26 -> 0.08 | E54: =attA_27 -> 0.11 | F54: =attA_28 -> 0.18 | G54: =attA_29 -> 0.26 | H54: =attA_30 -> 0.34
A55: 混合鍵合邏輯晶圓（需求指數） | B55: 千片當量 | D55: =D53*D54 -> 88.62861 | E55: =E53*E54 -> 230.60714 | F55: =F53*F54 -> 471.61607 | G55: =G53*G54 -> 783.46473 | H55: =H53*H54 -> 1126.9839
A56: 新機需求指數＝MAX(0, 下一年 − 本年)＋汰換 × 本年 | B56: 千片當量 | D56: =MAX(0,E55-D55)+dlt*D55 -> 150.84139 | E56: =MAX(0,F55-E55)+dlt*E55 -> 264.06964 | F56: =MAX(0,G55-F55)+dlt*F55 -> 359.01027 | G56: =MAX(0,H55-G55)+dlt*G55 -> 421.86563
A57: C. 損益（會計年度；FY2026＝錨點）
A58: HBM 混合鍵合營收＝新機 × 單價 × BESI 份額 | B58: €M | C58: =0 -> 0 | D58: =hbm26 -> 0 | E58: =E51*asp*shm_A -> 76.940726 | F58: =F51*asp*shm_A -> 164.44085 | G58: =G51*asp*shm_A -> 127.74247 | I58: FY2025–26 尚未量產（Assumed 0）
A59: 邏輯與其他混合鍵合營收 | B59: €M | C59: =hb25 -> 120 | D59: =rev26*hb_sh26-hbm26 -> 250.4 | E59: =$D60*E56*shl_A -> 438.36136 | F59: =$D60*F56*shl_A -> 595.96487 | G59: =$D60*G56*shl_A -> 700.30613 | I59: FY2026＝錨點營收 × 混合鍵合占比；FY2027 起＝k × 新機需求指數 × 相對份額
A60: 校準係數 k＝FY2026 邏輯混合鍵合營收 ÷ FY2026 新機需求指數 | B60: €M／千片當量 | D60: =D59/D56 -> 1.6600218 | I60: 只用 FY2026（台積電 CoWoS 需求自 2026 起）；不使用共識
A61: 混合鍵合營收合計 | B61: €M | C61: =C58+C59 -> 120 | D61: =D58+D59 -> 250.4 | E61: =E58+E59 -> 515.30209 | F61: =F58+F59 -> 760.40572 | G61: =G58+G59 -> 828.0486
A62: 主流業務營收（晶粒貼合、封裝、電鍍、TC 鍵合） | B62: €M | C62: =a25_rev-hb25 -> 471.3 | D62: =rev26-D61 -> 751.2 | E62: =D62*(1+el*eqgA_27) -> 900.49718 | F62: =E62*(1+el*eqgA_28) -> 1015.2253 | G62: =F62*(1+el*eqgA_29) -> 1075.5832 | I62: FY2027 起＝前一年 ×（1＋彈性 × 設備總額年增，markets/equipment 同字母）
A63: 營收 | B63: €M | C63: =C61+C62 -> 591.3 | D63: =D61+D62 -> 1001.6 | E63: =E61+E62 -> 1415.7993 | F63: =F61+F62 -> 1775.631 | G63: =G61+G62 -> 1903.6318
A64: 混合鍵合占營收 | B64: % | C64: =C61/C63 -> 0.20294267 | D64: =D61/D63 -> 0.25 | E64: =E61/E63 -> 0.3639655 | F64: =F61/F63 -> 0.42824535 | G64: =G61/G63 -> 0.4349836
A65: 毛利率 | B65: % | C65: =a25_gp/a25_rev -> 0.63301201 | D65: =gp26/rev26 -> 0.64664137 | E65: =$D65+gm_prem*(E64-$D64)+0 -> 0.65575861 | F65: =$D65+gm_prem*(F64-$D64)+0 -> 0.660901 | G65: =$D65+gm_prem*(G64-$D64)+0 -> 0.66144006 | I65: FY2026＝錨點；FY2027 起＝FY2026＋溢價 × 混合鍵合占比變化（情境 C 另扣價格競爭）
A66: 毛利 | B66: €M | C66: =a25_gp -> 374.3 | D66: =gp26 -> 647.676 | E66: =E63*E65 -> 928.42257 | F66: =F63*F65 -> 1173.5163 | G66: =G63*G65 -> 1259.1383
A67: 營業費用 | B67: €M | C67: =a25_opx -> 201.2 | D67: =opx26 -> 223.1325 | E67: =opex_fix+opex_var*E63 -> 260.04197 | F67: =opex_fix+opex_var*F63 -> 292.10673 | G67: =opex_fix+opex_var*G63 -> 303.51293 | I67: 固定＋變動 × 營收
A68: 營業利益 | B68: €M | C68: =C66-C67 -> 173.1 | D68: =D66-D67 -> 424.5435 | E68: =E66-E67 -> 668.38059 | F68: =F66-F67 -> 881.40959 | G68: =G66-G67 -> 955.62537
A69: 營業利益率 | B69: % | C69: =C68/C63 -> 0.2927448 | D69: =D68/D63 -> 0.42386532 | E69: =E68/E63 -> 0.47208712 | F69: =F68/F63 -> 0.49639231 | G69: =G68/G63 -> 0.50200117
A70: 淨利 | B70: €M | C70: =a25_ni -> 131.6 | D70: =ni26 -> 348.26413 | E70: =(E68-fin)*(1-tax) -> 560.84921 | F70: =(F68-fin)*(1-tax) -> 745.11929 | G70: =(G68-fin)*(1-tax) -> 809.31595
A71: EPS | B71: € | C71: =a25_eps -> 1.66 | D71: =eps26 -> 4.3364299 | E71: =E70/shares -> 6.9582971 | F71: =F70/shares -> 9.2444838 | G71: =G70/shares -> 10.040953
A72: 混合鍵合營收隱含機台數＝營收 ÷ 單價（對帳用） | B72: 台 | C72: =C61/asp -> 48 | D72: =D61/asp -> 100.16 | E72: =E61/asp -> 206.12083 | F72: =F61/asp -> 304.16229 | G72: =G61/asp -> 331.21944
A75: 情境 B（平平）：上游皆取 B（2028 顆數 ×0.8、2029 ×0.85；設備 2028 見頂）；HBM 混合鍵合取 Disco 基準；份額小降
A76: 項目 | B76: 單位 | C76: 2025 | D76: 2026 | E76: 2027 | F76: 2028 | G76: 2029 | H76: 2030 | I76: 說明
A77: A. HBM 混合鍵合（日曆年；與韓美同一晶粒口徑）
A78: HBM 出貨位元 | B78: EB | C78: =hsB_25 -> 2.2251147 | D78: =hsB_26 -> 3.782695 | E78: =hsB_27 -> 5.8631772 | F78: =hsB_28 -> 8.22296 | G78: =hsB_29 -> 11.357964 | H78: =G78*(1+g_tail) -> 12.49376 | I78: markets/memory 同字母情境；2030＝2029 ×（1＋g_tail）
A79: DRAM 晶粒容量 | B79: Gb | C79: =den_25 -> 24 | D79: =den_26 -> 24 | E79: =den_27 -> 26 | F79: =den_28 -> 28 | G79: =den_29 -> 30 | H79: =den_30 -> 32
A80: 核心晶粒數＝位元 × 8000 ÷ 容量 | B80: 百萬顆 | C80: =C78*8000/C79 -> 741.7049 | D80: =D78*8000/D79 -> 1260.8983 | E80: =E78*8000/E79 -> 1804.0545 | F80: =F78*8000/F79 -> 2349.4171 | G80: =G78*8000/G79 -> 3028.7903 | H80: =H78*8000/H79 -> 3123.44 | I80: 1 EB＝8×10⁹ Gb；每顆核心晶粒鍵合一次
A81: 平均堆疊層數 | B81: 層 | C81: =stk_25 -> 10 | D81: =stk_26 -> 12 | E81: =stk_27 -> 12.5 | F81: =stk_28 -> 14 | G81: =stk_29 -> 15 | H81: =stk_30 -> 16
A82: 層數加權（每顆晶粒鍵合時間） | B82: x | C82: =1+beta*(C81-$C81)/4 -> 1 | D82: =1+beta*(D81-$C81)/4 -> 1.05 | E82: =1+beta*(E81-$C81)/4 -> 1.0625 | F82: =1+beta*(F81-$C81)/4 -> 1.1 | G82: =1+beta*(G81-$C81)/4 -> 1.125 | H82: =1+beta*(H81-$C81)/4 -> 1.15
A83: 混合鍵合占比 | B83: % | C83: =hbp_25 -> 0 | D83: =hbp_26 -> 0 | E83: =hbp_27 -> 0 | F83: =hbp_28 -> 0.05 | G83: =hbp_29 -> 0.15 | H83: =hbp_30 -> 0.25 | I83: 情境 B：Disco 模型基準值
A84: 混合鍵合產能需求（晶粒 × 層數加權 × 混合鍵合占比） | B84: 百萬顆當量 | C84: =C80*C82*C83 -> 0 | D84: =D80*D82*D83 -> 0 | E84: =E80*E82*E83 -> 0 | F84: =F80*F82*F83 -> 129.21794 | G84: =G80*G82*G83 -> 511.10836 | H84: =H80*H82*H83 -> 897.98899
A85: 所需機台＝產能需求 ÷ 每台年產能 | B85: 台 | C85: =C84/thr -> 0 | D85: =D84/thr -> 0 | E85: =E84/thr -> 0 | F85: =F84/thr -> 21.072724 | G85: =G84/thr -> 83.351004 | H85: =H84/thr -> 146.44308
A86: 新機需求＝MAX(0, 下一年 − 本年)＋汰換 × 本年 | B86: 台 | C86: =MAX(0,D85-C85)+dlt*C85 -> 0 | D86: =MAX(0,E85-D85)+dlt*D85 -> 0 | E86: =MAX(0,F85-E85)+dlt*E85 -> 21.072724 | F86: =MAX(0,G85-F85)+dlt*F85 -> 64.385553 | G86: =MAX(0,H85-G85)+dlt*G85 -> 71.42718 | I86: 機台在產能需要前一年購入
A87: B. 邏輯混合鍵合（SoIC 類；日曆年）
A88: AI 先進封裝晶圓需求＝台積電 CoWoS 需求 × 情境顆數係數 | B88: 千片 | D88: =cow_26*1 -> 1107.8576 | E88: =cow_27*1 -> 2096.4286 | F88: =cow_28*um28_B -> 2096.0714 | G88: =cow_29*um29_B -> 2561.327 | H88: =G88*(1+g_tail) -> 2817.4597 | I88: 2030＝2029 ×（1＋g_tail）
A89: 混合鍵合占 AI 先進封裝晶圓比例 | B89: % | D89: =attB_26 -> 0.08 | E89: =attB_27 -> 0.11 | F89: =attB_28 -> 0.15 | G89: =attB_29 -> 0.2 | H89: =attB_30 -> 0.25
A90: 混合鍵合邏輯晶圓（需求指數） | B90: 千片當量 | D90: =D88*D89 -> 88.62861 | E90: =E88*E89 -> 230.60714 | F90: =F88*F89 -> 314.41071 | G90: =G88*G89 -> 512.2654 | H90: =H88*H89 -> 704.36493
A91: 新機需求指數＝MAX(0, 下一年 − 本年)＋汰換 × 本年 | B91: 千片當量 | D91: =MAX(0,E90-D90)+dlt*D90 -> 150.84139 | E91: =MAX(0,F90-E90)+dlt*E90 -> 106.86429 | F91: =MAX(0,G90-F90)+dlt*F90 -> 229.29576 | G91: =MAX(0,H90-G90)+dlt*G90 -> 243.32607
A92: C. 損益（會計年度；FY2026＝錨點）
A93: HBM 混合鍵合營收＝新機 × 單價 × BESI 份額 | B93: €M | C93: =0 -> 0 | D93: =hbm26 -> 0 | E93: =E86*asp*shm_B -> 26.340905 | F93: =F86*asp*shm_B -> 80.481941 | G93: =G86*asp*shm_B -> 89.283975 | I93: FY2025–26 尚未量產（Assumed 0）
A94: 邏輯與其他混合鍵合營收 | B94: €M | C94: =hb25 -> 120 | D94: =rev26*hb_sh26-hbm26 -> 250.4 | E94: =$D95*E91*shl_B -> 168.52719 | F94: =$D95*F91*shl_B -> 361.60416 | G94: =$D95*G91*shl_B -> 383.73024 | I94: FY2026＝錨點營收 × 混合鍵合占比；FY2027 起＝k × 新機需求指數 × 相對份額
A95: 校準係數 k＝FY2026 邏輯混合鍵合營收 ÷ FY2026 新機需求指數 | B95: €M／千片當量 | D95: =D94/D91 -> 1.6600218 | I95: 只用 FY2026（台積電 CoWoS 需求自 2026 起）；不使用共識
A96: 混合鍵合營收合計 | B96: €M | C96: =C93+C94 -> 120 | D96: =D93+D94 -> 250.4 | E96: =E93+E94 -> 194.8681 | F96: =F93+F94 -> 442.0861 | G96: =G93+G94 -> 473.01422
A97: 主流業務營收（晶粒貼合、封裝、電鍍、TC 鍵合） | B97: €M | C97: =a25_rev-hb25 -> 471.3 | D97: =rev26-D96 -> 751.2 | E97: =D97*(1+el*eqgB_27) -> 900.49718 | F97: =E97*(1+el*eqgB_28) -> 900.49718 | G97: =F97*(1+el*eqgB_29) -> 855.47232 | I97: FY2027 起＝前一年 ×（1＋彈性 × 設備總額年增，markets/equipment 同字母）
A98: 營收 | B98: €M | C98: =C96+C97 -> 591.3 | D98: =D96+D97 -> 1001.6 | E98: =E96+E97 -> 1095.3653 | F98: =F96+F97 -> 1342.5833 | G98: =G96+G97 -> 1328.4865
A99: 混合鍵合占營收 | B99: % | C99: =C96/C98 -> 0.20294267 | D99: =D96/D98 -> 0.25 | E99: =E96/E98 -> 0.17790238 | F99: =F96/F98 -> 0.32928021 | G99: =G96/G98 -> 0.35605496
A100: 毛利率 | B100: % | C100: =a25_gp/a25_rev -> 0.63301201 | D100: =gp26/rev26 -> 0.64664137 | E100: =$D100+gm_prem*(E99-$D99)+0 -> 0.64087356 | F100: =$D100+gm_prem*(F99-$D99)+0 -> 0.65298379 | G100: =$D100+gm_prem*(G99-$D99)+0 -> 0.65512577 | I100: FY2026＝錨點；FY2027 起＝FY2026＋溢價 × 混合鍵合占比變化（情境 C 另扣價格競爭）
A101: 毛利 | B101: €M | C101: =a25_gp -> 374.3 | D101: =gp26 -> 647.676 | E101: =E98*E100 -> 701.99065 | F101: =F98*F100 -> 876.68512 | G101: =G98*G100 -> 870.32577
A102: 營業費用 | B102: €M | C102: =a25_opx -> 201.2 | D102: =opx26 -> 223.1325 | E102: =opex_fix+opex_var*E98 -> 231.48796 | F102: =opex_fix+opex_var*F98 -> 253.51766 | G102: =opex_fix+opex_var*G98 -> 252.2615 | I102: 固定＋變動 × 營收
A103: 營業利益 | B103: €M | C103: =C101-C102 -> 173.1 | D103: =D101-D102 -> 424.5435 | E103: =E101-E102 -> 470.50269 | F103: =F101-F102 -> 623.16745 | G103: =G101-G102 -> 618.06427
A104: 營業利益率 | B104: % | C104: =C103/C98 -> 0.2927448 | D104: =D103/D98 -> 0.42386532 | E104: =E103/E98 -> 0.42953953 | F104: =F103/F98 -> 0.46415553 | G104: =G103/G98 -> 0.46523939
A105: 淨利 | B105: €M | C105: =a25_ni -> 131.6 | D105: =ni26 -> 348.26413 | E105: =(E103-fin)*(1-tax) -> 389.68482 | F105: =(F103-fin)*(1-tax) -> 521.73985 | G105: =(G103-fin)*(1-tax) -> 517.32559
A106: EPS | B106: € | C106: =a25_eps -> 1.66 | D106: =eps26 -> 4.3364299 | E106: =E105/shares -> 4.8347091 | F106: =F105/shares -> 6.4730783 | G106: =G105/shares -> 6.4183119
A107: 混合鍵合營收隱含機台數＝營收 ÷ 單價（對帳用） | B107: 台 | C107: =C96/asp -> 48 | D107: =D96/asp -> 100.16 | E107: =E96/asp -> 77.947238 | F107: =F96/asp -> 176.83444 | G107: =G96/asp -> 189.20569
A110: 情境 C（不如預期）：上游皆取 C（2028–29 顆數 ×0.6；設備 2027 見頂、2028 −20%）；HBM 混合鍵合取 Disco 低值；邏輯導入慢、份額流失、毛利率下調
A111: 項目 | B111: 單位 | C111: 2025 | D111: 2026 | E111: 2027 | F111: 2028 | G111: 2029 | H111: 2030 | I111: 說明
A112: A. HBM 混合鍵合（日曆年；與韓美同一晶粒口徑）
A113: HBM 出貨位元 | B113: EB | C113: =hsC_25 -> 2.2251147 | D113: =hsC_26 -> 3.782695 | E113: =hsC_27 -> 5.8631772 | F113: =hsC_28 -> 6.16722 | G113: =hsC_29 -> 8.017386 | H113: =G113*(1+g_tail) -> 8.8191246 | I113: markets/memory 同字母情境；2030＝2029 ×（1＋g_tail）
...

Sheet Val
A1: Val — P/E 估值。跨公司規則：合理倍數＝10 年（2016–2025 年底）P/E 的分位，依循環位置：見頂年 25 分位、中段中位數、谷底 75 分位。循環位置依設備股共用規則（第 4 節）。本版未做先驗，無 Andy 合理 P/E 對照
A2: P/E 定義：日曆年底收盤價 ÷ 當年 EPS（本公司會計年度＝日曆年）。兩個來源各自取分位再平均（tools/valuation_rule.py 的多來源慣例）
A3: 目標價（DCF 與 Comparable 加權）：見本頁第 77 列起「0. 目標價」（放在既有內容之後）；原「0. 目標價與上檔空間」改名為「舊法：規則值情境加權（參考）」
A4: 舊法：規則值情境加權（參考）
A5: 項目 | B5: 數值 | E5: 說明
A6: 規則值情境加權價（12 個月；參考） | B6: =tp_wA*B8+tp_wB*B9+tp_wC*B10 -> 184.83805 | E6: 權重 × 三情境隱含價
A7: 相對現價（規則值情境加權價 ÷ 現價 − 1） | B7: =B6/px-1 -> 0.27386665 | E7: 現價見第 6 節
A8: 情境 A 隱含價（順利） | B8: =F44 -> 266.4332 | E8: Val!F44：FY2027 EPS × 規則倍數
A9: 情境 B 隱含價（平平） | B9: =F51 -> 185.12101 | E9: Val!F51：FY2027 EPS × 規則倍數
A10: 情境 C 隱含價（不如預期） | B10: =F58 -> 61.737927 | E10: Val!F58：FY2027 EPS × 規則倍數
A11: 情境權重 A／B／C | B11: =tp_wA -> 0.3 | C11: =tp_wB -> 0.5 | D11: =tp_wC -> 0.2 | E11: In 頁 tp_wA／tp_wB／tp_wC（Assumed，Andy 可改）
A12: 規則值方法 | B12: P/E：各情境 FY2027 EPS（模型）× 依循環位置的十年（2016–2025 年底）P/E 分位（設備股共用規則：A、B 中段＝中位數，C 見頂＝25 分位），再以 0.3／0.5／0.2 加權。偏誤：2016–2022 年（混合鍵合前）倍數 8–27 倍，2023–25 年 54–80 倍（盈餘下滑、混合鍵合溢價），分位受兩段樣本拉扯
A14: 1. 十年 P/E（年底）— 兩個來源
A15: 年底 | B15: 來源1：macrotrends（BESIY） | C15: 來源2：stockanalysis（年底市值 ÷ 淨利） | D15: 兩者差距 | E15: 標記 | F15: 來源2 出處
A16: 2016-12 | B16: 12.14 | D16: =IF(OR(B16="",C16=""),"",B16-C16) | E16: Interested-party（資料商） | F16: 未找到（stockanalysis 只到 FY2021）
A17: 2017-12 | B17: 12.33 | D17: =IF(OR(B17="",C17=""),"",B17-C17) | E17: Interested-party（資料商） | F17: 未找到
A18: 2018-12 | B18: 8.01 | D18: =IF(OR(B18="",C18=""),"",B18-C18) | E18: Interested-party（資料商） | F18: 未找到
A19: 2019-12 | B19: 27.37 | D19: =IF(OR(B19="",C19=""),"",B19-C19) | E19: Interested-party（資料商） | F19: 未找到
A20: 2020-12 | B20: 26.94 | D20: =IF(OR(B20="",C20=""),"",B20-C20) | E20: Interested-party（資料商） | F20: 未找到
A21: 2021-12 | B21: 18.62 | C21: 20.63 | D21: =IF(OR(B21="",C21=""),"",B21-C21) -> -2.01 | E21: Interested-party（資料商） | F21: stockanalysis 比率頁
A22: 2022-12 | B22: 18.21 | C22: 18.73 | D22: =IF(OR(B22="",C22=""),"",B22-C22) -> -0.52 | E22: Interested-party（資料商） | F22: stockanalysis
A23: 2023-12 | B23: 60.96 | C23: 59.45 | D23: =IF(OR(B23="",C23=""),"",B23-C23) -> 1.51 | E23: Interested-party（資料商） | F23: stockanalysis
A24: 2024-12 | B24: 53.84 | C24: 57.95 | D24: =IF(OR(B24="",C24=""),"",B24-C24) -> -4.11 | E24: Interested-party（資料商） | F24: stockanalysis
A25: 2025-12 | C25: 80.1 | D25: =IF(OR(B25="",C25=""),"",B25-C25) | E25: Interested-party（資料商） | F25: stockanalysis（來源1 2025 年底未找到）
A26: 說明：macrotrends 以美國 ADR（BESIY）年底股價 ÷ 近 12 月 EPS（美元）；2025 年底值未找到（頁面最近一筆為 2025-06-17 的 60.7）。stockanalysis 以年底市值 ÷ 淨利（歐元），只有 2021–2025。兩源各自取分位再平均
A28: 2. 分位
A29: 統計 | B29: 採用（兩來源平均） | C29: 來源1 | D29: 來源2 | E29: 用途
A30: 25 分位 | B30: =ROUND(AVERAGE(C30,D30),2) -> 16.48 | C30: =PERCENTILE(B16:B25,0.25) -> 12.33 | D30: =PERCENTILE(C16:C25,0.25) -> 20.63 | E30: 見頂年
A31: 中位數 | B31: =ROUND(AVERAGE(C31,D31),2) -> 38.29 | C31: =PERCENTILE(B16:B25,0.5) -> 18.62 | D31: =PERCENTILE(C16:C25,0.5) -> 57.95 | E31: 中段
A32: 75 分位 | B32: =ROUND(AVERAGE(C32,D32),2) -> 43.41 | C32: =PERCENTILE(B16:B25,0.75) -> 27.37 | D32: =PERCENTILE(C16:C25,0.75) -> 59.45 | E32: 谷底
A33: 年數 | C33: =COUNT(B16:B25) -> 9 | D33: =COUNT(C16:C25) -> 5
A35: 4. 循環位置（設備股共用規則；見頂年度讀設備市場模型，不在本模型另訂）
A36: 循環位置（設備股共用規則）：各情境的見頂年度取自設備市場模型（markets/equipment 的 Mkt 頁「見頂年度」：A 2029、B 2028、C 2027）；會計年度 FY(t) 對照日曆年 t（FY(t) 有 3/4 落在 t 年）：t 早於見頂年＝中段（中位數）、等於＝見頂（25 分位）、晚於＝谷底（75 分位）。本公司會計年度＝日曆年，FY(t) 直接對照日曆年 t
A37: 情境 | B37: 設備市場見頂年度 | C37: FY2027 對照日曆年 | D37: 判定 | E37: 倍數 | F37: 規則
A38: A | B38: =pk_A -> 2029 | C38: 2027 | D38: =IF(C38<pk_A,"中段",IF(C38=pk_A,"見頂","谷底")) -> 中段 | E38: =IF(D38="見頂",pe_peak,IF(D38="谷底",pe_trough,pe_mid)) -> 38.29 | F38: tools/cycle_position.py
A39: B | B39: =pk_B -> 2028 | C39: 2027 | D39: =IF(C39<pk_B,"中段",IF(C39=pk_B,"見頂","谷底")) -> 中段 | E39: =IF(D39="見頂",pe_peak,IF(D39="谷底",pe_trough,pe_mid)) -> 38.29 | F39: tools/cycle_position.py
A40: C | B40: =pk_C -> 2027 | C40: 2027 | D40: =IF(C40<pk_C,"中段",IF(C40=pk_C,"見頂","谷底")) -> 見頂 | E40: =IF(D40="見頂",pe_peak,IF(D40="谷底",pe_trough,pe_mid)) -> 16.48 | F40: tools/cycle_position.py
A42: 5. 隱含股價（歐元）：規則值＝FY2027 EPS × 依循環位置的倍數；其餘倍數僅供參考
A43: 情境 | B43: EPS 年度 | C43: EPS | D43: 倍數類型 | E43: 倍數 | F43: 隱含股價 | G43: 相對現價 | H43: 備註
A44: A | B44: FY2027 | C44: =PL!E12 -> 6.9582971 | D44: ="規則值："&D38 -> 規則值：中段 | E44: =E38 -> 38.29 | F44: =C44*E44 -> 266.4332 | G44: =F44/px-1 -> 0.83620398
A45: A | B45: FY2027 | C45: =PL!E12 -> 6.9582971 | D45: 參考：25 分位 | E45: =pe_peak -> 16.48 | F45: =C45*E45 -> 114.67274 | G45: =F45/px-1 -> -0.20969857
A46: A | B46: FY2027 | C46: =PL!E12 -> 6.9582971 | D46: 參考：中位數 | E46: =pe_mid -> 38.29 | F46: =C46*E46 -> 266.4332 | G46: =F46/px-1 -> 0.83620398
A47: A | B47: FY2027 | C47: =PL!E12 -> 6.9582971 | D47: 參考：75 分位 | E47: =pe_trough -> 43.41 | F47: =C47*E47 -> 302.05968 | G47: =F47/px-1 -> 1.0817345
A48: A | B48: FY2028 | C48: =PL!F12 -> 9.2444838 | D48: 參考：25 分位 | E48: =pe_peak -> 16.48 | F48: =C48*E48 -> 152.34909 | G48: =F48/px-1 -> 0.049959286
A49: A | B49: FY2028 | C49: =PL!F12 -> 9.2444838 | D49: 參考：中位數 | E49: =pe_mid -> 38.29 | F49: =C49*E49 -> 353.97128 | G49: =F49/px-1 -> 1.4394989
A50: A | B50: FY2028 | C50: =PL!F12 -> 9.2444838 | D50: 參考：75 分位 | E50: =pe_trough -> 43.41 | F50: =C50*E50 -> 401.30304 | G50: =F50/px-1 -> 1.7656998
A51: B | B51: FY2027 | C51: =PL!E22 -> 4.8347091 | D51: ="規則值："&D39 -> 規則值：中段 | E51: =E39 -> 38.29 | F51: =C51*E51 -> 185.12101 | G51: =F51/px-1 -> 0.27581676
A52: B | B52: FY2027 | C52: =PL!E22 -> 4.8347091 | D52: 參考：25 分位 | E52: =pe_peak -> 16.48 | F52: =C52*E52 -> 79.676006 | G52: =F52/px-1 -> -0.450889
A53: B | B53: FY2027 | C53: =PL!E22 -> 4.8347091 | D53: 參考：中位數 | E53: =pe_mid -> 38.29 | F53: =C53*E53 -> 185.12101 | G53: =F53/px-1 -> 0.27581676
A54: B | B54: FY2027 | C54: =PL!E22 -> 4.8347091 | D54: 參考：75 分位 | E54: =pe_trough -> 43.41 | F54: =C54*E54 -> 209.87472 | G54: =F54/px-1 -> 0.44641435
A55: B | B55: FY2028 | C55: =PL!F22 -> 6.4730783 | D55: 參考：25 分位 | E55: =pe_peak -> 16.48 | F55: =C55*E55 -> 106.67633 | G55: =F55/px-1 -> -0.26480819
A56: B | B56: FY2028 | C56: =PL!F22 -> 6.4730783 | D56: 參考：中位數 | E56: =pe_mid -> 38.29 | F56: =C56*E56 -> 247.85417 | G56: =F56/px-1 -> 0.70816106
A57: B | B57: FY2028 | C57: =PL!F22 -> 6.4730783 | D57: 參考：75 分位 | E57: =pe_trough -> 43.41 | F57: =C57*E57 -> 280.99633 | G57: =F57/px-1 -> 0.93657016
A58: C | B58: FY2027 | C58: =PL!E32 -> 3.7462334 | D58: ="規則值："&D40 -> 規則值：見頂 | E58: =E40 -> 16.48 | F58: =C58*E58 -> 61.737927 | G58: =F58/px-1 -> -0.57451463
A59: C | B59: FY2027 | C59: =PL!E32 -> 3.7462334 | D59: 參考：25 分位 | E59: =pe_peak -> 16.48 | F59: =C59*E59 -> 61.737927 | G59: =F59/px-1 -> -0.57451463
A60: C | B60: FY2027 | C60: =PL!E32 -> 3.7462334 | D60: 參考：中位數 | E60: =pe_mid -> 38.29 | F60: =C60*E60 -> 143.44328 | G60: =F60/px-1 -> -0.011417799
A61: C | B61: FY2027 | C61: =PL!E32 -> 3.7462334 | D61: 參考：75 分位 | E61: =pe_trough -> 43.41 | F61: =C61*E61 -> 162.62399 | G61: =F61/px-1 -> 0.12077183
A62: C | B62: FY2028 | C62: =PL!F32 -> 3.1694636 | D62: 參考：25 分位 | E62: =pe_peak -> 16.48 | F62: =C62*E62 -> 52.23276 | G62: =F62/px-1 -> -0.64002233
A63: C | B63: FY2028 | C63: =PL!F32 -> 3.1694636 | D63: 參考：中位數 | E63: =pe_mid -> 38.29 | F63: =C63*E63 -> 121.35876 | G63: =F63/px-1 -> -0.16361984
A64: C | B64: FY2028 | C64: =PL!F32 -> 3.1694636 | D64: 參考：75 分位 | E64: =pe_trough -> 43.41 | F64: =C64*E64 -> 137.58642 | G64: =F64/px-1 -> -0.051782114
A66: 6. 目前倍數
A67: 項目 | B67: A | C67: B | D67: C | E67: 備註
A68: 現價（stockanalysis 2026-10-23 收盤） | B68: =px -> 145.1
A69: 現價 ÷ FY2026 EPS（模型） | B69: =px/PL!D12 -> 33.460704 | C69: =px/PL!D22 -> 33.460704 | D69: =px/PL!D32 -> 33.460704
A70: 現價 ÷ FY2027 EPS（模型） | B70: =px/PL!E12 -> 20.852803 | C70: =px/PL!E22 -> 30.012147 | D70: =px/PL!E32 -> 38.732237
A71: 現價 ÷ FY2028 EPS（模型） | B71: =px/PL!F12 -> 15.695847 | C71: =px/PL!F22 -> 22.415919 | D71: =px/PL!F32 -> 45.780617
A72: 近 12 月 P/E（stockanalysis，2026-10-23） | B72: 39.84 | E72: 近 12 月 EPS 3.64（同站）
A73: 現價 ÷ 共識 FY2027 EPS（marketscreener 6.448） | B73: =px/cons_eps27 -> 22.503102
A74: 現價隱含倍數 ÷ 規則倍數（情境 A，FY2027） | B74: =B70/E38 -> 0.5446018 | E74: >1＝現價高於規則給的倍數
A77: 0. 目標價
A78: 0.1 DCF（股東權益現金流，FY2027–FY2032 明確期＋FY2032 後永續）
A79: 項目 | B79: A（順利） | C79: B（平平） | D79: C（不如預期） | E79: 說明
A80: 情境 EPS（FY2027–FY2032） | E80: PL 頁延伸區塊；FY2030 起為收斂法
A81: FY2027 | B81: =PL!E153 -> 6.9582971 | C81: =PL!E160 -> 4.8347091 | D81: =PL!E167 -> 3.7462334
A82: FY2028 | B82: =PL!F153 -> 9.2444838 | C82: =PL!F160 -> 6.4730783 | D82: =PL!F167 -> 3.1694636
A83: FY2029 | B83: =PL!G153 -> 10.040953 | C83: =PL!G160 -> 6.4183119 | D83: =PL!G167 -> 3.2525311
A84: FY2030 | B84: =PL!H153 -> 10.724324 | C84: =PL!H160 -> 6.1545724 | D84: =PL!H167 -> 3.2163705
A85: FY2031 | B85: =PL!I153 -> 11.410993 | C85: =PL!I160 -> 5.9857122 | D85: =PL!I167 -> 3.1829944
A86: FY2032 | B86: =PL!J153 -> 12.095653 | C86: =PL!J160 -> 5.9012412 | D86: =PL!J167 -> 3.1521677
A87: 股東現金流＝EPS ×（1 − tp_g ÷ tp_roe） | E87: 模型無折舊與資本支出項目，故不用（淨利＋折舊－資本支出）；設備股資本支出低（2026 第三季資本支出含資本化研發 €8.5M），此式偏誤小
A88: 再投資率（tp_g ÷ tp_roe，上限 0.8） | B88: =MIN(tp_g/tp_roe,0.8) -> 0.11779719 | E88: ROE 為近三年平均（In 頁 tp_roe）
A89: FY2027 | B89: =B81*(1-$B$88) -> 6.1386293 | C89: =C81*(1-$B$88) -> 4.2651939 | D89: =D81*(1-$B$88) -> 3.3049376
A90: FY2028 | B90: =B82*(1-$B$88) -> 8.1555095 | C90: =C82*(1-$B$88) -> 5.7105679 | D90: =D82*(1-$B$88) -> 2.7961097
A91: FY2029 | B91: =B83*(1-$B$88) -> 8.8581573 | C91: =C83*(1-$B$88) -> 5.6622528 | D91: =D83*(1-$B$88) -> 2.869392
A92: FY2030 | B92: =B84*(1-$B$88) -> 9.4610285 | C92: =C84*(1-$B$88) -> 5.4295811 | D92: =D84*(1-$B$88) -> 2.8374911
A93: FY2031 | B93: =B85*(1-$B$88) -> 10.06681 | C93: =C85*(1-$B$88) -> 5.2806121 | D93: =D85*(1-$B$88) -> 2.8080466
A94: FY2032 | B94: =B86*(1-$B$88) -> 10.670819 | C94: =C86*(1-$B$88) -> 5.2060916 | D94: =D86*(1-$B$88) -> 2.7808512
A95: DCF 情境每股價值（折現率 tp_r） | B95: =MAX(0,SUMPRODUCT(B89:B94,1/(1+tp_r)^{1;2;3;4;5;6})+B94*(1+tp_g)/(tp_r-tp_g)/(1+tp_r)^6) -> 142.11762 | C95: =MAX(0,SUMPRODUCT(C89:C94,1/(1+tp_r)^{1;2;3;4;5;6})+C94*(1+tp_g)/(tp_r-tp_g)/(1+tp_r)^6) -> 73.714604 | D95: =MAX(0,SUMPRODUCT(D89:D94,1/(1+tp_r)^{1;2;3;4;5;6})+D94*(1+tp_g)/(tp_r-tp_g)/(1+tp_r)^6) -> 39.930924 | E95: Σ 明確期現金流 ÷ (1＋r)^t ＋ 永續價值 ÷ (1＋r)^6；永續價值＝FY2032 現金流 ×(1＋g)÷(r−g)；基準日 2026 年底，t＝1 對 FY2027；任一情境 DCF < 0 時取 0（股東有限責任），仍照 tp_w_dcf 加權
A96: DCF 情境價值推到 12 個月後（×(1＋tp_r)） | B96: =B95*(1+tp_r) -> 156.32938 | C96: =C95*(1+tp_r) -> 81.086064 | D96: =D95*(1+tp_r) -> 43.924016
A97: DCF 目標價（情境加權） | B97: =tp_wA*B96+tp_wB*C96+tp_wC*D96 -> 96.226649 | E97: Σ 權重 × 情境價值 ×(1＋r)；權重見 In 頁 tp_wA／tp_wB／tp_wC
A99: 0.2 Comparable（市場主流同業前瞻 P/E）
A100: 同業與前瞻 P/E | B100: 代號 | C100: 前瞻 12 月 P/E | D100: 日期 | E100: 來源 | F100: 標記
A101: ASM International | B101: ASM.AS | C101: 25.77 | D101: 2026-10-23 | E101: stockanalysis.com statistics：Forward PE（分析師共識；價格日期如左） | F101: Interested-party
A102: ASMPT | B102: 0522.HK | C102: 30.26 | D102: 2026-09-23 | E102: stockanalysis.com statistics：Forward PE（頁面價格日 2026-09-23，較舊） | F102: Interested-party
A103: Kulicke & Soffa | B103: KLIC | C103: 12.61 | D103: 2026-10-23 | E103: stockanalysis.com statistics：Forward PE | F103: Interested-party
A104: Disco | B104: 6146.T | C104: 26.01 | D104: 2026-10-23 | E104: stockanalysis.com statistics：Forward PE | F104: Interested-party
A105: 韓美半導體 Hanmi | B105: 042700.KS | C105: 44.63 | D105: 2026-08-07 | E105: stockanalysis.com statistics：Forward PE（頁面價格日 2026-08-07，較舊） | F105: Interested-party
A106: 同業前瞻 P/E 中位數 | B106: =MEDIAN(C101:C105) -> 26.01 | E106: 後段與鍵合設備同業：ASM International（前段沉積，券商常與 BESI 並列）、ASMPT（TC／混合鍵合）、Kulicke & Soffa、Disco、韓美（TC 鍵合）；不含 A 股；韓華 Semitech、SEMES 未上市
A107: 12 個月後的前瞻 EPS（情境加權） | B107: =tp_wA*(2/12*B81+10/12*B82)+tp_wB*(2/12*C81+10/12*C82)+tp_wC*(2/12*D81+10/12*D82) -> 6.4121626 | E107: 約 2027-10 時的未來 12 月 ≈ 2／12 × FY2027＋10／12 × FY2028（會計年度＝日曆年）
A108: Comparable 目標價 | B108: =B106*B107 -> 166.78035 | E108: 同業中位數 × 上列 EPS
...

Sheet Recon
A1: Recon — 本模型 vs 共識、公司長期目標、累計訂單。只作事後對照，不為對上數字而調整參數。差距 > 10% 的原因見 README
A3: 項目 | B3: 對照值 | C3: 模型 A | D3: 差距 A | E3: 模型 B | F3: 差距 B | G3: 模型 C | H3: 差距 C | I3: 對照來源 | J3: 說明
A4: A. FY2026 vs 共識（校準未使用）
A5: 營收 | B5: =cons_rev26 -> 1002 | C5: =PL!D5 -> 1001.6 | D5: =C5/B5-1 -> -0.0003992016 | E5: =PL!D15 -> 1001.6 | F5: =E5/B5-1 -> -0.0003992016 | G5: =PL!D25 -> 1001.6 | H5: =G5/B5-1 -> -0.0003992016 | I5: marketscreener 共識（2026-10-09） | J5: 錨點＝前三季實績＋第四季指引中點
A6: EPS（歐元） | B6: =cons_eps26 -> 4.334 | C6: =PL!D12 -> 4.3364299 | D6: =C6/B6-1 -> 0.00056066914 | E6: =PL!D22 -> 4.3364299 | F6: =E6/B6-1 -> 0.00056066914 | G6: =PL!D32 -> 4.3364299 | H6: =G6/B6-1 -> 0.00056066914 | I6: marketscreener 共識（2026-10-09） | J6: stockanalysis 4.42
A7: B. FY2027–FY2028 vs 共識（第三季財報前的共識）
A8: FY2027 營收 | B8: =cons_rev27 -> 1345 | C8: =PL!E5 -> 1415.7993 | D8: =C8/B8-1 -> 0.052638861 | E8: =PL!E15 -> 1095.3653 | F8: =E8/B8-1 -> -0.18560202 | G8: =PL!E25 -> 931.12221 | H8: =G8/B8-1 -> -0.30771583 | I8: marketscreener
A9: FY2027 EPS（歐元） | B9: =cons_eps27 -> 6.448 | C9: =PL!E12 -> 6.9582971 | D9: =C9/B9-1 -> 0.079140375 | E9: =PL!E22 -> 4.8347091 | F9: =E9/B9-1 -> -0.2502002 | G9: =PL!E32 -> 3.7462334 | H9: =G9/B9-1 -> -0.41900847 | I9: marketscreener
A10: FY2028 營收 | B10: =cons_rev28 -> 1649 | C10: =PL!F5 -> 1775.631 | D10: =C10/B10-1 -> 0.076792613 | E10: =PL!F15 -> 1342.5833 | F10: =E10/B10-1 -> -0.18581972 | G10: =PL!F25 -> 848.23202 | H10: =G10/B10-1 -> -0.48560824 | I10: marketscreener
A11: FY2028 EPS（歐元） | B11: =cons_eps28 -> 8.483 | C11: =PL!F12 -> 9.2444838 | D11: =C11/B11-1 -> 0.089765857 | E11: =PL!F22 -> 6.4730783 | F11: =E11/B11-1 -> -0.23693524 | G11: =PL!F32 -> 3.1694636 | H11: =G11/B11-1 -> -0.62637468 | I11: marketscreener
A12: C. 公司長期目標與累計訂單
A13: FY2029 營收 vs 長期目標下緣 €1.7B | B13: =lt_lo -> 1700 | C13: =PL!G5 -> 1903.6318 | D13: =C13/B13-1 -> 0.11978338 | E13: =PL!G15 -> 1328.4865 | F13: =E13/B13-1 -> -0.21853733 | G13: =PL!G25 -> 861.18583 | H13: =G13/B13-1 -> -0.4934201 | I13: 投資人日 2026-06-19（目標年度未載明） | J13: Interested-party
A14: FY2029 營收 vs 長期目標上緣 €2.2B | B14: =lt_hi -> 2200 | C14: =PL!G5 -> 1903.6318 | D14: =C14/B14-1 -> -0.13471284 | E14: =PL!G15 -> 1328.4865 | F14: =E14/B14-1 -> -0.39614248 | G14: =PL!G25 -> 861.18583 | H14: =G14/B14-1 -> -0.6085519 | I14: 同上
A15: FY2026 混合鍵合隱含機台數 vs 2026 年前三季新增訂單（215 − 150） | B15: =hb_cum26q3-hb_cum25 -> 65 | C15: =PL!D72 -> 100.16 | D15: =C15/B15-1 -> 0.54092308 | E15: =PL!D107 -> 100.16 | F15: =E15/B15-1 -> 0.54092308 | G15: =PL!D142 -> 100.16 | H15: =G15/B15-1 -> 0.54092308 | I15: 公司：累計 150＋→ 215＋台 | J15: 口徑：營收（出貨）vs 訂單；邏輯機台單價可能與 HBM 不同

Sheet Sens
A1: Sens — 一次動一個輸入（情境 A）：對 FY2027、FY2028 營收與 EPS 的影響。每個案例是一個完整的推導區塊（本頁下方，與 PL 同一引擎；校準係數 k 在各區塊內重算）
A3: 案例 | B3: 設定 | C3: FY2027 營收 €M | D3: FY2027 EPS € | E3: 相對基準 | F3: FY2028 營收 €M | G3: FY2028 EPS € | H3: 相對基準
A4: 基準（情境 A） | B4: PL 區塊 A | C4: =PL!E63 -> 1415.7993 | D4: =PL!E71 -> 6.9582971 | E4: =D4/D$4-1 -> 0 | F4: =PL!F63 -> 1775.631 | G4: =PL!F71 -> 9.2444838 | H4: =G4/G$4-1 -> 0
A5: HBM 混合鍵合 Disco 基準 | B5: 2028 5%、2029 15%、2030 25% | C5: =E83 -> 1371.5387 | D5: =E91 -> 6.6649727 | E5: =D5/D$4-1 -> -0.042154625 | F5: =F83 -> 1708.1167 | G5: =F91 -> 8.7970511 | H5: =G5/G$4-1 -> -0.048399962
A6: HBM 混合鍵合 Disco 低值 | B6: 2028 0、2029 5%、2030 10% | C6: =E128 -> 1338.8585 | D6: =E136 -> 6.4483937 | E6: =D6/D$4-1 -> -0.073279922 | F6: =F128 -> 1653.3031 | G6: =F136 -> 8.4337889 | H6: =G6/G$4-1 -> -0.08769498
A7: 邏輯導入 低（×0.7） | B7: 2028 起各年比例 × 0.7 | C7: =E173 -> 1180.9314 | D7: =E181 -> 5.4017749 | E7: =D7/D$4-1 -> -0.22369298 | F7: =F173 -> 1596.8416 | G7: =F181 -> 8.0596058 | H7: =G7/G$4-1 -> -0.12817134
A8: 邏輯導入 高（×1.3） | C8: =E218 -> 1650.6672 | D8: =E226 -> 8.5148194 | E8: =D8/D$4-1 -> 0.22369298 | F8: =F218 -> 1954.4205 | G8: =F226 -> 10.429362 | H8: =G8/G$4-1 -> 0.12817134
A9: 邏輯導入 取情境 B 路徑 | C9: =E263 -> 1285.3171 | D9: =E271 -> 6.0935626 | E9: =D9/D$4-1 -> -0.12427388 | F9: =F263 -> 1592.9338 | G9: =F271 -> 8.033708 | H9: =G9/G$4-1 -> -0.13097278
A10: FY2026 混合鍵合占比 18% | B10: k 較低、主流業務基期較高 | C10: =E308 -> 1377.1045 | D10: =E316 -> 6.712462 | E10: =D10/D$4-1 -> -0.035329789 | F10: =F308 -> 1703.5152 | G10: =F316 -> 8.7875834 | H10: =G10/G$4-1 -> -0.049424111
A11: FY2026 混合鍵合占比 35% | B11: k 較高、主流業務基期較低 | C11: =E353 -> 1471.0775 | D11: =E361 -> 7.3014222 | E11: =D11/D$4-1 -> 0.049311648 | F11: =F353 -> 1878.6536 | G11: =F361 -> 9.8821622 | H11: =G11/G$4-1 -> 0.068979345
A12: 機台有效產出 600／時 | B12: 機台數較多 | C12: =E398 -> 1467.0931 | D12: =E406 -> 7.2982328 | E12: =D12/D$4-1 -> 0.048853282 | F12: =F398 -> 1885.2583 | G12: =F406 -> 9.9710081 | H12: =G12/G$4-1 -> 0.078590037
A13: 機台有效產出 1,500／時 | C13: =E443 -> 1390.1524 | D13: =E451 -> 6.7883293 | E13: =D13/D$4-1 -> -0.024426641 | F13: =F443 -> 1720.8174 | G13: =F451 -> 8.8812216 | H13: =G13/G$4-1 -> -0.039295018
A14: HBM 機台單價 €2.0M | C14: =E488 -> 1400.4111 | D14: =E496 -> 6.8563164 | E14: =D14/D$4-1 -> -0.014655984 | F14: =F488 -> 1742.7428 | G14: =F496 -> 9.0265265 | H14: =G14/G$4-1 -> -0.023577011
A15: HBM 機台單價 €3.5M | C15: =E533 -> 1446.5756 | D15: =E541 -> 7.1622585 | E15: =D15/D$4-1 -> 0.029311969 | F15: =F533 -> 1841.4074 | G15: =F541 -> 9.6803984 | H15: =G15/G$4-1 -> 0.047154022
A16: BESI HBM 份額 −10pt | B16: 50% | C16: =E578 -> 1402.9758 | D16: =E586 -> 6.8733132 | E16: =D16/D$4-1 -> -0.01221332 | F16: =F578 -> 1748.2242 | G16: =F586 -> 9.0628527 | H16: =G16/G$4-1 -> -0.019647509
A17: BESI HBM 份額 +10pt | B17: 70% | C17: =E623 -> 1428.6227 | D17: =E631 -> 7.0432811 | E17: =D17/D$4-1 -> 0.01221332 | F17: =F623 -> 1803.0378 | G17: =F631 -> 9.4261148 | H17: =G17/G$4-1 -> 0.019647509
A18: 邏輯相對份額 0.9 | C18: =E668 -> 1371.9631 | D18: =E676 -> 6.6677852 | E18: =D18/D$4-1 -> -0.041750433 | F18: =F668 -> 1716.0345 | G18: =F676 -> 8.8495245 | H18: =G18/G$4-1 -> -0.042723782
A19: 晶粒容量 低 | B19: 各年取低值（晶粒較多） | C19: =E713 -> 1430.381 | D19: =E721 -> 7.0549339 | E19: =D19/D$4-1 -> 0.013887984 | F19: =F713 -> 1799.7984 | G19: =F721 -> 9.4046463 | H19: =G19/G$4-1 -> 0.017325196
A20: 晶粒容量 高 | B20: 各年取高值（晶粒較少） | C20: =E758 -> 1405.0513 | D20: =E766 -> 6.8870681 | E20: =D20/D$4-1 -> -0.01023656 | F20: =F758 -> 1770.8683 | G20: =F766 -> 9.2129198 | H20: =G20/G$4-1 -> -0.0034143537
A21: 汰換比例 5% | C21: =E803 -> 1408.1751 | D21: =E811 -> 6.9077699 | E21: =D21/D$4-1 -> -0.0072614365 | F21: =F803 -> 1748.4378 | G21: =F811 -> 9.064268 | H21: =G21/G$4-1 -> -0.019494411
A22: 汰換比例 15% | C22: =E848 -> 1423.0552 | D22: =E856 -> 7.0063837 | E22: =D22/D$4-1 -> 0.0069106846 | F22: =F848 -> 1801.5519 | G22: =F856 -> 9.4162673 | H22: =G22/G$4-1 -> 0.018582271
A23: 主流業務彈性 0.5 | C23: =E893 -> 1341.1507 | D23: =E901 -> 6.5276733 | E23: =D23/D$4-1 -> -0.061886381 | F23: =F893 -> 1638.8631 | G23: =F901 -> 8.4555132 | H23: =G23/G$4-1 -> -0.085345014
A24: 主流業務彈性 1.5 | C24: =E938 -> 1490.4479 | D24: =E946 -> 7.388921 | E24: =D24/D$4-1 -> 0.061886381 | F24: =F938 -> 1921.9096 | G24: =F946 -> 10.088318 | H24: =G24/G$4-1 -> 0.09127977
A25: 混合鍵合毛利溢價 0 | C25: =E983 -> 1415.7993 | D25: =E991 -> 6.819769 | E25: =D25/D$4-1 -> -0.01990834 | F25: =F983 -> 1775.631 | G25: =F991 -> 8.9727561 | H25: =G25/G$4-1 -> -0.029393494
A26: 混合鍵合毛利溢價 15pt | C26: =E1028 -> 1415.7993 | D26: =E1036 -> 7.0795093 | E26: =D26/D$4-1 -> 0.017419798 | F26: =F1028 -> 1775.631 | G26: =F1036 -> 9.4822455 | H26: =G26/G$4-1 -> 0.025719307
A27: 營業費用變動比例 25% | C27: =E1073 -> 1415.7993 | D27: =E1081 -> 7.1068367 | E27: =D27/D$4-1 -> 0.02134711 | F27: =F1073 -> 1775.631 | G27: =F1081 -> 9.5220656 | H27: =G27/G$4-1 -> 0.030026758
A28: 營業費用變動比例 60% | C28: =E1118 -> 1415.7993 | D28: =E1126 -> 6.7602444 | E28: =D28/D$4-1 -> -0.028462814 | F28: =F1118 -> 1775.631 | G28: =F1126 -> 8.8743746 | H28: =G28/G$4-1 -> -0.040035677
A29: 第四季營收 −5% | B29: 錨點較低 → k、主流基期較低 | C29: =E1163 -> 1396.8579 | D29: =E1171 -> 6.9828144 | E29: =D29/D$4-1 -> 0.0035234525 | F29: =F1163 -> 1752.8369 | G29: =F1171 -> 9.280312 | H29: =G29/G$4-1 -> 0.0038756292
A30: 第四季營收 +5% | C30: =E1208 -> 1434.7406 | D30: =E1216 -> 6.9339937 | E30: =D30/D$4-1 -> -0.0034927299 | F30: =F1208 -> 1798.4251 | G30: =F1216 -> 9.2091125 | H30: =G30/G$4-1 -> -0.003826206
A31: 稅率 16% | C31: =E1253 -> 1415.7993 | D31: =E1261 -> 6.7571903 | E31: =D31/D$4-1 -> -0.028901734 | F31: =F1253 -> 1775.631 | G31: =F1261 -> 8.9773022 | H31: =G31/G$4-1 -> -0.028901734
A32: 情境 B | B32: 上游皆取 B；HBM 混合鍵合基準；邏輯導入、份額取 B | C32: =PL!E98 -> 1095.3653 | D32: =PL!E106 -> 4.8347091 | E32: =D32/D$4-1 -> -0.30518789 | F32: =PL!F98 -> 1342.5833 | G32: =PL!F106 -> 6.4730783 | H32: =G32/G$4-1 -> -0.29979018
A33: 情境 C | B33: 上游皆取 C；HBM 混合鍵合低值；邏輯導入慢、份額流失、毛利率下調 | C33: =PL!E133 -> 931.12221 | D33: =PL!E141 -> 3.7462334 | E33: =D33/D$4-1 -> -0.46161635 | F33: =PL!F133 -> 848.23202 | G33: =PL!F141 -> 3.1694636 | H33: =G33/G$4-1 -> -0.65715083
A35: 讀法：機台比產能早一年買，FY2027 的營收看 CY2027→2028 的需求增量。邏輯段的校準係數 k 由 FY2026 營收推得，導入比例的水準被 k 吸收，只有比例的變化（斜率）影響之後各年；FY2026 混合鍵合占比同時改變 k 與主流業務基期，兩者方向相反。
A60: 案例區塊：HBM 混合鍵合 Disco 基準（情境 A）
A61: 項目 | B61: 單位 | C61: 2025 | D61: 2026 | E61: 2027 | F61: 2028 | G61: 2029 | H61: 2030 | I61: 說明
A62: A. HBM 混合鍵合（日曆年；與韓美同一晶粒口徑）
A63: HBM 出貨位元 | B63: EB | C63: =hsA_25 -> 2.2251147 | D63: =hsA_26 -> 3.782695 | E63: =hsA_27 -> 5.8631772 | F63: =hsA_28 -> 8.501607 | G63: =hsA_29 -> 11.477169 | H63: =G63*(1+g_tail) -> 12.624886 | I63: markets/memory 同字母情境；2030＝2029 ×（1＋g_tail）
A64: DRAM 晶粒容量 | B64: Gb | C64: =den_25 -> 24 | D64: =den_26 -> 24 | E64: =den_27 -> 26 | F64: =den_28 -> 28 | G64: =den_29 -> 30 | H64: =den_30 -> 32
A65: 核心晶粒數＝位元 × 8000 ÷ 容量 | B65: 百萬顆 | C65: =C63*8000/C64 -> 741.7049 | D65: =D63*8000/D64 -> 1260.8983 | E65: =E63*8000/E64 -> 1804.0545 | F65: =F63*8000/F64 -> 2429.0306 | G65: =G63*8000/G64 -> 3060.5785 | H65: =H63*8000/H64 -> 3156.2216 | I65: 1 EB＝8×10⁹ Gb；每顆核心晶粒鍵合一次
A66: 平均堆疊層數 | B66: 層 | C66: =stk_25 -> 10 | D66: =stk_26 -> 12 | E66: =stk_27 -> 12.5 | F66: =stk_28 -> 14 | G66: =stk_29 -> 15 | H66: =stk_30 -> 16
A67: 層數加權（每顆晶粒鍵合時間） | B67: x | C67: =1+beta*(C66-$C66)/4 -> 1 | D67: =1+beta*(D66-$C66)/4 -> 1.05 | E67: =1+beta*(E66-$C66)/4 -> 1.0625 | F67: =1+beta*(F66-$C66)/4 -> 1.1 | G67: =1+beta*(G66-$C66)/4 -> 1.125 | H67: =1+beta*(H66-$C66)/4 -> 1.15
A68: 混合鍵合占比 | B68: % | C68: =hbp_25 -> 0 | D68: =hbp_26 -> 0 | E68: =hbp_27 -> 0 | F68: =hbp_28 -> 0.05 | G68: =hbp_29 -> 0.15 | H68: =hbp_30 -> 0.25
A69: 混合鍵合產能需求（晶粒 × 層數加權 × 混合鍵合占比） | B69: 百萬顆當量 | C69: =C65*C67*C68 -> 0 | D69: =D65*D67*D68 -> 0 | E69: =E65*E67*E68 -> 0 | F69: =F65*F67*F68 -> 133.59668 | G69: =G65*G67*G68 -> 516.47263 | H69: =H65*H67*H68 -> 907.41371
A70: 所需機台＝產能需求 ÷ 每台年產能 | B70: 台 | C70: =C69/thr -> 0 | D70: =D69/thr -> 0 | E70: =E69/thr -> 0 | F70: =F69/thr -> 21.786804 | G70: =G69/thr -> 84.225803 | H70: =H69/thr -> 147.98006
A71: 新機需求＝MAX(0, 下一年 − 本年)＋汰換 × 本年 | B71: 台 | C71: =MAX(0,D70-C70)+dlt*C70 -> 0 | D71: =MAX(0,E70-D70)+dlt*D70 -> 0 | E71: =MAX(0,F70-E70)+dlt*E70 -> 21.786804 | F71: =MAX(0,G70-F70)+dlt*F70 -> 64.61768 | G71: =MAX(0,H70-G70)+dlt*G70 -> 72.176834 | I71: 機台在產能需要前一年購入
A72: B. 邏輯混合鍵合（SoIC 類；日曆年）
A73: AI 先進封裝晶圓需求＝台積電 CoWoS 需求 × 情境顆數係數 | B73: 千片 | D73: =cow_26*1 -> 1107.8576 | E73: =cow_27*1 -> 2096.4286 | F73: =cow_28*um28_A -> 2620.0893 | G73: =cow_29*um29_A -> 3013.3259 | H73: =G73*(1+g_tail) -> 3314.6585 | I73: 2030＝2029 ×（1＋g_tail）
A74: 混合鍵合占 AI 先進封裝晶圓比例 | B74: % | D74: =attA_26 -> 0.08 | E74: =attA_27 -> 0.11 | F74: =attA_28 -> 0.18 | G74: =attA_29 -> 0.26 | H74: =attA_30 -> 0.34
A75: 混合鍵合邏輯晶圓（需求指數） | B75: 千片當量 | D75: =D73*D74 -> 88.62861 | E75: =E73*E74 -> 230.60714 | F75: =F73*F74 -> 471.61607 | G75: =G73*G74 -> 783.46473 | H75: =H73*H74 -> 1126.9839
A76: 新機需求指數＝MAX(0, 下一年 − 本年)＋汰換 × 本年 | B76: 千片當量 | D76: =MAX(0,E75-D75)+dlt*D75 -> 150.84139 | E76: =MAX(0,F75-E75)+dlt*E75 -> 264.06964 | F76: =MAX(0,G75-F75)+dlt*F75 -> 359.01027 | G76: =MAX(0,H75-G75)+dlt*G75 -> 421.86563
A77: C. 損益（會計年度；FY2026＝錨點）
A78: HBM 混合鍵合營收＝新機 × 單價 × BESI 份額 | B78: €M | C78: =0 -> 0 | D78: =hbm26 -> 0 | E78: =E71*asp*shm_A -> 32.680206 | F78: =F71*asp*shm_A -> 96.92652 | G78: =G71*asp*shm_A -> 108.26525 | I78: FY2025–26 尚未量產（Assumed 0）
A79: 邏輯與其他混合鍵合營收 | B79: €M | C79: =hb25 -> 120 | D79: =rev26*hb_sh26-hbm26 -> 250.4 | E79: =$D80*E76*shl_A -> 438.36136 | F79: =$D80*F76*shl_A -> 595.96487 | G79: =$D80*G76*shl_A -> 700.30613 | I79: FY2026＝錨點營收 × 混合鍵合占比；FY2027 起＝k × 新機需求指數 × 相對份額
A80: 校準係數 k＝FY2026 邏輯混合鍵合營收 ÷ FY2026 新機需求指數 | B80: €M／千片當量 | D80: =D79/D76 -> 1.6600218 | I80: 只用 FY2026（台積電 CoWoS 需求自 2026 起）；不使用共識
A81: 混合鍵合營收合計 | B81: €M | C81: =C78+C79 -> 120 | D81: =D78+D79 -> 250.4 | E81: =E78+E79 -> 471.04157 | F81: =F78+F79 -> 692.89139 | G81: =G78+G79 -> 808.57138
A82: 主流業務營收（晶粒貼合、封裝、電鍍、TC 鍵合） | B82: €M | C82: =a25_rev-hb25 -> 471.3 | D82: =rev26-D81 -> 751.2 | E82: =D82*(1+el*eqgA_27) -> 900.49718 | F82: =E82*(1+el*eqgA_28) -> 1015.2253 | G82: =F82*(1+el*eqgA_29) -> 1075.5832 | I82: FY2027 起＝前一年 ×（1＋彈性 × 設備總額年增，markets/equipment 同字母）
A83: 營收 | B83: €M | C83: =C81+C82 -> 591.3 | D83: =D81+D82 -> 1001.6 | E83: =E81+E82 -> 1371.5387 | F83: =F81+F82 -> 1708.1167 | G83: =G81+G82 -> 1884.1545
A84: 混合鍵合占營收 | B84: % | C84: =C81/C83 -> 0.20294267 | D84: =D81/D83 -> 0.25 | E84: =E81/E83 -> 0.34344022 | F84: =F81/F83 -> 0.4056464 | G84: =G81/G83 -> 0.42914281
A85: 毛利率 | B85: % | C85: =a25_gp/a25_rev -> 0.63301201 | D85: =gp26/rev26 -> 0.64664137 | E85: =$D85+gm_prem*(E84-$D84)+0 -> 0.65411659 | F85: =$D85+gm_prem*(F84-$D84)+0 -> 0.65909309 | G85: =$D85+gm_prem*(G84-$D84)+0 -> 0.6609728 | I85: FY2026＝錨點；FY2027 起＝FY2026＋溢價 × 混合鍵合占比變化（情境 C 另扣價格競爭）
A86: 毛利 | B86: €M | C86: =a25_gp -> 374.3 | D86: =gp26 -> 647.676 | E86: =E83*E85 -> 897.14625 | F86: =F83*F85 -> 1125.8079 | G86: =G83*G85 -> 1245.3749
A87: 營業費用 | B87: €M | C87: =a25_opx -> 201.2 | D87: =opx26 -> 223.1325 | E87: =opex_fix+opex_var*E83 -> 256.0979 | F87: =opex_fix+opex_var*F83 -> 286.0905 | G87: =opex_fix+opex_var*G83 -> 301.77731 | I87: 固定＋變動 × 營收
A88: 營業利益 | B88: €M | C88: =C86-C87 -> 173.1 | D88: =D86-D87 -> 424.5435 | E88: =E86-E87 -> 641.04835 | F88: =F86-F87 -> 839.7174 | G88: =G86-G87 -> 943.59759
A89: 營業利益率 | B89: % | C89: =C88/C83 -> 0.2927448 | D89: =D88/D83 -> 0.42386532 | E89: =E88/E83 -> 0.46739354 | F89: =F88/F83 -> 0.49160423 | G89: =G88/G83 -> 0.5008069
A90: 淨利 | B90: €M | C90: =a25_ni -> 131.6 | D90: =ni26 -> 348.26413 | E90: =(E88-fin)*(1-tax) -> 537.20682 | F90: =(F88-fin)*(1-tax) -> 709.05555 | G90: =(G88-fin)*(1-tax) -> 798.91191
A91: EPS | B91: € | C91: =a25_eps -> 1.66 | D91: =eps26 -> 4.3364299 | E91: =E90/shares -> 6.6649727 | F91: =F90/shares -> 8.7970511 | G91: =G90/shares -> 9.9118736
A92: 混合鍵合營收隱含機台數＝營收 ÷ 單價（對帳用） | B92: 台 | C92: =C81/asp -> 48 | D92: =D81/asp -> 100.16 | E92: =E81/asp -> 188.41663 | F92: =F81/asp -> 277.15655 | G92: =G81/asp -> 323.42855
A105: 案例區塊：HBM 混合鍵合 Disco 低值（情境 A）
A106: 項目 | B106: 單位 | C106: 2025 | D106: 2026 | E106: 2027 | F106: 2028 | G106: 2029 | H106: 2030 | I106: 說明
A107: A. HBM 混合鍵合（日曆年；與韓美同一晶粒口徑）
A108: HBM 出貨位元 | B108: EB | C108: =hsA_25 -> 2.2251147 | D108: =hsA_26 -> 3.782695 | E108: =hsA_27 -> 5.8631772 | F108: =hsA_28 -> 8.501607 | G108: =hsA_29 -> 11.477169 | H108: =G108*(1+g_tail) -> 12.624886 | I108: markets/memory 同字母情境；2030＝2029 ×（1＋g_tail）
A109: DRAM 晶粒容量 | B109: Gb | C109: =den_25 -> 24 | D109: =den_26 -> 24 | E109: =den_27 -> 26 | F109: =den_28 -> 28 | G109: =den_29 -> 30 | H109: =den_30 -> 32
A110: 核心晶粒數＝位元 × 8000 ÷ 容量 | B110: 百萬顆 | C110: =C108*8000/C109 -> 741.7049 | D110: =D108*8000/D109 -> 1260.8983 | E110: =E108*8000/E109 -> 1804.0545 | F110: =F108*8000/F109 -> 2429.0306 | G110: =G108*8000/G109 -> 3060.5785 | H110: =H108*8000/H109 -> 3156.2216 | I110: 1 EB＝8×10⁹ Gb；每顆核心晶粒鍵合一次
A111: 平均堆疊層數 | B111: 層 | C111: =stk_25 -> 10 | D111: =stk_26 -> 12 | E111: =stk_27 -> 12.5 | F111: =stk_28 -> 14 | G111: =stk_29 -> 15 | H111: =stk_30 -> 16
A112: 層數加權（每顆晶粒鍵合時間） | B112: x | C112: =1+beta*(C111-$C111)/4 -> 1 | D112: =1+beta*(D111-$C111)/4 -> 1.05 | E112: =1+beta*(E111-$C111)/4 -> 1.0625 | F112: =1+beta*(F111-$C111)/4 -> 1.1 | G112: =1+beta*(G111-$C111)/4 -> 1.125 | H112: =1+beta*(H111-$C111)/4 -> 1.15
A113: 混合鍵合占比 | B113: % | C113: =hbp_25_lo -> 0 | D113: =hbp_26_lo -> 0 | E113: =hbp_27_lo -> 0 | F113: =hbp_28_lo -> 0 | G113: =hbp_29_lo -> 0.05 | H113: =hbp_30_lo -> 0.1
A114: 混合鍵合產能需求（晶粒 × 層數加權 × 混合鍵合占比） | B114: 百萬顆當量 | C114: =C110*C112*C113 -> 0 | D114: =D110*D112*D113 -> 0 | E114: =E110*E112*E113 -> 0 | F114: =F110*F112*F113 -> 0 | G114: =G110*G112*G113 -> 172.15754 | H114: =H110*H112*H113 -> 362.96548
A115: 所需機台＝產能需求 ÷ 每台年產能 | B115: 台 | C115: =C114/thr -> 0 | D115: =D114/thr -> 0 | E115: =E114/thr -> 0 | F115: =F114/thr -> 0 | G115: =G114/thr -> 28.075268 | H115: =H114/thr -> 59.192023
A116: 新機需求＝MAX(0, 下一年 − 本年)＋汰換 × 本年 | B116: 台 | C116: =MAX(0,D115-C115)+dlt*C115 -> 0 | D116: =MAX(0,E115-D115)+dlt*D115 -> 0 | E116: =MAX(0,F115-E115)+dlt*E115 -> 0 | F116: =MAX(0,G115-F115)+dlt*F115 -> 28.075268 | G116: =MAX(0,H115-G115)+dlt*G115 -> 33.924282 | I116: 機台在產能需要前一年購入
A117: B. 邏輯混合鍵合（SoIC 類；日曆年）
A118: AI 先進封裝晶圓需求＝台積電 CoWoS 需求 × 情境顆數係數 | B118: 千片 | D118: =cow_26*1 -> 1107.8576 | E118: =cow_27*1 -> 2096.4286 | F118: =cow_28*um28_A -> 2620.0893 | G118: =cow_29*um29_A -> 3013.3259 | H118: =G118*(1+g_tail) -> 3314.6585 | I118: 2030＝2029 ×（1＋g_tail）
A119: 混合鍵合占 AI 先進封裝晶圓比例 | B119: % | D119: =attA_26 -> 0.08 | E119: =attA_27 -> 0.11 | F119: =attA_28 -> 0.18 | G119: =attA_29 -> 0.26 | H119: =attA_30 -> 0.34
A120: 混合鍵合邏輯晶圓（需求指數） | B120: 千片當量 | D120: =D118*D119 -> 88.62861 | E120: =E118*E119 -> 230.60714 | F120: =F118*F119 -> 471.61607 | G120: =G118*G119 -> 783.46473 | H120: =H118*H119 -> 1126.9839
A121: 新機需求指數＝MAX(0, 下一年 − 本年)＋汰換 × 本年 | B121: 千片當量 | D121: =MAX(0,E120-D120)+dlt*D120 -> 150.84139 | E121: =MAX(0,F120-E120)+dlt*E120 -> 264.06964 | F121: =MAX(0,G120-F120)+dlt*F120 -> 359.01027 | G121: =MAX(0,H120-G120)+dlt*G120 -> 421.86563
A122: C. 損益（會計年度；FY2026＝錨點）
A123: HBM 混合鍵合營收＝新機 × 單價 × BESI 份額 | B123: €M | C123: =0 -> 0 | D123: =hbm26 -> 0 | E123: =E116*asp*shm_A -> 0 | F123: =F116*asp*shm_A -> 42.112902 | G123: =G116*asp*shm_A -> 50.886423 | I123: FY2025–26 尚未量產（Assumed 0）
A124: 邏輯與其他混合鍵合營收 | B124: €M | C124: =hb25 -> 120 | D124: =rev26*hb_sh26-hbm26 -> 250.4 | E124: =$D125*E121*shl_A -> 438.36136 | F124: =$D125*F121*shl_A -> 595.96487 | G124: =$D125*G121*shl_A -> 700.30613 | I124: FY2026＝錨點營收 × 混合鍵合占比；FY2027 起＝k × 新機需求指數 × 相對份額
A125: 校準係數 k＝FY2026 邏輯混合鍵合營收 ÷ FY2026 新機需求指數 | B125: €M／千片當量 | D125: =D124/D121 -> 1.6600218 | I125: 只用 FY2026（台積電 CoWoS 需求自 2026 起）；不使用共識
A126: 混合鍵合營收合計 | B126: €M | C126: =C123+C124 -> 120 | D126: =D123+D124 -> 250.4 | E126: =E123+E124 -> 438.36136 | F126: =F123+F124 -> 638.07777 | G126: =G123+G124 -> 751.19255
A127: 主流業務營收（晶粒貼合、封裝、電鍍、TC 鍵合） | B127: €M | C127: =a25_rev-hb25 -> 471.3 | D127: =rev26-D126 -> 751.2 | E127: =D127*(1+el*eqgA_27) -> 900.49718 | F127: =E127*(1+el*eqgA_28) -> 1015.2253 | G127: =F127*(1+el*eqgA_29) -> 1075.5832 | I127: FY2027 起＝前一年 ×（1＋彈性 × 設備總額年增，markets/equipment 同字母）
A128: 營收 | B128: €M | C128: =C126+C127 -> 591.3 | D128: =D126+D127 -> 1001.6 | E128: =E126+E127 -> 1338.8585 | F128: =F126+F127 -> 1653.3031 | G128: =G126+G127 -> 1826.7757
A129: 混合鍵合占營收 | B129: % | C129: =C126/C128 -> 0.20294267 | D129: =D126/D128 -> 0.25 | E129: =E126/E128 -> 0.32741425 | F129: =F126/F128 -> 0.3859412 | G129: =G126/G128 -> 0.41121225
A130: 毛利率 | B130: % | C130: =a25_gp/a25_rev -> 0.63301201 | D130: =gp26/rev26 -> 0.64664137 | E130: =$D130+gm_prem*(E129-$D129)+0 -> 0.65283451 | F130: =$D130+gm_prem*(F129-$D129)+0 -> 0.65751667 | G130: =$D130+gm_prem*(G129-$D129)+0 -> 0.65953835 | I130: FY2026＝錨點；FY2027 起＝FY2026＋溢價 × 混合鍵合占比變化（情境 C 另扣價格競爭）
A131: 毛利 | B131: €M | C131: =a25_gp -> 374.3 | D131: =gp26 -> 647.676 | E131: =E128*E130 -> 874.05307 | F131: =F128*F130 -> 1087.0743 | G131: =G128*G130 -> 1204.8286
A132: 營業費用 | B132: €M | C132: =a25_opx -> 201.2 | D132: =opx26 -> 223.1325 | E132: =opex_fix+opex_var*E128 -> 253.18575 | F132: =opex_fix+opex_var*F128 -> 281.20604 | G132: =opex_fix+opex_var*G128 -> 296.66426 | I132: 固定＋變動 × 營收
A133: 營業利益 | B133: €M | C133: =C131-C132 -> 173.1 | D133: =D131-D132 -> 424.5435 | E133: =E131-E132 -> 620.86731 | F133: =F131-F132 -> 805.86829 | G133: =G131-G132 -> 908.16439
A134: 營業利益率 | B134: % | C134: =C133/C128 -> 0.2927448 | D134: =D133/D128 -> 0.42386532 | E134: =E133/E128 -> 0.46372884 | F134: =F133/F128 -> 0.48742926 | G134: =G133/G128 -> 0.49714061
A135: 淨利 | B135: €M | C135: =a25_ni -> 131.6 | D135: =ni26 -> 348.26413 | E135: =(E133-fin)*(1-tax) -> 519.75023 | F135: =(F133-fin)*(1-tax) -> 679.77607 | G135: =(G133-fin)*(1-tax) -> 768.26219
A136: EPS | B136: € | C136: =a25_eps -> 1.66 | D136: =eps26 -> 4.3364299 | E136: =E135/shares -> 6.4483937 | F136: =F135/shares -> 8.4337889 | G136: =G135/shares -> 9.5316112
A137: 混合鍵合營收隱含機台數＝營收 ÷ 單價（對帳用） | B137: 台 | C137: =C126/asp -> 48 | D137: =D126/asp -> 100.16 | E137: =E126/asp -> 175.34454 | F137: =F126/asp -> 255.23111 | G137: =G126/asp -> 300.47702
A150: 案例區塊：邏輯導入 低（×0.7）（情境 A）
...

Sheet Sources
A1: 來源（公司新聞稿經 GlobeNewswire／stocktitan 轉載；法說與簡報取自摘要頁，原文待人工複核）
A2: 公司：Q3-26 與前九月實績（2026-10-22；investing.com 簡報摘要） | B2: https://www.investing.com/news/company-news/besi-q3-2026-slides-revenue-doubles-net-margin-hits-38-93CH-4966911
A3: gurufocus：Q3-26 法說重點（混合鍵合 23 家客戶、215＋台、策略檢討、回購 €100M） | B3: https://www.gurufocus.com/news/9137691/be-semiconductor-industries-nv-besiy-q3-2026-earnings-call-highlights-revenue-more-than-doubles-as-hybrid-bonding-momentum-builds
A4: 公司：Q2-26 與上半年實績（2026-07-23；stocktitan 轉載全文） | B4: https://www.stocktitan.net/news/BESIY/be-semiconductor-industries-n-v-announces-q2-26-and-h1-26-v0syj60xvlwf.html
A5: 公司：Q2-26 新聞稿（besi.com） | B5: https://www.besi.com/investor-relations/press-releases/details/be-semiconductor-industries-nv-announces-q2-26-and-h1-26-results/
A6: 公司：Q4-25 與 2025 全年實績（2026-02-19；stocktitan 轉載全文） | B6: https://www.stocktitan.net/news/BESIY/be-semiconductor-industries-n-v-announces-q4-25-and-full-year-2025-1hedov9aoxsi.html
A7: 公司：財務行事曆（2027-02-25 公布 2026 全年） | B7: https://www.besi.com/investor-relations/financial-calendar/
A8: quartr：投資人日 2026 摘要（長期營收 €1.7–2.2B、營業利益率 45–55%） | B8: https://quartr.com/events/be-semiconductor-industries-n-v-besi-investor-day-2026_3eFihPox
A9: 公司產品頁：Datacon 8800 CHAMEO ultra plus AC（2,000 CPH 乾循環、100nm） | B9: https://www.besi.com/products-technology/product-details/product/datacon-8800-chameo-ultra-plus-ac/
A10: tspasemiconductor：混合鍵合營收（FT 引 2023 年 €36M） | B10: https://tspasemiconductor.substack.com/p/hybrid-bonding-at-scale-besis-vision
A11: Morningstar：混合鍵合營收自 2023 年三倍（2025-02-21） | B11: https://morningstar.co.uk/uk/news/261234/be-semiconductor-guidance-disappoints;-long-term-outlook-strong.aspx
A12: stockanalysis：股價、統計、共識目標價、歷史收盤 | B12: https://stockanalysis.com/quote/ams/BESI/forecast/
A13: stockanalysis：年度損益、年底 P/E（2021–2025）、ROE | B13: https://stockanalysis.com/quote/ams/BESI/financials/ratios/
... A16: stockanalysis：同業前瞻 P/E（ASM International、ASMPT、Kulicke & Soffa、Disco、韓美） | B16: https://stockanalysis.com/quote/ams/ASM/statistics/
A17: 市場層與上游成品：skhynix／disco／tsmc／markets/equipment 的 dist（本 repo）
A18: SemiAnalysis | B18: 未使用
