Workbook

Sheet README
A1: 智譜（智譜華章，02513.HK）收支模型 v0.1-Z2（2026-10-08）
A2: 命題（規格 D1，與 OpenAI v0.6 同一句）：智譜每 VR 等值 GW 的年營收能否覆蓋每 GW 年全成本；若不能，缺口要多少外部資金、由誰以什麼條件提供。FY2025–FY2030，曆年制。
A4: 本版範圍 | B4: v0.1-Z2：SRC_ZP（公司財務原始數據）、TK_Link（Tokenomics 快照）、OAI_Link（OpenAI v0.6 命題輸出快照）、Inputs（假設）、Demand（需求與 token）、Revenue（營收）、Checks。Compute、Cost（Z3）與 Funding、Reverse（Z4）尚未建立；容量上限係數暫以 1 佔位（只回乘雲端營收）。
A5: 幣別與單位 | B5: 公司金額一律人民幣億元（RMB 億），與財報一致。港幣、美元數據以 Inputs 匯率（USD/CNY、HKD/CNY，2026-09-28 中間價；定義常數，區間 ±5%）換算後才進計算頁。API 牌價：人民幣元／百萬 token；token：兆（T）；Coding Plan 訂閱者：萬人；智譜清言用戶：百萬人。OAI_Link 為美元（$B），不換算、不參與計算。
A6: Excel 為唯一計算引擎 | B6: 藍字＝輸入（Excel 擁有）；黑字＝公式；綠字＝跨頁連結。builder 只產生結構，重建時保留 Excel 內已改過的藍字（隱藏頁 _Defaults）。公式不含常數（E6）：單位換算、天數、月數為 Inputs 的定義常數。
A7: SRC_ZP | B7: 604 列（SRC_ZP_001–604，Z1 發出、穩定不改號）；有數值者具名 SRC_ZP_nnn，有低／高者另具名 _Lo／_Hi。來源四欄為 CC 初評（builder/source_rules.py）。
A8: TK_Link | B8: Tokenomics v5.26（20261007_Tokenomics_v5.26.xlsx），master 提交 3dd1216，讀取日 2026-10-08；63 個具名範圍（同 OpenAI v0.6 的 63 名）＋7 列以列標籤讀表（狀態『讀表（非具名）』，只供對照）。
A9: OAI_Link | B9: OpenAI v0.6 Excel（20261008_OpenAI_v0.6.xlsx，claude/openai-s6-release@e91df57；SHA-256 34fc34a7ea2c18e8…）的命題輸出逐年值（美元）；只被 Checks 與 HTML 引用（規格 D26）。
A10: Inputs | B10: 73 列（INP_001 起，依 data/zhipu_inputs.yaml 的鍵發號）；每列附標記、依據、區間理由；Analogy／Assumed 一律給區間。
A11: Demand | B11: 需求：①API 按量計費 token（2025、1H26＝營收 ÷ 有效單價倒推；2H26 起任務數 × 每任務 token × 價格反應）②GLM Coding Plan 訂閱者（方案別）× 每訂閱者 token ③智譜清言（免費）用戶 × 任務 × 每任務 token；輸出 DEM_Tok_*（層級 Sol／Luna × 付費／免費）。本地化部署不耗智譜算力，不進 Demand（D4）。
A12: Revenue | B12: 營收：①開放平台及 API（按量計費：層級 × 輸入／快取／輸出 × 有效價；Coding Plan 子列：方案別訂閱）②企業級智能體 ③企業級通用大模型 ④技術服務及其他（②③④＝本地化部署分部，規格 D2r）；廣告＝0（D3）；總額＝淨額（D5）；雲端 vs 本地化、企業 vs 個人彙總；2025 與 1H26 對財報校準差距＝0；公司說法（ARR、平均售價 +101%、呼叫量 40 倍）只列對照。
A13: Checks | B13: C01 起；CHK_Errors 必須為 0。WARN（ARR 對照）與 INFO 不計入。
A14: 標記 | B14: Verified／Interested-party／Analogy／Assumed／Derived／Decision（Analogy、Assumed 一律附區間）。
A15: 分層 | B15: 公司財務原始數據→SRC_ZP；AI 技術與算力→TK_Link（取自 Tokenomics）；假設→Inputs；OpenAI 對照→OAI_Link（不進計算）。

Sheet SRC_ZP
A1: SRC_ZP — 第 0 層 Source：智譜公司財務原始數據（財報、分部、牌價、用戶、算力採購、融資、股本與市值）
A2: 只存已取得的原始訊息（非計算、非假設）。藍字＝原始值，由本活頁簿擁有；來源 data/zhipu_src.yaml（Z1）。AI 技術與算力的物理數據不在此登錄（取自 TK_Link）。
A3: 來源等級（1 一手已讀原文／2 二手或轉載／3 待查核）、立場、立場說明、一手／二手：builder/source_rules.py 機械初評（欄 X 標『CC 初評』）。無數值列＝日期、事件或找不到數值的說明列（另見 Checks）。
A4: SRC_ID | B4: 鍵（key） | C4: 項目 | D4: 值 | E4: 低 | F4: 高 | G4: 單位 | H4: 期間 | I4: 來源 | J4: 網址 | K4: 文件日期 | L4: 擷取日 | M4: 標記 | N4: 利害方與誘因 | O4: 口徑（basis） | P4: 來源等級 | Q4: 立場 | R4: 立場說明 | S4: 一手／二手 | T4: 備註 | U4: 無數值（公式） | V4: 缺出處（公式） | W4: 區間順序異常（公式） | X4: 四欄標註
A5: SRC_ZP_001 | B5: rev_total_fy22 | C5: 營收總額 | D5: 0.5741 | G5: RMB 億 | H5: FY2022 | I5: 智譜招股章程（概要節） | J5: https://www1.hkexnews.hk/listedco/listconews/sehk/2025/1230/2025123000018_c.pdf | K5: 2025-12-30 | L5: 2026-10-08 | M5: Verified | O5: 經審計（會計師報告，招股章程概要轉載） | P5: 1 | Q5: 利害關係方 | R5: 經審計或經審閱的公司公告（誘因：上市後股價、配售；數字可由公告原文核對） | S5: 一手 | T5: 原文「收入 57,409 100.0」；千元值 57,409；RMB 千元÷100,000 換算成億 | U5: =IF(AND($D5="",$E5="",$F5=""),1,0) -> 0 | V5: =IF(OR($I5="",$I5="—"),1,0) -> 0 | W5: =IF(AND(ISNUMBER($D5),ISNUMBER($E5)),IF($E5>$D5,1,0),0)+IF(AND(ISNUMBER($D5),ISNUMBER($F5)),IF($D5>$F5,1,0),0)+IF(AND(ISNUMBER($E5),ISNUMBER($F5)),IF($E5>$F5,1,0),0) -> 0 | X5: CC 初評
A6: SRC_ZP_002 | B6: rev_total_fy23 | C6: 營收總額 | D6: 1.2454 | G6: RMB 億 | H6: FY2023 | I6: 智譜招股章程（概要節） | J6: https://www1.hkexnews.hk/listedco/listconews/sehk/2025/1230/2025123000018_c.pdf | K6: 2025-12-30 | L6: 2026-10-08 | M6: Verified | O6: 經審計（會計師報告，招股章程概要轉載） | P6: 1 | Q6: 利害關係方 | R6: 經審計或經審閱的公司公告（誘因：上市後股價、配售；數字可由公告原文核對） | S6: 一手 | T6: 原文「收入 57,409 100.0」；千元值 124,538；RMB 千元÷100,000 換算成億 | U6: =IF(AND($D6="",$E6="",$F6=""),1,0) -> 0 | V6: =IF(OR($I6="",$I6="—"),1,0) -> 0 | W6: =IF(AND(ISNUMBER($D6),ISNUMBER($E6)),IF($E6>$D6,1,0),0)+IF(AND(ISNUMBER($D6),ISNUMBER($F6)),IF($D6>$F6,1,0),0)+IF(AND(ISNUMBER($E6),ISNUMBER($F6)),IF($E6>$F6,1,0),0) -> 0 | X6: CC 初評
A7: SRC_ZP_003 | B7: rev_total_fy24 | C7: 營收總額 | D7: 3.1241 | G7: RMB 億 | H7: FY2024 | I7: 智譜招股章程（概要節） | J7: https://www1.hkexnews.hk/listedco/listconews/sehk/2025/1230/2025123000018_c.pdf | K7: 2025-12-30 | L7: 2026-10-08 | M7: Verified | O7: 經審計（會計師報告，招股章程概要轉載） | P7: 1 | Q7: 利害關係方 | R7: 經審計或經審閱的公司公告（誘因：上市後股價、配售；數字可由公告原文核對） | S7: 一手 | T7: 原文「收入 57,409 100.0」；千元值 312,414；RMB 千元÷100,000 換算成億 | U7: =IF(AND($D7="",$E7="",$F7=""),1,0) -> 0 | V7: =IF(OR($I7="",$I7="—"),1,0) -> 0 | W7: =IF(AND(ISNUMBER($D7),ISNUMBER($E7)),IF($E7>$D7,1,0),0)+IF(AND(ISNUMBER($D7),ISNUMBER($F7)),IF($D7>$F7,1,0),0)+IF(AND(ISNUMBER($E7),ISNUMBER($F7)),IF($E7>$F7,1,0),0) -> 0 | X7: CC 初評
A8: SRC_ZP_004 | B8: rev_total_1h24 | C8: 營收總額 | D8: 0.4491 | G8: RMB 億 | H8: 1H2024 | I8: 智譜招股章程（概要節） | J8: https://www1.hkexnews.hk/listedco/listconews/sehk/2025/1230/2025123000018_c.pdf | K8: 2025-12-30 | L8: 2026-10-08 | M8: Verified | O8: 會計師報告（1H2024 比較期通常為未經審計已審閱；招股章程概要轉載） | P8: 1 | Q8: 利害關係方 | R8: 經審計或經審閱的公司公告（誘因：上市後股價、配售；數字可由公告原文核對） | S8: 一手 | T8: 原文「收入 57,409 100.0」；千元值 44,909；RMB 千元÷100,000 換算成億 | U8: =IF(AND($D8="",$E8="",$F8=""),1,0) -> 0 | V8: =IF(OR($I8="",$I8="—"),1,0) -> 0 | W8: =IF(AND(ISNUMBER($D8),ISNUMBER($E8)),IF($E8>$D8,1,0),0)+IF(AND(ISNUMBER($D8),ISNUMBER($F8)),IF($D8>$F8,1,0),0)+IF(AND(ISNUMBER($E8),ISNUMBER($F8)),IF($E8>$F8,1,0),0) -> 0 | X8: CC 初評
A9: SRC_ZP_005 | B9: rev_total_1h25 | C9: 營收總額 | D9: 1.9088 | G9: RMB 億 | H9: 1H2025 | I9: 智譜招股章程（概要節） | J9: https://www1.hkexnews.hk/listedco/listconews/sehk/2025/1230/2025123000018_c.pdf | K9: 2025-12-30 | L9: 2026-10-08 | M9: Verified | O9: 經審計（會計師報告，招股章程概要轉載） | P9: 1 | Q9: 利害關係方 | R9: 經審計或經審閱的公司公告（誘因：上市後股價、配售；數字可由公告原文核對） | S9: 一手 | T9: 原文「收入 57,409 100.0」；千元值 190,877；RMB 千元÷100,000 換算成億 | U9: =IF(AND($D9="",$E9="",$F9=""),1,0) -> 0 | V9: =IF(OR($I9="",$I9="—"),1,0) -> 0 | W9: =IF(AND(ISNUMBER($D9),ISNUMBER($E9)),IF($E9>$D9,1,0),0)+IF(AND(ISNUMBER($D9),ISNUMBER($F9)),IF($D9>$F9,1,0),0)+IF(AND(ISNUMBER($E9),ISNUMBER($F9)),IF($E9>$F9,1,0),0) -> 0 | X9: CC 初評
A10: SRC_ZP_006 | B10: rev_onprem_fy22 | C10: 本地化部署收入（舊分部） | D10: 0.5482 | G10: RMB 億 | H10: FY2022 | I10: 智譜招股章程（概要節） | J10: https://www1.hkexnews.hk/listedco/listconews/sehk/2025/1230/2025123000018_c.pdf | K10: 2025-12-30 | L10: 2026-10-08 | M10: Verified | O10: 經審計（會計師報告，招股章程概要轉載） | P10: 1 | Q10: 利害關係方 | R10: 經審計或經審閱的公司公告（誘因：上市後股價、配售；數字可由公告原文核對） | S10: 一手 | T10: 原文「本地化部署 54,815 95.5%」；千元值 54,815；RMB 千元÷100,000 換算成億；占比 95.5/90.4/84.5/59.7/84.8% | U10: =IF(AND($D10="",$E10="",$F10=""),1,0) -> 0 | V10: =IF(OR($I10="",$I10="—"),1,0) -> 0 | W10: =IF(AND(ISNUMBER($D10),ISNUMBER($E10)),IF($E10>$D10,1,0),0)+IF(AND(ISNUMBER($D10),ISNUMBER($F10)),IF($D10>$F10,1,0),0)+IF(AND(ISNUMBER($E10),ISNUMBER($F10)),IF($E10>$F10,1,0),0) -> 0 | X10: CC 初評
A11: SRC_ZP_007 | B11: rev_onprem_fy23 | C11: 本地化部署收入（舊分部） | D11: 1.1261 | G11: RMB 億 | H11: FY2023 | I11: 智譜招股章程（概要節） | J11: https://www1.hkexnews.hk/listedco/listconews/sehk/2025/1230/2025123000018_c.pdf | K11: 2025-12-30 | L11: 2026-10-08 | M11: Verified | O11: 經審計（會計師報告，招股章程概要轉載） | P11: 1 | Q11: 利害關係方 | R11: 經審計或經審閱的公司公告（誘因：上市後股價、配售；數字可由公告原文核對） | S11: 一手 | T11: 原文「本地化部署 54,815 95.5%」；千元值 112,614；RMB 千元÷100,000 換算成億；占比 95.5/90.4/84.5/59.7/84.8% | U11: =IF(AND($D11="",$E11="",$F11=""),1,0) -> 0 | V11: =IF(OR($I11="",$I11="—"),1,0) -> 0 | W11: =IF(AND(ISNUMBER($D11),ISNUMBER($E11)),IF($E11>$D11,1,0),0)+IF(AND(ISNUMBER($D11),ISNUMBER($F11)),IF($D11>$F11,1,0),0)+IF(AND(ISNUMBER($E11),ISNUMBER($F11)),IF($E11>$F11,1,0),0) -> 0 | X11: CC 初評
A12: SRC_ZP_008 | B12: rev_onprem_fy24 | C12: 本地化部署收入（舊分部） | D12: 2.6393 | G12: RMB 億 | H12: FY2024 | I12: 智譜招股章程（概要節） | J12: https://www1.hkexnews.hk/listedco/listconews/sehk/2025/1230/2025123000018_c.pdf | K12: 2025-12-30 | L12: 2026-10-08 | M12: Verified | O12: 經審計（會計師報告，招股章程概要轉載） | P12: 1 | Q12: 利害關係方 | R12: 經審計或經審閱的公司公告（誘因：上市後股價、配售；數字可由公告原文核對） | S12: 一手 | T12: 原文「本地化部署 54,815 95.5%」；千元值 263,930；RMB 千元÷100,000 換算成億；占比 95.5/90.4/84.5/59.7/84.8% | U12: =IF(AND($D12="",$E12="",$F12=""),1,0) -> 0 | V12: =IF(OR($I12="",$I12="—"),1,0) -> 0 | W12: =IF(AND(ISNUMBER($D12),ISNUMBER($E12)),IF($E12>$D12,1,0),0)+IF(AND(ISNUMBER($D12),ISNUMBER($F12)),IF($D12>$F12,1,0),0)+IF(AND(ISNUMBER($E12),ISNUMBER($F12)),IF($E12>$F12,1,0),0) -> 0 | X12: CC 初評
A13: SRC_ZP_009 | B13: rev_onprem_1h24 | C13: 本地化部署收入（舊分部） | D13: 0.2681 | G13: RMB 億 | H13: 1H2024 | I13: 智譜招股章程（概要節） | J13: https://www1.hkexnews.hk/listedco/listconews/sehk/2025/1230/2025123000018_c.pdf | K13: 2025-12-30 | L13: 2026-10-08 | M13: Verified | O13: 會計師報告（1H2024 比較期通常為未經審計已審閱；招股章程概要轉載） | P13: 1 | Q13: 利害關係方 | R13: 經審計或經審閱的公司公告（誘因：上市後股價、配售；數字可由公告原文核對） | S13: 一手 | T13: 原文「本地化部署 54,815 95.5%」；千元值 26,806；RMB 千元÷100,000 換算成億；占比 95.5/90.4/84.5/59.7/84.8% | U13: =IF(AND($D13="",$E13="",$F13=""),1,0) -> 0 | V13: =IF(OR($I13="",$I13="—"),1,0) -> 0 | W13: =IF(AND(ISNUMBER($D13),ISNUMBER($E13)),IF($E13>$D13,1,0),0)+IF(AND(ISNUMBER($D13),ISNUMBER($F13)),IF($D13>$F13,1,0),0)+IF(AND(ISNUMBER($E13),ISNUMBER($F13)),IF($E13>$F13,1,0),0) -> 0 | X13: CC 初評
A14: SRC_ZP_010 | B14: rev_onprem_1h25 | C14: 本地化部署收入（舊分部） | D14: 1.6178 | G14: RMB 億 | H14: 1H2025 | I14: 智譜招股章程（概要節） | J14: https://www1.hkexnews.hk/listedco/listconews/sehk/2025/1230/2025123000018_c.pdf | K14: 2025-12-30 | L14: 2026-10-08 | M14: Verified | O14: 經審計（會計師報告，招股章程概要轉載） | P14: 1 | Q14: 利害關係方 | R14: 經審計或經審閱的公司公告（誘因：上市後股價、配售；數字可由公告原文核對） | S14: 一手 | T14: 原文「本地化部署 54,815 95.5%」；千元值 161,777；RMB 千元÷100,000 換算成億；占比 95.5/90.4/84.5/59.7/84.8% | U14: =IF(AND($D14="",$E14="",$F14=""),1,0) -> 0 | V14: =IF(OR($I14="",$I14="—"),1,0) -> 0 | W14: =IF(AND(ISNUMBER($D14),ISNUMBER($E14)),IF($E14>$D14,1,0),0)+IF(AND(ISNUMBER($D14),ISNUMBER($F14)),IF($D14>$F14,1,0),0)+IF(AND(ISNUMBER($E14),ISNUMBER($F14)),IF($E14>$F14,1,0),0) -> 0 | X14: CC 初評
A15: SRC_ZP_011 | B15: rev_cloud_fy22 | C15: 雲端部署收入（舊分部；＝開放平台及API） | D15: 0.0259 | G15: RMB 億 | H15: FY2022 | I15: 智譜招股章程（概要節） | J15: https://www1.hkexnews.hk/listedco/listconews/sehk/2025/1230/2025123000018_c.pdf | K15: 2025-12-30 | L15: 2026-10-08 | M15: Verified | O15: 經審計（會計師報告，招股章程概要轉載） | P15: 1 | Q15: 利害關係方 | R15: 經審計或經審閱的公司公告（誘因：上市後股價、配售；數字可由公告原文核對） | S15: 一手 | T15: 原文「雲端部署 2,594 4.5%」；千元值 2,594；RMB 千元÷100,000 換算成億；占比 4.5/9.6/15.5/40.3/15.2%；2025 起新分類下雲端部署＝開放平台及 API | U15: =IF(AND($D15="",$E15="",$F15=""),1,0) -> 0 | V15: =IF(OR($I15="",$I15="—"),1,0) -> 0 | W15: =IF(AND(ISNUMBER($D15),ISNUMBER($E15)),IF($E15>$D15,1,0),0)+IF(AND(ISNUMBER($D15),ISNUMBER($F15)),IF($D15>$F15,1,0),0)+IF(AND(ISNUMBER($E15),ISNUMBER($F15)),IF($E15>$F15,1,0),0) -> 0 | X15: CC 初評
A16: SRC_ZP_012 | B16: rev_cloud_fy23 | C16: 雲端部署收入（舊分部；＝開放平台及API） | D16: 0.1192 | G16: RMB 億 | H16: FY2023 | I16: 智譜招股章程（概要節） | J16: https://www1.hkexnews.hk/listedco/listconews/sehk/2025/1230/2025123000018_c.pdf | K16: 2025-12-30 | L16: 2026-10-08 | M16: Verified | O16: 經審計（會計師報告，招股章程概要轉載） | P16: 1 | Q16: 利害關係方 | R16: 經審計或經審閱的公司公告（誘因：上市後股價、配售；數字可由公告原文核對） | S16: 一手 | T16: 原文「雲端部署 2,594 4.5%」；千元值 11,924；RMB 千元÷100,000 換算成億；占比 4.5/9.6/15.5/40.3/15.2%；2025 起新分類下雲端部署＝開放平台及 API | U16: =IF(AND($D16="",$E16="",$F16=""),1,0) -> 0 | V16: =IF(OR($I16="",$I16="—"),1,0) -> 0 | W16: =IF(AND(ISNUMBER($D16),ISNUMBER($E16)),IF($E16>$D16,1,0),0)+IF(AND(ISNUMBER($D16),ISNUMBER($F16)),IF($D16>$F16,1,0),0)+IF(AND(ISNUMBER($E16),ISNUMBER($F16)),IF($E16>$F16,1,0),0) -> 0 | X16: CC 初評
... A109: SRC_ZP_105 | B109: gm_total_1h25 | C109: 整體毛利率 | D109: 50 | G109: % | H109: 1H2025 | I109: 智譜招股章程（概要節） | J109: https://www1.hkexnews.hk/listedco/listconews/sehk/2025/1230/2025123000018_c.pdf | K109: 2025-12-30 | L109: 2026-10-08 | M109: Verified | O109: 經審計（會計師報告，招股章程概要轉載） | P109: 1 | Q109: 利害關係方 | R109: 經審計或經審閱的公司公告（誘因：上市後股價、配售；數字可由公告原文核對） | S109: 一手 | T109: 原文「毛利 31,360 54.6」表內毛利率欄 | U109: =IF(AND($D109="",$E109="",$F109=""),1,0) -> 0 | V109: =IF(OR($I109="",$I109="—"),1,0) -> 0 | W109: =IF(AND(ISNUMBER($D109),ISNUMBER($E109)),IF($E109>$D109,1,0),0)+IF(AND(ISNUMBER($D109),ISNUMBER($F109)),IF($D109>$F109,1,0),0)+IF(AND(ISNUMBER($E109),ISNUMBER($F109)),IF($E109>$F109,1,0),0) -> 0 | X109: CC 初評
A110: SRC_ZP_106 | B110: cash_burn_m_fy22 | C110: 平均每月現金消耗率 | D110: 0.03 | G110: RMB 億／月 | H110: FY2022 | I110: 智譜招股章程（概要節） | J110: https://www1.hkexnews.hk/listedco/listconews/sehk/2025/1230/2025123000017.pdf | K110: 2025-12-30 | L110: 2026-10-08 | M110: Interested-party | N110: 智譜：IPO 招股，誘因為發行定價 | O110: 管理層口徑（招股章程） | P110: 1 | Q110: 利害關係方 | R110: 智譜：IPO 招股，誘因為發行定價 | S110: 一手 | T110: 原文 average monthly cash burn RMB3.0 million；含經營現金流、購置設備、理財淨額、租賃付款；百萬÷100 換算成億 | U110: =IF(AND($D110="",$E110="",$F110=""),1,0) -> 0 | V110: =IF(OR($I110="",$I110="—"),1,0) -> 0 | W110: =IF(AND(ISNUMBER($D110),ISNUMBER($E110)),IF($E110>$D110,1,0),0)+IF(AND(ISNUMBER($D110),ISNUMBER($F110)),IF($D110>$F110,1,0),0)+IF(AND(ISNUMBER($E110),ISNUMBER($F110)),IF($E110>$F110,1,0),0) -> 0 | X110: CC 初評
A111: SRC_ZP_107 | B111: cash_burn_m_fy23 | C111: 平均每月現金消耗率 | D111: 1.059 | G111: RMB 億／月 | H111: FY2023 | I111: 智譜招股章程（概要節） | J111: https://www1.hkexnews.hk/listedco/listconews/sehk/2025/1230/2025123000017.pdf | K111: 2025-12-30 | L111: 2026-10-08 | M111: Interested-party | N111: 智譜：IPO 招股，誘因為發行定價 | O111: 管理層口徑（招股章程） | P111: 1 | Q111: 利害關係方 | R111: 智譜：IPO 招股，誘因為發行定價 | S111: 一手 | T111: 原文 average monthly cash burn RMB105.9 million；含經營現金流、購置設備、理財淨額、租賃付款；百萬÷100 換算成億 | U111: =IF(AND($D111="",$E111="",$F111=""),1,0) -> 0 | V111: =IF(OR($I111="",$I111="—"),1,0) -> 0 | W111: =IF(AND(ISNUMBER($D111),ISNUMBER($E111)),IF($E111>$D111,1,0),0)+IF(AND(ISNUMBER($D111),ISNUMBER($F111)),IF($D111>$F111,1,0),0)+IF(AND(ISNUMBER($E111),ISNUMBER($F111)),IF($E111>$F111,1,0),0) -> 0 | X111: CC 初評
A112: SRC_ZP_108 | B112: cash_burn_m_fy24 | C112: 平均每月現金消耗率 | D112: 1.945 | G112: RMB 億／月 | H112: FY2024 | I112: 智譜招股章程（概要節） | J112: https://www1.hkexnews.hk/listedco/listconews/sehk/2025/1230/2025123000017.pdf | K112: 2025-12-30 | L112: 2026-10-08 | M112: Interested-party | N112: 智譜：IPO 招股，誘因為發行定價 | O112: 管理層口徑（招股章程） | P112: 1 | Q112: 利害關係方 | R112: 智譜：IPO 招股，誘因為發行定價 | S112: 一手 | T112: 原文 average monthly cash burn RMB194.5 million；含經營現金流、購置設備、理財淨額、租賃付款；百萬÷100 換算成億 | U112: =IF(AND($D112="",$E112="",$F112=""),1,0) -> 0 | V112: =IF(OR($I112="",$I112="—"),1,0) -> 0 | W112: =IF(AND(ISNUMBER($D112),ISNUMBER($E112)),IF($E112>$D112,1,0),0)+IF(AND(ISNUMBER($D112),ISNUMBER($F112)),IF($D112>$F112,1,0),0)+IF(AND(ISNUMBER($E112),ISNUMBER($F112)),IF($E112>$F112,1,0),0) -> 0 | X112: CC 初評
A113: SRC_ZP_109 | B113: cash_burn_m_1h25 | C113: 平均每月現金消耗率 | D113: 3.273 | G113: RMB 億／月 | H113: 1H2025 | I113: 智譜招股章程（概要節） | J113: https://www1.hkexnews.hk/listedco/listconews/sehk/2025/1230/2025123000017.pdf | K113: 2025-12-30 | L113: 2026-10-08 | M113: Interested-party | N113: 智譜：IPO 招股，誘因為發行定價 | O113: 管理層口徑（招股章程） | P113: 1 | Q113: 利害關係方 | R113: 智譜：IPO 招股，誘因為發行定價 | S113: 一手 | T113: 原文 average monthly cash burn RMB327.3 million；含經營現金流、購置設備、理財淨額、租賃付款；百萬÷100 換算成億 | U113: =IF(AND($D113="",$E113="",$F113=""),1,0) -> 0 | V113: =IF(OR($I113="",$I113="—"),1,0) -> 0 | W113: =IF(AND(ISNUMBER($D113),ISNUMBER($E113)),IF($E113>$D113,1,0),0)+IF(AND(ISNUMBER($D113),ISNUMBER($F113)),IF($D113>$F113,1,0),0)+IF(AND(ISNUMBER($E113),ISNUMBER($F113)),IF($E113>$F113,1,0),0) -> 0 | X113: CC 初評
A114: SRC_ZP_110 | B114: liquidity_2510 | C114: 現金＋FVPL 短期投資＋可用承諾銀行授信合計 | D114: 89.431 | G114: RMB 億 | H114: 2025-10-31 | I114: 智譜招股章程（概要節） | J114: https://www1.hkexnews.hk/listedco/listconews/sehk/2025/1230/2025123000017.pdf | K114: 2025-12-30 | L114: 2026-10-08 | M114: Interested-party | N114: 智譜：IPO 招股，營運資金說明 | O114: 管理層口徑（招股章程營運資金充足性） | P114: 1 | Q114: 利害關係方 | R114: 智譜：IPO 招股，營運資金說明 | S114: 一手 | T114: 原文「available committed bank facilities of RMB8,943.1 million in aggregate」；三項合計，未拆授信額 | U114: =IF(AND($D114="",$E114="",$F114=""),1,0) -> 0 | V114: =IF(OR($I114="",$I114="—"),1,0) -> 0 | W114: =IF(AND(ISNUMBER($D114),ISNUMBER($E114)),IF($E114>$D114,1,0),0)+IF(AND(ISNUMBER($D114),ISNUMBER($F114)),IF($D114>$F114,1,0),0)+IF(AND(ISNUMBER($E114),ISNUMBER($F114)),IF($E114>$F114,1,0),0) -> 0 | X114: CC 初評
A115: SRC_ZP_111 | B115: rd_staff_1h25 | C115: 研發團隊人數 | D115: 657 | G115: 人 | H115: 2025-06-30 | I115: 智譜招股章程（概要節） | J115: https://www1.hkexnews.hk/listedco/listconews/sehk/2025/1230/2025123000018_c.pdf | K115: 2025-12-30 | L115: 2026-10-08 | M115: Verified | O115: 管理層口徑 | P115: 1 | Q115: 利害關係方 | R115: 經審計或經審閱的公司公告（誘因：上市後股價、配售；數字可由公告原文核對） | S115: 一手 | T115: 原文「一支由657名成員組成的研發團隊」 | U115: =IF(AND($D115="",$E115="",$F115=""),1,0) -> 0 | V115: =IF(OR($I115="",$I115="—"),1,0) -> 0 | W115: =IF(AND(ISNUMBER($D115),ISNUMBER($E115)),IF($E115>$D115,1,0),0)+IF(AND(ISNUMBER($D115),ISNUMBER($F115)),IF($D115>$F115,1,0),0)+IF(AND(ISNUMBER($E115),ISNUMBER($F115)),IF($E115>$F115,1,0),0) -> 0 | X115: CC 初評
A116: SRC_ZP_112 | B116: rev_api_fy25 | C116: 開放平台及 API 收入（新分類） | D116: 1.9038 | G116: RMB 億 | H116: FY2025 | I116: 智譜 2025 年度業績公告 | J116: https://www1.hkexnews.hk/listedco/listconews/sehk/2026/0331/2026033101549.pdf | K116: 2026-03-31 | L116: 2026-10-08 | M116: Verified | O116: 經審計（KPMG；年度業績公告） | P116: 1 | Q116: 利害關係方 | R116: 經審計或經審閱的公司公告（誘因：上市後股價、配售；數字可由公告原文核對） | S116: 一手 | T116: 原文「Open Platform and API」；千元值 190,379；RMB 千元÷100,000 換算成億；2025 占營收 26.3%；新分類下＝雲端部署 | U116: =IF(AND($D116="",$E116="",$F116=""),1,0) -> 0 | V116: =IF(OR($I116="",$I116="—"),1,0) -> 0 | W116: =IF(AND(ISNUMBER($D116),ISNUMBER($E116)),IF($E116>$D116,1,0),0)+IF(AND(ISNUMBER($D116),ISNUMBER($F116)),IF($D116>$F116,1,0),0)+IF(AND(ISNUMBER($E116),ISNUMBER($F116)),IF($E116>$F116,1,0),0) -> 0 | X116: CC 初評
A117: SRC_ZP_113 | B117: rev_api_fy24 | C117: 開放平台及 API 收入（新分類） | D117: 0.4848 | G117: RMB 億 | H117: FY2024 | I117: 智譜 2025 年度業績公告 | J117: https://www1.hkexnews.hk/listedco/listconews/sehk/2026/0331/2026033101549.pdf | K117: 2026-03-31 | L117: 2026-10-08 | M117: Verified | O117: 經審計（KPMG；年度業績公告） | P117: 1 | Q117: 利害關係方 | R117: 經審計或經審閱的公司公告（誘因：上市後股價、配售；數字可由公告原文核對） | S117: 一手 | T117: 原文「Open Platform and API」；千元值 48,484；RMB 千元÷100,000 換算成億；2025 占營收 26.3%；新分類下＝雲端部署 | U117: =IF(AND($D117="",$E117="",$F117=""),1,0) -> 0 | V117: =IF(OR($I117="",$I117="—"),1,0) -> 0 | W117: =IF(AND(ISNUMBER($D117),ISNUMBER($E117)),IF($E117>$D117,1,0),0)+IF(AND(ISNUMBER($D117),ISNUMBER($F117)),IF($D117>$F117,1,0),0)+IF(AND(ISNUMBER($E117),ISNUMBER($F117)),IF($E117>$F117,1,0),0) -> 0 | X117: CC 初評
A118: SRC_ZP_114 | B118: rev_agent_fy25 | C118: 企業級智能體收入（新分類） | D118: 1.6569 | G118: RMB 億 | H118: FY2025 | I118: 智譜 2025 年度業績公告 | J118: https://www1.hkexnews.hk/listedco/listconews/sehk/2026/0331/2026033101549.pdf | K118: 2026-03-31 | L118: 2026-10-08 | M118: Verified | O118: 經審計（KPMG；年度業績公告） | P118: 1 | Q118: 利害關係方 | R118: 經審計或經審閱的公司公告（誘因：上市後股價、配售；數字可由公告原文核對） | S118: 一手 | T118: 原文「Enterprise-level Agents」；千元值 165,687；RMB 千元÷100,000 換算成億；屬本地化部署分部 | U118: =IF(AND($D118="",$E118="",$F118=""),1,0) -> 0 | V118: =IF(OR($I118="",$I118="—"),1,0) -> 0 | W118: =IF(AND(ISNUMBER($D118),ISNUMBER($E118)),IF($E118>$D118,1,0),0)+IF(AND(ISNUMBER($D118),ISNUMBER($F118)),IF($D118>$F118,1,0),0)+IF(AND(ISNUMBER($E118),ISNUMBER($F118)),IF($E118>$F118,1,0),0) -> 0 | X118: CC 初評
A119: SRC_ZP_115 | B119: rev_agent_fy24 | C119: 企業級智能體收入（新分類） | D119: 0.4749 | G119: RMB 億 | H119: FY2024 | I119: 智譜 2025 年度業績公告 | J119: https://www1.hkexnews.hk/listedco/listconews/sehk/2026/0331/2026033101549.pdf | K119: 2026-03-31 | L119: 2026-10-08 | M119: Verified | O119: 經審計（KPMG；年度業績公告） | P119: 1 | Q119: 利害關係方 | R119: 經審計或經審閱的公司公告（誘因：上市後股價、配售；數字可由公告原文核對） | S119: 一手 | T119: 原文「Enterprise-level Agents」；千元值 47,492；RMB 千元÷100,000 換算成億；屬本地化部署分部 | U119: =IF(AND($D119="",$E119="",$F119=""),1,0) -> 0 | V119: =IF(OR($I119="",$I119="—"),1,0) -> 0 | W119: =IF(AND(ISNUMBER($D119),ISNUMBER($E119)),IF($E119>$D119,1,0),0)+IF(AND(ISNUMBER($D119),ISNUMBER($F119)),IF($D119>$F119,1,0),0)+IF(AND(ISNUMBER($E119),ISNUMBER($F119)),IF($E119>$F119,1,0),0) -> 0 | X119: CC 初評
A120: SRC_ZP_116 | B120: rev_gpllm_fy25 | C120: 企業級通用大模型收入（新分類） | D120: 3.6572 | G120: RMB 億 | H120: FY2025 | I120: 智譜 2025 年度業績公告 | J120: https://www1.hkexnews.hk/listedco/listconews/sehk/2026/0331/2026033101549.pdf | K120: 2026-03-31 | L120: 2026-10-08 | M120: Verified | O120: 經審計（KPMG；年度業績公告） | P120: 1 | Q120: 利害關係方 | R120: 經審計或經審閱的公司公告（誘因：上市後股價、配售；數字可由公告原文核對） | S120: 一手 | T120: 原文「Enterprise-level General-purpose Large Models」；千元值 365,724；RMB 千元÷100,000 換算成億；屬本地化部署分部 | U120: =IF(AND($D120="",$E120="",$F120=""),1,0) -> 0 | V120: =IF(OR($I120="",$I120="—"),1,0) -> 0 | W120: =IF(AND(ISNUMBER($D120),ISNUMBER($E120)),IF($E120>$D120,1,0),0)+IF(AND(ISNUMBER($D120),ISNUMBER($F120)),IF($D120>$F120,1,0),0)+IF(AND(ISNUMBER($E120),ISNUMBER($F120)),IF($E120>$F120,1,0),0) -> 0 | X120: CC 初評
A121: SRC_ZP_117 | B121: rev_gpllm_fy24 | C121: 企業級通用大模型收入（新分類） | D121: 2.145 | G121: RMB 億 | H121: FY2024 | I121: 智譜 2025 年度業績公告 | J121: https://www1.hkexnews.hk/listedco/listconews/sehk/2026/0331/2026033101549.pdf | K121: 2026-03-31 | L121: 2026-10-08 | M121: Verified | O121: 經審計（KPMG；年度業績公告） | P121: 1 | Q121: 利害關係方 | R121: 經審計或經審閱的公司公告（誘因：上市後股價、配售；數字可由公告原文核對） | S121: 一手 | T121: 原文「Enterprise-level General-purpose Large Models」；千元值 214,502；RMB 千元÷100,000 換算成億；屬本地化部署分部 | U121: =IF(AND($D121="",$E121="",$F121=""),1,0) -> 0 | V121: =IF(OR($I121="",$I121="—"),1,0) -> 0 | W121: =IF(AND(ISNUMBER($D121),ISNUMBER($E121)),IF($E121>$D121,1,0),0)+IF(AND(ISNUMBER($D121),ISNUMBER($F121)),IF($D121>$F121,1,0),0)+IF(AND(ISNUMBER($E121),ISNUMBER($F121)),IF($E121>$F121,1,0),0) -> 0 | X121: CC 初評
A122: SRC_ZP_118 | B122: rev_techsvc_fy25 | C122: 技術服務及其他收入（新分類） | D122: 0.0254 | G122: RMB 億 | H122: FY2025 | I122: 智譜 2025 年度業績公告 | J122: https://www1.hkexnews.hk/listedco/listconews/sehk/2026/0331/2026033101549.pdf | K122: 2026-03-31 | L122: 2026-10-08 | M122: Verified | O122: 經審計（KPMG；年度業績公告） | P122: 1 | Q122: 利害關係方 | R122: 經審計或經審閱的公司公告（誘因：上市後股價、配售；數字可由公告原文核對） | S122: 一手 | T122: 原文「Technical Services and Others」；千元值 2,544；RMB 千元÷100,000 換算成億 | U122: =IF(AND($D122="",$E122="",$F122=""),1,0) -> 0 | V122: =IF(OR($I122="",$I122="—"),1,0) -> 0 | W122: =IF(AND(ISNUMBER($D122),ISNUMBER($E122)),IF($E122>$D122,1,0),0)+IF(AND(ISNUMBER($D122),ISNUMBER($F122)),IF($D122>$F122,1,0),0)+IF(AND(ISNUMBER($E122),ISNUMBER($F122)),IF($E122>$F122,1,0),0) -> 0 | X122: CC 初評
A123: SRC_ZP_119 | B123: rev_techsvc_fy24 | C123: 技術服務及其他收入（新分類） | D123: 0.0194 | G123: RMB 億 | H123: FY2024 | I123: 智譜 2025 年度業績公告 | J123: https://www1.hkexnews.hk/listedco/listconews/sehk/2026/0331/2026033101549.pdf | K123: 2026-03-31 | L123: 2026-10-08 | M123: Verified | O123: 經審計（KPMG；年度業績公告） | P123: 1 | Q123: 利害關係方 | R123: 經審計或經審閱的公司公告（誘因：上市後股價、配售；數字可由公告原文核對） | S123: 一手 | T123: 原文「Technical Services and Others」；千元值 1,936；RMB 千元÷100,000 換算成億 | U123: =IF(AND($D123="",$E123="",$F123=""),1,0) -> 0 | V123: =IF(OR($I123="",$I123="—"),1,0) -> 0 | W123: =IF(AND(ISNUMBER($D123),ISNUMBER($E123)),IF($E123>$D123,1,0),0)+IF(AND(ISNUMBER($D123),ISNUMBER($F123)),IF($D123>$F123,1,0),0)+IF(AND(ISNUMBER($E123),ISNUMBER($F123)),IF($E123>$F123,1,0),0) -> 0 | X123: CC 初評
A124: SRC_ZP_120 | B124: rev_total_fy25 | C124: 營收總額 | D124: 7.2433 | G124: RMB 億 | H124: FY2025 | I124: 智譜 2025 年度業績公告 | J124: https://www1.hkexnews.hk/listedco/listconews/sehk/2026/0331/2026033101549.pdf | K124: 2026-03-31 | L124: 2026-10-08 | M124: Verified | O124: 經審計（KPMG；年度業績公告） | P124: 1 | Q124: 利害關係方 | R124: 經審計或經審閱的公司公告（誘因：上市後股價、配售；數字可由公告原文核對） | S124: 一手 | T124: 原文「total revenue reached RMB724.3 million」，同比 +131.9%；千元 724,334；RMB 千元÷100,000 換算成億 | U124: =IF(AND($D124="",$E124="",$F124=""),1,0) -> 0 | V124: =IF(OR($I124="",$I124="—"),1,0) -> 0 | W124: =IF(AND(ISNUMBER($D124),ISNUMBER($E124)),IF($E124>$D124,1,0),0)+IF(AND(ISNUMBER($D124),ISNUMBER($F124)),IF($D124>$F124,1,0),0)+IF(AND(ISNUMBER($E124),ISNUMBER($F124)),IF($E124>$F124,1,0),0) -> 0 | X124: CC 初評
A125: SRC_ZP_121 | B125: rev_onprem_fy25 | C125: 本地化部署收入（分部） | D125: 5.3396 | G125: RMB 億 | H125: FY2025 | I125: 智譜 2025 年度業績公告 | J125: https://www1.hkexnews.hk/listedco/listconews/sehk/2026/0331/2026033101549.pdf | K125: 2026-03-31 | L125: 2026-10-08 | M125: Verified | O125: 經審計（KPMG；年度業績公告） | P125: 1 | Q125: 利害關係方 | R125: 經審計或經審閱的公司公告（誘因：上市後股價、配售；數字可由公告原文核對） | S125: 一手 | T125: 分部附註 on-premise deployment 533,955 千元（＝智能體＋通用大模型＋技術服務）；RMB 千元÷100,000 換算成億 | U125: =IF(AND($D125="",$E125="",$F125=""),1,0) -> 0 | V125: =IF(OR($I125="",$I125="—"),1,0) -> 0 | W125: =IF(AND(ISNUMBER($D125),ISNUMBER($E125)),IF($E125>$D125,1,0),0)+IF(AND(ISNUMBER($D125),ISNUMBER($F125)),IF($D125>$F125,1,0),0)+IF(AND(ISNUMBER($E125),ISNUMBER($F125)),IF($E125>$F125,1,0),0) -> 0 | X125: CC 初評
A126: SRC_ZP_122 | B126: rev_cloud_fy25 | C126: 雲端部署收入（分部） | D126: 1.9038 | G126: RMB 億 | H126: FY2025 | I126: 智譜 2025 年度業績公告 | J126: https://www1.hkexnews.hk/listedco/listconews/sehk/2026/0331/2026033101549.pdf | K126: 2026-03-31 | L126: 2026-10-08 | M126: Verified | O126: 經審計（KPMG；年度業績公告） | P126: 1 | Q126: 利害關係方 | R126: 經審計或經審閱的公司公告（誘因：上市後股價、配售；數字可由公告原文核對） | S126: 一手 | T126: 分部附註 cloud-based deployment 190,379 千元＝開放平台及 API；RMB 千元÷100,000 換算成億 | U126: =IF(AND($D126="",$E126="",$F126=""),1,0) -> 0 | V126: =IF(OR($I126="",$I126="—"),1,0) -> 0 | W126: =IF(AND(ISNUMBER($D126),ISNUMBER($E126)),IF($E126>$D126,1,0),0)+IF(AND(ISNUMBER($D126),ISNUMBER($F126)),IF($D126>$F126,1,0),0)+IF(AND(ISNUMBER($E126),ISNUMBER($F126)),IF($E126>$F126,1,0),0) -> 0 | X126: CC 初評
... A168: SRC_ZP_164 | B168: comp_per_head_fy25 | C168: 人均薪酬（含股權報酬） | D168: 0.01246 | G168: RMB 億／人 | H168: FY2025 | I168: 智譜 2025 年度業績公告 | J168: https://www1.hkexnews.hk/listedco/listconews/sehk/2026/0331/2026033101549.pdf | K168: 2026-03-31 | L168: 2026-10-08 | M168: Derived | O168: Derived | P168: 2 | Q168: 推算 | R168: 由其他 SRC 列推算（見備註）；立場同其來源 | S168: 一手 | T168: 1,363.4 百萬÷期末人數 1,094＝約 RMB 124.6 萬／人；以期末人數計（無平均人數） | U168: =IF(AND($D168="",$E168="",$F168=""),1,0) -> 0 | V168: =IF(OR($I168="",$I168="—"),1,0) -> 0 | W168: =IF(AND(ISNUMBER($D168),ISNUMBER($E168)),IF($E168>$D168,1,0),0)+IF(AND(ISNUMBER($D168),ISNUMBER($F168)),IF($D168>$F168,1,0),0)+IF(AND(ISNUMBER($E168),ISNUMBER($F168)),IF($E168>$F168,1,0),0) -> 0 | X168: CC 初評
A169: SRC_ZP_165 | B169: esop_fy25 | C169: 員工激勵計畫 | H169: FY2025 | I169: 智譜 2025 年度業績公告 | J169: https://www1.hkexnews.hk/listedco/listconews/sehk/2026/0331/2026033101549.pdf | K169: 2026-03-31 | L169: 2026-10-08 | M169: Verified | O169: 經審計（KPMG；年度業績公告） | P169: 1 | Q169: 利害關係方 | R169: 經審計或經審閱的公司公告（誘因：上市後股價、配售；數字可由公告原文核對） | S169: 一手 | T169: 原文「adopted the employee incentive scheme and established an employee shareholding platform」；條款未揭露 | U169: =IF(AND($D169="",$E169="",$F169=""),1,0) -> 1 | V169: =IF(OR($I169="",$I169="—"),1,0) -> 0 | W169: =IF(AND(ISNUMBER($D169),ISNUMBER($E169)),IF($E169>$D169,1,0),0)+IF(AND(ISNUMBER($D169),ISNUMBER($F169)),IF($D169>$F169,1,0),0)+IF(AND(ISNUMBER($E169),ISNUMBER($F169)),IF($E169>$F169,1,0),0) -> 0 | X169: CC 初評
A170: SRC_ZP_166 | B170: api_price_fy25 | C170: API 呼叫價格較上年底上升 | D170: 83 | G170: % | H170: 2026Q1（公告時點） | I170: 智譜 2025 年度業績公告 | J170: https://www1.hkexnews.hk/listedco/listconews/sehk/2026/0331/2026033101549.pdf | K170: 2026-03-31 | L170: 2026-10-08 | M170: Interested-party | N170: 智譜：上市後股價、配售誘因 | O170: 管理層口徑 | P170: 1 | Q170: 利害關係方 | R170: 智譜：上市後股價、配售誘因 | S170: 一手 | T170: 原文「an 83% increase in API call pricing compared to the end of last year」 | U170: =IF(AND($D170="",$E170="",$F170=""),1,0) -> 0 | V170: =IF(OR($I170="",$I170="—"),1,0) -> 0 | W170: =IF(AND(ISNUMBER($D170),ISNUMBER($E170)),IF($E170>$D170,1,0),0)+IF(AND(ISNUMBER($D170),ISNUMBER($F170)),IF($D170>$F170,1,0),0)+IF(AND(ISNUMBER($E170),ISNUMBER($F170)),IF($E170>$F170,1,0),0) -> 0 | X170: CC 初評
A171: SRC_ZP_167 | B171: codingplan_class_fy25 | C171: GLM Coding Plan 收入歸屬 | H171: FY2025 | I171: 智譜 2025 年度業績公告 | J171: https://www1.hkexnews.hk/listedco/listconews/sehk/2026/0331/2026033101549.pdf | K171: 2026-03-31 | L171: 2026-10-08 | M171: Derived | O171: Derived | P171: 2 | Q171: 推算 | R171: 由其他 SRC 列推算（見備註）；立場同其來源 | S171: 一手 | T171: 公告於開放平台及 API 毛利段提及「programming subscription packages」；未單列收入。判定歸入開放平台及 API（雲端） | U171: =IF(AND($D171="",$E171="",$F171=""),1,0) -> 1 | V171: =IF(OR($I171="",$I171="—"),1,0) -> 0 | W171: =IF(AND(ISNUMBER($D171),ISNUMBER($E171)),IF($E171>$D171,1,0),0)+IF(AND(ISNUMBER($D171),ISNUMBER($F171)),IF($D171>$F171,1,0),0)+IF(AND(ISNUMBER($E171),ISNUMBER($F171)),IF($E171>$F171,1,0),0) -> 0 | X171: CC 初評
A172: SRC_ZP_168 | B172: codingplan_paying_fy25 | C172: Coding Plan 付費開發者 | D172: 242000 | E172: 242000 | G172: 人 | H172: FY2025 | I172: 智譜 2025 年度業績公告 | J172: https://www1.hkexnews.hk/listedco/listconews/sehk/2026/0331/2026033101549.pdf | K172: 2026-03-31 | L172: 2026-10-08 | M172: Interested-party | N172: 智譜：上市後股價、配售誘因 | O172: 管理層口徑 | P172: 1 | Q172: 利害關係方 | R172: 智譜：上市後股價、配售誘因 | S172: 一手 | T172: 原文 over 242,000 paying Coding Plan developers（下限值） | U172: =IF(AND($D172="",$E172="",$F172=""),1,0) -> 0 | V172: =IF(OR($I172="",$I172="—"),1,0) -> 0 | W172: =IF(AND(ISNUMBER($D172),ISNUMBER($E172)),IF($E172>$D172,1,0),0)+IF(AND(ISNUMBER($D172),ISNUMBER($F172)),IF($D172>$F172,1,0),0)+IF(AND(ISNUMBER($E172),ISNUMBER($F172)),IF($E172>$F172,1,0),0) -> 0 | X172: CC 初評
A173: SRC_ZP_169 | B173: rev_api_1h26 | C173: 開放平台及 API 收入 | D173: 8.2518 | G173: RMB 億 | H173: 1H2026 | I173: 智譜（Z.AI）2026 中期業績公告 | J173: https://www1.hkexnews.hk/listedco/listconews/sehk/2026/0831/2026083101539.pdf | K173: 2026-08-31 | L173: 2026-10-08 | M173: Verified | O173: 未經審計（中期業績公告；是否經核數師審閱公告未見明載） | P173: 1 | Q173: 利害關係方 | R173: 經審計或經審閱的公司公告（誘因：上市後股價、配售；數字可由公告原文核對） | S173: 一手 | T173: 原文「Open Platform and API」；千元值 825,176；RMB 千元÷100,000 換算成億；1H26 占 86.5%（1H25 15.2%）；＝雲端部署分部 | U173: =IF(AND($D173="",$E173="",$F173=""),1,0) -> 0 | V173: =IF(OR($I173="",$I173="—"),1,0) -> 0 | W173: =IF(AND(ISNUMBER($D173),ISNUMBER($E173)),IF($E173>$D173,1,0),0)+IF(AND(ISNUMBER($D173),ISNUMBER($F173)),IF($D173>$F173,1,0),0)+IF(AND(ISNUMBER($E173),ISNUMBER($F173)),IF($E173>$F173,1,0),0) -> 0 | X173: CC 初評
A174: SRC_ZP_170 | B174: rev_api_1h25 | C174: 開放平台及 API 收入 | D174: 0.291 | G174: RMB 億 | H174: 1H2025 | I174: 智譜（Z.AI）2026 中期業績公告 | J174: https://www1.hkexnews.hk/listedco/listconews/sehk/2026/0831/2026083101539.pdf | K174: 2026-08-31 | L174: 2026-10-08 | M174: Verified | O174: 未經審計（中期業績公告；是否經核數師審閱公告未見明載） | P174: 1 | Q174: 利害關係方 | R174: 經審計或經審閱的公司公告（誘因：上市後股價、配售；數字可由公告原文核對） | S174: 一手 | T174: 原文「Open Platform and API」；千元值 29,100；RMB 千元÷100,000 換算成億；1H26 占 86.5%（1H25 15.2%）；＝雲端部署分部 | U174: =IF(AND($D174="",$E174="",$F174=""),1,0) -> 0 | V174: =IF(OR($I174="",$I174="—"),1,0) -> 0 | W174: =IF(AND(ISNUMBER($D174),ISNUMBER($E174)),IF($E174>$D174,1,0),0)+IF(AND(ISNUMBER($D174),ISNUMBER($F174)),IF($D174>$F174,1,0),0)+IF(AND(ISNUMBER($E174),ISNUMBER($F174)),IF($E174>$F174,1,0),0) -> 0 | X174: CC 初評
A175: SRC_ZP_171 | B175: rev_agent_1h26 | C175: 企業級智能體收入 | D175: 0.5556 | G175: RMB 億 | H175: 1H2026 | I175: 智譜（Z.AI）2026 中期業績公告 | J175: https://www1.hkexnews.hk/listedco/listconews/sehk/2026/0831/2026083101539.pdf | K175: 2026-08-31 | L175: 2026-10-08 | M175: Verified | O175: 未經審計（中期業績公告；是否經核數師審閱公告未見明載） | P175: 1 | Q175: 利害關係方 | R175: 經審計或經審閱的公司公告（誘因：上市後股價、配售；數字可由公告原文核對） | S175: 一手 | T175: 原文「Enterprise-level Agents」；千元值 55,561；RMB 千元÷100,000 換算成億 | U175: =IF(AND($D175="",$E175="",$F175=""),1,0) -> 0 | V175: =IF(OR($I175="",$I175="—"),1,0) -> 0 | W175: =IF(AND(ISNUMBER($D175),ISNUMBER($E175)),IF($E175>$D175,1,0),0)+IF(AND(ISNUMBER($D175),ISNUMBER($F175)),IF($D175>$F175,1,0),0)+IF(AND(ISNUMBER($E175),ISNUMBER($F175)),IF($E175>$F175,1,0),0) -> 0 | X175: CC 初評
A176: SRC_ZP_172 | B176: rev_agent_1h25 | C176: 企業級智能體收入 | D176: 0.1374 | G176: RMB 億 | H176: 1H2025 | I176: 智譜（Z.AI）2026 中期業績公告 | J176: https://www1.hkexnews.hk/listedco/listconews/sehk/2026/0831/2026083101539.pdf | K176: 2026-08-31 | L176: 2026-10-08 | M176: Verified | O176: 未經審計（中期業績公告；是否經核數師審閱公告未見明載） | P176: 1 | Q176: 利害關係方 | R176: 經審計或經審閱的公司公告（誘因：上市後股價、配售；數字可由公告原文核對） | S176: 一手 | T176: 原文「Enterprise-level Agents」；千元值 13,739；RMB 千元÷100,000 換算成億 | U176: =IF(AND($D176="",$E176="",$F176=""),1,0) -> 0 | V176: =IF(OR($I176="",$I176="—"),1,0) -> 0 | W176: =IF(AND(ISNUMBER($D176),ISNUMBER($E176)),IF($E176>$D176,1,0),0)+IF(AND(ISNUMBER($D176),ISNUMBER($F176)),IF($D176>$F176,1,0),0)+IF(AND(ISNUMBER($E176),ISNUMBER($F176)),IF($E176>$F176,1,0),0) -> 0 | X176: CC 初評
A177: SRC_ZP_173 | B177: rev_gpllm_1h26 | C177: 企業級通用大模型收入 | D177: 0.6704 | G177: RMB 億 | H177: 1H2026 | I177: 智譜（Z.AI）2026 中期業績公告 | J177: https://www1.hkexnews.hk/listedco/listconews/sehk/2026/0831/2026083101539.pdf | K177: 2026-08-31 | L177: 2026-10-08 | M177: Verified | O177: 未經審計（中期業績公告；是否經核數師審閱公告未見明載） | P177: 1 | Q177: 利害關係方 | R177: 經審計或經審閱的公司公告（誘因：上市後股價、配售；數字可由公告原文核對） | S177: 一手 | T177: 原文「Enterprise-level General-purpose Large Models」；千元值 67,037；RMB 千元÷100,000 換算成億 | U177: =IF(AND($D177="",$E177="",$F177=""),1,0) -> 0 | V177: =IF(OR($I177="",$I177="—"),1,0) -> 0 | W177: =IF(AND(ISNUMBER($D177),ISNUMBER($E177)),IF($E177>$D177,1,0),0)+IF(AND(ISNUMBER($D177),ISNUMBER($F177)),IF($D177>$F177,1,0),0)+IF(AND(ISNUMBER($E177),ISNUMBER($F177)),IF($E177>$F177,1,0),0) -> 0 | X177: CC 初評
A178: SRC_ZP_174 | B178: rev_gpllm_1h25 | C178: 企業級通用大模型收入 | D178: 1.4755 | G178: RMB 億 | H178: 1H2025 | I178: 智譜（Z.AI）2026 中期業績公告 | J178: https://www1.hkexnews.hk/listedco/listconews/sehk/2026/0831/2026083101539.pdf | K178: 2026-08-31 | L178: 2026-10-08 | M178: Verified | O178: 未經審計（中期業績公告；是否經核數師審閱公告未見明載） | P178: 1 | Q178: 利害關係方 | R178: 經審計或經審閱的公司公告（誘因：上市後股價、配售；數字可由公告原文核對） | S178: 一手 | T178: 原文「Enterprise-level General-purpose Large Models」；千元值 147,555；RMB 千元÷100,000 換算成億 | U178: =IF(AND($D178="",$E178="",$F178=""),1,0) -> 0 | V178: =IF(OR($I178="",$I178="—"),1,0) -> 0 | W178: =IF(AND(ISNUMBER($D178),ISNUMBER($E178)),IF($E178>$D178,1,0),0)+IF(AND(ISNUMBER($D178),ISNUMBER($F178)),IF($D178>$F178,1,0),0)+IF(AND(ISNUMBER($E178),ISNUMBER($F178)),IF($E178>$F178,1,0),0) -> 0 | X178: CC 初評
A179: SRC_ZP_175 | B179: rev_techsvc_1h26 | C179: 技術服務及其他收入 | D179: 0.0612 | G179: RMB 億 | H179: 1H2026 | I179: 智譜（Z.AI）2026 中期業績公告 | J179: https://www1.hkexnews.hk/listedco/listconews/sehk/2026/0831/2026083101539.pdf | K179: 2026-08-31 | L179: 2026-10-08 | M179: Verified | O179: 未經審計（中期業績公告；是否經核數師審閱公告未見明載） | P179: 1 | Q179: 利害關係方 | R179: 經審計或經審閱的公司公告（誘因：上市後股價、配售；數字可由公告原文核對） | S179: 一手 | T179: 原文「Technical Services and Others」；千元值 6,118；RMB 千元÷100,000 換算成億 | U179: =IF(AND($D179="",$E179="",$F179=""),1,0) -> 0 | V179: =IF(OR($I179="",$I179="—"),1,0) -> 0 | W179: =IF(AND(ISNUMBER($D179),ISNUMBER($E179)),IF($E179>$D179,1,0),0)+IF(AND(ISNUMBER($D179),ISNUMBER($F179)),IF($D179>$F179,1,0),0)+IF(AND(ISNUMBER($E179),ISNUMBER($F179)),IF($E179>$F179,1,0),0) -> 0 | X179: CC 初評
A180: SRC_ZP_176 | B180: rev_techsvc_1h25 | C180: 技術服務及其他收入 | D180: 0.0048 | G180: RMB 億 | H180: 1H2025 | I180: 智譜（Z.AI）2026 中期業績公告 | J180: https://www1.hkexnews.hk/listedco/listconews/sehk/2026/0831/2026083101539.pdf | K180: 2026-08-31 | L180: 2026-10-08 | M180: Verified | O180: 未經審計（中期業績公告；是否經核數師審閱公告未見明載） | P180: 1 | Q180: 利害關係方 | R180: 經審計或經審閱的公司公告（誘因：上市後股價、配售；數字可由公告原文核對） | S180: 一手 | T180: 原文「Technical Services and Others」；千元值 483；RMB 千元÷100,000 換算成億 | U180: =IF(AND($D180="",$E180="",$F180=""),1,0) -> 0 | V180: =IF(OR($I180="",$I180="—"),1,0) -> 0 | W180: =IF(AND(ISNUMBER($D180),ISNUMBER($E180)),IF($E180>$D180,1,0),0)+IF(AND(ISNUMBER($D180),ISNUMBER($F180)),IF($D180>$F180,1,0),0)+IF(AND(ISNUMBER($E180),ISNUMBER($F180)),IF($E180>$F180,1,0),0) -> 0 | X180: CC 初評
A181: SRC_ZP_177 | B181: rev_total_1h26 | C181: 營收總額 | D181: 9.5389 | G181: RMB 億 | H181: 1H2026 | I181: 智譜（Z.AI）2026 中期業績公告 | J181: https://www1.hkexnews.hk/listedco/listconews/sehk/2026/0831/2026083101539.pdf | K181: 2026-08-31 | L181: 2026-10-08 | M181: Verified | O181: 未經審計（中期業績公告；是否經核數師審閱公告未見明載） | P181: 1 | Q181: 利害關係方 | R181: 經審計或經審閱的公司公告（誘因：上市後股價、配售；數字可由公告原文核對） | S181: 一手 | T181: 原文 revenue 953,892 千元（1H25 190,877），+399.7%；RMB 千元÷100,000 換算成億 | U181: =IF(AND($D181="",$E181="",$F181=""),1,0) -> 0 | V181: =IF(OR($I181="",$I181="—"),1,0) -> 0 | W181: =IF(AND(ISNUMBER($D181),ISNUMBER($E181)),IF($E181>$D181,1,0),0)+IF(AND(ISNUMBER($D181),ISNUMBER($F181)),IF($D181>$F181,1,0),0)+IF(AND(ISNUMBER($E181),ISNUMBER($F181)),IF($E181>$F181,1,0),0) -> 0 | X181: CC 初評
A182: SRC_ZP_178 | B182: rev_onprem_1h26 | C182: 本地化部署收入（分部） | D182: 1.2872 | G182: RMB 億 | H182: 1H2026 | I182: 智譜（Z.AI）2026 中期業績公告 | J182: https://ea-cdn.eurolandir.com/press-releases-attachments/4174939/HKEX-EPS_20260831_12308928_0.PDF | K182: 2026-08-31 | L182: 2026-10-08 | M182: Verified | O182: 未經審計（中期業績公告；是否經核數師審閱公告未見明載） | P182: 1 | Q182: 利害關係方 | R182: 經審計或經審閱的公司公告（誘因：上市後股價、配售；數字可由公告原文核對） | S182: 一手 | T182: on-premise deployment 128,716 千元（1H25 161,777），占 13.5%；RMB 千元÷100,000 換算成億 | U182: =IF(AND($D182="",$E182="",$F182=""),1,0) -> 0 | V182: =IF(OR($I182="",$I182="—"),1,0) -> 0 | W182: =IF(AND(ISNUMBER($D182),ISNUMBER($E182)),IF($E182>$D182,1,0),0)+IF(AND(ISNUMBER($D182),ISNUMBER($F182)),IF($D182>$F182,1,0),0)+IF(AND(ISNUMBER($E182),ISNUMBER($F182)),IF($E182>$F182,1,0),0) -> 0 | X182: CC 初評
A183: SRC_ZP_179 | B183: rev_cloud_1h26 | C183: 雲端部署收入（分部） | D183: 8.2518 | G183: RMB 億 | H183: 1H2026 | I183: 智譜（Z.AI）2026 中期業績公告 | J183: https://ea-cdn.eurolandir.com/press-releases-attachments/4174939/HKEX-EPS_20260831_12308928_0.PDF | K183: 2026-08-31 | L183: 2026-10-08 | M183: Verified | O183: 未經審計（中期業績公告；是否經核數師審閱公告未見明載） | P183: 1 | Q183: 利害關係方 | R183: 經審計或經審閱的公司公告（誘因：上市後股價、配售；數字可由公告原文核對） | S183: 一手 | T183: cloud-based deployment 825,176 千元＝開放平台及 API；RMB 千元÷100,000 換算成億 | U183: =IF(AND($D183="",$E183="",$F183=""),1,0) -> 0 | V183: =IF(OR($I183="",$I183="—"),1,0) -> 0 | W183: =IF(AND(ISNUMBER($D183),ISNUMBER($E183)),IF($E183>$D183,1,0),0)+IF(AND(ISNUMBER($D183),ISNUMBER($F183)),IF($D183>$F183,1,0),0)+IF(AND(ISNUMBER($E183),ISNUMBER($F183)),IF($E183>$F183,1,0),0) -> 0 | X183: CC 初評
A184: SRC_ZP_180 | B184: rev_onprem_1h26_b | C184: 本地化部署相關收入（媒體） | D184: 0.6704 | G184: RMB 億 | H184: 1H2026 | I184: 鉅亨號〈智譜上半年業績暴漲 造血能力驗證〉 | J184: https://hao.cnyes.com/post/265529 | K184: 2026-09-01 | L184: 2026-10-08 | M184: Interested-party | N184: 媒體（鉅亨號）轉述 | O184: 媒體轉述 | P184: 2 | Q184: 利害關係方 | R184: 媒體（鉅亨號）轉述 | S184: 二手 | T184: 原文「本地化部署相關收入6,704萬元」；與公告分部 1.287 億矛盾：媒體只計企業級通用大模型 | U184: =IF(AND($D184="",$E184="",$F184=""),1,0) -> 0 | V184: =IF(OR($I184="",$I184="—"),1,0) -> 0 | W184: =IF(AND(ISNUMBER($D184),ISNUMBER($E184)),IF($E184>$D184,1,0),0)+IF(AND(ISNUMBER($D184),ISNUMBER($F184)),IF($D184>$F184,1,0),0)+IF(AND(ISNUMBER($E184),ISNUMBER($F184)),IF($E184>$F184,1,0),0) -> 0 | X184: CC 初評
A185: SRC_ZP_181 | B185: rev_onprem_1h26_c | C185: 本地化部署收入（券商） | D185: 1.3 | G185: RMB 億 | H185: 1H2026 | I185: 國信證券〈26H1財報點評〉（格隆匯轉載） | J185: https://m.gelonghui.com/news/5306647 | K185: 2026-09-04 | L185: 2026-10-08 | M185: Interested-party | N185: 國信證券：券商研究，交易誘因 | O185: 券商口徑 | P185: 2 | Q185: 利害關係方 | R185: 國信證券：券商研究，交易誘因 | S185: 二手 | T185: 原文 本地化部署收入 1.30 億元、毛利率 37.9%；與公告 128,716 千元一致（四捨五入） | U185: =IF(AND($D185="",$E185="",$F185=""),1,0) -> 0 | V185: =IF(OR($I185="",$I185="—"),1,0) -> 0 | W185: =IF(AND(ISNUMBER($D185),ISNUMBER($E185)),IF($E185>$D185,1,0),0)+IF(AND(ISNUMBER($D185),ISNUMBER($F185)),IF($D185>$F185,1,0),0)+IF(AND(ISNUMBER($E185),ISNUMBER($F185)),IF($E185>$F185,1,0),0) -> 0 | X185: CC 初評
A186: SRC_ZP_182 | B186: cogs_1h26 | C186: 銷售成本 | D186: 7.0228 | G186: RMB 億 | H186: 1H2026 | I186: 智譜（Z.AI）2026 中期業績公告 | J186: https://www1.hkexnews.hk/listedco/listconews/sehk/2026/0831/2026083101539.pdf | K186: 2026-08-31 | L186: 2026-10-08 | M186: Verified | O186: 未經審計（中期業績公告；是否經核數師審閱公告未見明載） | P186: 1 | Q186: 利害關係方 | R186: 經審計或經審閱的公司公告（誘因：上市後股價、配售；數字可由公告原文核對） | S186: 一手 | T186: 原文「primarily attributable to the increase in computing service fees」；千元 702,281；算力服務費金額未揭露；RMB 千元÷100,000 換算成億 | U186: =IF(AND($D186="",$E186="",$F186=""),1,0) -> 0 | V186: =IF(OR($I186="",$I186="—"),1,0) -> 0 | W186: =IF(AND(ISNUMBER($D186),ISNUMBER($E186)),IF($E186>$D186,1,0),0)+IF(AND(ISNUMBER($D186),ISNUMBER($F186)),IF($D186>$F186,1,0),0)+IF(AND(ISNUMBER($E186),ISNUMBER($F186)),IF($E186>$F186,1,0),0) -> 0 | X186: CC 初評
A187: SRC_ZP_183 | B187: cogs_1h25_i | C187: 銷售成本（中期公告比較數） | D187: 0.9545 | G187: RMB 億 | H187: 1H2025 | I187: 智譜（Z.AI）2026 中期業績公告 | J187: https://www1.hkexnews.hk/listedco/listconews/sehk/2026/0831/2026083101539.pdf | K187: 2026-08-31 | L187: 2026-10-08 | M187: Verified | O187: 未經審計（中期業績公告；是否經核數師審閱公告未見明載） | P187: 1 | Q187: 利害關係方 | R187: 經審計或經審閱的公司公告（誘因：上市後股價、配售；數字可由公告原文核對） | S187: 一手 | T187: 千元 95,453，與招股章程一致；RMB 千元÷100,000 換算成億 | U187: =IF(AND($D187="",$E187="",$F187=""),1,0) -> 0 | V187: =IF(OR($I187="",$I187="—"),1,0) -> 0 | W187: =IF(AND(ISNUMBER($D187),ISNUMBER($E187)),IF($E187>$D187,1,0),0)+IF(AND(ISNUMBER($D187),ISNUMBER($F187)),IF($D187>$F187,1,0),0)+IF(AND(ISNUMBER($E187),ISNUMBER($F187)),IF($E187>$F187,1,0),0) -> 0 | X187: CC 初評
A188: SRC_ZP_184 | B188: gp_total_1h26 | C188: 毛利 | D188: 2.5161 | G188: RMB 億 | H188: 1H2026 | I188: 智譜（Z.AI）2026 中期業績公告 | J188: https://www1.hkexnews.hk/listedco/listconews/sehk/2026/0831/2026083101539.pdf | K188: 2026-08-31 | L188: 2026-10-08 | M188: Verified | O188: 未經審計（中期業績公告；是否經核數師審閱公告未見明載） | P188: 1 | Q188: 利害關係方 | R188: 經審計或經審閱的公司公告（誘因：上市後股價、配售；數字可由公告原文核對） | S188: 一手 | T188: gross profit 251,611 千元；毛利率 26.4%（1H25 50.0%）；RMB 千元÷100,000 換算成億 | U188: =IF(AND($D188="",$E188="",$F188=""),1,0) -> 0 | V188: =IF(OR($I188="",$I188="—"),1,0) -> 0 | W188: =IF(AND(ISNUMBER($D188),ISNUMBER($E188)),IF($E188>$D188,1,0),0)+IF(AND(ISNUMBER($D188),ISNUMBER($F188)),IF($D188>$F188,1,0),0)+IF(AND(ISNUMBER($E188),ISNUMBER($F188)),IF($E188>$F188,1,0),0) -> 0 | X188: CC 初評
A189: SRC_ZP_185 | B189: gm_total_1h26 | C189: 整體毛利率 | D189: 26.4 | G189: % | H189: 1H2026 | I189: 智譜（Z.AI）2026 中期業績公告 | J189: https://www1.hkexnews.hk/listedco/listconews/sehk/2026/0831/2026083101539.pdf | K189: 2026-08-31 | L189: 2026-10-08 | M189: Verified | O189: 未經審計（中期業績公告；是否經核數師審閱公告未見明載） | P189: 1 | Q189: 利害關係方 | R189: 經審計或經審閱的公司公告（誘因：上市後股價、配售；數字可由公告原文核對） | S189: 一手 | T189: 原文 gross margin 26.4%（1H25 50.0%） | U189: =IF(AND($D189="",$E189="",$F189=""),1,0) -> 0 | V189: =IF(OR($I189="",$I189="—"),1,0) -> 0 | W189: =IF(AND(ISNUMBER($D189),ISNUMBER($E189)),IF($E189>$D189,1,0),0)+IF(AND(ISNUMBER($D189),ISNUMBER($F189)),IF($D189>$F189,1,0),0)+IF(AND(ISNUMBER($E189),ISNUMBER($F189)),IF($E189>$F189,1,0),0) -> 0 | X189: CC 初評
A190: SRC_ZP_186 | B190: gp_api_1h26 | C190: 開放平台及 API 毛利 | D190: 2.0287 | G190: RMB 億 | H190: 1H2026 | I190: 智譜（Z.AI）2026 中期業績公告 | J190: https://ea-cdn.eurolandir.com/press-releases-attachments/4174939/HKEX-EPS_20260831_12308928_0.PDF | K190: 2026-08-31 | L190: 2026-10-08 | M190: Verified | O190: 未經審計（中期業績公告；是否經核數師審閱公告未見明載） | P190: 1 | Q190: 利害關係方 | R190: 經審計或經審閱的公司公告（誘因：上市後股價、配售；數字可由公告原文核對） | S190: 一手 | T190: 千元 202,871；毛利率 24.6%；RMB 千元÷100,000 換算成億 | U190: =IF(AND($D190="",$E190="",$F190=""),1,0) -> 0 | V190: =IF(OR($I190="",$I190="—"),1,0) -> 0 | W190: =IF(AND(ISNUMBER($D190),ISNUMBER($E190)),IF($E190>$D190,1,0),0)+IF(AND(ISNUMBER($D190),ISNUMBER($F190)),IF($D190>$F190,1,0),0)+IF(AND(ISNUMBER($E190),ISNUMBER($F190)),IF($E190>$F190,1,0),0) -> 0 | X190: CC 初評
A191: SRC_ZP_187 | B191: gp_api_1h25 | C191: 開放平台及 API 毛利 | D191: -0.0012 | G191: RMB 億 | H191: 1H2025 | I191: 智譜（Z.AI）2026 中期業績公告 | J191: https://ea-cdn.eurolandir.com/press-releases-attachments/4174939/HKEX-EPS_20260831_12308928_0.PDF | K191: 2026-08-31 | L191: 2026-10-08 | M191: Verified | O191: 未經審計（中期業績公告；是否經核數師審閱公告未見明載） | P191: 1 | Q191: 利害關係方 | R191: 經審計或經審閱的公司公告（誘因：上市後股價、配售；數字可由公告原文核對） | S191: 一手 | T191: 千元 -116；毛利率 -0.4%；RMB 千元÷100,000 換算成億 | U191: =IF(AND($D191="",$E191="",$F191=""),1,0) -> 0 | V191: =IF(OR($I191="",$I191="—"),1,0) -> 0 | W191: =IF(AND(ISNUMBER($D191),ISNUMBER($E191)),IF($E191>$D191,1,0),0)+IF(AND(ISNUMBER($D191),ISNUMBER($F191)),IF($D191>$F191,1,0),0)+IF(AND(ISNUMBER($E191),ISNUMBER($F191)),IF($E191>$F191,1,0),0) -> 0 | X191: CC 初評
A192: SRC_ZP_188 | B192: gp_agent_1h26 | C192: 企業級智能體毛利 | D192: 0.198 | G192: RMB 億 | H192: 1H2026 | I192: 智譜（Z.AI）2026 中期業績公告 | J192: https://ea-cdn.eurolandir.com/press-releases-attachments/4174939/HKEX-EPS_20260831_12308928_0.PDF | K192: 2026-08-31 | L192: 2026-10-08 | M192: Verified | O192: 未經審計（中期業績公告；是否經核數師審閱公告未見明載） | P192: 1 | Q192: 利害關係方 | R192: 經審計或經審閱的公司公告（誘因：上市後股價、配售；數字可由公告原文核對） | S192: 一手 | T192: 千元 19,796；毛利率 35.6%；RMB 千元÷100,000 換算成億 | U192: =IF(AND($D192="",$E192="",$F192=""),1,0) -> 0 | V192: =IF(OR($I192="",$I192="—"),1,0) -> 0 | W192: =IF(AND(ISNUMBER($D192),ISNUMBER($E192)),IF($E192>$D192,1,0),0)+IF(AND(ISNUMBER($D192),ISNUMBER($F192)),IF($D192>$F192,1,0),0)+IF(AND(ISNUMBER($E192),ISNUMBER($F192)),IF($E192>$F192,1,0),0) -> 0 | X192: CC 初評
A193: SRC_ZP_189 | B193: gp_agent_1h25 | C193: 企業級智能體毛利 | D193: 0.0888 | G193: RMB 億 | H193: 1H2025 | I193: 智譜（Z.AI）2026 中期業績公告 | J193: https://ea-cdn.eurolandir.com/press-releases-attachments/4174939/HKEX-EPS_20260831_12308928_0.PDF | K193: 2026-08-31 | L193: 2026-10-08 | M193: Verified | O193: 未經審計（中期業績公告；是否經核數師審閱公告未見明載） | P193: 1 | Q193: 利害關係方 | R193: 經審計或經審閱的公司公告（誘因：上市後股價、配售；數字可由公告原文核對） | S193: 一手 | T193: 千元 8,880；毛利率 64.6%；RMB 千元÷100,000 換算成億 | U193: =IF(AND($D193="",$E193="",$F193=""),1,0) -> 0 | V193: =IF(OR($I193="",$I193="—"),1,0) -> 0 | W193: =IF(AND(ISNUMBER($D193),ISNUMBER($E193)),IF($E193>$D193,1,0),0)+IF(AND(ISNUMBER($D193),ISNUMBER($F193)),IF($D193>$F193,1,0),0)+IF(AND(ISNUMBER($E193),ISNUMBER($F193)),IF($E193>$F193,1,0),0) -> 0 | X193: CC 初評
A194: SRC_ZP_190 | B194: gp_gpllm_1h26 | C194: 企業級通用大模型毛利 | D194: 0.2837 | G194: RMB 億 | H194: 1H2026 | I194: 智譜（Z.AI）2026 中期業績公告 | J194: https://ea-cdn.eurolandir.com/press-releases-attachments/4174939/HKEX-EPS_20260831_12308928_0.PDF | K194: 2026-08-31 | L194: 2026-10-08 | M194: Verified | O194: 未經審計（中期業績公告；是否經核數師審閱公告未見明載） | P194: 1 | Q194: 利害關係方 | R194: 經審計或經審閱的公司公告（誘因：上市後股價、配售；數字可由公告原文核對） | S194: 一手 | T194: 千元 28,368；毛利率 42.3%；RMB 千元÷100,000 換算成億 | U194: =IF(AND($D194="",$E194="",$F194=""),1,0) -> 0 | V194: =IF(OR($I194="",$I194="—"),1,0) -> 0 | W194: =IF(AND(ISNUMBER($D194),ISNUMBER($E194)),IF($E194>$D194,1,0),0)+IF(AND(ISNUMBER($D194),ISNUMBER($F194)),IF($D194>$F194,1,0),0)+IF(AND(ISNUMBER($E194),ISNUMBER($F194)),IF($E194>$F194,1,0),0) -> 0 | X194: CC 初評
A195: SRC_ZP_191 | B195: gp_gpllm_1h25 | C195: 企業級通用大模型毛利 | D195: 0.8634 | G195: RMB 億 | H195: 1H2025 | I195: 智譜（Z.AI）2026 中期業績公告 | J195: https://ea-cdn.eurolandir.com/press-releases-attachments/4174939/HKEX-EPS_20260831_12308928_0.PDF | K195: 2026-08-31 | L195: 2026-10-08 | M195: Verified | O195: 未經審計（中期業績公告；是否經核數師審閱公告未見明載） | P195: 1 | Q195: 利害關係方 | R195: 經審計或經審閱的公司公告（誘因：上市後股價、配售；數字可由公告原文核對） | S195: 一手 | T195: 千元 86,342；毛利率 58.5%；RMB 千元÷100,000 換算成億 | U195: =IF(AND($D195="",$E195="",$F195=""),1,0) -> 0 | V195: =IF(OR($I195="",$I195="—"),1,0) -> 0 | W195: =IF(AND(ISNUMBER($D195),ISNUMBER($E195)),IF($E195>$D195,1,0),0)+IF(AND(ISNUMBER($D195),ISNUMBER($F195)),IF($D195>$F195,1,0),0)+IF(AND(ISNUMBER($E195),ISNUMBER($F195)),IF($E195>$F195,1,0),0) -> 0 | X195: CC 初評
A196: SRC_ZP_192 | B196: gp_techsvc_1h26 | C196: 技術服務及其他毛利 | D196: 0.0058 | G196: RMB 億 | H196: 1H2026 | I196: 智譜（Z.AI）2026 中期業績公告 | J196: https://ea-cdn.eurolandir.com/press-releases-attachments/4174939/HKEX-EPS_20260831_12308928_0.PDF | K196: 2026-08-31 | L196: 2026-10-08 | M196: Verified | O196: 未經審計（中期業績公告；是否經核數師審閱公告未見明載） | P196: 1 | Q196: 利害關係方 | R196: 經審計或經審閱的公司公告（誘因：上市後股價、配售；數字可由公告原文核對） | S196: 一手 | T196: 千元 576；毛利率 9.4%；RMB 千元÷100,000 換算成億 | U196: =IF(AND($D196="",$E196="",$F196=""),1,0) -> 0 | V196: =IF(OR($I196="",$I196="—"),1,0) -> 0 | W196: =IF(AND(ISNUMBER($D196),ISNUMBER($E196)),IF($E196>$D196,1,0),0)+IF(AND(ISNUMBER($D196),ISNUMBER($F196)),IF($D196>$F196,1,0),0)+IF(AND(ISNUMBER($E196),ISNUMBER($F196)),IF($E196>$F196,1,0),0) -> 0 | X196: CC 初評
A197: SRC_ZP_193 | B197: gp_techsvc_1h25 | C197: 技術服務及其他毛利 | D197: 0.0032 | G197: RMB 億 | H197: 1H2025 | I197: 智譜（Z.AI）2026 中期業績公告 | J197: https://ea-cdn.eurolandir.com/press-releases-attachments/4174939/HKEX-EPS_20260831_12308928_0.PDF | K197: 2026-08-31 | L197: 2026-10-08 | M197: Verified | O197: 未經審計（中期業績公告；是否經核數師審閱公告未見明載） | P197: 1 | Q197: 利害關係方 | R197: 經審計或經審閱的公司公告（誘因：上市後股價、配售；數字可由公告原文核對） | S197: 一手 | T197: 千元 318；毛利率 65.8%；RMB 千元÷100,000 換算成億 | U197: =IF(AND($D197="",$E197="",$F197=""),1,0) -> 0 | V197: =IF(OR($I197="",$I197="—"),1,0) -> 0 | W197: =IF(AND(ISNUMBER($D197),ISNUMBER($E197)),IF($E197>$D197,1,0),0)+IF(AND(ISNUMBER($D197),ISNUMBER($F197)),IF($D197>$F197,1,0),0)+IF(AND(ISNUMBER($E197),ISNUMBER($F197)),IF($E197>$F197,1,0),0) -> 0 | X197: CC 初評
... A210: SRC_ZP_206 | B210: adj_loss_1h26 | C210: 經調整淨虧損（非IFRS） | D210: 19.6414 | G210: RMB 億 | H210: 1H2026 | I210: 智譜（Z.AI）2026 中期業績公告 | J210: https://www1.hkexnews.hk/listedco/listconews/sehk/2026/0831/2026083101539.pdf | K210: 2026-08-31 | L210: 2026-10-08 | M210: Verified | O210: 未經審計（中期業績公告；是否經核數師審閱公告未見明載） | P210: 1 | Q210: 利害關係方 | R210: 經審計或經審閱的公司公告（誘因：上市後股價、配售；數字可由公告原文核對） | S210: 一手 | T210: 加回 SBC 85,764、投資人工具變動 22,090；千元 1,964,138（1H25 1,751,974）；RMB 千元÷100,000 換算成億 | U210: =IF(AND($D210="",$E210="",$F210=""),1,0) -> 0 | V210: =IF(OR($I210="",$I210="—"),1,0) -> 0 | W210: =IF(AND(ISNUMBER($D210),ISNUMBER($E210)),IF($E210>$D210,1,0),0)+IF(AND(ISNUMBER($D210),ISNUMBER($F210)),IF($D210>$F210,1,0),0)+IF(AND(ISNUMBER($E210),ISNUMBER($F210)),IF($E210>$F210,1,0),0) -> 0 | X210: CC 初評
A211: SRC_ZP_207 | B211: net_loss_1h25_b | C211: 期內淨虧損（媒體引部落客） | D211: 17.51 | G211: RMB 億 | H211: 1H2025 | I211: 36氪轉載〈市值水晶〉 | J211: https://www.36kr.com/p/3611675144253960 | K211: 2025-12-26 | L211: 2026-10-08 | M211: Interested-party | N211: 媒體轉述 | O211: 媒體轉述 | P211: 2 | Q211: 利害關係方 | R211: 媒體轉述 | S211: 二手 | T211: 媒體稱淨虧損 17.51 億；實為經調整淨虧損（招股章程 17.52 億），與期內虧損 23.58 億矛盾 | U211: =IF(AND($D211="",$E211="",$F211=""),1,0) -> 0 | V211: =IF(OR($I211="",$I211="—"),1,0) -> 0 | W211: =IF(AND(ISNUMBER($D211),ISNUMBER($E211)),IF($E211>$D211,1,0),0)+IF(AND(ISNUMBER($D211),ISNUMBER($F211)),IF($D211>$F211,1,0),0)+IF(AND(ISNUMBER($E211),ISNUMBER($F211)),IF($E211>$F211,1,0),0) -> 0 | X211: CC 初評
A212: SRC_ZP_208 | B212: net_loss_1h25_c | C212: 淨利潤（券商） | D212: -23.51 | G212: RMB 億 | H212: 1H2025 | I212: 國信證券〈垂類AI應用專題：智譜〉 | J212: https://pdf.dfcfw.com/pdf/H3_AP202601071816825157_1.pdf | K212: 2026-01-07 | L212: 2026-10-08 | M212: Interested-party | N212: 國信證券：券商研究，交易誘因 | O212: 券商口徑 | P212: 2 | Q212: 利害關係方 | R212: 國信證券：券商研究，交易誘因 | S212: 二手 | T212: 原文「净利润为-23.51亿元」；與招股章程期內虧損 23.58 億不一致（可能為歸母） | U212: =IF(AND($D212="",$E212="",$F212=""),1,0) -> 0 | V212: =IF(OR($I212="",$I212="—"),1,0) -> 0 | W212: =IF(AND(ISNUMBER($D212),ISNUMBER($E212)),IF($E212>$D212,1,0),0)+IF(AND(ISNUMBER($D212),ISNUMBER($F212)),IF($D212>$F212,1,0),0)+IF(AND(ISNUMBER($E212),ISNUMBER($F212)),IF($E212>$F212,1,0),0) -> 0 | X212: CC 初評
A213: SRC_ZP_209 | B213: capex_1h26 | C213: 資本開支 | D213: 3.906 | G213: RMB 億 | H213: 1H2026 | I213: 智譜（Z.AI）2026 中期業績公告 | J213: https://ea-cdn.eurolandir.com/press-releases-attachments/4174939/HKEX-EPS_20260831_12308928_0.PDF | K213: 2026-08-31 | L213: 2026-10-08 | M213: Verified | O213: 未經審計（中期業績公告；是否經核數師審閱公告未見明載） | P213: 1 | Q213: 利害關係方 | R213: 經審計或經審閱的公司公告（誘因：上市後股價、配售；數字可由公告原文核對） | S213: 一手 | T213: 原文 increased from RMB53.7 million to RMB390.6 million（+627.4%），主因收購北京紅鑽；百萬÷100 | U213: =IF(AND($D213="",$E213="",$F213=""),1,0) -> 0 | V213: =IF(OR($I213="",$I213="—"),1,0) -> 0 | W213: =IF(AND(ISNUMBER($D213),ISNUMBER($E213)),IF($E213>$D213,1,0),0)+IF(AND(ISNUMBER($D213),ISNUMBER($F213)),IF($D213>$F213,1,0),0)+IF(AND(ISNUMBER($E213),ISNUMBER($F213)),IF($E213>$F213,1,0),0) -> 0 | X213: CC 初評
A214: SRC_ZP_210 | B214: capex_1h25 | C214: 資本開支 | D214: 0.537 | G214: RMB 億 | H214: 1H2025 | I214: 智譜（Z.AI）2026 中期業績公告 | J214: https://ea-cdn.eurolandir.com/press-releases-attachments/4174939/HKEX-EPS_20260831_12308928_0.PDF | K214: 2026-08-31 | L214: 2026-10-08 | M214: Verified | O214: 未經審計（中期業績公告；是否經核數師審閱公告未見明載） | P214: 1 | Q214: 利害關係方 | R214: 經審計或經審閱的公司公告（誘因：上市後股價、配售；數字可由公告原文核對） | S214: 一手 | T214: 中期公告比較數 RMB53.7 million；百萬÷100 | U214: =IF(AND($D214="",$E214="",$F214=""),1,0) -> 0 | V214: =IF(OR($I214="",$I214="—"),1,0) -> 0 | W214: =IF(AND(ISNUMBER($D214),ISNUMBER($E214)),IF($E214>$D214,1,0),0)+IF(AND(ISNUMBER($D214),ISNUMBER($F214)),IF($D214>$F214,1,0),0)+IF(AND(ISNUMBER($E214),ISNUMBER($F214)),IF($E214>$F214,1,0),0) -> 0 | X214: CC 初評
A215: SRC_ZP_211 | B215: cash_end_1h26 | C215: 期末現金及現金等價物 | D215: 39.9372 | G215: RMB 億 | H215: 2026-06-30 | I215: 智譜（Z.AI）2026 中期業績公告 | J215: https://www1.hkexnews.hk/listedco/listconews/sehk/2026/0831/2026083101539.pdf | K215: 2026-08-31 | L215: 2026-10-08 | M215: Verified | O215: 未經審計（中期業績公告；是否經核數師審閱公告未見明載） | P215: 1 | Q215: 利害關係方 | R215: 經審計或經審閱的公司公告（誘因：上市後股價、配售；數字可由公告原文核對） | S215: 一手 | T215: 千元 3,993,722（2025 年末 2,259,147）；RMB 千元÷100,000 換算成億 | U215: =IF(AND($D215="",$E215="",$F215=""),1,0) -> 0 | V215: =IF(OR($I215="",$I215="—"),1,0) -> 0 | W215: =IF(AND(ISNUMBER($D215),ISNUMBER($E215)),IF($E215>$D215,1,0),0)+IF(AND(ISNUMBER($D215),ISNUMBER($F215)),IF($D215>$F215,1,0),0)+IF(AND(ISNUMBER($E215),ISNUMBER($F215)),IF($E215>$F215,1,0),0) -> 0 | X215: CC 初評
A216: SRC_ZP_212 | B216: time_dep_1h26 | C216: 定期存款 | D216: 0 | G216: RMB 億 | H216: 2026-06-30 | I216: 智譜（Z.AI）2026 中期業績公告 | J216: https://www1.hkexnews.hk/listedco/listconews/sehk/2026/0831/2026083101539.pdf | K216: 2026-08-31 | L216: 2026-10-08 | M216: Verified | O216: 未經審計（中期業績公告；是否經核數師審閱公告未見明載） | P216: 1 | Q216: 利害關係方 | R216: 經審計或經審閱的公司公告（誘因：上市後股價、配售；數字可由公告原文核對） | S216: 一手 | T216: time deposits nil（2025 年末 108,593 千元） | U216: =IF(AND($D216="",$E216="",$F216=""),1,0) -> 0 | V216: =IF(OR($I216="",$I216="—"),1,0) -> 0 | W216: =IF(AND(ISNUMBER($D216),ISNUMBER($E216)),IF($E216>$D216,1,0),0)+IF(AND(ISNUMBER($D216),ISNUMBER($F216)),IF($D216>$F216,1,0),0)+IF(AND(ISNUMBER($E216),ISNUMBER($F216)),IF($E216>$F216,1,0),0) -> 0 | X216: CC 初評
A217: SRC_ZP_213 | B217: bank_loans_1h26 | C217: 銀行貸款合計 | D217: 22.2479 | G217: RMB 億 | H217: 2026-06-30 | I217: 智譜（Z.AI）2026 中期業績公告 | J217: https://www1.hkexnews.hk/listedco/listconews/sehk/2026/0831/2026083101539.pdf | K217: 2026-08-31 | L217: 2026-10-08 | M217: Verified | O217: 未經審計（中期業績公告；是否經核數師審閱公告未見明載） | P217: 1 | Q217: 利害關係方 | R217: 經審計或經審閱的公司公告（誘因：上市後股價、配售；數字可由公告原文核對） | S217: 一手 | T217: 流動 789,831＋非流動 1,434,958 千元；原文「interest-bearing, denominated primarily in RMB and unsecured」；利率、到期未揭露；RMB 千元÷100,000 換算成億 | U217: =IF(AND($D217="",$E217="",$F217=""),1,0) -> 0 | V217: =IF(OR($I217="",$I217="—"),1,0) -> 0 | W217: =IF(AND(ISNUMBER($D217),ISNUMBER($E217)),IF($E217>$D217,1,0),0)+IF(AND(ISNUMBER($D217),ISNUMBER($F217)),IF($D217>$F217,1,0),0)+IF(AND(ISNUMBER($E217),ISNUMBER($F217)),IF($E217>$F217,1,0),0) -> 0 | X217: CC 初評
A218: SRC_ZP_214 | B218: bank_loans_cur_1h26 | C218: 銀行貸款（流動，一年內到期） | D218: 7.8983 | G218: RMB 億 | H218: 2026-06-30 | I218: 智譜（Z.AI）2026 中期業績公告 | J218: https://www1.hkexnews.hk/listedco/listconews/sehk/2026/0831/2026083101539.pdf | K218: 2026-08-31 | L218: 2026-10-08 | M218: Verified | O218: 未經審計（中期業績公告；是否經核數師審閱公告未見明載） | P218: 1 | Q218: 利害關係方 | R218: 經審計或經審閱的公司公告（誘因：上市後股價、配售；數字可由公告原文核對） | S218: 一手 | T218: current 789,831 千元；RMB 千元÷100,000 換算成億 | U218: =IF(AND($D218="",$E218="",$F218=""),1,0) -> 0 | V218: =IF(OR($I218="",$I218="—"),1,0) -> 0 | W218: =IF(AND(ISNUMBER($D218),ISNUMBER($E218)),IF($E218>$D218,1,0),0)+IF(AND(ISNUMBER($D218),ISNUMBER($F218)),IF($D218>$F218,1,0),0)+IF(AND(ISNUMBER($E218),ISNUMBER($F218)),IF($E218>$F218,1,0),0) -> 0 | X218: CC 初評
A219: SRC_ZP_215 | B219: bank_loans_ncur_1h26 | C219: 銀行貸款（非流動） | D219: 14.3496 | G219: RMB 億 | H219: 2026-06-30 | I219: 智譜（Z.AI）2026 中期業績公告 | J219: https://www1.hkexnews.hk/listedco/listconews/sehk/2026/0831/2026083101539.pdf | K219: 2026-08-31 | L219: 2026-10-08 | M219: Verified | O219: 未經審計（中期業績公告；是否經核數師審閱公告未見明載） | P219: 1 | Q219: 利害關係方 | R219: 經審計或經審閱的公司公告（誘因：上市後股價、配售；數字可由公告原文核對） | S219: 一手 | T219: non-current 1,434,958 千元；RMB 千元÷100,000 換算成億 | U219: =IF(AND($D219="",$E219="",$F219=""),1,0) -> 0 | V219: =IF(OR($I219="",$I219="—"),1,0) -> 0 | W219: =IF(AND(ISNUMBER($D219),ISNUMBER($E219)),IF($E219>$D219,1,0),0)+IF(AND(ISNUMBER($D219),ISNUMBER($F219)),IF($D219>$F219,1,0),0)+IF(AND(ISNUMBER($E219),ISNUMBER($F219)),IF($E219>$F219,1,0),0) -> 0 | X219: CC 初評
A220: SRC_ZP_216 | B220: bank_loans_cur_fy25 | C220: 銀行貸款（流動） | D220: 6.0484 | G220: RMB 億 | H220: 2025-12-31 | I220: 智譜 2025 年度業績公告 | J220: https://www1.hkexnews.hk/listedco/listconews/sehk/2026/0331/2026033101549.pdf | K220: 2026-03-31 | L220: 2026-10-08 | M220: Verified | O220: 經審計（KPMG；年度業績公告） | P220: 1 | Q220: 利害關係方 | R220: 經審計或經審閱的公司公告（誘因：上市後股價、配售；數字可由公告原文核對） | S220: 一手 | T220: current 604,836 千元；RMB 千元÷100,000 換算成億 | U220: =IF(AND($D220="",$E220="",$F220=""),1,0) -> 0 | V220: =IF(OR($I220="",$I220="—"),1,0) -> 0 | W220: =IF(AND(ISNUMBER($D220),ISNUMBER($E220)),IF($E220>$D220,1,0),0)+IF(AND(ISNUMBER($D220),ISNUMBER($F220)),IF($D220>$F220,1,0),0)+IF(AND(ISNUMBER($E220),ISNUMBER($F220)),IF($E220>$F220,1,0),0) -> 0 | X220: CC 初評
A221: SRC_ZP_217 | B221: bank_loans_ncur_fy25 | C221: 銀行貸款（非流動） | D221: 0.8462 | G221: RMB 億 | H221: 2025-12-31 | I221: 智譜 2025 年度業績公告 | J221: https://www1.hkexnews.hk/listedco/listconews/sehk/2026/0331/2026033101549.pdf | K221: 2026-03-31 | L221: 2026-10-08 | M221: Verified | O221: 經審計（KPMG；年度業績公告） | P221: 1 | Q221: 利害關係方 | R221: 經審計或經審閱的公司公告（誘因：上市後股價、配售；數字可由公告原文核對） | S221: 一手 | T221: non-current 84,616 千元；RMB 千元÷100,000 換算成億 | U221: =IF(AND($D221="",$E221="",$F221=""),1,0) -> 0 | V221: =IF(OR($I221="",$I221="—"),1,0) -> 0 | W221: =IF(AND(ISNUMBER($D221),ISNUMBER($E221)),IF($E221>$D221,1,0),0)+IF(AND(ISNUMBER($D221),ISNUMBER($F221)),IF($D221>$F221,1,0),0)+IF(AND(ISNUMBER($E221),ISNUMBER($F221)),IF($E221>$F221,1,0),0) -> 0 | X221: CC 初評
A222: SRC_ZP_218 | B222: payable_compute_1h26 | C222: 應付算力服務費 | D222: 14.2742 | G222: RMB 億 | H222: 2026-06-30 | I222: 智譜（Z.AI）2026 中期業績公告 | J222: https://ea-cdn.eurolandir.com/press-releases-attachments/4174939/HKEX-EPS_20260831_12308928_0.PDF | K222: 2026-08-31 | L222: 2026-10-08 | M222: Verified | O222: 未經審計（中期業績公告；是否經核數師審閱公告未見明載） | P222: 1 | Q222: 利害關係方 | R222: 經審計或經審閱的公司公告（誘因：上市後股價、配售；數字可由公告原文核對） | S222: 一手 | T222: payables for computing service fees 1,427,415 千元；RMB 千元÷100,000 換算成億 | U222: =IF(AND($D222="",$E222="",$F222=""),1,0) -> 0 | V222: =IF(OR($I222="",$I222="—"),1,0) -> 0 | W222: =IF(AND(ISNUMBER($D222),ISNUMBER($E222)),IF($E222>$D222,1,0),0)+IF(AND(ISNUMBER($D222),ISNUMBER($F222)),IF($D222>$F222,1,0),0)+IF(AND(ISNUMBER($E222),ISNUMBER($F222)),IF($E222>$F222,1,0),0) -> 0 | X222: CC 初評
A223: SRC_ZP_219 | B223: prepay_compute_1h26 | C223: 預付算力服務費及其他 | D223: 12.4374 | G223: RMB 億 | H223: 2026-06-30 | I223: 智譜（Z.AI）2026 中期業績公告 | J223: https://ea-cdn.eurolandir.com/press-releases-attachments/4174939/HKEX-EPS_20260831_12308928_0.PDF | K223: 2026-08-31 | L223: 2026-10-08 | M223: Verified | O223: 未經審計（中期業績公告；是否經核數師審閱公告未見明載） | P223: 1 | Q223: 利害關係方 | R223: 經審計或經審閱的公司公告（誘因：上市後股價、配售；數字可由公告原文核對） | S223: 一手 | T223: prepayments for computing service fee and others 1,243,736（2025 年末 116,295）；RMB 千元÷100,000 換算成億 | U223: =IF(AND($D223="",$E223="",$F223=""),1,0) -> 0 | V223: =IF(OR($I223="",$I223="—"),1,0) -> 0 | W223: =IF(AND(ISNUMBER($D223),ISNUMBER($E223)),IF($E223>$D223,1,0),0)+IF(AND(ISNUMBER($D223),ISNUMBER($F223)),IF($D223>$F223,1,0),0)+IF(AND(ISNUMBER($E223),ISNUMBER($F223)),IF($E223>$F223,1,0),0) -> 0 | X223: CC 初評
A224: SRC_ZP_220 | B224: prepay_compute_fy25 | C224: 預付算力服務費及其他 | D224: 1.1629 | G224: RMB 億 | H224: 2025-12-31 | I224: 智譜（Z.AI）2026 中期業績公告 | J224: https://ea-cdn.eurolandir.com/press-releases-attachments/4174939/HKEX-EPS_20260831_12308928_0.PDF | K224: 2026-08-31 | L224: 2026-10-08 | M224: Verified | O224: 未經審計（中期業績公告；是否經核數師審閱公告未見明載） | P224: 1 | Q224: 利害關係方 | R224: 經審計或經審閱的公司公告（誘因：上市後股價、配售；數字可由公告原文核對） | S224: 一手 | T224: 中期公告比較數 116,295 千元；RMB 千元÷100,000 換算成億 | U224: =IF(AND($D224="",$E224="",$F224=""),1,0) -> 0 | V224: =IF(OR($I224="",$I224="—"),1,0) -> 0 | W224: =IF(AND(ISNUMBER($D224),ISNUMBER($E224)),IF($E224>$D224,1,0),0)+IF(AND(ISNUMBER($D224),ISNUMBER($F224)),IF($D224>$F224,1,0),0)+IF(AND(ISNUMBER($E224),ISNUMBER($F224)),IF($E224>$F224,1,0),0) -> 0 | X224: CC 初評
... A230: SRC_ZP_226 | B230: comp_per_head_1h26 | C230: 人均半年薪酬（含股權報酬） | D230: 0.00491 | G230: RMB 億／人／半年 | H230: 1H2026 | I230: 智譜（Z.AI）2026 中期業績公告 | J230: https://ea-cdn.eurolandir.com/press-releases-attachments/4174939/HKEX-EPS_20260831_12308928_0.PDF | K230: 2026-08-31 | L230: 2026-10-08 | M230: Derived | O230: Derived | P230: 2 | Q230: 推算 | R230: 由其他 SRC 列推算（見備註）；立場同其來源 | S230: 一手 | T230: 482.1 百萬÷期末 981 人＝約 49.1 萬元／人／半年 | U230: =IF(AND($D230="",$E230="",$F230=""),1,0) -> 0 | V230: =IF(OR($I230="",$I230="—"),1,0) -> 0 | W230: =IF(AND(ISNUMBER($D230),ISNUMBER($E230)),IF($E230>$D230,1,0),0)+IF(AND(ISNUMBER($D230),ISNUMBER($F230)),IF($D230>$F230,1,0),0)+IF(AND(ISNUMBER($E230),ISNUMBER($F230)),IF($E230>$F230,1,0),0) -> 0 | X230: CC 初評
A231: SRC_ZP_227 | B231: api_price_1h26 | C231: API 平均售價上升 | D231: 101 | G231: % | H231: 1H2026 | I231: 智譜（Z.AI）2026 中期業績公告 | J231: https://ea-cdn.eurolandir.com/press-releases-attachments/4174939/HKEX-EPS_20260831_12308928_0.PDF | K231: 2026-08-31 | L231: 2026-10-08 | M231: Interested-party | N231: 智譜：上市後股價、配售誘因 | O231: 管理層口徑 | P231: 1 | Q231: 利害關係方 | R231: 智譜：上市後股價、配售誘因 | S231: 一手 | T231: 原文「the average API selling price increased by approximately 101%」；比較基準未明 | U231: =IF(AND($D231="",$E231="",$F231=""),1,0) -> 0 | V231: =IF(OR($I231="",$I231="—"),1,0) -> 0 | W231: =IF(AND(ISNUMBER($D231),ISNUMBER($E231)),IF($E231>$D231,1,0),0)+IF(AND(ISNUMBER($D231),ISNUMBER($F231)),IF($D231>$F231,1,0),0)+IF(AND(ISNUMBER($E231),ISNUMBER($F231)),IF($E231>$F231,1,0),0) -> 0 | X231: CC 初評
A232: SRC_ZP_228 | B232: codingplan_class_1h26 | C232: GLM Coding Plan 收入歸屬 | H232: 1H2026 | I232: 智譜（Z.AI）2026 中期業績公告 | J232: https://ea-cdn.eurolandir.com/press-releases-attachments/4174939/HKEX-EPS_20260831_12308928_0.PDF | K232: 2026-08-31 | L232: 2026-10-08 | M232: Derived | O232: Derived | P232: 2 | Q232: 推算 | R232: 由其他 SRC 列推算（見備註）；立場同其來源 | S232: 一手 | T232: 未單列。雲端分部＝開放平台及 API（825,176），本地化＝其餘三線合計；Coding Plan 為雲端訂閱，故在開放平台及 API 內 | U232: =IF(AND($D232="",$E232="",$F232=""),1,0) -> 1 | V232: =IF(OR($I232="",$I232="—"),1,0) -> 0 | W232: =IF(AND(ISNUMBER($D232),ISNUMBER($E232)),IF($E232>$D232,1,0),0)+IF(AND(ISNUMBER($D232),ISNUMBER($F232)),IF($D232>$F232,1,0),0)+IF(AND(ISNUMBER($E232),ISNUMBER($F232)),IF($E232>$F232,1,0),0) -> 0 | X232: CC 初評
A233: SRC_ZP_229 | B233: domestic_chip_1h26 | C233: 國產晶片推論集群規模 | D233: 100000 | E233: 100000 | G233: 顆（下限） | H233: 1H2026 | I233: 智譜（Z.AI）2026 中期業績公告 | J233: https://ea-cdn.eurolandir.com/press-releases-attachments/4174939/HKEX-EPS_20260831_12308928_0.PDF | K233: 2026-08-31 | L233: 2026-10-08 | M233: Interested-party | N233: 智譜：上市後股價、配售誘因 | O233: 管理層口徑 | P233: 1 | Q233: 利害關係方 | R233: 智譜：上市後股價、配售誘因 | S233: 一手 | T233: 原文「across a cluster of over 100,000 domestic chips」 | U233: =IF(AND($D233="",$E233="",$F233=""),1,0) -> 0 | V233: =IF(OR($I233="",$I233="—"),1,0) -> 0 | W233: =IF(AND(ISNUMBER($D233),ISNUMBER($E233)),IF($E233>$D233,1,0),0)+IF(AND(ISNUMBER($D233),ISNUMBER($F233)),IF($D233>$F233,1,0),0)+IF(AND(ISNUMBER($E233),ISNUMBER($F233)),IF($E233>$F233,1,0),0) -> 0 | X233: CC 初評
A234: SRC_ZP_230 | B234: rd_compute_fy22 | C234: 研發開支中算力服務費（含模型訓練及雲端部署服務） | D234: 0.15 | G234: RMB 億 | H234: FY2022 | I234: 36氪轉載〈市值水晶〉（王浩然） | J234: https://www.36kr.com/p/3611675144253960 | K234: 2025-12-26 | L234: 2026-10-08 | M234: Interested-party | N234: 媒體轉述 | O234: 媒體轉述（招股章程） | P234: 2 | Q234: 利害關係方 | R234: 媒體轉述 | S234: 二手 | T234: 原文「从2022年的0.15亿元」；原始招股章程財務資料節未能讀取 | U234: =IF(AND($D234="",$E234="",$F234=""),1,0) -> 0 | V234: =IF(OR($I234="",$I234="—"),1,0) -> 0 | W234: =IF(AND(ISNUMBER($D234),ISNUMBER($E234)),IF($E234>$D234,1,0),0)+IF(AND(ISNUMBER($D234),ISNUMBER($F234)),IF($D234>$F234,1,0),0)+IF(AND(ISNUMBER($E234),ISNUMBER($F234)),IF($E234>$F234,1,0),0) -> 0 | X234: CC 初評
A235: SRC_ZP_231 | B235: rd_compute_1h25 | C235: 研發開支中算力服務費（含模型訓練及雲端部署服務） | D235: 11.45 | G235: RMB 億 | H235: 1H2025 | I235: 36氪轉載〈市值水晶〉（王浩然） | J235: https://www.36kr.com/p/3611675144253960 | K235: 2025-12-26 | L235: 2026-10-08 | M235: Interested-party | N235: 媒體轉述 | O235: 媒體轉述（招股章程） | P235: 2 | Q235: 利害關係方 | R235: 媒體轉述 | S235: 二手 | T235: 原文「到2025年上半年的11.45亿」；原始招股章程財務資料節未能讀取 | U235: =IF(AND($D235="",$E235="",$F235=""),1,0) -> 0 | V235: =IF(OR($I235="",$I235="—"),1,0) -> 0 | W235: =IF(AND(ISNUMBER($D235),ISNUMBER($E235)),IF($E235>$D235,1,0),0)+IF(AND(ISNUMBER($D235),ISNUMBER($F235)),IF($D235>$F235,1,0),0)+IF(AND(ISNUMBER($E235),ISNUMBER($F235)),IF($E235>$F235,1,0),0) -> 0 | X235: CC 初評
A236: SRC_ZP_232 | B236: rd_compute_fy24 | C236: 研發開支中算力服務費 | D236: 15.52 | G236: RMB 億 | H236: FY2024 | I236: 華爾街見聞 | J236: https://wallstreetcn.com/articles/3761769 | K236: 2025-12-20 | L236: 2026-10-08 | M236: Interested-party | N236: 媒體轉述 | O236: 媒體轉述（招股章程） | P236: 2 | Q236: 利害關係方 | R236: 媒體轉述 | S236: 二手 | T236: 原文 2024年算力服務費 15.52億元，「同期收入的5倍左右」；原始財務資料節未能讀取 | U236: =IF(AND($D236="",$E236="",$F236=""),1,0) -> 0 | V236: =IF(OR($I236="",$I236="—"),1,0) -> 0 | W236: =IF(AND(ISNUMBER($D236),ISNUMBER($E236)),IF($E236>$D236,1,0),0)+IF(AND(ISNUMBER($D236),ISNUMBER($F236)),IF($D236>$F236,1,0),0)+IF(AND(ISNUMBER($E236),ISNUMBER($F236)),IF($E236>$F236,1,0),0) -> 0 | X236: CC 初評
A237: SRC_ZP_233 | B237: rd_compute_fy24_b | C237: 研發開支中算力服務費 | D237: 15.53 | G237: RMB 億 | H237: FY2024 | I237: 每日經濟新聞 | J237: https://www.nbd.com.cn/articles/2025-12-21/4189232.html | K237: 2025-12-21 | L237: 2026-10-08 | M237: Interested-party | N237: 媒體轉述 | O237: 媒體轉述（招股章程） | P237: 2 | Q237: 利害關係方 | R237: 媒體轉述 | S237: 二手 | T237: 15.53 億元，占研發逾 70%；與華爾街見聞 15.52 億差 0.01（四捨五入） | U237: =IF(AND($D237="",$E237="",$F237=""),1,0) -> 0 | V237: =IF(OR($I237="",$I237="—"),1,0) -> 0 | W237: =IF(AND(ISNUMBER($D237),ISNUMBER($E237)),IF($E237>$D237,1,0),0)+IF(AND(ISNUMBER($D237),ISNUMBER($F237)),IF($D237>$F237,1,0),0)+IF(AND(ISNUMBER($E237),ISNUMBER($F237)),IF($E237>$F237,1,0),0) -> 0 | X237: CC 初評
A238: SRC_ZP_234 | B238: rd_compute_share_1h25 | C238: 算力服務費占研發開支比重 | D238: 70 | E238: 70 | G238: %（下限） | H238: 1H2025 | I238: 每日經濟新聞 | J238: https://www.nbd.com.cn/articles/2025-12-21/4189232.html | K238: 2025-12-21 | L238: 2026-10-08 | M238: Interested-party | N238: 媒體轉述 | O238: 媒體轉述（招股章程） | P238: 2 | Q238: 利害關係方 | R238: 媒體轉述 | S238: 二手 | T238: 原文「仍维持在七成以上」 | U238: =IF(AND($D238="",$E238="",$F238=""),1,0) -> 0 | V238: =IF(OR($I238="",$I238="—"),1,0) -> 0 | W238: =IF(AND(ISNUMBER($D238),ISNUMBER($E238)),IF($E238>$D238,1,0),0)+IF(AND(ISNUMBER($D238),ISNUMBER($F238)),IF($D238>$F238,1,0),0)+IF(AND(ISNUMBER($E238),ISNUMBER($F238)),IF($E238>$F238,1,0),0) -> 0 | X238: CC 初評
A239: SRC_ZP_235 | B239: rd_staff_cost_fy22 | C239: 研發人員工資成本 | D239: 0.42 | G239: RMB 億 | H239: FY2022 | I239: 36氪轉載〈市值水晶〉（王浩然） | J239: https://www.36kr.com/p/3611675144253960 | K239: 2025-12-26 | L239: 2026-10-08 | M239: Interested-party | N239: 媒體轉述 | O239: 媒體轉述（招股章程） | P239: 2 | Q239: 利害關係方 | R239: 媒體轉述 | S239: 二手 | T239: 原文「研发人员的工资成本分别为0.42亿、1.37亿、3.24亿元…2.66亿元」 | U239: =IF(AND($D239="",$E239="",$F239=""),1,0) -> 0 | V239: =IF(OR($I239="",$I239="—"),1,0) -> 0 | W239: =IF(AND(ISNUMBER($D239),ISNUMBER($E239)),IF($E239>$D239,1,0),0)+IF(AND(ISNUMBER($D239),ISNUMBER($F239)),IF($D239>$F239,1,0),0)+IF(AND(ISNUMBER($E239),ISNUMBER($F239)),IF($E239>$F239,1,0),0) -> 0 | X239: CC 初評
A240: SRC_ZP_236 | B240: rd_staff_cost_fy23 | C240: 研發人員工資成本 | D240: 1.37 | G240: RMB 億 | H240: FY2023 | I240: 36氪轉載〈市值水晶〉（王浩然） | J240: https://www.36kr.com/p/3611675144253960 | K240: 2025-12-26 | L240: 2026-10-08 | M240: Interested-party | N240: 媒體轉述 | O240: 媒體轉述（招股章程） | P240: 2 | Q240: 利害關係方 | R240: 媒體轉述 | S240: 二手 | T240: 原文「研发人员的工资成本分别为0.42亿、1.37亿、3.24亿元…2.66亿元」 | U240: =IF(AND($D240="",$E240="",$F240=""),1,0) -> 0 | V240: =IF(OR($I240="",$I240="—"),1,0) -> 0 | W240: =IF(AND(ISNUMBER($D240),ISNUMBER($E240)),IF($E240>$D240,1,0),0)+IF(AND(ISNUMBER($D240),ISNUMBER($F240)),IF($D240>$F240,1,0),0)+IF(AND(ISNUMBER($E240),ISNUMBER($F240)),IF($E240>$F240,1,0),0) -> 0 | X240: CC 初評
A241: SRC_ZP_237 | B241: rd_staff_cost_fy24 | C241: 研發人員工資成本 | D241: 3.24 | G241: RMB 億 | H241: FY2024 | I241: 36氪轉載〈市值水晶〉（王浩然） | J241: https://www.36kr.com/p/3611675144253960 | K241: 2025-12-26 | L241: 2026-10-08 | M241: Interested-party | N241: 媒體轉述 | O241: 媒體轉述（招股章程） | P241: 2 | Q241: 利害關係方 | R241: 媒體轉述 | S241: 二手 | T241: 原文「研发人员的工资成本分别为0.42亿、1.37亿、3.24亿元…2.66亿元」 | U241: =IF(AND($D241="",$E241="",$F241=""),1,0) -> 0 | V241: =IF(OR($I241="",$I241="—"),1,0) -> 0 | W241: =IF(AND(ISNUMBER($D241),ISNUMBER($E241)),IF($E241>$D241,1,0),0)+IF(AND(ISNUMBER($D241),ISNUMBER($F241)),IF($D241>$F241,1,0),0)+IF(AND(ISNUMBER($E241),ISNUMBER($F241)),IF($E241>$F241,1,0),0) -> 0 | X241: CC 初評
A242: SRC_ZP_238 | B242: rd_staff_cost_1h25 | C242: 研發人員工資成本 | D242: 2.66 | G242: RMB 億 | H242: 1H2025 | I242: 36氪轉載〈市值水晶〉（王浩然） | J242: https://www.36kr.com/p/3611675144253960 | K242: 2025-12-26 | L242: 2026-10-08 | M242: Interested-party | N242: 媒體轉述 | O242: 媒體轉述（招股章程） | P242: 2 | Q242: 利害關係方 | R242: 媒體轉述 | S242: 二手 | T242: 原文「研发人员的工资成本分别为0.42亿、1.37亿、3.24亿元…2.66亿元」 | U242: =IF(AND($D242="",$E242="",$F242=""),1,0) -> 0 | V242: =IF(OR($I242="",$I242="—"),1,0) -> 0 | W242: =IF(AND(ISNUMBER($D242),ISNUMBER($E242)),IF($E242>$D242,1,0),0)+IF(AND(ISNUMBER($D242),ISNUMBER($F242)),IF($D242>$F242,1,0),0)+IF(AND(ISNUMBER($E242),ISNUMBER($F242)),IF($E242>$F242,1,0),0) -> 0 | X242: CC 初評
A243: SRC_ZP_239 | B243: rd_staff_share_fy24 | C243: 工資成本占研發開支比重 | D243: 14.8 | G243: % | H243: FY2024 | I243: 鈦媒體（山上） | J243: https://www.tmtpost.com/7815849.html | K243: 2025-12-21 | L243: 2026-10-08 | M243: Interested-party | N243: 媒體轉述 | O243: 媒體轉述（招股章程） | P243: 2 | Q243: 利害關係方 | R243: 媒體轉述 | S243: 二手 | T243: 原文 2024 年工資成本占研發 14.8%（3.24/21.95 吻合） | U243: =IF(AND($D243="",$E243="",$F243=""),1,0) -> 0 | V243: =IF(OR($I243="",$I243="—"),1,0) -> 0 | W243: =IF(AND(ISNUMBER($D243),ISNUMBER($E243)),IF($E243>$D243,1,0),0)+IF(AND(ISNUMBER($D243),ISNUMBER($F243)),IF($D243>$F243,1,0),0)+IF(AND(ISNUMBER($E243),ISNUMBER($F243)),IF($E243>$F243,1,0),0) -> 0 | X243: CC 初評
A244: SRC_ZP_240 | B244: rd_staff_pct_1h25 | C244: 研發人員占員工比重 | D244: 74.4 | G244: % | H244: 2025-06-30 | I244: 鈦媒體（山上） | J244: https://www.tmtpost.com/7815849.html | K244: 2025-12-21 | L244: 2026-10-08 | M244: Interested-party | N244: 媒體轉述 | O244: 媒體轉述（招股章程） | P244: 2 | Q244: 利害關係方 | R244: 媒體轉述 | S244: 二手 | T244: 原文 員工 883 人、研發 657 人，占 74.4%（證券日報稱 74%） | U244: =IF(AND($D244="",$E244="",$F244=""),1,0) -> 0 | V244: =IF(OR($I244="",$I244="—"),1,0) -> 0 | W244: =IF(AND(ISNUMBER($D244),ISNUMBER($E244)),IF($E244>$D244,1,0),0)+IF(AND(ISNUMBER($D244),ISNUMBER($F244)),IF($D244>$F244,1,0),0)+IF(AND(ISNUMBER($E244),ISNUMBER($F244)),IF($E244>$F244,1,0),0) -> 0 | X244: CC 初評
A245: SRC_ZP_241 | B245: px_usd_glm53_in | C245: GLM-5.3 國際站牌價（輸入） | D245: 1.4 | G245: USD／百萬 token | H245: 2026-10（現行） | I245: Z.ai 開發者文件 Pricing 頁（國際站官方牌價） | J245: https://docs.z.ai/guides/overview/pricing.md | K245: 2026-10-08 | L245: 2026-10-08 | M245: Verified | P245: 1 | Q245: 利害關係方 | R245: 公司公開且具約束力的報價，誤報誘因低 | S245: 一手 | T245: 官方表列 GLM-5.3：Input $1.4／Cached Input $0.26／Output $4.4；快取儲存「Limited-time free」；無長度分段 | U245: =IF(AND($D245="",$E245="",$F245=""),1,0) -> 0 | V245: =IF(OR($I245="",$I245="—"),1,0) -> 0 | W245: =IF(AND(ISNUMBER($D245),ISNUMBER($E245)),IF($E245>$D245,1,0),0)+IF(AND(ISNUMBER($D245),ISNUMBER($F245)),IF($D245>$F245,1,0),0)+IF(AND(ISNUMBER($E245),ISNUMBER($F245)),IF($E245>$F245,1,0),0) -> 0 | X245: CC 初評
A246: SRC_ZP_242 | B246: px_usd_glm53_cache | C246: GLM-5.3 國際站牌價（快取命中輸入） | D246: 0.26 | G246: USD／百萬 token | H246: 2026-10（現行） | I246: Z.ai 開發者文件 Pricing 頁（國際站官方牌價） | J246: https://docs.z.ai/guides/overview/pricing.md | K246: 2026-10-08 | L246: 2026-10-08 | M246: Verified | P246: 1 | Q246: 利害關係方 | R246: 公司公開且具約束力的報價，誤報誘因低 | S246: 一手 | T246: 官方表列 GLM-5.3：Input $1.4／Cached Input $0.26／Output $4.4；快取儲存「Limited-time free」；無長度分段 | U246: =IF(AND($D246="",$E246="",$F246=""),1,0) -> 0 | V246: =IF(OR($I246="",$I246="—"),1,0) -> 0 | W246: =IF(AND(ISNUMBER($D246),ISNUMBER($E246)),IF($E246>$D246,1,0),0)+IF(AND(ISNUMBER($D246),ISNUMBER($F246)),IF($D246>$F246,1,0),0)+IF(AND(ISNUMBER($E246),ISNUMBER($F246)),IF($E246>$F246,1,0),0) -> 0 | X246: CC 初評
A247: SRC_ZP_243 | B247: px_usd_glm53_out | C247: GLM-5.3 國際站牌價（輸出） | D247: 4.4 | G247: USD／百萬 token | H247: 2026-10（現行） | I247: Z.ai 開發者文件 Pricing 頁（國際站官方牌價） | J247: https://docs.z.ai/guides/overview/pricing.md | K247: 2026-10-08 | L247: 2026-10-08 | M247: Verified | P247: 1 | Q247: 利害關係方 | R247: 公司公開且具約束力的報價，誤報誘因低 | S247: 一手 | T247: 官方表列 GLM-5.3：Input $1.4／Cached Input $0.26／Output $4.4；快取儲存「Limited-time free」；無長度分段 | U247: =IF(AND($D247="",$E247="",$F247=""),1,0) -> 0 | V247: =IF(OR($I247="",$I247="—"),1,0) -> 0 | W247: =IF(AND(ISNUMBER($D247),ISNUMBER($E247)),IF($E247>$D247,1,0),0)+IF(AND(ISNUMBER($D247),ISNUMBER($F247)),IF($D247>$F247,1,0),0)+IF(AND(ISNUMBER($E247),ISNUMBER($F247)),IF($E247>$F247,1,0),0) -> 0 | X247: CC 初評
A248: SRC_ZP_244 | B248: px_usd_glm52_in | C248: GLM-5.2 國際站牌價（輸入） | D248: 1.4 | G248: USD／百萬 token | H248: 2026-10（現行） | I248: Z.ai 開發者文件 Pricing 頁（國際站官方牌價） | J248: https://docs.z.ai/guides/overview/pricing.md | K248: 2026-10-08 | L248: 2026-10-08 | M248: Verified | P248: 1 | Q248: 利害關係方 | R248: 公司公開且具約束力的報價，誤報誘因低 | S248: 一手 | T248: 官方表列 GLM-5.2：Input $1.4／Cached Input $0.26／Output $4.4；快取儲存「Limited-time free」；無長度分段 | U248: =IF(AND($D248="",$E248="",$F248=""),1,0) -> 0 | V248: =IF(OR($I248="",$I248="—"),1,0) -> 0 | W248: =IF(AND(ISNUMBER($D248),ISNUMBER($E248)),IF($E248>$D248,1,0),0)+IF(AND(ISNUMBER($D248),ISNUMBER($F248)),IF($D248>$F248,1,0),0)+IF(AND(ISNUMBER($E248),ISNUMBER($F248)),IF($E248>$F248,1,0),0) -> 0 | X248: CC 初評
A249: SRC_ZP_245 | B249: px_usd_glm52_cache | C249: GLM-5.2 國際站牌價（快取命中輸入） | D249: 0.26 | G249: USD／百萬 token | H249: 2026-10（現行） | I249: Z.ai 開發者文件 Pricing 頁（國際站官方牌價） | J249: https://docs.z.ai/guides/overview/pricing.md | K249: 2026-10-08 | L249: 2026-10-08 | M249: Verified | P249: 1 | Q249: 利害關係方 | R249: 公司公開且具約束力的報價，誤報誘因低 | S249: 一手 | T249: 官方表列 GLM-5.2：Input $1.4／Cached Input $0.26／Output $4.4；快取儲存「Limited-time free」；無長度分段 | U249: =IF(AND($D249="",$E249="",$F249=""),1,0) -> 0 | V249: =IF(OR($I249="",$I249="—"),1,0) -> 0 | W249: =IF(AND(ISNUMBER($D249),ISNUMBER($E249)),IF($E249>$D249,1,0),0)+IF(AND(ISNUMBER($D249),ISNUMBER($F249)),IF($D249>$F249,1,0),0)+IF(AND(ISNUMBER($E249),ISNUMBER($F249)),IF($E249>$F249,1,0),0) -> 0 | X249: CC 初評
A250: SRC_ZP_246 | B250: px_usd_glm52_out | C250: GLM-5.2 國際站牌價（輸出） | D250: 4.4 | G250: USD／百萬 token | H250: 2026-10（現行） | I250: Z.ai 開發者文件 Pricing 頁（國際站官方牌價） | J250: https://docs.z.ai/guides/overview/pricing.md | K250: 2026-10-08 | L250: 2026-10-08 | M250: Verified | P250: 1 | Q250: 利害關係方 | R250: 公司公開且具約束力的報價，誤報誘因低 | S250: 一手 | T250: 官方表列 GLM-5.2：Input $1.4／Cached Input $0.26／Output $4.4；快取儲存「Limited-time free」；無長度分段 | U250: =IF(AND($D250="",$E250="",$F250=""),1,0) -> 0 | V250: =IF(OR($I250="",$I250="—"),1,0) -> 0 | W250: =IF(AND(ISNUMBER($D250),ISNUMBER($E250)),IF($E250>$D250,1,0),0)+IF(AND(ISNUMBER($D250),ISNUMBER($F250)),IF($D250>$F250,1,0),0)+IF(AND(ISNUMBER($E250),ISNUMBER($F250)),IF($E250>$F250,1,0),0) -> 0 | X250: CC 初評
...

Sheet TK_Link
A1: TK_Link — Tokenomics 快照（第 0 層連結；不用 Excel 外部連結）
A2: 具名區（同 OpenAI v0.6 的 63 名：IF_／SRC_DEM_／L1_）：值（藍字）由 builder 從 Tokenomics master 的 model/CURRENT 讀出寫入。本模型公式只引用 TK_ 名稱或本頁儲存格。
A3: Tokenomics 檔案 | B3: 20261007_Tokenomics_v5.26.xlsx
A4: Tokenomics 版本 | B4: v5.26
A5: Tokenomics 提交 SHA（master） | B5: 3dd1216688e3872fcb80b28c279d8976a07df29b
A6: 讀取日期 | B6: 2026-10-08
I7: 世代 | J7: Hopper H100 | K7: Hopper H100 | L7: Hopper H100 | M7: GB200 NVL72 | N7: GB200 NVL72 | O7: GB200 NVL72 | P7: GB300 NVL72 | Q7: GB300 NVL72 | R7: GB300 NVL72 | S7: VR200 NVL72 | T7: VR200 NVL72 | U7: VR200 NVL72 | V7: Rubin Ultra（MGX NVL 單架，72 GPU） | W7: Rubin Ultra（MGX NVL 單架，72 GPU） | X7: Rubin Ultra（MGX NVL 單架，72 GPU）
I8: 成本情境 | J8: 低成本 | K8: 基準 | L8: 高成本 | M8: 低成本 | N8: 基準 | O8: 高成本 | P8: 低成本 | Q8: 基準 | R8: 高成本 | S8: 低成本 | T8: 基準 | U8: 高成本 | V8: 低成本 | W8: 基準 | X8: 高成本
A9: Tokenomics 名稱 | B9: 本模型名稱 | C9: 說明 | D9: 單位 | E9: 欄數 | F9: 狀態 | G9: Tokenomics 版本 | H9: 提交 SHA | I9: 讀取日期 | J9: 值1 | K9: 值2 | L9: 值3 | M9: 值4 | N9: 值5 | O9: 值6 | P9: 值7 | Q9: 值8 | R9: 值9 | S9: 值10 | T9: 值11 | U9: 值12 | V9: 值13 | W9: 值14 | X9: 值15
A10: IF_TokGW_Astra | B10: TK_IF_TokGW_Astra | C10: 每 GW 總產出（100%） | D10: M tok/年 | E10: 15 | F10: OK | G10: v5.26 | H10: 3dd1216 | I10: 2026-10-08 | J10: 3.8765183e+09 | K10: 3.8765183e+09 | L10: 3.8765183e+09 | M10: 2.0041839e+10 | N10: 2.0041839e+10 | O10: 2.0041839e+10 | P10: 2.4234238e+10 | Q10: 2.4234238e+10 | R10: 2.4234238e+10 | S10: 5.1167891e+10 | T10: 5.1167891e+10 | U10: 5.1167891e+10 | V10: 7.4400956e+10 | W10: 7.4400956e+10 | X10: 7.4400956e+10
A11: IF_TokGW_Luna | B11: TK_IF_TokGW_Luna | C11: 每 GW 總產出（100%） | D11: M tok/年 | E11: 15 | F11: OK | G11: v5.26 | H11: 3dd1216 | I11: 2026-10-08 | J11: 7.4067251e+10 | K11: 7.4067251e+10 | L11: 7.4067251e+10 | M11: 3.6230689e+11 | N11: 3.6230689e+11 | O11: 3.6230689e+11 | P11: 5.2747392e+11 | Q11: 5.2747392e+11 | R11: 5.2747392e+11 | S11: 7.727784e+11 | T11: 7.727784e+11 | U11: 7.727784e+11 | V11: 1.0443737e+12 | W11: 1.0443737e+12 | X11: 1.0443737e+12
A12: IF_TokGW_Sol | B12: TK_IF_TokGW_Sol | C12: 每 GW 總產出（100%） | D12: M tok/年 | E12: 15 | F12: OK | G12: v5.26 | H12: 3dd1216 | I12: 2026-10-08 | J12: 2.149043e+10 | K12: 2.149043e+10 | L12: 2.149043e+10 | M12: 1.041254e+11 | N12: 1.041254e+11 | O12: 1.041254e+11 | P12: 1.5159367e+11 | Q12: 1.5159367e+11 | R12: 1.5159367e+11 | S12: 2.3728734e+11 | T12: 2.3728734e+11 | U12: 2.3728734e+11 | V12: 3.2618567e+11 | W12: 3.2618567e+11 | X12: 3.2618567e+11
A13: IF_Util | B13: TK_IF_Util | C13: 基準利用率（第 0 層；下游可覆寫） | D13: % | E13: 1 | F13: OK | G13: v5.26 | H13: 3dd1216 | I13: 2026-10-08 | J13: 0.6
A14: IF_HoldEcon | B14: TK_IF_HoldEcon | C14: 每 GW 年持有成本 — 經濟口徑 | D14: $B/年 | E14: 15 | F14: OK | G14: v5.26 | H14: 3dd1216 | I14: 2026-10-08 | J14: 7.0000433 | K14: 10.095795 | L14: 17.405972 | M14: 6.813167 | N14: 9.1709819 | O14: 14.920029 | P14: 8.7074708 | Q14: 12.724746 | R14: 23.871869 | S14: 9.8366806 | T14: 12.762016 | U14: 20.678089 | V14: 10.452242 | W14: 16.069457 | X14: 29.454615
A15: IF_FullCost_Astra | B15: TK_IF_FullCost_Astra | C15: 全成本 $/M（服務＋快取儲存＋自下而上攤提；基準利用率） | D15: $/M | E15: 15 | F15: OK | G15: v5.26 | H15: 3dd1216 | I15: 2026-10-08 | J15: 6.9823234 | K15: 10.07014 | L15: 17.361579 | M15: 0.92982466 | N15: 1.2515294 | O15: 2.0359402 | P15: 0.93305227 | Q15: 1.3634219 | R15: 2.5576103 | S15: 0.42538461 | T15: 0.55182355 | U15: 0.89397238 | V15: 0.27809403 | W15: 0.42742659 | X15: 0.78326839
A16: IF_FullCost_Luna | B16: TK_IF_FullCost_Luna | C16: 全成本 $/M（服務＋快取儲存＋自下而上攤提；基準利用率） | D16: $/M | E16: 15 | F16: OK | G16: v5.26 | H16: 3dd1216 | I16: 2026-10-08 | J16: 0.13332981 | K16: 0.19228981 | L16: 0.33151542 | M16: 0.02765365 | N16: 0.037219928 | O16: 0.060545328 | P16: 0.024207999 | Q16: 0.035371595 | R16: 0.066348304 | S16: 0.018368232 | T16: 0.023827547 | U16: 0.038600674 | V16: 0.014351218 | W16: 0.022057988 | X16: 0.04042231
A17: IF_FullCost_Sol | B17: TK_IF_FullCost_Sol | C17: 全成本 $/M（服務＋快取儲存＋自下而上攤提；基準利用率） | D17: $/M | E17: 15 | F17: OK | G17: v5.26 | H17: 3dd1216 | I17: 2026-10-08 | J17: 0.53191053 | K17: 0.76713986 | L17: 1.3226004 | M17: 0.10319199 | N17: 0.13889806 | O17: 0.22595995 | P17: 0.090371238 | Q17: 0.13205779 | R17: 0.2477295 | S17: 0.061571891 | T17: 0.079878216 | U17: 0.12941586 | V17: 0.046474526 | W17: 0.07144248 | X17: 0.13093816
A18: IF_PriceCached_Astra | B18: TK_IF_PriceCached_Astra | C18: 快取輸入 $/M — OpenAI 有效 | D18: $/M | E18: 1 | F18: OK | G18: v5.26 | H18: 3dd1216 | I18: 2026-10-08 | J18: 0.8
A19: IF_PriceCached_Luna | B19: TK_IF_PriceCached_Luna | C19: 快取輸入 $/M — OpenAI 有效 | D19: $/M | E19: 1 | F19: OK | G19: v5.26 | H19: 3dd1216 | I19: 2026-10-08 | J19: 0.008
A20: IF_PriceCached_Sol | B20: TK_IF_PriceCached_Sol | C20: 快取輸入 $/M — OpenAI 有效 | D20: $/M | E20: 1 | F20: OK | G20: v5.26 | H20: 3dd1216 | I20: 2026-10-08 | J20: 0.16
A21: IF_PriceFresh_Astra | B21: TK_IF_PriceFresh_Astra | C21: 新鮮輸入 $/M — OpenAI 有效 | D21: $/M | E21: 1 | F21: OK | G21: v5.26 | H21: 3dd1216 | I21: 2026-10-08 | J21: 8
A22: IF_PriceFresh_Luna | B22: TK_IF_PriceFresh_Luna | C22: 新鮮輸入 $/M — OpenAI 有效 | D22: $/M | E22: 1 | F22: OK | G22: v5.26 | H22: 3dd1216 | I22: 2026-10-08 | J22: 0.08
A23: IF_PriceFresh_Sol | B23: TK_IF_PriceFresh_Sol | C23: 新鮮輸入 $/M — OpenAI 有效 | D23: $/M | E23: 1 | F23: OK | G23: v5.26 | H23: 3dd1216 | I23: 2026-10-08 | J23: 1.6
A24: IF_PriceOut_Astra | B24: TK_IF_PriceOut_Astra | C24: 可見輸出 $/M — OpenAI 有效 | D24: $/M | E24: 1 | F24: OK | G24: v5.26 | H24: 3dd1216 | I24: 2026-10-08 | J24: 40
A25: IF_PriceOut_Luna | B25: TK_IF_PriceOut_Luna | C25: 可見輸出 $/M — OpenAI 有效 | D25: $/M | E25: 1 | F25: OK | G25: v5.26 | H25: 3dd1216 | I25: 2026-10-08 | J25: 0.4
A26: IF_PriceOut_Sol | B26: TK_IF_PriceOut_Sol | C26: 可見輸出 $/M — OpenAI 有效 | D26: $/M | E26: 1 | F26: OK | G26: v5.26 | H26: 3dd1216 | I26: 2026-10-08 | J26: 8
A27: IF_PriceRef_Astra | B27: TK_IF_PriceRef_Astra | C27: 參考請求混合 $/M — OpenAI 有效 | D27: $/M | E27: 1 | F27: OK | G27: v5.26 | H27: 3dd1216 | I27: 2026-10-08 | J27: 8.0355556
A28: IF_PriceRef_Luna | B28: TK_IF_PriceRef_Luna | C28: 參考請求混合 $/M — OpenAI 有效 | D28: $/M | E28: 1 | F28: OK | G28: v5.26 | H28: 3dd1216 | I28: 2026-10-08 | J28: 0.080355556
A29: IF_PriceRef_Sol | B29: TK_IF_PriceRef_Sol | C29: 參考請求混合 $/M — OpenAI 有效 | D29: $/M | E29: 1 | F29: OK | G29: v5.26 | H29: 3dd1216 | I29: 2026-10-08 | J29: 1.6071111
... A35: IF_FrontRef_Sol | B35: TK_IF_FrontRef_Sol | C35: 參考請求混合 $/M — 前緣有效 | D35: $/M | E35: 1 | F35: OK | G35: v5.26 | H35: 3dd1216 | I35: 2026-10-08 | J35: 1.6071111
A36: IF_ProgGWyr_Astra | B36: TK_IF_ProgGWyr_Astra | C36: 研發計畫占 1 GW 一年 | D36: % | E36: 15 | F36: OK | G36: v5.26 | H36: 3dd1216 | I36: 2026-10-08 | J36: 0.14267939 | K36: 0.14267939 | L36: 0.14267939 | M36: 0.07039759 | N36: 0.07039759 | O36: 0.07039759 | P36: 0.065586407 | Q36: 0.065586407 | R36: 0.065586407 | S36: 0.040017843 | T36: 0.040017843 | U36: 0.040017843 | V36: 0.027250415 | W36: 0.027250415 | X36: 0.027250415
A37: IF_ProgGWyr_Luna | B37: TK_IF_ProgGWyr_Luna | C37: 研發計畫占 1 GW 一年 | D37: % | E37: 15 | F37: OK | G37: v5.26 | H37: 3dd1216 | I37: 2026-10-08 | J37: 0.0081323583 | K37: 0.0081323583 | L37: 0.0081323583 | M37: 0.0037853004 | N37: 0.0037853004 | O37: 0.0037853004 | P37: 0.0033289655 | Q37: 0.0033289655 | R37: 0.0033289655 | S37: 0.0022043397 | T37: 0.0022043397 | U37: 0.0022043397 | V37: 0.0014304485 | W37: 0.0014304485 | X37: 0.0014304485
A38: IF_ProgGWyr_Sol | B38: TK_IF_ProgGWyr_Sol | C38: 研發計畫占 1 GW 一年 | D38: % | E38: 15 | F38: OK | G38: v5.26 | H38: 3dd1216 | I38: 2026-10-08 | J38: 0.023146292 | K38: 0.023146292 | L38: 0.023146292 | M38: 0.011197547 | N38: 0.011197547 | O38: 0.011197547 | P38: 0.010227304 | Q38: 0.010227304 | R38: 0.010227304 | S38: 0.006421121 | T38: 0.006421121 | U38: 0.006421121 | V38: 0.0043094856 | W38: 0.0043094856 | X38: 0.0043094856
A39: IF_RDMult | B39: TK_IF_RDMult | C39: 研發倍數（第 0 層基準；下游可覆寫） | D39: x | E39: 1 | F39: OK | G39: v5.26 | H39: 3dd1216 | I39: 2026-10-08 | J39: 8
A40: IF_TrainGenDefault | B40: TK_IF_TrainGenDefault | C40: 下游預設訓練世代（索引；J13） | D40: 索引 | E40: 1 | F40: OK | G40: v5.26 | H40: 3dd1216 | I40: 2026-10-08 | J40: 4
A41: SRC_DEM_004 | B41: TK_SRC_DEM_004 | C41: OpenAI 2025 推論支出（年度） | D41: $B | E41: 1 | F41: OK | G41: v5.26 | H41: 3dd1216 | I41: 2026-10-08 | J41: 8.4
A42: SRC_DEM_005 | B42: TK_SRC_DEM_005 | C42: OpenAI 2025 非付費用戶推論支出（年度） | D42: $B | E42: 1 | F42: OK | G42: v5.26 | H42: 3dd1216 | I42: 2026-10-08 | J42: 3.9
A43: SRC_DEM_006 | B43: TK_SRC_DEM_006 | C43: OpenAI 2025 訓練支出（年度；約值） | D43: $B | E43: 1 | F43: OK | G43: v5.26 | H43: 3dd1216 | I43: 2026-10-08 | J43: 12
A44: SRC_DEM_007 | B44: TK_SRC_DEM_007 | C44: OpenAI 2025 營收（年度） | D44: $B | E44: 1 | F44: OK | G44: v5.26 | H44: 3dd1216 | I44: 2026-10-08 | J44: 13.07
A45: SRC_DEM_008 | B45: TK_SRC_DEM_008 | C45: OpenAI 算力規模 2024 年底（GW 口徑未明（D1）） | D45: GW | E45: 1 | F45: OK | G45: v5.26 | H45: 3dd1216 | I45: 2026-10-08 | J45: 0.6
A46: SRC_DEM_009 | B46: TK_SRC_DEM_009 | C46: OpenAI 算力規模 2025 年底（約值；口徑未明） | D46: GW | E46: 1 | F46: OK | G46: v5.26 | H46: 3dd1216 | I46: 2026-10-08 | J46: 1.9
A47: SRC_DEM_010 | B47: TK_SRC_DEM_010 | C47: OpenAI API 處理量（時點值；API 全部） | D47: B tok/min | E47: 1 | F47: OK | G47: v5.26 | H47: 3dd1216 | I47: 2026-10-08 | J47: 6
A48: SRC_DEM_011 | B48: TK_SRC_DEM_011 | C48: OpenAI API 處理量（時點值；「超過」；API 全部） | D48: B tok/min | E48: 1 | F48: OK | G48: v5.26 | H48: 3dd1216 | I48: 2026-10-08 | J48: 15
A49: SRC_DEM_012 | B49: TK_SRC_DEM_012 | C49: ChatGPT 每日提示數（全球；其中美國約 0.33B） | D49: B 則/日 | E49: 1 | F49: OK | G49: v5.26 | H49: 3dd1216 | I49: 2026-10-08 | J49: 2.5
A50: SRC_DEM_013 | B50: TK_SRC_DEM_013 | C50: 前沿實驗室（OpenAI）每日 token（由算力推估） | D50: T tok/日 | E50: 1 | F50: OK | G50: v5.26 | H50: 3dd1216 | I50: 2026-10-08
A51: SRC_DEM_013_Lo | B51: TK_SRC_DEM_013_Lo | C51: 前沿實驗室（OpenAI）每日 token（由算力推估） | D51: T tok/日 | E51: 1 | F51: OK | G51: v5.26 | H51: 3dd1216 | I51: 2026-10-08 | J51: 10
A52: SRC_DEM_013_Hi | B52: TK_SRC_DEM_013_Hi | C52: 前沿實驗室（OpenAI）每日 token（由算力推估） | D52: T tok/日 | E52: 1 | F52: OK | G52: v5.26 | H52: 3dd1216 | I52: 2026-10-08 | J52: 100
A53: IF_AllocQ1 | B53: TK_IF_AllocQ1 | C53: 研發算力占比 Q1（R1：研發 GW ÷ 研發＋服務 GW） | D53: % | E53: 1 | F53: OK | G53: v5.26 | H53: 3dd1216 | I53: 2026-10-08 | J53: 0.63609602
A54: IF_AllocQ1_R2 | B54: TK_IF_AllocQ1_R2 | C54: 研發算力占比 Q1（R2：免費服務算作產品改良） | D54: % | E54: 1 | F54: OK | G54: v5.26 | H54: 3dd1216 | I54: 2026-10-08 | J54: 0.66722015
A55: IF_AllocQ2 | B55: TK_IF_AllocQ2 | C55: 研發算力成本占比 Q2（已裝 GW × 各世代每 GW 年持有成本；利用率不進入） | D55: % | E55: 1 | F55: OK | G55: v5.26 | H55: 3dd1216 | I55: 2026-10-08 | J55: 0.66355656
A56: IF_AllocServeGW | B56: TK_IF_AllocServeGW | C56: 服務 GW 合計（token 路線；付費＋免費；IT 關鍵電力） | D56: GW | E56: 1 | F56: OK | G56: v5.26 | H56: 3dd1216 | I56: 2026-10-08 | J56: 0.051879785
A57: IF_AllocRDGW | B57: TK_IF_AllocRDGW | C57: 研發 GW 年（k ×（N_major × 家族＋N_refresh × 改版）；訓練世代＝IF_TrainGenDefault） | D57: GW·年 | E57: 1 | F57: OK | G57: v5.26 | H57: 3dd1216 | I57: 2026-10-08 | J57: 0.090684704
A58: IF_AllocDemand | B58: TK_IF_AllocDemand | C58: 需求 D 合計（API＋ChatGPT；付費＋免費 token；2025） | D58: M tok/年 | E58: 1 | F58: OK | G58: v5.26 | H58: 3dd1216 | I58: 2026-10-08 | J58: 4190200000
A59: IF_AllocImpliedNk | B59: TK_IF_AllocImpliedNk | C59: 隱含 N × k（2025 支出比反推；以家族計畫當量；A3） | D59: 個 | E59: 1 | F59: OK | G59: v5.26 | H59: 3dd1216 | I59: 2026-10-08 | J59: 1.5236214
A60: IF_TrainCost_Astra | B60: TK_IF_TrainCost_Astra | C60: 最終訓練成本 — 經濟（依成本情境） | D60: $M | E60: 15 | F60: OK | G60: v5.26 | H60: 3dd1216 | I60: 2026-10-08 | J60: 124.84524 | K60: 180.05774 | L60: 310.43419 | M60: 59.953817 | N60: 80.701878 | O60: 131.29176 | P60: 71.386466 | Q60: 104.3213 | R60: 195.70877 | S60: 49.205343 | T60: 63.838544 | U60: 103.43657 | V60: 35.60349 | W60: 54.737419 | X60: 100.33131
A61: IF_TrainCost_Luna | B61: TK_IF_TrainCost_Luna | C61: 最終訓練成本 — 經濟（依成本情境） | D61: $M | E61: 15 | F61: OK | G61: v5.26 | H61: 3dd1216 | I61: 2026-10-08 | J61: 7.1158576 | K61: 10.262828 | L61: 17.69395 | M61: 3.2237355 | N61: 4.3393652 | O61: 7.0595988 | P61: 3.6233587 | Q61: 5.2950302 | R61: 9.9335787 | S61: 2.7104232 | T61: 3.5164772 | U61: 5.6976916 | V61: 1.8689242 | W61: 2.8733163 | X61: 5.2666638
A62: IF_TrainCost_Sol | B62: TK_IF_TrainCost_Sol | C62: 最終訓練成本 — 經濟（依成本情境） | D62: $M | E62: 15 | F62: OK | G62: v5.26 | H62: 3dd1216 | I62: 2026-10-08 | J62: 20.253131 | K62: 29.210028 | L62: 50.360464 | M62: 9.5363448 | N62: 12.836563 | O62: 20.883466 | P62: 11.131744 | Q62: 16.267482 | R62: 30.51811 | S62: 7.8953145 | T62: 10.243306 | U62: 16.597064 | V62: 5.630473 | W62: 8.6563864 | X62: 15.86678
A63: IF_RevGW_Astra | B63: TK_IF_RevGW_Astra | C63: 每 GW 理論營收 — OpenAI 有效單價（理想上限） | D63: $B/年 | E63: 15 | F63: OK | G63: v5.26 | H63: 3dd1216 | I63: 2026-10-08 | J63: 18.689987 | K63: 18.689987 | L63: 18.689987 | M63: 96.628385 | N63: 96.628385 | O63: 96.628385 | P63: 116.84134 | Q63: 116.84134 | R63: 116.84134 | S63: 246.69746 | T63: 246.69746 | U63: 246.69746 | V63: 358.71181 | W63: 358.71181 | X63: 358.71181
A64: IF_RevGW_Luna | B64: TK_IF_RevGW_Luna | C64: 每 GW 理論營收 — OpenAI 有效單價（理想上限） | D64: $B/年 | E64: 15 | F64: OK | G64: v5.26 | H64: 3dd1216 | I64: 2026-10-08 | J64: 3.5710291 | K64: 3.5710291 | L64: 3.5710291 | M64: 17.468023 | N64: 17.468023 | O64: 17.468023 | P64: 25.431276 | Q64: 25.431276 | R64: 25.431276 | S64: 37.258223 | T64: 37.258223 | U64: 37.258223 | V64: 50.352738 | W64: 50.352738 | X64: 50.352738
A65: IF_RevGW_Sol | B65: TK_IF_RevGW_Sol | C65: 每 GW 理論營收 — OpenAI 有效單價（理想上限） | D65: $B/年 | E65: 15 | F65: OK | G65: v5.26 | H65: 3dd1216 | I65: 2026-10-08 | J65: 20.722505 | K65: 20.722505 | L65: 20.722505 | M65: 100.40465 | N65: 100.40465 | O65: 100.40465 | P65: 146.17673 | Q65: 146.17673 | R65: 146.17673 | S65: 228.80827 | T65: 228.80827 | U65: 228.80827 | V65: 314.52997 | W65: 314.52997 | X65: 314.52997
A66: IF_FullCostDefault_Astra | B66: TK_IF_FullCostDefault_Astra | C66: 全成本 $/M（服務＋快取儲存＋K6 預設攤提；基準利用率；下游預設） | D66: $/M | E66: 15 | F66: OK | G66: v5.26 | H66: 3dd1216 | I66: 2026-10-08 | J66: 12.125949 | K66: 17.488224 | L66: 30.150469 | M66: 2.4787428 | N66: 3.3362463 | O66: 5.4270923 | P66: 2.5035913 | Q66: 3.6582184 | R66: 6.862074 | S66: 1.4363673 | T66: 1.8632734 | U66: 3.0184984 | V66: 1.0697411 | W66: 1.6441809 | X66: 3.0130029
A67: IF_FullCostDefault_Luna | B67: TK_IF_FullCostDefault_Luna | C67: 全成本 $/M（服務＋快取儲存＋K6 預設攤提；基準利用率；下游預設） | D67: $/M | E67: 15 | F67: OK | G67: v5.26 | H67: 3dd1216 | I67: 2026-10-08 | J67: 0.14312525 | K67: 0.20641669 | L67: 0.35587038 | M67: 0.030515905 | N67: 0.041072288 | O67: 0.066811858 | P67: 0.026689888 | Q67: 0.038998013 | R67: 0.073150556 | S67: 0.020467808 | T67: 0.026551124 | U67: 0.043012821 | V67: 0.015974716 | W67: 0.02455329 | X67: 0.044995017
A68: IF_FullCostDefault_Sol | B68: TK_IF_FullCostDefault_Sol | C68: 全成本 $/M（服務＋快取儲存＋K6 預設攤提；基準利用率；下游預設） | D68: $/M | E68: 15 | F68: OK | G68: v5.26 | H68: 3dd1216 | I68: 2026-10-08 | J68: 0.65231102 | K68: 0.94078019 | L68: 1.621959 | M68: 0.13922176 | N68: 0.18739118 | O68: 0.30484239 | P68: 0.12451033 | Q68: 0.1819402 | R68: 0.34129642 | S68: 0.086330412 | T68: 0.11199505 | U68: 0.18144457 | V68: 0.06588753 | W68: 0.10128009 | X68: 0.18561637
A69: L1_Ans3 | B69: TK_L1_Ans3 | C69: 問 3：研發占整體成本 Q3（算力部分）（基準） | D69: $B/年 | E69: 1 | F69: OK | G69: v5.26 | H69: 3dd1216 | I69: 2026-10-08 | J69: 1.1573196
A70: L1_Ans3_Lo | B70: TK_L1_Ans3_Lo | C70: 問 3：研發占整體成本 Q3（算力部分）（低） | D70: $B/年 | E70: 1 | F70: OK | G70: v5.26 | H70: 3dd1216 | I70: 2026-10-08 | J70: 0.57865981
A71: L1_Ans3_Hi | B71: TK_L1_Ans3_Hi | C71: 問 3：研發占整體成本 Q3（算力部分）（高） | D71: $B/年 | E71: 1 | F71: OK | G71: v5.26 | H71: 3dd1216 | I71: 2026-10-08 | J71: 8.1012373
A72: IF_CapexTotal | B72: TK_IF_CapexTotal | C72: 每 GW 資本支出 — 合計 | D72: $B | E72: 15 | F72: OK | G72: v5.26 | H72: 3dd1216 | I72: 2026-10-08 | J72: 31.632269 | K72: 40.180214 | L72: 50.306743 | M72: 30.85139 | N72: 36.685174 | O72: 43.836204 | P72: 38.766902 | Q72: 50.115504 | R72: 67.136506 | S72: 43.485403 | T72: 50.256352 | U72: 58.823575 | V72: 46.057578 | W72: 62.75578 | X72: 81.667558
A73: （讀表）Cap_In!54 | B73: TK_RD_CapIn_GLM53 | C73: Cap_In F 表 GLM-5.3：新鮮輸入、快取輸入、輸出（國際站 $/M）、尖峰離峰、能力指數（Cap_In!E54，標籤『GLM-5.3』） | D73: $/M；指數 | E73: 5 | F73: 讀表（非具名） | G73: v5.26 | H73: 3dd1216 | I73: 2026-10-08 | J73: 1.4 | K73: 0.26 | L73: 4.4 | M73: 0 | N73: 45
A74: （讀表）Cap_In!55 | B74: TK_RD_CapIn_GLM53Flash | C74: Cap_In F 表 GLM-5.3-Flash：同上（Cap_In!E55，標籤『GLM-5.3-Flash』） | D74: $/M；指數 | E74: 5 | F74: 讀表（非具名） | G74: v5.26 | H74: 3dd1216 | I74: 2026-10-08 | J74: 0.15 | K74: 0.03 | L74: 0.5 | M74: 0 | N74: 42
A75: （讀表）Price_Frontier!14 | B75: TK_RD_PF_GLM53_Mix | C75: Price_Frontier A 表 GLM-5.3：參考請求混合單價（Luna、Sol、Astra 參考請求）（Price_Frontier!H14，標籤『GLM-5.3』） | D75: $/M | E75: 3 | F75: 讀表（非具名） | G75: v5.26 | H75: 3dd1216 | I75: 2026-10-08 | J75: 1.176 | K75: 1.176 | L75: 1.176
A76: （讀表）Price_Frontier!15 | B76: TK_RD_PF_GLM53Flash_Mix | C76: Price_Frontier A 表 GLM-5.3-Flash：同上（Price_Frontier!H15，標籤『GLM-5.3-Flash』） | D76: $/M | E76: 3 | F76: 讀表（非具名） | G76: v5.26 | H76: 3dd1216 | I76: 2026-10-08 | J76: 0.13022222 | K76: 0.13022222 | L76: 0.13022222
A77: （讀表）Price_Frontier!31 | B77: TK_RD_PF_ChinaFront | C77: Price_Frontier B 表：中國合格前緣混合單價（Luna、Sol、Astra；無合格者為文字）（Price_Frontier!C31，標籤『中國廠商 合格者最低 混合單價』） | D77: $/M | E77: 3 | F77: 讀表（非具名） | G77: v5.26 | H77: 3dd1216 | I77: 2026-10-08 | J77: 0.13022222 | K77: 無合格 | L77: 無合格
A78: （讀表）Price_Frontier!32 | B78: TK_RD_PF_ChinaFrontModel | C78: Price_Frontier B 表：中國合格前緣模型名（Luna、Sol、Astra）（Price_Frontier!C32，標籤『中國廠商 合格者最低 模型』） | D78: 文字 | E78: 3 | F78: 讀表（非具名） | G78: v5.26 | H78: 3dd1216 | I78: 2026-10-08 | J78: GLM-5.3-Flash | K78: — | L78: —
A79: （讀表）Price_Frontier!33 | B79: TK_RD_PF_ChinaVsOAI | C79: Price_Frontier B 表：中國合格前緣 ÷ OpenAI 層級模型（Luna、Sol、Astra）（Price_Frontier!C33，標籤『中國合格者最低 ÷ OpenAI 層級模型』） | D79: x | E79: 3 | F79: 讀表（非具名） | G79: v5.26 | H79: 3dd1216 | I79: 2026-10-08 | J79: 1.2964602 | K79: — | L79: —

Sheet OAI_Link
A1: OAI_Link — OpenAI v0.6 命題輸出快照（美元；只被 Checks 與 HTML 引用，規格 D26）
A2: 值（藍字）由 builder 從 OpenAI v0.6 Excel 的具名範圍讀出（LibreOffice 重算後快取值）。本頁不參與任何計算；test_builder 掃描其他頁公式不得含 OAI_。
A3: OpenAI Excel 檔案 | B3: 20261008_OpenAI_v0.6.xlsx
A4: SHA-256 | B4: 34fc34a7ea2c18e8f608356ca462d8bd208496ca61780589b559fd2efc6597fe
A5: 來源分支與提交 | B5: claude/openai-s6-release@e91df57
A6: 讀取日期 | B6: 2026-10-08
A9: OpenAI 名稱 | B9: 本模型名稱 | C9: 說明 | D9: 單位 | E9: 狀態 | F9: 2025 | G9: 2026 | H9: 2027 | I9: 2028 | J9: 2029 | K9: 2030
A10: REV_Gross | B10: OAI_REV_Gross | C10: 營收總額（未截頂） | D10: $B | E10: OK | F10: 13.07 | G10: 34.203781 | H10: 54.795653 | I10: 78.424089 | J10: 102.12737 | K10: 126.38309
A11: REV_NetCapped | B11: OAI_REV_NetCapped | C11: 營收淨額（容量截頂後） | D11: $B | E11: OK | F11: 10.456 | G11: 27.363025 | H11: 43.836523 | I11: 62.739271 | J11: 97.612079 | K11: 126.38309
A12: DEM_Tok_Total | B12: OAI_DEM_Tok_Total | C12: token 合計（付費＋免費） | D12: T | E12: OK | F12: 3538.0601 | G12: 10018.624 | H12: 22447.299 | I12: 47137.552 | J12: 92412.32 | K12: 173673.87
A13: CMP_InfGW_Eff | B13: OAI_CMP_InfGW_Eff | C13: 有效推論 GW | D13: GW | E13: OK | F13: 0.7 | G13: 0.69567332 | H13: 1.0429667 | I13: 1.7703734 | J13: 3.1650072 | K13: 5.5973071
A14: CMP_Supply_VReq | B14: OAI_CMP_Supply_VReq | C14: 供給 VR 等值 GW | D14: GW | E14: OK | F14: 0.28264462 | G14: 1.1565252 | H14: 5.7520321 | I14: 8.9411774 | J14: 12.146409 | K14: 14.944726
A15: COST_Compute | B15: OAI_COST_Compute | C15: 算力成本（現金） | D15: $B | E15: OK | F15: 14.755238 | G15: 53.240635 | H15: 141.72603 | I15: 175.21143 | J15: 208.69683 | K15: 228.22222
A16: COST_FullCash | B16: OAI_COST_FullCash | C16: 全成本（現金，含股權報酬） | D16: $B | E16: OK | F16: 29.235238 | G16: 76.078955 | H16: 171.94384 | I16: 212.1254 | J16: 251.9209 | K16: 276.64452
A17: COST_PropRev_VR | B17: OAI_COST_PropRev_VR | C17: 每 VR 等值 GW 營收淨額 | D17: $B/GW | E17: OK | F17: 36.993451 | G17: 23.659688 | H17: 7.6210498 | I17: 7.0168914 | J17: 8.0362912 | K17: 8.456702
A18: COST_PropFull_VR | B18: OAI_COST_PropFull_VR | C18: 每 VR 等值 GW 全成本 | D18: $B/GW | E18: OK | F18: 103.43462 | G18: 65.782359 | H18: 29.892713 | I18: 23.724549 | J18: 20.740361 | K18: 18.511181
A19: COST_PropGap_VR | B19: OAI_COST_PropGap_VR | C19: 每 VR 等值 GW 差額（命題 1） | D19: $B/GW | E19: OK | F19: -66.441166 | G19: -42.122671 | H19: -22.271663 | I19: -16.707658 | J19: -12.704069 | K19: -10.054479
A20: COST_Coverage | B20: OAI_COST_Coverage | C20: 覆蓋率（營收 ÷ 全成本） | D20: 比例 | E20: OK | F20: 0.35765058 | G20: 0.35966615 | H20: 0.25494674 | I20: 0.29576501 | J20: 0.38747114 | K20: 0.45684293
A21: FND_FCF | B21: OAI_FND_FCF | C21: 自由現金流 | D21: $B | E21: OK | F21: -12.779238 | G21: -39.41593 | H21: -116.01732 | I21: -134.87813 | J21: -137.62462 | K21: -131.90881
A22: FND_ExtNeed | B22: OAI_FND_ExtNeed | C22: 外部資金需求（單年） | D22: $B | E22: OK | G22: 0 | H22: 38.433249 | I22: 134.87813 | J22: 137.62462 | K22: 131.90881
A23: FND_ExtNeedCum | B23: OAI_FND_ExtNeedCum | C23: 累計外部資金需求（命題 2） | D23: $B | E23: OK | G23: 0 | H23: 38.433249 | I23: 173.31138 | J23: 310.936 | K23: 442.84481

Sheet Inputs
A1: Inputs — 假設輸入（藍字）：值、低、高、標記、依據、區間理由；匯率與單位換算定義常數（D23、E6）
A2: 長表格式：一列一個參數（× 索引）。來源 data/zhipu_inputs.yaml；INP_nnn 由 builder/id_registry.json 依鍵發出，穩定不重用。
A3: Analogy 寫明參照（如『OpenAI v0.6 INP_nnn』）與差異；Assumed 寫明依據；兩者一律給區間。Decision＝定義常數或規格決策（低＝值＝高）。
A4: INP_ID | B4: 鍵（key） | C4: 參數 | D4: 索引 | E4: 單位 | F4: 值 | G4: 低 | H4: 高 | I4: 標記 | J4: 依據 | K4: 區間理由 | L4: 區間順序異常（公式） | M4: Analogy／Assumed 缺區間（公式）
A5: INP_001 | B5: year_2025 | C5: 模型年度 | D5: 第 1 年 | E5: 年 | F5: 2025 | G5: 2025 | H5: 2025 | I5: Decision | J5: 曆年制，2025 為實際校準年（規格 D1、D14） | K5: 定義 | L5: =IF(AND(ISNUMBER($F5),ISNUMBER($G5),ISNUMBER($H5)),IF(AND($G5<=$F5,$F5<=$H5),0,1),0) -> 0 | M5: =IF(AND(OR($I5="Analogy",$I5="Assumed"),OR($G5="",$H5="")),1,0) -> 0
A6: INP_002 | B6: year_2026 | C6: 模型年度 | D6: 第 2 年 | E6: 年 | F6: 2026 | G6: 2026 | H6: 2026 | I6: Decision | J6: 2026＝1H26 實際＋2H26 驅動（D14） | K6: 定義 | L6: =IF(AND(ISNUMBER($F6),ISNUMBER($G6),ISNUMBER($H6)),IF(AND($G6<=$F6,$F6<=$H6),0,1),0) -> 0 | M6: =IF(AND(OR($I6="Analogy",$I6="Assumed"),OR($G6="",$H6="")),1,0) -> 0
A7: INP_003 | B7: year_2027 | C7: 模型年度 | D7: 第 3 年 | E7: 年 | F7: 2027 | G7: 2027 | H7: 2027 | I7: Decision | J7: 定義 | K7: 定義 | L7: =IF(AND(ISNUMBER($F7),ISNUMBER($G7),ISNUMBER($H7)),IF(AND($G7<=$F7,$F7<=$H7),0,1),0) -> 0 | M7: =IF(AND(OR($I7="Analogy",$I7="Assumed"),OR($G7="",$H7="")),1,0) -> 0
A8: INP_004 | B8: year_2028 | C8: 模型年度 | D8: 第 4 年 | E8: 年 | F8: 2028 | G8: 2028 | H8: 2028 | I8: Decision | J8: 定義 | K8: 定義 | L8: =IF(AND(ISNUMBER($F8),ISNUMBER($G8),ISNUMBER($H8)),IF(AND($G8<=$F8,$F8<=$H8),0,1),0) -> 0 | M8: =IF(AND(OR($I8="Analogy",$I8="Assumed"),OR($G8="",$H8="")),1,0) -> 0
A9: INP_005 | B9: year_2029 | C9: 模型年度 | D9: 第 5 年 | E9: 年 | F9: 2029 | G9: 2029 | H9: 2029 | I9: Decision | J9: 定義 | K9: 定義 | L9: =IF(AND(ISNUMBER($F9),ISNUMBER($G9),ISNUMBER($H9)),IF(AND($G9<=$F9,$F9<=$H9),0,1),0) -> 0 | M9: =IF(AND(OR($I9="Analogy",$I9="Assumed"),OR($G9="",$H9="")),1,0) -> 0
A10: INP_006 | B10: year_2030 | C10: 模型年度 | D10: 第 6 年 | E10: 年 | F10: 2030 | G10: 2030 | H10: 2030 | I10: Decision | J10: 定義 | K10: 定義 | L10: =IF(AND(ISNUMBER($F10),ISNUMBER($G10),ISNUMBER($H10)),IF(AND($G10<=$F10,$F10<=$H10),0,1),0) -> 0 | M10: =IF(AND(OR($I10="Analogy",$I10="Assumed"),OR($G10="",$H10="")),1,0) -> 0
A11: INP_007 | B11: days_year | C11: 每年天數（定義常數） | D11: — | E11: 天 | F11: 365 | G11: 365 | H11: 365 | I11: Decision | J11: 同 OpenAI v0.6 INP_251 | K11: 定義 | L11: =IF(AND(ISNUMBER($F11),ISNUMBER($G11),ISNUMBER($H11)),IF(AND($G11<=$F11,$F11<=$H11),0,1),0) -> 0 | M11: =IF(AND(OR($I11="Analogy",$I11="Assumed"),OR($G11="",$H11="")),1,0) -> 0
A12: INP_008 | B12: days_1h26 | C12: 2026 上半年天數（定義常數） | D12: 1H2026 | E12: 天 | F12: 181 | G12: 181 | H12: 181 | I12: Decision | J12: 2026-01-01～06-30 | K12: 定義 | L12: =IF(AND(ISNUMBER($F12),ISNUMBER($G12),ISNUMBER($H12)),IF(AND($G12<=$F12,$F12<=$H12),0,1),0) -> 0 | M12: =IF(AND(OR($I12="Analogy",$I12="Assumed"),OR($G12="",$H12="")),1,0) -> 0
A13: INP_009 | B13: days_2h26 | C13: 2026 下半年天數（定義常數） | D13: 2H2026 | E13: 天 | F13: 184 | G13: 184 | H13: 184 | I13: Decision | J13: 2026-07-01～12-31 | K13: 定義 | L13: =IF(AND(ISNUMBER($F13),ISNUMBER($G13),ISNUMBER($H13)),IF(AND($G13<=$F13,$F13<=$H13),0,1),0) -> 0 | M13: =IF(AND(OR($I13="Analogy",$I13="Assumed"),OR($G13="",$H13="")),1,0) -> 0
A14: INP_010 | B14: months_year | C14: 每年月數（定義常數） | D14: — | E14: 月 | F14: 12 | G14: 12 | H14: 12 | I14: Decision | J14: 同 OpenAI v0.6 INP_252 | K14: 定義 | L14: =IF(AND(ISNUMBER($F14),ISNUMBER($G14),ISNUMBER($H14)),IF(AND($G14<=$F14,$F14<=$H14),0,1),0) -> 0 | M14: =IF(AND(OR($I14="Analogy",$I14="Assumed"),OR($G14="",$H14="")),1,0) -> 0
A15: INP_011 | B15: months_half | C15: 每半年月數（定義常數） | D15: — | E15: 月 | F15: 6 | G15: 6 | H15: 6 | I15: Decision | J15: 定義 | K15: 定義 | L15: =IF(AND(ISNUMBER($F15),ISNUMBER($G15),ISNUMBER($H15)),IF(AND($G15<=$F15,$F15<=$H15),0,1),0) -> 0 | M15: =IF(AND(OR($I15="Analogy",$I15="Assumed"),OR($G15="",$H15="")),1,0) -> 0
A16: INP_012 | B16: months_qtr | C16: 每季月數（定義常數） | D16: — | E16: 月 | F16: 3 | G16: 3 | H16: 3 | I16: Decision | J16: 國際站 Coding Plan 季付價換算每月 | K16: 定義 | L16: =IF(AND(ISNUMBER($F16),ISNUMBER($G16),ISNUMBER($H16)),IF(AND($G16<=$F16,$F16<=$H16),0,1),0) -> 0 | M16: =IF(AND(OR($I16="Analogy",$I16="Assumed"),OR($G16="",$H16="")),1,0) -> 0
... A77: INP_073 | B77: arr_warn | C77: ARR 對照 WARN 門檻（模型年化 ÷ 公司 ARR − 1 的絕對值） | D77: — | E77: 比例 | F77: 0.25 | G77: 0.25 | H77: 0.25 | I77: Decision | J77: 規格 D14r（WARN >25%） | K77: 規格 | L77: =IF(AND(ISNUMBER($F77),ISNUMBER($G77),ISNUMBER($H77)),IF(AND($G77<=$F77,$F77<=$H77),0,1),0) -> 0 | M77: =IF(AND(OR($I77="Analogy",$I77="Assumed"),OR($G77="",$H77="")),1,0) -> 0

Sheet Demand
A1: Demand — 需求：API 按量計費 token、GLM Coding Plan 訂閱者與 token、智譜清言（免費）token；輸出 DEM_Tok_*（層級 Sol／Luna × 付費／免費）
A2: 2025 與 1H26 為校準期：API 按量計費 token＝（開放平台及 API 實際營收 − Coding Plan 估計營收）÷ 組合有效單價（規格 D14；單價為驅動、token 為倒推）。2H26 起：任務數 ×（1＋成長）× 每任務 token ×（1＋成長）× 價格反應 (p/p前)^ε（D15）。本地化部署不耗智譜算力，不進本頁（D4）。
A3: token 單位 T＝10^12；Coding Plan 訂閱者單位萬人；清言用戶百萬人；任務數十億。容量上限於 Z3 接 Compute；本頁不截頂。
A5: 編號 | B5: 項目 | C5: 單位 | D5: 2025 | E5: 2026 | F5: 2027 | G5: 2028 | H5: 2029 | I5: 2030 | K5: 1H2026 | L5: 2H2026 | M5: 說明
B6: 年度 | D6: =INP_001 -> 2025 | E6: =INP_002 -> 2026 | F6: =INP_003 -> 2027 | G6: =INP_004 -> 2028 | H6: =INP_005 -> 2029 | I6: =INP_006 -> 2030 | K6: 1H2026（實際） | L6: 2H2026（驅動）
A7: 一、API 按量計費（開放平台及 API 扣除 Coding Plan）
A8: D01 | B8: 價格反應底數 p/p前（組合有效單價） | C8: 倍 | F8: =Revenue!F24/Revenue!L24 -> 0.8 | G8: =Revenue!G24/Revenue!F24 -> 0.8 | H8: =Revenue!H24/Revenue!G24 -> 0.8 | I8: =Revenue!I24/Revenue!H24 -> 0.8 | L8: =Revenue!L24/Revenue!K24 -> 1.2696313 | M8: 2H26＝2H26 ÷ 1H26；2027＝2027 ÷ 2H26（最新價格水準）；之後逐年
A9: D02 | B9: API 每任務 token | C9: K tok／任務 | D9: =INP_037 -> 20 | E9: =E11/E10 -> 20.316741 | F9: =E9*(1+INP_044)*F8^INP_046 -> 24.981867 | G9: =F9*(1+INP_044)*G8^INP_046 -> 30.718198 | H9: =G9*(1+INP_044)*H8^INP_046 -> 37.771704 | I9: =H9*(1+INP_044)*I8^INP_046 -> 46.444835 | K9: =INP_037 -> 20 | L9: =K9*(1+INP_039)*L8^INP_046 -> 20.479502 | M9: 校準期＝Inputs 基準（只影響任務數與每任務 token 的水準拆分，不影響營收）；2H26 起 ×（1＋成長）× 價格反應^ε（每任務 token）；2026 欄＝全年 token ÷ 全年任務
A10: D03 | B10: API 任務數 | C10: 十億 | D10: =D11/D9 -> 3.3230757 | E10: =K10+L10 -> 26.880458 | F10: =E10*(1+INP_040)*F8^INP_045 -> 56.56479 | G10: =F10*(1+INP_041)*G8^INP_045 -> 99.191498 | H10: =G10*(1+INP_042)*H8^INP_045 -> 156.54717 | I10: =H10*(1+INP_043)*I8^INP_045 -> 228.76641 | K10: =K11/K9 -> 9.1242437 | L10: =K10*(1+INP_038)*L8^INP_045 -> 17.756214 | M10: 校準期＝token ÷ 每任務 token；2H26＝1H26 ×（1＋半年成長）× 價格反應^ε；2027 起以 2026 全年為基期
A11: D04 | B11: API 按量計費 token | C11: T | D11: =Revenue!D44*INP_015/Revenue!D24 -> 66.461514 | E11: =K11+L11 -> 546.12331 | F11: =F10*F9 -> 1413.0941 | G11: =G10*G9 -> 3046.9841 | H11: =H10*H9 -> 5913.0535 | I11: =I10*I9 -> 10625.018 | K11: =Revenue!K44*INP_015/Revenue!K24 -> 182.48487 | L11: =L10*L9 -> 363.63844 | M11: 2025、1H26：按量計費營收（API 實際 − Coding Plan 估計）× 100 ÷ 組合有效單價（元／百萬 token；×100 為 Inputs 定義常數）；之後＝任務數 × 每任務 token
A12: D05 | B12: API 按量計費 token：Sol（GLM 旗艦） | C12: T | D12: =D11*Revenue!D22 -> 39.876908 | E12: =K12+L12 -> 382.28632 | F12: =F11*Revenue!F22 -> 989.16584 | G12: =G11*Revenue!G22 -> 2132.8888 | H12: =H11*Revenue!H22 -> 4139.1374 | I12: =I11*Revenue!I22 -> 7437.5125 | K12: =K11*Revenue!K22 -> 127.73941 | L12: =L11*Revenue!L22 -> 254.5469 | M12: token × 層級組合（Revenue）
A13: D06 | B13: API 按量計費 token：Luna（Air／Flash） | C13: T | D13: =D11*Revenue!D23 -> 26.584606 | E13: =K13+L13 -> 163.83699 | F13: =F11*Revenue!F23 -> 423.92822 | G13: =G11*Revenue!G23 -> 914.09522 | H13: =H11*Revenue!H23 -> 1773.916 | I13: =I11*Revenue!I23 -> 3187.5054 | K13: =K11*Revenue!K23 -> 54.745462 | L13: =L11*Revenue!L23 -> 109.09153 | M13: token × 層級組合（Revenue）
A14: D07 | B14: 免費 API 型號 token（Luna；耗算力無營收） | C14: T | D14: =D11*INP_047 -> 19.938454 | E14: =K14+L14 -> 163.83699 | F14: =F11*INP_047 -> 423.92822 | G14: =G11*INP_047 -> 914.09522 | H14: =H11*INP_047 -> 1773.916 | I14: =I11*INP_047 -> 3187.5054 | K14: =K11*INP_047 -> 54.745462 | L14: =L11*INP_047 -> 109.09153 | M14: GLM-4.7-Flash 等免費型號（SRC_ZP_333）＝付費 API token × Inputs 比例（D24r：免費型號單列）
A15: 二、GLM Coding Plan（訂閱者 × 每訂閱者 token；收入在開放平台及 API 內，D2r）
A16: D08 | B16: Coding Plan 付費訂閱者（期間平均） | C16: 萬人 | D16: =SRC_ZP_402*INP_049 -> 3.63 | E16: =(K16+L16)/INP_013 -> 30.25 | F16: =E16*(1+INP_051) -> 45.375 | G16: =F16*(1+INP_052) -> 58.9875 | H16: =G16*(1+INP_053) -> 70.785 | I16: =H16*(1+INP_054) -> 81.40275 | K16: =SRC_ZP_402*INP_048 -> 24.2 | L16: =K16*(1+INP_050) -> 36.3 | M16: 2025、1H26＝2026-03 付費開發者 24.2 萬（SRC_ZP_402）× Inputs 倍數（營收未單列，無法倒推；工作單：給區間）；2H26＝1H26 ×（1＋半年成長）；2026 欄＝兩個半年平均；2027 起 ×（1＋年增率）
A17: D09 | B17: Coding Plan 訂閱者：Lite | C17: 萬人 | D17: =D16*Revenue!D35 -> 2.178 | E17: =E16*Revenue!E35 -> 18.15 | F17: =F16*Revenue!F35 -> 27.225 | G17: =G16*Revenue!G35 -> 35.3925 | H17: =H16*Revenue!H35 -> 42.471 | I17: =I16*Revenue!I35 -> 48.84165 | K17: =K16*Revenue!K35 -> 14.52 | L17: =L16*Revenue!L35 -> 21.78 | M17: 訂閱者 × 方案組合（Revenue）
A18: D10 | B18: Coding Plan 訂閱者：Pro | C18: 萬人 | D18: =D16*Revenue!D36 -> 1.089 | E18: =E16*Revenue!E36 -> 9.075 | F18: =F16*Revenue!F36 -> 13.6125 | G18: =G16*Revenue!G36 -> 17.69625 | H18: =H16*Revenue!H36 -> 21.2355 | I18: =I16*Revenue!I36 -> 24.420825 | K18: =K16*Revenue!K36 -> 7.26 | L18: =L16*Revenue!L36 -> 10.89 | M18: 訂閱者 × 方案組合（Revenue）
A19: D11 | B19: Coding Plan 訂閱者：Max | C19: 萬人 | D19: =D16*Revenue!D37 -> 0.363 | E19: =E16*Revenue!E37 -> 3.025 | F19: =F16*Revenue!F37 -> 4.5375 | G19: =G16*Revenue!G37 -> 5.89875 | H19: =H16*Revenue!H37 -> 7.0785 | I19: =I16*Revenue!I37 -> 8.140275 | K19: =K16*Revenue!K37 -> 2.42 | L19: =L16*Revenue!L37 -> 3.63 | M19: 訂閱者 × 方案組合（Revenue）
A20: D12 | B20: 每訂閱者每日 token：Lite | C20: M tok／日 | D20: =SRC_ZP_376*INP_022*INP_060*INP_061*INP_062/INP_019 -> 20.16 | E20: =SRC_ZP_376*INP_022*INP_060*INP_061*INP_062/INP_019 -> 20.16 | F20: =SRC_ZP_376*INP_022*INP_060*INP_061*INP_062/INP_019 -> 20.16 | G20: =SRC_ZP_376*INP_022*INP_060*INP_061*INP_062/INP_019 -> 20.16 | H20: =SRC_ZP_376*INP_022*INP_060*INP_061*INP_062/INP_019 -> 20.16 | I20: =SRC_ZP_376*INP_022*INP_060*INP_061*INP_062/INP_019 -> 20.16 | K20: =SRC_ZP_376*INP_022*INP_060*INP_061*INP_062/INP_019 -> 20.16 | L20: =SRC_ZP_376*INP_022*INP_060*INP_061*INP_062/INP_019 -> 20.16 | M20: 每 5 小時額度（SRC_ZP_376–378）× 每日窗口數 × 額度使用率 × 每 prompt 呼叫次數 × 每次呼叫 token（K）÷ 1000
A21: D13 | B21: 每訂閱者每日 token：Pro | C21: M tok／日 | D21: =SRC_ZP_377*INP_022*INP_060*INP_061*INP_062/INP_019 -> 100.8 | E21: =SRC_ZP_377*INP_022*INP_060*INP_061*INP_062/INP_019 -> 100.8 | F21: =SRC_ZP_377*INP_022*INP_060*INP_061*INP_062/INP_019 -> 100.8 | G21: =SRC_ZP_377*INP_022*INP_060*INP_061*INP_062/INP_019 -> 100.8 | H21: =SRC_ZP_377*INP_022*INP_060*INP_061*INP_062/INP_019 -> 100.8 | I21: =SRC_ZP_377*INP_022*INP_060*INP_061*INP_062/INP_019 -> 100.8 | K21: =SRC_ZP_377*INP_022*INP_060*INP_061*INP_062/INP_019 -> 100.8 | L21: =SRC_ZP_377*INP_022*INP_060*INP_061*INP_062/INP_019 -> 100.8 | M21: 每 5 小時額度（SRC_ZP_376–378）× 每日窗口數 × 額度使用率 × 每 prompt 呼叫次數 × 每次呼叫 token（K）÷ 1000
A22: D14 | B22: 每訂閱者每日 token：Max | C22: M tok／日 | D22: =SRC_ZP_378*INP_022*INP_060*INP_061*INP_062/INP_019 -> 403.2 | E22: =SRC_ZP_378*INP_022*INP_060*INP_061*INP_062/INP_019 -> 403.2 | F22: =SRC_ZP_378*INP_022*INP_060*INP_061*INP_062/INP_019 -> 403.2 | G22: =SRC_ZP_378*INP_022*INP_060*INP_061*INP_062/INP_019 -> 403.2 | H22: =SRC_ZP_378*INP_022*INP_060*INP_061*INP_062/INP_019 -> 403.2 | I22: =SRC_ZP_378*INP_022*INP_060*INP_061*INP_062/INP_019 -> 403.2 | K22: =SRC_ZP_378*INP_022*INP_060*INP_061*INP_062/INP_019 -> 403.2 | L22: =SRC_ZP_378*INP_022*INP_060*INP_061*INP_062/INP_019 -> 403.2 | M22: 每 5 小時額度（SRC_ZP_376–378）× 每日窗口數 × 額度使用率 × 每 prompt 呼叫次數 × 每次呼叫 token（K）÷ 1000
A23: D15 | B23: Coding Plan token：Lite | C23: T | D23: =D17*D20*INP_007/INP_016 -> 160.26595 | E23: =K23+L23 -> 1337.745 | F23: =F17*F20*INP_007/INP_016 -> 2003.3244 | G23: =G17*G20*INP_007/INP_016 -> 2604.3217 | H23: =H17*H20*INP_007/INP_016 -> 3125.1861 | I23: =I17*I20*INP_007/INP_016 -> 3593.964 | K23: =K17*K20*INP_008/INP_016 -> 529.82899 | L23: =L17*L20*INP_009/INP_016 -> 807.91603 | M23: 訂閱者（萬）× 每日 token（M）× 天數 ÷ 100（萬 × M → T）
A24: D16 | B24: Coding Plan token：Pro | C24: T | D24: =D18*D21*INP_007/INP_016 -> 400.66488 | E24: =K24+L24 -> 3344.3626 | F24: =F18*F21*INP_007/INP_016 -> 5008.311 | G24: =G18*G21*INP_007/INP_016 -> 6510.8043 | H24: =H18*H21*INP_007/INP_016 -> 7812.9652 | I24: =I18*I21*INP_007/INP_016 -> 8984.9099 | K24: =K18*K21*INP_008/INP_016 -> 1324.5725 | L24: =L18*L21*INP_009/INP_016 -> 2019.7901 | M24: 訂閱者（萬）× 每日 token（M）× 天數 ÷ 100（萬 × M → T）
A25: D17 | B25: Coding Plan token：Max | C25: T | D25: =D19*D22*INP_007/INP_016 -> 534.21984 | E25: =K25+L25 -> 4459.1501 | F25: =F19*F22*INP_007/INP_016 -> 6677.748 | G25: =G19*G22*INP_007/INP_016 -> 8681.0724 | H25: =H19*H22*INP_007/INP_016 -> 10417.287 | I25: =I19*I22*INP_007/INP_016 -> 11979.88 | K25: =K19*K22*INP_008/INP_016 -> 1766.0966 | L25: =L19*L22*INP_009/INP_016 -> 2693.0534 | M25: 訂閱者（萬）× 每日 token（M）× 天數 ÷ 100（萬 × M → T）
A26: D18 | B26: Coding Plan token 合計 | C26: T | D26: =D23+D24+D25 -> 1095.1507 | E26: =E23+E24+E25 -> 9141.2577 | F26: =F23+F24+F25 -> 13689.383 | G26: =G23+G24+G25 -> 17796.198 | H26: =H23+H24+H25 -> 21355.438 | I26: =I23+I24+I25 -> 24558.754 | K26: =K23+K24+K25 -> 3620.4981 | L26: =L23+L24+L25 -> 5520.7596
A27: D19 | B27: Coding Plan token：Sol | C27: T | D27: =D26*INP_063 -> 985.6356 | E27: =E26*INP_063 -> 8227.1319 | F27: =F26*INP_063 -> 12320.445 | G27: =G26*INP_063 -> 16016.579 | H27: =H26*INP_063 -> 19219.894 | I27: =I26*INP_063 -> 22102.878 | K27: =K26*INP_063 -> 3258.4483 | L27: =L26*INP_063 -> 4968.6836 | M27: Coding Plan 以 GLM-5.x 旗艦為主（D24r）
A28: D20 | B28: Coding Plan token：Luna | C28: T | D28: =D26*(1-INP_063) -> 109.51507 | E28: =E26*(1-INP_063) -> 914.12577 | F28: =F26*(1-INP_063) -> 1368.9383 | G28: =G26*(1-INP_063) -> 1779.6198 | H28: =H26*(1-INP_063) -> 2135.5438 | I28: =I26*(1-INP_063) -> 2455.8754 | K28: =K26*(1-INP_063) -> 362.04981 | L28: =L26*(1-INP_063) -> 552.07596
A29: 三、智譜清言（C 端；無單列收入，免費 token 耗算力；年度）
A30: D21 | B30: 智譜清言月活用戶 | C30: 百萬人 | D30: =INP_064 -> 10 | E30: =D30*(1+INP_065) -> 11 | F30: =E30*(1+INP_065) -> 12.1 | G30: =F30*(1+INP_065) -> 13.31 | H30: =G30*(1+INP_065) -> 14.641 | I30: =H30*(1+INP_065) -> 16.1051 | M30: 2025 Inputs（QuestMobile 未進前 20，SRC_ZP_434；Assumed 區間）；之後 ×（1＋年增率）
A31: D22 | B31: 智譜清言 token | C31: T | D31: =D30*INP_066*INP_067*INP_007/INP_018 -> 10.95 | E31: =E30*INP_066*INP_067*INP_007/INP_018 -> 12.045 | F31: =F30*INP_066*INP_067*INP_007/INP_018 -> 13.2495 | G31: =G30*INP_066*INP_067*INP_007/INP_018 -> 14.57445 | H31: =H30*INP_066*INP_067*INP_007/INP_018 -> 16.031895 | I31: =I30*INP_066*INP_067*INP_007/INP_018 -> 17.635085 | M31: 用戶（百萬）× 每日任務 × 每任務 token（K）× 天數 ÷ 1000（百萬 × K → T）
A32: D23 | B32: 智譜清言 token：Sol | C32: T | D32: =D31*INP_068 -> 3.285 | E32: =E31*INP_068 -> 3.6135 | F32: =F31*INP_068 -> 3.97485 | G32: =G31*INP_068 -> 4.372335 | H32: =H31*INP_068 -> 4.8095685 | I32: =I31*INP_068 -> 5.2905254
A33: D24 | B33: 智譜清言 token：Luna | C33: T | D33: =D31*(1-INP_068) -> 7.665 | E33: =E31*(1-INP_068) -> 8.4315 | F33: =F31*(1-INP_068) -> 9.27465 | G33: =G31*(1-INP_068) -> 10.202115 | H33: =H31*(1-INP_068) -> 11.222326 | I33: =I31*(1-INP_068) -> 12.344559
A34: 四、輸出：token 量（層級 × 付費／免費；供 Z3 推論 GW）
A35: D25 | B35: 付費 token：Sol | C35: T | D35: =D12+D27 -> 1025.5125 | E35: =E12+E27 -> 8609.4182 | F35: =F12+F27 -> 13309.611 | G35: =G12+G27 -> 18149.467 | H35: =H12+H27 -> 23359.032 | I35: =I12+I27 -> 29540.391 | M35: API 按量計費 Sol ＋ Coding Plan Sol
A36: D26 | B36: 付費 token：Luna | C36: T | D36: =D13+D28 -> 136.09967 | E36: =E13+E28 -> 1077.9628 | F36: =F13+F28 -> 1792.8666 | G36: =G13+G28 -> 2693.7151 | H36: =H13+H28 -> 3909.4598 | I36: =I13+I28 -> 5643.3808 | M36: API 按量計費 Luna ＋ Coding Plan Luna
A37: D27 | B37: 免費 token：Sol | C37: T | D37: =D32 -> 3.285 | E37: =E32 -> 3.6135 | F37: =F32 -> 3.97485 | G37: =G32 -> 4.372335 | H37: =H32 -> 4.8095685 | I37: =I32 -> 5.2905254 | M37: 智譜清言 Sol
A38: D28 | B38: 免費 token：Luna | C38: T | D38: =D33+D14 -> 27.603454 | E38: =E33+E14 -> 172.26849 | F38: =F33+F14 -> 433.20287 | G38: =G33+G14 -> 924.29734 | H38: =H33+H14 -> 1785.1384 | I38: =I33+I14 -> 3199.8499 | M38: 智譜清言 Luna ＋ 免費 API 型號
A39: D29 | B39: 付費 token 合計 | C39: T | D39: =D35+D36 -> 1161.6122 | E39: =E35+E36 -> 9687.381 | F39: =F35+F36 -> 15102.477 | G39: =G35+G36 -> 20843.182 | H39: =H35+H36 -> 27268.492 | I39: =I35+I36 -> 35183.772
A40: D30 | B40: 免費 token 合計 | C40: T | D40: =D37+D38 -> 30.888454 | E40: =E37+E38 -> 175.88199 | F40: =F37+F38 -> 437.17772 | G40: =G37+G38 -> 928.66967 | H40: =H37+H38 -> 1789.9479 | I40: =I37+I38 -> 3205.1405
A41: D31 | B41: token 合計（付費＋免費） | C41: T | D41: =D39+D40 -> 1192.5006 | E41: =E39+E40 -> 9863.263 | F41: =F39+F40 -> 15539.655 | G41: =G39+G40 -> 21771.852 | H41: =H39+H40 -> 29058.439 | I41: =I39+I40 -> 38388.912
A42: 五、對照（只列差距，不校準）
A43: D32 | B43: 2H25→1H26 實際隱含量成長（營收倍數 ÷ 模型單價倍數） | C43: 倍 | K43: =(SRC_ZP_169/(SRC_ZP_112-SRC_ZP_170))/(Revenue!K24/Revenue!D24) -> 3.2409594 | M43: 開放平台及 API：1H26 ÷ 2H25（＝FY25 − 1H25）實際營收，除以 1H26 ÷ 2025 組合有效單價；Inputs 2H26 任務數成長的參考（實際值，非公司說法）
A44: D33 | B44: 模型 2H26 ÷ 1H26 API 按量計費 token | C44: 倍 | L44: =L11/K11 -> 1.9927045 | M44: 對照：公司稱 MaaS token 呼叫量『較年初 40 倍以上』（SRC_ZP_410；基期為年初時點，口徑不同）
A45: D34 | B45: 公司說法：MaaS token 呼叫量較年初倍數 | C45: 倍 | K45: =SRC_ZP_410 -> 40 | M45: Interested-party；只對照，不反推（D14r）
A46: D35 | B46: 模型 2025 token 合計 ÷ 天數 | C46: T／日 | D46: =D41/INP_007 -> 3.267125 | M46: 對照：招股章程 2025-11 日均 4.2T（SRC_ZP_413；口徑可能含全部雲端與免費）
A47: D36 | B47: 公司揭露：2025-11 日均 token | C47: T／日 | D47: =SRC_ZP_413 -> 4.2 | M47: Interested-party
A48: D37 | B48: 2025 計費比例＝API 按量計費 token ÷（日均 4.2T × 365） | C48: 比例 | D48: =D11/(SRC_ZP_413*INP_007) -> 0.04335389 | M48: 類比 OpenAI v0.6 DEM_ApiBilledRatio2025：揭露量多為免費、Coding Plan 與折扣流量

Sheet Revenue
A1: Revenue — 營收：①開放平台及 API（按量計費＋Coding Plan 子列）②企業級智能體 ③企業級通用大模型 ④技術服務及其他；總額＝淨額；雲端 vs 本地化、企業 vs 個人
A2: API 牌價：2025＝GLM-4.7／GLM-4.5-Air 牌價；1H26＝GLM-4.7→GLM-5→GLM-5.1 依發布日天數加權；2H26＝GLM-5.2／5.3（Sol）、GLM-4.5-Air→GLM-5.3-Flash（Luna）；2027 起 ×（1＋年變動率）。輸入價依長上下文占比混合兩檔。有效單價＝［(1−輸出占比)×(快取命中×快取價＋(1−快取命中)×輸入價)＋輸出占比×輸出價］×(1−折扣與免費額度)。
A3: 金額 RMB 億；牌價 元／百萬 token；Coding Plan 價格 元／月。②③④＝本地化部署分部（不耗智譜算力，D4、D2r）。容量上限暫以 Inputs 佔位 1（Z3 接 Compute），只回乘雲端營收。
A5: 編號 | B5: 項目 | C5: 單位 | D5: 2025 | E5: 2026 | F5: 2027 | G5: 2028 | H5: 2029 | I5: 2030 | K5: 1H2026 | L5: 2H2026 | M5: 說明
B6: 年度 | D6: =INP_001 -> 2025 | E6: =INP_002 -> 2026 | F6: =INP_003 -> 2027 | G6: =INP_004 -> 2028 | H6: =INP_005 -> 2029 | I6: =INP_006 -> 2030 | K6: 1H2026（實際） | L6: 2H2026（驅動）
A7: 一、價格期間權重（由發布日推得的天數；Inputs Derived）
A8: R01 | B8: 1H26 GLM-4.7 期間占比 | C8: 比例 | K8: =INP_026/INP_008 -> 0.2320442 | M8: 2026-01-01～02-11 ÷ 181 天
A9: R02 | B9: 1H26 GLM-5 期間占比 | C9: 比例 | K9: =INP_027/INP_008 -> 0.29834254 | M9: 2026-02-12～04-06 ÷ 181 天
A10: R03 | B10: 1H26 GLM-5.1 期間占比（＝1 − 前兩者） | C10: 比例 | K10: =(1-K8-K9) -> 0.46961326 | M10: 2026-04-07～06-30（GLM-5.2 於 06-16 發布，牌價同 GLM-5.1 ≥32K 檔）
A11: R04 | B11: 2H26 GLM-5.3-Flash 期間占比（Luna） | C11: 比例 | L11: =INP_028/INP_009 -> 0.69565217 | M11: 2026-08-26～12-31 ÷ 184 天；之前 Luna 以 GLM-4.5-Air 計
A12: 二、API 牌價（元／百萬 token；層級 × 輸入／快取／輸出）
A13: R05 | B13: Sol（GLM 旗艦） 輸入牌價 | C13: 元／M | D13: =(1-INP_025)*SRC_ZP_311+INP_025*SRC_ZP_314 -> 3.6 | E13: =(K13+L13)/INP_013 -> 6.8839779 | F13: =L13*(1+INP_035) -> 6.4 | G13: =F13*(1+INP_035) -> 5.12 | H13: =G13*(1+INP_035) -> 4.096 | I13: =H13*(1+INP_035) -> 3.2768 | K13: =K8*D13+K9*((1-INP_025)*SRC_ZP_302+INP_025*SRC_ZP_305)+K10*((1-INP_025)*SRC_ZP_290+INP_025*SRC_ZP_293) -> 5.7679558 | L13: =SRC_ZP_284 -> 8 | M13: 2025：GLM-4.7（<32K 且輸出 ≥0.2K 檔 與 32K–200K 檔，依長上下文占比混合）；1H26：期間加權 GLM-4.7／GLM-5／GLM-5.1；2H26：GLM-5.2／5.3 1M 全量；2027 起 ×（1＋年變動率）；2026 欄為兩個半年的平均（顯示用）
A14: R06 | B14: Sol（GLM 旗艦） 快取命中輸入牌價 | C14: 元／M | D14: =(1-INP_025)*SRC_ZP_312+INP_025*SRC_ZP_315 -> 0.72 | E14: =(K14+L14)/INP_013 -> 1.681326 | F14: =L14*(1+INP_035) -> 1.6 | G14: =F14*(1+INP_035) -> 1.28 | H14: =G14*(1+INP_035) -> 1.024 | I14: =H14*(1+INP_035) -> 0.8192 | K14: =K8*D14+K9*((1-INP_025)*SRC_ZP_303+INP_025*SRC_ZP_306)+K10*((1-INP_025)*SRC_ZP_291+INP_025*SRC_ZP_294) -> 1.3626519 | L14: =SRC_ZP_285 -> 2 | M14: 2025：GLM-4.7（<32K 且輸出 ≥0.2K 檔 與 32K–200K 檔，依長上下文占比混合）；1H26：期間加權 GLM-4.7／GLM-5／GLM-5.1；2H26：GLM-5.2／5.3 1M 全量；2027 起 ×（1＋年變動率）；2026 欄為兩個半年的平均（顯示用）
A15: R07 | B15: Sol（GLM 旗艦） 輸出牌價 | C15: 元／M | D15: =(1-INP_025)*SRC_ZP_313+INP_025*SRC_ZP_316 -> 15.2 | E15: =(K15+L15)/INP_013 -> 25.005525 | F15: =L15*(1+INP_035) -> 22.4 | G15: =F15*(1+INP_035) -> 17.92 | H15: =G15*(1+INP_035) -> 14.336 | I15: =H15*(1+INP_035) -> 11.4688 | K15: =K8*D15+K9*((1-INP_025)*SRC_ZP_304+INP_025*SRC_ZP_307)+K10*((1-INP_025)*SRC_ZP_292+INP_025*SRC_ZP_295) -> 22.01105 | L15: =SRC_ZP_286 -> 28 | M15: 2025：GLM-4.7（<32K 且輸出 ≥0.2K 檔 與 32K–200K 檔，依長上下文占比混合）；1H26：期間加權 GLM-4.7／GLM-5／GLM-5.1；2H26：GLM-5.2／5.3 1M 全量；2027 起 ×（1＋年變動率）；2026 欄為兩個半年的平均（顯示用）
A16: R08 | B16: Luna（Air／Flash） 輸入牌價 | C16: 元／M | D16: =(1-INP_025)*SRC_ZP_320+INP_025*SRC_ZP_323 -> 1.04 | E16: =(K16+L16)/INP_013 -> 0.95652174 | F16: =L16*(1+INP_036) -> 0.69843478 | G16: =F16*(1+INP_036) -> 0.55874783 | H16: =G16*(1+INP_036) -> 0.44699826 | I16: =H16*(1+INP_036) -> 0.35759861 | K16: =D16 -> 1.04 | L16: =(1-L11)*K16+L11*SRC_ZP_329 -> 0.87304348 | M16: 2025、1H26：GLM-4.5-Air（<32K 且輸出 ≥0.2K 檔 與 32K–128K 檔混合）；2H26：GLM-4.5-Air 與 GLM-5.3-Flash（08-26 起）期間加權；2027 起 ×（1＋年變動率）
A17: R09 | B17: Luna（Air／Flash） 快取命中輸入牌價 | C17: 元／M | D17: =(1-INP_025)*SRC_ZP_321+INP_025*SRC_ZP_324 -> 0.208 | E17: =(K17+L17)/INP_013 -> 0.21565217 | F17: =L17*(1+INP_036) -> 0.17864348 | G17: =F17*(1+INP_036) -> 0.14291478 | H17: =G17*(1+INP_036) -> 0.11433183 | I17: =H17*(1+INP_036) -> 0.091465461 | K17: =D17 -> 0.208 | L17: =(1-L11)*K17+L11*SRC_ZP_330 -> 0.22330435 | M17: 2025、1H26：GLM-4.5-Air（<32K 且輸出 ≥0.2K 檔 與 32K–128K 檔混合）；2H26：GLM-4.5-Air 與 GLM-5.3-Flash（08-26 起）期間加權；2027 起 ×（1＋年變動率）
A18: R10 | B18: Luna（Air／Flash） 輸出牌價 | C18: 元／M | D18: =(1-INP_025)*SRC_ZP_322+INP_025*SRC_ZP_325 -> 7.2 | E18: =(K18+L18)/INP_013 -> 5.6695652 | F18: =L18*(1+INP_036) -> 3.3113043 | G18: =F18*(1+INP_036) -> 2.6490435 | H18: =G18*(1+INP_036) -> 2.1192348 | I18: =H18*(1+INP_036) -> 1.6953878 | K18: =D18 -> 7.2 | L18: =(1-L11)*K18+L11*SRC_ZP_331 -> 4.1391304 | M18: 2025、1H26：GLM-4.5-Air（<32K 且輸出 ≥0.2K 檔 與 32K–128K 檔混合）；2H26：GLM-4.5-Air 與 GLM-5.3-Flash（08-26 起）期間加權；2027 起 ×（1＋年變動率）
A19: 三、有效單價（元／百萬 token；含快取、輸出占比、折扣與免費額度）
A20: R11 | B20: Sol（GLM 旗艦） 有效單價 | C20: 元／M | D20: =((1-INP_029)*(INP_030*D14+(1-INP_030)*D13)+INP_029*D15)*(1-INP_031) -> 3.087 | E20: =(K20+L20)/INP_013 -> 5.5433122 | F20: =((1-INP_029)*(INP_030*F14+(1-INP_030)*F13)+INP_029*F15)*(1-INP_031) -> 5.07 | G20: =((1-INP_029)*(INP_030*G14+(1-INP_030)*G13)+INP_029*G15)*(1-INP_031) -> 4.056 | H20: =((1-INP_029)*(INP_030*H14+(1-INP_030)*H13)+INP_029*H15)*(1-INP_031) -> 3.2448 | I20: =((1-INP_029)*(INP_030*I14+(1-INP_030)*I13)+INP_029*I15)*(1-INP_031) -> 2.59584 | K20: =((1-INP_029)*(INP_030*K14+(1-INP_030)*K13)+INP_029*K15)*(1-INP_031) -> 4.7491243 | L20: =((1-INP_029)*(INP_030*L14+(1-INP_030)*L13)+INP_029*L15)*(1-INP_031) -> 6.3375 | M20: ［(1−輸出占比)×(快取命中×快取價＋(1−快取命中)×輸入價)＋輸出占比×輸出價］×(1−折扣與免費額度)
A21: R12 | B21: Luna（Air／Flash） 有效單價 | C21: 元／M | D21: =((1-INP_029)*(INP_030*D17+(1-INP_030)*D16)+INP_029*D18)*(1-INP_031) -> 1.2078 | E21: =(K21+L21)/INP_013 -> 1.0114565 | F21: =((1-INP_029)*(INP_030*F17+(1-INP_030)*F16)+INP_029*F18)*(1-INP_031) -> 0.65209043 | G21: =((1-INP_029)*(INP_030*G17+(1-INP_030)*G16)+INP_029*G18)*(1-INP_031) -> 0.52167235 | H21: =((1-INP_029)*(INP_030*H17+(1-INP_030)*H16)+INP_029*H18)*(1-INP_031) -> 0.41733788 | I21: =((1-INP_029)*(INP_030*I17+(1-INP_030)*I16)+INP_029*I18)*(1-INP_031) -> 0.3338703 | K21: =((1-INP_029)*(INP_030*K17+(1-INP_030)*K16)+INP_029*K18)*(1-INP_031) -> 1.2078 | L21: =((1-INP_029)*(INP_030*L17+(1-INP_030)*L16)+INP_029*L18)*(1-INP_031) -> 0.81511304 | M21: ［(1−輸出占比)×(快取命中×快取價＋(1−快取命中)×輸入價)＋輸出占比×輸出價］×(1−折扣與免費額度)
A22: R13 | B22: 付費 API token 組合：Sol | C22: 比例 | D22: =INP_032 -> 0.6 | E22: =INP_033 -> 0.7 | F22: =INP_034 -> 0.7 | G22: =INP_034 -> 0.7 | H22: =INP_034 -> 0.7 | I22: =INP_034 -> 0.7 | K22: =INP_033 -> 0.7 | L22: =INP_033 -> 0.7 | M22: Inputs（2025、2026、2027 起）
A23: R14 | B23: 付費 API token 組合：Luna | C23: 比例 | D23: =(1-D22) -> 0.4 | E23: =(1-E22) -> 0.3 | F23: =(1-F22) -> 0.3 | G23: =(1-G22) -> 0.3 | H23: =(1-H22) -> 0.3 | I23: =(1-I22) -> 0.3 | K23: =(1-K22) -> 0.3 | L23: =(1-L22) -> 0.3 | M23: ＝1 − Sol（D24：無 Astra 級）
A24: R15 | B24: 組合有效單價 | C24: 元／M | D24: =D22*D20+D23*D21 -> 2.33532 | E24: =E47*INP_015/Demand!E11 -> 4.3486239 | F24: =F22*F20+F23*F21 -> 3.7446271 | G24: =G22*G20+G23*G21 -> 2.9957017 | H24: =H22*H20+H23*H21 -> 2.3965614 | I24: =I22*I20+I23*I21 -> 1.9172491 | K24: =K22*K20+K23*K21 -> 3.686727 | L24: =L22*L20+L23*L21 -> 4.6807839 | M24: Σ 層級組合 × 有效單價；2026 欄＝全年按量計費營收 ÷ 全年 token（token 加權）
A25: 四、GLM Coding Plan 方案價格（元／月／訂閱者）
A26: R16 | B26: Lite 國內月付牌價 | C26: 元／月 | K26: =SRC_ZP_356 -> 49 | L26: =SRC_ZP_356 -> 49 | M26: 2026-02-12 漲價後（SRC_ZP_356／359／362）
A27: R17 | B27: Lite 國際站月價（換人民幣） | C27: 元／月 | K27: =SRC_ZP_373/INP_012*INP_023 -> 67.399 | L27: =SRC_ZP_367*INP_023 -> 121.3182 | M27: 1H26：2026-02～07 季付價 ÷ 3（SRC_ZP_373–375）；2H26：2026-07 起牌價（SRC_ZP_367／369／371）；× USD/CNY
A28: R18 | B28: Lite 有效月價（實收） | C28: 元／月 | D28: =K28/(1+SRC_ZP_350/INP_014) -> 33.550585 | E28: =(K28+L28)/INP_013 -> 50.086064 | F28: =L28*(1+INP_059) -> 56.556368 | G28: =F28*(1+INP_059) -> 56.556368 | H28: =G28*(1+INP_059) -> 56.556368 | I28: =H28*(1+INP_059) -> 56.556368 | K28: =((1-INP_057)*K26+INP_057*K27)*(1-INP_058) -> 43.61576 | L28: =((1-INP_057)*L26+INP_057*L27)*(1-INP_058) -> 56.556368 | M28: ［(1−國際占比)×國內＋國際占比×國際］×(1−季／年付折扣)；2025＝1H26 ÷（1＋2026-02 漲價 30%，SRC_ZP_350）；2027 起 ×（1＋年變動率）
A29: R19 | B29: Pro 國內月付牌價 | C29: 元／月 | K29: =SRC_ZP_359 -> 149 | L29: =SRC_ZP_359 -> 149 | M29: 2026-02-12 漲價後（SRC_ZP_356／359／362）
A30: R20 | B30: Pro 國際站月價（換人民幣） | C30: 元／月 | K30: =SRC_ZP_374/INP_012*INP_023 -> 202.197 | L30: =SRC_ZP_369*INP_023 -> 485.2728 | M30: 1H26：2026-02～07 季付價 ÷ 3（SRC_ZP_373–375）；2H26：2026-07 起牌價（SRC_ZP_367／369／371）；× USD/CNY
A31: R21 | B31: Pro 有效月價（實收） | C31: 元／月 | D31: =K31/(1+SRC_ZP_350/INP_014) -> 101.51329 | E31: =(K31+L31)/INP_013 -> 165.93638 | F31: =L31*(1+INP_059) -> 199.90547 | G31: =F31*(1+INP_059) -> 199.90547 | H31: =G31*(1+INP_059) -> 199.90547 | I31: =H31*(1+INP_059) -> 199.90547 | K31: =((1-INP_057)*K29+INP_057*K30)*(1-INP_058) -> 131.96728 | L31: =((1-INP_057)*L29+INP_057*L30)*(1-INP_058) -> 199.90547 | M31: ［(1−國際占比)×國內＋國際占比×國際］×(1−季／年付折扣)；2025＝1H26 ÷（1＋2026-02 漲價 30%，SRC_ZP_350）；2027 起 ×（1＋年變動率）
A32: R22 | B32: Max 國內月付牌價 | C32: 元／月 | K32: =SRC_ZP_362 -> 469 | L32: =SRC_ZP_362 -> 469 | M32: 2026-02-12 漲價後（SRC_ZP_356／359／362）
A33: R23 | B33: Max 國際站月價（換人民幣） | C33: 元／月 | K33: =SRC_ZP_375/INP_012*INP_023 -> 539.192 | L33: =SRC_ZP_371*INP_023 -> 1078.384 | M33: 1H26：2026-02～07 季付價 ÷ 3（SRC_ZP_373–375）；2H26：2026-07 起牌價（SRC_ZP_367／369／371）；× USD/CNY
A34: R24 | B34: Max 有效月價（實收） | C34: 元／月 | D34: =K34/(1+SRC_ZP_350/INP_014) -> 301.57391 | E34: =(K34+L34)/INP_013 -> 456.74912 | F34: =L34*(1+INP_059) -> 521.45216 | G34: =F34*(1+INP_059) -> 521.45216 | H34: =G34*(1+INP_059) -> 521.45216 | I34: =H34*(1+INP_059) -> 521.45216 | K34: =((1-INP_057)*K32+INP_057*K33)*(1-INP_058) -> 392.04608 | L34: =((1-INP_057)*L32+INP_057*L33)*(1-INP_058) -> 521.45216 | M34: ［(1−國際占比)×國內＋國際占比×國際］×(1−季／年付折扣)；2025＝1H26 ÷（1＋2026-02 漲價 30%，SRC_ZP_350）；2027 起 ×（1＋年變動率）
A35: R25 | B35: 方案組合：Lite | C35: 比例 | D35: =INP_055 -> 0.6 | E35: =INP_055 -> 0.6 | F35: =INP_055 -> 0.6 | G35: =INP_055 -> 0.6 | H35: =INP_055 -> 0.6 | I35: =INP_055 -> 0.6 | K35: =INP_055 -> 0.6 | L35: =INP_055 -> 0.6 | M35: Inputs
A36: R26 | B36: 方案組合：Pro | C36: 比例 | D36: =INP_056 -> 0.3 | E36: =INP_056 -> 0.3 | F36: =INP_056 -> 0.3 | G36: =INP_056 -> 0.3 | H36: =INP_056 -> 0.3 | I36: =INP_056 -> 0.3 | K36: =INP_056 -> 0.3 | L36: =INP_056 -> 0.3 | M36: Inputs
A37: R27 | B37: 方案組合：Max（＝1 − Lite − Pro） | C37: 比例 | D37: =(1-D35-D36) -> 0.1 | E37: =(1-E35-E36) -> 0.1 | F37: =(1-F35-F36) -> 0.1 | G37: =(1-G35-G36) -> 0.1 | H37: =(1-H35-H36) -> 0.1 | I37: =(1-I35-I36) -> 0.1 | K37: =(1-K35-K36) -> 0.1 | L37: =(1-L35-L36) -> 0.1 | M37: 不另輸入
A38: R28 | B38: 每訂閱者加權有效月價 | C38: 元／月 | D38: =D35*D28+D36*D31+D37*D34 -> 80.741729 | E38: =E35*E28+E36*E31+E37*E34 -> 125.50746 | F38: =F35*F28+F36*F31+F37*F34 -> 146.05068 | G38: =G35*G28+G36*G31+G37*G34 -> 146.05068 | H38: =H35*H28+H36*H31+H37*H34 -> 146.05068 | I38: =I35*I28+I36*I31+I37*I34 -> 146.05068 | K38: =K35*K28+K36*K31+K37*K34 -> 104.96425 | L38: =L35*L28+L36*L31+L37*L34 -> 146.05068
A39: 五、營收（RMB 億）
A40: R29 | B40: ①-Coding Plan 子列：Lite | C40: RMB 億 | D40: =Demand!D17*D28*INP_010/INP_017 -> 0.087687808 | E40: =K40+L40 -> 1.1190591 | F40: =Demand!F17*F28*INP_010/INP_017 -> 1.8476965 | G40: =Demand!G17*G28*INP_010/INP_017 -> 2.4020055 | H40: =Demand!H17*H28*INP_010/INP_017 -> 2.8824066 | I40: =Demand!I17*I28*INP_010/INP_017 -> 3.3147676 | K40: =Demand!K17*K28*INP_011/INP_017 -> 0.3799805 | L40: =Demand!L17*L28*INP_011/INP_017 -> 0.73907862 | M40: 訂閱者（萬）× 有效月價 × 月數 ÷ 10,000（萬 × 元 → 億）
A41: R30 | B41: ①-Coding Plan 子列：Pro | C41: RMB 億 | D41: =Demand!D18*D31*INP_010/INP_017 -> 0.13265757 | E41: =K41+L41 -> 1.8810318 | F41: =Demand!F18*F31*INP_010/INP_017 -> 3.2654559 | G41: =Demand!G18*G31*INP_010/INP_017 -> 4.2450927 | H41: =Demand!H18*H31*INP_010/INP_017 -> 5.0941112 | I41: =Demand!I18*I31*INP_010/INP_017 -> 5.8582279 | K41: =Demand!K18*K31*INP_011/INP_017 -> 0.57484947 | L41: =Demand!L18*L31*INP_011/INP_017 -> 1.3061824 | M41: 訂閱者（萬）× 有效月價 × 月數 ÷ 10,000（萬 × 元 → 億）
A42: R31 | B42: ①-Coding Plan 子列：Max | C42: RMB 億 | D42: =Demand!D19*D34*INP_010/INP_017 -> 0.13136559 | E42: =K42+L42 -> 1.7049737 | F42: =Demand!F19*F34*INP_010/INP_017 -> 2.839307 | G42: =Demand!G19*G34*INP_010/INP_017 -> 3.6910991 | H42: =Demand!H19*H34*INP_010/INP_017 -> 4.4293189 | I42: =Demand!I19*I34*INP_010/INP_017 -> 5.0937168 | K42: =Demand!K19*K34*INP_011/INP_017 -> 0.56925091 | L42: =Demand!L19*L34*INP_011/INP_017 -> 1.1357228 | M42: 訂閱者（萬）× 有效月價 × 月數 ÷ 10,000（萬 × 元 → 億）
A43: R32 | B43: ①-Coding Plan 子列合計（訂閱） | C43: RMB 億 | D43: =D40+D41+D42 -> 0.35171097 | E43: =E40+E41+E42 -> 4.7050647 | F43: =F40+F41+F42 -> 7.9524594 | G43: =G40+G41+G42 -> 10.338197 | H43: =H40+H41+H42 -> 12.405837 | I43: =I40+I41+I42 -> 14.266712 | K43: =K40+K41+K42 -> 1.5240809 | L43: =L40+L41+L42 -> 3.1809838 | M43: 財報歸入開放平台及 API（D2r）；本模型以訂閱者驅動
A44: R33 | B44: 校準：按量計費營收＝開放平台及 API 實際 − Coding Plan 估計 | C44: RMB 億 | D44: =SRC_ZP_112-D43 -> 1.552089 | K44: =SRC_ZP_169-K43 -> 6.7277191 | M44: 2025（年報）、1H26（中期公告）；按量計費 token 由此倒推（D14）
A45: R34 | B45: ①-按量計費：Sol（GLM 旗艦） | C45: RMB 億 | D45: =Demand!D11*D22*D20/INP_015 -> 1.2310002 | E45: =K45+L45 -> 22.198414 | F45: =Demand!F11*F22*F20/INP_015 -> 50.150708 | G45: =Demand!G11*G22*G20/INP_015 -> 86.509972 | H45: =Demand!H11*H22*H20/INP_015 -> 134.30673 | I45: =Demand!I11*I22*I20/INP_015 -> 193.06593 | K45: =Demand!K11*K22*K20/INP_015 -> 6.0665034 | L45: =Demand!L11*L22*L20/INP_015 -> 16.13191 | M45: token × 組合 × 有效單價 ÷ 100（T × 元/M → 億）
A46: R35 | B46: ①-按量計費：Luna（Air／Flash） | C46: RMB 億 | D46: =Demand!D11*D23*D21/INP_015 -> 0.32108887 | E46: =K46+L46 -> 1.550435 | F46: =Demand!F11*F23*F21/INP_015 -> 2.7643954 | G46: =Demand!G11*G23*G21/INP_015 -> 4.768582 | H46: =Demand!H11*H23*H21/INP_015 -> 7.4032235 | I46: =Demand!I11*I23*I21/INP_015 -> 10.642134 | K46: =Demand!K11*K23*K21/INP_015 -> 0.66121569 | L46: =Demand!L11*L23*L21/INP_015 -> 0.88921929 | M46: token × 組合 × 有效單價 ÷ 100（T × 元/M → 億）
A47: R36 | B47: ①-按量計費合計 | C47: RMB 億 | D47: =D45+D46 -> 1.552089 | E47: =E45+E46 -> 23.748848 | F47: =F45+F46 -> 52.915104 | G47: =G45+G46 -> 91.278554 | H47: =H45+H46 -> 141.70995 | I47: =I45+I46 -> 203.70806 | K47: =K45+K46 -> 6.7277191 | L47: =L45+L46 -> 17.021129 | M47: 校準期恆等於上方校準列
A48: R37 | B48: ①開放平台及 API（按量計費＋Coding Plan） | C48: RMB 億 | D48: =D47+D43 -> 1.9038 | E48: =E47+E43 -> 28.453913 | F48: =F47+F43 -> 60.867563 | G48: =G47+G43 -> 101.61675 | H48: =H47+H43 -> 154.11579 | I48: =I47+I43 -> 217.97477 | K48: =K47+K43 -> 8.2518 | L48: =L47+L43 -> 20.202113 | M48: ＝雲端部署分部（D2r）
A49: R38 | B49: ②企業級智能體 | C49: RMB 億 | D49: =SRC_ZP_114 -> 1.6569 | E49: =K49+L49 -> 6.6999537 | F49: =E49*(1+INP_070) -> 6.6999537 | G49: =F49*(1+INP_070) -> 6.6999537 | H49: =G49*(1+INP_070) -> 6.6999537 | I49: =H49*(1+INP_070) -> 6.6999537 | K49: =SRC_ZP_171 -> 0.5556 | L49: =(SRC_ZP_114-SRC_ZP_172)*((1-INP_069)+INP_069*SRC_ZP_171/SRC_ZP_172) -> 6.1443537 | M49: 2025、1H26＝財報；2H26＝2H25（FY25 − 1H25）×［(1−延續係數)＋延續係數 × 1H26 ÷ 1H25］（工作單：依 1H26 實際、各線分開）；2027 起 ×（1＋年增率）
A50: R39 | B50: ③企業級通用大模型 | C50: RMB 億 | D50: =SRC_ZP_116 -> 3.6572 | E50: =K50+L50 -> 1.6616651 | F50: =E50*(1+INP_070) -> 1.6616651 | G50: =F50*(1+INP_070) -> 1.6616651 | H50: =G50*(1+INP_070) -> 1.6616651 | I50: =H50*(1+INP_070) -> 1.6616651 | K50: =SRC_ZP_173 -> 0.6704 | L50: =(SRC_ZP_116-SRC_ZP_174)*((1-INP_069)+INP_069*SRC_ZP_173/SRC_ZP_174) -> 0.99126512 | M50: 2025、1H26＝財報；2H26＝2H25（FY25 − 1H25）×［(1−延續係數)＋延續係數 × 1H26 ÷ 1H25］（工作單：依 1H26 實際、各線分開）；2027 起 ×（1＋年增率）
A51: R40 | B51: ④技術服務及其他（含 C 端） | C51: RMB 億 | D51: =SRC_ZP_118 -> 0.0254 | E51: =K51+L51 -> 0.32385 | F51: =E51*(1+INP_070) -> 0.32385 | G51: =F51*(1+INP_070) -> 0.32385 | H51: =G51*(1+INP_070) -> 0.32385 | I51: =H51*(1+INP_070) -> 0.32385 | K51: =SRC_ZP_175 -> 0.0612 | L51: =(SRC_ZP_118-SRC_ZP_176)*((1-INP_069)+INP_069*SRC_ZP_175/SRC_ZP_176) -> 0.26265 | M51: 2025、1H26＝財報；2H26＝2H25（FY25 − 1H25）×［(1−延續係數)＋延續係數 × 1H26 ÷ 1H25］（工作單：依 1H26 實際、各線分開）；2027 起 ×（1＋年增率）
A52: R41 | B52: 本地化部署分部（②＋③＋④；不耗智譜算力） | C52: RMB 億 | D52: =D49+D50+D51 -> 5.3395 | E52: =E49+E50+E51 -> 8.6854688 | F52: =F49+F50+F51 -> 8.6854688 | G52: =G49+G50+G51 -> 8.6854688 | H52: =H49+H50+H51 -> 8.6854688 | I52: =I49+I50+I51 -> 8.6854688 | K52: =K49+K50+K51 -> 1.2872 | L52: =L49+L50+L51 -> 7.3982688 | M52: D4：不進 Demand、不受容量上限截頂
A53: R42 | B53: 廣告 | C53: RMB 億 | D53: =INP_071 -> 0 | E53: =INP_071 -> 0 | F53: =INP_071 -> 0 | G53: =INP_071 -> 0 | H53: =INP_071 -> 0 | I53: =INP_071 -> 0 | K53: =INP_071 -> 0 | L53: =INP_071 -> 0 | M53: 規格 D3：無廣告業務（Decision＝0）
A54: R43 | B54: 營收總額（①＋本地化＋廣告） | C54: RMB 億 | D54: =D48+D52+D53 -> 7.2433 | E54: =E48+E52+E53 -> 37.139382 | F54: =F48+F52+F53 -> 69.553032 | G54: =G48+G52+G53 -> 110.30222 | H54: =H48+H52+H53 -> 162.80126 | I54: =I48+I52+I53 -> 226.66024 | K54: =K48+K52+K53 -> 9.539 | L54: =L48+L52+L53 -> 27.600382 | M54: 未截頂
A55: R44 | B55: 營收淨額（＝總額；無雲端夥伴分成，D5） | C55: RMB 億 | D55: =D54 -> 7.2433 | E55: =E54 -> 37.139382 | F55: =F54 -> 69.553032 | G55: =G54 -> 110.30222 | H55: =H54 -> 162.80126 | I55: =I54 -> 226.66024 | K55: =K54 -> 9.539 | L55: =L54 -> 27.600382 | M55: REV_PartnerShare 不建
A56: R45 | B56: 雲端營收（①；跑在智譜算力上） | C56: RMB 億 | D56: =D48 -> 1.9038 | E56: =E48 -> 28.453913 | F56: =F48 -> 60.867563 | G56: =G48 -> 101.61675 | H56: =H48 -> 154.11579 | I56: =I48 -> 217.97477 | K56: =K48 -> 8.2518 | L56: =L48 -> 20.202113 | M56: 規格 r1：②③④屬本地化部署分部；C 端收入在④內
A57: R46 | B57: 容量上限係數（佔位 1；Z3 接 Compute） | C57: 比例 | D57: =INP_072 -> 1 | E57: =INP_072 -> 1 | F57: =INP_072 -> 1 | G57: =INP_072 -> 1 | H57: =INP_072 -> 1 | I57: =INP_072 -> 1 | M57: Inputs Decision 佔位
A58: R47 | B58: 營收總額（截頂後）＝雲端 × 係數＋本地化＋廣告 | C58: RMB 億 | D58: =D56*D57+D52+D53 -> 7.2433 | E58: =E56*E57+E52+E53 -> 37.139382 | F58: =F56*F57+F52+F53 -> 69.553032 | G58: =G56*G57+G52+G53 -> 110.30222 | H58: =H56*H57+H52+H53 -> 162.80126 | I58: =I56*I57+I52+I53 -> 226.66024 | M58: 容量上限只回乘雲端營收（工作單 Z2 第 5 步）
A59: R48 | B59: 營收淨額（截頂後） | C59: RMB 億 | D59: =D58 -> 7.2433 | E59: =E58 -> 37.139382 | F59: =F58 -> 69.553032 | G59: =G58 -> 110.30222 | H59: =H58 -> 162.80126 | I59: =I58 -> 226.66024
A60: R49 | B60: 企業（按量計費＋本地化部署） | C60: RMB 億 | D60: =D47+D52 -> 6.891589 | E60: =E47+E52 -> 32.434317 | F60: =F47+F52 -> 61.600572 | G60: =G47+G52 -> 99.964022 | H60: =H47+H52 -> 150.39542 | I60: =I47+I52 -> 212.39353 | K60: =K47+K52 -> 8.0149191 | L60: =L47+L52 -> 24.419398 | M60: D2：企業 vs 個人；按量計費以企業與開發者為主，歸企業
A61: R50 | B61: 個人（Coding Plan 訂閱） | C61: RMB 億 | D61: =D43 -> 0.35171097 | E61: =E43 -> 4.7050647 | F61: =F43 -> 7.9524594 | G61: =G43 -> 10.338197 | H61: =H43 -> 12.405837 | I61: =I43 -> 14.266712 | K61: =K43 -> 1.5240809 | L61: =L43 -> 3.1809838 | M61: Coding Plan 以個人開發者為主；C 端清言收入在④內未拆，歸企業列（資料缺口）
A62: R51 | B62: 檢查：企業＋個人＋廣告 − 總額（應為 0） | C62: RMB 億 | D62: =D60+D61+D53-D54 -> 0 | E62: =E60+E61+E53-E54 -> 0 | F62: =F60+F61+F53-F54 -> 0 | G62: =G60+G61+G53-G54 -> 0 | H62: =H60+H61+H53-H54 -> 0 | I62: =I60+I61+I53-I54 -> 0 | K62: =K60+K61+K53-K54 -> 0 | L62: =L60+L61+L53-L54 -> 0
A63: R52 | B63: 雲端占總額 | C63: 比例 | D63: =D56/D54 -> 0.262836 | E63: =E56/E54 -> 0.76613857 | F63: =F56/F54 -> 0.87512451 | G63: =G56/G54 -> 0.92125753 | H63: =H56/H54 -> 0.94664987 | I63: =I56/I54 -> 0.96168067 | K63: =K56/K54 -> 0.86505923 | L63: =L56/L54 -> 0.73195049 | M63: 2025 約 26%、1H26 約 87%（財報）
A64: R53 | B64: 總額年增率 | C64: 比例 | E64: =(E54-D54)/D54 -> 4.1274118 | F64: =(F54-E54)/E54 -> 0.87275685 | G64: =(G54-F54)/F54 -> 0.5858722 | H64: =(H54-G54)/G54 -> 0.47595634 | I64: =(I54-H54)/H54 -> 0.39225114
A65: 六、校準差距（應為 0）與對照（公司說法、TK、未校準值；只列差距，不反推）
A66: R54 | B66: 2025 校準差距：①開放平台及 API（模型 − 年報） | C66: RMB 億 | D66: =D48-SRC_ZP_112 -> 0
A67: R55 | B67: 1H26 校準差距：①開放平台及 API（模型 − 中期公告） | C67: RMB 億 | K67: =K48-SRC_ZP_169 -> 0
A68: R56 | B68: 2025 校準差距：②企業級智能體（模型 − 年報） | C68: RMB 億 | D68: =D49-SRC_ZP_114 -> 0
A69: R57 | B69: 1H26 校準差距：②企業級智能體（模型 − 中期公告） | C69: RMB 億 | K69: =K49-SRC_ZP_171 -> 0
A70: R58 | B70: 2025 校準差距：③企業級通用大模型（模型 − 年報） | C70: RMB 億 | D70: =D50-SRC_ZP_116 -> 0
A71: R59 | B71: 1H26 校準差距：③企業級通用大模型（模型 − 中期公告） | C71: RMB 億 | K71: =K50-SRC_ZP_173 -> 0
A72: R60 | B72: 2025 校準差距：④技術服務及其他（含 C 端）（模型 − 年報） | C72: RMB 億 | D72: =D51-SRC_ZP_118 -> 0
A73: R61 | B73: 1H26 校準差距：④技術服務及其他（含 C 端）（模型 − 中期公告） | C73: RMB 億 | K73: =K51-SRC_ZP_175 -> 0
A74: R62 | B74: 2025 校準差距：營收總額（模型 − 年報） | C74: RMB 億 | D74: =D54-SRC_ZP_120 -> 0
A75: R63 | B75: 1H26 校準差距：營收總額（模型 − 中期公告） | C75: RMB 億 | K75: =K54-SRC_ZP_177 -> 0.0001 | M75: 公告以千元四捨五入至億元四位小數：四線合計 9.53892 vs 總額 9.5389
A76: R64 | B76: 2025 未校準 ①：日均 4.2T × 365 × 組合有效單價 ÷ 100 ＋ Coding Plan | C76: RMB 億 | D76: =SRC_ZP_413*INP_007*D24/INP_015+D43 -> 36.152167 | M76: 自下而上口徑（假設揭露 token 全數按有效單價計費）
A77: R65 | B77: 2025 未校準差距：未校準 − 年報 ① | C77: RMB 億 | D77: =D76-SRC_ZP_112 -> 34.248367 | M77: 差距大＝揭露量多為免費、Coding Plan 或年末時點
A78: R66 | B78: 模型組合有效單價變動：1H26 對 2025 | C78: 比例 | K78: =(K24-D24)/D24 -> 0.57868173 | M78: 對照：公司稱 API 平均售價較年初 +101%（SRC_ZP_347）
A79: R67 | B79: 模型組合有效單價變動：2H26 對 2025 | C79: 比例 | L79: =(L24-D24)/D24 -> 1.0043437 | M79: 對照：較 2025 年底 +83%（SRC_ZP_346，截至 2026-03）
A80: R68 | B80: 公司說法：API 平均售價較年初上升（中期） | C80: 比例 | K80: =SRC_ZP_347/INP_014 -> 1.01 | M80: Interested-party；實現平均售價口徑（收入 ÷ 計費 token），只對照
A81: R69 | B81: 公司說法：API 呼叫定價較 2025 年底上升 | C81: 比例 | L81: =SRC_ZP_346/INP_014 -> 0.83 | M81: Interested-party；只對照
A82: R70 | B82: 模型 2H26 雲端營收年化（2H26 × 2） | C82: RMB 億 | L82: =L56*INP_013 -> 40.404226 | M82: 對照 MaaS ARR（D14r）
A83: R71 | B83: 公司說法：MaaS ARR（2026-08 月度年化）× 匯率 | C83: RMB 億 | L83: =SRC_ZP_417*INP_023 -> 107.8384 | M83: SRC_ZP_417（USD 億）；Interested-party
A84: R72 | B84: 差距：模型 ÷ ARR − 1 | C84: 比例 | L84: =(L82-L83)/L83 -> -0.62532617 | M84: Checks WARN 門檻 25%（D14r）
A85: R73 | B85: 模型 2H26 營收總額年化（2H26 × 2） | C85: RMB 億 | L85: =L54*INP_013 -> 55.200764 | M85: 對照全業務 ARR
A86: R74 | B86: 公司說法：全業務 ARR（2026-09）× 匯率 | C86: RMB 億 | L86: =SRC_ZP_419*INP_023 -> 121.3182 | M86: SRC_ZP_419（USD 億）；Interested-party
A87: R75 | B87: 差距：模型 ÷ 全業務 ARR − 1 | C87: 比例 | L87: =(L85-L86)/L86 -> -0.5449919 | M87: Checks WARN 門檻 25%
A88: R76 | B88: 分析師共識營收 FY2026（Simply Wall St） | C88: RMB 億 | E88: =SRC_ZP_582/INP_020 -> 60.48 | M88: SRC_ZP_582；Interested-party（券商交易誘因）；只對照
A89: R77 | B89: 差距：模型 2026 總額 − 共識 | C89: RMB 億 | E89: =E54-E88 -> -23.340618
A90: R78 | B90: TK：GLM-5.3 國際站輸入價 × 匯率 ÷ 本模型 2H26 Sol 人民幣輸入牌價 | C90: 倍 | L90: =TK_Link!$J$73*INP_023/L13 -> 1.1794825 | M90: Tokenomics Cap_In F 表（讀表）；國際站美元價換人民幣後對國內牌價
A91: R79 | B91: TK：GLM-5.3 國際站輸出價 × 匯率 ÷ 本模型 2H26 Sol 人民幣輸出牌價 | C91: 倍 | L91: =TK_Link!$L$73*INP_023/L15 -> 1.0591271 | M91: 同上
A92: R80 | B92: TK：中國合格前緣（Luna）混合單價 × 匯率 | C92: 元／M | L92: =TK_Link!$J$77*INP_023 -> 0.87768476 | M92: Tokenomics Price_Frontier B 表（讀表；前緣模型 GLM-5.3-Flash）；Tokenomics 參考請求混合口徑，未扣折扣
A93: R81 | B93: TK：GLM-5.3 參考請求混合單價 × 匯率 | C93: 元／M | L93: =TK_Link!$K$75*INP_023 -> 7.9261224 | M93: Tokenomics Price_Frontier A 表（讀表，Sol 參考請求）
A94: R82 | B94: 本模型 2H26 有效單價 ÷ TK 混合單價（Sol） | C94: 倍 | L94: =L20/L93 -> 0.7995713 | M94: 口徑：本模型含快取、輸出占比與折扣；只列差距
A95: R83 | B95: 本模型 2H26 有效單價 ÷ TK 中國合格前緣（Luna） | C95: 倍 | L95: =L21/L92 -> 0.92870822 | M95: 同上

Sheet Checks
A1: Checks — v0.1-Z2 檢查（公式；結果 ERR 的格數＝CHK_Errors，必須為 0）
A2: OK／ERR：比對期望值；WARN：超出門檻只提示（不計入 CHK_Errors）；INFO：只列示。編號（C##）由 builder/id_registry.json 固定，新檢查取下一號，退役號碼不重用。期望值為 builder 寫入的常數。
A4: 編號 | B4: 檢查項 | C4: 值（公式） | D4: 期望 | E4: 結果 | F4: 說明
A5: C01 | B5: SRC_ZP 列數 | C5: =SUMPRODUCT(--(LEN(SRC_ZP!$A$5:$A$800)>0)) -> 604 | D5: 604 | E5: =IF(C5=D5,"OK","ERR") -> OK | F5: Z1 資料報告所列 604 筆（SRC_ZP_001–604）
A6: C02 | B6: SRC_ZP 無數值列數（日期、事件、找不到數值的說明列） | C6: =SUM(SRC_ZP!$U$5:$U$800) -> 22 | D6: 22 | E6: =IF(C6=D6,"OK","ERR") -> OK | F6: 值、低、高皆空的列數；與 yaml 一致（列被誤刪或誤填時轉 ERR）
A7: C03 | B7: SRC_ZP 缺出處列數 | C7: =SUM(SRC_ZP!$V$5:$V$800) -> 0 | D7: 0 | E7: =IF(C7=D7,"OK","ERR") -> OK
A8: C04 | B8: SRC_ZP 區間順序異常列數（低 ≤ 值 ≤ 高） | C8: =SUM(SRC_ZP!$W$5:$W$800) -> 0 | D8: 0 | E8: =IF(C8=D8,"OK","ERR") -> OK
A9: C05 | B9: Inputs 列數 | C9: =SUMPRODUCT(--(LEN(Inputs!$A$5:$A$600)>0)) -> 73 | D9: 73 | E9: =IF(C9=D9,"OK","ERR") -> OK | F9: data/zhipu_inputs.yaml
A10: C06 | B10: Inputs 區間順序異常列數 | C10: =SUM(Inputs!$L$5:$L$600) -> 0 | D10: 0 | E10: =IF(C10=D10,"OK","ERR") -> OK | F10: 低 ≤ 值 ≤ 高
A11: C07 | B11: Inputs Analogy／Assumed 缺區間列數 | C11: =SUM(Inputs!$M$5:$M$600) -> 0 | D11: 0 | E11: =IF(C11=D11,"OK","ERR") -> OK | F11: 共同規則第 4 節：Analogy／Assumed 一律給區間
A12: C08 | B12: TK_Link 具名名稱數（同 OpenAI v0.6 的 63 名） | C12: =COUNTIF(TK_Link!$F$10:$F$200,"OK") -> 63 | D12: 63 | E12: =IF(C12=D12,"OK","ERR") -> OK | F12: 取自 Tokenomics master CURRENT
A13: C09 | B13: TK_Link 讀表列數（Cap_In／Price_Frontier 的 GLM 列與中國合格前緣） | C13: =COUNTIF(TK_Link!$F$10:$F$200,"讀表（非具名）") -> 7 | D13: 7 | E13: =IF(C13=D13,"OK","ERR") -> OK | F13: 以列標籤讀表；Tokenomics 改版找不到標籤時狀態轉 MISSING
A14: C10 | B14: TK_Link 錯誤值格數 | C14: =SUMPRODUCT(--ISERROR(TK_Link!$J$10:$X$200)) -> 0 | D14: 0 | E14: =IF(C14=D14,"OK","ERR") -> OK
A15: C11 | B15: TK 快照版本 | C15: =TK_Version -> v5.26 | D15: v5.26 | E15: =IF(C15=D15,"OK","ERR") -> OK | F15: 共同規則第 8 節：master 3dd1216；tools/check_tk_snapshot.py 結果見報告
A16: C12 | B16: OAI_Link 已取值列數 | C16: =COUNTIF(OAI_Link!$E$10:$E$60,"OK") -> 14 | D16: 14 | E16: =IF(C16=D16,"OK","ERR") -> OK | F16: OpenAI v0.6 命題輸出（美元）
A17: C13 | B17: OAI_Link 被計算頁引用的公式格數（builder 掃描） | C17: 0 | D17: 0 | E17: =IF(C17=D17,"OK","ERR") -> OK | F17: 規格 D26：OAI_Link 只被 Checks 與 HTML 引用；值為 builder 建置時掃描結果，tests/parity/test_builder.py 每次逐格重驗
A18: C14 | B18: E6：計算頁公式含常數的格數（builder 掃描） | C18: 0 | D18: 0 | E18: =IF(C18=D18,"OK","ERR") -> OK | F18: Demand、Revenue（Z3 起含 Compute、Cost）；tests/parity/test_builder.py 每次逐格重驗
A19: C15 | B19: 2025 各分部校準差距（四線絕對值合計，RMB 億） | C19: =ABS(Revenue!$D$66)+ABS(Revenue!$D$68)+ABS(Revenue!$D$70)+ABS(Revenue!$D$72) -> 0 | D19: 0 | E19: =IF(ISNUMBER(C19),IF(ABS(C19-D19)<0.000000001,"OK","ERR"),"ERR") -> OK | F19: ①API（含 Coding Plan）②③④ 模型 − 年報；按量計費為倒推項，恆為 0
A20: C16 | B20: 1H26 各分部校準差距（四線絕對值合計，RMB 億） | C20: =ABS(Revenue!$K$67)+ABS(Revenue!$K$69)+ABS(Revenue!$K$71)+ABS(Revenue!$K$73) -> 0 | D20: 0 | E20: =IF(ISNUMBER(C20),IF(ABS(C20-D20)<0.000000001,"OK","ERR"),"ERR") -> OK | F20: 模型 − 中期公告
A21: C17 | B21: 2025 營收總額校準差距（RMB 億） | C21: =REV_Gap2025 -> 0 | D21: 0 | E21: =IF(ISNUMBER(C21),IF(ABS(C21-D21)<0.000000001,"OK","ERR"),"ERR") -> OK | F21: 四線合計＝年報總額 7.2433
A22: C18 | B22: 1H26 營收總額校準差距（RMB 億；公告四捨五入容差 0.0005） | C22: =REV_Gap1H26 -> 0.0001 | D22: 0 | E22: =IF(ISNUMBER(C22),IF(ABS(C22-D22)<=0.0005,"OK","ERR"),"ERR") -> OK | F22: 四線合計 9.53892（千元加總）vs 總額 9.5389
A23: C19 | B23: 分部合計＝總營收（API＋本地化＋廣告 − 總額；各期絕對值合計） | C23: =ABS(Revenue!D48+Revenue!D52+Revenue!D53-Revenue!D54)+ABS(Revenue!E48+Revenue!E52+Revenue!E53-Revenue!E54)+ABS(Revenue!F48+Revenue!F52+Revenue!F53-Revenue!F54)+ABS(Revenue!G48+Revenue!G52+Revenue!G53-Revenue!G54)+ABS(Revenue!H48+Revenue!H52+Revenue!H53-Revenue!H54)+ABS(Revenue!I48+Revenue!I52+Revenue!I53-Revenue!I54)+ABS(Revenue!K48+Revenue!K52+Revenue!K53-Revenue!K54)+ABS(Revenue!L48+Revenue!L52+Revenue!L53-Revenue!L54) -> 0 | D23: 0 | E23: =IF(ISNUMBER(C23),IF(ABS(C23-D23)<0.000000001,"OK","ERR"),"ERR") -> OK | F23: 2025–2030 與 1H26、2H26
A24: C20 | B24: 企業＋個人＋廣告 − 總額（各期絕對值合計） | C24: =ABS(Revenue!D62)+ABS(Revenue!E62)+ABS(Revenue!F62)+ABS(Revenue!G62)+ABS(Revenue!H62)+ABS(Revenue!I62)+ABS(Revenue!K62)+ABS(Revenue!L62) -> 0 | D24: 0 | E24: =IF(ISNUMBER(C24),IF(ABS(C24-D24)<0.000000001,"OK","ERR"),"ERR") -> OK | F24: D2 彙總列
A25: C21 | B25: 校準期按量計費營收 ≤0 的期數（Coding Plan 估計超過 API 實際） | C25: =(Revenue!D44<=0)+(Revenue!K44<=0) -> 0 | D25: 0 | E25: =IF(C25=D25,"OK","ERR") -> OK | F25: Coding Plan 訂閱者 × 價格的 Inputs 使估計值超過財報 API 營收時轉 ERR
A26: C22 | B26: token 層級拆分前後總量不一致的年數（相對差 >1e-9） | C26: =SUMPRODUCT(--(ABS(Demand!$D$11:$I$11+Demand!$D$26:$I$26+Demand!$D$31:$I$31+Demand!$D$14:$I$14-Demand!$D$41:$I$41)>0.000000001*Demand!$D$41:$I$41)) -> 0 | D26: 0 | E26: =IF(C26=D26,"OK","ERR") -> OK | F26: API＋Coding Plan＋清言＋免費 API ＝ 付費＋免費（Sol／Luna 拆分前後）
A27: C23 | B27: Coding Plan 方案組合 Max（＝1 − Lite − Pro）∉[0,1] 的期數 | C27: =(Revenue!D37<0)+(Revenue!D37>1)+(Revenue!E37<0)+(Revenue!E37>1)+(Revenue!F37<0)+(Revenue!F37>1)+(Revenue!G37<0)+(Revenue!G37>1)+(Revenue!H37<0)+(Revenue!H37>1)+(Revenue!I37<0)+(Revenue!I37>1)+(Revenue!K37<0)+(Revenue!K37>1)+(Revenue!L37<0)+(Revenue!L37>1) -> 0 | D27: 0 | E27: =IF(C27=D27,"OK","ERR") -> OK | F27: Inputs Lite＋Pro ≤ 1
A28: C24 | B28: API 層級組合 Sol ∉[0,1] 的期數 | C28: =(Revenue!D22<0)+(Revenue!D22>1)+(Revenue!E22<0)+(Revenue!E22>1)+(Revenue!F22<0)+(Revenue!F22>1)+(Revenue!G22<0)+(Revenue!G22>1)+(Revenue!H22<0)+(Revenue!H22>1)+(Revenue!I22<0)+(Revenue!I22>1)+(Revenue!K22<0)+(Revenue!K22>1)+(Revenue!L22<0)+(Revenue!L22>1) -> 0 | D28: 0 | E28: =IF(C28=D28,"OK","ERR") -> OK
A29: C25 | B29: 1H26 價格期間權重 GLM-5.1 ＜0（天數超過半年） | C29: =IF(Revenue!K10<0,1,0) -> 0 | D29: 0 | E29: =IF(C29=D29,"OK","ERR") -> OK | F29: Inputs 期間天數
A30: C26 | B30: 本地化部署延續係數 ∉[0,1] | C30: =IF(OR(INP_069<0,INP_069>1),1,0) -> 0 | D30: 0 | E30: =IF(C30=D30,"OK","ERR") -> OK | F30: 工作單：0＝下半年持平、1＝延續上半年同比
A31: C27 | B31: API 任務數或每任務 token ≤0 的期數 | C31: =SUMPRODUCT(--(Demand!$D$10:$I$10<=0))+SUMPRODUCT(--(Demand!$D$9:$I$9<=0)) -> 0 | D31: 0 | E31: =IF(C31=D31,"OK","ERR") -> OK
A32: C28 | B32: D14r：模型 2H26 年化雲端營收 ÷ MaaS ARR（2026-08，US$16 億）− 1 | C32: =REV_ARRGapMaaS -> -0.62532617 | E32: =IF(ISNUMBER(C32),IF(ABS(C32)>INP_073,"WARN","OK"),"WARN") -> WARN | F32: 絕對值 >25% 為 WARN；ARR 只對照、不反推參數；原因見報告
A33: C29 | B33: D14r：模型 2H26 年化總營收 ÷ 全業務 ARR（2026-09，US$18 億）− 1 | C33: =REV_ARRGapTotal -> -0.5449919 | E33: =IF(ISNUMBER(C33),IF(ABS(C33)>INP_073,"WARN","OK"),"WARN") -> WARN | F33: 同上
A34: C30 | B34: 對照：模型組合有效單價 1H26 對 2025 變動 | C34: =Revenue!K78 -> 0.57868173 | E34: INFO | F34: 公司稱平均售價較年初 +101%（實現售價口徑）；報告討論
A35: C31 | B35: 對照：模型組合有效單價 2H26 對 2025 變動 | C35: =Revenue!L79 -> 1.0043437 | E35: INFO | F35: 公司稱較 2025 年底 +83%（截至 2026-03）
A36: C32 | B36: 對照：模型 2H26 ÷ 1H26 API token | C36: =Demand!L44 -> 1.9927045 | E36: INFO | F36: 公司稱 MaaS 呼叫量較年初 40 倍以上（時點對時點，口徑不同）
A37: C33 | B37: 對照：2H25→1H26 實際隱含量成長（倍） | C37: =DEM_ImpliedVolGrowth -> 3.2409594 | E37: INFO | F37: Inputs 2H26 任務數成長 1.3（＋130%）的參考
A38: C34 | B38: 對照：2025 未校準差距（RMB 億） | C38: =REV_GapUncal2025 -> 34.248367 | E38: INFO | F38: 日均 4.2T 全數按有效單價計的假想營收 − 年報
A39: C35 | B39: 對照：2025 計費比例（按量計費 token ÷ 揭露日均 × 365） | C39: =DEM_ApiBilledRatio2025 -> 0.04335389 | E39: INFO
A40: C36 | B40: 對照：模型 2026 總額 − 分析師共識（RMB 億） | C40: =Revenue!E89 -> -23.340618 | E40: INFO | F40: 共識 60.48 億（Interested-party）
A41: C37 | B41: 對照：本模型 2H26 Sol 有效單價 ÷ TK GLM-5.3 混合單價 × 匯率 | C41: =Revenue!L94 -> 0.7995713 | E41: INFO | F41: TK_Link 讀表列
A42: C38 | B42: 對照：本模型 2H26 Luna 有效單價 ÷ TK 中國合格前緣 × 匯率 | C42: =Revenue!L95 -> 0.92870822 | E42: INFO | F42: TK_Link 讀表列
A43: C39 | B43: 對照：OpenAI v0.6 2030 每 VR 等值 GW 差額（$B/GW） | C43: =INDEX(OAI_COST_PropGap_VR,1,6) -> -10.054479 | E43: INFO | F43: OAI_Link；只並排（Z5 HTML）
A44: C40 | B44: 預覽：2030 營收總額（截頂後，RMB 億） | C44: =INDEX(REV_GrossCapped,1,6) -> 226.66024 | E44: INFO
A45: C41 | B45: 預覽：2030 token 合計（T） | C45: =INDEX(DEM_Tok_Total,1,6) -> 38388.912 | E45: INFO | F45: 供 Z3
A46: C42 | B46: 容量上限係數佔位值（Z3 接 Compute 前恆為 1） | C46: =INP_072 -> 1 | E46: INFO
A48: CHK_Errors | C48: =COUNTIF($E$5:$E$46,"ERR") -> 0

Sheet _Defaults
A1: sheet | B1: id | C1: col | D1: builder 預設值（上次寫入）
A2: SRC_ZP | B2: SRC_ZP_001 | C2: D | D2: 0.5741
A3: SRC_ZP | B3: SRC_ZP_001 | C3: E
A4: SRC_ZP | B4: SRC_ZP_001 | C4: F
A5: SRC_ZP | B5: SRC_ZP_002 | C5: D | D5: 1.2454
A6: SRC_ZP | B6: SRC_ZP_002 | C6: E
A7: SRC_ZP | B7: SRC_ZP_002 | C7: F
A8: SRC_ZP | B8: SRC_ZP_003 | C8: D | D8: 3.1241
A9: SRC_ZP | B9: SRC_ZP_003 | C9: E
A10: SRC_ZP | B10: SRC_ZP_003 | C10: F
A11: SRC_ZP | B11: SRC_ZP_004 | C11: D | D11: 0.4491
A12: SRC_ZP | B12: SRC_ZP_004 | C12: E
A13: SRC_ZP | B13: SRC_ZP_004 | C13: F
A14: SRC_ZP | B14: SRC_ZP_005 | C14: D | D14: 1.9088
A15: SRC_ZP | B15: SRC_ZP_005 | C15: E
A16: SRC_ZP | B16: SRC_ZP_005 | C16: F
A17: SRC_ZP | B17: SRC_ZP_006 | C17: D | D17: 0.5482
A18: SRC_ZP | B18: SRC_ZP_006 | C18: E
A19: SRC_ZP | B19: SRC_ZP_006 | C19: F
A20: SRC_ZP | B20: SRC_ZP_007 | C20: D | D20: 1.1261
A21: SRC_ZP | B21: SRC_ZP_007 | C21: E
A22: SRC_ZP | B22: SRC_ZP_007 | C22: F
A23: SRC_ZP | B23: SRC_ZP_008 | C23: D | D23: 2.6393
A24: SRC_ZP | B24: SRC_ZP_008 | C24: E
A25: SRC_ZP | B25: SRC_ZP_008 | C25: F
A26: SRC_ZP | B26: SRC_ZP_009 | C26: D | D26: 0.2681
A27: SRC_ZP | B27: SRC_ZP_009 | C27: E
A28: SRC_ZP | B28: SRC_ZP_009 | C28: F
A29: SRC_ZP | B29: SRC_ZP_010 | C29: D | D29: 1.6178
A30: SRC_ZP | B30: SRC_ZP_010 | C30: E
A31: SRC_ZP | B31: SRC_ZP_010 | C31: F
A32: SRC_ZP | B32: SRC_ZP_011 | C32: D | D32: 0.0259
A33: SRC_ZP | B33: SRC_ZP_011 | C33: E
A34: SRC_ZP | B34: SRC_ZP_011 | C34: F
A35: SRC_ZP | B35: SRC_ZP_012 | C35: D | D35: 0.1192
A36: SRC_ZP | B36: SRC_ZP_012 | C36: E
A37: SRC_ZP | B37: SRC_ZP_012 | C37: F
A38: SRC_ZP | B38: SRC_ZP_013 | C38: D | D38: 0.4848
A39: SRC_ZP | B39: SRC_ZP_013 | C39: E
A40: SRC_ZP | B40: SRC_ZP_013 | C40: F
A41: SRC_ZP | B41: SRC_ZP_014 | C41: D | D41: 0.181
A42: SRC_ZP | B42: SRC_ZP_014 | C42: E
A43: SRC_ZP | B43: SRC_ZP_014 | C43: F
A44: SRC_ZP | B44: SRC_ZP_015 | C44: D | D44: 0.291
A45: SRC_ZP | B45: SRC_ZP_015 | C45: E
A46: SRC_ZP | B46: SRC_ZP_015 | C46: F
A47: SRC_ZP | B47: SRC_ZP_016 | C47: D | D47: 0.2605
A48: SRC_ZP | B48: SRC_ZP_016 | C48: E
A49: SRC_ZP | B49: SRC_ZP_016 | C49: F
A50: SRC_ZP | B50: SRC_ZP_017 | C50: D | D50: 0.4406
A51: SRC_ZP | B51: SRC_ZP_017 | C51: E
A52: SRC_ZP | B52: SRC_ZP_017 | C52: F
A53: SRC_ZP | B53: SRC_ZP_018 | C53: D | D53: 1.3653
A54: SRC_ZP | B54: SRC_ZP_018 | C54: E
A55: SRC_ZP | B55: SRC_ZP_018 | C55: F
A56: SRC_ZP | B56: SRC_ZP_019 | C56: D | D56: 0.2295
A57: SRC_ZP | B57: SRC_ZP_019 | C57: E
A58: SRC_ZP | B58: SRC_ZP_019 | C58: F
A59: SRC_ZP | B59: SRC_ZP_020 | C59: D | D59: 0.9545
A60: SRC_ZP | B60: SRC_ZP_020 | C60: E
A61: SRC_ZP | B61: SRC_ZP_020 | C61: F
A62: SRC_ZP | B62: SRC_ZP_021 | C62: D | D62: 0
A63: SRC_ZP | B63: SRC_ZP_021 | C63: E
A64: SRC_ZP | B64: SRC_ZP_021 | C64: F
A65: SRC_ZP | B65: SRC_ZP_022 | C65: D | D65: 0.12
A66: SRC_ZP | B66: SRC_ZP_022 | C66: E
A67: SRC_ZP | B67: SRC_ZP_022 | C67: F
A68: SRC_ZP | B68: SRC_ZP_023 | C68: D | D68: 0.3017
A69: SRC_ZP | B69: SRC_ZP_023 | C69: E
A70: SRC_ZP | B70: SRC_ZP_023 | C70: F
A71: SRC_ZP | B71: SRC_ZP_024 | C71: D | D71: 0.0845
A72: SRC_ZP | B72: SRC_ZP_024 | C72: E
A73: SRC_ZP | B73: SRC_ZP_024 | C73: F
A74: SRC_ZP | B74: SRC_ZP_025 | C74: D | D74: 0.3584
A75: SRC_ZP | B75: SRC_ZP_025 | C75: E
A76: SRC_ZP | B76: SRC_ZP_025 | C76: F
A77: SRC_ZP | B77: SRC_ZP_026 | C77: D | D77: 0.1643
A78: SRC_ZP | B78: SRC_ZP_026 | C78: E
A79: SRC_ZP | B79: SRC_ZP_026 | C79: F
A80: SRC_ZP | B80: SRC_ZP_027 | C80: D | D80: 0.1537
A81: SRC_ZP | B81: SRC_ZP_027 | C81: E
A82: SRC_ZP | B82: SRC_ZP_027 | C82: F
A83: SRC_ZP | B83: SRC_ZP_028 | C83: D | D83: 0.7426
A84: SRC_ZP | B84: SRC_ZP_028 | C84: E
A85: SRC_ZP | B85: SRC_ZP_028 | C85: F
A86: SRC_ZP | B86: SRC_ZP_029 | C86: D | D86: 0.1083
A87: SRC_ZP | B87: SRC_ZP_029 | C87: E
A88: SRC_ZP | B88: SRC_ZP_029 | C88: F
A89: SRC_ZP | B89: SRC_ZP_030 | C89: D | D89: 0.3763
A90: SRC_ZP | B90: SRC_ZP_030 | C90: E
A91: SRC_ZP | B91: SRC_ZP_030 | C91: F
A92: SRC_ZP | B92: SRC_ZP_031 | C92: D | D92: 0.3136
A93: SRC_ZP | B93: SRC_ZP_031 | C93: E
A94: SRC_ZP | B94: SRC_ZP_031 | C94: F
A95: SRC_ZP | B95: SRC_ZP_032 | C95: D | D95: 0.8048
A96: SRC_ZP | B96: SRC_ZP_032 | C96: E
A97: SRC_ZP | B97: SRC_ZP_032 | C97: F
A98: SRC_ZP | B98: SRC_ZP_033 | C98: D | D98: 1.7589
A99: SRC_ZP | B99: SRC_ZP_033 | C99: E
A100: SRC_ZP | B100: SRC_ZP_033 | C100: F
...
