Workbook

Sheet README
A1: 智譜（智譜華章，02513.HK）收支模型 v0.1.2（2026-10-22）
A2: 命題（規格 D1，與 OpenAI v0.6 同一句）：智譜每 VR 等值 GW 的年營收能否覆蓋每 GW 年全成本；若不能，缺口要多少外部資金、由誰以什麼條件提供。FY2025–FY2030，曆年制。
A4: 本版範圍 | B4: v0.1（Z2–Z4）：SRC_ZP（公司財務原始數據）、TK_Link（Tokenomics 快照）、OAI_Link（OpenAI v0.6 命題輸出快照）、Inputs（假設）、Demand（需求與 token）、Revenue（營收）、Compute（算力）、Cost（成本與命題表）、Funding（融資，命題 2）、Reverse（反向模式，只對照）、Checks。v0.1.2：Revenue 第七節官方分部（部署方式）對帳列＋Checks C100–C103（既有數值不變）。
A5: 幣別與單位 | B5: 公司金額一律人民幣億元（RMB 億），與財報一致。港幣、美元數據以 Inputs 匯率（USD/CNY、HKD/CNY，2026-09-28 中間價；定義常數，區間 ±5%）換算後才進計算頁。API 牌價：人民幣元／百萬 token；token：兆（T）；Coding Plan 訂閱者：萬人；智譜清言用戶：百萬人。OAI_Link 為美元（$B），不換算、不參與計算。
A6: Excel 為唯一計算引擎 | B6: 藍字＝輸入（Excel 擁有）；黑字＝公式；綠字＝跨頁連結。builder 只產生結構，重建時保留 Excel 內已改過的藍字（隱藏頁 _Defaults）。公式不含常數（E6）：單位換算、天數、月數為 Inputs 的定義常數。
A7: SRC_ZP | B7: 1054 列（SRC_ZP_001–1054，Z1 發出、穩定不改號）；有數值者具名 SRC_ZP_nnn，有低／高者另具名 _Lo／_Hi。來源四欄為 CC 初評（builder/source_rules.py）。
A8: TK_Link | B8: Tokenomics v19.0（20261022_Tokenomics_v19.0.xlsx），master 提交 1916a06，讀取日 2026-10-22；77 個具名範圍（OpenAI v0.6 的 63 名＋智譜 Z3b 的逐 token 類型單位成本 9 名＋Z5b 的 IF_OpexGW、IF_DeprLifeIT＋v0.1.1 的 RNG_ 區間與時效旗標 3 名）＋7 列以列標籤讀表（狀態『讀表（非具名）』，只供對照）。
A9: OAI_Link | B9: OpenAI Excel（20261022_OpenAI_v0.6.2.xlsx，main@f645e19；SHA-256 7f023c084f2f6f3f…）的命題輸出逐年值（美元）；只被 Checks 與 HTML 引用（規格 D26）。
A10: Inputs | B10: 140 列（INP_001 起，依 data/zhipu_inputs.yaml 的鍵發號）；每列附標記、依據、區間理由；Analogy／Assumed 一律給區間。
A11: Demand | B11: 需求：①API 按量計費 token（2025、1H26＝營收 ÷ 有效單價倒推；2H26 起任務數 × 每任務 token × 價格反應）②GLM Coding Plan 訂閱者（方案別）× 每訂閱者 token ③智譜清言（免費）用戶 × 任務 × 每任務 token；輸出 DEM_Tok_*（層級 Sol／Luna × 付費／免費）。本地化部署不耗智譜算力，不進 Demand（D4）。
A12: Revenue | B12: 營收：①開放平台及 API（按量計費：層級 × 輸入／快取／輸出 × 有效價；Coding Plan 子列：方案別訂閱）②企業級智能體 ③企業級通用大模型 ④技術服務及其他（②③④＝本地化部署分部，規格 D2r）；廣告＝0（D3）；總額＝淨額（D5）；雲端 vs 本地化、企業 vs 個人彙總；2025 與 1H26 對財報校準差距＝0；公司說法（ARR、平均售價 +101%、呼叫量 40 倍）只列對照；第七節（v0.1.2）官方分部（本地化部署／雲端部署）對帳：FY2025 對年報、1H26 對中期公告子項加總，差額與 OK／差異判定（容差 Inputs seg_recon_tol）。
A13: Compute | B13: 晶片族（Hopper＝TK Hopper H100 欄；H20、國產＝Hopper × Inputs 比例，Tokenomics 缺口）× 層級（Sol／Luna）每 GW 年產能 → token 換算推論 GW；2025、1H26 算力服務費（推論＝API 銷售成本、研發＝研發開支扣股權報酬 × 占比）÷ 每 GW 價格（卡時租價 × 每 GW 卡數 × 小時）→ 供給 GW 與 η；2H26 起有效推論 GW＝token GW ÷ η，供給依需求配置；研發 GW＝殘差；容量上限係數回乘雲端營收；VR 等值 GW；10 萬國產晶片對照；R4 對帳；敏感度。
A14: Cost | B14: 算力成本（2025、1H26＝算力服務費實付；之後＝租用 GW × 每 GW 價格＋自有資本支出，基準 0）、供應商持有成本與雲端毛利、本地化部署交付成本、非算力成本（2025、1H26＝財報殘差；之後人數 × 每人成本）、股權報酬；命題表：每 VR 等值 GW 的營收、成本、差額、雲端口徑差額、覆蓋率（人民幣億與美元 $B）。2025 與 1H26 全成本對財報費用合計差距＝0。
A15: Funding | B15: 自由現金流（營收 − 算力 − 本地化交付 − 非算力（股權報酬加回）＋其他收益 − 利息）→ 非算力資本支出、併購 → 來源順序：①期初現金 ②已到位股權（2026-01 IPO、2026-07、2026-09 配售淨額，港幣 × 匯率）③已提用債務（銀行借款續借；可換股債券 2H26 流入、2027-09 到期償還，D16r）④外部資金需求（年底補足至最低現金，D17）。另列可換股債券轉股情境、或有、配售用途對照、回流對照（D19）、2025／1H26 現金對帳。
... A19: 分層 | B19: 公司財務原始數據→SRC_ZP；AI 技術與算力→TK_Link（取自 Tokenomics）；假設→Inputs；OpenAI 對照→OAI_Link（不進計算）。

Sheet SRC_ZP
A1: SRC_ZP — 第 0 層 Source：智譜公司財務原始數據（財報、分部、牌價、用戶、算力採購、融資、股本與市值）
A2: 只存已取得的原始訊息（非計算、非假設）。藍字＝原始值，由本活頁簿擁有；來源 data/zhipu_src.yaml（Z1）。AI 技術與算力的物理數據不在此登錄（取自 TK_Link）。
A3: 來源等級（1 一手已讀原文／2 二手或轉載／3 待查核）、立場、立場說明、一手／二手：builder/source_rules.py 機械初評（欄 X 標『CC 初評』）。無數值列＝日期、事件或找不到數值的說明列（另見 Checks）。
A4: SRC_ID | B4: 鍵（key） | C4: 項目 | D4: 值 | E4: 低 | F4: 高 | G4: 單位 | H4: 期間 | I4: 來源 | J4: 網址 | K4: 文件日期 | L4: 擷取日 | M4: 標記 | N4: 利害方與誘因 | O4: 口徑（basis） | P4: 來源等級 | Q4: 立場 | R4: 立場說明 | S4: 一手／二手 | T4: 備註 | U4: 無數值（公式） | V4: 缺出處（公式） | W4: 區間順序異常（公式） | X4: 四欄標註
A5: SRC_ZP_001 | B5: rev_total_fy22 | C5: 營收總額 | D5: 0.5741 | G5: RMB 億 | H5: FY2022 | I5: 智譜招股章程（概要節） | J5: https://www1.hkexnews.hk/listedco/listconews/sehk/2025/1230/2025123000018_c.pdf | K5: 2025-12-30 | L5: 2026-10-08 | M5: Verified | O5: 經審計（會計師報告，招股章程概要轉載） | P5: 1 | Q5: 利害關係方 | R5: 經審計或經審閱的公司公告（誘因：上市後股價、配售；數字可由公告原文核對） | S5: 一手 | T5: 原文「收入 57,409 100.0」；千元值 57,409；RMB 千元÷100,000 換算成億 | U5: =IF(AND($D5="",$E5="",$F5=""),1,0) -> 0 | V5: =IF(OR($I5="",$I5="—"),1,0) -> 0 | W5: =IF(AND(ISNUMBER($D5),ISNUMBER($E5)),IF($E5>$D5,1,0),0)+IF(AND(ISNUMBER($D5),ISNUMBER($F5)),IF($D5>$F5,1,0),0)+IF(AND(ISNUMBER($E5),ISNUMBER($F5)),IF($E5>$F5,1,0),0) -> 0 | X5: CC 初評
A6: SRC_ZP_002 | B6: rev_total_fy23 | C6: 營收總額 | D6: 1.2454 | G6: RMB 億 | H6: FY2023 | I6: 智譜招股章程（概要節） | J6: https://www1.hkexnews.hk/listedco/listconews/sehk/2025/1230/2025123000018_c.pdf | K6: 2025-12-30 | L6: 2026-10-08 | M6: Verified | O6: 經審計（會計師報告，招股章程概要轉載） | P6: 1 | Q6: 利害關係方 | R6: 經審計或經審閱的公司公告（誘因：上市後股價、配售；數字可由公告原文核對） | S6: 一手 | T6: 原文「收入 57,409 100.0」；千元值 124,538；RMB 千元÷100,000 換算成億 | U6: =IF(AND($D6="",$E6="",$F6=""),1,0) -> 0 | V6: =IF(OR($I6="",$I6="—"),1,0) -> 0 | W6: =IF(AND(ISNUMBER($D6),ISNUMBER($E6)),IF($E6>$D6,1,0),0)+IF(AND(ISNUMBER($D6),ISNUMBER($F6)),IF($D6>$F6,1,0),0)+IF(AND(ISNUMBER($E6),ISNUMBER($F6)),IF($E6>$F6,1,0),0) -> 0 | X6: CC 初評
A7: SRC_ZP_003 | B7: rev_total_fy24 | C7: 營收總額 | D7: 3.1241 | G7: RMB 億 | H7: FY2024 | I7: 智譜招股章程（概要節） | J7: https://www1.hkexnews.hk/listedco/listconews/sehk/2025/1230/2025123000018_c.pdf | K7: 2025-12-30 | L7: 2026-10-08 | M7: Verified | O7: 經審計（會計師報告，招股章程概要轉載） | P7: 1 | Q7: 利害關係方 | R7: 經審計或經審閱的公司公告（誘因：上市後股價、配售；數字可由公告原文核對） | S7: 一手 | T7: 原文「收入 57,409 100.0」；千元值 312,414；RMB 千元÷100,000 換算成億 | U7: =IF(AND($D7="",$E7="",$F7=""),1,0) -> 0 | V7: =IF(OR($I7="",$I7="—"),1,0) -> 0 | W7: =IF(AND(ISNUMBER($D7),ISNUMBER($E7)),IF($E7>$D7,1,0),0)+IF(AND(ISNUMBER($D7),ISNUMBER($F7)),IF($D7>$F7,1,0),0)+IF(AND(ISNUMBER($E7),ISNUMBER($F7)),IF($E7>$F7,1,0),0) -> 0 | X7: CC 初評
A8: SRC_ZP_004 | B8: rev_total_1h24 | C8: 營收總額 | D8: 0.4491 | G8: RMB 億 | H8: 1H2024 | I8: 智譜招股章程（概要節） | J8: https://www1.hkexnews.hk/listedco/listconews/sehk/2025/1230/2025123000018_c.pdf | K8: 2025-12-30 | L8: 2026-10-08 | M8: Verified | O8: 會計師報告（1H2024 比較期通常為未經審計已審閱；招股章程概要轉載） | P8: 1 | Q8: 利害關係方 | R8: 經審計或經審閱的公司公告（誘因：上市後股價、配售；數字可由公告原文核對） | S8: 一手 | T8: 原文「收入 57,409 100.0」；千元值 44,909；RMB 千元÷100,000 換算成億 | U8: =IF(AND($D8="",$E8="",$F8=""),1,0) -> 0 | V8: =IF(OR($I8="",$I8="—"),1,0) -> 0 | W8: =IF(AND(ISNUMBER($D8),ISNUMBER($E8)),IF($E8>$D8,1,0),0)+IF(AND(ISNUMBER($D8),ISNUMBER($F8)),IF($D8>$F8,1,0),0)+IF(AND(ISNUMBER($E8),ISNUMBER($F8)),IF($E8>$F8,1,0),0) -> 0 | X8: CC 初評
A9: SRC_ZP_005 | B9: rev_total_1h25 | C9: 營收總額 | D9: 1.9088 | G9: RMB 億 | H9: 1H2025 | I9: 智譜招股章程（概要節） | J9: https://www1.hkexnews.hk/listedco/listconews/sehk/2025/1230/2025123000018_c.pdf | K9: 2025-12-30 | L9: 2026-10-08 | M9: Verified | O9: 經審計（會計師報告，招股章程概要轉載） | P9: 1 | Q9: 利害關係方 | R9: 經審計或經審閱的公司公告（誘因：上市後股價、配售；數字可由公告原文核對） | S9: 一手 | T9: 原文「收入 57,409 100.0」；千元值 190,877；RMB 千元÷100,000 換算成億 | U9: =IF(AND($D9="",$E9="",$F9=""),1,0) -> 0 | V9: =IF(OR($I9="",$I9="—"),1,0) -> 0 | W9: =IF(AND(ISNUMBER($D9),ISNUMBER($E9)),IF($E9>$D9,1,0),0)+IF(AND(ISNUMBER($D9),ISNUMBER($F9)),IF($D9>$F9,1,0),0)+IF(AND(ISNUMBER($E9),ISNUMBER($F9)),IF($E9>$F9,1,0),0) -> 0 | X9: CC 初評
A10: SRC_ZP_006 | B10: rev_onprem_fy22 | C10: 本地化部署收入（舊分部） | D10: 0.5482 | G10: RMB 億 | H10: FY2022 | I10: 智譜招股章程（概要節） | J10: https://www1.hkexnews.hk/listedco/listconews/sehk/2025/1230/2025123000018_c.pdf | K10: 2025-12-30 | L10: 2026-10-08 | M10: Verified | O10: 經審計（會計師報告，招股章程概要轉載） | P10: 1 | Q10: 利害關係方 | R10: 經審計或經審閱的公司公告（誘因：上市後股價、配售；數字可由公告原文核對） | S10: 一手 | T10: 原文「本地化部署 54,815 95.5%」；千元值 54,815；RMB 千元÷100,000 換算成億；占比 95.5/90.4/84.5/59.7/84.8% | U10: =IF(AND($D10="",$E10="",$F10=""),1,0) -> 0 | V10: =IF(OR($I10="",$I10="—"),1,0) -> 0 | W10: =IF(AND(ISNUMBER($D10),ISNUMBER($E10)),IF($E10>$D10,1,0),0)+IF(AND(ISNUMBER($D10),ISNUMBER($F10)),IF($D10>$F10,1,0),0)+IF(AND(ISNUMBER($E10),ISNUMBER($F10)),IF($E10>$F10,1,0),0) -> 0 | X10: CC 初評
A11: SRC_ZP_007 | B11: rev_onprem_fy23 | C11: 本地化部署收入（舊分部） | D11: 1.1261 | G11: RMB 億 | H11: FY2023 | I11: 智譜招股章程（概要節） | J11: https://www1.hkexnews.hk/listedco/listconews/sehk/2025/1230/2025123000018_c.pdf | K11: 2025-12-30 | L11: 2026-10-08 | M11: Verified | O11: 經審計（會計師報告，招股章程概要轉載） | P11: 1 | Q11: 利害關係方 | R11: 經審計或經審閱的公司公告（誘因：上市後股價、配售；數字可由公告原文核對） | S11: 一手 | T11: 原文「本地化部署 54,815 95.5%」；千元值 112,614；RMB 千元÷100,000 換算成億；占比 95.5/90.4/84.5/59.7/84.8% | U11: =IF(AND($D11="",$E11="",$F11=""),1,0) -> 0 | V11: =IF(OR($I11="",$I11="—"),1,0) -> 0 | W11: =IF(AND(ISNUMBER($D11),ISNUMBER($E11)),IF($E11>$D11,1,0),0)+IF(AND(ISNUMBER($D11),ISNUMBER($F11)),IF($D11>$F11,1,0),0)+IF(AND(ISNUMBER($E11),ISNUMBER($F11)),IF($E11>$F11,1,0),0) -> 0 | X11: CC 初評
A12: SRC_ZP_008 | B12: rev_onprem_fy24 | C12: 本地化部署收入（舊分部） | D12: 2.6393 | G12: RMB 億 | H12: FY2024 | I12: 智譜招股章程（概要節） | J12: https://www1.hkexnews.hk/listedco/listconews/sehk/2025/1230/2025123000018_c.pdf | K12: 2025-12-30 | L12: 2026-10-08 | M12: Verified | O12: 經審計（會計師報告，招股章程概要轉載） | P12: 1 | Q12: 利害關係方 | R12: 經審計或經審閱的公司公告（誘因：上市後股價、配售；數字可由公告原文核對） | S12: 一手 | T12: 原文「本地化部署 54,815 95.5%」；千元值 263,930；RMB 千元÷100,000 換算成億；占比 95.5/90.4/84.5/59.7/84.8% | U12: =IF(AND($D12="",$E12="",$F12=""),1,0) -> 0 | V12: =IF(OR($I12="",$I12="—"),1,0) -> 0 | W12: =IF(AND(ISNUMBER($D12),ISNUMBER($E12)),IF($E12>$D12,1,0),0)+IF(AND(ISNUMBER($D12),ISNUMBER($F12)),IF($D12>$F12,1,0),0)+IF(AND(ISNUMBER($E12),ISNUMBER($F12)),IF($E12>$F12,1,0),0) -> 0 | X12: CC 初評
A13: SRC_ZP_009 | B13: rev_onprem_1h24 | C13: 本地化部署收入（舊分部） | D13: 0.2681 | G13: RMB 億 | H13: 1H2024 | I13: 智譜招股章程（概要節） | J13: https://www1.hkexnews.hk/listedco/listconews/sehk/2025/1230/2025123000018_c.pdf | K13: 2025-12-30 | L13: 2026-10-08 | M13: Verified | O13: 會計師報告（1H2024 比較期通常為未經審計已審閱；招股章程概要轉載） | P13: 1 | Q13: 利害關係方 | R13: 經審計或經審閱的公司公告（誘因：上市後股價、配售；數字可由公告原文核對） | S13: 一手 | T13: 原文「本地化部署 54,815 95.5%」；千元值 26,806；RMB 千元÷100,000 換算成億；占比 95.5/90.4/84.5/59.7/84.8% | U13: =IF(AND($D13="",$E13="",$F13=""),1,0) -> 0 | V13: =IF(OR($I13="",$I13="—"),1,0) -> 0 | W13: =IF(AND(ISNUMBER($D13),ISNUMBER($E13)),IF($E13>$D13,1,0),0)+IF(AND(ISNUMBER($D13),ISNUMBER($F13)),IF($D13>$F13,1,0),0)+IF(AND(ISNUMBER($E13),ISNUMBER($F13)),IF($E13>$F13,1,0),0) -> 0 | X13: CC 初評
A14: SRC_ZP_010 | B14: rev_onprem_1h25 | C14: 本地化部署收入（舊分部） | D14: 1.6178 | G14: RMB 億 | H14: 1H2025 | I14: 智譜招股章程（概要節） | J14: https://www1.hkexnews.hk/listedco/listconews/sehk/2025/1230/2025123000018_c.pdf | K14: 2025-12-30 | L14: 2026-10-08 | M14: Verified | O14: 經審計（會計師報告，招股章程概要轉載） | P14: 1 | Q14: 利害關係方 | R14: 經審計或經審閱的公司公告（誘因：上市後股價、配售；數字可由公告原文核對） | S14: 一手 | T14: 原文「本地化部署 54,815 95.5%」；千元值 161,777；RMB 千元÷100,000 換算成億；占比 95.5/90.4/84.5/59.7/84.8% | U14: =IF(AND($D14="",$E14="",$F14=""),1,0) -> 0 | V14: =IF(OR($I14="",$I14="—"),1,0) -> 0 | W14: =IF(AND(ISNUMBER($D14),ISNUMBER($E14)),IF($E14>$D14,1,0),0)+IF(AND(ISNUMBER($D14),ISNUMBER($F14)),IF($D14>$F14,1,0),0)+IF(AND(ISNUMBER($E14),ISNUMBER($F14)),IF($E14>$F14,1,0),0) -> 0 | X14: CC 初評
A15: SRC_ZP_011 | B15: rev_cloud_fy22 | C15: 雲端部署收入（舊分部；＝開放平台及API） | D15: 0.0259 | G15: RMB 億 | H15: FY2022 | I15: 智譜招股章程（概要節） | J15: https://www1.hkexnews.hk/listedco/listconews/sehk/2025/1230/2025123000018_c.pdf | K15: 2025-12-30 | L15: 2026-10-08 | M15: Verified | O15: 經審計（會計師報告，招股章程概要轉載） | P15: 1 | Q15: 利害關係方 | R15: 經審計或經審閱的公司公告（誘因：上市後股價、配售；數字可由公告原文核對） | S15: 一手 | T15: 原文「雲端部署 2,594 4.5%」；千元值 2,594；RMB 千元÷100,000 換算成億；占比 4.5/9.6/15.5/40.3/15.2%；2025 起新分類下雲端部署＝開放平台及 API | U15: =IF(AND($D15="",$E15="",$F15=""),1,0) -> 0 | V15: =IF(OR($I15="",$I15="—"),1,0) -> 0 | W15: =IF(AND(ISNUMBER($D15),ISNUMBER($E15)),IF($E15>$D15,1,0),0)+IF(AND(ISNUMBER($D15),ISNUMBER($F15)),IF($D15>$F15,1,0),0)+IF(AND(ISNUMBER($E15),ISNUMBER($F15)),IF($E15>$F15,1,0),0) -> 0 | X15: CC 初評
A16: SRC_ZP_012 | B16: rev_cloud_fy23 | C16: 雲端部署收入（舊分部；＝開放平台及API） | D16: 0.1192 | G16: RMB 億 | H16: FY2023 | I16: 智譜招股章程（概要節） | J16: https://www1.hkexnews.hk/listedco/listconews/sehk/2025/1230/2025123000018_c.pdf | K16: 2025-12-30 | L16: 2026-10-08 | M16: Verified | O16: 經審計（會計師報告，招股章程概要轉載） | P16: 1 | Q16: 利害關係方 | R16: 經審計或經審閱的公司公告（誘因：上市後股價、配售；數字可由公告原文核對） | S16: 一手 | T16: 原文「雲端部署 2,594 4.5%」；千元值 11,924；RMB 千元÷100,000 換算成億；占比 4.5/9.6/15.5/40.3/15.2%；2025 起新分類下雲端部署＝開放平台及 API | U16: =IF(AND($D16="",$E16="",$F16=""),1,0) -> 0 | V16: =IF(OR($I16="",$I16="—"),1,0) -> 0 | W16: =IF(AND(ISNUMBER($D16),ISNUMBER($E16)),IF($E16>$D16,1,0),0)+IF(AND(ISNUMBER($D16),ISNUMBER($F16)),IF($D16>$F16,1,0),0)+IF(AND(ISNUMBER($E16),ISNUMBER($F16)),IF($E16>$F16,1,0),0) -> 0 | X16: CC 初評
... A109: SRC_ZP_105 | B109: gm_total_1h25 | C109: 整體毛利率 | D109: 50 | G109: % | H109: 1H2025 | I109: 智譜招股章程（概要節） | J109: https://www1.hkexnews.hk/listedco/listconews/sehk/2025/1230/2025123000018_c.pdf | K109: 2025-12-30 | L109: 2026-10-08 | M109: Verified | O109: 經審計（會計師報告，招股章程概要轉載） | P109: 1 | Q109: 利害關係方 | R109: 經審計或經審閱的公司公告（誘因：上市後股價、配售；數字可由公告原文核對） | S109: 一手 | T109: 原文「毛利 31,360 54.6」表內毛利率欄 | U109: =IF(AND($D109="",$E109="",$F109=""),1,0) -> 0 | V109: =IF(OR($I109="",$I109="—"),1,0) -> 0 | W109: =IF(AND(ISNUMBER($D109),ISNUMBER($E109)),IF($E109>$D109,1,0),0)+IF(AND(ISNUMBER($D109),ISNUMBER($F109)),IF($D109>$F109,1,0),0)+IF(AND(ISNUMBER($E109),ISNUMBER($F109)),IF($E109>$F109,1,0),0) -> 0 | X109: CC 初評
A110: SRC_ZP_106 | B110: cash_burn_m_fy22 | C110: 平均每月現金消耗率 | D110: 0.03 | G110: RMB 億／月 | H110: FY2022 | I110: 智譜招股章程（概要節） | J110: https://www1.hkexnews.hk/listedco/listconews/sehk/2025/1230/2025123000017.pdf | K110: 2025-12-30 | L110: 2026-10-08 | M110: Interested-party | N110: 智譜：IPO 招股，誘因為發行定價 | O110: 管理層口徑（招股章程） | P110: 1 | Q110: 利害關係方 | R110: 智譜：IPO 招股，誘因為發行定價 | S110: 一手 | T110: 原文 average monthly cash burn RMB3.0 million；含經營現金流、購置設備、理財淨額、租賃付款；百萬÷100 換算成億 | U110: =IF(AND($D110="",$E110="",$F110=""),1,0) -> 0 | V110: =IF(OR($I110="",$I110="—"),1,0) -> 0 | W110: =IF(AND(ISNUMBER($D110),ISNUMBER($E110)),IF($E110>$D110,1,0),0)+IF(AND(ISNUMBER($D110),ISNUMBER($F110)),IF($D110>$F110,1,0),0)+IF(AND(ISNUMBER($E110),ISNUMBER($F110)),IF($E110>$F110,1,0),0) -> 0 | X110: CC 初評
A111: SRC_ZP_107 | B111: cash_burn_m_fy23 | C111: 平均每月現金消耗率 | D111: 1.059 | G111: RMB 億／月 | H111: FY2023 | I111: 智譜招股章程（概要節） | J111: https://www1.hkexnews.hk/listedco/listconews/sehk/2025/1230/2025123000017.pdf | K111: 2025-12-30 | L111: 2026-10-08 | M111: Interested-party | N111: 智譜：IPO 招股，誘因為發行定價 | O111: 管理層口徑（招股章程） | P111: 1 | Q111: 利害關係方 | R111: 智譜：IPO 招股，誘因為發行定價 | S111: 一手 | T111: 原文 average monthly cash burn RMB105.9 million；含經營現金流、購置設備、理財淨額、租賃付款；百萬÷100 換算成億 | U111: =IF(AND($D111="",$E111="",$F111=""),1,0) -> 0 | V111: =IF(OR($I111="",$I111="—"),1,0) -> 0 | W111: =IF(AND(ISNUMBER($D111),ISNUMBER($E111)),IF($E111>$D111,1,0),0)+IF(AND(ISNUMBER($D111),ISNUMBER($F111)),IF($D111>$F111,1,0),0)+IF(AND(ISNUMBER($E111),ISNUMBER($F111)),IF($E111>$F111,1,0),0) -> 0 | X111: CC 初評
A112: SRC_ZP_108 | B112: cash_burn_m_fy24 | C112: 平均每月現金消耗率 | D112: 1.945 | G112: RMB 億／月 | H112: FY2024 | I112: 智譜招股章程（概要節） | J112: https://www1.hkexnews.hk/listedco/listconews/sehk/2025/1230/2025123000017.pdf | K112: 2025-12-30 | L112: 2026-10-08 | M112: Interested-party | N112: 智譜：IPO 招股，誘因為發行定價 | O112: 管理層口徑（招股章程） | P112: 1 | Q112: 利害關係方 | R112: 智譜：IPO 招股，誘因為發行定價 | S112: 一手 | T112: 原文 average monthly cash burn RMB194.5 million；含經營現金流、購置設備、理財淨額、租賃付款；百萬÷100 換算成億 | U112: =IF(AND($D112="",$E112="",$F112=""),1,0) -> 0 | V112: =IF(OR($I112="",$I112="—"),1,0) -> 0 | W112: =IF(AND(ISNUMBER($D112),ISNUMBER($E112)),IF($E112>$D112,1,0),0)+IF(AND(ISNUMBER($D112),ISNUMBER($F112)),IF($D112>$F112,1,0),0)+IF(AND(ISNUMBER($E112),ISNUMBER($F112)),IF($E112>$F112,1,0),0) -> 0 | X112: CC 初評
A113: SRC_ZP_109 | B113: cash_burn_m_1h25 | C113: 平均每月現金消耗率 | D113: 3.273 | G113: RMB 億／月 | H113: 1H2025 | I113: 智譜招股章程（概要節） | J113: https://www1.hkexnews.hk/listedco/listconews/sehk/2025/1230/2025123000017.pdf | K113: 2025-12-30 | L113: 2026-10-08 | M113: Interested-party | N113: 智譜：IPO 招股，誘因為發行定價 | O113: 管理層口徑（招股章程） | P113: 1 | Q113: 利害關係方 | R113: 智譜：IPO 招股，誘因為發行定價 | S113: 一手 | T113: 原文 average monthly cash burn RMB327.3 million；含經營現金流、購置設備、理財淨額、租賃付款；百萬÷100 換算成億 | U113: =IF(AND($D113="",$E113="",$F113=""),1,0) -> 0 | V113: =IF(OR($I113="",$I113="—"),1,0) -> 0 | W113: =IF(AND(ISNUMBER($D113),ISNUMBER($E113)),IF($E113>$D113,1,0),0)+IF(AND(ISNUMBER($D113),ISNUMBER($F113)),IF($D113>$F113,1,0),0)+IF(AND(ISNUMBER($E113),ISNUMBER($F113)),IF($E113>$F113,1,0),0) -> 0 | X113: CC 初評
A114: SRC_ZP_110 | B114: liquidity_2510 | C114: 現金＋FVPL 短期投資＋可用承諾銀行授信合計 | D114: 89.431 | G114: RMB 億 | H114: 2025-10-31 | I114: 智譜招股章程（概要節） | J114: https://www1.hkexnews.hk/listedco/listconews/sehk/2025/1230/2025123000017.pdf | K114: 2025-12-30 | L114: 2026-10-08 | M114: Interested-party | N114: 智譜：IPO 招股，營運資金說明 | O114: 管理層口徑（招股章程營運資金充足性） | P114: 1 | Q114: 利害關係方 | R114: 智譜：IPO 招股，營運資金說明 | S114: 一手 | T114: 原文「available committed bank facilities of RMB8,943.1 million in aggregate」；三項合計，未拆授信額 | U114: =IF(AND($D114="",$E114="",$F114=""),1,0) -> 0 | V114: =IF(OR($I114="",$I114="—"),1,0) -> 0 | W114: =IF(AND(ISNUMBER($D114),ISNUMBER($E114)),IF($E114>$D114,1,0),0)+IF(AND(ISNUMBER($D114),ISNUMBER($F114)),IF($D114>$F114,1,0),0)+IF(AND(ISNUMBER($E114),ISNUMBER($F114)),IF($E114>$F114,1,0),0) -> 0 | X114: CC 初評
A115: SRC_ZP_111 | B115: rd_staff_1h25 | C115: 研發團隊人數 | D115: 657 | G115: 人 | H115: 2025-06-30 | I115: 智譜招股章程（概要節） | J115: https://www1.hkexnews.hk/listedco/listconews/sehk/2025/1230/2025123000018_c.pdf | K115: 2025-12-30 | L115: 2026-10-08 | M115: Verified | O115: 管理層口徑 | P115: 1 | Q115: 利害關係方 | R115: 經審計或經審閱的公司公告（誘因：上市後股價、配售；數字可由公告原文核對） | S115: 一手 | T115: 原文「一支由657名成員組成的研發團隊」 | U115: =IF(AND($D115="",$E115="",$F115=""),1,0) -> 0 | V115: =IF(OR($I115="",$I115="—"),1,0) -> 0 | W115: =IF(AND(ISNUMBER($D115),ISNUMBER($E115)),IF($E115>$D115,1,0),0)+IF(AND(ISNUMBER($D115),ISNUMBER($F115)),IF($D115>$F115,1,0),0)+IF(AND(ISNUMBER($E115),ISNUMBER($F115)),IF($E115>$F115,1,0),0) -> 0 | X115: CC 初評
A116: SRC_ZP_112 | B116: rev_api_fy25 | C116: 開放平台及 API 收入（新分類） | D116: 1.9038 | G116: RMB 億 | H116: FY2025 | I116: 智譜 2025 年度業績公告 | J116: https://www1.hkexnews.hk/listedco/listconews/sehk/2026/0331/2026033101549.pdf | K116: 2026-03-31 | L116: 2026-10-08 | M116: Verified | O116: 經審計（KPMG；年度業績公告） | P116: 1 | Q116: 利害關係方 | R116: 經審計或經審閱的公司公告（誘因：上市後股價、配售；數字可由公告原文核對） | S116: 一手 | T116: 原文「Open Platform and API」；千元值 190,379；RMB 千元÷100,000 換算成億；2025 占營收 26.3%；新分類下＝雲端部署 | U116: =IF(AND($D116="",$E116="",$F116=""),1,0) -> 0 | V116: =IF(OR($I116="",$I116="—"),1,0) -> 0 | W116: =IF(AND(ISNUMBER($D116),ISNUMBER($E116)),IF($E116>$D116,1,0),0)+IF(AND(ISNUMBER($D116),ISNUMBER($F116)),IF($D116>$F116,1,0),0)+IF(AND(ISNUMBER($E116),ISNUMBER($F116)),IF($E116>$F116,1,0),0) -> 0 | X116: CC 初評
A117: SRC_ZP_113 | B117: rev_api_fy24 | C117: 開放平台及 API 收入（新分類） | D117: 0.4848 | G117: RMB 億 | H117: FY2024 | I117: 智譜 2025 年度業績公告 | J117: https://www1.hkexnews.hk/listedco/listconews/sehk/2026/0331/2026033101549.pdf | K117: 2026-03-31 | L117: 2026-10-08 | M117: Verified | O117: 經審計（KPMG；年度業績公告） | P117: 1 | Q117: 利害關係方 | R117: 經審計或經審閱的公司公告（誘因：上市後股價、配售；數字可由公告原文核對） | S117: 一手 | T117: 原文「Open Platform and API」；千元值 48,484；RMB 千元÷100,000 換算成億；2025 占營收 26.3%；新分類下＝雲端部署 | U117: =IF(AND($D117="",$E117="",$F117=""),1,0) -> 0 | V117: =IF(OR($I117="",$I117="—"),1,0) -> 0 | W117: =IF(AND(ISNUMBER($D117),ISNUMBER($E117)),IF($E117>$D117,1,0),0)+IF(AND(ISNUMBER($D117),ISNUMBER($F117)),IF($D117>$F117,1,0),0)+IF(AND(ISNUMBER($E117),ISNUMBER($F117)),IF($E117>$F117,1,0),0) -> 0 | X117: CC 初評
A118: SRC_ZP_114 | B118: rev_agent_fy25 | C118: 企業級智能體收入（新分類） | D118: 1.6569 | G118: RMB 億 | H118: FY2025 | I118: 智譜 2025 年度業績公告 | J118: https://www1.hkexnews.hk/listedco/listconews/sehk/2026/0331/2026033101549.pdf | K118: 2026-03-31 | L118: 2026-10-08 | M118: Verified | O118: 經審計（KPMG；年度業績公告） | P118: 1 | Q118: 利害關係方 | R118: 經審計或經審閱的公司公告（誘因：上市後股價、配售；數字可由公告原文核對） | S118: 一手 | T118: 原文「Enterprise-level Agents」；千元值 165,687；RMB 千元÷100,000 換算成億；屬本地化部署分部 | U118: =IF(AND($D118="",$E118="",$F118=""),1,0) -> 0 | V118: =IF(OR($I118="",$I118="—"),1,0) -> 0 | W118: =IF(AND(ISNUMBER($D118),ISNUMBER($E118)),IF($E118>$D118,1,0),0)+IF(AND(ISNUMBER($D118),ISNUMBER($F118)),IF($D118>$F118,1,0),0)+IF(AND(ISNUMBER($E118),ISNUMBER($F118)),IF($E118>$F118,1,0),0) -> 0 | X118: CC 初評
A119: SRC_ZP_115 | B119: rev_agent_fy24 | C119: 企業級智能體收入（新分類） | D119: 0.4749 | G119: RMB 億 | H119: FY2024 | I119: 智譜 2025 年度業績公告 | J119: https://www1.hkexnews.hk/listedco/listconews/sehk/2026/0331/2026033101549.pdf | K119: 2026-03-31 | L119: 2026-10-08 | M119: Verified | O119: 經審計（KPMG；年度業績公告） | P119: 1 | Q119: 利害關係方 | R119: 經審計或經審閱的公司公告（誘因：上市後股價、配售；數字可由公告原文核對） | S119: 一手 | T119: 原文「Enterprise-level Agents」；千元值 47,492；RMB 千元÷100,000 換算成億；屬本地化部署分部 | U119: =IF(AND($D119="",$E119="",$F119=""),1,0) -> 0 | V119: =IF(OR($I119="",$I119="—"),1,0) -> 0 | W119: =IF(AND(ISNUMBER($D119),ISNUMBER($E119)),IF($E119>$D119,1,0),0)+IF(AND(ISNUMBER($D119),ISNUMBER($F119)),IF($D119>$F119,1,0),0)+IF(AND(ISNUMBER($E119),ISNUMBER($F119)),IF($E119>$F119,1,0),0) -> 0 | X119: CC 初評
A120: SRC_ZP_116 | B120: rev_gpllm_fy25 | C120: 企業級通用大模型收入（新分類） | D120: 3.6572 | G120: RMB 億 | H120: FY2025 | I120: 智譜 2025 年度業績公告 | J120: https://www1.hkexnews.hk/listedco/listconews/sehk/2026/0331/2026033101549.pdf | K120: 2026-03-31 | L120: 2026-10-08 | M120: Verified | O120: 經審計（KPMG；年度業績公告） | P120: 1 | Q120: 利害關係方 | R120: 經審計或經審閱的公司公告（誘因：上市後股價、配售；數字可由公告原文核對） | S120: 一手 | T120: 原文「Enterprise-level General-purpose Large Models」；千元值 365,724；RMB 千元÷100,000 換算成億；屬本地化部署分部 | U120: =IF(AND($D120="",$E120="",$F120=""),1,0) -> 0 | V120: =IF(OR($I120="",$I120="—"),1,0) -> 0 | W120: =IF(AND(ISNUMBER($D120),ISNUMBER($E120)),IF($E120>$D120,1,0),0)+IF(AND(ISNUMBER($D120),ISNUMBER($F120)),IF($D120>$F120,1,0),0)+IF(AND(ISNUMBER($E120),ISNUMBER($F120)),IF($E120>$F120,1,0),0) -> 0 | X120: CC 初評
A121: SRC_ZP_117 | B121: rev_gpllm_fy24 | C121: 企業級通用大模型收入（新分類） | D121: 2.145 | G121: RMB 億 | H121: FY2024 | I121: 智譜 2025 年度業績公告 | J121: https://www1.hkexnews.hk/listedco/listconews/sehk/2026/0331/2026033101549.pdf | K121: 2026-03-31 | L121: 2026-10-08 | M121: Verified | O121: 經審計（KPMG；年度業績公告） | P121: 1 | Q121: 利害關係方 | R121: 經審計或經審閱的公司公告（誘因：上市後股價、配售；數字可由公告原文核對） | S121: 一手 | T121: 原文「Enterprise-level General-purpose Large Models」；千元值 214,502；RMB 千元÷100,000 換算成億；屬本地化部署分部 | U121: =IF(AND($D121="",$E121="",$F121=""),1,0) -> 0 | V121: =IF(OR($I121="",$I121="—"),1,0) -> 0 | W121: =IF(AND(ISNUMBER($D121),ISNUMBER($E121)),IF($E121>$D121,1,0),0)+IF(AND(ISNUMBER($D121),ISNUMBER($F121)),IF($D121>$F121,1,0),0)+IF(AND(ISNUMBER($E121),ISNUMBER($F121)),IF($E121>$F121,1,0),0) -> 0 | X121: CC 初評
A122: SRC_ZP_118 | B122: rev_techsvc_fy25 | C122: 技術服務及其他收入（新分類） | D122: 0.0254 | G122: RMB 億 | H122: FY2025 | I122: 智譜 2025 年度業績公告 | J122: https://www1.hkexnews.hk/listedco/listconews/sehk/2026/0331/2026033101549.pdf | K122: 2026-03-31 | L122: 2026-10-08 | M122: Verified | O122: 經審計（KPMG；年度業績公告） | P122: 1 | Q122: 利害關係方 | R122: 經審計或經審閱的公司公告（誘因：上市後股價、配售；數字可由公告原文核對） | S122: 一手 | T122: 原文「Technical Services and Others」；千元值 2,544；RMB 千元÷100,000 換算成億 | U122: =IF(AND($D122="",$E122="",$F122=""),1,0) -> 0 | V122: =IF(OR($I122="",$I122="—"),1,0) -> 0 | W122: =IF(AND(ISNUMBER($D122),ISNUMBER($E122)),IF($E122>$D122,1,0),0)+IF(AND(ISNUMBER($D122),ISNUMBER($F122)),IF($D122>$F122,1,0),0)+IF(AND(ISNUMBER($E122),ISNUMBER($F122)),IF($E122>$F122,1,0),0) -> 0 | X122: CC 初評
A123: SRC_ZP_119 | B123: rev_techsvc_fy24 | C123: 技術服務及其他收入（新分類） | D123: 0.0194 | G123: RMB 億 | H123: FY2024 | I123: 智譜 2025 年度業績公告 | J123: https://www1.hkexnews.hk/listedco/listconews/sehk/2026/0331/2026033101549.pdf | K123: 2026-03-31 | L123: 2026-10-08 | M123: Verified | O123: 經審計（KPMG；年度業績公告） | P123: 1 | Q123: 利害關係方 | R123: 經審計或經審閱的公司公告（誘因：上市後股價、配售；數字可由公告原文核對） | S123: 一手 | T123: 原文「Technical Services and Others」；千元值 1,936；RMB 千元÷100,000 換算成億 | U123: =IF(AND($D123="",$E123="",$F123=""),1,0) -> 0 | V123: =IF(OR($I123="",$I123="—"),1,0) -> 0 | W123: =IF(AND(ISNUMBER($D123),ISNUMBER($E123)),IF($E123>$D123,1,0),0)+IF(AND(ISNUMBER($D123),ISNUMBER($F123)),IF($D123>$F123,1,0),0)+IF(AND(ISNUMBER($E123),ISNUMBER($F123)),IF($E123>$F123,1,0),0) -> 0 | X123: CC 初評
A124: SRC_ZP_120 | B124: rev_total_fy25 | C124: 營收總額 | D124: 7.2433 | G124: RMB 億 | H124: FY2025 | I124: 智譜 2025 年度業績公告 | J124: https://www1.hkexnews.hk/listedco/listconews/sehk/2026/0331/2026033101549.pdf | K124: 2026-03-31 | L124: 2026-10-08 | M124: Verified | O124: 經審計（KPMG；年度業績公告） | P124: 1 | Q124: 利害關係方 | R124: 經審計或經審閱的公司公告（誘因：上市後股價、配售；數字可由公告原文核對） | S124: 一手 | T124: 原文「total revenue reached RMB724.3 million」，同比 +131.9%；千元 724,334；RMB 千元÷100,000 換算成億 | U124: =IF(AND($D124="",$E124="",$F124=""),1,0) -> 0 | V124: =IF(OR($I124="",$I124="—"),1,0) -> 0 | W124: =IF(AND(ISNUMBER($D124),ISNUMBER($E124)),IF($E124>$D124,1,0),0)+IF(AND(ISNUMBER($D124),ISNUMBER($F124)),IF($D124>$F124,1,0),0)+IF(AND(ISNUMBER($E124),ISNUMBER($F124)),IF($E124>$F124,1,0),0) -> 0 | X124: CC 初評
A125: SRC_ZP_121 | B125: rev_onprem_fy25 | C125: 本地化部署收入（分部） | D125: 5.3396 | G125: RMB 億 | H125: FY2025 | I125: 智譜 2025 年度業績公告 | J125: https://www1.hkexnews.hk/listedco/listconews/sehk/2026/0331/2026033101549.pdf | K125: 2026-03-31 | L125: 2026-10-08 | M125: Verified | O125: 經審計（KPMG；年度業績公告） | P125: 1 | Q125: 利害關係方 | R125: 經審計或經審閱的公司公告（誘因：上市後股價、配售；數字可由公告原文核對） | S125: 一手 | T125: 分部附註 on-premise deployment 533,955 千元（＝智能體＋通用大模型＋技術服務）；RMB 千元÷100,000 換算成億 | U125: =IF(AND($D125="",$E125="",$F125=""),1,0) -> 0 | V125: =IF(OR($I125="",$I125="—"),1,0) -> 0 | W125: =IF(AND(ISNUMBER($D125),ISNUMBER($E125)),IF($E125>$D125,1,0),0)+IF(AND(ISNUMBER($D125),ISNUMBER($F125)),IF($D125>$F125,1,0),0)+IF(AND(ISNUMBER($E125),ISNUMBER($F125)),IF($E125>$F125,1,0),0) -> 0 | X125: CC 初評
A126: SRC_ZP_122 | B126: rev_cloud_fy25 | C126: 雲端部署收入（分部） | D126: 1.9038 | G126: RMB 億 | H126: FY2025 | I126: 智譜 2025 年度業績公告 | J126: https://www1.hkexnews.hk/listedco/listconews/sehk/2026/0331/2026033101549.pdf | K126: 2026-03-31 | L126: 2026-10-08 | M126: Verified | O126: 經審計（KPMG；年度業績公告） | P126: 1 | Q126: 利害關係方 | R126: 經審計或經審閱的公司公告（誘因：上市後股價、配售；數字可由公告原文核對） | S126: 一手 | T126: 分部附註 cloud-based deployment 190,379 千元＝開放平台及 API；RMB 千元÷100,000 換算成億 | U126: =IF(AND($D126="",$E126="",$F126=""),1,0) -> 0 | V126: =IF(OR($I126="",$I126="—"),1,0) -> 0 | W126: =IF(AND(ISNUMBER($D126),ISNUMBER($E126)),IF($E126>$D126,1,0),0)+IF(AND(ISNUMBER($D126),ISNUMBER($F126)),IF($D126>$F126,1,0),0)+IF(AND(ISNUMBER($E126),ISNUMBER($F126)),IF($E126>$F126,1,0),0) -> 0 | X126: CC 初評
... A168: SRC_ZP_164 | B168: comp_per_head_fy25 | C168: 人均薪酬（含股權報酬） | D168: 0.01246 | G168: RMB 億／人 | H168: FY2025 | I168: 智譜 2025 年度業績公告 | J168: https://www1.hkexnews.hk/listedco/listconews/sehk/2026/0331/2026033101549.pdf | K168: 2026-03-31 | L168: 2026-10-08 | M168: Derived | O168: Derived | P168: 2 | Q168: 推算 | R168: 由其他 SRC 列推算（見備註）；立場同其來源 | S168: 一手 | T168: 1,363.4 百萬÷期末人數 1,094＝約 RMB 124.6 萬／人；以期末人數計（無平均人數） | U168: =IF(AND($D168="",$E168="",$F168=""),1,0) -> 0 | V168: =IF(OR($I168="",$I168="—"),1,0) -> 0 | W168: =IF(AND(ISNUMBER($D168),ISNUMBER($E168)),IF($E168>$D168,1,0),0)+IF(AND(ISNUMBER($D168),ISNUMBER($F168)),IF($D168>$F168,1,0),0)+IF(AND(ISNUMBER($E168),ISNUMBER($F168)),IF($E168>$F168,1,0),0) -> 0 | X168: CC 初評
A169: SRC_ZP_165 | B169: esop_fy25 | C169: 員工激勵計畫 | H169: FY2025 | I169: 智譜 2025 年度業績公告 | J169: https://www1.hkexnews.hk/listedco/listconews/sehk/2026/0331/2026033101549.pdf | K169: 2026-03-31 | L169: 2026-10-08 | M169: Verified | O169: 經審計（KPMG；年度業績公告） | P169: 1 | Q169: 利害關係方 | R169: 經審計或經審閱的公司公告（誘因：上市後股價、配售；數字可由公告原文核對） | S169: 一手 | T169: 原文「adopted the employee incentive scheme and established an employee shareholding platform」；條款未揭露 | U169: =IF(AND($D169="",$E169="",$F169=""),1,0) -> 1 | V169: =IF(OR($I169="",$I169="—"),1,0) -> 0 | W169: =IF(AND(ISNUMBER($D169),ISNUMBER($E169)),IF($E169>$D169,1,0),0)+IF(AND(ISNUMBER($D169),ISNUMBER($F169)),IF($D169>$F169,1,0),0)+IF(AND(ISNUMBER($E169),ISNUMBER($F169)),IF($E169>$F169,1,0),0) -> 0 | X169: CC 初評
A170: SRC_ZP_166 | B170: api_price_fy25 | C170: API 呼叫價格較上年底上升 | D170: 83 | G170: % | H170: 2026Q1（公告時點） | I170: 智譜 2025 年度業績公告 | J170: https://www1.hkexnews.hk/listedco/listconews/sehk/2026/0331/2026033101549.pdf | K170: 2026-03-31 | L170: 2026-10-08 | M170: Interested-party | N170: 智譜：上市後股價、配售誘因 | O170: 管理層口徑 | P170: 1 | Q170: 利害關係方 | R170: 智譜：上市後股價、配售誘因 | S170: 一手 | T170: 原文「an 83% increase in API call pricing compared to the end of last year」 | U170: =IF(AND($D170="",$E170="",$F170=""),1,0) -> 0 | V170: =IF(OR($I170="",$I170="—"),1,0) -> 0 | W170: =IF(AND(ISNUMBER($D170),ISNUMBER($E170)),IF($E170>$D170,1,0),0)+IF(AND(ISNUMBER($D170),ISNUMBER($F170)),IF($D170>$F170,1,0),0)+IF(AND(ISNUMBER($E170),ISNUMBER($F170)),IF($E170>$F170,1,0),0) -> 0 | X170: CC 初評
A171: SRC_ZP_167 | B171: codingplan_class_fy25 | C171: GLM Coding Plan 收入歸屬 | H171: FY2025 | I171: 智譜 2025 年度業績公告 | J171: https://www1.hkexnews.hk/listedco/listconews/sehk/2026/0331/2026033101549.pdf | K171: 2026-03-31 | L171: 2026-10-08 | M171: Derived | O171: Derived | P171: 2 | Q171: 推算 | R171: 由其他 SRC 列推算（見備註）；立場同其來源 | S171: 一手 | T171: 公告於開放平台及 API 毛利段提及「programming subscription packages」；未單列收入。判定歸入開放平台及 API（雲端） | U171: =IF(AND($D171="",$E171="",$F171=""),1,0) -> 1 | V171: =IF(OR($I171="",$I171="—"),1,0) -> 0 | W171: =IF(AND(ISNUMBER($D171),ISNUMBER($E171)),IF($E171>$D171,1,0),0)+IF(AND(ISNUMBER($D171),ISNUMBER($F171)),IF($D171>$F171,1,0),0)+IF(AND(ISNUMBER($E171),ISNUMBER($F171)),IF($E171>$F171,1,0),0) -> 0 | X171: CC 初評
A172: SRC_ZP_168 | B172: codingplan_paying_fy25 | C172: Coding Plan 付費開發者 | D172: 242000 | E172: 242000 | G172: 人 | H172: FY2025 | I172: 智譜 2025 年度業績公告 | J172: https://www1.hkexnews.hk/listedco/listconews/sehk/2026/0331/2026033101549.pdf | K172: 2026-03-31 | L172: 2026-10-08 | M172: Interested-party | N172: 智譜：上市後股價、配售誘因 | O172: 管理層口徑 | P172: 1 | Q172: 利害關係方 | R172: 智譜：上市後股價、配售誘因 | S172: 一手 | T172: 原文 over 242,000 paying Coding Plan developers（下限值） | U172: =IF(AND($D172="",$E172="",$F172=""),1,0) -> 0 | V172: =IF(OR($I172="",$I172="—"),1,0) -> 0 | W172: =IF(AND(ISNUMBER($D172),ISNUMBER($E172)),IF($E172>$D172,1,0),0)+IF(AND(ISNUMBER($D172),ISNUMBER($F172)),IF($D172>$F172,1,0),0)+IF(AND(ISNUMBER($E172),ISNUMBER($F172)),IF($E172>$F172,1,0),0) -> 0 | X172: CC 初評
A173: SRC_ZP_169 | B173: rev_api_1h26 | C173: 開放平台及 API 收入 | D173: 8.2518 | G173: RMB 億 | H173: 1H2026 | I173: 智譜（Z.AI）2026 中期業績公告 | J173: https://www1.hkexnews.hk/listedco/listconews/sehk/2026/0831/2026083101539.pdf | K173: 2026-08-31 | L173: 2026-10-08 | M173: Verified | O173: 未經審計（中期業績公告；是否經核數師審閱公告未見明載） | P173: 1 | Q173: 利害關係方 | R173: 經審計或經審閱的公司公告（誘因：上市後股價、配售；數字可由公告原文核對） | S173: 一手 | T173: 原文「Open Platform and API」；千元值 825,176；RMB 千元÷100,000 換算成億；1H26 占 86.5%（1H25 15.2%）；＝雲端部署分部 | U173: =IF(AND($D173="",$E173="",$F173=""),1,0) -> 0 | V173: =IF(OR($I173="",$I173="—"),1,0) -> 0 | W173: =IF(AND(ISNUMBER($D173),ISNUMBER($E173)),IF($E173>$D173,1,0),0)+IF(AND(ISNUMBER($D173),ISNUMBER($F173)),IF($D173>$F173,1,0),0)+IF(AND(ISNUMBER($E173),ISNUMBER($F173)),IF($E173>$F173,1,0),0) -> 0 | X173: CC 初評
A174: SRC_ZP_170 | B174: rev_api_1h25 | C174: 開放平台及 API 收入 | D174: 0.291 | G174: RMB 億 | H174: 1H2025 | I174: 智譜（Z.AI）2026 中期業績公告 | J174: https://www1.hkexnews.hk/listedco/listconews/sehk/2026/0831/2026083101539.pdf | K174: 2026-08-31 | L174: 2026-10-08 | M174: Verified | O174: 未經審計（中期業績公告；是否經核數師審閱公告未見明載） | P174: 1 | Q174: 利害關係方 | R174: 經審計或經審閱的公司公告（誘因：上市後股價、配售；數字可由公告原文核對） | S174: 一手 | T174: 原文「Open Platform and API」；千元值 29,100；RMB 千元÷100,000 換算成億；1H26 占 86.5%（1H25 15.2%）；＝雲端部署分部 | U174: =IF(AND($D174="",$E174="",$F174=""),1,0) -> 0 | V174: =IF(OR($I174="",$I174="—"),1,0) -> 0 | W174: =IF(AND(ISNUMBER($D174),ISNUMBER($E174)),IF($E174>$D174,1,0),0)+IF(AND(ISNUMBER($D174),ISNUMBER($F174)),IF($D174>$F174,1,0),0)+IF(AND(ISNUMBER($E174),ISNUMBER($F174)),IF($E174>$F174,1,0),0) -> 0 | X174: CC 初評
A175: SRC_ZP_171 | B175: rev_agent_1h26 | C175: 企業級智能體收入 | D175: 0.5556 | G175: RMB 億 | H175: 1H2026 | I175: 智譜（Z.AI）2026 中期業績公告 | J175: https://www1.hkexnews.hk/listedco/listconews/sehk/2026/0831/2026083101539.pdf | K175: 2026-08-31 | L175: 2026-10-08 | M175: Verified | O175: 未經審計（中期業績公告；是否經核數師審閱公告未見明載） | P175: 1 | Q175: 利害關係方 | R175: 經審計或經審閱的公司公告（誘因：上市後股價、配售；數字可由公告原文核對） | S175: 一手 | T175: 原文「Enterprise-level Agents」；千元值 55,561；RMB 千元÷100,000 換算成億 | U175: =IF(AND($D175="",$E175="",$F175=""),1,0) -> 0 | V175: =IF(OR($I175="",$I175="—"),1,0) -> 0 | W175: =IF(AND(ISNUMBER($D175),ISNUMBER($E175)),IF($E175>$D175,1,0),0)+IF(AND(ISNUMBER($D175),ISNUMBER($F175)),IF($D175>$F175,1,0),0)+IF(AND(ISNUMBER($E175),ISNUMBER($F175)),IF($E175>$F175,1,0),0) -> 0 | X175: CC 初評
A176: SRC_ZP_172 | B176: rev_agent_1h25 | C176: 企業級智能體收入 | D176: 0.1374 | G176: RMB 億 | H176: 1H2025 | I176: 智譜（Z.AI）2026 中期業績公告 | J176: https://www1.hkexnews.hk/listedco/listconews/sehk/2026/0831/2026083101539.pdf | K176: 2026-08-31 | L176: 2026-10-08 | M176: Verified | O176: 未經審計（中期業績公告；是否經核數師審閱公告未見明載） | P176: 1 | Q176: 利害關係方 | R176: 經審計或經審閱的公司公告（誘因：上市後股價、配售；數字可由公告原文核對） | S176: 一手 | T176: 原文「Enterprise-level Agents」；千元值 13,739；RMB 千元÷100,000 換算成億 | U176: =IF(AND($D176="",$E176="",$F176=""),1,0) -> 0 | V176: =IF(OR($I176="",$I176="—"),1,0) -> 0 | W176: =IF(AND(ISNUMBER($D176),ISNUMBER($E176)),IF($E176>$D176,1,0),0)+IF(AND(ISNUMBER($D176),ISNUMBER($F176)),IF($D176>$F176,1,0),0)+IF(AND(ISNUMBER($E176),ISNUMBER($F176)),IF($E176>$F176,1,0),0) -> 0 | X176: CC 初評
A177: SRC_ZP_173 | B177: rev_gpllm_1h26 | C177: 企業級通用大模型收入 | D177: 0.6704 | G177: RMB 億 | H177: 1H2026 | I177: 智譜（Z.AI）2026 中期業績公告 | J177: https://www1.hkexnews.hk/listedco/listconews/sehk/2026/0831/2026083101539.pdf | K177: 2026-08-31 | L177: 2026-10-08 | M177: Verified | O177: 未經審計（中期業績公告；是否經核數師審閱公告未見明載） | P177: 1 | Q177: 利害關係方 | R177: 經審計或經審閱的公司公告（誘因：上市後股價、配售；數字可由公告原文核對） | S177: 一手 | T177: 原文「Enterprise-level General-purpose Large Models」；千元值 67,037；RMB 千元÷100,000 換算成億 | U177: =IF(AND($D177="",$E177="",$F177=""),1,0) -> 0 | V177: =IF(OR($I177="",$I177="—"),1,0) -> 0 | W177: =IF(AND(ISNUMBER($D177),ISNUMBER($E177)),IF($E177>$D177,1,0),0)+IF(AND(ISNUMBER($D177),ISNUMBER($F177)),IF($D177>$F177,1,0),0)+IF(AND(ISNUMBER($E177),ISNUMBER($F177)),IF($E177>$F177,1,0),0) -> 0 | X177: CC 初評
A178: SRC_ZP_174 | B178: rev_gpllm_1h25 | C178: 企業級通用大模型收入 | D178: 1.4755 | G178: RMB 億 | H178: 1H2025 | I178: 智譜（Z.AI）2026 中期業績公告 | J178: https://www1.hkexnews.hk/listedco/listconews/sehk/2026/0831/2026083101539.pdf | K178: 2026-08-31 | L178: 2026-10-08 | M178: Verified | O178: 未經審計（中期業績公告；是否經核數師審閱公告未見明載） | P178: 1 | Q178: 利害關係方 | R178: 經審計或經審閱的公司公告（誘因：上市後股價、配售；數字可由公告原文核對） | S178: 一手 | T178: 原文「Enterprise-level General-purpose Large Models」；千元值 147,555；RMB 千元÷100,000 換算成億 | U178: =IF(AND($D178="",$E178="",$F178=""),1,0) -> 0 | V178: =IF(OR($I178="",$I178="—"),1,0) -> 0 | W178: =IF(AND(ISNUMBER($D178),ISNUMBER($E178)),IF($E178>$D178,1,0),0)+IF(AND(ISNUMBER($D178),ISNUMBER($F178)),IF($D178>$F178,1,0),0)+IF(AND(ISNUMBER($E178),ISNUMBER($F178)),IF($E178>$F178,1,0),0) -> 0 | X178: CC 初評
A179: SRC_ZP_175 | B179: rev_techsvc_1h26 | C179: 技術服務及其他收入 | D179: 0.0612 | G179: RMB 億 | H179: 1H2026 | I179: 智譜（Z.AI）2026 中期業績公告 | J179: https://www1.hkexnews.hk/listedco/listconews/sehk/2026/0831/2026083101539.pdf | K179: 2026-08-31 | L179: 2026-10-08 | M179: Verified | O179: 未經審計（中期業績公告；是否經核數師審閱公告未見明載） | P179: 1 | Q179: 利害關係方 | R179: 經審計或經審閱的公司公告（誘因：上市後股價、配售；數字可由公告原文核對） | S179: 一手 | T179: 原文「Technical Services and Others」；千元值 6,118；RMB 千元÷100,000 換算成億 | U179: =IF(AND($D179="",$E179="",$F179=""),1,0) -> 0 | V179: =IF(OR($I179="",$I179="—"),1,0) -> 0 | W179: =IF(AND(ISNUMBER($D179),ISNUMBER($E179)),IF($E179>$D179,1,0),0)+IF(AND(ISNUMBER($D179),ISNUMBER($F179)),IF($D179>$F179,1,0),0)+IF(AND(ISNUMBER($E179),ISNUMBER($F179)),IF($E179>$F179,1,0),0) -> 0 | X179: CC 初評
A180: SRC_ZP_176 | B180: rev_techsvc_1h25 | C180: 技術服務及其他收入 | D180: 0.0048 | G180: RMB 億 | H180: 1H2025 | I180: 智譜（Z.AI）2026 中期業績公告 | J180: https://www1.hkexnews.hk/listedco/listconews/sehk/2026/0831/2026083101539.pdf | K180: 2026-08-31 | L180: 2026-10-08 | M180: Verified | O180: 未經審計（中期業績公告；是否經核數師審閱公告未見明載） | P180: 1 | Q180: 利害關係方 | R180: 經審計或經審閱的公司公告（誘因：上市後股價、配售；數字可由公告原文核對） | S180: 一手 | T180: 原文「Technical Services and Others」；千元值 483；RMB 千元÷100,000 換算成億 | U180: =IF(AND($D180="",$E180="",$F180=""),1,0) -> 0 | V180: =IF(OR($I180="",$I180="—"),1,0) -> 0 | W180: =IF(AND(ISNUMBER($D180),ISNUMBER($E180)),IF($E180>$D180,1,0),0)+IF(AND(ISNUMBER($D180),ISNUMBER($F180)),IF($D180>$F180,1,0),0)+IF(AND(ISNUMBER($E180),ISNUMBER($F180)),IF($E180>$F180,1,0),0) -> 0 | X180: CC 初評
A181: SRC_ZP_177 | B181: rev_total_1h26 | C181: 營收總額 | D181: 9.5389 | G181: RMB 億 | H181: 1H2026 | I181: 智譜（Z.AI）2026 中期業績公告 | J181: https://www1.hkexnews.hk/listedco/listconews/sehk/2026/0831/2026083101539.pdf | K181: 2026-08-31 | L181: 2026-10-08 | M181: Verified | O181: 未經審計（中期業績公告；是否經核數師審閱公告未見明載） | P181: 1 | Q181: 利害關係方 | R181: 經審計或經審閱的公司公告（誘因：上市後股價、配售；數字可由公告原文核對） | S181: 一手 | T181: 原文 revenue 953,892 千元（1H25 190,877），+399.7%；RMB 千元÷100,000 換算成億 | U181: =IF(AND($D181="",$E181="",$F181=""),1,0) -> 0 | V181: =IF(OR($I181="",$I181="—"),1,0) -> 0 | W181: =IF(AND(ISNUMBER($D181),ISNUMBER($E181)),IF($E181>$D181,1,0),0)+IF(AND(ISNUMBER($D181),ISNUMBER($F181)),IF($D181>$F181,1,0),0)+IF(AND(ISNUMBER($E181),ISNUMBER($F181)),IF($E181>$F181,1,0),0) -> 0 | X181: CC 初評
A182: SRC_ZP_178 | B182: rev_onprem_1h26 | C182: 本地化部署收入（分部） | D182: 1.2872 | G182: RMB 億 | H182: 1H2026 | I182: 智譜（Z.AI）2026 中期業績公告 | J182: https://ea-cdn.eurolandir.com/press-releases-attachments/4174939/HKEX-EPS_20260831_12308928_0.PDF | K182: 2026-08-31 | L182: 2026-10-08 | M182: Verified | O182: 未經審計（中期業績公告；是否經核數師審閱公告未見明載） | P182: 1 | Q182: 利害關係方 | R182: 經審計或經審閱的公司公告（誘因：上市後股價、配售；數字可由公告原文核對） | S182: 一手 | T182: on-premise deployment 128,716 千元（1H25 161,777），占 13.5%；RMB 千元÷100,000 換算成億 | U182: =IF(AND($D182="",$E182="",$F182=""),1,0) -> 0 | V182: =IF(OR($I182="",$I182="—"),1,0) -> 0 | W182: =IF(AND(ISNUMBER($D182),ISNUMBER($E182)),IF($E182>$D182,1,0),0)+IF(AND(ISNUMBER($D182),ISNUMBER($F182)),IF($D182>$F182,1,0),0)+IF(AND(ISNUMBER($E182),ISNUMBER($F182)),IF($E182>$F182,1,0),0) -> 0 | X182: CC 初評
A183: SRC_ZP_179 | B183: rev_cloud_1h26 | C183: 雲端部署收入（分部） | D183: 8.2518 | G183: RMB 億 | H183: 1H2026 | I183: 智譜（Z.AI）2026 中期業績公告 | J183: https://ea-cdn.eurolandir.com/press-releases-attachments/4174939/HKEX-EPS_20260831_12308928_0.PDF | K183: 2026-08-31 | L183: 2026-10-08 | M183: Verified | O183: 未經審計（中期業績公告；是否經核數師審閱公告未見明載） | P183: 1 | Q183: 利害關係方 | R183: 經審計或經審閱的公司公告（誘因：上市後股價、配售；數字可由公告原文核對） | S183: 一手 | T183: cloud-based deployment 825,176 千元＝開放平台及 API；RMB 千元÷100,000 換算成億 | U183: =IF(AND($D183="",$E183="",$F183=""),1,0) -> 0 | V183: =IF(OR($I183="",$I183="—"),1,0) -> 0 | W183: =IF(AND(ISNUMBER($D183),ISNUMBER($E183)),IF($E183>$D183,1,0),0)+IF(AND(ISNUMBER($D183),ISNUMBER($F183)),IF($D183>$F183,1,0),0)+IF(AND(ISNUMBER($E183),ISNUMBER($F183)),IF($E183>$F183,1,0),0) -> 0 | X183: CC 初評
A184: SRC_ZP_180 | B184: rev_onprem_1h26_b | C184: 本地化部署相關收入（媒體） | D184: 0.6704 | G184: RMB 億 | H184: 1H2026 | I184: 鉅亨號〈智譜上半年業績暴漲 造血能力驗證〉 | J184: https://hao.cnyes.com/post/265529 | K184: 2026-09-01 | L184: 2026-10-08 | M184: Interested-party | N184: 媒體（鉅亨號）轉述 | O184: 媒體轉述 | P184: 2 | Q184: 利害關係方 | R184: 媒體（鉅亨號）轉述 | S184: 二手 | T184: 原文「本地化部署相關收入6,704萬元」；與公告分部 1.287 億矛盾：媒體只計企業級通用大模型 | U184: =IF(AND($D184="",$E184="",$F184=""),1,0) -> 0 | V184: =IF(OR($I184="",$I184="—"),1,0) -> 0 | W184: =IF(AND(ISNUMBER($D184),ISNUMBER($E184)),IF($E184>$D184,1,0),0)+IF(AND(ISNUMBER($D184),ISNUMBER($F184)),IF($D184>$F184,1,0),0)+IF(AND(ISNUMBER($E184),ISNUMBER($F184)),IF($E184>$F184,1,0),0) -> 0 | X184: CC 初評
A185: SRC_ZP_181 | B185: rev_onprem_1h26_c | C185: 本地化部署收入（券商） | D185: 1.3 | G185: RMB 億 | H185: 1H2026 | I185: 國信證券〈26H1財報點評〉（格隆匯轉載） | J185: https://m.gelonghui.com/news/5306647 | K185: 2026-09-04 | L185: 2026-10-08 | M185: Interested-party | N185: 國信證券：券商研究，交易誘因 | O185: 券商口徑 | P185: 2 | Q185: 利害關係方 | R185: 國信證券：券商研究，交易誘因 | S185: 二手 | T185: 原文 本地化部署收入 1.30 億元、毛利率 37.9%；與公告 128,716 千元一致（四捨五入） | U185: =IF(AND($D185="",$E185="",$F185=""),1,0) -> 0 | V185: =IF(OR($I185="",$I185="—"),1,0) -> 0 | W185: =IF(AND(ISNUMBER($D185),ISNUMBER($E185)),IF($E185>$D185,1,0),0)+IF(AND(ISNUMBER($D185),ISNUMBER($F185)),IF($D185>$F185,1,0),0)+IF(AND(ISNUMBER($E185),ISNUMBER($F185)),IF($E185>$F185,1,0),0) -> 0 | X185: CC 初評
A186: SRC_ZP_182 | B186: cogs_1h26 | C186: 銷售成本 | D186: 7.0228 | G186: RMB 億 | H186: 1H2026 | I186: 智譜（Z.AI）2026 中期業績公告 | J186: https://www1.hkexnews.hk/listedco/listconews/sehk/2026/0831/2026083101539.pdf | K186: 2026-08-31 | L186: 2026-10-08 | M186: Verified | O186: 未經審計（中期業績公告；是否經核數師審閱公告未見明載） | P186: 1 | Q186: 利害關係方 | R186: 經審計或經審閱的公司公告（誘因：上市後股價、配售；數字可由公告原文核對） | S186: 一手 | T186: 原文「primarily attributable to the increase in computing service fees」；千元 702,281；算力服務費金額未揭露；RMB 千元÷100,000 換算成億 | U186: =IF(AND($D186="",$E186="",$F186=""),1,0) -> 0 | V186: =IF(OR($I186="",$I186="—"),1,0) -> 0 | W186: =IF(AND(ISNUMBER($D186),ISNUMBER($E186)),IF($E186>$D186,1,0),0)+IF(AND(ISNUMBER($D186),ISNUMBER($F186)),IF($D186>$F186,1,0),0)+IF(AND(ISNUMBER($E186),ISNUMBER($F186)),IF($E186>$F186,1,0),0) -> 0 | X186: CC 初評
A187: SRC_ZP_183 | B187: cogs_1h25_i | C187: 銷售成本（中期公告比較數） | D187: 0.9545 | G187: RMB 億 | H187: 1H2025 | I187: 智譜（Z.AI）2026 中期業績公告 | J187: https://www1.hkexnews.hk/listedco/listconews/sehk/2026/0831/2026083101539.pdf | K187: 2026-08-31 | L187: 2026-10-08 | M187: Verified | O187: 未經審計（中期業績公告；是否經核數師審閱公告未見明載） | P187: 1 | Q187: 利害關係方 | R187: 經審計或經審閱的公司公告（誘因：上市後股價、配售；數字可由公告原文核對） | S187: 一手 | T187: 千元 95,453，與招股章程一致；RMB 千元÷100,000 換算成億 | U187: =IF(AND($D187="",$E187="",$F187=""),1,0) -> 0 | V187: =IF(OR($I187="",$I187="—"),1,0) -> 0 | W187: =IF(AND(ISNUMBER($D187),ISNUMBER($E187)),IF($E187>$D187,1,0),0)+IF(AND(ISNUMBER($D187),ISNUMBER($F187)),IF($D187>$F187,1,0),0)+IF(AND(ISNUMBER($E187),ISNUMBER($F187)),IF($E187>$F187,1,0),0) -> 0 | X187: CC 初評
A188: SRC_ZP_184 | B188: gp_total_1h26 | C188: 毛利 | D188: 2.5161 | G188: RMB 億 | H188: 1H2026 | I188: 智譜（Z.AI）2026 中期業績公告 | J188: https://www1.hkexnews.hk/listedco/listconews/sehk/2026/0831/2026083101539.pdf | K188: 2026-08-31 | L188: 2026-10-08 | M188: Verified | O188: 未經審計（中期業績公告；是否經核數師審閱公告未見明載） | P188: 1 | Q188: 利害關係方 | R188: 經審計或經審閱的公司公告（誘因：上市後股價、配售；數字可由公告原文核對） | S188: 一手 | T188: gross profit 251,611 千元；毛利率 26.4%（1H25 50.0%）；RMB 千元÷100,000 換算成億 | U188: =IF(AND($D188="",$E188="",$F188=""),1,0) -> 0 | V188: =IF(OR($I188="",$I188="—"),1,0) -> 0 | W188: =IF(AND(ISNUMBER($D188),ISNUMBER($E188)),IF($E188>$D188,1,0),0)+IF(AND(ISNUMBER($D188),ISNUMBER($F188)),IF($D188>$F188,1,0),0)+IF(AND(ISNUMBER($E188),ISNUMBER($F188)),IF($E188>$F188,1,0),0) -> 0 | X188: CC 初評
A189: SRC_ZP_185 | B189: gm_total_1h26 | C189: 整體毛利率 | D189: 26.4 | G189: % | H189: 1H2026 | I189: 智譜（Z.AI）2026 中期業績公告 | J189: https://www1.hkexnews.hk/listedco/listconews/sehk/2026/0831/2026083101539.pdf | K189: 2026-08-31 | L189: 2026-10-08 | M189: Verified | O189: 未經審計（中期業績公告；是否經核數師審閱公告未見明載） | P189: 1 | Q189: 利害關係方 | R189: 經審計或經審閱的公司公告（誘因：上市後股價、配售；數字可由公告原文核對） | S189: 一手 | T189: 原文 gross margin 26.4%（1H25 50.0%） | U189: =IF(AND($D189="",$E189="",$F189=""),1,0) -> 0 | V189: =IF(OR($I189="",$I189="—"),1,0) -> 0 | W189: =IF(AND(ISNUMBER($D189),ISNUMBER($E189)),IF($E189>$D189,1,0),0)+IF(AND(ISNUMBER($D189),ISNUMBER($F189)),IF($D189>$F189,1,0),0)+IF(AND(ISNUMBER($E189),ISNUMBER($F189)),IF($E189>$F189,1,0),0) -> 0 | X189: CC 初評
A190: SRC_ZP_186 | B190: gp_api_1h26 | C190: 開放平台及 API 毛利 | D190: 2.0287 | G190: RMB 億 | H190: 1H2026 | I190: 智譜（Z.AI）2026 中期業績公告 | J190: https://ea-cdn.eurolandir.com/press-releases-attachments/4174939/HKEX-EPS_20260831_12308928_0.PDF | K190: 2026-08-31 | L190: 2026-10-08 | M190: Verified | O190: 未經審計（中期業績公告；是否經核數師審閱公告未見明載） | P190: 1 | Q190: 利害關係方 | R190: 經審計或經審閱的公司公告（誘因：上市後股價、配售；數字可由公告原文核對） | S190: 一手 | T190: 千元 202,871；毛利率 24.6%；RMB 千元÷100,000 換算成億 | U190: =IF(AND($D190="",$E190="",$F190=""),1,0) -> 0 | V190: =IF(OR($I190="",$I190="—"),1,0) -> 0 | W190: =IF(AND(ISNUMBER($D190),ISNUMBER($E190)),IF($E190>$D190,1,0),0)+IF(AND(ISNUMBER($D190),ISNUMBER($F190)),IF($D190>$F190,1,0),0)+IF(AND(ISNUMBER($E190),ISNUMBER($F190)),IF($E190>$F190,1,0),0) -> 0 | X190: CC 初評
A191: SRC_ZP_187 | B191: gp_api_1h25 | C191: 開放平台及 API 毛利 | D191: -0.0012 | G191: RMB 億 | H191: 1H2025 | I191: 智譜（Z.AI）2026 中期業績公告 | J191: https://ea-cdn.eurolandir.com/press-releases-attachments/4174939/HKEX-EPS_20260831_12308928_0.PDF | K191: 2026-08-31 | L191: 2026-10-08 | M191: Verified | O191: 未經審計（中期業績公告；是否經核數師審閱公告未見明載） | P191: 1 | Q191: 利害關係方 | R191: 經審計或經審閱的公司公告（誘因：上市後股價、配售；數字可由公告原文核對） | S191: 一手 | T191: 千元 -116；毛利率 -0.4%；RMB 千元÷100,000 換算成億 | U191: =IF(AND($D191="",$E191="",$F191=""),1,0) -> 0 | V191: =IF(OR($I191="",$I191="—"),1,0) -> 0 | W191: =IF(AND(ISNUMBER($D191),ISNUMBER($E191)),IF($E191>$D191,1,0),0)+IF(AND(ISNUMBER($D191),ISNUMBER($F191)),IF($D191>$F191,1,0),0)+IF(AND(ISNUMBER($E191),ISNUMBER($F191)),IF($E191>$F191,1,0),0) -> 0 | X191: CC 初評
A192: SRC_ZP_188 | B192: gp_agent_1h26 | C192: 企業級智能體毛利 | D192: 0.198 | G192: RMB 億 | H192: 1H2026 | I192: 智譜（Z.AI）2026 中期業績公告 | J192: https://ea-cdn.eurolandir.com/press-releases-attachments/4174939/HKEX-EPS_20260831_12308928_0.PDF | K192: 2026-08-31 | L192: 2026-10-08 | M192: Verified | O192: 未經審計（中期業績公告；是否經核數師審閱公告未見明載） | P192: 1 | Q192: 利害關係方 | R192: 經審計或經審閱的公司公告（誘因：上市後股價、配售；數字可由公告原文核對） | S192: 一手 | T192: 千元 19,796；毛利率 35.6%；RMB 千元÷100,000 換算成億 | U192: =IF(AND($D192="",$E192="",$F192=""),1,0) -> 0 | V192: =IF(OR($I192="",$I192="—"),1,0) -> 0 | W192: =IF(AND(ISNUMBER($D192),ISNUMBER($E192)),IF($E192>$D192,1,0),0)+IF(AND(ISNUMBER($D192),ISNUMBER($F192)),IF($D192>$F192,1,0),0)+IF(AND(ISNUMBER($E192),ISNUMBER($F192)),IF($E192>$F192,1,0),0) -> 0 | X192: CC 初評
A193: SRC_ZP_189 | B193: gp_agent_1h25 | C193: 企業級智能體毛利 | D193: 0.0888 | G193: RMB 億 | H193: 1H2025 | I193: 智譜（Z.AI）2026 中期業績公告 | J193: https://ea-cdn.eurolandir.com/press-releases-attachments/4174939/HKEX-EPS_20260831_12308928_0.PDF | K193: 2026-08-31 | L193: 2026-10-08 | M193: Verified | O193: 未經審計（中期業績公告；是否經核數師審閱公告未見明載） | P193: 1 | Q193: 利害關係方 | R193: 經審計或經審閱的公司公告（誘因：上市後股價、配售；數字可由公告原文核對） | S193: 一手 | T193: 千元 8,880；毛利率 64.6%；RMB 千元÷100,000 換算成億 | U193: =IF(AND($D193="",$E193="",$F193=""),1,0) -> 0 | V193: =IF(OR($I193="",$I193="—"),1,0) -> 0 | W193: =IF(AND(ISNUMBER($D193),ISNUMBER($E193)),IF($E193>$D193,1,0),0)+IF(AND(ISNUMBER($D193),ISNUMBER($F193)),IF($D193>$F193,1,0),0)+IF(AND(ISNUMBER($E193),ISNUMBER($F193)),IF($E193>$F193,1,0),0) -> 0 | X193: CC 初評
A194: SRC_ZP_190 | B194: gp_gpllm_1h26 | C194: 企業級通用大模型毛利 | D194: 0.2837 | G194: RMB 億 | H194: 1H2026 | I194: 智譜（Z.AI）2026 中期業績公告 | J194: https://ea-cdn.eurolandir.com/press-releases-attachments/4174939/HKEX-EPS_20260831_12308928_0.PDF | K194: 2026-08-31 | L194: 2026-10-08 | M194: Verified | O194: 未經審計（中期業績公告；是否經核數師審閱公告未見明載） | P194: 1 | Q194: 利害關係方 | R194: 經審計或經審閱的公司公告（誘因：上市後股價、配售；數字可由公告原文核對） | S194: 一手 | T194: 千元 28,368；毛利率 42.3%；RMB 千元÷100,000 換算成億 | U194: =IF(AND($D194="",$E194="",$F194=""),1,0) -> 0 | V194: =IF(OR($I194="",$I194="—"),1,0) -> 0 | W194: =IF(AND(ISNUMBER($D194),ISNUMBER($E194)),IF($E194>$D194,1,0),0)+IF(AND(ISNUMBER($D194),ISNUMBER($F194)),IF($D194>$F194,1,0),0)+IF(AND(ISNUMBER($E194),ISNUMBER($F194)),IF($E194>$F194,1,0),0) -> 0 | X194: CC 初評
A195: SRC_ZP_191 | B195: gp_gpllm_1h25 | C195: 企業級通用大模型毛利 | D195: 0.8634 | G195: RMB 億 | H195: 1H2025 | I195: 智譜（Z.AI）2026 中期業績公告 | J195: https://ea-cdn.eurolandir.com/press-releases-attachments/4174939/HKEX-EPS_20260831_12308928_0.PDF | K195: 2026-08-31 | L195: 2026-10-08 | M195: Verified | O195: 未經審計（中期業績公告；是否經核數師審閱公告未見明載） | P195: 1 | Q195: 利害關係方 | R195: 經審計或經審閱的公司公告（誘因：上市後股價、配售；數字可由公告原文核對） | S195: 一手 | T195: 千元 86,342；毛利率 58.5%；RMB 千元÷100,000 換算成億 | U195: =IF(AND($D195="",$E195="",$F195=""),1,0) -> 0 | V195: =IF(OR($I195="",$I195="—"),1,0) -> 0 | W195: =IF(AND(ISNUMBER($D195),ISNUMBER($E195)),IF($E195>$D195,1,0),0)+IF(AND(ISNUMBER($D195),ISNUMBER($F195)),IF($D195>$F195,1,0),0)+IF(AND(ISNUMBER($E195),ISNUMBER($F195)),IF($E195>$F195,1,0),0) -> 0 | X195: CC 初評
A196: SRC_ZP_192 | B196: gp_techsvc_1h26 | C196: 技術服務及其他毛利 | D196: 0.0058 | G196: RMB 億 | H196: 1H2026 | I196: 智譜（Z.AI）2026 中期業績公告 | J196: https://ea-cdn.eurolandir.com/press-releases-attachments/4174939/HKEX-EPS_20260831_12308928_0.PDF | K196: 2026-08-31 | L196: 2026-10-08 | M196: Verified | O196: 未經審計（中期業績公告；是否經核數師審閱公告未見明載） | P196: 1 | Q196: 利害關係方 | R196: 經審計或經審閱的公司公告（誘因：上市後股價、配售；數字可由公告原文核對） | S196: 一手 | T196: 千元 576；毛利率 9.4%；RMB 千元÷100,000 換算成億 | U196: =IF(AND($D196="",$E196="",$F196=""),1,0) -> 0 | V196: =IF(OR($I196="",$I196="—"),1,0) -> 0 | W196: =IF(AND(ISNUMBER($D196),ISNUMBER($E196)),IF($E196>$D196,1,0),0)+IF(AND(ISNUMBER($D196),ISNUMBER($F196)),IF($D196>$F196,1,0),0)+IF(AND(ISNUMBER($E196),ISNUMBER($F196)),IF($E196>$F196,1,0),0) -> 0 | X196: CC 初評
A197: SRC_ZP_193 | B197: gp_techsvc_1h25 | C197: 技術服務及其他毛利 | D197: 0.0032 | G197: RMB 億 | H197: 1H2025 | I197: 智譜（Z.AI）2026 中期業績公告 | J197: https://ea-cdn.eurolandir.com/press-releases-attachments/4174939/HKEX-EPS_20260831_12308928_0.PDF | K197: 2026-08-31 | L197: 2026-10-08 | M197: Verified | O197: 未經審計（中期業績公告；是否經核數師審閱公告未見明載） | P197: 1 | Q197: 利害關係方 | R197: 經審計或經審閱的公司公告（誘因：上市後股價、配售；數字可由公告原文核對） | S197: 一手 | T197: 千元 318；毛利率 65.8%；RMB 千元÷100,000 換算成億 | U197: =IF(AND($D197="",$E197="",$F197=""),1,0) -> 0 | V197: =IF(OR($I197="",$I197="—"),1,0) -> 0 | W197: =IF(AND(ISNUMBER($D197),ISNUMBER($E197)),IF($E197>$D197,1,0),0)+IF(AND(ISNUMBER($D197),ISNUMBER($F197)),IF($D197>$F197,1,0),0)+IF(AND(ISNUMBER($E197),ISNUMBER($F197)),IF($E197>$F197,1,0),0) -> 0 | X197: CC 初評
... A210: SRC_ZP_206 | B210: adj_loss_1h26 | C210: 經調整淨虧損（非IFRS） | D210: 19.6414 | G210: RMB 億 | H210: 1H2026 | I210: 智譜（Z.AI）2026 中期業績公告 | J210: https://www1.hkexnews.hk/listedco/listconews/sehk/2026/0831/2026083101539.pdf | K210: 2026-08-31 | L210: 2026-10-08 | M210: Verified | O210: 未經審計（中期業績公告；是否經核數師審閱公告未見明載） | P210: 1 | Q210: 利害關係方 | R210: 經審計或經審閱的公司公告（誘因：上市後股價、配售；數字可由公告原文核對） | S210: 一手 | T210: 加回 SBC 85,764、投資人工具變動 22,090；千元 1,964,138（1H25 1,751,974）；RMB 千元÷100,000 換算成億 | U210: =IF(AND($D210="",$E210="",$F210=""),1,0) -> 0 | V210: =IF(OR($I210="",$I210="—"),1,0) -> 0 | W210: =IF(AND(ISNUMBER($D210),ISNUMBER($E210)),IF($E210>$D210,1,0),0)+IF(AND(ISNUMBER($D210),ISNUMBER($F210)),IF($D210>$F210,1,0),0)+IF(AND(ISNUMBER($E210),ISNUMBER($F210)),IF($E210>$F210,1,0),0) -> 0 | X210: CC 初評
A211: SRC_ZP_207 | B211: net_loss_1h25_b | C211: 期內淨虧損（媒體引部落客） | D211: 17.51 | G211: RMB 億 | H211: 1H2025 | I211: 36氪轉載〈市值水晶〉 | J211: https://www.36kr.com/p/3611675144253960 | K211: 2025-12-26 | L211: 2026-10-08 | M211: Interested-party | N211: 媒體轉述 | O211: 媒體轉述 | P211: 2 | Q211: 利害關係方 | R211: 媒體轉述 | S211: 二手 | T211: 媒體稱淨虧損 17.51 億；實為經調整淨虧損（招股章程 17.52 億），與期內虧損 23.58 億矛盾 | U211: =IF(AND($D211="",$E211="",$F211=""),1,0) -> 0 | V211: =IF(OR($I211="",$I211="—"),1,0) -> 0 | W211: =IF(AND(ISNUMBER($D211),ISNUMBER($E211)),IF($E211>$D211,1,0),0)+IF(AND(ISNUMBER($D211),ISNUMBER($F211)),IF($D211>$F211,1,0),0)+IF(AND(ISNUMBER($E211),ISNUMBER($F211)),IF($E211>$F211,1,0),0) -> 0 | X211: CC 初評
A212: SRC_ZP_208 | B212: net_loss_1h25_c | C212: 淨利潤（券商） | D212: -23.51 | G212: RMB 億 | H212: 1H2025 | I212: 國信證券〈垂類AI應用專題：智譜〉 | J212: https://pdf.dfcfw.com/pdf/H3_AP202601071816825157_1.pdf | K212: 2026-01-07 | L212: 2026-10-08 | M212: Interested-party | N212: 國信證券：券商研究，交易誘因 | O212: 券商口徑 | P212: 2 | Q212: 利害關係方 | R212: 國信證券：券商研究，交易誘因 | S212: 二手 | T212: 原文「净利润为-23.51亿元」；與招股章程期內虧損 23.58 億不一致（可能為歸母） | U212: =IF(AND($D212="",$E212="",$F212=""),1,0) -> 0 | V212: =IF(OR($I212="",$I212="—"),1,0) -> 0 | W212: =IF(AND(ISNUMBER($D212),ISNUMBER($E212)),IF($E212>$D212,1,0),0)+IF(AND(ISNUMBER($D212),ISNUMBER($F212)),IF($D212>$F212,1,0),0)+IF(AND(ISNUMBER($E212),ISNUMBER($F212)),IF($E212>$F212,1,0),0) -> 0 | X212: CC 初評
A213: SRC_ZP_209 | B213: capex_1h26 | C213: 資本開支 | D213: 3.906 | G213: RMB 億 | H213: 1H2026 | I213: 智譜（Z.AI）2026 中期業績公告 | J213: https://ea-cdn.eurolandir.com/press-releases-attachments/4174939/HKEX-EPS_20260831_12308928_0.PDF | K213: 2026-08-31 | L213: 2026-10-08 | M213: Verified | O213: 未經審計（中期業績公告；是否經核數師審閱公告未見明載） | P213: 1 | Q213: 利害關係方 | R213: 經審計或經審閱的公司公告（誘因：上市後股價、配售；數字可由公告原文核對） | S213: 一手 | T213: 原文 increased from RMB53.7 million to RMB390.6 million（+627.4%），主因收購北京紅鑽；百萬÷100 | U213: =IF(AND($D213="",$E213="",$F213=""),1,0) -> 0 | V213: =IF(OR($I213="",$I213="—"),1,0) -> 0 | W213: =IF(AND(ISNUMBER($D213),ISNUMBER($E213)),IF($E213>$D213,1,0),0)+IF(AND(ISNUMBER($D213),ISNUMBER($F213)),IF($D213>$F213,1,0),0)+IF(AND(ISNUMBER($E213),ISNUMBER($F213)),IF($E213>$F213,1,0),0) -> 0 | X213: CC 初評
A214: SRC_ZP_210 | B214: capex_1h25 | C214: 資本開支 | D214: 0.537 | G214: RMB 億 | H214: 1H2025 | I214: 智譜（Z.AI）2026 中期業績公告 | J214: https://ea-cdn.eurolandir.com/press-releases-attachments/4174939/HKEX-EPS_20260831_12308928_0.PDF | K214: 2026-08-31 | L214: 2026-10-08 | M214: Verified | O214: 未經審計（中期業績公告；是否經核數師審閱公告未見明載） | P214: 1 | Q214: 利害關係方 | R214: 經審計或經審閱的公司公告（誘因：上市後股價、配售；數字可由公告原文核對） | S214: 一手 | T214: 中期公告比較數 RMB53.7 million；百萬÷100；【r2 P2 口徑差異】公告「資本開支」含使用權資產添置 0.34 億；現金資本開支 0.24 億見 SRC_ZP_891 | U214: =IF(AND($D214="",$E214="",$F214=""),1,0) -> 0 | V214: =IF(OR($I214="",$I214="—"),1,0) -> 0 | W214: =IF(AND(ISNUMBER($D214),ISNUMBER($E214)),IF($E214>$D214,1,0),0)+IF(AND(ISNUMBER($D214),ISNUMBER($F214)),IF($D214>$F214,1,0),0)+IF(AND(ISNUMBER($E214),ISNUMBER($F214)),IF($E214>$F214,1,0),0) -> 0 | X214: CC 初評
A215: SRC_ZP_211 | B215: cash_end_1h26 | C215: 期末現金及現金等價物 | D215: 39.9372 | G215: RMB 億 | H215: 2026-06-30 | I215: 智譜（Z.AI）2026 中期業績公告 | J215: https://www1.hkexnews.hk/listedco/listconews/sehk/2026/0831/2026083101539.pdf | K215: 2026-08-31 | L215: 2026-10-08 | M215: Verified | O215: 未經審計（中期業績公告；是否經核數師審閱公告未見明載） | P215: 1 | Q215: 利害關係方 | R215: 經審計或經審閱的公司公告（誘因：上市後股價、配售；數字可由公告原文核對） | S215: 一手 | T215: 千元 3,993,722（2025 年末 2,259,147）；RMB 千元÷100,000 換算成億 | U215: =IF(AND($D215="",$E215="",$F215=""),1,0) -> 0 | V215: =IF(OR($I215="",$I215="—"),1,0) -> 0 | W215: =IF(AND(ISNUMBER($D215),ISNUMBER($E215)),IF($E215>$D215,1,0),0)+IF(AND(ISNUMBER($D215),ISNUMBER($F215)),IF($D215>$F215,1,0),0)+IF(AND(ISNUMBER($E215),ISNUMBER($F215)),IF($E215>$F215,1,0),0) -> 0 | X215: CC 初評
A216: SRC_ZP_212 | B216: time_dep_1h26 | C216: 定期存款 | D216: 0 | G216: RMB 億 | H216: 2026-06-30 | I216: 智譜（Z.AI）2026 中期業績公告 | J216: https://www1.hkexnews.hk/listedco/listconews/sehk/2026/0831/2026083101539.pdf | K216: 2026-08-31 | L216: 2026-10-08 | M216: Verified | O216: 未經審計（中期業績公告；是否經核數師審閱公告未見明載） | P216: 1 | Q216: 利害關係方 | R216: 經審計或經審閱的公司公告（誘因：上市後股價、配售；數字可由公告原文核對） | S216: 一手 | T216: time deposits nil（2025 年末 108,593 千元） | U216: =IF(AND($D216="",$E216="",$F216=""),1,0) -> 0 | V216: =IF(OR($I216="",$I216="—"),1,0) -> 0 | W216: =IF(AND(ISNUMBER($D216),ISNUMBER($E216)),IF($E216>$D216,1,0),0)+IF(AND(ISNUMBER($D216),ISNUMBER($F216)),IF($D216>$F216,1,0),0)+IF(AND(ISNUMBER($E216),ISNUMBER($F216)),IF($E216>$F216,1,0),0) -> 0 | X216: CC 初評
A217: SRC_ZP_213 | B217: bank_loans_1h26 | C217: 銀行貸款合計 | D217: 22.2479 | G217: RMB 億 | H217: 2026-06-30 | I217: 智譜（Z.AI）2026 中期業績公告 | J217: https://www1.hkexnews.hk/listedco/listconews/sehk/2026/0831/2026083101539.pdf | K217: 2026-08-31 | L217: 2026-10-08 | M217: Verified | O217: 未經審計（中期業績公告；是否經核數師審閱公告未見明載） | P217: 1 | Q217: 利害關係方 | R217: 經審計或經審閱的公司公告（誘因：上市後股價、配售；數字可由公告原文核對） | S217: 一手 | T217: 流動 789,831＋非流動 1,434,958 千元；原文「interest-bearing, denominated primarily in RMB and unsecured」；利率、到期未揭露；RMB 千元÷100,000 換算成億 | U217: =IF(AND($D217="",$E217="",$F217=""),1,0) -> 0 | V217: =IF(OR($I217="",$I217="—"),1,0) -> 0 | W217: =IF(AND(ISNUMBER($D217),ISNUMBER($E217)),IF($E217>$D217,1,0),0)+IF(AND(ISNUMBER($D217),ISNUMBER($F217)),IF($D217>$F217,1,0),0)+IF(AND(ISNUMBER($E217),ISNUMBER($F217)),IF($E217>$F217,1,0),0) -> 0 | X217: CC 初評
A218: SRC_ZP_214 | B218: bank_loans_cur_1h26 | C218: 銀行貸款（流動，一年內到期） | D218: 7.8983 | G218: RMB 億 | H218: 2026-06-30 | I218: 智譜（Z.AI）2026 中期業績公告 | J218: https://www1.hkexnews.hk/listedco/listconews/sehk/2026/0831/2026083101539.pdf | K218: 2026-08-31 | L218: 2026-10-08 | M218: Verified | O218: 未經審計（中期業績公告；是否經核數師審閱公告未見明載） | P218: 1 | Q218: 利害關係方 | R218: 經審計或經審閱的公司公告（誘因：上市後股價、配售；數字可由公告原文核對） | S218: 一手 | T218: current 789,831 千元；RMB 千元÷100,000 換算成億 | U218: =IF(AND($D218="",$E218="",$F218=""),1,0) -> 0 | V218: =IF(OR($I218="",$I218="—"),1,0) -> 0 | W218: =IF(AND(ISNUMBER($D218),ISNUMBER($E218)),IF($E218>$D218,1,0),0)+IF(AND(ISNUMBER($D218),ISNUMBER($F218)),IF($D218>$F218,1,0),0)+IF(AND(ISNUMBER($E218),ISNUMBER($F218)),IF($E218>$F218,1,0),0) -> 0 | X218: CC 初評
A219: SRC_ZP_215 | B219: bank_loans_ncur_1h26 | C219: 銀行貸款（非流動） | D219: 14.3496 | G219: RMB 億 | H219: 2026-06-30 | I219: 智譜（Z.AI）2026 中期業績公告 | J219: https://www1.hkexnews.hk/listedco/listconews/sehk/2026/0831/2026083101539.pdf | K219: 2026-08-31 | L219: 2026-10-08 | M219: Verified | O219: 未經審計（中期業績公告；是否經核數師審閱公告未見明載） | P219: 1 | Q219: 利害關係方 | R219: 經審計或經審閱的公司公告（誘因：上市後股價、配售；數字可由公告原文核對） | S219: 一手 | T219: non-current 1,434,958 千元；RMB 千元÷100,000 換算成億 | U219: =IF(AND($D219="",$E219="",$F219=""),1,0) -> 0 | V219: =IF(OR($I219="",$I219="—"),1,0) -> 0 | W219: =IF(AND(ISNUMBER($D219),ISNUMBER($E219)),IF($E219>$D219,1,0),0)+IF(AND(ISNUMBER($D219),ISNUMBER($F219)),IF($D219>$F219,1,0),0)+IF(AND(ISNUMBER($E219),ISNUMBER($F219)),IF($E219>$F219,1,0),0) -> 0 | X219: CC 初評
A220: SRC_ZP_216 | B220: bank_loans_cur_fy25 | C220: 銀行貸款（流動） | D220: 6.0484 | G220: RMB 億 | H220: 2025-12-31 | I220: 智譜 2025 年度業績公告 | J220: https://www1.hkexnews.hk/listedco/listconews/sehk/2026/0331/2026033101549.pdf | K220: 2026-03-31 | L220: 2026-10-08 | M220: Verified | O220: 經審計（KPMG；年度業績公告） | P220: 1 | Q220: 利害關係方 | R220: 經審計或經審閱的公司公告（誘因：上市後股價、配售；數字可由公告原文核對） | S220: 一手 | T220: current 604,836 千元；RMB 千元÷100,000 換算成億 | U220: =IF(AND($D220="",$E220="",$F220=""),1,0) -> 0 | V220: =IF(OR($I220="",$I220="—"),1,0) -> 0 | W220: =IF(AND(ISNUMBER($D220),ISNUMBER($E220)),IF($E220>$D220,1,0),0)+IF(AND(ISNUMBER($D220),ISNUMBER($F220)),IF($D220>$F220,1,0),0)+IF(AND(ISNUMBER($E220),ISNUMBER($F220)),IF($E220>$F220,1,0),0) -> 0 | X220: CC 初評
A221: SRC_ZP_217 | B221: bank_loans_ncur_fy25 | C221: 銀行貸款（非流動） | D221: 0.8462 | G221: RMB 億 | H221: 2025-12-31 | I221: 智譜 2025 年度業績公告 | J221: https://www1.hkexnews.hk/listedco/listconews/sehk/2026/0331/2026033101549.pdf | K221: 2026-03-31 | L221: 2026-10-08 | M221: Verified | O221: 經審計（KPMG；年度業績公告） | P221: 1 | Q221: 利害關係方 | R221: 經審計或經審閱的公司公告（誘因：上市後股價、配售；數字可由公告原文核對） | S221: 一手 | T221: non-current 84,616 千元；RMB 千元÷100,000 換算成億 | U221: =IF(AND($D221="",$E221="",$F221=""),1,0) -> 0 | V221: =IF(OR($I221="",$I221="—"),1,0) -> 0 | W221: =IF(AND(ISNUMBER($D221),ISNUMBER($E221)),IF($E221>$D221,1,0),0)+IF(AND(ISNUMBER($D221),ISNUMBER($F221)),IF($D221>$F221,1,0),0)+IF(AND(ISNUMBER($E221),ISNUMBER($F221)),IF($E221>$F221,1,0),0) -> 0 | X221: CC 初評
A222: SRC_ZP_218 | B222: payable_compute_1h26 | C222: 應付算力服務費 | D222: 14.2742 | G222: RMB 億 | H222: 2026-06-30 | I222: 智譜（Z.AI）2026 中期業績公告 | J222: https://ea-cdn.eurolandir.com/press-releases-attachments/4174939/HKEX-EPS_20260831_12308928_0.PDF | K222: 2026-08-31 | L222: 2026-10-08 | M222: Verified | O222: 未經審計（中期業績公告；是否經核數師審閱公告未見明載） | P222: 1 | Q222: 利害關係方 | R222: 經審計或經審閱的公司公告（誘因：上市後股價、配售；數字可由公告原文核對） | S222: 一手 | T222: payables for computing service fees 1,427,415 千元；RMB 千元÷100,000 換算成億 | U222: =IF(AND($D222="",$E222="",$F222=""),1,0) -> 0 | V222: =IF(OR($I222="",$I222="—"),1,0) -> 0 | W222: =IF(AND(ISNUMBER($D222),ISNUMBER($E222)),IF($E222>$D222,1,0),0)+IF(AND(ISNUMBER($D222),ISNUMBER($F222)),IF($D222>$F222,1,0),0)+IF(AND(ISNUMBER($E222),ISNUMBER($F222)),IF($E222>$F222,1,0),0) -> 0 | X222: CC 初評
A223: SRC_ZP_219 | B223: prepay_compute_1h26 | C223: 預付算力服務費及其他 | D223: 12.4374 | G223: RMB 億 | H223: 2026-06-30 | I223: 智譜（Z.AI）2026 中期業績公告 | J223: https://ea-cdn.eurolandir.com/press-releases-attachments/4174939/HKEX-EPS_20260831_12308928_0.PDF | K223: 2026-08-31 | L223: 2026-10-08 | M223: Verified | O223: 未經審計（中期業績公告；是否經核數師審閱公告未見明載） | P223: 1 | Q223: 利害關係方 | R223: 經審計或經審閱的公司公告（誘因：上市後股價、配售；數字可由公告原文核對） | S223: 一手 | T223: prepayments for computing service fee and others 1,243,736（2025 年末 116,295）；RMB 千元÷100,000 換算成億 | U223: =IF(AND($D223="",$E223="",$F223=""),1,0) -> 0 | V223: =IF(OR($I223="",$I223="—"),1,0) -> 0 | W223: =IF(AND(ISNUMBER($D223),ISNUMBER($E223)),IF($E223>$D223,1,0),0)+IF(AND(ISNUMBER($D223),ISNUMBER($F223)),IF($D223>$F223,1,0),0)+IF(AND(ISNUMBER($E223),ISNUMBER($F223)),IF($E223>$F223,1,0),0) -> 0 | X223: CC 初評
A224: SRC_ZP_220 | B224: prepay_compute_fy25 | C224: 預付算力服務費及其他 | D224: 1.1629 | G224: RMB 億 | H224: 2025-12-31 | I224: 智譜（Z.AI）2026 中期業績公告 | J224: https://ea-cdn.eurolandir.com/press-releases-attachments/4174939/HKEX-EPS_20260831_12308928_0.PDF | K224: 2026-08-31 | L224: 2026-10-08 | M224: Verified | O224: 未經審計（中期業績公告；是否經核數師審閱公告未見明載） | P224: 1 | Q224: 利害關係方 | R224: 經審計或經審閱的公司公告（誘因：上市後股價、配售；數字可由公告原文核對） | S224: 一手 | T224: 中期公告比較數 116,295 千元；RMB 千元÷100,000 換算成億 | U224: =IF(AND($D224="",$E224="",$F224=""),1,0) -> 0 | V224: =IF(OR($I224="",$I224="—"),1,0) -> 0 | W224: =IF(AND(ISNUMBER($D224),ISNUMBER($E224)),IF($E224>$D224,1,0),0)+IF(AND(ISNUMBER($D224),ISNUMBER($F224)),IF($D224>$F224,1,0),0)+IF(AND(ISNUMBER($E224),ISNUMBER($F224)),IF($E224>$F224,1,0),0) -> 0 | X224: CC 初評
... A230: SRC_ZP_226 | B230: comp_per_head_1h26 | C230: 人均半年薪酬（含股權報酬） | D230: 0.00491 | G230: RMB 億／人／半年 | H230: 1H2026 | I230: 智譜（Z.AI）2026 中期業績公告 | J230: https://ea-cdn.eurolandir.com/press-releases-attachments/4174939/HKEX-EPS_20260831_12308928_0.PDF | K230: 2026-08-31 | L230: 2026-10-08 | M230: Derived | O230: Derived | P230: 2 | Q230: 推算 | R230: 由其他 SRC 列推算（見備註）；立場同其來源 | S230: 一手 | T230: 482.1 百萬÷期末 981 人＝約 49.1 萬元／人／半年 | U230: =IF(AND($D230="",$E230="",$F230=""),1,0) -> 0 | V230: =IF(OR($I230="",$I230="—"),1,0) -> 0 | W230: =IF(AND(ISNUMBER($D230),ISNUMBER($E230)),IF($E230>$D230,1,0),0)+IF(AND(ISNUMBER($D230),ISNUMBER($F230)),IF($D230>$F230,1,0),0)+IF(AND(ISNUMBER($E230),ISNUMBER($F230)),IF($E230>$F230,1,0),0) -> 0 | X230: CC 初評
A231: SRC_ZP_227 | B231: api_price_1h26 | C231: API 平均售價上升 | D231: 101 | G231: % | H231: 1H2026 | I231: 智譜（Z.AI）2026 中期業績公告 | J231: https://ea-cdn.eurolandir.com/press-releases-attachments/4174939/HKEX-EPS_20260831_12308928_0.PDF | K231: 2026-08-31 | L231: 2026-10-08 | M231: Interested-party | N231: 智譜：上市後股價、配售誘因 | O231: 管理層口徑 | P231: 1 | Q231: 利害關係方 | R231: 智譜：上市後股價、配售誘因 | S231: 一手 | T231: 原文「the average API selling price increased by approximately 101%」；比較基準未明 | U231: =IF(AND($D231="",$E231="",$F231=""),1,0) -> 0 | V231: =IF(OR($I231="",$I231="—"),1,0) -> 0 | W231: =IF(AND(ISNUMBER($D231),ISNUMBER($E231)),IF($E231>$D231,1,0),0)+IF(AND(ISNUMBER($D231),ISNUMBER($F231)),IF($D231>$F231,1,0),0)+IF(AND(ISNUMBER($E231),ISNUMBER($F231)),IF($E231>$F231,1,0),0) -> 0 | X231: CC 初評
A232: SRC_ZP_228 | B232: codingplan_class_1h26 | C232: GLM Coding Plan 收入歸屬 | H232: 1H2026 | I232: 智譜（Z.AI）2026 中期業績公告 | J232: https://ea-cdn.eurolandir.com/press-releases-attachments/4174939/HKEX-EPS_20260831_12308928_0.PDF | K232: 2026-08-31 | L232: 2026-10-08 | M232: Derived | O232: Derived | P232: 2 | Q232: 推算 | R232: 由其他 SRC 列推算（見備註）；立場同其來源 | S232: 一手 | T232: 未單列。雲端分部＝開放平台及 API（825,176），本地化＝其餘三線合計；Coding Plan 為雲端訂閱，故在開放平台及 API 內 | U232: =IF(AND($D232="",$E232="",$F232=""),1,0) -> 1 | V232: =IF(OR($I232="",$I232="—"),1,0) -> 0 | W232: =IF(AND(ISNUMBER($D232),ISNUMBER($E232)),IF($E232>$D232,1,0),0)+IF(AND(ISNUMBER($D232),ISNUMBER($F232)),IF($D232>$F232,1,0),0)+IF(AND(ISNUMBER($E232),ISNUMBER($F232)),IF($E232>$F232,1,0),0) -> 0 | X232: CC 初評
A233: SRC_ZP_229 | B233: domestic_chip_1h26 | C233: 國產晶片推論集群規模 | D233: 100000 | E233: 100000 | G233: 顆（下限） | H233: 1H2026 | I233: 智譜（Z.AI）2026 中期業績公告 | J233: https://ea-cdn.eurolandir.com/press-releases-attachments/4174939/HKEX-EPS_20260831_12308928_0.PDF | K233: 2026-08-31 | L233: 2026-10-08 | M233: Interested-party | N233: 智譜：上市後股價、配售誘因 | O233: 管理層口徑 | P233: 1 | Q233: 利害關係方 | R233: 智譜：上市後股價、配售誘因 | S233: 一手 | T233: 原文「across a cluster of over 100,000 domestic chips」 | U233: =IF(AND($D233="",$E233="",$F233=""),1,0) -> 0 | V233: =IF(OR($I233="",$I233="—"),1,0) -> 0 | W233: =IF(AND(ISNUMBER($D233),ISNUMBER($E233)),IF($E233>$D233,1,0),0)+IF(AND(ISNUMBER($D233),ISNUMBER($F233)),IF($D233>$F233,1,0),0)+IF(AND(ISNUMBER($E233),ISNUMBER($F233)),IF($E233>$F233,1,0),0) -> 0 | X233: CC 初評
A234: SRC_ZP_230 | B234: rd_compute_fy22 | C234: 研發開支中算力服務費（含模型訓練及雲端部署服務） | D234: 0.15 | G234: RMB 億 | H234: FY2022 | I234: 36氪轉載〈市值水晶〉（王浩然） | J234: https://www.36kr.com/p/3611675144253960 | K234: 2025-12-26 | L234: 2026-10-08 | M234: Interested-party | N234: 媒體轉述 | O234: 媒體轉述（招股章程） | P234: 2 | Q234: 利害關係方 | R234: 媒體轉述 | S234: 二手 | T234: 原文「从2022年的0.15亿元」；原始招股章程財務資料節未能讀取；【r2 P2 口徑更正】原文「含雲端部署」不正確：研發項下算力費（招股章程第 255、267 頁，SRC_ZP_611）不含營業成本中的雲端部署算力 | U234: =IF(AND($D234="",$E234="",$F234=""),1,0) -> 0 | V234: =IF(OR($I234="",$I234="—"),1,0) -> 0 | W234: =IF(AND(ISNUMBER($D234),ISNUMBER($E234)),IF($E234>$D234,1,0),0)+IF(AND(ISNUMBER($D234),ISNUMBER($F234)),IF($D234>$F234,1,0),0)+IF(AND(ISNUMBER($E234),ISNUMBER($F234)),IF($E234>$F234,1,0),0) -> 0 | X234: CC 初評
A235: SRC_ZP_231 | B235: rd_compute_1h25 | C235: 研發開支中算力服務費（含模型訓練及雲端部署服務） | D235: 11.45 | G235: RMB 億 | H235: 1H2025 | I235: 36氪轉載〈市值水晶〉（王浩然） | J235: https://www.36kr.com/p/3611675144253960 | K235: 2025-12-26 | L235: 2026-10-08 | M235: Interested-party | N235: 媒體轉述 | O235: 媒體轉述（招股章程） | P235: 2 | Q235: 利害關係方 | R235: 媒體轉述 | S235: 二手 | T235: 原文「到2025年上半年的11.45亿」；原始招股章程財務資料節未能讀取；【r2 P2 口徑更正】同 SRC_ZP_230；一手值見 SRC_ZP_615，三科目合計見 SRC_ZP_742 | U235: =IF(AND($D235="",$E235="",$F235=""),1,0) -> 0 | V235: =IF(OR($I235="",$I235="—"),1,0) -> 0 | W235: =IF(AND(ISNUMBER($D235),ISNUMBER($E235)),IF($E235>$D235,1,0),0)+IF(AND(ISNUMBER($D235),ISNUMBER($F235)),IF($D235>$F235,1,0),0)+IF(AND(ISNUMBER($E235),ISNUMBER($F235)),IF($E235>$F235,1,0),0) -> 0 | X235: CC 初評
A236: SRC_ZP_232 | B236: rd_compute_fy24 | C236: 研發開支中算力服務費 | D236: 15.52 | G236: RMB 億 | H236: FY2024 | I236: 華爾街見聞 | J236: https://wallstreetcn.com/articles/3761769 | K236: 2025-12-20 | L236: 2026-10-08 | M236: Interested-party | N236: 媒體轉述 | O236: 媒體轉述（招股章程） | P236: 2 | Q236: 利害關係方 | R236: 媒體轉述 | S236: 二手 | T236: 原文 2024年算力服務費 15.52億元，「同期收入的5倍左右」；原始財務資料節未能讀取 | U236: =IF(AND($D236="",$E236="",$F236=""),1,0) -> 0 | V236: =IF(OR($I236="",$I236="—"),1,0) -> 0 | W236: =IF(AND(ISNUMBER($D236),ISNUMBER($E236)),IF($E236>$D236,1,0),0)+IF(AND(ISNUMBER($D236),ISNUMBER($F236)),IF($D236>$F236,1,0),0)+IF(AND(ISNUMBER($E236),ISNUMBER($F236)),IF($E236>$F236,1,0),0) -> 0 | X236: CC 初評
A237: SRC_ZP_233 | B237: rd_compute_fy24_b | C237: 研發開支中算力服務費 | D237: 15.53 | G237: RMB 億 | H237: FY2024 | I237: 每日經濟新聞 | J237: https://www.nbd.com.cn/articles/2025-12-21/4189232.html | K237: 2025-12-21 | L237: 2026-10-08 | M237: Interested-party | N237: 媒體轉述 | O237: 媒體轉述（招股章程） | P237: 2 | Q237: 利害關係方 | R237: 媒體轉述 | S237: 二手 | T237: 15.53 億元，占研發逾 70%；與華爾街見聞 15.52 億差 0.01（四捨五入） | U237: =IF(AND($D237="",$E237="",$F237=""),1,0) -> 0 | V237: =IF(OR($I237="",$I237="—"),1,0) -> 0 | W237: =IF(AND(ISNUMBER($D237),ISNUMBER($E237)),IF($E237>$D237,1,0),0)+IF(AND(ISNUMBER($D237),ISNUMBER($F237)),IF($D237>$F237,1,0),0)+IF(AND(ISNUMBER($E237),ISNUMBER($F237)),IF($E237>$F237,1,0),0) -> 0 | X237: CC 初評
A238: SRC_ZP_234 | B238: rd_compute_share_1h25 | C238: 算力服務費占研發開支比重 | D238: 70 | E238: 70 | G238: %（下限） | H238: 1H2025 | I238: 每日經濟新聞 | J238: https://www.nbd.com.cn/articles/2025-12-21/4189232.html | K238: 2025-12-21 | L238: 2026-10-08 | M238: Interested-party | N238: 媒體轉述 | O238: 媒體轉述（招股章程） | P238: 2 | Q238: 利害關係方 | R238: 媒體轉述 | S238: 二手 | T238: 原文「仍维持在七成以上」 | U238: =IF(AND($D238="",$E238="",$F238=""),1,0) -> 0 | V238: =IF(OR($I238="",$I238="—"),1,0) -> 0 | W238: =IF(AND(ISNUMBER($D238),ISNUMBER($E238)),IF($E238>$D238,1,0),0)+IF(AND(ISNUMBER($D238),ISNUMBER($F238)),IF($D238>$F238,1,0),0)+IF(AND(ISNUMBER($E238),ISNUMBER($F238)),IF($E238>$F238,1,0),0) -> 0 | X238: CC 初評
A239: SRC_ZP_235 | B239: rd_staff_cost_fy22 | C239: 研發人員工資成本 | D239: 0.42 | G239: RMB 億 | H239: FY2022 | I239: 36氪轉載〈市值水晶〉（王浩然） | J239: https://www.36kr.com/p/3611675144253960 | K239: 2025-12-26 | L239: 2026-10-08 | M239: Interested-party | N239: 媒體轉述 | O239: 媒體轉述（招股章程） | P239: 2 | Q239: 利害關係方 | R239: 媒體轉述 | S239: 二手 | T239: 原文「研发人员的工资成本分别为0.42亿、1.37亿、3.24亿元…2.66亿元」 | U239: =IF(AND($D239="",$E239="",$F239=""),1,0) -> 0 | V239: =IF(OR($I239="",$I239="—"),1,0) -> 0 | W239: =IF(AND(ISNUMBER($D239),ISNUMBER($E239)),IF($E239>$D239,1,0),0)+IF(AND(ISNUMBER($D239),ISNUMBER($F239)),IF($D239>$F239,1,0),0)+IF(AND(ISNUMBER($E239),ISNUMBER($F239)),IF($E239>$F239,1,0),0) -> 0 | X239: CC 初評
A240: SRC_ZP_236 | B240: rd_staff_cost_fy23 | C240: 研發人員工資成本 | D240: 1.37 | G240: RMB 億 | H240: FY2023 | I240: 36氪轉載〈市值水晶〉（王浩然） | J240: https://www.36kr.com/p/3611675144253960 | K240: 2025-12-26 | L240: 2026-10-08 | M240: Interested-party | N240: 媒體轉述 | O240: 媒體轉述（招股章程） | P240: 2 | Q240: 利害關係方 | R240: 媒體轉述 | S240: 二手 | T240: 原文「研发人员的工资成本分别为0.42亿、1.37亿、3.24亿元…2.66亿元」 | U240: =IF(AND($D240="",$E240="",$F240=""),1,0) -> 0 | V240: =IF(OR($I240="",$I240="—"),1,0) -> 0 | W240: =IF(AND(ISNUMBER($D240),ISNUMBER($E240)),IF($E240>$D240,1,0),0)+IF(AND(ISNUMBER($D240),ISNUMBER($F240)),IF($D240>$F240,1,0),0)+IF(AND(ISNUMBER($E240),ISNUMBER($F240)),IF($E240>$F240,1,0),0) -> 0 | X240: CC 初評
A241: SRC_ZP_237 | B241: rd_staff_cost_fy24 | C241: 研發人員工資成本 | D241: 3.24 | G241: RMB 億 | H241: FY2024 | I241: 36氪轉載〈市值水晶〉（王浩然） | J241: https://www.36kr.com/p/3611675144253960 | K241: 2025-12-26 | L241: 2026-10-08 | M241: Interested-party | N241: 媒體轉述 | O241: 媒體轉述（招股章程） | P241: 2 | Q241: 利害關係方 | R241: 媒體轉述 | S241: 二手 | T241: 原文「研发人员的工资成本分别为0.42亿、1.37亿、3.24亿元…2.66亿元」 | U241: =IF(AND($D241="",$E241="",$F241=""),1,0) -> 0 | V241: =IF(OR($I241="",$I241="—"),1,0) -> 0 | W241: =IF(AND(ISNUMBER($D241),ISNUMBER($E241)),IF($E241>$D241,1,0),0)+IF(AND(ISNUMBER($D241),ISNUMBER($F241)),IF($D241>$F241,1,0),0)+IF(AND(ISNUMBER($E241),ISNUMBER($F241)),IF($E241>$F241,1,0),0) -> 0 | X241: CC 初評
A242: SRC_ZP_238 | B242: rd_staff_cost_1h25 | C242: 研發人員工資成本 | D242: 2.66 | G242: RMB 億 | H242: 1H2025 | I242: 36氪轉載〈市值水晶〉（王浩然） | J242: https://www.36kr.com/p/3611675144253960 | K242: 2025-12-26 | L242: 2026-10-08 | M242: Interested-party | N242: 媒體轉述 | O242: 媒體轉述（招股章程） | P242: 2 | Q242: 利害關係方 | R242: 媒體轉述 | S242: 二手 | T242: 原文「研发人员的工资成本分别为0.42亿、1.37亿、3.24亿元…2.66亿元」 | U242: =IF(AND($D242="",$E242="",$F242=""),1,0) -> 0 | V242: =IF(OR($I242="",$I242="—"),1,0) -> 0 | W242: =IF(AND(ISNUMBER($D242),ISNUMBER($E242)),IF($E242>$D242,1,0),0)+IF(AND(ISNUMBER($D242),ISNUMBER($F242)),IF($D242>$F242,1,0),0)+IF(AND(ISNUMBER($E242),ISNUMBER($F242)),IF($E242>$F242,1,0),0) -> 0 | X242: CC 初評
A243: SRC_ZP_239 | B243: rd_staff_share_fy24 | C243: 工資成本占研發開支比重 | D243: 14.8 | G243: % | H243: FY2024 | I243: 鈦媒體（山上） | J243: https://www.tmtpost.com/7815849.html | K243: 2025-12-21 | L243: 2026-10-08 | M243: Interested-party | N243: 媒體轉述 | O243: 媒體轉述（招股章程） | P243: 2 | Q243: 利害關係方 | R243: 媒體轉述 | S243: 二手 | T243: 原文 2024 年工資成本占研發 14.8%（3.24/21.95 吻合） | U243: =IF(AND($D243="",$E243="",$F243=""),1,0) -> 0 | V243: =IF(OR($I243="",$I243="—"),1,0) -> 0 | W243: =IF(AND(ISNUMBER($D243),ISNUMBER($E243)),IF($E243>$D243,1,0),0)+IF(AND(ISNUMBER($D243),ISNUMBER($F243)),IF($D243>$F243,1,0),0)+IF(AND(ISNUMBER($E243),ISNUMBER($F243)),IF($E243>$F243,1,0),0) -> 0 | X243: CC 初評
A244: SRC_ZP_240 | B244: rd_staff_pct_1h25 | C244: 研發人員占員工比重 | D244: 74.4 | G244: % | H244: 2025-06-30 | I244: 鈦媒體（山上） | J244: https://www.tmtpost.com/7815849.html | K244: 2025-12-21 | L244: 2026-10-08 | M244: Interested-party | N244: 媒體轉述 | O244: 媒體轉述（招股章程） | P244: 2 | Q244: 利害關係方 | R244: 媒體轉述 | S244: 二手 | T244: 原文 員工 883 人、研發 657 人，占 74.4%（證券日報稱 74%） | U244: =IF(AND($D244="",$E244="",$F244=""),1,0) -> 0 | V244: =IF(OR($I244="",$I244="—"),1,0) -> 0 | W244: =IF(AND(ISNUMBER($D244),ISNUMBER($E244)),IF($E244>$D244,1,0),0)+IF(AND(ISNUMBER($D244),ISNUMBER($F244)),IF($D244>$F244,1,0),0)+IF(AND(ISNUMBER($E244),ISNUMBER($F244)),IF($E244>$F244,1,0),0) -> 0 | X244: CC 初評
A245: SRC_ZP_241 | B245: px_usd_glm53_in | C245: GLM-5.3 國際站牌價（輸入） | D245: 1.4 | G245: USD／百萬 token | H245: 2026-10（現行） | I245: Z.ai 開發者文件 Pricing 頁（國際站官方牌價） | J245: https://docs.z.ai/guides/overview/pricing.md | K245: 2026-10-08 | L245: 2026-10-08 | M245: Verified | P245: 1 | Q245: 利害關係方 | R245: 公司公開且具約束力的報價，誤報誘因低 | S245: 一手 | T245: 官方表列 GLM-5.3：Input $1.4／Cached Input $0.26／Output $4.4；快取儲存「Limited-time free」；無長度分段 | U245: =IF(AND($D245="",$E245="",$F245=""),1,0) -> 0 | V245: =IF(OR($I245="",$I245="—"),1,0) -> 0 | W245: =IF(AND(ISNUMBER($D245),ISNUMBER($E245)),IF($E245>$D245,1,0),0)+IF(AND(ISNUMBER($D245),ISNUMBER($F245)),IF($D245>$F245,1,0),0)+IF(AND(ISNUMBER($E245),ISNUMBER($F245)),IF($E245>$F245,1,0),0) -> 0 | X245: CC 初評
A246: SRC_ZP_242 | B246: px_usd_glm53_cache | C246: GLM-5.3 國際站牌價（快取命中輸入） | D246: 0.26 | G246: USD／百萬 token | H246: 2026-10（現行） | I246: Z.ai 開發者文件 Pricing 頁（國際站官方牌價） | J246: https://docs.z.ai/guides/overview/pricing.md | K246: 2026-10-08 | L246: 2026-10-08 | M246: Verified | P246: 1 | Q246: 利害關係方 | R246: 公司公開且具約束力的報價，誤報誘因低 | S246: 一手 | T246: 官方表列 GLM-5.3：Input $1.4／Cached Input $0.26／Output $4.4；快取儲存「Limited-time free」；無長度分段 | U246: =IF(AND($D246="",$E246="",$F246=""),1,0) -> 0 | V246: =IF(OR($I246="",$I246="—"),1,0) -> 0 | W246: =IF(AND(ISNUMBER($D246),ISNUMBER($E246)),IF($E246>$D246,1,0),0)+IF(AND(ISNUMBER($D246),ISNUMBER($F246)),IF($D246>$F246,1,0),0)+IF(AND(ISNUMBER($E246),ISNUMBER($F246)),IF($E246>$F246,1,0),0) -> 0 | X246: CC 初評
A247: SRC_ZP_243 | B247: px_usd_glm53_out | C247: GLM-5.3 國際站牌價（輸出） | D247: 4.4 | G247: USD／百萬 token | H247: 2026-10（現行） | I247: Z.ai 開發者文件 Pricing 頁（國際站官方牌價） | J247: https://docs.z.ai/guides/overview/pricing.md | K247: 2026-10-08 | L247: 2026-10-08 | M247: Verified | P247: 1 | Q247: 利害關係方 | R247: 公司公開且具約束力的報價，誤報誘因低 | S247: 一手 | T247: 官方表列 GLM-5.3：Input $1.4／Cached Input $0.26／Output $4.4；快取儲存「Limited-time free」；無長度分段 | U247: =IF(AND($D247="",$E247="",$F247=""),1,0) -> 0 | V247: =IF(OR($I247="",$I247="—"),1,0) -> 0 | W247: =IF(AND(ISNUMBER($D247),ISNUMBER($E247)),IF($E247>$D247,1,0),0)+IF(AND(ISNUMBER($D247),ISNUMBER($F247)),IF($D247>$F247,1,0),0)+IF(AND(ISNUMBER($E247),ISNUMBER($F247)),IF($E247>$F247,1,0),0) -> 0 | X247: CC 初評
A248: SRC_ZP_244 | B248: px_usd_glm52_in | C248: GLM-5.2 國際站牌價（輸入） | D248: 1.4 | G248: USD／百萬 token | H248: 2026-10（現行） | I248: Z.ai 開發者文件 Pricing 頁（國際站官方牌價） | J248: https://docs.z.ai/guides/overview/pricing.md | K248: 2026-10-08 | L248: 2026-10-08 | M248: Verified | P248: 1 | Q248: 利害關係方 | R248: 公司公開且具約束力的報價，誤報誘因低 | S248: 一手 | T248: 官方表列 GLM-5.2：Input $1.4／Cached Input $0.26／Output $4.4；快取儲存「Limited-time free」；無長度分段 | U248: =IF(AND($D248="",$E248="",$F248=""),1,0) -> 0 | V248: =IF(OR($I248="",$I248="—"),1,0) -> 0 | W248: =IF(AND(ISNUMBER($D248),ISNUMBER($E248)),IF($E248>$D248,1,0),0)+IF(AND(ISNUMBER($D248),ISNUMBER($F248)),IF($D248>$F248,1,0),0)+IF(AND(ISNUMBER($E248),ISNUMBER($F248)),IF($E248>$F248,1,0),0) -> 0 | X248: CC 初評
A249: SRC_ZP_245 | B249: px_usd_glm52_cache | C249: GLM-5.2 國際站牌價（快取命中輸入） | D249: 0.26 | G249: USD／百萬 token | H249: 2026-10（現行） | I249: Z.ai 開發者文件 Pricing 頁（國際站官方牌價） | J249: https://docs.z.ai/guides/overview/pricing.md | K249: 2026-10-08 | L249: 2026-10-08 | M249: Verified | P249: 1 | Q249: 利害關係方 | R249: 公司公開且具約束力的報價，誤報誘因低 | S249: 一手 | T249: 官方表列 GLM-5.2：Input $1.4／Cached Input $0.26／Output $4.4；快取儲存「Limited-time free」；無長度分段 | U249: =IF(AND($D249="",$E249="",$F249=""),1,0) -> 0 | V249: =IF(OR($I249="",$I249="—"),1,0) -> 0 | W249: =IF(AND(ISNUMBER($D249),ISNUMBER($E249)),IF($E249>$D249,1,0),0)+IF(AND(ISNUMBER($D249),ISNUMBER($F249)),IF($D249>$F249,1,0),0)+IF(AND(ISNUMBER($E249),ISNUMBER($F249)),IF($E249>$F249,1,0),0) -> 0 | X249: CC 初評
A250: SRC_ZP_246 | B250: px_usd_glm52_out | C250: GLM-5.2 國際站牌價（輸出） | D250: 4.4 | G250: USD／百萬 token | H250: 2026-10（現行） | I250: Z.ai 開發者文件 Pricing 頁（國際站官方牌價） | J250: https://docs.z.ai/guides/overview/pricing.md | K250: 2026-10-08 | L250: 2026-10-08 | M250: Verified | P250: 1 | Q250: 利害關係方 | R250: 公司公開且具約束力的報價，誤報誘因低 | S250: 一手 | T250: 官方表列 GLM-5.2：Input $1.4／Cached Input $0.26／Output $4.4；快取儲存「Limited-time free」；無長度分段 | U250: =IF(AND($D250="",$E250="",$F250=""),1,0) -> 0 | V250: =IF(OR($I250="",$I250="—"),1,0) -> 0 | W250: =IF(AND(ISNUMBER($D250),ISNUMBER($E250)),IF($E250>$D250,1,0),0)+IF(AND(ISNUMBER($D250),ISNUMBER($F250)),IF($D250>$F250,1,0),0)+IF(AND(ISNUMBER($E250),ISNUMBER($F250)),IF($E250>$F250,1,0),0) -> 0 | X250: CC 初評
...

Sheet TK_Link
A1: TK_Link — Tokenomics 快照（第 0 層連結；不用 Excel 外部連結）
A2: 具名區（OpenAI v0.6 的 63 名：IF_／SRC_DEM_／L1_；Z3b 加 IF_CostPre／Cache／Dec_* 9 名）：值（藍字）由 builder 從 Tokenomics master 的 model/CURRENT 讀出寫入。本模型公式只引用 TK_ 名稱或本頁儲存格。
A3: Tokenomics 檔案 | B3: 20261022_Tokenomics_v19.0.xlsx
A4: Tokenomics 版本 | B4: v19.0
A5: Tokenomics 提交 SHA（master） | B5: 1916a06465bb0c7efed21383075f2ae098508e24
A6: 讀取日期 | B6: 2026-10-22
I7: 世代 | J7: Hopper H100 | K7: Hopper H100 | L7: Hopper H100 | M7: GB200 NVL72 | N7: GB200 NVL72 | O7: GB200 NVL72 | P7: GB300 NVL72 | Q7: GB300 NVL72 | R7: GB300 NVL72 | S7: VR200 NVL72 | T7: VR200 NVL72 | U7: VR200 NVL72 | V7: Rubin Ultra（MGX NVL 單架，72 GPU） | W7: Rubin Ultra（MGX NVL 單架，72 GPU） | X7: Rubin Ultra（MGX NVL 單架，72 GPU）
I8: 成本情境 | J8: 低成本 | K8: 基準 | L8: 高成本 | M8: 低成本 | N8: 基準 | O8: 高成本 | P8: 低成本 | Q8: 基準 | R8: 高成本 | S8: 低成本 | T8: 基準 | U8: 高成本 | V8: 低成本 | W8: 基準 | X8: 高成本
A9: Tokenomics 名稱 | B9: 本模型名稱 | C9: 說明 | D9: 單位 | E9: 欄數 | F9: 狀態 | G9: Tokenomics 版本 | H9: 提交 SHA | I9: 讀取日期 | J9: 值1 | K9: 值2 | L9: 值3 | M9: 值4 | N9: 值5 | O9: 值6 | P9: 值7 | Q9: 值8 | R9: 值9 | S9: 值10 | T9: 值11 | U9: 值12 | V9: 值13 | W9: 值14 | X9: 值15
A10: IF_TokGW_Astra | B10: TK_IF_TokGW_Astra | C10: 每 GW 總產出（100%） | D10: M tok/年 | E10: 15 | F10: OK | G10: v19.0 | H10: 1916a06 | I10: 2026-10-22 | J10: 6.8090257e+09 | K10: 6.8090257e+09 | L10: 6.8090257e+09 | M10: 3.3674782e+10 | N10: 3.3674782e+10 | O10: 3.3674782e+10 | P10: 3.9257828e+10 | Q10: 3.9257828e+10 | R10: 3.9257828e+10 | S10: 6.9625194e+10 | T10: 6.9625194e+10 | U10: 6.9625194e+10 | V10: 9.8521567e+10 | W10: 9.8521567e+10 | X10: 9.8521567e+10
A11: IF_TokGW_Luna | B11: TK_IF_TokGW_Luna | C11: 每 GW 總產出（100%） | D11: M tok/年 | E11: 15 | F11: OK | G11: v19.0 | H11: 1916a06 | I11: 2026-10-22 | J11: 1.1222824e+11 | K11: 1.1222824e+11 | L11: 1.1222824e+11 | M11: 5.5783891e+11 | N11: 5.5783891e+11 | O11: 5.5783891e+11 | P11: 7.2317604e+11 | Q11: 7.2317604e+11 | R11: 7.2317604e+11 | S11: 1.0432677e+12 | T11: 1.0432677e+12 | U11: 1.0432677e+12 | V11: 1.404588e+12 | W11: 1.404588e+12 | X11: 1.404588e+12
A12: IF_TokGW_Sol | B12: TK_IF_TokGW_Sol | C12: 每 GW 總產出（100%） | D12: M tok/年 | E12: 15 | F12: OK | G12: v19.0 | H12: 1916a06 | I12: 2026-10-22 | J12: 3.3634916e+10 | K12: 3.3634916e+10 | L12: 3.3634916e+10 | M12: 1.6371585e+11 | N12: 1.6371585e+11 | O12: 1.6371585e+11 | P12: 2.1233432e+11 | Q12: 2.1233432e+11 | R12: 2.1233432e+11 | S12: 3.189849e+11 | T12: 3.189849e+11 | U12: 3.189849e+11 | V12: 4.3438046e+11 | W12: 4.3438046e+11 | X12: 4.3438046e+11
A13: IF_Util | B13: TK_IF_Util | C13: 基準利用率（第 0 層；下游可覆寫） | D13: % | E13: 1 | F13: OK | G13: v19.0 | H13: 1916a06 | I13: 2026-10-22 | J13: 0.6
A14: IF_HoldEcon | B14: TK_IF_HoldEcon | C14: 每 GW 年持有成本 — 經濟口徑 | D14: $B/年 | E14: 15 | F14: OK | G14: v19.0 | H14: 1916a06 | I14: 2026-10-22 | J14: 6.7910747 | K14: 9.7030873 | L14: 16.66377 | M14: 6.6118163 | N14: 8.8281656 | O14: 14.318575 | P14: 8.4288991 | Q14: 10.886411 | R14: 18.534646 | S14: 9.5120769 | T14: 12.225471 | U14: 19.750627 | V14: 10.102545 | W14: 15.354483 | X14: 28.030245
A15: IF_FullCost_Astra | B15: TK_IF_FullCost_Astra | C15: 全成本 $/M（服務＋快取儲存＋自下而上攤提；基準利用率） | D15: $/M | E15: 15 | F15: OK | G15: v19.0 | H15: 1916a06 | I15: 2026-10-22 | J15: 4.4404114 | K15: 6.344364 | L15: 10.895446 | M15: 0.53031631 | N15: 0.708009 | O15: 1.1481948 | P15: 0.59852248 | Q15: 0.77296134 | R15: 1.3158475 | S15: 0.32897901 | T15: 0.42275916 | U15: 0.68284311 | V15: 0.22427424 | W15: 0.34075004 | X15: 0.62186904
A16: IF_FullCost_Luna | B16: TK_IF_FullCost_Luna | C16: 全成本 $/M（服務＋快取儲存＋自下而上攤提；基準利用率） | D16: $/M | E16: 15 | F16: OK | G16: v19.0 | H16: 1916a06 | I16: 2026-10-22 | J16: 0.14706463 | K16: 0.21012129 | L16: 0.36084777 | M16: 0.022499115 | N16: 0.03003742 | O16: 0.048711544 | P16: 0.022877902 | Q16: 0.029544976 | R16: 0.050294152 | S16: 0.016788463 | T16: 0.021574412 | U16: 0.034847464 | V16: 0.012809112 | W16: 0.019462463 | X16: 0.035520591
A17: IF_FullCost_Sol | B17: TK_IF_FullCost_Sol | C17: 全成本 $/M（服務＋快取儲存＋自下而上攤提；基準利用率） | D17: $/M | E17: 15 | F17: OK | G17: v19.0 | H17: 1916a06 | I17: 2026-10-22 | J17: 0.45057467 | K17: 0.64377448 | L17: 1.1055865 | M17: 0.075115753 | N17: 0.10029018 | O17: 0.16265305 | P17: 0.075557593 | Q17: 0.097582523 | R17: 0.16612821 | S17: 0.053782904 | T17: 0.069120513 | U17: 0.11165687 | V17: 0.040901542 | W17: 0.062156746 | X17: 0.11345703
A18: IF_PriceCached_Astra | B18: TK_IF_PriceCached_Astra | C18: 快取輸入 $/M — OpenAI 有效 | D18: $/M | E18: 1 | F18: OK | G18: v19.0 | H18: 1916a06 | I18: 2026-10-22 | J18: 0.8
A19: IF_PriceCached_Luna | B19: TK_IF_PriceCached_Luna | C19: 快取輸入 $/M — OpenAI 有效 | D19: $/M | E19: 1 | F19: OK | G19: v19.0 | H19: 1916a06 | I19: 2026-10-22 | J19: 0.008
A20: IF_PriceCached_Sol | B20: TK_IF_PriceCached_Sol | C20: 快取輸入 $/M — OpenAI 有效 | D20: $/M | E20: 1 | F20: OK | G20: v19.0 | H20: 1916a06 | I20: 2026-10-22 | J20: 0.16
A21: IF_PriceFresh_Astra | B21: TK_IF_PriceFresh_Astra | C21: 新鮮輸入 $/M — OpenAI 有效 | D21: $/M | E21: 1 | F21: OK | G21: v19.0 | H21: 1916a06 | I21: 2026-10-22 | J21: 8
A22: IF_PriceFresh_Luna | B22: TK_IF_PriceFresh_Luna | C22: 新鮮輸入 $/M — OpenAI 有效 | D22: $/M | E22: 1 | F22: OK | G22: v19.0 | H22: 1916a06 | I22: 2026-10-22 | J22: 0.08
A23: IF_PriceFresh_Sol | B23: TK_IF_PriceFresh_Sol | C23: 新鮮輸入 $/M — OpenAI 有效 | D23: $/M | E23: 1 | F23: OK | G23: v19.0 | H23: 1916a06 | I23: 2026-10-22 | J23: 1.6
A24: IF_PriceOut_Astra | B24: TK_IF_PriceOut_Astra | C24: 可見輸出 $/M — OpenAI 有效 | D24: $/M | E24: 1 | F24: OK | G24: v19.0 | H24: 1916a06 | I24: 2026-10-22 | J24: 40
A25: IF_PriceOut_Luna | B25: TK_IF_PriceOut_Luna | C25: 可見輸出 $/M — OpenAI 有效 | D25: $/M | E25: 1 | F25: OK | G25: v19.0 | H25: 1916a06 | I25: 2026-10-22 | J25: 0.4
A26: IF_PriceOut_Sol | B26: TK_IF_PriceOut_Sol | C26: 可見輸出 $/M — OpenAI 有效 | D26: $/M | E26: 1 | F26: OK | G26: v19.0 | H26: 1916a06 | I26: 2026-10-22 | J26: 8
A27: IF_PriceRef_Astra | B27: TK_IF_PriceRef_Astra | C27: 參考請求混合 $/M — OpenAI 有效 | D27: $/M | E27: 1 | F27: OK | G27: v19.0 | H27: 1916a06 | I27: 2026-10-22 | J27: 8.0355556
A28: IF_PriceRef_Luna | B28: TK_IF_PriceRef_Luna | C28: 參考請求混合 $/M — OpenAI 有效 | D28: $/M | E28: 1 | F28: OK | G28: v19.0 | H28: 1916a06 | I28: 2026-10-22 | J28: 0.080355556
A29: IF_PriceRef_Sol | B29: TK_IF_PriceRef_Sol | C29: 參考請求混合 $/M — OpenAI 有效 | D29: $/M | E29: 1 | F29: OK | G29: v19.0 | H29: 1916a06 | I29: 2026-10-22 | J29: 1.6071111
... A35: IF_FrontRef_Sol | B35: TK_IF_FrontRef_Sol | C35: 參考請求混合 $/M — 前緣有效 | D35: $/M | E35: 1 | F35: OK | G35: v19.0 | H35: 1916a06 | I35: 2026-10-22 | J35: 1.6071111
A36: IF_ProgGWyr_Astra | B36: TK_IF_ProgGWyr_Astra | C36: 研發計畫占 1 GW 一年 | D36: % | E36: 15 | F36: OK | G36: v19.0 | H36: 1916a06 | I36: 2026-10-22 | J36: 0.15684814 | K36: 0.15684814 | L36: 0.15684814 | M36: 0.057835529 | N36: 0.057835529 | O36: 0.057835529 | P36: 0.065586407 | Q36: 0.065586407 | R36: 0.065586407 | S36: 0.040017843 | T36: 0.040017843 | U36: 0.040017843 | V36: 0.027250415 | W36: 0.027250415 | X36: 0.027250415
A37: IF_ProgGWyr_Luna | B37: TK_IF_ProgGWyr_Luna | C37: 研發計畫占 1 GW 一年 | D37: % | E37: 15 | F37: OK | G37: v19.0 | H37: 1916a06 | I37: 2026-10-22 | J37: 0.009274344 | K37: 0.009274344 | L37: 0.009274344 | M37: 0.0027645609 | N37: 0.0027645609 | O37: 0.0027645609 | P37: 0.0033289655 | Q37: 0.0033289655 | R37: 0.0033289655 | S37: 0.0022043397 | T37: 0.0022043397 | U37: 0.0022043397 | V37: 0.0014304485 | W37: 0.0014304485 | X37: 0.0014304485
A38: IF_ProgGWyr_Sol | B38: TK_IF_ProgGWyr_Sol | C38: 研發計畫占 1 GW 一年 | D38: % | E38: 15 | F38: OK | G38: v19.0 | H38: 1916a06 | I38: 2026-10-22 | J38: 0.025757353 | K38: 0.025757353 | L38: 0.025757353 | M38: 0.0088777551 | N38: 0.0088777551 | O38: 0.0088777551 | P38: 0.010227304 | Q38: 0.010227304 | R38: 0.010227304 | S38: 0.006421121 | T38: 0.006421121 | U38: 0.006421121 | V38: 0.0043094856 | W38: 0.0043094856 | X38: 0.0043094856
A39: IF_RDMult | B39: TK_IF_RDMult | C39: 研發倍數（第 0 層基準；下游可覆寫） | D39: x | E39: 1 | F39: OK | G39: v19.0 | H39: 1916a06 | I39: 2026-10-22 | J39: 8
A40: IF_TrainGenDefault | B40: TK_IF_TrainGenDefault | C40: 下游預設訓練世代（索引；J13） | D40: 索引 | E40: 1 | F40: OK | G40: v19.0 | H40: 1916a06 | I40: 2026-10-22 | J40: 4
A41: SRC_DEM_004 | B41: TK_SRC_DEM_004 | C41: OpenAI 2025 推論支出（年度；json 一致集（與 005／006／007 同源）） | D41: $B | E41: 1 | F41: OK | G41: v19.0 | H41: 1916a06 | I41: 2026-10-22 | J41: 8.4
A42: SRC_DEM_005 | B42: TK_SRC_DEM_005 | C42: OpenAI 2025 非付費用戶推論支出（年度） | D42: $B | E42: 1 | F42: OK | G42: v19.0 | H42: 1916a06 | I42: 2026-10-22 | J42: 3.9
A43: SRC_DEM_006 | B43: TK_SRC_DEM_006 | C43: OpenAI 2025 訓練支出（年度；約值） | D43: $B | E43: 1 | F43: OK | G43: v19.0 | H43: 1916a06 | I43: 2026-10-22 | J43: 12
A44: SRC_DEM_007 | B44: TK_SRC_DEM_007 | C44: OpenAI 2025 營收（年度） | D44: $B | E44: 1 | F44: OK | G44: v19.0 | H44: 1916a06 | I44: 2026-10-22 | J44: 13.07
A45: SRC_DEM_008 | B45: TK_SRC_DEM_008 | C45: OpenAI 算力規模 2024 年底（GW 口徑未明（D1）） | D45: GW | E45: 1 | F45: OK | G45: v19.0 | H45: 1916a06 | I45: 2026-10-22 | J45: 0.6
A46: SRC_DEM_009 | B46: TK_SRC_DEM_009 | C46: OpenAI 算力規模 2025 年底（約值；口徑未明） | D46: GW | E46: 1 | F46: OK | G46: v19.0 | H46: 1916a06 | I46: 2026-10-22 | J46: 1.9
A47: SRC_DEM_010 | B47: TK_SRC_DEM_010 | C47: OpenAI API 處理量（時點值；API 全部） | D47: B tok/min | E47: 1 | F47: OK | G47: v19.0 | H47: 1916a06 | I47: 2026-10-22 | J47: 6
A48: SRC_DEM_011 | B48: TK_SRC_DEM_011 | C48: OpenAI API 處理量（時點值；「超過」；API 全部） | D48: B tok/min | E48: 1 | F48: OK | G48: v19.0 | H48: 1916a06 | I48: 2026-10-22 | J48: 15
A49: SRC_DEM_012 | B49: TK_SRC_DEM_012 | C49: ChatGPT 每日提示數（全球；其中美國約 0.33B） | D49: B 則/日 | E49: 1 | F49: OK | G49: v19.0 | H49: 1916a06 | I49: 2026-10-22 | J49: 2.5
A50: SRC_DEM_013 | B50: TK_SRC_DEM_013 | C50: 前沿實驗室（OpenAI）每日 token（由算力推估） | D50: T tok/日 | E50: 1 | F50: OK | G50: v19.0 | H50: 1916a06 | I50: 2026-10-22
A51: SRC_DEM_013_Lo | B51: TK_SRC_DEM_013_Lo | C51: 前沿實驗室（OpenAI）每日 token（由算力推估） | D51: T tok/日 | E51: 1 | F51: OK | G51: v19.0 | H51: 1916a06 | I51: 2026-10-22 | J51: 10
A52: SRC_DEM_013_Hi | B52: TK_SRC_DEM_013_Hi | C52: 前沿實驗室（OpenAI）每日 token（由算力推估） | D52: T tok/日 | E52: 1 | F52: OK | G52: v19.0 | H52: 1916a06 | I52: 2026-10-22 | J52: 100
A53: IF_AllocQ1 | B53: TK_IF_AllocQ1 | C53: 研發算力占比 Q1（R1：研發 GW ÷ 研發＋服務 GW；服務 GW＝支出路線，v8.0 D14 主口徑） | D53: % | E53: 1 | F53: OK | G53: v19.0 | H53: 1916a06 | I53: 2026-10-22 | J53: 0.18434736
A54: IF_AllocQ1_R2 | B54: TK_IF_AllocQ1_R2 | C54: 研發算力占比 Q1（R2：免費服務算作產品改良；服務 GW＝支出路線，免費服務 GW＝服務 GW × AL_FreeSpendShare；v9.0 M6） | D54: % | E54: 1 | F54: OK | G54: v19.0 | H54: 1916a06 | I54: 2026-10-22 | J54: 0.56304323
A55: IF_AllocQ2 | B55: TK_IF_AllocQ2 | C55: 研發算力成本占比 Q2（研發 GW × 持有成本 ÷（＋服務持有成本＝SRC_DEM_004，支出路線，v8.0 D14）；利用率不進入） | D55: % | E55: 1 | F55: OK | G55: v19.0 | H55: 1916a06 | I55: 2026-10-22 | J55: 0.1850086
A56: IF_AllocServeGW | B56: TK_IF_AllocServeGW | C56: 服務 GW 合計（支出路線＝SRC_DEM_004 ÷ Σ 世代占比 × 持有成本；v8.0 D14 主口徑；IT 關鍵電力） | D56: GW | E56: 1 | F56: OK | G56: v19.0 | H56: 1916a06 | I56: 2026-10-22 | J56: 0.89809617
A57: IF_AllocRDGW | B57: TK_IF_AllocRDGW | C57: 研發 GW 年（k ×（N_major × 家族＋N_refresh × 改版）；v8.0 L3：2025 研發世代組合加權，Alloc J 節） | D57: GW·年 | E57: 1 | F57: OK | G57: v19.0 | H57: 1916a06 | I57: 2026-10-22 | J57: 0.20298059
A58: IF_AllocDemand | B58: TK_IF_AllocDemand | C58: 需求 D 合計（API＋ChatGPT；付費＋免費 token；2025） | D58: M tok/年 | E58: 1 | F58: OK | G58: v19.0 | H58: 1916a06 | I58: 2026-10-22 | J58: 6015200000
A59: IF_AllocImpliedNk | B59: TK_IF_AllocImpliedNk | C59: 隱含 N × k（2025 支出比反推；以家族計畫當量；A3） [IF_AllocImpliedNk] ｜v10.0 N2（D4）：性質＝倒推（隱含 N × k／J8 落差由 2025 支出反推研發 GW，再除以計畫當量；不是觀測值） | D59: 個 | E59: 1 | F59: OK | G59: v19.0 | H59: 1916a06 | I59: 2026-10-22 | J59: 11.358895
A60: IF_TrainCost_Astra | B60: TK_IF_TrainCost_Astra | C60: 最終訓練成本 — 經濟（依成本情境） [IF_TrainCost_Astra]｜v15.0 O12 口徑：機隊占比取 2025 OpenAI 推論 ÷（推論＋訓練）支出比（B4_Serve×(1−B4_Free)，全部世代同值，Assumed）；訓練成本以 100% 利用率計、服務以 ÷IF_Util 計；縮放倍數與隱含家族計畫數為 Assumed，接受為決策（Decisions SL46-16） | D60: $M | E60: 15 | F60: OK | G60: v19.0 | H60: 1916a06 | I60: 2026-10-22 | J60: 133.14593 | K60: 190.2389 | L60: 326.71016 | M60: 47.799737 | N60: 63.822704 | O60: 103.51529 | P60: 69.102652 | Q60: 89.250074 | R60: 151.9526 | S60: 47.581601 | T60: 61.154623 | U60: 98.797187 | V60: 34.412316 | W60: 52.302002 | X60: 95.479474
A61: IF_TrainCost_Luna | B61: TK_IF_TrainCost_Luna | C61: 最終訓練成本 — 經濟（依成本情境） [IF_TrainCost_Luna]｜v15.0 O12 口徑：機隊占比取 2025 OpenAI 推論 ÷（推論＋訓練）支出比（B4_Serve×(1−B4_Free)，全部世代同值，Assumed）；訓練成本以 100% 利用率計、服務以 ÷IF_Util 計；縮放倍數與隱含家族計畫數為 Assumed，接受為決策（Decisions SL46-16） | D61: $M | E61: 15 | F61: OK | G61: v19.0 | H61: 1916a06 | I61: 2026-10-22 | J61: 7.8728453 | K61: 11.248721 | L61: 19.318192 | M61: 2.2848461 | N61: 3.0507501 | O61: 4.9480714 | P61: 3.5074393 | Q61: 4.5300608 | R61: 7.7126494 | S61: 2.6209811 | T61: 3.3686364 | U61: 5.4421363 | V61: 1.8063963 | W61: 2.7454746 | X61: 5.0119778
A62: IF_TrainCost_Sol | B62: TK_IF_TrainCost_Sol | C62: 最終訓練成本 — 經濟（依成本情境） [IF_TrainCost_Sol]｜v15.0 O12 口徑：機隊占比取 2025 OpenAI 推論 ÷（推論＋訓練）支出比（B4_Serve×(1−B4_Free)，全部世代同值，Assumed）；訓練成本以 100% 利用率計、服務以 ÷IF_Util 計；縮放倍數與隱含家族計畫數為 Assumed，接受為決策（Decisions SL46-16） | D62: $M | E62: 15 | F62: OK | G62: v19.0 | H62: 1916a06 | I62: 2026-10-22 | J62: 21.865014 | K62: 31.240731 | L62: 53.651825 | M62: 7.3372607 | N62: 9.7967864 | O62: 15.8896 | P62: 10.775615 | Q62: 13.91733 | R62: 23.694933 | S62: 7.6347746 | T62: 9.8126536 | U62: 15.852646 | V62: 5.4420963 | W62: 8.2712402 | X62: 15.099492
A63: IF_RevGW_Astra | B63: TK_IF_RevGW_Astra | C63: 每 GW 理論營收 — OpenAI 有效單價（理想上限） | D63: $B/年 | E63: 15 | F63: OK | G63: v19.0 | H63: 1916a06 | I63: 2026-10-22 | J63: 32.828583 | K63: 32.828583 | L63: 32.828583 | M63: 162.35735 | N63: 162.35735 | O63: 162.35735 | P63: 189.27508 | Q63: 189.27508 | R63: 189.27508 | S63: 335.68627 | T63: 335.68627 | U63: 335.68627 | V63: 475.00532 | W63: 475.00532 | X63: 475.00532
A64: IF_RevGW_Luna | B64: TK_IF_RevGW_Luna | C64: 每 GW 理論營收 — OpenAI 有效單價（理想上限） | D64: $B/年 | E64: 15 | F64: OK | G64: v19.0 | H64: 1916a06 | I64: 2026-10-22 | J64: 5.4108976 | K64: 5.4108976 | L64: 5.4108976 | M64: 26.895273 | N64: 26.895273 | O64: 26.895273 | P64: 34.866728 | Q64: 34.866728 | R64: 34.866728 | S64: 50.299414 | T64: 50.299414 | U64: 50.299414 | V64: 67.719869 | W64: 67.719869 | X64: 67.719869
A65: IF_RevGW_Sol | B65: TK_IF_RevGW_Sol | C65: 每 GW 理論營收 — OpenAI 有效單價（理想上限） | D65: $B/年 | E65: 15 | F65: OK | G65: v19.0 | H65: 1916a06 | I65: 2026-10-22 | J65: 32.433029 | K65: 32.433029 | L65: 32.433029 | M65: 157.86574 | N65: 157.86574 | O65: 157.86574 | P65: 204.74691 | Q65: 204.74691 | R65: 204.74691 | S65: 307.5865 | T65: 307.5865 | U65: 307.5865 | V65: 418.85859 | W65: 418.85859 | X65: 418.85859
A66: IF_FullCostDefault_Astra | B66: TK_IF_FullCostDefault_Astra | C66: 全成本 $/M（服務＋快取儲存＋K6 預設攤提；基準利用率；下游預設） [IF_FullCostDefault_Astra]｜v15.0 O12 口徑：機隊占比取 2025 OpenAI 推論 ÷（推論＋訓練）支出比（B4_Serve×(1−B4_Free)，全部世代同值，Assumed）；訓練成本以 100% 利用率計、服務以 ÷IF_Util 計；縮放倍數與隱含家族計畫數為 Assumed，接受為決策（Decisions SL46-16） | D66: $/M | E66: 15 | F66: OK | G66: v19.0 | H66: 1916a06 | I66: 2026-10-22 | J66: 8.3759713 | K66: 11.967214 | L66: 20.551484 | M66: 1.676047 | N66: 2.2375798 | O66: 3.6286264 | P66: 1.7628457 | Q66: 2.2765557 | R66: 3.8753169 | S66: 1.1877619 | T66: 1.5263351 | U66: 2.4653127 | V66: 0.90918461 | W66: 1.3813921 | X66: 2.5210836
A67: IF_FullCostDefault_Luna | B67: TK_IF_FullCostDefault_Luna | C67: 全成本 $/M（服務＋快取儲存＋K6 預設攤提；基準利用率；下游預設） [IF_FullCostDefault_Luna]｜v15.0 O12 口徑：機隊占比取 2025 OpenAI 推論 ÷（推論＋訓練）支出比（B4_Serve×(1−B4_Free)，全部世代同值，Assumed）；訓練成本以 100% 利用率計、服務以 ÷IF_Util 計；縮放倍數與隱含家族計畫數為 Assumed，接受為決策（Decisions SL46-16） | D67: $/M | E67: 15 | F67: OK | G67: v19.0 | H67: 1916a06 | I67: 2026-10-22 | J67: 0.21251361 | K67: 0.30363017 | L67: 0.52142919 | M67: 0.037902157 | N67: 0.050600756 | O67: 0.082058118 | P67: 0.03949907 | Q67: 0.051009372 | R67: 0.086831575 | S67: 0.030093029 | T67: 0.038671399 | U67: 0.062462111 | V67: 0.022920841 | W67: 0.034826064 | X67: 0.063559796
A68: IF_FullCostDefault_Sol | B68: TK_IF_FullCostDefault_Sol | C68: 全成本 $/M（服務＋快取儲存＋K6 預設攤提；基準利用率；下游預設） [IF_FullCostDefault_Sol]｜v15.0 O12 口徑：機隊占比取 2025 OpenAI 推論 ÷（推論＋訓練）支出比（B4_Serve×(1−B4_Free)，全部世代同值，Assumed）；訓練成本以 100% 利用率計、服務以 ÷IF_Util 計；縮放倍數與隱含家族計畫數為 Assumed，接受為決策（Decisions SL46-16） | D68: $/M | E68: 15 | F68: OK | G68: v19.0 | H68: 1916a06 | I68: 2026-10-22 | J68: 0.61214752 | K68: 0.87461837 | L68: 1.5020113 | M68: 0.11908317 | N68: 0.15898747 | O68: 0.25783963 | P68: 0.12094767 | Q68: 0.15619878 | R68: 0.26590678 | S68: 0.088232214 | T68: 0.11338948 | U68: 0.18315906 | V68: 0.067980133 | W68: 0.10329953 | X68: 0.18854431
A69: L1_Ans3 | B69: TK_L1_Ans3 | C69: 問 3：研發占整體成本 Q3（算力部分）（基準） | D69: $B/年 | E69: 1 | F69: OK | G69: v19.0 | H69: 1916a06 | I69: 2026-10-22 | J69: 1.9068572
A70: L1_Ans3_Lo | B70: TK_L1_Ans3_Lo | C70: 問 3：研發占整體成本 Q3（算力部分）（低） | D70: $B/年 | E70: 1 | F70: OK | G70: v19.0 | H70: 1916a06 | I70: 2026-10-22 | J70: 0.95342861
A71: L1_Ans3_Hi | B71: TK_L1_Ans3_Hi | C71: 問 3：研發占整體成本 Q3（算力部分）（高） | D71: $B/年 | E71: 1 | F71: OK | G71: v19.0 | H71: 1916a06 | I71: 2026-10-22 | J71: 13.348001
A72: IF_CapexTotal | B72: TK_IF_CapexTotal | C72: 每 GW 資本支出 — 合計 | D72: $B | E72: 15 | F72: OK | G72: v19.0 | H72: 1916a06 | I72: 2026-10-22 | J72: 31.632269 | K72: 40.180214 | L72: 50.306743 | M72: 30.85139 | N72: 36.685174 | O72: 43.836204 | P72: 38.766902 | Q72: 44.907224 | R72: 55.468606 | S72: 43.485403 | T72: 50.256352 | U72: 58.823575 | V72: 46.057578 | W72: 62.75578 | X72: 81.667558
A73: IF_CostCache_Astra | B73: TK_IF_CostCache_Astra | C73: 快取命中 prefill $/M（經濟、100%） | D73: $/M | E73: 15 | F73: OK | G73: v19.0 | H73: 1916a06 | I73: 2026-10-22 | J73: 0.00017274318 | K73: 0.00024681545 | L73: 0.0004238729 | M73: 0.0002406765 | N73: 0.00032135376 | O73: 0.00052120996 | P73: 0.00031611903 | Q73: 0.00040828602 | R73: 0.00069512685 | S73: 0.00059551033 | T73: 0.00076538429 | U73: 0.001236502 | V73: 0.00094742947 | W73: 0.0014399629 | X73: 0.002628712
A74: IF_CostCache_Luna | B74: TK_IF_CostCache_Luna | C74: 快取命中 prefill $/M（經濟、100%） | D74: $/M | E74: 15 | F74: OK | G74: v19.0 | H74: 1916a06 | I74: 2026-10-22 | J74: 8.3822427e-06 | K74: 1.1976548e-05 | L74: 2.0568138e-05 | M74: 1.167866e-05 | N74: 1.5593468e-05 | O74: 2.5291352e-05 | P74: 1.5339456e-05 | Q74: 1.9811795e-05 | R74: 3.3730548e-05 | S74: 2.8896725e-05 | T74: 3.7139741e-05 | U74: 6.0000402e-05 | V74: 4.5973357e-05 | W74: 6.9873199e-05 | X74: 0.00012755642
A75: IF_CostCache_Sol | B75: TK_IF_CostCache_Sol | C75: 快取命中 prefill $/M（經濟、100%） | D75: $/M | E75: 15 | F75: OK | G75: v19.0 | H75: 1916a06 | I75: 2026-10-22 | J75: 1.1891089e-05 | K75: 1.6989987e-05 | L75: 2.9178057e-05 | M75: 1.6567402e-05 | N75: 2.2120966e-05 | O75: 3.5878429e-05 | P75: 2.1760624e-05 | Q75: 2.8105105e-05 | R75: 4.7850312e-05 | S75: 4.0993029e-05 | T75: 5.2686609e-05 | U75: 8.5116849e-05 | V75: 6.5218018e-05 | W75: 9.9122446e-05 | X75: 0.00018095214
A76: IF_CostDec_Astra | B76: TK_IF_CostDec_Astra | C76: decode（含思考 token）$/M（經濟、100%） | D76: $/M | E76: 15 | F76: OK | G76: v19.0 | H76: 1916a06 | I76: 2026-10-22 | J76: 7.3732507 | K76: 10.5349 | L76: 18.092299 | M76: 1.5462031 | N76: 2.0645064 | O76: 3.3484634 | P76: 1.738939 | Q76: 2.2459403 | R76: 3.8238229 | S76: 1.0734098 | T76: 1.3796083 | U76: 2.2287999 | V76: 0.79865531 | W76: 1.2138466 | X76: 2.2159272
A77: IF_CostDec_Luna | B77: TK_IF_CostDec_Luna | C77: decode（含思考 token）$/M（經濟、100%） | D77: $/M | E77: 15 | F77: OK | G77: v19.0 | H77: 1916a06 | I77: 2026-10-22 | J77: 0.40538005 | K77: 0.579207 | L77: 0.99471146 | M77: 0.087489162 | N77: 0.11681644 | O77: 0.18946687 | P77: 0.088100381 | Q77: 0.11378674 | R77: 0.19372747 | S77: 0.068496248 | T77: 0.088035336 | U77: 0.14222381 | V77: 0.053944555 | W77: 0.081988327 | X77: 0.14967309
A78: IF_CostDec_Sol | B78: TK_IF_CostDec_Sol | C78: decode（含思考 token）$/M（經濟、100%） | D78: $/M | E78: 15 | F78: OK | G78: v19.0 | H78: 1916a06 | I78: 2026-10-22 | J78: 1.3339407 | K78: 1.9059345 | L78: 3.2731906 | M78: 0.29689026 | N78: 0.39641095 | O78: 0.64294669 | P78: 0.2989644 | Q78: 0.38612982 | R78: 0.65740484 | S78: 0.22130773 | T78: 0.28443748 | U78: 0.45951756 | V78: 0.17187256 | W78: 0.26122272 | X78: 0.47687291
A79: IF_CostPre_Astra | B79: TK_IF_CostPre_Astra | C79: 新鮮 prefill $/M（經濟、100%） | D79: $/M | E79: 15 | F79: OK | G79: v19.0 | H79: 1916a06 | I79: 2026-10-22 | J79: 0.4452839 | K79: 0.63622162 | L79: 1.0926265 | M79: 0.061357276 | N79: 0.081924871 | O79: 0.13287555 | P79: 0.053726897 | Q79: 0.069391396 | R79: 0.11814224 | S79: 0.043376413 | T79: 0.055749872 | U79: 0.090065645 | V79: 0.034504936 | W79: 0.052442772 | X79: 0.095736455
A80: IF_CostPre_Luna | B80: TK_IF_CostPre_Luna | C80: 新鮮 prefill $/M（經濟、100%） | D80: $/M | E80: 15 | F80: OK | G80: v19.0 | H80: 1916a06 | I80: 2026-10-22 | J80: 0.038672634 | K80: 0.055255459 | L80: 0.094893946 | M80: 0.0053288419 | N80: 0.0071151249 | O80: 0.011540161 | P80: 0.0046661481 | Q80: 0.0060266003 | R80: 0.010260581 | S80: 0.0037672149 | T80: 0.0048418423 | U80: 0.0078221462 | V80: 0.0029967326 | W80: 0.0045546227 | X80: 0.0083146526
A81: IF_CostPre_Sol | B81: TK_IF_CostPre_Sol | C81: 新鮮 prefill $/M（經濟、100%） | D81: $/M | E81: 15 | F81: OK | G81: v19.0 | H81: 1916a06 | I81: 2026-10-22 | J81: 0.13422466 | K81: 0.19178019 | L81: 0.32935712 | M81: 0.0184953 | N81: 0.024695116 | O81: 0.040053493 | P81: 0.016195228 | Q81: 0.020917074 | R81: 0.035612339 | S81: 0.013075218 | T81: 0.016805026 | U81: 0.02714904 | V81: 0.010401035 | W81: 0.015808146 | X81: 0.028858427
A82: IF_OpexGW | B82: TK_IF_OpexGW | C82: 每 GW 營運費用小計（不含折舊；含電費） | D82: $B/年 | E82: 15 | F82: OK | G82: v19.0 | H82: 1916a06 | I82: 2026-10-22 | J82: 1.1122255 | K82: 1.8846675 | L82: 2.8646514 | M82: 1.1018833 | N82: 1.8122327 | O82: 2.6948141 | P82: 1.2067191 | Q82: 1.9826348 | R82: 3.0001387 | S82: 1.2692126 | T82: 2.0934955 | U82: 3.0881992 | V82: 1.3032794 | W82: 2.3525463 | X82: 3.6878027
A83: IF_DeprLifeIT | B83: TK_IF_DeprLifeIT | C83: IT 折舊年限 | D83: 年 | E83: 15 | F83: OK | G83: v19.0 | H83: 1916a06 | I83: 2026-10-22 | J83: 6 | K83: 6 | L83: 4 | M83: 6 | N83: 6 | O83: 4 | P83: 6 | Q83: 6 | R83: 4 | S83: 6 | T83: 6 | U83: 4 | V83: 6 | W83: 6 | X83: 4
A84: RNG_IF_AllocRDGW_Lo | B84: TK_RNG_IF_AllocRDGW_Lo | C84: IF_AllocRDGW 下限 Lo | D84: GW·年 | E84: 1 | F84: OK | G84: v19.0 | H84: 1916a06 | I84: 2026-10-22 | J84: 0.16263889
A85: RNG_IF_AllocRDGW_Hi | B85: TK_RNG_IF_AllocRDGW_Hi | C85: IF_AllocRDGW 上限 Hi | D85: GW·年 | E85: 1 | F85: OK | G85: v19.0 | H85: 1916a06 | I85: 2026-10-22 | J85: 0.21162762
A86: RNG_StaleFlag | B86: TK_RNG_StaleFlag | C86: 區間時效旗標 | D86: 文字 | E86: 1 | F86: OK | G86: v19.0 | H86: 1916a06 | I86: 2026-10-22 | J86: 一致
A87: （讀表）Cap_In!54 | B87: TK_RD_CapIn_GLM53 | C87: Cap_In F 表 GLM-5.3：新鮮輸入、快取輸入、輸出（國際站 $/M）、尖峰離峰、能力指數（Cap_In!E54，標籤『GLM-5.3』） | D87: $/M；指數 | E87: 5 | F87: 讀表（非具名） | G87: v19.0 | H87: 1916a06 | I87: 2026-10-22 | J87: 1.4 | K87: 0.26 | L87: 4.4 | M87: 0 | N87: 45
A88: （讀表）Cap_In!55 | B88: TK_RD_CapIn_GLM53Flash | C88: Cap_In F 表 GLM-5.3-Flash：同上（Cap_In!E55，標籤『GLM-5.3-Flash』） | D88: $/M；指數 | E88: 5 | F88: 讀表（非具名） | G88: v19.0 | H88: 1916a06 | I88: 2026-10-22 | J88: 0.15 | K88: 0.03 | L88: 0.5 | M88: 0 | N88: 42
A89: （讀表）Price_Frontier!14 | B89: TK_RD_PF_GLM53_Mix | C89: Price_Frontier A 表 GLM-5.3：參考請求混合單價（Luna、Sol、Astra 參考請求）（Price_Frontier!H14，標籤『GLM-5.3』） | D89: $/M | E89: 3 | F89: 讀表（非具名） | G89: v19.0 | H89: 1916a06 | I89: 2026-10-22 | J89: 1.176 | K89: 1.176 | L89: 1.176
A90: （讀表）Price_Frontier!15 | B90: TK_RD_PF_GLM53Flash_Mix | C90: Price_Frontier A 表 GLM-5.3-Flash：同上（Price_Frontier!H15，標籤『GLM-5.3-Flash』） | D90: $/M | E90: 3 | F90: 讀表（非具名） | G90: v19.0 | H90: 1916a06 | I90: 2026-10-22 | J90: 0.13022222 | K90: 0.13022222 | L90: 0.13022222
A91: （讀表）Price_Frontier!31 | B91: TK_RD_PF_ChinaFront | C91: Price_Frontier B 表：中國合格前緣混合單價（Luna、Sol、Astra；無合格者為文字）（Price_Frontier!C31，標籤『中國廠商 合格者最低 混合單價』） | D91: $/M | E91: 3 | F91: 讀表（非具名） | G91: v19.0 | H91: 1916a06 | I91: 2026-10-22 | J91: 0.13022222 | K91: 無合格 | L91: 無合格
A92: （讀表）Price_Frontier!32 | B92: TK_RD_PF_ChinaFrontModel | C92: Price_Frontier B 表：中國合格前緣模型名（Luna、Sol、Astra）（Price_Frontier!C32，標籤『中國廠商 合格者最低 模型』） | D92: 文字 | E92: 3 | F92: 讀表（非具名） | G92: v19.0 | H92: 1916a06 | I92: 2026-10-22 | J92: GLM-5.3-Flash | K92: — | L92: —
A93: （讀表）Price_Frontier!33 | B93: TK_RD_PF_ChinaVsOAI | C93: Price_Frontier B 表：中國合格前緣 ÷ OpenAI 層級模型（Luna、Sol、Astra）（Price_Frontier!C33，標籤『中國合格者最低 ÷ OpenAI 層級模型』） | D93: x | E93: 3 | F93: 讀表（非具名） | G93: v19.0 | H93: 1916a06 | I93: 2026-10-22 | J93: 1.2964602 | K93: — | L93: —

Sheet OAI_Link
A1: OAI_Link — OpenAI 命題輸出快照（版本見檔名列）（美元；只被 Checks 與 HTML 引用，規格 D26）
A2: 值（藍字）由 builder 從 OpenAI Excel（main 上 openai/model/CURRENT）的具名範圍讀出（LibreOffice 重算後快取值）。本頁不參與任何計算；test_builder 掃描其他頁公式不得含 OAI_。
A3: OpenAI Excel 檔案 | B3: 20261022_OpenAI_v0.6.2.xlsx
A4: SHA-256 | B4: 7f023c084f2f6f3f0bf2ffba23015a36d2206509e66bcd422223f40b614cf9f3
A5: 來源分支與提交 | B5: main@f645e19
A6: 讀取日期 | B6: 2026-10-22
A9: OpenAI 名稱 | B9: 本模型名稱 | C9: 說明 | D9: 單位 | E9: 狀態 | F9: 2025 | G9: 2026 | H9: 2027 | I9: 2028 | J9: 2029 | K9: 2030
A10: REV_Gross | B10: OAI_REV_Gross | C10: 營收總額（未截頂） | D10: $B | E10: OK | F10: 13.07 | G10: 34.203781 | H10: 54.795653 | I10: 78.424089 | J10: 102.12737 | K10: 126.38309
A11: REV_NetCapped | B11: OAI_REV_NetCapped | C11: 營收淨額（容量截頂後） | D11: $B | E11: OK | F11: 10.456 | G11: 27.363025 | H11: 43.836523 | I11: 62.739271 | J11: 97.612079 | K11: 126.38309
A12: DEM_Tok_Total | B12: OAI_DEM_Tok_Total | C12: token 合計（付費＋免費） | D12: T | E12: OK | F12: 3538.0601 | G12: 10018.624 | H12: 22447.299 | I12: 47137.552 | J12: 92412.32 | K12: 173673.87
A13: CMP_InfGW_Eff | B13: OAI_CMP_InfGW_Eff | C13: 有效推論 GW | D13: GW | E13: OK | F13: 0.7 | G13: 0.75956479 | H13: 1.2055585 | I13: 2.1094912 | J13: 3.8245859 | K13: 6.8436388
A14: CMP_Supply_VReq | B14: OAI_CMP_Supply_VReq | C14: 供給 VR 等值 GW | D14: GW | E14: OK | F14: 0.33022495 | G14: 1.2501735 | H14: 5.9855062 | I14: 9.1175115 | J14: 12.270415 | K14: 14.984692
A15: COST_Compute | B15: OAI_COST_Compute | C15: 算力成本（現金） | D15: $B | E15: OK | F15: 14.755238 | G15: 53.240635 | H15: 141.72603 | I15: 175.21143 | J15: 208.69683 | K15: 228.22222
A16: COST_FullCash | B16: OAI_COST_FullCash | C16: 全成本（現金，含股權報酬） | D16: $B | E16: OK | F16: 29.235238 | G16: 76.078955 | H16: 171.94384 | I16: 212.1254 | J16: 251.9209 | K16: 276.64452
A17: COST_PropRev_VR | B17: OAI_COST_PropRev_VR | C17: 每 VR 等值 GW 營收淨額 | D17: $B/GW | E17: OK | F17: 31.663265 | G17: 21.887382 | H17: 7.3237786 | I17: 6.8811836 | J17: 7.9550756 | K17: 8.434147
A18: COST_PropFull_VR | B18: OAI_COST_PropFull_VR | C18: 每 VR 等值 GW 全成本 | D18: $B/GW | E18: OK | F18: 88.531282 | G18: 60.854717 | H18: 28.7267 | I18: 23.265713 | J18: 20.530756 | K18: 18.461809
A19: COST_PropGap_VR | B19: OAI_COST_PropGap_VR | C19: 每 VR 等值 GW 差額（命題 1） | D19: $B/GW | E19: OK | F19: -56.868017 | G19: -38.967335 | H19: -21.402921 | I19: -16.384529 | J19: -12.575681 | K19: -10.027662
A20: COST_Coverage | B20: OAI_COST_Coverage | C20: 覆蓋率（營收 ÷ 全成本） | D20: 比例 | E20: OK | F20: 0.35765058 | G20: 0.35966615 | H20: 0.25494674 | I20: 0.29576501 | J20: 0.38747114 | K20: 0.45684293
A21: FND_FCF | B21: OAI_FND_FCF | C21: 自由現金流 | D21: $B | E21: OK | F21: -12.779238 | G21: -39.41593 | H21: -116.01732 | I21: -134.87813 | J21: -137.62462 | K21: -131.90881
A22: FND_ExtNeed | B22: OAI_FND_ExtNeed | C22: 外部資金需求（單年） | D22: $B | E22: OK | G22: 0 | H22: 38.433249 | I22: 134.87813 | J22: 137.62462 | K22: 131.90881
A23: FND_ExtNeedCum | B23: OAI_FND_ExtNeedCum | C23: 累計外部資金需求（命題 2） | D23: $B | E23: OK | G23: 0 | H23: 38.433249 | I23: 173.31138 | J23: 310.936 | K23: 442.84481
A24: FND_CashEnd | B24: OAI_FND_CashEnd | C24: 年底現金 | D24: $B | E24: OK | F24: 40 | G24: 87.58407 | H24: 10 | I24: 10 | J24: 10 | K24: 10
A25: FND_Committed | B25: OAI_FND_Committed | C25: 已到位融資 | D25: $B | E25: OK | F25: 0 | G25: 87 | H25: 0 | I25: 0 | J25: 0 | K25: 0
A26: RVS_ExtNeedCum | B26: OAI_RVS_ExtNeedCum | C26: 反向累計外部資金需求（管理層目標） | D26: $B | E26: OK | G26: 0 | H26: 20.752797 | I26: 92.650199 | J26: 92.650199 | K26: 92.650199

Sheet Inputs
A1: Inputs — 假設輸入（藍字）：值、低、高、標記、依據、區間理由；匯率與單位換算定義常數（D23、E6）
A2: 長表格式：一列一個參數（× 索引）。來源 data/zhipu_inputs.yaml；INP_nnn 由 builder/id_registry.json 依鍵發出，穩定不重用。
A3: Analogy 寫明參照（如『OpenAI v0.6 INP_nnn』）與差異；Assumed 寫明依據；兩者一律給區間。Decision＝定義常數或規格決策（低＝值＝高）。
A4: INP_ID | B4: 鍵（key） | C4: 參數 | D4: 索引 | E4: 單位 | F4: 值 | G4: 低 | H4: 高 | I4: 標記 | J4: 依據 | K4: 區間理由 | L4: 區間順序異常（公式） | M4: Analogy／Assumed 缺區間（公式）
A5: INP_001 | B5: year_2025 | C5: 模型年度 | D5: 第 1 年 | E5: 年 | F5: 2025 | G5: 2025 | H5: 2025 | I5: Decision | J5: 曆年制，2025 為實際校準年（規格 D1、D14） | K5: 定義 | L5: =IF(AND(ISNUMBER($F5),ISNUMBER($G5),ISNUMBER($H5)),IF(AND($G5<=$F5,$F5<=$H5),0,1),0) -> 0 | M5: =IF(AND(OR($I5="Analogy",$I5="Assumed"),OR($G5="",$H5="")),1,0) -> 0
A6: INP_002 | B6: year_2026 | C6: 模型年度 | D6: 第 2 年 | E6: 年 | F6: 2026 | G6: 2026 | H6: 2026 | I6: Decision | J6: 2026＝1H26 實際＋2H26 驅動（D14） | K6: 定義 | L6: =IF(AND(ISNUMBER($F6),ISNUMBER($G6),ISNUMBER($H6)),IF(AND($G6<=$F6,$F6<=$H6),0,1),0) -> 0 | M6: =IF(AND(OR($I6="Analogy",$I6="Assumed"),OR($G6="",$H6="")),1,0) -> 0
A7: INP_003 | B7: year_2027 | C7: 模型年度 | D7: 第 3 年 | E7: 年 | F7: 2027 | G7: 2027 | H7: 2027 | I7: Decision | J7: 定義 | K7: 定義 | L7: =IF(AND(ISNUMBER($F7),ISNUMBER($G7),ISNUMBER($H7)),IF(AND($G7<=$F7,$F7<=$H7),0,1),0) -> 0 | M7: =IF(AND(OR($I7="Analogy",$I7="Assumed"),OR($G7="",$H7="")),1,0) -> 0
A8: INP_004 | B8: year_2028 | C8: 模型年度 | D8: 第 4 年 | E8: 年 | F8: 2028 | G8: 2028 | H8: 2028 | I8: Decision | J8: 定義 | K8: 定義 | L8: =IF(AND(ISNUMBER($F8),ISNUMBER($G8),ISNUMBER($H8)),IF(AND($G8<=$F8,$F8<=$H8),0,1),0) -> 0 | M8: =IF(AND(OR($I8="Analogy",$I8="Assumed"),OR($G8="",$H8="")),1,0) -> 0
A9: INP_005 | B9: year_2029 | C9: 模型年度 | D9: 第 5 年 | E9: 年 | F9: 2029 | G9: 2029 | H9: 2029 | I9: Decision | J9: 定義 | K9: 定義 | L9: =IF(AND(ISNUMBER($F9),ISNUMBER($G9),ISNUMBER($H9)),IF(AND($G9<=$F9,$F9<=$H9),0,1),0) -> 0 | M9: =IF(AND(OR($I9="Analogy",$I9="Assumed"),OR($G9="",$H9="")),1,0) -> 0
A10: INP_006 | B10: year_2030 | C10: 模型年度 | D10: 第 6 年 | E10: 年 | F10: 2030 | G10: 2030 | H10: 2030 | I10: Decision | J10: 定義 | K10: 定義 | L10: =IF(AND(ISNUMBER($F10),ISNUMBER($G10),ISNUMBER($H10)),IF(AND($G10<=$F10,$F10<=$H10),0,1),0) -> 0 | M10: =IF(AND(OR($I10="Analogy",$I10="Assumed"),OR($G10="",$H10="")),1,0) -> 0
A11: INP_007 | B11: days_year | C11: 每年天數（定義常數） | D11: — | E11: 天 | F11: 365 | G11: 365 | H11: 365 | I11: Decision | J11: 同 OpenAI v0.6 INP_251 | K11: 定義 | L11: =IF(AND(ISNUMBER($F11),ISNUMBER($G11),ISNUMBER($H11)),IF(AND($G11<=$F11,$F11<=$H11),0,1),0) -> 0 | M11: =IF(AND(OR($I11="Analogy",$I11="Assumed"),OR($G11="",$H11="")),1,0) -> 0
A12: INP_008 | B12: days_1h26 | C12: 2026 上半年天數（定義常數） | D12: 1H2026 | E12: 天 | F12: 181 | G12: 181 | H12: 181 | I12: Decision | J12: 2026-01-01～06-30 | K12: 定義 | L12: =IF(AND(ISNUMBER($F12),ISNUMBER($G12),ISNUMBER($H12)),IF(AND($G12<=$F12,$F12<=$H12),0,1),0) -> 0 | M12: =IF(AND(OR($I12="Analogy",$I12="Assumed"),OR($G12="",$H12="")),1,0) -> 0
A13: INP_009 | B13: days_2h26 | C13: 2026 下半年天數（定義常數） | D13: 2H2026 | E13: 天 | F13: 184 | G13: 184 | H13: 184 | I13: Decision | J13: 2026-07-01～12-31 | K13: 定義 | L13: =IF(AND(ISNUMBER($F13),ISNUMBER($G13),ISNUMBER($H13)),IF(AND($G13<=$F13,$F13<=$H13),0,1),0) -> 0 | M13: =IF(AND(OR($I13="Analogy",$I13="Assumed"),OR($G13="",$H13="")),1,0) -> 0
A14: INP_010 | B14: months_year | C14: 每年月數（定義常數） | D14: — | E14: 月 | F14: 12 | G14: 12 | H14: 12 | I14: Decision | J14: 同 OpenAI v0.6 INP_252 | K14: 定義 | L14: =IF(AND(ISNUMBER($F14),ISNUMBER($G14),ISNUMBER($H14)),IF(AND($G14<=$F14,$F14<=$H14),0,1),0) -> 0 | M14: =IF(AND(OR($I14="Analogy",$I14="Assumed"),OR($G14="",$H14="")),1,0) -> 0
A15: INP_011 | B15: months_half | C15: 每半年月數（定義常數） | D15: — | E15: 月 | F15: 6 | G15: 6 | H15: 6 | I15: Decision | J15: 定義 | K15: 定義 | L15: =IF(AND(ISNUMBER($F15),ISNUMBER($G15),ISNUMBER($H15)),IF(AND($G15<=$F15,$F15<=$H15),0,1),0) -> 0 | M15: =IF(AND(OR($I15="Analogy",$I15="Assumed"),OR($G15="",$H15="")),1,0) -> 0
A16: INP_012 | B16: months_qtr | C16: 每季月數（定義常數） | D16: — | E16: 月 | F16: 3 | G16: 3 | H16: 3 | I16: Decision | J16: 國際站 Coding Plan 季付價換算每月 | K16: 定義 | L16: =IF(AND(ISNUMBER($F16),ISNUMBER($G16),ISNUMBER($H16)),IF(AND($G16<=$F16,$F16<=$H16),0,1),0) -> 0 | M16: =IF(AND(OR($I16="Analogy",$I16="Assumed"),OR($G16="",$H16="")),1,0) -> 0
... A144: INP_141 | B144: seg_recon_tol | C144: 分部對帳容差（官方分部 vs 模型／子項加總；絕對差 ≤ 本值為 OK） | D144: 全期 | E144: RMB 億 | F144: 0.001 | G144: 0.001 | H144: 0.001 | I144: Decision | J144: 工作單 v0.1.2：財報以千元四捨五入至億元四位小數，年報本地化部署 5.3396 與四捨五入後子項 5.3395 差 0.0001；容差 0.001 為定義常數（Decision，低＝高＝值） | K144: 定義 | L144: =IF(AND(ISNUMBER($F144),ISNUMBER($G144),ISNUMBER($H144)),IF(AND($G144<=$F144,$F144<=$H144),0,1),0) -> 0 | M144: =IF(AND(OR($I144="Analogy",$I144="Assumed"),OR($G144="",$H144="")),1,0) -> 0

Sheet Demand
A1: Demand — 需求：API 按量計費 token、GLM Coding Plan 訂閱者與 token、智譜清言（免費）token；輸出 DEM_Tok_*（層級 Sol／Luna × 付費／免費）
A2: 2025 與 1H26 為校準期：API 按量計費 token＝（開放平台及 API 實際營收 − Coding Plan 估計營收）÷ 組合有效單價（規格 D14；單價為驅動、token 為倒推）。2H26 起：任務數 ×（1＋成長）× 每任務 token ×（1＋成長）× 價格反應 (p/p前)^ε（D15）。本地化部署不耗智譜算力，不進本頁（D4）。
A3: token 單位 T＝10^12；Coding Plan 訂閱者單位萬人；清言用戶百萬人；任務數十億。容量上限於 Z3 接 Compute；本頁不截頂。
A5: 編號 | B5: 項目 | C5: 單位 | D5: 2025 | E5: 2026 | F5: 2027 | G5: 2028 | H5: 2029 | I5: 2030 | K5: 1H2026 | L5: 2H2026 | M5: 說明
B6: 年度 | D6: =INP_001 -> 2025 | E6: =INP_002 -> 2026 | F6: =INP_003 -> 2027 | G6: =INP_004 -> 2028 | H6: =INP_005 -> 2029 | I6: =INP_006 -> 2030 | K6: 1H2026（實際） | L6: 2H2026（驅動）
A7: 一、API 按量計費（開放平台及 API 扣除 Coding Plan）
A8: D01 | B8: 價格反應底數 p/p前（組合有效單價） | C8: 倍 | F8: =Revenue!F24/Revenue!L24 -> 0.8 | G8: =Revenue!G24/Revenue!F24 -> 0.8 | H8: =Revenue!H24/Revenue!G24 -> 0.8 | I8: =Revenue!I24/Revenue!H24 -> 0.8 | L8: =Revenue!L24/Revenue!K24 -> 1.2696313 | M8: 2H26＝2H26 ÷ 1H26；2027＝2027 ÷ 2H26（最新價格水準）；之後逐年
A9: D02 | B9: API 每任務 token | C9: K tok／任務 | D9: =INP_037 -> 20 | E9: =E11/E10 -> 20.351341 | F9: =E9*(1+INP_044)*F8^INP_046 -> 25.024411 | G9: =F9*(1+INP_044)*G8^INP_046 -> 30.770511 | H9: =G9*(1+INP_044)*H8^INP_046 -> 37.83603 | I9: =H9*(1+INP_044)*I8^INP_046 -> 46.523931 | K9: =INP_037 -> 20 | L9: =K9*(1+INP_039)*L8^INP_046 -> 20.479502 | M9: 校準期＝Inputs 基準（只影響任務數與每任務 token 的水準拆分，不影響營收）；2H26 起 ×（1＋成長）× 價格反應^ε（每任務 token）；2026 欄＝全年 token ÷ 全年任務
A10: D03 | B10: API 任務數 | C10: 十億 | D10: =D11/D9 -> 3.3230757 | E10: =K10+L10 -> 34.137346 | F10: =E10*(1+INP_040)*F8^INP_045 -> 71.835524 | G10: =F10*(1+INP_041)*G8^INP_045 -> 125.97012 | H10: =G10*(1+INP_042)*H8^INP_045 -> 198.81004 | I10: =H10*(1+INP_043)*I8^INP_045 -> 290.52622 | K10: =K11/K9 -> 9.1242437 | L10: =K10*(1+INP_038)*L8^INP_045 -> 25.013102 | M10: 校準期＝token ÷ 每任務 token；2H26＝1H26 ×（1＋半年成長）× 價格反應^ε；2027 起以 2026 全年為基期
A11: D04 | B11: API 按量計費 token | C11: T | D11: =Revenue!D44*INP_015/Revenue!D24 -> 66.461514 | E11: =K11+L11 -> 694.74076 | F11: =F10*F9 -> 1797.6417 | G11: =G10*G9 -> 3876.1649 | H11: =H10*H9 -> 7522.1826 | I11: =I10*I9 -> 13516.422 | K11: =Revenue!K44*INP_015/Revenue!K24 -> 182.48487 | L11: =L10*L9 -> 512.25588 | M11: 2025、1H26：按量計費營收（API 實際 − Coding Plan 估計）× 100 ÷ 組合有效單價（元／百萬 token；×100 為 Inputs 定義常數）；之後＝任務數 × 每任務 token
A12: D05 | B12: API 按量計費 token：Sol（GLM 旗艦） | C12: T | D12: =D11*Revenue!D22 -> 39.876908 | E12: =K12+L12 -> 486.31853 | F12: =F11*Revenue!F22 -> 1258.3492 | G12: =G11*Revenue!G22 -> 2713.3154 | H12: =H11*Revenue!H22 -> 5265.5278 | I12: =I11*Revenue!I22 -> 9461.4953 | K12: =K11*Revenue!K22 -> 127.73941 | L12: =L11*Revenue!L22 -> 358.57912 | M12: token × 層級組合（Revenue）
A13: D06 | B13: API 按量計費 token：Luna（Air／Flash） | C13: T | D13: =D11*Revenue!D23 -> 26.584606 | E13: =K13+L13 -> 208.42223 | F13: =F11*Revenue!F23 -> 539.29251 | G13: =G11*Revenue!G23 -> 1162.8495 | H13: =H11*Revenue!H23 -> 2256.6548 | I13: =I11*Revenue!I23 -> 4054.9265 | K13: =K11*Revenue!K23 -> 54.745462 | L13: =L11*Revenue!L23 -> 153.67676 | M13: token × 層級組合（Revenue）
A14: D07 | B14: 免費 API 型號 token（Luna；耗算力無營收） | C14: T | D14: =D11*INP_047 -> 19.938454 | E14: =K14+L14 -> 208.42223 | F14: =F11*INP_047 -> 539.29251 | G14: =G11*INP_047 -> 1162.8495 | H14: =H11*INP_047 -> 2256.6548 | I14: =I11*INP_047 -> 4054.9265 | K14: =K11*INP_047 -> 54.745462 | L14: =L11*INP_047 -> 153.67676 | M14: GLM-4.7-Flash 等免費型號（SRC_ZP_333）＝付費 API token × Inputs 比例（D24r：免費型號單列）
A15: 二、GLM Coding Plan（訂閱者 × 每訂閱者 token；收入在開放平台及 API 內，D2r）
A16: D08 | B16: Coding Plan 付費訂閱者（期間平均） | C16: 萬人 | D16: =SRC_ZP_402*INP_049 -> 3.63 | E16: =(K16+L16)/INP_013 -> 30.25 | F16: =E16*(1+INP_051) -> 45.375 | G16: =F16*(1+INP_052) -> 58.9875 | H16: =G16*(1+INP_053) -> 70.785 | I16: =H16*(1+INP_054) -> 81.40275 | K16: =SRC_ZP_402*INP_048 -> 24.2 | L16: =K16*(1+INP_050) -> 36.3 | M16: 2025、1H26＝2026-03 付費開發者 24.2 萬（SRC_ZP_402）× Inputs 倍數（營收未單列，無法倒推；工作單：給區間）；2H26＝1H26 ×（1＋半年成長）；2026 欄＝兩個半年平均；2027 起 ×（1＋年增率）
A17: D09 | B17: Coding Plan 訂閱者：Lite | C17: 萬人 | D17: =D16*Revenue!D35 -> 2.178 | E17: =E16*Revenue!E35 -> 18.15 | F17: =F16*Revenue!F35 -> 27.225 | G17: =G16*Revenue!G35 -> 35.3925 | H17: =H16*Revenue!H35 -> 42.471 | I17: =I16*Revenue!I35 -> 48.84165 | K17: =K16*Revenue!K35 -> 14.52 | L17: =L16*Revenue!L35 -> 21.78 | M17: 訂閱者 × 方案組合（Revenue）
A18: D10 | B18: Coding Plan 訂閱者：Pro | C18: 萬人 | D18: =D16*Revenue!D36 -> 1.089 | E18: =E16*Revenue!E36 -> 9.075 | F18: =F16*Revenue!F36 -> 13.6125 | G18: =G16*Revenue!G36 -> 17.69625 | H18: =H16*Revenue!H36 -> 21.2355 | I18: =I16*Revenue!I36 -> 24.420825 | K18: =K16*Revenue!K36 -> 7.26 | L18: =L16*Revenue!L36 -> 10.89 | M18: 訂閱者 × 方案組合（Revenue）
A19: D11 | B19: Coding Plan 訂閱者：Max | C19: 萬人 | D19: =D16*Revenue!D37 -> 0.363 | E19: =E16*Revenue!E37 -> 3.025 | F19: =F16*Revenue!F37 -> 4.5375 | G19: =G16*Revenue!G37 -> 5.89875 | H19: =H16*Revenue!H37 -> 7.0785 | I19: =I16*Revenue!I37 -> 8.140275 | K19: =K16*Revenue!K37 -> 2.42 | L19: =L16*Revenue!L37 -> 3.63 | M19: 訂閱者 × 方案組合（Revenue）
A20: D12 | B20: 每訂閱者每日 token：Lite | C20: M tok／日 | D20: =SRC_ZP_376*INP_022*INP_060*INP_061*INP_062/INP_019 -> 20.16 | E20: =SRC_ZP_376*INP_022*INP_060*INP_061*INP_062/INP_019 -> 20.16 | F20: =SRC_ZP_376*INP_022*INP_060*INP_061*INP_062/INP_019 -> 20.16 | G20: =SRC_ZP_376*INP_022*INP_060*INP_061*INP_062/INP_019 -> 20.16 | H20: =SRC_ZP_376*INP_022*INP_060*INP_061*INP_062/INP_019 -> 20.16 | I20: =SRC_ZP_376*INP_022*INP_060*INP_061*INP_062/INP_019 -> 20.16 | K20: =SRC_ZP_376*INP_022*INP_060*INP_061*INP_062/INP_019 -> 20.16 | L20: =SRC_ZP_376*INP_022*INP_060*INP_061*INP_062/INP_019 -> 20.16 | M20: 每 5 小時額度（SRC_ZP_376–378）× 每日窗口數 × 額度使用率 × 每 prompt 呼叫次數 × 每次呼叫 token（K）÷ 1000
A21: D13 | B21: 每訂閱者每日 token：Pro | C21: M tok／日 | D21: =SRC_ZP_377*INP_022*INP_060*INP_061*INP_062/INP_019 -> 100.8 | E21: =SRC_ZP_377*INP_022*INP_060*INP_061*INP_062/INP_019 -> 100.8 | F21: =SRC_ZP_377*INP_022*INP_060*INP_061*INP_062/INP_019 -> 100.8 | G21: =SRC_ZP_377*INP_022*INP_060*INP_061*INP_062/INP_019 -> 100.8 | H21: =SRC_ZP_377*INP_022*INP_060*INP_061*INP_062/INP_019 -> 100.8 | I21: =SRC_ZP_377*INP_022*INP_060*INP_061*INP_062/INP_019 -> 100.8 | K21: =SRC_ZP_377*INP_022*INP_060*INP_061*INP_062/INP_019 -> 100.8 | L21: =SRC_ZP_377*INP_022*INP_060*INP_061*INP_062/INP_019 -> 100.8 | M21: 每 5 小時額度（SRC_ZP_376–378）× 每日窗口數 × 額度使用率 × 每 prompt 呼叫次數 × 每次呼叫 token（K）÷ 1000
A22: D14 | B22: 每訂閱者每日 token：Max | C22: M tok／日 | D22: =SRC_ZP_378*INP_022*INP_060*INP_061*INP_062/INP_019 -> 403.2 | E22: =SRC_ZP_378*INP_022*INP_060*INP_061*INP_062/INP_019 -> 403.2 | F22: =SRC_ZP_378*INP_022*INP_060*INP_061*INP_062/INP_019 -> 403.2 | G22: =SRC_ZP_378*INP_022*INP_060*INP_061*INP_062/INP_019 -> 403.2 | H22: =SRC_ZP_378*INP_022*INP_060*INP_061*INP_062/INP_019 -> 403.2 | I22: =SRC_ZP_378*INP_022*INP_060*INP_061*INP_062/INP_019 -> 403.2 | K22: =SRC_ZP_378*INP_022*INP_060*INP_061*INP_062/INP_019 -> 403.2 | L22: =SRC_ZP_378*INP_022*INP_060*INP_061*INP_062/INP_019 -> 403.2 | M22: 每 5 小時額度（SRC_ZP_376–378）× 每日窗口數 × 額度使用率 × 每 prompt 呼叫次數 × 每次呼叫 token（K）÷ 1000
A23: D15 | B23: Coding Plan token：Lite | C23: T | D23: =D17*D20*INP_007/INP_016 -> 160.26595 | E23: =K23+L23 -> 1337.745 | F23: =F17*F20*INP_007/INP_016 -> 2003.3244 | G23: =G17*G20*INP_007/INP_016 -> 2604.3217 | H23: =H17*H20*INP_007/INP_016 -> 3125.1861 | I23: =I17*I20*INP_007/INP_016 -> 3593.964 | K23: =K17*K20*INP_008/INP_016 -> 529.82899 | L23: =L17*L20*INP_009/INP_016 -> 807.91603 | M23: 訂閱者（萬）× 每日 token（M）× 天數 ÷ 100（萬 × M → T）
A24: D16 | B24: Coding Plan token：Pro | C24: T | D24: =D18*D21*INP_007/INP_016 -> 400.66488 | E24: =K24+L24 -> 3344.3626 | F24: =F18*F21*INP_007/INP_016 -> 5008.311 | G24: =G18*G21*INP_007/INP_016 -> 6510.8043 | H24: =H18*H21*INP_007/INP_016 -> 7812.9652 | I24: =I18*I21*INP_007/INP_016 -> 8984.9099 | K24: =K18*K21*INP_008/INP_016 -> 1324.5725 | L24: =L18*L21*INP_009/INP_016 -> 2019.7901 | M24: 訂閱者（萬）× 每日 token（M）× 天數 ÷ 100（萬 × M → T）
A25: D17 | B25: Coding Plan token：Max | C25: T | D25: =D19*D22*INP_007/INP_016 -> 534.21984 | E25: =K25+L25 -> 4459.1501 | F25: =F19*F22*INP_007/INP_016 -> 6677.748 | G25: =G19*G22*INP_007/INP_016 -> 8681.0724 | H25: =H19*H22*INP_007/INP_016 -> 10417.287 | I25: =I19*I22*INP_007/INP_016 -> 11979.88 | K25: =K19*K22*INP_008/INP_016 -> 1766.0966 | L25: =L19*L22*INP_009/INP_016 -> 2693.0534 | M25: 訂閱者（萬）× 每日 token（M）× 天數 ÷ 100（萬 × M → T）
A26: D18 | B26: Coding Plan token 合計 | C26: T | D26: =D23+D24+D25 -> 1095.1507 | E26: =E23+E24+E25 -> 9141.2577 | F26: =F23+F24+F25 -> 13689.383 | G26: =G23+G24+G25 -> 17796.198 | H26: =H23+H24+H25 -> 21355.438 | I26: =I23+I24+I25 -> 24558.754 | K26: =K23+K24+K25 -> 3620.4981 | L26: =L23+L24+L25 -> 5520.7596
A27: D19 | B27: Coding Plan token：Sol | C27: T | D27: =D26*INP_063 -> 985.6356 | E27: =E26*INP_063 -> 8227.1319 | F27: =F26*INP_063 -> 12320.445 | G27: =G26*INP_063 -> 16016.579 | H27: =H26*INP_063 -> 19219.894 | I27: =I26*INP_063 -> 22102.878 | K27: =K26*INP_063 -> 3258.4483 | L27: =L26*INP_063 -> 4968.6836 | M27: Coding Plan 以 GLM-5.x 旗艦為主（D24r）
A28: D20 | B28: Coding Plan token：Luna | C28: T | D28: =D26*(1-INP_063) -> 109.51507 | E28: =E26*(1-INP_063) -> 914.12577 | F28: =F26*(1-INP_063) -> 1368.9383 | G28: =G26*(1-INP_063) -> 1779.6198 | H28: =H26*(1-INP_063) -> 2135.5438 | I28: =I26*(1-INP_063) -> 2455.8754 | K28: =K26*(1-INP_063) -> 362.04981 | L28: =L26*(1-INP_063) -> 552.07596
A29: 三、智譜清言（C 端；無單列收入，免費 token 耗算力；年度）
A30: D21 | B30: 智譜清言月活用戶 | C30: 百萬人 | D30: =INP_064 -> 10 | E30: =D30*(1+INP_065) -> 11 | F30: =E30*(1+INP_065) -> 12.1 | G30: =F30*(1+INP_065) -> 13.31 | H30: =G30*(1+INP_065) -> 14.641 | I30: =H30*(1+INP_065) -> 16.1051 | M30: 2025 Inputs（QuestMobile 未進前 20，SRC_ZP_434；Assumed 區間）；之後 ×（1＋年增率）
A31: D22 | B31: 智譜清言 token | C31: T | D31: =D30*INP_066*INP_067*INP_007/INP_018 -> 10.95 | E31: =E30*INP_066*INP_067*INP_007/INP_018 -> 12.045 | F31: =F30*INP_066*INP_067*INP_007/INP_018 -> 13.2495 | G31: =G30*INP_066*INP_067*INP_007/INP_018 -> 14.57445 | H31: =H30*INP_066*INP_067*INP_007/INP_018 -> 16.031895 | I31: =I30*INP_066*INP_067*INP_007/INP_018 -> 17.635085 | M31: 用戶（百萬）× 每日任務 × 每任務 token（K）× 天數 ÷ 1000（百萬 × K → T）
A32: D23 | B32: 智譜清言 token：Sol | C32: T | D32: =D31*INP_068 -> 3.285 | E32: =E31*INP_068 -> 3.6135 | F32: =F31*INP_068 -> 3.97485 | G32: =G31*INP_068 -> 4.372335 | H32: =H31*INP_068 -> 4.8095685 | I32: =I31*INP_068 -> 5.2905254
A33: D24 | B33: 智譜清言 token：Luna | C33: T | D33: =D31*(1-INP_068) -> 7.665 | E33: =E31*(1-INP_068) -> 8.4315 | F33: =F31*(1-INP_068) -> 9.27465 | G33: =G31*(1-INP_068) -> 10.202115 | H33: =H31*(1-INP_068) -> 11.222326 | I33: =I31*(1-INP_068) -> 12.344559
A34: 四、輸出：token 量（層級 × 付費／免費；供 Z3 推論 GW）
A35: D25 | B35: 付費 token：Sol | C35: T | D35: =D12+D27 -> 1025.5125 | E35: =E12+E27 -> 8713.4504 | F35: =F12+F27 -> 13578.794 | G35: =G12+G27 -> 18729.894 | H35: =H12+H27 -> 24485.422 | I35: =I12+I27 -> 31564.374 | M35: API 按量計費 Sol ＋ Coding Plan Sol
A36: D26 | B36: 付費 token：Luna | C36: T | D36: =D13+D28 -> 136.09967 | E36: =E13+E28 -> 1122.548 | F36: =F13+F28 -> 1908.2309 | G36: =G13+G28 -> 2942.4693 | H36: =H13+H28 -> 4392.1986 | I36: =I13+I28 -> 6510.8019 | M36: API 按量計費 Luna ＋ Coding Plan Luna
A37: D27 | B37: 免費 token：Sol | C37: T | D37: =D32 -> 3.285 | E37: =E32 -> 3.6135 | F37: =F32 -> 3.97485 | G37: =G32 -> 4.372335 | H37: =H32 -> 4.8095685 | I37: =I32 -> 5.2905254 | M37: 智譜清言 Sol
A38: D28 | B38: 免費 token：Luna | C38: T | D38: =D33+D14 -> 27.603454 | E38: =E33+E14 -> 216.85373 | F38: =F33+F14 -> 548.56716 | G38: =G33+G14 -> 1173.0516 | H38: =H33+H14 -> 2267.8771 | I38: =I33+I14 -> 4067.2711 | M38: 智譜清言 Luna ＋ 免費 API 型號
A39: D29 | B39: 付費 token 合計 | C39: T | D39: =D35+D36 -> 1161.6122 | E39: =E35+E36 -> 9835.9984 | F39: =F35+F36 -> 15487.025 | G39: =G35+G36 -> 21672.363 | H39: =H35+H36 -> 28877.621 | I39: =I35+I36 -> 38075.176
A40: D30 | B40: 免費 token 合計 | C40: T | D40: =D37+D38 -> 30.888454 | E40: =E37+E38 -> 220.46723 | F40: =F37+F38 -> 552.54201 | G40: =G37+G38 -> 1177.4239 | H40: =H37+H38 -> 2272.6867 | I40: =I37+I38 -> 4072.5616
A41: D31 | B41: token 合計（付費＋免費） | C41: T | D41: =D39+D40 -> 1192.5006 | E41: =E39+E40 -> 10056.466 | F41: =F39+F40 -> 16039.567 | G41: =G39+G40 -> 22849.787 | H41: =H39+H40 -> 31150.307 | I41: =I39+I40 -> 42147.737
A42: 五、對照（只列差距，不校準）
A43: D32 | B43: 2H25→1H26 實際隱含量成長（營收倍數 ÷ 模型單價倍數） | C43: 倍 | K43: =(SRC_ZP_169/(SRC_ZP_112-SRC_ZP_170))/(Revenue!K24/Revenue!D24) -> 3.2409594 | M43: 開放平台及 API：1H26 ÷ 2H25（＝FY25 − 1H25）實際營收，除以 1H26 ÷ 2025 組合有效單價；Inputs 2H26 任務數成長的參考（實際值，非公司說法）
A44: D33 | B44: 模型 2H26 ÷ 1H26 API 按量計費 token | C44: 倍 | L44: =L11/K11 -> 2.8071142 | M44: 對照：公司稱 MaaS token 呼叫量『較年初 40 倍以上』（SRC_ZP_410；基期為年初時點，口徑不同）
A45: D34 | B45: 公司說法：MaaS token 呼叫量較年初倍數 | C45: 倍 | K45: =SRC_ZP_410 -> 40 | M45: Interested-party；只對照，不反推（D14r）
A46: D35 | B46: 模型 2025 token 合計 ÷ 天數 | C46: T／日 | D46: =D41/INP_007 -> 3.267125 | M46: 對照：招股章程 2025-11 日均 4.2T（SRC_ZP_991，招股章程第 32 頁；r2 P2 改引用一手列；口徑可能含全部雲端與免費）
A47: D36 | B47: 公司揭露：2025-11 日均 token | C47: T／日 | D47: =SRC_ZP_991 -> 4.2 | M47: Interested-party（SRC_ZP_991，招股章程月度點）
A48: D37 | B48: 2025 計費比例＝API 按量計費 token ÷（日均 4.2T × 365） | C48: 比例 | D48: =D11/(SRC_ZP_991*INP_007) -> 0.04335389 | M48: 類比 OpenAI v0.6 DEM_ApiBilledRatio2025：揭露量多為免費、Coding Plan 與折扣流量

Sheet Revenue
A1: Revenue — 營收：①開放平台及 API（按量計費＋Coding Plan 子列）②企業級智能體 ③企業級通用大模型 ④技術服務及其他；總額＝淨額；雲端 vs 本地化、企業 vs 個人
A2: API 牌價：2025＝GLM-4.7／GLM-4.5-Air 牌價；1H26＝GLM-4.7→GLM-5→GLM-5.1 依發布日天數加權；2H26＝GLM-5.2／5.3（Sol）、GLM-4.5-Air→GLM-5.3-Flash（Luna）；2027 起 ×（1＋年變動率）。輸入價依長上下文占比混合兩檔。有效單價＝［(1−輸出占比)×(快取命中×快取價＋(1−快取命中)×輸入價)＋輸出占比×輸出價］×(1−折扣與免費額度)。
A3: 金額 RMB 億；牌價 元／百萬 token；Coding Plan 價格 元／月。②③④＝本地化部署分部（不耗智譜算力，D4、D2r）。容量上限係數取自 Compute（Z3），只回乘雲端營收。
A5: 編號 | B5: 項目 | C5: 單位 | D5: 2025 | E5: 2026 | F5: 2027 | G5: 2028 | H5: 2029 | I5: 2030 | K5: 1H2026 | L5: 2H2026 | M5: 說明
B6: 年度 | D6: =INP_001 -> 2025 | E6: =INP_002 -> 2026 | F6: =INP_003 -> 2027 | G6: =INP_004 -> 2028 | H6: =INP_005 -> 2029 | I6: =INP_006 -> 2030 | K6: 1H2026（實際） | L6: 2H2026（驅動）
A7: 一、價格期間權重（由發布日推得的天數；Inputs Derived）
A8: R01 | B8: 1H26 GLM-4.7 期間占比 | C8: 比例 | K8: =INP_026/INP_008 -> 0.2320442 | M8: 2026-01-01～02-11 ÷ 181 天
A9: R02 | B9: 1H26 GLM-5 期間占比 | C9: 比例 | K9: =INP_027/INP_008 -> 0.29834254 | M9: 2026-02-12～04-06 ÷ 181 天
A10: R03 | B10: 1H26 GLM-5.1 期間占比（＝1 − 前兩者） | C10: 比例 | K10: =(1-K8-K9) -> 0.46961326 | M10: 2026-04-07～06-30（GLM-5.2 於 06-16 發布，牌價同 GLM-5.1 ≥32K 檔）
A11: R04 | B11: 2H26 GLM-5.3-Flash 期間占比（Luna） | C11: 比例 | L11: =INP_028/INP_009 -> 0.69565217 | M11: 2026-08-26～12-31 ÷ 184 天；之前 Luna 以 GLM-4.5-Air 計
A12: 二、API 牌價（元／百萬 token；層級 × 輸入／快取／輸出）
A13: R05 | B13: Sol（GLM 旗艦） 輸入牌價 | C13: 元／M | D13: =(1-INP_025)*SRC_ZP_311+INP_025*SRC_ZP_314 -> 3.6 | E13: =(K13+L13)/INP_013 -> 6.8839779 | F13: =L13*(1+INP_035) -> 6.4 | G13: =F13*(1+INP_035) -> 5.12 | H13: =G13*(1+INP_035) -> 4.096 | I13: =H13*(1+INP_035) -> 3.2768 | K13: =K8*D13+K9*((1-INP_025)*SRC_ZP_302+INP_025*SRC_ZP_305)+K10*((1-INP_025)*SRC_ZP_290+INP_025*SRC_ZP_293) -> 5.7679558 | L13: =SRC_ZP_284 -> 8 | M13: 2025：GLM-4.7（<32K 且輸出 ≥0.2K 檔 與 32K–200K 檔，依長上下文占比混合）；1H26：期間加權 GLM-4.7／GLM-5／GLM-5.1；2H26：GLM-5.2／5.3 1M 全量；2027 起 ×（1＋年變動率）；2026 欄為兩個半年的平均（顯示用）
A14: R06 | B14: Sol（GLM 旗艦） 快取命中輸入牌價 | C14: 元／M | D14: =(1-INP_025)*SRC_ZP_312+INP_025*SRC_ZP_315 -> 0.72 | E14: =(K14+L14)/INP_013 -> 1.681326 | F14: =L14*(1+INP_035) -> 1.6 | G14: =F14*(1+INP_035) -> 1.28 | H14: =G14*(1+INP_035) -> 1.024 | I14: =H14*(1+INP_035) -> 0.8192 | K14: =K8*D14+K9*((1-INP_025)*SRC_ZP_303+INP_025*SRC_ZP_306)+K10*((1-INP_025)*SRC_ZP_291+INP_025*SRC_ZP_294) -> 1.3626519 | L14: =SRC_ZP_285 -> 2 | M14: 2025：GLM-4.7（<32K 且輸出 ≥0.2K 檔 與 32K–200K 檔，依長上下文占比混合）；1H26：期間加權 GLM-4.7／GLM-5／GLM-5.1；2H26：GLM-5.2／5.3 1M 全量；2027 起 ×（1＋年變動率）；2026 欄為兩個半年的平均（顯示用）
A15: R07 | B15: Sol（GLM 旗艦） 輸出牌價 | C15: 元／M | D15: =(1-INP_025)*SRC_ZP_313+INP_025*SRC_ZP_316 -> 15.2 | E15: =(K15+L15)/INP_013 -> 25.005525 | F15: =L15*(1+INP_035) -> 22.4 | G15: =F15*(1+INP_035) -> 17.92 | H15: =G15*(1+INP_035) -> 14.336 | I15: =H15*(1+INP_035) -> 11.4688 | K15: =K8*D15+K9*((1-INP_025)*SRC_ZP_304+INP_025*SRC_ZP_307)+K10*((1-INP_025)*SRC_ZP_292+INP_025*SRC_ZP_295) -> 22.01105 | L15: =SRC_ZP_286 -> 28 | M15: 2025：GLM-4.7（<32K 且輸出 ≥0.2K 檔 與 32K–200K 檔，依長上下文占比混合）；1H26：期間加權 GLM-4.7／GLM-5／GLM-5.1；2H26：GLM-5.2／5.3 1M 全量；2027 起 ×（1＋年變動率）；2026 欄為兩個半年的平均（顯示用）
A16: R08 | B16: Luna（Air／Flash） 輸入牌價 | C16: 元／M | D16: =(1-INP_025)*SRC_ZP_320+INP_025*SRC_ZP_323 -> 1.04 | E16: =(K16+L16)/INP_013 -> 0.95652174 | F16: =L16*(1+INP_036) -> 0.69843478 | G16: =F16*(1+INP_036) -> 0.55874783 | H16: =G16*(1+INP_036) -> 0.44699826 | I16: =H16*(1+INP_036) -> 0.35759861 | K16: =D16 -> 1.04 | L16: =(1-L11)*K16+L11*SRC_ZP_329 -> 0.87304348 | M16: 2025、1H26：GLM-4.5-Air（<32K 且輸出 ≥0.2K 檔 與 32K–128K 檔混合）；2H26：GLM-4.5-Air 與 GLM-5.3-Flash（08-26 起）期間加權；2027 起 ×（1＋年變動率）
A17: R09 | B17: Luna（Air／Flash） 快取命中輸入牌價 | C17: 元／M | D17: =(1-INP_025)*SRC_ZP_321+INP_025*SRC_ZP_324 -> 0.208 | E17: =(K17+L17)/INP_013 -> 0.21565217 | F17: =L17*(1+INP_036) -> 0.17864348 | G17: =F17*(1+INP_036) -> 0.14291478 | H17: =G17*(1+INP_036) -> 0.11433183 | I17: =H17*(1+INP_036) -> 0.091465461 | K17: =D17 -> 0.208 | L17: =(1-L11)*K17+L11*SRC_ZP_330 -> 0.22330435 | M17: 2025、1H26：GLM-4.5-Air（<32K 且輸出 ≥0.2K 檔 與 32K–128K 檔混合）；2H26：GLM-4.5-Air 與 GLM-5.3-Flash（08-26 起）期間加權；2027 起 ×（1＋年變動率）
A18: R10 | B18: Luna（Air／Flash） 輸出牌價 | C18: 元／M | D18: =(1-INP_025)*SRC_ZP_322+INP_025*SRC_ZP_325 -> 7.2 | E18: =(K18+L18)/INP_013 -> 5.6695652 | F18: =L18*(1+INP_036) -> 3.3113043 | G18: =F18*(1+INP_036) -> 2.6490435 | H18: =G18*(1+INP_036) -> 2.1192348 | I18: =H18*(1+INP_036) -> 1.6953878 | K18: =D18 -> 7.2 | L18: =(1-L11)*K18+L11*SRC_ZP_331 -> 4.1391304 | M18: 2025、1H26：GLM-4.5-Air（<32K 且輸出 ≥0.2K 檔 與 32K–128K 檔混合）；2H26：GLM-4.5-Air 與 GLM-5.3-Flash（08-26 起）期間加權；2027 起 ×（1＋年變動率）
A19: 三、有效單價（元／百萬 token；含快取、輸出占比、折扣與免費額度）
A20: R11 | B20: Sol（GLM 旗艦） 有效單價 | C20: 元／M | D20: =((1-INP_029)*(INP_030*D14+(1-INP_030)*D13)+INP_029*D15)*(1-INP_031) -> 3.087 | E20: =(K20+L20)/INP_013 -> 5.5433122 | F20: =((1-INP_029)*(INP_030*F14+(1-INP_030)*F13)+INP_029*F15)*(1-INP_031) -> 5.07 | G20: =((1-INP_029)*(INP_030*G14+(1-INP_030)*G13)+INP_029*G15)*(1-INP_031) -> 4.056 | H20: =((1-INP_029)*(INP_030*H14+(1-INP_030)*H13)+INP_029*H15)*(1-INP_031) -> 3.2448 | I20: =((1-INP_029)*(INP_030*I14+(1-INP_030)*I13)+INP_029*I15)*(1-INP_031) -> 2.59584 | K20: =((1-INP_029)*(INP_030*K14+(1-INP_030)*K13)+INP_029*K15)*(1-INP_031) -> 4.7491243 | L20: =((1-INP_029)*(INP_030*L14+(1-INP_030)*L13)+INP_029*L15)*(1-INP_031) -> 6.3375 | M20: ［(1−輸出占比)×(快取命中×快取價＋(1−快取命中)×輸入價)＋輸出占比×輸出價］×(1−折扣與免費額度)
A21: R12 | B21: Luna（Air／Flash） 有效單價 | C21: 元／M | D21: =((1-INP_029)*(INP_030*D17+(1-INP_030)*D16)+INP_029*D18)*(1-INP_031) -> 1.2078 | E21: =(K21+L21)/INP_013 -> 1.0114565 | F21: =((1-INP_029)*(INP_030*F17+(1-INP_030)*F16)+INP_029*F18)*(1-INP_031) -> 0.65209043 | G21: =((1-INP_029)*(INP_030*G17+(1-INP_030)*G16)+INP_029*G18)*(1-INP_031) -> 0.52167235 | H21: =((1-INP_029)*(INP_030*H17+(1-INP_030)*H16)+INP_029*H18)*(1-INP_031) -> 0.41733788 | I21: =((1-INP_029)*(INP_030*I17+(1-INP_030)*I16)+INP_029*I18)*(1-INP_031) -> 0.3338703 | K21: =((1-INP_029)*(INP_030*K17+(1-INP_030)*K16)+INP_029*K18)*(1-INP_031) -> 1.2078 | L21: =((1-INP_029)*(INP_030*L17+(1-INP_030)*L16)+INP_029*L18)*(1-INP_031) -> 0.81511304 | M21: ［(1−輸出占比)×(快取命中×快取價＋(1−快取命中)×輸入價)＋輸出占比×輸出價］×(1−折扣與免費額度)
A22: R13 | B22: 付費 API token 組合：Sol | C22: 比例 | D22: =INP_032 -> 0.6 | E22: =INP_033 -> 0.7 | F22: =INP_034 -> 0.7 | G22: =INP_034 -> 0.7 | H22: =INP_034 -> 0.7 | I22: =INP_034 -> 0.7 | K22: =INP_033 -> 0.7 | L22: =INP_033 -> 0.7 | M22: Inputs（2025、2026、2027 起）
A23: R14 | B23: 付費 API token 組合：Luna | C23: 比例 | D23: =(1-D22) -> 0.4 | E23: =(1-E22) -> 0.3 | F23: =(1-F22) -> 0.3 | G23: =(1-G22) -> 0.3 | H23: =(1-H22) -> 0.3 | I23: =(1-I22) -> 0.3 | K23: =(1-K22) -> 0.3 | L23: =(1-L22) -> 0.3 | M23: ＝1 − Sol（D24：無 Astra 級）
A24: R15 | B24: 組合有效單價 | C24: 元／M | D24: =D22*D20+D23*D21 -> 2.33532 | E24: =E47*INP_015/Demand!E11 -> 4.4196788 | F24: =F22*F20+F23*F21 -> 3.7446271 | G24: =G22*G20+G23*G21 -> 2.9957017 | H24: =H22*H20+H23*H21 -> 2.3965614 | I24: =I22*I20+I23*I21 -> 1.9172491 | K24: =K22*K20+K23*K21 -> 3.686727 | L24: =L22*L20+L23*L21 -> 4.6807839 | M24: Σ 層級組合 × 有效單價；2026 欄＝全年按量計費營收 ÷ 全年 token（token 加權）
A25: 四、GLM Coding Plan 方案價格（元／月／訂閱者）
A26: R16 | B26: Lite 國內月付牌價 | C26: 元／月 | K26: =SRC_ZP_356 -> 49 | L26: =SRC_ZP_356 -> 49 | M26: 2026-02-12 漲價後（SRC_ZP_356／359／362）
A27: R17 | B27: Lite 國際站月價（換人民幣） | C27: 元／月 | K27: =SRC_ZP_373/INP_012*INP_023 -> 67.399 | L27: =SRC_ZP_367*INP_023 -> 121.3182 | M27: 1H26：2026-02～07 季付價 ÷ 3（SRC_ZP_373–375）；2H26：2026-07 起牌價（SRC_ZP_367／369／371）；× USD/CNY
A28: R18 | B28: Lite 有效月價（實收） | C28: 元／月 | D28: =K28/(1+SRC_ZP_350/INP_014) -> 33.550585 | E28: =(K28+L28)/INP_013 -> 50.086064 | F28: =L28*(1+INP_059) -> 56.556368 | G28: =F28*(1+INP_059) -> 56.556368 | H28: =G28*(1+INP_059) -> 56.556368 | I28: =H28*(1+INP_059) -> 56.556368 | K28: =((1-INP_057)*K26+INP_057*K27)*(1-INP_058) -> 43.61576 | L28: =((1-INP_057)*L26+INP_057*L27)*(1-INP_058) -> 56.556368 | M28: ［(1−國際占比)×國內＋國際占比×國際］×(1−季／年付折扣)；2025＝1H26 ÷（1＋2026-02 漲價 30%，SRC_ZP_350）；2027 起 ×（1＋年變動率）
A29: R19 | B29: Pro 國內月付牌價 | C29: 元／月 | K29: =SRC_ZP_359 -> 149 | L29: =SRC_ZP_359 -> 149 | M29: 2026-02-12 漲價後（SRC_ZP_356／359／362）
A30: R20 | B30: Pro 國際站月價（換人民幣） | C30: 元／月 | K30: =SRC_ZP_374/INP_012*INP_023 -> 202.197 | L30: =SRC_ZP_369*INP_023 -> 485.2728 | M30: 1H26：2026-02～07 季付價 ÷ 3（SRC_ZP_373–375）；2H26：2026-07 起牌價（SRC_ZP_367／369／371）；× USD/CNY
A31: R21 | B31: Pro 有效月價（實收） | C31: 元／月 | D31: =K31/(1+SRC_ZP_350/INP_014) -> 101.51329 | E31: =(K31+L31)/INP_013 -> 165.93638 | F31: =L31*(1+INP_059) -> 199.90547 | G31: =F31*(1+INP_059) -> 199.90547 | H31: =G31*(1+INP_059) -> 199.90547 | I31: =H31*(1+INP_059) -> 199.90547 | K31: =((1-INP_057)*K29+INP_057*K30)*(1-INP_058) -> 131.96728 | L31: =((1-INP_057)*L29+INP_057*L30)*(1-INP_058) -> 199.90547 | M31: ［(1−國際占比)×國內＋國際占比×國際］×(1−季／年付折扣)；2025＝1H26 ÷（1＋2026-02 漲價 30%，SRC_ZP_350）；2027 起 ×（1＋年變動率）
A32: R22 | B32: Max 國內月付牌價 | C32: 元／月 | K32: =SRC_ZP_362 -> 469 | L32: =SRC_ZP_362 -> 469 | M32: 2026-02-12 漲價後（SRC_ZP_356／359／362）
A33: R23 | B33: Max 國際站月價（換人民幣） | C33: 元／月 | K33: =SRC_ZP_375/INP_012*INP_023 -> 539.192 | L33: =SRC_ZP_371*INP_023 -> 1078.384 | M33: 1H26：2026-02～07 季付價 ÷ 3（SRC_ZP_373–375）；2H26：2026-07 起牌價（SRC_ZP_367／369／371）；× USD/CNY
A34: R24 | B34: Max 有效月價（實收） | C34: 元／月 | D34: =K34/(1+SRC_ZP_350/INP_014) -> 301.57391 | E34: =(K34+L34)/INP_013 -> 456.74912 | F34: =L34*(1+INP_059) -> 521.45216 | G34: =F34*(1+INP_059) -> 521.45216 | H34: =G34*(1+INP_059) -> 521.45216 | I34: =H34*(1+INP_059) -> 521.45216 | K34: =((1-INP_057)*K32+INP_057*K33)*(1-INP_058) -> 392.04608 | L34: =((1-INP_057)*L32+INP_057*L33)*(1-INP_058) -> 521.45216 | M34: ［(1−國際占比)×國內＋國際占比×國際］×(1−季／年付折扣)；2025＝1H26 ÷（1＋2026-02 漲價 30%，SRC_ZP_350）；2027 起 ×（1＋年變動率）
A35: R25 | B35: 方案組合：Lite | C35: 比例 | D35: =INP_055 -> 0.6 | E35: =INP_055 -> 0.6 | F35: =INP_055 -> 0.6 | G35: =INP_055 -> 0.6 | H35: =INP_055 -> 0.6 | I35: =INP_055 -> 0.6 | K35: =INP_055 -> 0.6 | L35: =INP_055 -> 0.6 | M35: Inputs
A36: R26 | B36: 方案組合：Pro | C36: 比例 | D36: =INP_056 -> 0.3 | E36: =INP_056 -> 0.3 | F36: =INP_056 -> 0.3 | G36: =INP_056 -> 0.3 | H36: =INP_056 -> 0.3 | I36: =INP_056 -> 0.3 | K36: =INP_056 -> 0.3 | L36: =INP_056 -> 0.3 | M36: Inputs
A37: R27 | B37: 方案組合：Max（＝1 − Lite − Pro） | C37: 比例 | D37: =(1-D35-D36) -> 0.1 | E37: =(1-E35-E36) -> 0.1 | F37: =(1-F35-F36) -> 0.1 | G37: =(1-G35-G36) -> 0.1 | H37: =(1-H35-H36) -> 0.1 | I37: =(1-I35-I36) -> 0.1 | K37: =(1-K35-K36) -> 0.1 | L37: =(1-L35-L36) -> 0.1 | M37: 不另輸入
A38: R28 | B38: 每訂閱者加權有效月價 | C38: 元／月 | D38: =D35*D28+D36*D31+D37*D34 -> 80.741729 | E38: =E35*E28+E36*E31+E37*E34 -> 125.50746 | F38: =F35*F28+F36*F31+F37*F34 -> 146.05068 | G38: =G35*G28+G36*G31+G37*G34 -> 146.05068 | H38: =H35*H28+H36*H31+H37*H34 -> 146.05068 | I38: =I35*I28+I36*I31+I37*I34 -> 146.05068 | K38: =K35*K28+K36*K31+K37*K34 -> 104.96425 | L38: =L35*L28+L36*L31+L37*L34 -> 146.05068
A39: 五、營收（RMB 億）
A40: R29 | B40: ①-Coding Plan 子列：Lite | C40: RMB 億 | D40: =Demand!D17*D28*INP_010/INP_017 -> 0.087687808 | E40: =K40+L40 -> 1.1190591 | F40: =Demand!F17*F28*INP_010/INP_017 -> 1.8476965 | G40: =Demand!G17*G28*INP_010/INP_017 -> 2.4020055 | H40: =Demand!H17*H28*INP_010/INP_017 -> 2.8824066 | I40: =Demand!I17*I28*INP_010/INP_017 -> 3.3147676 | K40: =Demand!K17*K28*INP_011/INP_017 -> 0.3799805 | L40: =Demand!L17*L28*INP_011/INP_017 -> 0.73907862 | M40: 訂閱者（萬）× 有效月價 × 月數 ÷ 10,000（萬 × 元 → 億）
A41: R30 | B41: ①-Coding Plan 子列：Pro | C41: RMB 億 | D41: =Demand!D18*D31*INP_010/INP_017 -> 0.13265757 | E41: =K41+L41 -> 1.8810318 | F41: =Demand!F18*F31*INP_010/INP_017 -> 3.2654559 | G41: =Demand!G18*G31*INP_010/INP_017 -> 4.2450927 | H41: =Demand!H18*H31*INP_010/INP_017 -> 5.0941112 | I41: =Demand!I18*I31*INP_010/INP_017 -> 5.8582279 | K41: =Demand!K18*K31*INP_011/INP_017 -> 0.57484947 | L41: =Demand!L18*L31*INP_011/INP_017 -> 1.3061824 | M41: 訂閱者（萬）× 有效月價 × 月數 ÷ 10,000（萬 × 元 → 億）
A42: R31 | B42: ①-Coding Plan 子列：Max | C42: RMB 億 | D42: =Demand!D19*D34*INP_010/INP_017 -> 0.13136559 | E42: =K42+L42 -> 1.7049737 | F42: =Demand!F19*F34*INP_010/INP_017 -> 2.839307 | G42: =Demand!G19*G34*INP_010/INP_017 -> 3.6910991 | H42: =Demand!H19*H34*INP_010/INP_017 -> 4.4293189 | I42: =Demand!I19*I34*INP_010/INP_017 -> 5.0937168 | K42: =Demand!K19*K34*INP_011/INP_017 -> 0.56925091 | L42: =Demand!L19*L34*INP_011/INP_017 -> 1.1357228 | M42: 訂閱者（萬）× 有效月價 × 月數 ÷ 10,000（萬 × 元 → 億）
A43: R32 | B43: ①-Coding Plan 子列合計（訂閱） | C43: RMB 億 | D43: =D40+D41+D42 -> 0.35171097 | E43: =E40+E41+E42 -> 4.7050647 | F43: =F40+F41+F42 -> 7.9524594 | G43: =G40+G41+G42 -> 10.338197 | H43: =H40+H41+H42 -> 12.405837 | I43: =I40+I41+I42 -> 14.266712 | K43: =K40+K41+K42 -> 1.5240809 | L43: =L40+L41+L42 -> 3.1809838 | M43: 財報歸入開放平台及 API（D2r）；本模型以訂閱者驅動
A44: R33 | B44: 校準：按量計費營收＝開放平台及 API 實際 − Coding Plan 估計 | C44: RMB 億 | D44: =SRC_ZP_112-D43 -> 1.552089 | K44: =SRC_ZP_169-K43 -> 6.7277191 | M44: 2025（年報）、1H26（中期公告）；按量計費 token 由此倒推（D14）
A45: R34 | B45: ①-按量計費：Sol（GLM 旗艦） | C45: RMB 億 | D45: =Demand!D11*D22*D20/INP_015 -> 1.2310002 | E45: =K45+L45 -> 28.791455 | F45: =Demand!F11*F22*F20/INP_015 -> 63.798304 | G45: =Demand!G11*G22*G20/INP_015 -> 110.05207 | H45: =Demand!H11*H22*H20/INP_015 -> 170.85585 | I45: =Demand!I11*I22*I20/INP_015 -> 245.60528 | K45: =Demand!K11*K22*K20/INP_015 -> 6.0665034 | L45: =Demand!L11*L22*L20/INP_015 -> 22.724952 | M45: token × 組合 × 有效單價 ÷ 100（T × 元/M → 億）
A46: R35 | B46: ①-按量計費：Luna（Air／Flash） | C46: RMB 億 | D46: =Demand!D11*D23*D21/INP_015 -> 0.32108887 | E46: =K46+L46 -> 1.913855 | F46: =Demand!F11*F23*F21/INP_015 -> 3.5166749 | G46: =Demand!G11*G23*G21/INP_015 -> 6.0662642 | H46: =Demand!H11*H23*H21/INP_015 -> 9.4178751 | I46: =Demand!I11*I23*I21/INP_015 -> 13.538195 | K46: =Demand!K11*K23*K21/INP_015 -> 0.66121569 | L46: =Demand!L11*L23*L21/INP_015 -> 1.2526394 | M46: token × 組合 × 有效單價 ÷ 100（T × 元/M → 億）
A47: R36 | B47: ①-按量計費合計 | C47: RMB 億 | D47: =D45+D46 -> 1.552089 | E47: =E45+E46 -> 30.70531 | F47: =F45+F46 -> 67.314979 | G47: =G45+G46 -> 116.11834 | H47: =H45+H46 -> 180.27372 | I47: =I45+I46 -> 259.14347 | K47: =K45+K46 -> 6.7277191 | L47: =L45+L46 -> 23.977591 | M47: 校準期恆等於上方校準列
A48: R37 | B48: ①開放平台及 API（按量計費＋Coding Plan） | C48: RMB 億 | D48: =D47+D43 -> 1.9038 | E48: =E47+E43 -> 35.410375 | F48: =F47+F43 -> 75.267438 | G48: =G47+G43 -> 126.45654 | H48: =H47+H43 -> 192.67956 | I48: =I47+I43 -> 273.41019 | K48: =K47+K43 -> 8.2518 | L48: =L47+L43 -> 27.158575 | M48: ＝雲端部署分部（D2r）
A49: R38 | B49: ②企業級智能體 | C49: RMB 億 | D49: =SRC_ZP_114 -> 1.6569 | E49: =K49+L49 -> 2.0751 | F49: =E49*(1+INP_070) -> 2.0751 | G49: =F49*(1+INP_070) -> 2.0751 | H49: =G49*(1+INP_070) -> 2.0751 | I49: =H49*(1+INP_070) -> 2.0751 | K49: =SRC_ZP_171 -> 0.5556 | L49: =(SRC_ZP_114-SRC_ZP_172)*((1-INP_069)+INP_069*SRC_ZP_171/SRC_ZP_172) -> 1.5195 | M49: 2025、1H26＝財報；2H26＝2H25（FY25 − 1H25）×［(1−延續係數)＋延續係數 × 1H26 ÷ 1H25］（工作單：依 1H26 實際、各線分開）；2027 起 ×（1＋年增率）
A50: R39 | B50: ③企業級通用大模型 | C50: RMB 億 | D50: =SRC_ZP_116 -> 3.6572 | E50: =K50+L50 -> 2.8521 | F50: =E50*(1+INP_070) -> 2.8521 | G50: =F50*(1+INP_070) -> 2.8521 | H50: =G50*(1+INP_070) -> 2.8521 | I50: =H50*(1+INP_070) -> 2.8521 | K50: =SRC_ZP_173 -> 0.6704 | L50: =(SRC_ZP_116-SRC_ZP_174)*((1-INP_069)+INP_069*SRC_ZP_173/SRC_ZP_174) -> 2.1817 | M50: 2025、1H26＝財報；2H26＝2H25（FY25 − 1H25）×［(1−延續係數)＋延續係數 × 1H26 ÷ 1H25］（工作單：依 1H26 實際、各線分開）；2027 起 ×（1＋年增率）
A51: R40 | B51: ④技術服務及其他（含 C 端） | C51: RMB 億 | D51: =SRC_ZP_118 -> 0.0254 | E51: =K51+L51 -> 0.0818 | F51: =E51*(1+INP_070) -> 0.0818 | G51: =F51*(1+INP_070) -> 0.0818 | H51: =G51*(1+INP_070) -> 0.0818 | I51: =H51*(1+INP_070) -> 0.0818 | K51: =SRC_ZP_175 -> 0.0612 | L51: =(SRC_ZP_118-SRC_ZP_176)*((1-INP_069)+INP_069*SRC_ZP_175/SRC_ZP_176) -> 0.0206 | M51: 2025、1H26＝財報；2H26＝2H25（FY25 − 1H25）×［(1−延續係數)＋延續係數 × 1H26 ÷ 1H25］（工作單：依 1H26 實際、各線分開）；2027 起 ×（1＋年增率）
A52: R41 | B52: 本地化部署分部（②＋③＋④；不耗智譜算力） | C52: RMB 億 | D52: =D49+D50+D51 -> 5.3395 | E52: =E49+E50+E51 -> 5.009 | F52: =F49+F50+F51 -> 5.009 | G52: =G49+G50+G51 -> 5.009 | H52: =H49+H50+H51 -> 5.009 | I52: =I49+I50+I51 -> 5.009 | K52: =K49+K50+K51 -> 1.2872 | L52: =L49+L50+L51 -> 3.7218 | M52: D4：不進 Demand、不受容量上限截頂
A53: R42 | B53: 廣告 | C53: RMB 億 | D53: =INP_071 -> 0 | E53: =INP_071 -> 0 | F53: =INP_071 -> 0 | G53: =INP_071 -> 0 | H53: =INP_071 -> 0 | I53: =INP_071 -> 0 | K53: =INP_071 -> 0 | L53: =INP_071 -> 0 | M53: 規格 D3：無廣告業務（Decision＝0）
A54: R43 | B54: 營收總額（①＋本地化＋廣告） | C54: RMB 億 | D54: =D48+D52+D53 -> 7.2433 | E54: =E48+E52+E53 -> 40.419375 | F54: =F48+F52+F53 -> 80.276438 | G54: =G48+G52+G53 -> 131.46554 | H54: =H48+H52+H53 -> 197.68856 | I54: =I48+I52+I53 -> 278.41919 | K54: =K48+K52+K53 -> 9.539 | L54: =L48+L52+L53 -> 30.880375 | M54: 未截頂
A55: R44 | B55: 營收淨額（＝總額；無雲端夥伴分成，D5） | C55: RMB 億 | D55: =D54 -> 7.2433 | E55: =E54 -> 40.419375 | F55: =F54 -> 80.276438 | G55: =G54 -> 131.46554 | H55: =H54 -> 197.68856 | I55: =I54 -> 278.41919 | K55: =K54 -> 9.539 | L55: =L54 -> 30.880375 | M55: REV_PartnerShare 不建
A56: R45 | B56: 雲端營收（①；跑在智譜算力上） | C56: RMB 億 | D56: =D48 -> 1.9038 | E56: =E48 -> 35.410375 | F56: =F48 -> 75.267438 | G56: =G48 -> 126.45654 | H56: =H48 -> 192.67956 | I56: =I48 -> 273.41019 | K56: =K48 -> 8.2518 | L56: =L48 -> 27.158575 | M56: 規格 r1：②③④屬本地化部署分部；C 端收入在④內
A57: R46 | B57: 容量上限係數（Compute） | C57: 比例 | D57: =Compute!D125 -> 1 | E57: =(K56+L56*Compute!L125)/E56 -> 1 | F57: =Compute!F125 -> 1 | G57: =Compute!G125 -> 1 | H57: =Compute!H125 -> 1 | I57: =Compute!I125 -> 1 | M57: Compute CMP_CapFactor（1＝未受限；Z3 取代 Z2 的佔位 1）；2026＝1H26 實際不截頂、2H26 依 Compute 係數，以雲端營收加權
A58: R47 | B58: 營收總額（截頂後）＝雲端 × 係數＋本地化＋廣告 | C58: RMB 億 | D58: =D56*D57+D52+D53 -> 7.2433 | E58: =E56*E57+E52+E53 -> 40.419375 | F58: =F56*F57+F52+F53 -> 80.276438 | G58: =G56*G57+G52+G53 -> 131.46554 | H58: =H56*H57+H52+H53 -> 197.68856 | I58: =I56*I57+I52+I53 -> 278.41919 | M58: 容量上限只回乘雲端營收（工作單 Z2 第 5 步）
A59: R48 | B59: 營收淨額（截頂後） | C59: RMB 億 | D59: =D58 -> 7.2433 | E59: =E58 -> 40.419375 | F59: =F58 -> 80.276438 | G59: =G58 -> 131.46554 | H59: =H58 -> 197.68856 | I59: =I58 -> 278.41919
A60: R49 | B60: 企業（按量計費＋本地化部署） | C60: RMB 億 | D60: =D47+D52 -> 6.891589 | E60: =E47+E52 -> 35.71431 | F60: =F47+F52 -> 72.323979 | G60: =G47+G52 -> 121.12734 | H60: =H47+H52 -> 185.28272 | I60: =I47+I52 -> 264.15247 | K60: =K47+K52 -> 8.0149191 | L60: =L47+L52 -> 27.699391 | M60: D2：企業 vs 個人；按量計費以企業與開發者為主，歸企業
A61: R50 | B61: 個人（Coding Plan 訂閱） | C61: RMB 億 | D61: =D43 -> 0.35171097 | E61: =E43 -> 4.7050647 | F61: =F43 -> 7.9524594 | G61: =G43 -> 10.338197 | H61: =H43 -> 12.405837 | I61: =I43 -> 14.266712 | K61: =K43 -> 1.5240809 | L61: =L43 -> 3.1809838 | M61: Coding Plan 以個人開發者為主；C 端清言收入在④內未拆，歸企業列（資料缺口）
A62: R51 | B62: 檢查：企業＋個人＋廣告 − 總額（應為 0） | C62: RMB 億 | D62: =D60+D61+D53-D54 -> 0 | E62: =E60+E61+E53-E54 -> 0 | F62: =F60+F61+F53-F54 -> 0 | G62: =G60+G61+G53-G54 -> 0 | H62: =H60+H61+H53-H54 -> 0 | I62: =I60+I61+I53-I54 -> 0 | K62: =K60+K61+K53-K54 -> 0 | L62: =L60+L61+L53-L54 -> 0
A63: R52 | B63: 雲端占總額 | C63: 比例 | D63: =D56/D54 -> 0.262836 | E63: =E56/E54 -> 0.87607428 | F63: =F56/F54 -> 0.93760311 | G63: =G56/G54 -> 0.96189876 | H63: =H56/H54 -> 0.97466217 | I63: =I56/I54 -> 0.98200914 | K63: =K56/K54 -> 0.86505923 | L63: =L56/L54 -> 0.87947685 | M63: 2025 約 26%、1H26 約 87%（財報）
A64: R53 | B64: 總額年增率 | C64: 比例 | E64: =(E54-D54)/D54 -> 4.5802431 | F64: =(F54-E54)/E54 -> 0.98608808 | G64: =(G54-F54)/F54 -> 0.6376603 | H64: =(H54-G54)/G54 -> 0.50372914 | I64: =(I54-H54)/H54 -> 0.40837279
A65: 六、校準差距（應為 0）與對照（公司說法、TK、未校準值；只列差距，不反推）
A66: R54 | B66: 2025 校準差距：①開放平台及 API（模型 − 年報） | C66: RMB 億 | D66: =D48-SRC_ZP_112 -> 0
A67: R55 | B67: 1H26 校準差距：①開放平台及 API（模型 − 中期公告） | C67: RMB 億 | K67: =K48-SRC_ZP_169 -> 0
A68: R56 | B68: 2025 校準差距：②企業級智能體（模型 − 年報） | C68: RMB 億 | D68: =D49-SRC_ZP_114 -> 0
A69: R57 | B69: 1H26 校準差距：②企業級智能體（模型 − 中期公告） | C69: RMB 億 | K69: =K49-SRC_ZP_171 -> 0
A70: R58 | B70: 2025 校準差距：③企業級通用大模型（模型 − 年報） | C70: RMB 億 | D70: =D50-SRC_ZP_116 -> 0
A71: R59 | B71: 1H26 校準差距：③企業級通用大模型（模型 − 中期公告） | C71: RMB 億 | K71: =K50-SRC_ZP_173 -> 0
A72: R60 | B72: 2025 校準差距：④技術服務及其他（含 C 端）（模型 − 年報） | C72: RMB 億 | D72: =D51-SRC_ZP_118 -> 0
A73: R61 | B73: 1H26 校準差距：④技術服務及其他（含 C 端）（模型 − 中期公告） | C73: RMB 億 | K73: =K51-SRC_ZP_175 -> 0
A74: R62 | B74: 2025 校準差距：營收總額（模型 − 年報） | C74: RMB 億 | D74: =D54-SRC_ZP_120 -> 0
A75: R63 | B75: 1H26 校準差距：營收總額（模型 − 中期公告） | C75: RMB 億 | K75: =K54-SRC_ZP_177 -> 0.0001 | M75: 公告以千元四捨五入至億元四位小數：四線合計 9.53892 vs 總額 9.5389
A76: R64 | B76: 2025 未校準 ①：日均 4.2T × 365 × 組合有效單價 ÷ 100 ＋ Coding Plan | C76: RMB 億 | D76: =SRC_ZP_991*INP_007*D24/INP_015+D43 -> 36.152167 | M76: 自下而上口徑（假設揭露 token 全數按有效單價計費）
A77: R65 | B77: 2025 未校準差距：未校準 − 年報 ① | C77: RMB 億 | D77: =D76-SRC_ZP_112 -> 34.248367 | M77: 差距大＝揭露量多為免費、Coding Plan 或年末時點
A78: R66 | B78: 模型組合有效單價變動：1H26 對 2025 | C78: 比例 | K78: =(K24-D24)/D24 -> 0.57868173 | M78: 對照：公司稱 API 平均售價較年初 +101%（SRC_ZP_347）
A79: R67 | B79: 模型組合有效單價變動：2H26 對 2025 | C79: 比例 | L79: =(L24-D24)/D24 -> 1.0043437 | M79: 對照：較 2025 年底 +83%（SRC_ZP_346，截至 2026-03）
A80: R68 | B80: 公司說法：API 平均售價較年初上升（中期） | C80: 比例 | K80: =SRC_ZP_347/INP_014 -> 1.01 | M80: Interested-party；實現平均售價口徑（收入 ÷ 計費 token），只對照
A81: R69 | B81: 公司說法：API 呼叫定價較 2025 年底上升 | C81: 比例 | L81: =SRC_ZP_346/INP_014 -> 0.83 | M81: Interested-party；只對照
A82: R70 | B82: 模型 2H26 雲端營收年化（2H26 × 2） | C82: RMB 億 | L82: =L56*INP_013 -> 54.317149 | M82: 對照 MaaS ARR（D14r）
A83: R71 | B83: 公司說法：MaaS ARR（2026-08 月度年化）× 匯率 | C83: RMB 億 | L83: =SRC_ZP_417*INP_023 -> 107.8384 | M83: SRC_ZP_417（USD 億）；Interested-party
A84: R72 | B84: 差距：模型 ÷ ARR − 1 | C84: 比例 | L84: =(L82-L83)/L83 -> -0.49630976 | M84: Checks WARN 門檻 25%（D14r）
A85: R73 | B85: 模型 2H26 營收總額年化（2H26 × 2） | C85: RMB 億 | L85: =L54*INP_013 -> 61.760749 | M85: 對照全業務 ARR
A86: R74 | B86: 公司說法：全業務 ARR（2026-09）× 匯率 | C86: RMB 億 | L86: =SRC_ZP_419*INP_023 -> 121.3182 | M86: SRC_ZP_419（USD 億）；Interested-party
A87: R75 | B87: 差距：模型 ÷ 全業務 ARR − 1 | C87: 比例 | L87: =(L85-L86)/L86 -> -0.49091934 | M87: Checks WARN 門檻 25%
A88: R76 | B88: 分析師共識營收 FY2026（Simply Wall St） | C88: RMB 億 | E88: =SRC_ZP_582/INP_020 -> 60.48 | M88: SRC_ZP_582；Interested-party（券商交易誘因）；只對照
A89: R77 | B89: 差距：模型 2026 總額 − 共識 | C89: RMB 億 | E89: =E54-E88 -> -20.060625
A90: R78 | B90: TK：GLM-5.3 國際站輸入價 × 匯率 ÷ 本模型 2H26 Sol 人民幣輸入牌價 | C90: 倍 | L90: =TK_Link!$J$87*INP_023/L13 -> 1.1794825 | M90: Tokenomics Cap_In F 表（讀表）；國際站美元價換人民幣後對國內牌價
A91: R79 | B91: TK：GLM-5.3 國際站輸出價 × 匯率 ÷ 本模型 2H26 Sol 人民幣輸出牌價 | C91: 倍 | L91: =TK_Link!$L$87*INP_023/L15 -> 1.0591271 | M91: 同上
A92: R80 | B92: TK：中國合格前緣（Luna）混合單價 × 匯率 | C92: 元／M | L92: =TK_Link!$J$91*INP_023 -> 0.87768476 | M92: Tokenomics Price_Frontier B 表（讀表；前緣模型 GLM-5.3-Flash）；Tokenomics 參考請求混合口徑，未扣折扣
A93: R81 | B93: TK：GLM-5.3 參考請求混合單價 × 匯率 | C93: 元／M | L93: =TK_Link!$K$89*INP_023 -> 7.9261224 | M93: Tokenomics Price_Frontier A 表（讀表，Sol 參考請求）
A94: R82 | B94: 本模型 2H26 有效單價 ÷ TK 混合單價（Sol） | C94: 倍 | L94: =L20/L93 -> 0.7995713 | M94: 口徑：本模型含快取、輸出占比與折扣；只列差距
A95: R83 | B95: 本模型 2H26 有效單價 ÷ TK 中國合格前緣（Luna） | C95: 倍 | L95: =L21/L92 -> 0.92870822 | M95: 同上
A96: 七、官方分部對帳（部署方式；v0.1.2）：年報／中期公告的官方分部 vs 模型列與子項加總（差額 = 模型或子項加總 − 官方）
A97: R84 | B97: 官方分部：FY2025 本地化部署（年報） | C97: RMB 億 | D97: =SRC_ZP_121 -> 5.3396 | M97: SRC_ZP_121；官方報告分部（部署方式）
A98: R85 | B98: 模型：本地化部署分部列（②＋③＋④）2025 欄 | C98: RMB 億 | D98: =D52 -> 5.3395
A99: R86 | B99: 對帳差額：FY2025 本地化部署（模型或子項加總 − 官方） | C99: RMB 億 | D99: =D98-D97 -> -0.0001 | M99: 財報千元四捨五入至億元四位小數，容許微小差；超過 Inputs 容差即為差異
A100: R87 | B100: 判定：FY2025 本地化部署（|差額| ≤ 分部對帳容差 → OK，否則 差異） | C100: 文字 | D100: =IF(ABS(D99)<=INP_141,"OK","差異") -> OK
A101: R88 | B101: 官方分部：FY2025 雲端部署（年報） | C101: RMB 億 | D101: =SRC_ZP_122 -> 1.9038 | M101: SRC_ZP_122；官方報告分部（部署方式）
...

Sheet Compute
A1: Compute — 算力：晶片族（Hopper／H20／國產）每 GW 產能、組合、token 換算 GW、算力服務費與每 GW 價格 → 供給 GW、η、有效推論 GW、研發 GW（殘差）、容量上限、VR 等值、10 萬國產晶片對照、敏感度
A2: 規格 D6–D12、r1 D8r／D9r／D10r／D11r。產能取 TK_Link（Hopper H100 欄的 IF_TokGW_*、IF_Util）；H20、國產＝Hopper × Inputs 比例（Tokenomics 缺口）。2025、1H26：供給 GW＝算力服務費 ÷ 每 GW 價格（智譜不揭露 GW，只能由金額推）；η＝token 換算推論 GW ÷ 支出換算推論 GW。2H26 起：供給依需求配置（見第八節）。
A3: GW＝IT 關鍵電力、期間平均；半年欄（K、L）為該半年平均 GW；2026（E）＝兩個半年依天數加權。每 GW 價格 RMB 億／GW／年。token：T（兆）；產能：M tok／GW／年。
A5: 編號 | B5: 項目 | C5: 單位 | D5: 2025 | E5: 2026 | F5: 2027 | G5: 2028 | H5: 2029 | I5: 2030 | K5: 1H2026 | L5: 2H2026 | M5: 說明
B6: 年度 | D6: =INP_001 -> 2025 | E6: =INP_002 -> 2026 | F6: =INP_003 -> 2027 | G6: =INP_004 -> 2028 | H6: =INP_005 -> 2029 | I6: =INP_006 -> 2030 | K6: 1H2026（實際） | L6: 2H2026（驅動）
A7: 一、晶片族每 GW 年產能（100% 利用率；TK IF_TokGW_* Hopper H100／VR200 NVL72 基準欄；H20、國產＝Hopper × 比例）
A8: G01 | B8: Tokenomics 世代鍵：Hopper | C8: 文字 | D8: Hopper H100 | M8: TK_HdrGen 的世代名稱（文字鍵，SUMIFS 用）
A9: G02 | B9: Tokenomics 世代鍵：VR200（VR 等值基準） | C9: 文字 | D9: VR200 NVL72
A10: G03 | B10: Tokenomics 成本情境鍵：基準 | C10: 文字 | D10: 基準 | M10: TK_HdrCost（每 GW 總產出三個成本情境同值）
A11: G04 | B11: TK 每 GW 總產出：Hopper × Sol | C11: M tok/GW/年 | D11: =SUMIFS(TK_IF_TokGW_Sol,TK_HdrGen,$D$8,TK_HdrCost,$D$10) -> 3.3634916e+10 | E11: =SUMIFS(TK_IF_TokGW_Sol,TK_HdrGen,$D$8,TK_HdrCost,$D$10) -> 3.3634916e+10 | F11: =SUMIFS(TK_IF_TokGW_Sol,TK_HdrGen,$D$8,TK_HdrCost,$D$10) -> 3.3634916e+10 | G11: =SUMIFS(TK_IF_TokGW_Sol,TK_HdrGen,$D$8,TK_HdrCost,$D$10) -> 3.3634916e+10 | H11: =SUMIFS(TK_IF_TokGW_Sol,TK_HdrGen,$D$8,TK_HdrCost,$D$10) -> 3.3634916e+10 | I11: =SUMIFS(TK_IF_TokGW_Sol,TK_HdrGen,$D$8,TK_HdrCost,$D$10) -> 3.3634916e+10 | K11: =SUMIFS(TK_IF_TokGW_Sol,TK_HdrGen,$D$8,TK_HdrCost,$D$10) -> 3.3634916e+10 | L11: =SUMIFS(TK_IF_TokGW_Sol,TK_HdrGen,$D$8,TK_HdrCost,$D$10) -> 3.3634916e+10 | M11: TK IF_TokGW_Sol（Hopper H100、基準欄）
A12: G05 | B12: TK 每 GW 總產出：Hopper × Luna | C12: M tok/GW/年 | D12: =SUMIFS(TK_IF_TokGW_Luna,TK_HdrGen,$D$8,TK_HdrCost,$D$10) -> 1.1222824e+11 | E12: =SUMIFS(TK_IF_TokGW_Luna,TK_HdrGen,$D$8,TK_HdrCost,$D$10) -> 1.1222824e+11 | F12: =SUMIFS(TK_IF_TokGW_Luna,TK_HdrGen,$D$8,TK_HdrCost,$D$10) -> 1.1222824e+11 | G12: =SUMIFS(TK_IF_TokGW_Luna,TK_HdrGen,$D$8,TK_HdrCost,$D$10) -> 1.1222824e+11 | H12: =SUMIFS(TK_IF_TokGW_Luna,TK_HdrGen,$D$8,TK_HdrCost,$D$10) -> 1.1222824e+11 | I12: =SUMIFS(TK_IF_TokGW_Luna,TK_HdrGen,$D$8,TK_HdrCost,$D$10) -> 1.1222824e+11 | K12: =SUMIFS(TK_IF_TokGW_Luna,TK_HdrGen,$D$8,TK_HdrCost,$D$10) -> 1.1222824e+11 | L12: =SUMIFS(TK_IF_TokGW_Luna,TK_HdrGen,$D$8,TK_HdrCost,$D$10) -> 1.1222824e+11 | M12: TK IF_TokGW_Luna（Hopper H100、基準欄）
A13: G06 | B13: TK 每 GW 總產出：VR200 × Sol | C13: M tok/GW/年 | D13: =SUMIFS(TK_IF_TokGW_Sol,TK_HdrGen,$D$9,TK_HdrCost,$D$10) -> 3.189849e+11 | E13: =SUMIFS(TK_IF_TokGW_Sol,TK_HdrGen,$D$9,TK_HdrCost,$D$10) -> 3.189849e+11 | F13: =SUMIFS(TK_IF_TokGW_Sol,TK_HdrGen,$D$9,TK_HdrCost,$D$10) -> 3.189849e+11 | G13: =SUMIFS(TK_IF_TokGW_Sol,TK_HdrGen,$D$9,TK_HdrCost,$D$10) -> 3.189849e+11 | H13: =SUMIFS(TK_IF_TokGW_Sol,TK_HdrGen,$D$9,TK_HdrCost,$D$10) -> 3.189849e+11 | I13: =SUMIFS(TK_IF_TokGW_Sol,TK_HdrGen,$D$9,TK_HdrCost,$D$10) -> 3.189849e+11 | K13: =SUMIFS(TK_IF_TokGW_Sol,TK_HdrGen,$D$9,TK_HdrCost,$D$10) -> 3.189849e+11 | L13: =SUMIFS(TK_IF_TokGW_Sol,TK_HdrGen,$D$9,TK_HdrCost,$D$10) -> 3.189849e+11 | M13: VR 等值換算基準（同 OpenAI v0.6：Sol 層級產能比）
A14: G07 | B14: H20 產出比（÷ Hopper） | C14: 倍 | D14: =INP_082 -> 0.34 | E14: =INP_082 -> 0.34 | F14: =INP_082 -> 0.34 | G14: =INP_082 -> 0.34 | H14: =INP_082 -> 0.34 | I14: =INP_082 -> 0.34 | K14: =INP_082 -> 0.34 | L14: =INP_082 -> 0.34 | M14: Inputs（SRC_ZP_490 區間；D6）
A15: G08 | B15: 國產產出比（÷ Hopper） | C15: 倍 | D15: =INP_083 -> 0.6 | E15: =INP_083 -> 0.6 | F15: =INP_083 -> 0.6 | G15: =INP_083 -> 0.6 | H15: =INP_083 -> 0.6 | I15: =INP_083 -> 0.6 | K15: =INP_083 -> 0.6 | L15: =INP_083 -> 0.6 | M15: Inputs（D6，0.4–0.9）
A16: G09 | B16: 每 GW 總產出：Hopper（H800／A800 等；TK Hopper H100 欄） × Sol | C16: M tok/GW/年 | D16: =D11 -> 3.3634916e+10 | E16: =E11 -> 3.3634916e+10 | F16: =F11 -> 3.3634916e+10 | G16: =G11 -> 3.3634916e+10 | H16: =H11 -> 3.3634916e+10 | I16: =I11 -> 3.3634916e+10 | K16: =K11 -> 3.3634916e+10 | L16: =L11 -> 3.3634916e+10 | M16: Hopper × 產出比（Tokenomics 缺口：無 H20／昇騰欄）
A17: G10 | B17: 每 GW 總產出：Hopper（H800／A800 等；TK Hopper H100 欄） × Luna | C17: M tok/GW/年 | D17: =D12 -> 1.1222824e+11 | E17: =E12 -> 1.1222824e+11 | F17: =F12 -> 1.1222824e+11 | G17: =G12 -> 1.1222824e+11 | H17: =H12 -> 1.1222824e+11 | I17: =I12 -> 1.1222824e+11 | K17: =K12 -> 1.1222824e+11 | L17: =L12 -> 1.1222824e+11 | M17: Hopper × 產出比（Tokenomics 缺口：無 H20／昇騰欄）
A18: G11 | B18: 每 GW 總產出：H20 × Sol | C18: M tok/GW/年 | D18: =D11*D14 -> 1.1435872e+10 | E18: =E11*E14 -> 1.1435872e+10 | F18: =F11*F14 -> 1.1435872e+10 | G18: =G11*G14 -> 1.1435872e+10 | H18: =H11*H14 -> 1.1435872e+10 | I18: =I11*I14 -> 1.1435872e+10 | K18: =K11*K14 -> 1.1435872e+10 | L18: =L11*L14 -> 1.1435872e+10 | M18: Hopper × 產出比（Tokenomics 缺口：無 H20／昇騰欄）
A19: G12 | B19: 每 GW 總產出：H20 × Luna | C19: M tok/GW/年 | D19: =D12*D14 -> 3.8157602e+10 | E19: =E12*E14 -> 3.8157602e+10 | F19: =F12*F14 -> 3.8157602e+10 | G19: =G12*G14 -> 3.8157602e+10 | H19: =H12*H14 -> 3.8157602e+10 | I19: =I12*I14 -> 3.8157602e+10 | K19: =K12*K14 -> 3.8157602e+10 | L19: =L12*L14 -> 3.8157602e+10 | M19: Hopper × 產出比（Tokenomics 缺口：無 H20／昇騰欄）
A20: G13 | B20: 每 GW 總產出：國產（昇騰 910B／910C 等） × Sol | C20: M tok/GW/年 | D20: =D11*D15 -> 2.018095e+10 | E20: =E11*E15 -> 2.018095e+10 | F20: =F11*F15 -> 2.018095e+10 | G20: =G11*G15 -> 2.018095e+10 | H20: =H11*H15 -> 2.018095e+10 | I20: =I11*I15 -> 2.018095e+10 | K20: =K11*K15 -> 2.018095e+10 | L20: =L11*L15 -> 2.018095e+10 | M20: Hopper × 產出比（Tokenomics 缺口：無 H20／昇騰欄）
A21: G14 | B21: 每 GW 總產出：國產（昇騰 910B／910C 等） × Luna | C21: M tok/GW/年 | D21: =D12*D15 -> 6.7336944e+10 | E21: =E12*E15 -> 6.7336944e+10 | F21: =F12*F15 -> 6.7336944e+10 | G21: =G12*G15 -> 6.7336944e+10 | H21: =H12*H15 -> 6.7336944e+10 | I21: =I12*I15 -> 6.7336944e+10 | K21: =K12*K15 -> 6.7336944e+10 | L21: =L12*L15 -> 6.7336944e+10 | M21: Hopper × 產出比（Tokenomics 缺口：無 H20／昇騰欄）
A22: 二、晶片族組合（實體 GW 占比；D7：時變，無新 NVIDIA 採購；Hopper＝1 − 國產 − H20）
A23: G15 | B23: 國產 | C23: 比例 | D23: =INP_084 -> 0.3 | E23: =INP_085 -> 0.6 | F23: =INP_086 -> 0.75 | G23: =INP_087 -> 0.85 | H23: =INP_088 -> 0.9 | I23: =INP_089 -> 0.95 | K23: =INP_085 -> 0.6 | L23: =INP_085 -> 0.6 | M23: Inputs（Assumed；2026 起依『10 萬級國產晶片用於推論』）
A24: G16 | B24: H20 | C24: 比例 | D24: =INP_090 -> 0.2 | E24: =INP_091 -> 0.15 | F24: =INP_092 -> 0.1 | G24: =INP_093 -> 0.05 | H24: =INP_094 -> 0.05 | I24: =INP_095 -> 0 | K24: =INP_091 -> 0.15 | L24: =INP_091 -> 0.15 | M24: Inputs（Assumed）
A25: G17 | B25: Hopper（H800／A800 等） | C25: 比例 | D25: =(1-D23-D24) -> 0.5 | E25: =(1-E23-E24) -> 0.25 | F25: =(1-F23-F24) -> 0.15 | G25: =(1-G23-G24) -> 0.1 | H25: =(1-H23-H24) -> 0.05 | I25: =(1-I23-I24) -> 0.05 | K25: =(1-K23-K24) -> 0.25 | L25: =(1-L23-L24) -> 0.25 | M25: ＝1 − 國產 − H20
A26: G18 | B26: 組合產出係數（÷ Hopper）＝Σ 占比 × 產出比 | C26: 倍 | D26: =D25+D24*D14+D23*D15 -> 0.748 | E26: =E25+E24*E14+E23*E15 -> 0.661 | F26: =F25+F24*F14+F23*F15 -> 0.634 | G26: =G25+G24*G14+G23*G15 -> 0.627 | H26: =H25+H24*H14+H23*H15 -> 0.607 | I26: =I25+I24*I14+I23*I15 -> 0.62 | K26: =K25+K24*K14+K23*K15 -> 0.661 | L26: =L25+L24*L14+L23*L15 -> 0.661 | M26: 各族每 GW 產出＝Hopper × 比例，故組合產能＝Hopper 產能 × 本係數
A27: 三、token（Demand；T）：依來源（API 按量、Coding Plan、免費 API、智譜清言）× 層級（半年欄：API／Coding Plan 取 Demand 半年欄；清言為年度值 × 天數比例）
A28: G19 | B28: API 按量計費 token：Sol | C28: T | D28: =Demand!D12 -> 39.876908 | E28: =Demand!E12 -> 486.31853 | F28: =Demand!F12 -> 1258.3492 | G28: =Demand!G12 -> 2713.3154 | H28: =Demand!H12 -> 5265.5278 | I28: =Demand!I12 -> 9461.4953 | K28: =Demand!K12 -> 127.73941 | L28: =Demand!L12 -> 358.57912 | M28: Demand（api_tok_sol）
A29: G20 | B29: API 按量計費 token：Luna | C29: T | D29: =Demand!D13 -> 26.584606 | E29: =Demand!E13 -> 208.42223 | F29: =Demand!F13 -> 539.29251 | G29: =Demand!G13 -> 1162.8495 | H29: =Demand!H13 -> 2256.6548 | I29: =Demand!I13 -> 4054.9265 | K29: =Demand!K13 -> 54.745462 | L29: =Demand!L13 -> 153.67676 | M29: Demand（api_tok_luna）
A30: G21 | B30: Coding Plan token：Sol | C30: T | D30: =Demand!D27 -> 985.6356 | E30: =Demand!E27 -> 8227.1319 | F30: =Demand!F27 -> 12320.445 | G30: =Demand!G27 -> 16016.579 | H30: =Demand!H27 -> 19219.894 | I30: =Demand!I27 -> 22102.878 | K30: =Demand!K27 -> 3258.4483 | L30: =Demand!L27 -> 4968.6836 | M30: Demand（cptok_sol）
A31: G22 | B31: Coding Plan token：Luna | C31: T | D31: =Demand!D28 -> 109.51507 | E31: =Demand!E28 -> 914.12577 | F31: =Demand!F28 -> 1368.9383 | G31: =Demand!G28 -> 1779.6198 | H31: =Demand!H28 -> 2135.5438 | I31: =Demand!I28 -> 2455.8754 | K31: =Demand!K28 -> 362.04981 | L31: =Demand!L28 -> 552.07596 | M31: Demand（cptok_luna）
A32: G23 | B32: 免費 API 型號 token：Luna | C32: T | D32: =Demand!D14 -> 19.938454 | E32: =Demand!E14 -> 208.42223 | F32: =Demand!F14 -> 539.29251 | G32: =Demand!G14 -> 1162.8495 | H32: =Demand!H14 -> 2256.6548 | I32: =Demand!I14 -> 4054.9265 | K32: =Demand!K14 -> 54.745462 | L32: =Demand!L14 -> 153.67676 | M32: Demand（api_free）
A33: G24 | B33: 智譜清言 token：Sol | C33: T | D33: =Demand!D32 -> 3.285 | E33: =K33+L33 -> 3.6135 | F33: =Demand!F32 -> 3.97485 | G33: =Demand!G32 -> 4.372335 | H33: =Demand!H32 -> 4.8095685 | I33: =Demand!I32 -> 5.2905254 | K33: =Demand!$E$32*INP_008/INP_007 -> 1.7919 | L33: =Demand!$E$32*INP_009/INP_007 -> 1.8216 | M33: Demand（qy_sol）
A34: G25 | B34: 智譜清言 token：Luna | C34: T | D34: =Demand!D33 -> 7.665 | E34: =K34+L34 -> 8.4315 | F34: =Demand!F33 -> 9.27465 | G34: =Demand!G33 -> 10.202115 | H34: =Demand!H33 -> 11.222326 | I34: =Demand!I33 -> 12.344559 | K34: =Demand!$E$33*INP_008/INP_007 -> 4.1811 | L34: =Demand!$E$33*INP_009/INP_007 -> 4.2504 | M34: Demand（qy_luna）
A35: G26 | B35: 付費 token：Sol | C35: T | D35: =D28+D30 -> 1025.5125 | E35: =E28+E30 -> 8713.4504 | F35: =F28+F30 -> 13578.794 | G35: =G28+G30 -> 18729.894 | H35: =H28+H30 -> 24485.422 | I35: =I28+I30 -> 31564.374 | K35: =K28+K30 -> 3386.1877 | L35: =L28+L30 -> 5327.2627 | M35: ＝Demand DEM_Tok_*
A36: G27 | B36: 付費 token：Luna | C36: T | D36: =D29+D31 -> 136.09967 | E36: =E29+E31 -> 1122.548 | F36: =F29+F31 -> 1908.2309 | G36: =G29+G31 -> 2942.4693 | H36: =H29+H31 -> 4392.1986 | I36: =I29+I31 -> 6510.8019 | K36: =K29+K31 -> 416.79527 | L36: =L29+L31 -> 705.75272 | M36: ＝Demand DEM_Tok_*
A37: G28 | B37: 免費 token：Sol | C37: T | D37: =D33 -> 3.285 | E37: =E33 -> 3.6135 | F37: =F33 -> 3.97485 | G37: =G33 -> 4.372335 | H37: =H33 -> 4.8095685 | I37: =I33 -> 5.2905254 | K37: =K33 -> 1.7919 | L37: =L33 -> 1.8216 | M37: ＝Demand DEM_Tok_*
A38: G29 | B38: 免費 token：Luna | C38: T | D38: =D32+D34 -> 27.603454 | E38: =E32+E34 -> 216.85373 | F38: =F32+F34 -> 548.56716 | G38: =G32+G34 -> 1173.0516 | H38: =H32+H34 -> 2267.8771 | I38: =I32+I34 -> 4067.2711 | K38: =K32+K34 -> 58.926562 | L38: =L32+L34 -> 157.92716 | M38: ＝Demand DEM_Tok_*
A39: G30 | B39: 付費 token 合計 | C39: T | D39: =D35+D36 -> 1161.6122 | E39: =E35+E36 -> 9835.9984 | F39: =F35+F36 -> 15487.025 | G39: =G35+G36 -> 21672.363 | H39: =H35+H36 -> 28877.621 | I39: =I35+I36 -> 38075.176 | K39: =K35+K36 -> 3802.983 | L39: =L35+L36 -> 6033.0154
A40: G31 | B40: 付費：Sol 占比 | C40: 比例 | D40: =D35/D39 -> 0.88283553 | E40: =E35/E39 -> 0.88587351 | F40: =F35/F39 -> 0.87678519 | G40: =G35/G39 -> 0.86422942 | H40: =H35/H39 -> 0.84790303 | I40: =I35/I39 -> 0.82900139 | K40: =K35/K39 -> 0.89040307 | L40: =L35/L39 -> 0.88301825
A41: G32 | B41: 付費：Luna 占比 | C41: 比例 | D41: =D36/D39 -> 0.11716447 | E41: =E36/E39 -> 0.11412649 | F41: =F36/F39 -> 0.12321481 | G41: =G36/G39 -> 0.13577058 | H41: =H36/H39 -> 0.15209697 | I41: =I36/I39 -> 0.17099861 | K41: =K36/K39 -> 0.10959693 | L41: =L36/L39 -> 0.11698175
A42: G33 | B42: 免費 token 合計 | C42: T | D42: =D37+D38 -> 30.888454 | E42: =E37+E38 -> 220.46723 | F42: =F37+F38 -> 552.54201 | G42: =G37+G38 -> 1177.4239 | H42: =H37+H38 -> 2272.6867 | I42: =I37+I38 -> 4072.5616 | K42: =K37+K38 -> 60.718462 | L42: =L37+L38 -> 159.74876
A43: G34 | B43: 免費：Sol 占比 | C43: 比例 | D43: =D37/D42 -> 0.10635042 | E43: =E37/E42 -> 0.016390191 | F43: =F37/F42 -> 0.0071937516 | G43: =G37/G42 -> 0.0037134756 | H43: =H37/H42 -> 0.002116248 | I43: =I37/I42 -> 0.0012990658 | K43: =K37/K42 -> 0.029511617 | L43: =L37/L42 -> 0.011402905
A44: G35 | B44: 免費：Luna 占比 | C44: 比例 | D44: =D38/D42 -> 0.89364958 | E44: =E38/E42 -> 0.98360981 | F44: =F38/F42 -> 0.99280625 | G44: =G38/G42 -> 0.99628652 | H44: =H38/H42 -> 0.99788375 | I44: =I38/I42 -> 0.99870093 | K44: =K38/K42 -> 0.97048838 | L44: =L38/L42 -> 0.98859709
A45: 四、token 換算推論 GW（Z3b F1）＝Σ token × 類型組成 × TK 逐類型單位成本（Hopper 基準欄，經濟、100% 利用率）÷ TK IF_HoldEcon（Hopper，100% 時數）÷ IF_Util ÷ 組合產出係數
A46: G36 | B46: TK 單位成本：Hopper × Sol × 新鮮 prefill | C46: $/M | D46: =SUMIFS(TK_IF_CostPre_Sol,TK_HdrGen,$D$8,TK_HdrCost,$D$10) -> 0.19178019 | E46: =SUMIFS(TK_IF_CostPre_Sol,TK_HdrGen,$D$8,TK_HdrCost,$D$10) -> 0.19178019 | F46: =SUMIFS(TK_IF_CostPre_Sol,TK_HdrGen,$D$8,TK_HdrCost,$D$10) -> 0.19178019 | G46: =SUMIFS(TK_IF_CostPre_Sol,TK_HdrGen,$D$8,TK_HdrCost,$D$10) -> 0.19178019 | H46: =SUMIFS(TK_IF_CostPre_Sol,TK_HdrGen,$D$8,TK_HdrCost,$D$10) -> 0.19178019 | I46: =SUMIFS(TK_IF_CostPre_Sol,TK_HdrGen,$D$8,TK_HdrCost,$D$10) -> 0.19178019 | K46: =SUMIFS(TK_IF_CostPre_Sol,TK_HdrGen,$D$8,TK_HdrCost,$D$10) -> 0.19178019 | L46: =SUMIFS(TK_IF_CostPre_Sol,TK_HdrGen,$D$8,TK_HdrCost,$D$10) -> 0.19178019 | M46: TK IF_CostPre_Sol（經濟、100%；Hopper H100 基準欄）
A47: G37 | B47: TK 單位成本：Hopper × Sol × 快取命中 prefill | C47: $/M | D47: =SUMIFS(TK_IF_CostCache_Sol,TK_HdrGen,$D$8,TK_HdrCost,$D$10) -> 1.6989987e-05 | E47: =SUMIFS(TK_IF_CostCache_Sol,TK_HdrGen,$D$8,TK_HdrCost,$D$10) -> 1.6989987e-05 | F47: =SUMIFS(TK_IF_CostCache_Sol,TK_HdrGen,$D$8,TK_HdrCost,$D$10) -> 1.6989987e-05 | G47: =SUMIFS(TK_IF_CostCache_Sol,TK_HdrGen,$D$8,TK_HdrCost,$D$10) -> 1.6989987e-05 | H47: =SUMIFS(TK_IF_CostCache_Sol,TK_HdrGen,$D$8,TK_HdrCost,$D$10) -> 1.6989987e-05 | I47: =SUMIFS(TK_IF_CostCache_Sol,TK_HdrGen,$D$8,TK_HdrCost,$D$10) -> 1.6989987e-05 | K47: =SUMIFS(TK_IF_CostCache_Sol,TK_HdrGen,$D$8,TK_HdrCost,$D$10) -> 1.6989987e-05 | L47: =SUMIFS(TK_IF_CostCache_Sol,TK_HdrGen,$D$8,TK_HdrCost,$D$10) -> 1.6989987e-05 | M47: TK IF_CostCache_Sol（經濟、100%；Hopper H100 基準欄）
A48: G38 | B48: TK 單位成本：Hopper × Sol × decode | C48: $/M | D48: =SUMIFS(TK_IF_CostDec_Sol,TK_HdrGen,$D$8,TK_HdrCost,$D$10) -> 1.9059345 | E48: =SUMIFS(TK_IF_CostDec_Sol,TK_HdrGen,$D$8,TK_HdrCost,$D$10) -> 1.9059345 | F48: =SUMIFS(TK_IF_CostDec_Sol,TK_HdrGen,$D$8,TK_HdrCost,$D$10) -> 1.9059345 | G48: =SUMIFS(TK_IF_CostDec_Sol,TK_HdrGen,$D$8,TK_HdrCost,$D$10) -> 1.9059345 | H48: =SUMIFS(TK_IF_CostDec_Sol,TK_HdrGen,$D$8,TK_HdrCost,$D$10) -> 1.9059345 | I48: =SUMIFS(TK_IF_CostDec_Sol,TK_HdrGen,$D$8,TK_HdrCost,$D$10) -> 1.9059345 | K48: =SUMIFS(TK_IF_CostDec_Sol,TK_HdrGen,$D$8,TK_HdrCost,$D$10) -> 1.9059345 | L48: =SUMIFS(TK_IF_CostDec_Sol,TK_HdrGen,$D$8,TK_HdrCost,$D$10) -> 1.9059345 | M48: TK IF_CostDec_Sol（經濟、100%；Hopper H100 基準欄）
A49: G39 | B49: TK 單位成本：Hopper × Luna × 新鮮 prefill | C49: $/M | D49: =SUMIFS(TK_IF_CostPre_Luna,TK_HdrGen,$D$8,TK_HdrCost,$D$10) -> 0.055255459 | E49: =SUMIFS(TK_IF_CostPre_Luna,TK_HdrGen,$D$8,TK_HdrCost,$D$10) -> 0.055255459 | F49: =SUMIFS(TK_IF_CostPre_Luna,TK_HdrGen,$D$8,TK_HdrCost,$D$10) -> 0.055255459 | G49: =SUMIFS(TK_IF_CostPre_Luna,TK_HdrGen,$D$8,TK_HdrCost,$D$10) -> 0.055255459 | H49: =SUMIFS(TK_IF_CostPre_Luna,TK_HdrGen,$D$8,TK_HdrCost,$D$10) -> 0.055255459 | I49: =SUMIFS(TK_IF_CostPre_Luna,TK_HdrGen,$D$8,TK_HdrCost,$D$10) -> 0.055255459 | K49: =SUMIFS(TK_IF_CostPre_Luna,TK_HdrGen,$D$8,TK_HdrCost,$D$10) -> 0.055255459 | L49: =SUMIFS(TK_IF_CostPre_Luna,TK_HdrGen,$D$8,TK_HdrCost,$D$10) -> 0.055255459 | M49: TK IF_CostPre_Luna（經濟、100%；Hopper H100 基準欄）
A50: G40 | B50: TK 單位成本：Hopper × Luna × 快取命中 prefill | C50: $/M | D50: =SUMIFS(TK_IF_CostCache_Luna,TK_HdrGen,$D$8,TK_HdrCost,$D$10) -> 1.1976548e-05 | E50: =SUMIFS(TK_IF_CostCache_Luna,TK_HdrGen,$D$8,TK_HdrCost,$D$10) -> 1.1976548e-05 | F50: =SUMIFS(TK_IF_CostCache_Luna,TK_HdrGen,$D$8,TK_HdrCost,$D$10) -> 1.1976548e-05 | G50: =SUMIFS(TK_IF_CostCache_Luna,TK_HdrGen,$D$8,TK_HdrCost,$D$10) -> 1.1976548e-05 | H50: =SUMIFS(TK_IF_CostCache_Luna,TK_HdrGen,$D$8,TK_HdrCost,$D$10) -> 1.1976548e-05 | I50: =SUMIFS(TK_IF_CostCache_Luna,TK_HdrGen,$D$8,TK_HdrCost,$D$10) -> 1.1976548e-05 | K50: =SUMIFS(TK_IF_CostCache_Luna,TK_HdrGen,$D$8,TK_HdrCost,$D$10) -> 1.1976548e-05 | L50: =SUMIFS(TK_IF_CostCache_Luna,TK_HdrGen,$D$8,TK_HdrCost,$D$10) -> 1.1976548e-05 | M50: TK IF_CostCache_Luna（經濟、100%；Hopper H100 基準欄）
A51: G41 | B51: TK 單位成本：Hopper × Luna × decode | C51: $/M | D51: =SUMIFS(TK_IF_CostDec_Luna,TK_HdrGen,$D$8,TK_HdrCost,$D$10) -> 0.579207 | E51: =SUMIFS(TK_IF_CostDec_Luna,TK_HdrGen,$D$8,TK_HdrCost,$D$10) -> 0.579207 | F51: =SUMIFS(TK_IF_CostDec_Luna,TK_HdrGen,$D$8,TK_HdrCost,$D$10) -> 0.579207 | G51: =SUMIFS(TK_IF_CostDec_Luna,TK_HdrGen,$D$8,TK_HdrCost,$D$10) -> 0.579207 | H51: =SUMIFS(TK_IF_CostDec_Luna,TK_HdrGen,$D$8,TK_HdrCost,$D$10) -> 0.579207 | I51: =SUMIFS(TK_IF_CostDec_Luna,TK_HdrGen,$D$8,TK_HdrCost,$D$10) -> 0.579207 | K51: =SUMIFS(TK_IF_CostDec_Luna,TK_HdrGen,$D$8,TK_HdrCost,$D$10) -> 0.579207 | L51: =SUMIFS(TK_IF_CostDec_Luna,TK_HdrGen,$D$8,TK_HdrCost,$D$10) -> 0.579207 | M51: TK IF_CostDec_Luna（經濟、100%；Hopper H100 基準欄）
A52: G42 | B52: TK 每 GW 年持有成本：Hopper（經濟） | C52: $B／GW／年 | D52: =SUMIFS(TK_IF_HoldEcon,TK_HdrGen,$D$8,TK_HdrCost,$D$10) -> 9.7030873 | E52: =SUMIFS(TK_IF_HoldEcon,TK_HdrGen,$D$8,TK_HdrCost,$D$10) -> 9.7030873 | F52: =SUMIFS(TK_IF_HoldEcon,TK_HdrGen,$D$8,TK_HdrCost,$D$10) -> 9.7030873 | G52: =SUMIFS(TK_IF_HoldEcon,TK_HdrGen,$D$8,TK_HdrCost,$D$10) -> 9.7030873 | H52: =SUMIFS(TK_IF_HoldEcon,TK_HdrGen,$D$8,TK_HdrCost,$D$10) -> 9.7030873 | I52: =SUMIFS(TK_IF_HoldEcon,TK_HdrGen,$D$8,TK_HdrCost,$D$10) -> 9.7030873 | K52: =SUMIFS(TK_IF_HoldEcon,TK_HdrGen,$D$8,TK_HdrCost,$D$10) -> 9.7030873 | L52: =SUMIFS(TK_IF_HoldEcon,TK_HdrGen,$D$8,TK_HdrCost,$D$10) -> 9.7030873 | M52: 與單位成本同為經濟口徑、100% 時數（單位成本＝每 GPU 小時持有成本 × 每 M token GPU 時間），兩者相除＝100% 利用率下所需 GW
A53: G43 | B53: 類型組成：API 按量／免費 API／清言（沿用 API 快取命中、輸出占比）：新鮮輸入 | C53: 比例 | D53: =(1-INP_029)*(1-INP_030) -> 0.425 | E53: =(1-INP_029)*(1-INP_030) -> 0.425 | F53: =(1-INP_029)*(1-INP_030) -> 0.425 | G53: =(1-INP_029)*(1-INP_030) -> 0.425 | H53: =(1-INP_029)*(1-INP_030) -> 0.425 | I53: =(1-INP_029)*(1-INP_030) -> 0.425 | K53: =(1-INP_029)*(1-INP_030) -> 0.425 | L53: =(1-INP_029)*(1-INP_030) -> 0.425 | M53: (1−輸出占比)×(1−快取命中)
A54: G44 | B54: 類型組成：API 按量／免費 API／清言（沿用 API 快取命中、輸出占比）：快取命中輸入 | C54: 比例 | D54: =(1-INP_029)*INP_030 -> 0.425 | E54: =(1-INP_029)*INP_030 -> 0.425 | F54: =(1-INP_029)*INP_030 -> 0.425 | G54: =(1-INP_029)*INP_030 -> 0.425 | H54: =(1-INP_029)*INP_030 -> 0.425 | I54: =(1-INP_029)*INP_030 -> 0.425 | K54: =(1-INP_029)*INP_030 -> 0.425 | L54: =(1-INP_029)*INP_030 -> 0.425 | M54: (1−輸出占比)×快取命中
A55: G45 | B55: 類型組成：API 按量／免費 API／清言（沿用 API 快取命中、輸出占比）：輸出 | C55: 比例 | D55: =INP_029 -> 0.15 | E55: =INP_029 -> 0.15 | F55: =INP_029 -> 0.15 | G55: =INP_029 -> 0.15 | H55: =INP_029 -> 0.15 | I55: =INP_029 -> 0.15 | K55: =INP_029 -> 0.15 | L55: =INP_029 -> 0.15 | M55: 輸出占比
A56: G46 | B56: 加權單位成本：API 按量／免費 API／清言（沿用 API 快取命中、輸出占比） × Sol | C56: $/M | D56: =D53*D46+D54*D47+D55*D48 -> 0.36740398 | E56: =E53*E46+E54*E47+E55*E48 -> 0.36740398 | F56: =F53*F46+F54*F47+F55*F48 -> 0.36740398 | G56: =G53*G46+G54*G47+G55*G48 -> 0.36740398 | H56: =H53*H46+H54*H47+H55*H48 -> 0.36740398 | I56: =I53*I46+I54*I47+I55*I48 -> 0.36740398 | K56: =K53*K46+K54*K47+K55*K48 -> 0.36740398 | L56: =L53*L46+L54*L47+L55*L48 -> 0.36740398 | M56: Hopper、100%
A57: G47 | B57: 加權單位成本：API 按量／免費 API／清言（沿用 API 快取命中、輸出占比） × Luna | C57: $/M | D57: =D53*D49+D54*D50+D55*D51 -> 0.11036971 | E57: =E53*E49+E54*E50+E55*E51 -> 0.11036971 | F57: =F53*F49+F54*F50+F55*F51 -> 0.11036971 | G57: =G53*G49+G54*G50+G55*G51 -> 0.11036971 | H57: =H53*H49+H54*H50+H55*H51 -> 0.11036971 | I57: =I53*I49+I54*I50+I55*I51 -> 0.11036971 | K57: =K53*K49+K54*K50+K55*K51 -> 0.11036971 | L57: =L53*L49+L54*L50+L55*L51 -> 0.11036971 | M57: Hopper、100%
A58: G48 | B58: 類型組成：Coding Plan（Inputs 快取命中 0.9、輸出 0.03）：新鮮輸入 | C58: 比例 | D58: =(1-INP_123)*(1-INP_122) -> 0.097 | E58: =(1-INP_123)*(1-INP_122) -> 0.097 | F58: =(1-INP_123)*(1-INP_122) -> 0.097 | G58: =(1-INP_123)*(1-INP_122) -> 0.097 | H58: =(1-INP_123)*(1-INP_122) -> 0.097 | I58: =(1-INP_123)*(1-INP_122) -> 0.097 | K58: =(1-INP_123)*(1-INP_122) -> 0.097 | L58: =(1-INP_123)*(1-INP_122) -> 0.097 | M58: (1−輸出占比)×(1−快取命中)
A59: G49 | B59: 類型組成：Coding Plan（Inputs 快取命中 0.9、輸出 0.03）：快取命中輸入 | C59: 比例 | D59: =(1-INP_123)*INP_122 -> 0.873 | E59: =(1-INP_123)*INP_122 -> 0.873 | F59: =(1-INP_123)*INP_122 -> 0.873 | G59: =(1-INP_123)*INP_122 -> 0.873 | H59: =(1-INP_123)*INP_122 -> 0.873 | I59: =(1-INP_123)*INP_122 -> 0.873 | K59: =(1-INP_123)*INP_122 -> 0.873 | L59: =(1-INP_123)*INP_122 -> 0.873 | M59: (1−輸出占比)×快取命中
A60: G50 | B60: 類型組成：Coding Plan（Inputs 快取命中 0.9、輸出 0.03）：輸出 | C60: 比例 | D60: =INP_123 -> 0.03 | E60: =INP_123 -> 0.03 | F60: =INP_123 -> 0.03 | G60: =INP_123 -> 0.03 | H60: =INP_123 -> 0.03 | I60: =INP_123 -> 0.03 | K60: =INP_123 -> 0.03 | L60: =INP_123 -> 0.03 | M60: 輸出占比
A61: G51 | B61: 加權單位成本：Coding Plan（Inputs 快取命中 0.9、輸出 0.03） × Sol | C61: $/M | D61: =D58*D46+D59*D47+D60*D48 -> 0.075795546 | E61: =E58*E46+E59*E47+E60*E48 -> 0.075795546 | F61: =F58*F46+F59*F47+F60*F48 -> 0.075795546 | G61: =G58*G46+G59*G47+G60*G48 -> 0.075795546 | H61: =H58*H46+H59*H47+H60*H48 -> 0.075795546 | I61: =I58*I46+I59*I47+I60*I48 -> 0.075795546 | K61: =K58*K46+K59*K47+K60*K48 -> 0.075795546 | L61: =L58*L46+L59*L47+L60*L48 -> 0.075795546 | M61: Hopper、100%
A62: G52 | B62: 加權單位成本：Coding Plan（Inputs 快取命中 0.9、輸出 0.03） × Luna | C62: $/M | D62: =D58*D49+D59*D50+D60*D51 -> 0.022746445 | E62: =E58*E49+E59*E50+E60*E51 -> 0.022746445 | F62: =F58*F49+F59*F50+F60*F51 -> 0.022746445 | G62: =G58*G49+G59*G50+G60*G51 -> 0.022746445 | H62: =H58*H49+H59*H50+H60*H51 -> 0.022746445 | I62: =I58*I49+I59*I50+I60*I51 -> 0.022746445 | K62: =K58*K49+K59*K50+K60*K51 -> 0.022746445 | L62: =L58*L49+L59*L50+L60*L51 -> 0.022746445 | M62: Hopper、100%
A63: G53 | B63: 推論 GW（token 換算）：付費 | C63: GW | D63: =(D28*D56+D29*D57+D30*D61+D31*D62)*INP_074/(D52*INP_078*TK_IF_Util*D26) -> 0.021765436 | E63: =(K63*INP_008+L63*INP_009)/INP_007 -> 0.219854 | F63: =(F28*F56+F29*F57+F30*F61+F31*F62)*INP_074/(F52*INP_078*TK_IF_Util*F26) -> 0.40281644 | G63: =(G28*G56+G29*G57+G30*G61+G31*G62)*INP_074/(G52*INP_078*TK_IF_Util*G26) -> 0.65191646 | H63: =(H28*H56+H29*H57+H30*H61+H31*H62)*INP_074/(H52*INP_078*TK_IF_Util*H26) -> 1.0438999 | I63: =(I28*I56+I29*I57+I30*I61+I31*I62)*INP_074/(I52*INP_078*TK_IF_Util*I26) -> 1.5666486 | K63: =(K28*K56+K29*K57+K30*K61+K31*K62)*INP_074/((K52*INP_078*TK_IF_Util*K26)*INP_008/INP_007) -> 0.16149673 | L63: =(L28*L56+L29*L57+L30*L61+L31*L62)*INP_074/((L52*INP_078*TK_IF_Util*L26)*INP_009/INP_007) -> 0.27725979 | M63: Σ token（T）× 10^6 × 加權單位成本 ÷（持有成本 × 10^9 × IF_Util × 組合產出係數 × 期間比例）；國產、H20 每 GW 產出＝Hopper × 產出比（持有比在成本與持有成本兩端相消）
A64: G54 | B64: 推論 GW（token 換算）：免費 | C64: GW | D64: =(D32*D57+D33*D56+D34*D57)*INP_074/(D52*INP_078*TK_IF_Util*D26) -> 0.0009767522 | E64: =(K64*INP_008+L64*INP_009)/INP_007 -> 0.0065644732 | F64: =(F32*F57+F33*F56+F34*F57)*INP_074/(F52*INP_078*TK_IF_Util*F26) -> 0.016798879 | G64: =(G32*G57+G33*G56+G34*G57)*INP_074/(G52*INP_078*TK_IF_Util*G26) -> 0.035908207 | H64: =(H32*H57+H33*H56+H34*H57)*INP_074/(H52*INP_078*TK_IF_Util*H26) -> 0.071330409 | I64: =(I32*I57+I33*I56+I34*I57)*INP_074/(I52*INP_078*TK_IF_Util*I26) -> 0.12490407 | K64: =(K32*K57+K33*K56+K34*K57)*INP_074/((K52*INP_078*TK_IF_Util*K26)*INP_008/INP_007) -> 0.0037530947 | L64: =(L32*L57+L33*L56+L34*L57)*INP_074/((L52*INP_078*TK_IF_Util*L26)*INP_009/INP_007) -> 0.009330014 | M64: Σ token（T）× 10^6 × 加權單位成本 ÷（持有成本 × 10^9 × IF_Util × 組合產出係數 × 期間比例）；國產、H20 每 GW 產出＝Hopper × 產出比（持有比在成本與持有成本兩端相消）
A65: G55 | B65: 推論 GW（token 換算）：合計 | C65: GW | D65: =D63+D64 -> 0.022742188 | E65: =E63+E64 -> 0.22641847 | F65: =F63+F64 -> 0.41961532 | G65: =G63+G64 -> 0.68782466 | H65: =H63+H64 -> 1.1152303 | I65: =I63+I64 -> 1.6915527 | K65: =K63+K64 -> 0.16524982 | L65: =L63+L64 -> 0.28658981
A66: G56 | B66: 其中 Coding Plan | C66: GW | D66: =(D30*D61+D31*D62)*INP_074/(D52*INP_078*TK_IF_Util*D26) -> 0.017727297 | E66: =(K66*INP_008+L66*INP_009)/INP_007 -> 0.16744598 | F66: =(F30*F61+F31*F62)*INP_074/(F52*INP_078*TK_IF_Util*F26) -> 0.26143568 | G66: =(G30*G61+G31*G62)*INP_074/(G52*INP_078*TK_IF_Util*G26) -> 0.34366075 | H66: =(H30*H61+H31*H62)*INP_074/(H52*INP_078*TK_IF_Util*H26) -> 0.42598081 | I66: =(I30*I61+I31*I62)*INP_074/(I52*INP_078*TK_IF_Util*I26) -> 0.47960629 | K66: =(K30*K61+K31*K62)*INP_074/((K52*INP_078*TK_IF_Util*K26)*INP_008/INP_007) -> 0.13373694 | L66: =(L30*L61+L31*L62)*INP_074/((L52*INP_078*TK_IF_Util*L26)*INP_009/INP_007) -> 0.20060542 | M66: R4 對帳用
A67: 四之一、對照：舊法（Z3）＝token ÷ 參考請求組合每 GW 年產能（TK IF_TokGW × IF_Util；Z3b F3：只列，不進計算鏈）
A68: G57 | B68: 舊法：付費每 GW 年產能：Hopper（H800／A800 等；TK Hopper H100 欄） | C68: M tok/GW/年 | D68: =TK_IF_Util/(D40/D16+D41/D17) -> 2.1984807e+10 | E68: =TK_IF_Util/(E40/E16+E41/E17) -> 2.1933971e+10 | F68: =TK_IF_Util/(F40/F16+F41/F17) -> 2.2086754e+10 | G68: =TK_IF_Util/(G40/G16+G41/G17) -> 2.2301363e+10 | H68: =TK_IF_Util/(H40/H16+H41/H17) -> 2.2586739e+10 | I68: =TK_IF_Util/(I40/I16+I41/I17) -> 2.2926388e+10 | K68: =TK_IF_Util/(K40/K16+K41/K17) -> 2.1858612e+10 | L68: =TK_IF_Util/(L40/L16+L41/L17) -> 2.1981743e+10
A69: G58 | B69: 舊法：付費每 GW 年產能：H20 | C69: M tok/GW/年 | D69: =TK_IF_Util/(D40/D18+D41/D19) -> 7.4748343e+09 | E69: =TK_IF_Util/(E40/E18+E41/E19) -> 7.4575502e+09 | F69: =TK_IF_Util/(F40/F18+F41/F19) -> 7.5094964e+09 | G69: =TK_IF_Util/(G40/G18+G41/G19) -> 7.5824636e+09 | H69: =TK_IF_Util/(H40/H18+H41/H19) -> 7.6794913e+09 | I69: =TK_IF_Util/(I40/I18+I41/I19) -> 7.794972e+09 | K69: =TK_IF_Util/(K40/K18+K41/K19) -> 7.431928e+09 | L69: =TK_IF_Util/(L40/L18+L41/L19) -> 7.4737925e+09
A70: G59 | B70: 舊法：付費每 GW 年產能：國產（昇騰 910B／910C 等） | C70: M tok/GW/年 | D70: =TK_IF_Util/(D40/D20+D41/D21) -> 1.3190884e+10 | E70: =TK_IF_Util/(E40/E20+E41/E21) -> 1.3160383e+10 | F70: =TK_IF_Util/(F40/F20+F41/F21) -> 1.3252052e+10 | G70: =TK_IF_Util/(G40/G20+G41/G21) -> 1.3380818e+10 | H70: =TK_IF_Util/(H40/H20+H41/H21) -> 1.3552043e+10 | I70: =TK_IF_Util/(I40/I20+I41/I21) -> 1.3755833e+10 | K70: =TK_IF_Util/(K40/K20+K41/K21) -> 1.3115167e+10 | L70: =TK_IF_Util/(L40/L20+L41/L21) -> 1.3189046e+10
A71: G60 | B71: 舊法：付費每 GW 年產能：組合後 | C71: M tok/GW/年 | D71: =D25*D68+D24*D69+D23*D70 -> 1.6444635e+10 | E71: =E25*E68+E24*E69+E23*E70 -> 1.4498355e+10 | F71: =F25*F68+F24*F69+F23*F70 -> 1.4003002e+10 | G71: =G25*G68+G24*G69+G23*G70 -> 1.3982955e+10 | H71: =H25*H68+H24*H69+H23*H70 -> 1.3710151e+10 | I71: =I25*I68+I24*I69+I23*I70 -> 1.4214361e+10 | K71: =K25*K68+K24*K69+K23*K70 -> 1.4448542e+10 | L71: =L25*L68+L24*L69+L23*L70 -> 1.4529932e+10 | M71: Σ 晶片族占比 × 各族產能
A72: G61 | B72: 舊法：免費每 GW 年產能：Hopper（H800／A800 等；TK Hopper H100 欄） | C72: M tok/GW/年 | D72: =TK_IF_Util/(D43/D16+D44/D17) -> 5.3934076e+10 | E72: =TK_IF_Util/(E43/E16+E44/E17) -> 6.4853179e+10 | F72: =TK_IF_Util/(F43/F16+F44/F17) -> 6.6223766e+10 | G72: =TK_IF_Util/(G43/G16+G44/G17) -> 6.675768e+10 | H72: =TK_IF_Util/(H43/H16+H44/H17) -> 6.7005605e+10 | I72: =TK_IF_Util/(I43/I16+I44/I17) -> 6.7133163e+10 | K72: =TK_IF_Util/(K43/K16+K44/K17) -> 6.2993034e+10 | L72: =TK_IF_Util/(L43/L16+L44/L17) -> 6.5589336e+10
A73: G62 | B73: 舊法：免費每 GW 年產能：H20 | C73: M tok/GW/年 | D73: =TK_IF_Util/(D43/D18+D44/D19) -> 1.8337586e+10 | E73: =TK_IF_Util/(E43/E18+E44/E19) -> 2.2050081e+10 | F73: =TK_IF_Util/(F43/F18+F44/F19) -> 2.2516081e+10 | G73: =TK_IF_Util/(G43/G18+G44/G19) -> 2.2697611e+10 | H73: =TK_IF_Util/(H43/H18+H44/H19) -> 2.2781906e+10 | I73: =TK_IF_Util/(I43/I18+I44/I19) -> 2.2825276e+10 | K73: =TK_IF_Util/(K43/K18+K44/K19) -> 2.1417632e+10 | L73: =TK_IF_Util/(L43/L18+L44/L19) -> 2.2300374e+10
A74: G63 | B74: 舊法：免費每 GW 年產能：國產（昇騰 910B／910C 等） | C74: M tok/GW/年 | D74: =TK_IF_Util/(D43/D20+D44/D21) -> 3.2360446e+10 | E74: =TK_IF_Util/(E43/E20+E44/E21) -> 3.8911907e+10 | F74: =TK_IF_Util/(F43/F20+F44/F21) -> 3.973426e+10 | G74: =TK_IF_Util/(G43/G20+G44/G21) -> 4.0054608e+10 | H74: =TK_IF_Util/(H43/H20+H44/H21) -> 4.0203363e+10 | I74: =TK_IF_Util/(I43/I20+I44/I21) -> 4.0279898e+10 | K74: =TK_IF_Util/(K43/K20+K44/K21) -> 3.779582e+10 | L74: =TK_IF_Util/(L43/L20+L44/L21) -> 3.9353602e+10
A75: G64 | B75: 舊法：免費每 GW 年產能：組合後 | C75: M tok/GW/年 | D75: =D25*D72+D24*D73+D23*D74 -> 4.0342689e+10 | E75: =E25*E72+E24*E73+E23*E74 -> 4.2867951e+10 | F75: =F25*F72+F24*F73+F23*F74 -> 4.1985868e+10 | G75: =G25*G72+G24*G73+G23*G74 -> 4.1857065e+10 | H75: =H25*H72+H24*H73+H23*H74 -> 4.0672402e+10 | I75: =I25*I72+I24*I73+I23*I74 -> 4.1622561e+10 | K75: =K25*K72+K24*K73+K23*K74 -> 4.1638396e+10 | L75: =L25*L72+L24*L73+L23*L74 -> 4.3354551e+10 | M75: Σ 晶片族占比 × 各族產能
A76: G65 | B76: 舊法：token 換算推論 GW（合計） | C76: GW | D76: =(D39*INP_074/D71)+(D42*INP_074/D75) -> 0.071403411 | E76: =(K76*INP_008+L76*INP_009)/INP_007 -> 0.68356462 | F76: =(F39*INP_074/F71)+(F42*INP_074/F75) -> 1.1191391 | G76: =(G39*INP_074/G71)+(G42*INP_074/G75) -> 1.5780426 | H76: =(H39*INP_074/H71)+(H42*INP_074/H75) -> 2.1621728 | I76: =(I39*INP_074/I71)+(I42*INP_074/I75) -> 2.7764865 | K76: =(K39*INP_074/(K71*INP_008/INP_007))+(K42*INP_074/(K75*INP_008/INP_007)) -> 0.53372074 | L76: =(L39*INP_074/(L71*INP_009/INP_007))+(L42*INP_074/(L75*INP_009/INP_007)) -> 0.8309654 | M76: Z3 原式
A77: G66 | B77: 新法 ÷ 舊法 | C77: 倍 | D77: =D65/D76 -> 0.31850283 | E77: =E65/E76 -> 0.33123199 | F77: =F65/F76 -> 0.37494474 | G77: =G65/G76 -> 0.43587205 | H77: =H65/H76 -> 0.51579147 | I77: =I65/I76 -> 0.60924219 | K77: =K65/K76 -> 0.30961852 | L77: =L65/L76 -> 0.34488777 | M77: 類型加權使快取命中為主的流量所需 GW 大幅下降
A78: 五、算力服務費（財報推得；RMB 億；2025 年報、1H26 中期公告）：r2 P1：總算力費＝營業成本中的計算服務費（推估＝開放平台及 API 銷售成本 × 占比）＋研發項下算力費（研發開支 × 1H25 占比 71.8%）；推論與研發不再以會計科目拆分（招股章程第 255 頁：研發算力費涵蓋訓練、推理及持續開發）
A79: G67 | B79: 開放平台及 API 銷售成本（推算） | C79: RMB 億 | D79: =SRC_ZP_197 -> 1.5438 | K79: =SRC_ZP_195 -> 6.223 | M79: SRC_ZP_197、195（Derived：毛利 − 收入）
A80: G68 | B80: 營業成本中的計算服務費（推估）＝API 銷售成本 × 算力費占比 | C80: RMB 億 | D80: =D79*INP_102 -> 1.5438 | K80: =K79*INP_102 -> 6.223 | M80: Inputs（基準 1＝上限；下限 0.22＝FY2024 銷售成本中算力費占比）。r2 P1：只是總算力費的一部分（招股章程期間占 2–3%），不再等於推論支出；舊法（D8r）以本列為推論支出，見第七節對照與第十五節
A81: G69 | B81: 研發開支 | C81: RMB 億 | D81: =SRC_ZP_139 -> 31.8044 | K81: =SRC_ZP_199 -> 21.3117 | M81: SRC_ZP_139、199
A82: G70 | B82: 股權報酬（總額） | C82: RMB 億 | D82: =SRC_ZP_142 -> 5.5827 | K82: =SRC_ZP_202 -> 0.8576 | M82: SRC_ZP_142、202
A83: G71 | B83: 研發開支（扣股權報酬中研發部分） | C83: RMB 億 | D83: =D81-D82*INP_104 -> 27.650871 | K83: =K81-K82*INP_104 -> 20.673646 | M83: 股權報酬 × 研發比例（Inputs，Analogy：研發人員占比 74.4%）
A84: G72 | B84: 研發項下算力服務費（基準：P1）＝研發開支 × 1H25 占比 | C84: RMB 億 | D84: =D81*INP_137 -> 22.835559 | K84: =K81*INP_137 -> 15.301801 | M84: r2 P1：占比 Inputs（招股章程 1H25 71.8%，SRC_ZP_640；Analogy 60–80%）；分母為研發開支總額（同招股章程）
A85: G73 | B85: 研發算力支出（對照：扣除法）＝研發（扣股權報酬）−（薪酬總額 − 股權報酬）× 研發人員占比 | C85: RMB 億 | D85: =D83-(SRC_ZP_163-D82)*SRC_ZP_848/INP_014 -> 21.660704 | K85: =K83-(SRC_ZP_224-K82)*SRC_ZP_848/INP_014 -> 17.724876 | M85: D10r 第一法；薪酬 SRC_ZP_163、224；研發人員占比 SRC_ZP_848（招股章程第 221 頁 657／883；r2 P2 改引用一手列）；扣除法把研發中的非人事非算力費用也算成算力（上限）
A86: G74 | B86: 對照：FY2024 研發算力占研發開支（SRC） | C86: 比例 | D86: =SRC_ZP_613/SRC_ZP_048 -> 0.70729785 | M86: SRC_ZP_613（招股章程一手；r2 P2 取代媒體 SRC_ZP_232）÷ SRC_ZP_048
A87: G75 | B87: 總算力費＝營業成本計算服務費＋研發項下算力費 | C87: RMB 億 | D87: =D80+D84 -> 24.379359 | K87: =K80+K84 -> 21.524801 | M87: r2 P1；銷售及營銷項下算力費未揭露（招股章程期間占總算力費 0–1.7%），不另估（見報告）
A88: G76 | B88: 研發科目占總算力費（會計科目；只列） | C88: 比例 | D88: =D84/D87 -> 0.93667594 | K88: =K84/K87 -> 0.71089163 | M88: Z3–Z5b 以本列為研發占比起點；r2 P1 起改用研發 GW 殘差占比（第八節）
A89: 六、每 GW 年算力價格（租用；D9r）＝卡時租價 × 每 GW 卡數 × 每年小時 ÷ 10^8（元→億）；2H26 起 ×（1＋年變動率），2H26 以半年計
A90: G77 | B90: 每卡 IT 功耗：Hopper（H800／A800 等；TK Hopper H100 欄） | C90: kW／卡 | D90: =INP_096 -> 1.393 | E90: =INP_096 -> 1.393 | F90: =INP_096 -> 1.393 | G90: =INP_096 -> 1.393 | H90: =INP_096 -> 1.393 | I90: =INP_096 -> 1.393 | K90: =INP_096 -> 1.393 | L90: =INP_096 -> 1.393 | M90: Inputs（Analogy；Hopper 依 TK DC_Cost 每 GW GPU 數換算）
A91: G78 | B91: 每 GW 卡數：Hopper（H800／A800 等；TK Hopper H100 欄） | C91: 卡／GW | D91: =INP_075/D90 -> 717875.09 | E91: =INP_075/E90 -> 717875.09 | F91: =INP_075/F90 -> 717875.09 | G91: =INP_075/G90 -> 717875.09 | H91: =INP_075/H90 -> 717875.09 | I91: =INP_075/I90 -> 717875.09 | K91: =INP_075/K90 -> 717875.09 | L91: =INP_075/L90 -> 717875.09 | M91: 10^6 kW ÷ 每卡 kW
A92: G79 | B92: 每卡 IT 功耗：H20 | C92: kW／卡 | D92: =INP_097 -> 1.09 | E92: =INP_097 -> 1.09 | F92: =INP_097 -> 1.09 | G92: =INP_097 -> 1.09 | H92: =INP_097 -> 1.09 | I92: =INP_097 -> 1.09 | K92: =INP_097 -> 1.09 | L92: =INP_097 -> 1.09 | M92: Inputs（Analogy；Hopper 依 TK DC_Cost 每 GW GPU 數換算）
A93: G80 | B93: 每 GW 卡數：H20 | C93: 卡／GW | D93: =INP_075/D92 -> 917431.19 | E93: =INP_075/E92 -> 917431.19 | F93: =INP_075/F92 -> 917431.19 | G93: =INP_075/G92 -> 917431.19 | H93: =INP_075/H92 -> 917431.19 | I93: =INP_075/I92 -> 917431.19 | K93: =INP_075/K92 -> 917431.19 | L93: =INP_075/L92 -> 917431.19 | M93: 10^6 kW ÷ 每卡 kW
A94: G81 | B94: 每卡 IT 功耗：國產（昇騰 910B／910C 等） | C94: kW／卡 | D94: =INP_098 -> 1 | E94: =INP_098 -> 1 | F94: =INP_098 -> 1 | G94: =INP_098 -> 1 | H94: =INP_098 -> 1 | I94: =INP_098 -> 1 | K94: =INP_098 -> 1 | L94: =INP_098 -> 1 | M94: Inputs（Analogy；Hopper 依 TK DC_Cost 每 GW GPU 數換算）
A95: G82 | B95: 每 GW 卡數：國產（昇騰 910B／910C 等） | C95: 卡／GW | D95: =INP_075/D94 -> 1000000 | E95: =INP_075/E94 -> 1000000 | F95: =INP_075/F94 -> 1000000 | G95: =INP_075/G94 -> 1000000 | H95: =INP_075/H94 -> 1000000 | I95: =INP_075/I94 -> 1000000 | K95: =INP_075/K94 -> 1000000 | L95: =INP_075/L94 -> 1000000 | M95: 10^6 kW ÷ 每卡 kW
A96: G83 | B96: 卡時租價：Hopper（H800／A800 等；TK Hopper H100 欄） | C96: 元／卡／時 | D96: =SRC_ZP_474 -> 13.36 | E96: =(K96*INP_008+L96*INP_009)/INP_007 -> 13.023255 | F96: =E96*(1+INP_100) -> 11.720929 | G96: =F96*(1+INP_100) -> 10.548836 | H96: =G96*(1+INP_100) -> 9.4939527 | I96: =H96*(1+INP_100) -> 8.5445575 | K96: =SRC_ZP_474 -> 13.36 | L96: =K96*(1+INP_100/INP_013) -> 12.692 | M96: SRC_ZP_474 H800（SMM 兩年約折算 13.36；阿里雲 18.75／圖靈 11.83 為區間 SRC_ZP_472–473）；2025 以 2026 觀察值計（2025 租價找不到）
A97: G84 | B97: 卡時租價：H20 | C97: 元／卡／時 | D97: =SRC_ZP_462 -> 7.47 | E97: =(K97*INP_008+L97*INP_009)/INP_007 -> 7.2817151 | F97: =E97*(1+INP_100) -> 6.5535436 | G97: =F97*(1+INP_100) -> 5.8981892 | H97: =G97*(1+INP_100) -> 5.3083703 | I97: =H97*(1+INP_100) -> 4.7775333 | K97: =SRC_ZP_462 -> 7.47 | L97: =K97*(1+INP_100/INP_013) -> 7.0965 | M97: SRC_ZP_462 H20 京津冀均價 7.47（7.03–8.16）；2025 以 2026 觀察值計（2025 租價找不到）
A98: G85 | B98: 卡時租價：國產（昇騰 910B／910C 等） | C98: 元／卡／時 | D98: =AVERAGE(SRC_ZP_478,SRC_ZP_479)*INP_099 -> 5.265 | E98: =(K98*INP_008+L98*INP_009)/INP_007 -> 5.1322932 | F98: =E98*(1+INP_100) -> 4.6190638 | G98: =F98*(1+INP_100) -> 4.1571575 | H98: =G98*(1+INP_100) -> 3.7414417 | I98: =H98*(1+INP_100) -> 3.3672975 | K98: =AVERAGE(SRC_ZP_478,SRC_ZP_479)*INP_099 -> 5.265 | L98: =K98*(1+INP_100/INP_013) -> 5.00175 | M98: 昇騰 910B 折算卡時價 2.74／4.28 的平均（SRC_ZP_478、479）× 國產卡別倍數（Inputs；910C 租價找不到）；2025 以 2026 觀察值計（2025 租價找不到）
A99: G86 | B99: 每 GW 年價格：Hopper（H800／A800 等；TK Hopper H100 欄） | C99: RMB 億／GW／年 | D99: =D188 -> 840.15506 | E99: =MAX(E188,E194) -> 818.97855 | F99: =MAX(F188,F194) -> 737.08069 | G99: =MAX(G188,G194) -> 663.37263 | H99: =MAX(H188,H194) -> 653.97838 | I99: =MAX(I188,I194) -> 653.97838 | K99: =K188 -> 840.15506 | L99: =MAX(L188,L194) -> 798.14731 | M99: Z5b V1：2H26 起＝MAX（觀察租價換算，供應商持有成本 ×（1＋最低毛利））（第十四節）；2025、1H26＝觀察值
A100: G87 | B100: 每 GW 年價格：H20 | C100: RMB 億／GW／年 | D100: =D189 -> 600.34128 | E100: =MAX(E189,E195) -> 585.20939 | F100: =MAX(F189,F195) -> 526.68846 | G100: =MAX(G189,G195) -> 474.01961 | H100: =MAX(H189,H195) -> 426.61765 | I100: =MAX(I189,I195) -> 392.38703 | K100: =K189 -> 600.34128 | L100: =MAX(L189,L195) -> 570.32422 | M100: Z5b V1：2H26 起＝MAX（觀察租價換算，供應商持有成本 ×（1＋最低毛利））（第十四節）；2025、1H26＝觀察值
A101: G88 | B101: 每 GW 年價格：國產（昇騰 910B／910C 等） | C101: RMB 億／GW／年 | D101: =D190 -> 461.214 | E101: =MAX(E190,E196) -> 449.58888 | F101: =MAX(F190,F196) -> 404.62999 | G101: =MAX(G190,G196) -> 392.38703 | H101: =MAX(H190,H196) -> 392.38703 | I101: =MAX(I190,I196) -> 392.38703 | K101: =K190 -> 461.214 | L101: =MAX(L190,L196) -> 438.1533 | M101: Z5b V1：2H26 起＝MAX（觀察租價換算，供應商持有成本 ×（1＋最低毛利））（第十四節）；2025、1H26＝觀察值
...

Sheet Cost
A1: Cost — 成本與命題表：算力成本（2025、1H26＝算力服務費實付；之後＝租用 GW × 每 GW 價格＋自有資本支出）、供應商持有成本與雲端毛利、本地化部署交付成本、非算力成本、股權報酬、每 VR 等值 GW 命題表（人民幣與美元）
A2: 規格 D4、D10、D11r、D13、D23。全成本＝算力成本＋本地化部署交付成本＋非算力成本（不含股權報酬）＋股權報酬（命題含股權報酬，較保守；另列不含者）。2025 全成本對財報（銷售成本＋研發＋銷售＋管理）差距＝0（非算力成本為財報減項的殘差）。
A3: 金額 RMB 億；命題表 RMB 億／VR 等值 GW／年，美元口徑 $B／VR 等值 GW／年（÷ USD/CNY ÷ 10）。2026（E）＝1H26＋2H26。
A5: 編號 | B5: 項目 | C5: 單位 | D5: 2025 | E5: 2026 | F5: 2027 | G5: 2028 | H5: 2029 | I5: 2030 | K5: 1H2026 | L5: 2H2026 | M5: 說明
B6: 年度 | D6: =INP_001 -> 2025 | E6: =INP_002 -> 2026 | F6: =INP_003 -> 2027 | G6: =INP_004 -> 2028 | H6: =INP_005 -> 2029 | I6: =INP_006 -> 2030 | K6: 1H2026（實際） | L6: 2H2026（驅動）
A7: 一、算力成本（D10）：2025、1H26＝算力服務費實付（Compute 第五節）；2H26 起＝租用 GW × 每 GW 價格 × 期間比例＋自有資本支出
A8: K01 | B8: 營業成本中的計算服務費（實付推估） | C8: RMB 億 | D8: =Compute!D80 -> 1.5438 | K8: =Compute!K80 -> 6.223 | M8: r2 P1：不再等於推論支出
A9: K02 | B9: 研發項下算力服務費（實付推估） | C9: RMB 億 | D9: =Compute!D84 -> 22.835559 | K9: =Compute!K84 -> 15.301801 | M9: r2 P1：研發開支 × 71.8%；含推理
A10: K03 | B10: 算力服務費（租用） | C10: RMB 億 | D10: =D8+D9 -> 24.379359 | E10: =K10+L10 -> 61.581874 | F10: =Compute!F120*Compute!F102 -> 99.088482 | G10: =Compute!G120*Compute!G102 -> 147.41135 | H10: =Compute!H120*Compute!H102 -> 229.76286 | I10: =Compute!I120*Compute!I102 -> 347.03354 | K10: =K8+K9 -> 21.524801 | L10: =Compute!L120*(Compute!L102*INP_009/INP_007) -> 40.057073 | M10: 2H26 起＝租用 GW × 每 GW 年價格 × 期間比例
A11: K04 | B11: 自有資本支出（現金） | C11: RMB 億 | F11: =Compute!F117 -> 0 | G11: =Compute!G117 -> 0 | H11: =Compute!H117 -> 0 | I11: =Compute!I117 -> 0 | M11: Compute 第八節（D11r：基準 0）
A12: K05 | B12: 算力成本（現金口徑）＝租用＋自有資本支出＋自有營運費用 | C12: RMB 億 | D12: =D10 -> 24.379359 | E12: =K12+L12 -> 61.581874 | F12: =F10+F11+F90 -> 99.088482 | G12: =G10+G11+G90 -> 147.41135 | H12: =H10+H11+H90 -> 229.76286 | I12: =I10+I11+I90 -> 347.03354 | K12: =K10 -> 21.524801 | L12: =L10 -> 40.057073 | M12: 命題輸出基準；Z5b V2：2027 起＋自有算力營運費用（第十節）
A13: K06 | B13: 算力成本拆分：推論 | C13: RMB 億 | D13: =IF(Compute!D119,D12*Compute!D124/Compute!D119,Compute!D119) -> 15.430802 | E13: =K13+L13 -> 40.303316 | F13: =IF(Compute!F119,F12*Compute!F124/Compute!F119,Compute!F119) -> 62.425744 | G13: =IF(Compute!G119,G12*Compute!G124/Compute!G119,Compute!G119) -> 92.86915 | H13: =IF(Compute!H119,H12*Compute!H124/Compute!H119,Compute!H119) -> 144.7506 | I13: =IF(Compute!I119,I12*Compute!I124/Compute!I119,Compute!I119) -> 218.63113 | K13: =IF(Compute!K119,K12*Compute!K124/Compute!K119,Compute!K119) -> 15.06736 | L13: =IF(Compute!L119,L12*Compute!L124/Compute!L119,Compute!L119) -> 25.235956 | M13: 依 GW 占比拆分（r2 P1：校準期也依 GW 占比，不再等於會計科目）；供給為 0 時顯示 0
A14: K07 | B14: 算力成本拆分：研發 | C14: RMB 億 | D14: =IF(Compute!D119,D12*Compute!D127/Compute!D119,Compute!D119) -> 8.9485573 | E14: =K14+L14 -> 17.27285 | F14: =IF(Compute!F119,F12*Compute!F127/Compute!F119,Compute!F119) -> 26.75389 | G14: =IF(Compute!G119,G12*Compute!G127/Compute!G119,Compute!G119) -> 39.801064 | H14: =IF(Compute!H119,H12*Compute!H127/Compute!H119,Compute!H119) -> 62.035972 | I14: =IF(Compute!I119,I12*Compute!I127/Compute!I119,Compute!I119) -> 93.699056 | K14: =IF(Compute!K119,K12*Compute!K127/Compute!K119,Compute!K119) -> 6.4574402 | L14: =IF(Compute!L119,L12*Compute!L127/Compute!L119,Compute!L119) -> 10.81541 | M14: 依 GW 占比拆分（r2 P1：校準期也依 GW 占比，不再等於會計科目）；供給為 0 時顯示 0
A15: K08 | B15: 算力成本拆分：閒置 | C15: RMB 億 | D15: =IF(Compute!D119,D12*Compute!D121/Compute!D119,Compute!D119) -> 0 | E15: =K15+L15 -> 4.0057073 | F15: =IF(Compute!F119,F12*Compute!F121/Compute!F119,Compute!F119) -> 9.9088482 | G15: =IF(Compute!G119,G12*Compute!G121/Compute!G119,Compute!G119) -> 14.741135 | H15: =IF(Compute!H119,H12*Compute!H121/Compute!H119,Compute!H119) -> 22.976286 | I15: =IF(Compute!I119,I12*Compute!I121/Compute!I119,Compute!I119) -> 34.703354 | K15: =IF(Compute!K119,K12*Compute!K121/Compute!K119,Compute!K119) -> 0 | L15: =IF(Compute!L119,L12*Compute!L121/Compute!L119,Compute!L119) -> 4.0057073 | M15: 依 GW 占比拆分（r2 P1：校準期也依 GW 占比，不再等於會計科目）；供給為 0 時顯示 0
A16: K09 | B16: 檢查：算力成本 −（營業成本計算服務費＋研發項下算力費） | C16: RMB 億 | D16: =D12-D8-D9 -> 0 | K16: =K12-K8-K9 -> 0 | M16: 2025、1H26 應為 0（Checks）
A17: 二、供應商持有成本與供應商推算毛利（D10：持有成本＝租用 GW × TK IF_HoldEcon（Hopper）× 持有比 × 匯率；差額＝供應商推算毛利，只作參考；Z5b V1：2H26 起不得為負）
A18: K10 | B18: 每 GW 年持有成本：Hopper（H800／A800 等；TK Hopper H100 欄） | C18: RMB 億／GW／年 | D18: =Compute!D191 -> 653.97838 | E18: =Compute!E191 -> 653.97838 | F18: =Compute!F191 -> 653.97838 | G18: =Compute!G191 -> 653.97838 | H18: =Compute!H191 -> 653.97838 | I18: =Compute!I191 -> 653.97838 | K18: =Compute!K191 -> 653.97838 | L18: =Compute!L191 -> 653.97838 | M18: Compute 第十四節（TK IF_HoldEcon（Hopper 基準欄，經濟口徑）× 持有比 × USD/CNY × 10）；亦為 2H26 起每 GW 租價下限（Z5b V1）
A19: K11 | B19: 每 GW 年持有成本：H20 | C19: RMB 億／GW／年 | D19: =Compute!D192 -> 392.38703 | E19: =Compute!E192 -> 392.38703 | F19: =Compute!F192 -> 392.38703 | G19: =Compute!G192 -> 392.38703 | H19: =Compute!H192 -> 392.38703 | I19: =Compute!I192 -> 392.38703 | K19: =Compute!K192 -> 392.38703 | L19: =Compute!L192 -> 392.38703 | M19: Compute 第十四節（TK IF_HoldEcon（Hopper 基準欄，經濟口徑）× 持有比 × USD/CNY × 10）；亦為 2H26 起每 GW 租價下限（Z5b V1）
A20: K12 | B20: 每 GW 年持有成本：國產（昇騰 910B／910C 等） | C20: RMB 億／GW／年 | D20: =Compute!D193 -> 392.38703 | E20: =Compute!E193 -> 392.38703 | F20: =Compute!F193 -> 392.38703 | G20: =Compute!G193 -> 392.38703 | H20: =Compute!H193 -> 392.38703 | I20: =Compute!I193 -> 392.38703 | K20: =Compute!K193 -> 392.38703 | L20: =Compute!L193 -> 392.38703 | M20: Compute 第十四節（TK IF_HoldEcon（Hopper 基準欄，經濟口徑）× 持有比 × USD/CNY × 10）；亦為 2H26 起每 GW 租價下限（Z5b V1）
A21: K13 | B21: 每 GW 年持有成本：組合後 | C21: RMB 億／GW／年 | D21: =Compute!D25*D18+Compute!D24*D19+Compute!D23*D20 -> 523.1827 | E21: =Compute!E25*E18+Compute!E24*E19+Compute!E23*E20 -> 457.78487 | F21: =Compute!F25*F18+Compute!F24*F19+Compute!F23*F20 -> 431.62573 | G21: =Compute!G25*G18+Compute!G24*G19+Compute!G23*G20 -> 418.54616 | H21: =Compute!H25*H18+Compute!H24*H19+Compute!H23*H20 -> 405.4666 | I21: =Compute!I25*I18+Compute!I24*I19+Compute!I23*I20 -> 405.4666 | K21: =Compute!K25*K18+Compute!K24*K19+Compute!K23*K20 -> 457.78487 | L21: =Compute!L25*L18+Compute!L24*L19+Compute!L23*L20 -> 457.78487
A22: K14 | B22: 供應商持有成本＝租用 GW × 持有成本 × 期間比例 | C22: RMB 億 | D22: =Compute!D120*D21 -> 18.798337 | E22: =K22+L22 -> 50.546905 | F22: =Compute!F120*F21 -> 91.640932 | G22: =Compute!G120*G21 -> 145.6639 | H22: =Compute!H120*H21 -> 228.79708 | I22: =Compute!I120*I21 -> 347.03354 | K22: =Compute!K120*(K21*INP_008/INP_007) -> 17.082896 | L22: =Compute!L120*(L21*INP_009/INP_007) -> 33.464009
A23: K15 | B23: 供應商推算毛利＝算力服務費 − 供應商持有成本 | C23: RMB 億 | D23: =D10-D22 -> 5.5810227 | E23: =E10-E22 -> 11.034969 | F23: =F10-F22 -> 7.4475502 | G23: =G10-G22 -> 1.7474447 | H23: =H10-H22 -> 0.96578436 | I23: =I10-I22 -> 0 | K23: =K10-K22 -> 4.4419047 | L23: =L10-L22 -> 6.5930643
A24: K16 | B24: 供應商推算毛利率 | C24: 比例 | D24: =IF(D10,D23/D10,D10) -> 0.22892409 | E24: =IF(E10,E23/E10,E10) -> 0.17919184 | F24: =IF(F10,F23/F10,F10) -> 0.075160604 | G24: =IF(G10,G23/G10,G10) -> 0.011854207 | H24: =IF(H10,H23/H10,H10) -> 0.0042033963 | I24: =IF(I10,I23/I10,I10) -> 0 | K24: =IF(K10,K23/K10,K10) -> 0.20636218 | L24: =IF(L10,L23/L10,L10) -> 0.16459176 | M24: 租用為 0（全自有）時顯示 0
A25: 三、本地化部署交付成本（D4：不耗智譜算力；2025、1H26＝財報推算；2H26 起＝本地化營收 × 1H26 成本率）
A26: K17 | B26: 本地化部署銷售成本（推算） | C26: RMB 億 | D26: =SRC_ZP_198 -> 2.733 | K26: =SRC_ZP_196 -> 0.7998 | M26: SRC_ZP_198、196（Derived）
A27: K18 | B27: 本地化部署成本率 | C27: 比例 | D27: =D26/Revenue!D52 -> 0.51184568 | K27: =K26/Revenue!K52 -> 0.62134866 | M27: 2025 0.51、1H26 0.62；2H26 起沿用 1H26（最新實際值，較保守）
A28: K19 | B28: 本地化部署交付成本 | C28: RMB 億 | D28: =D26 -> 2.733 | E28: =K28+L28 -> 3.1123355 | F28: =Revenue!F52*$K$27 -> 3.1123355 | G28: =Revenue!G52*$K$27 -> 3.1123355 | H28: =Revenue!H52*$K$27 -> 3.1123355 | I28: =Revenue!I52*$K$27 -> 3.1123355 | K28: =K26 -> 0.7998 | L28: =Revenue!L52*$K$27 -> 2.3125355
A29: 四、非算力成本（D13）：2025、1H26＝財報費用 − 算力服務費 − 本地化交付成本 − 股權報酬（殘差）；2H26 起＝人數 × 每人年成本；股權報酬單列
A30: K20 | B30: 銷售成本 | C30: RMB 億 | D30: =SRC_ZP_123 -> 4.2768 | K30: =SRC_ZP_182 -> 7.0228 | M30: SRC_ZP_123、182
A31: K21 | B31: 研發開支 | C31: RMB 億 | D31: =SRC_ZP_139 -> 31.8044 | K31: =SRC_ZP_199 -> 21.3117 | M31: SRC_ZP_139、199
A32: K22 | B32: 銷售及營銷開支 | C32: RMB 億 | D32: =SRC_ZP_140 -> 3.9087 | K32: =SRC_ZP_200 -> 1.7767 | M32: SRC_ZP_140、200
A33: K23 | B33: 一般及行政開支 | C33: RMB 億 | D33: =SRC_ZP_141 -> 5.0536 | K33: =SRC_ZP_201 -> 1.0335 | M33: SRC_ZP_141、201
A34: K24 | B34: 財報費用合計（銷售成本＋研發＋銷售＋管理） | C34: RMB 億 | D34: =D30+D31+D32+D33 -> 45.0435 | K34: =K30+K31+K32+K33 -> 31.1447
A35: K25 | B35: 股權報酬（財報） | C35: RMB 億 | D35: =SRC_ZP_142 -> 5.5827 | K35: =SRC_ZP_202 -> 0.8576 | M35: SRC_ZP_142、202
A36: K26 | B36: 非算力成本（不含股權報酬；財報殘差） | C36: RMB 億 | D36: =D34-D12-D28-D35 -> 12.348441 | K36: =K34-K12-K28-K35 -> 7.9624994 | M36: ＝研發、銷售、管理扣算力服務費與股權報酬，加 API 銷售成本中非算力部分（推論占比 <1 時）
A37: K27 | B37: 員工人數（期間平均） | C37: 人 | D37: =AVERAGE(SRC_ZP_844,SRC_ZP_162) -> 988.5 | E37: =(K37+L37)/INP_013 -> 1037.5 | F37: =E37*(1+INP_117) -> 1141.25 | G37: =F37*(1+INP_117) -> 1255.375 | H37: =G37*(1+INP_117) -> 1380.9125 | I37: =H37*(1+INP_117) -> 1519.0038 | K37: =AVERAGE(SRC_ZP_162,SRC_ZP_222) -> 1037.5 | L37: =K37*(1+INP_116) -> 1037.5 | M37: 2025＝AVERAGE（2025-06-30 883, 2025-12-31 1,094）；1H26＝AVERAGE（1,094, 2026-06-30 981）（SRC_ZP_844 招股章程、162、222；r2 P2 改引用一手列）；之後 Inputs 成長率
A38: K28 | B38: 每人年成本（不含股權報酬） | C38: RMB 億／人／年 | D38: =D36/D37 -> 0.0124921 | E38: =(K38*INP_008+L38*INP_009)/INP_007 -> 0.01559363 | F38: =E38*(1+INP_118) -> 0.016061439 | G38: =F38*(1+INP_118) -> 0.016543282 | H38: =G38*(1+INP_118) -> 0.01703958 | I38: =H38*(1+INP_118) -> 0.017550768 | K38: =K36/(K37*INP_008/INP_007) -> 0.015476601 | L38: =K38*(1+INP_118/INP_013) -> 0.01570875 | M38: 校準期＝財報殘差 ÷ 人數（1H26 年化）；2H26 起 ×（1＋年變動率；2H26 為半年）
A39: K29 | B39: 每人年股權報酬 | C39: RMB 億／人／年 | D39: =D35/D37 -> 0.005647648 | E39: =(K39*INP_008+L39*INP_009)/INP_007 -> 0.0016669054 | F39: =E39*(1+INP_119) -> 0.0016669054 | G39: =F39*(1+INP_119) -> 0.0016669054 | H39: =G39*(1+INP_119) -> 0.0016669054 | I39: =H39*(1+INP_119) -> 0.0016669054 | K39: =K35/(K37*INP_008/INP_007) -> 0.0016669054 | L39: =K39*(1+INP_119/INP_013) -> 0.0016669054 | M39: 1H26 年化為基期（上市後）；2025 含上市前授予，只列
A40: K30 | B40: 非算力成本（不含股權報酬） | C40: RMB 億 | D40: =D36 -> 12.348441 | E40: =K40+L40 -> 16.178391 | F40: =F37*F38 -> 18.330117 | G40: =G37*G38 -> 20.768023 | H40: =H37*H38 -> 23.53017 | I40: =I37*I38 -> 26.659682 | K40: =K36 -> 7.9624994 | L40: =L37*(L38*INP_009/INP_007) -> 8.2158916 | M40: 校準期＝財報殘差；2H26 起＝人數 × 每人年成本 × 期間比例
A41: K31 | B41: 股權報酬 | C41: RMB 億 | D41: =D35 -> 5.5827 | E41: =K41+L41 -> 1.7294144 | F41: =F37*F39 -> 1.9023558 | G41: =G37*G39 -> 2.0925914 | H41: =H37*H39 -> 2.3018505 | I41: =I37*I39 -> 2.5320356 | K41: =K35 -> 0.8576 | L41: =L37*(L39*INP_009/INP_007) -> 0.87181436 | M41: 校準期＝財報；2H26 起＝人數 × 每人股權報酬 × 期間比例
A42: 五、全成本與對帳（命題全成本含股權報酬；2025、1H26 對財報差距應為 0）
A43: K32 | B43: 全成本（含股權報酬）＝算力＋本地化交付＋非算力＋股權報酬 | C43: RMB 億 | D43: =D12+D28+D40+D41 -> 45.0435 | E43: =E12+E28+E40+E41 -> 82.602014 | F43: =F12+F28+F40+F41 -> 122.43329 | G43: =G12+G28+G40+G41 -> 173.3843 | H43: =H12+H28+H40+H41 -> 258.70722 | I43: =I12+I28+I40+I41 -> 379.3376 | K43: =K12+K28+K40+K41 -> 31.1447 | L43: =L12+L28+L40+L41 -> 51.457314
A44: K33 | B44: 全成本（不含股權報酬） | C44: RMB 億 | D44: =D43-D41 -> 39.4608 | E44: =E43-E41 -> 80.8726 | F44: =F43-F41 -> 120.53093 | G44: =G43-G41 -> 171.29171 | H44: =H43-H41 -> 256.40537 | I44: =I43-I41 -> 376.80556 | K44: =K43-K41 -> 30.2871 | L44: =L43-L41 -> 50.5855
A45: K34 | B45: 對帳：全成本 − 財報費用合計（應為 0） | C45: RMB 億 | D45: =D43-D34 -> 0 | K45: =K43-K34 -> 0 | M45: 工作單 Z3 第 2 步：2025 差距＝0（1H26 同）
A46: K35 | B46: 營收淨額（截頂後） | C46: RMB 億 | D46: =Revenue!D59 -> 7.2433 | E46: =Revenue!E59 -> 40.419375 | F46: =Revenue!F59 -> 80.276438 | G46: =Revenue!G59 -> 131.46554 | H46: =Revenue!H59 -> 197.68856 | I46: =Revenue!I59 -> 278.41919 | M46: REV_NetCapped
A47: K36 | B47: 雲端營收（截頂後）＝雲端 × 容量上限係數 | C47: RMB 億 | D47: =Revenue!D56*Revenue!D57 -> 1.9038 | E47: =Revenue!E56*Revenue!E57 -> 35.410375 | F47: =Revenue!F56*Revenue!F57 -> 75.267438 | G47: =Revenue!G56*Revenue!G57 -> 126.45654 | H47: =Revenue!H56*Revenue!H57 -> 192.67956 | I47: =Revenue!I56*Revenue!I57 -> 273.41019
A48: K37 | B48: 差額＝營收淨額 − 全成本（含股權報酬） | C48: RMB 億 | D48: =D46-D43 -> -37.8002 | E48: =E46-E43 -> -42.18264 | F48: =F46-F43 -> -42.156852 | G48: =G46-G43 -> -41.918763 | H48: =H46-H43 -> -61.018659 | I48: =I46-I43 -> -100.91841 | M48: 負＝缺口（Z4 融資）
A49: K38 | B49: 對照：財報年內虧損（2025） | C49: RMB 億 | D49: =-SRC_ZP_145 -> -47.1817 | M49: SRC_ZP_145；差額另含其他收入、財務成本、投資人金融工具公允值變動等
A50: 六、命題表（人民幣；每 VR 等值 GW；分母＝供給 VR 等值 GW）
A51: K39 | B51: 分母：供給 VR 等值 GW | C51: GW | D51: =Compute!D137 -> 0.0028339218 | E51: =Compute!E137 -> 0.0076958186 | F51: =Compute!F137 -> 0.01419357 | G51: =Compute!G137 -> 0.023008926 | H51: =Compute!H137 -> 0.036116388 | I51: =Compute!I137 -> 0.055953633 | M51: CMP_Supply_VReq
A52: K40 | B52: 每 VR 等值 GW：營收淨額 | C52: RMB 億／GW／年 | D52: =IF(D51,D46/D51,D51) -> 2555.9279 | E52: =IF(E51,E46/E51,E51) -> 5252.1215 | F52: =IF(F51,F46/F51,F51) -> 5655.8312 | G52: =IF(G51,G46/G51,G51) -> 5713.6754 | H52: =IF(H51,H46/H51,H51) -> 5473.6525 | I52: =IF(I51,I46/I51,I51) -> 4975.8911 | M52: 分母為 0（壓力情境）時顯示 0
A53: K41 | B53: 每 VR 等值 GW：雲端營收 | C53: RMB 億／GW／年 | D53: =IF(D51,D47/D51,D51) -> 671.78987 | E53: =IF(E51,E47/E51,E51) -> 4601.2486 | F53: =IF(F51,F47/F51,F51) -> 5302.9249 | G53: =IF(G51,G47/G51,G51) -> 5495.9773 | H53: =IF(H51,H47/H51,H51) -> 5334.962 | I53: =IF(I51,I47/I51,I51) -> 4886.3706 | M53: 分母為 0（壓力情境）時顯示 0
A54: K42 | B54: 每 VR 等值 GW：算力成本 | C54: RMB 億／GW／年 | D54: =IF(D51,D12/D51,D51) -> 8602.6929 | E54: =IF(E51,E12/E51,E51) -> 8001.9913 | F54: =IF(F51,F12/F51,F51) -> 6981.2231 | G54: =IF(G51,G12/G51,G51) -> 6406.7027 | H54: =IF(H51,H12/H51,H51) -> 6361.7342 | I54: =IF(I51,I12/I51,I51) -> 6202.1628 | M54: 分母為 0（壓力情境）時顯示 0
A55: K43 | B55: 每 VR 等值 GW：本地化部署交付成本 | C55: RMB 億／GW／年 | D55: =IF(D51,D28/D51,D51) -> 964.38792 | E55: =IF(E51,E28/E51,E51) -> 404.41902 | F55: =IF(F51,F28/F51,F51) -> 219.27784 | G55: =IF(G51,G28/G51,G51) -> 135.26644 | H55: =IF(H51,H28/H51,H51) -> 86.175158 | I55: =IF(I51,I28/I51,I51) -> 55.623474 | M55: 分母為 0（壓力情境）時顯示 0
A56: K44 | B56: 每 VR 等值 GW：非算力成本（不含股權報酬） | C56: RMB 億／GW／年 | D56: =IF(D51,D40/D51,D51) -> 4357.3682 | E56: =IF(E51,E40/E51,E51) -> 2102.2313 | F56: =IF(F51,F40/F51,F51) -> 1291.4381 | G56: =IF(G51,G40/G51,G51) -> 902.60721 | H56: =IF(H51,H40/H51,H51) -> 651.50949 | I56: =IF(I51,I40/I51,I51) -> 476.46025 | M56: 分母為 0（壓力情境）時顯示 0
A57: K45 | B57: 每 VR 等值 GW：股權報酬 | C57: RMB 億／GW／年 | D57: =IF(D51,D41/D51,D51) -> 1969.9555 | E57: =IF(E51,E41/E51,E51) -> 224.7213 | F57: =IF(F51,F41/F51,F51) -> 134.0294 | G57: =IF(G51,G41/G51,G51) -> 90.946938 | H57: =IF(H51,H41/H51,H51) -> 63.734239 | I57: =IF(I51,I41/I51,I51) -> 45.252389 | M57: 分母為 0（壓力情境）時顯示 0
A58: K46 | B58: 每 VR 等值 GW：全成本（含股權報酬） | C58: RMB 億／GW／年 | D58: =IF(D51,D43/D51,D51) -> 15894.404 | E58: =IF(E51,E43/E51,E51) -> 10733.363 | F58: =IF(F51,F43/F51,F51) -> 8625.9684 | G58: =IF(G51,G43/G51,G51) -> 7535.5232 | H58: =IF(H51,H43/H51,H51) -> 7163.1531 | I58: =IF(I51,I43/I51,I51) -> 6779.4989 | M58: 分母為 0（壓力情境）時顯示 0
A59: K47 | B59: 每 VR 等值 GW：全成本（不含股權報酬） | C59: RMB 億／GW／年 | D59: =IF(D51,D44/D51,D51) -> 13924.449 | E59: =IF(E51,E44/E51,E51) -> 10508.642 | F59: =IF(F51,F44/F51,F51) -> 8491.939 | G59: =IF(G51,G44/G51,G51) -> 7444.5763 | H59: =IF(H51,H44/H51,H51) -> 7099.4188 | I59: =IF(I51,I44/I51,I51) -> 6734.2465 | M59: 分母為 0（壓力情境）時顯示 0
A60: K48 | B60: 每 VR 等值 GW：差額（含股權報酬） | C60: RMB 億／GW／年 | D60: =D52-D58 -> -13338.477 | E60: =E52-E58 -> -5481.2414 | F60: =F52-F58 -> -2970.1372 | G60: =G52-G58 -> -1821.8478 | H60: =H52-H58 -> -1689.5006 | I60: =I52-I58 -> -1803.6078 | M60: 命題：負＝營收不足以覆蓋全成本
A61: K49 | B61: 每 VR 等值 GW：差額（不含股權報酬） | C61: RMB 億／GW／年 | D61: =D52-D59 -> -11368.521 | E61: =E52-E59 -> -5256.5201 | F61: =F52-F59 -> -2836.1078 | G61: =G52-G59 -> -1730.9009 | H61: =H52-H59 -> -1625.7663 | I61: =I52-I59 -> -1758.3554
A62: K50 | B62: 每 VR 等值 GW：雲端口徑差額＝雲端營收 −（全成本 − 本地化交付成本） | C62: RMB 億／GW／年 | D62: =D53-D58+D55 -> -14258.227 | E62: =E53-E58+E55 -> -5727.6953 | F62: =F53-F58+F55 -> -3103.7657 | G62: =G53-G58+G55 -> -1904.2795 | H62: =H53-H58+H55 -> -1742.0159 | I62: =I53-I58+I55 -> -1837.5049 | M62: D4：分子只計雲端營收、分母不變；本地化交付成本隨本地化營收一併排除（其餘成本全留，較保守）
A63: K51 | B63: 覆蓋率＝營收淨額 ÷ 全成本（含股權報酬） | C63: 倍 | D63: =D46/D43 -> 0.16080678 | E63: =E46/E43 -> 0.48932674 | F63: =F46/F43 -> 0.65567492 | G63: =G46/G43 -> 0.75823207 | H63: =H46/H43 -> 0.7641401 | I63: =I46/I43 -> 0.73396149
A64: K52 | B64: 雲端覆蓋率＝雲端營收 ÷（全成本 − 本地化交付成本） | C64: 倍 | D64: =D47/(D43-D28) -> 0.044995923 | E64: =E47/(E43-E28) -> 0.44547135 | F64: =F47/(F43-F28) -> 0.63079816 | G64: =G47/(G43-G28) -> 0.74267386 | H64: =H47/(H43-H28) -> 0.75384748 | I64: =I47/(I43-I28) -> 0.72671938
A65: 七、命題表（美元；$B／VR 等值 GW／年＝人民幣億 ÷ USD/CNY ÷ 10；同一匯率，D23）
A66: K53 | B66: 每 VR 等值 GW：營收淨額（美元） | C66: $B／GW／年 | D66: =D52/INP_023/INP_021 -> 37.922342 | E66: =E52/INP_023/INP_021 -> 77.925808 | F66: =F52/INP_023/INP_021 -> 83.915654 | G66: =G52/INP_023/INP_021 -> 84.77389 | H66: =H52/INP_023/INP_021 -> 81.212666 | I66: =I52/INP_023/INP_021 -> 73.827373
A67: K54 | B67: 每 VR 等值 GW：雲端營收（美元） | C67: $B／GW／年 | D67: =D53/INP_023/INP_021 -> 9.9673567 | E67: =E53/INP_023/INP_021 -> 68.268797 | F67: =F53/INP_023/INP_021 -> 78.679579 | G67: =G53/INP_023/INP_021 -> 81.5439 | H67: =H53/INP_023/INP_021 -> 79.154913 | I67: =I53/INP_023/INP_021 -> 72.499155
A68: K55 | B68: 每 VR 等值 GW：算力成本（美元） | C68: $B／GW／年 | D68: =D54/INP_023/INP_021 -> 127.63829 | E68: =E54/INP_023/INP_021 -> 118.72567 | F68: =F54/INP_023/INP_021 -> 103.58051 | G68: =G54/INP_023/INP_021 -> 95.056346 | H68: =H54/INP_023/INP_021 -> 94.389148 | I68: =I54/INP_023/INP_021 -> 92.021585
A69: K56 | B69: 每 VR 等值 GW：全成本（含股權報酬）（美元） | C69: $B／GW／年 | D69: =D58/INP_023/INP_021 -> 235.82552 | E69: =E58/INP_023/INP_021 -> 159.25107 | F69: =F58/INP_023/INP_021 -> 127.98363 | G69: =G58/INP_023/INP_021 -> 111.80467 | H69: =H58/INP_023/INP_021 -> 106.27981 | I69: =I58/INP_023/INP_021 -> 100.58753
A70: K57 | B70: 每 VR 等值 GW：差額（含股權報酬）（美元） | C70: $B／GW／年 | D70: =D60/INP_023/INP_021 -> -197.90318 | E70: =E60/INP_023/INP_021 -> -81.325263 | F70: =F60/INP_023/INP_021 -> -44.067972 | G70: =G60/INP_023/INP_021 -> -27.030784 | H70: =H60/INP_023/INP_021 -> -25.067146 | I70: =I60/INP_023/INP_021 -> -26.760157
