Workbook

Sheet README
A1: Amkor Technology（AMKR）收支與估值模型 v0.2.2（AI 半導體 Project：封測次產業） 2026-10-25
A2: 版本：v0.2.1（2026-10-25：補上檔空間級距、投資建議、重點觀察，數值不變）；v0.2（2026-10-25：tp_w_dcf 改 0.5；Comparable 同業移除 A 股；v0.1 初版）。Amkor 為全球第二大封測廠，承接台積電 CoWoS 後段（oS、測試）與 2.5D／HDFO 委外；亞利桑那廠為美國第一座量產先進封裝廠。日月光模型待 10-29 法說後建立，本版未讀。
A3: 模型命題：Amkor 的 AI 先進封裝營收＝AI 加速器顆數（tsmc 成品）× 後段委外比例 × Amkor 份額 × 每顆封測金額（隨封裝面積上升），FY2026 約占營收一成；其餘九成是通訊（Apple 占 29.8%）、車用與工業、消費與非 AI 運算。毛利率只有 14–19%，資本支出 2026 年約 US$2.75B（營收的三成以上），亞利桑那的啟動成本與折舊是 2027–29 毛利率的關鍵。
A4: 核心問題：AI 封裝的高成長能不能抵過通訊（Apple）停滯與亞利桑那折舊，讓 EPS 在 FY2027–28 持續成長；約 14 倍前瞻 P/E 隱含什麼路徑。
A6: 會計年度＝日曆年，FY(t)＝CY(t)，不平移。預測期 FY2027–FY2029（三年）。金額：百萬美元；EPS：美元（稀釋）。口徑：歸屬母公司淨利（GAAP）。3Q26 財報 2026-10-26 公布，本版未納入。
A8: 驅動因子 → 推導量（全部唯讀上游，不修改）
A9: AI 先進封裝：tsmc 成品的加速器顆數 × 情境係數（2028–29）× 後段委外比例（Assumed）× Amkor 份額（Assumed）× 每顆封測金額（FY2026 校準，之後 × 封裝面積指數 ^ 0.5；面積指數＝tsmc 成品 CoWoS 片數 ÷ 顆數）。FY2026 的 AI 金額由運算營收與公司「AI 封裝約三倍」說法反推。
A10: 其他終端：通訊依情境（A +3%／B 0%／C −6% 於 FY2027），車用與工業 +10%、消費 +3%（公司投資人日 CAGR），非 AI 運算 +3%。亞利桑那第一期營收 FY2028–29 依情境（Assumed）。
A11: 毛利：本業毛利＝FY2026 錨點＋現金流通率 40%（Assumed）× 營收增量 − 本業折舊增量（資本支出率 14%、年限 7 年）；亞利桑那毛利＝營收 × 55% − 固定現金成本 − 折舊（第一期 US$3.5B × (1 − 補助 35%) ÷ 12 年）。營業費用彈性 0.5；營業外、稅率 20%、股數持平。
A12: 校準：FY2026 ＝ 1H26 實績＋3Q26 公司指引（終端市場季增說法、毛利率 19%、營業費用 140）＋4Q26 假設。不用券商數字（只在 Recon 對帳）。
A13: 估值：Val 第 0 節目標價＝0.5 × DCF 目標價（股東現金流＝EPS ×（1 − g／ROE），FY2027–32 明確期＋永續，r 10%、g 4%，三情境權重 0.3／0.5／0.2）＋0.5 × Comparable 目標價（日月光、力成、京元電、矽格、南茂前瞻 P/E 中位數 × 12 個月後前瞻 EPS；不放 A 股）；另列 Comparable 單獨目標價、市場共識目標價與差距拆解。十年 P/E 規則值 × FY2027 EPS 保留為參考（不是目標價）。情境對應：A＝順利、B＝平平、C＝不如預期（原為顆數情境）。本版未做先驗，無 Andy 合理 P/E 對照。
A14: 預估期間：FY2027–FY2029 由驅動因子推導；FY2030 起為收斂法，非驅動因子推導（營收年增由 FY2029 線性收斂到 fade_g、淨利率收斂到 fade_m，FY2032 達到；PL 頁灰底）。
... A18: v0.2.1（2026-10-25）：補上檔空間級距、投資建議、重點觀察（Val 頁 0.3 結論加「上檔空間級距」「投資建議」兩列、README 頁加重點觀察三點；數值不變，既有儲存格位置不變）。
A19: ="投資建議："&Val!B50&"（依上檔空間固定規則）" -> 投資建議：強力買進（依上檔空間固定規則）
A20: ="重點觀察 1：目標價 US$"&TEXT(Val!$B$39,"0.00")&"（DCF "&TEXT(Val!$B$24,"0.00")&"、Comparable（相對倍數調整後）"&TEXT(tp_comp_adj,"0.00")&"；DCF 權重 "&TEXT(tp_w_dcf,"0%")&"），比現價 "&TEXT(px,"0.00")&"（2026-10-23）"&IF(Val!$B$42>=0,"高 "&TEXT(Val!$B$42,"0.0%"),"低 "&TEXT(-Val!$B$42,"0.0%"))&"，級距 "&Val!$B$49&"、投資建議 "&Val!$B$50&"。相對倍數調整係數 "&TEXT(rm_factor,"0.00")&"（本公司 10 年前瞻倍數中位數 ÷ 同業的中位數，夾在 0.5–2.0；Val 第 0.5 節），調整前加權上檔空間 "&TEXT((tp_w_dcf*Val!$B$24+(1-tp_w_dcf)*Val!$B$35)/px-1,"+0.0%;−0.0%")&"；Comparable 單獨（市場主流同業法、未調整）為 "&TEXT(Val!$B$43,"+0.0%;−0.0%")&"。"&"以下為 2026-10-29 相對倍數調整前撰寫的說明，其中數字為調整前：主因是倍數：本模型 12 個月後前瞻 EPS 3.23 比共識前瞻 EPS 2.80 高 15.3%（期間差約一年），台美封測同業（日月光、力成、京元電、矽格、南茂）前瞻 P/E 中位數 23.3 倍，現價只隱含 14.0 倍、共識目標價 76.40 隱含 27.3 倍；DCF 36.0 低於現價（−8.4%），因近三年 R"&"OE 8.9% 低於折現率 10%（可發放比例只 55%）。" -> 重點觀察 1：目標價 US$66.40（DCF 36.01、Comparable（相對倍數調整後）96.79；DCF 權重 50%），比現價 39.30（2026-10-23）高 69.0%，級距 大於 50%、投資建議 強力買進。相對倍數調整係數 1.28（本公司 10 年前瞻倍數中位數 ÷ 同業的中位數，夾在 0.5–2.0；Val 第 0.5 節），調整前加權上檔空間 +41.7%；Comparable 單獨（市場主流同業法、未調整）為 +91.7%。以下為 2026-10-29 相對倍數調整前撰寫的說明，其中數字為調整前：主因是倍數：本模型 12 個月後前瞻 EPS 3.23 比共識前瞻 EPS 2.80 高 15.3%（期間差約一年），台美封測同業（日月光、力成、京元電、矽格、南茂）前瞻 P/E 中位數 23.3 倍，現價只隱含 14.0 倍、共識目標價 76.40 隱含 27.3 倍；DCF 36.0 低於現價（−8.4%），因近三年 ROE 8.9% 低於折現率 10%（可發放比例只 55%）。
A21: 重點觀察 2：最敏感的是現金流通率、委外比例與份額：現金流通率 30% 時 FY2028 EPS −16.9%、委外比例低 −16.2%、Amkor 份額低（28%）−15.7%、AI 部署 ×0.8 −12.8%；情境 C FY2028 EPS 2.32，比情境 A 的 4.00 低 42.0%。
A22: 重點觀察 3：追蹤 3Q26 財報（2026-10-26）：本版 3Q26 用公司指引（毛利率 19%），AI 先進封裝金額公司未揭露、由「約三倍」說法反推；亞利桑那廠固定成本與折舊從 FY2028 起影響毛利率（固定成本高案例 FY2028 EPS −4.0%）。
A23: v0.2.2（2026-10-28）：分部原則重建（數值不變）。Q 頁最後追加核對列「檢查：分部合計 − 合併營收」；官方分部與子列宣告見 segments.json。
A25: 2026-10-29：加權目標價中的 Comparable 改用相對倍數調整後的值（Val 第 0.5 節：同業前瞻倍數中位數 × 本公司 10 年相對同業的倍數比，Bloomberg 前瞻倍數；Andy 2026-10-27「照建議做」、10-29 資料取回）。「Comparable 目標價（市場主流同業法）」維持不調整。重點觀察 1 的第一句已改為公式；重點觀察 2、3 與其他說明中的目標價與上檔空間數字為調整前撰寫，以 Val 頁為準。

Sheet In
A1: In — 輸入（藍字；基準欄 E，低 D、高 F）。金額：百萬美元（US$M）；顆數：百萬顆；比例：%。每個輸入附兩個來源（找不到者寫「未找到」）；公司原文算一個
A2: 標記：Verified／Interested-party／Analogy／Assumed／Derived；Analogy、Assumed 給低／高區間，不當點估計（放情境或 Sens）。SemiAnalysis 未使用。公司原文＝SEC 8-K 新聞稿、10-K、投資人日簡報；法說內容經 Motley Fool 逐字稿與 MarketBeat 摘要；公司指引與目標為 Interested-party；券商與資料商為 Interested-party
A3: 鍵 | B3: 項目 | C3: 單位 | D3: 低 | E3: 基準 | F3: 高 | G3: 標記 | H3: 來源1 | I3: 來源2／說明
A4: A. AI 加速器顆數、封裝面積與部署規模（讀 tsmc、markets/network、markets/chip_bridge 成品；唯讀，不自行重估）
A5: units_26 | B5: AI 加速器顆數 2026（情境 A 基準） | C5: 百萬顆 | E5: 15.2 | G5: Derived | H5: tsmc/dist/20261028_台積電個股模型_v0.4.xlsx｜In!E5:E36（八類加速器加總；2029＝2028 × (1＋各類 2029 成長)，與台積電模型 CoWoS 頁同口徑） | I5: NVIDIA、AMD、Google TPU、AWS Trainium、其他 ASIC 合計；台積電模型讀 markets/memory 的同一份顆數
A6: units_27 | B6: AI 加速器顆數 2027（情境 A 基準） | C6: 百萬顆 | E6: 23.7 | G6: Derived | H6: 同上 | I6: 同上
A7: units_28 | B7: AI 加速器顆數 2028（情境 A 基準） | C7: 百萬顆 | E7: 26.5 | G7: Derived | H7: 同上 | I7: 同上
A8: units_29 | B8: AI 加速器顆數 2029（情境 A 基準） | C8: 百萬顆 | E8: 30.15 | G8: Derived | H8: 同上 | I8: 同上
A9: um28_A | B9: 情境 A：2028 顆數 ÷ 基準 | C9: x | E9: 1 | G9: Assumed | H9: tsmc/dist/20261028_台積電個股模型_v0.4.xlsx｜In!E37 | I9: A＝基準；B＝AI 資本支出消化；C＝明顯下修（與台積電、廣達、NVIDIA 模型相同）
A10: um29_A | B10: 情境 A：2029 顆數 ÷ 基準 | C10: x | E10: 1 | G10: Assumed | H10: tsmc/dist/20261028_台積電個股模型_v0.4.xlsx｜In!E38 | I10: 同上
A11: um28_B | B11: 情境 B：2028 顆數 ÷ 基準 | C11: x | E11: 0.8 | G11: Assumed | H11: tsmc/dist/20261028_台積電個股模型_v0.4.xlsx｜In!E39 | I11: 同上
A12: um29_B | B12: 情境 B：2029 顆數 ÷ 基準 | C12: x | E12: 0.85 | G12: Assumed | H12: tsmc/dist/20261028_台積電個股模型_v0.4.xlsx｜In!E40 | I12: 同上
A13: um28_C | B13: 情境 C：2028 顆數 ÷ 基準 | C13: x | E13: 0.6 | G13: Assumed | H13: tsmc/dist/20261028_台積電個股模型_v0.4.xlsx｜In!E41 | I13: 同上
A14: um29_C | B14: 情境 C：2029 顆數 ÷ 基準 | C14: x | E14: 0.6 | G14: Assumed | H14: tsmc/dist/20261028_台積電個股模型_v0.4.xlsx｜In!E42 | I14: 同上
A15: ar_26 | B15: 封裝面積指數 2026（加速器用 CoWoS 片數 ÷ 顆數，2026＝1） | C15: x | E15: 1 | G15: Derived | H15: tsmc/dist/20261028_台積電個股模型_v0.4.xlsx｜CoWoS!B13:E13 減 tsmc/dist/20261028_台積電個股模型_v0.4.xlsx｜CoWoS!B12:E12，除以顆數 | I15: 每片封裝數下降＝單顆封裝面積變大（Rubin、Rubin Ultra）；台積電模型的每片封裝數為 Derived／Assumed
A16: ar_27 | B16: 封裝面積指數 2027（加速器用 CoWoS 片數 ÷ 顆數，2026＝1） | C16: x | E16: 1.278156 | G16: Derived | H16: 同上 | I16: 同上
... A26: capit_vr | B26: 每 GW IT 資本支出（VR200；2027 起） | C26: US$B | E26: 37.586352 | G26: Derived | H26: markets/chip_bridge/dist/20261027_晶片內容橋接表_v0.2.2.xlsx｜In!E10（GB300）、H10（VR200） | I26: 同上
A27: vr26 | B27: 2026 年部署中 Rubin 世代占比（混合每 GW IT 資本支出用） | C27: % | D27: 0.15 | E27: 0.22 | F27: 0.3 | G27: Interested-party | H27: TrendForce 2026 組合 Rubin 22%（經 markets/memory）；原在台達電、廣達、奇鋐、雙鴻、健策、台光電、勝宏、光寶等模型各自寫入，值相同 | I27: Siliconomics In 頁 M11（v0.4 起；CF22：與台達電、廣達等同一混合口徑）
A28: tam_gw | B28: OSAT 先進封裝可服務市場 ÷ 每 GW 部署（Recon 用） | C28: US$B/GW | E28: 0.5 | G28: Interested-party | H28: 公司投資人日簡報（SEC 8-K）：約 US$0.5B／GW installed（公司投資人日 2026-05-21） | I28: 第二來源：未找到
A29: B. AI 先進封裝（2.5D、HDFO、AI 測試）：營收＝顆數 × 後段委外比例 × Amkor 份額 × 每顆封測金額（FY2026 以公司「三倍」說法校準）
A30: tri | B30: FY2026 AI 先進封裝營收 ÷ FY2025（公司：約三倍） | C30: x | D30: 2.5 | E30: 3 | F30: 3.2 | G30: Interested-party | H30: 1Q26 法說逐字稿（Motley Fool）：Advanced AI packaging revenue still on track to triple in 2026（1Q26 法說） | I30: 4Q25 法說逐字稿（Motley Fool）：2.5D and HDFO … nearly triple over the course of this year（4Q25 法說）；低＝供應受限時
A31: g_pc26 | B31: FY2026 非 AI 運算（PC、儲存、基礎設施）年增 | C31: % | D31: -0.1 | E31: -0.03 | F31: 0.05 | G31: Assumed | H31: 公司：PC／筆電疲弱（1Q26、4Q25 法說）；運算成長由資料中心帶動 | I31: 非 AI 運算金額未揭露：未找到
A32: out_26 | B32: AI 加速器後段（oS、測試）委外比例 2026 | C32: % | D32: 0.4 | E32: 0.5 | F32: 0.6 | G32: Assumed | H32: 台積電 CoWoS 2027 需求 ÷ 產能約 96%（台積電模型）；台積電與 Amkor 十年合作（2026-06-16）、NVIDIA 與 Amkor 多年合作 US$1.5B（2026-07-23） | I32: FY2026 只影響拆分（每顆金額由校準吸收）；FY2027 起的相對變化才影響營收；委外比例的量化：未找到
A33: out_27 | B33: AI 加速器後段（oS、測試）委外比例 2027 | C33: % | D33: 0.45 | E33: 0.55 | F33: 0.65 | G33: Assumed | H33: 同上 | I33: Rubin 世代 CoWoS 緊、美國產能需求 → 委外上升（Assumed）
A34: out_28 | B34: AI 加速器後段（oS、測試）委外比例 2028 | C34: % | D34: 0.45 | E34: 0.6 | F34: 0.7 | G34: Assumed | H34: 同上 | I34: Rubin 世代 CoWoS 緊、美國產能需求 → 委外上升（Assumed）
A35: out_29 | B35: AI 加速器後段（oS、測試）委外比例 2029 | C35: % | D35: 0.45 | E35: 0.6 | F35: 0.75 | G35: Assumed | H35: 同上 | I35: Rubin 世代 CoWoS 緊、美國產能需求 → 委外上升（Assumed）
A36: sh_26 | B36: Amkor 占委外後段的份額 2026 | C36: % | D36: 0.28 | E36: 0.35 | F36: 0.4 | G36: Assumed | H36: Amkor 為全球第二大封測廠；競爭者日月光（含矽品）、京元電（測試） | I36: 份額的量化：未找到（日月光模型待 10-29 法說後建立）；FY2026 只影響拆分
A37: sh_27 | B37: Amkor 占委外後段的份額 2027 | C37: % | D37: 0.28 | E37: 0.35 | F37: 0.4 | G37: Assumed | H37: 同上 | I37: NVIDIA 合作與美國產能（Assumed）
A38: sh_28 | B38: Amkor 占委外後段的份額 2028 | C38: % | D38: 0.28 | E38: 0.37 | F38: 0.45 | G38: Assumed | H38: 同上 | I38: NVIDIA 合作與美國產能（Assumed）
A39: sh_29 | B39: Amkor 占委外後段的份額 2029 | C39: % | D39: 0.28 | E39: 0.38 | F39: 0.45 | G39: Assumed | H39: 同上 | I39: NVIDIA 合作與美國產能（Assumed）
A40: el | B40: 每顆封測金額對封裝面積的彈性 | C40: x | D40: 0.3 | E40: 0.5 | F40: 1 | G40: Assumed | H40: 封裝面積大 → 基板上封裝、測試時間與良率成本上升；後段金額不與面積等比例 | I40: 第二來源：未找到
A41: C. 其他終端市場成長（FY2027–FY2029）
A42: g_cm27_A | B42: 通訊年增 FY2027（情境 A） | C42: % | D42: -0.02 | E42: 0.03 | F42: 0.06 | G42: Assumed | H42: Apple 新機與高階組合；SiP 移轉越南後回到正常季節性 | I42: Apple 占 FY2025 營收 29.8%、Qualcomm 11.1%（10-K）；投資人日通訊 2025–30 CAGR 約 4%
A43: g_cmL_A | B43: 通訊年增 FY2028–29（情境 A） | C43: % | D43: -0.02 | E43: 0.04 | F43: 0.06 | G43: Assumed | H43: 同上 | I43: 同上
A44: g_cm27_B | B44: 通訊年增 FY2027（情境 B） | C44: % | D44: -0.05 | E44: 0 | F44: 0.04 | G44: Assumed | H44: 通訊逆風延續到 1H27（公司：一項逆風到 4Q 與明年上半年） | I44: 同上
A45: g_cmL_B | B45: 通訊年增 FY2028–29（情境 B） | C45: % | D45: -0.05 | E45: 0.03 | F45: 0.04 | G45: Assumed | H45: 同上 | I45: 同上
A46: g_cm27_C | B46: 通訊年增 FY2027（情境 C） | C46: % | D46: -0.12 | E46: -0.06 | F46: 0.02 | G46: Assumed | H46: Apple 分散封測供應或自行轉移（客戶集中風險） | I46: 同上
A47: g_cmL_C | B47: 通訊年增 FY2028–29（情境 C） | C47: % | D47: -0.12 | E47: 0 | F47: 0.02 | G47: Assumed | H47: 同上 | I47: 同上
A48: g_au | B48: 車用與工業年增 FY2027–29 | C48: % | D48: 0.04 | E48: 0.1 | F48: 0.14 | G48: Interested-party | H48: 公司投資人日簡報（SEC 8-K）：車用與工業 2025–30 CAGR 約 10%（公司） | I48: 公司：ADAS 與資訊娛樂帶動先進車用強勁成長（1Q26、2Q26 法說）
A49: g_cs | B49: 消費年增 FY2027–29 | C49: % | D49: -0.03 | E49: 0.03 | F49: 0.06 | G49: Interested-party | H49: 公司投資人日簡報（SEC 8-K）：消費 2025–30 CAGR 約 3%（公司） | I49: 第二來源：未找到
A50: g_pc | B50: 非 AI 運算年增 FY2027–29 | C50: % | D50: -0.05 | E50: 0.03 | F50: 0.06 | G50: Assumed | H50: 投資人日：運算 2025–30 CAGR 約 24%（含 AI；公司） | I50: 非 AI 運算拆分：未找到
A51: D. 亞利桑那廠（Peoria；第一期約 US$3.5B，2027 完工、2028 投產；第二期不在本模型）
A52: az_rev28_A | B52: 亞利桑那廠營收 FY2028（情境 A） | C52: US$M | E52: 150 | G52: Assumed | H52: 公司投資人日簡報（SEC 8-K）：第一期滿載約 US$1B 營收、2029 損益兩平、2030 滿載（公司） | I52: 1Q26 法說逐字稿（Motley Fool）：meaningful revenue by late 2029、full impact by 2030（1Q26 法說）
A53: az_rev29_A | B53: 亞利桑那廠營收 FY2029（情境 A） | C53: US$M | E53: 500 | G53: Assumed | H53: 同上 | I53: 同上
A54: az_rev28_B | B54: 亞利桑那廠營收 FY2028（情境 B） | C54: US$M | E54: 100 | G54: Assumed | H54: 同上 | I54: 同上
A55: az_rev29_B | B55: 亞利桑那廠營收 FY2029（情境 B） | C55: US$M | E55: 400 | G55: Assumed | H55: 同上 | I55: 同上
A56: az_rev28_C | B56: 亞利桑那廠營收 FY2028（情境 C） | C56: US$M | E56: 50 | G56: Assumed | H56: 同上 | I56: 同上
A57: az_rev29_C | B57: 亞利桑那廠營收 FY2029（情境 C） | C57: US$M | E57: 250 | G57: Assumed | H57: 同上 | I57: 同上
A58: az_cm | B58: 亞利桑那廠現金邊際貢獻率（營收 − 變動現金成本） | C58: % | D58: 0.45 | E58: 0.55 | F58: 0.6 | G58: Assumed | H58: 公司：滿載毛利率 30% 以上（投資人日）；以本參數與固定成本、折舊推得滿載毛利率約 30% | I58: 第二來源：未找到
A59: az_fix27 | B59: 亞利桑那廠固定現金成本（啟動、人力）FY2027 | C59: US$M | D59: 80 | E59: 120 | F59: 170 | G59: Assumed | H59: 1Q26 法說逐字稿（Motley Fool）：啟動成本自 2027 起稀釋營業利益率約 1–2%，2028 改善（1Q26 法說） | I59: MarketBeat 2Q26 摘要：Q3 之後毛利率承受美國低稼動產能（含亞利桑那折舊）負擔
A60: az_fix28 | B60: 亞利桑那廠固定現金成本（啟動、人力）FY2028 | C60: US$M | D60: 70 | E60: 100 | F60: 150 | G60: Assumed | H60: 同上 | I60: 同上
A61: az_fix29 | B61: 亞利桑那廠固定現金成本（啟動、人力）FY2029 | C61: US$M | D61: 70 | E61: 100 | F61: 150 | G61: Assumed | H61: 同上 | I61: 同上
A62: az_capex1 | B62: 亞利桑那第一期投資 | C62: US$M | D62: 3000 | E62: 3500 | F62: 4000 | G62: Interested-party | H62: 4Q25 法說逐字稿（Motley Fool）：Phase One（約 US$7B 美國計畫的一半）施工中（4Q25 法說） | I62: 第二期擴大至合計約 US$12B（公司 2026-09-08），2027 年底動工、2029 年底完工，不在本模型
A63: az_inc | B63: 政府補助與投資抵減 ÷ 投資（降低折舊基礎） | C63: % | D63: 0.2 | E63: 0.35 | F63: 0.4 | G63: Interested-party | H63: 1Q26 法說逐字稿（Motley Fool）：CHIPS 補助約 US$400M＋35% 投資抵減，合計約 US$2.8B 對應 US$7B（1Q26 法說） | I63: 公司投資人日簡報（SEC 8-K）：投資抵減約 US$2B、CHIPS 約 US$400M；會計上是否抵減資產成本：未找到（Assumed）
A64: az_life | B64: 亞利桑那資產平均折舊年限（廠房與設備混合） | C64: 年 | D64: 8 | E64: 12 | F64: 15 | G64: Assumed | H64: 10-K：測試設備年限 2024 年起由 5 年延長為 7 年（投資人日附錄）；廠房年限較長 | I64: 混合年限：未找到
A65: az_svc28 | B65: FY2028 折舊期間占比（2028 年初投產） | C65: x | D65: 0.25 | E65: 0.5 | F65: 0.75 | G65: Assumed | H65: 公司：2027 完工、2028 投產（投資人日） | I65: —
A66: E. 毛利率、折舊、營業費用與淨利（FY2027 起）
A67: ft | B67: 本業現金毛利增量 ÷ 營收增量（現金流通率） | C67: % | D67: 0.3 | E67: 0.4 | F67: 0.5 | G67: Assumed | H67: FY2025→FY2026 錨點實測見 Q 頁（稼動率由 50% 區間升到 70% 區間，屬一次性改善） | I67: 4Q25 法說逐字稿（Motley Fool）：公司預期 2026 年增量流通率約 30%（含折舊、扣除資產出售）
A68: capi | B68: 本業資本支出 ÷ 本業營收（FY2027 起，不含亞利桑那） | C68: % | D68: 0.1 | E68: 0.14 | F68: 0.18 | G68: Assumed | H68: FY2025 資本支出 904.6 ÷ 營收 6,708＝13.5%（公司） | I68: 2026 年 30–35% 用於 HDFO、測試與先進封裝產能（公司）
A69: cap_m26 | B69: FY2026 本業資本支出（不含亞利桑那） | C69: US$M | D69: 900 | E69: 1200 | F69: 1500 | G69: Assumed | H69: 公司 2Q26 新聞稿（SEC 8-K）：FY2026 資本支出約 US$2.5–3.0B（公司）；65–70% 為廠房（含亞利桑那、韓國松島） | I69: 亞利桑那 2026 年支出：未找到
A70: life | B70: 本業資產平均折舊年限（新增資本支出） | C70: 年 | D70: 5 | E70: 7 | F70: 9 | G70: Interested-party | H70: 公司投資人日簡報（SEC 8-K）：測試設備年限 7 年（2024 年起） | I70: 其他設備年限：未找到
A71: phi | B71: 營業費用成長對營收成長的彈性（FY2027 起） | C71: x | D71: 0.3 | E71: 0.5 | F71: 1 | G71: Assumed | H71: FY2026 實測見 Q 頁（含激勵費用上升，偏高） | I71: 營業費用率 FY2025 7.0% → 2Q26 6.3%（扣除不動產處分利益前）
A72: opx_gain | B72: 2Q26 不動產處分利益（從營業費用扣除；FY2027 基期加回） | C72: US$M | E72: 21 | G72: Interested-party | H72: 2Q26 法說摘要（MarketBeat）：營業費用 119 含 21 不動產處分利益（2Q26 法說） | I72: 1Q26 法說逐字稿（Motley Fool）：2Q26 指引含約 20 處分利益
A73: nonop27 | B73: 營業外淨額（其他收益 − 利息費用）FY2027 | C73: US$M | D73: -60 | E73: -20 | F73: 20 | G73: Assumed | H73: FY2025 −22.7、1H26 −0.7（公司）；2026-05 發行 US$1.15B 零息可轉債（公司） | I73: 亞利桑那第二期動工後現金下降、負債上升（Assumed）
A74: nonop28 | B74: 營業外淨額（其他收益 − 利息費用）FY2028 | C74: US$M | D74: -80 | E74: -40 | F74: 0 | G74: Assumed | H74: 同上 | I74: 同上
A75: nonop29 | B75: 營業外淨額（其他收益 − 利息費用）FY2029 | C75: US$M | D75: -100 | E75: -60 | F75: -20 | G75: Assumed | H75: 同上 | I75: 同上
A76: tax | B76: 有效稅率（FY2027 起） | C76: % | D76: 0.15 | E76: 0.2 | F76: 0.25 | G76: Interested-party | H76: 公司投資人日簡報（SEC 8-K）：規劃稅率 20%（公司） | I76: 1Q26 法說逐字稿（Motley Fool）：全年假設 20%；1Q26 12.8%、2Q26 14%（含一次性利益）
A77: nci | B77: 非控制權益（每年） | C77: US$M | E77: 3 | G77: Derived | H77: FY2025 2.3、1H26 1.7（公司損益表推得） | I77: —
A78: sh_g | B78: 稀釋股數年變動 | C78: % | D78: -0.01 | E78: 0 | F78: 0.01 | G78: Assumed | H78: FY2025 248.5 → 2Q26 250.0 百萬股（公司）；買回授權 US$300M（投資人日） | I78: 零息可轉債的轉換稀釋：轉換價未找到
A79: F. FY2026 錨點（1H26 實績＋3Q26 公司指引＋4Q26 假設）
A80: g3_cm | B80: 3Q26 通訊季增（公司說法） | C80: % | D80: -0.1 | E80: -0.08 | F80: -0.06 | G80: Interested-party | H80: 2Q26 法說摘要（MarketBeat）：high-single-digit 季減（2Q26 法說） | I80: Benzinga 2026-07-28 同（運算近 30%、通訊 high-single-digit 季減）
A81: g3_cp | B81: 3Q26 運算季增（公司說法） | C81: % | D81: 0.25 | E81: 0.3 | F81: 0.3 | G81: Interested-party | H81: 2Q26 法說摘要（MarketBeat）：近 30% 季增（AI 資料中心、HDFO 資料中心 CPU）（2Q26 法說） | I81: Benzinga 2026-07-28 同（運算近 30%、通訊 high-single-digit 季減）
A82: g3_au | B82: 3Q26 車用與工業季增（公司說法） | C82: % | D82: 0.03 | E82: 0.05 | F82: 0.07 | G82: Interested-party | H82: 2Q26 法說摘要（MarketBeat）：mid-single-digit 季增（2Q26 法說） | I82: 第二來源：未找到
A83: g3_cs | B83: 3Q26 消費季增（公司說法） | C83: % | D83: 0.13 | E83: 0.15 | F83: 0.17 | G83: Interested-party | H83: 2Q26 法說摘要（MarketBeat）：mid-teens 季增（2Q26 法說） | I83: 第二來源：未找到
A84: q3_gm | B84: 3Q26 毛利率（指引 18.5–19.5% 中點） | C84: % | D84: 0.185 | E84: 0.19 | F84: 0.195 | G84: Interested-party | H84: 公司 2Q26 新聞稿（SEC 8-K）：3Q26 毛利率 18.5–19.5%（公司） | I84: 2Q26 法說摘要（MarketBeat）：同；主因產品組合
A85: q3_opx | B85: 3Q26 營業費用（指引） | C85: US$M | E85: 140 | G85: Interested-party | H85: 2Q26 法說摘要（MarketBeat）：約 US$140M（2Q26 法說） | I85: 第二來源：未找到
A86: q4_cm | B86: 4Q26 通訊季增 | C86: % | D86: -0.05 | E86: 0.05 | F86: 0.15 | G86: Assumed | H86: 公司未給 4Q 指引（3Q26 財報 2026-10-26 公布） | I86: 通訊：公司稱一項逆風延續到 4Q 與明年上半年（2Q26 法說），低於 4Q 正常季節性
A87: q4_cp | B87: 4Q26 運算季增 | C87: % | D87: 0 | E87: 0.05 | F87: 0.12 | G87: Assumed | H87: 同上 | I87: —
A88: q4_au | B88: 4Q26 車用與工業季增 | C88: % | D88: -0.03 | E88: 0.02 | F88: 0.05 | G88: Assumed | H88: 同上 | I88: —
A89: q4_cs | B89: 4Q26 消費季增 | C89: % | D89: -0.1 | E89: -0.05 | F89: 0 | G89: Assumed | H89: 同上 | I89: —
A90: q4_gm | B90: 4Q26 毛利率 | C90: % | D90: 0.175 | E90: 0.185 | F90: 0.195 | G90: Assumed | H90: 3Q26 指引中點 19%；公司稱 3Q 之後毛利率看稼動與組合，並承受美國產能低稼動負擔（2Q26 法說） | I90: —
A91: q4_opx | B91: 4Q26 營業費用 | C91: US$M | D91: 130 | E91: 140 | F91: 150 | G91: Assumed | H91: 同 3Q26 指引 | I91: —
A92: q_nonop | B92: 3Q、4Q26 營業外淨額（每季） | C92: US$M | D92: -10 | E92: 0 | F92: 10 | G92: Assumed | H92: 1Q26 −4.0、2Q26 +3.3（公司） | I92: —
A93: q_tax | B93: 3Q、4Q26 有效稅率 | C93: % | D93: 0.15 | E93: 0.2 | F93: 0.22 | G93: Interested-party | H93: 公司全年規劃 20%（1Q26 法說） | I93: 3Q26 指引淨利 180–205 與營業利益推得約 20%
A94: q_nci | B94: 3Q、4Q26 非控制權益（每季） | C94: US$M | E94: 1 | G94: Derived | H94: 1Q26 0.6、2Q26 1.1（公司損益表推得） | I94: —
A95: q_sh | B95: 3Q、4Q26 稀釋股數 | C95: 百萬股 | E95: 250 | G95: Derived | H95: 3Q26 指引淨利 180–205 ÷ EPS 0.72–0.82 ≈ 250（公司） | I95: 2Q26 249.978（公司）
A96: q_da3 | B96: 3Q26 折舊攤提 | C96: US$M | D96: 180 | E96: 190 | F96: 200 | G96: Assumed | H96: 1Q26 171、2Q26 180（公司）；資本支出 70% 在下半年（1Q26 法說） | I96: —
A97: q_da4 | B97: 4Q26 折舊攤提 | C97: US$M | D97: 185 | E97: 200 | F97: 215 | G97: Assumed | H97: 同上 | I97: —
A98: gain25 | B98: 4Q25 毛利中的資產出售利益（一次性） | C98: US$M | E98: 30 | G98: Interested-party | H98: 4Q25 法說逐字稿（Motley Fool）：4Q25 毛利率 16.7% 含約 US$30M 資產出售（4Q25 法說） | I98: Futurum 2026-02 同
A99: G. 公司指引與長期目標、共識（只作 Recon 對帳，不作校準）
A100: g3_rev | B100: 3Q26 營收指引（1,950–2,050 中點） | C100: US$M | D100: 1950 | E100: 2000 | F100: 2050 | G100: Interested-party | H100: 公司 2Q26 新聞稿（SEC 8-K） | I100: MarketBeat 2Q26 摘要同
A101: g3_ni | B101: 3Q26 淨利指引（180–205 中點） | C101: US$M | D101: 180 | E101: 192.5 | F101: 205 | G101: Interested-party | H101: 公司 2Q26 新聞稿（SEC 8-K） | I101: —
A102: g3_eps | B102: 3Q26 EPS 指引（0.72–0.82 中點） | C102: US$ | D102: 0.72 | E102: 0.77 | F102: 0.82 | G102: Interested-party | H102: 公司 2Q26 新聞稿（SEC 8-K） | I102: —
A103: capex26 | B103: FY2026 資本支出指引（2.5–3.0B 中點） | C103: US$M | D103: 2500 | E103: 2750 | F103: 3000 | G103: Interested-party | H103: 公司 2Q26 新聞稿（SEC 8-K） | I103: 公司 4Q25 新聞稿（SEC 8-K）（2026-02 首次給出，維持不變）
A104: t28_rev | B104: 公司 2028 營收目標（±US$0.5B） | C104: US$M | D104: 8500 | E104: 9000 | F104: 9500 | G104: Interested-party | H104: 公司投資人日簡報（SEC 8-K）（投資人日 2026-05-21） | I104: 第二來源：未找到
A105: t28_gm | B105: 公司 2028 毛利率目標（±1 個百分點） | C105: % | D105: 0.165 | E105: 0.175 | F105: 0.185 | G105: Interested-party | H105: 公司投資人日簡報（SEC 8-K） | I105: —
A106: t28_eps | B106: 公司 2028 EPS 目標（±0.25） | C106: US$ | D106: 2.25 | E106: 2.5 | F106: 2.75 | G106: Interested-party | H106: 公司投資人日簡報（SEC 8-K） | I106: 含亞利桑那第一期；不含第二期
A107: t30_rev | B107: 公司 2030 營收目標（約 11B 以上） | C107: US$M | E107: 11000 | G107: Interested-party | H107: 公司投資人日簡報（SEC 8-K） | I107: —
A108: t30_gm | B108: 公司 2030 毛利率目標（約 22% 以上） | C108: % | E108: 0.22 | G108: Interested-party | H108: 公司投資人日簡報（SEC 8-K） | I108: —
A109: t30_eps | B109: 公司 2030 EPS 目標（約 5 以上） | C109: US$ | E109: 5 | G109: Interested-party | H109: 公司投資人日簡報（SEC 8-K） | I109: —
...

Sheet Q
A1: Q — 實績與 FY2026 錨點（百萬美元；EPS 為美元、稀釋；股數為百萬股）。藍字＝輸入（SEC 8-K 新聞稿）；黑字＝公式。1Q26＝1H26 − 2Q26（Derived）
A2: FY2026 錨點＝1Q、2Q26 實績＋3Q26 公司指引（營收依各終端市場季增說法、毛利率與營業費用指引）＋4Q26 假設。3Q26 財報 2026-10-26 公布，本版尚未納入，屆時以實績取代 E 欄
A3: 項目 | B3: FY2025A | C3: 1Q26（實績） | D3: 2Q26（實績） | E3: 3Q26（指引） | F3: 4Q26（模型） | G3: FY2026 錨點 | H3: 標記 | I3: 來源1（公司） | J3: 來源2／說明
A4: 營收 | B4: 6708 | C4: =3582.7-D4 -> 1684.7 | D4: 1898 | E4: =SUM(E5:E8) -> 2020.2312 | F4: =SUM(F5:F8) -> 2077.5318 | G4: =SUM(C4:F4) -> 7680.463 | H4: Verified／Derived | I4: FY2025：4Q25 新聞稿（SEC 8-K）；1H26、2Q26：2Q26 新聞稿（SEC 8-K） | J4: stockanalysis：FY2025 6,708；1H26 3,582.7、2Q26 1,898.0（公司）
A5: 通訊（手機、平板） | B5: =B4*0.46 -> 3085.68 | C5: =C4*0.44 -> 741.268 | D5: =D4*0.42 -> 797.16 | E5: =D5*(1+g3_cm) -> 733.3872 | F5: =E5*(1+q4_cm) -> 770.05656 | G5: =SUM(C5:F5) -> 3041.8718 | H5: Derived（占比 × 營收）／Interested-party | I5: FY2025：4Q25 新聞稿（SEC 8-K）；1H26、2Q26：2Q26 新聞稿（SEC 8-K） | J5: 占比：FY2025 46%、1Q26 44%、2Q26 42%（公司）
A6: 運算（資料中心、基礎設施、PC、儲存） | B6: =B4*0.2 -> 1341.6 | C6: =C4*0.21 -> 353.787 | D6: =D4*0.22 -> 417.56 | E6: =D6*(1+g3_cp) -> 542.828 | F6: =E6*(1+q4_cp) -> 569.9694 | G6: =SUM(C6:F6) -> 1884.1444 | H6: Derived／Interested-party | I6: FY2025：4Q25 新聞稿（SEC 8-K）；1H26、2Q26：2Q26 新聞稿（SEC 8-K） | J6: 占比：20%、21%、22%（公司）
A7: 車用、工業與其他 | B7: =B4*0.19 -> 1274.52 | C7: =C4*0.21 -> 353.787 | D7: =D4*0.22 -> 417.56 | E7: =D7*(1+g3_au) -> 438.438 | F7: =E7*(1+q4_au) -> 447.20676 | G7: =SUM(C7:F7) -> 1656.9918 | H7: Derived／Interested-party | I7: FY2025：4Q25 新聞稿（SEC 8-K）；1H26、2Q26：2Q26 新聞稿（SEC 8-K） | J7: 占比：19%、21%、22%（公司）
A8: 消費 | B8: =B4*0.15 -> 1006.2 | C8: =C4*0.14 -> 235.858 | D8: =D4*0.14 -> 265.72 | E8: =D8*(1+g3_cs) -> 305.578 | F8: =E8*(1+q4_cs) -> 290.2991 | G8: =SUM(C8:F8) -> 1097.4551 | H8: Derived／Interested-party | I8: FY2025：4Q25 新聞稿（SEC 8-K）；1H26、2Q26：2Q26 新聞稿（SEC 8-K） | J8: 占比：15%、14%、14%（公司）
A9: 毛利 | B9: 938.6 | C9: =557.6-D9 -> 239 | D9: 318.6 | E9: =E4*q3_gm -> 383.84393 | F9: =F4*q4_gm -> 384.34339 | G9: =SUM(C9:F9) -> 1325.7873 | H9: Verified／Interested-party（3Q）／Assumed（4Q） | I9: FY2025：4Q25 新聞稿（SEC 8-K）；1H26、2Q26：2Q26 新聞稿（SEC 8-K） | J9: FY2025 含 4Q25 資產出售約 30（公司法說）
A10: 毛利率 | B10: =B9/B4 -> 0.13992248 | C10: =C9/C4 -> 0.14186502 | D10: =D9/D4 -> 0.16786091 | E10: =E9/E4 -> 0.19 | F10: =F9/F4 -> 0.185 | G10: =G9/G4 -> 0.17261815 | H10: Derived | I10: — | J10: 公司：FY2025 14.0%、1Q26 14.2%、2Q26 16.8%
A11: 營業費用（銷管＋研發） | B11: =304.5+166.7 -> 471.2 | C11: =(175.9+81.6)-D11 -> 138.8 | D11: =78.9+39.8 -> 118.7 | E11: =q3_opx -> 140 | F11: =q4_opx -> 140 | G11: =SUM(C11:F11) -> 537.5 | H11: Verified／Interested-party | I11: FY2025：4Q25 新聞稿（SEC 8-K）；1H26、2Q26：2Q26 新聞稿（SEC 8-K） | J11: 2Q26 含不動產處分利益 21（降低費用）
A12: 營業利益 | B12: =B9-B11 -> 467.4 | C12: =C9-C11 -> 100.2 | D12: =D9-D11 -> 199.9 | E12: =E9-E11 -> 243.84393 | F12: =F9-F11 -> 244.34339 | G12: =SUM(C12:F12) -> 788.28731 | H12: Derived | I12: FY2025：4Q25 新聞稿（SEC 8-K）；1H26、2Q26：2Q26 新聞稿（SEC 8-K） | J12: 公司：FY2025 467.4、1H26 300.1、2Q26 199.9（核對見第 31 列）
A13: 營業外淨額（其他收益 − 利息費用） | B13: =52.7-75.4 -> -22.7 | C13: =(34-34.7)-D13 -> -4 | D13: =20.3-17 -> 3.3 | E13: =q_nonop -> 0 | F13: =q_nonop -> 0 | G13: =SUM(C13:F13) -> -0.7 | H13: Verified／Assumed | I13: FY2025：4Q25 新聞稿（SEC 8-K）；1H26、2Q26：2Q26 新聞稿（SEC 8-K） | J13: 其他收益含利息收入與匯兌（公司）
A14: 稅前利益 | B14: =B12+B13 -> 444.7 | C14: =C12+C13 -> 96.2 | D14: =D12+D13 -> 203.2 | E14: =E12+E13 -> 243.84393 | F14: =F12+F13 -> 244.34339 | G14: =SUM(C14:F14) -> 787.58731 | H14: Derived | I14: — | J14: —
A15: 所得稅 | B15: 68.5 | C15: =40.6-D15 -> 12.3 | D15: 28.3 | E15: =E14*q_tax -> 48.768786 | F15: =F14*q_tax -> 48.868677 | G15: =SUM(C15:F15) -> 138.23746 | H15: Verified／Interested-party | I15: FY2025：4Q25 新聞稿（SEC 8-K）；1H26、2Q26：2Q26 新聞稿（SEC 8-K） | J15: FY2025 有效稅率 15.4%（含遞延稅資產一次性利益）
A16: 非控制權益 | B16: =B14-B15-B17 -> 2.3 | C16: =C14-C15-C17 -> 0.6 | D16: =D14-D15-D17 -> 1.1 | E16: =q_nci -> 1 | F16: =q_nci -> 1 | G16: =SUM(C16:F16) -> 3.7 | H16: Derived | I16: 稅後 − 歸屬母公司淨利 | J16: —
A17: 歸屬母公司淨利 | B17: 373.9 | C17: =257.1-D17 -> 83.3 | D17: 173.8 | E17: =E14-E15-E16 -> 194.07514 | F17: =F14-F15-F16 -> 194.47471 | G17: =SUM(C17:F17) -> 645.64985 | H17: Verified／Derived | I17: FY2025：4Q25 新聞稿（SEC 8-K）；1H26、2Q26：2Q26 新聞稿（SEC 8-K） | J17: 1Q26 83（公司）
A18: 稀釋股數（百萬股） | B18: 248.5 | C18: =2*249.83-D18 -> 249.682 | D18: 249.978 | E18: =q_sh -> 250 | F18: =q_sh -> 250 | G18: =AVERAGE(C18:F18) -> 249.915 | H18: Verified／Derived | I18: FY2025：4Q25 新聞稿（SEC 8-K）；1H26、2Q26：2Q26 新聞稿（SEC 8-K） | J18: 1Q26＝2 × 1H26 加權 − 2Q26（Derived）
A19: EPS（稀釋） | B19: =B17/B18 -> 1.5046278 | C19: =C17/C18 -> 0.33362437 | D19: =D17/D18 -> 0.69526118 | E19: =E17/E18 -> 0.77630057 | F19: =F17/F18 -> 0.77789884 | G19: =G17/G18 -> 2.5834778 | H19: Derived | I19: 淨利 ÷ 股數 | J19: —
A20: 公司揭露 EPS | B20: 1.5 | C20: 0.33 | D20: 0.7 | H20: Verified | I20: FY2025：4Q25 新聞稿（SEC 8-K）；1H26、2Q26：2Q26 新聞稿（SEC 8-K） | J20: —
A21: 折舊攤提 | B21: 642 | C21: =350.6-D21 -> 170.6 | D21: 180 | E21: =q_da3 -> 190 | F21: =q_da4 -> 200 | G21: =SUM(C21:F21) -> 740.6 | H21: Verified／Assumed | I21: FY2025：4Q25 新聞稿（SEC 8-K）；1H26、2Q26：2Q26 新聞稿（SEC 8-K） | J21: 投資人日：LTM 1Q26 659
A22: 現金毛利（毛利＋折舊攤提） | B22: =B9+B21 -> 1580.6 | C22: =C9+C21 -> 409.6 | D22: =D9+D21 -> 498.6 | E22: =E9+E21 -> 573.84393 | F22: =F9+F21 -> 584.34339 | G22: =SUM(C22:F22) -> 2066.3873 | H22: Derived | I22: 假設折舊攤提全數在銷貨成本（近似） | J22: —
A24: FY2026 錨點的檢查（參考；校準未使用券商數字）
A25: FY2026 營收年增 | B25: =G4/B4-1 -> 0.14497064
A26: FY2026 運算年增（公司 2026-02 說法：超過 20%） | B26: =G6/B6-1 -> 0.40440101
A27: 現金毛利增量 ÷ 營收增量（FY2025 扣除資產出售利益；In 頁 ft 的對照） | B27: =(G22-(B22-gain25))/(G4-B4) -> 0.53039273
A28: 營業費用彈性（扣除 2Q26 處分利益；In 頁 phi 的對照） | B28: =((G11+opx_gain)/B11-1)/(G4/B4-1) -> 1.2779943
A29: 3Q26 營收 ÷ 指引中點 − 1 | B29: =E4/g3_rev-1 -> 0.0101156
A30: 3Q26 EPS ÷ 指引中點 − 1 | B30: =E19/g3_eps-1 -> 0.0081825579
A31: FY2025 營業利益 自算 − 公司公布 467.4（應為 0） | B31: =B12-467.4 -> 0
A32: 1H26 營業利益 自算 − 公司公布 300.1（應為 0） | B32: =C12+D12-300.1 -> 0
A34: 檢查：分部合計 − 合併營收 | B34: =ROUND(B5+B6+B7+B8-B4,3) -> 0 | C34: =ROUND(C5+C6+C7+C8-C4,3) -> 0 | D34: =ROUND(D5+D6+D7+D8-D4,3) -> 0 | E34: =ROUND(E5+E6+E7+E8-E4,3) -> 0 | F34: =ROUND(F5+F6+F7+F8-F4,3) -> 0 | G34: =ROUND(G5+G6+G7+G8-G4,3) -> 0
A35: 分部原則第 3 條（2026-10-28 追加）：終端市場別營收（公司揭露比重 × 營收）；分部宣告見 segments.json

Sheet Units
A1: Units — AI 加速器顆數（tsmc 成品）→ Amkor AI 先進封裝營收（情境 A）。部署 GW＝AI IT 資本支出（markets/network）÷ 每 GW IT 資本支出（Tokenomics，經橋接表），只作 Recon
A3: 項目 | B3: 單位 | C3: CY2026 | D3: CY2027 | E3: CY2028 | F3: CY2029 | G3: 說明
A4: AI 加速器顆數（情境 A） | B4: 百萬顆 | C4: =PL!D63 -> 15.2 | D4: =PL!E63 -> 23.7 | E4: =PL!F63 -> 26.5 | F4: =PL!G63 -> 30.15 | G4: tsmc 成品 In 頁（台積電模型與 HBM、網通同一份）
A5: 封裝面積指數（2026＝1） | B5: x | C5: =PL!D64 -> 1 | D5: =PL!E64 -> 1.278156 | E5: =PL!F64 -> 1.428615 | F5: =PL!G64 -> 1.431796 | G5: 加速器用 CoWoS 片數 ÷ 顆數（tsmc 成品 CoWoS 頁）
A6: 後段委外比例 | B6: % | C6: =PL!D65 -> 0.5 | D6: =PL!E65 -> 0.55 | E6: =PL!F65 -> 0.6 | F6: =PL!G65 -> 0.6 | G6: Assumed
A7: Amkor 份額（占委外後段） | B7: % | C7: =PL!D66 -> 0.35 | D7: =PL!E66 -> 0.35 | E7: =PL!F66 -> 0.37 | F7: =PL!G66 -> 0.38 | G7: Assumed
A8: 每顆封測金額 | B8: US$／顆 | C8: =PL!D68 -> 323.78555 | D8: =PL!E68 -> 366.05757 | E8: =PL!F68 -> 387.00365 | F8: =PL!G68 -> 387.43427 | G8: FY2026 校準；之後隨封裝面積
A9: Amkor AI 先進封裝營收 | B9: US$M | C9: =PL!D67 -> 861.26956 | D9: =PL!E67 -> 1670.0461 | E9: =PL!F67 -> 2276.7425 | F9: =PL!G67 -> 2663.3007 | G9: 顆數 × 委外 × 份額 × 每顆金額
A10: 每顆加速器的 Amkor AI 營收 | B10: US$／顆 | C10: =PL!D69 -> 56.662471 | D10: =PL!E69 -> 70.466082 | E10: =PL!F69 -> 85.914811 | F10: =PL!G69 -> 88.335013
A11: 部署 GW（AI IT 資本支出 ÷ 每 GW IT 資本支出） | B11: GW | C11: =itc_26/(capit_gb*(1-vr26)+capit_vr*vr26) -> 23.399538 | D11: =itc_27/capit_vr -> 41.646766 | E11: =itc_28/capit_vr -> 52.792138 | F11: =itc_29/capit_vr -> 60.138592 | G11: 2026 依 vr26 混合 GB300 與 VR200（v0.4 起，與其他模型同口徑）、2027 起用 VR200
A12: OSAT 先進封裝市場（GW × US$0.5B） | B12: US$M | C12: =C11*tam_gw*1000 -> 11699.769 | D12: =D11*tam_gw*1000 -> 20823.383 | E12: =E11*tam_gw*1000 -> 26396.069 | F12: =F11*tam_gw*1000 -> 30069.296 | G12: 公司投資人日口徑（Interested-party）
A13: Amkor AI 營收 ÷ OSAT 先進封裝市場 | B13: % | C13: =C9/C12 -> 0.073614236 | D13: =D9/D12 -> 0.08020052 | E13: =E9/E12 -> 0.086253088 | F13: =F9/F12 -> 0.088572099 | G13: 隱含市占（對照用）
A15: 讀法：AI 先進封裝 FY2026 以公司「約三倍」說法與運算營收反推，不是公司揭露數字；委外比例與份額是 Assumed，只有相對變化影響 FY2027 起的營收。每顆封測金額隨封裝面積上升（彈性 0.5），所以 Rubin 世代單顆金額高於 Blackwell。

Sheet PL
A1: PL — Amkor 損益（百萬美元；EPS 美元、稀釋；歸屬母公司）。FY2025A 實績、FY2026 錨點（1H26 實績＋3Q26 指引＋4Q26 假設；三情境相同），FY2027 起為模型。FY(t)＝CY(t)。三情境各一個完整推導區塊（本頁下方），頂端為摘要
A2: 灰底＝FY2030–FY2032 收斂法（上游只到 2029）：營收年增線性收斂到 fade_g、淨利率線性收斂到 fade_m（In 頁 I 節），非驅動因子推導
A3: 情境／項目 | B3: 單位 | C3: FY2025A | D3: FY2026（錨點） | E3: FY2027 | F3: FY2028 | G3: FY2029 | H3: FY2030（收斂） | I3: FY2031（收斂） | J3: FY2032（收斂） | K3: 說明
A4: 情境 A
A5: 營收 | B5: US$M | C5: =C77 -> 6708 | D5: =D77 -> 7680.463 | E5: =E77 -> 8809.8048 | F5: =F77 -> 9939.6136 | G5: =G77 -> 11074.49 | H5: =H77 -> 12138.948 | I5: =I77 -> 13086.502 | J5: =J77 -> 13871.693
A6: 營收年增 | B6: % | D6: =D78 -> 0.14497064 | E6: =E78 -> 0.14704085 | F6: =F78 -> 0.12824447 | G6: =G78 -> 0.11417708 | H6: =H78 -> 0.096118052 | I6: =I78 -> 0.078059026 | J6: =J78 -> 0.06
A7: AI 先進封裝 | B7: US$M | C7: =C67 -> 287.08985 | D7: =D67 -> 861.26956 | E7: =E67 -> 1670.0461 | F7: =F67 -> 2276.7425 | G7: =G67 -> 2663.3007
A8: 運算合計 | B8: US$M | C8: =C72 -> 1341.6 | D8: =D72 -> 1884.1444 | E8: =E72 -> 2723.6072 | F8: =F72 -> 3361.9104 | G8: =G72 -> 3781.0236
A9: 通訊 | B9: US$M | C9: =C73 -> 3085.68 | D9: =D73 -> 3041.8718 | E9: =E73 -> 3133.1279 | F9: =F73 -> 3258.453 | G9: =G73 -> 3388.7912
A10: 車用、工業與其他 | B10: US$M | C10: =C74 -> 1274.52 | D10: =D74 -> 1656.9918 | E10: =E74 -> 1822.6909 | F10: =F74 -> 2004.96 | G10: =G74 -> 2205.456
A11: 亞利桑那廠 | B11: US$M | C11: =C76 -> 0 | D11: =D76 -> 0 | E11: =E76 -> 0 | F11: =F76 -> 150 | G11: =G76 -> 500
A12: 毛利率 | B12: % | C12: =C90 -> 0.13992248 | D12: =D90 -> 0.17261815 | E12: =E90 -> 0.18069588 | F12: =F90 -> 0.19422352 | G12: =G90 -> 0.2049996
A13: 營業利益率 | B13: % | C13: =C94 -> 0.069677996 | D13: =D94 -> 0.10263539 | E13: =E94 -> 0.11263976 | F13: =F94 -> 0.13003527 | G13: =G94 -> 0.14410025
A14: 歸屬母公司淨利 | B14: US$M | C14: =C99 -> 373.9 | D14: =D99 -> 645.64985 | E14: =E99 -> 774.86745 | F14: =F99 -> 999.00028 | G14: =G99 -> 1225.6694 | H14: =H99 -> 1343.4783 | I14: =I99 -> 1448.3489 | J14: =J99 -> 1535.2499
A15: 淨利率 | B15: % | C15: =C103 -> 0.055739416 | D15: =D103 -> 0.084063923 | E15: =E103 -> 0.087955121 | F15: =F103 -> 0.10050695 | G15: =G103 -> 0.11067502 | H15: =H103 -> 0.11067502 | I15: =I103 -> 0.11067502 | J15: =J103 -> 0.11067502
A16: EPS | B16: US$ | C16: =C101 -> 1.5046278 | D16: =D101 -> 2.5834778 | E16: =E101 -> 3.100524 | F16: =F101 -> 3.9973602 | G16: =G101 -> 4.904345 | H16: =H101 -> 5.3757411 | I16: =I101 -> 5.7953662 | J16: =J101 -> 6.1430881
A17: EPS 年增 | B17: % | D17: =D102 -> 0.71702121 | E17: =E102 -> 0.20013572 | F17: =F102 -> 0.28925313 | G17: =G102 -> 0.22689592 | H17: =H102 -> 0.096118052 | I17: =I102 -> 0.078059026 | J17: =J102 -> 0.06
A19: 情境 B
A20: 營收 | B20: US$M | C20: =C123 -> 6708 | D20: =D123 -> 7680.463 | E20: =E123 -> 8718.5487 | F20: =F123 -> 9308.94 | G20: =G123 -> 10413.325 | H20: =H123 -> 11375.774 | I20: =I123 -> 12128.99 | J20: =J123 -> 12614.15
A21: 營收年增 | B21: % | D21: =D124 -> 0.14497064 | E21: =E124 -> 0.13515926 | F21: =F124 -> 0.067716693 | G21: =G124 -> 0.11863705 | H21: =H124 -> 0.092424698 | I21: =I124 -> 0.066212349 | J21: =J124 -> 0.04
A22: AI 先進封裝 | B22: US$M | C22: =C113 -> 287.08985 | D22: =D113 -> 861.26956 | E22: =E113 -> 1670.0461 | F22: =F113 -> 1821.394 | G22: =G113 -> 2263.8056
A23: 運算合計 | B23: US$M | C23: =C118 -> 1341.6 | D23: =D118 -> 1884.1444 | E23: =E118 -> 2723.6072 | F23: =F118 -> 2906.5619 | G23: =G118 -> 3381.5285
A24: 通訊 | B24: US$M | C24: =C119 -> 3085.68 | D24: =D119 -> 3041.8718 | E24: =E119 -> 3041.8718 | F24: =F119 -> 3133.1279 | G24: =G119 -> 3227.1218
A25: 車用、工業與其他 | B25: US$M | C25: =C120 -> 1274.52 | D25: =D120 -> 1656.9918 | E25: =E120 -> 1822.6909 | F25: =F120 -> 2004.96 | G25: =G120 -> 2205.456
A26: 亞利桑那廠 | B26: US$M | C26: =C122 -> 0 | D26: =D122 -> 0 | E26: =E122 -> 0 | F26: =F122 -> 100 | G26: =G122 -> 400
A27: 毛利率 | B27: % | C27: =C136 -> 0.13992248 | D27: =D136 -> 0.17261815 | E27: =E136 -> 0.17840045 | F27: =F136 -> 0.1796727 | G27: =G136 -> 0.19244362
A28: 營業利益率 | B28: % | C28: =C140 -> 0.069677996 | D28: =D140 -> 0.10263539 | E28: =E140 -> 0.11001255 | F28: =F140 -> 0.11345345 | G28: =G140 -> 0.12973581
A29: 歸屬母公司淨利 | B29: US$M | C29: =C145 -> 373.9 | D29: =D145 -> 645.64985 | E29: =E145 -> 748.31983 | F29: =F145 -> 809.90509 | G29: =G145 -> 1029.7849 | H29: =H145 -> 1053.2285 | I29: =I145 -> 1046.4815 | J29: =J145 -> 1008.7977
A30: 淨利率 | B30: % | C30: =C149 -> 0.055739416 | D30: =D149 -> 0.084063923 | E30: =E149 -> 0.085830779 | F30: =F149 -> 0.087002934 | G30: =G149 -> 0.098891078 | H30: =H149 -> 0.092585218 | I30: =I149 -> 0.086279358 | J30: =J149 -> 0.079973498
A31: EPS | B31: US$ | C31: =C147 -> 1.5046278 | D31: =D147 -> 2.5834778 | E31: =E147 -> 2.9942974 | F31: =F147 -> 3.2407222 | G31: =G147 -> 4.1205408 | H31: =H147 -> 4.2143468 | I31: =I147 -> 4.1873497 | J31: =J147 -> 4.0365632
A32: EPS 年增 | B32: % | D32: =D148 -> 0.71702121 | E32: =E148 -> 0.15901804 | F32: =F148 -> 0.082298045 | G32: =G148 -> 0.27148843 | H32: =H148 -> 0.022765459 | I32: =I148 -> -0.0064060015 | J32: =J148 -> -0.036010005
A34: 情境 C
A35: 營收 | B35: US$M | C35: =C169 -> 6708 | D35: =D169 -> 7680.463 | E35: =E169 -> 8536.0364 | F35: =F169 -> 8529.823 | G35: =G169 -> 9229.7377 | H35: =H169 -> 9796.1667 | I35: =I169 -> 10194.724 | J35: =J169 -> 10398.618
A36: 營收年增 | B36: % | D36: =D170 -> 0.14497064 | E36: =E170 -> 0.11139606 | F36: =F170 -> -0.00072789836 | G36: =G170 -> 0.082055002 | H36: =H170 -> 0.061370002 | I36: =I170 -> 0.040685001 | J36: =J170 -> 0.02
A37: AI 先進封裝 | B37: US$M | C37: =C159 -> 287.08985 | D37: =D159 -> 861.26956 | E37: =E159 -> 1670.0461 | F37: =F159 -> 1366.0455 | G37: =G159 -> 1597.9804
A38: 運算合計 | B38: US$M | C38: =C164 -> 1341.6 | D38: =D164 -> 1884.1444 | E38: =E164 -> 2723.6072 | F38: =F164 -> 2451.2134 | G38: =G164 -> 2715.7034
A39: 通訊 | B39: US$M | C39: =C165 -> 3085.68 | D39: =D165 -> 3041.8718 | E39: =E165 -> 2859.3595 | F39: =F165 -> 2859.3595 | G39: =G165 -> 2859.3595
A40: 車用、工業與其他 | B40: US$M | C40: =C166 -> 1274.52 | D40: =D166 -> 1656.9918 | E40: =E166 -> 1822.6909 | F40: =F166 -> 2004.96 | G40: =G166 -> 2205.456
A41: 亞利桑那廠 | B41: US$M | C41: =C168 -> 0 | D41: =D168 -> 0 | E41: =E168 -> 0 | F41: =F168 -> 50 | G41: =G168 -> 250
A42: 毛利率 | B42: % | C42: =C182 -> 0.13992248 | D42: =D182 -> 0.17261815 | E42: =E182 -> 0.17366234 | F42: =F182 -> 0.1590966 | G42: =G182 -> 0.1653085
A43: 營業利益率 | B43: % | C43: =C186 -> 0.069677996 | D43: =D186 -> 0.10263539 | E43: =E186 -> 0.10458961 | F43: =F186 -> 0.089998713 | G43: =G186 -> 0.09883055
A44: 歸屬母公司淨利 | B44: US$M | C44: =C191 -> 373.9 | D44: =D191 -> 645.64985 | E44: =E191 -> 695.22459 | F44: =F191 -> 579.13847 | G44: =G191 -> 678.74404 | H44: =H191 -> 679.63703 | I44: =I191 -> 664.86814 | J44: =J191 -> 634.89718
A45: 淨利率 | B45: % | C45: =C195 -> 0.055739416 | D45: =D195 -> 0.084063923 | E45: =E195 -> 0.081445832 | F45: =F195 -> 0.06789572 | G45: =G195 -> 0.073538823 | H45: =H195 -> 0.069377854 | I45: =I195 -> 0.065216886 | J45: =J195 -> 0.061055918
A46: EPS | B46: US$ | C46: =C193 -> 1.5046278 | D46: =D193 -> 2.5834778 | E46: =E193 -> 2.7818442 | F46: =F193 -> 2.3173418 | G46: =G193 -> 2.7158996 | H46: =H193 -> 2.7194727 | I46: =I193 -> 2.6603771 | J46: =J193 -> 2.5404525
A47: EPS 年增 | B47: % | D47: =D194 -> 0.71702121 | E47: =E194 -> 0.076782696 | F47: =F194 -> -0.16697642 | G47: =G194 -> 0.17198921 | H47: =H194 -> 0.0013156412 | I47: =I194 -> -0.021730555 | J47: =J194 -> -0.045078049
A49: 核對（應為 0）：FY2026 模型 − 錨點
A50: 三情境：營收差（US$M） | D50: =ABS(D77-a26_rev)+ABS(D123-a26_rev)+ABS(D169-a26_rev) -> 0
A51: 三情境：EPS 差（US$） | D51: =ABS(D101-a26_eps)+ABS(D147-a26_eps)+ABS(D193-a26_eps) -> 0
A52: 情境 A：AI＋非 AI 運算 − Q 頁運算（US$M） | D52: =D67+D71-a26_comp -> 0
A60: 情境 A：顆數基準；通訊 FY2027 +3%、之後 +4%；亞利桑那 FY2028 營收 150、FY2029 500
A61: 項目 | B61: 單位 | C61: FY2025A | D61: FY2026（錨點） | E61: FY2027 | F61: FY2028 | G61: FY2029 | H61: FY2030（收斂） | I61: FY2031（收斂） | J61: FY2032（收斂） | K61: 說明
A62: A. AI 加速器 → Amkor AI 先進封裝（D 欄＝FY2026 校準年）
A63: AI 加速器顆數（含情境係數） | B63: 百萬顆 | D63: =units_26 -> 15.2 | E63: =units_27*1 -> 23.7 | F63: =units_28*um28_A*1 -> 26.5 | G63: =units_29*um29_A*1 -> 30.15
A64: 封裝面積指數（2026＝1） | B64: x | D64: =ar_26 -> 1 | E64: =ar_27 -> 1.278156 | F64: =ar_28 -> 1.428615 | G64: =ar_29 -> 1.431796
A65: 後段委外比例 | B65: % | D65: =out_26 -> 0.5 | E65: =out_27 -> 0.55 | F65: =out_28 -> 0.6 | G65: =out_29 -> 0.6 | K65: FY2026 固定基準值（Sens 只動 FY2027 起）
A66: Amkor 份額（占委外後段） | B66: % | D66: =sh_26 -> 0.35 | E66: =sh_27 -> 0.35 | F66: =sh_28 -> 0.37 | G66: =sh_29 -> 0.38
A67: AI 先進封裝營收（2.5D、HDFO、AI 測試） | B67: US$M | C67: =(a26_comp-a25_comp*(1+g_pc26))/(tri-(1+g_pc26)) -> 287.08985 | D67: =C67*tri -> 861.26956 | E67: =E63*E65*E66*E68 -> 1670.0461 | F67: =F63*F65*F66*F68 -> 2276.7425 | G67: =G63*G65*G66*G68 -> 2663.3007 | K67: FY2025、FY2026：由運算營收與公司「約三倍」說法反推（Derived）；FY2027 起＝顆數 × 委外 × 份額 × 每顆金額
A68: 每顆封測金額（Amkor 營收 ÷ 委外 ÷ 份額） | B68: US$／顆 | D68: =D67/(D63*D65*D66) -> 323.78555 | E68: =$D68*E64^el -> 366.05757 | F68: =$D68*F64^el -> 387.00365 | G68: =$D68*G64^el -> 387.43427 | K68: FY2026 校準（Derived）；之後 × 封裝面積指數 ^ 彈性
A69: 每顆加速器的 Amkor AI 營收 | B69: US$／顆 | D69: =D67/D63 -> 56.662471 | E69: =E67/E63 -> 70.466082 | F69: =F67/F63 -> 85.914811 | G69: =G67/G63 -> 88.335013 | K69: 含資料中心 CPU 的 HDFO 等連帶營收（拆分未揭露）
A70: B. 終端市場與合計
A71: 運算（非 AI：PC、儲存、基礎設施） | B71: US$M | C71: =a25_comp-C67 -> 1054.5101 | D71: =a26_comp-D67 -> 1022.8748 | E71: =D71*(1+g_pc) -> 1053.5611 | F71: =E71*(1+g_pc) -> 1085.1679 | G71: =F71*(1+g_pc) -> 1117.723
A72: 運算合計 | B72: US$M | C72: =C67+C71 -> 1341.6 | D72: =D67+D71 -> 1884.1444 | E72: =E67+E71 -> 2723.6072 | F72: =F67+F71 -> 3361.9104 | G72: =G67+G71 -> 3781.0236
A73: 通訊（Apple 占 FY2025 營收 29.8%） | B73: US$M | C73: =a25_cm -> 3085.68 | D73: =a26_cm -> 3041.8718 | E73: =D73*(1+g_cm27_A) -> 3133.1279 | F73: =E73*(1+g_cmL_A) -> 3258.453 | G73: =F73*(1+g_cmL_A) -> 3388.7912
A74: 車用、工業與其他 | B74: US$M | C74: =a25_au -> 1274.52 | D74: =a26_au -> 1656.9918 | E74: =D74*(1+g_au) -> 1822.6909 | F74: =E74*(1+g_au) -> 2004.96 | G74: =F74*(1+g_au) -> 2205.456
A75: 消費 | B75: US$M | C75: =a25_cs -> 1006.2 | D75: =a26_cs -> 1097.4551 | E75: =D75*(1+g_cs) -> 1130.3788 | F75: =E75*(1+g_cs) -> 1164.2901 | G75: =F75*(1+g_cs) -> 1199.2188
A76: 亞利桑那廠營收（第一期） | B76: US$M | C76: =0 -> 0 | D76: =0 -> 0 | E76: =0 -> 0 | F76: =az_rev28_A -> 150 | G76: =az_rev29_A -> 500 | K76: 第一期滿載約 US$1B（公司）；與既有客戶的亞洲產能可能部分替代（限制）
A77: 營收 | B77: US$M | C77: =C72+C73+C74+C75+C76 -> 6708 | D77: =D72+D73+D74+D75+D76 -> 7680.463 | E77: =E72+E73+E74+E75+E76 -> 8809.8048 | F77: =F72+F73+F74+F75+F76 -> 9939.6136 | G77: =G72+G73+G74+G75+G76 -> 11074.49 | H77: =G77*(1+H78) -> 12138.948 | I77: =H77*(1+I78) -> 13086.502 | J77: =I77*(1+J78) -> 13871.693 | K77: FY2030 起為收斂法：營收年增由 FY2029 線性收斂到 fade_g、淨利率收斂到 fade_m（FY2032 達到），非驅動因子推導
A78: 營收年增 | B78: % | D78: =D77/C77-1 -> 0.14497064 | E78: =E77/D77-1 -> 0.14704085 | F78: =F77/E77-1 -> 0.12824447 | G78: =G77/F77-1 -> 0.11417708 | H78: =$G78+(fade_gA-$G78)*1/3 -> 0.096118052 | I78: =$G78+(fade_gA-$G78)*2/3 -> 0.078059026 | J78: =$G78+(fade_gA-$G78)*3/3 -> 0.06
A79: AI 先進封裝 ÷ 營收 | B79: % | C79: =C67/C77 -> 0.042798129 | D79: =D67/D77 -> 0.11213771 | E79: =E67/E77 -> 0.18956676 | F79: =F67/F77 -> 0.22905744 | G79: =G67/G77 -> 0.2404897
A80: 通訊 ÷ 營收 | B80: % | C80: =C73/C77 -> 0.46 | D80: =D73/D77 -> 0.39605317 | E80: =E73/E77 -> 0.35564101 | F80: =F73/F77 -> 0.32782492 | G80: =G73/G77 -> 0.30599976
A81: C. 折舊、毛利與損益
A82: 本業營收（不含亞利桑那） | B82: US$M | C82: =C77-C76 -> 6708 | D82: =D77-D76 -> 7680.463 | E82: =E77-E76 -> 8809.8048 | F82: =F77-F76 -> 9789.6136 | G82: =G77-G76 -> 10574.49
A83: 本業資本支出（不含亞利桑那） | B83: US$M | D83: =cap_m26 -> 1200 | E83: =capi*E82 -> 1233.3727 | F83: =capi*F82 -> 1370.5459 | G83: =capi*G82 -> 1480.4285 | K83: FY2026 為 Assumed（總額 2.5–3.0B 扣除亞利桑那）；之後＝本業營收 × 資本支出率
A84: 本業折舊攤提 | B84: US$M | C84: =a25_da -> 642 | D84: =a26_da -> 740.6 | E84: =D84*(1-1/life)+D83/life -> 806.22857 | F84: =E84*(1-1/life)+E83/life -> 867.24916 | G84: =F84*(1-1/life)+F83/life -> 939.14869 | K84: 前一年 ×（1 − 1／年限）＋前一年資本支出 ÷ 年限
A85: 亞利桑那折舊（第一期，扣除補助與抵減） | B85: US$M | E85: =0 -> 0 | F85: =az_capex1*(1-az_inc)/az_life*az_svc28 -> 94.791667 | G85: =az_capex1*(1-az_inc)/az_life -> 189.58333
A86: 折舊攤提合計 | B86: US$M | C86: =C84 -> 642 | D86: =D84 -> 740.6 | E86: =E84+E85 -> 806.22857 | F86: =F84+F85 -> 962.04082 | G86: =G84+G85 -> 1128.732
A87: 本業毛利 ＝ FY2026 ＋ 流通率 × 本業營收增量 − 本業折舊增量 | B87: US$M | C87: =a25_gp -> 938.6 | D87: =a26_gp -> 1325.7873 | E87: =$D87+ft*(E82-$D82)-(E84-$D84) -> 1711.8955 | F87: =$D87+ft*(F82-$D82)-(F84-$D84) -> 2042.7984 | G87: =$D87+ft*(G82-$D82)-(G84-$D84) -> 2284.8493 | K87: 流通率為現金毛利口徑；折舊另計
A88: 亞利桑那毛利 ＝ 營收 × 邊際貢獻率 − 固定現金成本 − 折舊 | B88: US$M | E88: =E76*az_cm-az_fix27 -> -120 | F88: =F76*az_cm-az_fix28-F85 -> -112.29167 | G88: =G76*az_cm-az_fix29-G85 -> -14.583333 | K88: 2027 為投產前啟動成本
A89: 毛利 | B89: US$M | C89: =a25_gp -> 938.6 | D89: =a26_gp -> 1325.7873 | E89: =E87+E88 -> 1591.8955 | F89: =F87+F88 -> 1930.5067 | G89: =G87+G88 -> 2270.2659
A90: 毛利率 | B90: % | C90: =C89/C77 -> 0.13992248 | D90: =D89/D77 -> 0.17261815 | E90: =E89/E77 -> 0.18069588 | F90: =F89/F77 -> 0.19422352 | G90: =G89/G77 -> 0.2049996
A91: 亞利桑那對毛利率的影響（亞利桑那毛利 ÷ 營收） | B91: pt | E91: =E88/E77 -> -0.013621187 | F91: =F88/F77 -> -0.011297388 | G91: =G88/G77 -> -0.0013168402 | K91: 公司：啟動成本使營業利益率降約 1–2%（2027 起、2028 改善）
A92: 營業費用（銷管＋研發） | B92: US$M | C92: =a25_opx -> 471.2 | D92: =a26_opx -> 537.5 | E92: =(D92+opx_gain)*(1+phi*E78) -> 599.56116 | F92: =E92*(1+phi*F78) -> 638.00636 | G92: =F92*(1+phi*G78) -> 674.42921 | K92: FY2027 基期加回 2Q26 不動產處分利益
A93: 營業利益 | B93: US$M | C93: =C89-C92 -> 467.4 | D93: =D89-D92 -> 788.28731 | E93: =E89-E92 -> 992.33431 | F93: =F89-F92 -> 1292.5004 | G93: =G89-G92 -> 1595.8367
A94: 營業利益率 | B94: % | C94: =C93/C77 -> 0.069677996 | D94: =D93/D77 -> 0.10263539 | E94: =E93/E77 -> 0.11263976 | F94: =F93/F77 -> 0.13003527 | G94: =G93/G77 -> 0.14410025
A95: 營業外淨額 | B95: US$M | C95: =a25_nonop -> -22.7 | D95: =a26_nonop -> -0.7 | E95: =nonop27 -> -20 | F95: =nonop28 -> -40 | G95: =nonop29 -> -60
A96: 稅前利益 | B96: US$M | C96: =C93+C95 -> 444.7 | D96: =D93+D95 -> 787.58731 | E96: =E93+E95 -> 972.33431 | F96: =F93+F95 -> 1252.5004 | G96: =G93+G95 -> 1535.8367
A97: 所得稅 | B97: US$M | C97: =a25_tax -> 68.5 | D97: =a26_tax -> 138.23746 | E97: =E96*tax -> 194.46686 | F97: =F96*tax -> 250.50007 | G97: =G96*tax -> 307.16734
A98: 非控制權益 | B98: US$M | C98: =a25_nci -> 2.3 | D98: =a26_nci -> 3.7 | E98: =nci -> 3 | F98: =nci -> 3 | G98: =nci -> 3
A99: 歸屬母公司淨利 | B99: US$M | C99: =C96-C97-C98 -> 373.9 | D99: =D96-D97-D98 -> 645.64985 | E99: =E96-E97-E98 -> 774.86745 | F99: =F96-F97-F98 -> 999.00028 | G99: =G96-G97-G98 -> 1225.6694 | H99: =H77*H103 -> 1343.4783 | I99: =I77*I103 -> 1448.3489 | J99: =J77*J103 -> 1535.2499
A100: 稀釋股數 | B100: 百萬股 | C100: =a25_sh -> 248.5 | D100: =a26_sh -> 249.915 | E100: =D100*(1+sh_g) -> 249.915 | F100: =E100*(1+sh_g) -> 249.915 | G100: =F100*(1+sh_g) -> 249.915 | H100: =G100*(1+sh_g) -> 249.915 | I100: =H100*(1+sh_g) -> 249.915 | J100: =I100*(1+sh_g) -> 249.915
A101: EPS（稀釋） | B101: US$ | C101: =C99/C100 -> 1.5046278 | D101: =D99/D100 -> 2.5834778 | E101: =E99/E100 -> 3.100524 | F101: =F99/F100 -> 3.9973602 | G101: =G99/G100 -> 4.904345 | H101: =H99/H100 -> 5.3757411 | I101: =I99/I100 -> 5.7953662 | J101: =J99/J100 -> 6.1430881
A102: EPS 年增 | B102: % | D102: =D101/C101-1 -> 0.71702121 | E102: =E101/D101-1 -> 0.20013572 | F102: =F101/E101-1 -> 0.28925313 | G102: =G101/F101-1 -> 0.22689592 | H102: =H101/G101-1 -> 0.096118052 | I102: =I101/H101-1 -> 0.078059026 | J102: =J101/I101-1 -> 0.06
A103: 淨利率（歸屬母公司淨利 ÷ 營收） | B103: % | C103: =C99/C77 -> 0.055739416 | D103: =D99/D77 -> 0.084063923 | E103: =E99/E77 -> 0.087955121 | F103: =F99/F77 -> 0.10050695 | G103: =G99/G77 -> 0.11067502 | H103: =$G103+(fade_mA-$G103)*1/3 -> 0.11067502 | I103: =$G103+(fade_mA-$G103)*2/3 -> 0.11067502 | J103: =$G103+(fade_mA-$G103)*3/3 -> 0.11067502
A106: 情境 B：CY2028 顆數 ×0.8、CY2029 ×0.85；通訊 FY2027 0%、之後 +3%；亞利桑那 100／400
A107: 項目 | B107: 單位 | C107: FY2025A | D107: FY2026（錨點） | E107: FY2027 | F107: FY2028 | G107: FY2029 | H107: FY2030（收斂） | I107: FY2031（收斂） | J107: FY2032（收斂） | K107: 說明
A108: A. AI 加速器 → Amkor AI 先進封裝（D 欄＝FY2026 校準年）
A109: AI 加速器顆數（含情境係數） | B109: 百萬顆 | D109: =units_26 -> 15.2 | E109: =units_27*1 -> 23.7 | F109: =units_28*um28_B*1 -> 21.2 | G109: =units_29*um29_B*1 -> 25.6275
A110: 封裝面積指數（2026＝1） | B110: x | D110: =ar_26 -> 1 | E110: =ar_27 -> 1.278156 | F110: =ar_28 -> 1.428615 | G110: =ar_29 -> 1.431796
A111: 後段委外比例 | B111: % | D111: =out_26 -> 0.5 | E111: =out_27 -> 0.55 | F111: =out_28 -> 0.6 | G111: =out_29 -> 0.6 | K111: FY2026 固定基準值（Sens 只動 FY2027 起）
A112: Amkor 份額（占委外後段） | B112: % | D112: =sh_26 -> 0.35 | E112: =sh_27 -> 0.35 | F112: =sh_28 -> 0.37 | G112: =sh_29 -> 0.38
...

Sheet Val
A1: Val — P/E 估值（美元）。結論用「現價 ÷ FY2027、FY2028 EPS（模型）」；目標價＝DCF 與 Comparable 加權（第 0 節）；十年 P/E 規則值（第 3 節，年底落後 P/E）只作參考
A2: 循環位置：Amkor 不是設備股，不套設備市場見頂年；以本模型營收最高的會計年度為見頂年（比照廣達、NVIDIA、Arista；FY(t)＝CY(t)）。營收到 FY2029 仍在增加時，見頂年未知，判為中段
A4: 0. 目標價
A5: 0.1 DCF（股東權益現金流，FY2027–FY2032 明確期＋FY2032 後永續）
A6: 項目 | B6: A（順利） | C6: B（平平） | D6: C（不如預期） | E6: 說明
A7: 情境 EPS（FY2027–FY2032） | E7: PL 頁各情境；FY2030 起為收斂法
A8: FY2027 | B8: =PL!E16 -> 3.100524 | C8: =PL!E31 -> 2.9942974 | D8: =PL!E46 -> 2.7818442
A9: FY2028 | B9: =PL!F16 -> 3.9973602 | C9: =PL!F31 -> 3.2407222 | D9: =PL!F46 -> 2.3173418
A10: FY2029 | B10: =PL!G16 -> 4.904345 | C10: =PL!G31 -> 4.1205408 | D10: =PL!G46 -> 2.7158996
A11: FY2030 | B11: =PL!H16 -> 5.3757411 | C11: =PL!H31 -> 4.2143468 | D11: =PL!H46 -> 2.7194727
A12: FY2031 | B12: =PL!I16 -> 5.7953662 | C12: =PL!I31 -> 4.1873497 | D12: =PL!I46 -> 2.6603771
A13: FY2032 | B13: =PL!J16 -> 6.1430881 | C13: =PL!J31 -> 4.0365632 | D13: =PL!J46 -> 2.5404525
A14: 股東現金流＝EPS ×（1 − tp_g ÷ tp_roe）
A15: 再投資率（tp_g ÷ tp_roe，上限 0.8） | B15: =MIN(tp_g/tp_roe,0.8) -> 0.44826298 | E15: ROE 為近三年平均（In 頁 tp_roe）
A16: FY2027 | B16: =B8*(1-$B$15) -> 1.7106739 | C16: =C8*(1-$B$15) -> 1.6520647 | D16: =D8*(1-$B$15) -> 1.5348464
A17: FY2028 | B17: =B9*(1-$B$15) -> 2.2054916 | C17: =C9*(1-$B$15) -> 1.7880264 | D17: =D9*(1-$B$15) -> 1.2785633
A18: FY2029 | B18: =B10*(1-$B$15) -> 2.7059087 | C18: =C10*(1-$B$15) -> 2.2734549 | D18: =D10*(1-$B$15) -> 1.4984623
A19: FY2030 | B19: =B11*(1-$B$15) -> 2.9659953 | C19: =C11*(1-$B$15) -> 2.3252111 | D19: =D11*(1-$B$15) -> 1.5004338
A20: FY2031 | B20: =B12*(1-$B$15) -> 3.1975181 | C20: =C12*(1-$B$15) -> 2.3103158 | D20: =D12*(1-$B$15) -> 1.4678285
A21: FY2032 | B21: =B13*(1-$B$15) -> 3.3893691 | C21: =C13*(1-$B$15) -> 2.2271213 | D21: =D13*(1-$B$15) -> 1.4016617
A22: DCF 情境每股價值（折現率 tp_r） | B22: =SUMPRODUCT(B16:B21,1/(1+tp_r)^{1;2;3;4;5;6})+B21*(1+tp_g)/(tp_r-tp_g)/(1+tp_r)^6 -> 44.497616 | C22: =SUMPRODUCT(C16:C21,1/(1+tp_r)^{1;2;3;4;5;6})+C21*(1+tp_g)/(tp_r-tp_g)/(1+tp_r)^6 -> 30.758125 | D22: =SUMPRODUCT(D16:D21,1/(1+tp_r)^{1;2;3;4;5;6})+D21*(1+tp_g)/(tp_r-tp_g)/(1+tp_r)^6 -> 20.019378 | E22: Σ 明確期現金流 ÷ (1＋r)^t ＋ 永續價值 ÷ (1＋r)^6；永續價值＝FY2032 現金流 ×(1＋g)÷(r−g)；基準日 2026 年底
A23: DCF 情境價值推到 12 個月後（×(1＋tp_r)） | B23: =B22*(1+tp_r) -> 48.947377 | C23: =C22*(1+tp_r) -> 33.833938 | D23: =D22*(1+tp_r) -> 22.021316
A24: DCF 目標價（情境加權） | B24: =tp_wA*B23+tp_wB*C23+tp_wC*D23 -> 36.005445 | E24: Σ 權重 × 情境價值 ×(1＋r)；權重見 In 頁
A26: 0.2 Comparable（市場主流同業前瞻 P/E）
A27: 同業與前瞻 P/E | B27: 代號 | C27: 前瞻 12 月 P/E | D27: 日期 | E27: 來源 | F27: 標記
A28: 日月光投控（ASE Technology） | B28: ASX／3711.TW | C28: 27.37 | D28: 2026-10-23 | E28: stockanalysis.com forward PE（分析師共識；價格日期如左） | F28: Interested-party
A29: 力成（Powertech） | B29: 6239.TW | C29: 20.6 | D29: 2026-10-02 | E29: stockanalysis.com forward PE（分析師共識；價格日期如左） | F29: Interested-party
A30: 京元電子（KYEC） | B30: 2449.TW | C30: 26.13 | D30: 2026-10-06 | E30: stockanalysis.com forward PE（分析師共識；價格日期如左） | F30: Interested-party
A31: 矽格（Sigurd） | B31: 6257.TW | C31: 23.3 | D31: 2026-10-02 | E31: stockanalysis.com forward PE（分析師共識；價格日期如左） | F31: Interested-party
A32: 南茂（ChipMOS） | B32: IMOS／8150.TW | C32: 22.08 | D32: 2026-10-08 | E32: stockanalysis.com forward PE（分析師共識；價格日期如左） | F32: Interested-party
A33: 同業前瞻 P/E 中位數 | B33: =MEDIAN(C28:C32) -> 23.3 | E33: 台美封測同業：日月光、力成、京元電、矽格、南茂（不放 A 股：長電、通富有結構性溢價）
A34: 12 個月後的前瞻 EPS（情境加權） | B34: =tp_wA*(2/12*B8+10/12*B9)+tp_wB*(2/12*C8+10/12*C9)+tp_wC*(2/12*D8+10/12*D9) -> 3.2331437 | E34: 約 2027-10 時的未來 12 月 EPS ≈ 2／12 × FY2027＋10／12 × FY2028（會計年度＝日曆年）
A35: Comparable 目標價 | B35: =B33*B34 -> 75.332249 | E35: 同業中位數 × 前瞻 EPS
A37: 0.3 結論
A38: 項目 | B38: 數值 | E38: 說明
A39: 目標價（DCF 與 Comparable 加權） | B39: =tp_w_dcf*B24+(1-tp_w_dcf)*tp_comp_adj -> 66.3976 | E39: tp_w_dcf × DCF＋（1 − tp_w_dcf）× Comparable；tp_w_dcf 見 In 頁
A40: Comparable 目標價（市場主流同業法） | B40: =B35 -> 75.332249
A41: 市場共識目標價 | B41: =cons_tp -> 76.4 | E41: stockanalysis：11 位分析師平均 76.40（中位數 73.50），2026-10-23 擷取；stocksguide 13 位 71.40
A42: 上檔空間：加權目標價 | B42: =B39/px-1 -> 0.68950636 | E42: 現價＝In 頁 px（2026-10-23 收盤）
A43: 上檔空間：Comparable 目標價 | B43: =B40/px-1 -> 0.91685111
A44: 與市場共識目標價的差距：EPS 因素 | B44: =B34/cons_feps-1 -> 0.1534014 | E44: 本模型前瞻 EPS ÷ 共識前瞻 EPS − 1；共識前瞻 EPS＝現價 ÷ 前瞻 P/E（In 頁 cons_feps）
A45: 與市場共識目標價的差距：倍數因素 | B45: =(cons_tp/cons_feps)/B33-1 -> 0.16974959 | E45: ="共識目標價隱含 "&TEXT(cons_tp/cons_feps,"0.0")&"x，同業中位數 "&TEXT(B33,"0.0")&"x" -> 共識目標價隱含 27.3x，同業中位數 23.3x
A46: 價格帶（DCF 不如預期～順利） | B46: =TEXT(D23,"0.00")&"～"&TEXT(B23,"0.00") -> 22.02～48.95 | E46: C 情境價值～A 情境價值（推到 12 個月後）
A47: 歷史倍數檢查：現價隱含 P/E 的十年分位（A／B／C） | B47: =PERCENTRANK($B$86:$B$95,px/B9) -> 0.281 | C47: =PERCENTRANK($B$86:$B$95,px/C9) -> 0.455 | D47: =PERCENTRANK($B$86:$B$95,px/D9) -> 0.636 | E47: 現價 ÷ 各情境 FY2028 EPS 在 2016–2025 年底 P/E（第 5 節兩來源平均）的分位；只作檢查，不進目標價
A48: 目標價方法 | B48: DCF：股東現金流＝GAAP 稀釋 EPS ×（1 − g／ROE），r＝10%、g＝4%、ROE 為近三年平均約 9%（再投資率約 45%），FY2027–32 明確期＋永續；Amkor 資本密集，但 FY2030 起只有收斂法、亞利桑那第二期支出未建，未改用淨利＋折舊－資本支出，現金流偏高估。Comparable：台美封測同業（日月光、力成、京元電、矽格、南茂）前瞻 P/E 中位數；不放 A 股（長電、通富約 35–50x，結構性溢價）；京元電以 AI 測試為主、倍數較高，部分價格為 10 月上旬。情境對應：A＝順利（顆數基準）、B＝平平（顆數 ×0.8／0.85）、C＝不如預期（顆數 ×0.6、通訊下滑）
A49: 上檔空間級距 | B49: =IF(B42>0.5,"大於 50%",IF(B42>0.25,"25%–50%",IF(B42>=0,"0%–25%",IF(B42>=-0.25,"0%～−25%",IF(B42>=-0.5,"−25%～−50%","小於 −50%"))))) -> 大於 50% | E49: 以「上檔空間：加權目標價」分六級（Andy 2026-10-25 14:00）
A50: 投資建議 | B50: =IF(B42>0.5,"強力買進",IF(B42>0.25,"買進",IF(B42>=-0.25,"中立",IF(B42>=-0.5,"放空","強力放空")))) -> 強力買進 | E50: 依上檔空間固定規則（Andy 2026-10-25 14:17）：大於 +50% 強力買進、+25%～+50% 買進、−25%～+25% 中立、−50%～−25% 放空、小於 −50% 強力放空
A51: 1. 價格與市場隱含倍數
A52: 項目 | B52: A | C52: B | D52: C | E52: 說明
A53: 現價（2026-10-23 收盤） | B53: =px -> 39.3
A54: 現價 ÷ FY2026 EPS（錨點） | B54: =px/PL!D16 -> 15.212053 | C54: =px/PL!D31 -> 15.212053 | D54: =px/PL!D46 -> 15.212053 | E54: FY2026 三情境相同（錨點）
A55: 現價 ÷ FY2027 EPS（模型） | B55: =px/PL!E16 -> 12.675277 | C55: =px/PL!E31 -> 13.124949 | D55: =px/PL!E46 -> 14.127319 | E55: FY2027 三情境只差通訊與亞利桑那啟動成本
A56: 現價 ÷ FY2028 EPS（模型） | B56: =px/PL!F16 -> 9.8314882 | C56: =px/PL!F31 -> 12.126927 | D56: =px/PL!F46 -> 16.959087
A57: 現價 ÷ FY2029 EPS（模型） | B57: =px/PL!G16 -> 8.0133025 | C57: =px/PL!G31 -> 9.5375831 | D57: =px/PL!G46 -> 14.470344
A58: 未來 12 月 EPS（模型 B）≈ 0.2 × FY2026＋0.8 × FY2027 | B58: =0.2*PL!D31+0.8*PL!E31 -> 2.9121335
A59: 現價 ÷ 未來 12 月 EPS（模型 B） | B59: =px/B58 -> 13.495261
A60: 近 12 月 P/E（stockanalysis，10-23） | B60: =pe_ttm -> 17.64
A61: 前瞻 P/E（stockanalysis，10-23） | B61: =fpe -> 14.02
A63: 2. 循環位置（本模型營收最高年；FY(t)＝CY(t)）
A64: 情境 | B64: 營收最高年（FY2026–FY2029） | C64: FY2027 判定 | D64: 規則倍數（P/E） | E64: 見頂年是否未知 | F64: 說明
A65: A | B65: =INDEX({2026,2027,2028,2029},MATCH(MAX(PL!D77:G77),PL!D77:G77,0)) -> 2029 | C65: =IF(B65=2029,"中段",IF(2027<B65,"中段",IF(2027=B65,"見頂","谷底"))) -> 中段 | D65: =IF(C65="見頂",pe_peak,IF(C65="谷底",pe_trough,pe_mid)) -> 13.34 | E65: =IF(B65=2029,"是：營收到觀測期末仍在增加","否") -> 是：營收到觀測期末仍在增加 | F65: tools/cycle_position.py excel_rule；營收最高年取代設備市場見頂年
A66: B | B66: =INDEX({2026,2027,2028,2029},MATCH(MAX(PL!D123:G123),PL!D123:G123,0)) -> 2029 | C66: =IF(B66=2029,"中段",IF(2027<B66,"中段",IF(2027=B66,"見頂","谷底"))) -> 中段 | D66: =IF(C66="見頂",pe_peak,IF(C66="谷底",pe_trough,pe_mid)) -> 13.34 | E66: =IF(B66=2029,"是：營收到觀測期末仍在增加","否") -> 是：營收到觀測期末仍在增加 | F66: 同上
A67: C | B67: =INDEX({2026,2027,2028,2029},MATCH(MAX(PL!D169:G169),PL!D169:G169,0)) -> 2029 | C67: =IF(B67=2029,"中段",IF(2027<B67,"中段",IF(2027=B67,"見頂","谷底"))) -> 中段 | D67: =IF(C67="見頂",pe_peak,IF(C67="谷底",pe_trough,pe_mid)) -> 13.34 | E67: =IF(B67=2029,"是：營收到觀測期末仍在增加","否") -> 是：營收到觀測期末仍在增加 | F67: 同上
A69: 3. 規則值隱含股價（美元；約 FY2027 年底，未折現）＝ FY2027 EPS × 規則倍數
A70: 情境 | B70: FY2027 EPS | C70: （同左） | D70: 規則倍數 | E70: 隱含股價 | F70: 相對現價 | G70: 現價 ÷ FY2027 EPS
A71: A | B71: =PL!E16 -> 3.100524 | C71: =B71 -> 3.100524 | D71: =D65 -> 13.34 | E71: =C71*D71 -> 41.36099 | F71: =E71/px-1 -> 0.05244249 | G71: =px/C71 -> 12.675277
A72: B | B72: =PL!E31 -> 2.9942974 | C72: =B72 -> 2.9942974 | D72: =D66 -> 13.34 | E72: =C72*D72 -> 39.943927 | F72: =E72/px-1 -> 0.016384911 | G72: =px/C72 -> 13.124949
A73: C | B73: =PL!E46 -> 2.7818442 | C73: =B73 -> 2.7818442 | D73: =D67 -> 13.34 | E73: =C73*D73 -> 37.109801 | F73: =E73/px-1 -> -0.055730246 | G73: =px/C73 -> 14.127319
A75: 4. What must be true：FY2027 年底價 ＝ 現價 ×（1＋報酬）所需的倍數（FY2028 EPS；約 2027 年底的價格看下一年 EPS）
A76: FY2027 年底價 ÷ 現價 | B76: 所需倍數（÷ FY2028 EPS，A） | C76: 所需倍數（÷ FY2028 EPS，B） | D76: 所需倍數（÷ FY2028 EPS，C） | E76: 對照：十年中位數
A77: 1 | B77: =px*A77/PL!F16 -> 9.8314882 | C77: =px*A77/PL!F31 -> 12.126927 | D77: =px*A77/PL!F46 -> 16.959087 | E77: =pe_mid -> 13.34
A78: 1.1 | B78: =px*A78/PL!F16 -> 10.814637 | C78: =px*A78/PL!F31 -> 13.339619 | D78: =px*A78/PL!F46 -> 18.654995 | E78: =pe_mid -> 13.34
A79: 1.21 | B79: =px*A79/PL!F16 -> 11.896101 | C79: =px*A79/PL!F31 -> 14.673581 | D79: =px*A79/PL!F46 -> 20.520495 | E79: =pe_mid -> 13.34
A80: 1.5 | B80: =px*A80/PL!F16 -> 14.747232 | C80: =px*A80/PL!F31 -> 18.19039 | D80: =px*A80/PL!F46 -> 25.43863 | E80: =pe_mid -> 13.34
A81: 2 | B81: =px*A81/PL!F16 -> 19.662976 | C81: =px*A81/PL!F31 -> 24.253853 | D81: =px*A81/PL!F46 -> 33.918173 | E81: =pe_mid -> 13.34
A82: 讀法：1.00＝價格不變、1.21＝一年約 21%。所需倍數低於歷史中位數時，現價相對便宜；倍數是否合理，另看前瞻 P/E 歷史（Bloomberg）。本版未做先驗，無 Andy 合理 P/E 對照。
A84: 5. 十年 P/E（2016–2025 年底；兩來源平均，分位排名用；無負值或 >200 需剔除）
A85: 年底 | B85: 兩來源平均 P/E | C85: companiesmarketcap | D85: 自算
A86: 2016 | B86: =AVERAGE(C86:D86) -> 14.844928 | C86: =B105 -> 14.4 | D86: =C105 -> 15.289855
A87: 2017 | B87: =AVERAGE(C87:D87) -> 8.9150917 | C87: =B106 -> 8.61 | D87: =C106 -> 9.2201835
A88: 2018 | B88: =AVERAGE(C88:D88) -> 11.838679 | C88: =B107 -> 11.3 | D88: =C107 -> 12.377358
A89: 2019 | B89: =AVERAGE(C89:D89) -> 25.15 | C89: =B108 -> 24.3 | D89: =C108 -> 26
A90: 2020 | B90: =AVERAGE(C90:D90) -> 10.435714 | C90: =B109 -> 10.1 | D90: =C109 -> 10.771429
A91: 2021 | B91: =AVERAGE(C91:D91) -> 9.155916 | C91: =B110 -> 8.85 | D91: =C110 -> 9.4618321
A92: 2022 | B92: =AVERAGE(C92:D92) -> 7.5053055 | C92: =B111 -> 7.3 | D92: =C111 -> 7.7106109
A93: 2023 | B93: =AVERAGE(C93:D93) -> 22.343836 | C93: =B112 -> 21.9 | D93: =C112 -> 22.787671
A94: 2024 | B94: =AVERAGE(C94:D94) -> 17.782517 | C94: =B113 -> 17.6 | D94: =C113 -> 17.965035
A95: 2025 | B95: =AVERAGE(C95:D95) -> 26.21 | C95: =B114 -> 26.1 | D95: =C114 -> 26.32
A96: 年數 | B96: =COUNT($B$86:$B$95) -> 10
A100: 6. 十年倍數與規則值（2016–2025 年底；見頂年 25 分位、中段中位數、谷底 75 分位）
A101: 規則（Andy 2026-10-13）：合理倍數＝2016–2025 年底 P/E 依循環位置取分位，兩個來源分別取分位再平均。Amkor 的落後 P/E 與盈餘反向：盈餘低谷年（2019、2023–2025）P/E 22–26x，高峰年（2021–2022）7–9x；套用在成長年的 EPS 時，中位數偏向高估。2017 EPS 含美國稅改一次性利益 0.17。
A103: P/E：十年歷史倍數
A104: 年底 | B104: companiesmarketcap（年底 P/E） | C104: 自算（digrin 12 月未調整股價 ÷ 公司稀釋 EPS） | D104: 標記／說明
A105: 2016 | B105: 14.4 | C105: =10.55/0.69 -> 15.289855 | D105: companiesmarketcap（年底 P/E）：Interested-party（資料商；2016–2025 共 10 年）；自算（digrin 12 月未調整股價 ÷ 公司稀釋 EPS）：Derived（價格為月資料的 12 月值，非逐日年底收盤；EPS 取自公司各年第四季新聞稿）
A106: 2017 | B106: 8.61 | C106: =10.05/1.09 -> 9.2201835
A107: 2018 | B107: 11.3 | C107: =6.56/0.53 -> 12.377358
A108: 2019 | B108: 24.3 | C108: =13/0.5 -> 26
A109: 2020 | B109: 10.1 | C109: =15.08/1.4 -> 10.771429
A110: 2021 | B110: 8.85 | C110: =24.79/2.62 -> 9.4618321
A111: 2022 | B111: 7.3 | C111: =23.98/3.11 -> 7.7106109
...

Sheet Recon
A1: Recon — 本模型 vs 公司指引、公司長期目標、共識與市場口徑。只作事後對照，不為對上數字而調參數。共識 FY2027 只有單一來源且年度標示不明
A3: 項目 | B3: 對照值 | C3: 模型 A | D3: 差距 A | E3: 模型 B | F3: 差距 B | G3: 模型 C | H3: 差距 C | I3: 對照來源 | J3: 說明
A4: A. FY2026 錨點 vs 公司指引與共識（錨點用 3Q 指引，非獨立檢驗）
A5: 3Q26 營收（各終端市場季增說法加總）vs 指引中點 | B5: =g3_rev -> 2000 | C5: =Q!E4 -> 2020.2312 | D5: =C5/B5-1 -> 0.0101156 | E5: =Q!E4 -> 2020.2312 | F5: =E5/B5-1 -> 0.0101156 | G5: =Q!E4 -> 2020.2312 | H5: =G5/B5-1 -> 0.0101156 | I5: 2Q26 新聞稿：1,950–2,050 | J5: 共識 3Q26 2,040（MarketBeat）
A6: 3Q26 EPS vs 指引中點 | B6: =g3_eps -> 0.77 | C6: =Q!E19 -> 0.77630057 | D6: =C6/B6-1 -> 0.0081825579 | E6: =Q!E19 -> 0.77630057 | F6: =E6/B6-1 -> 0.0081825579 | G6: =Q!E19 -> 0.77630057 | H6: =G6/B6-1 -> 0.0081825579 | I6: 2Q26 新聞稿：0.72–0.82
A7: FY2026 營收 vs 共識 | B7: =cons_rev26 -> 7670 | C7: =PL!D77 -> 7680.463 | D7: =C7/B7-1 -> 0.0013641486 | E7: =PL!D123 -> 7680.463 | F7: =E7/B7-1 -> 0.0013641486 | G7: =PL!D169 -> 7680.463 | H7: =G7/B7-1 -> 0.0013641486 | I7: stockanalysis（11 位） | J7: tickflow 7.47B（7 位）
A8: FY2026 EPS vs 共識（non-GAAP） | B8: =cons_eps26 -> 2.57 | C8: =PL!D101 -> 2.5834778 | D8: =C8/B8-1 -> 0.0052442761 | E8: =PL!D147 -> 2.5834778 | F8: =E8/B8-1 -> 0.0052442761 | G8: =PL!D193 -> 2.5834778 | H8: =G8/B8-1 -> 0.0052442761 | I8: stockanalysis（11 位） | J8: 模型為 GAAP
A9: FY2027 EPS vs 共識（MarketBeat，年度標示不明） | B9: =cons_eps27 -> 2.72 | C9: =PL!E101 -> 3.100524 | D9: =C9/B9-1 -> 0.13989852 | E9: =PL!E147 -> 2.9942974 | F9: =E9/B9-1 -> 0.10084462 | G9: =PL!E193 -> 2.7818442 | H9: =G9/B9-1 -> 0.02273683 | I9: MarketBeat（單一來源）
A10: FY2026 運算年增 vs 公司「超過 20%」（2026-02）（百分點） | B10: 0.2 | C10: =Q!G6/Q!B6-1 -> 0.40440101 | D10: =C10-B10 -> 0.20440101 | E10: =Q!G6/Q!B6-1 -> 0.40440101 | F10: =E10-B10 -> 0.20440101 | G10: =Q!G6/Q!B6-1 -> 0.40440101 | H10: =G10-B10 -> 0.20440101 | I10: 4Q25 法說 | J10: 3Q26 指引運算近 +30% 季增，已高於年初說法
A11: B. vs 公司長期目標（投資人日 2026-05-21；2Q26 財報前訂定）
A12: FY2028 營收 vs 目標 9.0B（±0.5B） | B12: =t28_rev -> 9000 | C12: =PL!F77 -> 9939.6136 | D12: =C12/B12-1 -> 0.10440151 | E12: =PL!F123 -> 9308.94 | F12: =E12/B12-1 -> 0.034326663 | G12: =PL!F169 -> 8529.823 | H12: =G12/B12-1 -> -0.052241888 | I12: 投資人日
A13: FY2028 毛利率 vs 目標 17.5%（±1pt）（百分點） | B13: =t28_gm -> 0.175 | C13: =PL!F90 -> 0.19422352 | D13: =C13-B13 -> 0.019223518 | E13: =PL!F136 -> 0.1796727 | F13: =E13-B13 -> 0.0046727014 | G13: =PL!F182 -> 0.1590966 | H13: =G13-B13 -> -0.015903398 | I13: 投資人日
A14: FY2028 EPS vs 目標 2.50（±0.25） | B14: =t28_eps -> 2.5 | C14: =PL!F101 -> 3.9973602 | D14: =C14/B14-1 -> 0.59894409 | E14: =PL!F147 -> 3.2407222 | F14: =E14/B14-1 -> 0.29628888 | G14: =PL!F193 -> 2.3173418 | H14: =G14/B14-1 -> -0.073063285 | I14: 投資人日 | J14: FY2026 錨點已高於 2028 目標
A15: FY2029 營收 vs 2030 目標 11B（目標年晚一年） | B15: =t30_rev -> 11000 | C15: =PL!G77 -> 11074.49 | D15: =C15/B15-1 -> 0.0067717832 | E15: =PL!G123 -> 10413.325 | F15: =E15/B15-1 -> -0.05333408 | G15: =PL!G169 -> 9229.7377 | H15: =G15/B15-1 -> -0.16093294 | I15: 投資人日
A16: FY2029 毛利率 vs 2030 目標 22%（百分點） | B16: =t30_gm -> 0.22 | C16: =PL!G90 -> 0.2049996 | D16: =C16-B16 -> -0.015000401 | E16: =PL!G136 -> 0.19244362 | F16: =E16-B16 -> -0.027556379 | G16: =PL!G182 -> 0.1653085 | H16: =G16-B16 -> -0.054691496 | I16: 投資人日
A17: FY2029 EPS vs 2030 目標 5.0 | B17: =t30_eps -> 5 | C17: =PL!G101 -> 4.904345 | D17: =C17/B17-1 -> -0.019131006 | E17: =PL!G147 -> 4.1205408 | F17: =E17/B17-1 -> -0.17589185 | G17: =PL!G193 -> 2.7158996 | H17: =G17/B17-1 -> -0.45682009 | I17: 投資人日
A18: 運算 FY2025–29 年均成長 vs 投資人日 2025–30 約 24%（百分點） | B18: 0.24 | C18: =(PL!G72/PL!C72)^(1/4)-1 -> 0.29567651 | D18: =C18-B18 -> 0.055676509 | E18: =(PL!G118/PL!C118)^(1/4)-1 -> 0.26000567 | F18: =E18-B18 -> 0.020005675 | G18: =(PL!G164/PL!C164)^(1/4)-1 -> 0.19279228 | H18: =G18-B18 -> -0.04720772 | I18: 投資人日
A19: C. AI 先進封裝的市場口徑
A20: FY2026 Amkor AI 營收 ÷ OSAT 先進封裝市場（GW × 0.5B） | C20: =Units!C13 -> 0.073614236 | E20: =Units!C13 -> 0.073614236 | G20: =Units!C13 -> 0.073614236 | I20: 投資人日 0.5B／GW；部署 GW 讀網通模型與橋接表 | J20: 隱含市占
A21: FY2027 Amkor AI 營收 ÷ OSAT 先進封裝市場 | C21: =Units!D13 -> 0.08020052 | E21: =Units!D13 -> 0.08020052 | G21: =Units!D13 -> 0.08020052 | I21: 同上 | J21: 情境 A
A22: 台積電 CoWoS 2027 需求 ÷ 可用產能（tsmc 成品） | C22: =cow_util27 -> 0.96254755 | E22: =cow_util27 -> 0.96254755 | G22: =cow_util27 -> 0.96254755 | I22: tsmc/dist CoWoS 頁 | J22: 接近 100% → 後段委外需求上升（本模型委外比例 Assumed 上升的依據之一）
A23: FY2026 每顆加速器 Amkor AI 營收（US$） | C23: =PL!D69 -> 56.662471 | E23: =PL!D115 -> 56.662471 | G23: =PL!D161 -> 56.662471 | I23: — | J23: 對照：台積電模型每顆台積電內容 1.1–6.0 千美元（邏輯＋CoWoS）
A24: D. 亞利桑那
A25: FY2027 亞利桑那對毛利率的影響 vs 公司對營業利益率 −1～−2%（取 −1.5%）（百分點） | B25: -0.015 | C25: =PL!E91 -> -0.013621187 | D25: =C25-B25 -> 0.0013788129 | E25: =PL!E137 -> -0.013763759 | F25: =E25-B25 -> 0.0012362413 | G25: =PL!E183 -> -0.014058047 | H25: =G25-B25 -> 0.00094195307 | I25: 1Q26 法說：2027 起 1–2%、2028 改善；2029 損益兩平（投資人日）
A26: FY2028 亞利桑那對毛利率的影響 vs 公司對營業利益率 −1～−2%（取 −1.5%）（百分點） | B26: -0.015 | C26: =PL!F91 -> -0.011297388 | D26: =C26-B26 -> 0.0037026125 | E26: =PL!F137 -> -0.015016926 | F26: =E26-B26 -> -1.6926438e-05 | G26: =PL!F183 -> -0.01961256 | H26: =G26-B26 -> -0.0046125601 | I26: 1Q26 法說：2027 起 1–2%、2028 改善；2029 損益兩平（投資人日）
A27: FY2029 亞利桑那對毛利率的影響 vs 公司對營業利益率 −1～−2%（取 −1.5%）（百分點） | B27: -0.015 | C27: =PL!G91 -> -0.0013168402 | D27: =C27-B27 -> 0.01368316 | E27: =PL!G137 -> -0.0066821436 | F27: =E27-B27 -> 0.0083178564 | G27: =PL!G183 -> -0.016477536 | H27: =G27-B27 -> -0.0014775359 | I27: 1Q26 法說：2027 起 1–2%、2028 改善；2029 損益兩平（投資人日）
A28: E. 客戶集中
A29: FY2027 通訊 ÷ 營收 vs FY2025 Apple 占營收 29.8%（百分點） | B29: =apple -> 0.298 | C29: =PL!E80 -> 0.35564101 | D29: =C29-B29 -> 0.057641013 | E29: =PL!E126 -> 0.34889657 | F29: =E29-B29 -> 0.050896573 | G29: =PL!E172 -> 0.33497508 | H29: =G29-B29 -> 0.036975078 | I29: 10-K | J29: 通訊含 Android 與 Qualcomm；只看方向

Sheet Sens
A1: Sens — 一次動一個輸入（情境 A；FY2026 恆等於錨點，AI 拆分與每顆金額在每個案例內重算）：對 FY2027、FY2028 營收、毛利率與 EPS 的影響。每個案例是一個完整推導區塊（本頁下方）
A3: 案例 | B3: 設定 | C3: FY2027 營收 | D3: FY2027 毛利率 | E3: FY2027 EPS | F3: FY2027 EPS 相對基準 | G3: FY2028 營收 | H3: FY2028 毛利率 | I3: FY2028 EPS | J3: FY2028 EPS 相對基準
A4: 基準（情境 A） | B4: PL 區塊 A | C4: =PL!E77 -> 8809.8048 | D4: =PL!E90 -> 0.18069588 | E4: =PL!E101 -> 3.100524 | F4: =E4/E$4-1 -> 0 | G4: =PL!F77 -> 9939.6136 | H4: =PL!F90 -> 0.19422352 | I4: =PL!F101 -> 3.9973602 | J4: =I4/I$4-1 -> 0
A5: AI 部署 ×0.8 | B5: FY2027 起顆數 ×0.8 | C5: =E57 -> 8475.7956 | D5: =E70 -> 0.17205367 | E5: =E81 -> 2.711721 | F5: =E5/E$4-1 -> -0.12539912 | G5: =F57 -> 9484.2651 | H5: =F70 -> 0.18504834 | I5: =F81 -> 3.4857749 | J5: =I5/I$4-1 -> -0.12798079
A6: AI 部署 ×1.2 | B6: ×1.2 | C6: =E103 -> 9143.8141 | D6: =E116 -> 0.18870672 | E6: =E127 -> 3.489327 | F6: =E6/E$4-1 -> 0.12539912 | G6: =F103 -> 10394.962 | H6: =F116 -> 0.20259486 | I6: =F127 -> 4.509248 | J6: =I6/I$4-1 -> 0.12805645
A7: 委外比例 低 | B7: 2027 45%、2028–29 45% | C7: =E149 -> 8506.1601 | D7: =E162 -> 0.17286738 | E7: =E173 -> 2.7470667 | F7: =E7/E$4-1 -> -0.1139992 | G7: =F149 -> 9370.428 | H7: =F162 -> 0.18237218 | I7: =F173 -> 3.3506942 | J7: =I7/I$4-1 -> -0.16177326
A8: 委外比例 高 | B8: 2027 65%、2028 70%、2029 75% | C8: =E195 -> 9113.4496 | D8: =E208 -> 0.18800273 | E8: =E219 -> 3.4539812 | F8: =E8/E$4-1 -> 0.1139992 | G8: =F195 -> 10319.071 | H8: =F208 -> 0.2012019 | I8: =F219 -> 4.4222303 | J8: =I8/I$4-1 -> 0.10628767
A9: Amkor 份額 低 | B9: 28%（日月光、矽品搶單） | C9: =E241 -> 8475.7956 | D9: =E254 -> 0.17205367 | E9: =E265 -> 2.711721 | F9: =E9/E$4-1 -> -0.12539912 | G9: =F241 -> 9385.8114 | H9: =F254 -> 0.18279357 | I9: =F265 -> 3.3706324 | J9: =I9/I$4-1 -> -0.15678543
A10: Amkor 份額 高 | B10: 2027 40%、2028–29 45% | C10: =E287 -> 9048.3829 | D10: =E300 -> 0.18647826 | E10: =E311 -> 3.3782404 | F10: =E10/E$4-1 -> 0.089570801 | G10: =F287 -> 10431.882 | H10: =F300 -> 0.20347647 | I10: =F311 -> 4.5588539 | J10: =I10/I$4-1 -> 0.14046611
A11: 每顆金額彈性 0.3 | B11: 封裝面積帶動較少 | C11: =E333 -> 8729.812 | D11: =E346 -> 0.17868636 | E11: =E357 -> 3.0074085 | F11: =E11/E$4-1 -> -0.030032179 | G11: =F333 -> 9782.8467 | H11: =F346 -> 0.19108956 | I11: =F357 -> 3.818935 | J11: =I11/I$4-1 -> -0.04463576
A12: 每顆金額彈性 1.0 | B12: 與面積等比例 | C12: =E379 -> 9027.8387 | D12: =E392 -> 0.18599236 | E12: =E403 -> 3.354326 | F12: =E12/E$4-1 -> 0.081857798 | G12: =F379 -> 10384.14 | H12: =F392 -> 0.20261251 | I12: =F403 -> 4.5042036 | J12: =I12/I$4-1 -> 0.12679451
A13: AI 三倍 → 2.5 倍 | B13: FY2026 AI 拆分較大、基期較高 | C13: =E425 -> 8892.5336 | D13: =E438 -> 0.18273611 | E13: =E449 -> 3.1968243 | F13: =E13/E$4-1 -> 0.031059376 | G13: =F425 -> 10083.637 | H13: =F438 -> 0.19699851 | I13: =F449 -> 4.160733 | J13: =I13/I$4-1 -> 0.040870156
A14: 通訊 情境 C 路徑 | B14: FY2027 −6%、之後 0% | C14: =E471 -> 8536.0364 | D14: =E484 -> 0.17366234 | E14: =E495 -> 2.7818442 | F14: =E14/E$4-1 -> -0.10278256 | G14: =F471 -> 9540.52 | H14: =F484 -> 0.1861895 | I14: =F495 -> 3.5477537 | J14: =I14/I$4-1 -> -0.11247586
A15: 車用與工業 +4% | B15: 基準 +10% | C15: =E517 -> 8710.3853 | D15: =E530 -> 0.17819277 | E15: =E541 -> 2.9847948 | F15: =E15/E$4-1 -> -0.037325671 | G15: =F517 -> 9726.8558 | H15: =F530 -> 0.18992694 | I15: =F541 -> 3.7546308 | J15: =I15/I$4-1 -> -0.060722433
A16: 車用與工業 +14% | C16: =E563 -> 8876.0845 | D16: =E576 -> 0.18233348 | E16: =E587 -> 3.1776767 | F16: =E16/E$4-1 -> 0.024883781 | G16: =F563 -> 10088.08 | H16: =F576 -> 0.19712053 | I16: =F587 -> 4.1670113 | J16: =I16/I$4-1 -> 0.042440782
A17: 現金流通率 30% | B17: 基準 40% | C17: =E609 -> 8809.8048 | D17: =E622 -> 0.16787674 | E17: =E633 -> 2.7390117 | F17: =E17/E$4-1 -> -0.11659716 | G17: =F609 -> 9939.6136 | H17: =F622 -> 0.17300387 | I17: =F633 -> 3.3222025 | J17: =I17/I$4-1 -> -0.1689009
A18: 現金流通率 50% | C18: =E655 -> 8809.8048 | D18: =E668 -> 0.19351503 | E18: =E679 -> 3.4620363 | F18: =E18/E$4-1 -> 0.11659716 | G18: =F655 -> 9939.6136 | H18: =F668 -> 0.21544316 | I18: =F679 -> 4.672518 | J18: =I18/I$4-1 -> 0.1689009
A19: 本業資本支出率 18% | B19: 折舊上升較快 | C19: =E701 -> 8809.8048 | D19: =E714 -> 0.18069588 | E19: =E725 -> 3.100524 | F19: =E19/E$4-1 -> 0 | G19: =F701 -> 9939.6136 | H19: =F714 -> 0.18915876 | I19: =F725 -> 3.8362119 | J19: =I19/I$4-1 -> -0.040313696
A20: 本業折舊年限 5 年 | B20: 基準 7 年 | C20: =E747 -> 8809.8048 | D20: =E760 -> 0.17771609 | E20: =E771 -> 3.0164908 | F20: =E20/E$4-1 -> -0.027102884 | G20: =F747 -> 9939.6136 | H20: =F760 -> 0.18965499 | I20: =F771 -> 3.8520008 | J20: =I20/I$4-1 -> -0.036363856
A21: 亞利桑那固定成本 高 | B21: 2027 170、2028–29 150 | C21: =E793 -> 8809.8048 | D21: =E806 -> 0.17502039 | E21: =E817 -> 2.9404696 | F21: =E21/E$4-1 -> -0.051621732 | G21: =F793 -> 9939.6136 | H21: =F806 -> 0.18919314 | I21: =F817 -> 3.8373058 | J21: =I21/I$4-1 -> -0.040040029
A22: 亞利桑那補助 20% | B22: 基準 35% | C22: =E839 -> 8809.8048 | D22: =E852 -> 0.18069588 | E22: =E863 -> 3.100524 | F22: =E22/E$4-1 -> 0 | G22: =F839 -> 9939.6136 | H22: =F852 -> 0.19202273 | I22: =F863 -> 3.9273364 | J22: =I22/I$4-1 -> -0.017517513
A23: 營業費用彈性 1.0 | B23: 基準 0.5 | C23: =E885 -> 8809.8048 | D23: =E898 -> 0.18069588 | E23: =E909 -> 2.9690836 | F23: =E23/E$4-1 -> -0.042392962 | G23: =F885 -> 9939.6136 | H23: =F898 -> 0.19422352 | I23: =F909 -> 3.7259969 | J23: =I23/I$4-1 -> -0.067885646
A24: 稅率 25% | B24: 基準 20% | C24: =E931 -> 8809.8048 | D24: =E944 -> 0.18069588 | E24: =E955 -> 2.905991 | F24: =E24/E$4-1 -> -0.062741977 | G24: =F931 -> 9939.6136 | H24: =F944 -> 0.19422352 | I24: =F955 -> 3.746775 | J24: =I24/I$4-1 -> -0.062687688
A25: 營業外 −40 | B25: 每年再 −40 | C25: =E977 -> 8809.8048 | D25: =E990 -> 0.18069588 | E25: =E1001 -> 2.9724804 | F25: =E25/E$4-1 -> -0.041297386 | G25: =F977 -> 9939.6136 | H25: =F990 -> 0.19422352 | I25: =F1001 -> 3.8693167 | J25: =I25/I$4-1 -> -0.032032023
A26: 情境 B | B26: CY2028 顆數 ×0.8、CY2029 ×0.85；通訊較弱 | C26: =PL!E123 -> 8718.5487 | D26: =PL!E136 -> 0.17840045 | E26: =PL!E147 -> 2.9942974 | F26: =E26/E$4-1 -> -0.034260854 | G26: =PL!F123 -> 9308.94 | H26: =PL!F136 -> 0.1796727 | I26: =PL!F147 -> 3.2407222 | J26: =I26/I$4-1 -> -0.18928443
A27: 情境 C | B27: CY2028–29 顆數 ×0.6；通訊 −6% | C27: =PL!E169 -> 8536.0364 | D27: =PL!E182 -> 0.17366234 | E27: =PL!E193 -> 2.7818442 | F27: =E27/E$4-1 -> -0.10278256 | G27: =PL!F169 -> 8529.823 | H27: =PL!F182 -> 0.1590966 | I27: =PL!F193 -> 2.3173418 | J27: =I27/I$4-1 -> -0.42028197
A29: 讀法：顆數情境 B、C 的差異從 FY2028 起；FY2027 只差通訊與亞利桑那啟動成本。委外比例、份額、彈性只影響 AI 先進封裝（FY2026 約占營收一成），所以單項影響小於流通率與通訊；毛利率對流通率最敏感。
A31: 目標價參數（只改 DCF 參數；PL 收斂法的 fade_g 不隨 tp_g 變動）
A32: 案例 | B32: 設定 | C32: DCF 目標價 | D32: Comparable 目標價（相對倍數調整後） | E32: 加權目標價 | F32: 相對基準
A33: 基準 | B33: r 10%、g 4%、DCF 權重 0.5 | C33: =(tp_wA*(Val!B8*(1-MIN(tp_g/tp_roe,0.8))/(1+tp_r)^1+Val!B9*(1-MIN(tp_g/tp_roe,0.8))/(1+tp_r)^2+Val!B10*(1-MIN(tp_g/tp_roe,0.8))/(1+tp_r)^3+Val!B11*(1-MIN(tp_g/tp_roe,0.8))/(1+tp_r)^4+Val!B12*(1-MIN(tp_g/tp_roe,0.8))/(1+tp_r)^5+Val!B13*(1-MIN(tp_g/tp_roe,0.8))/(1+tp_r)^6+Val!B13*(1-MIN(tp_g/tp_roe,0.8))*(1+tp_g)/(tp_r-tp_g)/(1+tp_r)^6)+tp_wB*(Val!C8*(1-MIN(tp_g/tp_roe,0.8))/(1+tp_r)^1+Val!C9*(1-MIN(tp_g/tp_roe,0.8))/(1+tp_r)^2+Val!C10*(1-MIN(tp_g/tp_roe,0.8))/(1+tp_r)^3+Val!C11*(1-MIN(tp_g/tp_roe,0.8))/(1+tp_r)^4+Val!C12*(1-MIN(tp_g/tp_roe,0.8))/(1+tp_r)^5+Val!C13*(1-MIN(tp_g/tp_roe,0.8))/(1+tp_r)^6+Val!C13*(1-MIN(tp_g/tp_roe,0.8))*(1+tp_g)/(tp_r-tp_g)/(1+tp_r)^6)+tp_wC*(Val!D8*(1-MIN(tp_g/tp_roe,0.8))/(1+tp_r)^1+Val!D9*(1-MIN(tp_g/tp_roe,0.8))/(1+tp_r)^2+Val!D10*(1-MIN(tp_g/tp_roe,0.8))/(1+tp_r)^3+Val!D11*(1-MIN(tp_g/tp_roe,0.8))/(1+tp_r)^4+Val!D12*(1-MIN(tp_g/tp_roe,0.8))/(1+tp_r)^5+Val!D13*(1-MIN(tp_g/tp_roe,0.8))/(1+tp_r)^6+Val!D13*(1-MIN(tp_g/tp_roe,0.8))*(1+tp_g)/(tp_r-tp_g)/(1+tp_r)^6))*(1+tp_r) -> 36.005445 | D33: =tp_comp_adj -> 96.789755 | E33: =tp_w_dcf*C33+(1-tp_w_dcf)*D33 -> 66.3976 | F33: =E33/E$33-1 -> 0
A34: 折現率 +1pt | B34: r 11% | C34: =(tp_wA*(Val!B8*(1-MIN(tp_g/tp_roe,0.8))/(1+(tp_r+0.01))^1+Val!B9*(1-MIN(tp_g/tp_roe,0.8))/(1+(tp_r+0.01))^2+Val!B10*(1-MIN(tp_g/tp_roe,0.8))/(1+(tp_r+0.01))^3+Val!B11*(1-MIN(tp_g/tp_roe,0.8))/(1+(tp_r+0.01))^4+Val!B12*(1-MIN(tp_g/tp_roe,0.8))/(1+(tp_r+0.01))^5+Val!B13*(1-MIN(tp_g/tp_roe,0.8))/(1+(tp_r+0.01))^6+Val!B13*(1-MIN(tp_g/tp_roe,0.8))*(1+tp_g)/((tp_r+0.01)-tp_g)/(1+(tp_r+0.01))^6)+tp_wB*(Val!C8*(1-MIN(tp_g/tp_roe,0.8))/(1+(tp_r+0.01))^1+Val!C9*(1-MIN(tp_g/tp_roe,0.8))/(1+(tp_r+0.01))^2+Val!C10*(1-MIN(tp_g/tp_roe,0.8))/(1+(tp_r+0.01))^3+Val!C11*(1-MIN(tp_g/tp_roe,0.8))/(1+(tp_r+0.01))^4+Val!C12*(1-MIN(tp_g/tp_roe,0.8))/(1+(tp_r+0.01))^5+Val!C13*(1-MIN(tp_g/tp_roe,0.8))/(1+(tp_r+0.01))^6+Val!C13*(1-MIN(tp_g/tp_roe,0.8))*(1+tp_g)/((tp_r+0.01)-tp_g)/(1+(tp_r+0.01))^6)+tp_wC*(Val!D8*(1-MIN(tp_g/tp_roe,0.8))/(1+(tp_r+0.01))^1+Val!D9*(1-MIN(tp_g/tp_roe,0.8))/(1+(tp_r+0.01))^2+Val!D10*(1-MIN(tp_g/tp_roe,0.8))/(1+(tp_r+0.01))^3+Val!D11*(1-MIN(tp_g/tp_roe,0.8))/(1+(tp_r+0.01))^4+Val!D12*(1-MIN(tp_g/tp_roe,0.8))/(1+(tp_r+0.01))^5+Val!D13*(1-MIN(tp_g/tp_roe,0.8))/(1+(tp_r+0.01))^6+Val!D13*(1-MIN(tp_g/tp_roe,0.8))*(1+tp_g)/((tp_r+0.01)-tp_g)/(1+(tp_r+0.01))^6))*(1+(tp_r+0.01)) -> 31.094876 | D34: =tp_comp_adj -> 96.789755 | E34: =tp_w_dcf*C34+(1-tp_w_dcf)*D34 -> 63.942315 | F34: =E34/E$33-1 -> -0.036978519
A35: 折現率 −1pt | B35: r 9% | C35: =(tp_wA*(Val!B8*(1-MIN(tp_g/tp_roe,0.8))/(1+(tp_r-0.01))^1+Val!B9*(1-MIN(tp_g/tp_roe,0.8))/(1+(tp_r-0.01))^2+Val!B10*(1-MIN(tp_g/tp_roe,0.8))/(1+(tp_r-0.01))^3+Val!B11*(1-MIN(tp_g/tp_roe,0.8))/(1+(tp_r-0.01))^4+Val!B12*(1-MIN(tp_g/tp_roe,0.8))/(1+(tp_r-0.01))^5+Val!B13*(1-MIN(tp_g/tp_roe,0.8))/(1+(tp_r-0.01))^6+Val!B13*(1-MIN(tp_g/tp_roe,0.8))*(1+tp_g)/((tp_r-0.01)-tp_g)/(1+(tp_r-0.01))^6)+tp_wB*(Val!C8*(1-MIN(tp_g/tp_roe,0.8))/(1+(tp_r-0.01))^1+Val!C9*(1-MIN(tp_g/tp_roe,0.8))/(1+(tp_r-0.01))^2+Val!C10*(1-MIN(tp_g/tp_roe,0.8))/(1+(tp_r-0.01))^3+Val!C11*(1-MIN(tp_g/tp_roe,0.8))/(1+(tp_r-0.01))^4+Val!C12*(1-MIN(tp_g/tp_roe,0.8))/(1+(tp_r-0.01))^5+Val!C13*(1-MIN(tp_g/tp_roe,0.8))/(1+(tp_r-0.01))^6+Val!C13*(1-MIN(tp_g/tp_roe,0.8))*(1+tp_g)/((tp_r-0.01)-tp_g)/(1+(tp_r-0.01))^6)+tp_wC*(Val!D8*(1-MIN(tp_g/tp_roe,0.8))/(1+(tp_r-0.01))^1+Val!D9*(1-MIN(tp_g/tp_roe,0.8))/(1+(tp_r-0.01))^2+Val!D10*(1-MIN(tp_g/tp_roe,0.8))/(1+(tp_r-0.01))^3+Val!D11*(1-MIN(tp_g/tp_roe,0.8))/(1+(tp_r-0.01))^4+Val!D12*(1-MIN(tp_g/tp_roe,0.8))/(1+(tp_r-0.01))^5+Val!D13*(1-MIN(tp_g/tp_roe,0.8))/(1+(tp_r-0.01))^6+Val!D13*(1-MIN(tp_g/tp_roe,0.8))*(1+tp_g)/((tp_r-0.01)-tp_g)/(1+(tp_r-0.01))^6))*(1+(tp_r-0.01)) -> 42.878767 | D35: =tp_comp_adj -> 96.789755 | E35: =tp_w_dcf*C35+(1-tp_w_dcf)*D35 -> 69.834261 | F35: =E35/E$33-1 -> 0.051758808
A36: 長期成長 +1pt | B36: g 5% | C36: =(tp_wA*(Val!B8*(1-MIN((tp_g+0.01)/tp_roe,0.8))/(1+tp_r)^1+Val!B9*(1-MIN((tp_g+0.01)/tp_roe,0.8))/(1+tp_r)^2+Val!B10*(1-MIN((tp_g+0.01)/tp_roe,0.8))/(1+tp_r)^3+Val!B11*(1-MIN((tp_g+0.01)/tp_roe,0.8))/(1+tp_r)^4+Val!B12*(1-MIN((tp_g+0.01)/tp_roe,0.8))/(1+tp_r)^5+Val!B13*(1-MIN((tp_g+0.01)/tp_roe,0.8))/(1+tp_r)^6+Val!B13*(1-MIN((tp_g+0.01)/tp_roe,0.8))*(1+(tp_g+0.01))/(tp_r-(tp_g+0.01))/(1+tp_r)^6)+tp_wB*(Val!C8*(1-MIN((tp_g+0.01)/tp_roe,0.8))/(1+tp_r)^1+Val!C9*(1-MIN((tp_g+0.01)/tp_roe,0.8))/(1+tp_r)^2+Val!C10*(1-MIN((tp_g+0.01)/tp_roe,0.8))/(1+tp_r)^3+Val!C11*(1-MIN((tp_g+0.01)/tp_roe,0.8))/(1+tp_r)^4+Val!C12*(1-MIN((tp_g+0.01)/tp_roe,0.8))/(1+tp_r)^5+Val!C13*(1-MIN((tp_g+0.01)/tp_roe,0.8))/(1+tp_r)^6+Val!C13*(1-MIN((tp_g+0.01)/tp_roe,0.8))*(1+(tp_g+0.01))/(tp_r-(tp_g+0.01))/(1+tp_r)^6)+tp_wC*(Val!D8*(1-MIN((tp_g+0.01)/tp_roe,0.8))/(1+tp_r)^1+Val!D9*(1-MIN((tp_g+0.01)/tp_roe,0.8))/(1+tp_r)^2+Val!D10*(1-MIN((tp_g+0.01)/tp_roe,0.8))/(1+tp_r)^3+Val!D11*(1-MIN((tp_g+0.01)/tp_roe,0.8))/(1+tp_r)^4+Val!D12*(1-MIN((tp_g+0.01)/tp_roe,0.8))/(1+tp_r)^5+Val!D13*(1-MIN((tp_g+0.01)/tp_roe,0.8))/(1+tp_r)^6+Val!D13*(1-MIN((tp_g+0.01)/tp_roe,0.8))*(1+(tp_g+0.01))/(tp_r-(tp_g+0.01))/(1+tp_r)^6))*(1+tp_r) -> 33.065908 | D36: =tp_comp_adj -> 96.789755 | E36: =tp_w_dcf*C36+(1-tp_w_dcf)*D36 -> 64.927832 | F36: =E36/E$33-1 -> -0.022135868
A37: 長期成長 −1pt | B37: g 3% | C37: =(tp_wA*(Val!B8*(1-MIN((tp_g-0.01)/tp_roe,0.8))/(1+tp_r)^1+Val!B9*(1-MIN((tp_g-0.01)/tp_roe,0.8))/(1+tp_r)^2+Val!B10*(1-MIN((tp_g-0.01)/tp_roe,0.8))/(1+tp_r)^3+Val!B11*(1-MIN((tp_g-0.01)/tp_roe,0.8))/(1+tp_r)^4+Val!B12*(1-MIN((tp_g-0.01)/tp_roe,0.8))/(1+tp_r)^5+Val!B13*(1-MIN((tp_g-0.01)/tp_roe,0.8))/(1+tp_r)^6+Val!B13*(1-MIN((tp_g-0.01)/tp_roe,0.8))*(1+(tp_g-0.01))/(tp_r-(tp_g-0.01))/(1+tp_r)^6)+tp_wB*(Val!C8*(1-MIN((tp_g-0.01)/tp_roe,0.8))/(1+tp_r)^1+Val!C9*(1-MIN((tp_g-0.01)/tp_roe,0.8))/(1+tp_r)^2+Val!C10*(1-MIN((tp_g-0.01)/tp_roe,0.8))/(1+tp_r)^3+Val!C11*(1-MIN((tp_g-0.01)/tp_roe,0.8))/(1+tp_r)^4+Val!C12*(1-MIN((tp_g-0.01)/tp_roe,0.8))/(1+tp_r)^5+Val!C13*(1-MIN((tp_g-0.01)/tp_roe,0.8))/(1+tp_r)^6+Val!C13*(1-MIN((tp_g-0.01)/tp_roe,0.8))*(1+(tp_g-0.01))/(tp_r-(tp_g-0.01))/(1+tp_r)^6)+tp_wC*(Val!D8*(1-MIN((tp_g-0.01)/tp_roe,0.8))/(1+tp_r)^1+Val!D9*(1-MIN((tp_g-0.01)/tp_roe,0.8))/(1+tp_r)^2+Val!D10*(1-MIN((tp_g-0.01)/tp_roe,0.8))/(1+tp_r)^3+Val!D11*(1-MIN((tp_g-0.01)/tp_roe,0.8))/(1+tp_r)^4+Val!D12*(1-MIN((tp_g-0.01)/tp_roe,0.8))/(1+tp_r)^5+Val!D13*(1-MIN((tp_g-0.01)/tp_roe,0.8))/(1+tp_r)^6+Val!D13*(1-MIN((tp_g-0.01)/tp_roe,0.8))*(1+(tp_g-0.01))/(tp_r-(tp_g-0.01))/(1+tp_r)^6))*(1+tp_r) -> 38.602052 | D37: =tp_comp_adj -> 96.789755 | E37: =tp_w_dcf*C37+(1-tp_w_dcf)*D37 -> 67.695903 | F37: =E37/E$33-1 -> 0.019553469
A38: DCF 權重 0.3 | B38: Comparable 0.7 | C38: =(tp_wA*(Val!B8*(1-MIN(tp_g/tp_roe,0.8))/(1+tp_r)^1+Val!B9*(1-MIN(tp_g/tp_roe,0.8))/(1+tp_r)^2+Val!B10*(1-MIN(tp_g/tp_roe,0.8))/(1+tp_r)^3+Val!B11*(1-MIN(tp_g/tp_roe,0.8))/(1+tp_r)^4+Val!B12*(1-MIN(tp_g/tp_roe,0.8))/(1+tp_r)^5+Val!B13*(1-MIN(tp_g/tp_roe,0.8))/(1+tp_r)^6+Val!B13*(1-MIN(tp_g/tp_roe,0.8))*(1+tp_g)/(tp_r-tp_g)/(1+tp_r)^6)+tp_wB*(Val!C8*(1-MIN(tp_g/tp_roe,0.8))/(1+tp_r)^1+Val!C9*(1-MIN(tp_g/tp_roe,0.8))/(1+tp_r)^2+Val!C10*(1-MIN(tp_g/tp_roe,0.8))/(1+tp_r)^3+Val!C11*(1-MIN(tp_g/tp_roe,0.8))/(1+tp_r)^4+Val!C12*(1-MIN(tp_g/tp_roe,0.8))/(1+tp_r)^5+Val!C13*(1-MIN(tp_g/tp_roe,0.8))/(1+tp_r)^6+Val!C13*(1-MIN(tp_g/tp_roe,0.8))*(1+tp_g)/(tp_r-tp_g)/(1+tp_r)^6)+tp_wC*(Val!D8*(1-MIN(tp_g/tp_roe,0.8))/(1+tp_r)^1+Val!D9*(1-MIN(tp_g/tp_roe,0.8))/(1+tp_r)^2+Val!D10*(1-MIN(tp_g/tp_roe,0.8))/(1+tp_r)^3+Val!D11*(1-MIN(tp_g/tp_roe,0.8))/(1+tp_r)^4+Val!D12*(1-MIN(tp_g/tp_roe,0.8))/(1+tp_r)^5+Val!D13*(1-MIN(tp_g/tp_roe,0.8))/(1+tp_r)^6+Val!D13*(1-MIN(tp_g/tp_roe,0.8))*(1+tp_g)/(tp_r-tp_g)/(1+tp_r)^6))*(1+tp_r) -> 36.005445 | D38: =tp_comp_adj -> 96.789755 | E38: =0.3*C38+(1-0.3)*D38 -> 78.554462 | F38: =E38/E$33-1 -> 0.18309189
A39: DCF 權重 0.7 | B39: Comparable 0.3 | C39: =(tp_wA*(Val!B8*(1-MIN(tp_g/tp_roe,0.8))/(1+tp_r)^1+Val!B9*(1-MIN(tp_g/tp_roe,0.8))/(1+tp_r)^2+Val!B10*(1-MIN(tp_g/tp_roe,0.8))/(1+tp_r)^3+Val!B11*(1-MIN(tp_g/tp_roe,0.8))/(1+tp_r)^4+Val!B12*(1-MIN(tp_g/tp_roe,0.8))/(1+tp_r)^5+Val!B13*(1-MIN(tp_g/tp_roe,0.8))/(1+tp_r)^6+Val!B13*(1-MIN(tp_g/tp_roe,0.8))*(1+tp_g)/(tp_r-tp_g)/(1+tp_r)^6)+tp_wB*(Val!C8*(1-MIN(tp_g/tp_roe,0.8))/(1+tp_r)^1+Val!C9*(1-MIN(tp_g/tp_roe,0.8))/(1+tp_r)^2+Val!C10*(1-MIN(tp_g/tp_roe,0.8))/(1+tp_r)^3+Val!C11*(1-MIN(tp_g/tp_roe,0.8))/(1+tp_r)^4+Val!C12*(1-MIN(tp_g/tp_roe,0.8))/(1+tp_r)^5+Val!C13*(1-MIN(tp_g/tp_roe,0.8))/(1+tp_r)^6+Val!C13*(1-MIN(tp_g/tp_roe,0.8))*(1+tp_g)/(tp_r-tp_g)/(1+tp_r)^6)+tp_wC*(Val!D8*(1-MIN(tp_g/tp_roe,0.8))/(1+tp_r)^1+Val!D9*(1-MIN(tp_g/tp_roe,0.8))/(1+tp_r)^2+Val!D10*(1-MIN(tp_g/tp_roe,0.8))/(1+tp_r)^3+Val!D11*(1-MIN(tp_g/tp_roe,0.8))/(1+tp_r)^4+Val!D12*(1-MIN(tp_g/tp_roe,0.8))/(1+tp_r)^5+Val!D13*(1-MIN(tp_g/tp_roe,0.8))/(1+tp_r)^6+Val!D13*(1-MIN(tp_g/tp_roe,0.8))*(1+tp_g)/(tp_r-tp_g)/(1+tp_r)^6))*(1+tp_r) -> 36.005445 | D39: =tp_comp_adj -> 96.789755 | E39: =0.7*C39+(1-0.7)*D39 -> 54.240738 | F39: =E39/E$33-1 -> -0.18309189
A40: 案例區塊：AI 部署 ×0.8（情境 A）
A41: 項目 | B41: 單位 | C41: FY2025A | D41: FY2026（錨點） | E41: FY2027 | F41: FY2028 | G41: FY2029 | H41: FY2030（收斂） | I41: FY2031（收斂） | J41: FY2032（收斂） | K41: 說明
A42: A. AI 加速器 → Amkor AI 先進封裝（D 欄＝FY2026 校準年）
A43: AI 加速器顆數（含情境係數） | B43: 百萬顆 | D43: =units_26 -> 15.2 | E43: =units_27*0.8 -> 18.96 | F43: =units_28*um28_A*0.8 -> 21.2 | G43: =units_29*um29_A*0.8 -> 24.12
A44: 封裝面積指數（2026＝1） | B44: x | D44: =ar_26 -> 1 | E44: =ar_27 -> 1.278156 | F44: =ar_28 -> 1.428615 | G44: =ar_29 -> 1.431796
A45: 後段委外比例 | B45: % | D45: =out_26 -> 0.5 | E45: =out_27 -> 0.55 | F45: =out_28 -> 0.6 | G45: =out_29 -> 0.6 | K45: FY2026 固定基準值（Sens 只動 FY2027 起）
A46: Amkor 份額（占委外後段） | B46: % | D46: =sh_26 -> 0.35 | E46: =sh_27 -> 0.35 | F46: =sh_28 -> 0.37 | G46: =sh_29 -> 0.38
A47: AI 先進封裝營收（2.5D、HDFO、AI 測試） | B47: US$M | C47: =(a26_comp-a25_comp*(1+g_pc26))/(tri-(1+g_pc26)) -> 287.08985 | D47: =C47*tri -> 861.26956 | E47: =E43*E45*E46*E48 -> 1336.0369 | F47: =F43*F45*F46*F48 -> 1821.394 | G47: =G43*G45*G46*G48 -> 2130.6405 | K47: FY2025、FY2026：由運算營收與公司「約三倍」說法反推（Derived）；FY2027 起＝顆數 × 委外 × 份額 × 每顆金額
A48: 每顆封測金額（Amkor 營收 ÷ 委外 ÷ 份額） | B48: US$／顆 | D48: =D47/(D43*D45*D46) -> 323.78555 | E48: =$D48*E44^el -> 366.05757 | F48: =$D48*F44^el -> 387.00365 | G48: =$D48*G44^el -> 387.43427 | K48: FY2026 校準（Derived）；之後 × 封裝面積指數 ^ 彈性
A49: 每顆加速器的 Amkor AI 營收 | B49: US$／顆 | D49: =D47/D43 -> 56.662471 | E49: =E47/E43 -> 70.466082 | F49: =F47/F43 -> 85.914811 | G49: =G47/G43 -> 88.335013 | K49: 含資料中心 CPU 的 HDFO 等連帶營收（拆分未揭露）
A50: B. 終端市場與合計
A51: 運算（非 AI：PC、儲存、基礎設施） | B51: US$M | C51: =a25_comp-C47 -> 1054.5101 | D51: =a26_comp-D47 -> 1022.8748 | E51: =D51*(1+g_pc) -> 1053.5611 | F51: =E51*(1+g_pc) -> 1085.1679 | G51: =F51*(1+g_pc) -> 1117.723
A52: 運算合計 | B52: US$M | C52: =C47+C51 -> 1341.6 | D52: =D47+D51 -> 1884.1444 | E52: =E47+E51 -> 2389.598 | F52: =F47+F51 -> 2906.5619 | G52: =G47+G51 -> 3248.3635
A53: 通訊（Apple 占 FY2025 營收 29.8%） | B53: US$M | C53: =a25_cm -> 3085.68 | D53: =a26_cm -> 3041.8718 | E53: =D53*(1+g_cm27_A) -> 3133.1279 | F53: =E53*(1+g_cmL_A) -> 3258.453 | G53: =F53*(1+g_cmL_A) -> 3388.7912
A54: 車用、工業與其他 | B54: US$M | C54: =a25_au -> 1274.52 | D54: =a26_au -> 1656.9918 | E54: =D54*(1+g_au) -> 1822.6909 | F54: =E54*(1+g_au) -> 2004.96 | G54: =F54*(1+g_au) -> 2205.456
A55: 消費 | B55: US$M | C55: =a25_cs -> 1006.2 | D55: =a26_cs -> 1097.4551 | E55: =D55*(1+g_cs) -> 1130.3788 | F55: =E55*(1+g_cs) -> 1164.2901 | G55: =F55*(1+g_cs) -> 1199.2188
A56: 亞利桑那廠營收（第一期） | B56: US$M | C56: =0 -> 0 | D56: =0 -> 0 | E56: =0 -> 0 | F56: =az_rev28_A -> 150 | G56: =az_rev29_A -> 500 | K56: 第一期滿載約 US$1B（公司）；與既有客戶的亞洲產能可能部分替代（限制）
A57: 營收 | B57: US$M | C57: =C52+C53+C54+C55+C56 -> 6708 | D57: =D52+D53+D54+D55+D56 -> 7680.463 | E57: =E52+E53+E54+E55+E56 -> 8475.7956 | F57: =F52+F53+F54+F55+F56 -> 9484.2651 | G57: =G52+G53+G54+G55+G56 -> 10541.829 | H57: =G57*(1+H58) -> 11536.326 | I57: =H57*(1+I58) -> 12426.574 | J57: =I57*(1+J58) -> 13172.169 | K57: FY2030 起為收斂法：營收年增由 FY2029 線性收斂到 fade_g、淨利率收斂到 fade_m（FY2032 達到），非驅動因子推導
A58: 營收年增 | B58: % | D58: =D57/C57-1 -> 0.14497064 | E58: =E57/D57-1 -> 0.10355269 | F58: =F57/E57-1 -> 0.11898228 | G58: =G57/F57-1 -> 0.11150726 | H58: =$G58+(fade_gA-$G58)*1/3 -> 0.094338173 | I58: =$G58+(fade_gA-$G58)*2/3 -> 0.077169086 | J58: =$G58+(fade_gA-$G58)*3/3 -> 0.06
A59: AI 先進封裝 ÷ 營收 | B59: % | C59: =C47/C57 -> 0.042798129 | D59: =D47/D57 -> 0.11213771 | E59: =E47/E57 -> 0.15762968 | F59: =F47/F57 -> 0.19204377 | G59: =G47/G57 -> 0.20211298
A60: 通訊 ÷ 營收 | B60: % | C60: =C53/C57 -> 0.46 | D60: =D53/D57 -> 0.39605317 | E60: =E53/E57 -> 0.36965591 | F60: =F53/F57 -> 0.3435641 | G60: =G53/G57 -> 0.32146139
A61: C. 折舊、毛利與損益
A62: 本業營收（不含亞利桑那） | B62: US$M | C62: =C57-C56 -> 6708 | D62: =D57-D56 -> 7680.463 | E62: =E57-E56 -> 8475.7956 | F62: =F57-F56 -> 9334.2651 | G62: =G57-G56 -> 10041.829
A63: 本業資本支出（不含亞利桑那） | B63: US$M | D63: =cap_m26 -> 1200 | E63: =capi*E62 -> 1186.6114 | F63: =capi*F62 -> 1306.7971 | G63: =capi*G62 -> 1405.8561 | K63: FY2026 為 Assumed（總額 2.5–3.0B 扣除亞利桑那）；之後＝本業營收 × 資本支出率
A64: 本業折舊攤提 | B64: US$M | C64: =a25_da -> 642 | D64: =a26_da -> 740.6 | E64: =D64*(1-1/life)+D63/life -> 806.22857 | F64: =E64*(1-1/life)+E63/life -> 860.56897 | G64: =F64*(1-1/life)+F63/life -> 924.31585 | K64: 前一年 ×（1 − 1／年限）＋前一年資本支出 ÷ 年限
A65: 亞利桑那折舊（第一期，扣除補助與抵減） | B65: US$M | E65: =0 -> 0 | F65: =az_capex1*(1-az_inc)/az_life*az_svc28 -> 94.791667 | G65: =az_capex1*(1-az_inc)/az_life -> 189.58333
A66: 折舊攤提合計 | B66: US$M | C66: =C64 -> 642 | D66: =D64 -> 740.6 | E66: =E64+E65 -> 806.22857 | F66: =F64+F65 -> 955.36064 | G66: =G64+G65 -> 1113.8992
A67: 本業毛利 ＝ FY2026 ＋ 流通率 × 本業營收增量 − 本業折舊增量 | B67: US$M | C67: =a25_gp -> 938.6 | D67: =a26_gp -> 1325.7873 | E67: =$D67+ft*(E62-$D62)-(E64-$D64) -> 1578.2918 | F67: =$D67+ft*(F62-$D62)-(F64-$D64) -> 1867.3392 | G67: =$D67+ft*(G62-$D62)-(G64-$D64) -> 2086.6181 | K67: 流通率為現金毛利口徑；折舊另計
A68: 亞利桑那毛利 ＝ 營收 × 邊際貢獻率 − 固定現金成本 − 折舊 | B68: US$M | E68: =E56*az_cm-az_fix27 -> -120 | F68: =F56*az_cm-az_fix28-F65 -> -112.29167 | G68: =G56*az_cm-az_fix29-G65 -> -14.583333 | K68: 2027 為投產前啟動成本
A69: 毛利 | B69: US$M | C69: =a25_gp -> 938.6 | D69: =a26_gp -> 1325.7873 | E69: =E67+E68 -> 1458.2918 | F69: =F67+F68 -> 1755.0475 | G69: =G67+G68 -> 2072.0347
A70: 毛利率 | B70: % | C70: =C69/C57 -> 0.13992248 | D70: =D69/D57 -> 0.17261815 | E70: =E69/E57 -> 0.17205367 | F70: =F69/F57 -> 0.18504834 | G70: =G69/G57 -> 0.19655362
A71: 亞利桑那對毛利率的影響（亞利桑那毛利 ÷ 營收） | B71: pt | E71: =E68/E57 -> -0.014157963 | F71: =F68/F57 -> -0.011839786 | G71: =G68/G57 -> -0.0013833778 | K71: 公司：啟動成本使營業利益率降約 1–2%（2027 起、2028 改善）
A72: 營業費用（銷管＋研發） | B72: US$M | C72: =a25_opx -> 471.2 | D72: =a26_opx -> 537.5 | E72: =(D72+opx_gain)*(1+phi*E58) -> 587.41709 | F72: =E72*(1+phi*F58) -> 622.3632 | G72: =F72*(1+phi*G58) -> 657.06221 | K72: FY2027 基期加回 2Q26 不動產處分利益
A73: 營業利益 | B73: US$M | C73: =C69-C72 -> 467.4 | D73: =D69-D72 -> 788.28731 | E73: =E69-E72 -> 870.87469 | F73: =F69-F72 -> 1132.6843 | G73: =G69-G72 -> 1414.9725
A74: 營業利益率 | B74: % | C74: =C73/C57 -> 0.069677996 | D74: =D73/D57 -> 0.10263539 | E74: =E73/E57 -> 0.10274843 | F74: =F73/F57 -> 0.11942774 | G74: =G73/G57 -> 0.13422457
A75: 營業外淨額 | B75: US$M | C75: =a25_nonop -> -22.7 | D75: =a26_nonop -> -0.7 | E75: =nonop27 -> -20 | F75: =nonop28 -> -40 | G75: =nonop29 -> -60
A76: 稅前利益 | B76: US$M | C76: =C73+C75 -> 444.7 | D76: =D73+D75 -> 787.58731 | E76: =E73+E75 -> 850.87469 | F76: =F73+F75 -> 1092.6843 | G76: =G73+G75 -> 1354.9725
A77: 所得稅 | B77: US$M | C77: =a25_tax -> 68.5 | D77: =a26_tax -> 138.23746 | E77: =E76*tax -> 170.17494 | F77: =F76*tax -> 218.53686 | G77: =G76*tax -> 270.9945
A78: 非控制權益 | B78: US$M | C78: =a25_nci -> 2.3 | D78: =a26_nci -> 3.7 | E78: =nci -> 3 | F78: =nci -> 3 | G78: =nci -> 3
A79: 歸屬母公司淨利 | B79: US$M | C79: =C76-C77-C78 -> 373.9 | D79: =D76-D77-D78 -> 645.64985 | E79: =E76-E77-E78 -> 677.69975 | F79: =F76-F77-F78 -> 871.14744 | G79: =G76-G77-G78 -> 1080.978 | H79: =H57*H83 -> 1214.2314 | I79: =I57*I83 -> 1341.6219 | J79: =J57*J83 -> 1457.83
A80: 稀釋股數 | B80: 百萬股 | C80: =a25_sh -> 248.5 | D80: =a26_sh -> 249.915 | E80: =D80*(1+sh_g) -> 249.915 | F80: =E80*(1+sh_g) -> 249.915 | G80: =F80*(1+sh_g) -> 249.915 | H80: =G80*(1+sh_g) -> 249.915 | I80: =H80*(1+sh_g) -> 249.915 | J80: =I80*(1+sh_g) -> 249.915
A81: EPS（稀釋） | B81: US$ | C81: =C79/C80 -> 1.5046278 | D81: =D79/D80 -> 2.5834778 | E81: =E79/E80 -> 2.711721 | F81: =F79/F80 -> 3.4857749 | G81: =G79/G80 -> 4.3253827 | H81: =H79/H80 -> 4.8585775 | I81: =I79/I80 -> 5.368313 | J81: =J79/J80 -> 5.8333035
A82: EPS 年增 | B82: % | D82: =D81/C81-1 -> 0.71702121 | E82: =E81/D81-1 -> 0.049639754 | F82: =F81/E81-1 -> 0.28544748 | G82: =G81/F81-1 -> 0.24086688 | H82: =H81/G81-1 -> 0.12327113 | I82: =I81/H81-1 -> 0.10491456 | J82: =J81/I81-1 -> 0.086617624
A83: 淨利率（歸屬母公司淨利 ÷ 營收） | B83: % | C83: =C79/C57 -> 0.055739416 | D83: =D79/D57 -> 0.084063923 | E83: =E79/E57 -> 0.079957066 | F83: =F79/F57 -> 0.091851865 | G83: =G79/G57 -> 0.10254178 | H83: =$G83+(fade_mA-$G83)*1/3 -> 0.10525286 | I83: =$G83+(fade_mA-$G83)*2/3 -> 0.10796394 | J83: =$G83+(fade_mA-$G83)*3/3 -> 0.11067502
A86: 案例區塊：AI 部署 ×1.2（情境 A）
A87: 項目 | B87: 單位 | C87: FY2025A | D87: FY2026（錨點） | E87: FY2027 | F87: FY2028 | G87: FY2029 | H87: FY2030（收斂） | I87: FY2031（收斂） | J87: FY2032（收斂） | K87: 說明
A88: A. AI 加速器 → Amkor AI 先進封裝（D 欄＝FY2026 校準年）
A89: AI 加速器顆數（含情境係數） | B89: 百萬顆 | D89: =units_26 -> 15.2 | E89: =units_27*1.2 -> 28.44 | F89: =units_28*um28_A*1.2 -> 31.8 | G89: =units_29*um29_A*1.2 -> 36.18
A90: 封裝面積指數（2026＝1） | B90: x | D90: =ar_26 -> 1 | E90: =ar_27 -> 1.278156 | F90: =ar_28 -> 1.428615 | G90: =ar_29 -> 1.431796
A91: 後段委外比例 | B91: % | D91: =out_26 -> 0.5 | E91: =out_27 -> 0.55 | F91: =out_28 -> 0.6 | G91: =out_29 -> 0.6 | K91: FY2026 固定基準值（Sens 只動 FY2027 起）
A92: Amkor 份額（占委外後段） | B92: % | D92: =sh_26 -> 0.35 | E92: =sh_27 -> 0.35 | F92: =sh_28 -> 0.37 | G92: =sh_29 -> 0.38
A93: AI 先進封裝營收（2.5D、HDFO、AI 測試） | B93: US$M | C93: =(a26_comp-a25_comp*(1+g_pc26))/(tri-(1+g_pc26)) -> 287.08985 | D93: =C93*tri -> 861.26956 | E93: =E89*E91*E92*E94 -> 2004.0554 | F93: =F89*F91*F92*F94 -> 2732.091 | G93: =G89*G91*G92*G94 -> 3195.9608 | K93: FY2025、FY2026：由運算營收與公司「約三倍」說法反推（Derived）；FY2027 起＝顆數 × 委外 × 份額 × 每顆金額
A94: 每顆封測金額（Amkor 營收 ÷ 委外 ÷ 份額） | B94: US$／顆 | D94: =D93/(D89*D91*D92) -> 323.78555 | E94: =$D94*E90^el -> 366.05757 | F94: =$D94*F90^el -> 387.00365 | G94: =$D94*G90^el -> 387.43427 | K94: FY2026 校準（Derived）；之後 × 封裝面積指數 ^ 彈性
A95: 每顆加速器的 Amkor AI 營收 | B95: US$／顆 | D95: =D93/D89 -> 56.662471 | E95: =E93/E89 -> 70.466082 | F95: =F93/F89 -> 85.914811 | G95: =G93/G89 -> 88.335013 | K95: 含資料中心 CPU 的 HDFO 等連帶營收（拆分未揭露）
A96: B. 終端市場與合計
A97: 運算（非 AI：PC、儲存、基礎設施） | B97: US$M | C97: =a25_comp-C93 -> 1054.5101 | D97: =a26_comp-D93 -> 1022.8748 | E97: =D97*(1+g_pc) -> 1053.5611 | F97: =E97*(1+g_pc) -> 1085.1679 | G97: =F97*(1+g_pc) -> 1117.723
A98: 運算合計 | B98: US$M | C98: =C93+C97 -> 1341.6 | D98: =D93+D97 -> 1884.1444 | E98: =E93+E97 -> 3057.6165 | F98: =F93+F97 -> 3817.2589 | G98: =G93+G97 -> 4313.6837
A99: 通訊（Apple 占 FY2025 營收 29.8%） | B99: US$M | C99: =a25_cm -> 3085.68 | D99: =a26_cm -> 3041.8718 | E99: =D99*(1+g_cm27_A) -> 3133.1279 | F99: =E99*(1+g_cmL_A) -> 3258.453 | G99: =F99*(1+g_cmL_A) -> 3388.7912
A100: 車用、工業與其他 | B100: US$M | C100: =a25_au -> 1274.52 | D100: =a26_au -> 1656.9918 | E100: =D100*(1+g_au) -> 1822.6909 | F100: =E100*(1+g_au) -> 2004.96 | G100: =F100*(1+g_au) -> 2205.456
A101: 消費 | B101: US$M | C101: =a25_cs -> 1006.2 | D101: =a26_cs -> 1097.4551 | E101: =D101*(1+g_cs) -> 1130.3788 | F101: =E101*(1+g_cs) -> 1164.2901 | G101: =F101*(1+g_cs) -> 1199.2188
A102: 亞利桑那廠營收（第一期） | B102: US$M | C102: =0 -> 0 | D102: =0 -> 0 | E102: =0 -> 0 | F102: =az_rev28_A -> 150 | G102: =az_rev29_A -> 500 | K102: 第一期滿載約 US$1B（公司）；與既有客戶的亞洲產能可能部分替代（限制）
A103: 營收 | B103: US$M | C103: =C98+C99+C100+C101+C102 -> 6708 | D103: =D98+D99+D100+D101+D102 -> 7680.463 | E103: =E98+E99+E100+E101+E102 -> 9143.8141 | F103: =F98+F99+F100+F101+F102 -> 10394.962 | G103: =G98+G99+G100+G101+G102 -> 11607.15 | H103: =G103*(1+H104) -> 12741.656 | I103: =H103*(1+I104) -> 13746.603 | J103: =I103*(1+J104) -> 14571.399 | K103: FY2030 起為收斂法：營收年增由 FY2029 線性收斂到 fade_g、淨利率收斂到 fade_m（FY2032 達到），非驅動因子推導
A104: 營收年增 | B104: % | D104: =D103/C103-1 -> 0.14497064 | E104: =E103/D103-1 -> 0.19052901 | F104: =F103/E103-1 -> 0.13682999 | G104: =G103/F103-1 -> 0.116613 | H104: =$G104+(fade_gA-$G104)*1/3 -> 0.097741997 | I104: =$G104+(fade_gA-$G104)*2/3 -> 0.078870999 | J104: =$G104+(fade_gA-$G104)*3/3 -> 0.06
A105: AI 先進封裝 ÷ 營收 | B105: % | C105: =C93/C103 -> 0.042798129 | D105: =D93/D103 -> 0.11213771 | E105: =E93/E103 -> 0.21917062 | F105: =F93/F103 -> 0.26282837 | G105: =G93/G103 -> 0.27534415
...

Sheet Sources
A1: 來源（SEC 申報為公司原文；法說內容經逐字稿與摘要；券商與資料商皆為 Interested-party）
A2: 公司：2Q26 新聞稿（SEC 8-K，2026-07-27；1H26、2Q26 損益、終端市場占比、3Q26 指引、資本支出） | B2: https://www.sec.gov/Archives/edgar/data/0001047127/000104712726000043/amkr6302026erex-991.htm
A3: 公司：4Q25 新聞稿（SEC 8-K，2026-02-09；FY2025 損益、終端市場占比、先進／主流產品） | B3: https://www.sec.gov/Archives/edgar/data/1047127/000104712726000007/amkr123125erex-991.htm
A4: 公司：FY2025 10-K（Apple 29.8%、Qualcomm 11.1%、前十大 72%、2.5D 與 HDFO 說明） | B4: https://www.sec.gov/Archives/edgar/data/1047127/000104712726000014/amkr-20251231.htm
A5: 公司：投資人日簡報（SEC 8-K，2026-05-21；2028、2030 目標、終端市場 CAGR、亞利桑那、0.5B／GW） | B5: https://www.sec.gov/Archives/edgar/data/0001047127/000104712726000036/ex-991amkorinvestorprese.htm
A6: 公司：4Q25 法說逐字稿（Motley Fool；2.5D 與 HDFO 近三倍、亞利桑那第一期約一半、資產出售 30） | B6: https://www.fool.com/earnings/call-transcripts/2026/02/09/amkor-amkr-q4-2025-earnings-call-transcript/
A7: 公司：1Q26 法說逐字稿（Motley Fool；AI 封裝三倍、亞利桑那稀釋 1–2%、CHIPS 400M＋35% 抵減） | B7: https://www.fool.com/earnings/call-transcripts/2026/04/27/amkor-amkr-q1-2026-earnings-call-transcript/
A8: 公司（摘要）：MarketBeat 2Q26 法說重點（3Q 各終端市場、營業費用 140、NVIDIA、台積電合作） | B8: https://www.marketbeat.com/instant-alerts/amkor-technology-q2-earnings-call-highlights-2026-07-27/
A9: 公司：亞利桑那第二期、投資擴大至約 US$12B（2026-09-08） | B9: https://ir.amkor.com/node/24686
A10: 公司：亞利桑那 US$7B 計畫（Business Wire 2025-10-06） | B10: https://www.businesswire.com/news/home/20251006108489/en
A11: 公司：與 NVIDIA 策略合作（Business Wire 2026-07-23）；Reuters 經 The Star：US$1.5B | B11: https://www.thestar.com.my/tech/tech-news/2026/07/24/nvidia-amkor-strike-15-billion-chip-packaging-deal
A12: 公司：與台積電長期合作（Business Wire 2026-06-16） | B12: https://www.businesswire.com/news/home/20260616574153/en/
A13: 媒體：Manufacturing Dive（亞利桑那 2027 年中完工、2028 年初投產、CHIPS 407M） | B13: https://www.manufacturingdive.com/news/amkor-arizona-7-billion-semiconductor-tsmc-apple-nvidia/802297/
... A25: SemiAnalysis | B25: 未使用
