Workbook

Sheet README
A1: AMD（AMD）收支與估值模型 v0.2（AI 半導體 Project：運算層，GPU 側非 NVIDIA 份額） 2026-10-25
A2: 本版：運算層第三個模型，複製 nvidia/ 的結構，匯入 nvidia/accel_share.py 的份額函式（AMD 為 GPU 側非 NVIDIA 份額）；Val 頁第 0 節為情境加權目標價。
A3: 模型命題：AMD 的資料中心 GPU 營收＝加速器市場（本專案加速器數量層 × 各平台每顆價）× AMD 金額份額；OpenAI、Meta 各 6 GW 與 Anthropic、Oracle 大單在 2026 下半年起放量，但每 GW 附帶認股權證稀釋，HBM 漲價又壓 GPU 毛利率。股價約為 FY2027 共識 EPS 的 33 倍：要多少大單如期放量、毛利率守住多少，才撐得住現價。
A4: 核心問題：以市場層顆數推得的 AMD 資料中心 GPU 營收與 EPS，能否支撐現價與公司「2027 年資料中心逾一倍、EPS 逾 $20」的說法；差距來自顆數、售價還是毛利率。
A6: 會計年度：AMD 會計年度約在 12 月最後一個週六結束，等於日曆年（FY2026＝CY2026），上游市場層直接對照，不平移。預測期 FY2027–FY2029；FY2026 為錨點（Q1、Q2 實績＋Q3 指引＋Q4 假設）。
A8: 驅動因子 → 推導量（全部唯讀上游，不修改）
A9: 資料中心 GPU：加速器市場金額（Units 頁，markets/memory UNITS × 情境係數 × NVIDIA 模型同一套每顆價）× AMD 金額份額 × k_rec（FY2026 校準）× 世代售價係數（基準 1.0）；HBM 漲價依吸收比例轉嫁或壓毛利率。資料中心非 GPU（EPYC CPU 等）、Client、Gaming、Embedded：FY2026 錨點 × 簡化成長率（Assumed）。
A10: 毛利率：GPU 毛利率（Assumed 50%）＋非 GPU 毛利率（FY2026 校準到錨點，Derived）；FY2027 起變化來自 GPU 占比上升與 HBM 價格（markets/memory 2027 +80%）。營業費用彈性（FY2026 推得）、稅率 13%（公司）、股數＋OpenAI／Meta 認股權證（各 160M 股，依 GW 線性歸屬，Assumed）。
A11: EPS 口徑：non-GAAP（公司口徑，排除股票薪酬與併購攤銷）；共識同口徑。
A12: 校準：k_rec＝FY2026 錨點 GPU 營收 ÷（AMD 市場層 CY2026 顆數 × pa_amd）；錨點 GPU 本身含 Assumed 拆分（公司不揭露）。不用共識、不用公司對 2027 的說法；後者只在 Recon 對帳。
A13: 估值：目標價＝十年 non-GAAP P/E 中位數 × FY2027 EPS（各情境），權重 A 0.3／B 0.5／C 0.2（Andy 可改）；依循環位置取分位的規則值不適用（落後倍數含高成長期溢價，比照 NVIDIA），保留計算。循環位置（共用規則，不平移）：見頂年度 A 2029、B 2028、C 2027 → FY2027：A 中段、B 中段、C 見頂。本版未做先驗，無 Andy 合理 P/E 對照。
A15: 標記：Verified、Interested-party、Analogy、Assumed、Derived。SemiAnalysis 未使用。公司原文＝8-K 新聞稿、簡報與 10-Q（sec.gov，已抓取）；法說逐字稿只經摘要（標二手）。
... A18: 情境對應（v0.2 延伸期）：A＝順利（市場層基準顆數）、B＝平平（AI 資本支出消化：CY2028 ×0.8、CY2029 ×0.85）、C＝不如預期（CY2028–29 ×0.6）；FY2027 三情境相同，情境差從 FY2028 起。本版未做先驗，無 Andy 合理 P/E 對照。

Sheet In
A1: In — 輸入（藍字；基準欄 E，低 D、高 F）。金額：十億美元（US$B）；每顆價格：千美元（US$K）；顆數：百萬顆；股數：十億股。每個輸入附兩個來源（找不到者寫「未找到」）；公司原文算一個
A2: 標記：Verified／Interested-party／Analogy／Assumed／Derived；Analogy、Assumed 給低／高區間。SemiAnalysis 未單獨使用。公司原文＝AMD 8-K 新聞稿與簡報（sec.gov 已逐頁抓取）；法說逐字稿只經摘要（二手）
A3: 鍵 | B3: 項目 | C3: 單位 | D3: 低 | E3: 基準 | F3: 高 | G3: 標記 | H3: 來源1 | I3: 來源2／說明
A4: A. 加速器顆數（markets/memory 與 HBM、台積電、網通、NVIDIA 模型同一份；情境係數讀台積電模型成品，不另訂）
A5: u_bw_26 | B5: NVIDIA Blackwell（B200／B300） 顆數 2026 | C5: 百萬顆 | E5: 5.4 | G5: Interested-party | H5: markets/memory/market.py UNITS：顆數：Morgan Stanley 2026-07（2026 5.4M）；AC Research 2027 約 2.4M；2028 Assumed。GB：B200 186、B300 288 組合 [Derived] | I5: 台積電模型 tsmc/dist/20261025_台積電模型_v0.3.xlsx｜In!E5（值相同，建置時檢查）
A6: u_bw_27 | B6: NVIDIA Blackwell（B200／B300） 顆數 2027 | C6: 百萬顆 | E6: 2.4 | G6: Interested-party | H6: 同上 | I6: 同上
A7: u_bw_28 | B7: NVIDIA Blackwell（B200／B300） 顆數 2028 | C7: 百萬顆 | E7: 0.5 | G7: Interested-party | H7: 同上 | I7: 同上
A8: g29_bw | B8: NVIDIA Blackwell（B200／B300） 2029 顆數成長 | C8: % | E8: -0.5 | G8: Assumed | H8: tsmc/dist/20261025_台積電模型_v0.3.xlsx｜In!E8 | I8: markets/memory 無 2029；沿用台積電模型
A9: u_rb_26 | B9: NVIDIA Rubin 顆數 2026 | C9: 百萬顆 | E9: 1.7 | G9: Interested-party | H9: markets/memory/market.py UNITS：2026：TrendForce 組合 Rubin 22% × 約 7.6M [Derived]；2027：Morgan Stanley 約 7.0M；2028 Assumed | I9: 台積電模型 tsmc/dist/20261025_台積電模型_v0.3.xlsx｜In!E9（值相同，建置時檢查）
A10: u_rb_27 | B10: NVIDIA Rubin 顆數 2027 | C10: 百萬顆 | E10: 7 | G10: Interested-party | H10: 同上 | I10: 同上
A11: u_rb_28 | B11: NVIDIA Rubin 顆數 2028 | C11: 百萬顆 | E11: 7 | G11: Interested-party | H11: 同上 | I11: 同上
A12: g29_rb | B12: NVIDIA Rubin 2029 顆數成長 | C12: % | E12: 0.15 | G12: Assumed | H12: tsmc/dist/20261025_台積電模型_v0.3.xlsx｜In!E12 | I12: markets/memory 無 2029；沿用台積電模型
A13: u_ru_26 | B13: NVIDIA Rubin Ultra 顆數 2026 | C13: 百萬顆 | E13: 0 | G13: Assumed | H13: markets/memory/market.py UNITS：時程 Assumed；GB：NVIDIA 1 TB／封裝 | I13: 台積電模型 tsmc/dist/20261025_台積電模型_v0.3.xlsx｜In!E13（值相同，建置時檢查）
A14: u_ru_27 | B14: NVIDIA Rubin Ultra 顆數 2027 | C14: 百萬顆 | E14: 0.3 | G14: Assumed | H14: 同上 | I14: 同上
A15: u_ru_28 | B15: NVIDIA Rubin Ultra 顆數 2028 | C15: 百萬顆 | E15: 2 | G15: Assumed | H15: 同上 | I15: 同上
A16: g29_ru | B16: NVIDIA Rubin Ultra 2029 顆數成長 | C16: % | E16: 0.15 | G16: Assumed | H16: tsmc/dist/20261025_台積電模型_v0.3.xlsx｜In!E16 | I16: markets/memory 無 2029；沿用台積電模型
... A45: gb_amd_28 | B45: AMD Instinct 每顆 HBM 2028 | C45: GB | E45: 432 | G45: Interested-party | H45: 同上 | I45: 同上
A46: B. 各平台每顆售價（金額份額用；與 NVIDIA 模型同一套價格，讀 NVIDIA 成品 In 頁；模組層級）
A47: pm_bw | B47: 每顆售價：NVIDIA Blackwell（B200／B300） | C47: US$K | D47: 37.6 | E47: 40.4 | F47: 47 | G47: Derived | H47: nvidia/dist/20261025_NVIDIA模型_v0.2.xlsx｜In!D56:F56 | I47: markets/chip_bridge/dist/20261023_晶片內容橋接表_v0.2.1.xlsx｜Rack!B6
A48: pm_rb | B48: 每顆售價：NVIDIA Rubin | C48: US$K | D48: 50 | E48: 55 | F48: 60 | G48: Derived | H48: nvidia/dist/20261025_NVIDIA模型_v0.2.xlsx｜In!D57:F57 | I48: markets/chip_bridge/dist/20261023_晶片內容橋接表_v0.2.1.xlsx｜Rack!C6
A49: pm_ru | B49: 每顆售價：NVIDIA Rubin Ultra | C49: US$K | D49: 60 | E49: 75 | F49: 100 | G49: Derived | H49: nvidia/dist/20261025_NVIDIA模型_v0.2.xlsx｜In!D58:F58 | I49: 無：未發布。基準＝VR200 55 ×（VR200／GB300 的 1.36 倍外推）＝75
A50: pm_hp | B50: 每顆售價：NVIDIA Hopper（H200 等） | C50: US$K | D50: 25 | E50: 30 | F50: 35 | G50: Derived | H50: nvidia/dist/20261025_NVIDIA模型_v0.2.xlsx｜In!D59:F59 | I50: 無：2026 出貨僅 0.5M，影響小
A51: pa_amd | B51: 每顆售價：AMD Instinct | C51: US$K | D51: 20 | E51: 30 | F51: 45 | G51: Derived | H51: nvidia/dist/20261025_NVIDIA模型_v0.2.xlsx｜In!D145:F145 | I51: MI355X：HSBC 約 $23K（自 $25K 下修）、其他報導 $20–25K；MI455X 無官方價，部落格 $15–50K（finviz、gpusmith、MikeLongTerm；賣方有目標價誘因）
A52: pa_tpu | B52: 每顆售價：Google TPU | C52: US$K | D52: 8 | E52: 12 | F52: 18 | G52: Derived | H52: nvidia/dist/20261025_NVIDIA模型_v0.2.xlsx｜In!D146:F146 | I52: 無：每顆 ASP 未找到（只有租用價代理：Ironwood $1.03–1.60／小時，SemiAnalysis，不可單獨使用）
A53: pa_trn | B53: 每顆售價：AWS Trainium | C53: US$K | D53: 5 | E53: 8 | F53: 12 | G53: Derived | H53: nvidia/dist/20261025_NVIDIA模型_v0.2.xlsx｜In!D147:F147 | I53: 無：每顆 ASP 未找到
A54: pa_oth | B54: 每顆售價：其他 ASIC（MTIA、Maia、Ascend 等） | C54: US$K | D54: 5 | E54: 8 | F54: 12 | G54: Derived | H54: nvidia/dist/20261025_NVIDIA模型_v0.2.xlsx｜In!D148:F148 | I54: 無：未找到（Maia、MTIA 皆無 ASP）
A55: C. HBM 價格路徑（情境別；讀 NVIDIA 成品 In 頁，原始來源 skhynix 成品 Mkt 頁；唯讀）
A56: hbm_A_26 | B56: HBM 混合單價 2026（A） | C56: US$/GB | E56: 14.6 | G56: Derived | H56: nvidia/dist/20261025_NVIDIA模型_v0.2.xlsx｜In!D79:F79 | I56: markets/memory：2026 BofA $14.6/GB；2027 +80% 三情境相同；2028–29 依情境
A57: hbm_A_27 | B57: HBM 混合單價 2027（A） | C57: US$/GB | E57: 26.28 | G57: Derived | H57: nvidia/dist/20261025_NVIDIA模型_v0.2.xlsx｜In!D80:F80 | I57: 同上
A58: hbm_A_28 | B58: HBM 混合單價 2028（A） | C58: US$/GB | E58: 28.908 | G58: Derived | H58: nvidia/dist/20261025_NVIDIA模型_v0.2.xlsx｜In!D81:F81 | I58: 同上
A59: hbm_A_29 | B59: HBM 混合單價 2029（A） | C59: US$/GB | E59: 27.4626 | G59: Derived | H59: nvidia/dist/20261025_NVIDIA模型_v0.2.xlsx｜In!D82:F82 | I59: 同上
A60: hbm_B_26 | B60: HBM 混合單價 2026（B） | C60: US$/GB | E60: 14.6 | G60: Derived | H60: nvidia/dist/20261025_NVIDIA模型_v0.2.xlsx｜In!D83:F83 | I60: 同上
A61: hbm_B_27 | B61: HBM 混合單價 2027（B） | C61: US$/GB | E61: 26.28 | G61: Derived | H61: nvidia/dist/20261025_NVIDIA模型_v0.2.xlsx｜In!D84:F84 | I61: 同上
A62: hbm_B_28 | B62: HBM 混合單價 2028（B） | C62: US$/GB | E62: 19.71 | G62: Derived | H62: nvidia/dist/20261025_NVIDIA模型_v0.2.xlsx｜In!D85:F85 | I62: 同上
A63: hbm_B_29 | B63: HBM 混合單價 2029（B） | C63: US$/GB | E63: 19.71 | G63: Derived | H63: nvidia/dist/20261025_NVIDIA模型_v0.2.xlsx｜In!D86:F86 | I63: 同上
A64: hbm_C_26 | B64: HBM 混合單價 2026（C） | C64: US$/GB | E64: 14.6 | G64: Derived | H64: nvidia/dist/20261025_NVIDIA模型_v0.2.xlsx｜In!D87:F87 | I64: 同上
A65: hbm_C_27 | B65: HBM 混合單價 2027（C） | C65: US$/GB | E65: 26.28 | G65: Derived | H65: nvidia/dist/20261025_NVIDIA模型_v0.2.xlsx｜In!D88:F88 | I65: 同上
A66: hbm_C_28 | B66: HBM 混合單價 2028（C） | C66: US$/GB | E66: 15.768 | G66: Derived | H66: nvidia/dist/20261025_NVIDIA模型_v0.2.xlsx｜In!D89:F89 | I66: 同上
A67: hbm_C_29 | B67: HBM 混合單價 2029（C） | C67: US$/GB | E67: 16.5564 | G67: Derived | H67: nvidia/dist/20261025_NVIDIA模型_v0.2.xlsx｜In!D90:F90 | I67: 同上
A68: D. AMD 資料中心 GPU（Instinct）：公司不拆分 GPU 與 CPU，拆分比例為 Assumed
A69: gpu25 | B69: FY2025 資料中心 GPU 營收（歷史對照；不進預測） | C69: US$B | D69: 5.9 | E69: 6.5 | F69: 7.5 | G69: Assumed | H69: 公司不揭露。Next Platform 估 Q4 2025 Instinct 2.65（含中國 MI308 0.39）；Wells Fargo 估 Q4 約 2.5–2.6（二手）；Q2 2025 有 MI308 出口管制費用 $0.8B（公司） | I69: 2024 Instinct 逾 $5B（公司 2025-01 法說，二手）。各季拆分：未找到
A70: gs_q1 | B70: Q1 2026 GPU 占資料中心營收 | C70: % | D70: 0.38 | E70: 0.42 | F70: 0.46 | G70: Assumed | H70: 公司不揭露；Q4 2025 Next Platform 估 GPU 約占 49%（含中國）；Q1 2026 中國 MI308 約 $0.1B（公司指引） | I70: 第二來源：未找到
A71: gs_q2 | B71: Q2 2026 GPU 占資料中心營收 | C71: % | D71: 0.39 | E71: 0.43 | F71: 0.47 | G71: Assumed | H71: 公司：資料中心 AI 營收年增逾一倍（Q2 2025 基期受 MI308 管制壓低）；伺服器 CPU 雲端與企業皆年增逾 70%（法說摘要，二手：MarketBeat） | I71: 第二來源：未找到
A72: ng_q3 | B72: Q3 2026 資料中心非 GPU（CPU 等）季增 | C72: % | D72: 0.04 | E72: 0.08 | F72: 0.12 | G72: Assumed | H72: 公司：下半年伺服器營收年增逾 80%、2026 伺服器 CPU 供給吃緊（法說摘要，二手） | I72: —
A73: ng_q4 | B73: Q4 2026 資料中心非 GPU 季增 | C73: % | D73: 0.02 | E73: 0.06 | F73: 0.1 | G73: Assumed | H73: 同上；Venice（Zen 6）2026 下半年開始部署（公司） | I73: —
A74: gm_gpu | B74: 資料中心 GPU 毛利率（FY2026；non-GAAP 口徑） | C74: % | D74: 0.4 | E74: 0.5 | F74: 0.55 | G74: Assumed | H74: 公司：資料中心 AI 毛利率低於公司平均（Q2 2026 法說摘要，二手）；公司平均 FY2026 錨點約 56% | I74: 第二來源：未找到。非 GPU 毛利率由此在 FY2026 校準（Derived，PL 各區塊）
A75: abs_mem | B75: HBM 漲價由 AMD 吸收的比例（其餘轉嫁到售價） | C75: x | D75: 0 | E75: 0.5 | F75: 1 | G75: Assumed | H75: 比照 NVIDIA 模型（Assumed 0–1，基準 0.5） | I75: 第二來源：未找到。AMD 對 HBM4 合約價轉嫁的公開說法：未找到
A76: uf | B76: AMD 顆數係數（Sens 用；FY2027 起乘以 AMD 市場層顆數） | C76: x | D76: 0.8 | E76: 1 | F76: 1.2 | G76: Assumed | H76: 無：OpenAI、Meta 各 6 GW、Anthropic 2 GW、Oracle 5 萬顆等大單的時點不確定（見 H 節） | I76: ±20%
A77: pg_27 | B77: 世代售價係數 2027（MI450／Helios 每顆售價 ÷ FY2026 認列售價） | C77: x | D77: 1 | E77: 1 | F77: 1.25 | G77: Analogy／Assumed | H77: 基準 1.0＝k_rec 延續（比照 NVIDIA 模型：FY2026 校準的水準沿用）；高＝售價隨 HBM 容量等比例（Analogy：432 ÷ 288） | I77: MI455X 官方價：未找到；部落格 $15–50K（NVIDIA 模型 In 頁 pa_amd 說明）
A78: pg_28 | B78: 世代售價係數 2028（MI450／Helios 每顆售價 ÷ FY2026 認列售價） | C78: x | D78: 1 | E78: 1 | F78: 1.5 | G78: Analogy／Assumed | H78: 基準 1.0＝k_rec 延續（比照 NVIDIA 模型：FY2026 校準的水準沿用）；高＝售價隨 HBM 容量等比例（Analogy：432 ÷ 288） | I78: MI455X 官方價：未找到；部落格 $15–50K（NVIDIA 模型 In 頁 pa_amd 說明）
A79: pg_29 | B79: 世代售價係數 2029（MI450／Helios 每顆售價 ÷ FY2026 認列售價） | C79: x | D79: 1 | E79: 1 | F79: 1.5 | G79: Analogy／Assumed | H79: 基準 1.0＝k_rec 延續（比照 NVIDIA 模型：FY2026 校準的水準沿用）；高＝售價隨 HBM 容量等比例（Analogy：432 ÷ 288） | I79: MI455X 官方價：未找到；部落格 $15–50K（NVIDIA 模型 In 頁 pa_amd 說明）
A80: E. 其他業務（簡化成長率；FY2027 起）
A81: g_cpu27 | B81: 資料中心非 GPU（EPYC CPU 等）年增 FY2027 | C81: % | D81: 0.3 | E81: 0.5 | F81: 0.7 | G81: Assumed | H81: 公司：2027 伺服器 CPU 年增逾 70%（Q2 2026 法說摘要，二手；只作 Recon，高＝公司說法） | I81: 伺服器 CPU 市場 2030 年約 $220B、年增逾 50%（公司，Interested-party）
A82: g_cpu28 | B82: 資料中心非 GPU 年增 FY2028 | C82: % | D82: 0.1 | E82: 0.25 | F82: 0.4 | G82: Assumed | H82: 無 | I82: —
A83: g_cpu29 | B83: 資料中心非 GPU 年增 FY2029 | C83: % | D83: 0.05 | E83: 0.15 | F83: 0.25 | G83: Assumed | H83: 無 | I83: —
A84: g_cli | B84: Client（PC 處理器）年增（FY2027 起） | C84: % | D84: -0.05 | E84: 0.03 | F84: 0.1 | G84: Assumed | H84: 公司：2026 下半年 PC 市場轉弱、季節性低於上半年（二手）；Q2 2026 Client 年增 23%（公司） | I84: 第二來源：未找到
A85: g_gam | B85: Gaming（主機半客製＋顯示卡）年增（FY2027 起） | C85: % | D85: -0.25 | E85: -0.1 | F85: 0.1 | G85: Assumed | H85: 公司：2026 半客製營收大幅雙位數下滑（Q4 2025 法說，二手）；Q2 2026 Gaming 年減 31%（公司） | I85: 下一代主機時程：未找到
A86: g_emb | B86: Embedded 年增（FY2027 起） | C86: % | D86: 0 | E86: 0.1 | F86: 0.15 | G86: Assumed | H86: 公司：Q2 2026 年增 19%、Q3 強勁雙位數季增；今年設計案逾 $18B（二手） | I86: —
A87: F. FY2026 錨點假設（Q1、Q2 實績＋Q3 指引＋Q4 假設）
A88: q3_rev | B88: Q3 2026 營收指引（±$0.3B） | C88: US$B | D88: 12.7 | E88: 13 | F88: 13.3 | G88: Interested-party | H88: https://www.sec.gov/Archives/edgar/data/2488/000000248826000121/q22026991.htm：約 $13B ±$300M | I88: MarketBeat、platformaeronaut 摘要（二手）
A89: q3_gm | B89: Q3 2026 non-GAAP 毛利率指引 | C89: % | E89: 0.56 | G89: Interested-party | H89: https://www.sec.gov/Archives/edgar/data/2488/000000248826000121/q22026991.htm：約 56% | I89: Q2 2026 簡報（同一公司文件）
A90: q3_opx | B90: Q3 2026 non-GAAP 營業費用指引 | C90: US$B | E90: 3.65 | G90: Interested-party | H90: https://www.sec.gov/Archives/edgar/data/2488/000000248826000121/amdq22026earningsslidesf.htm：約 $3.65B | I90: platformaeronaut 摘要（二手）
A91: q3_oth | B91: Q3 2026 non-GAAP 其他收益（扣利息費用）指引 | C91: US$B | E91: 0.055 | G91: Interested-party | H91: https://www.sec.gov/Archives/edgar/data/2488/000000248826000121/amdq22026earningsslidesf.htm：約 $55M | I91: —
A92: tx_26 | B92: FY2026 non-GAAP 有效稅率 | C92: % | E92: 0.13 | G92: Interested-party | H92: https://www.sec.gov/Archives/edgar/data/2488/000000248826000121/amdq22026earningsslidesf.htm：13% | I92: Q1–Q2 實績推得約 13.0%（Q 頁）
A93: q3_sh | B93: Q3 2026 稀釋股數指引 | C93: 十億股 | E93: 1.661 | G93: Interested-party | H93: https://www.sec.gov/Archives/edgar/data/2488/000000248826000121/amdq22026earningsslidesf.htm：約 1,661M | I93: —
A94: q3_cli | B94: Q3 2026 Client 季增（假設） | C94: % | D94: 0 | E94: 0.02 | F94: 0.05 | G94: Assumed | H94: 公司：Client 與 Gaming 合計小幅季減；Client 略增、Gaming 強勁雙位數下滑（法說摘要，二手） | I94: —
A95: q3_gam | B95: Q3 2026 Gaming 季增（假設） | C95: % | D95: -0.3 | E95: -0.2 | F95: -0.1 | G95: Assumed | H95: 同上 | I95: —
A96: q3_emb | B96: Q3 2026 Embedded 季增（假設） | C96: % | D96: 0.08 | E96: 0.12 | F96: 0.16 | G96: Assumed | H96: 公司：強勁雙位數季增（二手） | I96: —
A97: q4_dc | B97: Q4 2026 資料中心季增（假設） | C97: % | D97: 0.1 | E97: 0.25 | F97: 0.4 | G97: Assumed | H97: 公司：Helios 第三季底開始出貨、第四季放量（Q2 2026 法說摘要，二手）；MI450 第四季有顯著量（Q4 2025 法說） | I97: 共識 FY2026 營收 $51.0B 隱含 Q4 約 $16.2B（只作對照，不校準）
A98: q4_cli | B98: Q4 2026 Client 季增（假設） | C98: % | D98: -0.1 | E98: -0.05 | F98: 0.02 | G98: Assumed | H98: 公司：下半年季節性低於上半年（二手） | I98: —
A99: q4_gam | B99: Q4 2026 Gaming 季增（假設） | C99: % | D99: -0.2 | E99: -0.1 | F99: 0.1 | G99: Assumed | H99: 無 | I99: —
A100: q4_emb | B100: Q4 2026 Embedded 季增（假設） | C100: % | D100: 0 | E100: 0.03 | F100: 0.08 | G100: Assumed | H100: 無 | I100: —
A101: q4_gm | B101: Q4 2026 non-GAAP 毛利率（假設） | C101: % | D101: 0.54 | E101: 0.555 | F101: 0.57 | G101: Assumed | H101: 公司：資料中心 AI 毛利率低於平均，MI450 放量季組合偏低（二手） | I101: 高＝Q3 指引附近
A102: q4_opx_g | B102: Q4 2026 營業費用季增（假設） | C102: % | D102: 0.02 | E102: 0.05 | F102: 0.08 | G102: Assumed | H102: Q1→Q2 +7.9%、Q2→Q3 指引 +7.5%（公司）；下半年費用成長落後營收（公司，二手） | I102: —
A103: q4_sh | B103: Q4 2026 稀釋股數季變動 | C103: % | D103: 0 | E103: 0.002 | F103: 0.01 | G103: Assumed | H103: Q1→Q2 +0.5%（公司） | I103: 認股權證的稀釋另計（G 節）
A104: G. 營業費用、稅、股數、認股權證（FY2027 起）
A105: phi | B105: 營業費用成長對營收成長的彈性 | C105: x | D105: 0.5 | E105: =Q!B36 -> 0.80480984 | F105: 0.9 | G105: Derived | H105: FY2026 錨點營業費用年增 ÷ 營收年增（Q 頁） | I105: 低／高 Assumed；公司：費用成長低於營收成長（二手）
A106: g_opx_min | B106: 營業費用年增下限 | C106: % | D106: 0 | E106: 0.05 | F106: 0.1 | G106: Assumed | H106: 無 | I106: 營收下滑時費用僵固
A107: opx_adj | B107: 營業費用額外占營收比（Sens 用；基準為 0） | C107: pt | D107: -0.02 | E107: 0 | F107: 0.02 | G107: Assumed | H107: 無 | I107: Sens 用 ±2 個百分點
A108: tx_f | B108: non-GAAP 有效稅率（FY2027 起） | C108: % | D108: 0.12 | E108: 0.13 | F108: 0.15 | G108: Interested-party | H108: 公司 FY2026 13%；FY2025 推得 13.0%（Q 頁） | I108: —
A109: oth_f | B109: non-GAAP 其他收益淨額（扣利息；FY2027 起每年） | C109: US$B | D109: 0 | E109: 0.2 | F109: 0.4 | G109: Assumed | H109: Q3 2026 指引 $55M／季（公司）；Q1–Q2 2026 推得 0.06、0.08（Q 頁） | I109: —
A110: sh_g | B110: 稀釋股數年變動（不含認股權證；FY2027 起） | C110: % | D110: -0.005 | E110: 0.01 | F110: 0.015 | G110: Derived | H110: FY2025 1.636 → Q2 2026 1.659（年化約 +1.4%，公司）；2026 上半年買回僅 $0.22B（公司 10-Q） | I110: 低／高 Assumed
A111: w_tot | B111: 客戶認股權證上限：OpenAI 160M ＋ Meta 160M 股 | C111: 十億股 | E111: 0.32 | G111: Verified | H111: 公司 2025-10-06 OpenAI 新聞稿；2026-02-24 Meta 新聞稿（8-K EX-99.1） | I111: 依 GW 出貨里程碑與股價門檻分批歸屬；各批股數：未找到
A112: w_gw | B112: 認股權證對應的 GW 合計（OpenAI 6＋Meta 6） | C112: GW | E112: 12 | G112: Verified | H112: 同上 | I112: —
A113: gw_26 | B113: 已歸屬 GW 累計：2026 年底 | C113: GW | D113: 0 | E113: 0 | F113: 1 | G113: Assumed | H113: 首批隨首個 1 GW 歸屬；兩案首 1 GW 皆 2026 下半年開始出貨（公司） | I113: 歸屬時點：未找到
A114: gw_27 | B114: 已歸屬 GW 累計：2027 年底 | C114: GW | D114: 1 | E114: 2 | F114: 3 | G114: Assumed | H114: 假設兩案各完成 1 GW | I114: 股價門檻（OpenAI 最後一批 $600，媒體報導，二手）未模型化
A115: gw_28 | B115: 已歸屬 GW 累計：2028 年底（情境 B、C 乘顆數係數） | C115: GW | D115: 2 | E115: 4 | F115: 6 | G115: Assumed | H115: 無 | I115: —
A116: gw_29 | B116: 已歸屬 GW 累計：2029 年底（情境 B、C 乘顆數係數） | C116: GW | D116: 4 | E116: 6 | F116: 9 | G116: Assumed | H116: 無 | I116: —
A117: wf | B117: 認股權證歸屬速度係數（Sens 用） | C117: x | D117: 0 | E117: 1 | F117: 1.5 | G117: Assumed | H117: 0＝不歸屬（股價門檻或里程碑未達） | I117: —
A118: H. 公司指引、大單與共識（只作 Recon 對帳，不作校準）
A119: g_dc27 | B119: 公司：2027 資料中心營收年增（逾一倍） | C119: % | E119: 1 | G119: Interested-party | H119: Q2 2026 法說（MarketBeat、platformaeronaut 摘要，二手） | I119: 逐字稿未取得
A120: g_srv27 | B120: 公司：2027 伺服器 CPU 年增（逾 70%） | C120: % | E120: 0.7 | G120: Interested-party | H120: 同上 | I120: 下半年 2026 逾 80%
A121: lt_eps | B121: 公司：策略期間 EPS 逾 $20（Q2 2026 稱將顯著超過） | C121: US$ | E121: 20 | G121: Interested-party | H121: 2025-11 分析師日（Q4 2025 法說重述，Motley Fool 逐字稿） | I121: 營收年複合成長逾 35%、資料中心逾 60%
A122: openai_gw | B122: OpenAI：6 GW（首 1 GW MI450 於 2026 下半年）；CFO：數百億美元營收 | C122: GW | E122: 6 | G122: Interested-party | H122: AMD 2025-10-06 新聞稿（ir.amd.com） | I122: OpenAI 為交易對手（立場：取得認股權證）
A123: meta_gw | B123: Meta：最多 6 GW（首 1 GW 客製 MI450，2026 下半年出貨） | C123: GW | E123: 6 | G123: Interested-party | H123: AMD 2026-02-24 新聞稿（8-K EX-99.1） | I123: —
A124: anth_gw | B124: Anthropic：最多 2 GW MI450（首 1 GW 自 2027 上半年） | C124: GW | E124: 2 | G124: Interested-party | H124: https://www.sec.gov/Archives/edgar/data/2488/000000248826000121/q22026991.htm；MarketBeat 摘要 | I124: —
A125: orcl_u | B125: Oracle：首批 5 萬顆 MI450（2026 第三季起，2027 起擴大） | C125: 百萬顆 | E125: 0.05 | G125: Interested-party | H125: Oracle 2025-10-14 新聞稿（oracle.com） | I125: Oracle 為交易對手
A126: gpw | B126: 每 GW GPU 數（VR200 NVL72；Helios 每架 72 顆的 Analogy） | C126: 顆 | E126: 291744 | G126: Analogy | H126: markets/chip_bridge/dist/20261023_晶片內容橋接表_v0.2.1.xlsx｜In!H7（VR200 每 GW GPU 數，Tokenomics IF_GPUsPerGW） | I126: MI450 每 GW 顆數：未找到
A127: p355 | B127: MI355X 每顆售價（HSBC） | C127: US$K | D127: 20 | E127: 23 | F127: 25 | G127: Interested-party | H127: HSBC 約 $23K（自 $25K 下修；finviz 轉述） | I127: 其他報導 $20–25K
A128: cons_rev26 | B128: 共識 FY2026 營收（S&P Global，48 位） | C128: US$B | D128: 48.3 | E128: 51 | F128: 52.7 | G128: Interested-party | H128: stockanalysis.com（2026-10-23） | I128: 另一來源 tickflow（2026-10-24）47.15，可能較舊
...

Sheet Q
A1: Q — 實績（十億美元；EPS 為美元；股數為十億股；non-GAAP 公司口徑）。會計年度＝日曆年。藍字＝輸入；黑字＝公式。實績取自 AMD 8-K 新聞稿（sec.gov）；第二來源＝後續季度新聞稿的比較欄（同一公司不同文件）與 10-Q
A2: FY2026 錨點＝Q1、Q2 實績＋Q3 指引中點＋Q4 假設（I、J 欄，假設見 In 頁 F 節）。資料中心 GPU／非 GPU 拆分公司不揭露，為 Assumed（In 頁 D 節）。EPS 口徑：non-GAAP（排除股票薪酬、併購無形資產攤銷、投資損益等；公司口徑），共識亦為此口徑
A3: 項目 | B3: Q1 2025 | C3: Q2 2025 | D3: Q3 2025 | E3: Q4 2025 | F3: FY2025 全年 | G3: Q1 2026 | H3: Q2 2026 | I3: Q3 2026（指引中點） | J3: Q4 2026（假設） | K3: FY2026 錨點 | L3: 標記 | M3: 來源1（公司） | N3: 來源2／說明
A4: 營收 | B4: 7.438 | C4: 7.685 | D4: 9.246 | E4: 10.27 | F4: =SUM(B4:E4) -> 34.639 | G4: 10.253 | H4: 11.536 | I4: =q3_rev -> 13 | J4: =J5+J8+J9+J10 -> 14.854175 | K4: =SUM(G4:J4) -> 49.643175 | L4: Verified／Interested-party（Q3 指引）／Derived（Q4＝各段合計） | M4: AMD 8-K 新聞稿：Q1 2026 https://www.sec.gov/Archives/edgar/data/2488/000000248826000072/q12026991.htm；Q2 2026 https://www.sec.gov/Archives/edgar/data/2488/000000248826000121/q22026991.htm；Q4 2025（含 Q3 2025、全年）https://www.sec.gov/Archives/edgar/data/2488/000000248826000014/q42025991.htm | N4: Q1、Q2 2025 見 Q1、Q2 2026 稿比較欄；Q2 2025 毛利、利息、其他收益為全年 − 其餘三季（Derived）
A5: Data Center | B5: 3.674 | C5: 3.24 | D5: 4.341 | E5: 5.38 | F5: =SUM(B5:E5) -> 16.635 | G5: 5.775 | H5: 6.718 | I5: =I4-I8-I9-I10 -> 8.15932 | J5: =I5*(1+q4_dc) -> 10.19915 | K5: =SUM(G5:J5) -> 30.85147 | L5: Verified／Derived（Q3＝指引 − 其他段）／Assumed（Q4） | M5: AMD 8-K 新聞稿：Q1 2026 https://www.sec.gov/Archives/edgar/data/2488/000000248826000072/q12026991.htm；Q2 2026 https://www.sec.gov/Archives/edgar/data/2488/000000248826000121/q22026991.htm；Q4 2025（含 Q3 2025、全年）https://www.sec.gov/Archives/edgar/data/2488/000000248826000014/q42025991.htm | N5: Q1、Q2 2025 見 Q1、Q2 2026 稿比較欄；Q2 2025 毛利、利息、其他收益為全年 − 其餘三季（Derived）；FY2025 合計 16.635＝公司全年值
A6: 其中：資料中心 GPU（Instinct；Assumed 拆分） | F6: =gpu25 -> 6.5 | G6: =G5*gs_q1 -> 2.4255 | H6: =H5*gs_q2 -> 2.88874 | I6: =I5-I7 -> 4.0237192 | J6: =J5-J7 -> 5.8154132 | K6: =SUM(G6:J6) -> 15.153372 | L6: Assumed／Derived | M6: 公司不揭露 GPU 與 CPU 拆分；FY2025 為全年估計（In 頁 gpu25），各季：未找到 | N6: Q3、Q4＝資料中心 − 非 GPU
A7: 其中：資料中心非 GPU（EPYC CPU、DPU、FPGA 等） | F7: =F5-F6 -> 10.135 | G7: =G5-G6 -> 3.3495 | H7: =H5-H6 -> 3.82926 | I7: =H7*(1+ng_q3) -> 4.1356008 | J7: =I7*(1+ng_q4) -> 4.3837368 | K7: =SUM(G7:J7) -> 15.698098 | L7: Derived／Assumed（Q3、Q4 季增） | M7: 資料中心 − GPU | N7: —
A8: Client | B8: 2.294 | C8: 2.499 | D8: 2.75 | E8: 3.097 | F8: =SUM(B8:E8) -> 10.64 | G8: 2.885 | H8: 3.062 | I8: =H8*(1+q3_cli) -> 3.12324 | J8: =I8*(1+q4_cli) -> 2.967078 | K8: =SUM(G8:J8) -> 12.037318 | L8: Verified／Assumed（I、J） | M8: AMD 8-K 新聞稿：Q1 2026 https://www.sec.gov/Archives/edgar/data/2488/000000248826000072/q12026991.htm；Q2 2026 https://www.sec.gov/Archives/edgar/data/2488/000000248826000121/q22026991.htm；Q4 2025（含 Q3 2025、全年）https://www.sec.gov/Archives/edgar/data/2488/000000248826000014/q42025991.htm | N8: Q1、Q2 2025 見 Q1、Q2 2026 稿比較欄；Q2 2025 毛利、利息、其他收益為全年 − 其餘三季（Derived）
A9: Gaming | B9: 0.647 | C9: 1.122 | D9: 1.298 | E9: 0.843 | F9: =SUM(B9:E9) -> 3.91 | G9: 0.72 | H9: 0.779 | I9: =H9*(1+q3_gam) -> 0.6232 | J9: =I9*(1+q4_gam) -> 0.56088 | K9: =SUM(G9:J9) -> 2.68308 | L9: Verified／Assumed（I、J） | M9: AMD 8-K 新聞稿：Q1 2026 https://www.sec.gov/Archives/edgar/data/2488/000000248826000072/q12026991.htm；Q2 2026 https://www.sec.gov/Archives/edgar/data/2488/000000248826000121/q22026991.htm；Q4 2025（含 Q3 2025、全年）https://www.sec.gov/Archives/edgar/data/2488/000000248826000014/q42025991.htm | N9: Q1、Q2 2025 見 Q1、Q2 2026 稿比較欄；Q2 2025 毛利、利息、其他收益為全年 − 其餘三季（Derived）
A10: Embedded | B10: 0.823 | C10: 0.824 | D10: 0.857 | E10: 0.95 | F10: =SUM(B10:E10) -> 3.454 | G10: 0.873 | H10: 0.977 | I10: =H10*(1+q3_emb) -> 1.09424 | J10: =I10*(1+q4_emb) -> 1.1270672 | K10: =SUM(G10:J10) -> 4.0713072 | L10: Verified／Assumed（I、J） | M10: AMD 8-K 新聞稿：Q1 2026 https://www.sec.gov/Archives/edgar/data/2488/000000248826000072/q12026991.htm；Q2 2026 https://www.sec.gov/Archives/edgar/data/2488/000000248826000121/q22026991.htm；Q4 2025（含 Q3 2025、全年）https://www.sec.gov/Archives/edgar/data/2488/000000248826000014/q42025991.htm | N10: Q1、Q2 2025 見 Q1、Q2 2026 稿比較欄；Q2 2025 毛利、利息、其他收益為全年 − 其餘三季（Derived）
A11: 檢查：營收 − 各段合計（應為 0） | B11: =B4-B5-B8-B9-B10 -> 0 | C11: =C4-C5-C8-C9-C10 -> 0 | D11: =D4-D5-D8-D9-D10 -> 0 | E11: =E4-E5-E8-E9-E10 -> 0 | F11: =F4-F5-F8-F9-F10 -> 0 | G11: =G4-G5-G8-G9-G10 -> 0 | H11: =H4-H5-H8-H9-H10 -> 0 | I11: =I4-I5-I8-I9-I10 -> 0 | ... K11: =K4-K5-K8-K9-K10 -> 0 | L11: — | M11: — | N11: —
A12: 毛利（non-GAAP） | B12: 3.992 | C12: 3.326 | D12: 4.992 | E12: 5.855 | F12: =SUM(B12:E12) -> 18.165 | G12: 5.685 | H12: 6.488 | I12: =I4*q3_gm -> 7.28 | J12: =J4*q4_gm -> 8.2440672 | K12: =SUM(G12:J12) -> 27.697067 | L12: Verified（Q2 2025 Derived；Q2 2026＝營業利益＋營業費用）／Interested-party（I）／Assumed（J） | M12: AMD 8-K 新聞稿：Q1 2026 https://www.sec.gov/Archives/edgar/data/2488/000000248826000072/q12026991.htm；Q2 2026 https://www.sec.gov/Archives/edgar/data/2488/000000248826000121/q22026991.htm；Q4 2025（含 Q3 2025、全年）https://www.sec.gov/Archives/edgar/data/2488/000000248826000014/q42025991.htm | N12: FY2025 合計 18.165＝公司全年值
A13: 毛利率（non-GAAP） | B13: =B12/B4 -> 0.53670341 | C13: =C12/C4 -> 0.43279115 | D13: =D12/D4 -> 0.53990915 | E13: =E12/E4 -> 0.57010711 | F13: =F12/F4 -> 0.5244089 | G13: =G12/G4 -> 0.55447186 | H13: =H12/H4 -> 0.56241331 | I13: =I12/I4 -> 0.56 | ... K13: =K12/K4 -> 0.55792296 | L13: Derived | M13: — | N13: 公司：Q2 2025 43%（含 MI308 費用 $0.8B）、FY2025 52%、Q2 2026 56%
A14: 營業費用（non-GAAP） | B14: 2.213 | C14: 2.429 | D14: 2.754 | E14: 3.001 | F14: =SUM(B14:E14) -> 10.397 | G14: 3.145 | H14: 3.394 | I14: =q3_opx -> 3.65 | J14: =I14*(1+q4_opx_g) -> 3.8325 | K14: =SUM(G14:J14) -> 14.0215 | L14: Verified／Interested-party（I）／Assumed（J） | M14: AMD 8-K 新聞稿：Q1 2026 https://www.sec.gov/Archives/edgar/data/2488/000000248826000072/q12026991.htm；Q2 2026 https://www.sec.gov/Archives/edgar/data/2488/000000248826000121/q22026991.htm；Q4 2025（含 Q3 2025、全年）https://www.sec.gov/Archives/edgar/data/2488/000000248826000014/q42025991.htm | N14: Q1、Q2 2025 見 Q1、Q2 2026 稿比較欄；Q2 2025 毛利、利息、其他收益為全年 − 其餘三季（Derived）
A15: 營業利益（non-GAAP） | B15: 1.779 | C15: 0.897 | D15: 2.238 | E15: 2.854 | F15: =SUM(B15:E15) -> 7.768 | G15: 2.54 | H15: 3.094 | I15: =I12-I14 -> 3.63 | J15: =J12-J14 -> 4.4115672 | K15: =SUM(G15:J15) -> 13.675567 | L15: Verified／Derived（I、J） | M15: AMD 8-K 新聞稿：Q1 2026 https://www.sec.gov/Archives/edgar/data/2488/000000248826000072/q12026991.htm；Q2 2026 https://www.sec.gov/Archives/edgar/data/2488/000000248826000121/q22026991.htm；Q4 2025（含 Q3 2025、全年）https://www.sec.gov/Archives/edgar/data/2488/000000248826000014/q42025991.htm | N15: Q1、Q2 2025 見 Q1、Q2 2026 稿比較欄；Q2 2025 毛利、利息、其他收益為全年 − 其餘三季（Derived）
A16: 檢查：毛利 − 營業費用 − 營業利益（實績應為 0） | B16: =B12-B14-B15 -> 0 | C16: =C12-C14-C15 -> 0 | D16: =D12-D14-D15 -> 0 | E16: =E12-E14-E15 -> 0 | G16: =G12-G14-G15 -> 0 | H16: =H12-H14-H15 -> 0 | L16: — | M16: — | N16: —
A17: 利息費用 | B17: -0.02 | C17: -0.038 | D17: -0.037 | E17: -0.036 | F17: =SUM(B17:E17) -> -0.131 | G17: -0.037 | H17: -0.037 | L17: Verified（Q2 2025 Derived） | M17: AMD 8-K 新聞稿：Q1 2026 https://www.sec.gov/Archives/edgar/data/2488/000000248826000072/q12026991.htm；Q2 2026 https://www.sec.gov/Archives/edgar/data/2488/000000248826000121/q22026991.htm；Q4 2025（含 Q3 2025、全年）https://www.sec.gov/Archives/edgar/data/2488/000000248826000014/q42025991.htm | N17: Q1、Q2 2025 見 Q1、Q2 2026 稿比較欄；Q2 2025 毛利、利息、其他收益為全年 − 其餘三季（Derived）
A18: 其他收益淨額（GAAP） | B18: 0.039 | C18: 0.098 | D18: 0.082 | E18: 0.358 | F18: =SUM(B18:E18) -> 0.577 | G18: 0.165 | H18: 0.598 | L18: Verified（Q2 2025 Derived） | M18: AMD 8-K 新聞稿：Q1 2026 https://www.sec.gov/Archives/edgar/data/2488/000000248826000072/q12026991.htm；Q2 2026 https://www.sec.gov/Archives/edgar/data/2488/000000248826000121/q22026991.htm；Q4 2025（含 Q3 2025、全年）https://www.sec.gov/Archives/edgar/data/2488/000000248826000014/q42025991.htm | N18: Q1、Q2 2025 見 Q1、Q2 2026 稿比較欄；Q2 2025 毛利、利息、其他收益為全年 − 其餘三季（Derived）
A19: 長期投資（利得）損失（non-GAAP 調節，排除） | B19: 0.002 | C19: -0.061 | D19: -0.026 | E19: -0.28 | F19: =SUM(B19:E19) -> -0.365 | G19: -0.066 | H19: -0.483 | L19: Verified（Q2 2025 Derived） | M19: AMD 8-K 新聞稿：Q1 2026 https://www.sec.gov/Archives/edgar/data/2488/000000248826000072/q12026991.htm；Q2 2026 https://www.sec.gov/Archives/edgar/data/2488/000000248826000121/q22026991.htm；Q4 2025（含 Q3 2025、全年）https://www.sec.gov/Archives/edgar/data/2488/000000248826000014/q42025991.htm | N19: non-GAAP 調節表「(Gains) losses on long-term investments, net」
A20: 非營業淨額（non-GAAP）＝利息＋其他收益＋調節 | B20: =B17+B18+B19 -> 0.021 | C20: =C17+C18+C19 -> -0.001 | D20: =D17+D18+D19 -> 0.019 | E20: =E17+E18+E19 -> 0.042 | F20: =SUM(B20:E20) -> 0.081 | G20: =G17+G18+G19 -> 0.062 | H20: =H17+H18+H19 -> 0.078 | I20: =q3_oth -> 0.055 | J20: =q3_oth -> 0.055 | K20: =SUM(G20:J20) -> 0.25 | L20: Derived／Interested-party（I）／Assumed（J＝Q3 指引） | M20: AMD 8-K 新聞稿：Q1 2026 https://www.sec.gov/Archives/edgar/data/2488/000000248826000072/q12026991.htm；Q2 2026 https://www.sec.gov/Archives/edgar/data/2488/000000248826000121/q22026991.htm；Q4 2025（含 Q3 2025、全年）https://www.sec.gov/Archives/edgar/data/2488/000000248826000014/q42025991.htm | N20: Q1、Q2 2025 見 Q1、Q2 2026 稿比較欄；Q2 2025 毛利、利息、其他收益為全年 − 其餘三季（Derived）
A21: 稅前利益（non-GAAP） | B21: =B15+B20 -> 1.8 | C21: =C15+C20 -> 0.896 | D21: =D15+D20 -> 2.257 | E21: =E15+E20 -> 2.896 | F21: =SUM(B21:E21) -> 7.849 | G21: =G15+G20 -> 2.602 | H21: =H15+H20 -> 3.172 | I21: =I15+I20 -> 3.685 | J21: =J15+J20 -> 4.4665672 | K21: =SUM(G21:J21) -> 13.925567 | L21: Derived | M21: AMD 8-K 新聞稿：Q1 2026 https://www.sec.gov/Archives/edgar/data/2488/000000248826000072/q12026991.htm；Q2 2026 https://www.sec.gov/Archives/edgar/data/2488/000000248826000121/q22026991.htm；Q4 2025（含 Q3 2025、全年）https://www.sec.gov/Archives/edgar/data/2488/000000248826000014/q42025991.htm | N21: Q1、Q2 2025 見 Q1、Q2 2026 稿比較欄；Q2 2025 毛利、利息、其他收益為全年 − 其餘三季（Derived）
A22: 淨利（non-GAAP） | B22: 1.566 | C22: 0.781 | D22: 1.965 | E22: 2.519 | F22: =SUM(B22:E22) -> 6.831 | G22: 2.265 | H22: 2.76 | I22: =I21*(1-tx_26) -> 3.20595 | J22: =J21*(1-tx_26) -> 3.8859135 | K22: =SUM(G22:J22) -> 12.116863 | L22: Verified／Derived（I、J） | M22: AMD 8-K 新聞稿：Q1 2026 https://www.sec.gov/Archives/edgar/data/2488/000000248826000072/q12026991.htm；Q2 2026 https://www.sec.gov/Archives/edgar/data/2488/000000248826000121/q22026991.htm；Q4 2025（含 Q3 2025、全年）https://www.sec.gov/Archives/edgar/data/2488/000000248826000014/q42025991.htm | N22: Q1、Q2 2025 見 Q1、Q2 2026 稿比較欄；Q2 2025 毛利、利息、其他收益為全年 − 其餘三季（Derived）；FY2025 合計 6.831＝公司全年值
A23: 有效稅率（non-GAAP；1 − 淨利 ÷ 稅前） | B23: =1-B22/B21 -> 0.13 | C23: =1-C22/C21 -> 0.12834821 | D23: =1-D22/D21 -> 0.12937528 | E23: =1-E22/E21 -> 0.13017956 | F23: =1-F22/F21 -> 0.12969805 | G23: =1-G22/G21 -> 0.12951576 | H23: =1-H22/H21 -> 0.12988651 | I23: =tx_26 -> 0.13 | J23: =tx_26 -> 0.13 | K23: =1-K22/K21 -> 0.12988367 | L23: Derived／Interested-party（13%） | M23: — | N23: 公司 FY2026 non-GAAP 稅率 13%（Q2 2026 簡報）
A24: 稀釋股數（十億股） | B24: 1.626 | C24: 1.63 | D24: 1.641 | E24: 1.649 | F24: 1.636 | G24: 1.65 | H24: 1.659 | I24: =q3_sh -> 1.661 | J24: =I24*(1+q4_sh) -> 1.664322 | K24: =AVERAGE(G24:J24) -> 1.6585805 | L24: Verified／Interested-party（I）／Assumed（J） | M24: AMD 8-K 新聞稿：Q1 2026 https://www.sec.gov/Archives/edgar/data/2488/000000248826000072/q12026991.htm；Q2 2026 https://www.sec.gov/Archives/edgar/data/2488/000000248826000121/q22026991.htm；Q4 2025（含 Q3 2025、全年）https://www.sec.gov/Archives/edgar/data/2488/000000248826000014/q42025991.htm | N24: Q2 2025 1.630 見 Q2 2026 10-Q；FY2025 1.636（公司全年值）
A25: EPS（non-GAAP，模型算）＝淨利 ÷ 股數 | B25: =B22/B24 -> 0.96309963 | C25: =C22/C24 -> 0.4791411 | D25: =D22/D24 -> 1.1974406 | E25: =E22/E24 -> 1.5275925 | F25: =F22/F24 -> 4.1754279 | G25: =G22/G24 -> 1.3727273 | H25: =H22/H24 -> 1.6636528 | I25: =I22/I24 -> 1.9301325 | ... K25: =K22/K24 -> 7.3055625 | L25: Derived | M25: — | N25: FY2026 Q3、Q4 為指引與假設推得
A26: EPS（non-GAAP 稀釋，公司） | B26: 0.96 | C26: 0.48 | D26: 1.2 | E26: 1.53 | F26: 4.17 | G26: 1.37 | H26: 1.66 | L26: Verified | M26: AMD 8-K 新聞稿：Q1 2026 https://www.sec.gov/Archives/edgar/data/2488/000000248826000072/q12026991.htm；Q2 2026 https://www.sec.gov/Archives/edgar/data/2488/000000248826000121/q22026991.htm；Q4 2025（含 Q3 2025、全年）https://www.sec.gov/Archives/edgar/data/2488/000000248826000014/q42025991.htm | N26: Q1、Q2 2025 見 Q1、Q2 2026 稿比較欄；Q2 2025 毛利、利息、其他收益為全年 − 其餘三季（Derived）
A27: 檢查：模型算 EPS − 公司 EPS（四捨五入差） | B27: =B25-B26 -> 0.003099631 | C27: =C25-C26 -> -0.00085889571 | D27: =D25-D26 -> -0.002559415 | E27: =E25-E26 -> -0.0024075197 | F27: =F25-F26 -> 0.0054278729 | G27: =G25-G26 -> 0.0027272727 | H27: =H25-H26 -> 0.0036528029 | L27: — | M27: — | N27: —
A28: EPS（GAAP 稀釋，公司；參考） | B28: 0.44 | C28: 0.54 | D28: 0.75 | E28: 0.92 | F28: 2.65 | G28: 0.84 | H28: 1.38 | L28: Verified | M28: AMD 8-K 新聞稿：Q1 2026 https://www.sec.gov/Archives/edgar/data/2488/000000248826000072/q12026991.htm；Q2 2026 https://www.sec.gov/Archives/edgar/data/2488/000000248826000121/q22026991.htm；Q4 2025（含 Q3 2025、全年）https://www.sec.gov/Archives/edgar/data/2488/000000248826000014/q42025991.htm | N28: GAAP 含併購無形資產攤銷（FY2025 $2.25B）、股票薪酬（$1.64B）
A29: 檢查：FY2025 四季合計 − 公司全年值（營收 34.639、營業利益 7.768、淨利 6.831，應為 0） | F29: =(F4-34.639)+(F15-7.768)+(F22-6.831) -> 0 | L29: — | M29: — | N29: —
A31: FY2026 錨點與共識的距離（參考；校準時未使用共識）
A32: FY2026 營收 ÷ 共識營收 − 1 | B32: =K4/cons_rev26-1 -> -0.026604408
A33: FY2026 EPS ÷ 共識 EPS − 1 | B33: =K25/cons_eps26-1 -> -0.037475297
A34: FY2026 營收年增 | B34: =K4/F4-1 -> 0.43315844
A35: FY2026 營業費用年增 | B35: =K14/F14-1 -> 0.34861018
A36: 營業費用彈性（營業費用年增 ÷ 營收年增；In 頁 phi 的依據） | B36: =B35/B34 -> 0.80480984

Sheet Units
A1: Units — 加速器顆數（百萬顆；日曆年；與 HBM、台積電、網通、NVIDIA 模型同一份）與金額份額（模組層級每顆價 × 顆數；價格與 NVIDIA 模型相同）。AMD 會計年度＝日曆年
A3: 項目 | B3: 單位 | C3: CY2026（FY2026） | D3: CY2027（FY2027） | E3: CY2028（FY2028） | F3: CY2029（FY2029） | G3: 說明
A4: 情境 A：基準
A5: 顆數
A6: NVIDIA Blackwell（B200／B300） | B6: 百萬顆 | C6: =u_bw_26 -> 5.4 | D6: =u_bw_27 -> 2.4 | E6: =u_bw_28*um28_A -> 0.5 | F6: =u_bw_28*(1+g29_bw)*um29_A -> 0.25
A7: NVIDIA Rubin | B7: 百萬顆 | C7: =u_rb_26 -> 1.7 | D7: =u_rb_27 -> 7 | E7: =u_rb_28*um28_A -> 7 | F7: =u_rb_28*(1+g29_rb)*um29_A -> 8.05
A8: NVIDIA Rubin Ultra | B8: 百萬顆 | C8: =u_ru_26 -> 0 | D8: =u_ru_27 -> 0.3 | E8: =u_ru_28*um28_A -> 2 | F8: =u_ru_28*(1+g29_ru)*um29_A -> 2.3
A9: NVIDIA Hopper（H200 等） | B9: 百萬顆 | C9: =u_hp_26 -> 0.5 | D9: =u_hp_27 -> 0 | E9: =u_hp_28*um28_A -> 0 | F9: =u_hp_28*(1+g29_hp)*um29_A -> 0
A10: AMD Instinct | B10: 百萬顆 | C10: =u_amd_26 -> 0.75 | D10: =u_amd_27 -> 1.5 | E10: =u_amd_28*um28_A -> 2 | F10: =u_amd_28*(1+g29_amd)*um29_A -> 2.3
A11: Google TPU | B11: 百萬顆 | C11: =u_tpu_26 -> 3.85 | D11: =u_tpu_27 -> 5.5 | E11: =u_tpu_28*um28_A -> 7 | F11: =u_tpu_28*(1+g29_tpu)*um29_A -> 8.05
A12: AWS Trainium | B12: 百萬顆 | C12: =u_trn_26 -> 2 | D12: =u_trn_27 -> 2.5 | E12: =u_trn_28*um28_A -> 3 | F12: =u_trn_28*(1+g29_trn)*um29_A -> 3.45
A13: 其他 ASIC（MTIA、Maia、Ascend 等） | B13: 百萬顆 | C13: =u_oth_26 -> 1 | D13: =u_oth_27 -> 4.5 | E13: =u_oth_28*um28_A -> 5 | F13: =u_oth_28*(1+g29_oth)*um29_A -> 5.75
A14: 合計 | B14: 百萬顆 | C14: =SUM(C6:C13) -> 15.2 | D14: =SUM(D6:D13) -> 23.7 | E14: =SUM(E6:E13) -> 26.5 | F14: =SUM(F6:F13) -> 30.15
A15: 金額（顆數 × 每顆售價）
A16: NVIDIA Blackwell（B200／B300） | B16: US$B | C16: =u_bw_26*(pm_bw) -> 218.16 | D16: =u_bw_27*(pm_bw) -> 96.96 | E16: =u_bw_28*um28_A*(pm_bw) -> 20.2 | F16: =u_bw_28*(1+g29_bw)*um29_A*(pm_bw) -> 10.1
A17: NVIDIA Rubin | B17: US$B | C17: =u_rb_26*(pm_rb) -> 93.5 | D17: =u_rb_27*(pm_rb) -> 385 | E17: =u_rb_28*um28_A*(pm_rb) -> 385 | F17: =u_rb_28*(1+g29_rb)*um29_A*(pm_rb) -> 442.75
A18: NVIDIA Rubin Ultra | B18: US$B | C18: =u_ru_26*(pm_ru) -> 0 | D18: =u_ru_27*(pm_ru) -> 22.5 | E18: =u_ru_28*um28_A*(pm_ru) -> 150 | F18: =u_ru_28*(1+g29_ru)*um29_A*(pm_ru) -> 172.5
A19: NVIDIA Hopper（H200 等） | B19: US$B | C19: =u_hp_26*(pm_hp) -> 15 | D19: =u_hp_27*(pm_hp) -> 0 | E19: =u_hp_28*um28_A*(pm_hp) -> 0 | F19: =u_hp_28*(1+g29_hp)*um29_A*(pm_hp) -> 0
A20: AMD Instinct | B20: US$B | C20: =u_amd_26*(pa_amd) -> 22.5 | D20: =u_amd_27*(pa_amd) -> 45 | E20: =u_amd_28*um28_A*(pa_amd) -> 60 | F20: =u_amd_28*(1+g29_amd)*um29_A*(pa_amd) -> 69
A21: Google TPU | B21: US$B | C21: =u_tpu_26*(pa_tpu) -> 46.2 | D21: =u_tpu_27*(pa_tpu) -> 66 | E21: =u_tpu_28*um28_A*(pa_tpu) -> 84 | F21: =u_tpu_28*(1+g29_tpu)*um29_A*(pa_tpu) -> 96.6
A22: AWS Trainium | B22: US$B | C22: =u_trn_26*(pa_trn) -> 16 | D22: =u_trn_27*(pa_trn) -> 20 | E22: =u_trn_28*um28_A*(pa_trn) -> 24 | F22: =u_trn_28*(1+g29_trn)*um29_A*(pa_trn) -> 27.6
A23: 其他 ASIC（MTIA、Maia、Ascend 等） | B23: US$B | C23: =u_oth_26*(pa_oth) -> 8 | D23: =u_oth_27*(pa_oth) -> 36 | E23: =u_oth_28*um28_A*(pa_oth) -> 40 | F23: =u_oth_28*(1+g29_oth)*um29_A*(pa_oth) -> 46
A24: 合計 | B24: US$B | C24: =SUM(C16:C23) -> 419.36 | D24: =SUM(D16:D23) -> 671.46 | E24: =SUM(E16:E23) -> 763.2 | F24: =SUM(F16:F23) -> 864.55
A25: 顆數份額
A26: NVIDIA | B26: % | C26: =(C6+C7+C8+C9)/C14 -> 0.5 | D26: =(D6+D7+D8+D9)/D14 -> 0.4092827 | E26: =(E6+E7+E8+E9)/E14 -> 0.35849057 | F26: =(F6+F7+F8+F9)/F14 -> 0.35157546
A27: AMD | B27: % | C27: =(C10)/C14 -> 0.049342105 | D27: =(D10)/D14 -> 0.063291139 | E27: =(E10)/E14 -> 0.075471698 | F27: =(F10)/F14 -> 0.07628524
A28: Google TPU | B28: % | C28: =(C11)/C14 -> 0.25328947 | D28: =(D11)/D14 -> 0.23206751 | E28: =(E11)/E14 -> 0.26415094 | F28: =(F11)/F14 -> 0.26699834
A29: AWS Trainium | B29: % | C29: =(C12)/C14 -> 0.13157895 | D29: =(D12)/D14 -> 0.10548523 | E29: =(E12)/E14 -> 0.11320755 | F29: =(F12)/F14 -> 0.11442786
A30: 其他 ASIC | B30: % | C30: =(C13)/C14 -> 0.065789474 | D30: =(D13)/D14 -> 0.18987342 | E30: =(E13)/E14 -> 0.18867925 | F30: =(F13)/F14 -> 0.1907131
A31: 金額份額
A32: NVIDIA | B32: % | C32: =(C16+C17+C18+C19)/C24 -> 0.77894887 | D32: =(D16+D17+D18+D19)/D24 -> 0.75128824 | E32: =(E16+E17+E18+E19)/E24 -> 0.72746331 | F32: =(F16+F17+F18+F19)/F24 -> 0.72332427
A33: AMD | B33: % | C33: =(C20)/C24 -> 0.053653186 | D33: =(D20)/D24 -> 0.06701814 | E33: =(E20)/E24 -> 0.078616352 | F33: =(F20)/F24 -> 0.079810306
A34: Google TPU | B34: % | C34: =(C21)/C24 -> 0.11016787 | D34: =(D21)/D24 -> 0.098293271 | E34: =(E21)/E24 -> 0.11006289 | F34: =(F21)/F24 -> 0.11173443
A35: AWS Trainium | B35: % | C35: =(C22)/C24 -> 0.038153377 | D35: =(D22)/D24 -> 0.02978584 | E35: =(E22)/E24 -> 0.031446541 | F35: =(F22)/F24 -> 0.031924122
A36: 其他 ASIC | B36: % | C36: =(C23)/C24 -> 0.019076688 | D36: =(D23)/D24 -> 0.053614512 | E36: =(E23)/E24 -> 0.052410901 | F36: =(F23)/F24 -> 0.053206871
A38: 情境 B：2028 顆數 ×0.8、2029 ×0.85
A39: 顆數
A40: NVIDIA Blackwell（B200／B300） | B40: 百萬顆 | C40: =u_bw_26 -> 5.4 | D40: =u_bw_27 -> 2.4 | E40: =u_bw_28*um28_B -> 0.4 | F40: =u_bw_28*(1+g29_bw)*um29_B -> 0.2125
A41: NVIDIA Rubin | B41: 百萬顆 | C41: =u_rb_26 -> 1.7 | D41: =u_rb_27 -> 7 | E41: =u_rb_28*um28_B -> 5.6 | F41: =u_rb_28*(1+g29_rb)*um29_B -> 6.8425
A42: NVIDIA Rubin Ultra | B42: 百萬顆 | C42: =u_ru_26 -> 0 | D42: =u_ru_27 -> 0.3 | E42: =u_ru_28*um28_B -> 1.6 | F42: =u_ru_28*(1+g29_ru)*um29_B -> 1.955
A43: NVIDIA Hopper（H200 等） | B43: 百萬顆 | C43: =u_hp_26 -> 0.5 | D43: =u_hp_27 -> 0 | E43: =u_hp_28*um28_B -> 0 | F43: =u_hp_28*(1+g29_hp)*um29_B -> 0
A44: AMD Instinct | B44: 百萬顆 | C44: =u_amd_26 -> 0.75 | D44: =u_amd_27 -> 1.5 | E44: =u_amd_28*um28_B -> 1.6 | F44: =u_amd_28*(1+g29_amd)*um29_B -> 1.955
A45: Google TPU | B45: 百萬顆 | C45: =u_tpu_26 -> 3.85 | D45: =u_tpu_27 -> 5.5 | E45: =u_tpu_28*um28_B -> 5.6 | F45: =u_tpu_28*(1+g29_tpu)*um29_B -> 6.8425
A46: AWS Trainium | B46: 百萬顆 | C46: =u_trn_26 -> 2 | D46: =u_trn_27 -> 2.5 | E46: =u_trn_28*um28_B -> 2.4 | F46: =u_trn_28*(1+g29_trn)*um29_B -> 2.9325
A47: 其他 ASIC（MTIA、Maia、Ascend 等） | B47: 百萬顆 | C47: =u_oth_26 -> 1 | D47: =u_oth_27 -> 4.5 | E47: =u_oth_28*um28_B -> 4 | F47: =u_oth_28*(1+g29_oth)*um29_B -> 4.8875
A48: 合計 | B48: 百萬顆 | C48: =SUM(C40:C47) -> 15.2 | D48: =SUM(D40:D47) -> 23.7 | E48: =SUM(E40:E47) -> 21.2 | F48: =SUM(F40:F47) -> 25.6275
A49: 金額（顆數 × 每顆售價）
A50: NVIDIA Blackwell（B200／B300） | B50: US$B | C50: =u_bw_26*(pm_bw) -> 218.16 | D50: =u_bw_27*(pm_bw) -> 96.96 | E50: =u_bw_28*um28_B*(pm_bw) -> 16.16 | F50: =u_bw_28*(1+g29_bw)*um29_B*(pm_bw) -> 8.585
A51: NVIDIA Rubin | B51: US$B | C51: =u_rb_26*(pm_rb) -> 93.5 | D51: =u_rb_27*(pm_rb) -> 385 | E51: =u_rb_28*um28_B*(pm_rb) -> 308 | F51: =u_rb_28*(1+g29_rb)*um29_B*(pm_rb) -> 376.3375
A52: NVIDIA Rubin Ultra | B52: US$B | C52: =u_ru_26*(pm_ru) -> 0 | D52: =u_ru_27*(pm_ru) -> 22.5 | E52: =u_ru_28*um28_B*(pm_ru) -> 120 | F52: =u_ru_28*(1+g29_ru)*um29_B*(pm_ru) -> 146.625
A53: NVIDIA Hopper（H200 等） | B53: US$B | C53: =u_hp_26*(pm_hp) -> 15 | D53: =u_hp_27*(pm_hp) -> 0 | E53: =u_hp_28*um28_B*(pm_hp) -> 0 | F53: =u_hp_28*(1+g29_hp)*um29_B*(pm_hp) -> 0
A54: AMD Instinct | B54: US$B | C54: =u_amd_26*(pa_amd) -> 22.5 | D54: =u_amd_27*(pa_amd) -> 45 | E54: =u_amd_28*um28_B*(pa_amd) -> 48 | F54: =u_amd_28*(1+g29_amd)*um29_B*(pa_amd) -> 58.65
A55: Google TPU | B55: US$B | C55: =u_tpu_26*(pa_tpu) -> 46.2 | D55: =u_tpu_27*(pa_tpu) -> 66 | E55: =u_tpu_28*um28_B*(pa_tpu) -> 67.2 | F55: =u_tpu_28*(1+g29_tpu)*um29_B*(pa_tpu) -> 82.11
A56: AWS Trainium | B56: US$B | C56: =u_trn_26*(pa_trn) -> 16 | D56: =u_trn_27*(pa_trn) -> 20 | E56: =u_trn_28*um28_B*(pa_trn) -> 19.2 | F56: =u_trn_28*(1+g29_trn)*um29_B*(pa_trn) -> 23.46
A57: 其他 ASIC（MTIA、Maia、Ascend 等） | B57: US$B | C57: =u_oth_26*(pa_oth) -> 8 | D57: =u_oth_27*(pa_oth) -> 36 | E57: =u_oth_28*um28_B*(pa_oth) -> 32 | F57: =u_oth_28*(1+g29_oth)*um29_B*(pa_oth) -> 39.1
A58: 合計 | B58: US$B | C58: =SUM(C50:C57) -> 419.36 | D58: =SUM(D50:D57) -> 671.46 | E58: =SUM(E50:E57) -> 610.56 | F58: =SUM(F50:F57) -> 734.8675
A59: 顆數份額
A60: NVIDIA | B60: % | C60: =(C40+C41+C42+C43)/C48 -> 0.5 | D60: =(D40+D41+D42+D43)/D48 -> 0.4092827 | E60: =(E40+E41+E42+E43)/E48 -> 0.35849057 | F60: =(F40+F41+F42+F43)/F48 -> 0.35157546
A61: AMD | B61: % | C61: =(C44)/C48 -> 0.049342105 | D61: =(D44)/D48 -> 0.063291139 | E61: =(E44)/E48 -> 0.075471698 | F61: =(F44)/F48 -> 0.07628524
A62: Google TPU | B62: % | C62: =(C45)/C48 -> 0.25328947 | D62: =(D45)/D48 -> 0.23206751 | E62: =(E45)/E48 -> 0.26415094 | F62: =(F45)/F48 -> 0.26699834
A63: AWS Trainium | B63: % | C63: =(C46)/C48 -> 0.13157895 | D63: =(D46)/D48 -> 0.10548523 | E63: =(E46)/E48 -> 0.11320755 | F63: =(F46)/F48 -> 0.11442786
A64: 其他 ASIC | B64: % | C64: =(C47)/C48 -> 0.065789474 | D64: =(D47)/D48 -> 0.18987342 | E64: =(E47)/E48 -> 0.18867925 | F64: =(F47)/F48 -> 0.1907131
A65: 金額份額
A66: NVIDIA | B66: % | C66: =(C50+C51+C52+C53)/C58 -> 0.77894887 | D66: =(D50+D51+D52+D53)/D58 -> 0.75128824 | E66: =(E50+E51+E52+E53)/E58 -> 0.72746331 | F66: =(F50+F51+F52+F53)/F58 -> 0.72332427
A67: AMD | B67: % | C67: =(C54)/C58 -> 0.053653186 | D67: =(D54)/D58 -> 0.06701814 | E67: =(E54)/E58 -> 0.078616352 | F67: =(F54)/F58 -> 0.079810306
A68: Google TPU | B68: % | C68: =(C55)/C58 -> 0.11016787 | D68: =(D55)/D58 -> 0.098293271 | E68: =(E55)/E58 -> 0.11006289 | F68: =(F55)/F58 -> 0.11173443
A69: AWS Trainium | B69: % | C69: =(C56)/C58 -> 0.038153377 | D69: =(D56)/D58 -> 0.02978584 | E69: =(E56)/E58 -> 0.031446541 | F69: =(F56)/F58 -> 0.031924122
A70: 其他 ASIC | B70: % | C70: =(C57)/C58 -> 0.019076688 | D70: =(D57)/D58 -> 0.053614512 | E70: =(E57)/E58 -> 0.052410901 | F70: =(F57)/F58 -> 0.053206871
A72: 情境 C：2028–29 顆數 ×0.6
A73: 顆數
A74: NVIDIA Blackwell（B200／B300） | B74: 百萬顆 | C74: =u_bw_26 -> 5.4 | D74: =u_bw_27 -> 2.4 | E74: =u_bw_28*um28_C -> 0.3 | F74: =u_bw_28*(1+g29_bw)*um29_C -> 0.15
A75: NVIDIA Rubin | B75: 百萬顆 | C75: =u_rb_26 -> 1.7 | D75: =u_rb_27 -> 7 | E75: =u_rb_28*um28_C -> 4.2 | F75: =u_rb_28*(1+g29_rb)*um29_C -> 4.83
A76: NVIDIA Rubin Ultra | B76: 百萬顆 | C76: =u_ru_26 -> 0 | D76: =u_ru_27 -> 0.3 | E76: =u_ru_28*um28_C -> 1.2 | F76: =u_ru_28*(1+g29_ru)*um29_C -> 1.38
A77: NVIDIA Hopper（H200 等） | B77: 百萬顆 | C77: =u_hp_26 -> 0.5 | D77: =u_hp_27 -> 0 | E77: =u_hp_28*um28_C -> 0 | F77: =u_hp_28*(1+g29_hp)*um29_C -> 0
A78: AMD Instinct | B78: 百萬顆 | C78: =u_amd_26 -> 0.75 | D78: =u_amd_27 -> 1.5 | E78: =u_amd_28*um28_C -> 1.2 | F78: =u_amd_28*(1+g29_amd)*um29_C -> 1.38
A79: Google TPU | B79: 百萬顆 | C79: =u_tpu_26 -> 3.85 | D79: =u_tpu_27 -> 5.5 | E79: =u_tpu_28*um28_C -> 4.2 | F79: =u_tpu_28*(1+g29_tpu)*um29_C -> 4.83
A80: AWS Trainium | B80: 百萬顆 | C80: =u_trn_26 -> 2 | D80: =u_trn_27 -> 2.5 | E80: =u_trn_28*um28_C -> 1.8 | F80: =u_trn_28*(1+g29_trn)*um29_C -> 2.07
A81: 其他 ASIC（MTIA、Maia、Ascend 等） | B81: 百萬顆 | C81: =u_oth_26 -> 1 | D81: =u_oth_27 -> 4.5 | E81: =u_oth_28*um28_C -> 3 | F81: =u_oth_28*(1+g29_oth)*um29_C -> 3.45
A82: 合計 | B82: 百萬顆 | C82: =SUM(C74:C81) -> 15.2 | D82: =SUM(D74:D81) -> 23.7 | E82: =SUM(E74:E81) -> 15.9 | F82: =SUM(F74:F81) -> 18.09
A83: 金額（顆數 × 每顆售價）
A84: NVIDIA Blackwell（B200／B300） | B84: US$B | C84: =u_bw_26*(pm_bw) -> 218.16 | D84: =u_bw_27*(pm_bw) -> 96.96 | E84: =u_bw_28*um28_C*(pm_bw) -> 12.12 | F84: =u_bw_28*(1+g29_bw)*um29_C*(pm_bw) -> 6.06
A85: NVIDIA Rubin | B85: US$B | C85: =u_rb_26*(pm_rb) -> 93.5 | D85: =u_rb_27*(pm_rb) -> 385 | E85: =u_rb_28*um28_C*(pm_rb) -> 231 | F85: =u_rb_28*(1+g29_rb)*um29_C*(pm_rb) -> 265.65
A86: NVIDIA Rubin Ultra | B86: US$B | C86: =u_ru_26*(pm_ru) -> 0 | D86: =u_ru_27*(pm_ru) -> 22.5 | E86: =u_ru_28*um28_C*(pm_ru) -> 90 | F86: =u_ru_28*(1+g29_ru)*um29_C*(pm_ru) -> 103.5
A87: NVIDIA Hopper（H200 等） | B87: US$B | C87: =u_hp_26*(pm_hp) -> 15 | D87: =u_hp_27*(pm_hp) -> 0 | E87: =u_hp_28*um28_C*(pm_hp) -> 0 | F87: =u_hp_28*(1+g29_hp)*um29_C*(pm_hp) -> 0
A88: AMD Instinct | B88: US$B | C88: =u_amd_26*(pa_amd) -> 22.5 | D88: =u_amd_27*(pa_amd) -> 45 | E88: =u_amd_28*um28_C*(pa_amd) -> 36 | F88: =u_amd_28*(1+g29_amd)*um29_C*(pa_amd) -> 41.4
A89: Google TPU | B89: US$B | C89: =u_tpu_26*(pa_tpu) -> 46.2 | D89: =u_tpu_27*(pa_tpu) -> 66 | E89: =u_tpu_28*um28_C*(pa_tpu) -> 50.4 | F89: =u_tpu_28*(1+g29_tpu)*um29_C*(pa_tpu) -> 57.96
A90: AWS Trainium | B90: US$B | C90: =u_trn_26*(pa_trn) -> 16 | D90: =u_trn_27*(pa_trn) -> 20 | E90: =u_trn_28*um28_C*(pa_trn) -> 14.4 | F90: =u_trn_28*(1+g29_trn)*um29_C*(pa_trn) -> 16.56
A91: 其他 ASIC（MTIA、Maia、Ascend 等） | B91: US$B | C91: =u_oth_26*(pa_oth) -> 8 | D91: =u_oth_27*(pa_oth) -> 36 | E91: =u_oth_28*um28_C*(pa_oth) -> 24 | F91: =u_oth_28*(1+g29_oth)*um29_C*(pa_oth) -> 27.6
A92: 合計 | B92: US$B | C92: =SUM(C84:C91) -> 419.36 | D92: =SUM(D84:D91) -> 671.46 | E92: =SUM(E84:E91) -> 457.92 | F92: =SUM(F84:F91) -> 518.73
A93: 顆數份額
A94: NVIDIA | B94: % | C94: =(C74+C75+C76+C77)/C82 -> 0.5 | D94: =(D74+D75+D76+D77)/D82 -> 0.4092827 | E94: =(E74+E75+E76+E77)/E82 -> 0.35849057 | F94: =(F74+F75+F76+F77)/F82 -> 0.35157546
A95: AMD | B95: % | C95: =(C78)/C82 -> 0.049342105 | D95: =(D78)/D82 -> 0.063291139 | E95: =(E78)/E82 -> 0.075471698 | F95: =(F78)/F82 -> 0.07628524
A96: Google TPU | B96: % | C96: =(C79)/C82 -> 0.25328947 | D96: =(D79)/D82 -> 0.23206751 | E96: =(E79)/E82 -> 0.26415094 | F96: =(F79)/F82 -> 0.26699834
A97: AWS Trainium | B97: % | C97: =(C80)/C82 -> 0.13157895 | D97: =(D80)/D82 -> 0.10548523 | E97: =(E80)/E82 -> 0.11320755 | F97: =(F80)/F82 -> 0.11442786
A98: 其他 ASIC | B98: % | C98: =(C81)/C82 -> 0.065789474 | D98: =(D81)/D82 -> 0.18987342 | E98: =(E81)/E82 -> 0.18867925 | F98: =(F81)/F82 -> 0.1907131
A99: 金額份額
A100: NVIDIA | B100: % | C100: =(C84+C85+C86+C87)/C92 -> 0.77894887 | D100: =(D84+D85+D86+D87)/D92 -> 0.75128824 | E100: =(E84+E85+E86+E87)/E92 -> 0.72746331 | F100: =(F84+F85+F86+F87)/F92 -> 0.72332427
A101: AMD | B101: % | C101: =(C88)/C92 -> 0.053653186 | D101: =(D88)/D92 -> 0.06701814 | E101: =(E88)/E92 -> 0.078616352 | F101: =(F88)/F92 -> 0.079810306
A102: Google TPU | B102: % | C102: =(C89)/C92 -> 0.11016787 | D102: =(D89)/D92 -> 0.098293271 | E102: =(E89)/E92 -> 0.11006289 | F102: =(F89)/F92 -> 0.11173443
A103: AWS Trainium | B103: % | C103: =(C90)/C92 -> 0.038153377 | D103: =(D90)/D92 -> 0.02978584 | E103: =(E90)/E92 -> 0.031446541 | F103: =(F90)/F92 -> 0.031924122
...

Sheet PL
A1: PL — AMD 損益（US$B；non-GAAP；FY2025A 實績、FY2026 錨點，FY2027 起為模型）。會計年度＝日曆年。三情境各一個完整推導區塊（本頁下方），頂端為摘要。FY2026、FY2027 三情境相同（情境係數從 CY2028 才開始）
A3: 情境／項目 | B3: 單位 | C3: FY2025A | D3: FY2026 | E3: FY2027 | F3: FY2028 | G3: FY2029 | H3: 說明
A4: 情境 A
A5: 營收 | B5: US$B | C5: =C95 -> 34.639 | D5: =D95 -> 49.643175 | E5: =E95 -> 75.668419 | F5: =F95 -> 93.833597 | G5: =G95 -> 105.10784
A6: 營收年增 | B6: % | D6: =D101 -> 0.43315844 | E6: =E101 -> 0.52424615 | F6: =F101 -> 0.24006288 | G6: =G101 -> 0.1201514
A7: Data Center | B7: US$B | C7: =C96 -> 16.635 | D7: =D96 -> 30.85147 | E7: =E96 -> 56.376771 | F7: =F96 -> 73.96363 | G7: =G96 -> 84.579458
A8: 資料中心 GPU | B8: US$B | C8: =C97 -> 6.5 | D8: =D97 -> 15.153372 | E8: =E97 -> 32.829625 | F8: =F97 -> 44.529697 | G8: =G97 -> 50.730435
A9: 資料中心非 GPU | B9: US$B | C9: =C98 -> 10.135 | D9: =D98 -> 15.698098 | E9: =E98 -> 23.547146 | F9: =F98 -> 29.433933 | G9: =G98 -> 33.849023
A10: Client＋Gaming | B10: US$B | C10: =C99 -> 14.55 | D10: =D99 -> 14.720398 | E10: =E99 -> 14.81321 | F10: =F99 -> 14.943685 | G10: =G99 -> 15.109468
A11: Embedded | B11: US$B | C11: =C100 -> 3.454 | D11: =D100 -> 4.0713072 | E11: =E100 -> 4.4784379 | F11: =F100 -> 4.9262817 | G11: =G100 -> 5.4189099
A12: 毛利率 | B12: % | C12: =C103 -> 0.5244089 | D12: =D103 -> 0.55792296 | E12: =E103 -> 0.49718814 | F12: =F103 -> 0.47793437 | G12: =G103 -> 0.4823363
A13: 營業利益 | B13: US$B | C13: =C106 -> 7.768 | D13: =D106 -> 13.675567 | E13: =E106 -> 17.68401 | F13: =F106 -> 21.056861 | G13: =G106 -> 24.607468
A14: 營業利益率 | B14: % | C14: =C107 -> 0.2242559 | D14: =D107 -> 0.27547729 | E14: =E107 -> 0.23370398 | F14: =F107 -> 0.22440642 | G14: =G107 -> 0.2341164
A15: 淨利（non-GAAP） | B15: US$B | C15: =C110 -> 6.831 | D15: =D110 -> 12.116863 | E15: =E110 -> 15.559089 | F15: =F110 -> 18.493469 | G15: =G110 -> 21.582497
A16: 稀釋股數 | B16: 十億股 | C16: =C113 -> 1.636 | D16: =D113 -> 1.6585805 | E16: =E113 -> 1.701833 | F16: =F113 -> 1.771918 | G16: =G113 -> 1.8421705
A17: EPS（non-GAAP） | B17: US$ | C17: =C114 -> 4.1754279 | D17: =D114 -> 7.3055625 | E17: =E114 -> 9.1425476 | F17: =F114 -> 10.436978 | G17: =G114 -> 11.715798
A18: EPS 年增 | B18: % | D18: =D115 -> 0.74965602 | E18: =E115 -> 0.2514502 | F18: =F115 -> 0.14158314 | G18: =G115 -> 0.12252778
A20: 情境 B
A21: 營收 | B21: US$B | C21: =C143 -> 34.639 | D21: =D143 -> 49.643175 | E21: =E143 -> 75.668419 | F21: =F143 -> 82.808439 | G21: =G143 -> 95.315758
A22: 營收年增 | B22: % | D22: =D149 -> 0.43315844 | E22: =E149 -> 0.52424615 | F22: =F149 -> 0.094359313 | G22: =G149 -> 0.15103919
A23: Data Center | B23: US$B | C23: =C144 -> 16.635 | D23: =D144 -> 30.85147 | E23: =E144 -> 56.376771 | F23: =F144 -> 62.938471 | G23: =G144 -> 74.787381
A24: 資料中心 GPU | B24: US$B | C24: =C145 -> 6.5 | D24: =D145 -> 15.153372 | E24: =E145 -> 32.829625 | F24: =F145 -> 33.504538 | G24: =G145 -> 40.938358
A25: 資料中心非 GPU | B25: US$B | C25: =C146 -> 10.135 | D25: =D146 -> 15.698098 | E25: =E146 -> 23.547146 | F25: =F146 -> 29.433933 | G25: =G146 -> 33.849023
A26: Client＋Gaming | B26: US$B | C26: =C147 -> 14.55 | D26: =D147 -> 14.720398 | E26: =E147 -> 14.81321 | F26: =F147 -> 14.943685 | G26: =G147 -> 15.109468
A27: Embedded | B27: US$B | C27: =C148 -> 3.454 | D27: =D148 -> 4.0713072 | E27: =E148 -> 4.4784379 | F27: =F148 -> 4.9262817 | G27: =G148 -> 5.4189099
A28: 毛利率 | B28: % | C28: =C151 -> 0.5244089 | D28: =D151 -> 0.55792296 | E28: =E151 -> 0.49718814 | F28: =F151 -> 0.52831285 | G28: =G151 -> 0.52492447
A29: 營業利益 | B29: US$B | C29: =C154 -> 7.768 | D29: =D154 -> 13.675567 | E29: =E154 -> 17.68401 | F29: =F154 -> 22.297258 | G29: =G154 -> 25.974472
A30: 營業利益率 | B30: % | C30: =C155 -> 0.2242559 | D30: =D155 -> 0.27547729 | E30: =E155 -> 0.23370398 | F30: =F155 -> 0.26926311 | G30: =G155 -> 0.27250973
A31: 淨利（non-GAAP） | B31: US$B | C31: =C158 -> 6.831 | D31: =D158 -> 12.116863 | E31: =E158 -> 15.559089 | F31: =F158 -> 19.572614 | G31: =G158 -> 22.771791
A32: 稀釋股數 | B32: 十億股 | C32: =C161 -> 1.636 | D32: =D161 -> 1.6585805 | E32: =E161 -> 1.701833 | F32: =F161 -> 1.7612513 | G32: =G161 -> 1.8195038
A33: EPS（non-GAAP） | B33: US$ | C33: =C162 -> 4.1754279 | D33: =D162 -> 7.3055625 | E33: =E162 -> 9.1425476 | F33: =F162 -> 11.112903 | G33: =G162 -> 12.515385
A34: EPS 年增 | B34: % | D34: =D163 -> 0.74965602 | E34: =E163 -> 0.2514502 | F34: =F163 -> 0.21551489 | G34: =G163 -> 0.12620305
A36: 情境 C
A37: 營收 | B37: US$B | C37: =C191 -> 34.639 | D37: =D191 -> 49.643175 | E37: =E191 -> 75.668419 | F37: =F191 -> 73.751126 | G37: =G191 -> 82.648382
A38: 營收年增 | B38: % | D38: =D197 -> 0.43315844 | E38: =E197 -> 0.52424615 | F38: =F197 -> -0.025338077 | G38: =G197 -> 0.12063891
A39: Data Center | B39: US$B | C39: =C192 -> 16.635 | D39: =D192 -> 30.85147 | E39: =E192 -> 56.376771 | F39: =F192 -> 53.881159 | G39: =G192 -> 62.120004
A40: 資料中心 GPU | B40: US$B | C40: =C193 -> 6.5 | D40: =D193 -> 15.153372 | E40: =E193 -> 32.829625 | F40: =F193 -> 24.447226 | G40: =G193 -> 28.270981
A41: 資料中心非 GPU | B41: US$B | C41: =C194 -> 10.135 | D41: =D194 -> 15.698098 | E41: =E194 -> 23.547146 | F41: =F194 -> 29.433933 | G41: =G194 -> 33.849023
A42: Client＋Gaming | B42: US$B | C42: =C195 -> 14.55 | D42: =D195 -> 14.720398 | E42: =E195 -> 14.81321 | F42: =F195 -> 14.943685 | G42: =G195 -> 15.109468
A43: Embedded | B43: US$B | C43: =C196 -> 3.454 | D43: =D196 -> 4.0713072 | E43: =E196 -> 4.4784379 | F43: =F196 -> 4.9262817 | G43: =G196 -> 5.4189099
A44: 毛利率 | B44: % | C44: =C199 -> 0.5244089 | D44: =D199 -> 0.55792296 | E44: =E199 -> 0.49718814 | F44: =F199 -> 0.55163058 | G44: =G199 -> 0.54779746
A45: 營業利益 | B45: US$B | C45: =C202 -> 7.768 | D45: =D202 -> 13.675567 | E45: =E202 -> 17.68401 | F45: =F202 -> 19.749075 | G45: =G202 -> 22.307732
A46: 營業利益率 | B46: % | C46: =C203 -> 0.2242559 | D46: =D203 -> 0.27547729 | E46: =E203 -> 0.23370398 | F46: =F203 -> 0.26777998 | G46: =G203 -> 0.2699113
A47: 淨利（non-GAAP） | B47: US$B | C47: =C206 -> 6.831 | D47: =D206 -> 12.116863 | E47: =E206 -> 15.559089 | F47: =F206 -> 17.355695 | G47: =G206 -> 19.581727
A48: 稀釋股數 | B48: 十億股 | C48: =C209 -> 1.636 | D48: =D209 -> 1.6585805 | E48: =E209 -> 1.701833 | F48: =F209 -> 1.7505846 | G48: =G209 -> 1.7888371
A49: EPS（non-GAAP） | B49: US$ | C49: =C210 -> 4.1754279 | D49: =D210 -> 7.3055625 | E49: =E210 -> 9.1425476 | F49: =F210 -> 9.9142281 | G49: =G210 -> 10.946623
A50: EPS 年增 | B50: % | D50: =D211 -> 0.74965602 | E50: =E211 -> 0.2514502 | F50: =F211 -> 0.084405413 | G50: =G211 -> 0.1041327
A52: 核對（應為 0）：FY2026 由下而上營收、毛利率 − 錨點（k_rec、非 GPU 毛利率校準恆等式）
A53: 情境 A：營收差（US$B） | D53: =D91-a26_rev -> 0
A54: 情境 A：毛利率差 | D54: =D93-a26_gp/a26_rev -> 0
A70: 情境 A：基準（顆數係數 1.0）
A71: 項目 | B71: 單位 | C71: FY2025A | D71: FY2026 | E71: FY2027 | F71: FY2028 | G71: FY2029 | H71: 說明
A72: A. 由下而上（C 欄空白；D＝FY2026 … G＝FY2029；FY2026 由校準等於錨點，FY2027 起為驅動因子推導）
A73: AMD 認列係數（k_rec × Sens 顆數係數） | B73: x | D73: =k_rec -> 0.67348322 | E73: =k_rec*1 -> 0.67348322 | F73: =k_rec*1 -> 0.67348322 | G73: =k_rec*1 -> 0.67348322
A74: 加速器市場金額（Units 頁，模組層級） | B74: US$B | D74: =Units!C24 -> 419.36 | E74: =Units!D24 -> 671.46 | F74: =Units!E24 -> 763.2 | G74: =Units!F24 -> 864.55
A75: AMD 金額份額（Units 頁） | B75: % | D75: =Units!C33 -> 0.053653186 | E75: =Units!D33 -> 0.06701814 | F75: =Units!E33 -> 0.078616352 | G75: =Units!F33 -> 0.079810306
A76: AMD 市場層顆數 | B76: 百萬顆 | D76: =Units!C10 -> 0.75 | E76: =Units!D10 -> 1.5 | F76: =Units!E10 -> 2 | G76: =Units!F10 -> 2.3
A77: AMD 認列顆數（市場層 × 認列係數） | B77: 百萬顆 | D77: =D76*D73 -> 0.50511241 | E77: =E76*E73 -> 1.0102248 | F77: =F76*F73 -> 1.3469664 | G77: =G76*G73 -> 1.5490114
A78: 世代售價係數（MI450／Helios） | B78: x | D78: =1 -> 1 | E78: =pg_27 -> 1 | F78: =pg_28 -> 1 | G78: =pg_29 -> 1
A79: GPU 基準營收 ＝ 市場金額 × AMD 份額 × 認列係數 × 世代係數 | B79: US$B | D79: =D74*D75*D73*D78 -> 15.153372 | E79: =E74*E75*E73*E78 -> 30.306745 | F79: =F74*F75*F73*F78 -> 40.408993 | G79: =G74*G75*G73*G78 -> 46.470342
A80: HBM 價格指數（相對 2026） | B80: x | D80: =hbm_A_26/hbm_A_26 -> 1 | E80: =hbm_A_27/hbm_A_26 -> 1.8 | F80: =hbm_A_28/hbm_A_26 -> 1.98 | G80: =hbm_A_29/hbm_A_26 -> 1.881
A81: 資料中心 GPU 營收（含 HBM 漲價轉嫁 (1−吸收比例)） | B81: US$B | D81: =D79*(1+(1-abs_mem)*hs_26*(D80-1)) -> 15.153372 | E81: =E79*(1+(1-abs_mem)*hs_26*(E80-1)) -> 32.829625 | F81: =F79*(1+(1-abs_mem)*hs_26*(F80-1)) -> 44.529697 | G81: =G79*(1+(1-abs_mem)*hs_26*(G80-1)) -> 50.730435
A82: 資料中心 GPU 成本 | B82: US$B | D82: =D79*((1-gm_gpu)+hs_26*(D80-1)) -> 7.5766862 | E82: =E79*((1-gm_gpu)+hs_26*(E80-1)) -> 20.199132 | F82: =F79*((1-gm_gpu)+hs_26*(F80-1)) -> 28.445904 | G82: =G79*((1-gm_gpu)+hs_26*(G80-1)) -> 31.755357 | H82: 基準營收 ×（非 HBM 成本＋HBM 成本占比的增加）
A83: 資料中心 GPU 毛利率 | B83: % | D83: =1-D82/D81 -> 0.5 | E83: =1-E82/E81 -> 0.3847285 | F83: =1-F82/F81 -> 0.3611925 | G83: =1-G82/G81 -> 0.37403736
A84: 資料中心非 GPU（EPYC CPU 等） | B84: US$B | D84: =a26_dcx -> 15.698098 | E84: =D84*(1+g_cpu27) -> 23.547146 | F84: =E84*(1+g_cpu28) -> 29.433933 | G84: =F84*(1+g_cpu29) -> 33.849023
A85: Client | B85: US$B | D85: =a26_cli -> 12.037318 | E85: =D85*(1+g_cli) -> 12.398438 | F85: =E85*(1+g_cli) -> 12.770391 | G85: =F85*(1+g_cli) -> 13.153502
A86: Gaming | B86: US$B | D86: =a26_gam -> 2.68308 | E86: =D86*(1+g_gam) -> 2.414772 | F86: =E86*(1+g_gam) -> 2.1732948 | G86: =F86*(1+g_gam) -> 1.9559653
A87: Embedded | B87: US$B | D87: =a26_emb -> 4.0713072 | E87: =D87*(1+g_emb) -> 4.4784379 | F87: =E87*(1+g_emb) -> 4.9262817 | G87: =F87*(1+g_emb) -> 5.4189099
A88: 非 GPU 營收合計 | B88: US$B | D88: =D84+D85+D86+D87 -> 34.489803 | E88: =E84+E85+E86+E87 -> 42.838794 | F88: =F84+F85+F86+F87 -> 49.3039 | G88: =G84+G85+G86+G87 -> 54.377401
A89: 非 GPU 毛利率（FY2026 校準：錨點毛利 − GPU 毛利；FY2027 起沿用） | B89: % | D89: =(a26_gp-(D81-D82))/D88 -> 0.58337188 | E89: =$D89 -> 0.58337188 | F89: =$D89 -> 0.58337188 | G89: =$D89 -> 0.58337188 | H89: Derived；組合內（CPU、Client、Gaming、Embedded）毛利率差異不模型化
A90: 非 GPU 成本 | B90: US$B | D90: =(1-D89)*D88 -> 14.369422 | E90: =(1-E89)*E88 -> 17.847846 | F90: =(1-F89)*F88 -> 20.541391 | G90: =(1-G89)*G88 -> 22.655154
A91: 由下而上營收合計 | B91: US$B | D91: =D81+D88 -> 49.643175 | E91: =E81+E88 -> 75.668419 | F91: =F81+F88 -> 93.833597 | G91: =G81+G88 -> 105.10784
A92: 由下而上成本合計 | B92: US$B | D92: =D82+D90 -> 21.946108 | E92: =E82+E90 -> 38.046979 | F92: =F82+F90 -> 48.987296 | G92: =G82+G90 -> 54.410511
A93: 由下而上毛利率 | B93: % | D93: =1-D92/D91 -> 0.55792296 | E93: =1-E92/E91 -> 0.49718814 | F93: =1-F92/F91 -> 0.47793437 | G93: =1-G92/G91 -> 0.4823363 | H93: FY2026 ＝ 錨點毛利率（校準恆等式，非獨立檢驗）
A94: B. 報告值（FY2025A 實績、FY2026 錨點；FY2027 起為由下而上）
A95: 營收 | B95: US$B | C95: =a25_rev -> 34.639 | D95: =a26_rev -> 49.643175 | E95: =E91 -> 75.668419 | F95: =F91 -> 93.833597 | G95: =G91 -> 105.10784
A96: Data Center | B96: US$B | C96: =a25_dc -> 16.635 | D96: =a26_dc -> 30.85147 | E96: =E81+E84 -> 56.376771 | F96: =F81+F84 -> 73.96363 | G96: =G81+G84 -> 84.579458
A97: 資料中心 GPU | B97: US$B | C97: =a25_gpu -> 6.5 | D97: =a26_gpu -> 15.153372 | E97: =E81 -> 32.829625 | F97: =F81 -> 44.529697 | G97: =G81 -> 50.730435
A98: 資料中心非 GPU（CPU 等） | B98: US$B | C98: =a25_dcx -> 10.135 | D98: =a26_dcx -> 15.698098 | E98: =E84 -> 23.547146 | F98: =F84 -> 29.433933 | G98: =G84 -> 33.849023
A99: Client＋Gaming | B99: US$B | C99: =a25_cli+a25_gam -> 14.55 | D99: =a26_cli+a26_gam -> 14.720398 | E99: =E85+E86 -> 14.81321 | F99: =F85+F86 -> 14.943685 | G99: =G85+G86 -> 15.109468
A100: Embedded | B100: US$B | C100: =a25_emb -> 3.454 | D100: =a26_emb -> 4.0713072 | E100: =E87 -> 4.4784379 | F100: =F87 -> 4.9262817 | G100: =G87 -> 5.4189099
A101: 營收年增 | B101: % | D101: =D95/C95-1 -> 0.43315844 | E101: =E95/D95-1 -> 0.52424615 | F101: =F95/E95-1 -> 0.24006288 | G101: =G95/F95-1 -> 0.1201514
A102: 毛利（non-GAAP） | B102: US$B | C102: =a25_gp -> 18.165 | D102: =a26_gp -> 27.697067 | E102: =E95-E92 -> 37.62144 | F102: =F95-F92 -> 44.846301 | G102: =G95-G92 -> 50.697324
A103: 毛利率 | B103: % | C103: =C102/C95 -> 0.5244089 | D103: =D102/D95 -> 0.55792296 | E103: =E102/E95 -> 0.49718814 | F103: =F102/F95 -> 0.47793437 | G103: =G102/G95 -> 0.4823363
A104: 營業費用（基準路徑） | B104: US$B | C104: =a25_opx -> 10.397 | D104: =a26_opx -> 14.0215 | E104: =D104*(1+MAX(g_opx_min,phi*E101)) -> 19.93743 | F104: =E104*(1+MAX(g_opx_min,phi*F101)) -> 23.78944 | G104: =F104*(1+MAX(g_opx_min,phi*G101)) -> 26.089856 | H104: 前一年 ×（1＋MAX(下限, 彈性 × 營收年增)）
A105: 營業費用 | B105: US$B | C105: =C104 -> 10.397 | D105: =D104 -> 14.0215 | E105: =E104+0*E95 -> 19.93743 | F105: =F104+0*F95 -> 23.78944 | G105: =G104+0*G95 -> 26.089856
A106: 營業利益 | B106: US$B | C106: =C102-C105 -> 7.768 | D106: =D102-D105 -> 13.675567 | E106: =E102-E105 -> 17.68401 | F106: =F102-F105 -> 21.056861 | G106: =G102-G105 -> 24.607468
A107: 營業利益率 | B107: % | C107: =C106/C95 -> 0.2242559 | D107: =D106/D95 -> 0.27547729 | E107: =E106/E95 -> 0.23370398 | F107: =F106/F95 -> 0.22440642 | G107: =G106/G95 -> 0.2341164
A108: 非營業淨額（non-GAAP） | B108: US$B | C108: =a25_oth -> 0.081 | D108: =a26_oth -> 0.25 | E108: =oth_f -> 0.2 | F108: =oth_f -> 0.2 | G108: =oth_f -> 0.2
A109: 有效稅率 | B109: % | C109: =a25_etr -> 0.12969805 | D109: =a26_etr -> 0.12988367 | E109: =tx_f -> 0.13 | F109: =tx_f -> 0.13 | G109: =tx_f -> 0.13
A110: 淨利（non-GAAP） | B110: US$B | C110: =a25_ni -> 6.831 | D110: =a26_ni -> 12.116863 | E110: =(E106+E108)*(1-E109) -> 15.559089 | F110: =(F106+F108)*(1-F109) -> 18.493469 | G110: =(G106+G108)*(1-G109) -> 21.582497
A111: 稀釋股數（不含客戶認股權證） | B111: 十億股 | C111: =a25_sh -> 1.636 | D111: =a26_sh -> 1.6585805 | E111: =D111*(1+sh_g) -> 1.6751663 | F111: =E111*(1+sh_g) -> 1.691918 | G111: =F111*(1+sh_g) -> 1.7088371
A112: 客戶認股權證稀釋股數（年中平均已歸屬 GW × 每 GW 股數） | B112: 十億股 | C112: =0 -> 0 | D112: =0 -> 0 | E112: =w_tot/w_gw*(gw_26+gw_27)/2*wf -> 0.026666667 | F112: =w_tot/w_gw*(gw_27+gw_28*um28_A)/2*wf -> 0.08 | G112: =w_tot/w_gw*(gw_28*um28_A+gw_29*um29_A)/2*wf -> 0.13333333 | H112: OpenAI、Meta 各 160M 股，依 GW 分批歸屬（Assumed 線性）；行使價 $0.01，視同全額稀釋
A113: 稀釋股數 | B113: 十億股 | C113: =C111+C112 -> 1.636 | D113: =D111+D112 -> 1.6585805 | E113: =E111+E112 -> 1.701833 | F113: =F111+F112 -> 1.771918 | G113: =G111+G112 -> 1.8421705
A114: EPS（non-GAAP） | B114: US$ | C114: =C110/C113 -> 4.1754279 | D114: =D110/D113 -> 7.3055625 | E114: =E110/E113 -> 9.1425476 | F114: =F110/F113 -> 10.436978 | G114: =G110/G113 -> 11.715798
A115: EPS 年增 | B115: % | D115: =D114/C114-1 -> 0.74965602 | E115: =E114/D114-1 -> 0.2514502 | F115: =F114/E114-1 -> 0.14158314 | G115: =G114/F114-1 -> 0.12252778
A118: 情境 B：CY2028 顆數 ×0.8、CY2029 ×0.85
A119: 項目 | B119: 單位 | C119: FY2025A | D119: FY2026 | E119: FY2027 | F119: FY2028 | G119: FY2029 | H119: 說明
A120: A. 由下而上（C 欄空白；D＝FY2026 … G＝FY2029；FY2026 由校準等於錨點，FY2027 起為驅動因子推導）
A121: AMD 認列係數（k_rec × Sens 顆數係數） | B121: x | D121: =k_rec -> 0.67348322 | E121: =k_rec*1 -> 0.67348322 | F121: =k_rec*1 -> 0.67348322 | G121: =k_rec*1 -> 0.67348322
...

Sheet Val
A1: Val — P/E 估值（美元；non-GAAP EPS）。目標價＝十年 non-GAAP P/E 中位數 × FY2027 EPS（各情境），情境加權（第 0 節）。結論另看「現價 ÷ FY2027、FY2028 EPS」。跨公司規則：合理倍數＝10 年（2016–2025 年底）P/E 的分位，依循環位置：見頂年 25 分位、中段中位數、谷底 75 分位；AMD 會計年度＝日曆年，用共用規則 classify（不平移），見頂年度讀設備市場模型
A2: 依循環位置取分位的規則值：不適用（保留計算，不進結論；比照 NVIDIA 模型）。理由：歷史倍數是落後倍數（年底價 ÷ 當年 non-GAAP EPS），含高成長期溢價與 EPS 低谷年（2016 為虧損、2022 年 18.5x、2019 年 71.7x）；GAAP 倍數另受 Xilinx 併購攤銷扭曲（2023 年 283x），只列參考。本版未做先驗，無 Andy 合理 P/E 對照
A3: 0. 目標價（DCF 與 Comparable 加權；v0.2 新增，Andy 2026-10-25）
A4: 0.1 DCF（股東權益現金流，FY2027–FY2032 明確期＋FY2032 後永續）
A5: 項目 | B5: A | C5: B | D5: C | E5: 說明 | F5: 折現年數 t | G5: 期內占比（基準日後）
A6: 情境 EPS（FY2027–FY2032） | E6: 引用 PL 頁延伸表（上游結束後為收斂法）；三情境欄 B／C／D＝A／B／C
A7: FY2027 | B7: =PL!E223 -> 9.1425476 | C7: =PL!E232 -> 9.1425476 | D7: =PL!E241 -> 9.1425476 | F7: 1 | G7: 1
A8: FY2028 | B8: =PL!F223 -> 10.436978 | C8: =PL!F232 -> 11.112903 | D8: =PL!F241 -> 9.9142281 | F8: 2 | G8: 1
A9: FY2029 | B9: =PL!G223 -> 11.715798 | C9: =PL!G232 -> 12.515385 | D9: =PL!G241 -> 10.946623 | F9: 3 | G9: 1
A10: FY2030 | B10: =PL!H223 -> 12.397046 | C10: =PL!H232 -> 13.04622 | D10: =PL!H241 -> 10.869156 | F10: 4 | G10: 1
A11: FY2031 | B11: =PL!I223 -> 12.878819 | C11: =PL!I232 -> 13.132096 | D11: =PL!I241 -> 10.405838 | F11: 5 | G11: 1
A12: FY2032 | B12: =PL!J223 -> 13.130937 | C12: =PL!J232 -> 12.747983 | D12: =PL!J241 -> 9.5879868 | F12: 6 | G12: 1
A13: 股東現金流＝EPS ×（1 − tp_g ÷ tp_roe） | B13: =1-MIN(0.8,tp_g/tp_roe) -> 0.8 | E13: B 欄＝可發放比例（1 − 再投資率；再投資率＝tp_g ÷ tp_roe，上限 0.8）；下列六列＝EPS × 可發放比例 × 期內占比
A14: FY2027 股東現金流 | B14: =B7*$B$13*$G$7 -> 7.3140381 | C14: =C7*$B$13*$G$7 -> 7.3140381 | D14: =D7*$B$13*$G$7 -> 7.3140381
A15: FY2028 股東現金流 | B15: =B8*$B$13*$G$8 -> 8.3495826 | C15: =C8*$B$13*$G$8 -> 8.8903222 | D15: =D8*$B$13*$G$8 -> 7.9313825
A16: FY2029 股東現金流 | B16: =B9*$B$13*$G$9 -> 9.3726384 | C16: =C9*$B$13*$G$9 -> 10.012308 | D16: =D9*$B$13*$G$9 -> 8.7572987
A17: FY2030 股東現金流 | B17: =B10*$B$13*$G$10 -> 9.9176366 | C17: =C10*$B$13*$G$10 -> 10.436976 | D17: =D10*$B$13*$G$10 -> 8.6953244
A18: FY2031 股東現金流 | B18: =B11*$B$13*$G$11 -> 10.303055 | C18: =C11*$B$13*$G$11 -> 10.505677 | D18: =D11*$B$13*$G$11 -> 8.3246703
A19: FY2032 股東現金流 | B19: =B12*$B$13*$G$12 -> 10.504749 | C19: =C12*$B$13*$G$12 -> 10.198387 | D19: =D12*$B$13*$G$12 -> 7.6703894
A20: 永續價值（FY2032 年底；FY2032 現金流 ×(1＋tp_g) ÷ (tp_r − tp_g)） | B20: =B19*(1+tp_g)/(tp_r-tp_g) -> 182.08232 | C20: =C19*(1+tp_g)/(tp_r-tp_g) -> 176.77203 | D20: =D19*(1+tp_g)/(tp_r-tp_g) -> 132.95342
A21: DCF 情境每股價值（折現率 tp_r） | B21: =MAX(0,B14/(1+tp_r)^$F$7+B15/(1+tp_r)^$F$8+B16/(1+tp_r)^$F$9+B17/(1+tp_r)^$F$10+B18/(1+tp_r)^$F$11+B19/(1+tp_r)^$F$12+B20/(1+tp_r)^$F$12) -> 142.47306 | C21: =MAX(0,C14/(1+tp_r)^$F$7+C15/(1+tp_r)^$F$8+C16/(1+tp_r)^$F$9+C17/(1+tp_r)^$F$10+C18/(1+tp_r)^$F$11+C19/(1+tp_r)^$F$12+C20/(1+tp_r)^$F$12) -> 140.71062 | D21: =MAX(0,D14/(1+tp_r)^$F$7+D15/(1+tp_r)^$F$8+D16/(1+tp_r)^$F$9+D17/(1+tp_r)^$F$10+D18/(1+tp_r)^$F$11+D19/(1+tp_r)^$F$12+D20/(1+tp_r)^$F$12) -> 110.26994 | E21: 基準日 2026 年底；明確期現金流與永續價值依 F 欄年數折現；小於 0 時取 0（Andy 2026-10-25 12:22）
A22: 其中：永續價值現值占比 | B22: =B20/(1+tp_r)^$F$12/B21 -> 0.72140464 | C22: =C20/(1+tp_r)^$F$12/C21 -> 0.70913771 | D22: =D20/(1+tp_r)^$F$12/D21 -> 0.6805911
A23: DCF 目標價（情境加權） | B23: =(tp_wA*B21+tp_wB*C21+tp_wC*D21)*(1+tp_r) -> 148.66633 | E23: Σ 權重 × 情境價值 ×(1＋tp_r)：推到約 12 個月後
A25: 0.2 Comparable（市場主流同業前瞻 P/E）
A26: 同業與前瞻 P/E | B26: 代號 | C26: 前瞻 12 月 P/E | D26: 日期 | E26: 來源 | F26: 標記
A27: NVIDIA | B27: NVDA | C27: 17.44 | D27: 2026-10-23 | E27: stockanalysis.com 統計頁（Forward PE） | F27: Interested-party（資料商彙整賣方預估）
A28: Broadcom | B28: AVGO | C28: 18.52 | D28: 2026-10-23 | E28: 同上 | F28: Interested-party（同上）
A29: Intel | B29: INTC | C29: 50.64 | D29: 2026-10-23 | E29: 同上 | F29: Interested-party（同上）
A30: Qualcomm | B30: QCOM | C30: 18.98 | D30: 2026-10-23 | E30: 同上 | F30: Interested-party（同上）
A31: Marvell | B31: MRVL | C31: 40.44 | D31: 2026-10-23 | E31: 同上 | F31: Interested-party（同上）
A32: 同業選擇 | E32: 券商常用的 CPU／GPU／AI 半導體同業（NVIDIA、Intel 為直接競爭者）；不含 A 股（Andy 11:53）。前瞻 P/E 口徑為資料商的未來 12 個月共識 EPS，各家 GAAP／non-GAAP 口徑不一
A33: 同業前瞻 P/E 中位數 | B33: =MEDIAN(C27:C31) -> 18.98
A34: 各情境 12 個月後的前瞻 EPS | B34: =2/12*PL!E223+10/12*PL!F223 -> 10.22124 | C34: =2/12*PL!E232+10/12*PL!F232 -> 10.78451 | D34: =2/12*PL!E241+10/12*PL!F241 -> 9.7856147 | E34: 會計年度＝日曆年：約 12 個月後（2027-10 底）的未來 12 個月＝2027-11～2028-10（2/12 × FY2027＋10/12 × FY2028）
A35: 12 個月後的前瞻 EPS（情境加權） | B35: =tp_wA*B34+tp_wB*C34+tp_wC*D34 -> 10.41575
A36: Comparable 目標價 | B36: =B33*B35 -> 197.69093 | E36: 同業前瞻 P/E 中位數 × 12 個月後的前瞻 EPS（情境加權）
A38: 0.3 結論
A39: 項目 | B39: 數值 | C39: 對照 | D39: 對照 | E39: 說明
A40: 目標價（DCF 與 Comparable 加權） | B40: =tp_w_dcf*B23+(1-tp_w_dcf)*B36 -> 173.17863 | E40: ="DCF 權重 "&TEXT(tp_w_dcf,"0%")&"、Comparable 權重 "&TEXT(1-tp_w_dcf,"0%")&"（In 頁 tp_w_dcf，Andy 可改）" -> DCF 權重 50%、Comparable 權重 50%（In 頁 tp_w_dcf，Andy 可改）
A41: Comparable 目標價（市場主流同業法） | B41: =B36 -> 197.69093
A42: 市場共識目標價 | B42: =cons_tp -> 637.61 | E42: stockanalysis.com：55 位分析師平均目標價（2026-10-25 頁面）；Interested-party
A43: 上檔空間：加權目標價 | B43: =B40/px-1 -> -0.66489554
A44: 上檔空間：Comparable 目標價 | B44: =B41/px-1 -> -0.6174637
A45: 與市場共識目標價的差距：EPS 因素 | B45: =B35/C45-1 -> -0.46013735 | C45: =2/12*cons_eps27+10/12*cons_eps28 -> 19.293333 | E45: B＝我們的前瞻 EPS（情境加權）÷ 共識前瞻 EPS − 1；C＝共識前瞻 EPS（同權重的共識 EPS：2/12 × 共識 FY2027（15.76，stockanalysis）＋10/12 × 共識 FY2028（約 20，二手））
A46: 與市場共識目標價的差距：倍數因素 | B46: =C46/B33-1 -> 0.74121197 | C46: =B42/C45 -> 33.048203 | D46: =B33 -> 18.98 | E46: C＝市場共識目標價 ÷ 共識前瞻 EPS 隱含的倍數；D＝同業中位數；B＝C ÷ D − 1
A47: 價格帶（DCF 不如預期～順利） | B47: =D21*(1+tp_r) -> 121.29693 | C47: =B21*(1+tp_r) -> 156.72036 | E47: B＝C 情境 DCF 價值、C＝A 情境 DCF 價值（皆推到 12 個月後）
A48: 檢查用：現價 ÷ 各情境 FY2028 EPS | B48: =px/PL!F223 -> 49.51529 | C48: =px/PL!F232 -> 46.503601 | D48: =px/PL!F241 -> 52.126095
A49: 歷史倍數檢查：現價隱含 P/E 的十年分位（A／B／C） | B49: =IF(B48<MIN(B126:B135),0,IF(B48>MAX(B126:B135),1,PERCENTRANK(B126:B135,B48))) -> 0.354 | C49: =IF(C48<MIN(B126:B135),0,IF(C48>MAX(B126:B135),1,PERCENTRANK(B126:B135,C48))) -> 0.321 | D49: =IF(D48<MIN(B126:B135),0,IF(D48>MAX(B126:B135),1,PERCENTRANK(B126:B135,D48))) -> 0.517 | E49: 上一列在 2016–2025 年底 P/E 分布（Val!B126:B135）的分位（PERCENTRANK；低於最小＝0、高於最大＝1）；只作檢查，不進目標價
A50: 目標價方法 | B50: DCF：股東現金流＝non-GAAP EPS ×（1 − tp_g ÷ tp_roe），tp_r 10%、tp_g 4%、tp_roe 0.20（工作單預設；GAAP ROE 受 Xilinx 攤銷壓低不採）；基準日 2026 年底，FY2027 起逐年折現，FY2032 後永續。Comparable：NVIDIA、Broadcom、Intel、Qualcomm、Marvell 前瞻 P/E 中位數 × 12 個月後前瞻 EPS。偏誤方向：non-GAAP EPS 排除股票薪酬與攤銷（偏高）；C 情境 FY2030 起淨利率收斂到 FY2029 × 0.8（Assumed）；歷史分位用自算十年 non-GAAP 落後 P/E（含轉型期高倍數）；永續價值占 DCF 價值過半，對 tp_r、tp_g 敏感（Sens 頁）。
A51: 檢查：情境權重合計（應為 1） | B51: =ROUND(tp_wA+tp_wB+tp_wC,6) -> 1
A55: 舊法：規則值情境加權（參考）
A56: 項目 | B56: 值 | E56: 說明
A57: 規則值情境加權價（參考，非目標價） | B57: =tp_wA*B59+tp_wB*B60+tp_wC*B61 -> 471.57261
A58: 相對現價（參考） | B58: =B57/px-1 -> -0.08749665
A59: 情境 A 隱含價（樂觀） | B59: =pe_mid*PL!E17 -> 471.57261 | E59: 十年 non-GAAP P/E 中位數 × 情境 A FY2027 EPS
A60: 情境 B 隱含價（基準） | B60: =pe_mid*PL!E33 -> 471.57261 | E60: 十年 non-GAAP P/E 中位數 × 情境 B FY2027 EPS
A61: 情境 C 隱含價（下檔） | B61: =pe_mid*PL!E49 -> 471.57261 | E61: 十年 non-GAAP P/E 中位數 × 情境 C FY2027 EPS
A62: 情境權重 A／B／C | B62: =tp_wA -> 0.3 | C62: =tp_wB -> 0.5 | D62: =tp_wC -> 0.2 | E62: In 頁 tp_wA／tp_wB／tp_wC（Assumed，Andy 可改）
A63: 舊法說明 | B63: P/E：十年（2016–2025 年底）non-GAAP P/E 中位數（年底價 ÷ 公司 non-GAAP EPS，自算；規則值不適用時的替代）× FY2027（≈未來 12–14 個月）non-GAAP EPS，情境加權。偏誤方向：歷史倍數含 AMD 2017–2021 年轉型期與 AI 前的高成長溢價（偏高）。FY2027 EPS 三情境相同（情境係數自 CY2028 起），故三情境隱含價相同；樣板標籤 A 樂觀／B 基準／C 下檔沿用，本模型 A＝市場層基準、B＝AI 資本支出消化、C＝明顯下修
A65: 1. 價格與市場隱含倍數
A66: 項目 | B66: A | C66: B | D66: C | E66: 說明
A67: 現價（2026-10-23 收盤） | B67: =px -> 516.79
A68: 現價 ÷ FY2026 EPS（錨點） | B68: =px/PL!D17 -> 70.739248 | C68: =px/PL!D33 -> 70.739248 | D68: =px/PL!D49 -> 70.739248
A69: 現價 ÷ FY2027 EPS（模型） | B69: =px/PL!E17 -> 56.52582 | C69: =px/PL!E33 -> 56.52582 | D69: =px/PL!E49 -> 56.52582 | E69: FY2027 EPS 三情境相同（情境係數從 CY2028 才開始）
A70: 現價 ÷ FY2028 EPS（模型） | B70: =px/PL!F17 -> 49.51529 | C70: =px/PL!F33 -> 46.503601 | D70: =px/PL!F49 -> 52.126095
A71: 現價 ÷ FY2029 EPS（模型） | B71: =px/PL!G17 -> 44.110525 | C71: =px/PL!G33 -> 41.292377 | D71: =px/PL!G49 -> 47.209992
A72: 現價 ÷ 共識 FY2027 EPS | B72: =px/cons_eps27 -> 32.791244 | C72: =px/cons_eps27_lo -> 46.0187 | E72: B＝stockanalysis 15.76；C＝tickflow 四季合計 11.23（兩來源差大）
A73: 現價 ÷ 共識 FY2028 EPS（約 $20，二手） | B73: =px/cons_eps28 -> 25.8395
A75: 2. 循環位置（共用規則，不平移）與規則倍數
A76: 規則：各情境見頂年度（日曆年）取自設備市場模型（Mkt 頁「見頂年度」：A 2029、B 2028、C 2027）；AMD 會計年度＝日曆年：FY 早於見頂年＝中段（中位數）、等於＝見頂（25 分位）、晚於＝谷底（75 分位）。
A77: 情境 | B77: 設備市場見頂年度（CY） | C77: FY2027 判定 | D77: FY2027 倍數 | E77: FY2028 判定 | F77: FY2028 倍數 | G77: 規則
A78: A | B78: =pk_A -> 2029 | C78: =IF(2027<pk_A,"中段",IF(2027=pk_A,"見頂","谷底")) -> 中段 | D78: =IF(C78="見頂",pe_peak,IF(C78="谷底",pe_trough,pe_mid)) -> 51.58 | E78: =IF(2028<pk_A,"中段",IF(2028=pk_A,"見頂","谷底")) -> 中段 | F78: =IF(E78="見頂",pe_peak,IF(E78="谷底",pe_trough,pe_mid)) -> 51.58 | G78: tools/cycle_position.py classify（不平移）
A79: B | B79: =pk_B -> 2028 | C79: =IF(2027<pk_B,"中段",IF(2027=pk_B,"見頂","谷底")) -> 中段 | D79: =IF(C79="見頂",pe_peak,IF(C79="谷底",pe_trough,pe_mid)) -> 51.58 | E79: =IF(2028<pk_B,"中段",IF(2028=pk_B,"見頂","谷底")) -> 見頂 | F79: =IF(E79="見頂",pe_peak,IF(E79="谷底",pe_trough,pe_mid)) -> 40.13 | G79: tools/cycle_position.py classify（不平移）
A80: C | B80: =pk_C -> 2027 | C80: =IF(2027<pk_C,"中段",IF(2027=pk_C,"見頂","谷底")) -> 見頂 | D80: =IF(C80="見頂",pe_peak,IF(C80="谷底",pe_trough,pe_mid)) -> 40.13 | E80: =IF(2028<pk_C,"中段",IF(2028=pk_C,"見頂","谷底")) -> 谷底 | F80: =IF(E80="見頂",pe_peak,IF(E80="谷底",pe_trough,pe_mid)) -> 60.47 | G80: tools/cycle_position.py classify（不平移）
A82: 3. 規則值隱含股價（美元）——不適用：落後倍數含高成長期溢價，保留計算但不進結論；規則值＝FY2027 EPS × 依循環位置的倍數
A83: 情境 | B83: EPS 年度 | C83: EPS | D83: 倍數類型 | E83: 倍數 | F83: 隱含股價（不適用；約 FY2027 年底，未折現） | G83: 相對現價 | H83: 折現到現在
A84: A | B84: FY2027 | C84: =PL!E17 -> 9.1425476 | D84: ="規則值（不適用）："&C78 -> 規則值（不適用）：中段 | E84: =D78 -> 51.58 | F84: =C84*E84 -> 471.57261 | G84: =F84/px-1 -> -0.08749665 | H84: =F84/(1+r_disc)^(1.19+0) -> 421.0089
A85: A | B85: FY2027 | C85: =PL!E17 -> 9.1425476 | D85: 參考：25 分位 | E85: =pe_peak -> 40.13 | F85: =C85*E85 -> 366.89044 | G85: =F85/px-1 -> -0.29005895 | H85: =F85/(1+r_disc)^(1.19+0) -> 327.55112
A86: A | B86: FY2027 | C86: =PL!E17 -> 9.1425476 | D86: 參考：中位數 | E86: =pe_mid -> 51.58 | F86: =C86*E86 -> 471.57261 | G86: =F86/px-1 -> -0.08749665 | H86: =F86/(1+r_disc)^(1.19+0) -> 421.0089
A87: A | B87: FY2027 | C87: =PL!E17 -> 9.1425476 | D87: 參考：75 分位 | E87: =pe_trough -> 60.47 | F87: =C87*E87 -> 552.84985 | G87: =F87/px-1 -> 0.06977661 | H87: =F87/(1+r_disc)^(1.19+0) -> 493.57131
A88: A | B88: FY2028 | C88: =PL!F17 -> 10.436978 | D88: ="規則值（FY2028；不適用）："&E78 -> 規則值（FY2028；不適用）：中段 | E88: =F78 -> 51.58 | F88: =C88*E88 -> 538.33934 | G88: =F88/px-1 -> 0.041698438 | H88: =F88/(1+r_disc)^(1.19+1) -> 436.92423
A89: B | B89: FY2027 | C89: =PL!E33 -> 9.1425476 | D89: ="規則值（不適用）："&C79 -> 規則值（不適用）：中段 | E89: =D79 -> 51.58 | F89: =C89*E89 -> 471.57261 | G89: =F89/px-1 -> -0.08749665 | H89: =F89/(1+r_disc)^(1.19+0) -> 421.0089
A90: B | B90: FY2027 | C90: =PL!E33 -> 9.1425476 | D90: 參考：25 分位 | E90: =pe_peak -> 40.13 | F90: =C90*E90 -> 366.89044 | G90: =F90/px-1 -> -0.29005895 | H90: =F90/(1+r_disc)^(1.19+0) -> 327.55112
A91: B | B91: FY2027 | C91: =PL!E33 -> 9.1425476 | D91: 參考：中位數 | E91: =pe_mid -> 51.58 | F91: =C91*E91 -> 471.57261 | G91: =F91/px-1 -> -0.08749665 | H91: =F91/(1+r_disc)^(1.19+0) -> 421.0089
A92: B | B92: FY2027 | C92: =PL!E33 -> 9.1425476 | D92: 參考：75 分位 | E92: =pe_trough -> 60.47 | F92: =C92*E92 -> 552.84985 | G92: =F92/px-1 -> 0.06977661 | H92: =F92/(1+r_disc)^(1.19+0) -> 493.57131
A93: B | B93: FY2028 | C93: =PL!F33 -> 11.112903 | D93: ="規則值（FY2028；不適用）："&E79 -> 規則值（FY2028；不適用）：見頂 | E93: =F79 -> 40.13 | F93: =C93*E93 -> 445.96079 | G93: =F93/px-1 -> -0.13705608 | H93: =F93/(1+r_disc)^(1.19+1) -> 361.94843
A94: C | B94: FY2027 | C94: =PL!E49 -> 9.1425476 | D94: ="規則值（不適用）："&C80 -> 規則值（不適用）：見頂 | E94: =D80 -> 40.13 | F94: =C94*E94 -> 366.89044 | G94: =F94/px-1 -> -0.29005895 | H94: =F94/(1+r_disc)^(1.19+0) -> 327.55112
A95: C | B95: FY2027 | C95: =PL!E49 -> 9.1425476 | D95: 參考：25 分位 | E95: =pe_peak -> 40.13 | F95: =C95*E95 -> 366.89044 | G95: =F95/px-1 -> -0.29005895 | H95: =F95/(1+r_disc)^(1.19+0) -> 327.55112
A96: C | B96: FY2027 | C96: =PL!E49 -> 9.1425476 | D96: 參考：中位數 | E96: =pe_mid -> 51.58 | F96: =C96*E96 -> 471.57261 | G96: =F96/px-1 -> -0.08749665 | H96: =F96/(1+r_disc)^(1.19+0) -> 421.0089
A97: C | B97: FY2027 | C97: =PL!E49 -> 9.1425476 | D97: 參考：75 分位 | E97: =pe_trough -> 60.47 | F97: =C97*E97 -> 552.84985 | G97: =F97/px-1 -> 0.06977661 | H97: =F97/(1+r_disc)^(1.19+0) -> 493.57131
A98: C | B98: FY2028 | C98: =PL!F49 -> 9.9142281 | D98: ="規則值（FY2028；不適用）："&E80 -> 規則值（FY2028；不適用）：谷底 | E98: =F80 -> 60.47 | F98: =C98*E98 -> 599.51337 | G98: =F98/px-1 -> 0.16007155 | H98: =F98/(1+r_disc)^(1.19+1) -> 486.574
A99: FY2028 折現年數＝1.19＋1；折現率為 In 頁 r_disc（Assumed 8–12%）。
A101: 4. What must be true：要讓 FY2027 年底價等於現價 ×（1＋報酬），需要的倍數（情境 A 的 FY2027、FY2028 EPS）
A102: FY2027 年底隱含價 ÷ 現價 | B102: 所需倍數（÷ FY2027 EPS） | C102: 所需倍數（÷ FY2028 EPS） | D102: 對照：歷史 25 分位 | E102: 對照：歷史中位數 | F102: 對照：歷史 75 分位
A103: 1 | B103: =px*A103/PL!E17 -> 56.52582 | C103: =px*A103/PL!F17 -> 49.51529 | D103: =pe_peak -> 40.13 | E103: =pe_mid -> 51.58 | F103: =pe_trough -> 60.47
A104: 1.1 | B104: =px*A104/PL!E17 -> 62.178402 | C104: =px*A104/PL!F17 -> 54.466819 | D104: =pe_peak -> 40.13 | E104: =pe_mid -> 51.58 | F104: =pe_trough -> 60.47
A105: 1.21 | B105: =px*A105/PL!E17 -> 68.396242 | C105: =px*A105/PL!F17 -> 59.913501 | D105: =pe_peak -> 40.13 | E105: =pe_mid -> 51.58 | F105: =pe_trough -> 60.47
A106: 1.5 | B106: =px*A106/PL!E17 -> 84.78873 | C106: =px*A106/PL!F17 -> 74.272935 | D106: =pe_peak -> 40.13 | E106: =pe_mid -> 51.58 | F106: =pe_trough -> 60.47
A107: 2 | B107: =px*A107/PL!E17 -> 113.05164 | C107: =px*A107/PL!F17 -> 99.03058 | D107: =pe_peak -> 40.13 | E107: =pe_mid -> 51.58 | F107: =pe_trough -> 60.47
A108: 讀法：1.00＝價格不變、1.21＝約兩年 10% 年報酬。所需倍數高於歷史中位數時，現價已預支 FY2028 以後的成長（大單放量、毛利率不被 HBM 壓縮）。
A121: 6. 十年倍數與規則值（2016–2025 年底；見頂年 25 分位、中段中位數、谷底 75 分位）
...

Sheet Recon
A1: Recon — 本模型 vs 公司指引、大單、共識、市場層。只作事後對照，不為對上數字而調整參數。公司對 2027 的說法（資料中心逾一倍、伺服器 CPU 逾 70%）與共識只放在這裡，不用於校準
A3: 項目 | B3: 對照值 | C3: 模型 A | D3: 差距 A | E3: 模型 B | F3: 差距 B | G3: 模型 C | H3: 差距 C | I3: 對照來源 | J3: 說明
A4: A. FY2026 錨點與 FY2027–28 vs 公司說法與共識（校準時未使用）
A5: FY2026 營收 vs 共識（S&P Global，stockanalysis） | B5: =cons_rev26 -> 51 | C5: =PL!D5 -> 49.643175 | D5: =C5/B5-1 -> -0.026604408 | E5: =PL!D21 -> 49.643175 | F5: =E5/B5-1 -> -0.026604408 | G5: =PL!D37 -> 49.643175 | H5: =G5/B5-1 -> -0.026604408 | I5: stockanalysis（二手） | J5: 另一來源 tickflow 47.15
A6: FY2026 EPS vs 共識 | B6: =cons_eps26 -> 7.59 | C6: =PL!D17 -> 7.3055625 | D6: =C6/B6-1 -> -0.037475297 | E6: =PL!D33 -> 7.3055625 | F6: =E6/B6-1 -> -0.037475297 | G6: =PL!D49 -> 7.3055625 | H6: =G6/B6-1 -> -0.037475297 | I6: stockanalysis（二手） | J6: tickflow 6.81
A7: FY2027 資料中心營收 vs 公司「逾一倍」（FY2026 錨點 × 2） | B7: =a26_dc*(1+g_dc27) -> 61.70294 | C7: =PL!E7 -> 56.376771 | D7: =C7/B7-1 -> -0.086319531 | E7: =PL!E23 -> 56.376771 | F7: =E7/B7-1 -> -0.086319531 | G7: =PL!E39 -> 56.376771 | H7: =G7/B7-1 -> -0.086319531 | I7: 公司 Q2 2026 法說（二手）
A8: FY2027 資料中心非 GPU 年增 vs 公司伺服器 CPU「逾 70%」（百分點） | B8: =g_srv27 -> 0.7 | C8: =PL!E84/PL!D84-1 -> 0.5 | D8: =C8-B8 -> -0.2 | E8: =PL!E132/PL!D132-1 -> 0.5 | F8: =E8-B8 -> -0.2 | G8: =PL!E180/PL!D180-1 -> 0.5 | H8: =G8-B8 -> -0.2 | I8: 同上 | J8: 非 GPU 含 DPU、FPGA；基準 50%（Assumed）
A9: FY2027 營收 vs 共識（stockanalysis「Revenue Next Year」） | B9: =cons_rev27 -> 89.17 | C9: =PL!E5 -> 75.668419 | D9: =C9/B9-1 -> -0.15141394 | E9: =PL!E21 -> 75.668419 | F9: =E9/B9-1 -> -0.15141394 | G9: =PL!E37 -> 75.668419 | H9: =G9/B9-1 -> -0.15141394 | I9: stockanalysis（二手） | J9: tickflow 四季合計 67.1
A10: FY2027 EPS vs 共識（stockanalysis 15.76） | B10: =cons_eps27 -> 15.76 | C10: =PL!E17 -> 9.1425476 | D10: =C10/B10-1 -> -0.41988911 | E10: =PL!E33 -> 9.1425476 | F10: =E10/B10-1 -> -0.41988911 | G10: =PL!E49 -> 9.1425476 | H10: =G10/B10-1 -> -0.41988911 | I10: stockanalysis（二手） | J10: 差距超過 30% 的原因見 README
A11: FY2027 EPS vs 共識（tickflow 四季合計 11.23） | B11: =cons_eps27_lo -> 11.23 | C11: =PL!E17 -> 9.1425476 | D11: =C11/B11-1 -> -0.18588178 | E11: =PL!E33 -> 9.1425476 | F11: =E11/B11-1 -> -0.18588178 | G11: =PL!E49 -> 9.1425476 | H11: =G11/B11-1 -> -0.18588178 | I11: tickflow（二手；可能較舊）
A12: FY2028 EPS vs 共識約 $20（Motley Fool，二手） | B12: =cons_eps28 -> 20 | C12: =PL!F17 -> 10.436978 | D12: =C12/B12-1 -> -0.47815109 | E12: =PL!F33 -> 11.112903 | F12: =E12/B12-1 -> -0.44435486 | G12: =PL!F49 -> 9.9142281 | H12: =G12/B12-1 -> -0.50428859 | I12: ts2.tech 轉述（二手） | J12: tickflow 四季合計 14.41
A13: FY2029 EPS vs 公司策略期間 EPS 逾 $20 | B13: =lt_eps -> 20 | C13: =PL!G17 -> 11.715798 | D13: =C13/B13-1 -> -0.4142101 | E13: =PL!G33 -> 12.515385 | F13: =E13/B13-1 -> -0.37423075 | G13: =PL!G49 -> 10.946623 | H13: =G13/B13-1 -> -0.45266883 | I13: 公司 2025-11 分析師日（二手） | J13: 公司 Q2 2026 稱將顯著超過
A14: FY2027 資料中心 GPU 營收 vs 公司「2027 年資料中心 AI 數百億美元」（下限 20） | B14: 20 | C14: =PL!E8 -> 32.829625 | D14: =C14/B14-1 -> 0.64148124 | E14: =PL!E24 -> 32.829625 | F14: =E14/B14-1 -> 0.64148124 | G14: =PL!E40 -> 32.829625 | H14: =G14/B14-1 -> 0.64148124 | I14: 公司分析師日（二手）
A15: FY2027 毛利率 vs FY2026 錨點（百分點） | B15: =a26_gp/a26_rev -> 0.55792296 | C15: =PL!E12 -> 0.49718814 | D15: =C15-B15 -> -0.060734824 | E15: =PL!E28 -> 0.49718814 | F15: =E15-B15 -> -0.060734824 | G15: =PL!E44 -> 0.49718814 | H15: =G15-B15 -> -0.060734824 | I15: Q 頁 | J15: HBM 漲價（2027 +80%，三情境相同）× 吸收比例 0.5 壓 GPU 毛利率
A16: B. 認列係數 k_rec 與每顆售價
A17: k_rec（Derived） | C17: =k_rec -> 0.67348322 | E17: =k_rec -> 0.67348322 | G17: =k_rec -> 0.67348322 | I17: 錨點 GPU ÷ 市場層顆數 × pa_amd | J17: FY2027 起沿用
A18: FY2026 隱含每顆認列售價 vs HSBC MI355X（US$K） | B18: =p355 -> 23 | C18: =p_real26 -> 20.204496 | D18: =C18/B18-1 -> -0.12154363 | E18: =p_real26 -> 20.204496 | F18: =E18/B18-1 -> -0.12154363 | G18: =p_real26 -> 20.204496 | H18: =G18/B18-1 -> -0.12154363 | I18: HSBC（finviz 轉述，Interested-party） | J18: 若 k_rec 全歸售價層；與 MI355X 價接近＝2026 的水準差主要是售價（MI355X 為主）
A19: AMD 認列顆數 FY2026 vs 市場層（百萬顆） | B19: =u_amd_26 -> 0.75 | C19: =PL!D77 -> 0.50511241 | D19: =C19/B19-1 -> -0.32651678 | E19: =PL!D125 -> 0.50511241 | F19: =E19/B19-1 -> -0.32651678 | G19: =PL!D173 -> 0.50511241 | H19: =G19/B19-1 -> -0.32651678 | I19: markets/memory UNITS
A20: FY2026 GPU 營收 vs FY2025（Assumed 6.5）年增 | C20: =PL!D97/PL!C97-1 -> 1.3312881 | E20: =PL!D145/PL!C145-1 -> 1.3312881 | G20: =PL!D193/PL!C193-1 -> 1.3312881 | I20: Q 頁（皆含 Assumed 拆分）
A21: C. 大單（Interested-party）：認列顆數換算 GW
A22: FY2027 AMD 認列顆數 ÷ 每 GW GPU 數 → 隱含 GW | B22: =gw_27-gw_26 -> 2 | C22: =PL!E77*1000000/gpw -> 3.4627099 | D22: =C22/B22-1 -> 0.73135493 | E22: =PL!E125*1000000/gpw -> 3.4627099 | F22: =E22/B22-1 -> 0.73135493 | G22: =PL!E173*1000000/gpw -> 3.4627099 | H22: =G22/B22-1 -> 0.73135493 | I22: 對照值＝In 頁假設的 2027 年新歸屬 GW | J22: 每 GW 顆數以 VR200 NVL72 為 Analogy；每顆認列售價低於市場層時，顆數高估、GW 偏高
A23: FY2028 隱含 GW | B23: =gw_28-gw_27 -> 2 | C23: =PL!F77*1000000/gpw -> 4.6169465 | D23: =C23/B23-1 -> 1.3084732 | E23: =PL!F125*1000000/gpw -> 3.6935572 | F23: =E23/B23-1 -> 0.84677859 | G23: =PL!F173*1000000/gpw -> 2.7701679 | H23: =G23/B23-1 -> 0.38508394 | I23: 同上
A24: 已宣布大單合計 GW（OpenAI 6＋Meta 6＋Anthropic 2＋Oracle 首批） | B24: =openai_gw+meta_gw+anth_gw+orcl_u*1000000/gpw -> 14.171383 | C24: =SUM(PL!E77:G77)*1000000/gpw -> 13.389145 | D24: =C24/B24-1 -> -0.055198449 | E24: =SUM(PL!E125:G125)*1000000/gpw -> 11.669332 | F24: =E24/B24-1 -> -0.17655658 | G24: =SUM(PL!E173:G173)*1000000/gpw -> 9.4185708 | H24: =G24/B24-1 -> -0.33538098 | I24: 公司、Oracle 新聞稿 | J24: 模型值＝FY2027–29 認列顆數累計換算 GW；大單為多年期、上限值
A25: 認股權證稀釋占 FY2029 股數 | C25: =PL!G112/PL!G113 -> 0.07237839 | E25: =PL!G160/PL!G161 -> 0.060822443 | G25: =PL!G208/PL!G209 -> 0.04472179 | I25: In 頁 G 節 | J25: 上限 0.32B 股（約為 FY2026 股數的 19%）
A26: D. 份額（Units 頁，模組層級）
A27: 2027 年 AMD 金額份額 | C27: =Units!D33 -> 0.06701814 | E27: =Units!D67 -> 0.06701814 | G27: =Units!D101 -> 0.06701814 | I27: accel_share（NVIDIA 模型同一套價格）
A28: 2027 年 AMD 顆數份額 | C28: =Units!D27 -> 0.063291139 | E28: =Units!D61 -> 0.063291139 | G28: =Units!D95 -> 0.063291139 | I28: 同上 | J28: 公司目標「雙位數份額」（2025 分析師日，二手）
A29: 2027 年 NVIDIA 金額份額 | C29: =Units!D32 -> 0.75128824 | E29: =Units!D66 -> 0.75128824 | G29: =Units!D100 -> 0.75128824 | I29: 同上 | J29: 與 NVIDIA 模型 Units 頁的 CY2027 值相同（同一份顆數與價格）
A30: E. 預留
A31: R4 產業部署路徑（markets/deploy_path/，尚未建立）：上線後以 AMD 資料中心 GPU 營收 ÷ 部署 GW 對照 IT capex | J31: 預留列：本版無數值

Sheet Sens
A1: Sens — 一次動一個輸入（情境 A）：對 FY2027、FY2028、FY2029 的營收、EPS 與隱含股價（十年 P/E 中位數 × EPS，與目標價同法）的影響。每個案例是一個完整的推導區塊（本頁下方，與 PL 同一引擎）
A3: 案例 | B3: 設定 | C3: FY2027 營收 | D3: FY2027 EPS | E3: FY2027 EPS 相對基準 | F3: FY2027 隱含價（中位數 P/E） | G3: 隱含價相對基準 | H3: FY2028 營收 | I3: FY2028 EPS | J3: FY2028 EPS 相對基準 | K3: FY2028 隱含價（中位數 P/E） | L3: 隱含價相對基準 | M3: FY2029 EPS | N3: FY2029 EPS 年增（對 FY2028）
A4: 基準（情境 A） | B4: PL 區塊 A | C4: =PL!E95 -> 75.668419 | D4: =PL!E114 -> 9.1425476 | E4: =D4/D$4-1 -> 0 | F4: =D4*pe_mid -> 471.57261 | G4: =F4/F$4-1 -> 0 | H4: =PL!F95 -> 93.833597 | I4: =PL!F114 -> 10.436978 | J4: =I4/I$4-1 -> 0 | K4: =I4*pe_mid -> 538.33934 | L4: =K4/K$4-1 -> 0 | M4: =PL!G114 -> 11.715798 | N4: =M4/I4-1 -> 0.12252778
A5: AMD 顆數係數 低（×0.8） | B5: FY2027 起 AMD 認列顆數 ×0.8（大單延後） | C5: =E65 -> 69.102494 | D5: =E84 -> 8.6141753 | E5: =D5/D$4-1 -> -0.057792679 | F5: =D5*pe_mid -> 444.31916 | G5: =F5/F$4-1 -> -0.057792679 | H5: =F65 -> 84.927658 | I5: =F84 -> 9.8125405 | J5: =I5/I$4-1 -> -0.059829362 | K5: =I5*pe_mid -> 506.13084 | L5: =K5/K$4-1 -> -0.059829362 | M5: =G84 -> 10.947532 | N5: =M5/I5-1 -> 0.11566744
A6: AMD 顆數係數 高（×1.2） | B6: ×1.2（OpenAI、Meta、Anthropic、Oracle 提前放量） | C6: =E113 -> 82.234344 | D6: =E132 -> 9.6709199 | E6: =D6/D$4-1 -> 0.057792679 | F6: =D6*pe_mid -> 498.82605 | G6: =F6/F$4-1 -> 0.057792679 | H6: =F113 -> 102.73954 | I6: =F132 -> 11.063325 | J6: =I6/I$4-1 -> 0.060012254 | K6: =I6*pe_mid -> 570.64629 | L6: =K6/K$4-1 -> 0.060012254 | M6: =G132 -> 12.486515 | N6: =M6/I6-1 -> 0.12864039
A7: 世代售價係數 高（隨 HBM 容量） | B7: FY2027 ×1.25、FY2028 起 ×1.5（Analogy） | C7: =E161 -> 83.875825 | D7: =E180 -> 9.803013 | E7: =D7/D$4-1 -> 0.072240849 | F7: =D7*pe_mid -> 505.63941 | G7: =F7/F$4-1 -> 0.072240849 | H7: =F161 -> 116.09845 | I7: =F180 -> 12.050906 | J7: =I7/I$4-1 -> 0.15463553 | K7: =I7*pe_mid -> 621.58573 | L7: =K7/K$4-1 -> 0.15463553 | M7: =G180 -> 13.69403 | N7: =M7/I7-1 -> 0.13634861
A8: 對照：FY2027 起每顆＝市場層 pa_amd（k_rec 只解釋 2026 售價） | B8: 世代係數＝1 ÷ k_rec | C8: =E209 -> 91.584812 | D8: =E228 -> 10.42337 | E8: =D8/D$4-1 -> 0.14009465 | F8: =D8*pe_mid -> 537.63741 | G8: =F8/F$4-1 -> 0.14009465 | H8: =F209 -> 115.4224 | I8: =F228 -> 11.957785 | J8: =I8/I$4-1 -> 0.14571329 | K8: =I8*pe_mid -> 616.78253 | L8: =K8/K$4-1 -> 0.14571329 | M8: =G228 -> 13.587275 | N8: =M8/I8-1 -> 0.13627022
A9: HBM 吸收比例 0（全額轉嫁） | B9: 吸收比例 0.0 | C9: =E257 -> 78.191299 | D9: =E276 -> 10.139103 | E9: =D9/D$4-1 -> 0.10900192 | F9: =D9*pe_mid -> 522.97492 | G9: =F9/F$4-1 -> 0.10900192 | H9: =F257 -> 97.954301 | I9: =F276 -> 12.02139 | J9: =I9/I$4-1 -> 0.15180752 | K9: =I9*pe_mid -> 620.06329 | L9: =K9/K$4-1 -> 0.15180752 | M9: =G276 -> 13.29887 | N9: =M9/I9-1 -> 0.10626725
A10: HBM 吸收比例 1（全額吸收） | B10: 吸收比例 1.0 | C10: =E305 -> 73.145539 | D10: =E324 -> 8.1459924 | E10: =D10/D$4-1 -> -0.10900192 | F10: =D10*pe_mid -> 420.17029 | G10: =F10/F$4-1 -> -0.10900192 | H10: =F305 -> 89.712893 | I10: =F324 -> 8.8535131 | J10: =I10/I$4-1 -> -0.15171681 | K10: =I10*pe_mid -> 456.66421 | L10: =K10/K$4-1 -> -0.15171681 | M10: =G324 -> 10.133292 | N10: =M10/I10-1 -> 0.14455036
A11: GPU 毛利率 低（40%） | B11: FY2026 GPU 毛利率 40%（非 GPU 毛利率重新校準） | C11: =E353 -> 75.668419 | D11: =E372 -> 8.5554099 | E11: =D11/D$4-1 -> -0.064220361 | F11: =D11*pe_mid -> 441.28804 | G11: =F11/F$4-1 -> -0.064220361 | H11: =F353 -> 93.833597 | I11: =F372 -> 9.5165165 | J11: =I11/I$4-1 -> -0.088192361 | K11: =I11*pe_mid -> 490.86192 | L11: =K11/K$4-1 -> -0.088192361 | M11: =G372 -> 10.649453 | N11: =M11/I11-1 -> 0.11904947
A12: GPU 毛利率 高（55%） | B12: 55% | C12: =E401 -> 75.668419 | D12: =E420 -> 9.4361165 | E12: =D12/D$4-1 -> 0.03211018 | F12: =D12*pe_mid -> 486.71489 | G12: =F12/F$4-1 -> 0.03211018 | H12: =F401 -> 93.833597 | I12: =F420 -> 10.897209 | J12: =I12/I$4-1 -> 0.04409618 | K12: =I12*pe_mid -> 562.07804 | L12: =K12/K$4-1 -> 0.04409618 | M12: =G420 -> 12.248971 | N12: =M12/I12-1 -> 0.12404659
A13: 資料中心 CPU 成長 低 | B13: FY2027 +30%、FY2028 +10%、FY2029 +5% | C13: =E449 -> 72.528799 | D13: =E468 -> 8.5710708 | E13: =D13/D$4-1 -> -0.062507398 | F13: =D13*pe_mid -> 442.09583 | G13: =F13/F$4-1 -> -0.062507398 | H13: =F449 -> 86.847944 | I13: =F468 -> 9.178059 | J13: =I13/I$4-1 -> -0.12062105 | K13: =I13*pe_mid -> 473.40428 | L13: =K13/K$4-1 -> -0.12062105 | M13: =G468 -> 9.9059426 | N13: =M13/I13-1 -> 0.079306922
A14: 資料中心 CPU 成長 高（公司說法） | B14: FY2027 +70%、FY2028 +40%、FY2029 +25% | C14: =E497 -> 78.808038 | D14: =E516 -> 9.7140245 | E14: =D14/D$4-1 -> 0.062507398 | F14: =D14*pe_mid -> 501.04938 | G14: =F14/F$4-1 -> 0.062507398 | H14: =F497 -> 101.76114 | I14: =F516 -> 11.871827 | J14: =I14/I$4-1 -> 0.13747741 | K14: =I14*pe_mid -> 612.34883 | L14: =K14/K$4-1 -> 0.13747741 | M14: =G516 -> 13.996876 | N14: =M14/I14-1 -> 0.17899932
A15: 營業費用率 −2pt | B15: 營業費用額外 −2% × 營收 | C15: =E545 -> 75.668419 | D15: =E564 -> 9.916202 | E15: =D15/D$4-1 -> 0.08462131 | F15: =D15*pe_mid -> 511.4777 | G15: =F15/F$4-1 -> 0.08462131 | H15: =F545 -> 93.833597 | I15: =F564 -> 11.358412 | J15: =I15/I$4-1 -> 0.088285468 | K15: =I15*pe_mid -> 585.86688 | L15: =K15/K$4-1 -> 0.088285468 | M15: =G564 -> 12.708581 | N15: =M15/I15-1 -> 0.11886959
A16: 營業費用率 +2pt | B16: +2% × 營收 | C16: =E593 -> 75.668419 | D16: =E612 -> 8.3688933 | E16: =D16/D$4-1 -> -0.08462131 | F16: =D16*pe_mid -> 431.66751 | G16: =F16/F$4-1 -> -0.08462131 | H16: =F593 -> 93.833597 | I16: =F612 -> 9.5155447 | J16: =I16/I$4-1 -> -0.088285468 | K16: =I16*pe_mid -> 490.8118 | L16: =K16/K$4-1 -> -0.088285468 | M16: =G612 -> 10.723015 | N16: =M16/I16-1 -> 0.12689446
A17: 認股權證不歸屬 | B17: OpenAI、Meta 認股權證 0 股 | C17: =E641 -> 75.668419 | D17: =E660 -> 9.2880862 | E17: =D17/D$4-1 -> 0.015918817 | F17: =D17*pe_mid -> 479.07948 | G17: =F17/F$4-1 -> 0.015918817 | H17: =F641 -> 93.833597 | I17: =F660 -> 10.930476 | J17: =I17/I$4-1 -> 0.047283616 | K17: =I17*pe_mid -> 563.79397 | L17: =K17/K$4-1 -> 0.047283616 | M17: =G660 -> 12.629932 | N17: =M17/I17-1 -> 0.15547867
A18: 認股權證歸屬加速（×1.5） | B18: 已歸屬 GW ×1.5 | C18: =E689 -> 75.668419 | D18: =E708 -> 9.0714754 | E18: =D18/D$4-1 -> -0.0077737846 | F18: =D18*pe_mid -> 467.9067 | G18: =F18/F$4-1 -> -0.0077737846 | H18: =F689 -> 93.833597 | I18: =F708 -> 10.206571 | J18: =I18/I$4-1 -> -0.022076055 | K18: =I18*pe_mid -> 526.45493 | L18: =K18/K$4-1 -> -0.022076055 | M18: =G708 -> 11.306621 | N18: =M18/I18-1 -> 0.10777857
A19: 顆數情境 B | B19: CY2028 ×0.8、CY2029 ×0.85；記憶體 B 路徑 | C19: =PL!E143 -> 75.668419 | D19: =PL!E162 -> 9.1425476 | E19: =D19/D$4-1 -> 0 | F19: =D19*pe_mid -> 471.57261 | G19: =F19/F$4-1 -> 0 | H19: =PL!F143 -> 82.808439 | I19: =PL!F162 -> 11.112903 | J19: =I19/I$4-1 -> 0.064762475 | K19: =I19*pe_mid -> 573.20352 | L19: =K19/K$4-1 -> 0.064762475 | M19: =PL!G162 -> 12.515385 | N19: =M19/I19-1 -> 0.12620305
A20: 顆數情境 C | B20: CY2028–29 ×0.6；記憶體 C 路徑 | C20: =PL!E191 -> 75.668419 | D20: =PL!E210 -> 9.1425476 | E20: =D20/D$4-1 -> 0 | F20: =D20*pe_mid -> 471.57261 | G20: =F20/F$4-1 -> 0 | H20: =PL!F191 -> 73.751126 | I20: =PL!F210 -> 9.9142281 | J20: =I20/I$4-1 -> -0.050086344 | K20: =I20*pe_mid -> 511.37589 | L20: =K20/K$4-1 -> -0.050086344 | M20: =PL!G210 -> 10.946623 | N20: =M20/I20-1 -> 0.1041327
A22: 讀法：FY2027 三情境相同；顆數、售價、吸收比例與 CPU 成長從 FY2027 起作用，情境 B、C 從 FY2028 起。隱含價欄＝EPS × 十年 non-GAAP P/E 中位數（與目標價同法），只反映 EPS 變動。
A24: 目標價參數敏感度（v0.2）：加權目標價（Val 第 0 節）一次動一個參數；PL 延伸期的收斂路徑不隨 tp_g 變動，tp_g 只改再投資率與永續成長
A25: 參數 | B25: 設定（低／高） | C25: 低：加權目標價 | D25: 低：相對基準 | E25: 高：加權目標價 | F25: 高：相對基準 | G25: 基準加權目標價
A26: tp_r ±1pt | B26: 折現率 −1pt／＋1pt | C26: =tp_w_dcf*(tp_wA*(MAX(0,Val!B7*Val!$G$7*(1-MIN(0.8,tp_g/tp_roe))/(1+(tp_r-0.01))^Val!$F$7+Val!B8*Val!$G$8*(1-MIN(0.8,tp_g/tp_roe))/(1+(tp_r-0.01))^Val!$F$8+Val!B9*Val!$G$9*(1-MIN(0.8,tp_g/tp_roe))/(1+(tp_r-0.01))^Val!$F$9+Val!B10*Val!$G$10*(1-MIN(0.8,tp_g/tp_roe))/(1+(tp_r-0.01))^Val!$F$10+Val!B11*Val!$G$11*(1-MIN(0.8,tp_g/tp_roe))/(1+(tp_r-0.01))^Val!$F$11+Val!B12*Val!$G$12*(1-MIN(0.8,tp_g/tp_roe))/(1+(tp_r-0.01))^Val!$F$12+Val!B12*(1-MIN(0.8,tp_g/tp_roe))*(1+tp_g)/((tp_r-0.01)-tp_g)/(1+(tp_r-0.01))^Val!$F$12))+tp_wB*(MAX(0,Val!C7*Val!$G$7*(1-MIN(0.8,tp_g/tp_roe))/(1+(tp_r-0.01))^Val!$F$7+Val!C8*Val!$G$8*(1-MIN(0.8,tp_g/tp_roe))/(1+(tp_r-0.01))^Val!$F$8+Val!C9*Val!$G$9*(1-MIN(0.8,tp_g/tp_roe))/(1+(tp_r-0.01))^Val!$F$9+Val!C10*Val!$G$10*(1-MIN(0.8,tp_g/tp_roe))/(1+(tp_r-0.01))^Val!$F$10+Val!C11*Val!$G$11*(1-MIN(0.8,tp_g/tp_roe))/(1+(tp_r-0.01))^Val!$F$11+Val!C12*Val!$G$12*(1-MIN(0.8,tp_g/tp_roe))/(1+(tp_r-0.01))^Val!$F$12+Val!C12*(1-MIN(0.8,tp_g/tp_roe))*(1+tp_g)/((tp_r-0.01)-tp_g)/(1+(tp_r-0.01))^Val!$F$12))+tp_wC*(MAX(0,Val!D7*Val!$G$7*(1-MIN(0.8,tp_g/tp_roe))/(1+(tp_r-0.01))^Val!$F$7+Val!D8*Val!$G$8*(1-MIN(0.8,tp_g/tp_roe))/(1+(tp_r-0.01))^Val!$F$8+Val!D9*Val!$G$9*(1-MIN(0.8,tp_g/tp_roe))/(1+(tp_r-0.01))^Val!$F$9+Val!D10*Val!$G$10*(1-MIN(0.8,tp_g/tp_roe))/(1+(tp_r-0.01))^Val!$F$10+Val!D11*Val!$G$11*(1-MIN(0.8,tp_g/tp_roe))/(1+(tp_r-0.01))^Val!$F$11+Val!D12*Val!$G$12*(1-MIN(0.8,tp_g/tp_roe))/(1+(tp_r-0.01))^Val!$F$12+Val!D12*(1-MIN(0.8,tp_g/tp_roe))*(1+tp_g)/((tp_r-0.01)-tp_g)/(1+(tp_r-0.01))^Val!$F$12)))*(1+(tp_r-0.01))+(1-tp_w_dcf)*Val!$B$36 -> 187.14286 | D26: =C26/G26-1 -> 0.08063481 | E26: =tp_w_dcf*(tp_wA*(MAX(0,Val!B7*Val!$G$7*(1-MIN(0.8,tp_g/tp_roe))/(1+(tp_r+0.01))^Val!$F$7+Val!B8*Val!$G$8*(1-MIN(0.8,tp_g/tp_roe))/(1+(tp_r+0.01))^Val!$F$8+Val!B9*Val!$G$9*(1-MIN(0.8,tp_g/tp_roe))/(1+(tp_r+0.01))^Val!$F$9+Val!B10*Val!$G$10*(1-MIN(0.8,tp_g/tp_roe))/(1+(tp_r+0.01))^Val!$F$10+Val!B11*Val!$G$11*(1-MIN(0.8,tp_g/tp_roe))/(1+(tp_r+0.01))^Val!$F$11+Val!B12*Val!$G$12*(1-MIN(0.8,tp_g/tp_roe))/(1+(tp_r+0.01))^Val!$F$12+Val!B12*(1-MIN(0.8,tp_g/tp_roe))*(1+tp_g)/((tp_r+0.01)-tp_g)/(1+(tp_r+0.01))^Val!$F$12))+tp_wB*(MAX(0,Val!C7*Val!$G$7*(1-MIN(0.8,tp_g/tp_roe))/(1+(tp_r+0.01))^Val!$F$7+Val!C8*Val!$G$8*(1-MIN(0.8,tp_g/tp_roe))/(1+(tp_r+0.01))^Val!$F$8+Val!C9*Val!$G$9*(1-MIN(0.8,tp_g/tp_roe))/(1+(tp_r+0.01))^Val!$F$9+Val!C10*Val!$G$10*(1-MIN(0.8,tp_g/tp_roe))/(1+(tp_r+0.01))^Val!$F$10+Val!C11*Val!$G$11*(1-MIN(0.8,tp_g/tp_roe))/(1+(tp_r+0.01))^Val!$F$11+Val!C12*Val!$G$12*(1-MIN(0.8,tp_g/tp_roe))/(1+(tp_r+0.01))^Val!$F$12+Val!C12*(1-MIN(0.8,tp_g/tp_roe))*(1+tp_g)/((tp_r+0.01)-tp_g)/(1+(tp_r+0.01))^Val!$F$12))+tp_wC*(MAX(0,Val!D7*Val!$G$7*(1-MIN(0.8,tp_g/tp_roe))/(1+(tp_r+0.01))^Val!$F$7+Val!D8*Val!$G$8*(1-MIN(0.8,tp_g/tp_roe))/(1+(tp_r+0.01))^Val!$F$8+Val!D9*Val!$G$9*(1-MIN(0.8,tp_g/tp_roe))/(1+(tp_r+0.01))^Val!$F$9+Val!D10*Val!$G$10*(1-MIN(0.8,tp_g/tp_roe))/(1+(tp_r+0.01))^Val!$F$10+Val!D11*Val!$G$11*(1-MIN(0.8,tp_g/tp_roe))/(1+(tp_r+0.01))^Val!$F$11+Val!D12*Val!$G$12*(1-MIN(0.8,tp_g/tp_roe))/(1+(tp_r+0.01))^Val!$F$12+Val!D12*(1-MIN(0.8,tp_g/tp_roe))*(1+tp_g)/((tp_r+0.01)-tp_g)/(1+(tp_r+0.01))^Val!$F$12)))*(1+(tp_r+0.01))+(1-tp_w_dcf)*Val!$B$36 -> 163.19812 | F26: =E26/G26-1 -> -0.057631295 | G26: =Val!$B$40 -> 173.17863
A27: tp_g ±1pt | B27: 長期成長 −1pt／＋1pt | C27: =tp_w_dcf*(tp_wA*(MAX(0,Val!B7*Val!$G$7*(1-MIN(0.8,(tp_g-0.01)/tp_roe))/(1+tp_r)^Val!$F$7+Val!B8*Val!$G$8*(1-MIN(0.8,(tp_g-0.01)/tp_roe))/(1+tp_r)^Val!$F$8+Val!B9*Val!$G$9*(1-MIN(0.8,(tp_g-0.01)/tp_roe))/(1+tp_r)^Val!$F$9+Val!B10*Val!$G$10*(1-MIN(0.8,(tp_g-0.01)/tp_roe))/(1+tp_r)^Val!$F$10+Val!B11*Val!$G$11*(1-MIN(0.8,(tp_g-0.01)/tp_roe))/(1+tp_r)^Val!$F$11+Val!B12*Val!$G$12*(1-MIN(0.8,(tp_g-0.01)/tp_roe))/(1+tp_r)^Val!$F$12+Val!B12*(1-MIN(0.8,(tp_g-0.01)/tp_roe))*(1+(tp_g-0.01))/(tp_r-(tp_g-0.01))/(1+tp_r)^Val!$F$12))+tp_wB*(MAX(0,Val!C7*Val!$G$7*(1-MIN(0.8,(tp_g-0.01)/tp_roe))/(1+tp_r)^Val!$F$7+Val!C8*Val!$G$8*(1-MIN(0.8,(tp_g-0.01)/tp_roe))/(1+tp_r)^Val!$F$8+Val!C9*Val!$G$9*(1-MIN(0.8,(tp_g-0.01)/tp_roe))/(1+tp_r)^Val!$F$9+Val!C10*Val!$G$10*(1-MIN(0.8,(tp_g-0.01)/tp_roe))/(1+tp_r)^Val!$F$10+Val!C11*Val!$G$11*(1-MIN(0.8,(tp_g-0.01)/tp_roe))/(1+tp_r)^Val!$F$11+Val!C12*Val!$G$12*(1-MIN(0.8,(tp_g-0.01)/tp_roe))/(1+tp_r)^Val!$F$12+Val!C12*(1-MIN(0.8,(tp_g-0.01)/tp_roe))*(1+(tp_g-0.01))/(tp_r-(tp_g-0.01))/(1+tp_r)^Val!$F$12))+tp_wC*(MAX(0,Val!D7*Val!$G$7*(1-MIN(0.8,(tp_g-0.01)/tp_roe))/(1+tp_r)^Val!$F$7+Val!D8*Val!$G$8*(1-MIN(0.8,(tp_g-0.01)/tp_roe))/(1+tp_r)^Val!$F$8+Val!D9*Val!$G$9*(1-MIN(0.8,(tp_g-0.01)/tp_roe))/(1+tp_r)^Val!$F$9+Val!D10*Val!$G$10*(1-MIN(0.8,(tp_g-0.01)/tp_roe))/(1+tp_r)^Val!$F$10+Val!D11*Val!$G$11*(1-MIN(0.8,(tp_g-0.01)/tp_roe))/(1+tp_r)^Val!$F$11+Val!D12*Val!$G$12*(1-MIN(0.8,(tp_g-0.01)/tp_roe))/(1+tp_r)^Val!$F$12+Val!D12*(1-MIN(0.8,(tp_g-0.01)/tp_roe))*(1+(tp_g-0.01))/(tp_r-(tp_g-0.01))/(1+tp_r)^Val!$F$12)))*(1+tp_r)+(1-tp_w_dcf)*Val!$B$36 -> 169.37116 | D27: =C27/G27-1 -> -0.021985832 | E27: =tp_w_dcf*(tp_wA*(MAX(0,Val!B7*Val!$G$7*(1-MIN(0.8,(tp_g+0.01)/tp_roe))/(1+tp_r)^Val!$F$7+Val!B8*Val!$G$8*(1-MIN(0.8,(tp_g+0.01)/tp_roe))/(1+tp_r)^Val!$F$8+Val!B9*Val!$G$9*(1-MIN(0.8,(tp_g+0.01)/tp_roe))/(1+tp_r)^Val!$F$9+Val!B10*Val!$G$10*(1-MIN(0.8,(tp_g+0.01)/tp_roe))/(1+tp_r)^Val!$F$10+Val!B11*Val!$G$11*(1-MIN(0.8,(tp_g+0.01)/tp_roe))/(1+tp_r)^Val!$F$11+Val!B12*Val!$G$12*(1-MIN(0.8,(tp_g+0.01)/tp_roe))/(1+tp_r)^Val!$F$12+Val!B12*(1-MIN(0.8,(tp_g+0.01)/tp_roe))*(1+(tp_g+0.01))/(tp_r-(tp_g+0.01))/(1+tp_r)^Val!$F$12))+tp_wB*(MAX(0,Val!C7*Val!$G$7*(1-MIN(0.8,(tp_g+0.01)/tp_roe))/(1+tp_r)^Val!$F$7+Val!C8*Val!$G$8*(1-MIN(0.8,(tp_g+0.01)/tp_roe))/(1+tp_r)^Val!$F$8+Val!C9*Val!$G$9*(1-MIN(0.8,(tp_g+0.01)/tp_roe))/(1+tp_r)^Val!$F$9+Val!C10*Val!$G$10*(1-MIN(0.8,(tp_g+0.01)/tp_roe))/(1+tp_r)^Val!$F$10+Val!C11*Val!$G$11*(1-MIN(0.8,(tp_g+0.01)/tp_roe))/(1+tp_r)^Val!$F$11+Val!C12*Val!$G$12*(1-MIN(0.8,(tp_g+0.01)/tp_roe))/(1+tp_r)^Val!$F$12+Val!C12*(1-MIN(0.8,(tp_g+0.01)/tp_roe))*(1+(tp_g+0.01))/(tp_r-(tp_g+0.01))/(1+tp_r)^Val!$F$12))+tp_wC*(MAX(0,Val!D7*Val!$G$7*(1-MIN(0.8,(tp_g+0.01)/tp_roe))/(1+tp_r)^Val!$F$7+Val!D8*Val!$G$8*(1-MIN(0.8,(tp_g+0.01)/tp_roe))/(1+tp_r)^Val!$F$8+Val!D9*Val!$G$9*(1-MIN(0.8,(tp_g+0.01)/tp_roe))/(1+tp_r)^Val!$F$9+Val!D10*Val!$G$10*(1-MIN(0.8,(tp_g+0.01)/tp_roe))/(1+tp_r)^Val!$F$10+Val!D11*Val!$G$11*(1-MIN(0.8,(tp_g+0.01)/tp_roe))/(1+tp_r)^Val!$F$11+Val!D12*Val!$G$12*(1-MIN(0.8,(tp_g+0.01)/tp_roe))/(1+tp_r)^Val!$F$12+Val!D12*(1-MIN(0.8,(tp_g+0.01)/tp_roe))*(1+(tp_g+0.01))/(tp_r-(tp_g+0.01))/(1+tp_r)^Val!$F$12)))*(1+tp_r)+(1-tp_w_dcf)*Val!$B$36 -> 178.97512 | F27: =E27/G27-1 -> 0.03347115 | G27: =Val!$B$40 -> 173.17863
A28: tp_w_dcf 0.3／0.7 | B28: DCF 權重 0.3／0.7 | C28: =0.3*(tp_wA*(MAX(0,Val!B7*Val!$G$7*(1-MIN(0.8,tp_g/tp_roe))/(1+tp_r)^Val!$F$7+Val!B8*Val!$G$8*(1-MIN(0.8,tp_g/tp_roe))/(1+tp_r)^Val!$F$8+Val!B9*Val!$G$9*(1-MIN(0.8,tp_g/tp_roe))/(1+tp_r)^Val!$F$9+Val!B10*Val!$G$10*(1-MIN(0.8,tp_g/tp_roe))/(1+tp_r)^Val!$F$10+Val!B11*Val!$G$11*(1-MIN(0.8,tp_g/tp_roe))/(1+tp_r)^Val!$F$11+Val!B12*Val!$G$12*(1-MIN(0.8,tp_g/tp_roe))/(1+tp_r)^Val!$F$12+Val!B12*(1-MIN(0.8,tp_g/tp_roe))*(1+tp_g)/(tp_r-tp_g)/(1+tp_r)^Val!$F$12))+tp_wB*(MAX(0,Val!C7*Val!$G$7*(1-MIN(0.8,tp_g/tp_roe))/(1+tp_r)^Val!$F$7+Val!C8*Val!$G$8*(1-MIN(0.8,tp_g/tp_roe))/(1+tp_r)^Val!$F$8+Val!C9*Val!$G$9*(1-MIN(0.8,tp_g/tp_roe))/(1+tp_r)^Val!$F$9+Val!C10*Val!$G$10*(1-MIN(0.8,tp_g/tp_roe))/(1+tp_r)^Val!$F$10+Val!C11*Val!$G$11*(1-MIN(0.8,tp_g/tp_roe))/(1+tp_r)^Val!$F$11+Val!C12*Val!$G$12*(1-MIN(0.8,tp_g/tp_roe))/(1+tp_r)^Val!$F$12+Val!C12*(1-MIN(0.8,tp_g/tp_roe))*(1+tp_g)/(tp_r-tp_g)/(1+tp_r)^Val!$F$12))+tp_wC*(MAX(0,Val!D7*Val!$G$7*(1-MIN(0.8,tp_g/tp_roe))/(1+tp_r)^Val!$F$7+Val!D8*Val!$G$8*(1-MIN(0.8,tp_g/tp_roe))/(1+tp_r)^Val!$F$8+Val!D9*Val!$G$9*(1-MIN(0.8,tp_g/tp_roe))/(1+tp_r)^Val!$F$9+Val!D10*Val!$G$10*(1-MIN(0.8,tp_g/tp_roe))/(1+tp_r)^Val!$F$10+Val!D11*Val!$G$11*(1-MIN(0.8,tp_g/tp_roe))/(1+tp_r)^Val!$F$11+Val!D12*Val!$G$12*(1-MIN(0.8,tp_g/tp_roe))/(1+tp_r)^Val!$F$12+Val!D12*(1-MIN(0.8,tp_g/tp_roe))*(1+tp_g)/(tp_r-tp_g)/(1+tp_r)^Val!$F$12)))*(1+tp_r)+(1-0.3)*Val!$B$36 -> 182.98355 | D28: =C28/G28-1 -> 0.056617379 | E28: =0.7*(tp_wA*(MAX(0,Val!B7*Val!$G$7*(1-MIN(0.8,tp_g/tp_roe))/(1+tp_r)^Val!$F$7+Val!B8*Val!$G$8*(1-MIN(0.8,tp_g/tp_roe))/(1+tp_r)^Val!$F$8+Val!B9*Val!$G$9*(1-MIN(0.8,tp_g/tp_roe))/(1+tp_r)^Val!$F$9+Val!B10*Val!$G$10*(1-MIN(0.8,tp_g/tp_roe))/(1+tp_r)^Val!$F$10+Val!B11*Val!$G$11*(1-MIN(0.8,tp_g/tp_roe))/(1+tp_r)^Val!$F$11+Val!B12*Val!$G$12*(1-MIN(0.8,tp_g/tp_roe))/(1+tp_r)^Val!$F$12+Val!B12*(1-MIN(0.8,tp_g/tp_roe))*(1+tp_g)/(tp_r-tp_g)/(1+tp_r)^Val!$F$12))+tp_wB*(MAX(0,Val!C7*Val!$G$7*(1-MIN(0.8,tp_g/tp_roe))/(1+tp_r)^Val!$F$7+Val!C8*Val!$G$8*(1-MIN(0.8,tp_g/tp_roe))/(1+tp_r)^Val!$F$8+Val!C9*Val!$G$9*(1-MIN(0.8,tp_g/tp_roe))/(1+tp_r)^Val!$F$9+Val!C10*Val!$G$10*(1-MIN(0.8,tp_g/tp_roe))/(1+tp_r)^Val!$F$10+Val!C11*Val!$G$11*(1-MIN(0.8,tp_g/tp_roe))/(1+tp_r)^Val!$F$11+Val!C12*Val!$G$12*(1-MIN(0.8,tp_g/tp_roe))/(1+tp_r)^Val!$F$12+Val!C12*(1-MIN(0.8,tp_g/tp_roe))*(1+tp_g)/(tp_r-tp_g)/(1+tp_r)^Val!$F$12))+tp_wC*(MAX(0,Val!D7*Val!$G$7*(1-MIN(0.8,tp_g/tp_roe))/(1+tp_r)^Val!$F$7+Val!D8*Val!$G$8*(1-MIN(0.8,tp_g/tp_roe))/(1+tp_r)^Val!$F$8+Val!D9*Val!$G$9*(1-MIN(0.8,tp_g/tp_roe))/(1+tp_r)^Val!$F$9+Val!D10*Val!$G$10*(1-MIN(0.8,tp_g/tp_roe))/(1+tp_r)^Val!$F$10+Val!D11*Val!$G$11*(1-MIN(0.8,tp_g/tp_roe))/(1+tp_r)^Val!$F$11+Val!D12*Val!$G$12*(1-MIN(0.8,tp_g/tp_roe))/(1+tp_r)^Val!$F$12+Val!D12*(1-MIN(0.8,tp_g/tp_roe))*(1+tp_g)/(tp_r-tp_g)/(1+tp_r)^Val!$F$12)))*(1+tp_r)+(1-0.7)*Val!$B$36 -> 163.37371 | F28: =E28/G28-1 -> -0.056617379 | G28: =Val!$B$40 -> 173.17863
A40: 案例區塊：AMD 顆數係數 低（×0.8）（情境 A）
A41: 項目 | B41: 單位 | C41: FY2025A | D41: FY2026 | E41: FY2027 | F41: FY2028 | G41: FY2029 | H41: 說明
A42: A. 由下而上（C 欄空白；D＝FY2026 … G＝FY2029；FY2026 由校準等於錨點，FY2027 起為驅動因子推導）
A43: AMD 認列係數（k_rec × Sens 顆數係數） | B43: x | D43: =k_rec -> 0.67348322 | E43: =k_rec*uf_lo -> 0.53878657 | F43: =k_rec*uf_lo -> 0.53878657 | G43: =k_rec*uf_lo -> 0.53878657
A44: 加速器市場金額（Units 頁，模組層級） | B44: US$B | D44: =Units!C24 -> 419.36 | E44: =Units!D24 -> 671.46 | F44: =Units!E24 -> 763.2 | G44: =Units!F24 -> 864.55
A45: AMD 金額份額（Units 頁） | B45: % | D45: =Units!C33 -> 0.053653186 | E45: =Units!D33 -> 0.06701814 | F45: =Units!E33 -> 0.078616352 | G45: =Units!F33 -> 0.079810306
A46: AMD 市場層顆數 | B46: 百萬顆 | D46: =Units!C10 -> 0.75 | E46: =Units!D10 -> 1.5 | F46: =Units!E10 -> 2 | G46: =Units!F10 -> 2.3
A47: AMD 認列顆數（市場層 × 認列係數） | B47: 百萬顆 | D47: =D46*D43 -> 0.50511241 | E47: =E46*E43 -> 0.80817986 | F47: =F46*F43 -> 1.0775731 | G47: =G46*G43 -> 1.2392091
A48: 世代售價係數（MI450／Helios） | B48: x | D48: =1 -> 1 | E48: =pg_27 -> 1 | F48: =pg_28 -> 1 | G48: =pg_29 -> 1
A49: GPU 基準營收 ＝ 市場金額 × AMD 份額 × 認列係數 × 世代係數 | B49: US$B | D49: =D44*D45*D43*D48 -> 15.153372 | E49: =E44*E45*E43*E48 -> 24.245396 | F49: =F44*F45*F43*F48 -> 32.327194 | G49: =G44*G45*G43*G48 -> 37.176274
A50: HBM 價格指數（相對 2026） | B50: x | D50: =hbm_A_26/hbm_A_26 -> 1 | E50: =hbm_A_27/hbm_A_26 -> 1.8 | F50: =hbm_A_28/hbm_A_26 -> 1.98 | G50: =hbm_A_29/hbm_A_26 -> 1.881
A51: 資料中心 GPU 營收（含 HBM 漲價轉嫁 (1−吸收比例)） | B51: US$B | D51: =D49*(1+(1-abs_mem)*hs_26*(D50-1)) -> 15.153372 | E51: =E49*(1+(1-abs_mem)*hs_26*(E50-1)) -> 26.2637 | F51: =F49*(1+(1-abs_mem)*hs_26*(F50-1)) -> 35.623758 | G51: =G49*(1+(1-abs_mem)*hs_26*(G50-1)) -> 40.584348
A52: 資料中心 GPU 成本 | B52: US$B | D52: =D49*((1-gm_gpu)+hs_26*(D50-1)) -> 7.5766862 | E52: =E49*((1-gm_gpu)+hs_26*(E50-1)) -> 16.159306 | F52: =F49*((1-gm_gpu)+hs_26*(F50-1)) -> 22.756724 | G52: =G49*((1-gm_gpu)+hs_26*(G50-1)) -> 25.404286 | H52: 基準營收 ×（非 HBM 成本＋HBM 成本占比的增加）
A53: 資料中心 GPU 毛利率 | B53: % | D53: =1-D52/D51 -> 0.5 | E53: =1-E52/E51 -> 0.3847285 | F53: =1-F52/F51 -> 0.3611925 | G53: =1-G52/G51 -> 0.37403736
A54: 資料中心非 GPU（EPYC CPU 等） | B54: US$B | D54: =a26_dcx -> 15.698098 | E54: =D54*(1+g_cpu27) -> 23.547146 | F54: =E54*(1+g_cpu28) -> 29.433933 | G54: =F54*(1+g_cpu29) -> 33.849023
A55: Client | B55: US$B | D55: =a26_cli -> 12.037318 | E55: =D55*(1+g_cli) -> 12.398438 | F55: =E55*(1+g_cli) -> 12.770391 | G55: =F55*(1+g_cli) -> 13.153502
A56: Gaming | B56: US$B | D56: =a26_gam -> 2.68308 | E56: =D56*(1+g_gam) -> 2.414772 | F56: =E56*(1+g_gam) -> 2.1732948 | G56: =F56*(1+g_gam) -> 1.9559653
A57: Embedded | B57: US$B | D57: =a26_emb -> 4.0713072 | E57: =D57*(1+g_emb) -> 4.4784379 | F57: =E57*(1+g_emb) -> 4.9262817 | G57: =F57*(1+g_emb) -> 5.4189099
A58: 非 GPU 營收合計 | B58: US$B | D58: =D54+D55+D56+D57 -> 34.489803 | E58: =E54+E55+E56+E57 -> 42.838794 | F58: =F54+F55+F56+F57 -> 49.3039 | G58: =G54+G55+G56+G57 -> 54.377401
A59: 非 GPU 毛利率（FY2026 校準：錨點毛利 − GPU 毛利；FY2027 起沿用） | B59: % | D59: =(a26_gp-(D51-D52))/D58 -> 0.58337188 | E59: =$D59 -> 0.58337188 | F59: =$D59 -> 0.58337188 | G59: =$D59 -> 0.58337188 | H59: Derived；組合內（CPU、Client、Gaming、Embedded）毛利率差異不模型化
A60: 非 GPU 成本 | B60: US$B | D60: =(1-D59)*D58 -> 14.369422 | E60: =(1-E59)*E58 -> 17.847846 | F60: =(1-F59)*F58 -> 20.541391 | G60: =(1-G59)*G58 -> 22.655154
A61: 由下而上營收合計 | B61: US$B | D61: =D51+D58 -> 49.643175 | E61: =E51+E58 -> 69.102494 | F61: =F51+F58 -> 84.927658 | G61: =G51+G58 -> 94.961749
A62: 由下而上成本合計 | B62: US$B | D62: =D52+D60 -> 21.946108 | E62: =E52+E60 -> 34.007152 | F62: =F52+F60 -> 43.298115 | G62: =G52+G60 -> 48.05944
A63: 由下而上毛利率 | B63: % | D63: =1-D62/D61 -> 0.55792296 | E63: =1-E62/E61 -> 0.50787373 | F63: =1-F62/F61 -> 0.49017651 | G63: =1-G62/G61 -> 0.49390738 | H63: FY2026 ＝ 錨點毛利率（校準恆等式，非獨立檢驗）
A64: B. 報告值（FY2025A 實績、FY2026 錨點；FY2027 起為由下而上）
A65: 營收 | B65: US$B | C65: =a25_rev -> 34.639 | D65: =a26_rev -> 49.643175 | E65: =E61 -> 69.102494 | F65: =F61 -> 84.927658 | G65: =G61 -> 94.961749
A66: Data Center | B66: US$B | C66: =a25_dc -> 16.635 | D66: =a26_dc -> 30.85147 | E66: =E51+E54 -> 49.810846 | F66: =F51+F54 -> 65.057691 | G66: =G51+G54 -> 74.433371
A67: 資料中心 GPU | B67: US$B | C67: =a25_gpu -> 6.5 | D67: =a26_gpu -> 15.153372 | E67: =E51 -> 26.2637 | F67: =F51 -> 35.623758 | G67: =G51 -> 40.584348
A68: 資料中心非 GPU（CPU 等） | B68: US$B | C68: =a25_dcx -> 10.135 | D68: =a26_dcx -> 15.698098 | E68: =E54 -> 23.547146 | F68: =F54 -> 29.433933 | G68: =G54 -> 33.849023
A69: Client＋Gaming | B69: US$B | C69: =a25_cli+a25_gam -> 14.55 | D69: =a26_cli+a26_gam -> 14.720398 | E69: =E55+E56 -> 14.81321 | F69: =F55+F56 -> 14.943685 | G69: =G55+G56 -> 15.109468
A70: Embedded | B70: US$B | C70: =a25_emb -> 3.454 | D70: =a26_emb -> 4.0713072 | E70: =E57 -> 4.4784379 | F70: =F57 -> 4.9262817 | G70: =G57 -> 5.4189099
A71: 營收年增 | B71: % | D71: =D65/C65-1 -> 0.43315844 | E71: =E65/D65-1 -> 0.39198376 | F71: =F65/E65-1 -> 0.22901003 | G71: =G65/F65-1 -> 0.11814868
A72: 毛利（non-GAAP） | B72: US$B | C72: =a25_gp -> 18.165 | D72: =a26_gp -> 27.697067 | E72: =E65-E62 -> 35.095342 | F72: =F65-F62 -> 41.629543 | G72: =G65-G62 -> 46.902309
A73: 毛利率 | B73: % | C73: =C72/C65 -> 0.5244089 | D73: =D72/D65 -> 0.55792296 | E73: =E72/E65 -> 0.50787373 | F73: =F72/F65 -> 0.49017651 | G73: =G72/G65 -> 0.49390738
A74: 營業費用（基準路徑） | B74: US$B | C74: =a25_opx -> 10.397 | D74: =a26_opx -> 14.0215 | E74: =D74*(1+MAX(g_opx_min,phi*E71)) -> 18.444896 | F74: =E74*(1+MAX(g_opx_min,phi*F71)) -> 21.844466 | G74: =F74*(1+MAX(g_opx_min,phi*G71)) -> 23.921596 | H74: 前一年 ×（1＋MAX(下限, 彈性 × 營收年增)）
A75: 營業費用 | B75: US$B | C75: =C74 -> 10.397 | D75: =D74 -> 14.0215 | E75: =E74+0*E65 -> 18.444896 | F75: =F74+0*F65 -> 21.844466 | G75: =G74+0*G65 -> 23.921596
A76: 營業利益 | B76: US$B | C76: =C72-C75 -> 7.768 | D76: =D72-D75 -> 13.675567 | E76: =E72-E75 -> 16.650445 | F76: =F72-F75 -> 19.785077 | G76: =G72-G75 -> 22.980713
A77: 營業利益率 | B77: % | C77: =C76/C65 -> 0.2242559 | D77: =D76/D65 -> 0.27547729 | E77: =E76/E65 -> 0.24095289 | F77: =F76/F65 -> 0.23296388 | G77: =G76/G65 -> 0.24199968
A78: 非營業淨額（non-GAAP） | B78: US$B | C78: =a25_oth -> 0.081 | D78: =a26_oth -> 0.25 | E78: =oth_f -> 0.2 | F78: =oth_f -> 0.2 | G78: =oth_f -> 0.2
A79: 有效稅率 | B79: % | C79: =a25_etr -> 0.12969805 | D79: =a26_etr -> 0.12988367 | E79: =tx_f -> 0.13 | F79: =tx_f -> 0.13 | G79: =tx_f -> 0.13
A80: 淨利（non-GAAP） | B80: US$B | C80: =a25_ni -> 6.831 | D80: =a26_ni -> 12.116863 | E80: =(E76+E78)*(1-E79) -> 14.659888 | F80: =(F76+F78)*(1-F79) -> 17.387017 | G80: =(G76+G78)*(1-G79) -> 20.16722
A81: 稀釋股數（不含客戶認股權證） | B81: 十億股 | C81: =a25_sh -> 1.636 | D81: =a26_sh -> 1.6585805 | E81: =D81*(1+sh_g) -> 1.6751663 | F81: =E81*(1+sh_g) -> 1.691918 | G81: =F81*(1+sh_g) -> 1.7088371
A82: 客戶認股權證稀釋股數（年中平均已歸屬 GW × 每 GW 股數） | B82: 十億股 | C82: =0 -> 0 | D82: =0 -> 0 | E82: =w_tot/w_gw*(gw_26+gw_27)/2*wf -> 0.026666667 | F82: =w_tot/w_gw*(gw_27+gw_28*um28_A)/2*wf -> 0.08 | G82: =w_tot/w_gw*(gw_28*um28_A+gw_29*um29_A)/2*wf -> 0.13333333 | H82: OpenAI、Meta 各 160M 股，依 GW 分批歸屬（Assumed 線性）；行使價 $0.01，視同全額稀釋
A83: 稀釋股數 | B83: 十億股 | C83: =C81+C82 -> 1.636 | D83: =D81+D82 -> 1.6585805 | E83: =E81+E82 -> 1.701833 | F83: =F81+F82 -> 1.771918 | G83: =G81+G82 -> 1.8421705
A84: EPS（non-GAAP） | B84: US$ | C84: =C80/C83 -> 4.1754279 | D84: =D80/D83 -> 7.3055625 | E84: =E80/E83 -> 8.6141753 | F84: =F80/F83 -> 9.8125405 | G84: =G80/G83 -> 10.947532
A85: EPS 年增 | B85: % | D85: =D84/C84-1 -> 0.74965602 | E85: =E84/D84-1 -> 0.17912554 | F85: =F84/E84-1 -> 0.13911548 | G85: =G84/F84-1 -> 0.11566744
A88: 案例區塊：AMD 顆數係數 高（×1.2）（情境 A）
A89: 項目 | B89: 單位 | C89: FY2025A | D89: FY2026 | E89: FY2027 | F89: FY2028 | G89: FY2029 | H89: 說明
A90: A. 由下而上（C 欄空白；D＝FY2026 … G＝FY2029；FY2026 由校準等於錨點，FY2027 起為驅動因子推導）
A91: AMD 認列係數（k_rec × Sens 顆數係數） | B91: x | D91: =k_rec -> 0.67348322 | E91: =k_rec*uf_hi -> 0.80817986 | F91: =k_rec*uf_hi -> 0.80817986 | G91: =k_rec*uf_hi -> 0.80817986
A92: 加速器市場金額（Units 頁，模組層級） | B92: US$B | D92: =Units!C24 -> 419.36 | E92: =Units!D24 -> 671.46 | F92: =Units!E24 -> 763.2 | G92: =Units!F24 -> 864.55
A93: AMD 金額份額（Units 頁） | B93: % | D93: =Units!C33 -> 0.053653186 | E93: =Units!D33 -> 0.06701814 | F93: =Units!E33 -> 0.078616352 | G93: =Units!F33 -> 0.079810306
A94: AMD 市場層顆數 | B94: 百萬顆 | D94: =Units!C10 -> 0.75 | E94: =Units!D10 -> 1.5 | F94: =Units!E10 -> 2 | G94: =Units!F10 -> 2.3
A95: AMD 認列顆數（市場層 × 認列係數） | B95: 百萬顆 | D95: =D94*D91 -> 0.50511241 | E95: =E94*E91 -> 1.2122698 | F95: =F94*F91 -> 1.6163597 | G95: =G94*G91 -> 1.8588137
A96: 世代售價係數（MI450／Helios） | B96: x | D96: =1 -> 1 | E96: =pg_27 -> 1 | F96: =pg_28 -> 1 | G96: =pg_29 -> 1
A97: GPU 基準營收 ＝ 市場金額 × AMD 份額 × 認列係數 × 世代係數 | B97: US$B | D97: =D92*D93*D91*D96 -> 15.153372 | E97: =E92*E93*E91*E96 -> 36.368094 | F97: =F92*F93*F91*F96 -> 48.490792 | G97: =G92*G93*G91*G96 -> 55.76441
A98: HBM 價格指數（相對 2026） | B98: x | D98: =hbm_A_26/hbm_A_26 -> 1 | E98: =hbm_A_27/hbm_A_26 -> 1.8 | F98: =hbm_A_28/hbm_A_26 -> 1.98 | G98: =hbm_A_29/hbm_A_26 -> 1.881
A99: 資料中心 GPU 營收（含 HBM 漲價轉嫁 (1−吸收比例)） | B99: US$B | D99: =D97*(1+(1-abs_mem)*hs_26*(D98-1)) -> 15.153372 | E99: =E97*(1+(1-abs_mem)*hs_26*(E98-1)) -> 39.39555 | F99: =F97*(1+(1-abs_mem)*hs_26*(F98-1)) -> 53.435636 | G99: =G97*(1+(1-abs_mem)*hs_26*(G98-1)) -> 60.876522
A100: 資料中心 GPU 成本 | B100: US$B | D100: =D97*((1-gm_gpu)+hs_26*(D98-1)) -> 7.5766862 | E100: =E97*((1-gm_gpu)+hs_26*(E98-1)) -> 24.238959 | F100: =F97*((1-gm_gpu)+hs_26*(F98-1)) -> 34.135085 | G100: =G97*((1-gm_gpu)+hs_26*(G98-1)) -> 38.106429 | H100: 基準營收 ×（非 HBM 成本＋HBM 成本占比的增加）
A101: 資料中心 GPU 毛利率 | B101: % | D101: =1-D100/D99 -> 0.5 | E101: =1-E100/E99 -> 0.3847285 | F101: =1-F100/F99 -> 0.3611925 | G101: =1-G100/G99 -> 0.37403736
A102: 資料中心非 GPU（EPYC CPU 等） | B102: US$B | D102: =a26_dcx -> 15.698098 | E102: =D102*(1+g_cpu27) -> 23.547146 | F102: =E102*(1+g_cpu28) -> 29.433933 | G102: =F102*(1+g_cpu29) -> 33.849023
A103: Client | B103: US$B | D103: =a26_cli -> 12.037318 | E103: =D103*(1+g_cli) -> 12.398438 | F103: =E103*(1+g_cli) -> 12.770391 | G103: =F103*(1+g_cli) -> 13.153502
A104: Gaming | B104: US$B | D104: =a26_gam -> 2.68308 | E104: =D104*(1+g_gam) -> 2.414772 | F104: =E104*(1+g_gam) -> 2.1732948 | G104: =F104*(1+g_gam) -> 1.9559653
A105: Embedded | B105: US$B | D105: =a26_emb -> 4.0713072 | E105: =D105*(1+g_emb) -> 4.4784379 | F105: =E105*(1+g_emb) -> 4.9262817 | G105: =F105*(1+g_emb) -> 5.4189099
A106: 非 GPU 營收合計 | B106: US$B | D106: =D102+D103+D104+D105 -> 34.489803 | E106: =E102+E103+E104+E105 -> 42.838794 | F106: =F102+F103+F104+F105 -> 49.3039 | G106: =G102+G103+G104+G105 -> 54.377401
A107: 非 GPU 毛利率（FY2026 校準：錨點毛利 − GPU 毛利；FY2027 起沿用） | B107: % | D107: =(a26_gp-(D99-D100))/D106 -> 0.58337188 | E107: =$D107 -> 0.58337188 | F107: =$D107 -> 0.58337188 | G107: =$D107 -> 0.58337188 | H107: Derived；組合內（CPU、Client、Gaming、Embedded）毛利率差異不模型化
A108: 非 GPU 成本 | B108: US$B | D108: =(1-D107)*D106 -> 14.369422 | E108: =(1-E107)*E106 -> 17.847846 | F108: =(1-F107)*F106 -> 20.541391 | G108: =(1-G107)*G106 -> 22.655154
A109: 由下而上營收合計 | B109: US$B | D109: =D99+D106 -> 49.643175 | E109: =E99+E106 -> 82.234344 | F109: =F99+F106 -> 102.73954 | G109: =G99+G106 -> 115.25392
A110: 由下而上成本合計 | B110: US$B | D110: =D100+D108 -> 21.946108 | E110: =E100+E108 -> 42.086805 | F110: =F100+F108 -> 54.676477 | G110: =G100+G108 -> 60.761583
A111: 由下而上毛利率 | B111: % | D111: =1-D110/D109 -> 0.55792296 | E111: =1-E110/E109 -> 0.4882089 | F111: =1-F110/F109 -> 0.46781465 | G111: =1-G110/G109 -> 0.47280247 | H111: FY2026 ＝ 錨點毛利率（校準恆等式，非獨立檢驗）
A112: B. 報告值（FY2025A 實績、FY2026 錨點；FY2027 起為由下而上）
A113: 營收 | B113: US$B | C113: =a25_rev -> 34.639 | D113: =a26_rev -> 49.643175 | E113: =E109 -> 82.234344 | F113: =F109 -> 102.73954 | G113: =G109 -> 115.25392
A114: Data Center | B114: US$B | C114: =a25_dc -> 16.635 | D114: =a26_dc -> 30.85147 | E114: =E99+E102 -> 62.942696 | F114: =F99+F102 -> 82.869569 | G114: =G99+G102 -> 94.725545
A115: 資料中心 GPU | B115: US$B | C115: =a25_gpu -> 6.5 | D115: =a26_gpu -> 15.153372 | E115: =E99 -> 39.39555 | F115: =F99 -> 53.435636 | G115: =G99 -> 60.876522
A116: 資料中心非 GPU（CPU 等） | B116: US$B | C116: =a25_dcx -> 10.135 | D116: =a26_dcx -> 15.698098 | E116: =E102 -> 23.547146 | F116: =F102 -> 29.433933 | G116: =G102 -> 33.849023
...

Sheet Sources
A1: 來源（公司原文＝AMD 8-K 新聞稿、簡報與 10-Q，sec.gov 已逐頁抓取；法說逐字稿只經摘要）
A2: 公司：Q2 2026 新聞稿（2026-08-04） | B2: https://www.sec.gov/Archives/edgar/data/2488/000000248826000121/q22026991.htm
A3: 公司：Q2 2026 簡報（Q3 指引明細） | B3: https://www.sec.gov/Archives/edgar/data/2488/000000248826000121/amdq22026earningsslidesf.htm
A4: 公司：Q1 2026 新聞稿（2026-05-05） | B4: https://www.sec.gov/Archives/edgar/data/2488/000000248826000072/q12026991.htm
A5: 公司：Q4 2025 與全年新聞稿（2026-02-03） | B5: https://www.sec.gov/Archives/edgar/data/2488/000000248826000014/q42025991.htm
A6: 公司：Q2 2026 10-Q（股數、買回） | B6: https://www.sec.gov/Archives/edgar/data/2488/000000248826000123/amd-20260627.htm
A7: 公司：OpenAI 6 GW 合作新聞稿（2025-10-06） | B7: https://ir.amd.com/news-events/press-releases/detail/1260/amd-and-openai-announce-strategic-partnership-to-deploy-6-gigawatts-of-amd-gpus
A8: 公司：Meta 6 GW 合作新聞稿（2026-02-24，8-K EX-99.1） | B8: https://www.sec.gov/Archives/edgar/data/2488/000000248826000045/pressreleasedatedfebruary2.htm
A9: Oracle：5 萬顆 MI450 新聞稿（2025-10-14） | B9: https://oracle.com/news/announcement/ai-world-oracle-and-amd-expand-partnership-to-help-customers-achieve-next-generation-ai-scale-2025-10-14
A10: 公司：歷年第四季新聞稿（EPS 歷史） | B10: https://www.sec.gov/Archives/edgar/data/2488/000000248824000009/q42023991final.htm；000000248822000014/q421991amd.htm；000000248818000014/q417991.htm；000000248820000006/amdq4andfy2019earningsslides.pdf
A11: 公司：Q3 2026 財報日（2026-11-03 盤後） | B11: https://finviz.com/news/399552/amd-to-report-fiscal-third-quarter-2026-financial-results
A12: 二手：MarketBeat Q2 2026 法說摘要 | B12: https://www.marketbeat.com/instant-alerts/advanced-micro-devices-q2-earnings-call-highlights-2026-08-04/
A13: 二手：platformaeronaut Q2 2026 摘要 | B13: https://transcripts.platformaeronaut.com/summaries/AMD-2Q26-AI-Summary
... A21: 二手：heygotrade（每日收盤報導） | B21: https://www.heygotrade.com/en/news/amd-amd-stock-news-october-20-2026/
A22: 市場層：markets/memory/market.py（UNITS）；tsmc、nvidia（accel_share、In 頁價格與 HBM 路徑）、markets/chip_bridge、markets/equipment 成品（本 repo）
A23: 未找到：GPU／CPU 拆分（公司不揭露）；認股權證會計處理與各批股數；MI450 每顆售價；Q2 2026 法說逐字稿原文 | B23: 未找到
A24: SemiAnalysis | B24: 未使用
