Workbook

Sheet README
A1: 健策精密（3653.TW）收支與估值模型 v0.1.1（AI 半導體 Project：電源與散熱次產業；均熱片、加強環、液冷冷板元件；樣板＝奇鋐） 2026-10-25
A2: 版本：v0.1.1（2026-10-25：上游奇鋐 v0.2.1 液冷滲透率改依情境字母（奇鋐），數值變動：本模型讀奇鋐同字母情境液冷市場，情境 A、C 的液冷冷板元件營收與 EPS 隨之變動，情境 B 不變）。v0.1（初版）。加速器顆數取自 markets/network（× tsmc 同字母情境係數）；每顆均熱片金額、健策份額為本模型 Assumed（Units 頁）；液冷市場讀奇鋐模型 avc/dist 同字母情境，健策液冷份額 Assumed。
A3: 模型命題：健策的 AI 營收＝Σ 加速器顆數（Blackwell、Rubin、Rubin Ultra、AMD、ASIC）× 每顆均熱片／上蓋金額 × 健策份額，加上液冷冷板元件（奇鋐模型液冷市場 × 健策份額）。VR 世代每顆金額約為 Blackwell 的 3 倍，2027 年可拆式上蓋再提高單價；成長主要來自每顆金額，而非顆數。
A4: 核心問題：可拆式上蓋的滲透速度與單價、以及健策在新結構下的份額，能不能支撐 FY2027–28 EPS 倍增；現價約 59 倍前瞻 P/E（同業中位數約 26 倍）隱含的路徑合不合理。
A5: 投資建議：放空（依上檔空間固定規則；加權目標價 NT$3,903、上檔空間 −35.7%、級距 −25%～−50%；見 Val 第 0 節）
A6: 重點觀察（Andy 2026-10-25 14:00；數字見 Val 第 0 節）
A7: 1. 加權目標價 NT$3,903，上檔空間 −35.7%（級距 −25%～−50%），主因是倍數而非 EPS：本模型 12 個月後前瞻 EPS 176.8 元比共識前瞻 EPS 107.7 元高 64%（EPS 因素 +64%），但同業前瞻 P/E 中位數只有 25.8x（奇鋐 27.0x、雙鴻 17.3x、Vertiv 24.5x、台達電 30.5x），市場共識目標價 7,204 元隱含 66.9x（倍數因素 +159%）；Comparable 未給健策均熱片寡占溢價，DCF（3,247 元，ROE 24% 使再投資率 16%）也低於 Comparable（4,558 元）。
A8: 2. 可拆式上蓋（TR lid）單價是 EPS 最大的公司變數：基準假設 Rubin 每顆 2027 年 US$150（2026 年 US$100），若達本國投顧假設的 US$200，FY2027 EPS 由 147.8 升到 173.7 元（+17.5%），若只有 US$110 則降到 127.1 元（−14.0%）；追蹤 4Q26 送樣與 2027 年第一季量產（大和、本國投顧）以及 3Q26 財報（2026-11-09）的毛利率是否達本模型假設的 49%。
A9: 3. 份額與液冷是次要變數：FY2026 以 AI 占比 40%（Assumed）校準出健策 NVIDIA 均熱片份額 88%；液冷冷板元件份額基準 2027 年 0.8%、2029 年 2.5%，與奇鋐模型份額（47%→42%）合計不到 50%，其餘為雙鴻、酷碼、台達電等；MCL 驗證與 MLCP 認證（市場傳言）是否轉為營收，可由 2027 年月營收與法說檢驗。
A12: 會計年度＝日曆年，FY(t)＝CY(t)，不平移。預測期 FY2027–FY2029 由驅動因子推導，FY2030–FY2032 為收斂法。金額：十億新台幣；每顆金額與液冷市場以美元計、以匯率 32.0 換算。口徑：歸屬母公司淨利（IFRS）。
A14: 驅動因子 → 推導量（全部唯讀上游，不修改）
A15: AI 均熱片：markets/network Units 頁加速器顆數 × tsmc 同字母顆數係數（＝markets/memory SCEN_UNITS）× 每顆金額（Blackwell US$35、Rubin 2026 US$100 → 2027 150 → 2028 180、Rubin Ultra 200、AMD 40 → 80、ASIC 30 → 40；Interested-party／Assumed）× 健策份額（NVIDIA 份額 FY2026 校準，非 NVIDIA＝NVIDIA × 0.4）× 份額相對值。
... A23: 已知限制：(1) AI 加速器均熱片占營收比（2026 40%）與各客戶份額未揭露，為 Assumed；(2) 每顆金額只有媒體轉述的單一來源（理財周刊），可拆式上蓋單價為 Assumed；(3) 液冷份額為新產品 Assumed；(4) 未建資本支出與折舊；(5) 共識前瞻 EPS 以 FactSet 5 月 FY2027 中位數推算，較舊；(6) 十年 P/E 2016–2020 只有一個來源；(7) 3Q26 財報後更新錨點；R4 產業部署路徑未建。

Sheet In
A1: In — 輸入（藍字；基準欄 E，低 D、高 F）。金額：十億新台幣（NT$B）；每顆均熱片金額為美元、液冷市場為十億美元；比例：%。每個輸入盡量附兩個來源（找不到者寫「未找到」）；公司原文算一個
A2: 標記：Verified／Interested-party／Analogy／Assumed／Derived；Analogy、Assumed 給低／高區間。SemiAnalysis 未使用。公司原文＝健策財報、月營收與自結損益公告（經資料商與媒體轉述）；公司的產品與出貨說法為 Interested-party；券商與媒體估計皆為 Interested-party
A3: 鍵 | B3: 項目 | C3: 單位 | D3: 低 | E3: 基準 | F3: 高 | G3: 標記 | H3: 來源1 | I3: 來源2／說明
A4: A. AI 加速器顆數（讀 markets/network Units 頁，情境 A 基準；B／C 依 tsmc 同字母顆數係數縮放）
A5: u_bw26 | B5: NVIDIA Blackwell（B200／B300） 顆數 2026（網通模型） | C5: 百萬顆 | E5: 5.4 | G5: Derived | H5: markets/network/dist/20261026_AI網通市場模型_v0.2.3.xlsx｜Units!B4:E4 | I5: 唯讀 markets/network（顆數取自 markets/memory；2029 為成長率）
A6: u_bw27 | B6: NVIDIA Blackwell（B200／B300） 顆數 2027（網通模型） | C6: 百萬顆 | E6: 2.4 | G6: Derived | H6: markets/network/dist/20261026_AI網通市場模型_v0.2.3.xlsx｜Units!B4:E4 | I6: 同上
A7: u_bw28 | B7: NVIDIA Blackwell（B200／B300） 顆數 2028（網通模型） | C7: 百萬顆 | E7: 0.5 | G7: Derived | H7: markets/network/dist/20261026_AI網通市場模型_v0.2.3.xlsx｜Units!B4:E4 | I7: 同上
A8: u_bw29 | B8: NVIDIA Blackwell（B200／B300） 顆數 2029（網通模型） | C8: 百萬顆 | E8: 0.25 | G8: Derived | H8: markets/network/dist/20261026_AI網通市場模型_v0.2.3.xlsx｜Units!B4:E4 | I8: 同上
A9: u_rb26 | B9: NVIDIA Rubin 顆數 2026（網通模型） | C9: 百萬顆 | E9: 1.7 | G9: Derived | H9: markets/network/dist/20261026_AI網通市場模型_v0.2.3.xlsx｜Units!B5:E5 | I9: 唯讀 markets/network（顆數取自 markets/memory；2029 為成長率）
A10: u_rb27 | B10: NVIDIA Rubin 顆數 2027（網通模型） | C10: 百萬顆 | E10: 7 | G10: Derived | H10: markets/network/dist/20261026_AI網通市場模型_v0.2.3.xlsx｜Units!B5:E5 | I10: 同上
A11: u_rb28 | B11: NVIDIA Rubin 顆數 2028（網通模型） | C11: 百萬顆 | E11: 7 | G11: Derived | H11: markets/network/dist/20261026_AI網通市場模型_v0.2.3.xlsx｜Units!B5:E5 | I11: 同上
A12: u_rb29 | B12: NVIDIA Rubin 顆數 2029（網通模型） | C12: 百萬顆 | E12: 8.05 | G12: Derived | H12: markets/network/dist/20261026_AI網通市場模型_v0.2.3.xlsx｜Units!B5:E5 | I12: 同上
A13: u_ru26 | B13: NVIDIA Rubin Ultra 顆數 2026（網通模型） | C13: 百萬顆 | E13: 0 | G13: Derived | H13: markets/network/dist/20261026_AI網通市場模型_v0.2.3.xlsx｜Units!B6:E6 | I13: 唯讀 markets/network（顆數取自 markets/memory；2029 為成長率）
A14: u_ru27 | B14: NVIDIA Rubin Ultra 顆數 2027（網通模型） | C14: 百萬顆 | E14: 0.3 | G14: Derived | H14: markets/network/dist/20261026_AI網通市場模型_v0.2.3.xlsx｜Units!B6:E6 | I14: 同上
A15: u_ru28 | B15: NVIDIA Rubin Ultra 顆數 2028（網通模型） | C15: 百萬顆 | E15: 2 | G15: Derived | H15: markets/network/dist/20261026_AI網通市場模型_v0.2.3.xlsx｜Units!B6:E6 | I15: 同上
A16: u_ru29 | B16: NVIDIA Rubin Ultra 顆數 2029（網通模型） | C16: 百萬顆 | E16: 2.3 | G16: Derived | H16: markets/network/dist/20261026_AI網通市場模型_v0.2.3.xlsx｜Units!B6:E6 | I16: 同上
... A42: um29_C | B42: 情境 C：2029 顆數 ÷ 基準 | C42: x | E42: 0.6 | G42: Assumed | H42: tsmc/dist/20261028_台積電個股模型_v0.4.xlsx｜In!E42 | I42: 同上
A43: fx | B43: 匯率（新台幣 ÷ 美元） | C43: NT$/US$ | D43: 30.5 | E43: 32 | F43: 33 | G43: Derived | H43: 與奇鋐、台達電、金像電模型相同（avc/dist In 頁 fx＝32.0） | I43: 鉅亨 2026-05-22 頁面 32.508（只作參考）
A44: B. 每顆加速器均熱片／上蓋／加強環金額（美元；可拆式上蓋滲透為技術替代：A 取高值＝快、C 取低值＝慢）
A45: asp_bw | B45: Blackwell（B200／B300）每顆均熱片＋加強環 | C45: US$/顆 | D45: 30 | E45: 35 | F45: 40 | G45: Interested-party | H45: 理財周刊 2026-08-05：Blackwell Ultra 均熱片約 US$30（理財周刊 2026-08-05） | I45: 加強環另計 US$5（Assumed）；第二來源：未找到
A46: asp_hp | B46: Hopper 每顆均熱片 | C46: US$/顆 | D46: 10 | E46: 15 | F46: 20 | G46: Assumed | H46: 未找到（Hopper 單價低於 Blackwell） | I46: 2027 起顆數為 0，只影響 FY2026 校準
A47: asp_vr_26 | B47: Rubin（VR200）每顆均熱片／上蓋 2026（單片式 → 可拆式三件式上蓋） | C47: US$/顆 | E47: 100 | G47: Interested-party | H47: 理財周刊 2026-08-05：Rubin 均熱片約 US$100、較前代高約六成（理財周刊 2026-08-05） | I47: —
A48: asp_vr_27 | B48: Rubin（VR200）每顆均熱片／上蓋 2027（單片式 → 可拆式三件式上蓋） | C48: US$/顆 | D48: 110 | E48: 150 | F48: 200 | G48: Assumed | H48: 經濟日報 2026-10-08：本國投顧假設 2027 年 Rubin／Rubin Ultra 800–900 萬顆採可拆式上蓋、ASP 至少 US$200（經濟日報 2026-10-08） | I48: 可拆式上蓋 2027 年第一季量產（大和、本國投顧，Interested-party）；基準＝約一半出貨採可拆式（Assumed）
A49: asp_vr_28 | B49: Rubin（VR200）每顆均熱片／上蓋 2028（單片式 → 可拆式三件式上蓋） | C49: US$/顆 | D49: 120 | E49: 180 | F49: 220 | G49: Assumed | H49: 同上 | I49: —
A50: asp_vr_29 | B50: Rubin（VR200）每顆均熱片／上蓋 2029（單片式 → 可拆式三件式上蓋） | C50: US$/顆 | D50: 120 | E50: 180 | F50: 220 | G50: Assumed | H50: 同上 | I50: —
A51: asp_ru | B51: Rubin Ultra 每顆可拆式上蓋 | C51: US$/顆 | D51: 150 | E51: 200 | F51: 250 | G51: Interested-party | H51: 理財周刊 2026-08-05：Rubin Ultra 約 US$200（理財周刊 2026-08-05） | I51: 大和 2026-10-01：Vera Rubin、Rubin Ultra 自 2027 年第一季採用（經濟日報）
A52: asp_amd_26 | B52: AMD Instinct 每顆均熱片／上蓋 2026 | C52: US$/顆 | E52: 40 | G52: Assumed | H52: 口袋學堂 2025-12-15：健策為 AMD、Intel 長期 IHS 核心供應商（口袋學堂 2025-12-15） | I52: 單價：未找到
A53: asp_amd_27 | B53: AMD Instinct 每顆均熱片／上蓋 2027 | C53: US$/顆 | D53: 45 | E53: 60 | F53: 80 | G53: Assumed | H53: 經濟日報 2026-10-08：AMD GPU 與 ASIC 採可拆式上蓋、單價更高（本國投顧） | I53: —
A54: asp_amd_28 | B54: AMD Instinct 每顆均熱片／上蓋 2028 | C54: US$/顆 | D54: 50 | E54: 80 | F54: 110 | G54: Assumed | H54: 同上 | I54: —
A55: asp_amd_29 | B55: AMD Instinct 每顆均熱片／上蓋 2029 | C55: US$/顆 | D55: 50 | E55: 80 | F55: 110 | G55: Assumed | H55: 同上 | I55: —
A56: asp_asic_26 | B56: ASIC（TPU、Trainium、其他）每顆均熱片＋加強環 2026 | C56: US$/顆 | E56: 30 | G56: Assumed | H56: 工商時報 2026-08-07：多項 ASIC 產品採用加強環（stiffener），ASP 較高（工商時報 2026-08-07） | I56: AWS Trainium3 為客戶（口袋學堂 2026-08-26）；單價：未找到
A57: asp_asic_27 | B57: ASIC（TPU、Trainium、其他）每顆均熱片＋加強環 2027 | C57: US$/顆 | D57: 30 | E57: 35 | F57: 45 | G57: Assumed | H57: 同上 | I57: —
A58: asp_asic_28 | B58: ASIC（TPU、Trainium、其他）每顆均熱片＋加強環 2028 | C58: US$/顆 | D58: 30 | E58: 40 | F58: 55 | G58: Assumed | H58: 同上 | I58: —
A59: asp_asic_29 | B59: ASIC（TPU、Trainium、其他）每顆均熱片＋加強環 2029 | C59: US$/顆 | D59: 30 | E59: 40 | F59: 55 | G59: Assumed | H59: 同上 | I59: —
A60: C. 健策份額（FY2026 以 AI 均熱片營收校準）與液冷冷板元件份額
A61: k_non | B61: 非 NVIDIA（AMD、ASIC）份額 ÷ NVIDIA 份額 | C61: x | D61: 0.25 | E61: 0.4 | F61: 0.55 | G61: Assumed | H61: 口袋學堂 2025-12-15：健策為全球前兩大 IHS 供應商（口袋學堂，Interested-party）；份額數字：未找到 | I61: ASIC 客戶多、供應商分散（Assumed）；影響 FY2026 校準出的 NVIDIA 份額
A62: rel_27 | B62: 健策均熱片份額 2027 ÷ 2026（相對值；情境 A 取高、B 基準、C 取低） | C62: x | D62: 0.92 | E62: 0.97 | F62: 1 | G62: Assumed | H62: 可拆式上蓋（TR lid）結構複雜、單價數倍，新供應商可能切入（Assumed）；4Q26 小量送樣（優分析 2026-10-05） | I62: 對手份額：未找到
A63: rel_28 | B63: 健策均熱片份額 2028 ÷ 2026（相對值；情境 A 取高、B 基準、C 取低） | C63: x | D63: 0.85 | E63: 0.93 | F63: 1 | G63: Assumed | H63: 同上 | I63: —
A64: rel_29 | B64: 健策均熱片份額 2029 ÷ 2026（相對值；情境 A 取高、B 基準、C 取低） | C64: x | D64: 0.8 | E64: 0.9 | F64: 0.98 | G64: Assumed | H64: 同上 | I64: —
A65: lcs_27 | B65: 健策液冷冷板元件份額 2027（÷ 奇鋐模型液冷市場；MCL／MLCP；A 取高、C 取低） | C65: % | D65: 0.003 | E65: 0.008 | F65: 0.015 | G65: Assumed | H65: 理財周刊 2026-08-05：微通道上蓋（MCL）已通過主要客戶驗證；市場傳 MLCP 獲 NVIDIA 認證（傳言，理財周刊 2026-08-05） | I65: 口袋學堂 2025-12-15：已出貨 AI 伺服器 GPU 水冷模組，2026 年更多型號量產（口袋學堂，Interested-party）；液冷營收：未找到
A66: lcs_28 | B66: 健策液冷冷板元件份額 2028（÷ 奇鋐模型液冷市場；MCL／MLCP；A 取高、C 取低） | C66: % | D66: 0.006 | E66: 0.015 | F66: 0.03 | G66: Assumed | H66: 同上 | I66: —
A67: lcs_29 | B67: 健策液冷冷板元件份額 2029（÷ 奇鋐模型液冷市場；MCL／MLCP；A 取高、C 取低） | C67: % | D67: 0.01 | E67: 0.025 | F67: 0.045 | G67: Assumed | H67: 同上 | I67: —
A68: lmkA_26 | B68: 情境 A：AI 液冷市場 2026（奇鋐模型，同字母情境） | C68: US$B | E68: 4.5136876 | G68: Derived | H68: avc/dist/20261025_奇鋐模型_v0.2.1.xlsx｜PL!D68:G68 | I68: 唯讀 avc/dist（機架內冷板＋分歧管；不含 CDU）；雙鴻模型（auras/）未在 main，依工作單讀奇鋐模型
A69: lmkA_27 | B69: 情境 A：AI 液冷市場 2027（奇鋐模型，同字母情境） | C69: US$B | E69: 11.561247 | G69: Derived | H69: avc/dist/20261025_奇鋐模型_v0.2.1.xlsx｜PL!D68:G68 | I69: 同上
A70: lmkA_28 | B70: 情境 A：AI 液冷市場 2028（奇鋐模型，同字母情境） | C70: US$B | E70: 17.639327 | G70: Derived | H70: avc/dist/20261025_奇鋐模型_v0.2.1.xlsx｜PL!D68:G68 | I70: 同上
A71: lmkA_29 | B71: 情境 A：AI 液冷市場 2029（奇鋐模型，同字母情境） | C71: US$B | E71: 20.093983 | G71: Derived | H71: avc/dist/20261025_奇鋐模型_v0.2.1.xlsx｜PL!D68:G68 | I71: 同上
A72: lmkB_26 | B72: 情境 B：AI 液冷市場 2026（奇鋐模型，同字母情境） | C72: US$B | E72: 4.5136876 | G72: Derived | H72: avc/dist/20261025_奇鋐模型_v0.2.1.xlsx｜PL!D109:G109 | I72: 同上
A73: lmkB_27 | B73: 情境 B：AI 液冷市場 2027（奇鋐模型，同字母情境） | C73: US$B | E73: 10.2011 | G73: Derived | H73: avc/dist/20261025_奇鋐模型_v0.2.1.xlsx｜PL!D109:G109 | I73: 同上
A74: lmkB_28 | B74: 情境 B：AI 液冷市場 2028（奇鋐模型，同字母情境） | C74: US$B | E74: 12.626045 | G74: Derived | H74: avc/dist/20261025_奇鋐模型_v0.2.1.xlsx｜PL!D109:G109 | I74: 同上
A75: lmkB_29 | B75: 情境 B：AI 液冷市場 2029（奇鋐模型，同字母情境） | C75: US$B | E75: 16.180944 | G75: Derived | H75: avc/dist/20261025_奇鋐模型_v0.2.1.xlsx｜PL!D109:G109 | I75: 同上
A76: lmkC_26 | B76: 情境 C：AI 液冷市場 2026（奇鋐模型，同字母情境） | C76: US$B | E76: 4.5136876 | G76: Derived | H76: avc/dist/20261025_奇鋐模型_v0.2.1.xlsx｜PL!D150:G150 | I76: 同上
A77: lmkC_27 | B77: 情境 C：AI 液冷市場 2027（奇鋐模型，同字母情境） | C77: US$B | E77: 8.1608803 | G77: Derived | H77: avc/dist/20261025_奇鋐模型_v0.2.1.xlsx｜PL!D150:G150 | I77: 同上
A78: lmkC_28 | B78: 情境 C：AI 液冷市場 2028（奇鋐模型，同字母情境） | C78: US$B | E78: 7.7984394 | G78: Derived | H78: avc/dist/20261025_奇鋐模型_v0.2.1.xlsx｜PL!D150:G150 | I78: 同上
A79: lmkC_29 | B79: 情境 C：AI 液冷市場 2029（奇鋐模型，同字母情境） | C79: US$B | E79: 9.5182023 | G79: Derived | H79: avc/dist/20261025_奇鋐模型_v0.2.1.xlsx｜PL!D150:G150 | I79: 同上
... A91: avshC_29 | B91: 情境 C：奇鋐液冷有效份額 2029（奇鋐模型；份額合計檢查用） | C91: % | E91: 0.42408849 | G91: Derived | H91: avc/dist/20261025_奇鋐模型_v0.2.1.xlsx｜PL!D154:G154 | I91: 同上
A92: D. 營收結構錨點（公司與媒體揭露比例 × 營收）
A93: th_25 | B93: 2025 年散熱產品（均熱片、ILM、車用水冷模組等）÷ 營收 | C93: % | E93: 0.726 | G93: Interested-party | H93: 口袋學堂 2026-08-26：2025 年散熱產品占營收 72.6%（口袋學堂 2026-08-26） | I93: 第二來源：未找到
A94: th_26 | B94: 2026 年散熱產品 ÷ 營收 | C94: % | D94: 0.66 | E94: 0.75 | F94: 0.8 | G94: Interested-party | H94: 口袋學堂 2026-08-26：2Q26 散熱產品約 77% | I94: 理財周刊 2026-08-05：1H26 散熱 65.54%、導線架 13.64%（同文另稱約七成，口徑不一）；本國投顧：均熱片維持八成以上（經濟日報 2026-10-08）
A95: ai_25 | B95: 2025 年 AI 加速器均熱片（GPU、ASIC）÷ 營收 | C95: % | D95: 0.22 | E95: 0.3 | F95: 0.38 | G95: Assumed | H95: 未找到（公司未拆 AI 與伺服器 CPU、PC 均熱片） | I95: 只影響 FY2025 拆分顯示
A96: ai_26 | B96: 2026 年 AI 加速器均熱片 ÷ 營收 | C96: % | D96: 0.32 | E96: 0.4 | F96: 0.48 | G96: Assumed | H96: 未找到；推論：VR 均熱片 2026 年約 200 萬片 × US$100（工商時報 2026-08-07）＋Blackwell 約 500 萬顆 × US$35 ≈ US$0.37B ≈ 營收的 36% | I96: 其餘散熱＝伺服器與 PC CPU 均熱片、交換器加強環、ILM、車用水冷；影響 FY2026 份額校準
A97: g_oth_27 | B97: 其他散熱營收年增 2027（CPU 均熱片、交換器加強環、CPO、ILM、車用水冷） | C97: % | D97: 0.05 | E97: 0.12 | F97: 0.2 | G97: Assumed | H97: 工商時報 2026-08-07：Spectrum-X、Quantum-X 交換器加強環 2027 年貢獻（工商時報 2026-08-07） | I97: 經濟日報 2026-10-08：CPO 均熱片、Intel CPU 載具與插槽成長（本國投顧）
A98: g_oth_28 | B98: 其他散熱營收年增 2028（CPU 均熱片、交換器加強環、CPO、ILM、車用水冷） | C98: % | D98: 0.03 | E98: 0.1 | F98: 0.15 | G98: Assumed | H98: 同上 | I98: —
A99: g_oth_29 | B99: 其他散熱營收年增 2029（CPU 均熱片、交換器加強環、CPO、ILM、車用水冷） | C99: % | D99: 0.02 | E99: 0.08 | F99: 0.12 | G99: Assumed | H99: 同上 | I99: —
A100: g_lf_27 | B100: 導線架、精密沖壓與其他營收年增 2027 | C100: % | D100: -0.05 | E100: 0.03 | F100: 0.08 | G100: Assumed | H100: 800V 車用平台帶動導線架需求（口袋學堂，Interested-party） | I100: —
A101: g_lf_28 | B101: 導線架、精密沖壓與其他營收年增 2028 | C101: % | D101: -0.05 | E101: 0.03 | F101: 0.08 | G101: Assumed | H101: 同上 | I101: —
A102: g_lf_29 | B102: 導線架、精密沖壓與其他營收年增 2029 | C102: % | D102: -0.05 | E102: 0.03 | F102: 0.08 | G102: Assumed | H102: 同上 | I102: —
A103: E. 毛利率
A104: d_ai | B104: AI 加速器均熱片毛利率高於其他營收的幅度 | C104: pt | D104: 0.06 | E104: 0.12 | F104: 0.18 | G104: Assumed | H104: 產品別毛利率：未找到；毛利率 FY2025 41.6% → 1Q26 41.8% → 2Q26 46.8%（stockanalysis），同期 VR 均熱片出貨 | I104: 大和：3Q26 毛利率約 51%；券商：2027–28 年毛利率逾 50%（Interested-party）
A105: F. FY2026 錨點（1H26 財報＋3Q26 月營收實績＋假設；3Q26 財報預計 2026-11-09，截至 2026-10-25 尚未公布）
A106: q3_rev | B106: 3Q26 營收（7–9 月月營收合計，實績） | C106: NT$B | E106: =3.213+3.226+3.054 -> 9.493 | G106: Verified | H106: technews 2026-10-08：9 月 30.54 億、前 9 月 220.73 億（− 1H26 125.80 ＝ 94.93） | I106: technews 2026-08-07：7 月 32.13 億；8 月 32.26 億（財報狗）
A107: q_gm | B107: 3Q、4Q26 毛利率 | C107: % | D107: 0.47 | E107: 0.49 | F107: 0.51 | G107: Assumed | H107: 2Q26 46.81%（公司）；8 月自結淨利 10.79 億 ÷ 營收 32.26 億＝33.4%（優分析 2026-10-05），與本假設推得的 3Q 淨利率相近 | I107: 經濟日報 2026-10-01（大和）：大和估 3Q26 毛利率約 51%、營益率至 42%（Interested-party）
A108: q_opx | B108: 3Q、4Q26 營業費用 ÷ 營收 | C108: % | D108: 0.08 | E108: 0.085 | F108: 0.09 | G108: Derived | H108: 1Q26 9.8%、2Q26 9.0%（HiStock：毛利 − 營業利益） | I108: 營收放大、費用率下降（Assumed）
A109: q4g | B109: 4Q26 營收季增 | C109: % | D109: 0.03 | E109: 0.1 | F109: 0.15 | G109: Interested-party | H109: 經濟日報 2026-10-08：本國投顧估 4Q26 季增約 10% | I109: VR 均熱片 4Q 月出貨 50–60 萬片（工商時報 2026-08-07）
A110: q_nop | B110: 3Q、4Q26 業外收益（每季） | C110: NT$B | D110: -0.1 | E110: 0.08 | F110: 0.2 | G110: Derived | H110: 1Q26 +0.079、2Q26 +0.092（HiStock：稅前 − 營業利益） | I110: FY2025 −0.37～+0.24（匯兌）
A111: q_nir | B111: 3Q、4Q26 歸屬母公司淨利 ÷ 稅前 | C111: % | D111: 0.78 | E111: 0.805 | F111: 0.82 | G111: Derived | H111: 1H26：歸母淨利 37.16 ÷ 稅前 46.16＝0.805（stockanalysis、HiStock） | I111: FY2025：52.77 ÷ 66.07＝0.799
A112: q_sh | B112: 股數（十億股；EPS 換算） | C112: 十億股 | E112: =3.716/25.33 -> 0.14670351 | G112: Derived | H112: 1H26 歸母淨利 37.16 億 ÷ EPS 25.33（HiStock） | I112: stockanalysis 個股頁：流通股數 146.73 百萬股
A113: G. 營業費用、業外、稅與股數（FY2027 起）
A114: phi | B114: 營業費用成長對營收成長的彈性 | C114: x | D114: 0.4 | E114: 0.6 | F114: 0.9 | G114: Assumed | H114: FY2026 錨點實測約 0.8（Q 頁） | I114: 營收倍增期費用率下降（Assumed）
A115: opx_adj | B115: 營業費用額外占營收比（Sens 用；基準 0） | C115: pt | D115: -0.02 | E115: 0 | F115: 0.02 | G115: Assumed | H115: 無 | I115: Sens 用 ±2 個百分點
A116: nop_f | B116: 業外收益（每年） | C116: NT$B | D116: -0.5 | E116: 0.3 | F116: 1 | G116: Assumed | H116: FY2025 +0.11、1H26 +0.17（HiStock） | I116: 匯兌損益波動大
A117: nir_f | B117: 歸屬母公司淨利 ÷ 稅前 | C117: % | D117: 0.78 | E117: 0.805 | F117: 0.82 | G117: Derived | H117: 同 q_nir | I117: —
A118: sh_g | B118: 股數年變動 | C118: % | D118: 0 | E118: 0 | F118: 0.01 | G118: Assumed | H118: FY2025 推導 0.1436 → 1H26 0.1467 十億股（公司 EPS 與淨利） | I118: 可轉債、現金增資：未找到
A119: mf | B119: AI 部署係數（Sens 用；FY2027 起顆數 ×） | C119: x | D119: 0.8 | E119: 1 | F119: 1.2 | G119: Assumed | H119: 網通模型 2027 顆數 23.7M（2026 15.2M） | I119: ±20%
A120: H. 共識、券商（只作 Recon 對帳，不作校準）
A121: cons_rev26 | B121: 共識 FY2026 營收（stockanalysis，7 家） | C121: NT$B | E121: 32.7 | G121: Interested-party | H121: stockanalysis forecast 頁（頁面 2026-10-22；區間 32.4–33.3B） | I121: —
A122: cons_eps26 | B122: 共識 FY2026 EPS（stockanalysis，7 家） | C122: NT$ | E122: 69.96 | G122: Interested-party | H122: stockanalysis forecast 頁（區間 68.78–71.65） | I122: —
A123: fs_rev26 | B123: FactSet 中位數 FY2026 營收（2026-05-22，9 家） | C123: NT$B | E123: 28.94 | G123: Interested-party | H123: 鉅亨 2026-05-22（FactSet） | I123: 較舊（5 月）；較新 FactSet 調查：未找到
A124: fs_eps26 | B124: FactSet 中位數 FY2026 EPS（2026-05-22） | C124: NT$ | E124: 57.77 | G124: Interested-party | H124: 鉅亨 2026-05-22（FactSet） | I124: 平均 59.33／121.01／191.02
A125: fs_rev27 | B125: FactSet 中位數 FY2027 營收（2026-05-22，9 家） | C125: NT$B | E125: 51.836 | G125: Interested-party | H125: 鉅亨 2026-05-22（FactSet） | I125: —
A126: fs_eps27 | B126: FactSet 中位數 FY2027 EPS（2026-05-22） | C126: NT$ | E126: 117.18 | G126: Interested-party | H126: 鉅亨 2026-05-22（FactSet） | I126: —
A127: fs_rev28 | B127: FactSet 中位數 FY2028 營收（2026-05-22，9 家） | C127: NT$B | E127: 80.811 | G127: Interested-party | H127: 鉅亨 2026-05-22（FactSet） | I127: —
A128: fs_eps28 | B128: FactSet 中位數 FY2028 EPS（2026-05-22） | C128: NT$ | E128: 204.29 | G128: Interested-party | H128: 鉅亨 2026-05-22（FactSet） | I128: —
A129: ab_eps26 | B129: 亞系券商 FY2026 EPS（2026-08 下旬） | C129: NT$ | E129: 71 | G129: Interested-party | H129: 口袋學堂 2026-08-26（口袋學堂 2026-08-26 轉引，券商名未載明） | I129: —
A130: ab_eps27 | B130: 亞系券商 FY2027 EPS（2026-08 下旬） | C130: NT$ | E130: 151 | G130: Interested-party | H130: 口袋學堂 2026-08-26（口袋學堂 2026-08-26 轉引，券商名未載明） | I130: —
A131: ab_eps28 | B131: 亞系券商 FY2028 EPS（2026-08 下旬） | C131: NT$ | E131: 262 | G131: Interested-party | H131: 口袋學堂 2026-08-26（口袋學堂 2026-08-26 轉引，券商名未載明） | I131: —
A132: mw_eps27 | B132: 分析師 FY2027 EPS（理財周刊 2026-08-05） | C132: NT$ | E132: 123.83 | G132: Interested-party | H132: 理財周刊 2026-08-05 | I132: 2026 年 60.98
... A136: ld_g27 | B136: 本國投顧 FY2027 營收年增（2026-10-08） | C136: % | E136: 1.47 | G136: Interested-party | H136: 經濟日報 2026-10-08 | I136: 大和：2027–28 EPS 高於 Bloomberg 共識 14–21%
A137: I. 價格與估值
A138: px | B138: 股價（2026-10-22 收盤，臺灣證交所） | C138: NT$ | E138: 6070 | G138: Interested-party | H138: 財報狗：10/22 收盤 6,070（−465、−7.12%） | I138: stockanalysis 個股與 forecast 頁 2026-10-22 價格 6,070；10-23 收盤：未找到
A139: pe_ttm | B139: 近 12 月 P/E（財報狗，10-22） | C139: x | E139: 136.99 | G139: Interested-party | H139: 財報狗 | I139: 近 4 季 EPS 44.31
...

Sheet Q
A1: Q — 實績與 FY2026 錨點（十億新台幣；EPS 為新台幣；股數為十億股）。藍字＝輸入；黑字＝公式。實績取自健策財報與月營收公告（經 stockanalysis、HiStock、technews 轉述）
A2: FY2026 錨點＝1H26 財報＋3Q26 月營收實績（7–9 月 94.93 億）＋假設（3Q、4Q 毛利率、營業費用率、業外、淨利 ÷ 稅前；4Q 營收＝3Q × (1＋季增)）。3Q26 財報預計 2026-11-09（stockanalysis），截至 2026-10-25 尚未公布；公司每月公告自結損益（8 月淨利 10.79 億、EPS 7.35），7、9 月自結數：未找到
A3: 項目 | B3: FY2025A | C3: 1H26（實績） | D3: 3Q26（營收實績） | E3: 4Q26（模型） | F3: FY2026 錨點 | G3: 標記 | H3: 來源1 | I3: 來源2／說明
A4: 營收 | B4: 20.276 | C4: =5.305+7.275 -> 12.58 | D4: =q3_rev -> 9.493 | E4: =D4*(1+q4g) -> 10.4423 | F4: =SUM(C4:E4) -> 32.5153 | G4: Verified／Interested-party（4Q 季增） | H4: stockanalysis 季度損益（stockanalysis 季度損益）：FY2025 營收 202.76 億、毛利 84.34 億、營業利益 64.98 億、歸母淨利 52.77 億；1Q26、2Q26 各季 | I4: 1H26 125.80 億（口袋學堂、理財周刊同值）
A5: 毛利 | B5: 8.434 | C5: =2.217+3.405 -> 5.622 | D5: =D4*q_gm -> 4.65157 | E5: =E4*q_gm -> 5.116727 | F5: =SUM(C5:E5) -> 15.390297 | G5: Verified／Assumed | H5: stockanalysis 季度損益（stockanalysis 季度損益）：FY2025 營收 202.76 億、毛利 84.34 億、營業利益 64.98 億、歸母淨利 52.77 億；1Q26、2Q26 各季 | I5: HiStock 季度損益（HiStock 損益表）：營收、毛利、營業利益、稅前、稅後同值（稅後含非控制權益）
A6: 毛利率 | B6: =B5/B4 -> 0.41595976 | C6: =C5/C4 -> 0.44689984 | D6: =D5/D4 -> 0.49 | E6: =E5/E4 -> 0.49 | F6: =F5/F4 -> 0.47332477 | G6: Derived | H6: — | I6: FY2025 41.6%；1Q26 41.8%、2Q26 46.81%、1H26 44.69%（口袋學堂）
A7: 營業費用 | B7: =B5-B8 -> 1.936 | C7: =C5-C8 -> 1.176 | D7: =D4*q_opx -> 0.806905 | E7: =E4*q_opx -> 0.8875955 | F7: =SUM(C7:E7) -> 2.8705005 | G7: Derived（毛利 − 營業利益）／Assumed | H7: stockanalysis 季度損益（stockanalysis 季度損益）：FY2025 營收 202.76 億、毛利 84.34 億、營業利益 64.98 億、歸母淨利 52.77 億；1Q26、2Q26 各季 | I7: HiStock 季度損益（HiStock 損益表）：營收、毛利、營業利益、稅前、稅後同值（稅後含非控制權益）
A8: 營業利益 | B8: 6.498 | C8: =1.697+2.749 -> 4.446 | D8: =D5-D7 -> 3.844665 | E8: =E5-E7 -> 4.2291315 | F8: =SUM(C8:E8) -> 12.519796 | G8: Verified | H8: stockanalysis 季度損益（stockanalysis 季度損益）：FY2025 營收 202.76 億、毛利 84.34 億、營業利益 64.98 億、歸母淨利 52.77 億；1Q26、2Q26 各季 | I8: 2Q26 營益率 37.8%（口袋學堂）
A9: 營業利益率 | B9: =B8/B4 -> 0.32047741 | C9: =C8/C4 -> 0.35341812 | D9: =D8/D4 -> 0.405 | E9: =E8/E4 -> 0.405 | F9: =F8/F4 -> 0.38504324 | G9: Derived | H9: — | I9: —
A10: 業外收益 | B10: =B11-B8 -> 0.109 | C10: =C11-C8 -> 0.1705 | D10: =q_nop -> 0.08 | E10: =q_nop -> 0.08 | F10: =SUM(C10:E10) -> 0.3305 | G10: Derived | H10: stockanalysis 季度損益（stockanalysis 季度損益）：FY2025 營收 202.76 億、毛利 84.34 億、營業利益 64.98 億、歸母淨利 52.77 億；1Q26、2Q26 各季 | I10: HiStock 季度損益（HiStock 損益表）：營收、毛利、營業利益、稅前、稅後同值（稅後含非控制權益）
A11: 稅前利益 | B11: =1.7405+1.3271+1.7227+1.8167 -> 6.607 | C11: =1.7756+2.8409 -> 4.6165 | D11: =D8+D10 -> 3.924665 | E11: =E8+E10 -> 4.3091315 | F11: =SUM(C11:E11) -> 12.850297 | G11: Verified（HiStock 各季）／Derived | H11: HiStock 損益表 | I11: 各季稅前：1Q25 17.41、2Q25 13.27、3Q25 17.23、4Q25 18.17、1Q26 17.76、2Q26 28.41 億
A12: 歸屬母公司淨利 | B12: 5.277 | C12: =1.398+2.318 -> 3.716 | D12: =D11*q_nir -> 3.1593553 | E12: =E11*q_nir -> 3.4688509 | F12: =SUM(C12:E12) -> 10.344206 | G12: Verified／Derived（3Q、4Q） | H12: stockanalysis 季度損益（stockanalysis 季度損益）：FY2025 營收 202.76 億、毛利 84.34 億、營業利益 64.98 億、歸母淨利 52.77 億；1Q26、2Q26 各季 | I12: 稅後（含非控制權益）FY2025 53.10、1H26 37.33 億（HiStock）
A13: 淨利 ÷ 稅前（含稅與非控制權益） | B13: =B12/B11 -> 0.79869835 | C13: =C12/C11 -> 0.80493881 | D13: =D12/D11 -> 0.805 | E13: =E12/E11 -> 0.805 | F13: =F12/F11 -> 0.80497802 | G13: Derived | H13: — | I13: —
A14: 股數（十億股） | B14: =5.277/36.75 -> 0.14359184 | C14: =q_sh -> 0.14670351 | D14: =q_sh -> 0.14670351 | E14: =q_sh -> 0.14670351 | F14: =q_sh -> 0.14670351 | G14: Derived | H14: stockanalysis 季度損益（stockanalysis 季度損益）：FY2025 營收 202.76 億、毛利 84.34 億、營業利益 64.98 億、歸母淨利 52.77 億；1Q26、2Q26 各季 | I14: 歸母淨利 ÷ 公司 EPS
A15: EPS | B15: =B12/B14 -> 36.75 | C15: =C12/C14 -> 25.33 | D15: =D12/D14 -> 21.535649 | E15: =E12/E14 -> 23.645315 | F15: =F12/F14 -> 70.510964 | G15: Derived | H15: 淨利 ÷ 股數 | I15: —
A16: 公司揭露 EPS | B16: 36.75 | C16: 25.33 | G16: Verified | H16: HiStock 每股盈餘 | I16: FY2025 36.75（HiStock、Goodinfo、聚財網；stockanalysis 列 36.14，口徑未載明）；1Q26 9.53、2Q26 15.80
A17: AI 加速器均熱片營收（＝營收 × AI 占比） | B17: =B4*ai_25 -> 6.0828 | F17: =F4*ai_26 -> 13.00612 | G17: Assumed／Interested-party | H17: In 頁 D 節 | I17: 各產品季度金額未揭露：未找到
A18: 其他散熱營收（＝營收 ×（散熱占比 − AI 占比）） | B18: =B4*(th_25-ai_25) -> 8.637576 | F18: =F4*(th_26-ai_26) -> 11.380355 | G18: Assumed／Interested-party | H18: In 頁 D 節 | I18: —
A19: 導線架、精密沖壓與其他（＝營收 ×（1 − 散熱占比）） | B19: =B4*(1-th_25) -> 5.555624 | F19: =F4*(1-th_26) -> 8.128825 | G19: Assumed／Interested-party | H19: In 頁 D 節 | I19: —
A22: FY2026 錨點的檢查（參考；校準未使用券商數字）
A23: FY2026 營收年增 | B23: =F4/B4-1 -> 0.60363484
A24: FY2026 營業費用年增 | B24: =F7/B7-1 -> 0.48269654
A25: 營業費用彈性（營業費用年增 ÷ 營收年增；In 頁 phi 的參考） | B25: =B24/B23 -> 0.7996499
A26: FY2026 營收 ÷ 共識（stockanalysis）− 1 | B26: =F4/cons_rev26-1 -> -0.005648318
A27: FY2026 EPS ÷ 共識（stockanalysis）− 1 | B27: =F15/cons_eps26-1 -> 0.007875416
A28: 3Q26 淨利率（模型）vs 8 月自結淨利率 33.4%（百分點） | B28: =D12/D4-10.79/32.26 -> -0.0016609857

Sheet Units
A1: Units — AI 加速器均熱片市場（顆數 × 每顆金額）、健策份額與每顆營收；液冷冷板元件份額與奇鋐份額合計（情境 B）。顆數取自 markets/network（× tsmc 同字母係數）；液冷市場取自奇鋐模型 avc/dist（同字母情境）
A3: 項目 | B3: 單位 | C3: CY2026 | D3: CY2027 | E3: CY2028 | F3: CY2029 | G3: 說明
A4: AI 加速器顆數合計（情境 B） | B4: 百萬顆 | C4: =PL!D110+PL!D111+PL!D112+PL!D113+PL!D114+PL!D115 -> 15.2 | D4: =PL!E110+PL!E111+PL!E112+PL!E113+PL!E114+PL!E115 -> 23.7 | E4: =PL!F110+PL!F111+PL!F112+PL!F113+PL!F114+PL!F115 -> 21.2 | F4: =PL!G110+PL!G111+PL!G112+PL!G113+PL!G114+PL!G115 -> 25.6275 | G4: markets/network Units × tsmc 係數 B
A5: 其中 NVIDIA（Blackwell、Hopper、Rubin、Rubin Ultra） | B5: 百萬顆 | C5: =PL!D110+PL!D111+PL!D112+PL!D113 -> 7.6 | D5: =PL!E110+PL!E111+PL!E112+PL!E113 -> 9.7 | E5: =PL!F110+PL!F111+PL!F112+PL!F113 -> 7.6 | F5: =PL!G110+PL!G111+PL!G112+PL!G113 -> 9.01
A6: Rubin 每顆均熱片／上蓋 | B6: US$/顆 | C6: =PL!D116 -> 100 | D6: =PL!E116 -> 150 | E6: =PL!F116 -> 180 | F6: =PL!G116 -> 180 | G6: 2027 起可拆式上蓋滲透（In 頁 B 節）
A7: NVIDIA 加速器均熱片市場 | B7: US$B | C7: =PL!D119 -> 0.3665 | D7: =PL!E119 -> 1.194 | E7: =PL!F119 -> 1.342 | F7: =PL!G119 -> 1.6300875
A8: 非 NVIDIA（AMD、ASIC）均熱片市場 | B8: US$B | C8: =PL!D120 -> 0.2355 | D8: =PL!E120 -> 0.5275 | E8: =PL!F120 -> 0.608 | F8: =PL!G120 -> 0.7429
A9: 市場平均每顆金額 | B9: US$/顆 | C9: =PL!D121*1000/C4 -> 39.605263 | D9: =PL!E121*1000/D4 -> 72.637131 | E9: =PL!F121*1000/E4 -> 91.981132 | F9: =PL!G121*1000/F4 -> 92.595357
A10: 健策 NVIDIA 份額 | B10: % | C10: =PL!D124 -> 0.88222542 | D10: =PL!E124 -> 0.85575866 | E10: =PL!F124 -> 0.82046964 | F10: =PL!G124 -> 0.79400288 | G10: FY2026 以 AI 均熱片營收校準
A11: 健策非 NVIDIA 份額 | B11: % | C11: =PL!D125 -> 0.35289017 | D11: =PL!E125 -> 0.34230346 | E11: =PL!F125 -> 0.32818786 | F11: =PL!G125 -> 0.31760115 | G11: ＝ NVIDIA 份額 × k_non
A12: 健策 AI 加速器均熱片營收 | B12: US$B | C12: =PL!D126/fx -> 0.40644125 | D12: =PL!E126/fx -> 1.2023409 | E12: =PL!F126/fx -> 1.3006085 | F12: =PL!G126/fx -> 1.5302401
A13: 健策 AI 均熱片 ÷ 市場合計 | B13: % | C13: =PL!D126/fx/PL!D121 -> 0.67515158 | D13: =PL!E126/fx/PL!E121 -> 0.69842632 | E13: =PL!F126/fx/PL!F121 -> 0.6669787 | F13: =PL!G126/fx/PL!G121 -> 0.64485804
A14: 其他廠商均熱片（市場 − 健策） | B14: US$B | C14: =PL!D121-PL!D126/fx -> 0.19555875 | D14: =PL!E121-PL!E126/fx -> 0.51915909 | E14: =PL!F121-PL!F126/fx -> 0.64939153 | F14: =PL!G121-PL!G126/fx -> 0.84274744 | G14: 其他 IHS 供應商；奇鋐、雙鴻不以均熱片為主，與本項無重疊
A15: AI 液冷市場（奇鋐模型 B） | B15: US$B | C15: =PL!D128 -> 4.5136876 | D15: =PL!E128 -> 10.2011 | E15: =PL!F128 -> 12.626045 | F15: =PL!G128 -> 16.180944 | G15: 機架內冷板＋分歧管
A16: 健策液冷份額 | B16: % | C16: =PL!D129 -> 0 | D16: =PL!E129 -> 0.008 | E16: =PL!F129 -> 0.015 | F16: =PL!G129 -> 0.025 | G16: Assumed（MCL、MLCP）
A17: 奇鋐液冷有效份額（奇鋐模型 B） | B17: % | C17: =avshB_26 -> 0.49892764 | D17: =avshB_27 -> 0.47398126 | E17: =avshB_28 -> 0.44903488 | F17: =avshB_29 -> 0.42408849 | G17: 唯讀 avc/dist
A18: 奇鋐＋健策液冷份額合計 | B18: % | C18: =C17+C16 -> 0.49892764 | D18: =D17+D16 -> 0.48198126 | E18: =E17+E16 -> 0.46403488 | F18: =F17+F16 -> 0.44908849 | G18: 其餘為雙鴻、酷碼、台達電、Boyd、CoolIT 等；雙鴻模型未在 main，未納入合計
A19: 健策液冷冷板元件營收 | B19: US$B | C19: =PL!D130/fx -> 0 | D19: =PL!E130/fx -> 0.081608803 | E19: =PL!F130/fx -> 0.18939067 | F19: =PL!G130/fx -> 0.4045236
A21: 讀法：VR 世代每顆均熱片金額約為 Blackwell 的 3 倍，2027 年起可拆式上蓋再提高單價；健策營收成長主要來自每顆金額，而非顆數。FY2026 的 AI 占比（Assumed）決定校準份額；可拆式上蓋單價與份額相對值是最需要每季檢查的輸入。液冷冷板元件份額為新產品 Assumed，與奇鋐份額合計遠低於 100%。

Sheet PL
A1: PL — 健策損益（十億新台幣；EPS 新台幣；歸屬母公司）。FY2025A 實績、FY2026 錨點（1H26 財報＋3Q26 月營收＋假設），FY2027 起為模型。FY(t)＝CY(t)。三情境各一個完整推導區塊（本頁下方），頂端為摘要。顆數係數從 CY2028 開始；可拆式上蓋單價、份額、液冷份額從 FY2027 起依情境取高／基準／低值
A2: 灰底＝FY2030–FY2032 收斂法（上游只到 2029）：營收年增線性收斂到 fade_g、淨利率線性收斂到 fade_m（In 頁 J 節），非驅動因子推導
A3: 情境／項目 | B3: 單位 | C3: FY2025A | D3: FY2026（錨點） | E3: FY2027 | F3: FY2028 | G3: FY2029 | H3: FY2030（收斂） | I3: FY2031（收斂） | J3: FY2032（收斂） | K3: 說明
A4: 情境 A
A5: 營收 | B5: NT$B | C5: =C87 -> 20.276 | D5: =D87 -> 32.5153 | E5: =E87 -> 77.964201 | F5: =F87 -> 106.64147 | G5: =G87 -> 128.22574 | H5: =H87 -> 148.09221 | I5: =I87 -> 164.0072 | J5: =J87 -> 173.84763
A6: 營收年增 | B6: % | D6: =D88 -> 0.60363484 | E6: =E88 -> 1.3977697 | F6: =F88 -> 0.36782611 | G6: =G88 -> 0.20240034 | H6: =H88 -> 0.15493356 | I6: =I88 -> 0.10746678 | J6: =J88 -> 0.06
A7: AI 加速器均熱片營收 | B7: NT$B | C7: =C79 -> 6.0828 | D7: =D79 -> 13.00612 | E7: =E79 -> 51.296115 | F7: =F79 -> 67.063247 | G7: =G79 -> 75.265572
A8: 液冷冷板元件營收 | B8: NT$B | C8: =C83 -> 0 | D8: =D83 -> 0 | E8: =E83 -> 5.5493986 | F8: =F83 -> 16.933754 | G8: =G83 -> 28.935335
A9: 其他散熱營收 | B9: NT$B | C9: =C85 -> 8.637576 | D9: =D85 -> 11.380355 | E9: =E85 -> 12.745998 | F9: =F85 -> 14.020597 | G9: =G85 -> 15.142245
A10: 導線架與其他營收 | B10: NT$B | C10: =C86 -> 5.555624 | D10: =D86 -> 8.128825 | E10: =E86 -> 8.3726897 | F10: =F86 -> 8.6238704 | G10: =G86 -> 8.8825866
A11: 毛利率 | B11: % | C11: =C94 -> 0.41595976 | D11: =D94 -> 0.47332477 | E11: =E94 -> 0.50427811 | F11: =F94 -> 0.50078875 | G11: =G94 -> 0.49576203
A12: 營業利益率 | B12: % | C12: =C98 -> 0.32047741 | D12: =D98 -> 0.38504324 | E12: =E98 -> 0.43658192 | F12: =F98 -> 0.44037431 | G12: =G98 -> 0.43941541
A13: 歸屬母公司淨利 | B13: NT$B | C13: =C100 -> 5.277 | D13: =D100 -> 10.344206 | E13: =E100 -> 27.641897 | F13: =F100 -> 38.046042 | G13: =G100 -> 45.598715 | H13: =H100 -> 52.663486 | I13: =I100 -> 58.323061 | J13: =J100 -> 61.822445
A14: 淨利率 | B14: % | C14: =C104 -> 0.26025843 | D14: =D104 -> 0.3181335 | E14: =E104 -> 0.35454602 | F14: =F104 -> 0.35676592 | G14: =G104 -> 0.35561281 | H14: =H104 -> 0.35561281 | I14: =I104 -> 0.35561281 | J14: =J104 -> 0.35561281
A15: EPS | B15: NT$ | C15: =C102 -> 36.75 | D15: =D102 -> 70.510964 | E15: =E102 -> 188.42014 | F15: =F102 -> 259.33968 | G15: =G102 -> 310.82224 | H15: =H102 -> 358.97904 | I15: =I102 -> 397.55736 | J15: =J102 -> 421.4108
A16: EPS 年增 | B16: % | D16: =D103 -> 0.91866569 | E16: =E103 -> 1.6722105 | F16: =F103 -> 0.37639041 | G16: =G103 -> 0.19851403 | H16: =H103 -> 0.15493356 | I16: =I103 -> 0.10746678 | J16: =J103 -> 0.06
A18: 情境 B
A19: 營收 | B19: NT$B | C19: =C134 -> 20.276 | D19: =D134 -> 32.5153 | E19: =E134 -> 62.205078 | F19: =F134 -> 70.32444 | G19: =G134 -> 85.937269 | H19: =H134 -> 99.802468 | I19: =I134 -> 109.84963 | J19: =J134 -> 114.24362
A20: 營收年增 | B20: % | D20: =D135 -> 0.60363484 | E20: =E135 -> 0.91310178 | F20: =F135 -> 0.13052571 | G20: =G135 -> 0.22201141 | H20: =H135 -> 0.16134094 | I20: =I135 -> 0.10067047 | J20: =J135 -> 0.04
A21: AI 加速器均熱片營收 | B21: NT$B | C21: =C126 -> 6.0828 | D21: =D126 -> 13.00612 | E21: =E126 -> 38.474909 | F21: =F126 -> 41.619471 | G21: =G126 -> 48.967682
A22: 液冷冷板元件營收 | B22: NT$B | C22: =C130 -> 0 | D22: =D130 -> 0 | E22: =E130 -> 2.6114817 | F22: =F130 -> 6.0605015 | G22: =G130 -> 12.944755
A23: 其他散熱營收 | B23: NT$B | C23: =C132 -> 8.637576 | D23: =D132 -> 11.380355 | E23: =E132 -> 12.745998 | F23: =F132 -> 14.020597 | G23: =G132 -> 15.142245
A24: 導線架與其他營收 | B24: NT$B | C24: =C133 -> 5.555624 | D24: =D133 -> 8.128825 | E24: =E133 -> 8.3726897 | F24: =F133 -> 8.6238704 | G24: =G133 -> 8.8825866
A25: 毛利率 | B25: % | C25: =C141 -> 0.41595976 | D25: =D141 -> 0.47332477 | E25: =E141 -> 0.49954683 | F25: =F141 -> 0.49634328 | G25: =G141 -> 0.49370165
A26: 營業利益率 | B26: % | C26: =C145 -> 0.32047741 | D26: =D145 -> 0.38504324 | E26: =E145 -> 0.42811961 | F26: =F145 -> 0.42821473 | G26: =G145 -> 0.43052406
A27: 歸屬母公司淨利 | B27: NT$B | C27: =C147 -> 5.277 | D27: =D147 -> 10.344206 | E27: =E147 -> 21.679627 | F27: =F147 -> 24.483239 | G27: =G147 -> 30.024939 | H27: =H147 -> 33.400887 | I27: =I147 -> 35.147251 | J27: =J147 -> 34.872377
A28: 淨利率 | B28: % | C28: =C151 -> 0.26025843 | D28: =D151 -> 0.3181335 | E28: =E151 -> 0.34851861 | F28: =F151 -> 0.34814694 | G28: =G151 -> 0.34938205 | H28: =H151 -> 0.33466995 | I28: =I151 -> 0.31995785 | J28: =J151 -> 0.30524574
A29: EPS | B29: NT$ | C29: =C149 -> 36.75 | D29: =D149 -> 70.510964 | E29: =E149 -> 147.77851 | F29: =F149 -> 166.88925 | G29: =G149 -> 204.66408 | H29: =H149 -> 227.67612 | I29: =I149 -> 239.58016 | J29: =J149 -> 237.70649
A30: EPS 年增 | B30: % | D30: =D150 -> 0.91866569 | E30: =E150 -> 1.0958232 | F30: =F150 -> 0.1293201 | G30: =G150 -> 0.22634672 | H30: =H150 -> 0.11243812 | I30: =I150 -> 0.052284953 | J30: =J150 -> -0.0078206386
A32: 情境 C
A33: 營收 | B33: NT$B | C33: =C181 -> 20.276 | D33: =D181 -> 32.5153 | E33: =E181 -> 50.238365 | F33: =F181 -> 45.414693 | G33: =G181 -> 49.941327 | H33: =H181 -> 53.592815 | I33: =I181 -> 56.087977 | J33: =J181 -> 57.209737
A34: 營收年增 | B34: % | D34: =D182 -> 0.60363484 | E34: =E182 -> 0.54506849 | F34: =F182 -> -0.096015706 | G34: =G182 -> 0.099673332 | H34: =H182 -> 0.073115554 | I34: =I182 -> 0.046557777 | J34: =J182 -> 0.02
A35: AI 加速器均熱片營收 | B35: NT$B | C35: =C173 -> 6.0828 | D35: =D173 -> 13.00612 | E35: =E173 -> 28.336233 | F35: =F173 -> 21.272925 | G35: =G173 -> 22.870671
A36: 液冷冷板元件營收 | B36: NT$B | C36: =C177 -> 0 | D36: =D177 -> 0 | E36: =E177 -> 0.78344451 | F36: =F177 -> 1.4973004 | G36: =G177 -> 3.0458247
A37: 其他散熱營收 | B37: NT$B | C37: =C179 -> 8.637576 | D37: =D179 -> 11.380355 | E37: =E179 -> 12.745998 | F37: =F179 -> 14.020597 | G37: =G179 -> 15.142245
A38: 導線架與其他營收 | B38: NT$B | C38: =C180 -> 5.555624 | D38: =D180 -> 8.128825 | E38: =E180 -> 8.3726897 | F38: =F180 -> 8.6238704 | G38: =G180 -> 8.8825866
A39: 毛利率 | B39: % | C39: =C188 -> 0.41595976 | D39: =D188 -> 0.47332477 | E39: =E188 -> 0.49300906 | F39: =F188 -> 0.48153458 | G39: =G188 -> 0.48027887
A40: 營業利益率 | B40: % | C40: =C192 -> 0.32047741 | D40: =D192 -> 0.38504324 | E40: =E192 -> 0.4171851 | F40: =F192 -> 0.39765705 | G40: =G192 -> 0.39944237
A41: 歸屬母公司淨利 | B41: NT$B | C41: =C194 -> 5.277 | D41: =D194 -> 10.344206 | E41: =E194 -> 17.113251 | F41: =F194 -> 14.779376 | G41: =G194 -> 16.300189 | H41: =H194 -> 16.325854 | I41: =I194 -> 15.865525 | J41: =J194 -> 14.938002
A42: 淨利率 | B42: % | C42: =C198 -> 0.26025843 | D42: =D198 -> 0.3181335 | E42: =E198 -> 0.34064109 | F42: =F198 -> 0.32543159 | G42: =G198 -> 0.32638679 | H42: =H198 -> 0.30462767 | I42: =I198 -> 0.28286855 | J42: =J198 -> 0.26110943
A43: EPS | B43: NT$ | C43: =C196 -> 36.75 | D43: =D196 -> 70.510964 | E43: =E196 -> 116.65195 | F43: =F196 -> 100.74316 | G43: =G196 -> 111.10974 | H43: =H196 -> 111.28468 | I43: =I196 -> 108.14686 | J43: =J196 -> 101.82443
A44: EPS 年增 | B44: % | D44: =D197 -> 0.91866569 | E44: =E197 -> 0.65438033 | F44: =F197 -> -0.13637827 | G44: =G197 -> 0.10290106 | H44: =H197 -> 0.0015745174 | I44: =I197 -> -0.02819635 | J44: =J197 -> -0.058461538
A46: 核對（應為 0）：FY2026 模型 − 錨點
A47: 三情境：營收差（NT$B） | D47: =ABS(D87-a26_rev)+ABS(D134-a26_rev)+ABS(D181-a26_rev) -> 0
A48: 情境 B：AI 均熱片差（NT$B） | D48: =D126-a26_ail -> 0
A49: 情境 B：毛利差（NT$B） | D49: =D139*D134+d_ai*D126-a26_gp -> 0
A60: 情境 A（順利）：顆數基準（tsmc 係數 A＝1.0）；奇鋐模型液冷市場 A；可拆式上蓋單價、份額、液冷份額取高值
A61: 項目 | B61: 單位 | C61: FY2025A | D61: FY2026（錨點） | E61: FY2027 | F61: FY2028 | G61: FY2029 | H61: FY2030（收斂） | I61: FY2031（收斂） | J61: FY2032（收斂） | K61: 說明
A62: A. AI 加速器顆數與均熱片市場（D 欄＝FY2026 校準年；E–G＝FY2027–FY2029；顆數 × 同字母情境係數）
A63: Blackwell 顆數 | B63: 百萬顆 | D63: =(u_bw26)*1 -> 5.4 | E63: =(u_bw27)*1*1 -> 2.4 | F63: =(u_bw28)*um28_A*1 -> 0.5 | G63: =(u_bw29)*um29_A*1 -> 0.25
A64: Hopper 顆數 | B64: 百萬顆 | D64: =(u_hp26)*1 -> 0.5 | E64: =(u_hp27)*1*1 -> 0 | F64: =(u_hp28)*um28_A*1 -> 0 | G64: =(u_hp29)*um29_A*1 -> 0
A65: Rubin 顆數 | B65: 百萬顆 | D65: =(u_rb26)*1 -> 1.7 | E65: =(u_rb27)*1*1 -> 7 | F65: =(u_rb28)*um28_A*1 -> 7 | G65: =(u_rb29)*um29_A*1 -> 8.05
A66: Rubin Ultra 顆數 | B66: 百萬顆 | D66: =(u_ru26)*1 -> 0 | E66: =(u_ru27)*1*1 -> 0.3 | F66: =(u_ru28)*um28_A*1 -> 2 | G66: =(u_ru29)*um29_A*1 -> 2.3
A67: AMD Instinct 顆數 | B67: 百萬顆 | D67: =(u_amd26)*1 -> 0.75 | E67: =(u_amd27)*1*1 -> 1.5 | F67: =(u_amd28)*um28_A*1 -> 2 | G67: =(u_amd29)*um29_A*1 -> 2.3
A68: ASIC 顆數（TPU＋Trainium＋其他） | B68: 百萬顆 | D68: =(u_tpu26+u_trn26+u_oth26)*1 -> 6.85 | E68: =(u_tpu27+u_trn27+u_oth27)*1*1 -> 12.5 | F68: =(u_tpu28+u_trn28+u_oth28)*um28_A*1 -> 15 | G68: =(u_tpu29+u_trn29+u_oth29)*um29_A*1 -> 17.25
A69: Rubin 每顆均熱片／上蓋 | B69: US$/顆 | D69: =asp_vr_26 -> 100 | E69: =VRHI_27 -> 200 | F69: =VRHI_28 -> 220 | G69: =VRHI_29 -> 220
A70: AMD 每顆均熱片／上蓋 | B70: US$/顆 | D70: =asp_amd_26 -> 40 | E70: =AMHI_27 -> 80 | F70: =AMHI_28 -> 110 | G70: =AMHI_29 -> 110
A71: ASIC 每顆均熱片＋加強環 | B71: US$/顆 | D71: =asp_asic_26 -> 30 | E71: =ASHI_27 -> 45 | F71: =ASHI_28 -> 55 | G71: =ASHI_29 -> 55
A72: NVIDIA 加速器均熱片市場（美元） | B72: US$B | D72: =(D63*asp_bw+D64*asp_hp+D65*D69+D66*asp_ru)/1000 -> 0.3665 | E72: =(E63*asp_bw+E64*asp_hp+E65*E69+E66*asp_ru)/1000 -> 1.544 | F72: =(F63*asp_bw+F64*asp_hp+F65*F69+F66*asp_ru)/1000 -> 1.9575 | G72: =(G63*asp_bw+G64*asp_hp+G65*G69+G66*asp_ru)/1000 -> 2.23975 | K72: 百萬顆 × 美元 ÷ 1000＝十億美元
A73: 非 NVIDIA（AMD、ASIC）均熱片市場（美元） | B73: US$B | D73: =(D67*D70+D68*D71)/1000 -> 0.2355 | E73: =(E67*E70+E68*E71)/1000 -> 0.6825 | F73: =(F67*F70+F68*F71)/1000 -> 1.045 | G73: =(G67*G70+G68*G71)/1000 -> 1.20175
A74: AI 加速器均熱片市場合計 | B74: US$B | D74: =D72+D73 -> 0.602 | E74: =E72+E73 -> 2.2265 | F74: =F72+F73 -> 3.0025 | G74: =G72+G73 -> 3.4415
A75: 健策 NVIDIA 份額（FY2026 校準）＝ AI 均熱片營收 ÷（NVIDIA 市場＋k × 非 NVIDIA 市場） | B75: % | D75: =a26_rev*ai_26/fx/(D72+k_non*D73) -> 0.88222542 | K75: Derived：分子為 FY2026 錨點營收 × AI 占比（Assumed）；k＝非 NVIDIA 份額 ÷ NVIDIA 份額
A76: 份額相對值（÷ FY2026） | B76: x | D76: =1 -> 1 | E76: =RHI_27 -> 1 | F76: =RHI_28 -> 1 | G76: =RHI_29 -> 0.98
A77: 健策 NVIDIA 均熱片份額 | B77: % | D77: =$D$75*D76 -> 0.88222542 | E77: =$D$75*E76 -> 0.88222542 | F77: =$D$75*F76 -> 0.88222542 | G77: =$D$75*G76 -> 0.86458091
A78: 健策非 NVIDIA 均熱片份額 | B78: % | D78: =D77*k_non -> 0.35289017 | E78: =E77*k_non -> 0.35289017 | F78: =F77*k_non -> 0.35289017 | G78: =G77*k_non -> 0.34583236
A79: AI 加速器均熱片營收 | B79: NT$B | C79: =a25_ail -> 6.0828 | D79: =(D72*D77+D73*D78)*fx -> 13.00612 | E79: =(E72*E77+E73*E78)*fx -> 51.296115 | F79: =(F72*F77+F73*F78)*fx -> 67.063247 | G79: =(G72*G77+G73*G78)*fx -> 75.265572
A80: B. 液冷冷板元件（奇鋐模型同字母情境的液冷市場 × 健策份額）
A81: AI 液冷市場（奇鋐模型；美元） | B81: US$B | D81: =lmkA_26 -> 4.5136876 | E81: =lmkA_27*1 -> 11.561247 | F81: =lmkA_28*1 -> 17.639327 | G81: =lmkA_29*1 -> 20.093983 | K81: 唯讀 avc/dist PL 頁同字母情境；FY2026 健策液冷含在其他散熱內
A82: 健策液冷份額 | B82: % | D82: =0 -> 0 | E82: =LCHI_27 -> 0.015 | F82: =LCHI_28 -> 0.03 | G82: =LCHI_29 -> 0.045
A83: 液冷冷板元件營收（MCL、MLCP） | B83: NT$B | C83: =0 -> 0 | D83: =D81*D82*fx -> 0 | E83: =E81*E82*fx -> 5.5493986 | F83: =F81*F82*fx -> 16.933754 | G83: =G81*G82*fx -> 28.935335
A84: C. 其他散熱、導線架與合計
A85: 其他散熱營收（CPU 均熱片、交換器加強環、CPO、ILM、車用水冷） | B85: NT$B | C85: =a25_oth -> 8.637576 | D85: =a26_rev*(th_26-ai_26) -> 11.380355 | E85: =D85*(1+g_oth_27) -> 12.745998 | F85: =E85*(1+g_oth_28) -> 14.020597 | G85: =F85*(1+g_oth_29) -> 15.142245
A86: 導線架、精密沖壓與其他營收 | B86: NT$B | C86: =a25_lf -> 5.555624 | D86: =a26_lf -> 8.128825 | E86: =D86*(1+g_lf_27) -> 8.3726897 | F86: =E86*(1+g_lf_28) -> 8.6238704 | G86: =F86*(1+g_lf_29) -> 8.8825866
A87: 營收 | B87: NT$B | C87: =C79+C83+C85+C86 -> 20.276 | D87: =D79+D83+D85+D86 -> 32.5153 | E87: =E79+E83+E85+E86 -> 77.964201 | F87: =F79+F83+F85+F86 -> 106.64147 | G87: =G79+G83+G85+G86 -> 128.22574 | H87: =G87*(1+H88) -> 148.09221 | I87: =H87*(1+I88) -> 164.0072 | J87: =I87*(1+J88) -> 173.84763 | K87: FY2030 起為收斂法：營收年增由 FY2029 線性收斂到 fade_g、淨利率收斂到 fade_m（FY2032 達到），非驅動因子推導
A88: 營收年增 | B88: % | D88: =D87/C87-1 -> 0.60363484 | E88: =E87/D87-1 -> 1.3977697 | F88: =F87/E87-1 -> 0.36782611 | G88: =G87/F87-1 -> 0.20240034 | H88: =$G88+(fade_gA-$G88)*1/3 -> 0.15493356 | I88: =$G88+(fade_gA-$G88)*2/3 -> 0.10746678 | J88: =$G88+(fade_gA-$G88)*3/3 -> 0.06
A89: AI 加速器均熱片 ÷ 營收 | B89: % | C89: =C79/C87 -> 0.3 | D89: =D79/D87 -> 0.4 | E89: =E79/E87 -> 0.65794447 | F89: =F79/F87 -> 0.6288665 | G89: =G79/G87 -> 0.5869771
A90: 每顆加速器健策 AI 均熱片營收（全部加速器平均） | B90: US$/顆 | D90: =D79/fx*1000/(D63+D64+D65+D66+D67+D68) -> 26.739556 | E90: =E79/fx*1000/(E63+E64+E65+E66+E67+E68) -> 67.637282 | F90: =F79/fx*1000/(F63+F64+F65+F66+F67+F68) -> 79.084018 | G90: =G79/fx*1000/(G63+G64+G65+G66+G67+G68) -> 78.01158
A91: D. 損益
A92: 其他營收毛利率 ＝ 錨點毛利率 − 差距 × AI 占比（FY2026 校準） | B92: % | D92: =a26_gp/D87-d_ai*D89 -> 0.42532477 | K92: Derived：讓 FY2026 毛利率等於錨點；AI 均熱片毛利率＝其他＋差距；液冷與其他營收同毛利率
A93: 毛利 | B93: NT$B | C93: =a25_gp -> 8.434 | D93: =a26_gp -> 15.390297 | E93: =$D$92*E87+d_ai*E79 -> 39.31564 | F93: =$D$92*F87+d_ai*F79 -> 53.404848 | G93: =$D$92*G87+d_ai*G79 -> 63.569452
A94: 毛利率 | B94: % | C94: =C93/C87 -> 0.41595976 | D94: =D93/D87 -> 0.47332477 | E94: =E93/E87 -> 0.50427811 | F94: =F93/F87 -> 0.50078875 | G94: =G93/G87 -> 0.49576203
A95: 營業費用（基準路徑） | B95: NT$B | C95: =a25_opx -> 1.936 | D95: =a26_opx -> 2.8705005 | E95: =D95*(1+MAX(0,phi*E88)) -> 5.2778796 | F95: =E95*(1+MAX(0,phi*F88)) -> 6.4426848 | G95: =F95*(1+MAX(0,phi*G88)) -> 7.2250858
A96: 營業費用 | B96: NT$B | C96: =C95 -> 1.936 | D96: =D95 -> 2.8705005 | E96: =E95+0*E87 -> 5.2778796 | F96: =F95+0*F87 -> 6.4426848 | G96: =G95+0*G87 -> 7.2250858
A97: 營業利益 | B97: NT$B | C97: =C93-C96 -> 6.498 | D97: =D93-D96 -> 12.519796 | E97: =E93-E96 -> 34.03776 | F97: =F93-F96 -> 46.962164 | G97: =G93-G96 -> 56.344366
A98: 營業利益率 | B98: % | C98: =C97/C87 -> 0.32047741 | D98: =D97/D87 -> 0.38504324 | E98: =E97/E87 -> 0.43658192 | F98: =F97/F87 -> 0.44037431 | G98: =G97/G87 -> 0.43941541
A99: 業外收益 | B99: NT$B | C99: =a25_nop -> 0.109 | D99: =a26_nop -> 0.3305 | E99: =nop_f -> 0.3 | F99: =nop_f -> 0.3 | G99: =nop_f -> 0.3
A100: 歸屬母公司淨利 | B100: NT$B | C100: =a25_ni -> 5.277 | D100: =a26_ni -> 10.344206 | E100: =(E97+E99)*nir_f -> 27.641897 | F100: =(F97+F99)*nir_f -> 38.046042 | G100: =(G97+G99)*nir_f -> 45.598715 | H100: =H87*H104 -> 52.663486 | I100: =I87*I104 -> 58.323061 | J100: =J87*J104 -> 61.822445
A101: 股數 | B101: 十億股 | C101: =a25_sh -> 0.14359184 | D101: =a26_sh -> 0.14670351 | E101: =D101*(1+sh_g) -> 0.14670351 | F101: =E101*(1+sh_g) -> 0.14670351 | G101: =F101*(1+sh_g) -> 0.14670351 | H101: =G101*(1+sh_g) -> 0.14670351 | I101: =H101*(1+sh_g) -> 0.14670351 | J101: =I101*(1+sh_g) -> 0.14670351
A102: EPS | B102: NT$ | C102: =C100/C101 -> 36.75 | D102: =D100/D101 -> 70.510964 | E102: =E100/E101 -> 188.42014 | F102: =F100/F101 -> 259.33968 | G102: =G100/G101 -> 310.82224 | H102: =H100/H101 -> 358.97904 | I102: =I100/I101 -> 397.55736 | J102: =J100/J101 -> 421.4108
A103: EPS 年增 | B103: % | D103: =D102/C102-1 -> 0.91866569 | E103: =E102/D102-1 -> 1.6722105 | F103: =F102/E102-1 -> 0.37639041 | G103: =G102/F102-1 -> 0.19851403 | H103: =H102/G102-1 -> 0.15493356 | I103: =I102/H102-1 -> 0.10746678 | J103: =J102/I102-1 -> 0.06
A104: 淨利率（歸屬母公司淨利 ÷ 營收） | B104: % | C104: =C100/C87 -> 0.26025843 | D104: =D100/D87 -> 0.3181335 | E104: =E100/E87 -> 0.35454602 | F104: =F100/F87 -> 0.35676592 | G104: =G100/G87 -> 0.35561281 | H104: =$G104+(fade_mA-$G104)*1/3 -> 0.35561281 | I104: =$G104+(fade_mA-$G104)*2/3 -> 0.35561281 | J104: =$G104+(fade_mA-$G104)*3/3 -> 0.35561281
A107: 情境 B（平平）：tsmc 係數 B（CY2028 ×0.8、CY2029 ×0.85）；液冷市場 B；公司特有變數取基準
A108: 項目 | B108: 單位 | C108: FY2025A | D108: FY2026（錨點） | E108: FY2027 | F108: FY2028 | G108: FY2029 | H108: FY2030（收斂） | I108: FY2031（收斂） | J108: FY2032（收斂） | K108: 說明
A109: A. AI 加速器顆數與均熱片市場（D 欄＝FY2026 校準年；E–G＝FY2027–FY2029；顆數 × 同字母情境係數）
A110: Blackwell 顆數 | B110: 百萬顆 | D110: =(u_bw26)*1 -> 5.4 | E110: =(u_bw27)*1*1 -> 2.4 | F110: =(u_bw28)*um28_B*1 -> 0.4 | G110: =(u_bw29)*um29_B*1 -> 0.2125
A111: Hopper 顆數 | B111: 百萬顆 | D111: =(u_hp26)*1 -> 0.5 | E111: =(u_hp27)*1*1 -> 0 | F111: =(u_hp28)*um28_B*1 -> 0 | G111: =(u_hp29)*um29_B*1 -> 0
A112: Rubin 顆數 | B112: 百萬顆 | D112: =(u_rb26)*1 -> 1.7 | E112: =(u_rb27)*1*1 -> 7 | F112: =(u_rb28)*um28_B*1 -> 5.6 | G112: =(u_rb29)*um29_B*1 -> 6.8425
A113: Rubin Ultra 顆數 | B113: 百萬顆 | D113: =(u_ru26)*1 -> 0 | E113: =(u_ru27)*1*1 -> 0.3 | F113: =(u_ru28)*um28_B*1 -> 1.6 | G113: =(u_ru29)*um29_B*1 -> 1.955
A114: AMD Instinct 顆數 | B114: 百萬顆 | D114: =(u_amd26)*1 -> 0.75 | E114: =(u_amd27)*1*1 -> 1.5 | F114: =(u_amd28)*um28_B*1 -> 1.6 | G114: =(u_amd29)*um29_B*1 -> 1.955
A115: ASIC 顆數（TPU＋Trainium＋其他） | B115: 百萬顆 | D115: =(u_tpu26+u_trn26+u_oth26)*1 -> 6.85 | E115: =(u_tpu27+u_trn27+u_oth27)*1*1 -> 12.5 | F115: =(u_tpu28+u_trn28+u_oth28)*um28_B*1 -> 12 | G115: =(u_tpu29+u_trn29+u_oth29)*um29_B*1 -> 14.6625
...

Sheet Val
A1: Val — P/E 估值（新台幣）。結論用「現價 ÷ FY2027、FY2028 EPS（模型）」；目標價＝DCF 與 Comparable 加權（第 0 節）；十年 P/E 規則值（第 3 節，年底落後 P/E）只作參考。本版未做先驗，無 Andy 合理 P/E 對照
A2: 循環位置：健策不是設備股，不套設備市場見頂年；以本模型營收最高的會計年度為見頂年（比照奇鋐、台達電；FY(t)＝CY(t)）。營收到 FY2029 仍在增加時，見頂年未知，判為中段
A3: 目標價：見第 0 節（DCF 與 Comparable 加權）；第 3 節規則值不是目標價，只作參考
A4: 0. 目標價
A5: 0.1 DCF（股東權益現金流，FY2027–FY2032 明確期＋FY2032 後永續）
A6: 項目 | B6: A（順利） | C6: B（平平） | D6: C（不如預期） | E6: 說明
A7: 情境 EPS（FY2027–FY2032） | E7: PL 頁各情境；FY2030 起為收斂法
A8: FY2027 | B8: =PL!E15 -> 188.42014 | C8: =PL!E29 -> 147.77851 | D8: =PL!E43 -> 116.65195
A9: FY2028 | B9: =PL!F15 -> 259.33968 | C9: =PL!F29 -> 166.88925 | D9: =PL!F43 -> 100.74316
A10: FY2029 | B10: =PL!G15 -> 310.82224 | C10: =PL!G29 -> 204.66408 | D10: =PL!G43 -> 111.10974
A11: FY2030 | B11: =PL!H15 -> 358.97904 | C11: =PL!H29 -> 227.67612 | D11: =PL!H43 -> 111.28468
A12: FY2031 | B12: =PL!I15 -> 397.55736 | C12: =PL!I29 -> 239.58016 | D12: =PL!I43 -> 108.14686
A13: FY2032 | B13: =PL!J15 -> 421.4108 | C13: =PL!J29 -> 237.70649 | D13: =PL!J43 -> 101.82443
A14: 股東現金流＝EPS ×（1 − tp_g ÷ tp_roe）
A15: 再投資率（tp_g ÷ tp_roe，上限 0.8） | B15: =MIN(tp_g/tp_roe,0.8) -> 0.16391203 | E15: ROE 為近三年平均（In 頁 tp_roe）
A16: FY2027 | B16: =B8*(1-$B$15) -> 157.53581 | C16: =C8*(1-$B$15) -> 123.55584 | D16: =D8*(1-$B$15) -> 97.531294
A17: FY2028 | B17: =B9*(1-$B$15) -> 216.83078 | C17: =C9*(1-$B$15) -> 139.53409 | D17: =D9*(1-$B$15) -> 84.230145
A18: FY2029 | B18: =B10*(1-$B$15) -> 259.87474 | C18: =C10*(1-$B$15) -> 171.11717 | D18: =D10*(1-$B$15) -> 92.897516
A19: FY2030 | B19: =B11*(1-$B$15) -> 300.13805 | C19: =C11*(1-$B$15) -> 190.35727 | D19: =D11*(1-$B$15) -> 93.043785
A20: FY2031 | B20: =B12*(1-$B$15) -> 332.39292 | C20: =C12*(1-$B$15) -> 200.31009 | D20: =D12*(1-$B$15) -> 90.42029
A21: FY2032 | B21: =B13*(1-$B$15) -> 352.3365 | C21: =C13*(1-$B$15) -> 198.74353 | D21: =D13*(1-$B$15) -> 85.134181
A22: DCF 情境每股價值（折現率 tp_r） | B22: =MAX(0,SUMPRODUCT(B16:B21,1/(1+tp_r)^{1;2;3;4;5;6})+B21*(1+tp_g)/(tp_r-tp_g)/(1+tp_r)^6) -> 4575.27 | C22: =MAX(0,SUMPRODUCT(C16:C21,1/(1+tp_r)^{1;2;3;4;5;6})+C21*(1+tp_g)/(tp_r-tp_g)/(1+tp_r)^6) -> 2667.3321 | D22: =MAX(0,SUMPRODUCT(D16:D21,1/(1+tp_r)^{1;2;3;4;5;6})+D21*(1+tp_g)/(tp_r-tp_g)/(1+tp_r)^6) -> 1228.793 | E22: Σ 明確期現金流 ÷ (1＋r)^t ＋ 永續價值 ÷ (1＋r)^6；永續價值＝FY2032 現金流 ×(1＋g)÷(r−g)；基準日 2026 年底；負值取 0（Andy 12:22）
A23: DCF 情境價值推到 12 個月後（×(1＋tp_r)） | B23: =B22*(1+tp_r) -> 5032.797 | C23: =C22*(1+tp_r) -> 2934.0653 | D23: =D22*(1+tp_r) -> 1351.6723
A24: DCF 目標價（情境加權） | B24: =tp_wA*B23+tp_wB*C23+tp_wC*D23 -> 3247.2062 | E24: Σ 權重 × 情境價值 ×(1＋r)；權重見 In 頁
A26: 0.2 Comparable（市場主流同業前瞻 P/E；非 A 股公司，同業不放 A 股）
A27: 同業與前瞻 P/E | B27: 代號 | C27: 前瞻 12 月 P/E | D27: 日期 | E27: 來源 | F27: 標記
A28: 奇鋐（AVC） | B28: 3017.TW | C28: 27.04 | D28: 2026-10-05 | E28: stockanalysis.com forward PE（分析師共識；價格日期如左，臺股頁面為快取日期） | F28: Interested-party
A29: 雙鴻（Auras） | B29: 3324.TWO | C29: 17.27 | D29: 2026-08-28 | E29: stockanalysis.com forward PE（分析師共識；價格日期如左，臺股頁面為快取日期） | F29: Interested-party
A30: Vertiv | B30: VRT | C30: 24.53 | D30: 2026-10-23 | E30: stockanalysis.com forward PE（分析師共識；價格日期如左，臺股頁面為快取日期） | F30: Interested-party
A31: 台達電（Delta） | B31: 2308.TW | C31: 30.51 | D31: 2026-10-22 | E31: stockanalysis.com forward PE（分析師共識；價格日期如左，臺股頁面為快取日期） | F31: Interested-party
A33: 並列參考（不進目標價）：英維克（002837.SZ）為 A 股，依規則不列；均熱片專業同業（上市可比）：未找到
A34: 同業前瞻 P/E 中位數 | B34: =MEDIAN(C28:C31) -> 25.785 | E34: 散熱與液冷同業：奇鋐、雙鴻、Vertiv、台達電（與奇鋐模型同一比較組，以奇鋐取代健策）
A35: 12 個月後的前瞻 EPS（情境加權） | B35: =tp_wA*(2/12*B8+10/12*B9)+tp_wB*(2/12*C8+10/12*C9)+tp_wC*(2/12*D8+10/12*D9) -> 176.78691 | E35: 約 2027-10 時的未來 12 月 EPS ≈ 2／12 × FY2027＋10／12 × FY2028（會計年度＝日曆年）
A36: Comparable 目標價 | B36: =B34*B35 -> 4558.4506 | E36: 同業中位數 × 前瞻 EPS
A38: 0.3 結論
A39: 項目 | B39: 數值 | E39: 說明
A40: 目標價（DCF 與 Comparable 加權） | B40: =tp_w_dcf*B24+(1-tp_w_dcf)*B36 -> 3902.8284 | E40: tp_w_dcf × DCF＋（1 − tp_w_dcf）× Comparable；tp_w_dcf 見 In 頁
A41: Comparable 目標價（市場主流同業法） | B41: =B36 -> 4558.4506
A42: 市場共識目標價 | B42: =cons_tp -> 7204 | E42: stockanalysis（S&P Global）：11 位分析師平均 7,204、中位數 7,300（頁面 2026-10-22）
A43: 上檔空間：加權目標價 | B43: =B40/px-1 -> -0.35702992 | E43: 現價＝In 頁 px（2026-10-22 收盤）
A44: 上檔空間：Comparable 目標價 | B44: =B41/px-1 -> -0.24901968
A45: 上檔空間級距 | B45: =IF(B43>0.5,"大於 50%",IF(B43>0.25,"25%–50%",IF(B43>=0,"0%–25%",IF(B43>=-0.25,"0%～−25%",IF(B43>=-0.5,"−25%～−50%","小於 −50%"))))) -> −25%～−50% | E45: 以「上檔空間：加權目標價」分六級（Andy 2026-10-25 14:00）；負值區間同樣重要
A46: 投資建議 | B46: =IF(B43>0.5,"強力買進",IF(B43>0.25,"買進",IF(B43>=-0.25,"中立",IF(B43>=-0.5,"放空","強力放空")))) -> 放空 | E46: 依上檔空間固定規則（Andy 2026-10-25 14:17）：大於 +50% 強力買進、+25%～+50% 買進、−25%～+25% 中立、−50%～−25% 放空、小於 −50% 強力放空
A47: 與市場共識目標價的差距：EPS 因素 | B47: =B35/cons_feps-1 -> 0.64092702 | E47: 本模型前瞻 EPS ÷ 共識前瞻 EPS − 1；共識前瞻 EPS（In 頁 cons_feps）為現在起算 12 個月，期間與本模型不同
A48: 與市場共識目標價的差距：倍數因素 | B48: =(cons_tp/cons_feps)/B34-1 -> 1.593258 | E48: ="共識目標價隱含 "&TEXT(cons_tp/cons_feps,"0.0")&"x，同業中位數 "&TEXT(B34,"0.0")&"x" -> 共識目標價隱含 66.9x，同業中位數 25.8x
A49: 價格帶（DCF 不如預期～順利） | B49: =TEXT(D23,"#,##0")&"～"&TEXT(B23,"#,##0") -> 1,352～5,033 | E49: C 情境價值～A 情境價值（推到 12 個月後）
A50: 歷史倍數檢查：現價隱含 P/E 的十年分位（A／B／C） | B50: =IF(px/B9<MIN($B$93:$B$102),0,IF(px/B9>MAX($B$93:$B$102),1,PERCENTRANK($B$93:$B$102,px/B9))) -> 0.257 | C50: =IF(px/C9<MIN($B$93:$B$102),0,IF(px/C9>MAX($B$93:$B$102),1,PERCENTRANK($B$93:$B$102,px/C9))) -> 0.567 | D50: =IF(px/D9<MIN($B$93:$B$102),0,IF(px/D9>MAX($B$93:$B$102),1,PERCENTRANK($B$93:$B$102,px/D9))) -> 0.87 | E50: 現價 ÷ 各情境 FY2028 EPS 在 2016–2025 年底 P/E（第 6 節 Goodinfo）的分位；只作檢查，不進目標價
A51: 目標價方法 | B51: DCF：股東現金流＝歸母 EPS ×（1 − g／ROE），r＝10%、g＝4%、ROE 為近三年平均約 24%（再投資率約 16%），FY2027–29 驅動因子、FY2030–32 收斂法＋永續；本模型未建資本支出與折舊（大園新廠 2026-04 投產），未改用淨利＋折舊－資本支出。Comparable：奇鋐、雙鴻、Vertiv、台達電前瞻 P/E 中位數（散熱與液冷主流比較組，不放 A 股）；健策現價前瞻 P/E 約 59x，遠高於同業（均熱片近乎寡占、毛利率約 47%），Comparable 未給寡占溢價，方向偏低。情境對應：A＝順利（顆數基準、可拆式上蓋與份額高值）、B＝平平（顆數 ×0.8／0.85、基準）、C＝不如預期（顆數 ×0.6、低值）
A54: 1. 價格與市場隱含倍數
A55: 項目 | B55: A | C55: B | D55: C | E55: 說明
A56: 現價（2026-10-22 收盤） | B56: =px -> 6070
A57: 現價 ÷ FY2026 EPS（錨點） | B57: =px/PL!D15 -> 86.085903 | C57: =px/PL!D29 -> 86.085903 | D57: =px/PL!D43 -> 86.085903 | E57: FY2026 三情境相同（錨點）
A58: 現價 ÷ FY2027 EPS（模型） | B58: =px/PL!E15 -> 32.215239 | C58: =px/PL!E29 -> 41.074983 | D58: =px/PL!E43 -> 52.035134 | E58: FY2027 三情境差異只來自可拆式上蓋單價、份額、液冷份額（顆數係數從 CY2028 開始）
A59: 現價 ÷ FY2028 EPS（模型） | B59: =px/PL!F15 -> 23.405597 | C59: =px/PL!F29 -> 36.371427 | D59: =px/PL!F43 -> 60.252229
A60: 現價 ÷ FY2029 EPS（模型） | B60: =px/PL!G15 -> 19.528847 | C60: =px/PL!G29 -> 29.658355 | D60: =px/PL!G43 -> 54.630674
A61: 未來 12 月 EPS（模型 B）≈ 0.2 × FY2026＋0.8 × FY2027 | B61: =0.2*PL!D29+0.8*PL!E29 -> 132.325
A62: 現價 ÷ 未來 12 月 EPS（模型 B） | B62: =px/B61 -> 45.871905
A63: 近 12 月 P/E（財報狗，10-22） | B63: =pe_ttm -> 136.99
A64: 前瞻 P/E（stockanalysis，08-27） | B64: =fpe -> 59.27
A66: 2. 循環位置（本模型營收最高年；FY(t)＝CY(t)）
A67: 情境 | B67: 營收最高年（FY2026–FY2029） | C67: FY2027 判定 | D67: 規則倍數（P/E） | E67: 見頂年是否未知 | F67: 說明
A68: A | B68: =INDEX({2026,2027,2028,2029},MATCH(MAX(PL!D87:G87),PL!D87:G87,0)) -> 2029 | C68: =IF(B68=2029,"中段",IF(2027<B68,"中段",IF(2027=B68,"見頂","谷底"))) -> 中段 | D68: =IF(C68="見頂",pe_peak,IF(C68="谷底",pe_trough,pe_mid)) -> 33.13 | E68: =IF(B68=2029,"是：營收到觀測期末仍在增加","否") -> 是：營收到觀測期末仍在增加 | F68: tools/cycle_position.py excel_rule；營收最高年取代設備市場見頂年
A69: B | B69: =INDEX({2026,2027,2028,2029},MATCH(MAX(PL!D134:G134),PL!D134:G134,0)) -> 2029 | C69: =IF(B69=2029,"中段",IF(2027<B69,"中段",IF(2027=B69,"見頂","谷底"))) -> 中段 | D69: =IF(C69="見頂",pe_peak,IF(C69="谷底",pe_trough,pe_mid)) -> 33.13 | E69: =IF(B69=2029,"是：營收到觀測期末仍在增加","否") -> 是：營收到觀測期末仍在增加 | F69: 同上
A70: C | B70: =INDEX({2026,2027,2028,2029},MATCH(MAX(PL!D181:G181),PL!D181:G181,0)) -> 2027 | C70: =IF(B70=2029,"中段",IF(2027<B70,"中段",IF(2027=B70,"見頂","谷底"))) -> 見頂 | D70: =IF(C70="見頂",pe_peak,IF(C70="谷底",pe_trough,pe_mid)) -> 22.84 | E70: =IF(B70=2029,"是：營收到觀測期末仍在增加","否") -> 否 | F70: 同上
A72: 3. 規則值隱含股價（新台幣；約 FY2027 年底，未折現）＝ FY2027 EPS × 規則倍數（參考，不是目標價）
A73: 情境 | B73: FY2027 EPS | C73: （同左） | D73: 規則倍數 | E73: 隱含股價 | F73: 相對現價 | G73: 現價 ÷ FY2027 EPS
A74: A | B74: =PL!E15 -> 188.42014 | C74: =B74 -> 188.42014 | D74: =D68 -> 33.13 | E74: =C74*D74 -> 6242.3593 | F74: =E74/px-1 -> 0.028395273 | G74: =px/C74 -> 32.215239
A75: B | B75: =PL!E29 -> 147.77851 | C75: =B75 -> 147.77851 | D75: =D69 -> 33.13 | E75: =C75*D75 -> 4895.9022 | F75: =E75/px-1 -> -0.19342633 | G75: =px/C75 -> 41.074983
A76: C | B76: =PL!E43 -> 116.65195 | C76: =B76 -> 116.65195 | D76: =D70 -> 22.84 | E76: =C76*D76 -> 2664.3306 | F76: =E76/px-1 -> -0.5610658 | G76: =px/C76 -> 52.035134
A78: 4. What must be true：FY2027 年底價 ＝ 現價 ×（1＋報酬）所需的倍數（FY2028 EPS；約 2027 年底的價格看下一年 EPS）
A79: FY2027 年底價 ÷ 現價 | B79: 所需倍數（÷ FY2028 EPS，A） | C79: 所需倍數（÷ FY2028 EPS，B） | D79: 所需倍數（÷ FY2028 EPS，C） | E79: 對照：十年中位數
A80: 1 | B80: =px*A80/PL!F15 -> 23.405597 | C80: =px*A80/PL!F29 -> 36.371427 | D80: =px*A80/PL!F43 -> 60.252229 | E80: =pe_mid -> 33.13
A81: 1.1 | B81: =px*A81/PL!F15 -> 25.746157 | C81: =px*A81/PL!F29 -> 40.00857 | D81: =px*A81/PL!F43 -> 66.277452 | E81: =pe_mid -> 33.13
A82: 1.21 | B82: =px*A82/PL!F15 -> 28.320773 | C82: =px*A82/PL!F29 -> 44.009427 | D82: =px*A82/PL!F43 -> 72.905197 | E82: =pe_mid -> 33.13
A83: 1.5 | B83: =px*A83/PL!F15 -> 35.108396 | C83: =px*A83/PL!F29 -> 54.55714 | D83: =px*A83/PL!F43 -> 90.378343 | E83: =pe_mid -> 33.13
A84: 2 | B84: =px*A84/PL!F15 -> 46.811194 | C84: =px*A84/PL!F29 -> 72.742854 | D84: =px*A84/PL!F43 -> 120.50446 | E84: =pe_mid -> 33.13
A85: 讀法：1.00＝價格不變、1.21＝一年約 21%。所需倍數低於歷史中位數時，現價相對便宜；倍數是否合理，另看前瞻 P/E 歷史（Bloomberg）。本版未做先驗，無 Andy 合理 P/E 對照。
A88: 6. 十年倍數與規則值（2016–2025 年底；見頂年 25 分位、中段中位數、谷底 75 分位）
A89: 規則（Andy 2026-10-13）：合理倍數＝2016–2025 年底 P/E 依循環位置取分位。採用 Goodinfo 年底收盤 ÷ 當年 EPS（10 年；2016 年 EPS 取聚財網）；stockanalysis 只有 2021–2025，只作核對。健策 2019 年起已是 CPU 均熱片龍頭、2023 年起 AI 均熱片放量，十年倍數由約 17x 升到約 75x，分布本身已含 AI 溢價。
A91: P/E：十年歷史倍數
A92: 年底 | B92: Goodinfo（年底收盤 ÷ 當年 EPS） | C92: stockanalysis（年度 P/E） | D92: 標記／說明
A93: 2016 | B93: =47.5/2.32 -> 20.474138 | D93: Goodinfo（年底收盤 ÷ 當年 EPS）：Derived（Goodinfo 年底收盤與 EPS；2016 年 EPS 2.32 取聚財網；10 年）；stockanalysis（年度 P/E）：Interested-party（資料商；只有 2021–2025，只作核對、不採用）
A94: 2017 | B94: =66.7/2.19 -> 30.456621 | D94: stockanalysis 2021–2025 與 Goodinfo 推導差距在 1x 內；2016–2020 年：未找到第二來源
A95: 2018 | B95: =78.2/4.61 -> 16.963124
A96: 2019 | B96: =234.5/6.55 -> 35.801527
A97: 2020 | B97: =247.5/8.27 -> 29.927449
A98: 2021 | B98: =408/9.88 -> 41.295547 | C98: 41.68
A99: 2022 | B99: =376.5/19.54 -> 19.268168 | C99: 19.49
A100: 2023 | B100: =769/16.59 -> 46.353225 | C100: 47.12
A101: 2024 | B101: =1525/24.15 -> 63.146998 | C101: 63.57
A102: 2025 | B102: =2745/36.75 -> 74.693878 | C102: 74.34
A103: 25 分位（各來源） | B103: =PERCENTILE(B93:B102,0.25) -> 22.837466 | C103: =PERCENTILE(C93:C102,0.25) -> 41.68
A104: 中位數（各來源） | B104: =MEDIAN(B93:B102) -> 33.129074 | C104: =MEDIAN(C93:C102) -> 47.12
A105: 75 分位（各來源） | B105: =PERCENTILE(B93:B102,0.75) -> 45.088805 | C105: =PERCENTILE(C93:C102,0.75) -> 63.57
A106: 最小（各來源） | B106: =MIN(B93:B102) -> 16.963124 | C106: =MIN(C93:C102) -> 19.49
A107: 最大（各來源） | B107: =MAX(B93:B102) -> 74.693878 | C107: =MAX(C93:C102) -> 74.34
A108: 採用 25 分位（P/E） | B108: =ROUND(AVERAGE(B103),2) -> 22.84
A109: 採用 中位數（P/E） | B109: =ROUND(AVERAGE(B104),2) -> 33.13
A110: 採用 75 分位（P/E） | B110: =ROUND(AVERAGE(B105),2) -> 45.09
A111: 採用 最小（P/E） | B111: =ROUND(MIN(B106),2) -> 16.96
...

Sheet Recon
A1: Recon — 本模型 vs 共識、券商估計與奇鋐模型液冷份額。只作事後對照，不為對上數字而調參數。共識取自 stockanalysis（S&P Global）與 FactSet（鉅亨轉引，5 月）；券商多為單一來源
A3: 項目 | B3: 對照值 | C3: 模型 A | D3: 差距 A | E3: 模型 B | F3: 差距 B | G3: 模型 C | H3: 差距 C | I3: 對照來源 | J3: 說明
A4: A. 共識與券商估計（校準未使用）
A5: FY2026 營收 vs 共識（stockanalysis） | B5: =cons_rev26 -> 32.7 | C5: =PL!D87 -> 32.5153 | D5: =C5/B5-1 -> -0.005648318 | E5: =PL!D134 -> 32.5153 | F5: =E5/B5-1 -> -0.005648318 | G5: =PL!D181 -> 32.5153 | H5: =G5/B5-1 -> -0.005648318 | I5: stockanalysis 2026-10-22（7 家）
A6: FY2026 EPS vs 共識（stockanalysis） | B6: =cons_eps26 -> 69.96 | C6: =PL!D102 -> 70.510964 | D6: =C6/B6-1 -> 0.007875416 | E6: =PL!D149 -> 70.510964 | F6: =E6/B6-1 -> 0.007875416 | G6: =PL!D196 -> 70.510964 | H6: =G6/B6-1 -> 0.007875416 | I6: stockanalysis 2026-10-22（7 家） | J6: 3Q26 財報（11-09）前
A7: FY2026 EPS vs 亞系券商（08 月） | B7: =ab_eps26 -> 71 | C7: =PL!D102 -> 70.510964 | D7: =C7/B7-1 -> -0.0068878296 | E7: =PL!D149 -> 70.510964 | F7: =E7/B7-1 -> -0.0068878296 | G7: =PL!D196 -> 70.510964 | H7: =G7/B7-1 -> -0.0068878296 | I7: 口袋學堂 2026-08-26 轉引
A8: 3Q26 營收 vs 大和（10-01） | B8: =dw_q3rev -> 9.65 | C8: =Q!D4 -> 9.493 | D8: =C8/B8-1 -> -0.01626943 | E8: =Q!D4 -> 9.493 | F8: =E8/B8-1 -> -0.01626943 | G8: =Q!D4 -> 9.493 | H8: =G8/B8-1 -> -0.01626943 | I8: 大和（經濟日報 2026-10-01） | J8: 實績（月營收）低於大和
A9: 3Q26 EPS（模型）vs 大和（10-01） | B9: =dw_q3eps -> 22.77 | C9: =Q!D15 -> 21.535649 | D9: =C9/B9-1 -> -0.054209545 | E9: =Q!D15 -> 21.535649 | F9: =E9/B9-1 -> -0.054209545 | G9: =Q!D15 -> 21.535649 | H9: =G9/B9-1 -> -0.054209545 | I9: 大和（經濟日報 2026-10-01） | J9: Bloomberg 共識 20.37
A10: FY2027 營收 vs FactSet 中位數（05-22） | B10: =fs_rev27 -> 51.836 | C10: =PL!E87 -> 77.964201 | D10: =C10/B10-1 -> 0.50405511 | E10: =PL!E134 -> 62.205078 | F10: =E10/B10-1 -> 0.20003623 | G10: =PL!E181 -> 50.238365 | H10: =G10/B10-1 -> -0.030820948 | I10: FactSet（鉅亨 2026-05-22） | J10: 較舊
A11: FY2027 EPS vs FactSet 中位數（05-22） | B11: =fs_eps27 -> 117.18 | C11: =PL!E102 -> 188.42014 | D11: =C11/B11-1 -> 0.60795479 | E11: =PL!E149 -> 147.77851 | F11: =E11/B11-1 -> 0.26112403 | G11: =PL!E196 -> 116.65195 | H11: =G11/B11-1 -> -0.0045062946 | I11: FactSet（鉅亨 2026-05-22） | J11: 平均 121.01
A12: FY2027 EPS vs 亞系券商（08 月） | B12: =ab_eps27 -> 151 | C12: =PL!E102 -> 188.42014 | D12: =C12/B12-1 -> 0.24781551 | E12: =PL!E149 -> 147.77851 | F12: =E12/B12-1 -> -0.021334346 | G12: =PL!E196 -> 116.65195 | H12: =G12/B12-1 -> -0.22747051 | I12: 口袋學堂 2026-08-26 轉引
A13: FY2027 EPS vs 分析師（理財周刊 08-05） | B13: =mw_eps27 -> 123.83 | C13: =PL!E102 -> 188.42014 | D13: =C13/B13-1 -> 0.52160334 | E13: =PL!E149 -> 147.77851 | F13: =E13/B13-1 -> 0.19339832 | G13: =PL!E196 -> 116.65195 | H13: =G13/B13-1 -> -0.057966951 | I13: 理財周刊 2026-08-05
A14: FY2027 營收年增 vs 本國投顧（10-08）（百分點） | B14: =ld_g27 -> 1.47 | C14: =PL!E88 -> 1.3977697 | D14: =C14-B14 -> -0.072230314 | E14: =PL!E135 -> 0.91310178 | F14: =E14-B14 -> -0.55689822 | G14: =PL!E182 -> 0.54506849 | H14: =G14-B14 -> -0.92493151 | I14: 經濟日報 2026-10-08
A15: FY2028 營收 vs FactSet 中位數（05-22） | B15: =fs_rev28 -> 80.811 | C15: =PL!F87 -> 106.64147 | D15: =C15/B15-1 -> 0.31964051 | E15: =PL!F134 -> 70.32444 | F15: =E15/B15-1 -> -0.12976649 | G15: =PL!F181 -> 45.414693 | H15: =G15/B15-1 -> -0.43801347 | I15: FactSet（鉅亨 2026-05-22）
A16: FY2028 EPS vs FactSet 中位數（05-22） | B16: =fs_eps28 -> 204.29 | C16: =PL!F102 -> 259.33968 | D16: =C16/B16-1 -> 0.26946829 | E16: =PL!F149 -> 166.88925 | F16: =E16/B16-1 -> -0.18307678 | G16: =PL!F196 -> 100.74316 | H16: =G16/B16-1 -> -0.506862 | I16: FactSet（鉅亨 2026-05-22） | J16: 平均 191.02
A17: FY2028 EPS vs 亞系券商（08 月） | B17: =ab_eps28 -> 262 | C17: =PL!F102 -> 259.33968 | D17: =C17/B17-1 -> -0.010153907 | E17: =PL!F149 -> 166.88925 | F17: =E17/B17-1 -> -0.36301815 | G17: =PL!F196 -> 100.74316 | H17: =G17/B17-1 -> -0.61548412 | I17: 口袋學堂 2026-08-26 轉引
A18: B. 均熱片與液冷份額（機制檢查）
A19: FY2026 健策 NVIDIA 均熱片份額（校準） | C19: =PL!D75 -> 0.88222542 | E19: =PL!D122 -> 0.88222542 | G19: =PL!D169 -> 0.88222542 | I19: — | J19: 份額第二來源：未找到；公司稱全球前兩大 IHS 供應商
A20: CY2026 健策 AI 均熱片 ÷ 市場合計 | C20: =PL!D79/fx/PL!D74 -> 0.67515158 | E20: =PL!D126/fx/PL!D121 -> 0.67515158 | G20: =PL!D173/fx/PL!D168 -> 0.67515158 | I20: —
A21: CY2027 奇鋐＋健策液冷份額合計 | C21: =avshA_27+PL!E82 -> 0.48898126 | E21: =avshB_27+PL!E129 -> 0.48198126 | G21: =avshC_27+PL!E176 -> 0.47698126 | I21: avc/dist PL 頁（唯讀） | J21: 遠低於 100%：其餘為雙鴻、酷碼、台達電、Boyd、CoolIT 等；雙鴻模型未在 main，未納入
A22: CY2028 奇鋐＋健策液冷份額合計 | C22: =avshA_28+PL!F82 -> 0.47903488 | E22: =avshB_28+PL!F129 -> 0.46403488 | G22: =avshC_28+PL!F176 -> 0.45503488 | I22: avc/dist PL 頁（唯讀） | J22: —
A23: CY2029 奇鋐＋健策液冷份額合計 | C23: =avshA_29+PL!G82 -> 0.46908849 | E23: =avshB_29+PL!G129 -> 0.44908849 | G23: =avshC_29+PL!G176 -> 0.43408849 | I23: avc/dist PL 頁（唯讀） | J23: —
A24: CY2027 Rubin 每顆均熱片 vs 本國投顧假設（≥ US$200） | B24: =200 -> 200 | C24: =PL!E69 -> 200 | D24: =C24/B24-1 -> 0 | E24: =PL!E116 -> 150 | F24: =E24/B24-1 -> -0.25 | G24: =PL!E163 -> 110 | H24: =G24/B24-1 -> -0.45 | I24: 經濟日報 2026-10-08 | J24: 本國投顧假設 800–900 萬顆全採可拆式
A25: FY2027 每顆加速器健策 AI 均熱片營收（US$） | C25: =PL!E90 -> 67.637282 | E25: =PL!E137 -> 50.731684 | G25: =PL!E184 -> 37.363177 | I25: —
A26: C. 校準
A27: 其他營收毛利率（Derived） | C27: =PL!D92 -> 0.42532477 | E27: =PL!D139 -> 0.42532477 | G27: =PL!D186 -> 0.42532477 | I27: FY2026 錨點 | J27: AI 均熱片毛利率＝此值＋d_ai
A28: FY2027 毛利率 vs 券商（逾 50%）（百分點） | B28: =0.5 -> 0.5 | C28: =PL!E94 -> 0.50427811 | D28: =C28-B28 -> 0.0042781097 | E28: =PL!E141 -> 0.49954683 | F28: =E28-B28 -> -0.00045316593 | G28: =PL!E188 -> 0.49300906 | H28: =G28-B28 -> -0.0069909382 | I28: 大和、本國投顧（Interested-party）
A29: 4Q26 EPS（模型） | C29: =Q!E15 -> 23.645315 | E29: =Q!E15 -> 23.645315 | G29: =Q!E15 -> 23.645315 | I29: — | J29: 3Q26 財報 11-09 公布
A30: D. 目標價對帳（模型欄為情境加權值）
A31: 12 個月後的前瞻 EPS（情境加權）vs 共識前瞻 EPS | B31: =cons_feps -> 107.736 | C31: =Val!B35 -> 176.78691 | D31: =C31/B31-1 -> 0.64092702 | I31: In 頁 cons_feps（Derived） | J31: 共識只作對帳，不作校準
A32: 目標價（DCF 與 Comparable 加權）vs 市場共識目標價 | B32: =cons_tp -> 7204 | C32: =Val!B40 -> 3902.8284 | D32: =C32/B32-1 -> -0.45824148 | I32: stockanalysis 2026-10-22（11 位） | J32: 共識只作對帳，不作校準
A33: Comparable 目標價 vs 市場共識目標價 | B33: =cons_tp -> 7204 | C33: =Val!B36 -> 4558.4506 | D33: =C33/B33-1 -> -0.3672334 | I33: 同上 | J33: 共識只作對帳，不作校準
A34: E. 預留
A35: R4 產業部署路徑（markets/deploy_path/，尚未建立）：上線後以部署路徑取代網通模型顆數 | J35: 預留列：本版無數值

Sheet Sens
A1: Sens — 一次動一個輸入（情境 B＝基準輸入；健策份額、其他營收毛利率在每個案例內依 FY2026 錨點重算，FY2026 恆等於錨點）：對 FY2027、FY2028 的營收、AI 均熱片營收、毛利率與 EPS 的影響。每個案例是一個完整推導區塊（本頁下方）
A3: 案例 | B3: 設定 | C3: FY2027 營收 | D3: FY2027 AI 均熱片 | E3: FY2027 毛利率 | F3: FY2027 EPS | G3: FY2027 EPS 相對基準 | H3: FY2028 營收 | I3: FY2028 AI 均熱片 | J3: FY2028 毛利率 | K3: FY2028 EPS | L3: FY2028 EPS 相對基準
A4: 基準（情境 B） | B4: PL 區塊 B | C4: =PL!E134 -> 62.205078 | D4: =PL!E126 -> 38.474909 | E4: =PL!E141 -> 0.49954683 | F4: =PL!E149 -> 147.77851 | G4: =F4/F$4-1 -> 0 | H4: =PL!F134 -> 70.32444 | I4: =PL!F126 -> 41.619471 | J4: =PL!F141 -> 0.49634328 | K4: =PL!F149 -> 166.88925 | L4: =K4/K$4-1 -> 0
A5: 可拆式上蓋 慢（VR 單價 低） | B5: Rubin 每顆 2027 US$110、2028–29 120 | C5: =E77 -> 54.537481 | D5: =E69 -> 30.807312 | E5: =E84 -> 0.49311077 | F5: =E92 -> 127.06309 | G5: =F5/F$4-1 -> -0.14017885 | H5: =F77 -> 61.502751 | I5: =F69 -> 32.797782 | J5: =F84 -> 0.48931758 | K5: =F92 -> 142.93228 | L5: =K5/K$4-1 -> -0.14355009
A6: 可拆式上蓋 快（VR 單價 高） | B6: Rubin 每顆 2027 US$200、2028–29 220 | C6: =E124 -> 71.789575 | D6: =E116 -> 48.059406 | E6: =E131 -> 0.50565856 | F6: =E139 -> 173.67279 | G6: =F6/F$4-1 -> 0.17522356 | H6: =F124 -> 76.205567 | I6: =F116 -> 47.500597 | J6: =F131 -> 0.5001234 | K6: =F139 -> 182.60852 | L6: =K6/K$4-1 -> 0.09418983
A7: AMD、ASIC 單價 低 | B7: AMD 45／50／50、ASIC 30 | C7: =E171 -> 61.274013 | D7: =E163 -> 37.543844 | E7: =E178 -> 0.49885123 | F7: =E186 -> 145.26307 | G7: =F7/F$4-1 -> -0.017021717 | H7: =F171 -> 68.560102 | I7: =F163 -> 39.855133 | J7: =F178 -> 0.49508278 | K7: =F186 -> 162.0696 | L7: =K7/K$4-1 -> -0.028879329
A8: AMD、ASIC 單價 高 | B8: AMD 80／110／110、ASIC 45／55／55 | C8: =E218 -> 63.902903 | D8: =E210 -> 40.172734 | E8: =E225 -> 0.5007631 | F8: =E233 -> 152.3655 | G8: =F8/F$4-1 -> 0.031039602 | H8: =F218 -> 72.718899 | I8: =F210 -> 44.01393 | J8: =F225 -> 0.49795612 | K8: =F233 -> 173.41121 | L8: =K8/K$4-1 -> 0.039079572
A9: 份額流失（低） | B9: 份額相對值 0.92／0.85／0.80（可拆式上蓋新供應商切入） | C9: =E265 -> 60.221835 | D9: =E257 -> 36.491666 | E9: =E272 -> 0.49803926 | F9: =E280 -> 142.42042 | G9: =F9/F$4-1 -> -0.0362576 | H9: =F265 -> 66.744271 | I9: =F257 -> 38.039302 | J9: =F272 -> 0.4937159 | K9: =F280 -> 157.11509 | L9: =K9/K$4-1 -> -0.058566702
A10: 份額守住（高） | B10: 份額相對值 1.00／1.00／0.98 | C10: =E312 -> 63.395024 | D10: =E304 -> 39.664855 | E10: =E319 -> 0.5004061 | F10: =E327 -> 150.99337 | G10: =F10/F$4-1 -> 0.02175456 | H10: =F312 -> 73.457089 | I10: =F304 -> 44.752119 | J10: =F319 -> 0.49843214 | K10: =F327 -> 175.47195 | L10: =K10/K$4-1 -> 0.051427541
A11: 非 NVIDIA 份額比 0.25 | B11: k_non 0.25（FY2026 NVIDIA 份額校準變高） | C11: =E359 -> 63.053483 | D11: =E351 -> 39.323314 | E11: =E366 -> 0.50016279 | F11: =E374 -> 150.07064 | G11: =F11/F$4-1 -> 0.015510518 | H11: =F359 -> 71.187398 | I11: =F351 -> 42.482429 | J11: =F366 -> 0.49693705 | K11: =F374 -> 169.22814 | L11: =K11/K$4-1 -> 0.014014671
A12: 非 NVIDIA 份額比 0.55 | B12: k_non 0.55 | C12: =E406 -> 61.477514 | D12: =E398 -> 37.747345 | E12: =E413 -> 0.49900507 | F12: =E421 -> 145.81286 | G12: =F12/F$4-1 -> -0.013301319 | H12: =F406 -> 69.584396 | I12: =F398 -> 40.879426 | J12: =F413 -> 0.49582235 | K12: =F421 -> 164.88336 | L12: =K12/K$4-1 -> -0.012019289
A13: 2026 AI 占比 32%（讀法） | B13: FY2026 AI 均熱片＝營收 × 32%；份額變低、其他散熱變大 | C13: =E453 -> 57.423467 | D13: =E445 -> 30.779927 | E13: =E460 -> 0.49924676 | F13: =E468 -> 135.96668 | G13: =F13/F$4-1 -> -0.079929311 | H13: =F453 -> 65.205254 | I13: =F445 -> 33.295577 | J13: =F460 -> 0.49620004 | K13: =F468 -> 154.32537 | L13: =K13/K$4-1 -> -0.075282729
A14: 2026 AI 占比 48%（讀法） | B14: FY2026 AI 均熱片＝營收 × 48% | C14: =E500 -> 66.986689 | D14: =E492 -> 46.169891 | E14: =E507 -> 0.49843355 | F14: =E515 -> 159.08658 | G14: =F14/F$4-1 -> 0.076520369 | H14: =F500 -> 75.443627 | I14: =F492 -> 49.943365 | J14: =F507 -> 0.49516427 | K14: =F515 -> 178.9111 | L14: =K14/K$4-1 -> 0.072034906
A15: 液冷份額 低 | B15: 0.3%／0.6%／1.0% | C15: =E547 -> 60.572902 | D15: =E539 -> 38.474909 | E15: =E554 -> 0.5015468 | F15: =E562 -> 144.44363 | G15: =F15/F$4-1 -> -0.022566763 | H15: =F547 -> 66.688139 | I15: =F539 -> 41.619471 | J15: =F554 -> 0.5002157 | K15: =F562 -> 159.33829 | L15: =K15/K$4-1 -> -0.045245331
A16: 液冷份額 高 | B16: 1.5%／3.0%／4.5% | C16: =E594 -> 64.490125 | D16: =E586 -> 38.474909 | E16: =E601 -> 0.49691696 | F16: =E609 -> 152.44735 | G16: =F16/F$4-1 -> 0.031593468 | H16: =F594 -> 76.384942 | I16: =F586 -> 41.619471 | J16: =F601 -> 0.49070856 | K16: =F609 -> 179.50725 | L16: =K16/K$4-1 -> 0.075607071
A17: AI 部署 ×0.8 | B17: FY2027 起顆數與液冷市場 ×0.8 | C17: =E641 -> 53.9878 | D17: =E633 -> 30.779927 | E17: =E648 -> 0.49374007 | F17: =E656 -> 125.92195 | G17: =F17/F$4-1 -> -0.14790085 | H17: =F641 -> 60.788446 | I17: =F633 -> 33.295577 | J17: =F648 -> 0.49105222 | K17: =F656 -> 141.78806 | L17: =K17/K$4-1 -> -0.15040626
A18: AI 部署 ×1.2 | B18: ×1.2 | C18: =E688 -> 70.422356 | D18: =E680 -> 46.169891 | E18: =E695 -> 0.50399847 | F18: =E703 -> 169.63508 | G18: =F18/F$4-1 -> 0.14790085 | H18: =F688 -> 79.860435 | I18: =F680 -> 49.943365 | J18: =F695 -> 0.50037074 | K18: =F703 -> 191.99445 | L18: =K18/K$4-1 -> 0.15043036
A19: AI 毛利率差距 6pt | B19: AI 均熱片毛利率只高 6 個百分點 | C19: =E735 -> 62.205078 | D19: =E727 -> 38.474909 | E19: =E742 -> 0.4864358 | F19: =E750 -> 143.30326 | G19: =F19/F$4-1 -> -0.030283547 | H19: =F735 -> 70.32444 | I19: =F727 -> 41.619471 | J19: =F742 -> 0.48483403 | K19: =F750 -> 162.44796 | L19: =K19/K$4-1 -> -0.026612176
A20: AI 毛利率差距 18pt | B20: 高 18 個百分點 | C20: =E782 -> 62.205078 | D20: =E774 -> 38.474909 | E20: =E789 -> 0.51265786 | F20: =E797 -> 152.25377 | G20: =F20/F$4-1 -> 0.030283547 | H20: =F782 -> 70.32444 | I20: =F774 -> 41.619471 | J20: =F789 -> 0.50785253 | K20: =F797 -> 171.33053 | L20: =K20/K$4-1 -> 0.026612176
A21: 其他散熱成長 低 | B21: +5％／+3％／+2％ | C21: =E829 -> 61.408453 | D21: =E821 -> 38.474909 | E21: =E836 -> 0.50050968 | F21: =E844 -> 146.15084 | G21: =F21/F$4-1 -> -0.01101428 | H21: =F829 -> 68.611697 | I21: =F821 -> 41.619471 | J21: =F836 -> 0.4981161 | K21: =F844 -> 163.33323 | L21: =K21/K$4-1 -> -0.021307625
A22: 其他散熱成長 高 | B22: +20％／+15％／+12％ | C22: =E876 -> 63.115507 | D22: =E868 -> 38.474909 | E22: =E883 -> 0.4984762 | F22: =E891 -> 149.63871 | G22: =F22/F$4-1 -> 0.012587748 | H22: =F876 -> 72.008733 | I22: =F868 -> 41.619471 | J22: =F883 -> 0.49468215 | K22: =F891 -> 170.38135 | L22: =K22/K$4-1 -> 0.020924689
A23: 營業費用彈性 0.9 | B23: 基準 0.6 | C23: =E923 -> 62.205078 | D23: =E915 -> 38.474909 | E23: =E930 -> 0.49954683 | F23: =E938 -> 143.46379 | G23: =F23/F$4-1 -> -0.029197263 | H23: =F923 -> 70.32444 | I23: =F915 -> 41.619471 | J23: =F930 -> 0.49634328 | K23: =F938 -> 161.11296 | L23: =K23/K$4-1 -> -0.034611473
A24: 營業費用率 +2pt | B24: 營業費用額外 +2% × 營收 | C24: =E970 -> 62.205078 | D24: =E962 -> 38.474909 | E24: =E977 -> 0.49954683 | F24: =E985 -> 140.95181 | G24: =F24/F$4-1 -> -0.046195525 | H24: =F970 -> 70.32444 | I24: =F962 -> 41.619471 | J24: =F977 -> 0.49634328 | K24: =F985 -> 159.17148 | L24: =K24/K$4-1 -> -0.046244841
A25: 情境 A（全部） | B25: 顆數係數 A＋液冷市場 A＋可拆式上蓋、份額、液冷份額高值 | C25: =PL!E87 -> 77.964201 | D25: =PL!E79 -> 51.296115 | E25: =PL!E94 -> 0.50427811 | F25: =PL!E102 -> 188.42014 | G25: =F25/F$4-1 -> 0.27501717 | H25: =PL!F87 -> 106.64147 | I25: =PL!F79 -> 67.063247 | J25: =PL!F94 -> 0.50078875 | K25: =PL!F102 -> 259.33968 | L25: =K25/K$4-1 -> 0.55396278
A26: 情境 C（全部） | B26: 顆數係數 C＋液冷市場 C＋低值 | C26: =PL!E181 -> 50.238365 | D26: =PL!E173 -> 28.336233 | E26: =PL!E188 -> 0.49300906 | F26: =PL!E196 -> 116.65195 | G26: =F26/F$4-1 -> -0.21062982 | H26: =PL!F181 -> 45.414693 | I26: =PL!F173 -> 21.272925 | J26: =PL!F188 -> 0.48153458 | K26: =PL!F196 -> 100.74316 | L26: =K26/K$4-1 -> -0.39634719
A28: 讀法：基準為情境 B（顆數係數 B 從 CY2028 起）。每個案例的 FY2026 份額與其他營收毛利率依該案例重算，所以 FY2026 恆等於錨點。「2026 AI 占比」與「非 NVIDIA 份額比」只改校準：AI 占比高 → 份額高、其他散熱小，FY2027 起成長更集中在均熱片。
A30: 目標價參數（只改 DCF 參數；PL 收斂法的 fade_g 不隨 tp_g 變動）
A31: 案例 | B31: 設定 | C31: DCF 目標價 | D31: Comparable 目標價 | E31: 加權目標價 | F31: 相對基準
A32: 基準 | B32: r 10%、g 4%、DCF 權重 0.5 | C32: =(tp_wA*MAX(0,Val!B8*(1-MIN(tp_g/tp_roe,0.8))/(1+tp_r)^1+Val!B9*(1-MIN(tp_g/tp_roe,0.8))/(1+tp_r)^2+Val!B10*(1-MIN(tp_g/tp_roe,0.8))/(1+tp_r)^3+Val!B11*(1-MIN(tp_g/tp_roe,0.8))/(1+tp_r)^4+Val!B12*(1-MIN(tp_g/tp_roe,0.8))/(1+tp_r)^5+Val!B13*(1-MIN(tp_g/tp_roe,0.8))/(1+tp_r)^6+Val!B13*(1-MIN(tp_g/tp_roe,0.8))*(1+tp_g)/(tp_r-tp_g)/(1+tp_r)^6)+tp_wB*MAX(0,Val!C8*(1-MIN(tp_g/tp_roe,0.8))/(1+tp_r)^1+Val!C9*(1-MIN(tp_g/tp_roe,0.8))/(1+tp_r)^2+Val!C10*(1-MIN(tp_g/tp_roe,0.8))/(1+tp_r)^3+Val!C11*(1-MIN(tp_g/tp_roe,0.8))/(1+tp_r)^4+Val!C12*(1-MIN(tp_g/tp_roe,0.8))/(1+tp_r)^5+Val!C13*(1-MIN(tp_g/tp_roe,0.8))/(1+tp_r)^6+Val!C13*(1-MIN(tp_g/tp_roe,0.8))*(1+tp_g)/(tp_r-tp_g)/(1+tp_r)^6)+tp_wC*MAX(0,Val!D8*(1-MIN(tp_g/tp_roe,0.8))/(1+tp_r)^1+Val!D9*(1-MIN(tp_g/tp_roe,0.8))/(1+tp_r)^2+Val!D10*(1-MIN(tp_g/tp_roe,0.8))/(1+tp_r)^3+Val!D11*(1-MIN(tp_g/tp_roe,0.8))/(1+tp_r)^4+Val!D12*(1-MIN(tp_g/tp_roe,0.8))/(1+tp_r)^5+Val!D13*(1-MIN(tp_g/tp_roe,0.8))/(1+tp_r)^6+Val!D13*(1-MIN(tp_g/tp_roe,0.8))*(1+tp_g)/(tp_r-tp_g)/(1+tp_r)^6))*(1+tp_r) -> 3247.2062 | D32: =Val!B36 -> 4558.4506 | E32: =tp_w_dcf*C32+(1-tp_w_dcf)*D32 -> 3902.8284 | F32: =E32/E$32-1 -> 0
A33: 折現率 +1pt | B33: r 11% | C33: =(tp_wA*MAX(0,Val!B8*(1-MIN(tp_g/tp_roe,0.8))/(1+(tp_r+0.01))^1+Val!B9*(1-MIN(tp_g/tp_roe,0.8))/(1+(tp_r+0.01))^2+Val!B10*(1-MIN(tp_g/tp_roe,0.8))/(1+(tp_r+0.01))^3+Val!B11*(1-MIN(tp_g/tp_roe,0.8))/(1+(tp_r+0.01))^4+Val!B12*(1-MIN(tp_g/tp_roe,0.8))/(1+(tp_r+0.01))^5+Val!B13*(1-MIN(tp_g/tp_roe,0.8))/(1+(tp_r+0.01))^6+Val!B13*(1-MIN(tp_g/tp_roe,0.8))*(1+tp_g)/((tp_r+0.01)-tp_g)/(1+(tp_r+0.01))^6)+tp_wB*MAX(0,Val!C8*(1-MIN(tp_g/tp_roe,0.8))/(1+(tp_r+0.01))^1+Val!C9*(1-MIN(tp_g/tp_roe,0.8))/(1+(tp_r+0.01))^2+Val!C10*(1-MIN(tp_g/tp_roe,0.8))/(1+(tp_r+0.01))^3+Val!C11*(1-MIN(tp_g/tp_roe,0.8))/(1+(tp_r+0.01))^4+Val!C12*(1-MIN(tp_g/tp_roe,0.8))/(1+(tp_r+0.01))^5+Val!C13*(1-MIN(tp_g/tp_roe,0.8))/(1+(tp_r+0.01))^6+Val!C13*(1-MIN(tp_g/tp_roe,0.8))*(1+tp_g)/((tp_r+0.01)-tp_g)/(1+(tp_r+0.01))^6)+tp_wC*MAX(0,Val!D8*(1-MIN(tp_g/tp_roe,0.8))/(1+(tp_r+0.01))^1+Val!D9*(1-MIN(tp_g/tp_roe,0.8))/(1+(tp_r+0.01))^2+Val!D10*(1-MIN(tp_g/tp_roe,0.8))/(1+(tp_r+0.01))^3+Val!D11*(1-MIN(tp_g/tp_roe,0.8))/(1+(tp_r+0.01))^4+Val!D12*(1-MIN(tp_g/tp_roe,0.8))/(1+(tp_r+0.01))^5+Val!D13*(1-MIN(tp_g/tp_roe,0.8))/(1+(tp_r+0.01))^6+Val!D13*(1-MIN(tp_g/tp_roe,0.8))*(1+tp_g)/((tp_r+0.01)-tp_g)/(1+(tp_r+0.01))^6))*(1+(tp_r+0.01)) -> 2795.6424 | D33: =Val!B36 -> 4558.4506 | E33: =tp_w_dcf*C33+(1-tp_w_dcf)*D33 -> 3677.0465 | F33: =E33/E$32-1 -> -0.057850839
A34: 折現率 −1pt | B34: r 9% | C34: =(tp_wA*MAX(0,Val!B8*(1-MIN(tp_g/tp_roe,0.8))/(1+(tp_r-0.01))^1+Val!B9*(1-MIN(tp_g/tp_roe,0.8))/(1+(tp_r-0.01))^2+Val!B10*(1-MIN(tp_g/tp_roe,0.8))/(1+(tp_r-0.01))^3+Val!B11*(1-MIN(tp_g/tp_roe,0.8))/(1+(tp_r-0.01))^4+Val!B12*(1-MIN(tp_g/tp_roe,0.8))/(1+(tp_r-0.01))^5+Val!B13*(1-MIN(tp_g/tp_roe,0.8))/(1+(tp_r-0.01))^6+Val!B13*(1-MIN(tp_g/tp_roe,0.8))*(1+tp_g)/((tp_r-0.01)-tp_g)/(1+(tp_r-0.01))^6)+tp_wB*MAX(0,Val!C8*(1-MIN(tp_g/tp_roe,0.8))/(1+(tp_r-0.01))^1+Val!C9*(1-MIN(tp_g/tp_roe,0.8))/(1+(tp_r-0.01))^2+Val!C10*(1-MIN(tp_g/tp_roe,0.8))/(1+(tp_r-0.01))^3+Val!C11*(1-MIN(tp_g/tp_roe,0.8))/(1+(tp_r-0.01))^4+Val!C12*(1-MIN(tp_g/tp_roe,0.8))/(1+(tp_r-0.01))^5+Val!C13*(1-MIN(tp_g/tp_roe,0.8))/(1+(tp_r-0.01))^6+Val!C13*(1-MIN(tp_g/tp_roe,0.8))*(1+tp_g)/((tp_r-0.01)-tp_g)/(1+(tp_r-0.01))^6)+tp_wC*MAX(0,Val!D8*(1-MIN(tp_g/tp_roe,0.8))/(1+(tp_r-0.01))^1+Val!D9*(1-MIN(tp_g/tp_roe,0.8))/(1+(tp_r-0.01))^2+Val!D10*(1-MIN(tp_g/tp_roe,0.8))/(1+(tp_r-0.01))^3+Val!D11*(1-MIN(tp_g/tp_roe,0.8))/(1+(tp_r-0.01))^4+Val!D12*(1-MIN(tp_g/tp_roe,0.8))/(1+(tp_r-0.01))^5+Val!D13*(1-MIN(tp_g/tp_roe,0.8))/(1+(tp_r-0.01))^6+Val!D13*(1-MIN(tp_g/tp_roe,0.8))*(1+tp_g)/((tp_r-0.01)-tp_g)/(1+(tp_r-0.01))^6))*(1+(tp_r-0.01)) -> 3879.5729 | D34: =Val!B36 -> 4558.4506 | E34: =tp_w_dcf*C34+(1-tp_w_dcf)*D34 -> 4219.0117 | F34: =E34/E$32-1 -> 0.081013898
A35: 長期成長 +1pt | B35: g 5% | C35: =(tp_wA*MAX(0,Val!B8*(1-MIN((tp_g+0.01)/tp_roe,0.8))/(1+tp_r)^1+Val!B9*(1-MIN((tp_g+0.01)/tp_roe,0.8))/(1+tp_r)^2+Val!B10*(1-MIN((tp_g+0.01)/tp_roe,0.8))/(1+tp_r)^3+Val!B11*(1-MIN((tp_g+0.01)/tp_roe,0.8))/(1+tp_r)^4+Val!B12*(1-MIN((tp_g+0.01)/tp_roe,0.8))/(1+tp_r)^5+Val!B13*(1-MIN((tp_g+0.01)/tp_roe,0.8))/(1+tp_r)^6+Val!B13*(1-MIN((tp_g+0.01)/tp_roe,0.8))*(1+(tp_g+0.01))/(tp_r-(tp_g+0.01))/(1+tp_r)^6)+tp_wB*MAX(0,Val!C8*(1-MIN((tp_g+0.01)/tp_roe,0.8))/(1+tp_r)^1+Val!C9*(1-MIN((tp_g+0.01)/tp_roe,0.8))/(1+tp_r)^2+Val!C10*(1-MIN((tp_g+0.01)/tp_roe,0.8))/(1+tp_r)^3+Val!C11*(1-MIN((tp_g+0.01)/tp_roe,0.8))/(1+tp_r)^4+Val!C12*(1-MIN((tp_g+0.01)/tp_roe,0.8))/(1+tp_r)^5+Val!C13*(1-MIN((tp_g+0.01)/tp_roe,0.8))/(1+tp_r)^6+Val!C13*(1-MIN((tp_g+0.01)/tp_roe,0.8))*(1+(tp_g+0.01))/(tp_r-(tp_g+0.01))/(1+tp_r)^6)+tp_wC*MAX(0,Val!D8*(1-MIN((tp_g+0.01)/tp_roe,0.8))/(1+tp_r)^1+Val!D9*(1-MIN((tp_g+0.01)/tp_roe,0.8))/(1+tp_r)^2+Val!D10*(1-MIN((tp_g+0.01)/tp_roe,0.8))/(1+tp_r)^3+Val!D11*(1-MIN((tp_g+0.01)/tp_roe,0.8))/(1+tp_r)^4+Val!D12*(1-MIN((tp_g+0.01)/tp_roe,0.8))/(1+tp_r)^5+Val!D13*(1-MIN((tp_g+0.01)/tp_roe,0.8))/(1+tp_r)^6+Val!D13*(1-MIN((tp_g+0.01)/tp_roe,0.8))*(1+(tp_g+0.01))/(tp_r-(tp_g+0.01))/(1+tp_r)^6))*(1+tp_r) -> 3568.929 | D35: =Val!B36 -> 4558.4506 | E35: =tp_w_dcf*C35+(1-tp_w_dcf)*D35 -> 4063.6898 | F35: =E35/E$32-1 -> 0.041216621
A36: 長期成長 −1pt | B36: g 3% | C36: =(tp_wA*MAX(0,Val!B8*(1-MIN((tp_g-0.01)/tp_roe,0.8))/(1+tp_r)^1+Val!B9*(1-MIN((tp_g-0.01)/tp_roe,0.8))/(1+tp_r)^2+Val!B10*(1-MIN((tp_g-0.01)/tp_roe,0.8))/(1+tp_r)^3+Val!B11*(1-MIN((tp_g-0.01)/tp_roe,0.8))/(1+tp_r)^4+Val!B12*(1-MIN((tp_g-0.01)/tp_roe,0.8))/(1+tp_r)^5+Val!B13*(1-MIN((tp_g-0.01)/tp_roe,0.8))/(1+tp_r)^6+Val!B13*(1-MIN((tp_g-0.01)/tp_roe,0.8))*(1+(tp_g-0.01))/(tp_r-(tp_g-0.01))/(1+tp_r)^6)+tp_wB*MAX(0,Val!C8*(1-MIN((tp_g-0.01)/tp_roe,0.8))/(1+tp_r)^1+Val!C9*(1-MIN((tp_g-0.01)/tp_roe,0.8))/(1+tp_r)^2+Val!C10*(1-MIN((tp_g-0.01)/tp_roe,0.8))/(1+tp_r)^3+Val!C11*(1-MIN((tp_g-0.01)/tp_roe,0.8))/(1+tp_r)^4+Val!C12*(1-MIN((tp_g-0.01)/tp_roe,0.8))/(1+tp_r)^5+Val!C13*(1-MIN((tp_g-0.01)/tp_roe,0.8))/(1+tp_r)^6+Val!C13*(1-MIN((tp_g-0.01)/tp_roe,0.8))*(1+(tp_g-0.01))/(tp_r-(tp_g-0.01))/(1+tp_r)^6)+tp_wC*MAX(0,Val!D8*(1-MIN((tp_g-0.01)/tp_roe,0.8))/(1+tp_r)^1+Val!D9*(1-MIN((tp_g-0.01)/tp_roe,0.8))/(1+tp_r)^2+Val!D10*(1-MIN((tp_g-0.01)/tp_roe,0.8))/(1+tp_r)^3+Val!D11*(1-MIN((tp_g-0.01)/tp_roe,0.8))/(1+tp_r)^4+Val!D12*(1-MIN((tp_g-0.01)/tp_roe,0.8))/(1+tp_r)^5+Val!D13*(1-MIN((tp_g-0.01)/tp_roe,0.8))/(1+tp_r)^6+Val!D13*(1-MIN((tp_g-0.01)/tp_roe,0.8))*(1+(tp_g-0.01))/(tp_r-(tp_g-0.01))/(1+tp_r)^6))*(1+tp_r) -> 3027.4715 | D36: =Val!B36 -> 4558.4506 | E36: =tp_w_dcf*C36+(1-tp_w_dcf)*D36 -> 3792.961 | F36: =E36/E$32-1 -> -0.028150699
A37: DCF 權重 0.3 | C37: =(tp_wA*MAX(0,Val!B8*(1-MIN(tp_g/tp_roe,0.8))/(1+tp_r)^1+Val!B9*(1-MIN(tp_g/tp_roe,0.8))/(1+tp_r)^2+Val!B10*(1-MIN(tp_g/tp_roe,0.8))/(1+tp_r)^3+Val!B11*(1-MIN(tp_g/tp_roe,0.8))/(1+tp_r)^4+Val!B12*(1-MIN(tp_g/tp_roe,0.8))/(1+tp_r)^5+Val!B13*(1-MIN(tp_g/tp_roe,0.8))/(1+tp_r)^6+Val!B13*(1-MIN(tp_g/tp_roe,0.8))*(1+tp_g)/(tp_r-tp_g)/(1+tp_r)^6)+tp_wB*MAX(0,Val!C8*(1-MIN(tp_g/tp_roe,0.8))/(1+tp_r)^1+Val!C9*(1-MIN(tp_g/tp_roe,0.8))/(1+tp_r)^2+Val!C10*(1-MIN(tp_g/tp_roe,0.8))/(1+tp_r)^3+Val!C11*(1-MIN(tp_g/tp_roe,0.8))/(1+tp_r)^4+Val!C12*(1-MIN(tp_g/tp_roe,0.8))/(1+tp_r)^5+Val!C13*(1-MIN(tp_g/tp_roe,0.8))/(1+tp_r)^6+Val!C13*(1-MIN(tp_g/tp_roe,0.8))*(1+tp_g)/(tp_r-tp_g)/(1+tp_r)^6)+tp_wC*MAX(0,Val!D8*(1-MIN(tp_g/tp_roe,0.8))/(1+tp_r)^1+Val!D9*(1-MIN(tp_g/tp_roe,0.8))/(1+tp_r)^2+Val!D10*(1-MIN(tp_g/tp_roe,0.8))/(1+tp_r)^3+Val!D11*(1-MIN(tp_g/tp_roe,0.8))/(1+tp_r)^4+Val!D12*(1-MIN(tp_g/tp_roe,0.8))/(1+tp_r)^5+Val!D13*(1-MIN(tp_g/tp_roe,0.8))/(1+tp_r)^6+Val!D13*(1-MIN(tp_g/tp_roe,0.8))*(1+tp_g)/(tp_r-tp_g)/(1+tp_r)^6))*(1+tp_r) -> 3247.2062 | D37: =Val!B36 -> 4558.4506 | E37: =0.3*C37+(1-0.3)*D37 -> 4165.0773 | F37: =E37/E$32-1 -> 0.067194567
A38: DCF 權重 0.7 | C38: =(tp_wA*MAX(0,Val!B8*(1-MIN(tp_g/tp_roe,0.8))/(1+tp_r)^1+Val!B9*(1-MIN(tp_g/tp_roe,0.8))/(1+tp_r)^2+Val!B10*(1-MIN(tp_g/tp_roe,0.8))/(1+tp_r)^3+Val!B11*(1-MIN(tp_g/tp_roe,0.8))/(1+tp_r)^4+Val!B12*(1-MIN(tp_g/tp_roe,0.8))/(1+tp_r)^5+Val!B13*(1-MIN(tp_g/tp_roe,0.8))/(1+tp_r)^6+Val!B13*(1-MIN(tp_g/tp_roe,0.8))*(1+tp_g)/(tp_r-tp_g)/(1+tp_r)^6)+tp_wB*MAX(0,Val!C8*(1-MIN(tp_g/tp_roe,0.8))/(1+tp_r)^1+Val!C9*(1-MIN(tp_g/tp_roe,0.8))/(1+tp_r)^2+Val!C10*(1-MIN(tp_g/tp_roe,0.8))/(1+tp_r)^3+Val!C11*(1-MIN(tp_g/tp_roe,0.8))/(1+tp_r)^4+Val!C12*(1-MIN(tp_g/tp_roe,0.8))/(1+tp_r)^5+Val!C13*(1-MIN(tp_g/tp_roe,0.8))/(1+tp_r)^6+Val!C13*(1-MIN(tp_g/tp_roe,0.8))*(1+tp_g)/(tp_r-tp_g)/(1+tp_r)^6)+tp_wC*MAX(0,Val!D8*(1-MIN(tp_g/tp_roe,0.8))/(1+tp_r)^1+Val!D9*(1-MIN(tp_g/tp_roe,0.8))/(1+tp_r)^2+Val!D10*(1-MIN(tp_g/tp_roe,0.8))/(1+tp_r)^3+Val!D11*(1-MIN(tp_g/tp_roe,0.8))/(1+tp_r)^4+Val!D12*(1-MIN(tp_g/tp_roe,0.8))/(1+tp_r)^5+Val!D13*(1-MIN(tp_g/tp_roe,0.8))/(1+tp_r)^6+Val!D13*(1-MIN(tp_g/tp_roe,0.8))*(1+tp_g)/(tp_r-tp_g)/(1+tp_r)^6))*(1+tp_r) -> 3247.2062 | D38: =Val!B36 -> 4558.4506 | E38: =0.7*C38+(1-0.7)*D38 -> 3640.5795 | F38: =E38/E$32-1 -> -0.067194567
A50: 案例區塊：可拆式上蓋 慢（VR 單價 低）（情境 B）
A51: 項目 | B51: 單位 | C51: FY2025A | D51: FY2026（錨點） | E51: FY2027 | F51: FY2028 | G51: FY2029 | H51: FY2030（收斂） | I51: FY2031（收斂） | J51: FY2032（收斂） | K51: 說明
A52: A. AI 加速器顆數與均熱片市場（D 欄＝FY2026 校準年；E–G＝FY2027–FY2029；顆數 × 同字母情境係數）
A53: Blackwell 顆數 | B53: 百萬顆 | D53: =(u_bw26)*1 -> 5.4 | E53: =(u_bw27)*1*1 -> 2.4 | F53: =(u_bw28)*um28_B*1 -> 0.4 | G53: =(u_bw29)*um29_B*1 -> 0.2125
A54: Hopper 顆數 | B54: 百萬顆 | D54: =(u_hp26)*1 -> 0.5 | E54: =(u_hp27)*1*1 -> 0 | F54: =(u_hp28)*um28_B*1 -> 0 | G54: =(u_hp29)*um29_B*1 -> 0
A55: Rubin 顆數 | B55: 百萬顆 | D55: =(u_rb26)*1 -> 1.7 | E55: =(u_rb27)*1*1 -> 7 | F55: =(u_rb28)*um28_B*1 -> 5.6 | G55: =(u_rb29)*um29_B*1 -> 6.8425
A56: Rubin Ultra 顆數 | B56: 百萬顆 | D56: =(u_ru26)*1 -> 0 | E56: =(u_ru27)*1*1 -> 0.3 | F56: =(u_ru28)*um28_B*1 -> 1.6 | G56: =(u_ru29)*um29_B*1 -> 1.955
A57: AMD Instinct 顆數 | B57: 百萬顆 | D57: =(u_amd26)*1 -> 0.75 | E57: =(u_amd27)*1*1 -> 1.5 | F57: =(u_amd28)*um28_B*1 -> 1.6 | G57: =(u_amd29)*um29_B*1 -> 1.955
A58: ASIC 顆數（TPU＋Trainium＋其他） | B58: 百萬顆 | D58: =(u_tpu26+u_trn26+u_oth26)*1 -> 6.85 | E58: =(u_tpu27+u_trn27+u_oth27)*1*1 -> 12.5 | F58: =(u_tpu28+u_trn28+u_oth28)*um28_B*1 -> 12 | G58: =(u_tpu29+u_trn29+u_oth29)*um29_B*1 -> 14.6625
A59: Rubin 每顆均熱片／上蓋 | B59: US$/顆 | D59: =asp_vr_26 -> 100 | E59: =VRLO_27 -> 110 | F59: =VRLO_28 -> 120 | G59: =VRLO_29 -> 120
A60: AMD 每顆均熱片／上蓋 | B60: US$/顆 | D60: =asp_amd_26 -> 40 | E60: =asp_amd_27 -> 60 | F60: =asp_amd_28 -> 80 | G60: =asp_amd_29 -> 80
A61: ASIC 每顆均熱片＋加強環 | B61: US$/顆 | D61: =asp_asic_26 -> 30 | E61: =asp_asic_27 -> 35 | F61: =asp_asic_28 -> 40 | G61: =asp_asic_29 -> 40
A62: NVIDIA 加速器均熱片市場（美元） | B62: US$B | D62: =(D53*asp_bw+D54*asp_hp+D55*D59+D56*asp_ru)/1000 -> 0.3665 | E62: =(E53*asp_bw+E54*asp_hp+E55*E59+E56*asp_ru)/1000 -> 0.914 | F62: =(F53*asp_bw+F54*asp_hp+F55*F59+F56*asp_ru)/1000 -> 1.006 | G62: =(G53*asp_bw+G54*asp_hp+G55*G59+G56*asp_ru)/1000 -> 1.2195375 | K62: 百萬顆 × 美元 ÷ 1000＝十億美元
A63: 非 NVIDIA（AMD、ASIC）均熱片市場（美元） | B63: US$B | D63: =(D57*D60+D58*D61)/1000 -> 0.2355 | E63: =(E57*E60+E58*E61)/1000 -> 0.5275 | F63: =(F57*F60+F58*F61)/1000 -> 0.608 | G63: =(G57*G60+G58*G61)/1000 -> 0.7429
A64: AI 加速器均熱片市場合計 | B64: US$B | D64: =D62+D63 -> 0.602 | E64: =E62+E63 -> 1.4415 | F64: =F62+F63 -> 1.614 | G64: =G62+G63 -> 1.9624375
A65: 健策 NVIDIA 份額（FY2026 校準）＝ AI 均熱片營收 ÷（NVIDIA 市場＋k × 非 NVIDIA 市場） | B65: % | D65: =a26_rev*ai_26/fx/(D62+k_non*D63) -> 0.88222542 | K65: Derived：分子為 FY2026 錨點營收 × AI 占比（Assumed）；k＝非 NVIDIA 份額 ÷ NVIDIA 份額
A66: 份額相對值（÷ FY2026） | B66: x | D66: =1 -> 1 | E66: =rel_27 -> 0.97 | F66: =rel_28 -> 0.93 | G66: =rel_29 -> 0.9
A67: 健策 NVIDIA 均熱片份額 | B67: % | D67: =$D$65*D66 -> 0.88222542 | E67: =$D$65*E66 -> 0.85575866 | F67: =$D$65*F66 -> 0.82046964 | G67: =$D$65*G66 -> 0.79400288
A68: 健策非 NVIDIA 均熱片份額 | B68: % | D68: =D67*k_non -> 0.35289017 | E68: =E67*k_non -> 0.34230346 | F68: =F67*k_non -> 0.32818786 | G68: =G67*k_non -> 0.31760115
A69: AI 加速器均熱片營收 | B69: NT$B | C69: =a25_ail -> 6.0828 | D69: =(D62*D67+D63*D68)*fx -> 13.00612 | E69: =(E62*E67+E63*E68)*fx -> 30.807312 | F69: =(F62*F67+F63*F68)*fx -> 32.797782 | G69: =(G62*G67+G63*G68)*fx -> 38.53639
A70: B. 液冷冷板元件（奇鋐模型同字母情境的液冷市場 × 健策份額）
A71: AI 液冷市場（奇鋐模型；美元） | B71: US$B | D71: =lmkB_26 -> 4.5136876 | E71: =lmkB_27*1 -> 10.2011 | F71: =lmkB_28*1 -> 12.626045 | G71: =lmkB_29*1 -> 16.180944 | K71: 唯讀 avc/dist PL 頁同字母情境；FY2026 健策液冷含在其他散熱內
A72: 健策液冷份額 | B72: % | D72: =0 -> 0 | E72: =lcs_27 -> 0.008 | F72: =lcs_28 -> 0.015 | G72: =lcs_29 -> 0.025
A73: 液冷冷板元件營收（MCL、MLCP） | B73: NT$B | C73: =0 -> 0 | D73: =D71*D72*fx -> 0 | E73: =E71*E72*fx -> 2.6114817 | F73: =F71*F72*fx -> 6.0605015 | G73: =G71*G72*fx -> 12.944755
A74: C. 其他散熱、導線架與合計
A75: 其他散熱營收（CPU 均熱片、交換器加強環、CPO、ILM、車用水冷） | B75: NT$B | C75: =a25_oth -> 8.637576 | D75: =a26_rev*(th_26-ai_26) -> 11.380355 | E75: =D75*(1+g_oth_27) -> 12.745998 | F75: =E75*(1+g_oth_28) -> 14.020597 | G75: =F75*(1+g_oth_29) -> 15.142245
A76: 導線架、精密沖壓與其他營收 | B76: NT$B | C76: =a25_lf -> 5.555624 | D76: =a26_lf -> 8.128825 | E76: =D76*(1+g_lf_27) -> 8.3726897 | F76: =E76*(1+g_lf_28) -> 8.6238704 | G76: =F76*(1+g_lf_29) -> 8.8825866
A77: 營收 | B77: NT$B | C77: =C69+C73+C75+C76 -> 20.276 | D77: =D69+D73+D75+D76 -> 32.5153 | E77: =E69+E73+E75+E76 -> 54.537481 | F77: =F69+F73+F75+F76 -> 61.502751 | G77: =G69+G73+G75+G76 -> 75.505976 | H77: =G77*(1+H78) -> 87.973752 | I77: =H77*(1+I78) -> 96.996473 | J77: =I77*(1+J78) -> 100.87633 | K77: FY2030 起為收斂法：營收年增由 FY2029 線性收斂到 fade_g、淨利率收斂到 fade_m（FY2032 達到），非驅動因子推導
A78: 營收年增 | B78: % | D78: =D77/C77-1 -> 0.60363484 | E78: =E77/D77-1 -> 0.67728671 | F78: =F77/E77-1 -> 0.12771529 | G78: =G77/F77-1 -> 0.22768454 | H78: =$G78+(fade_gB-$G78)*1/3 -> 0.16512303 | I78: =$G78+(fade_gB-$G78)*2/3 -> 0.10256151 | J78: =$G78+(fade_gB-$G78)*3/3 -> 0.04
A79: AI 加速器均熱片 ÷ 營收 | B79: % | C79: =C69/C77 -> 0.3 | D79: =D69/D77 -> 0.4 | E79: =E69/E77 -> 0.56488329 | F79: =F69/F77 -> 0.53327341 | G79: =G69/G77 -> 0.51037536
A80: 每顆加速器健策 AI 均熱片營收（全部加速器平均） | B80: US$/顆 | D80: =D69/fx*1000/(D53+D54+D55+D56+D57+D58) -> 26.739556 | E80: =E69/fx*1000/(E53+E54+E55+E56+E57+E58) -> 40.621455 | F80: =F69/fx*1000/(F53+F54+F55+F56+F57+F58) -> 48.345786 | G80: =G69/fx*1000/(G53+G54+G55+G56+G57+G58) -> 46.991013
A81: D. 損益
A82: 其他營收毛利率 ＝ 錨點毛利率 − 差距 × AI 占比（FY2026 校準） | B82: % | D82: =a26_gp/D77-d_ai*D79 -> 0.42532477 | K82: Derived：讓 FY2026 毛利率等於錨點；AI 均熱片毛利率＝其他＋差距；液冷與其他營收同毛利率
A83: 毛利 | B83: NT$B | C83: =a25_gp -> 8.434 | D83: =a26_gp -> 15.390297 | E83: =$D$82*E77+d_ai*E69 -> 26.893019 | F83: =$D$82*F77+d_ai*F69 -> 30.094377 | G83: =$D$82*G77+d_ai*G69 -> 36.738929
A84: 毛利率 | B84: % | C84: =C83/C77 -> 0.41595976 | D84: =D83/D77 -> 0.47332477 | E84: =E83/E77 -> 0.49311077 | F84: =F83/F77 -> 0.48931758 | G84: =G83/G77 -> 0.48656982
A85: 營業費用（基準路徑） | B85: NT$B | C85: =a25_opx -> 1.936 | D85: =a26_opx -> 2.8705005 | E85: =D85*(1+MAX(0,phi*E78)) -> 4.0369916 | F85: =E85*(1+MAX(0,phi*F78)) -> 4.3463429 | G85: =F85*(1+MAX(0,phi*G78)) -> 4.9401
A86: 營業費用 | B86: NT$B | C86: =C85 -> 1.936 | D86: =D85 -> 2.8705005 | E86: =E85+0*E77 -> 4.0369916 | F86: =F85+0*F77 -> 4.3463429 | G86: =G85+0*G77 -> 4.9401
A87: 營業利益 | B87: NT$B | C87: =C83-C86 -> 6.498 | D87: =D83-D86 -> 12.519796 | E87: =E83-E86 -> 22.856027 | F87: =F83-F86 -> 25.748034 | G87: =G83-G86 -> 31.798829
A88: 營業利益率 | B88: % | C88: =C87/C77 -> 0.32047741 | D88: =D87/D77 -> 0.38504324 | E88: =E87/E77 -> 0.41908843 | F88: =F87/F77 -> 0.4186485 | G88: =G87/G77 -> 0.42114321
A89: 業外收益 | B89: NT$B | C89: =a25_nop -> 0.109 | D89: =a26_nop -> 0.3305 | E89: =nop_f -> 0.3 | F89: =nop_f -> 0.3 | G89: =nop_f -> 0.3
A90: 歸屬母公司淨利 | B90: NT$B | C90: =a25_ni -> 5.277 | D90: =a26_ni -> 10.344206 | E90: =(E87+E89)*nir_f -> 18.640602 | F90: =(F87+F89)*nir_f -> 20.968668 | G90: =(G87+G89)*nir_f -> 25.839557 | H90: =H77*H94 -> 29.022047 | I90: =I77*I94 -> 30.803176 | J90: =J77*J94 -> 30.792071
A91: 股數 | B91: 十億股 | C91: =a25_sh -> 0.14359184 | D91: =a26_sh -> 0.14670351 | E91: =D91*(1+sh_g) -> 0.14670351 | F91: =E91*(1+sh_g) -> 0.14670351 | G91: =F91*(1+sh_g) -> 0.14670351 | H91: =G91*(1+sh_g) -> 0.14670351 | I91: =H91*(1+sh_g) -> 0.14670351 | J91: =I91*(1+sh_g) -> 0.14670351
A92: EPS | B92: NT$ | C92: =C90/C91 -> 36.75 | D92: =D90/D91 -> 70.510964 | E92: =E90/E91 -> 127.06309 | F92: =F90/F91 -> 142.93228 | G92: =G90/G91 -> 176.13455 | H92: =H90/H91 -> 197.82789 | I92: =I90/I91 -> 209.9689 | J92: =J90/J91 -> 209.89321
A93: EPS 年增 | B93: % | D93: =D92/C92-1 -> 0.91866569 | E93: =E92/D92-1 -> 0.80203311 | F93: =F92/E92-1 -> 0.12489219 | G93: =G92/F92-1 -> 0.23229372 | H93: =H92/G92-1 -> 0.12316346 | I93: =I92/H92-1 -> 0.061371598 | J93: =J92/I92-1 -> -0.00036052245
A94: 淨利率（歸屬母公司淨利 ÷ 營收） | B94: % | C94: =C90/C77 -> 0.26025843 | D94: =D90/D77 -> 0.3181335 | E94: =E90/E77 -> 0.34179434 | F94: =F90/F77 -> 0.3409387 | G94: =G90/G77 -> 0.3422187 | H94: =$G94+(fade_mB-$G94)*1/3 -> 0.32989438 | I94: =$G94+(fade_mB-$G94)*2/3 -> 0.31757006 | J94: =$G94+(fade_mB-$G94)*3/3 -> 0.30524574
A97: 案例區塊：可拆式上蓋 快（VR 單價 高）（情境 B）
A98: 項目 | B98: 單位 | C98: FY2025A | D98: FY2026（錨點） | E98: FY2027 | F98: FY2028 | G98: FY2029 | H98: FY2030（收斂） | I98: FY2031（收斂） | J98: FY2032（收斂） | K98: 說明
A99: A. AI 加速器顆數與均熱片市場（D 欄＝FY2026 校準年；E–G＝FY2027–FY2029；顆數 × 同字母情境係數）
A100: Blackwell 顆數 | B100: 百萬顆 | D100: =(u_bw26)*1 -> 5.4 | E100: =(u_bw27)*1*1 -> 2.4 | F100: =(u_bw28)*um28_B*1 -> 0.4 | G100: =(u_bw29)*um29_B*1 -> 0.2125
A101: Hopper 顆數 | B101: 百萬顆 | D101: =(u_hp26)*1 -> 0.5 | E101: =(u_hp27)*1*1 -> 0 | F101: =(u_hp28)*um28_B*1 -> 0 | G101: =(u_hp29)*um29_B*1 -> 0
A102: Rubin 顆數 | B102: 百萬顆 | D102: =(u_rb26)*1 -> 1.7 | E102: =(u_rb27)*1*1 -> 7 | F102: =(u_rb28)*um28_B*1 -> 5.6 | G102: =(u_rb29)*um29_B*1 -> 6.8425
A103: Rubin Ultra 顆數 | B103: 百萬顆 | D103: =(u_ru26)*1 -> 0 | E103: =(u_ru27)*1*1 -> 0.3 | F103: =(u_ru28)*um28_B*1 -> 1.6 | G103: =(u_ru29)*um29_B*1 -> 1.955
A104: AMD Instinct 顆數 | B104: 百萬顆 | D104: =(u_amd26)*1 -> 0.75 | E104: =(u_amd27)*1*1 -> 1.5 | F104: =(u_amd28)*um28_B*1 -> 1.6 | G104: =(u_amd29)*um29_B*1 -> 1.955
A105: ASIC 顆數（TPU＋Trainium＋其他） | B105: 百萬顆 | D105: =(u_tpu26+u_trn26+u_oth26)*1 -> 6.85 | E105: =(u_tpu27+u_trn27+u_oth27)*1*1 -> 12.5 | F105: =(u_tpu28+u_trn28+u_oth28)*um28_B*1 -> 12 | G105: =(u_tpu29+u_trn29+u_oth29)*um29_B*1 -> 14.6625
A106: Rubin 每顆均熱片／上蓋 | B106: US$/顆 | D106: =asp_vr_26 -> 100 | E106: =VRHI_27 -> 200 | F106: =VRHI_28 -> 220 | G106: =VRHI_29 -> 220
A107: AMD 每顆均熱片／上蓋 | B107: US$/顆 | D107: =asp_amd_26 -> 40 | E107: =asp_amd_27 -> 60 | F107: =asp_amd_28 -> 80 | G107: =asp_amd_29 -> 80
A108: ASIC 每顆均熱片＋加強環 | B108: US$/顆 | D108: =asp_asic_26 -> 30 | E108: =asp_asic_27 -> 35 | F108: =asp_asic_28 -> 40 | G108: =asp_asic_29 -> 40
A109: NVIDIA 加速器均熱片市場（美元） | B109: US$B | D109: =(D100*asp_bw+D101*asp_hp+D102*D106+D103*asp_ru)/1000 -> 0.3665 | E109: =(E100*asp_bw+E101*asp_hp+E102*E106+E103*asp_ru)/1000 -> 1.544 | F109: =(F100*asp_bw+F101*asp_hp+F102*F106+F103*asp_ru)/1000 -> 1.566 | G109: =(G100*asp_bw+G101*asp_hp+G102*G106+G103*asp_ru)/1000 -> 1.9037875 | K109: 百萬顆 × 美元 ÷ 1000＝十億美元
A110: 非 NVIDIA（AMD、ASIC）均熱片市場（美元） | B110: US$B | D110: =(D104*D107+D105*D108)/1000 -> 0.2355 | E110: =(E104*E107+E105*E108)/1000 -> 0.5275 | F110: =(F104*F107+F105*F108)/1000 -> 0.608 | G110: =(G104*G107+G105*G108)/1000 -> 0.7429
A111: AI 加速器均熱片市場合計 | B111: US$B | D111: =D109+D110 -> 0.602 | E111: =E109+E110 -> 2.0715 | F111: =F109+F110 -> 2.174 | G111: =G109+G110 -> 2.6466875
A112: 健策 NVIDIA 份額（FY2026 校準）＝ AI 均熱片營收 ÷（NVIDIA 市場＋k × 非 NVIDIA 市場） | B112: % | D112: =a26_rev*ai_26/fx/(D109+k_non*D110) -> 0.88222542 | K112: Derived：分子為 FY2026 錨點營收 × AI 占比（Assumed）；k＝非 NVIDIA 份額 ÷ NVIDIA 份額
A113: 份額相對值（÷ FY2026） | B113: x | D113: =1 -> 1 | E113: =rel_27 -> 0.97 | F113: =rel_28 -> 0.93 | G113: =rel_29 -> 0.9
A114: 健策 NVIDIA 均熱片份額 | B114: % | D114: =$D$112*D113 -> 0.88222542 | E114: =$D$112*E113 -> 0.85575866 | F114: =$D$112*F113 -> 0.82046964 | G114: =$D$112*G113 -> 0.79400288
A115: 健策非 NVIDIA 均熱片份額 | B115: % | D115: =D114*k_non -> 0.35289017 | E115: =E114*k_non -> 0.34230346 | F115: =F114*k_non -> 0.32818786 | G115: =G114*k_non -> 0.31760115
A116: AI 加速器均熱片營收 | B116: NT$B | C116: =a25_ail -> 6.0828 | D116: =(D109*D114+D110*D115)*fx -> 13.00612 | E116: =(E109*E114+E110*E115)*fx -> 48.059406 | F116: =(F109*F114+F110*F115)*fx -> 47.500597 | G116: =(G109*G114+G110*G115)*fx -> 55.921877
...

Sheet Sources
A1: 來源（公司原文＝健策財報、月營收與自結損益公告，經資料商與媒體轉述；券商與媒體估計皆為 Interested-party）
A2: 資料商：stockanalysis 季度損益（1Q25–2Q26 營收、毛利、營業利益、歸母淨利、EPS） | B2: https://stockanalysis.com/quote/tpe/3653/financials/?p=quarterly
A3: 資料商：HiStock 季度損益（稅前、稅後）與每股盈餘（2018–2026） | B3: https://histock.tw/stock/3653/%E6%90%8D%E7%9B%8A%E8%A1%A8
A4: 二手：口袋學堂 2026-08-26（2Q26、1H26、2025 散熱占比 72.6%、2Q26 約 77%、7 月營收、亞系券商 EPS） | B4: https://www.pocket.tw/school/articles/6275/
A5: 二手：口袋學堂 2025-12-15（全球前兩大 IHS 供應商、AMD／Intel 核心供應商、水冷模組出貨） | B5: https://www.pocket.tw/school/articles/6817/
A6: 二手：理財周刊 2026-08-05（各世代均熱片單價、1H26 產品比重、MCL 驗證） | B6: https://www.moneyweekly.com.tw/_Article?AID=241110
A7: 二手：工商時報 2026-08-07（6 月自結、VR 均熱片出貨量、加強環） | B7: https://www.ctee.com.tw/news/20260807700227-439901
A8: 二手：優分析 2026-10-05（8 月自結淨利 10.79 億、EPS 7.35；可拆式上蓋 4Q26 送樣） | B8: https://uanalyze.com.tw/articles/8953956478
A9: 二手：technews 2026-10-08（9 月營收 30.54 億、前 9 月 220.73 億） | B9: https://finance.technews.tw/2026/10/08/jentech-3653-202609-financial-report/
A10: 二手：technews 2026-08-07（7 月營收 32.13 億） | B10: https://finance.technews.tw/2026/08/07/jentech-3653-202607-financial-report/
A11: 券商：大和（經濟日報 2026-10-01；目標價 10,000、3Q26 估計） | B11: https://money.udn.com/money/amp/story/5607/9786948
A12: 券商：本國投顧（經濟日報 2026-10-08；2027 營收 +147%、可拆式上蓋 ASP、均熱片占八成以上） | B12: https://money.udn.com/money/amp/story/5607/9802684
A13: 資料商：FactSet（鉅亨 2026-05-22；EPS 與營收中位數、目標價 4,920） | B13: https://news.cnyes.com/news/id/6468499
... A18: 資料商：財報狗（10-22 收盤 6,070、近 12 月 P/E） | B18: https://statementdog.com/analysis/3653
A19: 市場層：markets/network（加速器顆數）、tsmc（情境顆數係數）成品；奇鋐模型 avc/dist（液冷市場與奇鋐份額）（本 repo，唯讀）
A20: 待補（人工）：3Q26 財報（11-09）；10 月營收與自結（11-10 前後）；7、9 月自結損益；AI 均熱片占比與各客戶份額；可拆式上蓋實際單價；液冷營收；資本支出與折舊；2016–2020 營收與淨利；前瞻 P/E 十年歷史（Bloomberg）；較新的 FactSet 共識 | B20: 未找到
A21: SemiAnalysis | B21: 未使用
