Workbook

Sheet README
A1: Lumentum（LITE）收支與估值模型 v0.2.2（AI 半導體 Project：網通次產業內複製——雷射與光元件） 2026-10-26
A2: 版本：v0.2.1（2026-10-25：補上檔空間級距、投資建議、重點觀察，數值不變）；v0.2（2026-10-25：三情境延伸到 FY2032、目標價＝DCF 與 Comparable 加權；v0.1 初版）。Lumentum 的雷射有效份額（上游元件口徑）在本模型 Units 頁建立；不可與中際旭創等光模組廠份額相加。
A3: 模型命題：Lumentum 的雷射晶片營收＝高速光模組數量（本專案網通模型金額 ÷ 模組單價）× 每模組 EML／CW 雷射數 × 雷射單價 × Lumentum 份額；光模組、OCS（Google TPU）、CPO 外部光源另推；電信與 DCI、工業與 3D 感測依成長率推。股價約 35 倍共識 FY2027 EPS，遠高於十年 non-GAAP P/E 中位數。
A4: 核心問題：EML 供給缺口收斂、矽光以較少 CW 雷射替代、OCS 與 CPO 放量時程——哪一條路徑決定 FY2028 獲利，現價隱含的倍數與獲利要多少才合理？
A6: 會計年度 6 月底結束：FY2027＝2026-07～2027-06（FY(t) 後半年在日曆年 t）。市場層為日曆年，先算 CY2026–CY2029 產品營收，再換成 FY2027–FY2029（FY(t)＝CY(t−1) 下半年＋CY(t) 上半年，上半年占比 h＝47%）。口徑：公司 non-GAAP；EPS 以 non-GAAP 稀釋股數（含可轉債假設轉換）。
A8: 驅動因子 → 推導量（全部唯讀上游，不修改）
A9: 雷射晶片：markets/network 可插拔光模組市場 × 情境顆數係數 ÷ 模組單價 × 每模組雷射數 × 雷射單價 × 有效份額（CY2026 以產品拆分殘差校準）× 份額相對值。光模組：可插拔市場 × 份額。OCS：Google TPU 顆數（網通模型 Units）× 每顆 TPU 營收。CPO：CPO 光學市場 × 份額。
A10: CY2026 錨點＝FY2026 第三、四季實績＋FY2027 第一季指引中點＋第二季季增 12%（Assumed）。產品拆分（OCS、CPO、電信與 DCI、工業與 3D 感測、光模組）為 Assumed／公司展望，雷射晶片＝殘差。毛利率 FY2027 起為輸入路徑；營業費用彈性 phi（Derived）；稅率 16.5%；營業外淨收入由第一季指引推導。
A11: 估值：目標價（Val 第 0 節）＝0.5 × DCF（股東現金流＝EPS ×（1 − g／ROE），FY2027–32 明確期＋永續，r 10%、g 4%，情境權重 0.3／0.5／0.2）＋0.5 × Comparable（美股光通訊同業前瞻 P/E 中位數 × 12 個月後前瞻 EPS）。舊法規則值情境加權保留參考（不是目標價）；規則值＝FY2027 EPS × 十年 P/E 依循環位置取分位（年底股價 ÷ 近 12 月 non-GAAP EPS，推導）。本版未做先驗，無 Andy 合理 P/E 對照。
A12: 標記：Verified、Interested-party、Analogy、Assumed、Derived。SemiAnalysis 未使用。公司不揭露產品別營收；法說內容多經第三方轉述。
A14: 已知限制：(1) 產品拆分、雷射單價、每模組雷射數皆為 Assumed，雷射份額由殘差推得；(2) CY2026 下半年第二季為假設，FY2027 第一季財報約 11-05 公布；(3) 網通模型 CY2028 可插拔光模組只 +12%，比券商出貨預測保守；(4) 未設 EML 產能上限（公司 EML 出貨年增約 50%）；(5) 十年 P/E 為推導序列、多數年份在 AI 前，規則值偏低；(6) R4 產業部署路徑未建（Recon 預留列）。
A15: v0.2（2026-10-25）：Val 頁最前面新增「0. 目標價」（0.1 DCF、0.2 Comparable、0.3 結論），既有內容整體下移；原「0. 目標價與上檔空間」改名「舊法：規則值情境加權（參考）」保留。PL 三情境延伸到 FY2032（FY2030 起為收斂法，非驅動因子推導；灰底），說明欄移到 K 欄。In 頁新增 K 節（tp_r、tp_g、tp_roe、tp_w_dcf、收斂法參數、共識目標價）。Sens 加目標價參數列。FY2026–FY2029 既有數字不變。
A16: v0.2.1（2026-10-25）：補上檔空間級距、投資建議、重點觀察（Val 頁 0.3 結論加「上檔空間級距」「投資建議」兩列、README 頁加重點觀察三點；數值不變，既有儲存格位置不變）。
A17: ="投資建議："&Val!B50&"（依上檔空間固定規則）" -> 投資建議：中立（依上檔空間固定規則）
A18: 重點觀察 1：目標價 US$623（DCF 387、Comparable 860 各半），比現價 756.17（2026-10-23）低 17.6%，級距 0%～−25%；Comparable 單獨為 +13.7%。DCF 拉低：DCF 單獨 −48.8%（ROE 用預設 20%），而本模型 12 個月後前瞻 EPS 29.30 比共識前瞻 EPS 23.60 高 24.2%（共識 FY2028 只有單一來源）；共識目標價 1,165.03 隱含 49.4 倍，比同業中位數 29.3 倍高 68.3%，市場給 EML／CW 雷射供給缺口的溢價，Comparable 未計入。
A19: 重點觀察 2：最敏感的是 AI 市場與毛利率：AI 市場 ×0.8 時 FY2028 EPS −12.7%、毛利率低（FY2028 46%）−11.3%、雷射單價低 −9.5%、每模組雷射數低（矽光替代）−7.9%；情境 C FY2028 EPS 25.04，比情境 A 的 32.73 低 23.5%。現價 ÷ FY2028 EPS 23.1～30.2 倍，在十年分位 76%～80%。
A20: 重點觀察 3：追蹤 FY2027 Q1 財報（約 2026-11-05）：產品別營收（雷射、光模組、OCS）公司不揭露，本版為 Assumed 拆分。網通 CPO 已改三情境（v0.2.2；A＝替代快、C＝慢）：CPO 快對 Lumentum 外部光源是加分，情境 A FY2028 EPS 由 31.43 升到 32.73（+4.1%）、C 由 25.45 降到 25.04（−1.6%）、B 不變；CPO 外部光源份額低／高時 FY2028 EPS −8.2%／+5.4%。
A21: v0.2.2（2026-10-26）：網通模型 v0.2.3 的 CPO 滲透改三情境（A＝替代快、B＝平平、C＝慢），本模型 A／B／C 改讀同字母的可插拔與 CPO 市場（In 頁末新增 B、C 兩組；情境 A 沿用 A 節 mpl_／mcp_，數值改為網通情境 A）；FY2027 起三情境不再相同。其他輸入不變。

Sheet In
A1: In — 輸入（藍字；基準欄 E，低 D、高 F）。公司金額：十億美元（US$B；Q 頁百萬美元）；比例：%。每個輸入附兩個來源（找不到者寫「未找到」）；公司原文算一個
A2: 標記：Verified／Interested-party／Analogy／Assumed／Derived；Analogy、Assumed 給低／高區間。SemiAnalysis 未使用。公司不揭露產品別營收（只有元件／系統兩個部門），產品拆分為 Assumed；口徑為公司 non-GAAP
A3: 鍵 | B3: 項目 | C3: 單位 | D3: 低 | E3: 基準 | F3: 高 | G3: 標記 | H3: 來源1 | I3: 來源2／說明
A4: A. AI 光學市場與 TPU 顆數（讀 markets/network 成品；日曆年；情境 A 基準，B／C 依顆數係數縮放）
A5: mpl_26 | B5: AI 可插拔光模組市場 CY2026 | C5: US$B | E5: 29.753262 | G5: Derived | H5: markets/network/dist/20261026_AI網通市場模型_v0.2.3.xlsx｜Mkt!C45:F45 | I5: 加速器顆數 × 每顆光學內容 − CPO（網通模型；日曆年）
A6: mpl_27 | B6: AI 可插拔光模組市場 CY2027 | C6: US$B | E6: 53.560715 | G6: Derived | H6: markets/network/dist/20261026_AI網通市場模型_v0.2.3.xlsx｜Mkt!C45:F45 | I6: 同上
A7: mpl_28 | B7: AI 可插拔光模組市場 CY2028 | C7: US$B | E7: 57.9915 | G7: Derived | H7: markets/network/dist/20261026_AI網通市場模型_v0.2.3.xlsx｜Mkt!C45:F45 | I7: 同上
A8: mpl_29 | B8: AI 可插拔光模組市場 CY2029 | C8: US$B | E8: 72.9348 | G8: Derived | H8: markets/network/dist/20261026_AI網通市場模型_v0.2.3.xlsx｜Mkt!C45:F45 | I8: 同上
A9: mcp_26 | B9: AI CPO 光學市場 CY2026 | C9: US$B | E9: 0.300538 | G9: Derived | H9: markets/network/dist/20261026_AI網通市場模型_v0.2.3.xlsx｜Mkt!C44:F44 | I9: 共同封裝光學；外部光源（ELS）與超高功率雷射屬此
A10: mcp_27 | B10: AI CPO 光學市場 CY2027 | C10: US$B | E10: 2.818985 | G10: Derived | H10: markets/network/dist/20261026_AI網通市場模型_v0.2.3.xlsx｜Mkt!C44:F44 | I10: 同上
A11: mcp_28 | B11: AI CPO 光學市場 CY2028 | C11: US$B | E11: 6.4435 | G11: Derived | H11: markets/network/dist/20261026_AI網通市場模型_v0.2.3.xlsx｜Mkt!C44:F44 | I11: 同上
A12: mcp_29 | B12: AI CPO 光學市場 CY2029 | C12: US$B | E12: 11.74736 | G12: Derived | H12: markets/network/dist/20261026_AI網通市場模型_v0.2.3.xlsx｜Mkt!C44:F44 | I12: 同上
A13: tpu_26 | B13: Google TPU 顆數 CY2026 | C13: 百萬顆 | E13: 3.85 | G13: Derived | H13: markets/network/dist/20261026_AI網通市場模型_v0.2.3.xlsx｜Units!B9:E9 | I13: OCS（光路交換）的主要用戶是 Google TPU 叢集
A14: tpu_27 | B14: Google TPU 顆數 CY2027 | C14: 百萬顆 | E14: 5.5 | G14: Derived | H14: markets/network/dist/20261026_AI網通市場模型_v0.2.3.xlsx｜Units!B9:E9 | I14: 同上
A15: tpu_28 | B15: Google TPU 顆數 CY2028 | C15: 百萬顆 | E15: 7 | G15: Derived | H15: markets/network/dist/20261026_AI網通市場模型_v0.2.3.xlsx｜Units!B9:E9 | I15: 同上
A16: tpu_29 | B16: Google TPU 顆數 CY2029 | C16: 百萬顆 | E16: 8.05 | G16: Derived | H16: markets/network/dist/20261026_AI網通市場模型_v0.2.3.xlsx｜Units!B9:E9 | I16: 同上
... A26: um29_C | B26: 情境 C：CY2029 顆數 ÷ 基準 | C26: x | E26: 0.6 | G26: Assumed | H26: tsmc/dist/20261028_台積電個股模型_v0.4.xlsx｜In!E42 | I26: 同上
A27: B. 雷射晶片（EML／CW）：高速光模組數量 × 每模組雷射數 × 雷射單價 × Lumentum 份額（上游元件口徑，不可與光模組廠份額相加）
A28: asp_26 | B28: 光模組平均單價 CY2026（把網通模型金額換成模組數） | C28: $/個 | D28: 420 | E28: 500 | F28: 600 | G28: Assumed | H28: 800G 為主、1.6T 比重上升（每個模組單價上升）vs 每 Gb 降價（下壓） | I28: https://www.kgi.com.hk/en/-/media/files/kgishk/research-reports/us-daily/optical-networking-industry_20260818_tc.pdf：800G＋1.6T 出貨 2026 年 67.2M、2027 年 107.5M（凱基；只在 Recon 對照）
A29: asp_27 | B29: 光模組平均單價 CY2027（把網通模型金額換成模組數） | C29: $/個 | D29: 440 | E29: 520 | F29: 640 | G29: Assumed | H29: 同上 | I29: —
A30: asp_28 | B30: 光模組平均單價 CY2028（把網通模型金額換成模組數） | C30: $/個 | D30: 450 | E30: 540 | F30: 680 | G30: Assumed | H30: 同上 | I30: —
A31: asp_29 | B31: 光模組平均單價 CY2029（把網通模型金額換成模組數） | C31: $/個 | D31: 450 | E31: 560 | F31: 720 | G31: Assumed | H31: 同上 | I31: —
A32: lpm_26 | B32: 每模組雷射數 CY2026（EML 與 CW 加權） | C32: 顆 | E32: 5.5 | G32: Assumed | H32: EML 方案（DR8／2×FR4）每模組 8 顆；矽光方案每模組 1–4 顆高功率 CW（業界常識，未找到第一手來源） | I32: （網址見 Sources）：公司 FY2026 第四季約 20% 光模組改用自製 CW 雷射
A33: lpm_27 | B33: 每模組雷射數 CY2027（EML 與 CW 加權） | C33: 顆 | D33: 4.5 | E33: 5.5 | F33: 6 | G33: Assumed | H33: 矽光比重上升使每模組雷射數下降 | I33: —
A34: lpm_28 | B34: 每模組雷射數 CY2028（EML 與 CW 加權） | C34: 顆 | D34: 4 | E34: 5 | F34: 6 | G34: Assumed | H34: 矽光比重上升使每模組雷射數下降 | I34: —
A35: lpm_29 | B35: 每模組雷射數 CY2029（EML 與 CW 加權） | C35: 顆 | D35: 3.5 | E35: 4.8 | F35: 6 | G35: Assumed | H35: 矽光比重上升使每模組雷射數下降 | I35: —
A36: lasp_26 | B36: 雷射平均單價 CY2026（EML 與 CW 加權） | C36: $/顆 | E36: 13 | G36: Assumed | H36: （網址見 Sources）：光學元件與雷射約占光模組成本 25–35%（次級來源） | I36: 雷射單價：未找到；本列×每模組雷射數＝每模組雷射內容（2026 約占模組單價 14%）
A37: lasp_27 | B37: 雷射平均單價 CY2027（EML 與 CW 加權） | C37: $/顆 | D37: 12 | E37: 15 | F37: 17 | G37: Assumed | H37: 200G EML 比重上升（公司：2027 年中占 EML 出貨 50% 以上） | I37: —
A38: lasp_28 | B38: 雷射平均單價 CY2028（EML 與 CW 加權） | C38: $/顆 | D38: 11 | E38: 15 | F38: 18 | G38: Assumed | H38: 200G EML 比重上升（公司：2027 年中占 EML 出貨 50% 以上） | I38: —
A39: lasp_29 | B39: 雷射平均單價 CY2029（EML 與 CW 加權） | C39: $/顆 | D39: 10 | E39: 14 | F39: 18 | G39: Assumed | H39: 200G EML 比重上升（公司：2027 年中占 EML 出貨 50% 以上） | I39: —
A40: lrel_27 | B40: 雷射份額 CY2027 ÷ CY2026（相對值） | C40: x | D40: 0.85 | E40: 0.95 | F40: 1 | G40: Assumed | H40: https://www.trendforce.com/presscenter/news/20260603-13077.html：EML 前三大（Lumentum、Broadcom、三菱電機）合計約 72%；CW 由 Broadcom、住友電工領先（TrendForce，Interested-party） | I40: https://www.kgi.com.hk/en/-/media/files/kgishk/research-reports/us-daily/optical-networking-industry_20260818_tc.pdf：Lumentum 是唯一量產 200G EML 的供應商；EML 供需缺口約 30%（凱基）
A41: lrel_28 | B41: 雷射份額 CY2028 ÷ CY2026 | C41: x | D41: 0.8 | E41: 0.95 | F41: 1.05 | G41: Assumed | H41: Greensboro（第五座 InP 廠）2028 年初量產（公司） | I41: Coherent 擴 6 吋 InP、中國 EML 廠追趕（下壓）
A42: lrel_29 | B42: 雷射份額 CY2029 ÷ CY2026 | C42: x | D42: 0.7 | E42: 0.9 | F42: 1.05 | G42: Assumed | H42: 同上 | I42: —
A43: C. 光模組、OCS、CPO（另推）
A44: mrel_27 | B44: 光模組份額 CY2027 ÷ CY2026（相對值） | C44: x | D44: 0.8 | E44: 1 | F44: 1.2 | G44: Assumed | H44: https://www.marketbeat.com/instant-alerts/lumentum-q4-earnings-call-highlights-2026-08-11/：800G 出貨創新高、1.6T 開始量產（公司） | I44: 公司估光模組供給缺口約 30%（vocus 轉述法說，Interested-party）
A45: mrel_28 | B45: 光模組份額 CY2028 ÷ CY2026 | C45: x | D45: 0.7 | E45: 1 | F45: 1.3 | G45: Assumed | H45: 中際旭創、新易盛、Coherent 為主要競爭者 | I45: —
A46: mrel_29 | B46: 光模組份額 CY2029 ÷ CY2026 | C46: x | D46: 0.6 | E46: 1 | F46: 1.3 | G46: Assumed | H46: 同上 | I46: —
A47: ocsk_27 | B47: OCS 每顆 TPU 營收 CY2027 ÷ CY2026（相對值） | C47: x | D47: 1.2 | E47: 1.6 | F47: 2 | G47: Assumed | H47: https://www.zacks.com/stock/news/2973530/lumentum-q4-earnings-call-focuses-on-ai-optics-ocs-npo-ramps：2H CY2026 OCS 約 4 億美元（追上原展望、未超前）；FY2027 第一季首度超過 1 億美元（公司） | I47: https://s21.q4cdn.com/377324469/files/doc_financials/2026/q4/Q4-FY26-Earnings-Presentation_final.pdf：多年期、數十億美元的 OCS 採購協議（公司）
A48: ocsk_28 | B48: OCS 每顆 TPU 營收 CY2028 ÷ CY2026 | C48: x | D48: 1.2 | E48: 1.8 | F48: 2.4 | G48: Assumed | H48: 2H CY2026 年化 8 億美元 ÷ CY2026 約 5 億美元 ≈ 1.6（推導） | I48: https://www.kgi.com.hk/en/-/media/files/kgishk/research-reports/us-daily/optical-networking-industry_20260818_tc.pdf：Coherent 把 OCS 市場規模由 20 億上調到 40 億美元（Interested-party）
A49: ocsk_29 | B49: OCS 每顆 TPU 營收 CY2029 ÷ CY2026 | C49: x | D49: 1 | E49: 1.8 | F49: 2.4 | G49: Assumed | H49: 同上；Coherent 等競爭者加入（下壓） | I49: —
A50: cpo_27 | B50: Lumentum 占 CPO 光學金額 CY2027 | C50: % | D50: 0.1 | E50: 0.25 | F50: 0.35 | G50: Assumed | H50: https://cruxcapitalgroup.substack.com/p/lite-earnings-breakdown：外部光源／超高功率雷射數億美元訂單 1H CY2027 交貨（公司） | I50: https://www.kgi.com.hk/en/-/media/files/kgishk/research-reports/us-daily/optical-networking-industry_20260818_tc.pdf：超高功率雷射 2026 年約 5 千萬美元，目標 FY2027 第三季單季逾 1 億美元（凱基轉述）
A51: cpo_28 | B51: Lumentum 占 CPO 光學金額 CY2028 | C51: % | D51: 0.1 | E51: 0.25 | F51: 0.35 | G51: Assumed | H51: https://www.marketbeat.com/instant-alerts/lumentum-q4-earnings-call-highlights-2026-08-11/：scale-up 超高功率雷射 2H CY2027 大量出貨、供 2028 年部署（公司） | I51: 網通模型 scale-up 光學 CY2029 才開始（20%），NPO 可能早於此：低估風險
A52: cpo_29 | B52: Lumentum 占 CPO 光學金額 CY2029 | C52: % | D52: 0.1 | E52: 0.2 | F52: 0.3 | G52: Assumed | H52: 同上 | I52: —
A53: D. CY2026 錨點的產品拆分（公司只揭露元件／系統；以下為 Assumed，雷射晶片＝殘差）
A54: ocs_1h | B54: OCS 營收 1H CY2026（FY2026 第三、四季） | C54: US$B | D54: 0.06 | E54: 0.1 | F54: 0.14 | G54: Assumed | H54: （網址見 Sources）：FY2026 第四季 OCS 出貨較第三季倍增（公司） | I54: 金額：未找到
A55: ocs_2h | B55: OCS 營收 2H CY2026（公司展望） | C55: US$B | E55: 0.4 | G55: Interested-party | H55: https://www.zacks.com/stock/news/2973530/lumentum-q4-earnings-call-focuses-on-ai-optics-ocs-npo-ramps：約 4 億美元（公司） | I55: https://www.kgi.com.hk/en/-/media/files/kgishk/research-reports/us-daily/optical-networking-industry_20260818_tc.pdf：同值（凱基轉述）
A56: cpo_a26 | B56: CPO／超高功率雷射營收 CY2026 | C56: US$B | D56: 0.03 | E56: 0.05 | F56: 0.08 | G56: Interested-party | H56: https://www.kgi.com.hk/en/-/media/files/kgishk/research-reports/us-daily/optical-networking-industry_20260818_tc.pdf：2026 年約 5 千萬美元（凱基轉述公司） | I56: —
A57: tel_a26 | B57: 電信與 DCI 元件營收 CY2026（WSS、ROADM、泵浦、窄線寬雷射等） | C57: US$B | D57: 0.55 | E57: 0.75 | F57: 0.95 | G57: Assumed | H57: https://www.marketbeat.com/instant-alerts/lumentum-q4-earnings-call-highlights-2026-08-11/：窄線寬雷射 +130%、泵浦雷射 +80%（年增；公司） | I57: https://www.kgi.com.hk/en/-/media/files/kgishk/research-reports/us-daily/optical-networking-industry_20260818_tc.pdf：泵浦雷射份額 70–80%（凱基）
A58: ind_a26 | B58: 工業雷射與 3D 感測營收 CY2026 | C58: US$B | D58: 0.25 | E58: 0.3 | F58: 0.4 | G58: Assumed | H58: （網址見 Sources）：FY2024 舊部門 Industrial Tech 2.743 億美元（公司） | I58: FY2026 金額：未找到
A59: xcvr_a26 | B59: 光模組（收發器）營收 CY2026 | C59: US$B | D59: 0.7 | E59: 1 | F59: 1.3 | G59: Assumed | H59: （網址見 Sources）：系統部門 FY2026 第四季 3.569 億美元（含光模組、OCS、工業雷射） | I59: 光模組金額：未找到；系統部門 CY2026 約 16 億 − OCS 約 5 億 − 工業雷射（推導）
A60: g_tel_27 | B60: 電信與 DCI 營收年增 CY2027 | C60: % | D60: 0.1 | E60: 0.25 | F60: 0.4 | G60: Assumed | H60: 泵浦雷射出貨未來數季約 4 倍（公司）；DCI／scale-across | I60: —
A61: g_tel_28 | B61: 電信與 DCI 營收年增 CY2028 | C61: % | D61: 0 | E61: 0.15 | F61: 0.3 | G61: Assumed | H61: 同上 | I61: —
A62: g_tel_29 | B62: 電信與 DCI 營收年增 CY2029 | C62: % | D62: -0.05 | E62: 0.1 | F62: 0.2 | G62: Assumed | H62: 同上 | I62: —
A63: g_ind | B63: 工業雷射與 3D 感測年增（CY2027 起） | C63: % | D63: -0.05 | E63: 0.03 | F63: 0.1 | G63: Assumed | H63: FY2023 4.445 億 → FY2024 2.743 億美元（Industrial Tech；公司） | I63: 非 AI；成長假設低
A64: E. 季度實績與指引（百萬美元；CY2026 錨點）
A65: q3_26 | B65: FY2026 第三季營收（2026-01～03） | C65: US$M | E65: 808.4 | G65: Verified | H65: https://www.sec.gov/Archives/edgar/data/0001633978/000162828026055726/lite_ex991xq4fy26.htm：808.4 | I65: https://cruxcapitalgroup.substack.com/p/lite-earnings-breakdown：同值
A66: q4_26 | B66: FY2026 第四季營收（2026-04～06） | C66: US$M | E66: 1006.3 | G66: Verified | H66: https://www.sec.gov/Archives/edgar/data/0001633978/000162828026055726/lite_ex991xq4fy26.htm：1,006.3（元件 649.4、系統 356.9） | I66: https://s21.q4cdn.com/377324469/files/doc_financials/2026/q4/Q4-FY26-Earnings-Presentation_final.pdf：同值
A67: q1g | B67: FY2027 第一季營收指引中點（2026-07～09） | C67: US$M | E67: 1250 | G67: Interested-party | H67: https://www.sec.gov/Archives/edgar/data/0001633978/000162828026055726/lite_ex991xq4fy26.htm：12.25–12.75 億美元（公司） | I67: https://www.kgi.com.hk/en/-/media/files/kgishk/research-reports/us-daily/optical-networking-industry_20260818_tc.pdf：同值
A68: q_g | B68: FY2027 第二季營收季增（2026-10～12） | C68: % | D68: 0.05 | E68: 0.12 | F68: 0.2 | G68: Assumed | H68: FY2026 第三、四季、FY2027 第一季季增 21%、24%、24%（推導） | I68: 產能受限：EML、泵浦缺口 30% 以上（公司）
A69: om_g | B69: FY2027 第一季 non-GAAP 營業利益率指引中點 | C69: % | E69: 0.4 | G69: Interested-party | H69: https://www.sec.gov/Archives/edgar/data/0001633978/000162828026055726/lite_ex991xq4fy26.htm：39.5–40.5%（公司） | I69: —
A70: eps_g | B70: FY2027 第一季 non-GAAP EPS 指引中點 | C70: US$ | E70: 4.2 | G70: Interested-party | H70: https://www.sec.gov/Archives/edgar/data/0001633978/000162828026055726/lite_ex991xq4fy26.htm：4.05–4.35（公司） | I70: Zacks 共識 4.23（Recon 不用）
A71: sh_q1 | B71: FY2027 第一季 non-GAAP 稀釋股數指引 | C71: 百萬股 | E71: 102 | G71: Interested-party | H71: https://s21.q4cdn.com/377324469/files/doc_financials/2026/q4/Q4-FY26-Earnings-Presentation_final.pdf：約 1.02 億股（含可轉債假設轉換） | I71: https://www.sec.gov/Archives/edgar/data/0001633978/000162828026057358/lite-20260627.htm：普通股 8,970 萬股（2026-08-14）
A72: tx | B72: non-GAAP 有效稅率 | C72: % | D72: 0.14 | E72: 0.165 | F72: 0.19 | G72: Interested-party | H72: https://s21.q4cdn.com/377324469/files/doc_financials/2026/q4/Q4-FY26-Earnings-Presentation_final.pdf：16.5%（公司指引） | I72: —
A73: h_1h | B73: 日曆年上半年營收占全年比（CY2027 起；換算會計年度用） | C73: % | D73: 0.44 | E73: 0.47 | F73: 0.5 | G73: Assumed | H73: 成長期上半年小於一半；CY2026 上半年占 40.6%（推導，高成長） | I73: 會計年度 FY(t)＝CY(t−1) 下半年＋CY(t) 上半年
A74: F. FY2025、FY2026 實績（non-GAAP；百萬美元）
A75: a25_rev_in | B75: FY2025 營收 | C75: US$M | E75: 1645 | G75: Verified | H75: https://www.sec.gov/Archives/edgar/data/0001633978/000162828026055726/lite_ex991xq4fy26.htm：1,645.0 | I75: https://www.01net.it/lumentum-announces-fourth-quarter-and-full-fiscal-year-2026-results/：同值（轉載）
A76: a25_gm_in | B76: FY2025 non-GAAP 毛利率 | C76: % | E76: 0.347 | G76: Verified | H76: https://www.sec.gov/Archives/edgar/data/0001633978/000162828026055726/lite_ex991xq4fy26.htm：34.7% | I76: GAAP 28.0%
A77: a25_opx_in | B77: FY2025 non-GAAP 營業費用（研發＋銷管） | C77: US$M | E77: =256+155.4 -> 411.4 | G77: Verified | H77: https://www.sec.gov/Archives/edgar/data/0001633978/000162828026055726/lite_ex991xq4fy26.htm：研發 256.0、銷管 155.4 | I77: —
A78: a25_ni_in | B78: FY2025 non-GAAP 淨利 | C78: US$M | E78: 146.4 | G78: Verified | H78: https://www.sec.gov/Archives/edgar/data/0001633978/000162828026055726/lite_ex991xq4fy26.htm：146.4 | I78: GAAP 25.9
A79: a25_eps_in | B79: FY2025 non-GAAP 稀釋 EPS | C79: US$ | E79: 2.06 | G79: Verified | H79: https://www.sec.gov/Archives/edgar/data/0001633978/000162828026055726/lite_ex991xq4fy26.htm：2.06 | I79: GAAP 0.37
A80: a26_rev_in | B80: FY2026 營收 | C80: US$M | E80: 3014 | G80: Verified | H80: https://www.sec.gov/Archives/edgar/data/0001633978/000162828026055726/lite_ex991xq4fy26.htm：3,014.0（元件 2,005.6、系統 1,008.4） | I80: https://www.01net.it/lumentum-announces-fourth-quarter-and-full-fiscal-year-2026-results/：同值（轉載）
A81: a25_cmp | B81: FY2025 元件（Components）營收 | C81: US$M | E81: 1116.3 | G81: Verified | H81: https://www.sec.gov/Archives/edgar/data/0001633978/000162828026055726/lite_ex991xq4fy26.htm：產品類別 Components 1,116.3、Systems 528.7 | I81: 單一報告分部；公司依產品類別揭露 Components／Systems
A82: a25_sys | B82: FY2025 系統（Systems）營收 | C82: US$M | E82: 528.7 | G82: Verified | H82: https://www.sec.gov/Archives/edgar/data/0001633978/000162828026055726/lite_ex991xq4fy26.htm | I82: —
A83: a26_cmp | B83: FY2026 元件（Components）營收 | C83: US$M | E83: 2005.6 | G83: Verified | H83: https://www.sec.gov/Archives/edgar/data/0001633978/000162828026055726/lite_ex991xq4fy26.htm：Components 2,005.6、Systems 1,008.4（4Q FY26：649.4／356.9） | I83: —
A84: a26_sys | B84: FY2026 系統（Systems）營收 | C84: US$M | E84: 1008.4 | G84: Verified | H84: https://www.sec.gov/Archives/edgar/data/0001633978/000162828026055726/lite_ex991xq4fy26.htm | I84: —
A85: a26_gm_in | B85: FY2026 non-GAAP 毛利率 | C85: % | E85: 0.46 | G85: Verified | H85: https://www.sec.gov/Archives/edgar/data/0001633978/000162828026055726/lite_ex991xq4fy26.htm：46.0%（第四季 50.4%） | I85: GAAP 41.7%
A86: a26_opx_in | B86: FY2026 non-GAAP 營業費用（研發＋銷管） | C86: US$M | E86: =304.8+184.9 -> 489.7 | G86: Verified | H86: https://www.sec.gov/Archives/edgar/data/0001633978/000162828026055726/lite_ex991xq4fy26.htm：研發 304.8、銷管 184.9 | I86: —
A87: a26_ni_in | B87: FY2026 non-GAAP 淨利 | C87: US$M | E87: 782.3 | G87: Verified | H87: https://www.sec.gov/Archives/edgar/data/0001633978/000162828026055726/lite_ex991xq4fy26.htm：782.3 | I87: GAAP −6,935.1（含可轉債清償損失 7,756.6，非現金）
A88: a26_eps_in | B88: FY2026 non-GAAP 稀釋 EPS | C88: US$ | E88: 8.67 | G88: Verified | H88: https://www.sec.gov/Archives/edgar/data/0001633978/000162828026055726/lite_ex991xq4fy26.htm：8.67 | I88: GAAP −92.96
A89: G. 損益參數（FY2027 起）
A90: gm_27 | B90: non-GAAP 毛利率 FY2027 | C90: % | D90: 0.49 | E90: 0.52 | F90: 0.54 | G90: Assumed | H90: https://s21.q4cdn.com/377324469/files/doc_financials/2026/q4/Q4-FY26-Earnings-Presentation_final.pdf：FY2026 第四季 50.4%；FY2027 第一季指引隱含約 51–52%（營業利益率 40% ＋ 營業費用率約 11–12%，推導） | I90: https://www.kgi.com.hk/en/-/media/files/kgishk/research-reports/us-daily/optical-networking-industry_20260818_tc.pdf：公司長期毛利率目標 42% 以上（凱基轉述）
A91: gm_28 | B91: non-GAAP 毛利率 FY2028 | C91: % | D91: 0.46 | E91: 0.51 | F91: 0.54 | G91: Assumed | H91: 200G EML、OCS 規模效益（上推）vs 光模組占比上升、降價（下壓） | I91: —
A92: gm_29 | B92: non-GAAP 毛利率 FY2029 | C92: % | D92: 0.42 | E92: 0.49 | F92: 0.53 | G92: Assumed | H92: 供給缺口收斂後價格回落 | I92: —
A93: phi | B93: 營業費用成長對營收成長的彈性 | C93: x | D93: 0.1 | E93: =Q!B26 -> 0.22869672 | F93: 0.6 | G93: Derived | H93: FY2026 營業費用年增 ÷ 營收年增（Q 頁） | I93: 公司：營業利益率目標由 38–42% 可再上調 100–200bp（Zacks 轉述法說）
A94: opx_adj | B94: 營業費用額外占營收比（Sens 用；基準 0） | C94: pt | D94: -0.01 | E94: 0 | F94: 0.02 | G94: Assumed | H94: 無 | I94: Sens 用 +2 個百分點
A95: oi_oth | B95: 營業外淨收入（利息等，FY2027 起每年） | C95: US$B | D95: 0 | E95: =4*(eps_g*sh_q1/(1-tx)-om_g*q1g)/1000 -> 0.052215569 | F95: 0.08 | G95: Derived | H95: 由 FY2027 第一季指引推導：EPS × 股數 ÷（1 − 稅率）− 營業利益 | I95: 現金與短期投資 27.4 億美元（FY2026 年底，公司）
A96: sh_g | B96: non-GAAP 稀釋股數年變動（FY2028 起） | C96: % | D96: 0 | E96: 0.01 | F96: 0.03 | G96: Assumed | H96: 股票報酬稀釋；2032 年可轉債已計入稀釋股數（公司） | I96: A 系列可轉換特別股 290 萬股（2026-03 發行；公司）
A97: mf | B97: AI 市場係數（Sens 用；CY2027 起） | C97: x | D97: 0.8 | E97: 1 | F97: 1.2 | G97: Assumed | H97: 網通模型 CY2027 可插拔光模組 +84% | I97: ±20%
A98: H. 共識、券商、研調（只作 Recon 對帳，不作校準）
A99: cons_rev27 | B99: 共識 FY2027 營收 | C99: US$B | E99: 6.3 | G99: Interested-party | H99: https://stockanalysis.com/stocks/lite/forecast/（23 家，2026-10-21）：63 億美元（56–72） | I99: https://www.trefis.com/stock/lite/articles/617928/what-is-the-true-hidden-price-of-lumentum-stock/2026-10-08：同值
A100: cons_eps27 | B100: 共識 FY2027 EPS | C100: US$ | E100: 21.79 | G100: Interested-party | H100: https://stockanalysis.com/stocks/lite/forecast/（23 家，2026-10-21）：21.79（19.05–25.27） | I100: https://www.tickflow.io/stock/LITE/forecast：16.10（12 家；該頁年度與季度數字不一致）
A101: cons_eps28 | B101: 共識 FY2028 EPS（單一來源、5 家） | C101: US$ | E101: 23.6 | G101: Interested-party | H101: （網址見 Sources）（5 家，2026-10-24）：23.60（13.23–35.39） | I101: 第二來源：未找到（stockanalysis 需付費）
A102: cons_ni28 | B102: 共識 FY2028 淨利（trefis 轉述） | C102: US$B | E102: 2.4 | G102: Interested-party | H102: https://www.trefis.com/stock/lite/articles/617928/what-is-the-true-hidden-price-of-lumentum-stock/2026-10-08（2026-10-08）：約 24 億美元；FY2028 營收年增 55.5% | I102: 口徑未說明
A103: kgi_m26 | B103: 凱基：800G＋1.6T 光模組出貨 2026 | C103: 百萬個 | E103: =54.2+13 -> 67.2 | G103: Interested-party | H103: https://www.kgi.com.hk/en/-/media/files/kgishk/research-reports/us-daily/optical-networking-industry_20260818_tc.pdf：800G 54.2M、1.6T 13.0M | I103: 券商；只作對照
A104: kgi_m27 | B104: 凱基：800G＋1.6T 光模組出貨 2027 | C104: 百萬個 | E104: =76.7+30.8 -> 107.5 | G104: Interested-party | H104: https://www.kgi.com.hk/en/-/media/files/kgishk/research-reports/us-daily/optical-networking-industry_20260818_tc.pdf：800G 76.7M、1.6T 30.8M | I104: 券商；只作對照
A105: kgi_m28 | B105: 凱基：800G＋1.6T 光模組出貨 2028 | C105: 百萬個 | E105: =90.9+60.2 -> 151.1 | G105: Interested-party | H105: https://www.kgi.com.hk/en/-/media/files/kgishk/research-reports/us-daily/optical-networking-industry_20260818_tc.pdf：800G 90.9M、1.6T 60.2M | I105: 券商；只作對照
A106: tf_eml3 | B106: EML 前三大合計份額（Lumentum、Broadcom、三菱電機） | C106: % | E106: 0.72 | G106: Interested-party | H106: （網址見 Sources）（TrendForce 2026-06-03） | I106: Lumentum 個別份額：未找到
A107: cust_a | B107: 最大客戶占 FY2026 營收 | C107: % | E107: 0.266 | G107: Verified | H107: https://www.sec.gov/Archives/edgar/data/0001633978/000162828026057358/lite-20260627.htm：客戶 A 26.6%、客戶 B 15.0% | I107: 客戶名稱：未揭露
A108: kgi_pe | B108: 凱基：LITE 歷史平均 P/E | C108: x | E108: 45 | G108: Interested-party | H108: https://www.kgi.com.hk/en/-/media/files/kgishk/research-reports/us-daily/optical-networking-industry_20260818_tc.pdf（2026-08-17）：歷史平均 45.0x、高點 66.2x、最新 42.7x | I108: 計算口徑未說明；只作對照
A109: I. 價格與估值
...

Sheet Q
A1: Q — 實績與錨點（百萬美元；EPS 為美元；股數為百萬股）。藍字＝輸入；黑字＝公式。口徑：公司 non-GAAP（GAAP 含 FY2026 可轉債清償損失 77.6 億美元等非現金項目，不用於預測）
A2: CY2026 錨點＝FY2026 第三季（2026-01～03）＋第四季（04～06）實績＋FY2027 第一季（07～09）指引中點＋第二季（10～12，季增假設）。FY2027 第一季財報（約 2026-11-05）公布後以實績取代第一季、並以新指引取代第二季
A3: 項目 | B3: FY2025A | C3: FY2026A | D3: FY26 Q3（實績） | E3: FY26 Q4（實績） | F3: FY27 Q1（指引） | G3: FY27 Q2（假設） | H3: CY2026 錨點 | I3: 2H CY2026 | J3: 標記 | K3: 說明
A4: 營收 | B4: =a25_rev_in -> 1645 | C4: =a26_rev_in -> 3014 | D4: =q3_26 -> 808.4 | E4: =q4_26 -> 1006.3 | F4: =q1g -> 1250 | G4: =F4*(1+q_g) -> 1400 | H4: =D4+E4+F4+G4 -> 4464.7 | I4: =F4+G4 -> 2650 | J4: Verified／Interested-party（指引）／Assumed（Q2） | K4: FY(t) 由 CY(t−1) 7 月起算；CY2026＝FY2026 後兩季＋FY2027 前兩季
A5: 毛利率（non-GAAP） | B5: =a25_gm_in -> 0.347 | C5: =a26_gm_in -> 0.46 | J5: Verified
A6: 毛利 | B6: =B4*B5 -> 570.815 | C6: =C4*C5 -> 1386.44 | J6: Derived
A7: 營業費用（研發＋銷管，non-GAAP） | B7: =a25_opx_in -> 411.4 | C7: =a26_opx_in -> 489.7 | J7: Verified
A8: 營業利益（non-GAAP） | B8: =B6-B7 -> 159.415 | C8: =C6-C7 -> 896.74 | F8: =F4*om_g -> 500 | J8: Derived | K8: FY2026 公司揭露營業利益率 29.8%；FY2027 第一季＝指引營業利益率 × 營收
A9: 營業利益率 | B9: =B8/B4 -> 0.096908815 | C9: =C8/C4 -> 0.29752488 | F9: =F8/F4 -> 0.4 | J9: Derived
A10: 淨利（non-GAAP） | B10: =a25_ni_in -> 146.4 | C10: =a26_ni_in -> 782.3 | F10: =eps_g*sh_q1 -> 428.4 | J10: Verified／Derived（Q1 指引）
A11: 淨利 ÷ 營業利益（營業外與稅） | B11: =B10/B8 -> 0.91835775 | C11: =C10/C8 -> 0.87238218 | F11: =F10/F8 -> 0.8568 | J11: Derived | K11: FY2027 起＝（營業利益＋營業外）×（1 − 稅率）
A12: 稀釋股數（non-GAAP） | B12: =B10/B13 -> 71.067961 | C12: =C10/C13 -> 90.230681 | F12: =sh_q1 -> 102 | J12: Derived | K12: 淨利 ÷ EPS；公司揭露 FY2025 71.2、FY2026 90.2
A13: EPS（non-GAAP） | B13: =a25_eps_in -> 2.06 | C13: =a26_eps_in -> 8.67 | F13: =eps_g -> 4.2 | J13: Verified
A14: 產品拆分：OCS | H14: =(ocs_1h+ocs_2h)*1000 -> 500 | J14: Assumed／Interested-party | K14: 2H CY2026 公司展望 4 億美元＋1H 假設
A15: 產品拆分：CPO／超高功率雷射 | H15: =cpo_a26*1000 -> 50 | J15: Interested-party
A16: 產品拆分：電信與 DCI 元件 | H16: =tel_a26*1000 -> 750 | J16: Assumed
A17: 產品拆分：工業雷射與 3D 感測 | H17: =ind_a26*1000 -> 300 | J17: Assumed
A18: 產品拆分：光模組（收發器） | H18: =xcvr_a26*1000 -> 1000 | J18: Assumed
A19: 產品拆分：雷射晶片（EML／CW；殘差） | H19: =H4-SUM(H14:H18) -> 1864.7 | J19: Derived（殘差） | K19: 元件部門（約 64.5%）≈ 雷射晶片＋電信與 DCI＋3D 感測＋CPO 雷射（Recon 對照）
A20: AI 相關（雷射晶片＋光模組＋OCS＋CPO）÷ 營收 | H20: =(H19+H18+H14+H15)/H4 -> 0.76482182 | J20: Derived
A22: 參考與推導（校準未使用共識）
A23: FY2026 營收年增 | B23: =C4/B4-1 -> 0.83221884
A24: FY2026 營業費用年增 | B24: =C7/B7-1 -> 0.19032572
A25: 2H CY2026 ÷ CY2026（FY2027 換算用） | B25: =I4/H4 -> 0.59354492
A26: 營業費用彈性（營業費用年增 ÷ 營收年增；In 頁 phi 的依據） | B26: =B24/B23 -> 0.22869672
A27: 元件部門占 FY2026 第四季營收（公司揭露 64.5%） | B27: =649.4/1006.3 -> 0.64533439
A28: 1H CY2026 ÷ CY2026 | B28: =(D4+E4)/H4 -> 0.40645508

Sheet Units
A1: Units — 高速光模組數量、每模組雷射數與 Lumentum 份額（日曆年；情境 A）。雷射份額是上游元件口徑（占光模組內雷射金額），不可與中際旭創等光模組廠份額相加
A3: 項目 | B3: 單位 | C3: CY2026 | D3: CY2027 | E3: CY2028 | F3: CY2029 | G3: 說明
A4: 高速光模組數量（情境 A） | B4: 百萬個 | C4: =PL!C65 -> 59.506524 | D4: =PL!D65 -> 103.00137 | E4: =PL!E65 -> 107.39167 | F4: =PL!F65 -> 130.24071 | G4: 網通模型可插拔金額 ÷ 平均單價（Assumed）
A5: 每模組雷射數 | B5: 顆 | C5: =PL!C66 -> 5.5 | D5: =PL!D66 -> 5.5 | E5: =PL!E66 -> 5 | F5: =PL!F66 -> 4.8 | G5: EML 方案 8 顆、矽光 1–4 顆
A6: 光模組雷射市場 | B6: US$B | C6: =PL!C68 -> 4.2547165 | D6: =PL!D68 -> 8.4976134 | E6: =PL!E68 -> 8.054375 | F6: =PL!F68 -> 8.752176
A7: Lumentum 雷射有效份額 | B7: % | C7: =PL!C71 -> 0.43826657 | D7: =PL!D71 -> 0.41635324 | E7: =PL!E71 -> 0.41635324 | F7: =PL!F71 -> 0.39443991 | G7: CY2026 以錨點殘差校準
A8: Lumentum 雷射晶片營收 | B8: US$B | C8: =PL!C72 -> 1.8647 | D8: =PL!D72 -> 3.5380089 | E8: =PL!E72 -> 3.3534652 | F8: =PL!F72 -> 3.4522076
A9: Lumentum 光模組份額（模組廠口徑） | B9: % | C9: =PL!C74 -> 0.03360976 | D9: =PL!D74 -> 0.03360976 | E9: =PL!E74 -> 0.03360976 | F9: =PL!F74 -> 0.03360976 | G9: 與中際旭創份額同口徑
A10: OCS 每顆 TPU 營收 | B10: $/顆 | C10: =PL!C77 -> 129.87013 | D10: =PL!D77 -> 207.79221 | E10: =PL!E77 -> 233.76623 | F10: =PL!F77 -> 233.76623
A11: OCS 營收 | B11: US$B | C11: =PL!C78 -> 0.5 | D11: =PL!D78 -> 1.1428571 | E11: =PL!E78 -> 1.6363636 | F11: =PL!F78 -> 1.8818182
A12: Lumentum 占 CPO 光學金額 | B12: % | C12: =PL!C80 -> 0.16636831 | D12: =PL!D80 -> 0.25 | E12: =PL!E80 -> 0.25 | F12: =PL!F80 -> 0.2
A13: Lumentum AI 相關營收 ÷ AI IT 資本支出 | B13: % | C13: =PL!C82/itc_26 -> 0.0043673338 | D13: =PL!D82/itc_27 -> 0.0045905229 | E13: =PL!E82/itc_28 -> 0.0043087939 | F13: =PL!F82/itc_29 -> 0.0044836588 | G13: markets/network 的 AI IT 資本支出
A15: 讀法：雷射有效份額由 CY2026 產品拆分的殘差推得（拆分為 Assumed），是最需要每季檢查的輸入；每模組雷射數隨矽光比重上升而下降，單價隨 200G EML 比重上升而上升。

Sheet PL
A1: PL — Lumentum 損益（US$B；non-GAAP）。FY2025A、FY2026A 實績，FY2027 起為模型（會計年度 6 月底結束；FY2027＝2026-07～2027-06）。三情境各一個完整推導區塊（本頁下方），頂端為摘要。FY2027 三情境只差在網通 CPO 情境（A 替代快、C 慢），顆數係數從 CY2028 開始
A2: 灰底＝FY2030–FY2032 收斂法，非驅動因子推導（上游市場層只到 2029）：營收年增由 FY2029 線性收斂到 fade_g（A＝tp_g＋2pt、B＝tp_g、C＝tp_g−2pt），淨利率由 FY2029 線性收斂到 fade_m（In 頁 K 節），FY2032 達到；股數依 sh_g
A3: 情境／項目 | B3: 單位 | C3: FY2025A | D3: FY2026A（錨點） | E3: FY2027 | F3: FY2028 | G3: FY2029 | H3: FY2030（收斂） | I3: FY2031（收斂） | J3: FY2032（收斂） | K3: 說明
A4: 情境 A
A5: 營收 | B5: US$B | C5: =C93 -> 1.645 | D5: =D93 -> 3.014 | E5: =E93 -> 6.6131693 | F5: =F93 -> 9.14381 | G5: =G93 -> 10.746305 | H5: =H93 -> 12.216791 | I5: =I93 -> 13.419145 | J5: =J93 -> 14.224294
A6: 營收年增 | B6: % | D6: =D97 -> 0.83221884 | E6: =E97 -> 1.1941504 | F6: =F97 -> 0.38266686 | G6: =G97 -> 0.17525462 | H6: =H97 -> 0.13683641 | I6: =I97 -> 0.098418207 | J6: =J97 -> 0.06
A7: AI 相關營收 | B7: US$B | E7: =E91 -> 5.4040921 | F7: =F91 -> 7.8268594 | G7: =G91 -> 9.2947505
A8: 電信、DCI、工業與 3D 感測 | B8: US$B | E8: =E92 -> 1.2090772 | F8: =F92 -> 1.3169506 | G8: =G92 -> 1.4515545
A9: AI 相關 ÷ 營收 | B9: % | E9: =E98 -> 0.8171713 | F9: =F98 -> 0.85597353 | G9: =G98 -> 0.86492525
A10: 毛利率 | B10: % | C10: =C99 -> 0.347 | D10: =D99 -> 0.46 | E10: =E99 -> 0.52 | F10: =F99 -> 0.51 | G10: =G99 -> 0.49
A11: 營業利益率 | B11: % | C11: =C104 -> 0.096908815 | D11: =D104 -> 0.29752488 | E11: =E104 -> 0.42572807 | F11: =F104 -> 0.43585191 | G11: =G104 -> 0.42438022
A12: 淨利率 | B12: % | C12: =C106 -> 0.08899696 | D12: =D106 -> 0.25955541 | E12: =E106 -> 0.36207584 | F12: =F106 -> 0.3687046 | G12: =G106 -> 0.35841469 | H12: =H106 -> 0.35841469 | I12: =I106 -> 0.35841469 | J12: =J106 -> 0.35841469
A13: 淨利（non-GAAP） | B13: US$B | C13: =C105 -> 0.1464 | D13: =D105 -> 0.7823 | E13: =E105 -> 2.3944689 | F13: =F105 -> 3.3713648 | G13: =G105 -> 3.8516335 | H13: =H105 -> 4.3786773 | I13: =I105 -> 4.8096188 | J13: =J105 -> 5.098196
A14: EPS（non-GAAP） | B14: US$ | C14: =C108 -> 2.06 | D14: =D108 -> 8.67 | E14: =E108 -> 23.475185 | F14: =F108 -> 32.725343 | G14: =G108 -> 37.01707 | H14: =H108 -> 41.665696 | I14: =I108 -> 45.313227 | J14: =J108 -> 47.556456
A15: EPS 年增 | B15: % | D15: =D109 -> 3.2087379 | E15: =E109 -> 1.7076338 | F15: =F109 -> 0.39403983 | G15: =G109 -> 0.13114385 | H15: =H109 -> 0.12558061 | I15: =I109 -> 0.087542779 | J15: =J109 -> 0.04950495
A17: 情境 B
A18: 營收 | B18: US$B | C18: =C145 -> 1.645 | D18: =D145 -> 3.014 | E18: =E145 -> 6.5334968 | F18: =F145 -> 8.0582066 | G18: =G145 -> 8.6295495 | H18: =H145 -> 9.1525117 | I18: =I145 -> 9.6128891 | J18: =J145 -> 9.9974047
A19: 營收年增 | B19: % | D19: =D149 -> 0.83221884 | E19: =E149 -> 1.1677163 | F19: =F149 -> 0.23336812 | G19: =G149 -> 0.07090199 | H19: =H149 -> 0.060601327 | I19: =I149 -> 0.050300663 | J19: =J149 -> 0.04
A20: AI 相關營收 | B20: US$B | E20: =E143 -> 5.3244196 | F20: =F143 -> 6.741256 | G20: =G143 -> 7.1779951
A21: 電信、DCI、工業與 3D 感測 | B21: US$B | E21: =E144 -> 1.2090772 | F21: =F144 -> 1.3169506 | G21: =G144 -> 1.4515545
A22: AI 相關 ÷ 營收 | B22: % | E22: =E150 -> 0.8149418 | F22: =F150 -> 0.83657026 | G22: =G150 -> 0.83179255
A23: 毛利率 | B23: % | C23: =C151 -> 0.347 | D23: =D151 -> 0.46 | E23: =E151 -> 0.52 | F23: =F151 -> 0.51 | G23: =G151 -> 0.49
A24: 營業利益率 | B24: % | C24: =C156 -> 0.096908815 | D24: =D156 -> 0.29752488 | E24: =E156 -> 0.42503159 | F24: =F156 -> 0.42889127 | G24: =G156 -> 0.41303319
A25: 淨利率 | B25: % | C25: =C158 -> 0.08899696 | D25: =D158 -> 0.25955541 | E25: =E158 -> 0.36157468 | F25: =F158 -> 0.36353484 | G25: =G158 -> 0.34993512 | H25: =H158 -> 0.33827062 | I25: =I158 -> 0.32660611 | J25: =J158 -> 0.31494161
A26: 淨利（non-GAAP） | B26: US$B | C26: =C157 -> 0.1464 | D26: =D157 -> 0.7823 | E26: =E157 -> 2.362347 | F26: =F157 -> 2.9294389 | G26: =G157 -> 3.0197824 | H26: =H157 -> 3.0960258 | I26: =I157 -> 3.1396283 | J26: =J157 -> 3.1485987
A27: EPS（non-GAAP） | B27: US$ | C27: =C160 -> 2.06 | D27: =D160 -> 8.67 | E27: =E160 -> 23.160265 | F27: =F160 -> 28.435633 | G27: =G160 -> 29.022361 | H27: =H160 -> 29.460511 | I27: =I160 -> 29.579619 | J27: =J160 -> 29.370428
A28: EPS 年增 | B28: % | D28: =D161 -> 3.2087379 | E28: =E161 -> 1.6713108 | F28: =F161 -> 0.22777666 | G28: =G161 -> 0.020633548 | H28: =H161 -> 0.01509698 | I28: =I161 -> 0.0040429695 | J28: =J161 -> -0.0070721358
A30: 情境 C
A31: 營收 | B31: US$B | C31: =C197 -> 1.645 | D31: =D197 -> 3.014 | E31: =E197 -> 6.4936606 | F31: =F197 -> 7.2000012 | G31: =G197 -> 6.529818 | H31: =H197 -> 6.1681488 | I31: =I197 -> 6.0590117 | J31: =J197 -> 6.1801919
A32: 營收年增 | B32: % | D32: =D201 -> 0.83221884 | E32: =E201 -> 1.1544992 | F32: =F201 -> 0.10877388 | G32: =G201 -> -0.093080987 | H32: =H201 -> -0.055387325 | I32: =I201 -> -0.017693662 | J32: =J201 -> 0.02
A33: AI 相關營收 | B33: US$B | E33: =E195 -> 5.2845834 | F33: =F195 -> 5.8830505 | G33: =G195 -> 5.0782635
A34: 電信、DCI、工業與 3D 感測 | B34: US$B | E34: =E196 -> 1.2090772 | F34: =F196 -> 1.3169506 | G34: =G196 -> 1.4515545
A35: AI 相關 ÷ 營收 | B35: % | E35: =E202 -> 0.81380653 | F35: =F202 -> 0.81709022 | G35: =G202 -> 0.77770368
A36: 毛利率 | B36: % | C36: =C203 -> 0.347 | D36: =D203 -> 0.46 | E36: =E203 -> 0.52 | F36: =F203 -> 0.51 | G36: =G203 -> 0.49
A37: 營業利益率 | B37: % | C37: =C208 -> 0.096908815 | D37: =D208 -> 0.29752488 | E37: =E208 -> 0.42467694 | F37: =F208 -> 0.42188976 | G37: =G208 -> 0.39284663
A38: 淨利率 | B38: % | C38: =C210 -> 0.08899696 | D38: =D210 -> 0.25955541 | E38: =E210 -> 0.36131949 | F38: =F210 -> 0.3583335 | G38: =G210 -> 0.33470399 | H38: =H210 -> 0.31239039 | I38: =I210 -> 0.2900768 | J38: =J210 -> 0.2677632
A39: 淨利（non-GAAP） | B39: US$B | C39: =C209 -> 0.1464 | D39: =D209 -> 0.7823 | E39: =E209 -> 2.3462861 | F39: =F209 -> 2.5800016 | G39: =G209 -> 2.1855562 | H39: =H209 -> 1.9268704 | I39: =I209 -> 1.7575787 | J39: =J209 -> 1.6548279
A40: EPS（non-GAAP） | B40: US$ | C40: =C212 -> 2.06 | D40: =D212 -> 8.67 | E40: =E212 -> 23.002805 | F40: =F212 -> 25.043697 | G40: =G212 -> 21.004824 | H40: =H212 -> 18.335309 | I40: =I212 -> 16.55881 | J40: =J212 -> 15.436392
A41: EPS 年增 | B41: % | D41: =D213 -> 3.2087379 | E41: =E213 -> 1.6531494 | F41: =F213 -> 0.088723606 | G41: =G213 -> -0.16127302 | H41: =H213 -> -0.1270906 | I41: =I213 -> -0.096889506 | J41: =J213 -> -0.067783701
A43: 核對（應為 0）：CY2026 模型營收 − 錨點；雷射晶片營收 − 殘差（校準恆等式）
A44: 情境 A：CY2026 營收差（US$B） | D44: =C87-c26_rev/1000 -> 0
A45: 情境 A：CY2026 雷射晶片營收差（US$B） | D45: =C72-c26_las/1000 -> 0
A46: 情境 A：FY2027 上半年（Q 頁 2H CY2026）÷ 模型 FY2027 營收 | D46: =Q!I4/1000/E93 -> 0.40071558
A60: 情境 A：基準（顆數係數 1.0）；網通 CPO 情境 A（替代快）
A61: A. 日曆年產品營收（C 欄＝CY2026 錨點；D–F＝CY2027–CY2029）
A62: 項目 | B62: 單位 | C62: CY2026（錨點） | D62: CY2027 | E62: CY2028 | F62: CY2029 | H62: FY2030（收斂） | I62: FY2031（收斂） | J62: FY2032（收斂） | K62: 說明
A63: AI 可插拔光模組市場 × 情境顆數係數 | B63: US$B | C63: =mpl_26*1 -> 29.753262 | D63: =mpl_27*1*1 -> 53.560715 | E63: =mpl_28*um28_A*1 -> 57.9915 | F63: =mpl_29*um29_A*1 -> 72.9348
A64: 光模組平均單價 | B64: $/個 | C64: =asp_26 -> 500 | D64: =asp_27 -> 520 | E64: =asp_28 -> 540 | F64: =asp_29 -> 560
A65: 高速光模組數量 ＝ 市場 ÷ 單價 | B65: 百萬個 | C65: =C63*1000/C64 -> 59.506524 | D65: =D63*1000/D64 -> 103.00137 | E65: =E63*1000/E64 -> 107.39167 | F65: =F63*1000/F64 -> 130.24071
A66: 每模組雷射數（EML／CW） | B66: 顆 | C66: =lpm_26 -> 5.5 | D66: =lpm_27 -> 5.5 | E66: =lpm_28 -> 5 | F66: =lpm_29 -> 4.8
A67: 雷射平均單價 | B67: $/顆 | C67: =lasp_26 -> 13 | D67: =lasp_27 -> 15 | E67: =lasp_28 -> 15 | F67: =lasp_29 -> 14
A68: 光模組雷射市場 ＝ 數量 × 每模組雷射數 × 單價 | B68: US$B | C68: =C65*C66*C67/1000 -> 4.2547165 | D68: =D65*D66*D67/1000 -> 8.4976134 | E68: =E65*E66*E67/1000 -> 8.054375 | F68: =F65*F66*F67/1000 -> 8.752176
A69: Lumentum 雷射有效份額（CY2026 校準）＝ 雷射晶片營收 ÷ 雷射市場 | B69: % | C69: =c26_las/1000/C68 -> 0.43826657 | K69: Derived：雷射晶片營收為 CY2026 錨點殘差
A70: 雷射份額相對值（÷ CY2026） | B70: x | C70: =1 -> 1 | D70: =lrel_27 -> 0.95 | E70: =lrel_28 -> 0.95 | F70: =lrel_29 -> 0.9
A71: 雷射有效份額 | B71: % | C71: =$C$69*C70 -> 0.43826657 | D71: =$C$69*D70 -> 0.41635324 | E71: =$C$69*E70 -> 0.41635324 | F71: =$C$69*F70 -> 0.39443991
A72: 雷射晶片營收（EML／CW） | B72: US$B | C72: =C68*C71 -> 1.8647 | D72: =D68*D71 -> 3.5380089 | E72: =E68*E71 -> 3.3534652 | F72: =F68*F71 -> 3.4522076
A73: 光模組份額（CY2026 校準）＝ 光模組營收 ÷ 可插拔市場 | B73: % | C73: =c26_xcvr/1000/C63 -> 0.03360976
A74: 光模組份額 | B74: % | C74: =C73 -> 0.03360976 | D74: =$C$73*mrel_27 -> 0.03360976 | E74: =$C$73*mrel_28 -> 0.03360976 | F74: =$C$73*mrel_29 -> 0.03360976
A75: 光模組營收 | B75: US$B | C75: =C63*C74 -> 1 | D75: =D63*D74 -> 1.8001628 | E75: =E63*E74 -> 1.9490804 | F75: =F63*F74 -> 2.4513211
A76: Google TPU 顆數 × 情境顆數係數 | B76: 百萬顆 | C76: =tpu_26*1 -> 3.85 | D76: =tpu_27*1 -> 5.5 | E76: =tpu_28*um28_A -> 7 | F76: =tpu_29*um29_A -> 8.05
A77: OCS 每顆 TPU 營收（CY2026 校準 × 相對值） | B77: $/顆 | C77: =c26_ocs/C76 -> 129.87013 | D77: =$C77*ocsk_27 -> 207.79221 | E77: =$C77*ocsk_28 -> 233.76623 | F77: =$C77*ocsk_29 -> 233.76623
A78: OCS 營收 | B78: US$B | C78: =C76*C77/1000 -> 0.5 | D78: =D76*D77/1000 -> 1.1428571 | E78: =E76*E77/1000 -> 1.6363636 | F78: =F76*F77/1000 -> 1.8818182
A79: AI CPO 光學市場 × 情境顆數係數 | B79: US$B | C79: =mcp_26*1 -> 0.300538 | D79: =mcp_27*1 -> 2.818985 | E79: =mcp_28*um28_A -> 6.4435 | F79: =mcp_29*um29_A -> 11.74736
A80: Lumentum 占 CPO 光學金額 | B80: % | C80: =c26_cpo/1000/C79 -> 0.16636831 | D80: =cpo_27 -> 0.25 | E80: =cpo_28 -> 0.25 | F80: =cpo_29 -> 0.2
A81: CPO／外部光源營收 | B81: US$B | C81: =C79*C80 -> 0.05 | D81: =D79*D80 -> 0.70474625 | E81: =E79*E80 -> 1.610875 | F81: =F79*F80 -> 2.349472
A82: AI 相關營收（雷射晶片＋光模組＋OCS＋CPO） | B82: US$B | C82: =C72+C75+C78+C81 -> 3.4147 | D82: =D72+D75+D78+D81 -> 7.1857751 | E82: =E72+E75+E78+E81 -> 8.5497842 | F82: =F72+F75+F78+F81 -> 10.134819
A83: 電信與 DCI 元件 | B83: US$B | C83: =c26_tel/1000 -> 0.75 | D83: =C83*(1+g_tel_27) -> 0.9375 | E83: =D83*(1+g_tel_28) -> 1.078125 | F83: =E83*(1+g_tel_29) -> 1.1859375
A84: 工業雷射與 3D 感測 | B84: US$B | C84: =c26_ind/1000 -> 0.3 | D84: =C84*(1+g_ind) -> 0.309 | E84: =D84*(1+g_ind) -> 0.31827 | F84: =E84*(1+g_ind) -> 0.3278181
A85: 元件（雷射晶片＋電信與 DCI＋CPO＋工業與 3D 感測一半；日曆年） | B85: US$B | C85: =C72+C83+C81+C84/2 -> 2.8147 | D85: =D72+D83+D81+D84/2 -> 5.3347552 | E85: =E72+E83+E81+E84/2 -> 6.2016002 | F85: =F72+F83+F81+F84/2 -> 7.1515261 | K85: 對應口徑與 Recon 頁元件部門相同
A86: 系統（光模組＋OCS＋工業與 3D 感測一半；日曆年） | B86: US$B | C86: =C75+C78+C84/2 -> 1.65 | D86: =D75+D78+D84/2 -> 3.0975199 | E86: =E75+E78+E84/2 -> 3.744579 | F86: =F75+F78+F84/2 -> 4.4970484
A87: 營收（日曆年） | B87: US$B | C87: =C82+C83+C84 -> 4.4647 | D87: =D82+D83+D84 -> 8.4322751 | E87: =E82+E83+E84 -> 9.9461792 | F87: =F82+F83+F84 -> 11.648574
A88: 營收年增（日曆年） | B88: % | D88: =D87/C87-1 -> 0.88865435 | E88: =E87/D87-1 -> 0.17953685 | F88: =F87/E87-1 -> 0.17116073
A89: B. 會計年度損益（FY(t)＝CY(t−1) 下半年＋CY(t) 上半年；C、D 欄＝FY2025、FY2026 實績）
A90: 項目 | B90: 單位 | C90: FY2025A | D90: FY2026A（錨點） | E90: FY2027 | F90: FY2028 | G90: FY2029 | H90: FY2030（收斂） | I90: FY2031（收斂） | J90: FY2032（收斂） | K90: 說明
A91: AI 相關營收（會計年度） | B91: US$B | E91: =w2h_26*C82+h_1h*D82 -> 5.4040921 | F91: =(1-h_1h)*D82+h_1h*E82 -> 7.8268594 | G91: =(1-h_1h)*E82+h_1h*F82 -> 9.2947505 | K91: FY2027＝CY2026 下半年（Q 頁）＋ h × CY2027
A92: 電信、DCI、工業與 3D 感測（會計年度） | B92: US$B | E92: =w2h_26*C83+h_1h*D83+w2h_26*C84+h_1h*D84 -> 1.2090772 | F92: =(1-h_1h)*D83+h_1h*E83+(1-h_1h)*D84+h_1h*E84 -> 1.3169506 | G92: =(1-h_1h)*E83+h_1h*F83+(1-h_1h)*E84+h_1h*F84 -> 1.4515545
A93: 營收 | B93: US$B | C93: =a25_rev/1000 -> 1.645 | D93: =a26_rev/1000 -> 3.014 | E93: =E91+E92 -> 6.6131693 | F93: =F91+F92 -> 9.14381 | G93: =G91+G92 -> 10.746305 | H93: =G93*(1+H97) -> 12.216791 | I93: =H93*(1+I97) -> 13.419145 | J93: =I93*(1+J97) -> 14.224294
A94: 元件營收（Components） | B94: US$B | C94: =a25_cmp/1000 -> 1.1163 | D94: =a26_cmp/1000 -> 2.0056 | E94: =w2h_26*C85+h_1h*D85 -> 4.1779858 | F94: =(1-h_1h)*D85+h_1h*E85 -> 5.7421723 | G94: =(1-h_1h)*E85+h_1h*F85 -> 6.6480654 | K94: 公司產品類別：Components（FY2025、FY2026 實績）
A95: 系統營收（Systems） | B95: US$B | C95: =a25_sys/1000 -> 0.5287 | D95: =a26_sys/1000 -> 1.0084 | E95: =w2h_26*C86+h_1h*D86 -> 2.4351835 | F95: =(1-h_1h)*D86+h_1h*E86 -> 3.4016377 | G95: =(1-h_1h)*E86+h_1h*F86 -> 4.0982396 | K95: 公司產品類別：Systems
A96: 檢查：元件＋系統 − 合併營收 | B96: US$B | C96: =C94+C95-C93 -> 0 | D96: =D94+D95-D93 -> 0 | E96: =E94+E95-E93 -> 0 | F96: =F94+F95-F93 -> 0 | G96: =G94+G95-G93 -> 0
A97: 營收年增 | B97: % | D97: =D93/C93-1 -> 0.83221884 | E97: =E93/D93-1 -> 1.1941504 | F97: =F93/E93-1 -> 0.38266686 | G97: =G93/F93-1 -> 0.17525462 | H97: =$G97+(fade_gA-$G97)*1/3 -> 0.13683641 | I97: =$G97+(fade_gA-$G97)*2/3 -> 0.098418207 | J97: =$G97+(fade_gA-$G97)*3/3 -> 0.06
A98: AI 相關 ÷ 營收 | B98: % | E98: =E91/E93 -> 0.8171713 | F98: =F91/F93 -> 0.85597353 | G98: =G91/G93 -> 0.86492525
A99: 毛利率（non-GAAP） | B99: % | C99: =a25_gm -> 0.347 | D99: =a26_gm -> 0.46 | E99: =gm_27 -> 0.52 | F99: =gm_28 -> 0.51 | G99: =gm_29 -> 0.49
A100: 毛利 | B100: US$B | C100: =C93*C99 -> 0.570815 | D100: =D93*D99 -> 1.38644 | E100: =E93*E99 -> 3.438848 | F100: =F93*F99 -> 4.6633431 | G100: =G93*G99 -> 5.2656894
A101: 營業費用（基準路徑） | B101: US$B | C101: =a25_opx/1000 -> 0.4114 | D101: =a26_opx/1000 -> 0.4897 | E101: =D101*(1+MAX(0,phi*E97)) -> 0.62343622 | F101: =E101*(1+MAX(0,phi*F97)) -> 0.67799603 | G101: =F101*(1+MAX(0,phi*G97)) -> 0.70517022
A102: 營業費用（研發＋銷管） | B102: US$B | C102: =C101 -> 0.4114 | D102: =D101 -> 0.4897 | E102: =E101+0*E93 -> 0.62343622 | F102: =F101+0*F93 -> 0.67799603 | G102: =G101+0*G93 -> 0.70517022
A103: 營業利益 | B103: US$B | C103: =C100-C102 -> 0.159415 | D103: =D100-D102 -> 0.89674 | E103: =E100-E102 -> 2.8154118 | F103: =F100-F102 -> 3.9853471 | G103: =G100-G102 -> 4.5605192
A104: 營業利益率 | B104: % | C104: =C103/C93 -> 0.096908815 | D104: =D103/D93 -> 0.29752488 | E104: =E103/E93 -> 0.42572807 | F104: =F103/F93 -> 0.43585191 | G104: =G103/G93 -> 0.42438022
A105: 淨利（non-GAAP） | B105: US$B | C105: =a25_ni/1000 -> 0.1464 | D105: =a26_ni/1000 -> 0.7823 | E105: =(E103+oi_oth)*(1-tx) -> 2.3944689 | F105: =(F103+oi_oth)*(1-tx) -> 3.3713648 | G105: =(G103+oi_oth)*(1-tx) -> 3.8516335 | H105: =H93*H106 -> 4.3786773 | I105: =I93*I106 -> 4.8096188 | J105: =J93*J106 -> 5.098196
A106: 淨利率 | B106: % | C106: =C105/C93 -> 0.08899696 | D106: =D105/D93 -> 0.25955541 | E106: =E105/E93 -> 0.36207584 | F106: =F105/F93 -> 0.3687046 | G106: =G105/G93 -> 0.35841469 | H106: =$G106+(fade_mA-$G106)*1/3 -> 0.35841469 | I106: =$G106+(fade_mA-$G106)*2/3 -> 0.35841469 | J106: =$G106+(fade_mA-$G106)*3/3 -> 0.35841469
A107: 稀釋股數（non-GAAP） | B107: 百萬股 | C107: =a25_sh -> 71.067961 | D107: =a26_sh -> 90.230681 | E107: =sh_q1 -> 102 | F107: =E107*(1+sh_g) -> 103.02 | G107: =F107*(1+sh_g) -> 104.0502 | H107: =G107*(1+sh_g) -> 105.0907 | I107: =H107*(1+sh_g) -> 106.14161 | J107: =I107*(1+sh_g) -> 107.20303
A108: EPS（non-GAAP） | B108: US$ | C108: =C105*1000/C107 -> 2.06 | D108: =D105*1000/D107 -> 8.67 | E108: =E105*1000/E107 -> 23.475185 | F108: =F105*1000/F107 -> 32.725343 | G108: =G105*1000/G107 -> 37.01707 | H108: =H105*1000/H107 -> 41.665696 | I108: =I105*1000/I107 -> 45.313227 | J108: =J105*1000/J107 -> 47.556456
A109: EPS 年增 | B109: % | D109: =D108/C108-1 -> 3.2087379 | E109: =E108/D108-1 -> 1.7076338 | F109: =F108/E108-1 -> 0.39403983 | G109: =G108/F108-1 -> 0.13114385 | H109: =H108/G108-1 -> 0.12558061 | I109: =I108/H108-1 -> 0.087542779 | J109: =J108/I108-1 -> 0.04950495
A112: 情境 B：CY2028 顆數 ×0.8、CY2029 ×0.85；網通 CPO 情境 B
A113: A. 日曆年產品營收（C 欄＝CY2026 錨點；D–F＝CY2027–CY2029）
A114: 項目 | B114: 單位 | C114: CY2026（錨點） | D114: CY2027 | E114: CY2028 | F114: CY2029 | H114: FY2030（收斂） | I114: FY2031（收斂） | J114: FY2032（收斂） | K114: 說明
A115: AI 可插拔光模組市場 × 情境顆數係數 | B115: US$B | C115: =mplB_26*1 -> 29.753262 | D115: =mplB_27*1*1 -> 54.688309 | E115: =mplB_28*um28_B*1 -> 48.9706 | F115: =mplB_29*um29_B*1 -> 66.987208
A116: 光模組平均單價 | B116: $/個 | C116: =asp_26 -> 500 | D116: =asp_27 -> 520 | E116: =asp_28 -> 540 | F116: =asp_29 -> 560
A117: 高速光模組數量 ＝ 市場 ÷ 單價 | B117: 百萬個 | C117: =C115*1000/C116 -> 59.506524 | D117: =D115*1000/D116 -> 105.16983 | E117: =E115*1000/E116 -> 90.686296 | F117: =F115*1000/F116 -> 119.62001
A118: 每模組雷射數（EML／CW） | B118: 顆 | C118: =lpm_26 -> 5.5 | D118: =lpm_27 -> 5.5 | E118: =lpm_28 -> 5 | F118: =lpm_29 -> 4.8
...

Sheet Val
A1: Val — P/E 估值（美元；non-GAAP EPS）。目標價＝DCF 與 Comparable 加權（第 0 節）；舊法規則值情境加權保留參考；另列「現價 ÷ FY2027、FY2028 EPS（模型）」、市場隱含 EPS 與十年 P/E 規則值。十年 P/E 用年底股價 ÷ 近 12 月 non-GAAP EPS（推導；與模型 EPS 同口徑）
A2: 循環位置：Lumentum 不是設備股，不套設備市場見頂年；以本模型營收最高的會計年度為見頂年（比照中際旭創）。營收到 FY2029 仍在增加時，見頂年未知，判為中段
A4: 0. 目標價
A5: 0.1 DCF（股東權益現金流，FY2027–FY2032 明確期＋FY2032 後永續）
A6: 項目 | B6: A（順利） | C6: B（平平） | D6: C（不如預期） | E6: 說明
A7: 情境 EPS（FY2027–FY2032） | E7: PL 頁各情境；FY2030 起為收斂法（PL 頁灰底）
A8: FY2027 | B8: =PL!E14 -> 23.475185 | C8: =PL!E27 -> 23.160265 | D8: =PL!E40 -> 23.002805
A9: FY2028 | B9: =PL!F14 -> 32.725343 | C9: =PL!F27 -> 28.435633 | D9: =PL!F40 -> 25.043697
A10: FY2029 | B10: =PL!G14 -> 37.01707 | C10: =PL!G27 -> 29.022361 | D10: =PL!G40 -> 21.004824
A11: FY2030 | B11: =PL!H14 -> 41.665696 | C11: =PL!H27 -> 29.460511 | D11: =PL!H40 -> 18.335309
A12: FY2031 | B12: =PL!I14 -> 45.313227 | C12: =PL!I27 -> 29.579619 | D12: =PL!I40 -> 16.55881
A13: FY2032 | B13: =PL!J14 -> 47.556456 | C13: =PL!J27 -> 29.370428 | D13: =PL!J40 -> 15.436392
A14: 股東現金流＝EPS ×（1 − tp_g ÷ tp_roe）
A15: 再投資率（tp_g ÷ tp_roe，上限 0.8） | B15: =IF(tp_roe<=tp_g,0.8,MIN(tp_g/tp_roe,0.8)) -> 0.2 | E15: ROE＝In 頁 tp_roe；tp_roe ≤ tp_g 時取上限 0.8
A16: FY2027 | B16: =B8*(1-$B$15) -> 18.780148 | C16: =C8*(1-$B$15) -> 18.528212 | D16: =D8*(1-$B$15) -> 18.402244
A17: FY2028 | B17: =B9*(1-$B$15) -> 26.180274 | C17: =C9*(1-$B$15) -> 22.748506 | D17: =D9*(1-$B$15) -> 20.034957
A18: FY2029 | B18: =B10*(1-$B$15) -> 29.613656 | C18: =C10*(1-$B$15) -> 23.217889 | D18: =D10*(1-$B$15) -> 16.803859
A19: FY2030 | B19: =B11*(1-$B$15) -> 33.332557 | C19: =C11*(1-$B$15) -> 23.568409 | D19: =D11*(1-$B$15) -> 14.668247
A20: FY2031 | B20: =B12*(1-$B$15) -> 36.250582 | C20: =C12*(1-$B$15) -> 23.663695 | D20: =D12*(1-$B$15) -> 13.247048
A21: FY2032 | B21: =B13*(1-$B$15) -> 38.045165 | C21: =C13*(1-$B$15) -> 23.496342 | D21: =D13*(1-$B$15) -> 12.349114
A22: DCF 情境每股價值（折現率 tp_r） | B22: =SUMPRODUCT(B16:B21,1/(1+tp_r)^{1;2;3;4;5;6})+B21*(1+tp_g)/(tp_r-tp_g)/(1+tp_r)^6 -> 499.95154 | C22: =SUMPRODUCT(C16:C21,1/(1+tp_r)^{1;2;3;4;5;6})+C21*(1+tp_g)/(tp_r-tp_g)/(1+tp_r)^6 -> 327.03535 | D22: =SUMPRODUCT(D16:D21,1/(1+tp_r)^{1;2;3;4;5;6})+D21*(1+tp_g)/(tp_r-tp_g)/(1+tp_r)^6 -> 191.95324 | E22: Σ 明確期現金流 ÷ (1＋r)^t ＋ 永續價值 ÷ (1＋r)^6；永續價值＝FY2032 現金流 ×(1＋g)÷(r−g)；基準日 2026 年底，t＝1 對 FY2027
A23: DCF 情境價值推到 12 個月後（×(1＋tp_r)） | B23: =B22*(1+tp_r) -> 549.9467 | C23: =C22*(1+tp_r) -> 359.73889 | D23: =D22*(1+tp_r) -> 211.14856
A24: DCF 目標價（情境加權） | B24: =tp_wA*B23+tp_wB*C23+tp_wC*D23 -> 387.08317 | E24: Σ 權重 × 情境價值 ×(1＋r)；權重見 In 頁
A26: 0.2 Comparable（市場主流同業前瞻 P/E）
A27: 同業與前瞻 P/E | B27: 代號 | C27: 前瞻 12 月 P/E | D27: 日期 | E27: 來源 | F27: 標記
A28: Coherent | B28: COHR | C28: 22.3 | D28: 2026-10-23 | E28: stockanalysis forward PE（分析師共識；價格日期如左） | F28: Interested-party
A29: Fabrinet | B29: FN | C29: 17.27 | D29: 2026-10-23 | E29: stockanalysis forward PE（分析師共識；價格日期如左） | F29: Interested-party
A30: Applied Optoelectronics | B30: AAOI | C30: 29.34 | D30: 2026-10-23 | E30: stockanalysis forward PE（分析師共識；價格日期如左） | F30: Interested-party
A31: Ciena | B31: CIEN | C31: 30.77 | D31: 2026-10-23 | E31: stockanalysis forward PE（分析師共識；價格日期如左） | F31: Interested-party
A32: Corning | B32: GLW | C32: 32.89 | D32: 2026-10-23 | E32: stockanalysis forward PE（分析師共識；價格日期如左） | F32: Interested-party
A33: 同業前瞻 P/E 中位數 | B33: =MEDIAN(C28:C32) -> 29.34 | E33: 美股光通訊同業（不放 A 股）
A34: 12 個月後的前瞻 EPS（情境加權） | B34: =tp_wA*(8/12*B9+4/12*B10)+tp_wB*(8/12*C9+4/12*C10)+tp_wC*(8/12*D9+4/12*D10) -> 29.301861 | E34: 約 2027-10 時的未來 12 月（2027-11～2028-10）≈ 8／12 × FY2028＋4／12 × FY2029（會計年度 6 月底結束）
A35: Comparable 目標價 | B35: =B33*B34 -> 859.71661 | E35: 同業中位數 × 前瞻 EPS
A37: 0.3 結論
A38: 項目 | B38: 數值 | E38: 說明
A39: 目標價（DCF 與 Comparable 加權） | B39: =tp_w_dcf*B24+(1-tp_w_dcf)*B35 -> 623.39989 | E39: tp_w_dcf × DCF＋（1 − tp_w_dcf）× Comparable；tp_w_dcf 見 In 頁
A40: Comparable 目標價（市場主流同業法） | B40: =B35 -> 859.71661
A41: 市場共識目標價 | B41: =cons_tp -> 1165.03 | E41: stockanalysis：27 位分析師平均 1,165.03（2026-10-23）
A42: 上檔空間：加權目標價 | B42: =B39/px-1 -> -0.17558236 | E42: 現價＝In 頁 px
A43: 上檔空間：Comparable 目標價 | B43: =B40/px-1 -> 0.13693562
A44: 與市場共識目標價的差距：EPS 因素 | B44: =B34/cons_feps-1 -> 0.24160429 | E44: 本模型前瞻 EPS ÷ 共識前瞻 EPS − 1；共識前瞻 EPS＝In 頁 cons_feps
A45: 與市場共識目標價的差距：倍數因素 | B45: =(cons_tp/cons_feps)/B33-1 -> 0.68253844 | E45: ="共識目標價隱含 "&TEXT(cons_tp/cons_feps,"0.0")&"x，同業中位數 "&TEXT(B33,"0.0")&"x" -> 共識目標價隱含 49.4x，同業中位數 29.3x
A46: 價格帶（DCF 不如預期～順利） | B46: =TEXT(D23,"#,##0.00")&"～"&TEXT(B23,"#,##0.00") -> 211.15～549.95 | E46: C 情境價值～A 情境價值（推到 12 個月後）
A47: 歷史倍數檢查：現價隱含 P/E 的十年分位（A／B／C） | B47: =IF(px/B9>MAX($B$102:$B$111),1,IF(px/B9<MIN($B$102:$B$111),0,PERCENTRANK($B$102:$B$111,px/B9))) -> 0.76 | C47: =IF(px/C9>MAX($B$102:$B$111),1,IF(px/C9<MIN($B$102:$B$111),0,PERCENTRANK($B$102:$B$111,px/C9))) -> 0.787 | D47: =IF(px/D9>MAX($B$102:$B$111),1,IF(px/D9<MIN($B$102:$B$111),0,PERCENTRANK($B$102:$B$111,px/D9))) -> 0.8 | E47: 現價 ÷ 各情境 FY2028 EPS 在 2016–2025 年底 P/E（第 6 節採用來源）的分位；高於十年最大值＝100%；只作檢查，不進目標價
A48: 目標價方法 | B48: DCF：股東現金流＝EPS ×（1 − g／ROE），r＝10%、g＝4%；ROE 需與 non-GAAP EPS 同口徑，本模型無股東權益、算不出，取 0.20（Assumed；再投資率 20%），FY2027–32 明確期＋永續，FY2030 起為收斂法。Comparable：美股光通訊同業（Coherent、Fabrinet、AAOI、Ciena、Corning）前瞻 P/E 中位數 × 12 個月後前瞻 EPS（non-GAAP）。會計年度 6 月底結束：DCF 的 t＝1 對 FY2027（2026-07～2027-06），偏高估。情境對應：顆數情境 A＝順利、B＝平平、C＝不如預期。
A49: 上檔空間級距 | B49: =IF(B42>0.5,"大於 50%",IF(B42>0.25,"25%–50%",IF(B42>=0,"0%–25%",IF(B42>=-0.25,"0%～−25%",IF(B42>=-0.5,"−25%～−50%","小於 −50%"))))) -> 0%～−25% | E49: 以「上檔空間：加權目標價」分六級（Andy 2026-10-25 14:00）
A50: 投資建議 | B50: =IF(B42>0.5,"強力買進",IF(B42>0.25,"買進",IF(B42>=-0.25,"中立",IF(B42>=-0.5,"放空","強力放空")))) -> 中立 | E50: 依上檔空間固定規則（Andy 2026-10-25 14:17）：大於 +50% 強力買進、+25%～+50% 買進、−25%～+25% 中立、−50%～−25% 放空、小於 −50% 強力放空
A51: 舊法：規則值情境加權（參考）
A52: 項目 | B52: 數值 | E52: 說明
A53: 規則值情境加權價（參考，非目標價） | B53: =tp_wA*D80+tp_wB*D81+tp_wC*D82 -> 410.58704 | E53: 權重 × 各情境隱含價（第 3 節規則值）
A54: 規則值情境加權價 ÷ 現價 − 1（參考） | B54: =B53/px-1 -> -0.45701755 | E54: 現價＝In 頁 px（2026-10-23 收盤）
A55: 情境 A 隱含價（樂觀） | B55: =D80 -> 415.04127 | E55: ="FY2027 EPS "&TEXT(B80,"0.00")&" × "&TEXT(C80,"0.0")&"x（第 3 節；"&C74&"）" -> FY2027 EPS 23.48 × 17.7x（第 3 節；中段）
A56: 情境 B 隱含價（基準） | B56: =D81 -> 409.47348 | E56: ="FY2027 EPS "&TEXT(B81,"0.00")&" × "&TEXT(C81,"0.0")&"x（第 3 節；"&C75&"）" -> FY2027 EPS 23.16 × 17.7x（第 3 節；中段）
A57: 情境 C 隱含價（下檔） | B57: =D82 -> 406.68959 | E57: ="FY2027 EPS "&TEXT(B82,"0.00")&" × "&TEXT(C82,"0.0")&"x（第 3 節；"&C76&"）" -> FY2027 EPS 23.00 × 17.7x（第 3 節；中段）
A58: 情境權重 A／B／C | B58: =tp_wA -> 0.3 | C58: =tp_wB -> 0.5 | D58: =tp_wC -> 0.2 | E58: ="合計 "&TEXT(B58+C58+D58,"0%")&"；In 頁 tp_wA／tp_wB／tp_wC（Assumed，Andy 可改）" -> 合計 100%；In 頁 tp_wA／tp_wB／tp_wC（Assumed，Andy 可改）
A59: 舊法說明 | B59: P/E：各情境 FY2027（2026-07～2027-06）non-GAAP EPS × 十年（2016–2025 年底）P/E 依循環位置取分位（本模型營收到 FY2029 仍增加，三情境皆中段＝中位數）；P/E 為年底股價 ÷ 近 12 月 non-GAAP EPS（推導）。十年倍數 8 年落在 AI 前的電信、3D 感測期（約 10–24x），偏誤方向為低估；另 FY2027 EPS 三情境相近（只差在網通 CPO 情境）、且低於 FY2028，用 FY2027 也偏低。對照：凱基歷史平均 45x（口徑未說明）、現價 ÷ 共識 FY2027 EPS 約 35x
A61: 1. 價格與市場隱含倍數
A62: 項目 | B62: A | C62: B | D62: C | E62: 說明
A63: 現價（2026-10-23 收盤） | B63: =px -> 756.17
A64: 現價 ÷ FY2026 EPS（錨點） | B64: =px/PL!D14 -> 87.21684 | C64: =px/PL!D27 -> 87.21684 | D64: =px/PL!D40 -> 87.21684
A65: 現價 ÷ FY2027 EPS（模型） | B65: =px/PL!E14 -> 32.211461 | C65: =px/PL!E27 -> 32.649454 | D65: =px/PL!E40 -> 32.872947 | E65: FY2027 三情境只差在網通 CPO 情境（顆數係數從 CY2028 開始）
A66: 現價 ÷ FY2028 EPS（模型） | B66: =px/PL!F14 -> 23.106557 | C66: =px/PL!F27 -> 26.592339 | D66: =px/PL!F40 -> 30.194025
A67: 現價 ÷ FY2029 EPS（模型） | B67: =px/PL!G14 -> 20.427603 | C67: =px/PL!G27 -> 26.054738 | D67: =px/PL!G40 -> 35.999825
A68: 現價 ÷ 共識 FY2027 EPS | B68: =px/cons_eps27 -> 34.702616 | E68: 共識 21.79（stockanalysis，23 家）
A69: 現價 ÷ 2026 年內高點 − 1 | B69: =px/px_hi-1 -> -0.33843395
A70: 市值（普通股 × 現價；US$B） | B70: =px*sh_basic/1000 -> 67.828449
A72: 2. 循環位置（本模型營收最高的會計年度）
A73: 情境 | B73: 營收最高年（FY2026–FY2029） | C73: FY2027 判定 | D73: 規則倍數（P/E） | E73: 見頂年是否未知 | F73: 說明
A74: A | B74: =INDEX({2026,2027,2028,2029},MATCH(MAX(PL!D93:G93),PL!D93:G93,0)) -> 2029 | C74: =IF(B74=2029,"中段",IF(2027<B74,"中段",IF(2027=B74,"見頂","谷底"))) -> 中段 | D74: =IF(C74="見頂",pe_peak,IF(C74="谷底",pe_trough,pe_mid)) -> 17.68 | E74: =IF(B74=2029,"是：營收到觀測期末仍在增加","否") -> 是：營收到觀測期末仍在增加 | F74: tools/cycle_position.py excel_rule；營收最高年取代設備市場見頂年
A75: B | B75: =INDEX({2026,2027,2028,2029},MATCH(MAX(PL!D145:G145),PL!D145:G145,0)) -> 2029 | C75: =IF(B75=2029,"中段",IF(2027<B75,"中段",IF(2027=B75,"見頂","谷底"))) -> 中段 | D75: =IF(C75="見頂",pe_peak,IF(C75="谷底",pe_trough,pe_mid)) -> 17.68 | E75: =IF(B75=2029,"是：營收到觀測期末仍在增加","否") -> 是：營收到觀測期末仍在增加 | F75: 同上
A76: C | B76: =INDEX({2026,2027,2028,2029},MATCH(MAX(PL!D197:G197),PL!D197:G197,0)) -> 2028 | C76: =IF(B76=2029,"中段",IF(2027<B76,"中段",IF(2027=B76,"見頂","谷底"))) -> 中段 | D76: =IF(C76="見頂",pe_peak,IF(C76="谷底",pe_trough,pe_mid)) -> 17.68 | E76: =IF(B76=2029,"是：營收到觀測期末仍在增加","否") -> 否 | F76: 同上
A78: 3. 規則值隱含股價（美元；約 FY2027 年底＝2027-06，未折現）＝ FY2027 EPS × 規則倍數
A79: 情境 | B79: FY2027 EPS | C79: 規則倍數 | D79: 隱含股價 | E79: 相對現價 | F79: 現價 ÷ FY2027 EPS
A80: A | B80: =PL!E14 -> 23.475185 | C80: =D74 -> 17.68 | D80: =B80*C80 -> 415.04127 | E80: =D80/px-1 -> -0.45112704 | F80: =px/B80 -> 32.211461
A81: B | B81: =PL!E27 -> 23.160265 | C81: =D75 -> 17.68 | D81: =B81*C81 -> 409.47348 | E81: =D81/px-1 -> -0.45849017 | F81: =px/B81 -> 32.649454
A82: C | B82: =PL!E40 -> 23.002805 | C82: =D76 -> 17.68 | D82: =B82*C82 -> 406.68959 | E82: =D82/px-1 -> -0.46217174 | F82: =px/B82 -> 32.872947
A84: 4. 核心問題：市場隱含的 FY2028 EPS（＝現價 ÷ 假設倍數）與模型的距離
A85: 假設倍數（÷ FY2028 EPS） | B85: 市場隱含 FY2028 EPS | C85: 模型 FY2028 EPS（A） | D85: 隱含 ÷ 模型 A − 1 | E85: 模型 FY2028 EPS（C） | F85: 隱含 ÷ 模型 C − 1
A86: 15 | B86: =px/A86 -> 50.411333 | C86: =PL!F14 -> 32.725343 | D86: =B86/C86-1 -> 0.54043714 | E86: =PL!F40 -> 25.043697 | F86: =B86/E86-1 -> 1.012935
A87: 20 | B87: =px/A87 -> 37.8085 | C87: =PL!F14 -> 32.725343 | D87: =B87/C87-1 -> 0.15532785 | E87: =PL!F40 -> 25.043697 | F87: =B87/E87-1 -> 0.50970124
A88: 30 | B88: =px/A88 -> 25.205667 | C88: =PL!F14 -> 32.725343 | D88: =B88/C88-1 -> -0.22978143 | E88: =PL!F40 -> 25.043697 | F88: =B88/E88-1 -> 0.0064674906
A89: =pe_mid -> 17.68 | B89: =px/A89 -> 42.769796 | C89: =PL!F14 -> 32.725343 | D89: =B89/C89-1 -> 0.30693196 | E89: =PL!F40 -> 25.043697 | F89: =B89/E89-1 -> 0.70780683
A90: 讀法：第四列＝十年 P/E 中位數（規則中段倍數）。若市場對 FY2028 只給歷史中位數倍數，現價隱含的 FY2028 EPS 遠高於模型——現價定價的是 AI 時代的較高倍數或比模型更高的獲利（見第 0 節目標價方法）。
A92: 本版未做先驗：無 Andy 合理 P/E 對照。
A97: 6. 十年倍數與規則值（2016–2025 年底；見頂年 25 分位、中段中位數、谷底 75 分位）
A98: 規則（Andy 2026-10-13）：合理倍數＝年底 P/E 依循環位置取分位。採用 non-GAAP 推導序列（與模型 EPS 同口徑）；GAAP 序列（companiesmarketcap）只列參考。2016–2023 年 Lumentum 以電信、3D 感測為主（AI 前），倍數約 10–24x；2024–2025 年 AI 轉型期倍數 55–69x。
A100: P/E：十年歷史倍數
A101: 年底 | B101: 年底股價 ÷ 近 12 月 non-GAAP EPS（推導） | C101: companiesmarketcap（GAAP 年底 P/E） | D101: 標記／說明
A102: 2016 | B102: =38.65/((1.29+1.94)/2) -> 23.931889 | C102: 161 | D102: 年底股價 ÷ 近 12 月 non-GAAP EPS（推導）：Derived（股價：digrin 年底；EPS：公司新聞稿 FY2016–FY2026 non-GAAP 稀釋 EPS；近 12 月＝年底前後兩個會計年度平均）；companiesmarketcap（GAAP 年底 P/E）：Interested-party（資料商；GAAP 口徑含併購攤銷、可轉債損失，2019、2023、2024 為負不列；只作參考、不採用）
A103: 2017 | B103: =48.9/((1.94+3.82)/2) -> 16.979167 | C103: 32.6 | D103: FY2018 non-GAAP EPS 3.82 與 GAAP 同值（新聞稿擷取結果，待人工複核）；FY2020 起為公司新口徑
A104: 2018 | B104: =42.01/((3.82+4.25)/2) -> 10.4114 | C104: 27.5
A105: 2019 | B105: =79.3/((4.25+4.95)/2) -> 17.23913
A106: 2020 | B106: =94.8/((4.95+5.84)/2) -> 17.571826 | C106: 37.8
A107: 2021 | B107: =105.77/((5.84+6.05)/2) -> 17.791421 | C107: 20.5
A108: 2022 | B108: =52.17/((6.05+4.56)/2) -> 9.8341188 | C108: 130
A109: 2023 | B109: =52.42/((4.56+1.01)/2) -> 18.822262
A110: 2024 | B110: =83.95/((1.01+2.06)/2) -> 54.690554
A111: 2025 | B111: =368.59/((2.06+8.67)/2) -> 68.702703 | C111: 103
A112: 25 分位（各來源） | B112: =PERCENTILE(B102:B111,0.25) -> 17.044158 | C112: =PERCENTILE(C102:C111,0.25) -> 30.05
A113: 中位數（各來源） | B113: =MEDIAN(B102:B111) -> 17.681624 | C113: =MEDIAN(C102:C111) -> 37.8
...

Sheet Recon
A1: Recon — 本模型 vs 公司指引、共識、券商與研調。只作事後對照，不為對上數字而調參數。共識區間寬（FY2027 EPS 19.05–25.27），FY2028 共識只有單一來源、5 家
A3: 項目 | B3: 對照值 | C3: 模型 A | D3: 差距 A | E3: 模型 B | F3: 差距 B | G3: 模型 C | H3: 差距 C | I3: 對照來源 | J3: 說明
A4: A. 共識與券商（校準未使用）
A5: FY2027 營收 vs 共識 | B5: =cons_rev27 -> 6.3 | C5: =PL!E93 -> 6.6131693 | D5: =C5/B5-1 -> 0.049709412 | E5: =PL!E145 -> 6.5334968 | F5: =E5/B5-1 -> 0.037062985 | G5: =PL!E197 -> 6.4936606 | H5: =G5/B5-1 -> 0.030739771 | I5: stockanalysis（23 家；56–72 億美元） | J5: FY2027 上半年＝指引＋季增假設
A6: FY2027 EPS vs 共識 | B6: =cons_eps27 -> 21.79 | C6: =PL!E108 -> 23.475185 | D6: =C6/B6-1 -> 0.077337535 | E6: =PL!E160 -> 23.160265 | F6: =E6/B6-1 -> 0.062885037 | G6: =PL!E212 -> 23.002805 | H6: =G6/B6-1 -> 0.055658788 | I6: stockanalysis（23 家；19.05–25.27）
A7: FY2028 EPS vs 共識（單一來源） | B7: =cons_eps28 -> 23.6 | C7: =PL!F108 -> 32.725343 | D7: =C7/B7-1 -> 0.38666707 | E7: =PL!F160 -> 28.435633 | F7: =E7/B7-1 -> 0.20489969 | G7: =PL!F212 -> 25.043697 | H7: =G7/B7-1 -> 0.061173593 | I7: tickflow（5 家；13.23–35.39） | J7: 該頁年度與季度數字不一致；可信度低
A8: FY2028 淨利 vs trefis 轉述共識 | B8: =cons_ni28 -> 2.4 | C8: =PL!F105 -> 3.3713648 | D8: =C8/B8-1 -> 0.40473534 | E8: =PL!F157 -> 2.9294389 | F8: =E8/B8-1 -> 0.22059954 | G8: =PL!F209 -> 2.5800016 | H8: =G8/B8-1 -> 0.075000685 | I8: trefis（2026-10-08） | J8: 口徑未說明
A9: B. 數量、份額與產品（機制檢查）
A10: CY2026 高速光模組數量 vs 凱基 800G＋1.6T 出貨（百萬個） | B10: =kgi_m26 -> 67.2 | C10: =PL!C65 -> 59.506524 | D10: =C10/B10-1 -> -0.11448625 | E10: =PL!C117 -> 59.506524 | F10: =E10/B10-1 -> -0.11448625 | G10: =PL!C169 -> 59.506524 | H10: =G10/B10-1 -> -0.11448625 | I10: 凱基 2026-08-18 | J10: 差距＝網通模型金額 ÷ 本模型單價 vs 券商數量；凱基 2028 年遠高於網通模型（網通模型 2028 年保守）
A11: CY2027 高速光模組數量 vs 凱基 800G＋1.6T 出貨（百萬個） | B11: =kgi_m27 -> 107.5 | C11: =PL!D65 -> 103.00137 | D11: =C11/B11-1 -> -0.041847674 | E11: =PL!D117 -> 105.16983 | F11: =E11/B11-1 -> -0.021676047 | G11: =PL!D169 -> 106.25405 | H11: =G11/B11-1 -> -0.011590233 | I11: 凱基 2026-08-18 | J11: 差距＝網通模型金額 ÷ 本模型單價 vs 券商數量；凱基 2028 年遠高於網通模型（網通模型 2028 年保守）
A12: CY2028 高速光模組數量 vs 凱基 800G＋1.6T 出貨（百萬個） | B12: =kgi_m28 -> 151.1 | C12: =PL!E65 -> 107.39167 | D12: =C12/B12-1 -> -0.28926759 | E12: =PL!E117 -> 90.686296 | F12: =E12/B12-1 -> -0.39982597 | G12: =PL!E169 -> 69.446611 | H12: =G12/B12-1 -> -0.54039304 | I12: 凱基 2026-08-18 | J12: 差距＝網通模型金額 ÷ 本模型單價 vs 券商數量；凱基 2028 年遠高於網通模型（網通模型 2028 年保守）
A13: CY2026 雷射有效份額 vs EML 前三大合計 72%（百分點） | B13: =tf_eml3 -> 0.72 | C13: =PL!C71 -> 0.43826657 | D13: =C13-B13 -> -0.28173343 | E13: =PL!C123 -> 0.43826657 | F13: =E13-B13 -> -0.28173343 | G13: =PL!C175 -> 0.43826657 | H13: =G13-B13 -> -0.28173343 | I13: TrendForce | J13: 有效份額含 CW、以金額計；EML 前三大合計的三分之一約 24%，Lumentum 為 EML 第一、200G 唯一量產
A14: CY2026 雷射晶片 ÷ 營收 | C14: =PL!C72/(c26_rev/1000) -> 0.41765404 | E14: =PL!C124/(c26_rev/1000) -> 0.41765404 | G14: =PL!C176/(c26_rev/1000) -> 0.41765404 | I14: Q 頁殘差
A15: CY2026 元件類（雷射＋電信與 DCI＋CPO＋3D 感測一半）÷ 營收 vs 元件部門 64.5%（百分點） | B15: =Q!B27 -> 0.64533439 | C15: =(PL!C72+PL!C83+PL!C81+PL!C84/2)/(c26_rev/1000) -> 0.6304343 | D15: =C15-B15 -> -0.014900098 | E15: =(PL!C124+PL!C135+PL!C133+PL!C136/2)/(c26_rev/1000) -> 0.6304343 | F15: =E15-B15 -> -0.014900098 | G15: =(PL!C176+PL!C187+PL!C185+PL!C188/2)/(c26_rev/1000) -> 0.6304343 | H15: =G15-B15 -> -0.014900098 | I15: 公司 FY2026 第四季部門 | J15: 3D 感測（元件）與工業雷射（系統）各半，Assumed
A16: CY2027 OCS 營收 vs Coherent 估 OCS 市場 40 億美元（占比） | C16: =PL!D78/4 -> 0.28571429 | E16: =PL!D130/4 -> 0.28571429 | G16: =PL!D182/4 -> 0.28571429 | I16: 凱基轉述 Coherent
A17: CY2027 AI 相關營收 ÷ AI IT 資本支出 | C17: =PL!D82/itc_27 -> 0.0045905229 | E17: =PL!D134/itc_27 -> 0.0044822303 | G17: =PL!D186/itc_27 -> 0.0044280839 | I17: markets/network | J17: 每 1 美元 AI IT 資本支出分到的 Lumentum 營收
A18: CY2028 雷射有效份額 | C18: =PL!E71 -> 0.41635324 | E18: =PL!E123 -> 0.41635324 | G18: =PL!E175 -> 0.41635324 | I18: —
A19: C. 校準
A20: FY2025 EPS（淨利 ÷ 推導股數）vs 公司揭露（股數由 EPS 推導，恆等） | B20: =a25_eps_in -> 2.06 | C20: =Q!B13 -> 2.06 | D20: =C20/B20-1 -> 0 | E20: =Q!B13 -> 2.06 | F20: =E20/B20-1 -> 0 | G20: =Q!B13 -> 2.06 | H20: =G20/B20-1 -> 0 | I20: 公司 | J20: 公司揭露稀釋股數 71.2（推導 71.1）
A21: FY2026 EPS vs 公司揭露 8.67 | B21: =a26_eps_in -> 8.67 | C21: =PL!D108 -> 8.67 | D21: =C21/B21-1 -> 0 | E21: =PL!D160 -> 8.67 | F21: =E21/B21-1 -> 0 | G21: =PL!D212 -> 8.67 | H21: =G21/B21-1 -> 0 | I21: 公司 | J21: 公司揭露稀釋股數 90.2
A22: FY2027 第一季營業外淨收入（推導，年化 US$B） | C22: =oi_oth -> 0.052215569 | E22: =oi_oth -> 0.052215569 | G22: =oi_oth -> 0.052215569 | I22: Q1 指引
A23: D. 預留
A24: R4 產業部署路徑（markets/deploy_path/，尚未建立）：上線後以 Lumentum AI 營收 ÷ 部署 GW 計算每 GW 營收 | J24: 預留列：本版無數值
A25: FY2027 第一季財報（約 2026-11-05）：公布後以實績取代 Q 頁第一季、以新指引取代第二季 | J25: 預留列：本版無數值

Sheet Sens
A1: Sens — 一次動一個輸入（情境 A；份額在每個案例內依 CY2026 錨點重算，CY2026 恆等於錨點）：對 FY2027、FY2028 的營收、AI 相關營收、毛利率與 EPS 的影響。每個案例是一個完整推導區塊（本頁下方）
A3: 案例 | B3: 設定 | C3: FY2027 營收 | D3: FY2027 AI 相關營收 | E3: FY2027 毛利率 | F3: FY2027 EPS | G3: FY2027 EPS 相對基準 | H3: FY2028 營收 | I3: FY2028 AI 相關營收 | J3: FY2028 毛利率 | K3: FY2028 EPS | L3: FY2028 EPS 相對基準
A4: 基準（情境 A） | B4: PL 區塊 A | C4: =PL!E93 -> 6.6131693 | D4: =PL!E91 -> 5.4040921 | E4: =PL!E99 -> 0.52 | F4: =PL!E108 -> 23.475185 | G4: =F4/F$4-1 -> 0 | H4: =PL!F93 -> 9.14381 | I4: =PL!F91 -> 7.8268594 | J4: =PL!F99 -> 0.51 | K4: =PL!F108 -> 32.725343 | L4: =K4/K$4-1 -> 0
A5: 雷射份額流失（低） | B5: 雷射份額相對值 CY2027 0.85、CY2028 0.80、CY2029 0.70（Broadcom、Coherent、中國 EML 追趕） | C5: =E73 -> 6.438131 | D5: =E71 -> 5.2290538 | E5: =E79 -> 0.52 | F5: =E88 -> 22.783314 | G5: =F5/F$4-1 -> -0.029472429 | H5: =F73 -> 8.697564 | I5: =F71 -> 7.3806133 | J5: =F79 -> 0.51 | K5: =F88 -> 30.974317 | L5: =K5/K$4-1 -> -0.053506719
A6: 雷射份額 高 | B6: 相對值 1.00／1.05／1.05（Greensboro 擴產） | C6: =E125 -> 6.7006885 | D6: =E123 -> 5.4916113 | E6: =E131 -> 0.52 | F6: =E140 -> 23.82112 | G6: =F6/F$4-1 -> 0.014736214 | H6: =F125 -> 9.4084101 | I6: =F123 -> 8.0914595 | J6: =F131 -> 0.51 | K6: =F140 -> 33.765552 | L6: =K6/K$4-1 -> 0.031786057
A7: 每模組雷射數 低（矽光替代） | B7: CY2027 4.5、CY2028 4.0、CY2029 3.5 顆 | C7: =E177 -> 6.3108304 | D7: =E175 -> 5.1017532 | E7: =E183 -> 0.52 | F7: =E192 -> 22.280135 | G7: =F7/F$4-1 -> -0.050906922 | H7: =F177 -> 8.4876489 | I7: =F175 -> 7.1706982 | J7: =F183 -> 0.51 | K7: =F192 -> 30.154837 | L7: =K7/K$4-1 -> -0.078547858
A8: 雷射單價 低 | B8: CY2027 $12、CY2028 $11、CY2029 $10 | C8: =E229 -> 6.2805965 | D8: =E227 -> 5.0715193 | E8: =E235 -> 0.52 | F8: =E244 -> 22.160631 | G8: =F8/F$4-1 -> -0.055997614 | H8: =F229 -> 8.3484801 | I8: =F227 -> 7.0315295 | J8: =F235 -> 0.51 | K8: =F244 -> 29.60715 | L8: =K8/K$4-1 -> -0.095283734
A9: 雷射單價 高 | B9: $17／$18／$18 | C9: =E281 -> 6.8348845 | D9: =E279 -> 5.6258074 | E9: =E287 -> 0.52 | F9: =E296 -> 24.351554 | G9: =F9/F$4-1 -> 0.037331743 | H9: =F281 -> 9.709055 | I9: =F279 -> 8.3921044 | J9: =F287 -> 0.51 | K9: =F296 -> 34.944942 | L9: =K9/K$4-1 -> 0.067825077
A10: 光模組單價 高（模組數少） | B10: CY2027 $640、CY2028 $680、CY2029 $720 | C10: =E333 -> 6.3013823 | D10: =E331 -> 5.0923051 | E10: =E339 -> 0.52 | F10: =E348 -> 22.24279 | G10: =F10/F$4-1 -> -0.052497763 | H10: =F333 -> 8.4677233 | I10: =F331 -> 7.1507727 | J10: =F339 -> 0.51 | K10: =F348 -> 30.076841 | L10: =K10/K$4-1 -> -0.080931224
A11: 光模組份額 低 | B11: 相對值 0.80／0.70／0.60 | C11: =E385 -> 6.443954 | D11: =E383 -> 5.2348768 | E11: =E391 -> 0.52 | F11: =E400 -> 22.806331 | G11: =F11/F$4-1 -> -0.028491964 | H11: =F385 -> 8.6781724 | I11: =F383 -> 7.3612218 | J11: =F391 -> 0.51 | K11: =F400 -> 30.897104 | L11: =K11/K$4-1 -> -0.055866159
A12: 光模組份額 高 | B12: 相對值 1.20／1.30／1.30 | C12: =E437 -> 6.7823846 | D12: =E435 -> 5.5733074 | E12: =E443 -> 0.52 | F12: =E452 -> 24.144039 | G12: =F12/F$4-1 -> 0.028491964 | H12: =F437 -> 9.6094476 | I12: =F435 -> 8.292497 | J12: =F443 -> 0.51 | K12: =F452 -> 34.554838 | L12: =K12/K$4-1 -> 0.055904538
A13: OCS 低 | B13: 每顆 TPU 營收相對值 1.2／1.2／1.0 | C13: =E489 -> 6.4788836 | D13: =E487 -> 5.2698064 | E13: =E495 -> 0.52 | F13: =E504 -> 22.944396 | G13: =F13/F$4-1 -> -0.022610625 | H13: =F489 -> 8.7360178 | I13: =F487 -> 7.4190672 | J13: =F495 -> 0.51 | K13: =F504 -> 31.122951 | L13: =K13/K$4-1 -> -0.048964853
A14: OCS 高 | B14: 2.0／2.4／2.4 | C14: =E541 -> 6.747455 | D14: =E539 -> 5.5383778 | E14: =E547 -> 0.52 | F14: =E556 -> 24.005973 | G14: =F14/F$4-1 -> 0.022610625 | H14: =F541 -> 9.5516022 | I14: =F539 -> 8.2346516 | J14: =F547 -> 0.51 | K14: =F556 -> 34.32869 | L14: =K14/K$4-1 -> 0.048994047
A15: CPO 份額 低 | B15: 10% | C15: =E593 -> 6.4144309 | D15: =E591 -> 5.2053537 | E15: =E599 -> 0.52 | F15: =E608 -> 22.689635 | G15: =F15/F$4-1 -> -0.033462981 | H15: =F593 -> 8.465434 | I15: =F591 -> 7.1484833 | J15: =F599 -> 0.51 | K15: =F608 -> 30.058106 | L15: =K15/K$4-1 -> -0.081503716
A16: CPO 份額 高 | B16: 35%／35%／30% | C16: =E645 -> 6.7456616 | D16: =E643 -> 5.5365844 | E16: =E651 -> 0.52 | F16: =E660 -> 23.998885 | G16: =F16/F$4-1 -> 0.022308654 | H16: =F645 -> 9.5960607 | I16: =F643 -> 8.2791101 | J16: =F651 -> 0.51 | K16: =F660 -> 34.504943 | L16: =K16/K$4-1 -> 0.054379875
A17: 毛利率 低 | B17: FY2027 49%、FY2028 46%、FY2029 42% | C17: =E697 -> 6.6131693 | D17: =E695 -> 5.4040921 | E17: =E703 -> 0.49 | F17: =E712 -> 21.851068 | G17: =F17/F$4-1 -> -0.0691844 | H17: =F697 -> 9.14381 | I17: =F695 -> 7.8268594 | J17: =F703 -> 0.46 | K17: =F712 -> 29.019712 | L17: =K17/K$4-1 -> -0.11323428
A18: 毛利率 高 | B18: 54%／54%／53% | C18: =E749 -> 6.6131693 | D18: =E747 -> 5.4040921 | E18: =E755 -> 0.54 | F18: =E764 -> 24.557929 | G18: =F18/F$4-1 -> 0.046122933 | H18: =F749 -> 9.14381 | I18: =F747 -> 7.8268594 | J18: =F755 -> 0.54 | K18: =F764 -> 34.948721 | L18: =K18/K$4-1 -> 0.067940568
A19: AI 市場 ×0.8 | B19: CY2027 起可插拔光模組市場 ×0.8 | C19: =E801 -> 6.1113812 | D19: =E799 -> 4.902304 | E19: =E807 -> 0.52 | F19: =E816 -> 21.491776 | G19: =F19/F$4-1 -> -0.084489578 | H19: =F801 -> 8.0795245 | I19: =F799 -> 6.7625739 | J19: =F807 -> 0.51 | K19: =F816 -> 28.558254 | L19: =K19/K$4-1 -> -0.12733522
A20: AI 市場 ×1.2 | B20: ×1.2 | C20: =E853 -> 7.1149574 | D20: =E851 -> 5.9058803 | E20: =E859 -> 0.52 | F20: =E868 -> 25.458593 | G20: =F20/F$4-1 -> 0.084489578 | H20: =F853 -> 10.208096 | I20: =F851 -> 8.8911449 | J20: =F859 -> 0.51 | K20: =F868 -> 36.898418 | L20: =K20/K$4-1 -> 0.12751815
A21: 上半年占比 44% | B21: 日曆年上半年占 44%（會計年度換算） | C21: =E905 -> 6.360201 | D21: =E903 -> 5.1885189 | E21: =E911 -> 0.52 | F21: =E920 -> 22.475282 | G21: =F21/F$4-1 -> -0.042594034 | H21: =F905 -> 9.0983929 | I21: =F903 -> 7.7859391 | J21: =F911 -> 0.51 | K21: =F920 -> 32.565991 | L21: =K21/K$4-1 -> -0.0048693573
A22: 營業費用率 +2pt | B22: 營業費用額外 +2% × 營收 | C22: =E957 -> 6.6131693 | D22: =E955 -> 5.4040921 | E22: =E963 -> 0.52 | F22: =E972 -> 22.392441 | G22: =F22/F$4-1 -> -0.046122933 | H22: =F957 -> 9.14381 | I22: =F955 -> 7.8268594 | J22: =F963 -> 0.51 | K22: =F972 -> 31.243091 | L22: =K22/K$4-1 -> -0.045293712
A23: 顆數情境 B | B23: CY2028 ×0.8、CY2029 ×0.85；CPO 情境 B | C23: =PL!E145 -> 6.5334968 | D23: =PL!E143 -> 5.3244196 | E23: =PL!E151 -> 0.52 | F23: =PL!E160 -> 23.160265 | G23: =F23/F$4-1 -> -0.013415014 | H23: =PL!F145 -> 8.0582066 | I23: =PL!F143 -> 6.741256 | J23: =PL!F151 -> 0.51 | K23: =PL!F160 -> 28.435633 | L23: =K23/K$4-1 -> -0.1310822
A24: 顆數情境 C | B24: CY2028–29 ×0.6；CPO 情境 C | C24: =PL!E197 -> 6.4936606 | D24: =PL!E195 -> 5.2845834 | E24: =PL!E203 -> 0.52 | F24: =PL!E212 -> 23.002805 | G24: =F24/F$4-1 -> -0.020122522 | H24: =PL!F197 -> 7.2000012 | I24: =PL!F195 -> 5.8830505 | J24: =PL!F203 -> 0.51 | K24: =PL!F212 -> 25.043697 | L24: =K24/K$4-1 -> -0.2347308
A26: 讀法：FY2027 有一半來自 CY2026 下半年（指引＋假設），所以 FY2027 對各輸入的敏感度約只有 FY2028 的一半；顆數情境 B、C 的差異從 FY2028 起。雷射份額、單價、每模組雷射數三者相乘，是雷射晶片營收的三條路徑。
A28: 目標價參數（只改 DCF 參數與權重；PL 收斂法的 fade_g 不隨 tp_g 變動）
A29: 案例 | B29: 設定 | C29: DCF 目標價 | D29: Comparable 目標價 | E29: 加權目標價 | F29: 相對基準
A30: 基準 | B30: r 10%、g 4%、DCF 權重 0.5 | C30: =(tp_wA*(Val!B8*(1-IF(tp_roe<=tp_g,0.8,MIN(tp_g/tp_roe,0.8)))/(1+tp_r)^1+Val!B9*(1-IF(tp_roe<=tp_g,0.8,MIN(tp_g/tp_roe,0.8)))/(1+tp_r)^2+Val!B10*(1-IF(tp_roe<=tp_g,0.8,MIN(tp_g/tp_roe,0.8)))/(1+tp_r)^3+Val!B11*(1-IF(tp_roe<=tp_g,0.8,MIN(tp_g/tp_roe,0.8)))/(1+tp_r)^4+Val!B12*(1-IF(tp_roe<=tp_g,0.8,MIN(tp_g/tp_roe,0.8)))/(1+tp_r)^5+Val!B13*(1-IF(tp_roe<=tp_g,0.8,MIN(tp_g/tp_roe,0.8)))/(1+tp_r)^6+Val!B13*(1-IF(tp_roe<=tp_g,0.8,MIN(tp_g/tp_roe,0.8)))*(1+tp_g)/(tp_r-tp_g)/(1+tp_r)^6)+tp_wB*(Val!C8*(1-IF(tp_roe<=tp_g,0.8,MIN(tp_g/tp_roe,0.8)))/(1+tp_r)^1+Val!C9*(1-IF(tp_roe<=tp_g,0.8,MIN(tp_g/tp_roe,0.8)))/(1+tp_r)^2+Val!C10*(1-IF(tp_roe<=tp_g,0.8,MIN(tp_g/tp_roe,0.8)))/(1+tp_r)^3+Val!C11*(1-IF(tp_roe<=tp_g,0.8,MIN(tp_g/tp_roe,0.8)))/(1+tp_r)^4+Val!C12*(1-IF(tp_roe<=tp_g,0.8,MIN(tp_g/tp_roe,0.8)))/(1+tp_r)^5+Val!C13*(1-IF(tp_roe<=tp_g,0.8,MIN(tp_g/tp_roe,0.8)))/(1+tp_r)^6+Val!C13*(1-IF(tp_roe<=tp_g,0.8,MIN(tp_g/tp_roe,0.8)))*(1+tp_g)/(tp_r-tp_g)/(1+tp_r)^6)+tp_wC*(Val!D8*(1-IF(tp_roe<=tp_g,0.8,MIN(tp_g/tp_roe,0.8)))/(1+tp_r)^1+Val!D9*(1-IF(tp_roe<=tp_g,0.8,MIN(tp_g/tp_roe,0.8)))/(1+tp_r)^2+Val!D10*(1-IF(tp_roe<=tp_g,0.8,MIN(tp_g/tp_roe,0.8)))/(1+tp_r)^3+Val!D11*(1-IF(tp_roe<=tp_g,0.8,MIN(tp_g/tp_roe,0.8)))/(1+tp_r)^4+Val!D12*(1-IF(tp_roe<=tp_g,0.8,MIN(tp_g/tp_roe,0.8)))/(1+tp_r)^5+Val!D13*(1-IF(tp_roe<=tp_g,0.8,MIN(tp_g/tp_roe,0.8)))/(1+tp_r)^6+Val!D13*(1-IF(tp_roe<=tp_g,0.8,MIN(tp_g/tp_roe,0.8)))*(1+tp_g)/(tp_r-tp_g)/(1+tp_r)^6))*(1+tp_r) -> 387.08317 | D30: =Val!B35 -> 859.71661 | E30: =tp_w_dcf*C30+(1-tp_w_dcf)*D30 -> 623.39989 | F30: =E30/E$30-1 -> 0
A31: 折現率 +1pt | B31: r 11% | C31: =(tp_wA*(Val!B8*(1-IF(tp_roe<=tp_g,0.8,MIN(tp_g/tp_roe,0.8)))/(1+(tp_r+0.01))^1+Val!B9*(1-IF(tp_roe<=tp_g,0.8,MIN(tp_g/tp_roe,0.8)))/(1+(tp_r+0.01))^2+Val!B10*(1-IF(tp_roe<=tp_g,0.8,MIN(tp_g/tp_roe,0.8)))/(1+(tp_r+0.01))^3+Val!B11*(1-IF(tp_roe<=tp_g,0.8,MIN(tp_g/tp_roe,0.8)))/(1+(tp_r+0.01))^4+Val!B12*(1-IF(tp_roe<=tp_g,0.8,MIN(tp_g/tp_roe,0.8)))/(1+(tp_r+0.01))^5+Val!B13*(1-IF(tp_roe<=tp_g,0.8,MIN(tp_g/tp_roe,0.8)))/(1+(tp_r+0.01))^6+Val!B13*(1-IF(tp_roe<=tp_g,0.8,MIN(tp_g/tp_roe,0.8)))*(1+tp_g)/((tp_r+0.01)-tp_g)/(1+(tp_r+0.01))^6)+tp_wB*(Val!C8*(1-IF(tp_roe<=tp_g,0.8,MIN(tp_g/tp_roe,0.8)))/(1+(tp_r+0.01))^1+Val!C9*(1-IF(tp_roe<=tp_g,0.8,MIN(tp_g/tp_roe,0.8)))/(1+(tp_r+0.01))^2+Val!C10*(1-IF(tp_roe<=tp_g,0.8,MIN(tp_g/tp_roe,0.8)))/(1+(tp_r+0.01))^3+Val!C11*(1-IF(tp_roe<=tp_g,0.8,MIN(tp_g/tp_roe,0.8)))/(1+(tp_r+0.01))^4+Val!C12*(1-IF(tp_roe<=tp_g,0.8,MIN(tp_g/tp_roe,0.8)))/(1+(tp_r+0.01))^5+Val!C13*(1-IF(tp_roe<=tp_g,0.8,MIN(tp_g/tp_roe,0.8)))/(1+(tp_r+0.01))^6+Val!C13*(1-IF(tp_roe<=tp_g,0.8,MIN(tp_g/tp_roe,0.8)))*(1+tp_g)/((tp_r+0.01)-tp_g)/(1+(tp_r+0.01))^6)+tp_wC*(Val!D8*(1-IF(tp_roe<=tp_g,0.8,MIN(tp_g/tp_roe,0.8)))/(1+(tp_r+0.01))^1+Val!D9*(1-IF(tp_roe<=tp_g,0.8,MIN(tp_g/tp_roe,0.8)))/(1+(tp_r+0.01))^2+Val!D10*(1-IF(tp_roe<=tp_g,0.8,MIN(tp_g/tp_roe,0.8)))/(1+(tp_r+0.01))^3+Val!D11*(1-IF(tp_roe<=tp_g,0.8,MIN(tp_g/tp_roe,0.8)))/(1+(tp_r+0.01))^4+Val!D12*(1-IF(tp_roe<=tp_g,0.8,MIN(tp_g/tp_roe,0.8)))/(1+(tp_r+0.01))^5+Val!D13*(1-IF(tp_roe<=tp_g,0.8,MIN(tp_g/tp_roe,0.8)))/(1+(tp_r+0.01))^6+Val!D13*(1-IF(tp_roe<=tp_g,0.8,MIN(tp_g/tp_roe,0.8)))*(1+tp_g)/((tp_r+0.01)-tp_g)/(1+(tp_r+0.01))^6))*(1+(tp_r+0.01)) -> 334.85216 | D31: =Val!B35 -> 859.71661 | E31: =tp_w_dcf*C31+(1-tp_w_dcf)*D31 -> 597.28438 | F31: =E31/E$30-1 -> -0.041892058
A32: 折現率 −1pt | B32: r 9% | C32: =(tp_wA*(Val!B8*(1-IF(tp_roe<=tp_g,0.8,MIN(tp_g/tp_roe,0.8)))/(1+(tp_r-0.01))^1+Val!B9*(1-IF(tp_roe<=tp_g,0.8,MIN(tp_g/tp_roe,0.8)))/(1+(tp_r-0.01))^2+Val!B10*(1-IF(tp_roe<=tp_g,0.8,MIN(tp_g/tp_roe,0.8)))/(1+(tp_r-0.01))^3+Val!B11*(1-IF(tp_roe<=tp_g,0.8,MIN(tp_g/tp_roe,0.8)))/(1+(tp_r-0.01))^4+Val!B12*(1-IF(tp_roe<=tp_g,0.8,MIN(tp_g/tp_roe,0.8)))/(1+(tp_r-0.01))^5+Val!B13*(1-IF(tp_roe<=tp_g,0.8,MIN(tp_g/tp_roe,0.8)))/(1+(tp_r-0.01))^6+Val!B13*(1-IF(tp_roe<=tp_g,0.8,MIN(tp_g/tp_roe,0.8)))*(1+tp_g)/((tp_r-0.01)-tp_g)/(1+(tp_r-0.01))^6)+tp_wB*(Val!C8*(1-IF(tp_roe<=tp_g,0.8,MIN(tp_g/tp_roe,0.8)))/(1+(tp_r-0.01))^1+Val!C9*(1-IF(tp_roe<=tp_g,0.8,MIN(tp_g/tp_roe,0.8)))/(1+(tp_r-0.01))^2+Val!C10*(1-IF(tp_roe<=tp_g,0.8,MIN(tp_g/tp_roe,0.8)))/(1+(tp_r-0.01))^3+Val!C11*(1-IF(tp_roe<=tp_g,0.8,MIN(tp_g/tp_roe,0.8)))/(1+(tp_r-0.01))^4+Val!C12*(1-IF(tp_roe<=tp_g,0.8,MIN(tp_g/tp_roe,0.8)))/(1+(tp_r-0.01))^5+Val!C13*(1-IF(tp_roe<=tp_g,0.8,MIN(tp_g/tp_roe,0.8)))/(1+(tp_r-0.01))^6+Val!C13*(1-IF(tp_roe<=tp_g,0.8,MIN(tp_g/tp_roe,0.8)))*(1+tp_g)/((tp_r-0.01)-tp_g)/(1+(tp_r-0.01))^6)+tp_wC*(Val!D8*(1-IF(tp_roe<=tp_g,0.8,MIN(tp_g/tp_roe,0.8)))/(1+(tp_r-0.01))^1+Val!D9*(1-IF(tp_roe<=tp_g,0.8,MIN(tp_g/tp_roe,0.8)))/(1+(tp_r-0.01))^2+Val!D10*(1-IF(tp_roe<=tp_g,0.8,MIN(tp_g/tp_roe,0.8)))/(1+(tp_r-0.01))^3+Val!D11*(1-IF(tp_roe<=tp_g,0.8,MIN(tp_g/tp_roe,0.8)))/(1+(tp_r-0.01))^4+Val!D12*(1-IF(tp_roe<=tp_g,0.8,MIN(tp_g/tp_roe,0.8)))/(1+(tp_r-0.01))^5+Val!D13*(1-IF(tp_roe<=tp_g,0.8,MIN(tp_g/tp_roe,0.8)))/(1+(tp_r-0.01))^6+Val!D13*(1-IF(tp_roe<=tp_g,0.8,MIN(tp_g/tp_roe,0.8)))*(1+tp_g)/((tp_r-0.01)-tp_g)/(1+(tp_r-0.01))^6))*(1+(tp_r-0.01)) -> 460.18299 | D32: =Val!B35 -> 859.71661 | E32: =tp_w_dcf*C32+(1-tp_w_dcf)*D32 -> 659.9498 | F32: =E32/E$30-1 -> 0.058629965
A33: 長期成長 +1pt | B33: g 5% | C33: =(tp_wA*(Val!B8*(1-IF(tp_roe<=(tp_g+0.01),0.8,MIN((tp_g+0.01)/tp_roe,0.8)))/(1+tp_r)^1+Val!B9*(1-IF(tp_roe<=(tp_g+0.01),0.8,MIN((tp_g+0.01)/tp_roe,0.8)))/(1+tp_r)^2+Val!B10*(1-IF(tp_roe<=(tp_g+0.01),0.8,MIN((tp_g+0.01)/tp_roe,0.8)))/(1+tp_r)^3+Val!B11*(1-IF(tp_roe<=(tp_g+0.01),0.8,MIN((tp_g+0.01)/tp_roe,0.8)))/(1+tp_r)^4+Val!B12*(1-IF(tp_roe<=(tp_g+0.01),0.8,MIN((tp_g+0.01)/tp_roe,0.8)))/(1+tp_r)^5+Val!B13*(1-IF(tp_roe<=(tp_g+0.01),0.8,MIN((tp_g+0.01)/tp_roe,0.8)))/(1+tp_r)^6+Val!B13*(1-IF(tp_roe<=(tp_g+0.01),0.8,MIN((tp_g+0.01)/tp_roe,0.8)))*(1+(tp_g+0.01))/(tp_r-(tp_g+0.01))/(1+tp_r)^6)+tp_wB*(Val!C8*(1-IF(tp_roe<=(tp_g+0.01),0.8,MIN((tp_g+0.01)/tp_roe,0.8)))/(1+tp_r)^1+Val!C9*(1-IF(tp_roe<=(tp_g+0.01),0.8,MIN((tp_g+0.01)/tp_roe,0.8)))/(1+tp_r)^2+Val!C10*(1-IF(tp_roe<=(tp_g+0.01),0.8,MIN((tp_g+0.01)/tp_roe,0.8)))/(1+tp_r)^3+Val!C11*(1-IF(tp_roe<=(tp_g+0.01),0.8,MIN((tp_g+0.01)/tp_roe,0.8)))/(1+tp_r)^4+Val!C12*(1-IF(tp_roe<=(tp_g+0.01),0.8,MIN((tp_g+0.01)/tp_roe,0.8)))/(1+tp_r)^5+Val!C13*(1-IF(tp_roe<=(tp_g+0.01),0.8,MIN((tp_g+0.01)/tp_roe,0.8)))/(1+tp_r)^6+Val!C13*(1-IF(tp_roe<=(tp_g+0.01),0.8,MIN((tp_g+0.01)/tp_roe,0.8)))*(1+(tp_g+0.01))/(tp_r-(tp_g+0.01))/(1+tp_r)^6)+tp_wC*(Val!D8*(1-IF(tp_roe<=(tp_g+0.01),0.8,MIN((tp_g+0.01)/tp_roe,0.8)))/(1+tp_r)^1+Val!D9*(1-IF(tp_roe<=(tp_g+0.01),0.8,MIN((tp_g+0.01)/tp_roe,0.8)))/(1+tp_r)^2+Val!D10*(1-IF(tp_roe<=(tp_g+0.01),0.8,MIN((tp_g+0.01)/tp_roe,0.8)))/(1+tp_r)^3+Val!D11*(1-IF(tp_roe<=(tp_g+0.01),0.8,MIN((tp_g+0.01)/tp_roe,0.8)))/(1+tp_r)^4+Val!D12*(1-IF(tp_roe<=(tp_g+0.01),0.8,MIN((tp_g+0.01)/tp_roe,0.8)))/(1+tp_r)^5+Val!D13*(1-IF(tp_roe<=(tp_g+0.01),0.8,MIN((tp_g+0.01)/tp_roe,0.8)))/(1+tp_r)^6+Val!D13*(1-IF(tp_roe<=(tp_g+0.01),0.8,MIN((tp_g+0.01)/tp_roe,0.8)))*(1+(tp_g+0.01))/(tp_r-(tp_g+0.01))/(1+tp_r)^6))*(1+tp_r) -> 417.59887 | D33: =Val!B35 -> 859.71661 | E33: =tp_w_dcf*C33+(1-tp_w_dcf)*D33 -> 638.65774 | F33: =E33/E$30-1 -> 0.024475225
A34: 長期成長 −1pt | B34: g 3% | C34: =(tp_wA*(Val!B8*(1-IF(tp_roe<=(tp_g-0.01),0.8,MIN((tp_g-0.01)/tp_roe,0.8)))/(1+tp_r)^1+Val!B9*(1-IF(tp_roe<=(tp_g-0.01),0.8,MIN((tp_g-0.01)/tp_roe,0.8)))/(1+tp_r)^2+Val!B10*(1-IF(tp_roe<=(tp_g-0.01),0.8,MIN((tp_g-0.01)/tp_roe,0.8)))/(1+tp_r)^3+Val!B11*(1-IF(tp_roe<=(tp_g-0.01),0.8,MIN((tp_g-0.01)/tp_roe,0.8)))/(1+tp_r)^4+Val!B12*(1-IF(tp_roe<=(tp_g-0.01),0.8,MIN((tp_g-0.01)/tp_roe,0.8)))/(1+tp_r)^5+Val!B13*(1-IF(tp_roe<=(tp_g-0.01),0.8,MIN((tp_g-0.01)/tp_roe,0.8)))/(1+tp_r)^6+Val!B13*(1-IF(tp_roe<=(tp_g-0.01),0.8,MIN((tp_g-0.01)/tp_roe,0.8)))*(1+(tp_g-0.01))/(tp_r-(tp_g-0.01))/(1+tp_r)^6)+tp_wB*(Val!C8*(1-IF(tp_roe<=(tp_g-0.01),0.8,MIN((tp_g-0.01)/tp_roe,0.8)))/(1+tp_r)^1+Val!C9*(1-IF(tp_roe<=(tp_g-0.01),0.8,MIN((tp_g-0.01)/tp_roe,0.8)))/(1+tp_r)^2+Val!C10*(1-IF(tp_roe<=(tp_g-0.01),0.8,MIN((tp_g-0.01)/tp_roe,0.8)))/(1+tp_r)^3+Val!C11*(1-IF(tp_roe<=(tp_g-0.01),0.8,MIN((tp_g-0.01)/tp_roe,0.8)))/(1+tp_r)^4+Val!C12*(1-IF(tp_roe<=(tp_g-0.01),0.8,MIN((tp_g-0.01)/tp_roe,0.8)))/(1+tp_r)^5+Val!C13*(1-IF(tp_roe<=(tp_g-0.01),0.8,MIN((tp_g-0.01)/tp_roe,0.8)))/(1+tp_r)^6+Val!C13*(1-IF(tp_roe<=(tp_g-0.01),0.8,MIN((tp_g-0.01)/tp_roe,0.8)))*(1+(tp_g-0.01))/(tp_r-(tp_g-0.01))/(1+tp_r)^6)+tp_wC*(Val!D8*(1-IF(tp_roe<=(tp_g-0.01),0.8,MIN((tp_g-0.01)/tp_roe,0.8)))/(1+tp_r)^1+Val!D9*(1-IF(tp_roe<=(tp_g-0.01),0.8,MIN((tp_g-0.01)/tp_roe,0.8)))/(1+tp_r)^2+Val!D10*(1-IF(tp_roe<=(tp_g-0.01),0.8,MIN((tp_g-0.01)/tp_roe,0.8)))/(1+tp_r)^3+Val!D11*(1-IF(tp_roe<=(tp_g-0.01),0.8,MIN((tp_g-0.01)/tp_roe,0.8)))/(1+tp_r)^4+Val!D12*(1-IF(tp_roe<=(tp_g-0.01),0.8,MIN((tp_g-0.01)/tp_roe,0.8)))/(1+tp_r)^5+Val!D13*(1-IF(tp_roe<=(tp_g-0.01),0.8,MIN((tp_g-0.01)/tp_roe,0.8)))/(1+tp_r)^6+Val!D13*(1-IF(tp_roe<=(tp_g-0.01),0.8,MIN((tp_g-0.01)/tp_roe,0.8)))*(1+(tp_g-0.01))/(tp_r-(tp_g-0.01))/(1+tp_r)^6))*(1+tp_r) -> 366.98811 | D34: =Val!B35 -> 859.71661 | E34: =tp_w_dcf*C34+(1-tp_w_dcf)*D34 -> 613.35236 | F34: =E34/E$30-1 -> -0.016117309
A35: DCF 權重 0.3 | B35: Comparable 0.7 | C35: =(tp_wA*(Val!B8*(1-IF(tp_roe<=tp_g,0.8,MIN(tp_g/tp_roe,0.8)))/(1+tp_r)^1+Val!B9*(1-IF(tp_roe<=tp_g,0.8,MIN(tp_g/tp_roe,0.8)))/(1+tp_r)^2+Val!B10*(1-IF(tp_roe<=tp_g,0.8,MIN(tp_g/tp_roe,0.8)))/(1+tp_r)^3+Val!B11*(1-IF(tp_roe<=tp_g,0.8,MIN(tp_g/tp_roe,0.8)))/(1+tp_r)^4+Val!B12*(1-IF(tp_roe<=tp_g,0.8,MIN(tp_g/tp_roe,0.8)))/(1+tp_r)^5+Val!B13*(1-IF(tp_roe<=tp_g,0.8,MIN(tp_g/tp_roe,0.8)))/(1+tp_r)^6+Val!B13*(1-IF(tp_roe<=tp_g,0.8,MIN(tp_g/tp_roe,0.8)))*(1+tp_g)/(tp_r-tp_g)/(1+tp_r)^6)+tp_wB*(Val!C8*(1-IF(tp_roe<=tp_g,0.8,MIN(tp_g/tp_roe,0.8)))/(1+tp_r)^1+Val!C9*(1-IF(tp_roe<=tp_g,0.8,MIN(tp_g/tp_roe,0.8)))/(1+tp_r)^2+Val!C10*(1-IF(tp_roe<=tp_g,0.8,MIN(tp_g/tp_roe,0.8)))/(1+tp_r)^3+Val!C11*(1-IF(tp_roe<=tp_g,0.8,MIN(tp_g/tp_roe,0.8)))/(1+tp_r)^4+Val!C12*(1-IF(tp_roe<=tp_g,0.8,MIN(tp_g/tp_roe,0.8)))/(1+tp_r)^5+Val!C13*(1-IF(tp_roe<=tp_g,0.8,MIN(tp_g/tp_roe,0.8)))/(1+tp_r)^6+Val!C13*(1-IF(tp_roe<=tp_g,0.8,MIN(tp_g/tp_roe,0.8)))*(1+tp_g)/(tp_r-tp_g)/(1+tp_r)^6)+tp_wC*(Val!D8*(1-IF(tp_roe<=tp_g,0.8,MIN(tp_g/tp_roe,0.8)))/(1+tp_r)^1+Val!D9*(1-IF(tp_roe<=tp_g,0.8,MIN(tp_g/tp_roe,0.8)))/(1+tp_r)^2+Val!D10*(1-IF(tp_roe<=tp_g,0.8,MIN(tp_g/tp_roe,0.8)))/(1+tp_r)^3+Val!D11*(1-IF(tp_roe<=tp_g,0.8,MIN(tp_g/tp_roe,0.8)))/(1+tp_r)^4+Val!D12*(1-IF(tp_roe<=tp_g,0.8,MIN(tp_g/tp_roe,0.8)))/(1+tp_r)^5+Val!D13*(1-IF(tp_roe<=tp_g,0.8,MIN(tp_g/tp_roe,0.8)))/(1+tp_r)^6+Val!D13*(1-IF(tp_roe<=tp_g,0.8,MIN(tp_g/tp_roe,0.8)))*(1+tp_g)/(tp_r-tp_g)/(1+tp_r)^6))*(1+tp_r) -> 387.08317 | D35: =Val!B35 -> 859.71661 | E35: =0.3*C35+(1-0.3)*D35 -> 717.92657 | F35: =E35/E$30-1 -> 0.1516309
A36: DCF 權重 0.7 | B36: Comparable 0.3 | C36: =(tp_wA*(Val!B8*(1-IF(tp_roe<=tp_g,0.8,MIN(tp_g/tp_roe,0.8)))/(1+tp_r)^1+Val!B9*(1-IF(tp_roe<=tp_g,0.8,MIN(tp_g/tp_roe,0.8)))/(1+tp_r)^2+Val!B10*(1-IF(tp_roe<=tp_g,0.8,MIN(tp_g/tp_roe,0.8)))/(1+tp_r)^3+Val!B11*(1-IF(tp_roe<=tp_g,0.8,MIN(tp_g/tp_roe,0.8)))/(1+tp_r)^4+Val!B12*(1-IF(tp_roe<=tp_g,0.8,MIN(tp_g/tp_roe,0.8)))/(1+tp_r)^5+Val!B13*(1-IF(tp_roe<=tp_g,0.8,MIN(tp_g/tp_roe,0.8)))/(1+tp_r)^6+Val!B13*(1-IF(tp_roe<=tp_g,0.8,MIN(tp_g/tp_roe,0.8)))*(1+tp_g)/(tp_r-tp_g)/(1+tp_r)^6)+tp_wB*(Val!C8*(1-IF(tp_roe<=tp_g,0.8,MIN(tp_g/tp_roe,0.8)))/(1+tp_r)^1+Val!C9*(1-IF(tp_roe<=tp_g,0.8,MIN(tp_g/tp_roe,0.8)))/(1+tp_r)^2+Val!C10*(1-IF(tp_roe<=tp_g,0.8,MIN(tp_g/tp_roe,0.8)))/(1+tp_r)^3+Val!C11*(1-IF(tp_roe<=tp_g,0.8,MIN(tp_g/tp_roe,0.8)))/(1+tp_r)^4+Val!C12*(1-IF(tp_roe<=tp_g,0.8,MIN(tp_g/tp_roe,0.8)))/(1+tp_r)^5+Val!C13*(1-IF(tp_roe<=tp_g,0.8,MIN(tp_g/tp_roe,0.8)))/(1+tp_r)^6+Val!C13*(1-IF(tp_roe<=tp_g,0.8,MIN(tp_g/tp_roe,0.8)))*(1+tp_g)/(tp_r-tp_g)/(1+tp_r)^6)+tp_wC*(Val!D8*(1-IF(tp_roe<=tp_g,0.8,MIN(tp_g/tp_roe,0.8)))/(1+tp_r)^1+Val!D9*(1-IF(tp_roe<=tp_g,0.8,MIN(tp_g/tp_roe,0.8)))/(1+tp_r)^2+Val!D10*(1-IF(tp_roe<=tp_g,0.8,MIN(tp_g/tp_roe,0.8)))/(1+tp_r)^3+Val!D11*(1-IF(tp_roe<=tp_g,0.8,MIN(tp_g/tp_roe,0.8)))/(1+tp_r)^4+Val!D12*(1-IF(tp_roe<=tp_g,0.8,MIN(tp_g/tp_roe,0.8)))/(1+tp_r)^5+Val!D13*(1-IF(tp_roe<=tp_g,0.8,MIN(tp_g/tp_roe,0.8)))/(1+tp_r)^6+Val!D13*(1-IF(tp_roe<=tp_g,0.8,MIN(tp_g/tp_roe,0.8)))*(1+tp_g)/(tp_r-tp_g)/(1+tp_r)^6))*(1+tp_r) -> 387.08317 | D36: =Val!B35 -> 859.71661 | E36: =0.7*C36+(1-0.7)*D36 -> 528.8732 | F36: =E36/E$30-1 -> -0.1516309
A40: 案例區塊：雷射份額流失（低）（情境 A）
A41: A. 日曆年產品營收（C 欄＝CY2026 錨點；D–F＝CY2027–CY2029）
A42: 項目 | B42: 單位 | C42: CY2026（錨點） | D42: CY2027 | E42: CY2028 | F42: CY2029 | H42: 說明
A43: AI 可插拔光模組市場 × 情境顆數係數 | B43: US$B | C43: =mpl_26*1 -> 29.753262 | D43: =mpl_27*1*1 -> 53.560715 | E43: =mpl_28*um28_A*1 -> 57.9915 | F43: =mpl_29*um29_A*1 -> 72.9348
A44: 光模組平均單價 | B44: $/個 | C44: =asp_26 -> 500 | D44: =asp_27 -> 520 | E44: =asp_28 -> 540 | F44: =asp_29 -> 560
A45: 高速光模組數量 ＝ 市場 ÷ 單價 | B45: 百萬個 | C45: =C43*1000/C44 -> 59.506524 | D45: =D43*1000/D44 -> 103.00137 | E45: =E43*1000/E44 -> 107.39167 | F45: =F43*1000/F44 -> 130.24071
A46: 每模組雷射數（EML／CW） | B46: 顆 | C46: =lpm_26 -> 5.5 | D46: =lpm_27 -> 5.5 | E46: =lpm_28 -> 5 | F46: =lpm_29 -> 4.8
A47: 雷射平均單價 | B47: $/顆 | C47: =lasp_26 -> 13 | D47: =lasp_27 -> 15 | E47: =lasp_28 -> 15 | F47: =lasp_29 -> 14
A48: 光模組雷射市場 ＝ 數量 × 每模組雷射數 × 單價 | B48: US$B | C48: =C45*C46*C47/1000 -> 4.2547165 | D48: =D45*D46*D47/1000 -> 8.4976134 | E48: =E45*E46*E47/1000 -> 8.054375 | F48: =F45*F46*F47/1000 -> 8.752176
A49: Lumentum 雷射有效份額（CY2026 校準）＝ 雷射晶片營收 ÷ 雷射市場 | B49: % | C49: =c26_las/1000/C48 -> 0.43826657 | H49: Derived：雷射晶片營收為 CY2026 錨點殘差
A50: 雷射份額相對值（÷ CY2026） | B50: x | C50: =1 -> 1 | D50: =LRLO_27 -> 0.85 | E50: =LRLO_28 -> 0.8 | F50: =LRLO_29 -> 0.7
A51: 雷射有效份額 | B51: % | C51: =$C$49*C50 -> 0.43826657 | D51: =$C$49*D50 -> 0.37252659 | E51: =$C$49*E50 -> 0.35061326 | F51: =$C$49*F50 -> 0.3067866
A52: 雷射晶片營收（EML／CW） | B52: US$B | C52: =C48*C51 -> 1.8647 | D52: =D48*D51 -> 3.1655869 | E52: =E48*E51 -> 2.8239707 | F52: =F48*F51 -> 2.6850503
A53: 光模組份額（CY2026 校準）＝ 光模組營收 ÷ 可插拔市場 | B53: % | C53: =c26_xcvr/1000/C43 -> 0.03360976
A54: 光模組份額 | B54: % | C54: =C53 -> 0.03360976 | D54: =$C$53*mrel_27 -> 0.03360976 | E54: =$C$53*mrel_28 -> 0.03360976 | F54: =$C$53*mrel_29 -> 0.03360976
A55: 光模組營收 | B55: US$B | C55: =C43*C54 -> 1 | D55: =D43*D54 -> 1.8001628 | E55: =E43*E54 -> 1.9490804 | F55: =F43*F54 -> 2.4513211
A56: Google TPU 顆數 × 情境顆數係數 | B56: 百萬顆 | C56: =tpu_26*1 -> 3.85 | D56: =tpu_27*1 -> 5.5 | E56: =tpu_28*um28_A -> 7 | F56: =tpu_29*um29_A -> 8.05
A57: OCS 每顆 TPU 營收（CY2026 校準 × 相對值） | B57: $/顆 | C57: =c26_ocs/C56 -> 129.87013 | D57: =$C57*ocsk_27 -> 207.79221 | E57: =$C57*ocsk_28 -> 233.76623 | F57: =$C57*ocsk_29 -> 233.76623
A58: OCS 營收 | B58: US$B | C58: =C56*C57/1000 -> 0.5 | D58: =D56*D57/1000 -> 1.1428571 | E58: =E56*E57/1000 -> 1.6363636 | F58: =F56*F57/1000 -> 1.8818182
A59: AI CPO 光學市場 × 情境顆數係數 | B59: US$B | C59: =mcp_26*1 -> 0.300538 | D59: =mcp_27*1 -> 2.818985 | E59: =mcp_28*um28_A -> 6.4435 | F59: =mcp_29*um29_A -> 11.74736
A60: Lumentum 占 CPO 光學金額 | B60: % | C60: =c26_cpo/1000/C59 -> 0.16636831 | D60: =cpo_27 -> 0.25 | E60: =cpo_28 -> 0.25 | F60: =cpo_29 -> 0.2
A61: CPO／外部光源營收 | B61: US$B | C61: =C59*C60 -> 0.05 | D61: =D59*D60 -> 0.70474625 | E61: =E59*E60 -> 1.610875 | F61: =F59*F60 -> 2.349472
A62: AI 相關營收（雷射晶片＋光模組＋OCS＋CPO） | B62: US$B | C62: =C52+C55+C58+C61 -> 3.4147 | D62: =D52+D55+D58+D61 -> 6.8133531 | E62: =E52+E55+E58+E61 -> 8.0202897 | F62: =F52+F55+F58+F61 -> 9.3676616
A63: 電信與 DCI 元件 | B63: US$B | C63: =c26_tel/1000 -> 0.75 | D63: =C63*(1+g_tel_27) -> 0.9375 | E63: =D63*(1+g_tel_28) -> 1.078125 | F63: =E63*(1+g_tel_29) -> 1.1859375
A64: 工業雷射與 3D 感測 | B64: US$B | C64: =c26_ind/1000 -> 0.3 | D64: =C64*(1+g_ind) -> 0.309 | E64: =D64*(1+g_ind) -> 0.31827 | F64: =E64*(1+g_ind) -> 0.3278181
A65: 元件（雷射晶片＋電信與 DCI＋CPO＋工業與 3D 感測一半；日曆年） | B65: US$B | C65: =C52+C63+C61+C64/2 -> 2.8147 | D65: =D52+D63+D61+D64/2 -> 4.9623332 | E65: =E52+E63+E61+E64/2 -> 5.6721057 | F65: =F52+F63+F61+F64/2 -> 6.3843689 | H65: 對應口徑與 Recon 頁元件部門相同
A66: 系統（光模組＋OCS＋工業與 3D 感測一半；日曆年） | B66: US$B | C66: =C55+C58+C64/2 -> 1.65 | D66: =D55+D58+D64/2 -> 3.0975199 | E66: =E55+E58+E64/2 -> 3.744579 | F66: =F55+F58+F64/2 -> 4.4970484
A67: 營收（日曆年） | B67: US$B | C67: =C62+C63+C64 -> 4.4647 | D67: =D62+D63+D64 -> 8.0598531 | E67: =E62+E63+E64 -> 9.4166847 | F67: =F62+F63+F64 -> 10.881417
A68: 營收年增（日曆年） | B68: % | D68: =D67/C67-1 -> 0.80523957 | E68: =E67/D67-1 -> 0.16834446 | F68: =F67/E67-1 -> 0.15554652
A69: B. 會計年度損益（FY(t)＝CY(t−1) 下半年＋CY(t) 上半年；C、D 欄＝FY2025、FY2026 實績）
A70: 項目 | B70: 單位 | C70: FY2025A | D70: FY2026A（錨點） | E70: FY2027 | F70: FY2028 | G70: FY2029 | H70: 說明
A71: AI 相關營收（會計年度） | B71: US$B | E71: =w2h_26*C62+h_1h*D62 -> 5.2290538 | F71: =(1-h_1h)*D62+h_1h*E62 -> 7.3806133 | G71: =(1-h_1h)*E62+h_1h*F62 -> 8.6535545 | H71: FY2027＝CY2026 下半年（Q 頁）＋ h × CY2027
A72: 電信、DCI、工業與 3D 感測（會計年度） | B72: US$B | E72: =w2h_26*C63+h_1h*D63+w2h_26*C64+h_1h*D64 -> 1.2090772 | F72: =(1-h_1h)*D63+h_1h*E63+(1-h_1h)*D64+h_1h*E64 -> 1.3169506 | G72: =(1-h_1h)*E63+h_1h*F63+(1-h_1h)*E64+h_1h*F64 -> 1.4515545
A73: 營收 | B73: US$B | C73: =a25_rev/1000 -> 1.645 | D73: =a26_rev/1000 -> 3.014 | E73: =E71+E72 -> 6.438131 | F73: =F71+F72 -> 8.697564 | G73: =G71+G72 -> 10.105109
A74: 元件營收（Components） | B74: US$B | C74: =a25_cmp/1000 -> 1.1163 | D74: =a26_cmp/1000 -> 2.0056 | E74: =w2h_26*C65+h_1h*D65 -> 4.0029475 | F74: =(1-h_1h)*D65+h_1h*E65 -> 5.2959262 | G74: =(1-h_1h)*E65+h_1h*F65 -> 6.0068694 | H74: 公司產品類別：Components（FY2025、FY2026 實績）
A75: 系統營收（Systems） | B75: US$B | C75: =a25_sys/1000 -> 0.5287 | D75: =a26_sys/1000 -> 1.0084 | E75: =w2h_26*C66+h_1h*D66 -> 2.4351835 | F75: =(1-h_1h)*D66+h_1h*E66 -> 3.4016377 | G75: =(1-h_1h)*E66+h_1h*F66 -> 4.0982396 | H75: 公司產品類別：Systems
A76: 檢查：元件＋系統 − 合併營收 | B76: US$B | C76: =C74+C75-C73 -> 0 | D76: =D74+D75-D73 -> 0 | E76: =E74+E75-E73 -> 0 | F76: =F74+F75-F73 -> 0 | G76: =G74+G75-G73 -> 0
A77: 營收年增 | B77: % | D77: =D73/C73-1 -> 0.83221884 | E77: =E73/D73-1 -> 1.1360753 | F77: =F73/E73-1 -> 0.35094549 | G77: =G73/F73-1 -> 0.1618321
A78: AI 相關 ÷ 營收 | B78: % | E78: =E71/E73 -> 0.81220059 | F78: =F71/F73 -> 0.84858396 | G78: =G71/G73 -> 0.8563544
A79: 毛利率（non-GAAP） | B79: % | C79: =a25_gm -> 0.347 | D79: =a26_gm -> 0.46 | E79: =gm_27 -> 0.52 | F79: =gm_28 -> 0.51 | G79: =gm_29 -> 0.49
A80: 毛利 | B80: US$B | C80: =C73*C79 -> 0.570815 | D80: =D73*D79 -> 1.38644 | E80: =E73*E79 -> 3.3478281 | F80: =F73*F79 -> 4.4357576 | G80: =G73*G79 -> 4.9515034
A81: 營業費用（基準路徑） | B81: US$B | C81: =a25_opx/1000 -> 0.4114 | D81: =a26_opx/1000 -> 0.4897 | E81: =D81*(1+MAX(0,phi*E77)) -> 0.61693223 | F81: =E81*(1+MAX(0,phi*F77)) -> 0.66644726 | G81: =F81*(1+MAX(0,phi*G77)) -> 0.69111279
A82: 營業費用（研發＋銷管） | B82: US$B | C82: =C81 -> 0.4114 | D82: =D81 -> 0.4897 | E82: =E81+0*E73 -> 0.61693223 | F82: =F81+0*F73 -> 0.66644726 | G82: =G81+0*G73 -> 0.69111279
A83: 營業利益 | B83: US$B | C83: =C80-C82 -> 0.159415 | D83: =D80-D82 -> 0.89674 | E83: =E80-E82 -> 2.7308959 | F83: =F80-F82 -> 3.7693104 | G83: =G80-G82 -> 4.2603906
A84: 營業利益率 | B84: % | C84: =C83/C73 -> 0.096908815 | D84: =D83/D73 -> 0.29752488 | E84: =E83/E73 -> 0.42417526 | F84: =F83/F73 -> 0.43337541 | G84: =G83/G73 -> 0.42160759
A85: 淨利（non-GAAP） | B85: US$B | C85: =a25_ni/1000 -> 0.1464 | D85: =a26_ni/1000 -> 0.7823 | E85: =(E83+oi_oth)*(1-tx) -> 2.323898 | F85: =(F83+oi_oth)*(1-tx) -> 3.1909741 | G85: =(G83+oi_oth)*(1-tx) -> 3.6010262
A86: 淨利率 | B86: % | C86: =C85/C73 -> 0.08899696 | D86: =D85/D73 -> 0.25955541 | E86: =E85/E73 -> 0.36095849 | F86: =F85/F73 -> 0.36688137 | G86: =G85/G73 -> 0.35635698
A87: 稀釋股數（non-GAAP） | B87: 百萬股 | C87: =a25_sh -> 71.067961 | D87: =a26_sh -> 90.230681 | E87: =sh_q1 -> 102 | F87: =E87*(1+sh_g) -> 103.02 | G87: =F87*(1+sh_g) -> 104.0502
A88: EPS（non-GAAP） | B88: US$ | C88: =C85*1000/C87 -> 2.06 | D88: =D85*1000/D87 -> 8.67 | E88: =E85*1000/E87 -> 22.783314 | F88: =F85*1000/F87 -> 30.974317 | G88: =G85*1000/G87 -> 34.608546
A89: EPS 年增 | B89: % | D89: =D88/C88-1 -> 3.2087379 | E89: =E88/D88-1 -> 1.6278332 | F89: =F88/E88-1 -> 0.35951762 | G89: =G88/F88-1 -> 0.11733041
A92: 案例區塊：雷射份額 高（情境 A）
A93: A. 日曆年產品營收（C 欄＝CY2026 錨點；D–F＝CY2027–CY2029）
A94: 項目 | B94: 單位 | C94: CY2026（錨點） | D94: CY2027 | E94: CY2028 | F94: CY2029 | H94: 說明
A95: AI 可插拔光模組市場 × 情境顆數係數 | B95: US$B | C95: =mpl_26*1 -> 29.753262 | D95: =mpl_27*1*1 -> 53.560715 | E95: =mpl_28*um28_A*1 -> 57.9915 | F95: =mpl_29*um29_A*1 -> 72.9348
A96: 光模組平均單價 | B96: $/個 | C96: =asp_26 -> 500 | D96: =asp_27 -> 520 | E96: =asp_28 -> 540 | F96: =asp_29 -> 560
A97: 高速光模組數量 ＝ 市場 ÷ 單價 | B97: 百萬個 | C97: =C95*1000/C96 -> 59.506524 | D97: =D95*1000/D96 -> 103.00137 | E97: =E95*1000/E96 -> 107.39167 | F97: =F95*1000/F96 -> 130.24071
A98: 每模組雷射數（EML／CW） | B98: 顆 | C98: =lpm_26 -> 5.5 | D98: =lpm_27 -> 5.5 | E98: =lpm_28 -> 5 | F98: =lpm_29 -> 4.8
A99: 雷射平均單價 | B99: $/顆 | C99: =lasp_26 -> 13 | D99: =lasp_27 -> 15 | E99: =lasp_28 -> 15 | F99: =lasp_29 -> 14
A100: 光模組雷射市場 ＝ 數量 × 每模組雷射數 × 單價 | B100: US$B | C100: =C97*C98*C99/1000 -> 4.2547165 | D100: =D97*D98*D99/1000 -> 8.4976134 | E100: =E97*E98*E99/1000 -> 8.054375 | F100: =F97*F98*F99/1000 -> 8.752176
A101: Lumentum 雷射有效份額（CY2026 校準）＝ 雷射晶片營收 ÷ 雷射市場 | B101: % | C101: =c26_las/1000/C100 -> 0.43826657 | H101: Derived：雷射晶片營收為 CY2026 錨點殘差
A102: 雷射份額相對值（÷ CY2026） | B102: x | C102: =1 -> 1 | D102: =LRHI_27 -> 1 | E102: =LRHI_28 -> 1.05 | F102: =LRHI_29 -> 1.05
A103: 雷射有效份額 | B103: % | C103: =$C$101*C102 -> 0.43826657 | D103: =$C$101*D102 -> 0.43826657 | E103: =$C$101*E102 -> 0.4601799 | F103: =$C$101*F102 -> 0.4601799
A104: 雷射晶片營收（EML／CW） | B104: US$B | C104: =C100*C103 -> 1.8647 | D104: =D100*D103 -> 3.7242199 | E104: =E100*E103 -> 3.7064615 | F104: =F100*F103 -> 4.0275755
A105: 光模組份額（CY2026 校準）＝ 光模組營收 ÷ 可插拔市場 | B105: % | C105: =c26_xcvr/1000/C95 -> 0.03360976
A106: 光模組份額 | B106: % | C106: =C105 -> 0.03360976 | D106: =$C$105*mrel_27 -> 0.03360976 | E106: =$C$105*mrel_28 -> 0.03360976 | F106: =$C$105*mrel_29 -> 0.03360976
A107: 光模組營收 | B107: US$B | C107: =C95*C106 -> 1 | D107: =D95*D106 -> 1.8001628 | E107: =E95*E106 -> 1.9490804 | F107: =F95*F106 -> 2.4513211
A108: Google TPU 顆數 × 情境顆數係數 | B108: 百萬顆 | C108: =tpu_26*1 -> 3.85 | D108: =tpu_27*1 -> 5.5 | E108: =tpu_28*um28_A -> 7 | F108: =tpu_29*um29_A -> 8.05
...

Sheet Sources
A1: 來源（公司原文＝SEC 8-K 新聞稿、10-K、法說簡報；法說內容經第三方轉述者待人工複核）
A2: 公司：FY2026 第四季與全年新聞稿（SEC 8-K EX-99.1） | B2: https://www.sec.gov/Archives/edgar/data/0001633978/000162828026055726/lite_ex991xq4fy26.htm
A3: 公司：FY2026 第四季法說簡報 | B3: https://s21.q4cdn.com/377324469/files/doc_financials/2026/q4/Q4-FY26-Earnings-Presentation_final.pdf
A4: 公司：FY2026 10-K（部門定義、客戶集中度、股數） | B4: https://www.sec.gov/Archives/edgar/data/0001633978/000162828026057358/lite-20260627.htm
A5: 公司：歷年新聞稿（FY2016–FY2024 non-GAAP EPS；SEC 8-K） | B5: https://www.sec.gov/Archives/edgar/data/1633978/000162828024037191/lite_ex991xq4fy24.htm；…/000162828022022980/lite_ex991xq4fy22.htm；…/000162828021017219/lite_ex991xq4fy21.htm；…/000163397819000068/lite_ex991xq4fy19.htm；…/000163397818000056/lite_ex991xq4fy18.htm；…/000163397817000058/lite_ex991xq4fy17.htm
A6: 二手：法說重點（MarketBeat、Zacks、Crux Capital、PhotonCap、vocus） | B6: https://www.marketbeat.com/instant-alerts/lumentum-q4-earnings-call-highlights-2026-08-11/；https://www.zacks.com/stock/news/2973530/lumentum-q4-earnings-call-focuses-on-ai-optics-ocs-npo-ramps；https://cruxcapitalgroup.substack.com/p/lite-earnings-breakdown；https://photoncap.net/p/the-8-companies-behind-lumentums
A7: 券商：凱基 2026-08-18 光通訊產業報告（OCS、超高功率雷射、800G／1.6T 出貨、歷史 P/E） | B7: https://www.kgi.com.hk/en/-/media/files/kgishk/research-reports/us-daily/optical-networking-industry_20260818_tc.pdf
A8: 研調：TrendForce 2026-06-03（EML、CW 產能與份額） | B8: https://www.trendforce.com/presscenter/news/20260603-13077.html
A9: 券商：愛建證券 10-12 通信行業報告（光模組成本結構） | B9: https://pdf.dfcfw.com/pdf/H3_AP202610121830372080_1.pdf
A10: 共識：stockanalysis（2026-10-21）、tickflow（2026-10-24）、trefis（2026-10-08） | B10: https://stockanalysis.com/stocks/lite/forecast/；https://www.tickflow.io/stock/LITE/forecast；https://www.trefis.com/stock/lite/articles/617928/what-is-the-true-hidden-price-of-lumentum-stock/2026-10-08
A11: 價格：vcpscanner（10-23）、investsmart（年內高低點）、digrin（年底股價） | B11: https://www.vcpscanner.com/valuation/lite/estimates；https://www.investsmart.com.au/security/nasdaq/lite/lumentum-holdings/share-price；https://www.digrin.com/stocks/detail/LITE/price
A12: 資料商：companiesmarketcap GAAP 年底 P/E | B12: https://companiesmarketcap.com/lumentum/pe-ratio/
A13: 市場層：markets/network、tsmc 成品（本 repo，唯讀）
A14: 待補（人工）：FY2027 第一季財報（約 11-05）；產品別營收（雷射、光模組、OCS）；Lumentum 個別 EML／CW 份額；雷射單價；FY2028 共識第二來源；52 週高點；FY2018 non-GAAP EPS 複核 | B14: 未找到
A15: SemiAnalysis | B15: 未使用
