Workbook

Sheet README
A1: SpaceX（Nasdaq: SPCX，含 xAI）個股模型 v0.1（2026-10-30；2026Q3）— 命題模組＋官方營收分部 → 損益表
A3: 命題：SI 分部的算力投入（9M26 SI 資本支出約 400 億美元、名目算力 1.7 GW）能否由 SI 營收（對外算力出租＋Grok／Cursor／X）回本；Connectivity（Starlink）現金流與 IPO 資金能支撐多久；加計 AI 折舊與 Cursor 收購獎酬後的每股價值是否高於現價。
A4: 核心問題：FY2028 SI 每 GW 年營收 ÷ Tokenomics 每 GW 年持有成本（與 OpenAI PxQ 頁同口徑）；收支關卡＝FY2026–FY2030 自由現金流合計（扣融資租賃、失敗售後租回本金與以融資取得 PP&E）。
A5: ="投資建議："&Val!B14&"（加權目標價 US$"&TEXT(Val!B8,"0.00")&"，上檔空間 "&TEXT(Val!B11,"+0.0%;-0.0%")&"；現價 "&TEXT(px,"0.00")&"，2026-10-29 收盤）" -> 投資建議：強力放空（加權目標價 US$27.52，上檔空間 -80.9%；現價 143.89，2026-10-29 收盤）
A6: ="重點觀察 1：目標價 "&TEXT(Val!B8,"0.0")&"＝DCF "&TEXT(Val!B6,"0.0")&"、分部加總 "&TEXT(Val!B7,"0.0")&" 各半；情境 A／B／C 為 "&TEXT(Val!B17,"0.0")&"／"&TEXT(Val!C17,"0.0")&"／"&TEXT(Val!D17,"0.0")&"；市場共識目標價 "&TEXT(cons_tp,"0")&"，現價隱含 NTM EV/EBITDA "&TEXT(Val!B149,"0")&" 倍。" -> 重點觀察 1：目標價 27.5＝DCF 20.7、分部加總 34.4 各半；情境 A／B／C 為 39.1／26.7／17.6；市場共識目標價 245，現價隱含 NTM EV/EBITDA 26 倍。
A7: ="重點觀察 2：S2 核心問題比值（FY2028 SI 每 GW 年營收 ÷ Tokenomics 持有成本）A／B／C＝"&TEXT(Val!B24,"0.00")&"／"&TEXT(Val!C24,"0.00")&"／"&TEXT(Val!D24,"0.00")&"（2026Q3 校準 "&TEXT(k0,"0.00")&"）；SI 名目算力 FY2028 年底 "&TEXT(Thesis!I25,"0.0")&" GW，FY2027 SI 投資 "&TEXT(Thesis!H43,"0")&"。" -> 重點觀察 2：S2 核心問題比值（FY2028 SI 每 GW 年營收 ÷ Tokenomics 持有成本）A／B／C＝1.73／1.56／1.43（2026Q3 校準 1.87）；SI 名目算力 FY2028 年底 5.4 GW，FY2027 SI 投資 75。
A8: ="重點觀察 3：收支關卡（FY2026–2030 自由現金流，收支關卡口徑）B "&TEXT(CF!C6,"0.0")&"（公司口徑 "&TEXT(CF!C7,"0.0")&"），"&CF!C10&"；情境 B 合併營業利益率 FY2028 "&TEXT(PL!I120,"0.0%")&"（新增 AI 折舊 "&TEXT(PL!I106,"0.0")&"）。" -> 重點觀察 3：收支關卡（FY2026–2030 自由現金流，收支關卡口徑）B -96.9（公司口徑 -53.7），需要舉債；情境 B 合併營業利益率 FY2028 20.0%（新增 AI 折舊 18.5）。
A10: 驅動 → 推導對照表（每頁輸入、推導量、因果方向）
A11: 頁 | B11: 輸入（In 頁鍵） | C11: 推導量 | D11: 因果方向
A12: Thesis | B12: gw_0、si_cx_rr → pace、ext_sh、mix0_*、selfb、Tokenomics IF_HoldEcon／OpexGW／CapexIT／Facility | C12: SI 名目算力、對外／自用 GW、SI 投資、AI 折舊、自用增量成本、影子效益 | D12: SI 投資 ÷ 每 GW 投資 → GW；GW → 投資 → 折舊 → SI 營業利益
A13: Seg | B13: k30_A／B／C、conv_k、g27_nr、gl_nr、gl_ads、nl_*、g_rpl、gl_ld、nadd_A／B／C、g_arpu、gl_eg | C13: 三分部、六條子列、兩條 SI 命題子列、合併營收；非 AI 資本支出 | D13: 對外 GW × k × 持有成本；發射 × 每次收入；訂戶 × ARPU
A14: PL | B14: m_spl、m_cn、m_so、sbc_*、sbc_cur_left、da_*、tax | C14: 分部調整後 EBITDA、分部營業利益、合併營業利益、淨利、EPS | D14: 分部營收 → EBITDA − 折舊 − 股權報酬 → 營業利益 → EPS
A15: CF | B15: wc_k、cx_cn、cx_spl、fin_sh、mat_*、lease_*、spec_*、min_cash | C15: 公司口徑 FCF、收支關卡口徑 FCF、新債、淨現金 | D15: 淨利＋折舊＋SBC − 資本支出 → FCF → 舉債
A16: Val | B16: rf、beta、erp、kd、g_tv、ronic、同業倍數、evs_space、tp_w*、w_dcf | C16: DCF、分部加總、目標價、上檔空間、投資建議 | D16: 無槓桿 FCF 折現＋分部 EBITDA × 倍數 → 情境加權 → 50／50
A17: Sens | B17: In 頁敏感度低／高值 | C17: 加權目標價變動 | D17: 一次改一個輸入、整本重算
A19: 本版要點（v0.1：首版）
A20: 官方分部 Space、Connectivity、SI；子列＝10-Q 附註 3 收入拆分；SI S&I 之下以 Customer B 衍生 72% 拆「對外雲端服務」與「Grok／Cursor／X」命題子列（審查第 4 條）。
A21: SI 名目算力以實際值為錨（2025Q2 0.4 → 2026Q3 1.7 GW，IT 口徑），未來路徑由 SI 投資季速（含以融資取得 PP&E）÷ Tokenomics 每 GW 投資推算（審查第 3 條）。
A22: 收支關卡口徑扣融資租賃本金、Valor 失敗售後租回本金與以融資取得 PP&E，並列公司口徑 FCF（審查第 2 條）。
A23: 歷史欄：Q 頁 2025Q2–2026Q3 與 9M；FY2025* 為二手轉述 S-1（Space 資本支出未取得）。Cursor 2026-08-14 併入，預測以備考全季為起點（審查第 8 條）。
A24: Tesla 合併評估（董事會特別委員會）不建模，列事件風險；EchoStar 頻譜按成本（價值中性），交割發行股數列 Sens。
A26: 工作表：README → In → Q → Thesis → Seg → PL → CF → Val → Recon → Sens → Sources。藍字＝輸入、黑字＝公式；黃底＝判斷題。建置：bash spacex/make_v01.sh
A27: 數字標記：Verified（經查核）／Interested-party（公司或賣方自述）／Analogy／Assumed（給區間）／Derived（換算）／二手轉述 S-1。本模型是研究整理，不構成投資建議。

Sheet In
A1: In — 輸入（藍字；基準欄 E 進主模型；D／F＝敏感度低／高，只用於 Sens 頁、不進目標價；情境 A／B／C 的驅動見本頁最後一節「情境驅動對照」）。金額 US$B；每股 US$；股數十億股；GW＝IT 口徑名目算力（不乘 PUE）。標記：Verified／Interested-party／Analogy／Assumed／Derived（Analogy、Assumed 一律給低／高區間）
A2: 事實來源：spacex/data/spacex_facts_2026q3.json（10-Q 2026Q3 與 Q3／Q2 財報新聞稿兩讀核對；FY2025 為媒體轉述 S-1，標「二手轉述 S-1」）；Tokenomics v21.7 快照 spacex/data/tokenomics_snapshot_v21.7.json。黃底＝判斷題（Andy 可改；報告「待 Project 判斷」逐條列出預設）
A3: 鍵 | B3: 項目 | C3: 單位 | D3: 敏感度低 | E3: 基準 | F3: 敏感度高 | G3: 標記 | H3: 來源 | I3: 說明
A4: A. 現價、股數與資產負債（評價日 2026-09-30；10-Q 2026Q3）
A5: px | B5: 現價（2026-10-29 收盤） | C5: US$ | E5: 143.89 | G5: Verified | H5: MarketBeat SPCX 預測頁 https://www.marketbeat.com/stocks/NASDAQ/SPCX/forecast/（4:00 PM 收盤 143.89）；Equibles https://equibles.com/stocks/spcx/summary（10-29 收盤 143.89、跌 1.34；2026-10-30 讀取） | I5: 兩來源一致（審查第 7 條）；Digrin 月線 10 月 143.89 亦同。A 段候選 Robinhood 140.40 為盤中價，不採
A6: px_val | B6: 評價日股價（2026-09-30 收盤；WACC 權益權重用） | C6: US$ | E6: 150.86 | G6: Derived | H6: Digrin SPCX 月線 https://www.digrin.com/stocks/detail/SPCX/price（2026 年 9 月收盤 150.86；2026-10-30 讀取） | I6: 單一來源（第二來源未取得：StockAnalysis 歷史頁逾時）；只影響 WACC 權重，負債占比 < 2%，對目標價影響極小
A7: sh_out | B7: 流通股數（10-Q 封面 2026-10-15，A＋B 股） | C7: 十億股 | E7: 13.581064 | G7: Verified | H7: mag/extract/docs/2026Q3/spacex_2026Q3_10-Q.pdf 第 2 頁 10-Q 封面（2026-10-22；事實總帳 sh.out.AB.20261015；Derived） | I7: A 8,246.5M＋B 5,334.5M（審查第 6 條；稀釋項列 Sens，不進基準）
A8: sh_dil_9m | B8: 9M26 稀釋加權股數 | C8: 十億股 | E8: 7.274 | G8: Verified | H8: mag/extract/docs/2026Q3/spacex_2026Q3_10-Q.pdf 第 6 頁 合併損益表（2026-10-22；事實總帳 is.shDil.9m2026；Verified） | I8: IPO 在 2026-06，加權股數低於期末
A9: dil_perf | B9: 潛在稀釋：績效／市場條件獎酬（未計入稀釋股數） | C9: 十億股 | E9: 1.333 | G9: Verified | H9: mag/extract/docs/2026Q3/spacex_2026Q3_10-Q.pdf 第 31 頁 附註 13（2026-10-22；事實總帳 sh.perfAwards.20260930；Verified） | I9: 受獎人未見原文；Sens 用
A10: dil_opt | B10: 潛在稀釋：選擇權 | C10: 十億股 | E10: 0.508 | G10: Verified | H10: mag/extract/docs/2026Q3/spacex_2026Q3_10-Q.pdf 第 30 頁 附註 12 保留股數表（2026-10-22；事實總帳 sh.options.20260930；Verified） | I10: Sens 用
A11: dil_rsu | B11: 潛在稀釋：RSU | C11: 十億股 | E11: 0.142 | G11: Verified | H11: mag/extract/docs/2026Q3/spacex_2026Q3_10-Q.pdf 第 30 頁 附註 12（2026-10-22；事實總帳 sh.rsu.20260930；Verified） | I11: Sens 用
A12: dil_echo | B12: 潛在稀釋：EchoStar 頻譜交割發行 A 股（約） | C12: 十億股 | E12: 0.2618 | G12: Verified | H12: mag/extract/docs/2026Q3/spacex_2026Q3_10-Q.pdf 第 58 頁 MD&A Material Cash Commitments — Spectrum Transaction（2026-10-22；事實總帳 spectrum.echostar.shares；Verified） | I12: 固定每股 42.40；預計 2027-11-30 交割；Sens 用
A13: dil_x | B13: 評價股數加入上述潛在稀釋（1＝是；Sens 用） | C13: x | E13: 0 | F13: 1 | G13: Assumed | H13: 審查第 6 條：稀釋項列 Sens，不進基準 | I13: 高＝四項全部加入（約 2.24B 股，＋16.5%）
A14: cash_0 | B14: 現金＋有價證券（2026-09-30） | C14: US$B | E14: 89.855 | G14: Verified | H14: 10-Q 資產負債表：現金 51.294＋有價證券 38.561（事實總帳 bs.cash.20260930、bs.mktSec.20260930） | I14: 6-30 為 100.009
A15: cash_ye25 | B15: 現金＋有價證券（2025-12-31） | C15: US$B | E15: 24.747 | G15: Verified | H15: 10-Q 資產負債表比較欄（事實總帳 bs.cash.20251231、bs.mktSec.20251231）
A16: debt_0 | B16: 債務本金（2026-09-30；含失敗售後租回 12.897） | C16: US$B | E16: 38.006 | G16: Verified | H16: mag/extract/docs/2026Q3/spacex_2026Q3_10-Q.pdf 第 20 頁 附註 9 Debt 表（2026-10-22；事實總帳 debt.totalDebt.principal.20260930；Verified） | I16: SpaceX Notes 25.000＋其他融資 12.979（其中 Valor 失敗售後租回 12.897）＋X 票據 0.027
A17: debt_ye25 | B17: 債務本金（2025-12-31） | C17: US$B | E17: 22.049 | G17: Verified | H17: mag/extract/docs/2026Q3/spacex_2026Q3_10-Q.pdf 第 20 頁 附註 9 Debt 表（2025-12-31）（2026-10-22；事實總帳 debt.totalDebt.principal.20251231；Verified）
A18: slb_0 | B18: 其中：Valor 失敗售後租回債務（2026-09-30） | C18: US$B | E18: 12.897 | G18: Verified | H18: 10-Q 附註 9、附註 17：直接寫明為 Valor Transactions（失敗售後租回；審查第 1 條），流動 2.181＋非流動 10.716 | I18: 關係人（董事 Antonio Gracias）；利息 2026Q3 0.351
A19: fin_lease | B19: 融資租賃負債（2026-09-30） | C19: US$B | E19: 0.983 | G19: Verified | H19: mag/extract/docs/2026Q3/spacex_2026Q3_10-Q.pdf 第 20 頁 附註 9 Debt 表（2026-10-22；事實總帳 debt.finLease.principal.20260930；Verified） | I19: 計入 WACC 負債與淨負債
A20: btc | B20: 數位資產（比特幣 18,712 枚，2026-09-30 帳面） | C20: US$B | E20: 1.573 | G20: Verified | H20: mag/extract/docs/2026Q3/spacex_2026Q3_10-Q.pdf 第 5 頁 合併資產負債表（2026-10-22；事實總帳 bs.digital.20260930；Verified） | I20: 評價時加入（類現金持有）
A21: legal | B21: 訴訟準備（類債） | C21: US$B | E21: 0.35 | G21: Verified | H21: mag/extract/docs/2026Q3/spacex_2026Q3_10-Q.pdf 第 35 頁 10-Q 附註（2026-10-22；事實總帳 legal.accrual；Verified）
A22: B. 折現率與目標價規則
A23: rf | B23: 無風險利率（10 年美債，2026-10-27） | C23: % | E23: 0.0499 | G23: Verified | H23: 美國財政部每日殖利率曲線 10 Yr https://home.treasury.gov/resource-center/data-chart-center/interest-rates/TextView?type=daily_treasury_yield_curve&field_tdr_date_value_month=202610（Alphabet v0.3.2 同值，2026-10-29 讀取）
A24: beta | B24: β（2026-06 上市，歷史不足；判斷） | C24: x | D24: 1.1 | E24: 1.3 | F24: 1.6 | G24: Assumed | H24: 判斷：上市僅約 4 個月，無 3–5 年月資料 β；以高成長、高資本支出的大型科技股區間 1.1–1.6 取 1.3（Alphabet Blume 調整後 1.19 為下緣對照） | I24: Sens：1.1／1.6
A25: erp | B25: 股權風險溢酬 | C25: % | D25: 0.04 | E25: 0.05 | F25: 0.06 | G25: Assumed | H25: 同 Alphabet v0.3.2（S9）
A26: kd | B26: 稅前債務成本（SpaceX Notes 有效利率） | C26: % | E26: 0.06072 | G26: Verified | H26: mag/extract/docs/2026Q3/spacex_2026Q3_10-Q.pdf 第 21 頁 附註 9（2026-10-22；事實總帳 debt.spacexNotes.eir；Verified） | I26: 五批加權票面 5.855%；有效 6.072%
A27: tax_w | B27: WACC 用稅率（美國聯邦法定） | C27: % | E27: 0.21 | G27: Assumed | H27: 淨營業虧損抵減期間實際稅盾低於法定；負債占比 < 2%，影響極小
A28: wacc_adj | B28: WACC 調整（Sens 格：±1pt） | C28: % | D28: -0.01 | E28: 0 | F28: 0.01 | G28: Assumed | H28: Sens 用
A29: g_tv | B29: 永續成長率（FY2032 後） | C29: % | D29: 0.02 | E29: 0.03 | F29: 0.04 | G29: Assumed | H29: 同 Alphabet v0.3.2（S9）
A30: ronic_sp | B30: 永續期新投資報酬率 RONIC 相對 WACC 的差 | C30: % | E30: 0 | F30: 0.05 | G30: Assumed | H30: 同 Alphabet v0.3.2：RONIC＝WACC；終值＝NOPAT(FY2033) ×(1 − g ÷ RONIC) ÷ (WACC − g) | I30: Sens：WACC＋5pt
A31: mid | B31: 期中慣例：年度現金流距年初 | C31: 年 | E31: 0.5 | G31: Derived | H31: 年度現金流平均發生在年中
A32: t_val | B32: 評價日（2026-09-30）的年份小數 | C32: 年 | E32: 2026.75 | G32: Derived | H32: 年度折現年數＝年度＋mid − t_val
A33: t_q4 | B33: Q4 26 現金流折現年數（期中） | C33: 年 | E33: 0.125 | G33: Derived | H33: 2026-10-01～12-31 的中點
A34: tp_wA | B34: 情境權重 A | C34: % | E34: 0.25 | G34: Assumed | H34: 工作單 S9（同 Alphabet：A 25%／B 50%／C 25%）
A35: tp_wB | B35: 情境權重 B | C35: % | E35: 0.5 | G35: Assumed | H35: 同上
A36: tp_wC | B36: 情境權重 C | C36: % | E36: 0.25 | G36: Assumed | H36: 同上
A37: w_dcf | B37: 目標價中 DCF 的權重（其餘＝分部加總 SOTP） | C37: % | D37: 0.3 | E37: 0.5 | F37: 0.7 | G37: Assumed | H37: 工作單 S9（DCF 50%＋分部加總 50%）
A38: t_tgt | B38: 目標時點距評價日（2026-09-30 → 2027-10-30） | C38: 年 | E38: 1.0822 | G38: Derived | H38: 395 天 ÷ 365（工作單 S9：目標價時點 2027-10-30）
A39: w_ntm27 | B39: 目標時點 NTM 中 FY2027 的權重 | C39: % | E39: 0.1699 | G39: Derived | H39: (2027-12-31 − 2027-10-30) ÷ 365＝62 天；FY2028 權重＝1 − 本值
A40: cons_tp | B40: 市場共識目標價（平均） | C40: US$ | D40: 75 | E40: 244.97 | F40: 800 | G40: Interested-party | H40: MarketBeat 預測頁 https://www.marketbeat.com/stocks/NASDAQ/SPCX/forecast/（含 2026-10-26 Bernstein 動作，頁面約 2026-10-27～29；46 位分析師；data/consensus_spcx_20261030.json） | I40: 賣方多有承銷關係，只作對照；低／高＝最低／最高目標價（只作對照，不進模型）
A41: internal_ai_reading | B41: 自用 AI 讀法（2＝主值：自用 AI 價值中性，計影子效益；1＝敏感度：只計成本） | C41: x | D41: 1 | E41: 2 | G41: Assumed | H41: 原則第 7 節（Andy 2026-10-27 15:03 定案讀法 2）；工作單 S5：SI 自用 GW（＝在役 GW ×(1 − 對外出租占比)）評價日後新增者 × Tokenomics IF_HoldEcon（k＝1） | I41: 營收列與分部對帳不動；Val 頁兩種讀法的目標價並列
A42: sbc_add | B42: DCF 加回股權報酬（1＝是；Sens 用） | C42: x | E42: 0 | F42: 1 | G42: Assumed | H42: 同 Alphabet：股權報酬視為真實成本、不加回（含 Cursor 收購後服務期獎酬）
A43: tv_alt | B43: 終值改用 FY2032 無槓桿自由現金流 ×(1＋g)（1＝是；Sens 用） | C43: x | E43: 0 | F43: 1 | G43: Assumed | H43: 同 Alphabet
A44: C. 分部加總（SOTP）倍數（目標時點 NTM EBITDA × 同業 EV/EBITDA；Space 用 EV／營收；SI 對外出租用自身 DCF）
A45: pm_conn_irdm | B45: Connectivity 同業：Iridium Communications（IRDM）EV/EBITDA FY2026 | C45: x | E45: 13.39 | G45: Derived | H45: MarketScreener 產業估值表 https://it.marketscreener.com/quotazioni/azione/IRIDIUM-COMMUNICATIONS-IN-5602836/settore-valutazione/（2026-10-08；data/peers_connectivity_20261030.json）
A46: pm_conn_tmus | B46: Connectivity 同業：T-Mobile US（TMUS）EV/EBITDA FY2026 | C46: x | E46: 7.13 | G46: Derived | H46: MarketScreener 產業估值表 https://it.marketscreener.com/quotazioni/azione/IRIDIUM-COMMUNICATIONS-IN-5602836/settore-valutazione/（2026-10-08；data/peers_connectivity_20261030.json）
A47: pm_conn_t | B47: Connectivity 同業：AT&T（T）EV/EBITDA FY2026 | C47: x | E47: 6.57 | G47: Derived | H47: MarketScreener 產業估值表 https://it.marketscreener.com/quotazioni/azione/IRIDIUM-COMMUNICATIONS-IN-5602836/settore-valutazione/（2026-10-08；data/peers_connectivity_20261030.json）
A48: pm_conn_cmcsa | B48: Connectivity 同業：Comcast（CMCSA）EV/EBITDA FY2026 | C48: x | E48: 4.71 | G48: Derived | H48: MarketScreener 產業估值表 https://it.marketscreener.com/quotazioni/azione/IRIDIUM-COMMUNICATIONS-IN-5602836/settore-valutazione/（2026-10-08；data/peers_connectivity_20261030.json）
A49: pm_conn_sats | B49: Connectivity 同業：EchoStar（SATS）EV/EBITDA FY2026 | C49: x | E49: 16.66 | G49: Derived | H49: MarketScreener 產業估值表 https://it.marketscreener.com/quotazioni/azione/IRIDIUM-COMMUNICATIONS-IN-5602836/settore-valutazione/（2026-10-08；data/peers_connectivity_20261030.json） | I49: EchoStar 正處分頻譜（含售予 SpaceX），倍數受交易影響
A50: pm_si_crwv | B50: SI 同業（AI 基礎設施／雲）：CoreWeave（CRWV）EV/EBITDA FY2027 | C50: x | E50: 6.23 | G50: Derived | H50: MarketScreener 估值頁（2026-10-23（收盤 54.24）；data/peers_si_20261030.json）
A51: pm_si_nbis | B51: SI 同業（AI 基礎設施／雲）：Nebius Group（NBIS）EV/EBITDA FY2027 | C51: x | E51: 11.9 | G51: Derived | H51: MarketScreener 估值頁（2026-10-23（收盤 158.74）；data/peers_si_20261030.json） | I51: 2026 EBITDA 剛轉正，FY2026 倍數偏高
A52: pm_si_orcl | B52: SI 同業（AI 基礎設施／雲）：Oracle（ORCL）NTM EV/EBITDA | C52: x | E52: 9.49 | G52: Derived | H52: 複製 alphabet/data/peers_cloud_20261008.json（2026-10-07；data/peers_si_20261030.json） | I52: 財年 5 月；口徑為 NTM，與上兩家 FY 口徑不同
A53: mult_si_adj | B53: SI 其他（Grok／Cursor／X 與廣告）倍數＝SI 同業中位數 × 本係數 | C53: x | D53: 0.7 | E53: 1 | F53: 1.4 | G53: Assumed | H53: 審查第 6 條：同業樣本小（3 家、口徑不一），以中位數為基準、±30–40% 為區間 | I53: 上市 AI 平台（模型商）無可比公司（未找到）
A54: evs_space | B54: Space EV／NTM 營收 | C54: x | D54: 2 | E54: 3 | F54: 6 | G54: Assumed | H54: 工作單 S9：Space 無直接上市同業；Space 分部調整後 EBITDA 9M26 為負（Starship 開發），EBITDA 倍數不適用，改用 EV／營收（判斷） | I54: 對照：Rocket Lab 等小型發射商 EV／營收約 10× 以上，但規模與獲利不可比（本次未重新查核）
A55: D. 命題模組：SI 名目算力（GW，IT 口徑）與資本支出（審查第 3 條）
A56: gw_0 | B56: SI 名目算力（2026-09-30） | C56: GW | E56: 1.7 | G56: Interested-party | H56: mag/extract/docs/2026Q3/spacex_2026Q3_新聞稿.pdf 第 6 頁 SI 分部頁（2026-10-20；事實總帳 seg.si.kpi.gw.2026q3；Interested-party） | I56: 10-Q 定義：安裝 GPU × all-in power，不含冷卻與設施負載（IT 口徑）；含對外出租、推定不含第三方雲（S6）
A57: gw_q2 | B57: SI 名目算力（2026-06-30） | C57: GW | E57: 1.4 | G57: Interested-party | H57: mag/extract/docs/2026Q3/spacex_2026Q3_新聞稿.pdf 第 6 頁 SI 分部頁（2026-10-20；事實總帳 seg.si.kpi.gw.2026q2；Interested-party）
A58: gw_ye25 | B58: SI 名目算力（2025-12-31，內插） | C58: GW | D58: 0.7 | E58: 0.8 | F58: 0.9 | G58: Derived | H58: 2025Q3 0.6 與 2026Q1 1.0 線性內插（年底值未揭露） | I58: 汰換時點用
A59: gw_ye24 | B59: SI 名目算力（2024-12-31；汰換用） | C59: GW | D59: 0.1 | E59: 0.15 | F59: 0.25 | G59: Assumed | H59: 判斷：Colossus 1 首批約 10 萬顆 H100（2024-09 上線，公司與媒體自述）≈ 0.15 GW IT；2025Q2 為 0.4 | I59: 未找到：2024 年底名目算力
A60: ext_sh | B60: 對外出租占比（SI S&I 營收與在役 GW 同比例；Customer B 衍生） | C60: % | D60: 0.6 | E60: 0.72 | F60: 0.85 | G60: Derived | H60: 審查第 4 條：Customer B 2026Q3 占合併營收 34.5%（全屬 SI）→ 5.028 ÷ SI S&I 7.022＝71.6%（事實總帳 cust.B.rev.2026q3）；2026Q2 1.526 ÷ 2.194＝69.6% | I60: 區間 0.6–0.85（審查第 4 條）；客戶 B 是否全為雲端服務屬推論；自用 GW＝在役 GW ×(1 − 本值)
A61: mix0_h | B61: 評價日機隊：Hopper 錨（Colossus 1 H100／H200） | C61: % | E61: 0.3 | G61: Assumed | H61: 判斷：Colossus 1 約 20 萬顆 Hopper（公司自述，二手）≈ 0.3–0.4 GW | I61: 影響每 GW 持有成本的加權（k0 校準分母）
A62: mix0_b2 | B62: 評價日機隊：GB200 錨 | C62: % | E62: 0.4 | G62: Assumed | H62: 判斷：Colossus 2 首批 GB200（2025H2–2026H1）
A63: mix0_b3 | B63: 評價日機隊：GB300 錨 | C63: % | E63: 0.3 | G63: Assumed | H63: 判斷：Colossus 2 2026 年擴建（Q3 新聞稿：continued the buildout of COLOSSUS II）
A64: am_27 | B64: 2027 新增中 GB300 錨占比（其餘 VR200 錨） | C64: % | E64: 0.5 | G64: Assumed | H64: 同 Alphabet（2026 新增全為 GB300 錨；2028 起全為 VR200 錨）
A65: selfb | B65: 自建機房比例（不計機房資本支出的比例＝租用） | C65: % | D65: 0.75 | E65: 0.9 | F65: 1 | G65: Assumed | H65: 判斷：Colossus 1／2 為自建（Memphis）；PP&E 資料中心基礎設施 6.333 偏低，可能部分租用
A66: si_cx_rr | B66: SI 投資季速（2026Q3 SI 資本支出＋以其他融資取得 PP&E 季均） | C66: US$B/季 | E66: 17.751 | G66: Derived | H66: 10-Q 附註 18：2026Q3 SI 資本支出 16.444＋以其他融資取得 PP&E 9M 3.921 ÷ 3（審查第 3 條：含以融資取得之 PP&E） | I66: 以融資取得之 PP&E 未分分部，推定全屬 SI
A67: pace | B67: SI 名目算力每年新增（FY2027–FY2028；三情境相同） | C67: GW/年 | D67: 1.0847 | E67: =4*si_cx_rr/(cit_b3+selfb*cfac) -> 1.6270311 | F67: 2.4405 | G67: Derived | H67: 審查第 3 條：SI 投資季速 × 4 ÷ Tokenomics 每 GW 資本支出（GB300 錨 IT＋自建 × 機房） | I67: 基準約 1.627；Q4 26 新增＝本值 × 0.25（年底約 2.1 GW，公司 Q2 法說稱逾 2 GW，Recon 對照）；低／高＝× 2/3／× 1.5
A68: conv_mw | B68: FY2029 起新增速度收斂年數（到 FY2032 只剩 g × 期初 GW） | C68: 年 | E68: 4 | G68: Assumed | H68: 同 Alphabet 修正一 F5：終值不得落在建置高峰
A69: fin_sh | B69: SI 投資中以其他融資取得（非現金）比例 | C69: % | E69: 0.0893 | G69: Derived | H69: 9M26：3.921 ÷ (SI 資本支出 39.995＋3.921) | I69: 預測期 SI 投資按本比例拆現金資本支出與融資取得；收支關卡兩者都扣（審查第 2 條）
A70: he_h | B70: IF_HoldEcon｜H100（每 MW 年持有成本，經濟口徑） | C70: US$m/MW-年 | D70: 6.7910747 | E70: 9.7030873 | F70: 16.66377 | G70: Derived | H70: data/tokenomics_snapshot_v21.7.json（20261025_Tokenomics_v21.7.xlsx，Interface!C13:Q13） | I70: Tokenomics WACC 10% 下的打平持有成本；＝US$B/GW-年
A71: he_b2 | B71: IF_HoldEcon｜GB200（每 MW 年持有成本，經濟口徑） | C71: US$m/MW-年 | D71: 6.6118163 | E71: 8.8281656 | F71: 14.318575 | G71: Derived | H71: data/tokenomics_snapshot_v21.7.json（20261025_Tokenomics_v21.7.xlsx，Interface!C13:Q13） | I71: Tokenomics WACC 10% 下的打平持有成本；＝US$B/GW-年
A72: he_b3 | B72: IF_HoldEcon｜GB300（每 MW 年持有成本，經濟口徑） | C72: US$m/MW-年 | D72: 8.4288991 | E72: 10.886411 | F72: 18.534646 | G72: Derived | H72: data/tokenomics_snapshot_v21.7.json（20261025_Tokenomics_v21.7.xlsx，Interface!C13:Q13） | I72: Tokenomics WACC 10% 下的打平持有成本；＝US$B/GW-年
A73: he_vr | B73: IF_HoldEcon｜VR200（每 MW 年持有成本，經濟口徑） | C73: US$m/MW-年 | D73: 9.2190715 | E73: 12.225471 | F73: 19.750627 | G73: Derived | H73: data/tokenomics_snapshot_v21.7.json（20261025_Tokenomics_v21.7.xlsx，Interface!C13:Q13） | I73: Tokenomics WACC 10% 下的打平持有成本；＝US$B/GW-年
A74: opx_h | B74: IF_OpexGW｜H100（每 MW 年營運費用，不含折舊） | C74: US$m/MW-年 | E74: 1.8846675 | G74: Derived | H74: data/tokenomics_snapshot_v21.7.json
A75: opx_b2 | B75: IF_OpexGW｜GB200（每 MW 年營運費用，不含折舊） | C75: US$m/MW-年 | E75: 1.8122327 | G75: Derived | H75: data/tokenomics_snapshot_v21.7.json
A76: opx_b3 | B76: IF_OpexGW｜GB300（每 MW 年營運費用，不含折舊） | C76: US$m/MW-年 | E76: 1.9826348 | G76: Derived | H76: data/tokenomics_snapshot_v21.7.json
A77: opx_vr | B77: IF_OpexGW｜VR200（每 MW 年營運費用，不含折舊） | C77: US$m/MW-年 | E77: 2.0934955 | G77: Derived | H77: data/tokenomics_snapshot_v21.7.json
A78: cit_b3 | B78: IF_CapexIT｜GB300（每 MW IT 資本支出） | C78: US$m/MW | E78: 32.237224 | G78: Derived | H78: data/tokenomics_snapshot_v21.7.json
A79: cit_vr | B79: IF_CapexIT｜VR200（每 MW IT 資本支出） | C79: US$m/MW | E79: 37.586352 | G79: Derived | H79: data/tokenomics_snapshot_v21.7.json
A80: cfac | B80: IF_CapexFacility（每 MW 機房資本支出） | C80: US$m/MW | E80: 12.67 | G80: Derived | H80: data/tokenomics_snapshot_v21.7.json
A81: dpi_h | B81: IF_DeprIT｜H100（每 MW IT 年折舊） | C81: US$m/MW-年 | E81: 4.5850357 | G81: Derived | H81: data/tokenomics_snapshot_v21.7.json | I81: 期初機隊汰換時遞減基礎折舊
A82: dpi_b2 | B82: IF_DeprIT｜GB200（每 MW IT 年折舊） | C82: US$m/MW-年 | E82: 4.002529 | G82: Derived | H82: data/tokenomics_snapshot_v21.7.json | I82: 期初機隊汰換時遞減基礎折舊
A83: dpi_b3 | B83: IF_DeprIT｜GB300（每 MW IT 年折舊） | C83: US$m/MW-年 | E83: 5.3728707 | G83: Derived | H83: data/tokenomics_snapshot_v21.7.json | I83: 期初機隊汰換時遞減基礎折舊
A84: life_it | B84: AI IT 折舊年限 | C84: 年 | D84: 5 | E84: 6 | F84: 7 | G84: Derived | H84: Tokenomics IF_DeprLifeIT 6 年
A85: life_fac | B85: 機房折舊年限 | C85: 年 | D85: 15 | E85: 20 | F85: 25 | G85: Derived | H85: Tokenomics IF_CapexFacility 12.67 ÷ IF_DeprFac 0.634＝20 年
A86: phi_0 | B86: 資本支出當期折舊比例（在役時點與半年慣例） | C86: x | D86: 0 | E86: 0.25 | F86: 0.5 | G86: Assumed | H86: 同 Alphabet
A87: cip_0 | B87: 在建工程（2026-09-30） | C87: US$B | E87: 23.745 | G87: Verified | H87: mag/extract/docs/2026Q3/spacex_2026Q3_10-Q.pdf 第 17 頁 附註 5（2026-10-22；事實總帳 ppe.cip.20260930；Verified） | I87: 主要為伺服器與資料中心
A88: cip_si | B88: 在建工程中屬 SI 的比例 | C88: % | D88: 0 | E88: 0.85 | F88: 1 | G88: Assumed | H88: 判斷：9M26 SI 占資本支出 83%（39.995 ÷ 48.069） | I88: SI 部分 Q4 26 起依 IT／機房年限折舊（不另增 GW；同 Alphabet 修正三口徑，判斷題）
A89: cip_it | B89: 在建工程（SI）中 IT 占比 | C89: % | E89: 0.8 | G89: Assumed | H89: 判斷：9M26 伺服器與網通 +20.5、資料中心基礎設施 +3.4（PP&E 附註）
A90: da_si0 | B90: SI 評價日在役資產年折舊（2026Q3 × 4） | C90: US$B/年 | E90: 9.892 | G90: Derived | H90: mag/extract/docs/2026Q3/spacex_2026Q3_10-Q.pdf 第 36 頁 附註 18 Segments 表（2026-10-22；事實總帳 seg.si.da.2026q3；Verified） | I90: 期初機隊汰換時遞減（同 Alphabet 修正一）
A91: it_sh_da | B91: SI 基礎折舊中 IT 占比（汰換遞減上限） | C91: % | E91: 0.8 | G91: Assumed | H91: 判斷：伺服器 43.2 對資料中心 6.3（PP&E 附註）
A92: E. 命題模組：SI 每 GW 年營收（審查第 4 條；情境軸）
A93: k30_A | B93: 情境 A：FY2030 每 GW 年營收 ÷ Tokenomics 持有成本（k） | C93: x | E93: 1.6 | G93: Assumed | H93: 判斷：維持 2026Q3 校準值附近（供給吃緊、對外合約三年固定月費；Q2 新簽雲端合約 14.1B） | I93: FY2026Q4＝校準 k0，線性到 FY2030，之後持平
A94: k30_B | B94: 情境 B：FY2030 每 GW 年營收 ÷ Tokenomics 持有成本（k） | C94: x | D94: 1 | E94: 1.25 | F94: 1.5 | G94: Assumed | H94: 判斷：MAG 長約與現貨證據混合 k 約 1.2（Alphabet v0.3.2 Thesis k_blend）；合約到期後重新議價向持有成本收斂
A95: k30_C | B95: 情境 C：FY2030 每 GW 年營收 ÷ Tokenomics 持有成本（k） | C95: x | E95: 1 | G95: Assumed | H95: 判斷：算力供給追上後租金收斂到打平持有成本（報酬＝Tokenomics WACC 10%）
A96: conv_k | B96: k 收斂年數（Q4 26 校準值 → FY2030） | C96: 年 | E96: 4 | G96: Assumed | H96: 同成長率收斂（FY2030 到位）
A97: F. SI 其他收入（Grok／Cursor／X 訂閱、資料授權、API；X 廣告）
A98: cur_pf | B98: Cursor 備考補足（2026Q3 備考營收 − 實際營收） | C98: US$B/季 | E98: 0.539 | G98: Interested-party | H98: mag/extract/docs/2026Q3/spacex_2026Q3_10-Q.pdf 第 40 頁 附註 20 備考資訊（2026-10-22；事實總帳 cursor.proforma.rev.2026q3；Interested-party） | I98: 審查第 8 條：Cursor 2026-08-14 併入，Q3 只含約 1.5 月（608）；預測期以備考全季為起點（未經查核）
A99: g27_nr | B99: SI 其他收入 FY2027 年增（以 Q4 26 備考年化為基期） | C99: % | D99: 0.25 | E99: 0.5 | F99: 0.8 | G99: Assumed | H99: 判斷：Grok 訂閱與 API、Cursor（AI 程式助理）高速成長；公司未揭露拆分（A 段第 5 節）
A100: gl_nr | B100: SI 其他收入長期成長（FY2030 到位） | C100: % | D100: 0.08 | E100: 0.15 | F100: 0.25 | G100: Assumed | H100: 判斷
...

Sheet Q
A1: Q — 實績（US$B；EPS 美元；股數十億股；GW、訂戶、次數為原單位）。資料取自 data/spacex_facts_2026q3.json（10-Q 2026Q3、Q3 新聞稿、Q2 新聞稿兩讀核對）；FY2025* 為媒體轉述 S-1（二手，待 424B4 原文；Space 資本支出未取得）
A2: 核對列（實績必須為 0）：子列合計＝分部、分部合計＝合併（營收、營業利益、分部調整後 EBITDA、資本支出）、分部調整後 EBITDA 恆等式、損益表恆等式
A3: 項目 | B3: 2025Q2 | C3: 2025Q3 | D3: 2026Q1 | E3: 2026Q2 | F3: 2026Q3 | G3: 9M25 | H3: 9M26 | I3: FY2025* | J3: 標記 | K3: 來源
A4: 營收（官方分部與子列）
A5: Launch Services | B5: 0.49 | C5: 1 | D5: 0.33 | E5: 0.648 | F5: 1.13 | G5: 2.056 | H5: 2.108 | J5: Verified／Interested-party（KPI） | K5: 10-Q 2026Q3 附註 3、18（四期）；Q3 新聞稿（2026Q2 欄）；Q2 新聞稿（2026Q1、2025Q2）；FY2025＝媒體轉述 S-1（事實總帳 seg.*／is.*）
A6: Launch & Development | B6: 0.256 | C6: 0.666 | D6: 0.289 | E6: 0.314 | F6: 0.637 | G6: 1.221 | H6: 1.24 | J6: Verified／Interested-party（KPI） | K6: 10-Q 2026Q3 附註 3、18（四期）；Q3 新聞稿（2026Q2 欄）；Q2 新聞稿（2026Q1、2025Q2）；FY2025＝媒體轉述 S-1（事實總帳 seg.*／is.*）
A7: Space（分部） | B7: 0.746 | C7: 1.666 | D7: 0.619 | E7: 0.962 | F7: 1.767 | G7: 3.277 | H7: 3.348 | I7: 4.086 | J7: Verified／Interested-party（KPI） | K7: 10-Q 2026Q3 附註 3、18（四期）；Q3 新聞稿（2026Q2 欄）；Q2 新聞稿（2026Q1、2025Q2）；FY2025＝媒體轉述 S-1（事實總帳 seg.*／is.*）
A8: 檢查：Space 子列合計 − Space | B8: =B5+B6-B7 -> 0 | C8: =C5+C6-C7 -> 0 | D8: =D5+D6-D7 -> 0 | E8: =E5+E6-E7 -> 0 | F8: =F5+F6-F7 -> 0 | G8: =G5+G6-G7 -> 0 | H8: =H5+H6-H7 -> 0 | J8: — | K8: —
A9: Consumer | B9: 1.721 | C9: 1.986 | D9: 2.148 | E9: 2.485 | F9: 3.121 | G9: 5.198 | H9: 7.754 | J9: Verified／Interested-party（KPI） | K9: 10-Q 2026Q3 附註 3、18（四期）；Q3 新聞稿（2026Q2 欄）；Q2 新聞稿（2026Q1、2025Q2）；FY2025＝媒體轉述 S-1（事實總帳 seg.*／is.*）
A10: Enterprise & Government | B10: 0.867 | C10: 1.111 | D10: 1.109 | E10: 1.806 | F10: 2.127 | G10: 2.961 | H10: 5.042 | J10: Verified／Interested-party（KPI） | K10: 10-Q 2026Q3 附註 3、18（四期）；Q3 新聞稿（2026Q2 欄）；Q2 新聞稿（2026Q1、2025Q2）；FY2025＝媒體轉述 S-1（事實總帳 seg.*／is.*）
A11: Connectivity（分部） | B11: 2.588 | C11: 3.097 | D11: 3.257 | E11: 4.291 | F11: 5.248 | G11: 8.159 | H11: 12.796 | I11: 11.387 | J11: Verified／Interested-party（KPI） | K11: 10-Q 2026Q3 附註 3、18（四期）；Q3 新聞稿（2026Q2 欄）；Q2 新聞稿（2026Q1、2025Q2）；FY2025＝媒體轉述 S-1（事實總帳 seg.*／is.*）
A12: 檢查：Connectivity 子列合計 − Connectivity | B12: =B9+B10-B11 -> 0 | C12: =C9+C10-C11 -> 0 | D12: =D9+D10-D11 -> 0 | E12: =E9+E10-E11 -> 0 | F12: =F9+F10-F11 -> 0 | G12: =G9+G10-G11 -> 0 | H12: =H9+H10-H11 -> 0 | J12: — | K12: —
A13: Advertising | B13: 0.426 | C13: 0.454 | D13: 0.343 | E13: 0.367 | F13: 0.538 | G13: 1.323 | H13: 1.248 | J13: Verified／Interested-party（KPI） | K13: 10-Q 2026Q3 附註 3、18（四期）；Q3 新聞稿（2026Q2 欄）；Q2 新聞稿（2026Q1、2025Q2）；FY2025＝媒體轉述 S-1（事實總帳 seg.*／is.*）
A14: SI Solutions & Infrastructure | B14: 0.311 | C14: 0.359 | D14: 0.475 | E14: 2.194 | F14: 7.022 | G14: 0.955 | H14: 9.691 | J14: Verified／Interested-party（KPI） | K14: 10-Q 2026Q3 附註 3、18（四期）；Q3 新聞稿（2026Q2 欄）；Q2 新聞稿（2026Q1、2025Q2）；FY2025＝媒體轉述 S-1（事實總帳 seg.*／is.*）
A15: SI（分部） | B15: 0.737 | C15: 0.813 | D15: 0.818 | E15: 2.561 | F15: 7.56 | G15: 2.278 | H15: 10.939 | I15: 3.201 | J15: Verified／Interested-party（KPI） | K15: 10-Q 2026Q3 附註 3、18（四期）；Q3 新聞稿（2026Q2 欄）；Q2 新聞稿（2026Q1、2025Q2）；FY2025＝媒體轉述 S-1（事實總帳 seg.*／is.*）
A16: 檢查：SI 子列合計 − SI | B16: =B13+B14-B15 -> 0 | C16: =C13+C14-C15 -> 0 | D16: =D13+D14-D15 -> 0 | E16: =E13+E14-E15 -> 0 | F16: =F13+F14-F15 -> 0 | G16: =G13+G14-G15 -> 0 | H16: =H13+H14-H15 -> 0 | J16: — | K16: —
A17: 合併營收 | B17: 4.071 | C17: 5.576 | D17: 4.694 | E17: 7.814 | F17: 14.575 | G17: 13.714 | H17: 27.083 | I17: 18.674 | J17: Verified／Interested-party（KPI） | K17: 10-Q 2026Q3 附註 3、18（四期）；Q3 新聞稿（2026Q2 欄）；Q2 新聞稿（2026Q1、2025Q2）；FY2025＝媒體轉述 S-1（事實總帳 seg.*／is.*）
A18: 檢查：分部合計 − 合併營收 | B18: =B7+B11+B15-B17 -> 0 | C18: =C7+C11+C15-C17 -> 0 | D18: =D7+D11+D15-D17 -> 0 | E18: =E7+E11+E15-E17 -> 0 | F18: =F7+F11+F15-F17 -> 0 | G18: =G7+G11+G15-G17 -> 0 | H18: =H7+H11+H15-H17 -> 0 | I18: =I7+I11+I15-I17 -> 0 | J18: — | K18: —
A20: 分部營業利益（損失）
A21: Space：分部營業利益 | B21: -0.369 | C21: 0.259 | D21: -0.662 | E21: -0.542 | F21: -0.007 | G21: -0.181 | H21: -1.211 | I21: -0.657 | J21: Verified／Interested-party（KPI） | K21: 10-Q 2026Q3 附註 3、18（四期）；Q3 新聞稿（2026Q2 欄）；Q2 新聞稿（2026Q1、2025Q2）；FY2025＝媒體轉述 S-1（事實總帳 seg.*／is.*）
A22: Connectivity：分部營業利益 | B22: 0.923 | C22: 1.19 | D22: 1.188 | E22: 1.656 | F22: 2.367 | G22: 3.147 | H22: 5.211 | I22: 4.423 | J22: Verified／Interested-party（KPI） | K22: 10-Q 2026Q3 附註 3、18（四期）；Q3 新聞稿（2026Q2 欄）；Q2 新聞稿（2026Q1、2025Q2）；FY2025＝媒體轉述 S-1（事實總帳 seg.*／is.*）
A23: SI（原 AI）：分部營業利益 | B23: -1.524 | C23: -1.722 | D23: -2.469 | E23: -1.257 | F23: 0.431 | G23: -4.182 | H23: -3.295 | I23: -6.355 | J23: Verified／Interested-party（KPI） | K23: 10-Q 2026Q3 附註 3、18（四期）；Q3 新聞稿（2026Q2 欄）；Q2 新聞稿（2026Q1、2025Q2）；FY2025＝媒體轉述 S-1（事實總帳 seg.*／is.*）
A24: 合計：分部營業利益 | B24: -0.97 | C24: -0.273 | D24: -1.943 | E24: -0.143 | F24: 2.791 | G24: -1.216 | H24: 0.705 | I24: -2.589 | J24: Verified／Interested-party（KPI） | K24: 10-Q 2026Q3 附註 3、18（四期）；Q3 新聞稿（2026Q2 欄）；Q2 新聞稿（2026Q1、2025Q2）；FY2025＝媒體轉述 S-1（事實總帳 seg.*／is.*）
A25: 檢查：分部合計 − 合併（分部營業利益） | B25: =B21+B22+B23-B24 -> 0 | C25: =C21+C22+C23-C24 -> 0 | D25: =D21+D22+D23-D24 -> 0 | E25: =E21+E22+E23-E24 -> 0 | F25: =F21+F22+F23-F24 -> 0 | G25: =G21+G22+G23-G24 -> 0 | H25: =H21+H22+H23-H24 -> 0 | I25: =I21+I22+I23-I24 -> 0 | J25: — | K25: —
A27: 分部調整後 EBITDA（公司定義，不含 SBC）
A28: Space：分部調整後 EBITDA | B28: -0.093 | C28: 0.674 | D28: -0.351 | E28: -0.205 | F28: 0.357 | G28: 0.803 | H28: -0.199 | I28: 0.653 | J28: Verified／Interested-party（KPI） | K28: 10-Q 2026Q3 附註 3、18（四期）；Q3 新聞稿（2026Q2 欄）；Q2 新聞稿（2026Q1、2025Q2）；FY2025＝媒體轉述 S-1（事實總帳 seg.*／is.*）
A29: Connectivity：分部調整後 EBITDA | B29: 1.583 | C29: 1.923 | D29: 2.087 | E29: 2.597 | F29: 3.499 | G29: 5.123 | H29: 8.183 | I29: 7.168 | J29: Verified／Interested-party（KPI） | K29: 10-Q 2026Q3 附註 3、18（四期）；Q3 新聞稿（2026Q2 欄）；Q2 新聞稿（2026Q1、2025Q2）；FY2025＝媒體轉述 S-1（事實總帳 seg.*／is.*）
A30: SI（原 AI）：分部調整後 EBITDA | B30: -0.276 | C30: -0.428 | D30: -0.609 | E30: 1.146 | F30: 4.953 | G30: -0.813 | H30: 5.49 | I30: -1.237 | J30: Verified／Interested-party（KPI） | K30: 10-Q 2026Q3 附註 3、18（四期）；Q3 新聞稿（2026Q2 欄）；Q2 新聞稿（2026Q1、2025Q2）；FY2025＝媒體轉述 S-1（事實總帳 seg.*／is.*）
A31: 合計：分部調整後 EBITDA | B31: 1.214 | C31: 2.169 | D31: 1.127 | E31: 3.538 | F31: 8.809 | G31: 5.113 | H31: 13.474 | I31: 6.584 | J31: Verified／Interested-party（KPI） | K31: 10-Q 2026Q3 附註 3、18（四期）；Q3 新聞稿（2026Q2 欄）；Q2 新聞稿（2026Q1、2025Q2）；FY2025＝媒體轉述 S-1（事實總帳 seg.*／is.*）
A32: 檢查：分部合計 − 合併（分部調整後 EBITDA） | B32: =B28+B29+B30-B31 -> 0 | C32: =C28+C29+C30-C31 -> 0 | D32: =D28+D29+D30-D31 -> 0 | E32: =E28+E29+E30-E31 -> 0 | F32: =F28+F29+F30-F31 -> 0 | G32: =G28+G29+G30-G31 -> 0 | H32: =H28+H29+H30-H31 -> 0 | I32: =I28+I29+I30-I31 -> 0 | J32: — | K32: —
A34: 分部資本支出（購置不動產與設備）
A35: Space：分部資本支出 | B35: 0.946 | C35: 1.113 | D35: 1.052 | E35: 1.174 | F35: 1.606 | G35: 2.818 | H35: 3.832 | J35: Verified／Interested-party（KPI） | K35: 10-Q 2026Q3 附註 3、18（四期）；Q3 新聞稿（2026Q2 欄）；Q2 新聞稿（2026Q1、2025Q2）；FY2025＝媒體轉述 S-1（事實總帳 seg.*／is.*）
A36: Connectivity：分部資本支出 | B36: 1.13 | C36: 1.007 | D36: 1.332 | E36: 1.367 | F36: 1.543 | G36: 2.951 | H36: 4.242 | I36: 4.178 | J36: Verified／Interested-party（KPI） | K36: 10-Q 2026Q3 附註 3、18（四期）；Q3 新聞稿（2026Q2 欄）；Q2 新聞稿（2026Q1、2025Q2）；FY2025＝媒體轉述 S-1（事實總帳 seg.*／is.*）
A37: SI（原 AI）：分部資本支出 | B37: 0.749 | C37: 4.76 | D37: 7.723 | E37: 15.828 | F37: 16.444 | G37: 8.077 | H37: 39.995 | I37: 12.727 | J37: Verified／Interested-party（KPI） | K37: 10-Q 2026Q3 附註 3、18（四期）；Q3 新聞稿（2026Q2 欄）；Q2 新聞稿（2026Q1、2025Q2）；FY2025＝媒體轉述 S-1（事實總帳 seg.*／is.*）
A38: 合計：分部資本支出 | B38: 2.825 | C38: 6.88 | D38: 10.107 | E38: 18.369 | F38: 19.593 | G38: 13.846 | H38: 48.069 | I38: 20.737 | J38: Verified／Interested-party（KPI） | K38: 10-Q 2026Q3 附註 3、18（四期）；Q3 新聞稿（2026Q2 欄）；Q2 新聞稿（2026Q1、2025Q2）；FY2025＝媒體轉述 S-1（事實總帳 seg.*／is.*）
A39: 檢查：分部合計 − 合併（分部資本支出） | B39: =B35+B36+B37-B38 -> 0 | C39: =C35+C36+C37-C38 -> 0 | D39: =D35+D36+D37-D38 -> 0 | E39: =E35+E36+E37-E38 -> 0 | F39: =F35+F36+F37-F38 -> 0 | G39: =G35+G36+G37-G38 -> 0 | H39: =H35+H36+H37-H38 -> 0 | J39: — | K39: —
A41: 分部調整後 EBITDA 調節項（折舊攤銷、股權報酬、收購相關、重組、減損）
A42: Space：折舊攤銷 | B42: 0.146 | C42: 0.264 | D42: 0.166 | E42: 0.158 | F42: 0.185 | G42: 0.572 | H42: 0.509 | J42: Verified／Interested-party（KPI） | K42: 10-Q 2026Q3 附註 3、18（四期）；Q3 新聞稿（2026Q2 欄）；Q2 新聞稿（2026Q1、2025Q2）；FY2025＝媒體轉述 S-1（事實總帳 seg.*／is.*）
A43: Space：股權報酬（一般） | B43: 0.125 | C43: 0.151 | D43: 0.145 | E43: 0.179 | F43: 0.179 | G43: 0.383 | H43: 0.503 | J43: Verified／Interested-party（KPI） | K43: 10-Q 2026Q3 附註 3、18（四期）；Q3 新聞稿（2026Q2 欄）；Q2 新聞稿（2026Q1、2025Q2）；FY2025＝媒體轉述 S-1（事實總帳 seg.*／is.*）
A44: Connectivity：折舊攤銷 | B44: 0.569 | C44: 0.628 | D44: 0.783 | E44: 0.805 | F44: 0.986 | G44: 1.706 | H44: 2.574 | J44: Verified／Interested-party（KPI） | K44: 10-Q 2026Q3 附註 3、18（四期）；Q3 新聞稿（2026Q2 欄）；Q2 新聞稿（2026Q1、2025Q2）；FY2025＝媒體轉述 S-1（事實總帳 seg.*／is.*）
A45: Connectivity：股權報酬（一般） | B45: 0.091 | C45: 0.105 | D45: 0.116 | E45: 0.136 | F45: 0.146 | G45: 0.27 | H45: 0.398 | J45: Verified／Interested-party（KPI） | K45: 10-Q 2026Q3 附註 3、18（四期）；Q3 新聞稿（2026Q2 欄）；Q2 新聞稿（2026Q1、2025Q2）；FY2025＝媒體轉述 S-1（事實總帳 seg.*／is.*）
A46: SI（原 AI）：折舊攤銷 | B46: 0.811 | C46: 0.922 | D46: 1.493 | E46: 1.885 | F46: 2.473 | G46: 2.506 | H46: 5.851 | J46: Verified／Interested-party（KPI） | K46: 10-Q 2026Q3 附註 3、18（四期）；Q3 新聞稿（2026Q2 欄）；Q2 新聞稿（2026Q1、2025Q2）；FY2025＝媒體轉述 S-1（事實總帳 seg.*／is.*）
A47: SI（原 AI）：股權報酬（一般） | B47: 0.247 | C47: 0.094 | D47: 0.378 | E47: 0.516 | F47: 0.821 | G47: 0.391 | H47: 1.715 | J47: Verified／Interested-party（KPI） | K47: 10-Q 2026Q3 附註 3、18（四期）；Q3 新聞稿（2026Q2 欄）；Q2 新聞稿（2026Q1、2025Q2）；FY2025＝媒體轉述 S-1（事實總帳 seg.*／is.*）
A48: SI：收購相關股權報酬（Cursor） | E48: 0 | F48: 1.217 | H48: 1.217 | J48: Verified／Interested-party（KPI） | K48: 10-Q 2026Q3 附註 3、18（四期）；Q3 新聞稿（2026Q2 欄）；Q2 新聞稿（2026Q1、2025Q2）；FY2025＝媒體轉述 S-1（事實總帳 seg.*／is.*）
A49: SI：收購成本 | E49: 0 | F49: 0.008 | H49: 0.008 | J49: Verified／Interested-party（KPI） | K49: 10-Q 2026Q3 附註 3、18（四期）；Q3 新聞稿（2026Q2 欄）；Q2 新聞稿（2026Q1、2025Q2）；FY2025＝媒體轉述 S-1（事實總帳 seg.*／is.*）
A50: SI：重組費用（X） | C50: 0.278 | E50: 0.002 | F50: 0.003 | G50: 0.472 | H50: -0.006 | J50: Verified／Interested-party（KPI） | K50: 10-Q 2026Q3 附註 3、18（四期）；Q3 新聞稿（2026Q2 欄）；Q2 新聞稿（2026Q1、2025Q2）；FY2025＝媒體轉述 S-1（事實總帳 seg.*／is.*）
A51: Space：減損 | E51: 0 | G51: 0.029 | J51: Verified／Interested-party（KPI） | K51: 10-Q 2026Q3 附註 3、18（四期）；Q3 新聞稿（2026Q2 欄）；Q2 新聞稿（2026Q1、2025Q2）；FY2025＝媒體轉述 S-1（事實總帳 seg.*／is.*）
A52: 檢查：Space 調整後 EBITDA − (營業利益＋折舊攤銷＋SBC＋其他調節) | C52: =C28-(C21+C42+C43+N(C51)) -> 0 | E52: =E28-(E21+E42+E43+N(E51)) -> 0 | F52: =F28-(F21+F42+F43+N(F51)) -> 0 | G52: =G28-(G21+G42+G43+N(G51)) -> 0 | H52: =H28-(H21+H42+H43+N(H51)) -> 0 | J52: — | K52: 五期（10-Q／Q3 新聞稿）
A53: 檢查：Connectivity 調整後 EBITDA − (營業利益＋折舊攤銷＋SBC＋其他調節) | C53: =C29-(C22+C44+C45) -> 0 | E53: =E29-(E22+E44+E45) -> 0 | F53: =F29-(F22+F44+F45) -> 0 | G53: =G29-(G22+G44+G45) -> 0 | H53: =H29-(H22+H44+H45) -> 0 | J53: — | K53: 五期（10-Q／Q3 新聞稿）
A54: 檢查：SI（原 AI） 調整後 EBITDA − (營業利益＋折舊攤銷＋SBC＋其他調節) | C54: =C30-(C23+C46+C47+N(C48)+N(C49)+N(C50)) -> 0 | E54: =E30-(E23+E46+E47+N(E48)+N(E49)+N(E50)) -> 0 | F54: =F30-(F23+F46+F47+N(F48)+N(F49)+N(F50)) -> 0 | G54: =G30-(G23+G46+G47+N(G48)+N(G49)+N(G50)) -> 0 | H54: =H30-(H23+H46+H47+N(H48)+N(H49)+N(H50)) -> 0 | J54: — | K54: 五期（10-Q／Q3 新聞稿）
A56: 營運指標
A57: 客戶發射（次） | B57: 9 | C57: 15 | D57: 7 | E57: 10 | F57: 12 | G57: 36 | H57: 29 | J57: Verified／Interested-party（KPI） | K57: 10-Q 2026Q3 附註 3、18（四期）；Q3 新聞稿（2026Q2 欄）；Q2 新聞稿（2026Q1、2025Q2）；FY2025＝媒體轉述 S-1（事實總帳 seg.*／is.*）
A58: 發射合計（次） | B58: 46 | C58: 44 | D58: 40 | E58: 38 | F58: 35 | G58: 128 | H58: 113 | J58: Verified／Interested-party（KPI） | K58: 10-Q 2026Q3 附註 3、18（四期）；Q3 新聞稿（2026Q2 欄）；Q2 新聞稿（2026Q1、2025Q2）；FY2025＝媒體轉述 S-1（事實總帳 seg.*／is.*）
A59: Starlink 消費訂戶（百萬，期末） | B59: 6 | C59: 7.2 | D59: 10.3 | E59: 12 | F59: 13.6 | J59: Verified／Interested-party（KPI） | K59: 10-Q 2026Q3 附註 3、18（四期）；Q3 新聞稿（2026Q2 欄）；Q2 新聞稿（2026Q1、2025Q2）；FY2025＝媒體轉述 S-1（事實總帳 seg.*／is.*）
A60: 消費 ARPU（美元／月） | B60: 85 | C60: 83 | D60: 66 | E60: 66 | F60: 69 | G60: 84 | H60: 67 | J60: Verified／Interested-party（KPI） | K60: 10-Q 2026Q3 附註 3、18（四期）；Q3 新聞稿（2026Q2 欄）；Q2 新聞稿（2026Q1、2025Q2）；FY2025＝媒體轉述 S-1（事實總帳 seg.*／is.*）
A61: SI 名目算力（GW，期末；IT 口徑） | B61: 0.4 | C61: 0.6 | D61: 1 | E61: 1.4 | F61: 1.7 | J61: Verified／Interested-party（KPI） | K61: 10-Q 2026Q3 附註 3、18（四期）；Q3 新聞稿（2026Q2 欄）；Q2 新聞稿（2026Q1、2025Q2）；FY2025＝媒體轉述 S-1（事實總帳 seg.*／is.*）
A63: 合併損益（10-Q 四期；2026Q2 只有新聞稿 Highlights）
A64: 成本費用合計 | C64: 5.849 | F64: 11.784 | G64: 14.93 | H64: 26.378 | J64: Verified／Interested-party（KPI） | K64: 10-Q 2026Q3 附註 3、18（四期）；Q3 新聞稿（2026Q2 欄）；Q2 新聞稿（2026Q1、2025Q2）；FY2025＝媒體轉述 S-1（事實總帳 seg.*／is.*）
A65: 營業利益 | C65: -0.273 | E65: -0.143 | F65: 2.791 | G65: -1.216 | H65: 0.705 | J65: Verified／Interested-party（KPI） | K65: 10-Q 2026Q3 附註 3、18（四期）；Q3 新聞稿（2026Q2 欄）；Q2 新聞稿（2026Q1、2025Q2）；FY2025＝媒體轉述 S-1（事實總帳 seg.*／is.*）
A66: 檢查：營收 − 成本費用 − 營業利益 | C66: =C17-C64-C65 -> 0 | F66: =F17-F64-F65 -> 0 | G66: =G17-G64-G65 -> 0 | H66: =H17-H64-H65 -> 0 | J66: — | K66: —
A67: 利息費用（含 Valor 關係人） | C67: -0.514 | F67: -0.675 | G67: -1.372 | H67: -1.968 | J67: Verified／Interested-party（KPI） | K67: 10-Q 2026Q3 附註 3、18（四期）；Q3 新聞稿（2026Q2 欄）；Q2 新聞稿（2026Q1、2025Q2）；FY2025＝媒體轉述 S-1（事實總帳 seg.*／is.*）
A68: 利息收入 | C68: 0.155 | F68: 0.873 | G68: 0.37 | H68: 1.426 | J68: Verified／Interested-party（KPI） | K68: 10-Q 2026Q3 附註 3、18（四期）；Q3 新聞稿（2026Q2 欄）；Q2 新聞稿（2026Q1、2025Q2）；FY2025＝媒體轉述 S-1（事實總帳 seg.*／is.*）
A69: 其他收益（費用）淨額 | C69: 0.14 | F69: 1.025 | G69: 0.342 | H69: -0.937 | J69: Verified／Interested-party（KPI） | K69: 10-Q 2026Q3 附註 3、18（四期）；Q3 新聞稿（2026Q2 欄）；Q2 新聞稿（2026Q1、2025Q2）；FY2025＝媒體轉述 S-1（事實總帳 seg.*／is.*）
A70: 稅前利益 | C70: -0.492 | F70: 4.014 | G70: -1.876 | H70: -0.774 | J70: Verified／Interested-party（KPI） | K70: 10-Q 2026Q3 附註 3、18（四期）；Q3 新聞稿（2026Q2 欄）；Q2 新聞稿（2026Q1、2025Q2）；FY2025＝媒體轉述 S-1（事實總帳 seg.*／is.*）
A71: 檢查：營業利益＋利息＋其他 − 稅前 | C71: =C65+C67+C68+C69-C70 -> 0 | F71: =F65+F67+F68+F69-F70 -> 0 | G71: =G65+G67+G68+G69-G70 -> 0 | H71: =H65+H67+H68+H69-H70 -> 0 | J71: — | K71: —
A72: 所得稅費用（負值＝利益） | C72: 0.562 | F72: -0.39 | G72: 0.714 | H72: -0.361 | J72: Verified／Interested-party（KPI） | K72: 10-Q 2026Q3 附註 3、18（四期）；Q3 新聞稿（2026Q2 欄）；Q2 新聞稿（2026Q1、2025Q2）；FY2025＝媒體轉述 S-1（事實總帳 seg.*／is.*）
A73: 淨利（損） | C73: -1.054 | E73: -0.541 | F73: 4.404 | G73: -2.59 | H73: -0.413 | J73: Verified／Interested-party（KPI） | K73: 10-Q 2026Q3 附註 3、18（四期）；Q3 新聞稿（2026Q2 欄）；Q2 新聞稿（2026Q1、2025Q2）；FY2025＝媒體轉述 S-1（事實總帳 seg.*／is.*）
A74: 檢查：稅前 − 所得稅 − 淨利 | C74: =C70-C72-C73 -> 0 | F74: =F70-F72-F73 -> 0 | G74: =G70-G72-G73 -> 0 | H74: =H70-H72-H73 -> 0 | J74: — | K74: —
A75: 歸屬普通股淨利（扣視同股利） | C75: -1.054 | F75: 4.404 | G75: -2.59 | H75: -1.084 | J75: Verified／Interested-party（KPI） | K75: 10-Q 2026Q3 附註 3、18（四期）；Q3 新聞稿（2026Q2 欄）；Q2 新聞稿（2026Q1、2025Q2）；FY2025＝媒體轉述 S-1（事實總帳 seg.*／is.*）
A76: EPS（稀釋，美元） | C76: -0.36 | E76: -0.09 | F76: 0.35 | G76: -0.89 | H76: -0.15 | J76: Verified／Interested-party（KPI） | K76: 10-Q 2026Q3 附註 3、18（四期）；Q3 新聞稿（2026Q2 欄）；Q2 新聞稿（2026Q1、2025Q2）；FY2025＝媒體轉述 S-1（事實總帳 seg.*／is.*）
A77: 稀釋加權股數（十億股） | C77: 2.941 | E77: 5.864 | F77: 12.475 | G77: 2.915 | H77: 7.274 | J77: Verified／Interested-party（KPI） | K77: 10-Q 2026Q3 附註 3、18（四期）；Q3 新聞稿（2026Q2 欄）；Q2 新聞稿（2026Q1、2025Q2）；FY2025＝媒體轉述 S-1（事實總帳 seg.*／is.*）
A79: 現金流（9M；10-Q 現金流量表）
A80: 營運現金流 | G80: 4.12 | H80: 13.097 | J80: Verified／Interested-party（KPI） | K80: 10-Q 2026Q3 附註 3、18（四期）；Q3 新聞稿（2026Q2 欄）；Q2 新聞稿（2026Q1、2025Q2）；FY2025＝媒體轉述 S-1（事實總帳 seg.*／is.*）
A81: 折舊攤銷 | G81: 4.784 | H81: 8.934 | J81: Verified／Interested-party（KPI） | K81: 10-Q 2026Q3 附註 3、18（四期）；Q3 新聞稿（2026Q2 欄）；Q2 新聞稿（2026Q1、2025Q2）；FY2025＝媒體轉述 S-1（事實總帳 seg.*／is.*）
A82: 股權報酬 | G82: 1.044 | H82: 3.833 | J82: Verified／Interested-party（KPI） | K82: 10-Q 2026Q3 附註 3、18（四期）；Q3 新聞稿（2026Q2 欄）；Q2 新聞稿（2026Q1、2025Q2）；FY2025＝媒體轉述 S-1（事實總帳 seg.*／is.*）
A83: 資本支出（購置不動產與設備） | G83: 13.846 | H83: 48.069 | J83: Verified／Interested-party（KPI） | K83: 10-Q 2026Q3 附註 3、18（四期）；Q3 新聞稿（2026Q2 欄）；Q2 新聞稿（2026Q1、2025Q2）；FY2025＝媒體轉述 S-1（事實總帳 seg.*／is.*）
A84: 檢查：資本支出 − 分部資本支出合計 | G84: =G83-G38 -> 0 | H84: =H83-H38 -> 0 | J84: — | K84: —
A85: 以其他融資取得 PP&E（非現金） | G85: 0 | H85: 3.921 | J85: Verified／Interested-party（KPI） | K85: 10-Q 2026Q3 附註 3、18（四期）；Q3 新聞稿（2026Q2 欄）；Q2 新聞稿（2026Q1、2025Q2）；FY2025＝媒體轉述 S-1（事實總帳 seg.*／is.*）
A86: 融資租賃本金 | G86: 0.213 | H86: 0.27 | J86: Verified／Interested-party（KPI） | K86: 10-Q 2026Q3 附註 3、18（四期）；Q3 新聞稿（2026Q2 欄）；Q2 新聞稿（2026Q1、2025Q2）；FY2025＝媒體轉述 S-1（事實總帳 seg.*／is.*）
A87: 公司口徑 FCF（營運現金 − 資本支出） | G87: =G80-G83 -> -9.726 | H87: =H80-H83 -> -34.972 | J87: Derived | K87: —
A89: 核對彙總（實績必須為 0）
A90: 檢查：上列核對列絕對值合計 | B90: =SUMPRODUCT(ABS(B8:I8))+SUMPRODUCT(ABS(B12:I12))+SUMPRODUCT(ABS(B16:I16))+SUMPRODUCT(ABS(B18:I18))+SUMPRODUCT(ABS(B25:I25))+SUMPRODUCT(ABS(B32:I32))+SUMPRODUCT(ABS(B39:I39))+SUMPRODUCT(ABS(B52:I52))+SUMPRODUCT(ABS(B53:I53))+SUMPRODUCT(ABS(B54:I54))+SUMPRODUCT(ABS(B66:I66))+SUMPRODUCT(ABS(B71:I71))+SUMPRODUCT(ABS(B74:I74))+SUMPRODUCT(ABS(B84:I84)) -> 0
A91: 檢查：9M26 − (2026Q1＋Q2＋Q3)（三分部營收、營業利益、調整後 EBITDA、資本支出） | B91: =ABS(H7-D7-E7-F7)+ABS(H11-D11-E11-F11)+ABS(H15-D15-E15-F15)+ABS(H21-D21-E21-F21)+ABS(H22-D22-E22-F22)+ABS(H23-D23-E23-F23)+ABS(H28-D28-E28-F28)+ABS(H29-D29-E29-F29)+ABS(H30-D30-E30-F30)+ABS(H35-D35-E35-F35)+ABS(H36-D36-E36-F36)+ABS(H37-D37-E37-F37) -> 0
A93: 推導量（Seg、PL、Thesis 頁的起始值；[Derived]）
A94: 項目 | B94: 數值 | C94: 說明
A95: 9M 年增：Launch & Development | B95: =H6/G6-1 -> 0.015561016 | C95: 9M26 ÷ 9M25 − 1（最近可用的 Verified 同期比較；近四季需 2025Q4，為二手）
A96: 9M 年增：Enterprise & Government | B96: =H10/G10-1 -> 0.70280311
A97: 9M 年增：Advertising（X） | B97: =H13/G13-1 -> -0.056689342
A98: 每次客戶發射收入（9M26） | B98: =H5/H57 -> 0.072689655 | C98: US$B／次
A99: Space 調整後 EBITDA 率（9M26） | B99: =H28/H7 -> -0.059438471
A100: Connectivity 調整後 EBITDA 率（9M26） | B100: =H29/H11 -> 0.63949672
A101: Space 資本支出 ÷ 營收（9M26） | B101: =H35/H7 -> 1.1445639
A102: Connectivity 資本支出 ÷ 營收（9M26） | B102: =H36/H11 -> 0.33150985
A103: Space 一般股權報酬 ÷ 營收（2026Q3） | B103: =F43/F7 -> 0.10130164 | C103: 2026Q3 單季（IPO 後首個完整季）
A104: Connectivity 一般股權報酬 ÷ 營收（2026Q3） | B104: =F45/F11 -> 0.027820122 | C104: 2026Q3 單季（IPO 後首個完整季）
A105: SI（原 AI） 一般股權報酬 ÷ 營收（2026Q3） | B105: =F47/F15 -> 0.10859788 | C105: 2026Q3 單季（IPO 後首個完整季）
A106: Space 年折舊（2026Q3 × 4） | B106: =F42*4 -> 0.74
A107: Connectivity 年折舊（2026Q3 × 4） | B107: =F44*4 -> 3.944
A108: 消費營收 ÷ (平均訂戶 × ARPU × 3)（2026Q3；含 Kits 等） | B108: =F9/((E59+F59)/2*F60/1000*3) -> 1.1779136 | C108: Kits（產品）收入全屬 Connectivity、未拆消費／企業（A 段第 9 節）→ 以本係數併入消費
A109: 2026Q3 平均在役名目算力 | B109: =(E61+F61)/2 -> 1.55 | C109: GW
...

Sheet Thesis
A1: Thesis — 命題模組：SI 名目算力（IT 口徑 GW；2026-09-30 1.7）由 SI 投資季速 ÷ Tokenomics 每 GW 資本支出推進；對外出租 GW（× ext_sh）× 每 GW 年營收（k × Tokenomics 持有成本，k 由 2026Q3 校準值收斂，情境軸，見 Seg 頁）→ SI 對外雲端服務子列；同一套 GW 推出 SI 投資、AI 折舊、營運成本；自用 GW → 讀法 2 影子效益
A2: 三情境共用（情境軸是 k 與 Starlink 淨增，在 Seg 頁）。名目算力為 IT 口徑，與 Tokenomics Interface 第 1 列 IT 關鍵電力同口徑，不乘 PUE（審查第 3 條）；含對外出租、推定不含第三方雲（S6）。對外出租占比以 Customer B 衍生 72% 為起點，營收與 GW 同比例（審查第 4 條）
A4: A. 校準與起始值（單一數值，C 欄）
A5: 項目 | B5: 單位 | C5: 數值 | N5: 說明
A6: 評價日機隊每 GW 年持有成本（Tokenomics IF_HoldEcon 依機隊占比加權） | B6: US$B/GW-年 | C6: =mix0_h*he_h+mix0_b2*he_b2+mix0_b3*he_b3 -> 9.7081157
A7: 評價日機隊每 GW 年營運費用（IF_OpexGW 加權，不含折舊） | B7: US$B/GW-年 | C7: =mix0_h*opx_h+mix0_b2*opx_b2+mix0_b3*opx_b3 -> 1.8850838
A8: 2026Q3 每 GW 年營收＝SI S&I × 4 ÷ 平均在役 GW | B8: US$B/GW-年 | C8: =ssi_q3*4/avg_gw_q3 -> 18.12129 | N8: 審查第 4 條：2026Q3 年化 ÷ 平均在役 GW 校準；對外出租營收與 GW 同比例，故＝對外每 GW 年營收
A9: 校準 k0＝2026Q3 每 GW 年營收 ÷ 評價日機隊持有成本 | B9: x | C9: =rev_gw0/he0 -> 1.8666125 | N9: S2 核心問題比值的起點（FY2028 比值見 Seg 頁各情境）
A10: 2026Q3 對外雲端服務營收（SI S&I × ext_sh） | B10: US$B | C10: =ext_sh*ssi_q3 -> 5.05584 | N10: Customer B 衍生 5.028（事實總帳 cust.B.rev.2026q3）
A11: 9M26 對外雲端服務營收（(Q2＋Q3 SI S&I) × ext_sh；雲端服務自 Q2 開始） | B11: US$B | C11: =ext_sh*ssi_h2 -> 6.63552 | N11: Customer B 9M 衍生 6.554
A12: 2026Q3 SI 其他收入（Grok／Cursor／X 訂閱、資料授權、API） | B12: US$B | C12: =ssi_q3-rent_q3 -> 1.96616 | N12: 含 Cursor 約 1.5 月 0.608
A13: SI 其他 EBITDA 率（2026Q3 校準：(SI 調整後 EBITDA − 對外出租 EBITDA) ÷ (SI 營收 − 對外出租)） | B13: % | C13: =(sie_q3-(rent_q3-ext_sh*avg_gw_q3*opex0/4))/(si_q3-rent_q3) -> 0.1689582 | N13: 對外出租 EBITDA＝營收 − 對外 GW × Tokenomics 營運費用；殘差含 Grok 訓練人力、評價日自用 GW 營運
A14: SI 其他 EBITDA 率（預測期採用） | B14: % | C14: =m_so0+m_so_adj -> 0.1689582
A15: 每 GW 投資（2026 新增：GB300 錨 IT＋自建 × 機房） | B15: US$B/GW | C15: =cit_b3+selfb*cfac -> 43.640224 | N15: Tokenomics IF_CapexIT｜GB300＋selfb × IF_CapexFacility
A16: 對照：PP&E（伺服器與網通＋資料中心基礎設施，2026-09-30）÷ 名目算力 | B16: US$B/GW | C16: =(43.206+6.333)/gw_0 -> 29.140588 | N16: 毛額 43.206＋6.333 ÷ 1.7；含 Hopper 舊機隊、機房可能部分租用 → 低於 Tokenomics
A18: B. SI 名目算力（GW，期末；IT 口徑）— 依 Tokenomics 世代錨分桶
A19: 項目 | B19: 單位 | C19: FY2025* | D19: 9M25A | E19: 9M26A | F19: Q4 26E | G19: FY2026E | H19: FY2027E | I19: FY2028E | J19: FY2029E | K19: FY2030E | L19: FY2031E | M19: FY2032E | N19: 說明
A20: SI 名目算力新增（FY2029 起收斂到 g × 期初 GW） | B20: GW | F20: =pace*0.25 -> 0.40675777 | G20: =F20 -> 0.40675777 | H20: =pace -> 1.6270311 | I20: =pace -> 1.6270311 | J20: =pace+(g_tv*I25-pace)*MIN(1,(2029-2028)/conv_mw) -> 1.2604794 | K20: =pace+(g_tv*J25-pace)*MIN(1,(2030-2028)/conv_mw) -> 0.91283502 | L20: =pace+(g_tv*K25-pace)*MIN(1,(2031-2028)/conv_mw) -> 0.57627579 | M20: =pace+(g_tv*L25-pace)*MIN(1,(2032-2028)/conv_mw) -> 0.2433123 | N20: Q4 26 與 FY2027–28＝pace（SI 投資季速 × 4 ÷ 每 GW 投資）；FY2029–32 線性收斂（同 Alphabet 修正一 F5）
A21: 期末 GW：Hopper 錨 | B21: GW | E21: =gw_0*mix0_h -> 0.51 | F21: =E21+F20*0 -> 0.51 | G21: =F21 -> 0.51 | H21: =F21+H20*0 -> 0.51 | I21: =H21+I20*0 -> 0.51 | J21: =I21+J20*0 -> 0.51 | K21: =J21+K20*0 -> 0.51 | L21: =K21+L20*0 -> 0.51 | M21: =L21+M20*0 -> 0.51 | N21: 評價日 1.7 GW × 機隊占比（mix0）；新增：2026 GB300 錨、2027 GB300／VR200 各半、2028 起 VR200 錨
A22: 期末 GW：GB200 錨 | B22: GW | E22: =gw_0*mix0_b2 -> 0.68 | F22: =E22+F20*0 -> 0.68 | G22: =F22 -> 0.68 | H22: =F22+H20*0 -> 0.68 | I22: =H22+I20*0 -> 0.68 | J22: =I22+J20*0 -> 0.68 | K22: =J22+K20*0 -> 0.68 | L22: =K22+L20*0 -> 0.68 | M22: =L22+M20*0 -> 0.68
A23: 期末 GW：GB300 錨 | B23: GW | E23: =gw_0*mix0_b3 -> 0.51 | F23: =E23+F20*1 -> 0.91675777 | G23: =F23 -> 0.91675777 | H23: =F23+H20*am_27 -> 1.7302733 | I23: =H23+I20*0 -> 1.7302733 | J23: =I23+J20*0 -> 1.7302733 | K23: =J23+K20*0 -> 1.7302733 | L23: =K23+L20*0 -> 1.7302733 | M23: =L23+M20*0 -> 1.7302733
A24: 期末 GW：VR200 錨 | B24: GW | E24: =gw_0*0 -> 0 | F24: =E24+F20*0 -> 0 | G24: =F24 -> 0 | H24: =F24+H20*(1-am_27) -> 0.81351553 | I24: =H24+I20*1 -> 2.4405466 | J24: =I24+J20*1 -> 3.701026 | K24: =J24+K20*1 -> 4.6138611 | L24: =K24+L20*1 -> 5.1901368 | M24: =L24+M20*1 -> 5.4334492
A25: 期末 SI 名目算力 | B25: GW | E25: =E21+E22+E23+E24 -> 1.7 | F25: =F21+F22+F23+F24 -> 2.1067578 | G25: =G21+G22+G23+G24 -> 2.1067578 | H25: =H21+H22+H23+H24 -> 3.7337888 | I25: =I21+I22+I23+I24 -> 5.3608199 | J25: =J21+J22+J23+J24 -> 6.6212993 | K25: =K21+K22+K23+K24 -> 7.5341344 | L25: =L21+L22+L23+L24 -> 8.1104101 | M25: =M21+M22+M23+M24 -> 8.3537224
A26: 平均在役 GW：Hopper 錨 | B26: GW | F26: =(E21+F21)/2 -> 0.51 | H26: =(F21+H21)/2 -> 0.51 | I26: =(H21+I21)/2 -> 0.51 | J26: =(I21+J21)/2 -> 0.51 | K26: =(J21+K21)/2 -> 0.51 | L26: =(K21+L21)/2 -> 0.51 | M26: =(L21+M21)/2 -> 0.51
A27: 平均在役 GW：GB200 錨 | B27: GW | F27: =(E22+F22)/2 -> 0.68 | H27: =(F22+H22)/2 -> 0.68 | I27: =(H22+I22)/2 -> 0.68 | J27: =(I22+J22)/2 -> 0.68 | K27: =(J22+K22)/2 -> 0.68 | L27: =(K22+L22)/2 -> 0.68 | M27: =(L22+M22)/2 -> 0.68
A28: 平均在役 GW：GB300 錨 | B28: GW | F28: =(E23+F23)/2 -> 0.71337888 | H28: =(F23+H23)/2 -> 1.3235155 | I28: =(H23+I23)/2 -> 1.7302733 | J28: =(I23+J23)/2 -> 1.7302733 | K28: =(J23+K23)/2 -> 1.7302733 | L28: =(K23+L23)/2 -> 1.7302733 | M28: =(L23+M23)/2 -> 1.7302733
A29: 平均在役 GW：VR200 錨 | B29: GW | F29: =(E24+F24)/2 -> 0 | H29: =(F24+H24)/2 -> 0.40675777 | I29: =(H24+I24)/2 -> 1.6270311 | J29: =(I24+J24)/2 -> 3.0707863 | K29: =(J24+K24)/2 -> 4.1574435 | L29: =(K24+L24)/2 -> 4.901999 | M29: =(L24+M24)/2 -> 5.311793
A30: 平均在役 GW | B30: GW | F30: =F26+F27+F28+F29 -> 1.9033789 | H30: =H26+H27+H28+H29 -> 2.9202733 | I30: =I26+I27+I28+I29 -> 4.5473044 | J30: =J26+J27+J28+J29 -> 5.9910596 | K30: =K26+K27+K28+K29 -> 7.0777168 | L30: =L26+L27+L28+L29 -> 7.8222723 | M30: =M26+M27+M28+M29 -> 8.2320663
A31: 平均在役 GW：對外出租（× ext_sh） | B31: GW | F31: =F30*ext_sh -> 1.3704328 | H31: =H30*ext_sh -> 2.1025968 | I31: =I30*ext_sh -> 3.2740591 | J31: =J30*ext_sh -> 4.3135629 | K31: =K30*ext_sh -> 5.0959561 | L31: =L30*ext_sh -> 5.632036 | M31: =M30*ext_sh -> 5.9270877
A32: 平均在役 GW：自用（×(1 − ext_sh)） | B32: GW | F32: =F30*(1-ext_sh) -> 0.53294609 | H32: =H30*(1-ext_sh) -> 0.81767652 | I32: =I30*(1-ext_sh) -> 1.2732452 | J32: =J30*(1-ext_sh) -> 1.6774967 | K32: =K30*(1-ext_sh) -> 1.9817607 | L32: =L30*(1-ext_sh) -> 2.1902362 | M32: =M30*(1-ext_sh) -> 2.3049786
A33: 在役機隊每 GW 年持有成本（IF_HoldEcon 依平均在役 GW 加權） | B33: US$B/GW-年 | F33: =(F26*he_h+F27*he_b2+F28*he_b3+F29*he_vr)/F30 -> 9.8340183 | H33: =(H26*he_h+H27*he_b2+H28*he_b3+H29*he_vr)/H30 -> 10.386996 | I33: =(I26*he_h+I27*he_b2+I28*he_b3+I29*he_vr)/I30 -> 10.925025 | J33: =(J26*he_h+J27*he_b2+J28*he_b3+J29*he_vr)/J30 -> 11.238413 | K33: =(K26*he_h+K27*he_b2+K28*he_b3+K29*he_vr)/K30 -> 11.389958 | L33: =(L26*he_h+L27*he_b2+L28*he_b3+L29*he_vr)/L30 -> 11.469486 | M33: =(M26*he_h+M27*he_b2+M28*he_b3+M29*he_vr)/M30 -> 11.507119 | N33: k × 本列＝每 GW 年營收（Seg 頁）；S2 核心問題的分母
A34: 在役機隊每 GW 年營運費用（IF_OpexGW 加權） | B34: US$B/GW-年 | F34: =(F26*opx_h+F27*opx_b2+F28*opx_b3+F29*opx_vr)/F30 -> 1.8955073 | H34: =(H26*opx_h+H27*opx_b2+H28*opx_b3+H29*opx_vr)/H30 -> 1.9412882 | I34: =(I26*opx_h+I27*opx_b2+I28*opx_b3+I29*opx_vr)/I30 -> 1.9858317 | J34: =(J26*opx_h+J27*opx_b2+J28*opx_b3+J29*opx_vr)/J30 -> 2.011777 | K34: =(K26*opx_h+K27*opx_b2+K28*opx_b3+K29*opx_vr)/K30 -> 2.0243235 | L34: =(L26*opx_h+L27*opx_b2+L28*opx_b3+L29*opx_vr)/L30 -> 2.0309075 | M34: =(M26*opx_h+M27*opx_b2+M28*opx_b3+M29*opx_vr)/M30 -> 2.0340232
A35: 對外出租營運費用（對外 GW × 營運費用；含電費） | B35: US$B | F35: =F31*F34*0.25 -> 0.64941633 | G35: =F35 -> 0.64941633 | H35: =H31*H34*1 -> 4.0817464 | I35: =I31*I34*1 -> 6.5017303 | J35: =J31*J34*1 -> 8.6779269 | K35: =K31*K34*1 -> 10.315864 | L35: =L31*L34*1 -> 11.438144 | M35: =M31*M34*1 -> 12.055834
A36: 自用增量營運費用（相對評價日自用機隊；Tokenomics IF_OpexGW） | B36: US$B | F36: =(1-ext_sh)*((F26*opx_h+F27*opx_b2+F28*opx_b3+F29*opx_vr)-($E$21*opx_h+$E$22*opx_b2+$E$23*opx_b3+$E$24*opx_vr))*0.25 -> 0.028225824 | G36: =F36 -> 0.028225824 | H36: =(1-ext_sh)*((H26*opx_h+H27*opx_b2+H28*opx_b3+H29*opx_vr)-($E$21*opx_h+$E$22*opx_b2+$E$23*opx_b3+$E$24*opx_vr))*1 -> 0.69004594 | I36: =(1-ext_sh)*((I26*opx_h+I27*opx_b2+I28*opx_b3+I29*opx_vr)-($E$21*opx_h+$E$22*opx_b2+$E$23*opx_b3+$E$24*opx_vr))*1 -> 1.6311508 | J36: =(1-ext_sh)*((J26*opx_h+J27*opx_b2+J28*opx_b3+J29*opx_vr)-($E$21*opx_h+$E$22*opx_b2+$E$23*opx_b3+$E$24*opx_vr))*1 -> 2.4774495 | K36: =(1-ext_sh)*((K26*opx_h+K27*opx_b2+K28*opx_b3+K29*opx_vr)-($E$21*opx_h+$E$22*opx_b2+$E$23*opx_b3+$E$24*opx_vr))*1 -> 3.1144248 | L36: =(1-ext_sh)*((L26*opx_h+L27*opx_b2+L28*opx_b3+L29*opx_vr)-($E$21*opx_h+$E$22*opx_b2+$E$23*opx_b3+$E$24*opx_vr))*1 -> 3.5508674 | M36: =(1-ext_sh)*((M26*opx_h+M27*opx_b2+M28*opx_b3+M29*opx_vr)-($E$21*opx_h+$E$22*opx_b2+$E$23*opx_b3+$E$24*opx_vr))*1 -> 3.79108 | N36: 評價日自用機隊的營運費用已在 2026Q3 校準的 SI 其他 EBITDA 率內
A38: C. SI 投資（新增 GW × Tokenomics 每 GW 成本；汰換只換 IT；含以其他融資取得之 PP&E）
A39: SI IT 投資（成長） | B39: US$B | F39: =F20*(1*cit_b3+0*cit_vr) -> 13.112741 | G39: =F39 -> 13.112741 | H39: =H20*(am_27*cit_b3+(1-am_27)*cit_vr) -> 56.802564 | I39: =I20*(0*cit_b3+1*cit_vr) -> 61.154162 | J39: =J20*(0*cit_b3+1*cit_vr) -> 47.376824 | K39: =K20*(0*cit_b3+1*cit_vr) -> 34.310138 | L39: =L20*(0*cit_b3+1*cit_vr) -> 21.660105 | M39: =M20*(0*cit_b3+1*cit_vr) -> 9.1452219
A40: SI 機房投資（自建比例 × IF_CapexFacility） | B40: US$B | F40: =F20*selfb*cfac -> 4.6382588 | G40: =F40 -> 4.6382588 | H40: =H20*selfb*cfac -> 18.553035 | I40: =I20*selfb*cfac -> 18.553035 | J40: =J20*selfb*cfac -> 14.373247 | K40: =K20*selfb*cfac -> 10.409058 | L40: =L20*selfb*cfac -> 6.5712728 | M40: =M20*selfb*cfac -> 2.7744902
A41: 汰換 GW（6 年前上線，換成 VR200 錨 IT） | B41: GW | F41: 0 | G41: =F41 -> 0 | H41: 0 | I41: 0 | J41: 0 | K41: =gw_ye24 -> 0.15 | L41: =gw_ye25-gw_ye24 -> 0.65 | M41: =gw_0-gw_ye25+F20 -> 1.3067578 | N41: IT 壽命 6 年：2024 年底在役 → 2030 汰換，以此類推；汰換後 GW 照常在役
A42: SI 汰換投資（只含 IT） | B42: US$B | F42: =F41*cit_vr -> 0 | G42: =F42 -> 0 | H42: =H41*cit_vr -> 0 | I42: =I41*cit_vr -> 0 | J42: =J41*cit_vr -> 0 | K42: =K41*cit_vr -> 5.6379528 | L42: =L41*cit_vr -> 24.431129 | M42: =M41*cit_vr -> 49.116257
A43: SI 投資合計（現金資本支出＋以其他融資取得） | B43: US$B | E43: =Q!H37+ppefin_9m -> 43.916 | F43: =F39+F40+F42 -> 17.751 | G43: =E43+F43 -> 61.667 | H43: =H39+H40+H42 -> 75.355599 | I43: =I39+I40+I42 -> 79.707197 | J43: =J39+J40+J42 -> 61.750071 | K43: =K39+K40+K42 -> 50.357149 | L43: =L39+L40+L42 -> 52.662506 | M43: =M39+M40+M42 -> 61.035969 | N43: 9M26＝SI 資本支出 39.995＋以其他融資取得 3.921（推定全屬 SI）
A44: 其中：SI 現金資本支出（×(1 − fin_sh)） | B44: US$B | E44: =Q!H37 -> 39.995 | F44: =F43*(1-fin_sh) -> 16.165836 | G44: =E44+F44 -> 56.160836 | H44: =H43*(1-fin_sh) -> 68.626344 | I44: =I43*(1-fin_sh) -> 72.589345 | J44: =J43*(1-fin_sh) -> 56.23579 | K44: =K43*(1-fin_sh) -> 45.860256 | L44: =L43*(1-fin_sh) -> 47.959744 | M44: =M43*(1-fin_sh) -> 55.585457
A45: 其中：以其他融資取得 PP&E（× fin_sh；非現金） | B45: US$B | E45: =ppefin_9m -> 3.921 | F45: =F43*fin_sh -> 1.5851643 | G45: =E45+F45 -> 5.5061643 | H45: =H43*fin_sh -> 6.729255 | I45: =I43*fin_sh -> 7.1178527 | J45: =J43*fin_sh -> 5.5142814 | K45: =K43*fin_sh -> 4.4968934 | L45: =L43*fin_sh -> 4.7027618 | M45: =M43*fin_sh -> 5.4505121
A46: 對照：SI 投資 ÷ 新增 GW | B46: US$B/GW | F46: =IF(F20>0,(F39+F40)/F20,0) -> 43.640224 | H46: =IF(H20>0,(H39+H40)/H20,0) -> 46.314788 | I46: =IF(I20>0,(I39+I40)/I20,0) -> 48.989352 | J46: =IF(J20>0,(J39+J40)/J20,0) -> 48.989352 | K46: =IF(K20>0,(K39+K40)/K20,0) -> 48.989352 | L46: =IF(L20>0,(L39+L40)/L20,0) -> 48.989352 | M46: =IF(M20>0,(M39+M40)/M20,0) -> 48.989352
A48: D. 新增 AI 折舊（在建工程與新增投資依年限直線攤提；評價日在役資產的折舊見 E 節基礎折舊）
A49: 在建工程轉入（SI）：IT（2026 年度批次） | B49: US$B | F49: =cip_0*cip_si*cip_it -> 16.1466 | N49: 同 Alphabet 修正三：在建工程為已付資產，照時程折舊、不另增 GW（判斷題）
A50: 在建工程轉入（SI）：機房 | B50: US$B | F50: =cip_0*cip_si*(1-cip_it) -> 4.03665
A51: IT 批次金額（成長＋汰換） | B51: US$B | F51: =F39+F42 -> 13.112741 | H51: =H39+H42 -> 56.802564 | I51: =I39+I42 -> 61.154162 | J51: =J39+J42 -> 47.376824 | K51: =K39+K42 -> 39.948091 | L51: =L39+L42 -> 46.091233 | M51: =M39+M42 -> 58.261479
A52: 機房批次金額 | B52: US$B | F52: =F40 -> 4.6382588 | H52: =H40 -> 18.553035 | I52: =I40 -> 18.553035 | J52: =J40 -> 14.373247 | K52: =K40 -> 10.409058 | L52: =L40 -> 6.5712728 | M52: =M40 -> 2.7744902
A53: 新增 AI 折舊：IT | B53: US$B | F53: =($F$49/life_it*IF((0)<0,0,IF((0)=0,phi_0,IF((0)<life_it,1,IF((0)=life_it,1-phi_0,0))))+$F$51/life_it*IF((0)<0,0,IF((0)=0,phi_0,IF((0)<life_it,1,IF((0)=life_it,1-phi_0,0)))))*0.25 -> 0.3047848 | G53: =F53 -> 0.3047848 | H53: =($F$49/life_it*IF((1)<0,0,IF((1)=0,phi_0,IF((1)<life_it,1,IF((1)=life_it,1-phi_0,0))))+$F$51/life_it*IF((1)<0,0,IF((1)=0,phi_0,IF((1)<life_it,1,IF((1)=life_it,1-phi_0,0))))+$H$51/life_it*IF((0)<0,0,IF((0)=0,phi_0,IF((0)<life_it,1,IF((0)=life_it,1-phi_0,0))))) -> 7.2433303 | I53: =($F$49/life_it*IF((2)<0,0,IF((2)=0,phi_0,IF((2)<life_it,1,IF((2)=life_it,1-phi_0,0))))+$F$51/life_it*IF((2)<0,0,IF((2)=0,phi_0,IF((2)<life_it,1,IF((2)=life_it,1-phi_0,0))))+$H$51/life_it*IF((1)<0,0,IF((1)=0,phi_0,IF((1)<life_it,1,IF((1)=life_it,1-phi_0,0))))+$I$51/life_it*IF((0)<0,0,IF((0)=0,phi_0,IF((0)<life_it,1,IF((0)=life_it,1-phi_0,0))))) -> 16.891741 | J53: =($F$49/life_it*IF((3)<0,0,IF((3)=0,phi_0,IF((3)<life_it,1,IF((3)=life_it,1-phi_0,0))))+$F$51/life_it*IF((3)<0,0,IF((3)=0,phi_0,IF((3)<life_it,1,IF((3)=life_it,1-phi_0,0))))+$H$51/life_it*IF((2)<0,0,IF((2)=0,phi_0,IF((2)<life_it,1,IF((2)=life_it,1-phi_0,0))))+$I$51/life_it*IF((1)<0,0,IF((1)=0,phi_0,IF((1)<life_it,1,IF((1)=life_it,1-phi_0,0))))+$J$51/life_it*IF((0)<0,0,IF((0)=0,phi_0,IF((0)<life_it,1,IF((0)=life_it,1-phi_0,0))))) -> 26.510045 | K53: =($F$49/life_it*IF((4)<0,0,IF((4)=0,phi_0,IF((4)<life_it,1,IF((4)=life_it,1-phi_0,0))))+$F$51/life_it*IF((4)<0,0,IF((4)=0,phi_0,IF((4)<life_it,1,IF((4)=life_it,1-phi_0,0))))+$H$51/life_it*IF((3)<0,0,IF((3)=0,phi_0,IF((3)<life_it,1,IF((3)=life_it,1-phi_0,0))))+$I$51/life_it*IF((2)<0,0,IF((2)=0,phi_0,IF((2)<life_it,1,IF((2)=life_it,1-phi_0,0))))+$J$51/life_it*IF((1)<0,0,IF((1)=0,phi_0,IF((1)<life_it,1,IF((1)=life_it,1-phi_0,0))))+$K$51/life_it*IF((0)<0,0,IF((0)=0,phi_0,IF((0)<life_it,1,IF((0)=life_it,1-phi_0,0))))) -> 34.096652 | L53: =($F$49/life_it*IF((5)<0,0,IF((5)=0,phi_0,IF((5)<life_it,1,IF((5)=life_it,1-phi_0,0))))+$F$51/life_it*IF((5)<0,0,IF((5)=0,phi_0,IF((5)<life_it,1,IF((5)=life_it,1-phi_0,0))))+$H$51/life_it*IF((4)<0,0,IF((4)=0,phi_0,IF((4)<life_it,1,IF((4)=life_it,1-phi_0,0))))+$I$51/life_it*IF((3)<0,0,IF((3)=0,phi_0,IF((3)<life_it,1,IF((3)=life_it,1-phi_0,0))))+$J$51/life_it*IF((2)<0,0,IF((2)=0,phi_0,IF((2)<life_it,1,IF((2)=life_it,1-phi_0,0))))+$K$51/life_it*IF((1)<0,0,IF((1)=0,phi_0,IF((1)<life_it,1,IF((1)=life_it,1-phi_0,0))))+$L$51/life_it*IF((0)<0,0,IF((0)=0,phi_0,IF((0)<life_it,1,IF((0)=life_it,1-phi_0,0))))) -> 41.010632 | M53: =($F$49/life_it*IF((6)<0,0,IF((6)=0,phi_0,IF((6)<life_it,1,IF((6)=life_it,1-phi_0,0))))+$F$51/life_it*IF((6)<0,0,IF((6)=0,phi_0,IF((6)<life_it,1,IF((6)=life_it,1-phi_0,0))))+$H$51/life_it*IF((5)<0,0,IF((5)=0,phi_0,IF((5)<life_it,1,IF((5)=life_it,1-phi_0,0))))+$I$51/life_it*IF((4)<0,0,IF((4)=0,phi_0,IF((4)<life_it,1,IF((4)=life_it,1-phi_0,0))))+$J$51/life_it*IF((3)<0,0,IF((3)=0,phi_0,IF((3)<life_it,1,IF((3)=life_it,1-phi_0,0))))+$K$51/life_it*IF((2)<0,0,IF((2)=0,phi_0,IF((2)<life_it,1,IF((2)=life_it,1-phi_0,0))))+$L$51/life_it*IF((1)<0,0,IF((1)=0,phi_0,IF((1)<life_it,1,IF((1)=life_it,1-phi_0,0))))+$M$51/life_it*IF((0)<0,0,IF((0)=0,phi_0,IF((0)<life_it,1,IF((0)=life_it,1-phi_0,0))))) -> 47.980458 | N53: Q4 26 欄＝年折舊 × 0.25
A54: 新增 AI 折舊：機房 | B54: US$B | F54: =($F$50/life_fac*IF((0)<0,0,IF((0)=0,phi_0,IF((0)<life_fac,1,IF((0)=life_fac,1-phi_0,0))))+$F$52/life_fac*IF((0)<0,0,IF((0)=0,phi_0,IF((0)<life_fac,1,IF((0)=life_fac,1-phi_0,0)))))*0.25 -> 0.02710909 | G54: =F54 -> 0.02710909 | H54: =($F$50/life_fac*IF((1)<0,0,IF((1)=0,phi_0,IF((1)<life_fac,1,IF((1)=life_fac,1-phi_0,0))))+$F$52/life_fac*IF((1)<0,0,IF((1)=0,phi_0,IF((1)<life_fac,1,IF((1)=life_fac,1-phi_0,0))))+$H$52/life_fac*IF((0)<0,0,IF((0)=0,phi_0,IF((0)<life_fac,1,IF((0)=life_fac,1-phi_0,0))))) -> 0.66565838 | I54: =($F$50/life_fac*IF((2)<0,0,IF((2)=0,phi_0,IF((2)<life_fac,1,IF((2)=life_fac,1-phi_0,0))))+$F$52/life_fac*IF((2)<0,0,IF((2)=0,phi_0,IF((2)<life_fac,1,IF((2)=life_fac,1-phi_0,0))))+$H$52/life_fac*IF((1)<0,0,IF((1)=0,phi_0,IF((1)<life_fac,1,IF((1)=life_fac,1-phi_0,0))))+$I$52/life_fac*IF((0)<0,0,IF((0)=0,phi_0,IF((0)<life_fac,1,IF((0)=life_fac,1-phi_0,0))))) -> 1.5933101 | J54: =($F$50/life_fac*IF((3)<0,0,IF((3)=0,phi_0,IF((3)<life_fac,1,IF((3)=life_fac,1-phi_0,0))))+$F$52/life_fac*IF((3)<0,0,IF((3)=0,phi_0,IF((3)<life_fac,1,IF((3)=life_fac,1-phi_0,0))))+$H$52/life_fac*IF((2)<0,0,IF((2)=0,phi_0,IF((2)<life_fac,1,IF((2)=life_fac,1-phi_0,0))))+$I$52/life_fac*IF((1)<0,0,IF((1)=0,phi_0,IF((1)<life_fac,1,IF((1)=life_fac,1-phi_0,0))))+$J$52/life_fac*IF((0)<0,0,IF((0)=0,phi_0,IF((0)<life_fac,1,IF((0)=life_fac,1-phi_0,0))))) -> 2.4687145 | K54: =($F$50/life_fac*IF((4)<0,0,IF((4)=0,phi_0,IF((4)<life_fac,1,IF((4)=life_fac,1-phi_0,0))))+$F$52/life_fac*IF((4)<0,0,IF((4)=0,phi_0,IF((4)<life_fac,1,IF((4)=life_fac,1-phi_0,0))))+$H$52/life_fac*IF((3)<0,0,IF((3)=0,phi_0,IF((3)<life_fac,1,IF((3)=life_fac,1-phi_0,0))))+$I$52/life_fac*IF((2)<0,0,IF((2)=0,phi_0,IF((2)<life_fac,1,IF((2)=life_fac,1-phi_0,0))))+$J$52/life_fac*IF((1)<0,0,IF((1)=0,phi_0,IF((1)<life_fac,1,IF((1)=life_fac,1-phi_0,0))))+$K$52/life_fac*IF((0)<0,0,IF((0)=0,phi_0,IF((0)<life_fac,1,IF((0)=life_fac,1-phi_0,0))))) -> 3.1378245 | L54: =($F$50/life_fac*IF((5)<0,0,IF((5)=0,phi_0,IF((5)<life_fac,1,IF((5)=life_fac,1-phi_0,0))))+$F$52/life_fac*IF((5)<0,0,IF((5)=0,phi_0,IF((5)<life_fac,1,IF((5)=life_fac,1-phi_0,0))))+$H$52/life_fac*IF((4)<0,0,IF((4)=0,phi_0,IF((4)<life_fac,1,IF((4)=life_fac,1-phi_0,0))))+$I$52/life_fac*IF((3)<0,0,IF((3)=0,phi_0,IF((3)<life_fac,1,IF((3)=life_fac,1-phi_0,0))))+$J$52/life_fac*IF((2)<0,0,IF((2)=0,phi_0,IF((2)<life_fac,1,IF((2)=life_fac,1-phi_0,0))))+$K$52/life_fac*IF((1)<0,0,IF((1)=0,phi_0,IF((1)<life_fac,1,IF((1)=life_fac,1-phi_0,0))))+$L$52/life_fac*IF((0)<0,0,IF((0)=0,phi_0,IF((0)<life_fac,1,IF((0)=life_fac,1-phi_0,0))))) -> 3.6103051 | M54: =($F$50/life_fac*IF((6)<0,0,IF((6)=0,phi_0,IF((6)<life_fac,1,IF((6)=life_fac,1-phi_0,0))))+$F$52/life_fac*IF((6)<0,0,IF((6)=0,phi_0,IF((6)<life_fac,1,IF((6)=life_fac,1-phi_0,0))))+$H$52/life_fac*IF((5)<0,0,IF((5)=0,phi_0,IF((5)<life_fac,1,IF((5)=life_fac,1-phi_0,0))))+$I$52/life_fac*IF((4)<0,0,IF((4)=0,phi_0,IF((4)<life_fac,1,IF((4)=life_fac,1-phi_0,0))))+$J$52/life_fac*IF((3)<0,0,IF((3)=0,phi_0,IF((3)<life_fac,1,IF((3)=life_fac,1-phi_0,0))))+$K$52/life_fac*IF((2)<0,0,IF((2)=0,phi_0,IF((2)<life_fac,1,IF((2)=life_fac,1-phi_0,0))))+$L$52/life_fac*IF((1)<0,0,IF((1)=0,phi_0,IF((1)<life_fac,1,IF((1)=life_fac,1-phi_0,0))))+$M$52/life_fac*IF((0)<0,0,IF((0)=0,phi_0,IF((0)<life_fac,1,IF((0)=life_fac,1-phi_0,0))))) -> 3.891409
A55: 新增 AI 折舊合計 | B55: US$B | F55: =F53+F54 -> 0.33189389 | G55: =G53+G54 -> 0.33189389 | H55: =H53+H54 -> 7.9089887 | I55: =I53+I54 -> 18.485051 | J55: =J53+J54 -> 28.97876 | K55: =K53+K54 -> 37.234477 | L55: =L53+L54 -> 44.620937 | M55: =M53+M54 -> 51.871867
A56: 其中：對外（× ext_sh） | B56: US$B | F56: =F55*ext_sh -> 0.2389636 | G56: =G55*ext_sh -> 0.2389636 | H56: =H55*ext_sh -> 5.6944719 | I56: =I55*ext_sh -> 13.309237 | J56: =J55*ext_sh -> 20.864707 | K56: =K55*ext_sh -> 26.808823 | L56: =L55*ext_sh -> 32.127075 | M56: =M55*ext_sh -> 37.347744
A57: 其中：自用（×(1 − ext_sh)） | B57: US$B | F57: =F55*(1-ext_sh) -> 0.09293029 | G57: =G55*(1-ext_sh) -> 0.09293029 | H57: =H55*(1-ext_sh) -> 2.2145168 | I57: =I55*(1-ext_sh) -> 5.1758143 | J57: =J55*(1-ext_sh) -> 8.1140528 | K57: =K55*(1-ext_sh) -> 10.425654 | L57: =L55*(1-ext_sh) -> 12.493862 | M57: =M55*(1-ext_sh) -> 14.524123
A59: E. SI 評價日在役資產的基礎折舊（隨期初機隊汰換遞減）
A60: 累計已汰換的期初機隊 GW（當年以半年計） | B60: GW | F60: =mid*F41 -> 0 | G60: =F60 -> 0 | H60: =F41+mid*H41 -> 0 | I60: =F41+H41+mid*I41 -> 0 | J60: =F41+H41+I41+mid*J41 -> 0 | K60: =F41+H41+I41+J41+mid*K41 -> 0.075 | L60: =F41+H41+I41+J41+K41+mid*L41 -> 0.475 | M60: =F41+H41+I41+J41+K41+L41+mid*M41 -> 1.4533789
A61: 期初機隊每 GW IT 年折舊（Tokenomics IF_DeprIT 依期初占比加權） | B61: US$B/GW-年 | E61: =mix0_h*dpi_h+mix0_b2*dpi_b2+mix0_b3*dpi_b3 -> 4.5883835
A62: SI 基礎折舊＝da_si0 − MIN(da_si0 × IT 占比, 累計汰換 GW × 每 GW IT 折舊) | B62: US$B | F62: =(da_si0-MIN(da_si0*it_sh_da,F60*$E$61))*0.25 -> 2.473 | G62: =F62 -> 2.473 | H62: =(da_si0-MIN(da_si0*it_sh_da,H60*$E$61))*1 -> 9.892 | I62: =(da_si0-MIN(da_si0*it_sh_da,I60*$E$61))*1 -> 9.892 | J62: =(da_si0-MIN(da_si0*it_sh_da,J60*$E$61))*1 -> 9.892 | K62: =(da_si0-MIN(da_si0*it_sh_da,K60*$E$61))*1 -> 9.5478712 | L62: =(da_si0-MIN(da_si0*it_sh_da,L60*$E$61))*1 -> 7.7125178 | M62: =(da_si0-MIN(da_si0*it_sh_da,M60*$E$61))*1 -> 3.2233403 | N62: 2026Q3 SI 折舊攤銷 2.473 × 4（含 X 無形資產攤銷）；期初機隊汰換後由新購 IT 折舊取代
A64: F. 自用 AI（讀法 2 影子效益：自用增量 GW × Tokenomics 持有成本，k＝1；非財報營收）
A65: 自用 AI 影子效益（自用增量 GW × IF_HoldEcon） | B65: US$B | F65: =(1-ext_sh)*((F26*he_h+F27*he_b2+F28*he_b3+F29*he_vr)-($E$21*he_h+$E$22*he_b2+$E$23*he_b3+$E$24*he_vr))*0.25 -> 0.15498463 | G65: =F65 -> 0.15498463 | H65: =(1-ext_sh)*((H26*he_h+H27*he_b2+H28*he_b3+H29*he_vr)-($E$21*he_h+$E$22*he_b2+$E$23*he_b3+$E$24*he_vr))*1 -> 3.8721395 | I65: =(1-ext_sh)*((I26*he_h+I27*he_b2+I28*he_b3+I29*he_vr)-($E$21*he_h+$E$22*he_b2+$E$23*he_b3+$E$24*he_vr))*1 -> 9.289173 | J65: =(1-ext_sh)*((J26*he_h+J27*he_b2+J28*he_b3+J29*he_vr)-($E$21*he_h+$E$22*he_b2+$E$23*he_b3+$E$24*he_vr))*1 -> 14.231338 | K65: =(1-ext_sh)*((K26*he_h+K27*he_b2+K28*he_b3+K29*he_vr)-($E$21*he_h+$E$22*he_b2+$E$23*he_b3+$E$24*he_vr))*1 -> 17.951109 | L65: =(1-ext_sh)*((L26*he_h+L27*he_b2+L28*he_b3+L29*he_vr)-($E$21*he_h+$E$22*he_b2+$E$23*he_b3+$E$24*he_vr))*1 -> 20.49982 | M65: =(1-ext_sh)*((M26*he_h+M27*he_b2+M28*he_b3+M29*he_vr)-($E$21*he_h+$E$22*he_b2+$E$23*he_b3+$E$24*he_vr))*1 -> 21.902599 | N65: 原則第 7 節讀法 2：只進評價口徑（PL「營業利益（評價口徑）」、Val）；營收列與分部對帳不動
A66: 自用 AI 增量成本（營運＋自用新增折舊） | B66: US$B | F66: =F36+F57 -> 0.12115611 | G66: =G36+G57 -> 0.12115611 | H66: =H36+H57 -> 2.9045628 | I66: =I36+I57 -> 6.8069651 | J66: =J36+J57 -> 10.591502 | K66: =K36+K57 -> 13.540078 | L66: =L36+L57 -> 16.04473 | M66: =M36+M57 -> 18.315203
A67: 影子效益 ÷ 自用 AI 增量成本 | B67: x | F67: =IF(F66>0,F65/F66,0) -> 1.2792142 | H67: =IF(H66>0,H65/H66,0) -> 1.333123 | I67: =IF(I66>0,I65/I66,0) -> 1.3646571 | J67: =IF(J66>0,J65/J66,0) -> 1.3436562 | K67: =IF(K66>0,K65/K66,0) -> 1.3257758 | L67: =IF(L66>0,L65/L66,0) -> 1.2776669 | M67: =IF(M66>0,M65/M66,0) -> 1.1958699 | N67: 接近 1＝價值中性（持有成本以 10% 資金成本回收資本）

Sheet Seg
A1: Seg — 營收分部層：官方分部 Space（Launch Services、Launch & Development）、Connectivity（Consumer、Enterprise & Government）、SI（Advertising、SI Solutions & Infrastructure）；SI S&I 之下的命題子列＝SI 對外雲端服務＋Grok／Cursor／X 訂閱、資料授權與 API（子列合計＝SI S&I）。情境軸：SI 每 GW 年營收的 k（FY2030 到達）與 Starlink 消費訂戶淨增
A2: 成長路徑：起始年增＝9M26 對 9M25 年增（Q 頁；近四季需 2025Q4，只有二手），FY2030 收斂到長期值（conv_n）。Space＝客戶發射 × 每次收入＋發射與開發；Connectivity＝平均消費訂戶 × ARPU × 3 × 係數（含 Kits）＋企業與政府；SI 對外出租＝對外 GW × k × 持有成本（Thesis）；SI 其他以 Q4 26 備考全季（含 Cursor 全季）為基期
A4: 情境 A（算力租金維持高檔、Starlink 增長快）
A5: 項目 | B5: 單位 | C5: FY2025* | D5: 9M25A | E5: 9M26A | F5: Q4 26E | G5: FY2026E | H5: FY2027E | I5: FY2028E | J5: FY2029E | K5: FY2030E | L5: FY2031E | M5: FY2032E | N5: 說明
A6: k＝每 GW 年營收 ÷ 持有成本（Q4 26＝校準 k0，FY2030＝情境值） | B6: x | F6: =k0 -> 1.8666125 | H6: =k0+(k30_A-k0)*MIN(1,(2027-2026)/conv_k) -> 1.7999594 | I6: =k0+(k30_A-k0)*MIN(1,(2028-2026)/conv_k) -> 1.7333063 | J6: =k0+(k30_A-k0)*MIN(1,(2029-2026)/conv_k) -> 1.6666531 | K6: =k0+(k30_A-k0)*MIN(1,(2030-2026)/conv_k) -> 1.6 | L6: =k0+(k30_A-k0)*MIN(1,(2031-2026)/conv_k) -> 1.6 | M6: =k0+(k30_A-k0)*MIN(1,(2032-2026)/conv_k) -> 1.6
A7: 對外每 GW 年營收＝k × 在役機隊持有成本 | B7: US$B/GW-年 | F7: =F6*Thesis!F33 -> 18.356302 | H7: =H6*Thesis!H33 -> 18.696171 | I7: =I6*Thesis!I33 -> 18.936414 | J7: =J6*Thesis!J33 -> 18.730536 | K7: =K6*Thesis!K33 -> 18.223933 | L7: =L6*Thesis!L33 -> 18.351177 | M7: =M6*Thesis!M33 -> 18.41139
A8: SI 對外雲端服務（命題子列） | B8: US$B | E8: =Thesis!C11 -> 6.63552 | F8: =Thesis!F31*F7*0.25 -> 6.2890195 | G8: =E8+F8 -> 12.924539 | H8: =Thesis!H31*H7*1 -> 39.310508 | I8: =Thesis!I31*I7*1 -> 61.998941 | J8: =Thesis!J31*J7*1 -> 80.795347 | K8: =Thesis!K31*K7*1 -> 92.868364 | L8: =Thesis!L31*L7*1 -> 103.35449 | M8: =Thesis!M31*M7*1 -> 109.12592 | N8: 對外 GW × 每 GW 年營收；9M26＝(Q2＋Q3 SI S&I) × ext_sh（Customer B 衍生）
A9: SI 其他收入年增 | B9: % | H9: =g27_nr+(gl_nr-g27_nr)*MIN(1,(2027-2027)/(conv_n-1)) -> 0.5 | I9: =g27_nr+(gl_nr-g27_nr)*MIN(1,(2028-2027)/(conv_n-1)) -> 0.38333333 | J9: =g27_nr+(gl_nr-g27_nr)*MIN(1,(2029-2027)/(conv_n-1)) -> 0.26666667 | K9: =g27_nr+(gl_nr-g27_nr)*MIN(1,(2030-2027)/(conv_n-1)) -> 0.15 | L9: =g27_nr+(gl_nr-g27_nr)*MIN(1,(2031-2027)/(conv_n-1)) -> 0.15 | M9: =g27_nr+(gl_nr-g27_nr)*MIN(1,(2032-2027)/(conv_n-1)) -> 0.15 | N9: FY2027＝g27_nr（以 Q4 26 備考年化為基期），FY2030 收斂到 gl_nr
A10: Grok／Cursor／X 訂閱、資料授權與 API（命題子列） | B10: US$B | E10: =Q!H14-E8 -> 3.05548 | F10: =nr_q3+cur_pf -> 2.50516 | G10: =E10+F10 -> 5.56064 | H10: =F10*4*(1+H9)^0.625 -> 12.91078 | I10: =H10*(1+I9) -> 17.859913 | J10: =I10*(1+J9) -> 22.622556 | K10: =J10*(1+K9) -> 26.01594 | L10: =K10*(1+L9) -> 29.918331 | M10: =L10*(1+M9) -> 34.406081 | N10: Q4 26＝2026Q3 值＋Cursor 備考補足（審查第 8 條：以備考全季為起點）；FY2027＝Q4 26 × 4 ×(1＋年增)^0.625
A11: SI Solutions & Infrastructure | B11: US$B | D11: =Q!G14 -> 0.955 | E11: =Q!H14 -> 9.691 | F11: =F8+F10 -> 8.7941795 | G11: =E11+F11 -> 18.485179 | H11: =H8+H10 -> 52.221288 | I11: =I8+I10 -> 79.858854 | J11: =J8+J10 -> 103.4179 | K11: =K8+K10 -> 118.8843 | L11: =L8+L10 -> 133.27282 | M11: =M8+M10 -> 143.532
A12: Advertising 年增 | B12: % | F12: =g0_ads -> -0.056689342 | H12: =g0_ads+(gl_ads-g0_ads)*MIN(1,(2027-2026)/conv_n) -> -0.035017007 | I12: =g0_ads+(gl_ads-g0_ads)*MIN(1,(2028-2026)/conv_n) -> -0.013344671 | J12: =g0_ads+(gl_ads-g0_ads)*MIN(1,(2029-2026)/conv_n) -> 0.0083276644 | K12: =g0_ads+(gl_ads-g0_ads)*MIN(1,(2030-2026)/conv_n) -> 0.03 | L12: =g0_ads+(gl_ads-g0_ads)*MIN(1,(2031-2026)/conv_n) -> 0.03 | M12: =g0_ads+(gl_ads-g0_ads)*MIN(1,(2032-2026)/conv_n) -> 0.03 | N12: 起點＝9M 年增（Q 頁），FY2030 收斂到 gl_ads
A13: Advertising | B13: US$B | D13: =Q!G13 -> 1.323 | E13: =Q!H13 -> 1.248 | F13: =ads_q3*(1+F12)^0.25 -> 0.53020762 | G13: =E13+F13 -> 1.7782076 | H13: =G13*(1+H12) -> 1.7159401 | I13: =H13*(1+I12) -> 1.6930415 | J13: =I13*(1+J12) -> 1.7071405 | K13: =J13*(1+K12) -> 1.7583547 | L13: =K13*(1+L12) -> 1.8111054 | M13: =L13*(1+M12) -> 1.8654386
A14: SI (Super Intelligence; formerly AI) | B14: US$B | C14: =Q!I15 -> 3.201 | D14: =Q!G15 -> 2.278 | E14: =Q!H15 -> 10.939 | F14: =F13+F11 -> 9.3243871 | G14: =E14+F14 -> 20.263387 | H14: =H13+H11 -> 53.937229 | I14: =I13+I11 -> 81.551895 | J14: =J13+J11 -> 105.12504 | K14: =K13+K11 -> 120.64266 | L14: =L13+L11 -> 135.08393 | M14: =M13+M11 -> 145.39744
A15: 客戶發射次數 | B15: 次 | E15: =Q!H57 -> 29 | F15: =nl_q4 -> 12 | G15: =E15+F15 -> 41 | H15: =nl_27 -> 48 | I15: =H15*(1+g_nl) -> 50.4 | J15: =I15*(1+g_nl) -> 52.92 | K15: =J15*(1+g_nl) -> 55.566 | L15: =K15*(1+g_nl) -> 58.3443 | M15: =L15*(1+g_nl) -> 61.261515
A16: 每次客戶發射收入 | B16: US$B／次 | E16: =rpl0 -> 0.072689655 | F16: =rpl0 -> 0.072689655 | H16: =rpl0*(1+g_rpl)^(2027-2026) -> 0.074870345 | I16: =rpl0*(1+g_rpl)^(2028-2026) -> 0.077116455 | J16: =rpl0*(1+g_rpl)^(2029-2026) -> 0.079429949 | K16: =rpl0*(1+g_rpl)^(2030-2026) -> 0.081812847 | L16: =rpl0*(1+g_rpl)^(2031-2026) -> 0.084267233 | M16: =rpl0*(1+g_rpl)^(2032-2026) -> 0.08679525
A17: Launch Services | B17: US$B | D17: =Q!G5 -> 2.056 | E17: =Q!H5 -> 2.108 | F17: =F15*F16 -> 0.87227586 | G17: =E17+F17 -> 2.9802759 | H17: =H15*H16 -> 3.5937766 | I17: =I15*I16 -> 3.8866693 | J17: =J15*J16 -> 4.2034329 | K17: =K15*K16 -> 4.5460127 | L17: =L15*L16 -> 4.9165127 | M17: =M15*M16 -> 5.3172085
A18: Launch & Development 年增 | B18: % | F18: =g0_ld -> 0.015561016 | H18: =g0_ld+(gl_ld-g0_ld)*MIN(1,(2027-2026)/conv_n) -> 0.031670762 | I18: =g0_ld+(gl_ld-g0_ld)*MIN(1,(2028-2026)/conv_n) -> 0.047780508 | J18: =g0_ld+(gl_ld-g0_ld)*MIN(1,(2029-2026)/conv_n) -> 0.063890254 | K18: =g0_ld+(gl_ld-g0_ld)*MIN(1,(2030-2026)/conv_n) -> 0.08 | L18: =g0_ld+(gl_ld-g0_ld)*MIN(1,(2031-2026)/conv_n) -> 0.08 | M18: =g0_ld+(gl_ld-g0_ld)*MIN(1,(2032-2026)/conv_n) -> 0.08
A19: Launch & Development | B19: US$B | D19: =Q!G6 -> 1.221 | E19: =Q!H6 -> 1.24 | F19: =ld_9m/3*(1+F18)^0.25 -> 0.41493201 | G19: =E19+F19 -> 1.654932 | H19: =G19*(1+H18) -> 1.707345 | I19: =H19*(1+I18) -> 1.7889228 | J19: =I19*(1+J18) -> 1.9032175 | K19: =J19*(1+K18) -> 2.0554749 | L19: =K19*(1+L18) -> 2.2199129 | M19: =L19*(1+M18) -> 2.3975059 | N19: Q4 26＝9M26 季均 ×(1＋年增)^0.25（里程碑收入不規則）
A20: Space | B20: US$B | C20: =Q!I7 -> 4.086 | D20: =Q!G7 -> 3.277 | E20: =Q!H7 -> 3.348 | F20: =F17+F19 -> 1.2872079 | G20: =E20+F20 -> 4.6352079 | H20: =H17+H19 -> 5.3011215 | I20: =I17+I19 -> 5.6755921 | J20: =J17+J19 -> 6.1066504 | K20: =K17+K19 -> 6.6014876 | L20: =L17+L19 -> 7.1364256 | M20: =M17+M19 -> 7.7147144
A21: Starlink 消費訂戶（期末，百萬） | B21: 百萬 | E21: =subs_q3 -> 13.6 | F21: =E21+nadd_q4 -> 15.2 | H21: =F21+nadd_A -> 22.2 | I21: =H21+nadd_A*(1-nadd_dec)^(2028-2027) -> 28.5 | J21: =I21+nadd_A*(1-nadd_dec)^(2029-2027) -> 34.17 | K21: =J21+nadd_A*(1-nadd_dec)^(2030-2027) -> 39.273 | L21: =K21+nadd_A*(1-nadd_dec)^(2031-2027) -> 43.8657 | M21: =L21+nadd_A*(1-nadd_dec)^(2032-2027) -> 47.99913
A22: 平均消費訂戶 | B22: 百萬 | F22: =(E21+F21)/2 -> 14.4 | H22: =(F21+H21)/2 -> 18.7 | I22: =(H21+I21)/2 -> 25.35 | J22: =(I21+J21)/2 -> 31.335 | K22: =(J21+K21)/2 -> 36.7215 | L22: =(K21+L21)/2 -> 41.56935 | M22: =(L21+M21)/2 -> 45.932415
A23: 消費 ARPU（美元／月） | B23: US$ | F23: =arpu0*(1+g_arpu)^0.25 -> 68.652382 | H23: =arpu0*(1+g_arpu)^(2027+0.5-2026.75) -> 67.962391 | I23: =arpu0*(1+g_arpu)^(2028+0.5-2026.75) -> 66.603143 | J23: =arpu0*(1+g_arpu)^(2029+0.5-2026.75) -> 65.27108 | K23: =arpu0*(1+g_arpu)^(2030+0.5-2026.75) -> 63.965658 | L23: =arpu0*(1+g_arpu)^(2031+0.5-2026.75) -> 62.686345 | M23: =arpu0*(1+g_arpu)^(2032+0.5-2026.75) -> 61.432618
A24: Consumer | B24: US$B | D24: =Q!G9 -> 5.198 | E24: =Q!H9 -> 7.754 | F24: =F22*F23/1000*12*0.25*uplift -> 3.4934362 | G24: =E24+F24 -> 11.247436 | H24: =H22*H23/1000*12*1*uplift -> 17.964079 | I24: =I22*I23/1000*12*1*uplift -> 23.865327 | J24: =J22*J23/1000*12*1*uplift -> 28.909807 | K24: =K22*K23/1000*12*1*uplift -> 33.201827 | L24: =L22*L23/1000*12*1*uplift -> 36.833321 | M24: =M22*M23/1000*12*1*uplift -> 39.885313 | N24: 平均訂戶 × ARPU × 月數 × uplift（2026Q3 校準，含 Kits）
A25: Enterprise & Government 年增 | B25: % | F25: =g0_eg+g0_eg_adj -> 0.70280311 | H25: =g0_eg+g0_eg_adj+(gl_eg-g0_eg+g0_eg_adj)*MIN(1,(2027-2026)/conv_n) -> 0.55210233 | I25: =g0_eg+g0_eg_adj+(gl_eg-g0_eg+g0_eg_adj)*MIN(1,(2028-2026)/conv_n) -> 0.40140155 | J25: =g0_eg+g0_eg_adj+(gl_eg-g0_eg+g0_eg_adj)*MIN(1,(2029-2026)/conv_n) -> 0.25070078 | K25: =g0_eg+g0_eg_adj+(gl_eg-g0_eg+g0_eg_adj)*MIN(1,(2030-2026)/conv_n) -> 0.1 | L25: =g0_eg+g0_eg_adj+(gl_eg-g0_eg+g0_eg_adj)*MIN(1,(2031-2026)/conv_n) -> 0.1 | M25: =g0_eg+g0_eg_adj+(gl_eg-g0_eg+g0_eg_adj)*MIN(1,(2032-2026)/conv_n) -> 0.1 | N25: 起點＝9M 年增 +70%（Q 頁），FY2030 收斂到 gl_eg
A26: Enterprise & Government | B26: US$B | D26: =Q!G10 -> 2.961 | E26: =Q!H10 -> 5.042 | F26: =eg_q3*(1+F25)^0.25 -> 2.4297333 | G26: =E26+F26 -> 7.4717333 | H26: =G26*(1+H25) -> 11.596895 | I26: =H26*(1+I25) -> 16.251906 | J26: =I26*(1+J25) -> 20.326272 | K26: =J26*(1+K25) -> 22.358899 | L26: =K26*(1+L25) -> 24.594789 | M26: =L26*(1+M25) -> 27.054267
A27: Connectivity | B27: US$B | C27: =Q!I11 -> 11.387 | D27: =Q!G11 -> 8.159 | E27: =Q!H11 -> 12.796 | F27: =F24+F26 -> 5.9231694 | G27: =E27+F27 -> 18.719169 | H27: =H24+H26 -> 29.560973 | I27: =I24+I26 -> 40.117233 | J27: =J24+J26 -> 49.236079 | K27: =K24+K26 -> 55.560726 | L27: =L24+L26 -> 61.42811 | M27: =M24+M26 -> 66.939581
A28: 合併營收 | B28: US$B | C28: =Q!I17 -> 18.674 | D28: =Q!G17 -> 13.714 | E28: =Q!H17 -> 27.083 | F28: =F20+F27+F14 -> 16.534764 | G28: =E28+F28 -> 43.617764 | H28: =H20+H27+H14 -> 88.799324 | I28: =I20+I27+I14 -> 127.34472 | J28: =J20+J27+J14 -> 160.46777 | K28: =K20+K27+K14 -> 182.80487 | L28: =L20+L27+L14 -> 203.64846 | M28: =M20+M27+M14 -> 220.05174
A29: 檢查：Space 子列合計 − Space | B29: US$B | D29: =D17+D19-D20 -> 0 | E29: =E17+E19-E20 -> 0 | F29: =F17+F19-F20 -> 0 | G29: =G17+G19-G20 -> 0 | H29: =H17+H19-H20 -> 0 | I29: =I17+I19-I20 -> 0 | J29: =J17+J19-J20 -> 0 | K29: =K17+K19-K20 -> 0 | ... M29: =M17+M19-M20 -> 0
A30: 檢查：Connectivity 子列合計 − Connectivity | B30: US$B | D30: =D24+D26-D27 -> 0 | E30: =E24+E26-E27 -> 0 | F30: =F24+F26-F27 -> 0 | G30: =G24+G26-G27 -> 0 | H30: =H24+H26-H27 -> 0 | I30: =I24+I26-I27 -> 0 | J30: =J24+J26-J27 -> 0 | K30: =K24+K26-K27 -> 0 | ... M30: =M24+M26-M27 -> 0
A31: 檢查：SI 子列合計 − SI | B31: US$B | D31: =D13+D11-D14 -> 0 | E31: =E13+E11-E14 -> 0 | F31: =F13+F11-F14 -> 0 | G31: =G13+G11-G14 -> 0 | H31: =H13+H11-H14 -> 0 | I31: =I13+I11-I14 -> 0 | J31: =J13+J11-J14 -> 0 | K31: =K13+K11-K14 -> 0 | ... M31: =M13+M11-M14 -> 0
A32: 檢查：SI S&I 命題子列合計 − SI Solutions & Infrastructure | B32: US$B | E32: =E8+E10-E11 -> 0 | F32: =F8+F10-F11 -> 0 | G32: =G8+G10-G11 -> 0 | H32: =H8+H10-H11 -> 0 | I32: =I8+I10-I11 -> 0 | J32: =J8+J10-J11 -> 0 | K32: =K8+K10-K11 -> 0 | L32: =L8+L10-L11 -> 0 | M32: =M8+M10-M11 -> 0
A33: 檢查：分部合計 − 合併營收 | B33: US$B | C33: =C20+C27+C14-C28 -> 0 | D33: =D20+D27+D14-D28 -> 0 | E33: =E20+E27+E14-E28 -> 0 | F33: =F20+F27+F14-F28 -> 0 | G33: =G20+G27+G14-G28 -> 0 | H33: =H20+H27+H14-H28 -> 0 | I33: =I20+I27+I14-I28 -> 0 | J33: =J20+J27+J14-J28 -> 0 | ... M33: =M20+M27+M14-M28 -> 0
A34: 檢查：實績欄合併營收 − Q 頁 | B34: US$B | C34: =C28-Q!I17 -> 0 | D34: =D28-Q!G17 -> 0 | E34: =E28-Q!H17 -> 0
A35: S2 核心問題：SI 每 GW 年營收 ÷ Tokenomics 每 GW 年持有成本（＝k） | B35: x | F35: =F6 -> 1.8666125 | H35: =H6 -> 1.7999594 | I35: =I6 -> 1.7333063 | J35: =J6 -> 1.6666531 | K35: =K6 -> 1.6 | L35: =L6 -> 1.6 | M35: =M6 -> 1.6 | N35: 工作單 S2：與 OpenAI PxQ 頁同口徑；FY2028 欄為核心問題比值（> 1＝租金高於打平持有成本）
A36: Space 資本支出占營收 | B36: % | F36: =cx_sp0 -> 1.1445639 | H36: =cx_sp0+(cx_spl-cx_sp0)*MIN(1,(2027-2026)/conv_n) -> 0.93342294 | I36: =cx_sp0+(cx_spl-cx_sp0)*MIN(1,(2028-2026)/conv_n) -> 0.72228196 | J36: =cx_sp0+(cx_spl-cx_sp0)*MIN(1,(2029-2026)/conv_n) -> 0.51114098 | K36: =cx_sp0+(cx_spl-cx_sp0)*MIN(1,(2030-2026)/conv_n) -> 0.3 | L36: =cx_sp0+(cx_spl-cx_sp0)*MIN(1,(2031-2026)/conv_n) -> 0.3 | M36: =cx_sp0+(cx_spl-cx_sp0)*MIN(1,(2032-2026)/conv_n) -> 0.3
A37: 資本支出：Space | B37: US$B | F37: =F20*F36 -> 1.4732917 | G37: =F37 -> 1.4732917 | H37: =H20*H36 -> 4.9481884 | I37: =I20*I36 -> 4.0993778 | J37: =J20*J36 -> 3.1213593 | K37: =K20*K36 -> 1.9804463 | L37: =L20*L36 -> 2.1409277 | M37: =M20*M36 -> 2.3144143
A38: 資本支出：Connectivity（營收 × cx_cn） | B38: US$B | F38: =F27*cx_cn -> 1.963589 | G38: =F38 -> 1.963589 | H38: =H27*cx_cn -> 9.7997538 | I38: =I27*cx_cn -> 13.299258 | J38: =J27*cx_cn -> 16.322245 | K38: =K27*cx_cn -> 18.418928 | L38: =L27*cx_cn -> 20.364023 | M38: =M27*cx_cn -> 22.19113
A39: 新增折舊：Space（年限 life_sp） | B39: US$B | F39: =($F$37/life_sp*IF((0)<0,0,IF((0)=0,phi_0,IF((0)<life_sp,1,IF((0)=life_sp,1-phi_0,0)))))*0.25 -> 0.009208073 | G39: =F39 -> 0.009208073 | H39: =($F$37/life_sp*IF((1)<0,0,IF((1)=0,phi_0,IF((1)<life_sp,1,IF((1)=life_sp,1-phi_0,0))))+$H$37/life_sp*IF((0)<0,0,IF((0)=0,phi_0,IF((0)<life_sp,1,IF((0)=life_sp,1-phi_0,0))))) -> 0.27103388 | I39: =($F$37/life_sp*IF((2)<0,0,IF((2)=0,phi_0,IF((2)<life_sp,1,IF((2)=life_sp,1-phi_0,0))))+$H$37/life_sp*IF((1)<0,0,IF((1)=0,phi_0,IF((1)<life_sp,1,IF((1)=life_sp,1-phi_0,0))))+$I$37/life_sp*IF((0)<0,0,IF((0)=0,phi_0,IF((0)<life_sp,1,IF((0)=life_sp,1-phi_0,0))))) -> 0.74463246 | J39: =($F$37/life_sp*IF((3)<0,0,IF((3)=0,phi_0,IF((3)<life_sp,1,IF((3)=life_sp,1-phi_0,0))))+$H$37/life_sp*IF((2)<0,0,IF((2)=0,phi_0,IF((2)<life_sp,1,IF((2)=life_sp,1-phi_0,0))))+$I$37/life_sp*IF((1)<0,0,IF((1)=0,phi_0,IF((1)<life_sp,1,IF((1)=life_sp,1-phi_0,0))))+$J$37/life_sp*IF((0)<0,0,IF((0)=0,phi_0,IF((0)<life_sp,1,IF((0)=life_sp,1-phi_0,0))))) -> 1.1301198 | K39: =($F$37/life_sp*IF((4)<0,0,IF((4)=0,phi_0,IF((4)<life_sp,1,IF((4)=life_sp,1-phi_0,0))))+$H$37/life_sp*IF((3)<0,0,IF((3)=0,phi_0,IF((3)<life_sp,1,IF((3)=life_sp,1-phi_0,0))))+$I$37/life_sp*IF((2)<0,0,IF((2)=0,phi_0,IF((2)<life_sp,1,IF((2)=life_sp,1-phi_0,0))))+$J$37/life_sp*IF((1)<0,0,IF((1)=0,phi_0,IF((1)<life_sp,1,IF((1)=life_sp,1-phi_0,0))))+$K$37/life_sp*IF((0)<0,0,IF((0)=0,phi_0,IF((0)<life_sp,1,IF((0)=life_sp,1-phi_0,0))))) -> 1.4137329 | L39: =($F$37/life_sp*IF((5)<0,0,IF((5)=0,phi_0,IF((5)<life_sp,1,IF((5)=life_sp,1-phi_0,0))))+$H$37/life_sp*IF((4)<0,0,IF((4)=0,phi_0,IF((4)<life_sp,1,IF((4)=life_sp,1-phi_0,0))))+$I$37/life_sp*IF((3)<0,0,IF((3)=0,phi_0,IF((3)<life_sp,1,IF((3)=life_sp,1-phi_0,0))))+$J$37/life_sp*IF((2)<0,0,IF((2)=0,phi_0,IF((2)<life_sp,1,IF((2)=life_sp,1-phi_0,0))))+$K$37/life_sp*IF((1)<0,0,IF((1)=0,phi_0,IF((1)<life_sp,1,IF((1)=life_sp,1-phi_0,0))))+$L$37/life_sp*IF((0)<0,0,IF((0)=0,phi_0,IF((0)<life_sp,1,IF((0)=life_sp,1-phi_0,0))))) -> 1.6157895 | M39: =($F$37/life_sp*IF((6)<0,0,IF((6)=0,phi_0,IF((6)<life_sp,1,IF((6)=life_sp,1-phi_0,0))))+$H$37/life_sp*IF((5)<0,0,IF((5)=0,phi_0,IF((5)<life_sp,1,IF((5)=life_sp,1-phi_0,0))))+$I$37/life_sp*IF((4)<0,0,IF((4)=0,phi_0,IF((4)<life_sp,1,IF((4)=life_sp,1-phi_0,0))))+$J$37/life_sp*IF((3)<0,0,IF((3)=0,phi_0,IF((3)<life_sp,1,IF((3)=life_sp,1-phi_0,0))))+$K$37/life_sp*IF((2)<0,0,IF((2)=0,phi_0,IF((2)<life_sp,1,IF((2)=life_sp,1-phi_0,0))))+$L$37/life_sp*IF((1)<0,0,IF((1)=0,phi_0,IF((1)<life_sp,1,IF((1)=life_sp,1-phi_0,0))))+$M$37/life_sp*IF((0)<0,0,IF((0)=0,phi_0,IF((0)<life_sp,1,IF((0)=life_sp,1-phi_0,0))))) -> 1.8342195
A40: 新增折舊：Connectivity（年限 life_cn） | B40: US$B | F40: =($F$38/life_cn*IF((0)<0,0,IF((0)=0,phi_0,IF((0)<life_cn,1,IF((0)=life_cn,1-phi_0,0)))))*0.25 -> 0.020454052 | G40: =F40 -> 0.020454052 | H40: =($F$38/life_cn*IF((1)<0,0,IF((1)=0,phi_0,IF((1)<life_cn,1,IF((1)=life_cn,1-phi_0,0))))+$H$38/life_cn*IF((0)<0,0,IF((0)=0,phi_0,IF((0)<life_cn,1,IF((0)=life_cn,1-phi_0,0))))) -> 0.73558791 | I40: =($F$38/life_cn*IF((2)<0,0,IF((2)=0,phi_0,IF((2)<life_cn,1,IF((2)=life_cn,1-phi_0,0))))+$H$38/life_cn*IF((1)<0,0,IF((1)=0,phi_0,IF((1)<life_cn,1,IF((1)=life_cn,1-phi_0,0))))+$I$38/life_cn*IF((0)<0,0,IF((0)=0,phi_0,IF((0)<life_cn,1,IF((0)=life_cn,1-phi_0,0))))) -> 2.5146929 | J40: =($F$38/life_cn*IF((3)<0,0,IF((3)=0,phi_0,IF((3)<life_cn,1,IF((3)=life_cn,1-phi_0,0))))+$H$38/life_cn*IF((2)<0,0,IF((2)=0,phi_0,IF((2)<life_cn,1,IF((2)=life_cn,1-phi_0,0))))+$I$38/life_cn*IF((1)<0,0,IF((1)=0,phi_0,IF((1)<life_cn,1,IF((1)=life_cn,1-phi_0,0))))+$J$38/life_cn*IF((0)<0,0,IF((0)=0,phi_0,IF((0)<life_cn,1,IF((0)=life_cn,1-phi_0,0))))) -> 4.8571936 | K40: =($F$38/life_cn*IF((4)<0,0,IF((4)=0,phi_0,IF((4)<life_cn,1,IF((4)=life_cn,1-phi_0,0))))+$H$38/life_cn*IF((3)<0,0,IF((3)=0,phi_0,IF((3)<life_cn,1,IF((3)=life_cn,1-phi_0,0))))+$I$38/life_cn*IF((2)<0,0,IF((2)=0,phi_0,IF((2)<life_cn,1,IF((2)=life_cn,1-phi_0,0))))+$J$38/life_cn*IF((1)<0,0,IF((1)=0,phi_0,IF((1)<life_cn,1,IF((1)=life_cn,1-phi_0,0))))+$K$38/life_cn*IF((0)<0,0,IF((0)=0,phi_0,IF((0)<life_cn,1,IF((0)=life_cn,1-phi_0,0))))) -> 7.6649296 | L40: =($F$38/life_cn*IF((5)<0,0,IF((5)=0,phi_0,IF((5)<life_cn,1,IF((5)=life_cn,1-phi_0,0))))+$H$38/life_cn*IF((4)<0,0,IF((4)=0,phi_0,IF((4)<life_cn,1,IF((4)=life_cn,1-phi_0,0))))+$I$38/life_cn*IF((3)<0,0,IF((3)=0,phi_0,IF((3)<life_cn,1,IF((3)=life_cn,1-phi_0,0))))+$J$38/life_cn*IF((2)<0,0,IF((2)=0,phi_0,IF((2)<life_cn,1,IF((2)=life_cn,1-phi_0,0))))+$K$38/life_cn*IF((1)<0,0,IF((1)=0,phi_0,IF((1)<life_cn,1,IF((1)=life_cn,1-phi_0,0))))+$L$38/life_cn*IF((0)<0,0,IF((0)=0,phi_0,IF((0)<life_cn,1,IF((0)=life_cn,1-phi_0,0))))) -> 10.815797 | M40: =($F$38/life_cn*IF((6)<0,0,IF((6)=0,phi_0,IF((6)<life_cn,1,IF((6)=life_cn,1-phi_0,0))))+$H$38/life_cn*IF((5)<0,0,IF((5)=0,phi_0,IF((5)<life_cn,1,IF((5)=life_cn,1-phi_0,0))))+$I$38/life_cn*IF((4)<0,0,IF((4)=0,phi_0,IF((4)<life_cn,1,IF((4)=life_cn,1-phi_0,0))))+$J$38/life_cn*IF((3)<0,0,IF((3)=0,phi_0,IF((3)<life_cn,1,IF((3)=life_cn,1-phi_0,0))))+$K$38/life_cn*IF((2)<0,0,IF((2)=0,phi_0,IF((2)<life_cn,1,IF((2)=life_cn,1-phi_0,0))))+$L$38/life_cn*IF((1)<0,0,IF((1)=0,phi_0,IF((1)<life_cn,1,IF((1)=life_cn,1-phi_0,0))))+$M$38/life_cn*IF((0)<0,0,IF((0)=0,phi_0,IF((0)<life_cn,1,IF((0)=life_cn,1-phi_0,0))))) -> 14.204114
A42: 情境 B（租金向持有成本部分收斂；基準）
A43: 項目 | B43: 單位 | C43: FY2025* | D43: 9M25A | E43: 9M26A | F43: Q4 26E | G43: FY2026E | H43: FY2027E | I43: FY2028E | J43: FY2029E | K43: FY2030E | L43: FY2031E | M43: FY2032E | N43: 說明
A44: k＝每 GW 年營收 ÷ 持有成本（Q4 26＝校準 k0，FY2030＝情境值） | B44: x | F44: =k0 -> 1.8666125 | H44: =k0+(k30_B-k0)*MIN(1,(2027-2026)/conv_k) -> 1.7124594 | I44: =k0+(k30_B-k0)*MIN(1,(2028-2026)/conv_k) -> 1.5583063 | J44: =k0+(k30_B-k0)*MIN(1,(2029-2026)/conv_k) -> 1.4041531 | K44: =k0+(k30_B-k0)*MIN(1,(2030-2026)/conv_k) -> 1.25 | L44: =k0+(k30_B-k0)*MIN(1,(2031-2026)/conv_k) -> 1.25 | M44: =k0+(k30_B-k0)*MIN(1,(2032-2026)/conv_k) -> 1.25
A45: 對外每 GW 年營收＝k × 在役機隊持有成本 | B45: US$B/GW-年 | F45: =F44*Thesis!F33 -> 18.356302 | H45: =H44*Thesis!H33 -> 17.787308 | I45: =I44*Thesis!I33 -> 17.024535 | J45: =J44*Thesis!J33 -> 15.780453 | K45: =K44*Thesis!K33 -> 14.237448 | L45: =L44*Thesis!L33 -> 14.336857 | M45: =M44*Thesis!M33 -> 14.383898
A46: SI 對外雲端服務（命題子列） | B46: US$B | E46: =Thesis!C11 -> 6.63552 | F46: =Thesis!F31*F45*0.25 -> 6.2890195 | G46: =E46+F46 -> 12.924539 | H46: =Thesis!H31*H45*1 -> 37.399537 | I46: =Thesis!I31*I45*1 -> 55.739335 | J46: =Thesis!J31*J45*1 -> 68.069976 | K46: =Thesis!K31*K45*1 -> 72.553409 | L46: =Thesis!L31*L45*1 -> 80.745695 | M46: =Thesis!M31*M45*1 -> 85.254628 | N46: 對外 GW × 每 GW 年營收；9M26＝(Q2＋Q3 SI S&I) × ext_sh（Customer B 衍生）
A47: SI 其他收入年增 | B47: % | H47: =g27_nr+(gl_nr-g27_nr)*MIN(1,(2027-2027)/(conv_n-1)) -> 0.5 | I47: =g27_nr+(gl_nr-g27_nr)*MIN(1,(2028-2027)/(conv_n-1)) -> 0.38333333 | J47: =g27_nr+(gl_nr-g27_nr)*MIN(1,(2029-2027)/(conv_n-1)) -> 0.26666667 | K47: =g27_nr+(gl_nr-g27_nr)*MIN(1,(2030-2027)/(conv_n-1)) -> 0.15 | L47: =g27_nr+(gl_nr-g27_nr)*MIN(1,(2031-2027)/(conv_n-1)) -> 0.15 | M47: =g27_nr+(gl_nr-g27_nr)*MIN(1,(2032-2027)/(conv_n-1)) -> 0.15 | N47: FY2027＝g27_nr（以 Q4 26 備考年化為基期），FY2030 收斂到 gl_nr
A48: Grok／Cursor／X 訂閱、資料授權與 API（命題子列） | B48: US$B | E48: =Q!H14-E46 -> 3.05548 | F48: =nr_q3+cur_pf -> 2.50516 | G48: =E48+F48 -> 5.56064 | H48: =F48*4*(1+H47)^0.625 -> 12.91078 | I48: =H48*(1+I47) -> 17.859913 | J48: =I48*(1+J47) -> 22.622556 | K48: =J48*(1+K47) -> 26.01594 | L48: =K48*(1+L47) -> 29.918331 | M48: =L48*(1+M47) -> 34.406081 | N48: Q4 26＝2026Q3 值＋Cursor 備考補足（審查第 8 條：以備考全季為起點）；FY2027＝Q4 26 × 4 ×(1＋年增)^0.625
A49: SI Solutions & Infrastructure | B49: US$B | D49: =Q!G14 -> 0.955 | E49: =Q!H14 -> 9.691 | F49: =F46+F48 -> 8.7941795 | G49: =E49+F49 -> 18.485179 | H49: =H46+H48 -> 50.310318 | I49: =I46+I48 -> 73.599248 | J49: =J46+J48 -> 90.692533 | K49: =K46+K48 -> 98.569349 | L49: =L46+L48 -> 110.66403 | M49: =M46+M48 -> 119.66071
A50: Advertising 年增 | B50: % | F50: =g0_ads -> -0.056689342 | H50: =g0_ads+(gl_ads-g0_ads)*MIN(1,(2027-2026)/conv_n) -> -0.035017007 | I50: =g0_ads+(gl_ads-g0_ads)*MIN(1,(2028-2026)/conv_n) -> -0.013344671 | J50: =g0_ads+(gl_ads-g0_ads)*MIN(1,(2029-2026)/conv_n) -> 0.0083276644 | K50: =g0_ads+(gl_ads-g0_ads)*MIN(1,(2030-2026)/conv_n) -> 0.03 | L50: =g0_ads+(gl_ads-g0_ads)*MIN(1,(2031-2026)/conv_n) -> 0.03 | M50: =g0_ads+(gl_ads-g0_ads)*MIN(1,(2032-2026)/conv_n) -> 0.03 | N50: 起點＝9M 年增（Q 頁），FY2030 收斂到 gl_ads
A51: Advertising | B51: US$B | D51: =Q!G13 -> 1.323 | E51: =Q!H13 -> 1.248 | F51: =ads_q3*(1+F50)^0.25 -> 0.53020762 | G51: =E51+F51 -> 1.7782076 | H51: =G51*(1+H50) -> 1.7159401 | I51: =H51*(1+I50) -> 1.6930415 | J51: =I51*(1+J50) -> 1.7071405 | K51: =J51*(1+K50) -> 1.7583547 | L51: =K51*(1+L50) -> 1.8111054 | M51: =L51*(1+M50) -> 1.8654386
A52: SI (Super Intelligence; formerly AI) | B52: US$B | C52: =Q!I15 -> 3.201 | D52: =Q!G15 -> 2.278 | E52: =Q!H15 -> 10.939 | F52: =F51+F49 -> 9.3243871 | G52: =E52+F52 -> 20.263387 | H52: =H51+H49 -> 52.026258 | I52: =I51+I49 -> 75.292289 | J52: =J51+J49 -> 92.399673 | K52: =K51+K49 -> 100.3277 | L52: =L51+L49 -> 112.47513 | M52: =M51+M49 -> 121.52615
A53: 客戶發射次數 | B53: 次 | E53: =Q!H57 -> 29 | F53: =nl_q4 -> 12 | G53: =E53+F53 -> 41 | H53: =nl_27 -> 48 | I53: =H53*(1+g_nl) -> 50.4 | J53: =I53*(1+g_nl) -> 52.92 | K53: =J53*(1+g_nl) -> 55.566 | L53: =K53*(1+g_nl) -> 58.3443 | M53: =L53*(1+g_nl) -> 61.261515
A54: 每次客戶發射收入 | B54: US$B／次 | E54: =rpl0 -> 0.072689655 | F54: =rpl0 -> 0.072689655 | H54: =rpl0*(1+g_rpl)^(2027-2026) -> 0.074870345 | I54: =rpl0*(1+g_rpl)^(2028-2026) -> 0.077116455 | J54: =rpl0*(1+g_rpl)^(2029-2026) -> 0.079429949 | K54: =rpl0*(1+g_rpl)^(2030-2026) -> 0.081812847 | L54: =rpl0*(1+g_rpl)^(2031-2026) -> 0.084267233 | M54: =rpl0*(1+g_rpl)^(2032-2026) -> 0.08679525
A55: Launch Services | B55: US$B | D55: =Q!G5 -> 2.056 | E55: =Q!H5 -> 2.108 | F55: =F53*F54 -> 0.87227586 | G55: =E55+F55 -> 2.9802759 | H55: =H53*H54 -> 3.5937766 | I55: =I53*I54 -> 3.8866693 | J55: =J53*J54 -> 4.2034329 | K55: =K53*K54 -> 4.5460127 | L55: =L53*L54 -> 4.9165127 | M55: =M53*M54 -> 5.3172085
A56: Launch & Development 年增 | B56: % | F56: =g0_ld -> 0.015561016 | H56: =g0_ld+(gl_ld-g0_ld)*MIN(1,(2027-2026)/conv_n) -> 0.031670762 | I56: =g0_ld+(gl_ld-g0_ld)*MIN(1,(2028-2026)/conv_n) -> 0.047780508 | J56: =g0_ld+(gl_ld-g0_ld)*MIN(1,(2029-2026)/conv_n) -> 0.063890254 | K56: =g0_ld+(gl_ld-g0_ld)*MIN(1,(2030-2026)/conv_n) -> 0.08 | L56: =g0_ld+(gl_ld-g0_ld)*MIN(1,(2031-2026)/conv_n) -> 0.08 | M56: =g0_ld+(gl_ld-g0_ld)*MIN(1,(2032-2026)/conv_n) -> 0.08
A57: Launch & Development | B57: US$B | D57: =Q!G6 -> 1.221 | E57: =Q!H6 -> 1.24 | F57: =ld_9m/3*(1+F56)^0.25 -> 0.41493201 | G57: =E57+F57 -> 1.654932 | H57: =G57*(1+H56) -> 1.707345 | I57: =H57*(1+I56) -> 1.7889228 | J57: =I57*(1+J56) -> 1.9032175 | K57: =J57*(1+K56) -> 2.0554749 | L57: =K57*(1+L56) -> 2.2199129 | M57: =L57*(1+M56) -> 2.3975059 | N57: Q4 26＝9M26 季均 ×(1＋年增)^0.25（里程碑收入不規則）
A58: Space | B58: US$B | C58: =Q!I7 -> 4.086 | D58: =Q!G7 -> 3.277 | E58: =Q!H7 -> 3.348 | F58: =F55+F57 -> 1.2872079 | G58: =E58+F58 -> 4.6352079 | H58: =H55+H57 -> 5.3011215 | I58: =I55+I57 -> 5.6755921 | J58: =J55+J57 -> 6.1066504 | K58: =K55+K57 -> 6.6014876 | L58: =L55+L57 -> 7.1364256 | M58: =M55+M57 -> 7.7147144
A59: Starlink 消費訂戶（期末，百萬） | B59: 百萬 | E59: =subs_q3 -> 13.6 | F59: =E59+nadd_q4 -> 15.2 | H59: =F59+nadd_B -> 20.7 | I59: =H59+nadd_B*(1-nadd_dec)^(2028-2027) -> 25.65 | J59: =I59+nadd_B*(1-nadd_dec)^(2029-2027) -> 30.105 | K59: =J59+nadd_B*(1-nadd_dec)^(2030-2027) -> 34.1145 | L59: =K59+nadd_B*(1-nadd_dec)^(2031-2027) -> 37.72305 | M59: =L59+nadd_B*(1-nadd_dec)^(2032-2027) -> 40.970745
A60: 平均消費訂戶 | B60: 百萬 | F60: =(E59+F59)/2 -> 14.4 | H60: =(F59+H59)/2 -> 17.95 | I60: =(H59+I59)/2 -> 23.175 | J60: =(I59+J59)/2 -> 27.8775 | K60: =(J59+K59)/2 -> 32.10975 | L60: =(K59+L59)/2 -> 35.918775 | M60: =(L59+M59)/2 -> 39.346897
A61: 消費 ARPU（美元／月） | B61: US$ | F61: =arpu0*(1+g_arpu)^0.25 -> 68.652382 | H61: =arpu0*(1+g_arpu)^(2027+0.5-2026.75) -> 67.962391 | I61: =arpu0*(1+g_arpu)^(2028+0.5-2026.75) -> 66.603143 | J61: =arpu0*(1+g_arpu)^(2029+0.5-2026.75) -> 65.27108 | K61: =arpu0*(1+g_arpu)^(2030+0.5-2026.75) -> 63.965658 | L61: =arpu0*(1+g_arpu)^(2031+0.5-2026.75) -> 62.686345 | M61: =arpu0*(1+g_arpu)^(2032+0.5-2026.75) -> 61.432618
A62: Consumer | B62: US$B | D62: =Q!G9 -> 5.198 | E62: =Q!H9 -> 7.754 | F62: =F60*F61/1000*12*0.25*uplift -> 3.4934362 | G62: =E62+F62 -> 11.247436 | H62: =H60*H61/1000*12*1*uplift -> 17.243594 | I62: =I60*I61/1000*12*1*uplift -> 21.81771 | J62: =J60*J61/1000*12*1*uplift -> 25.719903 | K62: =K60*K61/1000*12*1*uplift -> 29.032103 | L62: =L60*L61/1000*12*1*uplift -> 31.826521 | M62: =M60*M61/1000*12*1*uplift -> 34.166793 | N62: 平均訂戶 × ARPU × 月數 × uplift（2026Q3 校準，含 Kits）
A63: Enterprise & Government 年增 | B63: % | F63: =g0_eg+g0_eg_adj -> 0.70280311 | H63: =g0_eg+g0_eg_adj+(gl_eg-g0_eg+g0_eg_adj)*MIN(1,(2027-2026)/conv_n) -> 0.55210233 | I63: =g0_eg+g0_eg_adj+(gl_eg-g0_eg+g0_eg_adj)*MIN(1,(2028-2026)/conv_n) -> 0.40140155 | J63: =g0_eg+g0_eg_adj+(gl_eg-g0_eg+g0_eg_adj)*MIN(1,(2029-2026)/conv_n) -> 0.25070078 | K63: =g0_eg+g0_eg_adj+(gl_eg-g0_eg+g0_eg_adj)*MIN(1,(2030-2026)/conv_n) -> 0.1 | L63: =g0_eg+g0_eg_adj+(gl_eg-g0_eg+g0_eg_adj)*MIN(1,(2031-2026)/conv_n) -> 0.1 | M63: =g0_eg+g0_eg_adj+(gl_eg-g0_eg+g0_eg_adj)*MIN(1,(2032-2026)/conv_n) -> 0.1 | N63: 起點＝9M 年增 +70%（Q 頁），FY2030 收斂到 gl_eg
A64: Enterprise & Government | B64: US$B | D64: =Q!G10 -> 2.961 | E64: =Q!H10 -> 5.042 | F64: =eg_q3*(1+F63)^0.25 -> 2.4297333 | G64: =E64+F64 -> 7.4717333 | H64: =G64*(1+H63) -> 11.596895 | I64: =H64*(1+I63) -> 16.251906 | J64: =I64*(1+J63) -> 20.326272 | K64: =J64*(1+K63) -> 22.358899 | L64: =K64*(1+L63) -> 24.594789 | M64: =L64*(1+M63) -> 27.054267
A65: Connectivity | B65: US$B | C65: =Q!I11 -> 11.387 | D65: =Q!G11 -> 8.159 | E65: =Q!H11 -> 12.796 | F65: =F62+F64 -> 5.9231694 | G65: =E65+F65 -> 18.719169 | H65: =H62+H64 -> 28.840489 | I65: =I62+I64 -> 38.069616 | J65: =J62+J64 -> 46.046174 | K65: =K62+K64 -> 51.391002 | L65: =L62+L64 -> 56.42131 | M65: =M62+M64 -> 61.221061
A66: 合併營收 | B66: US$B | C66: =Q!I17 -> 18.674 | D66: =Q!G17 -> 13.714 | E66: =Q!H17 -> 27.083 | F66: =F58+F65+F52 -> 16.534764 | G66: =E66+F66 -> 43.617764 | H66: =H58+H65+H52 -> 86.167868 | I66: =I58+I65+I52 -> 119.0375 | J66: =J58+J65+J52 -> 144.5525 | K66: =K58+K65+K52 -> 158.32019 | L66: =L58+L65+L52 -> 176.03287 | M66: =M58+M65+M52 -> 190.46192
A67: 檢查：Space 子列合計 − Space | B67: US$B | D67: =D55+D57-D58 -> 0 | E67: =E55+E57-E58 -> 0 | F67: =F55+F57-F58 -> 0 | G67: =G55+G57-G58 -> 0 | H67: =H55+H57-H58 -> 0 | I67: =I55+I57-I58 -> 0 | J67: =J55+J57-J58 -> 0 | K67: =K55+K57-K58 -> 0 | ... M67: =M55+M57-M58 -> 0
A68: 檢查：Connectivity 子列合計 − Connectivity | B68: US$B | D68: =D62+D64-D65 -> 0 | E68: =E62+E64-E65 -> 0 | F68: =F62+F64-F65 -> 0 | G68: =G62+G64-G65 -> 0 | H68: =H62+H64-H65 -> 0 | I68: =I62+I64-I65 -> 0 | J68: =J62+J64-J65 -> 0 | K68: =K62+K64-K65 -> 0 | ... M68: =M62+M64-M65 -> 0
A69: 檢查：SI 子列合計 − SI | B69: US$B | D69: =D51+D49-D52 -> 0 | E69: =E51+E49-E52 -> 0 | F69: =F51+F49-F52 -> 0 | G69: =G51+G49-G52 -> 0 | H69: =H51+H49-H52 -> 0 | I69: =I51+I49-I52 -> 0 | J69: =J51+J49-J52 -> 0 | K69: =K51+K49-K52 -> 0 | ... M69: =M51+M49-M52 -> 0
A70: 檢查：SI S&I 命題子列合計 − SI Solutions & Infrastructure | B70: US$B | E70: =E46+E48-E49 -> 0 | F70: =F46+F48-F49 -> 0 | G70: =G46+G48-G49 -> 0 | H70: =H46+H48-H49 -> 0 | I70: =I46+I48-I49 -> 0 | J70: =J46+J48-J49 -> 0 | K70: =K46+K48-K49 -> 0 | L70: =L46+L48-L49 -> 0 | M70: =M46+M48-M49 -> 0
A71: 檢查：分部合計 − 合併營收 | B71: US$B | C71: =C58+C65+C52-C66 -> 0 | D71: =D58+D65+D52-D66 -> 0 | E71: =E58+E65+E52-E66 -> 0 | F71: =F58+F65+F52-F66 -> 0 | G71: =G58+G65+G52-G66 -> 0 | H71: =H58+H65+H52-H66 -> 0 | I71: =I58+I65+I52-I66 -> 0 | J71: =J58+J65+J52-J66 -> 0 | ... M71: =M58+M65+M52-M66 -> 0
A72: 檢查：實績欄合併營收 − Q 頁 | B72: US$B | C72: =C66-Q!I17 -> 0 | D72: =D66-Q!G17 -> 0 | E72: =E66-Q!H17 -> 0
A73: S2 核心問題：SI 每 GW 年營收 ÷ Tokenomics 每 GW 年持有成本（＝k） | B73: x | F73: =F44 -> 1.8666125 | H73: =H44 -> 1.7124594 | I73: =I44 -> 1.5583063 | J73: =J44 -> 1.4041531 | K73: =K44 -> 1.25 | L73: =L44 -> 1.25 | M73: =M44 -> 1.25 | N73: 工作單 S2：與 OpenAI PxQ 頁同口徑；FY2028 欄為核心問題比值（> 1＝租金高於打平持有成本）
A74: Space 資本支出占營收 | B74: % | F74: =cx_sp0 -> 1.1445639 | H74: =cx_sp0+(cx_spl-cx_sp0)*MIN(1,(2027-2026)/conv_n) -> 0.93342294 | I74: =cx_sp0+(cx_spl-cx_sp0)*MIN(1,(2028-2026)/conv_n) -> 0.72228196 | J74: =cx_sp0+(cx_spl-cx_sp0)*MIN(1,(2029-2026)/conv_n) -> 0.51114098 | K74: =cx_sp0+(cx_spl-cx_sp0)*MIN(1,(2030-2026)/conv_n) -> 0.3 | L74: =cx_sp0+(cx_spl-cx_sp0)*MIN(1,(2031-2026)/conv_n) -> 0.3 | M74: =cx_sp0+(cx_spl-cx_sp0)*MIN(1,(2032-2026)/conv_n) -> 0.3
A75: 資本支出：Space | B75: US$B | F75: =F58*F74 -> 1.4732917 | G75: =F75 -> 1.4732917 | H75: =H58*H74 -> 4.9481884 | I75: =I58*I74 -> 4.0993778 | J75: =J58*J74 -> 3.1213593 | K75: =K58*K74 -> 1.9804463 | L75: =L58*L74 -> 2.1409277 | M75: =M58*M74 -> 2.3144143
A76: 資本支出：Connectivity（營收 × cx_cn） | B76: US$B | F76: =F65*cx_cn -> 1.963589 | G76: =F76 -> 1.963589 | H76: =H65*cx_cn -> 9.5609061 | I76: =I65*cx_cn -> 12.620453 | J76: =J65*cx_cn -> 15.26476 | K76: =K65*cx_cn -> 17.036623 | L76: =L65*cx_cn -> 18.70422 | M76: =M65*cx_cn -> 20.295384
A77: 新增折舊：Space（年限 life_sp） | B77: US$B | F77: =($F$75/life_sp*IF((0)<0,0,IF((0)=0,phi_0,IF((0)<life_sp,1,IF((0)=life_sp,1-phi_0,0)))))*0.25 -> 0.009208073 | G77: =F77 -> 0.009208073 | H77: =($F$75/life_sp*IF((1)<0,0,IF((1)=0,phi_0,IF((1)<life_sp,1,IF((1)=life_sp,1-phi_0,0))))+$H$75/life_sp*IF((0)<0,0,IF((0)=0,phi_0,IF((0)<life_sp,1,IF((0)=life_sp,1-phi_0,0))))) -> 0.27103388 | I77: =($F$75/life_sp*IF((2)<0,0,IF((2)=0,phi_0,IF((2)<life_sp,1,IF((2)=life_sp,1-phi_0,0))))+$H$75/life_sp*IF((1)<0,0,IF((1)=0,phi_0,IF((1)<life_sp,1,IF((1)=life_sp,1-phi_0,0))))+$I$75/life_sp*IF((0)<0,0,IF((0)=0,phi_0,IF((0)<life_sp,1,IF((0)=life_sp,1-phi_0,0))))) -> 0.74463246 | J77: =($F$75/life_sp*IF((3)<0,0,IF((3)=0,phi_0,IF((3)<life_sp,1,IF((3)=life_sp,1-phi_0,0))))+$H$75/life_sp*IF((2)<0,0,IF((2)=0,phi_0,IF((2)<life_sp,1,IF((2)=life_sp,1-phi_0,0))))+$I$75/life_sp*IF((1)<0,0,IF((1)=0,phi_0,IF((1)<life_sp,1,IF((1)=life_sp,1-phi_0,0))))+$J$75/life_sp*IF((0)<0,0,IF((0)=0,phi_0,IF((0)<life_sp,1,IF((0)=life_sp,1-phi_0,0))))) -> 1.1301198 | K77: =($F$75/life_sp*IF((4)<0,0,IF((4)=0,phi_0,IF((4)<life_sp,1,IF((4)=life_sp,1-phi_0,0))))+$H$75/life_sp*IF((3)<0,0,IF((3)=0,phi_0,IF((3)<life_sp,1,IF((3)=life_sp,1-phi_0,0))))+$I$75/life_sp*IF((2)<0,0,IF((2)=0,phi_0,IF((2)<life_sp,1,IF((2)=life_sp,1-phi_0,0))))+$J$75/life_sp*IF((1)<0,0,IF((1)=0,phi_0,IF((1)<life_sp,1,IF((1)=life_sp,1-phi_0,0))))+$K$75/life_sp*IF((0)<0,0,IF((0)=0,phi_0,IF((0)<life_sp,1,IF((0)=life_sp,1-phi_0,0))))) -> 1.4137329 | L77: =($F$75/life_sp*IF((5)<0,0,IF((5)=0,phi_0,IF((5)<life_sp,1,IF((5)=life_sp,1-phi_0,0))))+$H$75/life_sp*IF((4)<0,0,IF((4)=0,phi_0,IF((4)<life_sp,1,IF((4)=life_sp,1-phi_0,0))))+$I$75/life_sp*IF((3)<0,0,IF((3)=0,phi_0,IF((3)<life_sp,1,IF((3)=life_sp,1-phi_0,0))))+$J$75/life_sp*IF((2)<0,0,IF((2)=0,phi_0,IF((2)<life_sp,1,IF((2)=life_sp,1-phi_0,0))))+$K$75/life_sp*IF((1)<0,0,IF((1)=0,phi_0,IF((1)<life_sp,1,IF((1)=life_sp,1-phi_0,0))))+$L$75/life_sp*IF((0)<0,0,IF((0)=0,phi_0,IF((0)<life_sp,1,IF((0)=life_sp,1-phi_0,0))))) -> 1.6157895 | M77: =($F$75/life_sp*IF((6)<0,0,IF((6)=0,phi_0,IF((6)<life_sp,1,IF((6)=life_sp,1-phi_0,0))))+$H$75/life_sp*IF((5)<0,0,IF((5)=0,phi_0,IF((5)<life_sp,1,IF((5)=life_sp,1-phi_0,0))))+$I$75/life_sp*IF((4)<0,0,IF((4)=0,phi_0,IF((4)<life_sp,1,IF((4)=life_sp,1-phi_0,0))))+$J$75/life_sp*IF((3)<0,0,IF((3)=0,phi_0,IF((3)<life_sp,1,IF((3)=life_sp,1-phi_0,0))))+$K$75/life_sp*IF((2)<0,0,IF((2)=0,phi_0,IF((2)<life_sp,1,IF((2)=life_sp,1-phi_0,0))))+$L$75/life_sp*IF((1)<0,0,IF((1)=0,phi_0,IF((1)<life_sp,1,IF((1)=life_sp,1-phi_0,0))))+$M$75/life_sp*IF((0)<0,0,IF((0)=0,phi_0,IF((0)<life_sp,1,IF((0)=life_sp,1-phi_0,0))))) -> 1.8342195
A78: 新增折舊：Connectivity（年限 life_cn） | B78: US$B | F78: =($F$76/life_cn*IF((0)<0,0,IF((0)=0,phi_0,IF((0)<life_cn,1,IF((0)=life_cn,1-phi_0,0)))))*0.25 -> 0.020454052 | G78: =F78 -> 0.020454052 | H78: =($F$76/life_cn*IF((1)<0,0,IF((1)=0,phi_0,IF((1)<life_cn,1,IF((1)=life_cn,1-phi_0,0))))+$H$76/life_cn*IF((0)<0,0,IF((0)=0,phi_0,IF((0)<life_cn,1,IF((0)=life_cn,1-phi_0,0))))) -> 0.72563592 | I78: =($F$76/life_cn*IF((2)<0,0,IF((2)=0,phi_0,IF((2)<life_cn,1,IF((2)=life_cn,1-phi_0,0))))+$H$76/life_cn*IF((1)<0,0,IF((1)=0,phi_0,IF((1)<life_cn,1,IF((1)=life_cn,1-phi_0,0))))+$I$76/life_cn*IF((0)<0,0,IF((0)=0,phi_0,IF((0)<life_cn,1,IF((0)=life_cn,1-phi_0,0))))) -> 2.4466014 | J78: =($F$76/life_cn*IF((3)<0,0,IF((3)=0,phi_0,IF((3)<life_cn,1,IF((3)=life_cn,1-phi_0,0))))+$H$76/life_cn*IF((2)<0,0,IF((2)=0,phi_0,IF((2)<life_cn,1,IF((2)=life_cn,1-phi_0,0))))+$I$76/life_cn*IF((1)<0,0,IF((1)=0,phi_0,IF((1)<life_cn,1,IF((1)=life_cn,1-phi_0,0))))+$J$76/life_cn*IF((0)<0,0,IF((0)=0,phi_0,IF((0)<life_cn,1,IF((0)=life_cn,1-phi_0,0))))) -> 4.6601896 | K78: =($F$76/life_cn*IF((4)<0,0,IF((4)=0,phi_0,IF((4)<life_cn,1,IF((4)=life_cn,1-phi_0,0))))+$H$76/life_cn*IF((3)<0,0,IF((3)=0,phi_0,IF((3)<life_cn,1,IF((3)=life_cn,1-phi_0,0))))+$I$76/life_cn*IF((2)<0,0,IF((2)=0,phi_0,IF((2)<life_cn,1,IF((2)=life_cn,1-phi_0,0))))+$J$76/life_cn*IF((1)<0,0,IF((1)=0,phi_0,IF((1)<life_cn,1,IF((1)=life_cn,1-phi_0,0))))+$K$76/life_cn*IF((0)<0,0,IF((0)=0,phi_0,IF((0)<life_cn,1,IF((0)=life_cn,1-phi_0,0))))) -> 7.278144 | L78: =($F$76/life_cn*IF((5)<0,0,IF((5)=0,phi_0,IF((5)<life_cn,1,IF((5)=life_cn,1-phi_0,0))))+$H$76/life_cn*IF((4)<0,0,IF((4)=0,phi_0,IF((4)<life_cn,1,IF((4)=life_cn,1-phi_0,0))))+$I$76/life_cn*IF((3)<0,0,IF((3)=0,phi_0,IF((3)<life_cn,1,IF((3)=life_cn,1-phi_0,0))))+$J$76/life_cn*IF((2)<0,0,IF((2)=0,phi_0,IF((2)<life_cn,1,IF((2)=life_cn,1-phi_0,0))))+$K$76/life_cn*IF((1)<0,0,IF((1)=0,phi_0,IF((1)<life_cn,1,IF((1)=life_cn,1-phi_0,0))))+$L$76/life_cn*IF((0)<0,0,IF((0)=0,phi_0,IF((0)<life_cn,1,IF((0)=life_cn,1-phi_0,0))))) -> 10.187064 | M78: =($F$76/life_cn*IF((6)<0,0,IF((6)=0,phi_0,IF((6)<life_cn,1,IF((6)=life_cn,1-phi_0,0))))+$H$76/life_cn*IF((5)<0,0,IF((5)=0,phi_0,IF((5)<life_cn,1,IF((5)=life_cn,1-phi_0,0))))+$I$76/life_cn*IF((4)<0,0,IF((4)=0,phi_0,IF((4)<life_cn,1,IF((4)=life_cn,1-phi_0,0))))+$J$76/life_cn*IF((3)<0,0,IF((3)=0,phi_0,IF((3)<life_cn,1,IF((3)=life_cn,1-phi_0,0))))+$K$76/life_cn*IF((2)<0,0,IF((2)=0,phi_0,IF((2)<life_cn,1,IF((2)=life_cn,1-phi_0,0))))+$L$76/life_cn*IF((1)<0,0,IF((1)=0,phi_0,IF((1)<life_cn,1,IF((1)=life_cn,1-phi_0,0))))+$M$76/life_cn*IF((0)<0,0,IF((0)=0,phi_0,IF((0)<life_cn,1,IF((0)=life_cn,1-phi_0,0))))) -> 13.288917
A80: 情境 C（租金收斂到持有成本、Starlink 增長放緩）
A81: 項目 | B81: 單位 | C81: FY2025* | D81: 9M25A | E81: 9M26A | F81: Q4 26E | G81: FY2026E | H81: FY2027E | I81: FY2028E | J81: FY2029E | K81: FY2030E | L81: FY2031E | M81: FY2032E | N81: 說明
A82: k＝每 GW 年營收 ÷ 持有成本（Q4 26＝校準 k0，FY2030＝情境值） | B82: x | F82: =k0 -> 1.8666125 | H82: =k0+(k30_C-k0)*MIN(1,(2027-2026)/conv_k) -> 1.6499594 | I82: =k0+(k30_C-k0)*MIN(1,(2028-2026)/conv_k) -> 1.4333063 | J82: =k0+(k30_C-k0)*MIN(1,(2029-2026)/conv_k) -> 1.2166531 | K82: =k0+(k30_C-k0)*MIN(1,(2030-2026)/conv_k) -> 1 | L82: =k0+(k30_C-k0)*MIN(1,(2031-2026)/conv_k) -> 1 | M82: =k0+(k30_C-k0)*MIN(1,(2032-2026)/conv_k) -> 1
A83: 對外每 GW 年營收＝k × 在役機隊持有成本 | B83: US$B/GW-年 | F83: =F82*Thesis!F33 -> 18.356302 | H83: =H82*Thesis!H33 -> 17.138121 | I83: =I82*Thesis!I33 -> 15.658907 | J83: =J82*Thesis!J33 -> 13.67325 | K83: =K82*Thesis!K33 -> 11.389958 | L83: =L82*Thesis!L33 -> 11.469486 | M83: =M82*Thesis!M33 -> 11.507119
A84: SI 對外雲端服務（命題子列） | B84: US$B | E84: =Thesis!C11 -> 6.63552 | F84: =Thesis!F31*F83*0.25 -> 6.2890195 | G84: =E84+F84 -> 12.924539 | H84: =Thesis!H31*H83*1 -> 36.034558 | I84: =Thesis!I31*I83*1 -> 51.268187 | J84: =Thesis!J31*J83*1 -> 58.980426 | K84: =Thesis!K31*K83*1 -> 58.042727 | L84: =Thesis!L31*L83*1 -> 64.596556 | M84: =Thesis!M31*M83*1 -> 68.203703 | N84: 對外 GW × 每 GW 年營收；9M26＝(Q2＋Q3 SI S&I) × ext_sh（Customer B 衍生）
A85: SI 其他收入年增 | B85: % | H85: =g27_nr+(gl_nr-g27_nr)*MIN(1,(2027-2027)/(conv_n-1)) -> 0.5 | I85: =g27_nr+(gl_nr-g27_nr)*MIN(1,(2028-2027)/(conv_n-1)) -> 0.38333333 | J85: =g27_nr+(gl_nr-g27_nr)*MIN(1,(2029-2027)/(conv_n-1)) -> 0.26666667 | K85: =g27_nr+(gl_nr-g27_nr)*MIN(1,(2030-2027)/(conv_n-1)) -> 0.15 | L85: =g27_nr+(gl_nr-g27_nr)*MIN(1,(2031-2027)/(conv_n-1)) -> 0.15 | M85: =g27_nr+(gl_nr-g27_nr)*MIN(1,(2032-2027)/(conv_n-1)) -> 0.15 | N85: FY2027＝g27_nr（以 Q4 26 備考年化為基期），FY2030 收斂到 gl_nr
A86: Grok／Cursor／X 訂閱、資料授權與 API（命題子列） | B86: US$B | E86: =Q!H14-E84 -> 3.05548 | F86: =nr_q3+cur_pf -> 2.50516 | G86: =E86+F86 -> 5.56064 | H86: =F86*4*(1+H85)^0.625 -> 12.91078 | I86: =H86*(1+I85) -> 17.859913 | J86: =I86*(1+J85) -> 22.622556 | K86: =J86*(1+K85) -> 26.01594 | L86: =K86*(1+L85) -> 29.918331 | M86: =L86*(1+M85) -> 34.406081 | N86: Q4 26＝2026Q3 值＋Cursor 備考補足（審查第 8 條：以備考全季為起點）；FY2027＝Q4 26 × 4 ×(1＋年增)^0.625
A87: SI Solutions & Infrastructure | B87: US$B | D87: =Q!G14 -> 0.955 | E87: =Q!H14 -> 9.691 | F87: =F84+F86 -> 8.7941795 | G87: =E87+F87 -> 18.485179 | H87: =H84+H86 -> 48.945339 | I87: =I84+I86 -> 69.1281 | J87: =J84+J86 -> 81.602982 | K87: =K84+K86 -> 84.058667 | L87: =L84+L86 -> 94.514887 | M87: =M84+M86 -> 102.60978
A88: Advertising 年增 | B88: % | F88: =g0_ads -> -0.056689342 | H88: =g0_ads+(gl_ads-g0_ads)*MIN(1,(2027-2026)/conv_n) -> -0.035017007 | I88: =g0_ads+(gl_ads-g0_ads)*MIN(1,(2028-2026)/conv_n) -> -0.013344671 | J88: =g0_ads+(gl_ads-g0_ads)*MIN(1,(2029-2026)/conv_n) -> 0.0083276644 | K88: =g0_ads+(gl_ads-g0_ads)*MIN(1,(2030-2026)/conv_n) -> 0.03 | L88: =g0_ads+(gl_ads-g0_ads)*MIN(1,(2031-2026)/conv_n) -> 0.03 | M88: =g0_ads+(gl_ads-g0_ads)*MIN(1,(2032-2026)/conv_n) -> 0.03 | N88: 起點＝9M 年增（Q 頁），FY2030 收斂到 gl_ads
A89: Advertising | B89: US$B | D89: =Q!G13 -> 1.323 | E89: =Q!H13 -> 1.248 | F89: =ads_q3*(1+F88)^0.25 -> 0.53020762 | G89: =E89+F89 -> 1.7782076 | H89: =G89*(1+H88) -> 1.7159401 | I89: =H89*(1+I88) -> 1.6930415 | J89: =I89*(1+J88) -> 1.7071405 | K89: =J89*(1+K88) -> 1.7583547 | L89: =K89*(1+L88) -> 1.8111054 | M89: =L89*(1+M88) -> 1.8654386
A90: SI (Super Intelligence; formerly AI) | B90: US$B | C90: =Q!I15 -> 3.201 | D90: =Q!G15 -> 2.278 | E90: =Q!H15 -> 10.939 | F90: =F89+F87 -> 9.3243871 | G90: =E90+F90 -> 20.263387 | H90: =H89+H87 -> 50.661279 | I90: =I89+I87 -> 70.821142 | J90: =J89+J87 -> 83.310123 | K90: =K89+K87 -> 85.817022 | L90: =L89+L87 -> 96.325993 | M90: =M89+M87 -> 104.47522
A91: 客戶發射次數 | B91: 次 | E91: =Q!H57 -> 29 | F91: =nl_q4 -> 12 | G91: =E91+F91 -> 41 | H91: =nl_27 -> 48 | I91: =H91*(1+g_nl) -> 50.4 | J91: =I91*(1+g_nl) -> 52.92 | K91: =J91*(1+g_nl) -> 55.566 | L91: =K91*(1+g_nl) -> 58.3443 | M91: =L91*(1+g_nl) -> 61.261515
A92: 每次客戶發射收入 | B92: US$B／次 | E92: =rpl0 -> 0.072689655 | F92: =rpl0 -> 0.072689655 | H92: =rpl0*(1+g_rpl)^(2027-2026) -> 0.074870345 | I92: =rpl0*(1+g_rpl)^(2028-2026) -> 0.077116455 | J92: =rpl0*(1+g_rpl)^(2029-2026) -> 0.079429949 | K92: =rpl0*(1+g_rpl)^(2030-2026) -> 0.081812847 | L92: =rpl0*(1+g_rpl)^(2031-2026) -> 0.084267233 | M92: =rpl0*(1+g_rpl)^(2032-2026) -> 0.08679525
A93: Launch Services | B93: US$B | D93: =Q!G5 -> 2.056 | E93: =Q!H5 -> 2.108 | F93: =F91*F92 -> 0.87227586 | G93: =E93+F93 -> 2.9802759 | H93: =H91*H92 -> 3.5937766 | I93: =I91*I92 -> 3.8866693 | J93: =J91*J92 -> 4.2034329 | K93: =K91*K92 -> 4.5460127 | L93: =L91*L92 -> 4.9165127 | M93: =M91*M92 -> 5.3172085
A94: Launch & Development 年增 | B94: % | F94: =g0_ld -> 0.015561016 | H94: =g0_ld+(gl_ld-g0_ld)*MIN(1,(2027-2026)/conv_n) -> 0.031670762 | I94: =g0_ld+(gl_ld-g0_ld)*MIN(1,(2028-2026)/conv_n) -> 0.047780508 | J94: =g0_ld+(gl_ld-g0_ld)*MIN(1,(2029-2026)/conv_n) -> 0.063890254 | K94: =g0_ld+(gl_ld-g0_ld)*MIN(1,(2030-2026)/conv_n) -> 0.08 | L94: =g0_ld+(gl_ld-g0_ld)*MIN(1,(2031-2026)/conv_n) -> 0.08 | M94: =g0_ld+(gl_ld-g0_ld)*MIN(1,(2032-2026)/conv_n) -> 0.08
A95: Launch & Development | B95: US$B | D95: =Q!G6 -> 1.221 | E95: =Q!H6 -> 1.24 | F95: =ld_9m/3*(1+F94)^0.25 -> 0.41493201 | G95: =E95+F95 -> 1.654932 | H95: =G95*(1+H94) -> 1.707345 | I95: =H95*(1+I94) -> 1.7889228 | J95: =I95*(1+J94) -> 1.9032175 | K95: =J95*(1+K94) -> 2.0554749 | L95: =K95*(1+L94) -> 2.2199129 | M95: =L95*(1+M94) -> 2.3975059 | N95: Q4 26＝9M26 季均 ×(1＋年增)^0.25（里程碑收入不規則）
A96: Space | B96: US$B | C96: =Q!I7 -> 4.086 | D96: =Q!G7 -> 3.277 | E96: =Q!H7 -> 3.348 | F96: =F93+F95 -> 1.2872079 | G96: =E96+F96 -> 4.6352079 | H96: =H93+H95 -> 5.3011215 | I96: =I93+I95 -> 5.6755921 | J96: =J93+J95 -> 6.1066504 | K96: =K93+K95 -> 6.6014876 | L96: =L93+L95 -> 7.1364256 | M96: =M93+M95 -> 7.7147144
A97: Starlink 消費訂戶（期末，百萬） | B97: 百萬 | E97: =subs_q3 -> 13.6 | F97: =E97+nadd_q4 -> 15.2 | H97: =F97+nadd_C -> 19.2 | I97: =H97+nadd_C*(1-nadd_dec)^(2028-2027) -> 22.8 | J97: =I97+nadd_C*(1-nadd_dec)^(2029-2027) -> 26.04 | K97: =J97+nadd_C*(1-nadd_dec)^(2030-2027) -> 28.956 | L97: =K97+nadd_C*(1-nadd_dec)^(2031-2027) -> 31.5804 | M97: =L97+nadd_C*(1-nadd_dec)^(2032-2027) -> 33.94236
A98: 平均消費訂戶 | B98: 百萬 | F98: =(E97+F97)/2 -> 14.4 | H98: =(F97+H97)/2 -> 17.2 | I98: =(H97+I97)/2 -> 21 | J98: =(I97+J97)/2 -> 24.42 | K98: =(J97+K97)/2 -> 27.498 | L98: =(K97+L97)/2 -> 30.2682 | M98: =(L97+M97)/2 -> 32.76138
A99: 消費 ARPU（美元／月） | B99: US$ | F99: =arpu0*(1+g_arpu)^0.25 -> 68.652382 | H99: =arpu0*(1+g_arpu)^(2027+0.5-2026.75) -> 67.962391 | I99: =arpu0*(1+g_arpu)^(2028+0.5-2026.75) -> 66.603143 | J99: =arpu0*(1+g_arpu)^(2029+0.5-2026.75) -> 65.27108 | K99: =arpu0*(1+g_arpu)^(2030+0.5-2026.75) -> 63.965658 | L99: =arpu0*(1+g_arpu)^(2031+0.5-2026.75) -> 62.686345 | M99: =arpu0*(1+g_arpu)^(2032+0.5-2026.75) -> 61.432618
A100: Consumer | B100: US$B | D100: =Q!G9 -> 5.198 | E100: =Q!H9 -> 7.754 | F100: =F98*F99/1000*12*0.25*uplift -> 3.4934362 | G100: =E100+F100 -> 11.247436 | H100: =H98*H99/1000*12*1*uplift -> 16.52311 | I100: =I98*I99/1000*12*1*uplift -> 19.770093 | J100: =J98*J99/1000*12*1*uplift -> 22.529998 | K100: =K98*K99/1000*12*1*uplift -> 24.862379 | L100: =L98*L99/1000*12*1*uplift -> 26.81972 | M100: =M98*M99/1000*12*1*uplift -> 28.448273 | N100: 平均訂戶 × ARPU × 月數 × uplift（2026Q3 校準，含 Kits）
A101: Enterprise & Government 年增 | B101: % | F101: =g0_eg+g0_eg_adj -> 0.70280311 | H101: =g0_eg+g0_eg_adj+(gl_eg-g0_eg+g0_eg_adj)*MIN(1,(2027-2026)/conv_n) -> 0.55210233 | I101: =g0_eg+g0_eg_adj+(gl_eg-g0_eg+g0_eg_adj)*MIN(1,(2028-2026)/conv_n) -> 0.40140155 | J101: =g0_eg+g0_eg_adj+(gl_eg-g0_eg+g0_eg_adj)*MIN(1,(2029-2026)/conv_n) -> 0.25070078 | K101: =g0_eg+g0_eg_adj+(gl_eg-g0_eg+g0_eg_adj)*MIN(1,(2030-2026)/conv_n) -> 0.1 | L101: =g0_eg+g0_eg_adj+(gl_eg-g0_eg+g0_eg_adj)*MIN(1,(2031-2026)/conv_n) -> 0.1 | M101: =g0_eg+g0_eg_adj+(gl_eg-g0_eg+g0_eg_adj)*MIN(1,(2032-2026)/conv_n) -> 0.1 | N101: 起點＝9M 年增 +70%（Q 頁），FY2030 收斂到 gl_eg
A102: Enterprise & Government | B102: US$B | D102: =Q!G10 -> 2.961 | E102: =Q!H10 -> 5.042 | F102: =eg_q3*(1+F101)^0.25 -> 2.4297333 | G102: =E102+F102 -> 7.4717333 | H102: =G102*(1+H101) -> 11.596895 | I102: =H102*(1+I101) -> 16.251906 | J102: =I102*(1+J101) -> 20.326272 | K102: =J102*(1+K101) -> 22.358899 | L102: =K102*(1+L101) -> 24.594789 | M102: =L102*(1+M101) -> 27.054267
A103: Connectivity | B103: US$B | C103: =Q!I11 -> 11.387 | D103: =Q!G11 -> 8.159 | E103: =Q!H11 -> 12.796 | F103: =F100+F102 -> 5.9231694 | G103: =E103+F103 -> 18.719169 | H103: =H100+H102 -> 28.120005 | I103: =I100+I102 -> 36.021999 | J103: =J100+J102 -> 42.85627 | K103: =K100+K102 -> 47.221278 | L103: =L100+L102 -> 51.414509 | M103: =M100+M102 -> 55.502541
...

Sheet PL
A1: PL — 分部營收 → 分部調整後 EBITDA（公司定義，不含 SBC）− 折舊攤銷 − 股權報酬（含 Cursor 收購後服務期獎酬）→ 分部營業利益 → 合併 → 利息 → 稅 → 淨利 → EPS（三情境；US$B，EPS 美元）。實績欄 FY2025*（二手轉述 S-1，只有分部營收與營業利益）、9M25A、9M26A 取自 Q 頁；FY2026E＝9M 實績＋Q4 模型
A2: 分部調整後 EBITDA：Space＝營收 × 利益率（9M26 −5.9% → FY2030 m_spl）；Connectivity＝營收 × m_cn（9M26）；SI＝對外出租營收 − 對外 GW 營運費用（Tokenomics）＋SI 其他收入 × m_so（2026Q3 校準） − 自用增量營運費用。折舊：Space／Connectivity 基礎折舊（2026Q3 × 4，直線遞減到 0）＋新增資本支出折舊；SI＝基礎折舊（汰換遞減）＋新增 AI 折舊。三分部合計＝合併（無公司層級調節項）
A4: 分部對帳彙總（三情境 × 全部年度取絕對值最大者；實績欄同列）
A5: 項目 | B5: 單位 | C5: FY2025* | D5: 9M25A | E5: 9M26A | F5: Q4 26E | G5: FY2026E | H5: FY2027E | I5: FY2028E | J5: FY2029E | K5: FY2030E | L5: FY2031E | M5: FY2032E | N5: 說明
A6: 檢查：Space 子列合計 − Space | B6: US$B | D6: =MAX(ABS(D28),ABS(D90),ABS(D152)) -> 0 | E6: =MAX(ABS(E28),ABS(E90),ABS(E152)) -> 0 | F6: =MAX(ABS(F28),ABS(F90),ABS(F152)) -> 0 | G6: =MAX(ABS(G28),ABS(G90),ABS(G152)) -> 0 | H6: =MAX(ABS(H28),ABS(H90),ABS(H152)) -> 0 | I6: =MAX(ABS(I28),ABS(I90),ABS(I152)) -> 0 | J6: =MAX(ABS(J28),ABS(J90),ABS(J152)) -> 0 | K6: =MAX(ABS(K28),ABS(K90),ABS(K152)) -> 0 | ... M6: =MAX(ABS(M28),ABS(M90),ABS(M152)) -> 0 | N6: 三情境各區塊同名核對列的最大絕對值；必須為 0（tools/segment_check 讀本列）
A7: 檢查：Connectivity 子列合計 − Connectivity | B7: US$B | D7: =MAX(ABS(D29),ABS(D91),ABS(D153)) -> 0 | E7: =MAX(ABS(E29),ABS(E91),ABS(E153)) -> 0 | F7: =MAX(ABS(F29),ABS(F91),ABS(F153)) -> 0 | G7: =MAX(ABS(G29),ABS(G91),ABS(G153)) -> 0 | H7: =MAX(ABS(H29),ABS(H91),ABS(H153)) -> 0 | I7: =MAX(ABS(I29),ABS(I91),ABS(I153)) -> 0 | J7: =MAX(ABS(J29),ABS(J91),ABS(J153)) -> 0 | K7: =MAX(ABS(K29),ABS(K91),ABS(K153)) -> 0 | ... M7: =MAX(ABS(M29),ABS(M91),ABS(M153)) -> 0 | N7: 三情境各區塊同名核對列的最大絕對值；必須為 0（tools/segment_check 讀本列）
A8: 檢查：SI 子列合計 − SI | B8: US$B | D8: =MAX(ABS(D30),ABS(D92),ABS(D154)) -> 0 | E8: =MAX(ABS(E30),ABS(E92),ABS(E154)) -> 0 | F8: =MAX(ABS(F30),ABS(F92),ABS(F154)) -> 0 | G8: =MAX(ABS(G30),ABS(G92),ABS(G154)) -> 0 | H8: =MAX(ABS(H30),ABS(H92),ABS(H154)) -> 0 | I8: =MAX(ABS(I30),ABS(I92),ABS(I154)) -> 0 | J8: =MAX(ABS(J30),ABS(J92),ABS(J154)) -> 0 | K8: =MAX(ABS(K30),ABS(K92),ABS(K154)) -> 0 | ... M8: =MAX(ABS(M30),ABS(M92),ABS(M154)) -> 0 | N8: 三情境各區塊同名核對列的最大絕對值；必須為 0（tools/segment_check 讀本列）
A9: 檢查：SI S&I 命題子列合計 − SI Solutions & Infrastructure | B9: US$B | E9: =MAX(ABS(E31),ABS(E93),ABS(E155)) -> 0 | F9: =MAX(ABS(F31),ABS(F93),ABS(F155)) -> 0 | G9: =MAX(ABS(G31),ABS(G93),ABS(G155)) -> 0 | H9: =MAX(ABS(H31),ABS(H93),ABS(H155)) -> 0 | I9: =MAX(ABS(I31),ABS(I93),ABS(I155)) -> 0 | J9: =MAX(ABS(J31),ABS(J93),ABS(J155)) -> 0 | K9: =MAX(ABS(K31),ABS(K93),ABS(K155)) -> 0 | L9: =MAX(ABS(L31),ABS(L93),ABS(L155)) -> 0 | M9: =MAX(ABS(M31),ABS(M93),ABS(M155)) -> 0 | N9: 三情境各區塊同名核對列的最大絕對值；必須為 0（tools/segment_check 讀本列）
A10: 檢查：分部合計 − 合併營收 | B10: US$B | C10: =MAX(ABS(C32),ABS(C94),ABS(C156)) -> 0 | D10: =MAX(ABS(D32),ABS(D94),ABS(D156)) -> 0 | E10: =MAX(ABS(E32),ABS(E94),ABS(E156)) -> 0 | F10: =MAX(ABS(F32),ABS(F94),ABS(F156)) -> 0 | G10: =MAX(ABS(G32),ABS(G94),ABS(G156)) -> 0 | H10: =MAX(ABS(H32),ABS(H94),ABS(H156)) -> 0 | I10: =MAX(ABS(I32),ABS(I94),ABS(I156)) -> 0 | J10: =MAX(ABS(J32),ABS(J94),ABS(J156)) -> 0 | ... M10: =MAX(ABS(M32),ABS(M94),ABS(M156)) -> 0 | N10: 三情境各區塊同名核對列的最大絕對值；必須為 0（tools/segment_check 讀本列）
A11: 檢查：分部營業利益合計 − 合併營業利益 | B11: US$B | C11: =MAX(ABS(C55),ABS(C117),ABS(C179)) -> 0 | D11: =MAX(ABS(D55),ABS(D117),ABS(D179)) -> 0 | E11: =MAX(ABS(E55),ABS(E117),ABS(E179)) -> 0 | F11: =MAX(ABS(F55),ABS(F117),ABS(F179)) -> 0 | G11: =MAX(ABS(G55),ABS(G117),ABS(G179)) -> 0 | H11: =MAX(ABS(H55),ABS(H117),ABS(H179)) -> 0 | I11: =MAX(ABS(I55),ABS(I117),ABS(I179)) -> 0 | J11: =MAX(ABS(J55),ABS(J117),ABS(J179)) -> 0 | ... M11: =MAX(ABS(M55),ABS(M117),ABS(M179)) -> 0 | N11: 三情境各區塊同名核對列的最大絕對值；必須為 0（tools/segment_check 讀本列）
A13: 情境 A（算力租金維持高檔、Starlink 增長快）
A14: 項目 | B14: 單位 | C14: FY2025* | D14: 9M25A | E14: 9M26A | F14: Q4 26E | G14: FY2026E | H14: FY2027E | I14: FY2028E | J14: FY2029E | K14: FY2030E | L14: FY2031E | M14: FY2032E | N14: 說明
A15: Launch Services | B15: US$B | D15: =Seg!D17 -> 2.056 | E15: =Seg!E17 -> 2.108 | F15: =Seg!F17 -> 0.87227586 | G15: =Seg!G17 -> 2.9802759 | H15: =Seg!H17 -> 3.5937766 | I15: =Seg!I17 -> 3.8866693 | J15: =Seg!J17 -> 4.2034329 | K15: =Seg!K17 -> 4.5460127 | ... M15: =Seg!M17 -> 5.3172085
A16: Launch & Development | B16: US$B | D16: =Seg!D19 -> 1.221 | E16: =Seg!E19 -> 1.24 | F16: =Seg!F19 -> 0.41493201 | G16: =Seg!G19 -> 1.654932 | H16: =Seg!H19 -> 1.707345 | I16: =Seg!I19 -> 1.7889228 | J16: =Seg!J19 -> 1.9032175 | K16: =Seg!K19 -> 2.0554749 | ... M16: =Seg!M19 -> 2.3975059
A17: Space | B17: US$B | C17: =Seg!C20 -> 4.086 | D17: =Seg!D20 -> 3.277 | E17: =Seg!E20 -> 3.348 | F17: =Seg!F20 -> 1.2872079 | G17: =Seg!G20 -> 4.6352079 | H17: =Seg!H20 -> 5.3011215 | I17: =Seg!I20 -> 5.6755921 | J17: =Seg!J20 -> 6.1066504 | ... M17: =Seg!M20 -> 7.7147144
A18: Consumer | B18: US$B | D18: =Seg!D24 -> 5.198 | E18: =Seg!E24 -> 7.754 | F18: =Seg!F24 -> 3.4934362 | G18: =Seg!G24 -> 11.247436 | H18: =Seg!H24 -> 17.964079 | I18: =Seg!I24 -> 23.865327 | J18: =Seg!J24 -> 28.909807 | K18: =Seg!K24 -> 33.201827 | ... M18: =Seg!M24 -> 39.885313
A19: Enterprise & Government | B19: US$B | D19: =Seg!D26 -> 2.961 | E19: =Seg!E26 -> 5.042 | F19: =Seg!F26 -> 2.4297333 | G19: =Seg!G26 -> 7.4717333 | H19: =Seg!H26 -> 11.596895 | I19: =Seg!I26 -> 16.251906 | J19: =Seg!J26 -> 20.326272 | K19: =Seg!K26 -> 22.358899 | ... M19: =Seg!M26 -> 27.054267
A20: Connectivity | B20: US$B | C20: =Seg!C27 -> 11.387 | D20: =Seg!D27 -> 8.159 | E20: =Seg!E27 -> 12.796 | F20: =Seg!F27 -> 5.9231694 | G20: =Seg!G27 -> 18.719169 | H20: =Seg!H27 -> 29.560973 | I20: =Seg!I27 -> 40.117233 | J20: =Seg!J27 -> 49.236079 | ... M20: =Seg!M27 -> 66.939581
A21: Advertising | B21: US$B | D21: =Seg!D13 -> 1.323 | E21: =Seg!E13 -> 1.248 | F21: =Seg!F13 -> 0.53020762 | G21: =Seg!G13 -> 1.7782076 | H21: =Seg!H13 -> 1.7159401 | I21: =Seg!I13 -> 1.6930415 | J21: =Seg!J13 -> 1.7071405 | K21: =Seg!K13 -> 1.7583547 | ... M21: =Seg!M13 -> 1.8654386
A22: SI 對外雲端服務（命題子列） | B22: US$B | E22: =Seg!E8 -> 6.63552 | F22: =Seg!F8 -> 6.2890195 | G22: =Seg!G8 -> 12.924539 | H22: =Seg!H8 -> 39.310508 | I22: =Seg!I8 -> 61.998941 | J22: =Seg!J8 -> 80.795347 | K22: =Seg!K8 -> 92.868364 | L22: =Seg!L8 -> 103.35449 | M22: =Seg!M8 -> 109.12592
A23: Grok／Cursor／X 訂閱、資料授權與 API（命題子列） | B23: US$B | E23: =Seg!E10 -> 3.05548 | F23: =Seg!F10 -> 2.50516 | G23: =Seg!G10 -> 5.56064 | H23: =Seg!H10 -> 12.91078 | I23: =Seg!I10 -> 17.859913 | J23: =Seg!J10 -> 22.622556 | K23: =Seg!K10 -> 26.01594 | L23: =Seg!L10 -> 29.918331 | M23: =Seg!M10 -> 34.406081
A24: SI Solutions & Infrastructure | B24: US$B | D24: =Seg!D11 -> 0.955 | E24: =Seg!E11 -> 9.691 | F24: =Seg!F11 -> 8.7941795 | G24: =Seg!G11 -> 18.485179 | H24: =Seg!H11 -> 52.221288 | I24: =Seg!I11 -> 79.858854 | J24: =Seg!J11 -> 103.4179 | K24: =Seg!K11 -> 118.8843 | ... M24: =Seg!M11 -> 143.532
A25: SI (Super Intelligence; formerly AI) | B25: US$B | C25: =Seg!C14 -> 3.201 | D25: =Seg!D14 -> 2.278 | E25: =Seg!E14 -> 10.939 | F25: =Seg!F14 -> 9.3243871 | G25: =Seg!G14 -> 20.263387 | H25: =Seg!H14 -> 53.937229 | I25: =Seg!I14 -> 81.551895 | J25: =Seg!J14 -> 105.12504 | ... M25: =Seg!M14 -> 145.39744
A26: 合併營收 | B26: US$B | C26: =Seg!C28 -> 18.674 | D26: =Seg!D28 -> 13.714 | E26: =Seg!E28 -> 27.083 | F26: =Seg!F28 -> 16.534764 | G26: =Seg!G28 -> 43.617764 | H26: =Seg!H28 -> 88.799324 | I26: =Seg!I28 -> 127.34472 | J26: =Seg!J28 -> 160.46777 | ... M26: =Seg!M28 -> 220.05174
A27: 合併營收年增 | B27: % | E27: =E26/D26-1 -> 0.97484323 | G27: =G26/C26-1 -> 1.3357483 | H27: =H26/G26-1 -> 1.0358522 | I27: =I26/H26-1 -> 0.43407309 | J27: =J26/I26-1 -> 0.26010543 | K27: =K26/J26-1 -> 0.13919991 | L27: =L26/K26-1 -> 0.11402098 | M27: =M26/L26-1 -> 0.080547016
A28: 檢查：Space 子列合計 − Space | B28: US$B | D28: =D15+D16-D17 -> 0 | E28: =E15+E16-E17 -> 0 | F28: =F15+F16-F17 -> 0 | G28: =G15+G16-G17 -> 0 | H28: =H15+H16-H17 -> 0 | I28: =I15+I16-I17 -> 0 | J28: =J15+J16-J17 -> 0 | K28: =K15+K16-K17 -> 0 | ... M28: =M15+M16-M17 -> 0
A29: 檢查：Connectivity 子列合計 − Connectivity | B29: US$B | D29: =D18+D19-D20 -> 0 | E29: =E18+E19-E20 -> 0 | F29: =F18+F19-F20 -> 0 | G29: =G18+G19-G20 -> 0 | H29: =H18+H19-H20 -> 0 | I29: =I18+I19-I20 -> 0 | J29: =J18+J19-J20 -> 0 | K29: =K18+K19-K20 -> 0 | ... M29: =M18+M19-M20 -> 0
A30: 檢查：SI 子列合計 − SI | B30: US$B | D30: =D21+D24-D25 -> 0 | E30: =E21+E24-E25 -> 0 | F30: =F21+F24-F25 -> 0 | G30: =G21+G24-G25 -> 0 | H30: =H21+H24-H25 -> 0 | I30: =I21+I24-I25 -> 0 | J30: =J21+J24-J25 -> 0 | K30: =K21+K24-K25 -> 0 | ... M30: =M21+M24-M25 -> 0
A31: 檢查：SI S&I 命題子列合計 − SI Solutions & Infrastructure | B31: US$B | E31: =E22+E23-E24 -> 0 | F31: =F22+F23-F24 -> 0 | G31: =G22+G23-G24 -> 0 | H31: =H22+H23-H24 -> 0 | I31: =I22+I23-I24 -> 0 | J31: =J22+J23-J24 -> 0 | K31: =K22+K23-K24 -> 0 | L31: =L22+L23-L24 -> 0 | M31: =M22+M23-M24 -> 0
A32: 檢查：分部合計 − 合併營收 | B32: US$B | C32: =C17+C20+C25-C26 -> 0 | D32: =D17+D20+D25-D26 -> 0 | E32: =E17+E20+E25-E26 -> 0 | F32: =F17+F20+F25-F26 -> 0 | G32: =G17+G20+G25-G26 -> 0 | H32: =H17+H20+H25-H26 -> 0 | I32: =I17+I20+I25-I26 -> 0 | J32: =J17+J20+J25-J26 -> 0 | ... M32: =M17+M20+M25-M26 -> 0
A33: Space 調整後 EBITDA 率（9M26 → FY2030 m_spl） | B33: % | F33: =m_sp0 -> -0.059438471 | H33: =m_sp0+(m_spl-m_sp0)*MIN(1,(2027-2026)/conv_n) -> 0.005421147 | I33: =m_sp0+(m_spl-m_sp0)*MIN(1,(2028-2026)/conv_n) -> 0.070280765 | J33: =m_sp0+(m_spl-m_sp0)*MIN(1,(2029-2026)/conv_n) -> 0.13514038 | K33: =m_sp0+(m_spl-m_sp0)*MIN(1,(2030-2026)/conv_n) -> 0.2 | L33: =m_sp0+(m_spl-m_sp0)*MIN(1,(2031-2026)/conv_n) -> 0.2 | M33: =m_sp0+(m_spl-m_sp0)*MIN(1,(2032-2026)/conv_n) -> 0.2
A34: Space 分部調整後 EBITDA | B34: US$B | C34: =Q!I28 -> 0.653 | D34: =Q!G28 -> 0.803 | E34: =Q!H28 -> -0.199 | F34: =F17*F33 -> -0.076509667 | G34: =E34+F34 -> -0.27550967 | H34: =H17*H33 -> 0.028738159 | I34: =I17*I33 -> 0.39888495 | J34: =J17*J33 -> 0.82525507 | K34: =K17*K33 -> 1.3202975 | L34: =L17*L33 -> 1.4272851 | M34: =M17*M33 -> 1.5429429
A35: Connectivity 分部調整後 EBITDA | B35: US$B | C35: =Q!I29 -> 7.168 | D35: =Q!G29 -> 5.123 | E35: =Q!H29 -> 8.183 | F35: =F20*m_cn -> 3.7878474 | G35: =E35+F35 -> 11.970847 | H35: =H20*m_cn -> 18.904146 | I35: =I20*m_cn -> 25.654839 | J35: =J20*m_cn -> 31.486311 | K35: =K20*m_cn -> 35.530902 | L35: =L20*m_cn -> 39.283075 | M35: =M20*m_cn -> 42.807642
A36: SI 對外出租 EBITDA（營收 − 對外 GW × Tokenomics 營運費用） | B36: US$B | F36: =F22-Thesis!F35 -> 5.6396031 | G36: =F36 -> 5.6396031 | H36: =H22-Thesis!H35 -> 35.228762 | I36: =I22-Thesis!I35 -> 55.49721 | J36: =J22-Thesis!J35 -> 72.11742 | K36: =K22-Thesis!K35 -> 82.5525 | L36: =L22-Thesis!L35 -> 91.916346 | M36: =M22-Thesis!M35 -> 97.07009
A37: SI 其他 EBITDA（(SI 其他收入＋廣告) × m_so − 自用增量營運費用） | B37: US$B | F37: =(F23+F21)*m_so-Thesis!F36 -> 0.48462444 | G37: =F37 -> 0.48462444 | H37: =(H23+H21)*m_so-Thesis!H36 -> 1.7812585 | I37: =(I23+I21)*m_so-Thesis!I36 -> 1.6724813 | J37: =(J23+J21)*m_so-Thesis!J36 -> 1.6332524 | K37: =(K23+K21)*m_so-Thesis!K36 -> 1.5782701 | L37: =(L23+L21)*m_so-Thesis!L36 -> 1.8100812 | M37: =(M23+M21)*m_so-Thesis!M36 -> 2.3372907
A38: SI 分部調整後 EBITDA | B38: US$B | C38: =Q!I30 -> -1.237 | D38: =Q!G30 -> -0.813 | E38: =Q!H30 -> 5.49 | F38: =F36+F37 -> 6.1242276 | G38: =E38+F38 -> 11.614228 | H38: =H36+H37 -> 37.01002 | I38: =I36+I37 -> 57.169692 | J38: =J36+J37 -> 73.750672 | K38: =K36+K37 -> 84.13077 | L38: =L36+L37 -> 93.726427 | M38: =M36+M37 -> 99.407381
A39: 合併調整後 EBITDA（分部合計） | B39: US$B | C39: =C34+C35+C38 -> 6.584 | D39: =D34+D35+D38 -> 5.113 | E39: =E34+E35+E38 -> 13.474 | F39: =F34+F35+F38 -> 9.8355653 | G39: =G34+G35+G38 -> 23.309565 | H39: =H34+H35+H38 -> 55.942904 | I39: =I34+I35+I38 -> 83.223415 | J39: =J34+J35+J38 -> 106.06224 | ... M39: =M34+M35+M38 -> 143.75797
A40: Space 折舊攤銷（基礎遞減＋新增） | B40: US$B | D40: =Q!G42 -> 0.572 | E40: =Q!H42 -> 0.509 | F40: =da_sp0*0.25*MAX(0,1-(2026.875-t_val)/rem_sp)+Seg!F39 -> 0.18958307 | G40: =E40+F40 -> 0.69858307 | H40: =da_sp0*1*MAX(0,1-(2027.5-t_val)/rem_sp)+Seg!H39 -> 0.90003388 | I40: =da_sp0*1*MAX(0,1-(2028.5-t_val)/rem_sp)+Seg!I39 -> 1.2256325 | J40: =da_sp0*1*MAX(0,1-(2029.5-t_val)/rem_sp)+Seg!J39 -> 1.4631198 | K40: =da_sp0*1*MAX(0,1-(2030.5-t_val)/rem_sp)+Seg!K39 -> 1.5987329 | L40: =da_sp0*1*MAX(0,1-(2031.5-t_val)/rem_sp)+Seg!L39 -> 1.6527895 | M40: =da_sp0*1*MAX(0,1-(2032.5-t_val)/rem_sp)+Seg!M39 -> 1.8342195
A41: Connectivity 折舊攤銷（基礎遞減＋新增） | B41: US$B | D41: =Q!G44 -> 1.706 | E41: =Q!H44 -> 2.574 | F41: =da_cn0*0.25*MAX(0,1-(2026.875-t_val)/rem_cn)+Seg!F40 -> 0.96537072 | G41: =E41+F41 -> 3.5393707 | H41: =da_cn0*1*MAX(0,1-(2027.5-t_val)/rem_cn)+Seg!H40 -> 3.6935879 | I41: =da_cn0*1*MAX(0,1-(2028.5-t_val)/rem_cn)+Seg!I40 -> 4.1580262 | J41: =da_cn0*1*MAX(0,1-(2029.5-t_val)/rem_cn)+Seg!J40 -> 5.1858603 | K41: =da_cn0*1*MAX(0,1-(2030.5-t_val)/rem_cn)+Seg!K40 -> 7.6649296 | L41: =da_cn0*1*MAX(0,1-(2031.5-t_val)/rem_cn)+Seg!L40 -> 10.815797 | M41: =da_cn0*1*MAX(0,1-(2032.5-t_val)/rem_cn)+Seg!M40 -> 14.204114
A42: SI 折舊攤銷（基礎＋新增 AI） | B42: US$B | D42: =Q!G46 -> 2.506 | E42: =Q!H46 -> 5.851 | F42: =Thesis!F62+Thesis!F55 -> 2.8048939 | G42: =E42+F42 -> 8.6558939 | H42: =Thesis!H62+Thesis!H55 -> 17.800989 | I42: =Thesis!I62+Thesis!I55 -> 28.377051 | J42: =Thesis!J62+Thesis!J55 -> 38.87076 | K42: =Thesis!K62+Thesis!K55 -> 46.782348 | L42: =Thesis!L62+Thesis!L55 -> 52.333455 | M42: =Thesis!M62+Thesis!M55 -> 55.095208
A43: 折舊攤銷合計 | B43: US$B | D43: =D40+D41+D42 -> 4.784 | E43: =E40+E41+E42 -> 8.934 | F43: =F40+F41+F42 -> 3.9598477 | G43: =G40+G41+G42 -> 12.893848 | H43: =H40+H41+H42 -> 22.394611 | I43: =I40+I41+I42 -> 33.76071 | J43: =J40+J41+J42 -> 45.51974 | K43: =K40+K41+K42 -> 56.046011 | ... M43: =M40+M41+M42 -> 71.133541
A44: 其中：新增 AI 折舊 | B44: US$B | F44: =Thesis!F55 -> 0.33189389 | G44: =F44 -> 0.33189389 | H44: =Thesis!H55 -> 7.9089887 | I44: =Thesis!I55 -> 18.485051 | J44: =Thesis!J55 -> 28.97876 | K44: =Thesis!K55 -> 37.234477 | L44: =Thesis!L55 -> 44.620937 | M44: =Thesis!M55 -> 51.871867
A45: Space 股權報酬（一般；營收 × 2026Q3 比率） | B45: US$B | D45: =Q!G43 -> 0.383 | E45: =Q!H43 -> 0.503 | F45: =F17*sbcr_space -> 0.13039627 | G45: =E45+F45 -> 0.63339627 | H45: =H17*sbcr_space -> 0.53701231 | I45: =I17*sbcr_space -> 0.5749468 | J45: =J17*sbcr_space -> 0.61861371 | K45: =K17*sbcr_space -> 0.66874153 | L45: =L17*sbcr_space -> 0.72293163 | M45: =M17*sbcr_space -> 0.78151323
A46: Connectivity 股權報酬（一般；營收 × 2026Q3 比率） | B46: US$B | D46: =Q!G45 -> 0.27 | E46: =Q!H45 -> 0.398 | F46: =F20*sbcr_conn -> 0.1647833 | G46: =E46+F46 -> 0.5627833 | H46: =H20*sbcr_conn -> 0.82238989 | I46: =I20*sbcr_conn -> 1.1160663 | J46: =J20*sbcr_conn -> 1.3697537 | K46: =K20*sbcr_conn -> 1.5457062 | L46: =L20*sbcr_conn -> 1.7089375 | M46: =M20*sbcr_conn -> 1.8622673
A47: SI 股權報酬（一般；營收 × 2026Q3 比率） | B47: US$B | D47: =Q!G47 -> 0.391 | E47: =Q!H47 -> 1.715 | F47: =F25*sbcr_si -> 1.0126087 | G47: =E47+F47 -> 2.7276087 | H47: =H25*sbcr_si -> 5.8574689 | I47: =I25*sbcr_si -> 8.8563632 | J47: =J25*sbcr_si -> 11.416357 | K47: =K25*sbcr_si -> 13.101537 | L47: =L25*sbcr_si -> 14.669829 | M47: =M25*sbcr_si -> 15.789855
A48: SI 收購相關股權報酬（Cursor）與其他調節項（收購成本、重組、減損） | B48: US$B | D48: 0 | E48: =Q!H48+Q!H49+Q!H50+Q!H51 -> 1.219 | F48: =sbc_cur_left/sbc_cur_yrs*0.25 -> 2.0904717 | G48: =E48+F48 -> 3.3094717 | H48: =sbc_cur_left/sbc_cur_yrs -> 8.3618868 | I48: =sbc_cur_left/sbc_cur_yrs -> 8.3618868 | J48: =MAX(0,sbc_cur_left-2.25*sbc_cur_left/sbc_cur_yrs) -> 3.3447547 | K48: 0 | L48: 0 | M48: 0 | N48: 預測期只有 Cursor 收購後服務期獎酬（直線攤到 2029-06）；9M25 的重組與減損另含在下方實績差額
A49: 股權報酬與其他調節合計 | B49: US$B | D49: =D45+D46+D47+D48 -> 1.044 | E49: =E45+E46+E47+E48 -> 3.835 | F49: =F45+F46+F47+F48 -> 3.39826 | G49: =G45+G46+G47+G48 -> 7.23326 | H49: =H45+H46+H47+H48 -> 15.578758 | I49: =I45+I46+I47+I48 -> 18.909263 | J49: =J45+J46+J47+J48 -> 16.749479 | K49: =K45+K46+K47+K48 -> 15.315985 | ... M49: =M45+M46+M47+M48 -> 18.433635
A50: Space 分部營業利益 | B50: US$B | C50: =Q!I21 -> -0.657 | D50: =Q!G21 -> -0.181 | E50: =Q!H21 -> -1.211 | F50: =F34-F40-F45 -> -0.39648901 | G50: =E50+F50 -> -1.607489 | H50: =H34-H40-H45 -> -1.408308 | I50: =I34-I40-I45 -> -1.4016943 | J50: =J34-J40-J45 -> -1.2564784 | K50: =K34-K40-K45 -> -0.94717688 | L50: =L34-L40-L45 -> -0.94843604 | M50: =M34-M40-M45 -> -1.0727898
A51: Connectivity 分部營業利益 | B51: US$B | C51: =Q!I22 -> 4.423 | D51: =Q!G22 -> 3.147 | E51: =Q!H22 -> 5.211 | F51: =F35-F41-F46 -> 2.6576934 | G51: =E51+F51 -> 7.8686934 | H51: =H35-H41-H46 -> 14.388168 | I51: =I35-I41-I46 -> 20.380746 | J51: =J35-J41-J46 -> 24.930697 | K51: =K35-K41-K46 -> 26.320266 | L51: =L35-L41-L46 -> 26.758341 | M51: =M35-M41-M46 -> 26.741261
A52: SI 分部營業利益 | B52: US$B | C52: =Q!I23 -> -6.355 | D52: =Q!G23 -> -4.182 | E52: =Q!H23 -> -3.295 | F52: =F38-F42-F47-F48 -> 0.21625328 | G52: =E52+F52 -> -3.0787467 | H52: =H38-H42-H47-H48 -> 4.9896757 | I52: =I38-I42-I47-I48 -> 11.574391 | J52: =J38-J42-J47-J48 -> 20.1188 | K52: =K38-K42-K47-K48 -> 24.246885 | L52: =L38-L42-L47-L48 -> 26.723144 | M52: =M38-M42-M47-M48 -> 28.522319
A53: 分部營業利益合計 | B53: US$B | C53: =C50+C51+C52 -> -2.589 | D53: =D50+D51+D52 -> -1.216 | E53: =E50+E51+E52 -> 0.705 | F53: =F50+F51+F52 -> 2.4774577 | G53: =G50+G51+G52 -> 3.1824577 | H53: =H50+H51+H52 -> 17.969535 | I53: =I50+I51+I52 -> 30.553443 | J53: =J50+J51+J52 -> 43.793019 | ... M53: =M50+M51+M52 -> 54.19079
A54: 合併營業利益 | B54: US$B | C54: =Q!I24 -> -2.589 | D54: =Q!G24 -> -1.216 | E54: =Q!H24 -> 0.705 | F54: =F39-F43-F49 -> 2.4774577 | G54: =E54+F54 -> 3.1824577 | H54: =H39-H43-H49 -> 17.969535 | I54: =I39-I43-I49 -> 30.553443 | J54: =J39-J43-J49 -> 43.793019 | K54: =K39-K43-K49 -> 49.619974 | L54: =L39-L43-L49 -> 52.533048 | M54: =M39-M43-M49 -> 54.19079 | N54: 預測期＝合併調整後 EBITDA − 折舊攤銷 − 股權報酬與調節（與分部合計獨立計算）
A55: 檢查：分部營業利益合計 − 合併營業利益 | B55: US$B | C55: =C53-C54 -> 0 | D55: =D53-D54 -> 0 | E55: =E53-E54 -> 0 | F55: =F53-F54 -> 0 | G55: =G53-G54 -> 0 | H55: =H53-H54 -> 0 | I55: =I53-I54 -> 0 | J55: =J53-J54 -> 0 | ... M55: =M53-M54 -> 0
A56: 自用 AI 影子效益（讀法 2；非財報營收） | B56: US$B | F56: =Thesis!F65 -> 0.15498463 | G56: =F56 -> 0.15498463 | H56: =Thesis!H65 -> 3.8721395 | I56: =Thesis!I65 -> 9.289173 | J56: =Thesis!J65 -> 14.231338 | K56: =Thesis!K65 -> 17.951109 | L56: =Thesis!L65 -> 20.49982 | M56: =Thesis!M65 -> 21.902599
A57: 營業利益（評價口徑；讀法 2 含影子效益） | B57: US$B | C57: =C54 -> -2.589 | D57: =D54 -> -1.216 | E57: =E54 -> 0.705 | F57: =F54+(internal_ai_reading=2)*F56 -> 2.6324423 | G57: =G54+(internal_ai_reading=2)*G56 -> 3.3374423 | H57: =H54+(internal_ai_reading=2)*H56 -> 21.841675 | I57: =I54+(internal_ai_reading=2)*I56 -> 39.842616 | J57: =J54+(internal_ai_reading=2)*J56 -> 58.024356 | K57: =K54+(internal_ai_reading=2)*K56 -> 67.571083 | L57: =L54+(internal_ai_reading=2)*L56 -> 73.032868 | M57: =M54+(internal_ai_reading=2)*M56 -> 76.093389
A58: 營業利益率 | B58: % | C58: =C54/C26 -> -0.13864196 | D58: =D54/D26 -> -0.088668514 | E58: =E54/E26 -> 0.02603109 | F58: =F54/F26 -> 0.14983326 | G58: =G54/G26 -> 0.07296242 | H58: =H54/H26 -> 0.20236117 | I58: =I54/I26 -> 0.23992705 | J58: =J54/J26 -> 0.2729085 | ... M58: =M54/M26 -> 0.24626386
A59: SI 營業利益率 | B59: % | C59: =C52/C25 -> -1.9853171 | D59: =D52/D25 -> -1.8358209 | E59: =E52/E25 -> -0.30121583 | F59: =F52/F25 -> 0.023192225 | G59: =G52/G25 -> -0.15193643 | H59: =H52/H25 -> 0.092508937 | I59: =I52/I25 -> 0.14192669 | J59: =J52/J25 -> 0.19137971 | ... M59: =M52/M25 -> 0.19616795
A60: 調整後 EBITDA 率 | B60: % | C60: =C39/C26 -> 0.35257577 | D60: =D39/D26 -> 0.37283068 | E60: =E39/E26 -> 0.49750766 | F60: =F39/F26 -> 0.59484158 | G60: =G39/G26 -> 0.53440532 | H60: =H39/H26 -> 0.62999245 | I60: =I39/I26 -> 0.65352859 | J60: =J39/J26 -> 0.66095663 | ... M60: =M39/M26 -> 0.65329166
A61: 利息收入（期初現金 × r_cash） | B61: US$B | F61: =r_cash*CF!F34*0.25 -> 0.826666 | G61: =F61 -> 0.826666 | H61: =r_cash*CF!H34*1 -> 2.9162329 | I61: =r_cash*CF!I34*1 -> 1.4367961 | J61: =r_cash*CF!J34*1 -> 1.104 | K61: =r_cash*CF!K34*1 -> 1.8464797 | L61: =r_cash*CF!L34*1 -> 3.4624409 | M61: =r_cash*CF!M34*1 -> 5.4030218
A62: 利息費用（期初債務 × r_debt） | B62: US$B | F62: =r_debt*CF!F40*0.25 -> 0.6746065 | G62: =F62 -> 0.6746065 | H62: =r_debt*CF!H40*1 -> 2.7758277 | I62: =r_debt*CF!I40*1 -> 3.0814298 | J62: =r_debt*CF!J40*1 -> 3.7256457 | K62: =r_debt*CF!K40*1 -> 3.8741977 | L62: =r_debt*CF!L40*1 -> 3.9380901 | M62: =r_debt*CF!M40*1 -> 3.9169862
A63: 其他收益（預測期 0） | B63: US$B | D63: =Q!G69 -> 0.342 | E63: =Q!H69 -> -0.937 | F63: 0 | G63: =E63+F63 -> -0.937 | H63: 0 | I63: 0 | J63: 0 | K63: 0 | L63: 0 | M63: 0 | N63: 9M26 −0.937（含債務清償損失 1.544、TBC 利益 0.561）
A64: 稅前利益 | B64: US$B | D64: =D54+Q!G67+Q!G68+D63 -> -1.876 | E64: =E54+Q!H67+Q!H68+E63 -> -0.774 | F64: =F54+F61-F62+F63 -> 2.6295172 | G64: =E64+F64 -> 1.8555172 | H64: =H54+H61-H62+H63 -> 18.109941 | I64: =I54+I61-I62+I63 -> 28.908809 | J64: =J54+J61-J62+J63 -> 41.171373 | K64: =K54+K61-K62+K63 -> 47.592256 | L64: =L54+L61-L62+L63 -> 52.057399 | M64: =M54+M61-M62+M63 -> 55.676826
A65: 所得稅 | B65: US$B | D65: =Q!G72 -> 0.714 | E65: =Q!H72 -> -0.361 | F65: =F64*tax -> 0.31554206 | G65: =E65+F65 -> -0.045457941 | H65: =H64*tax -> 2.1731929 | I65: =I64*tax -> 3.4690571 | J65: =J64*tax -> 4.9405648 | K65: =K64*tax -> 5.7110707 | L65: =L64*tax -> 6.2468879 | M65: =M64*tax -> 6.6812191
A66: 淨利 | B66: US$B | D66: =D64-D65 -> -2.59 | E66: =E64-E65 -> -0.413 | F66: =F64-F65 -> 2.3139751 | G66: =G64-G65 -> 1.9009751 | H66: =H64-H65 -> 15.936748 | I66: =I64-I65 -> 25.439752 | J66: =J64-J65 -> 36.230808 | K66: =K64-K65 -> 41.881185 | ... M66: =M64-M65 -> 48.995606
A67: 檢查：實績淨利 − Q 頁 | B67: US$B | D67: =D66-Q!G73 -> 0 | E67: =E66-Q!H73 -> 0
A68: 視同股利（特別股轉換） | B68: US$B | E68: =deemed_1H -> 0.671 | F68: 0 | G68: =E68+F68 -> 0.671 | H68: 0 | I68: 0 | J68: 0 | K68: 0 | L68: 0 | M68: 0
A69: 歸屬普通股淨利 | B69: US$B | E69: =E66-E68 -> -1.084 | F69: =F66-F68 -> 2.3139751 | G69: =G66-G68 -> 1.2299751 | H69: =H66-H68 -> 15.936748 | I69: =I66-I68 -> 25.439752 | J69: =J66-J68 -> 36.230808 | K69: =K66-K68 -> 41.881185 | L69: =L66-L68 -> 45.810511 | M69: =M66-M68 -> 48.995606
A70: 期末股數（十億股） | B70: 十億股 | E70: =sh_out -> 13.581064 | F70: =E70*(1+dil*0.25) -> 13.615017 | H70: =F70*(1+dil*1) -> 13.751167 | I70: =H70*(1+dil*1) -> 13.888678 | J70: =I70*(1+dil*1) -> 14.027565 | K70: =J70*(1+dil*1) -> 14.167841 | L70: =K70*(1+dil*1) -> 14.309519 | M70: =L70*(1+dil*1) -> 14.452615 | N70: 9M26 期末＝10-Q 封面 A＋B 股；之後 ×(1＋dil × 期間長度)；不買回
A71: 平均稀釋股數（十億股） | B71: 十億股 | E71: =sh_dil_1H -> 7.274 | F71: =(E70+F70)/2 -> 13.59804 | G71: =0.75*E71+0.25*F71 -> 8.8550101 | H71: =(F70+H70)/2 -> 13.683092 | I71: =(H70+I70)/2 -> 13.819923 | J71: =(I70+J70)/2 -> 13.958122 | K71: =(J70+K70)/2 -> 14.097703 | L71: =(K70+L70)/2 -> 14.23868 | M71: =(L70+M70)/2 -> 14.381067 | N71: 9M26 為 IPO 前後加權（10-Q）
A72: EPS（GAAP 稀釋，美元） | B72: US$ | E72: =E69/E71 -> -0.14902392 | F72: =F69/F71 -> 0.17016975 | G72: =G69/G71 -> 0.1389016 | H72: =H69/H71 -> 1.1647037 | I72: =I69/I71 -> 1.8408028 | J72: =J69/J71 -> 2.5956793 | K72: =K69/K71 -> 2.9707808 | L72: =L69/L71 -> 3.2173285 | M72: =M69/M71 -> 3.4069521
A73: EPS（評價口徑；讀法 2 含稅後影子效益，美元） | B73: US$ | F73: =(F69+(internal_ai_reading=2)*F56*(1-tax))/F71 -> 0.18019961 | G73: =(G69+(internal_ai_reading=2)*G56*(1-tax))/G71 -> 0.15430378 | H73: =(H69+(internal_ai_reading=2)*H56*(1-tax))/H71 -> 1.4137324 | I73: =(I69+(internal_ai_reading=2)*I56*(1-tax))/I71 -> 2.4323019 | J73: =(J69+(internal_ai_reading=2)*J56*(1-tax))/J71 -> 3.4929044 | K73: =(K69+(internal_ai_reading=2)*K56*(1-tax))/K71 -> 4.0913162 | L73: =(L69+(internal_ai_reading=2)*L56*(1-tax))/L71 -> 4.4842887 | M73: =(M69+(internal_ai_reading=2)*M56*(1-tax))/M71 -> 4.7472064
A75: 情境 B（租金向持有成本部分收斂；基準）
A76: 項目 | B76: 單位 | C76: FY2025* | D76: 9M25A | E76: 9M26A | F76: Q4 26E | G76: FY2026E | H76: FY2027E | I76: FY2028E | J76: FY2029E | K76: FY2030E | L76: FY2031E | M76: FY2032E | N76: 說明
A77: Launch Services | B77: US$B | D77: =Seg!D55 -> 2.056 | E77: =Seg!E55 -> 2.108 | F77: =Seg!F55 -> 0.87227586 | G77: =Seg!G55 -> 2.9802759 | H77: =Seg!H55 -> 3.5937766 | I77: =Seg!I55 -> 3.8866693 | J77: =Seg!J55 -> 4.2034329 | K77: =Seg!K55 -> 4.5460127 | ... M77: =Seg!M55 -> 5.3172085
A78: Launch & Development | B78: US$B | D78: =Seg!D57 -> 1.221 | E78: =Seg!E57 -> 1.24 | F78: =Seg!F57 -> 0.41493201 | G78: =Seg!G57 -> 1.654932 | H78: =Seg!H57 -> 1.707345 | I78: =Seg!I57 -> 1.7889228 | J78: =Seg!J57 -> 1.9032175 | K78: =Seg!K57 -> 2.0554749 | ... M78: =Seg!M57 -> 2.3975059
A79: Space | B79: US$B | C79: =Seg!C58 -> 4.086 | D79: =Seg!D58 -> 3.277 | E79: =Seg!E58 -> 3.348 | F79: =Seg!F58 -> 1.2872079 | G79: =Seg!G58 -> 4.6352079 | H79: =Seg!H58 -> 5.3011215 | I79: =Seg!I58 -> 5.6755921 | J79: =Seg!J58 -> 6.1066504 | ... M79: =Seg!M58 -> 7.7147144
A80: Consumer | B80: US$B | D80: =Seg!D62 -> 5.198 | E80: =Seg!E62 -> 7.754 | F80: =Seg!F62 -> 3.4934362 | G80: =Seg!G62 -> 11.247436 | H80: =Seg!H62 -> 17.243594 | I80: =Seg!I62 -> 21.81771 | J80: =Seg!J62 -> 25.719903 | K80: =Seg!K62 -> 29.032103 | ... M80: =Seg!M62 -> 34.166793
A81: Enterprise & Government | B81: US$B | D81: =Seg!D64 -> 2.961 | E81: =Seg!E64 -> 5.042 | F81: =Seg!F64 -> 2.4297333 | G81: =Seg!G64 -> 7.4717333 | H81: =Seg!H64 -> 11.596895 | I81: =Seg!I64 -> 16.251906 | J81: =Seg!J64 -> 20.326272 | K81: =Seg!K64 -> 22.358899 | ... M81: =Seg!M64 -> 27.054267
A82: Connectivity | B82: US$B | C82: =Seg!C65 -> 11.387 | D82: =Seg!D65 -> 8.159 | E82: =Seg!E65 -> 12.796 | F82: =Seg!F65 -> 5.9231694 | G82: =Seg!G65 -> 18.719169 | H82: =Seg!H65 -> 28.840489 | I82: =Seg!I65 -> 38.069616 | J82: =Seg!J65 -> 46.046174 | ... M82: =Seg!M65 -> 61.221061
A83: Advertising | B83: US$B | D83: =Seg!D51 -> 1.323 | E83: =Seg!E51 -> 1.248 | F83: =Seg!F51 -> 0.53020762 | G83: =Seg!G51 -> 1.7782076 | H83: =Seg!H51 -> 1.7159401 | I83: =Seg!I51 -> 1.6930415 | J83: =Seg!J51 -> 1.7071405 | K83: =Seg!K51 -> 1.7583547 | ... M83: =Seg!M51 -> 1.8654386
A84: SI 對外雲端服務（命題子列） | B84: US$B | E84: =Seg!E46 -> 6.63552 | F84: =Seg!F46 -> 6.2890195 | G84: =Seg!G46 -> 12.924539 | H84: =Seg!H46 -> 37.399537 | I84: =Seg!I46 -> 55.739335 | J84: =Seg!J46 -> 68.069976 | K84: =Seg!K46 -> 72.553409 | L84: =Seg!L46 -> 80.745695 | M84: =Seg!M46 -> 85.254628
A85: Grok／Cursor／X 訂閱、資料授權與 API（命題子列） | B85: US$B | E85: =Seg!E48 -> 3.05548 | F85: =Seg!F48 -> 2.50516 | G85: =Seg!G48 -> 5.56064 | H85: =Seg!H48 -> 12.91078 | I85: =Seg!I48 -> 17.859913 | J85: =Seg!J48 -> 22.622556 | K85: =Seg!K48 -> 26.01594 | L85: =Seg!L48 -> 29.918331 | M85: =Seg!M48 -> 34.406081
A86: SI Solutions & Infrastructure | B86: US$B | D86: =Seg!D49 -> 0.955 | E86: =Seg!E49 -> 9.691 | F86: =Seg!F49 -> 8.7941795 | G86: =Seg!G49 -> 18.485179 | H86: =Seg!H49 -> 50.310318 | I86: =Seg!I49 -> 73.599248 | J86: =Seg!J49 -> 90.692533 | K86: =Seg!K49 -> 98.569349 | ... M86: =Seg!M49 -> 119.66071
A87: SI (Super Intelligence; formerly AI) | B87: US$B | C87: =Seg!C52 -> 3.201 | D87: =Seg!D52 -> 2.278 | E87: =Seg!E52 -> 10.939 | F87: =Seg!F52 -> 9.3243871 | G87: =Seg!G52 -> 20.263387 | H87: =Seg!H52 -> 52.026258 | I87: =Seg!I52 -> 75.292289 | J87: =Seg!J52 -> 92.399673 | ... M87: =Seg!M52 -> 121.52615
A88: 合併營收 | B88: US$B | C88: =Seg!C66 -> 18.674 | D88: =Seg!D66 -> 13.714 | E88: =Seg!E66 -> 27.083 | F88: =Seg!F66 -> 16.534764 | G88: =Seg!G66 -> 43.617764 | H88: =Seg!H66 -> 86.167868 | I88: =Seg!I66 -> 119.0375 | J88: =Seg!J66 -> 144.5525 | ... M88: =Seg!M66 -> 190.46192
A89: 合併營收年增 | B89: % | E89: =E88/D88-1 -> 0.97484323 | G89: =G88/C88-1 -> 1.3357483 | H89: =H88/G88-1 -> 0.97552235 | I89: =I88/H88-1 -> 0.38146039 | J89: =J88/I88-1 -> 0.21434423 | K89: =K88/J88-1 -> 0.095243565 | L89: =L88/K88-1 -> 0.1118788 | M89: =M88/L88-1 -> 0.081967963
A90: 檢查：Space 子列合計 − Space | B90: US$B | D90: =D77+D78-D79 -> 0 | E90: =E77+E78-E79 -> 0 | F90: =F77+F78-F79 -> 0 | G90: =G77+G78-G79 -> 0 | H90: =H77+H78-H79 -> 0 | I90: =I77+I78-I79 -> 0 | J90: =J77+J78-J79 -> 0 | K90: =K77+K78-K79 -> 0 | ... M90: =M77+M78-M79 -> 0
A91: 檢查：Connectivity 子列合計 − Connectivity | B91: US$B | D91: =D80+D81-D82 -> 0 | E91: =E80+E81-E82 -> 0 | F91: =F80+F81-F82 -> 0 | G91: =G80+G81-G82 -> 0 | H91: =H80+H81-H82 -> 0 | I91: =I80+I81-I82 -> 0 | J91: =J80+J81-J82 -> 0 | K91: =K80+K81-K82 -> 0 | ... M91: =M80+M81-M82 -> 0
A92: 檢查：SI 子列合計 − SI | B92: US$B | D92: =D83+D86-D87 -> 0 | E92: =E83+E86-E87 -> 0 | F92: =F83+F86-F87 -> 0 | G92: =G83+G86-G87 -> 0 | H92: =H83+H86-H87 -> 0 | I92: =I83+I86-I87 -> 0 | J92: =J83+J86-J87 -> 0 | K92: =K83+K86-K87 -> 0 | ... M92: =M83+M86-M87 -> 0
A93: 檢查：SI S&I 命題子列合計 − SI Solutions & Infrastructure | B93: US$B | E93: =E84+E85-E86 -> 0 | F93: =F84+F85-F86 -> 0 | G93: =G84+G85-G86 -> 0 | H93: =H84+H85-H86 -> 0 | I93: =I84+I85-I86 -> 0 | J93: =J84+J85-J86 -> 0 | K93: =K84+K85-K86 -> 0 | L93: =L84+L85-L86 -> 0 | M93: =M84+M85-M86 -> 0
A94: 檢查：分部合計 − 合併營收 | B94: US$B | C94: =C79+C82+C87-C88 -> 0 | D94: =D79+D82+D87-D88 -> 0 | E94: =E79+E82+E87-E88 -> 0 | F94: =F79+F82+F87-F88 -> 0 | G94: =G79+G82+G87-G88 -> 0 | H94: =H79+H82+H87-H88 -> 0 | I94: =I79+I82+I87-I88 -> 0 | J94: =J79+J82+J87-J88 -> 0 | ... M94: =M79+M82+M87-M88 -> 0
A95: Space 調整後 EBITDA 率（9M26 → FY2030 m_spl） | B95: % | F95: =m_sp0 -> -0.059438471 | H95: =m_sp0+(m_spl-m_sp0)*MIN(1,(2027-2026)/conv_n) -> 0.005421147 | I95: =m_sp0+(m_spl-m_sp0)*MIN(1,(2028-2026)/conv_n) -> 0.070280765 | J95: =m_sp0+(m_spl-m_sp0)*MIN(1,(2029-2026)/conv_n) -> 0.13514038 | K95: =m_sp0+(m_spl-m_sp0)*MIN(1,(2030-2026)/conv_n) -> 0.2 | L95: =m_sp0+(m_spl-m_sp0)*MIN(1,(2031-2026)/conv_n) -> 0.2 | M95: =m_sp0+(m_spl-m_sp0)*MIN(1,(2032-2026)/conv_n) -> 0.2
A96: Space 分部調整後 EBITDA | B96: US$B | C96: =Q!I28 -> 0.653 | D96: =Q!G28 -> 0.803 | E96: =Q!H28 -> -0.199 | F96: =F79*F95 -> -0.076509667 | G96: =E96+F96 -> -0.27550967 | H96: =H79*H95 -> 0.028738159 | I96: =I79*I95 -> 0.39888495 | J96: =J79*J95 -> 0.82525507 | K96: =K79*K95 -> 1.3202975 | L96: =L79*L95 -> 1.4272851 | M96: =M79*M95 -> 1.5429429
A97: Connectivity 分部調整後 EBITDA | B97: US$B | C97: =Q!I29 -> 7.168 | D97: =Q!G29 -> 5.123 | E97: =Q!H29 -> 8.183 | F97: =F82*m_cn -> 3.7878474 | G97: =E97+F97 -> 11.970847 | H97: =H82*m_cn -> 18.443398 | I97: =I82*m_cn -> 24.345395 | J97: =J82*m_cn -> 29.446377 | K97: =K82*m_cn -> 32.864377 | L97: =L82*m_cn -> 36.081242 | M97: =M82*m_cn -> 39.150667
A98: SI 對外出租 EBITDA（營收 − 對外 GW × Tokenomics 營運費用） | B98: US$B | F98: =F84-Thesis!F35 -> 5.6396031 | G98: =F98 -> 5.6396031 | H98: =H84-Thesis!H35 -> 33.317791 | I98: =I84-Thesis!I35 -> 49.237604 | J98: =J84-Thesis!J35 -> 59.392049 | K98: =K84-Thesis!K35 -> 62.237545 | L98: =L84-Thesis!L35 -> 69.307551 | M98: =M84-Thesis!M35 -> 73.198794
A99: SI 其他 EBITDA（(SI 其他收入＋廣告) × m_so − 自用增量營運費用） | B99: US$B | F99: =(F85+F83)*m_so-Thesis!F36 -> 0.48462444 | G99: =F99 -> 0.48462444 | H99: =(H85+H83)*m_so-Thesis!H36 -> 1.7812585 | I99: =(I85+I83)*m_so-Thesis!I36 -> 1.6724813 | J99: =(J85+J83)*m_so-Thesis!J36 -> 1.6332524 | K99: =(K85+K83)*m_so-Thesis!K36 -> 1.5782701 | L99: =(L85+L83)*m_so-Thesis!L36 -> 1.8100812 | M99: =(M85+M83)*m_so-Thesis!M36 -> 2.3372907
A100: SI 分部調整後 EBITDA | B100: US$B | C100: =Q!I30 -> -1.237 | D100: =Q!G30 -> -0.813 | E100: =Q!H30 -> 5.49 | F100: =F98+F99 -> 6.1242276 | G100: =E100+F100 -> 11.614228 | H100: =H98+H99 -> 35.099049 | I100: =I98+I99 -> 50.910085 | J100: =J98+J99 -> 61.025302 | K100: =K98+K99 -> 63.815816 | L100: =L98+L99 -> 71.117632 | M100: =M98+M99 -> 75.536085
A101: 合併調整後 EBITDA（分部合計） | B101: US$B | C101: =C96+C97+C100 -> 6.584 | D101: =D96+D97+D100 -> 5.113 | E101: =E96+E97+E100 -> 13.474 | F101: =F96+F97+F100 -> 9.8355653 | G101: =G96+G97+G100 -> 23.309565 | H101: =H96+H97+H100 -> 53.571186 | I101: =I96+I97+I100 -> 75.654365 | J101: =J96+J97+J100 -> 91.296934 | ... M101: =M96+M97+M100 -> 116.2297
A102: Space 折舊攤銷（基礎遞減＋新增） | B102: US$B | D102: =Q!G42 -> 0.572 | E102: =Q!H42 -> 0.509 | F102: =da_sp0*0.25*MAX(0,1-(2026.875-t_val)/rem_sp)+Seg!F77 -> 0.18958307 | G102: =E102+F102 -> 0.69858307 | H102: =da_sp0*1*MAX(0,1-(2027.5-t_val)/rem_sp)+Seg!H77 -> 0.90003388 | I102: =da_sp0*1*MAX(0,1-(2028.5-t_val)/rem_sp)+Seg!I77 -> 1.2256325 | J102: =da_sp0*1*MAX(0,1-(2029.5-t_val)/rem_sp)+Seg!J77 -> 1.4631198 | K102: =da_sp0*1*MAX(0,1-(2030.5-t_val)/rem_sp)+Seg!K77 -> 1.5987329 | L102: =da_sp0*1*MAX(0,1-(2031.5-t_val)/rem_sp)+Seg!L77 -> 1.6527895 | M102: =da_sp0*1*MAX(0,1-(2032.5-t_val)/rem_sp)+Seg!M77 -> 1.8342195
A103: Connectivity 折舊攤銷（基礎遞減＋新增） | B103: US$B | D103: =Q!G44 -> 1.706 | E103: =Q!H44 -> 2.574 | F103: =da_cn0*0.25*MAX(0,1-(2026.875-t_val)/rem_cn)+Seg!F78 -> 0.96537072 | G103: =E103+F103 -> 3.5393707 | H103: =da_cn0*1*MAX(0,1-(2027.5-t_val)/rem_cn)+Seg!H78 -> 3.6836359 | I103: =da_cn0*1*MAX(0,1-(2028.5-t_val)/rem_cn)+Seg!I78 -> 4.0899347 | J103: =da_cn0*1*MAX(0,1-(2029.5-t_val)/rem_cn)+Seg!J78 -> 4.9888563 | K103: =da_cn0*1*MAX(0,1-(2030.5-t_val)/rem_cn)+Seg!K78 -> 7.278144 | L103: =da_cn0*1*MAX(0,1-(2031.5-t_val)/rem_cn)+Seg!L78 -> 10.187064 | M103: =da_cn0*1*MAX(0,1-(2032.5-t_val)/rem_cn)+Seg!M78 -> 13.288917
...

Sheet CF
A1: CF — 現金流（US$B）。營運現金＝淨利＋折舊＋股權報酬＋營運資金；資本支出＝Space＋Connectivity（Seg）＋SI 現金資本支出（Thesis）。收支關卡口徑（審查第 2 條，預設）＝營運現金 − 資本支出 − 融資租賃本金 − Valor 失敗售後租回本金償還 − 以其他融資取得之 PP&E；公司口徑 FCF＝營運現金 − 資本支出（並列）
A2: 2026 年 9M：IPO 淨額 85.7、IPO 前發行 8.3、發債 51.8／償還 39.8（過橋與 xAI 舊債清償）。預測期不配息、不買回；EchoStar 頻譜現金（2026Q4 0.385、FY2027 9.328）列投資活動（按成本、價值中性）；現金低於最低現金 30 時以新債補足。失敗售後租回本金與資本支出可能重複扣（資產購置計入資本支出、售後租回現金列融資流入）——列為判斷題
A4: 收支關卡（地圖讀這兩列；FY2026–FY2030，FY2026 含 9M 實績）
A5: 項目 | B5: 情境 A | C5: 情境 B | D5: 情境 C | E5: 說明
A6: 收支關卡：自由現金流（收支關卡口徑，五年合計） | B6: =SUM(G30:K30) -> -55.482988 | C6: =SUM(G61:K61) -> -96.93727 | D6: =SUM(G92:K92) -> -127.38154 | E6: 審查第 2 條預設口徑；負值＝入不敷出（由 IPO 現金與舉債支應）
A7: 對照：公司口徑 FCF（營運現金 − 資本支出，五年合計） | B7: =SUM(G29:K29) -> -12.219542 | C7: =SUM(G60:K60) -> -53.673823 | D7: =SUM(G91:K91) -> -84.118092 | E7: 公司口徑（不扣融資租賃、失敗售後租回、以融資取得 PP&E）
A8: 其中：五年新增舉債 | B8: =SUM(G37:K37) -> 4.8226108 | C8: =SUM(G68:K68) -> 13.073683 | D8: =SUM(G99:K99) -> 21.293863
A9: 期末淨現金 FY2030 | B9: =K42 -> 38.622012 | C9: =K73 -> -2.8322698 | D9: =K104 -> -33.276538
A10: 是否需要舉債 | B10: =IF(B8>0.001,"需要舉債","不需舉債（IPO 現金足以支應）") -> 需要舉債 | C10: =IF(C8>0.001,"需要舉債","不需舉債（IPO 現金足以支應）") -> 需要舉債 | D10: =IF(D8>0.001,"需要舉債","不需舉債（IPO 現金足以支應）") -> 需要舉債
A11: 檢查：收支關卡 − 首年起五年逐欄加總（FY2026＋…＋FY2030） | B11: =B6-(G30+H30+I30+J30+K30) -> 0 | C11: =C6-(G61+H61+I61+J61+K61) -> 0 | D11: =D6-(G92+H92+I92+J92+K92) -> 0
A13: 情境 A（算力租金維持高檔、Starlink 增長快）
A14: 項目 | B14: 單位 | C14: FY2025* | D14: 9M25A | E14: 9M26A | F14: Q4 26E | G14: FY2026E | H14: FY2027E | I14: FY2028E | J14: FY2029E | K14: FY2030E | L14: FY2031E | M14: FY2032E | N14: 說明
A15: 淨利 | B15: US$B | E15: =PL!E66 -> -0.413 | F15: =PL!F66 -> 2.3139751 | G15: =PL!G66 -> 1.9009751 | H15: =PL!H66 -> 15.936748 | I15: =PL!I66 -> 25.439752 | J15: =PL!J66 -> 36.230808 | K15: =PL!K66 -> 41.881185 | L15: =PL!L66 -> 45.810511 | M15: =PL!M66 -> 48.995606
A16: 折舊攤銷 | B16: US$B | E16: =PL!E43 -> 8.934 | F16: =PL!F43 -> 3.9598477 | G16: =PL!G43 -> 12.893848 | H16: =PL!H43 -> 22.394611 | I16: =PL!I43 -> 33.76071 | J16: =PL!J43 -> 45.51974 | K16: =PL!K43 -> 56.046011 | L16: =PL!L43 -> 64.802041 | M16: =PL!M43 -> 71.133541
A17: 股權報酬（非現金；含 Cursor 收購後服務期獎酬） | B17: US$B | E17: =PL!E49 -> 3.835 | F17: =PL!F49 -> 3.39826 | G17: =PL!G49 -> 7.23326 | H17: =PL!H49 -> 15.578758 | I17: =PL!I49 -> 18.909263 | J17: =PL!J49 -> 16.749479 | K17: =PL!K49 -> 15.315985 | L17: =PL!L49 -> 17.101698 | M17: =PL!M49 -> 18.433635
A18: 營運資金變動（流入＋） | B18: US$B | F18: =wc_k*(PL!F26-(Q!I17-Q!G17)) -> 0.3240934 | G18: =F18 -> 0.3240934 | H18: =wc_k*(PL!H26-PL!G26) -> 1.2650837 | I18: =wc_k*(PL!I26-PL!H26) -> 1.0792711 | J18: =wc_k*(PL!J26-PL!I26) -> 0.92744548 | K18: =wc_k*(PL!K26-PL!J26) -> 0.62543877 | L18: =wc_k*(PL!L26-PL!K26) -> 0.58362053 | M18: =wc_k*(PL!M26-PL!L26) -> 0.45929173 | N18: Q4 26＝wc_k ×(Q4 26 營收 − 2025Q4 營收〔FY2025 二手 − 9M25〕)；之後＝營收增量 × wc_k
A19: 其他（9M26 實績差額：營運資金、遞延稅、清償損失等；預測期 0） | B19: US$B | E19: =cfo_9m-E15-E16-E17 -> 0.741 | F19: 0 | G19: =E19+F19 -> 0.741 | H19: 0 | I19: 0 | J19: 0 | K19: 0 | L19: 0 | M19: 0
A20: 營運現金流 | B20: US$B | E20: =E15+E16+E17+N(E18)+E19 -> 13.097 | F20: =F15+F16+F17+N(F18)+F19 -> 9.9961762 | G20: =G15+G16+G17+N(G18)+G19 -> 23.093176 | H20: =H15+H16+H17+N(H18)+H19 -> 55.1752 | I20: =I15+I16+I17+N(I18)+I19 -> 79.188996 | J20: =J15+J16+J17+N(J18)+J19 -> 99.427473 | K20: =K15+K16+K17+N(K18)+K19 -> 113.86862 | L20: =L15+L16+L17+N(L18)+L19 -> 128.29787 | M20: =M15+M16+M17+N(M18)+M19 -> 139.02207
A21: 資本支出：Space | B21: US$B | E21: =Q!H35 -> 3.832 | F21: =Seg!F37 -> 1.4732917 | G21: =E21+F21 -> 5.3052917 | H21: =Seg!H37 -> 4.9481884 | I21: =Seg!I37 -> 4.0993778 | J21: =Seg!J37 -> 3.1213593 | K21: =Seg!K37 -> 1.9804463 | L21: =Seg!L37 -> 2.1409277 | M21: =Seg!M37 -> 2.3144143
A22: 資本支出：Connectivity | B22: US$B | E22: =Q!H36 -> 4.242 | F22: =Seg!F38 -> 1.963589 | G22: =E22+F22 -> 6.205589 | H22: =Seg!H38 -> 9.7997538 | I22: =Seg!I38 -> 13.299258 | J22: =Seg!J38 -> 16.322245 | K22: =Seg!K38 -> 18.418928 | L22: =Seg!L38 -> 20.364023 | M22: =Seg!M38 -> 22.19113
A23: 資本支出：SI（現金） | B23: US$B | E23: =Thesis!E44 -> 39.995 | F23: =Thesis!F44 -> 16.165836 | G23: =Thesis!G44 -> 56.160836 | H23: =Thesis!H44 -> 68.626344 | I23: =Thesis!I44 -> 72.589345 | J23: =Thesis!J44 -> 56.23579 | K23: =Thesis!K44 -> 45.860256 | L23: =Thesis!L44 -> 47.959744 | M23: =Thesis!M44 -> 55.585457
A24: 資本支出合計（現金） | B24: US$B | E24: =E21+E22+E23 -> 48.069 | F24: =F21+F22+F23 -> 19.602716 | G24: =G21+G22+G23 -> 67.671716 | H24: =H21+H22+H23 -> 83.374286 | I24: =I21+I22+I23 -> 89.98798 | J24: =J21+J22+J23 -> 75.679394 | K24: =K21+K22+K23 -> 66.25963 | L24: =L21+L22+L23 -> 70.464695 | M24: =M21+M22+M23 -> 80.091002
A25: 檢查：9M26 資本支出 − 10-Q 購置不動產與設備 | B25: US$B | E25: =E24-capex_9m -> 0
A26: 以其他融資取得 PP&E（非現金；SI） | B26: US$B | E26: =Thesis!E45 -> 3.921 | F26: =Thesis!F45 -> 1.5851643 | G26: =Thesis!G45 -> 5.5061643 | H26: =Thesis!H45 -> 6.729255 | I26: =Thesis!I45 -> 7.1178527 | J26: =Thesis!J45 -> 5.5142814 | K26: =Thesis!K45 -> 4.4968934 | L26: =Thesis!L45 -> 4.7027618 | M26: =Thesis!M45 -> 5.4505121
A27: 融資租賃本金 | B27: US$B | E27: =lease_1H -> 0.27 | F27: =lease_2H -> 0.123 | G27: =E27+F27 -> 0.393 | H27: =lease_27 -> 0.25 | I27: =lease_28 -> 0.2 | J27: =lease_29 -> 0.15 | K27: =lease_30 -> 0.1 | L27: =lease_31 -> 0.1 | M27: =lease_32 -> 0.1
A28: Valor 失敗售後租回與設備融資本金償還（債務到期表） | B28: US$B | E28: =slb_1H -> 0 | F28: =mat_2H -> 0.495 | G28: =E28+F28 -> 0.495 | H28: =mat_27 -> 2.425 | I28: =mat_28 -> 2.867 | J28: =mat_29 -> 3.422 | K28: =mat_30 -> 3.597 | L28: =mat_31 -> 5 | M28: =mat_32 -> 5 | N28: 9M26 未單獨揭露（資料缺口，0）；預測期＝10-Q 到期表（SpaceX Notes 2031 前無重大本金 → 推定主要為失敗售後租回）
A29: 公司口徑 FCF（營運現金 − 資本支出） | B29: US$B | E29: =E20-E24 -> -34.972 | F29: =F20-F24 -> -9.6065402 | G29: =G20-G24 -> -44.57854 | H29: =H20-H24 -> -28.199086 | I29: =I20-I24 -> -10.798984 | J29: =J20-J24 -> 23.748079 | K29: =K20-K24 -> 47.60899 | L29: =L20-L24 -> 57.833175 | M29: =M20-M24 -> 58.931072
A30: 自由現金流（收支關卡口徑：− 融資租賃本金 − 失敗售後租回本金 − 以其他融資取得 PP&E） | B30: US$B | E30: =E29-E27-E28-E26 -> -39.163 | F30: =F29-F27-F28-F26 -> -11.809705 | G30: =G29-G27-G28-G26 -> -50.972705 | H30: =H29-H27-H28-H26 -> -37.603341 | I30: =I29-I27-I28-I26 -> -20.983837 | J30: =J29-J27-J28-J26 -> 14.661798 | K30: =K29-K27-K28-K26 -> 39.415097 | L30: =L29-L27-L28-L26 -> 48.030413 | M30: =M29-M27-M28-M26 -> 48.38056
A31: EchoStar 頻譜（投資活動；按成本） | B31: US$B | E31: 0 | F31: =spec_2h -> 0.385 | G31: =E31+F31 -> 0.385 | H31: =spec_27 -> 9.328 | I31: 0 | J31: 0 | K31: 0 | L31: 0 | M31: 0
A32: 9M26 債務淨流入／預測期已知新債 | B32: US$B | E32: =debt_1H -> 10.712 | F32: 0 | G32: =E32+F32 -> 10.712 | H32: 0 | I32: 0 | J32: 0 | K32: 0 | L32: 0 | M32: 0
A33: 股權淨流入（9M26 IPO 等） | B33: US$B | E33: =eq_1H -> 89.377 | F33: 0 | G33: =E33+F33 -> 89.377 | H33: 0 | I33: 0 | J33: 0 | K33: 0 | L33: 0 | M33: 0
A34: 期初現金（現金＋有價證券） | B34: US$B | E34: =cash_ye25 -> 24.747 | F34: =E38 -> 89.855 | H34: =F38 -> 79.24546 | I34: =H38 -> 39.043374 | J34: =I38 -> 30 | K34: =J38 -> 50.176079 | L34: =K38 -> 94.088069 | M34: =L38 -> 146.82124
A35: 其他（9M26 實績差額：收購現金、產品回饋金、匯率、頻譜預付等；預測期 0） | B35: US$B | E35: =cash_0-(E34+E20-E24-E27+E32+E33) -> 0.261 | F35: 0 | H35: 0 | I35: 0 | J35: 0 | K35: 0 | L35: 0 | M35: 0
A36: 新債前現金 | B36: US$B | E36: =E34+E20-E24-E27+E32+E33+E35 -> 89.855 | F36: =F34+F20-F24-F27-F28-F31 -> 79.24546 | H36: =H34+H20-H24-H27-H28-H31 -> 39.043374 | I36: =I34+I20-I24-I27-I28-I31 -> 25.177389 | J36: =J34+J20-J24-J27-J28-J31 -> 50.176079 | K36: =K34+K20-K24-K27-K28-K31 -> 94.088069 | L36: =L34+L20-L24-L27-L28-L31 -> 146.82124 | M36: =M34+M20-M24-M27-M28-M31 -> 200.65232
A37: 新增舉債（現金低於最低現金時） | B37: US$B | E37: 0 | F37: =MAX(0,min_cash-F36) -> 0 | G37: =E37+F37 -> 0 | H37: =MAX(0,min_cash-H36) -> 0 | I37: =MAX(0,min_cash-I36) -> 4.8226108 | J37: =MAX(0,min_cash-J36) -> 0 | K37: =MAX(0,min_cash-K36) -> 0 | L37: =MAX(0,min_cash-L36) -> 0 | M37: =MAX(0,min_cash-M36) -> 0
A38: 期末現金（現金＋有價證券） | B38: US$B | E38: =E36+E37 -> 89.855 | F38: =F36+F37 -> 79.24546 | H38: =H36+H37 -> 39.043374 | I38: =I36+I37 -> 30 | J38: =J36+J37 -> 50.176079 | K38: =K36+K37 -> 94.088069 | L38: =L36+L37 -> 146.82124 | M38: =M36+M37 -> 200.65232
A39: 檢查：9M26 期末現金 − 2026-09-30 資產負債表 | B39: US$B | E39: =E38-cash_0 -> 0
A40: 期初債務本金 | B40: US$B | E40: =debt_ye25 -> 22.049 | F40: =E41 -> 38.006 | H40: =F41 -> 39.096164 | I40: =H41 -> 43.400419 | J40: =I41 -> 52.473883 | K40: =J41 -> 54.566164 | L40: =K41 -> 55.466058 | M40: =L41 -> 55.168819
A41: 期末債務本金（＋以其他融資取得 PP&E） | B41: US$B | E41: =debt_0 -> 38.006 | F41: =F40-F28+F37+F26 -> 39.096164 | H41: =H40-H28+H37+H26 -> 43.400419 | I41: =I40-I28+I37+I26 -> 52.473883 | J41: =J40-J28+J37+J26 -> 54.566164 | K41: =K40-K28+K37+K26 -> 55.466058 | L41: =L40-L28+L37+L26 -> 55.168819 | M41: =M40-M28+M37+M26 -> 55.619331
A42: 淨現金（現金 − 債務） | B42: US$B | E42: =E38-E41 -> 51.849 | F42: =F38-F41 -> 40.149295 | H42: =H38-H41 -> -4.3570457 | I42: =I38-I41 -> -22.473883 | J42: =J38-J41 -> -4.3900851 | K42: =K38-K41 -> 38.622012 | L42: =L38-L41 -> 91.652425 | M42: =M38-M41 -> 145.03298
A44: 情境 B（租金向持有成本部分收斂；基準）
A45: 項目 | B45: 單位 | C45: FY2025* | D45: 9M25A | E45: 9M26A | F45: Q4 26E | G45: FY2026E | H45: FY2027E | I45: FY2028E | J45: FY2029E | K45: FY2030E | L45: FY2031E | M45: FY2032E | N45: 說明
A46: 淨利 | B46: US$B | E46: =PL!E128 -> -0.413 | F46: =PL!F128 -> 2.3139751 | G46: =PL!G128 -> 1.9009751 | H46: =PL!H128 -> 14.058656 | I46: =PL!I128 -> 19.42408 | J46: =PL!J128 -> 24.189386 | K46: =PL!K128 -> 23.109222 | L46: =PL!L128 -> 24.342874 | M46: =PL!M128 -> 25.65793
A47: 折舊攤銷 | B47: US$B | E47: =PL!E105 -> 8.934 | F47: =PL!F105 -> 3.9598477 | G47: =PL!G105 -> 12.893848 | H47: =PL!H105 -> 22.384659 | I47: =PL!I105 -> 33.692618 | J47: =PL!J105 -> 45.322736 | K47: =PL!K105 -> 55.659225 | L47: =PL!L105 -> 64.173309 | M47: =PL!M105 -> 70.218344
A48: 股權報酬（非現金；含 Cursor 收購後服務期獎酬） | B48: US$B | E48: =PL!E111 -> 3.835 | F48: =PL!F111 -> 3.39826 | G48: =PL!G111 -> 7.23326 | H48: =PL!H111 -> 15.351187 | I48: =PL!I111 -> 18.172518 | J48: =PL!J111 -> 15.278788 | K48: =PL!K111 -> 12.993822 | L48: =PL!L111 -> 14.507141 | M48: =PL!M111 -> 15.682173
A49: 營運資金變動（流入＋） | B49: US$B | F49: =wc_k*(PL!F88-(Q!I17-Q!G17)) -> 0.3240934 | G49: =F49 -> 0.3240934 | H49: =wc_k*(PL!H88-PL!G88) -> 1.1914029 | I49: =wc_k*(PL!I88-PL!H88) -> 0.92034961 | J49: =wc_k*(PL!J88-PL!I88) -> 0.71442002 | K49: =wc_k*(PL!K88-PL!J88) -> 0.38549547 | L49: =wc_k*(PL!L88-PL!K88) -> 0.49595486 | M49: =wc_k*(PL!M88-PL!L88) -> 0.40401355 | N49: Q4 26＝wc_k ×(Q4 26 營收 − 2025Q4 營收〔FY2025 二手 − 9M25〕)；之後＝營收增量 × wc_k
A50: 其他（9M26 實績差額：營運資金、遞延稅、清償損失等；預測期 0） | B50: US$B | E50: =cfo_9m-E46-E47-E48 -> 0.741 | F50: 0 | G50: =E50+F50 -> 0.741 | H50: 0 | I50: 0 | J50: 0 | K50: 0 | L50: 0 | M50: 0
A51: 營運現金流 | B51: US$B | E51: =E46+E47+E48+N(E49)+E50 -> 13.097 | F51: =F46+F47+F48+N(F49)+F50 -> 9.9961762 | G51: =G46+G47+G48+N(G49)+G50 -> 23.093176 | H51: =H46+H47+H48+N(H49)+H50 -> 52.985904 | I51: =I46+I47+I48+N(I49)+I50 -> 72.209566 | J51: =J46+J47+J48+N(J49)+J50 -> 85.50533 | K51: =K46+K47+K48+N(K49)+K50 -> 92.147764 | L51: =L46+L47+L48+N(L49)+L50 -> 103.51928 | M51: =M46+M47+M48+N(M49)+M50 -> 111.96246
A52: 資本支出：Space | B52: US$B | E52: =Q!H35 -> 3.832 | F52: =Seg!F75 -> 1.4732917 | G52: =E52+F52 -> 5.3052917 | H52: =Seg!H75 -> 4.9481884 | I52: =Seg!I75 -> 4.0993778 | J52: =Seg!J75 -> 3.1213593 | K52: =Seg!K75 -> 1.9804463 | L52: =Seg!L75 -> 2.1409277 | M52: =Seg!M75 -> 2.3144143
A53: 資本支出：Connectivity | B53: US$B | E53: =Q!H36 -> 4.242 | F53: =Seg!F76 -> 1.963589 | G53: =E53+F53 -> 6.205589 | H53: =Seg!H76 -> 9.5609061 | I53: =Seg!I76 -> 12.620453 | J53: =Seg!J76 -> 15.26476 | K53: =Seg!K76 -> 17.036623 | L53: =Seg!L76 -> 18.70422 | M53: =Seg!M76 -> 20.295384
A54: 資本支出：SI（現金） | B54: US$B | E54: =Thesis!E44 -> 39.995 | F54: =Thesis!F44 -> 16.165836 | G54: =Thesis!G44 -> 56.160836 | H54: =Thesis!H44 -> 68.626344 | I54: =Thesis!I44 -> 72.589345 | J54: =Thesis!J44 -> 56.23579 | K54: =Thesis!K44 -> 45.860256 | L54: =Thesis!L44 -> 47.959744 | M54: =Thesis!M44 -> 55.585457
A55: 資本支出合計（現金） | B55: US$B | E55: =E52+E53+E54 -> 48.069 | F55: =F52+F53+F54 -> 19.602716 | G55: =G52+G53+G54 -> 67.671716 | H55: =H52+H53+H54 -> 83.135438 | I55: =I52+I53+I54 -> 89.309175 | J55: =J52+J53+J54 -> 74.621909 | K55: =K52+K53+K54 -> 64.877325 | L55: =L52+L53+L54 -> 68.804892 | M55: =M52+M53+M54 -> 78.195256
A56: 檢查：9M26 資本支出 − 10-Q 購置不動產與設備 | B56: US$B | E56: =E55-capex_9m -> 0
A57: 以其他融資取得 PP&E（非現金；SI） | B57: US$B | E57: =Thesis!E45 -> 3.921 | F57: =Thesis!F45 -> 1.5851643 | G57: =Thesis!G45 -> 5.5061643 | H57: =Thesis!H45 -> 6.729255 | I57: =Thesis!I45 -> 7.1178527 | J57: =Thesis!J45 -> 5.5142814 | K57: =Thesis!K45 -> 4.4968934 | L57: =Thesis!L45 -> 4.7027618 | M57: =Thesis!M45 -> 5.4505121
A58: 融資租賃本金 | B58: US$B | E58: =lease_1H -> 0.27 | F58: =lease_2H -> 0.123 | G58: =E58+F58 -> 0.393 | H58: =lease_27 -> 0.25 | I58: =lease_28 -> 0.2 | J58: =lease_29 -> 0.15 | K58: =lease_30 -> 0.1 | L58: =lease_31 -> 0.1 | M58: =lease_32 -> 0.1
A59: Valor 失敗售後租回與設備融資本金償還（債務到期表） | B59: US$B | E59: =slb_1H -> 0 | F59: =mat_2H -> 0.495 | G59: =E59+F59 -> 0.495 | H59: =mat_27 -> 2.425 | I59: =mat_28 -> 2.867 | J59: =mat_29 -> 3.422 | K59: =mat_30 -> 3.597 | L59: =mat_31 -> 5 | M59: =mat_32 -> 5 | N59: 9M26 未單獨揭露（資料缺口，0）；預測期＝10-Q 到期表（SpaceX Notes 2031 前無重大本金 → 推定主要為失敗售後租回）
A60: 公司口徑 FCF（營運現金 − 資本支出） | B60: US$B | E60: =E51-E55 -> -34.972 | F60: =F51-F55 -> -9.6065402 | G60: =G51-G55 -> -44.57854 | H60: =H51-H55 -> -30.149534 | I60: =I51-I55 -> -17.099609 | J60: =J51-J55 -> 10.88342 | K60: =K51-K55 -> 27.270439 | L60: =L51-L55 -> 34.714386 | M60: =M51-M55 -> 33.767204
A61: 自由現金流（收支關卡口徑：− 融資租賃本金 − 失敗售後租回本金 − 以其他融資取得 PP&E） | B61: US$B | E61: =E60-E58-E59-E57 -> -39.163 | F61: =F60-F58-F59-F57 -> -11.809705 | G61: =G60-G58-G59-G57 -> -50.972705 | H61: =H60-H58-H59-H57 -> -39.553789 | I61: =I60-I58-I59-I57 -> -27.284462 | J61: =J60-J58-J59-J57 -> 1.797139 | K61: =K60-K58-K59-K57 -> 19.076546 | L61: =L60-L58-L59-L57 -> 24.911625 | M61: =M60-M58-M59-M57 -> 23.216692
A62: EchoStar 頻譜（投資活動；按成本） | B62: US$B | E62: 0 | F62: =spec_2h -> 0.385 | G62: =E62+F62 -> 0.385 | H62: =spec_27 -> 9.328 | I62: 0 | J62: 0 | K62: 0 | L62: 0 | M62: 0
A63: 9M26 債務淨流入／預測期已知新債 | B63: US$B | E63: =debt_1H -> 10.712 | F63: 0 | G63: =E63+F63 -> 10.712 | H63: 0 | I63: 0 | J63: 0 | K63: 0 | L63: 0 | M63: 0
A64: 股權淨流入（9M26 IPO 等） | B64: US$B | E64: =eq_1H -> 89.377 | F64: 0 | G64: =E64+F64 -> 89.377 | H64: 0 | I64: 0 | J64: 0 | K64: 0 | L64: 0 | M64: 0
A65: 期初現金（現金＋有價證券） | B65: US$B | E65: =cash_ye25 -> 24.747 | F65: =E69 -> 89.855 | H65: =F69 -> 79.24546 | I65: =H69 -> 37.092926 | J65: =I69 -> 30 | K65: =J69 -> 37.31142 | L65: =K69 -> 60.88486 | M65: =L69 -> 90.499246
A66: 其他（9M26 實績差額：收購現金、產品回饋金、匯率、頻譜預付等；預測期 0） | B66: US$B | E66: =cash_0-(E65+E51-E55-E58+E63+E64) -> 0.261 | F66: 0 | H66: 0 | I66: 0 | J66: 0 | K66: 0 | L66: 0 | M66: 0
A67: 新債前現金 | B67: US$B | E67: =E65+E51-E55-E58+E63+E64+E66 -> 89.855 | F67: =F65+F51-F55-F58-F59-F62 -> 79.24546 | H67: =H65+H51-H55-H58-H59-H62 -> 37.092926 | I67: =I65+I51-I55-I58-I59-I62 -> 16.926317 | J67: =J65+J51-J55-J58-J59-J62 -> 37.31142 | K67: =K65+K51-K55-K58-K59-K62 -> 60.88486 | L67: =L65+L51-L55-L58-L59-L62 -> 90.499246 | M67: =M65+M51-M55-M58-M59-M62 -> 119.16645
A68: 新增舉債（現金低於最低現金時） | B68: US$B | E68: 0 | F68: =MAX(0,min_cash-F67) -> 0 | G68: =E68+F68 -> 0 | H68: =MAX(0,min_cash-H67) -> 0 | I68: =MAX(0,min_cash-I67) -> 13.073683 | J68: =MAX(0,min_cash-J67) -> 0 | K68: =MAX(0,min_cash-K67) -> 0 | L68: =MAX(0,min_cash-L67) -> 0 | M68: =MAX(0,min_cash-M67) -> 0
A69: 期末現金（現金＋有價證券） | B69: US$B | E69: =E67+E68 -> 89.855 | F69: =F67+F68 -> 79.24546 | H69: =H67+H68 -> 37.092926 | I69: =I67+I68 -> 30 | J69: =J67+J68 -> 37.31142 | K69: =K67+K68 -> 60.88486 | L69: =L67+L68 -> 90.499246 | M69: =M67+M68 -> 119.16645
A70: 檢查：9M26 期末現金 − 2026-09-30 資產負債表 | B70: US$B | E70: =E69-cash_0 -> 0
A71: 期初債務本金 | B71: US$B | E71: =debt_ye25 -> 22.049 | F71: =E72 -> 38.006 | H71: =F72 -> 39.096164 | I71: =H72 -> 43.400419 | J71: =I72 -> 60.724955 | K71: =J72 -> 62.817236 | L71: =K72 -> 63.71713 | M71: =L72 -> 63.419891
A72: 期末債務本金（＋以其他融資取得 PP&E） | B72: US$B | E72: =debt_0 -> 38.006 | F72: =F71-F59+F68+F57 -> 39.096164 | H72: =H71-H59+H68+H57 -> 43.400419 | I72: =I71-I59+I68+I57 -> 60.724955 | J72: =J71-J59+J68+J57 -> 62.817236 | K72: =K71-K59+K68+K57 -> 63.71713 | L72: =L71-L59+L68+L57 -> 63.419891 | M72: =M71-M59+M68+M57 -> 63.870404
A73: 淨現金（現金 − 債務） | B73: US$B | E73: =E69-E72 -> 51.849 | F73: =F69-F72 -> 40.149295 | H73: =H69-H72 -> -6.3074934 | I73: =I69-I72 -> -30.724955 | J73: =J69-J72 -> -25.505816 | K73: =K69-K72 -> -2.8322698 | L73: =L69-L72 -> 27.079355 | M73: =M69-M72 -> 55.296047
A75: 情境 C（租金收斂到持有成本、Starlink 增長放緩）
A76: 項目 | B76: 單位 | C76: FY2025* | D76: 9M25A | E76: 9M26A | F76: Q4 26E | G76: FY2026E | H76: FY2027E | I76: FY2028E | J76: FY2029E | K76: FY2030E | L76: FY2031E | M76: FY2032E | N76: 說明
A77: 淨利 | B77: US$B | E77: =PL!E190 -> -0.413 | F77: =PL!F190 -> 2.3139751 | G77: =PL!G190 -> 1.9009751 | H77: =PL!H190 -> 12.608859 | I77: =PL!I190 -> 14.827622 | J77: =PL!J190 -> 15.134425 | K77: =PL!K190 -> 9.0720936 | L77: =PL!L190 -> 8.2998876 | M77: =PL!M190 -> 8.2268444
A78: 折舊攤銷 | B78: US$B | E78: =PL!E167 -> 8.934 | F78: =PL!F167 -> 3.9598477 | G78: =PL!G167 -> 12.893848 | H78: =PL!H167 -> 22.374707 | I78: =PL!I167 -> 33.624527 | J78: =PL!J167 -> 45.125732 | K78: =PL!K167 -> 55.272439 | L78: =PL!L167 -> 63.544576 | M78: =PL!M167 -> 69.303147
A79: 股權報酬（非現金；含 Cursor 收購後服務期獎酬） | B79: US$B | E79: =PL!E173 -> 3.835 | F79: =PL!F173 -> 3.39826 | G79: =PL!G173 -> 7.23326 | H79: =PL!H173 -> 15.182909 | I79: =PL!I173 -> 17.629996 | J79: =PL!J173 -> 14.202938 | K79: =PL!K173 -> 11.30199 | L79: =PL!L173 -> 12.614088 | M79: =PL!M173 -> 13.671389
A80: 營運資金變動（流入＋） | B80: US$B | F80: =wc_k*(PL!F150-(Q!I17-Q!G17)) -> 0.3240934 | G80: =F80 -> 0.3240934 | H80: =wc_k*(PL!H150-PL!G150) -> 1.1330099 | I80: =wc_k*(PL!I150-PL!H150) -> 0.79621719 | J80: =wc_k*(PL!J150-PL!I150) -> 0.55312068 | K80: =wc_k*(PL!K150-PL!J150) -> 0.20626883 | L80: =wc_k*(PL!L150-PL!K150) -> 0.42663992 | M80: =wc_k*(PL!M150-PL!L150) -> 0.35883539 | N80: Q4 26＝wc_k ×(Q4 26 營收 − 2025Q4 營收〔FY2025 二手 − 9M25〕)；之後＝營收增量 × wc_k
A81: 其他（9M26 實績差額：營運資金、遞延稅、清償損失等；預測期 0） | B81: US$B | E81: =cfo_9m-E77-E78-E79 -> 0.741 | F81: 0 | G81: =E81+F81 -> 0.741 | H81: 0 | I81: 0 | J81: 0 | K81: 0 | L81: 0 | M81: 0
A82: 營運現金流 | B82: US$B | E82: =E77+E78+E79+N(E80)+E81 -> 13.097 | F82: =F77+F78+F79+N(F80)+F81 -> 9.9961762 | G82: =G77+G78+G79+N(G80)+G81 -> 23.093176 | H82: =H77+H78+H79+N(H80)+H81 -> 51.299485 | I82: =I77+I78+I79+N(I80)+I81 -> 66.878362 | J82: =J77+J78+J79+N(J80)+J81 -> 75.016216 | K82: =K77+K78+K79+N(K80)+K81 -> 75.852792 | L82: =L77+L78+L79+N(L80)+L81 -> 84.885192 | M82: =M77+M78+M79+N(M80)+M81 -> 91.560215
A83: 資本支出：Space | B83: US$B | E83: =Q!H35 -> 3.832 | F83: =Seg!F113 -> 1.4732917 | G83: =E83+F83 -> 5.3052917 | H83: =Seg!H113 -> 4.9481884 | I83: =Seg!I113 -> 4.0993778 | J83: =Seg!J113 -> 3.1213593 | K83: =Seg!K113 -> 1.9804463 | L83: =Seg!L113 -> 2.1409277 | M83: =Seg!M113 -> 2.3144143
A84: 資本支出：Connectivity | B84: US$B | E84: =Q!H36 -> 4.242 | F84: =Seg!F114 -> 1.963589 | G84: =E84+F84 -> 6.205589 | H84: =Seg!H114 -> 9.3220584 | I84: =Seg!I114 -> 11.941647 | J84: =Seg!J114 -> 14.207275 | K84: =Seg!K114 -> 15.654319 | L84: =Seg!L114 -> 17.044416 | M84: =Seg!M114 -> 18.399639
A85: 資本支出：SI（現金） | B85: US$B | E85: =Thesis!E44 -> 39.995 | F85: =Thesis!F44 -> 16.165836 | G85: =Thesis!G44 -> 56.160836 | H85: =Thesis!H44 -> 68.626344 | I85: =Thesis!I44 -> 72.589345 | J85: =Thesis!J44 -> 56.23579 | K85: =Thesis!K44 -> 45.860256 | L85: =Thesis!L44 -> 47.959744 | M85: =Thesis!M44 -> 55.585457
A86: 資本支出合計（現金） | B86: US$B | E86: =E83+E84+E85 -> 48.069 | F86: =F83+F84+F85 -> 19.602716 | G86: =G83+G84+G85 -> 67.671716 | H86: =H83+H84+H85 -> 82.896591 | I86: =I83+I84+I85 -> 88.63037 | J86: =J83+J84+J85 -> 73.564425 | K86: =K83+K84+K85 -> 63.49502 | L86: =L83+L84+L85 -> 67.145088 | M86: =M83+M84+M85 -> 76.299511
A87: 檢查：9M26 資本支出 − 10-Q 購置不動產與設備 | B87: US$B | E87: =E86-capex_9m -> 0
A88: 以其他融資取得 PP&E（非現金；SI） | B88: US$B | E88: =Thesis!E45 -> 3.921 | F88: =Thesis!F45 -> 1.5851643 | G88: =Thesis!G45 -> 5.5061643 | H88: =Thesis!H45 -> 6.729255 | I88: =Thesis!I45 -> 7.1178527 | J88: =Thesis!J45 -> 5.5142814 | K88: =Thesis!K45 -> 4.4968934 | L88: =Thesis!L45 -> 4.7027618 | M88: =Thesis!M45 -> 5.4505121
A89: 融資租賃本金 | B89: US$B | E89: =lease_1H -> 0.27 | F89: =lease_2H -> 0.123 | G89: =E89+F89 -> 0.393 | H89: =lease_27 -> 0.25 | I89: =lease_28 -> 0.2 | J89: =lease_29 -> 0.15 | K89: =lease_30 -> 0.1 | L89: =lease_31 -> 0.1 | M89: =lease_32 -> 0.1
A90: Valor 失敗售後租回與設備融資本金償還（債務到期表） | B90: US$B | E90: =slb_1H -> 0 | F90: =mat_2H -> 0.495 | G90: =E90+F90 -> 0.495 | H90: =mat_27 -> 2.425 | I90: =mat_28 -> 2.867 | J90: =mat_29 -> 3.422 | K90: =mat_30 -> 3.597 | L90: =mat_31 -> 5 | M90: =mat_32 -> 5 | N90: 9M26 未單獨揭露（資料缺口，0）；預測期＝10-Q 到期表（SpaceX Notes 2031 前無重大本金 → 推定主要為失敗售後租回）
A91: 公司口徑 FCF（營運現金 − 資本支出） | B91: US$B | E91: =E82-E86 -> -34.972 | F91: =F82-F86 -> -9.6065402 | G91: =G82-G86 -> -44.57854 | H91: =H82-H86 -> -31.597106 | I91: =I82-I86 -> -21.752008 | J91: =J82-J86 -> 1.4517914 | K91: =K82-K86 -> 12.357772 | L91: =L82-L86 -> 17.740104 | M91: =M82-M86 -> 15.260705
A92: 自由現金流（收支關卡口徑：− 融資租賃本金 − 失敗售後租回本金 − 以其他融資取得 PP&E） | B92: US$B | E92: =E91-E89-E90-E88 -> -39.163 | F92: =F91-F89-F90-F88 -> -11.809705 | G92: =G91-G89-G90-G88 -> -50.972705 | H92: =H91-H89-H90-H88 -> -41.001361 | I92: =I91-I89-I90-I88 -> -31.936861 | J92: =J91-J89-J90-J88 -> -7.6344899 | K92: =K91-K89-K90-K88 -> 4.1638781 | L92: =L91-L89-L90-L88 -> 7.9373425 | M92: =M91-M89-M90-M88 -> 4.7101925
A93: EchoStar 頻譜（投資活動；按成本） | B93: US$B | E93: 0 | F93: =spec_2h -> 0.385 | G93: =E93+F93 -> 0.385 | H93: =spec_27 -> 9.328 | I93: 0 | J93: 0 | K93: 0 | L93: 0 | M93: 0
A94: 9M26 債務淨流入／預測期已知新債 | B94: US$B | E94: =debt_1H -> 10.712 | F94: 0 | G94: =E94+F94 -> 10.712 | H94: 0 | I94: 0 | J94: 0 | K94: 0 | L94: 0 | M94: 0
A95: 股權淨流入（9M26 IPO 等） | B95: US$B | E95: =eq_1H -> 89.377 | F95: 0 | G95: =E95+F95 -> 89.377 | H95: 0 | I95: 0 | J95: 0 | K95: 0 | L95: 0 | M95: 0
A96: 期初現金（現金＋有價證券） | B96: US$B | E96: =cash_ye25 -> 24.747 | F96: =E100 -> 89.855 | H96: =F100 -> 79.24546 | I96: =H100 -> 35.645354 | J96: =I100 -> 30 | K96: =J100 -> 30 | L96: =K100 -> 38.660772 | M96: =L100 -> 51.300876
A97: 其他（9M26 實績差額：收購現金、產品回饋金、匯率、頻譜預付等；預測期 0） | B97: US$B | E97: =cash_0-(E96+E82-E86-E89+E94+E95) -> 0.261 | F97: 0 | H97: 0 | I97: 0 | J97: 0 | K97: 0 | L97: 0 | M97: 0
A98: 新債前現金 | B98: US$B | E98: =E96+E82-E86-E89+E94+E95+E97 -> 89.855 | F98: =F96+F82-F86-F89-F90-F93 -> 79.24546 | H98: =H96+H82-H86-H89-H90-H93 -> 35.645354 | I98: =I96+I82-I86-I89-I90-I93 -> 10.826345 | J98: =J96+J82-J86-J89-J90-J93 -> 27.879791 | K98: =K96+K82-K86-K89-K90-K93 -> 38.660772 | L98: =L96+L82-L86-L89-L90-L93 -> 51.300876 | M98: =M96+M82-M86-M89-M90-M93 -> 61.46158
A99: 新增舉債（現金低於最低現金時） | B99: US$B | E99: 0 | F99: =MAX(0,min_cash-F98) -> 0 | G99: =E99+F99 -> 0 | H99: =MAX(0,min_cash-H98) -> 0 | I99: =MAX(0,min_cash-I98) -> 19.173655 | J99: =MAX(0,min_cash-J98) -> 2.1202086 | K99: =MAX(0,min_cash-K98) -> 0 | L99: =MAX(0,min_cash-L98) -> 0 | M99: =MAX(0,min_cash-M98) -> 0
A100: 期末現金（現金＋有價證券） | B100: US$B | E100: =E98+E99 -> 89.855 | F100: =F98+F99 -> 79.24546 | H100: =H98+H99 -> 35.645354 | I100: =I98+I99 -> 30 | J100: =J98+J99 -> 30 | K100: =K98+K99 -> 38.660772 | L100: =L98+L99 -> 51.300876 | M100: =M98+M99 -> 61.46158
A101: 檢查：9M26 期末現金 − 2026-09-30 資產負債表 | B101: US$B | E101: =E100-cash_0 -> 0
A102: 期初債務本金 | B102: US$B | E102: =debt_ye25 -> 22.049 | F102: =E103 -> 38.006 | H102: =F103 -> 39.096164 | I102: =H103 -> 43.400419 | J102: =I103 -> 66.824927 | K102: =J103 -> 71.037417 | L102: =K103 -> 71.93731 | M102: =L103 -> 71.640072
A103: 期末債務本金（＋以其他融資取得 PP&E） | B103: US$B | E103: =debt_0 -> 38.006 | F103: =F102-F90+F99+F88 -> 39.096164 | H103: =H102-H90+H99+H88 -> 43.400419 | I103: =I102-I90+I99+I88 -> 66.824927 | J103: =J102-J90+J99+J88 -> 71.037417 | K103: =K102-K90+K99+K88 -> 71.93731 | L103: =L102-L90+L99+L88 -> 71.640072 | M103: =M102-M90+M99+M88 -> 72.090584
A104: 淨現金（現金 − 債務） | B104: US$B | E104: =E100-E103 -> 51.849 | F104: =F100-F103 -> 40.149295 | H104: =H100-H103 -> -7.7550655 | I104: =I100-I103 -> -36.824927 | J104: =J100-J103 -> -41.037417 | K104: =K100-K103 -> -33.276538 | L104: =L100-L103 -> -20.339196 | M104: =M100-M103 -> -10.629004

Sheet Val
A1: Val — 目標價（2027-10-30）＝DCF 50%＋分部加總（SOTP）50%；情境權重 A 25%／B 50%／C 25%（In 頁，黃底＝判斷題）。分部加總即本模型的 Comparable（在分部層做）。主值＝自用 AI 讀法 2（In 頁 internal_ai_reading），讀法 1 並列
A2: DCF：無槓桿自由現金流（NOPAT＋折舊 − 全部投資〔現金資本支出＋以其他融資取得 PP&E〕＋營運資金；股權報酬視為成本、不加回）以 WACC 折現到評價日 2026-09-30（期中慣例），終值＝NOPAT(FY2033) ×(1 − g ÷ RONIC) ÷ (WACC − g)，以 ke 推到目標時點。SOTP：目標時點 NTM 分部調整後 EBITDA × 同業倍數；SI 對外出租用自身 DCF；Space 用 EV／營收
A4: 0.3 結論
A5: 項目 | B5: 數值 | C5: 對照 | D5: 對照 | E5: 說明
A6: DCF 目標價（情境加權） | B6: =tp_wA*B120+tp_wB*C120+tp_wC*D120 -> 20.658442
A7: Comparable 目標價（市場主流同業法） | B7: =tp_wA*B146+tp_wB*C146+tp_wC*D146 -> 34.372471 | E7: ＝分部加總（SOTP）情境加權；Connectivity、SI 其他用同業倍數，SI 對外出租用自身 DCF，Space 用 EV／營收
A8: 目標價（DCF 與 Comparable 加權） | B8: =w_dcf*B6+(1-w_dcf)*B7 -> 27.515456 | E8: ="DCF 權重 "&TEXT(w_dcf,"0%")&"、分部加總 "&TEXT(1-w_dcf,"0%")&"；自用 AI 讀法 "&internal_ai_reading -> DCF 權重 50%、分部加總 50%；自用 AI 讀法 2
A9: 現價（2026-10-29 收盤） | B9: =px -> 143.89 | E9: MarketBeat、Equibles 兩來源一致（In 頁 px）
A10: 市場共識目標價 | B10: =cons_tp -> 244.97 | E10: MarketBeat 46 位分析師平均（含 10-21～10-26 財報後調整）；只作對照
A11: 上檔空間：加權目標價 | B11: =B8/px-1 -> -0.80877437
A12: 上檔空間：Comparable 目標價 | B12: =B7/px-1 -> -0.76111981
A13: 上檔空間級距 | B13: =IF(B11>=0.5,"大於 50%",IF(B11>=0.25,"25%–50%",IF(B11>=0,"0%–25%",IF(B11>-0.25,"0%～−25%",IF(B11>-0.5,"−25%～−50%","小於 −50%"))))) -> 小於 −50% | E13: 以「上檔空間：加權目標價」分六級（Andy 2026-10-25 14:00）
A14: 投資建議 | B14: =IF(B11>=0.5,"強力買進",IF(B11>=0.25,"買進",IF(B11>-0.25,"中立",IF(B11>-0.5,"放空","強力放空")))) -> 強力放空 | E14: 五級固定規則：≥ +50% 強力買進、+25%～+50% 買進、−25%～+25% 中立、−50%～−25% 放空、≤ −50% 強力放空
A15: 價格帶（DCF 不如預期～順利） | B15: =D120 -> 10.98547 | C15: =B120 -> 31.885318 | E15: B＝C 情境 DCF、C＝A 情境 DCF（皆推到 12 個月後）
A16: 悲觀情境價（C 情境 DCF） | B16: =D120 -> 10.98547 | E16: 地圖「悲觀情境空間」＝本列 ÷ 現價 − 1
A17: 情境目標價（A／B／C；DCF 與分部加總加權） | B17: =w_dcf*B120+(1-w_dcf)*B146 -> 39.106868 | C17: =w_dcf*C120+(1-w_dcf)*C146 -> 26.690906 | D17: =w_dcf*D120+(1-w_dcf)*D146 -> 17.573145
A18: 情境上檔空間（A／B／C） | B18: =B17/px-1 -> -0.72821692 | C18: =C17/px-1 -> -0.81450479 | D18: =D17/px-1 -> -0.87787098
A19: DCF 終值占 EV（A／B／C） | B19: =B113 -> 0.93036334 | C19: =C113 -> 1.1310598 | D19: =D113 -> 1.7408204
A20: 讀法 2（自用 AI 價值中性）：目標價／上檔空間／投資建議 | B20: =w_dcf*(tp_wA*B119+tp_wB*C119+tp_wC*D119)+(1-w_dcf)*(tp_wA*B145+tp_wB*C145+tp_wC*D145) -> 27.515456 | C20: =B20/px-1 -> -0.80877437 | D20: =IF(C20>=0.5,"強力買進",IF(C20>=0.25,"買進",IF(C20>-0.25,"中立",IF(C20>-0.5,"放空","強力放空")))) -> 強力放空 | E20: 活公式（主值）
A21: 讀法 1（自用 AI 只計成本）：目標價／上檔空間／投資建議 | B21: =w_dcf*(tp_wA*B118+tp_wB*C118+tp_wC*D118)+(1-w_dcf)*(tp_wA*B144+tp_wB*C144+tp_wC*D144) -> 20.20877 | C21: =B21/px-1 -> -0.85955403 | D21: =IF(C21>=0.5,"強力買進",IF(C21>=0.25,"買進",IF(C21>-0.25,"中立",IF(C21>-0.5,"放空","強力放空")))) -> 強力放空 | E21: 活公式（下緣敏感度）
A22: 讀法 1／2 的 DCF 目標價（情境加權） | B22: =tp_wA*B118+tp_wB*C118+tp_wC*D118 -> 9.1994157 | C22: =tp_wA*B119+tp_wB*C119+tp_wC*D119 -> 20.658442
A23: 讀法 1／2 的分部加總目標價（情境加權） | B23: =tp_wA*B144+tp_wB*C144+tp_wC*D144 -> 31.218125 | C23: =tp_wA*B145+tp_wB*C145+tp_wC*D145 -> 34.372471
A24: S2 核心問題：FY2028 SI 每 GW 年營收 ÷ Tokenomics 每 GW 年持有成本（A／B／C） | B24: =Seg!I35 -> 1.7333063 | C24: =Seg!I73 -> 1.5583063 | D24: =Seg!I111 -> 1.4333063 | E24: ="2026Q3 校準 k0＝"&TEXT(k0,"0.00")&"；FY2028 情境 B 每 GW 年營收 "&TEXT(Seg!I45,"0.0")&"、持有成本 "&TEXT(Thesis!I33,"0.0")&"（US$B/GW-年）" -> 2026Q3 校準 k0＝1.87；FY2028 情境 B 每 GW 年營收 17.0、持有成本 10.9（US$B/GW-年）
A25: 收支關卡：FY2026–FY2030 自由現金流（收支關卡口徑；A／B／C） | B25: =CF!B6 -> -55.482988 | C25: =CF!C6 -> -96.93727 | D25: =CF!D6 -> -127.38154 | E25: CF 頁；公司口徑對照見 CF 頁
A26: 目標價方法 | B26: DCF（無槓桿 FCF、WACC、RONIC＝WACC）50%＋分部加總（Connectivity、SI 其他同業倍數；SI 對外出租自身 DCF；Space EV／營收）50%；情境 25／50／25；自用 AI 讀法 2
A27: 檢查：情境權重合計（應為 1） | B27: =ROUND(tp_wA+tp_wB+tp_wC,6) -> 1
A28: 檢查：主值目標價 − 所選讀法的目標價（應為 0） | B28: =B8-IF(internal_ai_reading=2,B20,B21) -> 0
A33: 0.0 折現率（CAPM；負債含融資租賃）
A34: 項目 | B34: 數值 | E34: 說明
A35: 股權市值 E＝評價日股價 × 流通股 | B35: =px_val*sh_out -> 2048.8393
A36: 負債 D（債務本金＋融資租賃） | B36: =debt_0+fin_lease -> 38.989
A37: 股東權益成本 ke＝rf＋β × ERP | B37: =rf+beta*erp -> 0.1149 | E37: ="β（判斷）"&TEXT(beta,"0.00") -> β（判斷）1.30
A38: 稅後債務成本 | B38: =kd*(1-tax_w) -> 0.0479688
A39: WACC（＋wacc_adj，Sens 用） | B39: =(B35*ke+B36*B38)/(B35+B36)+wacc_adj -> 0.1136501
A40: 永續期新投資報酬 RONIC＝WACC＋ronic_sp | B40: =wacc+ronic_sp -> 0.1136501
A42: 0.1 DCF（無槓桿自由現金流；三情境各一區塊；欄 F＝Q4 26、H–M＝FY2027–FY2032）＋0.15 SI 對外出租模組 DCF（分部加總的對外出租腿）
A43: 情境 A（算力租金維持高檔、Starlink 增長快）
A44: 項目 | E44: 說明 | F44: Q4 26E | H44: FY2027E | I44: FY2028E | J44: FY2029E | K44: FY2030E | L44: FY2031E | M44: FY2032E
A45: 營業利益（財報口徑 EBIT） | F45: =PL!F54 -> 2.4774577 | H45: =PL!H54 -> 17.969535 | I45: =PL!I54 -> 30.553443 | J45: =PL!J54 -> 43.793019 | K45: =PL!K54 -> 49.619974 | L45: =PL!L54 -> 52.533048 | M45: =PL!M54 -> 54.19079
A46: NOPAT＝(EBIT＋sbc_add × 股權報酬) ×(1 − 稅率) | F46: =(F45+sbc_add*PL!F49)*(1-tax) -> 2.1801627 | H46: =(H45+sbc_add*PL!H49)*(1-tax) -> 15.813191 | I46: =(I45+sbc_add*PL!I49)*(1-tax) -> 26.88703 | J46: =(J45+sbc_add*PL!J49)*(1-tax) -> 38.537856 | K46: =(K45+sbc_add*PL!K49)*(1-tax) -> 43.665577 | L46: =(L45+sbc_add*PL!L49)*(1-tax) -> 46.229083 | M46: =(M45+sbc_add*PL!M49)*(1-tax) -> 47.687895
A47: ＋折舊攤銷 | F47: =PL!F43 -> 3.9598477 | H47: =PL!H43 -> 22.394611 | I47: =PL!I43 -> 33.76071 | J47: =PL!J43 -> 45.51974 | K47: =PL!K43 -> 56.046011 | L47: =PL!L43 -> 64.802041 | M47: =PL!M43 -> 71.133541
A48: − 投資（現金資本支出＋以其他融資取得 PP&E） | F48: =CF!F24+CF!F26 -> 21.187881 | H48: =CF!H24+CF!H26 -> 90.103541 | I48: =CF!I24+CF!I26 -> 97.105833 | J48: =CF!J24+CF!J26 -> 81.193676 | K48: =CF!K24+CF!K26 -> 70.756523 | L48: =CF!L24+CF!L26 -> 75.167457 | M48: =CF!M24+CF!M26 -> 85.541514
A49: ＋營運資金變動 | F49: =CF!F18 -> 0.3240934 | H49: =CF!H18 -> 1.2650837 | I49: =CF!I18 -> 1.0792711 | J49: =CF!J18 -> 0.92744548 | K49: =CF!K18 -> 0.62543877 | L49: =CF!L18 -> 0.58362053 | M49: =CF!M18 -> 0.45929173
A50: 無槓桿自由現金流（財報口徑） | F50: =F46+F47-F48+F49 -> -14.723777 | H50: =H46+H47-H48+H49 -> -50.630656 | I50: =I46+I47-I48+I49 -> -35.378823 | J50: =J46+J47-J48+J49 -> 3.7913665 | K50: =K46+K47-K48+K49 -> 29.580503 | L50: =L46+L47-L48+L49 -> 36.447287 | M50: =M46+M47-M48+M49 -> 33.739214
A51: 自用 AI 影子效益（稅後；讀法 2 加入） | F51: =PL!F56*(1-tax) -> 0.13638647 | H51: =PL!H56*(1-tax) -> 3.4074828 | I51: =PL!I56*(1-tax) -> 8.1744722 | J51: =PL!J56*(1-tax) -> 12.523577 | K51: =PL!K56*(1-tax) -> 15.796976 | L51: =PL!L56*(1-tax) -> 18.039842 | M51: =PL!M56*(1-tax) -> 19.274287
A52: 折現年數（評價日 2026-09-30 起，期中） | F52: =t_q4 -> 0.125 | H52: =2027+mid-t_val -> 0.75 | I52: =2028+mid-t_val -> 1.75 | J52: =2029+mid-t_val -> 2.75 | K52: =2030+mid-t_val -> 3.75 | L52: =2031+mid-t_val -> 4.75 | M52: =2032+mid-t_val -> 5.75
A53: 折現因子 1 ÷ (1＋WACC)^年數 | F53: =1/(1+wacc)^F52 -> 0.98663474 | H53: =1/(1+wacc)^H52 -> 0.92244064 | I53: =1/(1+wacc)^I52 -> 0.82830383 | J53: =1/(1+wacc)^J52 -> 0.74377386 | K53: =1/(1+wacc)^K52 -> 0.66787033 | L53: =1/(1+wacc)^L52 -> 0.5997129 | M53: =1/(1+wacc)^M52 -> 0.53851107
A54: 現值（財報口徑） | F54: =F50*F53 -> -14.52699 | H54: =H50*H53 -> -46.703775 | I54: =I50*I53 -> -29.304414 | J54: =J50*J53 -> 2.8199193 | K54: =K50*K53 -> 19.755941 | L54: =L50*L53 -> 21.857908 | M54: =M50*M53 -> 18.16894
A55: 現值（影子效益） | F55: =F51*F53 -> 0.13456363 | H55: =H51*H53 -> 3.1432006 | I55: =I51*I53 -> 6.7709467 | J55: =J51*J53 -> 9.3147093 | K55: =K51*K53 -> 10.550331 | L55: =L51*L53 -> 10.818726 | M55: =M51*M53 -> 10.379417
A56: 0.15 SI 對外出租 EBITDA | F56: =PL!F36 -> 5.6396031 | H56: =PL!H36 -> 35.228762 | I56: =PL!I36 -> 55.49721 | J56: =PL!J36 -> 72.11742 | K56: =PL!K36 -> 82.5525 | L56: =PL!L36 -> 91.916346 | M56: =PL!M36 -> 97.07009
A57: 0.15 對外新增 AI 折舊 | F57: =Thesis!F56 -> 0.2389636 | H57: =Thesis!H56 -> 5.6944719 | I57: =Thesis!I56 -> 13.309237 | J57: =Thesis!J56 -> 20.864707 | K57: =Thesis!K56 -> 26.808823 | L57: =Thesis!L56 -> 32.127075 | M57: =Thesis!M56 -> 37.347744
A58: 0.15 對外出租 NOPAT | F58: =(F56-F57)*(1-tax) -> 4.7525628 | H58: =(H56-H57)*(1-tax) -> 25.990175 | I58: =(I56-I57)*(1-tax) -> 37.125417 | J58: =(J56-J57)*(1-tax) -> 45.102387 | K58: =(K56-K57)*(1-tax) -> 49.054435 | L58: =(L56-L57)*(1-tax) -> 52.614559 | M58: =(M56-M57)*(1-tax) -> 52.555664
A59: 0.15 對外出租投資（SI 投資 × ext_sh） | F59: =Thesis!F43*ext_sh -> 12.78072 | H59: =Thesis!H43*ext_sh -> 54.256031 | I59: =Thesis!I43*ext_sh -> 57.389182 | J59: =Thesis!J43*ext_sh -> 44.460051 | K59: =Thesis!K43*ext_sh -> 36.257147 | L59: =Thesis!L43*ext_sh -> 37.917005 | M59: =Thesis!M43*ext_sh -> 43.945898
A60: 0.15 對外出租自由現金流 | F60: =F58+F57-F59 -> -7.7891936 | H60: =H58+H57-H59 -> -22.571384 | I60: =I58+I57-I59 -> -6.9545285 | J60: =J58+J57-J59 -> 21.507043 | K60: =K58+K57-K59 -> 39.606112 | L60: =L58+L57-L59 -> 46.824629 | M60: =M58+M57-M59 -> 45.957511
A61: 0.15 現值 | F61: =F60*F53 -> -7.685089 | H61: =H60*H53 -> -20.820762 | I61: =I60*I53 -> -5.7604626 | J61: =J60*J53 -> 15.996376 | K61: =K60*K53 -> 26.451747 | L61: =L60*L53 -> 28.081334 | M61: =M60*M53 -> 24.748628
A63: 情境 B（租金向持有成本部分收斂；基準）
A64: 項目 | E64: 說明 | F64: Q4 26E | H64: FY2027E | I64: FY2028E | J64: FY2029E | K64: FY2030E | L64: FY2031E | M64: FY2032E
A65: 營業利益（財報口徑 EBIT） | F65: =PL!F116 -> 2.4774577 | H65: =PL!H116 -> 15.835341 | I65: =PL!I116 -> 23.789229 | J65: =PL!J116 -> 30.695411 | K65: =PL!K116 -> 29.347443 | L65: =PL!L116 -> 29.94571 | M65: =PL!M116 -> 30.329179
A66: NOPAT＝(EBIT＋sbc_add × 股權報酬) ×(1 − 稅率) | F66: =(F65+sbc_add*PL!F111)*(1-tax) -> 2.1801627 | H66: =(H65+sbc_add*PL!H111)*(1-tax) -> 13.9351 | I66: =(I65+sbc_add*PL!I111)*(1-tax) -> 20.934521 | J66: =(J65+sbc_add*PL!J111)*(1-tax) -> 27.011961 | K66: =(K65+sbc_add*PL!K111)*(1-tax) -> 25.82575 | L66: =(L65+sbc_add*PL!L111)*(1-tax) -> 26.352225 | M66: =(M65+sbc_add*PL!M111)*(1-tax) -> 26.689677
A67: ＋折舊攤銷 | F67: =PL!F105 -> 3.9598477 | H67: =PL!H105 -> 22.384659 | I67: =PL!I105 -> 33.692618 | J67: =PL!J105 -> 45.322736 | K67: =PL!K105 -> 55.659225 | L67: =PL!L105 -> 64.173309 | M67: =PL!M105 -> 70.218344
A68: − 投資（現金資本支出＋以其他融資取得 PP&E） | F68: =CF!F55+CF!F57 -> 21.187881 | H68: =CF!H55+CF!H57 -> 89.864693 | I68: =CF!I55+CF!I57 -> 96.427028 | J68: =CF!J55+CF!J57 -> 80.136191 | K68: =CF!K55+CF!K57 -> 69.374218 | L68: =CF!L55+CF!L57 -> 73.507654 | M68: =CF!M55+CF!M57 -> 83.645768
A69: ＋營運資金變動 | F69: =CF!F49 -> 0.3240934 | H69: =CF!H49 -> 1.1914029 | I69: =CF!I49 -> 0.92034961 | J69: =CF!J49 -> 0.71442002 | K69: =CF!K49 -> 0.38549547 | L69: =CF!L49 -> 0.49595486 | M69: =CF!M49 -> 0.40401355
A70: 無槓桿自由現金流（財報口徑） | F70: =F66+F67-F68+F69 -> -14.723777 | H70: =H66+H67-H68+H69 -> -52.353532 | I70: =I66+I67-I68+I69 -> -40.879539 | J70: =J66+J67-J68+J69 -> -7.0870733 | K70: =K66+K67-K68+K69 -> 12.496252 | L70: =L66+L67-L68+L69 -> 17.513835 | M70: =M66+M67-M68+M69 -> 13.666266
A71: 自用 AI 影子效益（稅後；讀法 2 加入） | F71: =PL!F118*(1-tax) -> 0.13638647 | H71: =PL!H118*(1-tax) -> 3.4074828 | I71: =PL!I118*(1-tax) -> 8.1744722 | J71: =PL!J118*(1-tax) -> 12.523577 | K71: =PL!K118*(1-tax) -> 15.796976 | L71: =PL!L118*(1-tax) -> 18.039842 | M71: =PL!M118*(1-tax) -> 19.274287
A72: 折現年數（評價日 2026-09-30 起，期中） | F72: =t_q4 -> 0.125 | H72: =2027+mid-t_val -> 0.75 | I72: =2028+mid-t_val -> 1.75 | J72: =2029+mid-t_val -> 2.75 | K72: =2030+mid-t_val -> 3.75 | L72: =2031+mid-t_val -> 4.75 | M72: =2032+mid-t_val -> 5.75
A73: 折現因子 1 ÷ (1＋WACC)^年數 | F73: =1/(1+wacc)^F72 -> 0.98663474 | H73: =1/(1+wacc)^H72 -> 0.92244064 | I73: =1/(1+wacc)^I72 -> 0.82830383 | J73: =1/(1+wacc)^J72 -> 0.74377386 | K73: =1/(1+wacc)^K72 -> 0.66787033 | L73: =1/(1+wacc)^L72 -> 0.5997129 | M73: =1/(1+wacc)^M72 -> 0.53851107
A74: 現值（財報口徑） | F74: =F70*F73 -> -14.52699 | H74: =H70*H73 -> -48.293026 | I74: =I70*I73 -> -33.860679 | J74: =J70*J73 -> -5.2711799 | K74: =K70*K73 -> 8.3458761 | L74: =L70*L73 -> 10.503273 | M74: =M70*M73 -> 7.3594356
A75: 現值（影子效益） | F75: =F71*F73 -> 0.13456363 | H75: =H71*H73 -> 3.1432006 | I75: =I71*I73 -> 6.7709467 | J75: =J71*J73 -> 9.3147093 | K75: =K71*K73 -> 10.550331 | L75: =L71*L73 -> 10.818726 | M75: =M71*M73 -> 10.379417
A76: 0.15 SI 對外出租 EBITDA | F76: =PL!F98 -> 5.6396031 | H76: =PL!H98 -> 33.317791 | I76: =PL!I98 -> 49.237604 | J76: =PL!J98 -> 59.392049 | K76: =PL!K98 -> 62.237545 | L76: =PL!L98 -> 69.307551 | M76: =PL!M98 -> 73.198794
A77: 0.15 對外新增 AI 折舊 | F77: =Thesis!F56 -> 0.2389636 | H77: =Thesis!H56 -> 5.6944719 | I77: =Thesis!I56 -> 13.309237 | J77: =Thesis!J56 -> 20.864707 | K77: =Thesis!K56 -> 26.808823 | L77: =Thesis!L56 -> 32.127075 | M77: =Thesis!M56 -> 37.347744
A78: 0.15 對外出租 NOPAT | F78: =(F76-F77)*(1-tax) -> 4.7525628 | H78: =(H76-H77)*(1-tax) -> 24.308521 | I78: =(I76-I77)*(1-tax) -> 31.616963 | J78: =(J76-J77)*(1-tax) -> 33.904061 | K78: =(K76-K77)*(1-tax) -> 31.177275 | L78: =(L76-L77)*(1-tax) -> 32.718819 | M78: =(M76-M77)*(1-tax) -> 31.548924
A79: 0.15 對外出租投資（SI 投資 × ext_sh） | F79: =Thesis!F43*ext_sh -> 12.78072 | H79: =Thesis!H43*ext_sh -> 54.256031 | I79: =Thesis!I43*ext_sh -> 57.389182 | J79: =Thesis!J43*ext_sh -> 44.460051 | K79: =Thesis!K43*ext_sh -> 36.257147 | L79: =Thesis!L43*ext_sh -> 37.917005 | M79: =Thesis!M43*ext_sh -> 43.945898
A80: 0.15 對外出租自由現金流 | F80: =F78+F77-F79 -> -7.7891936 | H80: =H78+H77-H79 -> -24.253038 | I80: =I78+I77-I79 -> -12.462982 | J80: =J78+J77-J79 -> 10.308717 | K80: =K78+K77-K79 -> 21.728952 | L80: =L78+L77-L79 -> 26.928889 | M80: =M78+M77-M79 -> 24.95077
A81: 0.15 現值 | F81: =F80*F73 -> -7.685089 | H81: =H80*H73 -> -22.371988 | I81: =I80*I73 -> -10.323136 | J81: =J80*J73 -> 7.6673542 | K81: =K80*K73 -> 14.512122 | L81: =L80*L73 -> 16.149602 | M81: =M80*M73 -> 13.436266
A83: 情境 C（租金收斂到持有成本、Starlink 增長放緩）
A84: 項目 | E84: 說明 | F84: Q4 26E | H84: FY2027E | I84: FY2028E | J84: FY2029E | K84: FY2030E | L84: FY2031E | M84: FY2032E
A85: 營業利益（財報口徑 EBIT） | F85: =PL!F178 -> 2.4774577 | H85: =PL!H178 -> 14.187844 | I85: =PL!I178 -> 18.619251 | J85: =PL!J178 -> 20.83878 | K85: =PL!K178 -> 14.248854 | L85: =PL!L178 -> 13.116523 | M85: =PL!M178 -> 12.54726
A86: NOPAT＝(EBIT＋sbc_add × 股權報酬) ×(1 − 稅率) | F86: =(F85+sbc_add*PL!F173)*(1-tax) -> 2.1801627 | H86: =(H85+sbc_add*PL!H173)*(1-tax) -> 12.485303 | I86: =(I85+sbc_add*PL!I173)*(1-tax) -> 16.384941 | J86: =(J85+sbc_add*PL!J173)*(1-tax) -> 18.338127 | K86: =(K85+sbc_add*PL!K173)*(1-tax) -> 12.538991 | L86: =(L85+sbc_add*PL!L173)*(1-tax) -> 11.54254 | M86: =(M85+sbc_add*PL!M173)*(1-tax) -> 11.041589
A87: ＋折舊攤銷 | F87: =PL!F167 -> 3.9598477 | H87: =PL!H167 -> 22.374707 | I87: =PL!I167 -> 33.624527 | J87: =PL!J167 -> 45.125732 | K87: =PL!K167 -> 55.272439 | L87: =PL!L167 -> 63.544576 | M87: =PL!M167 -> 69.303147
A88: − 投資（現金資本支出＋以其他融資取得 PP&E） | F88: =CF!F86+CF!F88 -> 21.187881 | H88: =CF!H86+CF!H88 -> 89.625846 | I88: =CF!I86+CF!I88 -> 95.748223 | J88: =CF!J86+CF!J88 -> 79.078706 | K88: =CF!K86+CF!K88 -> 67.991914 | L88: =CF!L86+CF!L88 -> 71.84785 | M88: =CF!M86+CF!M88 -> 81.750023
A89: ＋營運資金變動 | F89: =CF!F80 -> 0.3240934 | H89: =CF!H80 -> 1.1330099 | I89: =CF!I80 -> 0.79621719 | J89: =CF!J80 -> 0.55312068 | K89: =CF!K80 -> 0.20626883 | L89: =CF!L80 -> 0.42663992 | M89: =CF!M80 -> 0.35883539
A90: 無槓桿自由現金流（財報口徑） | F90: =F86+F87-F88+F89 -> -14.723777 | H90: =H86+H87-H88+H89 -> -53.632826 | I90: =I86+I87-I88+I89 -> -44.942538 | J90: =J86+J87-J88+J89 -> -15.061727 | K90: =K86+K87-K88+K89 -> 0.025785754 | L90: =L86+L87-L88+L89 -> 3.6659067 | M90: =M86+M87-M88+M89 -> -1.046452
A91: 自用 AI 影子效益（稅後；讀法 2 加入） | F91: =PL!F180*(1-tax) -> 0.13638647 | H91: =PL!H180*(1-tax) -> 3.4074828 | I91: =PL!I180*(1-tax) -> 8.1744722 | J91: =PL!J180*(1-tax) -> 12.523577 | K91: =PL!K180*(1-tax) -> 15.796976 | L91: =PL!L180*(1-tax) -> 18.039842 | M91: =PL!M180*(1-tax) -> 19.274287
A92: 折現年數（評價日 2026-09-30 起，期中） | F92: =t_q4 -> 0.125 | H92: =2027+mid-t_val -> 0.75 | I92: =2028+mid-t_val -> 1.75 | J92: =2029+mid-t_val -> 2.75 | K92: =2030+mid-t_val -> 3.75 | L92: =2031+mid-t_val -> 4.75 | M92: =2032+mid-t_val -> 5.75
A93: 折現因子 1 ÷ (1＋WACC)^年數 | F93: =1/(1+wacc)^F92 -> 0.98663474 | H93: =1/(1+wacc)^H92 -> 0.92244064 | I93: =1/(1+wacc)^I92 -> 0.82830383 | J93: =1/(1+wacc)^J92 -> 0.74377386 | K93: =1/(1+wacc)^K92 -> 0.66787033 | L93: =1/(1+wacc)^L92 -> 0.5997129 | M93: =1/(1+wacc)^M92 -> 0.53851107
A94: 現值（財報口徑） | F94: =F90*F93 -> -14.52699 | H94: =H90*H93 -> -49.473099 | I94: =I90*I93 -> -37.226077 | J94: =J90*J93 -> -11.202519 | K94: =K90*K93 -> 0.01722154 | L94: =L90*L93 -> 2.1984915 | M94: =M90*M93 -> -0.563526
A95: 現值（影子效益） | F95: =F91*F93 -> 0.13456363 | H95: =H91*H93 -> 3.1432006 | I95: =I91*I93 -> 6.7709467 | J95: =J91*J93 -> 9.3147093 | K95: =K91*K93 -> 10.550331 | L95: =L91*L93 -> 10.818726 | M95: =M91*M93 -> 10.379417
A96: 0.15 SI 對外出租 EBITDA | F96: =PL!F160 -> 5.6396031 | H96: =PL!H160 -> 31.952812 | I96: =PL!I160 -> 44.766457 | J96: =PL!J160 -> 50.302499 | K96: =PL!K160 -> 47.726864 | L96: =PL!L160 -> 53.158412 | M96: =PL!M160 -> 56.147869
A97: 0.15 對外新增 AI 折舊 | F97: =Thesis!F56 -> 0.2389636 | H97: =Thesis!H56 -> 5.6944719 | I97: =Thesis!I56 -> 13.309237 | J97: =Thesis!J56 -> 20.864707 | K97: =Thesis!K56 -> 26.808823 | L97: =Thesis!L56 -> 32.127075 | M97: =Thesis!M56 -> 37.347744
A98: 0.15 對外出租 NOPAT | F98: =(F96-F97)*(1-tax) -> 4.7525628 | H98: =(H96-H97)*(1-tax) -> 23.107339 | I98: =(I96-I97)*(1-tax) -> 27.682354 | J98: =(J96-J97)*(1-tax) -> 25.905257 | K98: =(K96-K97)*(1-tax) -> 18.407875 | L98: =(L96-L97)*(1-tax) -> 18.507577 | M98: =(M96-M97)*(1-tax) -> 16.544109
A99: 0.15 對外出租投資（SI 投資 × ext_sh） | F99: =Thesis!F43*ext_sh -> 12.78072 | H99: =Thesis!H43*ext_sh -> 54.256031 | I99: =Thesis!I43*ext_sh -> 57.389182 | J99: =Thesis!J43*ext_sh -> 44.460051 | K99: =Thesis!K43*ext_sh -> 36.257147 | L99: =Thesis!L43*ext_sh -> 37.917005 | M99: =Thesis!M43*ext_sh -> 43.945898
A100: 0.15 對外出租自由現金流 | F100: =F98+F97-F99 -> -7.7891936 | H100: =H98+H97-H99 -> -25.45422 | I100: =I98+I97-I99 -> -16.397592 | J100: =J98+J97-J99 -> 2.3099127 | K100: =K98+K97-K99 -> 8.9595515 | L100: =L98+L97-L99 -> 12.717647 | M100: =M98+M97-M99 -> 9.9459557
A101: 0.15 現值 | F101: =F100*F93 -> -7.685089 | H101: =H100*H93 -> -23.480007 | I101: =I100*I93 -> -13.582188 | J101: =J100*J93 -> 1.7180527 | K101: =K100*K93 -> 5.9838187 | L101: =L100*L93 -> 7.6269369 | M101: =M100*M93 -> 5.3560072
A103: DCF 彙總
A104: 項目 | B104: 情境 A | C104: 情境 B | D104: 情境 C | E104: 說明
A105: 明確期現值合計（財報口徑） | B105: =SUM(F54:M54) -> -27.932471 | C105: =SUM(F74:M74) -> -75.74329 | D105: =SUM(F94:M94) -> -110.7765
A106: 終值（FY2032 年底，財報口徑） | B106: =IF(tv_alt=1,M50*(1+g_tv)/(wacc-g_tv),M46*(1+g_tv)*(1-g_tv/ronic)/(wacc-g_tv)) -> 432.19085 | C106: =IF(tv_alt=1,M70*(1+g_tv)/(wacc-g_tv),M66*(1+g_tv)*(1-g_tv/ronic)/(wacc-g_tv)) -> 241.886 | D106: =IF(tv_alt=1,M90*(1+g_tv)/(wacc-g_tv),M86*(1+g_tv)*(1-g_tv/ronic)/(wacc-g_tv)) -> 100.06886 | E106: 價值驅動：NOPAT(FY2033) ×(1 − g ÷ RONIC) ÷ (WACC − g)
A107: 終值現值 | B107: =B106/(1+wacc)^($M$52+mid) -> 220.54429 | C107: =C106/(1+wacc)^($M$72+mid) -> 123.43291 | D107: =D106/(1+wacc)^($M$92+mid) -> 51.064516
A108: 企業價值 EV（讀法 1：自用 AI 只計成本） | B108: =B105+B107 -> 192.61182 | C108: =C105+C107 -> 47.689624 | D108: =D105+D107 -> -59.711981
A109: ＋自用 AI 影子效益現值：明確期 | B109: =SUM(F55:M55) -> 51.111894 | C109: =SUM(F75:M75) -> 51.111894 | D109: =SUM(F95:M95) -> 51.111894
...

Sheet Recon
A1: Recon — 口徑對照：合併層對市場共識（Q3 後年度共識未找到，只有 2026-06-22 過期的 Simply Wall St）、逐分部對公司指引與營運數字、S2 核心問題比值的兩種讀法、每 GW 投資對照。只作對照，不作校準
A3: 1. 合併層：本模型 vs 過期共識（Simply Wall St，2026-06-22，IPO 後首週）
A4: 項目 | B4: 年度 | C4: 情境 A | D4: 情境 B | E4: 情境 C | F4: 過期共識 | G4: B ÷ 共識 − 1 | H4: 說明
A5: 營收 | B5: FY2026 | C5: =PL!G26 -> 43.617764 | D5: =PL!G88 -> 43.617764 | E5: =PL!G150 -> 43.617764 | F5: =c_revenue_26 -> 36.85 | G5: =D5/F5-1 -> 0.18365711 | H5: 過期：Q3 實績 14.575 遠高於當時預期（Q3 共識 12.59，Shacknews）；Q3 後年度共識未找到
A6: 營收 | B6: FY2027 | C6: =PL!H26 -> 88.799324 | D6: =PL!H88 -> 86.167868 | E6: =PL!H150 -> 84.082405 | F6: =c_revenue_27 -> 68.255 | G6: =D6/F6-1 -> 0.26244039
A7: 營收 | B7: FY2028 | C7: =PL!I26 -> 127.34472 | D7: =PL!I88 -> 119.0375 | E7: =PL!I150 -> 112.51873 | F7: =c_revenue_28 -> 97.508 | G7: =D7/F7-1 -> 0.22079724
A8: 淨利 | B8: FY2026 | C8: =PL!G66 -> 1.9009751 | D8: =PL!G128 -> 1.9009751 | E8: =PL!G190 -> 1.9009751 | F8: =c_earnings_26 -> -6.912 | G8: =D8/F8-1 -> -1.2750253
A9: 淨利 | B9: FY2027 | C9: =PL!H66 -> 15.936748 | D9: =PL!H128 -> 14.058656 | E9: =PL!H190 -> 12.608859 | F9: =c_earnings_27 -> 3.35 | G9: =D9/F9-1 -> 3.1966138
A10: 淨利 | B10: FY2028 | C10: =PL!I66 -> 25.439752 | D10: =PL!I128 -> 19.42408 | E10: =PL!I190 -> 14.827622 | F10: =c_earnings_28 -> 7.646 | G10: =D10/F10-1 -> 1.5404238
A11: 公司口徑 FCF | B11: FY2026 | C11: =CF!G29 -> -44.57854 | D11: =CF!G60 -> -44.57854 | E11: =CF!G91 -> -44.57854 | F11: =c_fcf_26 -> -28.749 | G11: =D11/F11-1 -> 0.55061185
A12: 公司口徑 FCF | B12: FY2027 | C12: =CF!H29 -> -28.199086 | D12: =CF!H60 -> -30.149534 | E12: =CF!H91 -> -31.597106 | F12: =c_fcf_27 -> -28.378 | G12: =D12/F12-1 -> 0.062426313
A13: 公司口徑 FCF | B13: FY2028 | C13: =CF!I29 -> -10.798984 | D13: =CF!I60 -> -17.099609 | E13: =CF!I91 -> -21.752008 | F13: =c_fcf_28 -> -14.581 | G13: =D13/F13-1 -> 0.17273224
A14: 市場共識目標價（MarketBeat，46 位） | C14: =cons_tp -> 244.97 | D14: =Val!B8 -> 27.515456 | E14: =D14/C14-1 -> -0.88767826 | H14: C＝共識、D＝本模型加權目標價、E＝差距；共識區間 75–800
A16: 2. 逐分部：本模型（情境 B）vs 公司指引與營運數字
A17: 分部／項目 | B17: FY2026E | C17: FY2027E | D17: FY2028E | E17: 共識 | F17: 公司指引或原文 | G17: 說明
A18: Space | B18: =PL!G79 -> 4.6352079 | C18: =PL!H79 -> 5.3011215 | D18: =PL!I79 -> 5.6755921 | E18: 未找到 | F18: 無指引 | G18: 分部共識需付費資料（未找到）
A19: Connectivity | B19: =PL!G82 -> 18.719169 | C19: =PL!H82 -> 28.840489 | D19: =PL!I82 -> 38.069616 | E19: 未找到 | F19: 無指引
A20: SI (Super Intelligence; formerly AI) | B20: =PL!G87 -> 20.263387 | C20: =PL!H87 -> 52.026258 | D20: =PL!I87 -> 75.292289 | E20: 未找到 | F20: 無指引
A21: SI 對外雲端服務（命題子列） | B21: =PL!G84 -> 12.924539 | C21: =PL!H84 -> 37.399537 | D21: =PL!I84 -> 55.739335 | E21: 未找到 | F21: 未單獨揭露；Customer B 2026Q3 5.028（衍生）
A22: Grok／Cursor／X 訂閱、資料授權與 API（命題子列） | B22: =PL!G85 -> 5.56064 | C22: =PL!H85 -> 12.91078 | D22: =PL!I85 -> 17.859913 | E22: 未找到 | F22: 未單獨揭露
A23: Advertising | B23: =PL!G83 -> 1.7782076 | C23: =PL!H83 -> 1.7159401 | D23: =PL!I83 -> 1.6930415 | E23: 未找到
A24: SI 名目算力 2026 年底（GW）：本模型 vs 公司 Q2 法說「逾 2 GW」（二手轉述） | B24: =Thesis!F25 -> 2.1067578 | F24: =gw_ye26_co -> 2 | G24: 審查第 3 條：Interested-party，只作對照
A25: Backlog 62.959（67% 一年內）vs 本模型 FY2027 營收（B） | B25: =backlog*0.67 -> 42.18253 | C25: =PL!H88 -> 86.167868 | G25: Backlog 未分分部；B 欄＝一年內可認列約數
A26: 2026Q2 新簽雲端合約 14.1（三年固定月費）年化 vs 本模型 FY2027 對外雲端服務（B） | B26: =cloud_q2/3 -> 4.7 | C26: =PL!H84 -> 37.399537 | G26: 合約年化只是新簽部分；Q3 另有新簽、未給金額
A27: 不可取消承諾 FY2027（含 SI 基礎設施、第三方雲、頻譜）vs 本模型 FY2027 SI 投資（B） | B27: =commit_27 -> 25.569 | C27: =Thesis!H43 -> 75.355599 | G27: 承諾未拆分；第三方雲容量不在名目算力內（S6）→ 可能低估 SI 算力成本
A29: 3. S2 核心問題比值的讀法（審查第 3、4 條；S6）
A30: 項目 | B30: 情境 A | C30: 情境 B | D30: 情境 C | E30: 說明
A31: FY2028 對外每 GW 年營收（IT 口徑 GW） | B31: =Seg!I7 -> 18.936414 | C31: =Seg!I45 -> 17.024535 | D31: =Seg!I83 -> 15.658907
A32: FY2028 在役機隊每 GW 年持有成本（Tokenomics IF_HoldEcon；IT 口徑） | B32: =Thesis!I33 -> 10.925025 | C32: =Thesis!I33 -> 10.925025 | D32: =Thesis!I33 -> 10.925025
A33: 比值（讀法 A：名目算力＝IT 負載，主值） | B33: =B31/B32 -> 1.7333063 | C33: =C31/C32 -> 1.5583063 | D33: =D31/D32 -> 1.4333063 | E33: 與 Tokenomics Interface 第 1 列 IT 關鍵電力同口徑，不乘 PUE（審查第 3 條）
A34: 比值（讀法 B：若名目算力實為設施功率，IT ＝ GW ÷ IF_FacilityGW 1.2） | B34: =B33*1.2 -> 2.0799675 | C34: =C33*1.2 -> 1.8699675 | D34: =D33*1.2 -> 1.7199675 | E34: 10-Q 定義明確排除冷卻與設施負載 → 讀法 B 不採，只列對照（S6）
A35: 2026Q3 校準 k0（Q3 年化 SI S&I ÷ 平均在役 GW ÷ 評價日機隊持有成本） | B35: =k0 -> 1.8666125 | E35: 含 Grok／Cursor／X 收入的 GW 平均；對外出租與 GW 同比例時與對外每 GW 相同
A37: 4. 每 GW 投資對照
A38: Tokenomics 每 GW 投資（GB300 錨 IT＋自建 × 機房） | B38: =cxgw26 -> 43.640224
A39: PP&E（伺服器與網通＋資料中心基礎設施）÷ 名目算力（2026-09-30） | B39: =ppe_gw -> 29.140588 | E39: 低於 Tokenomics：含 Hopper 舊機隊、機房部分租用；第三方雲與失敗售後租回資產另列
A40: 近四季 SI 投資（2025Q4–2026Q3；FY2025 二手 − 9M25＋9M26＋以融資取得）÷ 名目算力增量（0.6 → 1.7） | B40: =(Q!I37-Q!G37+Q!H37+ppefin_9m)/(gw_0-Q!C61) -> 44.150909 | E40: 含在建工程（尚未在役）→ 高於每 GW 投資屬合理

Sheet Sens
A1: Sens — 一次改一個輸入（In 頁敏感度低／高值），整本活頁簿以 LibreOffice 重算後的加權目標價（Val 頁「目標價（DCF 與 Comparable 加權）」）；由 spacex/make_v01.sh 產生，建置時寫入（數值）
A2: 相對基準＝情境目標價 ÷ 基準加權目標價 − 1；龍捲風依絕對值排序（HTML）。基準與各案例的其他輸入相同
A3: 驅動 | B3: 設定 | C3: 方向 | D3: 加權目標價 | E3: 相對基準 | F3: 鍵 | G3: 說明 | H3: 收支關卡 B（五年） | I3: FY2028 S2 比值（B）
A4: 自用 AI 讀法 1（只計成本）：低 | B4: 讀法 2 → 讀法 1 | C4: 低 | D4: 20.20877 | E4: =D4/Val!$B$8-1 -> -0.26554842 | F4: internal_ai_reading | G4: 重算值（make_v01.sh） | H4: -96.93727 | I4: 1.5583063
A5: 對外出租占比：低 | B5: 72% → 60%／85%（審查第 4 條區間） | C5: 低 | D5: 29.930036 | E5: =D5/Val!$B$8-1 -> 0.087753576 | F5: ext_sh | G5: 重算值（make_v01.sh） | H5: -108.78797 | I5: 1.5583063
A6: 對外出租占比：高 | B6: 72% → 60%／85%（審查第 4 條區間） | C6: 高 | D6: 24.621438 | E6: =D6/Val!$B$8-1 -> -0.10517791 | F6: ext_sh | G6: 重算值（make_v01.sh） | H6: -85.657769 | I6: 1.5583063
A7: SI 名目算力新增速度：低 | B7: 基準 × 2/3／× 1.5 | C7: 低 | D7: 25.265191 | E7: =D7/Val!$B$8-1 -> -0.081781872 | F7: pace | G7: 重算值（make_v01.sh） | H7: -43.292243 | I7: 1.5583063
A8: SI 名目算力新增速度：高 | B8: 基準 × 2/3／× 1.5 | C8: 高 | D8: 30.89074 | E8: =D8/Val!$B$8-1 -> 0.12266864 | F8: pace | G8: 重算值（make_v01.sh） | H8: -180.80967 | I8: 1.5583063
A9: 自建機房比例：低 | B9: 90% → 75%／100% | C9: 低 | D9: 28.737351 | E9: =D9/Val!$B$8-1 -> 0.044407563 | F9: selfb | G9: 重算值（make_v01.sh） | H9: -91.838883 | I9: 1.5583063
A10: 自建機房比例：高 | B10: 90% → 75%／100% | C10: 高 | D10: 26.7577 | E10: =D10/Val!$B$8-1 -> -0.027539296 | F10: selfb | G10: 重算值（make_v01.sh） | H10: -100.09992 | I10: 1.5583063
A11: 情境 B 的 FY2030 k：低 | B11: 1.25 → 1.0／1.5（只影響情境 B） | C11: 低 | D11: 23.392706 | E11: =D11/Val!$B$8-1 -> -0.14983398 | F11: k30_B | G11: 重算值（make_v01.sh） | H11: -124.66008 | I11: 1.4333063
A12: 情境 B 的 FY2030 k：高 | B12: 1.25 → 1.0／1.5（只影響情境 B） | C12: 高 | D12: 31.638207 | E12: =D12/Val!$B$8-1 -> 0.14983398 | F12: k30_B | G12: 重算值（make_v01.sh） | H12: -69.252714 | I12: 1.6833063
A13: SI 其他 EBITDA 率：低 | B13: 校準值 ±10pt | C13: 低 | D13: 25.808257 | E13: =D13/Val!$B$8-1 -> -0.062045114 | F13: m_so_adj | G13: 重算值（make_v01.sh） | H13: -105.34933 | I13: 1.5583063
A14: SI 其他 EBITDA 率：高 | B14: 校準值 ±10pt | C14: 高 | D14: 29.222656 | E14: =D14/Val!$B$8-1 -> 0.062045114 | F14: m_so_adj | G14: 重算值（make_v01.sh） | H14: -88.52521 | I14: 1.5583063
A15: SI 其他收入 FY2027 年增：低 | B15: 50% → 25%／80% | C15: 低 | D15: 27.153462 | E15: =D15/Val!$B$8-1 -> -0.013156027 | F15: g27_nr | G15: 重算值（make_v01.sh） | H15: -100.24125 | I15: 1.5583063
... A57: DCF 加回股權報酬：高 | B57: 不加回 → 加回（稅後） | C57: 高 | D57: 32.747966 | E57: =D57/Val!$B$8-1 -> 0.1901662 | F57: sbc_add | G57: 重算值（make_v01.sh） | H57: -96.93727 | I57: 1.5583063
A59: 基準加權目標價（Val 頁） | D59: =Val!B8 -> 27.515456 | H59: =CF!C6 -> -96.93727 | I59: =Seg!I73 -> 1.5583063
A60: 敏感度重算時的基準值（應與上一列相同；不同表示敏感度已過期） | D60: 27.515456 | E60: =D60-D59 -> 0

Sheet Sources
A1: Sources — 來源（編號、文件、日期、網址、標記）
A3: 編號 | B3: 文件 | C3: 日期 | D3: 網址 | E3: 標記 | F3: 用途
A4: S01 | B4: SpaceX 10-Q 2026Q3（Andy 2026-10-30 提供原檔：mag/extract/docs/2026Q3/spacex_2026Q3_10-Q.pdf） | C4: 2026-10-22 | D4: https://ir.spacex.com（SEC 網站本環境不可達） | E4: Verified | F4: 分部、收入拆分、合併損益、現金流、資產負債、債務、承諾、客戶集中、名目算力定義（事實總帳 data/spacex_facts_2026q3.json）
A5: S02 | B5: SpaceX 2026Q3 財報新聞稿（8-K 附件；mag/extract/docs/2026Q3/spacex_2026Q3_新聞稿.pdf） | C5: 2026-10-20 | D5: https://ir.spacex.com | E5: Interested-party | F5: 2026Q2 比較欄、KPI（發射、訂戶、ARPU、名目算力）
A6: S03 | B6: SpaceX 2026Q2 財報新聞稿（WebFetch；PDF 未入庫） | C6: 2026-07 | D6: https://ir.spacex.com | E6: Interested-party | F6: 2026Q1、2025Q2、1H、Backlog 6-30、Q2 新簽雲端合約 14.1
A7: S04 | B7: 媒體轉述 SpaceX S-1／424B4（Motley Fool、Yahoo Finance、Implicator、Beancount） | C7: 2026-05～07 | D7: 見事實總帳 seg.*.fy2025 的 url | E7: 二手轉述 S-1 | F7: FY2025 分部營收與營業利益（Space 資本支出未取得）
A8: S05 | B8: Tokenomics 快照 spacex/data/tokenomics_snapshot_v21.7.json（自 alphabet/data/ 複製；20261025_Tokenomics_v21.7.xlsx） | C8: 2026-10-29 | D8: repo 內（YinchenChang/Tokenomics） | E8: Derived | F8: IF_HoldEcon、IF_OpexGW、IF_CapexIT／Facility、IF_DeprIT、IF_FacilityGW
A9: S06 | B9: MarketBeat SPCX 預測頁 | C9: 2026-10-29 | D9: https://www.marketbeat.com/stocks/NASDAQ/SPCX/forecast/ | E9: Interested-party／Verified | F9: 現價 143.89（4:00 PM 收盤）、共識目標價 244.97（46 位）
A10: S07 | B10: Equibles SPCX 摘要 | C10: 2026-10-29 | D10: https://equibles.com/stocks/spcx/summary | E10: Verified | F10: 10-29 收盤 143.89（第二來源）
A11: S08 | B11: Digrin SPCX 月線 | C11: 2026-10-30 | D11: https://www.digrin.com/stocks/detail/SPCX/price | E11: Derived | F11: 9 月收盤 150.86（評價日股價，單一來源）
A12: S09 | B12: 美國財政部每日殖利率曲線（10 Yr） | C12: 2026-10-27 | D12: https://home.treasury.gov/resource-center/data-chart-center/interest-rates/TextView?type=daily_treasury_yield_curve&field_tdr_date_value_month=202610 | E12: Verified | F12: 無風險利率 4.99%
A13: S10 | B13: 同業檔 spacex/data/peers_si_20261030.json、peers_connectivity_20261030.json（MarketScreener） | C13: 2026-10-08／10-23 | D13: repo 內 | E13: Derived | F13: SOTP 倍數
A14: S11 | B14: 共識檔 spacex/data/consensus_spcx_20261030.json（MarketBeat、Simply Wall St 過期、Shacknews） | C14: 2026-10-30 | D14: repo 內 | E14: Interested-party | F14: 共識目標價、過期年度共識
A15: S12 | B15: A 段事實總帳報告 spacex/docs/reports/20261030_spacex_v0.1_A段_事實總帳.md | C15: 2026-10-30 | D15: repo 內 | E15: — | F15: 名目算力口徑、Valor、找不到的項目
