Workbook

Sheet README
A1: 鴻海精密（2317）個股模型 v0.3（AI 半導體 Project：伺服器組裝次產業，樣板＝廣達） 2026-10-28
A2: 版本：v0.2.1（2026-10-25：補上檔空間級距、投資建議、重點觀察（數值不變））。v0.2（2026-10-25：目標價改為 DCF 與 Comparable 加權、三情境延伸到 FY2032；FY2025–FY2029 數值不變）。前版：v0.3（2026-10-28：依個股模型原則補上官方四大產品類別——新增「雲端網路產品」＝AI 伺服器＋雲端網路非 AI 與四類合計核對列，數值不變）；v0.2.x（2026-10-25～27）；v0.1.1（2026-10-25：Val 新增第 0 節「目標價與上檔空間」、In 新增情境權重 tp_wA／tp_wB／tp_wC；其餘數值與 v0.1 相同）。v0.1（初版）：AI 伺服器組裝市場與 ODM 每櫃價格讀廣達模型（本專案權威，規則第 13 條），與廣達同口徑；本模型只決定鴻海份額、客供與其他事業。
A3: 模型命題：鴻海是集團公司，AI 伺服器營收＝部署 GW（AI IT 資本支出 ÷ 每 GW IT 資本支出）× 每 GW ODM 整櫃價值 × 鴻海有效份額 ×（1 − 客供比例），2026 年約占營收三成；其餘七成（iPhone、網通與一般伺服器、電腦、元件）以簡化成長率推。AI 伺服器拉高營收與營業利益，但業外損失、稅率上升與少數股權使淨利 ÷ 營業利益從 0.73 降到約 0.66。市場約 10 倍未來 12 月 EPS。
A4: 核心問題：AI 伺服器份額（NVIDIA 整櫃最大組裝廠）能不能在客供上升下撐住營業利益成長，以及淨利 ÷ 營業利益能不能穩在 0.66 左右；約 10 倍未來 12 月 P/E 隱含什麼路徑。
A6: 會計年度＝日曆年，FY(t)＝CY(t)，不平移。預測期 FY2027–FY2029（三年）。金額：十億新台幣；整櫃價格與市場以美元計、以匯率換算。口徑：歸屬母公司淨利。
A8: 驅動因子 → 推導量（全部唯讀上游，不修改）
A9: AI 伺服器營收：markets/network 的 AI IT 資本支出 × 情境顆數係數 ÷ 每 GW IT 資本支出（Tokenomics，經橋接表）＝部署 GW；× 每 GW 架數（Tokenomics）× ODM 每櫃價格（廣達模型）＝組裝市場；× 鴻海有效份額（FY2026 以公司雲端網路占比 × AI 占雲端網路校準，金額口徑）× 份額相對值（Assumed）×（1 − 客供比例，Assumed）。
A10: 非 AI：雲端網路非 AI、消費智能、電腦終端、元件及其他各自以 FY2026 錨點 × 成長率（Assumed）。毛利率：AI 伺服器（毛額基礎）比其他營收低 d_ai（Assumed），FY2027 起再加 VR 稀釋 vrd（Assumed），其他毛利率為 FY2026 殘差（Derived）；客供部分不計營收、保留 keep 比例的毛利。營業費用：彈性 phi（Derived）。淨利：營業利益 × 淨利係數。
A11: 校準：FY2026 ＝ 1H26 實績＋3Q26 營收實績＋假設（4Q 季增、毛利率、營業費用率、淨利 ÷ 營業利益）。不用券商數字（只在 Recon 對帳）。
A12: 估值：Val 第 0 節目標價＝0.5 × DCF 目標價（股東現金流＝EPS ×（1 − tp_g ÷ tp_roe），FY2027–FY2032 明確期＋永續，r 10%、g 4%，三情境權重 0.3／0.5／0.2，推到 12 個月後）＋0.5 × Comparable 目標價（廣達、緯創、和碩、Jabil、Flex 前瞻 P/E 中位數 × 12 個月後前瞻 EPS）；另列 Comparable 單獨目標價、市場共識目標價與差距拆解（EPS 因素、倍數因素）、DCF 價格帶、十年 P/E 分位檢查（只作檢查）。（v0.1.1 原估值說明，保留作參考：現價 ÷ FY2027、FY2028 EPS；十年 P/E 規則值（兩個資料商來源）× FY2027 EPS；循環位置以本模型營收最高年判定（不套設備股見頂年）。本版未做先驗，無 Andy 合理 P/E 對照。）
A13: 標記：Verified、Interested-party、Analogy、Assumed、Derived。SemiAnalysis 未使用。公司原文只經法說摘要與新聞；券商多為 3Q 營收公布前。
A15: 已知限制：(1) AI 伺服器營收金額與占雲端網路比例公司未揭露，FY2026 以「1Q26 超過五成」與 2H 機櫃放量假設 60%，是份額校準的最大不確定；(2) 雲端網路非 AI（網通、一般伺服器）未拆，以單一成長率推；(3) 客供比例與保留毛利比例是 Assumed，鴻海已有半成品模式（1Q26 雲端網路營收受影響），FY2026 已含在錨點；(4) 份額為金額口徑，與櫃數份額（三家 ODM 中約 35%、法人估 NVIDIA 機櫃約 44%）不同；(5) 業外、稅與少數股權以一個係數涵蓋，季別業外與稅前未找到；(6) 十年 P/E 2016–2023 為 iPhone 組裝期低倍數，規則值可能低估 AI 期倍數；(7) 3Q26 法說（11 月中）後更新錨點；R4 產業部署路徑未建。
... A18: 先驗：本版未做先驗，無 Andy 合理 P/E 對照。
A19: ="投資建議："&Val!B136&"（依上檔空間固定規則）" -> 投資建議：買進（依上檔空間固定規則）
A20: ="重點觀察 1：目標價 NT$"&TEXT(Val!$B$120,"#,##0")&"（DCF "&TEXT(Val!$B$105,"#,##0")&"、Comparable（相對倍數調整後）"&TEXT(tp_comp_adj,"#,##0")&"；DCF 權重 "&TEXT(tp_w_dcf,"0%")&"），比現價 "&TEXT(px,"#,##0")&"（2026-10-22）"&IF(Val!$B$123>=0,"高 "&TEXT(Val!$B$123,"0.0%"),"低 "&TEXT(-Val!$B$123,"0.0%"))&"，級距 "&Val!$B$135&"、投資建議 "&Val!$B$136&"。相對倍數調整係數 "&TEXT(rm_factor,"0.00")&"（本公司 10 年前瞻倍數中位數 ÷ 同業的中位數，夾在 0.5–2.0；Val 第 0.5 節），調整前加權上檔空間 "&TEXT((tp_w_dcf*Val!$B$105+(1-tp_w_dcf)*Val!$B$116)/px-1,"+0.0%;−0.0%")&"；Comparable 單獨（市場主流同業法、未調整）為 "&TEXT(Val!$B$124,"+0.0%;−0.0%")&"。"&"以下為 2026-10-29 相對倍數調整前撰寫的說明，其中數字為調整前：主因是 EPS 與倍數兩者：本模型 12 個月後前瞻 EPS 27.78 比共識前瞻 EPS 21.06 高 31.9%（兩者期間差約一年），同業（廣達、緯創、和碩、Jabil、Flex）前瞻 P/E 中位數 14.7 倍也高於現價隱含 11.6 倍；DCF 只高 18.5%，因 ROE 10.1% 接近折現率 10%（再投"&"資率 39.7%）。" -> 重點觀察 1：目標價 NT$339（DCF 290、Comparable（相對倍數調整後）388；DCF 權重 50%），比現價 245（2026-10-22）高 38.4%，級距 25%–50%、投資建議 買進。相對倍數調整係數 0.95（本公司 10 年前瞻倍數中位數 ÷ 同業的中位數，夾在 0.5–2.0；Val 第 0.5 節），調整前加權上檔空間 +42.8%；Comparable 單獨（市場主流同業法、未調整）為 +67.2%。以下為 2026-10-29 相對倍數調整前撰寫的說明，其中數字為調整前：主因是 EPS 與倍數兩者：本模型 12 個月後前瞻 EPS 27.78 比共識前瞻 EPS 21.06 高 31.9%（兩者期間差約一年），同業（廣達、緯創、和碩、Jabil、Flex）前瞻 P/E 中位數 14.7 倍也高於現價隱含 11.6 倍；DCF 只高 18.5%，因 ROE 10.1% 接近折現率 10%（再投資率 39.7%）。
A21: 重點觀察 2：FY2027 EPS 26.71 比法人 22.0–25.0 高 6.9%–21.4%；淨利 ÷ 營業利益是顆數以外最敏感的變數（0.60 時 FY2027 EPS −9.1%，回到 FY2025 的 0.73 時 +10.6%）。3Q26 財報與法說（約 11 月中）的業外與稅率是第一個檢驗點。
A22: 重點觀察 3：FY2028 EPS A／B／C＝31.42／27.71／23.60，法人 28.0 落在 A 與 B 之間；份額相對值 0.75（廣達、緯創搶單）時 FY2028 EPS −14.3%，份額 1.15（Vera Rubin 市占目標五成）時 +8.5%。追蹤 Vera Rubin 整櫃出貨份額。
A24: 2026-10-29：加權目標價中的 Comparable 改用相對倍數調整後的值（Val 第 0.5 節：同業前瞻倍數中位數 × 本公司 10 年相對同業的倍數比，Bloomberg 前瞻倍數；Andy 2026-10-27「照建議做」、10-29 資料取回）。「Comparable 目標價（市場主流同業法）」維持不調整。重點觀察 1 的第一句已改為公式；重點觀察 2、3 與其他說明中的目標價與上檔空間數字為調整前撰寫，以 Val 頁為準。

Sheet In
A1: In — 輸入（藍字；基準欄 E，低 D、高 F）。金額：十億新台幣（NT$B），整櫃價格與市場為美元；比例：%。每個輸入附兩個來源（找不到者寫「未找到」）；公司原文算一個
A2: 標記：Verified／Interested-party／Analogy／Assumed／Derived；Analogy、Assumed 給低／高區間。SemiAnalysis 未使用。公司原文＝鴻海法說（經富果、鉅亨、優分析摘要）、月營收公告；公司的產品占比與展望為 Interested-party；券商估計皆為 Interested-party。組裝市場與 ODM 每櫃價格讀廣達模型（唯讀），口徑一致
A3: 鍵 | B3: 項目 | C3: 單位 | D3: 低 | E3: 基準 | F3: 高 | G3: 標記 | H3: 來源1 | I3: 來源2／說明
A4: A. AI 部署規模（讀 markets/network、markets/chip_bridge、tsmc 成品；情境 A 基準，B／C 依顆數係數縮放）
A5: itc_26 | B5: AI IT 資本支出 2026 | C5: US$B | E5: 781.87292 | G5: Derived | H5: markets/network/dist/20261026_AI網通市場模型_v0.2.3.xlsx｜Mkt!C27:F27 | I5: 加速器顆數 × 每顆 IT capex（含 ASIC）；除以每 GW IT 資本支出得到部署 GW（與廣達、台達電模型同口徑）
A6: itc_27 | B6: AI IT 資本支出 2027 | C6: US$B | E6: 1565.35 | G6: Derived | H6: markets/network/dist/20261026_AI網通市場模型_v0.2.3.xlsx｜Mkt!C27:F27 | I6: 同上
A7: itc_28 | B7: AI IT 資本支出 2028 | C7: US$B | E7: 1984.2639 | G7: Derived | H7: markets/network/dist/20261026_AI網通市場模型_v0.2.3.xlsx｜Mkt!C27:F27 | I7: 同上
A8: itc_29 | B8: AI IT 資本支出 2029 | C8: US$B | E8: 2260.3903 | G8: Derived | H8: markets/network/dist/20261026_AI網通市場模型_v0.2.3.xlsx｜Mkt!C27:F27 | I8: 同上
A9: itpg_gb | B9: 每 GW IT 資本支出（GB300） | C9: US$B | E9: 32.237224 | G9: Derived | H9: markets/chip_bridge/dist/20261027_晶片內容橋接表_v0.2.2.xlsx｜In!E10（GB300）、H10（VR200） | I9: Tokenomics v20.1 IF_CapexIT（經橋接表；唯讀）
A10: itpg_vr | B10: 每 GW IT 資本支出（VR200；2027 起） | C10: US$B | E10: 37.586352 | G10: Derived | H10: markets/chip_bridge/dist/20261027_晶片內容橋接表_v0.2.2.xlsx｜In!E10（GB300）、H10（VR200） | I10: 同上；Rubin Ultra 與 ASIC 機架未另訂（Assumed：同 VR200）
A11: vr26 | B11: 2026 年部署中 Rubin 世代占比（混合用） | C11: % | D11: 0.15 | E11: 0.22 | F11: 0.3 | G11: Derived | H11: quanta/dist/20261028_廣達個股模型_v0.3.xlsx｜In!D11:F11 | I11: 廣達模型輸入（TrendForce 2026 組合 Rubin 22%）；鴻海：LPU 與 Vera 相關產品 4Q26 逐步放量（2Q26 法說）
A12: racks_gb | B12: 每 GW 機架數（GB300） | C12: 架 | E12: 6764 | G12: Derived | H12: markets/chip_bridge/dist/20261027_晶片內容橋接表_v0.2.2.xlsx｜In!E6（GB300）、H6（VR200） | I12: Tokenomics IF_RacksPerGW（經橋接表）
A13: racks_vr | B13: 每 GW 機架數（VR200） | C13: 架 | E13: 4052 | G13: Derived | H13: markets/chip_bridge/dist/20261027_晶片內容橋接表_v0.2.2.xlsx｜In!E6（GB300）、H6（VR200） | I13: 同上
A14: rack_gb | B14: 整櫃買方價格（GB300，Tokenomics） | C14: US$M/架 | E14: 4.3 | G14: Derived | H14: markets/chip_bridge/dist/20261027_晶片內容橋接表_v0.2.2.xlsx｜In!E5（GB300）、H5（VR200） | I14: 參考：ODM 價 ÷ 買方價
A15: rack_vr | B15: 整櫃買方價格（VR200，Tokenomics） | C15: US$M/架 | E15: 8.4 | G15: Derived | H15: markets/chip_bridge/dist/20261027_晶片內容橋接表_v0.2.2.xlsx｜In!E5（GB300）、H5（VR200） | I15: 同上
A16: um28_A | B16: 情境 A：2028 顆數 ÷ 基準 | C16: x | E16: 1 | G16: Assumed | H16: tsmc/dist/20261028_台積電個股模型_v0.4.xlsx｜In!E37 | I16: A＝基準；B＝AI 資本支出消化；C＝明顯下修（與台積電、NVIDIA、廣達模型相同）
A17: um29_A | B17: 情境 A：2029 顆數 ÷ 基準 | C17: x | E17: 1 | G17: Assumed | H17: tsmc/dist/20261028_台積電個股模型_v0.4.xlsx｜In!E38 | I17: 同上
A18: um28_B | B18: 情境 B：2028 顆數 ÷ 基準 | C18: x | E18: 0.8 | G18: Assumed | H18: tsmc/dist/20261028_台積電個股模型_v0.4.xlsx｜In!E39 | I18: A＝基準；B＝AI 資本支出消化；C＝明顯下修（與台積電、NVIDIA、廣達模型相同）
A19: um29_B | B19: 情境 B：2029 顆數 ÷ 基準 | C19: x | E19: 0.85 | G19: Assumed | H19: tsmc/dist/20261028_台積電個股模型_v0.4.xlsx｜In!E40 | I19: 同上
A20: um28_C | B20: 情境 C：2028 顆數 ÷ 基準 | C20: x | E20: 0.6 | G20: Assumed | H20: tsmc/dist/20261028_台積電個股模型_v0.4.xlsx｜In!E41 | I20: A＝基準；B＝AI 資本支出消化；C＝明顯下修（與台積電、NVIDIA、廣達模型相同）
A21: um29_C | B21: 情境 C：2029 顆數 ÷ 基準 | C21: x | E21: 0.6 | G21: Assumed | H21: tsmc/dist/20261028_台積電個股模型_v0.4.xlsx｜In!E42 | I21: 同上
A22: fx | B22: 匯率（新台幣 ÷ 美元） | C22: NT$/US$ | D22: 30.5 | E22: 32 | F22: 33 | G22: Derived | H22: quanta/dist/20261028_廣達個股模型_v0.3.xlsx｜In!D22:F22 | I22: 與廣達、台達電模型相同
A23: B. 組裝價格（讀廣達模型，唯讀）、鴻海份額與客供
A24: odm_gb | B24: ODM 每櫃價格 GB300（廣達模型） | C24: US$M/架 | D24: 3.6 | E24: 4 | F24: 4.3 | G24: Derived | H24: quanta/dist/20261028_廣達個股模型_v0.3.xlsx｜In!D24:F24 | I24: 廣達模型標記 Interested-party（工商時報、FTNN 引述法人）；本模型不另訂
A25: odm_vr | B25: ODM 每櫃價格 VR200（廣達模型） | C25: US$M/架 | D25: 6.5 | E25: 6.75 | F25: 7 | G25: Derived | H25: quanta/dist/20261028_廣達個股模型_v0.3.xlsx｜In!D25:F25 | I25: 同上
A26: vpg_28 | B26: 每 GW ODM 整櫃價值 2028 ÷ 2027（Rubin Ultra；廣達模型） | C26: x | D26: 0.85 | E26: 1 | F26: 1.2 | G26: Assumed | H26: quanta/dist/20261028_廣達個股模型_v0.3.xlsx｜In!D26:F26 | I26: 廣達模型的 Assumed：Rubin Ultra 每櫃價格與每 GW 架數未找到
A27: vpg_29 | B27: 每 GW ODM 整櫃價值 2029 ÷ 2027（廣達模型） | C27: x | D27: 0.85 | E27: 1 | F27: 1.2 | G27: Assumed | H27: quanta/dist/20261028_廣達個股模型_v0.3.xlsx｜In!D27:F27 | I27: 同上
A28: rel_27 | B28: 鴻海 AI 伺服器有效份額 2027 ÷ 2026（相對值） | C28: x | D28: 0.85 | E28: 1 | F28: 1.15 | G28: Assumed | H28: 公司：Vera Rubin 市占目標五成、ASIC 市佔目標四成以上（2Q26 法說，富果） | I28: https://money.udn.com/money/story/5739/9716181：法人預期鴻海 VR200 整體市占 40% 以上、部分客戶超過 50%（Interested-party）
A29: rel_28 | B29: 鴻海份額 2028 ÷ 2026 | C29: x | D29: 0.75 | E29: 1 | F29: 1.15 | G29: Assumed | H29: 同上；廣達、緯創同時擴產（廣達模型假設廣達份額 0.95） | I29: —
A30: rel_29 | B30: 鴻海份額 2029 ÷ 2026 | C30: x | D30: 0.7 | E30: 0.95 | F30: 1.15 | G30: Assumed | H30: 同上 | I30: —
A31: cs_27 | B31: 客供比例 2027（AI 毛額價值中改為客戶供料、不計營收的比例） | C31: % | D31: 0 | E31: 0.1 | F31: 0.25 | G31: Assumed | H31: https://blog.fugle.tw/post/earnings-call-2317-2026-08-12：客供目前主要用於 ASIC 專案，未來 GPU 與 ASIC 都可能採用、占比逐步提升（公司；未給比例） | I31: https://news.cnyes.com/news/id/6458468：1Q26 雲端網路因營收認列模式改變低於預期、不影響獲利（公司）；與廣達模型同值
A32: cs_28 | B32: 客供比例 2028 | C32: % | D32: 0 | E32: 0.2 | F32: 0.4 | G32: Assumed | H32: 同上 | I32: —
A33: cs_29 | B33: 客供比例 2029 | C33: % | D33: 0 | E33: 0.25 | F33: 0.5 | G33: Assumed | H33: 同上 | I33: —
A34: keep | B34: 客供部分保留的毛利比例（相對買賣模式） | C34: x | D34: 0.7 | E34: 0.9 | F34: 1 | G34: Assumed | H34: 公司：營收認列模式改變不影響獲利（1Q26 法說，鉅亨） | I34: 與廣達模型同值；量化：未找到
A35: C. 營收結構錨點（公司揭露產品占比 × 營收）
A36: cl_25 | B36: 2025 年雲端網路產品 ÷ 營收 | C36: % | E36: 0.4 | G36: Verified | H36: https://blog.fugle.tw/post/earnings-call-2317-2026-03-16：2025 雲端網路 40%、消費智能 38%、電腦終端 15%、元件及其他 7%（公司） | I36: https://uanalyze.com.tw/articles/4369349056：同
A37: ce_25 | B37: 2025 年消費智能產品 ÷ 營收 | C37: % | E37: 0.38 | G37: Verified | H37: 同上 | I37: —
A38: pc_25 | B38: 2025 年電腦終端產品 ÷ 營收 | C38: % | E38: 0.15 | G38: Verified | H38: 同上（元件及其他＝殘差 7%） | I38: —
A39: ais_25 | B39: 2025 年 AI 伺服器 ÷ 雲端網路產品 | C39: % | D39: 0.45 | E39: 0.5 | F39: 0.55 | G39: Interested-party | H39: https://uanalyze.com.tw/articles/5938328761：2Q25 AI 伺服器占雲端網路超過五成（公司） | I39: 2023 約 22%、2024 約三成（數位時代 2026-03-16）；前三季 AI 伺服器營收已破兆元（世界新聞網 2025-11-12）
A40: cl_26 | B40: 2026 年雲端網路產品 ÷ 營收 | C40: % | D40: 0.51 | E40: 0.53 | F40: 0.56 | G40: Interested-party | H40: https://blog.fugle.tw/post/earnings-call-2317-2026-08-12：1Q26 48%、2Q26 51%；3Q26 雲端網路季增、年增強勁成長（公司） | I40: https://www.kgi.com.hk/zh-cn/-/media/files/kgishk/research-reports/tw-reports/hon-hai-precision-2317-tt20260812en.pdf：2026F 55%（凱基）
A41: ais_26 | B41: 2026 年 AI 伺服器 ÷ 雲端網路產品 | C41: % | D41: 0.52 | E41: 0.6 | F41: 0.68 | G41: Interested-party | H41: https://finance.technews.tw/2026/05/15/ai-server-800g-switch-foxconn/：AI 伺服器已占 1Q26 雲端網路營收超過 50%（摩根士丹利引述） | I41: 3Q26 AI 機櫃營收季增 30% 以上（公司，經凱基）；全年 AI 機櫃出貨倍數以上成長（公司）
A42: ce_26 | B42: 2026 年消費智能產品 ÷ 營收 | C42: % | D42: 0.28 | E42: 0.3 | F42: 0.32 | G42: Interested-party | H42: https://blog.fugle.tw/post/earnings-call-2317-2026-08-12：1Q26 33%、2Q26 29%；3Q26 季增、年增顯著成長（公司） | I42: https://www.kgi.com.hk/zh-cn/-/media/files/kgishk/research-reports/tw-reports/hon-hai-precision-2317-tt20260812en.pdf：2026F 29.4%
A43: pc_26 | B43: 2026 年電腦終端產品 ÷ 營收 | C43: % | D43: 0.11 | E43: 0.12 | F43: 0.13 | G43: Interested-party | H43: https://blog.fugle.tw/post/earnings-call-2317-2026-08-12：1Q26 14%、2Q26 15%；3Q26 季減（公司） | I43: https://www.kgi.com.hk/zh-cn/-/media/files/kgishk/research-reports/tw-reports/hon-hai-precision-2317-tt20260812en.pdf：2026F 11.2%；元件及其他＝殘差
A44: g_cn27 | B44: 雲端網路非 AI（網通、一般伺服器）年增 2027 | C44: % | D44: 0 | E44: 0.12 | F44: 0.25 | G44: Assumed | H44: 公司：800G 以上交換機 2026 營收倍增；通用伺服器 2H26 雙位數以上成長（2Q26 法說） | I44: AI 以外的雲端網路拆分未揭露：未找到
A45: g_cn28 | B45: 雲端網路非 AI 年增 2028 | C45: % | D45: -0.05 | E45: 0.08 | F45: 0.2 | G45: Assumed | H45: 同上 | I45: —
A46: g_cn29 | B46: 雲端網路非 AI 年增 2029 | C46: % | D46: -0.05 | E46: 0.06 | F46: 0.15 | G46: Assumed | H46: 同上 | I46: —
A47: g_ce27 | B47: 消費智能（iPhone 等）年增 2027 | C47: % | D47: -0.08 | E47: 0.03 | F47: 0.08 | G47: Assumed | H47: 公司：2026 消費智能顯著成長（2025 年報法說） | I47: https://www.kgi.com.hk/zh-cn/-/media/files/kgishk/research-reports/tw-reports/hon-hai-precision-2317-tt20260812en.pdf：2027F 消費電子 +2%
A48: g_ce28 | B48: 消費智能年增 2028 | C48: % | D48: -0.08 | E48: 0.02 | F48: 0.06 | G48: Assumed | H48: 同上 | I48: —
A49: g_ce29 | B49: 消費智能年增 2029 | C49: % | D49: -0.08 | E49: 0.02 | F49: 0.06 | G49: Assumed | H49: 同上 | I49: —
A50: g_pc27 | B50: 電腦終端年增 2027 | C50: % | D50: -0.1 | E50: -0.02 | F50: 0.05 | G50: Assumed | H50: 公司：2026 略微衰退（記憶體漲價） | I50: https://www.kgi.com.hk/zh-cn/-/media/files/kgishk/research-reports/tw-reports/hon-hai-precision-2317-tt20260812en.pdf：2027F 電腦 −5%
... A55: g_co29 | B55: 元件及其他年增 2029 | C55: % | D55: -0.05 | E55: 0.05 | F55: 0.15 | G55: Assumed | H55: 同上 | I55: —
A56: D. 毛利率
A57: d_ai | B57: AI 伺服器毛利率（毛額基礎）減其他營收毛利率 | C57: pt | D57: -0.015 | E57: -0.005 | F57: 0.005 | G57: Assumed | H57: 公司毛利率 FY2025 6.15%（雲端占 40%）、1H26 6.15%（雲端約 50%）：AI 占比上升而毛利率大致持平，差距小 | I57: 部門別毛利率未揭露：未找到；4Q25 毛利率 5.88% 受半成品模式伺服器比重影響（公司）
A58: vrd | B58: VR 世代起 AI 毛利率（毛額基礎）變動（FY2027 起） | C58: pt | D58: -0.005 | E58: -0.002 | F58: 0 | G58: Assumed | H58: 凱基 2026-08-12：毛利率 2026F 5.9% → 2027F 5.7% | I58: 瑞銀 2026-07-22：2026、2027 皆 6.1%；廣達模型 −0.3 個百分點
A59: E. FY2026 錨點（1H26 實績＋3Q26 營收實績＋假設）
A60: q3_rev | B60: 3Q26 營收（月營收合計） | C60: NT$B | E60: 3026.9 | G60: Verified | H60: https://finance.technews.tw/2026/10/05/2026-sep-foxconn/：3Q26 3 兆 269 億元、季增 20.44%、年增 47.12%；前 9 月 7 兆 6,698 億元（公司月營收） | I60: https://uanalyze.com.tw/articles/4830556496：3Q26 3.02 兆、9 月 1.15 兆（7 月 9,465 億、8 月 9,217.66 億，TechNews 2026-09-05）
A61: q4g | B61: 4Q26 營收季增 | C61: % | D61: 0 | E61: 0.15 | F61: 0.25 | G61: Interested-party | H61: 公司：AI 持續成長加上 ICT 旺季，4Q 整體營運可望符合目前市場預期（10-05 月營收公告） | I61: https://www.kgi.com.hk/zh-cn/-/media/files/kgishk/research-reports/tw-reports/hon-hai-precision-2317-tt20260812en.pdf：4Q26F 3,536（以 3Q26F 2,829 為基礎，季增 25%）；4Q25 季增 27%（公司）
A62: q_gm | B62: 3Q、4Q26 毛利率 | C62: % | D62: 0.057 | E62: 0.06 | F62: 0.063 | G62: Interested-party | H62: 1Q26 6.18%、2Q26 6.12%（公司）；4Q25 5.88%（半成品模式影響） | I62: https://www.kgi.com.hk/zh-cn/-/media/files/kgishk/research-reports/tw-reports/hon-hai-precision-2317-tt20260812en.pdf：2026F 5.9%；瑞銀 2026F 6.1%
A63: q_opx | B63: 3Q、4Q26 營業費用 ÷ 營收 | C63: % | D63: 0.02 | E63: 0.0215 | F63: 0.024 | G63: Assumed | H63: 1Q26 約 2.61%、2Q26 約 2.36%（公司毛利 − 營業利益推得）；營收放大後費用率下降 | I63: 公司：2026 研發近 200 億元、年增 40%（2Q26 法說）
A64: q_nio | B64: 3Q、4Q26 淨利 ÷ 營業利益 | C64: % | D64: 0.6 | E64: 0.66 | F64: 0.72 | G64: Derived | H64: 1H26 109.89 ÷ 170.45＝0.645；FY2025 189.35 ÷ 259.22＝0.730（公司） | I64: 公司：2026 平均稅率 24–26%（2025 約 20%）；1Q26 業外損失 16.2 億（匯兌、利息）；凱基 2026F 0.658
A65: q_sh | B65: 股數（十億股；EPS 換算） | C65: 十億股 | E65: =(49.919+59.974)/7.84 -> 14.016964 | G65: Derived | H65: 1H26 淨利 499.19＋599.74 億 ÷ EPS 7.84（公司） | I65: FY2025 189.354 ÷ 13.61＝13.913；凱基流通股數 14,076 百萬股
A66: F. 營業費用、淨利係數、股數（FY2027 起）
A67: phi | B67: 營業費用成長對營收成長的彈性 | C67: x | D67: 0.2 | E67: 0.4 | F67: 0.7 | G67: Derived | H67: FY2026 錨點實測（Q 頁 B21） | I67: 營業費用率 FY2025 2.95% → 2Q26 2.36%；研發年增 40%，基準取高於實測
A68: opx_adj | B68: 營業費用額外占營收比（Sens 用；基準 0） | C68: pt | D68: -0.002 | E68: 0 | F68: 0.002 | G68: Assumed | H68: 無 | I68: 營益率約 3.8%，±0.2 個百分點約 ±5% 的營業利益
A69: nio_f | B69: 淨利 ÷ 營業利益 | C69: % | D69: 0.6 | E69: 0.66 | F69: 0.73 | G69: Derived | H69: 同 q_nio（1H26 0.645、FY2025 0.730） | I69: 凱基隱含 2026F 0.658、2027F 0.663（稅率 25%、少數股權 380–440 億）
A70: sh_g | B70: 股數年變動 | C70: % | D70: 0 | E70: 0 | F70: 0.01 | G70: Assumed | H70: FY2025 13.913 → 1H26 14.017（可轉債轉換） | I70: —
A71: mf | B71: AI 部署係數（Sens 用；FY2027 起） | C71: x | D71: 0.8 | E71: 1 | F71: 1.2 | G71: Assumed | H71: 網通模型 2027 年 AI IT 資本支出約 2 倍 | I71: ±20%
A72: G. 共識、市場資料（只作 Recon 對帳，不作校準）
A73: b_rev26 | B73: 券商 FY2026 營收（凱基 08-12，3Q 前） | C73: NT$B | E73: 11010.682 | G73: Interested-party | H73: https://www.kgi.com.hk/zh-cn/-/media/files/kgishk/research-reports/tw-reports/hon-hai-precision-2317-tt20260812en.pdf | I73: 3Q26 實績 3,026.9 高於凱基 3Q26F 2,829
A74: b_eps26 | B74: 券商 FY2026 EPS（凱基 08-12） | C74: NT$ | E74: 18.67 | G74: Interested-party | H74: https://www.kgi.com.hk/zh-cn/-/media/files/kgishk/research-reports/tw-reports/hon-hai-precision-2317-tt20260812en.pdf | I74: 瑞銀 07-22：18.0；摩根士丹利 05-15：16.38
A75: b_rev27 | B75: 券商 FY2027 營收（凱基 08-12） | C75: NT$B | E75: 14019.401 | G75: Interested-party | H75: https://www.kgi.com.hk/zh-cn/-/media/files/kgishk/research-reports/tw-reports/hon-hai-precision-2317-tt20260812en.pdf | I75: 瑞銀：2027 年增 28%
A76: b_eps27a | B76: 券商 FY2027 EPS（凱基 08-12） | C76: NT$ | E76: 22.64 | G76: Interested-party | H76: https://www.kgi.com.hk/zh-cn/-/media/files/kgishk/research-reports/tw-reports/hon-hai-precision-2317-tt20260812en.pdf | I76: —
A77: b_eps27b | B77: 券商 FY2027 EPS（瑞銀 07-22） | C77: NT$ | E77: 22 | G77: Interested-party | H77: https://money.udn.com/money/amp/story/5607/9644763 | I77: 目標價 320＝15x 2027 EPS
A78: b_eps27c | B78: 券商 FY2027 EPS（法人，08-18） | C78: NT$ | E78: 25 | G78: Interested-party | H78: https://www.businesstoday.com.tw/article/category/183008/post/202608170022/（今周刊；未具名法人：2026 19、2027 25、2028 28） | I78: —
A79: b_eps28 | B79: 券商 FY2028 EPS（法人，08-18） | C79: NT$ | E79: 28 | G79: Interested-party | H79: https://www.businesstoday.com.tw/article/category/183008/post/202608170022/ | I79: 摩根士丹利 05-15：23.03
A80: b_gm27 | B80: 券商 FY2027 毛利率（凱基） | C80: % | E80: 0.057 | G80: Interested-party | H80: https://www.kgi.com.hk/zh-cn/-/media/files/kgishk/research-reports/tw-reports/hon-hai-precision-2317-tt20260812en.pdf | I80: 營益率 3.4%
A81: rk_sh | B81: 三家 ODM 中鴻海的 NVL72 櫃數份額（8 月調查） | C81: % | E81: =2600/(2600+2525+2350) -> 0.34782609 | G81: Interested-party | H81: 經濟日報 2026-09-10 引述美系券商：鴻海約 2,600 櫃、廣達 2,500–2,550、緯創 2,300–2,400（網址見 Sources） | I81: 櫃數口徑；單月、三家合計（不含 Dell、Supermicro 等）
A82: rk_sh2 | B82: 鴻海占 NVIDIA AI 伺服器機櫃的全球份額（法人估） | C82: % | E82: 0.44 | G82: Interested-party | H82: https://www.inside.com.tw/article/42074-foxconn-q2-2026-ai-server-revenue-passes-half：法人估約 44%（公司說 40% 以上） | I82: 櫃數口徑（推測；原文未寫明櫃數或金額）
A83: H. 價格與估值
A84: px | B84: 股價（2026-10-22 收盤） | C84: NT$ | E84: 245 | G84: Interested-party | H84: 聚財網 2317 日成交（10-22 收盤 245、10-21 250） | I84: Yahoo 股市：10-16 收盤 244
A85: pe_ttm | B85: 近 12 月 P/E（Yahoo，10-16） | C85: x | E85: 16.08 | G85: Interested-party | H85: Yahoo 股市 2317（10-16） | I85: Goodinfo 目前 P/E 16.14；companiesmarketcap TTM 15.3
A86: I. 目標價情境權重（Val 第 0 節用；Andy 可改）
A87: tp_wA | B87: 目標價情境權重：情境 A（順利） | C87: 權重 | E87: 0.3 | G87: Assumed | H87: Andy 可改（2026-10-25 目標價規格預設 A／B／C＝0.3／0.5／0.2） | I87: 三個權重合計應為 1；v0.2 起用於 DCF 與 Comparable 的情境加權（Val 第 0 節）
A88: tp_wB | B88: 目標價情境權重：情境 B（平平） | C88: 權重 | E88: 0.5 | G88: Assumed | H88: Andy 可改（2026-10-25 目標價規格預設 A／B／C＝0.3／0.5／0.2） | I88: 三個權重合計應為 1；v0.2 起用於 DCF 與 Comparable 的情境加權（Val 第 0 節）
A89: tp_wC | B89: 目標價情境權重：情境 C（不如預期） | C89: 權重 | E89: 0.2 | G89: Assumed | H89: Andy 可改（2026-10-25 目標價規格預設 A／B／C＝0.3／0.5／0.2） | I89: 三個權重合計應為 1；v0.2 起用於 DCF 與 Comparable 的情境加權（Val 第 0 節）
A90: J. 目標價（DCF 與 Comparable 加權）與收斂法參數（v0.2 新增；黃底＝Assumed，Andy 可改）
A91: tp_r | B91: 折現率／要求報酬（DCF） | C91: % | E91: 0.1 | G91: Assumed | H91: Andy 可改（工作單 2026-10-25 預設 10%；美、台、日、韓同一值） | I91: Sens 頁 ±1pt
A92: tp_g | B92: 長期成長率（DCF 永續；情境 B 的 FY2032 營收年增收斂目標） | C92: % | E92: 0.04 | G92: Assumed | H92: Andy 可改（工作單預設 4%） | I92: Sens 頁 ±1pt（只動 DCF，PL 收斂目標不隨之變動）
A93: tp_roe | B93: ROE（近三年平均） | C93: % | E93: =AVERAGE(0.0928,0.0971,0.1125) -> 0.1008 | G93: Derived | H93: stockanalysis 比率頁（Return on Equity）：FY2023 9.28%、FY2024 9.71%、FY2025 11.25% | I93: 單一來源；近 12 月 13.15%（同站，2026-09-18）
A94: tp_w_dcf | B94: 目標價中 DCF 的權重；其餘為 Comparable | C94: % | E94: 0.5 | G94: Assumed | H94: Andy 可改（2026-10-25 11:53 改為 0.5：DCF／Comparable 各半） | I94: Sens 頁 0.4／0.8
A95: fade_gA | B95: 情境 A（順利）：FY2032 營收年增收斂目標（tp_g＋2pt） | C95: % | E95: =tp_g+0.02 -> 0.06 | G95: Assumed | H95: 工作單 2026-10-25 11:20 收斂法 | I95: FY2030 起由 FY2029 年增線性收斂，FY2032 達到
A96: fade_gB | B96: 情境 B（平平）：FY2032 營收年增收斂目標（＝tp_g） | C96: % | E96: =tp_g -> 0.04 | G96: Assumed | H96: 同上 | I96: —
A97: fade_gC | B97: 情境 C（不如預期）：FY2032 營收年增收斂目標（tp_g−2pt） | C97: % | E97: =tp_g-0.02 -> 0.02 | G97: Assumed | H97: 同上 | I97: —
A98: nim10_f | B98: 十年平均淨利率的替代：最後一年（FY2029）淨利率 ×（本值） | C98: x | E98: 0.8 | G98: Assumed | H98: 十年（2016–2025）平均淨利率：未找到（免費資料商只到近五年）；依工作單以最後一年 × 0.8 替代 | I98: 淨利率收斂目標：A＝FY2029、B＝FY2029 與替代值的中點、C＝替代值（PL 延伸表）
A99: cons_tp | B99: 市場共識目標價（賣方平均） | C99: NT$ | E99: 347.45 | G99: Interested-party | H99: stockanalysis forecast 頁（S&P Global）21 位分析師平均 347.45（中位數 338.50），頁面時間 2026-10-12 | I99: 第二來源：未找到
A100: cons_feps | B100: 共識前瞻 12 月 EPS（＝價格 ÷ 前瞻 P/E） | C100: NT$ | E100: =239.5/11.37 -> 21.064204 | G100: Interested-party | H100: stockanalysis 個股頁 2026-10-19：價格 239.5 ÷ Forward PE 11.37 | I100: 賣方共識，只作對帳與差距拆解，不作校準

Sheet Q
A1: Q — 實績與 FY2026 錨點（十億新台幣；EPS 為新台幣；股數為十億股）。藍字＝輸入；黑字＝公式。實績取自鴻海法說摘要、凱基報告（實績欄）與月營收
A2: FY2026 錨點＝1H26 實績＋3Q26 營收實績（月營收）＋3Q、4Q 假設（毛利率、營業費用率、淨利 ÷ 營業利益；4Q 營收＝3Q × (1＋季增)）。1H26 營收＝前 9 月 − 3Q；1Q26 毛利由公司毛利率 6.18% × 營收推得。業外與稅前：只有 1Q26 業外（損失 16.2 億）與凱基 FY2025 稅前 2,934 億，季別未找到
A3: 項目 | B3: FY2025A | C3: 1H26（實績） | D3: 3Q26（營收實績） | E3: 4Q26（模型） | F3: FY2026 錨點 | G3: 標記 | H3: 來源1（公司） | I3: 來源2／說明
A4: 營收 | B4: 8103.105 | C4: =7669.8-q3_rev -> 4642.9 | D4: =q3_rev -> 3026.9 | E4: =D4*(1+q4g) -> 3480.935 | F4: =SUM(C4:E4) -> 11150.735 | G4: Verified／Interested-party（4Q 季增） | H4: FY2025：https://uanalyze.com.tw/articles/4369349056；1H26：https://blog.fugle.tw/post/earnings-call-2317-2026-08-12、https://news.cnyes.com/news/id/6458468 | I4: FY2025 8,103.105（凱基實績欄；公司 8.1 兆）；1H26＝前 9 月 7,669.8 − 3Q（2Q26 2,525.894，凱基）
A5: 毛利 | B5: 498.161 | C5: =(C4-2525.894)*0.0618+154.533 -> 285.36397 | D5: =D4*q_gm -> 181.614 | E5: =E4*q_gm -> 208.8561 | F5: =SUM(C5:E5) -> 675.83407 | G5: Verified／Derived（1Q26 毛利率 × 營收） | H5: FY2025：https://uanalyze.com.tw/articles/4369349056；1H26：https://blog.fugle.tw/post/earnings-call-2317-2026-08-12、https://news.cnyes.com/news/id/6458468 | I5: FY2025 毛利率 6.15%；1Q26 6.18%；2Q26 毛利 1,545.33 億（公司）
A6: 毛利率 | B6: =B5/B4 -> 0.061477792 | C6: =C5/C4 -> 0.061462442 | D6: =D5/D4 -> 0.06 | E6: =E5/E4 -> 0.06 | F6: =F5/F4 -> 0.060608926 | G6: Derived | H6: — | I6: —
A7: 營業費用 | B7: =B5-B8 -> 238.938 | C7: =C5-C8 -> 114.91197 | D7: =D4*q_opx -> 65.07835 | E7: =E4*q_opx -> 74.840103 | F7: =SUM(C7:E7) -> 254.83042 | G7: Derived（毛利 − 營業利益）／Assumed | H7: FY2025：https://uanalyze.com.tw/articles/4369349056；1H26：https://blog.fugle.tw/post/earnings-call-2317-2026-08-12、https://news.cnyes.com/news/id/6458468 | I7: 3Q26 營收：月營收公告（TechNews 2026-10-05）
A8: 營業利益 | B8: 259.223 | C8: =75.649+94.803 -> 170.452 | D8: =D5-D7 -> 116.53565 | E8: =E5-E7 -> 134.016 | F8: =SUM(C8:E8) -> 421.00365 | G8: Verified／Derived | H8: FY2025：https://uanalyze.com.tw/articles/4369349056；1H26：https://blog.fugle.tw/post/earnings-call-2317-2026-08-12、https://news.cnyes.com/news/id/6458468 | I8: FY2025 2,592.23 億、營益率 3.20%；1Q26 756.49 億、2Q26 948.03 億（公司）
A9: 營業利益率 | B9: =B8/B4 -> 0.031990576 | C9: =C8/C4 -> 0.0367124 | D9: =D8/D4 -> 0.0385 | E9: =E8/E4 -> 0.0385 | F9: =F8/F4 -> 0.037755686 | G9: Derived | H9: — | I9: —
A10: 歸屬母公司淨利 | B10: 189.354 | C10: =49.919+59.974 -> 109.893 | D10: =D8*q_nio -> 76.913529 | E10: =E8*q_nio -> 88.450558 | F10: =SUM(C10:E10) -> 275.25709 | G10: Verified／Derived（3Q、4Q） | H10: FY2025：https://uanalyze.com.tw/articles/4369349056；1H26：https://blog.fugle.tw/post/earnings-call-2317-2026-08-12、https://news.cnyes.com/news/id/6458468 | I10: FY2025 1,893.54 億；1Q26 499.19 億、2Q26 599.74 億（公司稅後淨利；凱基列為母公司淨利，少數股權另列）
A11: 淨利 ÷ 營業利益（含業外、稅、非控制權益） | B11: =B10/B8 -> 0.73046759 | C11: =C10/C8 -> 0.64471523 | D11: =D10/D8 -> 0.66 | E11: =E10/E8 -> 0.66 | F11: =F10/F8 -> 0.65381165 | G11: Derived | H11: — | I11: —
A12: 股數（十億股） | B12: =189.354/13.61 -> 13.912858 | C12: =q_sh -> 14.016964 | D12: =q_sh -> 14.016964 | E12: =q_sh -> 14.016964 | F12: =q_sh -> 14.016964 | G12: Derived | H12: FY2025：https://uanalyze.com.tw/articles/4369349056；1H26：https://blog.fugle.tw/post/earnings-call-2317-2026-08-12、https://news.cnyes.com/news/id/6458468 | I12: 淨利 ÷ EPS
A13: EPS | B13: =B10/B12 -> 13.61 | C13: =C10/C12 -> 7.84 | D13: =D10/D12 -> 5.4871745 | E13: =E10/E12 -> 6.3102507 | F13: =F10/F12 -> 19.637425 | G13: Derived | H13: 淨利 ÷ 股數 | I13: —
A14: 公司揭露 EPS | B14: 13.61 | C14: 7.84 | G14: Verified | H14: FY2025：https://uanalyze.com.tw/articles/4369349056；1H26：https://blog.fugle.tw/post/earnings-call-2317-2026-08-12、https://news.cnyes.com/news/id/6458468 | I14: 1Q26 3.56、2Q26 4.27
A15: AI 伺服器營收（＝營收 × 雲端網路占比 × AI 占雲端網路） | B15: =B4*cl_25*ais_25 -> 1620.621 | F15: =F4*cl_26*ais_26 -> 3545.9337 | G15: Derived／Interested-party | H15: 公司產品占比（In 頁 C 節） | I15: 各季與年度 AI 伺服器營收金額未揭露：未找到
A16: 雲端網路非 AI（網通、一般伺服器） | B16: =B4*cl_25-B15 -> 1620.621 | F16: =F4*cl_26-F15 -> 2363.9558 | G16: Derived | H16: — | I16: —
A17: 消費智能（iPhone 等） | B17: =B4*ce_25 -> 3079.1799 | F17: =F4*ce_26 -> 3345.2205 | G17: Derived／Interested-party | H17: — | I17: —
A18: 電腦終端 | B18: =B4*pc_25 -> 1215.4658 | F18: =F4*pc_26 -> 1338.0882 | G18: Derived／Interested-party | H18: — | I18: —
A19: 元件及其他（殘差） | B19: =B4-B15-B16-B17-B18 -> 567.21735 | F19: =F4-F15-F16-F17-F18 -> 557.53675 | G19: Derived | H19: — | I19: FY2025 公司揭露 7%
A20: 非 AI 營收合計 | B20: =B4-B15 -> 6482.484 | F20: =F4-F15 -> 7604.8013 | G20: Derived | H20: — | I20: —
A22: FY2026 錨點的檢查（參考；校準未使用券商數字）
A23: FY2026 營收年增 | B23: =F4/B4-1 -> 0.37610644
A24: FY2026 營業費用年增 | B24: =F7/B7-1 -> 0.066512749
A25: 營業費用彈性（營業費用年增 ÷ 營收年增；In 頁 phi 的依據） | B25: =B24/B23 -> 0.17684555
A26: FY2026 營收 ÷ 凱基（08-12，3Q 前）− 1 | B26: =F4/b_rev26-1 -> 0.012719739
A27: FY2026 EPS ÷ 凱基 − 1 | B27: =F13/b_eps26-1 -> 0.051817096
A28: AI 伺服器營收 FY2026 年增（隱含；公司說 AI 機櫃出貨倍數以上成長） | B28: =F15/B15-1 -> 1.1880092

Sheet Units
A1: Units — AI 伺服器組裝市場（與廣達模型同口徑）、鴻海份額、客供比例。部署 GW＝AI IT 資本支出（markets/network）÷ 每 GW IT 資本支出（Tokenomics，經橋接表）；ODM 每櫃價格讀廣達模型
A3: 項目 | B3: 單位 | C3: CY2026 | D3: CY2027 | E3: CY2028 | F3: CY2029 | G3: 說明
A4: 部署 GW（情境 A） | B4: GW | C4: =PL!D80 -> 23.399538 | D4: =PL!E80 -> 41.646766 | E4: =PL!F80 -> 52.792138 | F4: =PL!G80 -> 60.138592 | G4: AI IT 資本支出 ÷ 每 GW IT 資本支出
A5: 每 GW ODM 整櫃價值 | B5: US$B/GW | C5: =PL!D81 -> 27.1209 | D5: =PL!E81 -> 27.351 | E5: =PL!F81 -> 27.351 | F5: =PL!G81 -> 27.351 | G5: 架數 × ODM 每櫃價格（讀廣達模型）
A6: AI 伺服器組裝市場（ODM 價） | B6: US$B | C6: =PL!D82 -> 634.61653 | D6: =PL!E82 -> 1139.0807 | E6: =PL!F82 -> 1443.9178 | F6: =PL!G82 -> 1644.8506 | G6: 含 ASIC 機架（假設每 GW 價值相同）
A7: 鴻海有效份額（金額口徑） | B7: % | C7: =PL!D86 -> 0.17461006 | D7: =PL!E86 -> 0.17461006 | E7: =PL!F86 -> 0.17461006 | F7: =PL!G86 -> 0.16587955 | G7: FY2026 以公司雲端網路占比與 AI 占比校準
A8: 鴻海 AI 伺服器毛額價值 | B8: US$B | C8: =PL!D87/fx -> 110.81043 | D8: =PL!E87/fx -> 198.89495 | E8: =PL!F87/fx -> 252.12257 | F8: =PL!G87/fx -> 272.84709 | G8: 買賣模式下的營收
A9: 客供比例（FY2027 起新增） | B9: % | C9: =PL!D88 -> 0 | D9: =PL!E88 -> 0.1 | E9: =PL!F88 -> 0.2 | F9: =PL!G88 -> 0.25 | G9: Assumed
A10: 鴻海 AI 伺服器營收 | B10: US$B | C10: =PL!D89/fx -> 110.81043 | D10: =PL!E89/fx -> 179.00545 | E10: =PL!F89/fx -> 201.69805 | F10: =PL!G89/fx -> 204.63532
A11: 隱含鴻海出貨櫃數（NVL72 等值） | B11: 千櫃 | C11: =PL!D103 -> 24.063068 | D11: =PL!E103 -> 29.465918 | E11: =PL!F103 -> 37.351491 | F11: =PL!G103 -> 40.421791 | G11: 毛額價值 ÷ ODM 每櫃價格
A12: 每 GW 鴻海 AI 伺服器營收 | B12: US$B/GW | C12: =PL!D102 -> 4.7355819 | D12: =PL!E102 -> 4.2981837 | E12: =PL!F102 -> 3.8206077 | F12: =PL!G102 -> 3.4027288
A13: 鴻海 AI 伺服器毛利率（營收基礎） | B13: % | C13: =PL!D109 -> 0.057198926 | D13: =PL!E109 -> 0.060718818 | E13: =PL!F109 -> 0.067618684 | F13: =PL!G109 -> 0.071758604 | G13: 客供上升 → 毛利率上升、毛利金額大致不變
A14: 廣達有效份額（廣達模型 Units，唯讀） | B14: % | C14: 0.13389612 | D14: 0.13389612 | E14: 0.12720132 | F14: 0.12050651 | G14: 來源：quanta/dist/20261028_廣達個股模型_v0.3.xlsx｜Units!C7:F7
A15: 鴻海＋廣達合計有效份額 | B15: % | C15: =C7+C14 -> 0.30850618 | D15: =D7+D14 -> 0.30850618 | E15: =E7+E14 -> 0.30181138 | F15: =F7+F14 -> 0.28638607 | G15: 其餘為緯創、英業達、Dell、Supermicro、ASIC 自有組裝等
A16: 其他廠商（緯創、英業達、Dell、Supermicro 等）＝ 市場 ×（1 − 合計份額） | B16: US$B | C16: =C6*(1-C15) -> 438.83341 | D16: =D6*(1-D15) -> 787.66726 | E16: =E6*(1-E15) -> 1008.127 | F16: =F6*(1-F15) -> 1173.7883
A18: 讀法：鴻海有效份額（金額口徑，分母為全部 AI IT 資本支出換算的組裝市場，含 ASIC、HGX 與其他組裝廠）低於櫃數份額（三家 ODM 中約 35%、法人估 NVIDIA 機櫃約 44%），口徑不同。鴻海＋廣達合計約三成；份額相對值與客供比例是 Assumed，是最需要每季檢查的輸入。

Sheet PL
A1: PL — 鴻海損益（十億新台幣；EPS 新台幣；歸屬母公司）。FY2025A 實績、FY2026 錨點（1H26 實績＋3Q26 營收實績＋假設），FY2027 起為模型。FY(t)＝CY(t)。三情境各一個完整推導區塊（本頁下方），頂端為摘要。FY2026–FY2027 三情境相同（顆數係數從 CY2028 開始）
A3: 情境／項目 | B3: 單位 | C3: FY2025A | D3: FY2026（錨點） | E3: FY2027 | F3: FY2028 | G3: FY2029 | H3: 說明
A4: 情境 A
A5: 營收 | B5: NT$B | C5: =C96 -> 8103.105 | D5: =D96 -> 11150.735 | E5: =E96 -> 13734.848 | F5: =F96 -> 14777.862 | G5: =G96 -> 15145.624
A6: 營收年增 | B6: % | D6: =D99 -> 0.37610644 | E6: =E99 -> 0.23174375 | F6: =F99 -> 0.075939217 | G6: =G99 -> 0.024886015
A7: AI 伺服器營收 | B7: NT$B | C7: =C89 -> 1620.621 | D7: =D89 -> 3545.9337 | E7: =E89 -> 5728.1744 | F7: =F89 -> 6454.3377 | G7: =G89 -> 6548.3301
A8: 雲端網路產品 | B8: NT$B | C8: =C97 -> 3241.242 | D8: =D97 -> 5909.8895 | E8: =E97 -> 8375.8049 | F8: =F97 -> 9313.7786 | G8: =G97 -> 9579.3375
A9: 消費智能產品 | B9: NT$B | C9: =C92 -> 3079.1799 | D9: =D92 -> 3345.2205 | E9: =E92 -> 3445.5771 | F9: =F92 -> 3514.4887 | G9: =G92 -> 3584.7784
A10: 電腦終端產品 | B10: NT$B | C10: =C93 -> 1215.4658 | D10: =D93 -> 1338.0882 | E10: =E93 -> 1311.3264 | F10: =F93 -> 1311.3264 | G10: =G93 -> 1311.3264
A11: 元件及其他 | B11: NT$B | C11: =C94 -> 567.21735 | D11: =D94 -> 557.53675 | E11: =E94 -> 602.13969 | F11: =F94 -> 638.26807 | G11: =G94 -> 670.18147
A12: 非 AI 營收 | B12: NT$B | C12: =C95 -> 6482.484 | D12: =D95 -> 7604.8013 | E12: =E95 -> 8006.6738 | F12: =F95 -> 8323.5241 | G12: =G95 -> 8597.2938
A13: AI 伺服器 ÷ 營收 | B13: % | C13: =C100 -> 0.2 | D13: =D100 -> 0.318 | E13: =E100 -> 0.41705408 | F13: =F100 -> 0.43675721 | G13: =G100 -> 0.4323579
A14: 毛利 | B14: NT$B | C14: =C107 -> 498.161 | D14: =D107 -> 675.83407 | E14: =E107 -> 845.81449 | F14: =F107 -> 954.14808 | G14: =G107 -> 1004.6415
A15: 毛利率 | B15: % | C15: =C108 -> 0.061477792 | D15: =D108 -> 0.060608926 | E15: =E108 -> 0.061581641 | F15: =F108 -> 0.064566044 | G15: =G108 -> 0.066332128
A16: 營業利益率 | B16: % | C16: =C113 -> 0.031990576 | D16: =D113 -> 0.037755686 | E16: =E113 -> 0.041308205 | F16: =F113 -> 0.045151141 | G16: =G113 -> 0.047200082
A17: 歸屬母公司淨利 | B17: NT$B | C17: =C115 -> 189.354 | D17: =D115 -> 275.25709 | E17: =E115 -> 374.45887 | F17: =F115 -> 440.37663 | G17: =G115 -> 471.81729
A18: EPS | B18: NT$ | C18: =C117 -> 13.61 | D18: =D117 -> 19.637425 | E18: =E117 -> 26.714691 | F18: =F117 -> 31.417404 | G18: =G117 -> 33.660447
A19: EPS 年增 | B19: % | D19: =D118 -> 0.44286739 | E19: =E118 -> 0.36039683 | F19: =F118 -> 0.17603473 | G19: =G118 -> 0.071394922
A21: 情境 B
A22: 營收 | B22: NT$B | C22: =C142 -> 8103.105 | D22: =D142 -> 11150.735 | E22: =E142 -> 13734.848 | F22: =F142 -> 13486.994 | G22: =G142 -> 14163.374
A23: 營收年增 | B23: % | D23: =D145 -> 0.37610644 | E23: =E145 -> 0.23174375 | F23: =F145 -> -0.018045625 | G23: =G145 -> 0.050150545
A24: AI 伺服器營收 | B24: NT$B | C24: =C135 -> 1620.621 | D24: =D135 -> 3545.9337 | E24: =E135 -> 5728.1744 | F24: =F135 -> 5163.4701 | G24: =G135 -> 5566.0806
A25: 雲端網路產品 | B25: NT$B | C25: =C143 -> 3241.242 | D25: =D143 -> 5909.8895 | E25: =E143 -> 8375.8049 | F25: =F143 -> 8022.9111 | G25: =G143 -> 8597.088
A26: 消費智能產品 | B26: NT$B | C26: =C138 -> 3079.1799 | D26: =D138 -> 3345.2205 | E26: =E138 -> 3445.5771 | F26: =F138 -> 3514.4887 | G26: =G138 -> 3584.7784
A27: 電腦終端產品 | B27: NT$B | C27: =C139 -> 1215.4658 | D27: =D139 -> 1338.0882 | E27: =E139 -> 1311.3264 | F27: =F139 -> 1311.3264 | G27: =G139 -> 1311.3264
A28: 元件及其他 | B28: NT$B | C28: =C140 -> 567.21735 | D28: =D140 -> 557.53675 | E28: =E140 -> 602.13969 | F28: =F140 -> 638.26807 | G28: =G140 -> 670.18147
A29: 非 AI 營收 | B29: NT$B | C29: =C141 -> 6482.484 | D29: =D141 -> 7604.8013 | E29: =E141 -> 8006.6738 | F29: =F141 -> 8323.5241 | G29: =G141 -> 8597.2938
A30: AI 伺服器 ÷ 營收 | B30: % | C30: =C146 -> 0.2 | D30: =D146 -> 0.318 | E30: =E146 -> 0.41705408 | F30: =F146 -> 0.3828481 | G30: =G146 -> 0.39299114
A31: 毛利 | B31: NT$B | C31: =C153 -> 498.161 | D31: =D153 -> 675.83407 | E31: =E153 -> 845.81449 | F31: =F153 -> 866.86132 | G31: =G153 -> 934.15661
A32: 毛利率 | B32: % | C32: =C154 -> 0.061477792 | D32: =D154 -> 0.060608926 | E32: =E154 -> 0.061581641 | F32: =F154 -> 0.06427387 | G32: =G154 -> 0.065955794
A33: 營業利益率 | B33: % | C33: =C159 -> 0.031990576 | D33: =D159 -> 0.037755686 | E33: =E159 -> 0.041308205 | F33: =F159 -> 0.043627864 | G33: =G159 -> 0.045901365
A34: 歸屬母公司淨利 | B34: NT$B | C34: =C161 -> 189.354 | D34: =D161 -> 275.25709 | E34: =E161 -> 374.45887 | F34: =F161 -> 388.34977 | G34: =G161 -> 429.07803
A35: EPS | B35: NT$ | C35: =C163 -> 13.61 | D35: =D163 -> 19.637425 | E35: =E163 -> 26.714691 | F35: =F163 -> 27.705698 | G35: =G163 -> 30.611338
A36: EPS 年增 | B36: % | D36: =D164 -> 0.44286739 | E36: =E164 -> 0.36039683 | F36: =F164 -> 0.037095944 | G36: =G164 -> 0.10487518
A38: 情境 C
A39: 營收 | B39: NT$B | C39: =C188 -> 8103.105 | D39: =D188 -> 11150.735 | E39: =E188 -> 13734.848 | F39: =F188 -> 12196.127 | G39: =G188 -> 12526.292
A40: 營收年增 | B40: % | D40: =D191 -> 0.37610644 | E40: =E191 -> 0.23174375 | F40: =F191 -> -0.11203047 | G40: =G191 -> 0.027071309
A41: AI 伺服器營收 | B41: NT$B | C41: =C181 -> 1620.621 | D41: =D181 -> 3545.9337 | E41: =E181 -> 5728.1744 | F41: =F181 -> 3872.6026 | G41: =G181 -> 3928.9981
A42: 雲端網路產品 | B42: NT$B | C42: =C189 -> 3241.242 | D42: =D189 -> 5909.8895 | E42: =E189 -> 8375.8049 | F42: =F189 -> 6732.0436 | G42: =G189 -> 6960.0055
A43: 消費智能產品 | B43: NT$B | C43: =C184 -> 3079.1799 | D43: =D184 -> 3345.2205 | E43: =E184 -> 3445.5771 | F43: =F184 -> 3514.4887 | G43: =G184 -> 3584.7784
A44: 電腦終端產品 | B44: NT$B | C44: =C185 -> 1215.4658 | D44: =D185 -> 1338.0882 | E44: =E185 -> 1311.3264 | F44: =F185 -> 1311.3264 | G44: =G185 -> 1311.3264
A45: 元件及其他 | B45: NT$B | C45: =C186 -> 567.21735 | D45: =D186 -> 557.53675 | E45: =E186 -> 602.13969 | F45: =F186 -> 638.26807 | G45: =G186 -> 670.18147
A46: 非 AI 營收 | B46: NT$B | C46: =C187 -> 6482.484 | D46: =D187 -> 7604.8013 | E46: =E187 -> 8006.6738 | F46: =F187 -> 8323.5241 | G46: =G187 -> 8597.2938
A47: AI 伺服器 ÷ 營收 | B47: % | C47: =C192 -> 0.2 | D47: =D192 -> 0.318 | E47: =E192 -> 0.41705408 | F47: =F192 -> 0.31752725 | G47: =G192 -> 0.31366011
A48: 毛利 | B48: NT$B | C48: =C199 -> 498.161 | D48: =D199 -> 675.83407 | E48: =E199 -> 845.81449 | F48: =F199 -> 779.57455 | G48: =G199 -> 816.68185
A49: 毛利率 | B49: % | C49: =C200 -> 0.061477792 | D49: =D200 -> 0.060608926 | E49: =E200 -> 0.061581641 | F49: =F200 -> 0.063919847 | G49: =G200 -> 0.065197415
A50: 營業利益率 | B50: % | C50: =C205 -> 0.031990576 | D50: =D205 -> 0.037755686 | E50: =E205 -> 0.041308205 | F50: =F205 -> 0.041088617 | G50: =G205 -> 0.042727254
A51: 歸屬母公司淨利 | B51: NT$B | C51: =C207 -> 189.354 | D51: =D207 -> 275.25709 | E51: =E207 -> 374.45887 | F51: =F207 -> 330.74051 | G51: =G207 -> 353.24128
A52: EPS | B52: NT$ | C52: =C209 -> 13.61 | D52: =D209 -> 19.637425 | E52: =E209 -> 26.714691 | F52: =F209 -> 23.59573 | G52: =G209 -> 25.200983
A53: EPS 年增 | B53: % | D53: =D210 -> 0.44286739 | E53: =E210 -> 0.36039683 | F53: =F210 -> -0.11675076 | G53: =G210 -> 0.06803148
A55: 核對（應為 0）：FY2026 模型營收 − 錨點；FY2026 模型 AI 伺服器 − 錨點；FY2026 毛利 − 錨點
A56: 情境 A：營收差（NT$B） | D56: =D96-a26_rev -> 0
A57: 情境 A：AI 伺服器差（NT$B） | D57: =D89-a26_ai -> 0
A58: 情境 A：毛利差（NT$B；以 FY2027 公式套用 FY2026） | D58: =D105*D95+D106-a26_gp -> 0
A75: 情境 A：基準（顆數係數 1.0）
A76: 項目 | B76: 單位 | C76: FY2025A | D76: FY2026（錨點） | E76: FY2027 | F76: FY2028 | G76: FY2029 | H76: 說明
A77: A. AI 部署與整櫃組裝市場（D 欄＝FY2026 校準年；E–G＝FY2027–FY2029；與廣達模型同口徑）
A78: AI IT 資本支出 × 情境顆數係數 | B78: US$B | D78: =itc_26*1 -> 781.87292 | E78: =itc_27*1*1 -> 1565.35 | F78: =itc_28*um28_A*1 -> 1984.2639 | G78: =itc_29*um29_A*1 -> 2260.3903
A79: 每 GW IT 資本支出 | B79: US$B | D79: =itpg_gb*(1-vr26)+itpg_vr*vr26 -> 33.414032 | E79: =itpg_vr -> 37.586352 | F79: =itpg_vr -> 37.586352 | G79: =itpg_vr -> 37.586352
A80: 部署 GW（IT 電力） | B80: GW | D80: =D78/D79 -> 23.399538 | E80: =E78/E79 -> 41.646766 | F80: =F78/F79 -> 52.792138 | G80: =G78/G79 -> 60.138592
A81: 每 GW ODM 整櫃價值 | B81: US$B/GW | D81: =(racks_gb*odm_gb*(1-vr26)+racks_vr*odm_vr*vr26)/1000 -> 27.1209 | E81: =racks_vr*odm_vr/1000 -> 27.351 | F81: =$E81*vpg_28 -> 27.351 | G81: =$E81*vpg_29 -> 27.351 | H81: 架數 × ODM 每櫃價格；含 ASIC 機架（Assumed：每 GW 價值相同）
A82: AI 伺服器組裝市場（ODM 價，美元） | B82: US$B | D82: =D80*D81 -> 634.61653 | E82: =E80*E81 -> 1139.0807 | F82: =F80*F81 -> 1443.9178 | G82: =G80*G81 -> 1644.8506
A83: AI 伺服器組裝市場（新台幣） | B83: NT$B | D83: =D82*fx -> 20307.729 | E83: =E82*fx -> 36450.582 | F83: =F82*fx -> 46205.369 | G83: =G82*fx -> 52635.22
A84: 鴻海有效份額（FY2026 校準）＝ AI 伺服器營收 ÷ 市場 | B84: % | D84: =a26_ai/D83 -> 0.17461006 | H84: Derived：分子為公司雲端網路占比 × AI 占雲端網路 × 營收（金額口徑）；分母含 ASIC、HGX 機架，所以低於整櫃櫃數份額
A85: 份額相對值（÷ FY2026） | B85: x | D85: =1 -> 1 | E85: =rel_27 -> 1 | F85: =rel_28 -> 1 | G85: =rel_29 -> 0.95
A86: 鴻海有效份額 | B86: % | D86: =$D$84*D85 -> 0.17461006 | E86: =$D$84*E85 -> 0.17461006 | F86: =$D$84*F85 -> 0.17461006 | G86: =$D$84*G85 -> 0.16587955
A87: AI 伺服器毛額價值（買賣模式下的營收） | B87: NT$B | D87: =D83*D86 -> 3545.9337 | E87: =E83*E86 -> 6364.6382 | F87: =F83*F86 -> 8067.9221 | G87: =G83*G86 -> 8731.1068
A88: 客供比例（FY2027 起新增部分） | B88: % | D88: =0 -> 0 | E88: =cs_27 -> 0.1 | F88: =cs_28 -> 0.2 | G88: =cs_29 -> 0.25 | H88: FY2026 已有的半成品／客供已含在錨點與校準份額內，記為 0
A89: AI 伺服器營收 | B89: NT$B | C89: =a25_ai -> 1620.621 | D89: =D87*(1-D88) -> 3545.9337 | E89: =E87*(1-E88) -> 5728.1744 | F89: =F87*(1-F88) -> 6454.3377 | G89: =G87*(1-G88) -> 6548.3301
A90: B. 非 AI 事業（簡化成長率）與合計
A91: 雲端網路非 AI（網通、一般伺服器） | B91: NT$B | C91: =a25_cn -> 1620.621 | D91: =a26_cn -> 2363.9558 | E91: =D91*(1+g_cn27) -> 2647.6305 | F91: =E91*(1+g_cn28) -> 2859.441 | G91: =F91*(1+g_cn29) -> 3031.0074
A92: 消費智能（iPhone 等） | B92: NT$B | C92: =a25_ce -> 3079.1799 | D92: =a26_ce -> 3345.2205 | E92: =D92*(1+g_ce27) -> 3445.5771 | F92: =E92*(1+g_ce28) -> 3514.4887 | G92: =F92*(1+g_ce29) -> 3584.7784
A93: 電腦終端 | B93: NT$B | C93: =a25_pc -> 1215.4658 | D93: =a26_pc -> 1338.0882 | E93: =D93*(1+g_pc27) -> 1311.3264 | F93: =E93*(1+g_pc28) -> 1311.3264 | G93: =F93*(1+g_pc29) -> 1311.3264
A94: 元件及其他 | B94: NT$B | C94: =a25_co -> 567.21735 | D94: =a26_co -> 557.53675 | E94: =D94*(1+g_co27) -> 602.13969 | F94: =E94*(1+g_co28) -> 638.26807 | G94: =F94*(1+g_co29) -> 670.18147
A95: 非 AI 營收合計 | B95: NT$B | C95: =SUM(C91:C94) -> 6482.484 | D95: =SUM(D91:D94) -> 7604.8013 | E95: =SUM(E91:E94) -> 8006.6738 | F95: =SUM(F91:F94) -> 8323.5241 | G95: =SUM(G91:G94) -> 8597.2938
A96: 營收 | B96: NT$B | C96: =C89+C95 -> 8103.105 | D96: =D89+D95 -> 11150.735 | E96: =E89+E95 -> 13734.848 | F96: =F89+F95 -> 14777.862 | G96: =G89+G95 -> 15145.624
A97: 雲端網路產品（官方產品類別＝AI 伺服器＋雲端網路非 AI） | B97: NT$B | C97: =C89+C91 -> 3241.242 | D97: =D89+D91 -> 5909.8895 | E97: =E89+E91 -> 8375.8049 | F97: =F89+F91 -> 9313.7786 | G97: =G89+G91 -> 9579.3375 | H97: 官方四大產品類別：雲端網路產品、消費智能產品（上列「消費智能」）、電腦終端產品（「電腦終端」）、元件及其他
A98: 檢查：四大產品類別合計 − 合併營收（FY2025 實績、FY2026 錨點） | B98: NT$B | C98: =C97+C92+C93+C94-a25_rev -> 0 | D98: =D97+D92+D93+D94-a26_rev -> 0 | E98: =E97+E92+E93+E94-E96 -> 0 | F98: =F97+F92+F93+F94-F96 -> 0 | G98: =G97+G92+G93+G94-G96 -> 0
A99: 營收年增 | B99: % | D99: =D96/C96-1 -> 0.37610644 | E99: =E96/D96-1 -> 0.23174375 | F99: =F96/E96-1 -> 0.075939217 | G99: =G96/F96-1 -> 0.024886015
A100: AI 伺服器 ÷ 營收 | B100: % | C100: =C89/C96 -> 0.2 | D100: =D89/D96 -> 0.318 | E100: =E89/E96 -> 0.41705408 | F100: =F89/F96 -> 0.43675721 | G100: =G89/G96 -> 0.4323579
A101: 雲端網路產品 ÷ 營收 | B101: % | C101: =(C89+C91)/C96 -> 0.4 | D101: =(D89+D91)/D96 -> 0.53 | E101: =(E89+E91)/E96 -> 0.60982144 | F101: =(F89+F91)/F96 -> 0.63025211 | G101: =(G89+G91)/G96 -> 0.6324822
A102: 每 GW 鴻海 AI 伺服器營收 | B102: US$B/GW | D102: =D89/fx/D80 -> 4.7355819 | E102: =E89/fx/E80 -> 4.2981837 | F102: =F89/fx/F80 -> 3.8206077 | G102: =G89/fx/G80 -> 3.4027288
A103: 隱含鴻海出貨櫃數（毛額價值 ÷ ODM 每櫃價格；NVL72 等值） | B103: 千櫃 | D103: =D87/fx/(odm_gb*(1-vr26)+odm_vr*vr26) -> 24.063068 | E103: =E87/fx/odm_vr -> 29.465918 | F103: =F87/fx/odm_vr -> 37.351491 | G103: =G87/fx/odm_vr -> 40.421791 | H103: 十億美元 ÷ 百萬美元 ＝ 千櫃；FY2028 起若每 GW 價值改變，每櫃價格仍以 VR200 換算（參考）
A104: C. 損益
A105: 其他營收毛利率 ＝ 錨點毛利率 − 差距 × AI 占比（FY2026 校準） | B105: % | D105: =a26_gp/D96-d_ai*D100 -> 0.062198926 | H105: Derived：讓 FY2026 毛利率等於錨點；AI 毛利率（毛額基礎）＝其他 + 差距
A106: AI 伺服器毛利 ＝ AI 毛利率 × 毛額價值 ×（1 − 客供 ×（1 − 保留比例）） | B106: NT$B | D106: =($D$105+d_ai)*D87*(1-D88*(1-keep)) -> 202.8236 | E106: =($D$105+d_ai+vrd)*E87*(1-E88*(1-keep)) -> 347.80798 | F106: =($D$105+d_ai+vrd)*F87*(1-F88*(1-keep)) -> 436.43382 | G106: =($D$105+d_ai+vrd)*G87*(1-G88*(1-keep)) -> 469.89903 | H106: 客供部分不計營收，但大部分毛利金額保留（keep）；FY2027 起加 VR 稀釋 vrd
A107: 毛利 | B107: NT$B | C107: =a25_gp -> 498.161 | D107: =a26_gp -> 675.83407 | E107: =$D$105*E95+E106 -> 845.81449 | F107: =$D$105*F95+F106 -> 954.14808 | G107: =$D$105*G95+G106 -> 1004.6415
A108: 毛利率 | B108: % | C108: =C107/C96 -> 0.061477792 | D108: =D107/D96 -> 0.060608926 | E108: =E107/E96 -> 0.061581641 | F108: =F107/F96 -> 0.064566044 | G108: =G107/G96 -> 0.066332128
A109: AI 伺服器毛利率（營收基礎） | B109: % | D109: =D106/D89 -> 0.057198926 | E109: =E106/E89 -> 0.060718818 | F109: =F106/F89 -> 0.067618684 | G109: =G106/G89 -> 0.071758604 | H109: 客供比例上升 → 營收基礎毛利率上升
A110: 營業費用（基準路徑） | B110: NT$B | C110: =a25_opx -> 238.938 | D110: =a26_opx -> 254.83042 | E110: =D110*(1+MAX(0,phi*E99)) -> 278.45257 | F110: =E110*(1+MAX(0,phi*F99)) -> 286.91075 | G110: =F110*(1+MAX(0,phi*G99)) -> 289.76678
A111: 營業費用 | B111: NT$B | C111: =C110 -> 238.938 | D111: =D110 -> 254.83042 | E111: =E110+0*E96 -> 278.45257 | F111: =F110+0*F96 -> 286.91075 | G111: =G110+0*G96 -> 289.76678
A112: 營業利益 | B112: NT$B | C112: =C107-C111 -> 259.223 | D112: =D107-D111 -> 421.00365 | E112: =E107-E111 -> 567.36192 | F112: =F107-F111 -> 667.23733 | G112: =G107-G111 -> 714.87468
A113: 營業利益率 | B113: % | C113: =C112/C96 -> 0.031990576 | D113: =D112/D96 -> 0.037755686 | E113: =E112/E96 -> 0.041308205 | F113: =F112/F96 -> 0.045151141 | G113: =G112/G96 -> 0.047200082
A114: 淨利 ÷ 營業利益 | B114: % | C114: =a25_ni/a25_oi -> 0.73046759 | D114: =a26_ni/a26_oi -> 0.65381165 | E114: =nio_f -> 0.66 | F114: =nio_f -> 0.66 | G114: =nio_f -> 0.66
A115: 歸屬母公司淨利 | B115: NT$B | C115: =a25_ni -> 189.354 | D115: =a26_ni -> 275.25709 | E115: =E112*E114 -> 374.45887 | F115: =F112*F114 -> 440.37663 | G115: =G112*G114 -> 471.81729
A116: 股數 | B116: 十億股 | C116: =a25_sh -> 13.912858 | D116: =a26_sh -> 14.016964 | E116: =D116*(1+sh_g) -> 14.016964 | F116: =E116*(1+sh_g) -> 14.016964 | G116: =F116*(1+sh_g) -> 14.016964
A117: EPS | B117: NT$ | C117: =C115/C116 -> 13.61 | D117: =D115/D116 -> 19.637425 | E117: =E115/E116 -> 26.714691 | F117: =F115/F116 -> 31.417404 | G117: =G115/G116 -> 33.660447
A118: EPS 年增 | B118: % | D118: =D117/C117-1 -> 0.44286739 | E118: =E117/D117-1 -> 0.36039683 | F118: =F117/E117-1 -> 0.17603473 | G118: =G117/F117-1 -> 0.071394922
A121: 情境 B：CY2028 顆數 ×0.8、CY2029 ×0.85
A122: 項目 | B122: 單位 | C122: FY2025A | D122: FY2026（錨點） | E122: FY2027 | F122: FY2028 | G122: FY2029 | H122: 說明
...

Sheet Val
A1: Val — P/E 估值（新台幣）。結論用「現價 ÷ FY2027、FY2028 EPS（模型）」與十年 P/E 規則值（年底落後 P/E，基準為 FY2027 EPS）
A2: 循環位置：鴻海不是設備股，不套設備市場見頂年；以本模型營收最高的會計年度為見頂年（比照廣達、NVIDIA、台達電；FY(t)＝CY(t)）。營收到 FY2029 仍在增加時，見頂年未知，判為中段
A3: 目標價：見第 0 節（本頁第 85 列；v0.2 新增，DCF 與 Comparable 加權）。第 37 列「舊法：規則值情境加權（參考）」不再是目標價，只作參考
A4: 1. 價格與市場隱含倍數
A5: 項目 | B5: A | C5: B | D5: C | E5: 說明
A6: 現價（2026-10-22 收盤） | B6: =px -> 245
A7: 現價 ÷ FY2026 EPS（錨點） | B7: =px/PL!D18 -> 12.476177 | C7: =px/PL!D35 -> 12.476177 | D7: =px/PL!D52 -> 12.476177
A8: 現價 ÷ FY2027 EPS（模型） | B8: =px/PL!E18 -> 9.1709839 | C8: =px/PL!E35 -> 9.1709839 | D8: =px/PL!E52 -> 9.1709839 | E8: FY2027 三情境相同（顆數係數從 CY2028 開始）
A9: 現價 ÷ FY2028 EPS（模型） | B9: =px/PL!F18 -> 7.7982254 | C9: =px/PL!F35 -> 8.8429464 | D9: =px/PL!F52 -> 10.383234
A10: 現價 ÷ FY2029 EPS（模型） | B10: =px/PL!G18 -> 7.2785723 | C10: =px/PL!G35 -> 8.0035705 | D10: =px/PL!G52 -> 9.721843
A11: 未來 12 月 EPS（模型 A）≈ 0.2 × FY2026＋0.8 × FY2027 | B11: =0.2*PL!D18+0.8*PL!E18 -> 25.299238
A12: 現價 ÷ 未來 12 月 EPS（模型 A） | B12: =px/B11 -> 9.6840862
A13: 近 12 月 P/E（Yahoo，10-16） | B13: =pe_ttm -> 16.08
A15: 2. 循環位置（本模型營收最高年；FY(t)＝CY(t)）
A16: 情境 | B16: 營收最高年（FY2026–FY2029） | C16: FY2027 判定 | D16: 規則倍數（P/E） | E16: 見頂年是否未知 | F16: 說明
A17: A | B17: =INDEX({2026,2027,2028,2029},MATCH(MAX(PL!D96:G96),PL!D96:G96,0)) -> 2029 | C17: =IF(B17=2029,"中段",IF(2027<B17,"中段",IF(2027=B17,"見頂","谷底"))) -> 中段 | D17: =IF(C17="見頂",pe_peak,IF(C17="谷底",pe_trough,pe_mid)) -> 9.92 | E17: =IF(B17=2029,"是：營收到觀測期末仍在增加","否") -> 是：營收到觀測期末仍在增加 | F17: tools/cycle_position.py excel_rule；營收最高年取代設備市場見頂年
A18: B | B18: =INDEX({2026,2027,2028,2029},MATCH(MAX(PL!D142:G142),PL!D142:G142,0)) -> 2029 | C18: =IF(B18=2029,"中段",IF(2027<B18,"中段",IF(2027=B18,"見頂","谷底"))) -> 中段 | D18: =IF(C18="見頂",pe_peak,IF(C18="谷底",pe_trough,pe_mid)) -> 9.92 | E18: =IF(B18=2029,"是：營收到觀測期末仍在增加","否") -> 是：營收到觀測期末仍在增加 | F18: 同上
A19: C | B19: =INDEX({2026,2027,2028,2029},MATCH(MAX(PL!D188:G188),PL!D188:G188,0)) -> 2027 | C19: =IF(B19=2029,"中段",IF(2027<B19,"中段",IF(2027=B19,"見頂","谷底"))) -> 見頂 | D19: =IF(C19="見頂",pe_peak,IF(C19="谷底",pe_trough,pe_mid)) -> 9.25 | E19: =IF(B19=2029,"是：營收到觀測期末仍在增加","否") -> 否 | F19: 同上
A21: 3. 規則值隱含股價（新台幣；約 FY2027 年底，未折現）＝ FY2027 EPS × 規則倍數
A22: 情境 | B22: FY2027 EPS | C22: （同左） | D22: 規則倍數 | E22: 隱含股價 | F22: 相對現價 | G22: 現價 ÷ FY2027 EPS
A23: A | B23: =PL!E18 -> 26.714691 | C23: =B23 -> 26.714691 | D23: =D17 -> 9.92 | E23: =C23*D23 -> 265.00973 | F23: =E23/px-1 -> 0.081672386 | G23: =px/C23 -> 9.1709839
A24: B | B24: =PL!E35 -> 26.714691 | C24: =B24 -> 26.714691 | D24: =D18 -> 9.92 | E24: =C24*D24 -> 265.00973 | F24: =E24/px-1 -> 0.081672386 | G24: =px/C24 -> 9.1709839
A25: C | B25: =PL!E52 -> 26.714691 | C25: =B25 -> 26.714691 | D25: =D19 -> 9.25 | E25: =C25*D25 -> 247.11089 | F25: =E25/px-1 -> 0.0086158841 | G25: =px/C25 -> 9.1709839
A26: 4. What must be true：FY2027 年底價 ＝ 現價 ×（1＋報酬）所需的倍數（FY2028 EPS；約 2027 年底的價格看下一年 EPS）
A27: FY2027 年底價 ÷ 現價 | B27: 所需倍數（÷ FY2028 EPS，A） | C27: 所需倍數（÷ FY2028 EPS，C） | D27: 對照：十年中位數
A28: 1 | B28: =px*A28/PL!F18 -> 7.7982254 | C28: =px*A28/PL!F52 -> 10.383234 | D28: =pe_mid -> 9.92
A29: 1.1 | B29: =px*A29/PL!F18 -> 8.5780479 | C29: =px*A29/PL!F52 -> 11.421558 | D29: =pe_mid -> 9.92
A30: 1.21 | B30: =px*A30/PL!F18 -> 9.4358527 | C30: =px*A30/PL!F52 -> 12.563714 | D30: =pe_mid -> 9.92
A31: 1.5 | B31: =px*A31/PL!F18 -> 11.697338 | C31: =px*A31/PL!F52 -> 15.574852 | D31: =pe_mid -> 9.92
A32: 2 | B32: =px*A32/PL!F18 -> 15.596451 | C32: =px*A32/PL!F52 -> 20.766469 | D32: =pe_mid -> 9.92
A33: 讀法：1.00＝價格不變、1.21＝一年約 21%。所需倍數低於歷史中位數時，現價相對便宜；倍數是否合理，另看前瞻 P/E 歷史（Bloomberg）。
A35: 5. 先驗對照：本版未做先驗，無 Andy 合理 P/E 對照
A37: 舊法：規則值情境加權（參考；v0.1.1 的「0. 目標價與上檔空間」改名，不再是目標價；權重為 In 頁 tp_wA／tp_wB／tp_wC）
A38: 舊法隱含價（情境加權，參考） | B38: =tp_wA*B40+tp_wB*B41+tp_wC*B42 -> 261.42997 | E38: ＝權重 A × 情境 A 隱含價＋權重 B × 情境 B 隱含價＋權重 C × 情境 C 隱含價（NT$）
A39: 舊法隱含價相對現價（÷ 現價 − 1） | B39: =B38/px-1 -> 0.067061086 | E39: 相對「現價（2026-10-22 收盤）」
A40: 情境 A 隱含價（樂觀） | B40: =E23 -> 265.00973 | E40: ＝規則值隱含股價 E23（情境 A：基準（顆數係數 1.0））
A41: 情境 B 隱含價（基準） | B41: =E24 -> 265.00973 | E41: ＝規則值隱含股價 E24（情境 B：CY2028 顆數 ×0.8、CY2029 ×0.85）
A42: 情境 C 隱含價（下檔） | B42: =E25 -> 247.11089 | E42: ＝規則值隱含股價 E25（情境 C：CY2028–29 顆數 ×0.6）
A43: 情境權重 A／B／C | B43: =tp_wA -> 0.3 | C43: =tp_wB -> 0.5 | D43: =tp_wC -> 0.2 | E43: In 頁輸入（Assumed，Andy 可改）：B 欄＝情境 A、C 欄＝情境 B、D 欄＝情境 C
A44: 舊法說明 | B44: P/E 規則值：各情境 FY2027 EPS × 2016–2025 年底 P/E 依循環位置取分位（見頂＝25 分位、中段＝中位數、谷底＝75 分位；companiesmarketcap 與 Goodinfo 兩來源分別取分位再平均）。隱含價約為 FY2027 年底價、未折現，作 12 個月目標價的近似；情境 A／B／C 即本模型三個顆數情境（A 最高、C 最低）。偏誤：十年倍數含 2016–2023 年 iPhone 組裝期低倍數（約 7–12x），目標價可能偏低。
A50: 6. 十年倍數與規則值（2016–2025 年底；見頂年 25 分位、中段中位數、谷底 75 分位）
A51: 規則（Andy 2026-10-13）：合理倍數＝2016–2025 年底 P/E 依循環位置取分位，兩個來源分別取分位再平均。兩來源 2016–2020 年相差約 1–3 個倍數點（companiesmarketcap 疑用還原股價，數字較低；2016–2017 年有股票股利）。2016–2023 年鴻海以 iPhone 組裝為主（約 7–12x），2024 年起 AI 伺服器重新定價（約 16–17x），規則值可能低估 AI 期的合理倍數。
A53: P/E：十年歷史倍數
A54: 年底 | B54: companiesmarketcap（年底 P/E） | C54: Goodinfo（年底收盤 ÷ EPS） | D54: 標記／說明
A55: 2016 | B55: 6.85 | C55: =84.2/8.6 -> 9.7906977 | D55: companiesmarketcap（年底 P/E）：Interested-party（資料商；2016–2025 共 10 年；價格可能為還原股價）；Goodinfo（年底收盤 ÷ EPS）：Derived（資料商收盤價與 EPS；未還原除權息）
A56: 2017 | B56: 10.8 | C56: =95.2/8.01 -> 11.885144
A57: 2018 | B57: 6.5 | C57: =70.8/8.03 -> 8.8169365
A58: 2019 | B58: 8.55 | C58: =90.8/8.32 -> 10.913462
A59: 2020 | B59: 10.3 | C59: =92/7.34 -> 12.53406
A60: 2021 | B60: 8.83 | C60: =104/10.05 -> 10.348259
A61: 2022 | B61: 8.78 | C61: =99.9/10.21 -> 9.784525
A62: 2023 | B62: 9.59 | C62: =104.5/10.25 -> 10.195122
A63: 2024 | B63: 16.2 | C63: =184/11.01 -> 16.71208
A64: 2025 | B64: 16.8 | C64: =230.5/13.61 -> 16.936076
A65: 25 分位（各來源） | B65: =PERCENTILE(B55:B64,0.25) -> 8.6075 | C65: =PERCENTILE(C55:C64,0.25) -> 9.8918037
A66: 中位數（各來源） | B66: =MEDIAN(B55:B64) -> 9.21 | C66: =MEDIAN(C55:C64) -> 10.63086
A67: 75 分位（各來源） | B67: =PERCENTILE(B55:B64,0.75) -> 10.675 | C67: =PERCENTILE(C55:C64,0.75) -> 12.371831
A68: 最小（各來源） | B68: =MIN(B55:B64) -> 6.5 | C68: =MIN(C55:C64) -> 8.8169365
A69: 最大（各來源） | B69: =MAX(B55:B64) -> 16.8 | C69: =MAX(C55:C64) -> 16.936076
A70: 採用 25 分位（P/E） | B70: =ROUND(AVERAGE(B65,C65),2) -> 9.25
A71: 採用 中位數（P/E） | B71: =ROUND(AVERAGE(B66,C66),2) -> 9.92
A72: 採用 75 分位（P/E） | B72: =ROUND(AVERAGE(B67,C67),2) -> 11.52
A73: 採用 最小（P/E） | B73: =ROUND(MIN(B68,C68),2) -> 6.5
A74: 採用 最大（P/E） | B74: =ROUND(MAX(B69,C69),2) -> 16.94
A76: P/E：規則值
A77: 情形 | B77: 循環位置 | C77: 倍數 | D77: 基準 | E77: 每股基準 | F77: 隱含股價 | G77: 相對目前 | H77: 現價 ÷ 基準
A78: 規則值：見頂（P/E） | B78: 25 分位 | C78: =B70 -> 9.25 | D78: FY2027 EPS（A） | E78: =C23 -> 26.714691 | F78: =C78*E78 -> 247.11089 | G78: =F78/px-1 -> 0.0086158841 | H78: =px/E78 -> 9.1709839
A79: 規則值：中段（P/E） | B79: 中位數 | C79: =B71 -> 9.92 | D79: FY2027 EPS（A） | E79: =C23 -> 26.714691 | F79: =C79*E79 -> 265.00973 | G79: =F79/px-1 -> 0.081672386 | H79: =px/E79 -> 9.1709839
A80: 規則值：谷底（P/E） | B80: 75 分位 | C80: =B72 -> 11.52 | D80: FY2027 EPS（A） | E80: =C23 -> 26.714691 | F80: =C80*E80 -> 307.75324 | G80: =F80/px-1 -> 0.25613567 | H80: =px/E80 -> 9.1709839
A85: 0. 目標價（DCF 與 Comparable 加權；v0.2 新增，放在本頁既有內容之後以免位移既有儲存格；三情境欄 B／C／D＝A 順利／B 平平／C 不如預期）
A86: 0.1 DCF（股東權益現金流，FY2027–FY2032 明確期＋FY2032 後永續）
A87: 項目 | B87: A（順利） | C87: B（平平） | D87: C（不如預期） | E87: 說明
A88: 情境 EPS（FY2027–FY2032） | E88: PL 頁延伸表；FY2030 起為收斂法
A89: FY2027 | B89: =PL!E221 -> 26.714691 | C89: =PL!E233 -> 26.714691 | D89: =PL!E245 -> 26.714691
A90: FY2028 | B90: =PL!F221 -> 31.417404 | C90: =PL!F233 -> 27.705698 | D90: =PL!F245 -> 23.59573
A91: FY2029 | B91: =PL!G221 -> 33.660447 | C91: =PL!G233 -> 30.611338 | D91: =PL!G245 -> 25.200983
A92: FY2030 | B92: =PL!H221 -> 34.892106 | C92: =PL!H233 -> 30.974841 | D92: =PL!H245 -> 24.102218
A93: FY2031 | B93: =PL!I221 -> 36.577232 | C93: =PL!I233 -> 31.204203 | D93: =PL!I245 -> 22.880997
A94: FY2032 | B94: =PL!J221 -> 38.771866 | C94: =PL!J233 -> 31.293358 | D94: =PL!J245 -> 21.543339
A95: 股東現金流＝EPS ×（1 − tp_g ÷ tp_roe）
A96: 再投資率（tp_g ÷ tp_roe，上限 0.8） | B96: =MIN(tp_g/tp_roe,0.8) -> 0.3968254 | E96: ROE 為近三年平均（In 頁 tp_roe）
A97: FY2027 | B97: =B89*(1-$B$96) -> 16.113623 | C97: =C89*(1-$B$96) -> 16.113623 | D97: =D89*(1-$B$96) -> 16.113623
A98: FY2028 | B98: =B90*(1-$B$96) -> 18.95018 | C98: =C90*(1-$B$96) -> 16.711373 | D98: =D90*(1-$B$96) -> 14.232345
A99: FY2029 | B99: =B91*(1-$B$96) -> 20.303127 | C99: =C91*(1-$B$96) -> 18.463981 | D99: =D91*(1-$B$96) -> 15.200593
A100: FY2030 | B100: =B92*(1-$B$96) -> 21.046032 | C100: =C92*(1-$B$96) -> 18.683237 | D100: =D92*(1-$B$96) -> 14.537846
A101: FY2031 | B101: =B93*(1-$B$96) -> 22.062457 | C101: =C93*(1-$B$96) -> 18.821583 | D101: =D93*(1-$B$96) -> 13.801236
A102: FY2032 | B102: =B94*(1-$B$96) -> 23.386205 | C102: =C94*(1-$B$96) -> 18.875359 | D102: =D94*(1-$B$96) -> 12.994395
A103: DCF 情境每股價值（折現率 tp_r） | B103: =SUMPRODUCT(B97:B102,1/(1+tp_r)^{1;2;3;4;5;6})+B102*(1+tp_g)/(tp_r-tp_g)/(1+tp_r)^6 -> 315.65442 | C103: =SUMPRODUCT(C97:C102,1/(1+tp_r)^{1;2;3;4;5;6})+C102*(1+tp_g)/(tp_r-tp_g)/(1+tp_r)^6 -> 262.1149 | D103: =SUMPRODUCT(D97:D102,1/(1+tp_r)^{1;2;3;4;5;6})+D102*(1+tp_g)/(tp_r-tp_g)/(1+tp_r)^6 -> 190.80542 | E103: Σ 明確期現金流 ÷ (1＋r)^t ＋ 永續價值 ÷ (1＋r)^6；永續價值＝FY2032 現金流 ×(1＋g)÷(r−g)；基準日 2026 年底，t＝1 對 FY2027
A104: DCF 情境價值推到 12 個月後（×(1＋tp_r)） | B104: =B103*(1+tp_r) -> 347.21987 | C104: =C103*(1+tp_r) -> 288.32639 | D104: =D103*(1+tp_r) -> 209.88596
A105: DCF 目標價（情境加權） | B105: =tp_wA*B104+tp_wB*C104+tp_wC*D104 -> 290.30635 | E105: Σ tp_wA／wB／wC × 情境價值 ×(1＋tp_r)；權重見 In 頁
A107: 0.2 Comparable（市場主流同業前瞻 P/E）
A108: 同業與前瞻 P/E | B108: 代號 | C108: 前瞻 12 月 P/E | D108: 日期 | E108: 來源 | F108: 標記
A109: 廣達（Quanta） | B109: 2382.TW | C109: 11.31 | D109: 2026-10-14 | E109: stockanalysis.com 個股頁 Forward PE（分析師共識；價格日期如左） | F109: Interested-party（賣方共識）
A110: 緯創（Wistron） | B110: 3231.TW | C110: 9.93 | D110: 2026-09-29 | E110: stockanalysis.com 個股頁 Forward PE（分析師共識；價格日期如左） | F110: Interested-party（賣方共識）
A111: 和碩（Pegatron） | B111: 4938.TW | C111: 14.88 | D111: 2026-10-22 | E111: stockanalysis.com 個股頁 Forward PE（分析師共識；價格日期如左） | F111: Interested-party（賣方共識）
A112: Jabil | B112: JBL | C112: 15.49 | D112: 2026-10-23 | E112: stockanalysis.com 個股頁 Forward PE（分析師共識；價格日期如左） | F112: Interested-party（賣方共識）
A113: Flex | B113: FLEX | C113: 14.74 | D113: 2026-10-23 | E113: stockanalysis.com 個股頁 Forward PE（分析師共識；價格日期如左） | F113: Interested-party（賣方共識）
A114: 同業前瞻 P/E 中位數 | B114: =MEDIAN(C109:C113) -> 14.74 | E114: 電子代工與 AI 伺服器組裝同業：廣達、緯創、和碩、Jabil、Flex（券商常用比較組）。工業富聯（601138.SS，鴻海子公司）為 A 股，依規則不列。非 A 股公司的同業名單不放中國 A 股（A 股有結構性溢價；Andy 2026-10-25 11:53）
A115: 12 個月後的前瞻 EPS（情境加權） | B115: =tp_wA*(0.166666666666667*B89+0.833333333333333*B90)+tp_wB*(0.166666666666667*C89+0.833333333333333*C90)+tp_wC*(0.166666666666667*D89+0.833333333333333*D90) -> 27.783462 | E115: 約 2027-10 時的未來 12 月 EPS ≈ 2／12 × FY2027＋10／12 × FY2028（會計年度＝日曆年）
A116: Comparable 目標價 | B116: =B114*B115 -> 409.52823 | E116: 同業中位數 × 上列 EPS
...

Sheet Recon
A1: Recon — 本模型 vs 券商估計與櫃數份額。只作事後對照，不為對上數字而調參數。券商多為 3Q 營收公布前、部分未具名；FY2027 付費共識未找到
A3: 項目 | B3: 對照值 | C3: 模型 A | D3: 差距 A | E3: 模型 B | F3: 差距 B | G3: 模型 C | H3: 差距 C | I3: 對照來源 | J3: 說明
A4: A. 券商估計（校準未使用）
A5: FY2026 營收 vs 凱基（08-12，3Q 前） | B5: =b_rev26 -> 11010.682 | C5: =PL!D96 -> 11150.735 | D5: =C5/B5-1 -> 0.012719739 | E5: =PL!D142 -> 11150.735 | F5: =E5/B5-1 -> 0.012719739 | G5: =PL!D188 -> 11150.735 | H5: =G5/B5-1 -> 0.012719739 | I5: 凱基 2026-08-12 | J5: 3Q26 實績高於凱基估 7%
A6: FY2026 EPS vs 凱基 | B6: =b_eps26 -> 18.67 | C6: =PL!D117 -> 19.637425 | D6: =C6/B6-1 -> 0.051817096 | E6: =PL!D163 -> 19.637425 | F6: =E6/B6-1 -> 0.051817096 | G6: =PL!D209 -> 19.637425 | H6: =G6/B6-1 -> 0.051817096 | I6: 凱基 2026-08-12 | J6: 瑞銀 18.0、今周刊法人 19
A7: FY2027 營收 vs 凱基 | B7: =b_rev27 -> 14019.401 | C7: =PL!E96 -> 13734.848 | D7: =C7/B7-1 -> -0.020297074 | E7: =PL!E142 -> 13734.848 | F7: =E7/B7-1 -> -0.020297074 | G7: =PL!E188 -> 13734.848 | H7: =G7/B7-1 -> -0.020297074 | I7: 凱基 2026-08-12 | J7: 凱基元件及其他 2027F +93%
A8: FY2027 EPS vs 凱基 | B8: =b_eps27a -> 22.64 | C8: =PL!E117 -> 26.714691 | D8: =C8/B8-1 -> 0.17997752 | E8: =PL!E163 -> 26.714691 | F8: =E8/B8-1 -> 0.17997752 | G8: =PL!E209 -> 26.714691 | H8: =G8/B8-1 -> 0.17997752 | I8: 凱基 2026-08-12
A9: FY2027 EPS vs 瑞銀（07-22） | B9: =b_eps27b -> 22 | C9: =PL!E117 -> 26.714691 | D9: =C9/B9-1 -> 0.21430414 | E9: =PL!E163 -> 26.714691 | F9: =E9/B9-1 -> 0.21430414 | G9: =PL!E209 -> 26.714691 | H9: =G9/B9-1 -> 0.21430414 | I9: 經濟日報 2026-07-22
A10: FY2027 EPS vs 法人（08-18） | B10: =b_eps27c -> 25 | C10: =PL!E117 -> 26.714691 | D10: =C10/B10-1 -> 0.068587639 | E10: =PL!E163 -> 26.714691 | F10: =E10/B10-1 -> 0.068587639 | G10: =PL!E209 -> 26.714691 | H10: =G10/B10-1 -> 0.068587639 | I10: 今周刊 2026-08-18 | J10: 三家區間 22.0–25.0
A11: FY2028 EPS vs 法人（08-18） | B11: =b_eps28 -> 28 | C11: =PL!F117 -> 31.417404 | D11: =C11/B11-1 -> 0.12205016 | E11: =PL!F163 -> 27.705698 | F11: =E11/B11-1 -> -0.010510798 | G11: =PL!F209 -> 23.59573 | H11: =G11/B11-1 -> -0.15729534 | I11: 今周刊 2026-08-18 | J11: 摩根士丹利 05-15：23.03
A12: FY2027 毛利率 vs 凱基（百分點） | B12: =b_gm27 -> 0.057 | C12: =PL!E108 -> 0.061581641 | D12: =C12-B12 -> 0.004581641 | E12: =PL!E154 -> 0.061581641 | F12: =E12-B12 -> 0.004581641 | G12: =PL!E200 -> 0.061581641 | H12: =G12-B12 -> 0.004581641 | I12: 凱基 2026-08-12
A13: B. 份額（櫃數口徑 vs 本模型金額口徑）
A14: FY2026 有效份額 vs 三家 ODM 中的 NVL72 櫃數份額 | B14: =rk_sh -> 0.34782609 | C14: =PL!D84 -> 0.17461006 | D14: =C14-B14 -> -0.17321603 | E14: =PL!D130 -> 0.17461006 | F14: =E14-B14 -> -0.17321603 | G14: =PL!D176 -> 0.17461006 | H14: =G14-B14 -> -0.17321603 | I14: 經濟日報 2026-09-10（美系券商；櫃數） | J14: 口徑不同：本模型為金額、分母為全部 AI 組裝市場（含 ASIC、HGX、其他廠）
A15: FY2026 有效份額 vs NVIDIA AI 機櫃全球份額（法人估） | B15: =rk_sh2 -> 0.44 | C15: =PL!D84 -> 0.17461006 | D15: =C15-B15 -> -0.26538994 | E15: =PL!D130 -> 0.17461006 | F15: =E15-B15 -> -0.26538994 | G15: =PL!D176 -> 0.17461006 | H15: =G15-B15 -> -0.26538994 | I15: Inside 2026-08（法人；公司說 40% 以上） | J15: 同上
A16: FY2026 隱含鴻海出貨櫃數（千櫃，NVL72 等值） | C16: =PL!D103 -> 24.063068 | E16: =PL!D149 -> 24.063068 | G16: =PL!D195 -> 24.063068 | I16: — | J16: 櫃數調查單月約 2.6 千櫃 × 12 ≈ 31 千櫃（Interested-party；含運算托盤口徑不明）
A17: FY2026 每 GW 鴻海 AI 伺服器營收（US$B） | C17: =PL!D102 -> 4.7355819 | E17: =PL!D148 -> 4.7355819 | G17: =PL!D194 -> 4.7355819 | I17: —
A18: FY2026 鴻海 ÷ 廣達 AI 伺服器營收（倍） | C18: =Units!C10/(Units!C14*Units!C6) -> 1.304071 | E18: =Units!C10/(Units!C14*Units!C6) -> 1.304071 | G18: =Units!C10/(Units!C14*Units!C6) -> 1.304071 | I18: 廣達模型 Units（唯讀） | J18: 櫃數調查 2,600 ÷ 2,525 ≈ 1.03；鴻海含較多 ASIC 與交換機以外的 AI 產品
A19: C. 校準
A20: 其他營收毛利率（Derived） | C20: =PL!D105 -> 0.062198926 | E20: =PL!D151 -> 0.062198926 | G20: =PL!D197 -> 0.062198926 | I20: FY2026 錨點 | J20: AI 毛利率（毛額基礎）＝此值＋d_ai
A21: FY2027 毛利率 vs FY2026（百分點） | B21: =a26_gp/a26_rev -> 0.060608926 | C21: =PL!E108 -> 0.061581641 | D21: =C21-B21 -> 0.00097271517 | E21: =PL!E154 -> 0.061581641 | F21: =E21-B21 -> 0.00097271517 | G21: =PL!E200 -> 0.061581641 | H21: =G21-B21 -> 0.00097271517 | I21: 錨點
A22: FY2026 AI 伺服器 ÷ 營收 | C22: =PL!D100 -> 0.318 | E22: =PL!D146 -> 0.318 | G22: =PL!D192 -> 0.318 | I22: —
A23: 4Q26 EPS（模型） | C23: =Q!E13 -> 6.3102507 | E23: =Q!E13 -> 6.3102507 | G23: =Q!E13 -> 6.3102507 | I23: — | J23: 凱基 4Q26F 5.92
A24: D. 預留
A25: R4 產業部署路徑（markets/deploy_path/，尚未建立）：上線後以部署路徑取代「AI IT 資本支出 ÷ 每 GW IT 資本支出」 | J25: 預留列：本版無數值
A27: E. 目標價對帳（v0.2；模型欄為情境加權值，非情境 A）
A28: 12 個月後的前瞻 EPS（情境加權）vs 共識前瞻 EPS | B28: =cons_feps -> 21.064204 | C28: =Val!B115 -> 27.783462 | D28: =C28/B28-1 -> 0.31898941 | I28: stockanalysis 個股頁 2026-10-19：價格 239.5 ÷ Forward PE 11.37 | J28: 共識只作對帳，不作校準
A29: 目標價（DCF 與 Comparable 加權）vs 市場共識目標價 | B29: =cons_tp -> 347.45 | C29: =Val!B120 -> 339.09944 | D29: =C29/B29-1 -> -0.024033857 | I29: stockanalysis forecast 頁（S&P Global）21 位分析師平均 347.45（中位數 338.50），頁面時間 2026-10-12 | J29: 共識只作對帳，不作校準
A30: Comparable 目標價 vs 市場共識目標價 | B30: =cons_tp -> 347.45 | C30: =Val!B116 -> 409.52823 | D30: =C30/B30-1 -> 0.1786681 | I30: 同上 | J30: 共識只作對帳，不作校準

Sheet Sens
A1: Sens — 一次動一個輸入（情境 A；有效份額、其他營收毛利率在每個案例內依 FY2026 錨點重算，FY2026 恆等於錨點）：對 FY2027、FY2028 的營收、AI 伺服器營收、毛利率與 EPS 的影響。每個案例是一個完整推導區塊（本頁下方）
A3: 案例 | B3: 設定 | C3: FY2027 營收 | D3: FY2027 AI 伺服器營收 | E3: FY2027 毛利率 | F3: FY2027 EPS | G3: FY2027 EPS 相對基準 | H3: FY2028 營收 | I3: FY2028 AI 伺服器營收 | J3: FY2028 毛利率 | K3: FY2028 EPS | L3: FY2028 EPS 相對基準
A4: 基準（情境 A） | B4: PL 區塊 A | C4: =PL!E96 -> 13734.848 | D4: =PL!E89 -> 5728.1744 | E4: =PL!E108 -> 0.061581641 | F4: =PL!E117 -> 26.714691 | G4: =F4/F$4-1 -> 0 | H4: =PL!F96 -> 14777.862 | I4: =PL!F89 -> 6454.3377 | J4: =PL!F108 -> 0.064566044 | K4: =PL!F117 -> 31.417404 | L4: =K4/K$4-1 -> 0
A5: 份額流失（低） | B5: 份額相對值 2027 0.85、2028 0.75、2029 0.70（廣達、緯創搶單） | C5: =E61 -> 12875.622 | D5: =E54 -> 4868.9483 | E5: =E73 -> 0.06163922 | F5: =E82 -> 24.628001 | G5: =F5/F$4-1 -> -0.078110206 | H5: =F61 -> 13164.277 | I5: =F54 -> 4840.7533 | J5: =F73 -> 0.064191873 | K5: =F82 -> 26.933781 | L5: =K5/K$4-1 -> -0.14271146
A6: 份額上升（高） | B6: 份額相對值 1.15（Vera Rubin 市占目標五成） | C6: =E107 -> 14594.074 | D6: =E100 -> 6587.4006 | E6: =E119 -> 0.061530842 | F6: =E128 -> 28.801381 | G6: =F6/F$4-1 -> 0.078110206 | H6: =F107 -> 15746.012 | I6: =F100 -> 7422.4883 | J6: =F119 -> 0.064753737 | K6: =F128 -> 34.102675 | L6: =K6/K$4-1 -> 0.085470814
A7: 客供 0（維持買賣） | B7: 客供比例 2027–29 皆 0 | C7: =E153 -> 14371.312 | D7: =E146 -> 6364.6382 | E7: =E165 -> 0.059098828 | F7: =E174 -> 26.606163 | G7: =F7/F$4-1 -> -0.0040624726 | H7: =F153 -> 16391.446 | I7: =F146 -> 8067.9221 | J7: =F165 -> 0.058753504 | K7: =F174 -> 31.208496 | L7: =K7/K$4-1 -> -0.0066494325
A8: 客供 高 | B8: 客供比例 25%／40%／50% | C8: =E199 -> 12780.152 | D8: =E192 -> 4773.4787 | E8: =E211 -> 0.065769534 | F8: =E220 -> 26.877483 | G8: =F8/F$4-1 -> 0.0060937089 | H8: =F199 -> 13164.277 | I8: =F192 -> 4840.7533 | J8: =F211 -> 0.071803506 | K8: =F220 -> 31.654516 | L8: =K8/K$4-1 -> 0.0075471578
A9: 客供保留毛利 0.7 | B9: 客供部分只保留 70% 毛利 | C9: =E245 -> 13734.848 | D9: =E238 -> 5728.1744 | E9: =E257 -> 0.061070065 | F9: =E266 -> 26.383846 | G9: =F9/F$4-1 -> -0.012384377 | H9: =F245 -> 14777.862 | I9: =F238 -> 6454.3377 | J9: =F257 -> 0.063360618 | K9: =F266 -> 30.578636 | L9: =K9/K$4-1 -> -0.026697585
A10: 客供保留毛利 1.0 | B10: 毛利金額完全保留 | C10: =E291 -> 13734.848 | D10: =E284 -> 5728.1744 | E10: =E303 -> 0.061837429 | F10: =E312 -> 26.880113 | G10: =F10/F$4-1 -> 0.0061921884 | H10: =F291 -> 14777.862 | I10: =F284 -> 6454.3377 | J10: =F303 -> 0.065168758 | K10: =F312 -> 31.836789 | L10: =K10/K$4-1 -> 0.013348793
A11: 每 GW 價值 低 | B11: 2028–29 每 GW ODM 價值 ×0.85（Rubin Ultra 降價或客供更深） | C11: =E337 -> 13734.848 | D11: =E330 -> 5728.1744 | E11: =E349 -> 0.061581641 | F11: =E358 -> 26.714691 | G11: =F11/F$4-1 -> 0 | H11: =F337 -> 13809.711 | I11: =F330 -> 5486.187 | J11: =F349 -> 0.064352034 | K11: =F358 -> 28.704604 | L11: =K11/K$4-1 -> -0.086347053
A12: 每 GW 價值 高 | B12: ×1.2 | C12: =E383 -> 13734.848 | D12: =E376 -> 5728.1744 | E12: =E395 -> 0.061581641 | F12: =E404 -> 26.714691 | G12: =F12/F$4-1 -> 0 | H12: =F383 -> 16068.729 | I12: =F376 -> 7745.2052 | J12: =F395 -> 0.064811276 | K12: =F404 -> 35.034471 | L12: =K12/K$4-1 -> 0.1151294
A13: AI 部署 ×0.8 | B13: FY2027 起 AI IT 資本支出 ×0.8 | C13: =E429 -> 12589.213 | D13: =E422 -> 4582.5395 | E13: =E441 -> 0.061660159 | F13: =E450 -> 23.932438 | G13: =F13/F$4-1 -> -0.10414694 | H13: =F429 -> 13486.994 | I13: =F422 -> 5163.4701 | J13: =F441 -> 0.06427387 | K13: =F450 -> 27.838873 | L13: =K13/K$4-1 -> -0.11390284
A14: AI 部署 ×1.2 | B14: ×1.2 | C14: =E475 -> 14880.483 | D14: =E468 -> 6873.8093 | E14: =E487 -> 0.061515213 | F14: =E496 -> 29.496944 | G14: =F14/F$4-1 -> 0.10414694 | H14: =F475 -> 16068.729 | I14: =F468 -> 7745.2052 | J14: =F487 -> 0.064811276 | K14: =F496 -> 34.997987 | L14: =K14/K$4-1 -> 0.11396812
A15: 消費智能 低 | B15: 2027–29 −8%（iPhone 衰退） | C15: =E521 -> 13366.874 | D15: =E514 -> 5728.1744 | E15: =E533 -> 0.061564648 | F15: =E542 -> 25.795395 | G15: =F15/F$4-1 -> -0.034411618 | H15: =F521 -> 14094.768 | I15: =F514 -> 6454.3377 | J15: =F533 -> 0.064680765 | K15: =F542 -> 29.691345 | L15: =K15/K$4-1 -> -0.054939606
A16: 消費智能 高 | B16: 2027 +8%、2028–29 +6% | C16: =E567 -> 13902.109 | D16: =E560 -> 5728.1744 | E16: =E579 -> 0.061589068 | F16: =E588 -> 27.132553 | G16: =F16/F$4-1 -> 0.015641645 | H16: =F567 -> 15092.982 | I16: =F560 -> 6454.3377 | J16: =F579 -> 0.064516622 | K16: =F588 -> 32.214844 | L16: =K16/K$4-1 -> 0.025382103
A17: 雲端非 AI 低 | B17: 網通與一般伺服器 2027 0%、2028–29 −5% | C17: =E613 -> 13451.173 | D17: =E606 -> 5728.1744 | E17: =E625 -> 0.061568623 | F17: =E634 -> 26.005998 | G17: =F17/F$4-1 -> -0.026528229 | H17: =F613 -> 14164.179 | I17: =F606 -> 6454.3377 | J17: =F625 -> 0.064668603 | K17: =F634 -> 29.865077 | L17: =K17/K$4-1 -> -0.049409797
A18: 雲端非 AI 高 | B18: 2027 +25%、2028 +20%、2029 +15% | C18: =E659 -> 14042.162 | D18: =E652 -> 5728.1744 | E18: =E671 -> 0.06159515 | F18: =E680 -> 27.482442 | G18: =F18/F$4-1 -> 0.028738915 | H18: =F659 -> 15464.355 | I18: =F652 -> 6454.3377 | J18: =F671 -> 0.064460963 | K18: =F680 -> 33.157392 | L18: =K18/K$4-1 -> 0.055382927
A19: AI 毛利率差距 −1.5pt | B19: AI 毛利率（毛額基礎）比其他低 1.5 個百分點 | C19: =E705 -> 13734.848 | D19: =E698 -> 5728.1744 | E19: =E717 -> 0.060306669 | F19: =E726 -> 25.890146 | G19: =F19/F$4-1 -> -0.030864852 | H19: =F705 -> 14777.862 | I19: =F698 -> 6454.3377 | J19: =F717 -> 0.062708268 | K19: =F726 -> 30.124713 | L19: =K19/K$4-1 -> -0.041145716
A20: AI 毛利率差距 +0.5pt | B20: 高 0.5 個百分點 | C20: =E751 -> 13734.848 | D20: =E744 -> 5728.1744 | E20: =E763 -> 0.062856613 | F20: =E772 -> 27.539236 | G20: =F20/F$4-1 -> 0.030864852 | H20: =F751 -> 14777.862 | I20: =F744 -> 6454.3377 | J20: =F763 -> 0.06642382 | K20: =F772 -> 32.710096 | L20: =K20/K$4-1 -> 0.041145716
A21: VR 稀釋 −0.5pt | B21: FY2027 起 AI 毛利率（毛額基礎）−0.5 個百分點 | C21: =E797 -> 13734.848 | D21: =E790 -> 5728.1744 | E21: =E809 -> 0.060205363 | F21: =E818 -> 25.824629 | G21: =F21/F$4-1 -> -0.033317314 | H21: =F797 -> 14777.862 | I21: =F790 -> 6454.3377 | J21: =F809 -> 0.062960962 | K21: =F818 -> 30.300544 | L21: =K21/K$4-1 -> -0.035549107
A22: VR 不稀釋 | B22: FY2027 起不變 | C22: =E843 -> 13734.848 | D22: =E836 -> 5728.1744 | E22: =E855 -> 0.06249916 | F22: =E864 -> 27.308065 | G22: =F22/F$4-1 -> 0.022211543 | H22: =F843 -> 14777.862 | I22: =F836 -> 6454.3377 | J22: =F855 -> 0.0656361 | K22: =F864 -> 32.161978 | L22: =K22/K$4-1 -> 0.023699405
A23: 營業費用率 +0.2pt | B23: 營業費用額外 +0.2% × 營收 | C23: =E889 -> 13734.848 | D23: =E882 -> 5728.1744 | E23: =E901 -> 0.061581641 | F23: =E910 -> 25.421258 | G23: =F23/F$4-1 -> -0.048416531 | H23: =F889 -> 14777.862 | I23: =F882 -> 6454.3377 | J23: =F901 -> 0.064566044 | K23: =F910 -> 30.025749 | L23: =K23/K$4-1 -> -0.044295669
A24: 淨利 ÷ 營業利益 0.60 | B24: FY2027 起 0.60（業外損失擴大、稅率上升） | C24: =E935 -> 13734.848 | D24: =E928 -> 5728.1744 | E24: =E947 -> 0.061581641 | F24: =E956 -> 24.286083 | G24: =F24/F$4-1 -> -0.090909091 | H24: =F935 -> 14777.862 | I24: =F928 -> 6454.3377 | J24: =F947 -> 0.064566044 | K24: =F956 -> 28.561277 | L24: =K24/K$4-1 -> -0.090909091
A25: 淨利 ÷ 營業利益 0.73 | B25: FY2027 起 0.73（回到 FY2025） | C25: =E981 -> 13734.848 | D25: =E974 -> 5728.1744 | E25: =E993 -> 0.061581641 | F25: =E1002 -> 29.548067 | G25: =F25/F$4-1 -> 0.10606061 | H25: =F981 -> 14777.862 | I25: =F974 -> 6454.3377 | J25: =F993 -> 0.064566044 | K25: =F1002 -> 34.749553 | L25: =K25/K$4-1 -> 0.10606061
A26: 顆數情境 B | B26: CY2028 ×0.8、CY2029 ×0.85 | C26: =PL!E142 -> 13734.848 | D26: =PL!E135 -> 5728.1744 | E26: =PL!E154 -> 0.061581641 | F26: =PL!E163 -> 26.714691 | G26: =F26/F$4-1 -> 0 | H26: =PL!F142 -> 13486.994 | I26: =PL!F135 -> 5163.4701 | J26: =PL!F154 -> 0.06427387 | K26: =PL!F163 -> 27.705698 | L26: =K26/K$4-1 -> -0.11814174
A27: 顆數情境 C | B27: CY2028–29 ×0.6 | C27: =PL!E188 -> 13734.848 | D27: =PL!E181 -> 5728.1744 | E27: =PL!E200 -> 0.061581641 | F27: =PL!E209 -> 26.714691 | G27: =F27/F$4-1 -> 0 | H27: =PL!F188 -> 12196.127 | I27: =PL!F181 -> 3872.6026 | J27: =PL!F200 -> 0.063919847 | K27: =PL!F209 -> 23.59573 | L27: =K27/K$4-1 -> -0.2489599
A29: 讀法：FY2027 三情境相同；顆數情境 B、C 的差異從 FY2028 起。每個案例的 FY2026 有效份額與其他營收毛利率依該案例重算，所以 FY2026 恆等於錨點。鴻海 AI 伺服器約占營收三成，非 AI 事業（iPhone、網通、電腦）的成長率對營收影響大、對 EPS 影響小於 AI 部署與份額；淨利 ÷ 營業利益（業外、稅、少數股權）是單一最大的非營運變數。
A40: 案例區塊：份額流失（低）（情境 A）
A41: 項目 | B41: 單位 | C41: FY2025A | D41: FY2026（錨點） | E41: FY2027 | F41: FY2028 | G41: FY2029 | H41: 說明
A42: A. AI 部署與整櫃組裝市場（D 欄＝FY2026 校準年；E–G＝FY2027–FY2029；與廣達模型同口徑）
A43: AI IT 資本支出 × 情境顆數係數 | B43: US$B | D43: =itc_26*1 -> 781.87292 | E43: =itc_27*1*1 -> 1565.35 | F43: =itc_28*um28_A*1 -> 1984.2639 | G43: =itc_29*um29_A*1 -> 2260.3903
A44: 每 GW IT 資本支出 | B44: US$B | D44: =itpg_gb*(1-vr26)+itpg_vr*vr26 -> 33.414032 | E44: =itpg_vr -> 37.586352 | F44: =itpg_vr -> 37.586352 | G44: =itpg_vr -> 37.586352
A45: 部署 GW（IT 電力） | B45: GW | D45: =D43/D44 -> 23.399538 | E45: =E43/E44 -> 41.646766 | F45: =F43/F44 -> 52.792138 | G45: =G43/G44 -> 60.138592
A46: 每 GW ODM 整櫃價值 | B46: US$B/GW | D46: =(racks_gb*odm_gb*(1-vr26)+racks_vr*odm_vr*vr26)/1000 -> 27.1209 | E46: =racks_vr*odm_vr/1000 -> 27.351 | F46: =$E46*vpg_28 -> 27.351 | G46: =$E46*vpg_29 -> 27.351 | H46: 架數 × ODM 每櫃價格；含 ASIC 機架（Assumed：每 GW 價值相同）
A47: AI 伺服器組裝市場（ODM 價，美元） | B47: US$B | D47: =D45*D46 -> 634.61653 | E47: =E45*E46 -> 1139.0807 | F47: =F45*F46 -> 1443.9178 | G47: =G45*G46 -> 1644.8506
A48: AI 伺服器組裝市場（新台幣） | B48: NT$B | D48: =D47*fx -> 20307.729 | E48: =E47*fx -> 36450.582 | F48: =F47*fx -> 46205.369 | G48: =G47*fx -> 52635.22
A49: 鴻海有效份額（FY2026 校準）＝ AI 伺服器營收 ÷ 市場 | B49: % | D49: =a26_ai/D48 -> 0.17461006 | H49: Derived：分子為公司雲端網路占比 × AI 占雲端網路 × 營收（金額口徑）；分母含 ASIC、HGX 機架，所以低於整櫃櫃數份額
A50: 份額相對值（÷ FY2026） | B50: x | D50: =1 -> 1 | E50: =RLO_27 -> 0.85 | F50: =RLO_28 -> 0.75 | G50: =RLO_29 -> 0.7
A51: 鴻海有效份額 | B51: % | D51: =$D$49*D50 -> 0.17461006 | E51: =$D$49*E50 -> 0.14841855 | F51: =$D$49*F50 -> 0.13095754 | G51: =$D$49*G50 -> 0.12222704
A52: AI 伺服器毛額價值（買賣模式下的營收） | B52: NT$B | D52: =D48*D51 -> 3545.9337 | E52: =E48*E51 -> 5409.9425 | F52: =F48*F51 -> 6050.9416 | G52: =G48*G51 -> 6433.4471
A53: 客供比例（FY2027 起新增部分） | B53: % | D53: =0 -> 0 | E53: =cs_27 -> 0.1 | F53: =cs_28 -> 0.2 | G53: =cs_29 -> 0.25 | H53: FY2026 已有的半成品／客供已含在錨點與校準份額內，記為 0
A54: AI 伺服器營收 | B54: NT$B | C54: =a25_ai -> 1620.621 | D54: =D52*(1-D53) -> 3545.9337 | E54: =E52*(1-E53) -> 4868.9483 | F54: =F52*(1-F53) -> 4840.7533 | G54: =G52*(1-G53) -> 4825.0854
A55: B. 非 AI 事業（簡化成長率）與合計
A56: 雲端網路非 AI（網通、一般伺服器） | B56: NT$B | C56: =a25_cn -> 1620.621 | D56: =a26_cn -> 2363.9558 | E56: =D56*(1+g_cn27) -> 2647.6305 | F56: =E56*(1+g_cn28) -> 2859.441 | G56: =F56*(1+g_cn29) -> 3031.0074
A57: 消費智能（iPhone 等） | B57: NT$B | C57: =a25_ce -> 3079.1799 | D57: =a26_ce -> 3345.2205 | E57: =D57*(1+g_ce27) -> 3445.5771 | F57: =E57*(1+g_ce28) -> 3514.4887 | G57: =F57*(1+g_ce29) -> 3584.7784
A58: 電腦終端 | B58: NT$B | C58: =a25_pc -> 1215.4658 | D58: =a26_pc -> 1338.0882 | E58: =D58*(1+g_pc27) -> 1311.3264 | F58: =E58*(1+g_pc28) -> 1311.3264 | G58: =F58*(1+g_pc29) -> 1311.3264
A59: 元件及其他 | B59: NT$B | C59: =a25_co -> 567.21735 | D59: =a26_co -> 557.53675 | E59: =D59*(1+g_co27) -> 602.13969 | F59: =E59*(1+g_co28) -> 638.26807 | G59: =F59*(1+g_co29) -> 670.18147
A60: 非 AI 營收合計 | B60: NT$B | C60: =SUM(C56:C59) -> 6482.484 | D60: =SUM(D56:D59) -> 7604.8013 | E60: =SUM(E56:E59) -> 8006.6738 | F60: =SUM(F56:F59) -> 8323.5241 | G60: =SUM(G56:G59) -> 8597.2938
A61: 營收 | B61: NT$B | C61: =C54+C60 -> 8103.105 | D61: =D54+D60 -> 11150.735 | E61: =E54+E60 -> 12875.622 | F61: =F54+F60 -> 13164.277 | G61: =G54+G60 -> 13422.379
A62: 雲端網路產品（官方產品類別＝AI 伺服器＋雲端網路非 AI） | B62: NT$B | C62: =C54+C56 -> 3241.242 | D62: =D54+D56 -> 5909.8895 | E62: =E54+E56 -> 7516.5788 | F62: =F54+F56 -> 7700.1942 | G62: =G54+G56 -> 7856.0928 | H62: 官方四大產品類別：雲端網路產品、消費智能產品（上列「消費智能」）、電腦終端產品（「電腦終端」）、元件及其他
A63: 檢查：四大產品類別合計 − 合併營收（FY2025 實績、FY2026 錨點） | B63: NT$B | C63: =C62+C57+C58+C59-a25_rev -> 0 | D63: =D62+D57+D58+D59-a26_rev -> 0 | E63: =E62+E57+E58+E59-E61 -> 0 | F63: =F62+F57+F58+F59-F61 -> 0 | G63: =G62+G57+G58+G59-G61 -> 0
A64: 營收年增 | B64: % | D64: =D61/C61-1 -> 0.37610644 | E64: =E61/D61-1 -> 0.15468819 | F64: =F61/E61-1 -> 0.022418751 | G64: =G61/F61-1 -> 0.019606222
A65: AI 伺服器 ÷ 營收 | B65: % | C65: =C54/C61 -> 0.2 | D65: =D54/D61 -> 0.318 | E65: =E54/E61 -> 0.37815247 | F65: =F54/F61 -> 0.36771887 | G65: =G54/G61 -> 0.35948063
A66: 雲端網路產品 ÷ 營收 | B66: % | C66: =(C54+C56)/C61 -> 0.4 | D66: =(D54+D56)/D61 -> 0.53 | E66: =(E54+E56)/E61 -> 0.58378374 | F66: =(F54+F56)/F61 -> 0.58493102 | G66: =(G54+G56)/G61 -> 0.58529808
A67: 每 GW 鴻海 AI 伺服器營收 | B67: US$B/GW | D67: =D54/fx/D45 -> 4.7355819 | E67: =E54/fx/E45 -> 3.6534562 | F67: =F54/fx/F45 -> 2.8654558 | G67: =G54/fx/G45 -> 2.5072738
A68: 隱含鴻海出貨櫃數（毛額價值 ÷ ODM 每櫃價格；NVL72 等值） | B68: 千櫃 | D68: =D52/fx/(odm_gb*(1-vr26)+odm_vr*vr26) -> 24.063068 | E68: =E52/fx/odm_vr -> 25.04603 | F68: =F52/fx/odm_vr -> 28.013618 | G68: =G52/fx/odm_vr -> 29.784478 | H68: 十億美元 ÷ 百萬美元 ＝ 千櫃；FY2028 起若每 GW 價值改變，每櫃價格仍以 VR200 換算（參考）
A69: C. 損益
A70: 其他營收毛利率 ＝ 錨點毛利率 − 差距 × AI 占比（FY2026 校準） | B70: % | D70: =a26_gp/D61-d_ai*D65 -> 0.062198926 | H70: Derived：讓 FY2026 毛利率等於錨點；AI 毛利率（毛額基礎）＝其他 + 差距
A71: AI 伺服器毛利 ＝ AI 毛利率 × 毛額價值 ×（1 − 客供 ×（1 − 保留比例）） | B71: NT$B | D71: =($D$70+d_ai)*D52*(1-D53*(1-keep)) -> 202.8236 | E71: =($D$70+d_ai+vrd)*E52*(1-E53*(1-keep)) -> 295.63679 | F71: =($D$70+d_ai+vrd)*F52*(1-F53*(1-keep)) -> 327.32537 | G71: =($D$70+d_ai+vrd)*G52*(1-G53*(1-keep)) -> 346.24139 | H71: 客供部分不計營收，但大部分毛利金額保留（keep）；FY2027 起加 VR 稀釋 vrd
A72: 毛利 | B72: NT$B | C72: =a25_gp -> 498.161 | D72: =a26_gp -> 675.83407 | E72: =$D$70*E60+E71 -> 793.64329 | F72: =$D$70*F60+F71 -> 845.03963 | G72: =$D$70*G60+G71 -> 880.98382
A73: 毛利率 | B73: % | C73: =C72/C61 -> 0.061477792 | D73: =D72/D61 -> 0.060608926 | E73: =E72/E61 -> 0.06163922 | F73: =F72/F61 -> 0.064191873 | G73: =G72/G61 -> 0.065635445
A74: AI 伺服器毛利率（營收基礎） | B74: % | D74: =D71/D54 -> 0.057198926 | E74: =E71/E54 -> 0.060718818 | F74: =F71/F54 -> 0.067618684 | G74: =G71/G54 -> 0.071758604 | H74: 客供比例上升 → 營收基礎毛利率上升
A75: 營業費用（基準路徑） | B75: NT$B | C75: =a25_opx -> 238.938 | D75: =a26_opx -> 254.83042 | E75: =D75*(1+MAX(0,phi*E64)) -> 270.59813 | F75: =E75*(1+MAX(0,phi*F64)) -> 273.02471 | G75: =F75*(1+MAX(0,phi*G64)) -> 275.16591
A76: 營業費用 | B76: NT$B | C76: =C75 -> 238.938 | D76: =D75 -> 254.83042 | E76: =E75+0*E61 -> 270.59813 | F76: =F75+0*F61 -> 273.02471 | G76: =G75+0*G61 -> 275.16591
A77: 營業利益 | B77: NT$B | C77: =C72-C76 -> 259.223 | D77: =D72-D76 -> 421.00365 | E77: =E72-E76 -> 523.04517 | F77: =F72-F76 -> 572.01491 | G77: =G72-G76 -> 605.81792
A78: 營業利益率 | B78: % | C78: =C77/C61 -> 0.031990576 | D78: =D77/D61 -> 0.037755686 | E78: =E77/E61 -> 0.040622905 | F78: =F77/F61 -> 0.043452055 | G78: =G77/G61 -> 0.045134913
A79: 淨利 ÷ 營業利益 | B79: % | C79: =a25_ni/a25_oi -> 0.73046759 | D79: =a26_ni/a26_oi -> 0.65381165 | E79: =nio_f -> 0.66 | F79: =nio_f -> 0.66 | G79: =nio_f -> 0.66
A80: 歸屬母公司淨利 | B80: NT$B | C80: =a25_ni -> 189.354 | D80: =a26_ni -> 275.25709 | E80: =E77*E79 -> 345.20981 | F80: =F77*F79 -> 377.52984 | G80: =G77*G79 -> 399.83982
A81: 股數 | B81: 十億股 | C81: =a25_sh -> 13.912858 | D81: =a26_sh -> 14.016964 | E81: =D81*(1+sh_g) -> 14.016964 | F81: =E81*(1+sh_g) -> 14.016964 | G81: =F81*(1+sh_g) -> 14.016964
A82: EPS | B82: NT$ | C82: =C80/C81 -> 13.61 | D82: =D80/D81 -> 19.637425 | E82: =E80/E81 -> 24.628001 | F82: =F80/F81 -> 26.933781 | G82: =G80/G81 -> 28.525422
A83: EPS 年增 | B83: % | D83: =D82/C82-1 -> 0.44286739 | E83: =E82/D82-1 -> 0.25413595 | F83: =F82/E82-1 -> 0.093624311 | G83: =G82/F82-1 -> 0.059094625
A86: 案例區塊：份額上升（高）（情境 A）
A87: 項目 | B87: 單位 | C87: FY2025A | D87: FY2026（錨點） | E87: FY2027 | F87: FY2028 | G87: FY2029 | H87: 說明
A88: A. AI 部署與整櫃組裝市場（D 欄＝FY2026 校準年；E–G＝FY2027–FY2029；與廣達模型同口徑）
A89: AI IT 資本支出 × 情境顆數係數 | B89: US$B | D89: =itc_26*1 -> 781.87292 | E89: =itc_27*1*1 -> 1565.35 | F89: =itc_28*um28_A*1 -> 1984.2639 | G89: =itc_29*um29_A*1 -> 2260.3903
A90: 每 GW IT 資本支出 | B90: US$B | D90: =itpg_gb*(1-vr26)+itpg_vr*vr26 -> 33.414032 | E90: =itpg_vr -> 37.586352 | F90: =itpg_vr -> 37.586352 | G90: =itpg_vr -> 37.586352
A91: 部署 GW（IT 電力） | B91: GW | D91: =D89/D90 -> 23.399538 | E91: =E89/E90 -> 41.646766 | F91: =F89/F90 -> 52.792138 | G91: =G89/G90 -> 60.138592
A92: 每 GW ODM 整櫃價值 | B92: US$B/GW | D92: =(racks_gb*odm_gb*(1-vr26)+racks_vr*odm_vr*vr26)/1000 -> 27.1209 | E92: =racks_vr*odm_vr/1000 -> 27.351 | F92: =$E92*vpg_28 -> 27.351 | G92: =$E92*vpg_29 -> 27.351 | H92: 架數 × ODM 每櫃價格；含 ASIC 機架（Assumed：每 GW 價值相同）
A93: AI 伺服器組裝市場（ODM 價，美元） | B93: US$B | D93: =D91*D92 -> 634.61653 | E93: =E91*E92 -> 1139.0807 | F93: =F91*F92 -> 1443.9178 | G93: =G91*G92 -> 1644.8506
A94: AI 伺服器組裝市場（新台幣） | B94: NT$B | D94: =D93*fx -> 20307.729 | E94: =E93*fx -> 36450.582 | F94: =F93*fx -> 46205.369 | G94: =G93*fx -> 52635.22
A95: 鴻海有效份額（FY2026 校準）＝ AI 伺服器營收 ÷ 市場 | B95: % | D95: =a26_ai/D94 -> 0.17461006 | H95: Derived：分子為公司雲端網路占比 × AI 占雲端網路 × 營收（金額口徑）；分母含 ASIC、HGX 機架，所以低於整櫃櫃數份額
A96: 份額相對值（÷ FY2026） | B96: x | D96: =1 -> 1 | E96: =RHI_27 -> 1.15 | F96: =RHI_28 -> 1.15 | G96: =RHI_29 -> 1.15
A97: 鴻海有效份額 | B97: % | D97: =$D$95*D96 -> 0.17461006 | E97: =$D$95*E96 -> 0.20080157 | F97: =$D$95*F96 -> 0.20080157 | G97: =$D$95*G96 -> 0.20080157
A98: AI 伺服器毛額價值（買賣模式下的營收） | B98: NT$B | D98: =D94*D97 -> 3545.9337 | E98: =E94*E97 -> 7319.334 | F98: =F94*F97 -> 9278.1104 | G98: =G94*G97 -> 10569.235
A99: 客供比例（FY2027 起新增部分） | B99: % | D99: =0 -> 0 | E99: =cs_27 -> 0.1 | F99: =cs_28 -> 0.2 | G99: =cs_29 -> 0.25 | H99: FY2026 已有的半成品／客供已含在錨點與校準份額內，記為 0
A100: AI 伺服器營收 | B100: NT$B | C100: =a25_ai -> 1620.621 | D100: =D98*(1-D99) -> 3545.9337 | E100: =E98*(1-E99) -> 6587.4006 | F100: =F98*(1-F99) -> 7422.4883 | G100: =G98*(1-G99) -> 7926.9259
A101: B. 非 AI 事業（簡化成長率）與合計
A102: 雲端網路非 AI（網通、一般伺服器） | B102: NT$B | C102: =a25_cn -> 1620.621 | D102: =a26_cn -> 2363.9558 | E102: =D102*(1+g_cn27) -> 2647.6305 | F102: =E102*(1+g_cn28) -> 2859.441 | G102: =F102*(1+g_cn29) -> 3031.0074
A103: 消費智能（iPhone 等） | B103: NT$B | C103: =a25_ce -> 3079.1799 | D103: =a26_ce -> 3345.2205 | E103: =D103*(1+g_ce27) -> 3445.5771 | F103: =E103*(1+g_ce28) -> 3514.4887 | G103: =F103*(1+g_ce29) -> 3584.7784
A104: 電腦終端 | B104: NT$B | C104: =a25_pc -> 1215.4658 | D104: =a26_pc -> 1338.0882 | E104: =D104*(1+g_pc27) -> 1311.3264 | F104: =E104*(1+g_pc28) -> 1311.3264 | G104: =F104*(1+g_pc29) -> 1311.3264
A105: 元件及其他 | B105: NT$B | C105: =a25_co -> 567.21735 | D105: =a26_co -> 557.53675 | E105: =D105*(1+g_co27) -> 602.13969 | F105: =E105*(1+g_co28) -> 638.26807 | G105: =F105*(1+g_co29) -> 670.18147
A106: 非 AI 營收合計 | B106: NT$B | C106: =SUM(C102:C105) -> 6482.484 | D106: =SUM(D102:D105) -> 7604.8013 | E106: =SUM(E102:E105) -> 8006.6738 | F106: =SUM(F102:F105) -> 8323.5241 | G106: =SUM(G102:G105) -> 8597.2938
A107: 營收 | B107: NT$B | C107: =C100+C106 -> 8103.105 | D107: =D100+D106 -> 11150.735 | E107: =E100+E106 -> 14594.074 | F107: =F100+F106 -> 15746.012 | G107: =G100+G106 -> 16524.22
A108: 雲端網路產品（官方產品類別＝AI 伺服器＋雲端網路非 AI） | B108: NT$B | C108: =C100+C102 -> 3241.242 | D108: =D100+D102 -> 5909.8895 | E108: =E100+E102 -> 9235.0311 | F108: =F100+F102 -> 10281.929 | G108: =G100+G102 -> 10957.933 | H108: 官方四大產品類別：雲端網路產品、消費智能產品（上列「消費智能」）、電腦終端產品（「電腦終端」）、元件及其他
A109: 檢查：四大產品類別合計 − 合併營收（FY2025 實績、FY2026 錨點） | B109: NT$B | C109: =C108+C103+C104+C105-a25_rev -> 0 | D109: =D108+D103+D104+D105-a26_rev -> 0 | E109: =E108+E103+E104+E105-E107 -> 0 | F109: =F108+F103+F104+F105-F107 -> 0 | G109: =G108+G103+G104+G105-G107 -> 0
A110: 營收年增 | B110: % | D110: =D107/C107-1 -> 0.37610644 | E110: =E107/D107-1 -> 0.30879932 | F110: =F107/E107-1 -> 0.078931906 | G110: =G107/F107-1 -> 0.049422498
A111: AI 伺服器 ÷ 營收 | B111: % | C111: =C100/C107 -> 0.2 | D111: =D100/D107 -> 0.318 | E111: =E100/E107 -> 0.45137502 | F111: =F100/F107 -> 0.47138844 | G111: =G100/G107 -> 0.4797156
A112: 雲端網路產品 ÷ 營收 | B112: % | C112: =(C100+C102)/C107 -> 0.4 | D112: =(D100+D102)/D107 -> 0.53 | E112: =(E100+E102)/E107 -> 0.63279321 | F112: =(F100+F102)/F107 -> 0.65298623 | G112: =(G100+G102)/G107 -> 0.66314377
A113: 每 GW 鴻海 AI 伺服器營收 | B113: US$B/GW | D113: =D100/fx/D91 -> 4.7355819 | E113: =E100/fx/E91 -> 4.9429113 | F113: =F100/fx/F91 -> 4.3936989 | G113: =G100/fx/G91 -> 4.1190927
A114: 隱含鴻海出貨櫃數（毛額價值 ÷ ODM 每櫃價格；NVL72 等值） | B114: 千櫃 | D114: =D98/fx/(odm_gb*(1-vr26)+odm_vr*vr26) -> 24.063068 | E114: =E98/fx/odm_vr -> 33.885805 | F114: =F98/fx/odm_vr -> 42.954215 | G114: =G98/fx/odm_vr -> 48.931642 | H114: 十億美元 ÷ 百萬美元 ＝ 千櫃；FY2028 起若每 GW 價值改變，每櫃價格仍以 VR200 換算（參考）
...

Sheet Sources
A1: 來源（公司原文只經法說摘要與新聞轉述，原始簡報待人工複核；券商與資料商皆為 Interested-party）
A2: 公司（摘要）：富果 2Q26 法說摘要 2026-08-12（2Q26 與 1H26 損益、產品組合、AI 機櫃、客供、市占目標） | B2: https://blog.fugle.tw/post/earnings-call-2317-2026-08-12
A3: 公司（摘要）：鉅亨 1Q26 法說 2026-05-14（1Q26 營業利益、淨利、EPS、業外、產品組合、營收認列模式改變） | B3: https://news.cnyes.com/news/id/6458468
A4: 公司（摘要）：富果 2025 年法說 2026-03-16（2025 損益、產品組合、2026 展望、稅率） | B4: https://blog.fugle.tw/post/earnings-call-2317-2026-03-16
A5: 公司（摘要）：優分析 2025 年財報（營業利益 2,592.23 億、淨利 1,893.54 億、EPS 13.61、4Q25 業外） | B5: https://uanalyze.com.tw/articles/4369349056
A6: 公司（摘要）：優分析 2Q25 財報（AI 伺服器占雲端網路超過五成） | B6: https://uanalyze.com.tw/articles/5938328761
A7: 公司（摘要）：數位時代 2026-03-16（AI 伺服器占雲端 2023 約 22%、2024 約三成） | B7: https://www.bnext.com.tw/article/90315/2026-foxconn-earnings-call
A8: 月營收：TechNews 2026-10-05（9 月 1 兆 1,586.33 億、3Q26 3 兆 269 億、前 9 月 7 兆 6,698 億） | B8: https://finance.technews.tw/2026/10/05/2026-sep-foxconn/
A9: 月營收：TechNews 2026-09-05（8 月 9,217.66 億） | B9: https://finance.technews.tw/2026/09/05/hon-hai-2317-202608-financial-report/
A10: 月營收：優分析 2026-10-05（3Q26 3.02 兆） | B10: https://uanalyze.com.tw/articles/4830556496
A11: 券商：凱基 2026-08-12（2Q26 實績 vs 預估、2025A–2027F 損益、產品別、業外、少數股權） | B11: https://www.kgi.com.hk/zh-cn/-/media/files/kgishk/research-reports/tw-reports/hon-hai-precision-2317-tt20260812en.pdf
A12: 券商：經濟日報 2026-07-22（瑞銀 2026–27 EPS、毛利率、營益率） | B12: https://money.udn.com/money/amp/story/5607/9644763
A13: 券商：TechNews 2026-05-15（摩根士丹利 2026–28 EPS；AI 伺服器占 1Q26 雲端網路過半） | B13: https://finance.technews.tw/2026/05/15/ai-server-800g-switch-foxconn/
... A21: 資料商：Goodinfo 歷年經營績效（年底收盤、EPS） | B21: https://goodinfo.tw/tw/StockBzPerformance.asp?STOCK_ID=2317&RPT_CAT=M_YEAR
A22: 市場層：markets/network、markets/chip_bridge、tsmc、quanta 成品（本 repo，唯讀）
A23: 待補（人工）：3Q26 法說（11 月中）；AI 伺服器營收金額與占雲端網路比例；雲端網路非 AI 拆分；客供比例量化；季別業外與稅前利益；客戶占比（年報）；前瞻 P/E 十年歷史（Bloomberg）；券商共識（付費） | B23: 未找到
A24: SemiAnalysis | B24: 未使用
