Workbook

Sheet 導覽
A1: 預付款，能把 Backlog 變成現金嗎？｜Nebius 收支與評價模型 — Excel 版 v0.4（更新 2026-10-21；與 HTML v0.4 同步；市價截至 2026-10-06 收盤）
A3: 這個活頁簿在回答什麼
A4: 一句話：預付款，能把 Backlog 變成現金嗎？——Nebius 的營收＝已連網 MW × 每 MW 年收入；客戶預付款能支應多少擴張資本支出，剩下的缺口要靠多少資產擔保融資、可轉債與新股（答案見「摘要」）。
A5: 所有分頁用同一組數字，改任何一個輸入，後面全部會跟著動。
A7: 分頁結構（依模組分組，分頁標籤顏色相同者為同一模組）
A8: 摘要 一頁摘要：結論、與市場共識的差異、現價隱含什麼、驗證點（全部活公式）。
A9: 輸入與假設 所有可調參數（A 情境 → B 產能與收入 → C 利潤率 → D 支出 → E 融資 → F 評價 → G 1H 實際 → H 情境區間運算表 → I 市場共識 → J 季度追蹤輸入）。
A10: 各期收支 類現金流量：來源（含客戶預付）、用途、融資前缺口、期前融資瀑布。
A11: 季度追蹤 焦點季的模型／共識／指引／實際與差距（由年度模型拆分，只用於追蹤；實際數填在輸入與假設 J 區）。
A12: 運營_產能與收入 已連網 MW → 在役 MW → 營收（MW × 每 MW 年收入 × 利用率）；RPO 排程只作對照與產能瓶頸旗標。
A13: 資產負債_既有債務／新債與新股／租賃承諾 類資產負債表：季報債務明細、每期現金與總債務與股數、租賃承諾。
A14: 損益 類損益表（FY26＝1H 實際＋下半年模型）。
... A42: DCF 以融資後股數計每股，並加回新股募得現金的現值；EV/EBITDA 用錨定年末淨負債與錨定年末股數。

Sheet 摘要
A1: 預付款，能把 Backlog 變成現金嗎？｜一頁摘要 — 結論、與市場的差異、現價隱含什麼、驗證點（全部依輸入連動）
A2: ="模型端＝目前情境：" & CHOOSE(輸入與假設!$C$5,"保守 已簽約 3.5 GW","基準 合約 5 GW","積極 每年 >1 GW") & "（預設＝基準）；共識＝data/consensus_nbis_20261007.json（2026-10-07）" -> 模型端＝目前情境：基準 合約 5 GW（預設＝基準）；共識＝data/consensus_nbis_20261007.json（2026-10-07）
A4: 1｜結論
A5: 結論｜評等代碼（1＝買進、0＝中立、−1＝賣出） | C5: =評價_DCF與目標價!C76 -> -1
A6: 結論｜評等 | C6: =CHOOSE(C5+2,"賣出","中立","買進") -> 賣出
A7: 結論｜點位（加權目標價） | B7: US$ | C7: =評價_DCF與目標價!C49 -> 22.032804
A8: 結論｜現價 | B8: US$ | C8: =輸入與假設!$C$125 -> 249.87
A9: 結論｜空間 | B9: % | C9: =C7/C8-1 -> -0.91182293
A10: 結論｜情境區間（下緣／上緣） | B10: US$ | C10: =評價_DCF與目標價!C81 -> 20.398771 | D10: =評價_DCF與目標價!D81 -> 29.693039
A11: 結論｜方法區間（下緣／上緣） | B11: US$ | C11: =評價_DCF與目標價!C83 -> 13.403619 | D11: =評價_DCF與目標價!D83 -> 22.032804
A12: 結論｜賣出門檻價 | B12: US$ | C12: =評價_DCF與目標價!$C$77 -> 212.3895
A13: 結論｜點位 − 賣出門檻 | B13: US$ | C13: =C7-C12 -> -190.3567
A14: 結論｜結論句 | C14: =C6&"：點位 $"&TEXT(C7,"0.0")&"，較現價 $"&TEXT(C8,"0.00")&" "&IF(C9>=0,"高","低")&" "&TEXT(ABS(C9)*100,"0")&"%；情境區間 $"&TEXT(C10,"0.0")&"–$"&TEXT(D10,"0.0")&"，方法區間 $"&TEXT(C11,"0.0")&"–$"&TEXT(D11,"0.0")&"；點位"&IF(C13<0,"低於","高於")&"賣出門檻 $"&TEXT(C12,"0.0")&" 達 $"&TEXT(ABS(C13),"0.0")&"。" -> 賣出：點位 $22.0，較現價 $249.87 低 91%；情境區間 $20.4–$29.7，方法區間 $13.4–$22.0；點位低於賣出門檻 $212.4 達 $190.4。
A15: 結論｜情境判斷句 | C15: =評價_DCF與目標價!C89 -> 情境區間上緣 $29.7 低於現價 $249.87：賣出在三個擴張情境下都成立。
A17: 2｜與市場的差異（模型：目前情境 vs 共識；FY26–FY28）
A18: 項目 | B18: 單位 | C18: FY26 | D18: FY27 | E18: FY28
A19: 差異｜營收｜模型 | B19: US$bn | C19: =損益!C26 -> 2.3394994 | D19: =損益!D26 -> 5.9751652 | E19: =損益!E26 -> 13.139778
A20: 差異｜營收｜共識 | B20: US$bn | C20: =輸入與假設!$C$229 -> 3.379 | D20: =輸入與假設!$D$229 -> 11.418 | E20: =輸入與假設!$E$229 -> 21.458
A21: 差異｜營收｜差距 | B21: % | C21: =C19/C20-1 -> -0.30763556 | D21: =D19/D20-1 -> -0.47668898 | E21: =E19/E20-1 -> -0.3876513
A22: 差異｜調整後 EBITDA｜模型 | B22: US$bn | C22: =輸入與假設!$C$198+損益!C19 -> 0.94672512 | D22: =損益!D31 -> 2.7883247 | E22: =損益!E31 -> 6.2590829
A23: 差異｜調整後 EBITDA｜共識 | B23: US$bn | C23: =輸入與假設!$C$230 -> 1.338 | D23: =輸入與假設!$D$230 -> 6.194 | E23: =輸入與假設!$E$230 -> 13.404
A24: 差異｜調整後 EBITDA｜差距 | B24: % | C24: =C22/C23-1 -> -0.29243265 | D24: =D22/D23-1 -> -0.54983456 | E24: =E22/E23-1 -> -0.53304365 | I24: FY26 模型＝1H 實際調整後 EBITDA（輸入與假設 G 區，報導轉述 [Verified]）＋2H 模型
A25: 差異｜調整後 EBITDA｜差距（金額） | B25: US$bn | C25: =C22-C23 -> -0.39127488 | D25: =D22-D23 -> -3.4056753 | E25: =E22-E23 -> -7.1449171 | I25: 與 HTML 一頁摘要、市場共識分頁同一呈現；判斷門檻仍用上一列比例
A26: 差異｜EBITDA 率｜模型 | B26: % | C26: =C22/C19 -> 0.40466995 | D26: =D22/D19 -> 0.46665233 | E26: =E22/E19 -> 0.47634615
A27: 差異｜EBITDA 率｜共識 | B27: % | C27: =輸入與假設!$C$231 -> 0.396 | D27: =輸入與假設!$D$231 -> 0.542 | E27: =輸入與假設!$E$231 -> 0.625
A28: 差異｜EBITDA 率｜差距（百分點） | B28: pt | C28: =C26-C27 -> 0.0086699498 | D28: =D26-D27 -> -0.075347674 | E28: =E26-E27 -> -0.14865385 | I28: EBITDA 率以百分點列差距，不納入判斷
A29: 差異｜CapEx（毛額）｜模型 | B29: US$bn | C29: =輸入與假設!$C$182+輸入與假設!C$91 -> 26.04619 | D29: =輸入與假設!D$91 -> 27.597437 | E29: =輸入與假設!E$91 -> 29.148684
A30: 差異｜CapEx（毛額）｜共識 | B30: US$bn | C30: =輸入與假設!$C$235 -> 22.489 | D30: =輸入與假設!$D$235 -> 27.243 | E30: =輸入與假設!$E$235 -> 38.39
A31: 差異｜CapEx（毛額）｜差距 | B31: % | C31: =C29/C30-1 -> 0.15817466 | D31: =D29/D30-1 -> 0.013010206 | E31: =E29/E30-1 -> -0.24072195 | I31: 共識 CapEx 口徑未揭露；FY26＝1H 實際毛額＋2H 模型毛額
A32: 差異｜淨負債｜模型 | B32: US$bn | C32: =資產負債_新債與新股!C24 -> 4.4901304 | D32: =資產負債_新債與新股!D24 -> 16.684069 | E32: =資產負債_新債與新股!E24 -> 21.684069
A33: 差異｜淨負債｜共識 | B33: US$bn | C33: =輸入與假設!$C$237 -> 15.446 | D33: =輸入與假設!$D$237 -> 31.876 | E33: =輸入與假設!$E$237 -> 38.685
A34: 差異｜淨負債｜差距 | B34: % | C34: =C32/C33-1 -> -0.70930141 | D34: =D32/D33-1 -> -0.47659465 | E34: =E32/E33-1 -> -0.43947088 | I34: 共識淨負債不含租賃、口徑未揭露：只列不判斷
A35: 差異｜淨負債｜差距（金額） | B35: US$bn | C35: =C32-C33 -> -10.95587 | D35: =D32-D33 -> -15.191931 | E35: =E32-E33 -> -17.000931 | I35: 與 HTML 一頁摘要、市場共識分頁同一呈現；判斷門檻仍用上一列比例
A36: 差異｜分歧項目（超過門檻者） | C36: =MID(IF(ABS(C21)>輸入與假設!$C$274,"、營收 "&IF(C21<0,"−","+")&TEXT(ABS(C21)*100,"0.0")&"%","")&IF(ABS(C24)>輸入與假設!$C$274,"、EBITDA "&IF(C25<0,"−","+")&"$"&TEXT(ABS(C25),"#,##0.00")&"bn"&"／"&IF(C28<0,"−","+")&TEXT(ABS(C28)*100,"0.0")&"pt","")&IF(ABS(C31)>輸入與假設!$C$274,"、CapEx "&IF(C31<0,"−","+")&TEXT(ABS(C31)*100,"0.0")&"%",""),2,999) -> 營收 −30.8%、EBITDA −$0.39bn／+0.9pt、CapEx +15.8% | D36: =MID(IF(ABS(D21)>輸入與假設!$C$274,"、營收 "&IF(D21<0,"−","+")&TEXT(ABS(D21)*100,"0.0")&"%","")&IF(ABS(D24)>輸入與假設!$C$274,"、EBITDA "&IF(D25<0,"−","+")&"$"&TEXT(ABS(D25),"#,##0.00")&"bn"&"／"&IF(D28<0,"−","+")&TEXT(ABS(D28)*100,"0.0")&"pt","")&IF(ABS(D31)>輸入與假設!$C$274,"、CapEx "&IF(D31<0,"−","+")&TEXT(ABS(D31)*100,"0.0")&"%",""),2,999) -> 營收 −47.7%、EBITDA −$3.41bn／−7.5pt | E36: =MID(IF(ABS(E21)>輸入與假設!$C$274,"、營收 "&IF(E21<0,"−","+")&TEXT(ABS(E21)*100,"0.0")&"%","")&IF(ABS(E24)>輸入與假設!$C$274,"、EBITDA "&IF(E25<0,"−","+")&"$"&TEXT(ABS(E25),"#,##0.00")&"bn"&"／"&IF(E28<0,"−","+")&TEXT(ABS(E28)*100,"0.0")&"pt","")&IF(ABS(E31)>輸入與假設!$C$274,"、CapEx "&IF(E31<0,"−","+")&TEXT(ABS(E31)*100,"0.0")&"%",""),2,999) -> 營收 −38.8%、EBITDA −$7.14bn／−14.9pt、CapEx −24.1% | I36: 營收、EBITDA、CapEx 任一項差距絕對值超過門檻即列出（與 HTML 判斷句同一規則）
A37: 差異｜分歧起始年（1＝FY26…3＝FY28；0＝無） | C37: =IF(C36<>"",1,IF(D36<>"",2,IF(E36<>"",3,0))) -> 1
A38: 差異｜判斷句 | C38: =CHOOSE(C37+1,"FY26–FY28 營收、EBITDA、CapEx 與共識差距皆在 "&IF(ROUND(ABS(輸入與假設!$C$274)*100,4)=INT(ROUND(ABS(輸入與假設!$C$274)*100,4)),TEXT(ROUND(ABS(輸入與假設!$C$274)*100,4),"0"),TEXT(ROUND(ABS(輸入與假設!$C$274)*100,4),"0.0"))&"%"&" 以內。","分歧始於 FY26（"&C36&"）"&"；FY27 "&IF(D36="","回到 "&IF(ROUND(ABS(輸入與假設!$C$274)*100,4)=INT(ROUND(ABS(輸入與假設!$C$274)*100,4)),TEXT(ROUND(ABS(輸入與假設!$C$274)*100,4),"0"),TEXT(ROUND(ABS(輸入與假設!$C$274)*100,4),"0.0"))&"%"&" 以內",D36)&"；FY28 "&IF(E36="","回到 "&IF(ROUND(ABS(輸入與假設!$C$274)*100,4)=INT(ROUND(ABS(輸入與假設!$C$274)*100,4)),TEXT(ROUND(ABS(輸入與假設!$C$274)*100,4),"0"),TEXT(ROUND(ABS(輸入與假設!$C$274)*100,4),"0.0"))&"%"&" 以內",E36)&"。","FY26 營收、EBITDA、CapEx 與共識差距在 "&IF(ROUND(ABS(輸入與假設!$C$274)*100,4)=INT(ROUND(ABS(輸入與假設!$C$274)*100,4)),TEXT(ROUND(ABS(輸入與假設!$C$274)*100,4),"0"),TEXT(ROUND(ABS(輸入與假設!$C$274)*100,4),"0.0"))&"%"&" 以內；分歧始於 FY27（"&D36&"）"&"；FY28 "&IF(E36="","回到 "&IF(ROUND(ABS(輸入與假設!$C$274)*100,4)=INT(ROUND(ABS(輸入與假設!$C$274)*100,4)),TEXT(ROUND(ABS(輸入與假設!$C$274)*100,4),"0"),TEXT(ROUND(ABS(輸入與假設!$C$274)*100,4),"0.0"))&"%"&" 以內",E36)&"。","FY26–FY27 營收、EBITDA、CapEx 與共識差距在 "&IF(ROUND(ABS(輸入與假設!$C$274)*100,4)=INT(ROUND(ABS(輸入與假設!$C$274)*100,4)),TEXT(ROUND(ABS(輸入與假設!$C$274)*100,4),"0"),TEXT(ROUND(ABS(輸入與假設!$C$274)*100,4),"0.0"))&"%"&" 以內；分歧始於 FY28（"&E36&"）。") -> 分歧始於 FY26（營收 −30.8%、EBITDA −$0.39bn／+0.9pt、CapEx +15.8%）；FY27 營收 −47.7%、EBITDA −$3.41bn／−7.5pt；FY28 營收 −38.8%、EBITDA −$7.14bn／−14.9pt、CapEx −24.1%。
A39: 差異原因｜FY26｜營收 | C39: =IF(ABS(C21)>輸入與假設!$C$274,"觀點","") -> 觀點 | D39: =IF(ABS(C21)>輸入與假設!$C$274,"營收＝可計費 MW × 每 MW 年收入（Tokenomics 錨 × 定價倍數 k；v0.2a）；首期以最新季實際營收年化校準期初可計費 MW，可計費 MW 依爬坡係數（60%／80%／100%）收斂到已連網 MW（v0.1c）；年底已連網 "&IF((輸入與假設!C$39)<0,"−","")&TEXT(ABS((輸入與假設!C$39)),"#,##0")&" MW（目前情境）；共識未揭露 MW 假設","") -> 營收＝可計費 MW × 每 MW 年收入（Tokenomics 錨 × 定價倍數 k；v0.2a）；首期以最新季實際營收年化校準期初可計費 MW，可計費 MW 依爬坡係數（60%／80%／100%）收斂到已連網 MW（v0.1c）；年底已連網 750 MW（目前情境）；共識未揭露 MW 假設 | I39: C＝類型、D＝原因（需附原因時顯示；EBITDA 以利潤率差、其餘以比例門檻判斷）
A40: 差異原因｜FY26｜EBITDA | C40: =IF(ABS(C28)>輸入與假設!$C$275,"觀點","") | D40: =IF(ABS(C28)>輸入與假設!$C$275,"營收差距 "&IF((C21)<0,"−","+")&TEXT(ABS((C21))*100,"#,##0.0")&"%"&"；EBITDA 率 "&IF((C26)<0,"−","")&TEXT(ABS((C26))*100,"#,##0.0")&"%"&" 對共識 "&IF((C27)<0,"−","")&TEXT(ABS((C27))*100,"#,##0.0")&"%"&"（模型由 "&IF((輸入與假設!$C$50)<0,"−","")&TEXT(ABS((輸入與假設!$C$50))*100,"#,##0")&"%"&" 走向穩態 "&IF((輸入與假設!$C$51)<0,"−","")&TEXT(ABS((輸入與假設!$C$51))*100,"#,##0")&"%"&"，取可觀察 neocloud 區間）","")
A41: 差異原因｜FY26｜CapEx | C41: =IF(ABS(C31)>輸入與假設!$C$274,"觀點","") -> 觀點 | D41: =IF(ABS(C31)>輸入與假設!$C$274,"CapEx 依新增 MW 計算：新增 "&IF((輸入與假設!C$84)<0,"−","")&TEXT(ABS((輸入與假設!C$84)),"#,##0")&" MW × 每 MW $"&IF((輸入與假設!C$69)<0,"−","")&TEXT(ABS((輸入與假設!C$69)),"#,##0")&"m（含次年預建）；共識口徑未揭露","") -> CapEx 依新增 MW 計算：新增 580 MW × 每 MW $45m（含次年預建）；共識口徑未揭露
A42: 差異原因｜FY26｜淨負債 | C42: =IF(ABS(C34)>輸入與假設!$C$274,"觀點","") -> 觀點 | D42: =IF(ABS(C34)>輸入與假設!$C$274,"淨負債隨 CapEx、客戶預付與融資需求而定（模型 CapEx 差距 "&IF((C31)<0,"−","+")&TEXT(ABS((C31))*100,"#,##0.0")&"%"&"）；共識淨負債口徑未揭露","") -> 淨負債隨 CapEx、客戶預付與融資需求而定（模型 CapEx 差距 +15.8%）；共識淨負債口徑未揭露
A43: 差異原因｜FY27｜營收 | C43: =IF(ABS(D21)>輸入與假設!$C$274,"觀點","") -> 觀點 | D43: =IF(ABS(D21)>輸入與假設!$C$274,"營收＝可計費 MW × 每 MW 年收入（Tokenomics 錨 × 定價倍數 k；v0.2a）；首期以最新季實際營收年化校準期初可計費 MW，可計費 MW 依爬坡係數（60%／80%／100%）收斂到已連網 MW（v0.1c）；年底已連網 "&IF((輸入與假設!D$39)<0,"−","")&TEXT(ABS((輸入與假設!D$39)),"#,##0")&" MW（目前情境）；共識未揭露 MW 假設","") -> 營收＝可計費 MW × 每 MW 年收入（Tokenomics 錨 × 定價倍數 k；v0.2a）；首期以最新季實際營收年化校準期初可計費 MW，可計費 MW 依爬坡係數（60%／80%／100%）收斂到已連網 MW（v0.1c）；年底已連網 1,330 MW（目前情境）；共識未揭露 MW 假設
A44: 差異原因｜FY27｜EBITDA | C44: =IF(ABS(D28)>輸入與假設!$C$275,"觀點","") -> 觀點 | D44: =IF(ABS(D28)>輸入與假設!$C$275,"營收差距 "&IF((D21)<0,"−","+")&TEXT(ABS((D21))*100,"#,##0.0")&"%"&"；EBITDA 率 "&IF((D26)<0,"−","")&TEXT(ABS((D26))*100,"#,##0.0")&"%"&" 對共識 "&IF((D27)<0,"−","")&TEXT(ABS((D27))*100,"#,##0.0")&"%"&"（模型由 "&IF((輸入與假設!$C$50)<0,"−","")&TEXT(ABS((輸入與假設!$C$50))*100,"#,##0")&"%"&" 走向穩態 "&IF((輸入與假設!$C$51)<0,"−","")&TEXT(ABS((輸入與假設!$C$51))*100,"#,##0")&"%"&"，取可觀察 neocloud 區間）","") -> 營收差距 −47.7%；EBITDA 率 46.7% 對共識 54.2%（模型由 50% 走向穩態 47%，取可觀察 neocloud 區間）
A45: 差異原因｜FY27｜CapEx | C45: =IF(ABS(D31)>輸入與假設!$C$274,"觀點","") | D45: =IF(ABS(D31)>輸入與假設!$C$274,"CapEx 依新增 MW 計算：新增 "&IF((輸入與假設!D$84)<0,"−","")&TEXT(ABS((輸入與假設!D$84)),"#,##0")&" MW × 每 MW $"&IF((輸入與假設!D$69)<0,"−","")&TEXT(ABS((輸入與假設!D$69)),"#,##0")&"m（含次年預建）；共識口徑未揭露","")
A46: 差異原因｜FY27｜淨負債 | C46: =IF(ABS(D34)>輸入與假設!$C$274,"觀點","") -> 觀點 | D46: =IF(ABS(D34)>輸入與假設!$C$274,"淨負債隨 CapEx、客戶預付與融資需求而定（模型 CapEx 差距 "&IF((D31)<0,"−","+")&TEXT(ABS((D31))*100,"#,##0.0")&"%"&"）；共識淨負債口徑未揭露","") -> 淨負債隨 CapEx、客戶預付與融資需求而定（模型 CapEx 差距 +1.3%）；共識淨負債口徑未揭露
A47: 差異原因｜FY28｜營收 | C47: =IF(ABS(E21)>輸入與假設!$C$274,"觀點","") -> 觀點 | D47: =IF(ABS(E21)>輸入與假設!$C$274,"營收＝可計費 MW × 每 MW 年收入（Tokenomics 錨 × 定價倍數 k；v0.2a）；首期以最新季實際營收年化校準期初可計費 MW，可計費 MW 依爬坡係數（60%／80%／100%）收斂到已連網 MW（v0.1c）；年底已連網 "&IF((輸入與假設!E$39)<0,"−","")&TEXT(ABS((輸入與假設!E$39)),"#,##0")&" MW（目前情境）；共識未揭露 MW 假設","") -> 營收＝可計費 MW × 每 MW 年收入（Tokenomics 錨 × 定價倍數 k；v0.2a）；首期以最新季實際營收年化校準期初可計費 MW，可計費 MW 依爬坡係數（60%／80%／100%）收斂到已連網 MW（v0.1c）；年底已連網 1,910 MW（目前情境）；共識未揭露 MW 假設
A48: 差異原因｜FY28｜EBITDA | C48: =IF(ABS(E28)>輸入與假設!$C$275,"觀點","") -> 觀點 | D48: =IF(ABS(E28)>輸入與假設!$C$275,"營收差距 "&IF((E21)<0,"−","+")&TEXT(ABS((E21))*100,"#,##0.0")&"%"&"；EBITDA 率 "&IF((E26)<0,"−","")&TEXT(ABS((E26))*100,"#,##0.0")&"%"&" 對共識 "&IF((E27)<0,"−","")&TEXT(ABS((E27))*100,"#,##0.0")&"%"&"（模型由 "&IF((輸入與假設!$C$50)<0,"−","")&TEXT(ABS((輸入與假設!$C$50))*100,"#,##0")&"%"&" 走向穩態 "&IF((輸入與假設!$C$51)<0,"−","")&TEXT(ABS((輸入與假設!$C$51))*100,"#,##0")&"%"&"，取可觀察 neocloud 區間）","") -> 營收差距 −38.8%；EBITDA 率 47.6% 對共識 62.5%（模型由 50% 走向穩態 47%，取可觀察 neocloud 區間）
A49: 差異原因｜FY28｜CapEx | C49: =IF(ABS(E31)>輸入與假設!$C$274,"觀點","") -> 觀點 | D49: =IF(ABS(E31)>輸入與假設!$C$274,"CapEx 依新增 MW 計算：新增 "&IF((輸入與假設!E$84)<0,"−","")&TEXT(ABS((輸入與假設!E$84)),"#,##0")&" MW × 每 MW $"&IF((輸入與假設!E$69)<0,"−","")&TEXT(ABS((輸入與假設!E$69)),"#,##0")&"m（含次年預建）；共識口徑未揭露","") -> CapEx 依新增 MW 計算：新增 580 MW × 每 MW $50m（含次年預建）；共識口徑未揭露
A50: 差異原因｜FY28｜淨負債 | C50: =IF(ABS(E34)>輸入與假設!$C$274,"觀點","") -> 觀點 | D50: =IF(ABS(E34)>輸入與假設!$C$274,"淨負債隨 CapEx、客戶預付與融資需求而定（模型 CapEx 差距 "&IF((E31)<0,"−","+")&TEXT(ABS((E31))*100,"#,##0.0")&"%"&"）；共識淨負債口徑未揭露","") -> 淨負債隨 CapEx、客戶預付與融資需求而定（模型 CapEx 差距 −24.1%）；共識淨負債口徑未揭露
A51: 差異｜需附原因項數 | C51: =SUMPRODUCT(--(ABS(C21:E21)>輸入與假設!$C$274))+SUMPRODUCT(--(ABS(C28:E28)>輸入與假設!$C$275))+SUMPRODUCT(--(ABS(C31:E31)>輸入與假設!$C$274))+SUMPRODUCT(--(ABS(C34:E34)>輸入與假設!$C$274)) -> 10 | I51: 營收、EBITDA（利潤率差）、CapEx、淨負債 × FY26–FY28
A52: 差異｜差異原因摘要 | C52: =IF(C51=0,"","需附原因的 "&C51&" 項差距："&MID(IF((COUNTIF(C39,"觀點")+COUNTIF(C40,"觀點")+COUNTIF(C41,"觀點")+COUNTIF(C42,"觀點")+COUNTIF(C43,"觀點")+COUNTIF(C44,"觀點")+COUNTIF(C45,"觀點")+COUNTIF(C46,"觀點")+COUNTIF(C47,"觀點")+COUNTIF(C48,"觀點")+COUNTIF(C49,"觀點")+COUNTIF(C50,"觀點"))>0,"、觀點 "&(COUNTIF(C39,"觀點")+COUNTIF(C40,"觀點")+COUNTIF(C41,"觀點")+COUNTIF(C42,"觀點")+COUNTIF(C43,"觀點")+COUNTIF(C44,"觀點")+COUNTIF(C45,"觀點")+COUNTIF(C46,"觀點")+COUNTIF(C47,"觀點")+COUNTIF(C48,"觀點")+COUNTIF(C49,"觀點")+COUNTIF(C50,"觀點"))&" 項","")&IF((COUNTIF(C39,"拆法")+COUNTIF(C40,"拆法")+COUNTIF(C41,"拆法")+COUNTIF(C42,"拆法")+COUNTIF(C43,"拆法")+COUNTIF(C44,"拆法")+COUNTIF(C45,"拆法")+COUNTIF(C46,"拆法")+COUNTIF(C47,"拆法")+COUNTIF(C48,"拆法")+COUNTIF(C49,"拆法")+COUNTIF(C50,"拆法"))>0,"、拆法 "&(COUNTIF(C39,"拆法")+COUNTIF(C40,"拆法")+COUNTIF(C41,"拆法")+COUNTIF(C42,"拆法")+COUNTIF(C43,"拆法")+COUNTIF(C44,"拆法")+COUNTIF(C45,"拆法")+COUNTIF(C46,"拆法")+COUNTIF(C47,"拆法")+COUNTIF(C48,"拆法")+COUNTIF(C49,"拆法")+COUNTIF(C50,"拆法"))&" 項","")&IF((COUNTIF(C39,"已知限制")+COUNTIF(C40,"已知限制")+COUNTIF(C41,"已知限制")+COUNTIF(C42,"已知限制")+COUNTIF(C43,"已知限制")+COUNTIF(C44,"已知限制")+COUNTIF(C45,"已知限制")+COUNTIF(C46,"已知限制")+COUNTIF(C47,"已知限制")+COUNTIF(C48,"已知限制")+COUNTIF(C49,"已知限制")+COUNTIF(C50,"已知限制"))>0,"、已知限制 "&(COUNTIF(C39,"已知限制")+COUNTIF(C40,"已知限制")+COUNTIF(C41,"已知限制")+COUNTIF(C42,"已知限制")+COUNTIF(C43,"已知限制")+COUNTIF(C44,"已知限制")+COUNTIF(C45,"已知限制")+COUNTIF(C46,"已知限制")+COUNTIF(C47,"已知限制")+COUNTIF(C48,"已知限制")+COUNTIF(C49,"已知限制")+COUNTIF(C50,"已知限制"))&" 項","")&IF((C51-((COUNTIF(C39,"觀點")+COUNTIF(C40,"觀點")+COUNTIF(C41,"觀點")+COUNTIF(C42,"觀點")+COUNTIF(C43,"觀點")+COUNTIF(C44,"觀點")+COUNTIF(C45,"觀點")+COUNTIF(C46,"觀點")+COUNTIF(C47,"觀點")+COUNTIF(C48,"觀點")+COUNTIF(C49,"觀點")+COUNTIF(C50,"觀點"))+(COUNTIF(C39,"拆法")+COUNTIF(C40,"拆法")+COUNTIF(C41,"拆法")+COUNTIF(C42,"拆法")+COUNTIF(C43,"拆法")+COUNTIF(C44,"拆法")+COUNTIF(C45,"拆法")+COUNTIF(C46,"拆法")+COUNTIF(C47,"拆法")+COUNTIF(C48,"拆法")+COUNTIF(C49,"拆法")+COUNTIF(C50,"拆法"))+(COUNTIF(C39,"已知限制")+COUNTIF(C40,"已知限制")+COUNTIF(C41,"已知限制")+COUNTIF(C42,"已知限制")+COUNTIF(C43,"已知限制")+COUNTIF(C44,"已知限制")+COUNTIF(C45,"已知限制")+COUNTIF(C46,"已知限制")+COUNTIF(C47,"已知限制")+COUNTIF(C48,"已知限制")+COUNTIF(C49,"已知限制")+COUNTIF(C50,"已知限制"))))>0,"、未歸類 "&(C51-((COUNTIF(C39,"觀點")+COUNTIF(C40,"觀點")+COUNTIF(C41,"觀點")+COUNTIF(C42,"觀點")+COUNTIF(C43,"觀點")+COUNTIF(C44,"觀點")+COUNTIF(C45,"觀點")+COUNTIF(C46,"觀點")+COUNTIF(C47,"觀點")+COUNTIF(C48,"觀點")+COUNTIF(C49,"觀點")+COUNTIF(C50,"觀點"))+(COUNTIF(C39,"拆法")+COUNTIF(C40,"拆法")+COUNTIF(C41,"拆法")+COUNTIF(C42,"拆法")+COUNTIF(C43,"拆法")+COUNTIF(C44,"拆法")+COUNTIF(C45,"拆法")+COUNTIF(C46,"拆法")+COUNTIF(C47,"拆法")+COUNTIF(C48,"拆法")+COUNTIF(C49,"拆法")+COUNTIF(C50,"拆法"))+(COUNTIF(C39,"已知限制")+COUNTIF(C40,"已知限制")+COUNTIF(C41,"已知限制")+COUNTIF(C42,"已知限制")+COUNTIF(C43,"已知限制")+COUNTIF(C44,"已知限制")+COUNTIF(C45,"已知限制")+COUNTIF(C46,"已知限制")+COUNTIF(C47,"已知限制")+COUNTIF(C48,"已知限制")+COUNTIF(C49,"已知限制")+COUNTIF(C50,"已知限制"))))&" 項",""),2,999)&"；原因見「損益與評價 → 市場共識」。") -> 需附原因的 10 項差距：觀點 10 項；原因見「損益與評價 → 市場共識」。 | I52: 與 HTML 一頁摘要同一句
A54: 3｜現價隱含什麼
A55: 隱含｜共識平均目標價隱含 FY28 EV/EBITDA | B55: x | C55: =(輸入與假設!$C$209*輸入與假設!$C$126+輸入與假設!$E$237)/輸入與假設!$E$230 -> 9.6413081 | I55: ＝（共識平均目標價 × 股數＋共識 FY28 淨負債）÷ 共識 FY28 調整後 EBITDA
A56: 隱含｜現價隱含 FY28 EV/EBITDA | B56: x | C56: =(輸入與假設!$C$125*輸入與假設!$C$126+輸入與假設!$E$237)/輸入與假設!$E$230 -> 8.8382939 | I56: 同一共識 FY28 數字，價格換成現價
A57: 隱含｜模型方法區間上緣 | B57: x | C57: =MAX(輸入與假設!$C$146,輸入與假設!$C$147) -> 6 | I57: 模型 EV/EBITDA 腿錨定 FY29 並折回 2027-06-30，錨定年度與此不同
A58: 隱含｜隱含倍數句 | C58: ="共識平均目標價 $"&TEXT(輸入與假設!$C$209,"0.00")&" 隱含 FY28 EV/EBITDA "&TEXT(C55,"0.0")&"x，"&IF(ROUND(C55,1)>C57,"高於",IF(ROUND(C55,1)<C57,"低於","等於"))&"模型方法區間上緣 "&IF(C57=INT(C57),TEXT(C57,"0"),TEXT(C57,"0.0"))&"x；現價 $"&TEXT(輸入與假設!$C$125,"0.00")&" 隱含 "&TEXT(C56,"0.0")&"x。" -> 共識平均目標價 $283.58 隱含 FY28 EV/EBITDA 9.6x，高於模型方法區間上緣 6x；現價 $249.87 隱含 8.8x。
A59: 反向 DCF｜FY30 每 MW 年收入（目前／隱含／變動） | C59: =評價_反向DCF!B18 -> 10.3953 | D59: =評價_反向DCF!C18 -> 31.7846 | E59: =評價_反向DCF!D18 -> 2.0576 | I59: 快照（預設輸入）：見『評價_反向DCF』；改輸入後請以目標搜尋重算
A60: 反向 DCF｜每 MW 建置成本（目前／隱含／變動） | C60: =評價_反向DCF!B19 -> 50.2564 | D60: =評價_反向DCF!C19 -> 無解 | E60: =評價_反向DCF!D19 -> —
A61: 反向 DCF｜穩態 EBITDA 率（目前／隱含／變動 pt） | C61: =評價_反向DCF!B20 -> 0.47 | D61: =評價_反向DCF!C20 -> 無解 | E61: =評價_反向DCF!D20 -> —
A62: 反向 DCF｜加權目標價＝現價所需每 MW 年收入（目前／隱含／變動） | C62: =評價_反向DCF!B21 -> 10.3953 | D62: =評價_反向DCF!C21 -> 29.1587 | E62: =評價_反向DCF!D21 -> 1.805
A64: 4｜驗證點與市場看法（賣方與管理層數字標記 Interested-party）
A65: 驗證｜焦點季 | C65: =季度追蹤!C12 -> Q3'26 | I65: 『輸入與假設』J 區選擇；季度層由年度模型拆分，只用於追蹤
A66: 驗證｜營收（模型／共識／指引低／指引高／實際） | B66: US$bn | C66: =季度追蹤!C6 -> 0.64683314 | D66: =季度追蹤!D6 -> 0.8994 | E66: =季度追蹤!F6 -> 不適用 | F66: =季度追蹤!G6 -> 不適用 | G66: =季度追蹤!I6 -> 待公布 | I66: 共識、指引為 Interested-party
A67: 驗證｜營收｜句 | C67: =INDEX(季度追蹤!$C$124:$H$124,輸入與假設!$C$280) -> 營收：模型 $0.65bn｜共識 $0.90bn（−28.1%）〔觀點〕
A68: 驗證｜調整後 EBITDA（模型／共識／指引低／指引高／實際） | B68: US$bn | C68: =季度追蹤!C7 -> 0.27267199 | D68: =季度追蹤!D7 -> 0.3624 | E68: =季度追蹤!F7 -> 不適用 | F68: =季度追蹤!G7 -> 不適用 | G68: =季度追蹤!I7 -> 待公布 | I68: 共識、指引為 Interested-party
A69: 驗證｜調整後 EBITDA｜句 | C69: =INDEX(季度追蹤!$C$125:$H$125,輸入與假設!$C$280) -> 調整後 EBITDA：模型 $0.27bn｜共識 $0.36bn（−$0.09bn／+1.9pt）
A70: 驗證｜CapEx（毛額）（模型／共識／指引低／指引高／實際） | B70: US$bn | C70: =季度追蹤!C10 -> 8.957945 | D70: =季度追蹤!D10 -> 不適用 | E70: =季度追蹤!F10 -> 不適用 | F70: =季度追蹤!G10 -> 不適用 | G70: =季度追蹤!I10 -> 待公布 | I70: 共識、指引為 Interested-party
A71: 驗證｜CapEx（毛額）｜句 | C71: =INDEX(季度追蹤!$C$128:$H$128,輸入與假設!$C$280) -> CapEx（毛額）：模型 $8.96bn
A72: 驗證｜評等分布（強力買進／買進／持有／賣出／強力賣出） | B72: 家 | C72: =輸入與假設!$C$222 -> 4 | D72: =輸入與假設!$C$223 -> 1 | E72: =輸入與假設!$C$224 -> 3 | F72: =輸入與假設!$C$225 -> 0 | G72: =輸入與假設!$C$226 -> 1 | I72: 2026-09，合計 9 家 [Interested-party]
A73: 驗證｜目標價（平均／中位數／最低／最高） | B73: US$ | C73: =輸入與假設!$C$209 -> 283.58 | D73: =輸入與假設!$C$210 -> 300 | E73: =輸入與假設!$C$211 -> 84 | F73: =輸入與假設!$C$212 -> 415 | I73: 19 家；S&P Global Market Intelligence（經 StockAnalysis.com），擷取 2026-10-07 [Interested-party]
A75: 來源獨立性：StockAnalysis.com 的目標價、評等、營收預估引用 S&P Global Market Intelligence；MarketScreener 的年度與季度預估一般亦引用 S&P Capital IQ（同 CRWV 共識檔的判斷），FY26 營收兩者 3.34 對 3.379 接近，視為同一底層來源的兩個呈現，不算獨立交叉驗證。MarketBeat 的目標價與評等為 MarketBeat 自行彙整（獨立於 S&P），可作目標價的獨立交叉。Zacks（經 AP／WTOP）只取得 Q2 2026 財報前的單季營收共識，僅供量級確認。
A76: 共識來源：MarketScreener（S&P Capital IQ 系共識）、S&P Global Market Intelligence（經 StockAnalysis.com）；擷取 2026-10-07。逐筆來源、日期與標記見『輸入與假設』I 區。

Sheet 輸入與假設
A1: 輸入（依類別排序；點左側 ＋／− 展開或收合。藍字可改；黃底為最關鍵假設）
A2: A 情境 → B 產能與收入 → C 利潤率 → D 支出（CapEx／折舊／租賃／JV）→ E 融資 → F 評價 → G 參考：1H26 實際 → H 情境區間運算表 → I 市場共識 → J 季度追蹤輸入。灰底『▸』為明細子區，預設收合
A4: A｜情境與規模（管理層擴張力道）
A5: 情境選擇（1＝保守 已簽約 3.5 GW、2＝基準 合約 5 GW、3＝積極 每年 >1 GW） | C5: 2 | D5: =CHOOSE(C5,"保守 已簽約 3.5 GW","基準 合約 5 GW","積極 每年 >1 GW") -> 基準 合約 5 GW | E5: 價格情境（1 低／2 基準／3 高） | F5: 2 | G5: =CHOOSE(F5,"價格低","價格基準","價格高") -> 價格基準 | I5: 三情境只改擴張力道（已連網 MW 路徑）；每 MW 年收入由同列 E–G 欄價格情境（定價倍數 k）決定，兩條軸分離（v0.2a）。E–G 欄＝價格情境選擇（定價倍數 k 低／基準／高；k_長約 與 k_現貨 同時取低／基準／高，見『每MW收入_錨定』A 區），三個容量情境預設都用基準
A6: ▸ 情境路徑明細（已連網 MW、在役比例、表外租金基準）
A7: 已連網 MW 路徑 | B7: 單位 | C7: FY26 | D7: FY27 | E7: FY28 | F7: FY29 | G7: FY30 | I7: FY31 新增 MW
A8: 首期期末已連網 MW（三情境共用） | B8: MW | C8: 750 | I8: 2026 年底 connected 目標 0.8–1.0 GW 中點 ÷ PUE 1.2 [Interested-party／Derived]
A9: 保守 已簽約 3.5 GW｜合約 MW 上限 | B9: MW | C9: 2917 | D9: 2917 | E9: 2917 | F9: 2917 | G9: 2917 | I9: company.json → scenarios.mwPath.contracted
A10: 保守 已簽約 3.5 GW｜併網速度 | B10: MW／年 | C10: 580 | I10: company.json → scenarios.mwPath.pace
A11: 保守 已簽約 3.5 GW | B11: MW | C11: =MIN(C9,輸入與假設!$C$8) -> 750 | D11: =MIN(D9,C11+輸入與假設!$C$10*D$37) -> 1330 | E11: =MIN(E9,D11+輸入與假設!$C$10*E$37) -> 1910 | F11: =MIN(F9,E11+輸入與假設!$C$10*F$37) -> 2490 | G11: =MIN(G9,F11+輸入與假設!$C$10*G$37) -> 2917 | I11: 0 | J11: 只交付已簽約電力（>3.5 GW ÷1.2＝2,917 MW-IT），依歷史併網速度；I 欄＝FY31 新增 MW
A12: 基準 合約 5 GW｜合約 MW 上限 | B12: MW | C12: 4167 | D12: 4167 | E12: 4167 | F12: 4167 | G12: 4167 | I12: company.json → scenarios.mwPath.contracted
A13: 基準 合約 5 GW｜併網速度 | B13: MW／年 | C13: 580 | I13: company.json → scenarios.mwPath.pace
A14: 基準 合約 5 GW | B14: MW | C14: =MIN(C12,輸入與假設!$C$8) -> 750 | D14: =MIN(D12,C14+輸入與假設!$C$13*D$37) -> 1330 | E14: =MIN(E12,D14+輸入與假設!$C$13*E$37) -> 1910 | F14: =MIN(F12,E14+輸入與假設!$C$13*F$37) -> 2490 | G14: =MIN(G12,F14+輸入與假設!$C$13*G$37) -> 3070 | I14: 580 | J14: 2026 年底 5 GW 合約目標（÷1.2＝4,167 MW-IT）依歷史併網速度實現；I 欄＝FY31 新增 MW
A15: 積極 每年 >1 GW｜合約 MW 上限 | B15: MW | C15: 4167 | D15: 5000 | E15: 5833 | F15: 6667 | G15: 7500 | I15: company.json → scenarios.mwPath.contracted
A16: 積極 每年 >1 GW｜併網速度 | B16: MW／年 | C16: 833 | I16: company.json → scenarios.mwPath.pace
A17: 積極 每年 >1 GW | B17: MW | C17: =MIN(C15,輸入與假設!$C$8) -> 750 | D17: =MIN(D15,C17+輸入與假設!$C$16*D$37) -> 1583 | E17: =MIN(E15,D17+輸入與假設!$C$16*E$37) -> 2416 | F17: =MIN(F15,E17+輸入與假設!$C$16*F$37) -> 3249 | G17: =MIN(G15,F17+輸入與假設!$C$16*G$37) -> 4082 | I17: 833 | J17: 2027 起每年部署 >1 GW 全數實現（÷1.2＝833 MW-IT／年）；I 欄＝FY31 新增 MW
A18: 每 MW 年收入｜保守 已簽約 3.5 GW | B18: US$bn/MW | C18: =每MW收入_錨定!C63/1000 -> 0.0091925511 | D18: =每MW收入_錨定!D63/1000 -> 0.0096218441 | E18: =每MW收入_錨定!E63/1000 -> 0.010018893 | F18: =每MW收入_錨定!F63/1000 -> 0.010264054 | G18: =每MW收入_錨定!G63/1000 -> 0.010381213 | I18: ＝『每MW收入_錨定』Tokenomics 錨（IF_HoldEcon，在役世代加權）× 定價倍數 k（目前價格情境）÷ 1000 [Derived]；v0.2 舊值見該頁對照列
A19: 每 MW 年收入｜基準 合約 5 GW | B19: US$bn/MW | C19: =每MW收入_錨定!C93/1000 -> 0.0091925511 | D19: =每MW收入_錨定!D93/1000 -> 0.0096218441 | E19: =每MW收入_錨定!E93/1000 -> 0.010018893 | F19: =每MW收入_錨定!F93/1000 -> 0.010264054 | G19: =每MW收入_錨定!G93/1000 -> 0.0103953 | I19: ＝『每MW收入_錨定』Tokenomics 錨（IF_HoldEcon，在役世代加權）× 定價倍數 k（目前價格情境）÷ 1000 [Derived]；v0.2 舊值見該頁對照列
A20: 每 MW 年收入｜積極 每年 >1 GW | B20: US$bn/MW | C20: =每MW收入_錨定!C123/1000 -> 0.0091925511 | D20: =每MW收入_錨定!D123/1000 -> 0.0096978896 | E20: =每MW收入_錨定!E123/1000 -> 0.010112516 | F20: =每MW收入_錨定!F123/1000 -> 0.010354202 | G20: =每MW收入_錨定!G123/1000 -> 0.010476675 | I20: ＝『每MW收入_錨定』Tokenomics 錨（IF_HoldEcon，在役世代加權）× 定價倍數 k（目前價格情境）÷ 1000 [Derived]；v0.2 舊值見該頁對照列
A21: 在役／已連網比例 | B21: % | C21: 0.75 | D21: 0.85 | E21: 0.9 | F21: 0.9 | G21: 0.9 | I21: 三情境共用；新連網產能自驗收到可計費需數季 [Assumed]
A22: 可計費爬坡係數 | B22: % | C22: 0.6 | D22: 0.8 | E22: 1 | F22: 1 | G22: 1 | I22: v0.1c 首期營收校準：可計費 MW＝已連網 × 在役比例 × 爬坡係數，逐步收斂（60%／80%／100%）；60% 為能讓基準 FY26 落入公司指引的保守值 [Assumed]
A23: 表外現金租金（積極路徑） | B23: US$bn | C23: 0.05 | D23: 0.5 | E23: 1 | F23: 1 | G23: 1 | I23: 已簽約未起租租賃的現金路徑；其他情境依 MW 比例縮放（起算 0 MW）
A24: 表外租金起算 MW | B24: MW | C24: 0 | I24: 表外租金依超過此值的 MW 等比例縮放（company.json → scenarios.leaseRampFloorMw）
A25: B｜產能與收入（MW、每 MW 年收入、利用率、信用；RPO 只作對照）
A26: 6/30 RPO | B26: US$bn | C26: 37.4906 | I26: 季報 RPO 37.4906（只作對照與債務上限的 backlog）[Interested-party]
A27: Q3 初新增承諾 | B27: US$bn | C27: 0 | I27: 評價日後新簽、尚未進 RPO 的承諾；未揭露，取 0 [Assumed]
A28: 五期認列比例（至 2030 末） | B28: % | C28: 0.82 | I28: 季報桶 36／40／24（後段假設 49–72 個月）線性分攤後五期合計 82% [Derived]
A29: RPO 桶權重合計 | B29: % | C29: 0.82 | I29: 下方權重列的合計，用於歸一化
A30: 2025-12-31 主動電力 | B30: MW | C30: 170 | I30: Q4 2025 股東信與 20-F：active power 約 170 MW（IT 口徑）[Interested-party]
A31: 最新已申報季營收（單季） | B31: US$bn | C31: 0.5823 | I31: 期初可計費 MW 校準用：季報營收 [Interested-party]（company.json → latestQuarter.revenue）
A32: 6/30 Billable MW | B32: MW | C32: =ROUND(輸入與假設!$C$31*4/C42,0) -> 253 | I32: v0.1c 校準：＝最新季營收 × 4 ÷ 首期每 MW 年收入（對齊已實現年化營收；季末在役 MW 未揭露，不用內插值）[Derived]
A33: 收入用平均在役 MW（1=是） | C33: 1 | I33: 0＝用期末存量全期化；建議 1
A34: 營收驅動（mw＝MW × 每 MW 年收入；rpo＝RPO 排程） | C34: mw | I34: mw：新產能簽約率固定 100%，營收＝容量上限；RPO 只作對照與產能瓶頸旗標（company.json → defaults.revenueDriver）
A35: 每 MW 年收入倍數（整體） | B35: % | C35: 1 | I35: 反向 DCF 與壓力測試用；預設 100%。以『目標搜尋』調整此格即可反解市價隱含單價
A36: 項目 | B36: 單位 | C36: FY26 | D36: FY27 | E36: FY28 | F36: FY29 | G36: FY30 | I36: 來源／標籤
A37: 模型期長度（年） | C37: 0.5 | D37: 1 | E37: 1 | F37: 1 | G37: 1 | I37: 勿改。由 calendar_q.py 推算；只用於容量上限、電力、維護等年率換算 [Derived]
A38: RPO 桶權重 | B38: % | C38: 0.09 | D38: 0.18 | E38: 0.19 | F38: 0.2 | G38: 0.16 | H38: =SUM(C38:G38) -> 0.82 | I38: 季報 36%／24m、40%／25-48m、24%／之後（假設 49–72m）桶內線性分攤 [Derived]
A39: Accepted MW（期末主動電力） | B39: MW | C39: =CHOOSE(輸入與假設!$C$5,C11,C14,C17) -> 750 | D39: =CHOOSE(輸入與假設!$C$5,D11,D14,D17) -> 1330 | E39: =CHOOSE(輸入與假設!$C$5,E11,E14,E17) -> 1910 | F39: =CHOOSE(輸入與假設!$C$5,F11,F14,F17) -> 2490 | G39: =CHOOSE(輸入與假設!$C$5,G11,G14,G17) -> 3070 | I39: ＝依 A 區情境選擇器（已連網 MW-IT）
A40: Billable MW | B40: MW | C40: =ROUND(C39*C21*C22,0) -> 338 | D40: =ROUND(D39*D21*D22,0) -> 904 | E40: =ROUND(E39*E21*E22,0) -> 1719 | F40: =ROUND(F39*F21*F22,0) -> 2241 | G40: =ROUND(G39*G21*G22,0) -> 2763 | I40: ＝已連網 × 在役比例 × 爬坡係數（A 區）
A41: 利用率 | B41: % | C41: 1 | D41: 1 | E41: 1 | F41: 1 | G41: 1 | I41: 100%：按 MW-year 計價，收入取決於簽約率與爬坡（可計費 MW），不再乘 Tokenomics IF_Util（下游資料契約第 3 條；重複扣減禁止）[Derived]
A42: 每 MW 年收入 | B42: US$bn/MW | C42: =CHOOSE(輸入與假設!$C$5,C18,C19,C20) -> 0.0091925511 | D42: =CHOOSE(輸入與假設!$C$5,D18,D19,D20) -> 0.0096218441 | E42: =CHOOSE(輸入與假設!$C$5,E18,E19,E20) -> 0.010018893 | F42: =CHOOSE(輸入與假設!$C$5,F18,F19,F20) -> 0.010264054 | G42: =CHOOSE(輸入與假設!$C$5,G18,G19,G20) -> 0.0103953 | I42: ＝依 A 區情境選擇器（Tokenomics 錨 × 定價倍數 k；『每MW收入_錨定』）
A43: 新產能簽約率 | B43: % | C43: 1 | D43: 1 | E43: 1 | F43: 1 | G43: 1 | I43: MW 驅動：100%（RPO 只作對照）
A44: 客戶違約率 | B44: % | C44: 0.005 | D44: 0.01 | E44: 0.015 | F44: 0.02 | G44: 0.025 | I44: 前三大客戶約 59% 營收的定價，非預測 [Assumed]
A45: 回收率 | B45: % | C45: 0.5 | D45: 0.5 | E45: 0.5 | F45: 0.5 | G45: 0.5 | I45: [Assumed]
A46: 非算力服務營收 | B46: US$bn | C46: 0 | D46: 0 | E46: 0 | F46: 0 | G46: 0 | I46: 預設 0：AI cloud 軟體已含在每 MW 年收入；其他事業另列 [Assumed]
A47: 其他事業 EBITDA（Avride＋TripleTen） | B47: US$bn | C47: -0.094 | D47: -0.141 | E47: -0.094 | F47: -0.047 | G47: 0 | I47: 其他事業（Avride＋TripleTen）EBITDA：上半年 −0.094 × 2＝−0.188／年，各期＝−0.188 × 期間長度 × 線性遞減（首期 100%、FY27 75%、FY28 50%、FY29 25%、FY30 0%）；假設處分或自給 [Derived／Assumed]
A49: C｜利潤率（EBITDA 率單一來源；損益與資金共用）
A50: 起始 EBITDA 率（FY26） | B50: % | C50: 0.497 | I50: 季報 AI cloud 分部調整後 EBITDA 率 49.7%（Q2）[Interested-party]
A51: 穩態 EBITDA 率（FY30） | B51: % | C51: 0.47 | I51: 可觀察 neocloud 區間 IREN 約 35%／CRWV 約 59% 的中點 47%；不取自每 MW 推導路徑 A 的加成 [Analogy]
A52: 項目 | B52: 單位 | C52: FY26 | D52: FY27 | E52: FY28 | F52: FY29 | G52: FY30 | I52: 來源／標籤
A53: EBITDA 率 | B53: % | C53: =輸入與假設!$C$50+(輸入與假設!$C$51-輸入與假設!$C$50)*0/4 -> 0.497 | D53: =輸入與假設!$C$50+(輸入與假設!$C$51-輸入與假設!$C$50)*1/4 -> 0.49025 | E53: =輸入與假設!$C$50+(輸入與假設!$C$51-輸入與假設!$C$50)*2/4 -> 0.4835 | F53: =輸入與假設!$C$50+(輸入與假設!$C$51-輸入與假設!$C$50)*3/4 -> 0.47675 | G53: =輸入與假設!$C$50+(輸入與假設!$C$51-輸入與假設!$C$50)*4/4 -> 0.47 | I53: ＝起始＋(穩態−起始)×期數÷4（公式）
A54: 非算力服務現金 | B54: US$bn | C54: =輸入與假設!C$46*運營_產能與收入!C36 -> 0 | D54: =輸入與假設!D$46*運營_產能與收入!D36 -> 0 | E54: =輸入與假設!E$46*運營_產能與收入!E36 -> 0 | F54: =輸入與假設!F$46*運營_產能與收入!F36 -> 0 | G54: =輸入與假設!G$46*運營_產能與收入!G36 -> 0 | I54: ＝服務營收 × EBITDAR 率（公式）
A55: ▸ 電力／維護 overlay（預設關閉；EBITDA 已含電費）
A56: 電力／維護 overlay（1=開） | C56: 0 | I56: EBITDA 率已含電費，開啟會重複扣除，僅供壓力測試
A57: 電價 | B57: $/MWh | C57: 60 | D57: 62 | E57: 64 | F57: 66 | G57: 68 | I57: overlay 用 [Assumed]
A58: PUE | C58: 1.2 | D58: 1.2 | E58: 1.2 | F58: 1.2 | G58: 1.2 | I58: overlay 用 [Assumed]
A59: 維護成本 | B59: US$m/MW | C59: 0.15 | D59: 0.15 | E59: 0.16 | F59: 0.16 | G59: 0.17 | I59: overlay 用 [Assumed]
A61: D｜支出（CapEx、車隊折舊、租賃、JV）
A62: 提前支出比例 λ | B62: % | C62: 0.35 | I62: 次年才上線的 MW，其建置支出落在前一年的比例 [Assumed]
A63: FY31 新增 MW（FY30 預建用） | B63: MW | C63: =CHOOSE(輸入與假設!$C$5,I11,I14,I17) -> 580 | I63: 隨情境：保守 0／基準 500／積極 1,000 [Assumed]
A64: FY26 CapEx 下限（已承諾） | B64: US$bn | C64: 20 | I64: 全年指引下緣（法說會轉述）：當年支出多已下單 [Interested-party]
A65: GPU 經濟壽命（年） | B65: 年 | C65: 5 | I65: 公司 2026 起伺服器與網通設備折舊年限 5 年（Tokenomics 6 年）；取較保守者 [Interested-party]
A66: 6/30 毛 PP&E | B66: US$bn | C66: 14.1495 | I66: 季報毛額（含尚未啟用資產 7.8364）[Interested-party]
A67: 每 MW 建置成本倍數（整體） | B67: % | C67: 1 | I67: 同時影響 CapEx、汰換與車隊折舊；反向 DCF 用；預設 100%
A68: 項目 | B68: 單位 | C68: FY26 | D68: FY27 | E68: FY28 | F68: FY29 | G68: FY30 | I68: 來源／標籤
A69: 每 MW 建置成本 | B69: US$m/MW | C69: =每MW收入_錨定!C24*TK_CapexTotal_H100+每MW收入_錨定!C25*TK_CapexTotal_GB200+每MW收入_錨定!C26*TK_CapexTotal_GB300+每MW收入_錨定!C27*TK_CapexTotal_VR200 -> 44.907224 | D69: =每MW收入_錨定!D24*TK_CapexTotal_H100+每MW收入_錨定!D25*TK_CapexTotal_GB200+每MW收入_錨定!D26*TK_CapexTotal_GB300+每MW收入_錨定!D27*TK_CapexTotal_VR200 -> 47.581788 | E69: =每MW收入_錨定!E24*TK_CapexTotal_H100+每MW收入_錨定!E25*TK_CapexTotal_GB200+每MW收入_錨定!E26*TK_CapexTotal_GB300+每MW收入_錨定!E27*TK_CapexTotal_VR200 -> 50.256352 | F69: =每MW收入_錨定!F24*TK_CapexTotal_H100+每MW收入_錨定!F25*TK_CapexTotal_GB200+每MW收入_錨定!F26*TK_CapexTotal_GB300+每MW收入_錨定!F27*TK_CapexTotal_VR200 -> 50.256352 | G69: =每MW收入_錨定!G24*TK_CapexTotal_H100+每MW收入_錨定!G25*TK_CapexTotal_GB200+每MW收入_錨定!G26*TK_CapexTotal_GB300+每MW收入_錨定!G27*TK_CapexTotal_VR200 -> 50.256352 | I69: Σ 新增世代占比（『每MW收入_錨定』B 區）× Tokenomics IF_CapexTotal｜世代（TK_CapexTotal_*；IT 設備＋廠房，Nebius 自建）[Derived]
A70: 每 MW 建置成本（v0.3 舊值，對照） | B70: US$m/MW | C70: 50.12 | D70: 50.26 | E70: 50.26 | F70: 50.26 | G70: 50.26 | I70: v0.3 寫死值（Tokenomics v5.27：GB300 50.12、VR200 50.26；FY27 起全取 VR200，未依新增組合加權）；v0.4a 起只作對照，不入模型 [Derived]
A71: 有預付的合約比例 | B71: % | C71: 0.7 | I71: 股東信：約 70% 合約含客戶預付 [Interested-party]
A72: 預付占相關資本支出比 | B72: % | C72: 0.55 | I72: 股東信：預付覆蓋相關資本支出 50–60%，取中點 [Interested-party]
A73: 預付認列年數 | B73: 年 | C73: 3 | I73: 季報：遞延營收預計 1–5 年內認列，取中點 3 年；自下一期起依期初合約負債直線認列 [Interested-party]
A74: 6/30 合約負債（客戶預付餘額） | B74: US$bn | C74: 5.9752 | I74: 季報遞延營收 5.9752（流動 0.979＋非流動 4.996）[Interested-party]
A75: 項目 | B75: 單位 | C75: FY26 | D75: FY27 | E75: FY28 | F75: FY29 | G75: FY30 | I75: 來源／標籤
A76: 客戶預付占毛 CapEx | B76: % | C76: =輸入與假設!$C$71*輸入與假設!$C$72 -> 0.385 | D76: =輸入與假設!$C$71*輸入與假設!$C$72 -> 0.385 | E76: =輸入與假設!$C$71*輸入與假設!$C$72 -> 0.385 | F76: =輸入與假設!$C$71*輸入與假設!$C$72 -> 0.385 | G76: =輸入與假設!$C$71*輸入與假設!$C$72 -> 0.385 | I76: ＝有預付的合約比例 × 預付占相關資本支出比；乘成長型 CapEx 得預付流入
A77: 在帳現金租金（季報到期表） | B77: US$bn | C77: 0.0916 | D77: 0.2352 | E77: 0.2342 | F77: 0.2414 | G77: 0.2427 | I77: 營業＋融資租賃未折現付款；2030 後尚有 1.13 [Verified]
A78: 表外現金租金（未起租） | B78: US$bn | C78: =C23*MAX(0,C39-輸入與假設!$C$24)/(C17-輸入與假設!$C$24) -> 0.05 | D78: =D23*MAX(0,D39-輸入與假設!$C$24)/(D17-輸入與假設!$C$24) -> 0.42008844 | E78: =E23*MAX(0,E39-輸入與假設!$C$24)/(E17-輸入與假設!$C$24) -> 0.79056291 | F78: =F23*MAX(0,F39-輸入與假設!$C$24)/(F17-輸入與假設!$C$24) -> 0.76638966 | G78: =G23*MAX(0,G39-輸入與假設!$C$24)/(G17-輸入與假設!$C$24) -> 0.75208231 | I78: ＝積極路徑 × MW 比例（A 區）[Derived]
A79: JV 已承諾餘額出資 | B79: US$bn | C79: 0 | D79: 0 | E79: 0 | F79: 0 | G79: 0 | I79: 季報未揭露 JV 出資承諾（不適用）
A80: JV 後續增資＋策略投資 | B80: US$bn | C80: 0 | D80: 0 | E80: 0 | F80: 0 | G80: 0 | I80: 收購與策略投資，未揭露計畫 [Assumed]
A81: JV／策略投資出資 | B81: US$bn | C81: =C79+C80 -> 0 | D81: =D79+D80 -> 0 | E81: =E79+E80 -> 0 | F81: =F79+F80 -> 0 | G81: =G79+G80 -> 0 | I81: ＝已承諾餘額＋後續增資
A82: ▸ CapEx 推導明細（由 Accepted MW 連動）
A83: 期初主動電力 | B83: MW | C83: =輸入與假設!$C$30 -> 170 | D83: =C39 -> 750 | E83: =D39 -> 1330 | F83: =E39 -> 1910 | G83: =F39 -> 2490 | I83: FY26 期初＝2025 年底 170 MW
A84: 本期新增 MW | B84: MW | C84: =C39-C83 -> 580 | D84: =D39-D83 -> 580 | E84: =E39-E83 -> 580 | F84: =F39-F83 -> 580 | G84: =G39-G83 -> 580
A85: 次期新增 MW | B85: MW | C85: =D39-C39 -> 580 | D85: =E39-D39 -> 580 | E85: =F39-E39 -> 580 | F85: =G39-F39 -> 580 | G85: =輸入與假設!$C$63 -> 580
A86: 全年毛 CapEx（公式） | B86: US$bn | C86: =(C84*(1-輸入與假設!$C$62)+C85*輸入與假設!$C$62)*C69*輸入與假設!$C$67/1000 -> 26.04619 | D86: =(D84*(1-輸入與假設!$C$62)+D85*輸入與假設!$C$62)*D69*輸入與假設!$C$67/1000 -> 27.597437 | E86: =(E84*(1-輸入與假設!$C$62)+E85*輸入與假設!$C$62)*E69*輸入與假設!$C$67/1000 -> 29.148684 | F86: =(F84*(1-輸入與假設!$C$62)+F85*輸入與假設!$C$62)*F69*輸入與假設!$C$67/1000 -> 29.148684 | G86: =(G84*(1-輸入與假設!$C$62)+G85*輸入與假設!$C$62)*G69*輸入與假設!$C$67/1000 -> 29.148684 | I86: ＝(本期新增×(1−λ)＋次期新增×λ)×每 MW 成本
A87: 成長型 CapEx（模型期） | B87: US$bn | C87: =MAX(C86,輸入與假設!$C$64)-輸入與假設!$C$182 -> 17.91589 | D87: =D86 -> 27.597437 | E87: =E86 -> 29.148684 | F87: =F86 -> 29.148684 | G87: =G86 -> 29.148684 | I87: FY26＝MAX(全年公式, 下限) − 1H 已認列 8.1303
A88: GPU 汰換 CapEx | B88: US$bn | C88: =IF(2026-輸入與假設!$C$65=2025,輸入與假設!$C$30,0)*C69*輸入與假設!$C$67/1000 -> 0 | D88: =IF(2027-輸入與假設!$C$65=2025,輸入與假設!$C$30,0)*D69*輸入與假設!$C$67/1000 -> 0 | E88: =IF(2028-輸入與假設!$C$65=2025,輸入與假設!$C$30,0)*E69*輸入與假設!$C$67/1000 -> 0 | F88: =IF(2029-輸入與假設!$C$65=2025,輸入與假設!$C$30,0)*F69*輸入與假設!$C$67/1000 -> 0 | G88: =IF(2030-輸入與假設!$C$65=2025,輸入與假設!$C$30,0)*G69*輸入與假設!$C$67/1000 -> 8.5435798 | I88: ＝(本年 − 壽命) 那年新增的 MW × 每 MW 成本；取代已折舊完的設備
A89: 期初毛 PP&E | B89: US$bn | C89: =輸入與假設!$C$66 -> 14.1495 | D89: =C89+C87 -> 32.06539 | E89: =D89+D87 -> 59.662827 | F89: =E89+E87 -> 88.811511 | G89: =F89+F87 -> 117.9602 | I89: 之後＝前期期初＋前期成長型 CapEx（汰換不增加基礎）
A90: ▸ CapEx 與折舊（結果；下游引用）
A91: 毛 CapEx（模型期，下游引用此列） | B91: US$bn | C91: =C87+C88 -> 17.91589 | D91: =D87+D88 -> 27.597437 | E91: =E87+E88 -> 29.148684 | F91: =F87+F88 -> 29.148684 | G91: =G87+G88 -> 37.692264 | I91: ＝成長型＋汰換
A92: D&A（車隊折舊） | B92: US$bn | C92: =(C89+0.5*C87)/輸入與假設!$C$65*C37 -> 2.3107445 | D92: =(D89+0.5*D87)/輸入與假設!$C$65*D37 -> 9.1728217 | E92: =(E89+0.5*E87)/輸入與假設!$C$65*E37 -> 14.847434 | F92: =(F89+0.5*F87)/輸入與假設!$C$65*F37 -> 20.677171 | G92: =(G89+0.5*G87)/輸入與假設!$C$65*G37 -> 26.506907 | I92: ＝(期初毛 PP&E＋本期成長型×½)÷壽命×期間長度
A94: E｜融資（期初現金、既有債務、瀑布參數）
A95: 期初現金（2026-06-30） | B95: US$bn | C95: 8.0421 | I95: 季報現金 8.0421；受限現金 1.056 不計 [Interested-party]
A96: 股權／可轉債金額 | B96: US$bn | C96: 5.68 | I96: 2026-08 可轉債 $5.75B 淨額約 5.68（超額配售全數行使）[Interested-party]
A97: 計入股權／可轉債（1=是） | C97: 1 | I97: 關閉則首期少 5.68bn 來源
A98: 未動用信用額度 | B98: US$bn | C98: 0.775 | I98: 資產擔保定期貸款 $775M（2026-07-10 簽約，SOFR＋2.50%）[Interested-party]
A99: 瀑布可動用未動用額度（1=是） | C99: 1 | I99: 瀑布第一順位；已承諾額度，不受 債務／backlog 上限限制
A100: 債務排程攤還（1=開） | C100: 1 | I100: 季報到期表；關閉＝假設全額再融資
A101: 債務／backlog 上限 | B101: x | C101: 0.5 | I101: 資產擔保融資容量：總債務 ≤ 此倍數 × backlog；評價日實際約 0.27x，預設 0.5x [Assumed]
A102: 新簽合約年期 | B102: 年 | C102: 3 | I102: 股東信：核心合約 1–3 年、長約 5 年；取 3 年 [Assumed]
A103: 最低現金 | B103: US$bn | C103: 2 | I103: 期前融資的現金底線 [Assumed]
A104: 股權發行價 | B104: US$ | C104: 249.87 | I104: 預設＝現價（2026-10-06 收盤）[Verified]
...

Sheet 各期收支
A1: 支出與資金 — 五層支出、四層來源、現金橋
A2: FY26 欄＝1H 實際（季報現金流量表口徑）＋下半年模型；FY27 以後為純模型。瀑布以「融資前現金」決定需求並直接由各支出列加總，因此沒有循環參照
A4: 項目 | B4: 單位 | C4: FY26 | D4: FY27 | E4: FY28 | F4: FY29 | G4: FY30 | I4: 公式／來源說明
A5: 支出（五層）
A6: ① 毛 CapEx（認列，備忘） | B6: US$bn | C6: =輸入與假設!$C$182+輸入與假設!C$91 -> 26.04619 | D6: =輸入與假設!D$91 -> 27.597437 | E6: =輸入與假設!E$91 -> 29.148684 | F6: =輸入與假設!F$91 -> 29.148684 | G6: =輸入與假設!G$91 -> 37.692264 | I6: FY26＝1H 實際認列 8.1303＋2H 模型；對照公司全年指引 20–25。備忘列：用途合計採現金口徑，不用這一列
A7: 客戶預付率 | B7: % | C7: =輸入與假設!C$76 -> 0.385 | D7: =輸入與假設!D$76 -> 0.385 | E7: =輸入與假設!E$76 -> 0.385 | F7: =輸入與假設!F$76 -> 0.385 | G7: =輸入與假設!G$76 -> 0.385
A8: 客戶預付金額（抵減，2H 起） | B8: US$bn | C8: =輸入與假設!C$87*C7 -> 6.8976176 | D8: =輸入與假設!D$87*D7 -> 10.625013 | E8: =輸入與假設!E$87*E7 -> 11.222243 | F8: =輸入與假設!F$87*F7 -> 11.222243 | G8: =輸入與假設!G$87*G7 -> 11.222243 | I8: ＝成長型 CapEx × 預付比率（汰換 CapEx 不計）；1H 的預付已含在實際 CFO 內，不重複計入
A9: 合約負債期初（客戶預付餘額） | B9: US$bn | C9: =輸入與假設!$C$74 -> 5.9752 | D9: =C11 -> 11.876951 | E9: =D11 -> 18.542981 | F9: =E11 -> 23.58423 | G9: =F11 -> 26.945064 | I9: FY26 期初＝6/30 季報遞延營收
A10: 預付認列（非現金營收） | B10: US$bn | C10: =MIN(C9,C9/輸入與假設!$C$73*運營_產能與收入!C7) -> 0.99586667 | D10: =MIN(D9,D9/輸入與假設!$C$73*運營_產能與收入!D7) -> 3.9589837 | E10: =MIN(E9,E9/輸入與假設!$C$73*運營_產能與收入!E7) -> 6.1809935 | F10: =MIN(F9,F9/輸入與假設!$C$73*運營_產能與收入!F7) -> 7.8614101 | G10: =MIN(G9,G9/輸入與假設!$C$73*運營_產能與收入!G7) -> 8.9816879 | I10: ＝期初合約負債 ÷ 認列年數 × 期間長度；這部分營收已在預付時收現，自營運來源扣除
A11: 合約負債期末 | B11: US$bn | C11: =C9+C8-C10 -> 11.876951 | D11: =D9+D8-D10 -> 18.542981 | E11: =E9+E8-E10 -> 23.58423 | F11: =F9+F8-F10 -> 26.945064 | G11: =G9+G8-G10 -> 29.185619 | I11: ＝期初＋預付流入−認列
A12: ① CapEx（用途用：1H 現金／2H 毛額） | B12: US$bn | C12: =輸入與假設!$C$181+輸入與假設!C$91 -> 26.04619 | D12: =輸入與假設!D$91 -> 27.597437 | E12: =輸入與假設!E$91 -> 29.148684 | F12: =輸入與假設!F$91 -> 29.148684 | G12: =輸入與假設!G$91 -> 37.692264 | I12: 1H 採現金流量表的現金購置 8.1303；2H 起採毛額，客戶預付在來源端抵回（避免重複計入）
A13: ② 在帳現金租金（備忘，1H 已含在 CFO） | B13: US$bn | C13: =輸入與假設!C$77 -> 0.0916 | D13: =輸入與假設!D$77 -> 0.2352 | E13: =輸入與假設!E$77 -> 0.2342 | F13: =輸入與假設!F$77 -> 0.2414 | G13: =輸入與假設!G$77 -> 0.2427 | I13: 見『租賃與承諾』頁；2030 後尚有 1.13。FY26 欄僅 2H：1H 租金 0.0 已含在實際 CFO 內
A14: ② 表外現金租金（未起租） | B14: US$bn | C14: =輸入與假設!C$78 -> 0.05 | D14: =輸入與假設!D$78 -> 0.42008844 | E14: =輸入與假設!E$78 -> 0.79056291 | F14: =輸入與假設!F$78 -> 0.76638966 | G14: =輸入與假設!G$78 -> 0.75208231 | I14: 已簽約未起租租賃 12.0541 的現金路徑
A15: 租金合計 | B15: US$bn | C15: =C13+C14 -> 0.1416 | D15: =D13+D14 -> 0.65528844 | E15: =E13+E14 -> 1.0247629 | F15: =F13+F14 -> 1.0077897 | G15: =G13+G14 -> 0.99478231
A16: ③ 存量債務利息（備忘，1H 已含在 CFO） | B16: US$bn | C16: =輸入與假設!C$122 -> 0.060375 | D16: =輸入與假設!D$122 -> 0.12075 | E16: =輸入與假設!E$122 -> 0.12075 | F16: =輸入與假設!F$122 -> 0.12075 | G16: =輸入與假設!G$122 -> 0.112125 | I16: ="6/30 債務餘額的利息。FY26 全年利息＝1H 實際 0.1828＋2H "&TEXT(C16,"0.0")&"＝"&TEXT(0.1828+C16,"0.00")&"（見下方備忘）" -> 6/30 債務餘額的利息。FY26 全年利息＝1H 實際 0.1828＋2H 0.1＝0.24（見下方備忘）
A17: 期初累積現金 | B17: US$bn | C17: =輸入與假設!$C$179 -> 3.6781 | D17: =C47 -> 2.1798696 | E17: =D47 -> 2 | F17: =E47 -> 2 | G17: =F47 -> 2 | I17: FY26 自 2025-12-31 的 3.127 起算；之後＝前期期末累積現金
A18: 新債利率 | B18: % | C18: =IF(輸入與假設!$C$116=1,輸入與假設!C$121+MAX(0,輸入與假設!$C$115-450)/100*0.004,輸入與假設!C$121) -> 0.065 | D18: =IF(輸入與假設!$C$116=1,輸入與假設!D$121+MAX(0,輸入與假設!$C$115-450)/100*0.004,輸入與假設!D$121) -> 0.065 | E18: =IF(輸入與假設!$C$116=1,輸入與假設!E$121+MAX(0,輸入與假設!$C$115-450)/100*0.004,輸入與假設!E$121) -> 0.065 | F18: =IF(輸入與假設!$C$116=1,輸入與假設!F$121+MAX(0,輸入與假設!$C$115-450)/100*0.004,輸入與假設!F$121) -> 0.065 | G18: =IF(輸入與假設!$C$116=1,輸入與假設!G$121+MAX(0,輸入與假設!$C$115-450)/100*0.004,輸入與假設!G$121) -> 0.065 | I18: CDS 開關：＋MAX(0,CDS−450)×0.4bp/bp
A19: ③ 新債利息（瀑布） | B19: US$bn | C19: =C74 -> 0 | D19: =D74 -> 0.56091448 | E19: =E74 -> 0.66591448 | F19: =F74 -> 0.77091449 | G19: =G74 -> 1.9318825 | I19: ＝新債利率×期間長度×(期初新債＋本期舉借)；見下方「期前融資瀑布」
A20: 利息合計 | B20: US$bn | C20: =C16+C19 -> 0.060375 | D20: =D16+D19 -> 0.68166448 | E20: =E16+E19 -> 0.78666448 | F20: =F16+F19 -> 0.89166448 | G20: =G16+G19 -> 2.0440075
A21: ④ JV／策略投資出資 | B21: US$bn | C21: =輸入與假設!$C$183+輸入與假設!C$81 -> 0.2516 | D21: =輸入與假設!D$81 -> 0 | E21: =輸入與假設!E$81 -> 0 | F21: =輸入與假設!F$81 -> 0 | G21: =輸入與假設!G$81 -> 0 | I21: FY26＝1H 實際 0.2516（JV 0.000＋策略投資 0.252）＋2H 模型。NBIS 不發股息
A22: 電力（overlay） | B22: US$bn | C22: =IF(輸入與假設!$C$56=1,運營_產能與收入!C9*8760*輸入與假設!C$58*輸入與假設!C$57/1000000000*運營_產能與收入!C7,0) -> 0 | D22: =IF(輸入與假設!$C$56=1,運營_產能與收入!D9*8760*輸入與假設!D$58*輸入與假設!D$57/1000000000*運營_產能與收入!D7,0) -> 0 | E22: =IF(輸入與假設!$C$56=1,運營_產能與收入!E9*8760*輸入與假設!E$58*輸入與假設!E$57/1000000000*運營_產能與收入!E7,0) -> 0 | F22: =IF(輸入與假設!$C$56=1,運營_產能與收入!F9*8760*輸入與假設!F$58*輸入與假設!F$57/1000000000*運營_產能與收入!F7,0) -> 0 | G22: =IF(輸入與假設!$C$56=1,運營_產能與收入!G9*8760*輸入與假設!G$58*輸入與假設!G$57/1000000000*運營_產能與收入!G7,0) -> 0 | I22: ＝已連網 MW×8760×PUE×電價÷1e9×期間係數。EBITDA 率已含電費，預設關閉
A23: 維護（overlay） | B23: US$bn | C23: =IF(輸入與假設!$C$56=1,運營_產能與收入!C9*輸入與假設!C$59/1000*運營_產能與收入!C7,0) -> 0 | D23: =IF(輸入與假設!$C$56=1,運營_產能與收入!D9*輸入與假設!D$59/1000*運營_產能與收入!D7,0) -> 0 | E23: =IF(輸入與假設!$C$56=1,運營_產能與收入!E9*輸入與假設!E$59/1000*運營_產能與收入!E7,0) -> 0 | F23: =IF(輸入與假設!$C$56=1,運營_產能與收入!F9*輸入與假設!F$59/1000*運營_產能與收入!F7,0) -> 0 | G23: =IF(輸入與假設!$C$56=1,運營_產能與收入!G9*輸入與假設!G$59/1000*運營_產能與收入!G7,0) -> 0
A24: ⑤ 排程還本（季報到期表） | B24: US$bn | C24: =輸入與假設!$C$185+IF(輸入與假設!$C$100=1,輸入與假設!C$120,0)+資產負債_既有債務!C42 -> 0.0467 | D24: =IF(輸入與假設!$C$100=1,輸入與假設!D$120,0)+資產負債_既有債務!D42 -> 0 | E24: =IF(輸入與假設!$C$100=1,輸入與假設!E$120,0)+資產負債_既有債務!E42 -> 0 | F24: =IF(輸入與假設!$C$100=1,輸入與假設!F$120,0)+資產負債_既有債務!F42 -> 0 | G24: =IF(輸入與假設!$C$100=1,輸入與假設!G$120,0)+資產負債_既有債務!G42 -> 3.795 | I24: FY26＝1H 實際還款 0.0＋2H 到期表 0.0467
A25: ⑥ capped call 支出（1H 實際） | B25: US$bn | C25: =輸入與假設!$C$186 -> 0 | D25: =0 -> 0 | E25: =0 -> 0 | F25: =0 -> 0 | G25: =0 -> 0 | I25: 可轉債配套 capped call 現金支出（未見揭露，0）
A26: 用途合計（現金口徑） | B26: US$bn | C26: =C12+C15+C20+C21+C22+C23+C24+C25 -> 26.546465 | D26: =D12+D15+D20+D21+D22+D23+D24+D25 -> 28.93439 | E26: =E12+E15+E20+E21+E22+E23+E24+E25 -> 30.960112 | F26: =F12+F15+F20+F21+F22+F23+F24+F25 -> 31.048138 | G26: =G12+G15+G20+G21+G22+G23+G24+G25 -> 44.526054 | I26: FY26 的 1H 部分採季報現金流量表口徑（現金購置、還款、JV、capped call）；1H 的利息與租金已含在 CFO 內，不重複列
A27: 來源（四層）
A28: Ⓐ0 1H26 實際營運現金流（CFO） | B28: US$bn | C28: =輸入與假設!$C$180 -> 4.5041 | D28: =0 -> 0 | E28: =0 -> 0 | F28: =0 -> 0 | G28: =0 -> 0 | I28: 季報實際值，取代模型推算；已含 1H 的利息、租金與客戶預付
A29: Ⓐ RPO 現金（2H 起） | B29: US$bn | C29: =運營_產能與收入!C37 -> 0.81458355 | D29: =運營_產能與收入!D37 -> 3.5666901 | E29: =運營_產能與收入!E37 -> 3.9696118 | F29: =運營_產能與收入!F37 -> 3.9070878 | G29: =運營_產能與收入!G37 -> 3.0106119
A30: Ⓑ 新簽約現金 | B30: US$bn | C30: =運營_產能與收入!C38 -> 0 | D30: =運營_產能與收入!D38 -> 0 | E30: =運營_產能與收入!E38 -> 3.3529002 | F30: =運營_產能與收入!F38 -> 6.6826429 | G30: =運營_產能與收入!G38 -> 10.043181
A31: Ⓒ 非算力服務現金 | B31: US$bn | C31: =輸入與假設!C$54 -> 0 | D31: =輸入與假設!D$54 -> 0 | E31: =輸入與假設!E$54 -> 0 | F31: =輸入與假設!F$54 -> 0 | G31: =輸入與假設!G$54 -> 0
A32: Ⓒ2 其他事業 EBITDA（2H 起） | B32: US$bn | C32: =輸入與假設!C$47 -> -0.094 | D32: =輸入與假設!D$47 -> -0.141 | E32: =輸入與假設!E$47 -> -0.094 | F32: =輸入與假設!F$47 -> -0.047 | G32: =輸入與假設!G$47 -> 0 | I32: Avride＋TripleTen 燒錢（負值），視為現金（v0.1b）
A33: Ⓓ 客戶預付（2H 起） | B33: US$bn | C33: =C8 -> 6.8976176 | D33: =D8 -> 10.625013 | E33: =E8 -> 11.222243 | F33: =F8 -> 11.222243 | G33: =G8 -> 11.222243
A34: Ⓓ2 減：預付認列（非現金營收） | B34: US$bn | C34: =-C10 -> -0.99586667 | D34: =-D10 -> -3.9589837 | E34: =-E10 -> -6.1809935 | F34: =-F10 -> -7.8614101 | G34: =-G10 -> -8.9816879 | I34: 營收中由合約負債轉入的部分已在預付時收現，不重複計入服務現金（v0.1b）
A35: 營運來源合計 | B35: US$bn | C35: =C28+C29+C30+C31+C32+C33+C34 -> 11.126435 | D35: =D28+D29+D30+D31+D32+D33+D34 -> 10.09172 | E35: =E28+E29+E30+E31+E32+E33+E34 -> 12.269762 | F35: =F28+F29+F30+F31+F32+F33+F34 -> 13.903564 | G35: =G28+G29+G30+G31+G32+G33+G34 -> 15.294349
A36: Ⓔ 股權／可轉債（融資） | B36: US$bn | C36: =輸入與假設!$C$187+IF(輸入與假設!$C$97=1,輸入與假設!$C$96,0) -> 10.4911 | D36: =0 -> 0 | E36: =0 -> 0 | F36: =0 -> 0 | G36: =0 -> 0 | I36: FY26＝1H 股權 4.811（ATM 淨 2.811＋NVIDIA 預付認股權證 2.0）＋2H 期後可轉債淨現金 5.68（2026-08）
A37: Ⓕ 1H26 實際借款（融資） | B37: US$bn | C37: =輸入與假設!$C$184 -> 4.3375 | D37: =0 -> 0 | E37: =0 -> 0 | F37: =0 -> 0 | G37: =0 -> 0 | I37: 季報：H1 借款 4.3375（2026-03 可轉債）
A38: Ⓖ 瀑布：新債（額度＋資產層） | B38: US$bn | C38: =C66 -> 0 | D38: =D66 -> 7.014069 | E38: =E66 -> 0 | F38: =F66 -> 0 | G38: =G66 -> 0 | I38: 見下方「期前融資瀑布」
A39: Ⓖ2 瀑布：可轉債 | B39: US$bn | C39: =C69 -> 0 | D39: =D69 -> 5 | E39: =E69 -> 5 | F39: =F69 -> 5 | G39: =G69 -> 5 | I39: 資產擔保融資用罄後、股權之前；每年不超過可轉債上限（v0.1b）
A40: Ⓗ 瀑布：股權募資 | B40: US$bn | C40: =C72 -> 0 | D40: =D72 -> 6.6487317 | E40: =E72 -> 13.69035 | F40: =F72 -> 12.144574 | G40: =G72 -> 15.431971 | I40: 債務與可轉債用罄後的殘差；每年不超過股權吸收上限
A41: Ⓘ 瀑布：高息債（股權上限溢出） | B41: US$bn | C41: =C73 -> 0 | D41: =D73 -> 0 | E41: =E73 -> 0 | F41: =F73 -> 0 | G41: =G73 -> 8.7997338 | I41: 股權超過每年上限的部分；不受 backlog 上限約束
A42: 總來源（含融資） | B42: US$bn | C42: =C35+C36+C37+C38+C39+C40+C41 -> 25.955035 | D42: =D35+D36+D37+D38+D39+D40+D41 -> 28.75452 | E42: =E35+E36+E37+E38+E39+E40+E41 -> 30.960112 | F42: =F35+F36+F37+F38+F39+F40+F41 -> 31.048138 | G42: =G35+G36+G37+G38+G39+G40+G41 -> 44.526054
A43: 缺口與現金橋
A44: 1H 其他／受限現金調節 | B44: US$bn | C44: =輸入與假設!$C$95-(輸入與假設!$C$179+輸入與假設!$C$180+輸入與假設!$C$184+輸入與假設!$C$187-輸入與假設!$C$181-輸入與假設!$C$183-輸入與假設!$C$185-輸入與假設!$C$186) -> -0.9068 | D44: =0 -> 0 | E44: =0 -> 0 | F44: =0 -> 0 | G44: =0 -> 0 | I44: 使 1H 實際流量接回 6/30 現金餘額；差額來自受限現金重分類與未逐項列出的項目
A45: 營運缺口（不含融資、不含還本） | B45: US$bn | C45: =C35-(C26-C24-C25) -> -15.37333 | D45: =D35-(D26-D24-D25) -> -18.84267 | E45: =E35-(E26-E24-E25) -> -18.69035 | F45: =F35-(F26-F24-F25) -> -17.144574 | G45: =G35-(G26-G24-G25) -> -25.436705 | I45: 本業能不能自給：營運來源 −（用途 − 排程還本 − capped call）
A46: 期間缺口（含融資） | B46: US$bn | C46: =C42-C26+C44 -> -1.4982304 | D46: =D42-D26+D44 -> -0.17986959 | E46: =E42-E26+E44 -> 0 | F46: =F42-F26+F44 -> 0 | G46: =G42-G26+G44 -> 0
A47: 期末累積現金 | B47: US$bn | C47: =C17+C46 -> 2.1798696 | D47: =D17+D46 -> 2 | E47: =E17+E46 -> 2 | F47: =F17+F46 -> 2 | G47: =G17+G46 -> 2 | I47: 期前融資：每期末不低於最低現金
A49: 期前融資瀑布（缺口在需要前一期先融好：額度 → 資產層新債 → 股權）
A50: 用途（不含新債利息） | B50: US$bn | C50: =C12+C15+C16+C21+C22+C23+C24+C25 -> 26.546465 | D50: =D12+D15+D16+D21+D22+D23+D24+D25 -> 28.373475 | E50: =E12+E15+E16+E21+E22+E23+E24+E25 -> 30.294197 | F50: =F12+F15+F16+F21+F22+F23+F24+F25 -> 30.277224 | G50: =G12+G15+G16+G21+G22+G23+G24+G25 -> 42.594171 | I50: 避免循環參照：直接由各支出列加總
A51: 新債期初餘額 | B51: US$bn | C51: =0 -> 0 | D51: =C78 -> 0 | E51: =D78 -> 7.014069 | F51: =E78 -> 7.014069 | G51: =F78 -> 7.014069
A52: 新債利率 × 期間長度 | B52: % | C52: =C18*運營_產能與收入!C7 -> 0.0325 | D52: =D18*運營_產能與收入!D7 -> 0.065 | E52: =E18*運營_產能與收入!E7 -> 0.065 | F52: =F18*運營_產能與收入!F7 -> 0.065 | G52: =G18*運營_產能與收入!G7 -> 0.065
A53: 高息債期初餘額 | B53: US$bn | C53: =0 -> 0 | D53: =C80 -> 0 | E53: =D80 -> 0 | F53: =E80 -> 0 | G53: =F80 -> 0
A54: 可轉債（瀑布）期初餘額 | B54: US$bn | C54: =0 -> 0 | D54: =C81 -> 0 | E54: =D81 -> 5 | F54: =E81 -> 10 | G54: =F81 -> 15
A55: 可轉債票息 × 期間長度 | B55: % | C55: =輸入與假設!$C$112*運營_產能與收入!C7 -> 0.0105 | D55: =輸入與假設!$C$112*運營_產能與收入!D7 -> 0.021 | E55: =輸入與假設!$C$112*運營_產能與收入!E7 -> 0.021 | F55: =輸入與假設!$C$112*運營_產能與收入!F7 -> 0.021 | G55: =輸入與假設!$C$112*運營_產能與收入!G7 -> 0.021
A56: 高息債利率 × 期間長度 | B56: % | C56: =(輸入與假設!$C$114+IF(輸入與假設!$C$116=1,MAX(0,輸入與假設!$C$115-輸入與假設!$C$117)/10000*輸入與假設!$C$118,0))*運營_產能與收入!C7 -> 0.06 | D56: =(輸入與假設!$C$114+IF(輸入與假設!$C$116=1,MAX(0,輸入與假設!$C$115-輸入與假設!$C$117)/10000*輸入與假設!$C$118,0))*運營_產能與收入!D7 -> 0.12 | E56: =(輸入與假設!$C$114+IF(輸入與假設!$C$116=1,MAX(0,輸入與假設!$C$115-輸入與假設!$C$117)/10000*輸入與假設!$C$118,0))*運營_產能與收入!E7 -> 0.12 | F56: =(輸入與假設!$C$114+IF(輸入與假設!$C$116=1,MAX(0,輸入與假設!$C$115-輸入與假設!$C$117)/10000*輸入與假設!$C$118,0))*運營_產能與收入!F7 -> 0.12 | G56: =(輸入與假設!$C$114+IF(輸入與假設!$C$116=1,MAX(0,輸入與假設!$C$115-輸入與假設!$C$117)/10000*輸入與假設!$C$118,0))*運營_產能與收入!G7 -> 0.12
A57: 融資前現金（扣既有新債利息） | B57: US$bn | C57: =C17+C35+C36+C37+C44-C50-C52*C51-C56*C53-C55*C54 -> 2.1798696 | D57: =D17+D35+D36+D37+D44-D50-D52*D51-D56*D53-D55*D54 -> -16.101886 | E57: =E17+E35+E36+E37+E44-E50-E52*E51-E56*E53-E55*E54 -> -16.58535 | F57: =F17+F35+F36+F37+F44-F50-F52*F51-F56*F53-F55*F54 -> -15.039574 | G57: =G17+G35+G36+G37+G44-G50-G52*G51-G56*G53-G55*G54 -> -26.070737
A58: 融資需求（補足至最低現金） | B58: US$bn | C58: =MAX(0,輸入與假設!$C$103-C57) -> 0 | D58: =MAX(0,輸入與假設!$C$103-D57) -> 18.101886 | E58: =MAX(0,輸入與假設!$C$103-E57) -> 18.58535 | F58: =MAX(0,輸入與假設!$C$103-F57) -> 17.039574 | G58: =MAX(0,輸入與假設!$C$103-G57) -> 28.070737
A59: 期初 backlog | B59: US$bn | C59: =輸入與假設!$C$26+輸入與假設!$C$27 -> 37.4906 | D59: =C61 -> 34.116446 | E59: =D61 -> 27.368138 | F59: =E61 -> 32.278053 | G59: =F61 -> 32.379654 | I59: FY26 期初＝6/30 RPO 37.4906＋期後新增 0.0
A60: 新簽合約增量（年化增量×年期） | B60: US$bn | C60: =MAX(0,運營_產能與收入!C23/運營_產能與收入!C7-0)*輸入與假設!$C$102 -> 0 | D60: =MAX(0,運營_產能與收入!D23/運營_產能與收入!D7-運營_產能與收入!C23/運營_產能與收入!C7)*輸入與假設!$C$102 -> 0 | E60: =MAX(0,運營_產能與收入!E23/運營_產能與收入!E7-運營_產能與收入!D23/運營_產能與收入!D7)*輸入與假設!$C$102 -> 18.049693 | F60: =MAX(0,運營_產能與收入!F23/運營_產能與收入!F7-運營_產能與收入!E23/運營_產能與收入!E7)*輸入與假設!$C$102 -> 20.424429 | G60: =MAX(0,運營_產能與收入!G23/運營_產能與收入!G7-運營_產能與收入!F23/運營_產能與收入!F7)*輸入與假設!$C$102 -> 21.55751
A61: 期末 backlog | B61: US$bn | C61: =C59-運營_產能與收入!C17-運營_產能與收入!C23+C60 -> 34.116446 | D61: =D59-運營_產能與收入!D17-運營_產能與收入!D23+D60 -> 27.368138 | E61: =E59-運營_產能與收入!E17-運營_產能與收入!E23+E60 -> 32.278053 | F61: =F59-運營_產能與收入!F17-運營_產能與收入!F23+F60 -> 32.379654 | G61: =G59-運營_產能與收入!G17-運營_產能與收入!G23+G60 -> 27.928125 | I61: ＝期初 − 排程認列 − 新簽約認列 ＋ 新簽合約增量
A62: 既有債務＋期後可轉債（期末） | B62: US$bn | C62: =IF(輸入與假設!$C$100=1,資產負債_既有債務!C38,資產負債_既有債務!$E$6)+資產負債_既有債務!$E$9+資產負債_既有債務!C43 -> 6.67 | D62: =IF(輸入與假設!$C$100=1,資產負債_既有債務!D38,資產負債_既有債務!$E$6)+資產負債_既有債務!$E$9+資產負債_既有債務!D43 -> 6.67 | E62: =IF(輸入與假設!$C$100=1,資產負債_既有債務!E38,資產負債_既有債務!$E$6)+資產負債_既有債務!$E$9+資產負債_既有債務!E43 -> 6.67 | F62: =IF(輸入與假設!$C$100=1,資產負債_既有債務!F38,資產負債_既有債務!$E$6)+資產負債_既有債務!$E$9+資產負債_既有債務!F43 -> 6.67 | G62: =IF(輸入與假設!$C$100=1,資產負債_既有債務!G38,資產負債_既有債務!$E$6)+資產負債_既有債務!$E$9+資產負債_既有債務!G43 -> 2.875 | I62: ＝(依到期表遞減的既有本金，若關閉攤還則維持 10.0885)＋期後新發可轉債 0
A63: 債務上限（債務／backlog × 期末 backlog） | B63: US$bn | C63: =輸入與假設!$C$101*C61 -> 17.058223 | D63: =輸入與假設!$C$101*D61 -> 13.684069 | E63: =輸入與假設!$C$101*E61 -> 16.139026 | F63: =輸入與假設!$C$101*F61 -> 16.189827 | G63: =輸入與假設!$C$101*G61 -> 13.964062
A64: 未動用額度（期初） | B64: US$bn | C64: =IF(輸入與假設!$C$99=1,輸入與假設!$C$98,0) -> 0.775 | D64: =C79 -> 0.775 | E64: =D79 -> 0 | F64: =E79 -> 0 | G64: =F79 -> 0
A65: 新債可借上限 | B65: US$bn | C65: =MAX(0,C63-(C62+C51+C54),C64) -> 10.388223 | D65: =MAX(0,D63-(D62+D51+D54),D64) -> 7.014069 | E65: =MAX(0,E63-(E62+E51+E54),E64) -> 0 | F65: =MAX(0,F63-(F62+F51+F54),F64) -> 0 | G65: =MAX(0,G63-(G62+G51+G54),G64) -> 0 | I65: ＝MAX(上限 − 既有債務 − 期初新債 − 期初瀑布可轉債, 未動用額度)
A66: 新債舉借 | B66: US$bn | C66: =MIN(C65,C58/(1-C52)) -> 0 | D66: =MIN(D65,D58/(1-D52)) -> 7.014069 | E66: =MIN(E65,E58/(1-E52)) -> 0 | F66: =MIN(F65,F58/(1-F52)) -> 0 | G66: =MIN(G65,G58/(1-G52)) -> 0 | I66: 期前融資：期初到位，當期全額計息，所以需求要除以 (1−利率×期間)
A67: 債務後剩餘需求 | B67: US$bn | C67: =MAX(0,C58+C52*C66-C66) -> 0 | D67: =MAX(0,D58+D52*D66-D66) -> 11.543732 | E67: =MAX(0,E58+E52*E66-E66) -> 18.58535 | F67: =MAX(0,F58+F52*F66-F66) -> 17.039574 | G67: =MAX(0,G58+G52*G66-G66) -> 28.070737
A68: 可轉債可發行上限 | B68: US$bn | C68: =MAX(0,輸入與假設!$C$111)*運營_產能與收入!C7 -> 2.5 | D68: =MAX(0,輸入與假設!$C$111)*運營_產能與收入!D7 -> 5 | E68: =MAX(0,輸入與假設!$C$111)*運營_產能與收入!E7 -> 5 | F68: =MAX(0,輸入與假設!$C$111)*運營_產能與收入!F7 -> 5 | G68: =MAX(0,輸入與假設!$C$111)*運營_產能與收入!G7 -> 5 | I68: ＝每年上限（隨情境）× 期間長度
A69: 可轉債發行 | B69: US$bn | C69: =MIN(C68,C67/(1-C55)) -> 0 | D69: =MIN(D68,D67/(1-D55)) -> 5 | E69: =MIN(E68,E67/(1-E55)) -> 5 | F69: =MIN(F68,F67/(1-F55)) -> 5 | G69: =MIN(G68,G67/(1-G55)) -> 5 | I69: 期前融資：期初到位、當期全額計息
A70: 可轉債後剩餘需求 | B70: US$bn | C70: =MAX(0,C67+C55*C69-C69) -> 0 | D70: =MAX(0,D67+D55*D69-D69) -> 6.6487317 | E70: =MAX(0,E67+E55*E69-E69) -> 13.69035 | F70: =MAX(0,F67+F55*F69-F69) -> 12.144574 | G70: =MAX(0,G67+G55*G69-G69) -> 23.175737
A71: 每年股權吸收上限 | B71: US$bn | C71: =IF(輸入與假設!$C$106>=9,1E+099,輸入與假設!$C$106*輸入與假設!$C$104*輸入與假設!$C$107*運營_產能與收入!C7) -> 7.7159856 | D71: =IF(輸入與假設!$C$106>=9,1E+099,輸入與假設!$C$106*輸入與假設!$C$104*輸入與假設!$C$107*運營_產能與收入!D7) -> 15.431971 | E71: =IF(輸入與假設!$C$106>=9,1E+099,輸入與假設!$C$106*輸入與假設!$C$104*輸入與假設!$C$107*運營_產能與收入!E7) -> 15.431971 | F71: =IF(輸入與假設!$C$106>=9,1E+099,輸入與假設!$C$106*輸入與假設!$C$104*輸入與假設!$C$107*運營_產能與收入!F7) -> 15.431971 | G71: =IF(輸入與假設!$C$106>=9,1E+099,輸入與假設!$C$106*輸入與假設!$C$104*輸入與假設!$C$107*運營_產能與收入!G7) -> 15.431971 | I71: ＝現市值（發行參考價 × 0.3088bn 股）× 上限 % × 期間長度
A72: 股權募資 | B72: US$bn | C72: =MIN(C70,C71) -> 0 | D72: =MIN(D70,D71) -> 6.6487317 | E72: =MIN(E70,E71) -> 13.69035 | F72: =MIN(F70,F71) -> 12.144574 | G72: =MIN(G70,G71) -> 15.431971
A73: 高息債舉借（溢出） | B73: US$bn | C73: =(C70-C72)/(1-C56) -> 0 | D73: =(D70-D72)/(1-D56) -> 0 | E73: =(E70-E72)/(1-E56) -> 0 | F73: =(F70-F72)/(1-F56) -> 0 | G73: =(G70-G72)/(1-G56) -> 8.7997338
A74: 新債＋高息債利息（期初餘額＋本期舉借） | B74: US$bn | C74: =C52*(C51+C66)+C56*(C53+C73)+C55*(C54+C69) -> 0 | D74: =D52*(D51+D66)+D56*(D53+D73)+D55*(D54+D69) -> 0.56091448 | E74: =E52*(E51+E66)+E56*(E53+E73)+E55*(E54+E69) -> 0.66591448 | F74: =F52*(F51+F66)+F56*(F53+F73)+F55*(F54+F69) -> 0.77091449 | G74: =G52*(G51+G66)+G56*(G53+G73)+G55*(G54+G69) -> 1.9318825 | I74: 含瀑布可轉債票息（v0.1b）
A75: 發行價（現價×(1−折價)） | B75: US$ | C75: =輸入與假設!$C$104*(1-輸入與假設!$C$105) -> 224.883 | D75: =輸入與假設!$C$104*(1-輸入與假設!$C$105) -> 224.883 | E75: =輸入與假設!$C$104*(1-輸入與假設!$C$105) -> 224.883 | F75: =輸入與假設!$C$104*(1-輸入與假設!$C$105) -> 224.883 | G75: =輸入與假設!$C$104*(1-輸入與假設!$C$105) -> 224.883
A76: 新發行股數 | B76: bn | C76: =C72/C75 -> 0 | D76: =D72/D75 -> 0.029565292 | E76: =E72/E75 -> 0.060877655 | F76: =F72/F75 -> 0.054003968 | G76: =G72/G75 -> 0.068622222
A77: 累計新股 | B77: bn | C77: =C76 -> 0 | D77: =C77+D76 -> 0.029565292 | E77: =D77+E76 -> 0.090442948 | F77: =E77+F76 -> 0.14444692 | G77: =F77+G76 -> 0.21306914
A78: 新債期末餘額 | B78: US$bn | C78: =C51+C66 -> 0 | D78: =D51+D66 -> 7.014069 | E78: =E51+E66 -> 7.014069 | F78: =F51+F66 -> 7.014069 | G78: =G51+G66 -> 7.014069
A79: 未動用額度（期末） | B79: US$bn | C79: =C64-MIN(C64,C66) -> 0.775 | D79: =D64-MIN(D64,D66) -> 0 | E79: =E64-MIN(E64,E66) -> 0 | F79: =F64-MIN(F64,F66) -> 0 | G79: =G64-MIN(G64,G66) -> 0
A80: 高息債期末餘額 | B80: US$bn | C80: =C53+C73 -> 0 | D80: =D53+D73 -> 0 | E80: =E53+E73 -> 0 | F80: =F53+F73 -> 0 | G80: =G53+G73 -> 8.7997338
A81: 可轉債（瀑布）期末餘額 | B81: US$bn | C81: =C54+C69 -> 0 | D81: =D54+D69 -> 5 | E81: =E54+E69 -> 10 | F81: =F54+F69 -> 15 | G81: =G54+G69 -> 20
A82: 期末總債務（既有＋可轉債＋新債＋高息債） | B82: US$bn | C82: =C62+C78+C81+C80 -> 6.67 | D82: =D62+D78+D81+D80 -> 18.684069 | E82: =E62+E78+E81+E80 -> 23.684069 | F82: =F62+F78+F81+F80 -> 28.684069 | G82: =G62+G78+G81+G80 -> 38.688803
A83: 融資前累積現金 | B83: US$bn | C83: =C17+C35+C36+C37+C44-C50 -> 2.1798696 | D83: =C83+D35+D36-D50 -> -16.101886 | E83: =D83+E35+E36-E50 -> -34.126321 | F83: =E83+F35+F36-F50 -> -50.499981 | G83: =F83+G35+G36-G50 -> -77.799804 | I83: 若不做任何新融資的累積現金；負值＝外部資金需求
A85: 四層橋（驗算）
A86: 期初現金（2025-12-31） | C86: =輸入與假設!$C$179 -> 3.6781
A87: ＋ 營運缺口合計 | C87: =SUM(C45:G45) -> -95.48763
A88: ＋ 股權／可轉債合計 | C88: =SUM(C36:G36) -> 10.4911
A89: ＋ 1H 實際借款 | C89: =SUM(C37:G37) -> 4.3375
A90: − capped call（1H） | C90: =-SUM(C25:G25) -> 0
A91: ＋ 1H 其他／受限現金調節 | C91: =SUM(C44:G44) -> -0.9068
A92: ＋ 瀑布新債＋可轉債＋股權＋高息債合計 | C92: =SUM(C38:G38)+SUM(C39:G39)+SUM(C40:G40)+SUM(C41:G41) -> 83.72943
A93: − 排程還本合計 | C93: =-SUM(C24:G24) -> -3.8417
A94: ＝ 期末現金（橋算） | C94: =SUM(C86:C93) -> 2
A95: 對照：期末累積現金（表算） | C95: =G47 -> 2
A96: 差異（應為 0） | C96: =C94-C95 -> -9.3258734e-15 | I96: 若不為 0，表示公式鏈被改壞
A98: FY26 全年備忘（對照公司指引）
A99: FY26 總營收（1H 實際＋2H 模型） | C99: =運營_產能與收入!C28 -> 2.3394994 | I99: 公司指引 3.0–3.4
A100: FY26 CapEx 認列（1H＋2H） | C100: =C6 -> 26.04619 | I100: 公司指引 20–25（法說會轉述）
A101: FY26 利息（1H 實際＋2H 模型） | C101: =輸入與假設!$C$188+輸入與假設!C$122+C19 -> 0.243175 | I101: Q3 指引 0.86–0.94／季
A102: FY26 租賃現金（1H 實際＋2H 模型） | C102: =輸入與假設!$C$189+C15 -> 0.1416 | I102: 1H 實際支付 0.748
A103: FY26 排程還本（1H 實際＋2H） | C103: =C24 -> 0.0467 | I103: 1H 實際還款 5.219＋2H 到期表 4.413

Sheet 季度追蹤
A1: 季度追蹤 — 焦點季的模型／共識／指引／實際與差距（由年度模型拆分；只用於追蹤，不影響年度數字與目標價）
A2: 設定與實際數在『輸入與假設』J 區，共識在 I 區；缺資料顯示「不適用」，實際數空白＝待公布。差距超過門檻的項目附差異原因（拆法＝所屬期間合計差距在門檻內）。第 2 區為 6 季路徑與拆分明細（預設收合）。
A4: 1｜焦點季（『輸入與假設』J 區選擇）：模型／共識／指引／實際與差距
A5: 指標 | B5: 單位 | C5: 模型 | D5: 共識 | E5: 模型 vs 共識 | F5: 指引（低） | G5: 指引（高） | H5: 模型 vs 指引中點 | I5: 實際 | J5: 實際 vs 模型 | K5: 實際 vs 共識 | L5: 實際 vs 指引中點 | M5: 利潤率 pt：模型 vs 共識 | N5: 模型 vs 指引 | O5: 實際 vs 模型 | P5: 實際 vs 共識 | Q5: 實際 vs 指引
A6: 焦點｜營收 | B6: US$bn | C6: =INDEX($C$22:$H$22,輸入與假設!$C$280) -> 0.64683314 | D6: =INDEX($C$32:$H$32,輸入與假設!$C$280) -> 0.8994 | E6: =INDEX($C$42:$H$42,輸入與假設!$C$280) -> -0.28081705 | F6: 不適用 | G6: 不適用 | H6: =INDEX($C$43:$H$43,輸入與假設!$C$280) -> 不適用 | I6: =IF(ISNUMBER(INDEX($C$36:$H$36,輸入與假設!$C$280)),INDEX($C$36:$H$36,輸入與假設!$C$280),"待公布") -> 待公布 | J6: =INDEX($C$44:$H$44,輸入與假設!$C$280) | K6: =INDEX($C$45:$H$45,輸入與假設!$C$280) | L6: =INDEX($C$46:$H$46,輸入與假設!$C$280)
A7: 焦點｜調整後 EBITDA | B7: US$bn | C7: =INDEX($C$28:$H$28,輸入與假設!$C$280) -> 0.27267199 | D7: =INDEX($C$33:$H$33,輸入與假設!$C$280) -> 0.3624 | E7: =INDEX($C$47:$H$47,輸入與假設!$C$280) -> -0.089728008 | F7: 不適用 | G7: 不適用 | H7: =INDEX($C$48:$H$48,輸入與假設!$C$280) -> 不適用 | I7: =IF(ISNUMBER(INDEX($C$37:$H$37,輸入與假設!$C$280)),INDEX($C$37:$H$37,輸入與假設!$C$280),"待公布") -> 待公布 | J7: =INDEX($C$49:$H$49,輸入與假設!$C$280) | K7: =INDEX($C$50:$H$50,輸入與假設!$C$280) | L7: =INDEX($C$51:$H$51,輸入與假設!$C$280) | M7: =INDEX($C$52:$H$52,輸入與假設!$C$280) -> 0.018613906 | N7: =INDEX($C$53:$H$53,輸入與假設!$C$280) -> 不適用 | O7: =INDEX($C$54:$H$54,輸入與假設!$C$280) | P7: =INDEX($C$55:$H$55,輸入與假設!$C$280) | Q7: =INDEX($C$56:$H$56,輸入與假設!$C$280)
A8: 焦點｜EBITDA 率 | B8: % | C8: =INDEX($C$27:$H$27,輸入與假設!$C$280) -> 0.4215492 | D8: =INDEX($C$34:$H$34,輸入與假設!$C$280) -> 0.40293529 | E8: =INDEX($C$57:$H$57,輸入與假設!$C$280) -> 0.018613906 | F8: 不適用 | G8: 不適用 | H8: =INDEX($C$58:$H$58,輸入與假設!$C$280) -> 不適用 | I8: =IF(ISNUMBER(INDEX($C$38:$H$38,輸入與假設!$C$280)),INDEX($C$38:$H$38,輸入與假設!$C$280),"待公布") -> 待公布 | J8: =INDEX($C$59:$H$59,輸入與假設!$C$280) | K8: =INDEX($C$60:$H$60,輸入與假設!$C$280) | L8: =INDEX($C$61:$H$61,輸入與假設!$C$280)
A9: 焦點｜調整後營業利益 | B9: US$bn | C9: =INDEX($C$30:$H$30,輸入與假設!$C$280) -> -0.65875163 | D9: 不適用 | E9: =INDEX($C$62:$H$62,輸入與假設!$C$280) -> 不適用 | F9: 不適用 | G9: 不適用 | H9: =INDEX($C$63:$H$63,輸入與假設!$C$280) -> 不適用 | I9: =IF(ISNUMBER(INDEX($C$39:$H$39,輸入與假設!$C$280)),INDEX($C$39:$H$39,輸入與假設!$C$280),"待公布") -> 待公布 | J9: =INDEX($C$64:$H$64,輸入與假設!$C$280) | K9: =INDEX($C$65:$H$65,輸入與假設!$C$280) | L9: =INDEX($C$66:$H$66,輸入與假設!$C$280) | M9: =INDEX($C$67:$H$67,輸入與假設!$C$280) -> 不適用 | N9: =INDEX($C$68:$H$68,輸入與假設!$C$280) -> 不適用 | O9: =INDEX($C$69:$H$69,輸入與假設!$C$280) | P9: =INDEX($C$70:$H$70,輸入與假設!$C$280) | Q9: =INDEX($C$71:$H$71,輸入與假設!$C$280)
A10: 焦點｜CapEx（毛額） | B10: US$bn | C10: =INDEX($C$31:$H$31,輸入與假設!$C$280) -> 8.957945 | D10: 不適用 | E10: =INDEX($C$72:$H$72,輸入與假設!$C$280) -> 不適用 | F10: 不適用 | G10: 不適用 | H10: =INDEX($C$73:$H$73,輸入與假設!$C$280) -> 不適用 | I10: =IF(ISNUMBER(INDEX($C$40:$H$40,輸入與假設!$C$280)),INDEX($C$40:$H$40,輸入與假設!$C$280),"待公布") -> 待公布 | J10: =INDEX($C$74:$H$74,輸入與假設!$C$280) | K10: =INDEX($C$75:$H$75,輸入與假設!$C$280) | L10: =INDEX($C$76:$H$76,輸入與假設!$C$280)
A11: 焦點｜季末已連網 MW-IT | B11: MW | C11: =INDEX($C$19:$H$19,輸入與假設!$C$280) -> 605 | D11: 不適用 | E11: =INDEX($C$77:$H$77,輸入與假設!$C$280) -> 不適用 | F11: 不適用 | G11: 不適用 | H11: =INDEX($C$78:$H$78,輸入與假設!$C$280) -> 不適用 | I11: =IF(ISNUMBER(INDEX($C$41:$H$41,輸入與假設!$C$280)),INDEX($C$41:$H$41,輸入與假設!$C$280),"待公布") -> 待公布 | J11: =INDEX($C$79:$H$79,輸入與假設!$C$280) | K11: =INDEX($C$80:$H$80,輸入與假設!$C$280) | L11: =INDEX($C$81:$H$81,輸入與假設!$C$280)
A12: 焦點｜季度 | C12: =INDEX($C$16:$H$16,輸入與假設!$C$280) -> Q3'26
A13: 焦點｜差異原因 | C13: =IF(INDEX($C$118:$H$118,輸入與假設!$C$280)="","無（差距皆在 "&IF(ROUND(ABS(輸入與假設!$C$274)*100,4)=INT(ROUND(ABS(輸入與假設!$C$274)*100,4)),TEXT(ROUND(ABS(輸入與假設!$C$274)*100,4),"0"),TEXT(ROUND(ABS(輸入與假設!$C$274)*100,4),"0.0"))&"%"&" 以內）",INDEX($C$118:$H$118,輸入與假設!$C$280)) -> 營收 vs 共識 −28.1%：觀點（水準 −$0.395bn（2H26 模型 $1.358bn，共識合計 $2.420bn）；分配 +$0.142bn；每 MW 年收入＝Tokenomics 錨（IF_HoldEcon，在役世代加權）× 定價倍數 k（市場價格證據；v0.2a）；期初可計費 MW 以最新季實際營收年化校準，可計費 MW 依爬坡係數逐步收斂到已連網 MW（v0.1c）；共識未揭露 MW 與單價假設）
A15: 2｜6 季路徑、共識、指引、實際與差距（明細；第 1 區以焦點季引用本區）
A16: 項目 | B16: 單位 | C16: Q3'26 | D16: Q4'26 | E16: Q1'27 | F16: Q2'27 | G16: Q3'27 | H16: Q4'27
A17: 所屬期間 | C17: =輸入與假設!C$279 -> 1 | D17: =輸入與假設!D$279 -> 1 | E17: =輸入與假設!E$279 -> 2 | F17: =輸入與假設!F$279 -> 2 | G17: =輸入與假設!G$279 -> 2 | H17: =輸入與假設!H$279 -> 2 | J17: 1＝2H26、2＝FY27
A18: 季序 | C18: 1 | D18: 2 | E18: 3 | F18: 4 | G18: 5 | H18: 6 | J18: EBITDA 率直線的 x 軸
A19: 季末已連網 MW-IT（模型） | B19: MW | C19: =輸入與假設!$C$282+(輸入與假設!C$39-輸入與假設!$C$282)*1/2 -> 605 | D19: =輸入與假設!$C$282+(輸入與假設!C$39-輸入與假設!$C$282)*2/2 -> 750 | E19: =輸入與假設!C$39+(輸入與假設!D$39-輸入與假設!C$39)*1/4 -> 895 | F19: =輸入與假設!C$39+(輸入與假設!D$39-輸入與假設!C$39)*2/4 -> 1040 | G19: =輸入與假設!C$39+(輸入與假設!D$39-輸入與假設!C$39)*3/4 -> 1185 | H19: =輸入與假設!C$39+(輸入與假設!D$39-輸入與假設!C$39)*4/4 -> 1330 | J19: 期初與期末 Accepted 之間線性內插；第 1 期起點見 J 區
A20: 平均在役 MW（Billable，拆分依據） | B20: MW | C20: =輸入與假設!$C$32+(輸入與假設!C$40-輸入與假設!$C$32)*1/4 -> 274.25 | D20: =輸入與假設!$C$32+(輸入與假設!C$40-輸入與假設!$C$32)*3/4 -> 316.75 | E20: =輸入與假設!C$40+(輸入與假設!D$40-輸入與假設!C$40)*1/8 -> 408.75 | F20: =輸入與假設!C$40+(輸入與假設!D$40-輸入與假設!C$40)*3/8 -> 550.25 | G20: =輸入與假設!C$40+(輸入與假設!D$40-輸入與假設!C$40)*5/8 -> 691.75 | H20: =輸入與假設!C$40+(輸入與假設!D$40-輸入與假設!C$40)*7/8 -> 833.25 | J20: 期初與期末 Billable 之間線性內插的季平均
A21: 季內新增 Accepted MW | B21: MW | C21: =C19-輸入與假設!$C$282 -> 145 | D21: =D19-C19 -> 145 | E21: =E19-輸入與假設!C$39 -> 145 | F21: =F19-E19 -> 145 | G21: =G19-F19 -> 145 | H21: =H19-G19 -> 145 | J21: CapEx 拆分依據
A22: 營收（模型） | B22: US$bn | C22: =輸入與假設!$C$281+1*(損益!C8-2*輸入與假設!$C$281)/3 -> 0.64683314 | D22: =輸入與假設!$C$281+2*(損益!C8-2*輸入與假設!$C$281)/3 -> 0.71136629 | E22: =損益!D8*E20/(E20+F20+G20+H20) -> 0.9832322 | F22: =損益!D8*F20/(E20+F20+G20+H20) -> 1.3236049 | G22: =損益!D8*G20/(E20+F20+G20+H20) -> 1.6639777 | H22: =損益!D8*H20/(E20+F20+G20+H20) -> 2.0043504 | J22: 拆分方法見『輸入與假設』J 區與 HTML「拆分方法」
A23: EBITDA 率直線｜各期營收合計 S | C23: =C22+D22 -> 1.3581994 | D23: =E22+F22+G22+H22 -> 5.9751652 | J23: 欄＝期間（2H26、FY27）
A24: EBITDA 率直線｜營收 × 季序合計 T | C24: =C22*C18+D22*D18 -> 2.0695657 | D24: =E22*E18+F22*F18+G22*G18+H22*H18 -> 28.590107 | J24: 欄＝期間（2H26、FY27）
A25: EBITDA 率直線｜年度 EBITDA E | C25: =損益!C19 -> 0.58102512 | D25: =損益!D19 -> 2.7883247 | J25: 欄＝期間（2H26、FY27）
A26: EBITDA 率直線｜截距 a／斜率 b | C26: =(C25*D24-C24*D25)/(C23*D24-C24*D23) -> 0.40963236 | D26: =(C23*D25-D23*C25)/(C23*D24-C24*D23) -> 0.01191684 | J26: 解兩式：Σ營收×(a＋b×季序)＝各期年度 EBITDA
A27: EBITDA 率（模型） | B27: % | C27: =$C$26+$D$26*C18 -> 0.4215492 | D27: =$C$26+$D$26*D18 -> 0.43346604 | E27: =$C$26+$D$26*E18 -> 0.44538288 | F27: =$C$26+$D$26*F18 -> 0.45729972 | G27: =$C$26+$D$26*G18 -> 0.46921656 | H27: =$C$26+$D$26*H18 -> 0.4811334 | J27: 跨季一條直線，季度 EBITDA 加總＝年度
A28: 調整後 EBITDA（模型） | B28: US$bn | C28: =C22*C27 -> 0.27267199 | D28: =D22*D27 -> 0.30835313 | E28: =E22*E27 -> 0.43791478 | F28: =F22*F27 -> 0.60528416 | G28: =G22*G27 -> 0.78076587 | H28: =H22*H27 -> 0.96435992
A29: 車隊折舊（模型） | B29: US$bn | C29: =(輸入與假設!C$89+輸入與假設!C$87*1/4)/輸入與假設!$C$65*輸入與假設!C$37/2 -> 0.93142362 | D29: =(輸入與假設!C$89+輸入與假設!C$87*3/4)/輸入與假設!$C$65*輸入與假設!C$37/2 -> 1.3793209 | E29: =(輸入與假設!D$89+輸入與假設!D$87*1/8)/輸入與假設!$C$65*輸入與假設!D$37/4 -> 1.7757535 | F29: =(輸入與假設!D$89+輸入與假設!D$87*3/8)/輸入與假設!$C$65*輸入與假設!D$37/4 -> 2.1207214 | G29: =(輸入與假設!D$89+輸入與假設!D$87*5/8)/輸入與假設!$C$65*輸入與假設!D$37/4 -> 2.4656894 | H29: =(輸入與假設!D$89+輸入與假設!D$87*7/8)/輸入與假設!$C$65*輸入與假設!D$37/4 -> 2.8106574 | J29: 依期內平均 PP&E（與年度車隊折舊公式相同）
A30: 調整後營業利益（模型） | B30: US$bn | C30: =C28-C29 -> -0.65875163 | D30: =D28-D29 -> -1.0709677 | E30: =E28-E29 -> -1.3378387 | F30: =F28-F29 -> -1.5154373 | G30: =G28-G29 -> -1.6849235 | H30: =H28-H29 -> -1.8462974 | J30: ＝調整後 EBITDA − 車隊折舊（未扣 SBC）
A31: CapEx（毛額）（模型） | B31: US$bn | C31: =IF((C21+D21)>0,輸入與假設!C$91*C21/(C21+D21),輸入與假設!C$91/2) -> 8.957945 | D31: =IF((C21+D21)>0,輸入與假設!C$91*D21/(C21+D21),輸入與假設!C$91/2) -> 8.957945 | E31: =IF((E21+F21+G21+H21)>0,輸入與假設!D$91*E21/(E21+F21+G21+H21),輸入與假設!D$91/4) -> 6.8993593 | F31: =IF((E21+F21+G21+H21)>0,輸入與假設!D$91*F21/(E21+F21+G21+H21),輸入與假設!D$91/4) -> 6.8993593 | G31: =IF((E21+F21+G21+H21)>0,輸入與假設!D$91*G21/(E21+F21+G21+H21),輸入與假設!D$91/4) -> 6.8993593 | H31: =IF((E21+F21+G21+H21)>0,輸入與假設!D$91*H21/(E21+F21+G21+H21),輸入與假設!D$91/4) -> 6.8993593 | J31: 依季內新增 Accepted MW
A32: 共識｜營收 | B32: US$bn | C32: =IF(ISNUMBER(輸入與假設!$C$245),輸入與假設!$C$245,"不適用") -> 0.8994 | D32: =IF(ISNUMBER(輸入與假設!$D$245),輸入與假設!$D$245,"不適用") -> 1.521 | E32: 不適用 | F32: 不適用 | G32: 不適用 | H32: 不適用 | J32: I 區季度共識 [Interested-party]
A33: 共識｜調整後 EBITDA | B33: US$bn | C33: =IF(ISNUMBER(輸入與假設!$C$246),輸入與假設!$C$246,"不適用") -> 0.3624 | D33: =IF(ISNUMBER(輸入與假設!$D$246),輸入與假設!$D$246,"不適用") -> 0.74 | E33: 不適用 | F33: 不適用 | G33: 不適用 | H33: 不適用 | J33: I 區季度共識 [Interested-party]
A34: 共識｜EBITDA 率 [Derived] | B34: % | C34: =IF(AND(ISNUMBER(輸入與假設!$C$246),ISNUMBER(輸入與假設!$C$245)),輸入與假設!$C$246/輸入與假設!$C$245,"不適用") -> 0.40293529 | D34: =IF(AND(ISNUMBER(輸入與假設!$D$246),ISNUMBER(輸入與假設!$D$245)),輸入與假設!$D$246/輸入與假設!$D$245,"不適用") -> 0.48652202 | E34: 不適用 | F34: 不適用 | G34: 不適用 | H34: 不適用 | J34: ＝共識 EBITDA ÷ 共識營收
A35: 共識 EBIT（口徑未揭露） | B35: US$bn | C35: =IF(ISNUMBER(輸入與假設!$C$247),輸入與假設!$C$247,"不適用") -> -0.2239 | D35: =IF(ISNUMBER(輸入與假設!$D$247),輸入與假設!$D$247,"不適用") -> -0.1615 | E35: 不適用 | F35: 不適用 | G35: 不適用 | H35: 不適用 | J35: 口徑未揭露：只列不比較
A36: 實際｜營收 | B36: US$bn | C36: =IF(ISNUMBER(輸入與假設!C$283),輸入與假設!C$283,"") | D36: =IF(ISNUMBER(輸入與假設!D$283),輸入與假設!D$283,"") | E36: =IF(ISNUMBER(輸入與假設!E$283),輸入與假設!E$283,"") | F36: =IF(ISNUMBER(輸入與假設!F$283),輸入與假設!F$283,"") | G36: =IF(ISNUMBER(輸入與假設!G$283),輸入與假設!G$283,"") | H36: =IF(ISNUMBER(輸入與假設!H$283),輸入與假設!H$283,"")
A37: 實際｜調整後 EBITDA | B37: US$bn | C37: =IF(ISNUMBER(輸入與假設!C$284),輸入與假設!C$284,"") | D37: =IF(ISNUMBER(輸入與假設!D$284),輸入與假設!D$284,"") | E37: =IF(ISNUMBER(輸入與假設!E$284),輸入與假設!E$284,"") | F37: =IF(ISNUMBER(輸入與假設!F$284),輸入與假設!F$284,"") | G37: =IF(ISNUMBER(輸入與假設!G$284),輸入與假設!G$284,"") | H37: =IF(ISNUMBER(輸入與假設!H$284),輸入與假設!H$284,"")
A38: 實際｜EBITDA 率 | B38: % | C38: =IF(AND(ISNUMBER(輸入與假設!C$284),ISNUMBER(輸入與假設!C$283)),輸入與假設!C$284/輸入與假設!C$283,"") | D38: =IF(AND(ISNUMBER(輸入與假設!D$284),ISNUMBER(輸入與假設!D$283)),輸入與假設!D$284/輸入與假設!D$283,"") | E38: =IF(AND(ISNUMBER(輸入與假設!E$284),ISNUMBER(輸入與假設!E$283)),輸入與假設!E$284/輸入與假設!E$283,"") | F38: =IF(AND(ISNUMBER(輸入與假設!F$284),ISNUMBER(輸入與假設!F$283)),輸入與假設!F$284/輸入與假設!F$283,"") | G38: =IF(AND(ISNUMBER(輸入與假設!G$284),ISNUMBER(輸入與假設!G$283)),輸入與假設!G$284/輸入與假設!G$283,"") | H38: =IF(AND(ISNUMBER(輸入與假設!H$284),ISNUMBER(輸入與假設!H$283)),輸入與假設!H$284/輸入與假設!H$283,"") | J38: ＝實際 EBITDA ÷ 實際營收
A39: 實際｜調整後營業利益 | B39: US$bn | C39: =IF(ISNUMBER(輸入與假設!C$285),輸入與假設!C$285,"") | D39: =IF(ISNUMBER(輸入與假設!D$285),輸入與假設!D$285,"") | E39: =IF(ISNUMBER(輸入與假設!E$285),輸入與假設!E$285,"") | F39: =IF(ISNUMBER(輸入與假設!F$285),輸入與假設!F$285,"") | G39: =IF(ISNUMBER(輸入與假設!G$285),輸入與假設!G$285,"") | H39: =IF(ISNUMBER(輸入與假設!H$285),輸入與假設!H$285,"")
A40: 實際｜CapEx（毛額） | B40: US$bn | C40: =IF(ISNUMBER(輸入與假設!C$286),輸入與假設!C$286,"") | D40: =IF(ISNUMBER(輸入與假設!D$286),輸入與假設!D$286,"") | E40: =IF(ISNUMBER(輸入與假設!E$286),輸入與假設!E$286,"") | F40: =IF(ISNUMBER(輸入與假設!F$286),輸入與假設!F$286,"") | G40: =IF(ISNUMBER(輸入與假設!G$286),輸入與假設!G$286,"") | H40: =IF(ISNUMBER(輸入與假設!H$286),輸入與假設!H$286,"")
A41: 實際｜季末 connected power（IT） | B41: MW | C41: =IF(ISNUMBER(輸入與假設!C$287),輸入與假設!C$287,"") | D41: =IF(ISNUMBER(輸入與假設!D$287),輸入與假設!D$287,"") | E41: =IF(ISNUMBER(輸入與假設!E$287),輸入與假設!E$287,"") | F41: =IF(ISNUMBER(輸入與假設!F$287),輸入與假設!F$287,"") | G41: =IF(ISNUMBER(輸入與假設!G$287),輸入與假設!G$287,"") | H41: =IF(ISNUMBER(輸入與假設!H$287),輸入與假設!H$287,"")
A42: 差距｜營收｜模型 vs 共識 | B42: % | C42: =IF(AND(ISNUMBER(C22),ISNUMBER(C32),C32<>0),C22/(C32)-1,"不適用") -> -0.28081705 | D42: =IF(AND(ISNUMBER(D22),ISNUMBER(D32),D32<>0),D22/(D32)-1,"不適用") -> -0.53230356 | E42: =IF(AND(ISNUMBER(E22),ISNUMBER(E32),E32<>0),E22/(E32)-1,"不適用") -> 不適用 | F42: =IF(AND(ISNUMBER(F22),ISNUMBER(F32),F32<>0),F22/(F32)-1,"不適用") -> 不適用 | G42: =IF(AND(ISNUMBER(G22),ISNUMBER(G32),G32<>0),G22/(G32)-1,"不適用") -> 不適用 | H42: =IF(AND(ISNUMBER(H22),ISNUMBER(H32),H32<>0),H22/(H32)-1,"不適用") -> 不適用
A43: 差距｜營收｜模型 vs 指引中點 | B43: % | C43: 不適用 | D43: 不適用 | E43: 不適用 | F43: 不適用 | G43: 不適用 | H43: 不適用
A44: 差距｜營收｜實際 vs 模型 | B44: % | C44: =IF(ISNUMBER(C36),IF(AND(ISNUMBER(C22),C22<>0),C36/(C22)-1,"不適用"),"") | D44: =IF(ISNUMBER(D36),IF(AND(ISNUMBER(D22),D22<>0),D36/(D22)-1,"不適用"),"") | E44: =IF(ISNUMBER(E36),IF(AND(ISNUMBER(E22),E22<>0),E36/(E22)-1,"不適用"),"") | F44: =IF(ISNUMBER(F36),IF(AND(ISNUMBER(F22),F22<>0),F36/(F22)-1,"不適用"),"") | G44: =IF(ISNUMBER(G36),IF(AND(ISNUMBER(G22),G22<>0),G36/(G22)-1,"不適用"),"") | H44: =IF(ISNUMBER(H36),IF(AND(ISNUMBER(H22),H22<>0),H36/(H22)-1,"不適用"),"")
A45: 差距｜營收｜實際 vs 共識 | B45: % | C45: =IF(ISNUMBER(C36),IF(AND(ISNUMBER(C32),C32<>0),C36/(C32)-1,"不適用"),"") | D45: =IF(ISNUMBER(D36),IF(AND(ISNUMBER(D32),D32<>0),D36/(D32)-1,"不適用"),"") | E45: =IF(ISNUMBER(E36),IF(AND(ISNUMBER(E32),E32<>0),E36/(E32)-1,"不適用"),"") | F45: =IF(ISNUMBER(F36),IF(AND(ISNUMBER(F32),F32<>0),F36/(F32)-1,"不適用"),"") | G45: =IF(ISNUMBER(G36),IF(AND(ISNUMBER(G32),G32<>0),G36/(G32)-1,"不適用"),"") | H45: =IF(ISNUMBER(H36),IF(AND(ISNUMBER(H32),H32<>0),H36/(H32)-1,"不適用"),"")
A46: 差距｜營收｜實際 vs 指引中點 | B46: % | C46: =IF(ISNUMBER(C36),"不適用","") | D46: =IF(ISNUMBER(D36),"不適用","") | E46: =IF(ISNUMBER(E36),"不適用","") | F46: =IF(ISNUMBER(F36),"不適用","") | G46: =IF(ISNUMBER(G36),"不適用","") | H46: =IF(ISNUMBER(H36),"不適用","")
A47: 差距｜調整後 EBITDA｜模型 vs 共識 | B47: US$bn | C47: =IF(AND(ISNUMBER(C28),ISNUMBER(C33)),C28-(C33),"不適用") -> -0.089728008 | D47: =IF(AND(ISNUMBER(D28),ISNUMBER(D33)),D28-(D33),"不適用") -> -0.43164687 | E47: =IF(AND(ISNUMBER(E28),ISNUMBER(E33)),E28-(E33),"不適用") -> 不適用 | F47: =IF(AND(ISNUMBER(F28),ISNUMBER(F33)),F28-(F33),"不適用") -> 不適用 | G47: =IF(AND(ISNUMBER(G28),ISNUMBER(G33)),G28-(G33),"不適用") -> 不適用 | H47: =IF(AND(ISNUMBER(H28),ISNUMBER(H33)),H28-(H33),"不適用") -> 不適用
A48: 差距｜調整後 EBITDA｜模型 vs 指引中點 | B48: US$bn | C48: 不適用 | D48: 不適用 | E48: 不適用 | F48: 不適用 | G48: 不適用 | H48: 不適用
A49: 差距｜調整後 EBITDA｜實際 vs 模型 | B49: US$bn | C49: =IF(ISNUMBER(C37),IF(AND(ISNUMBER(C28)),C37-(C28),"不適用"),"") | D49: =IF(ISNUMBER(D37),IF(AND(ISNUMBER(D28)),D37-(D28),"不適用"),"") | E49: =IF(ISNUMBER(E37),IF(AND(ISNUMBER(E28)),E37-(E28),"不適用"),"") | F49: =IF(ISNUMBER(F37),IF(AND(ISNUMBER(F28)),F37-(F28),"不適用"),"") | G49: =IF(ISNUMBER(G37),IF(AND(ISNUMBER(G28)),G37-(G28),"不適用"),"") | H49: =IF(ISNUMBER(H37),IF(AND(ISNUMBER(H28)),H37-(H28),"不適用"),"")
A50: 差距｜調整後 EBITDA｜實際 vs 共識 | B50: US$bn | C50: =IF(ISNUMBER(C37),IF(AND(ISNUMBER(C33)),C37-(C33),"不適用"),"") | D50: =IF(ISNUMBER(D37),IF(AND(ISNUMBER(D33)),D37-(D33),"不適用"),"") | E50: =IF(ISNUMBER(E37),IF(AND(ISNUMBER(E33)),E37-(E33),"不適用"),"") | F50: =IF(ISNUMBER(F37),IF(AND(ISNUMBER(F33)),F37-(F33),"不適用"),"") | G50: =IF(ISNUMBER(G37),IF(AND(ISNUMBER(G33)),G37-(G33),"不適用"),"") | H50: =IF(ISNUMBER(H37),IF(AND(ISNUMBER(H33)),H37-(H33),"不適用"),"")
A51: 差距｜調整後 EBITDA｜實際 vs 指引中點 | B51: US$bn | C51: =IF(ISNUMBER(C37),"不適用","") | D51: =IF(ISNUMBER(D37),"不適用","") | E51: =IF(ISNUMBER(E37),"不適用","") | F51: =IF(ISNUMBER(F37),"不適用","") | G51: =IF(ISNUMBER(G37),"不適用","") | H51: =IF(ISNUMBER(H37),"不適用","")
A52: 差距｜調整後 EBITDA｜模型 vs 共識（利潤率 pt） | B52: pt | C52: =IF(AND(ISNUMBER(C28),ISNUMBER(C22),C22<>0,ISNUMBER(C33),ISNUMBER(C32),C32<>0),C28/C22-C33/C32,"不適用") -> 0.018613906 | D52: =IF(AND(ISNUMBER(D28),ISNUMBER(D22),D22<>0,ISNUMBER(D33),ISNUMBER(D32),D32<>0),D28/D22-D33/D32,"不適用") -> -0.053055988 | E52: =IF(AND(ISNUMBER(E28),ISNUMBER(E22),E22<>0,ISNUMBER(E33),ISNUMBER(E32),E32<>0),E28/E22-E33/E32,"不適用") -> 不適用 | F52: =IF(AND(ISNUMBER(F28),ISNUMBER(F22),F22<>0,ISNUMBER(F33),ISNUMBER(F32),F32<>0),F28/F22-F33/F32,"不適用") -> 不適用 | G52: =IF(AND(ISNUMBER(G28),ISNUMBER(G22),G22<>0,ISNUMBER(G33),ISNUMBER(G32),G32<>0),G28/G22-G33/G32,"不適用") -> 不適用 | H52: =IF(AND(ISNUMBER(H28),ISNUMBER(H22),H22<>0,ISNUMBER(H33),ISNUMBER(H32),H32<>0),H28/H22-H33/H32,"不適用") -> 不適用
A53: 差距｜調整後 EBITDA｜模型 vs 指引中點（利潤率 pt） | B53: pt | C53: 不適用 | D53: 不適用 | E53: 不適用 | F53: 不適用 | G53: 不適用 | H53: 不適用
A54: 差距｜調整後 EBITDA｜實際 vs 模型（利潤率 pt） | B54: pt | C54: =IF(ISNUMBER(C37),IF(AND(ISNUMBER(C37),ISNUMBER(C36),C36<>0,ISNUMBER(C28),ISNUMBER(C22),C22<>0),C37/C36-C28/C22,"不適用"),"") | D54: =IF(ISNUMBER(D37),IF(AND(ISNUMBER(D37),ISNUMBER(D36),D36<>0,ISNUMBER(D28),ISNUMBER(D22),D22<>0),D37/D36-D28/D22,"不適用"),"") | E54: =IF(ISNUMBER(E37),IF(AND(ISNUMBER(E37),ISNUMBER(E36),E36<>0,ISNUMBER(E28),ISNUMBER(E22),E22<>0),E37/E36-E28/E22,"不適用"),"") | F54: =IF(ISNUMBER(F37),IF(AND(ISNUMBER(F37),ISNUMBER(F36),F36<>0,ISNUMBER(F28),ISNUMBER(F22),F22<>0),F37/F36-F28/F22,"不適用"),"") | G54: =IF(ISNUMBER(G37),IF(AND(ISNUMBER(G37),ISNUMBER(G36),G36<>0,ISNUMBER(G28),ISNUMBER(G22),G22<>0),G37/G36-G28/G22,"不適用"),"") | H54: =IF(ISNUMBER(H37),IF(AND(ISNUMBER(H37),ISNUMBER(H36),H36<>0,ISNUMBER(H28),ISNUMBER(H22),H22<>0),H37/H36-H28/H22,"不適用"),"")
A55: 差距｜調整後 EBITDA｜實際 vs 共識（利潤率 pt） | B55: pt | C55: =IF(ISNUMBER(C37),IF(AND(ISNUMBER(C37),ISNUMBER(C36),C36<>0,ISNUMBER(C33),ISNUMBER(C32),C32<>0),C37/C36-C33/C32,"不適用"),"") | D55: =IF(ISNUMBER(D37),IF(AND(ISNUMBER(D37),ISNUMBER(D36),D36<>0,ISNUMBER(D33),ISNUMBER(D32),D32<>0),D37/D36-D33/D32,"不適用"),"") | E55: =IF(ISNUMBER(E37),IF(AND(ISNUMBER(E37),ISNUMBER(E36),E36<>0,ISNUMBER(E33),ISNUMBER(E32),E32<>0),E37/E36-E33/E32,"不適用"),"") | F55: =IF(ISNUMBER(F37),IF(AND(ISNUMBER(F37),ISNUMBER(F36),F36<>0,ISNUMBER(F33),ISNUMBER(F32),F32<>0),F37/F36-F33/F32,"不適用"),"") | G55: =IF(ISNUMBER(G37),IF(AND(ISNUMBER(G37),ISNUMBER(G36),G36<>0,ISNUMBER(G33),ISNUMBER(G32),G32<>0),G37/G36-G33/G32,"不適用"),"") | H55: =IF(ISNUMBER(H37),IF(AND(ISNUMBER(H37),ISNUMBER(H36),H36<>0,ISNUMBER(H33),ISNUMBER(H32),H32<>0),H37/H36-H33/H32,"不適用"),"")
A56: 差距｜調整後 EBITDA｜實際 vs 指引中點（利潤率 pt） | B56: pt | C56: =IF(ISNUMBER(C37),"不適用","") | D56: =IF(ISNUMBER(D37),"不適用","") | E56: =IF(ISNUMBER(E37),"不適用","") | F56: =IF(ISNUMBER(F37),"不適用","") | G56: =IF(ISNUMBER(G37),"不適用","") | H56: =IF(ISNUMBER(H37),"不適用","")
A57: 差距｜EBITDA 率｜模型 vs 共識 | B57: pt | C57: =IF(AND(ISNUMBER(C27),ISNUMBER(C34)),C27-(C34),"不適用") -> 0.018613906 | D57: =IF(AND(ISNUMBER(D27),ISNUMBER(D34)),D27-(D34),"不適用") -> -0.053055988 | E57: =IF(AND(ISNUMBER(E27),ISNUMBER(E34)),E27-(E34),"不適用") -> 不適用 | F57: =IF(AND(ISNUMBER(F27),ISNUMBER(F34)),F27-(F34),"不適用") -> 不適用 | G57: =IF(AND(ISNUMBER(G27),ISNUMBER(G34)),G27-(G34),"不適用") -> 不適用 | H57: =IF(AND(ISNUMBER(H27),ISNUMBER(H34)),H27-(H34),"不適用") -> 不適用
A58: 差距｜EBITDA 率｜模型 vs 指引中點 | B58: pt | C58: 不適用 | D58: 不適用 | E58: 不適用 | F58: 不適用 | G58: 不適用 | H58: 不適用
A59: 差距｜EBITDA 率｜實際 vs 模型 | B59: pt | C59: =IF(ISNUMBER(C38),IF(AND(ISNUMBER(C27)),C38-(C27),"不適用"),"") | D59: =IF(ISNUMBER(D38),IF(AND(ISNUMBER(D27)),D38-(D27),"不適用"),"") | E59: =IF(ISNUMBER(E38),IF(AND(ISNUMBER(E27)),E38-(E27),"不適用"),"") | F59: =IF(ISNUMBER(F38),IF(AND(ISNUMBER(F27)),F38-(F27),"不適用"),"") | G59: =IF(ISNUMBER(G38),IF(AND(ISNUMBER(G27)),G38-(G27),"不適用"),"") | H59: =IF(ISNUMBER(H38),IF(AND(ISNUMBER(H27)),H38-(H27),"不適用"),"")
A60: 差距｜EBITDA 率｜實際 vs 共識 | B60: pt | C60: =IF(ISNUMBER(C38),IF(AND(ISNUMBER(C34)),C38-(C34),"不適用"),"") | D60: =IF(ISNUMBER(D38),IF(AND(ISNUMBER(D34)),D38-(D34),"不適用"),"") | E60: =IF(ISNUMBER(E38),IF(AND(ISNUMBER(E34)),E38-(E34),"不適用"),"") | F60: =IF(ISNUMBER(F38),IF(AND(ISNUMBER(F34)),F38-(F34),"不適用"),"") | G60: =IF(ISNUMBER(G38),IF(AND(ISNUMBER(G34)),G38-(G34),"不適用"),"") | H60: =IF(ISNUMBER(H38),IF(AND(ISNUMBER(H34)),H38-(H34),"不適用"),"")
A61: 差距｜EBITDA 率｜實際 vs 指引中點 | B61: pt | C61: =IF(ISNUMBER(C38),"不適用","") | D61: =IF(ISNUMBER(D38),"不適用","") | E61: =IF(ISNUMBER(E38),"不適用","") | F61: =IF(ISNUMBER(F38),"不適用","") | G61: =IF(ISNUMBER(G38),"不適用","") | H61: =IF(ISNUMBER(H38),"不適用","")
A62: 差距｜調整後營業利益｜模型 vs 共識 | B62: US$bn | C62: 不適用 | D62: 不適用 | E62: 不適用 | F62: 不適用 | G62: 不適用 | H62: 不適用
A63: 差距｜調整後營業利益｜模型 vs 指引中點 | B63: US$bn | C63: 不適用 | D63: 不適用 | E63: 不適用 | F63: 不適用 | G63: 不適用 | H63: 不適用
A64: 差距｜調整後營業利益｜實際 vs 模型 | B64: US$bn | C64: =IF(ISNUMBER(C39),IF(AND(ISNUMBER(C30)),C39-(C30),"不適用"),"") | D64: =IF(ISNUMBER(D39),IF(AND(ISNUMBER(D30)),D39-(D30),"不適用"),"") | E64: =IF(ISNUMBER(E39),IF(AND(ISNUMBER(E30)),E39-(E30),"不適用"),"") | F64: =IF(ISNUMBER(F39),IF(AND(ISNUMBER(F30)),F39-(F30),"不適用"),"") | G64: =IF(ISNUMBER(G39),IF(AND(ISNUMBER(G30)),G39-(G30),"不適用"),"") | H64: =IF(ISNUMBER(H39),IF(AND(ISNUMBER(H30)),H39-(H30),"不適用"),"")
A65: 差距｜調整後營業利益｜實際 vs 共識 | B65: US$bn | C65: =IF(ISNUMBER(C39),"不適用","") | D65: =IF(ISNUMBER(D39),"不適用","") | E65: =IF(ISNUMBER(E39),"不適用","") | F65: =IF(ISNUMBER(F39),"不適用","") | G65: =IF(ISNUMBER(G39),"不適用","") | H65: =IF(ISNUMBER(H39),"不適用","")
A66: 差距｜調整後營業利益｜實際 vs 指引中點 | B66: US$bn | C66: =IF(ISNUMBER(C39),"不適用","") | D66: =IF(ISNUMBER(D39),"不適用","") | E66: =IF(ISNUMBER(E39),"不適用","") | F66: =IF(ISNUMBER(F39),"不適用","") | G66: =IF(ISNUMBER(G39),"不適用","") | H66: =IF(ISNUMBER(H39),"不適用","")
A67: 差距｜調整後營業利益｜模型 vs 共識（利潤率 pt） | B67: pt | C67: 不適用 | D67: 不適用 | E67: 不適用 | F67: 不適用 | G67: 不適用 | H67: 不適用
A68: 差距｜調整後營業利益｜模型 vs 指引中點（利潤率 pt） | B68: pt | C68: 不適用 | D68: 不適用 | E68: 不適用 | F68: 不適用 | G68: 不適用 | H68: 不適用
A69: 差距｜調整後營業利益｜實際 vs 模型（利潤率 pt） | B69: pt | C69: =IF(ISNUMBER(C39),IF(AND(ISNUMBER(C39),ISNUMBER(C36),C36<>0,ISNUMBER(C30),ISNUMBER(C22),C22<>0),C39/C36-C30/C22,"不適用"),"") | D69: =IF(ISNUMBER(D39),IF(AND(ISNUMBER(D39),ISNUMBER(D36),D36<>0,ISNUMBER(D30),ISNUMBER(D22),D22<>0),D39/D36-D30/D22,"不適用"),"") | E69: =IF(ISNUMBER(E39),IF(AND(ISNUMBER(E39),ISNUMBER(E36),E36<>0,ISNUMBER(E30),ISNUMBER(E22),E22<>0),E39/E36-E30/E22,"不適用"),"") | F69: =IF(ISNUMBER(F39),IF(AND(ISNUMBER(F39),ISNUMBER(F36),F36<>0,ISNUMBER(F30),ISNUMBER(F22),F22<>0),F39/F36-F30/F22,"不適用"),"") | G69: =IF(ISNUMBER(G39),IF(AND(ISNUMBER(G39),ISNUMBER(G36),G36<>0,ISNUMBER(G30),ISNUMBER(G22),G22<>0),G39/G36-G30/G22,"不適用"),"") | H69: =IF(ISNUMBER(H39),IF(AND(ISNUMBER(H39),ISNUMBER(H36),H36<>0,ISNUMBER(H30),ISNUMBER(H22),H22<>0),H39/H36-H30/H22,"不適用"),"")
A70: 差距｜調整後營業利益｜實際 vs 共識（利潤率 pt） | B70: pt | C70: =IF(ISNUMBER(C39),"不適用","") | D70: =IF(ISNUMBER(D39),"不適用","") | E70: =IF(ISNUMBER(E39),"不適用","") | F70: =IF(ISNUMBER(F39),"不適用","") | G70: =IF(ISNUMBER(G39),"不適用","") | H70: =IF(ISNUMBER(H39),"不適用","")
A71: 差距｜調整後營業利益｜實際 vs 指引中點（利潤率 pt） | B71: pt | C71: =IF(ISNUMBER(C39),"不適用","") | D71: =IF(ISNUMBER(D39),"不適用","") | E71: =IF(ISNUMBER(E39),"不適用","") | F71: =IF(ISNUMBER(F39),"不適用","") | G71: =IF(ISNUMBER(G39),"不適用","") | H71: =IF(ISNUMBER(H39),"不適用","")
A72: 差距｜CapEx（毛額）｜模型 vs 共識 | B72: % | C72: 不適用 | D72: 不適用 | E72: 不適用 | F72: 不適用 | G72: 不適用 | H72: 不適用
A73: 差距｜CapEx（毛額）｜模型 vs 指引中點 | B73: % | C73: 不適用 | D73: 不適用 | E73: 不適用 | F73: 不適用 | G73: 不適用 | H73: 不適用
A74: 差距｜CapEx（毛額）｜實際 vs 模型 | B74: % | C74: =IF(ISNUMBER(C40),IF(AND(ISNUMBER(C31),C31<>0),C40/(C31)-1,"不適用"),"") | D74: =IF(ISNUMBER(D40),IF(AND(ISNUMBER(D31),D31<>0),D40/(D31)-1,"不適用"),"") | E74: =IF(ISNUMBER(E40),IF(AND(ISNUMBER(E31),E31<>0),E40/(E31)-1,"不適用"),"") | F74: =IF(ISNUMBER(F40),IF(AND(ISNUMBER(F31),F31<>0),F40/(F31)-1,"不適用"),"") | G74: =IF(ISNUMBER(G40),IF(AND(ISNUMBER(G31),G31<>0),G40/(G31)-1,"不適用"),"") | H74: =IF(ISNUMBER(H40),IF(AND(ISNUMBER(H31),H31<>0),H40/(H31)-1,"不適用"),"")
A75: 差距｜CapEx（毛額）｜實際 vs 共識 | B75: % | C75: =IF(ISNUMBER(C40),"不適用","") | D75: =IF(ISNUMBER(D40),"不適用","") | E75: =IF(ISNUMBER(E40),"不適用","") | F75: =IF(ISNUMBER(F40),"不適用","") | G75: =IF(ISNUMBER(G40),"不適用","") | H75: =IF(ISNUMBER(H40),"不適用","")
A76: 差距｜CapEx（毛額）｜實際 vs 指引中點 | B76: % | C76: =IF(ISNUMBER(C40),"不適用","") | D76: =IF(ISNUMBER(D40),"不適用","") | E76: =IF(ISNUMBER(E40),"不適用","") | F76: =IF(ISNUMBER(F40),"不適用","") | G76: =IF(ISNUMBER(G40),"不適用","") | H76: =IF(ISNUMBER(H40),"不適用","")
A77: 差距｜季末已連網 MW-IT｜模型 vs 共識 | B77: MW | C77: 不適用 | D77: 不適用 | E77: 不適用 | F77: 不適用 | G77: 不適用 | H77: 不適用
A78: 差距｜季末已連網 MW-IT｜模型 vs 指引中點 | B78: MW | C78: 不適用 | D78: 不適用 | E78: 不適用 | F78: 不適用 | G78: 不適用 | H78: 不適用
A79: 差距｜季末已連網 MW-IT｜實際 vs 模型 | B79: MW | C79: =IF(ISNUMBER(C41),IF(AND(ISNUMBER(C19)),C41-(C19),"不適用"),"") | D79: =IF(ISNUMBER(D41),IF(AND(ISNUMBER(D19)),D41-(D19),"不適用"),"") | E79: =IF(ISNUMBER(E41),IF(AND(ISNUMBER(E19)),E41-(E19),"不適用"),"") | F79: =IF(ISNUMBER(F41),IF(AND(ISNUMBER(F19)),F41-(F19),"不適用"),"") | G79: =IF(ISNUMBER(G41),IF(AND(ISNUMBER(G19)),G41-(G19),"不適用"),"") | H79: =IF(ISNUMBER(H41),IF(AND(ISNUMBER(H19)),H41-(H19),"不適用"),"")
A80: 差距｜季末已連網 MW-IT｜實際 vs 共識 | B80: MW | C80: =IF(ISNUMBER(C41),"不適用","") | D80: =IF(ISNUMBER(D41),"不適用","") | E80: =IF(ISNUMBER(E41),"不適用","") | F80: =IF(ISNUMBER(F41),"不適用","") | G80: =IF(ISNUMBER(G41),"不適用","") | H80: =IF(ISNUMBER(H41),"不適用","")
A81: 差距｜季末已連網 MW-IT｜實際 vs 指引中點 | B81: MW | C81: =IF(ISNUMBER(C41),"不適用","") | D81: =IF(ISNUMBER(D41),"不適用","") | E81: =IF(ISNUMBER(E41),"不適用","") | F81: =IF(ISNUMBER(F41),"不適用","") | G81: =IF(ISNUMBER(G41),"不適用","") | H81: =IF(ISNUMBER(H41),"不適用","")
A82: 合計基準｜營收｜vs 共識 | B82: US$bn | C82: =IF(COUNT(C32,D32)=2,C32+D32,"不適用") -> 2.4204 | D82: =IF(COUNT(C32,D32)=2,C32+D32,"不適用") -> 2.4204 | E82: =IF(COUNT(E32,F32,G32,H32)=4,E32+F32+G32+H32,"不適用") -> 不適用 | F82: =IF(COUNT(E32,F32,G32,H32)=4,E32+F32+G32+H32,"不適用") -> 不適用 | G82: =IF(COUNT(E32,F32,G32,H32)=4,E32+F32+G32+H32,"不適用") -> 不適用 | H82: =IF(COUNT(E32,F32,G32,H32)=4,E32+F32+G32+H32,"不適用") -> 不適用 | J82: 所屬期間的季度共識合計
A83: 拆解｜營收｜vs 共識｜水準 | B83: US$bn | C83: =IF(AND(ISNUMBER(C82),C82<>0,ISNUMBER(C32),ISNUMBER(C22)),(損益!C8-C82)*(C32)/C82,"不適用") -> -0.39470467 | D83: =IF(AND(ISNUMBER(D82),D82<>0,ISNUMBER(D32),ISNUMBER(D22)),(損益!C8-D82)*(D32)/D82,"不適用") -> -0.6674959 | E83: =IF(AND(ISNUMBER(E82),E82<>0,ISNUMBER(E32),ISNUMBER(E22)),(損益!D8-E82)*(E32)/E82,"不適用") -> 不適用 | F83: =IF(AND(ISNUMBER(F82),F82<>0,ISNUMBER(F32),ISNUMBER(F22)),(損益!D8-F82)*(F32)/F82,"不適用") -> 不適用 | G83: =IF(AND(ISNUMBER(G82),G82<>0,ISNUMBER(G32),ISNUMBER(G22)),(損益!D8-G82)*(G32)/G82,"不適用") -> 不適用 | H83: =IF(AND(ISNUMBER(H82),H82<>0,ISNUMBER(H32),ISNUMBER(H22)),(損益!D8-H82)*(H32)/H82,"不適用") -> 不適用 | J83: (模型期間 − 比較期間) × 比較的季占比
A84: 拆解｜營收｜vs 共識｜分配 | B84: US$bn | C84: =IF(AND(ISNUMBER(C82),C82<>0,ISNUMBER(C32),ISNUMBER(C22)),(C22/損益!C8-(C32)/C82)*損益!C8,"不適用") -> 0.14213782 | D84: =IF(AND(ISNUMBER(D82),D82<>0,ISNUMBER(D32),ISNUMBER(D22)),(D22/損益!C8-(D32)/D82)*損益!C8,"不適用") -> -0.14213782 | E84: =IF(AND(ISNUMBER(E82),E82<>0,ISNUMBER(E32),ISNUMBER(E22)),(E22/損益!D8-(E32)/E82)*損益!D8,"不適用") -> 不適用 | F84: =IF(AND(ISNUMBER(F82),F82<>0,ISNUMBER(F32),ISNUMBER(F22)),(F22/損益!D8-(F32)/F82)*損益!D8,"不適用") -> 不適用 | G84: =IF(AND(ISNUMBER(G82),G82<>0,ISNUMBER(G32),ISNUMBER(G22)),(G22/損益!D8-(G32)/G82)*損益!D8,"不適用") -> 不適用 | H84: =IF(AND(ISNUMBER(H82),H82<>0,ISNUMBER(H32),ISNUMBER(H22)),(H22/損益!D8-(H32)/H82)*損益!D8,"不適用") -> 不適用 | J84: (模型季占比 − 比較季占比) × 模型期間；水準＋分配＝季度差距
A85: 原因｜營收｜vs 共識 | C85: =IF(ISNUMBER(C42),IF(ABS(C42)>輸入與假設!$C$274,IF(ISNUMBER(C83),IF(ABS(C84)>ABS(C83),"營收 vs 共識 "&IF(C42<0,"−","+")&TEXT(ABS(C42)*100,"#,##0.0")&"%"&"：拆法（分配 "&IF(C84<0,"−","+")&IF(ABS(C84)<0,"−","")&"$"&TEXT(ABS(ABS(C84)),"#,##0.000")&"bn"&"（Q3'26 占 2H26 "&TEXT((C22/損益!C8)*100,"#,##0.0")&"%"&"，共識合計 "&TEXT(((C32)/C82)*100,"#,##0.0")&"%"&"）；水準 "&IF(C83<0,"−","+")&IF(ABS(C83)<0,"−","")&"$"&TEXT(ABS(ABS(C83)),"#,##0.000")&"bn"&"）","營收 vs 共識 "&IF(C42<0,"−","+")&TEXT(ABS(C42)*100,"#,##0.0")&"%"&"：觀點（水準 "&IF(C83<0,"−","+")&IF(ABS(C83)<0,"−","")&"$"&TEXT(ABS(ABS(C83)),"#,##0.000")&"bn"&"（2H26 模型 "&IF(損益!C8<0,"−","")&"$"&TEXT(ABS(損益!C8),"#,##0.000")&"bn"&"，共識合計 "&IF(C82<0,"−","")&"$"&TEXT(ABS(C82),"#,##0.000")&"bn"&"）；分配 "&IF(C84<0,"−","+")&IF(ABS(C84)<0,"−","")&"$"&TEXT(ABS(ABS(C84)),"#,##0.000")&"bn"&"；"&"每 MW 年收入＝Tokenomics 錨（IF_HoldEcon，在役世代加權）× 定價倍數 k（市場價格證據；v0.2a）；期初可計費 MW 以最新季實際營收年化校準，可計費 MW 依爬坡係數逐步收斂到已連網 MW（v0.1c）；共識未揭露 MW 與單價假設"&"）"),"營收 vs 共識 "&IF(C42<0,"−","+")&TEXT(ABS(C42)*100,"#,##0.0")&"%"&"：觀點（"&"每 MW 年收入＝Tokenomics 錨（IF_HoldEcon，在役世代加權）× 定價倍數 k（市場價格證據；v0.2a）；期初可計費 MW 以最新季實際營收年化校準，可計費 MW 依爬坡係數逐步收斂到已連網 MW（v0.1c）；共識未揭露 MW 與單價假設"&"）"),""),"") -> 營收 vs 共識 −28.1%：觀點（水準 −$0.395bn（2H26 模型 $1.358bn，共識合計 $2.420bn）；分配 +$0.142bn；每 MW 年收入＝Tokenomics 錨（IF_HoldEcon，在役世代加權）× 定價倍數 k（市場價格證據；v0.2a）；期初可計費 MW 以最新季實際營收年化校準，可計費 MW 依爬坡係數逐步收斂到已連網 MW（v0.1c）；共識未揭露 MW 與單價假設） | D85: =IF(ISNUMBER(D42),IF(ABS(D42)>輸入與假設!$C$274,IF(ISNUMBER(D83),IF(ABS(D84)>ABS(D83),"營收 vs 共識 "&IF(D42<0,"−","+")&TEXT(ABS(D42)*100,"#,##0.0")&"%"&"：拆法（分配 "&IF(D84<0,"−","+")&IF(ABS(D84)<0,"−","")&"$"&TEXT(ABS(ABS(D84)),"#,##0.000")&"bn"&"（Q4'26 占 2H26 "&TEXT((D22/損益!C8)*100,"#,##0.0")&"%"&"，共識合計 "&TEXT(((D32)/D82)*100,"#,##0.0")&"%"&"）；水準 "&IF(D83<0,"−","+")&IF(ABS(D83)<0,"−","")&"$"&TEXT(ABS(ABS(D83)),"#,##0.000")&"bn"&"）","營收 vs 共識 "&IF(D42<0,"−","+")&TEXT(ABS(D42)*100,"#,##0.0")&"%"&"：觀點（水準 "&IF(D83<0,"−","+")&IF(ABS(D83)<0,"−","")&"$"&TEXT(ABS(ABS(D83)),"#,##0.000")&"bn"&"（2H26 模型 "&IF(損益!C8<0,"−","")&"$"&TEXT(ABS(損益!C8),"#,##0.000")&"bn"&"，共識合計 "&IF(D82<0,"−","")&"$"&TEXT(ABS(D82),"#,##0.000")&"bn"&"）；分配 "&IF(D84<0,"−","+")&IF(ABS(D84)<0,"−","")&"$"&TEXT(ABS(ABS(D84)),"#,##0.000")&"bn"&"；"&"每 MW 年收入＝Tokenomics 錨（IF_HoldEcon，在役世代加權）× 定價倍數 k（市場價格證據；v0.2a）；期初可計費 MW 以最新季實際營收年化校準，可計費 MW 依爬坡係數逐步收斂到已連網 MW（v0.1c）；共識未揭露 MW 與單價假設"&"）"),"營收 vs 共識 "&IF(D42<0,"−","+")&TEXT(ABS(D42)*100,"#,##0.0")&"%"&"：觀點（"&"每 MW 年收入＝Tokenomics 錨（IF_HoldEcon，在役世代加權）× 定價倍數 k（市場價格證據；v0.2a）；期初可計費 MW 以最新季實際營收年化校準，可計費 MW 依爬坡係數逐步收斂到已連網 MW（v0.1c）；共識未揭露 MW 與單價假設"&"）"),""),"") -> 營收 vs 共識 −53.2%：觀點（水準 −$0.667bn（2H26 模型 $1.358bn，共識合計 $2.420bn）；分配 −$0.142bn；每 MW 年收入＝Tokenomics 錨（IF_HoldEcon，在役世代加權）× 定價倍數 k（市場價格證據；v0.2a）；期初可計費 MW 以最新季實際營收年化校準，可計費 MW 依爬坡係數逐步收斂到已連網 MW（v0.1c）；共識未揭露 MW 與單價假設） | E85: =IF(ISNUMBER(E42),IF(ABS(E42)>輸入與假設!$C$274,IF(ISNUMBER(E83),IF(ABS(E84)>ABS(E83),"營收 vs 共識 "&IF(E42<0,"−","+")&TEXT(ABS(E42)*100,"#,##0.0")&"%"&"：拆法（分配 "&IF(E84<0,"−","+")&IF(ABS(E84)<0,"−","")&"$"&TEXT(ABS(ABS(E84)),"#,##0.000")&"bn"&"（Q1'27 占 FY27 "&TEXT((E22/損益!D8)*100,"#,##0.0")&"%"&"，共識合計 "&TEXT(((E32)/E82)*100,"#,##0.0")&"%"&"）；水準 "&IF(E83<0,"−","+")&IF(ABS(E83)<0,"−","")&"$"&TEXT(ABS(ABS(E83)),"#,##0.000")&"bn"&"）","營收 vs 共識 "&IF(E42<0,"−","+")&TEXT(ABS(E42)*100,"#,##0.0")&"%"&"：觀點（水準 "&IF(E83<0,"−","+")&IF(ABS(E83)<0,"−","")&"$"&TEXT(ABS(ABS(E83)),"#,##0.000")&"bn"&"（FY27 模型 "&IF(損益!D8<0,"−","")&"$"&TEXT(ABS(損益!D8),"#,##0.000")&"bn"&"，共識合計 "&IF(E82<0,"−","")&"$"&TEXT(ABS(E82),"#,##0.000")&"bn"&"）；分配 "&IF(E84<0,"−","+")&IF(ABS(E84)<0,"−","")&"$"&TEXT(ABS(ABS(E84)),"#,##0.000")&"bn"&"；"&"每 MW 年收入＝Tokenomics 錨（IF_HoldEcon，在役世代加權）× 定價倍數 k（市場價格證據；v0.2a）；期初可計費 MW 以最新季實際營收年化校準，可計費 MW 依爬坡係數逐步收斂到已連網 MW（v0.1c）；共識未揭露 MW 與單價假設"&"）"),"營收 vs 共識 "&IF(E42<0,"−","+")&TEXT(ABS(E42)*100,"#,##0.0")&"%"&"：觀點（"&"每 MW 年收入＝Tokenomics 錨（IF_HoldEcon，在役世代加權）× 定價倍數 k（市場價格證據；v0.2a）；期初可計費 MW 以最新季實際營收年化校準，可計費 MW 依爬坡係數逐步收斂到已連網 MW（v0.1c）；共識未揭露 MW 與單價假設"&"）"),""),"") | F85: =IF(ISNUMBER(F42),IF(ABS(F42)>輸入與假設!$C$274,IF(ISNUMBER(F83),IF(ABS(F84)>ABS(F83),"營收 vs 共識 "&IF(F42<0,"−","+")&TEXT(ABS(F42)*100,"#,##0.0")&"%"&"：拆法（分配 "&IF(F84<0,"−","+")&IF(ABS(F84)<0,"−","")&"$"&TEXT(ABS(ABS(F84)),"#,##0.000")&"bn"&"（Q2'27 占 FY27 "&TEXT((F22/損益!D8)*100,"#,##0.0")&"%"&"，共識合計 "&TEXT(((F32)/F82)*100,"#,##0.0")&"%"&"）；水準 "&IF(F83<0,"−","+")&IF(ABS(F83)<0,"−","")&"$"&TEXT(ABS(ABS(F83)),"#,##0.000")&"bn"&"）","營收 vs 共識 "&IF(F42<0,"−","+")&TEXT(ABS(F42)*100,"#,##0.0")&"%"&"：觀點（水準 "&IF(F83<0,"−","+")&IF(ABS(F83)<0,"−","")&"$"&TEXT(ABS(ABS(F83)),"#,##0.000")&"bn"&"（FY27 模型 "&IF(損益!D8<0,"−","")&"$"&TEXT(ABS(損益!D8),"#,##0.000")&"bn"&"，共識合計 "&IF(F82<0,"−","")&"$"&TEXT(ABS(F82),"#,##0.000")&"bn"&"）；分配 "&IF(F84<0,"−","+")&IF(ABS(F84)<0,"−","")&"$"&TEXT(ABS(ABS(F84)),"#,##0.000")&"bn"&"；"&"每 MW 年收入＝Tokenomics 錨（IF_HoldEcon，在役世代加權）× 定價倍數 k（市場價格證據；v0.2a）；期初可計費 MW 以最新季實際營收年化校準，可計費 MW 依爬坡係數逐步收斂到已連網 MW（v0.1c）；共識未揭露 MW 與單價假設"&"）"),"營收 vs 共識 "&IF(F42<0,"−","+")&TEXT(ABS(F42)*100,"#,##0.0")&"%"&"：觀點（"&"每 MW 年收入＝Tokenomics 錨（IF_HoldEcon，在役世代加權）× 定價倍數 k（市場價格證據；v0.2a）；期初可計費 MW 以最新季實際營收年化校準，可計費 MW 依爬坡係數逐步收斂到已連網 MW（v0.1c）；共識未揭露 MW 與單價假設"&"）"),""),"") | G85: =IF(ISNUMBER(G42),IF(ABS(G42)>輸入與假設!$C$274,IF(ISNUMBER(G83),IF(ABS(G84)>ABS(G83),"營收 vs 共識 "&IF(G42<0,"−","+")&TEXT(ABS(G42)*100,"#,##0.0")&"%"&"：拆法（分配 "&IF(G84<0,"−","+")&IF(ABS(G84)<0,"−","")&"$"&TEXT(ABS(ABS(G84)),"#,##0.000")&"bn"&"（Q3'27 占 FY27 "&TEXT((G22/損益!D8)*100,"#,##0.0")&"%"&"，共識合計 "&TEXT(((G32)/G82)*100,"#,##0.0")&"%"&"）；水準 "&IF(G83<0,"−","+")&IF(ABS(G83)<0,"−","")&"$"&TEXT(ABS(ABS(G83)),"#,##0.000")&"bn"&"）","營收 vs 共識 "&IF(G42<0,"−","+")&TEXT(ABS(G42)*100,"#,##0.0")&"%"&"：觀點（水準 "&IF(G83<0,"−","+")&IF(ABS(G83)<0,"−","")&"$"&TEXT(ABS(ABS(G83)),"#,##0.000")&"bn"&"（FY27 模型 "&IF(損益!D8<0,"−","")&"$"&TEXT(ABS(損益!D8),"#,##0.000")&"bn"&"，共識合計 "&IF(G82<0,"−","")&"$"&TEXT(ABS(G82),"#,##0.000")&"bn"&"）；分配 "&IF(G84<0,"−","+")&IF(ABS(G84)<0,"−","")&"$"&TEXT(ABS(ABS(G84)),"#,##0.000")&"bn"&"；"&"每 MW 年收入＝Tokenomics 錨（IF_HoldEcon，在役世代加權）× 定價倍數 k（市場價格證據；v0.2a）；期初可計費 MW 以最新季實際營收年化校準，可計費 MW 依爬坡係數逐步收斂到已連網 MW（v0.1c）；共識未揭露 MW 與單價假設"&"）"),"營收 vs 共識 "&IF(G42<0,"−","+")&TEXT(ABS(G42)*100,"#,##0.0")&"%"&"：觀點（"&"每 MW 年收入＝Tokenomics 錨（IF_HoldEcon，在役世代加權）× 定價倍數 k（市場價格證據；v0.2a）；期初可計費 MW 以最新季實際營收年化校準，可計費 MW 依爬坡係數逐步收斂到已連網 MW（v0.1c）；共識未揭露 MW 與單價假設"&"）"),""),"") | H85: =IF(ISNUMBER(H42),IF(ABS(H42)>輸入與假設!$C$274,IF(ISNUMBER(H83),IF(ABS(H84)>ABS(H83),"營收 vs 共識 "&IF(H42<0,"−","+")&TEXT(ABS(H42)*100,"#,##0.0")&"%"&"：拆法（分配 "&IF(H84<0,"−","+")&IF(ABS(H84)<0,"−","")&"$"&TEXT(ABS(ABS(H84)),"#,##0.000")&"bn"&"（Q4'27 占 FY27 "&TEXT((H22/損益!D8)*100,"#,##0.0")&"%"&"，共識合計 "&TEXT(((H32)/H82)*100,"#,##0.0")&"%"&"）；水準 "&IF(H83<0,"−","+")&IF(ABS(H83)<0,"−","")&"$"&TEXT(ABS(ABS(H83)),"#,##0.000")&"bn"&"）","營收 vs 共識 "&IF(H42<0,"−","+")&TEXT(ABS(H42)*100,"#,##0.0")&"%"&"：觀點（水準 "&IF(H83<0,"−","+")&IF(ABS(H83)<0,"−","")&"$"&TEXT(ABS(ABS(H83)),"#,##0.000")&"bn"&"（FY27 模型 "&IF(損益!D8<0,"−","")&"$"&TEXT(ABS(損益!D8),"#,##0.000")&"bn"&"，共識合計 "&IF(H82<0,"−","")&"$"&TEXT(ABS(H82),"#,##0.000")&"bn"&"）；分配 "&IF(H84<0,"−","+")&IF(ABS(H84)<0,"−","")&"$"&TEXT(ABS(ABS(H84)),"#,##0.000")&"bn"&"；"&"每 MW 年收入＝Tokenomics 錨（IF_HoldEcon，在役世代加權）× 定價倍數 k（市場價格證據；v0.2a）；期初可計費 MW 以最新季實際營收年化校準，可計費 MW 依爬坡係數逐步收斂到已連網 MW（v0.1c）；共識未揭露 MW 與單價假設"&"）"),"營收 vs 共識 "&IF(H42<0,"−","+")&TEXT(ABS(H42)*100,"#,##0.0")&"%"&"：觀點（"&"每 MW 年收入＝Tokenomics 錨（IF_HoldEcon，在役世代加權）× 定價倍數 k（市場價格證據；v0.2a）；期初可計費 MW 以最新季實際營收年化校準，可計費 MW 依爬坡係數逐步收斂到已連網 MW（v0.1c）；共識未揭露 MW 與單價假設"&"）"),""),"")
A86: 原因類型｜營收｜vs 共識 | C86: =IF(ISNUMBER(C42),IF(ABS(C42)>輸入與假設!$C$274,IF(ISNUMBER(C83),IF(ABS(C84)>ABS(C83),"拆法","觀點"),"觀點"),""),"") -> 觀點 | D86: =IF(ISNUMBER(D42),IF(ABS(D42)>輸入與假設!$C$274,IF(ISNUMBER(D83),IF(ABS(D84)>ABS(D83),"拆法","觀點"),"觀點"),""),"") -> 觀點 | E86: =IF(ISNUMBER(E42),IF(ABS(E42)>輸入與假設!$C$274,IF(ISNUMBER(E83),IF(ABS(E84)>ABS(E83),"拆法","觀點"),"觀點"),""),"") | F86: =IF(ISNUMBER(F42),IF(ABS(F42)>輸入與假設!$C$274,IF(ISNUMBER(F83),IF(ABS(F84)>ABS(F83),"拆法","觀點"),"觀點"),""),"") | G86: =IF(ISNUMBER(G42),IF(ABS(G42)>輸入與假設!$C$274,IF(ISNUMBER(G83),IF(ABS(G84)>ABS(G83),"拆法","觀點"),"觀點"),""),"") | H86: =IF(ISNUMBER(H42),IF(ABS(H42)>輸入與假設!$C$274,IF(ISNUMBER(H83),IF(ABS(H84)>ABS(H83),"拆法","觀點"),"觀點"),""),"")
A87: 原因｜營收｜vs 指引中點
A88: 原因類型｜營收｜vs 指引中點
A89: 原因｜營收｜實際 vs 模型 | C89: =IF(ISNUMBER(C44),IF(ABS(C44)>輸入與假設!$C$274,"營收 實際 vs 模型 "&IF(C44<0,"−","+")&TEXT(ABS(C44)*100,"#,##0.0")&"%"&"：觀點（"&"每 MW 年收入＝Tokenomics 錨（IF_HoldEcon，在役世代加權）× 定價倍數 k（市場價格證據；v0.2a）；期初可計費 MW 以最新季實際營收年化校準，可計費 MW 依爬坡係數逐步收斂到已連網 MW（v0.1c）；共識未揭露 MW 與單價假設"&"）",""),"") | D89: =IF(ISNUMBER(D44),IF(ABS(D44)>輸入與假設!$C$274,"營收 實際 vs 模型 "&IF(D44<0,"−","+")&TEXT(ABS(D44)*100,"#,##0.0")&"%"&"：觀點（"&"每 MW 年收入＝Tokenomics 錨（IF_HoldEcon，在役世代加權）× 定價倍數 k（市場價格證據；v0.2a）；期初可計費 MW 以最新季實際營收年化校準，可計費 MW 依爬坡係數逐步收斂到已連網 MW（v0.1c）；共識未揭露 MW 與單價假設"&"）",""),"") | E89: =IF(ISNUMBER(E44),IF(ABS(E44)>輸入與假設!$C$274,"營收 實際 vs 模型 "&IF(E44<0,"−","+")&TEXT(ABS(E44)*100,"#,##0.0")&"%"&"：觀點（"&"每 MW 年收入＝Tokenomics 錨（IF_HoldEcon，在役世代加權）× 定價倍數 k（市場價格證據；v0.2a）；期初可計費 MW 以最新季實際營收年化校準，可計費 MW 依爬坡係數逐步收斂到已連網 MW（v0.1c）；共識未揭露 MW 與單價假設"&"）",""),"") | F89: =IF(ISNUMBER(F44),IF(ABS(F44)>輸入與假設!$C$274,"營收 實際 vs 模型 "&IF(F44<0,"−","+")&TEXT(ABS(F44)*100,"#,##0.0")&"%"&"：觀點（"&"每 MW 年收入＝Tokenomics 錨（IF_HoldEcon，在役世代加權）× 定價倍數 k（市場價格證據；v0.2a）；期初可計費 MW 以最新季實際營收年化校準，可計費 MW 依爬坡係數逐步收斂到已連網 MW（v0.1c）；共識未揭露 MW 與單價假設"&"）",""),"") | G89: =IF(ISNUMBER(G44),IF(ABS(G44)>輸入與假設!$C$274,"營收 實際 vs 模型 "&IF(G44<0,"−","+")&TEXT(ABS(G44)*100,"#,##0.0")&"%"&"：觀點（"&"每 MW 年收入＝Tokenomics 錨（IF_HoldEcon，在役世代加權）× 定價倍數 k（市場價格證據；v0.2a）；期初可計費 MW 以最新季實際營收年化校準，可計費 MW 依爬坡係數逐步收斂到已連網 MW（v0.1c）；共識未揭露 MW 與單價假設"&"）",""),"") | H89: =IF(ISNUMBER(H44),IF(ABS(H44)>輸入與假設!$C$274,"營收 實際 vs 模型 "&IF(H44<0,"−","+")&TEXT(ABS(H44)*100,"#,##0.0")&"%"&"：觀點（"&"每 MW 年收入＝Tokenomics 錨（IF_HoldEcon，在役世代加權）× 定價倍數 k（市場價格證據；v0.2a）；期初可計費 MW 以最新季實際營收年化校準，可計費 MW 依爬坡係數逐步收斂到已連網 MW（v0.1c）；共識未揭露 MW 與單價假設"&"）",""),"")
A90: 原因類型｜營收｜實際 vs 模型 | C90: =IF(ISNUMBER(C44),IF(ABS(C44)>輸入與假設!$C$274,"觀點",""),"") | D90: =IF(ISNUMBER(D44),IF(ABS(D44)>輸入與假設!$C$274,"觀點",""),"") | E90: =IF(ISNUMBER(E44),IF(ABS(E44)>輸入與假設!$C$274,"觀點",""),"") | F90: =IF(ISNUMBER(F44),IF(ABS(F44)>輸入與假設!$C$274,"觀點",""),"") | G90: =IF(ISNUMBER(G44),IF(ABS(G44)>輸入與假設!$C$274,"觀點",""),"") | H90: =IF(ISNUMBER(H44),IF(ABS(H44)>輸入與假設!$C$274,"觀點",""),"")
A91: 合計基準｜調整後 EBITDA｜vs 共識 | B91: US$bn | C91: =IF(COUNT(C33,D33)=2,C33+D33,"不適用") -> 1.1024 | D91: =IF(COUNT(C33,D33)=2,C33+D33,"不適用") -> 1.1024 | E91: =IF(COUNT(E33,F33,G33,H33)=4,E33+F33+G33+H33,"不適用") -> 不適用 | F91: =IF(COUNT(E33,F33,G33,H33)=4,E33+F33+G33+H33,"不適用") -> 不適用 | G91: =IF(COUNT(E33,F33,G33,H33)=4,E33+F33+G33+H33,"不適用") -> 不適用 | H91: =IF(COUNT(E33,F33,G33,H33)=4,E33+F33+G33+H33,"不適用") -> 不適用 | J91: 所屬期間的季度共識合計
A92: 拆解｜調整後 EBITDA｜vs 共識｜水準 | B92: US$bn | C92: =IF(AND(ISNUMBER(C91),C91<>0,ISNUMBER(C33),ISNUMBER(C28)),(損益!C19-C91)*(C33)/C91,"不適用") -> -0.17139537 | D92: =IF(AND(ISNUMBER(D91),D91<>0,ISNUMBER(D33),ISNUMBER(D28)),(損益!C19-D91)*(D33)/D91,"不適用") -> -0.34997951 | E92: =IF(AND(ISNUMBER(E91),E91<>0,ISNUMBER(E33),ISNUMBER(E28)),(損益!D19-E91)*(E33)/E91,"不適用") -> 不適用 | F92: =IF(AND(ISNUMBER(F91),F91<>0,ISNUMBER(F33),ISNUMBER(F28)),(損益!D19-F91)*(F33)/F91,"不適用") -> 不適用 | G92: =IF(AND(ISNUMBER(G91),G91<>0,ISNUMBER(G33),ISNUMBER(G28)),(損益!D19-G91)*(G33)/G91,"不適用") -> 不適用 | H92: =IF(AND(ISNUMBER(H91),H91<>0,ISNUMBER(H33),ISNUMBER(H28)),(損益!D19-H91)*(H33)/H91,"不適用") -> 不適用 | J92: (模型期間 − 比較期間) × 比較的季占比
A93: 拆解｜調整後 EBITDA｜vs 共識｜分配 | B93: US$bn | C93: =IF(AND(ISNUMBER(C91),C91<>0,ISNUMBER(C33),ISNUMBER(C28)),(C28/損益!C19-(C33)/C91)*損益!C19,"不適用") -> 0.081667363 | D93: =IF(AND(ISNUMBER(D91),D91<>0,ISNUMBER(D33),ISNUMBER(D28)),(D28/損益!C19-(D33)/D91)*損益!C19,"不適用") -> -0.081667363 | E93: =IF(AND(ISNUMBER(E91),E91<>0,ISNUMBER(E33),ISNUMBER(E28)),(E28/損益!D19-(E33)/E91)*損益!D19,"不適用") -> 不適用 | F93: =IF(AND(ISNUMBER(F91),F91<>0,ISNUMBER(F33),ISNUMBER(F28)),(F28/損益!D19-(F33)/F91)*損益!D19,"不適用") -> 不適用 | G93: =IF(AND(ISNUMBER(G91),G91<>0,ISNUMBER(G33),ISNUMBER(G28)),(G28/損益!D19-(G33)/G91)*損益!D19,"不適用") -> 不適用 | H93: =IF(AND(ISNUMBER(H91),H91<>0,ISNUMBER(H33),ISNUMBER(H28)),(H28/損益!D19-(H33)/H91)*損益!D19,"不適用") -> 不適用 | J93: (模型季占比 − 比較季占比) × 模型期間；水準＋分配＝季度差距
A94: 原因｜調整後 EBITDA｜vs 共識 | C94: =IF(ISNUMBER(C47),IF(IF(ISNUMBER(C52),ABS(C52)>輸入與假設!$C$275,OR(AND(C33<>0,ABS(C47)>輸入與假設!$C$274*ABS(C33)),AND(C33=0,C47<>0))),IF(ISNUMBER(C92),IF(ABS(C93)>ABS(C92),"調整後 EBITDA vs 共識 "&IF(C47<0,"−","+")&IF(ABS(C47)<0,"−","")&"$"&TEXT(ABS(ABS(C47)),"#,##0.00")&"bn"&IF(ISNUMBER(C52),"／"&IF(C52<0,"−","+")&TEXT(ABS(C52)*100,"#,##0.0")&"pt","")&"：拆法（分配 "&IF(C93<0,"−","+")&IF(ABS(C93)<0,"−","")&"$"&TEXT(ABS(ABS(C93)),"#,##0.000")&"bn"&"（Q3'26 占 2H26 "&TEXT((C28/損益!C19)*100,"#,##0.0")&"%"&"，共識合計 "&TEXT(((C33)/C91)*100,"#,##0.0")&"%"&"）；水準 "&IF(C92<0,"−","+")&IF(ABS(C92)<0,"−","")&"$"&TEXT(ABS(ABS(C92)),"#,##0.000")&"bn"&"）","調整後 EBITDA vs 共識 "&IF(C47<0,"−","+")&IF(ABS(C47)<0,"−","")&"$"&TEXT(ABS(ABS(C47)),"#,##0.00")&"bn"&IF(ISNUMBER(C52),"／"&IF(C52<0,"−","+")&TEXT(ABS(C52)*100,"#,##0.0")&"pt","")&"：觀點（水準 "&IF(C92<0,"−","+")&IF(ABS(C92)<0,"−","")&"$"&TEXT(ABS(ABS(C92)),"#,##0.000")&"bn"&"（2H26 模型 "&IF(損益!C19<0,"−","")&"$"&TEXT(ABS(損益!C19),"#,##0.000")&"bn"&"，共識合計 "&IF(C91<0,"−","")&"$"&TEXT(ABS(C91),"#,##0.000")&"bn"&"）；分配 "&IF(C93<0,"−","+")&IF(ABS(C93)<0,"−","")&"$"&TEXT(ABS(ABS(C93)),"#,##0.000")&"bn"&"；"&"模型 EBITDA 率 "&IF((C27)<0,"−","")&TEXT(ABS((C27))*100,"#,##0.0")&"%"&"；季度共識 EBITDA "&IF((輸入與假設!$C$246)<0,"−","")&TEXT(ABS((輸入與假設!$C$246)),"#,##0.00")&"、營收 "&IF((輸入與假設!$C$245)<0,"−","")&TEXT(ABS((輸入與假設!$C$245)),"#,##0.00")&"（口徑未揭露）"&"）"),"調整後 EBITDA vs 共識 "&IF(C47<0,"−","+")&IF(ABS(C47)<0,"−","")&"$"&TEXT(ABS(ABS(C47)),"#,##0.00")&"bn"&IF(ISNUMBER(C52),"／"&IF(C52<0,"−","+")&TEXT(ABS(C52)*100,"#,##0.0")&"pt","")&"：觀點（"&"模型 EBITDA 率 "&IF((C27)<0,"−","")&TEXT(ABS((C27))*100,"#,##0.0")&"%"&"；季度共識 EBITDA "&IF((輸入與假設!$C$246)<0,"−","")&TEXT(ABS((輸入與假設!$C$246)),"#,##0.00")&"、營收 "&IF((輸入與假設!$C$245)<0,"−","")&TEXT(ABS((輸入與假設!$C$245)),"#,##0.00")&"（口徑未揭露）"&"）"),""),"") | D94: =IF(ISNUMBER(D47),IF(IF(ISNUMBER(D52),ABS(D52)>輸入與假設!$C$275,OR(AND(D33<>0,ABS(D47)>輸入與假設!$C$274*ABS(D33)),AND(D33=0,D47<>0))),IF(ISNUMBER(D92),IF(ABS(D93)>ABS(D92),"調整後 EBITDA vs 共識 "&IF(D47<0,"−","+")&IF(ABS(D47)<0,"−","")&"$"&TEXT(ABS(ABS(D47)),"#,##0.00")&"bn"&IF(ISNUMBER(D52),"／"&IF(D52<0,"−","+")&TEXT(ABS(D52)*100,"#,##0.0")&"pt","")&"：拆法（分配 "&IF(D93<0,"−","+")&IF(ABS(D93)<0,"−","")&"$"&TEXT(ABS(ABS(D93)),"#,##0.000")&"bn"&"（Q4'26 占 2H26 "&TEXT((D28/損益!C19)*100,"#,##0.0")&"%"&"，共識合計 "&TEXT(((D33)/D91)*100,"#,##0.0")&"%"&"）；水準 "&IF(D92<0,"−","+")&IF(ABS(D92)<0,"−","")&"$"&TEXT(ABS(ABS(D92)),"#,##0.000")&"bn"&"）","調整後 EBITDA vs 共識 "&IF(D47<0,"−","+")&IF(ABS(D47)<0,"−","")&"$"&TEXT(ABS(ABS(D47)),"#,##0.00")&"bn"&IF(ISNUMBER(D52),"／"&IF(D52<0,"−","+")&TEXT(ABS(D52)*100,"#,##0.0")&"pt","")&"：觀點（水準 "&IF(D92<0,"−","+")&IF(ABS(D92)<0,"−","")&"$"&TEXT(ABS(ABS(D92)),"#,##0.000")&"bn"&"（2H26 模型 "&IF(損益!C19<0,"−","")&"$"&TEXT(ABS(損益!C19),"#,##0.000")&"bn"&"，共識合計 "&IF(D91<0,"−","")&"$"&TEXT(ABS(D91),"#,##0.000")&"bn"&"）；分配 "&IF(D93<0,"−","+")&IF(ABS(D93)<0,"−","")&"$"&TEXT(ABS(ABS(D93)),"#,##0.000")&"bn"&"；"&"模型 EBITDA 率 "&IF((D27)<0,"−","")&TEXT(ABS((D27))*100,"#,##0.0")&"%"&"；季度共識 EBITDA "&IF((輸入與假設!$D$246)<0,"−","")&TEXT(ABS((輸入與假設!$D$246)),"#,##0.00")&"、營收 "&IF((輸入與假設!$D$245)<0,"−","")&TEXT(ABS((輸入與假設!$D$245)),"#,##0.00")&"（口徑未揭露）"&"）"),"調整後 EBITDA vs 共識 "&IF(D47<0,"−","+")&IF(ABS(D47)<0,"−","")&"$"&TEXT(ABS(ABS(D47)),"#,##0.00")&"bn"&IF(ISNUMBER(D52),"／"&IF(D52<0,"−","+")&TEXT(ABS(D52)*100,"#,##0.0")&"pt","")&"：觀點（"&"模型 EBITDA 率 "&IF((D27)<0,"−","")&TEXT(ABS((D27))*100,"#,##0.0")&"%"&"；季度共識 EBITDA "&IF((輸入與假設!$D$246)<0,"−","")&TEXT(ABS((輸入與假設!$D$246)),"#,##0.00")&"、營收 "&IF((輸入與假設!$D$245)<0,"−","")&TEXT(ABS((輸入與假設!$D$245)),"#,##0.00")&"（口徑未揭露）"&"）"),""),"") -> 調整後 EBITDA vs 共識 −$0.43bn／−5.3pt：觀點（水準 −$0.350bn（2H26 模型 $0.581bn，共識合計 $1.102bn）；分配 −$0.082bn；模型 EBITDA 率 43.3%；季度共識 EBITDA 0.74、營收 1.52（口徑未揭露）） | E94: =IF(ISNUMBER(E47),IF(IF(ISNUMBER(E52),ABS(E52)>輸入與假設!$C$275,OR(AND(E33<>0,ABS(E47)>輸入與假設!$C$274*ABS(E33)),AND(E33=0,E47<>0))),IF(ISNUMBER(E92),IF(ABS(E93)>ABS(E92),"調整後 EBITDA vs 共識 "&IF(E47<0,"−","+")&IF(ABS(E47)<0,"−","")&"$"&TEXT(ABS(ABS(E47)),"#,##0.00")&"bn"&IF(ISNUMBER(E52),"／"&IF(E52<0,"−","+")&TEXT(ABS(E52)*100,"#,##0.0")&"pt","")&"：拆法（分配 "&IF(E93<0,"−","+")&IF(ABS(E93)<0,"−","")&"$"&TEXT(ABS(ABS(E93)),"#,##0.000")&"bn"&"（Q1'27 占 FY27 "&TEXT((E28/損益!D19)*100,"#,##0.0")&"%"&"，共識合計 "&TEXT(((E33)/E91)*100,"#,##0.0")&"%"&"）；水準 "&IF(E92<0,"−","+")&IF(ABS(E92)<0,"−","")&"$"&TEXT(ABS(ABS(E92)),"#,##0.000")&"bn"&"）","調整後 EBITDA vs 共識 "&IF(E47<0,"−","+")&IF(ABS(E47)<0,"−","")&"$"&TEXT(ABS(ABS(E47)),"#,##0.00")&"bn"&IF(ISNUMBER(E52),"／"&IF(E52<0,"−","+")&TEXT(ABS(E52)*100,"#,##0.0")&"pt","")&"：觀點（水準 "&IF(E92<0,"−","+")&IF(ABS(E92)<0,"−","")&"$"&TEXT(ABS(ABS(E92)),"#,##0.000")&"bn"&"（FY27 模型 "&IF(損益!D19<0,"−","")&"$"&TEXT(ABS(損益!D19),"#,##0.000")&"bn"&"，共識合計 "&IF(E91<0,"−","")&"$"&TEXT(ABS(E91),"#,##0.000")&"bn"&"）；分配 "&IF(E93<0,"−","+")&IF(ABS(E93)<0,"−","")&"$"&TEXT(ABS(ABS(E93)),"#,##0.000")&"bn"&"；"&"模型 EBITDA 率 "&IF((E27)<0,"−","")&TEXT(ABS((E27))*100,"#,##0.0")&"%"&"；季度共識 EBITDA "&"不適用"&"、營收 "&"不適用"&"（口徑未揭露）"&"）"),"調整後 EBITDA vs 共識 "&IF(E47<0,"−","+")&IF(ABS(E47)<0,"−","")&"$"&TEXT(ABS(ABS(E47)),"#,##0.00")&"bn"&IF(ISNUMBER(E52),"／"&IF(E52<0,"−","+")&TEXT(ABS(E52)*100,"#,##0.0")&"pt","")&"：觀點（"&"模型 EBITDA 率 "&IF((E27)<0,"−","")&TEXT(ABS((E27))*100,"#,##0.0")&"%"&"；季度共識 EBITDA "&"不適用"&"、營收 "&"不適用"&"（口徑未揭露）"&"）"),""),"") | F94: =IF(ISNUMBER(F47),IF(IF(ISNUMBER(F52),ABS(F52)>輸入與假設!$C$275,OR(AND(F33<>0,ABS(F47)>輸入與假設!$C$274*ABS(F33)),AND(F33=0,F47<>0))),IF(ISNUMBER(F92),IF(ABS(F93)>ABS(F92),"調整後 EBITDA vs 共識 "&IF(F47<0,"−","+")&IF(ABS(F47)<0,"−","")&"$"&TEXT(ABS(ABS(F47)),"#,##0.00")&"bn"&IF(ISNUMBER(F52),"／"&IF(F52<0,"−","+")&TEXT(ABS(F52)*100,"#,##0.0")&"pt","")&"：拆法（分配 "&IF(F93<0,"−","+")&IF(ABS(F93)<0,"−","")&"$"&TEXT(ABS(ABS(F93)),"#,##0.000")&"bn"&"（Q2'27 占 FY27 "&TEXT((F28/損益!D19)*100,"#,##0.0")&"%"&"，共識合計 "&TEXT(((F33)/F91)*100,"#,##0.0")&"%"&"）；水準 "&IF(F92<0,"−","+")&IF(ABS(F92)<0,"−","")&"$"&TEXT(ABS(ABS(F92)),"#,##0.000")&"bn"&"）","調整後 EBITDA vs 共識 "&IF(F47<0,"−","+")&IF(ABS(F47)<0,"−","")&"$"&TEXT(ABS(ABS(F47)),"#,##0.00")&"bn"&IF(ISNUMBER(F52),"／"&IF(F52<0,"−","+")&TEXT(ABS(F52)*100,"#,##0.0")&"pt","")&"：觀點（水準 "&IF(F92<0,"−","+")&IF(ABS(F92)<0,"−","")&"$"&TEXT(ABS(ABS(F92)),"#,##0.000")&"bn"&"（FY27 模型 "&IF(損益!D19<0,"−","")&"$"&TEXT(ABS(損益!D19),"#,##0.000")&"bn"&"，共識合計 "&IF(F91<0,"−","")&"$"&TEXT(ABS(F91),"#,##0.000")&"bn"&"）；分配 "&IF(F93<0,"−","+")&IF(ABS(F93)<0,"−","")&"$"&TEXT(ABS(ABS(F93)),"#,##0.000")&"bn"&"；"&"模型 EBITDA 率 "&IF((F27)<0,"−","")&TEXT(ABS((F27))*100,"#,##0.0")&"%"&"；季度共識 EBITDA "&"不適用"&"、營收 "&"不適用"&"（口徑未揭露）"&"）"),"調整後 EBITDA vs 共識 "&IF(F47<0,"−","+")&IF(ABS(F47)<0,"−","")&"$"&TEXT(ABS(ABS(F47)),"#,##0.00")&"bn"&IF(ISNUMBER(F52),"／"&IF(F52<0,"−","+")&TEXT(ABS(F52)*100,"#,##0.0")&"pt","")&"：觀點（"&"模型 EBITDA 率 "&IF((F27)<0,"−","")&TEXT(ABS((F27))*100,"#,##0.0")&"%"&"；季度共識 EBITDA "&"不適用"&"、營收 "&"不適用"&"（口徑未揭露）"&"）"),""),"") | G94: =IF(ISNUMBER(G47),IF(IF(ISNUMBER(G52),ABS(G52)>輸入與假設!$C$275,OR(AND(G33<>0,ABS(G47)>輸入與假設!$C$274*ABS(G33)),AND(G33=0,G47<>0))),IF(ISNUMBER(G92),IF(ABS(G93)>ABS(G92),"調整後 EBITDA vs 共識 "&IF(G47<0,"−","+")&IF(ABS(G47)<0,"−","")&"$"&TEXT(ABS(ABS(G47)),"#,##0.00")&"bn"&IF(ISNUMBER(G52),"／"&IF(G52<0,"−","+")&TEXT(ABS(G52)*100,"#,##0.0")&"pt","")&"：拆法（分配 "&IF(G93<0,"−","+")&IF(ABS(G93)<0,"−","")&"$"&TEXT(ABS(ABS(G93)),"#,##0.000")&"bn"&"（Q3'27 占 FY27 "&TEXT((G28/損益!D19)*100,"#,##0.0")&"%"&"，共識合計 "&TEXT(((G33)/G91)*100,"#,##0.0")&"%"&"）；水準 "&IF(G92<0,"−","+")&IF(ABS(G92)<0,"−","")&"$"&TEXT(ABS(ABS(G92)),"#,##0.000")&"bn"&"）","調整後 EBITDA vs 共識 "&IF(G47<0,"−","+")&IF(ABS(G47)<0,"−","")&"$"&TEXT(ABS(ABS(G47)),"#,##0.00")&"bn"&IF(ISNUMBER(G52),"／"&IF(G52<0,"−","+")&TEXT(ABS(G52)*100,"#,##0.0")&"pt","")&"：觀點（水準 "&IF(G92<0,"−","+")&IF(ABS(G92)<0,"−","")&"$"&TEXT(ABS(ABS(G92)),"#,##0.000")&"bn"&"（FY27 模型 "&IF(損益!D19<0,"−","")&"$"&TEXT(ABS(損益!D19),"#,##0.000")&"bn"&"，共識合計 "&IF(G91<0,"−","")&"$"&TEXT(ABS(G91),"#,##0.000")&"bn"&"）；分配 "&IF(G93<0,"−","+")&IF(ABS(G93)<0,"−","")&"$"&TEXT(ABS(ABS(G93)),"#,##0.000")&"bn"&"；"&"模型 EBITDA 率 "&IF((G27)<0,"−","")&TEXT(ABS((G27))*100,"#,##0.0")&"%"&"；季度共識 EBITDA "&"不適用"&"、營收 "&"不適用"&"（口徑未揭露）"&"）"),"調整後 EBITDA vs 共識 "&IF(G47<0,"−","+")&IF(ABS(G47)<0,"−","")&"$"&TEXT(ABS(ABS(G47)),"#,##0.00")&"bn"&IF(ISNUMBER(G52),"／"&IF(G52<0,"−","+")&TEXT(ABS(G52)*100,"#,##0.0")&"pt","")&"：觀點（"&"模型 EBITDA 率 "&IF((G27)<0,"−","")&TEXT(ABS((G27))*100,"#,##0.0")&"%"&"；季度共識 EBITDA "&"不適用"&"、營收 "&"不適用"&"（口徑未揭露）"&"）"),""),"") | H94: =IF(ISNUMBER(H47),IF(IF(ISNUMBER(H52),ABS(H52)>輸入與假設!$C$275,OR(AND(H33<>0,ABS(H47)>輸入與假設!$C$274*ABS(H33)),AND(H33=0,H47<>0))),IF(ISNUMBER(H92),IF(ABS(H93)>ABS(H92),"調整後 EBITDA vs 共識 "&IF(H47<0,"−","+")&IF(ABS(H47)<0,"−","")&"$"&TEXT(ABS(ABS(H47)),"#,##0.00")&"bn"&IF(ISNUMBER(H52),"／"&IF(H52<0,"−","+")&TEXT(ABS(H52)*100,"#,##0.0")&"pt","")&"：拆法（分配 "&IF(H93<0,"−","+")&IF(ABS(H93)<0,"−","")&"$"&TEXT(ABS(ABS(H93)),"#,##0.000")&"bn"&"（Q4'27 占 FY27 "&TEXT((H28/損益!D19)*100,"#,##0.0")&"%"&"，共識合計 "&TEXT(((H33)/H91)*100,"#,##0.0")&"%"&"）；水準 "&IF(H92<0,"−","+")&IF(ABS(H92)<0,"−","")&"$"&TEXT(ABS(ABS(H92)),"#,##0.000")&"bn"&"）","調整後 EBITDA vs 共識 "&IF(H47<0,"−","+")&IF(ABS(H47)<0,"−","")&"$"&TEXT(ABS(ABS(H47)),"#,##0.00")&"bn"&IF(ISNUMBER(H52),"／"&IF(H52<0,"−","+")&TEXT(ABS(H52)*100,"#,##0.0")&"pt","")&"：觀點（水準 "&IF(H92<0,"−","+")&IF(ABS(H92)<0,"−","")&"$"&TEXT(ABS(ABS(H92)),"#,##0.000")&"bn"&"（FY27 模型 "&IF(損益!D19<0,"−","")&"$"&TEXT(ABS(損益!D19),"#,##0.000")&"bn"&"，共識合計 "&IF(H91<0,"−","")&"$"&TEXT(ABS(H91),"#,##0.000")&"bn"&"）；分配 "&IF(H93<0,"−","+")&IF(ABS(H93)<0,"−","")&"$"&TEXT(ABS(ABS(H93)),"#,##0.000")&"bn"&"；"&"模型 EBITDA 率 "&IF((H27)<0,"−","")&TEXT(ABS((H27))*100,"#,##0.0")&"%"&"；季度共識 EBITDA "&"不適用"&"、營收 "&"不適用"&"（口徑未揭露）"&"）"),"調整後 EBITDA vs 共識 "&IF(H47<0,"−","+")&IF(ABS(H47)<0,"−","")&"$"&TEXT(ABS(ABS(H47)),"#,##0.00")&"bn"&IF(ISNUMBER(H52),"／"&IF(H52<0,"−","+")&TEXT(ABS(H52)*100,"#,##0.0")&"pt","")&"：觀點（"&"模型 EBITDA 率 "&IF((H27)<0,"−","")&TEXT(ABS((H27))*100,"#,##0.0")&"%"&"；季度共識 EBITDA "&"不適用"&"、營收 "&"不適用"&"（口徑未揭露）"&"）"),""),"")
A95: 原因類型｜調整後 EBITDA｜vs 共識 | C95: =IF(ISNUMBER(C47),IF(IF(ISNUMBER(C52),ABS(C52)>輸入與假設!$C$275,OR(AND(C33<>0,ABS(C47)>輸入與假設!$C$274*ABS(C33)),AND(C33=0,C47<>0))),IF(ISNUMBER(C92),IF(ABS(C93)>ABS(C92),"拆法","觀點"),"觀點"),""),"") | D95: =IF(ISNUMBER(D47),IF(IF(ISNUMBER(D52),ABS(D52)>輸入與假設!$C$275,OR(AND(D33<>0,ABS(D47)>輸入與假設!$C$274*ABS(D33)),AND(D33=0,D47<>0))),IF(ISNUMBER(D92),IF(ABS(D93)>ABS(D92),"拆法","觀點"),"觀點"),""),"") -> 觀點 | E95: =IF(ISNUMBER(E47),IF(IF(ISNUMBER(E52),ABS(E52)>輸入與假設!$C$275,OR(AND(E33<>0,ABS(E47)>輸入與假設!$C$274*ABS(E33)),AND(E33=0,E47<>0))),IF(ISNUMBER(E92),IF(ABS(E93)>ABS(E92),"拆法","觀點"),"觀點"),""),"") | F95: =IF(ISNUMBER(F47),IF(IF(ISNUMBER(F52),ABS(F52)>輸入與假設!$C$275,OR(AND(F33<>0,ABS(F47)>輸入與假設!$C$274*ABS(F33)),AND(F33=0,F47<>0))),IF(ISNUMBER(F92),IF(ABS(F93)>ABS(F92),"拆法","觀點"),"觀點"),""),"") | G95: =IF(ISNUMBER(G47),IF(IF(ISNUMBER(G52),ABS(G52)>輸入與假設!$C$275,OR(AND(G33<>0,ABS(G47)>輸入與假設!$C$274*ABS(G33)),AND(G33=0,G47<>0))),IF(ISNUMBER(G92),IF(ABS(G93)>ABS(G92),"拆法","觀點"),"觀點"),""),"") | H95: =IF(ISNUMBER(H47),IF(IF(ISNUMBER(H52),ABS(H52)>輸入與假設!$C$275,OR(AND(H33<>0,ABS(H47)>輸入與假設!$C$274*ABS(H33)),AND(H33=0,H47<>0))),IF(ISNUMBER(H92),IF(ABS(H93)>ABS(H92),"拆法","觀點"),"觀點"),""),"")
A96: 原因｜調整後 EBITDA｜vs 指引中點
A97: 原因類型｜調整後 EBITDA｜vs 指引中點
A98: 原因｜調整後 EBITDA｜實際 vs 模型 | C98: =IF(ISNUMBER(C49),IF(IF(ISNUMBER(C54),ABS(C54)>輸入與假設!$C$275,OR(AND(C28<>0,ABS(C49)>輸入與假設!$C$274*ABS(C28)),AND(C28=0,C49<>0))),"調整後 EBITDA 實際 vs 模型 "&IF(C49<0,"−","+")&IF(ABS(C49)<0,"−","")&"$"&TEXT(ABS(ABS(C49)),"#,##0.00")&"bn"&IF(ISNUMBER(C54),"／"&IF(C54<0,"−","+")&TEXT(ABS(C54)*100,"#,##0.0")&"pt","")&"：觀點（"&"模型 EBITDA 率 "&IF((C27)<0,"−","")&TEXT(ABS((C27))*100,"#,##0.0")&"%"&"；季度共識 EBITDA "&IF((輸入與假設!$C$246)<0,"−","")&TEXT(ABS((輸入與假設!$C$246)),"#,##0.00")&"、營收 "&IF((輸入與假設!$C$245)<0,"−","")&TEXT(ABS((輸入與假設!$C$245)),"#,##0.00")&"（口徑未揭露）"&"）",""),"") | D98: =IF(ISNUMBER(D49),IF(IF(ISNUMBER(D54),ABS(D54)>輸入與假設!$C$275,OR(AND(D28<>0,ABS(D49)>輸入與假設!$C$274*ABS(D28)),AND(D28=0,D49<>0))),"調整後 EBITDA 實際 vs 模型 "&IF(D49<0,"−","+")&IF(ABS(D49)<0,"−","")&"$"&TEXT(ABS(ABS(D49)),"#,##0.00")&"bn"&IF(ISNUMBER(D54),"／"&IF(D54<0,"−","+")&TEXT(ABS(D54)*100,"#,##0.0")&"pt","")&"：觀點（"&"模型 EBITDA 率 "&IF((D27)<0,"−","")&TEXT(ABS((D27))*100,"#,##0.0")&"%"&"；季度共識 EBITDA "&IF((輸入與假設!$D$246)<0,"−","")&TEXT(ABS((輸入與假設!$D$246)),"#,##0.00")&"、營收 "&IF((輸入與假設!$D$245)<0,"−","")&TEXT(ABS((輸入與假設!$D$245)),"#,##0.00")&"（口徑未揭露）"&"）",""),"") | E98: =IF(ISNUMBER(E49),IF(IF(ISNUMBER(E54),ABS(E54)>輸入與假設!$C$275,OR(AND(E28<>0,ABS(E49)>輸入與假設!$C$274*ABS(E28)),AND(E28=0,E49<>0))),"調整後 EBITDA 實際 vs 模型 "&IF(E49<0,"−","+")&IF(ABS(E49)<0,"−","")&"$"&TEXT(ABS(ABS(E49)),"#,##0.00")&"bn"&IF(ISNUMBER(E54),"／"&IF(E54<0,"−","+")&TEXT(ABS(E54)*100,"#,##0.0")&"pt","")&"：觀點（"&"模型 EBITDA 率 "&IF((E27)<0,"−","")&TEXT(ABS((E27))*100,"#,##0.0")&"%"&"；季度共識 EBITDA "&"不適用"&"、營收 "&"不適用"&"（口徑未揭露）"&"）",""),"") | F98: =IF(ISNUMBER(F49),IF(IF(ISNUMBER(F54),ABS(F54)>輸入與假設!$C$275,OR(AND(F28<>0,ABS(F49)>輸入與假設!$C$274*ABS(F28)),AND(F28=0,F49<>0))),"調整後 EBITDA 實際 vs 模型 "&IF(F49<0,"−","+")&IF(ABS(F49)<0,"−","")&"$"&TEXT(ABS(ABS(F49)),"#,##0.00")&"bn"&IF(ISNUMBER(F54),"／"&IF(F54<0,"−","+")&TEXT(ABS(F54)*100,"#,##0.0")&"pt","")&"：觀點（"&"模型 EBITDA 率 "&IF((F27)<0,"−","")&TEXT(ABS((F27))*100,"#,##0.0")&"%"&"；季度共識 EBITDA "&"不適用"&"、營收 "&"不適用"&"（口徑未揭露）"&"）",""),"") | G98: =IF(ISNUMBER(G49),IF(IF(ISNUMBER(G54),ABS(G54)>輸入與假設!$C$275,OR(AND(G28<>0,ABS(G49)>輸入與假設!$C$274*ABS(G28)),AND(G28=0,G49<>0))),"調整後 EBITDA 實際 vs 模型 "&IF(G49<0,"−","+")&IF(ABS(G49)<0,"−","")&"$"&TEXT(ABS(ABS(G49)),"#,##0.00")&"bn"&IF(ISNUMBER(G54),"／"&IF(G54<0,"−","+")&TEXT(ABS(G54)*100,"#,##0.0")&"pt","")&"：觀點（"&"模型 EBITDA 率 "&IF((G27)<0,"−","")&TEXT(ABS((G27))*100,"#,##0.0")&"%"&"；季度共識 EBITDA "&"不適用"&"、營收 "&"不適用"&"（口徑未揭露）"&"）",""),"") | H98: =IF(ISNUMBER(H49),IF(IF(ISNUMBER(H54),ABS(H54)>輸入與假設!$C$275,OR(AND(H28<>0,ABS(H49)>輸入與假設!$C$274*ABS(H28)),AND(H28=0,H49<>0))),"調整後 EBITDA 實際 vs 模型 "&IF(H49<0,"−","+")&IF(ABS(H49)<0,"−","")&"$"&TEXT(ABS(ABS(H49)),"#,##0.00")&"bn"&IF(ISNUMBER(H54),"／"&IF(H54<0,"−","+")&TEXT(ABS(H54)*100,"#,##0.0")&"pt","")&"：觀點（"&"模型 EBITDA 率 "&IF((H27)<0,"−","")&TEXT(ABS((H27))*100,"#,##0.0")&"%"&"；季度共識 EBITDA "&"不適用"&"、營收 "&"不適用"&"（口徑未揭露）"&"）",""),"")
A99: 原因類型｜調整後 EBITDA｜實際 vs 模型 | C99: =IF(ISNUMBER(C49),IF(IF(ISNUMBER(C54),ABS(C54)>輸入與假設!$C$275,OR(AND(C28<>0,ABS(C49)>輸入與假設!$C$274*ABS(C28)),AND(C28=0,C49<>0))),"觀點",""),"") | D99: =IF(ISNUMBER(D49),IF(IF(ISNUMBER(D54),ABS(D54)>輸入與假設!$C$275,OR(AND(D28<>0,ABS(D49)>輸入與假設!$C$274*ABS(D28)),AND(D28=0,D49<>0))),"觀點",""),"") | E99: =IF(ISNUMBER(E49),IF(IF(ISNUMBER(E54),ABS(E54)>輸入與假設!$C$275,OR(AND(E28<>0,ABS(E49)>輸入與假設!$C$274*ABS(E28)),AND(E28=0,E49<>0))),"觀點",""),"") | F99: =IF(ISNUMBER(F49),IF(IF(ISNUMBER(F54),ABS(F54)>輸入與假設!$C$275,OR(AND(F28<>0,ABS(F49)>輸入與假設!$C$274*ABS(F28)),AND(F28=0,F49<>0))),"觀點",""),"") | G99: =IF(ISNUMBER(G49),IF(IF(ISNUMBER(G54),ABS(G54)>輸入與假設!$C$275,OR(AND(G28<>0,ABS(G49)>輸入與假設!$C$274*ABS(G28)),AND(G28=0,G49<>0))),"觀點",""),"") | H99: =IF(ISNUMBER(H49),IF(IF(ISNUMBER(H54),ABS(H54)>輸入與假設!$C$275,OR(AND(H28<>0,ABS(H49)>輸入與假設!$C$274*ABS(H28)),AND(H28=0,H49<>0))),"觀點",""),"")
A100: 原因｜調整後營業利益｜vs 共識
A101: 原因類型｜調整後營業利益｜vs 共識
A102: 原因｜調整後營業利益｜vs 指引中點
...

Sheet 運營_產能與收入
A1: 產能與收入 — 已連網 MW × 每 MW 年收入（RPO 排程只作對照與產能瓶頸旗標）
A2: 兩條線獨立產生後相減：排程>容量→瓶頸（收不到）；容量>排程→剩餘產能（要靠新簽約賣掉）
A3: FY26 欄口徑：MW 為年底存量；標示「（模型期）」的收入列只含 2026 下半年——RPO 桶自 2026-06-30 起算，1H 收入已實現、不再受產能約束。1H 實際單列，兩者相加即 FY26 全年（見本頁「FY26 全年」列）。
A5: 項目 | B5: 單位 | C5: FY26 | D5: FY27 | E5: FY28 | F5: FY29 | G5: FY30 | I5: 公式／來源說明
A6: 模型期間 | C6: ="2026-07-01~12-31" -> 2026-07-01~12-31 | D6: ="2027 全年" -> 2027 全年 | E6: ="2028 全年" -> 2028 全年 | F6: ="2029 全年" -> 2029 全年 | G6: ="2030 全年" -> 2030 全年 | I6: FY26 的模型期只有下半年；1H 已實現的營收單列於下方
A7: 模型期長度（年） | C7: =輸入與假設!C$37 -> 0.5 | D7: =輸入與假設!D$37 -> 1 | E7: =輸入與假設!E$37 -> 1 | F7: =輸入與假設!F$37 -> 1 | G7: =輸入與假設!G$37 -> 1 | I7: 只用於下方三處：容量上限、電力、維護——把年率換算成該期金額
A8: （A）機房：容量上限
A9: Accepted MW（已驗收，單調不減） | B9: MW | C9: =MAX(0,輸入與假設!C$39) -> 750 | D9: =MAX(輸入與假設!D$39,C9) -> 1330 | E9: =MAX(輸入與假設!E$39,D9) -> 1910 | F9: =MAX(輸入與假設!F$39,E9) -> 2490 | G9: =MAX(輸入與假設!G$39,F9) -> 3070 | I9: 引擎規則：不得低於前期（產能不會消失）
A10: Billable MW（上限為 Accepted） | B10: MW | C10: =MIN(MAX(0,輸入與假設!C$40),C9) -> 338 | D10: =MIN(MAX(0,輸入與假設!D$40),D9) -> 904 | E10: =MIN(MAX(0,輸入與假設!E$40),E9) -> 1719 | F10: =MIN(MAX(0,輸入與假設!F$40),F9) -> 2241 | G10: =MIN(MAX(0,輸入與假設!G$40),G9) -> 2763 | I10: 引擎規則：可計費不得超過已驗收
A11: 期初在役 MW | B11: MW | C11: =輸入與假設!$C$32 -> 253 | D11: =C10 -> 338 | E11: =D10 -> 904 | F11: =E10 -> 1719 | G11: =F10 -> 2241 | I11: 前期期末＝本期期初
A12: 平均在役 MW（FY26 欄為下半年平均） | B12: MW | C12: =IF(輸入與假設!$C$33=1,(C11+C10)/2,C10) -> 295.5 | D12: =IF(輸入與假設!$C$33=1,(D11+D10)/2,D10) -> 621 | E12: =IF(輸入與假設!$C$33=1,(E11+E10)/2,E10) -> 1311.5 | F12: =IF(輸入與假設!$C$33=1,(F11+F10)/2,F10) -> 1980 | G12: =IF(輸入與假設!$C$33=1,(G11+G10)/2,G10) -> 2502 | I12: 開關在輸入頁：1＝(期初+期末)/2，0＝期末全期化
A13: 利用率 | B13: % | C13: =輸入與假設!C$41 -> 1 | D13: =輸入與假設!D$41 -> 1 | E13: =輸入與假設!E$41 -> 1 | F13: =輸入與假設!F$41 -> 1 | G13: =輸入與假設!G$41 -> 1
A14: 每 MW 年收入 | B14: US$bn/MW | C14: =輸入與假設!C$42 -> 0.0091925511 | D14: =輸入與假設!D$42 -> 0.0096218441 | E14: =輸入與假設!E$42 -> 0.010018893 | F14: =輸入與假設!F$42 -> 0.010264054 | G14: =輸入與假設!G$42 -> 0.0103953
A15: 容量上限（模型期最多能交付的收入） | B15: US$bn | C15: =C12*輸入與假設!C$42*輸入與假設!$C$35*輸入與假設!C$41*C7 -> 1.3581994 | D15: =D12*輸入與假設!D$42*輸入與假設!$C$35*輸入與假設!D$41*D7 -> 5.9751652 | E15: =E12*輸入與假設!E$42*輸入與假設!$C$35*輸入與假設!E$41*E7 -> 13.139778 | F15: =F12*輸入與假設!F$42*輸入與假設!$C$35*輸入與假設!F$41*F7 -> 20.322827 | G15: =G12*輸入與假設!G$42*輸入與假設!$C$35*輸入與假設!G$41*G7 -> 26.00904 | I15: ＝平均在役 MW × 每 MW 年收入 × 利用率 × 期間係數。只看機房，不看合約
A16: （B）合約：排程 RPO
A17: 排程 RPO（模型期，依季報桶分攤） | B17: US$bn | C17: =(輸入與假設!$C$26+輸入與假設!$C$27)*(輸入與假設!C$38/輸入與假設!$C$29)*輸入與假設!$C$28 -> 3.374154 | D17: =(輸入與假設!$C$26+輸入與假設!$C$27)*(輸入與假設!D$38/輸入與假設!$C$29)*輸入與假設!$C$28 -> 6.748308 | E17: =(輸入與假設!$C$26+輸入與假設!$C$27)*(輸入與假設!E$38/輸入與假設!$C$29)*輸入與假設!$C$28 -> 7.123214 | F17: =(輸入與假設!$C$26+輸入與假設!$C$27)*(輸入與假設!F$38/輸入與假設!$C$29)*輸入與假設!$C$28 -> 7.49812 | G17: =(輸入與假設!$C$26+輸入與假設!$C$27)*(輸入與假設!G$38/輸入與假設!$C$29)*輸入與假設!$C$28 -> 5.998496 | I17: ＝(6/30 RPO＋Q3 新增)×本期權重÷權重合計×五期認列比例。只看合約，不看機房
A18: （C）兩條線相減
A19: 產能瓶頸（模型期：排程 − 容量） | B19: US$bn | C19: =MAX(0,C17-C15) -> 2.0159546 | D19: =MAX(0,D17-D15) -> 0.7731428 | E19: =MAX(0,E17-E15) -> 0 | F19: =MAX(0,F17-F15) -> 0 | G19: =MAX(0,G17-G15) -> 0 | I19: 合約有、機房沒有 → 本期收不到，且不遞延到下期（保守處理）
A20: 期初 RPO 轉換收入（模型期） | B20: US$bn | C20: =C17-C19 -> 1.3581994 | D20: =D17-D19 -> 5.9751652 | E20: =E17-E19 -> 7.123214 | F20: =F17-F19 -> 7.49812 | G20: =G17-G19 -> 5.998496 | I20: ＝排程 − 瓶頸。當瓶頸>0 時，此值恆等於容量上限
A21: 未被期初 RPO 占用的產能 | B21: US$bn | C21: =MAX(0,C15-C17) -> 0 | D21: =MAX(0,D15-D17) -> 0 | E21: =MAX(0,E15-E17) -> 6.0165645 | F21: =MAX(0,F15-F17) -> 12.824707 | G21: =MAX(0,G15-G17) -> 20.010544 | I21: 容量 − 排程。機房有、期初合約沒占滿 → 要靠新簽約
A22: 新產能簽約率 | B22: % | C22: =IF(輸入與假設!$C$34="mw",1,輸入與假設!C$43) -> 1 | D22: =IF(輸入與假設!$C$34="mw",1,輸入與假設!D$43) -> 1 | E22: =IF(輸入與假設!$C$34="mw",1,輸入與假設!E$43) -> 1 | F22: =IF(輸入與假設!$C$34="mw",1,輸入與假設!F$43) -> 1 | G22: =IF(輸入與假設!$C$34="mw",1,輸入與假設!G$43) -> 1 | I22: MW 驅動時固定 100%
A23: 新簽約收入 | B23: US$bn | C23: =C21*C22 -> 0 | D23: =D21*D22 -> 0 | E23: =E21*E22 -> 6.0165645 | F23: =F21*F22 -> 12.824707 | G23: =G21*G22 -> 20.010544 | I23: 超出期初 RPO 的產能收入（MW 驅動，簽約率 100%）
A24: 未售產能（浪費） | B24: US$bn | C24: =MAX(0,C15-C20-C23) -> 0 | D24: =MAX(0,D15-D20-D23) -> 0 | E24: =MAX(0,E15-E20-E23) -> 0 | F24: =MAX(0,F15-F20-F23) -> 0 | G24: =MAX(0,G15-G20-G23) -> 0 | I24: 蓋好但賣不掉（MW 驅動時為 0）
A25: 損益用算力收入（模型期＝RPO 轉換＋新簽約） | B25: US$bn | C25: =C20+C23 -> 1.3581994 | D25: =D20+D23 -> 5.9751652 | E25: =E20+E23 -> 13.139778 | F25: =F20+F23 -> 20.322827 | G25: =G20+G23 -> 26.00904 | I25: 損益與評價頁的算力收入由此連結，確保現金與損益同一組數字
A26: 核對：算力收入 − 平均在役 MW × 每 MW × 利用率 × 期間 | B26: US$bn | C26: =C25-C12*輸入與假設!C$42*輸入與假設!$C$35*輸入與假設!C$41*C7 -> 0 | D26: =D25-D12*輸入與假設!D$42*輸入與假設!$C$35*輸入與假設!D$41*D7 -> 0 | E26: =E25-E12*輸入與假設!E$42*輸入與假設!$C$35*輸入與假設!E$41*E7 -> 0 | F26: =F25-F12*輸入與假設!F$42*輸入與假設!$C$35*輸入與假設!F$41*F7 -> 0 | G26: =G25-G12*輸入與假設!G$42*輸入與假設!$C$35*輸入與假設!G$41*G7 -> 0 | I26: MW 驅動時應為 0：營收可追溯為 MW × 每 MW 年收入 × 利用率（v0.1b）
A27: 1H26 實際營收（季報，已實現） | B27: US$bn | C27: =輸入與假設!$C$190 -> 0.9813 | D27: =0 -> 0 | E27: =0 -> 0 | F27: =0 -> 0 | G27: =0 -> 0 | I27: 2026-01-01 至 06-30 已認列營收。已實現，不受下半年產能約束，故不進入上方的瓶頸計算
A28: FY26 全年總營收（1H 實際＋模型期算力＋服務） | B28: US$bn | C28: =C27+C25+輸入與假設!C$46 -> 2.3394994 | D28: =D27+D25+輸入與假設!D$46 -> 5.9751652 | E28: =E27+E25+輸入與假設!E$46 -> 13.139778 | F28: =F27+F25+輸入與假設!F$46 -> 20.322827 | G28: =G27+G25+輸入與假設!G$46 -> 26.00904 | I28: FY26 欄對照公司全年指引 3.0–3.4；FY27 以後即為該年度總營收
A29: （D）收入 → 現金：三道折扣
A30: 客戶違約率 | B30: % | C30: =輸入與假設!C$44 -> 0.005 | D30: =輸入與假設!D$44 -> 0.01 | E30: =輸入與假設!E$44 -> 0.015 | F30: =輸入與假設!F$44 -> 0.02 | G30: =輸入與假設!G$44 -> 0.025
A31: 回收率 | B31: % | C31: =輸入與假設!C$45 -> 0.5 | D31: =輸入與假設!D$45 -> 0.5 | E31: =輸入與假設!E$45 -> 0.5 | F31: =輸入與假設!F$45 -> 0.5 | G31: =輸入與假設!G$45 -> 0.5
A32: 信用損失（期初 RPO 部分） | B32: US$bn | C32: =C20*輸入與假設!C$44*(1-輸入與假設!C$45) -> 0.0033954986 | D32: =D20*輸入與假設!D$44*(1-輸入與假設!D$45) -> 0.029875826 | E32: =E20*輸入與假設!E$44*(1-輸入與假設!E$45) -> 0.053424105 | F32: =F20*輸入與假設!F$44*(1-輸入與假設!F$45) -> 0.0749812 | G32: =G20*輸入與假設!G$44*(1-輸入與假設!G$45) -> 0.0749812 | I32: ＝收入 × 違約率 × (1−回收率)
A33: 收現（期初 RPO 部分） | B33: US$bn | C33: =C20-C32 -> 1.3548039 | D33: =D20-D32 -> 5.9452894 | E33: =E20-E32 -> 7.0697899 | F33: =F20-F32 -> 7.4231388 | G33: =G20-G32 -> 5.9235148
A34: EBITDA 率（損益與資金共用） | B34: % | C34: =輸入與假設!C$53 -> 0.497 | D34: =輸入與假設!D$53 -> 0.49025 | E34: =輸入與假設!E$53 -> 0.4835 | F34: =輸入與假設!F$53 -> 0.47675 | G34: =輸入與假設!G$53 -> 0.47 | I34: 起始→穩態線性爬升
A35: 模型期總營收（算力＋服務） | B35: US$bn | C35: =C25+輸入與假設!C$46 -> 1.3581994 | D35: =D25+輸入與假設!D$46 -> 5.9751652 | E35: =E25+輸入與假設!E$46 -> 13.139778 | F35: =F25+輸入與假設!F$46 -> 20.322827 | G35: =G25+輸入與假設!G$46 -> 26.00904
A36: EBITDAR 率（EBITDA 率＋租金÷營收） | B36: % | C36: =輸入與假設!C$53+各期收支!C15/MAX(0.01,C35) -> 0.60125568 | D36: =輸入與假設!D$53+各期收支!D15/MAX(0.01,D35) -> 0.59991867 | E36: =輸入與假設!E$53+各期收支!E15/MAX(0.01,E35) -> 0.56148936 | F36: =輸入與假設!F$53+各期收支!F15/MAX(0.01,F35) -> 0.52633905 | G36: =輸入與假設!G$53+各期收支!G15/MAX(0.01,G35) -> 0.50824756 | I36: 租金前的 EBITDA 率。EBITDA 已扣租金，而資金模型把租金列在支出端，所以要加回，避免重複扣除
A37: RPO 現金（可支應資本用途） | B37: US$bn | C37: =C33*C36 -> 0.81458355 | D37: =D33*D36 -> 3.5666901 | E37: =E33*E36 -> 3.9696118 | F37: =F33*F36 -> 3.9070878 | G37: =G33*G36 -> 3.0106119 | I37: ×EBITDAR 率。租金與利息在支出頁單獨列示
A38: 新簽約現金 | B38: US$bn | C38: =C23*(1-輸入與假設!C$44*(1-輸入與假設!C$45))*C36 -> 0 | D38: =D23*(1-輸入與假設!D$44*(1-輸入與假設!D$45))*D36 -> 0 | E38: =E23*(1-輸入與假設!E$44*(1-輸入與假設!E$45))*E36 -> 3.3529002 | F38: =F23*(1-輸入與假設!F$44*(1-輸入與假設!F$45))*F36 -> 6.6826429 | G38: =G23*(1-輸入與假設!G$44*(1-輸入與假設!G$45))*G36 -> 10.043181 | I38: 同樣扣信用損失、乘 EBITDAR 率
A40: 讀法：FY26（2H）與 FY27 瓶頸>0，合約多於機房；FY28 起反轉，收入愈來愈靠『新簽約收入』這一列。
A41: 把『新產能簽約率』調到 0，就能看到只靠期初 RPO 的資金缺口有多大——這是最重要的一個壓力測試。

Sheet 運營_站點
A1: 站點租賃 — 公司揭露 vs 季報總額（檢驗租金路徑用）
A2: 季報不揭露逐站租金；下表為具名站點（company.json → defaults.sites），有租約金額者用來檢驗『每 MW 年租金』與模型租金路徑是否一致
A4: 站點 | B4: 營運方 | C4: 契約 MW | D4: 已驗收 MW | E4: 合約總值 $bn | F4: 年期 | G4: 年租金 $bn | H4: 每 MW 年租金 $m | I4: 時程 | J4: 季報對應 | K4: 說明
A5: Lappeenranta, Finland | B5: Nebius 自建（自有） | C5: 258 | D5: 0 | E5: 未揭露 | F5: 未揭露 | I5: 2027 | J5: — | K5: Q1 股東信：滿載 310 MW（口徑不明，÷1.2 換 IT 約 258 MW）、2027 可用 [Interested-party]
A6: Independence, Missouri | B6: Nebius 自建（greenfield） | C6: 1000 | D6: 0 | E6: 未揭露 | F6: 未揭露 | I6: 2027 | J6: — | K6: 最高 1.2 GW（÷1.2 換 IT 約 1,000 MW）；預計 2027 營運 [Interested-party]
A7: Pennsylvania | B7: Nebius 自建（自有） | C7: 1000 | D7: 0 | E7: 未揭露 | F7: 未揭露 | I7: 2027 起 | J7: — | K7: 最高 1.2 GW 電力與土地（÷1.2 換 IT 約 1,000 MW）；2027 起分期 [Interested-party]
A8: Vineland, New Jersey | B8: build-to-suit（Microsoft 專用） | C8: 0 | D8: 0 | E8: 未揭露 | F8: 未揭露 | I8: 2026 | J8: — | K8: Microsoft 5 年合約（TCV 約 $17.4B）；Q2 股東信：已交付全部 tranche；MW 未揭露
A9: Alabama | B9: Nebius 自建 | C9: 0 | D9: 0 | E9: 未揭露 | F9: 未揭露 | I9: 2027 | J9: — | K9: 施工中、預計 2027 營運；MW 未揭露
A10: Mäntsälä, Finland | B10: Nebius 自建（既有） | C10: 0 | D10: 0 | E10: 未揭露 | F10: 未揭露 | I10: 既有 | J10: — | K10: 既有自有站點；MW 未揭露
A11: 具名站點合計 | C11: =SUM(C5:C10) -> 2258 | D11: =SUM(D5:D10) -> 0 | E11: =SUM(E5:E10) -> 0 | G11: =SUM(G5:G10) -> 0 | H11: =IF(I11>0,G11/I11*1000,0) -> 0 | I11: =SUMPRODUCT(ISNUMBER(G5:G10)*C5:C10) -> 0 | K11: 加權每 MW 年租金＝具名站點的市場基準（I 欄＝有租約金額站點的契約 MW；沒有時為 0，不適用）
A13: 對帳：具名站點 vs 季報租賃承諾總額
A14: 季報在帳租賃（未折現，已起租） | E14: 2.1751 | K14: company.json → leases.facts.onBal
A15: 季報未起租租賃（未折現） | E15: 12.0541 | K15: company.json → leases.facts.notCommenced
A16: 季報單站按造價計租上限 | E16: 0 | K16: company.json → leases.facts.singleCap（無則 0）
A17: 季報已揭露租賃承諾合計 | E17: =SUM(E14:E16) -> 14.2292 | K17: 未折現金額
A18: 減：具名站點合約總值 | E18: =-E11 -> 0
A19: ＝ 未具名站點（殘差） | E19: =E17+E18 -> 14.2292 | K19: 未具名站點；公司不揭露逐站租金，殘差大是必然
A20: 殘差占季報總額 | E20: =IF(E17<>0,E19/E17,0) -> 1
A22: 檢驗：模型租金路徑 ÷ 在役 MW vs 市場基準
A23: 項目 | B23: 單位 | C23: FY26 | D23: FY27 | E23: FY28 | F23: FY29 | G23: FY30
A24: 模型租金（在帳＋表外） | B24: US$bn | C24: =各期收支!C15 -> 0.1416 | D24: =各期收支!D15 -> 0.65528844 | E24: =各期收支!E15 -> 1.0247629 | F24: =各期收支!F15 -> 1.0077897 | G24: =各期收支!G15 -> 0.99478231
A25: 平均在役 MW（已連網） | B25: MW | C25: =(輸入與假設!C$83+輸入與假設!C$39)/2 -> 460 | D25: =(輸入與假設!D$83+輸入與假設!D$39)/2 -> 1040 | E25: =(輸入與假設!E$83+輸入與假設!E$39)/2 -> 1620 | F25: =(輸入與假設!F$83+輸入與假設!F$39)/2 -> 2200 | G25: =(輸入與假設!G$83+輸入與假設!G$39)/2 -> 2780
A26: 模型期長度（年） | B26: 年 | C26: =輸入與假設!C$37 -> 0.5 | D26: =輸入與假設!D$37 -> 1 | E26: =輸入與假設!E$37 -> 1 | F26: =輸入與假設!F$37 -> 1 | G26: =輸入與假設!G$37 -> 1
A27: 模型每 MW 年租金 | B27: US$m/MW | C27: =C24/C26/C25*1000 -> 0.61565217 | D27: =D24/D26/D25*1000 -> 0.63008504 | E27: =E24/E26/E25*1000 -> 0.6325697 | F27: =F24/F26/F25*1000 -> 0.45808621 | G27: =G24/G26/G25*1000 -> 0.35783536 | K27: FY26 欄只含下半年租金、MW 取全年平均，略有低估
A28: 第三方租賃占比 | C28: 0.25 | K28: 其餘為自建，成本走 CapEx（company.json → leases.facts.share）[Assumed]
A29: 基準租金（MW×市場基準×占比） | B29: US$bn | C29: =C25*運營_站點!$H$11/1000*$C$28*C26 -> 0 | D29: =D25*運營_站點!$H$11/1000*$C$28*D26 -> 0 | E29: =E25*運營_站點!$H$11/1000*$C$28*E26 -> 0 | F29: =F25*運營_站點!$H$11/1000*$C$28*F26 -> 0 | G29: =G25*運營_站點!$H$11/1000*$C$28*G26 -> 0 | K29: 具名站點有租約金額時才有意義；否則為 0
A30: 差額（基準 − 模型） | B30: US$bn | C30: =C29-C24 -> -0.1416 | D30: =D29-D24 -> -0.65528844 | E30: =E29-E24 -> -1.0247629 | F30: =F29-F24 -> -1.0077897 | G30: =G29-G24 -> -0.99478231 | K30: 正值＝模型租金可能低估的金額
A31: 五期差額合計 | C31: =SUM(C30:G30) -> -3.8242233

Sheet 每MW收入_錨定
A1: 每 MW 收入 — Tokenomics 錨 × 定價倍數 k（v0.2a）
A2: 每 MW 年收入（100% 計費時數）＝ Σ 平均在役世代占比 × IF_HoldEcon（WACC 10% 打平租金）× k；k＝隨需占比 × k_現貨＋（1 − 隨需占比）× k_長約（新增產能按長約價；長約占比只作對照）。按 MW-year 計價：利用率不另扣（IF_Util 不進收入），爬坡與簽約率在『輸入與假設』B 區。k 只取市場價格證據，不以 Nebius 營收、ARR、RPO、ACV 反推。
A3: 容量情境（輸入與假設 A 區情境選擇）只改 MW 路徑；價格情境（A 區價格情境選擇）只改 k。Q2 實績只作驗證（D 區），不校準 k。
A4: A｜價格軸：定價倍數 k（低、基準、高 依序在 C、D、E 欄；藍字可改）
A5: 項目 | B5: 單位 | C5: 低 | D5: 基準 | E5: 高 | I5: 說明／來源
A6: k_長約（多年期專用容量合約） | B6: 倍 | C6: =8.9073/TK_HoldEcon_GB300 -> 0.81820354 | D6: =9.7/TK_HoldEcon_GB300 -> 0.89101909 | E6: =12.7247/TK_HoldEcon_GB300 -> 1.1688609 | I6: v0.4a 起 k 依目前快照重算（價格是事實，k＝價格 ÷ 同世代 Tokenomics 持有成本，錨改變時 k 跟著改；比照 CoreWeave W6 r1）。基準＝IREN–Microsoft GB300 五年約 9.70 ÷ IF_HoldEcon｜GB300（v5.27 12.72 → 0.762、v18.0 10.89 → 0.891）；區間端點為 v0.3 的 0.70–1.00 × v5.27 錨 12.725 換成固定價格 8.907／12.725 US$m/MW/年 [Derived]（v18.0 為 0.818–1.169）；中位數＝三筆長約（IREN–Microsoft、IREN–NVIDIA、Oracle–OpenAI〔未證實〕）倍數的中位數 [Analogy]
A7: k_現貨（非長約客戶：預留與隨需） | B7: 倍 | C7: =2.4075/TK_GPUhrEcon_H100 -> 1.5606803 | D7: =2.82/TK_GPUhrEcon_H100 -> 1.8280865 | E7: =6.82/TK_GPUhrEcon_GB300 -> 2.6726362 | I7: v0.4a 起 k 依目前快照重算（比照 CoreWeave W6 r1）。基準＝H100 Silicon Data 現貨指數 2.82 ÷ IF_GPUhrEcon｜H100（v5.27 1.605 → 1.757、v18.0 1.543 → 1.828）；上緣＝B300 指數 6.82 ÷ IF_GPUhrEcon｜GB300（v5.27 2.29、v18.0 2.67）；下緣＝v0.3 預設 1.5 × v5.27 H100 成本 1.605 換成固定價格 2.408 US$/GPU-hr [Derived]（v18.0 為 1.56）。Nebius 非長約客戶多為預留（數月至數年），介於長約與隨需之間，以現貨指數代表 [Analogy]
A8: k_長約（目前價格情境） | B8: 倍 | C8: =CHOOSE(輸入與假設!$F$5,C6,D6,E6) -> 0.89101909 | I8: ＝依『輸入與假設』A 區價格情境選擇（1 低／2 基準／3 高）
A9: k_現貨（目前價格情境） | B9: 倍 | C9: =CHOOSE(輸入與假設!$F$5,C7,D7,E7) -> 1.8280865 | I9: ＝依『輸入與假設』A 區價格情境選擇（1 低／2 基準／3 高）
A10: 隨需占比（新增產能按長約價；第 2 輪） | B10: % | C10: 0 | I10: 隨需（現貨）占在役計費產能的比例；公司未揭露長約／隨需比例（找不到）。基準 0%（新增產能按長約價：先簽多年期合約再建產能），敏感度 10%／20%；不得用 Q2 隱含 k 反推（第 2 輪，比照 CoreWeave W4 r2）；敏感度 10%／20% 見 G2 區
A11: Nebius 自身合約 k（Microsoft；只列為敏感度） | B11: 倍 | C11: =17400/5/300/TK_HoldEcon_GB300 -> 1.0655486 | D11: =17400/5/250/TK_HoldEcon_GB300 -> 1.2786583 | E11: =3.973/TK_GPUhrEcon_GB300 -> 1.5569478 | I11: C／D／E＝Vineland 300 MW 視為 IT／Vineland 300 MW 視為設施（÷ PUE 1.2）／約 10 萬顆 GB300（Bloomberg）。已決定事項 15：公司自身合約條款可作公司因素證據，但須能完全由已揭露條款算出。Microsoft 6-K（2025-09-08）與 Q3 2025 附註只揭露 TCV $17.4bn（可擴至 $19.4bn）、5 年、Vineland 專用 GPU 容量分批交付，未揭露 MW 或 GPU 數；Meta 兩份 6-K 亦未揭露容量。換算必須假設容量：Vineland 站點 300 MW（Nebius 新聞稿，站點容量而非合約容量）→ 17.4 ÷ 5 ÷ 250（設施口徑）÷ IF_HoldEcon｜GB300、或 ÷ 300（IT 口徑）；Bloomberg 引述匿名消息約 10 萬顆 GB300 → ÷ 487 顆/MW＝205 MW（等同證據表 GPU 小時價 3.973 ÷ IF_GPUhrEcon｜GB300）。v0.4a 起三個值由規格 specs 隨快照重算（TCV 與容量假設不變，價格是事實）：v5.27 為 0.91／1.09／1.33、v18.0（GB300 持有成本 12.72 → 10.89）為 1.07／1.28／1.56。條款不足以算出 → k_長約 基準維持市場長約（IREN–Microsoft），Nebius 自身合約列敏感度。 [Derived]／[Assumed]
A12: 長約的指定解讀（下游資料契約第 4 條） | I12: 契約第 4 條指定解讀（預設）：長約以低於打平租金（WACC 10% 經濟持有成本）的價格換取預付（20%）與五年確定性，客戶分攤部分資本成本——Nebius 對 Microsoft／Meta 長約同樣收預付（股東信約 70% 合約、預付占資本支出 50–60%）。替代解讀：(a) 成本結構不同（IREN 自有電力與廠房，持有成本低於 Tokenomics 基準）→ k 應以 IREN 自身成本計、高於基準；(b) 合約含非收入條款（預付的資金成本價值未計入價格）→ 經濟價格高於帳面價格。三者對 Nebius 收入的影響方向：預設解讀最保守。
A14: B｜Tokenomics 錨與世代組合（Tokenomics_取數 的 TK_ 名稱，基準成本情境）
A15: 世代 | B15: 單位 | C15: IF_HoldEcon | D15: IF_RevGWFleet | E15: 期初占比 | I15: 說明／來源
A16: 世代｜Hopper H100 | B16: US$m/MW | C16: =TK_HoldEcon_H100 -> 9.7030873 | D16: =TK_RevGWFleet_H100 -> 6.6830402 | E16: 0.28 | I16: Tokenomics 無 H200 欄，以 Hopper H100 欄代表；期初占比區間 20%–40% [Assumed]；IF_HoldEcon＝每 MW 年經濟持有成本（WACC 10%）、IF_RevGWFleet＝客戶每 MW 付費 token 營收（理想上限）
A17: 世代｜GB200 NVL72 | B17: US$m/MW | C17: =TK_HoldEcon_GB200 -> 8.8281656 | D17: =TK_RevGWFleet_GB200 -> 32.885504 | E17: 0.19 | I17: 期初占比區間 10%–25% [Assumed]；IF_HoldEcon＝每 MW 年經濟持有成本（WACC 10%）、IF_RevGWFleet＝客戶每 MW 付費 token 營收（理想上限）
A18: 世代｜GB300 NVL72 | B18: US$m/MW | C18: =TK_HoldEcon_GB300 -> 10.886411 | D18: =TK_RevGWFleet_GB300 -> 40.111465 | E18: 0.53 | I18: 期初占比區間 40%–65% [Assumed]；IF_HoldEcon＝每 MW 年經濟持有成本（WACC 10%）、IF_RevGWFleet＝客戶每 MW 付費 token 營收（理想上限）
A19: 世代｜VR200 NVL72 | B19: US$m/MW | C19: =TK_HoldEcon_VR200 -> 12.225471 | D19: =TK_RevGWFleet_VR200 -> 65.962839 | E19: 0 | I19: [Assumed]；IF_HoldEcon＝每 MW 年經濟持有成本（WACC 10%）、IF_RevGWFleet＝客戶每 MW 付費 token 營收（理想上限）
A20: 期初占比合計 | E20: =SUM(E16:E19) -> 1 | I20: 2025 年底 active 170 MW（20-F／股東信）假設 Hopper（H100／H200）60%、Blackwell（B200／GB200，以 GB200 欄代表）40%；2026 上半年新增約 196 MW（366 − 170，內插）以 Microsoft Vineland GB300／B300 為主（Bloomberg：約 10 萬顆 GB300；Epoch AI 估 B300）＝GB300 100%。公司未揭露世代組合（找不到）；Tokenomics 無 H200 欄，以 Hopper H100 欄代表。
A21: 期初在役 MW（最新季末） | B21: MW | C21: 366 | I21: 最新季末在役 MW 未揭露：以 2025 年底 active 170 MW 與首期末在役 563 MW 線性內插（[Derived]，v0.1c 報告第 3 節）；實現單價＝最新一季營收 × 4 ÷ 此值（company.json → priceCheck.inServiceMw）
A23: 新增在役 MW 的世代占比 | B23: 單位 | C23: FY26 | D23: FY27 | E23: FY28 | F23: FY29 | G23: FY30 | I23: 說明／來源
A24: 新增占比｜Hopper H100 | B24: % | C24: 0 | D24: 0 | E24: 0 | F24: 0 | G24: 0 | I24: [Assumed]：2H26 GB300 100%（2026 年交付主力）；FY27 GB300 50%／VR200 50%（Meta 第二份為 Vera Rubin、2027 年初起交付）；FY28–FY30 VR200 100%。區間：VR200 提前一年（FY27 100%）或延後一年（FY28 50%）
A25: 新增占比｜GB200 NVL72 | B25: % | C25: 0 | D25: 0 | E25: 0 | F25: 0 | G25: 0
A26: 新增占比｜GB300 NVL72 | B26: % | C26: 1 | D26: 0.5 | E26: 0 | F26: 0 | G26: 0
A27: 新增占比｜VR200 NVL72 | B27: % | C27: 0 | D27: 0.5 | E27: 1 | F27: 1 | G27: 1
A28: 期別序號（長約起始期比對用） | C28: 0 | D28: 1 | E28: 2 | F28: 3 | G28: 4 | I28: 0＝首期
A30: B2｜上限檢查用四層瀑布（IFW_RevGWFleet_*，各世代；基準成本情境）
A31: 世代 | B31: 單位 | C31: _100 | D31: _Util | E31: _Prod | F31: _Life | I31: 說明／來源
A32: 四層｜Hopper H100 | B32: US$m/MW | C32: =TK_RevGWFleet_100_H100 -> 11.1384 | D32: =TK_RevGWFleet_Util_H100 -> 6.6830402 | E32: =TK_RevGWFleet_Prod_H100 -> 5.0184896 | F32: =TK_RevGWFleet_Life_H100 -> 5.0184896 | I32: 四層＝_100 理論上限（100% 利用）→ _Util 扣技術利用率（＝IF_RevGWFleet）→ _Prod 再扣 SLO 下產能折減（門檻比較層）→ _Life 壽命期等值；用途限制（IFC_Use）：情境、相對比較、反轉門檻；上限，不得作預測
A33: 四層｜GB200 NVL72 | B33: US$m/MW | C33: =TK_RevGWFleet_100_GB200 -> 54.809174 | D33: =TK_RevGWFleet_Util_GB200 -> 32.885504 | E33: =TK_RevGWFleet_Prod_GB200 -> 26.277376 | F33: =TK_RevGWFleet_Life_GB200 -> 26.277376
A34: 四層｜GB300 NVL72 | B34: US$m/MW | C34: =TK_RevGWFleet_100_GB300 -> 66.852442 | D34: =TK_RevGWFleet_Util_GB300 -> 40.111465 | E34: =TK_RevGWFleet_Prod_GB300 -> 31.774316 | F34: =TK_RevGWFleet_Life_GB300 -> 31.774316
A35: 四層｜VR200 NVL72 | B35: US$m/MW | C35: =TK_RevGWFleet_100_VR200 -> 109.93806 | D35: =TK_RevGWFleet_Util_VR200 -> 65.962839 | E35: =TK_RevGWFleet_Prod_VR200 -> 53.154069 | F35: =TK_RevGWFleet_Life_VR200 -> 53.154069
A37: C｜已揭露多年期合約（長約占比用；只換算 MW 占比，不用來推 k）
A38: 合約 | B38: 單位 | C38: MW（基準） | D38: 起始期序號 | E38: MW 下緣 | F38: MW 上緣 | I38: 換算依據／來源
A39: 合約｜Microsoft（Vineland，5 年） | B39: MW | C39: 205 | D39: 0 | E39: 50 | F39: 274 | I39: 約 10 萬顆 GB300 ÷ 487 顆/MW＝205 MW-IT（Bloomberg 引述匿名消息）；下緣 50 MW＝Epoch AI 衛星估計 Vineland 第一期 IT 容量（2026-07）；上緣＝$17.4bn ÷ 5 ÷ 12.72＝274；6-K 2025-09-08；Bloomberg 2025-10-02；Epoch AI Frontier Data Centers（2026-08-24 更新） [Derived]
A40: 合約｜Meta 第一份（5 年） | B40: MW | C40: 46 | D40: 0 | E40: 37 | F40: 60 | I40: $2.9bn ÷ 5 ÷ 12.72（GB300 錨）＝46 MW；區間 [Assumed]：下緣＝基準 × 0.8（價格高於錨）、上緣＝÷（12.72 × k_長約 0.76）；6-K 2025-11-13 附件 99.2 [Derived]
A41: 合約｜Meta 第二份專用容量（5 年，2027 年初起） | B41: MW | C41: 188 | D41: 1 | E41: 150 | F41: 247 | I41: $12bn ÷ 5 ÷ 12.76（VR200 錨）＝188 MW；區間 [Assumed]：下緣＝基準 × 0.8、上緣＝÷（12.76 × 0.76）；6-K 2026-03-16 附件 99.1 [Derived]
A42: 合約｜Meta 未售容量承購（或有，最高 $15bn） | B42: MW | C42: 0 | D42: 1 | E42: 0 | F42: 235 | I42: 公司擬先賣給第三方客戶、未售部分才由 Meta 承購 → 基準不計為長約；上緣＝$15bn ÷ 5 ÷ 12.76＝235；6-K 2026-03-16 附件 99.1 [Assumed]
A43: 算式 | I43: 長約占比_t＝MIN(1, 已揭露多年期合約在役 MW_t ÷ 平均在役 MW_t)；合約 MW＝揭露的 GPU 數 ÷ 每 MW GPU 數（Microsoft），未揭露者＝TCV ÷ 年期 ÷ 錨價（IF_HoldEcon 基準，未乘 k）；平均在役 MW＝（期初＋期末）÷ 2，期末＝已連網 MW × 在役比例，期初（首期）＝priceCheck.inServiceMw [Derived]
A45: ▸ 容量情境｜保守 已簽約 3.5 GW
A46: 項目 | B46: 單位 | C46: FY26 | D46: FY27 | E46: FY28 | F46: FY29 | G46: FY30 | I46: 說明／來源
A47: 保守 已簽約 3.5 GW｜期末在役 MW（已連網 × 在役比例） | B47: MW | C47: =輸入與假設!C11*輸入與假設!C21 -> 562.5 | D47: =輸入與假設!D11*輸入與假設!D21 -> 1130.5 | E47: =輸入與假設!E11*輸入與假設!E21 -> 1719 | F47: =輸入與假設!F11*輸入與假設!F21 -> 2241 | G47: =輸入與假設!G11*輸入與假設!G21 -> 2625.3
A48: 保守 已簽約 3.5 GW｜期初在役 MW | B48: MW | C48: =$C$21 -> 366 | D48: =C47 -> 562.5 | E48: =D47 -> 1130.5 | F48: =E47 -> 1719 | G48: =F47 -> 2241
A49: 保守 已簽約 3.5 GW｜新增在役 MW | B49: MW | C49: =MAX(0,C47-C48) -> 196.5 | D49: =MAX(0,D47-D48) -> 568 | E49: =MAX(0,E47-E48) -> 588.5 | F49: =MAX(0,F47-F48) -> 522 | G49: =MAX(0,G47-G48) -> 384.3
A50: 保守 已簽約 3.5 GW｜期末 MW｜Hopper H100 | B50: MW | C50: =$C$21*$E$16+C49*C24 -> 102.48 | D50: =C50+D49*D24 -> 102.48 | E50: =D50+E49*E24 -> 102.48 | F50: =E50+F49*F24 -> 102.48 | G50: =F50+G49*G24 -> 102.48
A51: 保守 已簽約 3.5 GW｜期末 MW｜GB200 NVL72 | B51: MW | C51: =$C$21*$E$17+C49*C25 -> 69.54 | D51: =C51+D49*D25 -> 69.54 | E51: =D51+E49*E25 -> 69.54 | F51: =E51+F49*F25 -> 69.54 | G51: =F51+G49*G25 -> 69.54
A52: 保守 已簽約 3.5 GW｜期末 MW｜GB300 NVL72 | B52: MW | C52: =$C$21*$E$18+C49*C26 -> 390.48 | D52: =C52+D49*D26 -> 674.48 | E52: =D52+E49*E26 -> 674.48 | F52: =E52+F49*F26 -> 674.48 | G52: =F52+G49*G26 -> 674.48
A53: 保守 已簽約 3.5 GW｜期末 MW｜VR200 NVL72 | B53: MW | C53: =$C$21*$E$19+C49*C27 -> 0 | D53: =C53+D49*D27 -> 284 | E53: =D53+E49*E27 -> 872.5 | F53: =E53+F49*F27 -> 1394.5 | G53: =F53+G49*G27 -> 1778.8
A54: 保守 已簽約 3.5 GW｜平均在役占比｜Hopper H100 | B54: % | C54: =($C$21*$E$16+C50)/(C48+C47) -> 0.22074313 | D54: =(C50+D50)/(D48+D47) -> 0.1210632 | E54: =(D50+E50)/(E48+E47) -> 0.071928408 | F54: =(E50+F50)/(F48+F47) -> 0.051757576 | G54: =(F50+G50)/(G48+G47) -> 0.042118242
A55: 保守 已簽約 3.5 GW｜平均在役占比｜GB200 NVL72 | B55: % | C55: =($C$21*$E$17+C51)/(C48+C47) -> 0.14978998 | D55: =(C51+D51)/(D48+D47) -> 0.08215003 | E55: =(D51+E51)/(E48+E47) -> 0.048808563 | F55: =(E51+F51)/(F48+F47) -> 0.035121212 | G55: =(F51+G51)/(G48+G47) -> 0.028580235
A56: 保守 已簽約 3.5 GW｜平均在役占比｜GB300 NVL72 | B56: % | C56: =($C$21*$E$18+C52)/(C48+C47) -> 0.62946688 | D56: =(C52+D52)/(D48+D47) -> 0.62903721 | E56: =(D52+E52)/(E48+E47) -> 0.47340235 | F56: =(E52+F52)/(F48+F47) -> 0.34064646 | G56: =(F52+G52)/(G48+G47) -> 0.27720445
A57: 保守 已簽約 3.5 GW｜平均在役占比｜VR200 NVL72 | B57: % | C57: =($C$21*$E$19+C53)/(C48+C47) -> 0 | D57: =(C53+D53)/(D48+D47) -> 0.16774956 | E57: =(D53+E53)/(E48+E47) -> 0.40586068 | F57: =(E53+F53)/(F48+F47) -> 0.57247475 | G57: =(F53+G53)/(G48+G47) -> 0.65209708
A58: 保守 已簽約 3.5 GW｜錨：每 MW 經濟持有成本（IF_HoldEcon，在役世代加權） | B58: US$m/MW | C58: =C54*$C$16+C55*$C$17+C56*$C$18+C57*$C$19 -> 10.316896 | D58: =D54*$C$16+D55*$C$17+D56*$C$18+D57*$C$19 -> 10.798696 | E58: =E54*$C$16+E55*$C$17+E56*$C$18+E57*$C$19 -> 11.244308 | F58: =F54*$C$16+F55*$C$17+F56*$C$18+F57*$C$19 -> 11.519455 | G58: =G54*$C$16+G55*$C$17+G56*$C$18+G57*$C$19 -> 11.650943 | I58: WACC 10% 下的打平租金（100% 計費時數）
A59: 保守 已簽約 3.5 GW｜平均在役 MW | B59: MW | C59: =(C48+C47)/2 -> 464.25 | D59: =(D48+D47)/2 -> 846.5 | E59: =(E48+E47)/2 -> 1424.75 | F59: =(F48+F47)/2 -> 1980 | G59: =(G48+G47)/2 -> 2433.15
A60: 保守 已簽約 3.5 GW｜已揭露長約 MW（起始期 ≤ 本期） | B60: MW | C60: =SUMIF($D$39:$D$42,"<="&C$28,$C$39:$C$42) -> 251 | D60: =SUMIF($D$39:$D$42,"<="&D$28,$C$39:$C$42) -> 439 | E60: =SUMIF($D$39:$D$42,"<="&E$28,$C$39:$C$42) -> 439 | F60: =SUMIF($D$39:$D$42,"<="&F$28,$C$39:$C$42) -> 439 | G60: =SUMIF($D$39:$D$42,"<="&G$28,$C$39:$C$42) -> 439
A61: 保守 已簽約 3.5 GW｜長約占比（對照，不驅動 k；MIN(1, 長約 MW ÷ 平均在役 MW)） | B61: % | C61: =MIN(1,C60/C59) -> 0.54065697 | D61: =MIN(1,D60/D59) -> 0.51860602 | E61: =MIN(1,E60/E59) -> 0.30812423 | F61: =MIN(1,F60/F59) -> 0.22171717 | G61: =MIN(1,G60/G59) -> 0.18042455
A62: 保守 已簽約 3.5 GW｜定價倍數 k（隨需占比 × k_現貨＋（1 − 隨需占比）× k_長約） | B62: 倍 | C62: =$C$10*$C$9+(1-$C$10)*$C$8 -> 0.89101909 | D62: =$C$10*$C$9+(1-$C$10)*$C$8 -> 0.89101909 | E62: =$C$10*$C$9+(1-$C$10)*$C$8 -> 0.89101909 | F62: =$C$10*$C$9+(1-$C$10)*$C$8 -> 0.89101909 | G62: =$C$10*$C$9+(1-$C$10)*$C$8 -> 0.89101909
A63: 保守 已簽約 3.5 GW｜每 MW 年收入（錨 × k，100% 計費時數） | B63: US$m/MW | C63: =C58*C62 -> 9.1925511 | D63: =D58*D62 -> 9.6218441 | E63: =E58*E62 -> 10.018893 | F63: =F58*F62 -> 10.264054 | G63: =G58*G62 -> 10.381213 | I63: →『輸入與假設』A 區「每 MW 年收入｜保守 已簽約 3.5 GW」（÷ 1000）
A64: 保守 已簽約 3.5 GW｜上限檢查｜客戶每 MW 付費 token 營收（IF_RevGWFleet，在役世代加權） | B64: US$m/MW | C64: =C54*$D$16+C55*$D$17+C56*$D$18+C57*$D$19 -> 31.649993 | D64: =D54*$D$16+D55*$D$17+D56*$D$18+D57*$D$19 -> 39.807457 | E64: =E54*$D$16+E55*$D$17+E56*$D$18+E57*$D$19 -> 47.846379 | F64: =F54*$D$16+F55*$D$17+F56*$D$18+F57*$D$19 -> 52.926765 | G64: =G54*$D$16+G55*$D$17+G56*$D$18+G57*$D$19 -> 55.354604
A65: 保守 已簽約 3.5 GW｜上限檢查｜四層｜客戶每 MW 付費 token 營收｜_100（IFW_RevGWFleet_100，在役世代加權） | B65: US$m/MW | C65: =C54*$C$32+C55*$C$33+C56*$C$34+C57*$C$35 -> 52.749989 | D65: =D54*$C$32+D55*$C$33+D56*$C$34+D57*$C$35 -> 66.345761 | E65: =E54*$C$32+E55*$C$33+E56*$C$34+E57*$C$35 -> 79.743965 | F65: =F54*$C$32+F55*$C$33+F56*$C$34+F57*$C$35 -> 88.211275 | G65: =G54*$C$32+G55*$C$33+G56*$C$34+G57*$C$35 -> 92.257674
A66: 保守 已簽約 3.5 GW｜上限檢查｜四層｜客戶每 MW 付費 token 營收｜_Util（IFW_RevGWFleet_Util，在役世代加權） | B66: US$m/MW | C66: =C54*$D$32+C55*$D$33+C56*$D$34+C57*$D$35 -> 31.649993 | D66: =D54*$D$32+D55*$D$33+D56*$D$34+D57*$D$35 -> 39.807457 | E66: =E54*$D$32+E55*$D$33+E56*$D$34+E57*$D$35 -> 47.846379 | F66: =F54*$D$32+F55*$D$33+F56*$D$34+F57*$D$35 -> 52.926765 | G66: =G54*$D$32+G55*$D$33+G56*$D$34+G57*$D$35 -> 55.354604
A67: 保守 已簽約 3.5 GW｜上限檢查｜四層｜客戶每 MW 付費 token 營收｜_Prod（IFW_RevGWFleet_Prod，在役世代加權） | B67: US$m/MW | C67: =C54*$E$32+C55*$E$33+C56*$E$34+C57*$E$35 -> 25.044764 | D67: =D54*$E$32+D55*$E$33+D56*$E$34+D57*$E$35 -> 31.67004 | E67: =E54*$E$32+E55*$E$33+E56*$E$34+E57*$E$35 -> 38.258715 | F67: =F54*$E$32+F55*$E$33+F56*$E$34+F57*$E$35 -> 42.435809 | G67: =G54*$E$32+G55*$E$33+G56*$E$34+G57*$E$35 -> 44.431978
A68: 保守 已簽約 3.5 GW｜上限檢查｜四層｜客戶每 MW 付費 token 營收｜_Life（IFW_RevGWFleet_Life，在役世代加權） | B68: US$m/MW | C68: =C54*$F$32+C55*$F$33+C56*$F$34+C57*$F$35 -> 25.044764 | D68: =D54*$F$32+D55*$F$33+D56*$F$34+D57*$F$35 -> 31.67004 | E68: =E54*$F$32+E55*$F$33+E56*$F$34+E57*$F$35 -> 38.258715 | F68: =F54*$F$32+F55*$F$33+F56*$F$34+F57*$F$35 -> 42.435809 | G68: =G54*$F$32+G55*$F$33+G56*$F$34+G57*$F$35 -> 44.431978
A69: 保守 已簽約 3.5 GW｜上限檢查｜四層｜Nebius 每 MW 計費收入 ÷ _100 | B69: % | C69: =C63/C65 -> 0.17426641 | D69: =D63/D65 -> 0.14502576 | E69: =E63/E65 -> 0.12563826 | F69: =F63/F65 -> 0.11635762 | G69: =G63/G65 -> 0.11252411 | I69: ＝Nebius 每 MW 年收入（100% 計費時數）÷ 該層
A70: 保守 已簽約 3.5 GW｜上限檢查｜四層｜Nebius 每 MW 計費收入 ÷ _Util | B70: % | C70: =C63/C66 -> 0.29044401 | D70: =D63/D66 -> 0.24170959 | E70: =E63/E66 -> 0.2093971 | F70: =F63/F66 -> 0.19392937 | G70: =G63/G66 -> 0.18754019 | I70: ＝Nebius 每 MW 年收入（100% 計費時數）÷ 該層
A71: 保守 已簽約 3.5 GW｜上限檢查｜四層｜Nebius 每 MW 計費收入 ÷ _Prod | B71: % | C71: =C63/C67 -> 0.36704482 | D71: =D63/D67 -> 0.30381534 | E71: =E63/E67 -> 0.26187218 | F71: =F63/F67 -> 0.24187248 | G71: =G63/G67 -> 0.23364283 | I71: ＝Nebius 每 MW 年收入（100% 計費時數）÷ 該層（比較層，門檻判定用）
A72: 保守 已簽約 3.5 GW｜上限檢查｜四層｜Nebius 每 MW 計費收入 ÷ _Life | B72: % | C72: =C63/C68 -> 0.36704482 | D72: =D63/D68 -> 0.30381534 | E72: =E63/E68 -> 0.26187218 | F72: =F63/F68 -> 0.24187248 | G72: =G63/G68 -> 0.23364283 | I72: ＝Nebius 每 MW 年收入（100% 計費時數）÷ 該層
A73: 保守 已簽約 3.5 GW｜上限檢查｜每 MW 收入 ÷ 客戶付費 token 營收 | B73: % | C73: =C71 -> 0.36704482 | D73: =D71 -> 0.30381534 | E73: =E71 -> 0.26187218 | F73: =F71 -> 0.24187248 | G73: =G71 -> 0.23364283 | I73: neocloud 拿走客戶 token 營收的比例，取比較層 _Prod（methodology.checks.revCapLayer；_Prod 已扣 SLO 下的產能折減，最接近可實際售出 token）；> 50% 時『檢查_連動』警示（門檻 methodology.checks.revCapShareMax）
A75: ▸ 容量情境｜基準 合約 5 GW
A76: 項目 | B76: 單位 | C76: FY26 | D76: FY27 | E76: FY28 | F76: FY29 | G76: FY30 | I76: 說明／來源
A77: 基準 合約 5 GW｜期末在役 MW（已連網 × 在役比例） | B77: MW | C77: =輸入與假設!C14*輸入與假設!C21 -> 562.5 | D77: =輸入與假設!D14*輸入與假設!D21 -> 1130.5 | E77: =輸入與假設!E14*輸入與假設!E21 -> 1719 | F77: =輸入與假設!F14*輸入與假設!F21 -> 2241 | G77: =輸入與假設!G14*輸入與假設!G21 -> 2763
A78: 基準 合約 5 GW｜期初在役 MW | B78: MW | C78: =$C$21 -> 366 | D78: =C77 -> 562.5 | E78: =D77 -> 1130.5 | F78: =E77 -> 1719 | G78: =F77 -> 2241
A79: 基準 合約 5 GW｜新增在役 MW | B79: MW | C79: =MAX(0,C77-C78) -> 196.5 | D79: =MAX(0,D77-D78) -> 568 | E79: =MAX(0,E77-E78) -> 588.5 | F79: =MAX(0,F77-F78) -> 522 | G79: =MAX(0,G77-G78) -> 522
A80: 基準 合約 5 GW｜期末 MW｜Hopper H100 | B80: MW | C80: =$C$21*$E$16+C79*C24 -> 102.48 | D80: =C80+D79*D24 -> 102.48 | E80: =D80+E79*E24 -> 102.48 | F80: =E80+F79*F24 -> 102.48 | G80: =F80+G79*G24 -> 102.48
A81: 基準 合約 5 GW｜期末 MW｜GB200 NVL72 | B81: MW | C81: =$C$21*$E$17+C79*C25 -> 69.54 | D81: =C81+D79*D25 -> 69.54 | E81: =D81+E79*E25 -> 69.54 | F81: =E81+F79*F25 -> 69.54 | G81: =F81+G79*G25 -> 69.54
A82: 基準 合約 5 GW｜期末 MW｜GB300 NVL72 | B82: MW | C82: =$C$21*$E$18+C79*C26 -> 390.48 | D82: =C82+D79*D26 -> 674.48 | E82: =D82+E79*E26 -> 674.48 | F82: =E82+F79*F26 -> 674.48 | G82: =F82+G79*G26 -> 674.48
A83: 基準 合約 5 GW｜期末 MW｜VR200 NVL72 | B83: MW | C83: =$C$21*$E$19+C79*C27 -> 0 | D83: =C83+D79*D27 -> 284 | E83: =D83+E79*E27 -> 872.5 | F83: =E83+F79*F27 -> 1394.5 | G83: =F83+G79*G27 -> 1916.5
A84: 基準 合約 5 GW｜平均在役占比｜Hopper H100 | B84: % | C84: =($C$21*$E$16+C80)/(C78+C77) -> 0.22074313 | D84: =(C80+D80)/(D78+D77) -> 0.1210632 | E84: =(D80+E80)/(E78+E77) -> 0.071928408 | F84: =(E80+F80)/(F78+F77) -> 0.051757576 | G84: =(F80+G80)/(G78+G77) -> 0.040959233
A85: 基準 合約 5 GW｜平均在役占比｜GB200 NVL72 | B85: % | C85: =($C$21*$E$17+C81)/(C78+C77) -> 0.14978998 | D85: =(C81+D81)/(D78+D77) -> 0.08215003 | E85: =(D81+E81)/(E78+E77) -> 0.048808563 | F85: =(E81+F81)/(F78+F77) -> 0.035121212 | G85: =(F81+G81)/(G78+G77) -> 0.027793765
A86: 基準 合約 5 GW｜平均在役占比｜GB300 NVL72 | B86: % | C86: =($C$21*$E$18+C82)/(C78+C77) -> 0.62946688 | D86: =(C82+D82)/(D78+D77) -> 0.62903721 | E86: =(D82+E82)/(E78+E77) -> 0.47340235 | F86: =(E82+F82)/(F78+F77) -> 0.34064646 | G86: =(F82+G82)/(G78+G77) -> 0.26957634
A87: 基準 合約 5 GW｜平均在役占比｜VR200 NVL72 | B87: % | C87: =($C$21*$E$19+C83)/(C78+C77) -> 0 | D87: =(C83+D83)/(D78+D77) -> 0.16774956 | E87: =(D83+E83)/(E78+E77) -> 0.40586068 | F87: =(E83+F83)/(F78+F77) -> 0.57247475 | G87: =(F83+G83)/(G78+G77) -> 0.66167066
A88: 基準 合約 5 GW｜錨：每 MW 經濟持有成本（IF_HoldEcon，在役世代加權） | B88: US$m/MW | C88: =C84*$C$16+C85*$C$17+C86*$C$18+C87*$C$19 -> 10.316896 | D88: =D84*$C$16+D85*$C$17+D86*$C$18+D87*$C$19 -> 10.798696 | E88: =E84*$C$16+E85*$C$17+E86*$C$18+E87*$C$19 -> 11.244308 | F88: =F84*$C$16+F85*$C$17+F86*$C$18+F87*$C$19 -> 11.519455 | G88: =G84*$C$16+G85*$C$17+G86*$C$18+G87*$C$19 -> 11.666753
A89: 基準 合約 5 GW｜平均在役 MW | B89: MW | C89: =(C78+C77)/2 -> 464.25 | D89: =(D78+D77)/2 -> 846.5 | E89: =(E78+E77)/2 -> 1424.75 | F89: =(F78+F77)/2 -> 1980 | G89: =(G78+G77)/2 -> 2502
A90: 基準 合約 5 GW｜已揭露長約 MW（起始期 ≤ 本期） | B90: MW | C90: =SUMIF($D$39:$D$42,"<="&C$28,$C$39:$C$42) -> 251 | D90: =SUMIF($D$39:$D$42,"<="&D$28,$C$39:$C$42) -> 439 | E90: =SUMIF($D$39:$D$42,"<="&E$28,$C$39:$C$42) -> 439 | F90: =SUMIF($D$39:$D$42,"<="&F$28,$C$39:$C$42) -> 439 | G90: =SUMIF($D$39:$D$42,"<="&G$28,$C$39:$C$42) -> 439
A91: 基準 合約 5 GW｜長約占比（對照，不驅動 k；MIN(1, 長約 MW ÷ 平均在役 MW)） | B91: % | C91: =MIN(1,C90/C89) -> 0.54065697 | D91: =MIN(1,D90/D89) -> 0.51860602 | E91: =MIN(1,E90/E89) -> 0.30812423 | F91: =MIN(1,F90/F89) -> 0.22171717 | G91: =MIN(1,G90/G89) -> 0.17545963
A92: 基準 合約 5 GW｜定價倍數 k（隨需占比 × k_現貨＋（1 − 隨需占比）× k_長約） | B92: 倍 | C92: =$C$10*$C$9+(1-$C$10)*$C$8 -> 0.89101909 | D92: =$C$10*$C$9+(1-$C$10)*$C$8 -> 0.89101909 | E92: =$C$10*$C$9+(1-$C$10)*$C$8 -> 0.89101909 | F92: =$C$10*$C$9+(1-$C$10)*$C$8 -> 0.89101909 | G92: =$C$10*$C$9+(1-$C$10)*$C$8 -> 0.89101909
A93: 基準 合約 5 GW｜每 MW 年收入（錨 × k，100% 計費時數） | B93: US$m/MW | C93: =C88*C92 -> 9.1925511 | D93: =D88*D92 -> 9.6218441 | E93: =E88*E92 -> 10.018893 | F93: =F88*F92 -> 10.264054 | G93: =G88*G92 -> 10.3953 | I93: →『輸入與假設』A 區「每 MW 年收入｜基準 合約 5 GW」（÷ 1000）
A94: 基準 合約 5 GW｜上限檢查｜客戶每 MW 付費 token 營收（IF_RevGWFleet，在役世代加權） | B94: US$m/MW | C94: =C84*$D$16+C85*$D$17+C86*$D$18+C87*$D$19 -> 31.649993 | D94: =D84*$D$16+D85*$D$17+D86*$D$18+D87*$D$19 -> 39.807457 | E94: =E84*$D$16+E85*$D$17+E86*$D$18+E87*$D$19 -> 47.846379 | F94: =F84*$D$16+F85*$D$17+F86*$D$18+F87*$D$19 -> 52.926765 | G94: =G84*$D$16+G85*$D$17+G86*$D$18+G87*$D$19 -> 55.646522
A95: 基準 合約 5 GW｜上限檢查｜四層｜客戶每 MW 付費 token 營收｜_100（IFW_RevGWFleet_100，在役世代加權） | B95: US$m/MW | C95: =C84*$C$32+C85*$C$33+C86*$C$34+C87*$C$35 -> 52.749989 | D95: =D84*$C$32+D85*$C$33+D86*$C$34+D87*$C$35 -> 66.345761 | E95: =E84*$C$32+E85*$C$33+E86*$C$34+E87*$C$35 -> 79.743965 | F95: =F84*$C$32+F85*$C$33+F86*$C$34+F87*$C$35 -> 88.211275 | G95: =G84*$C$32+G85*$C$33+G86*$C$34+G87*$C$35 -> 92.744203
A96: 基準 合約 5 GW｜上限檢查｜四層｜客戶每 MW 付費 token 營收｜_Util（IFW_RevGWFleet_Util，在役世代加權） | B96: US$m/MW | C96: =C84*$D$32+C85*$D$33+C86*$D$34+C87*$D$35 -> 31.649993 | D96: =D84*$D$32+D85*$D$33+D86*$D$34+D87*$D$35 -> 39.807457 | E96: =E84*$D$32+E85*$D$33+E86*$D$34+E87*$D$35 -> 47.846379 | F96: =F84*$D$32+F85*$D$33+F86*$D$34+F87*$D$35 -> 52.926765 | G96: =G84*$D$32+G85*$D$33+G86*$D$34+G87*$D$35 -> 55.646522
A97: 基準 合約 5 GW｜上限檢查｜四層｜客戶每 MW 付費 token 營收｜_Prod（IFW_RevGWFleet_Prod，在役世代加權） | B97: US$m/MW | C97: =C84*$E$32+C85*$E$33+C86*$E$34+C87*$E$35 -> 25.044764 | D97: =D84*$E$32+D85*$E$33+D86*$E$34+D87*$E$35 -> 31.67004 | E97: =E84*$E$32+E85*$E$33+E86*$E$34+E87*$E$35 -> 38.258715 | F97: =F84*$E$32+F85*$E$33+F86*$E$34+F87*$E$35 -> 42.435809 | G97: =G84*$E$32+G85*$E$33+G86*$E$34+G87*$E$35 -> 44.671992
A98: 基準 合約 5 GW｜上限檢查｜四層｜客戶每 MW 付費 token 營收｜_Life（IFW_RevGWFleet_Life，在役世代加權） | B98: US$m/MW | C98: =C84*$F$32+C85*$F$33+C86*$F$34+C87*$F$35 -> 25.044764 | D98: =D84*$F$32+D85*$F$33+D86*$F$34+D87*$F$35 -> 31.67004 | E98: =E84*$F$32+E85*$F$33+E86*$F$34+E87*$F$35 -> 38.258715 | F98: =F84*$F$32+F85*$F$33+F86*$F$34+F87*$F$35 -> 42.435809 | G98: =G84*$F$32+G85*$F$33+G86*$F$34+G87*$F$35 -> 44.671992
A99: 基準 合約 5 GW｜上限檢查｜四層｜Nebius 每 MW 計費收入 ÷ _100 | B99: % | C99: =C93/C95 -> 0.17426641 | D99: =D93/D95 -> 0.14502576 | E99: =E93/E95 -> 0.12563826 | F99: =F93/F95 -> 0.11635762 | G99: =G93/G95 -> 0.11208571 | I99: ＝Nebius 每 MW 年收入（100% 計費時數）÷ 該層
A100: 基準 合約 5 GW｜上限檢查｜四層｜Nebius 每 MW 計費收入 ÷ _Util | B100: % | C100: =C93/C96 -> 0.29044401 | D100: =D93/D96 -> 0.24170959 | E100: =E93/E96 -> 0.2093971 | F100: =F93/F96 -> 0.19392937 | G100: =G93/G96 -> 0.18680952 | I100: ＝Nebius 每 MW 年收入（100% 計費時數）÷ 該層
A101: 基準 合約 5 GW｜上限檢查｜四層｜Nebius 每 MW 計費收入 ÷ _Prod | B101: % | C101: =C93/C97 -> 0.36704482 | D101: =D93/D97 -> 0.30381534 | E101: =E93/E97 -> 0.26187218 | F101: =F93/F97 -> 0.24187248 | G101: =G93/G97 -> 0.23270285 | I101: ＝Nebius 每 MW 年收入（100% 計費時數）÷ 該層（比較層，門檻判定用）
A102: 基準 合約 5 GW｜上限檢查｜四層｜Nebius 每 MW 計費收入 ÷ _Life | B102: % | C102: =C93/C98 -> 0.36704482 | D102: =D93/D98 -> 0.30381534 | E102: =E93/E98 -> 0.26187218 | F102: =F93/F98 -> 0.24187248 | G102: =G93/G98 -> 0.23270285 | I102: ＝Nebius 每 MW 年收入（100% 計費時數）÷ 該層
A103: 基準 合約 5 GW｜上限檢查｜每 MW 收入 ÷ 客戶付費 token 營收 | B103: % | C103: =C101 -> 0.36704482 | D103: =D101 -> 0.30381534 | E103: =E101 -> 0.26187218 | F103: =F101 -> 0.24187248 | G103: =G101 -> 0.23270285 | I103: neocloud 拿走客戶 token 營收的比例，取比較層 _Prod（methodology.checks.revCapLayer；_Prod 已扣 SLO 下的產能折減，最接近可實際售出 token）；> 50% 時『檢查_連動』警示（門檻 methodology.checks.revCapShareMax）
A105: ▸ 容量情境｜積極 每年 >1 GW
A106: 項目 | B106: 單位 | C106: FY26 | D106: FY27 | E106: FY28 | F106: FY29 | G106: FY30 | I106: 說明／來源
A107: 積極 每年 >1 GW｜期末在役 MW（已連網 × 在役比例） | B107: MW | C107: =輸入與假設!C17*輸入與假設!C21 -> 562.5 | D107: =輸入與假設!D17*輸入與假設!D21 -> 1345.55 | E107: =輸入與假設!E17*輸入與假設!E21 -> 2174.4 | F107: =輸入與假設!F17*輸入與假設!F21 -> 2924.1 | G107: =輸入與假設!G17*輸入與假設!G21 -> 3673.8
...

Sheet 公司實況驗證
A1: 公司實況驗證（Tokenomics 參數 vs Nebius 已申報實際數）
A2: 公司實況驗證（已決定事項 15；v0.2a 第 2 輪）：取自 Tokenomics 的參數與 Nebius 已申報實際數逐項對照；差距 > 10% 時找有證據的機制做公司調整並寫明何時回到 Tokenomics 值，找不到機制則維持 Tokenomics／現行值、公司實際列為敏感度；不為讓營收或 EBITDA 總數貼近而倒推係數。數值為建置前計算（[Derived]），Excel「公司實況驗證」分頁與報告呈現。
A3: 規則：差距 > 10% 時需有證據的機制才做公司調整；找不到機制則維持 Tokenomics／現行值，公司實際列為敏感度。
A4: 參數 | B4: Tokenomics 值（名稱） | C4: Tokenomics | D4: Nebius 實際（數值、期間） | E4: 實際 | F4: 差距 | G4: 差距原因（機制與證據） | H4: 公司調整（何時回到 Tokenomics 值） | I4: 採用值 | J4: 標記
A5: 驗證｜每 MW 年收入（定價倍數 k） | B5: IF_HoldEcon × k_長約 0.89（v18.0 隨成本重算）：FY26 9.19 US$m/MW（錨 10.32） | C5: 9.19 | D5: Q2 AI cloud 營收 574.9 × 4 ÷ 季末在役 366 MW（內插）＝6.28 US$m/MW（Q2 2026 6-K 附註 15 分部營收 [Interested-party]；在役 MW 為 [Derived] 內插） | E5: 6.28 | F5: =IF(ISNUMBER(E5),E5/C5-1,"不適用") -> -0.31664853 | G5: 找到：爬坡——Q2 股東信「brought additional capacity online across sites in the US and Europe during the second half of the second quarter」「delivered all capacity tranches to Microsoft」：新容量在季末前才上線，季內計費 MW 低於季末在役 MW。 | H5: 沿用既有機制：期初可計費 MW＝Q2 營收 × 4 ÷ 首期每 MW 年收入（253 ÷ 366＝69%），爬坡係數 60%／80%／100%，FY28 起回到全額計費；k 不調整 | I5: k＝0.89（市場長約；證據價格 ÷ v18.0 成本）；每 MW 年收入 9.19 → 10.40 | J5: [Derived]
A6: 驗證｜定價倍數 k：Nebius 自身合約（Microsoft） | B6: k_長約 0.89（IREN–Microsoft 9.70 ÷ IF_HoldEcon｜GB300 10.89） | C6: 0.891 | D6: 17.4bn ÷ 5 年 ÷ 假設容量 ÷ 10.89：1.07（300 MW 視為 IT）／1.28（視為設施）／1.56（約 10 萬顆 GB300）（Microsoft 協議 6-K 2025-09-08、Q3 2025 附註（TCV、5 年、Vineland 分批）[Interested-party]；容量為 Nebius 站點新聞稿與 Bloomberg 引述 [Assumed]） | E6: 1.28 | F6: =IF(ISNUMBER(E6),E6/C6-1,"不適用") -> 0.4365881 | G6: 找不到可用的已揭露條款：合約未揭露 MW 或 GPU 數，換算必須假設容量（已決定事項 15 要求完全由已揭露條款算出）。 | H6: 不調整；列敏感度（k_長約 1.07／1.28／1.56） | I6: k_長約 0.89 | J6: [Derived]／[Assumed]
A7: 驗證｜營運現金成本（不含 D&A，每 MW） | B7: IF_OpexGW（季末世代加權）1.92 US$m/MW·年（電費 0.67、IT 維護 0.46、廠房維護 0.25、人員軟體 0.33、稅險 0.21；v18.0 IT 維護約減半） | C7: 1.92 | D7: Q2 營業成本（不含 D&A）133.6 × 4 ÷ 366 MW＝1.46（Q2 2026 6-K 損益表 [Interested-party]） | E7: 1.46 | F7: =IF(ISNUMBER(E7),E7/C7-1,"不適用") -> -0.23958333 | G7: 未找到有證據的機制：可能來源——(a) 爬坡分母（季均在役 MW 低於季末 366，方向成立但幅度無法量化）；(b) IT 維護在保固期內（未找到 Nebius 保固條款）；(c) 營業成本口徑不含人員、稅險（未證實）。 | H7: 不調整（模型營運成本採 EBITDA 率路徑，不使用 Tokenomics 由下而上；第 1 輪結論保留）；Nebius 實際列為對照 | I7: EBITDA 率路徑（不切換） | J7: [Derived]
A8: 驗證｜EBITDA 率 | B8: 由下而上隱含（未扣管銷與租金）：1 − 1.94 ÷ 9.19＝78.9%（FY26） | C8: 0.789 | D8: Q2 AI cloud 分部調整後 EBITDA 285.7 ÷ 574.9＝49.7%（合併 236.2 ÷ 582.3＝40.6%）（Q2 2026 6-K 附註 15 [Interested-party]） | E8: 0.497 | F8: =IF(ISNUMBER(E8),E8/C8-1,"不適用") -> -0.37008872 | G8: 找到：管銷、研發與分部費用（Q2 合併營收 582.3 − 營業成本 133.6 − 調整後 EBITDA 236.2＝212.5，約占 36%）不在 Tokenomics 範圍。 | H8: 已在模型：EBITDA 率起點＝Q2 AI cloud 分部實際 49.7%，線性走向 47%（可觀察 neocloud 區間中點）；何時回到 Tokenomics：不回（成本端是否切換待 Andy 決定） | I8: 49.7% → 47% | J8: [Interested-party]
A9: 驗證｜每 MW 資本支出 | B9: IF_CapexTotal GB300 44.91／VR200 50.26 US$m/MW-IT（首期新增全為 GB300） | C9: 44.91 | D9: H1 現金資本支出 8,130 ÷ H1 新增在役 196 MW（366 − 170，內插）＝41.5（含預建，在建工程 7,836）；在役資產（毛額 − 在建）6,313 ÷ 366＝17.2（Q1／Q2 2026 6-K 現金流量表與 PP&E 附註 [Interested-party]；MW 為 [Derived] 內插） | E9: 41.5 | F9: =IF(ISNUMBER(E9),E9/C9-1,"不適用") -> -0.075929637 | G9: 未找到有證據的機制：H1 數字混入預建（在建工程）、在役 MW 為內插、部分站點為租賃（營業租賃負債 1,625），無法分離每 MW 單價；v18.0 的 GB300 值下降後差距縮小到門檻內（−8%），不再需要機制；模型 FY26 全年 CapEx 對公司指引 20–25 的口徑（應計 vs 現金、預建）仍不明。 | H9: 不調整（維持 Tokenomics 44.91）；公司實際列敏感度：每 MW 建置成本 × 0.92（41.5 ÷ 44.9）基準目標價 $23.5（v0.3 的 × 0.83 口徑，同一新快照下為 $25.5） | I9: 44.91／47.58／50.26（依新增世代組合加權） | J9: [Derived]
A10: 驗證｜GPU 折舊年限 | B10: IF_DeprLifeIT 6 年 | C10: 6 | D10: 伺服器與網通設備 5 年（2026-01-01 起由 4 年延長）（Q1／Q2 2026 6-K 附註（會計估計變更）[Interested-party]） | E10: 5 | F10: =IF(ISNUMBER(E10),E10/C10-1,"不適用") -> -0.16666667 | G10: 找到：公司會計政策（6-K 附註）。 | H10: 已在模型：GPU 經濟壽命 5 年（defaults.gpuLife）；會計政策，不回到 Tokenomics 值 | I10: 5 年 | J10: [Interested-party]
A11: 驗證｜電費 | B11: IF_PowerCost 0.67 US$m/MW·年（0.08 $/kWh、平均用電 80%、PUE 1.2） | C11: 0.67 | D11: 電力與能源最低承諾 2027 年 541.8（對應 MW 未揭露）（Q2 2026 6-K 附註 11 [Interested-party]） | E11: 找不到 | F11: =IF(ISNUMBER(E11),E11/C11-1,"不適用") -> 不適用 | G11: 無法對照：承諾金額對應的 MW 與電價未揭露（找不到）。 | H11: 不調整（模型以 EBITDA 率路徑涵蓋） | I11: — | J11: —

Sheet 資產負債_既有債務
A1: 債務明細 — 季報（2026-06-30）逐筆＋存量利息推導
A2: 有效利率為現金票息口徑（可轉債＝票息 ÷ 到期累積倍數，本金以到期累積本金計）。本頁算出的存量利息連回『輸入』頁，再進入支出與資金頁
A4: 工具 | B4: 類別 | C4: 到期 | D4: 有效利率 | E4: 6/30 本金 | F4: 年化利息 | I4: 備註
A5: 其他借款（流動） | B5: 追索 | C5: 2026-12 | D5: 0 | E5: 0.0467 | F5: =D5*E5 -> 0 | I5: 資產負債表 Debt, current；附註未逐項拆解 [Interested-party]
A6: 合計（6/30） | E6: =SUM(E5:E5) -> 0.0467 | F6: =SUM(F5:F5) -> 0 | I6: 應等於最新季報本金合計 10.0885（company.json → latestQuarter.debtPrincipal）
A7: 加權有效利率 | D7: =F6/E6 -> 0 | I7: ＝年化利息 ÷ 本金（company.json → debt.instruments 的有效利率）
A9: 評價日後新發可轉債 | D9: 0 | E9: 0 | F9: =D9*E9 -> 0 | I9: company.json → debt.convertible（期後新發；不在五期還本表內，只計利息）
A11: 可轉債逐檔（若轉換法：有效轉換價 < 判斷價 → 視為轉股，不計利息與還本）
A12: 可轉債 | B12: 到期 | C12: 票息 | D12: 原始本金 | E12: 到期累積倍數 | F12: 轉換價 | G12: 到期所屬模型期 | I12: 備註
A13: 2.00% 2029（2025-06） | B13: 2029-06 | C13: 0.02 | D13: 0.0875 | E13: 1.2 | F13: 51.45 | G13: 3 | I13: 2025-06 發行；原始 500 已轉換 12.5、以股換債 400 → 87.5；轉換率 19.4363 股／$1,000 [Verified 20-F／Interested-party 2026-08]
A14: 3.00% 2031（2025-06） | B14: 2031-06 | C14: 0.03 | D14: 0.0875 | E14: 1.25 | F14: 51.45 | G14: 5 | I14: 同上；原始 500 → 87.5 [Verified／Interested-party]
A15: 1.00% 2030（2025-09） | B15: 2030-09 | C15: 0.01 | D15: 1.58125 | E15: 1.15 | F15: 138.75 | G15: 4 | I15: 基本 1,375＋超額配售 206.25；轉換率 7.2072 [Verified 20-F]
A16: 2.75% 2032（2025-09） | B16: 2032-09 | C16: 0.0275 | D16: 1.58125 | E16: 1.15 | F16: 138.75 | G16: 5 | I16: 同上 [Verified 20-F]
A17: 1.25% 2031（2026-03） | B17: 2031-03 | C17: 0.0125 | D17: 2.5875 | E17: 1.2 | F17: 183.22 | G17: 5 | I17: 轉換率 5.4579 [Interested-party Q2 6-K]
A18: 2.625% 2033（2026-03） | B18: 2033-03 | C18: 0.02625 | D18: 1.75 | E18: 1.2 | F18: 180.31 | G18: 5 | I18: 轉換率 5.546 [Interested-party Q2 6-K]
A19: 0.50% 2030（2026-08） | B19: 2030-02 | C19: 0.005 | D19: 3.45 | E19: 1.1 | F19: 313.46 | G19: 4 | I19: 2026-08-24 交割；轉換率 3.1902；有效轉換價（含累積）約 $344.81 [Interested-party]
A20: 4.50% 2034（2026-08） | B20: 2034-02 | C20: 0.045 | D20: 2.3 | E20: 1.25 | F20: 324.65 | G20: 5 | I20: 2026-08-24 交割；轉換率 3.0802；有效轉換價約 $405.82 [Interested-party]
I21: 到期所屬模型期：0＝首期 … 4＝末期、5＝模型期後（建置時依期末日推算）
A23: 可轉債（推導） | C23: 到期本金 | D23: 若轉換股數 | E23: 有效轉換價 | F23: 融資分類 | G23: 評價第一輪 | H23: 評價第二輪 | I23: 說明
A24: =A13 -> 2.00% 2029（2025-06） | C24: =D13*E13 -> 0.105 | D24: =D13/F13 -> 0.0017006803 | E24: =F13*E13 -> 61.74 | F24: =IF(E24<輸入與假設!$C$104,1,0) -> 1 | G24: =IF(E24<輸入與假設!$C$125,1,0) -> 1 | H24: =IF(E24<評價_DCF與目標價!$C$64,1,0) -> 0
A25: =A14 -> 3.00% 2031（2025-06） | C25: =D14*E14 -> 0.109375 | D25: =D14/F14 -> 0.0017006803 | E25: =F14*E14 -> 64.3125 | F25: =IF(E25<輸入與假設!$C$104,1,0) -> 1 | G25: =IF(E25<輸入與假設!$C$125,1,0) -> 1 | H25: =IF(E25<評價_DCF與目標價!$C$64,1,0) -> 0
A26: =A15 -> 1.00% 2030（2025-09） | C26: =D15*E15 -> 1.8184375 | D26: =D15/F15 -> 0.011396396 | E26: =F15*E15 -> 159.5625 | F26: =IF(E26<輸入與假設!$C$104,1,0) -> 1 | G26: =IF(E26<輸入與假設!$C$125,1,0) -> 1 | H26: =IF(E26<評價_DCF與目標價!$C$64,1,0) -> 0
A27: =A16 -> 2.75% 2032（2025-09） | C27: =D16*E16 -> 1.8184375 | D27: =D16/F16 -> 0.011396396 | E27: =F16*E16 -> 159.5625 | F27: =IF(E27<輸入與假設!$C$104,1,0) -> 1 | G27: =IF(E27<輸入與假設!$C$125,1,0) -> 1 | H27: =IF(E27<評價_DCF與目標價!$C$64,1,0) -> 0
A28: =A17 -> 1.25% 2031（2026-03） | C28: =D17*E17 -> 3.105 | D28: =D17/F17 -> 0.014122367 | E28: =F17*E17 -> 219.864 | F28: =IF(E28<輸入與假設!$C$104,1,0) -> 1 | G28: =IF(E28<輸入與假設!$C$125,1,0) -> 1 | H28: =IF(E28<評價_DCF與目標價!$C$64,1,0) -> 0
A29: =A18 -> 2.625% 2033（2026-03） | C29: =D18*E18 -> 2.1 | D29: =D18/F18 -> 0.0097055072 | E29: =F18*E18 -> 216.372 | F29: =IF(E29<輸入與假設!$C$104,1,0) -> 1 | G29: =IF(E29<輸入與假設!$C$125,1,0) -> 1 | H29: =IF(E29<評價_DCF與目標價!$C$64,1,0) -> 0
A30: =A19 -> 0.50% 2030（2026-08） | C30: =D19*E19 -> 3.795 | D30: =D19/F19 -> 0.011006189 | E30: =F19*E19 -> 344.806 | F30: =IF(E30<輸入與假設!$C$104,1,0) -> 0 | G30: =IF(E30<輸入與假設!$C$125,1,0) -> 0 | H30: =IF(E30<評價_DCF與目標價!$C$64,1,0) -> 0
A31: =A20 -> 4.50% 2034（2026-08） | C31: =D20*E20 -> 2.875 | D31: =D20/F20 -> 0.0070845526 | E31: =F20*E20 -> 405.8125 | F31: =IF(E31<輸入與假設!$C$104,1,0) -> 0 | G31: =IF(E31<輸入與假設!$C$125,1,0) -> 0 | H31: =IF(E31<評價_DCF與目標價!$C$64,1,0) -> 0
A32: 合計 | C32: =SUM(C24:C31) -> 15.72625 | D32: =SUM(D24:D31) -> 0.068112769 | I32: 分類 1＝轉股（若轉換法）、0＝債務。融資分類判斷價＝股權發行價；評價第一輪＝現價；第二輪＝MIN(現價, 第一輪加權目標價)
A34: 存量利息推導（本金依季報到期表遞減）
A35: 項目 | B35: 單位 | C35: FY26 | D35: FY27 | E35: FY28 | F35: FY29 | G35: FY30 | I35: 公式／來源說明
A36: 期初本金 | B36: US$bn | C36: =E6 -> 0.0467 | D36: =C38 -> 0 | E36: =D38 -> 0 | F36: =E38 -> 0 | G36: =F38 -> 0 | I36: FY26 期初為 6/30 本金（模型期起點）
A37: 排程還本 | B37: US$bn | C37: =輸入與假設!C$120 -> 0.0467 | D37: =輸入與假設!D$120 -> 0 | E37: =輸入與假設!E$120 -> 0 | F37: =輸入與假設!F$120 -> 0 | G37: =輸入與假設!G$120 -> 0 | I37: 季報到期表
A38: 期末本金 | B38: US$bn | C38: =C36-C37 -> 0 | D38: =D36-D37 -> 0 | E38: =E36-E37 -> 0 | F38: =F36-F37 -> 0 | G38: =G36-G37 -> 0
A39: 平均本金 | B39: US$bn | C39: =(C36+C38)/2 -> 0.02335 | D39: =(D36+D38)/2 -> 0 | E39: =(E36+E38)/2 -> 0 | F39: =(F36+F38)/2 -> 0 | G39: =(G36+G38)/2 -> 0
A40: 存量債務利息 | B40: US$bn | C40: =C39*資產負債_既有債務!$D$7*輸入與假設!C$37 -> 0 | D40: =D39*資產負債_既有債務!$D$7*輸入與假設!D$37 -> 0 | E40: =E39*資產負債_既有債務!$D$7*輸入與假設!E$37 -> 0 | F40: =F39*資產負債_既有債務!$D$7*輸入與假設!F$37 -> 0 | G40: =G39*資產負債_既有債務!$D$7*輸入與假設!G$37 -> 0 | I40: ＝平均本金×加權有效利率×期間長度。限制：假設利率組合不變；可轉債折價攤銷（非現金）不計
A41: 期後新發可轉債利息 | B41: US$bn | C41: =資產負債_既有債務!$F$9*輸入與假設!C$37 -> 0 | D41: =資產負債_既有債務!$F$9*輸入與假設!D$37 -> 0 | E41: =資產負債_既有債務!$F$9*輸入與假設!E$37 -> 0 | F41: =資產負債_既有債務!$F$9*輸入與假設!F$37 -> 0 | G41: =資產負債_既有債務!$F$9*輸入與假設!G$37 -> 0
A42: 可轉債到期還本（債務處理） | B42: US$bn | C42: =IF(輸入與假設!$C$100=1,SUMPRODUCT((1-資產負債_既有債務!$F$24:$F$31)*資產負債_既有債務!$C$24:$C$31*(資產負債_既有債務!$G$13:$G$20=0)),0) -> 0 | D42: =IF(輸入與假設!$C$100=1,SUMPRODUCT((1-資產負債_既有債務!$F$24:$F$31)*資產負債_既有債務!$C$24:$C$31*(資產負債_既有債務!$G$13:$G$20=1)),0) -> 0 | E42: =IF(輸入與假設!$C$100=1,SUMPRODUCT((1-資產負債_既有債務!$F$24:$F$31)*資產負債_既有債務!$C$24:$C$31*(資產負債_既有債務!$G$13:$G$20=2)),0) -> 0 | F42: =IF(輸入與假設!$C$100=1,SUMPRODUCT((1-資產負債_既有債務!$F$24:$F$31)*資產負債_既有債務!$C$24:$C$31*(資產負債_既有債務!$G$13:$G$20=3)),0) -> 0 | G42: =IF(輸入與假設!$C$100=1,SUMPRODUCT((1-資產負債_既有債務!$F$24:$F$31)*資產負債_既有債務!$C$24:$C$31*(資產負債_既有債務!$G$13:$G$20=4)),0) -> 3.795 | I42: 融資分類為債務的可轉債，到期當期以到期累積本金現金還本
A43: 可轉債期末餘額（債務處理） | B43: US$bn | C43: =IF(輸入與假設!$C$100=1,SUMPRODUCT((1-資產負債_既有債務!$F$24:$F$31)*資產負債_既有債務!$C$24:$C$31*(資產負債_既有債務!$G$13:$G$20>0)),SUMPRODUCT((1-資產負債_既有債務!$F$24:$F$31)*資產負債_既有債務!$C$24:$C$31)) -> 6.67 | D43: =IF(輸入與假設!$C$100=1,SUMPRODUCT((1-資產負債_既有債務!$F$24:$F$31)*資產負債_既有債務!$C$24:$C$31*(資產負債_既有債務!$G$13:$G$20>1)),SUMPRODUCT((1-資產負債_既有債務!$F$24:$F$31)*資產負債_既有債務!$C$24:$C$31)) -> 6.67 | E43: =IF(輸入與假設!$C$100=1,SUMPRODUCT((1-資產負債_既有債務!$F$24:$F$31)*資產負債_既有債務!$C$24:$C$31*(資產負債_既有債務!$G$13:$G$20>2)),SUMPRODUCT((1-資產負債_既有債務!$F$24:$F$31)*資產負債_既有債務!$C$24:$C$31)) -> 6.67 | F43: =IF(輸入與假設!$C$100=1,SUMPRODUCT((1-資產負債_既有債務!$F$24:$F$31)*資產負債_既有債務!$C$24:$C$31*(資產負債_既有債務!$G$13:$G$20>3)),SUMPRODUCT((1-資產負債_既有債務!$F$24:$F$31)*資產負債_既有債務!$C$24:$C$31)) -> 6.67 | G43: =IF(輸入與假設!$C$100=1,SUMPRODUCT((1-資產負債_既有債務!$F$24:$F$31)*資產負債_既有債務!$C$24:$C$31*(資產負債_既有債務!$G$13:$G$20>4)),SUMPRODUCT((1-資產負債_既有債務!$F$24:$F$31)*資產負債_既有債務!$C$24:$C$31)) -> 2.875 | I43: 到期累積本金；關閉攤還時維持全額
A44: 可轉債票息（債務處理） | B44: US$bn | C44: =IF(輸入與假設!$C$100=1,SUMPRODUCT((1-資產負債_既有債務!$F$24:$F$31)*資產負債_既有債務!$D$13:$D$20*資產負債_既有債務!$C$13:$C$20*((資產負債_既有債務!$G$13:$G$20>0)+0.5*(資產負債_既有債務!$G$13:$G$20=0))),SUMPRODUCT((1-資產負債_既有債務!$F$24:$F$31)*資產負債_既有債務!$D$13:$D$20*資產負債_既有債務!$C$13:$C$20))*輸入與假設!C$37 -> 0.060375 | D44: =IF(輸入與假設!$C$100=1,SUMPRODUCT((1-資產負債_既有債務!$F$24:$F$31)*資產負債_既有債務!$D$13:$D$20*資產負債_既有債務!$C$13:$C$20*((資產負債_既有債務!$G$13:$G$20>1)+0.5*(資產負債_既有債務!$G$13:$G$20=1))),SUMPRODUCT((1-資產負債_既有債務!$F$24:$F$31)*資產負債_既有債務!$D$13:$D$20*資產負債_既有債務!$C$13:$C$20))*輸入與假設!D$37 -> 0.12075 | E44: =IF(輸入與假設!$C$100=1,SUMPRODUCT((1-資產負債_既有債務!$F$24:$F$31)*資產負債_既有債務!$D$13:$D$20*資產負債_既有債務!$C$13:$C$20*((資產負債_既有債務!$G$13:$G$20>2)+0.5*(資產負債_既有債務!$G$13:$G$20=2))),SUMPRODUCT((1-資產負債_既有債務!$F$24:$F$31)*資產負債_既有債務!$D$13:$D$20*資產負債_既有債務!$C$13:$C$20))*輸入與假設!E$37 -> 0.12075 | F44: =IF(輸入與假設!$C$100=1,SUMPRODUCT((1-資產負債_既有債務!$F$24:$F$31)*資產負債_既有債務!$D$13:$D$20*資產負債_既有債務!$C$13:$C$20*((資產負債_既有債務!$G$13:$G$20>3)+0.5*(資產負債_既有債務!$G$13:$G$20=3))),SUMPRODUCT((1-資產負債_既有債務!$F$24:$F$31)*資產負債_既有債務!$D$13:$D$20*資產負債_既有債務!$C$13:$C$20))*輸入與假設!F$37 -> 0.12075 | G44: =IF(輸入與假設!$C$100=1,SUMPRODUCT((1-資產負債_既有債務!$F$24:$F$31)*資產負債_既有債務!$D$13:$D$20*資產負債_既有債務!$C$13:$C$20*((資產負債_既有債務!$G$13:$G$20>4)+0.5*(資產負債_既有債務!$G$13:$G$20=4))),SUMPRODUCT((1-資產負債_既有債務!$F$24:$F$31)*資產負債_既有債務!$D$13:$D$20*資產負債_既有債務!$C$13:$C$20))*輸入與假設!G$37 -> 0.112125 | I44: ＝原始本金 × 票息 × 期間長度；到期當期計半期
A45: FY26 新增借款利息校準 | B45: US$bn | C45: =0 -> 0 | D45: =0 -> 0 | E45: =0 -> 0 | F45: =0 -> 0 | G45: =0 -> 0 | I45: 讓首期模型利息對上公司季度利息指引的校準值（company.json → defaults.intCal）；無指引時為 0
A46: 存量利息合計（連回輸入頁） | B46: US$bn | C46: =C40+C41+C44+C45 -> 0.060375 | D46: =D40+D41+D44+D45 -> 0.12075 | E46: =E40+E41+E44+E45 -> 0.12075 | F46: =F40+F41+F44+F45 -> 0.12075 | G46: =G40+G41+G44+G45 -> 0.112125 | I46: ＝存量債務利息＋期後新發可轉債利息＋可轉債票息＋首期校準

Sheet 資產負債_新債與新股
A1: 新債與新股（類資產負債表：現金、債務、股本、槓桿）
A2: 全部為連結公式。FY26 欄的現金自 2026-06-30 起算（模型期），與 HTML『資產與負債 → 新債與新股』同口徑
A4: 項目 | B4: 單位 | C4: FY26 | D4: FY27 | E4: FY28 | F4: FY29 | G4: FY30 | I4: 公式／來源說明
A5: 現金
A6: 期初現金 | B6: US$bn | C6: =輸入與假設!$C$95 -> 8.0421 | D6: =各期收支!C47 -> 2.1798696 | E6: =各期收支!D47 -> 2 | F6: =各期收支!E47 -> 2 | G6: =各期收支!F47 -> 2 | I6: FY26＝6/30 現金（模型期起點）
A7: 營運收支淨額（含期後股權／可轉債，不含瀑布） | B7: US$bn | C7: =各期收支!C83-輸入與假設!$C$95 -> -5.8622304 | D7: =各期收支!D83-各期收支!C83 -> -18.281756 | E7: =各期收支!E83-各期收支!D83 -> -18.024435 | F7: =各期收支!F83-各期收支!E83 -> -16.37366 | G7: =各期收支!G83-各期收支!F83 -> -27.299822 | I7: ＝融資前累積現金的當期變動；負值即當期外部資金需求
A8: ＋ 瀑布：新債（額度＋資產層） | B8: US$bn | C8: =各期收支!C66 -> 0 | D8: =各期收支!D66 -> 7.014069 | E8: =各期收支!E66 -> 0 | F8: =各期收支!F66 -> 0 | G8: =各期收支!G66 -> 0
A9: ＋ 瀑布：可轉債 | B9: US$bn | C9: =各期收支!C69 -> 0 | D9: =各期收支!D69 -> 5 | E9: =各期收支!E69 -> 5 | F9: =各期收支!F69 -> 5 | G9: =各期收支!G69 -> 5
A10: ＋ 瀑布：高息債 | B10: US$bn | C10: =各期收支!C73 -> 0 | D10: =各期收支!D73 -> 0 | E10: =各期收支!E73 -> 0 | F10: =各期收支!F73 -> 0 | G10: =各期收支!G73 -> 8.7997338
A11: ＋ 瀑布：股權募資 | B11: US$bn | C11: =各期收支!C72 -> 0 | D11: =各期收支!D72 -> 6.6487317 | E11: =各期收支!E72 -> 13.69035 | F11: =各期收支!F72 -> 12.144574 | G11: =各期收支!G72 -> 15.431971
A12: − 新融資利息（新債＋可轉債＋高息債） | B12: US$bn | C12: =-各期收支!C74 -> 0 | D12: =-各期收支!D74 -> -0.56091448 | E12: =-各期收支!E74 -> -0.66591448 | F12: =-各期收支!F74 -> -0.77091449 | G12: =-各期收支!G74 -> -1.9318825
A13: 期末現金 | B13: US$bn | C13: =SUM(C6:C12) -> 2.1798696 | D13: =SUM(D6:D12) -> 2 | E13: =SUM(E6:E12) -> 2 | F13: =SUM(F6:F12) -> 2 | G13: =SUM(G6:G12) -> 2 | I13: 應等於『各期收支』期末累積現金（見下列驗算）
A14: 驗算：與各期收支期末現金差異 | B14: US$bn | C14: =C13-各期收支!C47 -> 0 | D14: =D13-各期收支!D47 -> 0 | E14: =E13-各期收支!E47 -> 0 | F14: =F13-各期收支!F47 -> 0 | G14: =G13-各期收支!G47 -> 0 | I14: 應為 0
A15: 債務
A16: 既有債務期初（季報本金） | B16: US$bn | C16: =資產負債_既有債務!$E$6+SUMPRODUCT((1-資產負債_既有債務!$F$24:$F$31)*資產負債_既有債務!$C$24:$C$31) -> 6.7167 | D16: =C18 -> 6.67 | E16: =D18 -> 6.67 | F16: =E18 -> 6.67 | G16: =F18 -> 6.67 | I16: FY26＝其他借款＋債務處理可轉債到期本金（轉股處理者不列）
A17: − 排程還本（模型期） | B17: US$bn | C17: =-IF(輸入與假設!$C$100=1,輸入與假設!C$120,0)-資產負債_既有債務!C42 -> -0.0467 | D17: =-IF(輸入與假設!$C$100=1,輸入與假設!D$120,0)-資產負債_既有債務!D42 -> 0 | E17: =-IF(輸入與假設!$C$100=1,輸入與假設!E$120,0)-資產負債_既有債務!E42 -> 0 | F17: =-IF(輸入與假設!$C$100=1,輸入與假設!F$120,0)-資產負債_既有債務!F42 -> 0 | G17: =-IF(輸入與假設!$C$100=1,輸入與假設!G$120,0)-資產負債_既有債務!G42 -> -3.795
A18: 既有債務期末 | B18: US$bn | C18: =各期收支!C62-0 -> 6.67 | D18: =各期收支!D62-0 -> 6.67 | E18: =各期收支!E62-0 -> 6.67 | F18: =各期收支!F62-0 -> 6.67 | G18: =各期收支!G62-0 -> 2.875 | I18: ＝依到期表遞減（關閉攤還時維持期初）
A19: ＋ 期後新發可轉債 | B19: US$bn | C19: =0 -> 0 | D19: =0 -> 0 | E19: =0 -> 0 | F19: =0 -> 0 | G19: =0 -> 0
A20: ＋ 瀑布新債餘額 | B20: US$bn | C20: =各期收支!C78 -> 0 | D20: =各期收支!D78 -> 7.014069 | E20: =各期收支!E78 -> 7.014069 | F20: =各期收支!F78 -> 7.014069 | G20: =各期收支!G78 -> 7.014069
A21: ＋ 瀑布可轉債餘額 | B21: US$bn | C21: =各期收支!C81 -> 0 | D21: =各期收支!D81 -> 5 | E21: =各期收支!E81 -> 10 | F21: =各期收支!F81 -> 15 | G21: =各期收支!G81 -> 20
A22: ＋ 高息債餘額 | B22: US$bn | C22: =各期收支!C80 -> 0 | D22: =各期收支!D80 -> 0 | E22: =各期收支!E80 -> 0 | F22: =各期收支!F80 -> 0 | G22: =各期收支!G80 -> 8.7997338
A23: 總債務 | B23: US$bn | C23: =SUM(C18:C22) -> 6.67 | D23: =SUM(D18:D22) -> 18.684069 | E23: =SUM(E18:E22) -> 23.684069 | F23: =SUM(F18:F22) -> 28.684069 | G23: =SUM(G18:G22) -> 38.688803 | I23: 應等於『各期收支』期末總債務
A24: 淨負債（總債務 − 期末現金） | B24: US$bn | C24: =C23-C13 -> 4.4901304 | D24: =D23-D13 -> 16.684069 | E24: =E23-E13 -> 21.684069 | F24: =F23-F13 -> 26.684069 | G24: =G23-G13 -> 36.688803
A25: 股本
A26: 基礎股數（含 ATM 上限、SBC 稀釋） | B26: bn | C26: =損益!C20 -> 0.3193 | D26: =損益!D20 -> 0.322493 | E26: =損益!E20 -> 0.32571793 | F26: =損益!F20 -> 0.32897511 | G26: =損益!G20 -> 0.33226486
A27: ＋ 本期新股 | B27: bn | C27: =各期收支!C76 -> 0 | D27: =各期收支!D76 -> 0.029565292 | E27: =各期收支!E76 -> 0.060877655 | F27: =各期收支!F76 -> 0.054003968 | G27: =各期收支!G76 -> 0.068622222
A28: 總股數（期末） | B28: bn | C28: =損益!C21 -> 0.3193 | D28: =損益!D21 -> 0.35205829 | E28: =損益!E21 -> 0.41616088 | F28: =損益!F21 -> 0.47342202 | G28: =損益!G21 -> 0.545334 | I28: ＝基礎股數＋累計新股
A29: 槓桿
A30: 期末 backlog | B30: US$bn | C30: =各期收支!C61 -> 34.116446 | D30: =各期收支!D61 -> 27.368138 | E30: =各期收支!E61 -> 32.278053 | F30: =各期收支!F61 -> 32.379654 | G30: =各期收支!G61 -> 27.928125
A31: 債務上限（債務／backlog × 期末 backlog） | B31: US$bn | C31: =各期收支!C63 -> 17.058223 | D31: =各期收支!D63 -> 13.684069 | E31: =各期收支!E63 -> 16.139026 | F31: =各期收支!F63 -> 16.189827 | G31: =各期收支!G63 -> 13.964062
A32: 總債務 ÷ 期末 backlog | B32: x | C32: =C23/MAX(0.01,C30) -> 0.19550688 | D32: =D23/MAX(0.01,D30) -> 0.6826942 | E32: =E23/MAX(0.01,E30) -> 0.73375148 | F32: =F23/MAX(0.01,F30) -> 0.88586705 | G32: =G23/MAX(0.01,G30) -> 1.385299 | I32: 高息債不受 backlog 上限約束
A33: 總債務 ÷ EBITDA（年化） | B33: x | C33: =C23/MAX(0.01,損益!C19/輸入與假設!C$37) -> 5.7398551 | D33: =D23/MAX(0.01,損益!D19/輸入與假設!D$37) -> 6.7008224 | E33: =E23/MAX(0.01,損益!E19/輸入與假設!E$37) -> 3.783952 | F33: =F23/MAX(0.01,損益!F19/輸入與假設!F$37) -> 2.974937 | G33: =G23/MAX(0.01,損益!G19/輸入與假設!G$37) -> 3.1649227 | I33: FY26 模型期 EBITDA 以半年×2 年化

Sheet 資產負債_租賃承諾
A1: 租賃與承諾 — 季報（2026-06-30）原始揭露
A2: 本頁為硬編碼的申報數字（藍字），支出與資金頁的租金與還本列由此而來
A4: 在帳租賃到期表（未折現）
A5: 項目 | B5: 單位 | C5: 2026 下半 | D5: 2027 | E5: 2028 | F5: 2029 | G5: 2030 | H5: 其後
A6: 營業租賃付款 | B6: US$bn | C6: 0.0916 | D6: 0.2352 | E6: 0.2342 | F6: 0.2414 | G6: 0.2427 | H6: 1.13
A7: 融資租賃付款 | B7: US$bn | C7: 0 | D7: 0 | E7: 0 | F7: 0 | G7: 0 | H7: 0
A8: 合計（＝支出頁「在帳現金租金」） | C8: =SUM(C6:C7) -> 0.0916 | D8: =SUM(D6:D7) -> 0.2352 | E8: =SUM(E6:E7) -> 0.2342 | F8: =SUM(F6:F7) -> 0.2414 | G8: =SUM(G6:G7) -> 0.2427 | H8: =SUM(H6:H7) -> 1.13 | I8: 營業租賃負債現值 16.319、融資租賃 0.221；加權剩餘租期 12 年、折現率 10% [Verified]
A10: 債務本金到期表
A11: 項目 | B11: 單位 | C11: 2026 下半 | D11: 2027 | E11: 2028 | F11: 2029 | G11: 2030 | H11: 其後
A12: 本金（＝支出頁「排程還本」） | B12: US$bn | C12: 0.0467 | D12: 0 | E12: 0 | F12: 0 | G12: 0 | H12: 0 | I12: 其他借款到期表（company.json → debt.amortization）；可轉債到期還本依融資分類另計，見『資產負債_既有債務』逐檔表
A13: 合計 | C13: =SUM(C12:H12) -> 0.0467
A15: 表外與契約性承諾（未入表）
A16: 項目 | B16: 單位 | C16: 金額 | D16: 時程 | E16: 入表？ | F16: 模型位置
A17: 未起租租賃（未折現） | B17: US$bn | C17: 12.0541 | D17: 季報揭露之已簽約未起租租賃 | E17: 否 | F17: 表外現金租金
A18: 單站按造價計租，上限 | B18: US$bn | C18: 0 | D18: 無此類揭露時為 0 | E18: 否 | F18: 表外現金租金
A19: 未動用信用額度 | B19: US$bn | C19: 0.775 | D19: company.json → defaults.facility（評價日後簽約的資產擔保定期貸款） | E19: 否（來源） | F19: 瀑布：未動用額度
A20: 已揭露金額之承諾合計（未起租＋單站上限） | C20: =C17+C18 -> 12.0541
A21: 模型表外租金五期合計 | C21: =SUM(各期收支!C14:G14) -> 2.7791233
A22: 模型表外租金尾端（FY30×12 年） | C22: =各期收支!G14*12 -> 9.0249878
A23: 模型路徑合計 ÷ 已承諾（≥0.8 為合理） | C23: =(C21+C22)/C20 -> 0.97926109 | I23: 擴張路徑所需新租約多數尚未簽署，路徑高於已承諾屬假設而非錯誤

Sheet 損益
A1: 損益（類損益表）— 與資金模型同一組收入
A2: 算力收入、Cash CapEx、利息皆由前面分頁連結而來；改資金假設，此頁會跟著動
A4: 項目 | B4: 單位 | C4: FY26 | D4: FY27 | E4: FY28 | F4: FY29 | G4: FY30 | I4: 公式／來源說明
A5: 損益表
A6: 算力收入 | B6: US$bn | C6: =運營_產能與收入!C25 -> 1.3581994 | D6: =運營_產能與收入!D25 -> 5.9751652 | E6: =運營_產能與收入!E25 -> 13.139778 | F6: =運營_產能與收入!F25 -> 20.322827 | G6: =運營_產能與收入!G25 -> 26.00904 | I6: ＝RPO 轉換＋新簽約
A7: 非算力服務 | B7: US$bn | C7: =輸入與假設!C$46 -> 0 | D7: =輸入與假設!D$46 -> 0 | E7: =輸入與假設!E$46 -> 0 | F7: =輸入與假設!F$46 -> 0 | G7: =輸入與假設!G$46 -> 0
A8: 總營收 | B8: US$bn | C8: =C6+C7 -> 1.3581994 | D8: =D6+D7 -> 5.9751652 | E8: =E6+E7 -> 13.139778 | F8: =F6+F7 -> 20.322827 | G8: =G6+G7 -> 26.00904
A9: EBITDA 率 | B9: % | C9: =輸入與假設!C$53 -> 0.497 | D9: =輸入與假設!D$53 -> 0.49025 | E9: =輸入與假設!E$53 -> 0.4835 | F9: =輸入與假設!F$53 -> 0.47675 | G9: =輸入與假設!G$53 -> 0.47
A10: 營業利益（EBIT） | B10: US$bn | C10: =C8*輸入與假設!C$53+輸入與假設!C$47-輸入與假設!C$92 -> -1.7297194 | D10: =D8*輸入與假設!D$53+輸入與假設!D$47-輸入與假設!D$92 -> -6.3844969 | E10: =E8*輸入與假設!E$53+輸入與假設!E$47-輸入與假設!E$92 -> -8.5883509 | F10: =F8*輸入與假設!F$53+輸入與假設!F$47-輸入與假設!F$92 -> -11.035263 | G10: =G8*輸入與假設!G$53+輸入與假設!G$47-輸入與假設!G$92 -> -14.282659 | I10: ＝營收×EBITDA 率＋其他事業 EBITDA − 車隊 D&A
A11: 利息（含瀑布新債） | B11: US$bn | C11: =各期收支!C20 -> 0.060375 | D11: =各期收支!D20 -> 0.68166448 | E11: =各期收支!E20 -> 0.78666448 | F11: =各期收支!F20 -> 0.89166448 | G11: =各期收支!G20 -> 2.0440075
A12: 稅前損益 | B12: US$bn | C12: =C10-C11 -> -1.7900944 | D12: =D10-D11 -> -7.0661614 | E12: =E10-E11 -> -9.3750154 | F12: =F10-F11 -> -11.926927 | G12: =G10-G11 -> -16.326666
A13: NOL 期初餘額 | B13: US$bn | C13: =輸入與假設!$C$139 -> 0.8 | D13: =C15 -> 2.5900944 | E13: =D15 -> 9.6562558 | F13: =E15 -> 19.031271 | G13: =F15 -> 30.958198 | I13: 6/30 累積虧損約 0.8
A14: 本期動用 NOL | B14: US$bn | C14: =MIN(C13,MAX(0,C12)*輸入與假設!$C$140) -> 0 | D14: =MIN(D13,MAX(0,D12)*輸入與假設!$C$140) -> 0 | E14: =MIN(E13,MAX(0,E12)*輸入與假設!$C$140) -> 0 | F14: =MIN(F13,MAX(0,F12)*輸入與假設!$C$140) -> 0 | G14: =MIN(G13,MAX(0,G12)*輸入與假設!$C$140) -> 0 | I14: 美國規定：抵扣上限為應稅所得 50%
A15: NOL 期末餘額 | B15: US$bn | C15: =C13-C14+MAX(0,-C12) -> 2.5900944 | D15: =D13-D14+MAX(0,-D12) -> 9.6562558 | E15: =E13-E14+MAX(0,-E12) -> 19.031271 | F15: =F13-F14+MAX(0,-F12) -> 30.958198 | G15: =G13-G14+MAX(0,-G12) -> 47.284864
A16: 所得稅 | B16: US$bn | C16: =MAX(0,C12-C14)*輸入與假設!$C$138 -> 0 | D16: =MAX(0,D12-D14)*輸入與假設!$C$138 -> 0 | E16: =MAX(0,E12-E14)*輸入與假設!$C$138 -> 0 | F16: =MAX(0,F12-F14)*輸入與假設!$C$138 -> 0 | G16: =MAX(0,G12-G14)*輸入與假設!$C$138 -> 0 | I16: 虧損年不認列稅盾（與公司評價備抵一致）
A17: 淨利 | B17: US$bn | C17: =C12-C16 -> -1.7900944 | D17: =D12-D16 -> -7.0661614 | E17: =E12-E16 -> -9.3750154 | F17: =F12-F16 -> -11.926927 | G17: =G12-G16 -> -16.326666
A18: D&A | B18: US$bn | C18: =輸入與假設!C$92 -> 2.3107445 | D18: =輸入與假設!D$92 -> 9.1728217 | E18: =輸入與假設!E$92 -> 14.847434 | F18: =輸入與假設!F$92 -> 20.677171 | G18: =輸入與假設!G$92 -> 26.506907 | I18: 車隊折舊，見輸入頁
A19: EBITDA | B19: US$bn | C19: =C10+C18 -> 0.58102512 | D19: =D10+D18 -> 2.7883247 | E19: =E10+E18 -> 6.2590829 | F19: =F10+F18 -> 9.641908 | G19: =G10+G18 -> 12.224249
A20: 基礎股數（每年 +SBC 稀釋） | B20: bn | C20: =評價_DCF與目標價!$C$67 -> 0.3193 | D20: =C20*(1+輸入與假設!$C$148) -> 0.322493 | E20: =D20*(1+輸入與假設!$C$148) -> 0.32571793 | F20: =E20*(1+輸入與假設!$C$148) -> 0.32897511 | G20: =F20*(1+輸入與假設!$C$148) -> 0.33226486 | I20: FY26＝評價股數（含價內可轉債轉股，見『評價_DCF與目標價』可轉債區）；之後每年 ×(1＋股數年增)
A21: 股數（含瀑布新股） | B21: bn | C21: =C20+各期收支!C77 -> 0.3193 | D21: =D20+各期收支!D77 -> 0.35205829 | E21: =E20+各期收支!E77 -> 0.41616088 | F21: =F20+各期收支!F77 -> 0.47342202 | G21: =G20+各期收支!G77 -> 0.545334 | I21: ＝基礎股數＋累計瀑布新股
A22: 每股盈餘（EPS，模型期） | B22: US$ | C22: =C17/C21 -> -5.6063087 | D22: =D17/D21 -> -20.070998 | E22: =E17/E21 -> -22.527383 | F22: =F17/F21 -> -25.193013 | G22: =G17/G21 -> -29.938838 | I22: FY26 欄只含下半年；全年口徑見下方
A24: 損益表（全年口徑；FY26＝1H 實際＋下半年模型；與 HTML 損益簡表一致）
A25: 1H26 實際營收（已實現） | B25: US$bn | C25: =輸入與假設!$C$190 -> 0.9813 | D25: =0 -> 0 | E25: =0 -> 0 | F25: =0 -> 0 | G25: =0 -> 0
A26: 全年總營收 | B26: US$bn | C26: =C25+C8 -> 2.3394994 | D26: =D25+D8 -> 5.9751652 | E26: =E25+E8 -> 13.139778 | F26: =F25+F8 -> 20.322827 | G26: =G25+G8 -> 26.00904 | I26: FY26 可對照指引 3.0–3.4
A27: 營收 YoY | B27: % | C27: =C26/0.5298-1 -> 3.4158162 | D27: =D26/C26-1 -> 1.5540358 | E27: =E26/D26-1 -> 1.1990653 | F27: =F26/E26-1 -> 0.54666439 | G27: =G26/F26-1 -> 0.27979438 | I27: FY25 實際 0.5298
A28: 全年 GAAP 營業利益 | B28: US$bn | C28: =輸入與假設!$C$191+C10 -> -2.0336194 | D28: =D10 -> -6.3844969 | E28: =E10 -> -8.5883509 | F28: =F10 -> -11.035263 | G28: =G10 -> -14.282659
A29: 營利率 | B29: % | C29: =C28/C26 -> -0.86925406 | D29: =D28/D26 -> -1.0685055 | E29: =E28/E26 -> -0.65361459 | F29: =F28/F26 -> -0.54299839 | G29: =G28/G26 -> -0.54914208
A30: 全年 D&A | B30: US$bn | C30: =輸入與假設!$C$194+C18 -> 2.7824445 | D30: =D18 -> 9.1728217 | E30: =E18 -> 14.847434 | F30: =F18 -> 20.677171 | G30: =G18 -> 26.506907 | I30: 1H 實際 0.472
A31: 全年 EBITDA | B31: US$bn | C31: =C28+C30 -> 0.74882512 | D31: =D28+D30 -> 2.7883247 | E31: =E28+E30 -> 6.2590829 | F31: =F28+F30 -> 9.641908 | G31: =G28+G30 -> 12.224249
A32: 全年利息（含瀑布新債） | B32: US$bn | C32: =輸入與假設!$C$188+C11 -> 0.243175 | D32: =D11 -> 0.68166448 | E32: =E11 -> 0.78666448 | F32: =F11 -> 0.89166448 | G32: =G11 -> 2.0440075 | I32: FY27 起瀑布新債利息（9%）與新股同時影響 EPS
A33: 全年淨利 | B33: US$bn | C33: =輸入與假設!$C$192+C17 -> -1.3592944 | D33: =D17 -> -7.0661614 | E33: =E17 -> -9.3750154 | F33: =F17 -> -11.926927 | G33: =G17 -> -16.326666
A34: 淨利率 | B34: % | C34: =C33/C26 -> -0.58101932 | D34: =D33/D26 -> -1.1825885 | E34: =E33/E26 -> -0.71348352 | F34: =F33/F26 -> -0.58687341 | G34: =G33/G26 -> -0.62773043
A35: 全年 GAAP EPS | B35: US$ | C35: =輸入與假設!$C$196+C17/C21 -> -4.0063087 | D35: =D17/D21 -> -20.070998 | E35: =E17/E21 -> -22.527383 | F35: =F17/F21 -> -25.193013 | G35: =G17/G21 -> -29.938838 | I35: FY26＝1H 實際 EPS 1.60＋下半年淨利÷股數
A36: 全年 EPS（加回 SBC） | B36: US$ | C36: =輸入與假設!$C$197+(C17+輸入與假設!$C$149*輸入與假設!C$37)/C21 -> -3.2927384 | D36: =(D17+輸入與假設!$C$149*輸入與假設!D$37)/D21 -> -19.701741 | E36: =(E17+輸入與假設!$C$149*輸入與假設!E$37)/E21 -> -22.215004 | F36: =(F17+輸入與假設!$C$149*輸入與假設!F$37)/F21 -> -24.918416 | G36: =(G17+輸入與假設!$C$149*輸入與假設!G$37)/G21 -> -29.700452 | I36: ＝(淨利＋SBC)÷股數；NOL 狀態無現金稅，SBC 全額加回

Sheet 評價_DCF與目標價
A1: 評價 — DCF、EV/EBITDA、加權目標價
A2: 營收、營業利益、D&A、EBITDA、股數引用『損益』頁；Cash CapEx 與融資引用『各期收支』頁
A4: 項目 | B4: 單位 | C4: FY26 | D4: FY27 | E4: FY28 | F4: FY29 | G4: FY30 | I4: 公式／來源說明
A5: DCF（無槓桿自由現金流；起點為 2026-06-30）
A6: 現金 CapEx（2026-06-30 之後） | B6: US$bn | C6: =輸入與假設!C$91-各期收支!C8 -> 11.018272 | D6: =輸入與假設!D$91-各期收支!D8 -> 16.972424 | E6: =輸入與假設!E$91-各期收支!E8 -> 17.926441 | F6: =輸入與假設!F$91-各期收支!F8 -> 17.926441 | G6: =輸入與假設!G$91-各期收支!G8 -> 26.470021 | I6: DCF 起點為 6/30，故 FY26 欄只含 2H 的建置支出，不含 1H 已發生的 8.1303
A7: 比較基期營收 | B7: US$bn | C7: =0.5298 -> 0.5298 | D7: =0.9813+損益!C8 -> 2.3394994 | E7: =損益!D8 -> 5.9751652 | F7: =損益!E8 -> 13.139778 | G7: =損益!F8 -> 20.322827 | I7: FY25 實際 0.5298；FY27 基期＝1H 實際 0.9813＋FY26 模型期營收
A8: 預付認列（非現金營收，扣除） | B8: US$bn | C8: =各期收支!C10 -> 0.99586667 | D8: =各期收支!D10 -> 3.9589837 | E8: =各期收支!E10 -> 6.1809935 | F8: =各期收支!F10 -> 7.8614101 | G8: =各期收支!G10 -> 8.9816879 | I8: 營收中由合約負債轉入的部分已在預付時收現（預付流入已自現金 CapEx 抵減），UFCF 扣除以免重複（v0.1b）
A9: 營運資金變動 | B9: US$bn | C9: =輸入與假設!$C$141*MAX(0,損益!C8-C7) -> 0.016567989 | D9: =輸入與假設!$C$141*MAX(0,損益!D8-D7) -> 0.072713315 | E9: =輸入與假設!$C$141*MAX(0,損益!E8-E7) -> 0.14329227 | F9: =輸入與假設!$C$141*MAX(0,損益!F8-F7) -> 0.14366098 | G9: =輸入與假設!$C$141*MAX(0,損益!G8-G7) -> 0.11372426 | I9: 營收增量的 2%
A10: 無槓桿 NOL 期初 | B10: US$bn | C10: =輸入與假設!$C$139 -> 0.8 | D10: =C12 -> 2.5297194 | E10: =D12 -> 8.9142163 | F10: =E12 -> 17.502567 | G10: =F12 -> 28.53783 | I10: DCF 用無槓桿稅（利息不可抵稅，否則稅盾被計兩次：一次在 UFCF、一次在 WACC）
A11: 本期動用（無槓桿） | B11: US$bn | C11: =MIN(C10,MAX(0,損益!C10)*輸入與假設!$C$140) -> 0 | D11: =MIN(D10,MAX(0,損益!D10)*輸入與假設!$C$140) -> 0 | E11: =MIN(E10,MAX(0,損益!E10)*輸入與假設!$C$140) -> 0 | F11: =MIN(F10,MAX(0,損益!F10)*輸入與假設!$C$140) -> 0 | G11: =MIN(G10,MAX(0,損益!G10)*輸入與假設!$C$140) -> 0
A12: 無槓桿 NOL 期末 | B12: US$bn | C12: =C10-C11+MAX(0,-損益!C10) -> 2.5297194 | D12: =D10-D11+MAX(0,-損益!D10) -> 8.9142163 | E12: =E10-E11+MAX(0,-損益!E10) -> 17.502567 | F12: =F10-F11+MAX(0,-損益!F10) -> 28.53783 | G12: =G10-G11+MAX(0,-損益!G10) -> 42.820488
A13: 無槓桿所得稅（DCF 用） | B13: US$bn | C13: =MAX(0,損益!C10-C11)*輸入與假設!$C$138 -> 0 | D13: =MAX(0,損益!D10-D11)*輸入與假設!$C$138 -> 0 | E13: =MAX(0,損益!E10-E11)*輸入與假設!$C$138 -> 0 | F13: =MAX(0,損益!F10-F11)*輸入與假設!$C$138 -> 0 | G13: =MAX(0,損益!G10-G11)*輸入與假設!$C$138 -> 0 | I13: 與損益表的所得稅不同：此處不扣利息，數字較高，這是 DCF 的正確口徑
A14: UFCF | B14: US$bn | C14: =損益!C10-C13+損益!C18-C6-C9-C8 -> -11.449682 | D14: =損益!D10-D13+損益!D18-D6-D9-D8 -> -18.215796 | E14: =損益!E10-E13+損益!E18-E6-E9-E8 -> -17.991644 | F14: =損益!F10-F13+損益!F18-F6-F9-F8 -> -16.289604 | G14: =損益!G10-G13+損益!G18-G6-G9-G8 -> -23.341184 | I14: ＝EBIT−無槓桿稅＋D&A−現金 CapEx（已扣客戶預付）−營運資金−預付認列。建置期全為負是正常的
A15: 折現期數 | B15: 年 | C15: =輸入與假設!$C$167 -> 0.5 | D15: =輸入與假設!$D$167 -> 1.5 | E15: =輸入與假設!$E$167 -> 2.5 | F15: =輸入與假設!$F$167 -> 3.5 | G15: =輸入與假設!$G$167 -> 4.5 | I15: 自 2026-06-30 起算；FY26 模型期（下半年）的現金流平均落在 0.5 年
A16: 折現因子 | C16: =1/(1+輸入與假設!$C$135)^C15 -> 0.949158 | D16: =1/(1+輸入與假設!$C$135)^D15 -> 0.85509729 | E16: =1/(1+輸入與假設!$C$135)^E15 -> 0.77035792 | F16: =1/(1+輸入與假設!$C$135)^F15 -> 0.69401615 | G16: =1/(1+輸入與假設!$C$135)^G15 -> 0.62523977
A17: UFCF 現值 | B17: US$bn | C17: =C14*C16 -> -10.867557 | D17: =D14*D16 -> -15.576278 | E17: =E14*E16 -> -13.860005 | F17: =F14*F16 -> -11.305248 | G17: =G14*G16 -> -14.593836
A19: 五期 UFCF 現值合計 | C19: =SUM(C17:G17) -> -66.202925 | I19: 建置期現金流現值
A20: 常態化 FCF（FY30） | C20: =損益!G10*(1-輸入與假設!$C$138)+損益!G18-損益!G18*輸入與假設!$C$137 -> -5.2963511 | I20: ＝EBIT×(1−稅)＋D&A−維持性 CapEx(D&A×比率)。不讓成長性 CapEx 偽裝成永續 FCF
A21: 終值（Gordon） | C21: =IF(OR(C30=1,C20<=0),0,C20*(1+輸入與假設!$C$136)/(輸入與假設!$C$135-輸入與假設!$C$136)) -> 0 | I21: ＝常態化 FCF×(1+g)÷(WACC−g)；常態化 FCF ≤ 0 時以 0 計（v0.2）
A22: 終值現值 | C22: =C21*G16 -> 0
A23: 企業價值 EV | C23: =C19+C22 -> -66.202925
A24: 減：淨負債 | C24: =-評價_DCF與目標價!$C$68 -> 0.4566 | I24: ＝評價淨負債（不含可轉債的淨負債＋債務處理可轉債到期本金＋調整項；見下方可轉債區）
A25: 股權價值 | C25: =C23+C24 -> -65.746325
A26: DCF 每股 | C26: =IF(C30=1,0,IF(輸入與假設!$C$151=2,C32,C31)) -> 0 | I26: 採用值：失效時為 0 且權重歸零；否則依「DCF 下限方式」取 0 截斷或選擇權
A27: 終值占 EV 比重 | C27: =C22/C23 -> 0 | I27: ="超過 "&IF(ROUND(ABS(輸入與假設!$C$176)*100,4)=INT(ROUND(ABS(輸入與假設!$C$176)*100,4)),TEXT(ROUND(ABS(輸入與假設!$C$176)*100,4),"0"),TEXT(ROUND(ABS(輸入與假設!$C$176)*100,4),"0.0"))&"%"&" 表示結論由終值假設決定，不由現金流決定" -> 超過 85% 表示結論由終值假設決定，不由現金流決定
A28: 新股募得現金（現值） | C28: =各期收支!C72/(1+輸入與假設!$C$135)^輸入與假設!$C$168+各期收支!D72/(1+輸入與假設!$C$135)^輸入與假設!$D$168+各期收支!E72/(1+輸入與假設!$C$135)^輸入與假設!$E$168+各期收支!F72/(1+輸入與假設!$C$135)^輸入與假設!$F$168+各期收支!G72/(1+輸入與假設!$C$135)^輸入與假設!$G$168 -> 38.082984 | I28: 期初到位，折現期數 0／0.5／1.5／2.5／3.5 年
A29: 融資後股數（含瀑布新股） | C29: =評價_DCF與目標價!$C$67+各期收支!G77 -> 0.53236914
A30: DCF 失效？（WACC ≤ g） | C30: =IF(輸入與假設!$C$135<=輸入與假設!$C$136,1,0) -> 0 | I30: 1＝失效：DCF 權重歸零、EV/EBITDA 100%。常態化 FCF ≤ 0 時終值以 0 計、DCF 照常截斷並保留權重（v0.2）；股權為負不算失效
A31: DCF 每股：0 截斷 | C31: =MAX(0,(C25+C28)/C29) -> 0
A32: DCF 每股：選擇權（Merton） | C32: =IF((C23+C28)<=0,0,IF(評價_DCF與目標價!$C$68<=0,(C23+C28),(C23+C28)*NORMSDIST(C33)-評價_DCF與目標價!$C$68*EXP(-輸入與假設!$C$153*輸入與假設!$C$154)*NORMSDIST(C34))/C29) -> 0 | I32: Black-Scholes：S＝企業價值＋新股現值、K＝淨負債
A33: d1 | C33: =IF(OR((C23+C28)<=0,評價_DCF與目標價!$C$68<=0),0,(LN((C23+C28)/評價_DCF與目標價!$C$68)+(輸入與假設!$C$153+輸入與假設!$C$152^2/2)*輸入與假設!$C$154)/(輸入與假設!$C$152*SQRT(輸入與假設!$C$154))) -> 0
A34: d2 | C34: =C33-輸入與假設!$C$152*SQRT(輸入與假設!$C$154) -> -1.0606602
A36: 倍數法（錨定年度，預設 FY29；折回 2027-06-30）
A37: 錨定年度 | C37: =CHOOSE(輸入與假設!$C$143,"FY27","FY28","FY29","FY30") -> FY29 | I37: 輸入與假設 F 區可改
A38: 錨定年度 EBITDA | C38: =INDEX(損益!$D$19:$G$19,1,輸入與假設!$C$143) -> 9.641908
A39: 錨定年度企業價值（倍數 × EBITDA） | C39: =C38*輸入與假設!$C$142 -> 57.851448
A40: 錨定年度末淨負債（總債務 − 現金） | C40: =INDEX(各期收支!$D$82:$G$82,1,輸入與假設!$C$143)-INDEX(各期收支!$D$47:$G$47,1,輸入與假設!$C$143)+評價_DCF與目標價!$C$69 -> 33.232869 | I40: 含瀑布新債；加可轉債分類調整與淨負債調整項（見下方可轉債區）
A41: 錨定年度末股數（含瀑布新股） | C41: =INDEX(損益!$D$21:$G$21,1,輸入與假設!$C$143) -> 0.47342202 | I41: 損益股數：SBC 逐年稀釋＋瀑布新股
A42: 折回 2027-06-30 的折現因子 | C42: =1/(1+輸入與假設!$C$135)^(輸入與假設!$C$143-輸入與假設!$C$164) -> 0.77035792 | I42: 以 WACC 折現 [Assumed]
A43: EV/EBITDA 每股（融資後） | C43: =MAX(0,(C39-C40)/C41)*C42 -> 40.059643 | I43: 以 0 為下限
A45: 加權目標價
A46: DCF 每股（推到目標價時點） | C46: =C26*(1+輸入與假設!$C$135)^輸入與假設!$C$160 -> 0 | I46: ＝DCF 每股 ×（1＋WACC）^（評價日至目標價時點的年數）
A47: DCF 每股 × 有效權重 | C47: =C46*IF(C30=1,0,輸入與假設!$C$144) -> 0
A48: EV/EBITDA（融資後）× 有效權重 | C48: =C43*IF(C30=1,1,1-輸入與假設!$C$144) -> 22.032804
A49: 加權目標價 | C49: =SUM(C47:C48) -> 22.032804 | I49: 期前融資瀑布：缺口先由額度與資產層新債支應，殘差以股權募足；估值不再扣缺口本金
A50: 現價 | C50: =輸入與假設!$C$125 -> 249.87
A51: 潛在空間 | C51: =C49/C50-1 -> -0.91182293
A53: 可轉債稀釋（若轉換法；第一輪判斷價＝現價，第二輪＝MIN(現價, 第一輪目標價)）
A54: 第一輪：轉股股數 | C54: =SUMPRODUCT(資產負債_既有債務!$D$24:$D$31*資產負債_既有債務!$G$24:$G$31) -> 0.050022027 | I54: 有效轉換價 < 現價的可轉債：原始本金 ÷ 轉換價
A55: 第一輪：評價股數 | C55: =輸入與假設!$C$126+C54 -> 0.36932203
A56: 第一輪：評價淨負債 | C56: =輸入與假設!$C$127+SUMPRODUCT(資產負債_既有債務!$C$24:$C$31*(1-資產負債_既有債務!$G$24:$G$31))+輸入與假設!$C$134 -> -9.51285 | I56: ＝不含可轉債的淨負債＋債務處理可轉債到期本金＋調整項
A57: 第一輪：DCF 融資後股數 | C57: =C55+各期收支!G77 -> 0.58239116
A58: 第一輪：d1 | C58: =IF(OR((C23+C28)<=0,C56<=0),0,(LN((C23+C28)/C56)+(輸入與假設!$C$153+輸入與假設!$C$152^2/2)*輸入與假設!$C$154)/(輸入與假設!$C$152*SQRT(輸入與假設!$C$154))) -> 0
A59: 第一輪：DCF 每股（評價日） | C59: =IF(C30=1,0,IF(輸入與假設!$C$151=2,IF((C23+C28)<=0,0,IF(C56<=0,(C23+C28),(C23+C28)*NORMSDIST(C58)-C56*EXP(-輸入與假設!$C$153*輸入與假設!$C$154)*NORMSDIST(C58-輸入與假設!$C$152*SQRT(輸入與假設!$C$154)))/C57),MAX(0,(C23-C56+C28)/C57))) -> 0 | I59: 與上方 DCF 同算法，只換股數與淨負債
A60: 第一輪：錨定年末淨負債 | C60: =INDEX(各期收支!$D$82:$G$82,1,輸入與假設!$C$143)-INDEX(各期收支!$D$47:$G$47,1,輸入與假設!$C$143)+SUMPRODUCT(資產負債_既有債務!$C$24:$C$31*(資產負債_既有債務!$F$24:$F$31-資產負債_既有債務!$G$24:$G$31))+輸入與假設!$C$134 -> 24.176619 | I60: ＝融資表錨定年末淨負債＋（融資分類為轉股、評價分類為債務的到期本金）＋調整項
A61: 第一輪：錨定年末股數 | C61: =C55*(1+輸入與假設!$C$148)^輸入與假設!$C$143+INDEX(各期收支!$D$77:$G$77,1,輸入與假設!$C$143) -> 0.52495977
A62: 第一輪：EV/EBITDA 每股 | C62: =MAX(0,(C39-C60)/C61)*C42 -> 49.416494
A63: 第一輪：加權目標價 | C63: =C59*(1+輸入與假設!$C$135)^輸入與假設!$C$160*IF(C30=1,0,輸入與假設!$C$144)+C62*IF(C30=1,1,1-輸入與假設!$C$144) -> 27.179072
A64: 第二輪判斷價 | C64: =MIN(輸入與假設!$C$125,C63) -> 27.179072 | I64: ＝MIN(現價, 第一輪加權目標價)：以較保守者判斷是否價內
A65: 第二輪：轉股股數 | C65: =SUMPRODUCT(資產負債_既有債務!$D$24:$D$31*資產負債_既有債務!$H$24:$H$31) -> 0 | I65: 有效轉換價 < 第二輪判斷價的可轉債
A66: 第二輪：債務處理到期本金 | C66: =SUMPRODUCT(資產負債_既有債務!$C$24:$C$31*(1-資產負債_既有債務!$H$24:$H$31)) -> 15.72625
A67: 評價股數（含可轉債轉股） | C67: =輸入與假設!$C$126+C65 -> 0.3193 | I67: DCF、損益股數與錨定年末股數的起點
A68: 評價淨負債（含可轉債與調整項） | C68: =輸入與假設!$C$127+C66+輸入與假設!$C$134 -> -0.4566 | I68: DCF 減項與 Merton 履約價
A69: 錨定年末淨負債調整（可轉債分類差＋調整項） | C69: =SUMPRODUCT(資產負債_既有債務!$C$24:$C$31*(資產負債_既有債務!$F$24:$F$31-資產負債_既有債務!$H$24:$H$31))+輸入與假設!$C$134 -> 6.5488 | I69: 融資現金流依『融資分類』（判斷價＝股權發行價）；評價依第二輪分類，差額在錨定年末淨負債補回
A70: DCF 權重說明 | C70: =IF(C30=1,"DCF 失效，已以 EV/EBITDA 100% 計。",IF(AND(輸入與假設!$C$151<>2,C85<0),"DCF 為 $0 仍計 "&TEXT(輸入與假設!$C$144,"0%")&" 權重的原因：DCF 沒有失效，而是算出的股權價值為負（每股約 −$"&TEXT(ABS(C85),"0.0")&"），代表自由現金流折現後的企業價值不足以償還淨負債。EV/EBITDA 沒有扣除 GPU 汰換與擴張支出，保留 DCF 權重，是為了讓目標價反映「EBITDA 付不起資本成本」。若不計 DCF，目標價為 $"&TEXT(C43,"0.0")&"（"&CHOOSE(D84+2,"賣出","中立","買進")&"）；"&TEXT(輸入與假設!$C$144,"0%")&"／"&TEXT(1-輸入與假設!$C$144,"0%")&" 為判斷值。","")) -> DCF 為 $0 仍計 45% 權重的原因：DCF 沒有失效，而是算出的股權價值為負（每股約 −$52.0），代表自由現金流折現後的企業價值不足以償還淨負債。EV/EBITDA 沒有扣除 GPU 汰換與擴張支出，保留 DCF 權重，是為了讓目標價反映「EBITDA 付不起資本成本」。若不計 DCF，目標價為 $40.1（賣出）；45%／55% 為判斷值。 | I70: 只在 DCF 被 0 截斷時顯示；DCF 失效時改為一句；DCF 為正時空白（與 HTML 同一字串）
A72: 目標價區間（情境區間、方法區間；評等仍依點位）
A73: 目標價區間｜點位（目前輸入的加權目標價） | C73: =C49 -> 22.032804 | I73: ="評等規則不變：空間 ≥"&IF(ROUND(ABS(輸入與假設!$C$170)*100,4)=INT(ROUND(ABS(輸入與假設!$C$170)*100,4)),TEXT(ROUND(ABS(輸入與假設!$C$170)*100,4),"0"),TEXT(ROUND(ABS(輸入與假設!$C$170)*100,4),"0.0"))&"%"&" 且終值占比 <"&IF(ROUND(ABS(輸入與假設!$C$171)*100,4)=INT(ROUND(ABS(輸入與假設!$C$171)*100,4)),TEXT(ROUND(ABS(輸入與假設!$C$171)*100,4),"0"),TEXT(ROUND(ABS(輸入與假設!$C$171)*100,4),"0.0"))&"%"&"、股權募資 ≤"&IF(輸入與假設!$C$173=INT(輸入與假設!$C$173),TEXT(輸入與假設!$C$173,"0"),TEXT(輸入與假設!$C$173,"0.0"))&" 倍現市值 → 買進；空間 ≤−"&IF(ROUND(ABS(輸入與假設!$C$172)*100,4)=INT(ROUND(ABS(輸入與假設!$C$172)*100,4)),TEXT(ROUND(ABS(輸入與假設!$C$172)*100,4),"0"),TEXT(ROUND(ABS(輸入與假設!$C$172)*100,4),"0.0"))&"%"&"，或股權募資 >"&IF(輸入與假設!$C$173=INT(輸入與假設!$C$173),TEXT(輸入與假設!$C$173,"0"),TEXT(輸入與假設!$C$173,"0.0"))&" 倍且空間 ≤−"&IF(ROUND(ABS(輸入與假設!$C$174)*100,4)=INT(ROUND(ABS(輸入與假設!$C$174)*100,4)),TEXT(ROUND(ABS(輸入與假設!$C$174)*100,4),"0"),TEXT(ROUND(ABS(輸入與假設!$C$174)*100,4),"0.0"))&"%"&" → 賣出；其餘中立" -> 評等規則不變：空間 ≥25% 且終值占比 <90%、股權募資 ≤1.5 倍現市值 → 買進；空間 ≤−15%，或股權募資 >1.5 倍且空間 ≤−8% → 賣出；其餘中立
A74: 目標價區間｜終值占 EV（評等用） | C74: =C22/MAX(ABS(C23),1)*IF(C23=0,1,SIGN(C23)) -> 0
A75: 目標價區間｜股權募資 ÷ 現市值（評等用） | C75: =SUM(各期收支!C72:G72)/(輸入與假設!$C$125*輸入與假設!$C$126) -> 0.6005707
A76: 目標價區間｜點位評等代碼（1＝買進、0＝中立、−1＝賣出） | C76: =IF(AND((C49/MAX(輸入與假設!$C$125,0.01)-1)>=輸入與假設!$C$170,$C$74<輸入與假設!$C$171,$C$75<=輸入與假設!$C$173),1,IF(OR((C49/MAX(輸入與假設!$C$125,0.01)-1)<=輸入與假設!$C$172,AND($C$75>輸入與假設!$C$173,(C49/MAX(輸入與假設!$C$125,0.01)-1)<=輸入與假設!$C$174)),-1,0)) -> -1 | D76: =CHOOSE(C76+2,"賣出","中立","買進") -> 賣出
A77: 目標價區間｜賣出門檻價（現價 × (1 − 15%)） | C77: =輸入與假設!$C$125*(1+輸入與假設!$C$172) -> 212.3895
A78: 目標價區間｜保守 已簽約 3.5 GW（加權目標價／評等代碼／距賣出門檻） | C78: =輸入與假設!D202 -> 29.693039 | D78: =輸入與假設!E202 -> -1 | E78: =C78-$C$77 -> -182.69646 | I78: 引用『輸入與假設』底部模擬運算表（情境選擇 1／2／3），保留其餘手動輸入
A79: 目標價區間｜基準 合約 5 GW（加權目標價／評等代碼／距賣出門檻） | C79: =輸入與假設!D203 -> 22.032804 | D79: =輸入與假設!E203 -> -1 | E79: =C79-$C$77 -> -190.3567
A80: 目標價區間｜積極 每年 >1 GW（加權目標價／評等代碼／距賣出門檻） | C80: =輸入與假設!D204 -> 20.398771 | D80: =輸入與假設!E204 -> -1 | E80: =C80-$C$77 -> -191.99073
A81: 目標價區間｜情境區間（下緣／上緣） | C81: =MIN(C78,C80) -> 20.398771 | D81: =MAX(C78,C80) -> 29.693039
A82: 目標價區間｜方法區間倍數（下端／上端） | C82: =MIN(輸入與假設!$C$146,輸入與假設!$C$147) -> 5 | D82: =MAX(輸入與假設!$C$146,輸入與假設!$C$147) -> 6
A83: 目標價區間｜方法區間（下緣／上緣） | C83: =MIN(C46*IF(C30=1,0,輸入與假設!$C$144)+MAX(0,(C38*C82-C40)/C41)*C42*IF(C30=1,1,1-輸入與假設!$C$144),C46*IF(C30=1,0,輸入與假設!$C$144)+MAX(0,(C38*D82-C40)/C41)*C42*IF(C30=1,1,1-輸入與假設!$C$144)) -> 13.403619 | D83: =MAX(C46*IF(C30=1,0,輸入與假設!$C$144)+MAX(0,(C38*C82-C40)/C41)*C42*IF(C30=1,1,1-輸入與假設!$C$144),C46*IF(C30=1,0,輸入與假設!$C$144)+MAX(0,(C38*D82-C40)/C41)*C42*IF(C30=1,1,1-輸入與假設!$C$144)) -> 22.032804 | I83: ＝DCF 採用值 × 有效權重 ＋ EV/EBITDA 腿（倍數換成兩端）× 有效權重
A84: 目標價區間｜100% EV/EBITDA 目標價（價位／評等代碼） | C84: =C43 -> 40.059643 | D84: =IF(AND((C43/MAX(輸入與假設!$C$125,0.01)-1)>=輸入與假設!$C$170,$C$74<輸入與假設!$C$171,$C$75<=輸入與假設!$C$173),1,IF(OR((C43/MAX(輸入與假設!$C$125,0.01)-1)<=輸入與假設!$C$172,AND($C$75>輸入與假設!$C$173,(C43/MAX(輸入與假設!$C$125,0.01)-1)<=輸入與假設!$C$174)),-1,0)) -> -1 | E84: =CHOOSE(D84+2,"賣出","中立","買進") -> 賣出
A85: 目標價區間｜未截斷 DCF 每股 | C85: =(C25+C28)/C29 -> -51.962705
A86: 目標價區間｜點位摘要 | C86: ="目標價 $"&TEXT(C49,"0.0")&"（情境區間 $"&TEXT(C81,"0.0")&"–$"&TEXT(D81,"0.0")&"）" -> 目標價 $22.0（情境區間 $20.4–$29.7）
A87: 目標價區間｜方法區間標籤 | C87: ="方法區間（目前情境，"&IF(C82=INT(C82),TEXT(C82,"0"),TEXT(C82,"0.0"))&"–"&IF(D82=INT(D82),TEXT(D82,"0"),TEXT(D82,"0.0"))&"x）" -> 方法區間（目前情境，5–6x）
A88: 目標價區間｜點位位置 | C88: =IF(ABS(輸入與假設!$C$142-D82)<0.000000001,"目前點位位於方法區間上緣（"&IF(D82=INT(D82),TEXT(D82,"0"),TEXT(D82,"0.0"))&"x 為穩態倍數上緣）",IF(ABS(輸入與假設!$C$142-C82)<0.000000001,"目前點位位於方法區間下緣（"&IF(C82=INT(C82),TEXT(C82,"0"),TEXT(C82,"0.0"))&"x）","目前點位"&IF(AND(輸入與假設!$C$142>C82,輸入與假設!$C$142<D82),"位於方法區間內",IF(輸入與假設!$C$142>D82,"高於方法區間上緣","低於方法區間下緣"))&"（目前倍數 "&IF(輸入與假設!$C$142=INT(輸入與假設!$C$142),TEXT(輸入與假設!$C$142,"0"),TEXT(輸入與假設!$C$142,"0.0"))&"x）")) -> 目前點位位於方法區間上緣（6x 為穩態倍數上緣）
A89: 目標價區間｜判斷句 | C89: =IF(D81<輸入與假設!$C$125,"情境區間上緣 $"&TEXT(D81,"0.0")&" 低於現價 $"&TEXT(輸入與假設!$C$125,"0.00")&IF((D78<>-1)+(D79<>-1)+(D80<>-1)>0,"，但"&SUBSTITUTE(TRIM(IF(D78<>-1,"保守","")&" "&IF(D79<>-1,"基準","")&" "&IF(D80<>-1,"積極",""))," ","、")&"情境未達賣出門檻 $"&TEXT($C$77,"0.0"),"：賣出在三個擴張情境下都成立"),"情境區間上緣 $"&TEXT(D81,"0.0")&" 不低於現價 $"&TEXT(輸入與假設!$C$125,"0.00")&"：賣出並非在三個擴張情境下都成立")&"。"&IF(ABS(E78)<輸入與假設!$C$175*輸入與假設!$C$125,"保守情境 $"&TEXT(C78,"0.0")&"，"&IF(E78<0,"距賣出門檻","高於賣出門檻")&" $"&TEXT($C$77,"0.0")&" 僅 $"&TEXT(ABS(E78),"0.0")&"。","")&IF(ABS(E79)<輸入與假設!$C$175*輸入與假設!$C$125,"基準情境 $"&TEXT(C79,"0.0")&"，"&IF(E79<0,"距賣出門檻","高於賣出門檻")&" $"&TEXT($C$77,"0.0")&" 僅 $"&TEXT(ABS(E79),"0.0")&"。","")&IF(ABS(E80)<輸入與假設!$C$175*輸入與假設!$C$125,"積極情境 $"&TEXT(C80,"0.0")&"，"&IF(E80<0,"距賣出門檻","高於賣出門檻")&" $"&TEXT($C$77,"0.0")&" 僅 $"&TEXT(ABS(E80),"0.0")&"。","") -> 情境區間上緣 $29.7 低於現價 $249.87：賣出在三個擴張情境下都成立。
A91: 錨定年度 × 倍數矩陣（每股；以 WACC 折回 2027-06-30）
A92: 倍數 ＼ 錨定（EV/EBITDA 腿） | B92: 倍數 | C92: FY27 | D92: FY28 | E92: FY29 | F92: FY30 | I92: EV/EBITDA 腿＝(錨定年 EBITDA × 倍數 − 錨定年末淨負債) ÷ 錨定年末股數 × 折現因子；加權＝DCF 採用值 × 有效權重 ＋ 腿 × 有效權重。綠底＝不低於現價
A93: 錨定×倍數｜EV/EBITDA 腿｜3.4x | B93: 3.4 | C93: =MAX(0,(INDEX(損益!$D$19:$G$19,1,1)*$B93-(INDEX(各期收支!$D$82:$G$82,1,1)-INDEX(各期收支!$D$47:$G$47,1,1)+評價_DCF與目標價!$C$69))/INDEX(損益!$D$21:$G$21,1,1))/(1+輸入與假設!$C$135)^(1-輸入與假設!$C$164) -> 0 | D93: =MAX(0,(INDEX(損益!$D$19:$G$19,1,2)*$B93-(INDEX(各期收支!$D$82:$G$82,1,2)-INDEX(各期收支!$D$47:$G$47,1,2)+評價_DCF與目標價!$C$69))/INDEX(損益!$D$21:$G$21,1,2))/(1+輸入與假設!$C$135)^(2-輸入與假設!$C$164) -> 0 | E93: =MAX(0,(INDEX(損益!$D$19:$G$19,1,3)*$B93-(INDEX(各期收支!$D$82:$G$82,1,3)-INDEX(各期收支!$D$47:$G$47,1,3)+評價_DCF與目標價!$C$69))/INDEX(損益!$D$21:$G$21,1,3))/(1+輸入與假設!$C$135)^(3-輸入與假設!$C$164) -> 0 | F93: =MAX(0,(INDEX(損益!$D$19:$G$19,1,4)*$B93-(INDEX(各期收支!$D$82:$G$82,1,4)-INDEX(各期收支!$D$47:$G$47,1,4)+評價_DCF與目標價!$C$69))/INDEX(損益!$D$21:$G$21,1,4))/(1+輸入與假設!$C$135)^(4-輸入與假設!$C$164) -> 0
A94: 錨定×倍數｜EV/EBITDA 腿｜4.5x | B94: 4.5 | C94: =MAX(0,(INDEX(損益!$D$19:$G$19,1,1)*$B94-(INDEX(各期收支!$D$82:$G$82,1,1)-INDEX(各期收支!$D$47:$G$47,1,1)+評價_DCF與目標價!$C$69))/INDEX(損益!$D$21:$G$21,1,1))/(1+輸入與假設!$C$135)^(1-輸入與假設!$C$164) -> 0 | D94: =MAX(0,(INDEX(損益!$D$19:$G$19,1,2)*$B94-(INDEX(各期收支!$D$82:$G$82,1,2)-INDEX(各期收支!$D$47:$G$47,1,2)+評價_DCF與目標價!$C$69))/INDEX(損益!$D$21:$G$21,1,2))/(1+輸入與假設!$C$135)^(2-輸入與假設!$C$164) -> 0 | E94: =MAX(0,(INDEX(損益!$D$19:$G$19,1,3)*$B94-(INDEX(各期收支!$D$82:$G$82,1,3)-INDEX(各期收支!$D$47:$G$47,1,3)+評價_DCF與目標價!$C$69))/INDEX(損益!$D$21:$G$21,1,3))/(1+輸入與假設!$C$135)^(3-輸入與假設!$C$164) -> 16.525503 | F94: =MAX(0,(INDEX(損益!$D$19:$G$19,1,4)*$B94-(INDEX(各期收支!$D$82:$G$82,1,4)-INDEX(各期收支!$D$47:$G$47,1,4)+評價_DCF與目標價!$C$69))/INDEX(損益!$D$21:$G$21,1,4))/(1+輸入與假設!$C$135)^(4-輸入與假設!$C$164) -> 14.980953
A95: 錨定×倍數｜EV/EBITDA 腿｜5.0x | B95: 5 | C95: =MAX(0,(INDEX(損益!$D$19:$G$19,1,1)*$B95-(INDEX(各期收支!$D$82:$G$82,1,1)-INDEX(各期收支!$D$47:$G$47,1,1)+評價_DCF與目標價!$C$69))/INDEX(損益!$D$21:$G$21,1,1))/(1+輸入與假設!$C$135)^(1-輸入與假設!$C$164) -> 0 | D95: =MAX(0,(INDEX(損益!$D$19:$G$19,1,2)*$B95-(INDEX(各期收支!$D$82:$G$82,1,2)-INDEX(各期收支!$D$47:$G$47,1,2)+評價_DCF與目標價!$C$69))/INDEX(損益!$D$21:$G$21,1,2))/(1+輸入與假設!$C$135)^(2-輸入與假設!$C$164) -> 6.2926971 | E95: =MAX(0,(INDEX(損益!$D$19:$G$19,1,3)*$B95-(INDEX(各期收支!$D$82:$G$82,1,3)-INDEX(各期收支!$D$47:$G$47,1,3)+評價_DCF與目標價!$C$69))/INDEX(損益!$D$21:$G$21,1,3))/(1+輸入與假設!$C$135)^(3-輸入與假設!$C$164) -> 24.370216 | F95: =MAX(0,(INDEX(損益!$D$19:$G$19,1,4)*$B95-(INDEX(各期收支!$D$82:$G$82,1,4)-INDEX(各期收支!$D$47:$G$47,1,4)+評價_DCF與目標價!$C$69))/INDEX(損益!$D$21:$G$21,1,4))/(1+輸入與假設!$C$135)^(4-輸入與假設!$C$164) -> 22.759513
A96: 錨定×倍數｜EV/EBITDA 腿｜6.0x | B96: 6 | C96: =MAX(0,(INDEX(損益!$D$19:$G$19,1,1)*$B96-(INDEX(各期收支!$D$82:$G$82,1,1)-INDEX(各期收支!$D$47:$G$47,1,1)+評價_DCF與目標價!$C$69))/INDEX(損益!$D$21:$G$21,1,1))/(1+輸入與假設!$C$135)^(1-輸入與假設!$C$164) -> 0 | D96: =MAX(0,(INDEX(損益!$D$19:$G$19,1,2)*$B96-(INDEX(各期收支!$D$82:$G$82,1,2)-INDEX(各期收支!$D$47:$G$47,1,2)+評價_DCF與目標價!$C$69))/INDEX(損益!$D$21:$G$21,1,2))/(1+輸入與假設!$C$135)^(2-輸入與假設!$C$164) -> 19.153408 | E96: =MAX(0,(INDEX(損益!$D$19:$G$19,1,3)*$B96-(INDEX(各期收支!$D$82:$G$82,1,3)-INDEX(各期收支!$D$47:$G$47,1,3)+評價_DCF與目標價!$C$69))/INDEX(損益!$D$21:$G$21,1,3))/(1+輸入與假設!$C$135)^(3-輸入與假設!$C$164) -> 40.059643 | F96: =MAX(0,(INDEX(損益!$D$19:$G$19,1,4)*$B96-(INDEX(各期收支!$D$82:$G$82,1,4)-INDEX(各期收支!$D$47:$G$47,1,4)+評價_DCF與目標價!$C$69))/INDEX(損益!$D$21:$G$21,1,4))/(1+輸入與假設!$C$135)^(4-輸入與假設!$C$164) -> 38.316632
A97: 錨定×倍數｜EV/EBITDA 腿｜7.0x | B97: 7 | C97: =MAX(0,(INDEX(損益!$D$19:$G$19,1,1)*$B97-(INDEX(各期收支!$D$82:$G$82,1,1)-INDEX(各期收支!$D$47:$G$47,1,1)+評價_DCF與目標價!$C$69))/INDEX(損益!$D$21:$G$21,1,1))/(1+輸入與假設!$C$135)^(1-輸入與假設!$C$164) -> 0 | D97: =MAX(0,(INDEX(損益!$D$19:$G$19,1,2)*$B97-(INDEX(各期收支!$D$82:$G$82,1,2)-INDEX(各期收支!$D$47:$G$47,1,2)+評價_DCF與目標價!$C$69))/INDEX(損益!$D$21:$G$21,1,2))/(1+輸入與假設!$C$135)^(2-輸入與假設!$C$164) -> 32.014119 | E97: =MAX(0,(INDEX(損益!$D$19:$G$19,1,3)*$B97-(INDEX(各期收支!$D$82:$G$82,1,3)-INDEX(各期收支!$D$47:$G$47,1,3)+評價_DCF與目標價!$C$69))/INDEX(損益!$D$21:$G$21,1,3))/(1+輸入與假設!$C$135)^(3-輸入與假設!$C$164) -> 55.74907 | F97: =MAX(0,(INDEX(損益!$D$19:$G$19,1,4)*$B97-(INDEX(各期收支!$D$82:$G$82,1,4)-INDEX(各期收支!$D$47:$G$47,1,4)+評價_DCF與目標價!$C$69))/INDEX(損益!$D$21:$G$21,1,4))/(1+輸入與假設!$C$135)^(4-輸入與假設!$C$164) -> 53.873752
A99: 倍數 ＼ 錨定（加權目標價） | B99: 倍數 | C99: FY27 | D99: FY28 | E99: FY29 | F99: FY30
A100: 錨定×倍數｜加權目標價｜3.4x | B100: 3.4 | C100: =C46*IF(C30=1,0,輸入與假設!$C$144)+C93*IF(C30=1,1,1-輸入與假設!$C$144) -> 0 | D100: =C46*IF(C30=1,0,輸入與假設!$C$144)+D93*IF(C30=1,1,1-輸入與假設!$C$144) -> 0 | E100: =C46*IF(C30=1,0,輸入與假設!$C$144)+E93*IF(C30=1,1,1-輸入與假設!$C$144) -> 0 | F100: =C46*IF(C30=1,0,輸入與假設!$C$144)+F93*IF(C30=1,1,1-輸入與假設!$C$144) -> 0
A101: 錨定×倍數｜加權目標價｜4.5x | B101: 4.5 | C101: =C46*IF(C30=1,0,輸入與假設!$C$144)+C94*IF(C30=1,1,1-輸入與假設!$C$144) -> 0 | D101: =C46*IF(C30=1,0,輸入與假設!$C$144)+D94*IF(C30=1,1,1-輸入與假設!$C$144) -> 0 | E101: =C46*IF(C30=1,0,輸入與假設!$C$144)+E94*IF(C30=1,1,1-輸入與假設!$C$144) -> 9.0890266 | F101: =C46*IF(C30=1,0,輸入與假設!$C$144)+F94*IF(C30=1,1,1-輸入與假設!$C$144) -> 8.2395243
A102: 錨定×倍數｜加權目標價｜5.0x | B102: 5 | C102: =C46*IF(C30=1,0,輸入與假設!$C$144)+C95*IF(C30=1,1,1-輸入與假設!$C$144) -> 0 | D102: =C46*IF(C30=1,0,輸入與假設!$C$144)+D95*IF(C30=1,1,1-輸入與假設!$C$144) -> 3.4609834 | E102: =C46*IF(C30=1,0,輸入與假設!$C$144)+E95*IF(C30=1,1,1-輸入與假設!$C$144) -> 13.403619 | F102: =C46*IF(C30=1,0,輸入與假設!$C$144)+F95*IF(C30=1,1,1-輸入與假設!$C$144) -> 12.517732
A103: 錨定×倍數｜加權目標價｜6.0x | B103: 6 | C103: =C46*IF(C30=1,0,輸入與假設!$C$144)+C96*IF(C30=1,1,1-輸入與假設!$C$144) -> 0 | D103: =C46*IF(C30=1,0,輸入與假設!$C$144)+D96*IF(C30=1,1,1-輸入與假設!$C$144) -> 10.534375 | E103: =C46*IF(C30=1,0,輸入與假設!$C$144)+E96*IF(C30=1,1,1-輸入與假設!$C$144) -> 22.032804 | F103: =C46*IF(C30=1,0,輸入與假設!$C$144)+F96*IF(C30=1,1,1-輸入與假設!$C$144) -> 21.074148
A104: 錨定×倍數｜加權目標價｜7.0x | B104: 7 | C104: =C46*IF(C30=1,0,輸入與假設!$C$144)+C97*IF(C30=1,1,1-輸入與假設!$C$144) -> 0 | D104: =C46*IF(C30=1,0,輸入與假設!$C$144)+D97*IF(C30=1,1,1-輸入與假設!$C$144) -> 17.607766 | E104: =C46*IF(C30=1,0,輸入與假設!$C$144)+E97*IF(C30=1,1,1-輸入與假設!$C$144) -> 30.661988 | F104: =C46*IF(C30=1,0,輸入與假設!$C$144)+F97*IF(C30=1,1,1-輸入與假設!$C$144) -> 29.630564

Sheet 評價_反向DCF
A1: 反向 DCF — 現價隱含什麼樣的收入與成本
A2: 不是問「值多少」，而是問「要值現價，營運要長什麼樣」。Excel 以『目標搜尋』反解；下方另附 HTML 即時計算結果的快照（v4.0 預設輸入）
A4: 即時：目前 DCF 與現價的差距
A5: 現價 | B5: =輸入與假設!$C$125 -> 249.87
A6: 目前 DCF 每股（依下限方式） | B6: =評價_DCF與目標價!C26 -> 0
A7: 差距（DCF − 現價）＝目標搜尋的『設定儲存格』 | B7: =B6-B5 -> -249.87
A8: 目前每 MW 年收入倍數／建置成本倍數 | B8: =輸入與假設!$C$35 -> 1 | C8: =輸入與假設!$C$67 -> 1
A10: 操作：用『目標搜尋』反解（資料 → 模擬分析 → 目標搜尋）
A11: ① 設定儲存格：本頁 B7；目標值：0
A12: ② 變數儲存格（擇一）：輸入與假設 B 區『每 MW 年收入倍數』→ 市價隱含單價；或 D 區『每 MW 建置成本倍數』→ 市價隱含建置成本；或 C 區『穩態 EBITDA 率』
A13: ③ 解完請記下結果，再把倍數改回 100%（或按 Ctrl+Z）。DCF 以 0 截斷時，負值區域斜率為 0，請從 100% 以上開始搜尋
A14: ④ 組合分析：先把 D 區建置成本倍數與 C 區穩態 EBITDA 率設為想測的值，再對『每 MW 年收入倍數』做目標搜尋，即得下方矩陣中的一格
A16: 快照：單一槓桿（HTML v4.0 預設輸入，DCF 0 截斷）
A17: 單一槓桿（其他不變） | B17: 目前 | C17: 市價隱含 | D17: 變動 | G17: 對照
A18: FY30 每 MW 年收入（US$m） | B18: 10.3953 | C18: 31.7846 | D18: 2.0576 | G18: 期末 ARR 指引隱含約 $10.0–10.5m；7 月新約漲價約 25%
A19: 每 MW 建置成本（US$m） | B19: 50.2564 | C19: 無解 | D19: — | G19: FY26 指引隱含約 $32–37m
A20: 穩態 EBITDA 率（FY30） | B20: 0.47 | C20: 無解 | D20: — | G20: 可觀察 neocloud 區間 IREN 約 35%、CRWV 約 59%（變動為百分點）
A21: （對照）加權目標價＝現價所需每 MW 年收入 | B21: 10.3953 | C21: 29.1587 | D21: 1.805 | G21: 含 EV/EBITDA 6x（FY29 錨定） 腿；非純反向 DCF
A23: 快照：收入與成本的綜合影響——要值現價，FY30 每 MW 年收入需要多少（US$m）
A24: 建置成本 ＼ 穩態 EBITDA 率 | B24: 0.35 | C24: 0.47 | D24: 0.59 | E24: 0.7
A25: $35.2m（-30%） | B25: 33.65 | C25: 25.51 | D25: 20.55 | E25: 17.44
A26: $40.2m（-20%） | B26: 36.13 | C26: 27.39 | D26: 22.06 | E26: 18.72
A27: $45.2m（-10%） | B27: 39.03 | C27: 29.59 | D27: 23.83 | E27: 20.22
A28: $50.3m（目前） | B28: — | C28: 31.78 | D28: 25.6 | E28: 21.73
A29: $55.3m（+10%） | B29: — | C29: 33.98 | D29: 27.37 | E29: 23.24
A30: 快照為靜態數值（HTML 以同一引擎即時計算）；改變輸入後請以目標搜尋重算，或參考 HTML『評價 → 反向 DCF』

Sheet 評價_可比公司
A1: 可比公司 — 以 EV/Sales 為主（市值：2026-09-21 收盤）
A2: EV＝市值＋（有息負債−非受限現金）；含租賃＝EV＋營業租賃負債。EV/EBITDA 僅供參考（GAAP EBITDA 為負者顯示 n/m）。此表不進入目標價。與 HTML Comps 分頁同一組數字
A4: 公司 | B4: 市值 | C4: 淨負債 | D4: EV | E4: TTM 營收 | F4: EV/Sales（TTM） | G4: 含租賃 EV/Sales | H4: TTM EBITDA | I4: EV/EBITDA | J4: 資料期 | K4: 備註
A5: CRWV CoreWeave | B5: 47.12 | C5: 30.012 | D5: =B5+C5 -> 77.132 | E5: 7.59 | F5: =D5/E5 -> 10.162319 | G5: =(D5+16.54)/E5 -> 12.341502 | H5: =-0.231+3.991 -> 3.76 | I5: =IF(H5>0,D5/H5,"n/m") -> 20.51383 | J5: TTM 至 Q2（6/30，10-Q） | K5: 營業租賃負債 16.54；GAAP 營業損益 -0.231＋D&A 3.991。CRWV Q2 10-Q；以租約取得機房（租賃負債 16.54）；市值 9/21
A6: IREN | B6: 18.61 | C6: 1.7 | D6: =B6+C6 -> 20.31 | E6: 0.707 | F6: =D6/E6 -> 28.727016 | G6: =(D6+0.003)/E6 -> 28.731259 | H6: =-1.047+0.418 -> -0.629 | I6: =IF(H6>0,D6/H6,"n/m") -> n/m | J6: FY26 10-K（6/30）；未更新，日期 2026-09-21 | K6: 營業租賃負債 0.003；GAAP 營業損益 -1.047＋D&A 0.418。自有電廠、營業租賃負債僅 0.003bn；FY26 合約 ARR 4.0bn
A7: APLD Applied Digital | B7: 8.22 | C7: 3.37 | D7: =B7+C7 -> 11.59 | E7: 0.6113 | F7: =D7/E7 -> 18.959594 | G7: =(D7+0.066)/E7 -> 19.067561 | H7: =-0.236+0.067 -> -0.169 | I7: =IF(H7>0,D7/H7,"n/m") -> n/m | J7: FY26 10-K（5/31）；未更新，日期 2026-09-21 | K7: 營業租賃負債 0.066；GAAP 營業損益 -0.236＋D&A 0.067。租約多未起租，營收尚未反映約 36bn 合約
A8: CORZ Core Scientific | B8: 5.9 | C8: 2.53 | D8: =B8+C8 -> 8.43 | E8: 0.4403 | F8: =D8/E8 -> 19.146037 | G8: =(D8+0.109)/E8 -> 19.393595 | H8: =-0.561+0.063 -> -0.498 | I8: =IF(H8>0,D8/H8,"n/m") -> n/m | J8: TTM 至 Q2（6/30）；未更新，日期 2026-09-21 | K8: 營業租賃負債 0.109；GAAP 營業損益 -0.561＋D&A 0.063。託管轉型期
A9: 同業中位數 | F9: =MEDIAN(F5:F8) -> 19.052816 | G9: =MEDIAN(G5:G8) -> 19.230578
A10: NBIS（TTM 至 Q2） | B10: 63.81 | C10: =輸入與假設!$C$127+SUM(資產負債_既有債務!$C$24:$C$31)+輸入與假設!$C$134 -> -0.4566 | D10: =B10+C10 -> 63.3534 | E10: 1.36 | F10: =D10/E10 -> 46.583382 | G10: =(D10+1.6253)/E10 -> 47.778456 | H10: =-0.612+0.418 -> -0.194 | I10: =IF(H10>0,D10/H10,"n/m") -> n/m | J10: TTM 至 Q2 | K10: EV 用 2026-09-21 市值（基本股）與評價日淨負債（可轉債全數以到期本金計入）；含租賃再加營業租賃負債 1.6253
A11: NBIS 模型 FY27E | B11: =輸入與假設!$C$125*評價_DCF與目標價!$C$67 -> 79.783491 | C11: =評價_DCF與目標價!$C$68 -> -0.4566 | D11: =B11+C11 -> 79.326891 | E11: =損益!D8 -> 5.9751652 | F11: =D11/E11 -> 13.2761 | G11: =(D11+1.6253)/E11 -> 13.548109 | H11: =損益!D19 -> 2.7883247 | I11: =D11/H11 -> 28.44966 | K11: 市值用評價股數（含價內可轉債轉股）、淨負債用評價淨負債；分母為模型 FY27 營收
A13: 讀法：NBIS 的 TTM EV/Sales 遠高於同業，主因營收仍在爬坡（TTM 1.36 對 2026 指引 3.0–3.4），TTM 倍數偏高；
A14: CRWV 以租約取得機房，加入營業租賃負債後倍數上升；NBIS 自有占合約電力 >75%，加與不加差別小。
A15: 前瞻：見下方 NBIS 模型 FY27E 列。此表為市場比較用，不進入目標價（DCF 45%＋EV/EBITDA 55%）。

Sheet 檢查_連動
A1: 連動檢查 — 恆等式與口徑
A3: 檢查項目 | B3: 實際值 | C3: 標準 | D3: 結果 | E3: 說明
A4: RPO 桶權重合計 | B4: =SUM(輸入與假設!C38:G38) -> 0.82 | C4: =輸入與假設!$C$29 -> 0.82 | D4: =IF(ABS(B4-C4)<0.0001,"通過","不一致") -> 通過 | E4: 季報桶線性分攤後應為 82%
A5: 現金橋差異 | B5: =各期收支!C96 -> -9.3258734e-15 | C5: =0 -> 0 | D5: =IF(ABS(B5)<0.01,"通過","不一致") -> 通過 | E5: 期初＋營運缺口＋股權＋額度−還本 ＝ 期末
A6: Billable ≤ Accepted（FY30） | B6: =運營_產能與收入!G9-運營_產能與收入!G10 -> 307 | C6: ≥0 | D6: =IF(B6>=0,"通過","不一致") -> 通過 | E6: 引擎已以 MIN 截斷；此列驗證截斷有效
A7: FY26 CapEx 認列 vs 指引 | B7: =各期收支!C100 -> 26.04619 | C7: 20–25 | D7: =IF(AND(B7>=20,B7<=25),"通過","觀察") -> 觀察 | E7: 1H 實際認列 8.1303＋2H 模型；全年指引 20–25（法說會轉述）
A8: FY26 營收 vs 指引 | B8: =各期收支!C99 -> 2.3394994 | C8: 3–3.4 | D8: =IF(AND(B8>=3,B8<=3.4),"通過","觀察") -> 觀察 | E8: 1H 實際 0.9813＋2H 模型（算力＋非算力服務）
A9: CapEx 強度（模型期合計） | B9: =SUM(各期收支!C6:G6)/((運營_產能與收入!G9-輸入與假設!$C$32)/1000)/1000*1000 -> 53.117948 | C9: $38–68m/MW | D9: =IF(AND(B9>=38,B9<=68),"通過","觀察") -> 通過 | E9: Tokenomics IF_CapexTotal 低／高成本情境（GB300 38.8–67.1 US$m/MW-IT）
A10: 表外租金路徑 ÷ 已承諾 | B10: =資產負債_租賃承諾!C23 -> 0.97926109 | C10: ≥0.8x | D10: =IF(B10>=0.8,"通過","不一致") -> 通過 | E10: 表外租金路徑對已簽約未起租租賃
A11: FY26 利息（1H 實際＋2H） | B11: =各期收支!C101 -> 0.243175 | C11: ≥0.2 | D11: =IF(B11>=0.2,"通過","觀察") -> 通過 | E11: ="1H 實際 0.1828＋2H 模型 "&TEXT(各期收支!C16,"0.0")&"；公司未提供季度利息指引（不適用）" -> 1H 實際 0.1828＋2H 模型 0.1；公司未提供季度利息指引（不適用）
A12: FY28 起收入是否依賴未簽約 | B12: =SUM(運營_產能與收入!E23:G23)/SUM(運營_產能與收入!E25:G25) -> 0.65328301 | C12: <50% 較穩健 | D12: =IF(B12<0.5,"通過","觀察") -> 觀察 | E12: FY28–30 超出期初 RPO 的收入 ÷ 同期總算力收入（MW 驅動下為未簽約產能的比重）
A13: 損益營收＝資金營收 | B13: =損益!D6-運營_產能與收入!D25 -> 0 | C13: =0 -> 0 | D13: =IF(ABS(B13)<0.001,"通過","不一致") -> 通過 | E13: FY27 損益算力收入 − 產能頁 isRev。兩邊必須同一組數字
A14: 終值占 EV 比重 | B14: =評價_DCF與目標價!C27 -> 0 | C14: ="<"&IF(ROUND(ABS(輸入與假設!$C$176)*100,4)=INT(ROUND(ABS(輸入與假設!$C$176)*100,4)),TEXT(ROUND(ABS(輸入與假設!$C$176)*100,4),"0"),TEXT(ROUND(ABS(輸入與假設!$C$176)*100,4),"0.0"))&"%" -> <85% | D14: =IF(B14<輸入與假設!$C$176,"通過","觀察") -> 通過 | E14: 過高表示結論由終值假設決定
A15: EBITDA 單一來源（FY27 損益 EBITDA÷營收 − 輸入 EBITDA 率） | B15: =(損益!D19-輸入與假設!D47)/損益!D8-輸入與假設!D53 -> 0 | C15: =0 -> 0 | D15: =IF(ABS(B15)<0.0001,"通過","不一致") -> 通過 | E15: 損益與資金引用同一列 EBITDA 率
A16: 現金 EBITDA ＋ 信用調整 − 損益 EBITDA（FY27） | B16: =(運營_產能與收入!D37+運營_產能與收入!D38+輸入與假設!D54-各期收支!D15)+(運營_產能與收入!D32+運營_產能與收入!D23*輸入與假設!D44*(1-輸入與假設!D45))*運營_產能與收入!D36-(損益!D19-輸入與假設!D47) -> 0 | C16: =0 -> 0 | D16: =IF(ABS(B16)<0.001,"通過","不一致") -> 通過 | E16: 現金 EBITDA＝RPO 現金＋新簽約現金＋服務現金−租金；信用調整＝信用損失×EBITDAR 率
A17: DCF 有效性（1＝失效） | B17: =評價_DCF與目標價!C30 -> 0 | C17: 0 | D17: =IF(B17=0,"通過","觀察") -> 通過 | E17: 失效只定義為 WACC ≤ g（v0.2；常態化 FCF ≤ 0 時終值以 0 計、不算失效）；股權為負不算失效
A18: 期末現金 ≥ 最低現金（期前融資） | B18: =MIN(各期收支!C47:G47) -> 2 | C18: ≥2.0 | D18: =IF(B18>=1.999,"通過","不一致") -> 通過 | E18: 瀑布每期補足至最低現金；最小值應等於最低現金
A19: 股權募資 ÷ 現市值 | B19: =SUM(各期收支!C72:G72)/(輸入與假設!$C$125*輸入與假設!$C$126) -> 0.6005707 | C19: ="≤"&IF(輸入與假設!$C$173=INT(輸入與假設!$C$173),TEXT(輸入與假設!$C$173,"0"),TEXT(輸入與假設!$C$173,"0.0"))&"x" -> ≤1.5x | D19: =IF(B19<=輸入與假設!$C$173,"通過","觀察") -> 通過 | E19: ="超過 "&IF(輸入與假設!$C$173=INT(輸入與假設!$C$173),TEXT(輸入與假設!$C$173,"0"),TEXT(輸入與假設!$C$173,"0.0"))&" 倍：市場吸收能力存疑，結論不得為買進" -> 超過 1.5 倍：市場吸收能力存疑，結論不得為買進
A20: 債務明細合計 = 季報本金 10.0885 − 以股換債 ＋ 期後新發 | B20: =資產負債_既有債務!E6+SUM(資產負債_既有債務!$C$24:$C$31) -> 15.77295 | C20: 15.7785 | D20: =IF(ABS(B20-15.7785)<0.01,"通過","不一致") -> 通過 | E20: 其他借款 1 筆＋可轉債 8 檔到期本金（company.json → debt.convertibleBridge）
A21: FY26 全年 CapEx（MW 公式） | B21: =輸入與假設!C86 -> 26.04619 | C21: 20–25 | D21: =IF(AND(B21>=20,B21<=25),"通過","觀察") -> 觀察 | E21: 由已連網 MW 增量與預建次年推得；指引只作對照
A22: JV 已承諾餘額於 2026 年內履行 | B22: =SUM(輸入與假設!C79:G79) -> 0 | C22: =0 -> 0 | D22: =IF(ABS(B22-0)<0.01,"通過","不一致") -> 通過 | E22: 季報未揭露 JV 出資承諾（不適用）
A23: 模型每 MW 年租金（FY30） | B23: =運營_站點!G27 -> 0.35783536 | C23: ≥ 市場基準×占比 | D23: =IF(B23>=運營_站點!$H$11*運營_站點!$C$28*0.8,"通過","觀察") -> 通過 | E23: 低於基準×占比的八成即標示：模型租金路徑可能低估
A24: 站點租賃：五期租金可能低估 | B24: =運營_站點!$C$31 -> -3.8242233 | C24: <10 | D24: =IF(B24<10,"通過","觀察") -> 通過 | E24: ＝Σ(在役 MW×市場基準×第三方占比 − 模型租金)
A25: 營收＝在役 MW × 每 MW × 利用率（五期差額） | B25: =SUM(運營_產能與收入!C26:G26) -> 0 | C25: =0 -> 0 | D25: =IF(ABS(B25)<0.000001,"通過","不一致") -> 通過 | E25: MW 驅動：營收＝平均在役 MW × 每 MW 年收入 × 利用率 × 期間長度
A26: 收入上限：每 MW 收入 ÷ 客戶付費 token 營收（最高） | B26: =每MW收入_錨定!C146 -> 0.36704482 | C26: ≤50% | D26: =IF(B26<=0.5,"通過","警示") -> 通過 | E26: neocloud 拿走客戶 token 營收的比例＝每 MW 年收入 ÷ Tokenomics 四層瀑布比較層 _Prod（IFW_RevGWFleet_Prod，在役世代加權；company.json → methodology.checks.revCapLayer）；> 50% 警示；只警示、不改數字（v0.2a；v0.4a 改四層）
A28: 關鍵輸出（快照；「模型期」＝2026-07-01～2030，與 HTML 頂部 KPI 同口徑）
A29: 模型期排程 RPO | B29: =SUM(運營_產能與收入!C17:G17) -> 30.742292
A30: 模型期產能瓶頸 | B30: =SUM(運營_產能與收入!C19:G19) -> 2.7890974
A31: 模型期新簽約收入 | B31: =SUM(運營_產能與收入!C23:G23) -> 38.851816
A32: 模型期毛 CapEx（6/30 起） | B32: =SUM(輸入與假設!C91:G91) -> 141.50296
A33: 模型期租金（6/30 起） | B33: =SUM(各期收支!C15:G15) -> 3.8242233
A34: 模型期利息（6/30 起，含瀑布新債） | B34: =SUM(各期收支!C20:G20) -> 4.464376
A35: 模型期排程還本（6/30 起） | B35: =SUM(輸入與假設!C120:G120)*輸入與假設!$C$100+SUM(資產負債_既有債務!C42:G42) -> 3.8417
A36: 模型期營運缺口（6/30 起） | B36: =SUM(各期收支!C45:G45)-(輸入與假設!$C$180-輸入與假設!$C$181-輸入與假設!$C$183) -> -91.60983
A37: FY26 全年口徑營運缺口（含 1H 實際） | B37: =SUM(各期收支!C45:G45) -> -95.48763
A38: 期末現金 | B38: =各期收支!G47 -> 2
A39: DCF 每股 | B39: =評價_DCF與目標價!C26 -> 0
A40: 加權目標價 | B40: =評價_DCF與目標價!C49 -> 22.032804

Sheet 檢查_版本紀錄
A1: 版本紀錄（基準情境目標價變化與原因）
A2: v2.9 以前檔名日期統一沿用 20260918，此處日期為實際修改日。v1.7 以前基準為 8 GW、v1.7 為 5 GW、v1.8 起為 5.6 GW；情境定義改變的版本不可直接比較。目標價以當版預設輸入計算（DCF 0 截斷）
A4: 版本 | B4: 日期 | C4: 主要變更 | D4: 基準目標價 | E4: 變動原因
A5: v0.4 | B5: 10-21 | C5: 工作單 v0.4a：Tokenomics 快照 v5.27 → v18.0（master 868e2cc）；k 隨新成本重算（k_長約 0.76 → 0.89，證據價格不變）；每 MW 建置成本改引用 TK_CapexTotal（依新增世代組合加權）；收入上限檢查改四層（比較層 Prod）；成本端評估表重算（主值不切換）；不改任何公司層假設 | D5: $22.0 | E5: 基準 $17.2 → $22.0、保守 $23.5 → $29.7、積極 $12.2 → $20.4，全部為 (c) 假設變更中的 Tokenomics 同步（① 換快照〔k 固定 0.76〕−4.66／−3.74／−5.94、② k 隨成本重算 +9.32／+7.72／+12.29、③ 資本支出改引用 TK +1.53／+0.80／+1.90、④ 上限檢查 0；保守／基準／積極）；時間推移、實際數、方法變更皆 0
A6: v0.3 | B6: 10-08 | C6: 工作單 v0.2a（第 2 輪）：每 MW 收入改以 Tokenomics 錨（IF_HoldEcon v5.27，官方快照取數）× 定價倍數 k；k 採 CoreWeave W4 r2 口徑（新增產能按長約價，k_長約 0.76，Nebius 合約未揭露容量只列敏感度）；容量與價格兩條情境軸分離；新增容量 × 價格 3 × 3、收入上限檢查、Q2 驗證拆解、公司實況驗證 | D6: $17.2 | E6: 基準 $61.7 → $17.2、保守 $35.2 → $23.5、積極 $154.5 → $12.2，全部為 (d) 方法變更（① 錨取代舊推導 k＝1、② 套用 k、③ 情境軸分離、④ 上限檢查 0、⑤ 新增產能按長約價、⑥ 公司合約 k 未採用 0）；時間推移、實際數、假設皆 0
A7: v0.2 | B7: 10-08 | C7: 工作單 v0.1d：標題改為 Nebius 專屬「預付款，能把 Backlog 變成現金嗎？」與動態副標；總結簡報改為 8 頁故事線＋附錄，一頁摘要移到最後；CRWV 論點句改寫；第 2 輪：MW 輸入改整數、DCF 常態化 FCF ≤ 0 不再判失效（終值以 0 計、保留權重） | D7: $61.7 | E7: 基準不變；保守 $63.8 → $35.2（(d) 方法：DCF 失效口徑）、積極 $154.6 → $154.5（(c) 假設：MW 整數）；時間推移、實際數皆 0
A8: v0.1 | B8: 10-07 | C8: 由 CRWV v4.5 模板建立；MW × 每 MW 收入主軸、預付款、融資瀑布、可轉債稀釋、其他事業與持股 | D8: $61.7 | E8: 首版（基準）；保守 $63.8、積極 $154.6，三者皆賣出

Sheet 來源
A1: 來源與標籤
A3: 標籤 | B3: 內容
A4: Interested-party | B4: Q2 2026 6-K（2026-08-12；外國私人發行人，季報未經查核）：營收 0.582bn（年增 454%；H1 0.981）；AI cloud 分部 0.575；調整後 EBITDA 0.236（AI cloud 0.286、49.7%）；GAAP 營損 −0.176；利息費用 0.119（含可轉債攤銷等非現金）；D&A 0.260；SBC 0.103（含 Eigen AI 收購 0.075）。
A5: Interested-party | B5: 資產負債（6/30）：現金 8.042、受限 1.056；PP&E 毛額 14.150（尚未啟用 7.836）；遞延營收 5.975；可轉債到期本金 10.042（帳面 8.499）、其他借款 0.047；營業租賃負債 1.625；已簽約未起租租賃 12.054；股東權益 10.341。
A6: Interested-party | B6: RPO 37.491bn：36% 於 24 個月內、40% 於 25–48 個月、其餘之後。客戶集中（Q2）：C 24%、D 21%、E 14%（名稱未揭露）。Microsoft 5 年 TCV 約 $17.4B；Meta $2.9B 與 $12B 專用＋最高 $15B 未售容量承購。
A7: Interested-party | B7: 現金流（H1）：CFO 4.504（遞延營收增加 4.395）；現金購置 8.130；收購 0.252；可轉債 4.338（2026-03）；NVIDIA 預付認股權證 2.0；ATM 淨額 2.811。
A8: Interested-party | B8: 期後 6-K：2026-07-10 資產擔保定期貸款 $775M（SOFR＋2.50%、2030-10-31 到期）；2026-08 可轉債 $5.75B（0.50% 2030-02 轉換價 $313.46、4.50% 2034-02 轉換價 $324.65）並以約 1,580 萬股交換 2029／2031 舊債各 $400M。
A9: Verified | B9: 市值（2026-09-21 收盤，S&P Global via stockanalysis.com）：NBIS 現價 $249.87（2026-10-06 收盤）、市值 63.81bn（2026-09-21）、流通 271.86m；CRWV 47.12；IREN 18.61；APLD 8.22；CORZ 5.90。淨負債取各公司最新申報：CRWV 30.01、IREN 1.70、APLD 3.37、CORZ 2.53。
A10: Interested-party | B10: 賣方目標價（S&P Global Market Intelligence（經 StockAnalysis.com），擷取 2026-10-07）：平均 $283.58、中位數 $300.00、區間 $84.00–$415.00（19 家）；共識評等 Buy。對照 MarketBeat（自行彙整，獨立於 S&P）：平均 $241.80（20 家，Moderate Buy）。數字為賣方意見；逐筆來源與日期見『輸入與假設』I 區。
A11: Interested-party | B11: 股東信（Q1／Q2 2026）：2026 營收 $3.0–3.4B、年底 ARR $7–9B、調整後 EBITDA 率約 40%；2026 年底合約電力 5 GW（目前 >3.5 GW）、connected 0.8–1.0 GW；2027 起每年部署 >1 GW；70% 合約含預付、覆蓋 50–60% 相關資本支出；2026 預付 >$9B；Q2 新約 ACV $20–25M/MW（只作對照）；回收期 1 年 10 個月（只作對照）。
A12: Interested-party | B12: 法說會（二手轉述）：2026 資本支出 $20–25B（Q1 由 $16–20B 上調、Q2 重申）。
A13: Verified | B13: FY2025 20-F（經查核）：營收 0.530、營業損益 −0.612、續營淨損益 0.010、D&A 0.418、2025 年底現金 3.678；歷年損益 FY23–FY25 取自 20-F XBRL（SEC companyfacts）。
