Workbook

Sheet README
A1: 美超微 Super Micro Computer（SMCI US）收支與估值模型 v0.1（AI 半導體 Project：伺服器組裝次產業，樣板＝wiwynn/、quanta/） 2026-10-25
A2: 版本：v0.1（初版）。美超微是 AI 伺服器品牌商（整機、整櫃、直接液冷），客戶含 neocloud、大型資料中心與企業，以買賣模式銷售含 NVIDIA、AMD GPU 的系統。商用 GPU 顆數與情境係數讀台積電模型，每顆系統價值讀橋接表（Tokenomics 整櫃價格），本模型只決定美超微的份額、毛利率與非 AI 營收。
A3: 模型命題：美超微 AI 營收＝商用 GPU 顆數（台積電模型，同字母情境）× 每顆系統價值（整櫃買方價 ÷ 每架 GPU）× 美超微有效份額（FY2027 以公司指引校準，FY2028 起依情境變動）；非 AI 營收以成長率推；毛利率＝AI 與非 AI 加權，AI 毛利率依情境調整。
A4: 核心問題：FY2027 營收指引 650～720 億美元（1Q 已初報約 190 億）能否轉成 GAAP EPS 約 5 美元、並守住約 11% 毛利率；現價約 33 美元、約 7 倍前瞻 P/E 的治理折價是否過深。
A6: 會計年度：FY(t)＝t−1 年 7 月～t 年 6 月；FY2026 已結束（實績錨點）。上游為日曆年：FY(t) 市場＝½ CY(t−1)＋½ CY(t)。金額：十億美元；EPS：GAAP 稀釋（美元）。口徑：歸屬母公司淨利＝扣除強制可轉換特別股股利後、歸屬普通股；2029-06 特別股轉換後（FY2030 起）股利消失、股數增加。
A8: 驅動因子 → 推導量（全部唯讀上游，不修改）
A9: AI 營收：tsmc 成品的商用 GPU 顆數（Blackwell、Hopper、Rubin、Rubin Ultra、AMD）× 情境顆數係數 × 每顆系統價值（橋接表：GB300 機架 430 萬 ÷ 72、VR200 機架 840 萬 ÷ 72 美元）＝商用 GPU 系統市場；× 美超微有效份額（FY2027＝（指引營收 − 非 AI）÷ 基準市場，Derived；FY2028 起 × 份額相對值，Assumed）。
A10: 非 AI：FY2026 殘差 × 成長率（Assumed）。毛利率：非 AI 15%（Assumed）；AI 毛利率＝FY2026 校準值＋情境調整（Interested-party／Assumed）。營業費用彈性 phi（Derived）。淨利：營業利益 × 淨利係數（稅與利息）− 特別股股利。
A11: 校準：FY2026 ＝ 全年實績（公司 2026-08-11）；FY2027 營收＝公司指引（A 上緣、B 中點、C 下緣）。不用券商數字（只在 Recon 對帳）。
A12: 估值：Val 第 0 節目標價＝0.5 × DCF 目標價（股東現金流＝EPS ×（1 − g／ROE），FY2027–32 明確期＋永續，r 10%、g 4%，三情境權重 0.3／0.5／0.2）＋0.5 × Comparable 目標價（Dell、HPE、緯穎、廣達、緯創前瞻 P/E 中位數 × 12 個月後前瞻 EPS（8／12 × FY2028＋4／12 × FY2029）；不含 A 股）；另列 Comparable 單獨目標價、市場共識目標價與差距拆解。十年 P/E 規則值 × FY2027 EPS 保留為參考（不是目標價）。情境對應：A＝順利、B＝平平、C＝不如預期（原為顆數情境）。本版未做先驗，無 Andy 合理 P/E 對照。
A13: 預估期間：FY2027–FY2029 由驅動因子推導；FY2030 起為收斂法，非驅動因子推導（營收年增由 FY2029 線性收斂到 fade_g、淨利率由 FY2029 特別股股利前淨利率收斂到 fade_m，FY2032 達到；PL 頁灰底）。
A14: 標記：Verified、Interested-party、Analogy、Assumed、Derived。SemiAnalysis 未使用。公司原文為新聞稿與財報說明稿；10-K 只經二手摘要；券商與資料商為 Interested-party。
A16: 已知限制：(1) 治理風險：2024 年會計師辭任與延遲申報、2026-03 前員工與共同創辦人因出口管制被起訴、FY2026 10-K 內控仍未有效（BDO 否定意見）；不改情境結構，以 Sens 案例（大客戶流失、淨利係數）呈現；(2) FY2027 份額以公司指引校準，FY2028 起份額、AI 毛利率為 Assumed；(3) 最大客戶占 FY2026 營收 28%、單一供應商占採購 63.1%；(4) 每顆系統價值以 NVIDIA 整櫃買方價近似，HGX 與 AMD 為 Analogy；(5) EPS 推現金流未扣營運資金（FY2026 營業現金流 −68 億美元），DCF 偏高；(6) 共識 EPS 為 non-GAAP，本模型為 GAAP；(7) 1Q FY27 財報（2026-11-03）後更新；R4 產業部署路徑未建。

Sheet In
A1: In — 輸入（藍字；基準欄 E，低 D、高 F）。金額：十億美元（US$B）；每顆系統價值：千美元；比例：%。每個輸入附兩個來源（找不到者寫「未找到」）；公司原文算一個。EPS 為 GAAP 稀釋、美元
A2: 標記：Verified／Interested-party／Analogy／Assumed／Derived；Analogy、Assumed 給低／高區間，不當點估計（放情境或 Sens）。SemiAnalysis 未使用。公司原文＝美超微新聞稿（8-K）、財報說明稿、10-K（經二手摘要）；公司的 AI 占比、指引與展望為 Interested-party；券商與資料商估計皆為 Interested-party。商用 GPU 顆數與情境係數讀台積電模型、每顆系統價值讀橋接表（唯讀）
A3: 鍵 | B3: 項目 | C3: 單位 | D3: 低 | E3: 基準 | F3: 高 | G3: 標記 | H3: 來源1 | I3: 來源2／說明
A4: A. 商用 GPU 顆數與每顆系統價值（讀 tsmc、markets/chip_bridge 成品；情境 A 基準，B／C 依顆數係數縮放）
A5: uo_26 | B5: GB300 世代商用 GPU 顆數 CY2026（Blackwell＋Hopper＋AMD MI355） | C5: 百萬顆 | E5: 6.65 | G5: Derived | H5: tsmc/dist/20261025_台積電模型_v0.3.xlsx｜In!E5:E36 | I5: 台積電模型八類加速器中 NVIDIA Blackwell、Hopper（2026 另含 AMD）；2029＝2028 × (1＋各類成長)
A6: uo_27 | B6: GB300 世代商用 GPU 顆數 CY2027（Blackwell＋Hopper） | C6: 百萬顆 | E6: 2.4 | G6: Derived | H6: 同上 | I6: 同上
A7: uo_28 | B7: GB300 世代商用 GPU 顆數 CY2028（Blackwell＋Hopper） | C7: 百萬顆 | E7: 0.5 | G7: Derived | H7: 同上 | I7: 同上
A8: uo_29 | B8: GB300 世代商用 GPU 顆數 CY2029（Blackwell＋Hopper） | C8: 百萬顆 | E8: 0.25 | G8: Derived | H8: 同上 | I8: 同上
A9: un_26 | B9: Rubin 世代商用 GPU 顆數 CY2026（Rubin＋Rubin Ultra） | C9: 百萬顆 | E9: 1.7 | G9: Derived | H9: tsmc/dist/20261025_台積電模型_v0.3.xlsx｜In!E5:E36 | I9: 同上
A10: un_27 | B10: Rubin 世代商用 GPU 顆數 CY2027（Rubin＋Rubin Ultra＋AMD MI450） | C10: 百萬顆 | E10: 8.8 | G10: Derived | H10: 同上 | I10: AMD 自 2027 年起改計 Rubin 世代價值（MI450 整櫃；Analogy）
A11: un_28 | B11: Rubin 世代商用 GPU 顆數 CY2028（Rubin＋Rubin Ultra＋AMD MI450） | C11: 百萬顆 | E11: 11 | G11: Derived | H11: 同上 | I11: 同上
A12: un_29 | B12: Rubin 世代商用 GPU 顆數 CY2029（Rubin＋Rubin Ultra＋AMD MI450） | C12: 百萬顆 | E12: 12.65 | G12: Derived | H12: 同上 | I12: 同上
A13: ut_26 | B13: 全部 AI 加速器顆數 CY2026（對照） | C13: 百萬顆 | E13: 15.2 | G13: Derived | H13: tsmc/dist/20261025_台積電模型_v0.3.xlsx｜In!E5:E36 | I13: 八類合計；商用 GPU 以外為 TPU、Trainium、其他 ASIC（美超微不銷售）
A14: ut_27 | B14: 全部 AI 加速器顆數 CY2027（對照） | C14: 百萬顆 | E14: 23.7 | G14: Derived | H14: 同上 | I14: 同上
A15: ut_28 | B15: 全部 AI 加速器顆數 CY2028（對照） | C15: 百萬顆 | E15: 26.5 | G15: Derived | H15: 同上 | I15: 同上
A16: ut_29 | B16: 全部 AI 加速器顆數 CY2029（對照） | C16: 百萬顆 | E16: 30.15 | G16: Derived | H16: 同上 | I16: 同上
A17: v_gb | B17: 每顆系統價值：GB300 世代（整櫃買方價 ÷ 每架 GPU 封裝數） | C17: 千美元/顆 | E17: =4.3/72*1000 -> 59.722222 | G17: Derived | H17: markets/chip_bridge/dist/20261023_晶片內容橋接表_v0.2.1.xlsx｜In!E5（GB300）、H5（VR200） | I17: Tokenomics v20.1 機架單價 4.3 百萬美元 ÷ 72 顆（經橋接表；唯讀）；HGX 八卡伺服器與 AMD MI355 以同值近似（Analogy）
A18: v_vr | B18: 每顆系統價值：Rubin 世代（VR200 整櫃買方價 ÷ 每架 GPU 封裝數） | C18: 千美元/顆 | E18: =8.4/72*1000 -> 116.66667 | G18: Derived | H18: markets/chip_bridge/dist/20261023_晶片內容橋接表_v0.2.1.xlsx｜In!E5（GB300）、H5（VR200） | I18: 機架單價 8.4 百萬美元 ÷ 72 顆；Rubin Ultra 與 AMD MI450 未另訂（Analogy：同 VR200）
A19: vpg_28 | B19: 每顆系統價值 2028 ÷ 2027（Rubin 世代） | C19: x | D19: 0.85 | E19: 1 | F19: 1.2 | G19: Assumed | H19: Rubin Ultra（Kyber）整櫃價格：未找到 | I19: 與廣達、緯穎模型的每 GW 價值變動同區間
A20: vpg_29 | B20: 每顆系統價值 2029 ÷ 2027（Rubin 世代） | C20: x | D20: 0.85 | E20: 1 | F20: 1.2 | G20: Assumed | H20: 同上 | I20: —
A21: um28_A | B21: 情境 A：2028 顆數 ÷ 基準 | C21: x | E21: 1 | G21: Assumed | H21: tsmc/dist/20261025_台積電模型_v0.3.xlsx｜In!E37 | I21: A＝順利（基準）；B＝平平（AI 資本支出消化）；C＝不如預期（明顯下修）；與台積電、廣達、緯穎模型相同
A22: um29_A | B22: 情境 A：2029 顆數 ÷ 基準 | C22: x | E22: 1 | G22: Assumed | H22: tsmc/dist/20261025_台積電模型_v0.3.xlsx｜In!E38 | I22: 同上
A23: um28_B | B23: 情境 B：2028 顆數 ÷ 基準 | C23: x | E23: 0.8 | G23: Assumed | H23: tsmc/dist/20261025_台積電模型_v0.3.xlsx｜In!E39 | I23: A＝順利（基準）；B＝平平（AI 資本支出消化）；C＝不如預期（明顯下修）；與台積電、廣達、緯穎模型相同
A24: um29_B | B24: 情境 B：2029 顆數 ÷ 基準 | C24: x | E24: 0.85 | G24: Assumed | H24: tsmc/dist/20261025_台積電模型_v0.3.xlsx｜In!E40 | I24: 同上
A25: um28_C | B25: 情境 C：2028 顆數 ÷ 基準 | C25: x | E25: 0.6 | G25: Assumed | H25: tsmc/dist/20261025_台積電模型_v0.3.xlsx｜In!E41 | I25: A＝順利（基準）；B＝平平（AI 資本支出消化）；C＝不如預期（明顯下修）；與台積電、廣達、緯穎模型相同
A26: um29_C | B26: 情境 C：2029 顆數 ÷ 基準 | C26: x | E26: 0.6 | G26: Assumed | H26: tsmc/dist/20261025_台積電模型_v0.3.xlsx｜In!E42 | I26: 同上
A27: mf | B27: AI 部署係數（Sens 用；CY2027 起） | C27: x | D27: 0.8 | E27: 1 | F27: 1.2 | G27: Assumed | H27: 台積電模型 CY2027 商用 GPU 顆數約 1.4 倍（8.35 → 11.2 百萬顆） | I27: ±20%
A28: B. 營收結構、份額（FY2027 以公司指引校準）
A29: ais_25 | B29: FY2025 AI GPU 平台 ÷ 營收 | C29: % | D29: 0.65 | E29: 0.7 | F29: 0.75 | G29: Interested-party | H29: 公司：FY2025 AI GPU 平台占營收逾七成（法說；原文未逐字取得） | I29: 量化第二來源：未找到
A30: ais_1h | B30: 1H FY26（2025-07～12）AI GPU 平台 ÷ 營收 | C30: % | D30: 0.75 | E30: 0.85 | F30: 0.9 | G30: Assumed | H30: Futurum（2Q FY26）：2Q FY26 營收由 GB300 NVL72 與 AMD MI355 量產帶動（未給比例） | I30: 公司揭露比例：未找到
A31: ais_q3 | B31: 3Q FY26（2026-01～03）AI ÷ 營收 | C31: % | D31: 0.78 | E31: 0.8 | F31: 0.85 | G31: Interested-party | H31: 公司 4Q FY26 財報說明稿：3Q 逾 80%（公司） | I31: MarketBeat 2026-08-11（法說重點）：同
A32: ais_q4 | B32: 4Q FY26（2026-04～06）AI ÷ 營收 | C32: % | D32: 0.55 | E32: 0.6 | F32: 0.65 | G32: Interested-party | H32: 公司 4Q FY26 財報說明稿：約 60%，專案出貨時點使比重下降（公司） | I32: MarketBeat 2026-08-11（法說重點）：同；公司預期未來逾 80% 營收與 AI 相關、純 AI 約 60–70%
A33: g27 | B33: FY2027 營收指引（情境 A＝上緣、B＝中點、C＝下緣） | C33: US$B | D33: 65 | E33: 68.5 | F33: 72 | G33: Interested-party | H33: 公司 FY2026 第四季新聞稿（2026-08-11）：FY2027 營收 650～720 億美元（公司，2026-08-11） | I33: 公司 1Q FY27 初步營運更新（2026-10-20）：1Q FY27 初步營收 185～195 億美元，高於原指引 145～155 億；全年指引未調整（公司，2026-10-20）
A34: rel_28 | B34: 美超微份額 FY2028 ÷ FY2027（A＝高、B＝基準、C＝低） | C34: x | D34: 0.85 | E34: 0.95 | F34: 1 | G34: Assumed | H34: Dell、HPE 與 ODM 直供（廣達、緯創、鴻海）爭取 neocloud 與企業訂單；4Q FY26 逾 600 億美元新訂單（公司） | I34: 最大客戶占 FY2026 營收 28%（公司說明稿）：大客戶轉單為下檔
A35: rel_29 | B35: 美超微份額 FY2029 ÷ FY2027 | C35: x | D35: 0.8 | E35: 0.92 | F35: 1 | G35: Assumed | H35: 同上 | I35: —
A36: g_nai27 | B36: 非 AI（企業、儲存、邊緣）營收年增 FY2027 | C36: % | D36: 0 | E36: 0.15 | F36: 0.3 | G36: Assumed | H36: 公司 4Q FY26 財報說明稿：企業與通路營收 4Q FY26 年增 172%（含 AI，公司） | I36: 非 AI 營收分項：未找到；FY2026 非 AI 為殘差（Q 頁）
A37: g_nai28 | B37: 非 AI 營收年增 FY2028 | C37: % | D37: -0.05 | E37: 0.08 | F37: 0.2 | G37: Assumed | H37: 同上 | I37: —
A38: g_nai29 | B38: 非 AI 營收年增 FY2029 | C38: % | D38: -0.05 | E38: 0.06 | F38: 0.15 | G38: Assumed | H38: 同上 | I38: —
A39: C. 毛利率（A 最有利、C 最不利）
A40: gm_nai | B40: 非 AI 營收毛利率 | C40: % | D40: 0.13 | E40: 0.15 | F40: 0.18 | G40: Assumed | H40: FY2023（AI 占比低）GAAP 毛利率約 18%（公司年報，stockanalysis 損益表：毛利 1,283 ÷ 營收 7,123） | I40: 部門別毛利率：未找到；公司 DCBBS 目標毛利率 20%＋（Futurum 轉述）
A41: dgm_27 | B41: FY2027 AI 毛利率 − FY2026 校準值（A＝高、B＝基準、C＝低） | C41: pt | D41: -0.005 | E41: 0.005 | F41: 0.015 | G41: Interested-party | H41: 公司 1Q FY27 初步營運更新（2026-10-20）：1Q FY27 初步毛利率 12.0%–12.5%，客戶與產品組合（公司） | I41: 公司 4Q FY26 財報說明稿：4Q FY26 17.6%（non-GAAP）約四分之三來自組合與遞延至 FY27 的合約、四分之一來自關稅與存貨跌價回轉（可能不重複）
A42: dgm_28 | B42: FY2028–FY2029 AI 毛利率 − FY2026 校準值 | C42: pt | D42: -0.015 | E42: 0.003 | F42: 0.015 | G42: Assumed | H42: C：Dell、ODM 價格競爭與 GPU 轉手比重上升；A：液冷與 DCBBS 整體解決方案 | I42: FY2024 13.8% → FY2025 11.1% → FY2026 10.8%（GAAP；stockanalysis 損益表）
A43: D. 1Q FY27 初步數字（Recon 對帳用）
A44: q1_rev | B44: 1Q FY27（2026-07～09）初步營收 | C44: US$B | D44: 18.5 | E44: 19 | F44: 19.5 | G44: Interested-party | H44: 公司 1Q FY27 初步營運更新（2026-10-20）：185～195 億美元（公司，未經審計） | I44: Simply Wall St：同（2026-10）
A45: q1_gm | B45: 1Q FY27 初步毛利率 | C45: % | D45: 0.12 | E45: 0.1225 | F45: 0.125 | G45: Interested-party | H45: 公司 1Q FY27 初步營運更新（2026-10-20）：12.0%–12.5%（公司） | I45: 原指引 10.4%–10.8%（4Q FY26 財報說明稿）
A46: E. 營業費用、淨利係數、特別股與股數（FY2027 起）
A47: phi | B47: 營業費用成長對營收成長的彈性 | C47: x | D47: 0.3 | E47: 0.4 | F47: 0.6 | G47: Derived | H47: 公司 4Q FY26 財報說明稿：1Q FY27 GAAP 營業費用約 4.53 億美元（年化約 18.1 億，較 FY2026 14.57 億 +24%） | I47: FY2026 實測：營業費用 +24%、營收 +78%（Q 頁），彈性約 0.3
A48: opx_adj | B48: 營業費用額外占營收比（Sens 用；基準 0） | C48: pt | D48: -0.002 | E48: 0 | F48: 0.002 | G48: Assumed | H48: 無 | I48: 營益率約 8%，±0.2 個百分點約 ±2.5% 的營業利益
A49: nio_f | B49: 淨利（特別股股利前）÷ 營業利益 | C49: % | D49: 0.68 | E49: 0.75 | F49: 0.8 | G49: Derived | H49: FY2026 2,230.5 ÷ 2,770.5＝0.805；稅率 FY2026 19.9%、1Q FY27 指引 20.1%（公司） | I49: 1Q FY27 指引隱含約 0.68（GAAP EPS 0.89–0.98 × 7.45 億股＋特別股股利，÷ 營收 150 億 × 毛利率 10.6% − 營業費用 4.53 億）：銀行借款 40.6 億、可轉債 46.6 億美元的利息（Derived）
A50: pref_div | B50: 強制可轉換特別股股利（年） | C50: US$B | E50: =86.25*50/1000*0.07 -> 0.301875 | G50: Derived | H50: 公司 2026-06-11 股權與特別股定價公告：7,500 萬股存託股＋超額配售 1,125 萬股、每股 50 美元、股利率 7.0%，2029-06-01 強制轉換（公司） | I50: 公司 FY2026 第四季新聞稿（2026-08-11）：4Q FY26 募得淨額 56 億美元，其中強制可轉換特別股 42 億（公司）；超額配售全數執行為 Assumed
A51: sh27 | B51: FY2027 GAAP 稀釋股數 | C51: 十億股 | E51: 0.745 | G51: Interested-party | H51: 公司 FY2026 第四季新聞稿（2026-08-11）：1Q FY27 指引 GAAP 稀釋股數 7.45 億（公司） | I51: stockanalysis 統計頁：流通股數 6.5697 億（2026-10-24）
A52: sh_g | B52: 股數年變動（員工股票報酬、可轉債） | C52: % | D52: 0 | E52: 0.01 | F52: 0.03 | G52: Assumed | H52: FY2025 6.284 → FY2026 6.973 億股（GAAP 稀釋，含 6 月增資；公司） | I52: 1Q FY27 指引股票報酬費用約 1.06 億美元／季（公司）
A53: conv_sh | B53: 特別股轉換新增股數（FY2030 起；最低～最高轉換率中點） | C53: 十億股 | D53: =86.25*1.5152/1000 -> 0.130686 | E53: =86.25*(1.5152+1.8182)/2/1000 -> 0.14375288 | F53: =86.25*1.8182/1000 -> 0.15681975 | G53: Derived | H53: 公司 2026-06-11 股權與特別股定價公告：每股存託股轉換 1.5152～1.8182 股普通股（公司） | I53: 轉換後特別股股利消失；FY2029 股利以全年計（實際 2029-06 轉換，差約一個月）
A54: sbc_ps | B54: GAAP → non-GAAP EPS 調整（每股；Recon 對共識用） | C54: US$ | E54: =(0.106-0.032)*4/sh27 -> 0.39731544 | G54: Derived | H54: 公司 FY2026 第四季新聞稿（2026-08-11）：1Q FY27 股票報酬約 1.06 億美元、稅效果 0.32 億（公司） | I54: FY2026 non-GAAP 3.63 − GAAP 3.26＝0.37（公司）
A55: F. 共識（只作 Recon 對帳，不作校準；共識 EPS 為 non-GAAP）
A56: c_rev27 | B56: 共識 FY2027 營收 | C56: US$B | D56: 63.5 | E56: 70 | F56: 82 | G56: Interested-party | H56: stockanalysis 預測頁：平均 700 億美元（15 位，低 635、高 820；2026-10-22） | I56: Yahoo Finance 分析頁：同 700 億（15 位）
A57: c_rev28 | B57: 共識 FY2028 營收 | C57: US$B | D57: 70.84 | E57: 81.4 | F57: 92 | G57: Interested-party | H57: Yahoo Finance 分析頁：平均 814 億美元（15 位） | I57: stockanalysis FY2028 需付費：未找到
A58: c_eps27 | B58: 共識 FY2027 EPS（non-GAAP） | C58: US$ | D58: 3.5 | E58: 4.67 | F58: 6.4 | G58: Interested-party | H58: stockanalysis 預測頁：4.67（15 位，低 3.50、高 6.40） | I58: Yahoo Finance 分析頁：4.67（18 位）
A59: c_eps28 | B59: 共識 FY2028 EPS（non-GAAP） | C59: US$ | E59: 5.59 | G59: Interested-party | H59: Yahoo Finance 分析頁：5.59（17 位） | I59: 第二來源：未找到（tickflow 季度數字前後不一致，不採用）
A60: G. 價格與市場倍數
A61: px | B61: 股價（2026-10-23 收盤） | C61: US$ | E61: 32.94 | G61: Interested-party | H61: stockanalysis 統計頁：10-23 收盤 32.94 | I61: fullratio P/E：10-23 價格 32.94、近 12 月 EPS 3.65
A62: pe_ttm | B62: 近 12 月 P/E（stockanalysis，10-23） | C62: x | E62: 10.12 | G62: Interested-party | H62: stockanalysis 統計頁 | I62: fullratio 9.02（以 non-GAAP EPS）
A63: fpe | B63: 前瞻 P/E（stockanalysis，10-23） | C63: x | E63: 7.06 | G63: Interested-party | H63: stockanalysis 統計頁 | I63: 以 non-GAAP 共識 EPS
A64: cons_feps | B64: 共識前瞻 12 月 EPS（10-23 價格 ÷ 前瞻 P/E；non-GAAP） | C64: US$ | E64: =px/fpe -> 4.6657224 | G64: Derived | H64: stockanalysis 前瞻 P/E 7.06（2026-10-23） | I64: ≈ 共識 FY2027 EPS 4.67
A65: cons_tp | B65: 市場共識目標價（賣方平均） | C65: US$ | D65: 15 | E65: 43.27 | F65: 60 | G65: Interested-party | H65: stockanalysis 預測頁：18 位平均 43.27、中位數 45、最低 15、最高 60（S&P Global，2026-10-22） | I65: tickflow 預測頁：25 位平均 41.44（2026-10-24）；Simply Wall St 08-12：41.75（16 位）
A66: nim10 | B66: 十年平均淨利率（FY2016–FY2025，淨利 ÷ 營收） | C66: % | E66: =AVERAGE(72/2225,67/2485,46/3360,72/3500,84/3339,112/3557,285/5196,640/7123,1153/14989,1049/21972) -> 0.041959299 | G66: Derived | H66: Macrotrends 營收、Macrotrends 淨利：各年營收與淨利（百萬美元；FY2016 2,225／72 … FY2023 7,123／640） | I66: stockanalysis 損益表：FY2024 14,989／1,153、FY2025 21,972／1,049
A67: H. 目標價與收斂法參數（黃底；Assumed，Andy 可改）
A68: tp_wA | B68: 目標價情境權重 A（A 順利／B 平平／C 不如預期） | C68: % | E68: 0.3 | G68: Assumed | H68: Andy 可改（工作單 2026-10-25 預設 A 0.3／B 0.5／C 0.2） | I68: 三者合計應為 100%（Val 頁第 0 節列示）
A69: tp_wB | B69: 目標價情境權重 B（A 順利／B 平平／C 不如預期） | C69: % | E69: 0.5 | G69: Assumed | H69: Andy 可改（工作單 2026-10-25 預設 A 0.3／B 0.5／C 0.2） | I69: 三者合計應為 100%（Val 頁第 0 節列示）
A70: tp_wC | B70: 目標價情境權重 C（A 順利／B 平平／C 不如預期） | C70: % | E70: 0.2 | G70: Assumed | H70: Andy 可改（工作單 2026-10-25 預設 A 0.3／B 0.5／C 0.2） | I70: 三者合計應為 100%（Val 頁第 0 節列示）
A71: tp_r | B71: 折現率／要求報酬 | C71: % | E71: 0.1 | G71: Assumed | H71: Andy 可改（工作單預設 10%；美、台、日、韓同一值） | I71: DCF 折現率；DCF 情境價值 ×(1＋r) 推到 12 個月後。治理與會計風險不另加折現率（見 Sens、README）
A72: tp_g | B72: 長期成長率 | C72: % | E72: 0.04 | G72: Assumed | H72: Andy 可改（工作單預設 4%） | I72: DCF 永續成長率；FY2032 收斂目標（情境 B）
A73: tp_roe | B73: ROE（近三年平均，FY2024–26） | C73: % | E73: =AVERAGE(0.312,0.179,0.2147) -> 0.23523333 | G73: Derived | H73: stockanalysis 比率頁：ROE FY2024 31.20%、FY2025 17.90%、FY2026 21.47% | I73: 單一來源；Simply Wall St 三年後預測 22.3%
A74: tp_w_dcf | B74: 目標價中 DCF 的權重；其餘為 Comparable | C74: % | E74: 0.5 | G74: Assumed | H74: Andy 可改（Andy 2026-10-25 11:53 定 DCF／Comparable 各半） | I74: —
A75: fade_gA | B75: 情境 A：FY2032 營收年增收斂目標（tp_g＋2pt） | C75: % | E75: =tp_g+0.02 -> 0.06 | G75: Assumed | H75: 工作單 2026-10-25 11:20 收斂法 | I75: FY2030 起由 FY2029 年增線性收斂
A76: fade_gB | B76: 情境 B：FY2032 營收年增收斂目標（＝tp_g） | C76: % | E76: =tp_g -> 0.04 | G76: Assumed | H76: 同上 | I76: —
A77: fade_gC | B77: 情境 C：FY2032 營收年增收斂目標（tp_g−2pt） | C77: % | E77: =tp_g-0.02 -> 0.02 | G77: Assumed | H77: 同上 | I77: —
A78: fade_mA | B78: 情境 A：FY2032 淨利率收斂目標（＝情境 A FY2029 特別股股利前淨利率） | C78: % | E78: =PL!G95 -> 0.070114144 | G78: Derived | H78: PL 頁情境 A FY2029（公式於建置時連結）；FY2030 起特別股已轉換，股利消失 | I78: —
A79: fade_mB | B79: 情境 B：FY2032 淨利率收斂目標（情境 B FY2029 與十年平均的中點） | C79: % | E79: =(PL!G137+nim10)/2 -> 0.051388206 | G79: Derived | H79: PL 頁情境 B FY2029、In 頁 nim10 | I79: —
A80: fade_mC | B80: 情境 C：FY2032 淨利率收斂目標（＝十年平均淨利率） | C80: % | E80: =nim10 -> 0.041959299 | G80: Derived | H80: In 頁 nim10 | I80: —

Sheet Q
A1: Q — 實績與 FY2026 錨點（十億美元；EPS 為美元、GAAP 稀釋；股數為十億股）。藍字＝輸入；黑字＝公式。會計年度 FY2026＝2025-07～2026-06。實績取自美超微新聞稿（8-K）與財報說明稿
A2: FY2026 錨點＝全年實績（公司 2026-08-11 公布，10-K 2026-08-31 申報；新聞稿標示未經審計，需待審計確認）。3Q 營收、營業費用、營業利益、淨利＝全年 − 1H − 4Q（Derived）；毛利＝營業利益＋營業費用。股數＝淨利 ÷ 公司揭露稀釋 EPS（可轉債加回使其與揭露稀釋股數略有差異）
A3: 項目 | B3: FY2025A | C3: 1H FY26（2025-07～12） | D3: 3Q FY26（2026-01～03） | E3: 4Q FY26（2026-04～06） | F3: FY2026A（錨點） | G3: 標記 | H3: 來源1（公司） | I3: 來源2／說明
A4: 營收 | B4: 21.972 | C4: 17.7003 | D4: =39.063-C4-E4 -> 10.2427 | E4: 11.12 | F4: =SUM(C4:E4) -> 39.063 | G4: Verified／Derived（3Q） | H4: 公司 FY2026 第四季新聞稿（2026-08-11）；1H：公司 2Q FY26 新聞稿（8-K） | I4: 1Q FY26 5.0178、2Q 12.6825（8-K）；FY2026 39.063（stockanalysis）
A5: 毛利（＝營業利益＋營業費用） | B5: =B8+B7 -> 2.4299 | C5: =C8+C7 -> 1.266 | D5: =D8+D7 -> 1.0186 | E5: =E8+E7 -> 1.9427 | F5: =SUM(C5:E5) -> 4.2273 | G5: Derived | H5: 公司 FY2026 第四季新聞稿（2026-08-11）；1H：公司 2Q FY26 新聞稿（8-K） | I5: GAAP 毛利率：FY2025 11.1%、1H 7.2%、3Q 9.9%、4Q 17.5%、FY2026 10.8%（公司）
A6: 毛利率 | B6: =B5/B4 -> 0.11059075 | C6: =C5/C4 -> 0.071524211 | D6: =D5/D4 -> 0.099446435 | E6: =E5/E4 -> 0.17470324 | F6: =F5/F4 -> 0.10821749 | G6: Derived | H6: — | I6: —
A7: 營業費用（GAAP） | B7: 1.1769 | C7: 0.6094 | D7: =1.4568-C7-E7 -> 0.3928 | E7: 0.4546 | F7: =SUM(C7:E7) -> 1.4568 | G7: Verified／Derived（3Q） | H7: 公司 FY2026 第四季新聞稿（2026-08-11）；1H：公司 2Q FY26 新聞稿（8-K） | I7: FY2026 1.4568（公司）
A8: 營業利益 | B8: 1.253 | C8: 0.6566 | D8: =2.7705-C8-E8 -> 0.6258 | E8: 1.4881 | F8: =SUM(C8:E8) -> 2.7705 | G8: Verified／Derived（3Q） | H8: 公司 FY2026 第四季新聞稿（2026-08-11）；1H：公司 2Q FY26 新聞稿（8-K） | I8: FY2026 2.7705（公司）
A9: 營業利益率 | B9: =B8/B4 -> 0.057027125 | C9: =C8/C4 -> 0.037095416 | D9: =D8/D4 -> 0.061097172 | E9: =E8/E4 -> 0.13382194 | F9: =F8/F4 -> 0.070923892 | G9: Derived | H9: — | I9: —
A10: 歸屬母公司淨利（GAAP） | B10: 1.0489 | C10: 0.5688 | D10: =2.2305-C10-E10 -> 0.4835 | E10: 1.1782 | F10: =SUM(C10:E10) -> 2.2305 | G10: Verified／Derived（3Q） | H10: 公司 FY2026 第四季新聞稿（2026-08-11）；1H：公司 2Q FY26 新聞稿（8-K） | I10: 3Q 4.83 億（公司說明稿）；stockanalysis FY2026 淨利 2,196（可能已扣特別股股利，未採用）
A11: 淨利 ÷ 營業利益（含業外、稅） | B11: =B10/B8 -> 0.83711093 | C11: =C10/C8 -> 0.86628084 | D11: =D10/D8 -> 0.77261106 | E11: =E10/E8 -> 0.79174787 | F11: =F10/F8 -> 0.80508933 | G11: Derived | H11: — | I11: —
A12: 股數（十億股；＝淨利 ÷ 揭露稀釋 EPS） | B12: =B10/B14 -> 0.62434524 | C12: =C10/C14 -> 0.66139535 | D12: =D10/D14 -> 0.67152778 | E12: =E10/E14 -> 0.72728395 | F12: =F10/F14 -> 0.68420245 | G12: Derived | H12: 公司 FY2026 第四季新聞稿（2026-08-11）；1H：公司 2Q FY26 新聞稿（8-K） | I12: 淨利 ÷ 揭露 EPS；FY2026 揭露稀釋股數 6.973 億（第 15 列）
A13: EPS（GAAP 稀釋） | B13: =B10/B12 -> 1.68 | C13: =C10/C12 -> 0.86 | D13: =D10/D12 -> 0.72 | E13: =E10/E12 -> 1.62 | F13: =F10/F12 -> 3.26 | G13: Derived | H13: 淨利 ÷ 股數 | I13: —
A14: 公司揭露稀釋 EPS（GAAP） | B14: 1.68 | C14: 0.86 | D14: 0.72 | E14: 1.62 | F14: =3.26 -> 3.26 | G14: Verified | H14: 公司 FY2026 第四季新聞稿（2026-08-11）；1H：公司 2Q FY26 新聞稿（8-K） | I14: non-GAAP：FY2025 2.06、FY2026 3.63、4Q 1.70（公司）
A15: 公司揭露稀釋股數（對照） | B15: 0.6284 | C15: 0.6741 | D15: 0.692 | E15: 0.705 | F15: =0.6973 -> 0.6973 | G15: Verified | H15: 公司 FY2026 第四季新聞稿（2026-08-11）；1H：公司 2Q FY26 新聞稿（8-K） | I15: 4Q 7.050 億、3Q 6.92 億（公司說明稿）
A16: AI GPU 平台營收（＝營收 × AI 占比） | B16: =B4*ais_25 -> 15.3804 | C16: =C4*ais_1h -> 15.045255 | D16: =D4*ais_q3 -> 8.19416 | E16: =E4*ais_q4 -> 6.672 | F16: =SUM(C16:E16) -> 29.911415 | G16: Derived／Interested-party | H16: 公司比例（In 頁 B 節） | I16: AI 營收金額未揭露：未找到
A17: 非 AI（企業、儲存、邊緣等） | B17: =B4-B16 -> 6.5916 | C17: =C4-C16 -> 2.655045 | D17: =D4-D16 -> 2.04854 | E17: =E4-E16 -> 4.448 | F17: =SUM(C17:E17) -> 9.151585 | G17: Derived | H17: — | I17: —
A19: FY2026 錨點的檢查（參考；校準未使用券商數字）
A20: FY2026 營收年增 | B20: =F4/B4-1 -> 0.77785363
A21: FY2026 營業費用年增 | B21: =F7/B7-1 -> 0.23782819
A22: 營業費用彈性（營業費用年增 ÷ 營收年增；In 頁 phi 的對照） | B22: =B21/B20 -> 0.30574929
A23: FY2026 AI 占營收（Derived；1H、3Q、4Q 加權） | B23: =F16/F4 -> 0.76572242
A24: FY2026 毛利率（不含 4Q；1H＋3Q） | B24: =(C5+D5)/(C4+D4) -> 0.081759296
A25: 2026-01～06（2H FY26）AI GPU 平台營收（份額校準用） | B25: =D16+E16 -> 14.86616
A26: FY2026 EPS 自算 − 公司揭露（應為 0） | B26: =F13-F14 -> 0

Sheet Units
A1: Units — 商用 GPU 系統市場、美超微份額與隱含出貨（情境 A）。前五列為日曆年（CY），其後為美超微會計年度（FY，7 月～6 月）。顆數讀台積電模型、每顆系統價值讀橋接表（唯讀）
A3: 項目 | B3: 單位 | C3: 2026 | D3: 2027 | E3: 2028 | F3: 2029 | G3: 說明
A4: CY：GB300 世代商用 GPU 顆數 | B4: 百萬顆 | C4: =PL!D63 -> 6.65 | D4: =PL!E63 -> 2.4 | E4: =PL!F63 -> 0.5 | F4: =PL!G63 -> 0.25 | G4: tsmc 成品
A5: CY：Rubin 世代商用 GPU 顆數 | B5: 百萬顆 | C5: =PL!D64 -> 1.7 | D5: =PL!E64 -> 8.8 | E5: =PL!F64 -> 11 | F5: =PL!G64 -> 12.65 | G5: tsmc 成品
A6: CY：全部 AI 加速器顆數（對照） | B6: 百萬顆 | C6: =ut_26 -> 15.2 | D6: =ut_27 -> 23.7 | E6: =ut_28 -> 26.5 | F6: =ut_29 -> 30.15 | G6: 含 TPU、Trainium、其他 ASIC
A7: CY：每顆系統價值（Rubin 世代） | B7: 千美元/顆 | C7: =PL!D66 -> 116.66667 | D7: =PL!E66 -> 116.66667 | E7: =PL!F66 -> 116.66667 | F7: =PL!G66 -> 116.66667 | G7: GB300 世代為 In 頁 v_gb
A8: CY：商用 GPU 系統市場 | B8: US$B | C8: =PL!D67 -> 595.48611 | D8: =PL!E67 -> 1170 | E8: =PL!F67 -> 1313.1944 | F8: =PL!G67 -> 1490.7639 | G8: 顆數 × 每顆系統價值
A9: FY：商用 GPU 系統市場（½ 前一 CY＋½ 當年 CY） | B9: US$B | D9: =PL!E68 -> 882.74306 | E9: =PL!F68 -> 1241.5972 | F9: =PL!G68 -> 1401.9792 | G9: FY2026 需 CY2025（上游無），不列
A10: FY：美超微有效份額 | B10: % | C10: =PL!D70 -> 0.049929494 | D10: =PL!E73 -> 0.069641644 | E10: =PL!F73 -> 0.069641644 | F10: =PL!G73 -> 0.069641644 | G10: FY2026 欄＝2H FY26 校準值；FY2027 起以指引校準
A11: FY：美超微 AI GPU 平台營收 | B11: US$B | C11: =PL!D75 -> 29.911415 | D11: =PL!E75 -> 61.475677 | E11: =PL!F75 -> 86.466871 | F11: =PL!G75 -> 97.636133
A12: FY：隱含美超微商用 GPU 出貨 | B12: 百萬顆 | D12: =PL!E81 -> 0.68074707 | E12: =PL!F81 -> 0.79043265 | F12: =PL!G81 -> 0.84962805 | G12: AI 營收 ÷ 每顆平均系統價值
A13: FY：AI 毛利率 | B13: % | C13: =PL!D84 -> 0.095433875 | D13: =PL!E84 -> 0.11043388 | E13: =PL!F84 -> 0.11043388 | F13: =PL!G84 -> 0.11043388 | G13: FY2026 為校準值
A14: FY：毛利率 | B14: % | C14: =PL!D86 -> 0.10821749 | D14: =PL!E86 -> 0.1162173 | E14: =PL!F86 -> 0.11503067 | F14: =PL!G86 -> 0.11478
A16: 讀法：美超微賣的是含 GPU 的整機與整櫃（品牌商，買賣模式），營收隨商用 GPU 顆數 × 每顆系統價值放大；份額在 2H FY26 約數個百分點，FY2027 指引隱含份額明顯上升（大量新訂單）。FY2028 起份額相對值是 Assumed，大客戶（FY2026 占 28%）轉單是最大下檔。

Sheet PL
A1: PL — 美超微損益（十億美元；EPS 美元、GAAP 稀釋；歸屬母公司＝扣除特別股股利後）。FY2025A、FY2026A 實績（FY2026 為錨點），FY2027 起為模型。會計年度 7 月～6 月：FY(t) 市場＝½ CY(t−1)＋½ CY(t)。三情境各一個完整推導區塊（本頁下方），頂端為摘要
A2: 灰底＝FY2030–FY2032 收斂法（上游只到 CY2029，FY2030 需 CY2030）：營收年增線性收斂到 fade_g、淨利率線性收斂到 fade_m（In 頁 H 節），非驅動因子推導
A3: 情境／項目 | B3: 單位 | C3: FY2025A | D3: FY2026A（錨點） | E3: FY2027 | F3: FY2028 | G3: FY2029 | H3: FY2030（收斂） | I3: FY2031（收斂） | J3: FY2032（收斂） | K3: 說明
A4: 情境 A
A5: 營收 | B5: US$B | C5: =C78 -> 21.972 | D5: =D78 -> 39.063 | E5: =E78 -> 72 | F5: =F78 -> 97.83314 | G5: =G78 -> 109.68438 | H5: =H78 -> 120.73598 | I5: =I78 -> 130.44062 | J5: =J78 -> 138.26706
A6: 營收年增 | B6: % | D6: =D79 -> 0.77785363 | E6: =E79 -> 0.84317641 | F6: =F79 -> 0.35879361 | G6: =G79 -> 0.12113726 | H6: =H79 -> 0.10075817 | I6: =I79 -> 0.080379086 | J6: =J79 -> 0.06
A7: AI GPU 平台營收 | B7: US$B | C7: =C75 -> 15.3804 | D7: =D75 -> 29.911415 | E7: =E75 -> 61.475677 | F7: =F75 -> 86.466871 | G7: =G75 -> 97.636133
A8: 非 AI（企業、儲存、邊緣等） | B8: US$B | C8: =C77 -> 6.5916 | D8: =D77 -> 9.151585 | E8: =E77 -> 10.524323 | F8: =F77 -> 11.366269 | G8: =G77 -> 12.048245
A9: AI GPU 平台 ÷ 營收 | B9: % | C9: =C80 -> 0.7 | D9: =D80 -> 0.76572242 | E9: =E80 -> 0.85382885 | F9: =F80 -> 0.88381985 | G9: =G80 -> 0.89015533
A10: 毛利率 | B10: % | C10: =C86 -> 0.11059075 | D10: =D86 -> 0.10821749 | E10: =E86 -> 0.1162173 | F10: =F86 -> 0.11503067 | G10: =G86 -> 0.11478
A11: 營業利益率 | B11: % | C11: =C90 -> 0.057027125 | D11: =D90 -> 0.070923892 | E11: =E90 -> 0.08915986 | F11: =F90 -> 0.092259992 | G11: =G90 -> 0.093485526
A12: 歸屬母公司淨利 | B12: US$B | C12: =C94 -> 1.0489 | D12: =D94 -> 2.2305 | E12: =E94 -> 4.5127575 | F12: =F94 -> 6.4676886 | G12: =G94 -> 7.3885513 | H12: =H94 -> 8.4652996 | I12: =I94 -> 9.1457327 | J12: =J94 -> 9.6944766
A13: 淨利率 | B13: % | C13: =C99 -> 0.04773803 | D13: =D99 -> 0.057100069 | E13: =E99 -> 0.062677187 | F13: =F99 -> 0.066109383 | G13: =G99 -> 0.067361929 | H13: =H99 -> 0.070114144 | I13: =I99 -> 0.070114144 | J13: =J99 -> 0.070114144
A14: EPS | B14: US$ | C14: =C97 -> 1.68 | D14: =D97 -> 3.26 | E14: =E97 -> 6.0573926 | F14: =F97 -> 8.5955061 | G14: =G97 -> 9.7221043 | H14: =H97 -> 9.2889803 | I14: =I97 -> 9.9362574 | J14: =J97 -> 10.428151
A15: EPS 年增 | B15: % | D15: =D98 -> 0.94047619 | E15: =E98 -> 0.85809587 | F15: =F98 -> 0.41901091 | G15: =G98 -> 0.13106828 | H15: =H98 -> -0.044550438 | I15: =I98 -> 0.069682263 | J15: =J98 -> 0.04950495
A17: 情境 B
A18: 營收 | B18: US$B | C18: =C120 -> 21.972 | D18: =D120 -> 39.063 | E18: =E120 -> 68.5 | F18: =F120 -> 80.639712 | G18: =G120 -> 82.069112 | H18: =H120 -> 84.133191 | I18: =I120 -> 86.873851 | J18: =J120 -> 90.348805
A19: 營收年增 | B19: % | D19: =D121 -> 0.77785363 | E19: =E121 -> 0.75357755 | F19: =F121 -> 0.17722207 | G19: =G121 -> 0.017725759 | H19: =H121 -> 0.025150506 | I19: =I121 -> 0.032575253 | J19: =J121 -> 0.04
A20: AI GPU 平台營收 | B20: US$B | C20: =C117 -> 15.3804 | D20: =D117 -> 29.911415 | E20: =E117 -> 57.975677 | F20: =F117 -> 69.273443 | G20: =G117 -> 70.020867
A21: 非 AI（企業、儲存、邊緣等） | B21: US$B | C21: =C119 -> 6.5916 | D21: =D119 -> 9.151585 | E21: =E119 -> 10.524323 | F21: =F119 -> 11.366269 | G21: =G119 -> 12.048245
A22: AI GPU 平台 ÷ 營收 | B22: % | C22: =C122 -> 0.7 | D22: =D122 -> 0.76572242 | E22: =E122 -> 0.84636025 | F22: =F122 -> 0.85904874 | G22: =G122 -> 0.85319392
A23: 毛利率 | B23: % | C23: =C128 -> 0.11059075 | D23: =D128 -> 0.10821749 | E23: =E128 -> 0.1080492 | F23: =F128 -> 0.10570219 | G23: =G128 -> 0.1060041
A24: 營業利益率 | B24: % | C24: =C132 -> 0.057027125 | D24: =D132 -> 0.070923892 | E24: =E132 -> 0.080371469 | F24: =F132 -> 0.080524459 | G24: =G132 -> 0.081089482
A25: 歸屬母公司淨利 | B25: US$B | C25: =C136 -> 1.0489 | D25: =D136 -> 2.2305 | E25: =E136 -> 3.8272092 | F25: =F136 -> 4.5682269 | G25: =G136 -> 4.6893313 | H25: =H136 -> 4.8523097 | I25: =I136 -> 4.7373331 | J25: =J136 -> 4.642863
A26: 淨利率 | B26: % | C26: =C141 -> 0.04773803 | D26: =D141 -> 0.057100069 | E26: =E141 -> 0.055871668 | F26: =F141 -> 0.056649841 | G26: =G141 -> 0.05713881 | H26: =H141 -> 0.057674143 | I26: =I141 -> 0.054531174 | J26: =J141 -> 0.051388206
A27: EPS | B27: US$ | C27: =C139 -> 1.68 | D27: =D139 -> 3.26 | E27: =E139 -> 5.1371936 | F27: =F139 -> 6.0711368 | G27: =G139 -> 6.1703799 | H27: =H139 -> 5.3244435 | I27: =I139 -> 5.1468114 | J27: =J139 -> 4.9942333
A28: EPS 年增 | B28: % | D28: =D140 -> 0.94047619 | E28: =E140 -> 0.57582626 | F28: =F140 -> 0.18180027 | G28: =G140 -> 0.016346705 | H28: =H140 -> -0.13709632 | I28: =I140 -> -0.033361612 | J28: =J140 -> -0.029645179
A30: 情境 C
A31: 營收 | B31: US$B | C31: =C162 -> 21.972 | D31: =D162 -> 39.063 | E31: =E162 -> 65 | F31: =F162 -> 62.717571 | G31: =G162 -> 53.577211 | H31: =H162 -> 48.728888 | I31: =I162 -> 47.011382 | J31: =J162 -> 47.95161
A32: 營收年增 | B32: % | D32: =D163 -> 0.77785363 | E32: =E163 -> 0.6639787 | F32: =F163 -> -0.035114295 | G32: =G163 -> -0.14573842 | H32: =H163 -> -0.090492277 | I32: =I163 -> -0.035246139 | J32: =J163 -> 0.02
A33: AI GPU 平台營收 | B33: US$B | C33: =C159 -> 15.3804 | D33: =D159 -> 29.911415 | E33: =E159 -> 54.475677 | F33: =F159 -> 51.351302 | G33: =G159 -> 41.528967
A34: 非 AI（企業、儲存、邊緣等） | B34: US$B | C34: =C161 -> 6.5916 | D34: =D161 -> 9.151585 | E34: =E161 -> 10.524323 | F34: =F161 -> 11.366269 | G34: =G161 -> 12.048245
A35: AI GPU 平台 ÷ 營收 | B35: % | C35: =C164 -> 0.7 | D35: =D164 -> 0.76572242 | E35: =E164 -> 0.83808734 | F35: =F164 -> 0.81877059 | G35: =G164 -> 0.77512371
A36: 毛利率 | B36: % | C36: =C170 -> 0.11059075 | D36: =D170 -> 0.10821749 | E36: =E170 -> 0.10007838 | F36: =F170 -> 0.093041303 | G36: =G170 -> 0.096077648
A37: 營業利益率 | B37: % | C37: =C174 -> 0.057027125 | D37: =D174 -> 0.070923892 | E37: =E174 -> 0.071713559 | F37: =F174 -> 0.06364422 | G37: =G174 -> 0.061665374
A38: 歸屬母公司淨利 | B38: US$B | C38: =C178 -> 1.0489 | D38: =D178 -> 2.2305 | E38: =E178 -> 3.194161 | F38: =F178 -> 2.6918331 | G38: =G178 -> 2.1760191 | H38: =H178 -> 2.1839859 | I38: =I178 -> 2.0397867 | J38: =J178 -> 2.012016
A39: 淨利率 | B39: % | C39: =C183 -> 0.04773803 | D39: =D183 -> 0.057100069 | E39: =E183 -> 0.049140939 | F39: =F183 -> 0.04291992 | G39: =G183 -> 0.040614639 | H39: =H183 -> 0.04481912 | I39: =I183 -> 0.04338921 | J39: =J183 -> 0.041959299
A40: EPS | B40: US$ | C40: =C181 -> 1.68 | D40: =D181 -> 3.26 | E40: =E181 -> 4.2874644 | F40: =F181 -> 3.5774246 | G40: =G181 -> 2.8632791 | H40: =H181 -> 2.3964895 | I40: =I181 -> 2.2160987 | J40: =J181 -> 2.1642846
A41: EPS 年增 | B41: % | D41: =D182 -> 0.94047619 | E41: =E182 -> 0.31517314 | F41: =F182 -> -0.16560833 | G41: =G182 -> -0.1996256 | H41: =H182 -> -0.16302623 | I41: =I182 -> -0.075272941 | J41: =J182 -> -0.023380738
A43: 核對（應為 0）：FY2026 模型 − 實績
A44: 三情境：營收差（US$B） | D44: =ABS(D78-a26_rev)+ABS(D120-a26_rev)+ABS(D162-a26_rev) -> 0
A45: 三情境：EPS 差（US$） | D45: =ABS(D97-a26_eps)+ABS(D139-a26_eps)+ABS(D181-a26_eps) -> 0
A46: 情境 A：毛利差（US$B；以 FY2027 公式套用 FY2026） | D46: =D83*D75+gm_nai*D77-a26_gp -> 0
A60: 情境 A（順利）：顆數係數 1.0；FY2027 營收＝指引上緣；份額維持；AI 毛利率 +1.5pt
A61: 項目 | B61: 單位 | C61: FY2025A | D61: FY2026A（錨點） | E61: FY2027 | F61: FY2028 | G61: FY2029 | H61: FY2030（收斂） | I61: FY2031（收斂） | J61: FY2032（收斂） | K61: 說明
A62: A. 商用 GPU 系統市場（D–G 欄的「CY」列為日曆年 CY2026–CY2029；「FY」列為美超微會計年度）
A63: GB300 世代商用 GPU 顆數（CY） | B63: 百萬顆 | D63: =uo_26 -> 6.65 | E63: =uo_27*mf -> 2.4 | F63: =uo_28*um28_A*mf -> 0.5 | G63: =uo_29*um29_A*mf -> 0.25 | K63: Blackwell＋Hopper（2026 另含 AMD MI355）；台積電模型顆數 × 情境係數
A64: Rubin 世代商用 GPU 顆數（CY） | B64: 百萬顆 | D64: =un_26 -> 1.7 | E64: =un_27*mf -> 8.8 | F64: =un_28*um28_A*mf -> 11 | G64: =un_29*um29_A*mf -> 12.65 | K64: Rubin＋Rubin Ultra（2027 起另含 AMD MI450）
A65: 每顆系統價值：GB300 世代（CY） | B65: 千美元/顆 | D65: =v_gb -> 59.722222 | E65: =v_gb -> 59.722222 | F65: =v_gb -> 59.722222 | G65: =v_gb -> 59.722222
A66: 每顆系統價值：Rubin 世代（CY） | B66: 千美元/顆 | D66: =v_vr -> 116.66667 | E66: =v_vr -> 116.66667 | F66: =v_vr*vpg_28 -> 116.66667 | G66: =v_vr*vpg_29 -> 116.66667 | K66: 整櫃買方價 ÷ 每架 GPU 封裝數（橋接表）
A67: 商用 GPU 系統市場（CY） | B67: US$B | D67: =(D63*D65+D64*D66) -> 595.48611 | E67: =(E63*E65+E64*E66) -> 1170 | F67: =(F63*F65+F64*F66) -> 1313.1944 | G67: =(G63*G65+G64*G66) -> 1490.7639 | K67: 顆數 × 每顆系統價值；含 NVIDIA 與 AMD，不含 TPU、Trainium 與其他 ASIC
A68: 商用 GPU 系統市場（FY＝½ 前一 CY＋½ 當年 CY） | B68: US$B | E68: =0.5*D67+0.5*E67 -> 882.74306 | F68: =0.5*E67+0.5*F67 -> 1241.5972 | G68: =0.5*F67+0.5*G67 -> 1401.9792 | K68: 會計年度 7 月～6 月：各取前後日曆年一半（Derived；未考慮年內出貨季節性）
A69: FY2027 市場（部署係數 1.0；份額校準用） | B69: US$B | E69: =0.5*D67+0.5*(uo_27*v_gb+un_27*v_vr) -> 882.74306 | K69: 份額以基準市場校準，Sens 的部署係數才會改變 FY2027 營收
A70: 美超微有效份額（2H FY26 校準）＝ 2026-01～06 AI 營收 ÷ ½ CY2026 市場 | B70: % | D70: =a26_aih2/(0.5*D67) -> 0.049929494 | K70: Derived：CY2026 上下半年各半（Rubin 下半年放量，上半年市場偏小，此份額偏低估）；只作對照
A71: FY2027 營收（公司指引；A 上緣、B 中點、C 下緣） | B71: US$B | E71: =g27_hi -> 72 | K71: Interested-party：公司 2026-08-11 指引 650～720 億美元
A72: 份額相對值（÷ FY2027） | B72: x | E72: =1 -> 1 | F72: =rel_28_hi*1 -> 1 | G72: =rel_29_hi*1 -> 1 | K72: A 最有利、C 最不利（Assumed）；治理事件案例另見 Sens
A73: 美超微有效份額（FY2027 以指引校準） | B73: % | E73: =(E71-E77)/E69 -> 0.069641644 | F73: =$E73*F72 -> 0.069641644 | G73: =$E73*G72 -> 0.069641644 | K73: FY2027：（指引營收 − 非 AI 營收）÷ 基準市場；4Q FY26 逾 600 億美元新訂單使份額高於 2H FY26
A74: FY2027 份額 ÷ 2H FY26 份額 | B74: x | E74: =E73/D70 -> 1.3947997 | K74: Derived：指引隱含的份額上升幅度
A75: AI GPU 平台營收 | B75: US$B | C75: =a25_ai -> 15.3804 | D75: =a26_ai -> 29.911415 | E75: =E68*E73 -> 61.475677 | F75: =F68*F73 -> 86.466871 | G75: =G68*G73 -> 97.636133
A76: B. 非 AI 與合計
A77: 非 AI（企業、儲存、邊緣等） | B77: US$B | C77: =a25_nai -> 6.5916 | D77: =a26_nai -> 9.151585 | E77: =D77*(1+g_nai27) -> 10.524323 | F77: =E77*(1+g_nai28) -> 11.366269 | G77: =F77*(1+g_nai29) -> 12.048245
A78: 營收 | B78: US$B | C78: =C75+C77 -> 21.972 | D78: =D75+D77 -> 39.063 | E78: =E75+E77 -> 72 | F78: =F75+F77 -> 97.83314 | G78: =G75+G77 -> 109.68438 | H78: =G78*(1+H79) -> 120.73598 | I78: =H78*(1+I79) -> 130.44062 | J78: =I78*(1+J79) -> 138.26706 | K78: FY2030 起為收斂法：營收年增由 FY2029 線性收斂到 fade_g、淨利率由 FY2029 特別股股利前淨利率收斂到 fade_m（FY2032 達到），非驅動因子推導；FY2030 股數加特別股轉換股數
A79: 營收年增 | B79: % | D79: =D78/C78-1 -> 0.77785363 | E79: =E78/D78-1 -> 0.84317641 | F79: =F78/E78-1 -> 0.35879361 | G79: =G78/F78-1 -> 0.12113726 | H79: =$G79+(fade_gA-$G79)*1/3 -> 0.10075817 | I79: =$G79+(fade_gA-$G79)*2/3 -> 0.080379086 | J79: =$G79+(fade_gA-$G79)*3/3 -> 0.06
A80: AI GPU 平台 ÷ 營收 | B80: % | C80: =C75/C78 -> 0.7 | D80: =D75/D78 -> 0.76572242 | E80: =E75/E78 -> 0.85382885 | F80: =F75/F78 -> 0.88381985 | G80: =G75/G78 -> 0.89015533
A81: 隱含美超微商用 GPU 出貨（AI 營收 ÷ 每顆平均系統價值） | B81: 百萬顆 | E81: =E75/((0.5*(D63*D65+D64*D66)+0.5*(E63*E65+E64*E66))/(0.5*(D63+D64)+0.5*(E63+E64))) -> 0.68074707 | F81: =F75/((0.5*(E63*E65+E64*E66)+0.5*(F63*F65+F64*F66))/(0.5*(E63+E64)+0.5*(F63+F64))) -> 0.79043265 | G81: =G75/((0.5*(F63*F65+F64*F66)+0.5*(G63*G65+G64*G66))/(0.5*(F63+F64)+0.5*(G63+G64))) -> 0.84962805 | K81: 對照用：份額 × 會計年度商用 GPU 顆數
A82: C. 損益
A83: AI 毛利率 FY2026 校準值 ＝（毛利 − 非 AI 毛利率 × 非 AI 營收）÷ AI 營收 | B83: % | D83: =(a26_gp-gm_nai*a26_nai)/a26_ai -> 0.095433875 | K83: Derived：FY2026 含 4Q 一次性利益（遞延合約、關稅、存貨跌價回轉），校準值偏高
A84: AI 毛利率 | B84: % | D84: =D83 -> 0.095433875 | E84: =$D83+dgm_27_hi -> 0.11043388 | F84: =$D83+dgm_28_hi -> 0.11043388 | G84: =$D83+dgm_28_hi -> 0.11043388 | K84: A 最高、C 最低（In 頁 C 節）
A85: 毛利 | B85: US$B | C85: =a25_gp -> 2.4299 | D85: =a26_gp -> 4.2273 | E85: =E84*E75+gm_nai*E77 -> 8.3676457 | F85: =F84*F75+gm_nai*F77 -> 11.253812 | G85: =G84*G75+gm_nai*G77 -> 12.589573
A86: 毛利率 | B86: % | C86: =C85/C78 -> 0.11059075 | D86: =D85/D78 -> 0.10821749 | E86: =E85/E78 -> 0.1162173 | F86: =F85/F78 -> 0.11503067 | G86: =G85/G78 -> 0.11478
A87: 營業費用（基準路徑） | B87: US$B | C87: =a25_opx -> 1.1769 | D87: =a26_opx -> 1.4568 | E87: =D87*(1+MAX(0,phi*E79)) -> 1.9481358 | F87: =E87*(1+MAX(0,phi*F79)) -> 2.2277272 | G87: =F87*(1+MAX(0,phi*G79)) -> 2.3356715
A88: 營業費用 | B88: US$B | C88: =C87 -> 1.1769 | D88: =D87 -> 1.4568 | E88: =E87+0*E78 -> 1.9481358 | F88: =F87+0*F78 -> 2.2277272 | G88: =G87+0*G78 -> 2.3356715
A89: 營業利益 | B89: US$B | C89: =C85-C88 -> 1.253 | D89: =D85-D88 -> 2.7705 | E89: =E85-E88 -> 6.4195099 | F89: =F85-F88 -> 9.0260847 | G89: =G85-G88 -> 10.253902
A90: 營業利益率 | B90: % | C90: =C89/C78 -> 0.057027125 | D90: =D89/D78 -> 0.070923892 | E90: =E89/E78 -> 0.08915986 | F90: =F89/F78 -> 0.092259992 | G90: =G89/G78 -> 0.093485526
A91: 淨利（特別股股利前）÷ 營業利益 | B91: % | C91: =a25_ni/a25_oi -> 0.83711093 | D91: =a26_ni/a26_oi -> 0.80508933 | E91: =nio_f -> 0.75 | F91: =nio_f -> 0.75 | G91: =nio_f -> 0.75
A92: 淨利（特別股股利前） | B92: US$B | C92: =a25_ni -> 1.0489 | D92: =a26_ni -> 2.2305 | E92: =E89*E91 -> 4.8146325 | F92: =F89*F91 -> 6.7695636 | G92: =G89*G91 -> 7.6904263
A93: 特別股股利 | B93: US$B | C93: =0 -> 0 | D93: =0 -> 0 | E93: =pref_div -> 0.301875 | F93: =pref_div -> 0.301875 | G93: =pref_div -> 0.301875 | K93: FY2026 只有約 3 週，已含在實績；2029-06 強制轉換後為 0
A94: 歸屬母公司淨利 | B94: US$B | C94: =C92-C93 -> 1.0489 | D94: =D92-D93 -> 2.2305 | E94: =E92-E93 -> 4.5127575 | F94: =F92-F93 -> 6.4676886 | G94: =G92-G93 -> 7.3885513 | H94: =H78*H99 -> 8.4652996 | I94: =I78*I99 -> 9.1457327 | J94: =J78*J99 -> 9.6944766 | K94: 扣除特別股股利後、歸屬普通股（GAAP）
A95: 淨利率（特別股股利前） | B95: % | C95: =C92/C78 -> 0.04773803 | D95: =D92/D78 -> 0.057100069 | E95: =E92/E78 -> 0.066869895 | F95: =F92/F78 -> 0.069194994 | G95: =G92/G78 -> 0.070114144 | K95: 收斂法的起點（FY2030 起特別股已轉換）
A96: 股數（GAAP 稀釋） | B96: 十億股 | C96: =a25_sh -> 0.62434524 | D96: =a26_sh -> 0.68420245 | E96: =sh27 -> 0.745 | F96: =E96*(1+sh_g) -> 0.75245 | G96: =F96*(1+sh_g) -> 0.7599745 | H96: =G96*(1+sh_g)+conv_sh -> 0.91132712 | I96: =H96*(1+sh_g) -> 0.92044039 | J96: =I96*(1+sh_g) -> 0.9296448
A97: EPS（GAAP 稀釋） | B97: US$ | C97: =C94/C96 -> 1.68 | D97: =D94/D96 -> 3.26 | E97: =E94/E96 -> 6.0573926 | F97: =F94/F96 -> 8.5955061 | G97: =G94/G96 -> 9.7221043 | H97: =H94/H96 -> 9.2889803 | I97: =I94/I96 -> 9.9362574 | J97: =J94/J96 -> 10.428151
A98: EPS 年增 | B98: % | D98: =D97/C97-1 -> 0.94047619 | E98: =E97/D97-1 -> 0.85809587 | F98: =F97/E97-1 -> 0.41901091 | G98: =G97/F97-1 -> 0.13106828 | H98: =H97/G97-1 -> -0.044550438 | I98: =I97/H97-1 -> 0.069682263 | J98: =J97/I97-1 -> 0.04950495
A99: 淨利率（歸屬母公司淨利 ÷ 營收） | B99: % | C99: =C94/C78 -> 0.04773803 | D99: =D94/D78 -> 0.057100069 | E99: =E94/E78 -> 0.062677187 | F99: =F94/F78 -> 0.066109383 | G99: =G94/G78 -> 0.067361929 | H99: =$G95+(fade_mA-$G95)*1/3 -> 0.070114144 | I99: =$G95+(fade_mA-$G95)*2/3 -> 0.070114144 | J99: =$G95+(fade_mA-$G95)*3/3 -> 0.070114144
A102: 情境 B（平平）：CY2028 顆數 ×0.8、CY2029 ×0.85；FY2027 營收＝指引中點；份額 ×0.95／×0.92；AI 毛利率 +0.5pt／+0.3pt
A103: 項目 | B103: 單位 | C103: FY2025A | D103: FY2026A（錨點） | E103: FY2027 | F103: FY2028 | G103: FY2029 | H103: FY2030（收斂） | I103: FY2031（收斂） | J103: FY2032（收斂） | K103: 說明
A104: A. 商用 GPU 系統市場（D–G 欄的「CY」列為日曆年 CY2026–CY2029；「FY」列為美超微會計年度）
A105: GB300 世代商用 GPU 顆數（CY） | B105: 百萬顆 | D105: =uo_26 -> 6.65 | E105: =uo_27*mf -> 2.4 | F105: =uo_28*um28_B*mf -> 0.4 | G105: =uo_29*um29_B*mf -> 0.2125 | K105: Blackwell＋Hopper（2026 另含 AMD MI355）；台積電模型顆數 × 情境係數
A106: Rubin 世代商用 GPU 顆數（CY） | B106: 百萬顆 | D106: =un_26 -> 1.7 | E106: =un_27*mf -> 8.8 | F106: =un_28*um28_B*mf -> 8.8 | G106: =un_29*um29_B*mf -> 10.7525 | K106: Rubin＋Rubin Ultra（2027 起另含 AMD MI450）
A107: 每顆系統價值：GB300 世代（CY） | B107: 千美元/顆 | D107: =v_gb -> 59.722222 | E107: =v_gb -> 59.722222 | F107: =v_gb -> 59.722222 | G107: =v_gb -> 59.722222
A108: 每顆系統價值：Rubin 世代（CY） | B108: 千美元/顆 | D108: =v_vr -> 116.66667 | E108: =v_vr -> 116.66667 | F108: =v_vr*vpg_28 -> 116.66667 | G108: =v_vr*vpg_29 -> 116.66667 | K108: 整櫃買方價 ÷ 每架 GPU 封裝數（橋接表）
A109: 商用 GPU 系統市場（CY） | B109: US$B | D109: =(D105*D107+D106*D108) -> 595.48611 | E109: =(E105*E107+E106*E108) -> 1170 | F109: =(F105*F107+F106*F108) -> 1050.5556 | G109: =(G105*G107+G106*G108) -> 1267.1493 | K109: 顆數 × 每顆系統價值；含 NVIDIA 與 AMD，不含 TPU、Trainium 與其他 ASIC
A110: 商用 GPU 系統市場（FY＝½ 前一 CY＋½ 當年 CY） | B110: US$B | E110: =0.5*D109+0.5*E109 -> 882.74306 | F110: =0.5*E109+0.5*F109 -> 1110.2778 | G110: =0.5*F109+0.5*G109 -> 1158.8524 | K110: 會計年度 7 月～6 月：各取前後日曆年一半（Derived；未考慮年內出貨季節性）
A111: FY2027 市場（部署係數 1.0；份額校準用） | B111: US$B | E111: =0.5*D109+0.5*(uo_27*v_gb+un_27*v_vr) -> 882.74306 | K111: 份額以基準市場校準，Sens 的部署係數才會改變 FY2027 營收
A112: 美超微有效份額（2H FY26 校準）＝ 2026-01～06 AI 營收 ÷ ½ CY2026 市場 | B112: % | D112: =a26_aih2/(0.5*D109) -> 0.049929494 | K112: Derived：CY2026 上下半年各半（Rubin 下半年放量，上半年市場偏小，此份額偏低估）；只作對照
A113: FY2027 營收（公司指引；A 上緣、B 中點、C 下緣） | B113: US$B | E113: =g27 -> 68.5 | K113: Interested-party：公司 2026-08-11 指引 650～720 億美元
A114: 份額相對值（÷ FY2027） | B114: x | E114: =1 -> 1 | F114: =rel_28*1 -> 0.95 | G114: =rel_29*1 -> 0.92 | K114: A 最有利、C 最不利（Assumed）；治理事件案例另見 Sens
A115: 美超微有效份額（FY2027 以指引校準） | B115: % | E115: =(E113-E119)/E111 -> 0.06567673 | F115: =$E115*F114 -> 0.062392893 | G115: =$E115*G114 -> 0.060422592 | K115: FY2027：（指引營收 − 非 AI 營收）÷ 基準市場；4Q FY26 逾 600 億美元新訂單使份額高於 2H FY26
A116: FY2027 份額 ÷ 2H FY26 份額 | B116: x | E116: =E115/D112 -> 1.3153895 | K116: Derived：指引隱含的份額上升幅度
A117: AI GPU 平台營收 | B117: US$B | C117: =a25_ai -> 15.3804 | D117: =a26_ai -> 29.911415 | E117: =E110*E115 -> 57.975677 | F117: =F110*F115 -> 69.273443 | G117: =G110*G115 -> 70.020867
A118: B. 非 AI 與合計
...

Sheet Val
A1: Val — P/E 估值（美元，GAAP EPS）。結論用「現價 ÷ FY2027、FY2028 EPS（模型）」；目標價＝DCF 與 Comparable 加權（第 0 節）；十年 P/E 規則值（第 3 節，會計年度年底落後 P/E）只作參考
A2: 循環位置：美超微不是設備股，不套設備市場見頂年；以本模型營收最高的會計年度為見頂年（比照廣達、緯穎）。營收到 FY2029 仍在增加時，見頂年未知，判為中段
A4: 0. 目標價
A5: 0.1 DCF（股東權益現金流，FY2027–FY2032 明確期＋FY2032 後永續）
A6: 項目 | B6: A（順利） | C6: B（平平） | D6: C（不如預期） | E6: 說明
A7: 情境 EPS（FY2027–FY2032） | E7: PL 頁各情境（GAAP 稀釋）；FY2030 起為收斂法
A8: FY2027 | B8: =PL!E14 -> 6.0573926 | C8: =PL!E27 -> 5.1371936 | D8: =PL!E40 -> 4.2874644
A9: FY2028 | B9: =PL!F14 -> 8.5955061 | C9: =PL!F27 -> 6.0711368 | D9: =PL!F40 -> 3.5774246
A10: FY2029 | B10: =PL!G14 -> 9.7221043 | C10: =PL!G27 -> 6.1703799 | D10: =PL!G40 -> 2.8632791
A11: FY2030 | B11: =PL!H14 -> 9.2889803 | C11: =PL!H27 -> 5.3244435 | D11: =PL!H40 -> 2.3964895
A12: FY2031 | B12: =PL!I14 -> 9.9362574 | C12: =PL!I27 -> 5.1468114 | D12: =PL!I40 -> 2.2160987
A13: FY2032 | B13: =PL!J14 -> 10.428151 | C13: =PL!J27 -> 4.9942333 | D13: =PL!J40 -> 2.1642846
A14: 股東現金流＝EPS ×（1 − tp_g ÷ tp_roe）
A15: 再投資率（tp_g ÷ tp_roe，上限 0.8） | B15: =MIN(tp_g/tp_roe,0.8) -> 0.17004393 | E15: ROE 為近三年平均（In 頁 tp_roe）
A16: FY2027 | B16: =B8*(1-$B$15) -> 5.0273697 | C16: =C8*(1-$B$15) -> 4.263645 | D16: =D8*(1-$B$15) -> 3.5584071
A17: FY2028 | B17: =B9*(1-$B$15) -> 7.1338925 | C17: =C9*(1-$B$15) -> 5.0387768 | D17: =D9*(1-$B$15) -> 2.9691053
A18: FY2029 | B18: =B10*(1-$B$15) -> 8.0689195 | C18: =C10*(1-$B$15) -> 5.1211442 | D18: =D10*(1-$B$15) -> 2.3763958
A19: FY2030 | B19: =B11*(1-$B$15) -> 7.7094456 | C19: =C11*(1-$B$15) -> 4.4190542 | D19: =D11*(1-$B$15) -> 1.988981
A20: FY2031 | B20: =B12*(1-$B$15) -> 8.2466572 | C20: =C12*(1-$B$15) -> 4.2716274 | D20: =D12*(1-$B$15) -> 1.8392645
A21: FY2032 | B21: =B13*(1-$B$15) -> 8.6549075 | C21: =C13*(1-$B$15) -> 4.1449942 | D21: =D13*(1-$B$15) -> 1.7962612
A22: DCF 情境每股價值（折現率 tp_r） | B22: =MAX(0,SUMPRODUCT(B16:B21,1/(1+tp_r)^{1;2;3;4;5;6})+B21*(1+tp_g)/(tp_r-tp_g)/(1+tp_r)^6) -> 116.48154 | C22: =MAX(0,SUMPRODUCT(C16:C21,1/(1+tp_r)^{1;2;3;4;5;6})+C21*(1+tp_g)/(tp_r-tp_g)/(1+tp_r)^6) -> 60.453784 | D22: =MAX(0,SUMPRODUCT(D16:D21,1/(1+tp_r)^{1;2;3;4;5;6})+D21*(1+tp_g)/(tp_r-tp_g)/(1+tp_r)^6) -> 28.56363 | E22: Σ 明確期現金流 ÷ (1＋r)^t ＋ 永續價值 ÷ (1＋r)^6；永續價值＝FY2032 現金流 ×(1＋g)÷(r−g)；基準日 2026 年底、t＝1 對 FY2027（6 月底結束，實際約半年後，略保守）；低於 0 取 0
A23: DCF 情境價值推到 12 個月後（×(1＋tp_r)） | B23: =B22*(1+tp_r) -> 128.12969 | C23: =C22*(1+tp_r) -> 66.499162 | D23: =D22*(1+tp_r) -> 31.419993
A24: DCF 目標價（情境加權） | B24: =tp_wA*B23+tp_wB*C23+tp_wC*D23 -> 77.972487 | E24: Σ 權重 × 情境價值 ×(1＋r)；權重見 In 頁
A26: 0.2 Comparable（市場主流同業前瞻 P/E）
A27: 同業與前瞻 P/E | B27: 代號 | C27: 前瞻 12 月 P/E | D27: 日期 | E27: 來源 | F27: 標記
A28: Dell Technologies | B28: DELL | C28: 16.22 | D28: 2026-10-23 | E28: stockanalysis.com forward PE（分析師共識；價格日期如左） | F28: Interested-party
A29: Hewlett Packard Enterprise | B29: HPE | C29: 12.19 | D29: 2026-10-23 | E29: stockanalysis.com forward PE（分析師共識；價格日期如左） | F29: Interested-party
A30: 緯穎（Wiwynn） | B30: 6669.TW | C30: 11.73 | D30: 2026-10-21 | E30: stockanalysis.com forward PE（分析師共識；價格日期如左） | F30: Interested-party
A31: 廣達（Quanta） | B31: 2382.TW | C31: 11.52 | D31: 2026-10-21 | E31: stockanalysis.com forward PE（分析師共識；價格日期如左） | F31: Interested-party
A32: 緯創（Wistron） | B32: 3231.TW | C32: 9.21 | D32: 2026-10-19 | E32: stockanalysis.com forward PE（分析師共識；價格日期如左） | F32: Interested-party
A33: 同業前瞻 P/E 中位數 | B33: =MEDIAN(C28:C32) -> 11.73 | E33: AI 伺服器品牌與 ODM 同業：Dell、HPE、緯穎、廣達、緯創（不含 A 股）
A34: 12 個月後的前瞻 EPS（情境加權） | B34: =tp_wA*(8/12*B9+4/12*B10)+tp_wB*(8/12*C9+4/12*C10)+tp_wC*(8/12*D9+4/12*D10) -> 6.4112958 | E34: 會計年度 6 月底結束：約 2027-10 時的未來 12 月（2027-11～2028-10）≈ 8／12 × FY2028＋4／12 × FY2029
A35: Comparable 目標價 | B35: =B33*B34 -> 75.204499 | E35: 同業中位數 × 前瞻 EPS
A37: 0.3 結論
A38: 項目 | B38: 數值 | E38: 說明
A39: 目標價（DCF 與 Comparable 加權） | B39: =tp_w_dcf*B24+(1-tp_w_dcf)*B35 -> 76.588493 | E39: tp_w_dcf × DCF＋（1 − tp_w_dcf）× Comparable；tp_w_dcf 見 In 頁（0.5）
A40: Comparable 目標價（市場主流同業法） | B40: =B35 -> 75.204499
A41: 市場共識目標價 | B41: =cons_tp -> 43.27 | E41: stockanalysis（S&P Global）：18 位分析師平均 43.27（中位數 45、最低 15、最高 60），2026-10-22；tickflow 25 位 41.44
A42: 上檔空間：加權目標價 | B42: =B39/px-1 -> 1.3250909 | E42: 現價＝In 頁 px（2026-10-23 收盤）
A43: 上檔空間：Comparable 目標價 | B43: =B40/px-1 -> 1.2830753
A44: 與市場共識目標價的差距：EPS 因素 | B44: =B34/cons_feps-1 -> 0.37412714 | E44: 本模型前瞻 EPS（GAAP）÷ 共識前瞻 EPS（non-GAAP，＝價格 ÷ 前瞻 P/E）− 1；期間約晚一年、口徑不同（GAAP 較低）
A45: 與市場共識目標價的差距：倍數因素 | B45: =(cons_tp/cons_feps)/B33-1 -> -0.20937601 | E45: ="共識目標價隱含 "&TEXT(cons_tp/cons_feps,"0.0")&"x，同業中位數 "&TEXT(B33,"0.0")&"x" -> 共識目標價隱含 9.3x，同業中位數 11.7x
A46: 價格帶（DCF 不如預期～順利） | B46: =TEXT(D23,"0.0")&"～"&TEXT(B23,"0.0") -> 31.4～128.1 | E46: C 情境價值～A 情境價值（推到 12 個月後）
A47: 歷史倍數檢查：現價隱含 P/E 的十年分位（A／B／C） | B47: =IF(px/B9<=MIN($B$86:$B$95),0,IF(px/B9>=MAX($B$86:$B$95),1,PERCENTRANK($B$86:$B$95,px/B9))) -> 0 | C47: =IF(px/C9<=MIN($B$86:$B$95),0,IF(px/C9>=MAX($B$86:$B$95),1,PERCENTRANK($B$86:$B$95,px/C9))) -> 0 | D47: =IF(px/D9<=MIN($B$86:$B$95),0,IF(px/D9>=MAX($B$86:$B$95),1,PERCENTRANK($B$86:$B$95,px/D9))) -> 0.0302 | E47: 現價 ÷ 各情境 FY2028 EPS 在 FY2016–FY2025 年底 P/E（第 5 節兩來源平均）的分位；低於歷史最小值記 0%、高於最大值記 100%；只作檢查，不進目標價
A48: 目標價方法 | B48: DCF：股東現金流＝GAAP 稀釋 EPS ×（1 − g／ROE），r＝10%、g＝4%、ROE 為近三年平均約 23.5%（再投資率約 17%），FY2027–32 明確期＋永續；組裝與品牌商資本支出低（FY2026 1.62 億美元），未改用淨利＋折舊－資本支出；但營運資金占用大（FY2026 營業現金流 −68 億美元、以增資與特別股 56 億補足），以 EPS 推現金流會高估股東實拿的現金，偏誤向上。Comparable：Dell、HPE、緯穎、廣達、緯創前瞻 P/E 中位數（不含 A 股）；同業倍數未反映美超微的治理與會計折價（自身前瞻 P/E 約 7x），偏誤向上。FY2030 起為收斂法；FY2030 股數加特別股轉換股數。治理風險不改折現率，以 Sens 案例呈現。情境對應：A＝順利（顆數基準）、B＝平平（顆數 ×0.8／0.85）、C＝不如預期（顆數 ×0.6）
A51: 1. 價格與市場隱含倍數
A52: 項目 | B52: A | C52: B | D52: C | E52: 說明
A53: 現價（2026-10-23 收盤） | B53: =px -> 32.94
A54: 現價 ÷ FY2026 EPS（實績） | B54: =px/PL!D14 -> 10.104294 | C54: =px/PL!D27 -> 10.104294 | D54: =px/PL!D40 -> 10.104294 | E54: FY2026 三情境相同（實績）
A55: 現價 ÷ FY2027 EPS（模型） | B55: =px/PL!E14 -> 5.4379834 | C55: =px/PL!E27 -> 6.4120612 | D55: =px/PL!E40 -> 7.6828625
A56: 現價 ÷ FY2028 EPS（模型） | B56: =px/PL!F14 -> 3.8322351 | C56: =px/PL!F27 -> 5.4256725 | D56: =px/PL!F40 -> 9.2077412
A57: 現價 ÷ FY2029 EPS（模型） | B57: =px/PL!G14 -> 3.3881554 | C57: =px/PL!G27 -> 5.3384072 | D57: =px/PL!G40 -> 11.504293
A58: 未來 12 月 EPS（模型 B）≈ 8／12 × FY2027＋4／12 × FY2028 | B58: =8/12*PL!E27+4/12*PL!F27 -> 5.448508 | E58: 2026-11～2027-10：FY2027（7 月～6 月）8 個月＋FY2028 4 個月
A59: 現價 ÷ 未來 12 月 EPS（模型 B） | B59: =px/B58 -> 6.0456918
A60: 近 12 月 P/E（stockanalysis，10-23） | B60: =pe_ttm -> 10.12
A61: 前瞻 P/E（stockanalysis，10-23；non-GAAP） | B61: =fpe -> 7.06
A63: 2. 循環位置（本模型營收最高的會計年度）
A64: 情境 | B64: 營收最高年（FY2026–FY2029） | C64: FY2027 判定 | D64: 規則倍數（P/E） | E64: 見頂年是否未知 | F64: 說明
A65: A | B65: =INDEX({2026,2027,2028,2029},MATCH(MAX(PL!D78:G78),PL!D78:G78,0)) -> 2029 | C65: =IF(B65=2029,"中段",IF(2027<B65,"中段",IF(2027=B65,"見頂","谷底"))) -> 中段 | D65: =IF(C65="見頂",pe_peak,IF(C65="谷底",pe_trough,pe_mid)) -> 18.62 | E65: =IF(B65=2029,"是：營收到觀測期末仍在增加","否") -> 是：營收到觀測期末仍在增加 | F65: tools/cycle_position.py excel_rule；營收最高年取代設備市場見頂年
A66: B | B66: =INDEX({2026,2027,2028,2029},MATCH(MAX(PL!D120:G120),PL!D120:G120,0)) -> 2029 | C66: =IF(B66=2029,"中段",IF(2027<B66,"中段",IF(2027=B66,"見頂","谷底"))) -> 中段 | D66: =IF(C66="見頂",pe_peak,IF(C66="谷底",pe_trough,pe_mid)) -> 18.62 | E66: =IF(B66=2029,"是：營收到觀測期末仍在增加","否") -> 是：營收到觀測期末仍在增加 | F66: 同上
A67: C | B67: =INDEX({2026,2027,2028,2029},MATCH(MAX(PL!D162:G162),PL!D162:G162,0)) -> 2027 | C67: =IF(B67=2029,"中段",IF(2027<B67,"中段",IF(2027=B67,"見頂","谷底"))) -> 見頂 | D67: =IF(C67="見頂",pe_peak,IF(C67="谷底",pe_trough,pe_mid)) -> 16.39 | E67: =IF(B67=2029,"是：營收到觀測期末仍在增加","否") -> 否 | F67: 同上
A69: 3. 規則值隱含股價（美元；約 FY2027 年底＝2027-06，未折現）＝ FY2027 EPS × 規則倍數
A70: 情境 | B70: FY2027 EPS | C70: （同左） | D70: 規則倍數 | E70: 隱含股價 | F70: 相對現價 | G70: 現價 ÷ FY2027 EPS
A71: A | B71: =PL!E14 -> 6.0573926 | C71: =B71 -> 6.0573926 | D71: =D65 -> 18.62 | E71: =C71*D71 -> 112.78865 | F71: =E71/px-1 -> 2.4240634 | G71: =px/C71 -> 5.4379834
A72: B | B72: =PL!E27 -> 5.1371936 | C72: =B72 -> 5.1371936 | D72: =D66 -> 18.62 | E72: =C72*D72 -> 95.654545 | F72: =E72/px-1 -> 1.9039024 | G72: =px/C72 -> 6.4120612
A73: C | B73: =PL!E40 -> 4.2874644 | C73: =B73 -> 4.2874644 | D73: =D67 -> 16.39 | E73: =C73*D73 -> 70.271542 | F73: =E73/px-1 -> 1.1333194 | G73: =px/C73 -> 7.6828625
A75: 4. What must be true：FY2027 年底價 ＝ 現價 ×（1＋報酬）所需的倍數（FY2028 EPS；2027-06 的價格看下一會計年度 EPS）
A76: FY2027 年底價 ÷ 現價 | B76: 所需倍數（÷ FY2028 EPS，A） | C76: 所需倍數（÷ FY2028 EPS，B） | D76: 所需倍數（÷ FY2028 EPS，C） | E76: 對照：十年中位數
A77: 1 | B77: =px*A77/PL!F14 -> 3.8322351 | C77: =px*A77/PL!F27 -> 5.4256725 | D77: =px*A77/PL!F40 -> 9.2077412 | E77: =pe_mid -> 18.62
A78: 1.1 | B78: =px*A78/PL!F14 -> 4.2154586 | C78: =px*A78/PL!F27 -> 5.9682398 | D78: =px*A78/PL!F40 -> 10.128515 | E78: =pe_mid -> 18.62
A79: 1.21 | B79: =px*A79/PL!F14 -> 4.6370045 | C79: =px*A79/PL!F27 -> 6.5650638 | D79: =px*A79/PL!F40 -> 11.141367 | E79: =pe_mid -> 18.62
A80: 1.5 | B80: =px*A80/PL!F14 -> 5.7483526 | C80: =px*A80/PL!F27 -> 8.1385088 | D80: =px*A80/PL!F40 -> 13.811612 | E80: =pe_mid -> 18.62
A81: 2 | B81: =px*A81/PL!F14 -> 7.6644702 | C81: =px*A81/PL!F27 -> 10.851345 | D81: =px*A81/PL!F40 -> 18.415482 | E81: =pe_mid -> 18.62
A82: 讀法：1.00＝價格不變、1.21＝一年約 21%。所需倍數低於歷史中位數時，現價相對便宜；美超微的低倍數同時反映治理、會計與營運資金風險（見 README）。本版未做先驗，無 Andy 合理 P/E 對照。
A84: 5. 十年 P/E（FY2016–FY2025 會計年度年底＝6 月底；兩來源平均，分位排名用；Macrotrends 2018–2019 因延遲申報缺值）
A85: 年底 | B85: 兩來源平均 P/E | C85: Macrotrends | D85: fullratio
A86: 2016 | B86: =AVERAGE(C86:D86) -> 16.46 | C86: =IF(ISNUMBER(B105),B105,"") -> 16.35 | D86: =C105 -> 16.57
A87: 2017 | B87: =AVERAGE(C87:D87) -> 18.005 | C87: =IF(ISNUMBER(B106),B106,"") -> 18.4 | D87: =C106 -> 17.61
A88: 2018 | B88: =AVERAGE(C88:D88) -> 26.28 | C88: =IF(ISNUMBER(B107),B107,"") | D88: =C107 -> 26.28
A89: 2019 | B89: =AVERAGE(C89:D89) -> 13.82 | C89: =IF(ISNUMBER(B108),B108,"") | D89: =C108 -> 13.82
A90: 2020 | B90: =AVERAGE(C90:D90) -> 21.375 | C90: =IF(ISNUMBER(B109),B109,"") -> 26.05 | D90: =C109 -> 16.7
A91: 2021 | B91: =AVERAGE(C91:D91) -> 16.37 | C91: =IF(ISNUMBER(B110),B110,"") -> 16.75 | D91: =C110 -> 15.99
A92: 2022 | B92: =AVERAGE(C92:D92) -> 7.485 | C92: =IF(ISNUMBER(B111),B111,"") -> 7.63 | D92: =C111 -> 7.34
A93: 2023 | B93: =AVERAGE(C93:D93) -> 21.185 | C93: =IF(ISNUMBER(B112),B112,"") -> 21.77 | D93: =C112 -> 20.6
A94: 2024 | B94: =AVERAGE(C94:D94) -> 40.355 | C94: =IF(ISNUMBER(B113),B113,"") -> 41.13 | D94: =C113 -> 39.58
A95: 2025 | B95: =AVERAGE(C95:D95) -> 28.605 | C95: =IF(ISNUMBER(B114),B114,"") -> 29.52 | D95: =C114 -> 27.69
A96: 年數 | B96: =COUNT($B$86:$B$95) -> 10
A100: 6. 十年倍數與規則值（2016–2025 年底；見頂年 25 分位、中段中位數、谷底 75 分位）
A101: 規則（Andy 2026-10-13）：合理倍數＝2016–2025 年底 P/E 依循環位置取分位，兩個來源分別取分位再平均。美超微會計年度 6 月底結束，取會計年度年底。兩來源 2020 年相差約 9 個倍數點（Macrotrends 的 FY2020 EPS 受重編影響）；FY2024 因股價高峰達約 40x。
A103: P/E：十年歷史倍數
A104: 年底 | B104: Macrotrends（6 月底 P/E） | C104: fullratio（年度 P/E） | D104: 標記／說明
A105: 2016 | B105: 16.35 | C105: 16.57 | D105: Macrotrends（6 月底 P/E）：Interested-party（資料商；GAAP 近 12 月 EPS；2018–2019 延遲申報期間 EPS 記 0，缺值）；fullratio（年度 P/E）：Interested-party（資料商；年度值與 6 月季度相同，推定為會計年度年底；EPS 口徑可能為調整後）
A106: 2017 | B106: 18.4 | C106: 17.61
A107: 2018 | C107: 26.28
A108: 2019 | C108: 13.82
A109: 2020 | B109: 26.05 | C109: 16.7
A110: 2021 | B110: 16.75 | C110: 15.99
A111: 2022 | B111: 7.63 | C111: 7.34
A112: 2023 | B112: 21.77 | C112: 20.6
A113: 2024 | B113: 41.13 | C113: 39.58
...

Sheet Recon
A1: Recon — 本模型 vs 公司指引、共識與份額口徑。只作事後對照，不為對上數字而調參數。共識 EPS 為 non-GAAP；本模型為 GAAP，另列「模型＋股票報酬調整」對照
A3: 項目 | B3: 對照值 | C3: 模型 A | D3: 差距 A | E3: 模型 B | F3: 差距 B | G3: 模型 C | H3: 差距 C | I3: 對照來源 | J3: 說明
A4: A. 共識（校準未使用）
A5: FY2027 營收 vs 共識 | B5: =c_rev27 -> 70 | C5: =PL!E78 -> 72 | D5: =C5/B5-1 -> 0.028571429 | E5: =PL!E120 -> 68.5 | F5: =E5/B5-1 -> -0.021428571 | G5: =PL!E162 -> 65 | H5: =G5/B5-1 -> -0.071428571 | I5: stockanalysis／Yahoo（15 位） | J5: 本模型 FY2027 營收＝公司指引（A 上緣、B 中點、C 下緣）
A6: FY2028 營收 vs 共識 | B6: =c_rev28 -> 81.4 | C6: =PL!F78 -> 97.83314 | D6: =C6/B6-1 -> 0.20188132 | E6: =PL!F120 -> 80.639712 | F6: =E6/B6-1 -> -0.0093401519 | G6: =PL!F162 -> 62.717571 | H6: =G6/B6-1 -> -0.22951387 | I6: Yahoo（15 位）
A7: FY2027 EPS（GAAP）vs 共識（non-GAAP） | B7: =c_eps27 -> 4.67 | C7: =PL!E97 -> 6.0573926 | D7: =C7/B7-1 -> 0.2970862 | E7: =PL!E139 -> 5.1371936 | F7: =E7/B7-1 -> 0.10004146 | G7: =PL!E181 -> 4.2874644 | H7: =G7/B7-1 -> -0.081913395 | I7: stockanalysis／Yahoo | J7: 口徑不同：GAAP 較 non-GAAP 低約股票報酬
A8: FY2027 EPS（模型＋股票報酬調整）vs 共識 | B8: =c_eps27 -> 4.67 | C8: =PL!E97+sbc_ps -> 6.454708 | D8: =C8/B8-1 -> 0.38216445 | E8: =PL!E139+sbc_ps -> 5.534509 | F8: =E8/B8-1 -> 0.18511971 | G8: =PL!E181+sbc_ps -> 4.6847799 | H8: =G8/B8-1 -> 0.0031648568 | I8: 同上 | J8: 調整＝每季股票報酬（稅後）× 4 ÷ 股數（In 頁 sbc_ps）
A9: FY2028 EPS（模型＋股票報酬調整）vs 共識 | B9: =c_eps28 -> 5.59 | C9: =PL!F97+sbc_ps -> 8.9928215 | D9: =C9/B9-1 -> 0.60873373 | E9: =PL!F139+sbc_ps -> 6.4684522 | F9: =E9/B9-1 -> 0.15714709 | G9: =PL!F181+sbc_ps -> 3.97474 | H9: =G9/B9-1 -> -0.28895527 | I9: Yahoo（17 位）
A10: B. 公司指引與初步數字
A11: FY2027 營收 vs 指引中點（Interested-party） | B11: =g27 -> 68.5 | C11: =PL!E78 -> 72 | D11: =C11/B11-1 -> 0.051094891 | E11: =PL!E120 -> 68.5 | F11: =E11/B11-1 -> 0 | G11: =PL!E162 -> 65 | H11: =G11/B11-1 -> -0.051094891 | I11: 公司 2026-08-11 | J11: 依情境取指引上緣／中點／下緣，差距即指引區間
A12: FY2027 毛利率 vs 1Q FY27 初步毛利率（百分點） | B12: =q1_gm -> 0.1225 | C12: =PL!E86 -> 0.1162173 | D12: =C12-B12 -> -0.0062826988 | E12: =PL!E128 -> 0.1080492 | F12: =E12-B12 -> -0.014450798 | G12: =PL!E170 -> 0.10007838 | H12: =G12-B12 -> -0.022421615 | I12: 公司 2026-10-20 | J12: 1Q 含 4Q FY26 遞延合約的組合利益
A13: 1Q FY27 初步營收 × 4 vs FY2027 營收 | B13: =q1_rev*4 -> 76 | C13: =PL!E78 -> 72 | D13: =C13/B13-1 -> -0.052631579 | E13: =PL!E120 -> 68.5 | F13: =E13/B13-1 -> -0.098684211 | G13: =PL!E162 -> 65 | H13: =G13/B13-1 -> -0.14473684 | I13: 公司 2026-10-20 | J13: 1Q 年化已高於指引上緣；全年指引尚未調整（11-03 財報）
A14: C. 份額與市場
A15: 2H FY26 有效份額（商用 GPU 系統市場） | C15: =PL!D70 -> 0.049929494 | E15: =PL!D112 -> 0.049929494 | G15: =PL!D154 -> 0.049929494 | I15: Derived
A16: FY2027 有效份額（指引校準） | C16: =PL!E73 -> 0.069641644 | E16: =PL!E115 -> 0.06567673 | G16: =PL!E157 -> 0.061711816 | I16: Derived
A17: FY2027 份額 ÷ 2H FY26 份額 | C17: =PL!E74 -> 1.3947997 | E17: =PL!E116 -> 1.3153895 | G17: =PL!E158 -> 1.2359792 | I17: Derived | J17: 大於 1：指引隱含份額上升（4Q FY26 逾 600 億美元新訂單）
A18: FY2027 隱含商用 GPU 出貨（百萬顆） | C18: =PL!E81 -> 0.68074707 | E18: =PL!E123 -> 0.64199003 | G18: =PL!E165 -> 0.603233 | I18: Derived
A19: D. 校準
A20: AI 毛利率 FY2026 校準值（Derived） | C20: =PL!D83 -> 0.095433875 | E20: =PL!D125 -> 0.095433875 | G20: =PL!D167 -> 0.095433875 | I20: FY2026 實績 | J20: 含 4Q 一次性利益；不含 4Q 的 FY2026 毛利率見 Q 頁 B24
A21: E. 預留
A22: R4 產業部署路徑（markets/deploy_path/，尚未建立）：上線後以部署路徑取代「台積電顆數 × 情境係數」 | J22: 預留列：本版無數值

Sheet Sens
A1: Sens — 一次動一個輸入（情境 A；FY2027 份額在每個案例內依指引重新校準，部署係數與每顆價值除外）：對 FY2027、FY2028 營收、毛利率與 EPS 的影響。每個案例是一個完整推導區塊（本頁下方）
A3: 案例 | B3: 設定 | C3: FY2027 營收 | D3: FY2027 毛利率 | E3: FY2027 EPS | F3: FY2027 EPS 相對基準 | G3: FY2028 營收 | H3: FY2028 毛利率 | I3: FY2028 EPS | J3: FY2028 EPS 相對基準
A4: 基準（情境 A） | B4: PL 區塊 A | C4: =PL!E78 -> 72 | D4: =PL!E86 -> 0.1162173 | E4: =PL!E97 -> 6.0573926 | F4: =E4/E$4-1 -> 0 | G4: =PL!F78 -> 97.83314 | H4: =PL!F86 -> 0.11503067 | I4: =PL!F97 -> 8.5955061 | J4: =I4/I$4-1 -> 0
A5: AI 部署 ×0.8 | B5: CY2027 起商用 GPU 顆數 ×0.8 | C5: =E58 -> 63.851928 | D5: =E66 -> 0.11695532 | E5: =E77 -> 5.2738944 | F5: =E5/E$4-1 -> -0.12934577 | G5: =F58 -> 80.539766 | H5: =F66 -> 0.11601769 | I5: =F77 -> 6.9014525 | J5: =I5/I$4-1 -> -0.19708596
A6: AI 部署 ×1.2 | B6: ×1.2 | C6: =E100 -> 80.148072 | D6: =E108 -> 0.11562934 | E6: =E119 -> 6.8408907 | F6: =E6/E$4-1 -> 0.12934577 | G6: =F100 -> 115.12651 | H6: =F108 -> 0.11434018 | I6: =F119 -> 10.296464 | J6: =I6/I$4-1 -> 0.19788923
A7: FY2027 營收＝指引下緣 | B7: 650 億美元（情境 A 為上緣 720 億） | C7: =E142 -> 65 | D7: =E150 -> 0.11684013 | E7: =E161 -> 5.3842902 | F7: =E7/E$4-1 -> -0.11112081 | G7: =F142 -> 87.987488 | H7: =F150 -> 0.11554505 | I7: =F161 -> 7.6345509 | J7: =I7/I$4-1 -> -0.1117974
A8: 份額基準（B 值） | B8: 份額相對值 FY2028 0.95、FY2029 0.92 | C8: =E184 -> 72 | D8: =E192 -> 0.1162173 | E8: =E203 -> 6.0573926 | F8: =E8/E$4-1 -> 0 | G8: =F184 -> 93.509796 | H8: =F192 -> 0.1152432 | I8: =F203 -> 8.1662562 | J8: =I8/I$4-1 -> -0.049938877
A9: 份額流失（C 值） | B9: 份額相對值 0.85／0.80 | C9: =E226 -> 72 | D9: =E234 -> 0.1162173 | E9: =E245 -> 6.0573926 | F9: =E9/E$4-1 -> 0 | G9: =F226 -> 84.863109 | H9: =F234 -> 0.11573322 | I9: =F245 -> 7.3077563 | J9: =I9/I$4-1 -> -0.14981663
A10: 治理事件：大客戶流失 | B10: FY2027 指引下緣、FY2028 起份額 ×0.8（出口管制、會計或內控事件使客戶轉向 Dell、ODM） | C10: =E268 -> 65 | D10: =E276 -> 0.11684013 | E10: =E287 -> 5.3842902 | F10: =E10/E$4-1 -> -0.11112081 | G10: =F268 -> 72.663244 | H10: =F276 -> 0.11662296 | I10: =F287 -> 6.1210471 | J10: =I10/I$4-1 -> -0.28787822
A11: 每顆系統價值 低 | B11: 2028–29 Rubin 世代 ×0.85 | C11: =E310 -> 72 | D11: =E318 -> 0.1162173 | E11: =E329 -> 6.0573926 | F11: =E11/E$4-1 -> 0 | G11: =F310 -> 91.130132 | H11: =F318 -> 0.11536879 | I11: =F329 -> 7.9299874 | J11: =I11/I$4-1 -> -0.077426348
A12: 每顆系統價值 高 | B12: ×1.2 | C12: =E352 -> 72 | D12: =E360 -> 0.1162173 | E12: =E371 -> 6.0573926 | F12: =E12/E$4-1 -> 0 | G12: =F352 -> 106.77048 | H12: =F360 -> 0.11464589 | I12: =F371 -> 9.4828643 | J12: =I12/I$4-1 -> 0.10323513
A13: AI 毛利率 基準（B 值） | B13: FY2027 +0.5pt、FY2028 起 +0.3pt | C13: =E394 -> 72 | D13: =E402 -> 0.10767901 | E13: =E413 -> 5.4385099 | F13: =E13/E$4-1 -> -0.10216981 | G13: =F394 -> 97.83314 | H13: =F402 -> 0.10442484 | I13: =F413 -> 7.5612821 | J13: =I13/I$4-1 -> -0.12032148
A14: AI 毛利率 低（C 值） | B14: FY2027 −0.5pt、FY2028 起 −1.5pt | C14: =E436 -> 72 | D14: =E444 -> 0.099140724 | E14: =E455 -> 4.8196272 | F14: =E14/E$4-1 -> -0.20433962 | G14: =F436 -> 97.83314 | H14: =F444 -> 0.088516078 | I14: =F455 -> 6.0099461 | J14: =I14/I$4-1 -> -0.30080369
A15: 非 AI 毛利率 13% | B15: 基準 15% | C15: =E478 -> 72 | D15: =E486 -> 0.11851856 | E15: =E497 -> 6.2241955 | F15: =E15/E$4-1 -> 0.027537087 | G15: =F478 -> 97.83314 | H15: =F486 -> 0.11811528 | I15: =F497 -> 8.8962998 | J15: =I15/I$4-1 -> 0.034994294
A16: 非 AI 毛利率 18% | B16: 基準 15% | C16: =E520 -> 72 | D16: =E528 -> 0.11276541 | E16: =E539 -> 5.8071881 | F16: =E16/E$4-1 -> -0.04130563 | G16: =F520 -> 97.83314 | H16: =F528 -> 0.11040377 | I16: =F539 -> 8.1443156 | J16: =I16/I$4-1 -> -0.052491441
A17: 非 AI 成長 低 | B17: FY2027 0%、FY2028–29 −5% | C17: =E562 -> 72 | D17: =E570 -> 0.11546294 | E17: =E581 -> 6.0027141 | F17: =E17/E$4-1 -> -0.0090267282 | G17: =F562 -> 97.091662 | H17: =F570 -> 0.1139768 | I17: =F581 -> 8.4165005 | J17: =I17/I$4-1 -> -0.020825483
A18: 非 AI 成長 高 | B18: FY2027 +30%、FY2028 +20%、FY2029 +15% | C18: =E604 -> 72 | D18: =E612 -> 0.11697166 | E18: =E623 -> 6.112071 | F18: =E18/E$4-1 -> 0.0090267282 | G18: =F604 -> 98.812558 | H18: =F612 -> 0.1161504 | I18: =F623 -> 8.8075198 | J18: =I18/I$4-1 -> 0.024665644
A19: 營業費用率 +0.2pt | B19: 營業費用額外 +0.2% × 營收 | C19: =E646 -> 72 | D19: =E654 -> 0.1162173 | E19: =E665 -> 5.9124261 | F19: =E19/E$4-1 -> -0.023932153 | G19: =F646 -> 97.83314 | H19: =F654 -> 0.11503067 | I19: =F665 -> 8.4004769 | J19: =I19/I$4-1 -> -0.022689669
A20: 營業費用彈性 0.6 | B20: 基準 0.4 | C20: =E688 -> 72 | D20: =E696 -> 0.1162173 | E20: =E707 -> 5.8100759 | F20: =E20/E$4-1 -> -0.040828897 | G20: =F688 -> 97.83314 | H20: =F696 -> 0.11503067 | I20: =F707 -> 8.1585833 | J20: =I20/I$4-1 -> -0.050831535
A21: 淨利 ÷ 營業利益 0.68 | B21: 利息（營運資金借款）、合規與法律費用上升；1Q FY27 指引隱含值 | C21: =E730 -> 72 | D21: =E738 -> 0.1162173 | E21: =E749 -> 5.4542171 | F21: =E21/E$4-1 -> -0.099576744 | G21: =F730 -> 97.83314 | H21: =F738 -> 0.11503067 | I21: =F749 -> 7.7558145 | J21: =I21/I$4-1 -> -0.097689604
A22: 淨利 ÷ 營業利益 0.80 | B22: FY2026 實測約 0.805 | C22: =E772 -> 72 | D22: =E780 -> 0.1162173 | E22: =E791 -> 6.4882321 | F22: =E22/E$4-1 -> 0.071126246 | G22: =F772 -> 97.83314 | H22: =F780 -> 0.11503067 | I22: =F791 -> 9.1952858 | J22: =I22/I$4-1 -> 0.069778288
A23: 情境 B | B23: CY2028 顆數 ×0.8、CY2029 ×0.85；指引中點；份額、毛利率 B 值 | C23: =PL!E120 -> 68.5 | D23: =PL!E128 -> 0.1080492 | E23: =PL!E139 -> 5.1371936 | F23: =E23/E$4-1 -> -0.15191338 | G23: =PL!F120 -> 80.639712 | H23: =PL!F128 -> 0.10570219 | I23: =PL!F139 -> 6.0711368 | J23: =I23/I$4-1 -> -0.29368478
A24: 情境 C | B24: CY2028–29 顆數 ×0.6；指引下緣；份額、毛利率 C 值 | C24: =PL!E162 -> 65 | D24: =PL!E170 -> 0.10007838 | E24: =PL!E181 -> 4.2874644 | F24: =E24/E$4-1 -> -0.29219307 | G24: =PL!F162 -> 62.717571 | H24: =PL!F170 -> 0.093041303 | I24: =PL!F181 -> 3.5774246 | J24: =I24/I$4-1 -> -0.58380291
A26: 讀法：FY2027 營收以指引校準，所以 FY2027 主要受指引區間、毛利率與淨利係數影響；FY2028 起顆數情境、份額與每顆價值才發揮作用。美超微淨利率只有約 5%–6%，AI 毛利率每 1 個百分點約影響 EPS 10%。治理事件以份額與淨利係數案例呈現，不改情境結構。
A28: 目標價參數（只改 DCF 參數；PL 收斂法的 fade_g 不隨 tp_g 變動）
A29: 案例 | B29: 設定 | C29: DCF 目標價 | D29: Comparable 目標價 | E29: 加權目標價 | F29: 相對基準
A30: 基準 | B30: r 10%、g 4%、DCF 權重 0.5 | C30: =(tp_wA*MAX(0,Val!B8*(1-MIN(tp_g/tp_roe,0.8))/(1+tp_r)^1+Val!B9*(1-MIN(tp_g/tp_roe,0.8))/(1+tp_r)^2+Val!B10*(1-MIN(tp_g/tp_roe,0.8))/(1+tp_r)^3+Val!B11*(1-MIN(tp_g/tp_roe,0.8))/(1+tp_r)^4+Val!B12*(1-MIN(tp_g/tp_roe,0.8))/(1+tp_r)^5+Val!B13*(1-MIN(tp_g/tp_roe,0.8))/(1+tp_r)^6+Val!B13*(1-MIN(tp_g/tp_roe,0.8))*(1+tp_g)/(tp_r-tp_g)/(1+tp_r)^6)+tp_wB*MAX(0,Val!C8*(1-MIN(tp_g/tp_roe,0.8))/(1+tp_r)^1+Val!C9*(1-MIN(tp_g/tp_roe,0.8))/(1+tp_r)^2+Val!C10*(1-MIN(tp_g/tp_roe,0.8))/(1+tp_r)^3+Val!C11*(1-MIN(tp_g/tp_roe,0.8))/(1+tp_r)^4+Val!C12*(1-MIN(tp_g/tp_roe,0.8))/(1+tp_r)^5+Val!C13*(1-MIN(tp_g/tp_roe,0.8))/(1+tp_r)^6+Val!C13*(1-MIN(tp_g/tp_roe,0.8))*(1+tp_g)/(tp_r-tp_g)/(1+tp_r)^6)+tp_wC*MAX(0,Val!D8*(1-MIN(tp_g/tp_roe,0.8))/(1+tp_r)^1+Val!D9*(1-MIN(tp_g/tp_roe,0.8))/(1+tp_r)^2+Val!D10*(1-MIN(tp_g/tp_roe,0.8))/(1+tp_r)^3+Val!D11*(1-MIN(tp_g/tp_roe,0.8))/(1+tp_r)^4+Val!D12*(1-MIN(tp_g/tp_roe,0.8))/(1+tp_r)^5+Val!D13*(1-MIN(tp_g/tp_roe,0.8))/(1+tp_r)^6+Val!D13*(1-MIN(tp_g/tp_roe,0.8))*(1+tp_g)/(tp_r-tp_g)/(1+tp_r)^6))*(1+tp_r) -> 77.972487 | D30: =Val!B35 -> 75.204499 | E30: =tp_w_dcf*C30+(1-tp_w_dcf)*D30 -> 76.588493 | F30: =E30/E$30-1 -> 0
A31: 折現率 +1pt | B31: r 11% | C31: =(tp_wA*MAX(0,Val!B8*(1-MIN(tp_g/tp_roe,0.8))/(1+(tp_r+0.01))^1+Val!B9*(1-MIN(tp_g/tp_roe,0.8))/(1+(tp_r+0.01))^2+Val!B10*(1-MIN(tp_g/tp_roe,0.8))/(1+(tp_r+0.01))^3+Val!B11*(1-MIN(tp_g/tp_roe,0.8))/(1+(tp_r+0.01))^4+Val!B12*(1-MIN(tp_g/tp_roe,0.8))/(1+(tp_r+0.01))^5+Val!B13*(1-MIN(tp_g/tp_roe,0.8))/(1+(tp_r+0.01))^6+Val!B13*(1-MIN(tp_g/tp_roe,0.8))*(1+tp_g)/((tp_r+0.01)-tp_g)/(1+(tp_r+0.01))^6)+tp_wB*MAX(0,Val!C8*(1-MIN(tp_g/tp_roe,0.8))/(1+(tp_r+0.01))^1+Val!C9*(1-MIN(tp_g/tp_roe,0.8))/(1+(tp_r+0.01))^2+Val!C10*(1-MIN(tp_g/tp_roe,0.8))/(1+(tp_r+0.01))^3+Val!C11*(1-MIN(tp_g/tp_roe,0.8))/(1+(tp_r+0.01))^4+Val!C12*(1-MIN(tp_g/tp_roe,0.8))/(1+(tp_r+0.01))^5+Val!C13*(1-MIN(tp_g/tp_roe,0.8))/(1+(tp_r+0.01))^6+Val!C13*(1-MIN(tp_g/tp_roe,0.8))*(1+tp_g)/((tp_r+0.01)-tp_g)/(1+(tp_r+0.01))^6)+tp_wC*MAX(0,Val!D8*(1-MIN(tp_g/tp_roe,0.8))/(1+(tp_r+0.01))^1+Val!D9*(1-MIN(tp_g/tp_roe,0.8))/(1+(tp_r+0.01))^2+Val!D10*(1-MIN(tp_g/tp_roe,0.8))/(1+(tp_r+0.01))^3+Val!D11*(1-MIN(tp_g/tp_roe,0.8))/(1+(tp_r+0.01))^4+Val!D12*(1-MIN(tp_g/tp_roe,0.8))/(1+(tp_r+0.01))^5+Val!D13*(1-MIN(tp_g/tp_roe,0.8))/(1+(tp_r+0.01))^6+Val!D13*(1-MIN(tp_g/tp_roe,0.8))*(1+tp_g)/((tp_r+0.01)-tp_g)/(1+(tp_r+0.01))^6))*(1+(tp_r+0.01)) -> 67.707435 | D31: =Val!B35 -> 75.204499 | E31: =tp_w_dcf*C31+(1-tp_w_dcf)*D31 -> 71.455967 | F31: =E31/E$30-1 -> -0.067014325
A32: 折現率 −1pt | B32: r 9% | C32: =(tp_wA*MAX(0,Val!B8*(1-MIN(tp_g/tp_roe,0.8))/(1+(tp_r-0.01))^1+Val!B9*(1-MIN(tp_g/tp_roe,0.8))/(1+(tp_r-0.01))^2+Val!B10*(1-MIN(tp_g/tp_roe,0.8))/(1+(tp_r-0.01))^3+Val!B11*(1-MIN(tp_g/tp_roe,0.8))/(1+(tp_r-0.01))^4+Val!B12*(1-MIN(tp_g/tp_roe,0.8))/(1+(tp_r-0.01))^5+Val!B13*(1-MIN(tp_g/tp_roe,0.8))/(1+(tp_r-0.01))^6+Val!B13*(1-MIN(tp_g/tp_roe,0.8))*(1+tp_g)/((tp_r-0.01)-tp_g)/(1+(tp_r-0.01))^6)+tp_wB*MAX(0,Val!C8*(1-MIN(tp_g/tp_roe,0.8))/(1+(tp_r-0.01))^1+Val!C9*(1-MIN(tp_g/tp_roe,0.8))/(1+(tp_r-0.01))^2+Val!C10*(1-MIN(tp_g/tp_roe,0.8))/(1+(tp_r-0.01))^3+Val!C11*(1-MIN(tp_g/tp_roe,0.8))/(1+(tp_r-0.01))^4+Val!C12*(1-MIN(tp_g/tp_roe,0.8))/(1+(tp_r-0.01))^5+Val!C13*(1-MIN(tp_g/tp_roe,0.8))/(1+(tp_r-0.01))^6+Val!C13*(1-MIN(tp_g/tp_roe,0.8))*(1+tp_g)/((tp_r-0.01)-tp_g)/(1+(tp_r-0.01))^6)+tp_wC*MAX(0,Val!D8*(1-MIN(tp_g/tp_roe,0.8))/(1+(tp_r-0.01))^1+Val!D9*(1-MIN(tp_g/tp_roe,0.8))/(1+(tp_r-0.01))^2+Val!D10*(1-MIN(tp_g/tp_roe,0.8))/(1+(tp_r-0.01))^3+Val!D11*(1-MIN(tp_g/tp_roe,0.8))/(1+(tp_r-0.01))^4+Val!D12*(1-MIN(tp_g/tp_roe,0.8))/(1+(tp_r-0.01))^5+Val!D13*(1-MIN(tp_g/tp_roe,0.8))/(1+(tp_r-0.01))^6+Val!D13*(1-MIN(tp_g/tp_roe,0.8))*(1+tp_g)/((tp_r-0.01)-tp_g)/(1+(tp_r-0.01))^6))*(1+(tp_r-0.01)) -> 92.331922 | D32: =Val!B35 -> 75.204499 | E32: =tp_w_dcf*C32+(1-tp_w_dcf)*D32 -> 83.768211 | F32: =E32/E$30-1 -> 0.093744076
A33: 長期成長 +1pt | B33: g 5% | C33: =(tp_wA*MAX(0,Val!B8*(1-MIN((tp_g+0.01)/tp_roe,0.8))/(1+tp_r)^1+Val!B9*(1-MIN((tp_g+0.01)/tp_roe,0.8))/(1+tp_r)^2+Val!B10*(1-MIN((tp_g+0.01)/tp_roe,0.8))/(1+tp_r)^3+Val!B11*(1-MIN((tp_g+0.01)/tp_roe,0.8))/(1+tp_r)^4+Val!B12*(1-MIN((tp_g+0.01)/tp_roe,0.8))/(1+tp_r)^5+Val!B13*(1-MIN((tp_g+0.01)/tp_roe,0.8))/(1+tp_r)^6+Val!B13*(1-MIN((tp_g+0.01)/tp_roe,0.8))*(1+(tp_g+0.01))/(tp_r-(tp_g+0.01))/(1+tp_r)^6)+tp_wB*MAX(0,Val!C8*(1-MIN((tp_g+0.01)/tp_roe,0.8))/(1+tp_r)^1+Val!C9*(1-MIN((tp_g+0.01)/tp_roe,0.8))/(1+tp_r)^2+Val!C10*(1-MIN((tp_g+0.01)/tp_roe,0.8))/(1+tp_r)^3+Val!C11*(1-MIN((tp_g+0.01)/tp_roe,0.8))/(1+tp_r)^4+Val!C12*(1-MIN((tp_g+0.01)/tp_roe,0.8))/(1+tp_r)^5+Val!C13*(1-MIN((tp_g+0.01)/tp_roe,0.8))/(1+tp_r)^6+Val!C13*(1-MIN((tp_g+0.01)/tp_roe,0.8))*(1+(tp_g+0.01))/(tp_r-(tp_g+0.01))/(1+tp_r)^6)+tp_wC*MAX(0,Val!D8*(1-MIN((tp_g+0.01)/tp_roe,0.8))/(1+tp_r)^1+Val!D9*(1-MIN((tp_g+0.01)/tp_roe,0.8))/(1+tp_r)^2+Val!D10*(1-MIN((tp_g+0.01)/tp_roe,0.8))/(1+tp_r)^3+Val!D11*(1-MIN((tp_g+0.01)/tp_roe,0.8))/(1+tp_r)^4+Val!D12*(1-MIN((tp_g+0.01)/tp_roe,0.8))/(1+tp_r)^5+Val!D13*(1-MIN((tp_g+0.01)/tp_roe,0.8))/(1+tp_r)^6+Val!D13*(1-MIN((tp_g+0.01)/tp_roe,0.8))*(1+(tp_g+0.01))/(tp_r-(tp_g+0.01))/(1+tp_r)^6))*(1+tp_r) -> 84.840122 | D33: =Val!B35 -> 75.204499 | E33: =tp_w_dcf*C33+(1-tp_w_dcf)*D33 -> 80.02231 | F33: =E33/E$30-1 -> 0.044834635
A34: 長期成長 −1pt | B34: g 3% | C34: =(tp_wA*MAX(0,Val!B8*(1-MIN((tp_g-0.01)/tp_roe,0.8))/(1+tp_r)^1+Val!B9*(1-MIN((tp_g-0.01)/tp_roe,0.8))/(1+tp_r)^2+Val!B10*(1-MIN((tp_g-0.01)/tp_roe,0.8))/(1+tp_r)^3+Val!B11*(1-MIN((tp_g-0.01)/tp_roe,0.8))/(1+tp_r)^4+Val!B12*(1-MIN((tp_g-0.01)/tp_roe,0.8))/(1+tp_r)^5+Val!B13*(1-MIN((tp_g-0.01)/tp_roe,0.8))/(1+tp_r)^6+Val!B13*(1-MIN((tp_g-0.01)/tp_roe,0.8))*(1+(tp_g-0.01))/(tp_r-(tp_g-0.01))/(1+tp_r)^6)+tp_wB*MAX(0,Val!C8*(1-MIN((tp_g-0.01)/tp_roe,0.8))/(1+tp_r)^1+Val!C9*(1-MIN((tp_g-0.01)/tp_roe,0.8))/(1+tp_r)^2+Val!C10*(1-MIN((tp_g-0.01)/tp_roe,0.8))/(1+tp_r)^3+Val!C11*(1-MIN((tp_g-0.01)/tp_roe,0.8))/(1+tp_r)^4+Val!C12*(1-MIN((tp_g-0.01)/tp_roe,0.8))/(1+tp_r)^5+Val!C13*(1-MIN((tp_g-0.01)/tp_roe,0.8))/(1+tp_r)^6+Val!C13*(1-MIN((tp_g-0.01)/tp_roe,0.8))*(1+(tp_g-0.01))/(tp_r-(tp_g-0.01))/(1+tp_r)^6)+tp_wC*MAX(0,Val!D8*(1-MIN((tp_g-0.01)/tp_roe,0.8))/(1+tp_r)^1+Val!D9*(1-MIN((tp_g-0.01)/tp_roe,0.8))/(1+tp_r)^2+Val!D10*(1-MIN((tp_g-0.01)/tp_roe,0.8))/(1+tp_r)^3+Val!D11*(1-MIN((tp_g-0.01)/tp_roe,0.8))/(1+tp_r)^4+Val!D12*(1-MIN((tp_g-0.01)/tp_roe,0.8))/(1+tp_r)^5+Val!D13*(1-MIN((tp_g-0.01)/tp_roe,0.8))/(1+tp_r)^6+Val!D13*(1-MIN((tp_g-0.01)/tp_roe,0.8))*(1+(tp_g-0.01))/(tp_r-(tp_g-0.01))/(1+tp_r)^6))*(1+tp_r) -> 73.370458 | D34: =Val!B35 -> 75.204499 | E34: =tp_w_dcf*C34+(1-tp_w_dcf)*D34 -> 74.287479 | F34: =E34/E$30-1 -> -0.030043871
A35: DCF 權重 0.3 | C35: =(tp_wA*MAX(0,Val!B8*(1-MIN(tp_g/tp_roe,0.8))/(1+tp_r)^1+Val!B9*(1-MIN(tp_g/tp_roe,0.8))/(1+tp_r)^2+Val!B10*(1-MIN(tp_g/tp_roe,0.8))/(1+tp_r)^3+Val!B11*(1-MIN(tp_g/tp_roe,0.8))/(1+tp_r)^4+Val!B12*(1-MIN(tp_g/tp_roe,0.8))/(1+tp_r)^5+Val!B13*(1-MIN(tp_g/tp_roe,0.8))/(1+tp_r)^6+Val!B13*(1-MIN(tp_g/tp_roe,0.8))*(1+tp_g)/(tp_r-tp_g)/(1+tp_r)^6)+tp_wB*MAX(0,Val!C8*(1-MIN(tp_g/tp_roe,0.8))/(1+tp_r)^1+Val!C9*(1-MIN(tp_g/tp_roe,0.8))/(1+tp_r)^2+Val!C10*(1-MIN(tp_g/tp_roe,0.8))/(1+tp_r)^3+Val!C11*(1-MIN(tp_g/tp_roe,0.8))/(1+tp_r)^4+Val!C12*(1-MIN(tp_g/tp_roe,0.8))/(1+tp_r)^5+Val!C13*(1-MIN(tp_g/tp_roe,0.8))/(1+tp_r)^6+Val!C13*(1-MIN(tp_g/tp_roe,0.8))*(1+tp_g)/(tp_r-tp_g)/(1+tp_r)^6)+tp_wC*MAX(0,Val!D8*(1-MIN(tp_g/tp_roe,0.8))/(1+tp_r)^1+Val!D9*(1-MIN(tp_g/tp_roe,0.8))/(1+tp_r)^2+Val!D10*(1-MIN(tp_g/tp_roe,0.8))/(1+tp_r)^3+Val!D11*(1-MIN(tp_g/tp_roe,0.8))/(1+tp_r)^4+Val!D12*(1-MIN(tp_g/tp_roe,0.8))/(1+tp_r)^5+Val!D13*(1-MIN(tp_g/tp_roe,0.8))/(1+tp_r)^6+Val!D13*(1-MIN(tp_g/tp_roe,0.8))*(1+tp_g)/(tp_r-tp_g)/(1+tp_r)^6))*(1+tp_r) -> 77.972487 | D35: =Val!B35 -> 75.204499 | E35: =0.3*C35+(1-0.3)*D35 -> 76.034896 | F35: =E35/E$30-1 -> -0.0072282086
A36: DCF 權重 0.7 | C36: =(tp_wA*MAX(0,Val!B8*(1-MIN(tp_g/tp_roe,0.8))/(1+tp_r)^1+Val!B9*(1-MIN(tp_g/tp_roe,0.8))/(1+tp_r)^2+Val!B10*(1-MIN(tp_g/tp_roe,0.8))/(1+tp_r)^3+Val!B11*(1-MIN(tp_g/tp_roe,0.8))/(1+tp_r)^4+Val!B12*(1-MIN(tp_g/tp_roe,0.8))/(1+tp_r)^5+Val!B13*(1-MIN(tp_g/tp_roe,0.8))/(1+tp_r)^6+Val!B13*(1-MIN(tp_g/tp_roe,0.8))*(1+tp_g)/(tp_r-tp_g)/(1+tp_r)^6)+tp_wB*MAX(0,Val!C8*(1-MIN(tp_g/tp_roe,0.8))/(1+tp_r)^1+Val!C9*(1-MIN(tp_g/tp_roe,0.8))/(1+tp_r)^2+Val!C10*(1-MIN(tp_g/tp_roe,0.8))/(1+tp_r)^3+Val!C11*(1-MIN(tp_g/tp_roe,0.8))/(1+tp_r)^4+Val!C12*(1-MIN(tp_g/tp_roe,0.8))/(1+tp_r)^5+Val!C13*(1-MIN(tp_g/tp_roe,0.8))/(1+tp_r)^6+Val!C13*(1-MIN(tp_g/tp_roe,0.8))*(1+tp_g)/(tp_r-tp_g)/(1+tp_r)^6)+tp_wC*MAX(0,Val!D8*(1-MIN(tp_g/tp_roe,0.8))/(1+tp_r)^1+Val!D9*(1-MIN(tp_g/tp_roe,0.8))/(1+tp_r)^2+Val!D10*(1-MIN(tp_g/tp_roe,0.8))/(1+tp_r)^3+Val!D11*(1-MIN(tp_g/tp_roe,0.8))/(1+tp_r)^4+Val!D12*(1-MIN(tp_g/tp_roe,0.8))/(1+tp_r)^5+Val!D13*(1-MIN(tp_g/tp_roe,0.8))/(1+tp_r)^6+Val!D13*(1-MIN(tp_g/tp_roe,0.8))*(1+tp_g)/(tp_r-tp_g)/(1+tp_r)^6))*(1+tp_r) -> 77.972487 | D36: =Val!B35 -> 75.204499 | E36: =0.7*C36+(1-0.7)*D36 -> 77.142091 | F36: =E36/E$30-1 -> 0.0072282086
A40: 案例區塊：AI 部署 ×0.8（情境 A）
A41: 項目 | B41: 單位 | C41: FY2025A | D41: FY2026A（錨點） | E41: FY2027 | F41: FY2028 | G41: FY2029 | H41: FY2030（收斂） | I41: FY2031（收斂） | J41: FY2032（收斂） | K41: 說明
A42: A. 商用 GPU 系統市場（D–G 欄的「CY」列為日曆年 CY2026–CY2029；「FY」列為美超微會計年度）
A43: GB300 世代商用 GPU 顆數（CY） | B43: 百萬顆 | D43: =uo_26 -> 6.65 | E43: =uo_27*mf_lo -> 1.92 | F43: =uo_28*um28_A*mf_lo -> 0.4 | G43: =uo_29*um29_A*mf_lo -> 0.2 | K43: Blackwell＋Hopper（2026 另含 AMD MI355）；台積電模型顆數 × 情境係數
A44: Rubin 世代商用 GPU 顆數（CY） | B44: 百萬顆 | D44: =un_26 -> 1.7 | E44: =un_27*mf_lo -> 7.04 | F44: =un_28*um28_A*mf_lo -> 8.8 | G44: =un_29*um29_A*mf_lo -> 10.12 | K44: Rubin＋Rubin Ultra（2027 起另含 AMD MI450）
A45: 每顆系統價值：GB300 世代（CY） | B45: 千美元/顆 | D45: =v_gb -> 59.722222 | E45: =v_gb -> 59.722222 | F45: =v_gb -> 59.722222 | G45: =v_gb -> 59.722222
A46: 每顆系統價值：Rubin 世代（CY） | B46: 千美元/顆 | D46: =v_vr -> 116.66667 | E46: =v_vr -> 116.66667 | F46: =v_vr*vpg_28 -> 116.66667 | G46: =v_vr*vpg_29 -> 116.66667 | K46: 整櫃買方價 ÷ 每架 GPU 封裝數（橋接表）
A47: 商用 GPU 系統市場（CY） | B47: US$B | D47: =(D43*D45+D44*D46) -> 595.48611 | E47: =(E43*E45+E44*E46) -> 936 | F47: =(F43*F45+F44*F46) -> 1050.5556 | G47: =(G43*G45+G44*G46) -> 1192.6111 | K47: 顆數 × 每顆系統價值；含 NVIDIA 與 AMD，不含 TPU、Trainium 與其他 ASIC
A48: 商用 GPU 系統市場（FY＝½ 前一 CY＋½ 當年 CY） | B48: US$B | E48: =0.5*D47+0.5*E47 -> 765.74306 | F48: =0.5*E47+0.5*F47 -> 993.27778 | G48: =0.5*F47+0.5*G47 -> 1121.5833 | K48: 會計年度 7 月～6 月：各取前後日曆年一半（Derived；未考慮年內出貨季節性）
A49: FY2027 市場（部署係數 1.0；份額校準用） | B49: US$B | E49: =0.5*D47+0.5*(uo_27*v_gb+un_27*v_vr) -> 882.74306 | K49: 份額以基準市場校準，Sens 的部署係數才會改變 FY2027 營收
A50: 美超微有效份額（2H FY26 校準）＝ 2026-01～06 AI 營收 ÷ ½ CY2026 市場 | B50: % | D50: =a26_aih2/(0.5*D47) -> 0.049929494 | K50: Derived：CY2026 上下半年各半（Rubin 下半年放量，上半年市場偏小，此份額偏低估）；只作對照
A51: FY2027 營收（公司指引；A 上緣、B 中點、C 下緣） | B51: US$B | E51: =g27_hi -> 72 | K51: Interested-party：公司 2026-08-11 指引 650～720 億美元
A52: 份額相對值（÷ FY2027） | B52: x | E52: =1 -> 1 | F52: =rel_28_hi*1 -> 1 | G52: =rel_29_hi*1 -> 1 | K52: A 最有利、C 最不利（Assumed）；治理事件案例另見 Sens
A53: 美超微有效份額（FY2027 以指引校準） | B53: % | E53: =(E51-E57)/E49 -> 0.069641644 | F53: =$E53*F52 -> 0.069641644 | G53: =$E53*G52 -> 0.069641644 | K53: FY2027：（指引營收 − 非 AI 營收）÷ 基準市場；4Q FY26 逾 600 億美元新訂單使份額高於 2H FY26
A54: FY2027 份額 ÷ 2H FY26 份額 | B54: x | E54: =E53/D50 -> 1.3947997 | K54: Derived：指引隱含的份額上升幅度
A55: AI GPU 平台營收 | B55: US$B | C55: =a25_ai -> 15.3804 | D55: =a26_ai -> 29.911415 | E55: =E48*E53 -> 53.327605 | F55: =F48*F53 -> 69.173497 | G55: =G48*G53 -> 78.108907
A56: B. 非 AI 與合計
A57: 非 AI（企業、儲存、邊緣等） | B57: US$B | C57: =a25_nai -> 6.5916 | D57: =a26_nai -> 9.151585 | E57: =D57*(1+g_nai27) -> 10.524323 | F57: =E57*(1+g_nai28) -> 11.366269 | G57: =F57*(1+g_nai29) -> 12.048245
A58: 營收 | B58: US$B | C58: =C55+C57 -> 21.972 | D58: =D55+D57 -> 39.063 | E58: =E55+E57 -> 63.851928 | F58: =F55+F57 -> 80.539766 | G58: =G55+G57 -> 90.157151 | H58: =G58*(1+H59) -> 99.137504 | I58: =H58*(1+I59) -> 107.04906 | J58: =I58*(1+J59) -> 113.472 | K58: FY2030 起為收斂法：營收年增由 FY2029 線性收斂到 fade_g、淨利率由 FY2029 特別股股利前淨利率收斂到 fade_m（FY2032 達到），非驅動因子推導；FY2030 股數加特別股轉換股數
A59: 營收年增 | B59: % | D59: =D58/C58-1 -> 0.77785363 | E59: =E58/D58-1 -> 0.63458843 | F59: =F58/E58-1 -> 0.26135214 | G59: =G58/F58-1 -> 0.11941164 | H59: =$G59+(fade_gA-$G59)*1/3 -> 0.099607763 | I59: =$G59+(fade_gA-$G59)*2/3 -> 0.079803882 | J59: =$G59+(fade_gA-$G59)*3/3 -> 0.06
A60: AI GPU 平台 ÷ 營收 | B60: % | C60: =C55/C58 -> 0.7 | D60: =D55/D58 -> 0.76572242 | E60: =E55/E58 -> 0.83517612 | F60: =F55/F58 -> 0.85887383 | G60: =G55/G58 -> 0.86636396
A61: 隱含美超微商用 GPU 出貨（AI 營收 ÷ 每顆平均系統價值） | B61: 百萬顆 | E61: =E55/((0.5*(D43*D45+D44*D46)+0.5*(E43*E45+E44*E46))/(0.5*(D43+D44)+0.5*(E43+E44))) -> 0.60274843 | F61: =F55/((0.5*(E43*E45+E44*E46)+0.5*(F43*F45+F44*F46))/(0.5*(E43+E44)+0.5*(F43+F44))) -> 0.63234612 | G61: =G55/((0.5*(F43*F45+F44*F46)+0.5*(G43*G45+G44*G46))/(0.5*(F43+F44)+0.5*(G43+G44))) -> 0.67970244 | K61: 對照用：份額 × 會計年度商用 GPU 顆數
A62: C. 損益
A63: AI 毛利率 FY2026 校準值 ＝（毛利 − 非 AI 毛利率 × 非 AI 營收）÷ AI 營收 | B63: % | D63: =(a26_gp-gm_nai*a26_nai)/a26_ai -> 0.095433875 | K63: Derived：FY2026 含 4Q 一次性利益（遞延合約、關稅、存貨跌價回轉），校準值偏高
A64: AI 毛利率 | B64: % | D64: =D63 -> 0.095433875 | E64: =$D63+dgm_27_hi -> 0.11043388 | F64: =$D63+dgm_28_hi -> 0.11043388 | G64: =$D63+dgm_28_hi -> 0.11043388 | K64: A 最高、C 最低（In 頁 C 節）
A65: 毛利 | B65: US$B | C65: =a25_gp -> 2.4299 | D65: =a26_gp -> 4.2273 | E65: =E64*E55+gm_nai*E57 -> 7.4678225 | F65: =F64*F55+gm_nai*F57 -> 9.3440376 | G65: =G64*G55+gm_nai*G57 -> 10.433106
A66: 毛利率 | B66: % | C66: =C65/C58 -> 0.11059075 | D66: =D65/D58 -> 0.10821749 | E66: =E65/E58 -> 0.11695532 | F66: =F65/F58 -> 0.11601769 | G66: =G65/G58 -> 0.11572134
A67: 營業費用（基準路徑） | B67: US$B | C67: =a25_opx -> 1.1769 | D67: =a26_opx -> 1.4568 | E67: =D67*(1+MAX(0,phi*E59)) -> 1.8265874 | F67: =E67*(1+MAX(0,phi*F59)) -> 2.0175404 | G67: =F67*(1+MAX(0,phi*G59)) -> 2.1139075
A68: 營業費用 | B68: US$B | C68: =C67 -> 1.1769 | D68: =D67 -> 1.4568 | E68: =E67+0*E58 -> 1.8265874 | F68: =F67+0*F58 -> 2.0175404 | G68: =G67+0*G58 -> 2.1139075
A69: 營業利益 | B69: US$B | C69: =C65-C68 -> 1.253 | D69: =D65-D68 -> 2.7705 | E69: =E65-E68 -> 5.6412351 | F69: =F65-F68 -> 7.3264973 | G69: =G65-G68 -> 8.3191985
A70: 營業利益率 | B70: % | C70: =C69/C58 -> 0.057027125 | D70: =D69/D58 -> 0.070923892 | E70: =E69/E58 -> 0.088348705 | F70: =F69/F58 -> 0.090967452 | G70: =G69/G58 -> 0.092274416
A71: 淨利（特別股股利前）÷ 營業利益 | B71: % | C71: =a25_ni/a25_oi -> 0.83711093 | D71: =a26_ni/a26_oi -> 0.80508933 | E71: =nio_f -> 0.75 | F71: =nio_f -> 0.75 | G71: =nio_f -> 0.75
A72: 淨利（特別股股利前） | B72: US$B | C72: =a25_ni -> 1.0489 | D72: =a26_ni -> 2.2305 | E72: =E69*E71 -> 4.2309263 | F72: =F69*F71 -> 5.4948729 | G72: =G69*G71 -> 6.2393989
A73: 特別股股利 | B73: US$B | C73: =0 -> 0 | D73: =0 -> 0 | E73: =pref_div -> 0.301875 | F73: =pref_div -> 0.301875 | G73: =pref_div -> 0.301875 | K73: FY2026 只有約 3 週，已含在實績；2029-06 強制轉換後為 0
A74: 歸屬母公司淨利 | B74: US$B | C74: =C72-C73 -> 1.0489 | D74: =D72-D73 -> 2.2305 | E74: =E72-E73 -> 3.9290513 | F74: =F72-F73 -> 5.1929979 | G74: =G72-G73 -> 5.9375239 | H74: =H58*H79 -> 6.890908 | I74: =I58*I79 -> 7.4732413 | J74: =J58*J79 -> 7.9559925 | K74: 扣除特別股股利後、歸屬普通股（GAAP）
A75: 淨利率（特別股股利前） | B75: % | C75: =C72/C58 -> 0.04773803 | D75: =D72/D58 -> 0.057100069 | E75: =E72/E58 -> 0.066261529 | F75: =F72/F58 -> 0.068225589 | G75: =G72/G58 -> 0.069205812 | K75: 收斂法的起點（FY2030 起特別股已轉換）
A76: 股數（GAAP 稀釋） | B76: 十億股 | C76: =a25_sh -> 0.62434524 | D76: =a26_sh -> 0.68420245 | E76: =sh27 -> 0.745 | F76: =E76*(1+sh_g) -> 0.75245 | G76: =F76*(1+sh_g) -> 0.7599745 | H76: =G76*(1+sh_g)+conv_sh -> 0.91132712 | I76: =H76*(1+sh_g) -> 0.92044039 | J76: =I76*(1+sh_g) -> 0.9296448
A77: EPS（GAAP 稀釋） | B77: US$ | C77: =C74/C76 -> 1.68 | D77: =D74/D76 -> 3.26 | E77: =E74/E76 -> 5.2738944 | F77: =F74/F76 -> 6.9014525 | G77: =G74/G76 -> 7.8127935 | H77: =H74/H76 -> 7.5613991 | I77: =I74/I76 -> 8.1192018 | J77: =J74/J76 -> 8.5580994
A78: EPS 年增 | B78: % | D78: =D77/C77-1 -> 0.94047619 | E78: =E77/D77-1 -> 0.61775902 | F78: =F77/E77-1 -> 0.3086065 | G78: =G77/F77-1 -> 0.13205061 | H78: =H77/G77-1 -> -0.032177283 | I78: =I77/H77-1 -> 0.07376978 | J78: =J77/I77-1 -> 0.054056738
A79: 淨利率（歸屬母公司淨利 ÷ 營收） | B79: % | C79: =C74/C58 -> 0.04773803 | D79: =D74/D58 -> 0.057100069 | E79: =E74/E58 -> 0.061533794 | F79: =F74/F58 -> 0.06447744 | G79: =G74/G58 -> 0.065857492 | H79: =$G75+(fade_mA-$G75)*1/3 -> 0.069508589 | I79: =$G75+(fade_mA-$G75)*2/3 -> 0.069811367 | J79: =$G75+(fade_mA-$G75)*3/3 -> 0.070114144
A82: 案例區塊：AI 部署 ×1.2（情境 A）
A83: 項目 | B83: 單位 | C83: FY2025A | D83: FY2026A（錨點） | E83: FY2027 | F83: FY2028 | G83: FY2029 | H83: FY2030（收斂） | I83: FY2031（收斂） | J83: FY2032（收斂） | K83: 說明
A84: A. 商用 GPU 系統市場（D–G 欄的「CY」列為日曆年 CY2026–CY2029；「FY」列為美超微會計年度）
A85: GB300 世代商用 GPU 顆數（CY） | B85: 百萬顆 | D85: =uo_26 -> 6.65 | E85: =uo_27*mf_hi -> 2.88 | F85: =uo_28*um28_A*mf_hi -> 0.6 | G85: =uo_29*um29_A*mf_hi -> 0.3 | K85: Blackwell＋Hopper（2026 另含 AMD MI355）；台積電模型顆數 × 情境係數
A86: Rubin 世代商用 GPU 顆數（CY） | B86: 百萬顆 | D86: =un_26 -> 1.7 | E86: =un_27*mf_hi -> 10.56 | F86: =un_28*um28_A*mf_hi -> 13.2 | G86: =un_29*um29_A*mf_hi -> 15.18 | K86: Rubin＋Rubin Ultra（2027 起另含 AMD MI450）
A87: 每顆系統價值：GB300 世代（CY） | B87: 千美元/顆 | D87: =v_gb -> 59.722222 | E87: =v_gb -> 59.722222 | F87: =v_gb -> 59.722222 | G87: =v_gb -> 59.722222
A88: 每顆系統價值：Rubin 世代（CY） | B88: 千美元/顆 | D88: =v_vr -> 116.66667 | E88: =v_vr -> 116.66667 | F88: =v_vr*vpg_28 -> 116.66667 | G88: =v_vr*vpg_29 -> 116.66667 | K88: 整櫃買方價 ÷ 每架 GPU 封裝數（橋接表）
A89: 商用 GPU 系統市場（CY） | B89: US$B | D89: =(D85*D87+D86*D88) -> 595.48611 | E89: =(E85*E87+E86*E88) -> 1404 | F89: =(F85*F87+F86*F88) -> 1575.8333 | G89: =(G85*G87+G86*G88) -> 1788.9167 | K89: 顆數 × 每顆系統價值；含 NVIDIA 與 AMD，不含 TPU、Trainium 與其他 ASIC
A90: 商用 GPU 系統市場（FY＝½ 前一 CY＋½ 當年 CY） | B90: US$B | E90: =0.5*D89+0.5*E89 -> 999.74306 | F90: =0.5*E89+0.5*F89 -> 1489.9167 | G90: =0.5*F89+0.5*G89 -> 1682.375 | K90: 會計年度 7 月～6 月：各取前後日曆年一半（Derived；未考慮年內出貨季節性）
A91: FY2027 市場（部署係數 1.0；份額校準用） | B91: US$B | E91: =0.5*D89+0.5*(uo_27*v_gb+un_27*v_vr) -> 882.74306 | K91: 份額以基準市場校準，Sens 的部署係數才會改變 FY2027 營收
A92: 美超微有效份額（2H FY26 校準）＝ 2026-01～06 AI 營收 ÷ ½ CY2026 市場 | B92: % | D92: =a26_aih2/(0.5*D89) -> 0.049929494 | K92: Derived：CY2026 上下半年各半（Rubin 下半年放量，上半年市場偏小，此份額偏低估）；只作對照
A93: FY2027 營收（公司指引；A 上緣、B 中點、C 下緣） | B93: US$B | E93: =g27_hi -> 72 | K93: Interested-party：公司 2026-08-11 指引 650～720 億美元
A94: 份額相對值（÷ FY2027） | B94: x | E94: =1 -> 1 | F94: =rel_28_hi*1 -> 1 | G94: =rel_29_hi*1 -> 1 | K94: A 最有利、C 最不利（Assumed）；治理事件案例另見 Sens
A95: 美超微有效份額（FY2027 以指引校準） | B95: % | E95: =(E93-E99)/E91 -> 0.069641644 | F95: =$E95*F94 -> 0.069641644 | G95: =$E95*G94 -> 0.069641644 | K95: FY2027：（指引營收 − 非 AI 營收）÷ 基準市場；4Q FY26 逾 600 億美元新訂單使份額高於 2H FY26
A96: FY2027 份額 ÷ 2H FY26 份額 | B96: x | E96: =E95/D92 -> 1.3947997 | K96: Derived：指引隱含的份額上升幅度
A97: AI GPU 平台營收 | B97: US$B | C97: =a25_ai -> 15.3804 | D97: =a26_ai -> 29.911415 | E97: =E90*E95 -> 69.62375 | F97: =F90*F95 -> 103.76025 | G97: =G90*G95 -> 117.16336
A98: B. 非 AI 與合計
A99: 非 AI（企業、儲存、邊緣等） | B99: US$B | C99: =a25_nai -> 6.5916 | D99: =a26_nai -> 9.151585 | E99: =D99*(1+g_nai27) -> 10.524323 | F99: =E99*(1+g_nai28) -> 11.366269 | G99: =F99*(1+g_nai29) -> 12.048245
A100: 營收 | B100: US$B | C100: =C97+C99 -> 21.972 | D100: =D97+D99 -> 39.063 | E100: =E97+E99 -> 80.148072 | F100: =F97+F99 -> 115.12651 | G100: =G97+G99 -> 129.2116 | H100: =G100*(1+H101) -> 142.33472 | I100: =H100*(1+I101) -> 153.83273 | J100: =I100*(1+J101) -> 163.06269 | K100: FY2030 起為收斂法：營收年增由 FY2029 線性收斂到 fade_g、淨利率由 FY2029 特別股股利前淨利率收斂到 fade_m（FY2032 達到），非驅動因子推導；FY2030 股數加特別股轉換股數
A101: 營收年增 | B101: % | D101: =D100/C100-1 -> 0.77785363 | E101: =E100/D100-1 -> 1.0517644 | F101: =F100/E100-1 -> 0.43642275 | G101: =G100/F100-1 -> 0.12234446 | H101: =$G101+(fade_gA-$G101)*1/3 -> 0.10156297 | I101: =$G101+(fade_gA-$G101)*2/3 -> 0.080781485 | J101: =$G101+(fade_gA-$G101)*3/3 -> 0.06
A102: AI GPU 平台 ÷ 營收 | B102: % | C102: =C97/C100 -> 0.7 | D102: =D97/D100 -> 0.76572242 | E102: =E97/E100 -> 0.86868901 | F102: =F97/F100 -> 0.9012715 | G102: =G97/G100 -> 0.90675571
A103: 隱含美超微商用 GPU 出貨（AI 營收 ÷ 每顆平均系統價值） | B103: 百萬顆 | E103: =E97/((0.5*(D85*D87+D86*D88)+0.5*(E85*E87+E86*E88))/(0.5*(D85+D86)+0.5*(E85+E86))) -> 0.75874571 | F103: =F97/((0.5*(E85*E87+E86*E88)+0.5*(F85*F87+F86*F88))/(0.5*(E85+E86)+0.5*(F85+F86))) -> 0.94851919 | G103: =G97/((0.5*(F85*F87+F86*F88)+0.5*(G85*G87+G86*G88))/(0.5*(F85+F86)+0.5*(G85+G86))) -> 1.0195537 | K103: 對照用：份額 × 會計年度商用 GPU 顆數
A104: C. 損益
A105: AI 毛利率 FY2026 校準值 ＝（毛利 − 非 AI 毛利率 × 非 AI 營收）÷ AI 營收 | B105: % | D105: =(a26_gp-gm_nai*a26_nai)/a26_ai -> 0.095433875 | K105: Derived：FY2026 含 4Q 一次性利益（遞延合約、關稅、存貨跌價回轉），校準值偏高
A106: AI 毛利率 | B106: % | D106: =D105 -> 0.095433875 | E106: =$D105+dgm_27_hi -> 0.11043388 | F106: =$D105+dgm_28_hi -> 0.11043388 | G106: =$D105+dgm_28_hi -> 0.11043388 | K106: A 最高、C 最低（In 頁 C 節）
A107: 毛利 | B107: US$B | C107: =a25_gp -> 2.4299 | D107: =a26_gp -> 4.2273 | E107: =E106*E97+gm_nai*E99 -> 9.2674689 | F107: =F106*F97+gm_nai*F99 -> 13.163586 | G107: =G106*G97+gm_nai*G99 -> 14.746041
A108: 毛利率 | B108: % | C108: =C107/C100 -> 0.11059075 | D108: =D107/D100 -> 0.10821749 | E108: =E107/E100 -> 0.11562934 | F108: =F107/F100 -> 0.11434018 | G108: =G107/G100 -> 0.11412319
...

Sheet Sources
A1: 來源（公司原文為新聞稿與財報說明稿；10-K 內容只經二手摘要，原文待人工複核；券商與資料商皆為 Interested-party）
A2: 公司：FY2026 第四季與全年新聞稿（2026-08-11；營收、毛利率、營業費用、淨利、EPS、股數、1Q FY27 與 FY2027 指引、董事會調查） | B2: https://ir.supermicro.com/news/news-details/2026/Supermicro-Announces-Fourth-Quarter-and-Full-Fiscal-Year-2026-Financial-Results/default.aspx
A3: 公司：4Q FY26 財報說明稿（AI 占比、客戶與地區結構、最大客戶 28%、毛利率說明、新訂單） | B3: https://s204.q4cdn.com/707617056/files/doc_financials/2026/q4/V2/FQ426-SMCI-Prepared-Remarks.pdf
A4: 公司（摘要）：MarketBeat 2026-08-11 法說重點 | B4: https://www.marketbeat.com/instant-alerts/super-micro-computer-q4-earnings-call-highlights-2026-08-11/
A5: 公司：2Q FY26 新聞稿（8-K；1Q、2Q FY26 數字） | B5: https://www.sec.gov/Archives/edgar/data/1375365/000137536526000006/exhibit991_20251231.htm
A6: 公司：1Q FY27 初步營運更新（2026-10-20；營收 185～195 億、毛利率 12.0–12.5%、11-03 財報） | B6: https://ir.supermicro.com/news/news-details/2026/Supermicro-Provides-First-Quarter-of-Fiscal-Year-2027-Preliminary-Business-Update/default.aspx
A7: 公司：2026-06-11 普通股與強制可轉換特別股定價（股利率 7%、轉換率、2029-06-01 轉換） | B7: https://ir.supermicro.com/news/news-details/2026/Supermicro-Announces-Pricing-of-Equity-and-Equity-Linked-Financing-Transactions-To-Fund-AI-Orders/default.aspx
A8: 公司：2026-08 獨立調查完成公告（出口管制） | B8: https://www.supermicro.com/en/pressreleases/supermicro-announces-completion-independent-investigation-and-continued-enhancement
A9: 媒體：Stocktwits 2026-08-20（調查結論、2026-03 起訴、共同創辦人辭任董事） | B9: https://stocktwits.com/news-articles/markets/equity/smci-stock-gains-supermicro-clears-senior-management-export-control-case/cZYIq3bRJZ5
A10: 公司：FY2026 10-K（2026-08-31） | B10: https://www.sec.gov/Archives/edgar/data/0001375365/000137536526000022/smci-20260630.htm
A11: 媒體：StockTi（10-K 摘要：內控仍未有效、BDO 否定意見、單一供應商 63.1%） | B11: https://stockti.com/super-micro-revenue-surges-78-but-margin-pressures-and-control-gaps-linger
A12: 媒體：Futurum（2Q FY26 平台） | B12: https://futurumgroup.com/insights/supermicro-q2-fy2026-delivers-breakout-ai-gpu-platform-revenue
A13: 資料商：stockanalysis 統計頁（現價、股數、P/E、目標價） | B13: https://stockanalysis.com/stocks/smci/statistics/
... A31: SemiAnalysis | B31: 未使用
