Workbook

Sheet README
A1: 台光電（2383）收支與估值模型 v0.1（AI 半導體 Project：載板與 PCB 次產業；高速 CCL） 2026-10-25
A2: 版本：v0.1（初版）。每 GW 高速 CCL 金額（加速器／運算板、交換器板、UBB／中板）、台光電份額與產能在本模型 Units 頁建立，為本專案權威資料（規則第 13 條）；台燿、聯茂等 CCL 廠之後讀這條線。
A3: 模型命題：台光電的 AI 營收＝部署 GW（AI IT 資本支出 ÷ 每 GW IT 資本支出）× 每 GW 高速 CCL 金額（VR200 中板、M9 等級使每 GW 金額上升）× 台光電份額 × 價格指數，但受月產能 × 每張營收限制（全產全銷）。非 AI（通用伺服器、低軌衛星、手機、筆電、車用）另依成長率推。股價約 42 倍 FY2026、24 倍 FY2027 EPS（模型）。
A4: 核心問題：2027–28 年 AI 每 GW CCL 需求超過產能時，擴產（月產能 615 → 945 → 1,110 萬張）與 M9 組合升級能讓營收成長多少；價格與份額回落時 EPS 會少多少；現價隱含的路徑合不合理。
A6: 會計年度＝日曆年，FY(t)＝CY(t)，不平移。預測期 FY2027–FY2029（三年）。金額：十億新台幣；每 GW 金額以美元計、以匯率換算。口徑：歸屬母公司淨利。
A8: 驅動因子 → 推導量（全部唯讀上游，不修改）
A9: 需求面：markets/network 的 AI IT 資本支出 × 情境顆數係數 ÷ 每 GW IT 資本支出（Tokenomics，經橋接表）＝部署 GW；× 每 GW CCL 金額（2026 年三項合計 US$350M，Assumed；之後 × 世代指數，Analogy／Assumed）× 匯率 × 有效份額（FY2026 以公司 AI 相關占比校準）× 份額相對值 × 價格指數（Assumed）。
A10: 產能面：平均月產能（公司擴產計畫，Derived）× 12 × 每張營收（FY2026 校準）× 組合指數（M8→M9，Assumed）× 價格指數。AI 相關營收＝MIN（需求面、產能上限 − 非 AI）。
A11: 毛利率：AI 相關比其他營收高 d_ai（Assumed），其他毛利率為 FY2026 殘差（Derived）；價格指數變動全部落在 AI 毛利。營業費用：彈性 phi（Derived）。淨利 ÷ 稅前 0.77（2Q26 實績）。
A12: 校準：FY2026 ＝ 1H26 實績＋3Q26 營收實績（月營收）＋假設（4Q 季增 6%、毛利率 35%、營業費用率 6.5%）。3Q26 法說截至 2026-10-25 尚未舉行。不用券商數字（只在 Recon 對帳）。
A13: 估值：現價 ÷ FY2027、FY2028 EPS；十年 P/E 規則值（年底收盤 ÷ EPS，9 年）× FY2027 EPS；循環位置以本模型營收最高年判定（台光電不套設備股見頂年）。本版未做先驗，無 Andy 合理 P/E 對照。
A14: 標記：Verified、Interested-party、Analogy、Assumed、Derived。SemiAnalysis 未使用。公司原文＝法說（經轉述）與月營收；券商多為單一來源。
A16: 已知限制：(1) 每 GW CCL 金額的 2026 年水準與世代指數皆為 Assumed／Analogy（研調每架金額與張數口徑不一）；水準只影響校準份額，指數影響成長；(2) 2027–28 年產能受限，營收主要由擴產進度與每張組合指數（Assumed）決定；(3) AI 相關占比（基礎設施 × AI 伺服器＋交換器）為公司區間的中點，交換器含非 AI；(4) 1H26 與 FY2025 業外、稅前未找到，以淨利 ÷ 營業利益涵蓋；(5) 十年 P/E 只有一個採用來源，2016 年缺，且 2017–2022 年為 AI 前低倍數；(6) 3Q26 財報與法說（10 月底）後更新錨點；R4 產業部署路徑未建。

Sheet In
A1: In — 輸入（藍字；基準欄 E，低 D、高 F）。金額：十億新台幣（NT$B），每 GW CCL 金額為百萬美元；產能：百萬張／月；比例：%。每個輸入附兩個來源（找不到者寫「未找到」）；公司原文算一個
A2: 標記：Verified／Interested-party／Analogy／Assumed／Derived；Analogy、Assumed 給低／高區間。SemiAnalysis 未使用。公司原文＝台光電法說（經富果、鉅亨等轉述）與月營收公告；公司的產品組合、份額與毛利率指引為 Interested-party；券商估計皆為 Interested-party
A3: 鍵 | B3: 項目 | C3: 單位 | D3: 低 | E3: 基準 | F3: 高 | G3: 標記 | H3: 來源1 | I3: 來源2／說明
A4: A. AI 部署規模（讀 markets/network、markets/chip_bridge、tsmc 成品；情境 A 基準，B／C 依顆數係數縮放）
A5: itc_26 | B5: AI IT 資本支出 2026 | C5: US$B | E5: 781.87292 | G5: Derived | H5: markets/network/dist/20261023_AI網通市場模型_v0.2.2.xlsx｜Mkt!C27:F27 | I5: 加速器顆數 × 每顆 IT capex（含 ASIC）；本模型以此除以每 GW IT 資本支出得到部署 GW（與台達電、廣達模型相同）
A6: itc_27 | B6: AI IT 資本支出 2027 | C6: US$B | E6: 1565.35 | G6: Derived | H6: markets/network/dist/20261023_AI網通市場模型_v0.2.2.xlsx｜Mkt!C27:F27 | I6: 同上
A7: itc_28 | B7: AI IT 資本支出 2028 | C7: US$B | E7: 1984.2639 | G7: Derived | H7: markets/network/dist/20261023_AI網通市場模型_v0.2.2.xlsx｜Mkt!C27:F27 | I7: 同上
A8: itc_29 | B8: AI IT 資本支出 2029 | C8: US$B | E8: 2260.3903 | G8: Derived | H8: markets/network/dist/20261023_AI網通市場模型_v0.2.2.xlsx｜Mkt!C27:F27 | I8: 同上
A9: itpg_gb | B9: 每 GW IT 資本支出（GB300） | C9: US$B | E9: 32.237224 | G9: Derived | H9: markets/chip_bridge/dist/20261023_晶片內容橋接表_v0.2.1.xlsx｜In!E10（GB300）、H10（VR200） | I9: Tokenomics IF_CapexIT（經橋接表；唯讀）
A10: itpg_vr | B10: 每 GW IT 資本支出（VR200；2027 起） | C10: US$B | E10: 37.586352 | G10: Derived | H10: markets/chip_bridge/dist/20261023_晶片內容橋接表_v0.2.1.xlsx｜In!E10（GB300）、H10（VR200） | I10: 同上；Rubin Ultra 與 ASIC 機架未另訂（Assumed：同 VR200）
A11: vr26 | B11: 2026 年部署中 Rubin 世代占比（混合每 GW IT 資本支出與每 GW CCL 金額用） | C11: % | D11: 0.15 | E11: 0.22 | F11: 0.3 | G11: Interested-party | H11: TrendForce 2026 組合 Rubin 22%（經 markets/memory；與台達電模型相同） | I11: 公司：M9 2026 下半年開始出貨、2027 年明顯放量（富果 2026-03-12）
A12: racks_gb | B12: 每 GW 機架數（GB300） | C12: 架 | E12: 6764 | G12: Derived | H12: markets/chip_bridge/dist/20261023_晶片內容橋接表_v0.2.1.xlsx｜In!E6（GB300）、H6（VR200） | I12: Recon 用：每架 CCL 金額換算
A13: racks_vr | B13: 每 GW 機架數（VR200） | C13: 架 | E13: 4052 | G13: Derived | H13: markets/chip_bridge/dist/20261023_晶片內容橋接表_v0.2.1.xlsx｜In!E6（GB300）、H6（VR200） | I13: 同上
A14: um28_A | B14: 情境 A：2028 顆數 ÷ 基準 | C14: x | E14: 1 | G14: Assumed | H14: tsmc/dist/20261023_台積電模型_v0.2.1.xlsx｜In!E37 | I14: A＝基準；B＝AI 資本支出消化；C＝明顯下修（與台積電、NVIDIA、台達電、Ibiden 模型相同）
A15: um29_A | B15: 情境 A：2029 顆數 ÷ 基準 | C15: x | E15: 1 | G15: Assumed | H15: tsmc/dist/20261023_台積電模型_v0.2.1.xlsx｜In!E38 | I15: 同上
A16: um28_B | B16: 情境 B：2028 顆數 ÷ 基準 | C16: x | E16: 0.8 | G16: Assumed | H16: tsmc/dist/20261023_台積電模型_v0.2.1.xlsx｜In!E39 | I16: A＝基準；B＝AI 資本支出消化；C＝明顯下修（與台積電、NVIDIA、台達電、Ibiden 模型相同）
A17: um29_B | B17: 情境 B：2029 顆數 ÷ 基準 | C17: x | E17: 0.85 | G17: Assumed | H17: tsmc/dist/20261023_台積電模型_v0.2.1.xlsx｜In!E40 | I17: 同上
A18: um28_C | B18: 情境 C：2028 顆數 ÷ 基準 | C18: x | E18: 0.6 | G18: Assumed | H18: tsmc/dist/20261023_台積電模型_v0.2.1.xlsx｜In!E41 | I18: A＝基準；B＝AI 資本支出消化；C＝明顯下修（與台積電、NVIDIA、台達電、Ibiden 模型相同）
A19: um29_C | B19: 情境 C：2029 顆數 ÷ 基準 | C19: x | E19: 0.6 | G19: Assumed | H19: tsmc/dist/20261023_台積電模型_v0.2.1.xlsx｜In!E42 | I19: 同上
A20: fx | B20: 匯率（新台幣 ÷ 美元） | C20: NT$/US$ | D20: 30.5 | E20: 32 | F20: 33 | G20: Derived | H20: 與台達電、廣達模型相同（台達電 2Q26 法說換算約 32.7；2026 年初 31.4） | I20: 10-23 收盤：未找到
A21: B. 每 GW 高速 CCL 金額與台光電份額（本專案權威：每 GW CCL 金額、台光電份額，規則第 13 條）
A22: cmp_26 | B22: 每 GW CCL：加速器／運算板（運算匣、加速器模組板）2026 | C22: US$M/GW | D22: 130 | E22: 190 | F22: 250 | G22: Assumed | H22: 由上而下（Assumed）：三項合計 2026 年約 US$350M／GW＝CCL 高階（M7 以上）市場約 US$8B ÷ 部署約 23 GW；市場量級取自 Prismark 2024 年 M7 以上 US$57 億、年增 40%（https://finance.sina.cn/2026-09-28/detail-initkarh2920455.d.html，源達證券轉引，Interested-party） | I22: Morgan Stanley（經 Deep News 2026-09-23）：每架 CCL GB300 US$6,695、VR200 US$18,750（× 每 GW 架數＝45／76 百萬美元，口徑窄於本列，Interested-party）
A23: sw_26 | B23: 每 GW CCL：交換器板（NVLink 交換匣＋scale-out 800G／1.6T 交換器）2026 | C23: US$M/GW | D23: 60 | E23: 90 | F23: 120 | G23: Assumed | H23: 同上；公司：交換器占基礎設施營收 15–20%、AI 伺服器 55–60%（2Q26，凱基 2026-07-29 轉述）→ 交換器 ÷ AI 伺服器約 0.3 | I23: 800G 主用 M8、1.6T 用 M8+，1.6T 2026 Q1 開始出貨（富果 2026-03-12）
A24: ubb_26 | B24: 每 GW CCL：UBB／中板／正交背板 2026 | C24: US$M/GW | D24: 40 | E24: 70 | F24: 100 | G24: Assumed | H24: 同上；中板 44 層（2×22）M9、Rubin Ultra 正交背板 78 層 M9（台光電 EM-896K3）（源達證券轉引 NVIDIA、JPM） | I24: 2026 年以 GB300 為主（無中板）；中板金額多數從 VR200 開始
A25: cmpx_27 | B25: 每 GW CCL 金額指數：加速器／運算板 2027（2026＝1） | C25: x | D25: 1.2 | E25: 1.45 | F25: 1.8 | G25: Analogy | H25: 每架 CCL 張數：GB200／GB300 約 164 張、VR200 約 578 張（源達證券）→ 每 GW 張數 VR200 ÷ GB300＝2.1 倍；Morgan Stanley 每架金額 → 每 GW 1.68 倍（Interested-party） | I25: 2026 年已含 22% Rubin，所以 2027 ÷ 2026 小於世代倍數；ASIC（TPU V6 → V8 每台 144 → 200 張，+39%）
A26: cmpx_28 | B26: 每 GW CCL 金額指數：加速器／運算板 2028（2026＝1） | C26: x | D26: 1.3 | E26: 1.6 | F26: 2 | G26: Analogy | H26: 同上 | I26: —
A27: cmpx_29 | B27: 每 GW CCL 金額指數：加速器／運算板 2029（2026＝1） | C27: x | D27: 1.3 | E27: 1.7 | F27: 2.2 | G27: Analogy | H27: 同上 | I27: —
A28: swx_27 | B28: 每 GW CCL 金額指數：交換器板 2027（2026＝1） | C28: x | D28: 1.15 | E28: 1.4 | F28: 1.7 | G28: Assumed | H28: 交換器板 40 層以上、M9＋Q 布（Rubin；源達證券）；1.6T 2027 年隨 M8／M9 放量（本土投顧 2026-10-01） | I28: 網通模型：交換器市場 ÷ AI IT 資本支出 2026–27 持平（約 6.4%）；本列的上升來自材料等級
A29: swx_28 | B29: 每 GW CCL 金額指數：交換器板 2028（2026＝1） | C29: x | D29: 1.25 | E29: 1.6 | F29: 2 | G29: Assumed | H29: 同上 | I29: —
A30: swx_29 | B30: 每 GW CCL 金額指數：交換器板 2029（2026＝1） | C30: x | D30: 1.3 | E30: 1.75 | F30: 2.2 | G30: Assumed | H30: 同上 | I30: —
A31: ubbx_27 | B31: 每 GW CCL 金額指數：UBB／中板／背板 2027（2026＝1） | C31: x | D31: 1.3 | E31: 1.8 | F31: 2.5 | G31: Assumed | H31: VR200 中板、Rubin Ultra 78 層正交背板、Feynman 預計 144 層（源達證券） | I31: Morgan Stanley：M9 以上單價為基準 12.1 倍、M8 為 M7 兩倍以上（Interested-party）
A32: ubbx_28 | B32: 每 GW CCL 金額指數：UBB／中板／背板 2028（2026＝1） | C32: x | D32: 1.5 | E32: 2.3 | F32: 3 | G32: Assumed | H32: 同上 | I32: —
A33: ubbx_29 | B33: 每 GW CCL 金額指數：UBB／中板／背板 2029（2026＝1） | C33: x | D33: 1.5 | E33: 2.6 | F33: 3.5 | G33: Assumed | H33: 同上 | I33: —
... A39: pp_29 | B39: CCL 價格指數 2029（2026＝1；原料轉嫁與短缺） | C39: x | D39: 0.85 | E39: 0.93 | F39: 1 | G39: Assumed | H39: 同上 | I39: 新產能到位後價格回落（Assumed）
A40: C. 產能（全產全銷：營收上限＝平均月產能 × 12 × 每張營收）
A41: cap_26 | B41: 平均月產能 2026 | C41: 百萬張／月 | D41: 5.85 | E41: 6 | F41: 6.15 | G41: Derived | H41: 公司：2025 年 585 萬張／月；2026 Q1 中山 +30 萬、Q4 大園 +30 萬（富果 2026-03-12）；年底 615 萬（本土投顧 2026-10-01） | I41: 凱基 2026-07-29：585 萬張／月（公司簡介）
A42: cap_27 | B42: 平均月產能 2027 | C42: 百萬張／月 | D42: 7 | E42: 7.76 | F42: 8.2 | G42: Derived | H42: 公司：2027 年新增 330 萬張（Q1 120 萬、Q3 120 萬、Q4 90 萬；台灣、中國、馬來西亞），年底 945 萬（富果 2026-03-12） | I42: 依開出月份加權：6.15＋1.2 × 10.5／12＋1.2 × 4.5／12＋0.9 × 1.5／12；崑山、中山各 60 萬已從 2026 Q4 延到 2027 Q1（設備交期），低值反映再延遲
A43: cap_28 | B43: 平均月產能 2028 | C43: 百萬張／月 | D43: 9.5 | E43: 10.3 | F43: 10.8 | G43: Derived | H43: 公司：2028 年 1,110 萬張／月（富果 2026-08-27）；945 → 1,110 線性 | I43: 本土投顧 2026-10-01：2028 年底 1,110 萬
A44: cap_29 | B44: 平均月產能 2029 | C44: 百萬張／月 | D44: 11.1 | E44: 11.8 | F44: 13 | G44: Assumed | H44: 公司未揭露 2029 年計畫：未找到 | I44: 低值＝2028 年底不再擴產
A45: mix_27 | B45: 每張營收組合指數 2027（M8→M9、層數；不含價格；2026＝1） | C45: x | D45: 1.1 | E45: 1.25 | F45: 1.45 | G45: Assumed | H45: 公司：M7 以上占營收 1Q26 55–60% → 2Q26 60–65%；M9 2026 下半年個位數占比、2027 年明顯放量（凱基 2026-07-29、富果 2026-03-12） | I45: Morgan Stanley：M8 單價為 M7 兩倍以上、M9 以上為基準 12.1 倍（Interested-party）
A46: mix_28 | B46: 每張營收組合指數 2028（M8→M9、層數；不含價格；2026＝1） | C46: x | D46: 1.15 | E46: 1.4 | F46: 1.7 | G46: Assumed | H46: 同上 | I46: —
A47: mix_29 | B47: 每張營收組合指數 2029（M8→M9、層數；不含價格；2026＝1） | C47: x | D47: 1.2 | E47: 1.5 | F47: 1.85 | G47: Assumed | H47: 同上 | I47: —
A48: D. 營收結構錨點（公司揭露比例 × 營收）
A49: ai_25 | B49: 2025 年 AI 相關營收（AI 伺服器＋交換器）÷ 營收 | C49: % | D49: 0.45 | E49: 0.5 | F49: 0.55 | G49: Assumed | H49: 公司：2025 年基礎設施占 65–70%（凱基 2026-07-29）；4Q25 基礎設施中低軌衛星約 10%、其餘 AI 伺服器與交換器約 90%（含通用伺服器，富果 2026-03-12） | I49: 讀法：基礎設施 67.5% × AI 伺服器＋交換器 75%（2Q26 拆分比例）；只用於 FY2025 欄拆分
A50: ai_26 | B50: 2026 年 AI 相關營收（AI 伺服器＋交換器）÷ 營收 | C50: % | D50: 0.525 | E50: 0.585 | F50: 0.64 | G50: Interested-party | H50: 公司：2Q26 基礎設施 75–80%，其中 AI 伺服器 55–60%、通用伺服器 15–20%、交換器 15–20%、低軌衛星 5–10%（凱基 2026-07-29） | I50: 公司：下半年基礎設施 80% 以上（富果 2026-08-27）；基準＝78% ×（57.5%＋17.5%）；交換器含非 AI 企業交換器（未拆）
A51: g_nai27 | B51: 非 AI 營收年增 2027（通用伺服器、低軌衛星、手機、筆電、車用） | C51: % | D51: 0 | E51: 0.08 | F51: 0.15 | G51: Assumed | H51: 2Q26 年增：手持 +42%、車用 +58%（凱基 2026-07-29，含漲價）；3Q26 指引：手持持平、車用個位數季減 | I51: 通用伺服器、記憶體模組（DDR5 RDIMM）、低軌衛星持續成長（公司）；手機、筆電成熟
A52: g_nai28 | B52: 非 AI 營收年增 2028（通用伺服器、低軌衛星、手機、筆電、車用） | C52: % | D52: 0 | E52: 0.06 | F52: 0.12 | G52: Assumed | H52: 同上 | I52: —
A53: g_nai29 | B53: 非 AI 營收年增 2029（通用伺服器、低軌衛星、手機、筆電、車用） | C53: % | D53: 0 | E53: 0.05 | F53: 0.1 | G53: Assumed | H53: 同上 | I53: —
A54: E. 毛利率
A55: d_ai | B55: AI 相關（高速材料）毛利率高於其他營收的幅度 | C55: pt | D55: 0.04 | E55: 0.08 | F55: 0.12 | G55: Assumed | H55: 部門別毛利率未揭露：未找到；毛利率隨 M7 以上占比上升：2025 年 29.8% → 2Q26 33.9%（公司） | I55: 2Q26 毛利率改善歸因高階產品組合與滿載（富果 2026-08-27）
A56: F. FY2026 錨點（1H26 實績＋3Q26 營收實績＋假設；3Q26 法說截至 2026-10-25 尚未舉行）
A57: q3_rev | B57: 3Q26 營收（月營收合計＝前 9 月 − 上半年） | C57: NT$B | E57: =141.227-80.342 -> 60.885 | G57: Verified | H57: https://finance.technews.tw/2026/10/05/emc-2383-202609-financial-report/：9 月 215.32 億、前 9 月 1,412.27 億（年增 103.7%） | I57: 上半年 803.42 億（uanalyze 2026-07-29）；8 月 201.46 億（財報狗）
A58: q4g | B58: 4Q26 營收季增 | C58: % | D58: 0 | E58: 0.06 | F58: 0.12 | G58: Assumed | H58: 公司未給 4Q 指引（3Q 法說預計 10 月底，日期未找到）；9 月月營收 215.3 億 × 3＝646 億（季增 6%） | I58: 4Q 大園 +30 萬張；崑山、中山延到 2027 Q1（公司）
A59: q3_gm | B59: 3Q26 毛利率 | C59: % | D59: 0.335 | E59: 0.35 | F59: 0.365 | G59: Interested-party | H59: 公司 3Q 指引 35% ± 1.5%（富果 2026-08-27） | I59: 凱基 2026-07-29：3Q26 34.7%；本土投顧 35.08%
A60: q4_gm | B60: 4Q26 毛利率 | C60: % | D60: 0.335 | E60: 0.35 | F60: 0.37 | G60: Assumed | H60: 同 3Q 指引；下半年不排除再漲價（公司） | I60: —
A61: q_opx | B61: 3Q、4Q26 營業費用 ÷ 營收 | C61: % | D61: 0.06 | E61: 0.065 | F61: 0.07 | G61: Assumed | H61: 2Q26 6.9%（凱基：毛利 160.03 − 營業利益 127.34 億）、FY2025 9.6%（公司） | I61: 營收成長快於費用
A62: q_nop | B62: 3Q、4Q26 業外收益（每季） | C62: NT$B | D62: -0.5 | E62: 0.1 | F62: 0.5 | G62: Assumed | H62: 2Q26 0.05（含中國政府補助 1.35 億；凱基） | I62: 1H26、FY2025 業外：未找到
A63: q_nir | B63: 3Q、4Q26 歸屬母公司淨利 ÷ 稅前 | C63: % | D63: 0.75 | E63: 0.77 | F63: 0.79 | G63: Derived | H63: 2Q26 98.73 ÷（127.34＋0.52）＝0.772（凱基） | I63: FY2025 淨利 ÷ 營業利益 146.49 ÷ 191.08＝0.767（stockanalysis）
A64: q_sh | B64: 股數（十億股；EPS 換算） | C64: 十億股 | E64: =15.213/42.46 -> 0.35829016 | G64: Derived | H64: 1H26 淨利 152.13 億 ÷ EPS 42.46（uanalyze 2026-07-29） | I64: 凱基：358.3 百萬股；現金股利 89.6 億 ÷ 25 元＝358 百萬股
A65: G. 營業費用、業外、稅與股數（FY2027 起）
A66: phi | B66: 營業費用成長對營收成長的彈性 | C66: x | D66: 0.45 | E66: 0.6 | F66: 1 | G66: Derived | H66: FY2026 錨點實測約 0.47（Q 頁 B26） | I66: FY2025：營業費用 +55% ÷ 營收 +46%＝1.2（擴產期，stockanalysis）
A67: opx_adj | B67: 營業費用額外占營收比（Sens 用；基準 0） | C67: pt | D67: -0.01 | E67: 0 | F67: 0.01 | G67: Assumed | H67: 無 | I67: Sens 用 ±1 個百分點（台光電營業費用率約 7%）
A68: nop_f | B68: 業外收益（每年） | C68: NT$B | D68: -1 | E68: 0.5 | F68: 2 | G68: Assumed | H68: 2Q26 0.05（凱基） | I68: —
A69: nir_f | B69: 歸屬母公司淨利 ÷ 稅前 | C69: % | D69: 0.75 | E69: 0.77 | F69: 0.79 | G69: Derived | H69: 同 q_nir | I69: —
A70: sh_g | B70: 股數年變動 | C70: % | D70: 0 | E70: 0 | F70: 0.005 | G70: Assumed | H70: 1H26 358.3 百萬股；FY2025 推導 351.5（淨利 ÷ EPS，加權） | I70: —
A71: mf | B71: AI 部署係數（Sens 用；FY2027 起） | C71: x | D71: 0.8 | E71: 1 | F71: 1.2 | G71: Assumed | H71: 網通模型 2027 年 AI IT 資本支出約 2 倍 | I71: ±20%
A72: H. 共識、研調與市場資料（只作 Recon 對帳，不作校準）
A73: b_rev26k | B73: 凱基 FY2026 營收（2026-07-29） | C73: NT$B | E73: 191.123 | G73: Interested-party | H73: https://www.kgi.com.hk/zh-hk/-/media/files/kgishk/research-reports/tw-reports/emc-2383-tt20260729en.pdf | I73: —
A74: b_eps26k | B74: 凱基 FY2026 EPS（2026-07-29） | C74: NT$ | E74: 108.84 | G74: Interested-party | H74: https://www.kgi.com.hk/zh-hk/-/media/files/kgishk/research-reports/tw-reports/emc-2383-tt20260729en.pdf | I74: —
A75: b_eps26c | B75: 市場共識 FY2026 EPS（凱基報告所列，2026-07-29） | C75: NT$ | E75: 98.72 | G75: Interested-party | H75: https://www.kgi.com.hk/zh-hk/-/media/files/kgishk/research-reports/tw-reports/emc-2383-tt20260729en.pdf | I75: 共識來源（Bloomberg 或其他）未載明
A76: b_eps26l | B76: 本土投顧 FY2026 EPS（2026-10-01） | C76: NT$ | E76: 120.77 | G76: Interested-party | H76: https://www.mirrormedia.mg/external/setn_1915172（三立轉載，未具名本土投顧） | I76: 3Q26 EPS 估 36.85
A77: b_rev27k | B77: 凱基 FY2027 營收 | C77: NT$B | E77: 306.405 | G77: Interested-party | H77: https://www.kgi.com.hk/zh-hk/-/media/files/kgishk/research-reports/tw-reports/emc-2383-tt20260729en.pdf | I77: —
A78: b_rev27l | B78: 本土投顧 FY2027 營收 | C78: NT$B | E78: 353.014 | G78: Interested-party | H78: https://www.mirrormedia.mg/external/setn_1915172 | I78: —
A79: b_eps27k | B79: 凱基 FY2027 EPS（2026-07-29） | C79: NT$ | E79: 190.64 | G79: Interested-party | H79: https://www.kgi.com.hk/zh-hk/-/media/files/kgishk/research-reports/tw-reports/emc-2383-tt20260729en.pdf | I79: 目標價 7,625＝40 倍 2027 EPS
A80: b_eps27c | B80: 市場共識 FY2027 EPS（凱基報告所列，2026-07-29） | C80: NT$ | E80: 193.33 | G80: Interested-party | H80: https://www.kgi.com.hk/zh-hk/-/media/files/kgishk/research-reports/tw-reports/emc-2383-tt20260729en.pdf | I80: —
A81: b_eps27l | B81: 本土投顧 FY2027 EPS（2026-10-01） | C81: NT$ | E81: 204.85 | G81: Interested-party | H81: https://www.mirrormedia.mg/external/setn_1915172 | I81: 目標價 6,145＝30 倍 2027 EPS
A82: ms_rev28 | B82: Morgan Stanley 隱含 FY2028 營收（2025–28 年複合成長 76%） | C82: NT$B | E82: =94.261*1.76^3 -> 513.88986 | G82: Derived | H82: https://www.itiger.com/news/1142209073（Deep News 轉述，Interested-party） | I82: 以 FY2025 實績 942.61 億推算
A83: ms_eps28 | B83: Morgan Stanley 隱含 FY2028 EPS（目標價 8,400 ÷ 20 倍 2028 EPS） | C83: NT$ | E83: =8400/20 -> 420 | G83: Derived | H83: https://www.itiger.com/news/1142209073 | I83: 淨利 2025–28 年複合成長 117%（同上）
A84: hs_sh25 | B84: Prismark：台光電高速材料市占 2025 | C84: % | E84: 0.386 | G84: Interested-party | H84: https://uanalyze.com.tw/articles/9219952430（公司轉述 Prismark） | I84: 無鹵高速 2024 年 40.1%（富果 2026-03-12）
A85: hs_sh25c | B85: 公司自估：高速材料市占 2025 | C85: % | E85: 0.5 | G85: Interested-party | H85: https://blog.fugle.tw/post/earnings-call-2383-2026-03-12（「超過 50%」） | I85: 利基市場（HDI、高速、AI 伺服器、交換器、低軌衛星）多數超過 50%（富果 2026-08-27）
A86: ms_rk_gb | B86: Morgan Stanley：每架 CCL 金額 GB300 | C86: US$ | E86: 6695 | G86: Interested-party | H86: https://www.itiger.com/news/1142209073 | I86: VR200 18,750、VR300 35,601
A87: ms_rk_vr | B87: Morgan Stanley：每架 CCL 金額 VR200 | C87: US$ | E87: 18750 | G87: Interested-party | H87: https://www.itiger.com/news/1142209073 | I87: —
A88: sht_gb | B88: 每架 CCL 張數 GB200／GB300 | C88: 張 | E88: 164 | G88: Interested-party | H88: https://finance.sina.cn/2026-09-28/detail-initkarh2920455.d.html（源達證券測算） | I88: Hopper 約 212 張
A89: sht_vr | B89: 每架 CCL 張數 VR200 | C89: 張 | E89: 578 | G89: Interested-party | H89: https://finance.sina.cn/2026-09-28/detail-initkarh2920455.d.html | I89: —
A90: I. 價格與估值
A91: px | B91: 股價（2026-10-22 收盤） | C91: NT$ | E91: 5070 | G91: Interested-party | H91: Yahoo 股市 2383（10-22 14:30 收盤 5,070，+1.6%） | I91: 財報狗：10-22 收盤 5,070；10-23 收盤：未找到
A92: pe_ttm | B92: 近 12 月 P/E（10-22） | C92: x | E92: 79.28 | G92: Interested-party | H92: Yahoo 股市、財報狗（近四季 EPS 63.95） | I92: HiStock 10 月 79.28

Sheet Q
A1: Q — 實績與 FY2026 錨點（十億新台幣；EPS 為新台幣；股數為十億股）。藍字＝輸入；黑字＝公式。實績取自台光電法說（經轉述）、券商整理的季報數字與月營收公告
A2: FY2026 錨點＝1H26 實績＋3Q26 營收實績（月營收）＋3Q、4Q 假設（毛利率、營業費用率、業外、淨利 ÷ 稅前；4Q 營收＝3Q × (1＋季增)）。1H26 營業利益＝2Q26 127.34 億＋1Q26（2Q26 ÷ 1.7863；玩股網單季營業利益季增 78.63%）。1H26 與 FY2025 的業外、稅前利益：未找到。3Q26 財報與法說（預計 10 月底）公布後更新
A3: 項目 | B3: FY2025A | C3: 1H26（實績） | D3: 3Q26（營收實績） | E3: 4Q26（模型） | F3: FY2026 錨點 | G3: 標記 | H3: 來源1 | I3: 來源2／說明
A4: 營收 | B4: 94.261 | C4: 80.342 | D4: =q3_rev -> 60.885 | E4: =D4*(1+q4g) -> 64.5381 | F4: =SUM(C4:E4) -> 205.7651 | G4: Verified／Assumed（4Q 季增） | H4: FY2025：stockanalysis 年報數字、uanalyze 2026-03（EPS 41.67、營收 942.6 億、毛利率 29.8%）；1H26：https://uanalyze.com.tw/articles/9219952430、https://www.kgi.com.hk/zh-hk/-/media/files/kgishk/research-reports/tw-reports/emc-2383-tt20260729en.pdf | I4: FY2025 富果 943 億（同值）；1H26 富果：2Q26 472.7 億；3Q26 營收：月營收公告（TechNews 2026-10-05）
A5: 毛利 | B5: 28.12 | C5: =C4*0.3202 -> 25.725508 | D5: =D4*q3_gm -> 21.30975 | E5: =E4*q4_gm -> 22.588335 | F5: =SUM(C5:E5) -> 69.623593 | G5: Verified／Interested-party（3Q 指引） | H5: FY2025：stockanalysis 年報數字、uanalyze 2026-03（EPS 41.67、營收 942.6 億、毛利率 29.8%）；1H26：https://uanalyze.com.tw/articles/9219952430、https://www.kgi.com.hk/zh-hk/-/media/files/kgishk/research-reports/tw-reports/emc-2383-tt20260729en.pdf | I5: 1H26 毛利率 32.02%（uanalyze）；2Q26 毛利 160.03 億（凱基）
A6: 毛利率 | B6: =B5/B4 -> 0.29832062 | C6: =C5/C4 -> 0.3202 | D6: =D5/D4 -> 0.35 | E6: =E5/E4 -> 0.35 | F6: =F5/F4 -> 0.33836444 | G6: Derived | H6: — | I6: FY2025 29.8%（公司）；2Q26 33.9%
A7: 營業費用 | B7: =B5-B8 -> 9.012 | C7: =C5-C8 -> 5.8628066 | D7: =D4*q_opx -> 3.957525 | E7: =E4*q_opx -> 4.1949765 | F7: =SUM(C7:E7) -> 14.015308 | G7: Derived（毛利 − 營業利益）／Assumed | H7: FY2025：stockanalysis 年報數字、uanalyze 2026-03（EPS 41.67、營收 942.6 億、毛利率 29.8%）；1H26：https://uanalyze.com.tw/articles/9219952430、https://www.kgi.com.hk/zh-hk/-/media/files/kgishk/research-reports/tw-reports/emc-2383-tt20260729en.pdf | I7: 3Q26 營收：月營收公告（TechNews 2026-10-05）
A8: 營業利益 | B8: 19.108 | C8: =12.734+12.734/1.7863 -> 19.862702 | D8: =D5-D7 -> 17.352225 | E8: =E5-E7 -> 18.393359 | F8: =SUM(C8:E8) -> 55.608285 | G8: Verified／Derived | H8: FY2025：stockanalysis 年報數字、uanalyze 2026-03（EPS 41.67、營收 942.6 億、毛利率 29.8%）；1H26：https://uanalyze.com.tw/articles/9219952430、https://www.kgi.com.hk/zh-hk/-/media/files/kgishk/research-reports/tw-reports/emc-2383-tt20260729en.pdf | I8: FY2025 營益率 20.3%（富果）；2Q26 127.34 億（凱基）；1Q26 由玩股網季增率反推
A9: 營業利益率 | B9: =B8/B4 -> 0.20271374 | C9: =C8/C4 -> 0.24722688 | D9: =D8/D4 -> 0.285 | E9: =E8/E4 -> 0.285 | F9: =F8/F4 -> 0.2702513 | G9: Derived | H9: — | I9: 2Q26 26.9%（凱基）
A10: 業外收益 | D10: =q_nop -> 0.1 | E10: =q_nop -> 0.1 | G10: Assumed | H10: — | I10: FY2025、1H26：未找到
A11: 稅前利益 | D11: =D8+D10 -> 17.452225 | E11: =E8+E10 -> 18.493358 | G11: Derived | H11: — | I11: FY2025、1H26：未找到
A12: 歸屬母公司淨利 | B12: 14.649 | C12: 15.213 | D12: =D11*q_nir -> 13.438213 | E12: =E11*q_nir -> 14.239886 | F12: =SUM(C12:E12) -> 42.891099 | G12: Verified／Derived（3Q、4Q） | H12: FY2025：stockanalysis 年報數字、uanalyze 2026-03（EPS 41.67、營收 942.6 億、毛利率 29.8%）；1H26：https://uanalyze.com.tw/articles/9219952430、https://www.kgi.com.hk/zh-hk/-/media/files/kgishk/research-reports/tw-reports/emc-2383-tt20260729en.pdf | I12: FY2025 uanalyze 146.5 億；1H26 2Q26 98.73 億（凱基）
A13: 淨利 ÷ 營業利益 | B13: =B12/B8 -> 0.76664224 | C13: =C12/C8 -> 0.76590789 | D13: =D12/D8 -> 0.77443747 | E13: =E12/E8 -> 0.77418629 | F13: =F12/F8 -> 0.77130771 | G13: Derived | H13: — | I13: —
A14: 股數（十億股） | B14: =14.649/41.67 -> 0.35154788 | C14: =q_sh -> 0.35829016 | D14: =q_sh -> 0.35829016 | E14: =q_sh -> 0.35829016 | F14: =q_sh -> 0.35829016 | G14: Derived | H14: FY2025：stockanalysis 年報數字、uanalyze 2026-03（EPS 41.67、營收 942.6 億、毛利率 29.8%）；1H26：https://uanalyze.com.tw/articles/9219952430、https://www.kgi.com.hk/zh-hk/-/media/files/kgishk/research-reports/tw-reports/emc-2383-tt20260729en.pdf | I14: 淨利 ÷ EPS（FY2025 為加權平均）
A15: EPS | B15: =B12/B14 -> 41.67 | C15: =C12/C14 -> 42.46 | D15: =D12/D14 -> 37.50651 | E15: =E12/E14 -> 39.744006 | F15: =F12/F14 -> 119.71052 | G15: Derived | H15: 淨利 ÷ 股數 | I15: —
A16: 公司揭露 EPS | B16: 41.67 | C16: 42.46 | G16: Verified | H16: FY2025：stockanalysis 年報數字、uanalyze 2026-03（EPS 41.67、營收 942.6 億、毛利率 29.8%）；1H26：https://uanalyze.com.tw/articles/9219952430、https://www.kgi.com.hk/zh-hk/-/media/files/kgishk/research-reports/tw-reports/emc-2383-tt20260729en.pdf | I16: 1Q26 14.90、2Q26 27.55（udn、uanalyze）
A17: AI 相關營收（＝營收 × AI 相關占比） | B17: =B4*ai_25 -> 47.1305 | F17: =F4*ai_26 -> 120.37258 | G17: Derived／Interested-party | H17: 公司產品組合（In 頁 D 節） | I17: 各季 AI 營收金額未揭露：未找到
A18: 非 AI 營收（＝營收 − AI 相關） | B18: =B4-B17 -> 47.1305 | F18: =F4-F17 -> 85.392516 | G18: Derived | H18: — | I18: 通用伺服器、低軌衛星、手持（手機、筆電、記憶體模組）、車用與工業
A23: FY2026 錨點的檢查（參考；校準未使用券商數字）
A24: FY2026 營收年增 | B24: =F4/B4-1 -> 1.1829293
A25: FY2026 營業費用年增 | B25: =F7/B7-1 -> 0.55518288
A26: 營業費用彈性（營業費用年增 ÷ 營收年增；In 頁 phi 的依據） | B26: =B25/B24 -> 0.46932887
A27: FY2026 營收 ÷ 凱基（07-29）− 1 | B27: =F4/b_rev26k-1 -> 0.076610874
A28: FY2026 EPS ÷ 本土投顧（10-01）− 1 | B28: =F15/b_eps26l-1 -> -0.0087727437
A29: 3Q26 營收季增（實績；公司指引 15–20%） | B29: =D4/(C4-33.07)-1 -> 0.28797174 | C29: 2Q26 營收 472.75 億＝上半年 803.42 − 1Q26 330.7

Sheet Units
A1: Units — 每 GW 高速 CCL 金額（加速器／運算板、交換器板、UBB／中板）、台光電份額與產能（本專案權威，規則第 13 條）。部署 GW＝AI IT 資本支出（markets/network）÷ 每 GW IT 資本支出（Tokenomics，經橋接表）
A3: 項目 | B3: 單位 | C3: CY2026 | D3: CY2027 | E3: CY2028 | F3: CY2029 | G3: 說明
A4: 部署 GW（情境 A） | B4: GW | C4: =PL!D65 -> 23.399538 | D4: =PL!E65 -> 41.646766 | E4: =PL!F65 -> 52.792138 | F4: =PL!G65 -> 60.138592 | G4: AI IT 資本支出 ÷ 每 GW IT 資本支出
A5: 每 GW CCL：加速器／運算板 | B5: US$M/GW | C5: =PL!D66 -> 190 | D5: =PL!E66 -> 275.5 | E5: =PL!F66 -> 304 | F5: =PL!G66 -> 323 | G5: 2026 Assumed、之後 × 指數（Analogy）
A6: 每 GW CCL：交換器板 | B6: US$M/GW | C6: =PL!D67 -> 90 | D6: =PL!E67 -> 126 | E6: =PL!F67 -> 144 | F6: =PL!G67 -> 157.5 | G6: Assumed
A7: 每 GW CCL：UBB／中板／背板 | B7: US$M/GW | C7: =PL!D68 -> 70 | D7: =PL!E68 -> 126 | E7: =PL!F68 -> 161 | F7: =PL!G68 -> 182 | G7: Assumed；Rubin 中板、Rubin Ultra 正交背板
A8: 每 GW 高速 CCL 金額（合計，不含價格指數） | B8: US$M/GW | C8: =PL!D69 -> 350 | D8: =PL!E69 -> 527.5 | E8: =PL!F69 -> 609 | F8: =PL!G69 -> 662.5
A9: 每架等值 CCL 金額（以 VR200 每 GW 架數換算） | B9: US$K/架 | C9: =PL!D69*1000/racks_vr -> 86.377098 | D9: =PL!E69*1000/racks_vr -> 130.18263 | E9: =PL!F69*1000/racks_vr -> 150.29615 | F9: =PL!G69*1000/racks_vr -> 163.49951 | G9: 對照 Morgan Stanley VR200 每架 US$18.75K（口徑較窄）
A10: AI 高速 CCL 市場（含價格指數） | B10: US$B | C10: =PL!D70*PL!D72 -> 8.1898383 | D10: =PL!E70*PL!E72 -> 21.968669 | E10: =PL!F70*PL!F72 -> 31.1859 | F10: =PL!G70*PL!G72 -> 37.05289 | G10: 含 ASIC 部署（假設每 GW 金額相同）
A11: 台光電有效份額 | B11: % | C11: =PL!D75 -> 0.45930617 | D11: =PL!E75 -> 0.43634086 | E11: =PL!F75 -> 0.41337555 | F11: =PL!G75 -> 0.39041024 | G11: FY2026 以公司 AI 相關占比校準
A12: 台光電 AI 相關營收（需求面） | B12: US$B | C12: =PL!D76/fx -> 3.7616432 | D12: =PL!E76/fx -> 9.5858279 | E12: =PL!F76/fx -> 12.891488 | F12: =PL!G76/fx -> 14.465828
A13: 台光電 AI 相關營收（實際＝MIN 需求面、產能） | B13: US$B | C13: =PL!D83/fx -> 3.7616432 | D13: =PL!E83/fx -> 7.5134269 | E13: =PL!F83/fx -> 11.935285 | F13: =PL!G83/fx -> 14.433479
A14: 每 GW 台光電 AI 相關營收 | B14: US$M/GW | C14: =PL!D89 -> 160.75716 | D14: =PL!E89 -> 180.40841 | E14: =PL!F89 -> 226.08072 | F14: =PL!G89 -> 240.00361
A15: 平均月產能 | B15: 百萬張／月 | C15: =PL!D78 -> 6 | D15: =PL!E78 -> 7.76 | E15: =PL!F78 -> 10.3 | F15: =PL!G78 -> 11.8 | G15: 公司擴產計畫
A16: 每張營收（含組合與價格指數） | B16: NT$／張 | C16: =PL!$D$79*PL!D80*PL!D72 -> 2857.8486 | D16: =PL!$D$79*PL!E80*PL!E72 -> 3572.3108 | E16: =PL!$D$79*PL!F80*PL!F72 -> 3880.9584 | F16: =PL!$D$79*PL!G80*PL!G72 -> 3986.6988 | G16: FY2026 校準
A17: 需求面 ÷ 產能上限 | B17: % | C17: =PL!D88 -> 1 | D17: =PL!E88 -> 1.199357 | E17: =PL!F88 -> 1.0637886 | F17: =PL!G88 -> 1.0018337 | G17: 大於 100%＝產能受限
A18: 其他廠商 AI 高速 CCL（台燿、斗山、生益、松下等）＝ 市場 − 台光電 | B18: US$B | C18: =PL!D70*PL!D72-PL!D83/fx -> 4.4281951 | D18: =PL!E70*PL!E72-PL!E83/fx -> 14.455242 | E18: =PL!F70*PL!F72-PL!F83/fx -> 19.250615 | F18: =PL!G70*PL!G72-PL!G83/fx -> 22.619411 | G18: 產能受限時，未滿足需求計入其他廠商
A20: 讀法：每 GW CCL 金額的絕對水準只影響 FY2026 校準出的份額（金額高 → 份額低），不影響營收；影響營收的是金額指數（世代升級）與份額相對值。2027–28 年需求面高於產能時，營收由月產能 × 每張營收決定，擴產進度與 M9 組合比需求更關鍵。

Sheet PL
A1: PL — 台光電損益（十億新台幣；EPS 新台幣；歸屬母公司）。FY2025A 實績、FY2026 錨點（1H26 實績＋3Q26 營收實績＋假設），FY2027 起為模型。FY(t)＝CY(t)。三情境各一個完整推導區塊（本頁下方），頂端為摘要。FY2026–FY2027 三情境相同（顆數係數從 CY2028 開始）
A3: 情境／項目 | B3: 單位 | C3: FY2025A | D3: FY2026（錨點） | E3: FY2027 | F3: FY2028 | G3: FY2029 | H3: 說明
A4: 情境 A
A5: 營收 | B5: NT$B | C5: =C85 -> 94.261 | D5: =D85 -> 205.7651 | E5: =E85 -> 332.65358 | F5: =F85 -> 479.68646 | G5: =G85 -> 564.51655
A6: 營收年增 | B6: % | D6: =D86 -> 1.1829293 | E6: =E86 -> 0.61666667 | F6: =F86 -> 0.442 | G6: =G86 -> 0.17684487
A7: AI 相關營收（AI 伺服器＋交換器） | B7: NT$B | C7: =C83 -> 47.1305 | D7: =D83 -> 120.37258 | E7: =E83 -> 240.42966 | F7: =F83 -> 381.92911 | G7: =G83 -> 461.87133
A8: 非 AI 營收 | B8: NT$B | C8: =C82 -> 47.1305 | D8: =D82 -> 85.392516 | E8: =E82 -> 92.223918 | F8: =F82 -> 97.757353 | G8: =G82 -> 102.64522
A9: 需求面 ÷ 產能上限 | B9: % | D9: =D88 -> 1 | E9: =E88 -> 1.199357 | F9: =F88 -> 1.0637886 | G9: =G88 -> 1.0018337
A10: 毛利率 | B10: % | C10: =C94 -> 0.29832062 | D10: =D94 -> 0.33836444 | E10: =E94 -> 0.34938547 | F10: =F94 -> 0.33978573 | G10: =G94 -> 0.31831734
A11: 營業利益率 | B11: % | C11: =C98 -> 0.20271374 | D11: =D98 -> 0.2702513 | E11: =E98 -> 0.29166485 | F11: =F98 -> 0.28914208 | G11: =G98 -> 0.27071779
A12: 歸屬母公司淨利 | B12: NT$B | C12: =C100 -> 14.649 | D12: =D100 -> 42.891099 | E12: =E100 -> 75.092984 | F12: =F100 -> 107.18211 | G12: =G100 -> 118.06
A13: EPS | B13: NT$ | C13: =C103 -> 41.67 | D13: =D103 -> 119.71052 | E13: =E103 -> 209.58707 | F13: =F103 -> 299.1489 | G13: =G103 -> 329.50947
A14: EPS 年增 | B14: % | D14: =D104 -> 1.8728226 | E14: =E104 -> 0.75078245 | F14: =F104 -> 0.42732519 | G14: =G104 -> 0.10148981
A16: 情境 B
A17: 營收 | B17: NT$B | C17: =C132 -> 94.261 | D17: =D132 -> 205.7651 | E17: =E132 -> 332.65358 | F17: =F132 -> 427.77946 | G17: =G132 -> 496.11573
A18: 營收年增 | B18: % | D18: =D133 -> 1.1829293 | E18: =E133 -> 0.61666667 | F18: =F133 -> 0.28596079 | G18: =G133 -> 0.15974651
A19: AI 相關營收（AI 伺服器＋交換器） | B19: NT$B | C19: =C130 -> 47.1305 | D19: =D130 -> 120.37258 | E19: =E130 -> 240.42966 | F19: =F130 -> 330.0221 | G19: =G130 -> 393.47051
A20: 非 AI 營收 | B20: NT$B | C20: =C129 -> 47.1305 | D20: =D129 -> 85.392516 | E20: =E129 -> 92.223918 | F20: =F129 -> 97.757353 | G20: =G129 -> 102.64522
A21: 需求面 ÷ 產能上限 | B21: % | D21: =D135 -> 1 | E21: =E135 -> 1.199357 | F21: =F135 -> 0.89178973 | G21: =G135 -> 0.87883293
A22: 毛利率 | B22: % | C22: =C141 -> 0.29832062 | D22: =D141 -> 0.33836444 | E22: =E141 -> 0.34938547 | F22: =F141 -> 0.33828807 | G22: =G141 -> 0.31749762
A23: 營業利益率 | B23: % | C23: =C145 -> 0.20271374 | D23: =D145 -> 0.2702513 | E23: =E145 -> 0.29166485 | F23: =F145 -> 0.28570161 | G23: =G145 -> 0.26780852
A24: 歸屬母公司淨利 | B24: NT$B | C24: =C147 -> 14.649 | D24: =D147 -> 42.891099 | E24: =E147 -> 75.092984 | F24: =F147 -> 94.492306 | G24: =G147 -> 102.69029
A25: EPS | B25: NT$ | C25: =C150 -> 41.67 | D25: =D150 -> 119.71052 | E25: =E150 -> 209.58707 | F25: =F150 -> 263.73124 | G25: =G150 -> 286.6121
A26: EPS 年增 | B26: % | D26: =D151 -> 1.8728226 | E26: =E151 -> 0.75078245 | F26: =F151 -> 0.25833734 | G26: =G151 -> 0.086758256
A28: 情境 C
A29: 營收 | B29: NT$B | C29: =C179 -> 94.261 | D29: =D179 -> 205.7651 | E29: =E179 -> 332.65358 | F29: =F179 -> 345.27393 | G29: =G179 -> 380.38911
A30: 營收年增 | B30: % | D30: =D180 -> 1.1829293 | E30: =E180 -> 0.61666667 | F30: =F180 -> 0.037938425 | G30: =G180 -> 0.10170238
A31: AI 相關營收（AI 伺服器＋交換器） | B31: NT$B | C31: =C177 -> 47.1305 | D31: =D177 -> 120.37258 | E31: =E177 -> 240.42966 | F31: =F177 -> 247.51658 | G31: =G177 -> 277.74389
A32: 非 AI 營收 | B32: NT$B | C32: =C176 -> 47.1305 | D32: =D176 -> 85.392516 | E32: =E176 -> 92.223918 | F32: =F176 -> 97.757353 | G32: =G176 -> 102.64522
A33: 需求面 ÷ 產能上限 | B33: % | D33: =D182 -> 1 | E33: =E182 -> 1.199357 | F33: =F182 -> 0.71979086 | G33: =G182 -> 0.67383164
A34: 毛利率 | B34: % | C34: =C188 -> 0.29832062 | D34: =D188 -> 0.33836444 | E34: =E188 -> 0.34938547 | F34: =F188 -> 0.33498086 | G34: =G188 -> 0.31543942
A35: 營業利益率 | B35: % | C35: =C192 -> 0.20271374 | D35: =D192 -> 0.2702513 | E35: =E192 -> 0.29166485 | F35: =F192 -> 0.27810415 | G35: =G192 -> 0.26066291
A36: 歸屬母公司淨利 | B36: NT$B | C36: =C194 -> 14.649 | D36: =D194 -> 42.891099 | E36: =E194 -> 75.092984 | F36: =F194 -> 74.322027 | G36: =G194 -> 76.733067
A37: EPS | B37: NT$ | C37: =C197 -> 41.67 | D37: =D197 -> 119.71052 | E37: =E197 -> 209.58707 | F37: =F197 -> 207.4353 | G37: =G197 -> 214.1646
A38: EPS 年增 | B38: % | D38: =D198 -> 1.8728226 | E38: =E198 -> 0.75078245 | F38: =F198 -> -0.010266698 | G38: =G198 -> 0.032440445
A40: 核對（應為 0）：FY2026 模型營收 − 錨點；FY2026 模型 AI 相關 − 錨點；FY2026 毛利 − 錨點
A41: 情境 A：營收差（NT$B） | D41: =D85-a26_rev -> 0
A42: 情境 A：AI 相關差（NT$B） | D42: =D83-a26_ai -> 0
A43: 情境 A：毛利差（NT$B） | D43: =D92*D83+D91*D82-a26_gp -> 0
A44: 情境 A：產能上限 − 營收（NT$B；FY2026 校準恆等） | D44: =D81-D85 -> 0
A60: 情境 A：基準（顆數係數 1.0）
A61: 項目 | B61: 單位 | C61: FY2025A | D61: FY2026（錨點） | E61: FY2027 | F61: FY2028 | G61: FY2029 | H61: 說明
A62: A. AI 部署與每 GW 高速 CCL 金額（需求面；D 欄＝FY2026 校準年）
A63: AI IT 資本支出 × 情境顆數係數 | B63: US$B | D63: =itc_26*1 -> 781.87292 | E63: =itc_27*1*1 -> 1565.35 | F63: =itc_28*um28_A*1 -> 1984.2639 | G63: =itc_29*um29_A*1 -> 2260.3903
A64: 每 GW IT 資本支出 | B64: US$B | D64: =itpg_gb*(1-vr26)+itpg_vr*vr26 -> 33.414032 | E64: =itpg_vr -> 37.586352 | F64: =itpg_vr -> 37.586352 | G64: =itpg_vr -> 37.586352
A65: 部署 GW（IT 電力） | B65: GW | D65: =D63/D64 -> 23.399538 | E65: =E63/E64 -> 41.646766 | F65: =F63/F64 -> 52.792138 | G65: =G63/G64 -> 60.138592
A66: 每 GW CCL：加速器／運算板 | B66: US$M/GW | D66: =cmp_26 -> 190 | E66: =cmp_26*cmpx_27 -> 275.5 | F66: =cmp_26*cmpx_28 -> 304 | G66: =cmp_26*cmpx_29 -> 323
A67: 每 GW CCL：交換器板 | B67: US$M/GW | D67: =sw_26 -> 90 | E67: =sw_26*swx_27 -> 126 | F67: =sw_26*swx_28 -> 144 | G67: =sw_26*swx_29 -> 157.5
A68: 每 GW CCL：UBB／中板／背板 | B68: US$M/GW | D68: =ubb_26 -> 70 | E68: =ubb_26*ubbx_27 -> 126 | F68: =ubb_26*ubbx_28 -> 161 | G68: =ubb_26*ubbx_29 -> 182
A69: 每 GW 高速 CCL 金額（三項合計） | B69: US$M/GW | D69: =D66+D67+D68 -> 350 | E69: =E66+E67+E68 -> 527.5 | F69: =F66+F67+F68 -> 609 | G69: =G66+G67+G68 -> 662.5
A70: AI 高速 CCL 市場（美元；不含價格指數） | B70: US$B | D70: =D65*D69/1000 -> 8.1898383 | E70: =E65*E69/1000 -> 21.968669 | F70: =F65*F69/1000 -> 32.150412 | G70: =G65*G69/1000 -> 39.841817
A71: AI 高速 CCL 市場（新台幣） | B71: NT$B | D71: =D70*fx -> 262.07483 | E71: =E70*fx -> 702.99741 | F71: =F70*fx -> 1028.8132 | G71: =G70*fx -> 1274.9381
A72: CCL 價格指數（FY2026＝1） | B72: x | D72: =1 -> 1 | E72: =pp_27 -> 1 | F72: =pp_28 -> 0.97 | G72: =pp_29 -> 0.93
A73: 台光電有效份額（FY2026 校準）＝ AI 相關營收 ÷ 市場 | B73: % | D73: =a26_ai/D71 -> 0.45930617 | H73: Derived：分子為公司 AI 相關占比 × 營收；分母為本模型的 AI 高速 CCL 市場（含 ASIC）
A74: 份額相對值（÷ FY2026） | B74: x | D74: =1 -> 1 | E74: =rel_27 -> 0.95 | F74: =rel_28 -> 0.9 | G74: =rel_29 -> 0.85
A75: 台光電有效份額 | B75: % | D75: =$D$73*D74 -> 0.45930617 | E75: =$D$73*E74 -> 0.43634086 | F75: =$D$73*F74 -> 0.41337555 | G75: =$D$73*G74 -> 0.39041024
A76: AI 相關營收（需求面）＝ 市場 × 份額 × 價格指數 | B76: NT$B | D76: =D71*D75*D72 -> 120.37258 | E76: =E71*E75*E72 -> 306.74649 | F76: =F71*F75*F72 -> 412.52763 | G76: =G71*G75*G72 -> 462.90648
A77: B. 產能上限（全產全銷）與營收
A78: 平均月產能 | B78: 百萬張／月 | D78: =cap_26 -> 6 | E78: =cap_27 -> 7.76 | F78: =cap_28 -> 10.3 | G78: =cap_29 -> 11.8
A79: 每張營收（FY2026 校準）＝ 錨點營收 ÷（月產能 × 12） | B79: NT$／張 | D79: =a26_rev/(D78*12)*1000 -> 2857.8486 | H79: Derived：全產全銷，FY2026 營收全部由產能吸收；含 PP（膠片）與所有等級
A80: 每張營收組合指數（M8→M9、層數；FY2026＝1） | B80: x | D80: =1 -> 1 | E80: =mix_27 -> 1.25 | F80: =mix_28 -> 1.4 | G80: =mix_29 -> 1.5
A81: 產能上限營收 ＝ 月產能 × 12 × 每張營收 × 組合指數 × 價格指數 | B81: NT$B | D81: =D78*12*$D$79*D80*D72/1000 -> 205.7651 | E81: =E78*12*$D$79*E80*E72/1000 -> 332.65358 | F81: =F78*12*$D$79*F80*F72/1000 -> 479.68646 | G81: =G78*12*$D$79*G80*G72/1000 -> 564.51655
A82: 非 AI 營收 | B82: NT$B | C82: =a25_nai -> 47.1305 | D82: =a26_nai -> 85.392516 | E82: =D82*(1+g_nai27) -> 92.223918 | F82: =E82*(1+g_nai28) -> 97.757353 | G82: =F82*(1+g_nai29) -> 102.64522
A83: AI 相關營收 ＝ MIN（需求面、產能上限 − 非 AI） | B83: NT$B | C83: =a25_ai -> 47.1305 | D83: =D76 -> 120.37258 | E83: =MIN(E76,E81-E82) -> 240.42966 | F83: =MIN(F76,F81-F82) -> 381.92911 | G83: =MIN(G76,G81-G82) -> 461.87133 | H83: 產能不足時，非 AI 照成長率出貨、AI 取剩餘產能（Assumed）
A84: 產能是否受限 | E84: =IF(E76>E81-E82+0.0001,"受限","未受限") -> 受限 | F84: =IF(F76>F81-F82+0.0001,"受限","未受限") -> 受限 | G84: =IF(G76>G81-G82+0.0001,"受限","未受限") -> 受限
A85: 營收 | B85: NT$B | C85: =C83+C82 -> 94.261 | D85: =D83+D82 -> 205.7651 | E85: =E83+E82 -> 332.65358 | F85: =F83+F82 -> 479.68646 | G85: =G83+G82 -> 564.51655
A86: 營收年增 | B86: % | D86: =D85/C85-1 -> 1.1829293 | E86: =E85/D85-1 -> 0.61666667 | F86: =F85/E85-1 -> 0.442 | G86: =G85/F85-1 -> 0.17684487
A87: AI 相關 ÷ 營收 | B87: % | C87: =C83/C85 -> 0.5 | D87: =D83/D85 -> 0.585 | E87: =E83/E85 -> 0.72276289 | F87: =F83/F85 -> 0.79620573 | G87: =G83/G85 -> 0.81817146
A88: 需求面 ÷ 產能上限（AI 需求面＋非 AI） | B88: % | D88: =(D76+D82)/D81 -> 1 | E88: =(E76+E82)/E81 -> 1.199357 | F88: =(F76+F82)/F81 -> 1.0637886 | G88: =(G76+G82)/G81 -> 1.0018337 | H88: 大於 100%＝需求超過產能（營收由產能決定）
A89: 每 GW 台光電 AI 相關營收 | B89: US$M/GW | D89: =D83/fx/D65*1000 -> 160.75716 | E89: =E83/fx/E65*1000 -> 180.40841 | F89: =F83/fx/F65*1000 -> 226.08072 | G89: =G83/fx/G65*1000 -> 240.00361
A90: C. 損益
A91: 其他營收毛利率 ＝ 錨點毛利率 − 差距 × AI 占比（FY2026 校準） | B91: % | D91: =a26_gp/D85-d_ai*D87 -> 0.29156444 | H91: Derived：讓 FY2026 毛利率等於錨點；AI 相關毛利率＝其他＋差距
A92: AI 相關毛利率 ＝ 1 −（1 − 校準值）÷ 價格指數 | B92: % | D92: =D91+d_ai -> 0.37156444 | E92: =1-(1-$D$92)/E72 -> 0.37156444 | F92: =1-(1-$D$92)/F72 -> 0.35212829 | G92: =1-(1-$D$92)/G72 -> 0.32426284 | H92: Derived：每張成本不變，價格升降全部落在毛利（組合升級的毛利效果未另計）
A93: 毛利 | B93: NT$B | C93: =a25_gp -> 28.12 | D93: =a26_gp -> 69.623593 | E93: =E83*E92+E82*$D$91 -> 116.22433 | F93: =F83*F92+F82*$D$91 -> 162.99061 | G93: =G83*G92+G82*$D$91 -> 179.69541
A94: 毛利率 | B94: % | C94: =C93/C85 -> 0.29832062 | D94: =D93/D85 -> 0.33836444 | E94: =E93/E85 -> 0.34938547 | F94: =F93/F85 -> 0.33978573 | G94: =G93/G85 -> 0.31831734
A95: 營業費用（基準路徑） | B95: NT$B | C95: =a25_opx -> 9.012 | D95: =a26_opx -> 14.015308 | E95: =D95*(1+MAX(0,phi*E86)) -> 19.200972 | F95: =E95*(1+MAX(0,phi*F86)) -> 24.29307 | G95: =F95*(1+MAX(0,phi*G86)) -> 26.870733
A96: 營業費用 | B96: NT$B | C96: =C95 -> 9.012 | D96: =D95 -> 14.015308 | E96: =E95+0*E85 -> 19.200972 | F96: =F95+0*F85 -> 24.29307 | G96: =G95+0*G85 -> 26.870733
A97: 營業利益 | B97: NT$B | C97: =C93-C96 -> 19.108 | D97: =D93-D96 -> 55.608285 | E97: =E93-E96 -> 97.023356 | F97: =F93-F96 -> 138.69754 | G97: =G93-G96 -> 152.82467
A98: 營業利益率 | B98: % | C98: =C97/C85 -> 0.20271374 | D98: =D97/D85 -> 0.2702513 | E98: =E97/E85 -> 0.29166485 | F98: =F97/F85 -> 0.28914208 | G98: =G97/G85 -> 0.27071779
A99: 業外收益 | B99: NT$B | E99: =nop_f -> 0.5 | F99: =nop_f -> 0.5 | G99: =nop_f -> 0.5 | H99: FY2025、FY2026 含在淨利錨點內
A100: 歸屬母公司淨利 | B100: NT$B | C100: =a25_ni -> 14.649 | D100: =a26_ni -> 42.891099 | E100: =(E97+E99)*nir_f -> 75.092984 | F100: =(F97+F99)*nir_f -> 107.18211 | G100: =(G97+G99)*nir_f -> 118.06
A101: 淨利 ÷ 營業利益 | B101: % | C101: =C100/C97 -> 0.76664224 | D101: =D100/D97 -> 0.77130771 | E101: =E100/E97 -> 0.77396812 | F101: =F100/F97 -> 0.77277582 | G101: =G100/G97 -> 0.77251923
A102: 股數 | B102: 十億股 | C102: =a25_sh -> 0.35154788 | D102: =a26_sh -> 0.35829016 | E102: =D102*(1+sh_g) -> 0.35829016 | F102: =E102*(1+sh_g) -> 0.35829016 | G102: =F102*(1+sh_g) -> 0.35829016
A103: EPS | B103: NT$ | C103: =C100/C102 -> 41.67 | D103: =D100/D102 -> 119.71052 | E103: =E100/E102 -> 209.58707 | F103: =F100/F102 -> 299.1489 | G103: =G100/G102 -> 329.50947
A104: EPS 年增 | B104: % | D104: =D103/C103-1 -> 1.8728226 | E104: =E103/D103-1 -> 0.75078245 | F104: =F103/E103-1 -> 0.42732519 | G104: =G103/F103-1 -> 0.10148981
A107: 情境 B：CY2028 顆數 ×0.8、CY2029 ×0.85
A108: 項目 | B108: 單位 | C108: FY2025A | D108: FY2026（錨點） | E108: FY2027 | F108: FY2028 | G108: FY2029 | H108: 說明
A109: A. AI 部署與每 GW 高速 CCL 金額（需求面；D 欄＝FY2026 校準年）
A110: AI IT 資本支出 × 情境顆數係數 | B110: US$B | D110: =itc_26*1 -> 781.87292 | E110: =itc_27*1*1 -> 1565.35 | F110: =itc_28*um28_B*1 -> 1587.4111 | G110: =itc_29*um29_B*1 -> 1921.3317
A111: 每 GW IT 資本支出 | B111: US$B | D111: =itpg_gb*(1-vr26)+itpg_vr*vr26 -> 33.414032 | E111: =itpg_vr -> 37.586352 | F111: =itpg_vr -> 37.586352 | G111: =itpg_vr -> 37.586352
A112: 部署 GW（IT 電力） | B112: GW | D112: =D110/D111 -> 23.399538 | E112: =E110/E111 -> 41.646766 | F112: =F110/F111 -> 42.233711 | G112: =G110/G111 -> 51.117803
A113: 每 GW CCL：加速器／運算板 | B113: US$M/GW | D113: =cmp_26 -> 190 | E113: =cmp_26*cmpx_27 -> 275.5 | F113: =cmp_26*cmpx_28 -> 304 | G113: =cmp_26*cmpx_29 -> 323
A114: 每 GW CCL：交換器板 | B114: US$M/GW | D114: =sw_26 -> 90 | E114: =sw_26*swx_27 -> 126 | F114: =sw_26*swx_28 -> 144 | G114: =sw_26*swx_29 -> 157.5
A115: 每 GW CCL：UBB／中板／背板 | B115: US$M/GW | D115: =ubb_26 -> 70 | E115: =ubb_26*ubbx_27 -> 126 | F115: =ubb_26*ubbx_28 -> 161 | G115: =ubb_26*ubbx_29 -> 182
A116: 每 GW 高速 CCL 金額（三項合計） | B116: US$M/GW | D116: =D113+D114+D115 -> 350 | E116: =E113+E114+E115 -> 527.5 | F116: =F113+F114+F115 -> 609 | G116: =G113+G114+G115 -> 662.5
A117: AI 高速 CCL 市場（美元；不含價格指數） | B117: US$B | D117: =D112*D116/1000 -> 8.1898383 | E117: =E112*E116/1000 -> 21.968669 | F117: =F112*F116/1000 -> 25.72033 | G117: =G112*G116/1000 -> 33.865544
A118: AI 高速 CCL 市場（新台幣） | B118: NT$B | D118: =D117*fx -> 262.07483 | E118: =E117*fx -> 702.99741 | F118: =F117*fx -> 823.05055 | G118: =G117*fx -> 1083.6974
A119: CCL 價格指數（FY2026＝1） | B119: x | D119: =1 -> 1 | E119: =pp_27 -> 1 | F119: =pp_28 -> 0.97 | G119: =pp_29 -> 0.93
A120: 台光電有效份額（FY2026 校準）＝ AI 相關營收 ÷ 市場 | B120: % | D120: =a26_ai/D118 -> 0.45930617 | H120: Derived：分子為公司 AI 相關占比 × 營收；分母為本模型的 AI 高速 CCL 市場（含 ASIC）
A121: 份額相對值（÷ FY2026） | B121: x | D121: =1 -> 1 | E121: =rel_27 -> 0.95 | F121: =rel_28 -> 0.9 | G121: =rel_29 -> 0.85
...

Sheet Val
A1: Val — P/E 估值（新台幣）。結論用「現價 ÷ FY2027、FY2028 EPS（模型）」與十年 P/E 規則值（年底落後 P/E，基準為 FY2027 EPS）。本版未做先驗，無 Andy 合理 P/E 對照
A2: 循環位置：台光電不是設備股，不套設備市場見頂年；以本模型營收最高的會計年度為見頂年（比照 NVIDIA、Arista、台達電；FY(t)＝CY(t)）。營收到 FY2029 仍在增加時，見頂年未知，判為中段
A4: 1. 價格與市場隱含倍數
A5: 項目 | B5: A | C5: B | D5: C | E5: 說明
A6: 現價（2026-10-22 收盤） | B6: =px -> 5070
A7: 現價 ÷ FY2026 EPS（錨點） | B7: =px/PL!D13 -> 42.352169 | C7: =px/PL!D25 -> 42.352169 | D7: =px/PL!D37 -> 42.352169
A8: 現價 ÷ FY2027 EPS（模型） | B8: =px/PL!E13 -> 24.190424 | C8: =px/PL!E25 -> 24.190424 | D8: =px/PL!E37 -> 24.190424 | E8: FY2027 三情境相同（顆數係數從 CY2028 開始）
A9: 現價 ÷ FY2028 EPS（模型） | B9: =px/PL!F13 -> 16.948081 | C9: =px/PL!F25 -> 19.224116 | D9: =px/PL!F37 -> 24.441356
A10: 現價 ÷ FY2029 EPS（模型） | B10: =px/PL!G13 -> 15.386508 | C10: =px/PL!G25 -> 17.689414 | D10: =px/PL!G37 -> 23.673381
A11: 未來 12 月 EPS（模型 A）≈ ¼ FY2026＋¾ FY2027 | B11: =0.25*PL!D13+0.75*PL!E13 -> 187.11793
A12: 現價 ÷ 未來 12 月 EPS（模型 A） | B12: =px/B11 -> 27.095212
A13: 近 12 月 P/E（Yahoo 股市、財報狗，10-22） | B13: =pe_ttm -> 79.28
A15: 2. 循環位置（本模型營收最高年；FY(t)＝CY(t)）
A16: 情境 | B16: 營收最高年（FY2026–FY2029） | C16: FY2027 判定 | D16: 規則倍數（P/E） | E16: 見頂年是否未知 | F16: 說明
A17: A | B17: =INDEX({2026,2027,2028,2029},MATCH(MAX(PL!D85:G85),PL!D85:G85,0)) -> 2029 | C17: =IF(B17=2029,"中段",IF(2027<B17,"中段",IF(2027=B17,"見頂","谷底"))) -> 中段 | D17: =IF(C17="見頂",pe_peak,IF(C17="谷底",pe_trough,pe_mid)) -> 13.86 | E17: =IF(B17=2029,"是：營收到觀測期末仍在增加","否") -> 是：營收到觀測期末仍在增加 | F17: tools/cycle_position.py excel_rule；營收最高年取代設備市場見頂年
A18: B | B18: =INDEX({2026,2027,2028,2029},MATCH(MAX(PL!D132:G132),PL!D132:G132,0)) -> 2029 | C18: =IF(B18=2029,"中段",IF(2027<B18,"中段",IF(2027=B18,"見頂","谷底"))) -> 中段 | D18: =IF(C18="見頂",pe_peak,IF(C18="谷底",pe_trough,pe_mid)) -> 13.86 | E18: =IF(B18=2029,"是：營收到觀測期末仍在增加","否") -> 是：營收到觀測期末仍在增加 | F18: 同上
A19: C | B19: =INDEX({2026,2027,2028,2029},MATCH(MAX(PL!D179:G179),PL!D179:G179,0)) -> 2029 | C19: =IF(B19=2029,"中段",IF(2027<B19,"中段",IF(2027=B19,"見頂","谷底"))) -> 中段 | D19: =IF(C19="見頂",pe_peak,IF(C19="谷底",pe_trough,pe_mid)) -> 13.86 | E19: =IF(B19=2029,"是：營收到觀測期末仍在增加","否") -> 是：營收到觀測期末仍在增加 | F19: 同上
A21: 3. 規則值隱含股價（新台幣；約 FY2027 年底，未折現）＝ FY2027 EPS × 規則倍數
A22: 情境 | B22: FY2027 EPS | C22: （同左） | D22: 規則倍數 | E22: 隱含股價 | F22: 相對現價 | G22: 現價 ÷ FY2027 EPS
A23: A | B23: =PL!E13 -> 209.58707 | C23: =B23 -> 209.58707 | D23: =D17 -> 13.86 | E23: =C23*D23 -> 2904.8768 | F23: =E23/px-1 -> -0.427046 | G23: =px/C23 -> 24.190424
A24: B | B24: =PL!E25 -> 209.58707 | C24: =B24 -> 209.58707 | D24: =D18 -> 13.86 | E24: =C24*D24 -> 2904.8768 | F24: =E24/px-1 -> -0.427046 | G24: =px/C24 -> 24.190424
A25: C | B25: =PL!E37 -> 209.58707 | C25: =B25 -> 209.58707 | D25: =D19 -> 13.86 | E25: =C25*D25 -> 2904.8768 | F25: =E25/px-1 -> -0.427046 | G25: =px/C25 -> 24.190424
A26: 4. What must be true：FY2027 年底價 ＝ 現價 ×（1＋報酬）所需的倍數（FY2028 EPS；約 2027 年底的價格看下一年 EPS）
A27: FY2027 年底價 ÷ 現價 | B27: 所需倍數（÷ FY2028 EPS，A） | C27: 所需倍數（÷ FY2028 EPS，C） | D27: 對照：十年中位數 | E27: 對照：十年 75 分位
A28: 0.5 | B28: =px*A28/PL!F13 -> 8.4740407 | C28: =px*A28/PL!F37 -> 12.220678 | D28: =pe_mid -> 13.86 | E28: =pe_trough -> 22.22
A29: 0.75 | B29: =px*A29/PL!F13 -> 12.711061 | C29: =px*A29/PL!F37 -> 18.331017 | D29: =pe_mid -> 13.86 | E29: =pe_trough -> 22.22
A30: 1 | B30: =px*A30/PL!F13 -> 16.948081 | C30: =px*A30/PL!F37 -> 24.441356 | D30: =pe_mid -> 13.86 | E30: =pe_trough -> 22.22
A31: 1.21 | B31: =px*A31/PL!F13 -> 20.507179 | C31: =px*A31/PL!F37 -> 29.57404 | D31: =pe_mid -> 13.86 | E31: =pe_trough -> 22.22
A32: 1.5 | B32: =px*A32/PL!F13 -> 25.422122 | C32: =px*A32/PL!F37 -> 36.662033 | D32: =pe_mid -> 13.86 | E32: =pe_trough -> 22.22
A33: 讀法：1.00＝價格不變、1.21＝一年約 21%。所需倍數遠高於歷史中位數時，現價依賴「AI 期倍數高於 2017–2022 年」與 FY2028 以後的成長延續；倍數是否合理，另看前瞻 P/E 歷史（Bloomberg）。
A50: 6. 十年倍數與規則值（2016–2025 年底；見頂年 25 分位、中段中位數、谷底 75 分位）
A51: 規則（Andy 2026-10-13）：合理倍數＝2016–2025 年底 P/E 依循環位置取分位。採用一個來源（年底收盤 ÷ 當年 EPS，Derived；2016 年 EPS 未找到，共 9 年）；stockanalysis、HiStock 只有 2021–2025，兩者與採用值同量級，只作核對。2017–2022 年台光電以手機、筆電 HDI 材料為主（約 11–17x），AI 前後倍數口徑不同，規則值可能低估 AI 期的合理倍數。
A53: P/E：十年歷史倍數
A54: 年底 | B54: 年底收盤 ÷ 當年 EPS（Yahoo Finance 收盤、HiStock／nstock EPS） | C54: stockanalysis 年度 P/E | D54: HiStock 12 月本益比 | E54: 標記／說明
A55: 2016 | E55: 年底收盤 ÷ 當年 EPS（Yahoo Finance 收盤、HiStock／nstock EPS）：Derived（2017–2025 共 9 年；2016 年 EPS：未找到）；stockanalysis 年度 P/E：Interested-party（資料商；只有 2021–2025，只作核對，不採用）；HiStock 12 月本益比：Interested-party（資料商；近四季 EPS 口徑；只有 2021–2025，不採用）
A56: 2017 | B56: =101.5/8.73 -> 11.626575
A57: 2018 | B57: =65.7/5.48 -> 11.989051
A58: 2019 | B58: =137/10.14 -> 13.510848
A59: 2020 | B59: =157/11.33 -> 13.857017
A60: 2021 | B60: =278/16.5 -> 16.848485 | C60: 16.85 | D60: 18.6
A61: 2022 | B61: =171/15.24 -> 11.220472 | C61: 11.22 | D61: 10.94
A62: 2023 | B62: =382/16.35 -> 23.363914 | C62: 23.78 | D62: 26.84
A63: 2024 | B63: =618/27.81 -> 22.222222 | C63: 22.27 | D63: 23.93
A64: 2025 | B64: =1645/41.67 -> 39.476842 | C64: 40.15 | D64: 43.37
A65: 25 分位（各來源） | B65: =PERCENTILE(B55:B64,0.25) -> 11.989051 | C65: =PERCENTILE(C55:C64,0.25) -> 16.85 | D65: =PERCENTILE(D55:D64,0.25) -> 18.6
A66: 中位數（各來源） | B66: =MEDIAN(B55:B64) -> 13.857017 | C66: =MEDIAN(C55:C64) -> 22.27 | D66: =MEDIAN(D55:D64) -> 23.93
A67: 75 分位（各來源） | B67: =PERCENTILE(B55:B64,0.75) -> 22.222222 | C67: =PERCENTILE(C55:C64,0.75) -> 23.78 | D67: =PERCENTILE(D55:D64,0.75) -> 26.84
A68: 最小（各來源） | B68: =MIN(B55:B64) -> 11.220472 | C68: =MIN(C55:C64) -> 11.22 | D68: =MIN(D55:D64) -> 10.94
A69: 最大（各來源） | B69: =MAX(B55:B64) -> 39.476842 | C69: =MAX(C55:C64) -> 40.15 | D69: =MAX(D55:D64) -> 43.37
A70: 採用 25 分位（P/E） | B70: =ROUND(AVERAGE(B65),2) -> 11.99
A71: 採用 中位數（P/E） | B71: =ROUND(AVERAGE(B66),2) -> 13.86
A72: 採用 75 分位（P/E） | B72: =ROUND(AVERAGE(B67),2) -> 22.22
A73: 採用 最小（P/E） | B73: =ROUND(MIN(B68),2) -> 11.22
A74: 採用 最大（P/E） | B74: =ROUND(MAX(B69),2) -> 39.48
A76: P/E：規則值
A77: 情形 | B77: 循環位置 | C77: 倍數 | D77: 基準 | E77: 每股基準 | F77: 隱含股價 | G77: 相對目前 | H77: 現價 ÷ 基準
A78: 規則值：見頂（P/E） | B78: 25 分位 | C78: =B70 -> 11.99 | D78: FY2027 EPS（A） | E78: =C23 -> 209.58707 | F78: =C78*E78 -> 2512.949 | G78: =F78/px-1 -> -0.50434931 | H78: =px/E78 -> 24.190424
A79: 規則值：中段（P/E） | B79: 中位數 | C79: =B71 -> 13.86 | D79: FY2027 EPS（A） | E79: =C23 -> 209.58707 | F79: =C79*E79 -> 2904.8768 | G79: =F79/px-1 -> -0.427046 | H79: =px/E79 -> 24.190424
A80: 規則值：谷底（P/E） | B80: 75 分位 | C80: =B72 -> 22.22 | D80: FY2027 EPS（A） | E80: =C23 -> 209.58707 | F80: =C80*E80 -> 4657.0247 | G80: =F80/px-1 -> -0.081454693 | H80: =px/E80 -> 24.190424

Sheet Recon
A1: Recon — 本模型 vs 券商估計、研調份額與每架內容。只作事後對照，不為對上數字而調參數。券商多為單一來源；FY2028 共識（付費）未找到
A3: 項目 | B3: 對照值 | C3: 模型 A | D3: 差距 A | E3: 模型 B | F3: 差距 B | G3: 模型 C | H3: 差距 C | I3: 對照來源 | J3: 說明
A4: A. 券商估計（校準未使用）
A5: FY2026 營收 vs 凱基（07-29） | B5: =b_rev26k -> 191.123 | C5: =PL!D85 -> 205.7651 | D5: =C5/B5-1 -> 0.076610874 | E5: =PL!D132 -> 205.7651 | F5: =E5/B5-1 -> 0.076610874 | G5: =PL!D179 -> 205.7651 | H5: =G5/B5-1 -> 0.076610874 | I5: 凱基 2026-07-29 | J5: 3Q26 實際 608.9 億，高於凱基 556.0 億
A6: FY2026 EPS vs 凱基（07-29） | B6: =b_eps26k -> 108.84 | C6: =PL!D103 -> 119.71052 | D6: =C6/B6-1 -> 0.099876109 | E6: =PL!D150 -> 119.71052 | F6: =E6/B6-1 -> 0.099876109 | G6: =PL!D197 -> 119.71052 | H6: =G6/B6-1 -> 0.099876109 | I6: 凱基 2026-07-29
A7: FY2026 EPS vs 市場共識（07-29） | B7: =b_eps26c -> 98.72 | C7: =PL!D103 -> 119.71052 | D7: =C7/B7-1 -> 0.21262678 | E7: =PL!D150 -> 119.71052 | F7: =E7/B7-1 -> 0.21262678 | G7: =PL!D197 -> 119.71052 | H7: =G7/B7-1 -> 0.21262678 | I7: 凱基報告所列共識
A8: FY2026 EPS vs 本土投顧（10-01） | B8: =b_eps26l -> 120.77 | C8: =PL!D103 -> 119.71052 | D8: =C8/B8-1 -> -0.0087727437 | E8: =PL!D150 -> 119.71052 | F8: =E8/B8-1 -> -0.0087727437 | G8: =PL!D197 -> 119.71052 | H8: =G8/B8-1 -> -0.0087727437 | I8: 三立 2026-10-01 | J8: 3Q 營收公布前
A9: FY2027 營收 vs 凱基 | B9: =b_rev27k -> 306.405 | C9: =PL!E85 -> 332.65358 | D9: =C9/B9-1 -> 0.085666286 | E9: =PL!E132 -> 332.65358 | F9: =E9/B9-1 -> 0.085666286 | G9: =PL!E179 -> 332.65358 | H9: =G9/B9-1 -> 0.085666286 | I9: 凱基 2026-07-29
A10: FY2027 營收 vs 本土投顧 | B10: =b_rev27l -> 353.014 | C10: =PL!E85 -> 332.65358 | D10: =C10/B10-1 -> -0.057675961 | E10: =PL!E132 -> 332.65358 | F10: =E10/B10-1 -> -0.057675961 | G10: =PL!E179 -> 332.65358 | H10: =G10/B10-1 -> -0.057675961 | I10: 三立 2026-10-01
A11: FY2027 EPS vs 凱基（07-29） | B11: =b_eps27k -> 190.64 | C11: =PL!E103 -> 209.58707 | D11: =C11/B11-1 -> 0.099386647 | E11: =PL!E150 -> 209.58707 | F11: =E11/B11-1 -> 0.099386647 | G11: =PL!E197 -> 209.58707 | H11: =G11/B11-1 -> 0.099386647 | I11: 凱基 2026-07-29
A12: FY2027 EPS vs 市場共識（07-29） | B12: =b_eps27c -> 193.33 | C12: =PL!E103 -> 209.58707 | D12: =C12/B12-1 -> 0.084089745 | E12: =PL!E150 -> 209.58707 | F12: =E12/B12-1 -> 0.084089745 | G12: =PL!E197 -> 209.58707 | H12: =G12/B12-1 -> 0.084089745 | I12: 凱基報告所列共識
A13: FY2027 EPS vs 本土投顧（10-01） | B13: =b_eps27l -> 204.85 | C13: =PL!E103 -> 209.58707 | D13: =C13/B13-1 -> 0.023124581 | E13: =PL!E150 -> 209.58707 | F13: =E13/B13-1 -> 0.023124581 | G13: =PL!E197 -> 209.58707 | H13: =G13/B13-1 -> 0.023124581 | I13: 三立 2026-10-01 | J13: 三個來源區間 190.6–204.9
A14: FY2028 營收 vs Morgan Stanley 隱含（複合成長 76%） | B14: =ms_rev28 -> 513.88986 | C14: =PL!F85 -> 479.68646 | D14: =C14/B14-1 -> -0.066557837 | E14: =PL!F132 -> 427.77946 | F14: =E14/B14-1 -> -0.16756587 | G14: =PL!F179 -> 345.27393 | H14: =G14/B14-1 -> -0.32811686 | I14: Morgan Stanley（Deep News 2026-09-23） | J14: 由成長率推算，非原文數字
A15: FY2028 EPS vs Morgan Stanley 隱含（目標價 ÷ 20 倍） | B15: =ms_eps28 -> 420 | C15: =PL!F103 -> 299.1489 | D15: =C15/B15-1 -> -0.2877407 | E15: =PL!F150 -> 263.73124 | F15: =E15/B15-1 -> -0.37206848 | G15: =PL!F197 -> 207.4353 | H15: =G15/B15-1 -> -0.50610642 | I15: 同上 | J15: 由目標價推算，非原文數字
A16: B. 份額與每 GW 金額（機制檢查）
A17: FY2026 台光電有效份額 vs Prismark 高速材料 2025 | B17: =hs_sh25 -> 0.386 | C17: =PL!D73 -> 0.45930617 | D17: =C17-B17 -> 0.073306166 | E17: =PL!D120 -> 0.45930617 | F17: =E17-B17 -> 0.073306166 | G17: =PL!D167 -> 0.45930617 | H17: =G17-B17 -> 0.073306166 | I17: Prismark（公司轉述） | J17: 口徑不同：本模型分母只含 AI 部署（含 ASIC），不含非 AI 高速材料
A18: FY2026 台光電有效份額 vs 公司自估（超過 50%） | B18: =hs_sh25c -> 0.5 | C18: =PL!D73 -> 0.45930617 | D18: =C18-B18 -> -0.040693834 | E18: =PL!D120 -> 0.45930617 | F18: =E18-B18 -> -0.040693834 | G18: =PL!D167 -> 0.45930617 | H18: =G18-B18 -> -0.040693834 | I18: 公司（富果 2026-03-12）
A19: CY2027 每 GW 金額指數（÷ CY2026）vs Morgan Stanley 每架金額換算 | B19: =(ms_rk_vr*racks_vr)/(ms_rk_gb*racks_gb*(1-vr26)+ms_rk_vr*racks_vr*vr26) -> 1.4600249 | C19: =PL!E69/PL!D69 -> 1.5071429 | D19: =C19/B19-1 -> 0.032272036 | E19: =PL!E116/PL!D116 -> 1.5071429 | F19: =E19/B19-1 -> 0.032272036 | G19: =PL!E163/PL!D163 -> 1.5071429 | H19: =G19/B19-1 -> 0.032272036 | I19: Morgan Stanley 每架 GB300 6,695、VR200 18,750 美元 × 每 GW 架數 | J19: 對照值以 2026 年 Rubin 占比混合
A20: CY2027 每 GW 金額指數（÷ CY2026）vs 每架張數換算 | B20: =(sht_vr*racks_vr)/(sht_gb*racks_gb*(1-vr26)+sht_vr*racks_vr*vr26) -> 1.6965234 | C20: =PL!E69/PL!D69 -> 1.5071429 | D20: =C20/B20-1 -> -0.11162861 | E20: =PL!E116/PL!D116 -> 1.5071429 | F20: =E20/B20-1 -> -0.11162861 | G20: =PL!E163/PL!D163 -> 1.5071429 | H20: =G20/B20-1 -> -0.11162861 | I20: 源達證券：每架 164 張 → 578 張 | J20: 張數不含材料等級升級（M8 → M9）
A21: CY2027 每架等值 CCL（US$K，VR200 架數）vs Morgan Stanley VR200 每架 | B21: =ms_rk_vr/1000 -> 18.75 | C21: =PL!E69*1000/racks_vr -> 130.18263 | E21: =PL!E116*1000/racks_vr -> 130.18263 | G21: =PL!E163*1000/racks_vr -> 130.18263 | I21: Morgan Stanley | J21: 本模型含交換器（scale-out）、ASIC 與 UBB；Morgan Stanley 口徑較窄（未載明），差距不具意義，不列
A22: FY2027 每 GW 台光電 AI 相關營收（US$M） | C22: =PL!E89 -> 180.40841 | E22: =PL!E136 -> 180.40841 | G22: =PL!E183 -> 180.40841 | I22: —
A23: C. 產能與校準
A24: FY2027 需求面 ÷ 產能上限 | C24: =PL!E88 -> 1.199357 | E24: =PL!E135 -> 1.199357 | G24: =PL!E182 -> 1.199357 | I24: — | J24: 大於 100%＝產能受限
A25: FY2028 需求面 ÷ 產能上限 | C25: =PL!F88 -> 1.0637886 | E25: =PL!F135 -> 0.89178973 | G25: =PL!F182 -> 0.71979086 | I25: —
A26: 每張營收 FY2026（NT$；校準） | C26: =PL!D79 -> 2857.8486 | E26: =PL!D126 -> 2857.8486 | G26: =PL!D173 -> 2857.8486 | I26: — | J26: FY2025：942.6 億 ÷（585 萬張 × 12）≈ NT$1,343（Q 頁）；漲價與 M8 組合使每張營收倍增
A27: 其他營收毛利率（Derived） | C27: =PL!D91 -> 0.29156444 | E27: =PL!D138 -> 0.29156444 | G27: =PL!D185 -> 0.29156444 | I27: FY2026 錨點 | J27: AI 相關毛利率＝此值＋d_ai
A28: FY2027 毛利率 vs FY2026（百分點） | B28: =a26_gp/a26_rev -> 0.33836444 | C28: =PL!E94 -> 0.34938547 | D28: =C28-B28 -> 0.011021031 | E28: =PL!E141 -> 0.34938547 | F28: =E28-B28 -> 0.011021031 | G28: =PL!E188 -> 0.34938547 | H28: =G28-B28 -> 0.011021031 | I28: 錨點 | J28: AI 占比上升使毛利率上升
A29: 4Q26 EPS（模型） | C29: =Q!E15 -> 39.744006 | E29: =Q!E15 -> 39.744006 | G29: =Q!E15 -> 39.744006 | I29: — | J29: 本土投顧 3Q26 估 36.85（10-01）
A30: D. 預留
A31: R4 產業部署路徑（markets/deploy_path/，尚未建立）：上線後以部署路徑取代「AI IT 資本支出 ÷ 每 GW IT 資本支出」 | J31: 預留列：本版無數值

Sheet Sens
A1: Sens — 一次動一個輸入（情境 A；有效份額、每張營收、其他營收毛利率在每個案例內依 FY2026 錨點重算，FY2026 恆等於錨點）：對 FY2027、FY2028 的營收、AI 相關營收、毛利率與 EPS 的影響。每個案例是一個完整推導區塊（本頁下方）
A3: 案例 | B3: 設定 | C3: FY2027 營收 | D3: FY2027 AI 相關 | E3: FY2027 毛利率 | F3: FY2027 EPS | G3: FY2027 EPS 相對基準 | H3: FY2028 營收 | I3: FY2028 AI 相關 | J3: FY2028 毛利率 | K3: FY2028 EPS | L3: FY2028 EPS 相對基準
A4: 基準（情境 A） | B4: PL 區塊 A | C4: =PL!E85 -> 332.65358 | D4: =PL!E83 -> 240.42966 | E4: =PL!E94 -> 0.34938547 | F4: =PL!E103 -> 209.58707 | G4: =F4/F$4-1 -> 0 | H4: =PL!F85 -> 479.68646 | I4: =PL!F83 -> 381.92911 | J4: =PL!F94 -> 0.33978573 | K4: =PL!F103 -> 299.1489 | L4: =K4/K$4-1 -> 0
A5: 每 GW 金額成長 低 | B5: 三項指數皆取低值（運算板 2027 1.20、交換器 1.15、中板 1.30） | C5: =E65 -> 332.65358 | D5: =E63 -> 240.42966 | E5: =E74 -> 0.34938547 | F5: =E83 -> 209.58707 | G5: =F5/F$4-1 -> 0 | H5: =F65 -> 412.40281 | I5: =F63 -> 314.64546 | J5: =F74 -> 0.33777203 | K5: =F83 -> 253.2393 | L5: =K5/K$4-1 -> -0.15346739
A6: 每 GW 金額成長 高 | B6: 三項指數皆取高值（運算板 2027 1.80、交換器 1.70、中板 2.50） | C6: =E112 -> 332.65358 | D6: =E110 -> 240.42966 | E6: =E121 -> 0.34938547 | F6: =E130 -> 209.58707 | G6: =F6/F$4-1 -> 0 | H6: =F112 -> 479.68646 | I6: =F110 -> 381.92911 | J6: =F121 -> 0.33978573 | K6: =F130 -> 299.1489 | L6: =K6/K$4-1 -> 0
A7: 中板／背板成長 低 | B7: 只動 UBB／中板指數（2027 1.30、2028 1.50） | C7: =E159 -> 332.65358 | D7: =E157 -> 240.42966 | E7: =E168 -> 0.34938547 | F7: =E177 -> 209.58707 | G7: =F7/F$4-1 -> 0 | H7: =F159 -> 472.35141 | I7: =F157 -> 374.59406 | J7: =F168 -> 0.33959406 | K7: =F177 -> 294.14398 | L7: =K7/K$4-1 -> -0.016730532
A8: 中板／背板成長 高 | B8: 只動 UBB／中板指數（2027 2.50、2028 3.00） | C8: =E206 -> 332.65358 | D8: =E204 -> 240.42966 | E8: =E215 -> 0.34938547 | F8: =E224 -> 209.58707 | G8: =F8/F$4-1 -> 0 | H8: =F206 -> 479.68646 | I8: =F204 -> 381.92911 | J8: =F215 -> 0.33978573 | K8: =F224 -> 299.1489 | L8: =K8/K$4-1 -> 0
A9: 份額流失（低） | B9: 份額相對值 2027 0.85、2028 0.75、2029 0.70（台燿、斗山、生益追趕） | C9: =E253 -> 332.65358 | D9: =E251 -> 240.42966 | E9: =E262 -> 0.34938547 | F9: =E271 -> 209.58707 | G9: =F9/F$4-1 -> 0 | H9: =F253 -> 441.53038 | I9: =F251 -> 343.77303 | J9: =F262 -> 0.33871911 | K9: =F271 -> 273.11389 | L9: =K9/K$4-1 -> -0.087030273
A10: 份額上升（高） | B10: 份額相對值 2027 1.05、2028–29 1.00 | C10: =E300 -> 332.65358 | D10: =E298 -> 240.42966 | E10: =E309 -> 0.34938547 | F10: =E318 -> 209.58707 | G10: =F10/F$4-1 -> 0 | H10: =F300 -> 479.68646 | I10: =F298 -> 381.92911 | J10: =F309 -> 0.33978573 | K10: =F318 -> 299.1489 | L10: =K10/K$4-1 -> 0
A11: 價格回落快 | B11: 價格指數 2027 0.95、2028 0.88、2029 0.85 | C11: =E347 -> 316.0209 | D11: =E345 -> 223.79698 | E11: =E356 -> 0.324795 | F11: =E365 -> 181.85819 | G11: =F11/F$4-1 -> -0.13230245 | H11: =F347 -> 435.17947 | I11: =F345 -> 337.42212 | J11: =F356 -> 0.28714816 | K11: =F365 -> 220.81876 | L11: =K11/K$4-1 -> -0.26184332
A12: 價格延續 | B12: 價格指數 2027 1.08、2028 1.05、2029 1.00 | C12: =E394 -> 359.26586 | D12: =E392 -> 267.04195 | E12: =E403 -> 0.38562951 | F12: =E412 -> 255.21583 | G12: =F12/F$4-1 -> 0.21770788 | H12: =F394 -> 519.24823 | I12: =F392 -> 421.49088 | J12: =F403 -> 0.38079459 | K12: =F412 -> 370.75695 | L12: =K12/K$4-1 -> 0.23937258
A13: 擴產延遲 | B13: 平均月產能 2027 7.0、2028 9.5、2029 11.1 百萬張 | C13: =E441 -> 300.0741 | D13: =E439 -> 207.85019 | E13: =E450 -> 0.34697747 | F13: =E459 -> 186.43288 | G13: =F13/F$4-1 -> -0.11047528 | H13: =F441 -> 442.42926 | I13: =F439 -> 344.67191 | J13: =F450 -> 0.33874635 | K13: =F459 -> 273.82795 | L13: =K13/K$4-1 -> -0.084643319
A14: 擴產提前 | B14: 平均月產能 2027 8.2、2028 10.8、2029 13.0 百萬張 | C14: =E488 -> 351.51538 | D14: =E486 -> 259.29146 | E14: =E497 -> 0.35057556 | F14: =E506 -> 222.99213 | G14: =F14/F$4-1 -> 0.063959372 | H14: =F488 -> 502.97221 | I14: =F486 -> 405.21486 | J14: =F497 -> 0.34035714 | K14: =F506 -> 314.9613 | L14: =K14/K$4-1 -> 0.052857934
A15: 每張組合升級 慢 | B15: 組合指數 2027 1.10、2028 1.15、2029 1.20 | C15: =E535 -> 292.73515 | D15: =E533 -> 200.51123 | E15: =E544 -> 0.34636107 | F15: =E553 -> 181.21709 | G15: =F15/F$4-1 -> -0.13536129 | H15: =F535 -> 394.02816 | I15: =F533 -> 296.27081 | J15: =F544 -> 0.33710256 | K15: =F553 -> 240.93652 | L15: =K15/K$4-1 -> -0.19459335
A16: 每張組合升級 快 | B16: 組合指數 2027 1.45、2028 1.70、2029 1.85 | C16: =E582 -> 385.87815 | D16: =E580 -> 293.65423 | E16: =E591 -> 0.35244464 | F16: =E600 -> 247.41371 | G16: =F16/F$4-1 -> 0.18048172 | H16: =F582 -> 510.28498 | I16: =F580 -> 412.52763 | J16: =F591 -> 0.34052583 | K16: =F600 -> 319.68682 | L16: =K16/K$4-1 -> 0.068654482
A17: AI 部署 ×0.8 | B17: FY2027 起 AI IT 資本支出 ×0.8 | C17: =E629 -> 332.65358 | D17: =E627 -> 240.42966 | E17: =E638 -> 0.34938547 | F17: =E647 -> 209.58707 | G17: =F17/F$4-1 -> 0 | H17: =F629 -> 427.77946 | I17: =F627 -> 330.0221 | J17: =F638 -> 0.33828807 | K17: =F647 -> 263.73124 | L17: =K17/K$4-1 -> -0.11839477
A18: AI 部署 ×1.2 | B18: ×1.2 | C18: =E676 -> 332.65358 | D18: =E674 -> 240.42966 | E18: =E685 -> 0.34938547 | F18: =E694 -> 209.58707 | G18: =F18/F$4-1 -> 0 | H18: =F676 -> 479.68646 | I18: =F674 -> 381.92911 | J18: =F685 -> 0.33978573 | K18: =F694 -> 299.1489 | L18: =K18/K$4-1 -> 0
A19: AI 毛利率差距 4pt | B19: AI 相關毛利率只高 4 個百分點 | C19: =E723 -> 332.65358 | D19: =E721 -> 240.42966 | E19: =E732 -> 0.34387496 | F19: =E741 -> 205.64758 | G19: =F19/F$4-1 -> -0.018796448 | H19: =F723 -> 479.68646 | I19: =F721 -> 381.92911 | J19: =F732 -> 0.33092872 | K19: =F741 -> 290.01829 | L19: =K19/K$4-1 -> -0.030521978
A20: AI 毛利率差距 12pt | B20: 高 12 個百分點 | C20: =E770 -> 332.65358 | D20: =E768 -> 240.42966 | E20: =E779 -> 0.35489599 | F20: =E788 -> 213.52656 | G20: =F20/F$4-1 -> 0.018796448 | H20: =F770 -> 479.68646 | I20: =F768 -> 381.92911 | J20: =F779 -> 0.34864273 | K20: =F788 -> 308.27952 | L20: =K20/K$4-1 -> 0.030521978
A21: 非 AI 成長 低 | B21: 2027–29 0% | C21: =E817 -> 332.65358 | D21: =E815 -> 247.26106 | E21: =E826 -> 0.35102836 | F21: =E835 -> 210.76158 | G21: =F21/F$4-1 -> 0.00560391 | H21: =F817 -> 479.68646 | I21: =F815 -> 394.29394 | J21: =F826 -> 0.34134688 | K21: =F835 -> 300.75828 | L21: =K21/K$4-1 -> 0.0053798513
A22: 非 AI 成長 高 | B22: 2027 +15%、2028 +12%、2029 +10% | C22: =E864 -> 332.65358 | D22: =E862 -> 234.45218 | E22: =E873 -> 0.34794795 | F22: =E882 -> 208.55938 | G22: =F22/F$4-1 -> -0.0049034212 | H22: =F864 -> 479.68646 | I22: =F862 -> 369.7009 | J22: =F873 -> 0.33824183 | K22: =F882 -> 297.55731 | L22: =K22/K$4-1 -> -0.0053204054
A23: 顆數情境 B | B23: CY2028 ×0.8、CY2029 ×0.85 | C23: =PL!E132 -> 332.65358 | D23: =PL!E130 -> 240.42966 | E23: =PL!E141 -> 0.34938547 | F23: =PL!E150 -> 209.58707 | G23: =F23/F$4-1 -> 0 | H23: =PL!F132 -> 427.77946 | I23: =PL!F130 -> 330.0221 | J23: =PL!F141 -> 0.33828807 | K23: =PL!F150 -> 263.73124 | L23: =K23/K$4-1 -> -0.11839477
A24: 顆數情境 C | B24: CY2028–29 ×0.6 | C24: =PL!E179 -> 332.65358 | D24: =PL!E177 -> 240.42966 | E24: =PL!E188 -> 0.34938547 | F24: =PL!E197 -> 209.58707 | G24: =F24/F$4-1 -> 0 | H24: =PL!F179 -> 345.27393 | I24: =PL!F177 -> 247.51658 | J24: =PL!F188 -> 0.33498086 | K24: =PL!F197 -> 207.4353 | L24: =K24/K$4-1 -> -0.30658177
A26: 讀法：FY2027 三情境相同；顆數情境 B、C 的差異從 FY2028 起。產能受限的年度，需求面輸入（每 GW 金額、份額、AI 部署）對營收的影響被產能上限截斷，只有產能與每張組合指數會改變營收；價格指數同時改變產能上限營收與 AI 毛利率（成本不變），所以對 EPS 的影響大於對營收。
A40: 案例區塊：每 GW 金額成長 低（情境 A）
A41: 項目 | B41: 單位 | C41: FY2025A | D41: FY2026（錨點） | E41: FY2027 | F41: FY2028 | G41: FY2029 | H41: 說明
A42: A. AI 部署與每 GW 高速 CCL 金額（需求面；D 欄＝FY2026 校準年）
A43: AI IT 資本支出 × 情境顆數係數 | B43: US$B | D43: =itc_26*1 -> 781.87292 | E43: =itc_27*1*1 -> 1565.35 | F43: =itc_28*um28_A*1 -> 1984.2639 | G43: =itc_29*um29_A*1 -> 2260.3903
A44: 每 GW IT 資本支出 | B44: US$B | D44: =itpg_gb*(1-vr26)+itpg_vr*vr26 -> 33.414032 | E44: =itpg_vr -> 37.586352 | F44: =itpg_vr -> 37.586352 | G44: =itpg_vr -> 37.586352
A45: 部署 GW（IT 電力） | B45: GW | D45: =D43/D44 -> 23.399538 | E45: =E43/E44 -> 41.646766 | F45: =F43/F44 -> 52.792138 | G45: =G43/G44 -> 60.138592
A46: 每 GW CCL：加速器／運算板 | B46: US$M/GW | D46: =cmp_26 -> 190 | E46: =cmp_26*CXLO_27 -> 228 | F46: =cmp_26*CXLO_28 -> 247 | G46: =cmp_26*CXLO_29 -> 247
A47: 每 GW CCL：交換器板 | B47: US$M/GW | D47: =sw_26 -> 90 | E47: =sw_26*SXLO_27 -> 103.5 | F47: =sw_26*SXLO_28 -> 112.5 | G47: =sw_26*SXLO_29 -> 117
A48: 每 GW CCL：UBB／中板／背板 | B48: US$M/GW | D48: =ubb_26 -> 70 | E48: =ubb_26*UXLO_27 -> 91 | F48: =ubb_26*UXLO_28 -> 105 | G48: =ubb_26*UXLO_29 -> 105
A49: 每 GW 高速 CCL 金額（三項合計） | B49: US$M/GW | D49: =D46+D47+D48 -> 350 | E49: =E46+E47+E48 -> 422.5 | F49: =F46+F47+F48 -> 464.5 | G49: =G46+G47+G48 -> 469
A50: AI 高速 CCL 市場（美元；不含價格指數） | B50: US$B | D50: =D45*D49/1000 -> 8.1898383 | E50: =E45*E49/1000 -> 17.595759 | F50: =F45*F49/1000 -> 24.521948 | G50: =G45*G49/1000 -> 28.205
A51: AI 高速 CCL 市場（新台幣） | B51: NT$B | D51: =D50*fx -> 262.07483 | E51: =E50*fx -> 563.06427 | F51: =F50*fx -> 784.70234 | G51: =G50*fx -> 902.55998
A52: CCL 價格指數（FY2026＝1） | B52: x | D52: =1 -> 1 | E52: =pp_27 -> 1 | F52: =pp_28 -> 0.97 | G52: =pp_29 -> 0.93
A53: 台光電有效份額（FY2026 校準）＝ AI 相關營收 ÷ 市場 | B53: % | D53: =a26_ai/D51 -> 0.45930617 | H53: Derived：分子為公司 AI 相關占比 × 營收；分母為本模型的 AI 高速 CCL 市場（含 ASIC）
A54: 份額相對值（÷ FY2026） | B54: x | D54: =1 -> 1 | E54: =rel_27 -> 0.95 | F54: =rel_28 -> 0.9 | G54: =rel_29 -> 0.85
A55: 台光電有效份額 | B55: % | D55: =$D$53*D54 -> 0.45930617 | E55: =$D$53*E54 -> 0.43634086 | F55: =$D$53*F54 -> 0.41337555 | G55: =$D$53*G54 -> 0.39041024
A56: AI 相關營收（需求面）＝ 市場 × 份額 × 價格指數 | B56: NT$B | D56: =D51*D55*D52 -> 120.37258 | E56: =E51*E55*E52 -> 245.68795 | F56: =F51*F55*F52 -> 314.64546 | G56: =G51*G55*G52 -> 327.70285
A57: B. 產能上限（全產全銷）與營收
A58: 平均月產能 | B58: 百萬張／月 | D58: =cap_26 -> 6 | E58: =cap_27 -> 7.76 | F58: =cap_28 -> 10.3 | G58: =cap_29 -> 11.8
A59: 每張營收（FY2026 校準）＝ 錨點營收 ÷（月產能 × 12） | B59: NT$／張 | D59: =a26_rev/(D58*12)*1000 -> 2857.8486 | H59: Derived：全產全銷，FY2026 營收全部由產能吸收；含 PP（膠片）與所有等級
A60: 每張營收組合指數（M8→M9、層數；FY2026＝1） | B60: x | D60: =1 -> 1 | E60: =mix_27 -> 1.25 | F60: =mix_28 -> 1.4 | G60: =mix_29 -> 1.5
A61: 產能上限營收 ＝ 月產能 × 12 × 每張營收 × 組合指數 × 價格指數 | B61: NT$B | D61: =D58*12*$D$59*D60*D52/1000 -> 205.7651 | E61: =E58*12*$D$59*E60*E52/1000 -> 332.65358 | F61: =F58*12*$D$59*F60*F52/1000 -> 479.68646 | G61: =G58*12*$D$59*G60*G52/1000 -> 564.51655
A62: 非 AI 營收 | B62: NT$B | C62: =a25_nai -> 47.1305 | D62: =a26_nai -> 85.392516 | E62: =D62*(1+g_nai27) -> 92.223918 | F62: =E62*(1+g_nai28) -> 97.757353 | G62: =F62*(1+g_nai29) -> 102.64522
A63: AI 相關營收 ＝ MIN（需求面、產能上限 − 非 AI） | B63: NT$B | C63: =a25_ai -> 47.1305 | D63: =D56 -> 120.37258 | E63: =MIN(E56,E61-E62) -> 240.42966 | F63: =MIN(F56,F61-F62) -> 314.64546 | G63: =MIN(G56,G61-G62) -> 327.70285 | H63: 產能不足時，非 AI 照成長率出貨、AI 取剩餘產能（Assumed）
A64: 產能是否受限 | E64: =IF(E56>E61-E62+0.0001,"受限","未受限") -> 受限 | F64: =IF(F56>F61-F62+0.0001,"受限","未受限") -> 未受限 | G64: =IF(G56>G61-G62+0.0001,"受限","未受限") -> 未受限
A65: 營收 | B65: NT$B | C65: =C63+C62 -> 94.261 | D65: =D63+D62 -> 205.7651 | E65: =E63+E62 -> 332.65358 | F65: =F63+F62 -> 412.40281 | G65: =G63+G62 -> 430.34808
A66: 營收年增 | B66: % | D66: =D65/C65-1 -> 1.1829293 | E66: =E65/D65-1 -> 0.61666667 | F66: =F65/E65-1 -> 0.23973659 | G66: =G65/F65-1 -> 0.043513922
A67: AI 相關 ÷ 營收 | B67: % | C67: =C63/C65 -> 0.5 | D67: =D63/D65 -> 0.585 | E67: =E63/E65 -> 0.72276289 | F67: =F63/F65 -> 0.76295663 | G67: =G63/G65 -> 0.76148326
A68: 需求面 ÷ 產能上限（AI 需求面＋非 AI） | B68: % | D68: =(D56+D62)/D61 -> 1 | E68: =(E56+E62)/E61 -> 1.0158071 | F68: =(F56+F62)/F61 -> 0.85973411 | G68: =(G56+G62)/G61 -> 0.76233031 | H68: 大於 100%＝需求超過產能（營收由產能決定）
A69: 每 GW 台光電 AI 相關營收 | B69: US$M/GW | D69: =D63/fx/D45*1000 -> 160.75716 | E69: =E63/fx/E45*1000 -> 180.40841 | F69: =F63/fx/F45*1000 -> 186.25255 | G69: =G63/fx/G45*1000 -> 170.28523
A70: C. 損益
A71: 其他營收毛利率 ＝ 錨點毛利率 − 差距 × AI 占比（FY2026 校準） | B71: % | D71: =a26_gp/D65-d_ai*D67 -> 0.29156444 | H71: Derived：讓 FY2026 毛利率等於錨點；AI 相關毛利率＝其他＋差距
A72: AI 相關毛利率 ＝ 1 −（1 − 校準值）÷ 價格指數 | B72: % | D72: =D71+d_ai -> 0.37156444 | E72: =1-(1-$D$72)/E52 -> 0.37156444 | F72: =1-(1-$D$72)/F52 -> 0.35212829 | G72: =1-(1-$D$72)/G52 -> 0.32426284 | H72: Derived：每張成本不變，價格升降全部落在毛利（組合升級的毛利效果未另計）
A73: 毛利 | B73: NT$B | C73: =a25_gp -> 28.12 | D73: =a26_gp -> 69.623593 | E73: =E63*E72+E62*$D$71 -> 116.22433 | F73: =F63*F72+F62*$D$71 -> 139.29814 | G73: =G63*G72+G62*$D$71 -> 136.18956
A74: 毛利率 | B74: % | C74: =C73/C65 -> 0.29832062 | D74: =D73/D65 -> 0.33836444 | E74: =E73/E65 -> 0.34938547 | F74: =F73/F65 -> 0.33777203 | G74: =G73/G65 -> 0.31646373
A75: 營業費用（基準路徑） | B75: NT$B | C75: =a25_opx -> 9.012 | D75: =a26_opx -> 14.015308 | E75: =D75*(1+MAX(0,phi*E66)) -> 19.200972 | F75: =E75*(1+MAX(0,phi*F66)) -> 21.962877 | G75: =F75*(1+MAX(0,phi*G66)) -> 22.536292
A76: 營業費用 | B76: NT$B | C76: =C75 -> 9.012 | D76: =D75 -> 14.015308 | E76: =E75+0*E65 -> 19.200972 | F76: =F75+0*F65 -> 21.962877 | G76: =G75+0*G65 -> 22.536292
A77: 營業利益 | B77: NT$B | C77: =C73-C76 -> 19.108 | D77: =D73-D76 -> 55.608285 | E77: =E73-E76 -> 97.023356 | F77: =F73-F76 -> 117.33526 | G77: =G73-G76 -> 113.65326
A78: 營業利益率 | B78: % | C78: =C77/C65 -> 0.20271374 | D78: =D77/D65 -> 0.2702513 | E78: =E77/E65 -> 0.29166485 | F78: =F77/F65 -> 0.28451615 | G78: =G77/G65 -> 0.26409614
A79: 業外收益 | B79: NT$B | E79: =nop_f -> 0.5 | F79: =nop_f -> 0.5 | G79: =nop_f -> 0.5 | H79: FY2025、FY2026 含在淨利錨點內
A80: 歸屬母公司淨利 | B80: NT$B | C80: =a25_ni -> 14.649 | D80: =a26_ni -> 42.891099 | E80: =(E77+E79)*nir_f -> 75.092984 | F80: =(F77+F79)*nir_f -> 90.733149 | G80: =(G77+G79)*nir_f -> 87.898013
A81: 淨利 ÷ 營業利益 | B81: % | C81: =C80/C77 -> 0.76664224 | D81: =D80/D77 -> 0.77130771 | E81: =E80/E77 -> 0.77396812 | F81: =F80/F77 -> 0.7732812 | G81: =G80/G77 -> 0.7733875
A82: 股數 | B82: 十億股 | C82: =a25_sh -> 0.35154788 | D82: =a26_sh -> 0.35829016 | E82: =D82*(1+sh_g) -> 0.35829016 | F82: =E82*(1+sh_g) -> 0.35829016 | G82: =F82*(1+sh_g) -> 0.35829016
A83: EPS | B83: NT$ | C83: =C80/C82 -> 41.67 | D83: =D80/D82 -> 119.71052 | E83: =E80/E82 -> 209.58707 | F83: =F80/F82 -> 253.2393 | G83: =G80/G82 -> 245.32634
A84: EPS 年增 | B84: % | D84: =D83/C83-1 -> 1.8728226 | E84: =E83/D83-1 -> 0.75078245 | F84: =F83/E83-1 -> 0.20827731 | G84: =G83/F83-1 -> -0.031246972
A87: 案例區塊：每 GW 金額成長 高（情境 A）
A88: 項目 | B88: 單位 | C88: FY2025A | D88: FY2026（錨點） | E88: FY2027 | F88: FY2028 | G88: FY2029 | H88: 說明
A89: A. AI 部署與每 GW 高速 CCL 金額（需求面；D 欄＝FY2026 校準年）
A90: AI IT 資本支出 × 情境顆數係數 | B90: US$B | D90: =itc_26*1 -> 781.87292 | E90: =itc_27*1*1 -> 1565.35 | F90: =itc_28*um28_A*1 -> 1984.2639 | G90: =itc_29*um29_A*1 -> 2260.3903
A91: 每 GW IT 資本支出 | B91: US$B | D91: =itpg_gb*(1-vr26)+itpg_vr*vr26 -> 33.414032 | E91: =itpg_vr -> 37.586352 | F91: =itpg_vr -> 37.586352 | G91: =itpg_vr -> 37.586352
A92: 部署 GW（IT 電力） | B92: GW | D92: =D90/D91 -> 23.399538 | E92: =E90/E91 -> 41.646766 | F92: =F90/F91 -> 52.792138 | G92: =G90/G91 -> 60.138592
A93: 每 GW CCL：加速器／運算板 | B93: US$M/GW | D93: =cmp_26 -> 190 | E93: =cmp_26*CXHI_27 -> 342 | F93: =cmp_26*CXHI_28 -> 380 | G93: =cmp_26*CXHI_29 -> 418
A94: 每 GW CCL：交換器板 | B94: US$M/GW | D94: =sw_26 -> 90 | E94: =sw_26*SXHI_27 -> 153 | F94: =sw_26*SXHI_28 -> 180 | G94: =sw_26*SXHI_29 -> 198
A95: 每 GW CCL：UBB／中板／背板 | B95: US$M/GW | D95: =ubb_26 -> 70 | E95: =ubb_26*UXHI_27 -> 175 | F95: =ubb_26*UXHI_28 -> 210 | G95: =ubb_26*UXHI_29 -> 245
A96: 每 GW 高速 CCL 金額（三項合計） | B96: US$M/GW | D96: =D93+D94+D95 -> 350 | E96: =E93+E94+E95 -> 670 | F96: =F93+F94+F95 -> 770 | G96: =G93+G94+G95 -> 861
A97: AI 高速 CCL 市場（美元；不含價格指數） | B97: US$B | D97: =D92*D96/1000 -> 8.1898383 | E97: =E92*E96/1000 -> 27.903333 | F97: =F92*F96/1000 -> 40.649946 | G97: =G92*G96/1000 -> 51.779327
A98: AI 高速 CCL 市場（新台幣） | B98: NT$B | D98: =D97*fx -> 262.07483 | E98: =E97*fx -> 892.90666 | F98: =F97*fx -> 1300.7983 | G98: =G97*fx -> 1656.9385
A99: CCL 價格指數（FY2026＝1） | B99: x | D99: =1 -> 1 | E99: =pp_27 -> 1 | F99: =pp_28 -> 0.97 | G99: =pp_29 -> 0.93
A100: 台光電有效份額（FY2026 校準）＝ AI 相關營收 ÷ 市場 | B100: % | D100: =a26_ai/D98 -> 0.45930617 | H100: Derived：分子為公司 AI 相關占比 × 營收；分母為本模型的 AI 高速 CCL 市場（含 ASIC）
A101: 份額相對值（÷ FY2026） | B101: x | D101: =1 -> 1 | E101: =rel_27 -> 0.95 | F101: =rel_28 -> 0.9 | G101: =rel_29 -> 0.85
A102: 台光電有效份額 | B102: % | D102: =$D$100*D101 -> 0.45930617 | E102: =$D$100*E101 -> 0.43634086 | F102: =$D$100*F101 -> 0.41337555 | G102: =$D$100*G101 -> 0.39041024
A103: AI 相關營收（需求面）＝ 市場 × 份額 × 價格指數 | B103: NT$B | D103: =D98*D102*D99 -> 120.37258 | E103: =E98*E102*E99 -> 389.61166 | F103: =F98*F102*F99 -> 521.58666 | G103: =G98*G102*G99 -> 601.60375
A104: B. 產能上限（全產全銷）與營收
A105: 平均月產能 | B105: 百萬張／月 | D105: =cap_26 -> 6 | E105: =cap_27 -> 7.76 | F105: =cap_28 -> 10.3 | G105: =cap_29 -> 11.8
A106: 每張營收（FY2026 校準）＝ 錨點營收 ÷（月產能 × 12） | B106: NT$／張 | D106: =a26_rev/(D105*12)*1000 -> 2857.8486 | H106: Derived：全產全銷，FY2026 營收全部由產能吸收；含 PP（膠片）與所有等級
A107: 每張營收組合指數（M8→M9、層數；FY2026＝1） | B107: x | D107: =1 -> 1 | E107: =mix_27 -> 1.25 | F107: =mix_28 -> 1.4 | G107: =mix_29 -> 1.5
A108: 產能上限營收 ＝ 月產能 × 12 × 每張營收 × 組合指數 × 價格指數 | B108: NT$B | D108: =D105*12*$D$106*D107*D99/1000 -> 205.7651 | E108: =E105*12*$D$106*E107*E99/1000 -> 332.65358 | F108: =F105*12*$D$106*F107*F99/1000 -> 479.68646 | G108: =G105*12*$D$106*G107*G99/1000 -> 564.51655
A109: 非 AI 營收 | B109: NT$B | C109: =a25_nai -> 47.1305 | D109: =a26_nai -> 85.392516 | E109: =D109*(1+g_nai27) -> 92.223918 | F109: =E109*(1+g_nai28) -> 97.757353 | G109: =F109*(1+g_nai29) -> 102.64522
A110: AI 相關營收 ＝ MIN（需求面、產能上限 − 非 AI） | B110: NT$B | C110: =a25_ai -> 47.1305 | D110: =D103 -> 120.37258 | E110: =MIN(E103,E108-E109) -> 240.42966 | F110: =MIN(F103,F108-F109) -> 381.92911 | G110: =MIN(G103,G108-G109) -> 461.87133 | H110: 產能不足時，非 AI 照成長率出貨、AI 取剩餘產能（Assumed）
A111: 產能是否受限 | E111: =IF(E103>E108-E109+0.0001,"受限","未受限") -> 受限 | F111: =IF(F103>F108-F109+0.0001,"受限","未受限") -> 受限 | G111: =IF(G103>G108-G109+0.0001,"受限","未受限") -> 受限
A112: 營收 | B112: NT$B | C112: =C110+C109 -> 94.261 | D112: =D110+D109 -> 205.7651 | E112: =E110+E109 -> 332.65358 | F112: =F110+F109 -> 479.68646 | G112: =G110+G109 -> 564.51655
A113: 營收年增 | B113: % | D113: =D112/C112-1 -> 1.1829293 | E113: =E112/D112-1 -> 0.61666667 | F113: =F112/E112-1 -> 0.442 | G113: =G112/F112-1 -> 0.17684487
A114: AI 相關 ÷ 營收 | B114: % | C114: =C110/C112 -> 0.5 | D114: =D110/D112 -> 0.585 | E114: =E110/E112 -> 0.72276289 | F114: =F110/F112 -> 0.79620573 | G114: =G110/G112 -> 0.81817146
A115: 需求面 ÷ 產能上限（AI 需求面＋非 AI） | B115: % | D115: =(D103+D109)/D108 -> 1 | E115: =(E103+E109)/E108 -> 1.4484605 | F115: =(F103+F109)/F108 -> 1.2911434 | G115: =(G103+G109)/G108 -> 1.2475258 | H115: 大於 100%＝需求超過產能（營收由產能決定）
A116: 每 GW 台光電 AI 相關營收 | B116: US$M/GW | D116: =D110/fx/D92*1000 -> 160.75716 | E116: =E110/fx/E92*1000 -> 180.40841 | F116: =F110/fx/F92*1000 -> 226.08072 | G116: =G110/fx/G92*1000 -> 240.00361
A117: C. 損益
...

Sheet Sources
A1: 來源（公司原文＝台光電法說，經富果、uanalyze、udn 轉述；季報細項取自凱基整理；券商與研調皆為 Interested-party）
A2: 公司：4Q25 法說（富果 2026-03-12；FY2025、4Q25、產品組合、擴產、M8／M9、漲價、份額） | B2: https://blog.fugle.tw/post/earnings-call-2383-2026-03-12
A3: 公司：2Q26 法說（富果 2026-08-27；3Q26 指引、基礎設施占比、產能 2028 年 1,110 萬張） | B3: https://blog.fugle.tw/post/earnings-call-2383-2026-08-27
A4: 二手：uanalyze 2026-07-29（2Q26、1H26 營收、毛利率、淨利、EPS；Prismark 高速材料 38.6%） | B4: https://uanalyze.com.tw/articles/9219952430
A5: 二手：uanalyze FY2025（EPS 41.67、營收 942.6 億、股利 25 元） | B5: https://uanalyze.com.tw/articles/5965248827
A6: 二手：udn 1Q26（淨利 53.4 億、EPS 14.9） | B6: https://udn.com/news/story/7253/9472499
A7: 月營收：TechNews 2026-10-05（9 月 215.32 億、前 9 月 1,412.27 億） | B7: https://finance.technews.tw/2026/10/05/emc-2383-202609-financial-report/
A8: 券商：凱基 2026-07-29（2Q26 損益細項、3Q26 與 2026–27 預估、共識、產品組合、M7 以上占比） | B8: https://www.kgi.com.hk/zh-hk/-/media/files/kgishk/research-reports/tw-reports/emc-2383-tt20260729en.pdf
A9: 券商：三立／鏡週刊 2026-10-01（本土投顧 2026–27 EPS、產能路徑、高階 CCL 供需） | B9: https://www.mirrormedia.mg/external/setn_1915172
A10: 券商：Morgan Stanley（經 Deep News／老虎 2026-09-23；CCL 每架金額、TAM、台光電成長率與目標價） | B10: https://www.itiger.com/news/1142209073
A11: 研調：源達證券 2026-09-28（新浪轉載；每架 CCL 張數、板層數、Prismark 份額） | B11: https://finance.sina.cn/2026-09-28/detail-initkarh2920455.d.html
A12: 資料商：Yahoo 股市、財報狗（10-22 收盤、近 12 月 P/E） | B12: https://tw.stock.yahoo.com/quote/2383.TW
A13: 資料商：Yahoo Finance 月線收盤（2016–2025 年 12 月） | B13: https://finance.yahoo.com/quote/2383.TW/history/
... A15: 資料商：玩股網（單季營業利益季增率，用於拆 1Q26 營業利益） | B15: https://www.wantgoo.com/stock/2383/enterprise-growth/operating-profit-margin
A16: 市場層：markets/network、markets/chip_bridge、tsmc 成品（本 repo，唯讀）
A17: 待補（人工）：3Q26 財報與法說（10 月底）；10 月營收（11 月上旬）；法說原文（公司網站）；1H26 業外；2016 年 EPS；前瞻 P/E 十年歷史（Bloomberg）；每張 CCL 單價；FY2028 共識（付費） | B17: 未找到
A18: SemiAnalysis | B18: 未使用
