Workbook

Sheet README
A1: Lam Research（LRCX）收支與估值模型 v0.2.1（AI 半導體 Project 步驟 5：設備與材料） 2026-10-25
A2: 模型命題：Lam 的系統營收跟著晶圓前段設備（WFE）的記憶體與代工邏輯支出走，記憶體占系統營收近一半（DRAM 與 NAND 升級）、中國占營收約三分之一。核心問題：WFE 在 2027 年後放緩、或對中國的出口管制加嚴時，FY2027 以後的 EPS 還撐得住現在約 25 倍的遠期本益比嗎？
A4: 會計年度：7 月到隔年 6 月（FY2027＝2026-07～2027-06）；FY(t)＝CY(t−1) 下半＋CY(t) 上半（上半占比 h1，基準 50%）。FY2026 已結束（實績）；FY2027 第一季（2026-09 季）已於 2026-10-21 公布並納入，12 月季用公司指引。金額十億美元。
A6: 驅動因子 → 推導量
A7: 系統營收（日曆年）＝ k（份額係數）× 設備市場模型的 WFE 分項（代工與邏輯、DRAM、NAND；三情境；markets/equipment）；k 由 CY2026（FY26 Q3–Q4 實績＋FY27 Q1 實績＋Q2 指引）× 客戶別占比校準
A8: CSBG（服務、備件、升級、Reliant）另推：CY2026 錨點 × 年增（CY2027 公司稱逾 15%；之後依情境 Assumed）
A9: 毛利率＝截距＋斜率 × ln 營收（FY2026 與 FY2027 上半年化兩點推導）；營業費用＝固定＋變動 × 營收（同兩點）；稅率 16.5%（公司說法）；股數 1.253B 起每年 −1.5%
A10: 情境 A／B／C：WFE 分項讀設備市場模型 A（2029 見頂）／B（2028 持平）／C（2028 −20%）；情境 C 另加出口管制：中國系統營收 −20%（CY2028 起，Assumed；2022 管制類比約三到四成）
A11: Val：P/E 規則——10 年（2016–2025 年底）當期 P/E 分位，見頂年 25 分位、中段中位數、谷底 75 分位；循環位置依設備股共用規則（各情境見頂年度：A 2029、B 2028、C 2027 → FY2027：A 中段、B 中段、C 見頂）。第 0 節：情境加權目標價。本版未做先驗，無 Andy 合理 P/E 對照。
A13: 標記：Verified、Interested-party、Analogy、Assumed、Derived。SemiAnalysis 未使用。
A14: 已知限制：(1) k 只在 CY2026 一點校準，之後份額不變（漂移只在 Sens）；公司稱連續三年優於 WFE，若延續則模型偏低；(2) 客戶別占比為「設備與升級營收」口徑（10-Q），套用於系統營收；DRAM／NAND 拆分來自法說摘要；(3) 中國以總營收占比代用系統營收占比，出口管制折損為 Assumed；(4) 設備市場模型的 WFE 以 SEMI 2025 實績校準，與公司 WFE 口徑不同，只用成長率；(5) CY→FY 以上下半各半轉換，成長年下半較高（h1 區間 45–55%）；(6) CSBG 成長無由下而上（裝機量 × 每腔體支出）推導；(7) NAND 升級潮公司稱 2027 年結束，模型的 NAND 隨設備市場模型 NAND 支出成長，可能高估 CY2028 後的 NAND。
A15: v0.2（2026-10-25）估值 v2：Val 頁新增「0. 目標價」（放在既有內容之後，不位移既有列）＝0.5 × DCF 目標價（股東現金流＝EPS ×（1 − g／ROE），FY2027–32 明確期＋永續，r 10%、g 4%，情境權重 A 0.3／B 0.5／C 0.2）＋0.5 × Comparable 目標價（同業前瞻 P/E 中位數 × 12 個月後前瞻 EPS）；另列 Comparable 單獨目標價、市場共識目標價與差距拆解、歷史分位檢查。原「0. 目標價與上檔空間」改名「舊法：規則值情境加權（參考）」，不再叫目標價。
... A17: v0.2.1：補上檔空間級距、投資建議、重點觀察（數值不變）。Val 頁最後新增「上檔空間級距」「投資建議」兩列（第 138、139 列，依「上檔空間：加權目標價」的固定規則）；重點觀察見下方三列。
A18: ="投資建議："&Val!B139&"（依上檔空間固定規則）" -> 投資建議：中立（依上檔空間固定規則）
A19: 重點觀察 1：目標價 US$203（DCF 147、Comparable 259 各半），比現價 230.10（2026-10-23）低 11.8%，級距 0%～−25%；Comparable 單獨為 +12.5%。DCF 比現價低 36.2%，因情境 B、C 的 EPS 在 FY2029 後依收斂法下滑（C 的 FY2032 EPS 5.25 只有 FY2027 9.42 的 56%），不是 ROE（近三年 56.3%）。
A20: 重點觀察 2：與市場的主要差異在 EPS：本模型前瞻 EPS 10.07 比共識 FY2028 EPS 12.15 低 17.1%（期間約晚四個月），情境 A 的 FY2028 EPS 10.68 也比共識低 12.1%；共識目標價 364.03 隱含 30.0 倍，比同業前瞻 P/E 中位數 25.7 倍高 16.6%。
A21: 重點觀察 3：出口管制與設備市場情境最敏感：中國系統營收 −40% 使 FY2028 EPS −11.8%、設備情境 C 使 −18.2%。下一個檢驗點是 FY2027 第二季（12 月季）財報（預計 2027-01 下旬），檢驗 CY2027 上半年的權重（45%～55% 時 FY2027 EPS ±6.6%）。

Sheet In
A1: In — 輸入（藍字；基準欄 E，低 D、高 F）。金額：十億美元（US$B）；EPS 美元。每個輸入附兩個來源（來源2 找不到者寫「未找到」）；公司原文算一個
A2: 標記：Verified／Interested-party／Analogy／Assumed／Derived；Analogy、Assumed 給低／高區間。SemiAnalysis 未使用。公司財報（8-K 新聞稿、10-K、10-Q）取自 SEC EDGAR 原文；法說內容取自逐字稿摘要（Motley Fool、MarketBeat、TIKR）
A3: 鍵 | B3: 項目 | C3: 單位 | D3: 低 | E3: 基準 | F3: 高 | G3: 標記 | H3: 來源1 | I3: 來源2／說明
A4: A. 晶圓前段設備市場（讀 markets/equipment 成品 Mkt 頁 5A／5B／5C；三情境；日曆年 US$B；唯讀，不另估）
A5: advA_25 | B5: 先進邏輯〔AI〕 CY2025（情境 A） | C5: US$B | E5: 36.032336 | G5: Derived | H5: markets/equipment/dist/20261023_半導體設備市場模型_v0.1.3.xlsx｜Mkt!C120:G120 | I5: markets/equipment：公司資本支出 × 設備占比＋其他廠；2028 起 B、C 乘情境係數（Assumed）
A6: advA_26 | B6: 先進邏輯〔AI〕 CY2026（情境 A） | C6: US$B | E6: 50.324843 | G6: Derived | H6: 同上
A7: advA_27 | B7: 先進邏輯〔AI〕 CY2027（情境 A） | C7: US$B | E7: 60.776431 | G7: Derived | H7: 同上
A8: advA_28 | B8: 先進邏輯〔AI〕 CY2028（情境 A） | C8: US$B | E8: 70.016145 | G8: Derived | H8: 同上
A9: advA_29 | B9: 先進邏輯〔AI〕 CY2029（情境 A） | C9: US$B | E9: 74.209437 | G9: Derived | H9: 同上
A10: oflA_25 | B10: 其他代工與邏輯 CY2025（情境 A） | C10: US$B | E10: 29.569009 | G10: Derived | H10: markets/equipment/dist/20261023_半導體設備市場模型_v0.1.3.xlsx｜Mkt!C121:G121 | I10: markets/equipment：公司資本支出 × 設備占比＋其他廠；2028 起 B、C 乘情境係數（Assumed）
A11: oflA_26 | B11: 其他代工與邏輯 CY2026（情境 A） | C11: US$B | E11: 31.93453 | G11: Derived | H11: 同上
A12: oflA_27 | B12: 其他代工與邏輯 CY2027（情境 A） | C12: US$B | E12: 34.489292 | G12: Derived | H12: 同上
A13: oflA_28 | B13: 其他代工與邏輯 CY2028（情境 A） | C13: US$B | E13: 37.248436 | G13: Derived | H13: 同上
A14: oflA_29 | B14: 其他代工與邏輯 CY2029（情境 A） | C14: US$B | E14: 40.228311 | G14: Derived | H14: 同上
A15: dramA_25 | B15: DRAM（含 HBM）〔AI〕 CY2025（情境 A） | C15: US$B | E15: 26.376109 | G15: Derived | H15: markets/equipment/dist/20261023_半導體設備市場模型_v0.1.3.xlsx｜Mkt!C122:G122 | I15: markets/equipment：公司資本支出 × 設備占比＋其他廠；2028 起 B、C 乘情境係數（Assumed）
A16: dramA_26 | B16: DRAM（含 HBM）〔AI〕 CY2026（情境 A） | C16: US$B | E16: 39.365947 | G16: Derived | H16: 同上
A17: dramA_27 | B17: DRAM（含 HBM）〔AI〕 CY2027（情境 A） | C17: US$B | E17: 53.258733 | G17: Derived | H17: 同上
A18: dramA_28 | B18: DRAM（含 HBM）〔AI〕 CY2028（情境 A） | C18: US$B | E18: 59.5609 | G18: Derived | H18: 同上
A19: dramA_29 | B19: DRAM（含 HBM）〔AI〕 CY2029（情境 A） | C19: US$B | E19: 61.831293 | G19: Derived | H19: 同上
A20: nandA_25 | B20: NAND CY2025（情境 A） | C20: US$B | E20: 12.172602 | G20: Derived | H20: markets/equipment/dist/20261023_半導體設備市場模型_v0.1.3.xlsx｜Mkt!C123:G123 | I20: markets/equipment：公司資本支出 × 設備占比＋其他廠；2028 起 B、C 乘情境係數（Assumed）
A21: nandA_26 | B21: NAND CY2026（情境 A） | C21: US$B | E21: 17.503905 | G21: Derived | H21: 同上
A22: nandA_27 | B22: NAND CY2027（情境 A） | C22: US$B | E22: 23.248027 | G22: Derived | H22: 同上
A23: nandA_28 | B23: NAND CY2028（情境 A） | C23: US$B | E23: 26.181322 | G23: Derived | H23: 同上
A24: nandA_29 | B24: NAND CY2029（情境 A） | C24: US$B | E24: 27.674313 | G24: Derived | H24: 同上
A25: wfeA_25 | B25: 晶圓前段設備合計 CY2025（情境 A） | C25: US$B | E25: 116.89683 | G25: Derived | H25: markets/equipment/dist/20261023_半導體設備市場模型_v0.1.3.xlsx｜Mkt!C127:G127 | I25: markets/equipment：公司資本支出 × 設備占比＋其他廠；2028 起 B、C 乘情境係數（Assumed）
A26: wfeA_26 | B26: 晶圓前段設備合計 CY2026（情境 A） | C26: US$B | E26: 156.15705 | G26: Derived | H26: 同上
A27: wfeA_27 | B27: 晶圓前段設備合計 CY2027（情境 A） | C27: US$B | E27: 192.79547 | G27: Derived | H27: 同上
A28: wfeA_28 | B28: 晶圓前段設備合計 CY2028（情境 A） | C28: US$B | E28: 216.62863 | G28: Derived | H28: 同上
A29: wfeA_29 | B29: 晶圓前段設備合計 CY2029（情境 A） | C29: US$B | E29: 228.90369 | G29: Derived | H29: 同上
A30: advB_25 | B30: 先進邏輯〔AI〕 CY2025（情境 B） | C30: US$B | E30: 36.032336 | G30: Derived | H30: markets/equipment/dist/20261023_半導體設備市場模型_v0.1.3.xlsx｜Mkt!C139:G139 | I30: markets/equipment：公司資本支出 × 設備占比＋其他廠；2028 起 B、C 乘情境係數（Assumed）
A31: advB_26 | B31: 先進邏輯〔AI〕 CY2026（情境 B） | C31: US$B | E31: 50.324843 | G31: Derived | H31: 同上
A32: advB_27 | B32: 先進邏輯〔AI〕 CY2027（情境 B） | C32: US$B | E32: 60.776431 | G32: Derived | H32: 同上
A33: advB_28 | B33: 先進邏輯〔AI〕 CY2028（情境 B） | C33: US$B | E33: 60.776431 | G33: Derived | H33: 同上
A34: advB_29 | B34: 先進邏輯〔AI〕 CY2029（情境 B） | C34: US$B | E34: 57.737609 | G34: Derived | H34: 同上
A35: oflB_25 | B35: 其他代工與邏輯 CY2025（情境 B） | C35: US$B | E35: 29.569009 | G35: Derived | H35: markets/equipment/dist/20261023_半導體設備市場模型_v0.1.3.xlsx｜Mkt!C140:G140 | I35: markets/equipment：公司資本支出 × 設備占比＋其他廠；2028 起 B、C 乘情境係數（Assumed）
A36: oflB_26 | B36: 其他代工與邏輯 CY2026（情境 B） | C36: US$B | E36: 31.93453 | G36: Derived | H36: 同上
A37: oflB_27 | B37: 其他代工與邏輯 CY2027（情境 B） | C37: US$B | E37: 34.489292 | G37: Derived | H37: 同上
A38: oflB_28 | B38: 其他代工與邏輯 CY2028（情境 B） | C38: US$B | E38: 34.489292 | G38: Derived | H38: 同上
A39: oflB_29 | B39: 其他代工與邏輯 CY2029（情境 B） | C39: US$B | E39: 32.764828 | G39: Derived | H39: 同上
A40: dramB_25 | B40: DRAM（含 HBM）〔AI〕 CY2025（情境 B） | C40: US$B | E40: 26.376109 | G40: Derived | H40: markets/equipment/dist/20261023_半導體設備市場模型_v0.1.3.xlsx｜Mkt!C141:G141 | I40: markets/equipment：公司資本支出 × 設備占比＋其他廠；2028 起 B、C 乘情境係數（Assumed）
A41: dramB_26 | B41: DRAM（含 HBM）〔AI〕 CY2026（情境 B） | C41: US$B | E41: 39.365947 | G41: Derived | H41: 同上
A42: dramB_27 | B42: DRAM（含 HBM）〔AI〕 CY2027（情境 B） | C42: US$B | E42: 53.258733 | G42: Derived | H42: 同上
A43: dramB_28 | B43: DRAM（含 HBM）〔AI〕 CY2028（情境 B） | C43: US$B | E43: 53.258733 | G43: Derived | H43: 同上
A44: dramB_29 | B44: DRAM（含 HBM）〔AI〕 CY2029（情境 B） | C44: US$B | E44: 50.595796 | G44: Derived | H44: 同上
A45: nandB_25 | B45: NAND CY2025（情境 B） | C45: US$B | E45: 12.172602 | G45: Derived | H45: markets/equipment/dist/20261023_半導體設備市場模型_v0.1.3.xlsx｜Mkt!C142:G142 | I45: markets/equipment：公司資本支出 × 設備占比＋其他廠；2028 起 B、C 乘情境係數（Assumed）
A46: nandB_26 | B46: NAND CY2026（情境 B） | C46: US$B | E46: 17.503905 | G46: Derived | H46: 同上
A47: nandB_27 | B47: NAND CY2027（情境 B） | C47: US$B | E47: 23.248027 | G47: Derived | H47: 同上
A48: nandB_28 | B48: NAND CY2028（情境 B） | C48: US$B | E48: 23.248027 | G48: Derived | H48: 同上
A49: nandB_29 | B49: NAND CY2029（情境 B） | C49: US$B | E49: 22.085626 | G49: Derived | H49: 同上
A50: wfeB_25 | B50: 晶圓前段設備合計 CY2025（情境 B） | C50: US$B | E50: 116.89683 | G50: Derived | H50: markets/equipment/dist/20261023_半導體設備市場模型_v0.1.3.xlsx｜Mkt!C146:G146 | I50: markets/equipment：公司資本支出 × 設備占比＋其他廠；2028 起 B、C 乘情境係數（Assumed）
A51: wfeB_26 | B51: 晶圓前段設備合計 CY2026（情境 B） | C51: US$B | E51: 156.15705 | G51: Derived | H51: 同上
A52: wfeB_27 | B52: 晶圓前段設備合計 CY2027（情境 B） | C52: US$B | E52: 192.79547 | G52: Derived | H52: 同上
A53: wfeB_28 | B53: 晶圓前段設備合計 CY2028（情境 B） | C53: US$B | E53: 192.79547 | G53: Derived | H53: 同上
A54: wfeB_29 | B54: 晶圓前段設備合計 CY2029（情境 B） | C54: US$B | E54: 183.1557 | G54: Derived | H54: 同上
A55: advC_25 | B55: 先進邏輯〔AI〕 CY2025（情境 C） | C55: US$B | E55: 36.032336 | G55: Derived | H55: markets/equipment/dist/20261023_半導體設備市場模型_v0.1.3.xlsx｜Mkt!C158:G158 | I55: markets/equipment：公司資本支出 × 設備占比＋其他廠；2028 起 B、C 乘情境係數（Assumed）
A56: advC_26 | B56: 先進邏輯〔AI〕 CY2026（情境 C） | C56: US$B | E56: 50.324843 | G56: Derived | H56: 同上
A57: advC_27 | B57: 先進邏輯〔AI〕 CY2027（情境 C） | C57: US$B | E57: 60.776431 | G57: Derived | H57: 同上
A58: advC_28 | B58: 先進邏輯〔AI〕 CY2028（情境 C） | C58: US$B | E58: 48.621145 | G58: Derived | H58: 同上
A59: advC_29 | B59: 先進邏輯〔AI〕 CY2029（情境 C） | C59: US$B | E59: 48.621145 | G59: Derived | H59: 同上
A60: oflC_25 | B60: 其他代工與邏輯 CY2025（情境 C） | C60: US$B | E60: 29.569009 | G60: Derived | H60: markets/equipment/dist/20261023_半導體設備市場模型_v0.1.3.xlsx｜Mkt!C159:G159 | I60: markets/equipment：公司資本支出 × 設備占比＋其他廠；2028 起 B、C 乘情境係數（Assumed）
A61: oflC_26 | B61: 其他代工與邏輯 CY2026（情境 C） | C61: US$B | E61: 31.93453 | G61: Derived | H61: 同上
A62: oflC_27 | B62: 其他代工與邏輯 CY2027（情境 C） | C62: US$B | E62: 34.489292 | G62: Derived | H62: 同上
A63: oflC_28 | B63: 其他代工與邏輯 CY2028（情境 C） | C63: US$B | E63: 27.591434 | G63: Derived | H63: 同上
A64: oflC_29 | B64: 其他代工與邏輯 CY2029（情境 C） | C64: US$B | E64: 27.591434 | G64: Derived | H64: 同上
A65: dramC_25 | B65: DRAM（含 HBM）〔AI〕 CY2025（情境 C） | C65: US$B | E65: 26.376109 | G65: Derived | H65: markets/equipment/dist/20261023_半導體設備市場模型_v0.1.3.xlsx｜Mkt!C160:G160 | I65: markets/equipment：公司資本支出 × 設備占比＋其他廠；2028 起 B、C 乘情境係數（Assumed）
A66: dramC_26 | B66: DRAM（含 HBM）〔AI〕 CY2026（情境 C） | C66: US$B | E66: 39.365947 | G66: Derived | H66: 同上
A67: dramC_27 | B67: DRAM（含 HBM）〔AI〕 CY2027（情境 C） | C67: US$B | E67: 53.258733 | G67: Derived | H67: 同上
A68: dramC_28 | B68: DRAM（含 HBM）〔AI〕 CY2028（情境 C） | C68: US$B | E68: 42.606986 | G68: Derived | H68: 同上
A69: dramC_29 | B69: DRAM（含 HBM）〔AI〕 CY2029（情境 C） | C69: US$B | E69: 42.606986 | G69: Derived | H69: 同上
A70: nandC_25 | B70: NAND CY2025（情境 C） | C70: US$B | E70: 12.172602 | G70: Derived | H70: markets/equipment/dist/20261023_半導體設備市場模型_v0.1.3.xlsx｜Mkt!C161:G161 | I70: markets/equipment：公司資本支出 × 設備占比＋其他廠；2028 起 B、C 乘情境係數（Assumed）
A71: nandC_26 | B71: NAND CY2026（情境 C） | C71: US$B | E71: 17.503905 | G71: Derived | H71: 同上
A72: nandC_27 | B72: NAND CY2027（情境 C） | C72: US$B | E72: 23.248027 | G72: Derived | H72: 同上
A73: nandC_28 | B73: NAND CY2028（情境 C） | C73: US$B | E73: 18.598422 | G73: Derived | H73: 同上
A74: nandC_29 | B74: NAND CY2029（情境 C） | C74: US$B | E74: 18.598422 | G74: Derived | H74: 同上
A75: wfeC_25 | B75: 晶圓前段設備合計 CY2025（情境 C） | C75: US$B | E75: 116.89683 | G75: Derived | H75: markets/equipment/dist/20261023_半導體設備市場模型_v0.1.3.xlsx｜Mkt!C165:G165 | I75: markets/equipment：公司資本支出 × 設備占比＋其他廠；2028 起 B、C 乘情境係數（Assumed）
A76: wfeC_26 | B76: 晶圓前段設備合計 CY2026（情境 C） | C76: US$B | E76: 156.15705 | G76: Derived | H76: 同上
A77: wfeC_27 | B77: 晶圓前段設備合計 CY2027（情境 C） | C77: US$B | E77: 192.79547 | G77: Derived | H77: 同上
A78: wfeC_28 | B78: 晶圓前段設備合計 CY2028（情境 C） | C78: US$B | E78: 154.23638 | G78: Derived | H78: 同上
A79: wfeC_29 | B79: 晶圓前段設備合計 CY2029（情境 C） | C79: US$B | E79: 154.23638 | G79: Derived | H79: 同上
A80: pk_A | B80: 情境 A：設備市場見頂年度（日曆年；循環位置規則用） | C80: 年 | E80: 2029 | G80: Derived | H80: markets/equipment/dist/20261023_半導體設備市場模型_v0.1.3.xlsx｜Mkt!C12 | I80: 設備股共用規則（tools/cycle_position.py）：FY(t) 早於見頂年＝中段、等於＝見頂、晚於＝谷底
A81: pk_B | B81: 情境 B：設備市場見頂年度（日曆年；循環位置規則用） | C81: 年 | E81: 2028 | G81: Derived | H81: markets/equipment/dist/20261023_半導體設備市場模型_v0.1.3.xlsx｜Mkt!C20 | I81: 同上
A82: pk_C | B82: 情境 C：設備市場見頂年度（日曆年；循環位置規則用） | C82: 年 | E82: 2027 | G82: Derived | H82: markets/equipment/dist/20261023_半導體設備市場模型_v0.1.3.xlsx｜Mkt!C28 | I82: 同上
A83: B. 系統營收的情境與份額參數
A84: h1s | B84: 上半年（1–6 月）占日曆年系統營收與 CSBG 的比例（CY→FY 轉換用） | C84: % | D84: 0.45 | E84: 0.5 | F84: 0.55 | G84: Assumed | H84: 無：FY(t)＝CY(t−1) 下半＋CY(t) 上半；基準各半 | I84: CY2026 實績＋指引：上半 8.0、下半 11.8（系統）——成長年下半較高，故區間 45–55%
A85: drift | B85: 相對 WFE 分項的份額漂移（每年，CY2027 起） | C85: %/年 | D85: -0.02 | E85: 0 | F85: 0.02 | G85: Assumed | H85: 無：基準為 0（CY2026 的份額錨點延續） | I85: 公司稱 CY2026 為連續第三年優於 WFE、SAM 占 WFE 比重上升約 4 個百分點（Interested-party）；不放進基準，只在 Sens 列 ±2%
A86: cn_sh | B86: 中國占系統營收比重（以 FY2026 中國占總營收代用） | C86: % | D86: 0.26 | E86: 0.34 | F86: 0.43 | G86: Verified | H86: Lam FY2026 10-K：中國占營收 34%（FY2025 34%） | I86: 季別：FY26 Q1 43%、Q2 35%、Q3 34%、Q4 26%、FY27 Q1 35%（8-K）；低／高＝季別最小／最大。系統營收的中國比重未揭露（Assumed 同總營收）
A87: cutC | B87: 情境 C：出口管制加嚴，中國系統營收折損（CY2028 起） | C87: % | D87: 0 | E87: 0.2 | F87: 0.4 | G87: Assumed | H87: Analogy：2022-10 美國出口管制，公司估 2023 年營收影響 US$2.0–2.5B（techwireasia 轉述；當時中國約占營收 30%），約為中國營收的三到四成 | I87: 基準 20%＝類比區間的一半；高 40%＝類比上緣。CSBG（含 Reliant 成熟製程設備）未套用
A88: cut_sens | B88: Sens：中國系統營收折損（情境 A，CY2027 起） | C88: % | D88: 0.2 | E88: 0 | F88: 0.4 | G88: Assumed | H88: 同上：基準 0（現行管制已反映在 CY2026 錨點） | I88: 低欄＝20%、高欄＝40%（Sens 用）
A89: csq2_g | B89: FY2027 Q2 CSBG 相對 Q1 的變化（拆分指引營收用） | C89: % | D89: -0.05 | E89: 0 | F89: 0.1 | G89: Assumed | H89: 無：公司只給總營收指引 8.6 | I89: 結果檢查：CY2026 CSBG 年增＝33%（公司稱逾 30%，Recon）
A90: C. 客戶支援事業群 CSBG（服務、備件、升級、Reliant 成熟製程設備）
A91: g_cs27 | B91: CSBG CY2027 年增 | C91: % | D91: 0.1 | E91: 0.15 | F91: 0.2 | G91: Interested-party | H91: Lam FQ1-27 法說（2026-10-21）：CY2027 成長逾 15%（Motley Fool 逐字稿） | I91: 第二來源：未找到。低／高 Assumed
A92: g_cs_A | B92: CSBG CY2028–29 年增（A） | C92: % | D92: 0.08 | E92: 0.12 | F92: 0.16 | G92: Assumed | H92: 無：裝機量（公司稱逾 10 萬腔體）持續增加、記憶體稼動率隨情境；C 含 NAND 升級潮結束（公司稱 2027 年結束） | I92: —
A93: g_cs_B | B93: CSBG CY2028–29 年增（B） | C93: % | D93: 0.02 | E93: 0.06 | F93: 0.1 | G93: Assumed | H93: 無：裝機量（公司稱逾 10 萬腔體）持續增加、記憶體稼動率隨情境；C 含 NAND 升級潮結束（公司稱 2027 年結束） | I93: —
A94: g_cs_C | B94: CSBG CY2028–29 年增（C） | C94: % | D94: -0.07 | E94: -0.03 | F94: 0.01 | G94: Assumed | H94: 無：裝機量（公司稱逾 10 萬腔體）持續增加、記憶體稼動率隨情境；C 含 NAND 升級潮結束（公司稱 2027 年結束） | I94: —
A95: D. 毛利率與營業費用（兩點推導：FY2026 實績與 FY2027 上半〔Q1 實績＋Q2 指引〕年化；不寫死利益率）
A96: rev_h1 | B96: FY2027 上半營收年化（Q1 實績＋Q2 指引）× 2 | C96: US$B | E96: =2*(q1_rev+g_q2rev) -> 33.638836 | G96: Derived | H96: Q 頁 | I96: —
A97: gm_h1 | B97: FY2027 上半毛利率（Q1 實績＋Q2 指引 52.5%） | C97: % | E97: =(q1_gp+g_q2gm*g_q2rev)/(q1_rev+g_q2rev) -> 0.52402842 | G97: Derived | H97: Q 頁 | I97: —
A98: gm_b | B98: 毛利率斜率（每單位 ln 營收） | C98: pt | E98: =(gm_h1-a26_gp/a26_rev)/(LN(rev_h1)-LN(a26_rev)) -> 0.052248726 | G98: Derived | H98: 兩點：FY2026（營收 23.2、毛利率 50.5%）、FY2027 上半年化（33.6、52.4%） | I98: 對數形式：規模效益遞減；FY2025→FY2026 的斜率較大（7.8），未採
A99: gm_a | B99: 毛利率截距 | C99: % | E99: =a26_gp/a26_rev-gm_b*LN(a26_rev) -> 0.34033855 | G99: Derived | H99: 同上 | I99: 公司長期目標毛利率 mid-50s（Interested-party）；對照見 Recon
A100: opx_h1 | B100: FY2027 上半營業費用年化（Q1 實績＋Q2 指引〔毛利率 − 營益率〕× 營收）× 2 | C100: US$B | E100: =2*(q1_opx+(g_q2gm-g_q2om)*g_q2rev) -> 4.094252 | G100: Derived | H100: Q 頁 | I100: —
...

Sheet Q
A1: Q — 實績（十億美元；EPS 美元；GAAP）。會計年度 7–6 月：FY2026＝2025-07～2026-06。藍字＝輸入；黑字＝公式（Derived）。來源：Lam 8-K 新聞稿（Exhibit 99.1）、10-K、10-Q（SEC EDGAR 原文）
A2: FY2027 第一季（2026-07～09）已於 2026-10-21 公布並納入（G 欄）；H 欄為 12 月季指引（2026-10-21）。下一次財報：FY2027 第二季，預計 2027-01 下旬（公司尚未公告日期）
A3: 項目 | B3: FY2025 全年 | C3: FY26 Q1（7–9月） | D3: FY26 Q2（10–12月） | E3: FY26 Q3（1–3月） | F3: FY26 Q4（4–6月） | G3: FY27 Q1（7–9月） | H3: FY27 Q2（指引） | I3: FY2026 全年 | J3: 標記 | K3: 來源1（公司） | L3: 來源2／說明
A4: 系統營收（新的先進製程設備） | B4: 11.49128 | C4: 3.547565 | D4: 3.357493 | E4: 3.730582 | F4: 4.249848 | G4: 5.732907 | H4: =H6-H5 -> 6.113489 | I4: 14.885488 | J4: Verified | K4: 各季 8-K 新聞稿（2025-07-30、2025-10-22、2026-01-28、2026-04-22、2026-07-29、2026-10-21）：Systems revenue | L4: FY2026 10-K（2026-08-07）：FY2026 14,885.5、FY2025 11,491.3（百萬美元）；四季合計＝全年（見檢查列）
A5: 客戶支援與其他（CSBG：服務、備件、升級、Reliant 成熟製程設備） | B5: 6.944311 | C5: 1.776608 | D5: 1.987298 | E5: 2.110906 | F5: 2.47239 | G5: 2.486511 | H5: =G5*(1+csq2_g) -> 2.486511 | I5: 8.347202 | J5: Verified | K5: 各季 8-K 新聞稿（2025-07-30、2025-10-22、2026-01-28、2026-04-22、2026-07-29、2026-10-21）：Customer support-related revenue and other | L5: FY2026 10-K（2026-08-07）；Q2 指引欄＝Q1 × (1＋csq2_g)（Assumed）
A6: 營收 | B6: 18.435591 | C6: 5.324173 | D6: 5.344791 | E6: 5.841488 | F6: 6.722238 | G6: 8.219418 | H6: =g_q2rev -> 8.6 | I6: 23.23269 | J6: Verified | K6: 各季 8-K 新聞稿（2025-07-30、2025-10-22、2026-01-28、2026-04-22、2026-07-29、2026-10-21） | L6: FY2026 10-K（2026-08-07）：23,232.7、18,435.6
A7: 檢查：系統＋CSBG − 營收（應為 0） | B7: =B4+B5-B6 -> 0 | C7: =C4+C5-C6 -> 0 | D7: =D4+D5-D6 -> 0 | E7: =E4+E5-E6 -> 0 | F7: =F4+F5-F6 -> 0 | G7: =G4+G5-G6 -> 0 | H7: =H4+H5-H6 -> 0 | I7: =I4+I5-I6 -> 0 | J7: — | K7: — | L7: —
A8: 毛利 | B8: 8.979059 | C8: 2.684879 | D8: 2.651162 | E8: 2.910527 | F8: 3.47874 | G8: 4.298853 | H8: =H6*g_q2gm -> 4.515 | I8: 11.725308 | J8: Verified | K8: 各季 8-K 新聞稿（2025-07-30、2025-10-22、2026-01-28、2026-04-22、2026-07-29、2026-10-21） | L8: FY2026 10-K（2026-08-07）
A9: 毛利率 | B9: =B8/B6 -> 0.48705024 | C9: =C8/C6 -> 0.50428095 | D9: =D8/D6 -> 0.49602725 | E9: =E8/E6 -> 0.49825096 | F9: =F8/F6 -> 0.5174973 | G9: =G8/G6 -> 0.52301185 | H9: =H8/H6 -> 0.525 | I9: =I8/I6 -> 0.50469007 | J9: Derived | K9: — | L9: 公司：FY2026 50.5%、FY27 Q1 52.3%（GAAP）
A10: 研發費用 | B10: 2.096387 | C10: 0.576446 | D10: 0.573305 | E10: 0.5832 | F10: 0.642922 | G10: 0.666398 | I10: 2.375873 | J10: Verified | K10: 各季 8-K 新聞稿（2025-07-30、2025-10-22、2026-01-28、2026-04-22、2026-07-29、2026-10-21） | L10: FY2026 10-K（2026-08-07）
A11: 銷管費用 | B11: 0.981704 | C11: 0.279345 | D11: 0.267654 | E11: 0.280311 | F11: 0.32233 | G11: 0.348728 | I11: 1.14964 | J11: Verified | K11: 各季 8-K 新聞稿（2025-07-30、2025-10-22、2026-01-28、2026-04-22、2026-07-29、2026-10-21） | L11: FY2026 10-K（2026-08-07）
A12: 營業費用 | B12: =B10+B11 -> 3.078091 | C12: =C10+C11 -> 0.855791 | D12: =D10+D11 -> 0.840959 | E12: =E10+E11 -> 0.863511 | F12: =F10+F11 -> 0.965252 | G12: =G10+G11 -> 1.015126 | H12: =H8-H13 -> 1.032 | I12: =I10+I11 -> 3.525513 | J12: Derived | K12: — | L12: Q2 指引欄＝毛利 − 營業利益
A13: 營業利益 | B13: 5.900968 | C13: 1.829088 | D13: 1.810203 | E13: 2.047016 | F13: 2.513488 | G13: 3.283727 | H13: =H6*g_q2om -> 3.483 | I13: 8.199795 | J13: Verified | K13: 各季 8-K 新聞稿（2025-07-30、2025-10-22、2026-01-28、2026-04-22、2026-07-29、2026-10-21） | L13: FY2026 10-K（2026-08-07）
A14: 營業利益率 | B14: =B13/B6 -> 0.32008564 | C14: =C13/C6 -> 0.34354406 | D14: =D13/D6 -> 0.33868546 | E14: =E13/E6 -> 0.35042715 | F14: =F13/F6 -> 0.37390643 | G14: =G13/G6 -> 0.39950846 | H14: =H13/H6 -> 0.405 | I14: =I13/I6 -> 0.35294213 | J14: Derived | K14: — | L14: 公司：FY2026 35.3%、FY27 Q1 40.0%
A15: 業外收益淨額 | B15: 0.057161 | C15: 0.030074 | D15: 0.02641 | E15: -0.03546 | F15: 0.041654 | G15: 0.028493 | I15: 0.062678 | J15: Verified | K15: 各季 8-K 新聞稿（2025-07-30、2025-10-22、2026-01-28、2026-04-22、2026-07-29、2026-10-21） | L15: FY2026 10-K（2026-08-07）
A16: 所得稅 | B16: 0.599912 | C16: 0.290502 | D16: 0.242619 | E16: 0.186096 | F16: 0.27786 | G16: 0.559082 | I16: 0.997077 | J16: Verified | K16: 各季 8-K 新聞稿（2025-07-30、2025-10-22、2026-01-28、2026-04-22、2026-07-29、2026-10-21） | L16: FY2026 10-K（2026-08-07）
A17: 淨利 | B17: 5.358217 | C17: 1.56866 | D17: 1.593994 | E17: 1.82546 | F17: 2.277282 | G17: 2.753138 | H17: =H18*H19 -> 2.91949 | I17: 7.265396 | J17: Verified | K17: 各季 8-K 新聞稿（2025-07-30、2025-10-22、2026-01-28、2026-04-22、2026-07-29、2026-10-21） | L17: FY2026 10-K（2026-08-07）；Q2 指引欄＝指引 EPS × 指引股數（Derived）
A18: EPS（稀釋，美元） | B18: 4.15 | C18: 1.24 | D18: 1.26 | E18: 1.45 | F18: 1.81 | G18: 2.19 | H18: =g_q2eps -> 2.33 | I18: 5.76 | J18: Verified | K18: 各季 8-K 新聞稿（2025-07-30、2025-10-22、2026-01-28、2026-04-22、2026-07-29、2026-10-21） | L18: FY2026 10-K（2026-08-07）；非 GAAP FY2026 5.82（各季 1.26＋1.27＋1.47＋1.82）
A19: 稀釋股數（十億股） | B19: 1.290142 | C19: 1.269313 | D19: 1.261739 | E19: 1.257325 | F19: 1.256032 | G19: 1.255768 | H19: =sh_27 -> 1.253 | I19: 1.261102 | J19: Verified | K19: 各季 8-K 新聞稿（2025-07-30、2025-10-22、2026-01-28、2026-04-22、2026-07-29、2026-10-21） | L19: FY2026 10-K（2026-08-07）
A20: EPS（基本，美元；Val 的十年 P/E 用） | B20: 4.17 | C20: 1.24 | D20: 1.27 | E20: 1.46 | F20: 1.82 | G20: 2.2 | I20: 5.79 | J20: Verified | K20: 各季 8-K 新聞稿（2025-07-30、2025-10-22、2026-01-28、2026-04-22、2026-07-29、2026-10-21） | L20: FY2026 10-K（2026-08-07）
A21: 檢查：四季合計 − 全年（系統、CSBG、營收、毛利、營業利益、淨利依序在 B–G 欄） | B21: =SUM(C4:F4)-I4 -> 0 | C21: =SUM(C5:F5)-I5 -> 0 | D21: =SUM(C6:F6)-I6 -> 0 | E21: =SUM(C8:F8)-I8 -> 0 | F21: =SUM(C13:F13)-I13 -> 0 | G21: =SUM(C17:F17)-I17 -> 0 | J21: — | K21: — | L21: —
A23: 地區與客戶別（占比）
A24: 中國占營收 | B24: 0.34 | C24: 0.43 | D24: 0.35 | E24: 0.34 | F24: 0.26 | G24: 0.35 | I24: 0.34 | J24: Verified | K24: 各季 8-K 新聞稿（2025-07-30、2025-10-22、2026-01-28、2026-04-22、2026-07-29、2026-10-21）：Region revenue | L24: FY2026 10-K（2026-08-07）：FY2026、FY2025 皆 34%；管理層稱 12 月季中國占比將「明顯下降」（FQ1-27 法說）
A25: 代工（Foundry）占系統營收 | B25: 0.45 | C25: 0.6 | D25: 0.59 | E25: 0.54 | F25: 0.44 | G25: 0.46 | H25: =G25 -> 0.46 | I25: 0.54 | J25: Verified | K25: 各季 10-Q 與 FY2026 10-K：設備與升級營收的客戶別占比 | L25: 法說稱占「系統營收」，數字與 10-Q 相同；Q2 指引欄沿用 Q1（Assumed）
A26: 邏輯／IDM 占系統營收 | B26: 0.13 | C26: 0.06 | D26: 0.07 | E26: 0.07 | F26: 0.1 | G26: 0.08 | H26: =G26 -> 0.08 | I26: 0.07 | J26: Verified | K26: 同上 | L26: 同上
A27: DRAM 占系統營收 | C27: 0.16 | D27: 0.23 | E27: 0.27 | F27: 0.23 | G27: 0.2 | H27: =G27 -> 0.2 | J27: Interested-party | K27: 法說逐字稿摘要（TIKR FQ2-26；MarketBeat FQ4-26；Motley Fool FQ1-27）：Q1 16%、Q2 23%、Q3 27%、Q4 23%、FY27 Q1 20% | L27: 10-Q 只揭露記憶體合計；DRAM＋NAND＝記憶體（見檢查列）。FY2025 全年 DRAM／NAND 拆分：未找到
A28: NAND（非揮發性記憶體）占系統營收 | C28: 0.18 | D28: 0.11 | E28: 0.12 | F28: 0.23 | G28: 0.26 | H28: =G28 -> 0.26 | J28: Interested-party | K28: 同上：Q1 18%、Q2 11%、Q3 12%、Q4 23%、FY27 Q1 26% | L28: 同上
A29: 記憶體占系統營收（10-Q） | B29: 0.42 | C29: 0.34 | D29: 0.34 | E29: 0.39 | F29: 0.46 | G29: 0.46 | H29: =G29 -> 0.46 | I29: 0.39 | J29: Verified | K29: 10-Q／10-K：Memory | L29: —
A30: 檢查：代工＋邏輯＋記憶體 − 1；DRAM＋NAND − 記憶體（C–H 欄） | B30: =B25+B26+B29-1 -> 0 | C30: =C27+C28-C29 -> 0 | D30: =D27+D28-D29 -> 0 | E30: =E27+E28-E29 -> 0 | F30: =F27+F28-F29 -> 0 | G30: =G27+G28-G29 -> 0 | H30: =H27+H28-H29 -> 0 | I30: =I25+I26+I29-1 -> 0 | J30: — | K30: — | L30: B、I 欄為三項合計 − 1
A32: CY2025 對照用：FY2025 下半（2025-01～06）
A33: 項目 | B33: FY25 Q3（1–3月） | C33: FY25 Q4（4–6月） | J33: 標記 | K33: 來源1（公司） | L33: 來源2／說明
A34: 系統營收 | B34: 3.035276 | C34: 3.437625 | J34: Verified | K34: 8-K 2025-04-23、2025-07-30；FY26 Q3 與 Q1 新聞稿的前期比較欄 | L34: —
A35: CSBG | B35: 1.684899 | C35: 1.733768 | J35: Verified | K35: 8-K 2025-04-23、2025-07-30；FY26 Q3 與 Q1 新聞稿的前期比較欄 | L35: —
A36: 營收 | B36: 4.720175 | C36: 5.171393 | J36: Verified | K36: 8-K 2025-04-23、2025-07-30；FY26 Q3 與 Q1 新聞稿的前期比較欄 | L36: —

Sheet Units
A1: Units — 日曆年系統營收依客戶別的錨點：CY2026＝FY26 Q3＋Q4（實績）＋FY27 Q1（實績）＋FY27 Q2（指引）；各季系統營收 × 客戶別占比；再除以設備市場模型的 CY2026 分項，得到份額係數 k
A3: 項目 | B3: 單位 | C3: FY26 Q3 | D3: FY26 Q4 | E3: FY27 Q1 | F3: FY27 Q2（指引） | G3: CY2026 | H3: 說明
A4: 系統營收 | B4: US$B | C4: =Q!E4 -> 3.730582 | D4: =Q!F4 -> 4.249848 | E4: =Q!G4 -> 5.732907 | F4: =Q!H4 -> 6.113489 | G4: =SUM(C4:F4) -> 19.826826 | H4: Q2 指引欄＝指引營收 − CSBG 推估
A5: 代工與邏輯 | B5: US$B | C5: =Q!E4*(Q!E25+Q!E26) -> 2.275655 | D5: =Q!F4*(Q!F25+Q!F26) -> 2.2949179 | E5: =Q!G4*(Q!G25+Q!G26) -> 3.0957698 | F5: =Q!H4*(Q!H25+Q!H26) -> 3.3012841 | G5: =SUM(C5:F5) -> 10.967627
A6: DRAM | B6: US$B | C6: =Q!E4*Q!E27 -> 1.0072571 | D6: =Q!F4*Q!F27 -> 0.97746504 | E6: =Q!G4*Q!G27 -> 1.1465814 | F6: =Q!H4*Q!H27 -> 1.2226978 | G6: =SUM(C6:F6) -> 4.3540014
A7: NAND | B7: US$B | C7: =Q!E4*Q!E28 -> 0.44766984 | D7: =Q!F4*Q!F28 -> 0.97746504 | E7: =Q!G4*Q!G28 -> 1.4905558 | F7: =Q!H4*Q!H28 -> 1.5895071 | G7: =SUM(C7:F7) -> 4.5051978
A8: 檢查：三項 − 系統營收（應為 0） | B8: US$B | C8: =C5+C6+C7-C4 -> 0 | D8: =D5+D6+D7-D4 -> 0 | E8: =E5+E6+E7-E4 -> 0 | F8: =F5+F6+F7-F4 -> 0 | G8: =G5+G6+G7-G4 -> 0
A9: CSBG | B9: US$B | C9: =Q!E5 -> 2.110906 | D9: =Q!F5 -> 2.47239 | E9: =Q!G5 -> 2.486511 | F9: =Q!H5 -> 2.486511 | G9: =SUM(C9:F9) -> 9.556318
A11: CY2025 與 CY2026 年增（對照公司說法）
A12: CY2025 系統營收（FY25 Q3＋Q4＋FY26 Q1＋Q2） | B12: US$B | G12: =Q!B34+Q!C34+Q!C4+Q!D4 -> 13.377959
A13: CY2025 CSBG | B13: US$B | G13: =Q!B35+Q!C35+Q!C5+Q!D5 -> 7.182573
A14: CY2026 系統營收年增 | B14: % | G14: =G4/G12-1 -> 0.48205163 | H14: 公司：well over 40%（含 12 月季指引中點）
A15: CY2026 CSBG 年增 | B15: % | G15: =G9/G13-1 -> 0.33048672 | H15: 公司：逾 30%
A16: CY2026 下半系統營收（FY27 Q1＋Q2） | B16: US$B | G16: =E4+F4 -> 11.846396
A17: CY2026 下半 CSBG | B17: US$B | G17: =E9+F9 -> 4.973022
A19: 份額係數 k＝CY2026 Lam 系統營收（客戶別）÷ 設備市場模型 CY2026 分項（三情境 CY2026 相同）
A20: 分項 | B20: 單位 | C20: Lam CY2026 | D20: WFE 分項 CY2026 | E20: k | H20: 說明
A21: 代工與邏輯 | B21: US$B | C21: =cy26_fl -> 10.967627 | D21: =advA_26+oflA_26 -> 82.259373 | E21: =C21/D21 -> 0.13332981 | H21: Derived：只用公司實績與指引，未用共識；k 是「系統營收 ÷ 模型 WFE 分項」，不是嚴格市占（口徑：系統營收不含升級與 Reliant；WFE 模型為設備市場模型由下而上值）
A22: DRAM（含 HBM） | B22: US$B | C22: =cy26_dram -> 4.3540014 | D22: =dramA_26 -> 39.365947 | E22: =C22/D22 -> 0.11060324 | H22: Derived：只用公司實績與指引，未用共識；k 是「系統營收 ÷ 模型 WFE 分項」，不是嚴格市占（口徑：系統營收不含升級與 Reliant；WFE 模型為設備市場模型由下而上值）
A23: NAND | B23: US$B | C23: =cy26_nand -> 4.5051978 | D23: =nandA_26 -> 17.503905 | E23: =C23/D23 -> 0.25738244 | H23: Derived：只用公司實績與指引，未用共識；k 是「系統營收 ÷ 模型 WFE 分項」，不是嚴格市占（口徑：系統營收不含升級與 Reliant；WFE 模型為設備市場模型由下而上值）
A24: 合計：Lam 系統營收 ÷ 模型晶圓前段設備 | C24: =cy26_sys -> 19.826826 | D24: =wfeA_26 -> 156.15705 | E24: =C24/D24 -> 0.12696722
A25: 對照：Lam（系統＋CSBG）÷ 公司估 CY2026 WFE | C25: =cy26_sys+cy26_cs -> 29.383144 | D25: =co_wfe26 -> 155 | E25: =C25/D25 -> 0.18956867 | H25: CSBG 不屬 WFE，僅供量級參考

Sheet PL
A1: PL — Lam Research 損益（US$B；FY2025、FY2026 為實績，FY2027 起為模型；FY2027 上半錨定 Q1 實績＋Q2 指引）。三情境各一個完整推導區塊（見下方），本頁頂端為摘要
A3: 情境／項目 | B3: 單位 | C3: FY2025A | D3: FY2026A | E3: FY2027 | F3: FY2028 | G3: FY2029 | H3: 說明
A4: 情境 A
A5: 營收 | B5: US$B | C5: =C52 -> 18.435591 | D5: =D52 -> 23.23269 | E5: =E52 -> 34.602293 | F5: =F52 -> 37.751047 | G5: =G52 -> 41.470747
A6: 系統營收 | B6: US$B | C6: =C50 -> 11.49128 | D6: =D50 -> 14.885488 | E6: =E50 -> 24.134388 | F6: =F50 -> 26.101895 | G6: =G50 -> 28.423697
A7: CSBG | B7: US$B | C7: =C51 -> 6.944311 | D7: =D51 -> 8.347202 | E7: =E51 -> 10.467905 | F7: =F51 -> 11.649152 | G7: =G51 -> 13.04705
A8: 毛利率 | B8: % | C8: =C53 -> 0.48705024 | D8: =D53 -> 0.50469007 | E8: =E53 -> 0.52550385 | F8: =F53 -> 0.53005437 | G8: =G53 -> 0.53496444
A9: 營業利益 | B9: US$B | C9: =C56 -> 5.900968 | D9: =D56 -> 8.199795 | E9: =E56 -> 14.036729 | F9: =F56 -> 15.691106 | G9: =G56 -> 17.663077
A10: 營業利益率 | B10: % | C10: =C57 -> 0.32008564 | D10: =D57 -> 0.35294213 | E10: =E57 -> 0.40565894 | F10: =F57 -> 0.41564691 | G10: =G57 -> 0.42591653
A11: 淨利 | B11: US$B | C11: =C58 -> 5.358217 | D11: =D58 -> 7.265396 | E11: =E58 -> 11.804169 | F11: =F58 -> 13.185573 | G11: =G58 -> 14.832169
A12: EPS（稀釋） | B12: US$ | C12: =C60 -> 4.15 | D12: =D60 -> 5.76 | E12: =E60 -> 9.4207254 | F12: =F60 -> 10.683455 | G12: =G60 -> 12.200599
A14: 情境 B
A15: 營收 | B15: US$B | C15: =C76 -> 18.435591 | D15: =D76 -> 23.23269 | E15: =E76 -> 34.602293 | F15: =F76 -> 35.895442 | G15: =G76 -> 35.96021
A16: 系統營收 | B16: US$B | C16: =C74 -> 11.49128 | D16: =D74 -> 14.885488 | E16: =E74 -> 24.134388 | F16: =F74 -> 24.575983 | G16: =G74 -> 23.961584
A17: CSBG | B17: US$B | C17: =C75 -> 6.944311 | D17: =D75 -> 8.347202 | E17: =E75 -> 10.467905 | F17: =F75 -> 11.319459 | G17: =G75 -> 11.998626
A18: 毛利率 | B18: % | C18: =C77 -> 0.48705024 | D18: =D77 -> 0.50469007 | E18: =E77 -> 0.52550385 | F18: =F77 -> 0.52742088 | G18: =G77 -> 0.52751507
A19: 營業利益 | B19: US$B | C19: =C80 -> 5.900968 | D19: =D80 -> 8.199795 | E19: =E80 -> 14.036729 | F19: =F80 -> 14.714421 | G19: =G80 -> 14.748428
A20: 營業利益率 | B20: % | C20: =C81 -> 0.32008564 | D20: =D81 -> 0.35294213 | E20: =E81 -> 0.40565894 | F20: =F81 -> 0.40992449 | G20: =G81 -> 0.41013186
A21: 淨利 | B21: US$B | C21: =C82 -> 5.358217 | D21: =D82 -> 7.265396 | E21: =E82 -> 11.804169 | F21: =F82 -> 12.370041 | G21: =G82 -> 12.398437
A22: EPS（稀釋） | B22: US$ | C22: =C84 -> 4.15 | D22: =D84 -> 5.76 | E22: =E84 -> 9.4207254 | F22: =F84 -> 10.02268 | G22: =G84 -> 10.198667
A24: 情境 C
A25: 營收 | B25: US$B | C25: =C100 -> 18.435591 | D25: =D100 -> 23.23269 | E25: =E100 -> 34.602293 | F25: =F100 -> 32.274838 | G25: =G100 -> 28.824025
A26: 系統營收 | B26: US$B | C26: =C98 -> 11.49128 | D26: =D98 -> 14.885488 | E26: =E98 -> 24.134388 | F26: =F98 -> 21.449918 | G26: =G98 -> 18.323853
A27: CSBG | B27: US$B | C27: =C99 -> 6.944311 | D27: =D99 -> 8.347202 | E27: =E99 -> 10.467905 | F27: =F99 -> 10.824919 | G27: =G99 -> 10.500172
A28: 毛利率 | B28: % | C28: =C101 -> 0.48705024 | D28: =D101 -> 0.50469007 | E28: =E101 -> 0.52550385 | F28: =F101 -> 0.52186567 | G28: =G101 -> 0.51595745
A29: 營業利益 | B29: US$B | C29: =C104 -> 5.900968 | D29: =D104 -> 8.199795 | E29: =E104 -> 14.036729 | F29: =F104 -> 12.823426 | G29: =G104 -> 11.040868
A30: 營業利益率 | B30: % | C30: =C105 -> 0.32008564 | D30: =D105 -> 0.35294213 | E30: =E105 -> 0.40565894 | F30: =F105 -> 0.39731961 | G30: =G105 -> 0.38304393
A31: 淨利 | B31: US$B | C31: =C106 -> 5.358217 | D31: =D106 -> 7.265396 | E31: =E106 -> 11.804169 | F31: =F106 -> 10.791061 | G31: =G106 -> 9.3026246
A32: EPS（稀釋） | B32: US$ | C32: =C108 -> 4.15 | D32: =D108 -> 5.76 | E32: =E108 -> 9.4207254 | F32: =F108 -> 8.7433292 | G32: =G108 -> 7.6521234
A34: 核對：FY2025、FY2026 模型＝實績（營收、EPS 差的絕對值合計，應為 0）
C35: =ABS(C5-a25_rev)+ABS(C12-a25_eps)+ABS(D5-a26_rev)+ABS(D12-a26_eps)+ABS(C15-a25_rev)+ABS(C22-a25_eps)+ABS(D15-a26_rev)+ABS(D22-a26_eps)+ABS(C25-a25_rev)+ABS(C32-a25_eps)+ABS(D25-a26_rev)+ABS(D32-a26_eps) -> 0
A40: 情境 A：設備市場續增（markets/equipment A：2029 見頂）
A41: 項目 | B41: 單位 | C41: FY2025 | D41: CY2026／FY2026 | E41: CY2027／FY2027 | F41: CY2028／FY2028 | G41: CY2029／FY2029 | H41: 說明
A42: A. 日曆年（D＝CY2026 … G＝CY2029）
A43: 系統營收：代工與邏輯 | B43: US$B | D43: =cy26_fl -> 10.967627 | E43: =k_fl*(advA_27+oflA_27)*(1+drift)^1 -> 12.701761 | F43: =k_fl*(advA_28+oflA_28)*(1+drift)^2 -> 14.301566 | G43: =k_fl*(advA_29+oflA_29)*(1+drift)^3 -> 15.257963 | H43: CY2026＝錨點（實績＋指引）；之後＝k × 設備市場模型分項 × (1＋份額漂移)^年
A44: 系統營收：DRAM | B44: US$B | D44: =cy26_dram -> 4.3540014 | E44: =k_dram*dramA_27*(1+drift)^1 -> 5.8905886 | F44: =k_dram*dramA_28*(1+drift)^2 -> 6.5876287 | G44: =k_dram*dramA_29*(1+drift)^3 -> 6.8387415 | H44: CY2026＝錨點（實績＋指引）；之後＝k × 設備市場模型分項 × (1＋份額漂移)^年
A45: 系統營收：NAND | B45: US$B | D45: =cy26_nand -> 4.5051978 | E45: =k_nand*nandA_27*(1+drift)^1 -> 5.9836339 | F45: =k_nand*nandA_28*(1+drift)^2 -> 6.7386124 | G45: =k_nand*nandA_29*(1+drift)^3 -> 7.1228821 | H45: CY2026＝錨點（實績＋指引）；之後＝k × 設備市場模型分項 × (1＋份額漂移)^年
A46: 出口管制：中國系統營收折損 | B46: US$B | E46: =-cn_sh*0*(E43+E44+E45) -> 0 | F46: =-cn_sh*0*(F43+F44+F45) -> 0 | G46: =-cn_sh*0*(G43+G44+G45) -> 0 | H46: −中國占比 × 折損比例 × 系統營收；情境 C 自 CY2028 起 cutC，其餘為 0（Sens 另設）
A47: 系統營收 CY | B47: US$B | D47: =SUM(D43:D46) -> 19.826826 | E47: =SUM(E43:E46) -> 24.575983 | F47: =SUM(F43:F46) -> 27.627807 | G47: =SUM(G43:G46) -> 29.219587
A48: CSBG CY | B48: US$B | D48: =cy26_cs -> 9.556318 | E48: =D48*(1+g_cs27) -> 10.989766 | F48: =E48*(1+g_cs_A) -> 12.308538 | G48: =F48*(1+g_cs_A) -> 13.785562 | H48: CY2026＝錨點；CY2027 公司稱逾 15%；之後依情境
A49: B. 會計年度（C＝FY2025 … G＝FY2029；FY(t)＝CY(t−1) 下半＋CY(t) 上半）
A50: 系統營收 | B50: US$B | C50: =a25_sys -> 11.49128 | D50: =a26_sys -> 14.885488 | E50: =h2s26+h1s*E47 -> 24.134388 | F50: =(1-h1s)*E47+h1s*F47 -> 26.101895 | G50: =(1-h1s)*F47+h1s*G47 -> 28.423697 | H50: FY2027＝CY2026 下半（FY27 Q1 實績＋Q2 指引）＋ h1 × CY2027
A51: CSBG | B51: US$B | C51: =a25_cs -> 6.944311 | D51: =a26_cs -> 8.347202 | E51: =h2c26+h1s*E48 -> 10.467905 | F51: =(1-h1s)*E48+h1s*F48 -> 11.649152 | G51: =(1-h1s)*F48+h1s*G48 -> 13.04705
A52: 營收 | B52: US$B | C52: =C50+C51 -> 18.435591 | D52: =D50+D51 -> 23.23269 | E52: =E50+E51 -> 34.602293 | F52: =F50+F51 -> 37.751047 | G52: =G50+G51 -> 41.470747
A53: 毛利率 | B53: % | C53: =a25_gp/a25_rev -> 0.48705024 | D53: =a26_gp/a26_rev -> 0.50469007 | E53: =gm_a+gm_b*LN(E52) -> 0.52550385 | F53: =gm_a+gm_b*LN(F52) -> 0.53005437 | G53: =gm_a+gm_b*LN(G52) -> 0.53496444 | H53: 截距＋斜率 × ln 營收（兩點推導）
A54: 毛利 | B54: US$B | C54: =C52*C53 -> 8.979059 | D54: =D52*D53 -> 11.725308 | E54: =E52*E53 -> 18.183638 | F54: =F52*F53 -> 20.010107 | G54: =G52*G53 -> 22.185375
A55: 營業費用 | B55: US$B | C55: =a25_opx -> 3.078091 | D55: =a26_opx -> 3.525513 | E55: =opex_fix+opex_var*E52 -> 4.1469089 | F55: =opex_fix+opex_var*F52 -> 4.3190014 | G55: =opex_fix+opex_var*G52 -> 4.5222984 | H55: 固定＋變動 × 營收
A56: 營業利益 | B56: US$B | C56: =C54-C55 -> 5.900968 | D56: =D54-D55 -> 8.199795 | E56: =E54-E55 -> 14.036729 | F56: =F54-F55 -> 15.691106 | G56: =G54-G55 -> 17.663077
A57: 營業利益率 | B57: % | C57: =C56/C52 -> 0.32008564 | D57: =D56/D52 -> 0.35294213 | E57: =E56/E52 -> 0.40565894 | F57: =F56/F52 -> 0.41564691 | G57: =G56/G52 -> 0.42591653
A58: 淨利 | B58: US$B | C58: =a25_ni -> 5.358217 | D58: =a26_ni -> 7.265396 | E58: =(E56+oth_inc)*(1-tax) -> 11.804169 | F58: =(F56+oth_inc)*(1-tax) -> 13.185573 | G58: =(G56+oth_inc)*(1-tax) -> 14.832169
A59: 稀釋股數 | B59: 十億股 | C59: =a25_dsh -> 1.290142 | D59: =a26_dsh -> 1.261102 | E59: =sh_27 -> 1.253 | F59: =E59*(1-bb) -> 1.234205 | G59: =F59*(1-bb) -> 1.2156919
A60: EPS（稀釋） | B60: US$ | C60: =a25_eps -> 4.15 | D60: =a26_eps -> 5.76 | E60: =E58/E59 -> 9.4207254 | F60: =F58/F59 -> 10.683455 | G60: =G58/G59 -> 12.200599
A61: 系統營收占營收 | B61: % | C61: =C50/C52 -> 0.6233204 | D61: =D50/D52 -> 0.64071306 | E61: =E50/E52 -> 0.69747944 | F61: =F50/F52 -> 0.69142176 | G61: =G50/G52 -> 0.68539149
A64: 情境 B：設備市場 2028 持平、2029 −5%（markets/equipment B）
A65: 項目 | B65: 單位 | C65: FY2025 | D65: CY2026／FY2026 | E65: CY2027／FY2027 | F65: CY2028／FY2028 | G65: CY2029／FY2029 | H65: 說明
A66: A. 日曆年（D＝CY2026 … G＝CY2029）
A67: 系統營收：代工與邏輯 | B67: US$B | D67: =cy26_fl -> 10.967627 | E67: =k_fl*(advB_27+oflB_27)*(1+drift)^1 -> 12.701761 | F67: =k_fl*(advB_28+oflB_28)*(1+drift)^2 -> 12.701761 | G67: =k_fl*(advB_29+oflB_29)*(1+drift)^3 -> 12.066673 | H67: CY2026＝錨點（實績＋指引）；之後＝k × 設備市場模型分項 × (1＋份額漂移)^年
A68: 系統營收：DRAM | B68: US$B | D68: =cy26_dram -> 4.3540014 | E68: =k_dram*dramB_27*(1+drift)^1 -> 5.8905886 | F68: =k_dram*dramB_28*(1+drift)^2 -> 5.8905886 | G68: =k_dram*dramB_29*(1+drift)^3 -> 5.5960591 | H68: CY2026＝錨點（實績＋指引）；之後＝k × 設備市場模型分項 × (1＋份額漂移)^年
A69: 系統營收：NAND | B69: US$B | D69: =cy26_nand -> 4.5051978 | E69: =k_nand*nandB_27*(1+drift)^1 -> 5.9836339 | F69: =k_nand*nandB_28*(1+drift)^2 -> 5.9836339 | G69: =k_nand*nandB_29*(1+drift)^3 -> 5.6844522 | H69: CY2026＝錨點（實績＋指引）；之後＝k × 設備市場模型分項 × (1＋份額漂移)^年
A70: 出口管制：中國系統營收折損 | B70: US$B | E70: =-cn_sh*0*(E67+E68+E69) -> 0 | F70: =-cn_sh*0*(F67+F68+F69) -> 0 | G70: =-cn_sh*0*(G67+G68+G69) -> 0 | H70: −中國占比 × 折損比例 × 系統營收；情境 C 自 CY2028 起 cutC，其餘為 0（Sens 另設）
A71: 系統營收 CY | B71: US$B | D71: =SUM(D67:D70) -> 19.826826 | E71: =SUM(E67:E70) -> 24.575983 | F71: =SUM(F67:F70) -> 24.575983 | G71: =SUM(G67:G70) -> 23.347184
A72: CSBG CY | B72: US$B | D72: =cy26_cs -> 9.556318 | E72: =D72*(1+g_cs27) -> 10.989766 | F72: =E72*(1+g_cs_B) -> 11.649152 | G72: =F72*(1+g_cs_B) -> 12.348101 | H72: CY2026＝錨點；CY2027 公司稱逾 15%；之後依情境
A73: B. 會計年度（C＝FY2025 … G＝FY2029；FY(t)＝CY(t−1) 下半＋CY(t) 上半）
A74: 系統營收 | B74: US$B | C74: =a25_sys -> 11.49128 | D74: =a26_sys -> 14.885488 | E74: =h2s26+h1s*E71 -> 24.134388 | F74: =(1-h1s)*E71+h1s*F71 -> 24.575983 | G74: =(1-h1s)*F71+h1s*G71 -> 23.961584 | H74: FY2027＝CY2026 下半（FY27 Q1 實績＋Q2 指引）＋ h1 × CY2027
A75: CSBG | B75: US$B | C75: =a25_cs -> 6.944311 | D75: =a26_cs -> 8.347202 | E75: =h2c26+h1s*E72 -> 10.467905 | F75: =(1-h1s)*E72+h1s*F72 -> 11.319459 | G75: =(1-h1s)*F72+h1s*G72 -> 11.998626
A76: 營收 | B76: US$B | C76: =C74+C75 -> 18.435591 | D76: =D74+D75 -> 23.23269 | E76: =E74+E75 -> 34.602293 | F76: =F74+F75 -> 35.895442 | G76: =G74+G75 -> 35.96021
A77: 毛利率 | B77: % | C77: =a25_gp/a25_rev -> 0.48705024 | D77: =a26_gp/a26_rev -> 0.50469007 | E77: =gm_a+gm_b*LN(E76) -> 0.52550385 | F77: =gm_a+gm_b*LN(F76) -> 0.52742088 | G77: =gm_a+gm_b*LN(G76) -> 0.52751507 | H77: 截距＋斜率 × ln 營收（兩點推導）
A78: 毛利 | B78: US$B | C78: =C76*C77 -> 8.979059 | D78: =D76*D77 -> 11.725308 | E78: =E76*E77 -> 18.183638 | F78: =F76*F77 -> 18.932006 | G78: =G76*G77 -> 18.969553
A79: 營業費用 | B79: US$B | C79: =a25_opx -> 3.078091 | D79: =a26_opx -> 3.525513 | E79: =opex_fix+opex_var*E76 -> 4.1469089 | F79: =opex_fix+opex_var*F76 -> 4.2175849 | G79: =opex_fix+opex_var*G76 -> 4.2211247 | H79: 固定＋變動 × 營收
A80: 營業利益 | B80: US$B | C80: =C78-C79 -> 5.900968 | D80: =D78-D79 -> 8.199795 | E80: =E78-E79 -> 14.036729 | F80: =F78-F79 -> 14.714421 | G80: =G78-G79 -> 14.748428
A81: 營業利益率 | B81: % | C81: =C80/C76 -> 0.32008564 | D81: =D80/D76 -> 0.35294213 | E81: =E80/E76 -> 0.40565894 | F81: =F80/F76 -> 0.40992449 | G81: =G80/G76 -> 0.41013186
A82: 淨利 | B82: US$B | C82: =a25_ni -> 5.358217 | D82: =a26_ni -> 7.265396 | E82: =(E80+oth_inc)*(1-tax) -> 11.804169 | F82: =(F80+oth_inc)*(1-tax) -> 12.370041 | G82: =(G80+oth_inc)*(1-tax) -> 12.398437
A83: 稀釋股數 | B83: 十億股 | C83: =a25_dsh -> 1.290142 | D83: =a26_dsh -> 1.261102 | E83: =sh_27 -> 1.253 | F83: =E83*(1-bb) -> 1.234205 | G83: =F83*(1-bb) -> 1.2156919
A84: EPS（稀釋） | B84: US$ | C84: =a25_eps -> 4.15 | D84: =a26_eps -> 5.76 | E84: =E82/E83 -> 9.4207254 | F84: =F82/F83 -> 10.02268 | G84: =G82/G83 -> 10.198667
A85: 系統營收占營收 | B85: % | C85: =C74/C76 -> 0.6233204 | D85: =D74/D76 -> 0.64071306 | E85: =E74/E76 -> 0.69747944 | F85: =F74/F76 -> 0.68465471 | G85: =G74/G76 -> 0.66633604
A88: 情境 C：設備市場 2028 −20%（markets/equipment C）；另加出口管制中國系統營收 −20%（CY2028 起）
A89: 項目 | B89: 單位 | C89: FY2025 | D89: CY2026／FY2026 | E89: CY2027／FY2027 | F89: CY2028／FY2028 | G89: CY2029／FY2029 | H89: 說明
A90: A. 日曆年（D＝CY2026 … G＝CY2029）
A91: 系統營收：代工與邏輯 | B91: US$B | D91: =cy26_fl -> 10.967627 | E91: =k_fl*(advC_27+oflC_27)*(1+drift)^1 -> 12.701761 | F91: =k_fl*(advC_28+oflC_28)*(1+drift)^2 -> 10.161409 | G91: =k_fl*(advC_29+oflC_29)*(1+drift)^3 -> 10.161409 | H91: CY2026＝錨點（實績＋指引）；之後＝k × 設備市場模型分項 × (1＋份額漂移)^年
A92: 系統營收：DRAM | B92: US$B | D92: =cy26_dram -> 4.3540014 | E92: =k_dram*dramC_27*(1+drift)^1 -> 5.8905886 | F92: =k_dram*dramC_28*(1+drift)^2 -> 4.7124709 | G92: =k_dram*dramC_29*(1+drift)^3 -> 4.7124709 | H92: CY2026＝錨點（實績＋指引）；之後＝k × 設備市場模型分項 × (1＋份額漂移)^年
A93: 系統營收：NAND | B93: US$B | D93: =cy26_nand -> 4.5051978 | E93: =k_nand*nandC_27*(1+drift)^1 -> 5.9836339 | F93: =k_nand*nandC_28*(1+drift)^2 -> 4.7869071 | G93: =k_nand*nandC_29*(1+drift)^3 -> 4.7869071 | H93: CY2026＝錨點（實績＋指引）；之後＝k × 設備市場模型分項 × (1＋份額漂移)^年
A94: 出口管制：中國系統營收折損 | B94: US$B | E94: =-cn_sh*0*(E91+E92+E93) -> 0 | F94: =-cn_sh*cutC*(F91+F92+F93) -> -1.3369335 | G94: =-cn_sh*cutC*(G91+G92+G93) -> -1.3369335 | H94: −中國占比 × 折損比例 × 系統營收；情境 C 自 CY2028 起 cutC，其餘為 0（Sens 另設）
A95: 系統營收 CY | B95: US$B | D95: =SUM(D91:D94) -> 19.826826 | E95: =SUM(E91:E94) -> 24.575983 | F95: =SUM(F91:F94) -> 18.323853 | G95: =SUM(G91:G94) -> 18.323853
A96: CSBG CY | B96: US$B | D96: =cy26_cs -> 9.556318 | E96: =D96*(1+g_cs27) -> 10.989766 | F96: =E96*(1+g_cs_C) -> 10.660073 | G96: =F96*(1+g_cs_C) -> 10.340271 | H96: CY2026＝錨點；CY2027 公司稱逾 15%；之後依情境
A97: B. 會計年度（C＝FY2025 … G＝FY2029；FY(t)＝CY(t−1) 下半＋CY(t) 上半）
A98: 系統營收 | B98: US$B | C98: =a25_sys -> 11.49128 | D98: =a26_sys -> 14.885488 | E98: =h2s26+h1s*E95 -> 24.134388 | F98: =(1-h1s)*E95+h1s*F95 -> 21.449918 | G98: =(1-h1s)*F95+h1s*G95 -> 18.323853 | H98: FY2027＝CY2026 下半（FY27 Q1 實績＋Q2 指引）＋ h1 × CY2027
A99: CSBG | B99: US$B | C99: =a25_cs -> 6.944311 | D99: =a26_cs -> 8.347202 | E99: =h2c26+h1s*E96 -> 10.467905 | F99: =(1-h1s)*E96+h1s*F96 -> 10.824919 | G99: =(1-h1s)*F96+h1s*G96 -> 10.500172
A100: 營收 | B100: US$B | C100: =C98+C99 -> 18.435591 | D100: =D98+D99 -> 23.23269 | E100: =E98+E99 -> 34.602293 | F100: =F98+F99 -> 32.274838 | G100: =G98+G99 -> 28.824025
A101: 毛利率 | B101: % | C101: =a25_gp/a25_rev -> 0.48705024 | D101: =a26_gp/a26_rev -> 0.50469007 | E101: =gm_a+gm_b*LN(E100) -> 0.52550385 | F101: =gm_a+gm_b*LN(F100) -> 0.52186567 | G101: =gm_a+gm_b*LN(G100) -> 0.51595745 | H101: 截距＋斜率 × ln 營收（兩點推導）
A102: 毛利 | B102: US$B | C102: =C100*C101 -> 8.979059 | D102: =D100*D101 -> 11.725308 | E102: =E100*E101 -> 18.183638 | F102: =F100*F101 -> 16.84313 | G102: =G100*G101 -> 14.87197
A103: 營業費用 | B103: US$B | C103: =a25_opx -> 3.078091 | D103: =a26_opx -> 3.525513 | E103: =opex_fix+opex_var*E100 -> 4.1469089 | F103: =opex_fix+opex_var*F100 -> 4.0197038 | G103: =opex_fix+opex_var*G100 -> 3.8311026 | H103: 固定＋變動 × 營收
A104: 營業利益 | B104: US$B | C104: =C102-C103 -> 5.900968 | D104: =D102-D103 -> 8.199795 | E104: =E102-E103 -> 14.036729 | F104: =F102-F103 -> 12.823426 | G104: =G102-G103 -> 11.040868
A105: 營業利益率 | B105: % | C105: =C104/C100 -> 0.32008564 | D105: =D104/D100 -> 0.35294213 | E105: =E104/E100 -> 0.40565894 | F105: =F104/F100 -> 0.39731961 | G105: =G104/G100 -> 0.38304393
A106: 淨利 | B106: US$B | C106: =a25_ni -> 5.358217 | D106: =a26_ni -> 7.265396 | E106: =(E104+oth_inc)*(1-tax) -> 11.804169 | F106: =(F104+oth_inc)*(1-tax) -> 10.791061 | G106: =(G104+oth_inc)*(1-tax) -> 9.3026246
A107: 稀釋股數 | B107: 十億股 | C107: =a25_dsh -> 1.290142 | D107: =a26_dsh -> 1.261102 | E107: =sh_27 -> 1.253 | F107: =E107*(1-bb) -> 1.234205 | G107: =F107*(1-bb) -> 1.2156919
A108: EPS（稀釋） | B108: US$ | C108: =a25_eps -> 4.15 | D108: =a26_eps -> 5.76 | E108: =E106/E107 -> 9.4207254 | F108: =F106/F107 -> 8.7433292 | G108: =G106/G107 -> 7.6521234
A109: 系統營收占營收 | B109: % | C109: =C98/C100 -> 0.6233204 | D109: =D98/D100 -> 0.64071306 | E109: =E98/E100 -> 0.69747944 | F109: =F98/F100 -> 0.6646019 | G109: =G98/G100 -> 0.63571459
A112: 延伸到 FY2032（v2 新增）：FY2025–FY2029 引用本頁頂端摘要；灰底 FY2030–FY2032 為收斂法，非驅動因子推導
A113: 收斂法：營收年增由 FY2029 年增線性收斂到 FY2032 的長期成長（A＝tp_g＋2pt、B＝tp_g、C＝tp_g−2pt）；淨利率由 FY2029 線性收斂（A＝FY2029、B＝FY2029 與十年平均的中點、C＝十年平均）；股數維持 FY2029（EPS 與淨利同比例）
A114: 情境（延伸） | B114: 單位 | C114: FY2025A | D114: FY2026A | E114: FY2027 | F114: FY2028 | G114: FY2029 | H114: FY2030（收斂） | I114: FY2031（收斂） | J114: FY2032（收斂） | K114: 說明
...

Sheet Val
A1: Val — P/E 估值。跨公司規則：合理倍數＝10 年（2016–2025 年底）P/E 的分位，依循環位置：見頂年 25 分位、中段中位數、谷底 75 分位。循環位置依設備股共用規則（見第 4 節）
A2: P/E 定義（自算）：日曆年底收盤價 ÷ 「當期會計年度」公司公布的基本 EPS（年底所在會計年度，例如 2025-12 對 FY2026＝2025-07～2026-06）。價格與 EPS 皆為 2024-10 的 10 比 1 分割調整後
A3: 目標價（DCF 與 Comparable 加權）：見本頁第 94 列起「0. 目標價」（估值 v2 新增，放在既有內容之後以免位移既有列）；原「0. 目標價與上檔空間」改名為「舊法：規則值情境加權（參考）」
A4: 舊法：規則值情境加權（參考）
A5: 項目 | B5: 數值 | C5: 說明
A6: 規則值情境加權價（12 個月；參考） | B6: =tp_wA*B8+tp_wB*B9+tp_wC*B10 -> 154.25592 | C6: ＝權重 A × 情境 A 隱含價＋權重 B × 情境 B 隱含價＋權重 C × 情境 C 隱含價
A7: 相對現價（規則值情境加權價 ÷ 現價 − 1） | B7: =B6/px-1 -> -0.32961356 | C7: 現價：stockanalysis 2026-10-23 收盤
A8: 情境 A 隱含價（樂觀） | B8: =F61 -> 163.31512 | C8: ＝第 5 節規則值（FY2027 EPS × 依循環位置的倍數）
A9: 情境 B 隱含價（基準） | B9: =F68 -> 163.31512 | C9: 同上
A10: 情境 C 隱含價（下檔） | B10: =F75 -> 118.01913 | C10: 同上
A11: 情境權重 A／B／C | B11: =tp_wA -> 0.3 | C11: =tp_wB -> 0.5 | D11: =tp_wC -> 0.2 | E11: In 頁 tp_wA／tp_wB／tp_wC（Assumed；Andy 可改）
A12: 規則值方法 | B12: P/E：模型 FY2027 稀釋 EPS（A／B／C 各自）× 依設備股共用循環規則的 10 年（2016–2025 年底）當期 P/E 分位（A、B 中段＝中位數，C 見頂＝25 分位）；樣本含 2018、2022 記憶體下行年的低倍數與 2023、2025 年底的 AI 高倍數，未調整
A13: 檢查：權重合計 − 1（應為 0） | B13: =tp_wA+tp_wB+tp_wC-1 -> 0
A16: 1. 公司公布 EPS（會計年度，美元，分割調整後）— 兩個來源
A17: 會計年度（6 月結束） | B17: 來源1：10-K 基本 EPS（分割調整） | C17: 來源2：10-K 稀釋 EPS（分割調整） | D17: 基本 ÷ 稀釋 − 1 | E17: 原始基本 EPS（分割前） | F17: 標記 | G17: 說明
A18: FY2016 | B18: =E18/10 -> 0.575 | C18: 0.522 | D18: =B18/C18-1 -> 0.10153257 | E18: 5.75 | F18: Verified | G18: SEC XBRL（各年 10-K）：分割前基本 EPS ÷ 10；稀釋同理
A19: FY2017 | B19: =E19/10 -> 1.047 | C19: 0.924 | D19: =B19/C19-1 -> 0.13311688 | E19: 10.47 | F19: Verified | G19: SEC XBRL（各年 10-K）：分割前基本 EPS ÷ 10；稀釋同理
A20: FY2018 | B20: =E20/10 -> 1.473 | C20: 1.317 | D20: =B20/C20-1 -> 0.11845103 | E20: 14.73 | F20: Verified | G20: SEC XBRL（各年 10-K）：分割前基本 EPS ÷ 10；稀釋同理
A21: FY2019 | B21: =E21/10 -> 1.437 | C21: 1.37 | D21: =B21/C21-1 -> 0.048905109 | E21: 14.37 | F21: Verified | G21: SEC XBRL（各年 10-K）：分割前基本 EPS ÷ 10；稀釋同理
A22: FY2020 | B22: =E22/10 -> 1.555 | C22: 1.51 | D22: =B22/C22-1 -> 0.029801325 | E22: 15.55 | F22: Verified | G22: SEC XBRL（各年 10-K）：分割前基本 EPS ÷ 10；稀釋同理
A23: FY2021 | B23: =E23/10 -> 2.722 | C23: 2.69 | D23: =B23/C23-1 -> 0.011895911 | E23: 27.22 | F23: Verified | G23: SEC XBRL（各年 10-K）：分割前基本 EPS ÷ 10；稀釋同理
A24: FY2022 | B24: =E24/10 -> 3.292 | C24: 3.275 | D24: =B24/C24-1 -> 0.0051908397 | E24: 32.92 | F24: Verified | G24: SEC XBRL（各年 10-K）：分割前基本 EPS ÷ 10；稀釋同理
A25: FY2023 | B25: 3.33 | C25: 3.32 | D25: =B25/C25-1 -> 0.0030120482 | E25: =B25*10 -> 33.3 | F25: Verified | G25: FY2025／FY2026 10-K（分割後重編）；E 欄為 ×10 還原（Derived）
A26: FY2024 | B26: 2.91 | C26: 2.9 | D26: =B26/C26-1 -> 0.0034482759 | E26: =B26*10 -> 29.1 | F26: Verified | G26: FY2025／FY2026 10-K（分割後重編）；E 欄為 ×10 還原（Derived）
A27: FY2025 | B27: 4.17 | C27: 4.15 | D27: =B27/C27-1 -> 0.0048192771 | E27: =B27*10 -> 41.7 | F27: Verified | G27: FY2025／FY2026 10-K（分割後重編）；E 欄為 ×10 還原（Derived）
A28: FY2026 | B28: 5.79 | C28: 5.76 | D28: =B28/C28-1 -> 0.0052083333 | E28: =B28*10 -> 57.9 | F28: Verified | G28: FY2025／FY2026 10-K（分割後重編）；E 欄為 ×10 還原（Derived）
A29: 全部年度統一用基本 EPS（Basic，比照樣板）。來源2 為同一份 10-K 的稀釋 EPS（非獨立來源，只作口徑對照）；獨立的第二個 EPS 來源：未找到（macrotrends、stockanalysis 頁面未取得年度表）
A30: 2. 10 年 P/E（年底）
A31: 年底 | B31: 收盤價 US$（分割調整，未還原股利） | C31: 當期 FY EPS（基本） | D31: 前期 FY EPS（基本） | E31: P/E 當期（自算） | F31: P/E 前期（自算） | G31: companiesmarketcap P/E | H31: 自算當期 − cmc | I31: macrotrends 年底價（還原股利） | J31: 標記 | K31: 來源／說明
A32: 2016-12 | B32: =105.73/10 -> 10.573 | C32: =B19 -> 1.047 | D32: =B18 -> 0.575 | E32: =B32/C32 -> 10.098376 | F32: =B32/D32 -> 18.387826 | G32: 15.1 | H32: =E32-G32 -> -5.0016237 | I32: 9.3223 | J32: Verified／Derived | K32: 收盤價：digrin「Real price」（分割前原價 ÷ 10）
A33: 2017-12 | B33: =184.07/10 -> 18.407 | C33: =B20 -> 1.473 | D33: =B19 -> 1.047 | E33: =B33/C33 -> 12.496266 | F33: =B33/D33 -> 17.580707 | G33: 15.9 | H33: =E33-G33 -> -3.4037339 | I33: 16.4265 | J33: Verified／Derived | K33: 收盤價：digrin「Real price」（分割前原價 ÷ 10）
A34: 2018-12 | B34: =136.17/10 -> 13.617 | C34: =B21 -> 1.437 | D34: =B20 -> 1.473 | E34: =B34/C34 -> 9.4759916 | F34: =B34/D34 -> 9.2443992 | G34: 6.83 | H34: =E34-G34 -> 2.6459916 | I34: 12.4183 | J34: Verified／Derived | K34: 收盤價：digrin「Real price」（分割前原價 ÷ 10）
A35: 2019-12 | B35: =292.4/10 -> 29.24 | C35: =B22 -> 1.555 | D35: =B21 -> 1.437 | E35: =B35/C35 -> 18.803859 | F35: =B35/D35 -> 20.347947 | G35: 19.4 | H35: =E35-G35 -> -0.59614148 | I35: 27.2375 | J35: Verified／Derived | K35: 收盤價：digrin「Real price」（分割前原價 ÷ 10）
A36: 2020-12 | B36: =472.27/10 -> 47.227 | C36: =B23 -> 2.722 | D36: =B22 -> 1.555 | E36: =B36/C36 -> 17.35011 | F36: =B36/D36 -> 30.371061 | G36: 21.9 | H36: =E36-G36 -> -4.5498898 | I36: 44.7187 | J36: Verified／Derived | K36: 收盤價：digrin「Real price」（分割前原價 ÷ 10）
A37: 2021-12 | B37: =719.15/10 -> 71.915 | C37: =B24 -> 3.292 | D37: =B23 -> 2.722 | E37: =B37/C37 -> 21.845383 | F37: =B37/D37 -> 26.419912 | G37: 21.3 | H37: =E37-G37 -> 0.54538275 | I37: 68.7159 | J37: Verified／Derived | K37: 收盤價：digrin「Real price」（分割前原價 ÷ 10）
A38: 2022-12 | B38: =420.3/10 -> 42.03 | C38: =B25 -> 3.33 | D38: =B24 -> 3.292 | E38: =B38/C38 -> 12.621622 | F38: =B38/D38 -> 12.767315 | G38: 11 | H38: =E38-G38 -> 1.6216216 | I38: 40.7327 | J38: Verified／Derived | K38: 收盤價：digrin「Real price」（分割前原價 ÷ 10）
A39: 2023-12 | B39: =783.26/10 -> 78.326 | C39: =B26 -> 2.91 | D39: =B25 -> 3.33 | E39: =B39/C39 -> 26.916151 | F39: =B39/D39 -> 23.521321 | G39: 29.7 | H39: =E39-G39 -> -2.7838488 | I39: 76.8336 | J39: Verified／Derived | K39: 收盤價：digrin「Real price」（分割前原價 ÷ 10）
A40: 2024-12 | B40: 72.23 | C40: =B27 -> 4.17 | D40: =B26 -> 2.91 | E40: =B40/C40 -> 17.321343 | F40: =B40/D40 -> 24.821306 | G40: 21.7 | H40: =E40-G40 -> -4.3786571 | I40: 71.5745 | J40: Verified／Derived | K40: 收盤價：digrin（分割後）
A41: 2025-12 | B41: 171.18 | C41: =B28 -> 5.79 | D41: =B27 -> 4.17 | E41: =B41/C41 -> 29.564767 | F41: =B41/D41 -> 41.05036 | G41: 34.9 | H41: =E41-G41 -> -5.3352332 | I41: 171.18 | J41: Verified／Derived | K41: 收盤價：digrin（分割後）
A42: 收盤價來源1：digrin 年底原價（2016–2023 為分割前，公式 ÷ 10）；來源2：macrotrends 年底價（分割與股利還原，故早年較低；2025 相同）。companiesmarketcap 為 TTM 口徑，只作對照（差距見 H 欄）。
A44: 3. 分位
A45: 統計 | B45: P/E 當期（自算） | C45: P/E 前期（自算） | D45: cmc P/E（參考） | E45: 用途
A46: 25 分位 | B46: =PERCENTILE(E32:E41,0.25) -> 12.527605 | C46: =PERCENTILE(F32:F41,0.25) -> 17.782487 | D46: =PERCENTILE(G32:G41,0.25) -> 15.3 | E46: 見頂年
A47: 中位數 | B47: =PERCENTILE(E32:E41,0.5) -> 17.335727 | C47: =PERCENTILE(F32:F41,0.5) -> 21.934634 | D47: =PERCENTILE(G32:G41,0.5) -> 20.35 | E47: 中段
A48: 75 分位 | B48: =PERCENTILE(E32:E41,0.75) -> 21.085002 | C48: =PERCENTILE(F32:F41,0.75) -> 26.02026 | D48: =PERCENTILE(G32:G41,0.75) -> 21.85 | E48: 谷底
A49: 年數 | B49: =COUNT(E32:E41) -> 10 | C49: =COUNT(F32:F41) -> 10 | D49: =COUNT(G32:G41) -> 10
A50: 讀法：當期口徑的分母是年底時仍在進行中的會計年度（已過一半），接近遠期 P/E；2018、2022 年底記憶體下行使倍數偏低，2023、2025 年底 AI 預期使倍數偏高。
A52: 4. 循環位置（設備股共用規則；見頂年度讀設備市場模型，不在本模型另訂）
A53: 循環位置（設備股共用規則）：各情境的見頂年度取自設備市場模型（markets/equipment 的 Mkt 頁「見頂年度」：A 2029、B 2028、C 2027）；會計年度 FY(t) 對照日曆年 t（FY(t) 有 3/4 落在 t 年）：t 早於見頂年＝中段（中位數）、等於＝見頂（25 分位）、晚於＝谷底（75 分位）。Lam 的 FY(t)＝t−1 年 7 月～t 年 6 月，日曆年 t 只占一半；比照樣板以會計年度結束的年份 t 對照（FY2027 對照 2027）
A54: 情境 | B54: 設備市場見頂年度 | C54: FY2027 對照日曆年 | D54: 判定 | E54: 倍數 | F54: 對照：以 2026 對照（lag 1）的判定 | G54: 規則
A55: A | B55: =pk_A -> 2029 | C55: 2027 | D55: =IF(C55<pk_A,"中段",IF(C55=pk_A,"見頂","谷底")) -> 中段 | E55: =IF(D55="見頂",pe_peak,IF(D55="谷底",pe_trough,pe_mid)) -> 17.335727 | F55: =IF((C55-1)<pk_A,"中段",IF((C55-1)=pk_A,"見頂","谷底")) -> 中段 | G55: tools/cycle_position.py
A56: B | B56: =pk_B -> 2028 | C56: 2027 | D56: =IF(C56<pk_B,"中段",IF(C56=pk_B,"見頂","谷底")) -> 中段 | E56: =IF(D56="見頂",pe_peak,IF(D56="谷底",pe_trough,pe_mid)) -> 17.335727 | F56: =IF((C56-1)<pk_B,"中段",IF((C56-1)=pk_B,"見頂","谷底")) -> 中段 | G56: tools/cycle_position.py
A57: C | B57: =pk_C -> 2027 | C57: 2027 | D57: =IF(C57<pk_C,"中段",IF(C57=pk_C,"見頂","谷底")) -> 見頂 | E57: =IF(D57="見頂",pe_peak,IF(D57="谷底",pe_trough,pe_mid)) -> 12.527605 | F57: =IF((C57-1)<pk_C,"中段",IF((C57-1)=pk_C,"見頂","谷底")) -> 中段 | G57: tools/cycle_position.py
A59: 5. 隱含股價（美元）：規則值＝FY2027 EPS × 依循環位置的倍數；其餘倍數僅供參考
A60: 情境 | B60: EPS 年度 | C60: EPS | D60: 倍數類型 | E60: 倍數 | F60: 隱含股價 | G60: 相對現價 | H60: 備註
A61: A | B61: FY2027 | C61: =PL!E12 -> 9.4207254 | D61: ="規則值："&D55 -> 規則值：中段 | E61: =E55 -> 17.335727 | F61: =C61*E61 -> 163.31512 | G61: =F61/px-1 -> -0.29024285
A62: A | B62: FY2027 | C62: =PL!E12 -> 9.4207254 | D62: 參考：25 分位 | E62: =pe_peak -> 12.527605 | F62: =C62*E62 -> 118.01913 | G62: =F62/px-1 -> -0.48709637
A63: A | B63: FY2027 | C63: =PL!E12 -> 9.4207254 | D63: 參考：中位數 | E63: =pe_mid -> 17.335727 | F63: =C63*E63 -> 163.31512 | G63: =F63/px-1 -> -0.29024285
A64: A | B64: FY2027 | C64: =PL!E12 -> 9.4207254 | D64: 參考：75 分位 | E64: =pe_trough -> 21.085002 | F64: =C64*E64 -> 198.63601 | G64: =F64/px-1 -> -0.1367405
A65: A | B65: FY2028 | C65: =PL!F12 -> 10.683455 | D65: 參考：25 分位 | E65: =pe_peak -> 12.527605 | F65: =C65*E65 -> 133.8381 | G65: =F65/px-1 -> -0.41834809
A66: A | B66: FY2028 | C66: =PL!F12 -> 10.683455 | D66: 參考：中位數 | E66: =pe_mid -> 17.335727 | F66: =C66*E66 -> 185.20545 | G66: =F66/px-1 -> -0.19510885
A67: A | B67: FY2028 | C67: =PL!F12 -> 10.683455 | D67: 參考：75 分位 | E67: =pe_trough -> 21.085002 | F67: =C67*E67 -> 225.26067 | G67: =F67/px-1 -> -0.021031442
A68: B | B68: FY2027 | C68: =PL!E22 -> 9.4207254 | D68: ="規則值："&D56 -> 規則值：中段 | E68: =E56 -> 17.335727 | F68: =C68*E68 -> 163.31512 | G68: =F68/px-1 -> -0.29024285
A69: B | B69: FY2027 | C69: =PL!E22 -> 9.4207254 | D69: 參考：25 分位 | E69: =pe_peak -> 12.527605 | F69: =C69*E69 -> 118.01913 | G69: =F69/px-1 -> -0.48709637
A70: B | B70: FY2027 | C70: =PL!E22 -> 9.4207254 | D70: 參考：中位數 | E70: =pe_mid -> 17.335727 | F70: =C70*E70 -> 163.31512 | G70: =F70/px-1 -> -0.29024285
A71: B | B71: FY2027 | C71: =PL!E22 -> 9.4207254 | D71: 參考：75 分位 | E71: =pe_trough -> 21.085002 | F71: =C71*E71 -> 198.63601 | G71: =F71/px-1 -> -0.1367405
A72: B | B72: FY2028 | C72: =PL!F22 -> 10.02268 | D72: 參考：25 分位 | E72: =pe_peak -> 12.527605 | F72: =C72*E72 -> 125.56017 | G72: =F72/px-1 -> -0.45432346
A73: B | B73: FY2028 | C73: =PL!F22 -> 10.02268 | D73: 參考：中位數 | E73: =pe_mid -> 17.335727 | F73: =C73*E73 -> 173.75043 | G73: =F73/px-1 -> -0.24489164
A74: B | B74: FY2028 | C74: =PL!F22 -> 10.02268 | D74: 參考：75 分位 | E74: =pe_trough -> 21.085002 | F74: =C74*E74 -> 211.32822 | G74: =F74/px-1 -> -0.081580975
A75: C | B75: FY2027 | C75: =PL!E32 -> 9.4207254 | D75: ="規則值："&D57 -> 規則值：見頂 | E75: =E57 -> 12.527605 | F75: =C75*E75 -> 118.01913 | G75: =F75/px-1 -> -0.48709637
A76: C | B76: FY2027 | C76: =PL!E32 -> 9.4207254 | D76: 參考：25 分位 | E76: =pe_peak -> 12.527605 | F76: =C76*E76 -> 118.01913 | G76: =F76/px-1 -> -0.48709637
A77: C | B77: FY2027 | C77: =PL!E32 -> 9.4207254 | D77: 參考：中位數 | E77: =pe_mid -> 17.335727 | F77: =C77*E77 -> 163.31512 | G77: =F77/px-1 -> -0.29024285
A78: C | B78: FY2027 | C78: =PL!E32 -> 9.4207254 | D78: 參考：75 分位 | E78: =pe_trough -> 21.085002 | F78: =C78*E78 -> 198.63601 | G78: =F78/px-1 -> -0.1367405
A79: C | B79: FY2028 | C79: =PL!F32 -> 8.7433292 | D79: 參考：25 分位 | E79: =pe_peak -> 12.527605 | F79: =C79*E79 -> 109.53297 | G79: =F79/px-1 -> -0.52397664
A80: C | B80: FY2028 | C80: =PL!F32 -> 8.7433292 | D80: 參考：中位數 | E80: =pe_mid -> 17.335727 | F80: =C80*E80 -> 151.57196 | G80: =F80/px-1 -> -0.34127786
A81: C | B81: FY2028 | C81: =PL!F32 -> 8.7433292 | D81: 參考：75 分位 | E81: =pe_trough -> 21.085002 | F81: =C81*E81 -> 184.35311 | G81: =F81/px-1 -> -0.19881308
A83: 6. 目前遠期 P/E
A84: 項目 | B84: A | C84: B | D84: C | E84: 備註
A85: 現價（stockanalysis 2026-10-23 收盤） | B85: =px -> 230.1
A86: 遠期 P/E：stockanalysis | B86: =sa_fpe -> 22.39 | E86: stockanalysis 顯示 22.39x（遠期 EPS 口徑未註明）
A87: 遠期 P/E：現價 ÷ 共識 FY2027 EPS（Yahoo 9.63） | B87: =px/cons_eps27 -> 23.894081
A88: 現價 ÷ FY2026 EPS（實績 5.76） | B88: =px/a26_eps -> 39.947917 | E88: 已結束的會計年度
A89: 現價 ÷ FY2027 EPS（模型） | B89: =px/PL!E12 -> 24.424871 | C89: =px/PL!E22 -> 24.424871 | D89: =px/PL!E32 -> 24.424871 | E89: A／B／C
A90: 現價 ÷ FY2028 EPS（模型） | B90: =px/PL!F12 -> 21.537976 | C90: =px/PL!F22 -> 22.957932 | D90: =px/PL!F32 -> 26.317207 | E90: A／B／C
A91: 現價隱含倍數 ÷ 規則倍數（情境 A）— 以 FY2027 A EPS | B91: =B89/E55 -> 1.4089326 | E91: >1＝現價高於規則給的倍數
A94: 0. 目標價
A95: 0.1 DCF（股東權益現金流，FY2027–FY2032 明確期＋FY2032 後永續）
A96: 項目 | B96: A（順利） | C96: B（平平） | D96: C（不如預期） | E96: 說明
A97: 情境 EPS（FY2027–FY2032） | E97: PL 頁延伸區塊；FY2030 起為收斂法
A98: FY2027 | B98: =PL!E120 -> 9.4207254 | C98: =PL!E127 -> 9.4207254 | D98: =PL!E134 -> 9.4207254
A99: FY2028 | B99: =PL!F120 -> 10.683455 | C99: =PL!F127 -> 10.02268 | D99: =PL!F134 -> 8.7433292
A100: FY2029 | B100: =PL!G120 -> 12.200599 | C100: =PL!G127 -> 10.198667 | D100: =PL!G134 -> 7.6521234
A101: FY2030 | B101: =PL!H120 -> 13.246046 | C101: =PL!H127 -> 9.8100183 | D101: =PL!H134 -> 6.5270986
A102: FY2031 | B102: =PL!I120 -> 14.210943 | C102: =PL!I127 -> 9.5259798 | D102: =PL!I134 -> 5.7649705
A103: FY2032 | B103: =PL!J120 -> 15.0636 | C103: =PL!J127 -> 9.3334181 | D103: =PL!J134 -> 5.2514081
A104: 股東現金流＝EPS ×（1 − tp_g ÷ tp_roe） | E104: 模型無折舊與資本支出項目，故不用（淨利＋折舊－資本支出）；設備股資本支出低（輕資產），此式偏誤小
A105: 再投資率（tp_g ÷ tp_roe，上限 0.8） | B105: =MIN(tp_g/tp_roe,0.8) -> 0.070997515 | E105: ROE 為近三年平均（In 頁 tp_roe）
A106: FY2027 | B106: =B98*(1-$B$105) -> 8.7518773 | C106: =C98*(1-$B$105) -> 8.7518773 | D106: =D98*(1-$B$105) -> 8.7518773
A107: FY2028 | B107: =B99*(1-$B$105) -> 9.9249562 | C107: =C99*(1-$B$105) -> 9.3110943 | D107: =D99*(1-$B$105) -> 8.1225745
A108: FY2029 | B108: =B100*(1-$B$105) -> 11.334386 | C108: =C100*(1-$B$105) -> 9.4745872 | D108: =D100*(1-$B$105) -> 7.1088417
...

Sheet Recon
A1: Recon — 本模型 vs 公司說法、共識、設備市場模型。只作事後對照，不為對上數字而調整參數。差距 > 10% 的原因見 README
A3: 項目 | B3: 對照值 | C3: 模型 A | D3: 差距 A | E3: 模型 B | F3: 差距 B | G3: 模型 C | H3: 差距 C | I3: 對照來源 | J3: 說明
A4: A. FY2027、FY2028 vs 共識（校準未使用共識）
A5: FY2027 營收 | B5: =cons_rev27 -> 35.39 | C5: =PL!E5 -> 34.602293 | D5: =C5/B5-1 -> -0.02225791 | E5: =PL!E15 -> 34.602293 | F5: =E5/B5-1 -> -0.02225791 | G5: =PL!E25 -> 34.602293 | H5: =G5/B5-1 -> -0.02225791 | I5: Yahoo（29 位） | J5: stockanalysis 34.9
A6: FY2027 EPS（Yahoo） | B6: =cons_eps27 -> 9.63 | C6: =PL!E12 -> 9.4207254 | D6: =C6/B6-1 -> -0.02173153 | E6: =PL!E22 -> 9.4207254 | F6: =E6/B6-1 -> -0.02173153 | G6: =PL!E32 -> 9.4207254 | H6: =G6/B6-1 -> -0.02173153 | I6: Yahoo（9.63） | J6: 共識多為非 GAAP；Lam 非 GAAP 與 GAAP 差約 0.01／季
A7: FY2027 EPS（stockanalysis） | B7: =cons_eps27b -> 9.48 | C7: =PL!E12 -> 9.4207254 | D7: =C7/B7-1 -> -0.0062525981 | E7: =PL!E22 -> 9.4207254 | F7: =E7/B7-1 -> -0.0062525981 | G7: =PL!E32 -> 9.4207254 | H7: =G7/B7-1 -> -0.0062525981 | I7: stockanalysis（9.48）
A8: FY2028 營收 | B8: =cons_rev28 -> 42.68 | C8: =PL!F5 -> 37.751047 | D8: =C8/B8-1 -> -0.11548624 | E8: =PL!F15 -> 35.895442 | F8: =E8/B8-1 -> -0.1589634 | G8: =PL!F25 -> 32.274838 | H8: =G8/B8-1 -> -0.24379481 | I8: Yahoo（28 位；區間 36.5–49.2）
A9: FY2028 EPS | B9: =cons_eps28 -> 12.15 | C9: =PL!F12 -> 10.683455 | D9: =C9/B9-1 -> -0.1207033 | E9: =PL!F22 -> 10.02268 | F9: =E9/B9-1 -> -0.17508809 | G9: =PL!F32 -> 8.7433292 | H9: =G9/B9-1 -> -0.28038443 | I9: Yahoo（12.15；區間 10.41–15.12）
A10: B. 公司說法（法說，Interested-party）
A11: CY2026 系統營收年增（公司：well over 40%） | B11: =co_sys26 -> 0.4 | C11: =Units!G14 -> 0.48205163 | D11: =C11-B11 -> 0.082051634 | E11: =Units!G14 -> 0.48205163 | F11: =E11-B11 -> 0.082051634 | G11: =Units!G14 -> 0.48205163 | H11: =G11-B11 -> 0.082051634 | I11: FQ1-27 法說 | J11: 模型值＝實績＋指引（含 Q2 拆分假設），非獨立檢驗
A12: CY2026 CSBG 年增（公司：逾 30%） | B12: =co_cs26 -> 0.3 | C12: =Units!G15 -> 0.33048672 | D12: =C12-B12 -> 0.030486721 | E12: =Units!G15 -> 0.33048672 | F12: =E12-B12 -> 0.030486721 | G12: =Units!G15 -> 0.33048672 | H12: =G12-B12 -> 0.030486721 | I12: FQ1-27 法說 | J12: 同上；Q2 CSBG＝Q1 持平時
A13: FY2027 毛利率 vs Q2 指引 52.5% | B13: =g_q2gm -> 0.525 | C13: =PL!E8 -> 0.52550385 | D13: =C13-B13 -> 0.00050385404 | E13: =PL!E18 -> 0.52550385 | F13: =E13-B13 -> 0.00050385404 | G13: =PL!E28 -> 0.52550385 | H13: =G13-B13 -> 0.00050385404 | I13: 8-K 2026-10-21 | J13: 公司稱近期維持目前水準；長期 mid-50s
A14: FY2029 毛利率 vs 公司長期目標（mid-50s，取 55%） | B14: =0.55 -> 0.55 | C14: =PL!G8 -> 0.53496444 | D14: =C14-B14 -> -0.015035555 | E14: =PL!G18 -> 0.52751507 | F14: =E14-B14 -> -0.02248493 | G14: =PL!G28 -> 0.51595745 | H14: =G14-B14 -> -0.034042547 | I14: FQ4-26／FQ1-27 法說
A15: C. 設備市場（WFE，US$B）
A16: CY2026 晶圓前段（公司 mid-$150B vs 設備市場模型） | B16: =co_wfe26 -> 155 | C16: =wfeA_26 -> 156.15705 | D16: =C16/B16-1 -> 0.0074648424 | E16: =wfeB_26 -> 156.15705 | F16: =E16/B16-1 -> 0.0074648424 | G16: =wfeC_26 -> 156.15705 | H16: =G16/B16-1 -> 0.0074648424 | I16: FQ1-27 法說 | J16: 口徑不同（公司 CY2025 約 110、SEMI 116.9）
A17: CY2027 晶圓前段（公司 >$200B vs 設備市場模型） | B17: =co_wfe27 -> 200 | C17: =wfeA_27 -> 192.79547 | D17: =C17/B17-1 -> -0.036022653 | E17: =wfeB_27 -> 192.79547 | F17: =E17/B17-1 -> -0.036022653 | G17: =wfeC_27 -> 192.79547 | H17: =G17/B17-1 -> -0.036022653 | I17: FQ1-27 法說 | J17: 下限值
A18: CY2026／CY2025 晶圓前段成長：公司（155÷110）vs 模型 | B18: =co_wfe26/co_wfe25-1 -> 0.40909091 | C18: =wfeA_26/wfeA_25-1 -> 0.33585357 | D18: =C18-B18 -> -0.073237335 | E18: =wfeB_26/wfeB_25-1 -> 0.33585357 | F18: =E18-B18 -> -0.073237335 | G18: =wfeC_26/wfeC_25-1 -> 0.33585357 | H18: =G18-B18 -> -0.073237335 | I18: FQ2-26、FQ1-27 法說
A19: D. 其他資訊（非對帳）
A20: FY2027 上半（Q1 實績＋Q2 指引）÷ 模型 FY2027 全年營收（A） | C20: =(q1_rev+g_q2rev)/PL!E5 -> 0.48607814
A21: FY2027 上半 EPS（Q1 實績＋Q2 指引）÷ 模型 FY2027 EPS（A） | C21: =(q1_eps+g_q2eps)/PL!E12 -> 0.4797932
A22: Lam 系統營收 ÷ 模型晶圓前段（CY2026） | C22: =Units!E24 -> 0.12696722

Sheet Sens
A1: Sens — 一次動一個輸入（情境 A）：對 FY2027、FY2028 營收與 EPS 的影響。每個案例是一個完整的推導區塊（本頁下方，與 PL 同一引擎）
A3: 案例 | B3: 設定 | C3: FY2027 營收 US$B | D3: FY2027 EPS US$ | E3: 相對基準 | F3: FY2028 營收 US$B | G3: FY2028 EPS US$ | H3: 相對基準
A4: 基準（情境 A） | B4: PL 區塊 A | C4: =PL!E52 -> 34.602293 | D4: =PL!E60 -> 9.4207254 | E4: =D4/D$4-1 -> 0 | F4: =PL!F52 -> 37.751047 | G4: =PL!F60 -> 10.683455 | H4: =G4/G$4-1 -> 0
A5: 份額漂移 −2%／年 | B5: CY2027 起每年相對 WFE 分項 −2% | C5: =E62 -> 34.356533 | D5: =E70 -> 9.3350856 | E5: =D5/D$4-1 -> -0.0090905665 | F5: =F62 -> 36.958257 | G5: =F70 -> 10.400741 | H5: =G5/G$4-1 -> -0.026462808
A6: 份額漂移 +2%／年 | B6: 每年 +2% | C6: =E92 -> 34.848052 | D6: =E100 -> 9.5064259 | E6: =D6/D$4-1 -> 0.0090970178 | F6: =F92 -> 38.554889 | G6: =F100 -> 10.970711 | H6: =G6/G$4-1 -> 0.026887931
A7: 出口管制：中國系統營收 −20%（CY2027 起） | B7: cn_sh 34% × 20% | C7: =E122 -> 33.766709 | D7: =E130 -> 9.1298009 | E7: =D7/D$4-1 -> -0.030881327 | F7: =F122 -> 35.976118 | G7: =F130 -> 10.051339 | H7: =G7/G$4-1 -> -0.059167753
A8: 出口管制：中國系統營收 −40%（CY2027 起） | B8: cn_sh 34% × 40%（2022 管制類比上緣） | C8: =E152 -> 32.931126 | D8: =E160 -> 8.8395964 | E8: =D8/D$4-1 -> -0.061686225 | F8: =F152 -> 34.201189 | G8: =F160 -> 9.4223196 | H8: =G8/G$4-1 -> -0.11804565
A9: 上半年占比 45% | B9: FY(t) 中 CY(t) 上半的權重 | C9: =E182 -> 32.824005 | D9: =E190 -> 8.8024456 | E9: =D9/D$4-1 -> -0.065629742 | F9: =F182 -> 37.532517 | G9: =F190 -> 10.605466 | H9: =G9/G$4-1 -> -0.007299926
A10: 上半年占比 55% | C10: =E212 -> 36.38058 | D10: =E220 -> 10.042189 | E10: =D10/D$4-1 -> 0.065967665 | F10: =F212 -> 37.969577 | G10: =F220 -> 10.761488 | H10: =G10/G$4-1 -> 0.0073041116
A11: CSBG CY2027 +10% | B11: 公司稱逾 15% | C11: =E242 -> 34.363385 | D11: =E250 -> 9.3374725 | E11: =D11/D$4-1 -> -0.0088372056 | F11: =F242 -> 37.244562 | G11: =F250 -> 10.50277 | H11: =G11/G$4-1 -> -0.016912551
A12: CSBG CY2027 +20% | C12: =E272 -> 34.841201 | D12: =E280 -> 9.5040357 | E12: =D12/D$4-1 -> 0.0088433022 | F12: =F272 -> 38.257532 | G12: =F280 -> 10.86438 | H12: =G12/G$4-1 -> 0.016935035
A13: CSBG CY2028–29 +8% | C13: =E302 -> 34.602293 | D13: =E310 -> 9.4207254 | E13: =D13/D$4-1 -> 0 | F13: =F302 -> 37.531252 | G13: =F310 -> 10.605015 | H13: =G13/G$4-1 -> -0.0073421881
A14: CSBG CY2028–29 +16% | C14: =E332 -> 34.602293 | D14: =E340 -> 9.4207254 | E14: =D14/D$4-1 -> 0 | F14: =F332 -> 37.970842 | G14: =F340 -> 10.76194 | H14: =G14/G$4-1 -> 0.0073464223
A15: 營業費用變動比例 低（15%） | B15: FY2026 營業費用中變動部分 15% | C15: =E362 -> 34.602293 | D15: =E370 -> 9.6623615 | E15: =D15/D$4-1 -> 0.025649414 | F15: =F362 -> 37.751047 | G15: =F370 -> 10.99671 | H15: =G15/G$4-1 -> 0.029321489
A16: 營業費用變動比例 高（50%） | B16: 變動 50% | C16: =E392 -> 34.602293 | D16: =E400 -> 9.2599489 | E16: =D16/D$4-1 -> -0.017066255 | F16: =F392 -> 37.751047 | G16: =F400 -> 10.475026 | H16: =G16/G$4-1 -> -0.01950953
A17: 稅率 13% | C17: =E422 -> 34.602293 | D17: =E430 -> 9.8156061 | E17: =D17/D$4-1 -> 0.041916168 | F17: =F422 -> 37.751047 | G17: =F430 -> 11.131264 | H17: =G17/G$4-1 -> 0.041916168
A18: 稅率 19% | C18: =E452 -> 34.602293 | D18: =E460 -> 9.1386677 | E18: =D18/D$4-1 -> -0.02994012 | F18: =F452 -> 37.751047 | G18: =F460 -> 10.363591 | H18: =G18/G$4-1 -> -0.02994012
A19: 庫藏股 0%／年 | C19: =E482 -> 34.602293 | D19: =E490 -> 9.4207254 | E19: =D19/D$4-1 -> 0 | F19: =F482 -> 37.751047 | G19: =F490 -> 10.523203 | H19: =G19/G$4-1 -> -0.015
A20: 庫藏股 3%／年 | C20: =E512 -> 34.602293 | D20: =E520 -> 9.4207254 | E20: =D20/D$4-1 -> 0 | F20: =F512 -> 37.751047 | G20: =F520 -> 10.848663 | H20: =G20/G$4-1 -> 0.015463918
A21: 業外收益 0 | C21: =E542 -> 34.602293 | D21: =E550 -> 9.3540853 | E21: =D21/D$4-1 -> -0.0070737721 | F21: =F542 -> 37.751047 | G21: =F550 -> 10.6158 | H21: =G21/G$4-1 -> -0.0063326787
A22: 業外收益 0.2 | C22: =E572 -> 34.602293 | D22: =E580 -> 9.4873654 | E22: =D22/D$4-1 -> 0.0070737721 | F22: =F572 -> 37.751047 | G22: =F580 -> 10.75111 | H22: =G22/G$4-1 -> 0.0063326787
A23: 設備市場情境 B | B23: WFE 分項讀 markets/equipment B；CSBG 成長 B | C23: =PL!E76 -> 34.602293 | D23: =PL!E84 -> 9.4207254 | E23: =D23/D$4-1 -> 0 | F23: =PL!F76 -> 35.895442 | G23: =PL!F84 -> 10.02268 | H23: =G23/G$4-1 -> -0.061850335
A24: 設備市場情境 C | B24: WFE 分項讀 C；出口管制 −20%（CY2028 起）；CSBG 成長 C | C24: =PL!E100 -> 34.602293 | D24: =PL!E108 -> 9.4207254 | E24: =D24/D$4-1 -> 0 | F24: =PL!F100 -> 32.274838 | G24: =PL!F108 -> 8.7433292 | H24: =G24/G$4-1 -> -0.18160097
A26: 讀法：FY2027 上半已錨定（Q1 實績＋Q2 指引），只有下半（CY2027 上半）隨輸入變動，所以 FY2027 的敏感度小、FY2028 才明顯；設備市場 B、C 的係數從 CY2028 開始。
A50: 案例區塊：份額漂移 −2%／年（情境 A）
A51: 項目 | B51: 單位 | C51: FY2025 | D51: CY2026／FY2026 | E51: CY2027／FY2027 | F51: CY2028／FY2028 | G51: CY2029／FY2029 | H51: 說明
A52: A. 日曆年（D＝CY2026 … G＝CY2029）
A53: 系統營收：代工與邏輯 | B53: US$B | D53: =cy26_fl -> 10.967627 | E53: =k_fl*(advA_27+oflA_27)*(1+drift_lo)^1 -> 12.447726 | F53: =k_fl*(advA_28+oflA_28)*(1+drift_lo)^2 -> 13.735224 | G53: =k_fl*(advA_29+oflA_29)*(1+drift_lo)^3 -> 14.360673 | H53: CY2026＝錨點（實績＋指引）；之後＝k × 設備市場模型分項 × (1＋份額漂移)^年
A54: 系統營收：DRAM | B54: US$B | D54: =cy26_dram -> 4.3540014 | E54: =k_dram*dramA_27*(1+drift_lo)^1 -> 5.7727768 | F54: =k_dram*dramA_28*(1+drift_lo)^2 -> 6.3267586 | G54: =k_dram*dramA_29*(1+drift_lo)^3 -> 6.4365688 | H54: CY2026＝錨點（實績＋指引）；之後＝k × 設備市場模型分項 × (1＋份額漂移)^年
A55: 系統營收：NAND | B55: US$B | D55: =cy26_nand -> 4.5051978 | E55: =k_nand*nandA_27*(1+drift_lo)^1 -> 5.8639612 | F55: =k_nand*nandA_28*(1+drift_lo)^2 -> 6.4717633 | G55: =k_nand*nandA_29*(1+drift_lo)^3 -> 6.7039996 | H55: CY2026＝錨點（實績＋指引）；之後＝k × 設備市場模型分項 × (1＋份額漂移)^年
A56: 出口管制：中國系統營收折損 | B56: US$B | E56: =-cn_sh*0*(E53+E54+E55) -> 0 | F56: =-cn_sh*0*(F53+F54+F55) -> 0 | G56: =-cn_sh*0*(G53+G54+G55) -> 0 | H56: −中國占比 × 折損比例 × 系統營收；情境 C 自 CY2028 起 cutC，其餘為 0（Sens 另設）
A57: 系統營收 CY | B57: US$B | D57: =SUM(D53:D56) -> 19.826826 | E57: =SUM(E53:E56) -> 24.084464 | F57: =SUM(F53:F56) -> 26.533746 | G57: =SUM(G53:G56) -> 27.501241
A58: CSBG CY | B58: US$B | D58: =cy26_cs -> 9.556318 | E58: =D58*(1+g_cs27) -> 10.989766 | F58: =E58*(1+g_cs_A) -> 12.308538 | G58: =F58*(1+g_cs_A) -> 13.785562 | H58: CY2026＝錨點；CY2027 公司稱逾 15%；之後依情境
A59: B. 會計年度（C＝FY2025 … G＝FY2029；FY(t)＝CY(t−1) 下半＋CY(t) 上半）
A60: 系統營收 | B60: US$B | C60: =a25_sys -> 11.49128 | D60: =a26_sys -> 14.885488 | E60: =h2s26+h1s*E57 -> 23.888628 | F60: =(1-h1s)*E57+h1s*F57 -> 25.309105 | G60: =(1-h1s)*F57+h1s*G57 -> 27.017494 | H60: FY2027＝CY2026 下半（FY27 Q1 實績＋Q2 指引）＋ h1 × CY2027
A61: CSBG | B61: US$B | C61: =a25_cs -> 6.944311 | D61: =a26_cs -> 8.347202 | E61: =h2c26+h1s*E58 -> 10.467905 | F61: =(1-h1s)*E58+h1s*F58 -> 11.649152 | G61: =(1-h1s)*F58+h1s*G58 -> 13.04705
A62: 營收 | B62: US$B | C62: =C60+C61 -> 18.435591 | D62: =D60+D61 -> 23.23269 | E62: =E60+E61 -> 34.356533 | F62: =F60+F61 -> 36.958257 | G62: =G60+G61 -> 40.064544
A63: 毛利率 | B63: % | C63: =a25_gp/a25_rev -> 0.48705024 | D63: =a26_gp/a26_rev -> 0.50469007 | E63: =gm_a+gm_b*LN(E62) -> 0.52513144 | F63: =gm_a+gm_b*LN(F62) -> 0.52894543 | G63: =gm_a+gm_b*LN(G62) -> 0.53316204 | H63: 截距＋斜率 × ln 營收（兩點推導）
A64: 毛利 | B64: US$B | C64: =C62*C63 -> 8.979059 | D64: =D62*D63 -> 11.725308 | E64: =E62*E63 -> 18.041695 | F64: =F62*F63 -> 19.548901 | G64: =G62*G63 -> 21.360894
A65: 營業費用 | B65: US$B | C65: =a25_opx -> 3.078091 | D65: =a26_opx -> 3.525513 | E65: =opex_fix+opex_var*E62 -> 4.1334771 | F65: =opex_fix+opex_var*F62 -> 4.2756721 | G65: =opex_fix+opex_var*G62 -> 4.4454436 | H65: 固定＋變動 × 營收
A66: 營業利益 | B66: US$B | C66: =C64-C65 -> 5.900968 | D66: =D64-D65 -> 8.199795 | E66: =E64-E65 -> 13.908218 | F66: =F64-F65 -> 15.273229 | G66: =G64-G65 -> 16.91545
A67: 營業利益率 | B67: % | C67: =C66/C62 -> 0.32008564 | D67: =D66/D62 -> 0.35294213 | E67: =E66/E62 -> 0.4048202 | F67: =F66/F62 -> 0.41325621 | G67: =G66/G62 -> 0.42220499
A68: 淨利 | B68: US$B | C68: =a25_ni -> 5.358217 | D68: =a26_ni -> 7.265396 | E68: =(E66+oth_inc)*(1-tax) -> 11.696862 | F68: =(F66+oth_inc)*(1-tax) -> 12.836646 | G68: =(G66+oth_inc)*(1-tax) -> 14.207901
A69: 稀釋股數 | B69: 十億股 | C69: =a25_dsh -> 1.290142 | D69: =a26_dsh -> 1.261102 | E69: =sh_27 -> 1.253 | F69: =E69*(1-bb) -> 1.234205 | G69: =F69*(1-bb) -> 1.2156919
A70: EPS（稀釋） | B70: US$ | C70: =a25_eps -> 4.15 | D70: =a26_eps -> 5.76 | E70: =E68/E69 -> 9.3350856 | F70: =F68/F69 -> 10.400741 | G70: =G68/G69 -> 11.68709
A71: 系統營收占營收 | B71: % | C71: =C60/C62 -> 0.6233204 | D71: =D60/D62 -> 0.64071306 | E71: =E60/E62 -> 0.69531545 | F71: =F60/F62 -> 0.68480246 | G71: =G60/G62 -> 0.67434922
A80: 案例區塊：份額漂移 +2%／年（情境 A）
A81: 項目 | B81: 單位 | C81: FY2025 | D81: CY2026／FY2026 | E81: CY2027／FY2027 | F81: CY2028／FY2028 | G81: CY2029／FY2029 | H81: 說明
A82: A. 日曆年（D＝CY2026 … G＝CY2029）
A83: 系統營收：代工與邏輯 | B83: US$B | D83: =cy26_fl -> 10.967627 | E83: =k_fl*(advA_27+oflA_27)*(1+drift_hi)^1 -> 12.955796 | F83: =k_fl*(advA_28+oflA_28)*(1+drift_hi)^2 -> 14.87935 | G83: =k_fl*(advA_29+oflA_29)*(1+drift_hi)^3 -> 16.191873 | H83: CY2026＝錨點（實績＋指引）；之後＝k × 設備市場模型分項 × (1＋份額漂移)^年
A84: 系統營收：DRAM | B84: US$B | D84: =cy26_dram -> 4.3540014 | E84: =k_dram*dramA_27*(1+drift_hi)^1 -> 6.0084003 | F84: =k_dram*dramA_28*(1+drift_hi)^2 -> 6.8537689 | G84: =k_dram*dramA_29*(1+drift_hi)^3 -> 7.2573272 | H84: CY2026＝錨點（實績＋指引）；之後＝k × 設備市場模型分項 × (1＋份額漂移)^年
A85: 系統營收：NAND | B85: US$B | D85: =cy26_nand -> 4.5051978 | E85: =k_nand*nandA_27*(1+drift_hi)^1 -> 6.1033066 | F85: =k_nand*nandA_28*(1+drift_hi)^2 -> 7.0108523 | G85: =k_nand*nandA_29*(1+drift_hi)^3 -> 7.5588594 | H85: CY2026＝錨點（實績＋指引）；之後＝k × 設備市場模型分項 × (1＋份額漂移)^年
A86: 出口管制：中國系統營收折損 | B86: US$B | E86: =-cn_sh*0*(E83+E84+E85) -> 0 | F86: =-cn_sh*0*(F83+F84+F85) -> 0 | G86: =-cn_sh*0*(G83+G84+G85) -> 0 | H86: −中國占比 × 折損比例 × 系統營收；情境 C 自 CY2028 起 cutC，其餘為 0（Sens 另設）
A87: 系統營收 CY | B87: US$B | D87: =SUM(D83:D86) -> 19.826826 | E87: =SUM(E83:E86) -> 25.067503 | F87: =SUM(F83:F86) -> 28.743971 | G87: =SUM(G83:G86) -> 31.008059
A88: CSBG CY | B88: US$B | D88: =cy26_cs -> 9.556318 | E88: =D88*(1+g_cs27) -> 10.989766 | F88: =E88*(1+g_cs_A) -> 12.308538 | G88: =F88*(1+g_cs_A) -> 13.785562 | H88: CY2026＝錨點；CY2027 公司稱逾 15%；之後依情境
A89: B. 會計年度（C＝FY2025 … G＝FY2029；FY(t)＝CY(t−1) 下半＋CY(t) 上半）
A90: 系統營收 | B90: US$B | C90: =a25_sys -> 11.49128 | D90: =a26_sys -> 14.885488 | E90: =h2s26+h1s*E87 -> 24.380148 | F90: =(1-h1s)*E87+h1s*F87 -> 26.905737 | G90: =(1-h1s)*F87+h1s*G87 -> 29.876015 | H90: FY2027＝CY2026 下半（FY27 Q1 實績＋Q2 指引）＋ h1 × CY2027
A91: CSBG | B91: US$B | C91: =a25_cs -> 6.944311 | D91: =a26_cs -> 8.347202 | E91: =h2c26+h1s*E88 -> 10.467905 | F91: =(1-h1s)*E88+h1s*F88 -> 11.649152 | G91: =(1-h1s)*F88+h1s*G88 -> 13.04705
A92: 營收 | B92: US$B | C92: =C90+C91 -> 18.435591 | D92: =D90+D91 -> 23.23269 | E92: =E90+E91 -> 34.848052 | F92: =F90+F91 -> 38.554889 | G92: =G90+G91 -> 42.923065
A93: 毛利率 | B93: % | C93: =a25_gp/a25_rev -> 0.48705024 | D93: =a26_gp/a26_rev -> 0.50469007 | E93: =gm_a+gm_b*LN(E92) -> 0.52587363 | F93: =gm_a+gm_b*LN(F92) -> 0.53115523 | G93: =gm_a+gm_b*LN(G92) -> 0.5367629 | H93: 截距＋斜率 × ln 營收（兩點推導）
A94: 毛利 | B94: US$B | C94: =C92*C93 -> 8.979059 | D94: =D92*D93 -> 11.725308 | E94: =E92*E93 -> 18.325672 | F94: =F92*F93 -> 20.478631 | G94: =G92*G93 -> 23.039509
A95: 營業費用 | B95: US$B | C95: =a25_opx -> 3.078091 | D95: =a26_opx -> 3.525513 | E95: =opex_fix+opex_var*E92 -> 4.1603407 | F95: =opex_fix+opex_var*F92 -> 4.3629346 | G95: =opex_fix+opex_var*G92 -> 4.6016736 | H95: 固定＋變動 × 營收
A96: 營業利益 | B96: US$B | C96: =C94-C95 -> 5.900968 | D96: =D94-D95 -> 8.199795 | E96: =E94-E95 -> 14.165331 | F96: =F94-F95 -> 16.115696 | G96: =G94-G95 -> 18.437835
A97: 營業利益率 | B97: % | C97: =C96/C92 -> 0.32008564 | D97: =D96/D92 -> 0.35294213 | E97: =E96/E92 -> 0.40648846 | F97: =F96/F92 -> 0.41799359 | G97: =G96/G92 -> 0.42955542
A98: 淨利 | B98: US$B | C98: =a25_ni -> 5.358217 | D98: =a26_ni -> 7.265396 | E98: =(E96+oth_inc)*(1-tax) -> 11.911552 | F98: =(F96+oth_inc)*(1-tax) -> 13.540106 | G98: =(G96+oth_inc)*(1-tax) -> 15.479092
A99: 稀釋股數 | B99: 十億股 | C99: =a25_dsh -> 1.290142 | D99: =a26_dsh -> 1.261102 | E99: =sh_27 -> 1.253 | F99: =E99*(1-bb) -> 1.234205 | G99: =F99*(1-bb) -> 1.2156919
A100: EPS（稀釋） | B100: US$ | C100: =a25_eps -> 4.15 | D100: =a26_eps -> 5.76 | E100: =E98/E99 -> 9.5064259 | F100: =F98/F99 -> 10.970711 | G100: =G98/G99 -> 12.732743
A101: 系統營收占營收 | B101: % | C101: =C90/C92 -> 0.6233204 | D101: =D90/D92 -> 0.64071306 | E101: =E90/E92 -> 0.69961292 | F101: =F90/F92 -> 0.69785539 | G101: =G90/G92 -> 0.69603639
A110: 案例區塊：出口管制：中國系統營收 −20%（CY2027 起）（情境 A）
A111: 項目 | B111: 單位 | C111: FY2025 | D111: CY2026／FY2026 | E111: CY2027／FY2027 | F111: CY2028／FY2028 | G111: CY2029／FY2029 | H111: 說明
A112: A. 日曆年（D＝CY2026 … G＝CY2029）
A113: 系統營收：代工與邏輯 | B113: US$B | D113: =cy26_fl -> 10.967627 | E113: =k_fl*(advA_27+oflA_27)*(1+drift)^1 -> 12.701761 | F113: =k_fl*(advA_28+oflA_28)*(1+drift)^2 -> 14.301566 | G113: =k_fl*(advA_29+oflA_29)*(1+drift)^3 -> 15.257963 | H113: CY2026＝錨點（實績＋指引）；之後＝k × 設備市場模型分項 × (1＋份額漂移)^年
A114: 系統營收：DRAM | B114: US$B | D114: =cy26_dram -> 4.3540014 | E114: =k_dram*dramA_27*(1+drift)^1 -> 5.8905886 | F114: =k_dram*dramA_28*(1+drift)^2 -> 6.5876287 | G114: =k_dram*dramA_29*(1+drift)^3 -> 6.8387415 | H114: CY2026＝錨點（實績＋指引）；之後＝k × 設備市場模型分項 × (1＋份額漂移)^年
A115: 系統營收：NAND | B115: US$B | D115: =cy26_nand -> 4.5051978 | E115: =k_nand*nandA_27*(1+drift)^1 -> 5.9836339 | F115: =k_nand*nandA_28*(1+drift)^2 -> 6.7386124 | G115: =k_nand*nandA_29*(1+drift)^3 -> 7.1228821 | H115: CY2026＝錨點（實績＋指引）；之後＝k × 設備市場模型分項 × (1＋份額漂移)^年
A116: 出口管制：中國系統營收折損 | B116: US$B | E116: =-cn_sh*cut_sens_lo*(E113+E114+E115) -> -1.6711669 | F116: =-cn_sh*cut_sens_lo*(F113+F114+F115) -> -1.8786909 | G116: =-cn_sh*cut_sens_lo*(G113+G114+G115) -> -1.9869319 | H116: −中國占比 × 折損比例 × 系統營收；情境 C 自 CY2028 起 cutC，其餘為 0（Sens 另設）
A117: 系統營收 CY | B117: US$B | D117: =SUM(D113:D116) -> 19.826826 | E117: =SUM(E113:E116) -> 22.904817 | F117: =SUM(F113:F116) -> 25.749117 | G117: =SUM(G113:G116) -> 27.232655
A118: CSBG CY | B118: US$B | D118: =cy26_cs -> 9.556318 | E118: =D118*(1+g_cs27) -> 10.989766 | F118: =E118*(1+g_cs_A) -> 12.308538 | G118: =F118*(1+g_cs_A) -> 13.785562 | H118: CY2026＝錨點；CY2027 公司稱逾 15%；之後依情境
A119: B. 會計年度（C＝FY2025 … G＝FY2029；FY(t)＝CY(t−1) 下半＋CY(t) 上半）
A120: 系統營收 | B120: US$B | C120: =a25_sys -> 11.49128 | D120: =a26_sys -> 14.885488 | E120: =h2s26+h1s*E117 -> 23.298804 | F120: =(1-h1s)*E117+h1s*F117 -> 24.326967 | G120: =(1-h1s)*F117+h1s*G117 -> 26.490886 | H120: FY2027＝CY2026 下半（FY27 Q1 實績＋Q2 指引）＋ h1 × CY2027
A121: CSBG | B121: US$B | C121: =a25_cs -> 6.944311 | D121: =a26_cs -> 8.347202 | E121: =h2c26+h1s*E118 -> 10.467905 | F121: =(1-h1s)*E118+h1s*F118 -> 11.649152 | G121: =(1-h1s)*F118+h1s*G118 -> 13.04705
A122: 營收 | B122: US$B | C122: =C120+C121 -> 18.435591 | D122: =D120+D121 -> 23.23269 | E122: =E120+E121 -> 33.766709 | F122: =F120+F121 -> 35.976118 | G122: =G120+G121 -> 39.537936
A123: 毛利率 | B123: % | C123: =a25_gp/a25_rev -> 0.48705024 | D123: =a26_gp/a26_rev -> 0.50469007 | E123: =gm_a+gm_b*LN(E122) -> 0.52422666 | F123: =gm_a+gm_b*LN(F122) -> 0.52753818 | G123: =gm_a+gm_b*LN(G122) -> 0.53247073 | H123: 截距＋斜率 × ln 營收（兩點推導）
A124: 毛利 | B124: US$B | C124: =C122*C123 -> 8.979059 | D124: =D122*D123 -> 11.725308 | E124: =E122*E123 -> 17.701409 | F124: =F122*F123 -> 18.978776 | G124: =G122*G123 -> 21.052794
A125: 營業費用 | B125: US$B | C125: =a25_opx -> 3.078091 | D125: =a26_opx -> 3.525513 | E125: =opex_fix+opex_var*E122 -> 4.1012408 | F125: =opex_fix+opex_var*F122 -> 4.2219942 | G125: =opex_fix+opex_var*G122 -> 4.4166622 | H125: 固定＋變動 × 營收
A126: 營業利益 | B126: US$B | C126: =C124-C125 -> 5.900968 | D126: =D124-D125 -> 8.199795 | E126: =E124-E125 -> 13.600168 | F126: =F124-F125 -> 14.756782 | G126: =G124-G125 -> 16.636131
A127: 營業利益率 | B127: % | C127: =C126/C122 -> 0.32008564 | D127: =D126/D122 -> 0.35294213 | E127: =E126/E122 -> 0.40276854 | F127: =F126/F122 -> 0.41018271 | G127: =G126/G122 -> 0.42076378
A128: 淨利 | B128: US$B | C128: =a25_ni -> 5.358217 | D128: =a26_ni -> 7.265396 | E128: =(E126+oth_inc)*(1-tax) -> 11.43964 | F128: =(F126+oth_inc)*(1-tax) -> 12.405413 | G128: =(G126+oth_inc)*(1-tax) -> 13.97467
A129: 稀釋股數 | B129: 十億股 | C129: =a25_dsh -> 1.290142 | D129: =a26_dsh -> 1.261102 | E129: =sh_27 -> 1.253 | F129: =E129*(1-bb) -> 1.234205 | G129: =F129*(1-bb) -> 1.2156919
A130: EPS（稀釋） | B130: US$ | C130: =a25_eps -> 4.15 | D130: =a26_eps -> 5.76 | E130: =E128/E129 -> 9.1298009 | F130: =F128/F129 -> 10.051339 | G130: =G128/G129 -> 11.495239
A131: 系統營收占營收 | B131: % | C131: =C120/C122 -> 0.6233204 | D131: =D120/D122 -> 0.64071306 | E131: =E120/E122 -> 0.68999334 | F131: =F120/F122 -> 0.67619765 | G131: =G120/G122 -> 0.67001186
A140: 案例區塊：出口管制：中國系統營收 −40%（CY2027 起）（情境 A）
A141: 項目 | B141: 單位 | C141: FY2025 | D141: CY2026／FY2026 | E141: CY2027／FY2027 | F141: CY2028／FY2028 | G141: CY2029／FY2029 | H141: 說明
A142: A. 日曆年（D＝CY2026 … G＝CY2029）
A143: 系統營收：代工與邏輯 | B143: US$B | D143: =cy26_fl -> 10.967627 | E143: =k_fl*(advA_27+oflA_27)*(1+drift)^1 -> 12.701761 | F143: =k_fl*(advA_28+oflA_28)*(1+drift)^2 -> 14.301566 | G143: =k_fl*(advA_29+oflA_29)*(1+drift)^3 -> 15.257963 | H143: CY2026＝錨點（實績＋指引）；之後＝k × 設備市場模型分項 × (1＋份額漂移)^年
A144: 系統營收：DRAM | B144: US$B | D144: =cy26_dram -> 4.3540014 | E144: =k_dram*dramA_27*(1+drift)^1 -> 5.8905886 | F144: =k_dram*dramA_28*(1+drift)^2 -> 6.5876287 | G144: =k_dram*dramA_29*(1+drift)^3 -> 6.8387415 | H144: CY2026＝錨點（實績＋指引）；之後＝k × 設備市場模型分項 × (1＋份額漂移)^年
A145: 系統營收：NAND | B145: US$B | D145: =cy26_nand -> 4.5051978 | E145: =k_nand*nandA_27*(1+drift)^1 -> 5.9836339 | F145: =k_nand*nandA_28*(1+drift)^2 -> 6.7386124 | G145: =k_nand*nandA_29*(1+drift)^3 -> 7.1228821 | H145: CY2026＝錨點（實績＋指引）；之後＝k × 設備市場模型分項 × (1＋份額漂移)^年
A146: 出口管制：中國系統營收折損 | B146: US$B | E146: =-cn_sh*cut_sens_hi*(E143+E144+E145) -> -3.3423337 | F146: =-cn_sh*cut_sens_hi*(F143+F144+F145) -> -3.7573818 | G146: =-cn_sh*cut_sens_hi*(G143+G144+G145) -> -3.9738638 | H146: −中國占比 × 折損比例 × 系統營收；情境 C 自 CY2028 起 cutC，其餘為 0（Sens 另設）
A147: 系統營收 CY | B147: US$B | D147: =SUM(D143:D146) -> 19.826826 | E147: =SUM(E143:E146) -> 21.23365 | F147: =SUM(F143:F146) -> 23.870426 | G147: =SUM(G143:G146) -> 25.245723
A148: CSBG CY | B148: US$B | D148: =cy26_cs -> 9.556318 | E148: =D148*(1+g_cs27) -> 10.989766 | F148: =E148*(1+g_cs_A) -> 12.308538 | G148: =F148*(1+g_cs_A) -> 13.785562 | H148: CY2026＝錨點；CY2027 公司稱逾 15%；之後依情境
A149: B. 會計年度（C＝FY2025 … G＝FY2029；FY(t)＝CY(t−1) 下半＋CY(t) 上半）
...

Sheet Sources
A1: 來源（公司財報取自 SEC EDGAR 原文；法說取自逐字稿摘要）
A2: 公司：FY27 Q1 8-K 新聞稿（2026-10-21） | B2: https://www.sec.gov/Archives/edgar/data/707549/000070754926000052/lrcx_exhibitx991xq1x2027.htm
A3: 公司：FY27 Q1 10-Q（2026-10-22） | B3: https://www.sec.gov/Archives/edgar/data/707549/000070754926000054/lrcx-20260927.htm
A4: 公司：FY2026 10-K（2026-08-07） | B4: https://www.sec.gov/Archives/edgar/data/707549/000070754926000037/lrcx-20260628.htm
A5: 公司：FY26 Q4 8-K 新聞稿（2026-07-29） | B5: https://www.sec.gov/Archives/edgar/data/707549/000070754926000033/lrcx_exhibitx991xq4x2026.htm
A6: 公司：FY26 Q3 8-K 新聞稿（2026-04-22） | B6: https://www.sec.gov/Archives/edgar/data/707549/000070754926000020/lrcx_exhibitx991xq3x2026.htm
A7: 公司：FY26 Q2 8-K 新聞稿（2026-01-28） | B7: https://www.sec.gov/Archives/edgar/data/707549/000070754926000006/lrcx_exhibitx991xq2x2026.htm
A8: 公司：FY26 Q1 8-K 新聞稿（2025-10-22） | B8: https://www.sec.gov/Archives/edgar/data/707549/000070754925000082/lrcx_exhibitx991xq1x2026.htm
A9: 公司：FY25 Q4 8-K 新聞稿（2025-07-30） | B9: https://www.sec.gov/Archives/edgar/data/707549/000070754925000068/lrcx_exhibitx991xq4x2025.htm
A10: 公司：10-Q（FY26 Q1、Q2、Q3：客戶別占比） | B10: https://www.sec.gov/Archives/edgar/data/707549/000070754926000022/lrcx-20260329.htm
A11: SEC XBRL：EPS 歷史（基本、稀釋） | B11: https://data.sec.gov/api/xbrl/companyconcept/CIK0000707549/us-gaap/EarningsPerShareBasic.json
A12: Motley Fool：FQ1-27 法說逐字稿（WFE、客戶別、CSBG、稅率） | B12: https://www.fool.com/earnings/call-transcripts/2026/10/21/lam-research-lrcx-q1-2027-earnings-call-transcript/
A13: MarketBeat：FQ4-26 法說重點（6 月季客戶別、WFE low-$150B） | B13: https://www.marketbeat.com/instant-alerts/lam-research-q4-earnings-call-highlights-2026-07-29/
... A24: SemiAnalysis | B24: 未使用
