Workbook

Sheet README
A1: 瓦帳 v0.1.2 — 全市場 AI 資料中心 GW 唯一基準事實（20261028）
A2: 命題：市場總 GW 要與主要玩家 GW 對得上，再與資本支出、GPU／ASIC 顆數、記憶體、電廠與發電機組、電源散熱、AI 投資地圖個股逐環對得上；並加入與需求情景正交的基建延遲情景。
A3: 驅動 → 推導：In（Epoch 晶片功耗、玩家年底 MW、觀測、園區管線、延遲 D0–D2、世代組合、使用者分配）＋ TK_In（每 GW 係數、IF_FacilityGW）＋ SIL_In（顆數、情景係數）→ Players（玩家 × 年 IT GW）→ Matrix（營運者 × 使用者）→ Pipeline（上線事件 × 延遲）→ Deploy（需求 × 延遲 3×3）→ C0／C1／Compare（對帳）→ Interface（WIF_）→ Checks（WGOV_Errors＝0）。
A4: 單位（規劃書 r1）：主口徑 IT GW＝TK GW（IT 關鍵電力）；設施電力＝IT × TK IF_FacilityGW（1.2）。公司標設施者 ÷ IF_FacilityGW；口徑未說明者基準取 IT 讀法，Players 另列設施讀法；Epoch 晶片功耗 × k_chip2it。
A5: 頁面：README｜In 輸入｜TK_In、SIL_In 鏡像（綠字）｜Players 玩家 × 年｜Matrix 營運者 × 使用者｜Pipeline 園區管線 × 延遲｜Deploy 市場總 GW 需求 × 延遲｜C0 由下而上 vs 第三方｜C1 資本支出對帳｜Compare 與 Siliconomics 成本等值 GW｜Interface WIF_｜Checks｜Decisions｜DB_Evidence｜Sources｜Requests。
A6: v0.1 範圍：C0、C1、延遲管線（D0–D2）、WIF_ 輸出；C2–C7 自 v0.2 起。第 2 階段：填入 evidence_raw 證據（只用 C 段判屬實或已更正的列；DB_Evidence 頁列全部證據與判定），延遲參數依 B_delay 校準。
A7: 第 3 階段：新增 CapexGW 頁（甲2：資本支出推得 GW；MSFT、GOOGL、AMZN、META、ORCL、CRWV、NBIS 2027 起進主路徑）；Interface 另出 _SiteOnly（只有 甲）；WIF_Coverage_<yyyy>。下游取用 2027 年後數值前看覆蓋率。
A8: v0.1.1（改名 Wattonomics／瓦帳）：新增 Funding（玩家 × 年資金來源、循環融資 17 條）、FundRaw（F 段證據＋G 段判定）、Facility（每 IT GW 廠房拆分與市場層、自建發電）、SegIn（AI半導體 次產業比例鏡像）、Spend（年 × 項目市場金額）；C1 加廣義口徑（資本支出＋尚未起租變化）；Interface 增 WIF_Funding_*、WIF_Spend_*、WIF_Facility_*。
A9: v0.1.2：套用 H 段（API 旗標人工複核）更正——證據檔 79 筆、In 輸入 19 格（cp_msft_abl 改 336＋336 MW-IT、xfmr_gva 2.1／2.67／3.15、fac_gen_px 低 0.5），FundRaw F#31、F#199、F#222 改不採用（採購或投資存量，非融資）；園區候選（S 段 409 列，site_pipeline）經 API 回查與 I 段未參與代理開原文抽查後合併：新增 17 列（計入 13 列）、更正既有 20 列（Fairwater 拆分、Ports Pike 首批 800 MW 至 2031、Humain 1.7 GW 提前到 2027、Milam 308＋445、Jupiter 已知延遲刪除）、3 列改計入（Stargate UAE、Colossus 2、Mistral 96 MW）。Hyperion 5 GW、SoftBank 苫小牧依判斷題預設不入。
A10: 顏色：藍字＝輸入；黑字＝公式；綠字＝跨頁或外部鏡像；淡黃底＝關鍵輸出；亮黃底＝待證據或預設待決。
A11: Excel 優先：要改輸入，直接改 In 頁藍字；builder 重建時讀回（--base）。公式頁不要手改。下游只讀 Interface 的 WIF_ 名稱（經快照）。
A12: 版本命名：YYYYMMDD_Wattonomics_vX.Y.xlsx；model/CURRENT 記錄現行檔名；data/CURRENT_SNAPSHOT 指向現行快照。

Sheet In
A1: In — 瓦帳輸入（藍字＝輸入，由本活頁簿擁有；要改值直接改本頁，builder 重建時以 --base 讀回）。純量列：H／I／J＝低／基準／高，具名範圍＝鍵（I 欄）；年度列：H–Q＝2023–2032；T1 分配表、T2 園區表見節標題
A2: 標記：Verified／Interested-party（寫明是誰）／Analogy／Assumed（給低／高）／Derived（寫明換算）／待證據（值留空）。來源 ID 見 Sources 頁；說明欄的 A#n／B#n／D#n＝evidence_raw 列號（DB_Evidence 頁，含 C 段判定）。口徑：IT／設施／未說明／晶片（主口徑 IT GW；設施 ÷ IF_FacilityGW；未說明者基準取 IT 讀法）。S 欄＝輸入列類型（治理檢查用）
A4: 鍵 | B4: 項目 | C4: 口徑 | D4: 單位 | E4: 標記 | F4: 來源 ID | G4: 說明 | H4: 2023 | I4: 2024 | J4: 2025 | K4: 2026 | L4: 2027 | M4: 2028 | N4: 2029 | O4: 2030 | P4: 2031 | Q4: 2032 | S4: 類型
A5: S1. 單位換算與共用參數（主口徑 IT GW＝TK GW；設施電力＝IT × TK IF_FacilityGW）
A6: g_ITtoFac | B6: 公司 IT 值 → GW 帳主口徑（IT→IT）換算係數 | C6: — | D6: x | E6: Derived | F6: SRC_GL_003 | G6: Requests R1 裁定（2026-10-28）：TK Interface 每 GW＝IT 關鍵電力，主口徑＝IT GW，係數＝1；設施電力另列＝IT × TK_FacilityGW（TK_In） | I6: 1 | S6: 1
A7: k_chip2it | B7: Epoch 晶片功耗 → IT 電力換算係數 | C7: — | D7: x | E7: Analogy | F7: SRC_GL_203 | G7: 低 1.65＝repo mw.conv.itPerTdp；高 2.08＝Epoch 設施係數 2.5 ÷ 1.2；C 段 6.4：A 段 × 1.98 與 Epoch × 2.5 不一致 | H7: 1.65 | I7: 1.85 | J7: 2.08 | S7: 1
A8: asof | B8: 評價時點（小數年；2026-10-28） | C8: — | D8: 年 | E8: Derived | F8: SRC_GL_004 | G8: 2026 ＋（9 ＋ 28/31）÷ 12；延遲只作用於此時點之後的上線量 | I8: 2026.825 | S8: 1
A9: tolband | B9: 對帳容許帶（±） | C9: — | D9: % | E9: Assumed | F9: SRC_GL_003 | G9: 規劃書 G6 預設 ±15% | H9: 0.1 | I9: 0.15 | J9: 0.2 | S9: 1
A10: lag_bldg | B10: 建物資本支出提前入帳月數 | C10: — | D10: 月 | E10: Assumed | F10: SRC_GL_004 | G10: 工作單 C1：12–24 月；D#14 建物工期 12–24 月（屬實） | H10: 12 | I10: 18 | J10: 24 | S10: 1
A11: g_lt | B11: 長期年新增 GW 成長率（2030–2032 收斂目標） | C11: — | D11: % | E11: Assumed | F11: SRC_GL_004 | G11: 工作單 Deploy：2029 年增率線性收斂到長期成長率（chat 端第 2 階段指示） | H11: 0.05 | I11: 0.1 | J11: 0.15 | S11: 1
A12: S1b. 甲2 資本支出推得 GW（MSFT、GOOGL、AMZN、META、ORCL、CRWV、NBIS；2027 起主路徑）
A13: ai_sh | B13: 資本支出 AI 占比（全公司資本支出中用於 AI 資料中心的比例；各家未覆寫者） | C13: — | D13: % | E13: Assumed | F13: SRC_GL_004 | G13: chat 端第 3 階段指示 1；依證據逐家覆寫見 ai_<玩家> | H13: 0.75 | I13: 0.85 | J13: 0.95 | S13: 1
A14: ai_amzn | B14: Amazon 資本支出 AI 占比覆寫（AWS 占淨增加比） | C14: — | D14: % | E14: Derived | F14: SRC_GL_030 | G14: amazon/company.json mag.capex.netAddBySegFY FY2025：AWS 96.5 ÷ 全公司 142.4＝0.68（零售物流非 AI）；AWS 內 AI 占比未知，以 AWS 占比代（偏高） | H14: 0.6 | I14: 0.68 | J14: 0.75 | S14: 1
A15: cap_g_ext | B15: 個股模型最後一年之後的資本支出年增（甲2 外推） | C15: — | D15: % | E15: Assumed | F15: SRC_GL_004 | G15: 共識只到 FY28–FY29（Meta 只有 2026 指引）；之後以本值外推，基準＝g_lt；最早一年之前取最早值 | H15: 0 | I15: 0.1 | J15: 0.15 | S15: 1
A16: S1c. 中國 2027 年後路徑（Rystad：容量 × AI 占比，幾何／線性內插；2031–32 用 g_lt）
A17: cn_tot26 | B17: 中國資料中心總容量 2026 年底 | C17: 未說明 | D17: GW | E17: Analogy | F17: SRC_GL_201 | G17: B#51（屬實；Rystad）；單一來源（Rystad），區間 ±10% [Assumed]；Players 用基準 | H17: 36 | I17: 40 | J17: 44 | S17: 1
A18: cn_tot30 | B18: 中國資料中心總容量 2030 | C18: 未說明 | D18: GW | E18: Analogy | F18: SRC_GL_201 | G18: B#51（屬實；Rystad >60 GW 取下限）；單一來源（Rystad），區間 60–70（Rystad「>60」） [Assumed]；Players 用基準 | H18: 60 | I18: 60 | J18: 70 | S18: 1
A19: cn_sh26 | B19: 中國 AI／HPC 占比 2026 | C19: — | D19: % | E19: Analogy | F19: SRC_GL_201 | G19: B#51（屬實；Rystad）；單一來源（Rystad），區間 ±10% [Assumed]；Players 用基準 | H19: 0.351 | I19: 0.39 | J19: 0.429 | S19: 1
A20: cn_sh30 | B20: 中國 AI／HPC 占比 2030 | C20: — | D20: % | E20: Analogy | F20: SRC_GL_201 | G20: B#51（屬實；Rystad）。中國 2027–30＝2026 年底 × (容量 × 占比) 比值，容量幾何內插、占比線性內插 [Assumed]；單一來源（Rystad），區間 ±10% [Assumed]；Players 用基準 | H20: 0.432 | I20: 0.48 | J20: 0.528 | S20: 1
A21: S2. 基建延遲參數（D0 準時；D1 基準延遲；D2 嚴重延遲）
A22: dly_d1_s | B22: D1：每年排定新 GW 延後的比例 | C22: — | D22: % | E22: Derived | F22: SRC_GL_202 | G22: D#15（Sightline，屬實）：2025 26%（容量）延遲；2026 預測 30–50%；取中下。另 10%（專案數）延後商轉，單位不同不可相加（C 段第 2 節） | H22: 0.25 | I22: 0.35 | J22: 0.45 | S22: 1
A23: dly_d1_m | B23: D1：延後量的延遲月數 | C23: — | D23: 月 | E23: Derived | F23: SRC_GL_202 | G23: D#16 Oracle 部分站 12、D#19 Nebius NJ 首期延遲 6–7（實際 10–11 月對目標 4 月）；low 3 [Assumed]（H 段：刪除 Denton D#18，原頁無月數） | H23: 3 | I23: 6 | J23: 12 | S23: 1
A24: dly_d2_bind | B24: D2：2027–28 未確保電力的新 GW 再延比例 | C24: — | D24: % | E24: Derived | F24: SRC_GL_202 | G24: D#2、D#3（大負載併網 48 月以上）、D#5（發電側併網 48–60 月，LBNL 轉述；84 為 PJM 平均）、D#7、D#8（渦輪 ≥36 月）、D#11（升壓變壓器 37 月）長於建物工期 D#14；反證 D#25（表後發電）、D#7（許多案子渦輪不卡關）→ 不高於 50% | H24: 0.3 | I24: 0.4 | J24: 0.5 | S24: 1
A25: dly_d2_m | B25: D2：綁定部分再延月數 | C25: — | D25: 月 | E25: Derived | F25: SRC_GL_202 | G25: B_summary 5.3：再延 12 個月 | H25: 12 | I25: 12 | J25: 12 | S25: 1
A26: dly_d2_y0 | B26: D2 適用起年（原排定上線年） | C26: — | D26: 年 | E26: Derived | F26: SRC_GL_202 | G26: B_summary 5.3：2027–2028 新增 GW | I26: 2027 | S26: 1
A27: dly_d2_y1 | B27: D2 適用迄年（原排定上線年） | C27: — | D27: 年 | E27: Derived | F27: SRC_GL_202 | G27: 同上 | I27: 2028 | S27: 1
A28: S3. 玩家最新觀測（觀測年：年底值＝觀測值＋觀測後至年底的園區上線量）
A29: obs_msft | B29: Microsoft 自有 AI 在役 MW-IT（FY26 末） | C29: IT | D29: MW | E29: Derived／Assumed | F29: SRC_GL_010 | G29: microsoft/company.json mag.mw.aiOpenIT（三法交叉，未用營收）；A#13 同值 | H29: 3500 | I29: 4500 | J29: 5500 | S29: 1
A30: obsd_msft | B30: Microsoft 觀測時點 | C30: — | D30: 年 | E30: Verified | F30: SRC_GL_010 | G30: 2026-06-30 | I30: 2026.5 | S30: 1
A31: obschip_googl | B31: Alphabet 晶片功耗（2026Q2；× Google 倍數＝IT） | C31: 晶片 | D31: MW | E31: Derived | F31: SRC_GL_020 | G31: alphabet/company.json scenarios.mwPath.note（repo 由 Epoch AI Chip Owners 晶片功耗整理 3,841 MW）；IT＝本值 × Google 倍數（ovr25_googl ÷ 2025 晶片功耗），原 × 1.65＝6,338 | I31: 3841 | S31: 1
A32: obsd_googl | B32: Alphabet 觀測時點 | C32: — | D32: 年 | E32: Verified | F32: SRC_GL_020 | G32: 2026-06-30 | I32: 2026.5 | S32: 1
A33: obs_amzn | B33: Amazon AI 在役 MW-IT（2026Q2） | C33: IT | D33: MW | E33: Derived／Assumed | F33: SRC_GL_030 | G33: amazon/company.json mag.mw.aiInServiceIT（第三方估計）；A#40 同值 | H33: 2000 | I33: 2600 | J33: 3300 | S33: 1
A34: obsd_amzn | B34: Amazon 觀測時點 | C34: — | D34: 年 | E34: Verified | F34: SRC_GL_030 | G34: 2026-06-30 | I34: 2026.5 | S34: 1
A35: obs_orcl | B35: Oracle 已連網 MW-IT（FY27Q1 末） | C35: IT | D35: MW | E35: Derived | F35: SRC_GL_040 | G35: oracle/company.json fleet.openMw（FY26 末 1,835＋Q1 交付 850 ÷ 1.2）；A#64、A#65（屬實） | I35: 2543 | S35: 1
A36: obsd_orcl | B36: Oracle 觀測時點 | C36: — | D36: 年 | E36: Verified | F36: SRC_GL_040 | G36: 2026-08-31 | I36: 2026.667 | S36: 1
A37: obs_crwv | B37: CoreWeave active power MW（2026Q2） | C37: IT | D37: MW | E37: Interested-party | F37: SRC_GL_050 | G37: A#81（屬實）；2026 年底已有指引值，本觀測不進計算 | I37: 1500 | S37: 1
A38: obsd_crwv | B38: CoreWeave 觀測時點 | C38: — | D38: 年 | E38: Verified | F38: SRC_GL_050 | G38: 2026-06-30 | I38: 2026.5 | S38: 1
A39: obs_xai | B39: SpaceX／xAI nameplate compute（2026Q2） | C39: 未說明 | D39: MW | E39: Interested-party | F39: SRC_GL_201 | G39: B#46（屬實；SpaceX 季報，剛上市）；2026 年底已有目標值，本觀測不進計算 | I39: 1400 | S39: 1
A40: obsd_xai | B40: SpaceX／xAI 觀測時點 | C40: — | D40: 年 | E40: Verified | F40: SRC_GL_201 | G40: 2026-06-30 | I40: 2026.5 | S40: 1
A41: S3b. 2025 年底 IT 覆寫與區間（C 段更正；Epoch 推得者另依 k_chip2it 區間）
A42: ovr25_googl | B42: Google 2025 年底 AI IT（C 段 5.1 更正） | C42: IT | D42: MW | E42: Derived | F42: SRC_GL_203 | G42: C 段 5.1：TPU × 1.45、NVIDIA × 1.65 再酌減部署落差；4.9 只作上緣。Google 倍數＝本值 ÷ 2025 晶片功耗，用於 2023–24 與 2026 觀測 | H42: 3900 | I42: 4300 | J42: 4900 | S42: 1
A43: ovr25_amzn | B43: Amazon 2025 年底 AI IT 合計（C 段 5.2 更正） | C43: IT | D43: MW | E43: Derived | F43: SRC_GL_203 | G43: C 段 5.2：NVIDIA 1.0（0.7–1.4）＋Trainium 約 1.2；Amazon 倍數＝本值 ÷ 2025 晶片功耗 | H43: 1900 | I43: 2200 | J43: 2600 | S43: 1
A44: msft_guardian | B44: Microsoft AI 容量反證（Guardian 估，2026-08） | C44: 未說明 | D44: MW | E44: Analogy | F44: SRC_GL_203 | G44: D#24 補充（C 段屬實）：Guardian 估約 1.2 GW，對照公司稱 5 GW；Microsoft 稱估計不準。單點報導，區間 1.0–1.5 [Assumed]；Players 以基準 1.2 放寬 2025 區間下緣，不改基準 | H44: 1000 | I44: 1200 | J44: 1500 | S44: 1
A45: rng25_neo | B45: 其他新雲 2025 年底區間 | C45: IT | D45: MW | E45: Assumed | F45: SRC_GL_205 | G45: A.md 其他新雲最佳估計（C 段 6.1 加總採用）；基準須＝Y1 mw_neo 2025（Checks K11） | H45: 300 | I45: 500 | J45: 800 | S45: 1
A46: rng25_cn | B46: 中國 2025 年底 AI 區間（設施） | C46: 設施 | D46: MW | E46: Assumed | F46: SRC_GL_203 | G46: C 段 6.2：Rystad 32 GW × AI 占比 0.3–0.35（2025 占比 Rystad 未給）；基準須＝Y1 mw_cn 2025 | H46: 8000 | I46: 10000 | J46: 12000 | S46: 1
A47: rng26_cn | B47: 中國 2026 年底 AI 區間（設施） | C47: 設施 | D47: MW | E47: Derived | F47: SRC_GL_201 | G47: B_summary 第 2 節：12–16 GW（B#51 Rystad 40 GW × 39%＝15.6；SemiAnalysis >24 GW 總量只佐證）；chat 端指示基準 14；基準須＝Y1 mw_cn 2026 | H47: 12000 | I47: 14000 | J47: 16000 | S47: 1
A48: other_incl_china | B48: 開關：Epoch『Other』是否含中國買家晶片（1＝含 → 『其他』用扣除中國後的 oth_excn；0＝不含 → 用 oth_full） | C48: — | D48: 開關 | E48: Assumed | F48: SRC_GL_203 | G48: C 段 A#116：Epoch 擁有者表沒有中國類，中國買家的 NVIDIA／AMD 晶片很可能在 Other；GW 帳另有中國列（Rystad），不扣會重複。Decisions GL01-22 | H48: 0 | I48: 1 | J48: 1 | S48: 1
A49: oth_full | B49: 『其他』2025 年底（Epoch Other 扣新雲；不扣中國） | C49: IT | D49: MW | E49: Assumed | F49: SRC_GL_203 | G49: C 段 6.2：1.8–3.0 GW 設施 ÷ 1.2＝1.5–2.5 IT（原基準 2.4 設施＝2.0 IT） | H49: 1500 | I49: 2000 | J49: 2500 | S49: 1
A50: oth_excn | B50: 『其他』2025 年底（扣除中國部分；無法拆分，[Assumed]） | C50: IT | D50: MW | E50: Assumed | F50: SRC_GL_203 | G50: Epoch Other 中的中國 NVIDIA／AMD 部分無證據可拆（已搜尋：中國 2025 NVIDIA 晶片功耗未找到；B#57 H200 40 萬顆為 2026 許可）。基準降為 1.0（0.5–2.0）IT GW（chat 端核對指示 4） | H50: 500 | I50: 1000 | J50: 2000 | S50: 1
A51: S4. 合約與目標（對照用，不進加總）
A52: ctr_oai_90d | B52: OpenAI 近 90 天新簽容量（含 AWS 2 GW） | C52: 未說明 | D52: GW | E52: Interested-party | F52: SRC_GL_201 | G52: B#3（C 段更正：Three of those 10 gigawatts）；10 GW 簽約總量為 OpenAI 自述 | I52: 3 | S52: 1
A53: ctr_crwv | B53: CoreWeave 已簽約電力（contracted） | C53: 未說明 | D53: GW | E53: Interested-party | F53: SRC_GL_200 | G53: A#85（屬實；CEO 法說） | I53: 4.2 | S53: 1
A54: ctr_nbis | B54: Nebius 已簽約電力（2026 年底目標 5 GW） | C54: 未說明 | D54: GW | E54: Interested-party | F54: SRC_GL_061 | G54: nebius consensus companyGuidance.FY26.contractedPowerGW 5.0；A#98 >3.5 GW（未抽查） | I54: 3.5 | S54: 1
A55: ctr_orcl_oai | B55: Oracle–OpenAI 新增 Stargate 容量（不含 Abilene） | C55: 未說明 | D55: GW | E55: Interested-party | F55: SRC_GL_200 | G55: A#71（未抽查）；四站設施 6.9 GW 見 T2（A#72–75 屬實） | I55: 4.5 | S55: 1
A56: ctr_amzn_ant | B56: Anthropic–AWS 合約上限 | C56: 未說明 | D56: GW | E56: Interested-party | F56: SRC_GL_200 | G56: A#45（C 段更正標記）；不進加總（園區列 New Carlisle 已計） | I56: 5 | S56: 1
A57: ctr_msft_ant | B57: Anthropic–Azure：$30B 確定（GW 未揭露）＋額外至多 1 GW（上限） | C57: 未說明 | D57: GW | E57: Interested-party | F57: SRC_GL_200 | G57: A#19、B#33（H 段更正：$30B Azure 確定採購，GW 未揭露；另加額外至多 1 GW，上限、非確定量；取代 C 段『全案上限 1 GW』）；2026-11 至 2033-05 付款；上線量未揭露 | I57: 1 | S57: 1
A58: ctr_googl_ant | B58: Anthropic–Google Cloud TPU（2026 上線） | C58: 未說明 | D58: GW | E58: Interested-party | F58: SRC_GL_200 | G58: A#29（屬實；well over 1 GW） | I58: 1 | S58: 1
A59: tgt_xai_27 | B59: xAI 2027 年底宣稱（Musk「接近 10 GW」；不入主路徑，只作 Compare 敏感度） | C59: 未說明 | D59: GW | E59: Interested-party | F59: SRC_GL_201 | G59: B#46（屬實為引述正確；Interested-party 單一說法，SpaceX 剛上市；Musk 自稱 20 GW 不會達成）。主路徑 xAI 2027 起＝2026 年底 2 GW＋T2 園區（無）；Compare 頁列『主路徑＋xAI 宣稱增量』 | I59: 10 | S59: 1
A60: tgt_msft_32 | B60: Microsoft 2032 全公司容量（>38 GW，約 1/3 AI；未納入） | C60: 未說明 | D60: GW | E60: Interested-party | F60: SRC_GL_200 | G60: A#7、A#8（屬實；記者引知情人士，全部負載） | I60: 38 | S60: 1
A61: lease_nc_msft | B61: Microsoft 未起租租約（FY26 末） | C61: — | D61: $B | E61: Verified | F61: SRC_GL_010 | G61: microsoft/company.json mag.leases.notCommenced（10-K） | I61: 329.1 | S61: 1
A62: lease_nc_googl | B62: Alphabet 未起租租約（2026Q2） | C62: — | D62: $B | E62: Verified | F62: SRC_GL_020 | G62: alphabet/company.json mag.balance.leases.uncommenced（10-Q） | I62: 85.2 | S62: 1
A63: lease_nc_amzn | B63: Amazon 未起租租約（2026Q2） | C63: — | D63: $B | E63: Verified | F63: SRC_GL_030 | G63: amazon/company.json leases.facts.notCommenced（10-Q） | I63: 137.214 | S63: 1
A64: S7. 廠房資本支出拆分（每 IT GW，US$B；合計＝TK IF_CapexFacility 12.67；P_facility_power.md 建議表，G 段核對）
A65: fac_dist | B65: 配電（中低壓開關、廠內變壓器、PDU、母線、電纜） | C65: — | D65: $B/IT GW | E65: Derived | F65: SRC_GL_301 | G65: P#10（McKinsey 電力 37.5% × 配電 55%）、P#19；G 段 §5 屬實 | H65: 2 | I65: 2.55 | J65: 3.4 | S65: 1
A66: fac_gen_mult | B66: 備援發電機裝置容量倍數（GW genset ／ IT GW） | C66: — | D66: x | E66: Assumed | F66: SRC_GL_302 | G66: G 段 P28 建議：手冊含 20–25% 餘裕與機械負載為 1.5–1.9×（未加 N+1），基準 1.6；低 0＝Fairwater Atlanta 不設發電機（P#29）；高 2.4＝2N。原 P 段 1.4 | H66: 0 | I66: 1.6 | J66: 2.4 | S66: 1
A67: fac_gen_px | B67: 備援發電機單價（$M／MW genset） | C67: — | D67: $M/MW | E67: Analogy（基準）／Assumed（區間） | F67: SRC_GL_301 | G67: P#27（NREL 約 $1 | H67: 0.5 | I67: 1 | J67: 1.2 | S67: 1
A68: fac_ups | B68: UPS 與電池 | C68: — | D68: $B/IT GW | E68: Derived | F68: SRC_GL_301 | G68: 備援合計 16.9% × 12.67 ≈ 2.14 扣 genset 1.40（G 段 §5 屬實） | H68: 0.5 | I68: 0.75 | J68: 1.5 | S68: 1
A69: fac_cool | B69: 冷卻（冷卻塔、冰水機、乾冷器、CDU、液冷管路） | C69: — | D69: $B/IT GW | E69: Derived | F69: SRC_GL_301 | G69: P#11（McKinsey 15%）；Epoch 約 1.9；G 段：AI 液冷園區高值（3.5–5.2）機率不低 | H69: 1.5 | I69: 1.9 | J69: 3.5 | S69: 1
A70: fac_bldg | B70: 建築（核心殼體與結構） | C70: — | D70: $B/IT GW | E70: Derived | F70: SRC_GL_301 | G70: P#12（McKinsey 13.5%；標籤順序對應為推定，G 段 §5） | H70: 1.4 | I70: 1.7 | J70: 2.3 | S70: 1
A71: fac_labor | B71: 施工人工與工程設計 | C71: — | D71: $B/IT GW | E71: Derived | F71: SRC_GL_301 | G71: P#13（McKinsey 22–25%） | H71: 2.4 | I71: 2.95 | J71: 3.4 | S71: 1
A72: fac_prof0 | B72: 其他專業服務（試運轉、顧問、許可；未扣 genset 調整前） | C72: — | D72: $B/IT GW | E72: Derived | F72: SRC_GL_301 | G72: P#14（McKinsey 5–10%）；Facility 頁實際值＝本值 −（genset 新基準 − 原 1.40）（G 段建議由其他項吸收，chat 端指示『差額從其他扣』） | H72: 0.6 | I72: 0.9 | J72: 1.3 | S72: 1
A73: fac_net | B73: 網路、消防、安防、BMS | C73: — | D73: $B/IT GW | E73: Derived | F73: SRC_GL_301 | G73: McKinsey 網路 2–3%（G 段 §5 屬實） | H73: 0.25 | I73: 0.3 | J73: 0.9 | S73: 1
A74: fac_land | B74: 土地 | C74: — | D74: $B/IT GW | E74: Derived | F74: SRC_GL_301 | G74: P#23（Epoch 土地＋併網 <1%） | H74: 0.05 | I74: 0.2 | J74: 0.9 | S74: 1
A75: fac_gen_px0 | B75: 原 P 段 genset 金額基準（1.4 GW × 1.0） | C75: — | D75: $B/IT GW | E75: Derived | F75: SRC_GL_301 | G75: P_facility_power.md 第 1 節拆分表；用於計算 genset 調整差額 | H75: 1.4 | I75: 1.4 | J75: 1.4 | S75: 1
A76: S8. 自建發電與實物量（自建發電不在 12.67 內）
A77: self_gw | B77: 自建發電容量（GW gen ／ IT GW；僅有自建的園區） | C77: — | D77: x | E77: Assumed | F77: SRC_GL_301 | G77: P#38（設施 1.2 × 備用 1.2；G 段算術屬實） | H77: 1.1 | I77: 1.44 | J77: 1.8 | S77: 1
A78: self_px | B78: 自建發電單價（$M／MW gen） | C78: — | D78: $M/MW | E78: Analogy | F78: SRC_GL_301 | G78: P#32–35（CCGT 1.5–2.5、航改 1.2–2.2、表後燃機／往復機 0.8–1.2）；基準使 1.44 × 1.6＝2.3 $B（P.md 第 2 節 1.2／2.3／3.2） | H78: 0.8 | I78: 1.6 | J78: 2.2 | S78: 1
A79: self_sh | B79: 新增 IT GW 中自建發電的比例 | C79: — | D79: % | E79: Assumed | F79: SRC_GL_004 | G79: chat 端 v0.1.1 指示 4；佐證：P#39 Cleanview 表後規劃 90 GW、運轉 2 GW（延遲大） | H79: 0.1 | I79: 0.2 | J79: 0.35 | S79: 1
A80: xfmr_gva | B80: 主變壓器裝置容量（GVA ／ IT GW；含一台退出備援） | C80: — | D80: GVA | E80: Derived | F80: SRC_GL_302 | G80: P#50（H 段更正）：ModulEdge 60 MW IT 一台退出 4×40＝160 MVA → 2.67、3×63 → 3.15；ComEd 4×100 MVA ÷ 187.5 MW IT ≈ 2.13；只影響 Facility 實物量顯示 | H80: 2.1 | I80: 2.67 | J80: 3.15 | S80: 1
A81: btm_plan | B81: 美國表後自建發電：規劃 | C81: — | D81: GW | E81: Analogy | F81: SRC_GL_301 | G81: P#39（Cleanview 59 案；G 段屬實）；延遲佐證 | H81: 5 | I81: 90 | J81: 90 | S81: 1
A82: btm_run | B82: 美國表後自建發電：運轉中 | C82: — | D82: GW | E82: Analogy | F82: SRC_GL_301 | G82: P#39：運轉約 2 GW（2.2%）；2026 年底 2.8–3.2；延遲佐證 | H82: 2 | I82: 2 | J82: 3.2 | S82: 1
A83: spend_nnv_hold | B83: Spend：非 NVIDIA 每 GW IT capex ÷ VR200（無 NonNV 平台組合，取 TK 持有比平均） | C83: — | D83: x | E83: Derived | F83: SRC_GL_001 | G83: TK IF_NonNV_Hold：AMD 0.85、TPU 0.70、Trn 0.61、OAI 0.80、Ascend 0.55、Maia 0.50 平均 0.67；持有比借用為 IT capex 比（近似，規劃書第 6 節第 1 點） | H83: 0.5 | I83: 0.67 | J83: 0.85 | S83: 1
A84: S5. 玩家非 NVIDIA 占比覆寫（未列者＝市場 NonNV 比例）
A85: nnv_googl | B85: Alphabet（Google；TPU＋NVIDIA） 新增 GW 非 NVIDIA 占比 | C85: — | D85: % | E85: Derived | F85: SRC_GL_020 | G85: texts.mwFacts：Epoch 2025 年底 TPU 2,223 MW ÷（2,223＋730） | I85: 0.753 | S85: 1
A86: nnv_amzn | B86: Amazon（AWS；Trainium＋NVIDIA） 新增 GW 非 NVIDIA 占比 | C86: — | D86: % | E86: Derived | F86: SRC_GL_030 | G86: texts.mwYearEndNotes：Trainium2 約 1,220 ÷（1,220＋600） | I86: 0.67 | S86: 1
A87: nnv_crwv | B87: CoreWeave 新增 GW 非 NVIDIA 占比 | C87: — | D87: % | E87: Derived | F87: SRC_GL_050 | G87: fleet.generations 僅 NVIDIA 世代 | I87: 0 | S87: 1
A88: nnv_nbis | B88: Nebius 新增 GW 非 NVIDIA 占比 | C88: — | D88: % | E88: Derived | F88: SRC_GL_060 | G88: fleet.generations 僅 NVIDIA 世代 | I88: 0 | S88: 1
A89: nnv_wyfi | B89: WhiteFiber（雲端） 新增 GW 非 NVIDIA 占比 | C89: — | D89: % | E89: Derived | F89: SRC_GL_070 | G89: fleet.generations 僅 NVIDIA 世代 | I89: 0 | S89: 1
A90: nnv_xai | B90: SpaceX／xAI（Colossus；兼出租） 新增 GW 非 NVIDIA 占比 | C90: — | D90: % | E90: Derived | F90: SRC_GL_201 | G90: Colossus 為 NVIDIA（B#47：GB300） | I90: 0 | S90: 1
A91: S6. 個股模型財年結束月（C1 曆年→財年換算）
A92: fye_msft | B92: Microsoft（自有＋融資租賃 AI 在役） 財年結束月 | C92: — | D92: 月 | E92: Verified | F92: SRC_GL_010 | G92: company.json calendar.fiscalYearEndMonth | I92: 6 | S92: 1
A93: fye_googl | B93: Alphabet（Google；TPU＋NVIDIA） 財年結束月 | C93: — | D93: 月 | E93: Verified | F93: SRC_GL_020 | G93: company.json calendar.fiscalYearEndMonth | I93: 12 | S93: 1
A94: fye_amzn | B94: Amazon（AWS；Trainium＋NVIDIA） 財年結束月 | C94: — | D94: 月 | E94: Verified | F94: SRC_GL_030 | G94: company.json calendar.fiscalYearEndMonth | I94: 12 | S94: 1
A95: fye_orcl | B95: Oracle（OCI；含承租 Stargate 站點） 財年結束月 | C95: — | D95: 月 | E95: Verified | F95: SRC_GL_040 | G95: company.json calendar.fiscalYearEndMonth | I95: 5 | S95: 1
A96: fye_crwv | B96: CoreWeave 財年結束月 | C96: — | D96: 月 | E96: Verified | F96: SRC_GL_050 | G96: company.json calendar.fiscalYearEndMonth | I96: 12 | S96: 1
A97: fye_nbis | B97: Nebius 財年結束月 | C97: — | D97: 月 | E97: Verified | F97: SRC_GL_060 | G97: company.json calendar.fiscalYearEndMonth | I97: 12 | S97: 1
A98: fye_wyfi | B98: WhiteFiber（雲端） 財年結束月 | C98: — | D98: 月 | E98: Verified | F98: SRC_GL_070 | G98: company.json calendar.fiscalYearEndMonth | I98: 12 | S98: 1
A99: fye_meta | B99: Meta 財年結束月 | C99: — | D99: 月 | E99: Verified | F99: SRC_GL_200 | G99: Meta 財年＝曆年（A#63 8-K Ex.99.1 期末 2026-09-30 為第三季） | I99: 12 | S99: 1
A100: Y0. Epoch AI 晶片功耗（MW，晶片層；IT＝× 倍數：Google、Amazon 用 C 段 2025 更正值 ÷ 2025 晶片功耗，其他用 k_chip2it）
A101: chip_msft | B101: Microsoft（自有＋融資租賃 AI 在役） 擁有 AI 晶片功耗（年底） | C101: 晶片 | D101: MW | E101: Analogy | F101: SRC_GL_200 | G101: A#10、A#11（屬實；Epoch AI Chip Owners，NVIDIA＋AMD；累計未扣退役） | I101: 861.5 | J101: 2015.7 | S101: 2
...

Sheet TK_In
A1: TK_In — Tokenomics 取數（只讀鏡像；權威在 Tokenomics）：20261025_Tokenomics_v21.7.xlsx（v21.7，commit 91d541f，擷取 2026-10-27）。同一份快照與 Siliconomics 相同（siliconomics/data/tokenomics_snapshot_v21.7.json），不另抽；綠字不得修改
A2: 快照註記：主值取「基準」成本情境；低成本／高成本只作敏感度。每 GW＝IT 關鍵電力（Tokenomics Interface 第 1 列）。
A4: 名稱（TK） | B4: 世代／項目 | C4: 本庫名稱 | D4: 低 | E4: 基準 | F4: 高 | G4: 單位 | H4: TK 位置
A5: IF_RacksPerGW | B5: Hopper H100 | C5: TK_RacksPerGW_H100 | D5: 22439 | E5: 22439 | F5: 22439 | G5: 架 | H5: Interface!C6:Q6
A6: IF_RacksPerGW | B6: GB200 NVL72 | C6: TK_RacksPerGW_GB200 | D6: 6969 | E6: 6969 | F6: 6969 | G6: 架 | H6: Interface!C6:Q6
A7: IF_RacksPerGW | B7: GB300 NVL72 | C7: TK_RacksPerGW_GB300 | D7: 6764 | E7: 6764 | F7: 6764 | G7: 架 | H7: Interface!C6:Q6
A8: IF_RacksPerGW | B8: VR200 NVL72 | C8: TK_RacksPerGW_VR200 | D8: 4052 | E8: 4052 | F8: 4052 | G8: 架 | H8: Interface!C6:Q6
A9: IF_RacksPerGW | B9: Rubin Ultra（MGX NVL 單架，72 GPU） | C9: TK_RacksPerGW_RU | D9: 2705 | E9: 2705 | F9: 2705 | G9: 架 | H9: Interface!C6:Q6
A10: IF_GPUsPerGW | B10: Hopper H100 | C10: TK_GPUsPerGW_H100 | D10: 718048 | E10: 718048 | F10: 718048 | G10: 顆 | H10: Interface!C7:Q7
A11: IF_GPUsPerGW | B11: GB200 NVL72 | C11: TK_GPUsPerGW_GB200 | D11: 501768 | E11: 501768 | F11: 501768 | G11: 顆 | H11: Interface!C7:Q7
A12: IF_GPUsPerGW | B12: GB300 NVL72 | C12: TK_GPUsPerGW_GB300 | D12: 487008 | E12: 487008 | F12: 487008 | G12: 顆 | H12: Interface!C7:Q7
A13: IF_GPUsPerGW | B13: VR200 NVL72 | C13: TK_GPUsPerGW_VR200 | D13: 291744 | E13: 291744 | F13: 291744 | G13: 顆 | H13: Interface!C7:Q7
A14: IF_GPUsPerGW | B14: Rubin Ultra（MGX NVL 單架，72 GPU） | C14: TK_GPUsPerGW_RU | D14: 194760 | E14: 194760 | F14: 194760 | G14: 顆 | H14: Interface!C7:Q7
A15: IF_CapexIT | B15: Hopper H100 | C15: TK_CapexIT_H100 | D15: 21.420269 | E15: 27.510214 | F15: 34.120743 | G15: $B | H15: Interface!C9:Q9
A16: IF_CapexIT | B16: GB200 NVL72 | C16: TK_CapexIT_GB200 | D16: 20.63939 | E16: 24.015174 | F16: 27.650204 | G16: $B | H16: Interface!C9:Q9
... A63: IF_FacilityGW | B63: Rubin Ultra（MGX NVL 單架，72 GPU） | C63: TK_FacilityGW_RU | D63: 1.1 | E63: 1.2 | F63: 1.3 | G63: GW | H63: model/20261025_Tokenomics_v21.7.xlsx Interface!C8:Q8（快照未含；直接讀活頁簿，commit 730b6a5，SRC_GL_006）

Sheet SIL_In
A1: SIL_In — Siliconomics 取數（只讀鏡像；權威在 AI半導體）：20261028_Siliconomics_v0.8.3.xlsx（v0.8.3，sha256 86253373d4b3）。由 siliconomics/data/CURRENT_SNAPSHOT 指向；綠字不得修改
A3: 名稱（SIF_） | B3: 本庫名稱 | C3: 單位 | D3: 值（純量）／2023 | E3: 2024 | F3: 2025 | G3: 2026 | H3: 2027 | I3: 2028 | J3: 2029 | K3: 2030 | L3: 2031 | M3: 2032
A4: A. 純量
A5: SIF_vr26 | B5: SIL_vr26 | C5: x | D5: 0.22
A6: SIF_vr26_lo | B6: SIL_vr26_lo | C6: x | D6: 0.15
A7: SIF_vr26_hi | B7: SIL_vr26_hi | C7: x | D7: 0.3
A8: SIF_it_GB | B8: SIL_it_GB | C8: US$K／顆 | D8: 66.194444
A9: SIF_it_VR | B9: SIL_it_VR | C9: US$K／顆 | D9: 128.83333
A10: SIF_it_RU | B10: SIL_it_RU | C10: US$K／顆 | D10: 257.16667
A11: SIF_it_HP | B11: SIL_it_HP | C11: US$K／顆 | D11: 38.3125
A12: SIF_it_AMD8 | B12: SIL_it_AMD8 | C12: US$K／顆 | D12: 40
A13: SIF_it_AMDR | B13: SIL_it_AMDR | C13: US$K／顆 | D13: 100
A14: SIF_it_TPU | B14: SIL_it_TPU | C14: US$K／顆 | D14: 25
A15: SIF_it_TRN | B15: SIL_it_TRN | C15: US$K／顆 | D15: 20
A16: SIF_it_ASIC | B16: SIL_it_ASIC | C16: US$K／顆 | D16: 20
A18: B. 年度（欄 D–M＝2023–2032；Siliconomics 只到 2029）
A19: SIF_UnitsPlat_bw | C19: 百萬顆 | G19: 5.4 | H19: 2.4 | I19: 0.5 | J19: 0.25
A20: SIF_UnitsPlat_rb | C20: 百萬顆 | G20: 1.7 | H20: 7 | I20: 7 | J20: 8.05
A21: SIF_UnitsPlat_ru | C21: 百萬顆 | G21: 0 | H21: 0.3 | I21: 2 | J21: 2.3
A22: SIF_UnitsPlat_hp | C22: 百萬顆 | G22: 0.5 | H22: 0 | I22: 0 | J22: 0
A23: SIF_UnitsPlat_amd | C23: 百萬顆 | G23: 0.75 | H23: 1.5 | I23: 2 | J23: 2.3
A24: SIF_UnitsPlat_tpu | C24: 百萬顆 | G24: 3.85 | H24: 5.5 | I24: 7 | J24: 8.05
A25: SIF_UnitsPlat_trn | C25: 百萬顆 | G25: 2 | H25: 2.5 | I25: 3 | J25: 3.45
A26: SIF_UnitsPlat_oth | C26: 百萬顆 | G26: 1 | H26: 4.5 | I26: 5 | J26: 5.75
A27: SIF_UnitsCoef_A | C27: x | G27: 1 | H27: 1 | I27: 1 | J27: 1
A28: SIF_UnitsCoef_B | C28: x | G28: 1 | H28: 1 | I28: 0.8 | J28: 0.85
A29: SIF_UnitsCoef_C | C29: x | G29: 1 | H29: 1 | I29: 0.6 | J29: 0.6
A30: SIF_DeployGW_A | C30: GW（成本等值） | G30: 23.399538 | H30: 41.646766 | I30: 52.792138 | J30: 60.138592
... A36: SIF_ITCapexPerGW | C36: US$B/GW | G36: 33.414032 | H36: 37.586352 | I36: 37.586352 | J36: 37.586352

Sheet Players
A1: Players — 玩家 × 年（2023–2032）年底上線 IT GW（＝TK GW；甲：公告路徑；營運者口徑）。已知值優先序：In Y1 輸入（設施 ÷ IF_FacilityGW）→ Y0 晶片功耗 × 倍數 → S3 觀測＋觀測後至年底的 T2 園區上線量；兩已知值間線性內插；最後已知值後＝前年＋當年 T2 園區（D0）；第一個已知值前留空（GL01-03）
A2: 旗標：1 輸入／5 晶片換算／2 觀測／3 內插／4 園區延伸／0 未知。年新增＝年底差（第一個已知年為『新納入存量』，不計新增）。低／高列：晶片換算用 k_chip2it 區間或 C 段區間，其餘＝基準
A3: 項目 | B3: 鍵 | C3: 單位 | D3: 2023 | E3: 2024 | F3: 2025 | G3: 2026 | H3: 2027 | I3: 2028 | J3: 2029 | K3: 2030 | L3: 2031 | M3: 2032 | N3: 說明
A4: 世代組合（新增 GW；NVIDIA 內部占比）與換算係數
A5: 世代占比：Hopper H100 | B5: mix_H100 | C5: % | D5: =IF(In!$H$162<>"",In!$H$162,0) -> 1 | E5: =IF(In!$I$162<>"",In!$I$162,0) -> 1 | F5: =IF(In!$J$162<>"",In!$J$162,0) -> 0.1 | G5: =IF(In!$K$162<>"",In!$K$162,0) -> 0 | H5: =IF(In!$L$162<>"",In!$L$162,0) -> 0 | I5: =IF(In!$M$162<>"",In!$M$162,0) -> 0 | J5: =IF(In!$N$162<>"",In!$N$162,0) -> 0 | K5: =IF(In!$O$162<>"",In!$O$162,J5) -> 0 | L5: =IF(In!$P$162<>"",In!$P$162,J5) -> 0 | M5: =IF(In!$Q$162<>"",In!$Q$162,J5) -> 0
A6: 世代占比：GB200 NVL72 | B6: mix_GB200 | C6: % | D6: =IF(In!$H$163<>"",In!$H$163,0) -> 0 | E6: =IF(In!$I$163<>"",In!$I$163,0) -> 0 | F6: =IF(In!$J$163<>"",In!$J$163,0) -> 0.7 | G6: =IF(In!$K$163<>"",In!$K$163,0) -> 0 | H6: =IF(In!$L$163<>"",In!$L$163,0) -> 0 | I6: =IF(In!$M$163<>"",In!$M$163,0) -> 0 | J6: =IF(In!$N$163<>"",In!$N$163,0) -> 0 | K6: =IF(In!$O$163<>"",In!$O$163,J6) -> 0 | L6: =IF(In!$P$163<>"",In!$P$163,J6) -> 0 | M6: =IF(In!$Q$163<>"",In!$Q$163,J6) -> 0
A7: 世代占比：GB300 NVL72 | B7: mix_GB300 | C7: % | D7: =IF(In!$H$164<>"",In!$H$164,0) -> 0 | E7: =IF(In!$I$164<>"",In!$I$164,0) -> 0 | F7: =IF(In!$J$164<>"",In!$J$164,0) -> 0.2 | G7: =IF(In!$K$164<>"",In!$K$164,(1-SIL_vr26)) -> 0.78 | H7: =IF(In!$L$164<>"",In!$L$164,0) -> 0 | I7: =IF(In!$M$164<>"",In!$M$164,0) -> 0 | J7: =IF(In!$N$164<>"",In!$N$164,0) -> 0 | K7: =IF(In!$O$164<>"",In!$O$164,J7) -> 0 | L7: =IF(In!$P$164<>"",In!$P$164,J7) -> 0 | M7: =IF(In!$Q$164<>"",In!$Q$164,J7) -> 0
A8: 世代占比：VR200 NVL72 | B8: mix_VR200 | C8: % | D8: =IF(In!$H$165<>"",In!$H$165,0) -> 0 | E8: =IF(In!$I$165<>"",In!$I$165,0) -> 0 | F8: =IF(In!$J$165<>"",In!$J$165,0) -> 0 | G8: =IF(In!$K$165<>"",In!$K$165,SIL_vr26) -> 0.22 | H8: =IF(In!$L$165<>"",In!$L$165,(1-H$11)) -> 0.93967425 | I8: =IF(In!$M$165<>"",In!$M$165,(1-I$11)) -> 0.70028477 | J8: =IF(In!$N$165<>"",In!$N$165,(1-J$11)) -> 0.70028477 | K8: =IF(In!$O$165<>"",In!$O$165,J8) -> 0.70028477 | L8: =IF(In!$P$165<>"",In!$P$165,J8) -> 0.70028477 | M8: =IF(In!$Q$165<>"",In!$Q$165,J8) -> 0.70028477
A9: 世代占比：Rubin Ultra | B9: mix_RU | C9: % | D9: =IF(In!$H$166<>"",In!$H$166,0) -> 0 | E9: =IF(In!$I$166<>"",In!$I$166,0) -> 0 | F9: =IF(In!$J$166<>"",In!$J$166,0) -> 0 | G9: =IF(In!$K$166<>"",In!$K$166,0) -> 0 | H9: =IF(In!$L$166<>"",In!$L$166,H$11) -> 0.060325747 | I9: =IF(In!$M$166<>"",In!$M$166,I$11) -> 0.29971523 | J9: =IF(In!$N$166<>"",In!$N$166,J$11) -> 0.29971523 | K9: =IF(In!$O$166<>"",In!$O$166,J9) -> 0.29971523 | L9: =IF(In!$P$166<>"",In!$P$166,J9) -> 0.29971523 | M9: =IF(In!$Q$166<>"",In!$Q$166,J9) -> 0.29971523
A10: 世代占比合計（須＝1） | C10: % | D10: =SUM(D5:D9) -> 1 | E10: =SUM(E5:E9) -> 1 | F10: =SUM(F5:F9) -> 1 | G10: =SUM(G5:G9) -> 1 | H10: =SUM(H5:H9) -> 1 | I10: =SUM(I5:I9) -> 1 | J10: =SUM(J5:J9) -> 1 | K10: =SUM(K5:K9) -> 1 | ... M10: =SUM(M5:M9) -> 1
A11: Rubin Ultra 占 Rubin 平台 GW 比（Derived：Units ÷ TK 每 GW GPU 數） | C11: % | H11: =(SIL_In!$H$21/TK_GPUsPerGW_RU)/(SIL_In!$H$20/TK_GPUsPerGW_VR200+SIL_In!$H$21/TK_GPUsPerGW_RU) -> 0.060325747 | I11: =(SIL_In!$I$21/TK_GPUsPerGW_RU)/(SIL_In!$I$20/TK_GPUsPerGW_VR200+SIL_In!$I$21/TK_GPUsPerGW_RU) -> 0.29971523 | J11: =(SIL_In!$J$21/TK_GPUsPerGW_RU)/(SIL_In!$J$20/TK_GPUsPerGW_VR200+SIL_In!$J$21/TK_GPUsPerGW_RU) -> 0.29971523 | N11: 工作單：Rubin Ultra 比例讀 Siliconomics Units；以每 GW GPU 數換成 GW 占比（GL01-11）；2027 Blackwell 2.4M 顆不計（工作單：2027 起 VR200）
A12: 市場新增 GW 非 NVIDIA 占比 | B12: nnv_mkt | C12: % | D12: =IF(In!$H$167<>"",In!$H$167,G12) -> 0.23821007 | E12: =IF(In!$I$167<>"",In!$I$167,G12) -> 0.23821007 | F12: =IF(In!$J$167<>"",In!$J$167,G12) -> 0.23821007 | G12: =IF(In!$K$167<>"",In!$K$167,(SIL_In!$G$23*SIL_it_AMD8+SIL_In!$G$24*SIL_it_TPU+SIL_In!$G$25*SIL_it_TRN+SIL_In!$G$26*SIL_it_ASIC)/((SIL_In!$G$23*SIL_it_AMD8+SIL_In!$G$24*SIL_it_TPU+SIL_In!$G$25*SIL_it_TRN+SIL_In!$G$26*SIL_it_ASIC)+(SIL_In!$G$19*SIL_it_GB+SIL_In!$G$20*SIL_it_VR+SIL_In!$G$21*SIL_it_RU+SIL_In!$G$22*SIL_it_HP))) -> 0.23821007 | H12: =IF(In!$L$167<>"",In!$L$167,(SIL_In!$H$23*SIL_it_AMDR+SIL_In!$H$24*SIL_it_TPU+SIL_In!$H$25*SIL_it_TRN+SIL_In!$H$26*SIL_it_ASIC)/((SIL_In!$H$23*SIL_it_AMDR+SIL_In!$H$24*SIL_it_TPU+SIL_In!$H$25*SIL_it_TRN+SIL_In!$H$26*SIL_it_ASIC)+(SIL_In!$H$19*SIL_it_GB+SIL_In!$H$20*SIL_it_VR+SIL_In!$H$21*SIL_it_RU+SIL_In!$H$22*SIL_it_HP))) -> 0.27310186 | I12: =IF(In!$M$167<>"",In!$M$167,(SIL_In!$I$23*SIL_it_AMDR+SIL_In!$I$24*SIL_it_TPU+SIL_In!$I$25*SIL_it_TRN+SIL_In!$I$26*SIL_it_ASIC)/((SIL_In!$I$23*SIL_it_AMDR+SIL_In!$I$24*SIL_it_TPU+SIL_In!$I$25*SIL_it_TRN+SIL_In!$I$26*SIL_it_ASIC)+(SIL_In!$I$19*SIL_it_GB+SIL_In!$I$20*SIL_it_VR+SIL_In!$I$21*SIL_it_RU+SIL_In!$I$22*SIL_it_HP))) -> 0.2696214 | J12: =IF(In!$N$167<>"",In!$N$167,(SIL_In!$J$23*SIL_it_AMDR+SIL_In!$J$24*SIL_it_TPU+SIL_In!$J$25*SIL_it_TRN+SIL_In!$J$26*SIL_it_ASIC)/((SIL_In!$J$23*SIL_it_AMDR+SIL_In!$J$24*SIL_it_TPU+SIL_In!$J$25*SIL_it_TRN+SIL_In!$J$26*SIL_it_ASIC)+(SIL_In!$J$19*SIL_it_GB+SIL_In!$J$20*SIL_it_VR+SIL_In!$J$21*SIL_it_RU+SIL_In!$J$22*SIL_it_HP))) -> 0.27218751 | K12: =IF(In!$O$167<>"",In!$O$167,J12) -> 0.27218751 | L12: =IF(In!$P$167<>"",In!$P$167,J12) -> 0.27218751 | M12: =IF(In!$Q$167<>"",In!$Q$167,J12) -> 0.27218751 | N12: Derived：Siliconomics Units 非 NVIDIA 平台 IT capex 占比（工作單第 2 節）；2023–25 沿用 2026（待決）、2030–32 沿用 2029
A13: 每 IT GW 對應設施電力（TK IF_FacilityGW，世代加權） | C13: x | D13: =D5*TK_FacilityGW_H100+D6*TK_FacilityGW_GB200+D7*TK_FacilityGW_GB300+D8*TK_FacilityGW_VR200+D9*TK_FacilityGW_RU -> 1.2 | E13: =E5*TK_FacilityGW_H100+E6*TK_FacilityGW_GB200+E7*TK_FacilityGW_GB300+E8*TK_FacilityGW_VR200+E9*TK_FacilityGW_RU -> 1.2 | F13: =F5*TK_FacilityGW_H100+F6*TK_FacilityGW_GB200+F7*TK_FacilityGW_GB300+F8*TK_FacilityGW_VR200+F9*TK_FacilityGW_RU -> 1.2 | G13: =G5*TK_FacilityGW_H100+G6*TK_FacilityGW_GB200+G7*TK_FacilityGW_GB300+G8*TK_FacilityGW_VR200+G9*TK_FacilityGW_RU -> 1.2 | H13: =H5*TK_FacilityGW_H100+H6*TK_FacilityGW_GB200+H7*TK_FacilityGW_GB300+H8*TK_FacilityGW_VR200+H9*TK_FacilityGW_RU -> 1.2 | I13: =I5*TK_FacilityGW_H100+I6*TK_FacilityGW_GB200+I7*TK_FacilityGW_GB300+I8*TK_FacilityGW_VR200+I9*TK_FacilityGW_RU -> 1.2 | J13: =J5*TK_FacilityGW_H100+J6*TK_FacilityGW_GB200+J7*TK_FacilityGW_GB300+J8*TK_FacilityGW_VR200+J9*TK_FacilityGW_RU -> 1.2 | K13: =K5*TK_FacilityGW_H100+K6*TK_FacilityGW_GB200+K7*TK_FacilityGW_GB300+K8*TK_FacilityGW_VR200+K9*TK_FacilityGW_RU -> 1.2 | ... M13: =M5*TK_FacilityGW_H100+M6*TK_FacilityGW_GB200+M7*TK_FacilityGW_GB300+M8*TK_FacilityGW_VR200+M9*TK_FacilityGW_RU -> 1.2 | N13: TK_In（Tokenomics v21.7 Interface 第 8 列；快照未含，直接讀活頁簿，SRC_GL_006）；非 NVIDIA 以 NVIDIA 世代加權近似
A14: 晶片 → IT 倍數：Microsoft（自有＋融資租賃 AI 在役） | B14: mult_msft | C14: x | D14: =k_chip2it -> 1.85 | E14: =k_chip2it_lo -> 1.65 | F14: =k_chip2it_hi -> 2.08 | N14: k_chip2it（D＝基準、E＝低、F＝高）
A15: 晶片 → IT 倍數：Alphabet（Google；TPU＋NVIDIA） | B15: mult_googl | C15: x | D15: =ovr25_googl/In!$J$102 -> 1.4560477 | E15: =ovr25_googl_lo/In!$J$102 -> 1.3206014 | F15: =ovr25_googl_hi/In!$J$102 -> 1.6592171 | N15: C 段 2025 更正值 ovr25_googl ÷ 2025 晶片功耗（D＝基準、E＝低、F＝高）
A16: 晶片 → IT 倍數：Amazon（AWS；Trainium＋NVIDIA） | B16: mult_amzn | C16: x | D16: =ovr25_amzn/In!$J$103 -> 1.3153961 | E16: =ovr25_amzn_lo/In!$J$103 -> 1.1360239 | F16: =ovr25_amzn_hi/In!$J$103 -> 1.554559 | N16: C 段 2025 更正值 ovr25_amzn ÷ 2025 晶片功耗（D＝基準、E＝低、F＝高）
A17: 晶片 → IT 倍數：Meta | B17: mult_meta | C17: x | D17: =k_chip2it -> 1.85 | E17: =k_chip2it_lo -> 1.65 | F17: =k_chip2it_hi -> 2.08 | N17: k_chip2it（D＝基準、E＝低、F＝高）
A18: 晶片 → IT 倍數：Oracle（OCI；含承租 Stargate 站點） | B18: mult_orcl | C18: x | D18: =k_chip2it -> 1.85 | E18: =k_chip2it_lo -> 1.65 | F18: =k_chip2it_hi -> 2.08 | N18: k_chip2it（D＝基準、E＝低、F＝高）
A19: 晶片 → IT 倍數：SpaceX／xAI（Colossus；兼出租） | B19: mult_xai | C19: x | D19: =k_chip2it -> 1.85 | E19: =k_chip2it_lo -> 1.65 | F19: =k_chip2it_hi -> 2.08 | N19: k_chip2it（D＝基準、E＝低、F＝高）
A21: Microsoft（自有＋融資租賃 AI 在役） | B21: msft | N21: In 第 108 列；口徑＝In!C108
A22: 輸入（IT GW；設施 ÷ IF_FacilityGW） | B22: msft_in | C22: GW | D22: =IF(In!$H$108="","",IF(In!$C$108="設施",In!$H$108/1000/D$13,In!$H$108/1000)) | E22: =IF(In!$I$108="","",IF(In!$C$108="設施",In!$I$108/1000/E$13,In!$I$108/1000)) | F22: =IF(In!$J$108="","",IF(In!$C$108="設施",In!$J$108/1000/F$13,In!$J$108/1000)) | G22: =IF(In!$K$108="","",IF(In!$C$108="設施",In!$K$108/1000/G$13,In!$K$108/1000)) | H22: =IF(In!$L$108="","",IF(In!$C$108="設施",In!$L$108/1000/H$13,In!$L$108/1000)) | I22: =IF(In!$M$108="","",IF(In!$C$108="設施",In!$M$108/1000/I$13,In!$M$108/1000)) | J22: =IF(In!$N$108="","",IF(In!$C$108="設施",In!$N$108/1000/J$13,In!$N$108/1000)) | K22: =IF(In!$O$108="","",IF(In!$C$108="設施",In!$O$108/1000/K$13,In!$O$108/1000)) | L22: =IF(In!$P$108="","",IF(In!$C$108="設施",In!$P$108/1000/L$13,In!$P$108/1000)) | M22: =IF(In!$Q$108="","",IF(In!$C$108="設施",In!$Q$108/1000/M$13,In!$Q$108/1000))
A23: 晶片換算 IT GW | B23: msft_chip | C23: GW | D23: =IF(In!$H$101="","",In!$H$101*Players!$D$14/1000) | E23: =IF(In!$I$101="","",In!$I$101*Players!$D$14/1000) -> 1.593775 | F23: =IF(In!$J$101="","",In!$J$101*Players!$D$14/1000) -> 3.729045 | G23: =IF(In!$K$101="","",In!$K$101*Players!$D$14/1000) | H23: =IF(In!$L$101="","",In!$L$101*Players!$D$14/1000) | I23: =IF(In!$M$101="","",In!$M$101*Players!$D$14/1000) | J23: =IF(In!$N$101="","",In!$N$101*Players!$D$14/1000) | K23: =IF(In!$O$101="","",In!$O$101*Players!$D$14/1000) | L23: =IF(In!$P$101="","",In!$P$101*Players!$D$14/1000) | M23: =IF(In!$Q$101="","",In!$Q$101*Players!$D$14/1000)
A24: 已知值 | B24: msft_k | C24: GW | D24: =IF(D22<>"",D22,IF(D23<>"",D23,IF(INT(obsd_msft)=2023,obs_msft/1000+SUMIFS(Pipeline!$L$5:$L$64,Pipeline!$C$5:$C$64,"msft",Pipeline!$Q$5:$Q$64,1,Pipeline!$K$5:$K$64,">"&obsd_msft,Pipeline!$K$5:$K$64,"<="&2024),""))) | E24: =IF(E22<>"",E22,IF(E23<>"",E23,IF(INT(obsd_msft)=2024,obs_msft/1000+SUMIFS(Pipeline!$L$5:$L$64,Pipeline!$C$5:$C$64,"msft",Pipeline!$Q$5:$Q$64,1,Pipeline!$K$5:$K$64,">"&obsd_msft,Pipeline!$K$5:$K$64,"<="&2025),""))) -> 1.593775 | F24: =IF(F22<>"",F22,IF(F23<>"",F23,IF(INT(obsd_msft)=2025,obs_msft/1000+SUMIFS(Pipeline!$L$5:$L$64,Pipeline!$C$5:$C$64,"msft",Pipeline!$Q$5:$Q$64,1,Pipeline!$K$5:$K$64,">"&obsd_msft,Pipeline!$K$5:$K$64,"<="&2026),""))) -> 3.729045 | G24: =IF(G22<>"",G22,IF(G23<>"",G23,IF(INT(obsd_msft)=2026,obs_msft/1000+SUMIFS(Pipeline!$L$5:$L$64,Pipeline!$C$5:$C$64,"msft",Pipeline!$Q$5:$Q$64,1,Pipeline!$K$5:$K$64,">"&obsd_msft,Pipeline!$K$5:$K$64,"<="&2027),""))) -> 4.5 | H24: =IF(H22<>"",H22,IF(H23<>"",H23,IF(INT(obsd_msft)=2027,obs_msft/1000+SUMIFS(Pipeline!$L$5:$L$64,Pipeline!$C$5:$C$64,"msft",Pipeline!$Q$5:$Q$64,1,Pipeline!$K$5:$K$64,">"&obsd_msft,Pipeline!$K$5:$K$64,"<="&2028),""))) | I24: =IF(I22<>"",I22,IF(I23<>"",I23,IF(INT(obsd_msft)=2028,obs_msft/1000+SUMIFS(Pipeline!$L$5:$L$64,Pipeline!$C$5:$C$64,"msft",Pipeline!$Q$5:$Q$64,1,Pipeline!$K$5:$K$64,">"&obsd_msft,Pipeline!$K$5:$K$64,"<="&2029),""))) | J24: =IF(J22<>"",J22,IF(J23<>"",J23,IF(INT(obsd_msft)=2029,obs_msft/1000+SUMIFS(Pipeline!$L$5:$L$64,Pipeline!$C$5:$C$64,"msft",Pipeline!$Q$5:$Q$64,1,Pipeline!$K$5:$K$64,">"&obsd_msft,Pipeline!$K$5:$K$64,"<="&2030),""))) | K24: =IF(K22<>"",K22,IF(K23<>"",K23,IF(INT(obsd_msft)=2030,obs_msft/1000+SUMIFS(Pipeline!$L$5:$L$64,Pipeline!$C$5:$C$64,"msft",Pipeline!$Q$5:$Q$64,1,Pipeline!$K$5:$K$64,">"&obsd_msft,Pipeline!$K$5:$K$64,"<="&2031),""))) | L24: =IF(L22<>"",L22,IF(L23<>"",L23,IF(INT(obsd_msft)=2031,obs_msft/1000+SUMIFS(Pipeline!$L$5:$L$64,Pipeline!$C$5:$C$64,"msft",Pipeline!$Q$5:$Q$64,1,Pipeline!$K$5:$K$64,">"&obsd_msft,Pipeline!$K$5:$K$64,"<="&2032),""))) | M24: =IF(M22<>"",M22,IF(M23<>"",M23,IF(INT(obsd_msft)=2032,obs_msft/1000+SUMIFS(Pipeline!$L$5:$L$64,Pipeline!$C$5:$C$64,"msft",Pipeline!$Q$5:$Q$64,1,Pipeline!$K$5:$K$64,">"&obsd_msft,Pipeline!$K$5:$K$64,"<="&2033),"")))
A25: 前一已知值 | B25: msft_L | C25: GW | D25: =IF(D24<>"",D24,"") | E25: =IF(E24<>"",E24,D25) -> 1.593775 | F25: =IF(F24<>"",F24,E25) -> 3.729045 | G25: =IF(G24<>"",G24,F25) -> 4.5 | H25: =IF(H24<>"",H24,G25) -> 4.5 | I25: =IF(I24<>"",I24,H25) -> 4.5 | J25: =IF(J24<>"",J24,I25) -> 4.5 | K25: =IF(K24<>"",K24,J25) -> 4.5 | L25: =IF(L24<>"",L24,K25) -> 4.5 | M25: =IF(M24<>"",M24,L25) -> 4.5
A26: 前一已知年 | B26: msft_LY | C26: 年 | D26: =IF(D24<>"",2023,"") | E26: =IF(E24<>"",2024,D26) -> 2024 | F26: =IF(F24<>"",2025,E26) -> 2025 | G26: =IF(G24<>"",2026,F26) -> 2026 | H26: =IF(H24<>"",2027,G26) -> 2026 | I26: =IF(I24<>"",2028,H26) -> 2026 | J26: =IF(J24<>"",2029,I26) -> 2026 | K26: =IF(K24<>"",2030,J26) -> 2026 | L26: =IF(L24<>"",2031,K26) -> 2026 | M26: =IF(M24<>"",2032,L26) -> 2026
A27: 下一已知值 | B27: msft_N | C27: GW | D27: =IF(D24<>"",D24,E27) -> 1.593775 | E27: =IF(E24<>"",E24,F27) -> 1.593775 | F27: =IF(F24<>"",F24,G27) -> 3.729045 | G27: =IF(G24<>"",G24,H27) -> 4.5 | H27: =IF(H24<>"",H24,I27) | I27: =IF(I24<>"",I24,J27) | J27: =IF(J24<>"",J24,K27) | K27: =IF(K24<>"",K24,L27) | L27: =IF(L24<>"",L24,M27) | M27: =IF(M24<>"",M24,"")
A28: 下一已知年 | B28: msft_NY | C28: 年 | D28: =IF(D24<>"",2023,E28) -> 2024 | E28: =IF(E24<>"",2024,F28) -> 2024 | F28: =IF(F24<>"",2025,G28) -> 2025 | G28: =IF(G24<>"",2026,H28) -> 2026 | H28: =IF(H24<>"",2027,I28) | I28: =IF(I24<>"",2028,J28) | J28: =IF(J24<>"",2029,K28) | K28: =IF(K24<>"",2030,L28) | L28: =IF(L24<>"",2031,M28) | M28: =IF(M24<>"",2032,"")
A29: 當年 T2 園區上線（D0，IT GW） | B29: msft_cp | C29: GW | D29: =SUMIFS(Pipeline!$L$5:$L$64,Pipeline!$C$5:$C$64,"msft",Pipeline!$Q$5:$Q$64,1,Pipeline!$P$5:$P$64,2023) -> 0 | E29: =SUMIFS(Pipeline!$L$5:$L$64,Pipeline!$C$5:$C$64,"msft",Pipeline!$Q$5:$Q$64,1,Pipeline!$P$5:$P$64,2024) -> 0 | F29: =SUMIFS(Pipeline!$L$5:$L$64,Pipeline!$C$5:$C$64,"msft",Pipeline!$Q$5:$Q$64,1,Pipeline!$P$5:$P$64,2025) -> 0.321 | G29: =SUMIFS(Pipeline!$L$5:$L$64,Pipeline!$C$5:$C$64,"msft",Pipeline!$Q$5:$Q$64,1,Pipeline!$P$5:$P$64,2026) -> 0.684 | H29: =SUMIFS(Pipeline!$L$5:$L$64,Pipeline!$C$5:$C$64,"msft",Pipeline!$Q$5:$Q$64,1,Pipeline!$P$5:$P$64,2027) -> 1.04 | I29: =SUMIFS(Pipeline!$L$5:$L$64,Pipeline!$C$5:$C$64,"msft",Pipeline!$Q$5:$Q$64,1,Pipeline!$P$5:$P$64,2028) -> 1.526 | J29: =SUMIFS(Pipeline!$L$5:$L$64,Pipeline!$C$5:$C$64,"msft",Pipeline!$Q$5:$Q$64,1,Pipeline!$P$5:$P$64,2029) -> 0 | K29: =SUMIFS(Pipeline!$L$5:$L$64,Pipeline!$C$5:$C$64,"msft",Pipeline!$Q$5:$Q$64,1,Pipeline!$P$5:$P$64,2030) -> 0 | L29: =SUMIFS(Pipeline!$L$5:$L$64,Pipeline!$C$5:$C$64,"msft",Pipeline!$Q$5:$Q$64,1,Pipeline!$P$5:$P$64,2031) -> 0 | M29: =SUMIFS(Pipeline!$L$5:$L$64,Pipeline!$C$5:$C$64,"msft",Pipeline!$Q$5:$Q$64,1,Pipeline!$P$5:$P$64,2032) -> 0
A30: 年底上線 IT GW | B30: msft_tk | C30: GW | D30: =IF(D24<>"",D24,IF(AND(D25<>"",D27<>""),D25+(D27-D25)*(2023-D26)/(D28-D26),"")) | E30: =IF(E24<>"",E24,IF(AND(E25<>"",E27<>""),E25+(E27-E25)*(2024-E26)/(E28-E26),IF(D30<>"",D30+E29,""))) -> 1.593775 | F30: =IF(F24<>"",F24,IF(AND(F25<>"",F27<>""),F25+(F27-F25)*(2025-F26)/(F28-F26),IF(E30<>"",E30+F29,""))) -> 3.729045 | G30: =IF(G24<>"",G24,IF(AND(G25<>"",G27<>""),G25+(G27-G25)*(2026-G26)/(G28-G26),IF(F30<>"",F30+G29,""))) -> 4.5 | H30: =IF(H24<>"",H24,IF(AND(H25<>"",H27<>""),H25+(H27-H25)*(2027-H26)/(H28-H26),IF(G30<>"",G30+H29,""))) -> 5.54 | I30: =IF(I24<>"",I24,IF(AND(I25<>"",I27<>""),I25+(I27-I25)*(2028-I26)/(I28-I26),IF(H30<>"",H30+I29,""))) -> 7.066 | J30: =IF(J24<>"",J24,IF(AND(J25<>"",J27<>""),J25+(J27-J25)*(2029-J26)/(J28-J26),IF(I30<>"",I30+J29,""))) -> 7.066 | K30: =IF(K24<>"",K24,IF(AND(K25<>"",K27<>""),K25+(K27-K25)*(2030-K26)/(K28-K26),IF(J30<>"",J30+K29,""))) -> 7.066 | L30: =IF(L24<>"",L24,IF(AND(L25<>"",L27<>""),L25+(L27-L25)*(2031-L26)/(L28-L26),IF(K30<>"",K30+L29,""))) -> 7.066 | M30: =IF(M24<>"",M24,IF(AND(M25<>"",M27<>""),M25+(M27-M25)*(2032-M26)/(M28-M26),IF(L30<>"",L30+M29,""))) -> 7.066
A31: 旗標 | B31: msft_f | C31: — | D31: =IF(D22<>"",1,IF(D23<>"",5,IF(D24<>"",2,IF(AND(D25<>"",D27<>""),3,IF(D30<>"",4,0))))) -> 0 | E31: =IF(E22<>"",1,IF(E23<>"",5,IF(E24<>"",2,IF(AND(E25<>"",E27<>""),3,IF(E30<>"",4,0))))) -> 5 | F31: =IF(F22<>"",1,IF(F23<>"",5,IF(F24<>"",2,IF(AND(F25<>"",F27<>""),3,IF(F30<>"",4,0))))) -> 5 | G31: =IF(G22<>"",1,IF(G23<>"",5,IF(G24<>"",2,IF(AND(G25<>"",G27<>""),3,IF(G30<>"",4,0))))) -> 2 | H31: =IF(H22<>"",1,IF(H23<>"",5,IF(H24<>"",2,IF(AND(H25<>"",H27<>""),3,IF(H30<>"",4,0))))) -> 4 | I31: =IF(I22<>"",1,IF(I23<>"",5,IF(I24<>"",2,IF(AND(I25<>"",I27<>""),3,IF(I30<>"",4,0))))) -> 4 | J31: =IF(J22<>"",1,IF(J23<>"",5,IF(J24<>"",2,IF(AND(J25<>"",J27<>""),3,IF(J30<>"",4,0))))) -> 4 | K31: =IF(K22<>"",1,IF(K23<>"",5,IF(K24<>"",2,IF(AND(K25<>"",K27<>""),3,IF(K30<>"",4,0))))) -> 4 | ... M31: =IF(M22<>"",1,IF(M23<>"",5,IF(M24<>"",2,IF(AND(M25<>"",M27<>""),3,IF(M30<>"",4,0))))) -> 4
A32: 年底上線 IT GW：低 | B32: msft_lo | C32: GW | D32: =IF(D30="","",IF(D31=2,D30-(obs_msft-obs_msft_lo)/1000,IF(AND(D31=5,In!$H$101<>""),In!$H$101*Players!$E$14/1000,D30))) | E32: =IF(E30="","",IF(E31=2,E30-(obs_msft-obs_msft_lo)/1000,IF(AND(E31=5,In!$I$101<>""),In!$I$101*Players!$E$14/1000,E30))) -> 1.421475 | F32: =IF(F30="","",IF(F31=2,F30-(obs_msft-obs_msft_lo)/1000,MIN(IF(AND(F31=5,In!$J$101<>""),In!$J$101*Players!$E$14/1000,F30),msft_guardian_lo/1000))) -> 1 | G32: =IF(G30="","",IF(G31=2,G30-(obs_msft-obs_msft_lo)/1000,IF(AND(G31=5,In!$K$101<>""),In!$K$101*Players!$E$14/1000,G30))) -> 3.5 | H32: =IF(H30="","",IF(H31=2,H30-(obs_msft-obs_msft_lo)/1000,IF(AND(H31=5,In!$L$101<>""),In!$L$101*Players!$E$14/1000,H30))) -> 5.54 | I32: =IF(I30="","",IF(I31=2,I30-(obs_msft-obs_msft_lo)/1000,IF(AND(I31=5,In!$M$101<>""),In!$M$101*Players!$E$14/1000,I30))) -> 7.066 | J32: =IF(J30="","",IF(J31=2,J30-(obs_msft-obs_msft_lo)/1000,IF(AND(J31=5,In!$N$101<>""),In!$N$101*Players!$E$14/1000,J30))) -> 7.066 | K32: =IF(K30="","",IF(K31=2,K30-(obs_msft-obs_msft_lo)/1000,IF(AND(K31=5,In!$O$101<>""),In!$O$101*Players!$E$14/1000,K30))) -> 7.066 | L32: =IF(L30="","",IF(L31=2,L30-(obs_msft-obs_msft_lo)/1000,IF(AND(L31=5,In!$P$101<>""),In!$P$101*Players!$E$14/1000,L30))) -> 7.066 | M32: =IF(M30="","",IF(M31=2,M30-(obs_msft-obs_msft_lo)/1000,IF(AND(M31=5,In!$Q$101<>""),In!$Q$101*Players!$E$14/1000,M30))) -> 7.066
A33: 年底上線 IT GW：高 | B33: msft_hi | C33: GW | D33: =IF(D30="","",IF(D31=2,D30+(obs_msft_hi-obs_msft)/1000,IF(AND(D31=5,In!$H$101<>""),In!$H$101*Players!$F$14/1000,D30))) | E33: =IF(E30="","",IF(E31=2,E30+(obs_msft_hi-obs_msft)/1000,IF(AND(E31=5,In!$I$101<>""),In!$I$101*Players!$F$14/1000,E30))) -> 1.79192 | F33: =IF(F30="","",IF(F31=2,F30+(obs_msft_hi-obs_msft)/1000,IF(AND(F31=5,In!$J$101<>""),In!$J$101*Players!$F$14/1000,F30))) -> 4.192656 | G33: =IF(G30="","",IF(G31=2,G30+(obs_msft_hi-obs_msft)/1000,IF(AND(G31=5,In!$K$101<>""),In!$K$101*Players!$F$14/1000,G30))) -> 5.5 | H33: =IF(H30="","",IF(H31=2,H30+(obs_msft_hi-obs_msft)/1000,IF(AND(H31=5,In!$L$101<>""),In!$L$101*Players!$F$14/1000,H30))) -> 5.54 | I33: =IF(I30="","",IF(I31=2,I30+(obs_msft_hi-obs_msft)/1000,IF(AND(I31=5,In!$M$101<>""),In!$M$101*Players!$F$14/1000,I30))) -> 7.066 | J33: =IF(J30="","",IF(J31=2,J30+(obs_msft_hi-obs_msft)/1000,IF(AND(J31=5,In!$N$101<>""),In!$N$101*Players!$F$14/1000,J30))) -> 7.066 | K33: =IF(K30="","",IF(K31=2,K30+(obs_msft_hi-obs_msft)/1000,IF(AND(K31=5,In!$O$101<>""),In!$O$101*Players!$F$14/1000,K30))) -> 7.066 | L33: =IF(L30="","",IF(L31=2,L30+(obs_msft_hi-obs_msft)/1000,IF(AND(L31=5,In!$P$101<>""),In!$P$101*Players!$F$14/1000,L30))) -> 7.066 | M33: =IF(M30="","",IF(M31=2,M30+(obs_msft_hi-obs_msft)/1000,IF(AND(M31=5,In!$Q$101<>""),In!$Q$101*Players!$F$14/1000,M30))) -> 7.066
A34: 另讀（口徑未說明者讀為設施 ÷ IF_FacilityGW） | B34: msft_alt | C34: GW | D34: =IF(D30="","",IF(In!$C$108="未說明",D30/D$13,D30)) | E34: =IF(E30="","",IF(In!$C$108="未說明",E30/E$13,E30)) -> 1.593775 | F34: =IF(F30="","",IF(In!$C$108="未說明",F30/F$13,F30)) -> 3.729045 | G34: =IF(G30="","",IF(In!$C$108="未說明",G30/G$13,G30)) -> 4.5 | H34: =IF(H30="","",IF(In!$C$108="未說明",H30/H$13,H30)) -> 5.54 | I34: =IF(I30="","",IF(In!$C$108="未說明",I30/I$13,I30)) -> 7.066 | J34: =IF(J30="","",IF(In!$C$108="未說明",J30/J$13,J30)) -> 7.066 | K34: =IF(K30="","",IF(In!$C$108="未說明",K30/K$13,K30)) -> 7.066 | ... M34: =IF(M30="","",IF(In!$C$108="未說明",M30/M$13,M30)) -> 7.066
A35: 年平均 IT GW | B35: msft_avg | C35: GW | D35: ="" | E35: =IF(AND(D30<>"",E30<>""),(D30+E30)/2,"") | F35: =IF(AND(E30<>"",F30<>""),(E30+F30)/2,"") -> 2.66141 | G35: =IF(AND(F30<>"",G30<>""),(F30+G30)/2,"") -> 4.1145225 | H35: =IF(AND(G30<>"",H30<>""),(G30+H30)/2,"") -> 5.02 | I35: =IF(AND(H30<>"",I30<>""),(H30+I30)/2,"") -> 6.303 | J35: =IF(AND(I30<>"",J30<>""),(I30+J30)/2,"") -> 7.066 | K35: =IF(AND(J30<>"",K30<>""),(J30+K30)/2,"") -> 7.066 | L35: =IF(AND(K30<>"",L30<>""),(K30+L30)/2,"") -> 7.066 | M35: =IF(AND(L30<>"",M30<>""),(L30+M30)/2,"") -> 7.066
A36: 年新增 IT GW | B36: msft_add | C36: GW | D36: 0 | E36: =IF(AND(D30<>"",E30<>""),E30-D30,0) -> 0 | F36: =IF(AND(E30<>"",F30<>""),F30-E30,0) -> 2.13527 | G36: =IF(AND(F30<>"",G30<>""),G30-F30,0) -> 0.770955 | H36: =IF(AND(G30<>"",H30<>""),H30-G30,0) -> 1.04 | I36: =IF(AND(H30<>"",I30<>""),I30-H30,0) -> 1.526 | J36: =IF(AND(I30<>"",J30<>""),J30-I30,0) -> 0 | K36: =IF(AND(J30<>"",K30<>""),K30-J30,0) -> 0 | L36: =IF(AND(K30<>"",L30<>""),L30-K30,0) -> 0 | M36: =IF(AND(L30<>"",M30<>""),M30-L30,0) -> 0
A37: 新納入存量 IT GW | B37: msft_stk | C37: GW | D37: =IF(D30<>"",D30,0) -> 0 | E37: =IF(AND(D30="",E30<>""),E30,0) -> 1.593775 | F37: =IF(AND(E30="",F30<>""),F30,0) -> 0 | G37: =IF(AND(F30="",G30<>""),G30,0) -> 0 | H37: =IF(AND(G30="",H30<>""),H30,0) -> 0 | I37: =IF(AND(H30="",I30<>""),I30,0) -> 0 | J37: =IF(AND(I30="",J30<>""),J30,0) -> 0 | K37: =IF(AND(J30="",K30<>""),K30,0) -> 0 | L37: =IF(AND(K30="",L30<>""),L30,0) -> 0 | M37: =IF(AND(L30="",M30<>""),M30,0) -> 0
A38: 新增 GW 非 NVIDIA 占比 | B38: msft_nnv | C38: % | D38: =D$12 -> 0.23821007 | E38: =E$12 -> 0.23821007 | F38: =F$12 -> 0.23821007 | G38: =G$12 -> 0.23821007 | H38: =H$12 -> 0.27310186 | I38: =I$12 -> 0.2696214 | J38: =J$12 -> 0.27218751 | K38: =K$12 -> 0.27218751 | ... M38: =M$12 -> 0.27218751
A40: Alphabet（Google；TPU＋NVIDIA） | B40: googl | N40: In 第 109 列；口徑＝In!C109
A41: 輸入（IT GW；設施 ÷ IF_FacilityGW） | B41: googl_in | C41: GW | D41: =IF(In!$H$109="","",IF(In!$C$109="設施",In!$H$109/1000/D$13,In!$H$109/1000)) | E41: =IF(In!$I$109="","",IF(In!$C$109="設施",In!$I$109/1000/E$13,In!$I$109/1000)) | F41: =IF(In!$J$109="","",IF(In!$C$109="設施",In!$J$109/1000/F$13,In!$J$109/1000)) | G41: =IF(In!$K$109="","",IF(In!$C$109="設施",In!$K$109/1000/G$13,In!$K$109/1000)) | H41: =IF(In!$L$109="","",IF(In!$C$109="設施",In!$L$109/1000/H$13,In!$L$109/1000)) | I41: =IF(In!$M$109="","",IF(In!$C$109="設施",In!$M$109/1000/I$13,In!$M$109/1000)) | J41: =IF(In!$N$109="","",IF(In!$C$109="設施",In!$N$109/1000/J$13,In!$N$109/1000)) | K41: =IF(In!$O$109="","",IF(In!$C$109="設施",In!$O$109/1000/K$13,In!$O$109/1000)) | L41: =IF(In!$P$109="","",IF(In!$C$109="設施",In!$P$109/1000/L$13,In!$P$109/1000)) | M41: =IF(In!$Q$109="","",IF(In!$C$109="設施",In!$Q$109/1000/M$13,In!$Q$109/1000))
A42: 晶片換算 IT GW | B42: googl_chip | C42: GW | D42: =IF(In!$H$102="","",In!$H$102*Players!$D$15/1000) -> 0.56057836 | E42: =IF(In!$I$102="","",In!$I$102*Players!$D$15/1000) -> 1.8903867 | F42: =IF(In!$J$102="","",In!$J$102*Players!$D$15/1000) -> 4.3 | G42: =IF(In!$K$102="","",In!$K$102*Players!$D$15/1000) | H42: =IF(In!$L$102="","",In!$L$102*Players!$D$15/1000) | I42: =IF(In!$M$102="","",In!$M$102*Players!$D$15/1000) | J42: =IF(In!$N$102="","",In!$N$102*Players!$D$15/1000) | K42: =IF(In!$O$102="","",In!$O$102*Players!$D$15/1000) | L42: =IF(In!$P$102="","",In!$P$102*Players!$D$15/1000) | M42: =IF(In!$Q$102="","",In!$Q$102*Players!$D$15/1000)
A43: 已知值 | B43: googl_k | C43: GW | D43: =IF(D41<>"",D41,IF(D42<>"",D42,IF(INT(obsd_googl)=2023,obschip_googl*Players!$D$15/1000+SUMIFS(Pipeline!$L$5:$L$64,Pipeline!$C$5:$C$64,"googl",Pipeline!$Q$5:$Q$64,1,Pipeline!$K$5:$K$64,">"&obsd_googl,Pipeline!$K$5:$K$64,"<="&2024),""))) -> 0.56057836 | E43: =IF(E41<>"",E41,IF(E42<>"",E42,IF(INT(obsd_googl)=2024,obschip_googl*Players!$D$15/1000+SUMIFS(Pipeline!$L$5:$L$64,Pipeline!$C$5:$C$64,"googl",Pipeline!$Q$5:$Q$64,1,Pipeline!$K$5:$K$64,">"&obsd_googl,Pipeline!$K$5:$K$64,"<="&2025),""))) -> 1.8903867 | F43: =IF(F41<>"",F41,IF(F42<>"",F42,IF(INT(obsd_googl)=2025,obschip_googl*Players!$D$15/1000+SUMIFS(Pipeline!$L$5:$L$64,Pipeline!$C$5:$C$64,"googl",Pipeline!$Q$5:$Q$64,1,Pipeline!$K$5:$K$64,">"&obsd_googl,Pipeline!$K$5:$K$64,"<="&2026),""))) -> 4.3 | G43: =IF(G41<>"",G41,IF(G42<>"",G42,IF(INT(obsd_googl)=2026,obschip_googl*Players!$D$15/1000+SUMIFS(Pipeline!$L$5:$L$64,Pipeline!$C$5:$C$64,"googl",Pipeline!$Q$5:$Q$64,1,Pipeline!$K$5:$K$64,">"&obsd_googl,Pipeline!$K$5:$K$64,"<="&2027),""))) -> 5.5926791 | H43: =IF(H41<>"",H41,IF(H42<>"",H42,IF(INT(obsd_googl)=2027,obschip_googl*Players!$D$15/1000+SUMIFS(Pipeline!$L$5:$L$64,Pipeline!$C$5:$C$64,"googl",Pipeline!$Q$5:$Q$64,1,Pipeline!$K$5:$K$64,">"&obsd_googl,Pipeline!$K$5:$K$64,"<="&2028),""))) | I43: =IF(I41<>"",I41,IF(I42<>"",I42,IF(INT(obsd_googl)=2028,obschip_googl*Players!$D$15/1000+SUMIFS(Pipeline!$L$5:$L$64,Pipeline!$C$5:$C$64,"googl",Pipeline!$Q$5:$Q$64,1,Pipeline!$K$5:$K$64,">"&obsd_googl,Pipeline!$K$5:$K$64,"<="&2029),""))) | J43: =IF(J41<>"",J41,IF(J42<>"",J42,IF(INT(obsd_googl)=2029,obschip_googl*Players!$D$15/1000+SUMIFS(Pipeline!$L$5:$L$64,Pipeline!$C$5:$C$64,"googl",Pipeline!$Q$5:$Q$64,1,Pipeline!$K$5:$K$64,">"&obsd_googl,Pipeline!$K$5:$K$64,"<="&2030),""))) | K43: =IF(K41<>"",K41,IF(K42<>"",K42,IF(INT(obsd_googl)=2030,obschip_googl*Players!$D$15/1000+SUMIFS(Pipeline!$L$5:$L$64,Pipeline!$C$5:$C$64,"googl",Pipeline!$Q$5:$Q$64,1,Pipeline!$K$5:$K$64,">"&obsd_googl,Pipeline!$K$5:$K$64,"<="&2031),""))) | L43: =IF(L41<>"",L41,IF(L42<>"",L42,IF(INT(obsd_googl)=2031,obschip_googl*Players!$D$15/1000+SUMIFS(Pipeline!$L$5:$L$64,Pipeline!$C$5:$C$64,"googl",Pipeline!$Q$5:$Q$64,1,Pipeline!$K$5:$K$64,">"&obsd_googl,Pipeline!$K$5:$K$64,"<="&2032),""))) | M43: =IF(M41<>"",M41,IF(M42<>"",M42,IF(INT(obsd_googl)=2032,obschip_googl*Players!$D$15/1000+SUMIFS(Pipeline!$L$5:$L$64,Pipeline!$C$5:$C$64,"googl",Pipeline!$Q$5:$Q$64,1,Pipeline!$K$5:$K$64,">"&obsd_googl,Pipeline!$K$5:$K$64,"<="&2033),"")))
A44: 前一已知值 | B44: googl_L | C44: GW | D44: =IF(D43<>"",D43,"") -> 0.56057836 | E44: =IF(E43<>"",E43,D44) -> 1.8903867 | F44: =IF(F43<>"",F43,E44) -> 4.3 | G44: =IF(G43<>"",G43,F44) -> 5.5926791 | H44: =IF(H43<>"",H43,G44) -> 5.5926791 | I44: =IF(I43<>"",I43,H44) -> 5.5926791 | J44: =IF(J43<>"",J43,I44) -> 5.5926791 | K44: =IF(K43<>"",K43,J44) -> 5.5926791 | L44: =IF(L43<>"",L43,K44) -> 5.5926791 | M44: =IF(M43<>"",M43,L44) -> 5.5926791
A45: 前一已知年 | B45: googl_LY | C45: 年 | D45: =IF(D43<>"",2023,"") -> 2023 | E45: =IF(E43<>"",2024,D45) -> 2024 | F45: =IF(F43<>"",2025,E45) -> 2025 | G45: =IF(G43<>"",2026,F45) -> 2026 | H45: =IF(H43<>"",2027,G45) -> 2026 | I45: =IF(I43<>"",2028,H45) -> 2026 | J45: =IF(J43<>"",2029,I45) -> 2026 | K45: =IF(K43<>"",2030,J45) -> 2026 | L45: =IF(L43<>"",2031,K45) -> 2026 | M45: =IF(M43<>"",2032,L45) -> 2026
A46: 下一已知值 | B46: googl_N | C46: GW | D46: =IF(D43<>"",D43,E46) -> 0.56057836 | E46: =IF(E43<>"",E43,F46) -> 1.8903867 | F46: =IF(F43<>"",F43,G46) -> 4.3 | G46: =IF(G43<>"",G43,H46) -> 5.5926791 | H46: =IF(H43<>"",H43,I46) | I46: =IF(I43<>"",I43,J46) | J46: =IF(J43<>"",J43,K46) | K46: =IF(K43<>"",K43,L46) | L46: =IF(L43<>"",L43,M46) | M46: =IF(M43<>"",M43,"")
A47: 下一已知年 | B47: googl_NY | C47: 年 | D47: =IF(D43<>"",2023,E47) -> 2023 | E47: =IF(E43<>"",2024,F47) -> 2024 | F47: =IF(F43<>"",2025,G47) -> 2025 | G47: =IF(G43<>"",2026,H47) -> 2026 | H47: =IF(H43<>"",2027,I47) | I47: =IF(I43<>"",2028,J47) | J47: =IF(J43<>"",2029,K47) | K47: =IF(K43<>"",2030,L47) | L47: =IF(L43<>"",2031,M47) | M47: =IF(M43<>"",2032,"")
A48: 當年 T2 園區上線（D0，IT GW） | B48: googl_cp | C48: GW | D48: =SUMIFS(Pipeline!$L$5:$L$64,Pipeline!$C$5:$C$64,"googl",Pipeline!$Q$5:$Q$64,1,Pipeline!$P$5:$P$64,2023) -> 0 | E48: =SUMIFS(Pipeline!$L$5:$L$64,Pipeline!$C$5:$C$64,"googl",Pipeline!$Q$5:$Q$64,1,Pipeline!$P$5:$P$64,2024) -> 0 | F48: =SUMIFS(Pipeline!$L$5:$L$64,Pipeline!$C$5:$C$64,"googl",Pipeline!$Q$5:$Q$64,1,Pipeline!$P$5:$P$64,2025) -> 0 | G48: =SUMIFS(Pipeline!$L$5:$L$64,Pipeline!$C$5:$C$64,"googl",Pipeline!$Q$5:$Q$64,1,Pipeline!$P$5:$P$64,2026) -> 0 | H48: =SUMIFS(Pipeline!$L$5:$L$64,Pipeline!$C$5:$C$64,"googl",Pipeline!$Q$5:$Q$64,1,Pipeline!$P$5:$P$64,2027) -> 0 | I48: =SUMIFS(Pipeline!$L$5:$L$64,Pipeline!$C$5:$C$64,"googl",Pipeline!$Q$5:$Q$64,1,Pipeline!$P$5:$P$64,2028) -> 0 | J48: =SUMIFS(Pipeline!$L$5:$L$64,Pipeline!$C$5:$C$64,"googl",Pipeline!$Q$5:$Q$64,1,Pipeline!$P$5:$P$64,2029) -> 0 | K48: =SUMIFS(Pipeline!$L$5:$L$64,Pipeline!$C$5:$C$64,"googl",Pipeline!$Q$5:$Q$64,1,Pipeline!$P$5:$P$64,2030) -> 0 | L48: =SUMIFS(Pipeline!$L$5:$L$64,Pipeline!$C$5:$C$64,"googl",Pipeline!$Q$5:$Q$64,1,Pipeline!$P$5:$P$64,2031) -> 0 | M48: =SUMIFS(Pipeline!$L$5:$L$64,Pipeline!$C$5:$C$64,"googl",Pipeline!$Q$5:$Q$64,1,Pipeline!$P$5:$P$64,2032) -> 0
A49: 年底上線 IT GW | B49: googl_tk | C49: GW | D49: =IF(D43<>"",D43,IF(AND(D44<>"",D46<>""),D44+(D46-D44)*(2023-D45)/(D47-D45),"")) -> 0.56057836 | E49: =IF(E43<>"",E43,IF(AND(E44<>"",E46<>""),E44+(E46-E44)*(2024-E45)/(E47-E45),IF(D49<>"",D49+E48,""))) -> 1.8903867 | F49: =IF(F43<>"",F43,IF(AND(F44<>"",F46<>""),F44+(F46-F44)*(2025-F45)/(F47-F45),IF(E49<>"",E49+F48,""))) -> 4.3 | G49: =IF(G43<>"",G43,IF(AND(G44<>"",G46<>""),G44+(G46-G44)*(2026-G45)/(G47-G45),IF(F49<>"",F49+G48,""))) -> 5.5926791 | H49: =IF(H43<>"",H43,IF(AND(H44<>"",H46<>""),H44+(H46-H44)*(2027-H45)/(H47-H45),IF(G49<>"",G49+H48,""))) -> 5.5926791 | I49: =IF(I43<>"",I43,IF(AND(I44<>"",I46<>""),I44+(I46-I44)*(2028-I45)/(I47-I45),IF(H49<>"",H49+I48,""))) -> 5.5926791 | J49: =IF(J43<>"",J43,IF(AND(J44<>"",J46<>""),J44+(J46-J44)*(2029-J45)/(J47-J45),IF(I49<>"",I49+J48,""))) -> 5.5926791 | K49: =IF(K43<>"",K43,IF(AND(K44<>"",K46<>""),K44+(K46-K44)*(2030-K45)/(K47-K45),IF(J49<>"",J49+K48,""))) -> 5.5926791 | L49: =IF(L43<>"",L43,IF(AND(L44<>"",L46<>""),L44+(L46-L44)*(2031-L45)/(L47-L45),IF(K49<>"",K49+L48,""))) -> 5.5926791 | M49: =IF(M43<>"",M43,IF(AND(M44<>"",M46<>""),M44+(M46-M44)*(2032-M45)/(M47-M45),IF(L49<>"",L49+M48,""))) -> 5.5926791
A50: 旗標 | B50: googl_f | C50: — | D50: =IF(D41<>"",1,IF(D42<>"",5,IF(D43<>"",2,IF(AND(D44<>"",D46<>""),3,IF(D49<>"",4,0))))) -> 5 | E50: =IF(E41<>"",1,IF(E42<>"",5,IF(E43<>"",2,IF(AND(E44<>"",E46<>""),3,IF(E49<>"",4,0))))) -> 5 | F50: =IF(F41<>"",1,IF(F42<>"",5,IF(F43<>"",2,IF(AND(F44<>"",F46<>""),3,IF(F49<>"",4,0))))) -> 5 | G50: =IF(G41<>"",1,IF(G42<>"",5,IF(G43<>"",2,IF(AND(G44<>"",G46<>""),3,IF(G49<>"",4,0))))) -> 2 | H50: =IF(H41<>"",1,IF(H42<>"",5,IF(H43<>"",2,IF(AND(H44<>"",H46<>""),3,IF(H49<>"",4,0))))) -> 4 | I50: =IF(I41<>"",1,IF(I42<>"",5,IF(I43<>"",2,IF(AND(I44<>"",I46<>""),3,IF(I49<>"",4,0))))) -> 4 | J50: =IF(J41<>"",1,IF(J42<>"",5,IF(J43<>"",2,IF(AND(J44<>"",J46<>""),3,IF(J49<>"",4,0))))) -> 4 | K50: =IF(K41<>"",1,IF(K42<>"",5,IF(K43<>"",2,IF(AND(K44<>"",K46<>""),3,IF(K49<>"",4,0))))) -> 4 | ... M50: =IF(M41<>"",1,IF(M42<>"",5,IF(M43<>"",2,IF(AND(M44<>"",M46<>""),3,IF(M49<>"",4,0))))) -> 4
A51: 年底上線 IT GW：低 | B51: googl_lo | C51: GW | D51: =IF(D49="","",IF(AND(D50=5,In!$H$102<>""),In!$H$102*Players!$E$15/1000,D49)) -> 0.50843153 | E51: =IF(E49="","",IF(AND(E50=5,In!$I$102<>""),In!$I$102*Players!$E$15/1000,E49)) -> 1.7145368 | F51: =IF(F49="","",IF(AND(F50=5,In!$J$102<>""),In!$J$102*Players!$E$15/1000,F49)) -> 3.9 | G51: =IF(G49="","",IF(AND(G50=5,In!$K$102<>""),In!$K$102*Players!$E$15/1000,G49)) -> 5.5926791 | H51: =IF(H49="","",IF(AND(H50=5,In!$L$102<>""),In!$L$102*Players!$E$15/1000,H49)) -> 5.5926791 | I51: =IF(I49="","",IF(AND(I50=5,In!$M$102<>""),In!$M$102*Players!$E$15/1000,I49)) -> 5.5926791 | J51: =IF(J49="","",IF(AND(J50=5,In!$N$102<>""),In!$N$102*Players!$E$15/1000,J49)) -> 5.5926791 | K51: =IF(K49="","",IF(AND(K50=5,In!$O$102<>""),In!$O$102*Players!$E$15/1000,K49)) -> 5.5926791 | L51: =IF(L49="","",IF(AND(L50=5,In!$P$102<>""),In!$P$102*Players!$E$15/1000,L49)) -> 5.5926791 | M51: =IF(M49="","",IF(AND(M50=5,In!$Q$102<>""),In!$Q$102*Players!$E$15/1000,M49)) -> 5.5926791
A52: 年底上線 IT GW：高 | B52: googl_hi | C52: GW | D52: =IF(D49="","",IF(AND(D50=5,In!$H$102<>""),In!$H$102*Players!$F$15/1000,D49)) -> 0.63879859 | E52: =IF(E49="","",IF(AND(E50=5,In!$I$102<>""),In!$I$102*Players!$F$15/1000,E49)) -> 2.1541616 | F52: =IF(F49="","",IF(AND(F50=5,In!$J$102<>""),In!$J$102*Players!$F$15/1000,F49)) -> 4.9 | G52: =IF(G49="","",IF(AND(G50=5,In!$K$102<>""),In!$K$102*Players!$F$15/1000,G49)) -> 5.5926791 | H52: =IF(H49="","",IF(AND(H50=5,In!$L$102<>""),In!$L$102*Players!$F$15/1000,H49)) -> 5.5926791 | I52: =IF(I49="","",IF(AND(I50=5,In!$M$102<>""),In!$M$102*Players!$F$15/1000,I49)) -> 5.5926791 | J52: =IF(J49="","",IF(AND(J50=5,In!$N$102<>""),In!$N$102*Players!$F$15/1000,J49)) -> 5.5926791 | K52: =IF(K49="","",IF(AND(K50=5,In!$O$102<>""),In!$O$102*Players!$F$15/1000,K49)) -> 5.5926791 | L52: =IF(L49="","",IF(AND(L50=5,In!$P$102<>""),In!$P$102*Players!$F$15/1000,L49)) -> 5.5926791 | M52: =IF(M49="","",IF(AND(M50=5,In!$Q$102<>""),In!$Q$102*Players!$F$15/1000,M49)) -> 5.5926791
A53: 另讀（口徑未說明者讀為設施 ÷ IF_FacilityGW） | B53: googl_alt | C53: GW | D53: =IF(D49="","",IF(In!$C$109="未說明",D49/D$13,D49)) -> 0.56057836 | E53: =IF(E49="","",IF(In!$C$109="未說明",E49/E$13,E49)) -> 1.8903867 | F53: =IF(F49="","",IF(In!$C$109="未說明",F49/F$13,F49)) -> 4.3 | G53: =IF(G49="","",IF(In!$C$109="未說明",G49/G$13,G49)) -> 5.5926791 | H53: =IF(H49="","",IF(In!$C$109="未說明",H49/H$13,H49)) -> 5.5926791 | I53: =IF(I49="","",IF(In!$C$109="未說明",I49/I$13,I49)) -> 5.5926791 | J53: =IF(J49="","",IF(In!$C$109="未說明",J49/J$13,J49)) -> 5.5926791 | K53: =IF(K49="","",IF(In!$C$109="未說明",K49/K$13,K49)) -> 5.5926791 | ... M53: =IF(M49="","",IF(In!$C$109="未說明",M49/M$13,M49)) -> 5.5926791
A54: 年平均 IT GW | B54: googl_avg | C54: GW | D54: ="" | E54: =IF(AND(D49<>"",E49<>""),(D49+E49)/2,"") -> 1.2254825 | F54: =IF(AND(E49<>"",F49<>""),(E49+F49)/2,"") -> 3.0951933 | G54: =IF(AND(F49<>"",G49<>""),(F49+G49)/2,"") -> 4.9463396 | H54: =IF(AND(G49<>"",H49<>""),(G49+H49)/2,"") -> 5.5926791 | I54: =IF(AND(H49<>"",I49<>""),(H49+I49)/2,"") -> 5.5926791 | J54: =IF(AND(I49<>"",J49<>""),(I49+J49)/2,"") -> 5.5926791 | K54: =IF(AND(J49<>"",K49<>""),(J49+K49)/2,"") -> 5.5926791 | L54: =IF(AND(K49<>"",L49<>""),(K49+L49)/2,"") -> 5.5926791 | M54: =IF(AND(L49<>"",M49<>""),(L49+M49)/2,"") -> 5.5926791
A55: 年新增 IT GW | B55: googl_add | C55: GW | D55: 0 | E55: =IF(AND(D49<>"",E49<>""),E49-D49,0) -> 1.3298083 | F55: =IF(AND(E49<>"",F49<>""),F49-E49,0) -> 2.4096133 | G55: =IF(AND(F49<>"",G49<>""),G49-F49,0) -> 1.2926791 | H55: =IF(AND(G49<>"",H49<>""),H49-G49,0) -> 0 | I55: =IF(AND(H49<>"",I49<>""),I49-H49,0) -> 0 | J55: =IF(AND(I49<>"",J49<>""),J49-I49,0) -> 0 | K55: =IF(AND(J49<>"",K49<>""),K49-J49,0) -> 0 | L55: =IF(AND(K49<>"",L49<>""),L49-K49,0) -> 0 | M55: =IF(AND(L49<>"",M49<>""),M49-L49,0) -> 0
A56: 新納入存量 IT GW | B56: googl_stk | C56: GW | D56: =IF(D49<>"",D49,0) -> 0.56057836 | E56: =IF(AND(D49="",E49<>""),E49,0) -> 0 | F56: =IF(AND(E49="",F49<>""),F49,0) -> 0 | G56: =IF(AND(F49="",G49<>""),G49,0) -> 0 | H56: =IF(AND(G49="",H49<>""),H49,0) -> 0 | I56: =IF(AND(H49="",I49<>""),I49,0) -> 0 | J56: =IF(AND(I49="",J49<>""),J49,0) -> 0 | K56: =IF(AND(J49="",K49<>""),K49,0) -> 0 | L56: =IF(AND(K49="",L49<>""),L49,0) -> 0 | M56: =IF(AND(L49="",M49<>""),M49,0) -> 0
A57: 新增 GW 非 NVIDIA 占比 | B57: googl_nnv | C57: % | D57: =nnv_googl -> 0.753 | E57: =nnv_googl -> 0.753 | F57: =nnv_googl -> 0.753 | G57: =nnv_googl -> 0.753 | H57: =nnv_googl -> 0.753 | I57: =nnv_googl -> 0.753 | J57: =nnv_googl -> 0.753 | K57: =nnv_googl -> 0.753 | ... M57: =nnv_googl -> 0.753
A59: Amazon（AWS；Trainium＋NVIDIA） | B59: amzn | N59: In 第 110 列；口徑＝In!C110
A60: 輸入（IT GW；設施 ÷ IF_FacilityGW） | B60: amzn_in | C60: GW | D60: =IF(In!$H$110="","",IF(In!$C$110="設施",In!$H$110/1000/D$13,In!$H$110/1000)) | E60: =IF(In!$I$110="","",IF(In!$C$110="設施",In!$I$110/1000/E$13,In!$I$110/1000)) | F60: =IF(In!$J$110="","",IF(In!$C$110="設施",In!$J$110/1000/F$13,In!$J$110/1000)) | G60: =IF(In!$K$110="","",IF(In!$C$110="設施",In!$K$110/1000/G$13,In!$K$110/1000)) | H60: =IF(In!$L$110="","",IF(In!$C$110="設施",In!$L$110/1000/H$13,In!$L$110/1000)) | I60: =IF(In!$M$110="","",IF(In!$C$110="設施",In!$M$110/1000/I$13,In!$M$110/1000)) | J60: =IF(In!$N$110="","",IF(In!$C$110="設施",In!$N$110/1000/J$13,In!$N$110/1000)) | K60: =IF(In!$O$110="","",IF(In!$C$110="設施",In!$O$110/1000/K$13,In!$O$110/1000)) | L60: =IF(In!$P$110="","",IF(In!$C$110="設施",In!$P$110/1000/L$13,In!$P$110/1000)) | M60: =IF(In!$Q$110="","",IF(In!$C$110="設施",In!$Q$110/1000/M$13,In!$Q$110/1000))
A61: 晶片換算 IT GW | B61: amzn_chip | C61: GW | D61: =IF(In!$H$103="","",In!$H$103*Players!$D$16/1000) | E61: =IF(In!$I$103="","",In!$I$103*Players!$D$16/1000) -> 0.81028401 | F61: =IF(In!$J$103="","",In!$J$103*Players!$D$16/1000) -> 2.2 | G61: =IF(In!$K$103="","",In!$K$103*Players!$D$16/1000) | H61: =IF(In!$L$103="","",In!$L$103*Players!$D$16/1000) | I61: =IF(In!$M$103="","",In!$M$103*Players!$D$16/1000) | J61: =IF(In!$N$103="","",In!$N$103*Players!$D$16/1000) | K61: =IF(In!$O$103="","",In!$O$103*Players!$D$16/1000) | L61: =IF(In!$P$103="","",In!$P$103*Players!$D$16/1000) | M61: =IF(In!$Q$103="","",In!$Q$103*Players!$D$16/1000)
A62: 已知值 | B62: amzn_k | C62: GW | D62: =IF(D60<>"",D60,IF(D61<>"",D61,IF(INT(obsd_amzn)=2023,obs_amzn/1000+SUMIFS(Pipeline!$L$5:$L$64,Pipeline!$C$5:$C$64,"amzn",Pipeline!$Q$5:$Q$64,1,Pipeline!$K$5:$K$64,">"&obsd_amzn,Pipeline!$K$5:$K$64,"<="&2024),""))) | E62: =IF(E60<>"",E60,IF(E61<>"",E61,IF(INT(obsd_amzn)=2024,obs_amzn/1000+SUMIFS(Pipeline!$L$5:$L$64,Pipeline!$C$5:$C$64,"amzn",Pipeline!$Q$5:$Q$64,1,Pipeline!$K$5:$K$64,">"&obsd_amzn,Pipeline!$K$5:$K$64,"<="&2025),""))) -> 0.81028401 | F62: =IF(F60<>"",F60,IF(F61<>"",F61,IF(INT(obsd_amzn)=2025,obs_amzn/1000+SUMIFS(Pipeline!$L$5:$L$64,Pipeline!$C$5:$C$64,"amzn",Pipeline!$Q$5:$Q$64,1,Pipeline!$K$5:$K$64,">"&obsd_amzn,Pipeline!$K$5:$K$64,"<="&2026),""))) -> 2.2 | G62: =IF(G60<>"",G60,IF(G61<>"",G61,IF(INT(obsd_amzn)=2026,obs_amzn/1000+SUMIFS(Pipeline!$L$5:$L$64,Pipeline!$C$5:$C$64,"amzn",Pipeline!$Q$5:$Q$64,1,Pipeline!$K$5:$K$64,">"&obsd_amzn,Pipeline!$K$5:$K$64,"<="&2027),""))) -> 2.727 | H62: =IF(H60<>"",H60,IF(H61<>"",H61,IF(INT(obsd_amzn)=2027,obs_amzn/1000+SUMIFS(Pipeline!$L$5:$L$64,Pipeline!$C$5:$C$64,"amzn",Pipeline!$Q$5:$Q$64,1,Pipeline!$K$5:$K$64,">"&obsd_amzn,Pipeline!$K$5:$K$64,"<="&2028),""))) | I62: =IF(I60<>"",I60,IF(I61<>"",I61,IF(INT(obsd_amzn)=2028,obs_amzn/1000+SUMIFS(Pipeline!$L$5:$L$64,Pipeline!$C$5:$C$64,"amzn",Pipeline!$Q$5:$Q$64,1,Pipeline!$K$5:$K$64,">"&obsd_amzn,Pipeline!$K$5:$K$64,"<="&2029),""))) | J62: =IF(J60<>"",J60,IF(J61<>"",J61,IF(INT(obsd_amzn)=2029,obs_amzn/1000+SUMIFS(Pipeline!$L$5:$L$64,Pipeline!$C$5:$C$64,"amzn",Pipeline!$Q$5:$Q$64,1,Pipeline!$K$5:$K$64,">"&obsd_amzn,Pipeline!$K$5:$K$64,"<="&2030),""))) | K62: =IF(K60<>"",K60,IF(K61<>"",K61,IF(INT(obsd_amzn)=2030,obs_amzn/1000+SUMIFS(Pipeline!$L$5:$L$64,Pipeline!$C$5:$C$64,"amzn",Pipeline!$Q$5:$Q$64,1,Pipeline!$K$5:$K$64,">"&obsd_amzn,Pipeline!$K$5:$K$64,"<="&2031),""))) | L62: =IF(L60<>"",L60,IF(L61<>"",L61,IF(INT(obsd_amzn)=2031,obs_amzn/1000+SUMIFS(Pipeline!$L$5:$L$64,Pipeline!$C$5:$C$64,"amzn",Pipeline!$Q$5:$Q$64,1,Pipeline!$K$5:$K$64,">"&obsd_amzn,Pipeline!$K$5:$K$64,"<="&2032),""))) | M62: =IF(M60<>"",M60,IF(M61<>"",M61,IF(INT(obsd_amzn)=2032,obs_amzn/1000+SUMIFS(Pipeline!$L$5:$L$64,Pipeline!$C$5:$C$64,"amzn",Pipeline!$Q$5:$Q$64,1,Pipeline!$K$5:$K$64,">"&obsd_amzn,Pipeline!$K$5:$K$64,"<="&2033),"")))
A63: 前一已知值 | B63: amzn_L | C63: GW | D63: =IF(D62<>"",D62,"") | E63: =IF(E62<>"",E62,D63) -> 0.81028401 | F63: =IF(F62<>"",F62,E63) -> 2.2 | G63: =IF(G62<>"",G62,F63) -> 2.727 | H63: =IF(H62<>"",H62,G63) -> 2.727 | I63: =IF(I62<>"",I62,H63) -> 2.727 | J63: =IF(J62<>"",J62,I63) -> 2.727 | K63: =IF(K62<>"",K62,J63) -> 2.727 | L63: =IF(L62<>"",L62,K63) -> 2.727 | M63: =IF(M62<>"",M62,L63) -> 2.727
A64: 前一已知年 | B64: amzn_LY | C64: 年 | D64: =IF(D62<>"",2023,"") | E64: =IF(E62<>"",2024,D64) -> 2024 | F64: =IF(F62<>"",2025,E64) -> 2025 | G64: =IF(G62<>"",2026,F64) -> 2026 | H64: =IF(H62<>"",2027,G64) -> 2026 | I64: =IF(I62<>"",2028,H64) -> 2026 | J64: =IF(J62<>"",2029,I64) -> 2026 | K64: =IF(K62<>"",2030,J64) -> 2026 | L64: =IF(L62<>"",2031,K64) -> 2026 | M64: =IF(M62<>"",2032,L64) -> 2026
A65: 下一已知值 | B65: amzn_N | C65: GW | D65: =IF(D62<>"",D62,E65) -> 0.81028401 | E65: =IF(E62<>"",E62,F65) -> 0.81028401 | F65: =IF(F62<>"",F62,G65) -> 2.2 | G65: =IF(G62<>"",G62,H65) -> 2.727 | H65: =IF(H62<>"",H62,I65) | I65: =IF(I62<>"",I62,J65) | J65: =IF(J62<>"",J62,K65) | K65: =IF(K62<>"",K62,L65) | L65: =IF(L62<>"",L62,M65) | M65: =IF(M62<>"",M62,"")
A66: 下一已知年 | B66: amzn_NY | C66: 年 | D66: =IF(D62<>"",2023,E66) -> 2024 | E66: =IF(E62<>"",2024,F66) -> 2024 | F66: =IF(F62<>"",2025,G66) -> 2025 | G66: =IF(G62<>"",2026,H66) -> 2026 | H66: =IF(H62<>"",2027,I66) | I66: =IF(I62<>"",2028,J66) | J66: =IF(J62<>"",2029,K66) | K66: =IF(K62<>"",2030,L66) | L66: =IF(L62<>"",2031,M66) | M66: =IF(M62<>"",2032,"")
A67: 當年 T2 園區上線（D0，IT GW） | B67: amzn_cp | C67: GW | D67: =SUMIFS(Pipeline!$L$5:$L$64,Pipeline!$C$5:$C$64,"amzn",Pipeline!$Q$5:$Q$64,1,Pipeline!$P$5:$P$64,2023) -> 0 | E67: =SUMIFS(Pipeline!$L$5:$L$64,Pipeline!$C$5:$C$64,"amzn",Pipeline!$Q$5:$Q$64,1,Pipeline!$P$5:$P$64,2024) -> 0 | F67: =SUMIFS(Pipeline!$L$5:$L$64,Pipeline!$C$5:$C$64,"amzn",Pipeline!$Q$5:$Q$64,1,Pipeline!$P$5:$P$64,2025) -> 0 | G67: =SUMIFS(Pipeline!$L$5:$L$64,Pipeline!$C$5:$C$64,"amzn",Pipeline!$Q$5:$Q$64,1,Pipeline!$P$5:$P$64,2026) -> 0.127 | H67: =SUMIFS(Pipeline!$L$5:$L$64,Pipeline!$C$5:$C$64,"amzn",Pipeline!$Q$5:$Q$64,1,Pipeline!$P$5:$P$64,2027) -> 0.041 | I67: =SUMIFS(Pipeline!$L$5:$L$64,Pipeline!$C$5:$C$64,"amzn",Pipeline!$Q$5:$Q$64,1,Pipeline!$P$5:$P$64,2028) -> 1.444 | J67: =SUMIFS(Pipeline!$L$5:$L$64,Pipeline!$C$5:$C$64,"amzn",Pipeline!$Q$5:$Q$64,1,Pipeline!$P$5:$P$64,2029) -> 0.062 | K67: =SUMIFS(Pipeline!$L$5:$L$64,Pipeline!$C$5:$C$64,"amzn",Pipeline!$Q$5:$Q$64,1,Pipeline!$P$5:$P$64,2030) -> 0 | L67: =SUMIFS(Pipeline!$L$5:$L$64,Pipeline!$C$5:$C$64,"amzn",Pipeline!$Q$5:$Q$64,1,Pipeline!$P$5:$P$64,2031) -> 0 | M67: =SUMIFS(Pipeline!$L$5:$L$64,Pipeline!$C$5:$C$64,"amzn",Pipeline!$Q$5:$Q$64,1,Pipeline!$P$5:$P$64,2032) -> 0
A68: 年底上線 IT GW | B68: amzn_tk | C68: GW | D68: =IF(D62<>"",D62,IF(AND(D63<>"",D65<>""),D63+(D65-D63)*(2023-D64)/(D66-D64),"")) | E68: =IF(E62<>"",E62,IF(AND(E63<>"",E65<>""),E63+(E65-E63)*(2024-E64)/(E66-E64),IF(D68<>"",D68+E67,""))) -> 0.81028401 | F68: =IF(F62<>"",F62,IF(AND(F63<>"",F65<>""),F63+(F65-F63)*(2025-F64)/(F66-F64),IF(E68<>"",E68+F67,""))) -> 2.2 | G68: =IF(G62<>"",G62,IF(AND(G63<>"",G65<>""),G63+(G65-G63)*(2026-G64)/(G66-G64),IF(F68<>"",F68+G67,""))) -> 2.727 | H68: =IF(H62<>"",H62,IF(AND(H63<>"",H65<>""),H63+(H65-H63)*(2027-H64)/(H66-H64),IF(G68<>"",G68+H67,""))) -> 2.768 | I68: =IF(I62<>"",I62,IF(AND(I63<>"",I65<>""),I63+(I65-I63)*(2028-I64)/(I66-I64),IF(H68<>"",H68+I67,""))) -> 4.212 | J68: =IF(J62<>"",J62,IF(AND(J63<>"",J65<>""),J63+(J65-J63)*(2029-J64)/(J66-J64),IF(I68<>"",I68+J67,""))) -> 4.274 | K68: =IF(K62<>"",K62,IF(AND(K63<>"",K65<>""),K63+(K65-K63)*(2030-K64)/(K66-K64),IF(J68<>"",J68+K67,""))) -> 4.274 | L68: =IF(L62<>"",L62,IF(AND(L63<>"",L65<>""),L63+(L65-L63)*(2031-L64)/(L66-L64),IF(K68<>"",K68+L67,""))) -> 4.274 | M68: =IF(M62<>"",M62,IF(AND(M63<>"",M65<>""),M63+(M65-M63)*(2032-M64)/(M66-M64),IF(L68<>"",L68+M67,""))) -> 4.274
A69: 旗標 | B69: amzn_f | C69: — | D69: =IF(D60<>"",1,IF(D61<>"",5,IF(D62<>"",2,IF(AND(D63<>"",D65<>""),3,IF(D68<>"",4,0))))) -> 0 | E69: =IF(E60<>"",1,IF(E61<>"",5,IF(E62<>"",2,IF(AND(E63<>"",E65<>""),3,IF(E68<>"",4,0))))) -> 5 | F69: =IF(F60<>"",1,IF(F61<>"",5,IF(F62<>"",2,IF(AND(F63<>"",F65<>""),3,IF(F68<>"",4,0))))) -> 5 | G69: =IF(G60<>"",1,IF(G61<>"",5,IF(G62<>"",2,IF(AND(G63<>"",G65<>""),3,IF(G68<>"",4,0))))) -> 2 | H69: =IF(H60<>"",1,IF(H61<>"",5,IF(H62<>"",2,IF(AND(H63<>"",H65<>""),3,IF(H68<>"",4,0))))) -> 4 | I69: =IF(I60<>"",1,IF(I61<>"",5,IF(I62<>"",2,IF(AND(I63<>"",I65<>""),3,IF(I68<>"",4,0))))) -> 4 | J69: =IF(J60<>"",1,IF(J61<>"",5,IF(J62<>"",2,IF(AND(J63<>"",J65<>""),3,IF(J68<>"",4,0))))) -> 4 | K69: =IF(K60<>"",1,IF(K61<>"",5,IF(K62<>"",2,IF(AND(K63<>"",K65<>""),3,IF(K68<>"",4,0))))) -> 4 | ... M69: =IF(M60<>"",1,IF(M61<>"",5,IF(M62<>"",2,IF(AND(M63<>"",M65<>""),3,IF(M68<>"",4,0))))) -> 4
A70: 年底上線 IT GW：低 | B70: amzn_lo | C70: GW | D70: =IF(D68="","",IF(D69=2,D68-(obs_amzn-obs_amzn_lo)/1000,IF(AND(D69=5,In!$H$103<>""),In!$H$103*Players!$E$16/1000,D68))) | E70: =IF(E68="","",IF(E69=2,E68-(obs_amzn-obs_amzn_lo)/1000,IF(AND(E69=5,In!$I$103<>""),In!$I$103*Players!$E$16/1000,E68))) -> 0.69979073 | F70: =IF(F68="","",IF(F69=2,F68-(obs_amzn-obs_amzn_lo)/1000,IF(AND(F69=5,In!$J$103<>""),In!$J$103*Players!$E$16/1000,F68))) -> 1.9 | G70: =IF(G68="","",IF(G69=2,G68-(obs_amzn-obs_amzn_lo)/1000,IF(AND(G69=5,In!$K$103<>""),In!$K$103*Players!$E$16/1000,G68))) -> 2.127 | H70: =IF(H68="","",IF(H69=2,H68-(obs_amzn-obs_amzn_lo)/1000,IF(AND(H69=5,In!$L$103<>""),In!$L$103*Players!$E$16/1000,H68))) -> 2.768 | I70: =IF(I68="","",IF(I69=2,I68-(obs_amzn-obs_amzn_lo)/1000,IF(AND(I69=5,In!$M$103<>""),In!$M$103*Players!$E$16/1000,I68))) -> 4.212 | J70: =IF(J68="","",IF(J69=2,J68-(obs_amzn-obs_amzn_lo)/1000,IF(AND(J69=5,In!$N$103<>""),In!$N$103*Players!$E$16/1000,J68))) -> 4.274 | K70: =IF(K68="","",IF(K69=2,K68-(obs_amzn-obs_amzn_lo)/1000,IF(AND(K69=5,In!$O$103<>""),In!$O$103*Players!$E$16/1000,K68))) -> 4.274 | L70: =IF(L68="","",IF(L69=2,L68-(obs_amzn-obs_amzn_lo)/1000,IF(AND(L69=5,In!$P$103<>""),In!$P$103*Players!$E$16/1000,L68))) -> 4.274 | M70: =IF(M68="","",IF(M69=2,M68-(obs_amzn-obs_amzn_lo)/1000,IF(AND(M69=5,In!$Q$103<>""),In!$Q$103*Players!$E$16/1000,M68))) -> 4.274
A71: 年底上線 IT GW：高 | B71: amzn_hi | C71: GW | D71: =IF(D68="","",IF(D69=2,D68+(obs_amzn_hi-obs_amzn)/1000,IF(AND(D69=5,In!$H$103<>""),In!$H$103*Players!$F$16/1000,D68))) | E71: =IF(E68="","",IF(E69=2,E68+(obs_amzn_hi-obs_amzn)/1000,IF(AND(E69=5,In!$I$103<>""),In!$I$103*Players!$F$16/1000,E68))) -> 0.95760837 | F71: =IF(F68="","",IF(F69=2,F68+(obs_amzn_hi-obs_amzn)/1000,IF(AND(F69=5,In!$J$103<>""),In!$J$103*Players!$F$16/1000,F68))) -> 2.6 | G71: =IF(G68="","",IF(G69=2,G68+(obs_amzn_hi-obs_amzn)/1000,IF(AND(G69=5,In!$K$103<>""),In!$K$103*Players!$F$16/1000,G68))) -> 3.427 | H71: =IF(H68="","",IF(H69=2,H68+(obs_amzn_hi-obs_amzn)/1000,IF(AND(H69=5,In!$L$103<>""),In!$L$103*Players!$F$16/1000,H68))) -> 2.768 | I71: =IF(I68="","",IF(I69=2,I68+(obs_amzn_hi-obs_amzn)/1000,IF(AND(I69=5,In!$M$103<>""),In!$M$103*Players!$F$16/1000,I68))) -> 4.212 | J71: =IF(J68="","",IF(J69=2,J68+(obs_amzn_hi-obs_amzn)/1000,IF(AND(J69=5,In!$N$103<>""),In!$N$103*Players!$F$16/1000,J68))) -> 4.274 | K71: =IF(K68="","",IF(K69=2,K68+(obs_amzn_hi-obs_amzn)/1000,IF(AND(K69=5,In!$O$103<>""),In!$O$103*Players!$F$16/1000,K68))) -> 4.274 | L71: =IF(L68="","",IF(L69=2,L68+(obs_amzn_hi-obs_amzn)/1000,IF(AND(L69=5,In!$P$103<>""),In!$P$103*Players!$F$16/1000,L68))) -> 4.274 | M71: =IF(M68="","",IF(M69=2,M68+(obs_amzn_hi-obs_amzn)/1000,IF(AND(M69=5,In!$Q$103<>""),In!$Q$103*Players!$F$16/1000,M68))) -> 4.274
A72: 另讀（口徑未說明者讀為設施 ÷ IF_FacilityGW） | B72: amzn_alt | C72: GW | D72: =IF(D68="","",IF(In!$C$110="未說明",D68/D$13,D68)) | E72: =IF(E68="","",IF(In!$C$110="未說明",E68/E$13,E68)) -> 0.81028401 | F72: =IF(F68="","",IF(In!$C$110="未說明",F68/F$13,F68)) -> 2.2 | G72: =IF(G68="","",IF(In!$C$110="未說明",G68/G$13,G68)) -> 2.727 | H72: =IF(H68="","",IF(In!$C$110="未說明",H68/H$13,H68)) -> 2.768 | I72: =IF(I68="","",IF(In!$C$110="未說明",I68/I$13,I68)) -> 4.212 | J72: =IF(J68="","",IF(In!$C$110="未說明",J68/J$13,J68)) -> 4.274 | K72: =IF(K68="","",IF(In!$C$110="未說明",K68/K$13,K68)) -> 4.274 | ... M72: =IF(M68="","",IF(In!$C$110="未說明",M68/M$13,M68)) -> 4.274
A73: 年平均 IT GW | B73: amzn_avg | C73: GW | D73: ="" | E73: =IF(AND(D68<>"",E68<>""),(D68+E68)/2,"") | F73: =IF(AND(E68<>"",F68<>""),(E68+F68)/2,"") -> 1.505142 | G73: =IF(AND(F68<>"",G68<>""),(F68+G68)/2,"") -> 2.4635 | H73: =IF(AND(G68<>"",H68<>""),(G68+H68)/2,"") -> 2.7475 | I73: =IF(AND(H68<>"",I68<>""),(H68+I68)/2,"") -> 3.49 | J73: =IF(AND(I68<>"",J68<>""),(I68+J68)/2,"") -> 4.243 | K73: =IF(AND(J68<>"",K68<>""),(J68+K68)/2,"") -> 4.274 | L73: =IF(AND(K68<>"",L68<>""),(K68+L68)/2,"") -> 4.274 | M73: =IF(AND(L68<>"",M68<>""),(L68+M68)/2,"") -> 4.274
A74: 年新增 IT GW | B74: amzn_add | C74: GW | D74: 0 | E74: =IF(AND(D68<>"",E68<>""),E68-D68,0) -> 0 | F74: =IF(AND(E68<>"",F68<>""),F68-E68,0) -> 1.389716 | G74: =IF(AND(F68<>"",G68<>""),G68-F68,0) -> 0.527 | H74: =IF(AND(G68<>"",H68<>""),H68-G68,0) -> 0.041 | I74: =IF(AND(H68<>"",I68<>""),I68-H68,0) -> 1.444 | J74: =IF(AND(I68<>"",J68<>""),J68-I68,0) -> 0.062 | K74: =IF(AND(J68<>"",K68<>""),K68-J68,0) -> 0 | L74: =IF(AND(K68<>"",L68<>""),L68-K68,0) -> 0 | M74: =IF(AND(L68<>"",M68<>""),M68-L68,0) -> 0
A75: 新納入存量 IT GW | B75: amzn_stk | C75: GW | D75: =IF(D68<>"",D68,0) -> 0 | E75: =IF(AND(D68="",E68<>""),E68,0) -> 0.81028401 | F75: =IF(AND(E68="",F68<>""),F68,0) -> 0 | G75: =IF(AND(F68="",G68<>""),G68,0) -> 0 | H75: =IF(AND(G68="",H68<>""),H68,0) -> 0 | I75: =IF(AND(H68="",I68<>""),I68,0) -> 0 | J75: =IF(AND(I68="",J68<>""),J68,0) -> 0 | K75: =IF(AND(J68="",K68<>""),K68,0) -> 0 | L75: =IF(AND(K68="",L68<>""),L68,0) -> 0 | M75: =IF(AND(L68="",M68<>""),M68,0) -> 0
A76: 新增 GW 非 NVIDIA 占比 | B76: amzn_nnv | C76: % | D76: =nnv_amzn -> 0.67 | E76: =nnv_amzn -> 0.67 | F76: =nnv_amzn -> 0.67 | G76: =nnv_amzn -> 0.67 | H76: =nnv_amzn -> 0.67 | I76: =nnv_amzn -> 0.67 | J76: =nnv_amzn -> 0.67 | K76: =nnv_amzn -> 0.67 | ... M76: =nnv_amzn -> 0.67
A78: Meta | B78: meta | N78: In 第 111 列；口徑＝In!C111
A79: 輸入（IT GW；設施 ÷ IF_FacilityGW） | B79: meta_in | C79: GW | D79: =IF(In!$H$111="","",IF(In!$C$111="設施",In!$H$111/1000/D$13,In!$H$111/1000)) | E79: =IF(In!$I$111="","",IF(In!$C$111="設施",In!$I$111/1000/E$13,In!$I$111/1000)) | F79: =IF(In!$J$111="","",IF(In!$C$111="設施",In!$J$111/1000/F$13,In!$J$111/1000)) | G79: =IF(In!$K$111="","",IF(In!$C$111="設施",In!$K$111/1000/G$13,In!$K$111/1000)) | H79: =IF(In!$L$111="","",IF(In!$C$111="設施",In!$L$111/1000/H$13,In!$L$111/1000)) | I79: =IF(In!$M$111="","",IF(In!$C$111="設施",In!$M$111/1000/I$13,In!$M$111/1000)) | J79: =IF(In!$N$111="","",IF(In!$C$111="設施",In!$N$111/1000/J$13,In!$N$111/1000)) | K79: =IF(In!$O$111="","",IF(In!$C$111="設施",In!$O$111/1000/K$13,In!$O$111/1000)) | L79: =IF(In!$P$111="","",IF(In!$C$111="設施",In!$P$111/1000/L$13,In!$P$111/1000)) | M79: =IF(In!$Q$111="","",IF(In!$C$111="設施",In!$Q$111/1000/M$13,In!$Q$111/1000))
A80: 晶片換算 IT GW | B80: meta_chip | C80: GW | D80: =IF(In!$H$104="","",In!$H$104*Players!$D$17/1000) | E80: =IF(In!$I$104="","",In!$I$104*Players!$D$17/1000) -> 0.968475 | F80: =IF(In!$J$104="","",In!$J$104*Players!$D$17/1000) -> 2.476595 | G80: =IF(In!$K$104="","",In!$K$104*Players!$D$17/1000) | H80: =IF(In!$L$104="","",In!$L$104*Players!$D$17/1000) | I80: =IF(In!$M$104="","",In!$M$104*Players!$D$17/1000) | J80: =IF(In!$N$104="","",In!$N$104*Players!$D$17/1000) | K80: =IF(In!$O$104="","",In!$O$104*Players!$D$17/1000) | L80: =IF(In!$P$104="","",In!$P$104*Players!$D$17/1000) | M80: =IF(In!$Q$104="","",In!$Q$104*Players!$D$17/1000)
A81: 已知值 | B81: meta_k | C81: GW | D81: =IF(D79<>"",D79,IF(D80<>"",D80,"")) | E81: =IF(E79<>"",E79,IF(E80<>"",E80,"")) -> 0.968475 | F81: =IF(F79<>"",F79,IF(F80<>"",F80,"")) -> 2.476595 | G81: =IF(G79<>"",G79,IF(G80<>"",G80,"")) | H81: =IF(H79<>"",H79,IF(H80<>"",H80,"")) | I81: =IF(I79<>"",I79,IF(I80<>"",I80,"")) | J81: =IF(J79<>"",J79,IF(J80<>"",J80,"")) | K81: =IF(K79<>"",K79,IF(K80<>"",K80,"")) | ... M81: =IF(M79<>"",M79,IF(M80<>"",M80,""))
A82: 前一已知值 | B82: meta_L | C82: GW | D82: =IF(D81<>"",D81,"") | E82: =IF(E81<>"",E81,D82) -> 0.968475 | F82: =IF(F81<>"",F81,E82) -> 2.476595 | G82: =IF(G81<>"",G81,F82) -> 2.476595 | H82: =IF(H81<>"",H81,G82) -> 2.476595 | I82: =IF(I81<>"",I81,H82) -> 2.476595 | J82: =IF(J81<>"",J81,I82) -> 2.476595 | K82: =IF(K81<>"",K81,J82) -> 2.476595 | L82: =IF(L81<>"",L81,K82) -> 2.476595 | M82: =IF(M81<>"",M81,L82) -> 2.476595
A83: 前一已知年 | B83: meta_LY | C83: 年 | D83: =IF(D81<>"",2023,"") | E83: =IF(E81<>"",2024,D83) -> 2024 | F83: =IF(F81<>"",2025,E83) -> 2025 | G83: =IF(G81<>"",2026,F83) -> 2025 | H83: =IF(H81<>"",2027,G83) -> 2025 | I83: =IF(I81<>"",2028,H83) -> 2025 | J83: =IF(J81<>"",2029,I83) -> 2025 | K83: =IF(K81<>"",2030,J83) -> 2025 | L83: =IF(L81<>"",2031,K83) -> 2025 | M83: =IF(M81<>"",2032,L83) -> 2025
A84: 下一已知值 | B84: meta_N | C84: GW | D84: =IF(D81<>"",D81,E84) -> 0.968475 | E84: =IF(E81<>"",E81,F84) -> 0.968475 | F84: =IF(F81<>"",F81,G84) -> 2.476595 | G84: =IF(G81<>"",G81,H84) | H84: =IF(H81<>"",H81,I84) | I84: =IF(I81<>"",I81,J84) | J84: =IF(J81<>"",J81,K84) | K84: =IF(K81<>"",K81,L84) | L84: =IF(L81<>"",L81,M84) | M84: =IF(M81<>"",M81,"")
A85: 下一已知年 | B85: meta_NY | C85: 年 | D85: =IF(D81<>"",2023,E85) -> 2024 | E85: =IF(E81<>"",2024,F85) -> 2024 | F85: =IF(F81<>"",2025,G85) -> 2025 | G85: =IF(G81<>"",2026,H85) | H85: =IF(H81<>"",2027,I85) | I85: =IF(I81<>"",2028,J85) | J85: =IF(J81<>"",2029,K85) | K85: =IF(K81<>"",2030,L85) | L85: =IF(L81<>"",2031,M85) | M85: =IF(M81<>"",2032,"")
A86: 當年 T2 園區上線（D0，IT GW） | B86: meta_cp | C86: GW | D86: =SUMIFS(Pipeline!$L$5:$L$64,Pipeline!$C$5:$C$64,"meta",Pipeline!$Q$5:$Q$64,1,Pipeline!$P$5:$P$64,2023) -> 0 | E86: =SUMIFS(Pipeline!$L$5:$L$64,Pipeline!$C$5:$C$64,"meta",Pipeline!$Q$5:$Q$64,1,Pipeline!$P$5:$P$64,2024) -> 0 | F86: =SUMIFS(Pipeline!$L$5:$L$64,Pipeline!$C$5:$C$64,"meta",Pipeline!$Q$5:$Q$64,1,Pipeline!$P$5:$P$64,2025) -> 0 | G86: =SUMIFS(Pipeline!$L$5:$L$64,Pipeline!$C$5:$C$64,"meta",Pipeline!$Q$5:$Q$64,1,Pipeline!$P$5:$P$64,2026) -> 0.676 | H86: =SUMIFS(Pipeline!$L$5:$L$64,Pipeline!$C$5:$C$64,"meta",Pipeline!$Q$5:$Q$64,1,Pipeline!$P$5:$P$64,2027) -> 0.192 | I86: =SUMIFS(Pipeline!$L$5:$L$64,Pipeline!$C$5:$C$64,"meta",Pipeline!$Q$5:$Q$64,1,Pipeline!$P$5:$P$64,2028) -> 2.786 | J86: =SUMIFS(Pipeline!$L$5:$L$64,Pipeline!$C$5:$C$64,"meta",Pipeline!$Q$5:$Q$64,1,Pipeline!$P$5:$P$64,2029) -> 0.368 | K86: =SUMIFS(Pipeline!$L$5:$L$64,Pipeline!$C$5:$C$64,"meta",Pipeline!$Q$5:$Q$64,1,Pipeline!$P$5:$P$64,2030) -> 0 | L86: =SUMIFS(Pipeline!$L$5:$L$64,Pipeline!$C$5:$C$64,"meta",Pipeline!$Q$5:$Q$64,1,Pipeline!$P$5:$P$64,2031) -> 0 | M86: =SUMIFS(Pipeline!$L$5:$L$64,Pipeline!$C$5:$C$64,"meta",Pipeline!$Q$5:$Q$64,1,Pipeline!$P$5:$P$64,2032) -> 0
A87: 年底上線 IT GW | B87: meta_tk | C87: GW | D87: =IF(D81<>"",D81,IF(AND(D82<>"",D84<>""),D82+(D84-D82)*(2023-D83)/(D85-D83),"")) | E87: =IF(E81<>"",E81,IF(AND(E82<>"",E84<>""),E82+(E84-E82)*(2024-E83)/(E85-E83),IF(D87<>"",D87+E86,""))) -> 0.968475 | F87: =IF(F81<>"",F81,IF(AND(F82<>"",F84<>""),F82+(F84-F82)*(2025-F83)/(F85-F83),IF(E87<>"",E87+F86,""))) -> 2.476595 | G87: =IF(G81<>"",G81,IF(AND(G82<>"",G84<>""),G82+(G84-G82)*(2026-G83)/(G85-G83),IF(F87<>"",F87+G86,""))) -> 3.152595 | H87: =IF(H81<>"",H81,IF(AND(H82<>"",H84<>""),H82+(H84-H82)*(2027-H83)/(H85-H83),IF(G87<>"",G87+H86,""))) -> 3.344595 | I87: =IF(I81<>"",I81,IF(AND(I82<>"",I84<>""),I82+(I84-I82)*(2028-I83)/(I85-I83),IF(H87<>"",H87+I86,""))) -> 6.130595 | J87: =IF(J81<>"",J81,IF(AND(J82<>"",J84<>""),J82+(J84-J82)*(2029-J83)/(J85-J83),IF(I87<>"",I87+J86,""))) -> 6.498595 | K87: =IF(K81<>"",K81,IF(AND(K82<>"",K84<>""),K82+(K84-K82)*(2030-K83)/(K85-K83),IF(J87<>"",J87+K86,""))) -> 6.498595 | L87: =IF(L81<>"",L81,IF(AND(L82<>"",L84<>""),L82+(L84-L82)*(2031-L83)/(L85-L83),IF(K87<>"",K87+L86,""))) -> 6.498595 | M87: =IF(M81<>"",M81,IF(AND(M82<>"",M84<>""),M82+(M84-M82)*(2032-M83)/(M85-M83),IF(L87<>"",L87+M86,""))) -> 6.498595
A88: 旗標 | B88: meta_f | C88: — | D88: =IF(D79<>"",1,IF(D80<>"",5,IF(D81<>"",2,IF(AND(D82<>"",D84<>""),3,IF(D87<>"",4,0))))) -> 0 | E88: =IF(E79<>"",1,IF(E80<>"",5,IF(E81<>"",2,IF(AND(E82<>"",E84<>""),3,IF(E87<>"",4,0))))) -> 5 | F88: =IF(F79<>"",1,IF(F80<>"",5,IF(F81<>"",2,IF(AND(F82<>"",F84<>""),3,IF(F87<>"",4,0))))) -> 5 | G88: =IF(G79<>"",1,IF(G80<>"",5,IF(G81<>"",2,IF(AND(G82<>"",G84<>""),3,IF(G87<>"",4,0))))) -> 4 | H88: =IF(H79<>"",1,IF(H80<>"",5,IF(H81<>"",2,IF(AND(H82<>"",H84<>""),3,IF(H87<>"",4,0))))) -> 4 | I88: =IF(I79<>"",1,IF(I80<>"",5,IF(I81<>"",2,IF(AND(I82<>"",I84<>""),3,IF(I87<>"",4,0))))) -> 4 | J88: =IF(J79<>"",1,IF(J80<>"",5,IF(J81<>"",2,IF(AND(J82<>"",J84<>""),3,IF(J87<>"",4,0))))) -> 4 | K88: =IF(K79<>"",1,IF(K80<>"",5,IF(K81<>"",2,IF(AND(K82<>"",K84<>""),3,IF(K87<>"",4,0))))) -> 4 | ... M88: =IF(M79<>"",1,IF(M80<>"",5,IF(M81<>"",2,IF(AND(M82<>"",M84<>""),3,IF(M87<>"",4,0))))) -> 4
A89: 年底上線 IT GW：低 | B89: meta_lo | C89: GW | D89: =IF(D87="","",IF(AND(D88=5,In!$H$104<>""),In!$H$104*Players!$E$17/1000,D87)) | E89: =IF(E87="","",IF(AND(E88=5,In!$I$104<>""),In!$I$104*Players!$E$17/1000,E87)) -> 0.863775 | F89: =IF(F87="","",IF(AND(F88=5,In!$J$104<>""),In!$J$104*Players!$E$17/1000,F87)) -> 2.208855 | G89: =IF(G87="","",IF(AND(G88=5,In!$K$104<>""),In!$K$104*Players!$E$17/1000,G87)) -> 3.152595 | H89: =IF(H87="","",IF(AND(H88=5,In!$L$104<>""),In!$L$104*Players!$E$17/1000,H87)) -> 3.344595 | I89: =IF(I87="","",IF(AND(I88=5,In!$M$104<>""),In!$M$104*Players!$E$17/1000,I87)) -> 6.130595 | J89: =IF(J87="","",IF(AND(J88=5,In!$N$104<>""),In!$N$104*Players!$E$17/1000,J87)) -> 6.498595 | K89: =IF(K87="","",IF(AND(K88=5,In!$O$104<>""),In!$O$104*Players!$E$17/1000,K87)) -> 6.498595 | L89: =IF(L87="","",IF(AND(L88=5,In!$P$104<>""),In!$P$104*Players!$E$17/1000,L87)) -> 6.498595 | M89: =IF(M87="","",IF(AND(M88=5,In!$Q$104<>""),In!$Q$104*Players!$E$17/1000,M87)) -> 6.498595
A90: 年底上線 IT GW：高 | B90: meta_hi | C90: GW | D90: =IF(D87="","",IF(AND(D88=5,In!$H$104<>""),In!$H$104*Players!$F$17/1000,D87)) | E90: =IF(E87="","",IF(AND(E88=5,In!$I$104<>""),In!$I$104*Players!$F$17/1000,E87)) -> 1.08888 | F90: =IF(F87="","",IF(AND(F88=5,In!$J$104<>""),In!$J$104*Players!$F$17/1000,F87)) -> 2.784496 | G90: =IF(G87="","",IF(AND(G88=5,In!$K$104<>""),In!$K$104*Players!$F$17/1000,G87)) -> 3.152595 | H90: =IF(H87="","",IF(AND(H88=5,In!$L$104<>""),In!$L$104*Players!$F$17/1000,H87)) -> 3.344595 | I90: =IF(I87="","",IF(AND(I88=5,In!$M$104<>""),In!$M$104*Players!$F$17/1000,I87)) -> 6.130595 | J90: =IF(J87="","",IF(AND(J88=5,In!$N$104<>""),In!$N$104*Players!$F$17/1000,J87)) -> 6.498595 | K90: =IF(K87="","",IF(AND(K88=5,In!$O$104<>""),In!$O$104*Players!$F$17/1000,K87)) -> 6.498595 | L90: =IF(L87="","",IF(AND(L88=5,In!$P$104<>""),In!$P$104*Players!$F$17/1000,L87)) -> 6.498595 | M90: =IF(M87="","",IF(AND(M88=5,In!$Q$104<>""),In!$Q$104*Players!$F$17/1000,M87)) -> 6.498595
A91: 另讀（口徑未說明者讀為設施 ÷ IF_FacilityGW） | B91: meta_alt | C91: GW | D91: =IF(D87="","",IF(In!$C$111="未說明",D87/D$13,D87)) | E91: =IF(E87="","",IF(In!$C$111="未說明",E87/E$13,E87)) -> 0.968475 | F91: =IF(F87="","",IF(In!$C$111="未說明",F87/F$13,F87)) -> 2.476595 | G91: =IF(G87="","",IF(In!$C$111="未說明",G87/G$13,G87)) -> 3.152595 | H91: =IF(H87="","",IF(In!$C$111="未說明",H87/H$13,H87)) -> 3.344595 | I91: =IF(I87="","",IF(In!$C$111="未說明",I87/I$13,I87)) -> 6.130595 | J91: =IF(J87="","",IF(In!$C$111="未說明",J87/J$13,J87)) -> 6.498595 | K91: =IF(K87="","",IF(In!$C$111="未說明",K87/K$13,K87)) -> 6.498595 | ... M91: =IF(M87="","",IF(In!$C$111="未說明",M87/M$13,M87)) -> 6.498595
A92: 年平均 IT GW | B92: meta_avg | C92: GW | D92: ="" | E92: =IF(AND(D87<>"",E87<>""),(D87+E87)/2,"") | F92: =IF(AND(E87<>"",F87<>""),(E87+F87)/2,"") -> 1.722535 | G92: =IF(AND(F87<>"",G87<>""),(F87+G87)/2,"") -> 2.814595 | H92: =IF(AND(G87<>"",H87<>""),(G87+H87)/2,"") -> 3.248595 | I92: =IF(AND(H87<>"",I87<>""),(H87+I87)/2,"") -> 4.737595 | J92: =IF(AND(I87<>"",J87<>""),(I87+J87)/2,"") -> 6.314595 | K92: =IF(AND(J87<>"",K87<>""),(J87+K87)/2,"") -> 6.498595 | L92: =IF(AND(K87<>"",L87<>""),(K87+L87)/2,"") -> 6.498595 | M92: =IF(AND(L87<>"",M87<>""),(L87+M87)/2,"") -> 6.498595
A93: 年新增 IT GW | B93: meta_add | C93: GW | D93: 0 | E93: =IF(AND(D87<>"",E87<>""),E87-D87,0) -> 0 | F93: =IF(AND(E87<>"",F87<>""),F87-E87,0) -> 1.50812 | G93: =IF(AND(F87<>"",G87<>""),G87-F87,0) -> 0.676 | H93: =IF(AND(G87<>"",H87<>""),H87-G87,0) -> 0.192 | I93: =IF(AND(H87<>"",I87<>""),I87-H87,0) -> 2.786 | J93: =IF(AND(I87<>"",J87<>""),J87-I87,0) -> 0.368 | K93: =IF(AND(J87<>"",K87<>""),K87-J87,0) -> 0 | L93: =IF(AND(K87<>"",L87<>""),L87-K87,0) -> 0 | M93: =IF(AND(L87<>"",M87<>""),M87-L87,0) -> 0
A94: 新納入存量 IT GW | B94: meta_stk | C94: GW | D94: =IF(D87<>"",D87,0) -> 0 | E94: =IF(AND(D87="",E87<>""),E87,0) -> 0.968475 | F94: =IF(AND(E87="",F87<>""),F87,0) -> 0 | G94: =IF(AND(F87="",G87<>""),G87,0) -> 0 | H94: =IF(AND(G87="",H87<>""),H87,0) -> 0 | I94: =IF(AND(H87="",I87<>""),I87,0) -> 0 | J94: =IF(AND(I87="",J87<>""),J87,0) -> 0 | K94: =IF(AND(J87="",K87<>""),K87,0) -> 0 | L94: =IF(AND(K87="",L87<>""),L87,0) -> 0 | M94: =IF(AND(L87="",M87<>""),M87,0) -> 0
A95: 新增 GW 非 NVIDIA 占比 | B95: meta_nnv | C95: % | D95: =D$12 -> 0.23821007 | E95: =E$12 -> 0.23821007 | F95: =F$12 -> 0.23821007 | G95: =G$12 -> 0.23821007 | H95: =H$12 -> 0.27310186 | I95: =I$12 -> 0.2696214 | J95: =J$12 -> 0.27218751 | K95: =K$12 -> 0.27218751 | ... M95: =M$12 -> 0.27218751
A97: Oracle（OCI；含承租 Stargate 站點） | B97: orcl | N97: In 第 112 列；口徑＝In!C112
A98: 輸入（IT GW；設施 ÷ IF_FacilityGW） | B98: orcl_in | C98: GW | D98: =IF(In!$H$112="","",IF(In!$C$112="設施",In!$H$112/1000/D$13,In!$H$112/1000)) | E98: =IF(In!$I$112="","",IF(In!$C$112="設施",In!$I$112/1000/E$13,In!$I$112/1000)) | F98: =IF(In!$J$112="","",IF(In!$C$112="設施",In!$J$112/1000/F$13,In!$J$112/1000)) | G98: =IF(In!$K$112="","",IF(In!$C$112="設施",In!$K$112/1000/G$13,In!$K$112/1000)) | H98: =IF(In!$L$112="","",IF(In!$C$112="設施",In!$L$112/1000/H$13,In!$L$112/1000)) | I98: =IF(In!$M$112="","",IF(In!$C$112="設施",In!$M$112/1000/I$13,In!$M$112/1000)) | J98: =IF(In!$N$112="","",IF(In!$C$112="設施",In!$N$112/1000/J$13,In!$N$112/1000)) | K98: =IF(In!$O$112="","",IF(In!$C$112="設施",In!$O$112/1000/K$13,In!$O$112/1000)) | L98: =IF(In!$P$112="","",IF(In!$C$112="設施",In!$P$112/1000/L$13,In!$P$112/1000)) | M98: =IF(In!$Q$112="","",IF(In!$C$112="設施",In!$Q$112/1000/M$13,In!$Q$112/1000))
A99: 晶片換算 IT GW | B99: orcl_chip | C99: GW | D99: =IF(In!$H$105="","",In!$H$105*Players!$D$18/1000) | E99: =IF(In!$I$105="","",In!$I$105*Players!$D$18/1000) -> 0.386465 | F99: =IF(In!$J$105="","",In!$J$105*Players!$D$18/1000) -> 1.20287 | G99: =IF(In!$K$105="","",In!$K$105*Players!$D$18/1000) | H99: =IF(In!$L$105="","",In!$L$105*Players!$D$18/1000) | I99: =IF(In!$M$105="","",In!$M$105*Players!$D$18/1000) | J99: =IF(In!$N$105="","",In!$N$105*Players!$D$18/1000) | K99: =IF(In!$O$105="","",In!$O$105*Players!$D$18/1000) | L99: =IF(In!$P$105="","",In!$P$105*Players!$D$18/1000) | M99: =IF(In!$Q$105="","",In!$Q$105*Players!$D$18/1000)
A100: 已知值 | B100: orcl_k | C100: GW | D100: =IF(D98<>"",D98,IF(D99<>"",D99,IF(INT(obsd_orcl)=2023,obs_orcl/1000+SUMIFS(Pipeline!$L$5:$L$64,Pipeline!$C$5:$C$64,"orcl",Pipeline!$Q$5:$Q$64,1,Pipeline!$K$5:$K$64,">"&obsd_orcl,Pipeline!$K$5:$K$64,"<="&2024),""))) | E100: =IF(E98<>"",E98,IF(E99<>"",E99,IF(INT(obsd_orcl)=2024,obs_orcl/1000+SUMIFS(Pipeline!$L$5:$L$64,Pipeline!$C$5:$C$64,"orcl",Pipeline!$Q$5:$Q$64,1,Pipeline!$K$5:$K$64,">"&obsd_orcl,Pipeline!$K$5:$K$64,"<="&2025),""))) -> 0.386465 | F100: =IF(F98<>"",F98,IF(F99<>"",F99,IF(INT(obsd_orcl)=2025,obs_orcl/1000+SUMIFS(Pipeline!$L$5:$L$64,Pipeline!$C$5:$C$64,"orcl",Pipeline!$Q$5:$Q$64,1,Pipeline!$K$5:$K$64,">"&obsd_orcl,Pipeline!$K$5:$K$64,"<="&2026),""))) -> 1.20287 | G100: =IF(G98<>"",G98,IF(G99<>"",G99,IF(INT(obsd_orcl)=2026,obs_orcl/1000+SUMIFS(Pipeline!$L$5:$L$64,Pipeline!$C$5:$C$64,"orcl",Pipeline!$Q$5:$Q$64,1,Pipeline!$K$5:$K$64,">"&obsd_orcl,Pipeline!$K$5:$K$64,"<="&2027),""))) -> 2.749 | H100: =IF(H98<>"",H98,IF(H99<>"",H99,IF(INT(obsd_orcl)=2027,obs_orcl/1000+SUMIFS(Pipeline!$L$5:$L$64,Pipeline!$C$5:$C$64,"orcl",Pipeline!$Q$5:$Q$64,1,Pipeline!$K$5:$K$64,">"&obsd_orcl,Pipeline!$K$5:$K$64,"<="&2028),""))) | I100: =IF(I98<>"",I98,IF(I99<>"",I99,IF(INT(obsd_orcl)=2028,obs_orcl/1000+SUMIFS(Pipeline!$L$5:$L$64,Pipeline!$C$5:$C$64,"orcl",Pipeline!$Q$5:$Q$64,1,Pipeline!$K$5:$K$64,">"&obsd_orcl,Pipeline!$K$5:$K$64,"<="&2029),""))) | J100: =IF(J98<>"",J98,IF(J99<>"",J99,IF(INT(obsd_orcl)=2029,obs_orcl/1000+SUMIFS(Pipeline!$L$5:$L$64,Pipeline!$C$5:$C$64,"orcl",Pipeline!$Q$5:$Q$64,1,Pipeline!$K$5:$K$64,">"&obsd_orcl,Pipeline!$K$5:$K$64,"<="&2030),""))) | K100: =IF(K98<>"",K98,IF(K99<>"",K99,IF(INT(obsd_orcl)=2030,obs_orcl/1000+SUMIFS(Pipeline!$L$5:$L$64,Pipeline!$C$5:$C$64,"orcl",Pipeline!$Q$5:$Q$64,1,Pipeline!$K$5:$K$64,">"&obsd_orcl,Pipeline!$K$5:$K$64,"<="&2031),""))) | L100: =IF(L98<>"",L98,IF(L99<>"",L99,IF(INT(obsd_orcl)=2031,obs_orcl/1000+SUMIFS(Pipeline!$L$5:$L$64,Pipeline!$C$5:$C$64,"orcl",Pipeline!$Q$5:$Q$64,1,Pipeline!$K$5:$K$64,">"&obsd_orcl,Pipeline!$K$5:$K$64,"<="&2032),""))) | M100: =IF(M98<>"",M98,IF(M99<>"",M99,IF(INT(obsd_orcl)=2032,obs_orcl/1000+SUMIFS(Pipeline!$L$5:$L$64,Pipeline!$C$5:$C$64,"orcl",Pipeline!$Q$5:$Q$64,1,Pipeline!$K$5:$K$64,">"&obsd_orcl,Pipeline!$K$5:$K$64,"<="&2033),"")))
A101: 前一已知值 | B101: orcl_L | C101: GW | D101: =IF(D100<>"",D100,"") | E101: =IF(E100<>"",E100,D101) -> 0.386465 | F101: =IF(F100<>"",F100,E101) -> 1.20287 | G101: =IF(G100<>"",G100,F101) -> 2.749 | H101: =IF(H100<>"",H100,G101) -> 2.749 | I101: =IF(I100<>"",I100,H101) -> 2.749 | J101: =IF(J100<>"",J100,I101) -> 2.749 | K101: =IF(K100<>"",K100,J101) -> 2.749 | L101: =IF(L100<>"",L100,K101) -> 2.749 | M101: =IF(M100<>"",M100,L101) -> 2.749
A102: 前一已知年 | B102: orcl_LY | C102: 年 | D102: =IF(D100<>"",2023,"") | E102: =IF(E100<>"",2024,D102) -> 2024 | F102: =IF(F100<>"",2025,E102) -> 2025 | G102: =IF(G100<>"",2026,F102) -> 2026 | H102: =IF(H100<>"",2027,G102) -> 2026 | I102: =IF(I100<>"",2028,H102) -> 2026 | J102: =IF(J100<>"",2029,I102) -> 2026 | K102: =IF(K100<>"",2030,J102) -> 2026 | L102: =IF(L100<>"",2031,K102) -> 2026 | M102: =IF(M100<>"",2032,L102) -> 2026
A103: 下一已知值 | B103: orcl_N | C103: GW | D103: =IF(D100<>"",D100,E103) -> 0.386465 | E103: =IF(E100<>"",E100,F103) -> 0.386465 | F103: =IF(F100<>"",F100,G103) -> 1.20287 | G103: =IF(G100<>"",G100,H103) -> 2.749 | H103: =IF(H100<>"",H100,I103) | I103: =IF(I100<>"",I100,J103) | J103: =IF(J100<>"",J100,K103) | K103: =IF(K100<>"",K100,L103) | L103: =IF(L100<>"",L100,M103) | M103: =IF(M100<>"",M100,"")
A104: 下一已知年 | B104: orcl_NY | C104: 年 | D104: =IF(D100<>"",2023,E104) -> 2024 | E104: =IF(E100<>"",2024,F104) -> 2024 | F104: =IF(F100<>"",2025,G104) -> 2025 | G104: =IF(G100<>"",2026,H104) -> 2026 | H104: =IF(H100<>"",2027,I104) | I104: =IF(I100<>"",2028,J104) | J104: =IF(J100<>"",2029,K104) | K104: =IF(K100<>"",2030,L104) | L104: =IF(L100<>"",2031,M104) | M104: =IF(M100<>"",2032,"")
A105: 當年 T2 園區上線（D0，IT GW） | B105: orcl_cp | C105: GW | D105: =SUMIFS(Pipeline!$L$5:$L$64,Pipeline!$C$5:$C$64,"orcl",Pipeline!$Q$5:$Q$64,1,Pipeline!$P$5:$P$64,2023) -> 0 | E105: =SUMIFS(Pipeline!$L$5:$L$64,Pipeline!$C$5:$C$64,"orcl",Pipeline!$Q$5:$Q$64,1,Pipeline!$P$5:$P$64,2024) -> 0 | F105: =SUMIFS(Pipeline!$L$5:$L$64,Pipeline!$C$5:$C$64,"orcl",Pipeline!$Q$5:$Q$64,1,Pipeline!$P$5:$P$64,2025) -> 0 | G105: =SUMIFS(Pipeline!$L$5:$L$64,Pipeline!$C$5:$C$64,"orcl",Pipeline!$Q$5:$Q$64,1,Pipeline!$P$5:$P$64,2026) -> 0.206 | H105: =SUMIFS(Pipeline!$L$5:$L$64,Pipeline!$C$5:$C$64,"orcl",Pipeline!$Q$5:$Q$64,1,Pipeline!$P$5:$P$64,2027) -> 0.16666667 | I105: =SUMIFS(Pipeline!$L$5:$L$64,Pipeline!$C$5:$C$64,"orcl",Pipeline!$Q$5:$Q$64,1,Pipeline!$P$5:$P$64,2028) -> 5.5691667 | J105: =SUMIFS(Pipeline!$L$5:$L$64,Pipeline!$C$5:$C$64,"orcl",Pipeline!$Q$5:$Q$64,1,Pipeline!$P$5:$P$64,2029) -> 0 | K105: =SUMIFS(Pipeline!$L$5:$L$64,Pipeline!$C$5:$C$64,"orcl",Pipeline!$Q$5:$Q$64,1,Pipeline!$P$5:$P$64,2030) -> 0 | L105: =SUMIFS(Pipeline!$L$5:$L$64,Pipeline!$C$5:$C$64,"orcl",Pipeline!$Q$5:$Q$64,1,Pipeline!$P$5:$P$64,2031) -> 0 | M105: =SUMIFS(Pipeline!$L$5:$L$64,Pipeline!$C$5:$C$64,"orcl",Pipeline!$Q$5:$Q$64,1,Pipeline!$P$5:$P$64,2032) -> 0
...

Sheet Matrix
A1: Matrix — 營運者 × 使用者（年底 IT GW）。列＝營運者（Players 年底值），欄＝使用者：In T1 每筆分配（比＝× 營運者年底 GW；GW＝絕對值）加總；『未分配』＝列和缺口（無揭露者；Decisions GL01-15）。列和＝Players；欄和合計＝總量（市場總量只按營運者加總一次）
A3: 2025 年底
A4: 營運者 | B4: 鍵 | C4: 自用 | D4: OpenAI | E4: Anthropic | F4: xAI | G4: Meta | H4: Google（租用） | I4: Microsoft（租用） | J4: 其他 | K4: 未分配 | L4: 列和 | M4: Players | N4: 差
A5: Microsoft（自有＋融資租賃 AI 在役） | B5: msft | C5: =SUMPRODUCT((In!$H$170:$H$182="msft")*(In!$I$170:$I$182="self")*((In!$J$170:$J$182="比")*$M5+(In!$J$170:$J$182<>"比"))*In!K$170:K$182) -> 1.491618 | D5: =SUMPRODUCT((In!$H$170:$H$182="msft")*(In!$I$170:$I$182="oai")*((In!$J$170:$J$182="比")*$M5+(In!$J$170:$J$182<>"比"))*In!K$170:K$182) -> 0 | E5: =SUMPRODUCT((In!$H$170:$H$182="msft")*(In!$I$170:$I$182="ant")*((In!$J$170:$J$182="比")*$M5+(In!$J$170:$J$182<>"比"))*In!K$170:K$182) -> 0 | F5: =SUMPRODUCT((In!$H$170:$H$182="msft")*(In!$I$170:$I$182="xai")*((In!$J$170:$J$182="比")*$M5+(In!$J$170:$J$182<>"比"))*In!K$170:K$182) -> 0 | G5: =SUMPRODUCT((In!$H$170:$H$182="msft")*(In!$I$170:$I$182="meta")*((In!$J$170:$J$182="比")*$M5+(In!$J$170:$J$182<>"比"))*In!K$170:K$182) -> 0 | H5: =SUMPRODUCT((In!$H$170:$H$182="msft")*(In!$I$170:$I$182="googl")*((In!$J$170:$J$182="比")*$M5+(In!$J$170:$J$182<>"比"))*In!K$170:K$182) -> 0 | I5: =SUMPRODUCT((In!$H$170:$H$182="msft")*(In!$I$170:$I$182="msft")*((In!$J$170:$J$182="比")*$M5+(In!$J$170:$J$182<>"比"))*In!K$170:K$182) -> 0 | J5: =SUMPRODUCT((In!$H$170:$H$182="msft")*(In!$I$170:$I$182="oth")*((In!$J$170:$J$182="比")*$M5+(In!$J$170:$J$182<>"比"))*In!K$170:K$182) -> 0 | K5: =$M5-SUM(C5:J5) -> 2.237427 | L5: =SUM(C5:K5) -> 3.729045 | M5: =N(Players!F30) -> 3.729045 | N5: =L5-M5 -> 0
A6: Alphabet（Google；TPU＋NVIDIA） | B6: googl | C6: =SUMPRODUCT((In!$H$170:$H$182="googl")*(In!$I$170:$I$182="self")*((In!$J$170:$J$182="比")*$M6+(In!$J$170:$J$182<>"比"))*In!K$170:K$182) -> 3.01 | D6: =SUMPRODUCT((In!$H$170:$H$182="googl")*(In!$I$170:$I$182="oai")*((In!$J$170:$J$182="比")*$M6+(In!$J$170:$J$182<>"比"))*In!K$170:K$182) -> 0 | E6: =SUMPRODUCT((In!$H$170:$H$182="googl")*(In!$I$170:$I$182="ant")*((In!$J$170:$J$182="比")*$M6+(In!$J$170:$J$182<>"比"))*In!K$170:K$182) -> 0 | F6: =SUMPRODUCT((In!$H$170:$H$182="googl")*(In!$I$170:$I$182="xai")*((In!$J$170:$J$182="比")*$M6+(In!$J$170:$J$182<>"比"))*In!K$170:K$182) -> 0 | G6: =SUMPRODUCT((In!$H$170:$H$182="googl")*(In!$I$170:$I$182="meta")*((In!$J$170:$J$182="比")*$M6+(In!$J$170:$J$182<>"比"))*In!K$170:K$182) -> 0 | H6: =SUMPRODUCT((In!$H$170:$H$182="googl")*(In!$I$170:$I$182="googl")*((In!$J$170:$J$182="比")*$M6+(In!$J$170:$J$182<>"比"))*In!K$170:K$182) -> 0 | I6: =SUMPRODUCT((In!$H$170:$H$182="googl")*(In!$I$170:$I$182="msft")*((In!$J$170:$J$182="比")*$M6+(In!$J$170:$J$182<>"比"))*In!K$170:K$182) -> 0 | J6: =SUMPRODUCT((In!$H$170:$H$182="googl")*(In!$I$170:$I$182="oth")*((In!$J$170:$J$182="比")*$M6+(In!$J$170:$J$182<>"比"))*In!K$170:K$182) -> 0 | K6: =$M6-SUM(C6:J6) -> 1.29 | L6: =SUM(C6:K6) -> 4.3 | M6: =N(Players!F49) -> 4.3 | N6: =L6-M6 -> 0
A7: Amazon（AWS；Trainium＋NVIDIA） | B7: amzn | C7: =SUMPRODUCT((In!$H$170:$H$182="amzn")*(In!$I$170:$I$182="self")*((In!$J$170:$J$182="比")*$M7+(In!$J$170:$J$182<>"比"))*In!K$170:K$182) -> 0.44 | D7: =SUMPRODUCT((In!$H$170:$H$182="amzn")*(In!$I$170:$I$182="oai")*((In!$J$170:$J$182="比")*$M7+(In!$J$170:$J$182<>"比"))*In!K$170:K$182) -> 0 | E7: =SUMPRODUCT((In!$H$170:$H$182="amzn")*(In!$I$170:$I$182="ant")*((In!$J$170:$J$182="比")*$M7+(In!$J$170:$J$182<>"比"))*In!K$170:K$182) -> 0.626 | F7: =SUMPRODUCT((In!$H$170:$H$182="amzn")*(In!$I$170:$I$182="xai")*((In!$J$170:$J$182="比")*$M7+(In!$J$170:$J$182<>"比"))*In!K$170:K$182) -> 0 | G7: =SUMPRODUCT((In!$H$170:$H$182="amzn")*(In!$I$170:$I$182="meta")*((In!$J$170:$J$182="比")*$M7+(In!$J$170:$J$182<>"比"))*In!K$170:K$182) -> 0 | H7: =SUMPRODUCT((In!$H$170:$H$182="amzn")*(In!$I$170:$I$182="googl")*((In!$J$170:$J$182="比")*$M7+(In!$J$170:$J$182<>"比"))*In!K$170:K$182) -> 0 | I7: =SUMPRODUCT((In!$H$170:$H$182="amzn")*(In!$I$170:$I$182="msft")*((In!$J$170:$J$182="比")*$M7+(In!$J$170:$J$182<>"比"))*In!K$170:K$182) -> 0 | J7: =SUMPRODUCT((In!$H$170:$H$182="amzn")*(In!$I$170:$I$182="oth")*((In!$J$170:$J$182="比")*$M7+(In!$J$170:$J$182<>"比"))*In!K$170:K$182) -> 0 | K7: =$M7-SUM(C7:J7) -> 1.134 | L7: =SUM(C7:K7) -> 2.2 | M7: =N(Players!F68) -> 2.2 | N7: =L7-M7 -> 0
A8: Meta | B8: meta | C8: =SUMPRODUCT((In!$H$170:$H$182="meta")*(In!$I$170:$I$182="self")*((In!$J$170:$J$182="比")*$M8+(In!$J$170:$J$182<>"比"))*In!K$170:K$182) -> 0 | D8: =SUMPRODUCT((In!$H$170:$H$182="meta")*(In!$I$170:$I$182="oai")*((In!$J$170:$J$182="比")*$M8+(In!$J$170:$J$182<>"比"))*In!K$170:K$182) -> 0 | E8: =SUMPRODUCT((In!$H$170:$H$182="meta")*(In!$I$170:$I$182="ant")*((In!$J$170:$J$182="比")*$M8+(In!$J$170:$J$182<>"比"))*In!K$170:K$182) -> 0 | F8: =SUMPRODUCT((In!$H$170:$H$182="meta")*(In!$I$170:$I$182="xai")*((In!$J$170:$J$182="比")*$M8+(In!$J$170:$J$182<>"比"))*In!K$170:K$182) -> 0 | G8: =SUMPRODUCT((In!$H$170:$H$182="meta")*(In!$I$170:$I$182="meta")*((In!$J$170:$J$182="比")*$M8+(In!$J$170:$J$182<>"比"))*In!K$170:K$182) -> 2.476595 | H8: =SUMPRODUCT((In!$H$170:$H$182="meta")*(In!$I$170:$I$182="googl")*((In!$J$170:$J$182="比")*$M8+(In!$J$170:$J$182<>"比"))*In!K$170:K$182) -> 0 | I8: =SUMPRODUCT((In!$H$170:$H$182="meta")*(In!$I$170:$I$182="msft")*((In!$J$170:$J$182="比")*$M8+(In!$J$170:$J$182<>"比"))*In!K$170:K$182) -> 0 | J8: =SUMPRODUCT((In!$H$170:$H$182="meta")*(In!$I$170:$I$182="oth")*((In!$J$170:$J$182="比")*$M8+(In!$J$170:$J$182<>"比"))*In!K$170:K$182) -> 0 | K8: =$M8-SUM(C8:J8) -> 0 | L8: =SUM(C8:K8) -> 2.476595 | M8: =N(Players!F87) -> 2.476595 | N8: =L8-M8 -> 0
A9: Oracle（OCI；含承租 Stargate 站點） | B9: orcl | C9: =SUMPRODUCT((In!$H$170:$H$182="orcl")*(In!$I$170:$I$182="self")*((In!$J$170:$J$182="比")*$M9+(In!$J$170:$J$182<>"比"))*In!K$170:K$182) -> 0 | D9: =SUMPRODUCT((In!$H$170:$H$182="orcl")*(In!$I$170:$I$182="oai")*((In!$J$170:$J$182="比")*$M9+(In!$J$170:$J$182<>"比"))*In!K$170:K$182) -> 0 | E9: =SUMPRODUCT((In!$H$170:$H$182="orcl")*(In!$I$170:$I$182="ant")*((In!$J$170:$J$182="比")*$M9+(In!$J$170:$J$182<>"比"))*In!K$170:K$182) -> 0 | F9: =SUMPRODUCT((In!$H$170:$H$182="orcl")*(In!$I$170:$I$182="xai")*((In!$J$170:$J$182="比")*$M9+(In!$J$170:$J$182<>"比"))*In!K$170:K$182) -> 0 | G9: =SUMPRODUCT((In!$H$170:$H$182="orcl")*(In!$I$170:$I$182="meta")*((In!$J$170:$J$182="比")*$M9+(In!$J$170:$J$182<>"比"))*In!K$170:K$182) -> 0 | H9: =SUMPRODUCT((In!$H$170:$H$182="orcl")*(In!$I$170:$I$182="googl")*((In!$J$170:$J$182="比")*$M9+(In!$J$170:$J$182<>"比"))*In!K$170:K$182) -> 0 | I9: =SUMPRODUCT((In!$H$170:$H$182="orcl")*(In!$I$170:$I$182="msft")*((In!$J$170:$J$182="比")*$M9+(In!$J$170:$J$182<>"比"))*In!K$170:K$182) -> 0 | J9: =SUMPRODUCT((In!$H$170:$H$182="orcl")*(In!$I$170:$I$182="oth")*((In!$J$170:$J$182="比")*$M9+(In!$J$170:$J$182<>"比"))*In!K$170:K$182) -> 0 | K9: =$M9-SUM(C9:J9) -> 1.20287 | L9: =SUM(C9:K9) -> 1.20287 | M9: =N(Players!F106) -> 1.20287 | N9: =L9-M9 -> 0
A10: CoreWeave | B10: crwv | C10: =SUMPRODUCT((In!$H$170:$H$182="crwv")*(In!$I$170:$I$182="self")*((In!$J$170:$J$182="比")*$M10+(In!$J$170:$J$182<>"比"))*In!K$170:K$182) -> 0 | D10: =SUMPRODUCT((In!$H$170:$H$182="crwv")*(In!$I$170:$I$182="oai")*((In!$J$170:$J$182="比")*$M10+(In!$J$170:$J$182<>"比"))*In!K$170:K$182) -> 0 | E10: =SUMPRODUCT((In!$H$170:$H$182="crwv")*(In!$I$170:$I$182="ant")*((In!$J$170:$J$182="比")*$M10+(In!$J$170:$J$182<>"比"))*In!K$170:K$182) -> 0 | F10: =SUMPRODUCT((In!$H$170:$H$182="crwv")*(In!$I$170:$I$182="xai")*((In!$J$170:$J$182="比")*$M10+(In!$J$170:$J$182<>"比"))*In!K$170:K$182) -> 0 | G10: =SUMPRODUCT((In!$H$170:$H$182="crwv")*(In!$I$170:$I$182="meta")*((In!$J$170:$J$182="比")*$M10+(In!$J$170:$J$182<>"比"))*In!K$170:K$182) -> 0 | H10: =SUMPRODUCT((In!$H$170:$H$182="crwv")*(In!$I$170:$I$182="googl")*((In!$J$170:$J$182="比")*$M10+(In!$J$170:$J$182<>"比"))*In!K$170:K$182) -> 0 | I10: =SUMPRODUCT((In!$H$170:$H$182="crwv")*(In!$I$170:$I$182="msft")*((In!$J$170:$J$182="比")*$M10+(In!$J$170:$J$182<>"比"))*In!K$170:K$182) -> 0 | J10: =SUMPRODUCT((In!$H$170:$H$182="crwv")*(In!$I$170:$I$182="oth")*((In!$J$170:$J$182="比")*$M10+(In!$J$170:$J$182<>"比"))*In!K$170:K$182) -> 0 | K10: =$M10-SUM(C10:J10) -> 0.85 | L10: =SUM(C10:K10) -> 0.85 | M10: =N(Players!F125) -> 0.85 | N10: =L10-M10 -> 0
A11: Nebius | B11: nbis | C11: =SUMPRODUCT((In!$H$170:$H$182="nbis")*(In!$I$170:$I$182="self")*((In!$J$170:$J$182="比")*$M11+(In!$J$170:$J$182<>"比"))*In!K$170:K$182) -> 0 | D11: =SUMPRODUCT((In!$H$170:$H$182="nbis")*(In!$I$170:$I$182="oai")*((In!$J$170:$J$182="比")*$M11+(In!$J$170:$J$182<>"比"))*In!K$170:K$182) -> 0 | E11: =SUMPRODUCT((In!$H$170:$H$182="nbis")*(In!$I$170:$I$182="ant")*((In!$J$170:$J$182="比")*$M11+(In!$J$170:$J$182<>"比"))*In!K$170:K$182) -> 0 | F11: =SUMPRODUCT((In!$H$170:$H$182="nbis")*(In!$I$170:$I$182="xai")*((In!$J$170:$J$182="比")*$M11+(In!$J$170:$J$182<>"比"))*In!K$170:K$182) -> 0 | G11: =SUMPRODUCT((In!$H$170:$H$182="nbis")*(In!$I$170:$I$182="meta")*((In!$J$170:$J$182="比")*$M11+(In!$J$170:$J$182<>"比"))*In!K$170:K$182) -> 0 | H11: =SUMPRODUCT((In!$H$170:$H$182="nbis")*(In!$I$170:$I$182="googl")*((In!$J$170:$J$182="比")*$M11+(In!$J$170:$J$182<>"比"))*In!K$170:K$182) -> 0 | I11: =SUMPRODUCT((In!$H$170:$H$182="nbis")*(In!$I$170:$I$182="msft")*((In!$J$170:$J$182="比")*$M11+(In!$J$170:$J$182<>"比"))*In!K$170:K$182) -> 0 | J11: =SUMPRODUCT((In!$H$170:$H$182="nbis")*(In!$I$170:$I$182="oth")*((In!$J$170:$J$182="比")*$M11+(In!$J$170:$J$182<>"比"))*In!K$170:K$182) -> 0 | K11: =$M11-SUM(C11:J11) -> 0.17 | L11: =SUM(C11:K11) -> 0.17 | M11: =N(Players!F144) -> 0.17 | N11: =L11-M11 -> 0
A12: WhiteFiber（雲端） | B12: wyfi | C12: =SUMPRODUCT((In!$H$170:$H$182="wyfi")*(In!$I$170:$I$182="self")*((In!$J$170:$J$182="比")*$M12+(In!$J$170:$J$182<>"比"))*In!K$170:K$182) -> 0 | D12: =SUMPRODUCT((In!$H$170:$H$182="wyfi")*(In!$I$170:$I$182="oai")*((In!$J$170:$J$182="比")*$M12+(In!$J$170:$J$182<>"比"))*In!K$170:K$182) -> 0 | E12: =SUMPRODUCT((In!$H$170:$H$182="wyfi")*(In!$I$170:$I$182="ant")*((In!$J$170:$J$182="比")*$M12+(In!$J$170:$J$182<>"比"))*In!K$170:K$182) -> 0 | F12: =SUMPRODUCT((In!$H$170:$H$182="wyfi")*(In!$I$170:$I$182="xai")*((In!$J$170:$J$182="比")*$M12+(In!$J$170:$J$182<>"比"))*In!K$170:K$182) -> 0 | G12: =SUMPRODUCT((In!$H$170:$H$182="wyfi")*(In!$I$170:$I$182="meta")*((In!$J$170:$J$182="比")*$M12+(In!$J$170:$J$182<>"比"))*In!K$170:K$182) -> 0 | H12: =SUMPRODUCT((In!$H$170:$H$182="wyfi")*(In!$I$170:$I$182="googl")*((In!$J$170:$J$182="比")*$M12+(In!$J$170:$J$182<>"比"))*In!K$170:K$182) -> 0 | I12: =SUMPRODUCT((In!$H$170:$H$182="wyfi")*(In!$I$170:$I$182="msft")*((In!$J$170:$J$182="比")*$M12+(In!$J$170:$J$182<>"比"))*In!K$170:K$182) -> 0 | J12: =SUMPRODUCT((In!$H$170:$H$182="wyfi")*(In!$I$170:$I$182="oth")*((In!$J$170:$J$182="比")*$M12+(In!$J$170:$J$182<>"比"))*In!K$170:K$182) -> 0 | K12: =$M12-SUM(C12:J12) -> 0.0055 | L12: =SUM(C12:K12) -> 0.0055 | M12: =N(Players!F163) -> 0.0055 | N12: =L12-M12 -> 0
A13: SpaceX／xAI（Colossus；兼出租） | B13: xai | C13: =SUMPRODUCT((In!$H$170:$H$182="xai")*(In!$I$170:$I$182="self")*((In!$J$170:$J$182="比")*$M13+(In!$J$170:$J$182<>"比"))*In!K$170:K$182) -> 0 | D13: =SUMPRODUCT((In!$H$170:$H$182="xai")*(In!$I$170:$I$182="oai")*((In!$J$170:$J$182="比")*$M13+(In!$J$170:$J$182<>"比"))*In!K$170:K$182) -> 0 | E13: =SUMPRODUCT((In!$H$170:$H$182="xai")*(In!$I$170:$I$182="ant")*((In!$J$170:$J$182="比")*$M13+(In!$J$170:$J$182<>"比"))*In!K$170:K$182) -> 0 | F13: =SUMPRODUCT((In!$H$170:$H$182="xai")*(In!$I$170:$I$182="xai")*((In!$J$170:$J$182="比")*$M13+(In!$J$170:$J$182<>"比"))*In!K$170:K$182) -> 0 | G13: =SUMPRODUCT((In!$H$170:$H$182="xai")*(In!$I$170:$I$182="meta")*((In!$J$170:$J$182="比")*$M13+(In!$J$170:$J$182<>"比"))*In!K$170:K$182) -> 0 | H13: =SUMPRODUCT((In!$H$170:$H$182="xai")*(In!$I$170:$I$182="googl")*((In!$J$170:$J$182="比")*$M13+(In!$J$170:$J$182<>"比"))*In!K$170:K$182) -> 0 | I13: =SUMPRODUCT((In!$H$170:$H$182="xai")*(In!$I$170:$I$182="msft")*((In!$J$170:$J$182="比")*$M13+(In!$J$170:$J$182<>"比"))*In!K$170:K$182) -> 0 | J13: =SUMPRODUCT((In!$H$170:$H$182="xai")*(In!$I$170:$I$182="oth")*((In!$J$170:$J$182="比")*$M13+(In!$J$170:$J$182<>"比"))*In!K$170:K$182) -> 0 | K13: =$M13-SUM(C13:J13) -> 0.5698 | L13: =SUM(C13:K13) -> 0.5698 | M13: =N(Players!F182) -> 0.5698 | N13: =L13-M13 -> 0
A14: OpenAI／Stargate 自建（SoftBank、SB Energy 營運） | B14: oai | C14: =SUMPRODUCT((In!$H$170:$H$182="oai")*(In!$I$170:$I$182="self")*((In!$J$170:$J$182="比")*$M14+(In!$J$170:$J$182<>"比"))*In!K$170:K$182) -> 0 | D14: =SUMPRODUCT((In!$H$170:$H$182="oai")*(In!$I$170:$I$182="oai")*((In!$J$170:$J$182="比")*$M14+(In!$J$170:$J$182<>"比"))*In!K$170:K$182) -> 0 | E14: =SUMPRODUCT((In!$H$170:$H$182="oai")*(In!$I$170:$I$182="ant")*((In!$J$170:$J$182="比")*$M14+(In!$J$170:$J$182<>"比"))*In!K$170:K$182) -> 0 | F14: =SUMPRODUCT((In!$H$170:$H$182="oai")*(In!$I$170:$I$182="xai")*((In!$J$170:$J$182="比")*$M14+(In!$J$170:$J$182<>"比"))*In!K$170:K$182) -> 0 | G14: =SUMPRODUCT((In!$H$170:$H$182="oai")*(In!$I$170:$I$182="meta")*((In!$J$170:$J$182="比")*$M14+(In!$J$170:$J$182<>"比"))*In!K$170:K$182) -> 0 | H14: =SUMPRODUCT((In!$H$170:$H$182="oai")*(In!$I$170:$I$182="googl")*((In!$J$170:$J$182="比")*$M14+(In!$J$170:$J$182<>"比"))*In!K$170:K$182) -> 0 | I14: =SUMPRODUCT((In!$H$170:$H$182="oai")*(In!$I$170:$I$182="msft")*((In!$J$170:$J$182="比")*$M14+(In!$J$170:$J$182<>"比"))*In!K$170:K$182) -> 0 | J14: =SUMPRODUCT((In!$H$170:$H$182="oai")*(In!$I$170:$I$182="oth")*((In!$J$170:$J$182="比")*$M14+(In!$J$170:$J$182<>"比"))*In!K$170:K$182) -> 0 | K14: =$M14-SUM(C14:J14) -> 0 | L14: =SUM(C14:K14) -> 0 | M14: =N(Players!F201) -> 0 | N14: =L14-M14 -> 0
A15: Anthropic 自建 | B15: ant | C15: =SUMPRODUCT((In!$H$170:$H$182="ant")*(In!$I$170:$I$182="self")*((In!$J$170:$J$182="比")*$M15+(In!$J$170:$J$182<>"比"))*In!K$170:K$182) -> 0 | D15: =SUMPRODUCT((In!$H$170:$H$182="ant")*(In!$I$170:$I$182="oai")*((In!$J$170:$J$182="比")*$M15+(In!$J$170:$J$182<>"比"))*In!K$170:K$182) -> 0 | E15: =SUMPRODUCT((In!$H$170:$H$182="ant")*(In!$I$170:$I$182="ant")*((In!$J$170:$J$182="比")*$M15+(In!$J$170:$J$182<>"比"))*In!K$170:K$182) -> 0 | F15: =SUMPRODUCT((In!$H$170:$H$182="ant")*(In!$I$170:$I$182="xai")*((In!$J$170:$J$182="比")*$M15+(In!$J$170:$J$182<>"比"))*In!K$170:K$182) -> 0 | G15: =SUMPRODUCT((In!$H$170:$H$182="ant")*(In!$I$170:$I$182="meta")*((In!$J$170:$J$182="比")*$M15+(In!$J$170:$J$182<>"比"))*In!K$170:K$182) -> 0 | H15: =SUMPRODUCT((In!$H$170:$H$182="ant")*(In!$I$170:$I$182="googl")*((In!$J$170:$J$182="比")*$M15+(In!$J$170:$J$182<>"比"))*In!K$170:K$182) -> 0 | I15: =SUMPRODUCT((In!$H$170:$H$182="ant")*(In!$I$170:$I$182="msft")*((In!$J$170:$J$182="比")*$M15+(In!$J$170:$J$182<>"比"))*In!K$170:K$182) -> 0 | J15: =SUMPRODUCT((In!$H$170:$H$182="ant")*(In!$I$170:$I$182="oth")*((In!$J$170:$J$182="比")*$M15+(In!$J$170:$J$182<>"比"))*In!K$170:K$182) -> 0 | K15: =$M15-SUM(C15:J15) -> 0 | L15: =SUM(C15:K15) -> 0 | M15: =N(Players!F220) -> 0 | N15: =L15-M15 -> 0
A16: 其他新雲合計（IREN、TeraWulf、Lambda、Nscale、Crusoe 雲等） | B16: neo | C16: =SUMPRODUCT((In!$H$170:$H$182="neo")*(In!$I$170:$I$182="self")*((In!$J$170:$J$182="比")*$M16+(In!$J$170:$J$182<>"比"))*In!K$170:K$182) -> 0 | D16: =SUMPRODUCT((In!$H$170:$H$182="neo")*(In!$I$170:$I$182="oai")*((In!$J$170:$J$182="比")*$M16+(In!$J$170:$J$182<>"比"))*In!K$170:K$182) -> 0 | E16: =SUMPRODUCT((In!$H$170:$H$182="neo")*(In!$I$170:$I$182="ant")*((In!$J$170:$J$182="比")*$M16+(In!$J$170:$J$182<>"比"))*In!K$170:K$182) -> 0 | F16: =SUMPRODUCT((In!$H$170:$H$182="neo")*(In!$I$170:$I$182="xai")*((In!$J$170:$J$182="比")*$M16+(In!$J$170:$J$182<>"比"))*In!K$170:K$182) -> 0 | G16: =SUMPRODUCT((In!$H$170:$H$182="neo")*(In!$I$170:$I$182="meta")*((In!$J$170:$J$182="比")*$M16+(In!$J$170:$J$182<>"比"))*In!K$170:K$182) -> 0 | H16: =SUMPRODUCT((In!$H$170:$H$182="neo")*(In!$I$170:$I$182="googl")*((In!$J$170:$J$182="比")*$M16+(In!$J$170:$J$182<>"比"))*In!K$170:K$182) -> 0 | I16: =SUMPRODUCT((In!$H$170:$H$182="neo")*(In!$I$170:$I$182="msft")*((In!$J$170:$J$182="比")*$M16+(In!$J$170:$J$182<>"比"))*In!K$170:K$182) -> 0 | J16: =SUMPRODUCT((In!$H$170:$H$182="neo")*(In!$I$170:$I$182="oth")*((In!$J$170:$J$182="比")*$M16+(In!$J$170:$J$182<>"比"))*In!K$170:K$182) -> 0 | K16: =$M16-SUM(C16:J16) -> 0.5 | L16: =SUM(C16:K16) -> 0.5 | M16: =N(Players!F239) -> 0.5 | N16: =L16-M16 -> 0
A17: 主權 AI（中國以外；v0.1 只含 Humain） | B17: sov | C17: =SUMPRODUCT((In!$H$170:$H$182="sov")*(In!$I$170:$I$182="self")*((In!$J$170:$J$182="比")*$M17+(In!$J$170:$J$182<>"比"))*In!K$170:K$182) -> 0 | D17: =SUMPRODUCT((In!$H$170:$H$182="sov")*(In!$I$170:$I$182="oai")*((In!$J$170:$J$182="比")*$M17+(In!$J$170:$J$182<>"比"))*In!K$170:K$182) -> 0 | E17: =SUMPRODUCT((In!$H$170:$H$182="sov")*(In!$I$170:$I$182="ant")*((In!$J$170:$J$182="比")*$M17+(In!$J$170:$J$182<>"比"))*In!K$170:K$182) -> 0 | F17: =SUMPRODUCT((In!$H$170:$H$182="sov")*(In!$I$170:$I$182="xai")*((In!$J$170:$J$182="比")*$M17+(In!$J$170:$J$182<>"比"))*In!K$170:K$182) -> 0 | G17: =SUMPRODUCT((In!$H$170:$H$182="sov")*(In!$I$170:$I$182="meta")*((In!$J$170:$J$182="比")*$M17+(In!$J$170:$J$182<>"比"))*In!K$170:K$182) -> 0 | H17: =SUMPRODUCT((In!$H$170:$H$182="sov")*(In!$I$170:$I$182="googl")*((In!$J$170:$J$182="比")*$M17+(In!$J$170:$J$182<>"比"))*In!K$170:K$182) -> 0 | I17: =SUMPRODUCT((In!$H$170:$H$182="sov")*(In!$I$170:$I$182="msft")*((In!$J$170:$J$182="比")*$M17+(In!$J$170:$J$182<>"比"))*In!K$170:K$182) -> 0 | J17: =SUMPRODUCT((In!$H$170:$H$182="sov")*(In!$I$170:$I$182="oth")*((In!$J$170:$J$182="比")*$M17+(In!$J$170:$J$182<>"比"))*In!K$170:K$182) -> 0 | K17: =$M17-SUM(C17:J17) -> 0 | L17: =SUM(C17:K17) -> 0 | M17: =N(Players!F258) -> 0 | N17: =L17-M17 -> 0
A18: 中國合計（AI；Rystad 容量 × AI 占比） | B18: cn | C18: =SUMPRODUCT((In!$H$170:$H$182="cn")*(In!$I$170:$I$182="self")*((In!$J$170:$J$182="比")*$M18+(In!$J$170:$J$182<>"比"))*In!K$170:K$182) -> 8.3333333 | D18: =SUMPRODUCT((In!$H$170:$H$182="cn")*(In!$I$170:$I$182="oai")*((In!$J$170:$J$182="比")*$M18+(In!$J$170:$J$182<>"比"))*In!K$170:K$182) -> 0 | E18: =SUMPRODUCT((In!$H$170:$H$182="cn")*(In!$I$170:$I$182="ant")*((In!$J$170:$J$182="比")*$M18+(In!$J$170:$J$182<>"比"))*In!K$170:K$182) -> 0 | F18: =SUMPRODUCT((In!$H$170:$H$182="cn")*(In!$I$170:$I$182="xai")*((In!$J$170:$J$182="比")*$M18+(In!$J$170:$J$182<>"比"))*In!K$170:K$182) -> 0 | G18: =SUMPRODUCT((In!$H$170:$H$182="cn")*(In!$I$170:$I$182="meta")*((In!$J$170:$J$182="比")*$M18+(In!$J$170:$J$182<>"比"))*In!K$170:K$182) -> 0 | H18: =SUMPRODUCT((In!$H$170:$H$182="cn")*(In!$I$170:$I$182="googl")*((In!$J$170:$J$182="比")*$M18+(In!$J$170:$J$182<>"比"))*In!K$170:K$182) -> 0 | I18: =SUMPRODUCT((In!$H$170:$H$182="cn")*(In!$I$170:$I$182="msft")*((In!$J$170:$J$182="比")*$M18+(In!$J$170:$J$182<>"比"))*In!K$170:K$182) -> 0 | J18: =SUMPRODUCT((In!$H$170:$H$182="cn")*(In!$I$170:$I$182="oth")*((In!$J$170:$J$182="比")*$M18+(In!$J$170:$J$182<>"比"))*In!K$170:K$182) -> 0 | K18: =$M18-SUM(C18:J18) -> 0 | L18: =SUM(C18:K18) -> 8.3333333 | M18: =N(Players!F277) -> 8.3333333 | N18: =L18-M18 -> 0
A19: 其他（主權、企業、學研；Epoch Other 扣新雲） | B19: oth | C19: =SUMPRODUCT((In!$H$170:$H$182="oth")*(In!$I$170:$I$182="self")*((In!$J$170:$J$182="比")*$M19+(In!$J$170:$J$182<>"比"))*In!K$170:K$182) -> 0 | D19: =SUMPRODUCT((In!$H$170:$H$182="oth")*(In!$I$170:$I$182="oai")*((In!$J$170:$J$182="比")*$M19+(In!$J$170:$J$182<>"比"))*In!K$170:K$182) -> 0 | E19: =SUMPRODUCT((In!$H$170:$H$182="oth")*(In!$I$170:$I$182="ant")*((In!$J$170:$J$182="比")*$M19+(In!$J$170:$J$182<>"比"))*In!K$170:K$182) -> 0 | F19: =SUMPRODUCT((In!$H$170:$H$182="oth")*(In!$I$170:$I$182="xai")*((In!$J$170:$J$182="比")*$M19+(In!$J$170:$J$182<>"比"))*In!K$170:K$182) -> 0 | G19: =SUMPRODUCT((In!$H$170:$H$182="oth")*(In!$I$170:$I$182="meta")*((In!$J$170:$J$182="比")*$M19+(In!$J$170:$J$182<>"比"))*In!K$170:K$182) -> 0 | H19: =SUMPRODUCT((In!$H$170:$H$182="oth")*(In!$I$170:$I$182="googl")*((In!$J$170:$J$182="比")*$M19+(In!$J$170:$J$182<>"比"))*In!K$170:K$182) -> 0 | I19: =SUMPRODUCT((In!$H$170:$H$182="oth")*(In!$I$170:$I$182="msft")*((In!$J$170:$J$182="比")*$M19+(In!$J$170:$J$182<>"比"))*In!K$170:K$182) -> 0 | J19: =SUMPRODUCT((In!$H$170:$H$182="oth")*(In!$I$170:$I$182="oth")*((In!$J$170:$J$182="比")*$M19+(In!$J$170:$J$182<>"比"))*In!K$170:K$182) -> 0 | K19: =$M19-SUM(C19:J19) -> 1 | L19: =SUM(C19:K19) -> 1 | M19: =N(Players!F296) -> 1 | N19: =L19-M19 -> 0
A20: 欄和（使用者合計） | C20: =SUM(C5:C19) -> 13.274951 | D20: =SUM(D5:D19) -> 0 | E20: =SUM(E5:E19) -> 0.626 | F20: =SUM(F5:F19) -> 0 | G20: =SUM(G5:G19) -> 2.476595 | H20: =SUM(H5:H19) -> 0 | I20: =SUM(I5:I19) -> 0 | J20: =SUM(J5:J19) -> 0 | ... N20: =SUM(N5:N19) -> 0
A21: 對照：usr_oai 報導值（口徑 In!C156；未說明讀為 IT） | D21: =IF(In!J156="","",IF(In!$C$156="設施",In!J156/Players!F$13,In!J156)) -> 1.9 | L21: =IF(OR(D21="",N(D21)=0),"",D20/D21) -> 0 | M21: ← 矩陣欄和 ÷ 報導（< 1＝揭露不足，差額在『未分配』）
A22: 對照：usr_ant 報導值（口徑 In!C157；未說明讀為 IT） | E22: =IF(In!J157="","",IF(In!$C$157="設施",In!J157/Players!F$13,In!J157)) -> 1.4 | L22: =IF(OR(E22="",N(E22)=0),"",E20/E22) -> 0.44714286 | M22: ← 矩陣欄和 ÷ 報導（< 1＝揭露不足，差額在『未分配』）
A24: 2026 年底
A25: 營運者 | B25: 鍵 | C25: 自用 | D25: OpenAI | E25: Anthropic | F25: xAI | G25: Meta | H25: Google（租用） | I25: Microsoft（租用） | J25: 其他 | K25: 未分配 | L25: 列和 | M25: Players | N25: 差
A26: Microsoft（自有＋融資租賃 AI 在役） | B26: msft | C26: =SUMPRODUCT((In!$H$170:$H$182="msft")*(In!$I$170:$I$182="self")*((In!$J$170:$J$182="比")*$M26+(In!$J$170:$J$182<>"比"))*In!L$170:L$182) -> 1.8 | D26: =SUMPRODUCT((In!$H$170:$H$182="msft")*(In!$I$170:$I$182="oai")*((In!$J$170:$J$182="比")*$M26+(In!$J$170:$J$182<>"比"))*In!L$170:L$182) -> 0 | E26: =SUMPRODUCT((In!$H$170:$H$182="msft")*(In!$I$170:$I$182="ant")*((In!$J$170:$J$182="比")*$M26+(In!$J$170:$J$182<>"比"))*In!L$170:L$182) -> 0 | F26: =SUMPRODUCT((In!$H$170:$H$182="msft")*(In!$I$170:$I$182="xai")*((In!$J$170:$J$182="比")*$M26+(In!$J$170:$J$182<>"比"))*In!L$170:L$182) -> 0 | G26: =SUMPRODUCT((In!$H$170:$H$182="msft")*(In!$I$170:$I$182="meta")*((In!$J$170:$J$182="比")*$M26+(In!$J$170:$J$182<>"比"))*In!L$170:L$182) -> 0 | H26: =SUMPRODUCT((In!$H$170:$H$182="msft")*(In!$I$170:$I$182="googl")*((In!$J$170:$J$182="比")*$M26+(In!$J$170:$J$182<>"比"))*In!L$170:L$182) -> 0 | I26: =SUMPRODUCT((In!$H$170:$H$182="msft")*(In!$I$170:$I$182="msft")*((In!$J$170:$J$182="比")*$M26+(In!$J$170:$J$182<>"比"))*In!L$170:L$182) -> 0 | J26: =SUMPRODUCT((In!$H$170:$H$182="msft")*(In!$I$170:$I$182="oth")*((In!$J$170:$J$182="比")*$M26+(In!$J$170:$J$182<>"比"))*In!L$170:L$182) -> 0 | K26: =$M26-SUM(C26:J26) -> 2.7 | L26: =SUM(C26:K26) -> 4.5 | M26: =N(Players!G30) -> 4.5 | N26: =L26-M26 -> 0
A27: Alphabet（Google；TPU＋NVIDIA） | B27: googl | C27: =SUMPRODUCT((In!$H$170:$H$182="googl")*(In!$I$170:$I$182="self")*((In!$J$170:$J$182="比")*$M27+(In!$J$170:$J$182<>"比"))*In!L$170:L$182) -> 3.9148754 | D27: =SUMPRODUCT((In!$H$170:$H$182="googl")*(In!$I$170:$I$182="oai")*((In!$J$170:$J$182="比")*$M27+(In!$J$170:$J$182<>"比"))*In!L$170:L$182) -> 0 | E27: =SUMPRODUCT((In!$H$170:$H$182="googl")*(In!$I$170:$I$182="ant")*((In!$J$170:$J$182="比")*$M27+(In!$J$170:$J$182<>"比"))*In!L$170:L$182) -> 1 | F27: =SUMPRODUCT((In!$H$170:$H$182="googl")*(In!$I$170:$I$182="xai")*((In!$J$170:$J$182="比")*$M27+(In!$J$170:$J$182<>"比"))*In!L$170:L$182) -> 0 | G27: =SUMPRODUCT((In!$H$170:$H$182="googl")*(In!$I$170:$I$182="meta")*((In!$J$170:$J$182="比")*$M27+(In!$J$170:$J$182<>"比"))*In!L$170:L$182) -> 0 | H27: =SUMPRODUCT((In!$H$170:$H$182="googl")*(In!$I$170:$I$182="googl")*((In!$J$170:$J$182="比")*$M27+(In!$J$170:$J$182<>"比"))*In!L$170:L$182) -> 0 | I27: =SUMPRODUCT((In!$H$170:$H$182="googl")*(In!$I$170:$I$182="msft")*((In!$J$170:$J$182="比")*$M27+(In!$J$170:$J$182<>"比"))*In!L$170:L$182) -> 0 | J27: =SUMPRODUCT((In!$H$170:$H$182="googl")*(In!$I$170:$I$182="oth")*((In!$J$170:$J$182="比")*$M27+(In!$J$170:$J$182<>"比"))*In!L$170:L$182) -> 0 | K27: =$M27-SUM(C27:J27) -> 0.67780374 | L27: =SUM(C27:K27) -> 5.5926791 | M27: =N(Players!G49) -> 5.5926791 | N27: =L27-M27 -> 0
A28: Amazon（AWS；Trainium＋NVIDIA） | B28: amzn | C28: =SUMPRODUCT((In!$H$170:$H$182="amzn")*(In!$I$170:$I$182="self")*((In!$J$170:$J$182="比")*$M28+(In!$J$170:$J$182<>"比"))*In!L$170:L$182) -> 0.5454 | D28: =SUMPRODUCT((In!$H$170:$H$182="amzn")*(In!$I$170:$I$182="oai")*((In!$J$170:$J$182="比")*$M28+(In!$J$170:$J$182<>"比"))*In!L$170:L$182) -> 0 | E28: =SUMPRODUCT((In!$H$170:$H$182="amzn")*(In!$I$170:$I$182="ant")*((In!$J$170:$J$182="比")*$M28+(In!$J$170:$J$182<>"比"))*In!L$170:L$182) -> 1.037 | F28: =SUMPRODUCT((In!$H$170:$H$182="amzn")*(In!$I$170:$I$182="xai")*((In!$J$170:$J$182="比")*$M28+(In!$J$170:$J$182<>"比"))*In!L$170:L$182) -> 0 | G28: =SUMPRODUCT((In!$H$170:$H$182="amzn")*(In!$I$170:$I$182="meta")*((In!$J$170:$J$182="比")*$M28+(In!$J$170:$J$182<>"比"))*In!L$170:L$182) -> 0 | H28: =SUMPRODUCT((In!$H$170:$H$182="amzn")*(In!$I$170:$I$182="googl")*((In!$J$170:$J$182="比")*$M28+(In!$J$170:$J$182<>"比"))*In!L$170:L$182) -> 0 | I28: =SUMPRODUCT((In!$H$170:$H$182="amzn")*(In!$I$170:$I$182="msft")*((In!$J$170:$J$182="比")*$M28+(In!$J$170:$J$182<>"比"))*In!L$170:L$182) -> 0 | J28: =SUMPRODUCT((In!$H$170:$H$182="amzn")*(In!$I$170:$I$182="oth")*((In!$J$170:$J$182="比")*$M28+(In!$J$170:$J$182<>"比"))*In!L$170:L$182) -> 0 | K28: =$M28-SUM(C28:J28) -> 1.1446 | L28: =SUM(C28:K28) -> 2.727 | M28: =N(Players!G68) -> 2.727 | N28: =L28-M28 -> 0
A29: Meta | B29: meta | C29: =SUMPRODUCT((In!$H$170:$H$182="meta")*(In!$I$170:$I$182="self")*((In!$J$170:$J$182="比")*$M29+(In!$J$170:$J$182<>"比"))*In!L$170:L$182) -> 0 | D29: =SUMPRODUCT((In!$H$170:$H$182="meta")*(In!$I$170:$I$182="oai")*((In!$J$170:$J$182="比")*$M29+(In!$J$170:$J$182<>"比"))*In!L$170:L$182) -> 0 | E29: =SUMPRODUCT((In!$H$170:$H$182="meta")*(In!$I$170:$I$182="ant")*((In!$J$170:$J$182="比")*$M29+(In!$J$170:$J$182<>"比"))*In!L$170:L$182) -> 0 | F29: =SUMPRODUCT((In!$H$170:$H$182="meta")*(In!$I$170:$I$182="xai")*((In!$J$170:$J$182="比")*$M29+(In!$J$170:$J$182<>"比"))*In!L$170:L$182) -> 0 | G29: =SUMPRODUCT((In!$H$170:$H$182="meta")*(In!$I$170:$I$182="meta")*((In!$J$170:$J$182="比")*$M29+(In!$J$170:$J$182<>"比"))*In!L$170:L$182) -> 3.152595 | H29: =SUMPRODUCT((In!$H$170:$H$182="meta")*(In!$I$170:$I$182="googl")*((In!$J$170:$J$182="比")*$M29+(In!$J$170:$J$182<>"比"))*In!L$170:L$182) -> 0 | I29: =SUMPRODUCT((In!$H$170:$H$182="meta")*(In!$I$170:$I$182="msft")*((In!$J$170:$J$182="比")*$M29+(In!$J$170:$J$182<>"比"))*In!L$170:L$182) -> 0 | J29: =SUMPRODUCT((In!$H$170:$H$182="meta")*(In!$I$170:$I$182="oth")*((In!$J$170:$J$182="比")*$M29+(In!$J$170:$J$182<>"比"))*In!L$170:L$182) -> 0 | K29: =$M29-SUM(C29:J29) -> 0 | L29: =SUM(C29:K29) -> 3.152595 | M29: =N(Players!G87) -> 3.152595 | N29: =L29-M29 -> 0
A30: Oracle（OCI；含承租 Stargate 站點） | B30: orcl | C30: =SUMPRODUCT((In!$H$170:$H$182="orcl")*(In!$I$170:$I$182="self")*((In!$J$170:$J$182="比")*$M30+(In!$J$170:$J$182<>"比"))*In!L$170:L$182) -> 0 | D30: =SUMPRODUCT((In!$H$170:$H$182="orcl")*(In!$I$170:$I$182="oai")*((In!$J$170:$J$182="比")*$M30+(In!$J$170:$J$182<>"比"))*In!L$170:L$182) -> 0.824 | E30: =SUMPRODUCT((In!$H$170:$H$182="orcl")*(In!$I$170:$I$182="ant")*((In!$J$170:$J$182="比")*$M30+(In!$J$170:$J$182<>"比"))*In!L$170:L$182) -> 0 | F30: =SUMPRODUCT((In!$H$170:$H$182="orcl")*(In!$I$170:$I$182="xai")*((In!$J$170:$J$182="比")*$M30+(In!$J$170:$J$182<>"比"))*In!L$170:L$182) -> 0 | G30: =SUMPRODUCT((In!$H$170:$H$182="orcl")*(In!$I$170:$I$182="meta")*((In!$J$170:$J$182="比")*$M30+(In!$J$170:$J$182<>"比"))*In!L$170:L$182) -> 0 | H30: =SUMPRODUCT((In!$H$170:$H$182="orcl")*(In!$I$170:$I$182="googl")*((In!$J$170:$J$182="比")*$M30+(In!$J$170:$J$182<>"比"))*In!L$170:L$182) -> 0 | I30: =SUMPRODUCT((In!$H$170:$H$182="orcl")*(In!$I$170:$I$182="msft")*((In!$J$170:$J$182="比")*$M30+(In!$J$170:$J$182<>"比"))*In!L$170:L$182) -> 0 | J30: =SUMPRODUCT((In!$H$170:$H$182="orcl")*(In!$I$170:$I$182="oth")*((In!$J$170:$J$182="比")*$M30+(In!$J$170:$J$182<>"比"))*In!L$170:L$182) -> 0 | K30: =$M30-SUM(C30:J30) -> 1.925 | L30: =SUM(C30:K30) -> 2.749 | M30: =N(Players!G106) -> 2.749 | N30: =L30-M30 -> 0
A31: CoreWeave | B31: crwv | C31: =SUMPRODUCT((In!$H$170:$H$182="crwv")*(In!$I$170:$I$182="self")*((In!$J$170:$J$182="比")*$M31+(In!$J$170:$J$182<>"比"))*In!L$170:L$182) -> 0 | D31: =SUMPRODUCT((In!$H$170:$H$182="crwv")*(In!$I$170:$I$182="oai")*((In!$J$170:$J$182="比")*$M31+(In!$J$170:$J$182<>"比"))*In!L$170:L$182) -> 0 | E31: =SUMPRODUCT((In!$H$170:$H$182="crwv")*(In!$I$170:$I$182="ant")*((In!$J$170:$J$182="比")*$M31+(In!$J$170:$J$182<>"比"))*In!L$170:L$182) -> 0 | F31: =SUMPRODUCT((In!$H$170:$H$182="crwv")*(In!$I$170:$I$182="xai")*((In!$J$170:$J$182="比")*$M31+(In!$J$170:$J$182<>"比"))*In!L$170:L$182) -> 0 | G31: =SUMPRODUCT((In!$H$170:$H$182="crwv")*(In!$I$170:$I$182="meta")*((In!$J$170:$J$182="比")*$M31+(In!$J$170:$J$182<>"比"))*In!L$170:L$182) -> 0 | H31: =SUMPRODUCT((In!$H$170:$H$182="crwv")*(In!$I$170:$I$182="googl")*((In!$J$170:$J$182="比")*$M31+(In!$J$170:$J$182<>"比"))*In!L$170:L$182) -> 0 | I31: =SUMPRODUCT((In!$H$170:$H$182="crwv")*(In!$I$170:$I$182="msft")*((In!$J$170:$J$182="比")*$M31+(In!$J$170:$J$182<>"比"))*In!L$170:L$182) -> 0 | J31: =SUMPRODUCT((In!$H$170:$H$182="crwv")*(In!$I$170:$I$182="oth")*((In!$J$170:$J$182="比")*$M31+(In!$J$170:$J$182<>"比"))*In!L$170:L$182) -> 0 | K31: =$M31-SUM(C31:J31) -> 1.85 | L31: =SUM(C31:K31) -> 1.85 | M31: =N(Players!G125) -> 1.85 | N31: =L31-M31 -> 0
A32: Nebius | B32: nbis | C32: =SUMPRODUCT((In!$H$170:$H$182="nbis")*(In!$I$170:$I$182="self")*((In!$J$170:$J$182="比")*$M32+(In!$J$170:$J$182<>"比"))*In!L$170:L$182) -> 0 | D32: =SUMPRODUCT((In!$H$170:$H$182="nbis")*(In!$I$170:$I$182="oai")*((In!$J$170:$J$182="比")*$M32+(In!$J$170:$J$182<>"比"))*In!L$170:L$182) -> 0 | E32: =SUMPRODUCT((In!$H$170:$H$182="nbis")*(In!$I$170:$I$182="ant")*((In!$J$170:$J$182="比")*$M32+(In!$J$170:$J$182<>"比"))*In!L$170:L$182) -> 0 | F32: =SUMPRODUCT((In!$H$170:$H$182="nbis")*(In!$I$170:$I$182="xai")*((In!$J$170:$J$182="比")*$M32+(In!$J$170:$J$182<>"比"))*In!L$170:L$182) -> 0 | G32: =SUMPRODUCT((In!$H$170:$H$182="nbis")*(In!$I$170:$I$182="meta")*((In!$J$170:$J$182="比")*$M32+(In!$J$170:$J$182<>"比"))*In!L$170:L$182) -> 0 | H32: =SUMPRODUCT((In!$H$170:$H$182="nbis")*(In!$I$170:$I$182="googl")*((In!$J$170:$J$182="比")*$M32+(In!$J$170:$J$182<>"比"))*In!L$170:L$182) -> 0 | I32: =SUMPRODUCT((In!$H$170:$H$182="nbis")*(In!$I$170:$I$182="msft")*((In!$J$170:$J$182="比")*$M32+(In!$J$170:$J$182<>"比"))*In!L$170:L$182) -> 0 | J32: =SUMPRODUCT((In!$H$170:$H$182="nbis")*(In!$I$170:$I$182="oth")*((In!$J$170:$J$182="比")*$M32+(In!$J$170:$J$182<>"比"))*In!L$170:L$182) -> 0 | K32: =$M32-SUM(C32:J32) -> 0.9 | L32: =SUM(C32:K32) -> 0.9 | M32: =N(Players!G144) -> 0.9 | N32: =L32-M32 -> 0
A33: WhiteFiber（雲端） | B33: wyfi | C33: =SUMPRODUCT((In!$H$170:$H$182="wyfi")*(In!$I$170:$I$182="self")*((In!$J$170:$J$182="比")*$M33+(In!$J$170:$J$182<>"比"))*In!L$170:L$182) -> 0 | D33: =SUMPRODUCT((In!$H$170:$H$182="wyfi")*(In!$I$170:$I$182="oai")*((In!$J$170:$J$182="比")*$M33+(In!$J$170:$J$182<>"比"))*In!L$170:L$182) -> 0 | E33: =SUMPRODUCT((In!$H$170:$H$182="wyfi")*(In!$I$170:$I$182="ant")*((In!$J$170:$J$182="比")*$M33+(In!$J$170:$J$182<>"比"))*In!L$170:L$182) -> 0 | F33: =SUMPRODUCT((In!$H$170:$H$182="wyfi")*(In!$I$170:$I$182="xai")*((In!$J$170:$J$182="比")*$M33+(In!$J$170:$J$182<>"比"))*In!L$170:L$182) -> 0 | G33: =SUMPRODUCT((In!$H$170:$H$182="wyfi")*(In!$I$170:$I$182="meta")*((In!$J$170:$J$182="比")*$M33+(In!$J$170:$J$182<>"比"))*In!L$170:L$182) -> 0 | H33: =SUMPRODUCT((In!$H$170:$H$182="wyfi")*(In!$I$170:$I$182="googl")*((In!$J$170:$J$182="比")*$M33+(In!$J$170:$J$182<>"比"))*In!L$170:L$182) -> 0 | I33: =SUMPRODUCT((In!$H$170:$H$182="wyfi")*(In!$I$170:$I$182="msft")*((In!$J$170:$J$182="比")*$M33+(In!$J$170:$J$182<>"比"))*In!L$170:L$182) -> 0 | J33: =SUMPRODUCT((In!$H$170:$H$182="wyfi")*(In!$I$170:$I$182="oth")*((In!$J$170:$J$182="比")*$M33+(In!$J$170:$J$182<>"比"))*In!L$170:L$182) -> 0 | K33: =$M33-SUM(C33:J33) -> 0.014574 | L33: =SUM(C33:K33) -> 0.014574 | M33: =N(Players!G163) -> 0.014574 | N33: =L33-M33 -> 0
A34: SpaceX／xAI（Colossus；兼出租） | B34: xai | C34: =SUMPRODUCT((In!$H$170:$H$182="xai")*(In!$I$170:$I$182="self")*((In!$J$170:$J$182="比")*$M34+(In!$J$170:$J$182<>"比"))*In!L$170:L$182) -> 0 | D34: =SUMPRODUCT((In!$H$170:$H$182="xai")*(In!$I$170:$I$182="oai")*((In!$J$170:$J$182="比")*$M34+(In!$J$170:$J$182<>"比"))*In!L$170:L$182) -> 0 | E34: =SUMPRODUCT((In!$H$170:$H$182="xai")*(In!$I$170:$I$182="ant")*((In!$J$170:$J$182="比")*$M34+(In!$J$170:$J$182<>"比"))*In!L$170:L$182) -> 0 | F34: =SUMPRODUCT((In!$H$170:$H$182="xai")*(In!$I$170:$I$182="xai")*((In!$J$170:$J$182="比")*$M34+(In!$J$170:$J$182<>"比"))*In!L$170:L$182) -> 0 | G34: =SUMPRODUCT((In!$H$170:$H$182="xai")*(In!$I$170:$I$182="meta")*((In!$J$170:$J$182="比")*$M34+(In!$J$170:$J$182<>"比"))*In!L$170:L$182) -> 0 | H34: =SUMPRODUCT((In!$H$170:$H$182="xai")*(In!$I$170:$I$182="googl")*((In!$J$170:$J$182="比")*$M34+(In!$J$170:$J$182<>"比"))*In!L$170:L$182) -> 0.19 | I34: =SUMPRODUCT((In!$H$170:$H$182="xai")*(In!$I$170:$I$182="msft")*((In!$J$170:$J$182="比")*$M34+(In!$J$170:$J$182<>"比"))*In!L$170:L$182) -> 0 | J34: =SUMPRODUCT((In!$H$170:$H$182="xai")*(In!$I$170:$I$182="oth")*((In!$J$170:$J$182="比")*$M34+(In!$J$170:$J$182<>"比"))*In!L$170:L$182) -> 0 | K34: =$M34-SUM(C34:J34) -> 1.81 | L34: =SUM(C34:K34) -> 2 | M34: =N(Players!G182) -> 2 | N34: =L34-M34 -> 0
A35: OpenAI／Stargate 自建（SoftBank、SB Energy 營運） | B35: oai | C35: =SUMPRODUCT((In!$H$170:$H$182="oai")*(In!$I$170:$I$182="self")*((In!$J$170:$J$182="比")*$M35+(In!$J$170:$J$182<>"比"))*In!L$170:L$182) -> 0 | D35: =SUMPRODUCT((In!$H$170:$H$182="oai")*(In!$I$170:$I$182="oai")*((In!$J$170:$J$182="比")*$M35+(In!$J$170:$J$182<>"比"))*In!L$170:L$182) -> 0 | E35: =SUMPRODUCT((In!$H$170:$H$182="oai")*(In!$I$170:$I$182="ant")*((In!$J$170:$J$182="比")*$M35+(In!$J$170:$J$182<>"比"))*In!L$170:L$182) -> 0 | F35: =SUMPRODUCT((In!$H$170:$H$182="oai")*(In!$I$170:$I$182="xai")*((In!$J$170:$J$182="比")*$M35+(In!$J$170:$J$182<>"比"))*In!L$170:L$182) -> 0 | G35: =SUMPRODUCT((In!$H$170:$H$182="oai")*(In!$I$170:$I$182="meta")*((In!$J$170:$J$182="比")*$M35+(In!$J$170:$J$182<>"比"))*In!L$170:L$182) -> 0 | H35: =SUMPRODUCT((In!$H$170:$H$182="oai")*(In!$I$170:$I$182="googl")*((In!$J$170:$J$182="比")*$M35+(In!$J$170:$J$182<>"比"))*In!L$170:L$182) -> 0 | I35: =SUMPRODUCT((In!$H$170:$H$182="oai")*(In!$I$170:$I$182="msft")*((In!$J$170:$J$182="比")*$M35+(In!$J$170:$J$182<>"比"))*In!L$170:L$182) -> 0 | J35: =SUMPRODUCT((In!$H$170:$H$182="oai")*(In!$I$170:$I$182="oth")*((In!$J$170:$J$182="比")*$M35+(In!$J$170:$J$182<>"比"))*In!L$170:L$182) -> 0 | K35: =$M35-SUM(C35:J35) -> 0 | L35: =SUM(C35:K35) -> 0 | M35: =N(Players!G201) -> 0 | N35: =L35-M35 -> 0
A36: Anthropic 自建 | B36: ant | C36: =SUMPRODUCT((In!$H$170:$H$182="ant")*(In!$I$170:$I$182="self")*((In!$J$170:$J$182="比")*$M36+(In!$J$170:$J$182<>"比"))*In!L$170:L$182) -> 0 | D36: =SUMPRODUCT((In!$H$170:$H$182="ant")*(In!$I$170:$I$182="oai")*((In!$J$170:$J$182="比")*$M36+(In!$J$170:$J$182<>"比"))*In!L$170:L$182) -> 0 | E36: =SUMPRODUCT((In!$H$170:$H$182="ant")*(In!$I$170:$I$182="ant")*((In!$J$170:$J$182="比")*$M36+(In!$J$170:$J$182<>"比"))*In!L$170:L$182) -> 0 | F36: =SUMPRODUCT((In!$H$170:$H$182="ant")*(In!$I$170:$I$182="xai")*((In!$J$170:$J$182="比")*$M36+(In!$J$170:$J$182<>"比"))*In!L$170:L$182) -> 0 | G36: =SUMPRODUCT((In!$H$170:$H$182="ant")*(In!$I$170:$I$182="meta")*((In!$J$170:$J$182="比")*$M36+(In!$J$170:$J$182<>"比"))*In!L$170:L$182) -> 0 | H36: =SUMPRODUCT((In!$H$170:$H$182="ant")*(In!$I$170:$I$182="googl")*((In!$J$170:$J$182="比")*$M36+(In!$J$170:$J$182<>"比"))*In!L$170:L$182) -> 0 | I36: =SUMPRODUCT((In!$H$170:$H$182="ant")*(In!$I$170:$I$182="msft")*((In!$J$170:$J$182="比")*$M36+(In!$J$170:$J$182<>"比"))*In!L$170:L$182) -> 0 | J36: =SUMPRODUCT((In!$H$170:$H$182="ant")*(In!$I$170:$I$182="oth")*((In!$J$170:$J$182="比")*$M36+(In!$J$170:$J$182<>"比"))*In!L$170:L$182) -> 0 | K36: =$M36-SUM(C36:J36) -> 0 | L36: =SUM(C36:K36) -> 0 | M36: =N(Players!G220) -> 0 | N36: =L36-M36 -> 0
A37: 其他新雲合計（IREN、TeraWulf、Lambda、Nscale、Crusoe 雲等） | B37: neo | C37: =SUMPRODUCT((In!$H$170:$H$182="neo")*(In!$I$170:$I$182="self")*((In!$J$170:$J$182="比")*$M37+(In!$J$170:$J$182<>"比"))*In!L$170:L$182) -> 0 | D37: =SUMPRODUCT((In!$H$170:$H$182="neo")*(In!$I$170:$I$182="oai")*((In!$J$170:$J$182="比")*$M37+(In!$J$170:$J$182<>"比"))*In!L$170:L$182) -> 0 | E37: =SUMPRODUCT((In!$H$170:$H$182="neo")*(In!$I$170:$I$182="ant")*((In!$J$170:$J$182="比")*$M37+(In!$J$170:$J$182<>"比"))*In!L$170:L$182) -> 0 | F37: =SUMPRODUCT((In!$H$170:$H$182="neo")*(In!$I$170:$I$182="xai")*((In!$J$170:$J$182="比")*$M37+(In!$J$170:$J$182<>"比"))*In!L$170:L$182) -> 0 | G37: =SUMPRODUCT((In!$H$170:$H$182="neo")*(In!$I$170:$I$182="meta")*((In!$J$170:$J$182="比")*$M37+(In!$J$170:$J$182<>"比"))*In!L$170:L$182) -> 0 | H37: =SUMPRODUCT((In!$H$170:$H$182="neo")*(In!$I$170:$I$182="googl")*((In!$J$170:$J$182="比")*$M37+(In!$J$170:$J$182<>"比"))*In!L$170:L$182) -> 0 | I37: =SUMPRODUCT((In!$H$170:$H$182="neo")*(In!$I$170:$I$182="msft")*((In!$J$170:$J$182="比")*$M37+(In!$J$170:$J$182<>"比"))*In!L$170:L$182) -> 0.2 | J37: =SUMPRODUCT((In!$H$170:$H$182="neo")*(In!$I$170:$I$182="oth")*((In!$J$170:$J$182="比")*$M37+(In!$J$170:$J$182<>"比"))*In!L$170:L$182) -> 0 | K37: =$M37-SUM(C37:J37) -> 1.1 | L37: =SUM(C37:K37) -> 1.3 | M37: =N(Players!G239) -> 1.3 | N37: =L37-M37 -> 0
A38: 主權 AI（中國以外；v0.1 只含 Humain） | B38: sov | C38: =SUMPRODUCT((In!$H$170:$H$182="sov")*(In!$I$170:$I$182="self")*((In!$J$170:$J$182="比")*$M38+(In!$J$170:$J$182<>"比"))*In!L$170:L$182) -> 0 | D38: =SUMPRODUCT((In!$H$170:$H$182="sov")*(In!$I$170:$I$182="oai")*((In!$J$170:$J$182="比")*$M38+(In!$J$170:$J$182<>"比"))*In!L$170:L$182) -> 0 | E38: =SUMPRODUCT((In!$H$170:$H$182="sov")*(In!$I$170:$I$182="ant")*((In!$J$170:$J$182="比")*$M38+(In!$J$170:$J$182<>"比"))*In!L$170:L$182) -> 0 | F38: =SUMPRODUCT((In!$H$170:$H$182="sov")*(In!$I$170:$I$182="xai")*((In!$J$170:$J$182="比")*$M38+(In!$J$170:$J$182<>"比"))*In!L$170:L$182) -> 0 | G38: =SUMPRODUCT((In!$H$170:$H$182="sov")*(In!$I$170:$I$182="meta")*((In!$J$170:$J$182="比")*$M38+(In!$J$170:$J$182<>"比"))*In!L$170:L$182) -> 0 | H38: =SUMPRODUCT((In!$H$170:$H$182="sov")*(In!$I$170:$I$182="googl")*((In!$J$170:$J$182="比")*$M38+(In!$J$170:$J$182<>"比"))*In!L$170:L$182) -> 0 | I38: =SUMPRODUCT((In!$H$170:$H$182="sov")*(In!$I$170:$I$182="msft")*((In!$J$170:$J$182="比")*$M38+(In!$J$170:$J$182<>"比"))*In!L$170:L$182) -> 0 | J38: =SUMPRODUCT((In!$H$170:$H$182="sov")*(In!$I$170:$I$182="oth")*((In!$J$170:$J$182="比")*$M38+(In!$J$170:$J$182<>"比"))*In!L$170:L$182) -> 0 | K38: =$M38-SUM(C38:J38) -> 0.4 | L38: =SUM(C38:K38) -> 0.4 | M38: =N(Players!G258) -> 0.4 | N38: =L38-M38 -> 0
A39: 中國合計（AI；Rystad 容量 × AI 占比） | B39: cn | C39: =SUMPRODUCT((In!$H$170:$H$182="cn")*(In!$I$170:$I$182="self")*((In!$J$170:$J$182="比")*$M39+(In!$J$170:$J$182<>"比"))*In!L$170:L$182) -> 11.666667 | D39: =SUMPRODUCT((In!$H$170:$H$182="cn")*(In!$I$170:$I$182="oai")*((In!$J$170:$J$182="比")*$M39+(In!$J$170:$J$182<>"比"))*In!L$170:L$182) -> 0 | E39: =SUMPRODUCT((In!$H$170:$H$182="cn")*(In!$I$170:$I$182="ant")*((In!$J$170:$J$182="比")*$M39+(In!$J$170:$J$182<>"比"))*In!L$170:L$182) -> 0 | F39: =SUMPRODUCT((In!$H$170:$H$182="cn")*(In!$I$170:$I$182="xai")*((In!$J$170:$J$182="比")*$M39+(In!$J$170:$J$182<>"比"))*In!L$170:L$182) -> 0 | G39: =SUMPRODUCT((In!$H$170:$H$182="cn")*(In!$I$170:$I$182="meta")*((In!$J$170:$J$182="比")*$M39+(In!$J$170:$J$182<>"比"))*In!L$170:L$182) -> 0 | H39: =SUMPRODUCT((In!$H$170:$H$182="cn")*(In!$I$170:$I$182="googl")*((In!$J$170:$J$182="比")*$M39+(In!$J$170:$J$182<>"比"))*In!L$170:L$182) -> 0 | I39: =SUMPRODUCT((In!$H$170:$H$182="cn")*(In!$I$170:$I$182="msft")*((In!$J$170:$J$182="比")*$M39+(In!$J$170:$J$182<>"比"))*In!L$170:L$182) -> 0 | J39: =SUMPRODUCT((In!$H$170:$H$182="cn")*(In!$I$170:$I$182="oth")*((In!$J$170:$J$182="比")*$M39+(In!$J$170:$J$182<>"比"))*In!L$170:L$182) -> 0 | K39: =$M39-SUM(C39:J39) -> 0 | L39: =SUM(C39:K39) -> 11.666667 | M39: =N(Players!G277) -> 11.666667 | N39: =L39-M39 -> 0
A40: 其他（主權、企業、學研；Epoch Other 扣新雲） | B40: oth | C40: =SUMPRODUCT((In!$H$170:$H$182="oth")*(In!$I$170:$I$182="self")*((In!$J$170:$J$182="比")*$M40+(In!$J$170:$J$182<>"比"))*In!L$170:L$182) -> 0 | D40: =SUMPRODUCT((In!$H$170:$H$182="oth")*(In!$I$170:$I$182="oai")*((In!$J$170:$J$182="比")*$M40+(In!$J$170:$J$182<>"比"))*In!L$170:L$182) -> 0 | E40: =SUMPRODUCT((In!$H$170:$H$182="oth")*(In!$I$170:$I$182="ant")*((In!$J$170:$J$182="比")*$M40+(In!$J$170:$J$182<>"比"))*In!L$170:L$182) -> 0 | F40: =SUMPRODUCT((In!$H$170:$H$182="oth")*(In!$I$170:$I$182="xai")*((In!$J$170:$J$182="比")*$M40+(In!$J$170:$J$182<>"比"))*In!L$170:L$182) -> 0 | G40: =SUMPRODUCT((In!$H$170:$H$182="oth")*(In!$I$170:$I$182="meta")*((In!$J$170:$J$182="比")*$M40+(In!$J$170:$J$182<>"比"))*In!L$170:L$182) -> 0 | H40: =SUMPRODUCT((In!$H$170:$H$182="oth")*(In!$I$170:$I$182="googl")*((In!$J$170:$J$182="比")*$M40+(In!$J$170:$J$182<>"比"))*In!L$170:L$182) -> 0 | I40: =SUMPRODUCT((In!$H$170:$H$182="oth")*(In!$I$170:$I$182="msft")*((In!$J$170:$J$182="比")*$M40+(In!$J$170:$J$182<>"比"))*In!L$170:L$182) -> 0 | J40: =SUMPRODUCT((In!$H$170:$H$182="oth")*(In!$I$170:$I$182="oth")*((In!$J$170:$J$182="比")*$M40+(In!$J$170:$J$182<>"比"))*In!L$170:L$182) -> 0 | K40: =$M40-SUM(C40:J40) -> 1 | L40: =SUM(C40:K40) -> 1 | M40: =N(Players!G296) -> 1 | N40: =L40-M40 -> 0
A41: 欄和（使用者合計） | C41: =SUM(C26:C40) -> 17.926942 | D41: =SUM(D26:D40) -> 0.824 | E41: =SUM(E26:E40) -> 2.037 | F41: =SUM(F26:F40) -> 0 | G41: =SUM(G26:G40) -> 3.152595 | H41: =SUM(H26:H40) -> 0.19 | I41: =SUM(I26:I40) -> 0.2 | J41: =SUM(J26:J40) -> 0 | ... N41: =SUM(N26:N40) -> 0
A42: 對照：usr_oai 報導值（口徑 In!C156；未說明讀為 IT） | D42: =IF(In!K156="","",IF(In!$C$156="設施",In!K156/Players!G$13,In!K156)) -> 5 | L42: =IF(OR(D42="",N(D42)=0),"",D41/D42) -> 0.1648 | M42: ← 矩陣欄和 ÷ 報導（< 1＝揭露不足，差額在『未分配』）
A43: 對照：usr_ant 報導值（口徑 In!C157；未說明讀為 IT） | E43: =IF(In!K157="","",IF(In!$C$157="設施",In!K157/Players!G$13,In!K157)) -> 5 | L43: =IF(OR(E43="",N(E43)=0),"",E41/E43) -> 0.4074 | M43: ← 矩陣欄和 ÷ 報導（< 1＝揭露不足，差額在『未分配』）
A45: 2027 年底
A46: 營運者 | B46: 鍵 | C46: 自用 | D46: OpenAI | E46: Anthropic | F46: xAI | G46: Meta | H46: Google（租用） | I46: Microsoft（租用） | J46: 其他 | K46: 未分配 | L46: 列和 | M46: Players | N46: 差
A47: Microsoft（自有＋融資租賃 AI 在役） | B47: msft | C47: =SUMPRODUCT((In!$H$170:$H$182="msft")*(In!$I$170:$I$182="self")*((In!$J$170:$J$182="比")*$M47+(In!$J$170:$J$182<>"比"))*In!M$170:M$182) -> 2.216 | D47: =SUMPRODUCT((In!$H$170:$H$182="msft")*(In!$I$170:$I$182="oai")*((In!$J$170:$J$182="比")*$M47+(In!$J$170:$J$182<>"比"))*In!M$170:M$182) -> 0 | E47: =SUMPRODUCT((In!$H$170:$H$182="msft")*(In!$I$170:$I$182="ant")*((In!$J$170:$J$182="比")*$M47+(In!$J$170:$J$182<>"比"))*In!M$170:M$182) -> 0 | F47: =SUMPRODUCT((In!$H$170:$H$182="msft")*(In!$I$170:$I$182="xai")*((In!$J$170:$J$182="比")*$M47+(In!$J$170:$J$182<>"比"))*In!M$170:M$182) -> 0 | G47: =SUMPRODUCT((In!$H$170:$H$182="msft")*(In!$I$170:$I$182="meta")*((In!$J$170:$J$182="比")*$M47+(In!$J$170:$J$182<>"比"))*In!M$170:M$182) -> 0 | H47: =SUMPRODUCT((In!$H$170:$H$182="msft")*(In!$I$170:$I$182="googl")*((In!$J$170:$J$182="比")*$M47+(In!$J$170:$J$182<>"比"))*In!M$170:M$182) -> 0 | I47: =SUMPRODUCT((In!$H$170:$H$182="msft")*(In!$I$170:$I$182="msft")*((In!$J$170:$J$182="比")*$M47+(In!$J$170:$J$182<>"比"))*In!M$170:M$182) -> 0 | J47: =SUMPRODUCT((In!$H$170:$H$182="msft")*(In!$I$170:$I$182="oth")*((In!$J$170:$J$182="比")*$M47+(In!$J$170:$J$182<>"比"))*In!M$170:M$182) -> 0 | K47: =$M47-SUM(C47:J47) -> 3.324 | L47: =SUM(C47:K47) -> 5.54 | M47: =N(Players!H30) -> 5.54 | N47: =L47-M47 -> 0
A48: Alphabet（Google；TPU＋NVIDIA） | B48: googl | C48: =SUMPRODUCT((In!$H$170:$H$182="googl")*(In!$I$170:$I$182="self")*((In!$J$170:$J$182="比")*$M48+(In!$J$170:$J$182<>"比"))*In!M$170:M$182) -> 3.9148754 | D48: =SUMPRODUCT((In!$H$170:$H$182="googl")*(In!$I$170:$I$182="oai")*((In!$J$170:$J$182="比")*$M48+(In!$J$170:$J$182<>"比"))*In!M$170:M$182) -> 0 | E48: =SUMPRODUCT((In!$H$170:$H$182="googl")*(In!$I$170:$I$182="ant")*((In!$J$170:$J$182="比")*$M48+(In!$J$170:$J$182<>"比"))*In!M$170:M$182) -> 1 | F48: =SUMPRODUCT((In!$H$170:$H$182="googl")*(In!$I$170:$I$182="xai")*((In!$J$170:$J$182="比")*$M48+(In!$J$170:$J$182<>"比"))*In!M$170:M$182) -> 0 | G48: =SUMPRODUCT((In!$H$170:$H$182="googl")*(In!$I$170:$I$182="meta")*((In!$J$170:$J$182="比")*$M48+(In!$J$170:$J$182<>"比"))*In!M$170:M$182) -> 0 | H48: =SUMPRODUCT((In!$H$170:$H$182="googl")*(In!$I$170:$I$182="googl")*((In!$J$170:$J$182="比")*$M48+(In!$J$170:$J$182<>"比"))*In!M$170:M$182) -> 0 | I48: =SUMPRODUCT((In!$H$170:$H$182="googl")*(In!$I$170:$I$182="msft")*((In!$J$170:$J$182="比")*$M48+(In!$J$170:$J$182<>"比"))*In!M$170:M$182) -> 0 | J48: =SUMPRODUCT((In!$H$170:$H$182="googl")*(In!$I$170:$I$182="oth")*((In!$J$170:$J$182="比")*$M48+(In!$J$170:$J$182<>"比"))*In!M$170:M$182) -> 0 | K48: =$M48-SUM(C48:J48) -> 0.67780374 | L48: =SUM(C48:K48) -> 5.5926791 | M48: =N(Players!H49) -> 5.5926791 | N48: =L48-M48 -> 0
A49: Amazon（AWS；Trainium＋NVIDIA） | B49: amzn | C49: =SUMPRODUCT((In!$H$170:$H$182="amzn")*(In!$I$170:$I$182="self")*((In!$J$170:$J$182="比")*$M49+(In!$J$170:$J$182<>"比"))*In!M$170:M$182) -> 0.5536 | D49: =SUMPRODUCT((In!$H$170:$H$182="amzn")*(In!$I$170:$I$182="oai")*((In!$J$170:$J$182="比")*$M49+(In!$J$170:$J$182<>"比"))*In!M$170:M$182) -> 0 | E49: =SUMPRODUCT((In!$H$170:$H$182="amzn")*(In!$I$170:$I$182="ant")*((In!$J$170:$J$182="比")*$M49+(In!$J$170:$J$182<>"比"))*In!M$170:M$182) -> 1.037 | F49: =SUMPRODUCT((In!$H$170:$H$182="amzn")*(In!$I$170:$I$182="xai")*((In!$J$170:$J$182="比")*$M49+(In!$J$170:$J$182<>"比"))*In!M$170:M$182) -> 0 | G49: =SUMPRODUCT((In!$H$170:$H$182="amzn")*(In!$I$170:$I$182="meta")*((In!$J$170:$J$182="比")*$M49+(In!$J$170:$J$182<>"比"))*In!M$170:M$182) -> 0 | H49: =SUMPRODUCT((In!$H$170:$H$182="amzn")*(In!$I$170:$I$182="googl")*((In!$J$170:$J$182="比")*$M49+(In!$J$170:$J$182<>"比"))*In!M$170:M$182) -> 0 | I49: =SUMPRODUCT((In!$H$170:$H$182="amzn")*(In!$I$170:$I$182="msft")*((In!$J$170:$J$182="比")*$M49+(In!$J$170:$J$182<>"比"))*In!M$170:M$182) -> 0 | J49: =SUMPRODUCT((In!$H$170:$H$182="amzn")*(In!$I$170:$I$182="oth")*((In!$J$170:$J$182="比")*$M49+(In!$J$170:$J$182<>"比"))*In!M$170:M$182) -> 0 | K49: =$M49-SUM(C49:J49) -> 1.1774 | L49: =SUM(C49:K49) -> 2.768 | M49: =N(Players!H68) -> 2.768 | N49: =L49-M49 -> 0
A50: Meta | B50: meta | C50: =SUMPRODUCT((In!$H$170:$H$182="meta")*(In!$I$170:$I$182="self")*((In!$J$170:$J$182="比")*$M50+(In!$J$170:$J$182<>"比"))*In!M$170:M$182) -> 0 | D50: =SUMPRODUCT((In!$H$170:$H$182="meta")*(In!$I$170:$I$182="oai")*((In!$J$170:$J$182="比")*$M50+(In!$J$170:$J$182<>"比"))*In!M$170:M$182) -> 0 | E50: =SUMPRODUCT((In!$H$170:$H$182="meta")*(In!$I$170:$I$182="ant")*((In!$J$170:$J$182="比")*$M50+(In!$J$170:$J$182<>"比"))*In!M$170:M$182) -> 0 | F50: =SUMPRODUCT((In!$H$170:$H$182="meta")*(In!$I$170:$I$182="xai")*((In!$J$170:$J$182="比")*$M50+(In!$J$170:$J$182<>"比"))*In!M$170:M$182) -> 0 | G50: =SUMPRODUCT((In!$H$170:$H$182="meta")*(In!$I$170:$I$182="meta")*((In!$J$170:$J$182="比")*$M50+(In!$J$170:$J$182<>"比"))*In!M$170:M$182) -> 3.344595 | H50: =SUMPRODUCT((In!$H$170:$H$182="meta")*(In!$I$170:$I$182="googl")*((In!$J$170:$J$182="比")*$M50+(In!$J$170:$J$182<>"比"))*In!M$170:M$182) -> 0 | I50: =SUMPRODUCT((In!$H$170:$H$182="meta")*(In!$I$170:$I$182="msft")*((In!$J$170:$J$182="比")*$M50+(In!$J$170:$J$182<>"比"))*In!M$170:M$182) -> 0 | J50: =SUMPRODUCT((In!$H$170:$H$182="meta")*(In!$I$170:$I$182="oth")*((In!$J$170:$J$182="比")*$M50+(In!$J$170:$J$182<>"比"))*In!M$170:M$182) -> 0 | K50: =$M50-SUM(C50:J50) -> 0 | L50: =SUM(C50:K50) -> 3.344595 | M50: =N(Players!H87) -> 3.344595 | N50: =L50-M50 -> 0
A51: Oracle（OCI；含承租 Stargate 站點） | B51: orcl | C51: =SUMPRODUCT((In!$H$170:$H$182="orcl")*(In!$I$170:$I$182="self")*((In!$J$170:$J$182="比")*$M51+(In!$J$170:$J$182<>"比"))*In!M$170:M$182) -> 0 | D51: =SUMPRODUCT((In!$H$170:$H$182="orcl")*(In!$I$170:$I$182="oai")*((In!$J$170:$J$182="比")*$M51+(In!$J$170:$J$182<>"比"))*In!M$170:M$182) -> 0.991 | E51: =SUMPRODUCT((In!$H$170:$H$182="orcl")*(In!$I$170:$I$182="ant")*((In!$J$170:$J$182="比")*$M51+(In!$J$170:$J$182<>"比"))*In!M$170:M$182) -> 0 | F51: =SUMPRODUCT((In!$H$170:$H$182="orcl")*(In!$I$170:$I$182="xai")*((In!$J$170:$J$182="比")*$M51+(In!$J$170:$J$182<>"比"))*In!M$170:M$182) -> 0 | G51: =SUMPRODUCT((In!$H$170:$H$182="orcl")*(In!$I$170:$I$182="meta")*((In!$J$170:$J$182="比")*$M51+(In!$J$170:$J$182<>"比"))*In!M$170:M$182) -> 0 | H51: =SUMPRODUCT((In!$H$170:$H$182="orcl")*(In!$I$170:$I$182="googl")*((In!$J$170:$J$182="比")*$M51+(In!$J$170:$J$182<>"比"))*In!M$170:M$182) -> 0 | I51: =SUMPRODUCT((In!$H$170:$H$182="orcl")*(In!$I$170:$I$182="msft")*((In!$J$170:$J$182="比")*$M51+(In!$J$170:$J$182<>"比"))*In!M$170:M$182) -> 0 | J51: =SUMPRODUCT((In!$H$170:$H$182="orcl")*(In!$I$170:$I$182="oth")*((In!$J$170:$J$182="比")*$M51+(In!$J$170:$J$182<>"比"))*In!M$170:M$182) -> 0 | K51: =$M51-SUM(C51:J51) -> 1.9246667 | L51: =SUM(C51:K51) -> 2.9156667 | M51: =N(Players!H106) -> 2.9156667 | N51: =L51-M51 -> 0
A52: CoreWeave | B52: crwv | C52: =SUMPRODUCT((In!$H$170:$H$182="crwv")*(In!$I$170:$I$182="self")*((In!$J$170:$J$182="比")*$M52+(In!$J$170:$J$182<>"比"))*In!M$170:M$182) -> 0 | D52: =SUMPRODUCT((In!$H$170:$H$182="crwv")*(In!$I$170:$I$182="oai")*((In!$J$170:$J$182="比")*$M52+(In!$J$170:$J$182<>"比"))*In!M$170:M$182) -> 0 | E52: =SUMPRODUCT((In!$H$170:$H$182="crwv")*(In!$I$170:$I$182="ant")*((In!$J$170:$J$182="比")*$M52+(In!$J$170:$J$182<>"比"))*In!M$170:M$182) -> 0 | F52: =SUMPRODUCT((In!$H$170:$H$182="crwv")*(In!$I$170:$I$182="xai")*((In!$J$170:$J$182="比")*$M52+(In!$J$170:$J$182<>"比"))*In!M$170:M$182) -> 0 | G52: =SUMPRODUCT((In!$H$170:$H$182="crwv")*(In!$I$170:$I$182="meta")*((In!$J$170:$J$182="比")*$M52+(In!$J$170:$J$182<>"比"))*In!M$170:M$182) -> 0 | H52: =SUMPRODUCT((In!$H$170:$H$182="crwv")*(In!$I$170:$I$182="googl")*((In!$J$170:$J$182="比")*$M52+(In!$J$170:$J$182<>"比"))*In!M$170:M$182) -> 0 | I52: =SUMPRODUCT((In!$H$170:$H$182="crwv")*(In!$I$170:$I$182="msft")*((In!$J$170:$J$182="比")*$M52+(In!$J$170:$J$182<>"比"))*In!M$170:M$182) -> 0 | J52: =SUMPRODUCT((In!$H$170:$H$182="crwv")*(In!$I$170:$I$182="oth")*((In!$J$170:$J$182="比")*$M52+(In!$J$170:$J$182<>"比"))*In!M$170:M$182) -> 0 | K52: =$M52-SUM(C52:J52) -> 3.3875 | L52: =SUM(C52:K52) -> 3.3875 | M52: =N(Players!H125) -> 3.3875 | N52: =L52-M52 -> 0
A53: Nebius | B53: nbis | C53: =SUMPRODUCT((In!$H$170:$H$182="nbis")*(In!$I$170:$I$182="self")*((In!$J$170:$J$182="比")*$M53+(In!$J$170:$J$182<>"比"))*In!M$170:M$182) -> 0 | D53: =SUMPRODUCT((In!$H$170:$H$182="nbis")*(In!$I$170:$I$182="oai")*((In!$J$170:$J$182="比")*$M53+(In!$J$170:$J$182<>"比"))*In!M$170:M$182) -> 0 | E53: =SUMPRODUCT((In!$H$170:$H$182="nbis")*(In!$I$170:$I$182="ant")*((In!$J$170:$J$182="比")*$M53+(In!$J$170:$J$182<>"比"))*In!M$170:M$182) -> 0 | F53: =SUMPRODUCT((In!$H$170:$H$182="nbis")*(In!$I$170:$I$182="xai")*((In!$J$170:$J$182="比")*$M53+(In!$J$170:$J$182<>"比"))*In!M$170:M$182) -> 0 | G53: =SUMPRODUCT((In!$H$170:$H$182="nbis")*(In!$I$170:$I$182="meta")*((In!$J$170:$J$182="比")*$M53+(In!$J$170:$J$182<>"比"))*In!M$170:M$182) -> 0 | H53: =SUMPRODUCT((In!$H$170:$H$182="nbis")*(In!$I$170:$I$182="googl")*((In!$J$170:$J$182="比")*$M53+(In!$J$170:$J$182<>"比"))*In!M$170:M$182) -> 0 | I53: =SUMPRODUCT((In!$H$170:$H$182="nbis")*(In!$I$170:$I$182="msft")*((In!$J$170:$J$182="比")*$M53+(In!$J$170:$J$182<>"比"))*In!M$170:M$182) -> 0 | J53: =SUMPRODUCT((In!$H$170:$H$182="nbis")*(In!$I$170:$I$182="oth")*((In!$J$170:$J$182="比")*$M53+(In!$J$170:$J$182<>"比"))*In!M$170:M$182) -> 0 | K53: =$M53-SUM(C53:J53) -> 0.9 | L53: =SUM(C53:K53) -> 0.9 | M53: =N(Players!H144) -> 0.9 | N53: =L53-M53 -> 0
A54: WhiteFiber（雲端） | B54: wyfi | C54: =SUMPRODUCT((In!$H$170:$H$182="wyfi")*(In!$I$170:$I$182="self")*((In!$J$170:$J$182="比")*$M54+(In!$J$170:$J$182<>"比"))*In!M$170:M$182) -> 0 | D54: =SUMPRODUCT((In!$H$170:$H$182="wyfi")*(In!$I$170:$I$182="oai")*((In!$J$170:$J$182="比")*$M54+(In!$J$170:$J$182<>"比"))*In!M$170:M$182) -> 0 | E54: =SUMPRODUCT((In!$H$170:$H$182="wyfi")*(In!$I$170:$I$182="ant")*((In!$J$170:$J$182="比")*$M54+(In!$J$170:$J$182<>"比"))*In!M$170:M$182) -> 0 | F54: =SUMPRODUCT((In!$H$170:$H$182="wyfi")*(In!$I$170:$I$182="xai")*((In!$J$170:$J$182="比")*$M54+(In!$J$170:$J$182<>"比"))*In!M$170:M$182) -> 0 | G54: =SUMPRODUCT((In!$H$170:$H$182="wyfi")*(In!$I$170:$I$182="meta")*((In!$J$170:$J$182="比")*$M54+(In!$J$170:$J$182<>"比"))*In!M$170:M$182) -> 0 | H54: =SUMPRODUCT((In!$H$170:$H$182="wyfi")*(In!$I$170:$I$182="googl")*((In!$J$170:$J$182="比")*$M54+(In!$J$170:$J$182<>"比"))*In!M$170:M$182) -> 0 | I54: =SUMPRODUCT((In!$H$170:$H$182="wyfi")*(In!$I$170:$I$182="msft")*((In!$J$170:$J$182="比")*$M54+(In!$J$170:$J$182<>"比"))*In!M$170:M$182) -> 0 | J54: =SUMPRODUCT((In!$H$170:$H$182="wyfi")*(In!$I$170:$I$182="oth")*((In!$J$170:$J$182="比")*$M54+(In!$J$170:$J$182<>"比"))*In!M$170:M$182) -> 0 | K54: =$M54-SUM(C54:J54) -> 0.016548 | L54: =SUM(C54:K54) -> 0.016548 | M54: =N(Players!H163) -> 0.016548 | N54: =L54-M54 -> 0
A55: SpaceX／xAI（Colossus；兼出租） | B55: xai | C55: =SUMPRODUCT((In!$H$170:$H$182="xai")*(In!$I$170:$I$182="self")*((In!$J$170:$J$182="比")*$M55+(In!$J$170:$J$182<>"比"))*In!M$170:M$182) -> 0 | D55: =SUMPRODUCT((In!$H$170:$H$182="xai")*(In!$I$170:$I$182="oai")*((In!$J$170:$J$182="比")*$M55+(In!$J$170:$J$182<>"比"))*In!M$170:M$182) -> 0 | E55: =SUMPRODUCT((In!$H$170:$H$182="xai")*(In!$I$170:$I$182="ant")*((In!$J$170:$J$182="比")*$M55+(In!$J$170:$J$182<>"比"))*In!M$170:M$182) -> 0 | F55: =SUMPRODUCT((In!$H$170:$H$182="xai")*(In!$I$170:$I$182="xai")*((In!$J$170:$J$182="比")*$M55+(In!$J$170:$J$182<>"比"))*In!M$170:M$182) -> 0 | G55: =SUMPRODUCT((In!$H$170:$H$182="xai")*(In!$I$170:$I$182="meta")*((In!$J$170:$J$182="比")*$M55+(In!$J$170:$J$182<>"比"))*In!M$170:M$182) -> 0 | H55: =SUMPRODUCT((In!$H$170:$H$182="xai")*(In!$I$170:$I$182="googl")*((In!$J$170:$J$182="比")*$M55+(In!$J$170:$J$182<>"比"))*In!M$170:M$182) -> 0.19 | I55: =SUMPRODUCT((In!$H$170:$H$182="xai")*(In!$I$170:$I$182="msft")*((In!$J$170:$J$182="比")*$M55+(In!$J$170:$J$182<>"比"))*In!M$170:M$182) -> 0 | J55: =SUMPRODUCT((In!$H$170:$H$182="xai")*(In!$I$170:$I$182="oth")*((In!$J$170:$J$182="比")*$M55+(In!$J$170:$J$182<>"比"))*In!M$170:M$182) -> 0 | K55: =$M55-SUM(C55:J55) -> 2.395 | L55: =SUM(C55:K55) -> 2.585 | M55: =N(Players!H182) -> 2.585 | N55: =L55-M55 -> 0
A56: OpenAI／Stargate 自建（SoftBank、SB Energy 營運） | B56: oai | C56: =SUMPRODUCT((In!$H$170:$H$182="oai")*(In!$I$170:$I$182="self")*((In!$J$170:$J$182="比")*$M56+(In!$J$170:$J$182<>"比"))*In!M$170:M$182) -> 0 | D56: =SUMPRODUCT((In!$H$170:$H$182="oai")*(In!$I$170:$I$182="oai")*((In!$J$170:$J$182="比")*$M56+(In!$J$170:$J$182<>"比"))*In!M$170:M$182) -> 0.308 | E56: =SUMPRODUCT((In!$H$170:$H$182="oai")*(In!$I$170:$I$182="ant")*((In!$J$170:$J$182="比")*$M56+(In!$J$170:$J$182<>"比"))*In!M$170:M$182) -> 0 | F56: =SUMPRODUCT((In!$H$170:$H$182="oai")*(In!$I$170:$I$182="xai")*((In!$J$170:$J$182="比")*$M56+(In!$J$170:$J$182<>"比"))*In!M$170:M$182) -> 0 | G56: =SUMPRODUCT((In!$H$170:$H$182="oai")*(In!$I$170:$I$182="meta")*((In!$J$170:$J$182="比")*$M56+(In!$J$170:$J$182<>"比"))*In!M$170:M$182) -> 0 | H56: =SUMPRODUCT((In!$H$170:$H$182="oai")*(In!$I$170:$I$182="googl")*((In!$J$170:$J$182="比")*$M56+(In!$J$170:$J$182<>"比"))*In!M$170:M$182) -> 0 | I56: =SUMPRODUCT((In!$H$170:$H$182="oai")*(In!$I$170:$I$182="msft")*((In!$J$170:$J$182="比")*$M56+(In!$J$170:$J$182<>"比"))*In!M$170:M$182) -> 0 | J56: =SUMPRODUCT((In!$H$170:$H$182="oai")*(In!$I$170:$I$182="oth")*((In!$J$170:$J$182="比")*$M56+(In!$J$170:$J$182<>"比"))*In!M$170:M$182) -> 0 | K56: =$M56-SUM(C56:J56) -> 0 | L56: =SUM(C56:K56) -> 0.308 | M56: =N(Players!H201) -> 0.308 | N56: =L56-M56 -> 0
A57: Anthropic 自建 | B57: ant | C57: =SUMPRODUCT((In!$H$170:$H$182="ant")*(In!$I$170:$I$182="self")*((In!$J$170:$J$182="比")*$M57+(In!$J$170:$J$182<>"比"))*In!M$170:M$182) -> 0 | D57: =SUMPRODUCT((In!$H$170:$H$182="ant")*(In!$I$170:$I$182="oai")*((In!$J$170:$J$182="比")*$M57+(In!$J$170:$J$182<>"比"))*In!M$170:M$182) -> 0 | E57: =SUMPRODUCT((In!$H$170:$H$182="ant")*(In!$I$170:$I$182="ant")*((In!$J$170:$J$182="比")*$M57+(In!$J$170:$J$182<>"比"))*In!M$170:M$182) -> 0 | F57: =SUMPRODUCT((In!$H$170:$H$182="ant")*(In!$I$170:$I$182="xai")*((In!$J$170:$J$182="比")*$M57+(In!$J$170:$J$182<>"比"))*In!M$170:M$182) -> 0 | G57: =SUMPRODUCT((In!$H$170:$H$182="ant")*(In!$I$170:$I$182="meta")*((In!$J$170:$J$182="比")*$M57+(In!$J$170:$J$182<>"比"))*In!M$170:M$182) -> 0 | H57: =SUMPRODUCT((In!$H$170:$H$182="ant")*(In!$I$170:$I$182="googl")*((In!$J$170:$J$182="比")*$M57+(In!$J$170:$J$182<>"比"))*In!M$170:M$182) -> 0 | I57: =SUMPRODUCT((In!$H$170:$H$182="ant")*(In!$I$170:$I$182="msft")*((In!$J$170:$J$182="比")*$M57+(In!$J$170:$J$182<>"比"))*In!M$170:M$182) -> 0 | J57: =SUMPRODUCT((In!$H$170:$H$182="ant")*(In!$I$170:$I$182="oth")*((In!$J$170:$J$182="比")*$M57+(In!$J$170:$J$182<>"比"))*In!M$170:M$182) -> 0 | K57: =$M57-SUM(C57:J57) -> 0 | L57: =SUM(C57:K57) -> 0 | M57: =N(Players!H220) -> 0 | N57: =L57-M57 -> 0
A58: 其他新雲合計（IREN、TeraWulf、Lambda、Nscale、Crusoe 雲等） | B58: neo | C58: =SUMPRODUCT((In!$H$170:$H$182="neo")*(In!$I$170:$I$182="self")*((In!$J$170:$J$182="比")*$M58+(In!$J$170:$J$182<>"比"))*In!M$170:M$182) -> 0 | D58: =SUMPRODUCT((In!$H$170:$H$182="neo")*(In!$I$170:$I$182="oai")*((In!$J$170:$J$182="比")*$M58+(In!$J$170:$J$182<>"比"))*In!M$170:M$182) -> 0 | E58: =SUMPRODUCT((In!$H$170:$H$182="neo")*(In!$I$170:$I$182="ant")*((In!$J$170:$J$182="比")*$M58+(In!$J$170:$J$182<>"比"))*In!M$170:M$182) -> 0.2 | F58: =SUMPRODUCT((In!$H$170:$H$182="neo")*(In!$I$170:$I$182="xai")*((In!$J$170:$J$182="比")*$M58+(In!$J$170:$J$182<>"比"))*In!M$170:M$182) -> 0 | G58: =SUMPRODUCT((In!$H$170:$H$182="neo")*(In!$I$170:$I$182="meta")*((In!$J$170:$J$182="比")*$M58+(In!$J$170:$J$182<>"比"))*In!M$170:M$182) -> 0 | H58: =SUMPRODUCT((In!$H$170:$H$182="neo")*(In!$I$170:$I$182="googl")*((In!$J$170:$J$182="比")*$M58+(In!$J$170:$J$182<>"比"))*In!M$170:M$182) -> 0 | I58: =SUMPRODUCT((In!$H$170:$H$182="neo")*(In!$I$170:$I$182="msft")*((In!$J$170:$J$182="比")*$M58+(In!$J$170:$J$182<>"比"))*In!M$170:M$182) -> 0.2 | J58: =SUMPRODUCT((In!$H$170:$H$182="neo")*(In!$I$170:$I$182="oth")*((In!$J$170:$J$182="比")*$M58+(In!$J$170:$J$182<>"比"))*In!M$170:M$182) -> 0 | K58: =$M58-SUM(C58:J58) -> 2.007 | L58: =SUM(C58:K58) -> 2.407 | M58: =N(Players!H239) -> 2.407 | N58: =L58-M58 -> 0
A59: 主權 AI（中國以外；v0.1 只含 Humain） | B59: sov | C59: =SUMPRODUCT((In!$H$170:$H$182="sov")*(In!$I$170:$I$182="self")*((In!$J$170:$J$182="比")*$M59+(In!$J$170:$J$182<>"比"))*In!M$170:M$182) -> 0 | D59: =SUMPRODUCT((In!$H$170:$H$182="sov")*(In!$I$170:$I$182="oai")*((In!$J$170:$J$182="比")*$M59+(In!$J$170:$J$182<>"比"))*In!M$170:M$182) -> 0 | E59: =SUMPRODUCT((In!$H$170:$H$182="sov")*(In!$I$170:$I$182="ant")*((In!$J$170:$J$182="比")*$M59+(In!$J$170:$J$182<>"比"))*In!M$170:M$182) -> 0 | F59: =SUMPRODUCT((In!$H$170:$H$182="sov")*(In!$I$170:$I$182="xai")*((In!$J$170:$J$182="比")*$M59+(In!$J$170:$J$182<>"比"))*In!M$170:M$182) -> 0 | G59: =SUMPRODUCT((In!$H$170:$H$182="sov")*(In!$I$170:$I$182="meta")*((In!$J$170:$J$182="比")*$M59+(In!$J$170:$J$182<>"比"))*In!M$170:M$182) -> 0 | H59: =SUMPRODUCT((In!$H$170:$H$182="sov")*(In!$I$170:$I$182="googl")*((In!$J$170:$J$182="比")*$M59+(In!$J$170:$J$182<>"比"))*In!M$170:M$182) -> 0 | I59: =SUMPRODUCT((In!$H$170:$H$182="sov")*(In!$I$170:$I$182="msft")*((In!$J$170:$J$182="比")*$M59+(In!$J$170:$J$182<>"比"))*In!M$170:M$182) -> 0 | J59: =SUMPRODUCT((In!$H$170:$H$182="sov")*(In!$I$170:$I$182="oth")*((In!$J$170:$J$182="比")*$M59+(In!$J$170:$J$182<>"比"))*In!M$170:M$182) -> 0 | K59: =$M59-SUM(C59:J59) -> 1.9 | L59: =SUM(C59:K59) -> 1.9 | M59: =N(Players!H258) -> 1.9 | N59: =L59-M59 -> 0
A60: 中國合計（AI；Rystad 容量 × AI 占比） | B60: cn | C60: =SUMPRODUCT((In!$H$170:$H$182="cn")*(In!$I$170:$I$182="self")*((In!$J$170:$J$182="比")*$M60+(In!$J$170:$J$182<>"比"))*In!M$170:M$182) -> 13.656171 | D60: =SUMPRODUCT((In!$H$170:$H$182="cn")*(In!$I$170:$I$182="oai")*((In!$J$170:$J$182="比")*$M60+(In!$J$170:$J$182<>"比"))*In!M$170:M$182) -> 0 | E60: =SUMPRODUCT((In!$H$170:$H$182="cn")*(In!$I$170:$I$182="ant")*((In!$J$170:$J$182="比")*$M60+(In!$J$170:$J$182<>"比"))*In!M$170:M$182) -> 0 | F60: =SUMPRODUCT((In!$H$170:$H$182="cn")*(In!$I$170:$I$182="xai")*((In!$J$170:$J$182="比")*$M60+(In!$J$170:$J$182<>"比"))*In!M$170:M$182) -> 0 | G60: =SUMPRODUCT((In!$H$170:$H$182="cn")*(In!$I$170:$I$182="meta")*((In!$J$170:$J$182="比")*$M60+(In!$J$170:$J$182<>"比"))*In!M$170:M$182) -> 0 | H60: =SUMPRODUCT((In!$H$170:$H$182="cn")*(In!$I$170:$I$182="googl")*((In!$J$170:$J$182="比")*$M60+(In!$J$170:$J$182<>"比"))*In!M$170:M$182) -> 0 | I60: =SUMPRODUCT((In!$H$170:$H$182="cn")*(In!$I$170:$I$182="msft")*((In!$J$170:$J$182="比")*$M60+(In!$J$170:$J$182<>"比"))*In!M$170:M$182) -> 0 | J60: =SUMPRODUCT((In!$H$170:$H$182="cn")*(In!$I$170:$I$182="oth")*((In!$J$170:$J$182="比")*$M60+(In!$J$170:$J$182<>"比"))*In!M$170:M$182) -> 0 | K60: =$M60-SUM(C60:J60) -> 0 | L60: =SUM(C60:K60) -> 13.656171 | M60: =N(Players!H277) -> 13.656171 | N60: =L60-M60 -> 0
A61: 其他（主權、企業、學研；Epoch Other 扣新雲） | B61: oth | C61: =SUMPRODUCT((In!$H$170:$H$182="oth")*(In!$I$170:$I$182="self")*((In!$J$170:$J$182="比")*$M61+(In!$J$170:$J$182<>"比"))*In!M$170:M$182) -> 0 | D61: =SUMPRODUCT((In!$H$170:$H$182="oth")*(In!$I$170:$I$182="oai")*((In!$J$170:$J$182="比")*$M61+(In!$J$170:$J$182<>"比"))*In!M$170:M$182) -> 0 | E61: =SUMPRODUCT((In!$H$170:$H$182="oth")*(In!$I$170:$I$182="ant")*((In!$J$170:$J$182="比")*$M61+(In!$J$170:$J$182<>"比"))*In!M$170:M$182) -> 0 | F61: =SUMPRODUCT((In!$H$170:$H$182="oth")*(In!$I$170:$I$182="xai")*((In!$J$170:$J$182="比")*$M61+(In!$J$170:$J$182<>"比"))*In!M$170:M$182) -> 0 | G61: =SUMPRODUCT((In!$H$170:$H$182="oth")*(In!$I$170:$I$182="meta")*((In!$J$170:$J$182="比")*$M61+(In!$J$170:$J$182<>"比"))*In!M$170:M$182) -> 0 | H61: =SUMPRODUCT((In!$H$170:$H$182="oth")*(In!$I$170:$I$182="googl")*((In!$J$170:$J$182="比")*$M61+(In!$J$170:$J$182<>"比"))*In!M$170:M$182) -> 0 | I61: =SUMPRODUCT((In!$H$170:$H$182="oth")*(In!$I$170:$I$182="msft")*((In!$J$170:$J$182="比")*$M61+(In!$J$170:$J$182<>"比"))*In!M$170:M$182) -> 0 | J61: =SUMPRODUCT((In!$H$170:$H$182="oth")*(In!$I$170:$I$182="oth")*((In!$J$170:$J$182="比")*$M61+(In!$J$170:$J$182<>"比"))*In!M$170:M$182) -> 0 | K61: =$M61-SUM(C61:J61) -> 1 | L61: =SUM(C61:K61) -> 1 | M61: =N(Players!H296) -> 1 | N61: =L61-M61 -> 0
A62: 欄和（使用者合計） | C62: =SUM(C47:C61) -> 20.340647 | D62: =SUM(D47:D61) -> 1.299 | E62: =SUM(E47:E61) -> 2.237 | F62: =SUM(F47:F61) -> 0 | G62: =SUM(G47:G61) -> 3.344595 | H62: =SUM(H47:H61) -> 0.19 | I62: =SUM(I47:I61) -> 0.2 | J62: =SUM(J47:J61) -> 0 | ... N62: =SUM(N47:N61) -> 0
A63: 對照：usr_oai 報導值（口徑 In!C156；未說明讀為 IT） | D63: =IF(In!L156="","",IF(In!$C$156="設施",In!L156/Players!H$13,In!L156)) -> 11 | L63: =IF(OR(D63="",N(D63)=0),"",D62/D63) -> 0.11809091 | M63: ← 矩陣欄和 ÷ 報導（< 1＝揭露不足，差額在『未分配』）
A64: 對照：usr_ant 報導值（口徑 In!C157；未說明讀為 IT） | E64: =IF(In!L157="","",IF(In!$C$157="設施",In!L157/Players!H$13,In!L157)) -> 10 | L64: =IF(OR(E64="",N(E64)=0),"",E62/E64) -> 0.2237 | M64: ← 矩陣欄和 ÷ 報導（< 1＝揭露不足，差額在『未分配』）

Sheet Pipeline
A1: Pipeline — 上線事件 × 延遲情景（IT GW）。事件＝(1) 園區（In T2，有上線年月且納入＝1）＋(2) 各玩家各年『未分園區殘差』＝Players 年新增 − 該年 T2 園區；＋新納入存量（不延遲）。時間為小數年（年 Y 月 M 底＝Y＋M/12；Y 年底＝Y＋1）。延遲只作用於評價時點 asof 之後：D0＝0；D1＝每筆排定量的 dly_d1_s 延 dly_d1_m 月（園區有已知延遲者全額延已知月數）；D2＝D1 之上，原排定年在 dly_d2_y0–dly_d2_y1 且未確保電力者，dly_d2_bind 再延 dly_d2_m 月（殘差視為未確保電力）。殘差在年內均勻上線（觀測年在觀測時點前已上線）
A3: A. 園區（In T2 鏡像與上線時點）
A4: 園區鍵 | B4: 名稱 | C4: 營運者 | D4: 使用者 | E4: MW | F4: 口徑 | G4: 納入 | H4: 上線年 | I4: 上線月 | J4: 已知延遲月 | K4: t 公告 | L4: IT GW | M4: t D0 | N4: t D1 未延 | O4: t D1 延後 | P4: D0 上線年 | Q4: 有效納入 | R4: D2 適用 | S4: 已確保電力
A5: cp_msft_atl | B5: =In!B186 -> Fairwater Atlanta | C5: =IF(In!H186="","",In!H186) -> msft | D5: =IF(In!I186="","",In!I186) | E5: =IF(In!J186="","",In!J186) -> 321 | F5: =In!C186 -> IT | G5: =IF(In!N186="","",In!N186) -> 1 | H5: =IF(In!K186="","",In!K186) -> 2025 | I5: =IF(In!L186="","",In!L186) -> 10 | J5: =N(In!M186) -> 0 | K5: =IF(OR(H5="",I5=""),9999,H5+I5/12) -> 2025.8333 | L5: =IF(E5="",0,IF(F5="設施",E5/1000/INDEX(Players!$D$13:$M$13,1,MAX(1,MIN(10,H5-2022))),E5/1000*g_ITtoFac)) -> 0.321 | M5: =K5 -> 2025.8333 | N5: =IF(K5>asof,K5+N(J5)/12,K5) -> 2025.8333 | O5: =IF(K5>asof,K5+IF(N(J5)>0,N(J5),dly_d1_m)/12,K5) -> 2025.8333 | P5: =IF(K5=9999,"",ROUNDUP(K5,0)-1) -> 2025 | Q5: =IF(AND(N(G5)=1,K5<9999,L5>0),1,0) -> 1 | R5: =IF(AND(K5>asof,K5<9999,N(S5)<>1,P5>=dly_d2_y0,P5<=dly_d2_y1),1,0) -> 0 | S5: =IF(In!O186="","",In!O186) -> 0
A6: cp_msft_wi1 | B6: =In!B187 -> Fairwater Wisconsin 一期 | C6: =IF(In!H187="","",In!H187) -> msft | D6: =IF(In!I187="","",In!I187) | E6: =IF(In!J187="","",In!J187) -> 369 | F6: =In!C187 -> IT | G6: =IF(In!N187="","",In!N187) -> 1 | H6: =IF(In!K187="","",In!K187) -> 2026 | I6: =IF(In!L187="","",In!L187) -> 4 | J6: =N(In!M187) -> 0 | K6: =IF(OR(H6="",I6=""),9999,H6+I6/12) -> 2026.3333 | L6: =IF(E6="",0,IF(F6="設施",E6/1000/INDEX(Players!$D$13:$M$13,1,MAX(1,MIN(10,H6-2022))),E6/1000*g_ITtoFac)) -> 0.369 | M6: =K6 -> 2026.3333 | N6: =IF(K6>asof,K6+N(J6)/12,K6) -> 2026.3333 | O6: =IF(K6>asof,K6+IF(N(J6)>0,N(J6),dly_d1_m)/12,K6) -> 2026.3333 | P6: =IF(K6=9999,"",ROUNDUP(K6,0)-1) -> 2026 | Q6: =IF(AND(N(G6)=1,K6<9999,L6>0),1,0) -> 1 | R6: =IF(AND(K6>asof,K6<9999,N(S6)<>1,P6>=dly_d2_y0,P6<=dly_d2_y1),1,0) -> 0 | S6: =IF(In!O187="","",In!O187) -> 0
A7: cp_msft_wi2 | B7: =In!B188 -> Fairwater Wisconsin 全站餘量（2,263 − 369） | C7: =IF(In!H188="","",In!H188) -> msft | D7: =IF(In!I188="","",In!I188) | E7: =IF(In!J188="","",In!J188) -> 1526 | F7: =In!C188 -> IT | G7: =IF(In!N188="","",In!N188) -> 1 | H7: =IF(In!K188="","",In!K188) -> 2028 | I7: =IF(In!L188="","",In!L188) -> 5 | J7: =N(In!M188) -> 0 | K7: =IF(OR(H7="",I7=""),9999,H7+I7/12) -> 2028.4167 | L7: =IF(E7="",0,IF(F7="設施",E7/1000/INDEX(Players!$D$13:$M$13,1,MAX(1,MIN(10,H7-2022))),E7/1000*g_ITtoFac)) -> 1.526 | M7: =K7 -> 2028.4167 | N7: =IF(K7>asof,K7+N(J7)/12,K7) -> 2028.4167 | O7: =IF(K7>asof,K7+IF(N(J7)>0,N(J7),dly_d1_m)/12,K7) -> 2028.9167 | P7: =IF(K7=9999,"",ROUNDUP(K7,0)-1) -> 2028 | Q7: =IF(AND(N(G7)=1,K7<9999,L7>0),1,0) -> 1 | R7: =IF(AND(K7>asof,K7<9999,N(S7)<>1,P7>=dly_d2_y0,P7<=dly_d2_y1),1,0) -> 1 | S7: =IF(In!O188="","",In!O188) -> 0
A8: cp_msft_abl | B8: =In!B189 -> Abilene 鄰近園區（Crusoe 開發、Microsoft 承租） | C8: =IF(In!H189="","",In!H189) -> msft | D8: =IF(In!I189="","",In!I189) -> self | E8: =IF(In!J189="","",In!J189) -> 336 | F8: =In!C189 -> IT | G8: =IF(In!N189="","",In!N189) -> 1 | H8: =IF(In!K189="","",In!K189) -> 2027 | I8: =IF(In!L189="","",In!L189) -> 6 | J8: =N(In!M189) -> 0 | K8: =IF(OR(H8="",I8=""),9999,H8+I8/12) -> 2027.5 | L8: =IF(E8="",0,IF(F8="設施",E8/1000/INDEX(Players!$D$13:$M$13,1,MAX(1,MIN(10,H8-2022))),E8/1000*g_ITtoFac)) -> 0.336 | M8: =K8 -> 2027.5 | N8: =IF(K8>asof,K8+N(J8)/12,K8) -> 2027.5 | O8: =IF(K8>asof,K8+IF(N(J8)>0,N(J8),dly_d1_m)/12,K8) -> 2028 | P8: =IF(K8=9999,"",ROUNDUP(K8,0)-1) -> 2027 | Q8: =IF(AND(N(G8)=1,K8<9999,L8>0),1,0) -> 1 | R8: =IF(AND(K8>asof,K8<9999,N(S8)<>1,P8>=dly_d2_y0,P8<=dly_d2_y1),1,0) -> 1 | S8: =IF(In!O189="","",In!O189) -> 0
A9: cp_amzn_nc1 | B9: =In!B190 -> New Carlisle（Rainier）2026-03→10 增量 | C9: =IF(In!H190="","",In!H190) -> amzn | D9: =IF(In!I190="","",In!I190) -> ant | E9: =IF(In!J190="","",In!J190) -> 127 | F9: =In!C190 -> IT | G9: =IF(In!N190="","",In!N190) -> 1 | H9: =IF(In!K190="","",In!K190) -> 2026 | I9: =IF(In!L190="","",In!L190) -> 10 | J9: =N(In!M190) -> 0 | K9: =IF(OR(H9="",I9=""),9999,H9+I9/12) -> 2026.8333 | L9: =IF(E9="",0,IF(F9="設施",E9/1000/INDEX(Players!$D$13:$M$13,1,MAX(1,MIN(10,H9-2022))),E9/1000*g_ITtoFac)) -> 0.127 | M9: =K9 -> 2026.8333 | N9: =IF(K9>asof,K9+N(J9)/12,K9) -> 2026.8333 | O9: =IF(K9>asof,K9+IF(N(J9)>0,N(J9),dly_d1_m)/12,K9) -> 2027.3333 | P9: =IF(K9=9999,"",ROUNDUP(K9,0)-1) -> 2026 | Q9: =IF(AND(N(G9)=1,K9<9999,L9>0),1,0) -> 1 | R9: =IF(AND(K9>asof,K9<9999,N(S9)<>1,P9>=dly_d2_y0,P9<=dly_d2_y1),1,0) -> 0 | S9: =IF(In!O190="","",In!O190) -> 0
A10: cp_amzn_nc2 | B10: =In!B191 -> New Carlisle 至 2028 年 1,925 增量 | C10: =IF(In!H191="","",In!H191) -> amzn | D10: =IF(In!I191="","",In!I191) -> ant | E10: =IF(In!J191="","",In!J191) -> 888 | F10: =In!C191 -> IT | G10: =IF(In!N191="","",In!N191) -> 1 | H10: =IF(In!K191="","",In!K191) -> 2028 | I10: =IF(In!L191="","",In!L191) -> 6 | J10: =N(In!M191) -> 0 | K10: =IF(OR(H10="",I10=""),9999,H10+I10/12) -> 2028.5 | L10: =IF(E10="",0,IF(F10="設施",E10/1000/INDEX(Players!$D$13:$M$13,1,MAX(1,MIN(10,H10-2022))),E10/1000*g_ITtoFac)) -> 0.888 | M10: =K10 -> 2028.5 | N10: =IF(K10>asof,K10+N(J10)/12,K10) -> 2028.5 | O10: =IF(K10>asof,K10+IF(N(J10)>0,N(J10),dly_d1_m)/12,K10) -> 2029 | P10: =IF(K10=9999,"",ROUNDUP(K10,0)-1) -> 2028 | Q10: =IF(AND(N(G10)=1,K10<9999,L10>0),1,0) -> 1 | R10: =IF(AND(K10>asof,K10<9999,N(S10)<>1,P10>=dly_d2_y0,P10<=dly_d2_y1),1,0) -> 1 | S10: =IF(In!O191="","",In!O191) -> 0
A11: cp_meta_pro1 | B11: =In!B192 -> Prometheus（New Albany）至 2026-08 | C11: =IF(In!H192="","",In!H192) -> meta | D11: =IF(In!I192="","",In!I192) -> meta | E11: =IF(In!J192="","",In!J192) -> 471 | F11: =In!C192 -> IT | G11: =IF(In!N192="","",In!N192) -> 1 | H11: =IF(In!K192="","",In!K192) -> 2026 | I11: =IF(In!L192="","",In!L192) -> 8 | J11: =N(In!M192) -> 0 | K11: =IF(OR(H11="",I11=""),9999,H11+I11/12) -> 2026.6667 | L11: =IF(E11="",0,IF(F11="設施",E11/1000/INDEX(Players!$D$13:$M$13,1,MAX(1,MIN(10,H11-2022))),E11/1000*g_ITtoFac)) -> 0.471 | M11: =K11 -> 2026.6667 | N11: =IF(K11>asof,K11+N(J11)/12,K11) -> 2026.6667 | O11: =IF(K11>asof,K11+IF(N(J11)>0,N(J11),dly_d1_m)/12,K11) -> 2026.6667 | P11: =IF(K11=9999,"",ROUNDUP(K11,0)-1) -> 2026 | Q11: =IF(AND(N(G11)=1,K11<9999,L11>0),1,0) -> 1 | R11: =IF(AND(K11>asof,K11<9999,N(S11)<>1,P11>=dly_d2_y0,P11<=dly_d2_y1),1,0) -> 0 | S11: =IF(In!O192="","",In!O192) -> 0
A12: cp_meta_pro2 | B12: =In!B193 -> Prometheus 2026-11 增量 | C12: =IF(In!H193="","",In!H193) -> meta | D12: =IF(In!I193="","",In!I193) -> meta | E12: =IF(In!J193="","",In!J193) -> 205 | F12: =In!C193 -> IT | G12: =IF(In!N193="","",In!N193) -> 1 | H12: =IF(In!K193="","",In!K193) -> 2026 | I12: =IF(In!L193="","",In!L193) -> 11 | J12: =N(In!M193) -> 0 | K12: =IF(OR(H12="",I12=""),9999,H12+I12/12) -> 2026.9167 | L12: =IF(E12="",0,IF(F12="設施",E12/1000/INDEX(Players!$D$13:$M$13,1,MAX(1,MIN(10,H12-2022))),E12/1000*g_ITtoFac)) -> 0.205 | M12: =K12 -> 2026.9167 | N12: =IF(K12>asof,K12+N(J12)/12,K12) -> 2026.9167 | O12: =IF(K12>asof,K12+IF(N(J12)>0,N(J12),dly_d1_m)/12,K12) -> 2027.4167 | P12: =IF(K12=9999,"",ROUNDUP(K12,0)-1) -> 2026 | Q12: =IF(AND(N(G12)=1,K12<9999,L12>0),1,0) -> 1 | R12: =IF(AND(K12>asof,K12<9999,N(S12)<>1,P12>=dly_d2_y0,P12<=dly_d2_y1),1,0) -> 0 | S12: =IF(In!O193="","",In!O193) -> 0
A13: cp_meta_pro3 | B13: =In!B194 -> Prometheus 2027-07 增量 | C13: =IF(In!H194="","",In!H194) -> meta | D13: =IF(In!I194="","",In!I194) -> meta | E13: =IF(In!J194="","",In!J194) -> 192 | F13: =In!C194 -> IT | G13: =IF(In!N194="","",In!N194) -> 1 | H13: =IF(In!K194="","",In!K194) -> 2027 | I13: =IF(In!L194="","",In!L194) -> 7 | J13: =N(In!M194) -> 0 | K13: =IF(OR(H13="",I13=""),9999,H13+I13/12) -> 2027.5833 | L13: =IF(E13="",0,IF(F13="設施",E13/1000/INDEX(Players!$D$13:$M$13,1,MAX(1,MIN(10,H13-2022))),E13/1000*g_ITtoFac)) -> 0.192 | M13: =K13 -> 2027.5833 | N13: =IF(K13>asof,K13+N(J13)/12,K13) -> 2027.5833 | O13: =IF(K13>asof,K13+IF(N(J13)>0,N(J13),dly_d1_m)/12,K13) -> 2028.0833 | P13: =IF(K13=9999,"",ROUNDUP(K13,0)-1) -> 2027 | Q13: =IF(AND(N(G13)=1,K13<9999,L13>0),1,0) -> 1 | R13: =IF(AND(K13>asof,K13<9999,N(S13)<>1,P13>=dly_d2_y0,P13<=dly_d2_y1),1,0) -> 0 | S13: =IF(In!O194="","",In!O194) -> 1
A14: cp_meta_pro4 | B14: =In!B195 -> Prometheus 2028Q3 增量 | C14: =IF(In!H195="","",In!H195) -> meta | D14: =IF(In!I195="","",In!I195) -> meta | E14: =IF(In!J195="","",In!J195) -> 154 | F14: =In!C195 -> IT | G14: =IF(In!N195="","",In!N195) -> 1 | H14: =IF(In!K195="","",In!K195) -> 2028 | I14: =IF(In!L195="","",In!L195) -> 7 | J14: =N(In!M195) -> 0 | K14: =IF(OR(H14="",I14=""),9999,H14+I14/12) -> 2028.5833 | L14: =IF(E14="",0,IF(F14="設施",E14/1000/INDEX(Players!$D$13:$M$13,1,MAX(1,MIN(10,H14-2022))),E14/1000*g_ITtoFac)) -> 0.154 | M14: =K14 -> 2028.5833 | N14: =IF(K14>asof,K14+N(J14)/12,K14) -> 2028.5833 | O14: =IF(K14>asof,K14+IF(N(J14)>0,N(J14),dly_d1_m)/12,K14) -> 2029.0833 | P14: =IF(K14=9999,"",ROUNDUP(K14,0)-1) -> 2028 | Q14: =IF(AND(N(G14)=1,K14<9999,L14>0),1,0) -> 1 | R14: =IF(AND(K14>asof,K14<9999,N(S14)<>1,P14>=dly_d2_y0,P14<=dly_d2_y1),1,0) -> 0 | S14: =IF(In!O195="","",In!O195) -> 1
A15: cp_meta_hyp1 | B15: =In!B196 -> Hyperion 一期 | C15: =IF(In!H196="","",In!H196) -> meta | D15: =IF(In!I196="","",In!I196) -> meta | E15: =IF(In!J196="","",In!J196) -> 1632 | F15: =In!C196 -> IT | G15: =IF(In!N196="","",In!N196) -> 1 | H15: =IF(In!K196="","",In!K196) -> 2028 | I15: =IF(In!L196="","",In!L196) -> 1 | J15: =N(In!M196) -> 0 | K15: =IF(OR(H15="",I15=""),9999,H15+I15/12) -> 2028.0833 | L15: =IF(E15="",0,IF(F15="設施",E15/1000/INDEX(Players!$D$13:$M$13,1,MAX(1,MIN(10,H15-2022))),E15/1000*g_ITtoFac)) -> 1.632 | M15: =K15 -> 2028.0833 | N15: =IF(K15>asof,K15+N(J15)/12,K15) -> 2028.0833 | O15: =IF(K15>asof,K15+IF(N(J15)>0,N(J15),dly_d1_m)/12,K15) -> 2028.5833 | P15: =IF(K15=9999,"",ROUNDUP(K15,0)-1) -> 2028 | Q15: =IF(AND(N(G15)=1,K15<9999,L15>0),1,0) -> 1 | R15: =IF(AND(K15>asof,K15<9999,N(S15)<>1,P15>=dly_d2_y0,P15<=dly_d2_y1),1,0) -> 0 | S15: =IF(In!O196="","",In!O196) -> 1
A16: cp_meta_hyp2 | B16: =In!B197 -> Hyperion 至 2 GW（2030 前） | C16: =IF(In!H197="","",In!H197) -> meta | D16: =IF(In!I197="","",In!I197) -> meta | E16: =IF(In!J197="","",In!J197) -> 368 | F16: =In!C197 -> 未說明 | G16: =IF(In!N197="","",In!N197) -> 1 | H16: =IF(In!K197="","",In!K197) -> 2029 | I16: =IF(In!L197="","",In!L197) -> 12 | J16: =N(In!M197) -> 0 | K16: =IF(OR(H16="",I16=""),9999,H16+I16/12) -> 2030 | L16: =IF(E16="",0,IF(F16="設施",E16/1000/INDEX(Players!$D$13:$M$13,1,MAX(1,MIN(10,H16-2022))),E16/1000*g_ITtoFac)) -> 0.368 | M16: =K16 -> 2030 | N16: =IF(K16>asof,K16+N(J16)/12,K16) -> 2030 | O16: =IF(K16>asof,K16+IF(N(J16)>0,N(J16),dly_d1_m)/12,K16) -> 2030.5 | P16: =IF(K16=9999,"",ROUNDUP(K16,0)-1) -> 2029 | Q16: =IF(AND(N(G16)=1,K16<9999,L16>0),1,0) -> 1 | R16: =IF(AND(K16>asof,K16<9999,N(S16)<>1,P16>=dly_d2_y0,P16<=dly_d2_y1),1,0) -> 0 | S16: =IF(In!O197="","",In!O197) -> 0
... A64: cpx_sov_ajm | B64: =In!B245 -> Khazna Ajman（QAJ1） | C64: =IF(In!H245="","",In!H245) -> sov | D64: =IF(In!I245="","",In!I245) | E64: =IF(In!J245="","",In!J245) -> 30 | F64: =In!C245 -> IT | G64: =IF(In!N245="","",In!N245) -> 0 | H64: =IF(In!K245="","",In!K245) -> 2026 | I64: =IF(In!L245="","",In!L245) -> 12 | J64: =N(In!M245) -> 0 | K64: =IF(OR(H64="",I64=""),9999,H64+I64/12) -> 2027 | L64: =IF(E64="",0,IF(F64="設施",E64/1000/INDEX(Players!$D$13:$M$13,1,MAX(1,MIN(10,H64-2022))),E64/1000*g_ITtoFac)) -> 0.03 | M64: =K64 -> 2027 | N64: =IF(K64>asof,K64+N(J64)/12,K64) -> 2027 | O64: =IF(K64>asof,K64+IF(N(J64)>0,N(J64),dly_d1_m)/12,K64) -> 2027.5 | P64: =IF(K64=9999,"",ROUNDUP(K64,0)-1) -> 2026 | Q64: =IF(AND(N(G64)=1,K64<9999,L64>0),1,0) -> 0 | R64: =IF(AND(K64>asof,K64<9999,N(S64)<>1,P64>=dly_d2_y0,P64<=dly_d2_y1),1,0) -> 0 | S64: =IF(In!O245="","",In!O245) -> 0
A66: B. 未分園區殘差（IT GW；Players 年新增 − 該營運者該年 D0 上線的 T2 園區）
A67: 玩家 | B67: 鍵 | C67: 類別 | D67: 2023 | E67: 2024 | F67: 2025 | G67: 2026 | H67: 2027 | I67: 2028 | J67: 2029 | K67: 2030 | L67: 2031 | M67: 2032
A68: Microsoft（自有＋融資租賃 AI 在役） | B68: msft | C68: 殘差合計 | E68: =Players!E36-SUMIFS($L$5:$L$64,$C$5:$C$64,"msft",$Q$5:$Q$64,1,$P$5:$P$64,2024) -> 0 | F68: =Players!F36-SUMIFS($L$5:$L$64,$C$5:$C$64,"msft",$Q$5:$Q$64,1,$P$5:$P$64,2025) -> 1.81427 | G68: =Players!G36-SUMIFS($L$5:$L$64,$C$5:$C$64,"msft",$Q$5:$Q$64,1,$P$5:$P$64,2026) -> 0.086955 | H68: =Players!H36-SUMIFS($L$5:$L$64,$C$5:$C$64,"msft",$Q$5:$Q$64,1,$P$5:$P$64,2027) -> 0 | I68: =Players!I36-SUMIFS($L$5:$L$64,$C$5:$C$64,"msft",$Q$5:$Q$64,1,$P$5:$P$64,2028) -> 0 | J68: =Players!J36-SUMIFS($L$5:$L$64,$C$5:$C$64,"msft",$Q$5:$Q$64,1,$P$5:$P$64,2029) -> 0 | K68: =Players!K36-SUMIFS($L$5:$L$64,$C$5:$C$64,"msft",$Q$5:$Q$64,1,$P$5:$P$64,2030) -> 0 | L68: =Players!L36-SUMIFS($L$5:$L$64,$C$5:$C$64,"msft",$Q$5:$Q$64,1,$P$5:$P$64,2031) -> 0 | M68: =Players!M36-SUMIFS($L$5:$L$64,$C$5:$C$64,"msft",$Q$5:$Q$64,1,$P$5:$P$64,2032) -> 0
A69: Alphabet（Google；TPU＋NVIDIA） | B69: googl | C69: 殘差合計 | E69: =Players!E55-SUMIFS($L$5:$L$64,$C$5:$C$64,"googl",$Q$5:$Q$64,1,$P$5:$P$64,2024) -> 1.3298083 | F69: =Players!F55-SUMIFS($L$5:$L$64,$C$5:$C$64,"googl",$Q$5:$Q$64,1,$P$5:$P$64,2025) -> 2.4096133 | G69: =Players!G55-SUMIFS($L$5:$L$64,$C$5:$C$64,"googl",$Q$5:$Q$64,1,$P$5:$P$64,2026) -> 1.2926791 | H69: =Players!H55-SUMIFS($L$5:$L$64,$C$5:$C$64,"googl",$Q$5:$Q$64,1,$P$5:$P$64,2027) -> 0 | I69: =Players!I55-SUMIFS($L$5:$L$64,$C$5:$C$64,"googl",$Q$5:$Q$64,1,$P$5:$P$64,2028) -> 0 | J69: =Players!J55-SUMIFS($L$5:$L$64,$C$5:$C$64,"googl",$Q$5:$Q$64,1,$P$5:$P$64,2029) -> 0 | K69: =Players!K55-SUMIFS($L$5:$L$64,$C$5:$C$64,"googl",$Q$5:$Q$64,1,$P$5:$P$64,2030) -> 0 | L69: =Players!L55-SUMIFS($L$5:$L$64,$C$5:$C$64,"googl",$Q$5:$Q$64,1,$P$5:$P$64,2031) -> 0 | M69: =Players!M55-SUMIFS($L$5:$L$64,$C$5:$C$64,"googl",$Q$5:$Q$64,1,$P$5:$P$64,2032) -> 0
A70: Amazon（AWS；Trainium＋NVIDIA） | B70: amzn | C70: 殘差合計 | E70: =Players!E74-SUMIFS($L$5:$L$64,$C$5:$C$64,"amzn",$Q$5:$Q$64,1,$P$5:$P$64,2024) -> 0 | F70: =Players!F74-SUMIFS($L$5:$L$64,$C$5:$C$64,"amzn",$Q$5:$Q$64,1,$P$5:$P$64,2025) -> 1.389716 | G70: =Players!G74-SUMIFS($L$5:$L$64,$C$5:$C$64,"amzn",$Q$5:$Q$64,1,$P$5:$P$64,2026) -> 0.4 | H70: =Players!H74-SUMIFS($L$5:$L$64,$C$5:$C$64,"amzn",$Q$5:$Q$64,1,$P$5:$P$64,2027) -> 0 | I70: =Players!I74-SUMIFS($L$5:$L$64,$C$5:$C$64,"amzn",$Q$5:$Q$64,1,$P$5:$P$64,2028) -> 0 | J70: =Players!J74-SUMIFS($L$5:$L$64,$C$5:$C$64,"amzn",$Q$5:$Q$64,1,$P$5:$P$64,2029) -> 2.7755576e-16 | K70: =Players!K74-SUMIFS($L$5:$L$64,$C$5:$C$64,"amzn",$Q$5:$Q$64,1,$P$5:$P$64,2030) -> 0 | L70: =Players!L74-SUMIFS($L$5:$L$64,$C$5:$C$64,"amzn",$Q$5:$Q$64,1,$P$5:$P$64,2031) -> 0 | M70: =Players!M74-SUMIFS($L$5:$L$64,$C$5:$C$64,"amzn",$Q$5:$Q$64,1,$P$5:$P$64,2032) -> 0
A71: Meta | B71: meta | C71: 殘差合計 | E71: =Players!E93-SUMIFS($L$5:$L$64,$C$5:$C$64,"meta",$Q$5:$Q$64,1,$P$5:$P$64,2024) -> 0 | F71: =Players!F93-SUMIFS($L$5:$L$64,$C$5:$C$64,"meta",$Q$5:$Q$64,1,$P$5:$P$64,2025) -> 1.50812 | G71: =Players!G93-SUMIFS($L$5:$L$64,$C$5:$C$64,"meta",$Q$5:$Q$64,1,$P$5:$P$64,2026) -> 0 | H71: =Players!H93-SUMIFS($L$5:$L$64,$C$5:$C$64,"meta",$Q$5:$Q$64,1,$P$5:$P$64,2027) -> 0 | I71: =Players!I93-SUMIFS($L$5:$L$64,$C$5:$C$64,"meta",$Q$5:$Q$64,1,$P$5:$P$64,2028) -> 0 | J71: =Players!J93-SUMIFS($L$5:$L$64,$C$5:$C$64,"meta",$Q$5:$Q$64,1,$P$5:$P$64,2029) -> 0 | K71: =Players!K93-SUMIFS($L$5:$L$64,$C$5:$C$64,"meta",$Q$5:$Q$64,1,$P$5:$P$64,2030) -> 0 | L71: =Players!L93-SUMIFS($L$5:$L$64,$C$5:$C$64,"meta",$Q$5:$Q$64,1,$P$5:$P$64,2031) -> 0 | M71: =Players!M93-SUMIFS($L$5:$L$64,$C$5:$C$64,"meta",$Q$5:$Q$64,1,$P$5:$P$64,2032) -> 0
A72: Oracle（OCI；含承租 Stargate 站點） | B72: orcl | C72: 殘差合計 | E72: =Players!E112-SUMIFS($L$5:$L$64,$C$5:$C$64,"orcl",$Q$5:$Q$64,1,$P$5:$P$64,2024) -> 0 | F72: =Players!F112-SUMIFS($L$5:$L$64,$C$5:$C$64,"orcl",$Q$5:$Q$64,1,$P$5:$P$64,2025) -> 0.816405 | G72: =Players!G112-SUMIFS($L$5:$L$64,$C$5:$C$64,"orcl",$Q$5:$Q$64,1,$P$5:$P$64,2026) -> 1.34013 | H72: =Players!H112-SUMIFS($L$5:$L$64,$C$5:$C$64,"orcl",$Q$5:$Q$64,1,$P$5:$P$64,2027) -> 0 | I72: =Players!I112-SUMIFS($L$5:$L$64,$C$5:$C$64,"orcl",$Q$5:$Q$64,1,$P$5:$P$64,2028) -> 0 | J72: =Players!J112-SUMIFS($L$5:$L$64,$C$5:$C$64,"orcl",$Q$5:$Q$64,1,$P$5:$P$64,2029) -> 0 | K72: =Players!K112-SUMIFS($L$5:$L$64,$C$5:$C$64,"orcl",$Q$5:$Q$64,1,$P$5:$P$64,2030) -> 0 | L72: =Players!L112-SUMIFS($L$5:$L$64,$C$5:$C$64,"orcl",$Q$5:$Q$64,1,$P$5:$P$64,2031) -> 0 | M72: =Players!M112-SUMIFS($L$5:$L$64,$C$5:$C$64,"orcl",$Q$5:$Q$64,1,$P$5:$P$64,2032) -> 0
A73: CoreWeave | B73: crwv | C73: 殘差合計 | E73: =Players!E131-SUMIFS($L$5:$L$64,$C$5:$C$64,"crwv",$Q$5:$Q$64,1,$P$5:$P$64,2024) -> 0.29 | F73: =Players!F131-SUMIFS($L$5:$L$64,$C$5:$C$64,"crwv",$Q$5:$Q$64,1,$P$5:$P$64,2025) -> 0.49 | G73: =Players!G131-SUMIFS($L$5:$L$64,$C$5:$C$64,"crwv",$Q$5:$Q$64,1,$P$5:$P$64,2026) -> 1 | H73: =Players!H131-SUMIFS($L$5:$L$64,$C$5:$C$64,"crwv",$Q$5:$Q$64,1,$P$5:$P$64,2027) -> 1.2775 | I73: =Players!I131-SUMIFS($L$5:$L$64,$C$5:$C$64,"crwv",$Q$5:$Q$64,1,$P$5:$P$64,2028) -> 1.5375 | J73: =Players!J131-SUMIFS($L$5:$L$64,$C$5:$C$64,"crwv",$Q$5:$Q$64,1,$P$5:$P$64,2029) -> 1.5375 | K73: =Players!K131-SUMIFS($L$5:$L$64,$C$5:$C$64,"crwv",$Q$5:$Q$64,1,$P$5:$P$64,2030) -> 1.5375 | L73: =Players!L131-SUMIFS($L$5:$L$64,$C$5:$C$64,"crwv",$Q$5:$Q$64,1,$P$5:$P$64,2031) -> 0 | M73: =Players!M131-SUMIFS($L$5:$L$64,$C$5:$C$64,"crwv",$Q$5:$Q$64,1,$P$5:$P$64,2032) -> 0
A74: Nebius | B74: nbis | C74: 殘差合計 | E74: =Players!E150-SUMIFS($L$5:$L$64,$C$5:$C$64,"nbis",$Q$5:$Q$64,1,$P$5:$P$64,2024) -> 0 | F74: =Players!F150-SUMIFS($L$5:$L$64,$C$5:$C$64,"nbis",$Q$5:$Q$64,1,$P$5:$P$64,2025) -> 0 | G74: =Players!G150-SUMIFS($L$5:$L$64,$C$5:$C$64,"nbis",$Q$5:$Q$64,1,$P$5:$P$64,2026) -> 0.73 | H74: =Players!H150-SUMIFS($L$5:$L$64,$C$5:$C$64,"nbis",$Q$5:$Q$64,1,$P$5:$P$64,2027) -> 0 | I74: =Players!I150-SUMIFS($L$5:$L$64,$C$5:$C$64,"nbis",$Q$5:$Q$64,1,$P$5:$P$64,2028) -> 0 | J74: =Players!J150-SUMIFS($L$5:$L$64,$C$5:$C$64,"nbis",$Q$5:$Q$64,1,$P$5:$P$64,2029) -> 0 | K74: =Players!K150-SUMIFS($L$5:$L$64,$C$5:$C$64,"nbis",$Q$5:$Q$64,1,$P$5:$P$64,2030) -> 0 | L74: =Players!L150-SUMIFS($L$5:$L$64,$C$5:$C$64,"nbis",$Q$5:$Q$64,1,$P$5:$P$64,2031) -> 0 | M74: =Players!M150-SUMIFS($L$5:$L$64,$C$5:$C$64,"nbis",$Q$5:$Q$64,1,$P$5:$P$64,2032) -> 0
A75: WhiteFiber（雲端） | B75: wyfi | C75: 殘差合計 | E75: =Players!E169-SUMIFS($L$5:$L$64,$C$5:$C$64,"wyfi",$Q$5:$Q$64,1,$P$5:$P$64,2024) -> 0 | F75: =Players!F169-SUMIFS($L$5:$L$64,$C$5:$C$64,"wyfi",$Q$5:$Q$64,1,$P$5:$P$64,2025) -> 0 | G75: =Players!G169-SUMIFS($L$5:$L$64,$C$5:$C$64,"wyfi",$Q$5:$Q$64,1,$P$5:$P$64,2026) -> 0.009074 | H75: =Players!H169-SUMIFS($L$5:$L$64,$C$5:$C$64,"wyfi",$Q$5:$Q$64,1,$P$5:$P$64,2027) -> 0.001974 | I75: =Players!I169-SUMIFS($L$5:$L$64,$C$5:$C$64,"wyfi",$Q$5:$Q$64,1,$P$5:$P$64,2028) -> 0 | J75: =Players!J169-SUMIFS($L$5:$L$64,$C$5:$C$64,"wyfi",$Q$5:$Q$64,1,$P$5:$P$64,2029) -> 0 | K75: =Players!K169-SUMIFS($L$5:$L$64,$C$5:$C$64,"wyfi",$Q$5:$Q$64,1,$P$5:$P$64,2030) -> 0 | L75: =Players!L169-SUMIFS($L$5:$L$64,$C$5:$C$64,"wyfi",$Q$5:$Q$64,1,$P$5:$P$64,2031) -> 0 | M75: =Players!M169-SUMIFS($L$5:$L$64,$C$5:$C$64,"wyfi",$Q$5:$Q$64,1,$P$5:$P$64,2032) -> 0
A76: SpaceX／xAI（Colossus；兼出租） | B76: xai | C76: 殘差合計 | E76: =Players!E188-SUMIFS($L$5:$L$64,$C$5:$C$64,"xai",$Q$5:$Q$64,1,$P$5:$P$64,2024) -> 0 | F76: =Players!F188-SUMIFS($L$5:$L$64,$C$5:$C$64,"xai",$Q$5:$Q$64,1,$P$5:$P$64,2025) -> 0 | G76: =Players!G188-SUMIFS($L$5:$L$64,$C$5:$C$64,"xai",$Q$5:$Q$64,1,$P$5:$P$64,2026) -> 1.4302 | H76: =Players!H188-SUMIFS($L$5:$L$64,$C$5:$C$64,"xai",$Q$5:$Q$64,1,$P$5:$P$64,2027) -> 0 | I76: =Players!I188-SUMIFS($L$5:$L$64,$C$5:$C$64,"xai",$Q$5:$Q$64,1,$P$5:$P$64,2028) -> 0 | J76: =Players!J188-SUMIFS($L$5:$L$64,$C$5:$C$64,"xai",$Q$5:$Q$64,1,$P$5:$P$64,2029) -> 0 | K76: =Players!K188-SUMIFS($L$5:$L$64,$C$5:$C$64,"xai",$Q$5:$Q$64,1,$P$5:$P$64,2030) -> 0 | L76: =Players!L188-SUMIFS($L$5:$L$64,$C$5:$C$64,"xai",$Q$5:$Q$64,1,$P$5:$P$64,2031) -> 0 | M76: =Players!M188-SUMIFS($L$5:$L$64,$C$5:$C$64,"xai",$Q$5:$Q$64,1,$P$5:$P$64,2032) -> 0
A77: OpenAI／Stargate 自建（SoftBank、SB Energy 營運） | B77: oai | C77: 殘差合計 | E77: =Players!E207-SUMIFS($L$5:$L$64,$C$5:$C$64,"oai",$Q$5:$Q$64,1,$P$5:$P$64,2024) -> 0 | F77: =Players!F207-SUMIFS($L$5:$L$64,$C$5:$C$64,"oai",$Q$5:$Q$64,1,$P$5:$P$64,2025) -> 0 | G77: =Players!G207-SUMIFS($L$5:$L$64,$C$5:$C$64,"oai",$Q$5:$Q$64,1,$P$5:$P$64,2026) -> 0 | H77: =Players!H207-SUMIFS($L$5:$L$64,$C$5:$C$64,"oai",$Q$5:$Q$64,1,$P$5:$P$64,2027) -> 0 | I77: =Players!I207-SUMIFS($L$5:$L$64,$C$5:$C$64,"oai",$Q$5:$Q$64,1,$P$5:$P$64,2028) -> 0 | J77: =Players!J207-SUMIFS($L$5:$L$64,$C$5:$C$64,"oai",$Q$5:$Q$64,1,$P$5:$P$64,2029) -> 0 | K77: =Players!K207-SUMIFS($L$5:$L$64,$C$5:$C$64,"oai",$Q$5:$Q$64,1,$P$5:$P$64,2030) -> 0 | L77: =Players!L207-SUMIFS($L$5:$L$64,$C$5:$C$64,"oai",$Q$5:$Q$64,1,$P$5:$P$64,2031) -> 0 | M77: =Players!M207-SUMIFS($L$5:$L$64,$C$5:$C$64,"oai",$Q$5:$Q$64,1,$P$5:$P$64,2032) -> 0
A78: Anthropic 自建 | B78: ant | C78: 殘差合計 | E78: =Players!E226-SUMIFS($L$5:$L$64,$C$5:$C$64,"ant",$Q$5:$Q$64,1,$P$5:$P$64,2024) -> 0 | F78: =Players!F226-SUMIFS($L$5:$L$64,$C$5:$C$64,"ant",$Q$5:$Q$64,1,$P$5:$P$64,2025) -> 0 | G78: =Players!G226-SUMIFS($L$5:$L$64,$C$5:$C$64,"ant",$Q$5:$Q$64,1,$P$5:$P$64,2026) -> 0 | H78: =Players!H226-SUMIFS($L$5:$L$64,$C$5:$C$64,"ant",$Q$5:$Q$64,1,$P$5:$P$64,2027) -> 0 | I78: =Players!I226-SUMIFS($L$5:$L$64,$C$5:$C$64,"ant",$Q$5:$Q$64,1,$P$5:$P$64,2028) -> 0 | J78: =Players!J226-SUMIFS($L$5:$L$64,$C$5:$C$64,"ant",$Q$5:$Q$64,1,$P$5:$P$64,2029) -> 0 | K78: =Players!K226-SUMIFS($L$5:$L$64,$C$5:$C$64,"ant",$Q$5:$Q$64,1,$P$5:$P$64,2030) -> 0 | L78: =Players!L226-SUMIFS($L$5:$L$64,$C$5:$C$64,"ant",$Q$5:$Q$64,1,$P$5:$P$64,2031) -> 0 | M78: =Players!M226-SUMIFS($L$5:$L$64,$C$5:$C$64,"ant",$Q$5:$Q$64,1,$P$5:$P$64,2032) -> 0
A79: 其他新雲合計（IREN、TeraWulf、Lambda、Nscale、Crusoe 雲等） | B79: neo | C79: 殘差合計 | E79: =Players!E245-SUMIFS($L$5:$L$64,$C$5:$C$64,"neo",$Q$5:$Q$64,1,$P$5:$P$64,2024) -> 0 | F79: =Players!F245-SUMIFS($L$5:$L$64,$C$5:$C$64,"neo",$Q$5:$Q$64,1,$P$5:$P$64,2025) -> 0.3 | G79: =Players!G245-SUMIFS($L$5:$L$64,$C$5:$C$64,"neo",$Q$5:$Q$64,1,$P$5:$P$64,2026) -> 0.7 | H79: =Players!H245-SUMIFS($L$5:$L$64,$C$5:$C$64,"neo",$Q$5:$Q$64,1,$P$5:$P$64,2027) -> 0 | I79: =Players!I245-SUMIFS($L$5:$L$64,$C$5:$C$64,"neo",$Q$5:$Q$64,1,$P$5:$P$64,2028) -> 0 | J79: =Players!J245-SUMIFS($L$5:$L$64,$C$5:$C$64,"neo",$Q$5:$Q$64,1,$P$5:$P$64,2029) -> 0 | K79: =Players!K245-SUMIFS($L$5:$L$64,$C$5:$C$64,"neo",$Q$5:$Q$64,1,$P$5:$P$64,2030) -> 0 | L79: =Players!L245-SUMIFS($L$5:$L$64,$C$5:$C$64,"neo",$Q$5:$Q$64,1,$P$5:$P$64,2031) -> 0 | M79: =Players!M245-SUMIFS($L$5:$L$64,$C$5:$C$64,"neo",$Q$5:$Q$64,1,$P$5:$P$64,2032) -> 0
A80: 主權 AI（中國以外；v0.1 只含 Humain） | B80: sov | C80: 殘差合計 | E80: =Players!E264-SUMIFS($L$5:$L$64,$C$5:$C$64,"sov",$Q$5:$Q$64,1,$P$5:$P$64,2024) -> 0 | F80: =Players!F264-SUMIFS($L$5:$L$64,$C$5:$C$64,"sov",$Q$5:$Q$64,1,$P$5:$P$64,2025) -> 0 | G80: =Players!G264-SUMIFS($L$5:$L$64,$C$5:$C$64,"sov",$Q$5:$Q$64,1,$P$5:$P$64,2026) -> 0 | H80: =Players!H264-SUMIFS($L$5:$L$64,$C$5:$C$64,"sov",$Q$5:$Q$64,1,$P$5:$P$64,2027) -> 0 | I80: =Players!I264-SUMIFS($L$5:$L$64,$C$5:$C$64,"sov",$Q$5:$Q$64,1,$P$5:$P$64,2028) -> 0 | J80: =Players!J264-SUMIFS($L$5:$L$64,$C$5:$C$64,"sov",$Q$5:$Q$64,1,$P$5:$P$64,2029) -> 0 | K80: =Players!K264-SUMIFS($L$5:$L$64,$C$5:$C$64,"sov",$Q$5:$Q$64,1,$P$5:$P$64,2030) -> 0 | L80: =Players!L264-SUMIFS($L$5:$L$64,$C$5:$C$64,"sov",$Q$5:$Q$64,1,$P$5:$P$64,2031) -> 0 | M80: =Players!M264-SUMIFS($L$5:$L$64,$C$5:$C$64,"sov",$Q$5:$Q$64,1,$P$5:$P$64,2032) -> 0
A81: 中國合計（AI；Rystad 容量 × AI 占比） | B81: cn | C81: 殘差合計 | E81: =Players!E283-SUMIFS($L$5:$L$64,$C$5:$C$64,"cn",$Q$5:$Q$64,1,$P$5:$P$64,2024) -> 0 | F81: =Players!F283-SUMIFS($L$5:$L$64,$C$5:$C$64,"cn",$Q$5:$Q$64,1,$P$5:$P$64,2025) -> 0 | G81: =Players!G283-SUMIFS($L$5:$L$64,$C$5:$C$64,"cn",$Q$5:$Q$64,1,$P$5:$P$64,2026) -> 3.3333333 | H81: =Players!H283-SUMIFS($L$5:$L$64,$C$5:$C$64,"cn",$Q$5:$Q$64,1,$P$5:$P$64,2027) -> 1.9895045 | I81: =Players!I283-SUMIFS($L$5:$L$64,$C$5:$C$64,"cn",$Q$5:$Q$64,1,$P$5:$P$64,2028) -> 2.2812141 | J81: =Players!J283-SUMIFS($L$5:$L$64,$C$5:$C$64,"cn",$Q$5:$Q$64,1,$P$5:$P$64,2029) -> 2.6125213 | K81: =Players!K283-SUMIFS($L$5:$L$64,$C$5:$C$64,"cn",$Q$5:$Q$64,1,$P$5:$P$64,2030) -> 2.988555 | L81: =Players!L283-SUMIFS($L$5:$L$64,$C$5:$C$64,"cn",$Q$5:$Q$64,1,$P$5:$P$64,2031) -> 2.1538462 | M81: =Players!M283-SUMIFS($L$5:$L$64,$C$5:$C$64,"cn",$Q$5:$Q$64,1,$P$5:$P$64,2032) -> 2.3692308
A82: 其他（主權、企業、學研；Epoch Other 扣新雲） | B82: oth | C82: 殘差合計 | E82: =Players!E302-SUMIFS($L$5:$L$64,$C$5:$C$64,"oth",$Q$5:$Q$64,1,$P$5:$P$64,2024) -> 0 | F82: =Players!F302-SUMIFS($L$5:$L$64,$C$5:$C$64,"oth",$Q$5:$Q$64,1,$P$5:$P$64,2025) -> 0 | G82: =Players!G302-SUMIFS($L$5:$L$64,$C$5:$C$64,"oth",$Q$5:$Q$64,1,$P$5:$P$64,2026) -> 0 | H82: =Players!H302-SUMIFS($L$5:$L$64,$C$5:$C$64,"oth",$Q$5:$Q$64,1,$P$5:$P$64,2027) -> 0 | I82: =Players!I302-SUMIFS($L$5:$L$64,$C$5:$C$64,"oth",$Q$5:$Q$64,1,$P$5:$P$64,2028) -> 0 | J82: =Players!J302-SUMIFS($L$5:$L$64,$C$5:$C$64,"oth",$Q$5:$Q$64,1,$P$5:$P$64,2029) -> 0 | K82: =Players!K302-SUMIFS($L$5:$L$64,$C$5:$C$64,"oth",$Q$5:$Q$64,1,$P$5:$P$64,2030) -> 0 | L82: =Players!L302-SUMIFS($L$5:$L$64,$C$5:$C$64,"oth",$Q$5:$Q$64,1,$P$5:$P$64,2031) -> 0 | M82: =Players!M302-SUMIFS($L$5:$L$64,$C$5:$C$64,"oth",$Q$5:$Q$64,1,$P$5:$P$64,2032) -> 0
A84: Microsoft（自有＋融資租賃 AI 在役） | B84: msft | C84: 觀測型（不延遲） | E84: =IF(Players!E31=2,E68,0) -> 0 | F84: =IF(Players!F31=2,F68,0) -> 0 | G84: =IF(Players!G31=2,G68,0) -> 0.086955 | H84: =IF(Players!H31=2,H68,0) -> 0 | I84: =IF(Players!I31=2,I68,0) -> 0 | J84: =IF(Players!J31=2,J68,0) -> 0 | K84: =IF(Players!K31=2,K68,0) -> 0 | L84: =IF(Players!L31=2,L68,0) -> 0 | M84: =IF(Players!M31=2,M68,0) -> 0
A85: Alphabet（Google；TPU＋NVIDIA） | B85: googl | C85: 觀測型（不延遲） | E85: =IF(Players!E50=2,E69,0) -> 0 | F85: =IF(Players!F50=2,F69,0) -> 0 | G85: =IF(Players!G50=2,G69,0) -> 1.2926791 | H85: =IF(Players!H50=2,H69,0) -> 0 | I85: =IF(Players!I50=2,I69,0) -> 0 | J85: =IF(Players!J50=2,J69,0) -> 0 | K85: =IF(Players!K50=2,K69,0) -> 0 | L85: =IF(Players!L50=2,L69,0) -> 0 | M85: =IF(Players!M50=2,M69,0) -> 0
A86: Amazon（AWS；Trainium＋NVIDIA） | B86: amzn | C86: 觀測型（不延遲） | E86: =IF(Players!E69=2,E70,0) -> 0 | F86: =IF(Players!F69=2,F70,0) -> 0 | G86: =IF(Players!G69=2,G70,0) -> 0.4 | H86: =IF(Players!H69=2,H70,0) -> 0 | I86: =IF(Players!I69=2,I70,0) -> 0 | J86: =IF(Players!J69=2,J70,0) -> 0 | K86: =IF(Players!K69=2,K70,0) -> 0 | L86: =IF(Players!L69=2,L70,0) -> 0 | M86: =IF(Players!M69=2,M70,0) -> 0
A87: Meta | B87: meta | C87: 觀測型（不延遲） | E87: =IF(Players!E88=2,E71,0) -> 0 | F87: =IF(Players!F88=2,F71,0) -> 0 | G87: =IF(Players!G88=2,G71,0) -> 0 | H87: =IF(Players!H88=2,H71,0) -> 0 | I87: =IF(Players!I88=2,I71,0) -> 0 | J87: =IF(Players!J88=2,J71,0) -> 0 | K87: =IF(Players!K88=2,K71,0) -> 0 | L87: =IF(Players!L88=2,L71,0) -> 0 | M87: =IF(Players!M88=2,M71,0) -> 0
A88: Oracle（OCI；含承租 Stargate 站點） | B88: orcl | C88: 觀測型（不延遲） | E88: =IF(Players!E107=2,E72,0) -> 0 | F88: =IF(Players!F107=2,F72,0) -> 0 | G88: =IF(Players!G107=2,G72,0) -> 1.34013 | H88: =IF(Players!H107=2,H72,0) -> 0 | I88: =IF(Players!I107=2,I72,0) -> 0 | J88: =IF(Players!J107=2,J72,0) -> 0 | K88: =IF(Players!K107=2,K72,0) -> 0 | L88: =IF(Players!L107=2,L72,0) -> 0 | M88: =IF(Players!M107=2,M72,0) -> 0
A89: CoreWeave | B89: crwv | C89: 觀測型（不延遲） | E89: =IF(Players!E126=2,E73,0) -> 0 | F89: =IF(Players!F126=2,F73,0) -> 0 | G89: =IF(Players!G126=2,G73,0) -> 0 | H89: =IF(Players!H126=2,H73,0) -> 0 | I89: =IF(Players!I126=2,I73,0) -> 0 | J89: =IF(Players!J126=2,J73,0) -> 0 | K89: =IF(Players!K126=2,K73,0) -> 0 | L89: =IF(Players!L126=2,L73,0) -> 0 | M89: =IF(Players!M126=2,M73,0) -> 0
A90: Nebius | B90: nbis | C90: 觀測型（不延遲） | E90: =IF(Players!E145=2,E74,0) -> 0 | F90: =IF(Players!F145=2,F74,0) -> 0 | G90: =IF(Players!G145=2,G74,0) -> 0 | H90: =IF(Players!H145=2,H74,0) -> 0 | I90: =IF(Players!I145=2,I74,0) -> 0 | J90: =IF(Players!J145=2,J74,0) -> 0 | K90: =IF(Players!K145=2,K74,0) -> 0 | L90: =IF(Players!L145=2,L74,0) -> 0 | M90: =IF(Players!M145=2,M74,0) -> 0
A91: WhiteFiber（雲端） | B91: wyfi | C91: 觀測型（不延遲） | E91: =IF(Players!E164=2,E75,0) -> 0 | F91: =IF(Players!F164=2,F75,0) -> 0 | G91: =IF(Players!G164=2,G75,0) -> 0 | H91: =IF(Players!H164=2,H75,0) -> 0 | I91: =IF(Players!I164=2,I75,0) -> 0 | J91: =IF(Players!J164=2,J75,0) -> 0 | K91: =IF(Players!K164=2,K75,0) -> 0 | L91: =IF(Players!L164=2,L75,0) -> 0 | M91: =IF(Players!M164=2,M75,0) -> 0
A92: SpaceX／xAI（Colossus；兼出租） | B92: xai | C92: 觀測型（不延遲） | E92: =IF(Players!E183=2,E76,0) -> 0 | F92: =IF(Players!F183=2,F76,0) -> 0 | G92: =IF(Players!G183=2,G76,0) -> 0 | H92: =IF(Players!H183=2,H76,0) -> 0 | I92: =IF(Players!I183=2,I76,0) -> 0 | J92: =IF(Players!J183=2,J76,0) -> 0 | K92: =IF(Players!K183=2,K76,0) -> 0 | L92: =IF(Players!L183=2,L76,0) -> 0 | M92: =IF(Players!M183=2,M76,0) -> 0
A93: OpenAI／Stargate 自建（SoftBank、SB Energy 營運） | B93: oai | C93: 觀測型（不延遲） | E93: =IF(Players!E202=2,E77,0) -> 0 | F93: =IF(Players!F202=2,F77,0) -> 0 | G93: =IF(Players!G202=2,G77,0) -> 0 | H93: =IF(Players!H202=2,H77,0) -> 0 | I93: =IF(Players!I202=2,I77,0) -> 0 | J93: =IF(Players!J202=2,J77,0) -> 0 | K93: =IF(Players!K202=2,K77,0) -> 0 | L93: =IF(Players!L202=2,L77,0) -> 0 | M93: =IF(Players!M202=2,M77,0) -> 0
A94: Anthropic 自建 | B94: ant | C94: 觀測型（不延遲） | E94: =IF(Players!E221=2,E78,0) -> 0 | F94: =IF(Players!F221=2,F78,0) -> 0 | G94: =IF(Players!G221=2,G78,0) -> 0 | H94: =IF(Players!H221=2,H78,0) -> 0 | I94: =IF(Players!I221=2,I78,0) -> 0 | J94: =IF(Players!J221=2,J78,0) -> 0 | K94: =IF(Players!K221=2,K78,0) -> 0 | L94: =IF(Players!L221=2,L78,0) -> 0 | M94: =IF(Players!M221=2,M78,0) -> 0
A95: 其他新雲合計（IREN、TeraWulf、Lambda、Nscale、Crusoe 雲等） | B95: neo | C95: 觀測型（不延遲） | E95: =IF(Players!E240=2,E79,0) -> 0 | F95: =IF(Players!F240=2,F79,0) -> 0 | G95: =IF(Players!G240=2,G79,0) -> 0 | H95: =IF(Players!H240=2,H79,0) -> 0 | I95: =IF(Players!I240=2,I79,0) -> 0 | J95: =IF(Players!J240=2,J79,0) -> 0 | K95: =IF(Players!K240=2,K79,0) -> 0 | L95: =IF(Players!L240=2,L79,0) -> 0 | M95: =IF(Players!M240=2,M79,0) -> 0
A96: 主權 AI（中國以外；v0.1 只含 Humain） | B96: sov | C96: 觀測型（不延遲） | E96: =IF(Players!E259=2,E80,0) -> 0 | F96: =IF(Players!F259=2,F80,0) -> 0 | G96: =IF(Players!G259=2,G80,0) -> 0 | H96: =IF(Players!H259=2,H80,0) -> 0 | I96: =IF(Players!I259=2,I80,0) -> 0 | J96: =IF(Players!J259=2,J80,0) -> 0 | K96: =IF(Players!K259=2,K80,0) -> 0 | L96: =IF(Players!L259=2,L80,0) -> 0 | M96: =IF(Players!M259=2,M80,0) -> 0
A97: 中國合計（AI；Rystad 容量 × AI 占比） | B97: cn | C97: 觀測型（不延遲） | E97: =IF(Players!E278=2,E81,0) -> 0 | F97: =IF(Players!F278=2,F81,0) -> 0 | G97: =IF(Players!G278=2,G81,0) -> 0 | H97: =IF(Players!H278=2,H81,0) -> 0 | I97: =IF(Players!I278=2,I81,0) -> 0 | J97: =IF(Players!J278=2,J81,0) -> 0 | K97: =IF(Players!K278=2,K81,0) -> 0 | L97: =IF(Players!L278=2,L81,0) -> 0 | M97: =IF(Players!M278=2,M81,0) -> 0
A98: 其他（主權、企業、學研；Epoch Other 扣新雲） | B98: oth | C98: 觀測型（不延遲） | E98: =IF(Players!E297=2,E82,0) -> 0 | F98: =IF(Players!F297=2,F82,0) -> 0 | G98: =IF(Players!G297=2,G82,0) -> 0 | H98: =IF(Players!H297=2,H82,0) -> 0 | I98: =IF(Players!I297=2,I82,0) -> 0 | J98: =IF(Players!J297=2,J82,0) -> 0 | K98: =IF(Players!K297=2,K82,0) -> 0 | L98: =IF(Players!L297=2,L82,0) -> 0 | M98: =IF(Players!M297=2,M82,0) -> 0
A100: Microsoft（自有＋融資租賃 AI 在役） | B100: msft | C100: 均勻型（延遲適用） | E100: =E68-E84 -> 0 | F100: =F68-F84 -> 1.81427 | G100: =G68-G84 -> 0 | H100: =H68-H84 -> 0 | I100: =I68-I84 -> 0 | J100: =J68-J84 -> 0 | K100: =K68-K84 -> 0 | L100: =L68-L84 -> 0 | M100: =M68-M84 -> 0
A101: Alphabet（Google；TPU＋NVIDIA） | B101: googl | C101: 均勻型（延遲適用） | E101: =E69-E85 -> 1.3298083 | F101: =F69-F85 -> 2.4096133 | G101: =G69-G85 -> 0 | H101: =H69-H85 -> 0 | I101: =I69-I85 -> 0 | J101: =J69-J85 -> 0 | K101: =K69-K85 -> 0 | L101: =L69-L85 -> 0 | M101: =M69-M85 -> 0
A102: Amazon（AWS；Trainium＋NVIDIA） | B102: amzn | C102: 均勻型（延遲適用） | E102: =E70-E86 -> 0 | F102: =F70-F86 -> 1.389716 | G102: =G70-G86 -> 0 | H102: =H70-H86 -> 0 | I102: =I70-I86 -> 0 | J102: =J70-J86 -> 2.7755576e-16 | K102: =K70-K86 -> 0 | L102: =L70-L86 -> 0 | M102: =M70-M86 -> 0
A103: Meta | B103: meta | C103: 均勻型（延遲適用） | E103: =E71-E87 -> 0 | F103: =F71-F87 -> 1.50812 | G103: =G71-G87 -> 0 | H103: =H71-H87 -> 0 | I103: =I71-I87 -> 0 | J103: =J71-J87 -> 0 | K103: =K71-K87 -> 0 | L103: =L71-L87 -> 0 | M103: =M71-M87 -> 0
A104: Oracle（OCI；含承租 Stargate 站點） | B104: orcl | C104: 均勻型（延遲適用） | E104: =E72-E88 -> 0 | F104: =F72-F88 -> 0.816405 | G104: =G72-G88 -> 0 | H104: =H72-H88 -> 0 | I104: =I72-I88 -> 0 | J104: =J72-J88 -> 0 | K104: =K72-K88 -> 0 | L104: =L72-L88 -> 0 | M104: =M72-M88 -> 0
A105: CoreWeave | B105: crwv | C105: 均勻型（延遲適用） | E105: =E73-E89 -> 0.29 | F105: =F73-F89 -> 0.49 | G105: =G73-G89 -> 1 | H105: =H73-H89 -> 1.2775 | I105: =I73-I89 -> 1.5375 | J105: =J73-J89 -> 1.5375 | K105: =K73-K89 -> 1.5375 | L105: =L73-L89 -> 0 | M105: =M73-M89 -> 0
A106: Nebius | B106: nbis | C106: 均勻型（延遲適用） | E106: =E74-E90 -> 0 | F106: =F74-F90 -> 0 | G106: =G74-G90 -> 0.73 | H106: =H74-H90 -> 0 | I106: =I74-I90 -> 0 | J106: =J74-J90 -> 0 | K106: =K74-K90 -> 0 | L106: =L74-L90 -> 0 | M106: =M74-M90 -> 0
A107: WhiteFiber（雲端） | B107: wyfi | C107: 均勻型（延遲適用） | E107: =E75-E91 -> 0 | F107: =F75-F91 -> 0 | G107: =G75-G91 -> 0.009074 | H107: =H75-H91 -> 0.001974 | I107: =I75-I91 -> 0 | J107: =J75-J91 -> 0 | K107: =K75-K91 -> 0 | L107: =L75-L91 -> 0 | M107: =M75-M91 -> 0
A108: SpaceX／xAI（Colossus；兼出租） | B108: xai | C108: 均勻型（延遲適用） | E108: =E76-E92 -> 0 | F108: =F76-F92 -> 0 | G108: =G76-G92 -> 1.4302 | H108: =H76-H92 -> 0 | I108: =I76-I92 -> 0 | J108: =J76-J92 -> 0 | K108: =K76-K92 -> 0 | L108: =L76-L92 -> 0 | M108: =M76-M92 -> 0
A109: OpenAI／Stargate 自建（SoftBank、SB Energy 營運） | B109: oai | C109: 均勻型（延遲適用） | E109: =E77-E93 -> 0 | F109: =F77-F93 -> 0 | G109: =G77-G93 -> 0 | H109: =H77-H93 -> 0 | I109: =I77-I93 -> 0 | J109: =J77-J93 -> 0 | K109: =K77-K93 -> 0 | L109: =L77-L93 -> 0 | M109: =M77-M93 -> 0
A110: Anthropic 自建 | B110: ant | C110: 均勻型（延遲適用） | E110: =E78-E94 -> 0 | F110: =F78-F94 -> 0 | G110: =G78-G94 -> 0 | H110: =H78-H94 -> 0 | I110: =I78-I94 -> 0 | J110: =J78-J94 -> 0 | K110: =K78-K94 -> 0 | L110: =L78-L94 -> 0 | M110: =M78-M94 -> 0
A111: 其他新雲合計（IREN、TeraWulf、Lambda、Nscale、Crusoe 雲等） | B111: neo | C111: 均勻型（延遲適用） | E111: =E79-E95 -> 0 | F111: =F79-F95 -> 0.3 | G111: =G79-G95 -> 0.7 | H111: =H79-H95 -> 0 | I111: =I79-I95 -> 0 | J111: =J79-J95 -> 0 | K111: =K79-K95 -> 0 | L111: =L79-L95 -> 0 | M111: =M79-M95 -> 0
... A114: 其他（主權、企業、學研；Epoch Other 扣新雲） | B114: oth | C114: 均勻型（延遲適用） | E114: =E82-E98 -> 0 | F114: =F82-F98 -> 0 | G114: =G82-G98 -> 0 | H114: =H82-H98 -> 0 | I114: =I82-I98 -> 0 | J114: =J82-J98 -> 0 | K114: =K82-K98 -> 0 | L114: =L82-L98 -> 0 | M114: =M82-M98 -> 0
A116: 殘差合計 | D116: 0 | E116: =SUM(E68:E82) -> 1.6198083 | F116: =SUM(F68:F82) -> 8.7281243 | G116: =SUM(G68:G82) -> 10.322371 | H116: =SUM(H68:H82) -> 3.2689785 | I116: =SUM(I68:I82) -> 3.8187141 | J116: =SUM(J68:J82) -> 4.1500213 | K116: =SUM(K68:K82) -> 4.526055 | L116: =SUM(L68:L82) -> 2.1538462 | M116: =SUM(M68:M82) -> 2.3692308
A117: 觀測型殘差合計 | D117: 0 | E117: =SUM(E84:E98) -> 0 | F117: =SUM(F84:F98) -> 0 | G117: =SUM(G84:G98) -> 3.1197641 | H117: =SUM(H84:H98) -> 0 | I117: =SUM(I84:I98) -> 0 | J117: =SUM(J84:J98) -> 0 | K117: =SUM(K84:K98) -> 0 | L117: =SUM(L84:L98) -> 0 | M117: =SUM(M84:M98) -> 0
A118: 均勻型殘差合計 | D118: 0 | E118: =SUM(E100:E114) -> 1.6198083 | F118: =SUM(F100:F114) -> 8.7281243 | G118: =SUM(G100:G114) -> 7.2026073 | H118: =SUM(H100:H114) -> 3.2689785 | I118: =SUM(I100:I114) -> 3.8187141 | J118: =SUM(J100:J114) -> 4.1500213 | K118: =SUM(K100:K114) -> 4.526055 | L118: =SUM(L100:L114) -> 2.1538462 | M118: =SUM(M100:M114) -> 2.3692308
A119: 園區（D0 上線年）合計 | D119: =SUMIFS($L$5:$L$64,$Q$5:$Q$64,1,$P$5:$P$64,2023) -> 0 | E119: =SUMIFS($L$5:$L$64,$Q$5:$Q$64,1,$P$5:$P$64,2024) -> 0 | F119: =SUMIFS($L$5:$L$64,$Q$5:$Q$64,1,$P$5:$P$64,2025) -> 0.321 | G119: =SUMIFS($L$5:$L$64,$Q$5:$Q$64,1,$P$5:$P$64,2026) -> 2.193 | H119: =SUMIFS($L$5:$L$64,$Q$5:$Q$64,1,$P$5:$P$64,2027) -> 5.1996667 | I119: =SUMIFS($L$5:$L$64,$Q$5:$Q$64,1,$P$5:$P$64,2028) -> 14.569167 | J119: =SUMIFS($L$5:$L$64,$Q$5:$Q$64,1,$P$5:$P$64,2029) -> 1.579 | K119: =SUMIFS($L$5:$L$64,$Q$5:$Q$64,1,$P$5:$P$64,2030) -> 1.349 | L119: =SUMIFS($L$5:$L$64,$Q$5:$Q$64,1,$P$5:$P$64,2031) -> 1.15 | M119: =SUMIFS($L$5:$L$64,$Q$5:$Q$64,1,$P$5:$P$64,2032) -> 0
A120: 新納入存量（Players） | D120: =Players!D314 -> 0.63057836 | E120: =Players!E314 -> 3.958999 | F120: =Players!F314 -> 10.078633 | G120: =Players!G314 -> 0 | H120: =Players!H314 -> 0 | I120: =Players!I314 -> 0 | J120: =Players!J314 -> 0 | K120: =Players!K314 -> 0 | ... M120: =Players!M314 -> 0
A121: 殘差＋園區（須＝Players 年新增） | D121: =D116+D119 -> 0 | E121: =E116+E119 -> 1.6198083 | F121: =F116+F119 -> 9.0491243 | G121: =G116+G119 -> 12.515371 | H121: =H116+H119 -> 8.4686451 | I121: =I116+I119 -> 18.387881 | J121: =J116+J119 -> 5.7290213 | K121: =K116+K119 -> 5.875055 | ... M121: =M116+M119 -> 2.3692308
A123: C. 均勻型事件的年底上線比例矩陣（列＝年底 z，欄＝事件年 y；asof 前部分不延遲，asof 後部分依情景延後）
A124: 延遲情景 D0 | B124: 年底 z | E124: 2024 | F124: 2025 | G124: 2026 | H124: 2027 | I124: 2028 | J124: 2029 | K124: 2030 | L124: 2031 | M124: 2032
A125: D0：2023 年底 | B125: 2023 | E125: =MAX(0,MIN(2023+1,2024+MAX(0,MIN(1,asof-2024)))-2024)+MAX(0,MIN(2023+1,2024+1+0)-(MAX(2024,asof)+0)) -> 0 | F125: =MAX(0,MIN(2023+1,2025+MAX(0,MIN(1,asof-2025)))-2025)+MAX(0,MIN(2023+1,2025+1+0)-(MAX(2025,asof)+0)) -> 0 | G125: =MAX(0,MIN(2023+1,2026+MAX(0,MIN(1,asof-2026)))-2026)+MAX(0,MIN(2023+1,2026+1+0)-(MAX(2026,asof)+0)) -> 0 | H125: =MAX(0,MIN(2023+1,2027+MAX(0,MIN(1,asof-2027)))-2027)+MAX(0,MIN(2023+1,2027+1+0)-(MAX(2027,asof)+0)) -> 0 | I125: =MAX(0,MIN(2023+1,2028+MAX(0,MIN(1,asof-2028)))-2028)+MAX(0,MIN(2023+1,2028+1+0)-(MAX(2028,asof)+0)) -> 0 | J125: =MAX(0,MIN(2023+1,2029+MAX(0,MIN(1,asof-2029)))-2029)+MAX(0,MIN(2023+1,2029+1+0)-(MAX(2029,asof)+0)) -> 0 | K125: =MAX(0,MIN(2023+1,2030+MAX(0,MIN(1,asof-2030)))-2030)+MAX(0,MIN(2023+1,2030+1+0)-(MAX(2030,asof)+0)) -> 0 | L125: =MAX(0,MIN(2023+1,2031+MAX(0,MIN(1,asof-2031)))-2031)+MAX(0,MIN(2023+1,2031+1+0)-(MAX(2031,asof)+0)) -> 0 | M125: =MAX(0,MIN(2023+1,2032+MAX(0,MIN(1,asof-2032)))-2032)+MAX(0,MIN(2023+1,2032+1+0)-(MAX(2032,asof)+0)) -> 0
A126: D0：2024 年底 | B126: 2024 | E126: =MAX(0,MIN(2024+1,2024+MAX(0,MIN(1,asof-2024)))-2024)+MAX(0,MIN(2024+1,2024+1+0)-(MAX(2024,asof)+0)) -> 1 | F126: =MAX(0,MIN(2024+1,2025+MAX(0,MIN(1,asof-2025)))-2025)+MAX(0,MIN(2024+1,2025+1+0)-(MAX(2025,asof)+0)) -> 0 | G126: =MAX(0,MIN(2024+1,2026+MAX(0,MIN(1,asof-2026)))-2026)+MAX(0,MIN(2024+1,2026+1+0)-(MAX(2026,asof)+0)) -> 0 | H126: =MAX(0,MIN(2024+1,2027+MAX(0,MIN(1,asof-2027)))-2027)+MAX(0,MIN(2024+1,2027+1+0)-(MAX(2027,asof)+0)) -> 0 | I126: =MAX(0,MIN(2024+1,2028+MAX(0,MIN(1,asof-2028)))-2028)+MAX(0,MIN(2024+1,2028+1+0)-(MAX(2028,asof)+0)) -> 0 | J126: =MAX(0,MIN(2024+1,2029+MAX(0,MIN(1,asof-2029)))-2029)+MAX(0,MIN(2024+1,2029+1+0)-(MAX(2029,asof)+0)) -> 0 | K126: =MAX(0,MIN(2024+1,2030+MAX(0,MIN(1,asof-2030)))-2030)+MAX(0,MIN(2024+1,2030+1+0)-(MAX(2030,asof)+0)) -> 0 | L126: =MAX(0,MIN(2024+1,2031+MAX(0,MIN(1,asof-2031)))-2031)+MAX(0,MIN(2024+1,2031+1+0)-(MAX(2031,asof)+0)) -> 0 | M126: =MAX(0,MIN(2024+1,2032+MAX(0,MIN(1,asof-2032)))-2032)+MAX(0,MIN(2024+1,2032+1+0)-(MAX(2032,asof)+0)) -> 0
A127: D0：2025 年底 | B127: 2025 | E127: =MAX(0,MIN(2025+1,2024+MAX(0,MIN(1,asof-2024)))-2024)+MAX(0,MIN(2025+1,2024+1+0)-(MAX(2024,asof)+0)) -> 1 | F127: =MAX(0,MIN(2025+1,2025+MAX(0,MIN(1,asof-2025)))-2025)+MAX(0,MIN(2025+1,2025+1+0)-(MAX(2025,asof)+0)) -> 1 | G127: =MAX(0,MIN(2025+1,2026+MAX(0,MIN(1,asof-2026)))-2026)+MAX(0,MIN(2025+1,2026+1+0)-(MAX(2026,asof)+0)) -> 0 | H127: =MAX(0,MIN(2025+1,2027+MAX(0,MIN(1,asof-2027)))-2027)+MAX(0,MIN(2025+1,2027+1+0)-(MAX(2027,asof)+0)) -> 0 | I127: =MAX(0,MIN(2025+1,2028+MAX(0,MIN(1,asof-2028)))-2028)+MAX(0,MIN(2025+1,2028+1+0)-(MAX(2028,asof)+0)) -> 0 | J127: =MAX(0,MIN(2025+1,2029+MAX(0,MIN(1,asof-2029)))-2029)+MAX(0,MIN(2025+1,2029+1+0)-(MAX(2029,asof)+0)) -> 0 | K127: =MAX(0,MIN(2025+1,2030+MAX(0,MIN(1,asof-2030)))-2030)+MAX(0,MIN(2025+1,2030+1+0)-(MAX(2030,asof)+0)) -> 0 | L127: =MAX(0,MIN(2025+1,2031+MAX(0,MIN(1,asof-2031)))-2031)+MAX(0,MIN(2025+1,2031+1+0)-(MAX(2031,asof)+0)) -> 0 | M127: =MAX(0,MIN(2025+1,2032+MAX(0,MIN(1,asof-2032)))-2032)+MAX(0,MIN(2025+1,2032+1+0)-(MAX(2032,asof)+0)) -> 0
A128: D0：2026 年底 | B128: 2026 | E128: =MAX(0,MIN(2026+1,2024+MAX(0,MIN(1,asof-2024)))-2024)+MAX(0,MIN(2026+1,2024+1+0)-(MAX(2024,asof)+0)) -> 1 | F128: =MAX(0,MIN(2026+1,2025+MAX(0,MIN(1,asof-2025)))-2025)+MAX(0,MIN(2026+1,2025+1+0)-(MAX(2025,asof)+0)) -> 1 | G128: =MAX(0,MIN(2026+1,2026+MAX(0,MIN(1,asof-2026)))-2026)+MAX(0,MIN(2026+1,2026+1+0)-(MAX(2026,asof)+0)) -> 1 | H128: =MAX(0,MIN(2026+1,2027+MAX(0,MIN(1,asof-2027)))-2027)+MAX(0,MIN(2026+1,2027+1+0)-(MAX(2027,asof)+0)) -> 0 | I128: =MAX(0,MIN(2026+1,2028+MAX(0,MIN(1,asof-2028)))-2028)+MAX(0,MIN(2026+1,2028+1+0)-(MAX(2028,asof)+0)) -> 0 | J128: =MAX(0,MIN(2026+1,2029+MAX(0,MIN(1,asof-2029)))-2029)+MAX(0,MIN(2026+1,2029+1+0)-(MAX(2029,asof)+0)) -> 0 | K128: =MAX(0,MIN(2026+1,2030+MAX(0,MIN(1,asof-2030)))-2030)+MAX(0,MIN(2026+1,2030+1+0)-(MAX(2030,asof)+0)) -> 0 | L128: =MAX(0,MIN(2026+1,2031+MAX(0,MIN(1,asof-2031)))-2031)+MAX(0,MIN(2026+1,2031+1+0)-(MAX(2031,asof)+0)) -> 0 | M128: =MAX(0,MIN(2026+1,2032+MAX(0,MIN(1,asof-2032)))-2032)+MAX(0,MIN(2026+1,2032+1+0)-(MAX(2032,asof)+0)) -> 0
A129: D0：2027 年底 | B129: 2027 | E129: =MAX(0,MIN(2027+1,2024+MAX(0,MIN(1,asof-2024)))-2024)+MAX(0,MIN(2027+1,2024+1+0)-(MAX(2024,asof)+0)) -> 1 | F129: =MAX(0,MIN(2027+1,2025+MAX(0,MIN(1,asof-2025)))-2025)+MAX(0,MIN(2027+1,2025+1+0)-(MAX(2025,asof)+0)) -> 1 | G129: =MAX(0,MIN(2027+1,2026+MAX(0,MIN(1,asof-2026)))-2026)+MAX(0,MIN(2027+1,2026+1+0)-(MAX(2026,asof)+0)) -> 1 | H129: =MAX(0,MIN(2027+1,2027+MAX(0,MIN(1,asof-2027)))-2027)+MAX(0,MIN(2027+1,2027+1+0)-(MAX(2027,asof)+0)) -> 1 | I129: =MAX(0,MIN(2027+1,2028+MAX(0,MIN(1,asof-2028)))-2028)+MAX(0,MIN(2027+1,2028+1+0)-(MAX(2028,asof)+0)) -> 0 | J129: =MAX(0,MIN(2027+1,2029+MAX(0,MIN(1,asof-2029)))-2029)+MAX(0,MIN(2027+1,2029+1+0)-(MAX(2029,asof)+0)) -> 0 | K129: =MAX(0,MIN(2027+1,2030+MAX(0,MIN(1,asof-2030)))-2030)+MAX(0,MIN(2027+1,2030+1+0)-(MAX(2030,asof)+0)) -> 0 | L129: =MAX(0,MIN(2027+1,2031+MAX(0,MIN(1,asof-2031)))-2031)+MAX(0,MIN(2027+1,2031+1+0)-(MAX(2031,asof)+0)) -> 0 | M129: =MAX(0,MIN(2027+1,2032+MAX(0,MIN(1,asof-2032)))-2032)+MAX(0,MIN(2027+1,2032+1+0)-(MAX(2032,asof)+0)) -> 0
A130: D0：2028 年底 | B130: 2028 | E130: =MAX(0,MIN(2028+1,2024+MAX(0,MIN(1,asof-2024)))-2024)+MAX(0,MIN(2028+1,2024+1+0)-(MAX(2024,asof)+0)) -> 1 | F130: =MAX(0,MIN(2028+1,2025+MAX(0,MIN(1,asof-2025)))-2025)+MAX(0,MIN(2028+1,2025+1+0)-(MAX(2025,asof)+0)) -> 1 | G130: =MAX(0,MIN(2028+1,2026+MAX(0,MIN(1,asof-2026)))-2026)+MAX(0,MIN(2028+1,2026+1+0)-(MAX(2026,asof)+0)) -> 1 | H130: =MAX(0,MIN(2028+1,2027+MAX(0,MIN(1,asof-2027)))-2027)+MAX(0,MIN(2028+1,2027+1+0)-(MAX(2027,asof)+0)) -> 1 | I130: =MAX(0,MIN(2028+1,2028+MAX(0,MIN(1,asof-2028)))-2028)+MAX(0,MIN(2028+1,2028+1+0)-(MAX(2028,asof)+0)) -> 1 | J130: =MAX(0,MIN(2028+1,2029+MAX(0,MIN(1,asof-2029)))-2029)+MAX(0,MIN(2028+1,2029+1+0)-(MAX(2029,asof)+0)) -> 0 | K130: =MAX(0,MIN(2028+1,2030+MAX(0,MIN(1,asof-2030)))-2030)+MAX(0,MIN(2028+1,2030+1+0)-(MAX(2030,asof)+0)) -> 0 | L130: =MAX(0,MIN(2028+1,2031+MAX(0,MIN(1,asof-2031)))-2031)+MAX(0,MIN(2028+1,2031+1+0)-(MAX(2031,asof)+0)) -> 0 | M130: =MAX(0,MIN(2028+1,2032+MAX(0,MIN(1,asof-2032)))-2032)+MAX(0,MIN(2028+1,2032+1+0)-(MAX(2032,asof)+0)) -> 0
A131: D0：2029 年底 | B131: 2029 | E131: =MAX(0,MIN(2029+1,2024+MAX(0,MIN(1,asof-2024)))-2024)+MAX(0,MIN(2029+1,2024+1+0)-(MAX(2024,asof)+0)) -> 1 | F131: =MAX(0,MIN(2029+1,2025+MAX(0,MIN(1,asof-2025)))-2025)+MAX(0,MIN(2029+1,2025+1+0)-(MAX(2025,asof)+0)) -> 1 | G131: =MAX(0,MIN(2029+1,2026+MAX(0,MIN(1,asof-2026)))-2026)+MAX(0,MIN(2029+1,2026+1+0)-(MAX(2026,asof)+0)) -> 1 | H131: =MAX(0,MIN(2029+1,2027+MAX(0,MIN(1,asof-2027)))-2027)+MAX(0,MIN(2029+1,2027+1+0)-(MAX(2027,asof)+0)) -> 1 | I131: =MAX(0,MIN(2029+1,2028+MAX(0,MIN(1,asof-2028)))-2028)+MAX(0,MIN(2029+1,2028+1+0)-(MAX(2028,asof)+0)) -> 1 | J131: =MAX(0,MIN(2029+1,2029+MAX(0,MIN(1,asof-2029)))-2029)+MAX(0,MIN(2029+1,2029+1+0)-(MAX(2029,asof)+0)) -> 1 | K131: =MAX(0,MIN(2029+1,2030+MAX(0,MIN(1,asof-2030)))-2030)+MAX(0,MIN(2029+1,2030+1+0)-(MAX(2030,asof)+0)) -> 0 | L131: =MAX(0,MIN(2029+1,2031+MAX(0,MIN(1,asof-2031)))-2031)+MAX(0,MIN(2029+1,2031+1+0)-(MAX(2031,asof)+0)) -> 0 | M131: =MAX(0,MIN(2029+1,2032+MAX(0,MIN(1,asof-2032)))-2032)+MAX(0,MIN(2029+1,2032+1+0)-(MAX(2032,asof)+0)) -> 0
