Workbook

Sheet README
A1: NVIDIA（NVDA）收支與估值模型 v0.2（AI 半導體 Project：運算層第一個樣板） 2026-10-25
A2: v0.1.1（PR 審查後）：(1) 新增 NVIDIA 認列顆數係數 k_rec（Derived，只在本模型內縮放，不改 markets/memory 的共用顆數；營收與成本同比例縮放），使 FY2027 由下而上的 Data Center 營收與毛利率等於錨點，FY2028 起沿用；v0.1 的未校準基準保留在 PL 對照區塊與 Sens。(2) 原 pf_cal（只調售價）留在 Sens 當對照。(3) Recon 新增 B2「差額來源待查」。(4) Val：10 年落後 P/E 規則值標「不適用」（保留計算，不進結論）。
A3: 模型命題：NVIDIA 的營收＝加速器顆數 × 每顆售價＋網通附掛。2027 年 ASIC 把 NVIDIA 的金額份額壓到約 75–80%，HBM 漲價壓毛利 2–3 個百分點。股價取決於 2028 年顆數持平之後，EPS 還能不能成長：現價約為 2027 年 EPS 的 13.5 倍，是低估，還是見頂前的折價。
A4: 核心問題：加速器顆數在 2028 年持平以後，NVIDIA 的 EPS 還能不能成長。（命題的「2027 年」＝日曆年 2027＝FY2028；「2028 年顆數持平」＝CY2028＝FY2029，故問題是 FY2030 EPS 相對 FY2029。）
A6: 會計年度：FY(t)＝t−1 年 2 月～t 年 1 月，約等於日曆年 t−1（FY2027＝CY2026 … FY2030＝CY2029）。上游市場層是日曆年，FY(t) 直接取 CY(t−1)，不做跨年加權（11/12 落在同一日曆年）——這是近似。預測期 FY2027–FY2030。
A8: 驅動因子 → 推導量（全部唯讀上游，不修改）
A9: 各世代顆數（markets/memory UNITS × 情境係數）× 每顆售價（橋接表 Rack 頁：GPU 模組＋CPU＋LPDDR＋匣級加價中 NVIDIA 保留的部分；Rubin Ultra 為 Assumed 區間）→ 運算營收；＋網通附掛（markets/network 的「NVIDIA 網通（本模型歸屬）」列，B／C 依顆數係數縮放）＋Edge Computing（公司實績＋成長率）
A10: 毛利率：非 HBM 成本占基準售價的比例（c_nh）在 FY2027 校準到公司錨點毛利率；FY2028 起毛利率的變化來自 HBM 與 LPDDR 成本（markets/memory 的情境別價格路徑 × 每顆容量）、NVIDIA 吸收比例（In 頁 abs_mem，Assumed 0–1，基準 0.5）、世代與顆數組合。中國資料中心運算基準為 0（公司 Q3 FY27 指引假設），Sens 列恢復。
A11: EPS 口徑：GAAP 扣除權益證券損益（一次性），含股票薪酬；近似公司自 Q1 FY27 起的新 non-GAAP（含 SBC；Q 頁檢查列差 −0.03～−0.02）。營業費用、稅率、股數：公司實績（Q 頁）＋In 頁假設。
A12: 校準：FY2027 ＝ Q1、Q2 實績＋Q3 指引（$108B ±2%）＋Q4 假設。k_rec（Derived）＝錨點 Data Center 營收 ÷ 未校準的由下而上（市場層顆數 × 橋接表售價＋網通歸屬）；以已發生的實績校準，不用公司對 FY2028 的預測；顆數層與售價層無法分開識別，k_rec 是合併係數，FY2028 起沿用。c_nh 另讓 FY2027 毛利率等於錨點毛利率。驅動因子從 FY2028 起作用。公司指引（FY2028 營收約 +70%、毛利率 72–73%）與共識只在 Recon 對帳，不作校準。
A13: 估值：P/E 規則——FY2016–FY2025 年底 P/E 分位（見頂 25 分位、中段中位數、谷底 75 分位）；循環位置用 tools/cycle_position.py 的共用規則（lag 版：FY(t) 對照 CY t−1；見頂年度讀設備市場模型 A 2029、B 2028、C 2027 → FY2028：A 中段、B 中段、C 見頂）；另列以本模型營收路徑自己的見頂年判斷的對照欄（只作對照）。10 年落後 P/E 規則值標「不適用」（歷史倍數含高成長期溢價；保留計算，不進結論）；結論用現價 ÷ FY2028 EPS（模型與共識）。前瞻 P/E 歷史資料由擁有者另行提供，本版不做。
A15: 標記：Verified、Interested-party、Analogy、Assumed、Derived。SemiAnalysis 未單獨使用。公司原文＝8-K 新聞稿（nvidianews.nvidia.com，已抓取）；CFO 書面說明、10-Q、法說逐字稿無法開啟，相關數字只經搜尋摘要（標二手），原文待人工複核。
... A19: 情境對應（v0.2 延伸期）：A＝順利（基準顆數）、B＝平平（CY2028 顆數 ×0.8、CY2029 ×0.85）、C＝不如預期（CY2028–29 ×0.6）。三情境在 FY2027 相同、FY2028 幾乎相同（只差 LPDDR 成本），DCF 的情境差異主要來自 FY2029 之後。本版未做先驗，無 Andy 合理 P/E 對照。

Sheet In
A1: In — 輸入（藍字；基準欄 E，低 D、高 F）。金額：十億美元（US$B）；每顆價格：千美元（US$K）；顆數：百萬顆。每個輸入附兩個來源（找不到者寫「未找到」）；公司原文算一個
A2: 標記：Verified／Interested-party／Analogy／Assumed／Derived；Analogy、Assumed 給低／高區間。SemiAnalysis 未單獨使用。公司原文＝NVIDIA 8-K 新聞稿（nvidianews.nvidia.com）；CFO 書面說明與 10-Q 在建置環境無法開啟，標「未找到」
A3: 鍵 | B3: 項目 | C3: 單位 | D3: 低 | E3: 基準 | F3: 高 | G3: 標記 | H3: 來源1 | I3: 來源2／說明
A4: A. 加速器顆數（markets/memory 與 HBM、台積電、網通模型同一份；情境係數讀台積電模型成品，不另訂）
A5: u_bw_26 | B5: NVIDIA Blackwell（B200／B300） 顆數 2026 | C5: 百萬顆 | E5: 5.4 | G5: Interested-party | H5: markets/memory/market.py UNITS：顆數：Morgan Stanley 2026-07（2026 5.4M）；AC Research 2027 約 2.4M；2028 Assumed。GB：B200 186、B300 288 組合 [Derived] | I5: 台積電模型 tsmc/dist/20261025_台積電模型_v0.3.xlsx｜In!E5（值相同，建置時檢查）
A6: u_bw_27 | B6: NVIDIA Blackwell（B200／B300） 顆數 2027 | C6: 百萬顆 | E6: 2.4 | G6: Interested-party | H6: 同上 | I6: 同上
A7: u_bw_28 | B7: NVIDIA Blackwell（B200／B300） 顆數 2028 | C7: 百萬顆 | E7: 0.5 | G7: Interested-party | H7: 同上 | I7: 同上
A8: g29_bw | B8: NVIDIA Blackwell（B200／B300） 2029 顆數成長 | C8: % | E8: -0.5 | G8: Assumed | H8: tsmc/dist/20261025_台積電模型_v0.3.xlsx｜In!E8 | I8: markets/memory 無 2029；沿用台積電模型（網通模型相同，建置時檢查）
A9: u_rb_26 | B9: NVIDIA Rubin 顆數 2026 | C9: 百萬顆 | E9: 1.7 | G9: Interested-party | H9: markets/memory/market.py UNITS：2026：TrendForce 組合 Rubin 22% × 約 7.6M [Derived]；2027：Morgan Stanley 約 7.0M；2028 Assumed | I9: 台積電模型 tsmc/dist/20261025_台積電模型_v0.3.xlsx｜In!E9（值相同，建置時檢查）
A10: u_rb_27 | B10: NVIDIA Rubin 顆數 2027 | C10: 百萬顆 | E10: 7 | G10: Interested-party | H10: 同上 | I10: 同上
A11: u_rb_28 | B11: NVIDIA Rubin 顆數 2028 | C11: 百萬顆 | E11: 7 | G11: Interested-party | H11: 同上 | I11: 同上
A12: g29_rb | B12: NVIDIA Rubin 2029 顆數成長 | C12: % | E12: 0.15 | G12: Assumed | H12: tsmc/dist/20261025_台積電模型_v0.3.xlsx｜In!E12 | I12: markets/memory 無 2029；沿用台積電模型（網通模型相同，建置時檢查）
A13: u_ru_26 | B13: NVIDIA Rubin Ultra 顆數 2026 | C13: 百萬顆 | E13: 0 | G13: Assumed | H13: markets/memory/market.py UNITS：時程 Assumed；GB：NVIDIA 1 TB／封裝 | I13: 台積電模型 tsmc/dist/20261025_台積電模型_v0.3.xlsx｜In!E13（值相同，建置時檢查）
A14: u_ru_27 | B14: NVIDIA Rubin Ultra 顆數 2027 | C14: 百萬顆 | E14: 0.3 | G14: Assumed | H14: 同上 | I14: 同上
A15: u_ru_28 | B15: NVIDIA Rubin Ultra 顆數 2028 | C15: 百萬顆 | E15: 2 | G15: Assumed | H15: 同上 | I15: 同上
A16: g29_ru | B16: NVIDIA Rubin Ultra 2029 顆數成長 | C16: % | E16: 0.15 | G16: Assumed | H16: tsmc/dist/20261025_台積電模型_v0.3.xlsx｜In!E16 | I16: markets/memory 無 2029；沿用台積電模型（網通模型相同，建置時檢查）
... A54: gb_hp_28 | B54: NVIDIA Hopper（H200 等） 每顆 HBM 2028 | C54: GB | E54: 141 | G54: Interested-party | H54: markets/memory/market.py UNITS（GB300：B300 288；Rubin 288；Rubin Ultra：NVIDIA 1 TB／封裝） | I54: 同上
A55: B. 每顆售價（運算部分）：GPU 模組＋CPU＋LPDDR＋匣級加價中 NVIDIA 保留的部分（US$K／顆；橋接表 v0.2.1 Rack 頁）
A56: pm_bw | B56: GPU 模組售價：Blackwell（GB300，NVIDIA 對買方） | C56: US$K | D56: 37.6 | E56: 40.4 | F56: 47 | G56: Derived | H56: markets/chip_bridge/dist/20261023_晶片內容橋接表_v0.2.1.xlsx｜Rack!B6 | I56: 橋接表 In!D15:F15（低／基準／高）；Tokenomics v20.1 機架基準價 $4.3M。B200 較 B300 便宜，本模型不分（在 Recon 列為顆數＋價格差額的候選來源）
A57: pm_rb | B57: GPU 模組售價：Rubin（VR200，2026 HBM 價） | C57: US$K | D57: 50 | E57: 55 | F57: 60 | G57: Derived | H57: markets/chip_bridge/dist/20261023_晶片內容橋接表_v0.2.1.xlsx｜Rack!C6 | I57: 橋接表 In!G15:I15；Bernstein 估 VR200 機架 $9.1M、Fubon 估 Rubin GPU $78–80K（二手，Interested-party）高於此基準，未採
A58: pm_ru | B58: GPU 模組售價：Rubin Ultra | C58: US$K | D58: 60 | E58: 75 | F58: 100 | G58: Assumed | H58: 無：未發布。基準＝VR200 55 ×（VR200／GB300 的 1.36 倍外推）＝75 | I58: BofA 估 Rubin Ultra 機架約 $21M（二手；每封裝約 $146K 是本模型算術，封裝數有爭議；wccftech）。擁有者待定區間
A59: pm_hp | B59: GPU 模組售價：Hopper（H200 等） | C59: US$K | D59: 25 | E59: 30 | F59: 35 | G59: Assumed | H59: 無：2026 出貨僅 0.5M，影響小 | I59: 第二來源：未找到
A60: pcpu_bw | B60: CPU 每顆 GPU 分攤（GB300） | C60: US$K | E60: 2 | G60: Derived | H60: markets/chip_bridge/dist/20261023_晶片內容橋接表_v0.2.1.xlsx｜Rack!B20（$M／架 × 1000 ÷ 72） | I60: NVIDIA 自家 Grace／Vera
A61: plp_bw | B61: LPDDR5X 每顆 GPU 分攤（GB300） | C61: US$K | E61: 3.069444 | G61: Derived | H61: markets/chip_bridge/dist/20261023_晶片內容橋接表_v0.2.1.xlsx｜Rack!B21（÷ 72） | I61: 隨一般 DRAM 價格路徑變動（見 D 節）
A62: pres_bw | B62: 匣級加價（殘差）每顆 GPU（GB300） | C62: US$K | E62: 3.072222 | G62: Derived | H62: markets/chip_bridge/dist/20261023_晶片內容橋接表_v0.2.1.xlsx｜Rack!B30（÷ 72） | I62: 匣級電路板、供電與 NVIDIA／ODM 匣級加價；NVIDIA 保留比例見 k_tray
A63: pcpu_rb | B63: CPU 每顆 GPU 分攤（VR200） | C63: US$K | E63: 2.5 | G63: Derived | H63: markets/chip_bridge/dist/20261023_晶片內容橋接表_v0.2.1.xlsx｜Rack!C20（$M／架 × 1000 ÷ 72） | I63: NVIDIA 自家 Grace／Vera
A64: plp_rb | B64: LPDDR5X 每顆 GPU 分攤（VR200） | C64: US$K | E64: 5.055556 | G64: Derived | H64: markets/chip_bridge/dist/20261023_晶片內容橋接表_v0.2.1.xlsx｜Rack!C21（÷ 72） | I64: 隨一般 DRAM 價格路徑變動（見 D 節）
A65: pres_rb | B65: 匣級加價（殘差）每顆 GPU（VR200） | C65: US$K | E65: 19.222222 | G65: Derived | H65: markets/chip_bridge/dist/20261023_晶片內容橋接表_v0.2.1.xlsx｜Rack!C30（÷ 72） | I65: 匣級電路板、供電與 NVIDIA／ODM 匣級加價；NVIDIA 保留比例見 k_tray
A66: pcpu_ru | B66: CPU 每顆 GPU 分攤（Rubin Ultra） | C66: US$K | E66: =pcpu_rb -> 2.5 | G66: Analogy | H66: 比照 VR200 | I66: —
A67: plp_ru | B67: LPDDR5X 每顆 GPU 分攤（Rubin Ultra） | C67: US$K | E67: =plp_rb -> 5.055556 | G67: Analogy | H67: 比照 VR200 | I67: —
A68: pres_ru | B68: 匣級加價每顆 GPU（Rubin Ultra） | C68: US$K | E68: =pres_rb -> 19.222222 | G68: Analogy | H68: 比照 VR200 | I68: —
A69: pcpu_hp | B69: CPU 每顆 GPU 分攤（Hopper） | C69: US$K | E69: 0 | G69: Assumed | H69: Hopper 以 HGX 板出貨，價格已含在模組價 | I69: —
A70: plp_hp | B70: LPDDR5X 每顆 GPU 分攤（Hopper） | C70: US$K | E70: 0 | G70: Assumed | H70: 同上 | I70: —
A71: pres_hp | B71: 匣級加價每顆 GPU（Hopper） | C71: US$K | E71: 0 | G71: Assumed | H71: 同上 | I71: —
A72: k_tray | B72: 匣級加價中 NVIDIA 保留的比例 | C72: x | D72: 0 | E72: 0.5 | F72: 1 | G72: Assumed | H72: 無：橋接表殘差由 NVIDIA 與 ODM 共享，公司未揭露 | I72: 第二來源：未找到。影響運算營收水準（Blackwell 每顆 ±1.5K）；FY2027 的水準差額見 Recon
A73: hpx_bw | B73: HBM 單價 2026 合約：Blackwell（GB300） | C73: US$/GB | E73: 15.5 | G73: Derived | H73: markets/chip_bridge/dist/20261023_晶片內容橋接表_v0.2.1.xlsx｜Rack!B4 | I73: 橋接表 In!hbm_p（Tokenomics）；Hopper 比照
A74: hpx_rb | B74: HBM 單價 2026 合約：Rubin（VR200） | C74: US$/GB | E74: 16.7 | G74: Derived | H74: markets/chip_bridge/dist/20261023_晶片內容橋接表_v0.2.1.xlsx｜Rack!C4 | I74: Rubin Ultra 比照；HBM4 估計 $15–53/GB（Silicon Analysts／Fubon／Bernstein，二手，見 Recon）
A75: hpx_ru | B75: HBM 單價 2026 合約：Rubin Ultra | C75: US$/GB | E75: =hpx_rb -> 16.7 | G75: Analogy | H75: 比照 VR200 | I75: —
A76: hpx_hp | B76: HBM 單價 2026 合約：Hopper | C76: US$/GB | E76: =hpx_bw -> 15.5 | G76: Analogy | H76: 比照 GB300 | I76: —
A77: abs_mem | B77: HBM／LPDDR 漲價由 NVIDIA 吸收的比例（其餘轉嫁到售價） | C77: x | D77: 0 | E77: 0.5 | F77: 1 | G77: Assumed | H77: 無：橋接表 Rack 頁列兩端（D 欄吸收＝1、E 欄全額轉嫁＝0）；公司稱 FY2028 Q1 起調價（二手：Yahoo Finance、247wallst） | I77: 第二來源：未找到。擁有者待定基準值；基準取兩端中點，不為對上公司毛利率指引而調（指引只在 Recon 對帳）
A78: C. 記憶體價格路徑（讀 skhynix 成品；唯讀；情境別）
A79: hbm_A_26 | B79: HBM 混合單價 2026（A） | C79: US$/GB | E79: 14.6 | G79: Derived | H79: skhynix/dist/20261025_SK海力士模型_v0.5.xlsx｜Mkt!C30:G30 | I79: markets/memory：2026 BofA $14.6/GB；2027 +80% 三情境相同；2028–29 依情境
A80: hbm_A_27 | B80: HBM 混合單價 2027（A） | C80: US$/GB | E80: 26.28 | G80: Derived | H80: skhynix/dist/20261025_SK海力士模型_v0.5.xlsx｜Mkt!C30:G30 | I80: 同上
A81: hbm_A_28 | B81: HBM 混合單價 2028（A） | C81: US$/GB | E81: 28.908 | G81: Derived | H81: skhynix/dist/20261025_SK海力士模型_v0.5.xlsx｜Mkt!C30:G30 | I81: 同上
A82: hbm_A_29 | B82: HBM 混合單價 2029（A） | C82: US$/GB | E82: 27.4626 | G82: Derived | H82: skhynix/dist/20261025_SK海力士模型_v0.5.xlsx｜Mkt!C30:G30 | I82: 同上
A83: hbm_B_26 | B83: HBM 混合單價 2026（B） | C83: US$/GB | E83: 14.6 | G83: Derived | H83: skhynix/dist/20261025_SK海力士模型_v0.5.xlsx｜Mkt!C31:G31 | I83: 同上
A84: hbm_B_27 | B84: HBM 混合單價 2027（B） | C84: US$/GB | E84: 26.28 | G84: Derived | H84: skhynix/dist/20261025_SK海力士模型_v0.5.xlsx｜Mkt!C31:G31 | I84: 同上
A85: hbm_B_28 | B85: HBM 混合單價 2028（B） | C85: US$/GB | E85: 19.71 | G85: Derived | H85: skhynix/dist/20261025_SK海力士模型_v0.5.xlsx｜Mkt!C31:G31 | I85: 同上
A86: hbm_B_29 | B86: HBM 混合單價 2029（B） | C86: US$/GB | E86: 19.71 | G86: Derived | H86: skhynix/dist/20261025_SK海力士模型_v0.5.xlsx｜Mkt!C31:G31 | I86: 同上
A87: hbm_C_26 | B87: HBM 混合單價 2026（C） | C87: US$/GB | E87: 14.6 | G87: Derived | H87: skhynix/dist/20261025_SK海力士模型_v0.5.xlsx｜Mkt!C32:G32 | I87: 同上
A88: hbm_C_27 | B88: HBM 混合單價 2027（C） | C88: US$/GB | E88: 26.28 | G88: Derived | H88: skhynix/dist/20261025_SK海力士模型_v0.5.xlsx｜Mkt!C32:G32 | I88: 同上
A89: hbm_C_28 | B89: HBM 混合單價 2028（C） | C89: US$/GB | E89: 15.768 | G89: Derived | H89: skhynix/dist/20261025_SK海力士模型_v0.5.xlsx｜Mkt!C32:G32 | I89: 同上
A90: hbm_C_29 | B90: HBM 混合單價 2029（C） | C90: US$/GB | E90: 16.5564 | G90: Derived | H90: skhynix/dist/20261025_SK海力士模型_v0.5.xlsx｜Mkt!C32:G32 | I90: 同上
... A102: cdx_C_29 | B102: 一般 DRAM 合約價年均指數 2029（C；2025Q1＝1） | C102: x | E102: 1.6666068 | G102: Derived | H102: skhynix/dist/20261025_SK海力士模型_v0.5.xlsx｜Path!C16:G16 | I102: 同上
A103: D. 網通（讀 markets/network 成品；情境 A 基準，B／C 依 NVIDIA 顆數係數縮放——網通金額與顆數成正比、組合不變，故縮放精確）
A104: net_26 | B104: NVIDIA 網通（本模型歸屬）2026 | C104: US$B | E104: 61.733865 | G104: Derived | H104: markets/network/dist/20261023_AI網通市場模型_v0.2.2.xlsx｜Mkt!C32:F32 | I104: 廠商歸屬比例為 Assumed（markets/network In 頁 E 節）；2026 較實際推估低 16.6%（見 Recon）
A105: net_27 | B105: NVIDIA 網通（本模型歸屬）2027 | C105: US$B | E105: 122.48807 | G105: Derived | H105: markets/network/dist/20261023_AI網通市場模型_v0.2.2.xlsx｜Mkt!C32:F32 | I105: 同上
A106: net_28 | B106: NVIDIA 網通（本模型歸屬）2028 | C106: US$B | E106: 138.6168 | G106: Derived | H106: markets/network/dist/20261023_AI網通市場模型_v0.2.2.xlsx｜Mkt!C32:F32 | I106: 同上
A107: net_29 | B107: NVIDIA 網通（本模型歸屬）2029 | C107: US$B | E107: 157.29971 | G107: Derived | H107: markets/network/dist/20261023_AI網通市場模型_v0.2.2.xlsx｜Mkt!C32:F32 | I107: 同上
A108: rep_nv26 | B108: NVIDIA 網通營收 2026（實際＋推估） | C108: US$B | D108: 68 | E108: 74 | F108: 80 | G108: Verified／Derived | H108: markets/network/dist/20261023_AI網通市場模型_v0.2.2.xlsx｜In!D120:F120 | I108: Q1 FY27 14.8（公司，8-K 新聞稿）、Q2 約 17.5（法說「季增 18%」，二手）、Q3–Q4 Assumed
A109: net_q1 | B109: Data Center 網通營收 Q1 FY27 | C109: US$B | E109: 14.8 | G109: Verified | H109: https://nvidianews.nvidia.com/news/nvidia-announces-financial-results-for-first-quarter-fiscal-2027（公司最後一次揭露 compute／networking 拆分） | I109: Q2 FY27 起不再揭露：未找到（CFO 書面說明無法開啟）
A110: c_net | B110: 網通非 HBM 成本占營收 | C110: x | D110: 0.2 | E110: 0.3 | F110: 0.4 | G110: Assumed | H110: 無：公司不揭露網通毛利率 | I110: 第二來源：未找到。決定網通毛利率 60–80%
A111: E. Edge Computing（PC、遊戲機、工作站、機器人、車用；自 Q1 FY27 起公司只揭露 Data Center 與 Edge Computing 兩個平台）
A112: gm_edge | B112: Edge Computing 毛利率 | C112: x | D112: 0.5 | E112: 0.6 | F112: 0.7 | G112: Assumed | H112: 無：公司不揭露平台毛利率（舊 Gaming／ProViz／Auto 的毛利率亦未揭露） | I112: 第二來源：未找到
A113: eg | B113: Edge Computing 營收年增（FY2028 起） | C113: % | D113: 0 | E113: 0.08 | F113: 0.15 | G113: Assumed | H113: 公司：Q2 FY27 年增 27%、季增 13%；記憶體成本壓抑消費端需求（二手） | I113: 第二來源：未找到
A114: edge_q | B114: Edge Computing 季增（Q3、Q4 FY27 假設） | C114: % | D114: 0 | E114: 0.05 | F114: 0.1 | G114: Assumed | H114: Q1 FY27 季增 10%、Q2 季增 13%（公司） | I114: —
A115: F. 中國資料中心運算（基準為 0＝公司 Q3 FY27 指引假設；只在 Sens 列「恢復」）
A116: cn_amt | B116: 中國恢復後的資料中心運算營收（FY2028 起，每年） | C116: US$B | D116: 10 | E116: 20 | F116: 40 | G116: Assumed | H116: 公司 Q3 FY27 指引不假設中國資料中心運算營收；Q2 FY27 的 H200 對中國出貨 < 資料中心營收的 1%（二手：Yahoo／CNBC 摘要） | I116: 第二來源：未找到。FY2026 Q1 H20 費用 $4.5B（公司）作為量級參照
A117: G. 營業費用、稅、股數（FY2028 起）
A118: phi | B118: 營業費用成長對營收成長的彈性 | C118: x | D118: 0.4 | E118: 0.6 | F118: 0.8 | G118: Derived | H118: FY2027 錨點營業費用年增 ÷ 營收年增（Q 頁：約 0.6） | I118: 低／高 Assumed
A119: g_opx_min | B119: 營業費用年增下限 | C119: % | D119: 0 | E119: 0.05 | F119: 0.1 | G119: Assumed | H119: 無 | I119: 營收下滑時費用僵固
A120: opx_adj | B120: 營業費用額外占營收比（Sens 用；基準為 0） | C120: pt | D120: -0.02 | E120: 0 | F120: 0.02 | G120: Assumed | H120: 無 | I120: Sens 用 ±2 個百分點
A121: tx_f | B121: 有效稅率（FY2028 起） | C121: % | D121: 0.16 | E121: 0.17 | F121: 0.18 | G121: Interested-party | H121: 公司：FY2027 全年 GAAP／non-GAAP 稅率 16.0%–18.0%（Q2 FY27 新聞稿） | I121: FY2026 15.1%、Q1 FY27 16.6%、Q2 16.5%（公司，Q 頁）
A122: oth_f | B122: 其他收益淨額（不含權益證券損益；FY2028 起每年） | C122: US$B | D122: 0.5 | E122: 1.2 | F122: 2.4 | G122: Assumed | H122: FY2026 2.1、Q1 FY27 0.43、Q2 FY27 0.00（GAAP 扣權益證券損益；Q 頁） | I122: 權益證券損益屬一次性，一律排除
A123: sh_g | B123: 稀釋股數年變動（FY2028 起） | C123: % | D123: -0.025 | E123: -0.012 | F123: 0 | G123: Derived | H123: FY2025→FY2026 −1.2%（公司，Q 頁）；Q2 FY27 回購 $19.7B＋股息 $6.0B、剩餘授權約 $99B（公司） | I123: 低／高 Assumed
A124: H. FY2027 錨點假設（Q1、Q2 實績＋Q3 指引＋Q4 假設）
A125: q3_rev | B125: Q3 FY27 營收指引（±2%） | C125: US$B | D125: 105.84 | E125: 108 | F125: 110.16 | G125: Interested-party | H125: https://nvidianews.nvidia.com/news/nvidia-announces-financial-results-for-second-quarter-fiscal-2027：$108.0B ±2%；不假設中國資料中心運算營收 | I125: Webull、Yahoo Finance 摘要（二手）
A126: q3_gm | B126: Q3 FY27 毛利率指引（GAAP＝non-GAAP） | C126: % | D126: 0.735 | E126: 0.74 | F126: 0.745 | G126: Interested-party | H126: https://nvidianews.nvidia.com/news/nvidia-announces-financial-results-for-second-quarter-fiscal-2027：74.0% ±50bp | I126: implicator.ai（二手）
A127: q3_opx | B127: Q3 FY27 GAAP 營業費用指引 | C127: US$B | E127: 9.2 | G127: Interested-party | H127: https://nvidianews.nvidia.com/news/nvidia-announces-financial-results-for-second-quarter-fiscal-2027：約 $9.2B（non-GAAP $9.0B） | I127: —
A128: q4_g | B128: Q4 FY27 營收季增（Q4 假設） | C128: % | D128: 0.05 | E128: 0.1 | F128: 0.15 | G128: Assumed | H128: 無：Q1→Q2 +17.9%、Q2→Q3 指引 +12.2%（公司）；共識 FY2027 營收約 $411.7B（stockanalysis 摘要，二手） | I128: 第二來源：未找到
A129: q4_gm | B129: Q4 FY27 毛利率（Q4 假設） | C129: % | D129: 0.71 | E129: 0.715 | F129: 0.74 | G129: Assumed | H129: 二手報導：Q4 FY27 谷底 71–72%（implicator.ai、siliconanalysts；逐字稿未取得） | I129: 高＝與 Q3 指引持平
A130: q4_opx_g | B130: Q4 FY27 營業費用季增（Q4 假設） | C130: % | D130: 0.05 | E130: 0.08 | F130: 0.12 | G130: Assumed | H130: Q1→Q2 +10.3%、Q2→Q3 指引 +9.4%（公司） | I130: —
A131: q_oth | B131: Q3、Q4 FY27 其他收益淨額（不含權益證券損益；每季） | C131: US$B | D131: 0 | E131: 0.35 | F131: 0.45 | G131: Assumed | H131: Q1 FY27 0.43、Q2 0.00（GAAP 扣權益證券損益）；non-GAAP 0.46、0.30（公司） | I131: 公司 Q3 指引未列：未找到
A132: tx_27 | B132: Q3、Q4 FY27 有效稅率 | C132: % | D132: 0.16 | E132: 0.17 | F132: 0.18 | G132: Interested-party | H132: 公司：FY2027 全年 16.0%–18.0% | I132: —
A133: q_sh | B133: Q3、Q4 FY27 稀釋股數季變動 | C133: % | D133: -0.006 | E133: -0.003 | F133: 0 | G133: Derived | H133: FY2026 季均 −0.2%（公司，Q 頁） | I133: —
A134: I. 公司指引與共識（只作 Recon 對帳，不作校準）
A135: g28_gr | B135: 公司 FY2028 營收年增 | C135: % | E135: 0.7 | G135: Interested-party | H135: Q2 FY27 法說（二手：Yahoo Finance、CNBC 標題確認「約 70%」）；假設供給受限；逐字稿未取得 | I135: 工作單記約 US$690B：未找到公司直接陳述的美元金額，Recon 以 FY2027 錨點 ×1.7 推算
A136: g28_gm | B136: 公司 FY2028 毛利率指引 | C136: % | D136: 0.72 | E136: 0.725 | F136: 0.73 | G136: Interested-party | H136: 二手報導：FY2028 全年 72–73%（Q1 FY28 起調價生效）；Q4 FY27 谷底 71–72%（moomoo、biggo；逐字稿未取得） | I136: 公司 Q3 FY27 指引 74.0%（8-K）
A137: cons_g28 | B137: 共識 FY2028 營收年增（指引後） | C137: % | E137: 0.63 | G137: Interested-party | H137: Yahoo Finance 摘要（二手）；指引前 LSEG 約 44% | I137: 第二來源：未找到
A138: cons_rev27 | B138: 共識 FY2027 營收 | C138: US$B | E138: 411.7 | G138: Interested-party | H138: stockanalysis.com（搜尋摘要，頁面無法開啟）；另一來源 396（可能較舊） | I138: —
A139: cons_eps27 | B139: 共識 FY2027 EPS | C139: US$ | E139: 9.31 | G139: Interested-party | H139: stockanalysis.com（搜尋摘要）；9.28–9.31 的其他摘要 | I139: 新口徑 non-GAAP（含 SBC）
A140: cons_eps28 | B140: 共識 FY2028 EPS | C140: US$ | D140: 15.7 | E140: 15.91 | F140: 16.13 | G140: Interested-party | H140: 247wallst 2026-10-19：15.70–15.91；Wallstreetzen 平均 16.13（68 位分析師，區間 13.13–19.65） | I140: 新口徑 non-GAAP（含 SBC）。FY2029 共識：未找到
A141: th_mult | B141: 命題中現價對「2027 年 EPS」的倍數（日曆年 2027＝FY2028） | C141: x | E141: 13.5 | G141: Interested-party | H141: 擁有者命題（工作單） | I141: 對照：現價 ÷ 共識 FY2028 EPS 約 13.4–13.5x（Val 頁）
A142: th_sh_lo | B142: 命題：2027 年 NVIDIA 金額份額（下緣） | C142: % | E142: 0.75 | G142: Interested-party | H142: 擁有者命題；可歸屬的外部來源：未找到（Kaiso：2028 前 60–75%；Silicon Analysts：2025 約 80%） | I142: —
A143: th_sh_hi | B143: 命題：2027 年 NVIDIA 金額份額（上緣） | C143: % | E143: 0.8 | G143: Interested-party | H143: 同上 | I143: —
A144: J. 各家每顆加速器金額（份額計算用；模組層級，與 NVIDIA 的 GPU 模組價同一口徑）
A145: pa_amd | B145: AMD Instinct 每顆 | C145: US$K | D145: 20 | E145: 30 | F145: 45 | G145: Interested-party | H145: MI355X：HSBC 約 $23K（自 $25K 下修）、其他報導 $20–25K；MI455X 無官方價，部落格 $15–50K（finviz、gpusmith、MikeLongTerm；賣方有目標價誘因） | I145: 第二來源：以上三者互相一致於 $20–25K（MI355X）；MI455X 無獨立來源
A146: pa_tpu | B146: Google TPU 每顆 | C146: US$K | D146: 8 | E146: 12 | F146: 18 | G146: Assumed | H146: 無：每顆 ASP 未找到（只有租用價代理：Ironwood $1.03–1.60／小時，SemiAnalysis，不可單獨使用） | I146: 未找到
A147: pa_trn | B147: AWS Trainium 每顆 | C147: US$K | D147: 5 | E147: 8 | F147: 12 | G147: Assumed | H147: 無：每顆 ASP 未找到 | I147: Maia 200 約為 NVIDIA（逾 $30K）的 30–40%＝$9–12K（二手，cryptobriefing）作量級參照
A148: pa_oth | B148: 其他 ASIC 每顆 | C148: US$K | D148: 5 | E148: 8 | F148: 12 | G148: Assumed | H148: 無：未找到（Maia、MTIA 皆無 ASP） | I148: 同上
...

Sheet Q
A1: Q — 實績（十億美元；EPS 為美元；股數為十億股）。會計年度 FY2026＝2025-02～2026-01。藍字＝輸入；黑字＝公式。實績取自 NVIDIA 8-K 新聞稿；第二來源＝後續季度新聞稿的比較欄（同一公司不同文件）
A2: FY2027 錨點＝Q1、Q2 實績＋Q3 指引中點＋Q4 假設（I、J 欄，假設見 In 頁 H 節）。EPS 口徑：GAAP 扣除權益證券損益（一次性；權益證券損益 Q1 FY27 為 $15.9B、Q2 為 $7.8B），含股票薪酬；與公司自 Q1 FY27 起的新 non-GAAP 口徑（含 SBC）相近，差額見下方檢查列
A3: 項目 | B3: FY26 Q1（2025-02～04） | C3: FY26 Q2（～07） | D3: FY26 Q3（～10） | E3: FY26 Q4（～2026-01） | F3: FY2026 全年 | G3: FY27 Q1（2026-02～04） | H3: FY27 Q2（～07） | I3: FY27 Q3（指引中點） | J3: FY27 Q4（假設） | K3: FY2027 錨點 | L3: 標記 | M3: 來源1（公司） | N3: 來源2／說明
A4: 營收 | B4: 44.062 | C4: 46.743 | D4: 57.006 | E4: 68.127 | F4: =SUM(B4:E4) -> 215.938 | G4: 81.615 | H4: 96.221 | I4: =q3_rev -> 108 | J4: =I4*(1+q4_g) -> 118.8 | K4: =SUM(G4:J4) -> 404.636 | L4: Verified／Interested-party（Q3 指引）／Assumed（Q4） | M4: NVIDIA 8-K 新聞稿（nvidianews.nvidia.com/news/nvidia-announces-financial-results-for-）：B欄＝first-quarter-fiscal-2026；C欄＝second-quarter-fiscal-2026；D欄＝third-quarter-fiscal-2026；E欄＝fourth-quarter-and-fiscal-2026；G欄＝first-quarter-fiscal-2027；H欄＝second-quarter-fiscal-2027 | N4: 後續季度新聞稿比較欄交叉：Q1、Q4 FY26 見 Q1 FY27 稿；Q2 FY26 見 Q2 FY27 稿；Q3 FY26 見 Q4 FY26 稿
A5: Data Center 營收（公司揭露，四捨五入到 0.1） | B5: 39.1 | C5: 41.1 | D5: 51.2 | E5: 62.3 | F5: =SUM(B5:E5) -> 193.7 | G5: 75.2 | H5: 89 | I5: =I4-I6 -> 100.41795 | J5: =J4-J6 -> 110.83885 | K5: =SUM(G5:J5) -> 375.4568 | L5: Verified／Derived（I、J） | M5: NVIDIA 8-K 新聞稿（nvidianews.nvidia.com/news/nvidia-announces-financial-results-for-）：B欄＝first-quarter-fiscal-2026；C欄＝second-quarter-fiscal-2026；D欄＝third-quarter-fiscal-2026；E欄＝fourth-quarter-and-fiscal-2026；G欄＝first-quarter-fiscal-2027；H欄＝second-quarter-fiscal-2027 | N5: 後續季度新聞稿比較欄交叉：Q1、Q4 FY26 見 Q1 FY27 稿；Q2 FY26 見 Q2 FY27 稿；Q3 FY26 見 Q4 FY26 稿；FY2026 合計 193.7＝公司全年值
A6: Edge Computing 營收（＝營收 − Data Center） | B6: =B4-B5 -> 4.962 | C6: =C4-C5 -> 5.643 | D6: =D4-D5 -> 5.806 | E6: =E4-E5 -> 5.827 | F6: =SUM(B6:E6) -> 22.238 | G6: =G4-G5 -> 6.415 | H6: =H4-H5 -> 7.221 | I6: =H6*(1+edge_q) -> 7.58205 | J6: =I6*(1+edge_q) -> 7.9611525 | K6: =SUM(G6:J6) -> 29.179202 | L6: Derived（實績）／Assumed（I、J） | M6: 公司 Q1 FY27 起只揭露 Data Center 與 Edge Computing 兩個平台；FY26 各季 Edge＝營收 − Data Center（舊 Gaming＋ProViz＋Auto＋OEM 合計） | N6: Q1、Q2 FY27 公司官方 Edge 為 6.4、7.2（下一列核對）
A7: 公司官方揭露的 Edge Computing（Q1、Q2 FY27） | G7: 6.4 | H7: 7.2 | L7: Verified | M7: https://nvidianews.nvidia.com/news/nvidia-announces-financial-results-for-first-quarter-fiscal-2027；https://nvidianews.nvidia.com/news/nvidia-announces-financial-results-for-second-quarter-fiscal-2027 | N7: 與上列推得值差 < 0.05（四捨五入）
A8: 毛利（GAAP） | B8: 26.668 | C8: 33.853 | D8: 41.849 | E8: 51.093 | F8: =SUM(B8:E8) -> 153.463 | G8: 61.157 | H8: 72.142 | I8: =I4*q3_gm -> 79.92 | J8: =J4*q4_gm -> 84.942 | K8: =SUM(G8:J8) -> 298.161 | L8: Verified／Interested-party（I）／Assumed（J） | M8: NVIDIA 8-K 新聞稿（nvidianews.nvidia.com/news/nvidia-announces-financial-results-for-）：B欄＝first-quarter-fiscal-2026；C欄＝second-quarter-fiscal-2026；D欄＝third-quarter-fiscal-2026；E欄＝fourth-quarter-and-fiscal-2026；G欄＝first-quarter-fiscal-2027；H欄＝second-quarter-fiscal-2027 | N8: 後續季度新聞稿比較欄交叉：Q1、Q4 FY26 見 Q1 FY27 稿；Q2 FY26 見 Q2 FY27 稿；Q3 FY26 見 Q4 FY26 稿
A9: 毛利率 | B9: =B8/B4 -> 0.60523807 | C9: =C8/C4 -> 0.72423678 | D9: =D8/D4 -> 0.73411571 | E9: =E8/E4 -> 0.74996697 | F9: =F8/F4 -> 0.71068084 | G9: =G8/G4 -> 0.74933529 | H9: =H8/H4 -> 0.74975317 | I9: =I8/I4 -> 0.74 | ... K9: =K8/K4 -> 0.73686227 | L9: Derived | M9: — | N9: 公司：Q1 FY26 60.5%（含 H20 費用 $4.5B）、FY2026 71.1%
A10: 營業費用（GAAP，R&D＋SG&A） | B10: 5.03 | C10: 5.413 | D10: 5.839 | E10: 6.794 | F10: =SUM(B10:E10) -> 23.076 | G10: 7.621 | H10: 8.408 | I10: =q3_opx -> 9.2 | J10: =I10*(1+q4_opx_g) -> 9.936 | K10: =SUM(G10:J10) -> 35.165 | L10: Verified／Interested-party（I）／Assumed（J） | M10: NVIDIA 8-K 新聞稿（nvidianews.nvidia.com/news/nvidia-announces-financial-results-for-）：B欄＝first-quarter-fiscal-2026；C欄＝second-quarter-fiscal-2026；D欄＝third-quarter-fiscal-2026；E欄＝fourth-quarter-and-fiscal-2026；G欄＝first-quarter-fiscal-2027；H欄＝second-quarter-fiscal-2027 | N10: 後續季度新聞稿比較欄交叉：Q1、Q4 FY26 見 Q1 FY27 稿；Q2 FY26 見 Q2 FY27 稿；Q3 FY26 見 Q4 FY26 稿
A11: 營業利益 | B11: 21.638 | C11: 28.44 | D11: 36.01 | E11: 44.299 | F11: =SUM(B11:E11) -> 130.387 | G11: 53.536 | H11: 63.734 | I11: =I8-I10 -> 70.72 | J11: =J8-J10 -> 75.006 | K11: =SUM(G11:J11) -> 262.996 | L11: Verified／Derived（I、J） | M11: NVIDIA 8-K 新聞稿（nvidianews.nvidia.com/news/nvidia-announces-financial-results-for-）：B欄＝first-quarter-fiscal-2026；C欄＝second-quarter-fiscal-2026；D欄＝third-quarter-fiscal-2026；E欄＝fourth-quarter-and-fiscal-2026；G欄＝first-quarter-fiscal-2027；H欄＝second-quarter-fiscal-2027 | N11: 後續季度新聞稿比較欄交叉：Q1、Q4 FY26 見 Q1 FY27 稿；Q2 FY26 見 Q2 FY27 稿；Q3 FY26 見 Q4 FY26 稿
A12: 檢查：毛利 − 營業費用 − 營業利益（實績應為 0） | B12: =B8-B10-B11 -> 0 | C12: =C8-C10-C11 -> 0 | D12: =D8-D10-D11 -> 0 | E12: =E8-E10-E11 -> 0 | F12: =SUM(B12:E12) -> 0 | G12: =G8-G10-G11 -> 0 | H12: =H8-H10-H11 -> 0 | K12: =SUM(G12:J12) -> 0 | L12: — | M12: — | N12: —
A13: 其他收益淨額（GAAP 合計，含權益證券損益） | B13: 0.272 | C13: 2.766 | D13: 1.926 | E13: 6.098 | F13: =SUM(B13:E13) -> 11.062 | G13: 16.367 | H13: 7.773 | L13: Verified | M13: NVIDIA 8-K 新聞稿（nvidianews.nvidia.com/news/nvidia-announces-financial-results-for-）：B欄＝first-quarter-fiscal-2026；C欄＝second-quarter-fiscal-2026；D欄＝third-quarter-fiscal-2026；E欄＝fourth-quarter-and-fiscal-2026；G欄＝first-quarter-fiscal-2027；H欄＝second-quarter-fiscal-2027 | N13: 後續季度新聞稿比較欄交叉：Q1、Q4 FY26 見 Q1 FY27 稿；Q2 FY26 見 Q2 FY27 稿；Q3 FY26 見 Q4 FY26 稿
A14: 其中：權益證券淨損益（一次性，排除） | B14: -0.175 | C14: 2.247 | D14: 1.354 | E14: 5.491 | F14: =SUM(B14:E14) -> 8.917 | G14: 15.936 | H14: 7.771 | L14: Verified | M14: NVIDIA 8-K 新聞稿（nvidianews.nvidia.com/news/nvidia-announces-financial-results-for-）：B欄＝first-quarter-fiscal-2026；C欄＝second-quarter-fiscal-2026；D欄＝third-quarter-fiscal-2026；E欄＝fourth-quarter-and-fiscal-2026；G欄＝first-quarter-fiscal-2027；H欄＝second-quarter-fiscal-2027（non-GAAP 調節表「Gains from equity securities, net」） | N14: 後續季度新聞稿比較欄交叉：Q1、Q4 FY26 見 Q1 FY27 稿；Q2 FY26 見 Q2 FY27 稿；Q3 FY26 見 Q4 FY26 稿
A15: 其他收益淨額（不含權益證券損益） | B15: =B13-B14 -> 0.447 | C15: =C13-C14 -> 0.519 | D15: =D13-D14 -> 0.572 | E15: =E13-E14 -> 0.607 | F15: =SUM(B15:E15) -> 2.145 | G15: =G13-G14 -> 0.431 | H15: =H13-H14 -> 0.002 | I15: =q_oth -> 0.35 | J15: =q_oth -> 0.35 | K15: =SUM(G15:J15) -> 1.133 | L15: Derived／Assumed（I、J） | M15: GAAP 合計 − 權益證券損益；利息收入、利息費用與其他 | N15: 公司 non-GAAP 其他收益：Q1 FY26 0.45、Q2 0.52、Q4 0.62、Q1 FY27 0.46、Q2 FY27 0.30（另含股息收入等調節）
A16: 稅前利益（不含權益證券損益） | B16: =B11+B15 -> 22.085 | C16: =C11+C15 -> 28.959 | D16: =D11+D15 -> 36.582 | E16: =E11+E15 -> 44.906 | F16: =SUM(B16:E16) -> 132.532 | G16: =G11+G15 -> 53.967 | H16: =H11+H15 -> 63.736 | I16: =I11+I15 -> 71.07 | J16: =J11+J15 -> 75.356 | K16: =SUM(G16:J16) -> 264.129 | L16: Derived | M16: NVIDIA 8-K 新聞稿（nvidianews.nvidia.com/news/nvidia-announces-financial-results-for-）：B欄＝first-quarter-fiscal-2026；C欄＝second-quarter-fiscal-2026；D欄＝third-quarter-fiscal-2026；E欄＝fourth-quarter-and-fiscal-2026；G欄＝first-quarter-fiscal-2027；H欄＝second-quarter-fiscal-2027 | N16: 後續季度新聞稿比較欄交叉：Q1、Q4 FY26 見 Q1 FY27 稿；Q2 FY26 見 Q2 FY27 稿；Q3 FY26 見 Q4 FY26 稿
A17: 所得稅（GAAP） | B17: 3.135 | C17: 4.784 | D17: 6.026 | E17: 7.437 | F17: =SUM(B17:E17) -> 21.382 | G17: 11.582 | H17: 11.819 | L17: Verified | M17: NVIDIA 8-K 新聞稿（nvidianews.nvidia.com/news/nvidia-announces-financial-results-for-）：B欄＝first-quarter-fiscal-2026；C欄＝second-quarter-fiscal-2026；D欄＝third-quarter-fiscal-2026；E欄＝fourth-quarter-and-fiscal-2026；G欄＝first-quarter-fiscal-2027；H欄＝second-quarter-fiscal-2027 | N17: 後續季度新聞稿比較欄交叉：Q1、Q4 FY26 見 Q1 FY27 稿；Q2 FY26 見 Q2 FY27 稿；Q3 FY26 見 Q4 FY26 稿
A18: 稅前利益（GAAP） | B18: =B11+B13 -> 21.91 | C18: =C11+C13 -> 31.206 | D18: =D11+D13 -> 37.936 | E18: =E11+E13 -> 50.397 | F18: =SUM(B18:E18) -> 141.449 | G18: =G11+G13 -> 69.903 | H18: =H11+H13 -> 71.507 | L18: Derived | M18: 營業利益＋其他收益淨額 | N18: 公司 Q1 FY27 69.903、Q2 71.507
A19: 有效稅率 | B19: =B17/B18 -> 0.14308535 | C19: =C17/C18 -> 0.15330385 | D19: =D17/D18 -> 0.15884648 | E19: =E17/E18 -> 0.14756831 | F19: =F17/F18 -> 0.15116402 | G19: =G17/G18 -> 0.16568674 | H19: =H17/H18 -> 0.16528452 | I19: =tx_27 -> 0.17 | J19: =tx_27 -> 0.17 | K19: =1-K20/K16 -> 0.16798084 | L19: Derived／Interested-party（FY2027 全年 16.0–18.0%） | M19: GAAP 稅 ÷ GAAP 稅前；K 欄為扣除權益證券損益後的全年有效稅率（實績季用 GAAP 有效稅率套用在不含損益的稅前利益） | N19: 公司：FY2027 全年 GAAP／non-GAAP 稅率 16.0%–18.0%
A20: 淨利（不含權益證券損益）＝稅前 ×（1 − 有效稅率） | B20: =B16*(1-B19) -> 18.92496 | C20: =C16*(1-C19) -> 24.519474 | D20: =D16*(1-D19) -> 30.771078 | E20: =E16*(1-E19) -> 38.279298 | F20: =SUM(B20:E20) -> 112.49481 | G20: =G16*(1-G19) -> 45.025384 | H20: =H16*(1-H19) -> 53.201426 | I20: =I16*(1-I19) -> 58.9881 | J20: =J16*(1-J19) -> 62.54548 | K20: =SUM(G20:J20) -> 219.76039 | L20: Derived | M20: NVIDIA 8-K 新聞稿（nvidianews.nvidia.com/news/nvidia-announces-financial-results-for-）：B欄＝first-quarter-fiscal-2026；C欄＝second-quarter-fiscal-2026；D欄＝third-quarter-fiscal-2026；E欄＝fourth-quarter-and-fiscal-2026；G欄＝first-quarter-fiscal-2027；H欄＝second-quarter-fiscal-2027 | N20: 後續季度新聞稿比較欄交叉：Q1、Q4 FY26 見 Q1 FY27 稿；Q2 FY26 見 Q2 FY27 稿；Q3 FY26 見 Q4 FY26 稿
A21: 稀釋股數（十億股） | B21: 24.611 | C21: 24.532 | D21: 24.483 | E21: 24.432 | F21: =AVERAGE(B21:E21) -> 24.5145 | G21: 24.391 | H21: 24.285 | I21: =H21*(1+q_sh) -> 24.212145 | J21: =I21*(1+q_sh) -> 24.139509 | K21: =AVERAGE(G21:J21) -> 24.256913 | L21: Verified／Derived（I、J） | M21: NVIDIA 8-K 新聞稿（nvidianews.nvidia.com/news/nvidia-announces-financial-results-for-）：B欄＝first-quarter-fiscal-2026；C欄＝second-quarter-fiscal-2026；D欄＝third-quarter-fiscal-2026；E欄＝fourth-quarter-and-fiscal-2026；G欄＝first-quarter-fiscal-2027；H欄＝second-quarter-fiscal-2027 | N21: 後續季度新聞稿比較欄交叉：Q1、Q4 FY26 見 Q1 FY27 稿；Q2 FY26 見 Q2 FY27 稿；Q3 FY26 見 Q4 FY26 稿
A22: EPS（不含權益證券損益，美元） | B22: =B20/B21 -> 0.76896347 | C22: =C20/C21 -> 0.99948939 | D22: =D20/D21 -> 1.2568345 | E22: =E20/E21 -> 1.5667689 | F22: =F20/F21 -> 4.588909 | G22: =G20/G21 -> 1.8459835 | H22: =H20/H21 -> 2.1907114 | I22: =I20/I21 -> 2.4363021 | ... K22: =K20/K21 -> 9.0597013 | L22: Derived | M22: 淨利（不含權益證券損益）÷ 稀釋股數 | N22: FY2027 Q3、Q4 為指引與假設推得
A23: 淨利（GAAP，公司） | B23: 18.775 | C23: 26.422 | D23: 31.91 | E23: 42.96 | F23: =SUM(B23:E23) -> 120.067 | G23: 58.321 | H23: 59.688 | L23: Verified | M23: NVIDIA 8-K 新聞稿（nvidianews.nvidia.com/news/nvidia-announces-financial-results-for-）：B欄＝first-quarter-fiscal-2026；C欄＝second-quarter-fiscal-2026；D欄＝third-quarter-fiscal-2026；E欄＝fourth-quarter-and-fiscal-2026；G欄＝first-quarter-fiscal-2027；H欄＝second-quarter-fiscal-2027 | N23: 後續季度新聞稿比較欄交叉：Q1、Q4 FY26 見 Q1 FY27 稿；Q2 FY26 見 Q2 FY27 稿；Q3 FY26 見 Q4 FY26 稿
A24: EPS（GAAP 稀釋，公司） | B24: 0.76 | C24: 1.08 | D24: 1.3 | E24: 1.76 | F24: 4.9 | G24: 2.39 | H24: 2.46 | L24: Verified | M24: NVIDIA 8-K 新聞稿（nvidianews.nvidia.com/news/nvidia-announces-financial-results-for-）：B欄＝first-quarter-fiscal-2026；C欄＝second-quarter-fiscal-2026；D欄＝third-quarter-fiscal-2026；E欄＝fourth-quarter-and-fiscal-2026；G欄＝first-quarter-fiscal-2027；H欄＝second-quarter-fiscal-2027 | N24: 後續季度新聞稿比較欄交叉：Q1、Q4 FY26 見 Q1 FY27 稿；Q2 FY26 見 Q2 FY27 稿；Q3 FY26 見 Q4 FY26 稿；FY2026 全年 4.90（公司）
A25: EPS（non-GAAP 稀釋，新口徑含 SBC；Q3 FY26 官方重編值：未找到） | B25: 0.78 | C25: 1.01 | E25: 1.59 | G25: 1.87 | H25: 2.22 | L25: Verified | M25: Q1 FY27 稿對帳表（Q1、Q4 FY26、Q1 FY27）；Q2 FY27 稿對帳表（Q2 FY26、Q2 FY27） | N25: 舊口徑（排除 SBC）原值：0.81、1.05、1.30、1.62；FY2026 4.77
A26: 股票薪酬 SBC（現金流量表） | B26: 1.474 | C26: 1.624 | D26: 1.655 | E26: 1.633 | F26: =SUM(B26:E26) -> 6.386 | G26: 1.928 | H26: 2.027 | L26: Verified | M26: NVIDIA 8-K 新聞稿（nvidianews.nvidia.com/news/nvidia-announces-financial-results-for-）：B欄＝first-quarter-fiscal-2026；C欄＝second-quarter-fiscal-2026；D欄＝third-quarter-fiscal-2026；E欄＝fourth-quarter-and-fiscal-2026；G欄＝first-quarter-fiscal-2027；H欄＝second-quarter-fiscal-2027 | N26: 後續季度新聞稿比較欄交叉：Q1、Q4 FY26 見 Q1 FY27 稿；Q2 FY26 見 Q2 FY27 稿；Q3 FY26 見 Q4 FY26 稿
A27: 檢查：GAAP 淨利 − (GAAP 稅前 − 稅)（應為 0） | B27: =B23-(B18-B17) -> 0 | C27: =C23-(C18-C17) -> 0 | D27: =D23-(D18-D17) -> 0 | E27: =E23-(E18-E17) -> 0 | G27: =G23-(G18-G17) -> 0 | H27: =H23-(H18-H17) -> 0 | L27: — | M27: — | N27: —
A28: 檢查：EPS（不含權益證券損益）− non-GAAP EPS（新口徑） | B28: =B22-B25 -> -0.011036526 | C28: =C22-C25 -> -0.010510608 | E28: =E22-E25 -> -0.023231108 | G28: =G22-G25 -> -0.024016488 | H28: =H22-H25 -> -0.029288615 | L28: — | M28: 差額來自收購相關成本、其他調節項與稅 | N28: Q1、Q2 FY27 差 −0.03～−0.02：本模型 EPS 口徑可近似公司新 non-GAAP
A29: 檢查：FY2026 四季合計 − 公司全年值（營收 215.938、營業利益 130.387，應為 0） | F29: =(F4-215.938)+(F11-130.387) -> 0 | L29: — | M29: — | N29: —
A31: FY2027 錨點與共識、指引的距離（參考；校準時未使用共識）
A32: FY2027 營收 ÷ 共識營收 − 1 | B32: =K4/cons_rev27-1 -> -0.017158125
A33: FY2027 EPS（不含權益證券損益）÷ 共識 EPS − 1 | B33: =K22/cons_eps27-1 -> -0.02688493
A34: FY2027 營收年增 | B34: =K4/F4-1 -> 0.87385268
A35: FY2027 營業費用年增 | B35: =K10/F10-1 -> 0.52387762
A36: 營業費用彈性（營業費用年增 ÷ 營收年增；In 頁 phi 的依據） | B36: =B35/B34 -> 0.59950336

Sheet Units
A1: Units — 加速器顆數（百萬顆；日曆年；與 HBM、台積電、網通模型同一份）與金額份額（模組層級每顆價 × 顆數）。NVIDIA 會計年度 FY(t) 對照日曆年 t−1（FY2027＝CY2026 … FY2030＝CY2029）
A3: 項目 | B3: 單位 | C3: CY2026（FY2027） | D3: CY2027（FY2028） | E3: CY2028（FY2029） | F3: CY2029（FY2030） | G3: 說明
A4: 情境 A：基準
A5: 顆數
A6: NVIDIA Blackwell（B200／B300） | B6: 百萬顆 | C6: =u_bw_26 -> 5.4 | D6: =u_bw_27 -> 2.4 | E6: =u_bw_28*um28_A -> 0.5 | F6: =u_bw_28*(1+g29_bw)*um29_A -> 0.25
A7: NVIDIA Rubin | B7: 百萬顆 | C7: =u_rb_26 -> 1.7 | D7: =u_rb_27 -> 7 | E7: =u_rb_28*um28_A -> 7 | F7: =u_rb_28*(1+g29_rb)*um29_A -> 8.05
A8: NVIDIA Rubin Ultra | B8: 百萬顆 | C8: =u_ru_26 -> 0 | D8: =u_ru_27 -> 0.3 | E8: =u_ru_28*um28_A -> 2 | F8: =u_ru_28*(1+g29_ru)*um29_A -> 2.3
A9: NVIDIA Hopper（H200 等） | B9: 百萬顆 | C9: =u_hp_26 -> 0.5 | D9: =u_hp_27 -> 0 | E9: =u_hp_28*um28_A -> 0 | F9: =u_hp_28*(1+g29_hp)*um29_A -> 0
A10: AMD Instinct | B10: 百萬顆 | C10: =u_amd_26 -> 0.75 | D10: =u_amd_27 -> 1.5 | E10: =u_amd_28*um28_A -> 2 | F10: =u_amd_28*(1+g29_amd)*um29_A -> 2.3
A11: Google TPU | B11: 百萬顆 | C11: =u_tpu_26 -> 3.85 | D11: =u_tpu_27 -> 5.5 | E11: =u_tpu_28*um28_A -> 7 | F11: =u_tpu_28*(1+g29_tpu)*um29_A -> 8.05
A12: AWS Trainium | B12: 百萬顆 | C12: =u_trn_26 -> 2 | D12: =u_trn_27 -> 2.5 | E12: =u_trn_28*um28_A -> 3 | F12: =u_trn_28*(1+g29_trn)*um29_A -> 3.45
A13: 其他 ASIC（MTIA、Maia、Ascend 等） | B13: 百萬顆 | C13: =u_oth_26 -> 1 | D13: =u_oth_27 -> 4.5 | E13: =u_oth_28*um28_A -> 5 | F13: =u_oth_28*(1+g29_oth)*um29_A -> 5.75
A14: 合計 | B14: 百萬顆 | C14: =SUM(C6:C13) -> 15.2 | D14: =SUM(D6:D13) -> 23.7 | E14: =SUM(E6:E13) -> 26.5 | F14: =SUM(F6:F13) -> 30.15
A15: 金額（顆數 × 每顆售價）
A16: NVIDIA Blackwell（B200／B300） | B16: US$B | C16: =u_bw_26*(pm_bw) -> 218.16 | D16: =u_bw_27*(pm_bw) -> 96.96 | E16: =u_bw_28*um28_A*(pm_bw) -> 20.2 | F16: =u_bw_28*(1+g29_bw)*um29_A*(pm_bw) -> 10.1
A17: NVIDIA Rubin | B17: US$B | C17: =u_rb_26*(pm_rb) -> 93.5 | D17: =u_rb_27*(pm_rb) -> 385 | E17: =u_rb_28*um28_A*(pm_rb) -> 385 | F17: =u_rb_28*(1+g29_rb)*um29_A*(pm_rb) -> 442.75
A18: NVIDIA Rubin Ultra | B18: US$B | C18: =u_ru_26*(pm_ru) -> 0 | D18: =u_ru_27*(pm_ru) -> 22.5 | E18: =u_ru_28*um28_A*(pm_ru) -> 150 | F18: =u_ru_28*(1+g29_ru)*um29_A*(pm_ru) -> 172.5
A19: NVIDIA Hopper（H200 等） | B19: US$B | C19: =u_hp_26*(pm_hp) -> 15 | D19: =u_hp_27*(pm_hp) -> 0 | E19: =u_hp_28*um28_A*(pm_hp) -> 0 | F19: =u_hp_28*(1+g29_hp)*um29_A*(pm_hp) -> 0
A20: AMD Instinct | B20: US$B | C20: =u_amd_26*(pa_amd) -> 22.5 | D20: =u_amd_27*(pa_amd) -> 45 | E20: =u_amd_28*um28_A*(pa_amd) -> 60 | F20: =u_amd_28*(1+g29_amd)*um29_A*(pa_amd) -> 69
A21: Google TPU | B21: US$B | C21: =u_tpu_26*(pa_tpu) -> 46.2 | D21: =u_tpu_27*(pa_tpu) -> 66 | E21: =u_tpu_28*um28_A*(pa_tpu) -> 84 | F21: =u_tpu_28*(1+g29_tpu)*um29_A*(pa_tpu) -> 96.6
A22: AWS Trainium | B22: US$B | C22: =u_trn_26*(pa_trn) -> 16 | D22: =u_trn_27*(pa_trn) -> 20 | E22: =u_trn_28*um28_A*(pa_trn) -> 24 | F22: =u_trn_28*(1+g29_trn)*um29_A*(pa_trn) -> 27.6
A23: 其他 ASIC（MTIA、Maia、Ascend 等） | B23: US$B | C23: =u_oth_26*(pa_oth) -> 8 | D23: =u_oth_27*(pa_oth) -> 36 | E23: =u_oth_28*um28_A*(pa_oth) -> 40 | F23: =u_oth_28*(1+g29_oth)*um29_A*(pa_oth) -> 46
A24: 合計 | B24: US$B | C24: =SUM(C16:C23) -> 419.36 | D24: =SUM(D16:D23) -> 671.46 | E24: =SUM(E16:E23) -> 763.2 | F24: =SUM(F16:F23) -> 864.55
A25: 顆數份額
A26: NVIDIA | B26: % | C26: =(C6+C7+C8+C9)/C14 -> 0.5 | D26: =(D6+D7+D8+D9)/D14 -> 0.4092827 | E26: =(E6+E7+E8+E9)/E14 -> 0.35849057 | F26: =(F6+F7+F8+F9)/F14 -> 0.35157546
A27: AMD | B27: % | C27: =(C10)/C14 -> 0.049342105 | D27: =(D10)/D14 -> 0.063291139 | E27: =(E10)/E14 -> 0.075471698 | F27: =(F10)/F14 -> 0.07628524
A28: Google TPU | B28: % | C28: =(C11)/C14 -> 0.25328947 | D28: =(D11)/D14 -> 0.23206751 | E28: =(E11)/E14 -> 0.26415094 | F28: =(F11)/F14 -> 0.26699834
A29: AWS Trainium | B29: % | C29: =(C12)/C14 -> 0.13157895 | D29: =(D12)/D14 -> 0.10548523 | E29: =(E12)/E14 -> 0.11320755 | F29: =(F12)/F14 -> 0.11442786
A30: 其他 ASIC | B30: % | C30: =(C13)/C14 -> 0.065789474 | D30: =(D13)/D14 -> 0.18987342 | E30: =(E13)/E14 -> 0.18867925 | F30: =(F13)/F14 -> 0.1907131
A31: 金額份額
A32: NVIDIA | B32: % | C32: =(C16+C17+C18+C19)/C24 -> 0.77894887 | D32: =(D16+D17+D18+D19)/D24 -> 0.75128824 | E32: =(E16+E17+E18+E19)/E24 -> 0.72746331 | F32: =(F16+F17+F18+F19)/F24 -> 0.72332427
A33: AMD | B33: % | C33: =(C20)/C24 -> 0.053653186 | D33: =(D20)/D24 -> 0.06701814 | E33: =(E20)/E24 -> 0.078616352 | F33: =(F20)/F24 -> 0.079810306
A34: Google TPU | B34: % | C34: =(C21)/C24 -> 0.11016787 | D34: =(D21)/D24 -> 0.098293271 | E34: =(E21)/E24 -> 0.11006289 | F34: =(F21)/F24 -> 0.11173443
A35: AWS Trainium | B35: % | C35: =(C22)/C24 -> 0.038153377 | D35: =(D22)/D24 -> 0.02978584 | E35: =(E22)/E24 -> 0.031446541 | F35: =(F22)/F24 -> 0.031924122
A36: 其他 ASIC | B36: % | C36: =(C23)/C24 -> 0.019076688 | D36: =(D23)/D24 -> 0.053614512 | E36: =(E23)/E24 -> 0.052410901 | F36: =(F23)/F24 -> 0.053206871
A38: 情境 B：2028 顆數 ×0.8、2029 ×0.85
A39: 顆數
A40: NVIDIA Blackwell（B200／B300） | B40: 百萬顆 | C40: =u_bw_26 -> 5.4 | D40: =u_bw_27 -> 2.4 | E40: =u_bw_28*um28_B -> 0.4 | F40: =u_bw_28*(1+g29_bw)*um29_B -> 0.2125
A41: NVIDIA Rubin | B41: 百萬顆 | C41: =u_rb_26 -> 1.7 | D41: =u_rb_27 -> 7 | E41: =u_rb_28*um28_B -> 5.6 | F41: =u_rb_28*(1+g29_rb)*um29_B -> 6.8425
A42: NVIDIA Rubin Ultra | B42: 百萬顆 | C42: =u_ru_26 -> 0 | D42: =u_ru_27 -> 0.3 | E42: =u_ru_28*um28_B -> 1.6 | F42: =u_ru_28*(1+g29_ru)*um29_B -> 1.955
A43: NVIDIA Hopper（H200 等） | B43: 百萬顆 | C43: =u_hp_26 -> 0.5 | D43: =u_hp_27 -> 0 | E43: =u_hp_28*um28_B -> 0 | F43: =u_hp_28*(1+g29_hp)*um29_B -> 0
A44: AMD Instinct | B44: 百萬顆 | C44: =u_amd_26 -> 0.75 | D44: =u_amd_27 -> 1.5 | E44: =u_amd_28*um28_B -> 1.6 | F44: =u_amd_28*(1+g29_amd)*um29_B -> 1.955
A45: Google TPU | B45: 百萬顆 | C45: =u_tpu_26 -> 3.85 | D45: =u_tpu_27 -> 5.5 | E45: =u_tpu_28*um28_B -> 5.6 | F45: =u_tpu_28*(1+g29_tpu)*um29_B -> 6.8425
A46: AWS Trainium | B46: 百萬顆 | C46: =u_trn_26 -> 2 | D46: =u_trn_27 -> 2.5 | E46: =u_trn_28*um28_B -> 2.4 | F46: =u_trn_28*(1+g29_trn)*um29_B -> 2.9325
A47: 其他 ASIC（MTIA、Maia、Ascend 等） | B47: 百萬顆 | C47: =u_oth_26 -> 1 | D47: =u_oth_27 -> 4.5 | E47: =u_oth_28*um28_B -> 4 | F47: =u_oth_28*(1+g29_oth)*um29_B -> 4.8875
A48: 合計 | B48: 百萬顆 | C48: =SUM(C40:C47) -> 15.2 | D48: =SUM(D40:D47) -> 23.7 | E48: =SUM(E40:E47) -> 21.2 | F48: =SUM(F40:F47) -> 25.6275
A49: 金額（顆數 × 每顆售價）
A50: NVIDIA Blackwell（B200／B300） | B50: US$B | C50: =u_bw_26*(pm_bw) -> 218.16 | D50: =u_bw_27*(pm_bw) -> 96.96 | E50: =u_bw_28*um28_B*(pm_bw) -> 16.16 | F50: =u_bw_28*(1+g29_bw)*um29_B*(pm_bw) -> 8.585
A51: NVIDIA Rubin | B51: US$B | C51: =u_rb_26*(pm_rb) -> 93.5 | D51: =u_rb_27*(pm_rb) -> 385 | E51: =u_rb_28*um28_B*(pm_rb) -> 308 | F51: =u_rb_28*(1+g29_rb)*um29_B*(pm_rb) -> 376.3375
A52: NVIDIA Rubin Ultra | B52: US$B | C52: =u_ru_26*(pm_ru) -> 0 | D52: =u_ru_27*(pm_ru) -> 22.5 | E52: =u_ru_28*um28_B*(pm_ru) -> 120 | F52: =u_ru_28*(1+g29_ru)*um29_B*(pm_ru) -> 146.625
A53: NVIDIA Hopper（H200 等） | B53: US$B | C53: =u_hp_26*(pm_hp) -> 15 | D53: =u_hp_27*(pm_hp) -> 0 | E53: =u_hp_28*um28_B*(pm_hp) -> 0 | F53: =u_hp_28*(1+g29_hp)*um29_B*(pm_hp) -> 0
A54: AMD Instinct | B54: US$B | C54: =u_amd_26*(pa_amd) -> 22.5 | D54: =u_amd_27*(pa_amd) -> 45 | E54: =u_amd_28*um28_B*(pa_amd) -> 48 | F54: =u_amd_28*(1+g29_amd)*um29_B*(pa_amd) -> 58.65
A55: Google TPU | B55: US$B | C55: =u_tpu_26*(pa_tpu) -> 46.2 | D55: =u_tpu_27*(pa_tpu) -> 66 | E55: =u_tpu_28*um28_B*(pa_tpu) -> 67.2 | F55: =u_tpu_28*(1+g29_tpu)*um29_B*(pa_tpu) -> 82.11
A56: AWS Trainium | B56: US$B | C56: =u_trn_26*(pa_trn) -> 16 | D56: =u_trn_27*(pa_trn) -> 20 | E56: =u_trn_28*um28_B*(pa_trn) -> 19.2 | F56: =u_trn_28*(1+g29_trn)*um29_B*(pa_trn) -> 23.46
A57: 其他 ASIC（MTIA、Maia、Ascend 等） | B57: US$B | C57: =u_oth_26*(pa_oth) -> 8 | D57: =u_oth_27*(pa_oth) -> 36 | E57: =u_oth_28*um28_B*(pa_oth) -> 32 | F57: =u_oth_28*(1+g29_oth)*um29_B*(pa_oth) -> 39.1
A58: 合計 | B58: US$B | C58: =SUM(C50:C57) -> 419.36 | D58: =SUM(D50:D57) -> 671.46 | E58: =SUM(E50:E57) -> 610.56 | F58: =SUM(F50:F57) -> 734.8675
A59: 顆數份額
A60: NVIDIA | B60: % | C60: =(C40+C41+C42+C43)/C48 -> 0.5 | D60: =(D40+D41+D42+D43)/D48 -> 0.4092827 | E60: =(E40+E41+E42+E43)/E48 -> 0.35849057 | F60: =(F40+F41+F42+F43)/F48 -> 0.35157546
A61: AMD | B61: % | C61: =(C44)/C48 -> 0.049342105 | D61: =(D44)/D48 -> 0.063291139 | E61: =(E44)/E48 -> 0.075471698 | F61: =(F44)/F48 -> 0.07628524
A62: Google TPU | B62: % | C62: =(C45)/C48 -> 0.25328947 | D62: =(D45)/D48 -> 0.23206751 | E62: =(E45)/E48 -> 0.26415094 | F62: =(F45)/F48 -> 0.26699834
A63: AWS Trainium | B63: % | C63: =(C46)/C48 -> 0.13157895 | D63: =(D46)/D48 -> 0.10548523 | E63: =(E46)/E48 -> 0.11320755 | F63: =(F46)/F48 -> 0.11442786
A64: 其他 ASIC | B64: % | C64: =(C47)/C48 -> 0.065789474 | D64: =(D47)/D48 -> 0.18987342 | E64: =(E47)/E48 -> 0.18867925 | F64: =(F47)/F48 -> 0.1907131
A65: 金額份額
A66: NVIDIA | B66: % | C66: =(C50+C51+C52+C53)/C58 -> 0.77894887 | D66: =(D50+D51+D52+D53)/D58 -> 0.75128824 | E66: =(E50+E51+E52+E53)/E58 -> 0.72746331 | F66: =(F50+F51+F52+F53)/F58 -> 0.72332427
A67: AMD | B67: % | C67: =(C54)/C58 -> 0.053653186 | D67: =(D54)/D58 -> 0.06701814 | E67: =(E54)/E58 -> 0.078616352 | F67: =(F54)/F58 -> 0.079810306
A68: Google TPU | B68: % | C68: =(C55)/C58 -> 0.11016787 | D68: =(D55)/D58 -> 0.098293271 | E68: =(E55)/E58 -> 0.11006289 | F68: =(F55)/F58 -> 0.11173443
A69: AWS Trainium | B69: % | C69: =(C56)/C58 -> 0.038153377 | D69: =(D56)/D58 -> 0.02978584 | E69: =(E56)/E58 -> 0.031446541 | F69: =(F56)/F58 -> 0.031924122
A70: 其他 ASIC | B70: % | C70: =(C57)/C58 -> 0.019076688 | D70: =(D57)/D58 -> 0.053614512 | E70: =(E57)/E58 -> 0.052410901 | F70: =(F57)/F58 -> 0.053206871
A72: 情境 C：2028–29 顆數 ×0.6
A73: 顆數
A74: NVIDIA Blackwell（B200／B300） | B74: 百萬顆 | C74: =u_bw_26 -> 5.4 | D74: =u_bw_27 -> 2.4 | E74: =u_bw_28*um28_C -> 0.3 | F74: =u_bw_28*(1+g29_bw)*um29_C -> 0.15
A75: NVIDIA Rubin | B75: 百萬顆 | C75: =u_rb_26 -> 1.7 | D75: =u_rb_27 -> 7 | E75: =u_rb_28*um28_C -> 4.2 | F75: =u_rb_28*(1+g29_rb)*um29_C -> 4.83
A76: NVIDIA Rubin Ultra | B76: 百萬顆 | C76: =u_ru_26 -> 0 | D76: =u_ru_27 -> 0.3 | E76: =u_ru_28*um28_C -> 1.2 | F76: =u_ru_28*(1+g29_ru)*um29_C -> 1.38
A77: NVIDIA Hopper（H200 等） | B77: 百萬顆 | C77: =u_hp_26 -> 0.5 | D77: =u_hp_27 -> 0 | E77: =u_hp_28*um28_C -> 0 | F77: =u_hp_28*(1+g29_hp)*um29_C -> 0
A78: AMD Instinct | B78: 百萬顆 | C78: =u_amd_26 -> 0.75 | D78: =u_amd_27 -> 1.5 | E78: =u_amd_28*um28_C -> 1.2 | F78: =u_amd_28*(1+g29_amd)*um29_C -> 1.38
A79: Google TPU | B79: 百萬顆 | C79: =u_tpu_26 -> 3.85 | D79: =u_tpu_27 -> 5.5 | E79: =u_tpu_28*um28_C -> 4.2 | F79: =u_tpu_28*(1+g29_tpu)*um29_C -> 4.83
A80: AWS Trainium | B80: 百萬顆 | C80: =u_trn_26 -> 2 | D80: =u_trn_27 -> 2.5 | E80: =u_trn_28*um28_C -> 1.8 | F80: =u_trn_28*(1+g29_trn)*um29_C -> 2.07
A81: 其他 ASIC（MTIA、Maia、Ascend 等） | B81: 百萬顆 | C81: =u_oth_26 -> 1 | D81: =u_oth_27 -> 4.5 | E81: =u_oth_28*um28_C -> 3 | F81: =u_oth_28*(1+g29_oth)*um29_C -> 3.45
A82: 合計 | B82: 百萬顆 | C82: =SUM(C74:C81) -> 15.2 | D82: =SUM(D74:D81) -> 23.7 | E82: =SUM(E74:E81) -> 15.9 | F82: =SUM(F74:F81) -> 18.09
A83: 金額（顆數 × 每顆售價）
A84: NVIDIA Blackwell（B200／B300） | B84: US$B | C84: =u_bw_26*(pm_bw) -> 218.16 | D84: =u_bw_27*(pm_bw) -> 96.96 | E84: =u_bw_28*um28_C*(pm_bw) -> 12.12 | F84: =u_bw_28*(1+g29_bw)*um29_C*(pm_bw) -> 6.06
A85: NVIDIA Rubin | B85: US$B | C85: =u_rb_26*(pm_rb) -> 93.5 | D85: =u_rb_27*(pm_rb) -> 385 | E85: =u_rb_28*um28_C*(pm_rb) -> 231 | F85: =u_rb_28*(1+g29_rb)*um29_C*(pm_rb) -> 265.65
A86: NVIDIA Rubin Ultra | B86: US$B | C86: =u_ru_26*(pm_ru) -> 0 | D86: =u_ru_27*(pm_ru) -> 22.5 | E86: =u_ru_28*um28_C*(pm_ru) -> 90 | F86: =u_ru_28*(1+g29_ru)*um29_C*(pm_ru) -> 103.5
A87: NVIDIA Hopper（H200 等） | B87: US$B | C87: =u_hp_26*(pm_hp) -> 15 | D87: =u_hp_27*(pm_hp) -> 0 | E87: =u_hp_28*um28_C*(pm_hp) -> 0 | F87: =u_hp_28*(1+g29_hp)*um29_C*(pm_hp) -> 0
A88: AMD Instinct | B88: US$B | C88: =u_amd_26*(pa_amd) -> 22.5 | D88: =u_amd_27*(pa_amd) -> 45 | E88: =u_amd_28*um28_C*(pa_amd) -> 36 | F88: =u_amd_28*(1+g29_amd)*um29_C*(pa_amd) -> 41.4
A89: Google TPU | B89: US$B | C89: =u_tpu_26*(pa_tpu) -> 46.2 | D89: =u_tpu_27*(pa_tpu) -> 66 | E89: =u_tpu_28*um28_C*(pa_tpu) -> 50.4 | F89: =u_tpu_28*(1+g29_tpu)*um29_C*(pa_tpu) -> 57.96
A90: AWS Trainium | B90: US$B | C90: =u_trn_26*(pa_trn) -> 16 | D90: =u_trn_27*(pa_trn) -> 20 | E90: =u_trn_28*um28_C*(pa_trn) -> 14.4 | F90: =u_trn_28*(1+g29_trn)*um29_C*(pa_trn) -> 16.56
A91: 其他 ASIC（MTIA、Maia、Ascend 等） | B91: US$B | C91: =u_oth_26*(pa_oth) -> 8 | D91: =u_oth_27*(pa_oth) -> 36 | E91: =u_oth_28*um28_C*(pa_oth) -> 24 | F91: =u_oth_28*(1+g29_oth)*um29_C*(pa_oth) -> 27.6
A92: 合計 | B92: US$B | C92: =SUM(C84:C91) -> 419.36 | D92: =SUM(D84:D91) -> 671.46 | E92: =SUM(E84:E91) -> 457.92 | F92: =SUM(F84:F91) -> 518.73
A93: 顆數份額
A94: NVIDIA | B94: % | C94: =(C74+C75+C76+C77)/C82 -> 0.5 | D94: =(D74+D75+D76+D77)/D82 -> 0.4092827 | E94: =(E74+E75+E76+E77)/E82 -> 0.35849057 | F94: =(F74+F75+F76+F77)/F82 -> 0.35157546
A95: AMD | B95: % | C95: =(C78)/C82 -> 0.049342105 | D95: =(D78)/D82 -> 0.063291139 | E95: =(E78)/E82 -> 0.075471698 | F95: =(F78)/F82 -> 0.07628524
A96: Google TPU | B96: % | C96: =(C79)/C82 -> 0.25328947 | D96: =(D79)/D82 -> 0.23206751 | E96: =(E79)/E82 -> 0.26415094 | F96: =(F79)/F82 -> 0.26699834
A97: AWS Trainium | B97: % | C97: =(C80)/C82 -> 0.13157895 | D97: =(D80)/D82 -> 0.10548523 | E97: =(E80)/E82 -> 0.11320755 | F97: =(F80)/F82 -> 0.11442786
A98: 其他 ASIC | B98: % | C98: =(C81)/C82 -> 0.065789474 | D98: =(D81)/D82 -> 0.18987342 | E98: =(E81)/E82 -> 0.18867925 | F98: =(F81)/F82 -> 0.1907131
A99: 金額份額
A100: NVIDIA | B100: % | C100: =(C84+C85+C86+C87)/C92 -> 0.77894887 | D100: =(D84+D85+D86+D87)/D92 -> 0.75128824 | E100: =(E84+E85+E86+E87)/E92 -> 0.72746331 | F100: =(F84+F85+F86+F87)/F92 -> 0.72332427
A101: AMD | B101: % | C101: =(C88)/C92 -> 0.053653186 | D101: =(D88)/D92 -> 0.06701814 | E101: =(E88)/E92 -> 0.078616352 | F101: =(F88)/F92 -> 0.079810306
A102: Google TPU | B102: % | C102: =(C89)/C92 -> 0.11016787 | D102: =(D89)/D92 -> 0.098293271 | E102: =(E89)/E92 -> 0.11006289 | F102: =(F89)/F92 -> 0.11173443
A103: AWS Trainium | B103: % | C103: =(C90)/C92 -> 0.038153377 | D103: =(D90)/D92 -> 0.02978584 | E103: =(E90)/E92 -> 0.031446541 | F103: =(F90)/F92 -> 0.031924122
...

Sheet PL
A1: PL — NVIDIA 損益（US$B；FY2026A、FY2027 為實績與錨點，FY2028 起為模型，顆數用認列顆數＝市場層顆數 × k_rec）。FY(t)≈CY(t−1)。三情境各一個完整推導區塊（本頁下方），頂端為摘要。FY2027、FY2028 三情境幾乎相同（情境係數從 CY2028＝FY2029 才開始；FY2028 的差在 B、C 的 LPDDR 成本）
A3: 情境／項目 | B3: 單位 | C3: FY2026A | D3: FY2027 | E3: FY2028 | F3: FY2029 | G3: FY2030 | H3: 說明
A4: 情境 A
A5: 營收 | B5: US$B | C5: =C109 -> 215.938 | D5: =D109 -> 404.636 | E5: =E109 -> 689.42768 | F5: =F109 -> 771.17753 | G5: =G109 -> 863.69529
A6: 營收年增 | B6: % | D6: =D112 -> 0.87385268 | E6: =E112 -> 0.7038219 | F6: =F112 -> 0.1185764 | G6: =G112 -> 0.11996948
A7: Data Center | B7: US$B | C7: =C110 -> 193.7 | D7: =D110 -> 375.4568 | E7: =E110 -> 657.91414 | F7: =F110 -> 737.14291 | G7: =G110 -> 826.9379
A8: Edge Computing | B8: US$B | C8: =C111 -> 22.238 | D8: =D111 -> 29.179202 | E8: =E111 -> 31.513539 | F8: =F111 -> 34.034622 | G8: =G111 -> 36.757392
A9: 毛利率 | B9: % | C9: =C114 -> 0.71068084 | D9: =D114 -> 0.73686227 | E9: =E114 -> 0.68711022 | F9: =F114 -> 0.65325542 | G9: =G114 -> 0.66424828
A10: 營業利益 | B10: US$B | C10: =C117 -> 130.387 | D10: =D117 -> 262.996 | E10: =E117 -> 423.69787 | F10: =F117 -> 450.20261 | G10: =G117 -> 516.27853
A11: 營業利益率 | B11: % | C11: =C118 -> 0.60381684 | D11: =D118 -> 0.649957 | E11: =E118 -> 0.61456463 | F11: =F118 -> 0.58378595 | G11: =G118 -> 0.5977554
A12: 淨利（不含權益證券損益） | B12: US$B | C12: =C121 -> 112.49481 | D12: =D121 -> 219.76039 | E12: =E121 -> 352.66523 | F12: =F121 -> 374.66417 | G12: =G121 -> 429.50718
A13: EPS（不含權益證券損益） | B13: US$ | C13: =C123 -> 4.588909 | D13: =D123 -> 9.0597013 | E13: =E123 -> 14.715335 | F13: =F123 -> 15.823142 | G13: =G123 -> 18.359635
A14: EPS 年增 | B14: % | D14: =D124 -> 0.9742604 | E14: =E124 -> 0.62426274 | F14: =F124 -> 0.075282482 | G14: =G124 -> 0.16030275
A16: 情境 B
A17: 營收 | B17: US$B | C17: =C166 -> 215.938 | D17: =D166 -> 404.636 | E17: =E166 -> 688.816 | F17: =F166 -> 601.37015 | G17: =G166 -> 717.28393
A18: 營收年增 | B18: % | D18: =D169 -> 0.87385268 | E18: =E169 -> 0.70231023 | F18: =F169 -> -0.12695096 | G18: =G169 -> 0.19274947
A19: Data Center | B19: US$B | C19: =C167 -> 193.7 | D19: =D167 -> 375.4568 | E19: =E167 -> 657.30246 | F19: =F167 -> 567.33553 | G19: =G167 -> 680.52654
A20: Edge Computing | B20: US$B | C20: =C168 -> 22.238 | D20: =D168 -> 29.179202 | E20: =E168 -> 31.513539 | F20: =F168 -> 34.034622 | G20: =G168 -> 36.757392
A21: 毛利率 | B21: % | C21: =C171 -> 0.71068084 | D21: =D171 -> 0.73686227 | E21: =E171 -> 0.68860839 | F21: =F171 -> 0.71417524 | G21: =G171 -> 0.71565905
A22: 營業利益 | B22: US$B | C22: =C174 -> 130.387 | D22: =D174 -> 262.996 | E22: =E174 -> 424.34144 | F22: =F174 -> 377.00148 | G22: =G174 -> 454.77899
A23: 營業利益率 | B23: % | C23: =C175 -> 0.60381684 | D23: =D175 -> 0.649957 | E23: =E175 -> 0.61604469 | F23: =F175 -> 0.6269042 | G23: =G175 -> 0.63402925
A24: 淨利（不含權益證券損益） | B24: US$B | C24: =C178 -> 112.49481 | D24: =D178 -> 219.76039 | E24: =E178 -> 353.19939 | F24: =F178 -> 313.90723 | G24: =G178 -> 378.46256
A25: EPS（不含權益證券損益） | B25: US$ | C25: =C180 -> 4.588909 | D25: =D180 -> 9.0597013 | E25: =E180 -> 14.737624 | F25: =F180 -> 13.257202 | G25: =G180 -> 16.177692
A26: EPS 年增 | B26: % | D26: =D181 -> 0.9742604 | E26: =E181 -> 0.62672293 | F26: =F181 -> -0.10045184 | G26: =G181 -> 0.22029455
A28: 情境 C
A29: 營收 | B29: US$B | C29: =C223 -> 215.938 | D29: =D223 -> 404.636 | E29: =E223 -> 688.816 | F29: =F223 -> 452.37727 | G29: =G223 -> 508.58356
A30: 營收年增 | B30: % | D30: =D226 -> 0.87385268 | E30: =E226 -> 0.70231023 | F30: =F226 -> -0.34325384 | G30: =G226 -> 0.12424651
A31: Data Center | B31: US$B | C31: =C224 -> 193.7 | D31: =D224 -> 375.4568 | E31: =E224 -> 657.30246 | F31: =F224 -> 418.34264 | G31: =G224 -> 471.82617
A32: Edge Computing | B32: US$B | C32: =C225 -> 22.238 | D32: =D225 -> 29.179202 | E32: =E225 -> 31.513539 | F32: =F225 -> 34.034622 | G32: =G225 -> 36.757392
A33: 毛利率 | B33: % | C33: =C228 -> 0.71068084 | D33: =D228 -> 0.73686227 | E33: =E228 -> 0.68860839 | F33: =F228 -> 0.73915508 | G33: =G228 -> 0.74202794
A34: 營業利益 | B34: US$B | C34: =C231 -> 130.387 | D34: =D231 -> 262.996 | E34: =E231 -> 424.34144 | F34: =F231 -> 281.89476 | G34: =G231 -> 320.98858
A35: 營業利益率 | B35: % | C35: =C232 -> 0.60381684 | D35: =D232 -> 0.649957 | E35: =E232 -> 0.61604469 | F35: =F232 -> 0.62314086 | G35: =G232 -> 0.63114227
A36: 淨利（不含權益證券損益） | B36: US$B | C36: =C235 -> 112.49481 | D36: =D235 -> 219.76039 | E36: =E235 -> 353.19939 | F36: =F235 -> 234.96865 | G36: =G235 -> 267.41652
A37: EPS（不含權益證券損益） | B37: US$ | C37: =C237 -> 4.588909 | D37: =D237 -> 9.0597013 | E37: =E237 -> 14.737624 | F37: =F237 -> 9.9233999 | G37: =G237 -> 11.430938
A38: EPS 年增 | B38: % | D38: =D238 -> 0.9742604 | E38: =E238 -> 0.62672293 | F38: =F238 -> -0.32666216 | G38: =G238 -> 0.15191749
A40: 核對（應為 0）：FY2027 由下而上毛利率 − 錨點毛利率；FY2027 由下而上營收 − 錨點營收（k_rec、c_nh 校準恆等式）
A41: 情境 A：毛利率差 | D41: =D106-D114 -> 0
A42: 情境 A：營收差（US$B） | D42: =D104-a27_rev -> 0
A70: 情境 A：基準（顆數係數 1.0）
A71: 項目 | B71: 單位 | C71: FY2026A | D71: FY2027 | E71: FY2028 | F71: FY2029 | G71: FY2030 | H71: 說明
A72: A. 由下而上（C 欄空白；D＝FY2027≈CY2026 … G＝FY2030≈CY2029；顆數為「認列顆數」＝市場層顆數 × k_rec，FY2027 的 Data Center 營收與毛利率因此等於錨點，FY2028 起沿用 k_rec）
A73: NVIDIA 認列顆數乘數（k_rec × Sens 乘數） | B73: x | D73: =k_rec -> 0.82837092 | E73: =k_rec*1 -> 0.82837092 | F73: =k_rec*1 -> 0.82837092 | G73: =k_rec*1 -> 0.82837092
A74: NVIDIA Blackwell（B200／B300） 認列顆數 | B74: 百萬顆 | D74: =(u_bw_26)*D73 -> 4.473203 | E74: =(u_bw_27)*E73 -> 1.9880902 | F74: =(u_bw_28*um28_A)*F73 -> 0.41418546 | G74: =(u_bw_28*(1+g29_bw)*um29_A)*G73 -> 0.20709273
A75: NVIDIA Rubin 認列顆數 | B75: 百萬顆 | D75: =(u_rb_26)*D73 -> 1.4082306 | E75: =(u_rb_27)*E73 -> 5.7985965 | F75: =(u_rb_28*um28_A)*F73 -> 5.7985965 | G75: =(u_rb_28*(1+g29_rb)*um29_A)*G73 -> 6.6683859
A76: NVIDIA Rubin Ultra 認列顆數 | B76: 百萬顆 | D76: =(u_ru_26)*D73 -> 0 | E76: =(u_ru_27)*E73 -> 0.24851128 | F76: =(u_ru_28*um28_A)*F73 -> 1.6567418 | G76: =(u_ru_28*(1+g29_ru)*um29_A)*G73 -> 1.9052531
A77: NVIDIA Hopper（H200 等） 認列顆數 | B77: 百萬顆 | D77: =(u_hp_26)*D73 -> 0.41418546 | E77: =(u_hp_27)*E73 -> 0 | F77: =(u_hp_28*um28_A)*F73 -> 0 | G77: =(u_hp_28*(1+g29_hp)*um29_A)*G73 -> 0
A78: NVIDIA 認列顆數合計 | B78: 百萬顆 | D78: =SUM(D74:D77) -> 6.295619 | E78: =SUM(E74:E77) -> 8.0351979 | F78: =SUM(F74:F77) -> 7.8695238 | G78: =SUM(G74:G77) -> 8.7807318 | H78: 2026＝7.6、2027＝9.7、2028＝9.5（A）
A79: NVIDIA Blackwell（B200／B300） 每顆售價 | B79: US$K | D79: =1*(pm_bw+pcpu_bw+plp_bw+k_tray*pres_bw)+(1-abs_mem)*(gb_bw_26*hpx_bw*(hbm_A_26/hbm_A_26-1)/1000+plp_bw*(cdx_A_26/cdx_A_26-1)) -> 47.005555 | E79: =1*(pm_bw+pcpu_bw+plp_bw+k_tray*pres_bw)+(1-abs_mem)*(gb_bw_27*hpx_bw*(hbm_A_27/hbm_A_26-1)/1000+plp_bw*(cdx_A_27/cdx_A_26-1)) -> 49.186873 | F79: =1*(pm_bw+pcpu_bw+plp_bw+k_tray*pres_bw)+(1-abs_mem)*(gb_bw_28*hpx_bw*(hbm_A_28/hbm_A_26-1)/1000+plp_bw*(cdx_A_28/cdx_A_26-1)) -> 49.44753 | G79: =1*(pm_bw+pcpu_bw+plp_bw+k_tray*pres_bw)+(1-abs_mem)*(gb_bw_28*hpx_bw*(hbm_A_29/hbm_A_26-1)/1000+plp_bw*(cdx_A_29/cdx_A_26-1)) -> 49.054142 | H79: 基準價 ＋ (1−吸收比例) ×（HBM 與 LPDDR 相對 2026 的成本增加）
A80: NVIDIA Rubin 每顆售價 | B80: US$K | D80: =1*(pm_rb+pcpu_rb+plp_rb+k_tray*pres_rb)+(1-abs_mem)*(gb_rb_26*hpx_rb*(hbm_A_26/hbm_A_26-1)/1000+plp_rb*(cdx_A_26/cdx_A_26-1)) -> 72.166667 | E80: =1*(pm_rb+pcpu_rb+plp_rb+k_tray*pres_rb)+(1-abs_mem)*(gb_rb_27*hpx_rb*(hbm_A_27/hbm_A_26-1)/1000+plp_rb*(cdx_A_27/cdx_A_26-1)) -> 74.823972 | F80: =1*(pm_rb+pcpu_rb+plp_rb+k_tray*pres_rb)+(1-abs_mem)*(gb_rb_28*hpx_rb*(hbm_A_28/hbm_A_26-1)/1000+plp_rb*(cdx_A_28/cdx_A_26-1)) -> 74.942737 | G80: =1*(pm_rb+pcpu_rb+plp_rb+k_tray*pres_rb)+(1-abs_mem)*(gb_rb_28*hpx_rb*(hbm_A_29/hbm_A_26-1)/1000+plp_rb*(cdx_A_29/cdx_A_26-1)) -> 74.420676
A81: NVIDIA Rubin Ultra 每顆售價 | B81: US$K | D81: =1*(pm_ru+pcpu_ru+plp_ru+k_tray*pres_ru)+(1-abs_mem)*(gb_ru_26*hpx_ru*(hbm_A_26/hbm_A_26-1)/1000+plp_ru*(cdx_A_26/cdx_A_26-1)) -> 92.166667 | E81: =1*(pm_ru+pcpu_ru+plp_ru+k_tray*pres_ru)+(1-abs_mem)*(gb_ru_27*hpx_ru*(hbm_A_27/hbm_A_26-1)/1000+plp_ru*(cdx_A_27/cdx_A_26-1)) -> 99.740452 | F81: =1*(pm_ru+pcpu_ru+plp_ru+k_tray*pres_ru)+(1-abs_mem)*(gb_ru_28*hpx_ru*(hbm_A_28/hbm_A_26-1)/1000+plp_ru*(cdx_A_28/cdx_A_26-1)) -> 100.96543 | G81: =1*(pm_ru+pcpu_ru+plp_ru+k_tray*pres_ru)+(1-abs_mem)*(gb_ru_28*hpx_ru*(hbm_A_29/hbm_A_26-1)/1000+plp_ru*(cdx_A_29/cdx_A_26-1)) -> 99.83495
A82: NVIDIA Hopper（H200 等） 每顆售價 | B82: US$K | D82: =1*(pm_hp+pcpu_hp+plp_hp+k_tray*pres_hp)+(1-abs_mem)*(gb_hp_26*hpx_hp*(hbm_A_26/hbm_A_26-1)/1000+plp_hp*(cdx_A_26/cdx_A_26-1)) -> 30 | E82: =1*(pm_hp+pcpu_hp+plp_hp+k_tray*pres_hp)+(1-abs_mem)*(gb_hp_27*hpx_hp*(hbm_A_27/hbm_A_26-1)/1000+plp_hp*(cdx_A_27/cdx_A_26-1)) -> 30.8742 | F82: =1*(pm_hp+pcpu_hp+plp_hp+k_tray*pres_hp)+(1-abs_mem)*(gb_hp_28*hpx_hp*(hbm_A_28/hbm_A_26-1)/1000+plp_hp*(cdx_A_28/cdx_A_26-1)) -> 31.070895 | G82: =1*(pm_hp+pcpu_hp+plp_hp+k_tray*pres_hp)+(1-abs_mem)*(gb_hp_28*hpx_hp*(hbm_A_29/hbm_A_26-1)/1000+plp_hp*(cdx_A_29/cdx_A_26-1)) -> 30.962713
A83: NVIDIA Blackwell（B200／B300） 每顆 HBM 成本 | B83: US$K | D83: =gb_bw_26*hpx_bw*hbm_A_26/hbm_A_26/1000 -> 4.03 | E83: =gb_bw_27*hpx_bw*hbm_A_27/hbm_A_26/1000 -> 7.812 | F83: =gb_bw_28*hpx_bw*hbm_A_28/hbm_A_26/1000 -> 8.83872 | G83: =gb_bw_28*hpx_bw*hbm_A_29/hbm_A_26/1000 -> 8.396784 | H83: 容量 × 2026 合約價 × 情境別 HBM 價格指數（markets/memory）
A84: NVIDIA Rubin 每顆 HBM 成本 | B84: US$K | D84: =gb_rb_26*hpx_rb*hbm_A_26/hbm_A_26/1000 -> 4.8096 | E84: =gb_rb_27*hpx_rb*hbm_A_27/hbm_A_26/1000 -> 8.65728 | F84: =gb_rb_28*hpx_rb*hbm_A_28/hbm_A_26/1000 -> 9.523008 | G84: =gb_rb_28*hpx_rb*hbm_A_29/hbm_A_26/1000 -> 9.0468576
A85: NVIDIA Rubin Ultra 每顆 HBM 成本 | B85: US$K | D85: =gb_ru_26*hpx_ru*hbm_A_26/hbm_A_26/1000 -> 17.1008 | E85: =gb_ru_27*hpx_ru*hbm_A_27/hbm_A_26/1000 -> 30.78144 | F85: =gb_ru_28*hpx_ru*hbm_A_28/hbm_A_26/1000 -> 33.859584 | G85: =gb_ru_28*hpx_ru*hbm_A_29/hbm_A_26/1000 -> 32.166605
A86: NVIDIA Hopper（H200 等） 每顆 HBM 成本 | B86: US$K | D86: =gb_hp_26*hpx_hp*hbm_A_26/hbm_A_26/1000 -> 2.1855 | E86: =gb_hp_27*hpx_hp*hbm_A_27/hbm_A_26/1000 -> 3.9339 | F86: =gb_hp_28*hpx_hp*hbm_A_28/hbm_A_26/1000 -> 4.32729 | G86: =gb_hp_28*hpx_hp*hbm_A_29/hbm_A_26/1000 -> 4.1109255
A87: NVIDIA Blackwell（B200／B300） 每顆成本 | B87: US$K | D87: =1*c_nh*(pm_bw+pcpu_bw+plp_bw+k_tray*pres_bw)+D83+plp_bw*(cdx_A_26/cdx_A_26-1) -> 11.821282 | E87: =1*c_nh*(pm_bw+pcpu_bw+plp_bw+k_tray*pres_bw)+E83+plp_bw*(cdx_A_27/cdx_A_26-1) -> 16.493919 | F87: =1*c_nh*(pm_bw+pcpu_bw+plp_bw+k_tray*pres_bw)+F83+plp_bw*(cdx_A_28/cdx_A_26-1) -> 17.139233 | G87: =1*c_nh*(pm_bw+pcpu_bw+plp_bw+k_tray*pres_bw)+G83+plp_bw*(cdx_A_29/cdx_A_26-1) -> 16.352457 | H87: 非 HBM 成本（基準價 × c_nh，FY2027 校準）＋ HBM 成本 ＋ LPDDR 成本增加（每顆；顆數另乘 k_rec）
A88: NVIDIA Rubin 每顆成本 | B88: US$K | D88: =1*c_nh*(pm_rb+pcpu_rb+plp_rb+k_tray*pres_rb)+D84+plp_rb*(cdx_A_26/cdx_A_26-1) -> 16.771396 | E88: =1*c_nh*(pm_rb+pcpu_rb+plp_rb+k_tray*pres_rb)+E84+plp_rb*(cdx_A_27/cdx_A_26-1) -> 22.086007 | F88: =1*c_nh*(pm_rb+pcpu_rb+plp_rb+k_tray*pres_rb)+F84+plp_rb*(cdx_A_28/cdx_A_26-1) -> 22.323537 | G88: =1*c_nh*(pm_rb+pcpu_rb+plp_rb+k_tray*pres_rb)+G84+plp_rb*(cdx_A_29/cdx_A_26-1) -> 21.279415
A89: NVIDIA Rubin Ultra 每顆成本 | B89: US$K | D89: =1*c_nh*(pm_ru+pcpu_ru+plp_ru+k_tray*pres_ru)+D85+plp_ru*(cdx_A_26/cdx_A_26-1) -> 32.377644 | E89: =1*c_nh*(pm_ru+pcpu_ru+plp_ru+k_tray*pres_ru)+E85+plp_ru*(cdx_A_27/cdx_A_26-1) -> 47.525215 | F89: =1*c_nh*(pm_ru+pcpu_ru+plp_ru+k_tray*pres_ru)+F85+plp_ru*(cdx_A_28/cdx_A_26-1) -> 49.97516 | G89: =1*c_nh*(pm_ru+pcpu_ru+plp_ru+k_tray*pres_ru)+G85+plp_ru*(cdx_A_29/cdx_A_26-1) -> 47.71421
A90: NVIDIA Hopper（H200 等） 每顆成本 | B90: US$K | D90: =1*c_nh*(pm_hp+pcpu_hp+plp_hp+k_tray*pres_hp)+D86+plp_hp*(cdx_A_26/cdx_A_26-1) -> 7.1580712 | E90: =1*c_nh*(pm_hp+pcpu_hp+plp_hp+k_tray*pres_hp)+E86+plp_hp*(cdx_A_27/cdx_A_26-1) -> 8.9064712 | F90: =1*c_nh*(pm_hp+pcpu_hp+plp_hp+k_tray*pres_hp)+F86+plp_hp*(cdx_A_28/cdx_A_26-1) -> 9.2998612 | G90: =1*c_nh*(pm_hp+pcpu_hp+plp_hp+k_tray*pres_hp)+G86+plp_hp*(cdx_A_29/cdx_A_26-1) -> 9.0834967
A91: NVIDIA Blackwell（B200／B300） 運算營收 | B91: US$B | D91: =D74*D79 -> 210.26539 | E91: =E74*E79 -> 97.787941 | F91: =F74*F79 -> 20.480448 | G91: =G74*G79 -> 10.158756
A92: NVIDIA Rubin 運算營收 | B92: US$B | D92: =D75*D80 -> 101.62731 | E92: =E75*E80 -> 433.87402 | F92: =F75*F80 -> 434.56269 | G92: =G75*G80 -> 496.26579
A93: NVIDIA Rubin Ultra 運算營收 | B93: US$B | D93: =D76*D81 -> 0 | E93: =E76*E81 -> 24.786627 | F93: =F76*F81 -> 167.27364 | G93: =G76*G81 -> 190.21085
A94: NVIDIA Hopper（H200 等） 運算營收 | B94: US$B | D94: =D77*D82 -> 12.425564 | E94: =E77*E82 -> 0 | F94: =F77*F82 -> 0 | G94: =G77*G82 -> 0
A95: 運算營收（Σ 顆數 × 每顆售價） | B95: US$B | D95: =SUM(D91:D94) -> 324.31826 | E95: =SUM(E91:E94) -> 556.44859 | F95: =SUM(F91:F94) -> 622.31678 | G95: =SUM(G91:G94) -> 696.6354
A96: 運算成本 | B96: US$B | D96: =D74*D87+D75*D88+D76*D89+D77*D90 -> 79.461757 | E96: =E74*E87+E75*E88+E76*E89+E77*E90 -> 172.66979 | F96: =F74*F87+F75*F88+F76*F89+F77*F90 -> 219.33994 | G96: =G74*G87+G75*G88+G76*G89+G77*G90 -> 236.19347
A97: 其中 HBM 成本 | B97: US$B | D97: =D74*D83+D75*D84+D76*D85+D77*D86 -> 25.705236 | E97: =E74*E83+E75*E84+E76*E85+E77*E86 -> 73.380569 | F97: =F74*F83+F75*F84+F76*F85+F77*F86 -> 114.97754 | G97: =G74*G83+G75*G84+G76*G85+G77*G86 -> 123.35237
A98: 中國資料中心運算營收（基準為 0＝公司指引假設；Sens 列恢復） | B98: US$B | D98: =0 -> 0 | E98: =0 -> 0 | F98: =0 -> 0 | G98: =0 -> 0
A99: 中國部分成本（毛利率同運算） | B99: US$B | D99: =D98*D96/D95 -> 0 | E99: =E98*E96/E95 -> 0 | F99: =F98*F96/F95 -> 0 | G99: =G98*G96/G95 -> 0
A100: NVIDIA 網通營收（本模型歸屬 × 情境顆數係數 × 乘數） | B100: US$B | D100: =net_26*1*D73 -> 51.138539 | E100: =net_27*1*E73 -> 101.46555 | F100: =net_28*um28_A*F73 -> 114.82613 | G100: =net_29*um29_A*G73 -> 130.30251 | H100: markets/network；網通金額與 NVIDIA 顆數成正比
A101: 網通成本（c_net × 營收） | B101: US$B | D101: =c_net*D100 -> 15.341562 | E101: =c_net*E100 -> 30.439665 | F101: =c_net*F100 -> 34.447838 | G101: =c_net*G100 -> 39.090752
A102: Edge Computing 營收 | B102: US$B | D102: =a27_edge -> 29.179202 | E102: =D102*(1+eg) -> 31.513539 | F102: =E102*(1+eg) -> 34.034622 | G102: =F102*(1+eg) -> 36.757392
A103: Edge 成本 | B103: US$B | D103: =(1-gm_edge)*D102 -> 11.671681 | E103: =(1-gm_edge)*E102 -> 12.605415 | F103: =(1-gm_edge)*F102 -> 13.613849 | G103: =(1-gm_edge)*G102 -> 14.702957
A104: 由下而上營收合計 | B104: US$B | D104: =D95+D98+D100+D102 -> 404.636 | E104: =E95+E98+E100+E102 -> 689.42768 | F104: =F95+F98+F100+F102 -> 771.17753 | G104: =G95+G98+G100+G102 -> 863.69529
A105: 由下而上成本合計 | B105: US$B | D105: =D96+D99+D101+D103 -> 106.475 | E105: =E96+E99+E101+E103 -> 215.71487 | F105: =F96+F99+F101+F103 -> 267.40163 | G105: =G96+G99+G101+G103 -> 289.98718
A106: 由下而上毛利率 | B106: % | D106: =1-D105/D104 -> 0.73686227 | E106: =1-E105/E104 -> 0.68711022 | F106: =1-F105/F104 -> 0.65325542 | G106: =1-G105/G104 -> 0.66424828 | H106: FY2027 ＝ 錨點毛利率（c_nh 校準的恆等式，非獨立檢驗；對照區塊 k_rec＝1 時用 c_nh_p）
A107: HBM 成本占由下而上營收 | B107: % | D107: =D97/D104 -> 0.063526814 | E107: =E97/E104 -> 0.10643693 | F107: =F97/F104 -> 0.14909348 | G107: =G97/G104 -> 0.14281932
A108: B. 報告值（FY2026A、FY2027 為實績與錨點；FY2028 起為由下而上）
A109: 營收 | B109: US$B | C109: =a26_rev -> 215.938 | D109: =a27_rev -> 404.636 | E109: =E104 -> 689.42768 | F109: =F104 -> 771.17753 | G109: =G104 -> 863.69529
A110: Data Center（運算＋網通＋中國） | B110: US$B | C110: =a26_dc -> 193.7 | D110: =a27_dc -> 375.4568 | E110: =E95+E98+E100 -> 657.91414 | F110: =F95+F98+F100 -> 737.14291 | G110: =G95+G98+G100 -> 826.9379
A111: Edge Computing | B111: US$B | C111: =a26_edge -> 22.238 | D111: =a27_edge -> 29.179202 | E111: =E102 -> 31.513539 | F111: =F102 -> 34.034622 | G111: =G102 -> 36.757392
A112: 營收年增 | B112: % | D112: =D109/C109-1 -> 0.87385268 | E112: =E109/D109-1 -> 0.7038219 | F112: =F109/E109-1 -> 0.1185764 | G112: =G109/F109-1 -> 0.11996948
A113: 毛利 | B113: US$B | C113: =a26_gp -> 153.463 | D113: =a27_gp -> 298.161 | E113: =E109-E105 -> 473.71281 | F113: =F109-F105 -> 503.7759 | G113: =G109-G105 -> 573.70811
A114: 毛利率 | B114: % | C114: =C113/C109 -> 0.71068084 | D114: =D113/D109 -> 0.73686227 | E114: =E113/E109 -> 0.68711022 | F114: =F113/F109 -> 0.65325542 | G114: =G113/G109 -> 0.66424828
A115: 營業費用（基準路徑） | B115: US$B | C115: =a26_opx -> 23.076 | D115: =a27_opx -> 35.165 | E115: =D115*(1+MAX(g_opx_min,phi*E112)) -> 50.014938 | F115: =E115*(1+MAX(g_opx_min,phi*F112)) -> 53.573293 | G115: =F115*(1+MAX(g_opx_min,phi*G112)) -> 57.429589 | H115: 前一年 ×（1＋MAX(下限, 彈性 × 營收年增)）
A116: 營業費用 | B116: US$B | C116: =C115 -> 23.076 | D116: =D115 -> 35.165 | E116: =E115+0*E109 -> 50.014938 | F116: =F115+0*F109 -> 53.573293 | G116: =G115+0*G109 -> 57.429589
A117: 營業利益 | B117: US$B | C117: =C113-C116 -> 130.387 | D117: =D113-D116 -> 262.996 | E117: =E113-E116 -> 423.69787 | F117: =F113-F116 -> 450.20261 | G117: =G113-G116 -> 516.27853
A118: 營業利益率 | B118: % | C118: =C117/C109 -> 0.60381684 | D118: =D117/D109 -> 0.649957 | E118: =E117/E109 -> 0.61456463 | F118: =F117/F109 -> 0.58378595 | G118: =G117/G109 -> 0.5977554
A119: 其他收益淨額（不含權益證券損益） | B119: US$B | C119: =a26_oth -> 2.145 | D119: =a27_oth -> 1.133 | E119: =oth_f -> 1.2 | F119: =oth_f -> 1.2 | G119: =oth_f -> 1.2
A120: 有效稅率 | B120: % | C120: =1-a26_ni/(a26_oi+a26_oth) -> 0.15118757 | D120: =a27_etr -> 0.16798084 | E120: =tx_f -> 0.17 | F120: =tx_f -> 0.17 | G120: =tx_f -> 0.17
A121: 淨利（不含權益證券損益） | B121: US$B | C121: =a26_ni -> 112.49481 | D121: =a27_ni -> 219.76039 | E121: =(E117+E119)*(1-E120) -> 352.66523 | F121: =(F117+F119)*(1-F120) -> 374.66417 | G121: =(G117+G119)*(1-G120) -> 429.50718
A122: 稀釋股數 | B122: 十億股 | C122: =a26_sh -> 24.5145 | D122: =a27_sh -> 24.256913 | E122: =D122*(1+sh_g) -> 23.96583 | F122: =E122*(1+sh_g) -> 23.67824 | G122: =F122*(1+sh_g) -> 23.394102
A123: EPS（不含權益證券損益） | B123: US$ | C123: =C121/C122 -> 4.588909 | D123: =D121/D122 -> 9.0597013 | E123: =E121/E122 -> 14.715335 | F123: =F121/F122 -> 15.823142 | G123: =G121/G122 -> 18.359635
A124: EPS 年增 | B124: % | D124: =D123/C123-1 -> 0.9742604 | E124: =E123/D123-1 -> 0.62426274 | F124: =F123/E123-1 -> 0.075282482 | G124: =G123/F123-1 -> 0.16030275
A127: 情境 B：CY2028 顆數 ×0.8、CY2029 ×0.85
A128: 項目 | B128: 單位 | C128: FY2026A | D128: FY2027 | E128: FY2028 | F128: FY2029 | G128: FY2030 | H128: 說明
A129: A. 由下而上（C 欄空白；D＝FY2027≈CY2026 … G＝FY2030≈CY2029；顆數為「認列顆數」＝市場層顆數 × k_rec，FY2027 的 Data Center 營收與毛利率因此等於錨點，FY2028 起沿用 k_rec）
A130: NVIDIA 認列顆數乘數（k_rec × Sens 乘數） | B130: x | D130: =k_rec -> 0.82837092 | E130: =k_rec*1 -> 0.82837092 | F130: =k_rec*1 -> 0.82837092 | G130: =k_rec*1 -> 0.82837092
A131: NVIDIA Blackwell（B200／B300） 認列顆數 | B131: 百萬顆 | D131: =(u_bw_26)*D130 -> 4.473203 | E131: =(u_bw_27)*E130 -> 1.9880902 | F131: =(u_bw_28*um28_B)*F130 -> 0.33134837 | G131: =(u_bw_28*(1+g29_bw)*um29_B)*G130 -> 0.17602882
A132: NVIDIA Rubin 認列顆數 | B132: 百萬顆 | D132: =(u_rb_26)*D130 -> 1.4082306 | E132: =(u_rb_27)*E130 -> 5.7985965 | F132: =(u_rb_28*um28_B)*F130 -> 4.6388772 | G132: =(u_rb_28*(1+g29_rb)*um29_B)*G130 -> 5.668128
A133: NVIDIA Rubin Ultra 認列顆數 | B133: 百萬顆 | D133: =(u_ru_26)*D130 -> 0 | E133: =(u_ru_27)*E130 -> 0.24851128 | F133: =(u_ru_28*um28_B)*F130 -> 1.3253935 | G133: =(u_ru_28*(1+g29_ru)*um29_B)*G130 -> 1.6194652
...

Sheet Val
A1: Val — P/E 估值（美元）。結論用「現價 ÷ FY2028 EPS（模型與共識）」；10 年落後 P/E 規則值不適用（保留計算，不進結論）。跨公司規則：合理倍數＝10 年（FY2016–FY2025 年底）P/E 的分位，依循環位置：見頂年 25 分位、中段中位數、谷底 75 分位。NVIDIA 的 FY(t) 對照日曆年 t−1，循環位置用共用規則的 lag 包裝（tools/cycle_position.py classify_lag），見頂年度讀設備市場模型
A2: 不適用的理由：歷史倍數是「會計年度年底價 ÷ 該年度（剛結束）GAAP 稀釋 EPS」＝落後（trailing）倍數；規則把它乘在 FY2028 EPS 上，得到的是約 2028-01 的價格（距 2026-10-22 約 1.27 年，未折現；折現值另列）。歷史倍數含高成長期的高估值（FY2023 因 EPS 低谷達 114x），規則值遠高於現價——見下方「What must be true」
A3: 0. 目標價（DCF 與 Comparable 加權；v0.2 新增，Andy 2026-10-25）
A4: 0.1 DCF（股東權益現金流，FY2027–FY2032 明確期＋FY2032 後永續）
A5: 項目 | B5: A | C5: B | D5: C | E5: 說明 | F5: 折現年數 t | G5: 期內占比（基準日後）
A6: 情境 EPS（FY2027–FY2032） | E6: 引用 PL 頁延伸表（上游結束後為收斂法）；三情境欄 B／C／D＝A／B／C
A7: FY2027 | B7: =PL!D307 -> 9.0597013 | C7: =PL!D316 -> 9.0597013 | D7: =PL!D325 -> 9.0597013 | F7: 0.083333 | G7: 0.083333
A8: FY2028 | B8: =PL!E307 -> 14.715335 | C8: =PL!E316 -> 14.737624 | D8: =PL!E325 -> 14.737624 | F8: 1.083333 | G8: 1
A9: FY2029 | B9: =PL!F307 -> 15.823142 | C9: =PL!F316 -> 13.257202 | D9: =PL!F325 -> 9.9233999 | F9: 2.083333 | G9: 1
A10: FY2030 | B10: =PL!G307 -> 18.359635 | C10: =PL!G316 -> 16.177692 | D10: =PL!G325 -> 11.430938 | F10: 3.083333 | G10: 1
A11: FY2031 | B11: =PL!H307 -> 20.25478 | C11: =PL!H316 -> 16.410353 | D11: =PL!H325 -> 9.8799271 | F11: 4.083333 | G11: 1
A12: FY2032 | B12: =PL!I307 -> 21.730837 | C12: =PL!I316 -> 15.306297 | D12: =PL!I325 -> 7.5938682 | F12: 5.083333 | G12: 1
A13: 股東現金流＝EPS ×（1 − tp_g ÷ tp_roe） | B13: =1-MIN(0.8,tp_g/tp_roe) -> 0.94946304 | E13: B 欄＝可發放比例（1 − 再投資率；再投資率＝tp_g ÷ tp_roe，上限 0.8）；下列六列＝EPS × 可發放比例 × 期內占比
A14: FY2027 股東現金流 | B14: =B7*$B$13*$G$7 -> 0.7168181 | C14: =C7*$B$13*$G$7 -> 0.7168181 | D14: =D7*$B$13*$G$7 -> 0.7168181
A15: FY2028 股東現金流 | B15: =B8*$B$13*$G$8 -> 13.971667 | C15: =C8*$B$13*$G$8 -> 13.992829 | D15: =D8*$B$13*$G$8 -> 13.992829
A16: FY2029 股東現金流 | B16: =B9*$B$13*$G$9 -> 15.023489 | C16: =C9*$B$13*$G$9 -> 12.587224 | D16: =D9*$B$13*$G$9 -> 9.4219014
A17: FY2030 股東現金流 | B17: =B10*$B$13*$G$10 -> 17.431795 | C17: =C10*$B$13*$G$10 -> 15.36012 | D17: =D10*$B$13*$G$10 -> 10.853253
A18: FY2031 股東現金流 | B18: =B11*$B$13*$G$11 -> 19.231165 | C18: =C11*$B$13*$G$11 -> 15.581023 | D18: =D11*$B$13*$G$11 -> 9.3806257
A19: FY2032 股東現金流 | B19: =B12*$B$13*$G$12 -> 20.632626 | C19: =C12*$B$13*$G$12 -> 14.532764 | D19: =D12*$B$13*$G$12 -> 7.2100972
A20: 永續價值（FY2032 年底；FY2032 現金流 ×(1＋tp_g) ÷ (tp_r − tp_g)） | B20: =B19*(1+tp_g)/(tp_r-tp_g) -> 357.63219 | C20: =C19*(1+tp_g)/(tp_r-tp_g) -> 251.90124 | D20: =D19*(1+tp_g)/(tp_r-tp_g) -> 124.97502
A21: DCF 情境每股價值（折現率 tp_r） | B21: =MAX(0,B14/(1+tp_r)^$F$7+B15/(1+tp_r)^$F$8+B16/(1+tp_r)^$F$9+B17/(1+tp_r)^$F$10+B18/(1+tp_r)^$F$11+B19/(1+tp_r)^$F$12+B20/(1+tp_r)^$F$12) -> 284.66906 | C21: =MAX(0,C14/(1+tp_r)^$F$7+C15/(1+tp_r)^$F$8+C16/(1+tp_r)^$F$9+C17/(1+tp_r)^$F$10+C18/(1+tp_r)^$F$11+C19/(1+tp_r)^$F$12+C20/(1+tp_r)^$F$12) -> 209.78428 | D21: =MAX(0,D14/(1+tp_r)^$F$7+D15/(1+tp_r)^$F$8+D16/(1+tp_r)^$F$9+D17/(1+tp_r)^$F$10+D18/(1+tp_r)^$F$11+D19/(1+tp_r)^$F$12+D20/(1+tp_r)^$F$12) -> 116.92972 | E21: 基準日 2026 年底；明確期現金流與永續價值依 F 欄年數折現；小於 0 時取 0（Andy 2026-10-25 12:22）
A22: 其中：永續價值現值占比 | B22: =B20/(1+tp_r)^$F$12/B21 -> 0.77389766 | C22: =C20/(1+tp_r)^$F$12/C21 -> 0.73968116 | D22: =D20/(1+tp_r)^$F$12/D21 -> 0.65839346
A23: DCF 目標價（情境加權） | B23: =(tp_wA*B21+tp_wB*C21+tp_wC*D21)*(1+tp_r) -> 235.04668 | E23: Σ 權重 × 情境價值 ×(1＋tp_r)：推到約 12 個月後
A25: 0.2 Comparable（市場主流同業前瞻 P/E）
A26: 同業與前瞻 P/E | B26: 代號 | C26: 前瞻 12 月 P/E | D26: 日期 | E26: 來源 | F26: 標記
A27: AMD | B27: AMD | C27: 46.49 | D27: 2026-10-23 | E27: stockanalysis.com 統計頁（Forward PE） | F27: Interested-party（資料商彙整賣方預估）
A28: Broadcom | B28: AVGO | C28: 18.52 | D28: 2026-10-23 | E28: 同上 | F28: Interested-party（同上）
A29: Marvell | B29: MRVL | C29: 40.44 | D29: 2026-10-23 | E29: 同上 | F29: Interested-party（同上）
A30: 台積電 ADR | B30: TSM | C30: 19.61 | D30: 2026-10-23 | E30: 同上 | F30: Interested-party（同上）
A31: Qualcomm | B31: QCOM | C31: 18.98 | D31: 2026-10-23 | E31: 同上 | F31: Interested-party（同上）
A32: 同業選擇 | E32: 券商常用的 AI 運算／半導體大型股同業（GPU、客製 ASIC、代工、手機 SoC）；不含 A 股（Andy 11:53）。前瞻 P/E 口徑為資料商的未來 12 個月共識 EPS，各家 GAAP／non-GAAP 口徑不一
A33: 同業前瞻 P/E 中位數 | B33: =MEDIAN(C27:C31) -> 19.61
A34: 各情境 12 個月後的前瞻 EPS | B34: =0.25*PL!E307+0.75*PL!F307 -> 15.54619 | C34: =0.25*PL!E316+0.75*PL!F316 -> 13.627308 | D34: =0.25*PL!E325+0.75*PL!F325 -> 11.126956 | E34: 會計年度 FY(t)＝t−1 年 2 月～t 年 1 月：約 12 個月後（2027-10 底）的未來 12 個月＝2027-11～2028-10＝FY2028 的 3 個月＋FY2029 的 9 個月（3/12 × FY2028＋9/12 × FY2029）
A35: 12 個月後的前瞻 EPS（情境加權） | B35: =tp_wA*B34+tp_wB*C34+tp_wC*D34 -> 13.702902
A36: Comparable 目標價 | B36: =B33*B35 -> 268.71391 | E36: 同業前瞻 P/E 中位數 × 12 個月後的前瞻 EPS（情境加權）
A38: 0.3 結論
A39: 項目 | B39: 數值 | C39: 對照 | D39: 對照 | E39: 說明
A40: 目標價（DCF 與 Comparable 加權） | B40: =tp_w_dcf*B23+(1-tp_w_dcf)*B36 -> 251.8803 | E40: ="DCF 權重 "&TEXT(tp_w_dcf,"0%")&"、Comparable 權重 "&TEXT(1-tp_w_dcf,"0%")&"（In 頁 tp_w_dcf，Andy 可改）" -> DCF 權重 50%、Comparable 權重 50%（In 頁 tp_w_dcf，Andy 可改）
A41: Comparable 目標價（市場主流同業法） | B41: =B36 -> 268.71391
A42: 市場共識目標價 | B42: =cons_tp -> 328.95 | E42: stockanalysis.com：62 位分析師平均目標價（2026-10-25 頁面）；Interested-party
A43: 上檔空間：加權目標價 | B43: =B40/px-1 -> 0.19397183
A44: 上檔空間：Comparable 目標價 | B44: =B41/px-1 -> 0.27376712
A45: 與市場共識目標價的差距：EPS 因素 | B45: =(tp_wA*PL!E307+tp_wB*PL!E316+tp_wC*PL!E325)/C45-1 -> -0.074108281 | C45: =cons_eps28 -> 15.91 | E45: B＝我們的前瞻 EPS（情境加權）÷ 共識前瞻 EPS − 1；C＝共識前瞻 EPS（共識 FY2028 EPS（In 頁 cons_eps28；FY2029 共識未找到，故 EPS 因素以 FY2028 同年度比較：B＝情境加權 FY2028 EPS ÷ 共識 − 1））
A46: 與市場共識目標價的差距：倍數因素 | B46: =C46/B33-1 -> 0.054343482 | C46: =B42/C45 -> 20.675676 | D46: =B33 -> 19.61 | E46: C＝市場共識目標價 ÷ 共識前瞻 EPS 隱含的倍數；D＝同業中位數；B＝C ÷ D − 1
A47: 價格帶（DCF 不如預期～順利） | B47: =D21*(1+tp_r) -> 128.62269 | C47: =B21*(1+tp_r) -> 313.13596 | E47: B＝C 情境 DCF 價值、C＝A 情境 DCF 價值（皆推到 12 個月後）
A48: 檢查用：現價 ÷ 各情境 FY2028 EPS | B48: =px/PL!E307 -> 14.336065 | C48: =px/PL!E316 -> 14.314384 | D48: =px/PL!E325 -> 14.314384
A49: 歷史倍數檢查：現價隱含 P/E 的十年分位（A／B／C） | B49: =IF(B48<MIN(B126:B135),0,IF(B48>MAX(B126:B135),1,PERCENTRANK(B126:B135,B48))) -> 0 | C49: =IF(C48<MIN(B126:B135),0,IF(C48>MAX(B126:B135),1,PERCENTRANK(B126:B135,C48))) -> 0 | D49: =IF(D48<MIN(B126:B135),0,IF(D48>MAX(B126:B135),1,PERCENTRANK(B126:B135,D48))) -> 0 | E49: 上一列在 2016–2025 年底 P/E 分布（Val!B126:B135）的分位（PERCENTRANK；低於最小＝0、高於最大＝1）；只作檢查，不進目標價
A50: 目標價方法 | B50: DCF：股東現金流＝EPS ×（1 − tp_g ÷ tp_roe），tp_r 10%、tp_g 4%、tp_roe 近三年平均 79%（再投資率約 5%）；基準日 2026 年底，FY2027 只計 2027-01 一個月，FY2032 後永續。Comparable：AMD、Broadcom、Marvell、台積電 ADR、Qualcomm 前瞻 P/E 中位數 × 12 個月後前瞻 EPS。偏誤方向：C 情境 FY2031 起淨利率收斂到十年平均 31%（低於近年 55% 以上），偏保守；FY2028 三情境 EPS 幾乎相同，情境差主要來自 FY2029 起；永續價值占 DCF 價值過半，對 tp_r、tp_g 敏感（Sens 頁）。
A51: 檢查：情境權重合計（應為 1） | B51: =ROUND(tp_wA+tp_wB+tp_wC,6) -> 1
A55: 1. 價格與市場隱含倍數
A56: 項目 | B56: A | C56: B | D56: C | E56: 說明
A57: 現價（2026-10-23 收盤） | B57: =px -> 210.96
A58: 現價 ÷ FY2028 EPS（模型） | B58: =px/PL!E13 -> 14.336065 | C58: =px/PL!E25 -> 14.314384 | D58: =px/PL!E37 -> 14.314384 | E58: FY2028 EPS 三情境幾乎相同（情境係數從 FY2029 才開始；差在 B、C 的 LPDDR 成本），故 A、B、C 的 FY2028 倍數相近
A59: 現價 ÷ FY2029 EPS（模型） | B59: =px/PL!F13 -> 13.332371 | C59: =px/PL!F25 -> 15.91286 | D59: =px/PL!F37 -> 21.258843
A60: 現價 ÷ 共識 FY2028 EPS | B60: =px/cons_eps28 -> 13.259585 | E60: 共識 EPS 為新 non-GAAP 口徑（含 SBC），與本模型口徑近似（Q 頁檢查列）
A61: 命題：現價約為「2027 年 EPS」的倍數（工作單：13.5x；2027 年＝FY2028） | B61: =th_mult -> 13.5
A63: 2. 循環位置（共用規則的 lag 版）與規則倍數
A64: 規則：各情境見頂年度（日曆年）取自設備市場模型（Mkt 頁「見頂年度」：A 2029、B 2028、C 2027）；NVIDIA 的 FY(t) 對照日曆年 t−1：t−1 早於見頂年＝中段（中位數）、等於＝見頂（25 分位）、晚於＝谷底（75 分位）。擁有者 2026-10-23 核准：FY2028 在 A、B 為中段，C 為見頂。
A65: 情境 | B65: 設備市場見頂年度（CY） | C65: FY2028 對照 CY | D65: FY2028 判定 | E65: FY2028 倍數 | F65: FY2029 對照 CY | G65: FY2029 判定 | H65: FY2029 倍數 | I65: 規則
A66: A | B66: =pk_A -> 2029 | C66: =2028-1 -> 2027 | D66: =IF((2028-1)<pk_A,"中段",IF((2028-1)=pk_A,"見頂","谷底")) -> 中段 | E66: =IF(D66="見頂",pe_peak,IF(D66="谷底",pe_trough,pe_mid)) -> 51.61 | F66: =2029-1 -> 2028 | G66: =IF((2029-1)<pk_A,"中段",IF((2029-1)=pk_A,"見頂","谷底")) -> 中段 | H66: =IF(G66="見頂",pe_peak,IF(G66="谷底",pe_trough,pe_mid)) -> 51.61 | I66: tools/cycle_position.py classify_lag（lag＝1）
A67: B | B67: =pk_B -> 2028 | C67: =2028-1 -> 2027 | D67: =IF((2028-1)<pk_B,"中段",IF((2028-1)=pk_B,"見頂","谷底")) -> 中段 | E67: =IF(D67="見頂",pe_peak,IF(D67="谷底",pe_trough,pe_mid)) -> 51.61 | F67: =2029-1 -> 2028 | G67: =IF((2029-1)<pk_B,"中段",IF((2029-1)=pk_B,"見頂","谷底")) -> 見頂 | H67: =IF(G67="見頂",pe_peak,IF(G67="谷底",pe_trough,pe_mid)) -> 42.09 | I67: tools/cycle_position.py classify_lag（lag＝1）
A68: C | B68: =pk_C -> 2027 | C68: =2028-1 -> 2027 | D68: =IF((2028-1)<pk_C,"中段",IF((2028-1)=pk_C,"見頂","谷底")) -> 見頂 | E68: =IF(D68="見頂",pe_peak,IF(D68="谷底",pe_trough,pe_mid)) -> 42.09 | F68: =2029-1 -> 2028 | G68: =IF((2029-1)<pk_C,"中段",IF((2029-1)=pk_C,"見頂","谷底")) -> 谷底 | H68: =IF(G68="見頂",pe_peak,IF(G68="谷底",pe_trough,pe_mid)) -> 63.4 | I68: tools/cycle_position.py classify_lag（lag＝1）
A70: 對照欄（只作對照，不當主值）：以 NVIDIA 本模型營收路徑自己的見頂年判斷循環位置
A71: 情境 | B71: 營收見頂 FY（FY2027–FY2030 內） | C71: 對照 CY | D71: FY2028 判定 | E71: FY2028 倍數 | F71: 觀測期是否截尾 | G71: 說明
A72: A | B72: =INDEX({2027,2028,2029,2030},MATCH(MAX(PL!D109:G109),PL!D109:G109,0)) -> 2030 | C72: =B72-1 -> 2029 | D72: =IF((2028-1)<C72,"中段",IF((2028-1)=C72,"見頂","谷底")) -> 中段 | E72: =IF(D72="見頂",pe_peak,IF(D72="谷底",pe_trough,pe_mid)) -> 51.61 | F72: =IF(B72=2030,"是：營收到觀測期末仍在增加，見頂年未知","否") -> 是：營收到觀測期末仍在增加，見頂年未知 | G72: FY(t) 對照 CY t−1；以本模型營收最大的會計年度為見頂
A73: B | B73: =INDEX({2027,2028,2029,2030},MATCH(MAX(PL!D166:G166),PL!D166:G166,0)) -> 2030 | C73: =B73-1 -> 2029 | D73: =IF((2028-1)<C73,"中段",IF((2028-1)=C73,"見頂","谷底")) -> 中段 | E73: =IF(D73="見頂",pe_peak,IF(D73="谷底",pe_trough,pe_mid)) -> 51.61 | F73: =IF(B73=2030,"是：營收到觀測期末仍在增加，見頂年未知","否") -> 是：營收到觀測期末仍在增加，見頂年未知 | G73: 同上
A74: C | B74: =INDEX({2027,2028,2029,2030},MATCH(MAX(PL!D223:G223),PL!D223:G223,0)) -> 2028 | C74: =B74-1 -> 2027 | D74: =IF((2028-1)<C74,"中段",IF((2028-1)=C74,"見頂","谷底")) -> 見頂 | E74: =IF(D74="見頂",pe_peak,IF(D74="谷底",pe_trough,pe_mid)) -> 42.09 | F74: =IF(B74=2030,"是：營收到觀測期末仍在增加，見頂年未知","否") -> 否 | G74: 同上
A76: 3. 規則值隱含股價（美元）——不適用：落後倍數含高成長期溢價，保留計算但不進結論；規則值＝FY2028 EPS × 依循環位置的倍數
A77: 情境 | B77: EPS 年度 | C77: EPS | D77: 倍數類型 | E77: 倍數 | F77: 隱含股價（不適用；約 FY2028 年底，未折現） | G77: 相對現價 | H77: 折現到現在
A78: A | B78: FY2028 | C78: =PL!E13 -> 14.715335 | D78: ="規則值（不適用）："&D66 -> 規則值（不適用）：中段 | E78: =E66 -> 51.61 | F78: =C78*E78 -> 759.45845 | G78: =F78/px-1 -> 2.6000116 | H78: =F78/(1+r_disc)^(1.27+0) -> 672.87642
A79: A | B79: FY2028 | C79: =PL!E13 -> 14.715335 | D79: 參考：25 分位 | E79: =pe_peak -> 42.09 | F79: =C79*E79 -> 619.36846 | G79: =F79/px-1 -> 1.9359521 | H79: =F79/(1+r_disc)^(1.27+0) -> 548.75738
A80: A | B80: FY2028 | C80: =PL!E13 -> 14.715335 | D80: 參考：中位數 | E80: =pe_mid -> 51.61 | F80: =C80*E80 -> 759.45845 | G80: =F80/px-1 -> 2.6000116 | H80: =F80/(1+r_disc)^(1.27+0) -> 672.87642
A81: A | B81: FY2028 | C81: =PL!E13 -> 14.715335 | D81: 參考：75 分位 | E81: =pe_trough -> 63.4 | F81: =C81*E81 -> 932.95226 | G81: =F81/px-1 -> 3.422413 | H81: =F81/(1+r_disc)^(1.27+0) -> 826.59107
A82: A | B82: FY2029 | C82: =PL!F13 -> 15.823142 | D82: ="規則值（FY2029；不適用）："&G66 -> 規則值（FY2029；不適用）：中段 | E82: =H66 -> 51.61 | F82: =C82*E82 -> 816.63237 | G82: =F82/px-1 -> 2.8710294 | H82: =F82/(1+r_disc)^(1.27+1) -> 657.75657
A83: B | B83: FY2028 | C83: =PL!E25 -> 14.737624 | D83: ="規則值（不適用）："&D67 -> 規則值（不適用）：中段 | E83: =E67 -> 51.61 | F83: =C83*E83 -> 760.60877 | G83: =F83/px-1 -> 2.6054644 | H83: =F83/(1+r_disc)^(1.27+0) -> 673.89559
A84: B | B84: FY2028 | C84: =PL!E25 -> 14.737624 | D84: 參考：25 分位 | E84: =pe_peak -> 42.09 | F84: =C84*E84 -> 620.30659 | G84: =F84/px-1 -> 1.9403991 | H84: =F84/(1+r_disc)^(1.27+0) -> 549.58856
A85: B | B85: FY2028 | C85: =PL!E25 -> 14.737624 | D85: 參考：中位數 | E85: =pe_mid -> 51.61 | F85: =C85*E85 -> 760.60877 | G85: =F85/px-1 -> 2.6054644 | H85: =F85/(1+r_disc)^(1.27+0) -> 673.89559
A86: B | B86: FY2028 | C86: =PL!E25 -> 14.737624 | D86: 參考：75 分位 | E86: =pe_trough -> 63.4 | F86: =C86*E86 -> 934.36535 | G86: =F86/px-1 -> 3.4291114 | H86: =F86/(1+r_disc)^(1.27+0) -> 827.84306
A87: B | B87: FY2029 | C87: =PL!F25 -> 13.257202 | D87: ="規則值（FY2029；不適用）："&G67 -> 規則值（FY2029；不適用）：見頂 | E87: =H67 -> 42.09 | F87: =C87*E87 -> 557.99565 | G87: =F87/px-1 -> 1.6450306 | H87: =F87/(1+r_disc)^(1.27+1) -> 449.43761
A88: C | B88: FY2028 | C88: =PL!E37 -> 14.737624 | D88: ="規則值（不適用）："&D68 -> 規則值（不適用）：見頂 | E88: =E68 -> 42.09 | F88: =C88*E88 -> 620.30659 | G88: =F88/px-1 -> 1.9403991 | H88: =F88/(1+r_disc)^(1.27+0) -> 549.58856
A89: C | B89: FY2028 | C89: =PL!E37 -> 14.737624 | D89: 參考：25 分位 | E89: =pe_peak -> 42.09 | F89: =C89*E89 -> 620.30659 | G89: =F89/px-1 -> 1.9403991 | H89: =F89/(1+r_disc)^(1.27+0) -> 549.58856
A90: C | B90: FY2028 | C90: =PL!E37 -> 14.737624 | D90: 參考：中位數 | E90: =pe_mid -> 51.61 | F90: =C90*E90 -> 760.60877 | G90: =F90/px-1 -> 2.6054644 | H90: =F90/(1+r_disc)^(1.27+0) -> 673.89559
A91: C | B91: FY2028 | C91: =PL!E37 -> 14.737624 | D91: 參考：75 分位 | E91: =pe_trough -> 63.4 | F91: =C91*E91 -> 934.36535 | G91: =F91/px-1 -> 3.4291114 | H91: =F91/(1+r_disc)^(1.27+0) -> 827.84306
A92: C | B92: FY2029 | C92: =PL!F37 -> 9.9233999 | D92: ="規則值（FY2029；不適用）："&G68 -> 規則值（FY2029；不適用）：谷底 | E92: =H68 -> 63.4 | F92: =C92*E92 -> 629.14355 | G92: =F92/px-1 -> 1.9822884 | H92: =F92/(1+r_disc)^(1.27+1) -> 506.74369
A93: FY2029 折現年數＝1.27＋1（FY2029 年底約 2029-01）；折現率為 In 頁 r_disc（Assumed 8–12%）。
A95: 4. What must be true：要讓 FY2028 年底價等於現價 ×（1＋報酬），需要的倍數（情境 A 的 FY2028 EPS）
A96: FY2028 年底隱含價 ÷ 現價 | B96: 所需倍數 | C96: 對照：歷史 25 分位 | D96: 對照：歷史中位數 | E96: 對照：歷史 75 分位
A97: 1 | B97: =px*A97/PL!E13 -> 14.336065 | C97: =pe_peak -> 42.09 | D97: =pe_mid -> 51.61 | E97: =pe_trough -> 63.4
A98: 1.1 | B98: =px*A98/PL!E13 -> 15.769671 | C98: =pe_peak -> 42.09 | D98: =pe_mid -> 51.61 | E98: =pe_trough -> 63.4
A99: 1.21 | B99: =px*A99/PL!E13 -> 17.346638 | C99: =pe_peak -> 42.09 | D99: =pe_mid -> 51.61 | E99: =pe_trough -> 63.4
A100: 1.5 | B100: =px*A100/PL!E13 -> 21.504097 | C100: =pe_peak -> 42.09 | D100: =pe_mid -> 51.61 | E100: =pe_trough -> 63.4
A101: 2 | B101: =px*A101/PL!E13 -> 28.67213 | C101: =pe_peak -> 42.09 | D101: =pe_mid -> 51.61 | E101: =pe_trough -> 63.4
A102: 讀法：1.00＝價格不變、1.21＝兩年約 10% 年報酬。現價 ÷ FY2028 EPS 約 15x，遠低於歷史年底倍數的 25 分位；規則值反映的是 NVIDIA 過去的高成長溢價，不是它在 EPS 成長放緩時仍會被給的倍數。
A121: 6. 十年倍數與規則值（2016–2025 年底；見頂年 25 分位、中段中位數、谷底 75 分位）
A122: 規則（Andy 2026-10-13）：合理倍數＝2016–2025 年底 P/E 依循環位置取分位。本模型來源：只有 Macrotrends 一個序列可用（9 年，缺 FY2016）；第二個來源（fullratio）為日曆年年底口徑，只列參考。自算（會計年度年底收盤價 ÷ GAAP 稀釋 EPS）的收盤價在建置環境找不到（未找到），見 Sources 頁待補。
A124: P/E：十年歷史倍數
A125: 年底 | B125: Macrotrends（1 月 31 日 ÷ TTM GAAP EPS） | C125: fullratio（日曆年年底 P/E，僅參考） | D125: 標記／說明
A126: 2016 | C126: 24.4 | D126: Macrotrends（1 月 31 日 ÷ TTM GAAP EPS）：Interested-party（資料商；搜尋摘要，頁面無法開啟）；FY2016 未找到；FY2017 取自另一摘要；FY2023 114.67（區間 112.19–114.67）；與 Wisesheets 對照：FY2019 20.29、FY2023 106.44、FY2024 51.63；fullratio（日曆年年底 P/E，僅參考）：Interested-party（日期口徑為 12 月底而非會計年度年底；2016–2022 共 7 年；不採用）
A127: 2017 | B127: 42.09 | C127: 34.93
A128: 2018 | B128: 50.33 | C128: 46.79
...

Sheet Recon
A1: Recon — 本模型 vs 公司指引、共識、市場層。只作事後對照，不為對上數字而調整參數。公司指引（FY2028 營收年增約 70%、毛利率 72–73%）與共識只放在這裡，不用於校準
A3: 項目 | B3: 對照值 | C3: 模型 A | D3: 差距 A | E3: 模型 B | F3: 差距 B | G3: 模型 C | H3: 差距 C | I3: 對照來源 | J3: 說明
A4: A. FY2028 vs 公司指引與共識（校準時未使用）
A5: FY2028 營收 vs 指引推算（FY2027 錨點 ×(1＋70%)） | B5: =a27_rev*(1+g28_gr) -> 687.8812 | C5: =PL!E5 -> 689.42768 | D5: =C5/B5-1 -> 0.0022481779 | E5: =PL!E17 -> 688.816 | F5: =E5/B5-1 -> 0.0013589603 | G5: =PL!E29 -> 688.816 | H5: =G5/B5-1 -> 0.0013589603 | I5: 公司 Q2 FY27 法說（二手）；美元金額：未找到公司直接陳述 | J5: 工作單記約 US$690B；本列用錨點 × 1.7 推算
A6: FY2028 營收年增 vs 指引 70%（差距以百分點計） | B6: =g28_gr -> 0.7 | C6: =PL!E6 -> 0.7038219 | D6: =C6-B6 -> 0.0038219025 | E6: =PL!E18 -> 0.70231023 | F6: =E6-B6 -> 0.0023102325 | G6: =PL!E30 -> 0.70231023 | H6: =G6-B6 -> 0.0023102325 | I6: 同上
A7: FY2028 營收 vs 共識推算（共識 FY2027 營收 ×(1＋63%)） | B7: =cons_rev27*(1+cons_g28) -> 671.071 | C7: =PL!E5 -> 689.42768 | D7: =C7/B7-1 -> 0.027354303 | E7: =PL!E17 -> 688.816 | F7: =E7/B7-1 -> 0.02644281 | G7: =PL!E29 -> 688.816 | H7: =G7/B7-1 -> 0.02644281 | I7: stockanalysis／Yahoo（二手） | J7: 共識 FY2028 營收直接值：未找到
A8: FY2028 毛利率 vs 指引 72–73% 中點（百分點） | B8: =g28_gm -> 0.725 | C8: =PL!E9 -> 0.68711022 | D8: =C8-B8 -> -0.037889779 | E8: =PL!E21 -> 0.68860839 | F8: =E8-B8 -> -0.036391606 | G8: =PL!E33 -> 0.68860839 | H8: =G8-B8 -> -0.036391606 | I8: 二手報導；逐字稿未取得
A9: FY2027 錨點 EPS vs 共識 FY2027 EPS | B9: =cons_eps27 -> 9.31 | C9: =PL!D13 -> 9.0597013 | D9: =C9/B9-1 -> -0.02688493 | E9: =PL!D25 -> 9.0597013 | F9: =E9/B9-1 -> -0.02688493 | G9: =PL!D37 -> 9.0597013 | H9: =G9/B9-1 -> -0.02688493 | I9: stockanalysis（二手）
A10: FY2028 EPS vs 共識 FY2028 EPS | B10: =cons_eps28 -> 15.91 | C10: =PL!E13 -> 14.715335 | D10: =C10/B10-1 -> -0.075088921 | E10: =PL!E25 -> 14.737624 | F10: =E10/B10-1 -> -0.073688006 | G10: =PL!E37 -> 14.737624 | H10: =G10/B10-1 -> -0.073688006 | I10: 247wallst／Wallstreetzen（二手） | J10: 共識區間 15.70–16.13（In 頁）
A11: FY2028 毛利率：v0.1 對照案例（只調售價 pf_cal）vs 指引 72–73% 中點（百分點） | B11: =g28_gm -> 0.725 | C11: =Sens!E882 -> 0.65929559 | D11: =C11-B11 -> -0.065704405 | E11: =Sens!E882 -> 0.65929559 | F11: =E11-B11 -> -0.065704405 | G11: =Sens!E882 -> 0.65929559 | H11: =G11-B11 -> -0.065704405 | I11: Sens 對照案例（只調售價，顆數不縮放） | J11: 與公司指引不一致：只調售價時 HBM 成本相對營收被放大，FY2028 毛利率偏低
A12: FY2029 EPS（共識：未找到） | C12: =PL!F13 -> 15.823142 | E12: =PL!F25 -> 13.257202 | G12: =PL!F37 -> 9.9233999 | I12: — | J12: WallStreetSmart 自有模型 FY2029 EPS 20.70（非共識，不採）
A13: B. FY2027 水準差與 k_rec（v0.1.1：基準已用 k_rec 校準到錨點；未校準的差額保留供查）
A14: Data Center 營收：未校準由下而上（k_rec＝1；運算＋網通）vs 公司錨點 | B14: =a27_dc -> 375.4568 | C14: =PL!D266+PL!D271 -> 453.2472 | D14: =C14/B14-1 -> 0.20718868 | E14: =PL!D266+PL!D271 -> 453.2472 | F14: =E14/B14-1 -> 0.20718868 | G14: =PL!D266+PL!D271 -> 453.2472 | H14: =G14/B14-1 -> 0.20718868 | I14: 公司 Q1、Q2 實績＋Q3 指引＋Q4 假設（v0.1 基準的差額） | J14: FY2027 三情境相同（情境係數從 CY2028 起）
A15: 認列顆數係數 k_rec（Derived） | C15: =k_rec -> 0.82837092 | E15: =k_rec -> 0.82837092 | G15: =k_rec -> 0.82837092 | I15: 錨點 Data Center ÷ 未校準由下而上 | J15: 以已發生的實績校準，FY2028 起沿用；營收與成本同比例縮放；顆數層與售價層無法分開識別
A16: 認列後 FY2027 Data Center 營收 vs 錨點（應為 0） | B16: =a27_dc -> 375.4568 | C16: =PL!D95+PL!D100 -> 375.4568 | D16: =C16/B16-1 -> 0 | E16: =PL!D95+PL!D100 -> 375.4568 | F16: =E16/B16-1 -> 0 | G16: =PL!D95+PL!D100 -> 375.4568 | H16: =G16/B16-1 -> 0 | I16: 校準恆等式，非獨立檢驗
A17: 認列後 FY2027 毛利率 vs 錨點毛利率（應為 0；百分點） | B17: =a27_gp/a27_rev -> 0.73686227 | C17: =PL!D106 -> 0.73686227 | D17: =C17-B17 -> 0 | E17: =PL!D106 -> 0.73686227 | F17: =E17-B17 -> 0 | G17: =PL!D106 -> 0.73686227 | H17: =G17-B17 -> 0 | I17: c_nh 校準恆等式，非獨立檢驗
A18: 認列顆數（百萬顆）：k_rec × 市場層 vs 市場層 CY2026 NVIDIA 顆數 | B18: =u_bw_26+u_rb_26+u_ru_26+u_hp_26 -> 7.6 | C18: =PL!D78 -> 6.295619 | D18: =C18/B18-1 -> -0.17162908 | E18: =PL!D78 -> 6.295619 | F18: =E18/B18-1 -> -0.17162908 | G18: =PL!D78 -> 6.295619 | H18: =G18/B18-1 -> -0.17162908 | I18: 市場層 UNITS（markets/memory，未修改） | J18: 認列顆數低於市場層＝顆數層與售價層的合併下調
A19: 網通：本模型歸屬（未縮放）vs 實際推估 rep_nv26（markets/network 的對帳） | B19: =rep_nv26 -> 74 | C19: =PL!D271 -> 61.733865 | D19: =C19/B19-1 -> -0.16575858 | E19: =PL!D271 -> 61.733865 | F19: =E19/B19-1 -> -0.16575858 | G19: =PL!D271 -> 61.733865 | H19: =G19/B19-1 -> -0.16575858 | I19: markets/network v0.2.2 Recon：−16.6% | J19: 歸屬比例為 Assumed
A20: 網通：本模型歸屬（未縮放）vs Q1 FY27 實際年化（14.8 × 4） | B20: =net_q1*4 -> 59.2 | C20: =PL!D271 -> 61.733865 | D20: =C20/B20-1 -> 0.042801774 | E20: =PL!D271 -> 61.733865 | F20: =E20/B20-1 -> 0.042801774 | G20: =PL!D271 -> 61.733865 | H20: =G20/B20-1 -> 0.042801774 | I20: 公司 Q1 FY27 稿 | J20: 網通季增中，年化為下限
A21: 運算：未校準由下而上 vs 錨點 Data Center − 網通推估（rep_nv26） | B21: =a27_dc-rep_nv26 -> 301.4568 | C21: =PL!D266 -> 391.51333 | D21: =C21/B21-1 -> 0.29873778 | E21: =PL!D266 -> 391.51333 | F21: =E21/B21-1 -> 0.29873778 | G21: =PL!D266 -> 391.51333 | H21: =G21/B21-1 -> 0.29873778 | I21: 網通推估 rep_nv26＝74（Q1 實際 14.8＋推估） | J21: 把網通拿掉後的運算差距（B2 節各候選來源以此為缺口）
A22: B2. 差額來源待查（以上一列的運算缺口為準；各列為候選來源，未驗證）
A23: 候選來源 | B23: 對照值 | C23: 模型 A | D23: 差距 A | E23: 模型 B | F23: 差距 B | G23: 模型 C | H23: 差距 C | I23: 目前狀態 | J23: 可查的公開資料
A24: ① Rubin CY2026 出貨時點（FY↔CY）：缺口相當於 Rubin 顆數（百萬）；對照值＝Rubin CY2026 顆數 | B24: =u_rb_26 -> 1.7 | C24: =(PL!D266-(a27_dc-rep_nv26))/PL!D251 -> 1.2478965 | D24: =C24/B24-1 -> -0.26594322 | E24: =(PL!D266-(a27_dc-rep_nv26))/PL!D251 -> 1.2478965 | F24: =E24/B24-1 -> -0.26594322 | G24: =(PL!D266-(a27_dc-rep_nv26))/PL!D251 -> 1.2478965 | H24: =G24/B24-1 -> -0.26594322 | I24: 未驗證。二手報導：Rubin 量產出貨自日曆年 2026 第三季開始、第四季放量（digitalcitizen、winbuzzer、經濟日報經 wccftech）；日曆年第三季多數落在 FY2027 第二、三季，只有 2027 年 1 月落在 FY2027 之外，時點本身應只解釋小部分缺口（本模型推論，未驗證） | J24: 可查：公司法說與 10-Q 的 Rubin 營收認列時點與出貨顆數（財務長書面說明、10-Q 本環境無法開啟）；TrendForce 的 Rubin 季別出貨；ODM（鴻海、廣達）月營收與機櫃出貨
A25: ① 同上：缺口占 Rubin CY2026 顆數的比例（需落在 FY2027 之外的比例） | C25: =(PL!D266-(a27_dc-rep_nv26))/PL!D251/u_rb_26 -> 0.73405678 | E25: =(PL!D266-(a27_dc-rep_nv26))/PL!D251/u_rb_26 -> 0.73405678 | G25: =(PL!D266-(a27_dc-rep_nv26))/PL!D251/u_rb_26 -> 0.73405678 | I25: — | J25: 比例愈高，愈難只用出貨時點解釋
A26: ② B200／B300 價差：僅靠 Blackwell 均價下調解釋缺口，所需降幅 | C26: =(PL!D266-(a27_dc-rep_nv26))/PL!D262 -> 0.35479074 | E26: =(PL!D266-(a27_dc-rep_nv26))/PL!D262 -> 0.35479074 | G26: =(PL!D266-(a27_dc-rep_nv26))/PL!D262 -> 0.35479074 | I26: 未驗證。公司不分 B200／B300 揭露；橋接表 Rack 頁只有 GB300（模組價 40.4K）。二手：HSBC 稱 B200→B300（GB200→GB300）沒有明顯 ASP 提升（wccftech 轉述，原報告未取得）→ 價差本身不足以解釋缺口 | J26: 可查：賣方 ASP 估計（HSBC、KeyBanc）、B200 HGX 8 卡系統報價（經銷商）、GB200 機架價與 GB300 機架價對照；目前只找到機架層級 $3.7–4.0M（blog，無原始出處）
A27: ③ 匣級加價保留比例 k_tray 由基準降到 0：未校準運算營收變動占缺口的比例 | C27: =k_tray*(u_bw_26*pres_bw+u_rb_26*pres_rb+u_ru_26*pres_ru+u_hp_26*pres_hp)/(PL!D266-(a27_dc-rep_nv26)) -> 0.27353805 | E27: =k_tray*(u_bw_26*pres_bw+u_rb_26*pres_rb+u_ru_26*pres_ru+u_hp_26*pres_hp)/(PL!D266-(a27_dc-rep_nv26)) -> 0.27353805 | G27: =k_tray*(u_bw_26*pres_bw+u_rb_26*pres_rb+u_ru_26*pres_ru+u_hp_26*pres_hp)/(PL!D266-(a27_dc-rep_nv26)) -> 0.27353805 | I27: Assumed（0–1）。公司不揭露匣級加價與 ODM 分成 | J27: 可查：NVIDIA 與 ODM（鴻海、廣達、緯創）的毛利率與營收認列方式（是否以機櫃或 GPU 板認列）
A28: ④ 顆數層（市場層 UNITS 為賣方與研調估計）：全歸顆數層時，CY2026 NVIDIA 顆數需為（百萬顆）；對照值＝市場層 | B28: =u_bw_26+u_rb_26+u_ru_26+u_hp_26 -> 7.6 | C28: =(a27_dc-rep_nv26)/(PL!D266/PL!D249) -> 5.8518356 | D28: =C28/B28-1 -> -0.23002163 | E28: =(a27_dc-rep_nv26)/(PL!D266/PL!D249) -> 5.8518356 | F28: =E28/B28-1 -> -0.23002163 | G28: =(a27_dc-rep_nv26)/(PL!D266/PL!D249) -> 5.8518356 | H28: =G28/B28-1 -> -0.23002163 | I28: 未驗證。市場層顆數為 Morgan Stanley、TrendForce 等估計（Interested-party） | J28: 可查：台積電 CoWoS 出貨與 NVIDIA 分配、各研調的 2026 出貨更新；公司不揭露顆數
A29: ⑤ 全歸售價層時，每顆平均運算售價（US$K）；對照值＝模型（未校準） | B29: =PL!D266/PL!D249 -> 51.514912 | C29: =(a27_dc-rep_nv26)/PL!D249 -> 39.665368 | D29: =C29/B29-1 -> -0.23002163 | E29: =(a27_dc-rep_nv26)/PL!D249 -> 39.665368 | F29: =E29/B29-1 -> -0.23002163 | G29: =(a27_dc-rep_nv26)/PL!D249 -> 39.665368 | H29: =G29/B29-1 -> -0.23002163 | I29: 未驗證 | J29: 同②③
A30: C. 網通與記憶體
A31: HBM 價格指數 CY2027 ÷ CY2026：本模型（markets/memory）vs 橋接表 VR200 2027 合約（36 ÷ 16.7） | B31: =36/16.7 -> 2.1556886 | C31: =hbm_A_27/hbm_A_26 -> 1.8 | D31: =C31/B31-1 -> -0.165 | E31: =hbm_B_27/hbm_B_26 -> 1.8 | F31: =E31/B31-1 -> -0.165 | G31: =hbm_C_27/hbm_C_26 -> 1.8 | H31: =G31/B31-1 -> -0.165 | I31: 橋接表 Rack 頁 D4／C4（Tokenomics v20.1） | J31: 市場層混合價 +80%；橋接表 HBM4 合約 +116%：吸收時毛利率壓力的上限
A32: HBM 價格 CY2027 ($/GB)：市場層 vs 二手 HBM4 估計（Bernstein 約 $53、Fubon $31–32、TrendForce 約 $36） | B32: 36 | C32: =hbm_A_27 -> 26.28 | D32: =C32/B32-1 -> -0.27 | E32: =hbm_B_27 -> 26.28 | F32: =E32/B32-1 -> -0.27 | G32: =hbm_C_27 -> 26.28 | H32: =G32/B32-1 -> -0.27 | I32: Silicon Analysts／TrendForce／Bernstein（二手；賣方與記憶體廠有價格方向誘因） | J32: 市場層為混合單價（含 HBM3E）
A33: D. 命題檢查（不為對上而調參數）
A34: 2027 年 NVIDIA 金額份額（加速器晶片，模組層級）vs 命題下緣 75% | B34: =th_sh_lo -> 0.75 | C34: =Units!D32 -> 0.75128824 | D34: =C34-B34 -> 0.0012882376 | E34: =Units!D66 -> 0.75128824 | F34: =E34-B34 -> 0.0012882376 | G34: =Units!D100 -> 0.75128824 | H34: =G34-B34 -> 0.0012882376 | I34: 擁有者命題；外部來源：未找到 | J34: 區間見 Sens（ASIC 單價 Assumed）；命題上緣 80%
A35: 2027 年 NVIDIA 金額份額 vs 命題上緣 80% | B35: =th_sh_hi -> 0.8 | C35: =Units!D32 -> 0.75128824 | D35: =C35-B35 -> -0.048711762 | E35: =Units!D66 -> 0.75128824 | F35: =E35-B35 -> -0.048711762 | G35: =Units!D100 -> 0.75128824 | H35: =G35-B35 -> -0.048711762 | I35: 同上
A36: 2027 年 NVIDIA 顆數份額（對照 DIGITIMES：約 35% 的 2027 顆數） | B36: 0.351 | C36: =Units!D26 -> 0.4092827 | D36: =C36-B36 -> 0.0582827 | E36: =Units!D60 -> 0.4092827 | F36: =E36-B36 -> 0.0582827 | G36: =Units!D94 -> 0.4092827 | H36: =G36-B36 -> 0.0582827 | I36: DIGITIMES Research 2026-10-13（二手） | J36: 顆數份額與金額份額差距大＝NVIDIA 單價遠高於 ASIC
A37: FY2028 毛利率 − FY2027 毛利率（百分點；命題：HBM 漲價壓毛利 2–3 個百分點） | B37: -0.025 | C37: =PL!E9-PL!D9 -> -0.049752045 | D37: =C37-B37 -> -0.024752045 | E37: =PL!E21-PL!D21 -> -0.048253873 | F37: =E37-B37 -> -0.023253873 | G37: =PL!E33-PL!D33 -> -0.048253873 | H37: =G37-B37 -> -0.023253873 | I37: 擁有者命題（中點 −2.5pt） | J37: 含吸收比例、世代組合與 Rubin 較高售價；HBM 成本占營收的變化見下一列
A38: HBM 成本占由下而上營收：FY2028 − FY2027（百分點，吸收前） | C38: =PL!E107-PL!D107 -> 0.04291012 | E38: =PL!E164-PL!D164 -> 0.043004637 | G38: =PL!E221-PL!D221 -> 0.043004637 | I38: — | J38: 吸收比例 0.5 時約一半轉嫁到售價
A39: 現價 ÷ FY2028 EPS vs 命題 13.5x | B39: =th_mult -> 13.5 | C39: =px/PL!E13 -> 14.336065 | D39: =C39/B39-1 -> 0.061930726 | E39: =px/PL!E25 -> 14.314384 | F39: =E39/B39-1 -> 0.060324707 | G39: =px/PL!E37 -> 14.314384 | H39: =G39/B39-1 -> 0.060324707 | I39: 擁有者命題；共識 EPS 下約 13.4x | J39: EPS 越高，現價越便宜
A40: E. 預留
A41: R4 產業部署路徑（markets/deploy_path/，尚未建立）：上線後以 NVIDIA 資料中心營收 ÷ 部署 GW 對照 IT capex | J41: 預留列：本版無數值

Sheet Sens
A1: Sens — 一次動一個輸入（情境 A，k_rec 校準後的基準）：對 FY2028、FY2029、FY2030 的營收、EPS 與隱含股價（規則值，不適用，僅供對照）的影響。每個案例是一個完整的推導區塊（本頁下方，與 PL 同一引擎）。隱含股價＝EPS × 情境 A 的規則倍數（FY2028：Val!E15；FY2029：Val!H15）
A3: 案例 | B3: 設定 | C3: FY2028 營收 | D3: FY2028 EPS | E3: FY2028 EPS 相對基準 | F3: FY2028 隱含價（規則值，不適用，僅供對照） | G3: 隱含價相對基準 | H3: FY2029 營收 | I3: FY2029 EPS | J3: FY2029 EPS 相對基準 | K3: FY2029 隱含價（規則值，不適用） | L3: 隱含價相對基準 | M3: FY2030 EPS | N3: FY2030 EPS 年增（對 FY2029）
A4: 基準（情境 A） | B4: PL 區塊 A | C4: =PL!E109 -> 689.42768 | D4: =PL!E123 -> 14.715335 | E4: =D4/D$4-1 -> 0 | F4: =D4*Val!$E$66 -> 759.45845 | G4: =F4/F$4-1 -> 0 | H4: =PL!F109 -> 771.17753 | I4: =PL!F123 -> 15.823142 | J4: =I4/I$4-1 -> 0 | K4: =I4*Val!$H$66 -> 816.63237 | L4: =K4/K$4-1 -> 0 | M4: =PL!G123 -> 18.359635 | N4: =M4/I4-1 -> 0.16030275
A5: NVIDIA 顆數係數 低（×0.9） | B5: FY2028 起所有 NVIDIA 世代顆數 ×0.9 | C5: =E79 -> 623.63627 | D5: =E93 -> 13.259036 | E5: =D5/D$4-1 -> -0.098964714 | F5: =D5*Val!$E$66 -> 684.29886 | G5: =F5/F$4-1 -> -0.098964714 | H5: =F79 -> 697.46324 | I5: =F93 -> 14.257823 | J5: =I5/I$4-1 -> -0.098925926 | K5: =I5*Val!$H$66 -> 735.84626 | L5: =K5/K$4-1 -> -0.098925926 | M5: =G93 -> 16.542593 | N5: =M5/I5-1 -> 0.16024677
A6: NVIDIA 顆數係數 高（×1.1） | B6: ×1.1 | C6: =E136 -> 755.21909 | D6: =E150 -> 16.171634 | E6: =D6/D$4-1 -> 0.098964714 | F6: =D6*Val!$E$66 -> 834.61804 | G6: =F6/F$4-1 -> 0.098964714 | H6: =F136 -> 844.89182 | I6: =F150 -> 17.388471 | J6: =I6/I$4-1 -> 0.098926561 | K6: =I6*Val!$H$66 -> 897.419 | L6: =K6/K$4-1 -> 0.098926561 | M6: =G150 -> 20.176699 | N6: =M6/I6-1 -> 0.16034923
A7: Rubin Ultra 售價 低 | B7: GPU 模組價 60K | C7: =E193 -> 685.70001 | D7: =E207 -> 14.614366 | E7: =D7/D$4-1 -> -0.0068614764 | F7: =D7*Val!$E$66 -> 754.24745 | G7: =F7/F$4-1 -> -0.0068614764 | H7: =F193 -> 746.3264 | I7: =F207 -> 15.135319 | J7: =I7/I$4-1 -> -0.043469417 | K7: =I7*Val!$H$66 -> 781.13384 | L7: =K7/K$4-1 -> -0.043469417 | M7: =G207 -> 17.557077 | N7: =M7/I7-1 -> 0.16000702
A8: Rubin Ultra 售價 高 | B8: GPU 模組價 100K | C8: =E250 -> 695.64046 | D8: =E264 -> 14.883617 | E8: =D8/D$4-1 -> 0.011435794 | F8: =D8*Val!$E$66 -> 768.14346 | G8: =F8/F$4-1 -> 0.011435794 | H8: =F250 -> 812.59608 | I8: =F264 -> 16.969726 | J8: =I8/I$4-1 -> 0.072462458 | K8: =I8*Val!$H$66 -> 875.80756 | L8: =K8/K$4-1 -> 0.072462458 | M8: =G264 -> 19.697519 | N8: =M8/I8-1 -> 0.16074468
A9: ASIC 金額份額 +5pt（NVIDIA 份額 −5pt） | B9: NVIDIA 顆數 ×(份額−5pt)÷份額（Units 頁金額份額），總市場金額不變 | C9: =E307 -> 645.64195 | D9: =E321 -> 13.746134 | E9: =D9/D$4-1 -> -0.065863346 | F9: =D9*Val!$E$66 -> 709.43798 | G9: =F9/F$4-1 -> -0.065863346 | H9: =F307 -> 720.51223 | I9: =F321 -> 14.746953 | J9: =I9/I$4-1 -> -0.068013651 | K9: =I9*Val!$H$66 -> 761.09022 | L9: =K9/K$4-1 -> -0.068013651 | M9: =G321 -> 17.103196 | N9: =M9/I9-1 -> 0.15977834
A10: ASIC 金額份額 −5pt（NVIDIA 份額 +5pt） | B10: NVIDIA 顆數 ×(份額+5pt)÷份額 | C10: =E364 -> 733.21341 | D10: =E378 -> 15.684536 | E10: =D10/D$4-1 -> 0.065863346 | F10: =D10*Val!$E$66 -> 809.47893 | G10: =F10/F$4-1 -> 0.065863346 | H10: =F364 -> 821.84283 | I10: =F378 -> 16.899424 | J10: =I10/I$4-1 -> 0.068019488 | K10: =I10*Val!$H$66 -> 872.17929 | L10: =K10/K$4-1 -> 0.068019488 | M10: =G378 -> 19.616198 | N10: =M10/I10-1 -> 0.16076132
A11: HBM／LPDDR 吸收比例 0（全額轉嫁） | B11: 吸收比例 0.0 | C11: =E421 -> 711.05515 | D11: =E435 -> 15.425296 | E11: =D11/D$4-1 -> 0.048246289 | F11: =D11*Val!$E$66 -> 796.09951 | G11: =F11/F$4-1 -> 0.048246289 | H11: =F421 -> 802.86354 | I11: =F435 -> 16.880162 | J11: =I11/I$4-1 -> 0.066802116 | K11: =I11*Val!$H$66 -> 871.18514 | L11: =K11/K$4-1 -> 0.066802116 | M11: =G435 -> 19.375988 | N11: =M11/I11-1 -> 0.14785562
A12: HBM／LPDDR 吸收比例 1（全額吸收） | B12: 吸收比例 1.0 | C12: =E478 -> 667.80021 | D12: =E492 -> 14.005375 | E12: =D12/D$4-1 -> -0.048246289 | F12: =D12*Val!$E$66 -> 722.8174 | G12: =F12/F$4-1 -> -0.048246289 | H12: =F478 -> 739.49152 | I12: =F492 -> 14.766325 | J12: =I12/I$4-1 -> -0.066789352 | K12: =I12*Val!$H$66 -> 762.09002 | L12: =K12/K$4-1 -> -0.066789352 | M12: =G492 -> 17.343302 | N12: =M12/I12-1 -> 0.17451715
A13: 中國恢復 低（10） | B13: FY2028 起每年加 10 | C13: =E535 -> 699.42768 | D13: =E549 -> 14.936136 | E13: =D13/D$4-1 -> 0.015004783 | F13: =D13*Val!$E$66 -> 770.85396 | G13: =F13/F$4-1 -> 0.015004783 | H13: =F535 -> 781.17753 | I13: =F549 -> 16.032351 | J13: =I13/I$4-1 -> 0.013221691 | K13: =I13*Val!$H$66 -> 827.42963 | L13: =K13/K$4-1 -> 0.013221691 | M13: =G549 -> 18.576615 | N13: =M13/I13-1 -> 0.15869564
A14: 中國恢復 基準（20） | B14: 每年加 20 | C14: =E592 -> 709.42768 | D14: =E606 -> 15.156936 | E14: =D14/D$4-1 -> 0.030009565 | F14: =D14*Val!$E$66 -> 782.24947 | G14: =F14/F$4-1 -> 0.030009565 | H14: =F592 -> 791.17753 | I14: =F606 -> 16.241545 | J14: =I14/I$4-1 -> 0.026442488 | K14: =I14*Val!$H$66 -> 838.22616 | L14: =K14/K$4-1 -> 0.026442488 | M14: =G606 -> 18.793567 | N14: =M14/I14-1 -> 0.15712926
A15: 中國恢復 高（40） | B15: 每年加 40 | C15: =E649 -> 729.42768 | D15: =E663 -> 15.598537 | E15: =D15/D$4-1 -> 0.060019131 | F15: =D15*Val!$E$66 -> 805.04049 | G15: =F15/F$4-1 -> 0.060019131 | H15: =F649 -> 811.17753 | I15: =F663 -> 16.659894 | J15: =I15/I$4-1 -> 0.052881549 | K15: =I15*Val!$H$66 -> 859.81715 | L15: =K15/K$4-1 -> 0.052881549 | M15: =G663 -> 19.227395 | N15: =M15/I15-1 -> 0.15411264
A16: 營業費用率 −2pt | B16: 營業費用額外 −2% × 營收 | C16: =E706 -> 689.42768 | D16: =E720 -> 15.192869 | E16: =D16/D$4-1 -> 0.032451454 | F16: =D16*Val!$E$66 -> 784.10398 | G16: =F16/F$4-1 -> 0.032451454 | H16: =F706 -> 771.17753 | I16: =F720 -> 16.363788 | J16: =I16/I$4-1 -> 0.034168058 | K16: =I16*Val!$H$66 -> 844.53511 | L16: =K16/K$4-1 -> 0.034168058 | M16: =G720 -> 18.972497 | N16: =M16/I16-1 -> 0.1594196
A17: 營業費用率 +2pt | B17: +2% × 營收 | C17: =E763 -> 689.42768 | D17: =E777 -> 14.237801 | E17: =D17/D$4-1 -> -0.032451454 | F17: =D17*Val!$E$66 -> 734.81292 | G17: =F17/F$4-1 -> -0.032451454 | H17: =F763 -> 771.17753 | I17: =F777 -> 15.282496 | J17: =I17/I$4-1 -> -0.034168058 | K17: =I17*Val!$H$66 -> 788.72963 | L17: =K17/K$4-1 -> -0.034168058 | M17: =G777 -> 17.746774 | N17: =M17/I17-1 -> 0.16124839
A18: CY2029 顆數與 CY2028 持平（FY2030 顆數持平） | B18: 核心問題：顆數持平以後 EPS 還能不能成長；網通同步持平 | C18: =E820 -> 689.42768 | D18: =E834 -> 14.715335 | E18: =D18/D$4-1 -> 0 | F18: =D18*Val!$E$66 -> 759.45845 | G18: =F18/F$4-1 -> 0 | H18: =F820 -> 771.17753 | I18: =F834 -> 15.823142 | J18: =I18/I$4-1 -> 0 | K18: =I18*Val!$H$66 -> 816.63237 | L18: =K18/K$4-1 -> 0 | M18: =G834 -> 16.157883 | N18: =M18/I18-1 -> 0.021155138
A19: 對照：v0.1 的作法——只調售價（pf_cal；k_rec＝1） | B19: 全部運算售價（與非 HBM 成本）× pf_cal，顆數不縮放：讓 FY2027 的 Data Center 等於錨點；FY2028 毛利率與公司指引不一致（見 Recon 對應列）；不進基準 | C19: =E877 -> 697.4588 | D19: =E891 -> 14.220087 | E19: =D19/D$4-1 -> -0.033655281 | F19: =D19*Val!$E$66 -> 733.89867 | G19: =F19/F$4-1 -> -0.033655281 | H19: =F877 -> 782.23756 | I19: =F891 -> 15.129568 | J19: =I19/I$4-1 -> -0.043832901 | K19: =I19*Val!$H$66 -> 780.837 | L19: =K19/K$4-1 -> -0.043832901 | M19: =G891 -> 17.61506 | N19: =M19/I19-1 -> 0.16428043
A20: 顆數情境 B | B20: CY2028 ×0.8、CY2029 ×0.85；記憶體 B 路徑 | C20: =PL!E166 -> 688.816 | D20: =PL!E180 -> 14.737624 | E20: =D20/D$4-1 -> 0.0015146483 | F20: =D20*Val!$E$66 -> 760.60877 | G20: =F20/F$4-1 -> 0.0015146483 | H20: =PL!F166 -> 601.37015 | I20: =PL!F180 -> 13.257202 | J20: =I20/I$4-1 -> -0.16216374 | K20: =I20*Val!$H$66 -> 684.20421 | L20: =K20/K$4-1 -> -0.16216374 | M20: =PL!G180 -> 16.177692 | N20: =M20/I20-1 -> 0.22029455
A21: 顆數情境 C | B21: CY2028–29 ×0.6；記憶體 C 路徑 | C21: =PL!E223 -> 688.816 | D21: =PL!E237 -> 14.737624 | E21: =D21/D$4-1 -> 0.0015146483 | F21: =D21*Val!$E$66 -> 760.60877 | G21: =F21/F$4-1 -> 0.0015146483 | H21: =PL!F223 -> 452.37727 | I21: =PL!F237 -> 9.9233999 | J21: =I21/I$4-1 -> -0.3728553 | K21: =I21*Val!$H$66 -> 512.14667 | L21: =K21/K$4-1 -> -0.3728553 | M21: =PL!G237 -> 11.430938 | N21: =M21/I21-1 -> 0.15191749
A22: 對照：v0.1 基準（k_rec＝1，未校準） | B22: FY2027 由下而上高於錨點；FY2028 起沿用未校準水準 | C22: =PL!E280 -> 825.74004 | D22: =PL!E294 -> 17.685367 | E22: =D22/D$4-1 -> 0.20183242 | F22: =D22*Val!$E$66 -> 912.74179 | G22: =F22/F$4-1 -> 0.20183242 | H22: =PL!F280 -> 923.9052 | I22: =PL!F294 -> 19.013515 | J22: =I22/I$4-1 -> 0.20162703 | K22: =I22*Val!$H$66 -> 981.28753 | L22: =K22/K$4-1 -> 0.20162703 | M22: =PL!G294 -> 22.064069 | N22: =M22/I22-1 -> 0.16044134
A24: 讀法：FY2028（≈CY2027）三情境幾乎相同；顆數係數、售價與吸收比例的影響從 FY2028 起；情境 B、C 的差異從 FY2029 起。隱含價欄為規則值（10 年落後 P/E 分位，不適用，僅供對照），只反映 EPS 變動，不反映循環位置變動。
A26: 目標價參數敏感度（v0.2）：加權目標價（Val 第 0 節）一次動一個參數；PL 延伸期的收斂路徑不隨 tp_g 變動，tp_g 只改再投資率與永續成長
A27: 參數 | B27: 設定（低／高） | C27: 低：加權目標價 | D27: 低：相對基準 | E27: 高：加權目標價 | F27: 高：相對基準 | G27: 基準加權目標價
A28: tp_r ±1pt | B28: 折現率 −1pt／＋1pt | C28: =tp_w_dcf*(tp_wA*(MAX(0,Val!B7*Val!$G$7*(1-MIN(0.8,tp_g/tp_roe))/(1+(tp_r-0.01))^Val!$F$7+Val!B8*Val!$G$8*(1-MIN(0.8,tp_g/tp_roe))/(1+(tp_r-0.01))^Val!$F$8+Val!B9*Val!$G$9*(1-MIN(0.8,tp_g/tp_roe))/(1+(tp_r-0.01))^Val!$F$9+Val!B10*Val!$G$10*(1-MIN(0.8,tp_g/tp_roe))/(1+(tp_r-0.01))^Val!$F$10+Val!B11*Val!$G$11*(1-MIN(0.8,tp_g/tp_roe))/(1+(tp_r-0.01))^Val!$F$11+Val!B12*Val!$G$12*(1-MIN(0.8,tp_g/tp_roe))/(1+(tp_r-0.01))^Val!$F$12+Val!B12*(1-MIN(0.8,tp_g/tp_roe))*(1+tp_g)/((tp_r-0.01)-tp_g)/(1+(tp_r-0.01))^Val!$F$12))+tp_wB*(MAX(0,Val!C7*Val!$G$7*(1-MIN(0.8,tp_g/tp_roe))/(1+(tp_r-0.01))^Val!$F$7+Val!C8*Val!$G$8*(1-MIN(0.8,tp_g/tp_roe))/(1+(tp_r-0.01))^Val!$F$8+Val!C9*Val!$G$9*(1-MIN(0.8,tp_g/tp_roe))/(1+(tp_r-0.01))^Val!$F$9+Val!C10*Val!$G$10*(1-MIN(0.8,tp_g/tp_roe))/(1+(tp_r-0.01))^Val!$F$10+Val!C11*Val!$G$11*(1-MIN(0.8,tp_g/tp_roe))/(1+(tp_r-0.01))^Val!$F$11+Val!C12*Val!$G$12*(1-MIN(0.8,tp_g/tp_roe))/(1+(tp_r-0.01))^Val!$F$12+Val!C12*(1-MIN(0.8,tp_g/tp_roe))*(1+tp_g)/((tp_r-0.01)-tp_g)/(1+(tp_r-0.01))^Val!$F$12))+tp_wC*(MAX(0,Val!D7*Val!$G$7*(1-MIN(0.8,tp_g/tp_roe))/(1+(tp_r-0.01))^Val!$F$7+Val!D8*Val!$G$8*(1-MIN(0.8,tp_g/tp_roe))/(1+(tp_r-0.01))^Val!$F$8+Val!D9*Val!$G$9*(1-MIN(0.8,tp_g/tp_roe))/(1+(tp_r-0.01))^Val!$F$9+Val!D10*Val!$G$10*(1-MIN(0.8,tp_g/tp_roe))/(1+(tp_r-0.01))^Val!$F$10+Val!D11*Val!$G$11*(1-MIN(0.8,tp_g/tp_roe))/(1+(tp_r-0.01))^Val!$F$11+Val!D12*Val!$G$12*(1-MIN(0.8,tp_g/tp_roe))/(1+(tp_r-0.01))^Val!$F$12+Val!D12*(1-MIN(0.8,tp_g/tp_roe))*(1+tp_g)/((tp_r-0.01)-tp_g)/(1+(tp_r-0.01))^Val!$F$12)))*(1+(tp_r-0.01))+(1-tp_w_dcf)*Val!$B$36 -> 273.90138 | D28: =C28/G28-1 -> 0.087426797 | E28: =tp_w_dcf*(tp_wA*(MAX(0,Val!B7*Val!$G$7*(1-MIN(0.8,tp_g/tp_roe))/(1+(tp_r+0.01))^Val!$F$7+Val!B8*Val!$G$8*(1-MIN(0.8,tp_g/tp_roe))/(1+(tp_r+0.01))^Val!$F$8+Val!B9*Val!$G$9*(1-MIN(0.8,tp_g/tp_roe))/(1+(tp_r+0.01))^Val!$F$9+Val!B10*Val!$G$10*(1-MIN(0.8,tp_g/tp_roe))/(1+(tp_r+0.01))^Val!$F$10+Val!B11*Val!$G$11*(1-MIN(0.8,tp_g/tp_roe))/(1+(tp_r+0.01))^Val!$F$11+Val!B12*Val!$G$12*(1-MIN(0.8,tp_g/tp_roe))/(1+(tp_r+0.01))^Val!$F$12+Val!B12*(1-MIN(0.8,tp_g/tp_roe))*(1+tp_g)/((tp_r+0.01)-tp_g)/(1+(tp_r+0.01))^Val!$F$12))+tp_wB*(MAX(0,Val!C7*Val!$G$7*(1-MIN(0.8,tp_g/tp_roe))/(1+(tp_r+0.01))^Val!$F$7+Val!C8*Val!$G$8*(1-MIN(0.8,tp_g/tp_roe))/(1+(tp_r+0.01))^Val!$F$8+Val!C9*Val!$G$9*(1-MIN(0.8,tp_g/tp_roe))/(1+(tp_r+0.01))^Val!$F$9+Val!C10*Val!$G$10*(1-MIN(0.8,tp_g/tp_roe))/(1+(tp_r+0.01))^Val!$F$10+Val!C11*Val!$G$11*(1-MIN(0.8,tp_g/tp_roe))/(1+(tp_r+0.01))^Val!$F$11+Val!C12*Val!$G$12*(1-MIN(0.8,tp_g/tp_roe))/(1+(tp_r+0.01))^Val!$F$12+Val!C12*(1-MIN(0.8,tp_g/tp_roe))*(1+tp_g)/((tp_r+0.01)-tp_g)/(1+(tp_r+0.01))^Val!$F$12))+tp_wC*(MAX(0,Val!D7*Val!$G$7*(1-MIN(0.8,tp_g/tp_roe))/(1+(tp_r+0.01))^Val!$F$7+Val!D8*Val!$G$8*(1-MIN(0.8,tp_g/tp_roe))/(1+(tp_r+0.01))^Val!$F$8+Val!D9*Val!$G$9*(1-MIN(0.8,tp_g/tp_roe))/(1+(tp_r+0.01))^Val!$F$9+Val!D10*Val!$G$10*(1-MIN(0.8,tp_g/tp_roe))/(1+(tp_r+0.01))^Val!$F$10+Val!D11*Val!$G$11*(1-MIN(0.8,tp_g/tp_roe))/(1+(tp_r+0.01))^Val!$F$11+Val!D12*Val!$G$12*(1-MIN(0.8,tp_g/tp_roe))/(1+(tp_r+0.01))^Val!$F$12+Val!D12*(1-MIN(0.8,tp_g/tp_roe))*(1+tp_g)/((tp_r+0.01)-tp_g)/(1+(tp_r+0.01))^Val!$F$12)))*(1+(tp_r+0.01))+(1-tp_w_dcf)*Val!$B$36 -> 236.14619 | F28: =E28/G28-1 -> -0.062466608 | G28: =Val!$B$40 -> 251.8803
A29: tp_g ±1pt | B29: 長期成長 −1pt／＋1pt | C29: =tp_w_dcf*(tp_wA*(MAX(0,Val!B7*Val!$G$7*(1-MIN(0.8,(tp_g-0.01)/tp_roe))/(1+tp_r)^Val!$F$7+Val!B8*Val!$G$8*(1-MIN(0.8,(tp_g-0.01)/tp_roe))/(1+tp_r)^Val!$F$8+Val!B9*Val!$G$9*(1-MIN(0.8,(tp_g-0.01)/tp_roe))/(1+tp_r)^Val!$F$9+Val!B10*Val!$G$10*(1-MIN(0.8,(tp_g-0.01)/tp_roe))/(1+tp_r)^Val!$F$10+Val!B11*Val!$G$11*(1-MIN(0.8,(tp_g-0.01)/tp_roe))/(1+tp_r)^Val!$F$11+Val!B12*Val!$G$12*(1-MIN(0.8,(tp_g-0.01)/tp_roe))/(1+tp_r)^Val!$F$12+Val!B12*(1-MIN(0.8,(tp_g-0.01)/tp_roe))*(1+(tp_g-0.01))/(tp_r-(tp_g-0.01))/(1+tp_r)^Val!$F$12))+tp_wB*(MAX(0,Val!C7*Val!$G$7*(1-MIN(0.8,(tp_g-0.01)/tp_roe))/(1+tp_r)^Val!$F$7+Val!C8*Val!$G$8*(1-MIN(0.8,(tp_g-0.01)/tp_roe))/(1+tp_r)^Val!$F$8+Val!C9*Val!$G$9*(1-MIN(0.8,(tp_g-0.01)/tp_roe))/(1+tp_r)^Val!$F$9+Val!C10*Val!$G$10*(1-MIN(0.8,(tp_g-0.01)/tp_roe))/(1+tp_r)^Val!$F$10+Val!C11*Val!$G$11*(1-MIN(0.8,(tp_g-0.01)/tp_roe))/(1+tp_r)^Val!$F$11+Val!C12*Val!$G$12*(1-MIN(0.8,(tp_g-0.01)/tp_roe))/(1+tp_r)^Val!$F$12+Val!C12*(1-MIN(0.8,(tp_g-0.01)/tp_roe))*(1+(tp_g-0.01))/(tp_r-(tp_g-0.01))/(1+tp_r)^Val!$F$12))+tp_wC*(MAX(0,Val!D7*Val!$G$7*(1-MIN(0.8,(tp_g-0.01)/tp_roe))/(1+tp_r)^Val!$F$7+Val!D8*Val!$G$8*(1-MIN(0.8,(tp_g-0.01)/tp_roe))/(1+tp_r)^Val!$F$8+Val!D9*Val!$G$9*(1-MIN(0.8,(tp_g-0.01)/tp_roe))/(1+tp_r)^Val!$F$9+Val!D10*Val!$G$10*(1-MIN(0.8,(tp_g-0.01)/tp_roe))/(1+tp_r)^Val!$F$10+Val!D11*Val!$G$11*(1-MIN(0.8,(tp_g-0.01)/tp_roe))/(1+tp_r)^Val!$F$11+Val!D12*Val!$G$12*(1-MIN(0.8,(tp_g-0.01)/tp_roe))/(1+tp_r)^Val!$F$12+Val!D12*(1-MIN(0.8,(tp_g-0.01)/tp_roe))*(1+(tp_g-0.01))/(tp_r-(tp_g-0.01))/(1+tp_r)^Val!$F$12)))*(1+tp_r)+(1-tp_w_dcf)*Val!$B$36 -> 240.04838 | D29: =C29/G29-1 -> -0.046974377 | E29: =tp_w_dcf*(tp_wA*(MAX(0,Val!B7*Val!$G$7*(1-MIN(0.8,(tp_g+0.01)/tp_roe))/(1+tp_r)^Val!$F$7+Val!B8*Val!$G$8*(1-MIN(0.8,(tp_g+0.01)/tp_roe))/(1+tp_r)^Val!$F$8+Val!B9*Val!$G$9*(1-MIN(0.8,(tp_g+0.01)/tp_roe))/(1+tp_r)^Val!$F$9+Val!B10*Val!$G$10*(1-MIN(0.8,(tp_g+0.01)/tp_roe))/(1+tp_r)^Val!$F$10+Val!B11*Val!$G$11*(1-MIN(0.8,(tp_g+0.01)/tp_roe))/(1+tp_r)^Val!$F$11+Val!B12*Val!$G$12*(1-MIN(0.8,(tp_g+0.01)/tp_roe))/(1+tp_r)^Val!$F$12+Val!B12*(1-MIN(0.8,(tp_g+0.01)/tp_roe))*(1+(tp_g+0.01))/(tp_r-(tp_g+0.01))/(1+tp_r)^Val!$F$12))+tp_wB*(MAX(0,Val!C7*Val!$G$7*(1-MIN(0.8,(tp_g+0.01)/tp_roe))/(1+tp_r)^Val!$F$7+Val!C8*Val!$G$8*(1-MIN(0.8,(tp_g+0.01)/tp_roe))/(1+tp_r)^Val!$F$8+Val!C9*Val!$G$9*(1-MIN(0.8,(tp_g+0.01)/tp_roe))/(1+tp_r)^Val!$F$9+Val!C10*Val!$G$10*(1-MIN(0.8,(tp_g+0.01)/tp_roe))/(1+tp_r)^Val!$F$10+Val!C11*Val!$G$11*(1-MIN(0.8,(tp_g+0.01)/tp_roe))/(1+tp_r)^Val!$F$11+Val!C12*Val!$G$12*(1-MIN(0.8,(tp_g+0.01)/tp_roe))/(1+tp_r)^Val!$F$12+Val!C12*(1-MIN(0.8,(tp_g+0.01)/tp_roe))*(1+(tp_g+0.01))/(tp_r-(tp_g+0.01))/(1+tp_r)^Val!$F$12))+tp_wC*(MAX(0,Val!D7*Val!$G$7*(1-MIN(0.8,(tp_g+0.01)/tp_roe))/(1+tp_r)^Val!$F$7+Val!D8*Val!$G$8*(1-MIN(0.8,(tp_g+0.01)/tp_roe))/(1+tp_r)^Val!$F$8+Val!D9*Val!$G$9*(1-MIN(0.8,(tp_g+0.01)/tp_roe))/(1+tp_r)^Val!$F$9+Val!D10*Val!$G$10*(1-MIN(0.8,(tp_g+0.01)/tp_roe))/(1+tp_r)^Val!$F$10+Val!D11*Val!$G$11*(1-MIN(0.8,(tp_g+0.01)/tp_roe))/(1+tp_r)^Val!$F$11+Val!D12*Val!$G$12*(1-MIN(0.8,(tp_g+0.01)/tp_roe))/(1+tp_r)^Val!$F$12+Val!D12*(1-MIN(0.8,(tp_g+0.01)/tp_roe))*(1+(tp_g+0.01))/(tp_r-(tp_g+0.01))/(1+tp_r)^Val!$F$12)))*(1+tp_r)+(1-tp_w_dcf)*Val!$B$36 -> 268.57797 | F29: =E29/G29-1 -> 0.066292092 | G29: =Val!$B$40 -> 251.8803
A30: tp_w_dcf 0.3／0.7 | B30: DCF 權重 0.3／0.7 | C30: =0.3*(tp_wA*(MAX(0,Val!B7*Val!$G$7*(1-MIN(0.8,tp_g/tp_roe))/(1+tp_r)^Val!$F$7+Val!B8*Val!$G$8*(1-MIN(0.8,tp_g/tp_roe))/(1+tp_r)^Val!$F$8+Val!B9*Val!$G$9*(1-MIN(0.8,tp_g/tp_roe))/(1+tp_r)^Val!$F$9+Val!B10*Val!$G$10*(1-MIN(0.8,tp_g/tp_roe))/(1+tp_r)^Val!$F$10+Val!B11*Val!$G$11*(1-MIN(0.8,tp_g/tp_roe))/(1+tp_r)^Val!$F$11+Val!B12*Val!$G$12*(1-MIN(0.8,tp_g/tp_roe))/(1+tp_r)^Val!$F$12+Val!B12*(1-MIN(0.8,tp_g/tp_roe))*(1+tp_g)/(tp_r-tp_g)/(1+tp_r)^Val!$F$12))+tp_wB*(MAX(0,Val!C7*Val!$G$7*(1-MIN(0.8,tp_g/tp_roe))/(1+tp_r)^Val!$F$7+Val!C8*Val!$G$8*(1-MIN(0.8,tp_g/tp_roe))/(1+tp_r)^Val!$F$8+Val!C9*Val!$G$9*(1-MIN(0.8,tp_g/tp_roe))/(1+tp_r)^Val!$F$9+Val!C10*Val!$G$10*(1-MIN(0.8,tp_g/tp_roe))/(1+tp_r)^Val!$F$10+Val!C11*Val!$G$11*(1-MIN(0.8,tp_g/tp_roe))/(1+tp_r)^Val!$F$11+Val!C12*Val!$G$12*(1-MIN(0.8,tp_g/tp_roe))/(1+tp_r)^Val!$F$12+Val!C12*(1-MIN(0.8,tp_g/tp_roe))*(1+tp_g)/(tp_r-tp_g)/(1+tp_r)^Val!$F$12))+tp_wC*(MAX(0,Val!D7*Val!$G$7*(1-MIN(0.8,tp_g/tp_roe))/(1+tp_r)^Val!$F$7+Val!D8*Val!$G$8*(1-MIN(0.8,tp_g/tp_roe))/(1+tp_r)^Val!$F$8+Val!D9*Val!$G$9*(1-MIN(0.8,tp_g/tp_roe))/(1+tp_r)^Val!$F$9+Val!D10*Val!$G$10*(1-MIN(0.8,tp_g/tp_roe))/(1+tp_r)^Val!$F$10+Val!D11*Val!$G$11*(1-MIN(0.8,tp_g/tp_roe))/(1+tp_r)^Val!$F$11+Val!D12*Val!$G$12*(1-MIN(0.8,tp_g/tp_roe))/(1+tp_r)^Val!$F$12+Val!D12*(1-MIN(0.8,tp_g/tp_roe))*(1+tp_g)/(tp_r-tp_g)/(1+tp_r)^Val!$F$12)))*(1+tp_r)+(1-0.3)*Val!$B$36 -> 258.61374 | D30: =C30/G30-1 -> 0.026732723 | E30: =0.7*(tp_wA*(MAX(0,Val!B7*Val!$G$7*(1-MIN(0.8,tp_g/tp_roe))/(1+tp_r)^Val!$F$7+Val!B8*Val!$G$8*(1-MIN(0.8,tp_g/tp_roe))/(1+tp_r)^Val!$F$8+Val!B9*Val!$G$9*(1-MIN(0.8,tp_g/tp_roe))/(1+tp_r)^Val!$F$9+Val!B10*Val!$G$10*(1-MIN(0.8,tp_g/tp_roe))/(1+tp_r)^Val!$F$10+Val!B11*Val!$G$11*(1-MIN(0.8,tp_g/tp_roe))/(1+tp_r)^Val!$F$11+Val!B12*Val!$G$12*(1-MIN(0.8,tp_g/tp_roe))/(1+tp_r)^Val!$F$12+Val!B12*(1-MIN(0.8,tp_g/tp_roe))*(1+tp_g)/(tp_r-tp_g)/(1+tp_r)^Val!$F$12))+tp_wB*(MAX(0,Val!C7*Val!$G$7*(1-MIN(0.8,tp_g/tp_roe))/(1+tp_r)^Val!$F$7+Val!C8*Val!$G$8*(1-MIN(0.8,tp_g/tp_roe))/(1+tp_r)^Val!$F$8+Val!C9*Val!$G$9*(1-MIN(0.8,tp_g/tp_roe))/(1+tp_r)^Val!$F$9+Val!C10*Val!$G$10*(1-MIN(0.8,tp_g/tp_roe))/(1+tp_r)^Val!$F$10+Val!C11*Val!$G$11*(1-MIN(0.8,tp_g/tp_roe))/(1+tp_r)^Val!$F$11+Val!C12*Val!$G$12*(1-MIN(0.8,tp_g/tp_roe))/(1+tp_r)^Val!$F$12+Val!C12*(1-MIN(0.8,tp_g/tp_roe))*(1+tp_g)/(tp_r-tp_g)/(1+tp_r)^Val!$F$12))+tp_wC*(MAX(0,Val!D7*Val!$G$7*(1-MIN(0.8,tp_g/tp_roe))/(1+tp_r)^Val!$F$7+Val!D8*Val!$G$8*(1-MIN(0.8,tp_g/tp_roe))/(1+tp_r)^Val!$F$8+Val!D9*Val!$G$9*(1-MIN(0.8,tp_g/tp_roe))/(1+tp_r)^Val!$F$9+Val!D10*Val!$G$10*(1-MIN(0.8,tp_g/tp_roe))/(1+tp_r)^Val!$F$10+Val!D11*Val!$G$11*(1-MIN(0.8,tp_g/tp_roe))/(1+tp_r)^Val!$F$11+Val!D12*Val!$G$12*(1-MIN(0.8,tp_g/tp_roe))/(1+tp_r)^Val!$F$12+Val!D12*(1-MIN(0.8,tp_g/tp_roe))*(1+tp_g)/(tp_r-tp_g)/(1+tp_r)^Val!$F$12)))*(1+tp_r)+(1-0.7)*Val!$B$36 -> 245.14685 | F30: =E30/G30-1 -> -0.026732723 | G30: =Val!$B$40 -> 251.8803
A40: 案例區塊：NVIDIA 顆數係數 低（×0.9）（情境 A）
A41: 項目 | B41: 單位 | C41: FY2026A | D41: FY2027 | E41: FY2028 | F41: FY2029 | G41: FY2030 | H41: 說明
A42: A. 由下而上（C 欄空白；D＝FY2027≈CY2026 … G＝FY2030≈CY2029；顆數為「認列顆數」＝市場層顆數 × k_rec，FY2027 的 Data Center 營收與毛利率因此等於錨點，FY2028 起沿用 k_rec）
A43: NVIDIA 認列顆數乘數（k_rec × Sens 乘數） | B43: x | D43: =k_rec -> 0.82837092 | E43: =k_rec*uk_lo -> 0.74553383 | F43: =k_rec*uk_lo -> 0.74553383 | G43: =k_rec*uk_lo -> 0.74553383
A44: NVIDIA Blackwell（B200／B300） 認列顆數 | B44: 百萬顆 | D44: =(u_bw_26)*D43 -> 4.473203 | E44: =(u_bw_27)*E43 -> 1.7892812 | F44: =(u_bw_28*um28_A)*F43 -> 0.37276691 | G44: =(u_bw_28*(1+g29_bw)*um29_A)*G43 -> 0.18638346
A45: NVIDIA Rubin 認列顆數 | B45: 百萬顆 | D45: =(u_rb_26)*D43 -> 1.4082306 | E45: =(u_rb_27)*E43 -> 5.2187368 | F45: =(u_rb_28*um28_A)*F43 -> 5.2187368 | G45: =(u_rb_28*(1+g29_rb)*um29_A)*G43 -> 6.0015473
A46: NVIDIA Rubin Ultra 認列顆數 | B46: 百萬顆 | D46: =(u_ru_26)*D43 -> 0 | E46: =(u_ru_27)*E43 -> 0.22366015 | F46: =(u_ru_28*um28_A)*F43 -> 1.4910677 | G46: =(u_ru_28*(1+g29_ru)*um29_A)*G43 -> 1.7147278
A47: NVIDIA Hopper（H200 等） 認列顆數 | B47: 百萬顆 | D47: =(u_hp_26)*D43 -> 0.41418546 | E47: =(u_hp_27)*E43 -> 0 | F47: =(u_hp_28*um28_A)*F43 -> 0 | G47: =(u_hp_28*(1+g29_hp)*um29_A)*G43 -> 0
A48: NVIDIA 認列顆數合計 | B48: 百萬顆 | D48: =SUM(D44:D47) -> 6.295619 | E48: =SUM(E44:E47) -> 7.2316781 | F48: =SUM(F44:F47) -> 7.0825714 | G48: =SUM(G44:G47) -> 7.9026586 | H48: 2026＝7.6、2027＝9.7、2028＝9.5（A）
A49: NVIDIA Blackwell（B200／B300） 每顆售價 | B49: US$K | D49: =1*(pm_bw+pcpu_bw+plp_bw+k_tray*pres_bw)+(1-abs_mem)*(gb_bw_26*hpx_bw*(hbm_A_26/hbm_A_26-1)/1000+plp_bw*(cdx_A_26/cdx_A_26-1)) -> 47.005555 | E49: =1*(pm_bw+pcpu_bw+plp_bw+k_tray*pres_bw)+(1-abs_mem)*(gb_bw_27*hpx_bw*(hbm_A_27/hbm_A_26-1)/1000+plp_bw*(cdx_A_27/cdx_A_26-1)) -> 49.186873 | F49: =1*(pm_bw+pcpu_bw+plp_bw+k_tray*pres_bw)+(1-abs_mem)*(gb_bw_28*hpx_bw*(hbm_A_28/hbm_A_26-1)/1000+plp_bw*(cdx_A_28/cdx_A_26-1)) -> 49.44753 | G49: =1*(pm_bw+pcpu_bw+plp_bw+k_tray*pres_bw)+(1-abs_mem)*(gb_bw_28*hpx_bw*(hbm_A_29/hbm_A_26-1)/1000+plp_bw*(cdx_A_29/cdx_A_26-1)) -> 49.054142 | H49: 基準價 ＋ (1−吸收比例) ×（HBM 與 LPDDR 相對 2026 的成本增加）
A50: NVIDIA Rubin 每顆售價 | B50: US$K | D50: =1*(pm_rb+pcpu_rb+plp_rb+k_tray*pres_rb)+(1-abs_mem)*(gb_rb_26*hpx_rb*(hbm_A_26/hbm_A_26-1)/1000+plp_rb*(cdx_A_26/cdx_A_26-1)) -> 72.166667 | E50: =1*(pm_rb+pcpu_rb+plp_rb+k_tray*pres_rb)+(1-abs_mem)*(gb_rb_27*hpx_rb*(hbm_A_27/hbm_A_26-1)/1000+plp_rb*(cdx_A_27/cdx_A_26-1)) -> 74.823972 | F50: =1*(pm_rb+pcpu_rb+plp_rb+k_tray*pres_rb)+(1-abs_mem)*(gb_rb_28*hpx_rb*(hbm_A_28/hbm_A_26-1)/1000+plp_rb*(cdx_A_28/cdx_A_26-1)) -> 74.942737 | G50: =1*(pm_rb+pcpu_rb+plp_rb+k_tray*pres_rb)+(1-abs_mem)*(gb_rb_28*hpx_rb*(hbm_A_29/hbm_A_26-1)/1000+plp_rb*(cdx_A_29/cdx_A_26-1)) -> 74.420676
A51: NVIDIA Rubin Ultra 每顆售價 | B51: US$K | D51: =1*(pm_ru+pcpu_ru+plp_ru+k_tray*pres_ru)+(1-abs_mem)*(gb_ru_26*hpx_ru*(hbm_A_26/hbm_A_26-1)/1000+plp_ru*(cdx_A_26/cdx_A_26-1)) -> 92.166667 | E51: =1*(pm_ru+pcpu_ru+plp_ru+k_tray*pres_ru)+(1-abs_mem)*(gb_ru_27*hpx_ru*(hbm_A_27/hbm_A_26-1)/1000+plp_ru*(cdx_A_27/cdx_A_26-1)) -> 99.740452 | F51: =1*(pm_ru+pcpu_ru+plp_ru+k_tray*pres_ru)+(1-abs_mem)*(gb_ru_28*hpx_ru*(hbm_A_28/hbm_A_26-1)/1000+plp_ru*(cdx_A_28/cdx_A_26-1)) -> 100.96543 | G51: =1*(pm_ru+pcpu_ru+plp_ru+k_tray*pres_ru)+(1-abs_mem)*(gb_ru_28*hpx_ru*(hbm_A_29/hbm_A_26-1)/1000+plp_ru*(cdx_A_29/cdx_A_26-1)) -> 99.83495
A52: NVIDIA Hopper（H200 等） 每顆售價 | B52: US$K | D52: =1*(pm_hp+pcpu_hp+plp_hp+k_tray*pres_hp)+(1-abs_mem)*(gb_hp_26*hpx_hp*(hbm_A_26/hbm_A_26-1)/1000+plp_hp*(cdx_A_26/cdx_A_26-1)) -> 30 | E52: =1*(pm_hp+pcpu_hp+plp_hp+k_tray*pres_hp)+(1-abs_mem)*(gb_hp_27*hpx_hp*(hbm_A_27/hbm_A_26-1)/1000+plp_hp*(cdx_A_27/cdx_A_26-1)) -> 30.8742 | F52: =1*(pm_hp+pcpu_hp+plp_hp+k_tray*pres_hp)+(1-abs_mem)*(gb_hp_28*hpx_hp*(hbm_A_28/hbm_A_26-1)/1000+plp_hp*(cdx_A_28/cdx_A_26-1)) -> 31.070895 | G52: =1*(pm_hp+pcpu_hp+plp_hp+k_tray*pres_hp)+(1-abs_mem)*(gb_hp_28*hpx_hp*(hbm_A_29/hbm_A_26-1)/1000+plp_hp*(cdx_A_29/cdx_A_26-1)) -> 30.962713
A53: NVIDIA Blackwell（B200／B300） 每顆 HBM 成本 | B53: US$K | D53: =gb_bw_26*hpx_bw*hbm_A_26/hbm_A_26/1000 -> 4.03 | E53: =gb_bw_27*hpx_bw*hbm_A_27/hbm_A_26/1000 -> 7.812 | F53: =gb_bw_28*hpx_bw*hbm_A_28/hbm_A_26/1000 -> 8.83872 | G53: =gb_bw_28*hpx_bw*hbm_A_29/hbm_A_26/1000 -> 8.396784 | H53: 容量 × 2026 合約價 × 情境別 HBM 價格指數（markets/memory）
A54: NVIDIA Rubin 每顆 HBM 成本 | B54: US$K | D54: =gb_rb_26*hpx_rb*hbm_A_26/hbm_A_26/1000 -> 4.8096 | E54: =gb_rb_27*hpx_rb*hbm_A_27/hbm_A_26/1000 -> 8.65728 | F54: =gb_rb_28*hpx_rb*hbm_A_28/hbm_A_26/1000 -> 9.523008 | G54: =gb_rb_28*hpx_rb*hbm_A_29/hbm_A_26/1000 -> 9.0468576
A55: NVIDIA Rubin Ultra 每顆 HBM 成本 | B55: US$K | D55: =gb_ru_26*hpx_ru*hbm_A_26/hbm_A_26/1000 -> 17.1008 | E55: =gb_ru_27*hpx_ru*hbm_A_27/hbm_A_26/1000 -> 30.78144 | F55: =gb_ru_28*hpx_ru*hbm_A_28/hbm_A_26/1000 -> 33.859584 | G55: =gb_ru_28*hpx_ru*hbm_A_29/hbm_A_26/1000 -> 32.166605
A56: NVIDIA Hopper（H200 等） 每顆 HBM 成本 | B56: US$K | D56: =gb_hp_26*hpx_hp*hbm_A_26/hbm_A_26/1000 -> 2.1855 | E56: =gb_hp_27*hpx_hp*hbm_A_27/hbm_A_26/1000 -> 3.9339 | F56: =gb_hp_28*hpx_hp*hbm_A_28/hbm_A_26/1000 -> 4.32729 | G56: =gb_hp_28*hpx_hp*hbm_A_29/hbm_A_26/1000 -> 4.1109255
A57: NVIDIA Blackwell（B200／B300） 每顆成本 | B57: US$K | D57: =1*c_nh*(pm_bw+pcpu_bw+plp_bw+k_tray*pres_bw)+D53+plp_bw*(cdx_A_26/cdx_A_26-1) -> 11.821282 | E57: =1*c_nh*(pm_bw+pcpu_bw+plp_bw+k_tray*pres_bw)+E53+plp_bw*(cdx_A_27/cdx_A_26-1) -> 16.493919 | F57: =1*c_nh*(pm_bw+pcpu_bw+plp_bw+k_tray*pres_bw)+F53+plp_bw*(cdx_A_28/cdx_A_26-1) -> 17.139233 | G57: =1*c_nh*(pm_bw+pcpu_bw+plp_bw+k_tray*pres_bw)+G53+plp_bw*(cdx_A_29/cdx_A_26-1) -> 16.352457 | H57: 非 HBM 成本（基準價 × c_nh，FY2027 校準）＋ HBM 成本 ＋ LPDDR 成本增加（每顆；顆數另乘 k_rec）
A58: NVIDIA Rubin 每顆成本 | B58: US$K | D58: =1*c_nh*(pm_rb+pcpu_rb+plp_rb+k_tray*pres_rb)+D54+plp_rb*(cdx_A_26/cdx_A_26-1) -> 16.771396 | E58: =1*c_nh*(pm_rb+pcpu_rb+plp_rb+k_tray*pres_rb)+E54+plp_rb*(cdx_A_27/cdx_A_26-1) -> 22.086007 | F58: =1*c_nh*(pm_rb+pcpu_rb+plp_rb+k_tray*pres_rb)+F54+plp_rb*(cdx_A_28/cdx_A_26-1) -> 22.323537 | G58: =1*c_nh*(pm_rb+pcpu_rb+plp_rb+k_tray*pres_rb)+G54+plp_rb*(cdx_A_29/cdx_A_26-1) -> 21.279415
A59: NVIDIA Rubin Ultra 每顆成本 | B59: US$K | D59: =1*c_nh*(pm_ru+pcpu_ru+plp_ru+k_tray*pres_ru)+D55+plp_ru*(cdx_A_26/cdx_A_26-1) -> 32.377644 | E59: =1*c_nh*(pm_ru+pcpu_ru+plp_ru+k_tray*pres_ru)+E55+plp_ru*(cdx_A_27/cdx_A_26-1) -> 47.525215 | F59: =1*c_nh*(pm_ru+pcpu_ru+plp_ru+k_tray*pres_ru)+F55+plp_ru*(cdx_A_28/cdx_A_26-1) -> 49.97516 | G59: =1*c_nh*(pm_ru+pcpu_ru+plp_ru+k_tray*pres_ru)+G55+plp_ru*(cdx_A_29/cdx_A_26-1) -> 47.71421
A60: NVIDIA Hopper（H200 等） 每顆成本 | B60: US$K | D60: =1*c_nh*(pm_hp+pcpu_hp+plp_hp+k_tray*pres_hp)+D56+plp_hp*(cdx_A_26/cdx_A_26-1) -> 7.1580712 | E60: =1*c_nh*(pm_hp+pcpu_hp+plp_hp+k_tray*pres_hp)+E56+plp_hp*(cdx_A_27/cdx_A_26-1) -> 8.9064712 | F60: =1*c_nh*(pm_hp+pcpu_hp+plp_hp+k_tray*pres_hp)+F56+plp_hp*(cdx_A_28/cdx_A_26-1) -> 9.2998612 | G60: =1*c_nh*(pm_hp+pcpu_hp+plp_hp+k_tray*pres_hp)+G56+plp_hp*(cdx_A_29/cdx_A_26-1) -> 9.0834967
A61: NVIDIA Blackwell（B200／B300） 運算營收 | B61: US$B | D61: =D44*D49 -> 210.26539 | E61: =E44*E49 -> 88.009147 | F61: =F44*F49 -> 18.432403 | G61: =G44*G49 -> 9.1428806
A62: NVIDIA Rubin 運算營收 | B62: US$B | D62: =D45*D50 -> 101.62731 | E62: =E45*E50 -> 390.48662 | F62: =F45*F50 -> 391.10642 | G62: =G45*G50 -> 446.63921
A63: NVIDIA Rubin Ultra 運算營收 | B63: US$B | D63: =D46*D51 -> 0 | E63: =E46*E51 -> 22.307964 | F63: =F46*F51 -> 150.54628 | G63: =G46*G51 -> 171.18976
A64: NVIDIA Hopper（H200 等） 運算營收 | B64: US$B | D64: =D47*D52 -> 12.425564 | E64: =E47*E52 -> 0 | F64: =F47*F52 -> 0 | G64: =G47*G52 -> 0
A65: 運算營收（Σ 顆數 × 每顆售價） | B65: US$B | D65: =SUM(D61:D64) -> 324.31826 | E65: =SUM(E61:E64) -> 500.80373 | F65: =SUM(F61:F64) -> 560.0851 | G65: =SUM(G61:G64) -> 626.97186
A66: 運算成本 | B66: US$B | D66: =D44*D57+D45*D58+D46*D59+D47*D60 -> 79.461757 | E66: =E44*E57+E45*E58+E46*E59+E47*E60 -> 155.40281 | F66: =F44*F57+F45*F58+F46*F59+F47*F60 -> 197.40595 | G66: =G44*G57+G45*G58+G46*G59+G47*G60 -> 212.57412
A67: 其中 HBM 成本 | B67: US$B | D67: =D44*D53+D45*D54+D46*D55+D47*D56 -> 25.705236 | E67: =E44*E53+E45*E54+E46*E55+E47*E56 -> 66.042512 | F67: =F44*F53+F45*F54+F46*F55+F47*F56 -> 103.47979 | G67: =G44*G53+G45*G54+G46*G55+G47*G56 -> 111.01714
A68: 中國資料中心運算營收（基準為 0＝公司指引假設；Sens 列恢復） | B68: US$B | D68: =0 -> 0 | E68: =0 -> 0 | F68: =0 -> 0 | G68: =0 -> 0
A69: 中國部分成本（毛利率同運算） | B69: US$B | D69: =D68*D66/D65 -> 0 | E69: =E68*E66/E65 -> 0 | F69: =F68*F66/F65 -> 0 | G69: =G68*G66/G65 -> 0
A70: NVIDIA 網通營收（本模型歸屬 × 情境顆數係數 × 乘數） | B70: US$B | D70: =net_26*1*D43 -> 51.138539 | E70: =net_27*1*E43 -> 91.318996 | F70: =net_28*um28_A*F43 -> 103.34351 | G70: =net_29*um29_A*G43 -> 117.27226 | H70: markets/network；網通金額與 NVIDIA 顆數成正比
A71: 網通成本（c_net × 營收） | B71: US$B | D71: =c_net*D70 -> 15.341562 | E71: =c_net*E70 -> 27.395699 | F71: =c_net*F70 -> 31.003054 | G71: =c_net*G70 -> 35.181677
A72: Edge Computing 營收 | B72: US$B | D72: =a27_edge -> 29.179202 | E72: =D72*(1+eg) -> 31.513539 | F72: =E72*(1+eg) -> 34.034622 | G72: =F72*(1+eg) -> 36.757392
A73: Edge 成本 | B73: US$B | D73: =(1-gm_edge)*D72 -> 11.671681 | E73: =(1-gm_edge)*E72 -> 12.605415 | F73: =(1-gm_edge)*F72 -> 13.613849 | G73: =(1-gm_edge)*G72 -> 14.702957
A74: 由下而上營收合計 | B74: US$B | D74: =D65+D68+D70+D72 -> 404.636 | E74: =E65+E68+E70+E72 -> 623.63627 | F74: =F65+F68+F70+F72 -> 697.46324 | G74: =G65+G68+G70+G72 -> 781.0015
A75: 由下而上成本合計 | B75: US$B | D75: =D66+D69+D71+D73 -> 106.475 | E75: =E66+E69+E71+E73 -> 195.40393 | F75: =F66+F69+F71+F73 -> 242.02285 | G75: =G66+G69+G71+G73 -> 262.45876
A76: 由下而上毛利率 | B76: % | D76: =1-D75/D74 -> 0.73686227 | E76: =1-E75/E74 -> 0.68667004 | F76: =1-F75/F74 -> 0.65299555 | G76: =1-G75/G74 -> 0.6639459 | H76: FY2027 ＝ 錨點毛利率（c_nh 校準的恆等式，非獨立檢驗；對照區塊 k_rec＝1 時用 c_nh_p）
A77: HBM 成本占由下而上營收 | B77: % | D77: =D67/D74 -> 0.063526814 | E77: =E67/E74 -> 0.10589909 | F77: =F67/F74 -> 0.14836593 | G77: =G67/G74 -> 0.14214715
A78: B. 報告值（FY2026A、FY2027 為實績與錨點；FY2028 起為由下而上）
A79: 營收 | B79: US$B | C79: =a26_rev -> 215.938 | D79: =a27_rev -> 404.636 | E79: =E74 -> 623.63627 | F79: =F74 -> 697.46324 | G79: =G74 -> 781.0015
A80: Data Center（運算＋網通＋中國） | B80: US$B | C80: =a26_dc -> 193.7 | D80: =a27_dc -> 375.4568 | E80: =E65+E68+E70 -> 592.12273 | F80: =F65+F68+F70 -> 663.42862 | G80: =G65+G68+G70 -> 744.24411
A81: Edge Computing | B81: US$B | C81: =a26_edge -> 22.238 | D81: =a27_edge -> 29.179202 | E81: =E72 -> 31.513539 | F81: =F72 -> 34.034622 | G81: =G72 -> 36.757392
A82: 營收年增 | B82: % | D82: =D79/C79-1 -> 0.87385268 | E82: =E79/D79-1 -> 0.54122783 | F82: =F79/E79-1 -> 0.11838147 | G82: =G79/F79-1 -> 0.11977443
A83: 毛利 | B83: US$B | C83: =a26_gp -> 153.463 | D83: =a27_gp -> 298.161 | E83: =E79-E75 -> 428.23234 | F83: =F79-F75 -> 455.44039 | G83: =G79-G75 -> 518.54275
A84: 毛利率 | B84: % | C84: =C83/C79 -> 0.71068084 | D84: =D83/D79 -> 0.73686227 | E84: =E83/E79 -> 0.68667004 | F84: =F83/F79 -> 0.65299555 | G84: =G83/G79 -> 0.6639459
A85: 營業費用（基準路徑） | B85: US$B | C85: =a26_opx -> 23.076 | D85: =a27_opx -> 35.165 | E85: =D85*(1+MAX(g_opx_min,phi*E82)) -> 46.584366 | F85: =E85*(1+MAX(g_opx_min,phi*F82)) -> 49.893201 | G85: =F85*(1+MAX(g_opx_min,phi*G82)) -> 53.478759 | H85: 前一年 ×（1＋MAX(下限, 彈性 × 營收年增)）
A86: 營業費用 | B86: US$B | C86: =C85 -> 23.076 | D86: =D85 -> 35.165 | E86: =E85+0*E79 -> 46.584366 | F86: =F85+0*F79 -> 49.893201 | G86: =G85+0*G79 -> 53.478759
A87: 營業利益 | B87: US$B | C87: =C83-C86 -> 130.387 | D87: =D83-D86 -> 262.996 | E87: =E83-E86 -> 381.64797 | F87: =F83-F86 -> 405.54719 | G87: =G83-G86 -> 465.06399
A88: 營業利益率 | B88: % | C88: =C87/C79 -> 0.60381684 | D88: =D87/D79 -> 0.649957 | E88: =E87/E79 -> 0.61197206 | F88: =F87/F79 -> 0.58146031 | G88: =G87/G79 -> 0.59547131
A89: 其他收益淨額（不含權益證券損益） | B89: US$B | C89: =a26_oth -> 2.145 | D89: =a27_oth -> 1.133 | E89: =oth_f -> 1.2 | F89: =oth_f -> 1.2 | G89: =oth_f -> 1.2
A90: 有效稅率 | B90: % | C90: =1-a26_ni/(a26_oi+a26_oth) -> 0.15118757 | D90: =a27_etr -> 0.16798084 | E90: =tx_f -> 0.17 | F90: =tx_f -> 0.17 | G90: =tx_f -> 0.17
A91: 淨利（不含權益證券損益） | B91: US$B | C91: =a26_ni -> 112.49481 | D91: =a27_ni -> 219.76039 | E91: =(E87+E89)*(1-E90) -> 317.76382 | F91: =(F87+F89)*(1-F90) -> 337.60017 | G91: =(G87+G89)*(1-G90) -> 386.99911
A92: 稀釋股數 | B92: 十億股 | C92: =a26_sh -> 24.5145 | D92: =a27_sh -> 24.256913 | E92: =D92*(1+sh_g) -> 23.96583 | F92: =E92*(1+sh_g) -> 23.67824 | G92: =F92*(1+sh_g) -> 23.394102
A93: EPS（不含權益證券損益） | B93: US$ | C93: =C91/C92 -> 4.588909 | D93: =D91/D92 -> 9.0597013 | E93: =E91/E92 -> 13.259036 | F93: =F91/F92 -> 14.257823 | G93: =G91/G92 -> 16.542593
A94: EPS 年增 | B94: % | D94: =D93/C93-1 -> 0.9742604 | E94: =E93/D93-1 -> 0.46351804 | F94: =F93/E93-1 -> 0.075328771 | G94: =G93/F93-1 -> 0.16024677
A97: 案例區塊：NVIDIA 顆數係數 高（×1.1）（情境 A）
A98: 項目 | B98: 單位 | C98: FY2026A | D98: FY2027 | E98: FY2028 | F98: FY2029 | G98: FY2030 | H98: 說明
A99: A. 由下而上（C 欄空白；D＝FY2027≈CY2026 … G＝FY2030≈CY2029；顆數為「認列顆數」＝市場層顆數 × k_rec，FY2027 的 Data Center 營收與毛利率因此等於錨點，FY2028 起沿用 k_rec）
A100: NVIDIA 認列顆數乘數（k_rec × Sens 乘數） | B100: x | D100: =k_rec -> 0.82837092 | E100: =k_rec*uk_hi -> 0.91120801 | F100: =k_rec*uk_hi -> 0.91120801 | G100: =k_rec*uk_hi -> 0.91120801
A101: NVIDIA Blackwell（B200／B300） 認列顆數 | B101: 百萬顆 | D101: =(u_bw_26)*D100 -> 4.473203 | E101: =(u_bw_27)*E100 -> 2.1868992 | F101: =(u_bw_28*um28_A)*F100 -> 0.45560401 | G101: =(u_bw_28*(1+g29_bw)*um29_A)*G100 -> 0.227802
A102: NVIDIA Rubin 認列顆數 | B102: 百萬顆 | D102: =(u_rb_26)*D100 -> 1.4082306 | E102: =(u_rb_27)*E100 -> 6.3784561 | F102: =(u_rb_28*um28_A)*F100 -> 6.3784561 | G102: =(u_rb_28*(1+g29_rb)*um29_A)*G100 -> 7.3352245
A103: NVIDIA Rubin Ultra 認列顆數 | B103: 百萬顆 | D103: =(u_ru_26)*D100 -> 0 | E103: =(u_ru_27)*E100 -> 0.2733624 | F103: =(u_ru_28*um28_A)*F100 -> 1.822416 | G103: =(u_ru_28*(1+g29_ru)*um29_A)*G100 -> 2.0957784
A104: NVIDIA Hopper（H200 等） 認列顆數 | B104: 百萬顆 | D104: =(u_hp_26)*D100 -> 0.41418546 | E104: =(u_hp_27)*E100 -> 0 | F104: =(u_hp_28*um28_A)*F100 -> 0 | G104: =(u_hp_28*(1+g29_hp)*um29_A)*G100 -> 0
A105: NVIDIA 認列顆數合計 | B105: 百萬顆 | D105: =SUM(D101:D104) -> 6.295619 | E105: =SUM(E101:E104) -> 8.8387177 | F105: =SUM(F101:F104) -> 8.6564761 | G105: =SUM(G101:G104) -> 9.6588049 | H105: 2026＝7.6、2027＝9.7、2028＝9.5（A）
A106: NVIDIA Blackwell（B200／B300） 每顆售價 | B106: US$K | D106: =1*(pm_bw+pcpu_bw+plp_bw+k_tray*pres_bw)+(1-abs_mem)*(gb_bw_26*hpx_bw*(hbm_A_26/hbm_A_26-1)/1000+plp_bw*(cdx_A_26/cdx_A_26-1)) -> 47.005555 | E106: =1*(pm_bw+pcpu_bw+plp_bw+k_tray*pres_bw)+(1-abs_mem)*(gb_bw_27*hpx_bw*(hbm_A_27/hbm_A_26-1)/1000+plp_bw*(cdx_A_27/cdx_A_26-1)) -> 49.186873 | F106: =1*(pm_bw+pcpu_bw+plp_bw+k_tray*pres_bw)+(1-abs_mem)*(gb_bw_28*hpx_bw*(hbm_A_28/hbm_A_26-1)/1000+plp_bw*(cdx_A_28/cdx_A_26-1)) -> 49.44753 | G106: =1*(pm_bw+pcpu_bw+plp_bw+k_tray*pres_bw)+(1-abs_mem)*(gb_bw_28*hpx_bw*(hbm_A_29/hbm_A_26-1)/1000+plp_bw*(cdx_A_29/cdx_A_26-1)) -> 49.054142 | H106: 基準價 ＋ (1−吸收比例) ×（HBM 與 LPDDR 相對 2026 的成本增加）
A107: NVIDIA Rubin 每顆售價 | B107: US$K | D107: =1*(pm_rb+pcpu_rb+plp_rb+k_tray*pres_rb)+(1-abs_mem)*(gb_rb_26*hpx_rb*(hbm_A_26/hbm_A_26-1)/1000+plp_rb*(cdx_A_26/cdx_A_26-1)) -> 72.166667 | E107: =1*(pm_rb+pcpu_rb+plp_rb+k_tray*pres_rb)+(1-abs_mem)*(gb_rb_27*hpx_rb*(hbm_A_27/hbm_A_26-1)/1000+plp_rb*(cdx_A_27/cdx_A_26-1)) -> 74.823972 | F107: =1*(pm_rb+pcpu_rb+plp_rb+k_tray*pres_rb)+(1-abs_mem)*(gb_rb_28*hpx_rb*(hbm_A_28/hbm_A_26-1)/1000+plp_rb*(cdx_A_28/cdx_A_26-1)) -> 74.942737 | G107: =1*(pm_rb+pcpu_rb+plp_rb+k_tray*pres_rb)+(1-abs_mem)*(gb_rb_28*hpx_rb*(hbm_A_29/hbm_A_26-1)/1000+plp_rb*(cdx_A_29/cdx_A_26-1)) -> 74.420676
A108: NVIDIA Rubin Ultra 每顆售價 | B108: US$K | D108: =1*(pm_ru+pcpu_ru+plp_ru+k_tray*pres_ru)+(1-abs_mem)*(gb_ru_26*hpx_ru*(hbm_A_26/hbm_A_26-1)/1000+plp_ru*(cdx_A_26/cdx_A_26-1)) -> 92.166667 | E108: =1*(pm_ru+pcpu_ru+plp_ru+k_tray*pres_ru)+(1-abs_mem)*(gb_ru_27*hpx_ru*(hbm_A_27/hbm_A_26-1)/1000+plp_ru*(cdx_A_27/cdx_A_26-1)) -> 99.740452 | F108: =1*(pm_ru+pcpu_ru+plp_ru+k_tray*pres_ru)+(1-abs_mem)*(gb_ru_28*hpx_ru*(hbm_A_28/hbm_A_26-1)/1000+plp_ru*(cdx_A_28/cdx_A_26-1)) -> 100.96543 | G108: =1*(pm_ru+pcpu_ru+plp_ru+k_tray*pres_ru)+(1-abs_mem)*(gb_ru_28*hpx_ru*(hbm_A_29/hbm_A_26-1)/1000+plp_ru*(cdx_A_29/cdx_A_26-1)) -> 99.83495
A109: NVIDIA Hopper（H200 等） 每顆售價 | B109: US$K | D109: =1*(pm_hp+pcpu_hp+plp_hp+k_tray*pres_hp)+(1-abs_mem)*(gb_hp_26*hpx_hp*(hbm_A_26/hbm_A_26-1)/1000+plp_hp*(cdx_A_26/cdx_A_26-1)) -> 30 | E109: =1*(pm_hp+pcpu_hp+plp_hp+k_tray*pres_hp)+(1-abs_mem)*(gb_hp_27*hpx_hp*(hbm_A_27/hbm_A_26-1)/1000+plp_hp*(cdx_A_27/cdx_A_26-1)) -> 30.8742 | F109: =1*(pm_hp+pcpu_hp+plp_hp+k_tray*pres_hp)+(1-abs_mem)*(gb_hp_28*hpx_hp*(hbm_A_28/hbm_A_26-1)/1000+plp_hp*(cdx_A_28/cdx_A_26-1)) -> 31.070895 | G109: =1*(pm_hp+pcpu_hp+plp_hp+k_tray*pres_hp)+(1-abs_mem)*(gb_hp_28*hpx_hp*(hbm_A_29/hbm_A_26-1)/1000+plp_hp*(cdx_A_29/cdx_A_26-1)) -> 30.962713
A110: NVIDIA Blackwell（B200／B300） 每顆 HBM 成本 | B110: US$K | D110: =gb_bw_26*hpx_bw*hbm_A_26/hbm_A_26/1000 -> 4.03 | E110: =gb_bw_27*hpx_bw*hbm_A_27/hbm_A_26/1000 -> 7.812 | F110: =gb_bw_28*hpx_bw*hbm_A_28/hbm_A_26/1000 -> 8.83872 | G110: =gb_bw_28*hpx_bw*hbm_A_29/hbm_A_26/1000 -> 8.396784 | H110: 容量 × 2026 合約價 × 情境別 HBM 價格指數（markets/memory）
A111: NVIDIA Rubin 每顆 HBM 成本 | B111: US$K | D111: =gb_rb_26*hpx_rb*hbm_A_26/hbm_A_26/1000 -> 4.8096 | E111: =gb_rb_27*hpx_rb*hbm_A_27/hbm_A_26/1000 -> 8.65728 | F111: =gb_rb_28*hpx_rb*hbm_A_28/hbm_A_26/1000 -> 9.523008 | G111: =gb_rb_28*hpx_rb*hbm_A_29/hbm_A_26/1000 -> 9.0468576
A112: NVIDIA Rubin Ultra 每顆 HBM 成本 | B112: US$K | D112: =gb_ru_26*hpx_ru*hbm_A_26/hbm_A_26/1000 -> 17.1008 | E112: =gb_ru_27*hpx_ru*hbm_A_27/hbm_A_26/1000 -> 30.78144 | F112: =gb_ru_28*hpx_ru*hbm_A_28/hbm_A_26/1000 -> 33.859584 | G112: =gb_ru_28*hpx_ru*hbm_A_29/hbm_A_26/1000 -> 32.166605
A113: NVIDIA Hopper（H200 等） 每顆 HBM 成本 | B113: US$K | D113: =gb_hp_26*hpx_hp*hbm_A_26/hbm_A_26/1000 -> 2.1855 | E113: =gb_hp_27*hpx_hp*hbm_A_27/hbm_A_26/1000 -> 3.9339 | F113: =gb_hp_28*hpx_hp*hbm_A_28/hbm_A_26/1000 -> 4.32729 | G113: =gb_hp_28*hpx_hp*hbm_A_29/hbm_A_26/1000 -> 4.1109255
A114: NVIDIA Blackwell（B200／B300） 每顆成本 | B114: US$K | D114: =1*c_nh*(pm_bw+pcpu_bw+plp_bw+k_tray*pres_bw)+D110+plp_bw*(cdx_A_26/cdx_A_26-1) -> 11.821282 | E114: =1*c_nh*(pm_bw+pcpu_bw+plp_bw+k_tray*pres_bw)+E110+plp_bw*(cdx_A_27/cdx_A_26-1) -> 16.493919 | F114: =1*c_nh*(pm_bw+pcpu_bw+plp_bw+k_tray*pres_bw)+F110+plp_bw*(cdx_A_28/cdx_A_26-1) -> 17.139233 | G114: =1*c_nh*(pm_bw+pcpu_bw+plp_bw+k_tray*pres_bw)+G110+plp_bw*(cdx_A_29/cdx_A_26-1) -> 16.352457 | H114: 非 HBM 成本（基準價 × c_nh，FY2027 校準）＋ HBM 成本 ＋ LPDDR 成本增加（每顆；顆數另乘 k_rec）
...

Sheet Sources
A1: 來源（公司原文＝NVIDIA 8-K 新聞稿，已逐頁抓取；CFO 書面說明、10-Q、法說逐字稿在建置環境無法開啟，其內容只經搜尋摘要）
A2: 公司：Q2 FY27 新聞稿（2026-08-26） | B2: https://nvidianews.nvidia.com/news/nvidia-announces-financial-results-for-second-quarter-fiscal-2027
A3: 公司：Q1 FY27 新聞稿（2026-05-20） | B3: https://nvidianews.nvidia.com/news/nvidia-announces-financial-results-for-first-quarter-fiscal-2027
A4: 公司：Q4 FY26 新聞稿 | B4: https://nvidianews.nvidia.com/news/nvidia-announces-financial-results-for-fourth-quarter-and-fiscal-2026
A5: 公司：Q3 FY26 新聞稿 | B5: https://nvidianews.nvidia.com/news/nvidia-announces-financial-results-for-third-quarter-fiscal-2026
A6: 公司：Q2 FY26 新聞稿 | B6: https://nvidianews.nvidia.com/news/nvidia-announces-financial-results-for-second-quarter-fiscal-2026
A7: 公司：Q1 FY26 新聞稿 | B7: https://nvidianews.nvidia.com/news/nvidia-announces-financial-results-for-first-quarter-fiscal-2026
A8: 公司：Q4 FY25 新聞稿（FY2025 全年；EPS 歷史） | B8: https://nvidianews.nvidia.com/news/nvidia-announces-financial-results-for-fourth-quarter-and-fiscal-2025
A9: 公司：FY2016–FY2024 第四季新聞稿（EPS 歷史） | B9: https://nvidianews.nvidia.com/news/nvidia-announces-financial-results-for-fourth-quarter-and-fiscal-2024 等
A10: 公司：Q1 FY27 CFO 書面說明（網通 14.8 之外的拆分；無法開啟：未找到） | B10: https://s201.q4cdn.com/141608511/files/doc_financials/2027/Q127/Q1FY27-CFO-Commentary.pdf
A11: 二手：Q2 FY27 法說摘要（FY2028 營收約 +70%、毛利率路徑） | B11: https://finance.yahoo.com/technology/ai/articles/nvidia-q2-earnings-call-highlights-230417656.html
A12: 二手：CNBC（70% 成長） | B12: https://www.cnbc.com/2026/08/26/nvidia-70percent-growth-forecast-puts-it-on-track-to-be-tech-no-2-company.html
A13: 二手：implicator.ai（毛利率路徑 Q4 FY27 71–72%、FY2028 72–73%） | B13: https://www.implicator.ai/nvidia-70-percent-growth-forecast-margin-outlook/
... A26: 二手：Kaiso（2028 前 NVIDIA 份額 60–75%） | B26: https://www.kaisoresearch.com/blog/ai-accelerators-market-431b-by
A27: 市場層：markets/memory/market.py（UNITS）；tsmc、skhynix、markets/network、markets/chip_bridge、markets/equipment 成品（本 repo）
A28: 待補（人工）：FY2016–FY2025 會計年度年底收盤價（Yahoo／Nasdaq 歷史價）；CFO 書面說明；Q2 FY27 法說逐字稿 | B28: 未找到
A29: SemiAnalysis | B29: 未單獨使用（僅作為 Ironwood 租用價的二手出處，未採）
