Workbook

Sheet README
A1: Kioxia（285A JP）收支與估值模型 v0.1（AI 半導體 Project：記憶體——NAND） 2026-10-25
A2: 模型命題：Kioxia 是全球第三、四大 NAND 廠（2Q26 營收市占 13.6%），與 SanDisk 共用四日市、北上合資產能；盈餘由 NAND 合約價循環、AI 推論帶動的企業級 SSD 位元與日圓匯率決定。問題是 2026 年的高價能維持多久（FY2027 起三情境分歧），以及現價約 2.6 倍前瞻 P/E 是否已反映循環見頂。
A3: 重點觀察
A4: ="1. 加權目標價 ¥"&TEXT(Val!B49,"#,##0")&"，相對現價 ¥"&TEXT(px,"#,##0")&"（2026-10-23 收盤）"&TEXT(Val!B52,"+0.0%;−0.0%")&"。主因是現價的倍數低於同業：Kioxia 現價 ÷ 2028-03 共識每股淨值 1.63x，同業中位數 "&TEXT(Val!B32,"0.00")&"x（SanDisk 2.86x、美光 3.35x），Comparable ¥"&TEXT(Val!B34,"#,##0")&"（"&TEXT(Val!B53,"+0%;−0%")&"）；DCF ¥"&TEXT(Val!B24,"#,##0")&" 也高於現價，因現價只有 FY2027 EPS（A）的 "&TEXT(Val!B85,"0.0")&" 倍。股價 10-09 至 10-23 已跌 27%（17,505 → 12,755）。" -> 1. 加權目標價 ¥20,500，相對現價 ¥12,755（2026-10-23 收盤）+60.7%。主因是現價的倍數低於同業：Kioxia 現價 ÷ 2028-03 共識每股淨值 1.63x，同業中位數 2.10x（SanDisk 2.86x、美光 3.35x），Comparable ¥18,948（+49%）；DCF ¥22,052 也高於現價，因現價只有 FY2027 EPS（A）的 2.7 倍。股價 10-09 至 10-23 已跌 27%（17,505 → 12,755）。
A5: ="2. 本模型 FY2026 EPS（A）¥"&TEXT(PL!D14,"#,##0")&"，比共識 ¥3,486 "&TEXT(PL!D14/cons_eps26-1,"+0%;−0%")&"；上半年已由兩季實績鎖定（淨利 ¥2,202B）。v0.3 滾入第二季（營收 ¥2,480.0B、營業利益 ¥1,994.7B，皆高於指引）。v0.4 對帳：模型第三季營收 ¥"&TEXT(Recon!C7,"#,##0")&"B，比指引 ¥2,500B "&TEXT(Recon!D7,"+0.0%;−0.0%")&"（v0.3 為 +21.5%）。原因是市場層把合約價當實現價（2026Q3 實現 +25%、2026Q4 改 +8.1%，兩季累計不變），且份額只用出貨提前的單一季（改取兩季平均）；餘差為匯率假設與公司出貨季別移動（同一會計年度內）。" -> 2. 本模型 FY2026 EPS（A）¥3,360，比共識 ¥3,486 −4%；上半年已由兩季實績鎖定（淨利 ¥2,202B）。v0.3 滾入第二季（營收 ¥2,480.0B、營業利益 ¥1,994.7B，皆高於指引）。v0.4 對帳：模型第三季營收 ¥2,671B，比指引 ¥2,500B +6.8%（v0.3 為 +21.5%）。原因是市場層把合約價當實現價（2026Q3 實現 +25%、2026Q4 改 +8.1%，兩季累計不變），且份額只用出貨提前的單一季（改取兩季平均）；餘差為匯率假設與公司出貨季別移動（同一會計年度內）。
A6: ="3. 營收以美元計、成本以日圓計：匯率 145／170 日圓使 FY2028 EPS（A）變動 "&TEXT(Sens!H9,"+0%;−0%")&"／"&TEXT(Sens!H10,"+0%;−0%")&"；2027 起季價 ±20% 為 "&TEXT(Sens!H5,"+0%;−0%")&"／"&TEXT(Sens!H6,"+0%;−0%")&"。情境 C 的 FY2029 毛利率降到 "&TEXT(PL!G38,"0%")&"。追蹤：TrendForce 每季初的 NAND 合約價、日圓匯率、SanDisk 2026-10-29 財報（合資群位元）。" -> 3. 營收以美元計、成本以日圓計：匯率 145／170 日圓使 FY2028 EPS（A）變動 −13%／+9%；2027 起季價 ±20% 為 −28%／+30%。情境 C 的 FY2029 毛利率降到 49%。追蹤：TrendForce 每季初的 NAND 合約價、日圓匯率、SanDisk 2026-10-29 財報（合資群位元）。
A7: ="投資建議："&Val!B55&"（依上檔空間固定規則；上檔空間："&TEXT(Val!B52,"+0.0%;−0.0%")&"，級距："&Val!B54&"）" -> 投資建議：強力買進（依上檔空間固定規則；上檔空間：+60.7%，級距：大於 50%）
A9: 驅動因子 → 推導量（因果方向：左邊決定右邊）
A10: Units｜markets/nand 成品：Kioxia 季度營收（市場營收 × 份額，美元；同字母情境）與位元（季度出貨 × 份額）
A11: PL 區塊｜營收＝市場層 × 公司口徑係數 × 匯率；營業成本＝位元 × 每 EB 成本（日圓；第二季以實績校準，之後每年 × (1 − 成本年降)）；營業費用＝固定＋變動
A12: PL 區塊｜淨利＝（營業利益＋業外＋淨現金收益）×（1 − 稅率）；自由現金流＝淨利＋折舊 − 資本支出（¥470B／年）；股東回饋＝20% × FCF（以買回計）→ 股數 → EPS、每股淨值
A13: Val｜第 0 節目標價＝DCF（FY2027–FY2032＋永續）與 Comparable（同業前瞻 P/B × 約 2028 年底每股淨值）各半；第 5–6 節目前倍數、十年倍數規則值（美光 Analogy）
A15: 會計年度：4 月到隔年 3 月（FY2026＝2026-04～2027-03 ≈ CY2026Q2–CY2027Q1）。前瞻 EPS 依月份調整：12 個月後（約 2027-10）的未來 12 月＝5／12 FY2027＋7／12 FY2028。每股數字為 2026-10-01 一股分三股後。
A16: 情境：A＝順利、B＝平平、C＝不如預期，讀 markets/nand 同字母（價格＝markets/memory NAND_S；顆數＝SCEN_UNITS；合資群份額年變動）；公司特有變數（每位元成本年降 14%／12%／10%，與 SanDisk 同值）A 最有利、C 最不利。FY2026 的 B、C 略高於 A：上游 B、C 價格路徑 2027Q1 漲幅較大。FY2030 起為收斂法，非驅動因子推導。
A17: 十年歷史不足：2024-12 上市，只有兩個年底；十年 P/B、P/E 與十年平均淨利率以美光為 Analogy，tp_roe 只用 FY2024–FY2025。本版未做先驗，無 Andy 合理 P/E 對照。
A19: 2026-10-29：加權目標價中的 Comparable 改用相對倍數調整後的值（Val 第 0.5 節：同業前瞻倍數中位數 × 本公司 10 年相對同業的倍數比，Bloomberg 前瞻倍數；Andy 2026-10-27「照建議做」、10-29 資料取回）。「Comparable 目標價（市場主流同業法）」維持不調整。重點觀察 1 的第一句已改為公式；重點觀察 2、3 與其他說明中的目標價與上檔空間數字為調整前撰寫，以 Val 頁為準。
A21: v0.2.1（2026-10-30）：依個股模型原則第 8 節調整 In 頁呈現（數值不變）。In 頁 D／F 欄名改「敏感度低」「敏感度高」（只用於 Sens 頁、不進目標價）；In 頁最後新增「情境驅動對照」一節，把上方各情境專屬輸入三情境並排（只引用上方各列，純展示）；HTML 驅動因子一節分「情境驅動」與「單一參數」兩張表。

Sheet In
A1: In — 輸入（藍字；基準欄 E，低 D、高 F）。金額：十億日圓（¥B）；每股：日圓（2026-10-01 一股分三股後）；股數：百萬股。每個輸入附標記與來源；找不到者寫「未找到」。【v0.2.1】基準欄 E 進主模型；D／F＝敏感度低／高，只用於 Sens 頁（一次動一個參數）、不進目標價；情境 A／B／C 的驅動見本頁最後一節「情境驅動對照」。
A2: 標記：Verified（公司文件、交易所資料）／Interested-party（寫明是誰、立場）／Analogy（寫明對照與差異）／Assumed（給低／高區間）／Derived（寫明換算）。SemiAnalysis 未使用
A3: 鍵 | B3: 項目 | C3: 單位 | D3: 敏感度低 | E3: 基準 | F3: 敏感度高 | G3: 標記 | H3: 來源1 | I3: 來源2／說明
A4: A. 季度實績與公司指引（¥B；EPS 日圓，分割後）
A5: p1_rev | B5: FY2025 第1季營收 | C5: ¥B | E5: 342.8 | G5: Verified | H5: Kioxia FY2026 第一季財報（2026-07-31；SGX 轉載 Earnings Release FY2026 1Q）https://links.sgx.com/1.0.0/corporate-announcements/DOATO9EIE4EEQ2Y8/898078_Earnings-Release-FY2026-1Q-EN.pdf（前期欄：營收 342.8、營業利益 44.9、淨利 18.3） | I5: 四季合計 2,337.6＝公司 FY2025 營收（storagenewsletter 轉載決算；MarketScreener 2,337.6）
A6: p1_gp | B6: FY2025 第1季毛利 | C6: ¥B | E6: 71.2 | G6: Interested-party | H6: stockanalysis 季度損益（TYO:285A；2026-10-25 讀取）
A7: p1_op | B7: FY2025 第1季營業利益 | C7: ¥B | E7: 44.9 | G7: Verified | H7: Kioxia FY2026 第一季財報（2026-07-31；SGX 轉載 Earnings Release FY2026 1Q）https://links.sgx.com/1.0.0/corporate-announcements/DOATO9EIE4EEQ2Y8/898078_Earnings-Release-FY2026-1Q-EN.pdf（前期欄：營收 342.8、營業利益 44.9、淨利 18.3） | I7: 四季合計 869.0（公司 870.4，取整差）
A8: p1_ni | B8: FY2025 第1季淨利 | C8: ¥B | E8: 18.3 | G8: Verified | H8: Kioxia FY2026 第一季財報（2026-07-31；SGX 轉載 Earnings Release FY2026 1Q）https://links.sgx.com/1.0.0/corporate-announcements/DOATO9EIE4EEQ2Y8/898078_Earnings-Release-FY2026-1Q-EN.pdf（前期欄：營收 342.8、營業利益 44.9、淨利 18.3） | I8: 四季合計 554.5（公司 554.5）
A9: p2_rev | B9: FY2025 第2季營收 | C9: ¥B | E9: 448.3 | G9: Interested-party | H9: stockanalysis 季度損益（TYO:285A；2026-10-25 讀取） | I9: 四季合計 2,337.6＝公司 FY2025 營收（storagenewsletter 轉載決算；MarketScreener 2,337.6）
A10: p2_gp | B10: FY2025 第2季毛利 | C10: ¥B | E10: 122.1 | G10: Interested-party | H10: stockanalysis 季度損益（TYO:285A；2026-10-25 讀取）
A11: p2_op | B11: FY2025 第2季營業利益 | C11: ¥B | E11: 85.9 | G11: Interested-party | H11: stockanalysis 季度損益（TYO:285A；2026-10-25 讀取） | I11: 四季合計 869.0（公司 870.4，取整差）
A12: p2_ni | B12: FY2025 第2季淨利 | C12: ¥B | E12: 40.7 | G12: Interested-party | H12: stockanalysis 季度損益（TYO:285A；2026-10-25 讀取） | I12: 四季合計 554.5（公司 554.5）
A13: p3_rev | B13: FY2025 第3季營收 | C13: ¥B | E13: 543.6 | G13: Interested-party | H13: stockanalysis 季度損益（TYO:285A；2026-10-25 讀取） | I13: 四季合計 2,337.6＝公司 FY2025 營收（storagenewsletter 轉載決算；MarketScreener 2,337.6）
A14: p3_gp | B14: FY2025 第3季毛利 | C14: ¥B | E14: 176.6 | G14: Interested-party | H14: stockanalysis 季度損益（TYO:285A；2026-10-25 讀取）
A15: p3_op | B15: FY2025 第3季營業利益 | C15: ¥B | E15: 142.8 | G15: Interested-party | H15: stockanalysis 季度損益（TYO:285A；2026-10-25 讀取） | I15: 四季合計 869.0（公司 870.4，取整差）
A16: p3_ni | B16: FY2025 第3季淨利 | C16: ¥B | E16: 87.8 | G16: Interested-party | H16: stockanalysis 季度損益（TYO:285A；2026-10-25 讀取） | I16: 四季合計 554.5（公司 554.5）
A17: p4_rev | B17: FY2025 第4季營收 | C17: ¥B | E17: 1002.9 | G17: Interested-party | H17: stockanalysis 季度損益（TYO:285A；2026-10-25 讀取） | I17: 四季合計 2,337.6＝公司 FY2025 營收（storagenewsletter 轉載決算；MarketScreener 2,337.6）
A18: p4_gp | B18: FY2025 第4季毛利 | C18: ¥B | E18: 642.9 | G18: Interested-party | H18: stockanalysis 季度損益（TYO:285A；2026-10-25 讀取）
A19: p4_op | B19: FY2025 第4季營業利益 | C19: ¥B | E19: 595.4 | G19: Interested-party | H19: stockanalysis 季度損益（TYO:285A；2026-10-25 讀取） | I19: 四季合計 869.0（公司 870.4，取整差）
A20: p4_ni | B20: FY2025 第4季淨利 | C20: ¥B | E20: 407.7 | G20: Interested-party | H20: stockanalysis 季度損益（TYO:285A；2026-10-25 讀取） | I20: 四季合計 554.5（公司 554.5）
A21: p1_ss | B21: FY2025 第1季營收：SSD 與儲存 | C21: ¥B | E21: 217.4 | G21: Interested-party | H21: blocksandfiles 2025-08-11（轉載 FY2025 第一季決算；分部 46.3 為其他） | I21: 官方分部：SSD & Storage（企業級、資料中心、PC 用 SSD）
A22: p1_sd | B22: FY2025 第1季營收：智慧裝置 | C22: ¥B | E22: 79 | G22: Interested-party | H22: blocksandfiles 2025-08-11（轉載 FY2025 第一季決算；分部 46.3 為其他） | I22: 官方分部：Smart Devices（手機、車用等嵌入式）
A23: p2_ss | B23: FY2025 第2季營收：SSD 與儲存 | C23: ¥B | E23: 246.6 | G23: Derived | H23: longportapp（轉載 FY2025 第二季決算）：SSD 與儲存占 55%、智慧裝置占 35% × 營收 448.3（Derived） | I23: 官方分部：SSD & Storage（企業級、資料中心、PC 用 SSD）
A24: p2_sd | B24: FY2025 第2季營收：智慧裝置 | C24: ¥B | E24: 156.9 | G24: Derived | H24: longportapp（轉載 FY2025 第二季決算）：SSD 與儲存占 55%、智慧裝置占 35% × 營收 448.3（Derived） | I24: 官方分部：Smart Devices（手機、車用等嵌入式）
A25: p3_ss | B25: FY2025 第3季營收：SSD 與儲存 | C25: ¥B | E25: 300.4 | G25: Interested-party | H25: blocksandfiles 2026-02-13（轉載 FY2025 第三季決算；其他 57.0） | I25: 官方分部：SSD & Storage（企業級、資料中心、PC 用 SSD）
A26: p3_sd | B26: FY2025 第3季營收：智慧裝置 | C26: ¥B | E26: 186.3 | G26: Interested-party | H26: blocksandfiles 2026-02-13（轉載 FY2025 第三季決算；其他 57.0） | I26: 官方分部：Smart Devices（手機、車用等嵌入式）
A27: p4_ss | B27: FY2025 第4季營收：SSD 與儲存 | C27: ¥B | E27: 600.3 | G27: Interested-party | H27: blocksandfiles 2026-05-21（轉載 FY2025 第四季決算；其他 65.2） | I27: 官方分部：SSD & Storage（企業級、資料中心、PC 用 SSD）
A28: p4_sd | B28: FY2025 第4季營收：智慧裝置 | C28: ¥B | E28: 337.3 | G28: Interested-party | H28: blocksandfiles 2026-05-21（轉載 FY2025 第四季決算；其他 65.2） | I28: 官方分部：Smart Devices（手機、車用等嵌入式）
A29: q1_ss | B29: FY2026 第一季營收：SSD 與儲存 | C29: ¥B | E29: 1174.7 | G29: Verified | H29: Kioxia FY2026 第一季財報（2026-07-31；SGX 轉載 Earnings Release FY2026 1Q）https://links.sgx.com/1.0.0/corporate-announcements/DOATO9EIE4EEQ2Y8/898078_Earnings-Release-FY2026-1Q-EN.pdf
A30: q1_sd | B30: FY2026 第一季營收：智慧裝置 | C30: ¥B | E30: 525.7 | G30: Verified | H30: Kioxia FY2026 第一季財報（2026-07-31；SGX 轉載 Earnings Release FY2026 1Q）https://links.sgx.com/1.0.0/corporate-announcements/DOATO9EIE4EEQ2Y8/898078_Earnings-Release-FY2026-1Q-EN.pdf | I30: 其他 66.7（零售、對 SanDisk 銷售）＝營收 − 兩主分部
A31: q1_rev | B31: FY2026 第一季營收（2026-04～06） | C31: ¥B | E31: 1767.1 | G31: Verified | H31: Kioxia FY2026 第一季財報（2026-07-31；SGX 轉載 Earnings Release FY2026 1Q）https://links.sgx.com/1.0.0/corporate-announcements/DOATO9EIE4EEQ2Y8/898078_Earnings-Release-FY2026-1Q-EN.pdf | I31: SSD 與儲存 1,174.7、智慧裝置 525.7、其他 66.7；平均匯率 160 日圓
A32: q1_gp | B32: FY2026 第一季毛利 | C32: ¥B | E32: 1380.1 | G32: Interested-party | H32: stockanalysis 季度損益（TYO:285A；2026-10-25 讀取）：1,380,066 百萬日圓 | I32: 財報摘要未列毛利
A33: q1_op | B33: FY2026 第一季營業利益 | C33: ¥B | E33: 1270 | G33: Verified | H33: Kioxia FY2026 第一季財報（2026-07-31；SGX 轉載 Earnings Release FY2026 1Q）https://links.sgx.com/1.0.0/corporate-announcements/DOATO9EIE4EEQ2Y8/898078_Earnings-Release-FY2026-1Q-EN.pdf | I33: 含訴訟損失準備 36.6、股份報酬 19.4（non-GAAP 加回）
A34: q1_ni | B34: FY2026 第一季淨利（歸屬母公司） | C34: ¥B | E34: 842.2 | G34: Verified | H34: Kioxia FY2026 第一季財報（2026-07-31；SGX 轉載 Earnings Release FY2026 1Q）https://links.sgx.com/1.0.0/corporate-announcements/DOATO9EIE4EEQ2Y8/898078_Earnings-Release-FY2026-1Q-EN.pdf
A35: q1_eps | B35: FY2026 第一季基本 EPS（分割後） | C35: JPY | E35: =1539.91/3 -> 513.30333 | G35: Derived | H35: Kioxia FY2026 第一季財報（2026-07-31；SGX 轉載 Earnings Release FY2026 1Q）https://links.sgx.com/1.0.0/corporate-announcements/DOATO9EIE4EEQ2Y8/898078_Earnings-Release-FY2026-1Q-EN.pdf：基本 EPS ¥1,539.91（分割前）÷ 3 | I35: 2026-10-01 一股分三股（2026-07-31 董事會）
A36: g2_rev | B36: FY2026 第二季（2026-07～09）營收實績 | C36: ¥B | E36: 2480 | G36: Verified | H36: Kioxia FY2026 第二季財報（2026-10-30；404K Research 法說整理、PANews／TechFlow 轉載）：¥2,480.0B（指引 2,390.0；平均匯率 161） | I36: v0.3 前為公司指引
A37: g2_op | B37: FY2026 第二季營業利益實績 | C37: ¥B | E37: 1994.7 | G37: Verified | H37: Kioxia FY2026 第二季財報（2026-10-30；404K Research 法說整理、PANews／TechFlow 轉載）：¥1,994.7B（non-GAAP 1,988.3；指引 1,890.0）
A38: g2_ni | B38: FY2026 第二季淨利實績 | C38: ¥B | E38: 1360 | G38: Verified | H38: Kioxia FY2026 第二季財報（2026-10-30；404K Research 法說整理、PANews／TechFlow 轉載）：約 ¥1.36T（non-GAAP 1,348.6；指引 1,270.0） | I38: 第二來源：TechFlow 2026-10-30（1.36 兆）
A39: g2_ox | B39: FY2026 第二季營業費用（推估；校準用） | C39: ¥B | D39: 50 | E39: 59 | F39: 70 | G39: Derived | H39: 毛利率約 82.8%（404K Research 依損益表推算）× 2,480.0 − 營業利益 1,994.7 ≈ 59 | I39: 第二季營業成本＝營收 − 營業利益 − 本值；公司損益表原文未取得
A40: a25_rev | B40: FY2025 營收（2025-04～2026-03） | C40: ¥B | E40: =p1_rev+p2_rev+p3_rev+p4_rev -> 2337.6 | G40: Derived | H40: 四季合計 | I40: 公司 2,337.6（storagenewsletter 轉載 FY25 決算，+37%）
A41: a25_ni | B41: FY2025 淨利 | C41: ¥B | E41: =p1_ni+p2_ni+p3_ni+p4_ni -> 554.5 | G41: Derived | H41: 四季合計 | I41: 公司 554.0（storagenewsletter）、MarketScreener 554.5
A42: a25_eps | B42: FY2025 EPS（分割後） | C42: JPY | E42: 341.4 | G42: Interested-party | H42: MarketScreener 預估頁（2026-10-25 擷取；頁面為 10-16 收盤；會計年度 3 月；每股數字已依分割調整，股數 1,644 百萬股）：341.4 | I42: ≈ 554.5 ÷ 平均約 1,624 百萬股（分割後，Derived）
A43: kx_k | B43: 公司營收 ÷ 市場層 Kioxia 營收（TrendForce 口徑 × 匯率） | C43: x | E43: =q1_rev/160/Units!H4 -> 1.0302589 | G43: Derived | H43: 第一季營收 ÷ 平均匯率 160 ÷ 市場層 2026Q2 Kioxia 營收（Units 頁） | I43: 公司營收含其他（¥66.7B）
A44: B. 成本、費用、稅、匯率（公司特有；隨情境者 A 最有利、C 最不利）
A45: cd_A | B45: 情境 A：每位元成本年降 | C45: % | D45: 0.1 | E45: 0.14 | F45: 0.18 | G45: Assumed | H45: A：BiCS10（332 層，北上 K2）FY2026 量產、密度約 +59% | I45: 與 sndk/ 同值（同一合資晶圓廠與 BiCS 世代）；以第二季指引校準的單位成本為起點
A46: cd_B | B46: 情境 B：每位元成本年降 | C46: % | D46: 0.08 | E46: 0.12 | F46: 0.16 | G46: Assumed | H46: B：轉換略延後 | I46: 同上
A47: cd_C | B47: 情境 C：每位元成本年降 | C47: % | D47: 0.06 | E47: 0.1 | F47: 0.14 | G47: Assumed | H47: C：需求轉弱、稼動率下降 | I47: 同上
A48: fx | B48: 匯率（FY2026 第三季起） | C48: ¥／$ | D48: 145 | E48: 160 | F48: 170 | G48: Assumed | H48: 第一季平均 160、第二季指引假設 162 | I48: 營收以美元計價（TrendForce 口徑 × 匯率）；成本以日圓計，不隨匯率
A49: ox_var | B49: 營業費用變動率（÷ 營收） | C49: % | D49: 0.005 | E49: 0.01 | F49: 0.02 | G49: Assumed | H49: FY2025 營業費用（毛利 − 營業利益）143.8 ÷ 營收 2,337.6 ≈ 6%，多為固定 | I49: 固定部分＝第二季營業費用 − 變動率 × 第二季營收（Derived）
A50: ox_g | B50: 營業費用固定部分年增 | C50: % | D50: 0.05 | E50: 0.1 | F50: 0.15 | G50: Assumed | H50: 研發（BiCS10、CBA）與人事
A51: nonop_q | B51: 每季業外淨額（利息、匯兌等；FY2026 第三季起） | C51: ¥B | D51: -40 | E51: -15 | F51: 0 | G51: Assumed | H51: Kioxia FY2026 第一季財報（2026-07-31；SGX 轉載 Earnings Release FY2026 1Q）https://links.sgx.com/1.0.0/corporate-announcements/DOATO9EIE4EEQ2Y8/898078_Earnings-Release-FY2026-1Q-EN.pdf：第一季稅前 − 營業利益＝−35.3；第二季指引 −20.0 | I51: 2026 年第一季已提前償還長期借款 ¥433.2B
A52: tax | B52: 有效稅率 | C52: % | D52: 0.28 | E52: 0.32 | F52: 0.35 | G52: Derived | H52: Kioxia FY2026 第一季財報（2026-07-31；SGX 轉載 Earnings Release FY2026 1Q）https://links.sgx.com/1.0.0/corporate-announcements/DOATO9EIE4EEQ2Y8/898078_Earnings-Release-FY2026-1Q-EN.pdf：第一季淨利 842.2 ÷ 稅前 1,234.7 → 稅率 31.8%；第二季指引 1,270 ÷ 1,870 → 32.1%
A53: sssh_26 | B53: FY2026 SSD 與儲存占營收（第二至四季） | C53: % | D53: 0.6 | E53: 0.66 | F53: 0.72 | G53: Assumed | H53: FY2025 第一至四季依序 63%、55%、55%、60%；FY2026 第一季 66.5%（Verified） | I53: 低＝回到 FY2025 水準；分部拆分不影響合併營收與 EPS
A54: otsh_26 | B54: FY2026 其他占營收 | C54: % | D54: 0.03 | E54: 0.04 | F54: 0.06 | G54: Assumed | H54: FY2026 第一季 3.8%；FY2025 第四季 6.5%（含對 SanDisk 銷售） | I54: 智慧裝置＝1 − SSD 與儲存 − 其他（Derived）
A55: sssh_27 | B55: FY2027 SSD 與儲存占營收 | C55: % | D55: 0.6 | E55: 0.68 | F55: 0.76 | G55: Assumed | H55: FY2025 第一至四季依序 63%、55%、55%、60%；FY2026 第一季 66.5%（Verified） | I55: 低＝回到 FY2025 水準；分部拆分不影響合併營收與 EPS
A56: otsh_27 | B56: FY2027 其他占營收 | C56: % | D56: 0.03 | E56: 0.04 | F56: 0.06 | G56: Assumed | H56: FY2026 第一季 3.8%；FY2025 第四季 6.5%（含對 SanDisk 銷售） | I56: 智慧裝置＝1 − SSD 與儲存 − 其他（Derived）
A57: sssh_28 | B57: FY2028 SSD 與儲存占營收 | C57: % | D57: 0.6 | E57: 0.7 | F57: 0.78 | G57: Assumed | H57: FY2025 第一至四季依序 63%、55%、55%、60%；FY2026 第一季 66.5%（Verified） | I57: 低＝回到 FY2025 水準；分部拆分不影響合併營收與 EPS
A58: otsh_28 | B58: FY2028 其他占營收 | C58: % | D58: 0.03 | E58: 0.04 | F58: 0.06 | G58: Assumed | H58: FY2026 第一季 3.8%；FY2025 第四季 6.5%（含對 SanDisk 銷售） | I58: 智慧裝置＝1 − SSD 與儲存 − 其他（Derived）
A59: sssh_29 | B59: FY2029 SSD 與儲存占營收 | C59: % | D59: 0.6 | E59: 0.7 | F59: 0.78 | G59: Assumed | H59: FY2025 第一至四季依序 63%、55%、55%、60%；FY2026 第一季 66.5%（Verified） | I59: 低＝回到 FY2025 水準；分部拆分不影響合併營收與 EPS
A60: otsh_29 | B60: FY2029 其他占營收 | C60: % | D60: 0.03 | E60: 0.04 | F60: 0.06 | G60: Assumed | H60: FY2026 第一季 3.8%；FY2025 第四季 6.5%（含對 SanDisk 銷售） | I60: 智慧裝置＝1 − SSD 與儲存 − 其他（Derived）
A61: rf | B61: 淨現金收益率 | C61: % | D61: 0 | E61: 0.01 | F61: 0.02 | G61: Assumed | H61: 日圓利率
A62: C. 資本、股東回饋（2026-06-30 資產負債表；股數為分割後）
A63: eq_j | B63: 2026-06-30 股東權益（歸屬母公司） | C63: ¥B | E63: 2404.3 | G63: Verified | H63: Kioxia FY2026 第一季財報（2026-07-31；SGX 轉載 Earnings Release FY2026 1Q）https://links.sgx.com/1.0.0/corporate-announcements/DOATO9EIE4EEQ2Y8/898078_Earnings-Release-FY2026-1Q-EN.pdf | I63: 2026-03-31 為 1,399.1
A64: nc_j | B64: 2026-06-30 淨現金（現金 − 公司債與借款；不含租賃負債） | C64: ¥B | E64: =791-634.6 -> 156.4 | G64: Derived | H64: Kioxia FY2026 第一季財報（2026-07-31；SGX 轉載 Earnings Release FY2026 1Q）https://links.sgx.com/1.0.0/corporate-announcements/DOATO9EIE4EEQ2Y8/898078_Earnings-Release-FY2026-1Q-EN.pdf：現金 791.0、公司債與借款 634.6（另有租賃負債 203.3）
A65: eq25 | B65: FY2025 年底（2026-03-31）股東權益 | C65: ¥B | E65: 1399.1 | G65: Verified | H65: Kioxia FY2026 第一季財報（2026-07-31；SGX 轉載 Earnings Release FY2026 1Q）https://links.sgx.com/1.0.0/corporate-announcements/DOATO9EIE4EEQ2Y8/898078_Earnings-Release-FY2026-1Q-EN.pdf
A66: sh0 | B66: 流通股數（分割後） | C66: 百萬股 | E66: =548.014638*3 -> 1644.0439 | G66: Derived | H66: Kioxia FY2026 第一季財報（2026-07-31；SGX 轉載 Earnings Release FY2026 1Q）https://links.sgx.com/1.0.0/corporate-announcements/DOATO9EIE4EEQ2Y8/898078_Earnings-Release-FY2026-1Q-EN.pdf：2026-06-30 發行 548,015,088 股、庫藏 450 股；× 3（2026-10-01 分割） | I66: MarketScreener 1,644.0 百萬股
A67: dil | B67: 稀釋股數 − 流通股數 | C67: 百萬股 | E67: =sh0*(1539.91/1525.09-1) -> 15.97593 | G67: Derived | H67: Kioxia FY2026 第一季財報（2026-07-31；SGX 轉載 Earnings Release FY2026 1Q）https://links.sgx.com/1.0.0/corporate-announcements/DOATO9EIE4EEQ2Y8/898078_Earnings-Release-FY2026-1Q-EN.pdf：基本 EPS 1,539.91 ÷ 稀釋 1,525.09 | I67: 各年固定
A68: da_y | B68: 折舊攤銷（年） | C68: ¥B | D68: 280 | E68: 320 | F68: 380 | G68: Assumed | H68: Kioxia FY2026 第一季財報（2026-07-31；SGX 轉載 Earnings Release FY2026 1Q）https://links.sgx.com/1.0.0/corporate-announcements/DOATO9EIE4EEQ2Y8/898078_Earnings-Release-FY2026-1Q-EN.pdf：第一季 76.1（× 4 ≈ 304） | I68: 新廠（北上 K2）投產後增加
A69: cap_2026 | B69: 資本支出 FY2026 | C69: ¥B | D69: 400 | E69: 450 | F69: 500 | G69: Interested-party | H69: TrendForce 2026-06-03：FY2026 ¥450B、FY2026–28 年均 ¥470B（較 FY2025 ¥283.7B +66%） | I69: 含合資廠 Kioxia 分攤；SanDisk 分攤另計於 sndk/
A70: cap_2027 | B70: 資本支出 FY2027 | C70: ¥B | D70: 400 | E70: 470 | F70: 550 | G70: Interested-party | H70: 同上 | I70: 含合資廠 Kioxia 分攤；SanDisk 分攤另計於 sndk/
A71: cap_2028 | B71: 資本支出 FY2028 | C71: ¥B | D71: 400 | E71: 470 | F71: 550 | G71: Interested-party | H71: 同上 | I71: 含合資廠 Kioxia 分攤；SanDisk 分攤另計於 sndk/
A72: cap_2029 | B72: 資本支出 FY2029 | C72: ¥B | D72: 350 | E72: 470 | F72: 550 | G72: Interested-party | H72: Assumed：延續 FY2026–28 年均 | I72: 含合資廠 Kioxia 分攤；SanDisk 分攤另計於 sndk/
A73: payout | B73: 股東回饋（股利＋買回）÷ 自由現金流 | C73: % | D73: 0 | E73: 0.2 | F73: 0.5 | G73: Assumed | H73: FY2025 無股利；MarketScreener 共識 FY2026 每股股利 ¥266（Interested-party） | I73: 以買回計（股數減少）
A74: px | B74: 股價（2026-10-23 收盤） | C74: JPY | E74: 12755 | G74: Verified | H74: stockanalysis 歷史股價（TYO:285A，2026-10-23 收盤 ¥12,755；分割後） | I74: MarketScreener 2026-10-16 收盤 ¥13,375（同一序列）；10-01 為 ¥19,100
A75: bb_px | B75: 未來買回均價 | C75: JPY | E75: =px -> 12755 | G75: Assumed | H75: ＝現價
A76: D. 共識與對帳參考（只放 Recon，不作校準）
A77: cons_rev26 | B77: 共識營收 FY2026（2027-03） | C77: ¥B | D77: 9100 | E77: 10071.4 | F77: 11400 | G77: Interested-party | H77: MarketScreener 預估頁（2026-10-25 擷取；頁面為 10-16 收盤；會計年度 3 月；每股數字已依分割調整，股數 1,644 百萬股）：10,071,396 百萬日圓 | I77: stockanalysis（15 位）平均 10.1 兆、區間 9.1–11.4 兆
A78: cons_rev27 | B78: 共識營收 FY2027（2028-03） | C78: ¥B | E78: 13477.2 | G78: Interested-party | H78: MarketScreener 預估頁（2026-10-25 擷取；頁面為 10-16 收盤；會計年度 3 月；每股數字已依分割調整，股數 1,644 百萬股）
A79: cons_ni26 | B79: 共識淨利 FY2026 | C79: ¥B | E79: 5573.9 | G79: Interested-party | H79: MarketScreener 預估頁（2026-10-25 擷取；頁面為 10-16 收盤；會計年度 3 月；每股數字已依分割調整，股數 1,644 百萬股）
A80: cons_ni27 | B80: 共識淨利 FY2027 | C80: ¥B | E80: 7730 | G80: Interested-party | H80: MarketScreener 預估頁（2026-10-25 擷取；頁面為 10-16 收盤；會計年度 3 月；每股數字已依分割調整，股數 1,644 百萬股）
A81: cons_eps26 | B81: 共識 EPS FY2026 | C81: JPY | E81: 3486 | G81: Interested-party | H81: MarketScreener 預估頁（2026-10-25 擷取；頁面為 10-16 收盤；會計年度 3 月；每股數字已依分割調整，股數 1,644 百萬股）
A82: cons_eps27 | B82: 共識 EPS FY2027 | C82: JPY | E82: 4871 | G82: Interested-party | H82: MarketScreener 預估頁（2026-10-25 擷取；頁面為 10-16 收盤；會計年度 3 月；每股數字已依分割調整，股數 1,644 百萬股）
A83: cons_eps28 | B83: 共識 EPS FY2028 | C83: JPY | E83: 5467 | G83: Interested-party | H83: MarketScreener 預估頁（2026-10-25 擷取；頁面為 10-16 收盤；會計年度 3 月；每股數字已依分割調整，股數 1,644 百萬股）
A84: cons_bv26 | B84: 共識每股淨值 FY2026 年底（2027-03） | C84: JPY | E84: 3830 | G84: Interested-party | H84: MarketScreener 預估頁（2026-10-25 擷取；頁面為 10-16 收盤；會計年度 3 月；每股數字已依分割調整，股數 1,644 百萬股）
A85: cons_bv27 | B85: 共識每股淨值 FY2027 年底（2028-03） | C85: JPY | E85: 7808 | G85: Interested-party | H85: MarketScreener 預估頁（2026-10-25 擷取；頁面為 10-16 收盤；會計年度 3 月；每股數字已依分割調整，股數 1,644 百萬股）
A86: cons_bv28 | B86: 共識每股淨值 FY2028 年底（2029-03） | C86: JPY | E86: 11928 | G86: Interested-party | H86: MarketScreener 預估頁（2026-10-25 擷取；頁面為 10-16 收盤；會計年度 3 月；每股數字已依分割調整，股數 1,644 百萬股）
A87: E. 目標價參數（黃底；Val 頁第 0 節 DCF＋Comparable 與收斂法用；Assumed 者 Andy 可改）
A88: tp_wA | B88: 目標價情境權重 A（A 順利／B 平平／C 不如預期） | C88: % | E88: 0.3 | G88: Assumed | H88: Andy 可改（工作單 2026-10-25 預設 A 0.3／B 0.5／C 0.2） | I88: 三者合計應為 100%
A89: tp_wB | B89: 目標價情境權重 B（A 順利／B 平平／C 不如預期） | C89: % | E89: 0.5 | G89: Assumed | H89: Andy 可改（工作單 2026-10-25 預設 A 0.3／B 0.5／C 0.2） | I89: 三者合計應為 100%
A90: tp_wC | B90: 目標價情境權重 C（A 順利／B 平平／C 不如預期） | C90: % | E90: 0.2 | G90: Assumed | H90: Andy 可改（工作單 2026-10-25 預設 A 0.3／B 0.5／C 0.2） | I90: 三者合計應為 100%
A91: tp_r | B91: 折現率（股東權益要求報酬；美、台、日、韓同一值） | C91: % | E91: 0.1 | G91: Assumed | H91: Andy 可改（工作單預設 10%） | I91: 日本利率較低，但依工作單不改值
A92: tp_g | B92: 長期成長率（永續；收斂法 B 的 FY2032 營收年增） | C92: % | E92: 0.04 | G92: Assumed | H92: Andy 可改（工作單預設 4%）
A93: tp_roe | B93: ROE（近年平均；FY2024–FY2025，上市不足三年） | C93: % | E93: =AVERAGE(272.3/737.1,554.5/1399.1) -> 0.38287346 | G93: Derived | H93: FY2024（2025-03）淨利 272.3 ÷ 權益 737.1（MarketScreener 每股淨值 455.8 × 1,617.2 百萬股，Derived）；FY2025 554.5 ÷ 1,399.1（公司） | I93: 2024-12 上市；FY2023 權益未找到，只用兩年
A94: tp_w_dcf | B94: 目標價中 DCF 的權重；其餘為 Comparable | C94: % | E94: 0.5 | G94: Assumed | H94: Andy 可改（2026-10-25 11:53：DCF／Comparable 各半）
A95: nim10 | B95: 十年平均淨利率（Analogy：美光 FY2016–FY2025） | C95: % | E95: 0.14662864 | G95: Analogy | H95: micron/dist/20261030_美光個股模型_v0.4.3.xlsx｜In!E244 | I95: Kioxia 2024-12 上市，2018 年以前為東芝記憶體事業，十年連續的獨立財報未找到；以同為記憶體循環股的美光十年平均代替（與 sndk/ 同值）
A96: cyc_mA | B96: 循環中段係數：情境 A 淨利率收斂目標 ÷ 十年平均 | C96: x | E96: 1.2 | G96: Assumed | H96: 記憶體樣板預設 1.2 | I96: Andy 可改
A97: cyc_mC | B97: 循環中段係數：情境 C 淨利率收斂目標 ÷ 十年平均 | C97: x | E97: 0.8 | G97: Assumed | H97: 記憶體樣板預設 0.8 | I97: Andy 可改
A98: fade_mA | B98: 情境 A：FY2032 淨利率收斂目標（循環中段：十年平均 × cyc_mA） | C98: % | E98: =nim10*cyc_mA -> 0.17595436 | G98: Derived | H98: 主串指示：循環產業 FY2030 後收斂用十年平均（記憶體樣板的循環中段） | I98: FY2030 起由 FY2029 淨利率線性收斂，FY2032 達到
A99: fade_mB | B99: 情境 B：FY2032 淨利率收斂目標（循環中段：＝十年平均） | C99: % | E99: =nim10 -> 0.14662864 | G99: Derived | H99: 主串指示：循環產業 FY2030 後收斂用十年平均（記憶體樣板的循環中段） | I99: FY2030 起由 FY2029 淨利率線性收斂，FY2032 達到
A100: fade_mC | B100: 情境 C：FY2032 淨利率收斂目標（循環中段：十年平均 × cyc_mC） | C100: % | E100: =nim10*cyc_mC -> 0.11730291 | G100: Derived | H100: 主串指示：循環產業 FY2030 後收斂用十年平均（記憶體樣板的循環中段） | I100: FY2030 起由 FY2029 淨利率線性收斂，FY2032 達到
...

Sheet Q
A1: Q — 季度實績（¥B）與公司指引。會計年度 4–3 月；第一季＝4–6 月
A3: 項目 | B3: FY2025 第一季 | C3: FY2025 第二季 | D3: FY2025 第三季 | E3: FY2025 第四季 | F3: FY2025 | G3: FY2026 第一季 | H3: FY2026 第二季 | I3: 標記 | J3: 來源
A4: 營收 | B4: =p1_rev -> 342.8 | C4: =p2_rev -> 448.3 | D4: =p3_rev -> 543.6 | E4: =p4_rev -> 1002.9 | F4: =SUM(B4:E4) -> 2337.6 | G4: =q1_rev -> 1767.1 | H4: =g2_rev -> 2480 | I4: Verified／Interested-party | J4: 公司財報（第一季前期欄）；stockanalysis 季度表；第二季為公司指引
A5: 毛利 | B5: =p1_gp -> 71.2 | C5: =p2_gp -> 122.1 | D5: =p3_gp -> 176.6 | E5: =p4_gp -> 642.9 | F5: =SUM(B5:E5) -> 1012.8 | G5: =q1_gp -> 1380.1 | I5: Verified／Interested-party | J5: 公司財報（第一季前期欄）；stockanalysis 季度表；第二季為公司指引
A6: 營業利益 | B6: =p1_op -> 44.9 | C6: =p2_op -> 85.9 | D6: =p3_op -> 142.8 | E6: =p4_op -> 595.4 | F6: =SUM(B6:E6) -> 869 | G6: =q1_op -> 1270 | H6: =g2_op -> 1994.7 | I6: Verified／Interested-party | J6: 公司財報（第一季前期欄）；stockanalysis 季度表；第二季為公司指引
A7: 淨利 | B7: =p1_ni -> 18.3 | C7: =p2_ni -> 40.7 | D7: =p3_ni -> 87.8 | E7: =p4_ni -> 407.7 | F7: =SUM(B7:E7) -> 554.5 | G7: =q1_ni -> 842.2 | H7: =g2_ni -> 1360 | I7: Verified／Interested-party | J7: 公司財報（第一季前期欄）；stockanalysis 季度表；第二季為公司指引
A8: 毛利率 | B8: =B5/B4 -> 0.20770128 | C8: =C5/C4 -> 0.27236226 | D8: =D5/D4 -> 0.32487123 | E8: =E5/E4 -> 0.64104098 | F8: =F5/F4 -> 0.43326489 | G8: =G5/G4 -> 0.78099711
A9: 營業利益率 | B9: =B6/B4 -> 0.13098016 | C9: =C6/C4 -> 0.19161276 | D9: =D6/D4 -> 0.26269316 | E9: =E6/E4 -> 0.59367833 | F9: =F6/F4 -> 0.3717488 | G9: =G6/G4 -> 0.71869164 | H9: =H6/H4 -> 0.80431452
A10: 季增：營收 | C10: =C4/B4-1 -> 0.30775963 | D10: =D4/C4-1 -> 0.21258086 | E10: =E4/D4-1 -> 0.84492274 | G10: =G4/E4-1 -> 0.76199023 | H10: =H4/G4-1 -> 0.40342935
A12: v0.3（2026-10-31）：FY2026 第二季（2026-07～09）實績已滾入（2026-10-30：營收 2,480.0、營業利益 1,994.7、淨利 1,360；平均匯率 161）；第三季起＝市場層推導。第三季指引：營收 2,500.0、營業利益約 2,000（假設 157 日圓）

Sheet Units
A1: Units — 市場層 markets/nand 成品的 Kioxia 季度營收與位元（三情境；唯讀抄錄，藍字）。來源：markets/nand/dist/20261031_NAND市場模型_v0.3.xlsx
A2: C..Z＝CY2025Q1..CY2030Q4；營收為 TrendForce 口徑（$B，美元），位元為季度出貨 × 營收份額（EB）。合資群份額＝Kioxia＋SanDisk（與 sndk/ 模型讀同一列）
A3: 項目 | B3: 單位 | C3: 2025Q1 | D3: 2025Q2 | E3: 2025Q3 | F3: 2025Q4 | G3: 2026Q1 | H3: 2026Q2 | I3: 2026Q3 | J3: 2026Q4 | K3: 2027Q1 | L3: 2027Q2 | M3: 2027Q3 | N3: 2027Q4 | O3: 2028Q1 | P3: 2028Q2 | Q3: 2028Q3 | R3: 2028Q4 | S3: 2029Q1 | T3: 2029Q2 | U3: 2029Q3 | V3: 2029Q4 | W3: 2030Q1 | X3: 2030Q2 | Y3: 2030Q3 | Z3: 2030Q4 | AA3: 來源
A4: Kioxia 營收（情境 A） | B4: $B | C4: 1.92 | D4: 2.14 | E4: 2.84 | F4: 3.31 | G4: 5.96 | H4: 10.72 | I4: 14.951317 | J4: 16.203565 | K4: 17.854345 | L4: 18.878671 | M4: 18.963676 | N4: 18.648031 | O4: 18.731998 | P4: 18.816342 | Q4: 18.901067 | R4: 18.986172 | S4: 19.187419 | T4: 19.560424 | U4: 19.940679 | V4: 20.328327 | W4: 20.059327 | X4: 20.160861 | Y4: 20.262908 | Z4: 20.365471 | AA4: markets/nand/dist/20261031_NAND市場模型_v0.3.xlsx｜Mkt!C43:Z43
A5: Kioxia 營收（情境 B） | B5: $B | C5: 1.92 | D5: 2.14 | E5: 2.84 | F5: 3.31 | G5: 5.96 | H5: 10.72 | I5: 14.951317 | J5: 16.203565 | K5: 17.97424 | L5: 19.385554 | M5: 18.447955 | N5: 15.60507 | O5: 10.837585 | P5: 8.4170171 | Q5: 6.9728873 | R5: 6.4985969 | S5: 7.2624323 | T5: 8.0276379 | U5: 8.7044508 | V5: 9.4383261 | W5: 9.0583649 | X5: 9.0586145 | Y5: 9.0588641 | Z5: 9.0591137 | AA5: markets/nand/dist/20261031_NAND市場模型_v0.3.xlsx｜Mkt!C91:Z91
A6: Kioxia 營收（情境 C） | B6: $B | C6: 1.92 | D6: 2.14 | E6: 2.84 | F6: 3.31 | G6: 5.96 | H6: 10.72 | I6: 14.951317 | J6: 16.203565 | K6: 17.74745 | L6: 19.140956 | M6: 18.215187 | N6: 15.408172 | O6: 9.0479482 | P6: 5.8954184 | Q6: 4.4322787 | R6: 3.5544157 | S6: 3.8038503 | T6: 4.1553937 | U6: 4.6691238 | V6: 5.3435212 | W6: 5.1151445 | X6: 5.1042459 | Y6: 5.0933705 | Z6: 5.0825183 | AA6: markets/nand/dist/20261031_NAND市場模型_v0.3.xlsx｜Mkt!C139:Z139
A7: Kioxia 位元（情境 A） | B7: EB | C7: 35.545444 | D7: 33.356174 | E7: 38.303462 | F7: 36.611793 | G7: 38.133315 | H7: 40.175758 | I7: 44.826902 | J7: 44.941148 | K7: 48.077324 | L7: 50.835581 | M7: 53.752082 | N7: 56.835907 | O7: 60.096655 | P7: 63.544476 | Q7: 67.190103 | R7: 71.044884 | S7: 74.01849 | T7: 77.791148 | U7: 81.756094 | V7: 85.923131 | W7: 87.539517 | X7: 90.839802 | Y7: 94.26451 | Z7: 97.818331 | AA7: markets/nand/dist/20261031_NAND市場模型_v0.3.xlsx｜Mkt!C47:Z47
A8: Kioxia 位元（情境 B） | B8: EB | C8: 35.545444 | D8: 33.356174 | E8: 38.303462 | F8: 36.611793 | G8: 38.133315 | H8: 40.175758 | I8: 44.826902 | J8: 44.941148 | K8: 47.478265 | L8: 50.202153 | M8: 53.082313 | N8: 56.127713 | O8: 55.686007 | P8: 57.664765 | Q8: 59.713836 | R8: 61.83572 | S8: 65.813141 | T8: 69.283369 | U8: 72.936576 | V8: 76.782412 | W8: 76.084452 | X8: 78.557421 | Y8: 81.110768 | Z8: 83.747107 | AA8: markets/nand/dist/20261031_NAND市場模型_v0.3.xlsx｜Mkt!C95:Z95
A9: Kioxia 位元（情境 C） | B9: EB | C9: 35.545444 | D9: 33.356174 | E9: 38.303462 | F9: 36.611793 | G9: 38.133315 | H9: 40.175758 | I9: 44.826902 | J9: 44.941148 | K9: 46.879205 | L9: 49.568724 | M9: 52.412545 | N9: 55.419519 | O9: 50.066631 | P9: 50.187959 | Q9: 50.309582 | R9: 50.431499 | S9: 53.970578 | T9: 56.150876 | U9: 58.419252 | V9: 60.779266 | W9: 60.07104 | X9: 61.88967 | Y9: 63.763358 | Z9: 65.693772 | AA9: markets/nand/dist/20261031_NAND市場模型_v0.3.xlsx｜Mkt!C143:Z143
A10: Kioxia＋SanDisk 合資群份額（情境 A） | B10: % | C10: 0.27907731 | D10: 0.25560769 | E10: 0.27406433 | F10: 0.2689697 | G10: 0.27096015 | H10: 0.25018083 | I10: 0.25187361 | J10: 0.24502666 | K10: 0.24502666 | L10: 0.24502666 | M10: 0.24502666 | N10: 0.24502666 | O10: 0.24502666 | P10: 0.24502666 | Q10: 0.24502666 | R10: 0.24502666 | S10: 0.24502666 | T10: 0.24502666 | U10: 0.24502666 | V10: 0.24502666 | W10: 0.24502666 | X10: 0.24502666 | Y10: 0.24502666 | Z10: 0.24502666 | AA10: markets/nand/dist/20261031_NAND市場模型_v0.3.xlsx｜Mkt!C46:Z46
A11: Kioxia＋SanDisk 合資群份額（情境 B） | B11: % | C11: 0.27907731 | D11: 0.25560769 | E11: 0.27406433 | F11: 0.2689697 | G11: 0.27096015 | H11: 0.25018083 | I11: 0.25187361 | J11: 0.24502666 | K11: 0.24202666 | L11: 0.24202666 | M11: 0.24202666 | N11: 0.24202666 | O11: 0.23902666 | P11: 0.23902666 | Q11: 0.23902666 | R11: 0.23902666 | S11: 0.23602666 | T11: 0.23602666 | U11: 0.23602666 | V11: 0.23602666 | W11: 0.23302666 | X11: 0.23302666 | Y11: 0.23302666 | Z11: 0.23302666 | AA11: markets/nand/dist/20261031_NAND市場模型_v0.3.xlsx｜Mkt!C94:Z94
A12: Kioxia＋SanDisk 合資群份額（情境 C） | B12: % | C12: 0.27907731 | D12: 0.25560769 | E12: 0.27406433 | F12: 0.2689697 | G12: 0.27096015 | H12: 0.25018083 | I12: 0.25187361 | J12: 0.24502666 | K12: 0.23902666 | L12: 0.23902666 | M12: 0.23902666 | N12: 0.23902666 | O12: 0.23302666 | P12: 0.23302666 | Q12: 0.23302666 | R12: 0.23302666 | S12: 0.22702666 | T12: 0.22702666 | U12: 0.22702666 | V12: 0.22702666 | W12: 0.22102666 | X12: 0.22102666 | Y12: 0.22102666 | Z12: 0.22102666 | AA12: markets/nand/dist/20261031_NAND市場模型_v0.3.xlsx｜Mkt!C142:Z142
A14: AI 企業級 SSD 占（企業級＋PC）SSD 位元需求（日曆年；markets/nand Ann 頁）
A15: 項目 | B15: 單位 | C15: CY2025 | D15: CY2026 | E15: CY2027 | F15: CY2028 | G15: CY2029 | H15: CY2030 | I15: 來源
A16: AI ÷（企業級＋PC）SSD（情境 A） | B16: % | C16: 0.31132075 | D16: 0.55407047 | E16: 0.67848272 | F16: 0.72045375 | G16: 0.75784396 | H16: 0.77509863 | I16: markets/nand/dist/20261031_NAND市場模型_v0.3.xlsx｜Ann!D6:I6 ÷（同列＋下一列＋PC 列）
A17: AI ÷（企業級＋PC）SSD（情境 B） | B17: % | C17: 0.31132075 | D17: 0.55407047 | E17: 0.67848272 | F17: 0.67339265 | G17: 0.72678592 | H17: 0.74551045 | I17: markets/nand/dist/20261031_NAND市場模型_v0.3.xlsx｜Ann!D33:I33 ÷（同列＋下一列＋PC 列）
A18: AI ÷（企業級＋PC）SSD（情境 C） | B18: % | C18: 0.31132075 | D18: 0.55407047 | E18: 0.67848272 | F18: 0.60727875 | G18: 0.65250524 | H18: 0.67403734 | I18: markets/nand/dist/20261031_NAND市場模型_v0.3.xlsx｜Ann!D60:I60 ÷（同列＋下一列＋PC 列）

Sheet PL
A1: PL — Kioxia 損益（¥B；FY2025 實績；FY2026＝第一、二季實績＋第三、四季推導；FY2027–FY2029 由市場層 markets/nand 驅動；FY2030–FY2032 收斂法見底部）
A3: 情境／項目 | B3: 單位 | C3: FY2025A | D3: FY2026 | E3: FY2027 | F3: FY2028 | G3: FY2029 | H3: 說明
A4: 情境 A（順利）
A5: 營收 | B5: ¥B | C5: =C77 -> 2337.6 | D5: =D77 -> 9861.2541 | E5: =E77 -> 12399.763 | F5: =F77 -> 12509.98 | G5: =G77 -> 13168.976
A6: SSD 與儲存 | B6: ¥B | C6: =C78 -> 1364.7 | D6: =D78 -> 6516.8417 | E6: =E78 -> 8431.839 | F6: =F78 -> 8756.9861 | G6: =G78 -> 9218.2833
A7: SSD 與儲存：AI 相關 | B7: ¥B | C7: =C79 -> 507.67957 | D7: =D79 -> 3813.4833 | E7: =E79 -> 5809.3303 | F7: =F79 -> 6390.8599 | G7: =G79 -> 7025.7849
A8: 智慧裝置 | B8: ¥B | C8: =C80 -> 759.5 | D8: =D80 -> 2953.9462 | E8: =E80 -> 3471.9337 | F8: =F80 -> 3252.5948 | G8: =G80 -> 3423.9338
A9: 其他 | B9: ¥B | C9: =C81 -> 213.4 | D9: =D81 -> 390.46617 | E9: =E81 -> 495.99053 | F9: =F81 -> 500.3992 | G9: =G81 -> 526.75904
A10: 毛利率 | B10: % | C10: =C84 -> 0.43326489 | D10: =D84 -> 0.83279289 | E10: =E84 -> 0.85686965 | F10: =F84 -> 0.84806522 | G10: =G84 -> 0.8500484
A11: 營業利益 | B11: ¥B | C11: =C86 -> 869 | D11: =D86 -> 7916.2468 | E11: =E86 -> 10348.646 | F11: =F86 -> 10316.608 | G11: =G86 -> 10878.249
A12: 營業利益率 | B12: % | C12: =C87 -> 0.3717488 | D12: =D87 -> 0.80276268 | E12: =E87 -> 0.83458413 | F12: =F87 -> 0.82467021 | G12: =G87 -> 0.82605123
A13: 淨利 | B13: ¥B | C13: =C88 -> 554.5 | D13: =D88 -> 5345.3836 | E13: =E88 -> 7021.3094 | F13: =F88 -> 7036.9038 | G13: =G88 -> 7456.2844
A14: EPS | B14: JPY | C14: =C96 -> 341.4 | D14: =D96 -> 3359.894 | E14: =E96 -> 4733.9079 | F14: =F96 -> 5116.9754 | G14: =G96 -> 5914.662
A15: 每股淨值 | B15: JPY | D15: =D97 -> 3826.3437 | E15: =E97 -> 7956.135 | F15: =F97 -> 12751.996 | G15: =G97 -> 18742.299
A16: 自由現金流 | B16: ¥B | D16: =D91 -> 5215.3836 | E16: =E91 -> 6871.3094 | F16: =F91 -> 6886.9038 | G16: =G91 -> 7306.2844
A18: 情境 B（平平）
A19: 營收 | B19: ¥B | C19: =C124 -> 2337.6 | D19: =D124 -> 9881.0179 | E19: =E124 -> 10595.374 | F19: =F124 -> 4805.2812 | G19: =G124 -> 5807.162
A20: SSD 與儲存 | B20: ¥B | C20: =C125 -> 1364.7 | D20: =D125 -> 6529.8858 | E20: =E125 -> 7204.8543 | F20: =F125 -> 3363.6969 | G20: =G125 -> 4065.0134
A21: SSD 與儲存：AI 相關 | B21: ¥B | C21: =C126 -> 507.67957 | D21: =D126 -> 3821.1164 | E21: =E126 -> 4879.2009 | F21: =F126 -> 2309.9884 | G21: =G126 -> 2973.4234
A22: 智慧裝置 | B22: ¥B | C22: =C127 -> 759.5 | D22: =D127 -> 2959.8754 | E22: =E127 -> 2966.7047 | F22: =F127 -> 1249.3731 | G22: =G127 -> 1509.8621
A23: 其他 | B23: ¥B | C23: =C128 -> 213.4 | D23: =D128 -> 391.25672 | E23: =E128 -> 423.81496 | F23: =F128 -> 192.21125 | G23: =G128 -> 232.28648
A24: 毛利率 | B24: % | C24: =C131 -> 0.43326489 | D24: =D131 -> 0.83293202 | E24: =E131 -> 0.83293536 | F24: =F131 -> 0.63083179 | G24: =G131 -> 0.67612737
A25: 營業利益 | B25: ¥B | C25: =C133 -> 869 | D25: =D133 -> 7933.883 | E25: =E133 -> 8566.9704 | F25: =F133 -> 2815.7 | G25: =G133 -> 3683.9811
A26: 營業利益率 | B26: % | C26: =C134 -> 0.3717488 | D26: =D134 -> 0.80294187 | E26: =E134 -> 0.80855762 | F26: =F134 -> 0.58595947 | G26: =G134 -> 0.6343858
A27: 淨利 | B27: ¥B | C27: =C135 -> 554.5 | D27: =D135 -> 5357.3762 | E27: =E135 -> 5809.8356 | F27: =F135 -> 1929.7612 | G27: =G135 -> 2529.8742
A28: EPS | B28: JPY | C28: =C143 -> 341.4 | D28: =D143 -> 3367.8301 | E28: =E143 -> 3868.0581 | F28: =F143 -> 1309.1147 | G28: =G143 -> 1760.7949
A29: 每股淨值 | B29: JPY | D29: =D144 -> 3832.893 | E29: =E144 -> 7209.6991 | F29: =F144 -> 8427.026 | G29: =G144 -> 10093.948
A30: 自由現金流 | B30: ¥B | D30: =D138 -> 5227.3762 | E30: =E138 -> 5659.8356 | F30: =F138 -> 1779.7612 | G30: =G138 -> 2379.8742
A32: 情境 C（不如預期）
A33: 營收 | B33: ¥B | C33: =C171 -> 2337.6 | D33: =D171 -> 9843.6334 | E33: =E171 -> 10189.221 | F33: =F171 -> 2915.3792 | G33: =G171 -> 3178.6673
A34: SSD 與儲存 | B34: ¥B | C34: =C172 -> 1364.7 | D34: =D172 -> 6505.212 | E34: =E172 -> 6928.6704 | F34: =F172 -> 2040.7655 | G34: =G172 -> 2225.0671
A35: SSD 與儲存：AI 相關 | B35: ¥B | C35: =C173 -> 507.67957 | D35: =D173 -> 3806.6779 | E35: =E173 -> 4577.6459 | F35: =F173 -> 1262.3877 | G35: =G173 -> 1463.8455
A36: 智慧裝置 | B36: ¥B | C36: =C174 -> 759.5 | D36: =D174 -> 2948.66 | E36: =E174 -> 2852.9819 | F36: =F174 -> 757.9986 | G36: =G174 -> 826.45349
A37: 其他 | B37: ¥B | C37: =C175 -> 213.4 | D37: =D175 -> 389.76133 | E37: =E175 -> 407.56885 | F37: =F175 -> 116.61517 | G37: =G175 -> 127.14669
A38: 毛利率 | B38: % | C38: =C178 -> 0.43326489 | D38: =D178 -> 0.83212343 | E38: =E178 -> 0.82798488 | F38: =F178 -> 0.46585568 | G38: =G178 -> 0.49344477
A39: 營業利益 | B39: ¥B | C39: =C180 -> 869 | D39: =D180 -> 7895.1587 | E39: =E180 -> 8182.2913 | F39: =F180 -> 1161.4209 | G39: =G180 -> 1352.3816
A40: 營業利益率 | B40: % | C40: =C181 -> 0.3717488 | D40: =D181 -> 0.80205737 | E40: =E181 -> 0.80303402 | F40: =F181 -> 0.39837729 | G40: =G181 -> 0.42545555
A41: 淨利 | B41: ¥B | C41: =C182 -> 554.5 | D41: =D182 -> 5331.0437 | E41: =E182 -> 5548.1105 | F41: =F182 -> 803.28436 | G41: =G182 -> 936.69152
A42: EPS | B42: JPY | C42: =C190 -> 341.4 | D42: =D190 -> 3350.407 | E42: =E190 -> 3682.7328 | F42: =F190 -> 536.8556 | G42: =G190 -> 631.21886
A43: 每股淨值 | B43: JPY | D43: =D191 -> 3818.5146 | E43: =E191 -> 7033.2463 | F43: =F191 -> 7536.3017 | G43: =G191 -> 8130.537
A44: 自由現金流 | B44: ¥B | D44: =D185 -> 5201.0437 | E44: =E185 -> 5398.1105 | F44: =F185 -> 653.28436 | G44: =G185 -> 786.69152
A46: 核對：三情境 FY2025、第一季、第二季 − 實績與指引（應為 0） | D46: =D100+D147+D194 -> 0
A56: 情境 A（順利）：markets/nand 情境 A（價格路徑 A、2028–29 顆數係數 A、合資群份額 A）；每位元成本年降 cd_A
A57: A. 季度 | B57: 單位 | C57: FY26 第1季（2026Q2） | D57: FY26 第2季（2026Q3） | E57: FY26 第3季（2026Q4） | F57: FY26 第4季（2027Q1） | G57: FY27 第1季（2027Q2） | H57: FY27 第2季（2027Q3） | I57: FY27 第3季（2027Q4） | J57: FY27 第4季（2028Q1） | K57: FY28 第1季（2028Q2） | L57: FY28 第2季（2028Q3） | M57: FY28 第3季（2028Q4） | N57: FY28 第4季（2029Q1） | O57: FY29 第1季（2029Q2） | P57: FY29 第2季（2029Q3） | Q57: FY29 第3季（2029Q4） | R57: FY29 第4季（2030Q1） | T57: 說明
A58: 市場層營收（TrendForce 口徑，美元，同字母情境） | B58: $B | C58: =Units!H4*1 -> 10.72 | D58: =Units!I4*1 -> 14.951317 | E58: =Units!J4*1*1 -> 16.203565 | F58: =Units!K4*1*1 -> 17.854345 | G58: =Units!L4*1*1 -> 18.878671 | H58: =Units!M4*1*1 -> 18.963676 | I58: =Units!N4*1*1 -> 18.648031 | J58: =Units!O4*1*1 -> 18.731998 | K58: =Units!P4*1*1 -> 18.816342 | L58: =Units!Q4*1*1 -> 18.901067 | ... R58: =Units!W4*1*1 -> 20.059327 | T58: markets/nand；Sens 可乘份額係數、價格係數（第三季起）
A59: 位元（市場層；同字母） | B59: EB | C59: =Units!H7*1 -> 40.175758 | D59: =Units!I7*1 -> 44.826902 | E59: =Units!J7*1 -> 44.941148 | F59: =Units!K7*1 -> 48.077324 | G59: =Units!L7*1 -> 50.835581 | H59: =Units!M7*1 -> 53.752082 | I59: =Units!N7*1 -> 56.835907 | J59: =Units!O7*1 -> 60.096655 | ... R59: =Units!W7*1 -> 87.539517
A60: 營收 | B60: ¥B | C60: =q1_rev -> 1767.1 | D60: =g2_rev -> 2480 | E60: =E58*kx_k*fx -> 2671.0186 | F60: =F58*kx_k*fx -> 2943.1355 | G60: =G58*kx_k*fx -> 3111.9869 | H60: =H58*kx_k*fx -> 3125.9993 | I60: =I58*kx_k*fx -> 3073.9679 | J60: =J58*kx_k*fx -> 3087.809 | K60: =K58*kx_k*fx -> 3101.7125 | L60: =L58*kx_k*fx -> 3115.6786 | ... R60: =R58*kx_k*fx -> 3306.608 | T60: 第一、二季實績；之後＝市場層 × 公司口徑係數 × 匯率
A61: SSD 與儲存 | B61: ¥B | C61: =q1_ss -> 1174.7 | D61: =D60*sssh_26 -> 1636.8 | E61: =E60*sssh_26 -> 1762.8723 | F61: =F60*sssh_26 -> 1942.4695 | G61: =G60*sssh_27 -> 2116.1511 | H61: =H60*sssh_27 -> 2125.6795 | I61: =I60*sssh_27 -> 2090.2982 | J61: =J60*sssh_27 -> 2099.7102 | K61: =K60*sssh_28 -> 2171.1988 | L61: =L60*sssh_28 -> 2180.975 | M61: =M60*sssh_28 -> 2190.7953 | N61: =N60*sssh_28 -> 2214.017 | O61: =O60*sssh_29 -> 2257.0576 | P61: =P60*sssh_29 -> 2300.9349 | Q61: =Q60*sssh_29 -> 2345.6652 | R61: =R60*sssh_29 -> 2314.6256 | T61: 官方分部；第一季實績，之後＝營收 × 占比（In）
A62: SSD 與儲存：AI 相關（＝SSD 與儲存 × AI 企業級 SSD 占比） | B62: ¥B | C62: =C61*(0.75*Units!D16+0.25*Units!E16) -> 687.40335 | D62: =D61*(0.75*Units!D16+0.25*Units!E16) -> 957.81204 | E62: =E61*(0.75*Units!D16+0.25*Units!E16) -> 1031.5862 | F62: =F61*(0.75*Units!D16+0.25*Units!E16) -> 1136.6817 | G62: =G61*(0.75*Units!E16+0.25*Units!F16) -> 1457.9762 | H62: =H61*(0.75*Units!E16+0.25*Units!F16) -> 1464.5411 | I62: =I61*(0.75*Units!E16+0.25*Units!F16) -> 1440.1642 | J62: =J61*(0.75*Units!E16+0.25*Units!F16) -> 1446.6488 | K62: =K61*(0.75*Units!F16+0.25*Units!G16) -> 1584.5437 | L62: =L61*(0.75*Units!F16+0.25*Units!G16) -> 1591.6784 | M62: =M61*(0.75*Units!F16+0.25*Units!G16) -> 1598.8453 | N62: =N61*(0.75*Units!F16+0.25*Units!G16) -> 1615.7925 | O62: =O61*(0.75*Units!G16+0.25*Units!H16) -> 1720.2337 | P62: =P61*(0.75*Units!G16+0.25*Units!H16) -> 1753.6751 | Q62: =Q61*(0.75*Units!G16+0.25*Units!H16) -> 1787.7666 | R62: =R61*(0.75*Units!G16+0.25*Units!H16) -> 1764.1095 | T62: 命題子列（Derived）：會計年度（4 月起）≈ 0.75 × 當年＋0.25 × 次年；假設公司 SSD 組合與產業（企業級＋PC）相同
A63: SSD 與儲存：非 AI | B63: ¥B | C63: =C61-C62 -> 487.29665 | D63: =D61-D62 -> 678.98796 | E63: =E61-E62 -> 731.28607 | F63: =F61-F62 -> 805.78774 | G63: =G61-G62 -> 658.1749 | H63: =H61-H62 -> 661.13846 | I63: =I61-I62 -> 650.13399 | J63: =J61-J62 -> 653.06135 | ... R63: =R61-R62 -> 550.51603
A64: 其他 | B64: ¥B | C64: =q1_rev-q1_ss-q1_sd -> 66.7 | D64: =D60*otsh_26 -> 99.2 | E64: =E60*otsh_26 -> 106.84074 | F64: =F60*otsh_26 -> 117.72542 | G64: =G60*otsh_27 -> 124.47948 | H64: =H60*otsh_27 -> 125.03997 | I64: =I60*otsh_27 -> 122.95872 | J64: =J60*otsh_27 -> 123.51236 | K64: =K60*otsh_28 -> 124.0685 | L64: =L60*otsh_28 -> 124.62714 | M64: =M60*otsh_28 -> 125.1883 | N64: =N60*otsh_28 -> 126.51526 | O64: =O60*otsh_29 -> 128.97472 | P64: =P60*otsh_29 -> 131.48199 | Q64: =Q60*otsh_29 -> 134.03801 | R64: =R60*otsh_29 -> 132.26432 | T64: 官方分部（零售、對 SanDisk 銷售）；實績＝營收 − 兩主分部
A65: 智慧裝置 | B65: ¥B | C65: =q1_sd -> 525.7 | D65: =D60-D61-D64 -> 744 | E65: =E60-E61-E64 -> 801.30558 | F65: =F60-F61-F64 -> 882.94066 | G65: =G60-G61-G64 -> 871.35635 | H65: =H60-H61-H64 -> 875.2798 | I65: =I60-I61-I64 -> 860.71101 | J65: =J60-J61-J64 -> 864.58653 | K65: =K60-K61-K64 -> 806.44526 | ... R65: =R60-R61-R64 -> 859.71807 | T65: 官方分部；預測季＝營收 − SSD 與儲存 − 其他
A66: 檢查：分部合計 − 營收（季） | B66: ¥B | C66: =C61+C65+C64-C60 -> 0 | D66: =D61+D65+D64-D60 -> 0 | E66: =E61+E65+E64-E60 -> 0 | F66: =F61+F65+F64-F60 -> 0 | G66: =G61+G65+G64-G60 -> 0 | H66: =H61+H65+H64-H60 -> 0 | I66: =I61+I65+I64-I60 -> 0 | J66: =J61+J65+J64-J60 -> 0 | ... R66: =R61+R65+R64-R60 -> 0
A67: 每 EB 營業成本（第二季以實績校準，之後每年 × (1 − 成本年降)） | B67: ¥B/EB | C67: =C68/C59 -> 9.6326745 | D67: =D68/D59 -> 9.5099143 | E67: =$D67*(1-cd_A)^(1/4) -> 9.1580122 | F67: =$D67*(1-cd_A)^(2/4) -> 8.8191318 | G67: =$D67*(1-cd_A)^(3/4) -> 8.4927911 | H67: =$D67*(1-cd_A)^(4/4) -> 8.1785263 | I67: =$D67*(1-cd_A)^(5/4) -> 7.8758905 | J67: =$D67*(1-cd_A)^(6/4) -> 7.5844533 | K67: =$D67*(1-cd_A)^(7/4) -> 7.3038004 | L67: =$D67*(1-cd_A)^(8/4) -> 7.0335326 | M67: =$D67*(1-cd_A)^(9/4) -> 6.7732658 | N67: =$D67*(1-cd_A)^(10/4) -> 6.5226298 | O67: =$D67*(1-cd_A)^(11/4) -> 6.2812683 | P67: =$D67*(1-cd_A)^(12/4) -> 6.0488381 | Q67: =$D67*(1-cd_A)^(13/4) -> 5.8250086 | R67: =$D67*(1-cd_A)^(14/4) -> 5.6094617
A68: 營業成本 | B68: ¥B | C68: =q1_rev-q1_gp -> 387 | D68: =g2_rev-g2_op-g2_ox -> 426.3 | E68: =E59*E67 -> 411.57158 | F68: =F59*F67 -> 424.00025 | G68: =G59*G67 -> 431.73597 | H68: =H59*H67 -> 439.61282 | I68: =I59*I67 -> 447.63338 | J68: =J59*J67 -> 455.80027 | K68: =K59*K67 -> 464.11617 | L68: =L59*L67 -> 472.58378 | ... R68: =R59*R67 -> 491.04957 | T68: 第二季＝實績營收 − 實績營業利益 − 推估營業費用
A69: 毛利率 | B69: % | C69: =1-C68/C60 -> 0.78099711 | D69: =1-D68/D60 -> 0.82810484 | E69: =1-E68/E60 -> 0.84591213 | F69: =1-F68/F60 -> 0.85593587 | G69: =1-G68/G60 -> 0.86126678 | H69: =1-H68/H60 -> 0.85936887 | I69: =1-I68/I60 -> 0.85437929 | J69: =1-J68/J60 -> 0.85238716 | ... R69: =1-R68/R60 -> 0.85149447
A70: 營業費用 | B70: ¥B | C70: =q1_gp-q1_op -> 110.1 | D70: =g2_ox -> 59 | E70: =(g2_ox-ox_var*g2_rev)*(1+ox_g)^(1/4)+ox_var*E60 -> 61.734874 | F70: =(g2_ox-ox_var*g2_rev)*(1+ox_g)^(2/4)+ox_var*F60 -> 65.300618 | G70: =(g2_ox-ox_var*g2_rev)*(1+ox_g)^(3/4)+ox_var*G60 -> 67.854072 | H70: =(g2_ox-ox_var*g2_rev)*(1+ox_g)^(4/4)+ox_var*H60 -> 68.879993 | I70: =(g2_ox-ox_var*g2_rev)*(1+ox_g)^(5/4)+ox_var*I60 -> 69.266836 | J70: =(g2_ox-ox_var*g2_rev)*(1+ox_g)^(6/4)+ox_var*J60 -> 70.334279 | K70: =(g2_ox-ox_var*g2_rev)*(1+ox_g)^(7/4)+ox_var*K60 -> 71.424748 | L70: =(g2_ox-ox_var*g2_rev)*(1+ox_g)^(8/4)+ox_var*L60 -> 72.538786 | M70: =(g2_ox-ox_var*g2_rev)*(1+ox_g)^(9/4)+ox_var*M60 -> 73.676948 | N70: =(g2_ox-ox_var*g2_rev)*(1+ox_g)^(10/4)+ox_var*N60 -> 75.030622 | O70: =(g2_ox-ox_var*g2_rev)*(1+ox_g)^(11/4)+ox_var*O60 -> 76.692065 | P70: =(g2_ox-ox_var*g2_rev)*(1+ox_g)^(12/4)+ox_var*P60 -> 78.390699 | Q70: =(g2_ox-ox_var*g2_rev)*(1+ox_g)^(13/4)+ox_var*Q60 -> 80.127363 | R70: =(g2_ox-ox_var*g2_rev)*(1+ox_g)^(14/4)+ox_var*R60 -> 80.808068 | T70: 固定部分以第二季校準（Derived）
A71: 營業利益 | B71: ¥B | C71: =C60-C68-C70 -> 1270 | D71: =D60-D68-D70 -> 1994.7 | E71: =E60-E68-E70 -> 2197.7121 | F71: =F60-F68-F70 -> 2453.8347 | G71: =G60-G68-G70 -> 2612.3969 | H71: =H60-H68-H70 -> 2617.5065 | I71: =I60-I68-I70 -> 2557.0677 | J71: =J60-J68-J70 -> 2561.6745 | ... R71: =R60-R68-R70 -> 2734.7503
A73: 淨利 | B73: ¥B | C73: =q1_ni -> 842.2 | D73: =g2_ni -> 1360 | E73: =(E71+nonop_q+rf*nc_j/4)*(1-tax) -> 1484.5101 | F73: =(F71+nonop_q+rf*nc_j/4)*(1-tax) -> 1658.6735 | G73: =(G71+nonop_q+rf*$D94/4)*(1-tax) -> 1772.4875 | H73: =(H71+nonop_q+rf*$D94/4)*(1-tax) -> 1775.962 | I73: =(I71+nonop_q+rf*$D94/4)*(1-tax) -> 1734.8636 | J73: =(J71+nonop_q+rf*$D94/4)*(1-tax) -> 1737.9963 | K73: =(K71+nonop_q+rf*$E94/4)*(1-tax) -> 1750.3993 | L73: =(L71+nonop_q+rf*$E94/4)*(1-tax) -> 1753.3807 | M73: =(M71+nonop_q+rf*$E94/4)*(1-tax) -> 1756.2834 | N73: =(N71+nonop_q+rf*$E94/4)*(1-tax) -> 1776.8404 | O73: =(O71+nonop_q+rf*$F94/4)*(1-tax) -> 1822.922 | P73: =(P71+nonop_q+rf*$F94/4)*(1-tax) -> 1860.377 | Q73: =(Q71+nonop_q+rf*$F94/4)*(1-tax) -> 1898.5863 | R73: =(R71+nonop_q+rf*$F94/4)*(1-tax) -> 1874.399 | T73: （營業利益＋業外＋淨現金 × 收益率 ÷ 4）×（1 − 稅率）；FY2026 用 2026-06-30 淨現金
A74: 季 EPS（稀釋，分割後） | B74: JPY | C74: =C73/(sh0+dil)*1000 -> 507.34333 | D74: =D73/(sh0+dil)*1000 -> 819.26731 | E74: =E73/(sh0+dil)*1000 -> 894.27253 | F74: =F73/(sh0+dil)*1000 -> 999.18893 | G74: =G73/(sh0+dil)*1000 -> 1067.7508 | H74: =H73/(sh0+dil)*1000 -> 1069.8438 | I74: =I73/(sh0+dil)*1000 -> 1045.0861 | J74: =J73/(sh0+dil)*1000 -> 1046.9732 | ... R74: =R73/(sh0+dil)*1000 -> 1129.1425
A76: B. 年度（會計年度） | B76: 單位 | C76: FY2025A | D76: FY2026 | E76: FY2027 | F76: FY2028 | G76: FY2029 | T76: 說明
A77: 營收 | B77: ¥B | C77: =a25_rev -> 2337.6 | D77: =SUM(C60:F60) -> 9861.2541 | E77: =SUM(G60:J60) -> 12399.763 | F77: =SUM(K60:N60) -> 12509.98 | G77: =SUM(O60:R60) -> 13168.976 | T77: FY2026＝第一、二季實績＋第三、四季推導
A78: 營收：SSD 與儲存 | B78: ¥B | C78: =p1_ss+p2_ss+p3_ss+p4_ss -> 1364.7 | D78: =SUM(C61:F61) -> 6516.8417 | E78: =SUM(G61:J61) -> 8431.839 | F78: =SUM(K61:N61) -> 8756.9861 | G78: =SUM(O61:R61) -> 9218.2833
A79: SSD 與儲存：AI 相關 | B79: ¥B | C79: =C78*(0.75*Units!C16+0.25*Units!D16) -> 507.67957 | D79: =SUM(C62:F62) -> 3813.4833 | E79: =SUM(G62:J62) -> 5809.3303 | F79: =SUM(K62:N62) -> 6390.8599 | G79: =SUM(O62:R62) -> 7025.7849
A80: 營收：智慧裝置 | B80: ¥B | C80: =p1_sd+p2_sd+p3_sd+p4_sd -> 759.5 | D80: =SUM(C65:F65) -> 2953.9462 | E80: =SUM(G65:J65) -> 3471.9337 | F80: =SUM(K65:N65) -> 3252.5948 | G80: =SUM(O65:R65) -> 3423.9338
A81: 營收：其他 | B81: ¥B | C81: =a25_rev-C78-C80 -> 213.4 | D81: =SUM(C64:F64) -> 390.46617 | E81: =SUM(G64:J64) -> 495.99053 | F81: =SUM(K64:N64) -> 500.3992 | G81: =SUM(O64:R64) -> 526.75904 | T81: FY2025＝營收 − 兩主分部（含報導值進位差約 0.1）
A82: 檢查：分部合計 − 合併營收（年） | B82: ¥B | C82: =C78+C80+C81-C77 -> 0 | D82: =D78+D80+D81-D77 -> 0 | E82: =E78+E80+E81-E77 -> 0 | F82: =F78+F80+F81-F77 -> 0 | G82: =G78+G80+G81-G77 -> 0
A83: 營業成本 | B83: ¥B | C83: =a25_rev-(p1_gp+p2_gp+p3_gp+p4_gp) -> 1324.8 | D83: =SUM(C68:F68) -> 1648.8718 | E83: =SUM(G68:J68) -> 1774.7824 | F83: =SUM(K68:N68) -> 1900.701 | G83: =SUM(O68:R68) -> 1974.709
A84: 毛利率 | B84: % | C84: =1-C83/C77 -> 0.43326489 | D84: =1-D83/D77 -> 0.83279289 | E84: =1-E83/E77 -> 0.85686965 | F84: =1-F83/F77 -> 0.84806522 | G84: =1-G83/G77 -> 0.8500484
A85: 營業費用 | B85: ¥B | D85: =SUM(C70:F70) -> 296.13549 | E85: =SUM(G70:J70) -> 276.33518 | F85: =SUM(K70:N70) -> 292.6711 | G85: =SUM(O70:R70) -> 316.01819
A86: 營業利益 | B86: ¥B | C86: =p1_op+p2_op+p3_op+p4_op -> 869 | D86: =SUM(C71:F71) -> 7916.2468 | E86: =SUM(G71:J71) -> 10348.646 | F86: =SUM(K71:N71) -> 10316.608 | G86: =SUM(O71:R71) -> 10878.249
A87: 營業利益率 | B87: % | C87: =C86/C77 -> 0.3717488 | D87: =D86/D77 -> 0.80276268 | E87: =E86/E77 -> 0.83458413 | F87: =F86/F77 -> 0.82467021 | G87: =G86/G77 -> 0.82605123
A88: 淨利 | B88: ¥B | C88: =a25_ni -> 554.5 | D88: =SUM(C73:F73) -> 5345.3836 | E88: =SUM(G73:J73) -> 7021.3094 | F88: =SUM(K73:N73) -> 7036.9038 | G88: =SUM(O73:R73) -> 7456.2844
A89: 折舊攤銷 | B89: ¥B | D89: =da_y -> 320 | E89: =da_y -> 320 | F89: =da_y -> 320 | G89: =da_y -> 320
A90: 資本支出（含合資廠分攤） | B90: ¥B | D90: =cap_2026 -> 450 | E90: =cap_2027 -> 470 | F90: =cap_2028 -> 470 | G90: =cap_2029 -> 470
A91: 自由現金流（淨利＋折舊 − 資本支出） | B91: ¥B | D91: =D88+D89-D90 -> 5215.3836 | E91: =E88+E89-E90 -> 6871.3094 | F91: =F88+F89-F90 -> 6886.9038 | G91: =G88+G89-G90 -> 7306.2844
A92: 股東回饋（以買回計） | B92: ¥B | D92: =MAX(0,payout*(SUM(D73:F73)+0.75*(D89-D90))) -> 881.13672 | E92: =MAX(0,payout*E91) -> 1374.2619 | F92: =MAX(0,payout*F91) -> 1377.3808 | G92: =MAX(0,payout*G91) -> 1461.2569 | T92: FY2026 只計 2026-07 以後三季的自由現金流
A93: 期末權益 | B93: ¥B | C93: =eq25 -> 1399.1 | D93: =eq_j+SUM(D73:F73)-D92 -> 6026.3469 | E93: =D93+E88-E92 -> 11673.394 | F93: =E93+F88-F92 -> 17332.917 | G93: =F93+G88-G92 -> 23327.945 | T93: FY2026＝2026-06-30 權益＋第二至四季淨利 − 回饋（不含其他綜合損益）
A94: 期末淨現金 | B94: ¥B | D94: =nc_j+(SUM(D73:F73)+0.75*(D89-D90))-D92 -> 3680.9469 | E94: =D94+E91-E92 -> 9177.9944 | F94: =E94+F91-F92 -> 14687.517 | G94: =F94+G91-G92 -> 20532.545
A95: 期末流通股數（分割後） | B95: 百萬股 | D95: =sh0-D92/bb_px*1000 -> 1574.9622 | E95: =D95-E92/bb_px*1000 -> 1467.2192 | F95: =E95-F92/bb_px*1000 -> 1359.2317 | G95: =F95-G92/bb_px*1000 -> 1244.6683
A96: EPS（稀釋：期末流通股數＋dil；分割後） | B96: JPY | C96: =a25_eps -> 341.4 | D96: =D88/(D95+dil)*1000 -> 3359.894 | E96: =E88/(E95+dil)*1000 -> 4733.9079 | F96: =F88/(F95+dil)*1000 -> 5116.9754 | G96: =G88/(G95+dil)*1000 -> 5914.662
A97: 每股淨值 BVPS（期末流通股數） | B97: JPY | D97: =D93/D95*1000 -> 3826.3437 | E97: =E93/E95*1000 -> 7956.135 | F97: =F93/F95*1000 -> 12751.996 | G97: =G93/G95*1000 -> 18742.299
A98: ROE（期末權益） | B98: % | D98: =D88/D93 -> 0.88700231 | E98: =E88/E93 -> 0.60147967 | F98: =F88/F93 -> 0.40598496 | G98: =G88/G93 -> 0.31962886
A99: 每股自由現金流（稀釋） | B99: JPY | E99: =E91/(E95+dil)*1000 -> 4632.7749 | F99: =F91/(F95+dil)*1000 -> 5007.901 | G99: =G91/(G95+dil)*1000 -> 5795.6752
A100: 檢查：FY2025 營收、淨利 − 四季合計；第一季、第二季 − 實績與指引（應為 0） | B100: ¥B | D100: =ABS(C60-q1_rev)+ABS(D71-g2_op)+ABS(C77-2337.6) -> 0
A103: 情境 B（平平）：markets/nand 情境 B（價格路徑 B、2028–29 顆數係數 B、合資群份額 B）；每位元成本年降 cd_B
A104: A. 季度 | B104: 單位 | C104: FY26 第1季（2026Q2） | D104: FY26 第2季（2026Q3） | E104: FY26 第3季（2026Q4） | F104: FY26 第4季（2027Q1） | G104: FY27 第1季（2027Q2） | H104: FY27 第2季（2027Q3） | I104: FY27 第3季（2027Q4） | J104: FY27 第4季（2028Q1） | K104: FY28 第1季（2028Q2） | L104: FY28 第2季（2028Q3） | M104: FY28 第3季（2028Q4） | N104: FY28 第4季（2029Q1） | O104: FY29 第1季（2029Q2） | P104: FY29 第2季（2029Q3） | Q104: FY29 第3季（2029Q4） | R104: FY29 第4季（2030Q1） | T104: 說明
A105: 市場層營收（TrendForce 口徑，美元，同字母情境） | B105: $B | C105: =Units!H5*1 -> 10.72 | D105: =Units!I5*1 -> 14.951317 | E105: =Units!J5*1*1 -> 16.203565 | F105: =Units!K5*1*1 -> 17.97424 | G105: =Units!L5*1*1 -> 19.385554 | H105: =Units!M5*1*1 -> 18.447955 | I105: =Units!N5*1*1 -> 15.60507 | J105: =Units!O5*1*1 -> 10.837585 | K105: =Units!P5*1*1 -> 8.4170171 | L105: =Units!Q5*1*1 -> 6.9728873 | ... R105: =Units!W5*1*1 -> 9.0583649 | T105: markets/nand；Sens 可乘份額係數、價格係數（第三季起）
A106: 位元（市場層；同字母） | B106: EB | C106: =Units!H8*1 -> 40.175758 | D106: =Units!I8*1 -> 44.826902 | E106: =Units!J8*1 -> 44.941148 | F106: =Units!K8*1 -> 47.478265 | G106: =Units!L8*1 -> 50.202153 | H106: =Units!M8*1 -> 53.082313 | I106: =Units!N8*1 -> 56.127713 | J106: =Units!O8*1 -> 55.686007 | ... R106: =Units!W8*1 -> 76.084452
A107: 營收 | B107: ¥B | C107: =q1_rev -> 1767.1 | D107: =g2_rev -> 2480 | E107: =E105*kx_k*fx -> 2671.0186 | F107: =F105*kx_k*fx -> 2962.8993 | G107: =G105*kx_k*fx -> 3195.5422 | H107: =H105*kx_k*fx -> 3040.9871 | I107: =I105*kx_k*fx -> 2572.3619 | J107: =J105*kx_k*fx -> 1786.4828 | K107: =K105*kx_k*fx -> 1387.473 | L107: =L105*kx_k*fx -> 1149.4206 | ... R107: =R105*kx_k*fx -> 1493.1937 | T107: 第一、二季實績；之後＝市場層 × 公司口徑係數 × 匯率
A108: SSD 與儲存 | B108: ¥B | C108: =q1_ss -> 1174.7 | D108: =D107*sssh_26 -> 1636.8 | E108: =E107*sssh_26 -> 1762.8723 | F108: =F107*sssh_26 -> 1955.5135 | G108: =G107*sssh_27 -> 2172.9687 | H108: =H107*sssh_27 -> 2067.8712 | I108: =I107*sssh_27 -> 1749.2061 | J108: =J107*sssh_27 -> 1214.8083 | K108: =K107*sssh_28 -> 971.23112 | L108: =L107*sssh_28 -> 804.59444 | M108: =M107*sssh_28 -> 749.86655 | N108: =N107*sssh_28 -> 838.00474 | O108: =O107*sssh_29 -> 926.30105 | P108: =P107*sssh_29 -> 1004.3978 | Q108: =Q107*sssh_29 -> 1089.0789 | R108: =R107*sssh_29 -> 1045.2356 | T108: 官方分部；第一季實績，之後＝營收 × 占比（In）
A109: SSD 與儲存：AI 相關（＝SSD 與儲存 × AI 企業級 SSD 占比） | B109: ¥B | C109: =C108*(0.75*Units!D17+0.25*Units!E17) -> 687.40335 | D109: =D108*(0.75*Units!D17+0.25*Units!E17) -> 957.81204 | E109: =E108*(0.75*Units!D17+0.25*Units!E17) -> 1031.5862 | F109: =F108*(0.75*Units!D17+0.25*Units!E17) -> 1144.3148 | G109: =G108*(0.75*Units!E17+0.25*Units!F17) -> 1471.5566 | H109: =H108*(0.75*Units!E17+0.25*Units!F17) -> 1400.3835 | I109: =I108*(0.75*Units!E17+0.25*Units!F17) -> 1184.5802 | J109: =J108*(0.75*Units!E17+0.25*Units!F17) -> 822.68058 | K109: =K108*(0.75*Units!F17+0.25*Units!G17) -> 666.9842 | L109: =L108*(0.75*Units!F17+0.25*Units!G17) -> 552.54796 | M109: =M108*(0.75*Units!F17+0.25*Units!G17) -> 514.96408 | N109: =N108*(0.75*Units!F17+0.25*Units!G17) -> 575.49219 | O109: =O108*(0.75*Units!G17+0.25*Units!H17) -> 677.5587 | P109: =P108*(0.75*Units!G17+0.25*Units!H17) -> 734.68391 | Q109: =Q108*(0.75*Units!G17+0.25*Units!H17) -> 796.62536 | R109: =R108*(0.75*Units!G17+0.25*Units!H17) -> 764.5554 | T109: 命題子列（Derived）：會計年度（4 月起）≈ 0.75 × 當年＋0.25 × 次年；假設公司 SSD 組合與產業（企業級＋PC）相同
A110: SSD 與儲存：非 AI | B110: ¥B | C110: =C108-C109 -> 487.29665 | D110: =D108-D109 -> 678.98796 | E110: =E108-E109 -> 731.28607 | F110: =F108-F109 -> 811.19876 | G110: =G108-G109 -> 701.41214 | H110: =H108-H109 -> 667.48773 | I110: =I108-I109 -> 564.62588 | J110: =J108-J109 -> 392.12773 | ... R110: =R108-R109 -> 280.6802
A111: 其他 | B111: ¥B | C111: =q1_rev-q1_ss-q1_sd -> 66.7 | D111: =D107*otsh_26 -> 99.2 | E111: =E107*otsh_26 -> 106.84074 | F111: =F107*otsh_26 -> 118.51597 | G111: =G107*otsh_27 -> 127.82169 | H111: =H107*otsh_27 -> 121.63948 | I111: =I107*otsh_27 -> 102.89448 | J111: =J107*otsh_27 -> 71.459312 | K111: =K107*otsh_28 -> 55.498921 | L111: =L107*otsh_28 -> 45.976825 | M111: =M107*otsh_28 -> 42.849517 | N111: =N107*otsh_28 -> 47.885985 | O111: =O107*otsh_29 -> 52.931488 | P111: =P107*otsh_29 -> 57.394161 | Q111: =Q107*otsh_29 -> 62.233082 | R111: =R107*otsh_29 -> 59.727749 | T111: 官方分部（零售、對 SanDisk 銷售）；實績＝營收 − 兩主分部
A112: 智慧裝置 | B112: ¥B | C112: =q1_sd -> 525.7 | D112: =D107-D108-D111 -> 744 | E112: =E107-E108-E111 -> 801.30558 | F112: =F107-F108-F111 -> 888.86978 | G112: =G107-G108-G111 -> 894.75183 | H112: =H107-H108-H111 -> 851.47639 | I112: =I107-I108-I111 -> 720.26133 | J112: =J107-J108-J111 -> 500.21519 | K112: =K107-K108-K111 -> 360.74299 | ... R112: =R107-R108-R111 -> 388.23037 | T112: 官方分部；預測季＝營收 − SSD 與儲存 − 其他
A113: 檢查：分部合計 − 營收（季） | B113: ¥B | C113: =C108+C112+C111-C107 -> 0 | D113: =D108+D112+D111-D107 -> 0 | E113: =E108+E112+E111-E107 -> 0 | F113: =F108+F112+F111-F107 -> 0 | G113: =G108+G112+G111-G107 -> 0 | H113: =H108+H112+H111-H107 -> 0 | I113: =I108+I112+I111-I107 -> 0 | J113: =J108+J112+J111-J107 -> 0 | ... R113: =R108+R112+R111-R107 -> 0
A114: 每 EB 營業成本（第二季以實績校準，之後每年 × (1 − 成本年降)） | B114: ¥B/EB | C114: =C115/C106 -> 9.6326745 | D114: =D115/D106 -> 9.5099143 | E114: =$D114*(1-cd_B)^(1/4) -> 9.2107983 | F114: =$D114*(1-cd_B)^(2/4) -> 8.9210904 | G114: =$D114*(1-cd_B)^(3/4) -> 8.6404947 | H114: =$D114*(1-cd_B)^(4/4) -> 8.3687246 | I114: =$D114*(1-cd_B)^(5/4) -> 8.1055025 | J114: =$D114*(1-cd_B)^(6/4) -> 7.8505596 | K114: =$D114*(1-cd_B)^(7/4) -> 7.6036354 | L114: =$D114*(1-cd_B)^(8/4) -> 7.3644777 | M114: =$D114*(1-cd_B)^(9/4) -> 7.1328422 | N114: =$D114*(1-cd_B)^(10/4) -> 6.9084924 | O114: =$D114*(1-cd_B)^(11/4) -> 6.6911991 | P114: =$D114*(1-cd_B)^(12/4) -> 6.4807403 | Q114: =$D114*(1-cd_B)^(13/4) -> 6.2769012 | R114: =$D114*(1-cd_B)^(14/4) -> 6.0794733
A115: 營業成本 | B115: ¥B | C115: =q1_rev-q1_gp -> 387 | D115: =g2_rev-g2_op-g2_ox -> 426.3 | E115: =E106*E114 -> 413.94385 | F115: =F106*F114 -> 423.55789 | G115: =G106*G114 -> 433.77143 | H115: =H106*H114 -> 444.23126 | I115: =I106*I114 -> 454.94332 | J115: =J106*J114 -> 437.16632 | K115: =K106*K114 -> 438.46185 | L115: =L106*L114 -> 439.76121 | ... R115: =R106*R114 -> 462.5534 | T115: 第二季＝實績營收 − 實績營業利益 − 推估營業費用
A116: 毛利率 | B116: % | C116: =1-C115/C107 -> 0.78099711 | D116: =1-D115/D107 -> 0.82810484 | E116: =1-E115/E107 -> 0.84502397 | F116: =1-F115/F107 -> 0.85704614 | G116: =1-G115/G107 -> 0.86425733 | H116: =1-H115/H107 -> 0.85391873 | I116: =1-I115/I107 -> 0.82314179 | J116: =1-J115/J107 -> 0.75529218 | ... R116: =1-R115/R107 -> 0.69022546
A117: 營業費用 | B117: ¥B | C117: =q1_gp-q1_op -> 110.1 | D117: =g2_ox -> 59 | E117: =(g2_ox-ox_var*g2_rev)*(1+ox_g)^(1/4)+ox_var*E107 -> 61.734874 | F117: =(g2_ox-ox_var*g2_rev)*(1+ox_g)^(2/4)+ox_var*F107 -> 65.498255 | G117: =(g2_ox-ox_var*g2_rev)*(1+ox_g)^(3/4)+ox_var*G107 -> 68.689625 | H117: =(g2_ox-ox_var*g2_rev)*(1+ox_g)^(4/4)+ox_var*H107 -> 68.029871 | I117: =(g2_ox-ox_var*g2_rev)*(1+ox_g)^(5/4)+ox_var*I107 -> 64.250776 | J117: =(g2_ox-ox_var*g2_rev)*(1+ox_g)^(6/4)+ox_var*J107 -> 57.321017 | K117: =(g2_ox-ox_var*g2_rev)*(1+ox_g)^(7/4)+ox_var*K107 -> 54.282353 | L117: =(g2_ox-ox_var*g2_rev)*(1+ox_g)^(8/4)+ox_var*L107 -> 52.876206 | M117: =(g2_ox-ox_var*g2_rev)*(1+ox_g)^(9/4)+ox_var*M107 -> 53.092252 | N117: =(g2_ox-ox_var*g2_rev)*(1+ox_g)^(10/4)+ox_var*N107 -> 55.373304 | O117: =(g2_ox-ox_var*g2_rev)*(1+ox_g)^(11/4)+ox_var*O107 -> 57.681258 | P117: =(g2_ox-ox_var*g2_rev)*(1+ox_g)^(12/4)+ox_var*P107 -> 59.86874 | Q117: =(g2_ox-ox_var*g2_rev)*(1+ox_g)^(13/4)+ox_var*Q107 -> 62.176131 | R117: =(g2_ox-ox_var*g2_rev)*(1+ox_g)^(14/4)+ox_var*R107 -> 62.673926 | T117: 固定部分以第二季校準（Derived）
...

Sheet Val
A1: Val — 估值。第 0 節為目標價（DCF 與 Comparable 加權；Comparable 依記憶體慣例用前瞻 P/B）；第 5–6 節為目前倍數、十年倍數與規則值（舊法參考）
A2: Kioxia 2024-12 上市，只有兩個年底：十年 P/B、P/E 以美光（同為記憶體循環股）為 Analogy，見第 6 節。每股數字皆為 2026-10-01 一股分三股後
A4: 0. 目標價
A5: 0.1 DCF（股東權益現金流，FY2027–FY2032 明確期＋FY2032 後永續）
A6: 項目 | B6: A（順利） | C6: B（平平） | D6: C（不如預期） | E6: 說明
A7: 情境 EPS（FY2027–FY2032） | E7: PL 頁延伸區塊；FY2030 起為收斂法（灰底）
A8: FY2027 | B8: =PL!D205 -> 4733.9079 | C8: =PL!D212 -> 3868.0581 | D8: =PL!D219 -> 3682.7328
A9: FY2028 | B9: =PL!E205 -> 5116.9754 | C9: =PL!E212 -> 1309.1147 | D9: =PL!E219 -> 536.8556
A10: FY2029 | B10: =PL!F205 -> 5914.662 | C10: =PL!F212 -> 1760.7949 | D10: =PL!F219 -> 631.21886
A11: FY2030 | B11: =PL!G205 -> 4806.9026 | C11: =PL!G212 -> 1580.3184 | D11: =PL!G219 -> 538.31078
A12: FY2031 | B12: =PL!H205 -> 3567.2914 | C12: =PL!H212 -> 1240.4415 | D12: =PL!H219 -> 420.70425
A13: FY2032 | B13: =PL!I205 -> 2174.0587 | C13: =PL!I212 -> 778.53657 | D13: =PL!I219 -> 285.30959
A14: 股東現金流＝EPS ×（1 − tp_g ÷ tp_roe） | E14: 記憶體資本密集：FY2027–FY2029 改用每股（淨利＋折舊－資本支出）＝ PL 區塊每股自由現金流；收斂期（FY2030 起）用 EPS ×（1 − 再投資率）
A15: 再投資率（tp_g ÷ tp_roe，上限 0.8；FY2030 起用） | B15: =MIN(tp_g/tp_roe,0.8) -> 0.10447316 | E15: ROE 為 FY2024–FY2025 平均（In 頁 tp_roe）
A16: FY2027（淨利＋折舊－資本支出，每股） | B16: =PL!E99 -> 4632.7749 | C16: =PL!E146 -> 3768.1914 | D16: =PL!E193 -> 3583.1656
A17: FY2028（淨利＋折舊－資本支出，每股） | B17: =PL!F99 -> 5007.901 | C17: =PL!F146 -> 1207.3575 | D17: =PL!F193 -> 436.60674
A18: FY2029（淨利＋折舊－資本支出，每股） | B18: =PL!G99 -> 5795.6752 | C18: =PL!G146 -> 1656.3948 | D18: =PL!G193 -> 530.13667
A19: FY2030（EPS ×（1 − 再投資率）） | B19: =B11*(1-$B$15) -> 4304.7103 | C19: =C11*(1-$B$15) -> 1415.2175 | D19: =D11*(1-$B$15) -> 482.07175
A20: FY2031（EPS ×（1 − 再投資率）） | B20: =B12*(1-$B$15) -> 3194.6052 | C20: =C12*(1-$B$15) -> 1110.8486 | D20: =D12*(1-$B$15) -> 376.75194
A21: FY2032（EPS ×（1 − 再投資率）） | B21: =B13*(1-$B$15) -> 1946.928 | C21: =C13*(1-$B$15) -> 697.2004 | D21: =D13*(1-$B$15) -> 255.50239
A22: DCF 情境每股價值（折現率 tp_r） | B22: =MAX(0,SUMPRODUCT(B16:B21,1/(1+tp_r)^{1;2;3;4;5;6})+B21*(1+tp_g)/(tp_r-tp_g)/(1+tp_r)^6) -> 37776.676 | C22: =MAX(0,SUMPRODUCT(C16:C21,1/(1+tp_r)^{1;2;3;4;5;6})+C21*(1+tp_g)/(tp_r-tp_g)/(1+tp_r)^6) -> 14539.391 | D22: =MAX(0,SUMPRODUCT(D16:D21,1/(1+tp_r)^{1;2;3;4;5;6})+D21*(1+tp_g)/(tp_r-tp_g)/(1+tp_r)^6) -> 7223.8643 | E22: Σ 明確期現金流 ÷ (1＋r)^t ＋ 永續價值 ÷ (1＋r)^6；永續價值＝FY2032 現金流 ×(1＋g)÷(r−g)；基準日 2026 年底，t＝1 對 FY2027（2027-04～2028-03，t 以會計年度計，略低估）；FY2026 剩餘一季的現金流未計入；負值取 0
A23: DCF 情境價值推到 12 個月後（×(1＋tp_r)） | B23: =B22*(1+tp_r) -> 41554.344 | C23: =C22*(1+tp_r) -> 15993.33 | D23: =D22*(1+tp_r) -> 7946.2508
A24: DCF 目標價（情境加權） | B24: =tp_wA*B23+tp_wB*C23+tp_wC*D23 -> 22052.218 | E24: Σ 權重 × 情境價值 ×(1＋r)；權重見 In 頁 tp_wA／tp_wB／tp_wC
A26: 0.2 Comparable（市場主流同業前瞻 P/B；記憶體慣例）
A27: 同業與前瞻 P/B | B27: 代號 | C27: 前瞻 P/B | D27: 日期 | E27: 來源 | F27: 標記
A28: 美光 | B28: MU | C28: 3.35 | D28: 2026-10-23 | E28: MarketScreener：現價 ÷ FY2027E（2027-09）每股淨值（micron/ 模型同值） | F28: Interested-party
A29: SK 海力士 | B29: 000660.KS | C29: 1.35 | D29: 2026-10-23 | E29: MarketScreener：現價 ÷ 2027E 每股淨值（skhynix/ 模型同值） | F29: Interested-party
A30: 三星電子 | B30: 005930.KS | C30: 1.26 | D30: 2026-10-23 | E30: MarketScreener：現價 ÷ 2027E 每股淨值（samsung/ 模型同值） | F30: Interested-party
A31: SanDisk | B31: SNDK | C31: =1238.03/((313.8+553.1)/2) -> 2.8562233 | D31: 2026-10-23 | E31: 現價 1,238.03 ÷ MarketScreener 約 2027 年底每股淨值（FY2027、FY2028 年底平均；sndk/ 模型同口徑） | F31: Interested-party
A32: 同業前瞻 P/B 中位數 | B32: =MEDIAN(C28:C31) -> 2.1031117 | E32: 記憶體同業（美光、SK 海力士、三星、SanDisk；無 A 股）。WDC（硬碟）不列入 P/B（僅有落後 P/B），P/E 並列參考見下方。Kioxia 自身現價 ÷ FY2027 年底（2028-03）共識每股淨值 1.63x（sndk/ 同業表同值）
A33: 12 個月後的前瞻每股淨值（情境加權） | B33: =tp_wA*(0.25*PL!E97+0.75*PL!F97)+tp_wB*(0.25*PL!E144+0.75*PL!F144)+tp_wC*(0.25*PL!E191+0.75*PL!F191) -> 9009.3639 | E33: 同業倍數＝現價 ÷ 約 14 個月後（約 2027 年底）每股淨值；對應 12 個月後（約 2027-10）用約 2028 年底每股淨值＝¼ × FY2027 年底（2028-03）＋¾ × FY2028 年底（2029-03）（會計年度 3 月，依月份調整）
A34: Comparable 目標價 | B34: =B32*B33 -> 18947.698 | E34: 同業中位數 × 前瞻每股淨值
A35: 12 個月後的前瞻 EPS（情境加權） | B35: =tp_wA*(5/12*B8+7/12*B9)+tp_wB*(5/12*C8+7/12*C9)+tp_wC*(5/12*D8+7/12*D9) -> 3044.4073 | E35: 約 2027-10 時的未來 12 月（2027-11～2028-10）≈ 5／12 × FY2027（2027-04～2028-03）＋7／12 × FY2028（會計年度 3 月，依月份調整）
A37: 並列參考：同業前瞻 P/E（不進目標價）
A38: 同業與前瞻 P/E | B38: 代號 | C38: 前瞻 P/E | D38: 日期 | E38: 來源 | F38: 標記
A39: 美光 | B39: MU | C39: =877.55/173 -> 5.0725434 | D39: 2026-10-23 | E39: 現價 877.55 ÷ MarketScreener FY2027 共識 EPS 173（micron/ 模型 In 頁） | F39: Interested-party
A40: SK 海力士 | B40: 000660.KS | C40: =1277000/475721 -> 2.6843465 | D40: 2026-10-23 | E40: 現價 ÷ MarketScreener 2027 共識 EPS（skhynix/ 模型 In 頁） | F40: Interested-party
A41: 三星電子 | B41: 005930.KS | C41: =215500/72279 -> 2.9815022 | D41: 2026-10-23 | E41: 現價 ÷ MarketScreener 2027 共識 EPS（samsung/ 模型 In 頁） | F41: Interested-party
A42: SanDisk | B42: SNDK | C42: =1238.03/217.4 -> 5.6947102 | D42: 2026-10-23 | E42: 現價 1,238.03 ÷ MarketScreener FY2027（2027-06）共識 EPS 217.4 | F42: Interested-party
A43: Western Digital | B43: WDC | C43: 11.91 | D43: 2026-10-23 | E43: stockanalysis 統計頁 Forward P/E（硬碟為主，參考） | F43: Interested-party
A44: 同業前瞻 P/E 中位數（並列參考） | B44: =MEDIAN(C39:C43) -> 5.0725434
A45: Comparable（P/E 並列參考）＝中位數 × 12 個月後前瞻 EPS | B45: =B44*B35 -> 15442.888 | E45: 不進目標價：高峰期 EPS × 低倍數，與 P/B 法互相對照
A47: 0.3 結論
A48: 項目 | B48: 數值 | E48: 說明
A49: 目標價（DCF 與 Comparable 加權） | B49: =tp_w_dcf*B24+(1-tp_w_dcf)*tp_comp_adj -> 20499.958 | E49: tp_w_dcf × DCF 目標價＋（1 − tp_w_dcf）× Comparable 目標價；tp_w_dcf 見 In 頁
A50: Comparable 目標價（市場主流同業法） | B50: =B34 -> 18947.698 | E50: 引用 0.2（前瞻 P/B）
A51: 市場共識目標價 | B51: =cons_tp -> 36929.23 | E51: MarketScreener（16 位，2026-10-16 收盤時）：平均 ¥36,929（最低 16,333、最高 66,667；分割後）；stockanalysis（16 位，09-09）分割調整後 ¥37,085
A52: 上檔空間：加權目標價 | B52: =B49/px-1 -> 0.60720958 | E52: 現價＝In 頁 px（2026-10-23 收盤）
A53: 上檔空間：Comparable 目標價 | B53: =B50/px-1 -> 0.48551143
A54: 上檔空間級距 | B54: =IF(B52>0.5,"大於 50%",IF(B52>0.25,"25%–50%",IF(B52>=0,"0%–25%",IF(B52>=-0.25,"0%～−25%",IF(B52>=-0.5,"−25%～−50%","小於 −50%"))))) -> 大於 50% | E54: 以「上檔空間：加權目標價」分六級（Andy 2026-10-25 14:00）
A55: 投資建議 | B55: =IF(B52>0.5,"強力買進",IF(B52>0.25,"買進",IF(B52>=-0.25,"中立",IF(B52>=-0.5,"放空","強力放空")))) -> 強力買進 | E55: 依上檔空間固定規則（Andy 2026-10-25 14:17）：>+50% 強力買進、+25～+50% 買進、−25～+25% 中立、−50～−25% 放空、<−50% 強力放空
A56: DCF ÷ 現價 | B56: =B23/px -> 3.2578866 | C56: =C23/px -> 1.2538871 | D56: =D23/px -> 0.62299104 | E56: 各情境 DCF 價值（推到 12 個月後）÷ 現價（A／B／C）
A57: 與市場共識目標價的差距：EPS 因素（記憶體以每股淨值計） | B57: =B33/(0.25*cons_bv27+0.75*cons_bv28)-1 -> -0.17330117 | E57: 本模型約 2028 年底每股淨值（情境加權）÷ 共識（¼ FY2027＋¾ FY2028 年底）− 1（Comparable 用 P/B，故以每股淨值代 EPS）
A58: 對照：前瞻 EPS ÷ 共識前瞻 EPS − 1 | B58: =B35/(5/12*cons_eps27+7/12*cons_eps28)-1 -> -0.4166312 | E58: 共識前瞻 EPS＝5／12 × FY2027 4,871＋7／12 × FY2028 5,467（MarketScreener）
A59: 與市場共識目標價的差距：倍數因素 | B59: =(cons_tp/(0.25*cons_bv27+0.75*cons_bv28))/B32-1 -> 0.61124327 | E59: ="共識目標價隱含 P/B "&TEXT(cons_tp/(0.25*cons_bv27+0.75*cons_bv28),"0.00")&"x（÷ 共識約 2028 年底每股淨值），同業中位數 "&TEXT(B32,"0.00")&"x" -> 共識目標價隱含 P/B 3.39x（÷ 共識約 2028 年底每股淨值），同業中位數 2.10x
A60: 價格帶（DCF 不如預期～順利） | B60: =TEXT(D23,"#,##0")&"～"&TEXT(B23,"#,##0") -> 7,946～41,554 | E60: C 情境價值～A 情境價值（推到 12 個月後）
A61: 歷史倍數檢查：現價隱含 P/B 的十年分位（A／B／C） | B61: =IF(px/PL!F15>=MAX($B$95:$B$104),1,IF(px/PL!F15<=MIN($B$95:$B$104),0,PERCENTRANK($B$95:$B$104,px/PL!F15))) -> 0 | C61: =IF(px/PL!F29>=MAX($B$95:$B$104),1,IF(px/PL!F29<=MIN($B$95:$B$104),0,PERCENTRANK($B$95:$B$104,px/PL!F29))) -> 0.386 | D61: =IF(px/PL!F43>=MAX($B$95:$B$104),1,IF(px/PL!F43<=MIN($B$95:$B$104),0,PERCENTRANK($B$95:$B$104,px/PL!F43))) -> 0.437 | E61: 現價 ÷ 各情境 FY2028 年底每股淨值，在 2016–2025 年底 P/B（第 6 節，美光 Analogy）分布的分位（高於最大值記 100%、低於最小值記 0%）；只作檢查，不進目標價
A62: 目標價方法 | B62: DCF：股東現金流 FY2027–FY2029 用每股（淨利＋折舊－資本支出；資本支出 ¥470B／年，TrendForce），FY2030–FY2032 收斂期用 EPS ×（1 − g／ROE），r 10%、g 4%、ROE 為 FY2024–FY2025 平均；明確期＋永續，基準日 2026 年底。Comparable：美光、SK 海力士、三星、SanDisk 前瞻 P/B 中位數 × 約 2028 年底每股淨值（情境加權）；P/E 並列參考不進目標價。偏誤：FY2027–FY2029 為高峰期盈餘、收斂期淨利率以美光十年平均代替；營收以美元計、成本以日圓計，日圓貶值（匯率）使盈餘偏高。
A80: 5. 目前倍數（僅供參考）
A81: 項目 | B81: A／數值 | C81: B | D81: C | E81: 備註
A82: 現價（2026-10-23 收盤） | B82: =px -> 12755 | E82: stockanalysis（分割後）
A83: P/E：現價 ÷ FY2025 EPS 341.4 | B83: =px/a25_eps -> 37.360867 | E83: 落後（分割後）
A84: P/B：現價 ÷ 2026-06-30 每股淨值 | B84: =px/(eq_j/sh0*1000) -> 8.7217819 | E84: 權益 2,404.3 ÷ 1,644.0 百萬股
A85: 現價 ÷ FY2027 EPS（模型） | B85: =px/PL!E14 -> 2.6943912 | C85: =px/PL!E28 -> 3.2975203 | D85: =px/PL!E42 -> 3.4634606 | E85: A／B／C
A86: 現價 ÷ FY2028 EPS（模型） | B86: =px/PL!F14 -> 2.4926835 | C86: =px/PL!F28 -> 9.7432255 | D86: =px/PL!F42 -> 23.758717 | E86: A／B／C
A87: 現價 ÷ FY2028 年底每股淨值（模型） | B87: =px/PL!F15 -> 1.0002356 | C87: =px/PL!F29 -> 1.5135826 | D87: =px/PL!F43 -> 1.6924747 | E87: A／B／C；第 0 節歷史分位檢查用
A90: 6. 十年倍數與規則值（2016–2025 年底；見頂年 25 分位、中段中位數、谷底 75 分位）
A91: 規則（Andy 2026-10-13）：合理倍數＝2016–2025 年底倍數依循環位置取分位。Kioxia 無十年自身歷史，以美光為 Analogy（同為記憶體循環股；差異：美光 DRAM 為主）。見頂與中段用 FY2027 A、谷底用 FY2028 C。
A93: P/B（主）：十年歷史倍數
A94: 年底 | B94: 美光（Analogy；會計年度 8 月底） | C94: 標記／說明
A95: 2016 | B95: 1.29 | C95: 美光（Analogy；會計年度 8 月底）：Analogy
A96: 2017 | B96: 1.78 | C96: 來源：micron/dist/20261030_美光個股模型_v0.4.3.xlsx｜Val!B82:B91（macrotrends）；Kioxia 自身 2024-12 上市，2024、2025 年底倍數未找到
A97: 2018 | B97: 1.79
A98: 2019 | B98: 1.33
A99: 2020 | B99: 1.27
A100: 2021 | B100: 1.83
A101: 2022 | B101: 1.22
A102: 2023 | B102: 1.72
A103: 2024 | B103: 2.35
A104: 2025 | B104: 2.46
A105: 25 分位（各來源） | B105: =PERCENTILE(B95:B104,0.25) -> 1.3
A106: 中位數（各來源） | B106: =MEDIAN(B95:B104) -> 1.75
A107: 75 分位（各來源） | B107: =PERCENTILE(B95:B104,0.75) -> 1.82
A108: 最小（各來源） | B108: =MIN(B95:B104) -> 1.22
A109: 最大（各來源） | B109: =MAX(B95:B104) -> 2.46
A110: 採用 25 分位（P/B） | B110: =ROUND(AVERAGE(B105),2) -> 1.3
A111: 採用 中位數（P/B） | B111: =ROUND(AVERAGE(B106),2) -> 1.75
A112: 採用 75 分位（P/B） | B112: =ROUND(AVERAGE(B107),2) -> 1.82
A113: 採用 最小（P/B） | B113: =ROUND(MIN(B108),2) -> 1.22
A114: 採用 最大（P/B） | B114: =ROUND(MAX(B109),2) -> 2.46
A116: P/B（主）：規則值
A117: 情形 | B117: 循環位置 | C117: 倍數 | D117: 基準 | E117: 每股基準 | F117: 隱含股價 | G117: 相對目前 | H117: 現價 ÷ 基準
A118: 規則值：見頂（P/B） | B118: 見頂年 → 25 分位 | C118: =B110 -> 1.3 | D118: FY2027 年底每股淨值（A） | E118: =PL!E97 -> 7956.135 | F118: =C118*E118 -> 10342.975 | G118: =F118/px-1 -> -0.18910423 | H118: =px/E118 -> 1.6031654
A119: 規則值：中段（P/B） | B119: 中段 → 中位數 | C119: =B111 -> 1.75 | D119: FY2027 年底每股淨值（A） | E119: =PL!E97 -> 7956.135 | F119: =C119*E119 -> 13923.236 | G119: =F119/px-1 -> 0.091590454 | H119: =px/E119 -> 1.6031654
A120: 規則值：谷底（P/B） | B120: 谷底 → 75 分位 | C120: =B112 -> 1.82 | D120: FY2028 年底每股淨值（C） | E120: =PL!F191 -> 7536.3017 | F120: =C120*E120 -> 13716.069 | G120: =F120/px-1 -> 0.075348414 | H120: =px/E120 -> 1.6924747
A123: P/E（對照）：十年歷史倍數
A124: 年底 | B124: 美光（Analogy；SEC 10-K 換算） | C124: 標記／說明
A125: 2016 | C125: 美光（Analogy；SEC 10-K 換算）：Analogy
A126: 2017 | B126: 6.5131421 | C126: 來源：micron/dist/20261030_美光個股模型_v0.4.3.xlsx｜Val!B115:B124；虧損年不計
A127: 2018 | B127: 4.0895833
...

Sheet Recon
A1: Recon — 本模型 vs 公司實績、指引與共識（共識只作對照，未用於校準）。差距＝模型 ÷ 對照 − 1（百分點列為相減）
A3: 項目 | B3: 對照值 | C3: 模型 A | D3: 差距 A | E3: 模型 B | F3: 差距 B | G3: 模型 C | H3: 差距 C | I3: 對照來源 | J3: 說明
A4: A. 實績與公司指引
A5: FY2025 營收（四季合計）vs 公司 2,337.6 | B5: 2337.6 | C5: =PL!C5 -> 2337.6 | D5: =C5/B5-1 -> 0 | E5: =PL!C19 -> 2337.6 | F5: =E5/B5-1 -> 0 | G5: =PL!C33 -> 2337.6 | H5: =G5/B5-1 -> 0 | I5: storagenewsletter 轉載 FY25 決算；MarketScreener
A6: FY2026 上半營收 vs 公司指引 4,157.1 | B6: 4157.1 | C6: =PL!C60+PL!D60 -> 4247.1 | D6: =C6/B6-1 -> 0.021649708 | E6: =PL!C107+PL!D107 -> 4247.1 | F6: =E6/B6-1 -> 0.021649708 | G6: =PL!C154+PL!D154 -> 4247.1 | H6: =G6/B6-1 -> 0.021649708 | I6: Kioxia FY2026 第一季財報（2026-07-31） | J6: 恆等式
A7: FY2026 第三季營收（推導）vs 第三季指引 2,500（假設 157 日圓） | B7: =g3_rev -> 2500 | C7: =PL!E60 -> 2671.0186 | D7: =C7/B7-1 -> 0.06840744 | E7: =PL!E107 -> 2671.0186 | F7: =E7/B7-1 -> 0.06840744 | G7: =PL!E154 -> 2671.0186 | H7: =G7/B7-1 -> 0.06840744 | I7: Kioxia 第二季財報（2026-10-30）第三季指引 | J7: v0.4：市場層 2026Q4 季價 +8.1%（實現價口徑；v0.3 為合約價 +17.5%、差距 +21.5%），份額取 2026Q3 實績與第三季指引的平均。餘差：匯率假設 160 對 157 約 +1.9%；其餘為公司稱 7–9 月提前出貨、部分遞延到 1–3 月（同一會計年度內）與產品組合
A8: FY2026 第二季毛利率（校準值）vs 第一季（百分點） | B8: =q1_gp/q1_rev -> 0.78099711 | C8: =PL!D69 -> 0.82810484 | D8: =C8-B8 -> 0.047107725 | E8: =PL!D116 -> 0.82810484 | F8: =E8-B8 -> 0.047107725 | G8: =PL!D163 -> 0.82810484 | H8: =G8-B8 -> 0.047107725 | I8: Kioxia FY2026 第一季財報（2026-07-31） | J8: 第二季營業費用為 Assumed（g2_ox）
A9: B. 共識（MarketScreener 2026-10-25 擷取；只作參考）
A10: FY2026 營收 vs 共識 | B10: =cons_rev26 -> 10071.4 | C10: =PL!D5 -> 9861.2541 | D10: =C10/B10-1 -> -0.020865605 | E10: =PL!D19 -> 9881.0179 | F10: =E10/B10-1 -> -0.018903243 | G10: =PL!D33 -> 9843.6334 | H10: =G10/B10-1 -> -0.022615192 | I10: MarketScreener 預估頁（2026-10-25 擷取；頁面為 10-16 收盤；會計年度 3 月；每股數字已依分割調整，股數 1,644 百萬股）
A11: FY2026 淨利 vs 共識 | B11: =cons_ni26 -> 5573.9 | C11: =PL!D13 -> 5345.3836 | D11: =C11/B11-1 -> -0.040997579 | E11: =PL!D27 -> 5357.3762 | F11: =E11/B11-1 -> -0.038846013 | G11: =PL!D41 -> 5331.0437 | H11: =G11/B11-1 -> -0.043570269 | I11: MarketScreener 預估頁（2026-10-25 擷取；頁面為 10-16 收盤；會計年度 3 月；每股數字已依分割調整，股數 1,644 百萬股）
A12: FY2026 EPS vs 共識 | B12: =cons_eps26 -> 3486 | C12: =PL!D14 -> 3359.894 | D12: =C12/B12-1 -> -0.03617499 | E12: =PL!D28 -> 3367.8301 | F12: =E12/B12-1 -> -0.033898413 | G12: =PL!D42 -> 3350.407 | H12: =G12/B12-1 -> -0.038896453 | I12: MarketScreener 預估頁（2026-10-25 擷取；頁面為 10-16 收盤；會計年度 3 月；每股數字已依分割調整，股數 1,644 百萬股） | J12: 差距超過 30% 見 README
A13: FY2027 營收 vs 共識 | B13: =cons_rev27 -> 13477.2 | C13: =PL!E5 -> 12399.763 | D13: =C13/B13-1 -> -0.079945153 | E13: =PL!E19 -> 10595.374 | F13: =E13/B13-1 -> -0.21382972 | G13: =PL!E33 -> 10189.221 | H13: =G13/B13-1 -> -0.24396601 | I13: MarketScreener 預估頁（2026-10-25 擷取；頁面為 10-16 收盤；會計年度 3 月；每股數字已依分割調整，股數 1,644 百萬股）
A14: FY2027 EPS vs 共識 | B14: =cons_eps27 -> 4871 | C14: =PL!E14 -> 4733.9079 | D14: =C14/B14-1 -> -0.028144543 | E14: =PL!E28 -> 3868.0581 | F14: =E14/B14-1 -> -0.20590062 | G14: =PL!E42 -> 3682.7328 | H14: =G14/B14-1 -> -0.24394728 | I14: MarketScreener 預估頁（2026-10-25 擷取；頁面為 10-16 收盤；會計年度 3 月；每股數字已依分割調整，股數 1,644 百萬股）
A15: FY2028 EPS vs 共識 | B15: =cons_eps28 -> 5467 | C15: =PL!F14 -> 5116.9754 | D15: =C15/B15-1 -> -0.064024986 | E15: =PL!F28 -> 1309.1147 | F15: =E15/B15-1 -> -0.76054239 | G15: =PL!F42 -> 536.8556 | H15: =G15/B15-1 -> -0.9018007 | I15: MarketScreener 預估頁（2026-10-25 擷取；頁面為 10-16 收盤；會計年度 3 月；每股數字已依分割調整，股數 1,644 百萬股）
A16: FY2027 年底每股淨值 vs 共識 | B16: =cons_bv27 -> 7808 | C16: =PL!E15 -> 7956.135 | D16: =C16/B16-1 -> 0.018972208 | E16: =PL!E29 -> 7209.6991 | F16: =E16/B16-1 -> -0.076626654 | G16: =PL!E43 -> 7033.2463 | H16: =G16/B16-1 -> -0.09922563 | I16: MarketScreener 預估頁（2026-10-25 擷取；頁面為 10-16 收盤；會計年度 3 月；每股數字已依分割調整，股數 1,644 百萬股）
A17: C. 市場層一致性
A18: Kioxia 營收 ÷ 市場層（公司口徑係數 kx_k） | C18: =kx_k -> 1.0302589 | I18: In 頁
A19: Kioxia＋SanDisk 合資群份額 CY2027（市場層 Ann 頁，A／B／C） | C19: 0.24502666 | E19: 0.24202666 | G19: 0.23902666 | I19: markets/nand/dist/20261031_NAND市場模型_v0.3.xlsx｜Ann!F27（sndk/ 模型讀同一組列）

Sheet Sens
A1: Sens — 一次動一個輸入（情境 A）：對 FY2027、FY2028 營收與 EPS 的影響。每個案例為一個完整推導區塊（本頁下方，與 PL 同一引擎）
A3: 案例 | B3: 設定 | C3: FY2027 營收 ¥B | D3: FY2027 EPS | E3: 相對基準 | F3: FY2028 營收 ¥B | G3: FY2028 EPS | H3: 相對基準 | I3: FY2027 毛利率
A4: 基準（情境 A） | B4: PL 區塊 A | C4: =PL!E77 -> 12399.763 | D4: =PL!E96 -> 4733.9079 | E4: =D4/D$4-1 -> 0 | F4: =PL!F77 -> 12509.98 | G4: =PL!F96 -> 5116.9754 | H4: =G4/G$4-1 -> 0 | I4: =PL!E84 -> 0.85686965
A5: 市場層營收 −20%（價格；第三季起） | B5: 價格係數 0.8 | C5: =E81 -> 9919.8105 | D5: =E100 -> 3515.2356 | E5: =D5/D$4-1 -> -0.25743473 | F5: =F81 -> 10007.984 | G5: =F100 -> 3708.082 | H5: =G5/G$4-1 -> -0.27533715 | I5: =E88 -> 0.82108706
A6: 市場層營收 +20%（價格） | B6: 價格係數 1.2 | C6: =E131 -> 14879.716 | D6: =E150 -> 6016.8322 | E6: =D6/D$4-1 -> 0.27100744 | F6: =F131 -> 15011.976 | G6: =F150 -> 6665.0126 | H6: =G6/G$4-1 -> 0.30252973 | I6: =E138 -> 0.88072471
A7: 份額 ×0.9（營收與位元） | B7: 份額係數 0.9 | C7: =E181 -> 11159.787 | D7: =E200 -> 4116.8458 | E7: =D7/D$4-1 -> -0.13034942 | F7: =F181 -> 11258.982 | G7: =F200 -> 4396.3352 | H7: =G7/G$4-1 -> -0.14083324 | I7: =E188 -> 0.84096628
A8: 份額 ×1.1 | B8: 份額係數 1.1 | C8: =E231 -> 13639.739 | D8: =E250 -> 5367.0251 | E8: =D8/D$4-1 -> 0.13374092 | F8: =F231 -> 13760.978 | G8: =F250 -> 5872.3438 | H8: =G8/G$4-1 -> 0.14762009 | I8: =E238 -> 0.8698815
A9: 匯率 145 日圓 | B9: fx 低 | C9: =E281 -> 11237.285 | D9: =E300 -> 4154.9534 | E9: =D9/D$4-1 -> -0.1222995 | F9: =F281 -> 11337.169 | G9: =F300 -> 4440.4032 | H9: =G9/G$4-1 -> -0.13222113 | I9: =E288 -> 0.84206306
A10: 匯率 170 日圓 | B10: fx 高 | C10: =E331 -> 13174.748 | D10: =E350 -> 5127.6851 | E10: =D10/D$4-1 -> 0.083182272 | F10: =F331 -> 13291.854 | G10: =F350 -> 5584.853 | H10: =G10/G$4-1 -> 0.091436359 | I10: =E338 -> 0.86528908
A11: 每位元成本年降 10%（C 的值） | B11: cd_C | C11: =E381 -> 12399.763 | D11: =E400 -> 4687.2351 | E11: =D11/D$4-1 -> -0.0098592677 | F11: =F381 -> 12509.98 | G11: =F400 -> 5009.3356 | H11: =G11/G$4-1 -> -0.02103583 | I11: =E388 -> 0.84930793
A12: 每位元成本年降 18% | B12: cd_A 高 | C12: =E431 -> 12399.763 | D12: =E450 -> 4780.2406 | E12: =D12/D$4-1 -> 0.0097873934 | F12: =F431 -> 12509.98 | G12: =F450 -> 5219.6277 | H12: =G12/G$4-1 -> 0.020061121 | I12: =E438 -> 0.86436144
A13: 第二季營業費用 50（校準） | B13: g2_ox 低 | C13: =E481 -> 12399.763 | D13: =E500 -> 4735.2355 | E13: =D13/D$4-1 -> 0.00028044175 | F13: =F481 -> 12509.98 | G13: =F500 -> 5119.2513 | H13: =G13/G$4-1 -> 0.00044477336 | I13: =E488 -> 0.8538479
A14: 第二季營業費用 70 | B14: g2_ox 高 | C14: =E531 -> 12399.763 | D14: =E550 -> 4732.2854 | E14: =D14/D$4-1 -> -0.0003427422 | F14: =F531 -> 12509.98 | G14: =F550 -> 5114.1941 | H14: =G14/G$4-1 -> -0.00054354041 | I14: =E538 -> 0.8605629
A15: 營業費用變動率 2% | B15: ox_var 高 | C15: =E581 -> 12399.763 | D15: =E600 -> 4727.0712 | E15: =D15/D$4-1 -> -0.0014441997 | F15: =F581 -> 12509.98 | G15: =F600 -> 5114.2816 | H15: =G15/G$4-1 -> -0.00052644314 | I15: =E588 -> 0.85686965
A16: 稅率 35% | B16: tax 高 | C16: =E631 -> 12399.763 | D16: =E650 -> 4503.1899 | E16: =D16/D$4-1 -> -0.04873732 | F16: =F631 -> 12509.98 | G16: =F650 -> 4847.4154 | H16: =G16/G$4-1 -> -0.052679558 | I16: =E638 -> 0.85686965
A17: 稅率 28% | B17: tax 低 | C17: =E681 -> 12399.763 | D17: =E700 -> 5045.0378 | E17: =D17/D$4-1 -> 0.065723681 | F17: =F681 -> 12509.98 | G17: =F700 -> 5484.0348 | H17: =G17/G$4-1 -> 0.071733672 | I17: =E688 -> 0.85686965
A18: 股東回饋 ÷ FCF 50% | B18: payout 高 | C18: =E731 -> 12399.763 | D18: =E750 -> 5755.7756 | E18: =D18/D$4-1 -> 0.21586133 | F18: =F731 -> 12509.98 | G18: =F750 -> 7388.8936 | H18: =G18/G$4-1 -> 0.44399631 | I18: =E738 -> 0.85686965
A19: 股東回饋 0 | B19: payout 低 | C19: =E781 -> 12399.763 | D19: =E800 -> 4233.2633 | E19: =D19/D$4-1 -> -0.10575715 | F19: =F781 -> 12509.98 | G19: =F800 -> 4248.3114 | H19: =G19/G$4-1 -> -0.16976122 | I19: =E788 -> 0.85686965
A20: 情境 B | B20: markets/nand B；成本年降 12% | C20: =PL!E124 -> 10595.374 | D20: =PL!E143 -> 3868.0581 | E20: =D20/D$4-1 -> -0.18290383 | F20: =PL!F124 -> 4805.2812 | G20: =PL!F143 -> 1309.1147 | H20: =G20/G$4-1 -> -0.74416239 | I20: =PL!E131 -> 0.83293536
A21: 情境 C | B21: markets/nand C；成本年降 10% | C21: =PL!E171 -> 10189.221 | D21: =PL!E190 -> 3682.7328 | E21: =D21/D$4-1 -> -0.2220523 | F21: =PL!F171 -> 2915.3792 | G21: =PL!F190 -> 536.8556 | H21: =G21/G$4-1 -> -0.89508341 | I21: =PL!E178 -> 0.82798488
A23: 讀法：第二季為公司指引（固定），價格與匯率係數只作用在第三季起；營業費用校準改變成本起點（第二季營業成本＝營收 − 營業利益 − 營業費用）。
A60: 案例區塊：市場層營收 −20%（價格；第三季起）（情境 A）
A61: A. 季度 | B61: 單位 | C61: FY26 第1季（2026Q2） | D61: FY26 第2季（2026Q3） | E61: FY26 第3季（2026Q4） | F61: FY26 第4季（2027Q1） | G61: FY27 第1季（2027Q2） | H61: FY27 第2季（2027Q3） | I61: FY27 第3季（2027Q4） | J61: FY27 第4季（2028Q1） | K61: FY28 第1季（2028Q2） | L61: FY28 第2季（2028Q3） | M61: FY28 第3季（2028Q4） | N61: FY28 第4季（2029Q1） | O61: FY29 第1季（2029Q2） | P61: FY29 第2季（2029Q3） | Q61: FY29 第3季（2029Q4） | R61: FY29 第4季（2030Q1） | T61: 說明
A62: 市場層營收（TrendForce 口徑，美元，同字母情境） | B62: $B | C62: =Units!H4*1 -> 10.72 | D62: =Units!I4*1 -> 14.951317 | E62: =Units!J4*1*0.8 -> 12.962852 | F62: =Units!K4*1*0.8 -> 14.283476 | G62: =Units!L4*1*0.8 -> 15.102937 | H62: =Units!M4*1*0.8 -> 15.170941 | I62: =Units!N4*1*0.8 -> 14.918425 | J62: =Units!O4*1*0.8 -> 14.985598 | K62: =Units!P4*1*0.8 -> 15.053074 | L62: =Units!Q4*1*0.8 -> 15.120853 | ... R62: =Units!W4*1*0.8 -> 16.047462 | T62: markets/nand；Sens 可乘份額係數、價格係數（第三季起）
A63: 位元（市場層；同字母） | B63: EB | C63: =Units!H7*1 -> 40.175758 | D63: =Units!I7*1 -> 44.826902 | E63: =Units!J7*1 -> 44.941148 | F63: =Units!K7*1 -> 48.077324 | G63: =Units!L7*1 -> 50.835581 | H63: =Units!M7*1 -> 53.752082 | I63: =Units!N7*1 -> 56.835907 | J63: =Units!O7*1 -> 60.096655 | ... R63: =Units!W7*1 -> 87.539517
A64: 營收 | B64: ¥B | C64: =q1_rev -> 1767.1 | D64: =g2_rev -> 2480 | E64: =E62*kx_k*fx -> 2136.8149 | F64: =F62*kx_k*fx -> 2354.5084 | G64: =G62*kx_k*fx -> 2489.5896 | H64: =H62*kx_k*fx -> 2500.7994 | I64: =I62*kx_k*fx -> 2459.1743 | J64: =J62*kx_k*fx -> 2470.2472 | K64: =K62*kx_k*fx -> 2481.37 | L64: =L62*kx_k*fx -> 2492.5429 | ... R64: =R62*kx_k*fx -> 2645.2864 | T64: 第一、二季實績；之後＝市場層 × 公司口徑係數 × 匯率
A65: SSD 與儲存 | B65: ¥B | C65: =q1_ss -> 1174.7 | D65: =D64*sssh_26 -> 1636.8 | E65: =E64*sssh_26 -> 1410.2978 | F65: =F64*sssh_26 -> 1553.9756 | G65: =G64*sssh_27 -> 1692.9209 | H65: =H64*sssh_27 -> 1700.5436 | I65: =I64*sssh_27 -> 1672.2385 | J65: =J64*sssh_27 -> 1679.7681 | K65: =K64*sssh_28 -> 1736.959 | L65: =L64*sssh_28 -> 1744.78 | M65: =M64*sssh_28 -> 1752.6362 | N65: =N64*sssh_28 -> 1771.2136 | O65: =O64*sssh_29 -> 1805.6461 | P65: =P64*sssh_29 -> 1840.7479 | Q65: =Q64*sssh_29 -> 1876.5322 | R65: =R64*sssh_29 -> 1851.7005 | T65: 官方分部；第一季實績，之後＝營收 × 占比（In）
A66: SSD 與儲存：AI 相關（＝SSD 與儲存 × AI 企業級 SSD 占比） | B66: ¥B | C66: =C65*(0.75*Units!D16+0.25*Units!E16) -> 687.40335 | D66: =D65*(0.75*Units!D16+0.25*Units!E16) -> 957.81204 | E66: =E65*(0.75*Units!D16+0.25*Units!E16) -> 825.26896 | F66: =F65*(0.75*Units!D16+0.25*Units!E16) -> 909.34538 | G66: =G65*(0.75*Units!E16+0.25*Units!F16) -> 1166.381 | H66: =H65*(0.75*Units!E16+0.25*Units!F16) -> 1171.6328 | I66: =I65*(0.75*Units!E16+0.25*Units!F16) -> 1152.1313 | J66: =J65*(0.75*Units!E16+0.25*Units!F16) -> 1157.319 | K66: =K65*(0.75*Units!F16+0.25*Units!G16) -> 1267.635 | L66: =L65*(0.75*Units!F16+0.25*Units!G16) -> 1273.3427 | M66: =M65*(0.75*Units!F16+0.25*Units!G16) -> 1279.0762 | N66: =N65*(0.75*Units!F16+0.25*Units!G16) -> 1292.634 | O66: =O65*(0.75*Units!G16+0.25*Units!H16) -> 1376.1869 | P66: =P65*(0.75*Units!G16+0.25*Units!H16) -> 1402.9401 | Q66: =Q65*(0.75*Units!G16+0.25*Units!H16) -> 1430.2133 | R66: =R65*(0.75*Units!G16+0.25*Units!H16) -> 1411.2876 | T66: 命題子列（Derived）：會計年度（4 月起）≈ 0.75 × 當年＋0.25 × 次年；假設公司 SSD 組合與產業（企業級＋PC）相同
A67: SSD 與儲存：非 AI | B67: ¥B | C67: =C65-C66 -> 487.29665 | D67: =D65-D66 -> 678.98796 | E67: =E65-E66 -> 585.02886 | F67: =F65-F66 -> 644.63019 | G67: =G65-G66 -> 526.53992 | H67: =H65-H66 -> 528.91077 | I67: =I65-I66 -> 520.10719 | J67: =J65-J66 -> 522.44908 | ... R67: =R65-R66 -> 440.41283
A68: 其他 | B68: ¥B | C68: =q1_rev-q1_ss-q1_sd -> 66.7 | D68: =D64*otsh_26 -> 99.2 | E68: =E64*otsh_26 -> 85.472595 | F68: =F64*otsh_26 -> 94.180337 | G68: =G64*otsh_27 -> 99.583582 | H68: =H64*otsh_27 -> 100.03198 | I68: =I64*otsh_27 -> 98.366973 | J68: =J64*otsh_27 -> 98.80989 | K68: =K64*otsh_28 -> 99.254801 | L68: =L64*otsh_28 -> 99.701716 | M68: =M64*otsh_28 -> 100.15064 | N68: =N64*otsh_28 -> 101.21221 | O68: =O64*otsh_29 -> 103.17978 | P68: =P64*otsh_29 -> 105.1856 | Q68: =Q64*otsh_29 -> 107.23041 | R68: =R64*otsh_29 -> 105.81145 | T68: 官方分部（零售、對 SanDisk 銷售）；實績＝營收 − 兩主分部
A69: 智慧裝置 | B69: ¥B | C69: =q1_sd -> 525.7 | D69: =D64-D65-D68 -> 744 | E69: =E64-E65-E68 -> 641.04446 | F69: =F64-F65-F68 -> 706.35253 | G69: =G64-G65-G68 -> 697.08508 | H69: =H64-H65-H68 -> 700.22384 | I69: =I64-I65-I68 -> 688.56881 | J69: =J64-J65-J68 -> 691.66923 | K69: =K64-K65-K68 -> 645.15621 | ... R69: =R64-R65-R68 -> 687.77446 | T69: 官方分部；預測季＝營收 − SSD 與儲存 − 其他
A70: 檢查：分部合計 − 營收（季） | B70: ¥B | C70: =C65+C69+C68-C64 -> 0 | D70: =D65+D69+D68-D64 -> 0 | E70: =E65+E69+E68-E64 -> 0 | F70: =F65+F69+F68-F64 -> 0 | G70: =G65+G69+G68-G64 -> 0 | H70: =H65+H69+H68-H64 -> 0 | I70: =I65+I69+I68-I64 -> 0 | J70: =J65+J69+J68-J64 -> 0 | ... R70: =R65+R69+R68-R64 -> 0
A71: 每 EB 營業成本（第二季以實績校準，之後每年 × (1 − 成本年降)） | B71: ¥B/EB | C71: =C72/C63 -> 9.6326745 | D71: =D72/D63 -> 9.5099143 | E71: =$D71*(1-cd_A)^(1/4) -> 9.1580122 | F71: =$D71*(1-cd_A)^(2/4) -> 8.8191318 | G71: =$D71*(1-cd_A)^(3/4) -> 8.4927911 | H71: =$D71*(1-cd_A)^(4/4) -> 8.1785263 | I71: =$D71*(1-cd_A)^(5/4) -> 7.8758905 | J71: =$D71*(1-cd_A)^(6/4) -> 7.5844533 | K71: =$D71*(1-cd_A)^(7/4) -> 7.3038004 | L71: =$D71*(1-cd_A)^(8/4) -> 7.0335326 | M71: =$D71*(1-cd_A)^(9/4) -> 6.7732658 | N71: =$D71*(1-cd_A)^(10/4) -> 6.5226298 | O71: =$D71*(1-cd_A)^(11/4) -> 6.2812683 | P71: =$D71*(1-cd_A)^(12/4) -> 6.0488381 | Q71: =$D71*(1-cd_A)^(13/4) -> 5.8250086 | R71: =$D71*(1-cd_A)^(14/4) -> 5.6094617
A72: 營業成本 | B72: ¥B | C72: =q1_rev-q1_gp -> 387 | D72: =g2_rev-g2_op-g2_ox -> 426.3 | E72: =E63*E71 -> 411.57158 | F72: =F63*F71 -> 424.00025 | G72: =G63*G71 -> 431.73597 | H72: =H63*H71 -> 439.61282 | I72: =I63*I71 -> 447.63338 | J72: =J63*J71 -> 455.80027 | K72: =K63*K71 -> 464.11617 | L72: =L63*L71 -> 472.58378 | ... R72: =R63*R71 -> 491.04957 | T72: 第二季＝實績營收 − 實績營業利益 − 推估營業費用
A73: 毛利率 | B73: % | C73: =1-C72/C64 -> 0.78099711 | D73: =1-D72/D64 -> 0.82810484 | E73: =1-E72/E64 -> 0.80739016 | F73: =1-F72/F64 -> 0.81991984 | G73: =1-G72/G64 -> 0.82658348 | H73: =1-H72/H64 -> 0.82421109 | I73: =1-I72/I64 -> 0.81797412 | J73: =1-J72/J64 -> 0.81548395 | ... R73: =1-R72/R64 -> 0.81436809
A74: 營業費用 | B74: ¥B | C74: =q1_gp-q1_op -> 110.1 | D74: =g2_ox -> 59 | E74: =(g2_ox-ox_var*g2_rev)*(1+ox_g)^(1/4)+ox_var*E64 -> 56.392837 | F74: =(g2_ox-ox_var*g2_rev)*(1+ox_g)^(2/4)+ox_var*F64 -> 59.414347 | G74: =(g2_ox-ox_var*g2_rev)*(1+ox_g)^(3/4)+ox_var*G64 -> 61.630098 | H74: =(g2_ox-ox_var*g2_rev)*(1+ox_g)^(4/4)+ox_var*H64 -> 62.627994 | I74: =(g2_ox-ox_var*g2_rev)*(1+ox_g)^(5/4)+ox_var*I64 -> 63.1189 | J74: =(g2_ox-ox_var*g2_rev)*(1+ox_g)^(6/4)+ox_var*J64 -> 64.158661 | K74: =(g2_ox-ox_var*g2_rev)*(1+ox_g)^(7/4)+ox_var*K64 -> 65.221323 | L74: =(g2_ox-ox_var*g2_rev)*(1+ox_g)^(8/4)+ox_var*L64 -> 66.307429 | M74: =(g2_ox-ox_var*g2_rev)*(1+ox_g)^(9/4)+ox_var*M64 -> 67.417533 | N74: =(g2_ox-ox_var*g2_rev)*(1+ox_g)^(10/4)+ox_var*N64 -> 68.704859 | O74: =(g2_ox-ox_var*g2_rev)*(1+ox_g)^(11/4)+ox_var*O64 -> 70.243329 | P74: =(g2_ox-ox_var*g2_rev)*(1+ox_g)^(12/4)+ox_var*P64 -> 71.816599 | Q74: =(g2_ox-ox_var*g2_rev)*(1+ox_g)^(13/4)+ox_var*Q64 -> 73.425462 | R74: =(g2_ox-ox_var*g2_rev)*(1+ox_g)^(14/4)+ox_var*R64 -> 74.194852 | T74: 固定部分以第二季校準（Derived）
A75: 營業利益 | B75: ¥B | C75: =C64-C72-C74 -> 1270 | D75: =D64-D72-D74 -> 1994.7 | E75: =E64-E72-E74 -> 1668.8505 | F75: =F64-F72-F74 -> 1871.0938 | G75: =G64-G72-G74 -> 1996.2235 | H75: =H64-H72-H74 -> 1998.5586 | I75: =I64-I72-I74 -> 1948.422 | J75: =J64-J72-J74 -> 1950.2883 | ... R75: =R64-R72-R74 -> 2080.0419
A77: 淨利 | B77: ¥B | C77: =q1_ni -> 842.2 | D77: =g2_ni -> 1360 | E77: =(E75+nonop_q+rf*nc_j/4)*(1-tax) -> 1124.8842 | F77: =(F75+nonop_q+rf*nc_j/4)*(1-tax) -> 1262.4097 | G77: =(G75+nonop_q+rf*$D98/4)*(1-tax) -> 1352.4616 | H77: =(H75+nonop_q+rf*$D98/4)*(1-tax) -> 1354.0495 | I77: =(I75+nonop_q+rf*$D98/4)*(1-tax) -> 1319.9566 | J77: =(J75+nonop_q+rf*$D98/4)*(1-tax) -> 1321.2256 | K77: =(K75+nonop_q+rf*$E98/4)*(1-tax) -> 1329.4806 | L77: =(L75+nonop_q+rf*$E98/4)*(1-tax) -> 1330.5816 | M77: =(M75+nonop_q+rf*$E98/4)*(1-tax) -> 1331.5955 | N77: =(N75+nonop_q+rf*$E98/4)*(1-tax) -> 1347.6859 | O77: =(O75+nonop_q+rf*$F98/4)*(1-tax) -> 1383.1803 | P77: =(P75+nonop_q+rf*$F98/4)*(1-tax) -> 1412.1958 | Q77: =(Q75+nonop_q+rf*$F98/4)*(1-tax) -> 1441.8016 | R77: =(R75+nonop_q+rf*$F98/4)*(1-tax) -> 1423.5845 | T77: （營業利益＋業外＋淨現金 × 收益率 ÷ 4）×（1 − 稅率）；FY2026 用 2026-06-30 淨現金
A78: 季 EPS（稀釋，分割後） | B78: JPY | C78: =C77/(sh0+dil)*1000 -> 507.34333 | D78: =D77/(sh0+dil)*1000 -> 819.26731 | E78: =E77/(sh0+dil)*1000 -> 677.63298 | F78: =F77/(sh0+dil)*1000 -> 760.47867 | G78: =G77/(sh0+dil)*1000 -> 814.72615 | H78: =H77/(sh0+dil)*1000 -> 815.6827 | I78: =I77/(sh0+dil)*1000 -> 795.14506 | J78: =J77/(sh0+dil)*1000 -> 795.90955 | ... R78: =R77/(sh0+dil)*1000 -> 857.57077
A80: B. 年度（會計年度） | B80: 單位 | C80: FY2025A | D80: FY2026 | E80: FY2027 | F80: FY2028 | G80: FY2029 | T80: 說明
A81: 營收 | B81: ¥B | C81: =a25_rev -> 2337.6 | D81: =SUM(C64:F64) -> 8738.4233 | E81: =SUM(G64:J64) -> 9919.8105 | F81: =SUM(K64:N64) -> 10007.984 | G81: =SUM(O64:R64) -> 10535.181 | T81: FY2026＝第一、二季實績＋第三、四季推導
A82: 營收：SSD 與儲存 | B82: ¥B | C82: =p1_ss+p2_ss+p3_ss+p4_ss -> 1364.7 | D82: =SUM(C65:F65) -> 5775.7734 | E82: =SUM(G65:J65) -> 6745.4712 | F82: =SUM(K65:N65) -> 7005.5889 | G82: =SUM(O65:R65) -> 7374.6266
A83: SSD 與儲存：AI 相關 | B83: ¥B | C83: =C82*(0.75*Units!C16+0.25*Units!D16) -> 507.67957 | D83: =SUM(C66:F66) -> 3379.8297 | E83: =SUM(G66:J66) -> 4647.4642 | F83: =SUM(K66:N66) -> 5112.6879 | G83: =SUM(O66:R66) -> 5620.6279
A84: 營收：智慧裝置 | B84: ¥B | C84: =p1_sd+p2_sd+p3_sd+p4_sd -> 759.5 | D84: =SUM(C69:F69) -> 2617.097 | E84: =SUM(G69:J69) -> 2777.547 | F84: =SUM(K69:N69) -> 2602.0759 | G84: =SUM(O69:R69) -> 2739.147
A85: 營收：其他 | B85: ¥B | C85: =a25_rev-C82-C84 -> 213.4 | D85: =SUM(C68:F68) -> 345.55293 | E85: =SUM(G68:J68) -> 396.79242 | F85: =SUM(K68:N68) -> 400.31936 | G85: =SUM(O68:R68) -> 421.40723 | T85: FY2025＝營收 − 兩主分部（含報導值進位差約 0.1）
A86: 檢查：分部合計 − 合併營收（年） | B86: ¥B | C86: =C82+C84+C85-C81 -> 0 | D86: =D82+D84+D85-D81 -> 0 | E86: =E82+E84+E85-E81 -> 0 | F86: =F82+F84+F85-F81 -> 0 | G86: =G82+G84+G85-G81 -> 0
A87: 營業成本 | B87: ¥B | C87: =a25_rev-(p1_gp+p2_gp+p3_gp+p4_gp) -> 1324.8 | D87: =SUM(C72:F72) -> 1648.8718 | E87: =SUM(G72:J72) -> 1774.7824 | F87: =SUM(K72:N72) -> 1900.701 | G87: =SUM(O72:R72) -> 1974.709
A88: 毛利率 | B88: % | C88: =1-C87/C81 -> 0.43326489 | D88: =1-D87/D81 -> 0.81130786 | E88: =1-E87/E81 -> 0.82108706 | F88: =1-F87/F81 -> 0.81008153 | G88: =1-G87/G81 -> 0.8125605
A89: 營業費用 | B89: ¥B | D89: =SUM(C74:F74) -> 284.90718 | E89: =SUM(G74:J74) -> 251.53565 | F89: =SUM(K74:N74) -> 267.65114 | G89: =SUM(O74:R74) -> 289.68024
A90: 營業利益 | B90: ¥B | C90: =p1_op+p2_op+p3_op+p4_op -> 869 | D90: =SUM(C75:F75) -> 6804.6443 | E90: =SUM(G75:J75) -> 7893.4925 | F90: =SUM(K75:N75) -> 7839.6319 | G90: =SUM(O75:R75) -> 8270.7916
A91: 營業利益率 | B91: % | C91: =C90/C81 -> 0.3717488 | D91: =D90/D81 -> 0.7787039 | E91: =E90/E81 -> 0.79573016 | F91: =F90/F81 -> 0.78333777 | G91: =G90/G81 -> 0.78506404
A92: 淨利 | B92: ¥B | C92: =a25_ni -> 554.5 | D92: =SUM(C77:F77) -> 4589.4939 | E92: =SUM(G77:J77) -> 5347.6933 | F92: =SUM(K77:N77) -> 5339.3436 | G92: =SUM(O77:R77) -> 5660.7622
A93: 折舊攤銷 | B93: ¥B | D93: =da_y -> 320 | E93: =da_y -> 320 | F93: =da_y -> 320 | G93: =da_y -> 320
A94: 資本支出（含合資廠分攤） | B94: ¥B | D94: =cap_2026 -> 450 | E94: =cap_2027 -> 470 | F94: =cap_2028 -> 470 | G94: =cap_2029 -> 470
A95: 自由現金流（淨利＋折舊 − 資本支出） | B95: ¥B | D95: =D92+D93-D94 -> 4459.4939 | E95: =E92+E93-E94 -> 5197.6933 | F95: =F92+F93-F94 -> 5189.3436 | G95: =G92+G93-G94 -> 5510.7622
A96: 股東回饋（以買回計） | B96: ¥B | D96: =MAX(0,payout*(SUM(D77:F77)+0.75*(D93-D94))) -> 729.95878 | E96: =MAX(0,payout*E95) -> 1039.5387 | F96: =MAX(0,payout*F95) -> 1037.8687 | G96: =MAX(0,payout*G95) -> 1102.1524 | T96: FY2026 只計 2026-07 以後三季的自由現金流
A97: 期末權益 | B97: ¥B | C97: =eq25 -> 1399.1 | D97: =eq_j+SUM(D77:F77)-D96 -> 5421.6351 | E97: =D97+E92-E96 -> 9729.7897 | F97: =E97+F92-F96 -> 14031.265 | G97: =F97+G92-G96 -> 18589.874 | T97: FY2026＝2026-06-30 權益＋第二至四季淨利 − 回饋（不含其他綜合損益）
A98: 期末淨現金 | B98: ¥B | D98: =nc_j+(SUM(D77:F77)+0.75*(D93-D94))-D96 -> 3076.2351 | E98: =D98+E95-E96 -> 7234.3897 | F98: =E98+F95-F96 -> 11385.865 | G98: =F98+G95-G96 -> 15794.474
A99: 期末流通股數（分割後） | B99: 百萬股 | D99: =sh0-D96/bb_px*1000 -> 1586.8147 | E99: =D99-E96/bb_px*1000 -> 1505.3142 | F99: =E99-F96/bb_px*1000 -> 1423.9446 | G99: =F99-G96/bb_px*1000 -> 1337.5352
A100: EPS（稀釋：期末流通股數＋dil；分割後） | B100: JPY | C100: =a25_eps -> 341.4 | D100: =D92/(D99+dil)*1000 -> 2863.4394 | E100: =E92/(E99+dil)*1000 -> 3515.2356 | F100: =F92/(F99+dil)*1000 -> 3708.082 | G100: =G92/(G99+dil)*1000 -> 4182.2797
A101: 每股淨值 BVPS（期末流通股數） | B101: JPY | D101: =D97/D99*1000 -> 3416.6782 | E101: =E97/E99*1000 -> 6463.6271 | F101: =F97/F99*1000 -> 9853.7991 | G101: =G97/G99*1000 -> 13898.606
A102: ROE（期末權益） | B102: % | D102: =D92/D97 -> 0.84651471 | E102: =E92/E97 -> 0.54962064 | F102: =F92/F97 -> 0.38053188 | G102: =G92/G97 -> 0.30450782
A103: 每股自由現金流（稀釋） | B103: JPY | E103: =E95/(E99+dil)*1000 -> 3416.6351 | F103: =F95/(F99+dil)*1000 -> 3603.9096 | G103: =G95/(G99+dil)*1000 -> 4071.4569
A104: 檢查：FY2025 營收、淨利 − 四季合計；第一季、第二季 − 實績與指引（應為 0） | B104: ¥B | D104: =ABS(C64-q1_rev)+ABS(D75-g2_op)+ABS(C81-2337.6) -> 0
A110: 案例區塊：市場層營收 +20%（價格）（情境 A）
A111: A. 季度 | B111: 單位 | C111: FY26 第1季（2026Q2） | D111: FY26 第2季（2026Q3） | E111: FY26 第3季（2026Q4） | F111: FY26 第4季（2027Q1） | G111: FY27 第1季（2027Q2） | H111: FY27 第2季（2027Q3） | I111: FY27 第3季（2027Q4） | J111: FY27 第4季（2028Q1） | K111: FY28 第1季（2028Q2） | L111: FY28 第2季（2028Q3） | M111: FY28 第3季（2028Q4） | N111: FY28 第4季（2029Q1） | O111: FY29 第1季（2029Q2） | P111: FY29 第2季（2029Q3） | Q111: FY29 第3季（2029Q4） | R111: FY29 第4季（2030Q1） | T111: 說明
A112: 市場層營收（TrendForce 口徑，美元，同字母情境） | B112: $B | C112: =Units!H4*1 -> 10.72 | D112: =Units!I4*1 -> 14.951317 | E112: =Units!J4*1*1.2 -> 19.444278 | F112: =Units!K4*1*1.2 -> 21.425214 | G112: =Units!L4*1*1.2 -> 22.654406 | H112: =Units!M4*1*1.2 -> 22.756412 | I112: =Units!N4*1*1.2 -> 22.377637 | J112: =Units!O4*1*1.2 -> 22.478397 | K112: =Units!P4*1*1.2 -> 22.579611 | L112: =Units!Q4*1*1.2 -> 22.68128 | ... R112: =Units!W4*1*1.2 -> 24.071193 | T112: markets/nand；Sens 可乘份額係數、價格係數（第三季起）
A113: 位元（市場層；同字母） | B113: EB | C113: =Units!H7*1 -> 40.175758 | D113: =Units!I7*1 -> 44.826902 | E113: =Units!J7*1 -> 44.941148 | F113: =Units!K7*1 -> 48.077324 | G113: =Units!L7*1 -> 50.835581 | H113: =Units!M7*1 -> 53.752082 | I113: =Units!N7*1 -> 56.835907 | J113: =Units!O7*1 -> 60.096655 | ... R113: =Units!W7*1 -> 87.539517
A114: 營收 | B114: ¥B | C114: =q1_rev -> 1767.1 | D114: =g2_rev -> 2480 | E114: =E112*kx_k*fx -> 3205.2223 | F114: =F112*kx_k*fx -> 3531.7627 | G114: =G112*kx_k*fx -> 3734.3843 | H114: =H112*kx_k*fx -> 3751.1991 | I114: =I112*kx_k*fx -> 3688.7615 | J114: =J112*kx_k*fx -> 3705.3709 | K114: =K112*kx_k*fx -> 3722.055 | L114: =L112*kx_k*fx -> 3738.8143 | ... R114: =R112*kx_k*fx -> 3967.9295 | T114: 第一、二季實績；之後＝市場層 × 公司口徑係數 × 匯率
A115: SSD 與儲存 | B115: ¥B | C115: =q1_ss -> 1174.7 | D115: =D114*sssh_26 -> 1636.8 | E115: =E114*sssh_26 -> 2115.4467 | F115: =F114*sssh_26 -> 2330.9633 | G115: =G114*sssh_27 -> 2539.3813 | H115: =H114*sssh_27 -> 2550.8154 | I115: =I114*sssh_27 -> 2508.3578 | J115: =J114*sssh_27 -> 2519.6522 | K115: =K114*sssh_28 -> 2605.4385 | L115: =L114*sssh_28 -> 2617.17 | M115: =M114*sssh_28 -> 2628.9544 | N115: =N114*sssh_28 -> 2656.8204 | O115: =O114*sssh_29 -> 2708.4691 | P115: =P114*sssh_29 -> 2761.1219 | Q115: =Q114*sssh_29 -> 2814.7982 | R115: =R114*sssh_29 -> 2777.5507 | T115: 官方分部；第一季實績，之後＝營收 × 占比（In）
A116: SSD 與儲存：AI 相關（＝SSD 與儲存 × AI 企業級 SSD 占比） | B116: ¥B | C116: =C115*(0.75*Units!D16+0.25*Units!E16) -> 687.40335 | D116: =D115*(0.75*Units!D16+0.25*Units!E16) -> 957.81204 | E116: =E115*(0.75*Units!D16+0.25*Units!E16) -> 1237.9034 | F116: =F115*(0.75*Units!D16+0.25*Units!E16) -> 1364.0181 | G116: =G115*(0.75*Units!E16+0.25*Units!F16) -> 1749.5715 | H116: =H115*(0.75*Units!E16+0.25*Units!F16) -> 1757.4493 | I116: =I115*(0.75*Units!E16+0.25*Units!F16) -> 1728.197 | J116: =J115*(0.75*Units!E16+0.25*Units!F16) -> 1735.9786 | K116: =K115*(0.75*Units!F16+0.25*Units!G16) -> 1901.4524 | L116: =L115*(0.75*Units!F16+0.25*Units!G16) -> 1910.0141 | M116: =M115*(0.75*Units!F16+0.25*Units!G16) -> 1918.6143 | N116: =N115*(0.75*Units!F16+0.25*Units!G16) -> 1938.951 | O116: =O115*(0.75*Units!G16+0.25*Units!H16) -> 2064.2804 | P116: =P115*(0.75*Units!G16+0.25*Units!H16) -> 2104.4101 | Q116: =Q115*(0.75*Units!G16+0.25*Units!H16) -> 2145.32 | R116: =R115*(0.75*Units!G16+0.25*Units!H16) -> 2116.9314 | T116: 命題子列（Derived）：會計年度（4 月起）≈ 0.75 × 當年＋0.25 × 次年；假設公司 SSD 組合與產業（企業級＋PC）相同
A117: SSD 與儲存：非 AI | B117: ¥B | C117: =C115-C116 -> 487.29665 | D117: =D115-D116 -> 678.98796 | E117: =E115-E116 -> 877.54329 | F117: =F115-F116 -> 966.94529 | G117: =G115-G116 -> 789.80988 | H117: =H115-H116 -> 793.36615 | I117: =I115-I116 -> 780.16079 | J117: =J115-J116 -> 783.67362 | ... R117: =R115-R116 -> 660.61924
A118: 其他 | B118: ¥B | C118: =q1_rev-q1_ss-q1_sd -> 66.7 | D118: =D114*otsh_26 -> 99.2 | E118: =E114*otsh_26 -> 128.20889 | F118: =F114*otsh_26 -> 141.27051 | G118: =G114*otsh_27 -> 149.37537 | H118: =H114*otsh_27 -> 150.04797 | I118: =I114*otsh_27 -> 147.55046 | J118: =J114*otsh_27 -> 148.21483 | K118: =K114*otsh_28 -> 148.8822 | L118: =L114*otsh_28 -> 149.55257 | M118: =M114*otsh_28 -> 150.22596 | N118: =N114*otsh_28 -> 151.81831 | O118: =O114*otsh_29 -> 154.76966 | P118: =P114*otsh_29 -> 157.77839 | Q118: =Q114*otsh_29 -> 160.84561 | R118: =R114*otsh_29 -> 158.71718 | T118: 官方分部（零售、對 SanDisk 銷售）；實績＝營收 − 兩主分部
A119: 智慧裝置 | B119: ¥B | C119: =q1_sd -> 525.7 | D119: =D114-D115-D118 -> 744 | E119: =E114-E115-E118 -> 961.5667 | F119: =F114-F115-F118 -> 1059.5288 | G119: =G114-G115-G118 -> 1045.6276 | H119: =H114-H115-H118 -> 1050.3358 | I119: =I114-I115-I118 -> 1032.8532 | J119: =J114-J115-J118 -> 1037.5038 | K119: =K114-K115-K118 -> 967.73431 | ... R119: =R114-R115-R118 -> 1031.6617 | T119: 官方分部；預測季＝營收 − SSD 與儲存 − 其他
A120: 檢查：分部合計 − 營收（季） | B120: ¥B | C120: =C115+C119+C118-C114 -> 0 | D120: =D115+D119+D118-D114 -> 0 | E120: =E115+E119+E118-E114 -> 0 | F120: =F115+F119+F118-F114 -> 0 | G120: =G115+G119+G118-G114 -> 0 | H120: =H115+H119+H118-H114 -> 0 | I120: =I115+I119+I118-I114 -> 0 | J120: =J115+J119+J118-J114 -> 0 | ... R120: =R115+R119+R118-R114 -> 0
A121: 每 EB 營業成本（第二季以實績校準，之後每年 × (1 − 成本年降)） | B121: ¥B/EB | C121: =C122/C113 -> 9.6326745 | D121: =D122/D113 -> 9.5099143 | E121: =$D121*(1-cd_A)^(1/4) -> 9.1580122 | F121: =$D121*(1-cd_A)^(2/4) -> 8.8191318 | G121: =$D121*(1-cd_A)^(3/4) -> 8.4927911 | H121: =$D121*(1-cd_A)^(4/4) -> 8.1785263 | I121: =$D121*(1-cd_A)^(5/4) -> 7.8758905 | J121: =$D121*(1-cd_A)^(6/4) -> 7.5844533 | K121: =$D121*(1-cd_A)^(7/4) -> 7.3038004 | L121: =$D121*(1-cd_A)^(8/4) -> 7.0335326 | M121: =$D121*(1-cd_A)^(9/4) -> 6.7732658 | N121: =$D121*(1-cd_A)^(10/4) -> 6.5226298 | O121: =$D121*(1-cd_A)^(11/4) -> 6.2812683 | P121: =$D121*(1-cd_A)^(12/4) -> 6.0488381 | Q121: =$D121*(1-cd_A)^(13/4) -> 5.8250086 | R121: =$D121*(1-cd_A)^(14/4) -> 5.6094617
A122: 營業成本 | B122: ¥B | C122: =q1_rev-q1_gp -> 387 | D122: =g2_rev-g2_op-g2_ox -> 426.3 | E122: =E113*E121 -> 411.57158 | F122: =F113*F121 -> 424.00025 | G122: =G113*G121 -> 431.73597 | H122: =H113*H121 -> 439.61282 | I122: =I113*I121 -> 447.63338 | J122: =J113*J121 -> 455.80027 | K122: =K113*K121 -> 464.11617 | L122: =L113*L121 -> 472.58378 | ... R122: =R113*R121 -> 491.04957 | T122: 第二季＝實績營收 − 實績營業利益 − 推估營業費用
A123: 毛利率 | B123: % | C123: =1-C122/C114 -> 0.78099711 | D123: =1-D122/D114 -> 0.82810484 | E123: =1-E122/E114 -> 0.87159344 | F123: =1-F122/F114 -> 0.87994656 | G123: =1-G122/G114 -> 0.88438898 | H123: =1-H122/H114 -> 0.88280739 | I123: =1-I122/I114 -> 0.87864941 | J123: =1-J122/J114 -> 0.8769893 | ... R123: =1-R122/R114 -> 0.87624539
A124: 營業費用 | B124: ¥B | C124: =q1_gp-q1_op -> 110.1 | D124: =g2_ox -> 59 | E124: =(g2_ox-ox_var*g2_rev)*(1+ox_g)^(1/4)+ox_var*E114 -> 67.076911 | F124: =(g2_ox-ox_var*g2_rev)*(1+ox_g)^(2/4)+ox_var*F114 -> 71.186889 | G124: =(g2_ox-ox_var*g2_rev)*(1+ox_g)^(3/4)+ox_var*G114 -> 74.078046 | H124: =(g2_ox-ox_var*g2_rev)*(1+ox_g)^(4/4)+ox_var*H114 -> 75.131991 | I124: =(g2_ox-ox_var*g2_rev)*(1+ox_g)^(5/4)+ox_var*I114 -> 75.414772 | J124: =(g2_ox-ox_var*g2_rev)*(1+ox_g)^(6/4)+ox_var*J114 -> 76.509897 | K124: =(g2_ox-ox_var*g2_rev)*(1+ox_g)^(7/4)+ox_var*K114 -> 77.628173 | L124: =(g2_ox-ox_var*g2_rev)*(1+ox_g)^(8/4)+ox_var*L114 -> 78.770143 | M124: =(g2_ox-ox_var*g2_rev)*(1+ox_g)^(9/4)+ox_var*M114 -> 79.936364 | N124: =(g2_ox-ox_var*g2_rev)*(1+ox_g)^(10/4)+ox_var*N114 -> 81.356385 | O124: =(g2_ox-ox_var*g2_rev)*(1+ox_g)^(11/4)+ox_var*O114 -> 83.140801 | P124: =(g2_ox-ox_var*g2_rev)*(1+ox_g)^(12/4)+ox_var*P114 -> 84.964798 | Q124: =(g2_ox-ox_var*g2_rev)*(1+ox_g)^(13/4)+ox_var*Q114 -> 86.829263 | R124: =(g2_ox-ox_var*g2_rev)*(1+ox_g)^(14/4)+ox_var*R114 -> 87.421284 | T124: 固定部分以第二季校準（Derived）
A125: 營業利益 | B125: ¥B | C125: =C114-C122-C124 -> 1270 | D125: =D114-D122-D124 -> 1994.7 | E125: =E114-E122-E124 -> 2726.5738 | F125: =F114-F122-F124 -> 3036.5755 | G125: =G114-G122-G124 -> 3228.5703 | H125: =H114-H122-H124 -> 3236.4543 | I125: =I114-I122-I124 -> 3165.7133 | J125: =J114-J122-J124 -> 3173.0607 | ... R125: =R114-R122-R124 -> 3389.4587
A127: 淨利 | B127: ¥B | C127: =q1_ni -> 842.2 | D127: =g2_ni -> 1360 | E127: =(E125+nonop_q+rf*nc_j/4)*(1-tax) -> 1844.1361 | F127: =(F125+nonop_q+rf*nc_j/4)*(1-tax) -> 2054.9372 | G127: =(G125+nonop_q+rf*$D148/4)*(1-tax) -> 2192.5134 | H127: =(H125+nonop_q+rf*$D148/4)*(1-tax) -> 2197.8746 | I127: =(I125+nonop_q+rf*$D148/4)*(1-tax) -> 2149.7707 | J127: =(J125+nonop_q+rf*$D148/4)*(1-tax) -> 2154.7669 | K127: =(K125+nonop_q+rf*$E148/4)*(1-tax) -> 2171.318 | L127: =(L125+nonop_q+rf*$E148/4)*(1-tax) -> 2176.1798 | M127: =(M125+nonop_q+rf*$E148/4)*(1-tax) -> 2180.9714 | N127: =(N125+nonop_q+rf*$E148/4)*(1-tax) -> 2205.9949 | O127: =(O125+nonop_q+rf*$F148/4)*(1-tax) -> 2262.6637 | P127: =(P125+nonop_q+rf*$F148/4)*(1-tax) -> 2308.5582 | Q127: =(Q125+nonop_q+rf*$F148/4)*(1-tax) -> 2355.3711 | R127: =(R125+nonop_q+rf*$F148/4)*(1-tax) -> 2325.2135 | T127: （營業利益＋業外＋淨現金 × 收益率 ÷ 4）×（1 − 稅率）；FY2026 用 2026-06-30 淨現金
A128: 季 EPS（稀釋，分割後） | B128: JPY | C128: =C127/(sh0+dil)*1000 -> 507.34333 | D128: =D127/(sh0+dil)*1000 -> 819.26731 | E128: =E127/(sh0+dil)*1000 -> 1110.9121 | F128: =F127/(sh0+dil)*1000 -> 1237.8992 | G128: =G127/(sh0+dil)*1000 -> 1320.7754 | H128: =H127/(sh0+dil)*1000 -> 1324.005 | I128: =I127/(sh0+dil)*1000 -> 1295.0271 | J128: =J127/(sh0+dil)*1000 -> 1298.0368 | ... R128: =R127/(sh0+dil)*1000 -> 1400.7143
A130: B. 年度（會計年度） | B130: 單位 | C130: FY2025A | D130: FY2026 | E130: FY2027 | F130: FY2028 | G130: FY2029 | T130: 說明
A131: 營收 | B131: ¥B | C131: =a25_rev -> 2337.6 | D131: =SUM(C114:F114) -> 10984.085 | E131: =SUM(G114:J114) -> 14879.716 | F131: =SUM(K114:N114) -> 15011.976 | G131: =SUM(O114:R114) -> 15802.771 | T131: FY2026＝第一、二季實績＋第三、四季推導
A132: 營收：SSD 與儲存 | B132: ¥B | C132: =p1_ss+p2_ss+p3_ss+p4_ss -> 1364.7 | D132: =SUM(C115:F115) -> 7257.9101 | E132: =SUM(G115:J115) -> 10118.207 | F132: =SUM(K115:N115) -> 10508.383 | G132: =SUM(O115:R115) -> 11061.94
A133: SSD 與儲存：AI 相關 | B133: ¥B | C133: =C132*(0.75*Units!C16+0.25*Units!D16) -> 507.67957 | D133: =SUM(C116:F116) -> 4247.1369 | E133: =SUM(G116:J116) -> 6971.1963 | F133: =SUM(K116:N116) -> 7669.0318 | G133: =SUM(O116:R116) -> 8430.9419
A134: 營收：智慧裝置 | B134: ¥B | C134: =p1_sd+p2_sd+p3_sd+p4_sd -> 759.5 | D134: =SUM(C119:F119) -> 3290.7955 | E134: =SUM(G119:J119) -> 4166.3204 | F134: =SUM(K119:N119) -> 3903.1138 | G134: =SUM(O119:R119) -> 4108.7205
A135: 營收：其他 | B135: ¥B | C135: =a25_rev-C132-C134 -> 213.4 | D135: =SUM(C118:F118) -> 435.3794 | E135: =SUM(G118:J118) -> 595.18863 | F135: =SUM(K118:N118) -> 600.47905 | G135: =SUM(O118:R118) -> 632.11085 | T135: FY2025＝營收 − 兩主分部（含報導值進位差約 0.1）
A136: 檢查：分部合計 − 合併營收（年） | B136: ¥B | C136: =C132+C134+C135-C131 -> 0 | D136: =D132+D134+D135-D131 -> 0 | E136: =E132+E134+E135-E131 -> 0 | F136: =F132+F134+F135-F131 -> 0 | G136: =G132+G134+G135-G131 -> 0
A137: 營業成本 | B137: ¥B | C137: =a25_rev-(p1_gp+p2_gp+p3_gp+p4_gp) -> 1324.8 | D137: =SUM(C122:F122) -> 1648.8718 | E137: =SUM(G122:J122) -> 1774.7824 | F137: =SUM(K122:N122) -> 1900.701 | G137: =SUM(O122:R122) -> 1974.709
A138: 毛利率 | B138: % | C138: =1-C137/C131 -> 0.43326489 | D138: =1-D137/D131 -> 0.84988537 | E138: =1-E137/E131 -> 0.88072471 | F138: =1-F137/F131 -> 0.87338769 | G138: =1-G137/G131 -> 0.87504034
A139: 營業費用 | B139: ¥B | D139: =SUM(C124:F124) -> 307.3638 | E139: =SUM(G124:J124) -> 301.13471 | F139: =SUM(K124:N124) -> 317.69107 | G139: =SUM(O124:R124) -> 342.35615
A140: 營業利益 | B140: ¥B | C140: =p1_op+p2_op+p3_op+p4_op -> 869 | D140: =SUM(C125:F125) -> 9027.8493 | E140: =SUM(G125:J125) -> 12803.799 | F140: =SUM(K125:N125) -> 12793.584 | G140: =SUM(O125:R125) -> 13485.706
A141: 營業利益率 | B141: % | C141: =C140/C131 -> 0.3717488 | D141: =D140/D131 -> 0.82190272 | E141: =E140/E131 -> 0.86048677 | F141: =F140/F131 -> 0.85222518 | G141: =G140/G131 -> 0.85337603
A142: 淨利 | B142: ¥B | C142: =a25_ni -> 554.5 | D142: =SUM(C127:F127) -> 6101.2733 | E142: =SUM(G127:J127) -> 8694.9256 | F142: =SUM(K127:N127) -> 8734.464 | G142: =SUM(O127:R127) -> 9251.8065
A143: 折舊攤銷 | B143: ¥B | D143: =da_y -> 320 | E143: =da_y -> 320 | F143: =da_y -> 320 | G143: =da_y -> 320
A144: 資本支出（含合資廠分攤） | B144: ¥B | D144: =cap_2026 -> 450 | E144: =cap_2027 -> 470 | F144: =cap_2028 -> 470 | G144: =cap_2029 -> 470
A145: 自由現金流（淨利＋折舊 − 資本支出） | B145: ¥B | D145: =D142+D143-D144 -> 5971.2733 | E145: =E142+E143-E144 -> 8544.9256 | F145: =F142+F143-F144 -> 8584.464 | G145: =G142+G143-G144 -> 9101.8065
A146: 股東回饋（以買回計） | B146: ¥B | D146: =MAX(0,payout*(SUM(D127:F127)+0.75*(D143-D144))) -> 1032.3147 | E146: =MAX(0,payout*E145) -> 1708.9851 | F146: =MAX(0,payout*F145) -> 1716.8928 | G146: =MAX(0,payout*G145) -> 1820.3613 | T146: FY2026 只計 2026-07 以後三季的自由現金流
A147: 期末權益 | B147: ¥B | C147: =eq25 -> 1399.1 | D147: =eq_j+SUM(D127:F127)-D146 -> 6631.0586 | E147: =D147+E142-E146 -> 13616.999 | F147: =E147+F142-F146 -> 20634.57 | G147: =F147+G142-G146 -> 28066.016 | T147: FY2026＝2026-06-30 權益＋第二至四季淨利 − 回饋（不含其他綜合損益）
...

Sheet Sources
A1: 來源
A2: Kioxia FY2026 第一季財報（2026-07-31；SGX 轉載） | B2: https://links.sgx.com/1.0.0/corporate-announcements/DOATO9EIE4EEQ2Y8/898078_Earnings-Release-FY2026-1Q-EN.pdf
A3: Kioxia：第二季財報 2026-10-30 18:45（JST）公布（公司新聞頁） | B3: https://www.kioxia-holdings.com/en-jp/news/2026.html
A4: storagenewsletter：Kioxia FY25 決算（營收 2,337.6、營業利益 870、淨利 554） | B4: https://www.storagenewsletter.com/?p=302700
A5: stockanalysis：季度損益、歷史股價、共識 | B5: https://stockanalysis.com/quote/tyo/285A/financials/?p=quarterly
A6: MarketScreener：Kioxia 預估與共識目標價 | B6: https://uk.marketscreener.com/quote/stock/KIOXIA-HOLDINGS-CORPORATI-180030735/finances/
A7: MarketScreener：SanDisk 預估（同業 P/B、P/E） | B7: https://uk.marketscreener.com/quote/stock/SANDISK-CORPORATION-182801077/finances/
A8: TrendForce：Kioxia FY26–28 資本支出（2026-06-03） | B8: https://www.trendforce.com/news/2026/06/03/news-kioxia-targets-%C2%A5470b-yearly-capex-in-fy26-28-up-66-from-fy25-reportedly-weighing-third-kitakami-fab-and-ma/
A9: newsquawk：一股分三股公告（2026-07-31） | B9: https://www.newsquawk.com/headlines/kioxia-285a-jt-q1-jpy-net-profit-84217bln-exp-9736bln-revenue-177tln-prev-3428bln-yy-announces-a-3-for-1-stock-split-and-announces-a-share-buyback
A10: stockanalysis：WDC 統計（Forward P/E） | B10: https://stockanalysis.com/stocks/wdc/statistics/
A11: 市場層：markets/nand/dist/20261031_NAND市場模型_v0.3.xlsx（markets/nand v0.1） | B11: 本 repo
A12: 美光十年倍數與淨利率（Analogy）：micron/dist/20261030_美光個股模型_v0.4.3.xlsx | B12: 本 repo
A13: SemiAnalysis | B13: 未使用
