Workbook

Sheet README
A1: Kioxia（285A JP）收支與估值模型 v0.1（AI 半導體 Project：記憶體——NAND） 2026-10-25
A2: 模型命題：Kioxia 是全球第三、四大 NAND 廠（2Q26 營收市占 13.6%），與 SanDisk 共用四日市、北上合資產能；盈餘由 NAND 合約價循環、AI 推論帶動的企業級 SSD 位元與日圓匯率決定。問題是 2026 年的高價能維持多久（FY2027 起三情境分歧），以及現價約 2.6 倍前瞻 P/E 是否已反映循環見頂。
A3: 重點觀察
A4: ="1. 加權目標價 ¥"&TEXT(Val!B49,"#,##0")&"，相對現價 ¥"&TEXT(px,"#,##0")&"（2026-10-23 收盤）"&TEXT(Val!B52,"+0.0%;−0.0%")&"。主因是現價的倍數低於同業：Kioxia 現價 ÷ 2028-03 共識每股淨值 1.63x，同業中位數 "&TEXT(Val!B32,"0.00")&"x（SanDisk 2.86x、美光 3.35x），Comparable ¥"&TEXT(Val!B34,"#,##0")&"（"&TEXT(Val!B53,"+0%;−0%")&"）；DCF ¥"&TEXT(Val!B24,"#,##0")&" 也高於現價，因現價只有 FY2027 EPS（A）的 "&TEXT(Val!B85,"0.0")&" 倍。股價 10-09 至 10-23 已跌 27%（17,505 → 12,755）。" -> 1. 加權目標價 ¥22,268，相對現價 ¥12,755（2026-10-23 收盤）+74.6%。主因是現價的倍數低於同業：Kioxia 現價 ÷ 2028-03 共識每股淨值 1.63x，同業中位數 2.10x（SanDisk 2.86x、美光 3.35x），Comparable ¥20,357（+60%）；DCF ¥24,180 也高於現價，因現價只有 FY2027 EPS（A）的 2.4 倍。股價 10-09 至 10-23 已跌 27%（17,505 → 12,755）。
A5: ="2. 本模型 FY2026 EPS（A）¥"&TEXT(PL!D10,"#,##0")&"，比共識 ¥3,486 "&TEXT(PL!D10/cons_eps26-1,"+0%;−0%")&"；上半年已由第一季實績與第二季指引鎖定（淨利 ¥2,112B）。追蹤：2026-10-30 第二季財報（實績 vs 指引 ¥2,390B／¥1,890B）與第三季指引。" -> 2. 本模型 FY2026 EPS（A）¥3,492，比共識 ¥3,486 +0%；上半年已由第一季實績與第二季指引鎖定（淨利 ¥2,112B）。追蹤：2026-10-30 第二季財報（實績 vs 指引 ¥2,390B／¥1,890B）與第三季指引。
A6: ="3. 營收以美元計、成本以日圓計：匯率 145／170 日圓使 FY2028 EPS（A）變動 "&TEXT(Sens!H9,"+0%;−0%")&"／"&TEXT(Sens!H10,"+0%;−0%")&"；2027 起季價 ±20% 為 "&TEXT(Sens!H5,"+0%;−0%")&"／"&TEXT(Sens!H6,"+0%;−0%")&"。情境 C 的 FY2029 毛利率降到 "&TEXT(PL!G26,"0%")&"。追蹤：TrendForce 每季初的 NAND 合約價、日圓匯率、SanDisk 2026-10-29 財報（合資群位元）。" -> 3. 營收以美元計、成本以日圓計：匯率 145／170 日圓使 FY2028 EPS（A）變動 −13%／+9%；2027 起季價 ±20% 為 −28%／+31%。情境 C 的 FY2029 毛利率降到 51%。追蹤：TrendForce 每季初的 NAND 合約價、日圓匯率、SanDisk 2026-10-29 財報（合資群位元）。
A7: ="投資建議："&Val!B55&"（依上檔空間固定規則；上檔空間："&TEXT(Val!B52,"+0.0%;−0.0%")&"，級距："&Val!B54&"）" -> 投資建議：強力買進（依上檔空間固定規則；上檔空間：+74.6%，級距：大於 50%）
A9: 驅動因子 → 推導量（因果方向：左邊決定右邊）
A10: Units｜markets/nand 成品：Kioxia 季度營收（市場營收 × 份額，美元；同字母情境）與位元（季度出貨 × 份額）
A11: PL 區塊｜營收＝市場層 × 公司口徑係數 × 匯率；營業成本＝位元 × 每 EB 成本（日圓；第二季以指引校準，之後每年 × (1 − 成本年降)）；營業費用＝固定＋變動
A12: PL 區塊｜淨利＝（營業利益＋業外＋淨現金收益）×（1 − 稅率）；自由現金流＝淨利＋折舊 − 資本支出（¥470B／年）；股東回饋＝20% × FCF（以買回計）→ 股數 → EPS、每股淨值
A13: Val｜第 0 節目標價＝DCF（FY2027–FY2032＋永續）與 Comparable（同業前瞻 P/B × 約 2028 年底每股淨值）各半；第 5–6 節目前倍數、十年倍數規則值（美光 Analogy）
A15: 會計年度：4 月到隔年 3 月（FY2026＝2026-04～2027-03 ≈ CY2026Q2–CY2027Q1）。前瞻 EPS 依月份調整：12 個月後（約 2027-10）的未來 12 月＝5／12 FY2027＋7／12 FY2028。每股數字為 2026-10-01 一股分三股後。
A16: 情境：A＝順利、B＝平平、C＝不如預期，讀 markets/nand 同字母（價格＝markets/memory NAND_S；顆數＝SCEN_UNITS；合資群份額年變動）；公司特有變數（每位元成本年降 14%／12%／10%，與 SanDisk 同值）A 最有利、C 最不利。FY2026 的 B、C 略高於 A：上游 B、C 價格路徑 2027Q1 漲幅較大。FY2030 起為收斂法，非驅動因子推導。
A17: 十年歷史不足：2024-12 上市，只有兩個年底；十年 P/B、P/E 與十年平均淨利率以美光為 Analogy，tp_roe 只用 FY2024–FY2025。本版未做先驗，無 Andy 合理 P/E 對照。

Sheet In
A1: In — 輸入（藍字；基準欄 E，低 D、高 F）。金額：十億日圓（¥B）；每股：日圓（2026-10-01 一股分三股後）；股數：百萬股。每個輸入附標記與來源；找不到者寫「未找到」
A2: 標記：Verified（公司文件、交易所資料）／Interested-party（寫明是誰、立場）／Analogy（寫明對照與差異）／Assumed（給低／高區間）／Derived（寫明換算）。SemiAnalysis 未使用
A3: 鍵 | B3: 項目 | C3: 單位 | D3: 低 | E3: 基準 | F3: 高 | G3: 標記 | H3: 來源1 | I3: 來源2／說明
A4: A. 季度實績與公司指引（¥B；EPS 日圓，分割後）
A5: p1_rev | B5: FY2025 第1季營收 | C5: ¥B | E5: 342.8 | G5: Verified | H5: Kioxia FY2026 第一季財報（2026-07-31；SGX 轉載 Earnings Release FY2026 1Q）https://links.sgx.com/1.0.0/corporate-announcements/DOATO9EIE4EEQ2Y8/898078_Earnings-Release-FY2026-1Q-EN.pdf（前期欄：營收 342.8、營業利益 44.9、淨利 18.3） | I5: 四季合計 2,337.6＝公司 FY2025 營收（storagenewsletter 轉載決算；MarketScreener 2,337.6）
A6: p1_gp | B6: FY2025 第1季毛利 | C6: ¥B | E6: 71.2 | G6: Interested-party | H6: stockanalysis 季度損益（TYO:285A；2026-10-25 讀取）
A7: p1_op | B7: FY2025 第1季營業利益 | C7: ¥B | E7: 44.9 | G7: Verified | H7: Kioxia FY2026 第一季財報（2026-07-31；SGX 轉載 Earnings Release FY2026 1Q）https://links.sgx.com/1.0.0/corporate-announcements/DOATO9EIE4EEQ2Y8/898078_Earnings-Release-FY2026-1Q-EN.pdf（前期欄：營收 342.8、營業利益 44.9、淨利 18.3） | I7: 四季合計 869.0（公司 870.4，取整差）
A8: p1_ni | B8: FY2025 第1季淨利 | C8: ¥B | E8: 18.3 | G8: Verified | H8: Kioxia FY2026 第一季財報（2026-07-31；SGX 轉載 Earnings Release FY2026 1Q）https://links.sgx.com/1.0.0/corporate-announcements/DOATO9EIE4EEQ2Y8/898078_Earnings-Release-FY2026-1Q-EN.pdf（前期欄：營收 342.8、營業利益 44.9、淨利 18.3） | I8: 四季合計 554.5（公司 554.5）
A9: p2_rev | B9: FY2025 第2季營收 | C9: ¥B | E9: 448.3 | G9: Interested-party | H9: stockanalysis 季度損益（TYO:285A；2026-10-25 讀取） | I9: 四季合計 2,337.6＝公司 FY2025 營收（storagenewsletter 轉載決算；MarketScreener 2,337.6）
A10: p2_gp | B10: FY2025 第2季毛利 | C10: ¥B | E10: 122.1 | G10: Interested-party | H10: stockanalysis 季度損益（TYO:285A；2026-10-25 讀取）
A11: p2_op | B11: FY2025 第2季營業利益 | C11: ¥B | E11: 85.9 | G11: Interested-party | H11: stockanalysis 季度損益（TYO:285A；2026-10-25 讀取） | I11: 四季合計 869.0（公司 870.4，取整差）
A12: p2_ni | B12: FY2025 第2季淨利 | C12: ¥B | E12: 40.7 | G12: Interested-party | H12: stockanalysis 季度損益（TYO:285A；2026-10-25 讀取） | I12: 四季合計 554.5（公司 554.5）
A13: p3_rev | B13: FY2025 第3季營收 | C13: ¥B | E13: 543.6 | G13: Interested-party | H13: stockanalysis 季度損益（TYO:285A；2026-10-25 讀取） | I13: 四季合計 2,337.6＝公司 FY2025 營收（storagenewsletter 轉載決算；MarketScreener 2,337.6）
A14: p3_gp | B14: FY2025 第3季毛利 | C14: ¥B | E14: 176.6 | G14: Interested-party | H14: stockanalysis 季度損益（TYO:285A；2026-10-25 讀取）
A15: p3_op | B15: FY2025 第3季營業利益 | C15: ¥B | E15: 142.8 | G15: Interested-party | H15: stockanalysis 季度損益（TYO:285A；2026-10-25 讀取） | I15: 四季合計 869.0（公司 870.4，取整差）
A16: p3_ni | B16: FY2025 第3季淨利 | C16: ¥B | E16: 87.8 | G16: Interested-party | H16: stockanalysis 季度損益（TYO:285A；2026-10-25 讀取） | I16: 四季合計 554.5（公司 554.5）
A17: p4_rev | B17: FY2025 第4季營收 | C17: ¥B | E17: 1002.9 | G17: Interested-party | H17: stockanalysis 季度損益（TYO:285A；2026-10-25 讀取） | I17: 四季合計 2,337.6＝公司 FY2025 營收（storagenewsletter 轉載決算；MarketScreener 2,337.6）
A18: p4_gp | B18: FY2025 第4季毛利 | C18: ¥B | E18: 642.9 | G18: Interested-party | H18: stockanalysis 季度損益（TYO:285A；2026-10-25 讀取）
A19: p4_op | B19: FY2025 第4季營業利益 | C19: ¥B | E19: 595.4 | G19: Interested-party | H19: stockanalysis 季度損益（TYO:285A；2026-10-25 讀取） | I19: 四季合計 869.0（公司 870.4，取整差）
A20: p4_ni | B20: FY2025 第4季淨利 | C20: ¥B | E20: 407.7 | G20: Interested-party | H20: stockanalysis 季度損益（TYO:285A；2026-10-25 讀取） | I20: 四季合計 554.5（公司 554.5）
A21: q1_rev | B21: FY2026 第一季營收（2026-04～06） | C21: ¥B | E21: 1767.1 | G21: Verified | H21: Kioxia FY2026 第一季財報（2026-07-31；SGX 轉載 Earnings Release FY2026 1Q）https://links.sgx.com/1.0.0/corporate-announcements/DOATO9EIE4EEQ2Y8/898078_Earnings-Release-FY2026-1Q-EN.pdf | I21: SSD 與儲存 1,174.7、智慧裝置 525.7、其他 66.7；平均匯率 160 日圓
A22: q1_gp | B22: FY2026 第一季毛利 | C22: ¥B | E22: 1380.1 | G22: Interested-party | H22: stockanalysis 季度損益（TYO:285A；2026-10-25 讀取）：1,380,066 百萬日圓 | I22: 財報摘要未列毛利
A23: q1_op | B23: FY2026 第一季營業利益 | C23: ¥B | E23: 1270 | G23: Verified | H23: Kioxia FY2026 第一季財報（2026-07-31；SGX 轉載 Earnings Release FY2026 1Q）https://links.sgx.com/1.0.0/corporate-announcements/DOATO9EIE4EEQ2Y8/898078_Earnings-Release-FY2026-1Q-EN.pdf | I23: 含訴訟損失準備 36.6、股份報酬 19.4（non-GAAP 加回）
A24: q1_ni | B24: FY2026 第一季淨利（歸屬母公司） | C24: ¥B | E24: 842.2 | G24: Verified | H24: Kioxia FY2026 第一季財報（2026-07-31；SGX 轉載 Earnings Release FY2026 1Q）https://links.sgx.com/1.0.0/corporate-announcements/DOATO9EIE4EEQ2Y8/898078_Earnings-Release-FY2026-1Q-EN.pdf
A25: q1_eps | B25: FY2026 第一季基本 EPS（分割後） | C25: JPY | E25: =1539.91/3 -> 513.30333 | G25: Derived | H25: Kioxia FY2026 第一季財報（2026-07-31；SGX 轉載 Earnings Release FY2026 1Q）https://links.sgx.com/1.0.0/corporate-announcements/DOATO9EIE4EEQ2Y8/898078_Earnings-Release-FY2026-1Q-EN.pdf：基本 EPS ¥1,539.91（分割前）÷ 3 | I25: 2026-10-01 一股分三股（2026-07-31 董事會）
A26: g2_rev | B26: 公司指引：FY2026 第二季（2026-07～09）營收 | C26: ¥B | E26: 2390 | G26: Interested-party | H26: Kioxia FY2026 第一季財報（2026-07-31；SGX 轉載 Earnings Release FY2026 1Q）https://links.sgx.com/1.0.0/corporate-announcements/DOATO9EIE4EEQ2Y8/898078_Earnings-Release-FY2026-1Q-EN.pdf：¥2,390.0B（假設 1 美元＝162 日圓） | I26: 公司不提供全年計畫（立場：公司）
A27: g2_op | B27: 公司指引：FY2026 第二季營業利益 | C27: ¥B | E27: 1890 | G27: Interested-party | H27: Kioxia FY2026 第一季財報（2026-07-31；SGX 轉載 Earnings Release FY2026 1Q）https://links.sgx.com/1.0.0/corporate-announcements/DOATO9EIE4EEQ2Y8/898078_Earnings-Release-FY2026-1Q-EN.pdf：¥1,890.0B（non-GAAP 1,900.0）
A28: g2_ni | B28: 公司指引：FY2026 第二季淨利 | C28: ¥B | E28: 1270 | G28: Interested-party | H28: Kioxia FY2026 第一季財報（2026-07-31；SGX 轉載 Earnings Release FY2026 1Q）https://links.sgx.com/1.0.0/corporate-announcements/DOATO9EIE4EEQ2Y8/898078_Earnings-Release-FY2026-1Q-EN.pdf：¥1,270.0B；基本 EPS ¥2,317.46（分割前）
A29: g2_ox | B29: FY2026 第二季營業費用（推估；校準用） | C29: ¥B | D29: 55 | E29: 70 | F29: 90 | G29: Assumed | H29: 第一季毛利 − 營業利益＝110.1（含一次性 56.0）；第二季 GAAP 與 non-GAAP 營業利益差 10 | I29: 第二季營業成本＝營收 − 營業利益 − 本值（Derived），用於校準每 EB 成本
A30: a25_rev | B30: FY2025 營收（2025-04～2026-03） | C30: ¥B | E30: =p1_rev+p2_rev+p3_rev+p4_rev -> 2337.6 | G30: Derived | H30: 四季合計 | I30: 公司 2,337.6（storagenewsletter 轉載 FY25 決算，+37%）
A31: a25_ni | B31: FY2025 淨利 | C31: ¥B | E31: =p1_ni+p2_ni+p3_ni+p4_ni -> 554.5 | G31: Derived | H31: 四季合計 | I31: 公司 554.0（storagenewsletter）、MarketScreener 554.5
A32: a25_eps | B32: FY2025 EPS（分割後） | C32: JPY | E32: 341.4 | G32: Interested-party | H32: MarketScreener 預估頁（2026-10-25 擷取；頁面為 10-16 收盤；會計年度 3 月；每股數字已依分割調整，股數 1,644 百萬股）：341.4 | I32: ≈ 554.5 ÷ 平均約 1,624 百萬股（分割後，Derived）
A33: kx_k | B33: 公司營收 ÷ 市場層 Kioxia 營收（TrendForce 口徑 × 匯率） | C33: x | E33: =q1_rev/160/Units!H4 -> 1.0302589 | G33: Derived | H33: 第一季營收 ÷ 平均匯率 160 ÷ 市場層 2026Q2 Kioxia 營收（Units 頁） | I33: 公司營收含其他（¥66.7B）
A34: B. 成本、費用、稅、匯率（公司特有；隨情境者 A 最有利、C 最不利）
A35: cd_A | B35: 情境 A：每位元成本年降 | C35: % | D35: 0.1 | E35: 0.14 | F35: 0.18 | G35: Assumed | H35: A：BiCS10（332 層，北上 K2）FY2026 量產、密度約 +59% | I35: 與 sndk/ 同值（同一合資晶圓廠與 BiCS 世代）；以第二季指引校準的單位成本為起點
A36: cd_B | B36: 情境 B：每位元成本年降 | C36: % | D36: 0.08 | E36: 0.12 | F36: 0.16 | G36: Assumed | H36: B：轉換略延後 | I36: 同上
A37: cd_C | B37: 情境 C：每位元成本年降 | C37: % | D37: 0.06 | E37: 0.1 | F37: 0.14 | G37: Assumed | H37: C：需求轉弱、稼動率下降 | I37: 同上
A38: fx | B38: 匯率（FY2026 第三季起） | C38: ¥／$ | D38: 145 | E38: 160 | F38: 170 | G38: Assumed | H38: 第一季平均 160、第二季指引假設 162 | I38: 營收以美元計價（TrendForce 口徑 × 匯率）；成本以日圓計，不隨匯率
A39: ox_var | B39: 營業費用變動率（÷ 營收） | C39: % | D39: 0.005 | E39: 0.01 | F39: 0.02 | G39: Assumed | H39: FY2025 營業費用（毛利 − 營業利益）143.8 ÷ 營收 2,337.6 ≈ 6%，多為固定 | I39: 固定部分＝第二季營業費用 − 變動率 × 第二季營收（Derived）
A40: ox_g | B40: 營業費用固定部分年增 | C40: % | D40: 0.05 | E40: 0.1 | F40: 0.15 | G40: Assumed | H40: 研發（BiCS10、CBA）與人事
A41: nonop_q | B41: 每季業外淨額（利息、匯兌等；FY2026 第三季起） | C41: ¥B | D41: -40 | E41: -15 | F41: 0 | G41: Assumed | H41: Kioxia FY2026 第一季財報（2026-07-31；SGX 轉載 Earnings Release FY2026 1Q）https://links.sgx.com/1.0.0/corporate-announcements/DOATO9EIE4EEQ2Y8/898078_Earnings-Release-FY2026-1Q-EN.pdf：第一季稅前 − 營業利益＝−35.3；第二季指引 −20.0 | I41: 2026 年第一季已提前償還長期借款 ¥433.2B
A42: tax | B42: 有效稅率 | C42: % | D42: 0.28 | E42: 0.32 | F42: 0.35 | G42: Derived | H42: Kioxia FY2026 第一季財報（2026-07-31；SGX 轉載 Earnings Release FY2026 1Q）https://links.sgx.com/1.0.0/corporate-announcements/DOATO9EIE4EEQ2Y8/898078_Earnings-Release-FY2026-1Q-EN.pdf：第一季淨利 842.2 ÷ 稅前 1,234.7 → 稅率 31.8%；第二季指引 1,270 ÷ 1,870 → 32.1%
A43: rf | B43: 淨現金收益率 | C43: % | D43: 0 | E43: 0.01 | F43: 0.02 | G43: Assumed | H43: 日圓利率
A44: C. 資本、股東回饋（2026-06-30 資產負債表；股數為分割後）
A45: eq_j | B45: 2026-06-30 股東權益（歸屬母公司） | C45: ¥B | E45: 2404.3 | G45: Verified | H45: Kioxia FY2026 第一季財報（2026-07-31；SGX 轉載 Earnings Release FY2026 1Q）https://links.sgx.com/1.0.0/corporate-announcements/DOATO9EIE4EEQ2Y8/898078_Earnings-Release-FY2026-1Q-EN.pdf | I45: 2026-03-31 為 1,399.1
A46: nc_j | B46: 2026-06-30 淨現金（現金 − 公司債與借款；不含租賃負債） | C46: ¥B | E46: =791-634.6 -> 156.4 | G46: Derived | H46: Kioxia FY2026 第一季財報（2026-07-31；SGX 轉載 Earnings Release FY2026 1Q）https://links.sgx.com/1.0.0/corporate-announcements/DOATO9EIE4EEQ2Y8/898078_Earnings-Release-FY2026-1Q-EN.pdf：現金 791.0、公司債與借款 634.6（另有租賃負債 203.3）
A47: eq25 | B47: FY2025 年底（2026-03-31）股東權益 | C47: ¥B | E47: 1399.1 | G47: Verified | H47: Kioxia FY2026 第一季財報（2026-07-31；SGX 轉載 Earnings Release FY2026 1Q）https://links.sgx.com/1.0.0/corporate-announcements/DOATO9EIE4EEQ2Y8/898078_Earnings-Release-FY2026-1Q-EN.pdf
A48: sh0 | B48: 流通股數（分割後） | C48: 百萬股 | E48: =548.014638*3 -> 1644.0439 | G48: Derived | H48: Kioxia FY2026 第一季財報（2026-07-31；SGX 轉載 Earnings Release FY2026 1Q）https://links.sgx.com/1.0.0/corporate-announcements/DOATO9EIE4EEQ2Y8/898078_Earnings-Release-FY2026-1Q-EN.pdf：2026-06-30 發行 548,015,088 股、庫藏 450 股；× 3（2026-10-01 分割） | I48: MarketScreener 1,644.0 百萬股
A49: dil | B49: 稀釋股數 − 流通股數 | C49: 百萬股 | E49: =sh0*(1539.91/1525.09-1) -> 15.97593 | G49: Derived | H49: Kioxia FY2026 第一季財報（2026-07-31；SGX 轉載 Earnings Release FY2026 1Q）https://links.sgx.com/1.0.0/corporate-announcements/DOATO9EIE4EEQ2Y8/898078_Earnings-Release-FY2026-1Q-EN.pdf：基本 EPS 1,539.91 ÷ 稀釋 1,525.09 | I49: 各年固定
A50: da_y | B50: 折舊攤銷（年） | C50: ¥B | D50: 280 | E50: 320 | F50: 380 | G50: Assumed | H50: Kioxia FY2026 第一季財報（2026-07-31；SGX 轉載 Earnings Release FY2026 1Q）https://links.sgx.com/1.0.0/corporate-announcements/DOATO9EIE4EEQ2Y8/898078_Earnings-Release-FY2026-1Q-EN.pdf：第一季 76.1（× 4 ≈ 304） | I50: 新廠（北上 K2）投產後增加
A51: cap_2026 | B51: 資本支出 FY2026 | C51: ¥B | D51: 400 | E51: 450 | F51: 500 | G51: Interested-party | H51: TrendForce 2026-06-03：FY2026 ¥450B、FY2026–28 年均 ¥470B（較 FY2025 ¥283.7B +66%） | I51: 含合資廠 Kioxia 分攤；SanDisk 分攤另計於 sndk/
A52: cap_2027 | B52: 資本支出 FY2027 | C52: ¥B | D52: 400 | E52: 470 | F52: 550 | G52: Interested-party | H52: 同上 | I52: 含合資廠 Kioxia 分攤；SanDisk 分攤另計於 sndk/
A53: cap_2028 | B53: 資本支出 FY2028 | C53: ¥B | D53: 400 | E53: 470 | F53: 550 | G53: Interested-party | H53: 同上 | I53: 含合資廠 Kioxia 分攤；SanDisk 分攤另計於 sndk/
A54: cap_2029 | B54: 資本支出 FY2029 | C54: ¥B | D54: 350 | E54: 470 | F54: 550 | G54: Interested-party | H54: Assumed：延續 FY2026–28 年均 | I54: 含合資廠 Kioxia 分攤；SanDisk 分攤另計於 sndk/
A55: payout | B55: 股東回饋（股利＋買回）÷ 自由現金流 | C55: % | D55: 0 | E55: 0.2 | F55: 0.5 | G55: Assumed | H55: FY2025 無股利；MarketScreener 共識 FY2026 每股股利 ¥266（Interested-party） | I55: 以買回計（股數減少）
A56: px | B56: 股價（2026-10-23 收盤） | C56: JPY | E56: 12755 | G56: Verified | H56: stockanalysis 歷史股價（TYO:285A，2026-10-23 收盤 ¥12,755；分割後） | I56: MarketScreener 2026-10-16 收盤 ¥13,375（同一序列）；10-01 為 ¥19,100
A57: bb_px | B57: 未來買回均價 | C57: JPY | E57: =px -> 12755 | G57: Assumed | H57: ＝現價
A58: D. 共識與對帳參考（只放 Recon，不作校準）
A59: cons_rev26 | B59: 共識營收 FY2026（2027-03） | C59: ¥B | D59: 9100 | E59: 10071.4 | F59: 11400 | G59: Interested-party | H59: MarketScreener 預估頁（2026-10-25 擷取；頁面為 10-16 收盤；會計年度 3 月；每股數字已依分割調整，股數 1,644 百萬股）：10,071,396 百萬日圓 | I59: stockanalysis（15 位）平均 10.1 兆、區間 9.1–11.4 兆
A60: cons_rev27 | B60: 共識營收 FY2027（2028-03） | C60: ¥B | E60: 13477.2 | G60: Interested-party | H60: MarketScreener 預估頁（2026-10-25 擷取；頁面為 10-16 收盤；會計年度 3 月；每股數字已依分割調整，股數 1,644 百萬股）
A61: cons_ni26 | B61: 共識淨利 FY2026 | C61: ¥B | E61: 5573.9 | G61: Interested-party | H61: MarketScreener 預估頁（2026-10-25 擷取；頁面為 10-16 收盤；會計年度 3 月；每股數字已依分割調整，股數 1,644 百萬股）
A62: cons_ni27 | B62: 共識淨利 FY2027 | C62: ¥B | E62: 7730 | G62: Interested-party | H62: MarketScreener 預估頁（2026-10-25 擷取；頁面為 10-16 收盤；會計年度 3 月；每股數字已依分割調整，股數 1,644 百萬股）
A63: cons_eps26 | B63: 共識 EPS FY2026 | C63: JPY | E63: 3486 | G63: Interested-party | H63: MarketScreener 預估頁（2026-10-25 擷取；頁面為 10-16 收盤；會計年度 3 月；每股數字已依分割調整，股數 1,644 百萬股）
A64: cons_eps27 | B64: 共識 EPS FY2027 | C64: JPY | E64: 4871 | G64: Interested-party | H64: MarketScreener 預估頁（2026-10-25 擷取；頁面為 10-16 收盤；會計年度 3 月；每股數字已依分割調整，股數 1,644 百萬股）
A65: cons_eps28 | B65: 共識 EPS FY2028 | C65: JPY | E65: 5467 | G65: Interested-party | H65: MarketScreener 預估頁（2026-10-25 擷取；頁面為 10-16 收盤；會計年度 3 月；每股數字已依分割調整，股數 1,644 百萬股）
A66: cons_bv26 | B66: 共識每股淨值 FY2026 年底（2027-03） | C66: JPY | E66: 3830 | G66: Interested-party | H66: MarketScreener 預估頁（2026-10-25 擷取；頁面為 10-16 收盤；會計年度 3 月；每股數字已依分割調整，股數 1,644 百萬股）
A67: cons_bv27 | B67: 共識每股淨值 FY2027 年底（2028-03） | C67: JPY | E67: 7808 | G67: Interested-party | H67: MarketScreener 預估頁（2026-10-25 擷取；頁面為 10-16 收盤；會計年度 3 月；每股數字已依分割調整，股數 1,644 百萬股）
A68: cons_bv28 | B68: 共識每股淨值 FY2028 年底（2029-03） | C68: JPY | E68: 11928 | G68: Interested-party | H68: MarketScreener 預估頁（2026-10-25 擷取；頁面為 10-16 收盤；會計年度 3 月；每股數字已依分割調整，股數 1,644 百萬股）
A69: E. 目標價參數（黃底；Val 頁第 0 節 DCF＋Comparable 與收斂法用；Assumed 者 Andy 可改）
A70: tp_wA | B70: 目標價情境權重 A（A 順利／B 平平／C 不如預期） | C70: % | E70: 0.3 | G70: Assumed | H70: Andy 可改（工作單 2026-10-25 預設 A 0.3／B 0.5／C 0.2） | I70: 三者合計應為 100%
A71: tp_wB | B71: 目標價情境權重 B（A 順利／B 平平／C 不如預期） | C71: % | E71: 0.5 | G71: Assumed | H71: Andy 可改（工作單 2026-10-25 預設 A 0.3／B 0.5／C 0.2） | I71: 三者合計應為 100%
A72: tp_wC | B72: 目標價情境權重 C（A 順利／B 平平／C 不如預期） | C72: % | E72: 0.2 | G72: Assumed | H72: Andy 可改（工作單 2026-10-25 預設 A 0.3／B 0.5／C 0.2） | I72: 三者合計應為 100%
A73: tp_r | B73: 折現率（股東權益要求報酬；美、台、日、韓同一值） | C73: % | E73: 0.1 | G73: Assumed | H73: Andy 可改（工作單預設 10%） | I73: 日本利率較低，但依工作單不改值
A74: tp_g | B74: 長期成長率（永續；收斂法 B 的 FY2032 營收年增） | C74: % | E74: 0.04 | G74: Assumed | H74: Andy 可改（工作單預設 4%）
A75: tp_roe | B75: ROE（近年平均；FY2024–FY2025，上市不足三年） | C75: % | E75: =AVERAGE(272.3/737.1,554.5/1399.1) -> 0.38287346 | G75: Derived | H75: FY2024（2025-03）淨利 272.3 ÷ 權益 737.1（MarketScreener 每股淨值 455.8 × 1,617.2 百萬股，Derived）；FY2025 554.5 ÷ 1,399.1（公司） | I75: 2024-12 上市；FY2023 權益未找到，只用兩年
A76: tp_w_dcf | B76: 目標價中 DCF 的權重；其餘為 Comparable | C76: % | E76: 0.5 | G76: Assumed | H76: Andy 可改（2026-10-25 11:53：DCF／Comparable 各半）
A77: nim10 | B77: 十年平均淨利率（Analogy：美光 FY2016–FY2025） | C77: % | E77: 0.14662864 | G77: Analogy | H77: micron/dist/20261025_美光模型_v0.4.xlsx｜In!E244 | I77: Kioxia 2024-12 上市，2018 年以前為東芝記憶體事業，十年連續的獨立財報未找到；以同為記憶體循環股的美光十年平均代替（與 sndk/ 同值）
A78: cyc_mA | B78: 循環中段係數：情境 A 淨利率收斂目標 ÷ 十年平均 | C78: x | E78: 1.2 | G78: Assumed | H78: 記憶體樣板預設 1.2 | I78: Andy 可改
A79: cyc_mC | B79: 循環中段係數：情境 C 淨利率收斂目標 ÷ 十年平均 | C79: x | E79: 0.8 | G79: Assumed | H79: 記憶體樣板預設 0.8 | I79: Andy 可改
A80: fade_mA | B80: 情境 A：FY2032 淨利率收斂目標（循環中段：十年平均 × cyc_mA） | C80: % | E80: =nim10*cyc_mA -> 0.17595436 | G80: Derived | H80: 主串指示：循環產業 FY2030 後收斂用十年平均（記憶體樣板的循環中段） | I80: FY2030 起由 FY2029 淨利率線性收斂，FY2032 達到
A81: fade_mB | B81: 情境 B：FY2032 淨利率收斂目標（循環中段：＝十年平均） | C81: % | E81: =nim10 -> 0.14662864 | G81: Derived | H81: 主串指示：循環產業 FY2030 後收斂用十年平均（記憶體樣板的循環中段） | I81: FY2030 起由 FY2029 淨利率線性收斂，FY2032 達到
A82: fade_mC | B82: 情境 C：FY2032 淨利率收斂目標（循環中段：十年平均 × cyc_mC） | C82: % | E82: =nim10*cyc_mC -> 0.11730291 | G82: Derived | H82: 主串指示：循環產業 FY2030 後收斂用十年平均（記憶體樣板的循環中段） | I82: FY2030 起由 FY2029 淨利率線性收斂，FY2032 達到
A83: fade_gA | B83: 情境 A：FY2032 營收年增收斂目標（tp_g＋2pt） | C83: % | E83: =tp_g+0.02 -> 0.06 | G83: Assumed | H83: 工作單 2026-10-25 11:20 收斂法 | I83: FY2030 起由 FY2029 年增線性收斂
A84: fade_gB | B84: 情境 B：FY2032 營收年增收斂目標（＝tp_g） | C84: % | E84: =tp_g -> 0.04 | G84: Assumed | H84: 工作單 2026-10-25 11:20 收斂法 | I84: FY2030 起由 FY2029 年增線性收斂
A85: fade_gC | B85: 情境 C：FY2032 營收年增收斂目標（tp_g−2pt） | C85: % | E85: =tp_g-0.02 -> 0.02 | G85: Assumed | H85: 工作單 2026-10-25 11:20 收斂法 | I85: FY2030 起由 FY2029 年增線性收斂
A86: cons_tp | B86: 市場共識目標價（賣方平均；低／高＝最低／最高） | C86: JPY | D86: 16333.33 | E86: 36929.23 | F86: 66666.67 | G86: Interested-party | H86: MarketScreener 共識頁（16 位，2026-10-25 擷取，頁面收盤日 10-16）：平均 ¥36,929（分割後） | I86: stockanalysis（16 位，2026-09-09）：平均 ¥111,256（分割前）÷ 3 ＝ ¥37,085

Sheet Q
A1: Q — 季度實績（¥B）與公司指引。會計年度 4–3 月；第一季＝4–6 月
A3: 項目 | B3: FY2025 第一季 | C3: FY2025 第二季 | D3: FY2025 第三季 | E3: FY2025 第四季 | F3: FY2025 | G3: FY2026 第一季 | H3: FY2026 第二季（指引） | I3: 標記 | J3: 來源
A4: 營收 | B4: =p1_rev -> 342.8 | C4: =p2_rev -> 448.3 | D4: =p3_rev -> 543.6 | E4: =p4_rev -> 1002.9 | F4: =SUM(B4:E4) -> 2337.6 | G4: =q1_rev -> 1767.1 | H4: =g2_rev -> 2390 | I4: Verified／Interested-party | J4: 公司財報（第一季前期欄）；stockanalysis 季度表；第二季為公司指引
A5: 毛利 | B5: =p1_gp -> 71.2 | C5: =p2_gp -> 122.1 | D5: =p3_gp -> 176.6 | E5: =p4_gp -> 642.9 | F5: =SUM(B5:E5) -> 1012.8 | G5: =q1_gp -> 1380.1 | I5: Verified／Interested-party | J5: 公司財報（第一季前期欄）；stockanalysis 季度表；第二季為公司指引
A6: 營業利益 | B6: =p1_op -> 44.9 | C6: =p2_op -> 85.9 | D6: =p3_op -> 142.8 | E6: =p4_op -> 595.4 | F6: =SUM(B6:E6) -> 869 | G6: =q1_op -> 1270 | H6: =g2_op -> 1890 | I6: Verified／Interested-party | J6: 公司財報（第一季前期欄）；stockanalysis 季度表；第二季為公司指引
A7: 淨利 | B7: =p1_ni -> 18.3 | C7: =p2_ni -> 40.7 | D7: =p3_ni -> 87.8 | E7: =p4_ni -> 407.7 | F7: =SUM(B7:E7) -> 554.5 | G7: =q1_ni -> 842.2 | H7: =g2_ni -> 1270 | I7: Verified／Interested-party | J7: 公司財報（第一季前期欄）；stockanalysis 季度表；第二季為公司指引
A8: 毛利率 | B8: =B5/B4 -> 0.20770128 | C8: =C5/C4 -> 0.27236226 | D8: =D5/D4 -> 0.32487123 | E8: =E5/E4 -> 0.64104098 | F8: =F5/F4 -> 0.43326489 | G8: =G5/G4 -> 0.78099711
A9: 營業利益率 | B9: =B6/B4 -> 0.13098016 | C9: =C6/C4 -> 0.19161276 | D9: =D6/D4 -> 0.26269316 | E9: =E6/E4 -> 0.59367833 | F9: =F6/F4 -> 0.3717488 | G9: =G6/G4 -> 0.71869164 | H9: =H6/H4 -> 0.79079498
A10: 季增：營收 | C10: =C4/B4-1 -> 0.30775963 | D10: =D4/C4-1 -> 0.21258086 | E10: =E4/D4-1 -> 0.84492274 | G10: =G4/E4-1 -> 0.76199023 | H10: =H4/G4-1 -> 0.35249844
A12: FY2026 第二季（2026-07～09）財報 2026-10-30 公布（公司公告）；本版 FY2026 第二季＝公司指引（固定），第三季起＝市場層推導

Sheet Units
A1: Units — 市場層 markets/nand 成品的 Kioxia 季度營收與位元（三情境；唯讀抄錄，藍字）。來源：markets/nand/dist/20261025_NAND市場模型_v0.1.xlsx
A2: C..Z＝CY2025Q1..CY2030Q4；營收為 TrendForce 口徑（$B，美元），位元為季度出貨 × 營收份額（EB）。合資群份額＝Kioxia＋SanDisk（與 sndk/ 模型讀同一列）
A3: 項目 | B3: 單位 | C3: 2025Q1 | D3: 2025Q2 | E3: 2025Q3 | F3: 2025Q4 | G3: 2026Q1 | H3: 2026Q2 | I3: 2026Q3 | J3: 2026Q4 | K3: 2027Q1 | L3: 2027Q2 | M3: 2027Q3 | N3: 2027Q4 | O3: 2028Q1 | P3: 2028Q2 | Q3: 2028Q3 | R3: 2028Q4 | S3: 2029Q1 | T3: 2029Q2 | U3: 2029Q3 | V3: 2029Q4 | W3: 2030Q1 | X3: 2030Q2 | Y3: 2030Q3 | Z3: 2030Q4 | AA3: 來源
A4: Kioxia 營收（情境 A） | B4: $B | C4: 1.92 | D4: 2.14 | E4: 2.84 | F4: 3.31 | G4: 5.96 | H4: 10.72 | I4: 14.319786 | J4: 17.646994 | K4: 19.444827 | L4: 20.560401 | M4: 20.652979 | N4: 20.309216 | O4: 20.400662 | P4: 20.49252 | Q4: 20.584792 | R4: 20.677479 | S4: 20.849997 | T4: 21.235847 | U4: 21.628838 | V4: 22.029101 | W4: 21.540765 | X4: 21.5582 | Y4: 21.57565 | Z4: 21.593113 | AA4: markets/nand/dist/20261025_NAND市場模型_v0.1.xlsx｜Mkt!C43:Z43
A5: Kioxia 營收（情境 B） | B5: $B | C5: 1.92 | D5: 2.14 | E5: 2.84 | F5: 3.31 | G5: 5.96 | H5: 10.72 | I5: 14.319786 | J5: 17.646994 | K5: 19.595468 | L5: 21.134079 | M5: 20.111911 | N5: 17.012605 | O5: 11.827513 | P5: 9.1858457 | Q5: 7.6098059 | R5: 7.0921929 | S5: 7.845464 | T5: 8.6321407 | U5: 9.3167901 | V5: 10.055742 | W5: 9.7210303 | X5: 9.7192853 | Y5: 9.7175405 | Z5: 9.7157961 | AA5: markets/nand/dist/20261025_NAND市場模型_v0.1.xlsx｜Mkt!C91:Z91
A6: Kioxia 營收（情境 C） | B6: $B | C6: 1.92 | D6: 2.14 | E6: 2.84 | F6: 3.31 | G6: 5.96 | H6: 10.72 | I6: 14.319786 | J6: 17.646994 | K6: 19.36854 | L6: 20.889333 | M6: 19.879002 | N6: 16.815588 | O6: 9.8959399 | P6: 6.4479488 | Q6: 4.8476808 | R6: 3.8875427 | S6: 4.1303339 | T6: 4.4945496 | U6: 5.0306216 | V6: 5.7349027 | W6: 5.5313594 | X6: 5.5184177 | Y6: 5.5055063 | Z6: 5.492625 | AA6: markets/nand/dist/20261025_NAND市場模型_v0.1.xlsx｜Mkt!C139:Z139
A7: Kioxia 位元（情境 A） | B7: EB | C7: 35.545444 | D7: 33.356174 | E7: 38.303462 | F7: 36.611793 | G7: 38.133315 | H7: 40.175758 | I7: 46.666796 | J7: 48.944548 | K7: 52.360098 | L7: 55.364063 | M7: 58.540369 | N7: 61.898904 | O7: 65.450123 | P7: 69.205079 | Q7: 73.175462 | R7: 77.37363 | S7: 80.432143 | T7: 84.454249 | U7: 88.677485 | V7: 93.111909 | W7: 94.004556 | X7: 97.135866 | Y7: 100.37148 | Z7: 103.71487 | AA7: markets/nand/dist/20261025_NAND市場模型_v0.1.xlsx｜Mkt!C47:Z47
A8: Kioxia 位元（情境 B） | B8: EB | C8: 35.545444 | D8: 33.356174 | E8: 38.303462 | F8: 36.611793 | G8: 38.133315 | H8: 40.175758 | I8: 46.666796 | J8: 48.944548 | K8: 51.760676 | L8: 54.730251 | M8: 57.870195 | N8: 61.190281 | O8: 60.772488 | P8: 62.93199 | Q8: 65.168228 | R8: 67.483929 | S8: 71.096653 | T8: 74.500593 | U8: 78.067507 | V8: 81.805196 | W8: 81.650416 | X8: 84.286839 | Y8: 87.008389 | Z8: 89.817816 | AA8: markets/nand/dist/20261025_NAND市場模型_v0.1.xlsx｜Mkt!C95:Z95
A9: Kioxia 位元（情境 C） | B9: EB | C9: 35.545444 | D9: 33.356174 | E9: 38.303462 | F9: 36.611793 | G9: 38.133315 | H9: 40.175758 | I9: 46.666796 | J9: 48.944548 | K9: 51.161254 | L9: 54.096439 | M9: 57.200021 | N9: 60.481658 | O9: 54.758976 | P9: 54.891675 | Q9: 55.024697 | R9: 55.15804 | S9: 58.602861 | T9: 60.733812 | U9: 62.942249 | V9: 65.23099 | W9: 64.958969 | X9: 66.911559 | Y9: 68.922841 | Z9: 70.994581 | AA9: markets/nand/dist/20261025_NAND市場模型_v0.1.xlsx｜Mkt!C143:Z143
A10: Kioxia＋SanDisk 合資群份額（情境 A） | B10: % | C10: 0.27907731 | D10: 0.25560769 | E10: 0.27406433 | F10: 0.2689697 | G10: 0.27096015 | H10: 0.25018083 | I10: 0.26205287 | J10: 0.26205287 | K10: 0.26205287 | L10: 0.26205287 | M10: 0.26205287 | N10: 0.26205287 | O10: 0.26205287 | P10: 0.26205287 | Q10: 0.26205287 | R10: 0.26205287 | S10: 0.26205287 | T10: 0.26205287 | U10: 0.26205287 | V10: 0.26205287 | W10: 0.26205287 | X10: 0.26205287 | Y10: 0.26205287 | Z10: 0.26205287 | AA10: markets/nand/dist/20261025_NAND市場模型_v0.1.xlsx｜Mkt!C46:Z46
A11: Kioxia＋SanDisk 合資群份額（情境 B） | B11: % | C11: 0.27907731 | D11: 0.25560769 | E11: 0.27406433 | F11: 0.2689697 | G11: 0.27096015 | H11: 0.25018083 | I11: 0.26205287 | J11: 0.26205287 | K11: 0.25905287 | L11: 0.25905287 | M11: 0.25905287 | N11: 0.25905287 | O11: 0.25605287 | P11: 0.25605287 | Q11: 0.25605287 | R11: 0.25605287 | S11: 0.25305287 | T11: 0.25305287 | U11: 0.25305287 | V11: 0.25305287 | W11: 0.25005287 | X11: 0.25005287 | Y11: 0.25005287 | Z11: 0.25005287 | AA11: markets/nand/dist/20261025_NAND市場模型_v0.1.xlsx｜Mkt!C94:Z94
A12: Kioxia＋SanDisk 合資群份額（情境 C） | B12: % | C12: 0.27907731 | D12: 0.25560769 | E12: 0.27406433 | F12: 0.2689697 | G12: 0.27096015 | H12: 0.25018083 | I12: 0.26205287 | J12: 0.26205287 | K12: 0.25605287 | L12: 0.25605287 | M12: 0.25605287 | N12: 0.25605287 | O12: 0.25005287 | P12: 0.25005287 | Q12: 0.25005287 | R12: 0.25005287 | S12: 0.24405287 | T12: 0.24405287 | U12: 0.24405287 | V12: 0.24405287 | W12: 0.23805287 | X12: 0.23805287 | Y12: 0.23805287 | Z12: 0.23805287 | AA12: markets/nand/dist/20261025_NAND市場模型_v0.1.xlsx｜Mkt!C142:Z142

Sheet PL
A1: PL — Kioxia 損益（¥B；FY2025 實績；FY2026＝第一季實績＋第二季指引＋第三、四季推導；FY2027–FY2029 由市場層 markets/nand 驅動；FY2030–FY2032 收斂法見底部）
A3: 情境／項目 | B3: 單位 | C3: FY2025A | D3: FY2026 | E3: FY2027 | F3: FY2028 | G3: FY2029 | H3: 說明
A4: 情境 A（順利）
A5: 營收 | B5: ¥B | C5: =C55 -> 2337.6 | D5: =D55 -> 10271.368 | E5: =E55 -> 13504.346 | F5: =F55 -> 13616.69 | G5: =G55 -> 14247.994
A6: 毛利率 | B6: % | C6: =C57 -> 0.43326489 | D6: =D57 -> 0.83461657 | E6: =E57 -> 0.86131944 | F6: =F57 -> 0.85278912 | G6: =G57 -> 0.85470626
A7: 營業利益 | B7: ¥B | C7: =C59 -> 869 | D7: =D59 -> 8235.8498 | E7: =E59 -> 11291.168 | F7: =F59 -> 11250.12 | G7: =G59 -> 11786.904
A8: 營業利益率 | B8: % | C8: =C60 -> 0.3717488 | D8: =D60 -> 0.80182596 | E8: =E60 -> 0.83611367 | F8: =F60 -> 0.82620078 | G8: =G60 -> 0.82726759
A9: 淨利 | B9: ¥B | C9: =C61 -> 554.5 | D9: =D61 -> 5543.9096 | E9: =E61 -> 7663.3049 | F9: =F61 -> 7676.2645 | G9: =G61 -> 8082.2201
A10: EPS | B10: JPY | C10: =C69 -> 341.4 | D10: =D69 -> 3491.5112 | E10: =E69 -> 5213.0769 | F10: =F69 -> 5677.6981 | G10: =G69 -> 6583.6244
A11: 每股淨值 | B11: JPY | D11: =D70 -> 3934.9622 | E11: =E70 -> 8490.6974 | F11: =F70 -> 13859.618 | G11: =G70 -> 20643.44
A12: 自由現金流 | B12: ¥B | D12: =D64 -> 5413.9096 | E12: =E64 -> 7513.3049 | F12: =F64 -> 7526.2645 | G12: =G64 -> 7932.2201
A14: 情境 B（平平）
A15: 營收 | B15: ¥B | C15: =C91 -> 2337.6 | D15: =D91 -> 10296.2 | E15: =E91 -> 11553.093 | F15: =F91 -> 5230.9636 | G15: =G91 -> 6218.7584
A16: 毛利率 | B16: % | C16: =C93 -> 0.43326489 | D16: =D93 -> 0.83477314 | E16: =E93 -> 0.83811592 | F16: =F93 -> 0.64233494 | G16: =G93 -> 0.68616158
A17: 營業利益 | B17: ¥B | C17: =C95 -> 869 | D17: =D95 -> 8257.9388 | E17: =E95 -> 9361.9568 | F17: =F95 -> 3081.8427 | G17: =G95 -> 3956.4194
A18: 營業利益率 | B18: % | C18: =C96 -> 0.3717488 | D18: =D96 -> 0.8020375 | E18: =E96 -> 0.81034199 | F18: =F96 -> 0.58915393 | G18: =G96 -> 0.63620729
A19: 淨利 | B19: ¥B | C19: =C97 -> 554.5 | D19: =D97 -> 5558.9301 | E19: =E97 -> 6351.5227 | F19: =F97 -> 2114.7815 | G19: =G97 -> 2720.182
A20: EPS | B20: JPY | C20: =C105 -> 341.4 | D20: =D105 -> 3501.4903 | E20: =E105 -> 4261.7685 | F20: =F105 -> 1448.9359 | G20: =G105 -> 1916.6466
A21: 每股淨值 | B21: JPY | D21: =D106 -> 3943.1978 | E21: =E106 -> 7669.973 | F21: =F106 -> 9026.4216 | G21: =G106 -> 10857.807
A22: 自由現金流 | B22: ¥B | D22: =D100 -> 5428.9301 | E22: =E100 -> 6201.5227 | F22: =F100 -> 1964.7815 | G22: =G100 -> 2570.182
A24: 情境 C（不如預期）
A25: 營收 | B25: ¥B | C25: =C127 -> 2337.6 | D25: =D127 -> 10258.793 | E25: =E127 -> 11123.476 | F25: =F127 -> 3183.6657 | G25: =G127 -> 3427.2893
A26: 毛利率 | B26: % | C26: =C129 -> 0.43326489 | D26: =D129 -> 0.83394874 | E26: =E129 -> 0.83330157 | F26: =F129 -> 0.48260457 | G26: =G129 -> 0.50912407
A27: 營業利益 | B27: ¥B | C27: =C131 -> 869 | D27: =D131 -> 8218.6289 | E27: =E131 -> 8952.6316 | F27: =F131 -> 1278.7367 | G27: =G131 -> 1462.1765
A28: 營業利益率 | B28: % | C28: =C132 -> 0.3717488 | D28: =D132 -> 0.80113019 | E28: =E132 -> 0.80484117 | F28: =F132 -> 0.40165546 | G28: =G132 -> 0.42662768
A29: 淨利 | B29: ¥B | C29: =C133 -> 554.5 | D29: =D133 -> 5532.1994 | E29: =E133 -> 6073.0362 | F29: =F133 -> 887.009 | G29: =G133 -> 1015.7574
A30: EPS | B30: JPY | C30: =C141 -> 341.4 | D30: =D141 -> 3483.7333 | E30: =E141 -> 4061.865 | F30: =F141 -> 597.88476 | G30: =G141 -> 690.98984
A31: 每股淨值 | B31: JPY | D31: =D142 -> 3928.5433 | E31: =E142 -> 7480.0806 | F31: =F142 -> 8042.9373 | G31: =G142 -> 8697.5262
A32: 自由現金流 | B32: ¥B | D32: =D136 -> 5402.1994 | E32: =E136 -> 5923.0362 | F32: =F136 -> 737.009 | G32: =G136 -> 865.75738
A34: 核對：三情境 FY2025、第一季、第二季 − 實績與指引（應為 0） | D34: =D73+D109+D145 -> 0
A40: 情境 A（順利）：markets/nand 情境 A（價格路徑 A、2028–29 顆數係數 A、合資群份額 A）；每位元成本年降 cd_A
A41: A. 季度 | B41: 單位 | C41: FY26 第1季（2026Q2） | D41: FY26 第2季（2026Q3） | E41: FY26 第3季（2026Q4） | F41: FY26 第4季（2027Q1） | G41: FY27 第1季（2027Q2） | H41: FY27 第2季（2027Q3） | I41: FY27 第3季（2027Q4） | J41: FY27 第4季（2028Q1） | K41: FY28 第1季（2028Q2） | L41: FY28 第2季（2028Q3） | M41: FY28 第3季（2028Q4） | N41: FY28 第4季（2029Q1） | O41: FY29 第1季（2029Q2） | P41: FY29 第2季（2029Q3） | Q41: FY29 第3季（2029Q4） | R41: FY29 第4季（2030Q1） | T41: 說明
A42: 市場層營收（TrendForce 口徑，美元，同字母情境） | B42: $B | C42: =Units!H4*1 -> 10.72 | D42: =Units!I4*1 -> 14.319786 | E42: =Units!J4*1*1 -> 17.646994 | F42: =Units!K4*1*1 -> 19.444827 | G42: =Units!L4*1*1 -> 20.560401 | H42: =Units!M4*1*1 -> 20.652979 | I42: =Units!N4*1*1 -> 20.309216 | J42: =Units!O4*1*1 -> 20.400662 | K42: =Units!P4*1*1 -> 20.49252 | L42: =Units!Q4*1*1 -> 20.584792 | ... R42: =Units!W4*1*1 -> 21.540765 | T42: markets/nand；Sens 可乘份額係數、價格係數（第三季起）
A43: 位元（市場層；同字母） | B43: EB | C43: =Units!H7*1 -> 40.175758 | D43: =Units!I7*1 -> 46.666796 | E43: =Units!J7*1 -> 48.944548 | F43: =Units!K7*1 -> 52.360098 | G43: =Units!L7*1 -> 55.364063 | H43: =Units!M7*1 -> 58.540369 | I43: =Units!N7*1 -> 61.898904 | J43: =Units!O7*1 -> 65.450123 | ... R43: =Units!W7*1 -> 94.004556
A44: 營收 | B44: ¥B | C44: =q1_rev -> 1767.1 | D44: =g2_rev -> 2390 | E44: =E42*kx_k*fx -> 2908.9555 | F44: =F42*kx_k*fx -> 3205.3129 | G44: =G42*kx_k*fx -> 3389.2057 | H44: =H42*kx_k*fx -> 3404.4663 | I44: =I42*kx_k*fx -> 3347.7999 | J44: =J42*kx_k*fx -> 3362.874 | K44: =K42*kx_k*fx -> 3378.0161 | L44: =L42*kx_k*fx -> 3393.2263 | ... R44: =R42*kx_k*fx -> 3550.8102 | T44: 第一季實績、第二季公司指引；之後＝市場層 × 公司口徑係數 × 匯率
A45: 每 EB 營業成本（第二季以指引校準，之後每年 × (1 − 成本年降)） | B45: ¥B/EB | C45: =C46/C43 -> 9.6326745 | D45: =D46/D43 -> 9.2142602 | E45: =$D45*(1-cd_A)^(1/4) -> 8.8732984 | F45: =$D45*(1-cd_A)^(2/4) -> 8.5449534 | G45: =$D45*(1-cd_A)^(3/4) -> 8.2287584 | H45: =$D45*(1-cd_A)^(4/4) -> 7.9242638 | I45: =$D45*(1-cd_A)^(5/4) -> 7.6310366 | J45: =$D45*(1-cd_A)^(6/4) -> 7.3486599 | K45: =$D45*(1-cd_A)^(7/4) -> 7.0767322 | L45: =$D45*(1-cd_A)^(8/4) -> 6.8148669 | M45: =$D45*(1-cd_A)^(9/4) -> 6.5626915 | N45: =$D45*(1-cd_A)^(10/4) -> 6.3198475 | O45: =$D45*(1-cd_A)^(11/4) -> 6.0859897 | P45: =$D45*(1-cd_A)^(12/4) -> 5.8607855 | Q45: =$D45*(1-cd_A)^(13/4) -> 5.6439147 | R45: =$D45*(1-cd_A)^(14/4) -> 5.4350689
A46: 營業成本 | B46: ¥B | C46: =q1_rev-q1_gp -> 387 | D46: =g2_rev-g2_op-g2_ox -> 430 | E46: =E43*E45 -> 434.29958 | F46: =F43*F45 -> 447.4146 | G46: =G43*G45 -> 455.5775 | H46: =H43*H45 -> 463.88933 | I46: =I43*I45 -> 472.3528 | J46: =J43*J45 -> 480.97069 | K46: =K43*K45 -> 489.74581 | L46: =L43*L45 -> 498.68103 | ... R46: =R43*R45 -> 510.92124 | T46: 第二季＝指引營收 − 指引營業利益 − 推估營業費用
A47: 毛利率 | B47: % | C47: =1-C46/C44 -> 0.78099711 | D47: =1-D46/D44 -> 0.82008368 | E47: =1-E46/E44 -> 0.85070257 | F47: =1-F46/F44 -> 0.86041469 | G47: =1-G46/G44 -> 0.86557986 | H47: =1-H46/H44 -> 0.86374095 | I47: =1-I46/I44 -> 0.8589065 | J47: =1-J46/J44 -> 0.8569763 | ... R47: =1-R46/R44 -> 0.85611136
A48: 營業費用 | B48: ¥B | C48: =q1_gp-q1_op -> 110.1 | D48: =g2_ox -> 70 | E48: =(g2_ox-ox_var*g2_rev)*(1+ox_g)^(1/4)+ox_var*E44 -> 76.301196 | F48: =(g2_ox-ox_var*g2_rev)*(1+ox_g)^(2/4)+ox_var*F44 -> 80.403217 | G48: =(g2_ox-ox_var*g2_rev)*(1+ox_g)^(3/4)+ox_var*G44 -> 83.408044 | H48: =(g2_ox-ox_var*g2_rev)*(1+ox_g)^(4/4)+ox_var*H44 -> 84.754663 | I48: =(g2_ox-ox_var*g2_rev)*(1+ox_g)^(5/4)+ox_var*I44 -> 85.410804 | J48: =(g2_ox-ox_var*g2_rev)*(1+ox_g)^(6/4)+ox_var*J44 -> 86.813837 | K48: =(g2_ox-ox_var*g2_rev)*(1+ox_g)^(7/4)+ox_var*K44 -> 88.247746 | L48: =(g2_ox-ox_var*g2_rev)*(1+ox_g)^(8/4)+ox_var*L44 -> 89.713263 | M48: =(g2_ox-ox_var*g2_rev)*(1+ox_g)^(9/4)+ox_var*M44 -> 91.211135 | N48: =(g2_ox-ox_var*g2_rev)*(1+ox_g)^(10/4)+ox_var*N44 -> 92.873036 | O48: =(g2_ox-ox_var*g2_rev)*(1+ox_g)^(11/4)+ox_var*O44 -> 94.919815 | P48: =(g2_ox-ox_var*g2_rev)*(1+ox_g)^(12/4)+ox_var*P44 -> 97.012383 | Q48: =(g2_ox-ox_var*g2_rev)*(1+ox_g)^(13/4)+ox_var*Q44 -> 99.151777 | R48: =(g2_ox-ox_var*g2_rev)*(1+ox_g)^(14/4)+ox_var*R44 -> 99.862069 | T48: 固定部分以第二季校準（Derived）
A49: 營業利益 | B49: ¥B | C49: =C44-C46-C48 -> 1270 | D49: =D44-D46-D48 -> 1890 | E49: =E44-E46-E48 -> 2398.3547 | F49: =F44-F46-F48 -> 2677.4951 | G49: =G44-G46-G48 -> 2850.2202 | H49: =H44-H46-H48 -> 2855.8223 | I49: =I44-I46-I48 -> 2790.0363 | J49: =J44-J46-J48 -> 2795.0895 | ... R49: =R44-R46-R48 -> 2940.0269
A51: 淨利 | B51: ¥B | C51: =q1_ni -> 842.2 | D51: =g2_ni -> 1270 | E51: =(E49+nonop_q+rf*nc_j/4)*(1-tax) -> 1620.9471 | F51: =(F49+nonop_q+rf*nc_j/4)*(1-tax) -> 1810.7625 | G51: =(G49+nonop_q+rf*$D67/4)*(1-tax) -> 1934.4773 | H51: =(H49+nonop_q+rf*$D67/4)*(1-tax) -> 1938.2868 | I51: =(I49+nonop_q+rf*$D67/4)*(1-tax) -> 1893.5523 | J51: =(J49+nonop_q+rf*$D67/4)*(1-tax) -> 1896.9885 | K51: =(K49+nonop_q+rf*$E67/4)*(1-tax) -> 1910.561 | L51: =(L49+nonop_q+rf*$E67/4)*(1-tax) -> 1913.8314 | M51: =(M49+nonop_q+rf*$E67/4)*(1-tax) -> 1917.0156 | N51: =(N49+nonop_q+rf*$E67/4)*(1-tax) -> 1934.8564 | O51: =(O49+nonop_q+rf*$F67/4)*(1-tax) -> 1983.0964 | P51: =(P49+nonop_q+rf*$F67/4)*(1-tax) -> 2021.8268 | Q51: =(Q49+nonop_q+rf*$F67/4)*(1-tax) -> 2061.2972 | R51: =(R49+nonop_q+rf*$F67/4)*(1-tax) -> 2015.9997 | T51: （營業利益＋業外＋淨現金 × 收益率 ÷ 4）×（1 − 稅率）；FY2026 用 2026-06-30 淨現金
A52: 季 EPS（稀釋，分割後） | B52: JPY | C52: =C51/(sh0+dil)*1000 -> 507.34333 | D52: =D51/(sh0+dil)*1000 -> 765.0511 | E52: =E51/(sh0+dil)*1000 -> 976.46248 | F52: =F51/(sh0+dil)*1000 -> 1090.8078 | G52: =G51/(sh0+dil)*1000 -> 1165.3339 | H52: =H51/(sh0+dil)*1000 -> 1167.6287 | I52: =I51/(sh0+dil)*1000 -> 1140.6805 | J52: =J51/(sh0+dil)*1000 -> 1142.7505 | ... R52: =R51/(sh0+dil)*1000 -> 1214.4431
A54: B. 年度（會計年度） | B54: 單位 | C54: FY2025A | D54: FY2026 | E54: FY2027 | F54: FY2028 | G54: FY2029 | T54: 說明
A55: 營收 | B55: ¥B | C55: =a25_rev -> 2337.6 | D55: =SUM(C44:F44) -> 10271.368 | E55: =SUM(G44:J44) -> 13504.346 | F55: =SUM(K44:N44) -> 13616.69 | G55: =SUM(O44:R44) -> 14247.994 | T55: FY2026＝第一季實績＋第二季指引＋第三、四季推導
A56: 營業成本 | B56: ¥B | C56: =a25_rev-(p1_gp+p2_gp+p3_gp+p4_gp) -> 1324.8 | D56: =SUM(C46:F46) -> 1698.7142 | E56: =SUM(G46:J46) -> 1872.7903 | F56: =SUM(K46:N46) -> 2004.525 | G56: =SUM(O46:R46) -> 2070.1443
A57: 毛利率 | B57: % | C57: =1-C56/C55 -> 0.43326489 | D57: =1-D56/D55 -> 0.83461657 | E57: =1-E56/E55 -> 0.86131944 | F57: =1-F56/F55 -> 0.85278912 | G57: =1-G56/G55 -> 0.85470626
A58: 營業費用 | B58: ¥B | D58: =SUM(C48:F48) -> 336.80441 | E58: =SUM(G48:J48) -> 340.38735 | F58: =SUM(K48:N48) -> 362.04518 | G58: =SUM(O48:R48) -> 390.94604
A59: 營業利益 | B59: ¥B | C59: =p1_op+p2_op+p3_op+p4_op -> 869 | D59: =SUM(C49:F49) -> 8235.8498 | E59: =SUM(G49:J49) -> 11291.168 | F59: =SUM(K49:N49) -> 11250.12 | G59: =SUM(O49:R49) -> 11786.904
A60: 營業利益率 | B60: % | C60: =C59/C55 -> 0.3717488 | D60: =D59/D55 -> 0.80182596 | E60: =E59/E55 -> 0.83611367 | F60: =F59/F55 -> 0.82620078 | G60: =G59/G55 -> 0.82726759
A61: 淨利 | B61: ¥B | C61: =a25_ni -> 554.5 | D61: =SUM(C51:F51) -> 5543.9096 | E61: =SUM(G51:J51) -> 7663.3049 | F61: =SUM(K51:N51) -> 7676.2645 | G61: =SUM(O51:R51) -> 8082.2201
A62: 折舊攤銷 | B62: ¥B | D62: =da_y -> 320 | E62: =da_y -> 320 | F62: =da_y -> 320 | G62: =da_y -> 320
A63: 資本支出（含合資廠分攤） | B63: ¥B | D63: =cap_2026 -> 450 | E63: =cap_2027 -> 470 | F63: =cap_2028 -> 470 | G63: =cap_2029 -> 470
A64: 自由現金流（淨利＋折舊 − 資本支出） | B64: ¥B | D64: =D61+D62-D63 -> 5413.9096 | E64: =E61+E62-E63 -> 7513.3049 | F64: =F61+F62-F63 -> 7526.2645 | G64: =G61+G62-G63 -> 7932.2201
A65: 股東回饋（以買回計） | B65: ¥B | D65: =MAX(0,payout*(SUM(D51:F51)+0.75*(D62-D63))) -> 920.84192 | E65: =MAX(0,payout*E64) -> 1502.661 | F65: =MAX(0,payout*F64) -> 1505.2529 | G65: =MAX(0,payout*G64) -> 1586.444 | T65: FY2026 只計 2026-07 以後三季的自由現金流
A66: 期末權益 | B66: ¥B | C66: =eq25 -> 1399.1 | D66: =eq_j+SUM(D51:F51)-D65 -> 6185.1677 | E66: =D66+E61-E65 -> 12345.812 | F66: =E66+F61-F65 -> 18516.823 | G66: =F66+G61-G65 -> 25012.599 | T66: FY2026＝2026-06-30 權益＋第二至四季淨利 − 回饋（不含其他綜合損益）
A67: 期末淨現金 | B67: ¥B | D67: =nc_j+(SUM(D51:F51)+0.75*(D62-D63))-D65 -> 3839.7677 | E67: =D67+E64-E65 -> 9850.4116 | F67: =E67+F64-F65 -> 15871.423 | G67: =F67+G64-G65 -> 22217.199
A68: 期末流通股數（分割後） | B68: 百萬股 | D68: =sh0-D65/bb_px*1000 -> 1571.8493 | E68: =D68-E65/bb_px*1000 -> 1454.0398 | F68: =E68-F65/bb_px*1000 -> 1336.027 | G68: =F68-G65/bb_px*1000 -> 1211.6488
A69: EPS（稀釋：期末流通股數＋dil；分割後） | B69: JPY | C69: =a25_eps -> 341.4 | D69: =D61/(D68+dil)*1000 -> 3491.5112 | E69: =E61/(E68+dil)*1000 -> 5213.0769 | F69: =F61/(F68+dil)*1000 -> 5677.6981 | G69: =G61/(G68+dil)*1000 -> 6583.6244
A70: 每股淨值 BVPS（期末流通股數） | B70: JPY | D70: =D66/D68*1000 -> 3934.9622 | E70: =E66/E68*1000 -> 8490.6974 | F70: =F66/F68*1000 -> 13859.618 | G70: =G66/G68*1000 -> 20643.44
A71: ROE（期末權益） | B71: % | D71: =D61/D66 -> 0.89632325 | E71: =E61/E66 -> 0.62072103 | F71: =F61/F66 -> 0.41455623 | G71: =G61/G66 -> 0.32312596
A72: 每股自由現金流（稀釋） | B72: JPY | E72: =E64/(E68+dil)*1000 -> 5111.0372 | F72: =F64/(F68+dil)*1000 -> 5566.7516 | G72: =G64/(G68+dil)*1000 -> 6461.4372
A73: 檢查：FY2025 營收、淨利 − 四季合計；第一季、第二季 − 實績與指引（應為 0） | B73: ¥B | D73: =ABS(C44-q1_rev)+ABS(D49-g2_op)+ABS(C55-2337.6) -> 0
A76: 情境 B（平平）：markets/nand 情境 B（價格路徑 B、2028–29 顆數係數 B、合資群份額 B）；每位元成本年降 cd_B
A77: A. 季度 | B77: 單位 | C77: FY26 第1季（2026Q2） | D77: FY26 第2季（2026Q3） | E77: FY26 第3季（2026Q4） | F77: FY26 第4季（2027Q1） | G77: FY27 第1季（2027Q2） | H77: FY27 第2季（2027Q3） | I77: FY27 第3季（2027Q4） | J77: FY27 第4季（2028Q1） | K77: FY28 第1季（2028Q2） | L77: FY28 第2季（2028Q3） | M77: FY28 第3季（2028Q4） | N77: FY28 第4季（2029Q1） | O77: FY29 第1季（2029Q2） | P77: FY29 第2季（2029Q3） | Q77: FY29 第3季（2029Q4） | R77: FY29 第4季（2030Q1） | T77: 說明
A78: 市場層營收（TrendForce 口徑，美元，同字母情境） | B78: $B | C78: =Units!H5*1 -> 10.72 | D78: =Units!I5*1 -> 14.319786 | E78: =Units!J5*1*1 -> 17.646994 | F78: =Units!K5*1*1 -> 19.595468 | G78: =Units!L5*1*1 -> 21.134079 | H78: =Units!M5*1*1 -> 20.111911 | I78: =Units!N5*1*1 -> 17.012605 | J78: =Units!O5*1*1 -> 11.827513 | K78: =Units!P5*1*1 -> 9.1858457 | L78: =Units!Q5*1*1 -> 7.6098059 | ... R78: =Units!W5*1*1 -> 9.7210303 | T78: markets/nand；Sens 可乘份額係數、價格係數（第三季起）
A79: 位元（市場層；同字母） | B79: EB | C79: =Units!H8*1 -> 40.175758 | D79: =Units!I8*1 -> 46.666796 | E79: =Units!J8*1 -> 48.944548 | F79: =Units!K8*1 -> 51.760676 | G79: =Units!L8*1 -> 54.730251 | H79: =Units!M8*1 -> 57.870195 | I79: =Units!N8*1 -> 61.190281 | J79: =Units!O8*1 -> 60.772488 | ... R79: =Units!W8*1 -> 81.650416
A80: 營收 | B80: ¥B | C80: =q1_rev -> 1767.1 | D80: =g2_rev -> 2390 | E80: =E78*kx_k*fx -> 2908.9555 | F80: =F78*kx_k*fx -> 3230.1448 | G80: =G78*kx_k*fx -> 3483.7715 | H80: =H78*kx_k*fx -> 3315.2759 | I80: =I78*kx_k*fx -> 2804.382 | J80: =J78*kx_k*fx -> 1949.664 | K80: =K78*kx_k*fx -> 1514.2078 | L80: =L78*kx_k*fx -> 1254.4112 | ... R80: =R78*kx_k*fx -> 1602.4284 | T80: 第一季實績、第二季公司指引；之後＝市場層 × 公司口徑係數 × 匯率
A81: 每 EB 營業成本（第二季以指引校準，之後每年 × (1 − 成本年降)） | B81: ¥B/EB | C81: =C82/C79 -> 9.6326745 | D81: =D82/D79 -> 9.2142602 | E81: =$D81*(1-cd_B)^(1/4) -> 8.9244434 | F81: =$D81*(1-cd_B)^(2/4) -> 8.6437423 | G81: =$D81*(1-cd_B)^(3/4) -> 8.37187 | H81: =$D81*(1-cd_B)^(4/4) -> 8.108549 | I81: =$D81*(1-cd_B)^(5/4) -> 7.8535102 | J81: =$D81*(1-cd_B)^(6/4) -> 7.6064932 | K81: =$D81*(1-cd_B)^(7/4) -> 7.3672456 | L81: =$D81*(1-cd_B)^(8/4) -> 7.1355231 | M81: =$D81*(1-cd_B)^(9/4) -> 6.911089 | N81: =$D81*(1-cd_B)^(10/4) -> 6.693714 | O81: =$D81*(1-cd_B)^(11/4) -> 6.4831762 | P81: =$D81*(1-cd_B)^(12/4) -> 6.2792604 | Q81: =$D81*(1-cd_B)^(13/4) -> 6.0817583 | R81: =$D81*(1-cd_B)^(14/4) -> 5.8904683
A82: 營業成本 | B82: ¥B | C82: =q1_rev-q1_gp -> 387 | D82: =g2_rev-g2_op-g2_ox -> 430 | E82: =E79*E81 -> 436.80285 | F82: =F79*F81 -> 447.40594 | G82: =G79*G81 -> 458.19455 | H82: =H79*H81 -> 469.24331 | I82: =I79*I81 -> 480.5585 | J82: =J79*J81 -> 462.26552 | K82: =K79*K81 -> 463.63543 | L82: =L79*L81 -> 465.0094 | ... R82: =R79*R81 -> 480.95919 | T82: 第二季＝指引營收 − 指引營業利益 − 推估營業費用
A83: 毛利率 | B83: % | C83: =1-C82/C80 -> 0.78099711 | D83: =1-D82/D80 -> 0.82008368 | E83: =1-E82/E80 -> 0.84984203 | F83: =1-F82/F80 -> 0.86149044 | G83: =1-G82/G80 -> 0.86847744 | H83: =1-H82/H80 -> 0.85846025 | I83: =1-I82/I80 -> 0.82864014 | J83: =1-J82/J80 -> 0.76289991 | ... R83: =1-R82/R80 -> 0.69985605
A84: 營業費用 | B84: ¥B | C84: =q1_gp-q1_op -> 110.1 | D84: =g2_ox -> 70 | E84: =(g2_ox-ox_var*g2_rev)*(1+ox_g)^(1/4)+ox_var*E80 -> 76.301196 | F84: =(g2_ox-ox_var*g2_rev)*(1+ox_g)^(2/4)+ox_var*F80 -> 80.651536 | G84: =(g2_ox-ox_var*g2_rev)*(1+ox_g)^(3/4)+ox_var*G80 -> 84.353702 | H84: =(g2_ox-ox_var*g2_rev)*(1+ox_g)^(4/4)+ox_var*H80 -> 83.862759 | I84: =(g2_ox-ox_var*g2_rev)*(1+ox_g)^(5/4)+ox_var*I80 -> 79.976625 | J84: =(g2_ox-ox_var*g2_rev)*(1+ox_g)^(6/4)+ox_var*J80 -> 72.681737 | K84: =(g2_ox-ox_var*g2_rev)*(1+ox_g)^(7/4)+ox_var*K80 -> 69.609664 | L84: =(g2_ox-ox_var*g2_rev)*(1+ox_g)^(8/4)+ox_var*L80 -> 68.325112 | M84: =(g2_ox-ox_var*g2_rev)*(1+ox_g)^(9/4)+ox_var*M80 -> 68.816957 | N84: =(g2_ox-ox_var*g2_rev)*(1+ox_g)^(10/4)+ox_var*N80 -> 71.43618 | O84: =(g2_ox-ox_var*g2_rev)*(1+ox_g)^(11/4)+ox_var*O80 -> 74.143687 | P84: =(g2_ox-ox_var*g2_rev)*(1+ox_g)^(12/4)+ox_var*P80 -> 76.717029 | Q84: =(g2_ox-ox_var*g2_rev)*(1+ox_g)^(13/4)+ox_var*Q80 -> 79.414722 | R84: =(g2_ox-ox_var*g2_rev)*(1+ox_g)^(14/4)+ox_var*R80 -> 80.378251 | T84: 固定部分以第二季校準（Derived）
A85: 營業利益 | B85: ¥B | C85: =C80-C82-C84 -> 1270 | D85: =D80-D82-D84 -> 1890 | E85: =E80-E82-E84 -> 2395.8515 | F85: =F80-F82-F84 -> 2702.0873 | G85: =G80-G82-G84 -> 2941.2233 | H85: =H80-H82-H84 -> 2762.1698 | I85: =I80-I82-I84 -> 2243.8469 | J85: =J80-J82-J84 -> 1414.7168 | ... R85: =R80-R82-R84 -> 1041.091
A87: 淨利 | B87: ¥B | C87: =q1_ni -> 842.2 | D87: =g2_ni -> 1270 | E87: =(E85+nonop_q+rf*nc_j/4)*(1-tax) -> 1619.2449 | F87: =(F85+nonop_q+rf*nc_j/4)*(1-tax) -> 1827.4853 | G87: =(G85+nonop_q+rf*$D103/4)*(1-tax) -> 1996.3799 | H87: =(H85+nonop_q+rf*$D103/4)*(1-tax) -> 1874.6235 | I87: =(I85+nonop_q+rf*$D103/4)*(1-tax) -> 1522.1639 | J87: =(J85+nonop_q+rf*$D103/4)*(1-tax) -> 958.35544 | K87: =(K85+nonop_q+rf*$E103/4)*(1-tax) -> 671.83677 | L87: =(L85+nonop_q+rf*$E103/4)*(1-tax) -> 495.11425 | M87: =(M85+nonop_q+rf*$E103/4)*(1-tax) -> 435.82236 | N87: =(N85+nonop_q+rf*$E103/4)*(1-tax) -> 512.00809 | O87: =(O85+nonop_q+rf*$F103/4)*(1-tax) -> 596.19151 | P87: =(P85+nonop_q+rf*$F103/4)*(1-tax) -> 666.28558 | Q87: =(Q85+nonop_q+rf*$F103/4)*(1-tax) -> 742.30885 | R87: =(R85+nonop_q+rf*$F103/4)*(1-tax) -> 715.39607 | T87: （營業利益＋業外＋淨現金 × 收益率 ÷ 4）×（1 − 稅率）；FY2026 用 2026-06-30 淨現金
A88: 季 EPS（稀釋，分割後） | B88: JPY | C88: =C87/(sh0+dil)*1000 -> 507.34333 | D88: =D87/(sh0+dil)*1000 -> 765.0511 | E88: =E87/(sh0+dil)*1000 -> 975.43706 | F88: =F87/(sh0+dil)*1000 -> 1100.8816 | G88: =G87/(sh0+dil)*1000 -> 1202.6241 | H88: =H87/(sh0+dil)*1000 -> 1129.2778 | I88: =I87/(sh0+dil)*1000 -> 916.95524 | J88: =J87/(sh0+dil)*1000 -> 577.31565 | ... R88: =R87/(sh0+dil)*1000 -> 430.95634
A90: B. 年度（會計年度） | B90: 單位 | C90: FY2025A | D90: FY2026 | E90: FY2027 | F90: FY2028 | G90: FY2029 | T90: 說明
A91: 營收 | B91: ¥B | C91: =a25_rev -> 2337.6 | D91: =SUM(C80:F80) -> 10296.2 | E91: =SUM(G80:J80) -> 11553.093 | F91: =SUM(K80:N80) -> 5230.9636 | G91: =SUM(O80:R80) -> 6218.7584 | T91: FY2026＝第一季實績＋第二季指引＋第三、四季推導
A92: 營業成本 | B92: ¥B | C92: =a25_rev-(p1_gp+p2_gp+p3_gp+p4_gp) -> 1324.8 | D92: =SUM(C82:F82) -> 1701.2088 | E92: =SUM(G82:J82) -> 1870.2619 | F92: =SUM(K82:N82) -> 1870.9329 | G92: =SUM(O82:R82) -> 1951.6853
A93: 毛利率 | B93: % | C93: =1-C92/C91 -> 0.43326489 | D93: =1-D92/D91 -> 0.83477314 | E93: =1-E92/E91 -> 0.83811592 | F93: =1-F92/F91 -> 0.64233494 | G93: =1-G92/G91 -> 0.68616158
A94: 營業費用 | B94: ¥B | D94: =SUM(C84:F84) -> 337.05273 | E94: =SUM(G84:J84) -> 320.87482 | F94: =SUM(K84:N84) -> 278.18791 | G94: =SUM(O84:R84) -> 310.65369
A95: 營業利益 | B95: ¥B | C95: =p1_op+p2_op+p3_op+p4_op -> 869 | D95: =SUM(C85:F85) -> 8257.9388 | E95: =SUM(G85:J85) -> 9361.9568 | F95: =SUM(K85:N85) -> 3081.8427 | G95: =SUM(O85:R85) -> 3956.4194
A96: 營業利益率 | B96: % | C96: =C95/C91 -> 0.3717488 | D96: =D95/D91 -> 0.8020375 | E96: =E95/E91 -> 0.81034199 | F96: =F95/F91 -> 0.58915393 | G96: =G95/G91 -> 0.63620729
A97: 淨利 | B97: ¥B | C97: =a25_ni -> 554.5 | D97: =SUM(C87:F87) -> 5558.9301 | E97: =SUM(G87:J87) -> 6351.5227 | F97: =SUM(K87:N87) -> 2114.7815 | G97: =SUM(O87:R87) -> 2720.182
A98: 折舊攤銷 | B98: ¥B | D98: =da_y -> 320 | E98: =da_y -> 320 | F98: =da_y -> 320 | G98: =da_y -> 320
A99: 資本支出（含合資廠分攤） | B99: ¥B | D99: =cap_2026 -> 450 | E99: =cap_2027 -> 470 | F99: =cap_2028 -> 470 | G99: =cap_2029 -> 470
A100: 自由現金流（淨利＋折舊 − 資本支出） | B100: ¥B | D100: =D97+D98-D99 -> 5428.9301 | E100: =E97+E98-E99 -> 6201.5227 | F100: =F97+F98-F99 -> 1964.7815 | G100: =G97+G98-G99 -> 2570.182
A101: 股東回饋（以買回計） | B101: ¥B | D101: =MAX(0,payout*(SUM(D87:F87)+0.75*(D98-D99))) -> 923.84603 | E101: =MAX(0,payout*E100) -> 1240.3045 | F101: =MAX(0,payout*F100) -> 392.9563 | G101: =MAX(0,payout*G100) -> 514.0364 | T101: FY2026 只計 2026-07 以後三季的自由現金流
A102: 期末權益 | B102: ¥B | C102: =eq25 -> 1399.1 | D102: =eq_j+SUM(D87:F87)-D101 -> 6197.1841 | E102: =D102+E97-E101 -> 11308.402 | F102: =E102+F97-F101 -> 13030.227 | G102: =F102+G97-G101 -> 15236.373 | T102: FY2026＝2026-06-30 權益＋第二至四季淨利 − 回饋（不含其他綜合損益）
A103: 期末淨現金 | B103: ¥B | D103: =nc_j+(SUM(D87:F87)+0.75*(D98-D99))-D101 -> 3851.7841 | E103: =D103+E100-E101 -> 8813.0023 | F103: =E103+F100-F101 -> 10384.827 | G103: =F103+G100-G101 -> 12440.973
A104: 期末流通股數（分割後） | B104: 百萬股 | D104: =sh0-D101/bb_px*1000 -> 1571.6138 | E104: =D104-E101/bb_px*1000 -> 1474.3732 | F104: =E104-F101/bb_px*1000 -> 1443.5651 | G104: =F104-G101/bb_px*1000 -> 1403.2644
A105: EPS（稀釋：期末流通股數＋dil；分割後） | B105: JPY | C105: =a25_eps -> 341.4 | D105: =D97/(D104+dil)*1000 -> 3501.4903 | E105: =E97/(E104+dil)*1000 -> 4261.7685 | F105: =F97/(F104+dil)*1000 -> 1448.9359 | G105: =G97/(G104+dil)*1000 -> 1916.6466
A106: 每股淨值 BVPS（期末流通股數） | B106: JPY | D106: =D102/D104*1000 -> 3943.1978 | E106: =E102/E104*1000 -> 7669.973 | F106: =F102/F104*1000 -> 9026.4216 | G106: =G102/G104*1000 -> 10857.807
A107: ROE（期末權益） | B107: % | D107: =D97/D102 -> 0.89700903 | E107: =E97/E102 -> 0.56166402 | F107: =F97/F102 -> 0.16229812 | G107: =G97/G102 -> 0.17853212
A108: 每股自由現金流（稀釋） | B108: JPY | E108: =E100/(E104+dil)*1000 -> 4161.1209 | F108: =F100/(F104+dil)*1000 -> 1346.1639 | G108: =G100/(G104+dil)*1000 -> 1810.9562
A109: 檢查：FY2025 營收、淨利 − 四季合計；第一季、第二季 − 實績與指引（應為 0） | B109: ¥B | D109: =ABS(C80-q1_rev)+ABS(D85-g2_op)+ABS(C91-2337.6) -> 0
A112: 情境 C（不如預期）：markets/nand 情境 C（價格路徑 C、2028–29 顆數係數 C、合資群份額 C）；每位元成本年降 cd_C
A113: A. 季度 | B113: 單位 | C113: FY26 第1季（2026Q2） | D113: FY26 第2季（2026Q3） | E113: FY26 第3季（2026Q4） | F113: FY26 第4季（2027Q1） | G113: FY27 第1季（2027Q2） | H113: FY27 第2季（2027Q3） | I113: FY27 第3季（2027Q4） | J113: FY27 第4季（2028Q1） | K113: FY28 第1季（2028Q2） | L113: FY28 第2季（2028Q3） | M113: FY28 第3季（2028Q4） | N113: FY28 第4季（2029Q1） | O113: FY29 第1季（2029Q2） | P113: FY29 第2季（2029Q3） | Q113: FY29 第3季（2029Q4） | R113: FY29 第4季（2030Q1） | T113: 說明
A114: 市場層營收（TrendForce 口徑，美元，同字母情境） | B114: $B | C114: =Units!H6*1 -> 10.72 | D114: =Units!I6*1 -> 14.319786 | E114: =Units!J6*1*1 -> 17.646994 | F114: =Units!K6*1*1 -> 19.36854 | G114: =Units!L6*1*1 -> 20.889333 | H114: =Units!M6*1*1 -> 19.879002 | I114: =Units!N6*1*1 -> 16.815588 | J114: =Units!O6*1*1 -> 9.8959399 | K114: =Units!P6*1*1 -> 6.4479488 | L114: =Units!Q6*1*1 -> 4.8476808 | ... R114: =Units!W6*1*1 -> 5.5313594 | T114: markets/nand；Sens 可乘份額係數、價格係數（第三季起）
A115: 位元（市場層；同字母） | B115: EB | C115: =Units!H9*1 -> 40.175758 | D115: =Units!I9*1 -> 46.666796 | E115: =Units!J9*1 -> 48.944548 | F115: =Units!K9*1 -> 51.161254 | G115: =Units!L9*1 -> 54.096439 | H115: =Units!M9*1 -> 57.200021 | I115: =Units!N9*1 -> 60.481658 | J115: =Units!O9*1 -> 54.758976 | ... R115: =Units!W9*1 -> 64.958969
A116: 營收 | B116: ¥B | C116: =q1_rev -> 1767.1 | D116: =g2_rev -> 2390 | E116: =E114*kx_k*fx -> 2908.9555 | F116: =F114*kx_k*fx -> 3192.7376 | G116: =G114*kx_k*fx -> 3443.4272 | H116: =H114*kx_k*fx -> 3276.8829 | I116: =I114*kx_k*fx -> 2771.9054 | J116: =J114*kx_k*fx -> 1631.2608 | K116: =K114*kx_k*fx -> 1062.889 | L116: =L114*kx_k*fx -> 799.09857 | ... R116: =R114*kx_k*fx -> 911.79712 | T116: 第一季實績、第二季公司指引；之後＝市場層 × 公司口徑係數 × 匯率
A117: 每 EB 營業成本（第二季以指引校準，之後每年 × (1 − 成本年降)） | B117: ¥B/EB | C117: =C118/C115 -> 9.6326745 | D117: =D118/D115 -> 9.2142602 | E117: =$D117*(1-cd_C)^(1/4) -> 8.974724 | F117: =$D117*(1-cd_C)^(2/4) -> 8.7414148 | G117: =$D117*(1-cd_C)^(3/4) -> 8.5141708 | H117: =$D117*(1-cd_C)^(4/4) -> 8.2928342 | I117: =$D117*(1-cd_C)^(5/4) -> 8.0772516 | J117: =$D117*(1-cd_C)^(6/4) -> 7.8672733 | K117: =$D117*(1-cd_C)^(7/4) -> 7.6627537 | L117: =$D117*(1-cd_C)^(8/4) -> 7.4635508 | M117: =$D117*(1-cd_C)^(9/4) -> 7.2695264 | N117: =$D117*(1-cd_C)^(10/4) -> 7.080546 | O117: =$D117*(1-cd_C)^(11/4) -> 6.8964783 | P117: =$D117*(1-cd_C)^(12/4) -> 6.7171957 | Q117: =$D117*(1-cd_C)^(13/4) -> 6.5425738 | R117: =$D117*(1-cd_C)^(14/4) -> 6.3724914
...

Sheet Val
A1: Val — 估值。第 0 節為目標價（DCF 與 Comparable 加權；Comparable 依記憶體慣例用前瞻 P/B）；第 5–6 節為目前倍數、十年倍數與規則值（舊法參考）
A2: Kioxia 2024-12 上市，只有兩個年底：十年 P/B、P/E 以美光（同為記憶體循環股）為 Analogy，見第 6 節。每股數字皆為 2026-10-01 一股分三股後
A4: 0. 目標價
A5: 0.1 DCF（股東權益現金流，FY2027–FY2032 明確期＋FY2032 後永續）
A6: 項目 | B6: A（順利） | C6: B（平平） | D6: C（不如預期） | E6: 說明
A7: 情境 EPS（FY2027–FY2032） | E7: PL 頁延伸區塊；FY2030 起為收斂法（灰底）
A8: FY2027 | B8: =PL!D156 -> 5213.0769 | C8: =PL!D163 -> 4261.7685 | D8: =PL!D170 -> 4061.865
A9: FY2028 | B9: =PL!E156 -> 5677.6981 | C9: =PL!E163 -> 1448.9359 | D9: =PL!E170 -> 597.88476
A10: FY2029 | B10: =PL!F156 -> 6583.6244 | C10: =PL!F163 -> 1916.6466 | D10: =PL!F170 -> 690.98984
A11: FY2030 | B11: =PL!G156 -> 5327.8954 | C11: =PL!G163 -> 1699.6401 | D11: =PL!G170 -> 583.65344
A12: FY2031 | B12: =PL!H156 -> 3944.2377 | C12: =PL!H163 -> 1324.7396 | D12: =PL!H170 -> 453.41189
A13: FY2032 | B13: =PL!I156 -> 2401.0335 | C13: =PL!I163 -> 829.43228 | D13: =PL!I170 -> 306.51067
A14: 股東現金流＝EPS ×（1 − tp_g ÷ tp_roe） | E14: 記憶體資本密集：FY2027–FY2029 改用每股（淨利＋折舊－資本支出）＝ PL 區塊每股自由現金流；收斂期（FY2030 起）用 EPS ×（1 − 再投資率）
A15: 再投資率（tp_g ÷ tp_roe，上限 0.8；FY2030 起用） | B15: =MIN(tp_g/tp_roe,0.8) -> 0.10447316 | E15: ROE 為 FY2024–FY2025 平均（In 頁 tp_roe）
A16: FY2027（淨利＋折舊－資本支出，每股） | B16: =PL!E72 -> 5111.0372 | C16: =PL!E108 -> 4161.1209 | D16: =PL!E144 -> 3961.5396
A17: FY2028（淨利＋折舊－資本支出，每股） | B17: =PL!F72 -> 5566.7516 | C17: =PL!F108 -> 1346.1639 | D17: =PL!F144 -> 496.77788
A18: FY2029（淨利＋折舊－資本支出，每股） | B18: =PL!G72 -> 6461.4372 | C18: =PL!G108 -> 1810.9562 | D18: =PL!G144 -> 588.94926
A19: FY2030（EPS ×（1 − 再投資率）） | B19: =B11*(1-$B$15) -> 4771.2734 | C19: =C11*(1-$B$15) -> 1522.0733 | D19: =D11*(1-$B$15) -> 522.67732
A20: FY2031（EPS ×（1 − 再投資率）） | B20: =B12*(1-$B$15) -> 3532.1707 | C20: =C12*(1-$B$15) -> 1186.3399 | D20: =D12*(1-$B$15) -> 406.04251
A21: FY2032（EPS ×（1 − 再投資率）） | B21: =B13*(1-$B$15) -> 2150.1899 | C21: =C13*(1-$B$15) -> 742.77886 | D21: =D13*(1-$B$15) -> 274.48853
A22: DCF 情境每股價值（折現率 tp_r） | B22: =MAX(0,SUMPRODUCT(B16:B21,1/(1+tp_r)^{1;2;3;4;5;6})+B21*(1+tp_g)/(tp_r-tp_g)/(1+tp_r)^6) -> 41805.282 | C22: =MAX(0,SUMPRODUCT(C16:C21,1/(1+tp_r)^{1;2;3;4;5;6})+C21*(1+tp_g)/(tp_r-tp_g)/(1+tp_r)^6) -> 15718.975 | D22: =MAX(0,SUMPRODUCT(D16:D21,1/(1+tp_r)^{1;2;3;4;5;6})+D21*(1+tp_g)/(tp_r-tp_g)/(1+tp_r)^6) -> 7904.1586 | E22: Σ 明確期現金流 ÷ (1＋r)^t ＋ 永續價值 ÷ (1＋r)^6；永續價值＝FY2032 現金流 ×(1＋g)÷(r−g)；基準日 2026 年底，t＝1 對 FY2027（2027-04～2028-03，t 以會計年度計，略低估）；FY2026 剩餘一季的現金流未計入；負值取 0
A23: DCF 情境價值推到 12 個月後（×(1＋tp_r)） | B23: =B22*(1+tp_r) -> 45985.81 | C23: =C22*(1+tp_r) -> 17290.873 | D23: =D22*(1+tp_r) -> 8694.5744
A24: DCF 目標價（情境加權） | B24: =tp_wA*B23+tp_wB*C23+tp_wC*D23 -> 24180.094 | E24: Σ 權重 × 情境價值 ×(1＋r)；權重見 In 頁 tp_wA／tp_wB／tp_wC
A26: 0.2 Comparable（市場主流同業前瞻 P/B；記憶體慣例）
A27: 同業與前瞻 P/B | B27: 代號 | C27: 前瞻 P/B | D27: 日期 | E27: 來源 | F27: 標記
A28: 美光 | B28: MU | C28: 3.35 | D28: 2026-10-23 | E28: MarketScreener：現價 ÷ FY2027E（2027-09）每股淨值（micron/ 模型同值） | F28: Interested-party
A29: SK 海力士 | B29: 000660.KS | C29: 1.35 | D29: 2026-10-23 | E29: MarketScreener：現價 ÷ 2027E 每股淨值（skhynix/ 模型同值） | F29: Interested-party
A30: 三星電子 | B30: 005930.KS | C30: 1.26 | D30: 2026-10-23 | E30: MarketScreener：現價 ÷ 2027E 每股淨值（samsung/ 模型同值） | F30: Interested-party
A31: SanDisk | B31: SNDK | C31: =1238.03/((313.8+553.1)/2) -> 2.8562233 | D31: 2026-10-23 | E31: 現價 1,238.03 ÷ MarketScreener 約 2027 年底每股淨值（FY2027、FY2028 年底平均；sndk/ 模型同口徑） | F31: Interested-party
A32: 同業前瞻 P/B 中位數 | B32: =MEDIAN(C28:C31) -> 2.1031117 | E32: 記憶體同業（美光、SK 海力士、三星、SanDisk；無 A 股）。WDC（硬碟）不列入 P/B（僅有落後 P/B），P/E 並列參考見下方。Kioxia 自身現價 ÷ FY2027 年底（2028-03）共識每股淨值 1.63x（sndk/ 同業表同值）
A33: 12 個月後的前瞻每股淨值（情境加權） | B33: =tp_wA*(0.25*PL!E70+0.75*PL!F70)+tp_wB*(0.25*PL!E106+0.75*PL!F106)+tp_wC*(0.25*PL!E142+0.75*PL!F142) -> 9679.3156 | E33: 同業倍數＝現價 ÷ 約 14 個月後（約 2027 年底）每股淨值；對應 12 個月後（約 2027-10）用約 2028 年底每股淨值＝¼ × FY2027 年底（2028-03）＋¾ × FY2028 年底（2029-03）（會計年度 3 月，依月份調整）
A34: Comparable 目標價 | B34: =B32*B33 -> 20356.682 | E34: 同業中位數 × 前瞻每股淨值
A35: 12 個月後的前瞻 EPS（情境加權） | B35: =tp_wA*(5/12*B8+7/12*B9)+tp_wB*(5/12*C8+7/12*C9)+tp_wC*(5/12*D8+7/12*D9) -> 3363.9485 | E35: 約 2027-10 時的未來 12 月（2027-11～2028-10）≈ 5／12 × FY2027（2027-04～2028-03）＋7／12 × FY2028（會計年度 3 月，依月份調整）
A37: 並列參考：同業前瞻 P/E（不進目標價）
A38: 同業與前瞻 P/E | B38: 代號 | C38: 前瞻 P/E | D38: 日期 | E38: 來源 | F38: 標記
A39: 美光 | B39: MU | C39: =877.55/173 -> 5.0725434 | D39: 2026-10-23 | E39: 現價 877.55 ÷ MarketScreener FY2027 共識 EPS 173（micron/ 模型 In 頁） | F39: Interested-party
A40: SK 海力士 | B40: 000660.KS | C40: =1277000/475721 -> 2.6843465 | D40: 2026-10-23 | E40: 現價 ÷ MarketScreener 2027 共識 EPS（skhynix/ 模型 In 頁） | F40: Interested-party
A41: 三星電子 | B41: 005930.KS | C41: =215500/72279 -> 2.9815022 | D41: 2026-10-23 | E41: 現價 ÷ MarketScreener 2027 共識 EPS（samsung/ 模型 In 頁） | F41: Interested-party
A42: SanDisk | B42: SNDK | C42: =1238.03/217.4 -> 5.6947102 | D42: 2026-10-23 | E42: 現價 1,238.03 ÷ MarketScreener FY2027（2027-06）共識 EPS 217.4 | F42: Interested-party
A43: Western Digital | B43: WDC | C43: 11.91 | D43: 2026-10-23 | E43: stockanalysis 統計頁 Forward P/E（硬碟為主，參考） | F43: Interested-party
A44: 同業前瞻 P/E 中位數（並列參考） | B44: =MEDIAN(C39:C43) -> 5.0725434
A45: Comparable（P/E 並列參考）＝中位數 × 12 個月後前瞻 EPS | B45: =B44*B35 -> 17063.775 | E45: 不進目標價：高峰期 EPS × 低倍數，與 P/B 法互相對照
A47: 0.3 結論
A48: 項目 | B48: 數值 | E48: 說明
A49: 目標價（DCF 與 Comparable 加權） | B49: =tp_w_dcf*B24+(1-tp_w_dcf)*B34 -> 22268.388 | E49: tp_w_dcf × DCF 目標價＋（1 − tp_w_dcf）× Comparable 目標價；tp_w_dcf 見 In 頁
A50: Comparable 目標價（市場主流同業法） | B50: =B34 -> 20356.682 | E50: 引用 0.2（前瞻 P/B）
A51: 市場共識目標價 | B51: =cons_tp -> 36929.23 | E51: MarketScreener（16 位，2026-10-16 收盤時）：平均 ¥36,929（最低 16,333、最高 66,667；分割後）；stockanalysis（16 位，09-09）分割調整後 ¥37,085
A52: 上檔空間：加權目標價 | B52: =B49/px-1 -> 0.74585558 | E52: 現價＝In 頁 px（2026-10-23 收盤）
A53: 上檔空間：Comparable 目標價 | B53: =B50/px-1 -> 0.5959766
A54: 上檔空間級距 | B54: =IF(B52>0.5,"大於 50%",IF(B52>0.25,"25%–50%",IF(B52>=0,"0%–25%",IF(B52>=-0.25,"0%～−25%",IF(B52>=-0.5,"−25%～−50%","小於 −50%"))))) -> 大於 50% | E54: 以「上檔空間：加權目標價」分六級（Andy 2026-10-25 14:00）
A55: 投資建議 | B55: =IF(B52>0.5,"強力買進",IF(B52>0.25,"買進",IF(B52>=-0.25,"中立",IF(B52>=-0.5,"放空","強力放空")))) -> 強力買進 | E55: 依上檔空間固定規則（Andy 2026-10-25 14:17）：>+50% 強力買進、+25～+50% 買進、−25～+25% 中立、−50～−25% 放空、<−50% 強力放空
A56: DCF ÷ 現價 | B56: =B23/px -> 3.6053164 | C56: =C23/px -> 1.3556153 | D56: =D23/px -> 0.68166009 | E56: 各情境 DCF 價值（推到 12 個月後）÷ 現價（A／B／C）
A57: 與市場共識目標價的差距：EPS 因素（記憶體以每股淨值計） | B57: =B33/(0.25*cons_bv27+0.75*cons_bv28)-1 -> -0.11182643 | E57: 本模型約 2028 年底每股淨值（情境加權）÷ 共識（¼ FY2027＋¾ FY2028 年底）− 1（Comparable 用 P/B，故以每股淨值代 EPS）
A58: 對照：前瞻 EPS ÷ 共識前瞻 EPS − 1 | B58: =B35/(5/12*cons_eps27+7/12*cons_eps28)-1 -> -0.35540077 | E58: 共識前瞻 EPS＝5／12 × FY2027 4,871＋7／12 × FY2028 5,467（MarketScreener）
A59: 與市場共識目標價的差距：倍數因素 | B59: =(cons_tp/(0.25*cons_bv27+0.75*cons_bv28))/B32-1 -> 0.61124327 | E59: ="共識目標價隱含 P/B "&TEXT(cons_tp/(0.25*cons_bv27+0.75*cons_bv28),"0.00")&"x（÷ 共識約 2028 年底每股淨值），同業中位數 "&TEXT(B32,"0.00")&"x" -> 共識目標價隱含 P/B 3.39x（÷ 共識約 2028 年底每股淨值），同業中位數 2.10x
A60: 價格帶（DCF 不如預期～順利） | B60: =TEXT(D23,"#,##0")&"～"&TEXT(B23,"#,##0") -> 8,695～45,986 | E60: C 情境價值～A 情境價值（推到 12 個月後）
A61: 歷史倍數檢查：現價隱含 P/B 的十年分位（A／B／C） | B61: =IF(px/PL!F11>=MAX($B$95:$B$104),1,IF(px/PL!F11<=MIN($B$95:$B$104),0,PERCENTRANK($B$95:$B$104,px/PL!F11))) -> 0 | C61: =IF(px/PL!F21>=MAX($B$95:$B$104),1,IF(px/PL!F21<=MIN($B$95:$B$104),0,PERCENTRANK($B$95:$B$104,px/PL!F21))) -> 0.357 | D61: =IF(px/PL!F31>=MAX($B$95:$B$104),1,IF(px/PL!F31<=MIN($B$95:$B$104),0,PERCENTRANK($B$95:$B$104,px/PL!F31))) -> 0.406 | E61: 現價 ÷ 各情境 FY2028 年底每股淨值，在 2016–2025 年底 P/B（第 6 節，美光 Analogy）分布的分位（高於最大值記 100%、低於最小值記 0%）；只作檢查，不進目標價
A62: 目標價方法 | B62: DCF：股東現金流 FY2027–FY2029 用每股（淨利＋折舊－資本支出；資本支出 ¥470B／年，TrendForce），FY2030–FY2032 收斂期用 EPS ×（1 − g／ROE），r 10%、g 4%、ROE 為 FY2024–FY2025 平均；明確期＋永續，基準日 2026 年底。Comparable：美光、SK 海力士、三星、SanDisk 前瞻 P/B 中位數 × 約 2028 年底每股淨值（情境加權）；P/E 並列參考不進目標價。偏誤：FY2027–FY2029 為高峰期盈餘、收斂期淨利率以美光十年平均代替；營收以美元計、成本以日圓計，日圓貶值（匯率）使盈餘偏高。
A80: 5. 目前倍數（僅供參考）
A81: 項目 | B81: A／數值 | C81: B | D81: C | E81: 備註
A82: 現價（2026-10-23 收盤） | B82: =px -> 12755 | E82: stockanalysis（分割後）
A83: P/E：現價 ÷ FY2025 EPS 341.4 | B83: =px/a25_eps -> 37.360867 | E83: 落後（分割後）
A84: P/B：現價 ÷ 2026-06-30 每股淨值 | B84: =px/(eq_j/sh0*1000) -> 8.7217819 | E84: 權益 2,404.3 ÷ 1,644.0 百萬股
A85: 現價 ÷ FY2027 EPS（模型） | B85: =px/PL!E10 -> 2.4467316 | C85: =px/PL!E20 -> 2.992889 | D85: =px/PL!E30 -> 3.1401831 | E85: A／B／C
A86: 現價 ÷ FY2028 EPS（模型） | B86: =px/PL!F10 -> 2.246509 | C86: =px/PL!F20 -> 8.8030118 | D86: =px/PL!F30 -> 21.333542 | E86: A／B／C
A87: 現價 ÷ FY2028 年底每股淨值（模型） | B87: =px/PL!F11 -> 0.92029957 | C87: =px/PL!F21 -> 1.4130738 | D87: =px/PL!F31 -> 1.5858634 | E87: A／B／C；第 0 節歷史分位檢查用
A90: 6. 十年倍數與規則值（2016–2025 年底；見頂年 25 分位、中段中位數、谷底 75 分位）
A91: 規則（Andy 2026-10-13）：合理倍數＝2016–2025 年底倍數依循環位置取分位。Kioxia 無十年自身歷史，以美光為 Analogy（同為記憶體循環股；差異：美光 DRAM 為主）。見頂與中段用 FY2027 A、谷底用 FY2028 C。
A93: P/B（主）：十年歷史倍數
A94: 年底 | B94: 美光（Analogy；會計年度 8 月底） | C94: 標記／說明
A95: 2016 | B95: 1.29 | C95: 美光（Analogy；會計年度 8 月底）：Analogy
A96: 2017 | B96: 1.78 | C96: 來源：micron/dist/20261025_美光模型_v0.4.xlsx｜Val!B82:B91（macrotrends）；Kioxia 自身 2024-12 上市，2024、2025 年底倍數未找到
A97: 2018 | B97: 1.79
A98: 2019 | B98: 1.33
A99: 2020 | B99: 1.27
A100: 2021 | B100: 1.83
A101: 2022 | B101: 1.22
A102: 2023 | B102: 1.72
A103: 2024 | B103: 2.35
A104: 2025 | B104: 2.46
A105: 25 分位（各來源） | B105: =PERCENTILE(B95:B104,0.25) -> 1.3
A106: 中位數（各來源） | B106: =MEDIAN(B95:B104) -> 1.75
A107: 75 分位（各來源） | B107: =PERCENTILE(B95:B104,0.75) -> 1.82
A108: 最小（各來源） | B108: =MIN(B95:B104) -> 1.22
A109: 最大（各來源） | B109: =MAX(B95:B104) -> 2.46
A110: 採用 25 分位（P/B） | B110: =ROUND(AVERAGE(B105),2) -> 1.3
A111: 採用 中位數（P/B） | B111: =ROUND(AVERAGE(B106),2) -> 1.75
A112: 採用 75 分位（P/B） | B112: =ROUND(AVERAGE(B107),2) -> 1.82
A113: 採用 最小（P/B） | B113: =ROUND(MIN(B108),2) -> 1.22
A114: 採用 最大（P/B） | B114: =ROUND(MAX(B109),2) -> 2.46
A116: P/B（主）：規則值
A117: 情形 | B117: 循環位置 | C117: 倍數 | D117: 基準 | E117: 每股基準 | F117: 隱含股價 | G117: 相對目前 | H117: 現價 ÷ 基準
A118: 規則值：見頂（P/B） | B118: 見頂年 → 25 分位 | C118: =B110 -> 1.3 | D118: FY2027 年底每股淨值（A） | E118: =PL!E70 -> 8490.6974 | F118: =C118*E118 -> 11037.907 | G118: =F118/px-1 -> -0.1346212 | H118: =px/E118 -> 1.5022323
A119: 規則值：中段（P/B） | B119: 中段 → 中位數 | C119: =B111 -> 1.75 | D119: FY2027 年底每股淨值（A） | E119: =PL!E70 -> 8490.6974 | F119: =C119*E119 -> 14858.72 | G119: =F119/px-1 -> 0.164933 | H119: =px/E119 -> 1.5022323
A120: 規則值：谷底（P/B） | B120: 谷底 → 75 分位 | C120: =B112 -> 1.82 | D120: FY2028 年底每股淨值（C） | E120: =PL!F142 -> 8042.9373 | F120: =C120*E120 -> 14638.146 | G120: =F120/px-1 -> 0.14763982 | H120: =px/E120 -> 1.5858634
A123: P/E（對照）：十年歷史倍數
A124: 年底 | B124: 美光（Analogy；SEC 10-K 換算） | C124: 標記／說明
A125: 2016 | C125: 美光（Analogy；SEC 10-K 換算）：Analogy
A126: 2017 | B126: 6.5131421 | C126: 來源：micron/dist/20261025_美光模型_v0.4.xlsx｜Val!B115:B124；虧損年不計
A127: 2018 | B127: 4.0895833
...

Sheet Recon
A1: Recon — 本模型 vs 公司實績、指引與共識（共識只作對照，未用於校準）。差距＝模型 ÷ 對照 − 1（百分點列為相減）
A3: 項目 | B3: 對照值 | C3: 模型 A | D3: 差距 A | E3: 模型 B | F3: 差距 B | G3: 模型 C | H3: 差距 C | I3: 對照來源 | J3: 說明
A4: A. 實績與公司指引
A5: FY2025 營收（四季合計）vs 公司 2,337.6 | B5: 2337.6 | C5: =PL!C5 -> 2337.6 | D5: =C5/B5-1 -> 0 | E5: =PL!C15 -> 2337.6 | F5: =E5/B5-1 -> 0 | G5: =PL!C25 -> 2337.6 | H5: =G5/B5-1 -> 0 | I5: storagenewsletter 轉載 FY25 決算；MarketScreener
A6: FY2026 上半營收 vs 公司指引 4,157.1 | B6: 4157.1 | C6: =PL!C44+PL!D44 -> 4157.1 | D6: =C6/B6-1 -> 0 | E6: =PL!C80+PL!D80 -> 4157.1 | F6: =E6/B6-1 -> 0 | G6: =PL!C116+PL!D116 -> 4157.1 | H6: =G6/B6-1 -> 0 | I6: Kioxia FY2026 第一季財報（2026-07-31） | J6: 恆等式
A7: FY2026 第三季營收（推導）vs 第二季指引（季增） | B7: =g2_rev -> 2390 | C7: =PL!E44 -> 2908.9555 | D7: =C7/B7-1 -> 0.21713619 | E7: =PL!E80 -> 2908.9555 | F7: =E7/B7-1 -> 0.21713619 | G7: =PL!E116 -> 2908.9555 | H7: =G7/B7-1 -> 0.21713619 | I7: 公司第二季指引 | J7: 市場層 2026Q4 季價 +17.5%（markets/memory）
A8: FY2026 第二季毛利率（校準值）vs 第一季（百分點） | B8: =q1_gp/q1_rev -> 0.78099711 | C8: =PL!D47 -> 0.82008368 | D8: =C8-B8 -> 0.039086568 | E8: =PL!D83 -> 0.82008368 | F8: =E8-B8 -> 0.039086568 | G8: =PL!D119 -> 0.82008368 | H8: =G8-B8 -> 0.039086568 | I8: Kioxia FY2026 第一季財報（2026-07-31） | J8: 第二季營業費用為 Assumed（g2_ox）
A9: B. 共識（MarketScreener 2026-10-25 擷取；只作參考）
A10: FY2026 營收 vs 共識 | B10: =cons_rev26 -> 10071.4 | C10: =PL!D5 -> 10271.368 | D10: =C10/B10-1 -> 0.019855074 | E10: =PL!D15 -> 10296.2 | F10: =E10/B10-1 -> 0.022320661 | G10: =PL!D25 -> 10258.793 | H10: =G10/B10-1 -> 0.018606464 | I10: MarketScreener 預估頁（2026-10-25 擷取；頁面為 10-16 收盤；會計年度 3 月；每股數字已依分割調整，股數 1,644 百萬股）
A11: FY2026 淨利 vs 共識 | B11: =cons_ni26 -> 5573.9 | C11: =PL!D9 -> 5543.9096 | D11: =C11/B11-1 -> -0.0053805017 | E11: =PL!D19 -> 5558.9301 | F11: =E11/B11-1 -> -0.0026857085 | G11: =PL!D29 -> 5532.1994 | H11: =G11/B11-1 -> -0.0074813991 | I11: MarketScreener 預估頁（2026-10-25 擷取；頁面為 10-16 收盤；會計年度 3 月；每股數字已依分割調整，股數 1,644 百萬股）
A12: FY2026 EPS vs 共識 | B12: =cons_eps26 -> 3486 | C12: =PL!D10 -> 3491.5112 | D12: =C12/B12-1 -> 0.0015809424 | E12: =PL!D20 -> 3501.4903 | F12: =E12/B12-1 -> 0.0044435867 | G12: =PL!D30 -> 3483.7333 | H12: =G12/B12-1 -> -0.00065022494 | I12: MarketScreener 預估頁（2026-10-25 擷取；頁面為 10-16 收盤；會計年度 3 月；每股數字已依分割調整，股數 1,644 百萬股） | J12: 差距超過 30% 見 README
A13: FY2027 營收 vs 共識 | B13: =cons_rev27 -> 13477.2 | C13: =PL!E5 -> 13504.346 | D13: =C13/B13-1 -> 0.0020142168 | E13: =PL!E15 -> 11553.093 | F13: =E13/B13-1 -> -0.14276753 | G13: =PL!E25 -> 11123.476 | H13: =G13/B13-1 -> -0.17464486 | I13: MarketScreener 預估頁（2026-10-25 擷取；頁面為 10-16 收盤；會計年度 3 月；每股數字已依分割調整，股數 1,644 百萬股）
A14: FY2027 EPS vs 共識 | B14: =cons_eps27 -> 4871 | C14: =PL!E10 -> 5213.0769 | D14: =C14/B14-1 -> 0.070227245 | E14: =PL!E20 -> 4261.7685 | F14: =E14/B14-1 -> -0.12507319 | G14: =PL!E30 -> 4061.865 | H14: =G14/B14-1 -> -0.16611271 | I14: MarketScreener 預估頁（2026-10-25 擷取；頁面為 10-16 收盤；會計年度 3 月；每股數字已依分割調整，股數 1,644 百萬股）
A15: FY2028 EPS vs 共識 | B15: =cons_eps28 -> 5467 | C15: =PL!F10 -> 5677.6981 | D15: =C15/B15-1 -> 0.038539987 | E15: =PL!F20 -> 1448.9359 | F15: =E15/B15-1 -> -0.73496691 | G15: =PL!F30 -> 597.88476 | H15: =G15/B15-1 -> -0.8906375 | I15: MarketScreener 預估頁（2026-10-25 擷取；頁面為 10-16 收盤；會計年度 3 月；每股數字已依分割調整，股數 1,644 百萬股）
A16: FY2027 年底每股淨值 vs 共識 | B16: =cons_bv27 -> 7808 | C16: =PL!E11 -> 8490.6974 | D16: =C16/B16-1 -> 0.087435625 | E16: =PL!E21 -> 7669.973 | F16: =E16/B16-1 -> -0.017677636 | G16: =PL!E31 -> 7480.0806 | H16: =G16/B16-1 -> -0.041997873 | I16: MarketScreener 預估頁（2026-10-25 擷取；頁面為 10-16 收盤；會計年度 3 月；每股數字已依分割調整，股數 1,644 百萬股）
A17: C. 市場層一致性
A18: Kioxia 營收 ÷ 市場層（公司口徑係數 kx_k） | C18: =kx_k -> 1.0302589 | I18: In 頁
A19: Kioxia＋SanDisk 合資群份額 CY2027（市場層 Ann 頁，A／B／C） | C19: 0.26205287 | E19: 0.25905287 | G19: 0.25605287 | I19: markets/nand/dist/20261025_NAND市場模型_v0.1.xlsx｜Ann!F27（sndk/ 模型讀同一組列）

Sheet Sens
A1: Sens — 一次動一個輸入（情境 A）：對 FY2027、FY2028 營收與 EPS 的影響。每個案例為一個完整推導區塊（本頁下方，與 PL 同一引擎）
A3: 案例 | B3: 設定 | C3: FY2027 營收 ¥B | D3: FY2027 EPS | E3: 相對基準 | F3: FY2028 營收 ¥B | G3: FY2028 EPS | H3: 相對基準 | I3: FY2027 毛利率
A4: 基準（情境 A） | B4: PL 區塊 A | C4: =PL!E55 -> 13504.346 | D4: =PL!E69 -> 5213.0769 | E4: =D4/D$4-1 -> 0 | F4: =PL!F55 -> 13616.69 | G4: =PL!F69 -> 5677.6981 | H4: =G4/G$4-1 -> 0 | I4: =PL!E57 -> 0.86131944
A5: 市場層營收 −20%（價格；第三季起） | B5: 價格係數 0.8 | C5: =E75 -> 10803.477 | D5: =E89 -> 3864.0987 | E5: =D5/D$4-1 -> -0.25876814 | F5: =F75 -> 10893.352 | G5: =F89 -> 4097.4803 | H5: =G5/G$4-1 -> -0.27832015 | I5: =E77 -> 0.82664929
A6: 市場層營收 +20%（價格） | B6: 價格係數 1.2 | C6: =E125 -> 16205.215 | D6: =E139 -> 6640.4114 | E6: =D6/D$4-1 -> 0.27379886 | F6: =F125 -> 16340.028 | G6: =F139 -> 7431.6821 | H6: =G6/G$4-1 -> 0.3089252 | I6: =E127 -> 0.88443286
A7: 份額 ×0.9（營收與位元） | B7: 份額係數 0.9 | C7: =E175 -> 12153.911 | D7: =E189 -> 4529.2022 | E7: =D7/D$4-1 -> -0.13118448 | F7: =F175 -> 12255.021 | G7: =F189 -> 4867.5233 | H7: =G7/G$4-1 -> -0.14269424 | I7: =E177 -> 0.84591048
A8: 份額 ×1.1 | B8: 份額係數 1.1 | C8: =E225 -> 14854.781 | D8: =E239 -> 5916.529 | E8: =D8/D$4-1 -> 0.13493991 | F8: =F225 -> 14978.359 | G8: =F239 -> 6531.2259 | H8: =G8/G$4-1 -> 0.1503299 | I8: =E227 -> 0.87392676
A9: 匯率 145 日圓 | B9: fx 低 | C9: =E275 -> 12238.314 | D9: =E289 -> 4571.3862 | E9: =D9/D$4-1 -> -0.1230925 | F9: =F275 -> 12340.126 | G9: =F289 -> 4916.9517 | H9: =G9/G$4-1 -> -0.13398852 | I9: =E277 -> 0.84697317
A10: 匯率 170 日圓 | B10: fx 高 | C10: =E325 -> 14348.368 | D10: =E339 -> 5650.3872 | E10: =D10/D$4-1 -> 0.083887173 | F10: =F325 -> 14467.733 | G10: =F339 -> 6205.8539 | H10: =G10/G$4-1 -> 0.093022865 | I10: =E327 -> 0.86947712
A11: 每位元成本年降 10%（C 的值） | B11: cd_C | C11: =E375 -> 13504.346 | D11: =E389 -> 5162.9908 | E11: =D11/D$4-1 -> -0.0096077911 | F11: =F375 -> 13616.69 | G11: =F389 -> 5560.8523 | H11: =G11/G$4-1 -> -0.020579777 | I11: =E377 -> 0.8539928
A12: 每位元成本年降 18% | B12: cd_A 高 | C12: =E425 -> 13504.346 | D12: =E439 -> 5262.8047 | E12: =D12/D$4-1 -> 0.0095390522 | F12: =F425 -> 13616.69 | G12: =F439 -> 5789.1901 | H12: =G12/G$4-1 -> 0.019636838 | I12: =E427 -> 0.86857831
A13: 第二季營業費用 55（校準） | B13: g2_ox 低 | C13: =E475 -> 13504.346 | D13: =E489 -> 5213.8335 | E13: =D13/D$4-1 -> 0.00014514198 | F13: =F475 -> 13616.69 | G13: =F489 -> 5679.7412 | H13: =G13/G$4-1 -> 0.00035983769 | I13: =E477 -> 0.85648174
A14: 第二季營業費用 90 | B14: g2_ox 高 | C14: =E525 -> 13504.346 | D14: =E539 -> 5212.0681 | E14: =D14/D$4-1 -> -0.00019351667 | F14: =F525 -> 13616.69 | G14: =F539 -> 5674.9743 | H14: =G14/G$4-1 -> -0.00047973588 | I14: =E527 -> 0.86776969
A15: 營業費用變動率 2% | B15: ox_var 高 | C15: =E575 -> 13504.346 | D15: =E589 -> 5198.3071 | E15: =D15/D$4-1 -> -0.0028332141 | F15: =F575 -> 13616.69 | G15: =F589 -> 5665.3403 | H15: =G15/G$4-1 -> -0.0021765445 | I15: =E577 -> 0.86131944
A16: 稅率 35% | B16: tax 高 | C16: =E625 -> 13504.346 | D16: =E639 -> 4956.6316 | E16: =D16/D$4-1 -> -0.049192691 | F16: =F625 -> 13616.69 | G16: =F639 -> 5373.5076 | H16: =G16/G$4-1 -> -0.053576385 | I16: =E627 -> 0.86131944
A17: 稅率 28% | B17: tax 低 | C17: =E675 -> 13504.346 | D17: =E689 -> 5559.2897 | E17: =D17/D$4-1 -> 0.066412377 | F17: =F675 -> 13616.69 | G17: =F689 -> 6092.8396 | H17: =G17/G$4-1 -> 0.073117921 | I17: =E677 -> 0.86131944
A18: 股東回饋 ÷ FCF 50% | B18: payout 高 | C18: =E725 -> 13504.346 | D18: =E739 -> 6456.9398 | E18: =D18/D$4-1 -> 0.23860437 | F18: =F725 -> 13616.69 | G18: =F739 -> 8584.5118 | H18: =G18/G$4-1 -> 0.51197045 | I18: =E727 -> 0.86131944
A19: 股東回饋 0 | B19: payout 低 | C19: =E775 -> 13504.346 | D19: =E789 -> 4620.1656 | E19: =D19/D$4-1 -> -0.11373538 | F19: =F775 -> 13616.69 | G19: =F789 -> 4634.1536 | H19: =G19/G$4-1 -> -0.18379712 | I19: =E777 -> 0.86131944
A20: 情境 B | B20: markets/nand B；成本年降 12% | C20: =PL!E91 -> 11553.093 | D20: =PL!E105 -> 4261.7685 | E20: =D20/D$4-1 -> -0.18248502 | F20: =PL!F91 -> 5230.9636 | G20: =PL!F105 -> 1448.9359 | H20: =G20/G$4-1 -> -0.74480223 | I20: =PL!E93 -> 0.83811592
A21: 情境 C | B21: markets/nand C；成本年降 10% | C21: =PL!E127 -> 11123.476 | D21: =PL!E141 -> 4061.865 | E21: =D21/D$4-1 -> -0.22083156 | F21: =PL!F127 -> 3183.6657 | G21: =PL!F141 -> 597.88476 | H21: =G21/G$4-1 -> -0.89469592 | I21: =PL!E129 -> 0.83330157
A23: 讀法：第二季為公司指引（固定），價格與匯率係數只作用在第三季起；營業費用校準改變成本起點（第二季營業成本＝營收 − 營業利益 − 營業費用）。
A60: 案例區塊：市場層營收 −20%（價格；第三季起）（情境 A）
A61: A. 季度 | B61: 單位 | C61: FY26 第1季（2026Q2） | D61: FY26 第2季（2026Q3） | E61: FY26 第3季（2026Q4） | F61: FY26 第4季（2027Q1） | G61: FY27 第1季（2027Q2） | H61: FY27 第2季（2027Q3） | I61: FY27 第3季（2027Q4） | J61: FY27 第4季（2028Q1） | K61: FY28 第1季（2028Q2） | L61: FY28 第2季（2028Q3） | M61: FY28 第3季（2028Q4） | N61: FY28 第4季（2029Q1） | O61: FY29 第1季（2029Q2） | P61: FY29 第2季（2029Q3） | Q61: FY29 第3季（2029Q4） | R61: FY29 第4季（2030Q1） | T61: 說明
A62: 市場層營收（TrendForce 口徑，美元，同字母情境） | B62: $B | C62: =Units!H4*1 -> 10.72 | D62: =Units!I4*1 -> 14.319786 | E62: =Units!J4*1*0.8 -> 14.117595 | F62: =Units!K4*1*0.8 -> 15.555862 | G62: =Units!L4*1*0.8 -> 16.448321 | H62: =Units!M4*1*0.8 -> 16.522383 | I62: =Units!N4*1*0.8 -> 16.247373 | J62: =Units!O4*1*0.8 -> 16.32053 | K62: =Units!P4*1*0.8 -> 16.394016 | L62: =Units!Q4*1*0.8 -> 16.467833 | ... R62: =Units!W4*1*0.8 -> 17.232612 | T62: markets/nand；Sens 可乘份額係數、價格係數（第三季起）
A63: 位元（市場層；同字母） | B63: EB | C63: =Units!H7*1 -> 40.175758 | D63: =Units!I7*1 -> 46.666796 | E63: =Units!J7*1 -> 48.944548 | F63: =Units!K7*1 -> 52.360098 | G63: =Units!L7*1 -> 55.364063 | H63: =Units!M7*1 -> 58.540369 | I63: =Units!N7*1 -> 61.898904 | J63: =Units!O7*1 -> 65.450123 | ... R63: =Units!W7*1 -> 94.004556
A64: 營收 | B64: ¥B | C64: =q1_rev -> 1767.1 | D64: =g2_rev -> 2390 | E64: =E62*kx_k*fx -> 2327.1644 | F64: =F62*kx_k*fx -> 2564.2503 | G64: =G62*kx_k*fx -> 2711.3646 | H64: =H62*kx_k*fx -> 2723.5731 | I64: =I62*kx_k*fx -> 2678.2399 | J64: =J62*kx_k*fx -> 2690.2992 | K64: =K62*kx_k*fx -> 2702.4128 | L64: =L62*kx_k*fx -> 2714.581 | ... R64: =R62*kx_k*fx -> 2840.6482 | T64: 第一季實績、第二季公司指引；之後＝市場層 × 公司口徑係數 × 匯率
A65: 每 EB 營業成本（第二季以指引校準，之後每年 × (1 − 成本年降)） | B65: ¥B/EB | C65: =C66/C63 -> 9.6326745 | D65: =D66/D63 -> 9.2142602 | E65: =$D65*(1-cd_A)^(1/4) -> 8.8732984 | F65: =$D65*(1-cd_A)^(2/4) -> 8.5449534 | G65: =$D65*(1-cd_A)^(3/4) -> 8.2287584 | H65: =$D65*(1-cd_A)^(4/4) -> 7.9242638 | I65: =$D65*(1-cd_A)^(5/4) -> 7.6310366 | J65: =$D65*(1-cd_A)^(6/4) -> 7.3486599 | K65: =$D65*(1-cd_A)^(7/4) -> 7.0767322 | L65: =$D65*(1-cd_A)^(8/4) -> 6.8148669 | M65: =$D65*(1-cd_A)^(9/4) -> 6.5626915 | N65: =$D65*(1-cd_A)^(10/4) -> 6.3198475 | O65: =$D65*(1-cd_A)^(11/4) -> 6.0859897 | P65: =$D65*(1-cd_A)^(12/4) -> 5.8607855 | Q65: =$D65*(1-cd_A)^(13/4) -> 5.6439147 | R65: =$D65*(1-cd_A)^(14/4) -> 5.4350689
A66: 營業成本 | B66: ¥B | C66: =q1_rev-q1_gp -> 387 | D66: =g2_rev-g2_op-g2_ox -> 430 | E66: =E63*E65 -> 434.29958 | F66: =F63*F65 -> 447.4146 | G66: =G63*G65 -> 455.5775 | H66: =H63*H65 -> 463.88933 | I66: =I63*I65 -> 472.3528 | J66: =J63*J65 -> 480.97069 | K66: =K63*K65 -> 489.74581 | L66: =L63*L65 -> 498.68103 | ... R66: =R63*R65 -> 510.92124 | T66: 第二季＝指引營收 − 指引營業利益 − 推估營業費用
A67: 毛利率 | B67: % | C67: =1-C66/C64 -> 0.78099711 | D67: =1-D66/D64 -> 0.82008368 | E67: =1-E66/E64 -> 0.81337821 | F67: =1-F66/F64 -> 0.82551836 | G67: =1-G66/G64 -> 0.83197483 | H67: =1-H66/H64 -> 0.82967619 | I67: =1-I66/I64 -> 0.82363313 | J67: =1-J66/J64 -> 0.82122037 | ... R67: =1-R66/R64 -> 0.82013921
A68: 營業費用 | B68: ¥B | C68: =q1_gp-q1_op -> 110.1 | D68: =g2_ox -> 70 | E68: =(g2_ox-ox_var*g2_rev)*(1+ox_g)^(1/4)+ox_var*E64 -> 70.483285 | F68: =(g2_ox-ox_var*g2_rev)*(1+ox_g)^(2/4)+ox_var*F64 -> 73.992591 | G68: =(g2_ox-ox_var*g2_rev)*(1+ox_g)^(3/4)+ox_var*G64 -> 76.629633 | H68: =(g2_ox-ox_var*g2_rev)*(1+ox_g)^(4/4)+ox_var*H64 -> 77.945731 | I68: =(g2_ox-ox_var*g2_rev)*(1+ox_g)^(5/4)+ox_var*I64 -> 78.715204 | J68: =(g2_ox-ox_var*g2_rev)*(1+ox_g)^(6/4)+ox_var*J64 -> 80.088089 | K68: =(g2_ox-ox_var*g2_rev)*(1+ox_g)^(7/4)+ox_var*K64 -> 81.491714 | L68: =(g2_ox-ox_var*g2_rev)*(1+ox_g)^(8/4)+ox_var*L64 -> 82.92681 | M68: =(g2_ox-ox_var*g2_rev)*(1+ox_g)^(9/4)+ox_var*M64 -> 84.394125 | N68: =(g2_ox-ox_var*g2_rev)*(1+ox_g)^(10/4)+ox_var*N64 -> 85.99915 | O68: =(g2_ox-ox_var*g2_rev)*(1+ox_g)^(11/4)+ox_var*O64 -> 87.918721 | P68: =(g2_ox-ox_var*g2_rev)*(1+ox_g)^(12/4)+ox_var*P64 -> 89.881726 | Q68: =(g2_ox-ox_var*g2_rev)*(1+ox_g)^(13/4)+ox_var*Q64 -> 91.889161 | R68: =(g2_ox-ox_var*g2_rev)*(1+ox_g)^(14/4)+ox_var*R64 -> 92.760449 | T68: 固定部分以第二季校準（Derived）
A69: 營業利益 | B69: ¥B | C69: =C64-C66-C68 -> 1270 | D69: =D64-D66-D68 -> 1890 | E69: =E64-E66-E68 -> 1822.3815 | F69: =F64-F66-F68 -> 2042.8431 | G69: =G64-G66-G68 -> 2179.1575 | H69: =H64-H66-H68 -> 2181.738 | I69: =I64-I66-I68 -> 2127.1719 | J69: =J64-J66-J68 -> 2129.2405 | ... R69: =R64-R66-R68 -> 2236.9665
A71: 淨利 | B71: ¥B | C71: =q1_ni -> 842.2 | D71: =g2_ni -> 1270 | E71: =(E69+nonop_q+rf*nc_j/4)*(1-tax) -> 1229.2853 | F71: =(F69+nonop_q+rf*nc_j/4)*(1-tax) -> 1379.1992 | G71: =(G69+nonop_q+rf*$D87/4)*(1-tax) -> 1477.0351 | H71: =(H69+nonop_q+rf*$D87/4)*(1-tax) -> 1478.7899 | I71: =(I69+nonop_q+rf*$D87/4)*(1-tax) -> 1441.6849 | J71: =(J69+nonop_q+rf*$D87/4)*(1-tax) -> 1443.0915 | K71: =(K69+nonop_q+rf*$E87/4)*(1-tax) -> 1452.1465 | L71: =(L69+nonop_q+rf*$E87/4)*(1-tax) -> 1453.369 | M71: =(M69+nonop_q+rf*$E87/4)*(1-tax) -> 1454.496 | N71: =(N69+nonop_q+rf*$E87/4)*(1-tax) -> 1468.508 | O71: =(O69+nonop_q+rf*$F87/4)*(1-tax) -> 1505.6713 | P71: =(P69+nonop_q+rf*$F87/4)*(1-tax) -> 1535.6796 | Q71: =(Q69+nonop_q+rf*$F87/4)*(1-tax) -> 1566.2664 | R71: =(R69+nonop_q+rf*$F87/4)*(1-tax) -> 1531.8072 | T71: （營業利益＋業外＋淨現金 × 收益率 ÷ 4）×（1 − 稅率）；FY2026 用 2026-06-30 淨現金
A72: 季 EPS（稀釋，分割後） | B72: JPY | C72: =C71/(sh0+dil)*1000 -> 507.34333 | D72: =D71/(sh0+dil)*1000 -> 765.0511 | E72: =E71/(sh0+dil)*1000 -> 740.52448 | F72: =F71/(sh0+dil)*1000 -> 830.83296 | G72: =G71/(sh0+dil)*1000 -> 889.76954 | H72: =H71/(sh0+dil)*1000 -> 890.82661 | I72: =I71/(sh0+dil)*1000 -> 868.47451 | J72: =J71/(sh0+dil)*1000 -> 869.32185 | ... R72: =R71/(sh0+dil)*1000 -> 922.76441
A74: B. 年度（會計年度） | B74: 單位 | C74: FY2025A | D74: FY2026 | E74: FY2027 | F74: FY2028 | G74: FY2029 | T74: 說明
A75: 營收 | B75: ¥B | C75: =a25_rev -> 2337.6 | D75: =SUM(C64:F64) -> 9048.5147 | E75: =SUM(G64:J64) -> 10803.477 | F75: =SUM(K64:N64) -> 10893.352 | G75: =SUM(O64:R64) -> 11398.395 | T75: FY2026＝第一季實績＋第二季指引＋第三、四季推導
A76: 營業成本 | B76: ¥B | C76: =a25_rev-(p1_gp+p2_gp+p3_gp+p4_gp) -> 1324.8 | D76: =SUM(C66:F66) -> 1698.7142 | E76: =SUM(G66:J66) -> 1872.7903 | F76: =SUM(K66:N66) -> 2004.525 | G76: =SUM(O66:R66) -> 2070.1443
A77: 毛利率 | B77: % | C77: =1-C76/C75 -> 0.43326489 | D77: =1-D76/D75 -> 0.81226596 | E77: =1-E76/E75 -> 0.82664929 | F77: =1-F76/F75 -> 0.8159864 | G77: =1-G76/G75 -> 0.81838283
A78: 營業費用 | B78: ¥B | D78: =SUM(C68:F68) -> 324.57588 | E78: =SUM(G68:J68) -> 313.37866 | F78: =SUM(K68:N68) -> 334.8118 | G78: =SUM(O68:R68) -> 362.45006
A79: 營業利益 | B79: ¥B | C79: =p1_op+p2_op+p3_op+p4_op -> 869 | D79: =SUM(C69:F69) -> 7025.2247 | E79: =SUM(G69:J69) -> 8617.3078 | F79: =SUM(K69:N69) -> 8554.0154 | G79: =SUM(O69:R69) -> 8965.8007
A80: 營業利益率 | B80: % | C80: =C79/C75 -> 0.3717488 | D80: =D79/D75 -> 0.77639534 | E80: =E79/E75 -> 0.79764209 | F80: =F79/F75 -> 0.78525097 | G80: =G79/G75 -> 0.78658448
A81: 淨利 | B81: ¥B | C81: =a25_ni -> 554.5 | D81: =SUM(C71:F71) -> 4720.6845 | E81: =SUM(G71:J71) -> 5840.6014 | F81: =SUM(K71:N71) -> 5828.5194 | G81: =SUM(O71:R71) -> 6139.4246
A82: 折舊攤銷 | B82: ¥B | D82: =da_y -> 320 | E82: =da_y -> 320 | F82: =da_y -> 320 | G82: =da_y -> 320
A83: 資本支出（含合資廠分攤） | B83: ¥B | D83: =cap_2026 -> 450 | E83: =cap_2027 -> 470 | F83: =cap_2028 -> 470 | G83: =cap_2029 -> 470
A84: 自由現金流（淨利＋折舊 − 資本支出） | B84: ¥B | D84: =D81+D82-D83 -> 4590.6845 | E84: =E81+E82-E83 -> 5690.6014 | F84: =F81+F82-F83 -> 5678.5194 | G84: =G81+G82-G83 -> 5989.4246
A85: 股東回饋（以買回計） | B85: ¥B | D85: =MAX(0,payout*(SUM(D71:F71)+0.75*(D82-D83))) -> 756.19691 | E85: =MAX(0,payout*E84) -> 1138.1203 | F85: =MAX(0,payout*F84) -> 1135.7039 | G85: =MAX(0,payout*G84) -> 1197.8849 | T85: FY2026 只計 2026-07 以後三季的自由現金流
A86: 期末權益 | B86: ¥B | C86: =eq25 -> 1399.1 | D86: =eq_j+SUM(D71:F71)-D85 -> 5526.5876 | E86: =D86+E81-E85 -> 10229.069 | F86: =E86+F81-F85 -> 14921.884 | G86: =F86+G81-G85 -> 19863.424 | T86: FY2026＝2026-06-30 權益＋第二至四季淨利 − 回饋（不含其他綜合損益）
A87: 期末淨現金 | B87: ¥B | D87: =nc_j+(SUM(D71:F71)+0.75*(D82-D83))-D85 -> 3181.1876 | E87: =D87+E84-E85 -> 7733.6687 | F87: =E87+F84-F85 -> 12276.484 | G87: =F87+G84-G85 -> 17068.024
A88: 期末流通股數（分割後） | B88: 百萬股 | D88: =sh0-D85/bb_px*1000 -> 1584.7576 | E88: =D88-E85/bb_px*1000 -> 1495.5283 | F88: =E88-F85/bb_px*1000 -> 1406.4884 | G88: =F88-G85/bb_px*1000 -> 1312.5734
A89: EPS（稀釋：期末流通股數＋dil；分割後） | B89: JPY | C89: =a25_eps -> 341.4 | D89: =D81/(D88+dil)*1000 -> 2949.0758 | E89: =E81/(E88+dil)*1000 -> 3864.0987 | F89: =F81/(F88+dil)*1000 -> 4097.4803 | G89: =G81/(G88+dil)*1000 -> 4621.149
A90: 每股淨值 BVPS（期末流通股數） | B90: JPY | D90: =D86/D88*1000 -> 3487.3394 | E90: =E86/E88*1000 -> 6839.7696 | F90: =F86/F88*1000 -> 10609.319 | G90: =G86/G88*1000 -> 15133.191
A91: ROE（期末權益） | B91: % | D91: =D81/D86 -> 0.85417709 | E91: =E81/E86 -> 0.57098076 | F91: =F81/F86 -> 0.39060211 | G91: =G81/G86 -> 0.30908189
A92: 每股自由現金流（稀釋） | B92: JPY | E92: =E84/(E88+dil)*1000 -> 3764.8598 | F92: =F84/(F88+dil)*1000 -> 3992.0295 | G92: =G84/(G88+dil)*1000 -> 4508.2439
A93: 檢查：FY2025 營收、淨利 − 四季合計；第一季、第二季 − 實績與指引（應為 0） | B93: ¥B | D93: =ABS(C64-q1_rev)+ABS(D69-g2_op)+ABS(C75-2337.6) -> 0
A110: 案例區塊：市場層營收 +20%（價格）（情境 A）
A111: A. 季度 | B111: 單位 | C111: FY26 第1季（2026Q2） | D111: FY26 第2季（2026Q3） | E111: FY26 第3季（2026Q4） | F111: FY26 第4季（2027Q1） | G111: FY27 第1季（2027Q2） | H111: FY27 第2季（2027Q3） | I111: FY27 第3季（2027Q4） | J111: FY27 第4季（2028Q1） | K111: FY28 第1季（2028Q2） | L111: FY28 第2季（2028Q3） | M111: FY28 第3季（2028Q4） | N111: FY28 第4季（2029Q1） | O111: FY29 第1季（2029Q2） | P111: FY29 第2季（2029Q3） | Q111: FY29 第3季（2029Q4） | R111: FY29 第4季（2030Q1） | T111: 說明
A112: 市場層營收（TrendForce 口徑，美元，同字母情境） | B112: $B | C112: =Units!H4*1 -> 10.72 | D112: =Units!I4*1 -> 14.319786 | E112: =Units!J4*1*1.2 -> 21.176393 | F112: =Units!K4*1*1.2 -> 23.333793 | G112: =Units!L4*1*1.2 -> 24.672482 | H112: =Units!M4*1*1.2 -> 24.783575 | I112: =Units!N4*1*1.2 -> 24.371059 | J112: =Units!O4*1*1.2 -> 24.480794 | K112: =Units!P4*1*1.2 -> 24.591024 | L112: =Units!Q4*1*1.2 -> 24.70175 | ... R112: =Units!W4*1*1.2 -> 25.848918 | T112: markets/nand；Sens 可乘份額係數、價格係數（第三季起）
A113: 位元（市場層；同字母） | B113: EB | C113: =Units!H7*1 -> 40.175758 | D113: =Units!I7*1 -> 46.666796 | E113: =Units!J7*1 -> 48.944548 | F113: =Units!K7*1 -> 52.360098 | G113: =Units!L7*1 -> 55.364063 | H113: =Units!M7*1 -> 58.540369 | I113: =Units!N7*1 -> 61.898904 | J113: =Units!O7*1 -> 65.450123 | ... R113: =Units!W7*1 -> 94.004556
A114: 營收 | B114: ¥B | C114: =q1_rev -> 1767.1 | D114: =g2_rev -> 2390 | E114: =E112*kx_k*fx -> 3490.7466 | F114: =F112*kx_k*fx -> 3846.3755 | G114: =G112*kx_k*fx -> 4067.0469 | H114: =H112*kx_k*fx -> 4085.3596 | I114: =I112*kx_k*fx -> 4017.3599 | J114: =J112*kx_k*fx -> 4035.4489 | K114: =K112*kx_k*fx -> 4053.6193 | L114: =L112*kx_k*fx -> 4071.8715 | ... R114: =R112*kx_k*fx -> 4260.9723 | T114: 第一季實績、第二季公司指引；之後＝市場層 × 公司口徑係數 × 匯率
A115: 每 EB 營業成本（第二季以指引校準，之後每年 × (1 − 成本年降)） | B115: ¥B/EB | C115: =C116/C113 -> 9.6326745 | D115: =D116/D113 -> 9.2142602 | E115: =$D115*(1-cd_A)^(1/4) -> 8.8732984 | F115: =$D115*(1-cd_A)^(2/4) -> 8.5449534 | G115: =$D115*(1-cd_A)^(3/4) -> 8.2287584 | H115: =$D115*(1-cd_A)^(4/4) -> 7.9242638 | I115: =$D115*(1-cd_A)^(5/4) -> 7.6310366 | J115: =$D115*(1-cd_A)^(6/4) -> 7.3486599 | K115: =$D115*(1-cd_A)^(7/4) -> 7.0767322 | L115: =$D115*(1-cd_A)^(8/4) -> 6.8148669 | M115: =$D115*(1-cd_A)^(9/4) -> 6.5626915 | N115: =$D115*(1-cd_A)^(10/4) -> 6.3198475 | O115: =$D115*(1-cd_A)^(11/4) -> 6.0859897 | P115: =$D115*(1-cd_A)^(12/4) -> 5.8607855 | Q115: =$D115*(1-cd_A)^(13/4) -> 5.6439147 | R115: =$D115*(1-cd_A)^(14/4) -> 5.4350689
A116: 營業成本 | B116: ¥B | C116: =q1_rev-q1_gp -> 387 | D116: =g2_rev-g2_op-g2_ox -> 430 | E116: =E113*E115 -> 434.29958 | F116: =F113*F115 -> 447.4146 | G116: =G113*G115 -> 455.5775 | H116: =H113*H115 -> 463.88933 | I116: =I113*I115 -> 472.3528 | J116: =J113*J115 -> 480.97069 | K116: =K113*K115 -> 489.74581 | L116: =L113*L115 -> 498.68103 | ... R116: =R113*R115 -> 510.92124 | T116: 第二季＝指引營收 − 指引營業利益 − 推估營業費用
A117: 毛利率 | B117: % | C117: =1-C116/C114 -> 0.78099711 | D117: =1-D116/D114 -> 0.82008368 | E117: =1-E116/E114 -> 0.87558547 | F117: =1-F116/F114 -> 0.88367891 | G117: =1-G116/G114 -> 0.88798322 | H117: =1-H116/H114 -> 0.8864508 | I117: =1-I116/I114 -> 0.88242208 | J117: =1-J116/J114 -> 0.88081358 | ... R117: =1-R116/R114 -> 0.8800928
A118: 營業費用 | B118: ¥B | C118: =q1_gp-q1_op -> 110.1 | D118: =g2_ox -> 70 | E118: =(g2_ox-ox_var*g2_rev)*(1+ox_g)^(1/4)+ox_var*E114 -> 82.119107 | F118: =(g2_ox-ox_var*g2_rev)*(1+ox_g)^(2/4)+ox_var*F114 -> 86.813843 | G118: =(g2_ox-ox_var*g2_rev)*(1+ox_g)^(3/4)+ox_var*G114 -> 90.186456 | H118: =(g2_ox-ox_var*g2_rev)*(1+ox_g)^(4/4)+ox_var*H114 -> 91.563596 | I118: =(g2_ox-ox_var*g2_rev)*(1+ox_g)^(5/4)+ox_var*I114 -> 92.106404 | J118: =(g2_ox-ox_var*g2_rev)*(1+ox_g)^(6/4)+ox_var*J114 -> 93.539585 | K118: =(g2_ox-ox_var*g2_rev)*(1+ox_g)^(7/4)+ox_var*K114 -> 95.003778 | L118: =(g2_ox-ox_var*g2_rev)*(1+ox_g)^(8/4)+ox_var*L114 -> 96.499715 | M118: =(g2_ox-ox_var*g2_rev)*(1+ox_g)^(9/4)+ox_var*M114 -> 98.028145 | N118: =(g2_ox-ox_var*g2_rev)*(1+ox_g)^(10/4)+ox_var*N114 -> 99.746922 | O118: =(g2_ox-ox_var*g2_rev)*(1+ox_g)^(11/4)+ox_var*O114 -> 101.92091 | P118: =(g2_ox-ox_var*g2_rev)*(1+ox_g)^(12/4)+ox_var*P114 -> 104.14304 | Q118: =(g2_ox-ox_var*g2_rev)*(1+ox_g)^(13/4)+ox_var*Q114 -> 106.41439 | R118: =(g2_ox-ox_var*g2_rev)*(1+ox_g)^(14/4)+ox_var*R114 -> 106.96369 | T118: 固定部分以第二季校準（Derived）
A119: 營業利益 | B119: ¥B | C119: =C114-C116-C118 -> 1270 | D119: =D114-D116-D118 -> 1890 | E119: =E114-E116-E118 -> 2974.3279 | F119: =F114-F116-F118 -> 3312.147 | G119: =G114-G116-G118 -> 3521.2829 | H119: =H114-H116-H118 -> 3529.9067 | I119: =I114-I116-I118 -> 3452.9007 | J119: =J114-J116-J118 -> 3460.9386 | ... R119: =R114-R116-R118 -> 3643.0873
A121: 淨利 | B121: ¥B | C121: =q1_ni -> 842.2 | D121: =g2_ni -> 1270 | E121: =(E119+nonop_q+rf*nc_j/4)*(1-tax) -> 2012.6089 | F121: =(F119+nonop_q+rf*nc_j/4)*(1-tax) -> 2242.3259 | G121: =(G119+nonop_q+rf*$D137/4)*(1-tax) -> 2391.9196 | H121: =(H119+nonop_q+rf*$D137/4)*(1-tax) -> 2397.7837 | I121: =(I119+nonop_q+rf*$D137/4)*(1-tax) -> 2345.4197 | J121: =(J119+nonop_q+rf*$D137/4)*(1-tax) -> 2350.8854 | K121: =(K119+nonop_q+rf*$E137/4)*(1-tax) -> 2368.9755 | L121: =(L119+nonop_q+rf*$E137/4)*(1-tax) -> 2374.2939 | M121: =(M119+nonop_q+rf*$E137/4)*(1-tax) -> 2379.5352 | N121: =(N119+nonop_q+rf*$E137/4)*(1-tax) -> 2401.2049 | O121: =(O119+nonop_q+rf*$F137/4)*(1-tax) -> 2460.5214 | P121: =(P119+nonop_q+rf*$F137/4)*(1-tax) -> 2507.974 | Q121: =(Q119+nonop_q+rf*$F137/4)*(1-tax) -> 2556.3279 | R121: =(R119+nonop_q+rf*$F137/4)*(1-tax) -> 2500.1922 | T121: （營業利益＋業外＋淨現金 × 收益率 ÷ 4）×（1 − 稅率）；FY2026 用 2026-06-30 淨現金
A122: 季 EPS（稀釋，分割後） | B122: JPY | C122: =C121/(sh0+dil)*1000 -> 507.34333 | D122: =D121/(sh0+dil)*1000 -> 765.0511 | E122: =E121/(sh0+dil)*1000 -> 1212.4005 | F122: =F121/(sh0+dil)*1000 -> 1350.7826 | G122: =G121/(sh0+dil)*1000 -> 1440.8982 | H122: =H121/(sh0+dil)*1000 -> 1444.4308 | I122: =I121/(sh0+dil)*1000 -> 1412.8865 | J122: =J121/(sh0+dil)*1000 -> 1416.1791 | ... R122: =R121/(sh0+dil)*1000 -> 1506.1219
A124: B. 年度（會計年度） | B124: 單位 | C124: FY2025A | D124: FY2026 | E124: FY2027 | F124: FY2028 | G124: FY2029 | T124: 說明
A125: 營收 | B125: ¥B | C125: =a25_rev -> 2337.6 | D125: =SUM(C114:F114) -> 11494.222 | E125: =SUM(G114:J114) -> 16205.215 | F125: =SUM(K114:N114) -> 16340.028 | G125: =SUM(O114:R114) -> 17097.593 | T125: FY2026＝第一季實績＋第二季指引＋第三、四季推導
A126: 營業成本 | B126: ¥B | C126: =a25_rev-(p1_gp+p2_gp+p3_gp+p4_gp) -> 1324.8 | D126: =SUM(C116:F116) -> 1698.7142 | E126: =SUM(G116:J116) -> 1872.7903 | F126: =SUM(K116:N116) -> 2004.525 | G126: =SUM(O116:R116) -> 2070.1443
A127: 毛利率 | B127: % | C127: =1-C126/C125 -> 0.43326489 | D127: =1-D126/D125 -> 0.85221147 | E127: =1-E126/E125 -> 0.88443286 | F127: =1-F126/F125 -> 0.87732426 | G127: =1-G126/G125 -> 0.87892188
A128: 營業費用 | B128: ¥B | D128: =SUM(C118:F118) -> 349.03295 | E128: =SUM(G118:J118) -> 367.39604 | F128: =SUM(K118:N118) -> 389.27856 | G128: =SUM(O118:R118) -> 419.44203
A129: 營業利益 | B129: ¥B | C129: =p1_op+p2_op+p3_op+p4_op -> 869 | D129: =SUM(C119:F119) -> 9446.4749 | E129: =SUM(G119:J119) -> 13965.029 | F129: =SUM(K119:N119) -> 13946.225 | G129: =SUM(O119:R119) -> 14608.006
A130: 營業利益率 | B130: % | C130: =C129/C125 -> 0.3717488 | D130: =D129/D125 -> 0.82184552 | E130: =E129/E125 -> 0.86176139 | F130: =F129/F125 -> 0.85350065 | G130: =G129/G125 -> 0.85438966
A131: 淨利 | B131: ¥B | C131: =a25_ni -> 554.5 | D131: =SUM(C121:F121) -> 6367.1347 | E131: =SUM(G121:J121) -> 9486.0084 | F131: =SUM(K121:N121) -> 9524.0095 | G131: =SUM(O121:R121) -> 10025.016
A132: 折舊攤銷 | B132: ¥B | D132: =da_y -> 320 | E132: =da_y -> 320 | F132: =da_y -> 320 | G132: =da_y -> 320
A133: 資本支出（含合資廠分攤） | B133: ¥B | D133: =cap_2026 -> 450 | E133: =cap_2027 -> 470 | F133: =cap_2028 -> 470 | G133: =cap_2029 -> 470
A134: 自由現金流（淨利＋折舊 − 資本支出） | B134: ¥B | D134: =D131+D132-D133 -> 6237.1347 | E134: =E131+E132-E133 -> 9336.0084 | F134: =F131+F132-F133 -> 9374.0095 | G134: =G131+G132-G133 -> 9875.0156
A135: 股東回饋（以買回計） | B135: ¥B | D135: =MAX(0,payout*(SUM(D121:F121)+0.75*(D132-D133))) -> 1085.4869 | E135: =MAX(0,payout*E134) -> 1867.2017 | F135: =MAX(0,payout*F134) -> 1874.8019 | G135: =MAX(0,payout*G134) -> 1975.0031 | T135: FY2026 只計 2026-07 以後三季的自由現金流
A136: 期末權益 | B136: ¥B | C136: =eq25 -> 1399.1 | D136: =eq_j+SUM(D121:F121)-D135 -> 6843.7478 | E136: =D136+E131-E135 -> 14462.554 | F136: =E136+F131-F135 -> 22111.762 | G136: =F136+G131-G135 -> 30161.775 | T136: FY2026＝2026-06-30 權益＋第二至四季淨利 − 回饋（不含其他綜合損益）
A137: 期末淨現金 | B137: ¥B | D137: =nc_j+(SUM(D121:F121)+0.75*(D132-D133))-D135 -> 4498.3478 | E137: =D137+E134-E135 -> 11967.154 | F137: =E137+F134-F135 -> 19466.362 | G137: =F137+G134-G135 -> 27366.375
A138: 期末流通股數（分割後） | B138: 百萬股 | D138: =sh0-D135/bb_px*1000 -> 1558.9411 | E138: =D138-E135/bb_px*1000 -> 1412.5513 | F138: =E138-F135/bb_px*1000 -> 1265.5656 | G138: =F138-G135/bb_px*1000 -> 1110.7241
A139: EPS（稀釋：期末流通股數＋dil；分割後） | B139: JPY | C139: =a25_eps -> 341.4 | D139: =D131/(D138+dil)*1000 -> 4042.8383 | E139: =E131/(E138+dil)*1000 -> 6640.4114 | F139: =F131/(F138+dil)*1000 -> 7431.6821 | G139: =G131/(G138+dil)*1000 -> 8897.679
A140: 每股淨值 BVPS（期末流通股數） | B140: JPY | D140: =D136/D138*1000 -> 4389.9978 | E140: =E136/E138*1000 -> 10238.605 | F140: =F136/F138*1000 -> 17471.841 | G140: =G136/G138*1000 -> 27155.054
A141: ROE（期末權益） | B141: % | D141: =D131/D136 -> 0.93035789 | E141: =E131/E136 -> 0.65590131 | F141: =F131/F136 -> 0.43072142 | G141: =G131/G136 -> 0.33237486
A142: 每股自由現金流（稀釋） | B142: JPY | E142: =E134/(E138+dil)*1000 -> 6535.4082 | F142: =F134/(F138+dil)*1000 -> 7314.6356 | G142: =G134/(G138+dil)*1000 -> 8764.5468
A143: 檢查：FY2025 營收、淨利 − 四季合計；第一季、第二季 − 實績與指引（應為 0） | B143: ¥B | D143: =ABS(C114-q1_rev)+ABS(D119-g2_op)+ABS(C125-2337.6) -> 0
A160: 案例區塊：份額 ×0.9（營收與位元）（情境 A）
A161: A. 季度 | B161: 單位 | C161: FY26 第1季（2026Q2） | D161: FY26 第2季（2026Q3） | E161: FY26 第3季（2026Q4） | F161: FY26 第4季（2027Q1） | G161: FY27 第1季（2027Q2） | H161: FY27 第2季（2027Q3） | I161: FY27 第3季（2027Q4） | J161: FY27 第4季（2028Q1） | K161: FY28 第1季（2028Q2） | L161: FY28 第2季（2028Q3） | M161: FY28 第3季（2028Q4） | N161: FY28 第4季（2029Q1） | O161: FY29 第1季（2029Q2） | P161: FY29 第2季（2029Q3） | Q161: FY29 第3季（2029Q4） | R161: FY29 第4季（2030Q1） | T161: 說明
A162: 市場層營收（TrendForce 口徑，美元，同字母情境） | B162: $B | C162: =Units!H4*0.9 -> 9.648 | D162: =Units!I4*0.9 -> 12.887807 | E162: =Units!J4*0.9*1 -> 15.882295 | F162: =Units!K4*0.9*1 -> 17.500344 | G162: =Units!L4*0.9*1 -> 18.504361 | H162: =Units!M4*0.9*1 -> 18.587681 | I162: =Units!N4*0.9*1 -> 18.278294 | J162: =Units!O4*0.9*1 -> 18.360596 | K162: =Units!P4*0.9*1 -> 18.443268 | L162: =Units!Q4*0.9*1 -> 18.526313 | ... R162: =Units!W4*0.9*1 -> 19.386688 | T162: markets/nand；Sens 可乘份額係數、價格係數（第三季起）
A163: 位元（市場層；同字母） | B163: EB | C163: =Units!H7*0.9 -> 36.158182 | D163: =Units!I7*0.9 -> 42.000116 | E163: =Units!J7*0.9 -> 44.050093 | F163: =Units!K7*0.9 -> 47.124088 | G163: =Units!L7*0.9 -> 49.827657 | H163: =Units!M7*0.9 -> 52.686332 | I163: =Units!N7*0.9 -> 55.709014 | J163: =Units!O7*0.9 -> 58.90511 | ... R163: =Units!W7*0.9 -> 84.6041
A164: 營收 | B164: ¥B | C164: =q1_rev -> 1767.1 | D164: =g2_rev -> 2390 | E164: =E162*kx_k*fx -> 2618.06 | F164: =F162*kx_k*fx -> 2884.7816 | G164: =G162*kx_k*fx -> 3050.2852 | H164: =H162*kx_k*fx -> 3064.0197 | I164: =I162*kx_k*fx -> 3013.0199 | J164: =J162*kx_k*fx -> 3026.5866 | K164: =K162*kx_k*fx -> 3040.2145 | L164: =L162*kx_k*fx -> 3053.9036 | ... R164: =R162*kx_k*fx -> 3195.7292 | T164: 第一季實績、第二季公司指引；之後＝市場層 × 公司口徑係數 × 匯率
A165: 每 EB 營業成本（第二季以指引校準，之後每年 × (1 − 成本年降)） | B165: ¥B/EB | C165: =C166/C163 -> 10.702972 | D165: =D166/D163 -> 10.238067 | E165: =$D165*(1-cd_A)^(1/4) -> 9.8592204 | F165: =$D165*(1-cd_A)^(2/4) -> 9.4943927 | G165: =$D165*(1-cd_A)^(3/4) -> 9.1430649 | H165: =$D165*(1-cd_A)^(4/4) -> 8.8047376 | I165: =$D165*(1-cd_A)^(5/4) -> 8.4789296 | J165: =$D165*(1-cd_A)^(6/4) -> 8.1651777 | K165: =$D165*(1-cd_A)^(7/4) -> 7.8630358 | L165: =$D165*(1-cd_A)^(8/4) -> 7.5720743 | M165: =$D165*(1-cd_A)^(9/4) -> 7.2918794 | N165: =$D165*(1-cd_A)^(10/4) -> 7.0220528 | O165: =$D165*(1-cd_A)^(11/4) -> 6.7622108 | P165: =$D165*(1-cd_A)^(12/4) -> 6.5119839 | Q165: =$D165*(1-cd_A)^(13/4) -> 6.2710163 | R165: =$D165*(1-cd_A)^(14/4) -> 6.0389654
A166: 營業成本 | B166: ¥B | C166: =q1_rev-q1_gp -> 387 | D166: =g2_rev-g2_op-g2_ox -> 430 | E166: =E163*E165 -> 434.29958 | F166: =F163*F165 -> 447.4146 | G166: =G163*G165 -> 455.5775 | H166: =H163*H165 -> 463.88933 | I166: =I163*I165 -> 472.3528 | J166: =J163*J165 -> 480.97069 | K166: =K163*K165 -> 489.74581 | L166: =L163*L165 -> 498.68103 | ... R166: =R163*R165 -> 510.92124 | T166: 第二季＝指引營收 − 指引營業利益 − 推估營業費用
A167: 毛利率 | B167: % | C167: =1-C166/C164 -> 0.78099711 | D167: =1-D166/D164 -> 0.82008368 | E167: =1-E166/E164 -> 0.83411397 | F167: =1-F166/F164 -> 0.84490521 | G167: =1-G166/G164 -> 0.85064429 | H167: =1-H166/H164 -> 0.84860106 | I167: =1-I166/I164 -> 0.84322944 | J167: =1-J166/J164 -> 0.84108478 | ... R167: =1-R166/R164 -> 0.84012374
A168: 營業費用 | B168: ¥B | C168: =q1_gp-q1_op -> 110.1 | D168: =g2_ox -> 70 | E168: =(g2_ox-ox_var*g2_rev)*(1+ox_g)^(1/4)+ox_var*E164 -> 73.392241 | F168: =(g2_ox-ox_var*g2_rev)*(1+ox_g)^(2/4)+ox_var*F164 -> 77.197904 | G168: =(g2_ox-ox_var*g2_rev)*(1+ox_g)^(3/4)+ox_var*G164 -> 80.018839 | H168: =(g2_ox-ox_var*g2_rev)*(1+ox_g)^(4/4)+ox_var*H164 -> 81.350197 | I168: =(g2_ox-ox_var*g2_rev)*(1+ox_g)^(5/4)+ox_var*I164 -> 82.063004 | J168: =(g2_ox-ox_var*g2_rev)*(1+ox_g)^(6/4)+ox_var*J164 -> 83.450963 | K168: =(g2_ox-ox_var*g2_rev)*(1+ox_g)^(7/4)+ox_var*K164 -> 84.86973 | L168: =(g2_ox-ox_var*g2_rev)*(1+ox_g)^(8/4)+ox_var*L164 -> 86.320036 | M168: =(g2_ox-ox_var*g2_rev)*(1+ox_g)^(9/4)+ox_var*M164 -> 87.80263 | N168: =(g2_ox-ox_var*g2_rev)*(1+ox_g)^(10/4)+ox_var*N164 -> 89.436093 | O168: =(g2_ox-ox_var*g2_rev)*(1+ox_g)^(11/4)+ox_var*O164 -> 91.419268 | P168: =(g2_ox-ox_var*g2_rev)*(1+ox_g)^(12/4)+ox_var*P164 -> 93.447055 | Q168: =(g2_ox-ox_var*g2_rev)*(1+ox_g)^(13/4)+ox_var*Q164 -> 95.520469 | R168: =(g2_ox-ox_var*g2_rev)*(1+ox_g)^(14/4)+ox_var*R164 -> 96.311259 | T168: 固定部分以第二季校準（Derived）
A169: 營業利益 | B169: ¥B | C169: =C164-C166-C168 -> 1270 | D169: =D164-D166-D168 -> 1890 | E169: =E164-E166-E168 -> 2110.3681 | F169: =F164-F166-F168 -> 2360.1691 | G169: =G164-G166-G168 -> 2514.6888 | H169: =H164-H166-H168 -> 2518.7802 | I169: =I164-I166-I168 -> 2458.6041 | J169: =J164-J166-J168 -> 2462.165 | ... R169: =R164-R166-R168 -> 2588.4967
A171: 淨利 | B171: ¥B | C171: =q1_ni -> 842.2 | D171: =g2_ni -> 1270 | E171: =(E169+nonop_q+rf*nc_j/4)*(1-tax) -> 1425.1162 | F171: =(F169+nonop_q+rf*nc_j/4)*(1-tax) -> 1594.9809 | G171: =(G169+nonop_q+rf*$D187/4)*(1-tax) -> 1705.7562 | H171: =(H169+nonop_q+rf*$D187/4)*(1-tax) -> 1708.5383 | I171: =(I169+nonop_q+rf*$D187/4)*(1-tax) -> 1667.6186 | J171: =(J169+nonop_q+rf*$D187/4)*(1-tax) -> 1670.04 | K171: =(K169+nonop_q+rf*$E187/4)*(1-tax) -> 1681.3537 | L171: =(L169+nonop_q+rf*$E187/4)*(1-tax) -> 1683.6002 | M171: =(M169+nonop_q+rf*$E187/4)*(1-tax) -> 1685.7558 | N171: =(N169+nonop_q+rf*$E187/4)*(1-tax) -> 1701.6822 | O171: =(O169+nonop_q+rf*$F187/4)*(1-tax) -> 1744.3838 | P171: =(P169+nonop_q+rf*$F187/4)*(1-tax) -> 1778.7532 | Q171: =(Q169+nonop_q+rf*$F187/4)*(1-tax) -> 1813.7818 | R171: =(R169+nonop_q+rf*$F187/4)*(1-tax) -> 1773.9035 | T171: （營業利益＋業外＋淨現金 × 收益率 ÷ 4）×（1 − 稅率）；FY2026 用 2026-06-30 淨現金
A172: 季 EPS（稀釋，分割後） | B172: JPY | C172: =C171/(sh0+dil)*1000 -> 507.34333 | D172: =D171/(sh0+dil)*1000 -> 765.0511 | E172: =E171/(sh0+dil)*1000 -> 858.49348 | F172: =F171/(sh0+dil)*1000 -> 960.82036 | G172: =G171/(sh0+dil)*1000 -> 1027.5517 | H172: =H171/(sh0+dil)*1000 -> 1029.2276 | I172: =I171/(sh0+dil)*1000 -> 1004.5775 | J172: =J171/(sh0+dil)*1000 -> 1006.0362 | ... R172: =R171/(sh0+dil)*1000 -> 1068.6038
A174: B. 年度（會計年度） | B174: 單位 | C174: FY2025A | D174: FY2026 | E174: FY2027 | F174: FY2028 | G174: FY2029 | T174: 說明
A175: 營收 | B175: ¥B | C175: =a25_rev -> 2337.6 | D175: =SUM(C164:F164) -> 9659.9416 | E175: =SUM(G164:J164) -> 12153.911 | F175: =SUM(K164:N164) -> 12255.021 | G175: =SUM(O164:R164) -> 12823.195 | T175: FY2026＝第一季實績＋第二季指引＋第三、四季推導
A176: 營業成本 | B176: ¥B | C176: =a25_rev-(p1_gp+p2_gp+p3_gp+p4_gp) -> 1324.8 | D176: =SUM(C166:F166) -> 1698.7142 | E176: =SUM(G166:J166) -> 1872.7903 | F176: =SUM(K166:N166) -> 2004.525 | G176: =SUM(O166:R166) -> 2070.1443
...

Sheet Sources
A1: 來源
A2: Kioxia FY2026 第一季財報（2026-07-31；SGX 轉載） | B2: https://links.sgx.com/1.0.0/corporate-announcements/DOATO9EIE4EEQ2Y8/898078_Earnings-Release-FY2026-1Q-EN.pdf
A3: Kioxia：第二季財報 2026-10-30 18:45（JST）公布（公司新聞頁） | B3: https://www.kioxia-holdings.com/en-jp/news/2026.html
A4: storagenewsletter：Kioxia FY25 決算（營收 2,337.6、營業利益 870、淨利 554） | B4: https://www.storagenewsletter.com/?p=302700
A5: stockanalysis：季度損益、歷史股價、共識 | B5: https://stockanalysis.com/quote/tyo/285A/financials/?p=quarterly
A6: MarketScreener：Kioxia 預估與共識目標價 | B6: https://uk.marketscreener.com/quote/stock/KIOXIA-HOLDINGS-CORPORATI-180030735/finances/
A7: MarketScreener：SanDisk 預估（同業 P/B、P/E） | B7: https://uk.marketscreener.com/quote/stock/SANDISK-CORPORATION-182801077/finances/
A8: TrendForce：Kioxia FY26–28 資本支出（2026-06-03） | B8: https://www.trendforce.com/news/2026/06/03/news-kioxia-targets-%C2%A5470b-yearly-capex-in-fy26-28-up-66-from-fy25-reportedly-weighing-third-kitakami-fab-and-ma/
A9: newsquawk：一股分三股公告（2026-07-31） | B9: https://www.newsquawk.com/headlines/kioxia-285a-jt-q1-jpy-net-profit-84217bln-exp-9736bln-revenue-177tln-prev-3428bln-yy-announces-a-3-for-1-stock-split-and-announces-a-share-buyback
A10: stockanalysis：WDC 統計（Forward P/E） | B10: https://stockanalysis.com/stocks/wdc/statistics/
A11: 市場層：markets/nand/dist/20261025_NAND市場模型_v0.1.xlsx（markets/nand v0.1） | B11: 本 repo
A12: 美光十年倍數與淨利率（Analogy）：micron/dist/20261025_美光模型_v0.4.xlsx | B12: 本 repo
A13: SemiAnalysis | B13: 未使用
