Workbook

Sheet README
A1: 欣興電子（3037.TW）收支與估值模型 v0.1.1（AI 半導體 Project：載板與 PCB 次產業） 2026-10-25
A2: 版本：v0.1.1（2026-10-25：補上檔空間級距、投資建議、重點觀察，數值不變）。前版：v0.1（初版）。樣板：ibiden/。AI 加速器載板的每顆金額、Ibiden 份額與非 NVIDIA 權重讀 ibiden/dist（本專案權威），欣興份額與 Ibiden 合計在 Units 頁檢查。
A3: 模型命題：欣興的 ABF 載板營收＝MIN（需求, 產能）；需求＝AI 加速器顆數 × 每顆載板金額（面積與層數 × 溢價，與 Ibiden 同口徑）× 欣興份額，加上交換器、伺服器 CPU 等其他 AI 載板（隨 AI IT 資本支出）與非 AI ABF；產能依光復二廠、楊梅二廠時程擴張。BT、HDI／PCB、軟板另推。2026 年資本支出 537 億、2027–28 年仍在 400–550 億，擴產折舊是毛利率的關鍵。
A4: 核心問題：ABF 短缺與漲價能不能抵過擴產折舊，讓毛利率從 FY2026 約 25% 持續上升、EPS 在 FY2027–28 倍增；約 42 倍前瞻 P/E 隱含什麼路徑。
A6: 會計年度＝日曆年，FY(t)＝CY(t)，不平移。預測期 FY2027–FY2029 由驅動因子推導；FY2030 起為收斂法，非驅動因子推導（延伸到 FY2032；PL 頁灰底）。金額：十億新台幣；EPS：新台幣（基本、歸屬母公司）。3Q26 財報約 2026-10-29 公布，本版只納入 3Q26 營收實績。
A8: 驅動因子 → 推導量（全部唯讀上游，不修改）
A9: 加速器載板：markets/network 的 NVIDIA 與非 NVIDIA 顆數 × 情境係數（tsmc）× 每顆 NVIDIA 載板金額（Ibiden 模型 FY2026 校準 US$215 × 面積層數 +18%／年 × Ibiden 溢價指數）× 欣興份額（NVIDIA 25%→30%、非 NVIDIA 金額 30%→33%，Assumed；非 NVIDIA 每顆金額 ＝ 0.8 × NVIDIA）× 漲價年度化 1.05。
A10: 其他 AI 載板＝FY2026 AI 載板（ABF × 75%）− 加速器載板（校準殘差），之後 × AI IT 資本支出成長 ^ 0.5；非 AI ABF +3%。ABF 產能指數 1.35／1.70／2.00（Assumed）× 組合 +5%／年 × 溢價；營收＝MIN（需求, 產能）。BT +5%、AI HDI／PCB +20%／+15%／+10%（× 顆數情境係數）、非 AI HDI／PCB +2%、軟板與其他持平。
A11: 毛利＝FY2026 錨點＋ABF 現金毛利增量（50%）＋其他產品現金毛利增量（25%）＋漲價溢價營收 − 折舊增量；折舊＝前一年 ×（1 − 1／8 年）＋前一年資本支出 ÷ 8 年；資本支出依情境。營業費用彈性 0.6；業外每年 20 億；稅與少數股權 18%；股數持平（GDR 後 16.4 億股）。
A12: 校準：FY2026 ＝ 1H26 財報實績（EPS 11.70，含 2Q26 一次性業外約 89 億）＋3Q26 營收實績 526.5 億＋3Q26 毛利率 27%、4Q26 營收季增 5%、毛利率 28.5%（Assumed）。不用券商數字（只在 Recon 對帳）。
A13: 估值：Val 第 0 節目標價＝0.5 × DCF 目標價（股東現金流＝每股（淨利＋折舊－資本支出），FY2027–32 明確期＋永續，r 10%、g 4%，三情境權重 0.3／0.5／0.2）＋0.5 × Comparable 目標價（Ibiden、景碩、南電、三星電機、AT&S 前瞻 P/E 中位數 × 12 個月後前瞻 EPS；無 A 股）；另列 Comparable 單獨目標價、市場共識目標價與差距拆解。十年 P/E 規則值 × FY2027 EPS 保留為參考（不是目標價）。情境對應：A＝順利、B＝平平、C＝不如預期（原為顆數情境，另含資本支出路徑）。本版未做先驗，無 Andy 合理 P/E 對照。
A14: 預估期間：FY2027–FY2029 由驅動因子推導；FY2030 起為收斂法，非驅動因子推導（營收年增由 FY2029 線性收斂到 fade_g、淨利率收斂到 fade_m，FY2032 達到；十年平均淨利率未找到，依工作單以 FY2029 × 0.8 代替）。
... A18: v0.1.1：補上檔空間級距、投資建議、重點觀察（數值不變）。Val 頁最後新增「上檔空間級距」「投資建議」兩列（第 133、134 列，依「上檔空間：加權目標價」的固定規則）；重點觀察見下方三列。
A19: ="投資建議："&Val!B134&"（依上檔空間固定規則）" -> 投資建議：放空（依上檔空間固定規則）
A20: 重點觀察 1：目標價 NT$727（DCF 389、Comparable 1,065 各半），比現價 1,085（2026-10-22）低 33.0%，級距 −25%～−50%；Comparable 單獨為 −1.8%。主因是 DCF 不是 EPS：本模型前瞻 EPS 24.54 只比共識前瞻 EPS 25.66 低 4.4%，同業前瞻 P/E 中位數 43.4 倍與現價 ÷ 共識前瞻 EPS 42.3 倍相近；DCF 用每股（淨利＋折舊 − 資本支出），擴產期 FY2027 情境 A 每股現金流 9.16 只有 EPS 27.51 的 33%，DCF 比現價低 64.2%（改用 EPS ×（1 − g／ROE）只有 249，因 ROE 8.6% 低於折現率 10%）。
A21: 重點觀察 2：ABF 漲價路徑最敏感：ABF 溢價取 Ibiden 低值（2028 年 0.85）時 FY2028 EPS −24.1%、取高值 +24.1%；漲價年度化 0%（基準 5%）時 FY2027 EPS −11.1%，AI 部署 ×0.8 時 −19.4%。
A22: 重點觀察 3：情境分歧從 FY2028 開始：FY2027 EPS 三情境同為 27.51（比 2026-06 FactSet 共識 30.37 低 9.4%），FY2028 為 30.44／23.21／16.05。下一個檢驗點是 3Q26 財報與法說（約 2026-10-29）：ABF 報價與 2027 年資本支出。

Sheet In
A1: In — 輸入（藍字；基準欄 E，低 D、高 F）。金額：十億新台幣（NT$B）；顆數：百萬顆；比例：%。每個輸入附兩個來源（找不到者寫「未找到」）；公司原文算一個
A2: 標記：Verified／Interested-party／Analogy／Assumed／Derived；Analogy、Assumed 給低／高區間，不當點估計（放情境或 Sens）。SemiAnalysis 未使用。公司原文＝公開資訊觀測站財報與法說會（經工商時報、Quartr 轉載）；公司說法與指引為 Interested-party；券商、媒體、資料商為 Interested-party
A3: 鍵 | B3: 項目 | C3: 單位 | D3: 低 | E3: 基準 | F3: 高 | G3: 標記 | H3: 來源1 | I3: 來源2／說明
A4: A. AI 加速器顆數與 AI IT 資本支出（讀 markets/network、tsmc 成品；唯讀，不自行重估）
A5: u_bw_26 | B5: NVIDIA Blackwell（B200／B300） 顆數 2026 | C5: 百萬顆 | E5: 5.4 | G5: Derived | H5: markets/network/dist/20261026_AI網通市場模型_v0.2.3.xlsx｜In!E5 | I5: 唯讀上游；與 Ibiden、台積電模型同一份顆數
A6: u_bw_27 | B6: NVIDIA Blackwell（B200／B300） 顆數 2027 | C6: 百萬顆 | E6: 2.4 | G6: Derived | H6: markets/network/dist/20261026_AI網通市場模型_v0.2.3.xlsx｜In!E6 | I6: 唯讀上游；與 Ibiden、台積電模型同一份顆數
A7: u_bw_28 | B7: NVIDIA Blackwell（B200／B300） 顆數 2028 | C7: 百萬顆 | E7: 0.5 | G7: Derived | H7: markets/network/dist/20261026_AI網通市場模型_v0.2.3.xlsx｜In!E7 | I7: 唯讀上游；與 Ibiden、台積電模型同一份顆數
A8: g29_bw | B8: NVIDIA Blackwell（B200／B300） 2029 顆數成長 | C8: % | E8: -0.5 | G8: Derived | H8: markets/network/dist/20261026_AI網通市場模型_v0.2.3.xlsx｜In!E8 | I8: 同上
A9: u_rb_26 | B9: NVIDIA Rubin 顆數 2026 | C9: 百萬顆 | E9: 1.7 | G9: Derived | H9: markets/network/dist/20261026_AI網通市場模型_v0.2.3.xlsx｜In!E9 | I9: 唯讀上游；與 Ibiden、台積電模型同一份顆數
A10: u_rb_27 | B10: NVIDIA Rubin 顆數 2027 | C10: 百萬顆 | E10: 7 | G10: Derived | H10: markets/network/dist/20261026_AI網通市場模型_v0.2.3.xlsx｜In!E10 | I10: 唯讀上游；與 Ibiden、台積電模型同一份顆數
A11: u_rb_28 | B11: NVIDIA Rubin 顆數 2028 | C11: 百萬顆 | E11: 7 | G11: Derived | H11: markets/network/dist/20261026_AI網通市場模型_v0.2.3.xlsx｜In!E11 | I11: 唯讀上游；與 Ibiden、台積電模型同一份顆數
A12: g29_rb | B12: NVIDIA Rubin 2029 顆數成長 | C12: % | E12: 0.15 | G12: Derived | H12: markets/network/dist/20261026_AI網通市場模型_v0.2.3.xlsx｜In!E12 | I12: 同上
A13: u_ru_26 | B13: NVIDIA Rubin Ultra 顆數 2026 | C13: 百萬顆 | E13: 0 | G13: Derived | H13: markets/network/dist/20261026_AI網通市場模型_v0.2.3.xlsx｜In!E13 | I13: 唯讀上游；與 Ibiden、台積電模型同一份顆數
A14: u_ru_27 | B14: NVIDIA Rubin Ultra 顆數 2027 | C14: 百萬顆 | E14: 0.3 | G14: Derived | H14: markets/network/dist/20261026_AI網通市場模型_v0.2.3.xlsx｜In!E14 | I14: 唯讀上游；與 Ibiden、台積電模型同一份顆數
A15: u_ru_28 | B15: NVIDIA Rubin Ultra 顆數 2028 | C15: 百萬顆 | E15: 2 | G15: Derived | H15: markets/network/dist/20261026_AI網通市場模型_v0.2.3.xlsx｜In!E15 | I15: 唯讀上游；與 Ibiden、台積電模型同一份顆數
A16: g29_ru | B16: NVIDIA Rubin Ultra 2029 顆數成長 | C16: % | E16: 0.15 | G16: Derived | H16: markets/network/dist/20261026_AI網通市場模型_v0.2.3.xlsx｜In!E16 | I16: 同上
... A46: um29_C | B46: 情境 C：2029 顆數 ÷ 基準 | C46: x | E46: 0.6 | G46: Assumed | H46: tsmc/dist/20261025_台積電模型_v0.3.1.xlsx｜In!E42 | I46: 同上
A47: B. 每顆加速器載板金額與份額（口徑與 Ibiden 一致；Ibiden 數字唯讀取自 ibiden/dist）
A48: v26 | B48: FY2026 每顆 NVIDIA 加速器載板金額（全市場；Ibiden 模型校準） | C48: US$ | E48: 215.3086 | G48: Derived | H48: ibiden/dist/20261025_Ibiden模型_v0.2.1.xlsx｜Units!C8 | I48: Ibiden 模型：Ibiden 每顆營收 ÷ 份額 70%（BofA：Ibiden 占 GPU 載板 70–80%，Interested-party）
A49: g_asp | B49: 每顆載板金額年增（面積、層數；Ibiden 模型） | C49: % | D49: 0.1 | E49: 0.18 | F49: 0.22 | G49: Analogy | H49: ibiden/dist/20261025_Ibiden模型_v0.2.1.xlsx｜In!E50 | I49: Ibiden 路線圖 2026 年 90×90 mm → 2028 年 110×110 mm（Tom's Hardware，經 Ibiden 模型）
A50: ibpp_27 | B50: ABF 價格溢價指數 2027（FY2026＝1；Ibiden 模型） | C50: x | D50: 0.95 | E50: 1 | F50: 1.05 | G50: Assumed | H50: ibiden/dist/20261025_Ibiden模型_v0.2.1.xlsx｜In!E55 | I50: 全市場短缺溢價；新產能到位後回落（Ibiden 模型）
A51: ibrel_27 | B51: Ibiden NVIDIA 份額 2027 ÷ 2026（Ibiden 模型） | C51: x | E51: 0.95 | G51: Assumed | H51: ibiden/dist/20261025_Ibiden模型_v0.2.1.xlsx｜In!E51 | I51: Units 頁份額合計檢查用
A52: ibpp_28 | B52: ABF 價格溢價指數 2028（FY2026＝1；Ibiden 模型） | C52: x | D52: 0.85 | E52: 0.95 | F52: 1.05 | G52: Assumed | H52: ibiden/dist/20261025_Ibiden模型_v0.2.1.xlsx｜In!E56 | I52: 同上
A53: ibrel_28 | B53: Ibiden NVIDIA 份額 2028 ÷ 2026（Ibiden 模型） | C53: x | E53: 0.88 | G53: Assumed | H53: ibiden/dist/20261025_Ibiden模型_v0.2.1.xlsx｜In!E52 | I53: Units 頁份額合計檢查用
A54: ibpp_29 | B54: ABF 價格溢價指數 2029（FY2026＝1；Ibiden 模型） | C54: x | D54: 0.75 | E54: 0.9 | F54: 1 | G54: Assumed | H54: ibiden/dist/20261025_Ibiden模型_v0.2.1.xlsx｜In!E57 | I54: 同上
A55: ibrel_29 | B55: Ibiden NVIDIA 份額 2029 ÷ 2026（Ibiden 模型） | C55: x | E55: 0.85 | G55: Assumed | H55: ibiden/dist/20261025_Ibiden模型_v0.2.1.xlsx｜In!E53 | I55: Units 頁份額合計檢查用
A56: ib_sh26 | B56: Ibiden 占 NVIDIA 加速器載板 FY2026（Ibiden 模型假設） | C56: % | D56: 0.7 | E56: 0.7 | F56: 0.8 | G56: Interested-party | H56: ibiden/dist/20261025_Ibiden模型_v0.2.1.xlsx｜Units!C8（列標籤：假設 FY2026 份額 70%） | I56: BofA（經 thebuildout 2026-03-26）：Ibiden 70–80%
A57: ib_w_ot | B57: Ibiden 非 NVIDIA 權重（份額 × 每顆金額，相對 NVIDIA；Ibiden 模型） | C57: x | D57: 0.2 | E57: 0.4 | F57: 0.6 | G57: Assumed | H57: ibiden/dist/20261025_Ibiden模型_v0.2.1.xlsx｜In!E48 | I57: Units 頁：÷ v_ot 即 Ibiden 非 NVIDIA 份額
A58: v_ot | B58: 非 NVIDIA 加速器每顆載板金額 ÷ NVIDIA | C58: x | D58: 0.6 | E58: 0.8 | F58: 1 | G58: Assumed | H58: TPU、Trainium、MI 系列封裝面積接近 GPU，但層數與 CoWoS 規格不同；量化：未找到 | I58: Ibiden 權重 0.4 ÷ 0.8 ＝ Ibiden 非 NVIDIA 份額 50%（Units 頁合計檢查）
A59: sh_nv_26 | B59: 欣興占 NVIDIA 加速器載板 2026 | C59: % | D59: 0.2 | E59: 0.25 | F59: 0.3 | G59: Assumed | H59: 市場分析：欣興約占 Blackwell 載板供應鏈 30%（口袋學堂 2026-07，未經公司確認，Interested-party） | I59: Encyclopedia of Stocks 2026-03-04：欣興 2025 年約 30% NVIDIA AI 載板顆數（Interested-party）；與 Ibiden 70% 合計不超過 100%（Units 頁）
A60: sh_nv_27 | B60: 欣興占 NVIDIA 加速器載板 2027 | C60: % | D60: 0.22 | E60: 0.27 | F60: 0.32 | G60: Assumed | H60: Ibiden 份額相對值 0.95／0.88／0.85（Ibiden 模型）→ 由欣興、三星電機等分食 | I60: 光復二廠 2027、楊梅二廠 2028 量產，客戶全額預付（三立 2026-10-19，Interested-party）
A61: sh_nv_28 | B61: 欣興占 NVIDIA 加速器載板 2028 | C61: % | D61: 0.22 | E61: 0.29 | F61: 0.35 | G61: Assumed | H61: Ibiden 份額相對值 0.95／0.88／0.85（Ibiden 模型）→ 由欣興、三星電機等分食 | I61: 光復二廠 2027、楊梅二廠 2028 量產，客戶全額預付（三立 2026-10-19，Interested-party）
A62: sh_nv_29 | B62: 欣興占 NVIDIA 加速器載板 2029 | C62: % | D62: 0.22 | E62: 0.3 | F62: 0.36 | G62: Assumed | H62: Ibiden 份額相對值 0.95／0.88／0.85（Ibiden 模型）→ 由欣興、三星電機等分食 | I62: 光復二廠 2027、楊梅二廠 2028 量產，客戶全額預付（三立 2026-10-19，Interested-party）
A63: sh_ot_26 | B63: 欣興占非 NVIDIA 加速器載板（金額）2026 | C63: % | D63: 0.22 | E63: 0.3 | F63: 0.4 | G63: Assumed | H63: 欣興為 ASIC（TPU、Trainium 等）主要載板廠之一（第三方研究，Interested-party）；量化：未找到 | I63: 合計檢查：Ibiden 50%＋欣興 30%＝80%，其餘為三星電機、景碩、南電、AT&S（Units 頁）
A64: sh_ot_27 | B64: 欣興占非 NVIDIA 加速器載板（金額）2027 | C64: % | D64: 0.22 | E64: 0.31 | F64: 0.4 | G64: Assumed | H64: 同上 | I64: —
A65: sh_ot_28 | B65: 欣興占非 NVIDIA 加速器載板（金額）2028 | C65: % | D65: 0.22 | E65: 0.32 | F65: 0.4 | G65: Assumed | H65: 同上 | I65: —
A66: sh_ot_29 | B66: 欣興占非 NVIDIA 加速器載板（金額）2029 | C66: % | D66: 0.22 | E66: 0.33 | F66: 0.4 | G66: Assumed | H66: 同上 | I66: —
A67: C. FY2026 產品組合與 AI 占比（公司說法；Q2 組合推全年）
A68: mx_abf | B68: FY2026 ABF 載板 ÷ 營收 | C68: % | D68: 0.5 | E68: 0.53 | F68: 0.56 | G68: Interested-party | H68: 工商時報 2026-07-29（2Q26 法說：產品組合、稼動率、AI 占比、資本支出）：2Q26 ABF 52%（季增 22%）→ 1Q26 約 49%；下半年 AI 占比升 | I68: 富果 4Q25 法說摘要（2026-02-25，AI 摘要）：4Q25 載板（ABF＋BT）59%
A69: mx_bt | B69: FY2026 BT 載板 ÷ 營收 | C69: % | D69: 0.08 | E69: 0.09 | F69: 0.1 | G69: Interested-party | H69: 工商時報 2026-07-29（2Q26 法說：產品組合、稼動率、AI 占比、資本支出）：2Q26 BT 9% | I69: —
A70: mx_pcb | B70: FY2026 HDI＋PCB ÷ 營收 | C70: % | D70: 0.29 | E70: 0.31 | F70: 0.33 | G70: Interested-party | H70: 工商時報 2026-07-29（2Q26 法說：產品組合、稼動率、AI 占比、資本支出）：2Q26 HDI 22%、PCB 9% | I70: 富果 4Q25 法說摘要（2026-02-25，AI 摘要）：4Q25 HDI 27%、PCB 11%
A71: ai_abf | B71: FY2026 AI 載板 ÷ ABF 營收 | C71: % | D71: 0.65 | E71: 0.75 | F71: 0.85 | G71: Assumed | H71: 工商時報 2026-07-29（2Q26 法說：產品組合、稼動率、AI 占比、資本支出）：載板 AI 占比上半年逾 60%、下半年 70%（ABF＋BT 口徑） | I71: BT 多為記憶體與手機，AI 集中在 ABF：0.66 × 62% ÷ 53% ≈ 0.77（Derived）
A72: ai_pcb | B72: FY2026 HDI＋PCB 的 AI 占比 | C72: % | D72: 0.55 | E72: 0.65 | F72: 0.75 | G72: Interested-party | H72: 工商時報 2026-07-29（2Q26 法說：產品組合、稼動率、AI 占比、資本支出）：PCB AI 占比上半年逾 60%、下半年 65–70% | I72: 富果 4Q25 法說摘要（2026-02-25，AI 摘要）：2025 年 55–60%
A73: D. 需求與產能（FY2027 起）
A74: el_o | B74: 其他 AI 載板（交換器、伺服器 CPU、網通）對 AI IT 資本支出的彈性 | C74: x | D74: 0.3 | E74: 0.5 | F74: 0.8 | G74: Assumed | H74: 其他 AI 載板＝FY2026 AI 載板 − 加速器載板（校準殘差）；隨部署規模成長但低於等比例 | I74: 量化：未找到
A75: g_nai | B75: 非 AI ABF（PC、一般伺服器）年增 | C75: % | D75: -0.02 | E75: 0.03 | F75: 0.06 | G75: Assumed | H75: PC、一般伺服器緩步成長 | I75: —
A76: cap_27 | B76: ABF 產能指數 2027（FY2026 平均＝1） | C76: x | D76: 1.25 | E76: 1.35 | F76: 1.45 | G76: Assumed | H76: 三立 2026-10-19（本土法人；Q3 營收、Q4 預估、產能時程）：ABF 產能 2026 年增約 40%、2027 年 30–40%；光復一廠三期 2H26、光復二廠 2027、楊梅二廠 2028、楊梅三廠 2029 | I76: 工商時報 2026-07-29（2Q26 法說：產品組合、稼動率、AI 占比、資本支出）：ABF 稼動率逾 90%；資本支出主要為光復二廠與楊梅二廠
A77: cap_28 | B77: ABF 產能指數 2028（FY2026 平均＝1） | C77: x | D77: 1.5 | E77: 1.7 | F77: 1.9 | G77: Assumed | H77: 同上 | I77: 楊梅五廠 2030、新竹新廠 2030 年後（三立）
A78: cap_29 | B78: ABF 產能指數 2029（FY2026 平均＝1） | C78: x | D78: 1.7 | E78: 2 | F78: 2.3 | G78: Assumed | H78: 同上 | I78: 楊梅五廠 2030、新竹新廠 2030 年後（三立）
A79: g_mix | B79: 每單位產能營收年增（層數、尺寸組合） | C79: % | D79: 0 | E79: 0.05 | F79: 0.08 | G79: Assumed | H79: 高層數載板每片金額高，但也占用較多製程時間；淨效果 Assumed | I79: —
A80: carry | B80: 欣興漲價年度化（CY2026 只反映約半年漲價；FY2027 起 ×(1＋此值)） | C80: % | D80: 0 | E80: 0.05 | F80: 0.1 | G80: Assumed | H80: Ibiden 溢價指數以 FY2026（2026-04～2027-03）為基期，已含 2026 下半年漲價；欣興 CY2026 基期含上半年較低價格 | I80: 媒體與法人：2026 年 ABF 漲價約 15–20%，外資估最高 30%（口袋學堂，非公司指引）
A81: g_bt | B81: BT 載板年增 | C81: % | D81: 0 | E81: 0.05 | F81: 0.1 | G81: Assumed | H81: 工商時報 2026-07-29（2Q26 法說：產品組合、稼動率、AI 占比、資本支出）：BT 稼動率 80–85%；2Q26 年減 4% | I81: 記憶體循環上行（Assumed）
A82: g_pai_27 | B82: AI HDI／PCB 年增 2027（顆數情境係數另乘） | C82: % | D82: 0.1 | E82: 0.2 | F82: 0.3 | G82: Assumed | H82: 工商時報 2026-07-29（2Q26 法說：產品組合、稼動率、AI 占比、資本支出）：HDI 2Q26 年增 29%；HDI／PCB 稼動率 85–90% | I82: AI 伺服器加速器板、交換器板（Assumed）
A83: g_pai_28 | B83: AI HDI／PCB 年增 2028（顆數情境係數另乘） | C83: % | D83: 0.05 | E83: 0.15 | F83: 0.25 | G83: Assumed | H83: 同上 | I83: —
A84: g_pai_29 | B84: AI HDI／PCB 年增 2029（顆數情境係數另乘） | C84: % | D84: 0 | E84: 0.1 | F84: 0.2 | G84: Assumed | H84: 同上 | I84: —
A85: g_pcbn | B85: 非 AI HDI／PCB 年增（手機、消費、車用） | C85: % | D85: -0.03 | E85: 0.02 | F85: 0.05 | G85: Assumed | H85: 工商時報 2026-07-29（2Q26 法說：產品組合、稼動率、AI 占比、資本支出）：IoT 年減 3%、車用年減 26%（2Q26 應用別） | I85: —
A86: g_fpc | B86: 軟板與其他年增 | C86: % | D86: -0.05 | E86: 0 | F86: 0.03 | G86: Assumed | H86: 工商時報 2026-07-29（2Q26 法說：產品組合、稼動率、AI 占比、資本支出）：軟板 2Q26 年減 14% | I86: —
A87: E. 毛利、折舊、費用與淨利（FY2027 起）：擴產折舊是毛利率關鍵
A88: ft_abf | B88: ABF 營收增量的現金毛利率（扣除漲價溢價後） | C88: % | D88: 0.4 | E88: 0.5 | F88: 0.6 | G88: Assumed | H88: FY2025→FY2026 全公司現金毛利增量 ÷ 營收增量見 Q 頁（含漲價，偏高） | I88: 法人：ABF 毛利率可能接近 40%（三立，Interested-party）；加回折舊約 50%
A89: ft_oth | B89: 其他產品（BT、HDI、PCB、軟板）營收增量的現金毛利率 | C89: % | D89: 0.15 | E89: 0.25 | F89: 0.35 | G89: Assumed | H89: FY2025 全公司毛利率 13.9%、折舊 ÷ 營收 14%（現金毛利率約 28%） | I89: —
A90: cx27_A | B90: 資本支出 FY2027（情境 A） | C90: NT$B | E90: 55 | G90: Assumed | H90: 經濟日報 2026-10-12（美系券商 EPS 預估）：美系券商估 2027、2028 年資本支出均逾 400 億（Interested-party） | I90: 2026 年預算 537 億（第三次上修；公司）；光復二廠設備 300–400 億（富果 4Q25 法說摘要（2026-02-25，AI 摘要））
A91: cx28_A | B91: 資本支出 FY2028（情境 A） | C91: NT$B | E91: 50 | G91: Assumed | H91: 同上 | I91: —
A92: cx29_A | B92: 資本支出 FY2029（情境 A） | C92: NT$B | E92: 45 | G92: Assumed | H92: 同上 | I92: —
A93: cx27_B | B93: 資本支出 FY2027（情境 B） | C93: NT$B | E93: 48 | G93: Assumed | H93: 同上 | I93: —
A94: cx28_B | B94: 資本支出 FY2028（情境 B） | C94: NT$B | E94: 42 | G94: Assumed | H94: 同上 | I94: —
A95: cx29_B | B95: 資本支出 FY2029（情境 B） | C95: NT$B | E95: 38 | G95: Assumed | H95: 同上 | I95: —
A96: cx27_C | B96: 資本支出 FY2027（情境 C） | C96: NT$B | E96: 40 | G96: Assumed | H96: 同上 | I96: —
A97: cx28_C | B97: 資本支出 FY2028（情境 C） | C97: NT$B | E97: 30 | G97: Assumed | H97: 同上 | I97: —
A98: cx29_C | B98: 資本支出 FY2029（情境 C） | C98: NT$B | E98: 28 | G98: Assumed | H98: 同上 | I98: —
A99: capex26 | B99: FY2026 資本支出（公司預算） | C99: NT$B | E99: 53.7 | G99: Interested-party | H99: 工商時報 2026-07-29（2Q26 財報：營收、營業利益、業外、淨利）：董事會由 340 億上修至 537 億 | I99: 口袋學堂同；長交期設備另追加 176 億
A100: da26 | B100: FY2026 折舊攤提（公司預估） | C100: NT$B | E100: 20.8 | G100: Interested-party | H100: 富果 4Q25 法說摘要（2026-02-25，AI 摘要）：2025 年 188 億、2026 年約 208 億 | I100: 資本支出上修後可能更高（未找到更新）
A101: life | B101: 新增資產平均折舊年限 | C101: 年 | D101: 6 | E101: 8 | F101: 10 | G101: Assumed | H101: 載板設備與廠房混合；FY2025 折舊 188 ÷ 近 8 年資本支出約合 8 年 | I101: 會計年限：未找到
A102: phi | B102: 營業費用成長對營收成長的彈性 | C102: x | D102: 0.3 | E102: 0.6 | F102: 1 | G102: Assumed | H102: 1Q26 營業費用 39.7 億、2Q26 39.9 億（營收季增 15%；Q 頁推得） | I102: —
A103: nonop27 | B103: 營業外淨額 FY2027 | C103: NT$B | D103: 0 | E103: 2 | F103: 4 | G103: Assumed | H103: 2Q26 業外 89.2 億含金融資產評價利益 92.1 億等一次性項目（口袋學堂、工商時報）；不外推 | I103: 利息收入（GDR 募資約 US$14 億）＋權益法（Assumed）
A104: nonop28 | B104: 營業外淨額 FY2028 | C104: NT$B | D104: 0 | E104: 2 | F104: 4 | G104: Assumed | H104: 同上 | I104: —
A105: nonop29 | B105: 營業外淨額 FY2029 | C105: NT$B | D105: 0 | E105: 2 | F105: 4 | G105: Assumed | H105: 同上 | I105: —
A106: tax | B106: 所得稅與少數股權 ÷ 稅前利益 | C106: % | D106: 0.15 | E106: 0.18 | F106: 0.22 | G106: Derived | H106: 1H26：稅前 218.75、歸屬母公司 181.57 → 17.0%（工商時報） | I106: 2Q26 15.8%；營所稅 20%
A107: sh_g | B107: 股數年變動（可轉債轉換、員工酬勞） | C107: % | D107: 0 | E107: 0 | F107: 0.01 | G107: Assumed | H107: 可轉債 40 億（永豐 1Q26）；轉換價：未找到 | I107: —
A108: F. FY2026 錨點（1H26 實績＋3Q26 營收實績＋假設）
A109: q3_rev | B109: 3Q26 營收（月營收實績加總） | C109: NT$B | E109: 52.65 | G109: Verified | H109: TechNews 2026-10-08（9 月營收、前 9 月累計）：前 9 月 1,329.86 億 − 1H26 803.36 億 | I109: 三立 2026-10-19（本土法人；Q3 營收、Q4 預估、產能時程）：3Q26 526.5 億（季增 22.8%）
A110: q3_gm | B110: 3Q26 毛利率 | C110: % | D110: 0.255 | E110: 0.27 | F110: 0.285 | G110: Assumed | H110: 公司：3Q 毛利率可望優於 2Q 的 24.8%（2Q26 法說，Interested-party） | I110: 三立 2026-10-19（本土法人；Q3 營收、Q4 預估、產能時程）：法人估 27.2%
A111: q3_opx | B111: 3Q26 營業費用 | C111: NT$B | D111: 4 | E111: 4.3 | F111: 4.6 | G111: Assumed | H111: 1Q26 3.97、2Q26 3.99（Q 頁推得） | I111: —
A112: q4_g | B112: 4Q26 營收季增 | C112: % | D112: 0 | E112: 0.05 | F112: 0.1 | G112: Assumed | H112: 三立 2026-10-19（本土法人；Q3 營收、Q4 預估、產能時程）：法人估 4Q26 579.2 億（季增 10%） | I112: 公司未給指引
A113: q4_gm | B113: 4Q26 毛利率 | C113: % | D113: 0.265 | E113: 0.285 | F113: 0.305 | G113: Assumed | H113: 三立 2026-10-19（本土法人；Q3 營收、Q4 預估、產能時程）：法人估 30.5% | I113: —
A114: q4_opx | B114: 4Q26 營業費用 | C114: NT$B | D114: 4.1 | E114: 4.4 | F114: 4.8 | G114: Assumed | H114: 同上 | I114: —
A115: q_nonop | B115: 3Q、4Q26 營業外淨額（每季） | C115: NT$B | D115: 0 | E115: 1 | F115: 3 | G115: Assumed | H115: 1Q26 3.54、2Q26 8.92（含一次性評價利益） | I115: 3Q26 財報 2026-10-29 前後公布（stockanalysis 估計）
A116: q_sh | B116: 3Q、4Q26 加權股數（GDR 後） | C116: 十億股 | E116: 1.64 | G116: Interested-party | H116: stockanalysis.com（3037）：流通股數 1.64B（2026-10-22） | I116: 優分析 2026-07-06（GDR 5,000 萬單位、詢價）：5,000 萬單位（每單位 1 股，以每單位 US$27 ÷ 台股約 NT$880 推得）
A117: G. 共識與券商（只作 Recon 與 Val 對照，不作校準）
A118: cons_eps26 | B118: 共識 EPS FY2026（FactSet 中位數，2026-06） | C118: NT$ | D118: 10.5 | E118: 15.17 | F118: 18.55 | G118: Interested-party | H118: 鉅亨 2026-06-24（FactSet 22 位分析師） | I118: 2Q26 一次性業外（EPS 約 5 元）之前；本土法人 2026-10：23.42（三立）
A119: cons_eps27 | B119: 共識 EPS FY2027（FactSet 平均，2026-06） | C119: NT$ | D119: 21.27 | E119: 30.37 | F119: 41.37 | G119: Interested-party | H119: 鉅亨 2026-06-24（FactSet 22 位分析師） | I119: 美系券商 2026-10：37（經濟日報 2026-10-12（美系券商 EPS 預估））；本土法人 41.10（三立）
A120: cons_eps28 | B120: 共識 EPS FY2028（FactSet 平均，2026-06） | C120: NT$ | D120: 36.59 | E120: 48.52 | F120: 60.83 | G120: Interested-party | H120: 鉅亨 2026-06-24（FactSet 22 位分析師） | I120: 美系券商 2026-10：64.8（經濟日報）
A121: cons_rev27 | B121: 共識營收 FY2027（FactSet 平均，2026-06） | C121: NT$B | D121: 193.5 | E121: 255.2 | F121: 320.2 | G121: Interested-party | H121: 鉅亨 2026-06-24（FactSet 22 位分析師） | I121: —
A122: cons_rev28 | B122: 共識營收 FY2028（FactSet 平均，2026-06） | C122: NT$B | D122: 259.7 | E122: 326.5 | F122: 402.5 | G122: Interested-party | H122: 鉅亨 2026-06-24（FactSet 22 位分析師） | I122: —
A123: bk_eps27 | B123: 券商 EPS FY2027（2026-10 兩家平均：美系 37、本土 41.10） | C123: NT$ | D123: 37 | E123: 39.05 | F123: 41.1 | G123: Interested-party | H123: 經濟日報 2026-10-12（美系券商 EPS 預估） | I123: 三立 2026-10-19（本土法人；Q3 營收、Q4 預估、產能時程）
A124: H. 價格與市場資料
A125: px | B125: 股價（2026-10-22 收盤；10-23 收盤未取得） | C125: NT$ | E125: 1085 | G125: Interested-party | H125: stockanalysis.com（3037）：10-22 收盤 1,085、10-21 1,100 | I125: HiStock 2026-10-25 頁面：1,085
A126: fpe | B126: 前瞻 P/E（stockanalysis，10-22） | C126: x | E126: 42.28 | G126: Interested-party | H126: stockanalysis.com（3037） | I126: 口徑：頁面未明示（約未來 12 月）
A127: pe_ttm | B127: 近 12 月 P/E（stockanalysis，10-22） | C127: x | E127: 70.74 | G127: Interested-party | H127: stockanalysis.com（3037） | I127: HiStock 72.24
A128: cons_feps | B128: 共識前瞻 12 月 EPS（現價 ÷ 前瞻 P/E） | C128: NT$ | E128: =px/fpe -> 25.662252 | G128: Derived | H128: stockanalysis.com（3037） | I128: 直接數字：未找到
A129: cons_tp | B129: 市場共識目標價（賣方平均） | C129: NT$ | E129: 1317.37 | G129: Interested-party | H129: stockanalysis.com（3037）：19 位分析師平均 1,317.37（2026-10-22 擷取） | I129: 本土法人 1,500（三立 2026-10-19）；FactSet 2026-06：1,000
...

Sheet Q
A1: Q — FY2025 實績、1H26 實績、3Q26 營收實績與 FY2026 錨點（十億新台幣；EPS 新台幣、基本；股數十億股）。藍字＝輸入；黑字＝公式
A2: FY2026 錨點＝1Q、2Q26 財報實績＋3Q26 營收實績（月營收）與 3Q26 毛利率、費用假設＋4Q26 假設。3Q26 財報約 2026-10-29 公布，屆時以實績取代 E 欄（毛利率、費用、業外、淨利）
A3: 項目 | B3: FY2025A | C3: 1Q26（實績） | D3: 2Q26（實績） | E3: 3Q26（營收實績） | F3: 4Q26（模型） | G3: FY2026 錨點 | H3: 標記 | I3: 來源1（公司） | J3: 來源2／說明
A4: 營收 | B4: 131.241 | C4: =80.336-D4 -> 37.447 | D4: 42.889 | E4: =q3_rev -> 52.65 | F4: =E4*(1+q4_g) -> 55.2825 | G4: =SUM(C4:F4) -> 188.2685 | H4: Verified／Assumed（4Q） | I4: FY2025：stockanalysis 損益表（公司財報）；1H26、2Q26：工商時報 2026-07-29（公司財報） | J4: 1Q26 374.46 億（永豐 1Q26）；2Q26 428.89 億（Quartr 同）
A5: 毛利 | B5: 18.292 | C5: =C4*0.1796 -> 6.7254812 | D5: =D4*0.248 -> 10.636472 | E5: =E4*q3_gm -> 14.2155 | F5: =F4*q4_gm -> 15.755513 | G5: =SUM(C5:F5) -> 47.332966 | H5: Verified（毛利率 × 營收）／Assumed | I5: FY2025：stockanalysis 損益表（公司財報）；1H26、2Q26：工商時報 2026-07-29（公司財報） | J5: 毛利率：1Q26 17.96%、2Q26 24.8%（公司；Quartr 同）
A6: 毛利率 | B6: =B5/B4 -> 0.13937718 | C6: =C5/C4 -> 0.1796 | D6: =D5/D4 -> 0.248 | E6: =E5/E4 -> 0.27 | F6: =F5/F4 -> 0.285 | G6: =G5/G4 -> 0.25141203 | H6: Derived | I6: — | J6: FY2025 13.94%
A7: 營業費用 | B7: =B5-B8 -> 11.618 | C7: =C5-C8 -> 3.9684812 | D7: =D5-D8 -> 3.985472 | E7: =q3_opx -> 4.3 | F7: =q4_opx -> 4.4 | G7: =SUM(C7:F7) -> 16.653953 | H7: Derived／Assumed | I7: 毛利 − 營業利益 | J7: —
A8: 營業利益 | B8: 6.674 | C8: =9.408-D8 -> 2.757 | D8: 6.651 | E8: =E5-E7 -> 9.9155 | F8: =F5-F7 -> 11.355512 | G8: =SUM(C8:F8) -> 30.679012 | H8: Verified／Derived | I8: FY2025：stockanalysis 損益表（公司財報）；1H26、2Q26：工商時報 2026-07-29（公司財報） | J8: 1H26 94.08 億（口袋學堂；工商時報 94.07）
A9: 營業外淨額（FY2025＝淨利 − 營業利益，近似） | B9: =B11-B8 -> -0.001 | C9: =12.466-D9 -> 3.542 | D9: 8.924 | E9: =q_nonop -> 1 | F9: =q_nonop -> 1 | G9: =SUM(C9:F9) -> 14.466 | H9: Verified／Assumed | I9: FY2025：stockanalysis 損益表（公司財報）；1H26、2Q26：工商時報 2026-07-29（公司財報） | J9: 2Q26 含金融資產評價利益 92.1 億、湖口廠處分利益 5.6 億、欣興同泰減損 13.7 億（口袋學堂）
A10: 稅前利益 | C10: =C8+C9 -> 6.299 | D10: =D8+D9 -> 15.575 | E10: =E8+E9 -> 10.9155 | F10: =F8+F9 -> 12.355512 | G10: =SUM(C10:F10) -> 45.145012 | H10: Derived | I10: — | J10: 1H26 公布 218.75 億（核對見第 24 列）
A11: 歸屬母公司淨利 | B11: 6.673 | C11: =18.157-D11 -> 5.043 | D11: 13.114 | E11: =E10*(1-tax) -> 8.95071 | F11: =F10*(1-tax) -> 10.13152 | G11: =SUM(C11:F11) -> 37.23923 | H11: Verified／Derived | I11: FY2025：stockanalysis 損益表（公司財報）；1H26、2Q26：工商時報 2026-07-29（公司財報） | J11: 1Q26 50.43 億（永豐）；FY2025 業外與稅後淨利接近營業利益
A12: 所得稅與少數股權 | C12: =C10-C11 -> 1.256 | D12: =D10-D11 -> 2.461 | E12: =E10-E11 -> 1.96479 | F12: =F10-F11 -> 2.2239922 | G12: =SUM(C12:F12) -> 7.9057822 | H12: Derived | I12: — | J12: —
A13: 加權股數（十億股） | B13: =B11/B14 -> 1.523516 | C13: =C11/C14 -> 1.5375 | D13: =D11/D14 -> 1.5519527 | E13: =q_sh -> 1.64 | F13: =q_sh -> 1.64 | G13: =AVERAGE(C13:F13) -> 1.5923632 | H13: Derived | I13: 淨利 ÷ EPS；3Q 起含 GDR | J13: —
A14: EPS（基本） | B14: 4.38 | C14: 3.28 | D14: 8.45 | E14: =E11/E13 -> 5.45775 | F14: =F11/F13 -> 6.1777562 | G14: =G11/G13 -> 23.386141 | H14: Verified／Derived | I14: FY2025：stockanalysis 損益表（公司財報）；1H26、2Q26：工商時報 2026-07-29（公司財報） | J14: 1H26 11.70（工商時報）
A15: 折舊攤提（年度） | B15: 18.8 | G15: =da26 -> 20.8 | H15: Interested-party | I15: 富果 4Q25 法說摘要（2026-02-25，AI 摘要） | J15: stockanalysis 現金流量表 FY2025 18.46
A16: 資本支出（年度） | B16: 25.617 | G16: =capex26 -> 53.7 | H16: Verified／Interested-party | I16: FY2025：stockanalysis 現金流量表；FY2026：公司預算 537 億 | J16: —
A18: FY2026 產品別（錨點營收 × In 頁 C 節占比）
A19: ABF 載板 | G19: =G4*mx_abf -> 99.782305 | H19: Derived
A20: BT 載板 | G20: =G4*mx_bt -> 16.944165 | H20: Derived
A21: HDI＋PCB | G21: =G4*mx_pcb -> 58.363235 | H21: Derived
A22: 軟板與其他 | G22: =G4*(1-mx_abf-mx_bt-mx_pcb) -> 13.178795 | H22: Derived
A23: 檢查（參考；校準未使用券商數字）
A24: 1H26 稅前利益 自算 − 公司公布 21.875（應接近 0） | B24: =C10+D10-21.875 -> -0.001
A25: FY2026 營收年增 | B25: =G4/B4-1 -> 0.43452503
A26: FY2025→FY2026 現金毛利增量 ÷ 營收增量（含漲價；In 頁 ft_abf、ft_oth 的對照） | B26: =((G5+G15)-(B5+B15))/(G4-B4) -> 0.54431574
A27: FY2026 EPS ÷ 本土法人 23.42 − 1 | B27: =G14/23.42-1 -> -0.0014457105
A28: 4Q26 營收 ÷ 本土法人 57.92 − 1 | B28: =F4/57.92-1 -> -0.045536948

Sheet Units
A1: Units — 欣興在 AI 加速器載板的份額與每顆金額（口徑與 Ibiden 模型一致；情境 A）。份額合計＝Ibiden（ibiden/dist）＋欣興，其餘為三星電機、景碩、南電、AT&S 等
A3: 項目 | B3: 單位 | C3: CY2026 | D3: CY2027 | E3: CY2028 | F3: CY2029 | G3: 說明
A4: NVIDIA 加速器顆數 | B4: 百萬顆 | C4: =PL!D63 -> 7.6 | D4: =PL!E63 -> 9.7 | E4: =PL!F63 -> 9.5 | F4: =PL!G63 -> 10.6 | G4: markets/network
A5: 非 NVIDIA 加速器顆數 | B5: 百萬顆 | C5: =PL!D64 -> 7.6 | D5: =PL!E64 -> 14 | E5: =PL!F64 -> 17 | F5: =PL!G64 -> 19.55
A6: 每顆 NVIDIA 加速器載板金額（全市場） | B6: US$ | C6: =PL!D68 -> 215.3086 | D6: =PL!E68 -> 254.06414 | E6: =PL!F68 -> 284.8059 | F6: =PL!G68 -> 318.38302 | G6: Ibiden 模型 Units 頁同值（FY2026 校準 × 面積層數 × 溢價）
A7: 欣興份額：NVIDIA | B7: % | C7: =PL!D69 -> 0.25 | D7: =PL!E69 -> 0.27 | E7: =PL!F69 -> 0.29 | F7: =PL!G69 -> 0.3 | G7: Assumed
A8: Ibiden 份額：NVIDIA（70% × Ibiden 份額相對值） | B8: % | C8: =ib_sh26*1 -> 0.7 | D8: =ib_sh26*ibrel_27 -> 0.665 | E8: =ib_sh26*ibrel_28 -> 0.616 | F8: =ib_sh26*ibrel_29 -> 0.595 | G8: Ibiden 模型
A9: 合計：Ibiden＋欣興（NVIDIA） | B9: % | C9: =C7+C8 -> 0.95 | D9: =D7+D8 -> 0.935 | E9: =E7+E8 -> 0.906 | F9: =F7+F8 -> 0.895 | G9: 應 ≤ 100%；其餘為三星電機等
A10: 欣興份額：非 NVIDIA（金額） | B10: % | C10: =PL!D70 -> 0.3 | D10: =PL!E70 -> 0.31 | E10: =PL!F70 -> 0.32 | F10: =PL!G70 -> 0.33 | G10: Assumed
A11: Ibiden 份額：非 NVIDIA（Ibiden 權重 × 份額相對值 ÷ v_ot） | B11: % | C11: =ib_w_ot*1/v_ot -> 0.5 | D11: =ib_w_ot*ibrel_27/v_ot -> 0.475 | E11: =ib_w_ot*ibrel_28/v_ot -> 0.44 | F11: =ib_w_ot*ibrel_29/v_ot -> 0.425 | G11: Ibiden 模型的非 NVIDIA 權重假設份額相對值與 NVIDIA 同步
A12: 合計：Ibiden＋欣興（非 NVIDIA） | B12: % | C12: =C10+C11 -> 0.8 | D12: =D10+D11 -> 0.785 | E12: =E10+E11 -> 0.76 | F12: =F10+F11 -> 0.755 | G12: 應 ≤ 100%；其餘為景碩、南電、三星電機、AT&S
A13: 每顆 NVIDIA 加速器的欣興營收 | B13: US$ | C13: =PL!D68*PL!D69*PL!D67 -> 53.827149 | D13: =PL!E68*PL!E69*PL!E67 -> 72.027185 | E13: =PL!F68*PL!F69*PL!F67 -> 86.723398 | F13: =PL!G68*PL!G69*PL!G67 -> 100.29065 | G13: Ibiden 對照值見 ibiden/dist Units 頁
A14: 欣興加速器載板營收 | B14: US$M | C14: =PL!D71 -> 801.80921 | D14: =PL!E71 -> 1624.8799 | E14: =PL!F71 -> 2125.3213 | F14: =PL!G71 -> 2788.4813
A15: 欣興 AI 載板營收（含其他 AI） | B15: NT$B | C15: =PL!D81 -> 74.836729 | D15: =PL!E81 -> 123.23783 | E15: =PL!F81 -> 146.58476 | F15: =PL!G81 -> 169.00087
A16: 欣興 AI 載板營收 ÷ AI IT 資本支出 | B16: % | C16: =PL!D81/fx/itc_26 -> 0.0029450676 | D16: =PL!E81/fx/itc_27 -> 0.0024224187 | E16: =PL!F81/fx/itc_28 -> 0.0022730345 | F16: =PL!G81/fx/itc_29 -> 0.0023004995 | G16: × 每 GW IT capex 即每 GW 營收
A17: 每 GW 欣興 AI 載板營收（VR200 每 GW IT capex 37.59B） | B17: US$M | C17: =PL!D81/fx/itc_26*37.59*1000 -> 110.70509 | D17: =PL!E81/fx/itc_27*37.59*1000 -> 91.05872 | E17: =PL!F81/fx/itc_28*37.59*1000 -> 85.443365 | F17: =PL!G81/fx/itc_29*37.59*1000 -> 86.475776 | G17: Tokenomics IF_CapexIT（VR200 基準，經橋接表；與 Ibiden 模型相同係數）
A19: 讀法：欣興在 NVIDIA 加速器載板約占兩到三成、在 ASIC 約三成；加速器載板只占欣興 AI 載板約三成，其餘是交換器、伺服器 CPU 與網通 ASIC 載板（校準殘差，公司未揭露）。份額合計留給三星電機、景碩、南電、AT&S。

Sheet PL
A1: PL — 欣興損益（十億新台幣；EPS 新台幣、基本；歸屬母公司）。FY2025A 實績、FY2026 錨點（1H26 實績＋3Q26 營收實績＋假設；三情境相同），FY2027–FY2029 由驅動因子推導，FY2030 起為收斂法。三情境各一個完整推導區塊（本頁下方），頂端為摘要
A2: 灰底＝FY2030–FY2032 收斂法（上游顆數只到 2029）：營收年增線性收斂到 fade_g、淨利率線性收斂到 fade_m（In 頁 I 節），非驅動因子推導
A3: 情境／項目 | B3: 單位 | C3: FY2025A | D3: FY2026（錨點） | E3: FY2027 | F3: FY2028 | G3: FY2029 | H3: FY2030（收斂） | I3: FY2031（收斂） | J3: FY2032（收斂） | K3: 說明
A4: 情境 A
A5: 營收 | B5: NT$B | C5: =C88 -> 131.241 | D5: =D88 -> 188.2685 | E5: =E88 -> 245.84265 | F5: =F88 -> 278.51347 | G5: =G88 -> 308.3178 | H5: =H88 -> 336.47999 | I5: =I88 -> 361.94167 | J5: =J88 -> 383.65817
A6: 營收年增 | B6: % | D6: =D89 -> 0.43452503 | E6: =E89 -> 0.30580875 | F6: =F89 -> 0.13289317 | G6: =G89 -> 0.10701217 | H6: =H89 -> 0.091341446 | I6: =I89 -> 0.075670723 | J6: =J89 -> 0.06
A7: ABF 載板 | B7: NT$B | D7: =D79 -> 99.782305 | E7: =E79 -> 148.51349 | F7: =F79 -> 173.04952 | G7: =G79 -> 196.25957
A8: AI 載板 | B8: NT$B | D8: =D81 -> 74.836729 | E8: =E81 -> 123.23783 | F8: =F81 -> 146.58476 | G8: =G81 -> 169.00087
A9: ABF 需求滿足率 | B9: % | D9: =D80 -> 1 | E9: =E80 -> 0.98372057 | F9: =F80 -> 1 | G9: =G80 -> 1
A10: 毛利率 | B10: % | C10: =C98 -> 0.13937718 | D10: =D98 -> 0.25141203 | E10: =E98 -> 0.29584384 | F10: =F98 -> 0.28779177 | G10: =G98 -> 0.27895676
A11: 折舊攤提 | B11: NT$B | C11: =C94 -> 18.8 | D11: =D94 -> 20.8 | E11: =E94 -> 24.9125 | F11: =F94 -> 28.673437 | G11: =G94 -> 31.339258 | H11: =H94 -> 34.201831 | I11: =I94 -> 36.789908 | J11: =J94 -> 38.997303
A12: 營業利益率 | B12: % | C12: =C101 -> 0.050853011 | D12: =D101 -> 0.16295351 | E12: =E101 -> 0.21567179 | F12: =F101 -> 0.21138153 | G12: =G101 -> 0.20550108
A13: 歸屬母公司淨利 | B13: NT$B | C13: =C105 -> 6.673 | D13: =D105 -> 37.23923 | E13: =E105 -> 45.117487 | F13: =F105 -> 49.915535 | G13: =G105 -> 53.594905 | H13: =H105 -> 58.490342 | I13: =I105 -> 62.916348 | J13: =J105 -> 66.691329
A14: 淨利率 | B14: % | C14: =C109 -> 0.050845391 | D14: =D109 -> 0.19779852 | E14: =E109 -> 0.1835218 | F14: =F109 -> 0.17922126 | G14: =G109 -> 0.17383007 | H14: =H109 -> 0.17383007 | I14: =I109 -> 0.17383007 | J14: =J109 -> 0.17383007
A15: EPS | B15: NT$ | C15: =C107 -> 4.38 | D15: =D107 -> 23.386141 | E15: =E107 -> 27.510663 | F15: =F107 -> 30.436302 | G15: =G107 -> 32.67982 | H15: =H107 -> 35.664842 | I15: =I107 -> 38.363627 | J15: =J107 -> 40.665444
A16: EPS 年增 | B16: % | D16: =D108 -> 4.3393017 | E16: =E108 -> 0.17636606 | F16: =F108 -> 0.10634562 | G16: =G108 -> 0.073711936 | H16: =H108 -> 0.091341446 | I16: =I108 -> 0.075670723 | J16: =J108 -> 0.06
A18: 情境 B
A19: 營收 | B19: NT$B | C19: =C143 -> 131.241 | D19: =D143 -> 188.2685 | E19: =E143 -> 245.84265 | F19: =F143 -> 238.72615 | G19: =G143 -> 274.32961 | H19: =H143 -> 305.2629 | I19: =I143 -> 328.57882 | J19: =J143 -> 341.72197
A20: 營收年增 | B20: % | D20: =D144 -> 0.43452503 | E20: =E144 -> 0.30580875 | F20: =F144 -> -0.028947397 | G20: =G144 -> 0.14913936 | H20: =H144 -> 0.11275957 | I20: =I144 -> 0.076379786 | J20: =J144 -> 0.04
A21: ABF 載板 | B21: NT$B | D21: =D134 -> 99.782305 | E21: =E134 -> 148.51349 | F21: =F134 -> 143.73257 | G21: =G134 -> 170.90944
A22: AI 載板 | B22: NT$B | D22: =D136 -> 74.836729 | E22: =E136 -> 123.23783 | F22: =F136 -> 117.26781 | G22: =G136 -> 143.65074
A23: ABF 需求滿足率 | B23: % | D23: =D135 -> 1 | E23: =E135 -> 0.98372057 | F23: =F135 -> 1 | G23: =G135 -> 1
A24: 毛利率 | B24: % | C24: =C153 -> 0.13937718 | D24: =D153 -> 0.25141203 | E24: =E153 -> 0.29584384 | F24: =F153 -> 0.26720807 | G24: =G153 -> 0.26856773
A25: 折舊攤提 | B25: NT$B | C25: =C149 -> 18.8 | D25: =D149 -> 20.8 | E25: =E149 -> 24.9125 | F25: =F149 -> 27.798437 | G25: =G149 -> 29.573633 | H25: =H149 -> 32.908343 | I25: =I149 -> 35.421875 | J25: =J149 -> 36.83875
A26: 營業利益率 | B26: % | C26: =C156 -> 0.050853011 | D26: =D156 -> 0.16295351 | E26: =E156 -> 0.21567179 | F26: =F156 -> 0.18608005 | G26: =G156 -> 0.19165134
A27: 歸屬母公司淨利 | B27: NT$B | C27: =C160 -> 6.673 | D27: =D160 -> 37.23923 | E27: =E160 -> 45.117487 | F27: =F160 -> 38.066182 | G27: =G160 -> 44.752024 | H27: =H160 -> 48.138301 | I27: =I160 -> 50.028367 | J27: =J160 -> 50.171305
A28: 淨利率 | B28: % | C28: =C164 -> 0.050845391 | D28: =D164 -> 0.19779852 | E28: =E164 -> 0.1835218 | F28: =F164 -> 0.15945543 | G28: =G164 -> 0.16313231 | H28: =H164 -> 0.15769457 | I28: =I164 -> 0.15225682 | J28: =J164 -> 0.14681908
A29: EPS | B29: NT$ | C29: =C162 -> 4.38 | D29: =D162 -> 23.386141 | E29: =E162 -> 27.510663 | F29: =F162 -> 23.211086 | G29: =G162 -> 27.287819 | H29: =H162 -> 29.352623 | I29: =I162 -> 30.505102 | J29: =J162 -> 30.592259
A30: EPS 年增 | B30: % | D30: =D163 -> 4.3393017 | E30: =E163 -> 0.17636606 | F30: =F163 -> -0.15628764 | G30: =G163 -> 0.17563732 | H30: =H163 -> 0.075667587 | I30: =I163 -> 0.039263242 | J30: =J163 -> 0.0028571429
A32: 情境 C
A33: 營收 | B33: NT$B | C33: =C198 -> 131.241 | D33: =D198 -> 188.2685 | E33: =E198 -> 245.84265 | F33: =F198 -> 198.93883 | G33: =G198 -> 217.68265 | H33: =H198 -> 232.80709 | I33: =I198 -> 243.2228 | J33: =J198 -> 248.08725
A34: 營收年增 | B34: % | D34: =D199 -> 0.43452503 | E34: =E199 -> 0.30580875 | F34: =F199 -> -0.19078797 | G34: =G199 -> 0.094218975 | H34: =H199 -> 0.069479317 | I34: =I199 -> 0.044739658 | J34: =J199 -> 0.02
A35: ABF 載板 | B35: NT$B | D35: =D189 -> 99.782305 | E35: =E189 -> 148.51349 | F35: =F189 -> 114.41562 | G35: =G189 -> 128.65922
A36: AI 載板 | B36: NT$B | D36: =D191 -> 74.836729 | E36: =E191 -> 123.23783 | F36: =F191 -> 87.950854 | G36: =G191 -> 101.40052
A37: ABF 需求滿足率 | B37: % | D37: =D190 -> 1 | E37: =E190 -> 0.98372057 | F37: =F190 -> 1 | G37: =G190 -> 1
A38: 毛利率 | B38: % | C38: =C208 -> 0.13937718 | D38: =D208 -> 0.25141203 | E38: =E208 -> 0.29584384 | F38: =F208 -> 0.23901932 | G38: =G208 -> 0.24143537
A39: 折舊攤提 | B39: NT$B | C39: =C204 -> 18.8 | D39: =D204 -> 20.8 | E39: =E204 -> 24.9125 | F39: =F204 -> 26.798437 | G39: =G204 -> 27.198633 | H39: =H204 -> 29.088375 | I39: =I204 -> 30.389779 | J39: =J204 -> 30.997575
A40: 營業利益率 | B40: % | C40: =C211 -> 0.050853011 | D40: =D211 -> 0.16295351 | E40: =E211 -> 0.21567179 | F40: =F211 -> 0.15128641 | G40: =G211 -> 0.1567242
A41: 歸屬母公司淨利 | B41: NT$B | C41: =C215 -> 6.673 | D41: =D215 -> 37.23923 | E41: =E215 -> 45.117487 | F41: =F215 -> 26.319329 | G41: =G215 -> 29.615233 | H41: =H215 -> 29.561354 | I41: =I215 -> 28.677925 | J41: =J215 -> 27.001369
A42: 淨利率 | B42: % | C42: =C219 -> 0.050845391 | D42: =D219 -> 0.19779852 | E42: =E219 -> 0.1835218 | F42: =F219 -> 0.1322986 | G42: =G219 -> 0.13604775 | H42: =H219 -> 0.1269779 | I42: =I219 -> 0.11790805 | J42: =J219 -> 0.1088382
A43: EPS | B43: NT$ | C43: =C217 -> 4.38 | D43: =D217 -> 23.386141 | E43: =E217 -> 27.510663 | F43: =F217 -> 16.048371 | G43: =G217 -> 18.058069 | H43: =H217 -> 18.025216 | I43: =I217 -> 17.48654 | J43: =J217 -> 16.46425
A44: EPS 年增 | B44: % | D44: =D218 -> 4.3393017 | E44: =E218 -> 0.17636606 | F44: =F218 -> -0.41664906 | G44: =G218 -> 0.12522753 | H44: =H218 -> -0.0018193044 | I44: =I218 -> -0.029884603 | J44: =J218 -> -0.058461538
A46: 核對（應為 0）：FY2026 模型 − 錨點
A47: 三情境：營收差（NT$B） | D47: =ABS(D88-a26_rev)+ABS(D143-a26_rev)+ABS(D198-a26_rev) -> 0
A48: 三情境：EPS 差（NT$） | D48: =ABS(D107-a26_eps)+ABS(D162-a26_eps)+ABS(D217-a26_eps) -> 0
A49: 情境 A：其他 AI 載板 FY2026 應 > 0（1＝是） | D49: =IF(D75>0,0,1) -> 0
A60: 情境 A（順利）：顆數基準；資本支出 FY2027–29 為 550／500／450 億
A61: 項目 | B61: 單位 | C61: FY2025A | D61: FY2026（錨點） | E61: FY2027 | F61: FY2028 | G61: FY2029 | H61: FY2030（收斂） | I61: FY2031（收斂） | J61: FY2032（收斂） | K61: 說明
A62: A. AI 加速器載板（口徑與 Ibiden 一致；D 欄＝FY2026 校準年）
A63: NVIDIA 加速器顆數 × 情境係數 | B63: 百萬顆 | D63: =(u_bw_26+u_rb_26+u_ru_26+u_hp_26)*1 -> 7.6 | E63: =(u_bw_27+u_rb_27+u_ru_27+u_hp_27)*1*1 -> 9.7 | F63: =(u_bw_28+u_rb_28+u_ru_28+u_hp_28)*um28_A*1 -> 9.5 | G63: =(u_bw_28*(1+g29_bw)+u_rb_28*(1+g29_rb)+u_ru_28*(1+g29_ru)+u_hp_28*(1+g29_hp))*um29_A*1 -> 10.6 | K63: markets/network In：Blackwell、Rubin、Rubin Ultra、Hopper
A64: 非 NVIDIA 加速器顆數 × 情境係數 | B64: 百萬顆 | D64: =(u_amd_26+u_tpu_26+u_trn_26+u_oth_26)*1 -> 7.6 | E64: =(u_amd_27+u_tpu_27+u_trn_27+u_oth_27)*1*1 -> 14 | F64: =(u_amd_28+u_tpu_28+u_trn_28+u_oth_28)*um28_A*1 -> 17 | G64: =(u_amd_28*(1+g29_amd)+u_tpu_28*(1+g29_tpu)+u_trn_28*(1+g29_trn)+u_oth_28*(1+g29_oth))*um29_A*1 -> 19.55 | K64: AMD、TPU、Trainium、其他 ASIC
A65: 每顆載板面積與層數指數（FY2026＝1） | B65: x | D65: =1 -> 1 | E65: =D65*(1+g_asp) -> 1.18 | F65: =E65*(1+g_asp) -> 1.3924 | G65: =F65*(1+g_asp) -> 1.643032 | K65: Ibiden 模型 g_asp（Analogy）
A66: ABF 價格溢價指數（全市場；FY2026＝1） | B66: x | D66: =1 -> 1 | E66: =ibpp_27 -> 1 | F66: =ibpp_28 -> 0.95 | G66: =ibpp_29 -> 0.9 | K66: Ibiden 模型 pp（Assumed）
A67: 欣興漲價年度化（CY2026 基期；FY2026＝1） | B67: x | D67: =1 -> 1 | E67: =1+carry -> 1.05 | F67: =1+carry -> 1.05 | G67: =1+carry -> 1.05 | K67: In 頁 carry（Assumed）
A68: 每顆 NVIDIA 加速器載板金額（全市場）＝ FY2026 金額 × 面積層數 × 溢價 | B68: US$／顆 | D68: =v26*D65*D66 -> 215.3086 | E68: =v26*E65*E66 -> 254.06414 | F68: =v26*F65*F66 -> 284.8059 | G68: =v26*G65*G66 -> 318.38302 | K68: FY2026 金額取自 Ibiden 模型 Units 頁（權威）
A69: 欣興份額：NVIDIA 加速器載板 | B69: % | D69: =sh_nv_26 -> 0.25 | E69: =sh_nv_27 -> 0.27 | F69: =sh_nv_28 -> 0.29 | G69: =sh_nv_29 -> 0.3
A70: 欣興份額：非 NVIDIA 加速器載板（金額） | B70: % | D70: =sh_ot_26 -> 0.3 | E70: =sh_ot_27 -> 0.31 | F70: =sh_ot_28 -> 0.32 | G70: =sh_ot_29 -> 0.33
A71: 欣興加速器載板營收 ＝（NVIDIA × 金額 × 份額 ＋ 非 NVIDIA × 金額 × v_ot × 份額）× 漲價年度化 | B71: US$M | D71: =(D63*D68*D69+D64*D68*v_ot*D70)*D67 -> 801.80921 | E71: =(E63*E68*E69+E64*E68*v_ot*E70)*E67 -> 1624.8799 | F71: =(F63*F68*F69+F64*F68*v_ot*F70)*F67 -> 2125.3213 | G71: =(G63*G68*G69+G64*G68*v_ot*G70)*G67 -> 2788.4813
A72: 欣興加速器載板營收（新台幣） | B72: NT$B | D72: =D71*fx/1000 -> 26.058799 | E72: =E71*fx/1000 -> 52.808598 | F72: =F71*fx/1000 -> 69.072944 | G72: =G71*fx/1000 -> 90.625642
A73: B. ABF 需求與產能（營收＝MIN（需求, 產能））
A74: AI 載板需求（FY2026＝ABF × AI 占比） | B74: NT$B | D74: =a26_abf*ai_abf -> 74.836729 | K74: 公司：載板 AI 占比上半年逾 60%、下半年 70%
A75: 其他 AI 載板需求（交換器、伺服器 CPU、網通 ASIC） | B75: NT$B | D75: =D74-D72 -> 48.777929 | E75: =$D75*(itc_27/itc_26)^el_o*1*1*E66*E67 -> 72.468672 | F75: =$D75*(itc_28/itc_26)^el_o*um28_A*1*F66*F67 -> 77.511813 | G75: =$D75*(itc_29/itc_26)^el_o*um29_A*1*G66*G67 -> 78.375225 | K75: FY2026＝校準殘差（Derived）；之後 × AI IT 資本支出成長 ^ 彈性 × 溢價
A76: 非 AI ABF 需求（PC、一般伺服器） | B76: NT$B | D76: =a26_abf-D74 -> 24.945576 | E76: =D76*(1+g_nai) -> 25.693944 | F76: =E76*(1+g_nai) -> 26.464762 | G76: =F76*(1+g_nai) -> 27.258705
A77: ABF 需求合計 | B77: NT$B | D77: =D72+D75+D76 -> 99.782305 | E77: =E72+E75+E76 -> 150.97121 | F77: =F72+F75+F76 -> 173.04952 | G77: =G72+G75+G76 -> 196.25957
A78: ABF 產能上限（FY2026 營收 × 產能指數 × 組合 × 溢價） | B78: NT$B | D78: =a26_abf -> 99.782305 | E78: =$D77*cap_27*(1+g_mix)^1*E66*E67 -> 148.51349 | F78: =$D77*cap_28*(1+g_mix)^2*F66*F67 -> 186.54944 | G78: =$D77*cap_29*(1+g_mix)^3*G66*G67 -> 218.31483 | K78: FY2026 稼動率逾 90%，以 FY2026 營收為產能基準
A79: ABF 載板營收 ＝ MIN（需求, 產能） | B79: NT$B | D79: =a26_abf -> 99.782305 | E79: =MIN(E77,E78) -> 148.51349 | F79: =MIN(F77,F78) -> 173.04952 | G79: =MIN(G77,G78) -> 196.25957
A80: 需求滿足率（營收 ÷ 需求；< 100% 表示產能受限） | B80: % | D80: =D79/D77 -> 1 | E80: =E79/E77 -> 0.98372057 | F80: =F79/F77 -> 1 | G80: =G79/G77 -> 1
A81: AI 載板營收（加速器＋其他 AI，乘滿足率） | B81: NT$B | D81: =(D72+D75)*D80 -> 74.836729 | E81: =(E72+E75)*E80 -> 123.23783 | F81: =(F72+F75)*F80 -> 146.58476 | G81: =(G72+G75)*G80 -> 169.00087
A82: 加速器載板 ÷ AI 載板 | B82: % | D82: =D72/(D72+D75) -> 0.34820869 | E82: =E72/(E72+E75) -> 0.42153375 | F82: =F72/(F72+F75) -> 0.47121505 | G82: =G72/(G72+G75) -> 0.53624365
A83: C. 其他產品與合計
A84: BT 載板 | B84: NT$B | D84: =a26_bt -> 16.944165 | E84: =D84*(1+g_bt) -> 17.791373 | F84: =E84*(1+g_bt) -> 18.680942 | G84: =F84*(1+g_bt) -> 19.614989
A85: AI HDI／PCB | B85: NT$B | D85: =a26_pcb*ai_pcb -> 37.936103 | E85: =D85*(1+g_pai_27) -> 45.523323 | F85: =D85*(1+g_pai_27)*(1+g_pai_28)*um28_A -> 52.351822 | G85: =D85*(1+g_pai_27)*(1+g_pai_28)*(1+g_pai_29)*um29_A -> 57.587004 | K85: 基準路徑 × 顆數情境係數
A86: 非 AI HDI／PCB | B86: NT$B | D86: =a26_pcb*(1-ai_pcb) -> 20.427132 | E86: =D86*(1+g_pcbn) -> 20.835675 | F86: =E86*(1+g_pcbn) -> 21.252388 | G86: =F86*(1+g_pcbn) -> 21.677436
A87: 軟板與其他 | B87: NT$B | D87: =a26_fpc -> 13.178795 | E87: =D87*(1+g_fpc) -> 13.178795 | F87: =E87*(1+g_fpc) -> 13.178795 | G87: =F87*(1+g_fpc) -> 13.178795
A88: 營收 | B88: NT$B | C88: =a25_rev -> 131.241 | D88: =D79+D84+D85+D86+D87 -> 188.2685 | E88: =E79+E84+E85+E86+E87 -> 245.84265 | F88: =F79+F84+F85+F86+F87 -> 278.51347 | G88: =G79+G84+G85+G86+G87 -> 308.3178 | H88: =G88*(1+H89) -> 336.47999 | I88: =H88*(1+I89) -> 361.94167 | J88: =I88*(1+J89) -> 383.65817 | K88: FY2030 起為收斂法：營收年增由 FY2029 線性收斂到 fade_g、淨利率收斂到 fade_m（FY2032 達到），非驅動因子推導
A89: 營收年增 | B89: % | D89: =D88/C88-1 -> 0.43452503 | E89: =E88/D88-1 -> 0.30580875 | F89: =F88/E88-1 -> 0.13289317 | G89: =G88/F88-1 -> 0.10701217 | H89: =$G89+(fade_gA-$G89)*1/3 -> 0.091341446 | I89: =$G89+(fade_gA-$G89)*2/3 -> 0.075670723 | J89: =$G89+(fade_gA-$G89)*3/3 -> 0.06
A90: ABF ÷ 營收 | B90: % | D90: =D79/D88 -> 0.53 | E90: =E79/E88 -> 0.60409976 | F90: =F79/F88 -> 0.62133268 | G90: =G79/G88 -> 0.63654961
A91: AI（載板＋HDI／PCB）÷ 營收 | B91: % | D91: =(D81+D85)/D88 -> 0.599 | E91: =(E81+E85)/E88 -> 0.68646001 | F91: =(F81+F85)/F88 -> 0.71427993 | G91: =(G81+G85)/G88 -> 0.73491661 | K91: 公司：2H26 約 70%
A92: D. 擴產折舊、毛利與損益
A93: 資本支出 | B93: NT$B | C93: =a25_cx -> 25.617 | D93: =capex26 -> 53.7 | E93: =cx27_A -> 55 | F93: =cx28_A -> 50 | G93: =cx29_A -> 45 | H93: =H88*H110 -> 46.077345 | I93: =I88*I110 -> 46.30152 | J93: =J88*J110 -> 45.621328
A94: 折舊攤提 ＝ 前一年 ×（1 − 1／年限）＋ 前一年資本支出 ÷ 年限 | B94: NT$B | C94: =a25_da -> 18.8 | D94: =da26 -> 20.8 | E94: =D94*(1-1/life)+D93/life -> 24.9125 | F94: =E94*(1-1/life)+E93/life -> 28.673437 | G94: =F94*(1-1/life)+F93/life -> 31.339258 | H94: =H88*H95 -> 34.201831 | I94: =I88*I95 -> 36.789908 | J94: =J88*J95 -> 38.997303 | K94: 新產能前一年投入、當年開始折舊（近似）
A95: 折舊 ÷ 營收 | B95: % | C95: =C94/C88 -> 0.14324792 | D95: =D94/D88 -> 0.11048051 | E95: =E94/E88 -> 0.10133514 | F95: =F94/F88 -> 0.10295171 | G95: =G94/G88 -> 0.10164596 | H95: =$G95 -> 0.10164596 | I95: =$G95 -> 0.10164596 | J95: =$G95 -> 0.10164596
A96: 漲價溢價營收（相對 FY2026 價格；全數落在毛利） | B96: NT$B | E96: =E81*(1-1/(E66*E67)) -> 5.868468 | F96: =F81*(1-1/(F66*F67)) -> -0.36738034 | G96: =G81*(1-1/(G66*G67)) -> -9.8360293 | K96: AI 載板營收 ×（1 − 1／價格指數）
A97: 毛利 ＝ FY2026 ＋ ABF 現金毛利增量 ＋ 其他產品現金毛利增量 ＋ 溢價 − 折舊增量 | B97: NT$B | C97: =a25_gp -> 18.292 | D97: =a26_gp -> 47.332966 | E97: =$D97+ft_abf*(E79-E96-$D79)+ft_oth*((E88-E79)-($D88-$D79))+E96-(E94-$D94) -> 72.731034 | F97: =$D97+ft_abf*(F79-F96-$D79)+ft_oth*((F88-F79)-($D88-$D79))+F96-(F94-$D94) -> 80.153883 | G97: =$D97+ft_abf*(G79-G96-$D79)+ft_oth*((G88-G79)-($D88-$D79))+G96-(G94-$D94) -> 86.007334 | K97: 流通率為現金毛利口徑；折舊另計
A98: 毛利率 | B98: % | C98: =C97/C88 -> 0.13937718 | D98: =D97/D88 -> 0.25141203 | E98: =E97/E88 -> 0.29584384 | F98: =F97/F88 -> 0.28779177 | G98: =G97/G88 -> 0.27895676
A99: 營業費用 | B99: NT$B | C99: =a25_opx -> 11.618 | D99: =a26_opx -> 16.653953 | E99: =D99*(1+phi*E89) -> 19.709708 | F99: =E99*(1+phi*F89) -> 21.281279 | G99: =F99*(1+phi*G89) -> 22.647693
A100: 營業利益 | B100: NT$B | C100: =C97-C99 -> 6.674 | D100: =D97-D99 -> 30.679012 | E100: =E97-E99 -> 53.021326 | F100: =F97-F99 -> 58.872603 | G100: =G97-G99 -> 63.359641
A101: 營業利益率 | B101: % | C101: =C100/C88 -> 0.050853011 | D101: =D100/D88 -> 0.16295351 | E101: =E100/E88 -> 0.21567179 | F101: =F100/F88 -> 0.21138153 | G101: =G100/G88 -> 0.20550108
A102: 營業外淨額 | B102: NT$B | C102: =a25_nonop -> -0.001 | D102: =a26_nonop -> 14.466 | E102: =nonop27 -> 2 | F102: =nonop28 -> 2 | G102: =nonop29 -> 2 | K102: FY2026 含 2Q26 一次性評價利益
A103: 稅前利益 | B103: NT$B | C103: =C100+C102 -> 6.673 | D103: =D100+D102 -> 45.145012 | E103: =E100+E102 -> 55.021326 | F103: =F100+F102 -> 60.872603 | G103: =G100+G102 -> 65.359641
A104: 所得稅與少數股權 | B104: NT$B | E104: =E103*tax -> 9.9038387 | F104: =F103*tax -> 10.957069 | G104: =G103*tax -> 11.764735
A105: 歸屬母公司淨利 | B105: NT$B | C105: =a25_ni -> 6.673 | D105: =a26_ni -> 37.23923 | E105: =E103-E104 -> 45.117487 | F105: =F103-F104 -> 49.915535 | G105: =G103-G104 -> 53.594905 | H105: =H88*H109 -> 58.490342 | I105: =I88*I109 -> 62.916348 | J105: =J88*J109 -> 66.691329
A106: 加權股數 | B106: 十億股 | C106: =a25_sh -> 1.523516 | D106: =a26_sh -> 1.5923632 | E106: =a26_shend*(1+sh_g) -> 1.64 | F106: =E106*(1+sh_g) -> 1.64 | G106: =F106*(1+sh_g) -> 1.64 | H106: =G106*(1+sh_g) -> 1.64 | I106: =H106*(1+sh_g) -> 1.64 | J106: =I106*(1+sh_g) -> 1.64
A107: EPS（基本） | B107: NT$ | C107: =C105/C106 -> 4.38 | D107: =D105/D106 -> 23.386141 | E107: =E105/E106 -> 27.510663 | F107: =F105/F106 -> 30.436302 | G107: =G105/G106 -> 32.67982 | H107: =H105/H106 -> 35.664842 | I107: =I105/I106 -> 38.363627 | J107: =J105/J106 -> 40.665444
A108: EPS 年增 | B108: % | D108: =D107/C107-1 -> 4.3393017 | E108: =E107/D107-1 -> 0.17636606 | F108: =F107/E107-1 -> 0.10634562 | G108: =G107/F107-1 -> 0.073711936 | H108: =H107/G107-1 -> 0.091341446 | I108: =I107/H107-1 -> 0.075670723 | J108: =J107/I107-1 -> 0.06
A109: 淨利率（歸屬母公司淨利 ÷ 營收） | B109: % | C109: =C105/C88 -> 0.050845391 | D109: =D105/D88 -> 0.19779852 | E109: =E105/E88 -> 0.1835218 | F109: =F105/F88 -> 0.17922126 | G109: =G105/G88 -> 0.17383007 | H109: =$G109+(fade_mA-$G109)*1/3 -> 0.17383007 | I109: =$G109+(fade_mA-$G109)*2/3 -> 0.17383007 | J109: =$G109+(fade_mA-$G109)*3/3 -> 0.17383007
A110: 資本支出 ÷ 營收 | B110: % | C110: =C93/C88 -> 0.19519053 | D110: =D93/D88 -> 0.28523093 | E110: =E93/E88 -> 0.22372033 | F110: =F93/F88 -> 0.17952453 | G110: =G93/G88 -> 0.1459533 | H110: =$G110+($G95*(1+tp_g)^(life/2)-$G110)*1/3 -> 0.13693933 | I110: =$G110+($G95*(1+tp_g)^(life/2)-$G110)*2/3 -> 0.12792536 | J110: =$G110+($G95*(1+tp_g)^(life/2)-$G110)*3/3 -> 0.11891139 | K110: FY2030 起：資本支出率由 FY2029 線性收斂到 折舊率 ×（1＋tp_g）^（年限／2）（穩態更新）；折舊率維持 FY2029
A111: 股東現金流 ＝ 淨利 ＋ 折舊 − 資本支出 | B111: NT$B | E111: =E105+E94-E93 -> 15.029987 | F111: =F105+F94-F93 -> 28.588972 | G111: =G105+G94-G93 -> 39.934163 | H111: =H105+H94-H93 -> 46.614828 | I111: =I105+I94-I93 -> 53.404736 | J111: =J105+J94-J93 -> 60.067303 | K111: 不含客戶預付款（光復二廠、楊梅二廠由客戶全額預付）與營運資金變動
A112: 每股股東現金流 | B112: NT$ | E112: =E111/E106 -> 9.1646265 | F112: =F111/F106 -> 17.4323 | G112: =G111/G106 -> 24.3501 | H112: =H111/H106 -> 28.423675 | I112: =I111/I106 -> 32.563864 | J112: =J111/J106 -> 36.626404
A115: 情境 B（平平）：CY2028 顆數 ×0.8、CY2029 ×0.85；資本支出 480／420／380 億
...

Sheet Val
A1: Val — P/E 估值（新台幣）。結論用「現價 ÷ FY2027、FY2028 EPS（模型）」；目標價＝DCF 與 Comparable 加權（第 0 節）；十年 P/E 規則值（第 3 節，年底落後 P/E）只作參考
A2: 循環位置：欣興不是設備股，不套設備市場見頂年；以本模型營收最高的會計年度為見頂年（比照 Ibiden、NVIDIA；FY(t)＝CY(t)）。營收到 FY2029 仍在增加時，見頂年未知，判為中段
A4: 0. 目標價
A5: 0.1 DCF（股東權益現金流，FY2027–FY2032 明確期＋FY2032 後永續）
A6: 項目 | B6: A（順利） | C6: B（平平） | D6: C（不如預期） | E6: 說明
A7: 情境 EPS（FY2027–FY2032） | E7: PL 頁各情境；FY2030 起為收斂法
A8: FY2027 | B8: =PL!E15 -> 27.510663 | C8: =PL!E29 -> 27.510663 | D8: =PL!E43 -> 27.510663
A9: FY2028 | B9: =PL!F15 -> 30.436302 | C9: =PL!F29 -> 23.211086 | D9: =PL!F43 -> 16.048371
A10: FY2029 | B10: =PL!G15 -> 32.67982 | C10: =PL!G29 -> 27.287819 | D10: =PL!G43 -> 18.058069
A11: FY2030 | B11: =PL!H15 -> 35.664842 | C11: =PL!H29 -> 29.352623 | D11: =PL!H43 -> 18.025216
A12: FY2031 | B12: =PL!I15 -> 38.363627 | C12: =PL!I29 -> 30.505102 | D12: =PL!I43 -> 17.48654
A13: FY2032 | B13: =PL!J15 -> 40.665444 | C13: =PL!J29 -> 30.592259 | D13: =PL!J43 -> 16.46425
A14: 股東現金流＝EPS ×（1 − tp_g ÷ tp_roe） | E14: 方法：欣興資本密集、模型有資本支出與折舊，改用每股（淨利＋折舊－資本支出）（PL 頁「每股股東現金流」；FY2030 起資本支出率收斂到穩態更新）
A15: 參考：再投資率（tp_g ÷ tp_roe，上限 0.8） | B15: =MIN(tp_g/tp_roe,0.8) -> 0.46296296 | E15: ROE 為近三年平均（In 頁 tp_roe）；本模型不採用，只作對照（第 25 列）
A16: FY2027 | B16: =PL!E112 -> 9.1646265 | C16: =PL!E167 -> 13.432919 | D16: =PL!E222 -> 18.310968
A17: FY2028 | B17: =PL!F112 -> 17.4323 | C17: =PL!F167 -> 14.551597 | D17: =PL!F222 -> 14.096199
A18: FY2029 | B18: =PL!G112 -> 24.3501 | C18: =PL!G167 -> 22.149791 | D18: =PL!G222 -> 17.569431
A19: FY2030 | B19: =PL!H112 -> 28.423675 | C19: =PL!H167 -> 24.404898 | D19: =PL!H222 -> 16.672574
A20: FY2031 | B20: =PL!I112 -> 32.563864 | C20: =PL!I167 -> 26.007924 | D20: =PL!I222 -> 15.20619
A21: FY2032 | B21: =PL!J112 -> 36.626404 | C21: =PL!J167 -> 26.776786 | D21: =PL!J222 -> 13.25376
A22: DCF 情境每股價值（折現率 tp_r） | B22: =SUMPRODUCT(B16:B21,1/(1+tp_r)^{1;2;3;4;5;6})+B21*(1+tp_g)/(tp_r-tp_g)/(1+tp_r)^6 -> 459.70154 | C22: =SUMPRODUCT(C16:C21,1/(1+tp_r)^{1;2;3;4;5;6})+C21*(1+tp_g)/(tp_r-tp_g)/(1+tp_r)^6 -> 350.80169 | D22: =SUMPRODUCT(D16:D21,1/(1+tp_r)^{1;2;3;4;5;6})+D21*(1+tp_g)/(tp_r-tp_g)/(1+tp_r)^6 -> 199.48473 | E22: Σ 明確期現金流 ÷ (1＋r)^t ＋ 永續價值 ÷ (1＋r)^6；永續價值＝FY2032 現金流 ×(1＋g)÷(r−g)；基準日 2026 年底
A23: DCF 情境價值推到 12 個月後（×(1＋tp_r)） | B23: =B22*(1+tp_r) -> 505.67169 | C23: =C22*(1+tp_r) -> 385.88186 | D23: =D22*(1+tp_r) -> 219.43321
A24: DCF 目標價（情境加權） | B24: =tp_wA*B23+tp_wB*C23+tp_wC*D23 -> 388.52908 | E24: Σ 權重 × 情境價值 ×(1＋r)；權重見 In 頁
A25: 參考：EPS ×（1 − g／ROE）法的 DCF 目標價（情境加權） | B25: =(tp_wA*(SUMPRODUCT(B8:B13,1/(1+tp_r)^{1;2;3;4;5;6})+B13*(1+tp_g)/(tp_r-tp_g)/(1+tp_r)^6)+tp_wB*(SUMPRODUCT(C8:C13,1/(1+tp_r)^{1;2;3;4;5;6})+C13*(1+tp_g)/(tp_r-tp_g)/(1+tp_r)^6)+tp_wC*(SUMPRODUCT(D8:D13,1/(1+tp_r)^{1;2;3;4;5;6})+D13*(1+tp_g)/(tp_r-tp_g)/(1+tp_r)^6))*(1-B15)*(1+tp_r) -> 249.49021 | E25: 近三年 ROE 約 9% → 再投資率約 46%；不進目標價
A26: 0.2 Comparable（市場主流同業前瞻 P/E）
A27: 同業與前瞻 P/E | B27: 代號 | C27: 前瞻 12 月 P/E | D27: 日期 | E27: 來源 | F27: 標記
A28: Ibiden（揖斐電） | B28: 4062.T | C28: 53.97 | D28: 2026-10-16 | E28: stockanalysis.com forward PE（分析師共識；價格日期如左） | F28: Interested-party
A29: 景碩（Kinsus） | B29: 3189.TW | C29: 44.7 | D29: 2026-10-22 | E29: stockanalysis.com forward PE（分析師共識；價格日期如左） | F29: Interested-party
A30: 南電（Nan Ya PCB） | B30: 8046.TW | C30: 33.73 | D30: 2026-09-07 | E30: stockanalysis.com forward PE（分析師共識；價格日期如左） | F30: Interested-party
A31: 三星電機（Samsung Electro-Mechanics） | B31: 009150.KS | C31: 43.4 | D31: 2026-08-28 | E31: stockanalysis.com forward PE（分析師共識；價格日期如左） | F31: Interested-party
A32: AT&S | B32: ATS.VI | C32: 14.91 | D32: 2026-10-23 | E32: stockanalysis.com forward PE（分析師共識；價格日期如左） | F32: Interested-party
A33: 同業前瞻 P/E 中位數 | B33: =MEDIAN(C28:C32) -> 43.4 | E33: ABF 載板同業：Ibiden、景碩、南電、三星電機、AT&S（無中國 A 股）；南電、三星電機價格日期較舊
A34: 12 個月後的前瞻 EPS（情境加權） | B34: =tp_wA*(2/12*B8+10/12*B9)+tp_wB*(2/12*C8+10/12*C9)+tp_wC*(2/12*D8+10/12*D9) -> 24.5402 | E34: 約 2027-10 時的未來 12 月 EPS ≈ 2／12 × FY2027＋10／12 × FY2028（會計年度＝日曆年）
A35: Comparable 目標價 | B35: =B33*B34 -> 1065.0447 | E35: 同業中位數 × 前瞻 EPS
A37: 0.3 結論
A38: 項目 | B38: 數值 | E38: 說明
A39: 目標價（DCF 與 Comparable 加權） | B39: =tp_w_dcf*B24+(1-tp_w_dcf)*B35 -> 726.78689 | E39: tp_w_dcf × DCF＋（1 − tp_w_dcf）× Comparable；tp_w_dcf 見 In 頁（0.5）
A40: Comparable 目標價（市場主流同業法） | B40: =B35 -> 1065.0447
A41: 市場共識目標價 | B41: =cons_tp -> 1317.37 | E41: stockanalysis：19 位分析師平均 1,317.37（2026-10-22 擷取）；本土法人 1,500（2026-10-19）
A42: 上檔空間：加權目標價 | B42: =B39/px-1 -> -0.33015033 | E42: 現價＝In 頁 px（2026-10-22 收盤）
A43: 上檔空間：Comparable 目標價 | B43: =B40/px-1 -> -0.01839198
A44: 與市場共識目標價的差距：EPS 因素 | B44: =B34/cons_feps-1 -> -0.0437238 | E44: 本模型前瞻 EPS ÷ 共識前瞻 EPS − 1；共識前瞻 EPS＝現價 ÷ 前瞻 P/E（In 頁 cons_feps）
A45: 與市場共識目標價的差距：倍數因素 | B45: =(cons_tp/cons_feps)/B33-1 -> 0.18283259 | E45: ="共識目標價隱含 "&TEXT(cons_tp/cons_feps,"0.0")&"x，同業中位數 "&TEXT(B33,"0.0")&"x" -> 共識目標價隱含 51.3x，同業中位數 43.4x
A46: 價格帶（DCF 不如預期～順利） | B46: =TEXT(D23,"#,##0")&"～"&TEXT(B23,"#,##0") -> 219～506 | E46: C 情境價值～A 情境價值（推到 12 個月後）
A47: 歷史倍數檢查：現價隱含 P/E 的十年分位（A／B／C） | B47: =IF(px/B9>=MAX($B$86:$B$95),1,IF(px/B9<=MIN($B$86:$B$95),0,PERCENTRANK($B$86:$B$95,px/B9))) -> 0.704 | C47: =IF(px/C9>=MAX($B$86:$B$95),1,IF(px/C9<=MIN($B$86:$B$95),0,PERCENTRANK($B$86:$B$95,px/C9))) -> 0.822 | D47: =IF(px/D9>=MAX($B$86:$B$95),1,IF(px/D9<=MIN($B$86:$B$95),0,PERCENTRANK($B$86:$B$95,px/D9))) -> 1 | E47: 現價 ÷ 各情境 FY2028 EPS 在 2017–2025 年底 P/E（第 5 節兩來源平均，2016 不計）的分位（超出十年區間時記 0% 或 100%）；只作檢查，不進目標價
A48: 目標價方法 | B48: DCF：股東現金流＝每股（淨利＋折舊－資本支出），r＝10%、g＝4%，FY2027–32 明確期＋永續；欣興 2026–28 年資本支出 400–550 億，明確期現金流被擴產壓低，且未計客戶預付款（光復二廠、楊梅二廠全額預付），DCF 偏低估。Comparable：Ibiden、景碩、南電、三星電機、AT&S 前瞻 P/E 中位數（無 A 股）；同業同處 ABF 短缺溢價期，倍數偏高、部分價格為 8–9 月。情境對應：A＝順利（顆數基準）、B＝平平（顆數 ×0.8／0.85）、C＝不如預期（顆數 ×0.6）
A51: 1. 價格與市場隱含倍數
A52: 項目 | B52: A | C52: B | D52: C | E52: 說明
A53: 現價（2026-10-22 收盤） | B53: =px -> 1085
A54: 現價 ÷ FY2026 EPS（錨點） | B54: =px/PL!D15 -> 46.394999 | C54: =px/PL!D29 -> 46.394999 | D54: =px/PL!D43 -> 46.394999 | E54: FY2026 三情境相同（錨點；含 2Q26 一次性業外）
A55: 現價 ÷ FY2027 EPS（模型） | B55: =px/PL!E15 -> 39.439253 | C55: =px/PL!E29 -> 39.439253 | D55: =px/PL!E43 -> 39.439253 | E55: FY2027 三情境相同（顆數係數從 CY2028 開始；資本支出差異從 FY2028 折舊起）
A56: 現價 ÷ FY2028 EPS（模型） | B56: =px/PL!F15 -> 35.648221 | C56: =px/PL!F29 -> 46.744904 | D56: =px/PL!F43 -> 67.608107
A57: 現價 ÷ FY2029 EPS（模型） | B57: =px/PL!G15 -> 33.200917 | C57: =px/PL!G29 -> 39.76133 | D57: =px/PL!G43 -> 60.083943
A58: 未來 12 月 EPS（模型 B）≈ 0.2 × FY2026＋0.8 × FY2027 | B58: =0.2*PL!D29+0.8*PL!E29 -> 26.685759
A59: 現價 ÷ 未來 12 月 EPS（模型 B） | B59: =px/B58 -> 40.65839
A60: 近 12 月 P/E（stockanalysis，10-22） | B60: =pe_ttm -> 70.74
A61: 前瞻 P/E（stockanalysis，10-22） | B61: =fpe -> 42.28
A63: 2. 循環位置（本模型營收最高年；FY(t)＝CY(t)）
A64: 情境 | B64: 營收最高年（FY2026–FY2029） | C64: FY2027 判定 | D64: 規則倍數（P/E） | E64: 見頂年是否未知 | F64: 說明
A65: A | B65: =INDEX({2026,2027,2028,2029},MATCH(MAX(PL!D88:G88),PL!D88:G88,0)) -> 2029 | C65: =IF(B65=2029,"中段",IF(2027<B65,"中段",IF(2027=B65,"見頂","谷底"))) -> 中段 | D65: =IF(C65="見頂",pe_peak,IF(C65="谷底",pe_trough,pe_mid)) -> 22.63 | E65: =IF(B65=2029,"是：營收到觀測期末仍在增加","否") -> 是：營收到觀測期末仍在增加 | F65: tools/cycle_position.py excel_rule；營收最高年取代設備市場見頂年
A66: B | B66: =INDEX({2026,2027,2028,2029},MATCH(MAX(PL!D143:G143),PL!D143:G143,0)) -> 2029 | C66: =IF(B66=2029,"中段",IF(2027<B66,"中段",IF(2027=B66,"見頂","谷底"))) -> 中段 | D66: =IF(C66="見頂",pe_peak,IF(C66="谷底",pe_trough,pe_mid)) -> 22.63 | E66: =IF(B66=2029,"是：營收到觀測期末仍在增加","否") -> 是：營收到觀測期末仍在增加 | F66: 同上
A67: C | B67: =INDEX({2026,2027,2028,2029},MATCH(MAX(PL!D198:G198),PL!D198:G198,0)) -> 2027 | C67: =IF(B67=2029,"中段",IF(2027<B67,"中段",IF(2027=B67,"見頂","谷底"))) -> 見頂 | D67: =IF(C67="見頂",pe_peak,IF(C67="谷底",pe_trough,pe_mid)) -> 18.4 | E67: =IF(B67=2029,"是：營收到觀測期末仍在增加","否") -> 否 | F67: 同上
A69: 3. 規則值隱含股價（新台幣；約 FY2027 年底，未折現）＝ FY2027 EPS × 規則倍數
A70: 情境 | B70: FY2027 EPS | C70: （同左） | D70: 規則倍數 | E70: 隱含股價 | F70: 相對現價 | G70: 現價 ÷ FY2027 EPS
A71: A | B71: =PL!E15 -> 27.510663 | C71: =B71 -> 27.510663 | D71: =D65 -> 22.63 | E71: =C71*D71 -> 622.56631 | F71: =E71/px-1 -> -0.42620617 | G71: =px/C71 -> 39.439253
A72: B | B72: =PL!E29 -> 27.510663 | C72: =B72 -> 27.510663 | D72: =D66 -> 22.63 | E72: =C72*D72 -> 622.56631 | F72: =E72/px-1 -> -0.42620617 | G72: =px/C72 -> 39.439253
A73: C | B73: =PL!E43 -> 27.510663 | C73: =B73 -> 27.510663 | D73: =D67 -> 18.4 | E73: =C73*D73 -> 506.1962 | F73: =E73/px-1 -> -0.53345972 | G73: =px/C73 -> 39.439253
A75: 4. What must be true：FY2027 年底價 ＝ 現價 ×（1＋報酬）所需的倍數（FY2028 EPS；約 2027 年底的價格看下一年 EPS）
A76: FY2027 年底價 ÷ 現價 | B76: 所需倍數（÷ FY2028 EPS，A） | C76: 所需倍數（÷ FY2028 EPS，B） | D76: 所需倍數（÷ FY2028 EPS，C） | E76: 對照：十年中位數
A77: 0.75 | B77: =px*A77/PL!F15 -> 26.736166 | C77: =px*A77/PL!F29 -> 35.058678 | D77: =px*A77/PL!F43 -> 50.70608 | E77: =pe_mid -> 22.63
A78: 1 | B78: =px*A78/PL!F15 -> 35.648221 | C78: =px*A78/PL!F29 -> 46.744904 | D78: =px*A78/PL!F43 -> 67.608107 | E78: =pe_mid -> 22.63
A79: 1.1 | B79: =px*A79/PL!F15 -> 39.213043 | C79: =px*A79/PL!F29 -> 51.419394 | D79: =px*A79/PL!F43 -> 74.368918 | E79: =pe_mid -> 22.63
A80: 1.21 | B80: =px*A80/PL!F15 -> 43.134347 | C80: =px*A80/PL!F29 -> 56.561333 | D80: =px*A80/PL!F43 -> 81.80581 | E80: =pe_mid -> 22.63
A81: 1.5 | B81: =px*A81/PL!F15 -> 53.472331 | C81: =px*A81/PL!F29 -> 70.117356 | D81: =px*A81/PL!F43 -> 101.41216 | E81: =pe_mid -> 22.63
A82: 讀法：1.00＝價格不變、1.21＝一年約 21%。所需倍數愈高，現價愈依賴「ABF 短缺與漲價延續、擴產折舊被營收吸收」。本版未做先驗，無 Andy 合理 P/E 對照。
A84: 5. 十年 P/E（2016–2025 年底；兩來源平均，分位排名用；2016 年 EPS 0.01 元，P/E 逾 1,000 倍無意義，不計）
A85: 年底 | B85: 兩來源平均 P/E | C85: companiesmarketcap | D85: 自算
A86: 2016 | E86: 不計（EPS 0.01 元，P/E 無意義）
A87: 2017 | B87: =AVERAGE(C87:D87) -> 53.607143 | C87: =B106 -> 49 | D87: =C106 -> 58.214286
A88: 2018 | B88: =AVERAGE(C88:D88) -> 18.395652 | C88: =B107 -> 17.4 | D88: =C107 -> 19.391304
A89: 2019 | B89: =AVERAGE(C89:D89) -> 17.625 | C89: =B108 -> 16.5 | D89: =C108 -> 18.75
A90: 2020 | B90: =AVERAGE(C90:D90) -> 22.184492 | C90: =B109 -> 21 | D90: =C109 -> 23.368984
A91: 2021 | B91: =AVERAGE(C91:D91) -> 24.611915 | C91: =B110 -> 23.5 | D91: =C110 -> 25.723831
A92: 2022 | B92: =AVERAGE(C92:D92) -> 5.7730478 | C92: =B111 -> 5.57 | D92: =C111 -> 5.9760956
A93: 2023 | B93: =AVERAGE(C93:D93) -> 22.117513 | C93: =B112 -> 21.9 | D93: =C112 -> 22.335025
A94: 2024 | B94: =AVERAGE(C94:D94) -> 42.007784 | C94: =B113 -> 41.8 | D94: =C113 -> 42.215569
A95: 2025 | B95: =AVERAGE(C95:D95) -> 50.25 | C95: =B114 -> 50.1 | D95: =C114 -> 50.4
A96: 年數 | B96: =COUNT($B$86:$B$95) -> 9
A100: 6. 十年倍數與規則值（2016–2025 年底；見頂年 25 分位、中段中位數、谷底 75 分位）
A101: 規則（Andy 2026-10-13）：合理倍數＝2016–2025 年底 P/E 依循環位置取分位，兩個來源分別取分位再平均。欣興的落後 P/E 與盈餘反向：盈餘低谷年（2017、2024–2025）P/E 42–58x，高峰年（2022）約 6x；十年多為 AI 載板需求前的 PCB 循環，套用在 FY2027 EPS 時偏誤方向不明確。
A103: P/E：十年歷史倍數
A104: 年底 | B104: companiesmarketcap（年底 P/E） | C104: 自算（digrin 12 月未調整股價 ÷ 年度 EPS） | D104: 標記／說明
A105: 2016 | D105: companiesmarketcap（年底 P/E）：Interested-party（資料商；2017–2025 共 9 年，2016 逾 1,000 倍不計）；自算（digrin 12 月未調整股價 ÷ 年度 EPS）：Derived（價格為月資料的 12 月值；EPS 取自 wantgoo 歷年股利表；2025 年 digrin 無資料，改用 stockanalysis 年底 P/E 50.40）
A106: 2017 | B106: 49 | C106: =16.3/0.28 -> 58.214286
A107: 2018 | B107: 17.4 | C107: =22.3/1.15 -> 19.391304
A108: 2019 | B108: 16.5 | C108: =42/2.24 -> 18.75
A109: 2020 | B109: 21 | C109: =87.4/3.74 -> 23.368984
A110: 2021 | B110: 23.5 | C110: =231/8.98 -> 25.723831
A111: 2022 | B111: 5.57 | C111: =120/20.08 -> 5.9760956
A112: 2023 | B112: 21.9 | C112: =176/7.88 -> 22.335025
...

Sheet Recon
A1: Recon — 本模型 vs 券商、共識與市場口徑。只作事後對照，不為對上數字而調參數。FactSet 共識為 2026-06（2Q26 財報前），10 月券商數字只有兩家
A3: 項目 | B3: 對照值 | C3: 模型 A | D3: 差距 A | E3: 模型 B | F3: 差距 B | G3: 模型 C | H3: 差距 C | I3: 對照來源 | J3: 說明
A4: A. EPS 與營收 vs 共識、券商
A5: FY2026 EPS vs 本土法人 23.42（2026-10-19） | B5: 23.42 | C5: =PL!D107 -> 23.386141 | D5: =C5/B5-1 -> -0.0014457105 | E5: =PL!D162 -> 23.386141 | F5: =E5/B5-1 -> -0.0014457105 | G5: =PL!D217 -> 23.386141 | H5: =G5/B5-1 -> -0.0014457105 | I5: 三立（本土法人） | J5: FactSet 2026-06 中位數 15.17 為 2Q26 一次性業外之前
A6: FY2026 EPS vs 美系券商 21（2026-10-12） | B6: 21 | C6: =PL!D107 -> 23.386141 | D6: =C6/B6-1 -> 0.11362578 | E6: =PL!D162 -> 23.386141 | F6: =E6/B6-1 -> 0.11362578 | G6: =PL!D217 -> 23.386141 | H6: =G6/B6-1 -> 0.11362578 | I6: 經濟日報（美系券商）
A7: FY2027 EPS vs 2026-10 券商平均（美系 37、本土 41.10） | B7: =bk_eps27 -> 39.05 | C7: =PL!E107 -> 27.510663 | D7: =C7/B7-1 -> -0.29550159 | E7: =PL!E162 -> 27.510663 | F7: =E7/B7-1 -> -0.29550159 | G7: =PL!E217 -> 27.510663 | H7: =G7/B7-1 -> -0.29550159 | I7: 經濟日報、三立 | J7: 差距超過 30% 的原因見 README
A8: FY2027 EPS vs FactSet 平均 30.37（2026-06） | B8: =cons_eps27 -> 30.37 | C8: =PL!E107 -> 27.510663 | D8: =C8/B8-1 -> -0.094150046 | E8: =PL!E162 -> 27.510663 | F8: =E8/B8-1 -> -0.094150046 | G8: =PL!E217 -> 27.510663 | H8: =G8/B8-1 -> -0.094150046 | I8: 鉅亨（FactSet 22 位）
A9: FY2028 EPS vs FactSet 平均 48.52（2026-06） | B9: =cons_eps28 -> 48.52 | C9: =PL!F107 -> 30.436302 | D9: =C9/B9-1 -> -0.37270607 | E9: =PL!F162 -> 23.211086 | F9: =E9/B9-1 -> -0.52161817 | G9: =PL!F217 -> 16.048371 | H9: =G9/B9-1 -> -0.66924214 | I9: 鉅亨（FactSet） | J9: 美系券商 2026-10：64.8
A10: FY2028 EPS vs 美系券商 64.8（2026-10） | B10: 64.8 | C10: =PL!F107 -> 30.436302 | D10: =C10/B10-1 -> -0.53030399 | E10: =PL!F162 -> 23.211086 | F10: =E10/B10-1 -> -0.64180422 | G10: =PL!F217 -> 16.048371 | H10: =G10/B10-1 -> -0.75233995 | I10: 經濟日報
A11: FY2027 營收 vs FactSet 平均（2026-06） | B11: =cons_rev27 -> 255.2 | C11: =PL!E88 -> 245.84265 | D11: =C11/B11-1 -> -0.036666714 | E11: =PL!E143 -> 245.84265 | F11: =E11/B11-1 -> -0.036666714 | G11: =PL!E198 -> 245.84265 | H11: =G11/B11-1 -> -0.036666714 | I11: 鉅亨（FactSet）
A12: FY2028 營收 vs FactSet 平均（2026-06） | B12: =cons_rev28 -> 326.5 | C12: =PL!F88 -> 278.51347 | D12: =C12/B12-1 -> -0.14697254 | E12: =PL!F143 -> 238.72615 | F12: =E12/B12-1 -> -0.26883262 | G12: =PL!F198 -> 198.93883 | H12: =G12/B12-1 -> -0.3906927 | I12: 鉅亨（FactSet）
A13: 模型前瞻 12 月 EPS（0.2 × FY2026＋0.8 × FY2027）vs 現價 ÷ 前瞻 P/E | B13: =cons_feps -> 25.662252 | C13: =0.2*PL!D107+0.8*PL!E107 -> 26.685759 | D13: =C13/B13-1 -> 0.039883761 | E13: =0.2*PL!D162+0.8*PL!E162 -> 26.685759 | F13: =E13/B13-1 -> 0.039883761 | G13: =0.2*PL!D217+0.8*PL!E217 -> 26.685759 | H13: =G13/B13-1 -> 0.039883761 | I13: stockanalysis（推導） | J13: 口徑不同，只作量級比較
A14: B. 錨點與毛利率
A15: 3Q26 毛利率（假設）vs 本土法人估 27.2%（百分點） | B15: 0.272 | C15: =Q!E6 -> 0.27 | D15: =C15-B15 -> -0.002 | E15: =Q!E6 -> 0.27 | F15: =E15-B15 -> -0.002 | G15: =Q!E6 -> 0.27 | H15: =G15-B15 -> -0.002 | I15: 三立（本土法人） | J15: 3Q26 財報約 10-29
A16: 4Q26 營收（假設）vs 本土法人估 579.2 億 | B16: 57.92 | C16: =Q!F4 -> 55.2825 | D16: =C16/B16-1 -> -0.045536948 | E16: =Q!F4 -> 55.2825 | F16: =E16/B16-1 -> -0.045536948 | G16: =Q!F4 -> 55.2825 | H16: =G16/B16-1 -> -0.045536948 | I16: 三立
A17: FY2027 毛利率 vs 4Q26 毛利率（假設）（百分點） | B17: =Q!F6 -> 0.285 | C17: =PL!E98 -> 0.29584384 | D17: =C17-B17 -> 0.010843837 | E17: =PL!E153 -> 0.29584384 | F17: =E17-B17 -> 0.010843837 | G17: =PL!E208 -> 0.29584384 | H17: =G17-B17 -> 0.010843837 | I17: Q 頁 | J17: 擴產折舊增量抵銷部分規模效益
A18: FY2028 毛利率 vs FY2026 錨點（百分點） | B18: =Q!G6 -> 0.25141203 | C18: =PL!F98 -> 0.28779177 | D18: =C18-B18 -> 0.036379739 | E18: =PL!F153 -> 0.26720807 | F18: =E18-B18 -> 0.015796042 | G18: =PL!F208 -> 0.23901932 | H18: =G18-B18 -> -0.012392707 | I18: Q 頁
A19: C. 產能、份額與 AI 口徑
A20: FY2027 ABF 需求滿足率（< 100%＝產能受限） | C20: =PL!E80 -> 0.98372057 | E20: =PL!E135 -> 0.98372057 | G20: =PL!E190 -> 0.98372057 | I20: PL 頁 | J20: 外資：ABF 供需缺口 2027 年 27%（永豐 1Q26 轉述）
A21: FY2028 ABF 需求滿足率 | C21: =PL!F80 -> 1 | E21: =PL!F135 -> 1 | G21: =PL!F190 -> 1 | I21: PL 頁
A22: FY2026 AI 占營收 vs 公司 2H26 約 70%（百分點） | B22: 0.7 | C22: =PL!D91 -> 0.599 | D22: =C22-B22 -> -0.101 | E22: =PL!D146 -> 0.599 | F22: =E22-B22 -> -0.101 | G22: =PL!D201 -> 0.599 | H22: =G22-B22 -> -0.101 | I22: 工商時報 2Q26 法說 | J22: 全年口徑低於下半年
A23: FY2027 份額合計：Ibiden＋欣興（NVIDIA） | C23: =Units!D9 -> 0.935 | E23: =Units!D9 -> 0.935 | G23: =Units!D9 -> 0.935 | I23: Units 頁 | J23: 應 ≤ 100%
A24: FY2027 份額合計：Ibiden＋欣興（非 NVIDIA） | C24: =Units!D12 -> 0.785 | E24: =Units!D12 -> 0.785 | G24: =Units!D12 -> 0.785 | I24: Units 頁 | J24: 應 ≤ 100%
A25: FY2027 每顆 NVIDIA 加速器的欣興營收（US$） | C25: =Units!D13 -> 72.027185 | E25: =Units!D13 -> 72.027185 | G25: =Units!D13 -> 72.027185 | I25: Units 頁 | J25: Ibiden 同期約 169（ibiden/dist Units 頁）
A26: FY2027 每 GW 欣興 AI 載板營收（US$M） | C26: =Units!D17 -> 91.05872 | E26: =Units!D17 -> 91.05872 | G26: =Units!D17 -> 91.05872 | I26: Units 頁 | J26: Ibiden 同期約 62（只含加速器載板）
A27: D. 資本支出
A28: FY2027 資本支出 vs 美系券商「逾 400 億」 | B28: 40 | C28: =PL!E93 -> 55 | D28: =C28/B28-1 -> 0.375 | E28: =PL!E148 -> 48 | F28: =E28/B28-1 -> 0.2 | G28: =PL!E203 -> 40 | H28: =G28/B28-1 -> 0 | I28: 經濟日報
A29: FY2028 資本支出 vs 美系券商「逾 400 億」 | B29: 40 | C29: =PL!F93 -> 50 | D29: =C29/B29-1 -> 0.25 | E29: =PL!F148 -> 42 | F29: =E29/B29-1 -> 0.05 | G29: =PL!F203 -> 30 | H29: =G29/B29-1 -> -0.25 | I29: 經濟日報

Sheet Sens
A1: Sens — 一次動一個輸入（情境 A；FY2026 恆等於錨點，其他 AI 載板在每個案例內重新校準）：對 FY2027、FY2028 營收、毛利率與 EPS 的影響。每個案例是一個完整推導區塊（本頁下方）
A3: 案例 | B3: 設定 | C3: FY2027 營收 | D3: FY2027 毛利率 | E3: FY2027 EPS | F3: FY2027 EPS 相對基準 | G3: FY2028 營收 | H3: FY2028 毛利率 | I3: FY2028 EPS | J3: FY2028 EPS 相對基準
A4: 基準（情境 A） | B4: PL 區塊 A | C4: =PL!E88 -> 245.84265 | D4: =PL!E98 -> 0.29584384 | E4: =PL!E107 -> 27.510663 | F4: =E4/E$4-1 -> 0 | G4: =PL!F88 -> 278.51347 | H4: =PL!F98 -> 0.28779177 | I4: =PL!F107 -> 30.436302 | J4: =I4/I$4-1 -> 0
A5: AI 部署 ×0.8 | B5: FY2027 起顆數與其他 AI ×0.8 | C5: =E78 -> 223.24493 | D5: =E88 -> 0.27272364 | E5: =E97 -> 22.186919 | F5: =E5/E$4-1 -> -0.19351565 | G5: =F78 -> 249.19651 | H5: =F88 -> 0.26297376 | I5: =F97 -> 23.865375 | J5: =I5/I$4-1 -> -0.2158911
A6: AI 部署 ×1.2 | B6: ×1.2 | C6: =E133 -> 245.84265 | D6: =E143 -> 0.29619227 | E6: =E152 -> 27.553493 | F6: =E6/E$4-1 -> 0.0015568472 | G6: =F133 -> 292.01339 | H6: =F143 -> 0.29753545 | I6: =F152 -> 33.476833 | J6: =I6/I$4-1 -> 0.099898191
A7: ABF 產能 低 | B7: 產能指數 1.25／1.50／1.70 | C7: =E188 -> 234.84166 | D7: =E198 -> 0.28535476 | E7: =E207 -> 24.943678 | F7: =E7/E$4-1 -> -0.093308746 | G7: =F188 -> 270.0664 | H7: =F198 -> 0.28118757 | I7: =F207 -> 28.546118 | J7: =I7/I$4-1 -> -0.06210295
A8: ABF 產能 高 | B8: 1.45／1.90／2.30 | C8: =E243 -> 248.30038 | D8: =E253 -> 0.29806018 | E8: =E262 -> 28.084151 | F8: =E8/E$4-1 -> 0.020846039 | G8: =F243 -> 278.51347 | H8: =F253 -> 0.28779177 | I8: =F262 -> 30.432623 | J8: =I8/I$4-1 -> -0.00012086635
A9: ABF 溢價 低（Ibiden 低值） | B9: 0.95／0.85／0.75 | C9: =E298 -> 238.41698 | D9: =E308 -> 0.27656819 | E9: =E317 -> 24.311482 | F9: =E9/E$4-1 -> -0.11628876 | G9: =F298 -> 263.08349 | H9: =F308 -> 0.24602041 | I9: =F317 -> 23.104645 | J9: =I9/I$4-1 -> -0.24088527
A10: ABF 溢價 高（Ibiden 高值） | B10: 1.05／1.05／1.00 | C10: =E353 -> 253.26833 | D10: =E363 -> 0.31418837 | E10: =E372 -> 30.735069 | F10: =E10/E$4-1 -> 0.11720568 | G10: =F353 -> 293.94344 | H10: =F363 -> 0.32517772 | I10: =F372 -> 37.771408 | J10: =I10/I$4-1 -> 0.2409986
A11: 漲價年度化 0% | B11: 基準 5% | C11: =E408 -> 238.77058 | D11: =E418 -> 0.27750807 | E11: =E427 -> 24.463204 | F11: =E11/E$4-1 -> -0.11077375 | G11: =F408 -> 271.53324 | H11: =F418 -> 0.26948324 | I11: =F427 -> 27.123767 | J11: =I11/I$4-1 -> -0.10883501
A12: 漲價年度化 10% | C12: =E463 -> 252.91473 | D12: =E473 -> 0.31333508 | E12: =E482 -> 30.580998 | F12: =E12/E$4-1 -> 0.11160528 | G12: =F463 -> 285.49369 | H12: =F473 -> 0.30520502 | I12: =F482 -> 33.748354 | J12: =I12/I$4-1 -> 0.10881914
A13: ABF 現金毛利率 40% | B13: 基準 50% | C13: =E518 -> 245.84265 | D13: =E528 -> 0.27840882 | E13: =E537 -> 25.367527 | F13: =E13/E$4-1 -> -0.077902003 | G13: =F518 -> 278.51347 | H13: =F528 -> 0.26135334 | I13: =F537 -> 26.754572 | J13: =I13/I$4-1 -> -0.12096508
A14: ABF 現金毛利率 60% | C14: =E573 -> 245.84265 | D14: =E583 -> 0.31327886 | E14: =E592 -> 29.653799 | F14: =E14/E$4-1 -> 0.077902003 | G14: =F573 -> 278.51347 | H14: =F583 -> 0.3142302 | I14: =F592 -> 34.118031 | J14: =I14/I$4-1 -> 0.12096508
A15: 其他產品現金毛利率 15% | B15: 基準 25% | C15: =E628 -> 245.84265 | D15: =E638 -> 0.29224683 | E15: =E647 -> 27.068515 | F15: =E15/E$4-1 -> -0.016071898 | G15: =F628 -> 278.51347 | H15: =F638 -> 0.28169592 | I15: =F647 -> 29.587414 | J15: =I15/I$4-1 -> -0.027890629
A16: 其他產品現金毛利率 35% | C16: =E683 -> 245.84265 | D16: =E693 -> 0.29944084 | E16: =E702 -> 27.952812 | F16: =E16/E$4-1 -> 0.016071898 | G16: =F683 -> 278.51347 | H16: =F693 -> 0.29388761 | I16: =F702 -> 31.285189 | J16: =I16/I$4-1 -> 0.027890629
A17: 折舊年限 6 年 | B17: 基準 8 年 | C17: =E738 -> 245.84265 | D17: =E748 -> 0.29026778 | E17: =E757 -> 26.825246 | F17: =E17/E$4-1 -> -0.024914582 | G17: =F738 -> 278.51347 | H17: =F748 -> 0.27918893 | I17: =F757 -> 29.238298 | J17: =I17/I$4-1 -> -0.039361007
A18: 折舊年限 10 年 | C18: =E793 -> 245.84265 | D18: =E803 -> 0.29918947 | E18: =E812 -> 27.921913 | F18: =E18/E$4-1 -> 0.014948749 | G18: =F793 -> 278.51347 | H18: =F803 -> 0.29315035 | I18: =F812 -> 31.18252 | J18: =I18/I$4-1 -> 0.024517392
A19: 資本支出 走 C 路徑 | B19: 400／300／280 億（折舊較低） | C19: =E848 -> 245.84265 | D19: =E858 -> 0.29584384 | E19: =E867 -> 27.510663 | F19: =E19/E$4-1 -> 0 | G19: =F848 -> 278.51347 | H19: =F858 -> 0.29452394 | I19: =F867 -> 31.373802 | J19: =I19/I$4-1 -> 0.030802034
A20: 欣興 NVIDIA 份額 低 | B20: 20%→22% | C20: =E903 -> 245.84265 | D20: =E913 -> 0.2958397 | E20: =E922 -> 27.510155 | F20: =E20/E$4-1 -> -1.8461312e-05 | G20: =F903 -> 276.27578 | H20: =F913 -> 0.28608314 | I20: =F922 -> 29.932102 | J20: =I20/I$4-1 -> -0.016565735
A21: 欣興 NVIDIA 份額 高 | B21: 30%→36% | C21: =E958 -> 245.84265 | D21: =E968 -> 0.29584795 | E21: =E977 -> 27.511169 | F21: =E21/E$4-1 -> 1.8399201e-05 | G21: =F958 -> 279.82785 | H21: =F968 -> 0.28878265 | I21: =F977 -> 30.732461 | J21: =I21/I$4-1 -> 0.0097304503
A22: 欣興 ASIC 份額 低 | B22: 22% | C22: =E1013 -> 244.61776 | D22: =E1023 -> 0.29466161 | E22: =E1032 -> 27.217383 | F22: =E22/E$4-1 -> -0.010660589 | G22: =F1013 -> 270.7042 | H22: =F1023 -> 0.28170614 | I22: =F1032 -> 28.678687 | J22: =I22/I$4-1 -> -0.057747331
A23: 欣興 ASIC 份額 高 | B23: 40% | C23: =E1068 -> 245.84265 | D23: =E1078 -> 0.29588243 | E23: =E1087 -> 27.515407 | F23: =E23/E$4-1 -> 0.00017245012 | G23: =F1068 -> 282.32702 | H23: =F1078 -> 0.29064126 | I23: =F1087 -> 31.295579 | J23: =I23/I$4-1 -> 0.028231985
A24: 其他 AI 彈性 0.3 | B24: 基準 0.5 | C24: =E1123 -> 238.90642 | D24: =E1133 -> 0.28918356 | E24: =E1142 -> 25.87312 | F24: =E24/E$4-1 -> -0.059523931 | G24: =F1123 -> 265.34079 | H24: =F1133 -> 0.27731904 | I24: =F1142 -> 27.479215 | J24: =I24/I$4-1 -> -0.097156571
A25: 其他 AI 彈性 0.8 | C25: =E1178 -> 245.84265 | D25: =E1188 -> 0.29608868 | E25: =E1197 -> 27.540759 | F25: =E25/E$4-1 -> 0.0010939714 | G25: =F1178 -> 292.01339 | H25: =F1188 -> 0.29753774 | I25: =F1197 -> 33.477168 | J25: =I25/I$4-1 -> 0.099909179
A26: AI HDI／PCB 成長 低 | B26: 每年 −10pt | C26: =E1233 -> 242.04904 | D26: =E1243 -> 0.29656234 | E26: =E1252 -> 27.137135 | F26: =E26/E$4-1 -> -0.013577577 | G26: =F1233 -> 269.97784 | H26: =F1243 -> 0.28898659 | I26: =F1252 -> 29.580517 | J26: =I26/I$4-1 -> -0.028117246
A27: AI HDI／PCB 成長 高 | B27: 每年 +10pt | C27: =E1288 -> 249.63626 | D27: =E1298 -> 0.29514717 | E27: =E1307 -> 27.884191 | F27: =E27/E$4-1 -> 0.013577577 | G27: =F1288 -> 287.80781 | H27: =F1298 -> 0.28657134 | I27: =F1307 -> 31.369836 | J27: =I27/I$4-1 -> 0.030671727
A28: 營業費用彈性 1.0 | B28: 基準 0.6 | C28: =E1343 -> 245.84265 | D28: =E1353 -> 0.29584384 | E28: =E1362 -> 26.492078 | F28: =E28/E$4-1 -> -0.037025095 | G28: =F1343 -> 278.51347 | H28: =F1353 -> 0.28779177 | I28: =F1362 -> 28.758497 | J28: =I28/I$4-1 -> -0.055125128
A29: 稅率 22% | B29: 基準 18% | C29: =E1398 -> 245.84265 | D29: =E1408 -> 0.29584384 | E29: =E1417 -> 26.16868 | F29: =E29/E$4-1 -> -0.048780488 | G29: =F1398 -> 278.51347 | H29: =F1408 -> 0.28779177 | I29: =F1417 -> 28.951604 | J29: =I29/I$4-1 -> -0.048780488
A30: 業外 0 | B30: 每年 0（基準 20 億） | C30: =E1453 -> 245.84265 | D30: =E1463 -> 0.29584384 | E30: =E1472 -> 26.510663 | F30: =E30/E$4-1 -> -0.036349542 | G30: =F1453 -> 278.51347 | H30: =F1463 -> 0.28779177 | I30: =F1472 -> 29.436302 | J30: =I30/I$4-1 -> -0.032855503
A31: 情境 B | B31: CY2028 顆數 ×0.8、CY2029 ×0.85；資本支出較低 | C31: =PL!E143 -> 245.84265 | D31: =PL!E153 -> 0.29584384 | E31: =PL!E162 -> 27.510663 | F31: =E31/E$4-1 -> 0 | G31: =PL!F143 -> 238.72615 | H31: =PL!F153 -> 0.26720807 | I31: =PL!F162 -> 23.211086 | J31: =I31/I$4-1 -> -0.23738808
A32: 情境 C | B32: CY2028–29 顆數 ×0.6；資本支出最低 | C32: =PL!E198 -> 245.84265 | D32: =PL!E208 -> 0.29584384 | E32: =PL!E217 -> 27.510663 | F32: =E32/E$4-1 -> 0 | G32: =PL!F198 -> 198.93883 | H32: =PL!F208 -> 0.23901932 | I32: =PL!F217 -> 16.048371 | J32: =I32/I$4-1 -> -0.47272269
A34: 讀法：ABF 產能受限時，顆數與份額的上修只部分轉成營收（滿足率 < 100%），產能與價格的影響較大；折舊年限與資本支出路徑直接改變毛利率；FY2027 三情境相同，差異從 FY2028 起。
A36: 目標價參數（只改 DCF 參數；PL 收斂法的 fade_g 與資本支出率路徑不隨 tp_g 變動）
A37: 案例 | B37: 設定 | C37: DCF 目標價 | D37: Comparable 目標價 | E37: 加權目標價 | F37: 相對基準
A38: 基準 | B38: r 10%、g 4%、DCF 權重 0.5 | C38: =(tp_wA*(SUMPRODUCT(Val!B16:B21,1/(1+tp_r)^{1;2;3;4;5;6})+Val!B21*(1+tp_g)/(tp_r-tp_g)/(1+tp_r)^6)+tp_wB*(SUMPRODUCT(Val!C16:C21,1/(1+tp_r)^{1;2;3;4;5;6})+Val!C21*(1+tp_g)/(tp_r-tp_g)/(1+tp_r)^6)+tp_wC*(SUMPRODUCT(Val!D16:D21,1/(1+tp_r)^{1;2;3;4;5;6})+Val!D21*(1+tp_g)/(tp_r-tp_g)/(1+tp_r)^6))*(1+tp_r) -> 388.52908 | D38: =Val!B35 -> 1065.0447 | E38: =tp_w_dcf*C38+(1-tp_w_dcf)*D38 -> 726.78689 | F38: =E38/E$38-1 -> 0
A39: 折現率 +1pt | B39: r 11% | C39: =(tp_wA*(SUMPRODUCT(Val!B16:B21,1/(1+(tp_r+0.01))^{1;2;3;4;5;6})+Val!B21*(1+tp_g)/((tp_r+0.01)-tp_g)/(1+(tp_r+0.01))^6)+tp_wB*(SUMPRODUCT(Val!C16:C21,1/(1+(tp_r+0.01))^{1;2;3;4;5;6})+Val!C21*(1+tp_g)/((tp_r+0.01)-tp_g)/(1+(tp_r+0.01))^6)+tp_wC*(SUMPRODUCT(Val!D16:D21,1/(1+(tp_r+0.01))^{1;2;3;4;5;6})+Val!D21*(1+tp_g)/((tp_r+0.01)-tp_g)/(1+(tp_r+0.01))^6))*(1+(tp_r+0.01)) -> 333.64042 | D39: =Val!B35 -> 1065.0447 | E39: =tp_w_dcf*C39+(1-tp_w_dcf)*D39 -> 699.34256 | F39: =E39/E$38-1 -> -0.037761179
A40: 折現率 −1pt | B40: r 9% | C40: =(tp_wA*(SUMPRODUCT(Val!B16:B21,1/(1+(tp_r-0.01))^{1;2;3;4;5;6})+Val!B21*(1+tp_g)/((tp_r-0.01)-tp_g)/(1+(tp_r-0.01))^6)+tp_wB*(SUMPRODUCT(Val!C16:C21,1/(1+(tp_r-0.01))^{1;2;3;4;5;6})+Val!C21*(1+tp_g)/((tp_r-0.01)-tp_g)/(1+(tp_r-0.01))^6)+tp_wC*(SUMPRODUCT(Val!D16:D21,1/(1+(tp_r-0.01))^{1;2;3;4;5;6})+Val!D21*(1+tp_g)/((tp_r-0.01)-tp_g)/(1+(tp_r-0.01))^6))*(1+(tp_r-0.01)) -> 465.41753 | D40: =Val!B35 -> 1065.0447 | E40: =tp_w_dcf*C40+(1-tp_w_dcf)*D40 -> 765.23111 | F40: =E40/E$38-1 -> 0.052896143
A41: 長期成長 +1pt | B41: g 5% | C41: =(tp_wA*(SUMPRODUCT(Val!B16:B21,1/(1+tp_r)^{1;2;3;4;5;6})+Val!B21*(1+(tp_g+0.01))/(tp_r-(tp_g+0.01))/(1+tp_r)^6)+tp_wB*(SUMPRODUCT(Val!C16:C21,1/(1+tp_r)^{1;2;3;4;5;6})+Val!C21*(1+(tp_g+0.01))/(tp_r-(tp_g+0.01))/(1+tp_r)^6)+tp_wC*(SUMPRODUCT(Val!D16:D21,1/(1+tp_r)^{1;2;3;4;5;6})+Val!D21*(1+(tp_g+0.01))/(tp_r-(tp_g+0.01))/(1+tp_r)^6))*(1+tp_r) -> 450.06191 | D41: =Val!B35 -> 1065.0447 | E41: =tp_w_dcf*C41+(1-tp_w_dcf)*D41 -> 757.55331 | F41: =E41/E$38-1 -> 0.042332101
A42: 長期成長 −1pt | B42: g 3% | C42: =(tp_wA*(SUMPRODUCT(Val!B16:B21,1/(1+tp_r)^{1;2;3;4;5;6})+Val!B21*(1+(tp_g-0.01))/(tp_r-(tp_g-0.01))/(1+tp_r)^6)+tp_wB*(SUMPRODUCT(Val!C16:C21,1/(1+tp_r)^{1;2;3;4;5;6})+Val!C21*(1+(tp_g-0.01))/(tp_r-(tp_g-0.01))/(1+tp_r)^6)+tp_wC*(SUMPRODUCT(Val!D16:D21,1/(1+tp_r)^{1;2;3;4;5;6})+Val!D21*(1+(tp_g-0.01))/(tp_r-(tp_g-0.01))/(1+tp_r)^6))*(1+tp_r) -> 344.57706 | D42: =Val!B35 -> 1065.0447 | E42: =tp_w_dcf*C42+(1-tp_w_dcf)*D42 -> 704.81088 | F42: =E42/E$38-1 -> -0.030237215
A43: DCF 權重 0.3 | C43: =(tp_wA*(SUMPRODUCT(Val!B16:B21,1/(1+tp_r)^{1;2;3;4;5;6})+Val!B21*(1+tp_g)/(tp_r-tp_g)/(1+tp_r)^6)+tp_wB*(SUMPRODUCT(Val!C16:C21,1/(1+tp_r)^{1;2;3;4;5;6})+Val!C21*(1+tp_g)/(tp_r-tp_g)/(1+tp_r)^6)+tp_wC*(SUMPRODUCT(Val!D16:D21,1/(1+tp_r)^{1;2;3;4;5;6})+Val!D21*(1+tp_g)/(tp_r-tp_g)/(1+tp_r)^6))*(1+tp_r) -> 388.52908 | D43: =Val!B35 -> 1065.0447 | E43: =0.3*C43+(1-0.3)*D43 -> 862.09001 | F43: =E43/E$38-1 -> 0.18616616
A44: DCF 權重 0.7 | C44: =(tp_wA*(SUMPRODUCT(Val!B16:B21,1/(1+tp_r)^{1;2;3;4;5;6})+Val!B21*(1+tp_g)/(tp_r-tp_g)/(1+tp_r)^6)+tp_wB*(SUMPRODUCT(Val!C16:C21,1/(1+tp_r)^{1;2;3;4;5;6})+Val!C21*(1+tp_g)/(tp_r-tp_g)/(1+tp_r)^6)+tp_wC*(SUMPRODUCT(Val!D16:D21,1/(1+tp_r)^{1;2;3;4;5;6})+Val!D21*(1+tp_g)/(tp_r-tp_g)/(1+tp_r)^6))*(1+tp_r) -> 388.52908 | D44: =Val!B35 -> 1065.0447 | E44: =0.7*C44+(1-0.7)*D44 -> 591.48377 | F44: =E44/E$38-1 -> -0.18616616
A50: 案例區塊：AI 部署 ×0.8（情境 A）
A51: 項目 | B51: 單位 | C51: FY2025A | D51: FY2026（錨點） | E51: FY2027 | F51: FY2028 | G51: FY2029 | H51: FY2030（收斂） | I51: FY2031（收斂） | J51: FY2032（收斂） | K51: 說明
A52: A. AI 加速器載板（口徑與 Ibiden 一致；D 欄＝FY2026 校準年）
A53: NVIDIA 加速器顆數 × 情境係數 | B53: 百萬顆 | D53: =(u_bw_26+u_rb_26+u_ru_26+u_hp_26)*1 -> 7.6 | E53: =(u_bw_27+u_rb_27+u_ru_27+u_hp_27)*1*0.8 -> 7.76 | F53: =(u_bw_28+u_rb_28+u_ru_28+u_hp_28)*um28_A*0.8 -> 7.6 | G53: =(u_bw_28*(1+g29_bw)+u_rb_28*(1+g29_rb)+u_ru_28*(1+g29_ru)+u_hp_28*(1+g29_hp))*um29_A*0.8 -> 8.48 | K53: markets/network In：Blackwell、Rubin、Rubin Ultra、Hopper
A54: 非 NVIDIA 加速器顆數 × 情境係數 | B54: 百萬顆 | D54: =(u_amd_26+u_tpu_26+u_trn_26+u_oth_26)*1 -> 7.6 | E54: =(u_amd_27+u_tpu_27+u_trn_27+u_oth_27)*1*0.8 -> 11.2 | F54: =(u_amd_28+u_tpu_28+u_trn_28+u_oth_28)*um28_A*0.8 -> 13.6 | G54: =(u_amd_28*(1+g29_amd)+u_tpu_28*(1+g29_tpu)+u_trn_28*(1+g29_trn)+u_oth_28*(1+g29_oth))*um29_A*0.8 -> 15.64 | K54: AMD、TPU、Trainium、其他 ASIC
A55: 每顆載板面積與層數指數（FY2026＝1） | B55: x | D55: =1 -> 1 | E55: =D55*(1+g_asp) -> 1.18 | F55: =E55*(1+g_asp) -> 1.3924 | G55: =F55*(1+g_asp) -> 1.643032 | K55: Ibiden 模型 g_asp（Analogy）
A56: ABF 價格溢價指數（全市場；FY2026＝1） | B56: x | D56: =1 -> 1 | E56: =ibpp_27 -> 1 | F56: =ibpp_28 -> 0.95 | G56: =ibpp_29 -> 0.9 | K56: Ibiden 模型 pp（Assumed）
A57: 欣興漲價年度化（CY2026 基期；FY2026＝1） | B57: x | D57: =1 -> 1 | E57: =1+carry -> 1.05 | F57: =1+carry -> 1.05 | G57: =1+carry -> 1.05 | K57: In 頁 carry（Assumed）
A58: 每顆 NVIDIA 加速器載板金額（全市場）＝ FY2026 金額 × 面積層數 × 溢價 | B58: US$／顆 | D58: =v26*D55*D56 -> 215.3086 | E58: =v26*E55*E56 -> 254.06414 | F58: =v26*F55*F56 -> 284.8059 | G58: =v26*G55*G56 -> 318.38302 | K58: FY2026 金額取自 Ibiden 模型 Units 頁（權威）
A59: 欣興份額：NVIDIA 加速器載板 | B59: % | D59: =sh_nv_26 -> 0.25 | E59: =sh_nv_27 -> 0.27 | F59: =sh_nv_28 -> 0.29 | G59: =sh_nv_29 -> 0.3
A60: 欣興份額：非 NVIDIA 加速器載板（金額） | B60: % | D60: =sh_ot_26 -> 0.3 | E60: =sh_ot_27 -> 0.31 | F60: =sh_ot_28 -> 0.32 | G60: =sh_ot_29 -> 0.33
A61: 欣興加速器載板營收 ＝（NVIDIA × 金額 × 份額 ＋ 非 NVIDIA × 金額 × v_ot × 份額）× 漲價年度化 | B61: US$M | D61: =(D53*D58*D59+D54*D58*v_ot*D60)*D57 -> 801.80921 | E61: =(E53*E58*E59+E54*E58*v_ot*E60)*E57 -> 1299.9039 | F61: =(F53*F58*F59+F54*F58*v_ot*F60)*F57 -> 1700.2571 | G61: =(G53*G58*G59+G54*G58*v_ot*G60)*G57 -> 2230.785
A62: 欣興加速器載板營收（新台幣） | B62: NT$B | D62: =D61*fx/1000 -> 26.058799 | E62: =E61*fx/1000 -> 42.246878 | F62: =F61*fx/1000 -> 55.258355 | G62: =G61*fx/1000 -> 72.500513
A63: B. ABF 需求與產能（營收＝MIN（需求, 產能））
A64: AI 載板需求（FY2026＝ABF × AI 占比） | B64: NT$B | D64: =a26_abf*ai_abf -> 74.836729 | K64: 公司：載板 AI 占比上半年逾 60%、下半年 70%
A65: 其他 AI 載板需求（交換器、伺服器 CPU、網通 ASIC） | B65: NT$B | D65: =D64-D62 -> 48.777929 | E65: =$D65*(itc_27/itc_26)^el_o*1*0.8*E56*E57 -> 57.974938 | F65: =$D65*(itc_28/itc_26)^el_o*um28_A*0.8*F56*F57 -> 62.00945 | G65: =$D65*(itc_29/itc_26)^el_o*um29_A*0.8*G56*G57 -> 62.70018 | K65: FY2026＝校準殘差（Derived）；之後 × AI IT 資本支出成長 ^ 彈性 × 溢價
A66: 非 AI ABF 需求（PC、一般伺服器） | B66: NT$B | D66: =a26_abf-D64 -> 24.945576 | E66: =D66*(1+g_nai) -> 25.693944 | F66: =E66*(1+g_nai) -> 26.464762 | G66: =F66*(1+g_nai) -> 27.258705
A67: ABF 需求合計 | B67: NT$B | D67: =D62+D65+D66 -> 99.782305 | E67: =E62+E65+E66 -> 125.91576 | F67: =F62+F65+F66 -> 143.73257 | G67: =G62+G65+G66 -> 162.4594
A68: ABF 產能上限（FY2026 營收 × 產能指數 × 組合 × 溢價） | B68: NT$B | D68: =a26_abf -> 99.782305 | E68: =$D67*cap_27*(1+g_mix)^1*E56*E57 -> 148.51349 | F68: =$D67*cap_28*(1+g_mix)^2*F56*F57 -> 186.54944 | G68: =$D67*cap_29*(1+g_mix)^3*G56*G57 -> 218.31483 | K68: FY2026 稼動率逾 90%，以 FY2026 營收為產能基準
A69: ABF 載板營收 ＝ MIN（需求, 產能） | B69: NT$B | D69: =a26_abf -> 99.782305 | E69: =MIN(E67,E68) -> 125.91576 | F69: =MIN(F67,F68) -> 143.73257 | G69: =MIN(G67,G68) -> 162.4594
A70: 需求滿足率（營收 ÷ 需求；< 100% 表示產能受限） | B70: % | D70: =D69/D67 -> 1 | E70: =E69/E67 -> 1 | F70: =F69/F67 -> 1 | G70: =G69/G67 -> 1
A71: AI 載板營收（加速器＋其他 AI，乘滿足率） | B71: NT$B | D71: =(D62+D65)*D70 -> 74.836729 | E71: =(E62+E65)*E70 -> 100.22182 | F71: =(F62+F65)*F70 -> 117.26781 | G71: =(G62+G65)*G70 -> 135.20069
A72: 加速器載板 ÷ AI 載板 | B72: % | D72: =D62/(D62+D65) -> 0.34820869 | E72: =E62/(E62+E65) -> 0.42153375 | F72: =F62/(F62+F65) -> 0.47121505 | G72: =G62/(G62+G65) -> 0.53624365
A73: C. 其他產品與合計
A74: BT 載板 | B74: NT$B | D74: =a26_bt -> 16.944165 | E74: =D74*(1+g_bt) -> 17.791373 | F74: =E74*(1+g_bt) -> 18.680942 | G74: =F74*(1+g_bt) -> 19.614989
A75: AI HDI／PCB | B75: NT$B | D75: =a26_pcb*ai_pcb -> 37.936103 | E75: =D75*(1+g_pai_27) -> 45.523323 | F75: =D75*(1+g_pai_27)*(1+g_pai_28)*um28_A -> 52.351822 | G75: =D75*(1+g_pai_27)*(1+g_pai_28)*(1+g_pai_29)*um29_A -> 57.587004 | K75: 基準路徑 × 顆數情境係數
A76: 非 AI HDI／PCB | B76: NT$B | D76: =a26_pcb*(1-ai_pcb) -> 20.427132 | E76: =D76*(1+g_pcbn) -> 20.835675 | F76: =E76*(1+g_pcbn) -> 21.252388 | G76: =F76*(1+g_pcbn) -> 21.677436
A77: 軟板與其他 | B77: NT$B | D77: =a26_fpc -> 13.178795 | E77: =D77*(1+g_fpc) -> 13.178795 | F77: =E77*(1+g_fpc) -> 13.178795 | G77: =F77*(1+g_fpc) -> 13.178795
A78: 營收 | B78: NT$B | C78: =a25_rev -> 131.241 | D78: =D69+D74+D75+D76+D77 -> 188.2685 | E78: =E69+E74+E75+E76+E77 -> 223.24493 | F78: =F69+F74+F75+F76+F77 -> 249.19651 | G78: =G69+G74+G75+G76+G77 -> 274.51762 | H78: =G78*(1+H79) -> 298.60398 | I78: =H78*(1+I79) -> 320.66196 | J78: =I78*(1+J79) -> 339.90168 | K78: FY2030 起為收斂法：營收年增由 FY2029 線性收斂到 fade_g、淨利率收斂到 fade_m（FY2032 達到），非驅動因子推導
A79: 營收年增 | B79: % | D79: =D78/C78-1 -> 0.43452503 | E79: =E78/D78-1 -> 0.18577949 | F79: =F78/E78-1 -> 0.11624716 | G79: =G78/F78-1 -> 0.101611 | H79: =$G79+(fade_gA-$G79)*1/3 -> 0.087740669 | I79: =$G79+(fade_gA-$G79)*2/3 -> 0.073870335 | J79: =$G79+(fade_gA-$G79)*3/3 -> 0.06
A80: ABF ÷ 營收 | B80: % | D80: =D69/D78 -> 0.53 | E80: =E69/E78 -> 0.56402518 | F80: =F69/F78 -> 0.57678402 | G80: =G69/G78 -> 0.59179952
A81: AI（載板＋HDI／PCB）÷ 營收 | B81: % | D81: =(D71+D75)/D78 -> 0.599 | E81: =(E71+E75)/E78 -> 0.65284861 | F81: =(F71+F75)/F78 -> 0.68066613 | G81: =(G71+G75)/G78 -> 0.70227804 | K81: 公司：2H26 約 70%
A82: D. 擴產折舊、毛利與損益
A83: 資本支出 | B83: NT$B | C83: =a25_cx -> 25.617 | D83: =capex26 -> 53.7 | E83: =cx27_A -> 55 | F83: =cx28_A -> 50 | G83: =cx29_A -> 45 | H83: =H78*H100 -> 45.925317 | I83: =I78*I100 -> 46.071512 | J83: =J78*J100 -> 45.394699
A84: 折舊攤提 ＝ 前一年 ×（1 − 1／年限）＋ 前一年資本支出 ÷ 年限 | B84: NT$B | C84: =a25_da -> 18.8 | D84: =da26 -> 20.8 | E84: =D84*(1-1/life)+D83/life -> 24.9125 | F84: =E84*(1-1/life)+E83/life -> 28.673437 | G84: =F84*(1-1/life)+F83/life -> 31.339258 | H84: =H78*H85 -> 34.088985 | I84: =I78*I85 -> 36.60715 | J84: =J78*J85 -> 38.803579 | K84: 新產能前一年投入、當年開始折舊（近似）
A85: 折舊 ÷ 營收 | B85: % | C85: =C84/C78 -> 0.14324792 | D85: =D84/D78 -> 0.11048051 | E85: =E84/E78 -> 0.11159268 | F85: =F84/F78 -> 0.11506356 | G85: =G84/G78 -> 0.11416119 | H85: =$G85 -> 0.11416119 | I85: =$G85 -> 0.11416119 | J85: =$G85 -> 0.11416119
A86: 漲價溢價營收（相對 FY2026 價格；全數落在毛利） | B86: NT$B | E86: =E71*(1-1/(E56*E57)) -> 4.7724674 | F86: =F71*(1-1/(F56*F57)) -> -0.29390427 | G86: =G71*(1-1/(G56*G57)) -> -7.8688234 | K86: AI 載板營收 ×（1 − 1／價格指數）
A87: 毛利 ＝ FY2026 ＋ ABF 現金毛利增量 ＋ 其他產品現金毛利增量 ＋ 溢價 − 折舊增量 | B87: NT$B | C87: =a25_gp -> 18.292 | D87: =a26_gp -> 47.332966 | E87: =$D87+ft_abf*(E69-E86-$D69)+ft_oth*((E78-E69)-($D78-$D69))+E86-(E84-$D84) -> 60.884169 | F87: =$D87+ft_abf*(F69-F86-$D69)+ft_oth*((F78-F69)-($D78-$D69))+F86-(F84-$D84) -> 65.532145 | G87: =$D87+ft_abf*(G69-G86-$D69)+ft_oth*((G78-G69)-($D78-$D69))+G86-(G84-$D84) -> 70.09085 | K87: 流通率為現金毛利口徑；折舊另計
A88: 毛利率 | B88: % | C88: =C87/C78 -> 0.13937718 | D88: =D87/D78 -> 0.25141203 | E88: =E87/E78 -> 0.27272364 | F88: =F87/F78 -> 0.26297376 | G88: =G87/G78 -> 0.25532368
A89: 營業費用 | B89: NT$B | C89: =a25_opx -> 11.618 | D89: =a26_opx -> 16.653953 | E89: =D89*(1+phi*E79) -> 18.510331 | F89: =E89*(1+phi*F79) -> 19.801395 | G89: =F89*(1+phi*G79) -> 21.008619
A90: 營業利益 | B90: NT$B | C90: =C87-C89 -> 6.674 | D90: =D87-D89 -> 30.679012 | E90: =E87-E89 -> 42.373839 | F90: =F87-F89 -> 45.73075 | G90: =G87-G89 -> 49.082231
A91: 營業利益率 | B91: % | C91: =C90/C78 -> 0.050853011 | D91: =D90/D78 -> 0.16295351 | E91: =E90/E78 -> 0.18980874 | F91: =F90/F78 -> 0.1835128 | G91: =G90/G78 -> 0.17879446
A92: 營業外淨額 | B92: NT$B | C92: =a25_nonop -> -0.001 | D92: =a26_nonop -> 14.466 | E92: =nonop27 -> 2 | F92: =nonop28 -> 2 | G92: =nonop29 -> 2 | K92: FY2026 含 2Q26 一次性評價利益
A93: 稅前利益 | B93: NT$B | C93: =C90+C92 -> 6.673 | D93: =D90+D92 -> 45.145012 | E93: =E90+E92 -> 44.373839 | F93: =F90+F92 -> 47.73075 | G93: =G90+G92 -> 51.082231
A94: 所得稅與少數股權 | B94: NT$B | E94: =E93*tax -> 7.9872909 | F94: =F93*tax -> 8.591535 | G94: =G93*tax -> 9.1948016
A95: 歸屬母公司淨利 | B95: NT$B | C95: =a25_ni -> 6.673 | D95: =a26_ni -> 37.23923 | E95: =E93-E94 -> 36.386548 | F95: =F93-F94 -> 39.139215 | G95: =G93-G94 -> 41.88743 | H95: =H78*H99 -> 47.677225 | I95: =I78*I99 -> 53.469925 | J95: =J78*J99 -> 59.085134
A96: 加權股數 | B96: 十億股 | C96: =a25_sh -> 1.523516 | D96: =a26_sh -> 1.5923632 | E96: =a26_shend*(1+sh_g) -> 1.64 | F96: =E96*(1+sh_g) -> 1.64 | G96: =F96*(1+sh_g) -> 1.64 | H96: =G96*(1+sh_g) -> 1.64 | I96: =H96*(1+sh_g) -> 1.64 | J96: =I96*(1+sh_g) -> 1.64
A97: EPS（基本） | B97: NT$ | C97: =C95/C96 -> 4.38 | D97: =D95/D96 -> 23.386141 | E97: =E95/E96 -> 22.186919 | F97: =F95/F96 -> 23.865375 | G97: =G95/G96 -> 25.541116 | H97: =H95/H96 -> 29.071478 | I97: =I95/I96 -> 32.603613 | J97: =J95/J96 -> 36.027521
A98: EPS 年增 | B98: % | D98: =D97/C97-1 -> 4.3393017 | E98: =E97/D97-1 -> -0.051279182 | F98: =F97/E97-1 -> 0.075650692 | G98: =G97/F97-1 -> 0.070216392 | H98: =H97/G97-1 -> 0.13822273 | I98: =I97/H97-1 -> 0.12149826 | J98: =J97/I97-1 -> 0.10501621
A99: 淨利率（歸屬母公司淨利 ÷ 營收） | B99: % | C99: =C95/C78 -> 0.050845391 | D99: =D95/D78 -> 0.19779852 | E99: =E95/E78 -> 0.16298936 | F99: =F95/F78 -> 0.15706165 | G99: =G95/G78 -> 0.15258558 | H99: =$G99+(fade_mA-$G99)*1/3 -> 0.15966708 | I99: =$G99+(fade_mA-$G99)*2/3 -> 0.16674858 | J99: =$G99+(fade_mA-$G99)*3/3 -> 0.17383007
A100: 資本支出 ÷ 營收 | B100: % | C100: =C83/C78 -> 0.19519053 | D100: =D83/D78 -> 0.28523093 | E100: =E83/E78 -> 0.24636618 | F100: =F83/F78 -> 0.20064486 | G100: =G83/G78 -> 0.1639239 | H100: =$G100+($G85*(1+tp_g)^(life/2)-$G100)*1/3 -> 0.15380008 | I100: =$G100+($G85*(1+tp_g)^(life/2)-$G100)*2/3 -> 0.14367626 | J100: =$G100+($G85*(1+tp_g)^(life/2)-$G100)*3/3 -> 0.13355244 | K100: FY2030 起：資本支出率由 FY2029 線性收斂到 折舊率 ×（1＋tp_g）^（年限／2）（穩態更新）；折舊率維持 FY2029
A101: 股東現金流 ＝ 淨利 ＋ 折舊 − 資本支出 | B101: NT$B | E101: =E95+E84-E83 -> 6.2990476 | F101: =F95+F84-F83 -> 17.812653 | G101: =G95+G84-G83 -> 28.226687 | H101: =H95+H84-H83 -> 35.840893 | I101: =I95+I84-I83 -> 44.005563 | J101: =J95+J84-J83 -> 52.494014 | K101: 不含客戶預付款（光復二廠、楊梅二廠由客戶全額預付）與營運資金變動
A102: 每股股東現金流 | B102: NT$ | E102: =E101/E96 -> 3.8408827 | F102: =F101/F96 -> 10.861374 | G102: =G101/G96 -> 17.211395 | H102: =H101/H96 -> 21.854203 | I102: =I101/I96 -> 26.83266 | J102: =J101/J96 -> 32.008545
A105: 案例區塊：AI 部署 ×1.2（情境 A）
A106: 項目 | B106: 單位 | C106: FY2025A | D106: FY2026（錨點） | E106: FY2027 | F106: FY2028 | G106: FY2029 | H106: FY2030（收斂） | I106: FY2031（收斂） | J106: FY2032（收斂） | K106: 說明
A107: A. AI 加速器載板（口徑與 Ibiden 一致；D 欄＝FY2026 校準年）
A108: NVIDIA 加速器顆數 × 情境係數 | B108: 百萬顆 | D108: =(u_bw_26+u_rb_26+u_ru_26+u_hp_26)*1 -> 7.6 | E108: =(u_bw_27+u_rb_27+u_ru_27+u_hp_27)*1*1.2 -> 11.64 | F108: =(u_bw_28+u_rb_28+u_ru_28+u_hp_28)*um28_A*1.2 -> 11.4 | G108: =(u_bw_28*(1+g29_bw)+u_rb_28*(1+g29_rb)+u_ru_28*(1+g29_ru)+u_hp_28*(1+g29_hp))*um29_A*1.2 -> 12.72 | K108: markets/network In：Blackwell、Rubin、Rubin Ultra、Hopper
A109: 非 NVIDIA 加速器顆數 × 情境係數 | B109: 百萬顆 | D109: =(u_amd_26+u_tpu_26+u_trn_26+u_oth_26)*1 -> 7.6 | E109: =(u_amd_27+u_tpu_27+u_trn_27+u_oth_27)*1*1.2 -> 16.8 | F109: =(u_amd_28+u_tpu_28+u_trn_28+u_oth_28)*um28_A*1.2 -> 20.4 | G109: =(u_amd_28*(1+g29_amd)+u_tpu_28*(1+g29_tpu)+u_trn_28*(1+g29_trn)+u_oth_28*(1+g29_oth))*um29_A*1.2 -> 23.46 | K109: AMD、TPU、Trainium、其他 ASIC
A110: 每顆載板面積與層數指數（FY2026＝1） | B110: x | D110: =1 -> 1 | E110: =D110*(1+g_asp) -> 1.18 | F110: =E110*(1+g_asp) -> 1.3924 | G110: =F110*(1+g_asp) -> 1.643032 | K110: Ibiden 模型 g_asp（Analogy）
...

Sheet Sources
A1: 來源（公司財報經媒體與資料商轉載；法說內容經媒體摘要；券商與資料商皆為 Interested-party）
A2: 公司（轉載）：工商時報 2026-07-29 2Q26 財報（營收、營業利益、業外、淨利、資本支出） | B2: https://www.ctee.com.tw/news/20260729700548-430201
A3: 公司（轉載）：工商時報 2026-07-29 2Q26 法說（產品組合、應用別、稼動率、AI 占比、產能時程） | B3: https://www.ctee.com.tw/news/20260729701506-430201
A4: 公司（轉載）：Quartr 2Q26 摘要（營收、毛利率、營業利益、EBITDA、1H26） | B4: https://quartr.com/events/unimicron-technology-corp-3037-q2-2026_F9DCOIJX
A5: 公司（摘要）：富果 4Q25 法說摘要（FY2025、折舊 188 億 → 208 億、4Q25 產品組合、光復二廠） | B5: https://blog.fugle.tw/post/earnings-call-3037-2026-02-25
A6: 媒體：口袋學堂 2Q26 法說（業外明細、ABF 52%、Blackwell 約 30%） | B6: https://www.pocket.tw/school/articles/7708/
A7: 媒體：優分析 2Q26（資本支出 537 億） | B7: https://uanalyze.com.tw/articles/4246852366
A8: 媒體：永豐 豐學 1Q26（1Q26 營收、毛利率、EPS、ABF 供需缺口、私募與可轉債） | B8: https://www.sinotrade.com.tw/richclub/hotstock/欣興-3037--1Q26-EPS繳出3-28元改寫13季新高-T-glass缺料推升ABF漲價循環的預期差再放大-豐學PRIME盤後精選--69f16461f5cc3b01237ecb00
A9: 媒體：優分析 2026-04-10（GDR 董事會決議） | B9: https://uanalyze.com.tw/articles/7364850419
A10: 媒體：優分析 2026-07（GDR 5,000 萬單位、每單位 US$26.96–27.76） | B10: https://uanalyze.com.tw/articles/9347152010
A11: 媒體：TechNews 2026-10-08（9 月營收 186.51 億、前 9 月 1,329.86 億） | B11: https://finance.technews.tw/2026/10/08/unimicron-3037-202609-financial-report/
A12: 券商（媒體）：三立 2026-10-19 本土法人（目標價 1,500、EPS 2026 23.42／2027 41.10、Q3、Q4 預估、產能時程） | B12: https://www.mirrormedia.mg/external/setn_1923649
A13: 券商（媒體）：經濟日報 2026-10-12 美系券商（EPS 2026 21／2027 37／2028 64.8、資本支出逾 400 億） | B13: https://money.udn.com/money/story/5607/9808557
... A23: SemiAnalysis | B23: 未使用
