Workbook

Sheet README
A1: Credo（CRDO）收支與估值模型 v0.2.3（AI 半導體 Project：網通次產業內複製——主動電纜 AEC、SerDes、光 DSP） 2026-10-26
A2: 版本：v0.2（2026-10-25：三情境延伸到 FY2032、目標價＝DCF 與 Comparable 加權；v0.1 初版）。Credo 在 AI 銅纜（AEC）與光學的份額在本模型 Units 頁建立，為本專案權威資料（規則第 13 條）。
A3: 模型命題：Credo 的 AEC 營收＝AI 銅纜市場（本專案網通模型：scale-up 背板與線纜＋scale-out DAC／AEC）× Credo 有效份額（AEC 滲透率 × Credo 占 AEC）；光學（光 DSP、矽光 PIC、ZeroFlap 光學）＝可插拔光模組市場 × 光學份額；線卡 PHY、重定時器與 SerDes IP 另依成長率推。股價自 52 週高點跌約 52%、只約 15 倍共識 FY2028 EPS：市場定價像是 AEC 成長在 FY2028 前後見頂。
A4: 核心問題：市場隱含的 FY2028 EPS 是否低於模型——要成立，AEC 份額（競爭、主動光纜自我替代）、客戶集中（前四大終端客戶占 84%）、銅轉光（AI 銅纜市場）三條路徑各要不利到什麼程度？
A6: 會計年度：FY(t) 於 t 年 4 月底／5 月初結束（FY2027＝2026-05-03～2027-05-01），8 個月落在日曆年 t−1；上游市場層為日曆年，FY(t) 市場＝8/12 × CY(t−1)＋4/12 × CY(t)。預測期 FY2028–FY2029（FY2027 為錨點）。口徑：公司 non-GAAP；十年 P/E 規則值用 GAAP 換算 EPS。
A8: 驅動因子 → 推導量（全部唯讀上游，不修改）
A9: AEC：markets/network 的 AI 銅纜市場（FY 加權）× 情境顆數係數 × Credo AEC 有效份額（FY2027 錨點校準）× 份額相對值（Assumed）。光學：可插拔光模組市場 × 光學有效份額（FY2027 以公司目標逾 6 億美元校準）× 相對值（Assumed）。
A10: 其他 IC 與 IP：FY2026 營收 × 7%（Assumed）× 成長率。毛利率：FY2028 起為輸入路徑（Assumed）。營業費用：彈性 phi（FY2027 錨點 Derived）。稅率：FY2028 起 13–14%（Assumed，OECD 最低稅）。
A11: 校準：FY2027 ＝ 1Q27 實績（營收 4.79 億美元、non-GAAP EPS 1.20）＋ 2Q27 指引中點（5.30 億美元）＋ 2H27（全年年增 85% 下緣減 1H）。產品線拆分公司未揭露：光學 FY2026 為假設、FY2027 用公司目標，AEC 為殘差。不用共識（只在 Recon 對帳）。
A12: 估值：目標價（Val 第 0 節）＝0.5 × DCF（股東現金流＝EPS ×（1 − g／ROE），FY2027–32 明確期＋永續，r 10%、g 4%，情境權重 0.3／0.5／0.2）＋0.5 × Comparable（美股高速連接晶片同業前瞻 P/E 中位數 × 12 個月後前瞻 EPS）。舊法規則值情境加權保留參考（不是目標價）；市場隱含 FY2028 EPS（Val 第 4 節）；十年 P/E 規則值（只有 2025 年一個正值）× 2027 年底近 12 月 GAAP 換算 EPS；循環位置以本模型營收最高年判定。Val 第 0 節為情境加權目標價。本版未做先驗，無 Andy 合理 P/E 對照。
A13: 標記：Verified、Interested-party、Analogy、Assumed、Derived。SemiAnalysis 未使用。客戶名稱（Amazon、xAI、Microsoft）只有券商與媒體來源；公司 10-K 只揭露未具名的客戶占比。
A15: 已知限制：(1) AEC 與光學份額相對值、毛利率路徑、FY2028 起稅率皆為 Assumed，是 FY2028–FY2029 EPS 最敏感的輸入（Sens）；(2) 產品線營收未揭露，AEC 為殘差；(3) 網通模型的銅纜市場以 NVIDIA 平台為主，Credo 客戶以 ASIC 與超大規模業者為主，份額校準吸收了這個口徑差；(4) 十年 P/E 只有 2025 年一個觀測值、含高成長期溢價，規則值與目標價明顯偏高；(5) 會計年度與日曆年以月數加權近似；(6) R4 產業部署路徑未建（Recon 預留列）。
... A17: v0.2.1（2026-10-25）：補上檔空間級距、投資建議、重點觀察（數值不變）。Val 頁末新增「上檔空間級距」「投資建議」兩列（Andy 2026-10-25 14:00、14:17 固定規則），README 頁末新增投資建議與重點觀察三點；既有儲存格位置與數值不變。
A18: ="投資建議："&Val!B130&"（依上檔空間固定規則）" -> 投資建議：買進（依上檔空間固定規則）
A19: 重點觀察 1：目標價 US$195（DCF 100、Comparable 289 各半），比現價 147.29（2026-10-23）高 32.1%，級距 25%–50%；Comparable 單獨為 +96.1%。上檔全部來自倍數：本模型 12 個月後前瞻 EPS 8.37 比共識 9.69 低 13.6%，但現價只隱含 15.2 倍共識前瞻 EPS，同業（Astera Labs、Marvell、Broadcom、MACOM）前瞻 P/E 中位數 34.5 倍、共識目標價 279.09 隱含 28.8 倍；DCF 100 反而比現價低 32.0%，因 B、C 情境 FY2029 起 EPS 下滑（FY2032 B 7.64、C 3.74），且 ROE 無同口徑資料、取 20%。
A20: 重點觀察 2：目標價對 DCF 權重最敏感：DCF 權重 0.3／0.7 時目標價 232.2／156.8（±19.4%），權重 0.7 時上檔空間只剩 +6.4%、落入中立。
A21: 重點觀察 3：FY2028 EPS 最敏感的是 AEC：最大客戶流失時 −24.7%、AEC 份額流失 −18.7%、AI 銅纜市場 ×0.8 時 −15.0%（Sens 頁）。光學的可插拔市場改讀同字母網通 CPO 情境（v0.2.2），情境 A FY2028 EPS 9.20 → 9.11（−0.9%）、C 7.81 → 7.84（+0.4%）。下一個檢驗點是 2Q FY27 財報（約 2026-12 初）的 AEC 營收與最大客戶占比。
A22: v0.2.3（2026-10-28）：分部原則重建（數值不變）。Q 頁最後追加核對列「檢查：分部合計 − 合併營收」；官方分部與子列宣告見 segments.json。
A23: v0.2.2（2026-10-26）：網通模型 v0.2.3 的 CPO 滲透改三情境（A＝替代快、B＝平平、C＝慢），本模型光學的可插拔市場 A／B／C 改讀同字母列（In 頁末新增 B、C；情境 A 沿用 mpl_，數值改為網通情境 A）。光學有效份額以 FY2027 錨點 ÷ 情境 B 市場校準（三情境同一份額；B 的 CPO 路徑＝v0.2.1，故情境 B 數值不變），所以 CPO 快 → 光學營收較少。銅纜（AEC）市場不受 CPO 影響。其他輸入不變。

Sheet In
A1: In — 輸入（藍字；基準欄 E，低 D、高 F）。金額：十億美元（US$B）；比例：%。每個輸入附兩個來源（找不到者寫「未找到」）；公司原文算一個
A2: 標記：Verified／Interested-party／Analogy／Assumed／Derived；Analogy、Assumed 給低／高區間。SemiAnalysis 未使用。公司原文＝SEC 8-K 新聞稿與 10-K；公司不揭露產品線營收（AEC、光學、IC、IP）與客戶名稱；客戶名稱只有券商與媒體來源
A3: 鍵 | B3: 項目 | C3: 單位 | D3: 低 | E3: 基準 | F3: 高 | G3: 標記 | H3: 來源1 | I3: 來源2／說明
A4: A. AI 銅纜與光模組市場（讀 markets/network 成品；日曆年 CY2026–CY2029；情境 A 基準，B／C 依顆數係數縮放）
A5: mcu_26 | B5: AI 銅纜市場 CY2026（scale-up 背板與線纜＋scale-out DAC／AEC） | C5: US$B | E5: 25.97546 | G5: Derived | H5: markets/network/dist/20261026_AI網通市場模型_v0.2.3.xlsx｜Mkt!C21:F21 | I5: 加速器顆數 × 每顆銅內容；scale-up 銅＝互連 × 銅占比、2029 年 scale-up 光學占 20%（網通模型）
A6: mcu_27 | B6: AI 銅纜市場 CY2027（scale-up 背板與線纜＋scale-out DAC／AEC） | C6: US$B | E6: 51.06612 | G6: Derived | H6: markets/network/dist/20261026_AI網通市場模型_v0.2.3.xlsx｜Mkt!C21:F21 | I6: 同上
A7: mcu_28 | B7: AI 銅纜市場 CY2028（scale-up 背板與線纜＋scale-out DAC／AEC） | C7: US$B | E7: 59.4676 | G7: Derived | H7: markets/network/dist/20261026_AI網通市場模型_v0.2.3.xlsx｜Mkt!C21:F21 | I7: 同上
A8: mcu_29 | B8: AI 銅纜市場 CY2029（scale-up 背板與線纜＋scale-out DAC／AEC） | C8: US$B | E8: 60.951534 | G8: Derived | H8: markets/network/dist/20261026_AI網通市場模型_v0.2.3.xlsx｜Mkt!C21:F21 | I8: 同上
A9: mso_26 | B9: 其中 scale-out 銅纜（DAC／AEC）CY2026 | C9: US$B | E9: 13.8758 | G9: Derived | H9: markets/network/dist/20261026_AI網通市場模型_v0.2.3.xlsx｜Mkt!C9:F9 | I9: Units、Recon 用（只作拆分參考）
A10: mso_27 | B10: 其中 scale-out 銅纜（DAC／AEC）CY2027 | C10: US$B | E10: 26.4567 | G10: Derived | H10: markets/network/dist/20261026_AI網通市場模型_v0.2.3.xlsx｜Mkt!C9:F9 | I10: 同上
A11: mso_28 | B11: 其中 scale-out 銅纜（DAC／AEC）CY2028 | C11: US$B | E11: 29.8375 | G11: Derived | H11: markets/network/dist/20261026_AI網通市場模型_v0.2.3.xlsx｜Mkt!C9:F9 | I11: 同上
A12: mso_29 | B12: 其中 scale-out 銅纜（DAC／AEC）CY2029 | C12: US$B | E12: 33.92475 | G12: Derived | H12: markets/network/dist/20261026_AI網通市場模型_v0.2.3.xlsx｜Mkt!C9:F9 | I12: 同上
A13: mpl_26 | B13: AI 可插拔光模組市場 CY2026 | C13: US$B | E13: 29.753262 | G13: Derived | H13: markets/network/dist/20261026_AI網通市場模型_v0.2.3.xlsx｜Mkt!C45:F45 | I13: 光 DSP、矽光 PIC、ZeroFlap 光學的市場基底
A14: mpl_27 | B14: AI 可插拔光模組市場 CY2027 | C14: US$B | E14: 53.560715 | G14: Derived | H14: markets/network/dist/20261026_AI網通市場模型_v0.2.3.xlsx｜Mkt!C45:F45 | I14: 同上
A15: mpl_28 | B15: AI 可插拔光模組市場 CY2028 | C15: US$B | E15: 57.9915 | G15: Derived | H15: markets/network/dist/20261026_AI網通市場模型_v0.2.3.xlsx｜Mkt!C45:F45 | I15: 同上
A16: mpl_29 | B16: AI 可插拔光模組市場 CY2029 | C16: US$B | E16: 72.9348 | G16: Derived | H16: markets/network/dist/20261026_AI網通市場模型_v0.2.3.xlsx｜Mkt!C45:F45 | I16: 同上
... A26: um29_C | B26: 情境 C：CY2029 顆數 ÷ 基準 | C26: x | E26: 0.6 | G26: Assumed | H26: tsmc/dist/20261028_台積電個股模型_v0.4.xlsx｜In!E42 | I26: 同上
A27: w8 | B27: FY(t) 落在日曆年 t−1 的比重（5–12 月） | C27: x | E27: =8/12 -> 0.66666667 | G27: Derived | H27: https://www.sec.gov/Archives/edgar/data/0001807794/000162828026043303/crdo-20260502.htm：FY2026 截至 2026-05-02、FY2025 截至 2025-05-03（52／53 週） | I27: FY(t) 市場＝w8 × CY(t−1)＋（1 − w8）× CY(t)
A28: B. AEC 份額（本專案為權威：Credo 在 AI 銅纜的份額，規則第 13 條）與客戶集中
A29: rel_a_28 | B29: AEC 有效份額 FY2028 ÷ FY2027（相對值；＝AEC 滲透率變化 × Credo 份額變化） | C29: x | D29: 0.75 | E29: 1 | F29: 1.15 | G29: Assumed | H29: https://invezz.com/en-ae/news/2026/04/13/credo-jumps-11percent-as-jefferies-backs-copper-tech-in-ai-boom-debate/：Jefferies（2026-04）AEC 2026 年 860 萬條、2027 年 1,230 萬條；Credo 份額樂觀情境約 70%（Interested-party） | I29: 1.6T 使被動 DAC 距離更短（AEC 滲透率上推）vs Astera Labs、Marvell、Broadcom 與線纜廠競爭（10-K 列名競爭者）
A30: rel_a_29 | B30: AEC 有效份額 FY2029 ÷ FY2027 | C30: x | D30: 0.6 | E30: 0.95 | F30: 1.2 | G30: Assumed | H30: 同上；ZeroFlap 主動光纜（ALC，2027 年出貨）可能部分自我替代 AEC | I30: https://www.tikr.com/blog/credo-stock-fell-22-last-week-as-it-launched-a-new-optical-cable-heres-where-it-could-go-by-2031：ALC 50 公尺、每端約 12 瓦（公司在 OCP 2026-10 發表）
A31: cr_aec_sh | B31: Credo 占 AEC 市場（Units 拆分用；不進損益） | C31: % | D31: 0.6 | E31: 0.75 | F31: 0.9 | G31: Assumed | H31: Invezz 轉述 Jefferies（網址見 Sources）：樂觀情境 2027 年約 70% | I31: 第一手 AEC 市場份額：未找到
A32: cust_top | B32: 最大終端客戶占營收（Sens「最大客戶流失」用） | C32: % | E32: 0.33 | G32: Interested-party | H32: https://www.yourwyominglink.com/credo-q1-earnings-call-highlights-optics-as-the-next-growth-engine/article_d01cfee6-9667-5ab6-8b08-fcf8fffa13d0.html：1Q27 前四大終端客戶 33%、28%、13%、10%（Zacks 轉述法說） | I32: https://www.sec.gov/Archives/edgar/data/0001807794/000162828026043303/crdo-20260502.htm：FY2026 終端客戶 D 33%（FY2025 63%）、B 32%、E 19%（公司，未具名）
A33: cl_28 | B33: 最大客戶流失情境：AEC 有效份額 FY2028 ÷ FY2027（Sens 用） | C33: x | E33: =rel_a_28*(1-cust_top) -> 0.67 | G33: Derived | H33: AEC 份額相對值 ×（1 − 最大客戶占比）；假設流失的客戶全是 AEC | I33: 客戶名稱：Amazon、xAI、Microsoft（Needham 等券商，Benzinga 2025-03；Interested-party）；公司未具名
A34: cl_29 | B34: 最大客戶流失情境：AEC 有效份額 FY2029 ÷ FY2027（Sens 用） | C34: x | E34: =rel_a_29*(1-cust_top) -> 0.6365 | G34: Derived | H34: 同上 | I34: https://www.benzinga.com/25/03/44149586/credo-expands-hyperscaler-partnerships-with-amazon-microsoft-xai-amid-nvidia-powered-ai-boom：Amazon 曾占單季營收 86%（FY2025 Q3）
A35: C. 光學（光 DSP、矽光 PIC〔DustPhotonics〕、ZeroFlap 光學；讀可插拔光模組市場）
A36: opt_26 | B36: FY2026 光學營收（未揭露） | C36: US$B | D36: 0.08 | E36: 0.15 | F36: 0.25 | G36: Assumed | H36: 公司不揭露產品線營收：未找到 | I36: Let's Data Science（網址見 Sources）：FY2027 光學三條產品線各逾 1 億美元、合計逾 6 億美元（公司法說，Interested-party）
A37: opt_27 | B37: FY2027 光學營收（公司目標「逾 6 億美元」） | C37: US$B | D37: 0.5 | E37: 0.6 | F37: 0.7 | G37: Interested-party | H37: https://www.itiger.com/news/1122940235：FY2027 光學逾 6 億美元（1Q27 法說重申） | I37: https://finance.yahoo.com/markets/stocks/articles/credo-makes-875-million-move-013700129.html：2026-04 宣布併購時為「逾 5 億美元」
A38: rel_o_28 | B38: 光學有效份額 FY2028 ÷ FY2027 | C38: x | D38: 0.9 | E38: 1.2 | F38: 1.6 | G38: Assumed | H38: https://www.yourwyominglink.com/credo-q1-earnings-call-highlights-optics-as-the-next-growth-engine/article_d01cfee6-9667-5ab6-8b08-fcf8fffa13d0.html：兩個次世代大型設計案預計 FY2028 量產；1.6T DSP 於 FY2027 後段開始貢獻（公司） | I38: DSP 競爭：Marvell、Broadcom 為主要供應商（10-K 列名競爭者）
A39: rel_o_29 | B39: 光學有效份額 FY2029 ÷ FY2027 | C39: x | D39: 0.9 | E39: 1.35 | F39: 2 | G39: Assumed | H39: 同上 | I39: —
A40: D. 其他營收（線卡 PHY、PCIe 重定時器、SerDes IP 授權與小晶片；網通模型未涵蓋）
A41: oth_s | B41: 其他 IC 與 IP ÷ 總營收（FY2026） | C41: % | D41: 0.04 | E41: 0.07 | F41: 0.1 | G41: Assumed | H41: 公司不揭露產品與 IP 授權拆分：未找到 | I41: 公司 FY2026 10-K（網址見 Sources）：未滿足履約義務約 3,190 萬美元，預計下一會計年度認列（IP 授權）
A42: g_oth | B42: 其他 IC 與 IP 年增（FY2027 起） | C42: % | D42: 0 | E42: 0.15 | F42: 0.3 | G42: Assumed | H42: 無 | I42: —
A43: E. FY2027 錨點（1Q27 實績＋2Q27 指引＋2H27 依全年指引推導）
A44: q1_rev | B44: 1Q27 營收（截至 2026-08-01） | C44: US$B | E44: 0.479003 | G44: Verified | H44: https://www.sec.gov/Archives/edgar/data/0001807794/000162828026059795/credoq12027ex-991.htm：479,003 千美元（年增 114.7%） | I44: https://pulse2.com/credo-reports-q1-fiscal-2027-revenue-of-479-million-up-115-year-over-year/：同值
A45: q1_gp | B45: 1Q27 non-GAAP 毛利（＝營業利益＋營業費用） | C45: US$B | E45: =0.230641+0.095154 -> 0.325795 | G45: Verified | H45: https://www.sec.gov/Archives/edgar/data/0001807794/000162828026059795/credoq12027ex-991.htm：non-GAAP 營業利益 230,641、營業費用 95,154 千美元；毛利率 68.0% | I45: GAAP 毛利率 64.5%（併購攤銷）
A46: q1_opx | B46: 1Q27 non-GAAP 營業費用 | C46: US$B | E46: 0.095154 | G46: Verified | H46: https://www.sec.gov/Archives/edgar/data/0001807794/000162828026059795/credoq12027ex-991.htm | I46: GAAP 188.4（含股票薪酬 82.3）
A47: q1_ninc | B47: 1Q27 其他收益（淨） | C47: US$B | E47: 0.00814 | G47: Verified | H47: https://www.sec.gov/Archives/edgar/data/0001807794/000162828026059795/credoq12027ex-991.htm：8,140 千美元 | I47: 現金與短期投資 7.64 億美元（DustPhotonics 現金對價後）
A48: q1_ni | B48: 1Q27 non-GAAP 淨利 | C48: US$B | E48: 0.236262 | G48: Verified | H48: https://www.sec.gov/Archives/edgar/data/0001807794/000162828026059795/credoq12027ex-991.htm：236,262 千美元 | I48: https://www.itiger.com/news/1122940235：同值（淨利率 49.3%）
A49: q1_sh | B49: 1Q27 non-GAAP 稀釋股數 | C49: 十億股 | E49: 0.197505 | G49: Verified | H49: https://www.sec.gov/Archives/edgar/data/0001807794/000162828026059795/credoq12027ex-991.htm：197,505 千股 | I49: GAAP 稀釋 194,378 千股
A50: q1_eps | B50: 1Q27 non-GAAP 稀釋 EPS | C50: US$ | E50: 1.2 | G50: Verified | H50: https://www.sec.gov/Archives/edgar/data/0001807794/000162828026059795/credoq12027ex-991.htm：1.20（GAAP 0.67） | I50: https://www.yourwyominglink.com/credo-q1-earnings-call-highlights-optics-as-the-next-growth-engine/article_d01cfee6-9667-5ab6-8b08-fcf8fffa13d0.html：同值；共識 1.17
A51: q2_rev | B51: 2Q27 營收指引（中點；截至 2026-10-31） | C51: US$B | D51: 0.525 | E51: 0.53 | F51: 0.535 | G51: Interested-party | H51: https://www.sec.gov/Archives/edgar/data/0001807794/000162828026059795/credoq12027ex-991.htm：5.25–5.35 億美元 | I51: https://www.itiger.com/news/1122940235：同值
A52: q2_gm | B52: 2Q27 non-GAAP 毛利率指引（中點） | C52: % | D52: 0.67 | E52: 0.68 | F52: 0.69 | G52: Interested-party | H52: https://www.sec.gov/Archives/edgar/data/0001807794/000162828026059795/credoq12027ex-991.htm：67.0–69.0% | I52: GAAP 62.9–64.9%
A53: q2_opx | B53: 2Q27 non-GAAP 營業費用指引（中點） | C53: US$B | D53: 0.1 | E53: 0.1025 | F53: 0.105 | G53: Interested-party | H53: https://www.sec.gov/Archives/edgar/data/0001807794/000162828026059795/credoq12027ex-991.htm：1.00–1.05 億美元 | I53: GAAP 1.99–2.04 億美元
A54: g27 | B54: FY2027 營收年增（公司「逾 85%」；取下緣） | C54: % | D54: 0.85 | E54: 0.85 | F54: 0.95 | G54: Interested-party | H54: https://www.itiger.com/news/1122940235：1Q27 法說：全年年增逾 85%（4Q26 法說時為逾 80%） | I54: https://www.trefis.com/articles/618478/does-the-drop-in-credo-stock-change-anything/2026-10-13：同（逾 85%）
A55: gm_h2 | B55: 2H27 non-GAAP 毛利率 | C55: % | D55: 0.66 | E55: 0.68 | F55: 0.69 | G55: Assumed | H55: 老虎證券新聞（網址見 Sources）：FY2027 non-GAAP 毛利率約與 FY2026 持平（68.1%）（公司） | I55: 光學占比上升可能下壓：未找到量化
A56: g_opx27 | B56: FY2027 non-GAAP 營業費用年增（公司「約 50%」） | C56: % | D56: 0.45 | E56: 0.5 | F56: 0.6 | G56: Interested-party | H56: https://letsdatascience.com/news/credo-raises-guidance-as-optical-ramp-accelerates-30d77185：FY2027 non-GAAP 營業費用年增約 50%（4Q26 法說） | I56: https://www.tikr.com/blog/credo-stock-fell-22-last-week-as-it-launched-a-new-optical-cable-heres-where-it-could-go-by-2031：同（約 50%）
A57: q_oth | B57: 2Q27 起每季其他收益 | C57: US$B | D57: 0.005 | E57: 0.007 | F57: 0.009 | G57: Assumed | H57: 1Q27 0.0081；現金自 14.4 億降至 7.64 億美元（DustPhotonics） | I57: —
A58: tx27 | B58: FY2027 non-GAAP 有效稅率（2Q27 起） | C58: % | D58: 0.01 | E58: 0.015 | F58: 0.04 | G58: Assumed | H58: 1Q27：1 − 236.262 ÷（230.641＋8.140）＝1.05%；FY2026 1.15%（推導） | I58: https://www.sec.gov/Archives/edgar/data/0001807794/000162828026043303/crdo-20260502.htm：開曼群島法定稅率 0；FY2026 GAAP 有效稅率 1%
A59: sh_27 | B59: FY2027 non-GAAP 稀釋股數（全年平均） | C59: 十億股 | D59: 0.198 | E59: 0.199 | F59: 0.201 | G59: Assumed | H59: 1Q27 197.5 百萬股；4Q26→1Q27 季增約 1.6 百萬股（含 DustPhotonics 約 80 萬股） | I59: https://www.sec.gov/Archives/edgar/data/0001807794/000162828026043303/crdo-20260502.htm：DustPhotonics 或有對價最多約 280 萬股
A60: F. FY2025、FY2026 實績（non-GAAP）
A61: a25_rev_in | B61: FY2025 營收 | C61: US$B | E61: 0.436775 | G61: Verified | H61: https://www.sec.gov/Archives/edgar/data/0001807794/000162828026039474/credoq42026ex-991.htm | I61: 10-K FY2026（三年損益表）：營收 436,775 千美元
A62: a25_gp_in | B62: FY2025 non-GAAP 毛利（＝營業利益＋營業費用） | C62: US$B | E62: =0.115352+0.168751 -> 0.284103 | G62: Verified | H62: https://www.sec.gov/Archives/edgar/data/0001807794/000162828026039474/credoq42026ex-991.htm：non-GAAP 毛利率 65.0% | I62: —
A63: a25_opx_in | B63: FY2025 non-GAAP 營業費用 | C63: US$B | E63: 0.168751 | G63: Verified | H63: https://www.sec.gov/Archives/edgar/data/0001807794/000162828026039474/credoq42026ex-991.htm | I63: —
A64: a25_ninc_in | B64: FY2025 其他收益（淨） | C64: US$B | E64: 0.017746 | G64: Verified | H64: https://www.sec.gov/Archives/edgar/data/0001807794/000162828026039474/credoq42026ex-991.htm | I64: —
A65: a25_ni_in | B65: FY2025 non-GAAP 淨利 | C65: US$B | E65: 0.129926 | G65: Verified | H65: https://www.sec.gov/Archives/edgar/data/0001807794/000162828026039474/credoq42026ex-991.htm | I65: https://letsdatascience.com/news/credo-raises-guidance-as-optical-ramp-accelerates-30d77185—
A66: a25_sh_in | B66: FY2025 non-GAAP 稀釋股數 | C66: 十億股 | E66: 0.184644 | G66: Verified | H66: https://www.sec.gov/Archives/edgar/data/0001807794/000162828026039474/credoq42026ex-991.htm | I66: —
A67: a25_eps_in | B67: FY2025 non-GAAP 稀釋 EPS | C67: US$ | E67: 0.7 | G67: Verified | H67: https://www.sec.gov/Archives/edgar/data/0001807794/000162828026039474/credoq42026ex-991.htm：0.70（GAAP 0.29） | I67: —
A68: a26_rev_in | B68: FY2026 營收 | C68: US$B | E68: 1.335116 | G68: Verified | H68: https://www.sec.gov/Archives/edgar/data/0001807794/000162828026039474/credoq42026ex-991.htm | I68: https://www.sec.gov/Archives/edgar/data/0001807794/000162828026043303/crdo-20260502.htm：營收 1,335,116 千美元、GAAP 淨利 472,279
A69: a26_gp_in | B69: FY2026 non-GAAP 毛利（＝營業利益＋營業費用） | C69: US$B | E69: =0.638822+0.270945 -> 0.909767 | G69: Verified | H69: https://www.sec.gov/Archives/edgar/data/0001807794/000162828026039474/credoq42026ex-991.htm：non-GAAP 毛利率 68.1% | I69: —
A70: a26_opx_in | B70: FY2026 non-GAAP 營業費用 | C70: US$B | E70: 0.270945 | G70: Verified | H70: https://www.sec.gov/Archives/edgar/data/0001807794/000162828026039474/credoq42026ex-991.htm | I70: —
A71: a26_ninc_in | B71: FY2026 其他收益（淨） | C71: US$B | E71: 0.03043 | G71: Verified | H71: https://www.sec.gov/Archives/edgar/data/0001807794/000162828026039474/credoq42026ex-991.htm | I71: —
A72: a26_ni_in | B72: FY2026 non-GAAP 淨利 | C72: US$B | E72: 0.661543 | G72: Verified | H72: https://www.sec.gov/Archives/edgar/data/0001807794/000162828026039474/credoq42026ex-991.htm | I72: https://letsdatascience.com/news/credo-raises-guidance-as-optical-ramp-accelerates-30d77185：FY2026 non-GAAP 淨利 6.62 億美元
A73: a26_sh_in | B73: FY2026 non-GAAP 稀釋股數 | C73: 十億股 | E73: 0.191256 | G73: Verified | H73: https://www.sec.gov/Archives/edgar/data/0001807794/000162828026039474/credoq42026ex-991.htm | I73: —
A74: a26_eps_in | B74: FY2026 non-GAAP 稀釋 EPS | C74: US$ | E74: 3.46 | G74: Verified | H74: https://www.sec.gov/Archives/edgar/data/0001807794/000162828026039474/credoq42026ex-991.htm：3.46（GAAP 2.51） | I74: —
A75: G. 營業費用、稅率、股數（FY2028 起）
A76: phi | B76: 營業費用成長對營收成長的彈性 | C76: x | D76: 0.3 | E76: =Q!B28 -> 0.58823529 | F76: 0.9 | G76: Derived | H76: FY2027 錨點營業費用年增 ÷ 營收年增（Q 頁） | I76: FY2026：60.6% ÷ 205.7% ＝ 0.29（推導；費用落後營收）
A77: opx_adj | B77: 營業費用額外占營收比（Sens 用；基準 0） | C77: pt | D77: -0.01 | E77: 0 | F77: 0.02 | G77: Assumed | H77: 無 | I77: Sens 用 +2 個百分點
A78: gm_28 | B78: non-GAAP 毛利率 FY2028 | C78: % | D78: 0.63 | E78: 0.67 | F78: 0.69 | G78: Assumed | H78: FY2025 65.0%、FY2026 68.1%、1Q27 68.0%（公司） | I78: 光學（PIC、ZeroFlap 光學）毛利率可能低於 AEC：未找到量化
A79: gm_29 | B79: non-GAAP 毛利率 FY2029 | C79: % | D79: 0.6 | E79: 0.66 | F79: 0.69 | G79: Assumed | H79: 同上；AEC 競爭者增加時價格下壓 | I79: —
A80: oth_f | B80: 其他收益（每年，FY2028 起） | C80: US$B | D80: 0.02 | E80: 0.03 | F80: 0.06 | G80: Assumed | H80: 現金與短期投資 7.64 億美元 × 約 4% | I80: —
A81: tx_28 | B81: non-GAAP 有效稅率 FY2028 | C81: % | D81: 0.05 | E81: 0.13 | F81: 0.17 | G81: Assumed | H81: 公司 FY2026 10-K（網址見 Sources）：預期 FY2028 起適用 OECD 15% 全球最低稅（公司） | I81: FY2026、1Q27 約 1%；共識是否已含：未找到
A82: tx_29 | B82: non-GAAP 有效稅率 FY2029 | C82: % | D82: 0.05 | E82: 0.14 | F82: 0.17 | G82: Assumed | H82: 同上 | I82: —
A83: sh_g | B83: 股數年變動（FY2028 起） | C83: % | D83: 0.005 | E83: 0.015 | F83: 0.03 | G83: Assumed | H83: FY2025→FY2026 non-GAAP 稀釋股數 +3.6%（含 Amazon 認股權證）；FY2026 股票薪酬 1.83 億美元 | I83: 無買回計畫：未找到
A84: mf | B84: AI 銅纜市場係數（Sens 用；FY2028 起） | C84: x | D84: 0.8 | E84: 1 | F84: 1.2 | G84: Assumed | H84: 網通模型 CY2027 銅 +97%、CY2028 +16%、CY2029 +2.5% | I84: ±20%（銅轉光提前、或 scale-up 銅擴大）
A85: g2n | B85: GAAP EPS ÷ non-GAAP EPS（規則值換算用） | C85: x | D85: 0.56 | E85: 0.7 | F85: 0.75 | G85: Assumed | H85: https://www.sec.gov/Archives/edgar/data/0001807794/000162828026039474/credoq42026ex-991.htm：FY2026 GAAP 2.51 ÷ non-GAAP 3.46 ＝ 0.725；1Q27 0.67 ÷ 1.20 ＝ 0.56（含 DustPhotonics 攤銷與整合費用） | I85: https://www.tikr.com/blog/credo-stock-fell-22-last-week-as-it-launched-a-new-optical-cable-heres-where-it-could-go-by-2031：FY2027 共識 GAAP 約 4.40 ÷ 調整後約 6.30 ＝ 0.70（Interested-party）
A86: H. 共識、市場資料（只作 Recon 對帳，不作校準）
A87: cons_q2 | B87: 共識 2Q27 營收 | C87: US$B | E87: 0.53165 | G87: Interested-party | H87: https://finance.yahoo.com/quote/CRDO/analysis/（17 家，2026-10-01 收盤時） | I87: —
A88: cons_rev27 | B88: 共識 FY2027 營收 | C88: US$B | E88: 2.5 | G88: Interested-party | H88: https://finance.yahoo.com/quote/CRDO/analysis/（19 家；2.47–2.58） | I88: https://stockanalysis.com/stocks/crdo/forecast/：2.5（19 家）
A89: cons_eps27 | B89: 共識 FY2027 non-GAAP EPS | C89: US$ | E89: 6.31 | G89: Interested-party | H89: https://finance.yahoo.com/quote/CRDO/analysis/（20 家；5.98–6.64） | I89: https://stockanalysis.com/stocks/crdo/forecast/：6.31（19 家）
A90: cons_rev28 | B90: 共識 FY2028 營收 | C90: US$B | E90: 3.87 | G90: Interested-party | H90: Yahoo Finance（網址見 Sources）（19 家；3.59–4.41） | I90: 第二來源：未找到（StockAnalysis 需付費）
A91: cons_eps28 | B91: 共識 FY2028 non-GAAP EPS | C91: US$ | E91: 9.69 | G91: Interested-party | H91: Yahoo Finance（網址見 Sources）（20 家；8.69–11.31） | I91: 第二來源：未找到
A92: jef_aec | B92: Jefferies 引述 AEC 營收共識（期間未明示） | C92: US$B | E92: 2.3 | G92: Interested-party | H92: Invezz 轉述 Jefferies（網址見 Sources）：共識 23 億美元、Jefferies 樂觀情境約 30 億美元（2026-04） | I92: 期間：未找到（推測為 CY2027 或 FY2028）
A93: jef_u26 | B93: Jefferies：AEC 市場 2026 年（條） | C93: 百萬條 | E93: 8.6 | G93: Interested-party | H93: https://invezz.com/en-ae/news/2026/04/13/credo-jumps-11percent-as-jefferies-backs-copper-tech-in-ai-boom-debate/ | I93: 樂觀 9.5
A94: jef_u27 | B94: Jefferies：AEC 市場 2027 年（條） | C94: 百萬條 | E94: 12.3 | G94: Interested-party | H94: https://invezz.com/en-ae/news/2026/04/13/credo-jumps-11percent-as-jefferies-backs-copper-tech-in-ai-boom-debate/ | I94: 樂觀 14.6
A95: tp_street | B95: 賣方平均目標價 | C95: US$ | E95: 279.09 | G95: Interested-party | H95: https://stockanalysis.com/stocks/crdo/forecast/（20 家，2026-10-05；185–315） | I95: https://www.tikr.com/blog/credo-stock-fell-22-last-week-as-it-launched-a-new-optical-cable-heres-where-it-could-go-by-2031：約 279
A96: tp_wA | B96: 目標價情境權重 A | C96: % | E96: 0.3 | G96: Assumed | H96: Andy 可改（工作單 2026-10-25 預設 A 0.3／B 0.5／C 0.2） | I96: 三者合計應為 100%（Val 頁第 0 節列示）
A97: tp_wB | B97: 目標價情境權重 B | C97: % | E97: 0.5 | G97: Assumed | H97: Andy 可改 | I97: —
A98: tp_wC | B98: 目標價情境權重 C | C98: % | E98: 0.2 | G98: Assumed | H98: Andy 可改 | I98: —
A99: I. 價格與估值
A100: px | B100: 股價（2026-10-23 收盤） | C100: US$ | E100: 147.29 | G100: Interested-party | H100: https://stockanalysis.com/stocks/crdo/：147.29（前收 162.77；盤後 148.75） | I100: https://companiesmarketcap.com/credo-technology/pe-ratio/：147.29（市值 276.8 億美元）
A101: px_hi | B101: 52 週高點 | C101: US$ | E101: 308.67 | G101: Interested-party | H101: https://stockanalysis.com/stocks/crdo/：52 週區間 86.49–308.67 | I101: https://www.tikr.com/blog/credo-stock-fell-22-last-week-as-it-launched-a-new-optical-cable-heres-where-it-could-go-by-2031：2026-06-22 收盤 302.52
A102: sh_out | B102: 流通股數（2026-10） | C102: 十億股 | E102: 0.18795 | G102: Interested-party | H102: https://stockanalysis.com/stocks/crdo/：187.95 百萬股 | I102: https://www.sec.gov/Archives/edgar/data/0001807794/000162828026043303/crdo-20260502.htm：186,477,898 股（2026-06-08，公司）
A103: K. 目標價（DCF＋Comparable）與收斂法參數（v0.2 新增；黃底，Assumed，Andy 可改）
A104: tp_r | B104: 折現率／要求報酬（DCF） | C104: % | E104: 0.1 | G104: Assumed | H104: Andy 可改（工作單 2026-10-25 預設 10%；各市場同一值） | I104: DCF 與 Sens
A105: tp_g | B105: 長期成長率（DCF 永續；收斂法情境 B 的 FY2032 營收年增） | C105: % | E105: 0.04 | G105: Assumed | H105: Andy 可改（工作單預設 4%） | I105: —
A106: tp_roe | B106: ROE（與 EPS 同口徑：non-GAAP 淨利 ÷ 平均股東權益，近三年平均；DCF 再投資率＝tp_g ÷ tp_roe） | C106: % | E106: 0.2 | G106: Assumed | H106: 本模型沒有股東權益（資產負債表未建），non-GAAP ROE 算不出；依主串規則（2026-10-25）取 0.20 | I106: 參考（不採）：GAAP ROE stockanalysis FY2024 −6.39%、FY2025 8.54%、FY2026 34.41%（與 non-GAAP EPS 口徑不一致）
A107: tp_w_dcf | B107: 目標價中 DCF 的權重；其餘為 Comparable | C107: % | E107: 0.5 | G107: Assumed | H107: Andy 可改（工作單 2026-10-25 11:53 定 DCF／Comparable 各半） | I107: —
A108: fade_gA | B108: 收斂法：情境 A 於 FY2032 的營收年增（＝tp_g＋2pt） | C108: % | E108: =tp_g+0.02 -> 0.06 | G108: Assumed | H108: 工作單 2026-10-25 11:20 收斂法；FY2030 起由 FY2029 年增線性收斂 | I108: FY2030 起為收斂法，非驅動因子推導
A109: fade_gB | B109: 收斂法：情境 B 於 FY2032 的營收年增（＝tp_g） | C109: % | E109: =tp_g -> 0.04 | G109: Assumed | H109: 同上 | I109: —
...

Sheet Q
A1: Q — 實績與 FY2027 錨點（十億美元；EPS 為美元；股數為十億股；non-GAAP）。藍字＝輸入；黑字＝公式。FY2027＝2026-05-03～2027-05-01
A2: FY2027 錨點＝1Q27 實績＋2Q27 指引中點＋2H27（全年營收＝FY2026 ×（1＋85%）減 1H；毛利率 gm_h2；營業費用＝FY2026 ×（1＋50%）減 1H）。產品線拆分（光學、其他 IC 與 IP）為假設，AEC 為殘差。2Q27 財報（約 2026-12 初）公布後以實績取代 2Q
A3: 項目 | B3: FY2025A | C3: FY2026A | D3: 1Q27（實績） | E3: 2Q27（指引） | F3: 2H27（推導） | G3: FY2027 錨點 | H3: 標記 | I3: 說明
A4: 營收 | B4: =a25_rev_in -> 0.436775 | C4: =a26_rev_in -> 1.335116 | D4: =q1_rev -> 0.479003 | E4: =q2_rev -> 0.53 | F4: =G4-D4-E4 -> 1.4609616 | G4: =C4*(1+g27) -> 2.4699646 | H4: Verified／Interested-party（指引） | I4: 2H27＝全年指引 − 1Q27 − 2Q27
A5: 毛利（non-GAAP） | B5: =a25_gp_in -> 0.284103 | C5: =a26_gp_in -> 0.909767 | D5: =q1_gp -> 0.325795 | E5: =E4*q2_gm -> 0.3604 | F5: =F4*gm_h2 -> 0.99345389 | G5: =D5+E5+F5 -> 1.6796489 | H5: Verified／Derived
A6: 毛利率 | B6: =B5/B4 -> 0.65045618 | C6: =C5/C4 -> 0.6814142 | D6: =D5/D4 -> 0.68015232 | E6: =E5/E4 -> 0.68 | F6: =F5/F4 -> 0.68 | G6: =G5/G4 -> 0.68002954 | H6: Derived
A7: 營業費用（non-GAAP） | B7: =a25_opx_in -> 0.168751 | C7: =a26_opx_in -> 0.270945 | D7: =q1_opx -> 0.095154 | E7: =q2_opx -> 0.1025 | F7: =G7-D7-E7 -> 0.2087635 | G7: =C7*(1+g_opx27) -> 0.4064175 | H7: Verified／Interested-party（指引） | I7: 2H27＝全年（年增約 50%）− 1H
A8: 營業費用率 | B8: =B7/B4 -> 0.38635682 | C8: =C7/C4 -> 0.20293742 | D8: =D7/D4 -> 0.19865011 | E8: =E7/E4 -> 0.19339623 | F8: =F7/F4 -> 0.14289458 | G8: =G7/G4 -> 0.16454386 | H8: Derived
A9: 營業利益（non-GAAP） | B9: =B5-B7 -> 0.115352 | C9: =C5-C7 -> 0.638822 | D9: =D5-D7 -> 0.230641 | E9: =E5-E7 -> 0.2579 | F9: =F5-F7 -> 0.78469039 | G9: =G5-G7 -> 1.2732314 | H9: Derived
A10: 其他收益（淨） | B10: =a25_ninc_in -> 0.017746 | C10: =a26_ninc_in -> 0.03043 | D10: =q1_ninc -> 0.00814 | E10: =q_oth -> 0.007 | F10: =2*q_oth -> 0.014 | G10: =D10+E10+F10 -> 0.02914 | H10: Verified／Assumed
A11: 稅前利益 | B11: =B9+B10 -> 0.133098 | C11: =C9+C10 -> 0.669252 | D11: =D9+D10 -> 0.238781 | E11: =E9+E10 -> 0.2649 | F11: =F9+F10 -> 0.79869039 | G11: =G9+G10 -> 1.3023714 | H11: Derived
A12: 所得稅（non-GAAP） | B12: =B11-a25_ni_in -> 0.003172 | C12: =C11-a26_ni_in -> 0.007709 | D12: =D11-q1_ni -> 0.002519 | E12: =E11*tx27 -> 0.0039735 | F12: =F11*tx27 -> 0.011980356 | G12: =D12+E12+F12 -> 0.018472856 | H12: Derived | I12: 實績＝稅前 − 淨利（推導）
A13: 有效稅率 | B13: =B12/B11 -> 0.023832064 | C13: =C12/C11 -> 0.01151883 | D13: =D12/D11 -> 0.010549416 | E13: =E12/E11 -> 0.015 | F13: =F12/F11 -> 0.015 | G13: =G12/G11 -> 0.014184015 | H13: Derived
A14: 淨利（non-GAAP） | B14: =a25_ni_in -> 0.129926 | C14: =a26_ni_in -> 0.661543 | D14: =q1_ni -> 0.236262 | E14: =E11-E12 -> 0.2609265 | F14: =F11-F12 -> 0.78671003 | G14: =D14+E14+F14 -> 1.2838985 | H14: Verified／Derived
A15: 淨利率 | B15: =B14/B4 -> 0.29746666 | C15: =C14/C4 -> 0.49549477 | D15: =D14/D4 -> 0.49323699 | E15: =E14/E4 -> 0.49231415 | F15: =F14/F4 -> 0.53848782 | G15: =G14/G4 -> 0.51980443 | H15: Derived | I15: 公司 FY2027 non-GAAP 淨利率目標約 50%
A16: 稀釋股數（non-GAAP） | B16: =a25_sh_in -> 0.184644 | C16: =a26_sh_in -> 0.191256 | D16: =q1_sh -> 0.197505 | G16: =sh_27 -> 0.199 | H16: Verified／Assumed
A17: EPS（non-GAAP） | B17: =B14/B16 -> 0.70365677 | C17: =C14/C16 -> 3.4589399 | D17: =D14/D16 -> 1.196233 | G17: =G14/G16 -> 6.4517514 | H17: Derived | I17: 公司揭露：FY2025 0.70、FY2026 3.46、1Q27 1.20
A18: 光學營收（光 DSP、矽光 PIC、ZeroFlap 光學） | C18: =opt_26 -> 0.15 | G18: =opt_27 -> 0.6 | H18: Assumed／Interested-party
A19: 其他 IC 與 IP（＝FY2026 營收 × oth_s × 成長） | C19: =C4*oth_s -> 0.09345812 | G19: =C19*(1+g_oth) -> 0.10747684 | H19: Assumed
A20: AEC（＝營收 − 光學 − 其他；殘差） | C20: =C4-C18-C19 -> 1.0916579 | G20: =G4-G18-G19 -> 1.7624878 | H20: Derived
A21: AEC ÷ 營收 | C21: =C20/C4 -> 0.81765021 | G21: =G20/G4 -> 0.71356803 | H21: Derived | I21: 公司：AEC 仍是最大業務；1Q27 營收年增額逾九成來自 AEC
A23: FY2027 錨點的檢查（參考；校準未使用共識）
A24: FY2027 營收 ÷ 共識 − 1 | B24: =G4/cons_rev27-1 -> -0.01201416
A25: FY2027 EPS ÷ 共識 − 1 | B25: =G17/cons_eps27-1 -> 0.022464567
A26: FY2027 營收年增 | B26: =G4/C4-1 -> 0.85
A27: FY2027 營業費用年增 | B27: =G7/C7-1 -> 0.5
A28: 營業費用彈性（營業費用年增 ÷ 營收年增；In 頁 phi 的依據） | B28: =B27/B26 -> 0.58823529
A29: 1Q27 EPS（模型）vs 公司揭露 1.20 | B29: =D17/q1_eps-1 -> -0.003139161
A30: FY2027 AEC 年增 | B30: =G20/C20-1 -> 0.6145056
A31: 2H27 每季平均營收 ÷ 2Q27 − 1 | B31: =F4/2/E4-1 -> 0.37826566
A33: 檢查：分部合計 − 合併營收 | C33: =ROUND(C18+C19+C20-C4,6) -> 0
A34: 分部原則第 3 條（2026-10-28 追加）；分部宣告見 segments.json

Sheet Units
A1: Units — Credo 在 AI 銅纜（AEC）與光學的份額（本專案權威，規則第 13 條）。市場取自 markets/network（加速器顆數 × 每顆內容；日曆年 → 會計年度月數加權）
A3: 項目 | B3: 單位 | C3: FY2027（錨點） | D3: FY2028 | E3: FY2029 | F3: 說明
A4: AI 銅纜市場（情境 A；FY 加權） | B4: US$B | C4: =PL!E63 -> 34.339013 | D4: =PL!F63 -> 53.866613 | E4: =PL!G63 -> 59.962245 | F4: markets/network Mkt 頁「銅」
A5: 其中 scale-out 銅纜（DAC／AEC） | B5: US$B | C5: =w8*mso_26+(1-w8)*mso_27 -> 18.069433 | D5: =w8*mso_27+(1-w8)*mso_28 -> 27.583633 | E5: =w8*mso_28+(1-w8)*mso_29 -> 31.199917 | F5: 其餘為 scale-up 背板與線纜
A6: Credo AEC 營收（情境 A） | B6: US$B | C6: =PL!E67 -> 1.7624878 | D6: =PL!F67 -> 2.7647634 | E6: =PL!G67 -> 2.923747 | F6: FY2027 為錨點殘差
A7: Credo AEC 有效份額（÷ 銅纜市場） | B7: % | C7: =PL!E66 -> 0.051326104 | D7: =PL!F66 -> 0.051326104 | E7: =PL!G66 -> 0.048759799 | F7: FY2027 校準
A8: Credo AEC ÷ scale-out 銅纜 | B8: % | C8: =PL!E67/C5 -> 0.097539736 | D8: =PL!F67/D5 -> 0.10023202 | E8: =PL!G67/E5 -> 0.093710089 | F8: 若 AEC 全在 scale-out
A9: 隱含 AEC 滲透率（＝有效份額 ÷ Credo 占 AEC） | B9: % | C9: =PL!E66/cr_aec_sh -> 0.068434805 | D9: =PL!F66/cr_aec_sh -> 0.068434805 | E9: =PL!G66/cr_aec_sh -> 0.065013065 | F9: Credo 占 AEC 75%（Assumed）
A10: AI 可插拔光模組市場（情境 A；FY 加權） | B10: US$B | C10: =PL!E69 -> 37.68908 | D10: =PL!F69 -> 55.037643 | E10: =PL!G69 -> 62.9726 | F10: markets/network Mkt 頁「其中可插拔」
A11: Credo 光學營收（情境 A） | B11: US$B | C11: =PL!E72 -> 0.6 | D11: =PL!F72 -> 1.0410393 | E11: =PL!G72 -> 1.3400205
A12: Credo 光學有效份額（÷ 可插拔市場） | B12: % | C12: =PL!E72/PL!E69 -> 0.015919731 | D12: =PL!F72/PL!F69 -> 0.018915041 | E12: =PL!G72/PL!G69 -> 0.021279422 | F12: 光 DSP 約占模組成本兩成（次級來源），換算 DSP 份額約為本列 5 倍
A13: Credo 營收 ÷ AI IT 資本支出（FY 加權） | B13: % | C13: =PL!E75/(w8*itc_26+(1-w8)*itc_27) -> 0.0023680623 | D13: =PL!F75/(w8*itc_27+(1-w8)*itc_28) -> 0.0023046503 | E13: =PL!G75/(w8*itc_28+(1-w8)*itc_29) -> 0.0021219924 | F13: markets/network 的 AI IT 資本支出
A15: 讀法：有效份額＝AEC 滲透率 × Credo 占 AEC；兩者都沒有第一手資料，只校準乘積（FY2027 錨點）。AEC 份額相對值、光學份額相對值是 Assumed，是最需要每季檢查的輸入。

Sheet PL
A1: PL — Credo 損益（US$B；non-GAAP）。FY2025A、FY2026A 實績、FY2027 錨點（1Q27 實績＋2Q27 指引＋2H27 依全年指引），FY2028 起為模型。FY(t) 截至 t 年 4 月底／5 月初。三情境各一個完整推導區塊（本頁下方），頂端為摘要。FY2027 三情境相同；FY2028 起光學可插拔市場讀同字母網通 CPO 情境，FY2028 只有 4/12 落在 CY2028，顆數情境 B、C 的差異主要在 FY2029
A2: 灰底＝FY2030–FY2032 收斂法，非驅動因子推導（上游市場層只到 2029）：營收年增由 FY2029 線性收斂到 fade_g（A＝tp_g＋2pt、B＝tp_g、C＝tp_g−2pt），淨利率由 FY2029 線性收斂到 fade_m（In 頁 K 節），FY2032 達到；股數依 sh_g
A3: 情境／項目 | B3: 單位 | C3: FY2025A | D3: FY2026A | E3: FY2027（錨點） | F3: FY2028 | G3: FY2029 | H3: FY2030（收斂） | I3: FY2031（收斂） | J3: FY2032（收斂） | K3: 說明
A4: 情境 A
A5: 營收 | B5: US$B | C5: =C75 -> 0.436775 | D5: =D75 -> 1.335116 | E5: =E75 -> 2.4699646 | F5: =F75 -> 3.9294011 | G5: =G75 -> 4.4059056 | H5: =H75 -> 4.8502161 | I5: =I75 -> 5.2402809 | J5: =J75 -> 5.5546978
A6: 營收年增 | B6: % | D6: =D76 -> 2.0567592 | E6: =E76 -> 0.85 | F6: =F76 -> 0.59087343 | G6: =G76 -> 0.12126646 | H6: =H76 -> 0.1008443 | I6: =I76 -> 0.080422152 | J6: =J76 -> 0.06
A7: AEC 營收 | B7: US$B | D7: =D67 -> 1.0916579 | E7: =E67 -> 1.7624878 | F7: =F67 -> 2.7647634 | G7: =G67 -> 2.923747
A8: 光學營收 | B8: US$B | D8: =D72 -> 0.15 | E8: =E72 -> 0.6 | F8: =F72 -> 1.0410393 | G8: =G72 -> 1.3400205
A9: 其他 IC 與 IP | B9: US$B | D9: =D74 -> 0.09345812 | E9: =E74 -> 0.10747684 | F9: =F74 -> 0.12359836 | G9: =G74 -> 0.14213812
A10: 毛利率 | B10: % | C10: =C80 -> 0.65045618 | D10: =D80 -> 0.6814142 | E10: =E80 -> 0.68002954 | F10: =F80 -> 0.67 | G10: =G80 -> 0.66
A11: 營業利益率 | B11: % | C11: =C85 -> 0.26409936 | D11: =D85 -> 0.47847678 | E11: =E85 -> 0.51548568 | F11: =F85 -> 0.53062072 | G11: =G85 -> 0.52682768
A12: 淨利率 | B12: % | C12: =C89 -> 0.29746666 | D12: =D89 -> 0.49549477 | E12: =E89 -> 0.51980443 | F12: =F89 -> 0.46828226 | G12: =G89 -> 0.45892758 | H12: =H89 -> 0.45892758 | I12: =I89 -> 0.45892758 | J12: =J89 -> 0.45892758
A13: 淨利 | B13: US$B | C13: =C88 -> 0.129926 | D13: =D88 -> 0.661543 | E13: =E88 -> 1.2838985 | F13: =F88 -> 1.8400688 | G13: =G88 -> 2.0219916 | H13: =H88 -> 2.225898 | I13: =I88 -> 2.4049095 | J13: =J88 -> 2.549204
A14: EPS（non-GAAP） | B14: US$ | C14: =C91 -> 0.70365677 | D14: =D91 -> 3.4589399 | E14: =E91 -> 6.4517514 | F14: =F91 -> 9.109928 | G14: =G91 -> 9.8626629 | H14: =H91 -> 10.696804 | I14: =I91 -> 11.38627 | J14: =J91 -> 11.89108
A15: EPS 年增 | B15: % | D15: =D92 -> 3.9156635 | E15: =E92 -> 0.86523955 | F15: =F92 -> 0.41200852 | G15: =G92 -> 0.082627974 | H15: =H92 -> 0.084575669 | I15: =I92 -> 0.064455322 | J15: =J92 -> 0.044334975
A17: 情境 B
A18: 營收 | B18: US$B | C18: =C110 -> 0.436775 | D18: =D110 -> 1.335116 | E18: =E110 -> 2.4699646 | F18: =F110 -> 3.6832605 | G18: =G110 -> 3.7005291 | H18: =H110 -> 3.761436 | I18: =I110 -> 3.8676193 | J18: =J110 -> 4.0223241
A19: 營收年增 | B19: % | D19: =D111 -> 2.0567592 | E19: =E111 -> 0.85 | F19: =F111 -> 0.49121994 | G19: =G111 -> 0.004688423 | H19: =H111 -> 0.016458949 | I19: =I111 -> 0.028229474 | J19: =J111 -> 0.04
A20: AEC 營收 | B20: US$B | D20: =D102 -> 1.0916579 | E20: =E102 -> 1.7624878 | F20: =F102 -> 2.5612807 | G20: =G102 -> 2.3885307
A21: 光學營收 | B21: US$B | D21: =D107 -> 0.15 | E21: =E107 -> 0.6 | F21: =F107 -> 0.9983814 | G21: =G107 -> 1.1698604
A22: 其他 IC 與 IP | B22: US$B | D22: =D109 -> 0.09345812 | E22: =E109 -> 0.10747684 | F22: =F109 -> 0.12359836 | G22: =G109 -> 0.14213812
A23: 毛利率 | B23: % | C23: =C115 -> 0.65045618 | D23: =D115 -> 0.6814142 | E23: =E115 -> 0.68002954 | F23: =F115 -> 0.67 | G23: =G115 -> 0.66
A24: 營業利益率 | B24: % | C24: =C120 -> 0.26409936 | D24: =D120 -> 0.47847678 | E24: =E120 -> 0.51548568 | F24: =F120 -> 0.52777465 | G24: =G120 -> 0.51804794
A25: 淨利率 | B25: % | C25: =C124 -> 0.29746666 | D25: =D124 -> 0.49549477 | E25: =E124 -> 0.51980443 | F25: =F124 -> 0.46625006 | G25: =G124 -> 0.4524932 | H25: =H124 -> 0.43741009 | I25: =I124 -> 0.42232699 | J25: =J124 -> 0.40724388
A26: 淨利 | B26: US$B | C26: =C123 -> 0.129926 | D26: =D123 -> 0.661543 | E26: =E123 -> 1.2838985 | F26: =F123 -> 1.7173204 | G26: =G123 -> 1.6744643 | H26: =H123 -> 1.6452901 | I26: =I123 -> 1.6334 | J26: =J123 -> 1.6380669
A27: EPS（non-GAAP） | B27: US$ | C27: =C126 -> 0.70365677 | D27: =D126 -> 3.4589399 | E27: =E126 -> 6.4517514 | F27: =F126 -> 8.5022175 | G27: =G126 -> 8.1675298 | H27: =H126 -> 7.9066274 | I27: =I126 -> 7.7334861 | J27: =J126 -> 7.6409673
A28: EPS 年增 | B28: % | D28: =D127 -> 3.9156635 | E28: =E127 -> 0.86523955 | F28: =F127 -> 0.31781542 | G28: =G127 -> -0.039364755 | H28: =H127 -> -0.031943858 | I28: =I127 -> -0.021898241 | J28: =J127 -> -0.011963406
A30: 情境 C
A31: 營收 | B31: US$B | C31: =C145 -> 0.436775 | D31: =D145 -> 1.335116 | E31: =E145 -> 2.4699646 | F31: =F145 -> 3.4145724 | G31: =G145 -> 2.7731624 | H31: =H145 -> 2.4443672 | I31: =I145 -> 2.3239048 | J31: =J145 -> 2.3703828
A32: 營收年增 | B32: % | D32: =D146 -> 2.0567592 | E32: =E146 -> 0.85 | F32: =F146 -> 0.38243778 | G32: =G146 -> -0.1878449 | H32: =H146 -> -0.11856327 | I32: =I146 -> -0.049281634 | J32: =J146 -> 0.02
A33: AEC 營收 | B33: US$B | D33: =D137 -> 1.0916579 | E33: =E137 -> 1.7624878 | F33: =F137 -> 2.357798 | G33: =G137 -> 1.7542482
A34: 光學營收 | B34: US$B | D34: =D142 -> 0.15 | E34: =E142 -> 0.6 | F34: =F142 -> 0.93317598 | G34: =G142 -> 0.87677605
A35: 其他 IC 與 IP | B35: US$B | D35: =D144 -> 0.09345812 | E35: =E144 -> 0.10747684 | F35: =F144 -> 0.12359836 | G35: =G144 -> 0.14213812
A36: 毛利率 | B36: % | C36: =C150 -> 0.65045618 | D36: =D150 -> 0.6814142 | E36: =E150 -> 0.68002954 | F36: =F150 -> 0.67 | G36: =G150 -> 0.66
A37: 營業利益率 | B37: % | C37: =C155 -> 0.26409936 | D37: =D155 -> 0.47847678 | E37: =E155 -> 0.51548568 | F37: =F155 -> 0.52419944 | G37: =G155 -> 0.48047695
A38: 淨利率 | B38: % | C38: =C159 -> 0.29746666 | D38: =D159 -> 0.49549477 | E38: =E159 -> 0.51980443 | F38: =F159 -> 0.46369722 | G38: =G159 -> 0.42251364 | H38: =H159 -> 0.39434606 | I38: =I159 -> 0.36617848 | J38: =J159 -> 0.33801091
A39: 淨利 | B39: US$B | C39: =C158 -> 0.129926 | D39: =D158 -> 0.661543 | E39: =E158 -> 1.2838985 | F39: =F158 -> 1.5833277 | G39: =G158 -> 1.1716989 | H39: =H158 -> 0.96392656 | I39: =I158 -> 0.85096392 | J39: =J158 -> 0.80121526
A40: EPS（non-GAAP） | B40: US$ | C40: =C161 -> 0.70365677 | D40: =D161 -> 3.4589399 | E40: =E161 -> 6.4517514 | F40: =F161 -> 7.8388382 | G40: =G161 -> 5.7151925 | H40: =H161 -> 4.632258 | I40: =I161 -> 4.0289688 | J40: =J161 -> 3.7373685
A41: EPS 年增 | B41: % | D41: =D162 -> 3.9156635 | E41: =E162 -> 0.86523955 | F41: =F162 -> 0.21499383 | G41: =G162 -> -0.27091331 | H41: =H162 -> -0.18948347 | I41: =I162 -> -0.13023654 | J41: =J162 -> -0.0723759
A43: 核對（應為 0）：FY2027 模型營收、AEC 營收、淨利 − 錨點（校準恆等式）
A44: 情境 A：營收差（US$B） | E44: =E75-a27_rev -> 0
A45: 情境 A：AEC 營收 − 銅纜市場 × 有效份額（US$B） | E45: =E67-E63*E66 -> 0
A46: 情境 A：（營業利益＋其他收益）×（1 − 稅率）− 淨利錨點 | E46: =(E84+E86)*(1-E87)-a27_ni -> 0
A60: 情境 A：基準（顆數係數 1.0）；網通 CPO 情境 A（替代快）
A61: 項目 | B61: 單位 | C61: FY2025A | D61: FY2026A | E61: FY2027（錨點） | F61: FY2028 | G61: FY2029 | H61: FY2030（收斂） | I61: FY2031（收斂） | J61: FY2032（收斂） | K61: 說明
A62: A. AEC（E 欄＝FY2027 校準年；F–G＝FY2028–FY2029；市場為日曆年月數加權）
A63: AI 銅纜市場（FY 加權）× 情境顆數係數 | B63: US$B | E63: =(w8*mcu_26*1+(1-w8)*mcu_27*1) -> 34.339013 | F63: =(w8*mcu_27*1+(1-w8)*mcu_28*um28_A) -> 53.866613 | G63: =(w8*mcu_28*um28_A+(1-w8)*mcu_29*um29_A) -> 59.962245 | K63: FY(t)＝8/12 × CY(t−1)＋4/12 × CY(t)；CY2028 起乘顆數係數
A64: Credo AEC 有效份額（FY2027 校準）＝ AEC 營收 ÷ 銅纜市場 | B64: % | E64: =a27_aec/E63 -> 0.051326104 | K64: Derived：＝AEC 滲透率 × Credo 占 AEC（拆分見 Units）
A65: AEC 有效份額相對值（÷ FY2027） | B65: x | E65: =1 -> 1 | F65: =rel_a_28 -> 1 | G65: =rel_a_29 -> 0.95
A66: AEC 有效份額 | B66: % | E66: =$E$64*E65 -> 0.051326104 | F66: =$E$64*F65 -> 0.051326104 | G66: =$E$64*G65 -> 0.048759799
A67: AEC 營收 | B67: US$B | D67: =a26_aec -> 1.0916579 | E67: =a27_aec -> 1.7624878 | F67: =F63*F66 -> 2.7647634 | G67: =G63*G66 -> 2.923747
A68: B. 光學（光 DSP、矽光 PIC、ZeroFlap 光學）
A69: AI 可插拔光模組市場（FY 加權）× 情境顆數係數 | B69: US$B | E69: =(w8*mpl_26*1+(1-w8)*mpl_27*1) -> 37.68908 | F69: =(w8*mpl_27*1+(1-w8)*mpl_28*um28_A) -> 55.037643 | G69: =(w8*mpl_28*um28_A+(1-w8)*mpl_29*um29_A) -> 62.9726
A70: Credo 光學有效份額（FY2027 校準）＝ 光學營收 ÷ 可插拔市場 | B70: % | E70: =a27_opt/(w8*mplB_26*1+(1-w8)*mplB_27*1) -> 0.015762535
A71: 光學有效份額相對值（÷ FY2027） | B71: x | E71: =1 -> 1 | F71: =rel_o_28 -> 1.2 | G71: =rel_o_29 -> 1.35
A72: 光學營收 | B72: US$B | D72: =a26_opt -> 0.15 | E72: =a27_opt -> 0.6 | F72: =F69*$E$70*F71 -> 1.0410393 | G72: =G69*$E$70*G71 -> 1.3400205
A73: C. 其他營收與合計
A74: 其他 IC 與 IP（線卡 PHY、重定時器、SerDes 授權） | B74: US$B | D74: =a26_ic -> 0.09345812 | E74: =a27_ic -> 0.10747684 | F74: =E74*(1+g_oth) -> 0.12359836 | G74: =F74*(1+g_oth) -> 0.14213812
A75: 營收 | B75: US$B | C75: =a25_rev -> 0.436775 | D75: =a26_rev -> 1.335116 | E75: =E67+E72+E74 -> 2.4699646 | F75: =F67+F72+F74 -> 3.9294011 | G75: =G67+G72+G74 -> 4.4059056 | H75: =G75*(1+H76) -> 4.8502161 | I75: =H75*(1+I76) -> 5.2402809 | J75: =I75*(1+J76) -> 5.5546978
A76: 營收年增 | B76: % | D76: =D75/C75-1 -> 2.0567592 | E76: =E75/D75-1 -> 0.85 | F76: =F75/E75-1 -> 0.59087343 | G76: =G75/F75-1 -> 0.12126646 | H76: =$G76+(fade_gA-$G76)*1/3 -> 0.1008443 | I76: =$G76+(fade_gA-$G76)*2/3 -> 0.080422152 | J76: =$G76+(fade_gA-$G76)*3/3 -> 0.06
A77: AEC ÷ 營收 | B77: % | D77: =D67/D75 -> 0.81765021 | E77: =E67/E75 -> 0.71356803 | F77: =F67/F75 -> 0.70360937 | G77: =G67/G75 -> 0.66359728
A78: 光學 ÷ 營收 | B78: % | D78: =D72/D75 -> 0.11234979 | E78: =E72/E75 -> 0.24291846 | F78: =F72/F75 -> 0.26493587 | G78: =G72/G75 -> 0.3041419
A79: D. 損益（non-GAAP）
A80: 毛利率 | B80: % | C80: =a25_gp/a25_rev -> 0.65045618 | D80: =a26_gp/a26_rev -> 0.6814142 | E80: =a27_gp/a27_rev -> 0.68002954 | F80: =gm_28 -> 0.67 | G80: =gm_29 -> 0.66 | K80: FY2028 起為輸入路徑（光學占比上升、AEC 競爭）
A81: 毛利 | B81: US$B | C81: =C75*C80 -> 0.284103 | D81: =D75*D80 -> 0.909767 | E81: =E75*E80 -> 1.6796489 | F81: =F75*F80 -> 2.6326987 | G81: =G75*G80 -> 2.9078977
A82: 營業費用（基準路徑） | B82: US$B | C82: =a25_opx -> 0.168751 | D82: =a26_opx -> 0.270945 | E82: =a27_opx -> 0.4064175 | F82: =E82*(1+MAX(0,phi*F76)) -> 0.54767709 | G82: =F82*(1+MAX(0,phi*G76)) -> 0.58674465
A83: 營業費用 | B83: US$B | C83: =C82 -> 0.168751 | D83: =D82 -> 0.270945 | E83: =E82 -> 0.4064175 | F83: =F82+0*F75 -> 0.54767709 | G83: =G82+0*G75 -> 0.58674465
A84: 營業利益 | B84: US$B | C84: =C81-C83 -> 0.115352 | D84: =D81-D83 -> 0.638822 | E84: =E81-E83 -> 1.2732314 | F84: =F81-F83 -> 2.0850216 | G84: =G81-G83 -> 2.321153
A85: 營業利益率 | B85: % | C85: =C84/C75 -> 0.26409936 | D85: =D84/D75 -> 0.47847678 | E85: =E84/E75 -> 0.51548568 | F85: =F84/F75 -> 0.53062072 | G85: =G84/G75 -> 0.52682768
A86: 其他收益（淨） | B86: US$B | C86: =a25_ninc -> 0.017746 | D86: =a26_ninc -> 0.03043 | E86: =a27_ninc -> 0.02914 | F86: =oth_f -> 0.03 | G86: =oth_f -> 0.03
A87: 有效稅率 | B87: % | C87: =a25_tx -> 0.023832064 | D87: =a26_tx -> 0.01151883 | E87: =a27_tx -> 0.014184015 | F87: =tx_28 -> 0.13 | G87: =tx_29 -> 0.14 | K87: FY2028 起 OECD 15% 全球最低稅（10-K）
A88: 淨利 | B88: US$B | C88: =a25_ni -> 0.129926 | D88: =a26_ni -> 0.661543 | E88: =a27_ni -> 1.2838985 | F88: =(F84+F86)*(1-F87) -> 1.8400688 | G88: =(G84+G86)*(1-G87) -> 2.0219916 | H88: =H75*H89 -> 2.225898 | I88: =I75*I89 -> 2.4049095 | J88: =J75*J89 -> 2.549204
A89: 淨利率 | B89: % | C89: =C88/C75 -> 0.29746666 | D89: =D88/D75 -> 0.49549477 | E89: =E88/E75 -> 0.51980443 | F89: =F88/F75 -> 0.46828226 | G89: =G88/G75 -> 0.45892758 | H89: =$G89+(fade_mA-$G89)*1/3 -> 0.45892758 | I89: =$G89+(fade_mA-$G89)*2/3 -> 0.45892758 | J89: =$G89+(fade_mA-$G89)*3/3 -> 0.45892758
A90: 稀釋股數 | B90: 十億股 | C90: =a25_sh -> 0.184644 | D90: =a26_sh -> 0.191256 | E90: =a27_sh -> 0.199 | F90: =E90*(1+sh_g) -> 0.201985 | G90: =F90*(1+sh_g) -> 0.20501478 | H90: =G90*(1+sh_g) -> 0.20809 | I90: =H90*(1+sh_g) -> 0.21121135 | J90: =I90*(1+sh_g) -> 0.21437952
A91: EPS（non-GAAP） | B91: US$ | C91: =C88/C90 -> 0.70365677 | D91: =D88/D90 -> 3.4589399 | E91: =E88/E90 -> 6.4517514 | F91: =F88/F90 -> 9.109928 | G91: =G88/G90 -> 9.8626629 | H91: =H88/H90 -> 10.696804 | I91: =I88/I90 -> 11.38627 | J91: =J88/J90 -> 11.89108
A92: EPS 年增 | B92: % | D92: =D91/C91-1 -> 3.9156635 | E92: =E91/D91-1 -> 0.86523955 | F92: =F91/E91-1 -> 0.41200852 | G92: =G91/F91-1 -> 0.082627974 | H92: =H91/G91-1 -> 0.084575669 | I92: =I91/H91-1 -> 0.064455322 | J92: =J91/I91-1 -> 0.044334975
A95: 情境 B：CY2028 顆數 ×0.8、CY2029 ×0.85；網通 CPO 情境 B
A96: 項目 | B96: 單位 | C96: FY2025A | D96: FY2026A | E96: FY2027（錨點） | F96: FY2028 | G96: FY2029 | H96: FY2030（收斂） | I96: FY2031（收斂） | J96: FY2032（收斂） | K96: 說明
A97: A. AEC（E 欄＝FY2027 校準年；F–G＝FY2028–FY2029；市場為日曆年月數加權）
A98: AI 銅纜市場（FY 加權）× 情境顆數係數 | B98: US$B | E98: =(w8*mcu_26*1+(1-w8)*mcu_27*1) -> 34.339013 | F98: =(w8*mcu_27*1+(1-w8)*mcu_28*um28_B) -> 49.902107 | G98: =(w8*mcu_28*um28_B+(1-w8)*mcu_29*um29_B) -> 48.985655 | K98: FY(t)＝8/12 × CY(t−1)＋4/12 × CY(t)；CY2028 起乘顆數係數
A99: Credo AEC 有效份額（FY2027 校準）＝ AEC 營收 ÷ 銅纜市場 | B99: % | E99: =a27_aec/E98 -> 0.051326104 | K99: Derived：＝AEC 滲透率 × Credo 占 AEC（拆分見 Units）
A100: AEC 有效份額相對值（÷ FY2027） | B100: x | E100: =1 -> 1 | F100: =rel_a_28 -> 1 | G100: =rel_a_29 -> 0.95
A101: AEC 有效份額 | B101: % | E101: =$E$99*E100 -> 0.051326104 | F101: =$E$99*F100 -> 0.051326104 | G101: =$E$99*G100 -> 0.048759799
A102: AEC 營收 | B102: US$B | D102: =a26_aec -> 1.0916579 | E102: =a27_aec -> 1.7624878 | F102: =F98*F101 -> 2.5612807 | G102: =G98*G101 -> 2.3885307
A103: B. 光學（光 DSP、矽光 PIC、ZeroFlap 光學）
A104: AI 可插拔光模組市場（FY 加權）× 情境顆數係數 | B104: US$B | E104: =(w8*mplB_26*1+(1-w8)*mplB_27*1) -> 38.064944 | F104: =(w8*mplB_27*1+(1-w8)*mplB_28*um28_B) -> 52.782406 | G104: =(w8*mplB_28*um28_B+(1-w8)*mplB_29*um29_B) -> 54.976136
A105: Credo 光學有效份額（FY2027 校準）＝ 光學營收 ÷ 可插拔市場 | B105: % | E105: =a27_opt/(w8*mplB_26*1+(1-w8)*mplB_27*1) -> 0.015762535
A106: 光學有效份額相對值（÷ FY2027） | B106: x | E106: =1 -> 1 | F106: =rel_o_28 -> 1.2 | G106: =rel_o_29 -> 1.35
A107: 光學營收 | B107: US$B | D107: =a26_opt -> 0.15 | E107: =a27_opt -> 0.6 | F107: =F104*$E$105*F106 -> 0.9983814 | G107: =G104*$E$105*G106 -> 1.1698604
A108: C. 其他營收與合計
A109: 其他 IC 與 IP（線卡 PHY、重定時器、SerDes 授權） | B109: US$B | D109: =a26_ic -> 0.09345812 | E109: =a27_ic -> 0.10747684 | F109: =E109*(1+g_oth) -> 0.12359836 | G109: =F109*(1+g_oth) -> 0.14213812
A110: 營收 | B110: US$B | C110: =a25_rev -> 0.436775 | D110: =a26_rev -> 1.335116 | E110: =E102+E107+E109 -> 2.4699646 | F110: =F102+F107+F109 -> 3.6832605 | G110: =G102+G107+G109 -> 3.7005291 | H110: =G110*(1+H111) -> 3.761436 | I110: =H110*(1+I111) -> 3.8676193 | J110: =I110*(1+J111) -> 4.0223241
A111: 營收年增 | B111: % | D111: =D110/C110-1 -> 2.0567592 | E111: =E110/D110-1 -> 0.85 | F111: =F110/E110-1 -> 0.49121994 | G111: =G110/F110-1 -> 0.004688423 | H111: =$G111+(fade_gB-$G111)*1/3 -> 0.016458949 | I111: =$G111+(fade_gB-$G111)*2/3 -> 0.028229474 | J111: =$G111+(fade_gB-$G111)*3/3 -> 0.04
A112: AEC ÷ 營收 | B112: % | D112: =D102/D110 -> 0.81765021 | E112: =E102/E110 -> 0.71356803 | F112: =F102/F110 -> 0.69538408 | G112: =G102/G110 -> 0.64545652
A113: 光學 ÷ 營收 | B113: % | D113: =D107/D110 -> 0.11234979 | E113: =E107/E110 -> 0.24291846 | F113: =F107/F110 -> 0.27105914 | G113: =G107/G110 -> 0.31613327
A114: D. 損益（non-GAAP）
A115: 毛利率 | B115: % | C115: =a25_gp/a25_rev -> 0.65045618 | D115: =a26_gp/a26_rev -> 0.6814142 | E115: =a27_gp/a27_rev -> 0.68002954 | F115: =gm_28 -> 0.67 | G115: =gm_29 -> 0.66 | K115: FY2028 起為輸入路徑（光學占比上升、AEC 競爭）
A116: 毛利 | B116: US$B | C116: =C110*C115 -> 0.284103 | D116: =D110*D115 -> 0.909767 | E116: =E110*E115 -> 1.6796489 | F116: =F110*F115 -> 2.4677845 | G116: =G110*G115 -> 2.4423492
A117: 營業費用（基準路徑） | B117: US$B | C117: =a25_opx -> 0.168751 | D117: =a26_opx -> 0.270945 | E117: =a27_opx -> 0.4064175 | F117: =E117*(1+MAX(0,phi*F111)) -> 0.52385302 | G117: =F117*(1+MAX(0,phi*G111)) -> 0.52529775
A118: 營業費用 | B118: US$B | C118: =C117 -> 0.168751 | D118: =D117 -> 0.270945 | E118: =E117 -> 0.4064175 | F118: =F117+0*F110 -> 0.52385302 | G118: =G117+0*G110 -> 0.52529775
...

Sheet Val
A1: Val — P/E 估值（美元）。目標價＝DCF 與 Comparable 加權（第 0 節）；舊法規則值情境加權保留參考；另列「現價 ÷ FY2027、FY2028 EPS（模型，non-GAAP）」、市場隱含 EPS 與十年 P/E 規則值。Credo 2022-01 上市，年底 P/E 只有 2023–2025，且 2023、2024 為虧損（負值，不用）：規則值只有 2025 年一個觀測值
A2: 循環位置：Credo 不是設備股，不套設備市場見頂年；以本模型營收最高的會計年度為見頂年（比照 Arista、中際旭創）。營收到 FY2029 仍在增加時，見頂年未知，判為中段。規則值基準＝2027 年底的近 12 月 GAAP 換算 EPS（≈ ½ FY2027＋½ FY2028，× g2n），與年底 P/E 的計算口徑一致
A4: 0. 目標價
A5: 0.1 DCF（股東權益現金流，FY2027–FY2032 明確期＋FY2032 後永續）
A6: 項目 | B6: A（順利） | C6: B（平平） | D6: C（不如預期） | E6: 說明
A7: 情境 EPS（FY2027–FY2032） | E7: PL 頁各情境；FY2030 起為收斂法（PL 頁灰底）
A8: FY2027 | B8: =PL!E14 -> 6.4517514 | C8: =PL!E27 -> 6.4517514 | D8: =PL!E40 -> 6.4517514
A9: FY2028 | B9: =PL!F14 -> 9.109928 | C9: =PL!F27 -> 8.5022175 | D9: =PL!F40 -> 7.8388382
A10: FY2029 | B10: =PL!G14 -> 9.8626629 | C10: =PL!G27 -> 8.1675298 | D10: =PL!G40 -> 5.7151925
A11: FY2030 | B11: =PL!H14 -> 10.696804 | C11: =PL!H27 -> 7.9066274 | D11: =PL!H40 -> 4.632258
A12: FY2031 | B12: =PL!I14 -> 11.38627 | C12: =PL!I27 -> 7.7334861 | D12: =PL!I40 -> 4.0289688
A13: FY2032 | B13: =PL!J14 -> 11.89108 | C13: =PL!J27 -> 7.6409673 | D13: =PL!J40 -> 3.7373685
A14: 股東現金流＝EPS ×（1 − tp_g ÷ tp_roe）
A15: 再投資率（tp_g ÷ tp_roe，上限 0.8） | B15: =IF(tp_roe<=tp_g,0.8,MIN(tp_g/tp_roe,0.8)) -> 0.2 | E15: ROE＝In 頁 tp_roe；tp_roe ≤ tp_g 時取上限 0.8
A16: FY2027 | B16: =B8*(1-$B$15) -> 5.1614011 | C16: =C8*(1-$B$15) -> 5.1614011 | D16: =D8*(1-$B$15) -> 5.1614011
A17: FY2028 | B17: =B9*(1-$B$15) -> 7.2879424 | C17: =C9*(1-$B$15) -> 6.801774 | D17: =D9*(1-$B$15) -> 6.2710705
A18: FY2029 | B18: =B10*(1-$B$15) -> 7.8901303 | C18: =C10*(1-$B$15) -> 6.5340238 | D18: =D10*(1-$B$15) -> 4.572154
A19: FY2030 | B19: =B11*(1-$B$15) -> 8.5574434 | C19: =C11*(1-$B$15) -> 6.3253019 | D19: =D11*(1-$B$15) -> 3.7058064
A20: FY2031 | B20: =B12*(1-$B$15) -> 9.1090161 | C20: =C12*(1-$B$15) -> 6.1867889 | D20: =D12*(1-$B$15) -> 3.223175
A21: FY2032 | B21: =B13*(1-$B$15) -> 9.5128641 | C21: =C13*(1-$B$15) -> 6.1127738 | D21: =D13*(1-$B$15) -> 2.9898948
A22: DCF 情境每股價值（折現率 tp_r） | B22: =SUMPRODUCT(B16:B21,1/(1+tp_r)^{1;2;3;4;5;6})+B21*(1+tp_g)/(tp_r-tp_g)/(1+tp_r)^6 -> 126.58975 | C22: =SUMPRODUCT(C16:C21,1/(1+tp_r)^{1;2;3;4;5;6})+C21*(1+tp_g)/(tp_r-tp_g)/(1+tp_r)^6 -> 86.643562 | D22: =SUMPRODUCT(D16:D21,1/(1+tp_r)^{1;2;3;4;5;6})+D21*(1+tp_g)/(tp_r-tp_g)/(1+tp_r)^6 -> 48.783957 | E22: Σ 明確期現金流 ÷ (1＋r)^t ＋ 永續價值 ÷ (1＋r)^6；永續價值＝FY2032 現金流 ×(1＋g)÷(r−g)；基準日 2026 年底，t＝1 對 FY2027
A23: DCF 情境價值推到 12 個月後（×(1＋tp_r)） | B23: =B22*(1+tp_r) -> 139.24872 | C23: =C22*(1+tp_r) -> 95.307918 | D23: =D22*(1+tp_r) -> 53.662353
A24: DCF 目標價（情境加權） | B24: =tp_wA*B23+tp_wB*C23+tp_wC*D23 -> 100.16105 | E24: Σ 權重 × 情境價值 ×(1＋r)；權重見 In 頁
A26: 0.2 Comparable（市場主流同業前瞻 P/E）
A27: 同業與前瞻 P/E | B27: 代號 | C27: 前瞻 12 月 P/E | D27: 日期 | E27: 來源 | F27: 標記
A28: Astera Labs | B28: ALAB | C28: 45.77 | D28: 2026-10-23 | E28: stockanalysis forward PE（分析師共識；價格日期如左） | F28: Interested-party
A29: Marvell | B29: MRVL | C29: 40.44 | D29: 2026-10-23 | E29: stockanalysis forward PE（分析師共識；價格日期如左） | F29: Interested-party
A30: Broadcom | B30: AVGO | C30: 18.52 | D30: 2026-10-23 | E30: stockanalysis forward PE（分析師共識；價格日期如左） | F30: Interested-party
A31: MACOM | B31: MTSI | C31: 28.59 | D31: 2026-10-23 | E31: stockanalysis forward PE（分析師共識；價格日期如左） | F31: Interested-party
A33: 同業前瞻 P/E 中位數 | B33: =MEDIAN(C28:C31) -> 34.515 | E33: 美股高速連接晶片同業（Astera Labs、Marvell、Broadcom、MACOM；不放 A 股）
A34: 12 個月後的前瞻 EPS（情境加權） | B34: =tp_wA*(6/12*B9+6/12*B10)+tp_wB*(6/12*C9+6/12*C10)+tp_wC*(6/12*D9+6/12*D10) -> 8.3687285 | E34: 約 2027-10 時的未來 12 月（2027-11～2028-10）≈ 6／12 × FY2028＋6／12 × FY2029（會計年度 4 月底／5 月初結束）
A35: Comparable 目標價 | B35: =B33*B34 -> 288.84666 | E35: 同業中位數 × 前瞻 EPS
A37: 0.3 結論
A38: 項目 | B38: 數值 | E38: 說明
A39: 目標價（DCF 與 Comparable 加權） | B39: =tp_w_dcf*B24+(1-tp_w_dcf)*B35 -> 194.50386 | E39: tp_w_dcf × DCF＋（1 − tp_w_dcf）× Comparable；tp_w_dcf 見 In 頁
A40: Comparable 目標價（市場主流同業法） | B40: =B35 -> 288.84666
A41: 市場共識目標價 | B41: =cons_tp -> 279.09 | E41: In 頁 tp_street：20 家平均 279.09（2026-10-05）；10-23 為 284.05
A42: 上檔空間：加權目標價 | B42: =B39/px-1 -> 0.32055031 | E42: 現價＝In 頁 px
A43: 上檔空間：Comparable 目標價 | B43: =B40/px-1 -> 0.96107451
A44: 與市場共識目標價的差距：EPS 因素 | B44: =B34/cons_feps-1 -> -0.13635413 | E44: 本模型前瞻 EPS ÷ 共識前瞻 EPS − 1；共識前瞻 EPS＝In 頁 cons_feps
A45: 與市場共識目標價的差距：倍數因素 | B45: =(cons_tp/cons_feps)/B33-1 -> -0.16552636 | E45: ="共識目標價隱含 "&TEXT(cons_tp/cons_feps,"0.0")&"x，同業中位數 "&TEXT(B33,"0.0")&"x" -> 共識目標價隱含 28.8x，同業中位數 34.5x
A46: 價格帶（DCF 不如預期～順利） | B46: =TEXT(D23,"#,##0.00")&"～"&TEXT(B23,"#,##0.00") -> 53.66～139.25 | E46: C 情境價值～A 情境價值（推到 12 個月後）
A47: 歷史倍數檢查：現價隱含 P/E 的十年分位（A／B／C） | B47: =IF(px/B9>MAX($B$102:$B$111),1,IF(px/B9<MIN($B$102:$B$111),0,PERCENTRANK($B$102:$B$111,px/B9))) -> 0 | C47: =IF(px/C9>MAX($B$102:$B$111),1,IF(px/C9<MIN($B$102:$B$111),0,PERCENTRANK($B$102:$B$111,px/C9))) -> 0 | D47: =IF(px/D9>MAX($B$102:$B$111),1,IF(px/D9<MIN($B$102:$B$111),0,PERCENTRANK($B$102:$B$111,px/D9))) -> 0 | E47: 現價 ÷ 各情境 FY2028 EPS 在 2016–2025 年底 P/E（第 6 節採用來源）的分位；高於十年最大值＝100%；只作檢查，不進目標價
A48: 目標價方法 | B48: DCF：股東現金流＝EPS（non-GAAP）×（1 − g／ROE），r＝10%、g＝4%、ROE 需與 non-GAAP EPS 同口徑，本模型無股東權益、算不出，取 0.20（Assumed；再投資率 20%），FY2027–32 明確期＋永續，FY2030 起為收斂法。Comparable：美股高速連接晶片同業（Astera Labs、Marvell、Broadcom、MACOM）前瞻 P/E 中位數 × 12 個月後前瞻 EPS（non-GAAP）；Broadcom 規模與業務組合不同，拉低中位數。會計年度 4 月底結束：FY2027 為錨點年（2026-05～2027-04），DCF 的 t＝1 對 FY2027，偏高估。十年 P/E 只有 2025 年一個觀測值（GAAP），分位檢查參考性低。情境對應：顆數情境 A＝順利、B＝平平、C＝不如預期。
A51: 舊法：規則值情境加權（參考）
A52: 項目 | B52: 數值 | E52: 說明
A53: 規則值情境加權價（參考，非目標價） | B53: =tp_wA*F81+tp_wB*F82+tp_wC*F83 -> 619.64894 | E53: 權重 × 各情境隱含價（第 3 節規則值）
A54: 規則值情境加權價 ÷ 現價 − 1（參考） | B54: =B53/px-1 -> 3.2069994 | E54: 現價＝In 頁 px（2026-10-23 收盤）
A55: 情境 A 隱含價（樂觀） | B55: =F81 -> 642.69736 | E55: ="近 12 月 GAAP 換算 EPS "&TEXT(D81,"0.00")&" × "&TEXT(E81,"0.0")&" 倍（第 3 節）" -> 近 12 月 GAAP 換算 EPS 5.45 × 118.0 倍（第 3 節）
A56: 情境 B 隱含價（基準） | B56: =F82 -> 617.59892 | E56: ="近 12 月 GAAP 換算 EPS "&TEXT(D82,"0.00")&" × "&TEXT(E82,"0.0")&" 倍（第 3 節）" -> 近 12 月 GAAP 換算 EPS 5.23 × 118.0 倍（第 3 節）
A57: 情境 C 隱含價（下檔） | B57: =F83 -> 590.20135 | E57: ="近 12 月 GAAP 換算 EPS "&TEXT(D83,"0.00")&" × "&TEXT(E83,"0.0")&" 倍（第 3 節）" -> 近 12 月 GAAP 換算 EPS 5.00 × 118.0 倍（第 3 節）
A58: 情境權重 A／B／C | B58: =tp_wA -> 0.3 | C58: =tp_wB -> 0.5 | D58: =tp_wC -> 0.2 | E58: ="合計 "&TEXT(B58+C58+D58,"0%")&"；In 頁 tp_wA／tp_wB／tp_wC（Assumed，Andy 可改）" -> 合計 100%；In 頁 tp_wA／tp_wB／tp_wC（Assumed，Andy 可改）
A59: 舊法說明 | B59: P/E：各情境 2027 年底近 12 月 GAAP 換算 EPS（≈ ½ FY2027＋½ FY2028 non-GAAP EPS × g2n 0.70）× 十年年底 GAAP P/E 依循環位置取分位（非設備股：以本模型營收最高年判定，三情境皆為中段＝中位數）。Credo 2022 年上市，十年倍數只有 2025 年一個正值（118x，FY2026 營收年增 206% 的高成長期；2023、2024 年虧損為負值不用），偏誤方向為明顯高估；隱含價約為 2027 年底價格、未折現。對照：現價只約 23 倍共識 FY2027 non-GAAP EPS、15 倍 FY2028（第 1 節）
A61: 1. 價格與市場隱含倍數
A62: 項目 | B62: A | C62: B | D62: C | E62: 說明
A63: 現價（2026-10-23 收盤） | B63: =px -> 147.29
A64: 現價 ÷ FY2026 EPS（實績） | B64: =px/PL!D14 -> 42.582411 | C64: =px/PL!D27 -> 42.582411 | D64: =px/PL!D40 -> 42.582411
A65: 現價 ÷ FY2027 EPS（模型） | B65: =px/PL!E14 -> 22.82946 | C65: =px/PL!E27 -> 22.82946 | D65: =px/PL!E40 -> 22.82946 | E65: FY2027 三情境相同（錨點）
A66: 現價 ÷ FY2028 EPS（模型） | B66: =px/PL!F14 -> 16.168075 | C66: =px/PL!F27 -> 17.323716 | D66: =px/PL!F40 -> 18.789774 | E66: FY2028 只有 4/12 落在 CY2028；B、C 的差異主要在 FY2029
A67: 現價 ÷ FY2029 EPS（模型） | B67: =px/PL!G14 -> 14.934101 | C67: =px/PL!G27 -> 18.033604 | D67: =px/PL!G40 -> 25.77166
A68: 現價 ÷ 共識 FY2027 EPS | B68: =px/cons_eps27 -> 23.342314
A69: 現價 ÷ 共識 FY2028 EPS | B69: =px/cons_eps28 -> 15.200206
A70: 現價 ÷ 52 週高點 − 1 | B70: =px/px_hi-1 -> -0.52282373
A71: 現價 ÷ 賣方平均目標價 − 1 | B71: =px/tp_street-1 -> -0.4722491
A73: 2. 循環位置（本模型營收最高年）
A74: 情境 | B74: 營收最高年（FY2026–FY2029） | C74: FY2027 判定 | D74: 規則倍數（P/E） | E74: 見頂年是否未知 | F74: 說明
A75: A | B75: =INDEX({2026,2027,2028,2029},MATCH(MAX(PL!D75:G75),PL!D75:G75,0)) -> 2029 | C75: =IF(B75=2029,"中段",IF(2027<B75,"中段",IF(2027=B75,"見頂","谷底"))) -> 中段 | D75: =IF(C75="見頂",pe_peak,IF(C75="谷底",pe_trough,pe_mid)) -> 118 | E75: =IF(B75=2029,"是：營收到觀測期末仍在增加","否") -> 是：營收到觀測期末仍在增加 | F75: tools/cycle_position.py excel_rule；營收最高年取代設備市場見頂年
A76: B | B76: =INDEX({2026,2027,2028,2029},MATCH(MAX(PL!D110:G110),PL!D110:G110,0)) -> 2029 | C76: =IF(B76=2029,"中段",IF(2027<B76,"中段",IF(2027=B76,"見頂","谷底"))) -> 中段 | D76: =IF(C76="見頂",pe_peak,IF(C76="谷底",pe_trough,pe_mid)) -> 118 | E76: =IF(B76=2029,"是：營收到觀測期末仍在增加","否") -> 是：營收到觀測期末仍在增加 | F76: 同上
A77: C | B77: =INDEX({2026,2027,2028,2029},MATCH(MAX(PL!D145:G145),PL!D145:G145,0)) -> 2028 | C77: =IF(B77=2029,"中段",IF(2027<B77,"中段",IF(2027=B77,"見頂","谷底"))) -> 中段 | D77: =IF(C77="見頂",pe_peak,IF(C77="谷底",pe_trough,pe_mid)) -> 118 | E77: =IF(B77=2029,"是：營收到觀測期末仍在增加","否") -> 否 | F77: 同上
A79: 3. 規則值隱含股價（美元；約 2027 年底，未折現）＝ 2027 年底近 12 月 GAAP 換算 EPS × 規則倍數
A80: 情境 | B80: FY2027 EPS | C80: FY2028 EPS | D80: 2027 年底近 12 月 GAAP 換算 EPS | E80: 規則倍數 | F80: 隱含股價 | G80: 相對現價 | H80: 現價 ÷ FY2027 EPS
A81: A | B81: =PL!E14 -> 6.4517514 | C81: =PL!F14 -> 9.109928 | D81: =(B81+C81)/2*g2n -> 5.4465878 | E81: =D75 -> 118 | F81: =D81*E81 -> 642.69736 | G81: =F81/px-1 -> 3.3634827 | H81: =px/B81 -> 22.82946
A82: B | B82: =PL!E27 -> 6.4517514 | C82: =PL!F27 -> 8.5022175 | D82: =(B82+C82)/2*g2n -> 5.2338891 | E82: =D76 -> 118 | F82: =D82*E82 -> 617.59892 | G82: =F82/px-1 -> 3.1930811 | H82: =px/B82 -> 22.82946
A83: C | B83: =PL!E40 -> 6.4517514 | C83: =PL!F40 -> 7.8388382 | D83: =(B83+C83)/2*g2n -> 5.0017063 | E83: =D77 -> 118 | F83: =D83*E83 -> 590.20135 | G83: =F83/px-1 -> 3.0070701 | H83: =px/B83 -> 22.82946
A84: 近 12 月＝2026-11～2027-10（3Q27–2Q28）≈ ½ FY2027＋½ FY2028；年底 P/E 資料商以近 12 月 GAAP EPS 計算，故以 g2n 換算
A86: 4. 核心問題：市場隱含的 FY2028 EPS（＝現價 ÷ 假設倍數；non-GAAP）與模型的距離
A87: 假設倍數（÷ FY2028 EPS） | B87: 市場隱含 FY2028 EPS | C87: 模型 FY2028 EPS（A） | D87: 隱含 ÷ 模型 A − 1 | E87: 模型 FY2028 EPS（C） | F87: 隱含 ÷ 模型 C − 1
A88: 10 | B88: =px/A88 -> 14.729 | C88: =PL!F14 -> 9.109928 | D88: =B88/C88-1 -> 0.61680751 | E88: =PL!F40 -> 7.8388382 | F88: =B88/E88-1 -> 0.87897743
A89: 15 | B89: =px/A89 -> 9.8193333 | C89: =PL!F14 -> 9.109928 | D89: =B89/C89-1 -> 0.077871673 | E89: =PL!F40 -> 7.8388382 | F89: =B89/E89-1 -> 0.25265162
A90: 20 | B90: =px/A90 -> 7.3645 | C90: =PL!F14 -> 9.109928 | D90: =B90/C90-1 -> -0.19159625 | E90: =PL!F40 -> 7.8388382 | F90: =B90/E90-1 -> -0.060511283
A91: 30 | B91: =px/A91 -> 4.9096667 | C91: =PL!F14 -> 9.109928 | D91: =B91/C91-1 -> -0.46106416 | E91: =PL!F40 -> 7.8388382 | F91: =B91/E91-1 -> -0.37367419
A92: 讀法：以 15 倍計（約等於現價 ÷ 共識 FY2028 EPS），現價隱含的 FY2028 EPS 與模型 A 相近；以 20 倍計約等於情境 C；以 30 倍（高成長股常見）計約為模型 A 的一半，需要 AEC 份額流失、最大客戶流失、銅纜市場 ×0.8 其中兩到三項同時發生（見 Sens）。
A93: 本版未做先驗，無 Andy 合理 P/E 對照。
A97: 6. 十年倍數與規則值（2016–2025 年底；見頂年 25 分位、中段中位數、谷底 75 分位）
A98: 規則（Andy 2026-10-13）：合理倍數＝年底 P/E 依循環位置取分位。Credo 只有 2025 年一個正值（118x，營收年增約兩倍的高成長期），三個分位相同；歷史倍數為 GAAP 落後 P/E，規則值偏高的方向明確。第二來源：未找到（StockAnalysis 只有會計年度末，列為參考）；前瞻 P/E 歷史待 Bloomberg。
A100: P/E：十年歷史倍數
A101: 年底 | B101: companiesmarketcap（年底 P/E） | C101: StockAnalysis（會計年度末 P/E；參考） | D101: 標記／說明
A102: 2016 | D102: companiesmarketcap（年底 P/E）：Interested-party（資料商；只有 2025 年一個正值；2023 −92.7x、2024 −456x 為虧損，不用）；StockAnalysis（會計年度末 P/E；參考）：Interested-party（資料商；2025 列＝FY2025 年底 2025-05-03；FY2026 年底 2026-05-02 72.0x；日期口徑不同，只作參考、不採用）
A103: 2017
A104: 2018
A105: 2019
A106: 2020
A107: 2021
A108: 2022
A109: 2023
A110: 2024
A111: 2025 | B111: 118 | C111: 157.04
A112: 25 分位（各來源） | B112: =PERCENTILE(B102:B111,0.25) -> 118 | C112: =PERCENTILE(C102:C111,0.25) -> 157.04
A113: 中位數（各來源） | B113: =MEDIAN(B102:B111) -> 118 | C113: =MEDIAN(C102:C111) -> 157.04
A114: 75 分位（各來源） | B114: =PERCENTILE(B102:B111,0.75) -> 118 | C114: =PERCENTILE(C102:C111,0.75) -> 157.04
...

Sheet Recon
A1: Recon — 本模型 vs 共識、券商、研調。只作事後對照，不為對上數字而調參數。共識 FY2028 EPS 區間 8.69–11.31
A3: 項目 | B3: 對照值 | C3: 模型 A | D3: 差距 A | E3: 模型 B | F3: 差距 B | G3: 模型 C | H3: 差距 C | I3: 對照來源 | J3: 說明
A4: A. 共識與指引（校準未使用共識）
A5: 2Q27 營收（指引中點）vs 共識 | B5: =cons_q2 -> 0.53165 | C5: =Q!E4 -> 0.53 | D5: =C5/B5-1 -> -0.0031035456 | E5: =Q!E4 -> 0.53 | F5: =E5/B5-1 -> -0.0031035456 | G5: =Q!E4 -> 0.53 | H5: =G5/B5-1 -> -0.0031035456 | I5: Yahoo（17 家） | J5: 指引 5.25–5.35
A6: FY2027 營收 vs 共識 | B6: =cons_rev27 -> 2.5 | C6: =PL!E75 -> 2.4699646 | D6: =C6/B6-1 -> -0.01201416 | E6: =PL!E110 -> 2.4699646 | F6: =E6/B6-1 -> -0.01201416 | G6: =PL!E145 -> 2.4699646 | H6: =G6/B6-1 -> -0.01201416 | I6: Yahoo（19 家；2.47–2.58） | J6: 錨點＝公司「年增逾 85%」下緣
A7: FY2027 EPS vs 共識 | B7: =cons_eps27 -> 6.31 | C7: =PL!E91 -> 6.4517514 | D7: =C7/B7-1 -> 0.022464567 | E7: =PL!E126 -> 6.4517514 | F7: =E7/B7-1 -> 0.022464567 | G7: =PL!E161 -> 6.4517514 | H7: =G7/B7-1 -> 0.022464567 | I7: Yahoo（20 家；5.98–6.64）
A8: FY2027 淨利率 vs 公司目標約 50% | B8: 0.5 | C8: =PL!E89 -> 0.51980443 | D8: =C8-B8 -> 0.019804426 | E8: =PL!E124 -> 0.51980443 | F8: =E8-B8 -> 0.019804426 | G8: =PL!E159 -> 0.51980443 | H8: =G8-B8 -> 0.019804426 | I8: 公司 1Q27 法說
A9: FY2028 營收 vs 共識 | B9: =cons_rev28 -> 3.87 | C9: =PL!F75 -> 3.9294011 | D9: =C9/B9-1 -> 0.01534911 | E9: =PL!F110 -> 3.6832605 | F9: =E9/B9-1 -> -0.048253109 | G9: =PL!F145 -> 3.4145724 | H9: =G9/B9-1 -> -0.11768156 | I9: Yahoo（19 家；3.59–4.41）
A10: FY2028 EPS vs 共識 | B10: =cons_eps28 -> 9.69 | C10: =PL!F91 -> 9.109928 | D10: =C10/B10-1 -> -0.059862952 | E10: =PL!F126 -> 8.5022175 | F10: =E10/B10-1 -> -0.12257817 | G10: =PL!F161 -> 7.8388382 | H10: =G10/B10-1 -> -0.19103837 | I10: Yahoo（20 家；8.69–11.31） | J10: 模型 FY2028 稅率 13%（OECD 最低稅）；共識是否已含：未找到
A11: FY2028 AEC 營收 vs Jefferies 引述共識 | B11: =jef_aec -> 2.3 | C11: =PL!F67 -> 2.7647634 | D11: =C11/B11-1 -> 0.20207104 | E11: =PL!F102 -> 2.5612807 | F11: =E11/B11-1 -> 0.11360031 | G11: =PL!F137 -> 2.357798 | H11: =G11/B11-1 -> 0.025129576 | I11: Jefferies（Invezz 轉述，2026-04） | J11: 共識期間未明示
A12: B. 份額與市場（機制檢查）
A13: FY2027 隱含 AEC 單價（＝AEC 營收 ÷〔Jefferies 條數 × Credo 占 AEC〕；美元／條） | C13: =PL!E67*1000/((w8*jef_u26+(1-w8)*jef_u27)*cr_aec_sh) -> 238.98139 | E13: =PL!E102*1000/((w8*jef_u26+(1-w8)*jef_u27)*cr_aec_sh) -> 238.98139 | G13: =PL!E137*1000/((w8*jef_u26+(1-w8)*jef_u27)*cr_aec_sh) -> 238.98139 | I13: Jefferies 條數（FY 加權） | J13: 800G AEC 單價一般認知為數百美元（第一手：未找到）
A14: FY2027 Credo AEC ÷ scale-out 銅纜（網通模型） | C14: =Units!C8 -> 0.097539736 | E14: =Units!C8 -> 0.097539736 | G14: =Units!C8 -> 0.097539736 | I14: markets/network
A15: FY2028 AEC 有效份額（÷ 銅纜市場） | C15: =PL!F66 -> 0.051326104 | E15: =PL!F101 -> 0.051326104 | G15: =PL!F136 -> 0.051326104 | I15: —
A16: FY2028 Credo 營收 ÷ AI IT 資本支出 | C16: =PL!F75/(w8*itc_27+(1-w8)*itc_28) -> 0.0023046503 | E16: =PL!F110/(w8*itc_27+(1-w8)*itc_28) -> 0.0021602853 | G16: =PL!F145/(w8*itc_27+(1-w8)*itc_28) -> 0.0020026959 | I16: markets/network | J16: 每 1 美元 AI IT 資本支出分到的 Credo 營收
A17: C. 校準
A18: 1Q27 EPS（模型）vs 公司揭露 1.20 | B18: =q1_eps -> 1.2 | C18: =Q!D17 -> 1.196233 | D18: =C18/B18-1 -> -0.003139161 | E18: =Q!D17 -> 1.196233 | F18: =E18/B18-1 -> -0.003139161 | G18: =Q!D17 -> 1.196233 | H18: =G18/B18-1 -> -0.003139161 | I18: 公司 | J18: 淨利 ÷ 稀釋股數
A19: FY2026 EPS（模型）vs 公司揭露 3.46 | B19: =a26_eps_in -> 3.46 | C19: =PL!D91 -> 3.4589399 | D19: =C19/B19-1 -> -0.00030640166 | E19: =PL!D126 -> 3.4589399 | F19: =E19/B19-1 -> -0.00030640166 | G19: =PL!D161 -> 3.4589399 | H19: =G19/B19-1 -> -0.00030640166 | I19: 公司
A20: FY2027 營業費用彈性（Derived） | C20: =Q!B28 -> 0.58823529 | E20: =Q!B28 -> 0.58823529 | G20: =Q!B28 -> 0.58823529 | I20: Q 頁
A21: D. 預留
A22: R4 產業部署路徑（markets/deploy_path/，尚未建立）：上線後以 Credo 營收 ÷ 部署 GW 計算每 GW 營收 | J22: 預留列：本版無數值
A23: 2Q27 財報（約 2026-12 初）：公布後以實績取代 Q 頁 2Q 指引，並更新全年指引 | J23: 預留列：本版無數值

Sheet Sens
A1: Sens — 一次動一個輸入（情境 A；有效份額在每個案例內依 FY2027 錨點重算，FY2027 恆等於錨點）：對 FY2028、FY2029 的營收、AEC 營收、毛利率與 EPS 的影響。每個案例是一個完整推導區塊（本頁下方）
A3: 案例 | B3: 設定 | C3: FY2028 營收 | D3: FY2028 AEC 營收 | E3: FY2028 毛利率 | F3: FY2028 EPS | G3: FY2028 EPS 相對基準 | H3: FY2029 營收 | I3: FY2029 AEC 營收 | J3: FY2029 毛利率 | K3: FY2029 EPS | L3: FY2029 EPS 相對基準
A4: 基準（情境 A） | B4: PL 區塊 A | C4: =PL!F75 -> 3.9294011 | D4: =PL!F67 -> 2.7647634 | E4: =PL!F80 -> 0.67 | F4: =PL!F91 -> 9.109928 | G4: =F4/F$4-1 -> 0 | H4: =PL!G75 -> 4.4059056 | I4: =PL!G67 -> 2.923747 | J4: =PL!G80 -> 0.66 | K4: =PL!G91 -> 9.8626629 | L4: =K4/K$4-1 -> 0
A5: AEC 份額流失（低） | B5: AEC 有效份額相對值 FY2028 0.75、FY2029 0.60（Astera、Marvell、Broadcom 與線纜廠搶份額；或 ALC 自我替代） | C5: =F55 -> 3.2382102 | D5: =F47 -> 2.0735725 | E5: =F60 -> 0.67 | F5: =F71 -> 7.4034076 | G5: =F5/F$4-1 -> -0.18732535 | H5: =G55 -> 3.3287357 | I5: =G47 -> 1.846577 | J5: =G60 -> 0.66 | K5: =G71 -> 7.2917841 | L5: =K5/K$4-1 -> -0.26066782
A6: AEC 份額上升（高） | B6: FY2028 1.15、FY2029 1.20（1.6T 使 DAC 退場，AEC 滲透率上升） | C6: =F90 -> 4.3441156 | D6: =F82 -> 3.1794779 | E6: =F95 -> 0.67 | F6: =F106 -> 10.13384 | G6: =F6/F$4-1 -> 0.11239521 | H6: =G90 -> 5.1753127 | I6: =G82 -> 3.6931541 | J6: =G95 -> 0.66 | K6: =G106 -> 11.710799 | L6: =K6/K$4-1 -> 0.18738708
A7: 最大客戶流失 | B7: FY2028 起 AEC × (1 − 33%)（最大終端客戶轉用其他供應商或光學） | C7: =F125 -> 3.0170291 | D7: =F117 -> 1.8523915 | E7: =F130 -> 0.67 | F7: =F141 -> 6.857321 | G7: =F7/F$4-1 -> -0.24726946 | H7: =G125 -> 3.4410691 | I7: =G117 -> 1.9589105 | J7: =G130 -> 0.66 | K7: =G141 -> 7.5664429 | L7: =K7/K$4-1 -> -0.23281947
A8: 光學份額 低 | B8: 光學有效份額相對值 0.90（設計案延後） | C8: =F160 -> 3.6691412 | D8: =F152 -> 2.7647634 | E8: =F165 -> 0.67 | F8: =F176 -> 8.4673577 | G8: =F8/F$4-1 -> -0.070535167 | H8: =G160 -> 3.9592321 | I8: =G152 -> 2.923747 | J8: =G165 -> 0.66 | K8: =G176 -> 8.7936313 | L8: =K8/K$4-1 -> -0.10839179
A9: 光學份額 高 | B9: FY2028 1.60、FY2029 2.00 | C9: =F195 -> 4.2764142 | D9: =F187 -> 2.7647634 | E9: =F200 -> 0.67 | F9: =F211 -> 9.9666884 | G9: =F9/F$4-1 -> 0.09404689 | H9: =G195 -> 5.0511007 | I9: =G187 -> 2.923747 | J9: =G200 -> 0.66 | K9: =G211 -> 11.412098 | L9: =K9/K$4-1 -> 0.1571011
A10: 毛利率 低（價格戰） | B10: 毛利率 FY2028 63%、FY2029 60% | C10: =F230 -> 3.9294011 | D10: =F222 -> 2.7647634 | E10: =F235 -> 0.63 | F10: =F246 -> 8.4329314 | G10: =F10/F$4-1 -> -0.074314154 | H10: =G230 -> 4.4059056 | I10: =G222 -> 2.923747 | J10: =G235 -> 0.6 | K10: =G246 -> 8.7537441 | L10: =K10/K$4-1 -> -0.11243604
A11: 毛利率 高 | B11: 毛利率 69% | C11: =F265 -> 3.9294011 | D11: =F257 -> 2.7647634 | E11: =F270 -> 0.69 | F11: =F281 -> 9.4484263 | G11: =F11/F$4-1 -> 0.037157077 | H11: =G265 -> 4.4059056 | I11: =G257 -> 2.923747 | J11: =G270 -> 0.69 | K11: =G281 -> 10.417122 | L11: =K11/K$4-1 -> 0.05621802
A12: 稅率 17% | B12: FY2028 起 non-GAAP 稅率 17% | C12: =F300 -> 3.9294011 | D12: =F292 -> 2.7647634 | E12: =F305 -> 0.67 | F12: =F316 -> 8.6910807 | G12: =F12/F$4-1 -> -0.045977011 | H12: =G300 -> 4.4059056 | I12: =G292 -> 2.923747 | J12: =G305 -> 0.66 | K12: =G316 -> 9.5186165 | L12: =K12/K$4-1 -> -0.034883721
A13: 稅率 5% | B13: 全球最低稅延後或抵減 | C13: =F335 -> 3.9294011 | D13: =F327 -> 2.7647634 | E13: =F340 -> 0.67 | F13: =F351 -> 9.9476225 | G13: =F13/F$4-1 -> 0.091954023 | H13: =G335 -> 4.4059056 | I13: =G327 -> 2.923747 | J13: =G340 -> 0.66 | K13: =G351 -> 10.894802 | L13: =K13/K$4-1 -> 0.10465116
A14: AI 銅纜市場 ×0.8 | B14: FY2028 起銅纜市場 ×0.8（銅轉光提前） | C14: =F370 -> 3.3764484 | D14: =F362 -> 2.2118107 | E14: =F375 -> 0.67 | F14: =F386 -> 7.7447117 | G14: =F14/F$4-1 -> -0.14986028 | H14: =G370 -> 3.8211562 | I14: =G362 -> 2.3389976 | J14: =G375 -> 0.66 | K14: =G386 -> 8.4715281 | L14: =K14/K$4-1 -> -0.14105063
A15: AI 銅纜市場 ×1.2 | B15: ×1.2（scale-up 銅擴大） | C15: =F405 -> 4.4823537 | D15: =F397 -> 3.3177161 | E15: =F410 -> 0.67 | F15: =F421 -> 10.475144 | G15: =F15/F$4-1 -> 0.14986028 | H15: =G405 -> 4.990655 | I15: =G397 -> 3.5084964 | J15: =G410 -> 0.66 | K15: =G421 -> 11.252734 | L15: =K15/K$4-1 -> 0.14094276
A16: 營業費用彈性 0.9 | B16: 營業費用隨營收成長較多 | C16: =F440 -> 3.9294011 | D16: =F432 -> 2.7647634 | E16: =F445 -> 0.67 | F16: =F456 -> 8.7874546 | G16: =F16/F$4-1 -> -0.035398022 | H16: =G440 -> 4.4059056 | I16: =G432 -> 2.923747 | J16: =G445 -> 0.66 | K16: =G456 -> 9.4274737 | L16: =K16/K$4-1 -> -0.044124914
A17: 營業費用率 +2pt | B17: 營業費用額外 +2% × 營收 | C17: =F475 -> 3.9294011 | D17: =F467 -> 2.7647634 | E17: =F480 -> 0.67 | F17: =F491 -> 8.7714297 | G17: =F17/F$4-1 -> -0.037157077 | H17: =G475 -> 4.4059056 | I17: =G467 -> 2.923747 | J17: =G480 -> 0.66 | K17: =G491 -> 9.4930233 | L17: =K17/K$4-1 -> -0.03747868
A18: 顆數情境 B | B18: CY2028 ×0.8、CY2029 ×0.85；CPO 情境 B | C18: =PL!F110 -> 3.6832605 | D18: =PL!F102 -> 2.5612807 | E18: =PL!F115 -> 0.67 | F18: =PL!F126 -> 8.5022175 | G18: =F18/F$4-1 -> -0.066708596 | H18: =PL!G110 -> 3.7005291 | I18: =PL!G102 -> 2.3885307 | J18: =PL!G115 -> 0.66 | K18: =PL!G126 -> 8.1675298 | L18: =K18/K$4-1 -> -0.17187378
A19: 顆數情境 C | B19: CY2028–29 ×0.6；CPO 情境 C | C19: =PL!F145 -> 3.4145724 | D19: =PL!F137 -> 2.357798 | E19: =PL!F150 -> 0.67 | F19: =PL!F161 -> 7.8388382 | G19: =F19/F$4-1 -> -0.13952798 | H19: =PL!G145 -> 2.7731624 | I19: =PL!G137 -> 1.7542482 | J19: =PL!G150 -> 0.66 | K19: =PL!G161 -> 5.7151925 | L19: =K19/K$4-1 -> -0.42052237
A21: 讀法：FY2027 為錨點、各案例相同；顆數情境只影響 FY2028 的 4/12（CY2028），差異主要在 FY2029。「AEC 份額流失」「最大客戶流失」「AI 銅纜市場 ×0.8」是 FY2028 EPS 最大的三條不利路徑；FY2028 起稅率 17%（OECD 最低稅）影響較小；顆數情境 C 主要打在 FY2029。光學在 FY2029 前仍小於 AEC。
A23: 目標價參數（只改 DCF 參數與權重；PL 收斂法的 fade_g 不隨 tp_g 變動）
A24: 案例 | B24: 設定 | C24: DCF 目標價 | D24: Comparable 目標價 | E24: 加權目標價 | F24: 相對基準
A25: 基準 | B25: r 10%、g 4%、DCF 權重 0.5 | C25: =(tp_wA*(Val!B8*(1-IF(tp_roe<=tp_g,0.8,MIN(tp_g/tp_roe,0.8)))/(1+tp_r)^1+Val!B9*(1-IF(tp_roe<=tp_g,0.8,MIN(tp_g/tp_roe,0.8)))/(1+tp_r)^2+Val!B10*(1-IF(tp_roe<=tp_g,0.8,MIN(tp_g/tp_roe,0.8)))/(1+tp_r)^3+Val!B11*(1-IF(tp_roe<=tp_g,0.8,MIN(tp_g/tp_roe,0.8)))/(1+tp_r)^4+Val!B12*(1-IF(tp_roe<=tp_g,0.8,MIN(tp_g/tp_roe,0.8)))/(1+tp_r)^5+Val!B13*(1-IF(tp_roe<=tp_g,0.8,MIN(tp_g/tp_roe,0.8)))/(1+tp_r)^6+Val!B13*(1-IF(tp_roe<=tp_g,0.8,MIN(tp_g/tp_roe,0.8)))*(1+tp_g)/(tp_r-tp_g)/(1+tp_r)^6)+tp_wB*(Val!C8*(1-IF(tp_roe<=tp_g,0.8,MIN(tp_g/tp_roe,0.8)))/(1+tp_r)^1+Val!C9*(1-IF(tp_roe<=tp_g,0.8,MIN(tp_g/tp_roe,0.8)))/(1+tp_r)^2+Val!C10*(1-IF(tp_roe<=tp_g,0.8,MIN(tp_g/tp_roe,0.8)))/(1+tp_r)^3+Val!C11*(1-IF(tp_roe<=tp_g,0.8,MIN(tp_g/tp_roe,0.8)))/(1+tp_r)^4+Val!C12*(1-IF(tp_roe<=tp_g,0.8,MIN(tp_g/tp_roe,0.8)))/(1+tp_r)^5+Val!C13*(1-IF(tp_roe<=tp_g,0.8,MIN(tp_g/tp_roe,0.8)))/(1+tp_r)^6+Val!C13*(1-IF(tp_roe<=tp_g,0.8,MIN(tp_g/tp_roe,0.8)))*(1+tp_g)/(tp_r-tp_g)/(1+tp_r)^6)+tp_wC*(Val!D8*(1-IF(tp_roe<=tp_g,0.8,MIN(tp_g/tp_roe,0.8)))/(1+tp_r)^1+Val!D9*(1-IF(tp_roe<=tp_g,0.8,MIN(tp_g/tp_roe,0.8)))/(1+tp_r)^2+Val!D10*(1-IF(tp_roe<=tp_g,0.8,MIN(tp_g/tp_roe,0.8)))/(1+tp_r)^3+Val!D11*(1-IF(tp_roe<=tp_g,0.8,MIN(tp_g/tp_roe,0.8)))/(1+tp_r)^4+Val!D12*(1-IF(tp_roe<=tp_g,0.8,MIN(tp_g/tp_roe,0.8)))/(1+tp_r)^5+Val!D13*(1-IF(tp_roe<=tp_g,0.8,MIN(tp_g/tp_roe,0.8)))/(1+tp_r)^6+Val!D13*(1-IF(tp_roe<=tp_g,0.8,MIN(tp_g/tp_roe,0.8)))*(1+tp_g)/(tp_r-tp_g)/(1+tp_r)^6))*(1+tp_r) -> 100.16105 | D25: =Val!B35 -> 288.84666 | E25: =tp_w_dcf*C25+(1-tp_w_dcf)*D25 -> 194.50386 | F25: =E25/E$25-1 -> 0
A26: 折現率 +1pt | B26: r 11% | C26: =(tp_wA*(Val!B8*(1-IF(tp_roe<=tp_g,0.8,MIN(tp_g/tp_roe,0.8)))/(1+(tp_r+0.01))^1+Val!B9*(1-IF(tp_roe<=tp_g,0.8,MIN(tp_g/tp_roe,0.8)))/(1+(tp_r+0.01))^2+Val!B10*(1-IF(tp_roe<=tp_g,0.8,MIN(tp_g/tp_roe,0.8)))/(1+(tp_r+0.01))^3+Val!B11*(1-IF(tp_roe<=tp_g,0.8,MIN(tp_g/tp_roe,0.8)))/(1+(tp_r+0.01))^4+Val!B12*(1-IF(tp_roe<=tp_g,0.8,MIN(tp_g/tp_roe,0.8)))/(1+(tp_r+0.01))^5+Val!B13*(1-IF(tp_roe<=tp_g,0.8,MIN(tp_g/tp_roe,0.8)))/(1+(tp_r+0.01))^6+Val!B13*(1-IF(tp_roe<=tp_g,0.8,MIN(tp_g/tp_roe,0.8)))*(1+tp_g)/((tp_r+0.01)-tp_g)/(1+(tp_r+0.01))^6)+tp_wB*(Val!C8*(1-IF(tp_roe<=tp_g,0.8,MIN(tp_g/tp_roe,0.8)))/(1+(tp_r+0.01))^1+Val!C9*(1-IF(tp_roe<=tp_g,0.8,MIN(tp_g/tp_roe,0.8)))/(1+(tp_r+0.01))^2+Val!C10*(1-IF(tp_roe<=tp_g,0.8,MIN(tp_g/tp_roe,0.8)))/(1+(tp_r+0.01))^3+Val!C11*(1-IF(tp_roe<=tp_g,0.8,MIN(tp_g/tp_roe,0.8)))/(1+(tp_r+0.01))^4+Val!C12*(1-IF(tp_roe<=tp_g,0.8,MIN(tp_g/tp_roe,0.8)))/(1+(tp_r+0.01))^5+Val!C13*(1-IF(tp_roe<=tp_g,0.8,MIN(tp_g/tp_roe,0.8)))/(1+(tp_r+0.01))^6+Val!C13*(1-IF(tp_roe<=tp_g,0.8,MIN(tp_g/tp_roe,0.8)))*(1+tp_g)/((tp_r+0.01)-tp_g)/(1+(tp_r+0.01))^6)+tp_wC*(Val!D8*(1-IF(tp_roe<=tp_g,0.8,MIN(tp_g/tp_roe,0.8)))/(1+(tp_r+0.01))^1+Val!D9*(1-IF(tp_roe<=tp_g,0.8,MIN(tp_g/tp_roe,0.8)))/(1+(tp_r+0.01))^2+Val!D10*(1-IF(tp_roe<=tp_g,0.8,MIN(tp_g/tp_roe,0.8)))/(1+(tp_r+0.01))^3+Val!D11*(1-IF(tp_roe<=tp_g,0.8,MIN(tp_g/tp_roe,0.8)))/(1+(tp_r+0.01))^4+Val!D12*(1-IF(tp_roe<=tp_g,0.8,MIN(tp_g/tp_roe,0.8)))/(1+(tp_r+0.01))^5+Val!D13*(1-IF(tp_roe<=tp_g,0.8,MIN(tp_g/tp_roe,0.8)))/(1+(tp_r+0.01))^6+Val!D13*(1-IF(tp_roe<=tp_g,0.8,MIN(tp_g/tp_roe,0.8)))*(1+tp_g)/((tp_r+0.01)-tp_g)/(1+(tp_r+0.01))^6))*(1+(tp_r+0.01)) -> 86.879119 | D26: =Val!B35 -> 288.84666 | E26: =tp_w_dcf*C26+(1-tp_w_dcf)*D26 -> 187.86289 | F26: =E26/E$25-1 -> -0.034143097
A27: 折現率 −1pt | B27: r 9% | C27: =(tp_wA*(Val!B8*(1-IF(tp_roe<=tp_g,0.8,MIN(tp_g/tp_roe,0.8)))/(1+(tp_r-0.01))^1+Val!B9*(1-IF(tp_roe<=tp_g,0.8,MIN(tp_g/tp_roe,0.8)))/(1+(tp_r-0.01))^2+Val!B10*(1-IF(tp_roe<=tp_g,0.8,MIN(tp_g/tp_roe,0.8)))/(1+(tp_r-0.01))^3+Val!B11*(1-IF(tp_roe<=tp_g,0.8,MIN(tp_g/tp_roe,0.8)))/(1+(tp_r-0.01))^4+Val!B12*(1-IF(tp_roe<=tp_g,0.8,MIN(tp_g/tp_roe,0.8)))/(1+(tp_r-0.01))^5+Val!B13*(1-IF(tp_roe<=tp_g,0.8,MIN(tp_g/tp_roe,0.8)))/(1+(tp_r-0.01))^6+Val!B13*(1-IF(tp_roe<=tp_g,0.8,MIN(tp_g/tp_roe,0.8)))*(1+tp_g)/((tp_r-0.01)-tp_g)/(1+(tp_r-0.01))^6)+tp_wB*(Val!C8*(1-IF(tp_roe<=tp_g,0.8,MIN(tp_g/tp_roe,0.8)))/(1+(tp_r-0.01))^1+Val!C9*(1-IF(tp_roe<=tp_g,0.8,MIN(tp_g/tp_roe,0.8)))/(1+(tp_r-0.01))^2+Val!C10*(1-IF(tp_roe<=tp_g,0.8,MIN(tp_g/tp_roe,0.8)))/(1+(tp_r-0.01))^3+Val!C11*(1-IF(tp_roe<=tp_g,0.8,MIN(tp_g/tp_roe,0.8)))/(1+(tp_r-0.01))^4+Val!C12*(1-IF(tp_roe<=tp_g,0.8,MIN(tp_g/tp_roe,0.8)))/(1+(tp_r-0.01))^5+Val!C13*(1-IF(tp_roe<=tp_g,0.8,MIN(tp_g/tp_roe,0.8)))/(1+(tp_r-0.01))^6+Val!C13*(1-IF(tp_roe<=tp_g,0.8,MIN(tp_g/tp_roe,0.8)))*(1+tp_g)/((tp_r-0.01)-tp_g)/(1+(tp_r-0.01))^6)+tp_wC*(Val!D8*(1-IF(tp_roe<=tp_g,0.8,MIN(tp_g/tp_roe,0.8)))/(1+(tp_r-0.01))^1+Val!D9*(1-IF(tp_roe<=tp_g,0.8,MIN(tp_g/tp_roe,0.8)))/(1+(tp_r-0.01))^2+Val!D10*(1-IF(tp_roe<=tp_g,0.8,MIN(tp_g/tp_roe,0.8)))/(1+(tp_r-0.01))^3+Val!D11*(1-IF(tp_roe<=tp_g,0.8,MIN(tp_g/tp_roe,0.8)))/(1+(tp_r-0.01))^4+Val!D12*(1-IF(tp_roe<=tp_g,0.8,MIN(tp_g/tp_roe,0.8)))/(1+(tp_r-0.01))^5+Val!D13*(1-IF(tp_roe<=tp_g,0.8,MIN(tp_g/tp_roe,0.8)))/(1+(tp_r-0.01))^6+Val!D13*(1-IF(tp_roe<=tp_g,0.8,MIN(tp_g/tp_roe,0.8)))*(1+tp_g)/((tp_r-0.01)-tp_g)/(1+(tp_r-0.01))^6))*(1+(tp_r-0.01)) -> 118.7424 | D27: =Val!B35 -> 288.84666 | E27: =tp_w_dcf*C27+(1-tp_w_dcf)*D27 -> 203.79453 | F27: =E27/E$25-1 -> 0.047766025
A28: 長期成長 +1pt | B28: g 5% | C28: =(tp_wA*(Val!B8*(1-IF(tp_roe<=(tp_g+0.01),0.8,MIN((tp_g+0.01)/tp_roe,0.8)))/(1+tp_r)^1+Val!B9*(1-IF(tp_roe<=(tp_g+0.01),0.8,MIN((tp_g+0.01)/tp_roe,0.8)))/(1+tp_r)^2+Val!B10*(1-IF(tp_roe<=(tp_g+0.01),0.8,MIN((tp_g+0.01)/tp_roe,0.8)))/(1+tp_r)^3+Val!B11*(1-IF(tp_roe<=(tp_g+0.01),0.8,MIN((tp_g+0.01)/tp_roe,0.8)))/(1+tp_r)^4+Val!B12*(1-IF(tp_roe<=(tp_g+0.01),0.8,MIN((tp_g+0.01)/tp_roe,0.8)))/(1+tp_r)^5+Val!B13*(1-IF(tp_roe<=(tp_g+0.01),0.8,MIN((tp_g+0.01)/tp_roe,0.8)))/(1+tp_r)^6+Val!B13*(1-IF(tp_roe<=(tp_g+0.01),0.8,MIN((tp_g+0.01)/tp_roe,0.8)))*(1+(tp_g+0.01))/(tp_r-(tp_g+0.01))/(1+tp_r)^6)+tp_wB*(Val!C8*(1-IF(tp_roe<=(tp_g+0.01),0.8,MIN((tp_g+0.01)/tp_roe,0.8)))/(1+tp_r)^1+Val!C9*(1-IF(tp_roe<=(tp_g+0.01),0.8,MIN((tp_g+0.01)/tp_roe,0.8)))/(1+tp_r)^2+Val!C10*(1-IF(tp_roe<=(tp_g+0.01),0.8,MIN((tp_g+0.01)/tp_roe,0.8)))/(1+tp_r)^3+Val!C11*(1-IF(tp_roe<=(tp_g+0.01),0.8,MIN((tp_g+0.01)/tp_roe,0.8)))/(1+tp_r)^4+Val!C12*(1-IF(tp_roe<=(tp_g+0.01),0.8,MIN((tp_g+0.01)/tp_roe,0.8)))/(1+tp_r)^5+Val!C13*(1-IF(tp_roe<=(tp_g+0.01),0.8,MIN((tp_g+0.01)/tp_roe,0.8)))/(1+tp_r)^6+Val!C13*(1-IF(tp_roe<=(tp_g+0.01),0.8,MIN((tp_g+0.01)/tp_roe,0.8)))*(1+(tp_g+0.01))/(tp_r-(tp_g+0.01))/(1+tp_r)^6)+tp_wC*(Val!D8*(1-IF(tp_roe<=(tp_g+0.01),0.8,MIN((tp_g+0.01)/tp_roe,0.8)))/(1+tp_r)^1+Val!D9*(1-IF(tp_roe<=(tp_g+0.01),0.8,MIN((tp_g+0.01)/tp_roe,0.8)))/(1+tp_r)^2+Val!D10*(1-IF(tp_roe<=(tp_g+0.01),0.8,MIN((tp_g+0.01)/tp_roe,0.8)))/(1+tp_r)^3+Val!D11*(1-IF(tp_roe<=(tp_g+0.01),0.8,MIN((tp_g+0.01)/tp_roe,0.8)))/(1+tp_r)^4+Val!D12*(1-IF(tp_roe<=(tp_g+0.01),0.8,MIN((tp_g+0.01)/tp_roe,0.8)))/(1+tp_r)^5+Val!D13*(1-IF(tp_roe<=(tp_g+0.01),0.8,MIN((tp_g+0.01)/tp_roe,0.8)))/(1+tp_r)^6+Val!D13*(1-IF(tp_roe<=(tp_g+0.01),0.8,MIN((tp_g+0.01)/tp_roe,0.8)))*(1+(tp_g+0.01))/(tp_r-(tp_g+0.01))/(1+tp_r)^6))*(1+tp_r) -> 107.79225 | D28: =Val!B35 -> 288.84666 | E28: =tp_w_dcf*C28+(1-tp_w_dcf)*D28 -> 198.31946 | F28: =E28/E$25-1 -> 0.019617095
A29: 長期成長 −1pt | B29: g 3% | C29: =(tp_wA*(Val!B8*(1-IF(tp_roe<=(tp_g-0.01),0.8,MIN((tp_g-0.01)/tp_roe,0.8)))/(1+tp_r)^1+Val!B9*(1-IF(tp_roe<=(tp_g-0.01),0.8,MIN((tp_g-0.01)/tp_roe,0.8)))/(1+tp_r)^2+Val!B10*(1-IF(tp_roe<=(tp_g-0.01),0.8,MIN((tp_g-0.01)/tp_roe,0.8)))/(1+tp_r)^3+Val!B11*(1-IF(tp_roe<=(tp_g-0.01),0.8,MIN((tp_g-0.01)/tp_roe,0.8)))/(1+tp_r)^4+Val!B12*(1-IF(tp_roe<=(tp_g-0.01),0.8,MIN((tp_g-0.01)/tp_roe,0.8)))/(1+tp_r)^5+Val!B13*(1-IF(tp_roe<=(tp_g-0.01),0.8,MIN((tp_g-0.01)/tp_roe,0.8)))/(1+tp_r)^6+Val!B13*(1-IF(tp_roe<=(tp_g-0.01),0.8,MIN((tp_g-0.01)/tp_roe,0.8)))*(1+(tp_g-0.01))/(tp_r-(tp_g-0.01))/(1+tp_r)^6)+tp_wB*(Val!C8*(1-IF(tp_roe<=(tp_g-0.01),0.8,MIN((tp_g-0.01)/tp_roe,0.8)))/(1+tp_r)^1+Val!C9*(1-IF(tp_roe<=(tp_g-0.01),0.8,MIN((tp_g-0.01)/tp_roe,0.8)))/(1+tp_r)^2+Val!C10*(1-IF(tp_roe<=(tp_g-0.01),0.8,MIN((tp_g-0.01)/tp_roe,0.8)))/(1+tp_r)^3+Val!C11*(1-IF(tp_roe<=(tp_g-0.01),0.8,MIN((tp_g-0.01)/tp_roe,0.8)))/(1+tp_r)^4+Val!C12*(1-IF(tp_roe<=(tp_g-0.01),0.8,MIN((tp_g-0.01)/tp_roe,0.8)))/(1+tp_r)^5+Val!C13*(1-IF(tp_roe<=(tp_g-0.01),0.8,MIN((tp_g-0.01)/tp_roe,0.8)))/(1+tp_r)^6+Val!C13*(1-IF(tp_roe<=(tp_g-0.01),0.8,MIN((tp_g-0.01)/tp_roe,0.8)))*(1+(tp_g-0.01))/(tp_r-(tp_g-0.01))/(1+tp_r)^6)+tp_wC*(Val!D8*(1-IF(tp_roe<=(tp_g-0.01),0.8,MIN((tp_g-0.01)/tp_roe,0.8)))/(1+tp_r)^1+Val!D9*(1-IF(tp_roe<=(tp_g-0.01),0.8,MIN((tp_g-0.01)/tp_roe,0.8)))/(1+tp_r)^2+Val!D10*(1-IF(tp_roe<=(tp_g-0.01),0.8,MIN((tp_g-0.01)/tp_roe,0.8)))/(1+tp_r)^3+Val!D11*(1-IF(tp_roe<=(tp_g-0.01),0.8,MIN((tp_g-0.01)/tp_roe,0.8)))/(1+tp_r)^4+Val!D12*(1-IF(tp_roe<=(tp_g-0.01),0.8,MIN((tp_g-0.01)/tp_roe,0.8)))/(1+tp_r)^5+Val!D13*(1-IF(tp_roe<=(tp_g-0.01),0.8,MIN((tp_g-0.01)/tp_roe,0.8)))/(1+tp_r)^6+Val!D13*(1-IF(tp_roe<=(tp_g-0.01),0.8,MIN((tp_g-0.01)/tp_roe,0.8)))*(1+(tp_g-0.01))/(tp_r-(tp_g-0.01))/(1+tp_r)^6))*(1+tp_r) -> 95.175801 | D29: =Val!B35 -> 288.84666 | E29: =tp_w_dcf*C29+(1-tp_w_dcf)*D29 -> 192.01123 | F29: =E29/E$25-1 -> -0.012815288
A30: DCF 權重 0.3 | B30: Comparable 0.7 | C30: =(tp_wA*(Val!B8*(1-IF(tp_roe<=tp_g,0.8,MIN(tp_g/tp_roe,0.8)))/(1+tp_r)^1+Val!B9*(1-IF(tp_roe<=tp_g,0.8,MIN(tp_g/tp_roe,0.8)))/(1+tp_r)^2+Val!B10*(1-IF(tp_roe<=tp_g,0.8,MIN(tp_g/tp_roe,0.8)))/(1+tp_r)^3+Val!B11*(1-IF(tp_roe<=tp_g,0.8,MIN(tp_g/tp_roe,0.8)))/(1+tp_r)^4+Val!B12*(1-IF(tp_roe<=tp_g,0.8,MIN(tp_g/tp_roe,0.8)))/(1+tp_r)^5+Val!B13*(1-IF(tp_roe<=tp_g,0.8,MIN(tp_g/tp_roe,0.8)))/(1+tp_r)^6+Val!B13*(1-IF(tp_roe<=tp_g,0.8,MIN(tp_g/tp_roe,0.8)))*(1+tp_g)/(tp_r-tp_g)/(1+tp_r)^6)+tp_wB*(Val!C8*(1-IF(tp_roe<=tp_g,0.8,MIN(tp_g/tp_roe,0.8)))/(1+tp_r)^1+Val!C9*(1-IF(tp_roe<=tp_g,0.8,MIN(tp_g/tp_roe,0.8)))/(1+tp_r)^2+Val!C10*(1-IF(tp_roe<=tp_g,0.8,MIN(tp_g/tp_roe,0.8)))/(1+tp_r)^3+Val!C11*(1-IF(tp_roe<=tp_g,0.8,MIN(tp_g/tp_roe,0.8)))/(1+tp_r)^4+Val!C12*(1-IF(tp_roe<=tp_g,0.8,MIN(tp_g/tp_roe,0.8)))/(1+tp_r)^5+Val!C13*(1-IF(tp_roe<=tp_g,0.8,MIN(tp_g/tp_roe,0.8)))/(1+tp_r)^6+Val!C13*(1-IF(tp_roe<=tp_g,0.8,MIN(tp_g/tp_roe,0.8)))*(1+tp_g)/(tp_r-tp_g)/(1+tp_r)^6)+tp_wC*(Val!D8*(1-IF(tp_roe<=tp_g,0.8,MIN(tp_g/tp_roe,0.8)))/(1+tp_r)^1+Val!D9*(1-IF(tp_roe<=tp_g,0.8,MIN(tp_g/tp_roe,0.8)))/(1+tp_r)^2+Val!D10*(1-IF(tp_roe<=tp_g,0.8,MIN(tp_g/tp_roe,0.8)))/(1+tp_r)^3+Val!D11*(1-IF(tp_roe<=tp_g,0.8,MIN(tp_g/tp_roe,0.8)))/(1+tp_r)^4+Val!D12*(1-IF(tp_roe<=tp_g,0.8,MIN(tp_g/tp_roe,0.8)))/(1+tp_r)^5+Val!D13*(1-IF(tp_roe<=tp_g,0.8,MIN(tp_g/tp_roe,0.8)))/(1+tp_r)^6+Val!D13*(1-IF(tp_roe<=tp_g,0.8,MIN(tp_g/tp_roe,0.8)))*(1+tp_g)/(tp_r-tp_g)/(1+tp_r)^6))*(1+tp_r) -> 100.16105 | D30: =Val!B35 -> 288.84666 | E30: =0.3*C30+(1-0.3)*D30 -> 232.24098 | F30: =E30/E$25-1 -> 0.19401736
A31: DCF 權重 0.7 | B31: Comparable 0.3 | C31: =(tp_wA*(Val!B8*(1-IF(tp_roe<=tp_g,0.8,MIN(tp_g/tp_roe,0.8)))/(1+tp_r)^1+Val!B9*(1-IF(tp_roe<=tp_g,0.8,MIN(tp_g/tp_roe,0.8)))/(1+tp_r)^2+Val!B10*(1-IF(tp_roe<=tp_g,0.8,MIN(tp_g/tp_roe,0.8)))/(1+tp_r)^3+Val!B11*(1-IF(tp_roe<=tp_g,0.8,MIN(tp_g/tp_roe,0.8)))/(1+tp_r)^4+Val!B12*(1-IF(tp_roe<=tp_g,0.8,MIN(tp_g/tp_roe,0.8)))/(1+tp_r)^5+Val!B13*(1-IF(tp_roe<=tp_g,0.8,MIN(tp_g/tp_roe,0.8)))/(1+tp_r)^6+Val!B13*(1-IF(tp_roe<=tp_g,0.8,MIN(tp_g/tp_roe,0.8)))*(1+tp_g)/(tp_r-tp_g)/(1+tp_r)^6)+tp_wB*(Val!C8*(1-IF(tp_roe<=tp_g,0.8,MIN(tp_g/tp_roe,0.8)))/(1+tp_r)^1+Val!C9*(1-IF(tp_roe<=tp_g,0.8,MIN(tp_g/tp_roe,0.8)))/(1+tp_r)^2+Val!C10*(1-IF(tp_roe<=tp_g,0.8,MIN(tp_g/tp_roe,0.8)))/(1+tp_r)^3+Val!C11*(1-IF(tp_roe<=tp_g,0.8,MIN(tp_g/tp_roe,0.8)))/(1+tp_r)^4+Val!C12*(1-IF(tp_roe<=tp_g,0.8,MIN(tp_g/tp_roe,0.8)))/(1+tp_r)^5+Val!C13*(1-IF(tp_roe<=tp_g,0.8,MIN(tp_g/tp_roe,0.8)))/(1+tp_r)^6+Val!C13*(1-IF(tp_roe<=tp_g,0.8,MIN(tp_g/tp_roe,0.8)))*(1+tp_g)/(tp_r-tp_g)/(1+tp_r)^6)+tp_wC*(Val!D8*(1-IF(tp_roe<=tp_g,0.8,MIN(tp_g/tp_roe,0.8)))/(1+tp_r)^1+Val!D9*(1-IF(tp_roe<=tp_g,0.8,MIN(tp_g/tp_roe,0.8)))/(1+tp_r)^2+Val!D10*(1-IF(tp_roe<=tp_g,0.8,MIN(tp_g/tp_roe,0.8)))/(1+tp_r)^3+Val!D11*(1-IF(tp_roe<=tp_g,0.8,MIN(tp_g/tp_roe,0.8)))/(1+tp_r)^4+Val!D12*(1-IF(tp_roe<=tp_g,0.8,MIN(tp_g/tp_roe,0.8)))/(1+tp_r)^5+Val!D13*(1-IF(tp_roe<=tp_g,0.8,MIN(tp_g/tp_roe,0.8)))/(1+tp_r)^6+Val!D13*(1-IF(tp_roe<=tp_g,0.8,MIN(tp_g/tp_roe,0.8)))*(1+tp_g)/(tp_r-tp_g)/(1+tp_r)^6))*(1+tp_r) -> 100.16105 | D31: =Val!B35 -> 288.84666 | E31: =0.7*C31+(1-0.7)*D31 -> 156.76673 | F31: =E31/E$25-1 -> -0.19401736
A40: 案例區塊：AEC 份額流失（低）（情境 A）
A41: 項目 | B41: 單位 | C41: FY2025A | D41: FY2026A | E41: FY2027（錨點） | F41: FY2028 | G41: FY2029 | H41: 說明
A42: A. AEC（E 欄＝FY2027 校準年；F–G＝FY2028–FY2029；市場為日曆年月數加權）
A43: AI 銅纜市場（FY 加權）× 情境顆數係數 | B43: US$B | E43: =(w8*mcu_26*1+(1-w8)*mcu_27*1) -> 34.339013 | F43: =(w8*mcu_27*1+(1-w8)*mcu_28*um28_A) -> 53.866613 | G43: =(w8*mcu_28*um28_A+(1-w8)*mcu_29*um29_A) -> 59.962245 | H43: FY(t)＝8/12 × CY(t−1)＋4/12 × CY(t)；CY2028 起乘顆數係數
A44: Credo AEC 有效份額（FY2027 校準）＝ AEC 營收 ÷ 銅纜市場 | B44: % | E44: =a27_aec/E43 -> 0.051326104 | H44: Derived：＝AEC 滲透率 × Credo 占 AEC（拆分見 Units）
A45: AEC 有效份額相對值（÷ FY2027） | B45: x | E45: =1 -> 1 | F45: =RLO_28 -> 0.75 | G45: =RLO_29 -> 0.6
A46: AEC 有效份額 | B46: % | E46: =$E$44*E45 -> 0.051326104 | F46: =$E$44*F45 -> 0.038494578 | G46: =$E$44*G45 -> 0.030795662
A47: AEC 營收 | B47: US$B | D47: =a26_aec -> 1.0916579 | E47: =a27_aec -> 1.7624878 | F47: =F43*F46 -> 2.0735725 | G47: =G43*G46 -> 1.846577
A48: B. 光學（光 DSP、矽光 PIC、ZeroFlap 光學）
A49: AI 可插拔光模組市場（FY 加權）× 情境顆數係數 | B49: US$B | E49: =(w8*mpl_26*1+(1-w8)*mpl_27*1) -> 37.68908 | F49: =(w8*mpl_27*1+(1-w8)*mpl_28*um28_A) -> 55.037643 | G49: =(w8*mpl_28*um28_A+(1-w8)*mpl_29*um29_A) -> 62.9726
A50: Credo 光學有效份額（FY2027 校準）＝ 光學營收 ÷ 可插拔市場 | B50: % | E50: =a27_opt/(w8*mplB_26*1+(1-w8)*mplB_27*1) -> 0.015762535
A51: 光學有效份額相對值（÷ FY2027） | B51: x | E51: =1 -> 1 | F51: =rel_o_28 -> 1.2 | G51: =rel_o_29 -> 1.35
A52: 光學營收 | B52: US$B | D52: =a26_opt -> 0.15 | E52: =a27_opt -> 0.6 | F52: =F49*$E$50*F51 -> 1.0410393 | G52: =G49*$E$50*G51 -> 1.3400205
A53: C. 其他營收與合計
A54: 其他 IC 與 IP（線卡 PHY、重定時器、SerDes 授權） | B54: US$B | D54: =a26_ic -> 0.09345812 | E54: =a27_ic -> 0.10747684 | F54: =E54*(1+g_oth) -> 0.12359836 | G54: =F54*(1+g_oth) -> 0.14213812
A55: 營收 | B55: US$B | C55: =a25_rev -> 0.436775 | D55: =a26_rev -> 1.335116 | E55: =E47+E52+E54 -> 2.4699646 | F55: =F47+F52+F54 -> 3.2382102 | G55: =G47+G52+G54 -> 3.3287357
A56: 營收年增 | B56: % | D56: =D55/C55-1 -> 2.0567592 | E56: =E55/D55-1 -> 0.85 | F56: =F55/E55-1 -> 0.31103507 | G56: =G55/F55-1 -> 0.027955397
A57: AEC ÷ 營收 | B57: % | D57: =D47/D55 -> 0.81765021 | E57: =E47/E55 -> 0.71356803 | F57: =F47/F55 -> 0.64034525 | G57: =G47/G55 -> 0.55473826
A58: 光學 ÷ 營收 | B58: % | D58: =D52/D55 -> 0.11234979 | E58: =E52/E55 -> 0.24291846 | F58: =F52/F55 -> 0.32148602 | G58: =G52/G55 -> 0.40256141
A59: D. 損益（non-GAAP）
A60: 毛利率 | B60: % | C60: =a25_gp/a25_rev -> 0.65045618 | D60: =a26_gp/a26_rev -> 0.6814142 | E60: =a27_gp/a27_rev -> 0.68002954 | F60: =gm_28 -> 0.67 | G60: =gm_29 -> 0.66 | H60: FY2028 起為輸入路徑（光學占比上升、AEC 競爭）
A61: 毛利 | B61: US$B | C61: =C55*C60 -> 0.284103 | D61: =D55*D60 -> 0.909767 | E61: =E55*E60 -> 1.6796489 | F61: =F55*F60 -> 2.1696008 | G61: =G55*G60 -> 2.1969655
A62: 營業費用（基準路徑） | B62: US$B | C62: =a25_opx -> 0.168751 | D62: =a26_opx -> 0.270945 | E62: =a27_opx -> 0.4064175 | F62: =E62*(1+MAX(0,phi*F56)) -> 0.48077638 | G62: =F62*(1+MAX(0,phi*G56)) -> 0.48868244
A63: 營業費用 | B63: US$B | C63: =C62 -> 0.168751 | D63: =D62 -> 0.270945 | E63: =E62 -> 0.4064175 | F63: =F62+0*F55 -> 0.48077638 | G63: =G62+0*G55 -> 0.48868244
A64: 營業利益 | B64: US$B | C64: =C61-C63 -> 0.115352 | D64: =D61-D63 -> 0.638822 | E64: =E61-E63 -> 1.2732314 | F64: =F61-F63 -> 1.6888245 | G64: =G61-G63 -> 1.7082831
A65: 營業利益率 | B65: % | C65: =C64/C55 -> 0.26409936 | D65: =D64/D55 -> 0.47847678 | E65: =E64/E55 -> 0.51548568 | F65: =F64/F55 -> 0.52153021 | G65: =G64/G55 -> 0.51319278
A66: 其他收益（淨） | B66: US$B | C66: =a25_ninc -> 0.017746 | D66: =a26_ninc -> 0.03043 | E66: =a27_ninc -> 0.02914 | F66: =oth_f -> 0.03 | G66: =oth_f -> 0.03
A67: 有效稅率 | B67: % | C67: =a25_tx -> 0.023832064 | D67: =a26_tx -> 0.01151883 | E67: =a27_tx -> 0.014184015 | F67: =tx_28 -> 0.13 | G67: =tx_29 -> 0.14 | H67: FY2028 起 OECD 15% 全球最低稅（10-K）
A68: 淨利 | B68: US$B | C68: =a25_ni -> 0.129926 | D68: =a26_ni -> 0.661543 | E68: =a27_ni -> 1.2838985 | F68: =(F64+F66)*(1-F67) -> 1.4953773 | G68: =(G64+G66)*(1-G67) -> 1.4949235
A69: 淨利率 | B69: % | C69: =C68/C55 -> 0.29746666 | D69: =D68/D55 -> 0.49549477 | E69: =E68/E55 -> 0.51980443 | F69: =F68/F55 -> 0.46179129 | G69: =G68/G55 -> 0.44909648
A70: 稀釋股數 | B70: 十億股 | C70: =a25_sh -> 0.184644 | D70: =a26_sh -> 0.191256 | E70: =a27_sh -> 0.199 | F70: =E70*(1+sh_g) -> 0.201985 | G70: =F70*(1+sh_g) -> 0.20501478
A71: EPS（non-GAAP） | B71: US$ | C71: =C68/C70 -> 0.70365677 | D71: =D68/D70 -> 3.4589399 | E71: =E68/E70 -> 6.4517514 | F71: =F68/F70 -> 7.4034076 | G71: =G68/G70 -> 7.2917841
A72: EPS 年增 | B72: % | D72: =D71/C71-1 -> 3.9156635 | E72: =E71/D71-1 -> 0.86523955 | F72: =F71/E71-1 -> 0.14750354 | G72: =G71/F71-1 -> -0.015077318
A75: 案例區塊：AEC 份額上升（高）（情境 A）
A76: 項目 | B76: 單位 | C76: FY2025A | D76: FY2026A | E76: FY2027（錨點） | F76: FY2028 | G76: FY2029 | H76: 說明
A77: A. AEC（E 欄＝FY2027 校準年；F–G＝FY2028–FY2029；市場為日曆年月數加權）
A78: AI 銅纜市場（FY 加權）× 情境顆數係數 | B78: US$B | E78: =(w8*mcu_26*1+(1-w8)*mcu_27*1) -> 34.339013 | F78: =(w8*mcu_27*1+(1-w8)*mcu_28*um28_A) -> 53.866613 | G78: =(w8*mcu_28*um28_A+(1-w8)*mcu_29*um29_A) -> 59.962245 | H78: FY(t)＝8/12 × CY(t−1)＋4/12 × CY(t)；CY2028 起乘顆數係數
A79: Credo AEC 有效份額（FY2027 校準）＝ AEC 營收 ÷ 銅纜市場 | B79: % | E79: =a27_aec/E78 -> 0.051326104 | H79: Derived：＝AEC 滲透率 × Credo 占 AEC（拆分見 Units）
A80: AEC 有效份額相對值（÷ FY2027） | B80: x | E80: =1 -> 1 | F80: =RHI_28 -> 1.15 | G80: =RHI_29 -> 1.2
A81: AEC 有效份額 | B81: % | E81: =$E$79*E80 -> 0.051326104 | F81: =$E$79*F80 -> 0.059025019 | G81: =$E$79*G80 -> 0.061591325
A82: AEC 營收 | B82: US$B | D82: =a26_aec -> 1.0916579 | E82: =a27_aec -> 1.7624878 | F82: =F78*F81 -> 3.1794779 | G82: =G78*G81 -> 3.6931541
A83: B. 光學（光 DSP、矽光 PIC、ZeroFlap 光學）
A84: AI 可插拔光模組市場（FY 加權）× 情境顆數係數 | B84: US$B | E84: =(w8*mpl_26*1+(1-w8)*mpl_27*1) -> 37.68908 | F84: =(w8*mpl_27*1+(1-w8)*mpl_28*um28_A) -> 55.037643 | G84: =(w8*mpl_28*um28_A+(1-w8)*mpl_29*um29_A) -> 62.9726
A85: Credo 光學有效份額（FY2027 校準）＝ 光學營收 ÷ 可插拔市場 | B85: % | E85: =a27_opt/(w8*mplB_26*1+(1-w8)*mplB_27*1) -> 0.015762535
A86: 光學有效份額相對值（÷ FY2027） | B86: x | E86: =1 -> 1 | F86: =rel_o_28 -> 1.2 | G86: =rel_o_29 -> 1.35
A87: 光學營收 | B87: US$B | D87: =a26_opt -> 0.15 | E87: =a27_opt -> 0.6 | F87: =F84*$E$85*F86 -> 1.0410393 | G87: =G84*$E$85*G86 -> 1.3400205
A88: C. 其他營收與合計
A89: 其他 IC 與 IP（線卡 PHY、重定時器、SerDes 授權） | B89: US$B | D89: =a26_ic -> 0.09345812 | E89: =a27_ic -> 0.10747684 | F89: =E89*(1+g_oth) -> 0.12359836 | G89: =F89*(1+g_oth) -> 0.14213812
A90: 營收 | B90: US$B | C90: =a25_rev -> 0.436775 | D90: =a26_rev -> 1.335116 | E90: =E82+E87+E89 -> 2.4699646 | F90: =F82+F87+F89 -> 4.3441156 | G90: =G82+G87+G89 -> 5.1753127
A91: 營收年增 | B91: % | D91: =D90/C90-1 -> 2.0567592 | E91: =E90/D90-1 -> 0.85 | F91: =F90/E90-1 -> 0.75877645 | G91: =G90/F90-1 -> 0.19133863
A92: AEC ÷ 營收 | B92: % | D92: =D82/D90 -> 0.81765021 | E92: =E82/E90 -> 0.71356803 | F92: =F82/F90 -> 0.73190454 | G92: =G82/G90 -> 0.71360984
A93: 光學 ÷ 營收 | B93: % | D93: =D87/D90 -> 0.11234979 | E93: =E87/E90 -> 0.24291846 | F93: =F87/F90 -> 0.23964356 | G93: =G87/G90 -> 0.25892552
A94: D. 損益（non-GAAP）
A95: 毛利率 | B95: % | C95: =a25_gp/a25_rev -> 0.65045618 | D95: =a26_gp/a26_rev -> 0.6814142 | E95: =a27_gp/a27_rev -> 0.68002954 | F95: =gm_28 -> 0.67 | G95: =gm_29 -> 0.66 | H95: FY2028 起為輸入路徑（光學占比上升、AEC 競爭）
A96: 毛利 | B96: US$B | C96: =C90*C95 -> 0.284103 | D96: =D90*D95 -> 0.909767 | E96: =E90*E95 -> 1.6796489 | F96: =F90*F95 -> 2.9105574 | G96: =G90*G95 -> 3.4157064
A97: 營業費用（基準路徑） | B97: US$B | C97: =a25_opx -> 0.168751 | D97: =a26_opx -> 0.270945 | E97: =a27_opx -> 0.4064175 | F97: =E97*(1+MAX(0,phi*F91)) -> 0.58781752 | G97: =F97*(1+MAX(0,phi*G91)) -> 0.65397763
A98: 營業費用 | B98: US$B | C98: =C97 -> 0.168751 | D98: =D97 -> 0.270945 | E98: =E97 -> 0.4064175 | F98: =F97+0*F90 -> 0.58781752 | G98: =G97+0*G90 -> 0.65397763
A99: 營業利益 | B99: US$B | C99: =C96-C98 -> 0.115352 | D99: =D96-D98 -> 0.638822 | E99: =E96-E98 -> 1.2732314 | F99: =F96-F98 -> 2.3227399 | G99: =G96-G98 -> 2.7617287
A100: 營業利益率 | B100: % | C100: =C99/C90 -> 0.26409936 | D100: =D99/D90 -> 0.47847678 | E100: =E99/E90 -> 0.51548568 | F100: =F99/F90 -> 0.53468649 | G100: =G99/G90 -> 0.53363515
A101: 其他收益（淨） | B101: US$B | C101: =a25_ninc -> 0.017746 | D101: =a26_ninc -> 0.03043 | E101: =a27_ninc -> 0.02914 | F101: =oth_f -> 0.03 | G101: =oth_f -> 0.03
A102: 有效稅率 | B102: % | C102: =a25_tx -> 0.023832064 | D102: =a26_tx -> 0.01151883 | E102: =a27_tx -> 0.014184015 | F102: =tx_28 -> 0.13 | G102: =tx_29 -> 0.14 | H102: FY2028 起 OECD 15% 全球最低稅（10-K）
A103: 淨利 | B103: US$B | C103: =a25_ni -> 0.129926 | D103: =a26_ni -> 0.661543 | E103: =a27_ni -> 1.2838985 | F103: =(F99+F101)*(1-F102) -> 2.0468837 | G103: =(G99+G101)*(1-G102) -> 2.4008867
A104: 淨利率 | B104: % | C104: =C103/C90 -> 0.29746666 | D104: =D103/D90 -> 0.49549477 | E104: =E103/E90 -> 0.51980443 | F104: =F103/F90 -> 0.47118538 | G104: =G103/G90 -> 0.46391143
A105: 稀釋股數 | B105: 十億股 | C105: =a25_sh -> 0.184644 | D105: =a26_sh -> 0.191256 | E105: =a27_sh -> 0.199 | F105: =E105*(1+sh_g) -> 0.201985 | G105: =F105*(1+sh_g) -> 0.20501478
A106: EPS（non-GAAP） | B106: US$ | C106: =C103/C105 -> 0.70365677 | D106: =D103/D105 -> 3.4589399 | E106: =E103/E105 -> 6.4517514 | F106: =F103/F105 -> 10.13384 | G106: =G103/G105 -> 11.710799
A107: EPS 年增 | B107: % | D107: =D106/C106-1 -> 3.9156635 | E107: =E106/D106-1 -> 0.86523955 | F107: =F106/E106-1 -> 0.57071152 | G107: =G106/F106-1 -> 0.1556131
A110: 案例區塊：最大客戶流失（情境 A）
A111: 項目 | B111: 單位 | C111: FY2025A | D111: FY2026A | E111: FY2027（錨點） | F111: FY2028 | G111: FY2029 | H111: 說明
A112: A. AEC（E 欄＝FY2027 校準年；F–G＝FY2028–FY2029；市場為日曆年月數加權）
A113: AI 銅纜市場（FY 加權）× 情境顆數係數 | B113: US$B | E113: =(w8*mcu_26*1+(1-w8)*mcu_27*1) -> 34.339013 | F113: =(w8*mcu_27*1+(1-w8)*mcu_28*um28_A) -> 53.866613 | G113: =(w8*mcu_28*um28_A+(1-w8)*mcu_29*um29_A) -> 59.962245 | H113: FY(t)＝8/12 × CY(t−1)＋4/12 × CY(t)；CY2028 起乘顆數係數
A114: Credo AEC 有效份額（FY2027 校準）＝ AEC 營收 ÷ 銅纜市場 | B114: % | E114: =a27_aec/E113 -> 0.051326104 | H114: Derived：＝AEC 滲透率 × Credo 占 AEC（拆分見 Units）
A115: AEC 有效份額相對值（÷ FY2027） | B115: x | E115: =1 -> 1 | F115: =cl_28 -> 0.67 | G115: =cl_29 -> 0.6365
...

Sheet Sources
A1: 來源（公司原文＝SEC 8-K 新聞稿與 10-K）
A2: 公司：4Q26 與 FY2026 實績、1Q27 指引（8-K 附件 99.1） | B2: https://www.sec.gov/Archives/edgar/data/0001807794/000162828026039474/credoq42026ex-991.htm
A3: 公司：1Q27 實績、2Q27 指引（8-K 附件 99.1） | B3: https://www.sec.gov/Archives/edgar/data/0001807794/000162828026059795/credoq12027ex-991.htm
A4: 公司：FY2026 10-K（客戶集中、DustPhotonics、OECD 最低稅、股數、地區營收） | B4: https://www.sec.gov/Archives/edgar/data/0001807794/000162828026043303/crdo-20260502.htm
A5: 二手：4Q26 法說摘要（FY2027 年增逾 80%、光學逾 6 億美元、營業費用約 +50%） | B5: https://letsdatascience.com/news/credo-raises-guidance-as-optical-ramp-accelerates-30d77185
A6: 二手：1Q27 摘要（年增逾 85%、淨利率約 50%、AEC 占營收年增九成以上） | B6: https://www.itiger.com/news/1122940235
A7: 二手：1Q27 法說重點（Zacks；前四大終端客戶 33%、28%、13%、10%；五家超大規模客戶） | B7: https://www.yourwyominglink.com/credo-q1-earnings-call-highlights-optics-as-the-next-growth-engine/article_d01cfee6-9667-5ab6-8b08-fcf8fffa13d0.html
A8: 券商：Jefferies AEC 條數與份額（Invezz 轉述） | B8: https://invezz.com/en-ae/news/2026/04/13/credo-jumps-11percent-as-jefferies-backs-copper-tech-in-ai-boom-debate/
A9: 券商：Needham 等（客戶名稱 Amazon、Microsoft、xAI；Benzinga 2025-03） | B9: https://www.benzinga.com/25/03/44149586/credo-expands-hyperscaler-partnerships-with-amazon-microsoft-xai-amid-nvidia-powered-ai-boom
A10: 共識：Yahoo Finance 分析師預估（2026-10-01） | B10: https://finance.yahoo.com/quote/CRDO/analysis/
A11: 共識：StockAnalysis 預估與目標價（2026-10-05） | B11: https://stockanalysis.com/stocks/crdo/forecast/
A12: 價格：StockAnalysis（2026-10-23 收盤、52 週區間、股數） | B12: https://stockanalysis.com/stocks/crdo/
A13: 價格與評論：TIKR（10 月跌幅、OCP 發表 ALC、FY2027 共識 GAAP／調整後 EPS） | B13: https://www.tikr.com/blog/credo-stock-fell-22-last-week-as-it-launched-a-new-optical-cable-heres-where-it-could-go-by-2031
... A15: 資料商：StockAnalysis 會計年度末 P/E | B15: https://stockanalysis.com/stocks/crdo/financials/ratios/
A16: 市場層：markets/network、tsmc 成品（本 repo，唯讀）
A17: 待補（人工）：2Q27 財報；產品線營收拆分（AEC、光學、IC、IP）；客戶名稱第一手出處；AEC 市場份額第一手來源；共識 FY2028 是否含 OECD 最低稅；P/E 第二來源；前瞻 P/E 歷史（Bloomberg） | B17: 未找到
A18: SemiAnalysis | B18: 未使用
