Workbook

Sheet README
A1: Astera Labs（ALAB）收支與估值模型 v0.1.1（AI 半導體 Project：網通次產業內複製——PCIe／CXL 重定時器、Scorpio 交換晶片、AEC 模組；scale-up 互連） 2026-10-25
A2: 版本：v0.1（2026-10-25 初版；三情境延伸到 FY2032、目標價＝DCF 與 Comparable 加權）。Astera Labs 在非 NVIDIA scale-up 交換晶片（Scorpio X）與 PCIe／CXL／AEC 的份額在本模型 Units 頁建立，為本專案權威資料（規則第 13 條）。
A3: 模型命題：Astera Labs 的 Scorpio X 營收＝非 NVIDIA scale-up 交換晶片市場（本專案網通模型：AMD、Trainium、其他 ASIC 顆數 × 每顆 scale-up 交換晶片內容）× Astera 有效份額；PCIe 與訊號調節（Aries 重定時器、Scorpio P、Taurus AEC、Leo CXL）＝AI 加速器顆數 × 每顆內容 × 份額。3Q26 指引季增約 40%、Scorpio 成為最大產品線：成長重心正由重定時器轉到 scale-up 交換晶片。現價約 64 倍共識 FY2026 EPS、40 倍 FY2027。
A4: 核心問題：現價隱含的 FY2028 EPS 需要 Scorpio X 在非 NVIDIA scale-up 交換晶片維持多少份額、PCIe 等業務流失多少才成立？非 NVIDIA 加速器顆數（AMD、Trainium、其他 ASIC）與 NVLink Fusion 的競爭是主要不確定性。
A6: 會計年度：日曆年（12 月底結束）；上游市場層為日曆年，FY(t) 市場＝CY(t)。預測期 FY2027–FY2029（FY2026 為錨點），FY2030–FY2032 為收斂法。口徑：公司 non-GAAP；十年 P/E 規則值用 GAAP 換算 EPS。
A8: 驅動因子 → 推導量（全部唯讀上游，不修改）
A9: Scorpio X：markets/network 的非 NVIDIA scale-up 交換晶片市場 × 情境顆數係數 × Astera 有效份額（FY2026 錨點校準）× 份額相對值（Assumed）。PCIe 等：AI 加速器顆數 × 情境顆數係數 × 每顆內容 × 有效份額（FY2026 校準）× 相對值（Assumed）。
A10: 毛利率：FY2027 起為輸入路徑（Assumed；公司長期目標 70%）。營業費用：彈性 phi（FY2026 錨點 Derived）。稅率：約 12%（公司 non-GAAP 稅率）。股數：+1.5%／年。
A11: 校準：FY2026 ＝ 1Q26、2Q26 實績（營收 3.08、3.92 億美元；non-GAAP EPS 0.61、0.80）＋ 3Q26 指引中點（5.50 億美元）＋ 4Q26（季增 15%，Assumed）。產品線拆分公司未揭露：Scorpio X FY2026 為假設，PCIe 等為殘差。不用共識（只在 Recon 對帳）。
A12: 估值：目標價（Val 第 0 節）＝0.5 × DCF（股東現金流＝EPS ×（1 − g／ROE），FY2027–32 明確期＋永續，r 10%、g 4%，情境權重 0.3／0.5／0.2）＋0.5 × Comparable（美股高速連接晶片同業前瞻 P/E 中位數 × 12 個月後前瞻 EPS）。舊法規則值情境加權保留參考（不是目標價）；市場隱含 FY2028 EPS（Val 第 4 節）；十年 P/E 規則值（只有 2025 年一個正值）× FY2027 GAAP 換算 EPS；循環位置以本模型營收最高年判定。本版未做先驗，無 Andy 合理 P/E 對照。
A13: 標記：Verified、Interested-party、Analogy、Assumed、Derived。SemiAnalysis 未使用。客戶名稱公司未具名；10-K 只揭露單一終端客戶逾 70%、前三大約 86%（FY2025）。
A15: 已知限制：(1) Scorpio X FY2026 營收、兩條業務的份額相對值、毛利率路徑皆為 Assumed，是 FY2027–FY2029 EPS 最敏感的輸入（Sens）；(2) 產品線營收未揭露，PCIe 等為殘差；(3) 網通模型沒有 PCIe 重定時器與 PCIe 交換晶片的獨立列，本模型以加速器顆數 × 每顆內容代替；(4) 非 NVIDIA scale-up 交換晶片市場排除 NVIDIA（NVLink）與 TPU（ICI／光學電路交換），NVLink Fusion 若開放第三方交換晶片會改變分母；(5) 十年 P/E 只有 2025 年一個觀測值、含高成長期溢價，規則值明顯偏高；(6) R4 產業部署路徑未建（Recon 預留列）。
A16: v0.1.1（2026-10-25）：補上檔空間級距、投資建議、重點觀察（數值不變）。Val 頁末新增「上檔空間級距」「投資建議」兩列（Andy 2026-10-25 14:00、14:17 固定規則），README 頁末新增投資建議與重點觀察三點；既有儲存格位置與數值不變。
A17: ="投資建議："&Val!B130&"（依上檔空間固定規則）" -> 投資建議：放空（依上檔空間固定規則）
A18: 重點觀察 1：目標價 US$132（DCF 105、Comparable 160 各半），比現價 257.16（2026-10-23）低 48.5%，級距 −25%～−50%；Comparable 單獨為 −37.9%。EPS 與倍數兩個因素都在：本模型 12 個月後前瞻 EPS 6.33 比共識 8.21 低 22.9%；同業（Credo、Marvell、Broadcom、Rambus、MACOM）前瞻 P/E 中位數 25.2 倍，現價隱含 31.3 倍共識 EPS、共識目標價 388.36 隱含 47.3 倍（比同業高 87.5%）；Comparable 未給 Astera 的成長溢價（本身前瞻 P/E 約 46 倍）。
A19: 重點觀察 2：情境分歧從 FY2028 起：FY2027 EPS 三情境同為 6.90，FY2028 A／B／C 為 8.10／6.13／3.60，DCF 價格帶 52～139；Val 頁讀法：以同業約 25 倍計，現價隱含的 FY2028 EPS 比模型 A 高約三成，需要 Scorpio X 份額上升才達得到。
A20: 重點觀察 3：FY2027 EPS 最敏感的是 Scorpio X 份額（高 +18.7%、低 −14.0%）與 PCIe 等份額（高 +15.2%、低 −11.4%）；最大客戶 30% 轉單時 −12.8%（Sens 頁）。下一個檢驗點是 3Q26 財報（2026-11-03）的 Scorpio X 營收與客戶數。

Sheet In
A1: In — 輸入（藍字；基準欄 E，低 D、高 F）。金額：十億美元（US$B）；比例：%。每個輸入附兩個來源（找不到者寫「未找到」）；公司原文算一個
A2: 標記：Verified／Interested-party／Analogy／Assumed／Derived；Analogy、Assumed 給低／高區間。SemiAnalysis 未使用。公司原文＝SEC 8-K 新聞稿與 10-K；公司不揭露產品線營收（Aries、Taurus、Leo、Scorpio P／X）與客戶名稱
A3: 鍵 | B3: 項目 | C3: 單位 | D3: 低 | E3: 基準 | F3: 高 | G3: 標記 | H3: 來源1 | I3: 來源2／說明
A4: A. 市場（讀 markets/network 成品；日曆年 CY2026–CY2029＝會計年度；情境 A 基準，B／C 依顆數係數縮放）
A5: msx_26 | B5: 非 NVIDIA scale-up 交換晶片市場 CY2026（AMD、Trainium、其他 ASIC；不含 TPU） | C5: US$B | E5: 2.025 | G5: Derived | H5: markets/network/dist/20261026_AI網通市場模型_v0.2.3.xlsx｜Units!B8:E8、B10:E10、B11:E11 × In!E62（2026）／E68、E80、E86 | I5: 顆數 × 每顆 scale-up 交換晶片內容（網通模型 In 頁 c_*_su_sw）；NVIDIA 平台用自家 NVLink 交換晶片、TPU 用 ICI／光學電路交換，不列入 Scorpio X 可服務市場
A6: msx_27 | B6: 非 NVIDIA scale-up 交換晶片市場 CY2027（AMD、Trainium、其他 ASIC；不含 TPU） | C6: US$B | E6: 7.701 | G6: Derived | H6: 同上 | I6: 同上
A7: msx_28 | B7: 非 NVIDIA scale-up 交換晶片市場 CY2028（AMD、Trainium、其他 ASIC；不含 TPU） | C7: US$B | E7: 9.468 | G7: Derived | H7: 同上 | I7: 同上
A8: msx_29 | B8: 非 NVIDIA scale-up 交換晶片市場 CY2029（AMD、Trainium、其他 ASIC；不含 TPU） | C8: US$B | E8: 10.8882 | G8: Derived | H8: 同上 | I8: 同上
A9: msu_26 | B9: scale-up 交換晶片市場合計 CY2026（含 NVIDIA NVLink；Units、Recon 用） | C9: US$B | E9: 18.2761 | G9: Derived | H9: markets/network/dist/20261026_AI網通市場模型_v0.2.3.xlsx｜Mkt!C5:F5 | I9: 只作對照，不進損益
A10: msu_27 | B10: scale-up 交換晶片市場合計 CY2027（含 NVIDIA NVLink；Units、Recon 用） | C10: US$B | E10: 37.4157 | G10: Derived | H10: markets/network/dist/20261026_AI網通市場模型_v0.2.3.xlsx｜Mkt!C5:F5 | I10: 同上
A11: msu_28 | B11: scale-up 交換晶片市場合計 CY2028（含 NVIDIA NVLink；Units、Recon 用） | C11: US$B | E11: 44.9835 | G11: Derived | H11: markets/network/dist/20261026_AI網通市場模型_v0.2.3.xlsx｜Mkt!C5:F5 | I11: 同上
A12: msu_29 | B12: scale-up 交換晶片市場合計 CY2029（含 NVIDIA NVLink；Units、Recon 用） | C12: US$B | E12: 51.2458 | G12: Derived | H12: markets/network/dist/20261026_AI網通市場模型_v0.2.3.xlsx｜Mkt!C5:F5 | I12: 同上
A13: u_26 | B13: AI 加速器顆數合計 CY2026 | C13: 百萬顆 | E13: 15.2 | G13: Derived | H13: markets/network/dist/20261026_AI網通市場模型_v0.2.3.xlsx｜Units!B12 | I13: 網通模型 Units 頁（顆數取自 markets/memory，2029 為成長率）
A14: u_27 | B14: AI 加速器顆數合計 CY2027 | C14: 百萬顆 | E14: 23.7 | G14: Derived | H14: markets/network/dist/20261026_AI網通市場模型_v0.2.3.xlsx｜Units!C12 | I14: 同上
A15: u_28 | B15: AI 加速器顆數合計 CY2028 | C15: 百萬顆 | E15: 26.5 | G15: Derived | H15: markets/network/dist/20261026_AI網通市場模型_v0.2.3.xlsx｜Units!D12 | I15: 同上
A16: u_29 | B16: AI 加速器顆數合計 CY2029 | C16: 百萬顆 | E16: 30.15 | G16: Derived | H16: markets/network/dist/20261026_AI網通市場模型_v0.2.3.xlsx｜Units!E12 | I16: 同上
... A30: um29_C | B30: 情境 C：CY2029 顆數 ÷ 基準 | C30: x | E30: 0.6 | G30: Assumed | H30: tsmc/dist/20261025_台積電模型_v0.3.1.xlsx｜In!E42 | I30: 同上
A31: B. Scorpio X（scale-up 交換晶片；本專案為權威：Astera 在非 NVIDIA scale-up 交換晶片的份額，規則第 13 條）
A32: x_25 | B32: FY2025 Scorpio X 營收 | C32: US$B | D32: 0 | E32: 0 | F32: 0.02 | G32: Assumed | H32: https://www.tikr.com/blog/astera-labs-what-a-224-bull-case-looks-like：Scorpio X 在 FY2025「not meaningful」（Interested-party） | I32: https://www.fool.com/earnings/call-transcripts/2026/05/05/astera-labs-alab-q1-2026-earnings-transcript/：Scorpio X 初期量產於 1Q26 開始出貨（公司）
A33: x_26 | B33: FY2026 Scorpio X 營收（未揭露） | C33: US$B | D33: 0.28 | E33: 0.38 | F33: 0.5 | G33: Assumed | H33: 公司不揭露產品線營收：未找到；推估：Scorpio 1Q26 約占 20%（分析師於法說引述，公司未證實）、3Q26 成為最大產品線且 X 超過 P | I33: MarketBeat 法說摘要（網址見 Sources）：Scorpio 於 3Q26 成為最大產品線（提前一季）、X 系列 3Q26 超過 P 系列；逾 10 家客戶接洽 Scorpio X（公司）
A34: rel_x_27 | B34: Scorpio X 有效份額 FY2027 ÷ FY2026（相對值） | C34: x | D34: 0.7 | E34: 1 | F34: 1.4 | G34: Assumed | H34: https://www.marketbeat.com/instant-alerts/astera-labs-q2-earnings-call-highlights-2026-08-04/：第二家以後的客戶 2026 年底起出貨、2027 年初更多客戶量產（公司） | I34: 競爭：Broadcom Tomahawk Ultra、NVLink Fusion、其他 UALink 交換晶片（10-K 列名競爭者含 Broadcom、Marvell）
A35: rel_x_28 | B35: Scorpio X 有效份額 FY2028 ÷ FY2026 | C35: x | D35: 0.6 | E35: 1.1 | F35: 1.7 | G35: Assumed | H35: https://www.fool.com/earnings/call-transcripts/2026/05/05/astera-labs-alab-q1-2026-earnings-transcript/：現有設計案每顆加速器內容逾 1,000 美元（公司） | I35: 整合 CPO 的 Scorpio X 規劃 2028 年後（公司，Futurum 轉述）
A36: rel_x_29 | B36: Scorpio X 有效份額 FY2029 ÷ FY2026 | C36: x | D36: 0.5 | E36: 1.15 | F36: 2 | G36: Assumed | H36: 同上 | I36: —
A37: C. PCIe 與訊號調節（Aries 重定時器、Scorpio P PCIe 交換晶片、Taurus AEC 模組、Leo CXL；讀加速器顆數）
A38: c_pcie | B38: 每顆加速器 PCIe／CXL／AEC 可服務內容（只作份額顯示；不影響損益） | C38: US$/顆 | D38: 150 | E38: 250 | F38: 400 | G38: Assumed | H38: 第一手每顆內容：未找到 | I38: 損益＝FY2026 營收 × 顆數成長 × 相對值，與本列無關（校準時抵銷）
A39: rel_p_27 | B39: PCIe 等有效份額 × 每顆內容 FY2027 ÷ FY2026（相對值） | C39: x | D39: 0.65 | E39: 0.8 | F39: 1 | G39: Assumed | H39: https://www.sec.gov/Archives/edgar/data/1736297/000173629726000010/alab-20251231.htm：競爭者 Broadcom、Credo、Marvell、Microchip、Montage、Parade、Rambus（公司） | I39: PCIe 6／7 單價上升 vs 重定時器份額競爭、平台整合（每顆加速器重定時器數減少）；Aries FY2025 年增約 70%（TIKR，Interested-party）
A40: rel_p_28 | B40: PCIe 等有效份額 × 每顆內容 FY2028 ÷ FY2026 | C40: x | D40: 0.55 | E40: 0.75 | F40: 1 | G40: Assumed | H40: 同上；Taurus 3.2T 可服務市場 2030 年逾 40 億美元（公司，MarketBeat 轉述） | I40: Leo CXL 2027 年起兩家美國超大規模業者量產（公司）
A41: rel_p_29 | B41: PCIe 等有效份額 × 每顆內容 FY2029 ÷ FY2026 | C41: x | D41: 0.45 | E41: 0.7 | F41: 1 | G41: Assumed | H41: 同上 | I41: —
A42: cust_top | B42: 最大終端客戶占營收（FY2025；Sens「最大客戶部分轉單」用） | C42: % | E42: 0.7 | G42: Verified | H42: 公司 FY2025 10-K（網址見 Sources）：單一終端客戶「逾 70%」、前三大約 86%（FY2025，公司未具名） | I42: 客戶名稱：未找到（公司未具名）
A43: cl_loss | B43: 最大客戶部分轉單：其 PCIe 等內容轉給其他供應商或自製的比例（Sens 用） | C43: % | E43: 0.3 | G43: Assumed | H43: 無 | I43: —
A44: cl_27 | B44: 最大客戶部分轉單情境：PCIe 等相對值 FY2027（Sens 用） | C44: x | E44: =rel_p_27*(1-cust_top*cl_loss) -> 0.632 | G44: Derived | H44: 相對值 ×（1 − 最大客戶占比 × 轉單比例） | I44: 假設轉單只發生在 PCIe 等（Scorpio X 不變）
A45: cl_28 | B45: 最大客戶部分轉單情境：PCIe 等相對值 FY2028（Sens 用） | C45: x | E45: =rel_p_28*(1-cust_top*cl_loss) -> 0.5925 | G45: Derived | H45: 相對值 ×（1 − 最大客戶占比 × 轉單比例） | I45: 同上
A46: cl_29 | B46: 最大客戶部分轉單情境：PCIe 等相對值 FY2029（Sens 用） | C46: x | E46: =rel_p_29*(1-cust_top*cl_loss) -> 0.553 | G46: Derived | H46: 相對值 ×（1 − 最大客戶占比 × 轉單比例） | I46: 同上
A47: D. FY2026 錨點（1Q26、2Q26 實績＋3Q26 指引＋4Q26 假設）
A48: q1_rev | B48: 1Q26 營收（截至 2026-03-31） | C48: US$B | E48: 0.308361 | G48: Verified | H48: https://www.sec.gov/Archives/edgar/data/0001736297/000173629726000033/q226exhibit991.htm：308,361 千美元（2Q26 新聞稿比較欄） | I48: https://www.fool.com/earnings/call-transcripts/2026/05/05/astera-labs-alab-q1-2026-earnings-transcript/：1Q26 法說
A49: q1_gp | B49: 1Q26 non-GAAP 毛利 | C49: US$B | E49: 0.23564 | G49: Verified | H49: https://www.sec.gov/Archives/edgar/data/0001736297/000173629726000033/q226exhibit991.htm：235,640 千美元（毛利率 76.4%） | I49: https://www.fool.com/earnings/call-transcripts/2026/05/05/astera-labs-alab-q1-2026-earnings-transcript/：76.4%
A50: q1_opx | B50: 1Q26 non-GAAP 營業費用（＝毛利 − 營業利益） | C50: US$B | E50: =0.23564-0.111729 -> 0.123911 | G50: Verified | H50: https://www.sec.gov/Archives/edgar/data/0001736297/000173629726000033/q226exhibit991.htm：non-GAAP 營業利益 111,729 千美元 | I50: —
A51: q1_ninc | B51: 1Q26 利息與其他收益（non-GAAP） | C51: US$B | E51: 0.011581 | G51: Verified | H51: https://www.sec.gov/Archives/edgar/data/0001736297/000173629726000033/q226exhibit991.htm：11,581 千美元 | I51: —
A52: q1_ni | B52: 1Q26 non-GAAP 淨利 | C52: US$B | E52: 0.110069 | G52: Verified | H52: https://www.sec.gov/Archives/edgar/data/0001736297/000173629726000033/q226exhibit991.htm：110,069 千美元 | I52: —
A53: q1_sh | B53: 1Q26 稀釋股數 | C53: 十億股 | E53: 0.181157 | G53: Verified | H53: https://www.sec.gov/Archives/edgar/data/0001736297/000173629726000033/q226exhibit991.htm：181,157 千股 | I53: —
A54: q2_rev | B54: 2Q26 營收（截至 2026-06-30） | C54: US$B | E54: 0.3924 | G54: Verified | H54: https://www.sec.gov/Archives/edgar/data/0001736297/000173629726000033/q226exhibit991.htm：392,400 千美元（年增 104%、季增 27%） | I54: https://www.marketbeat.com/instant-alerts/astera-labs-q2-earnings-call-highlights-2026-08-04/：3.924 億美元
A55: q2_gp | B55: 2Q26 non-GAAP 毛利 | C55: US$B | E55: 0.289259 | G55: Verified | H55: https://www.sec.gov/Archives/edgar/data/0001736297/000173629726000033/q226exhibit991.htm：289,259 千美元（毛利率 73.7%；含 Amazon 認股權證約 200bp 非現金營收減項） | I55: https://futurumgroup.com/insights/astera-labs-q2-fy-2026-earnings-pull-scorpio-switch-leadership-forward/：73.7%
A56: q2_opx | B56: 2Q26 non-GAAP 營業費用（＝毛利 − 營業利益） | C56: US$B | E56: =0.289259-0.153472 -> 0.135787 | G56: Verified | H56: https://www.sec.gov/Archives/edgar/data/0001736297/000173629726000033/q226exhibit991.htm：non-GAAP 營業利益 153,472 千美元（營業利益率 39.1%） | I56: https://www.marketbeat.com/instant-alerts/astera-labs-q2-earnings-call-highlights-2026-08-04/：營業費用 1.358 億美元
A57: q2_ninc | B57: 2Q26 利息與其他收益（non-GAAP；扣除 150 萬美元公允價值調整） | C57: US$B | E57: =0.013577-0.0015 -> 0.012077 | G57: Verified | H57: https://www.sec.gov/Archives/edgar/data/0001736297/000173629726000033/q226exhibit991.htm：GAAP 13,577 千美元；non-GAAP 調整 −1,500 | I57: https://www.marketbeat.com/instant-alerts/astera-labs-q2-earnings-call-highlights-2026-08-04/：利息與其他收益 1,210 萬美元
A58: q2_ni | B58: 2Q26 non-GAAP 淨利 | C58: US$B | E58: 0.145816 | G58: Verified | H58: https://www.sec.gov/Archives/edgar/data/0001736297/000173629726000033/q226exhibit991.htm：145,816 千美元 | I58: https://futurumgroup.com/insights/astera-labs-q2-fy-2026-earnings-pull-scorpio-switch-leadership-forward/：1.458 億美元
A59: q2_sh | B59: 2Q26 稀釋股數 | C59: 十億股 | E59: 0.18334 | G59: Verified | H59: https://www.sec.gov/Archives/edgar/data/0001736297/000173629726000033/q226exhibit991.htm：183,340 千股 | I59: —
A60: q2_eps | B60: 2Q26 non-GAAP 稀釋 EPS | C60: US$ | E60: 0.8 | G60: Verified | H60: https://www.sec.gov/Archives/edgar/data/0001736297/000173629726000033/q226exhibit991.htm：0.80（GAAP 0.83，含所得稅利益） | I60: https://futurumgroup.com/insights/astera-labs-q2-fy-2026-earnings-pull-scorpio-switch-leadership-forward/：0.80
A61: q3_rev | B61: 3Q26 營收指引（中點；截至 2026-09-30） | C61: US$B | D61: 0.54 | E61: 0.55 | F61: 0.56 | G61: Interested-party | H61: https://www.sec.gov/Archives/edgar/data/0001736297/000173629726000033/q226exhibit991.htm：5.40–5.60 億美元（Scorpio X 320 通道交換晶片量產） | I61: https://www.marketbeat.com/instant-alerts/astera-labs-q2-earnings-call-highlights-2026-08-04/：同值，中點季增約 40%
A62: q3_gm | B62: 3Q26 non-GAAP 毛利率指引 | C62: % | D62: 0.715 | E62: 0.72 | F62: 0.725 | G62: Interested-party | H62: https://www.sec.gov/Archives/edgar/data/0001736297/000173629726000033/q226exhibit991.htm：約 72% | I62: https://futurumgroup.com/insights/astera-labs-q2-fy-2026-earnings-pull-scorpio-switch-leadership-forward/：硬體比重較高的交換晶片占比上升
A63: q3_opx | B63: 3Q26 non-GAAP 營業費用指引（中點） | C63: US$B | D63: 0.156 | E63: 0.158 | F63: 0.16 | G63: Interested-party | H63: https://www.sec.gov/Archives/edgar/data/0001736297/000173629726000033/q226exhibit991.htm：1.56–1.60 億美元 | I63: https://www.marketbeat.com/instant-alerts/astera-labs-q2-earnings-call-highlights-2026-08-04/：同值
A64: q3_eps | B64: 3Q26 non-GAAP EPS 指引（中點） | C64: US$ | D64: 1.16 | E64: 1.185 | F64: 1.21 | G64: Interested-party | H64: https://www.sec.gov/Archives/edgar/data/0001736297/000173629726000033/q226exhibit991.htm：1.16–1.21 | I64: https://www.marketbeat.com/instant-alerts/astera-labs-q2-earnings-call-highlights-2026-08-04/：同值；稀釋股數約 1.85 億股
A65: q3_sh | B65: 3Q26 稀釋股數指引 | C65: 十億股 | E65: 0.185 | G65: Interested-party | H65: https://www.sec.gov/Archives/edgar/data/0001736297/000173629726000033/q226exhibit991.htm：約 1.85 億股 | I65: —
A66: tx_26 | B66: FY2026 下半年 non-GAAP 稅率 | C66: % | D66: 0.11 | E66: 0.12 | F66: 0.13 | G66: Interested-party | H66: https://www.sec.gov/Archives/edgar/data/0001736297/000173629726000033/q226exhibit991.htm：3Q26 non-GAAP 稅率約 12% | I66: 1H26 推導約 11%
A67: q_oth | B67: 3Q26、4Q26 每季利息與其他收益 | C67: US$B | D67: 0.011 | E67: 0.0125 | F67: 0.014 | G67: Assumed | H67: 2Q26 0.0121；現金與有價證券 12.5 億美元（2026-06-30） | I67: —
A68: g_q4 | B68: 4Q26 營收季增 | C68: % | D68: 0.05 | E68: 0.15 | F68: 0.3 | G68: Assumed | H68: 公司未給 4Q26 指引；Scorpio X 第二家以後客戶 2026 年底起出貨（公司） | I68: https://finance.yahoo.com/quote/ALAB/analysis/：共識 4Q26 營收 6.557 億美元（18 家；6.09–7.38；Interested-party，不作校準）
A69: gm_q4 | B69: 4Q26 non-GAAP 毛利率 | C69: % | D69: 0.7 | E69: 0.715 | F69: 0.725 | G69: Assumed | H69: 3Q26 指引 72%；公司長期目標 70%（公司，MarketBeat 轉述） | I69: —
A70: q4_opx | B70: 4Q26 non-GAAP 營業費用 | C70: US$B | D70: 0.162 | E70: 0.168 | F70: 0.176 | G70: Assumed | H70: 3Q26 指引中點 1.58 億美元；2Q→3Q 季增約 16% | I70: —
A71: q4_sh | B71: 4Q26 稀釋股數 | C71: 十億股 | D71: 0.1855 | E71: 0.1865 | F71: 0.188 | G71: Assumed | H71: 3Q26 約 1.85 億股；Amazon 認股權證最多 326 萬股（TIKR 轉述，Interested-party） | I71: —
A72: E. FY2024、FY2025 實績（non-GAAP）與股東權益
A73: a24_rev_in | B73: FY2024 營收 | C73: US$B | E73: 0.39629 | G73: Verified | H73: https://www.sec.gov/Archives/edgar/data/1736297/000173629726000005/q425exhibit991.htm | I73: https://uk.marketscreener.com/quote/stock/ASTERA-LABS-INC-167508773/finances/：同值（396.3 百萬美元）
A74: a24_gp_in | B74: FY2024 non-GAAP 毛利 | C74: US$B | E74: 0.303544 | G74: Verified | H74: https://www.sec.gov/Archives/edgar/data/1736297/000173629726000005/q425exhibit991.htm：non-GAAP 毛利率 76.6% | I74: —
A75: a24_opx_in | B75: FY2024 non-GAAP 營業費用（＝毛利 − 營業利益） | C75: US$B | E75: =0.303544-0.119594 -> 0.18395 | G75: Verified | H75: https://www.sec.gov/Archives/edgar/data/1736297/000173629726000005/q425exhibit991.htm：non-GAAP 營業利益 119,594 千美元 | I75: —
A76: a24_ninc_in | B76: FY2024 利息收入 | C76: US$B | E76: 0.034288 | G76: Verified | H76: https://www.sec.gov/Archives/edgar/data/1736297/000173629726000005/q425exhibit991.htm | I76: —
A77: a24_ni_in | B77: FY2024 non-GAAP 淨利 | C77: US$B | E77: 0.143329 | G77: Verified | H77: https://www.sec.gov/Archives/edgar/data/1736297/000173629726000005/q425exhibit991.htm | I77: 非 GAAP 擬制稀釋股數 168,913 千股（2024-03 上市前後）；GAAP 淨損 83,421
A78: a24_sh_in | B78: FY2024 non-GAAP 稀釋股數 | C78: 十億股 | E78: 0.168913 | G78: Verified | H78: https://www.sec.gov/Archives/edgar/data/1736297/000173629726000005/q425exhibit991.htm | I78: —
A79: a24_eps_in | B79: FY2024 non-GAAP 稀釋 EPS | C79: US$ | E79: 0.84 | G79: Verified | H79: https://www.sec.gov/Archives/edgar/data/1736297/000173629726000005/q425exhibit991.htm：0.84（GAAP −0.64） | I79: —
A80: a25_rev_in | B80: FY2025 營收 | C80: US$B | E80: 0.852525 | G80: Verified | H80: https://www.sec.gov/Archives/edgar/data/1736297/000173629726000005/q425exhibit991.htm | I80: https://uk.marketscreener.com/quote/stock/ASTERA-LABS-INC-167508773/finances/：同值（852.5 百萬美元）
A81: a25_gp_in | B81: FY2025 non-GAAP 毛利 | C81: US$B | E81: 0.646384 | G81: Verified | H81: https://www.sec.gov/Archives/edgar/data/1736297/000173629726000005/q425exhibit991.htm：non-GAAP 毛利率 75.8% | I81: —
A82: a25_opx_in | B82: FY2025 non-GAAP 營業費用（＝毛利 − 營業利益） | C82: US$B | E82: =0.646384-0.334406 -> 0.311978 | G82: Verified | H82: https://www.sec.gov/Archives/edgar/data/1736297/000173629726000005/q425exhibit991.htm：non-GAAP 營業利益 334,406 千美元 | I82: —
A83: a25_ninc_in | B83: FY2025 利息收入 | C83: US$B | E83: 0.04473 | G83: Verified | H83: https://www.sec.gov/Archives/edgar/data/1736297/000173629726000005/q425exhibit991.htm | I83: —
A84: a25_ni_in | B84: FY2025 non-GAAP 淨利 | C84: US$B | E84: 0.331015 | G84: Verified | H84: https://www.sec.gov/Archives/edgar/data/1736297/000173629726000005/q425exhibit991.htm | I84: GAAP 淨利 219,134、GAAP 稀釋 EPS 1.22
A85: a25_sh_in | B85: FY2025 non-GAAP 稀釋股數 | C85: 十億股 | E85: 0.179551 | G85: Verified | H85: https://www.sec.gov/Archives/edgar/data/1736297/000173629726000005/q425exhibit991.htm | I85: —
A86: a25_eps_in | B86: FY2025 non-GAAP 稀釋 EPS | C86: US$ | E86: 1.84 | G86: Verified | H86: https://www.sec.gov/Archives/edgar/data/1736297/000173629726000005/q425exhibit991.htm：1.84（GAAP 1.22） | I86: —
A87: a25_ni_h1 | B87: 1H25 non-GAAP 淨利（近 12 月 ROE 用） | C87: US$B | E87: 0.13765 | G87: Verified | H87: https://www.sec.gov/Archives/edgar/data/0001736297/000173629726000033/q226exhibit991.htm：1H25 137,650 千美元 | I87: —
A88: eq_23 | B88: 股東權益 2023-12-31 | C88: US$B | E88: 0.15743 | G88: Verified | H88: https://stockanalysis.com/stocks/alab/financials/balance-sheet/ | I88: 上市前（2024-03 IPO）
A89: eq_24 | B89: 股東權益 2024-12-31 | C89: US$B | E89: 0.9648 | G89: Verified | H89: https://stockanalysis.com/stocks/alab/financials/balance-sheet/ | I89: —
A90: eq_25 | B90: 股東權益 2025-12-31 | C90: US$B | E90: 1.363634 | G90: Verified | H90: https://stockanalysis.com/stocks/alab/financials/balance-sheet/ | I90: https://www.sec.gov/Archives/edgar/data/0001736297/000173629726000033/q226exhibit991.htm：1,363,634 千美元
A91: eq_q2 | B91: 股東權益 2026-06-30 | C91: US$B | E91: 1.725704 | G91: Verified | H91: https://stockanalysis.com/stocks/alab/financials/balance-sheet/ | I91: https://www.sec.gov/Archives/edgar/data/0001736297/000173629726000033/q226exhibit991.htm：1,725,704 千美元
A92: G. 營業費用、毛利率、稅率、股數（FY2027 起）
A93: phi | B93: 營業費用成長對營收成長的彈性 | C93: x | D93: 0.4 | E93: =Q!B28 -> 0.72567513 | F93: 0.9 | G93: Derived | H93: FY2026 錨點營業費用年增 ÷ 營收年增（Q 頁） | I93: FY2025：69.6% ÷ 115.1% ＝ 0.60（推導）
A94: opx_adj | B94: 營業費用額外占營收比（Sens 用；基準 0） | C94: pt | D94: -0.01 | E94: 0 | F94: 0.02 | G94: Assumed | H94: 無 | I94: Sens 用 +2 個百分點
A95: gm_27 | B95: non-GAAP 毛利率 FY2027 | C95: % | D95: 0.66 | E95: 0.7 | F95: 0.72 | G95: Assumed | H95: https://www.marketbeat.com/instant-alerts/astera-labs-q2-earnings-call-highlights-2026-08-04/：長期毛利率目標 70%（公司） | I95: FY2024 76.6%、FY2025 75.8%、3Q26 指引 72%（交換晶片硬體占比上升）
A96: gm_28 | B96: non-GAAP 毛利率 FY2028 | C96: % | D96: 0.65 | E96: 0.695 | F96: 0.72 | G96: Assumed | H96: 同上 | I96: —
A97: gm_29 | B97: non-GAAP 毛利率 FY2029 | C97: % | D97: 0.64 | E97: 0.69 | F97: 0.72 | G97: Assumed | H97: 同上；競爭者增加時價格下壓 | I97: —
A98: oth_f | B98: 利息與其他收益（每年，FY2027 起） | C98: US$B | D98: 0.03 | E98: 0.05 | F98: 0.07 | G98: Assumed | H98: 現金與有價證券 12.5 億美元（2026-06-30）× 約 4% | I98: —
A99: tx_27 | B99: non-GAAP 有效稅率 FY2027 | C99: % | D99: 0.1 | E99: 0.12 | F99: 0.15 | G99: Assumed | H99: https://www.sec.gov/Archives/edgar/data/0001736297/000173629726000033/q226exhibit991.htm：non-GAAP 稅率約 12%（公司） | I99: FY2025 推導 12.7%
A100: tx_28 | B100: non-GAAP 有效稅率 FY2028 | C100: % | D100: 0.1 | E100: 0.12 | F100: 0.15 | G100: Assumed | H100: 同上 | I100: —
A101: tx_29 | B101: non-GAAP 有效稅率 FY2029 | C101: % | D101: 0.1 | E101: 0.12 | F101: 0.15 | G101: Assumed | H101: 同上 | I101: —
A102: sh_g | B102: 股數年變動（FY2027 起） | C102: % | D102: 0.005 | E102: 0.015 | F102: 0.03 | G102: Assumed | H102: FY2025→1H26 稀釋股數 179.6→183.3 百萬股；1H26 股票薪酬 1.13 億美元 | I102: 買回計畫：未找到
A103: mf | B103: 非 NVIDIA scale-up 交換晶片市場係數（Sens 用；FY2027 起） | C103: x | D103: 0.8 | E103: 1 | F103: 1.2 | G103: Assumed | H103: 網通模型 CY2027 非 NVIDIA scale-up 交換 +279%（AMD 改機架）、CY2028 +23%、CY2029 +15% | I103: ±20%（NVLink Fusion、乙太網路 scale-up 搶占 UALink／PCIe 架構）
A104: g2n | B104: GAAP EPS ÷ non-GAAP EPS（規則值換算用） | C104: x | D104: 0.62 | E104: 0.7 | F104: 0.78 | G104: Assumed | H104: https://www.sec.gov/Archives/edgar/data/1736297/000173629726000005/q425exhibit991.htm：FY2025 GAAP 1.22 ÷ non-GAAP 1.84 ＝ 0.66 | I104: https://uk.marketscreener.com/quote/stock/ASTERA-LABS-INC-167508773/finances/：FY2027 共識 GAAP 4.75 ÷ Yahoo non-GAAP 6.40 ＝ 0.74（Interested-party）
A105: H. 共識、市場資料（只作 Recon 對帳，不作校準）
A106: cons_q3 | B106: 共識 3Q26 營收 | C106: US$B | E106: 0.5508 | G106: Interested-party | H106: https://finance.yahoo.com/quote/ALAB/analysis/（18 家；5.457–5.570） | I106: —
A107: cons_q4 | B107: 共識 4Q26 營收 | C107: US$B | E107: 0.65571 | G107: Interested-party | H107: https://finance.yahoo.com/quote/ALAB/analysis/（18 家；6.091–7.379） | I107: —
A108: cons_rev26 | B108: 共識 FY2026 營收 | C108: US$B | E108: 1.91 | G108: Interested-party | H108: https://finance.yahoo.com/quote/ALAB/analysis/（21 家；1.86–1.99） | I108: https://stockanalysis.com/stocks/alab/forecast/：1.91（21 家）
A109: cons_eps26 | B109: 共識 FY2026 non-GAAP EPS | C109: US$ | E109: 4.03 | G109: Interested-party | H109: https://finance.yahoo.com/quote/ALAB/analysis/（21 家；3.90–4.33） | I109: https://stockanalysis.com/stocks/alab/forecast/：4.03
A110: cons_rev27 | B110: 共識 FY2027 營收 | C110: US$B | E110: 2.98 | G110: Interested-party | H110: https://finance.yahoo.com/quote/ALAB/analysis/（24 家；2.19–3.68） | I110: https://uk.marketscreener.com/quote/stock/ASTERA-LABS-INC-167508773/finances/：2.976
A111: cons_eps27 | B111: 共識 FY2027 non-GAAP EPS | C111: US$ | E111: 6.4 | G111: Interested-party | H111: Yahoo Finance（網址見 Sources）（23 家；4.35–8.80） | I111: 第二來源（non-GAAP）：未找到；MarketScreener GAAP 4.749
A112: cons_rev28 | B112: 共識 FY2028 營收 | C112: US$B | E112: 3.835 | G112: Interested-party | H112: MarketScreener（網址見 Sources）（26 家） | I112: 第二來源：未找到
A113: cons_eps28 | B113: 共識 FY2028 non-GAAP EPS（推導＝MarketScreener GAAP 6.36 × FY2027 non-GAAP ÷ GAAP） | C113: US$ | E113: =6.36*cons_eps27/4.749 -> 8.5710676 | G113: Derived | H113: MarketScreener（網址見 Sources）：FY2028 GAAP EPS 6.36、FY2027 4.749（Interested-party） | I113: non-GAAP FY2028 共識：未找到（stockanalysis 需付費）
...

Sheet Q
A1: Q — 實績與 FY2026 錨點（十億美元；EPS 為美元；股數為十億股；non-GAAP）。藍字＝輸入；黑字＝公式。會計年度＝日曆年
A2: FY2026 錨點＝1Q26、2Q26 實績＋3Q26 指引中點（營收 5.50 億美元、毛利率 72%、營業費用 1.58 億美元）＋4Q26（季增 g_q4、毛利率 gm_q4，Assumed）。產品線拆分（Scorpio X）為假設，PCIe 與訊號調節為殘差。3Q26 財報（2026-11-03）公布後以實績取代 3Q
A3: 項目 | B3: FY2024A | C3: FY2025A | D3: 1Q26（實績） | E3: 2Q26（實績） | F3: 3Q26（指引） | G3: 4Q26（假設） | H3: FY2026 錨點 | I3: 標記 | J3: 說明
A4: 營收 | B4: =a24_rev_in -> 0.39629 | C4: =a25_rev_in -> 0.852525 | D4: =q1_rev -> 0.308361 | E4: =q2_rev -> 0.3924 | F4: =q3_rev -> 0.55 | G4: =F4*(1+g_q4) -> 0.6325 | H4: =SUM(D4:G4) -> 1.883261 | I4: Verified／Interested-party（指引）／Assumed | J4: 4Q26＝3Q26 ×（1＋g_q4）
A5: 毛利（non-GAAP） | B5: =a24_gp_in -> 0.303544 | C5: =a25_gp_in -> 0.646384 | D5: =q1_gp -> 0.23564 | E5: =q2_gp -> 0.289259 | F5: =F4*q3_gm -> 0.396 | G5: =G4*gm_q4 -> 0.4522375 | H5: =SUM(D5:G5) -> 1.3731365 | I5: Verified／Derived
A6: 毛利率 | B6: =B5/B4 -> 0.76596432 | C6: =C5/C4 -> 0.75819947 | D6: =D5/D4 -> 0.76416927 | E6: =E5/E4 -> 0.73715341 | F6: =F5/F4 -> 0.72 | G6: =G5/G4 -> 0.715 | H6: =H5/H4 -> 0.72912703 | I6: Derived
A7: 營業費用（non-GAAP） | B7: =a24_opx_in -> 0.18395 | C7: =a25_opx_in -> 0.311978 | D7: =q1_opx -> 0.123911 | E7: =q2_opx -> 0.135787 | F7: =q3_opx -> 0.158 | G7: =q4_opx -> 0.168 | H7: =SUM(D7:G7) -> 0.585698 | I7: Verified／Interested-party（指引）／Assumed
A8: 營業費用率 | B8: =B7/B4 -> 0.46418027 | C8: =C7/C4 -> 0.36594587 | D8: =D7/D4 -> 0.40183746 | E8: =E7/E4 -> 0.3460423 | F8: =F7/F4 -> 0.28727273 | G8: =G7/G4 -> 0.26561265 | H8: =H7/H4 -> 0.31100203 | I8: Derived
A9: 營業利益（non-GAAP） | B9: =B5-B7 -> 0.119594 | C9: =C5-C7 -> 0.334406 | D9: =D5-D7 -> 0.111729 | E9: =E5-E7 -> 0.153472 | F9: =F5-F7 -> 0.238 | G9: =G5-G7 -> 0.2842375 | H9: =H5-H7 -> 0.7874385 | I9: Derived
A10: 利息與其他收益 | B10: =a24_ninc_in -> 0.034288 | C10: =a25_ninc_in -> 0.04473 | D10: =q1_ninc -> 0.011581 | E10: =q2_ninc -> 0.012077 | F10: =q_oth -> 0.0125 | G10: =q_oth -> 0.0125 | H10: =SUM(D10:G10) -> 0.048658 | I10: Verified／Assumed
A11: 稅前利益 | B11: =B9+B10 -> 0.153882 | C11: =C9+C10 -> 0.379136 | D11: =D9+D10 -> 0.12331 | E11: =E9+E10 -> 0.165549 | F11: =F9+F10 -> 0.2505 | G11: =G9+G10 -> 0.2967375 | H11: =H9+H10 -> 0.8360965 | I11: Derived
A12: 所得稅（non-GAAP） | B12: =B11-a24_ni_in -> 0.010553 | C12: =C11-a25_ni_in -> 0.048121 | D12: =D11-q1_ni -> 0.013241 | E12: =E11-q2_ni -> 0.019733 | F12: =F11*tx_26 -> 0.03006 | G12: =G11*tx_26 -> 0.0356085 | H12: =SUM(D12:G12) -> 0.0986425 | I12: Derived | J12: 實績＝稅前 − 淨利（推導）
A13: 有效稅率 | B13: =B12/B11 -> 0.068578521 | C13: =C12/C11 -> 0.12692279 | D13: =D12/D11 -> 0.10737977 | E13: =E12/E11 -> 0.11919734 | F13: =F12/F11 -> 0.12 | G13: =G12/G11 -> 0.12 | H13: =H12/H11 -> 0.1179798 | I13: Derived
A14: 淨利（non-GAAP） | B14: =a24_ni_in -> 0.143329 | C14: =a25_ni_in -> 0.331015 | D14: =q1_ni -> 0.110069 | E14: =q2_ni -> 0.145816 | F14: =F11-F12 -> 0.22044 | G14: =G11-G12 -> 0.261129 | H14: =SUM(D14:G14) -> 0.737454 | I14: Verified／Derived
A15: 淨利率 | B15: =B14/B4 -> 0.36167705 | C15: =C14/C4 -> 0.388276 | D15: =D14/D4 -> 0.35694851 | E15: =E14/E4 -> 0.37160041 | F15: =F14/F4 -> 0.4008 | G15: =G14/G4 -> 0.41285217 | H15: =H14/H4 -> 0.39158354 | I15: Derived
A16: 稀釋股數（non-GAAP） | B16: =a24_sh_in -> 0.168913 | C16: =a25_sh_in -> 0.179551 | D16: =q1_sh -> 0.181157 | E16: =q2_sh -> 0.18334 | F16: =q3_sh -> 0.185 | G16: =q4_sh -> 0.1865 | H16: =AVERAGE(D16:G16) -> 0.18399925 | I16: Verified／Assumed | J16: 全年＝四季平均
A17: EPS（non-GAAP） | B17: =B14/B16 -> 0.84853741 | C17: =C14/C16 -> 1.8435709 | D17: =D14/D16 -> 0.607589 | E17: =E14/E16 -> 0.79533108 | F17: =F14/F16 -> 1.1915676 | G17: =G14/G16 -> 1.4001555 | H17: =H14/H16 -> 4.0079185 | I17: Derived | J17: 公司揭露：FY2024 0.84、FY2025 1.84、1Q26 0.61、2Q26 0.80；3Q26 指引 1.16–1.21
A18: Scorpio X 營收 | C18: =x_25 -> 0 | H18: =x_26 -> 0.38 | I18: Assumed
A19: PCIe 與訊號調節（Aries、Scorpio P、Taurus、Leo）＝營收 − Scorpio X（殘差） | C19: =C4-C18 -> 0.852525 | H19: =H4-H18 -> 1.503261 | I19: Derived
A20: Scorpio X ÷ 營收 | C20: =C18/C4 -> 0 | H20: =H18/H4 -> 0.20177766 | I20: Derived | J20: 公司：Scorpio 3Q26 成為最大產品線、X 超過 P
A23: FY2026 錨點的檢查（參考；校準未使用共識）
A24: FY2026 營收 ÷ 共識 − 1 | B24: =H4/cons_rev26-1 -> -0.013999476
A25: FY2026 EPS ÷ 共識 − 1 | B25: =H17/cons_eps26-1 -> -0.0054792778
A26: FY2026 營收年增 | B26: =H4/C4-1 -> 1.209039
A27: FY2026 營業費用年增 | B27: =H7/C7-1 -> 0.87736956
A28: 營業費用彈性（營業費用年增 ÷ 營收年增；In 頁 phi 的依據） | B28: =B27/B26 -> 0.72567513
A29: 2Q26 EPS（模型）vs 公司揭露 0.80 | B29: =E17/q2_eps-1 -> -0.0058361514
A30: 3Q26 EPS（模型）vs 指引中點 1.185 | B30: =F17/q3_eps-1 -> 0.0055422511
A31: 4Q26 營收 ÷ 共識 − 1 | B31: =G4/cons_q4-1 -> -0.035396746

Sheet Units
A1: Units — Astera Labs 在非 NVIDIA scale-up 交換晶片（Scorpio X）與 PCIe／CXL／AEC 的份額（本專案權威，規則第 13 條）。市場取自 markets/network（加速器顆數 × 每顆內容；日曆年＝會計年度）
A3: 項目 | B3: 單位 | C3: FY2026（錨點） | D3: FY2027 | E3: FY2028 | F3: FY2029 | G3: 說明
A4: scale-up 交換晶片市場合計（含 NVIDIA NVLink；情境 A） | B4: US$B | C4: =msu_26 -> 18.2761 | D4: =msu_27 -> 37.4157 | E4: =msu_28 -> 44.9835 | F4: =msu_29 -> 51.2458 | G4: markets/network Mkt 頁「scale-up 交換晶片」
A5: 其中非 NVIDIA、非 TPU（Scorpio X 可服務市場） | B5: US$B | C5: =PL!D63 -> 2.025 | D5: =PL!E63 -> 7.701 | E5: =PL!F63 -> 9.468 | F5: =PL!G63 -> 10.8882 | G5: AMD、Trainium、其他 ASIC
A6: Astera Scorpio X 營收（情境 A） | B6: US$B | C6: =PL!D67 -> 0.38 | D6: =PL!E67 -> 1.4451259 | E6: =PL!F67 -> 1.9543822 | F6: =PL!G67 -> 2.3497004 | G6: FY2026 為假設（公司未揭露）
A7: Scorpio X 有效份額（÷ 非 NVIDIA scale-up 交換晶片） | B7: % | C7: =PL!D66 -> 0.18765432 | D7: =PL!E66 -> 0.18765432 | E7: =PL!F66 -> 0.20641975 | F7: =PL!G66 -> 0.21580247 | G7: FY2026 校準
A8: Scorpio X ÷ scale-up 交換晶片合計 | B8: % | C8: =PL!D67/C4 -> 0.020792182 | D8: =PL!E67/D4 -> 0.038623517 | E8: =PL!F67/E4 -> 0.043446646 | F8: =PL!G67/F4 -> 0.045851571 | G8: 含 NVIDIA NVLink 的分母
A9: Scorpio X 每顆非 NVIDIA 加速器營收（美元／顆） | B9: US$/顆 | C9: =PL!D67*1000/nnu_26 -> 101.33333 | D9: =PL!E67*1000/nnu_27 -> 170.01481 | E9: =PL!F67*1000/nnu_28 -> 195.43822 | F9: =PL!G67*1000/nnu_29 -> 204.32178 | G9: 公司：現有設計案每顆加速器內容逾 1,000 美元（採用該平台者）
A10: AI 加速器顆數（情境 A） | B10: 百萬顆 | C10: =PL!D69 -> 15.2 | D10: =PL!E69 -> 23.7 | E10: =PL!F69 -> 26.5 | F10: =PL!G69 -> 30.15 | G10: markets/network Units 頁
A11: Astera PCIe 與訊號調節營收（情境 A） | B11: US$B | C11: =PL!D73 -> 1.503261 | D11: =PL!E73 -> 1.8751203 | E11: =PL!F73 -> 1.9656127 | F11: =PL!G73 -> 2.0872581 | G11: FY2026 為錨點殘差
A12: PCIe 等每顆加速器營收（美元／顆） | B12: US$/顆 | C12: =PL!D73*1000/PL!D69 -> 98.89875 | D12: =PL!E73*1000/PL!E69 -> 79.119 | E12: =PL!F73*1000/PL!F69 -> 74.174063 | F12: =PL!G73*1000/PL!G69 -> 69.229125 | G12: ＝c_pcie × 有效份額
A13: PCIe 等有效份額（÷ 顆數 × c_pcie） | B13: % | C13: =PL!D73/PL!D70 -> 0.395595 | D13: =PL!E73/PL!E70 -> 0.316476 | E13: =PL!F73/PL!F70 -> 0.29669625 | F13: =PL!G73/PL!G70 -> 0.2769165 | G13: c_pcie 250 美元／顆（Assumed）
A14: Astera 營收 ÷ AI IT 資本支出 | B14: % | C14: =PL!D75/itc_26 -> 0.0024086536 | D14: =PL!E75/itc_27 -> 0.0021210887 | E14: =PL!F75/itc_28 -> 0.0019755411 | F14: =PL!G75/itc_29 -> 0.001962917 | G14: markets/network 的 AI IT 資本支出
A16: 讀法：Scorpio X 的 FY2026 營收為假設（公司未揭露產品線），PCIe 等為殘差；兩者的份額相對值是 Assumed，是最需要每季檢查的輸入。每顆加速器營收 ＝ Astera 營收 ÷ 顆數，可直接與公司「每顆逾 1,000 美元」的說法對照。

Sheet PL
A1: PL — Astera Labs 損益（US$B；non-GAAP）。FY2025A 實績、FY2026 錨點（1Q26、2Q26 實績＋3Q26 指引＋4Q26 假設），FY2027 起為模型。會計年度＝日曆年。三情境各一個完整推導區塊（本頁下方），頂端為摘要。FY2026–FY2027 三情境相同（顆數係數 CY2028 起），差異在 FY2028 起
A2: 灰底＝FY2030–FY2032 收斂法，非驅動因子推導（上游市場層只到 2029）：營收年增由 FY2029 線性收斂到 fade_g（A＝tp_g＋2pt、B＝tp_g、C＝tp_g−2pt），淨利率由 FY2029 線性收斂到 fade_m（In 頁 K 節），FY2032 達到；股數依 sh_g
A3: 情境／項目 | B3: 單位 | C3: FY2025A | D3: FY2026（錨點） | E3: FY2027 | F3: FY2028 | G3: FY2029 | H3: FY2030（收斂） | I3: FY2031（收斂） | J3: FY2032（收斂） | K3: 說明
A4: 情境 A
A5: 營收 | B5: US$B | C5: =C75 -> 0.852525 | D5: =D75 -> 1.883261 | E5: =E75 -> 3.3202462 | F5: =F75 -> 3.9199949 | G5: =G75 -> 4.4369586 | H5: =H75 -> 4.9157912 | I5: =I75 -> 5.3285188 | J5: =J75 -> 5.6482299
A6: 營收年增 | B6: % | D6: =D76 -> 1.209039 | E6: =E76 -> 0.76303031 | F6: =F76 -> 0.18063379 | G6: =G76 -> 0.13187866 | H6: =H76 -> 0.10791911 | I6: =I76 -> 0.083959554 | J6: =J76 -> 0.06
A7: Scorpio X 營收 | B7: US$B | C7: =C67 -> 0 | D7: =D67 -> 0.38 | E7: =E67 -> 1.4451259 | F7: =F67 -> 1.9543822 | G7: =G67 -> 2.3497004
A8: PCIe 與訊號調節營收 | B8: US$B | C8: =C73 -> 0.852525 | D8: =D73 -> 1.503261 | E8: =E73 -> 1.8751203 | F8: =F73 -> 1.9656127 | G8: =G73 -> 2.0872581
A9: 毛利率 | B9: % | C9: =C79 -> 0.75819947 | D9: =D79 -> 0.72912703 | E9: =E79 -> 0.7 | F9: =F79 -> 0.695 | G9: =G79 -> 0.69
A10: 營業利益率 | B10: % | C10: =C84 -> 0.3922536 | D10: =D84 -> 0.418125 | E10: =E84 -> 0.42592211 | F10: =F84 -> 0.43242542 | G10: =G84 -> 0.43581795
A11: 淨利率 | B11: % | C11: =C88 -> 0.388276 | D11: =D88 -> 0.39158354 | E11: =E88 -> 0.38806349 | F11: =F88 -> 0.39175888 | G11: =G88 -> 0.3934365 | H11: =H88 -> 0.3934365 | I11: =I88 -> 0.3934365 | J11: =J88 -> 0.3934365
A12: 淨利 | B12: US$B | C12: =C87 -> 0.331015 | D12: =D87 -> 0.737454 | E12: =E87 -> 1.2884663 | F12: =F87 -> 1.5356928 | G12: =G87 -> 1.7456614 | H12: =H87 -> 1.9340517 | I12: =I87 -> 2.0964338 | J12: =J87 -> 2.2222198
A13: EPS（non-GAAP） | B13: US$ | C13: =C90 -> 1.8435709 | D13: =D90 -> 4.0079185 | E13: =E90 -> 6.8990768 | F13: =F90 -> 8.1013279 | G13: =G90 -> 9.072894 | H13: =H90 -> 9.9034804 | I13: =I90 -> 10.576327 | J13: =J90 -> 11.045229
A14: EPS 年增 | B14: % | D14: =D91 -> 1.1739975 | E14: =E91 -> 0.72136153 | F14: =F91 -> 0.17426261 | G14: =G91 -> 0.11992677 | H14: =H91 -> 0.09154592 | I14: =I91 -> 0.067940448 | J14: =J91 -> 0.044334975
A16: 情境 B
A17: 營收 | B17: US$B | C17: =C109 -> 0.852525 | D17: =D109 -> 1.883261 | E17: =E109 -> 3.3202462 | F17: =F109 -> 3.1359959 | G17: =G109 -> 3.7714148 | H17: =H109 -> 4.3311457 | I17: =I109 -> 4.7391701 | J17: =J109 -> 4.9287369
A18: 營收年增 | B18: % | D18: =D110 -> 1.209039 | E18: =E110 -> 0.76303031 | F18: =F110 -> -0.05549297 | G18: =G110 -> 0.20262108 | H18: =H110 -> 0.14841405 | I18: =I110 -> 0.094207027 | J18: =J110 -> 0.04
A19: Scorpio X 營收 | B19: US$B | C19: =C101 -> 0 | D19: =D101 -> 0.38 | E19: =E101 -> 1.4451259 | F19: =F101 -> 1.5635058 | G19: =G101 -> 1.9972454
A20: PCIe 與訊號調節營收 | B20: US$B | C20: =C107 -> 0.852525 | D20: =D107 -> 1.503261 | E20: =E107 -> 1.8751203 | F20: =F107 -> 1.5724901 | G20: =G107 -> 1.7741694
A21: 毛利率 | B21: % | C21: =C113 -> 0.75819947 | D21: =D113 -> 0.72912703 | E21: =E113 -> 0.7 | F21: =F113 -> 0.695 | G21: =G113 -> 0.69
A22: 營業利益率 | B22: % | C22: =C118 -> 0.3922536 | D22: =D118 -> 0.418125 | E22: =E118 -> 0.42592211 | F22: =F118 -> 0.40481911 | G22: =G118 -> 0.41323099
A23: 淨利率 | B23: % | C23: =C122 -> 0.388276 | D23: =D122 -> 0.39158354 | E23: =E122 -> 0.38806349 | F23: =F122 -> 0.37027145 | G23: =G122 -> 0.37530998 | H23: =H122 -> 0.36279965 | I23: =I122 -> 0.35028932 | J23: =J122 -> 0.33777899
A24: 淨利 | B24: US$B | C24: =C121 -> 0.331015 | D24: =D121 -> 0.737454 | E24: =E121 -> 1.2884663 | F24: =F121 -> 1.1611697 | G24: =G121 -> 1.4154496 | H24: =H121 -> 1.5713382 | I24: =I121 -> 1.6600807 | J24: =J121 -> 1.6648238
A25: EPS（non-GAAP） | B25: US$ | C25: =C124 -> 1.8435709 | D25: =D124 -> 4.0079185 | E25: =E124 -> 6.8990768 | F25: =F124 -> 6.125585 | G25: =G124 -> 7.3566524 | H25: =H124 -> 8.0461743 | I25: =I124 -> 8.3749636 | J25: =J124 -> 8.2747705
A26: EPS 年增 | B26: % | D26: =D125 -> 1.1739975 | E26: =E125 -> 0.72136153 | F26: =F125 -> -0.11211525 | G26: =G125 -> 0.2009714 | H26: =H125 -> 0.09372767 | I26: =I125 -> 0.040862808 | J26: =J125 -> -0.011963406
A28: 情境 C
A29: 營收 | B29: US$B | C29: =C143 -> 0.852525 | D29: =D143 -> 1.883261 | E29: =E143 -> 3.3202462 | F29: =F143 -> 2.3519969 | G29: =G143 -> 2.6621751 | H29: =H143 -> 2.913979 | I29: =I143 -> 3.0809293 | J29: =J143 -> 3.1425479
A30: 營收年增 | B30: % | D30: =D144 -> 1.209039 | E30: =E144 -> 0.76303031 | F30: =F144 -> -0.29161973 | G30: =G144 -> 0.13187866 | H30: =H144 -> 0.094585776 | I30: =I144 -> 0.057292888 | J30: =J144 -> 0.02
A31: Scorpio X 營收 | B31: US$B | C31: =C135 -> 0 | D31: =D135 -> 0.38 | E31: =E135 -> 1.4451259 | F31: =F135 -> 1.1726293 | G31: =G135 -> 1.4098203
A32: PCIe 與訊號調節營收 | B32: US$B | C32: =C141 -> 0.852525 | D32: =D141 -> 1.503261 | E32: =E141 -> 1.8751203 | F32: =F141 -> 1.1793676 | G32: =G141 -> 1.2523549
A33: 毛利率 | B33: % | C33: =C147 -> 0.75819947 | D33: =D147 -> 0.72912703 | E33: =E147 -> 0.7 | F33: =F147 -> 0.695 | G33: =G147 -> 0.69
A34: 營業利益率 | B34: % | C34: =C152 -> 0.3922536 | D34: =D152 -> 0.418125 | E34: =E152 -> 0.42592211 | F34: =F152 -> 0.30809215 | G34: =G152 -> 0.31545866
A35: 淨利率 | B35: % | C35: =C156 -> 0.388276 | D35: =D156 -> 0.39158354 | E35: =E156 -> 0.38806349 | F35: =F156 -> 0.2898286 | G35: =G156 -> 0.29413146 | H35: =H156 -> 0.2745227 | I35: =I156 -> 0.25491393 | J35: =J156 -> 0.23530517
A36: 淨利 | B36: US$B | C36: =C155 -> 0.331015 | D36: =D155 -> 0.737454 | E36: =E155 -> 1.2884663 | F36: =F155 -> 0.68167597 | G36: =G155 -> 0.78302947 | H36: =H155 -> 0.79995339 | I36: =I155 -> 0.78537181 | J36: =J155 -> 0.73945777
A37: EPS（non-GAAP） | B37: US$ | C37: =C158 -> 1.8435709 | D37: =D158 -> 4.0079185 | E37: =E158 -> 6.8990768 | F37: =F158 -> 3.5960842 | G37: =G158 -> 4.0697143 | H37: =H158 -> 4.0962312 | I37: =I158 -> 3.962133 | J37: =J158 -> 3.67537
A38: EPS 年增 | B38: % | D38: =D159 -> 1.1739975 | E38: =E159 -> 0.72136153 | F38: =F159 -> -0.47875864 | G38: =G159 -> 0.1317072 | H38: =H159 -> 0.0065156557 | I38: =I159 -> -0.032736978 | J38: =J159 -> -0.0723759
A40: 核對（應為 0）：FY2026 模型營收、Scorpio X 營收、淨利 − 錨點（校準恆等式）
A41: 情境 A：營收差（US$B） | D41: =D75-a26_rev -> 0
A42: 情境 A：Scorpio X 營收 − 市場 × 有效份額（US$B） | D42: =D67-D63*D66 -> 0
A43: 情境 A：（營業利益＋其他收益）×（1 − 稅率）− 淨利錨點 | D43: =(D83+D85)*(1-D86)-a26_ni -> 0
A60: 情境 A：順利（顆數係數 1.0）
A61: 項目 | B61: 單位 | C61: FY2025A | D61: FY2026（錨點） | E61: FY2027 | F61: FY2028 | G61: FY2029 | H61: FY2030（收斂） | I61: FY2031（收斂） | J61: FY2032（收斂） | K61: 說明
A62: A. Scorpio X（D 欄＝FY2026 校準年；E–G＝FY2027–FY2029；市場為日曆年＝會計年度）
A63: 非 NVIDIA scale-up 交換晶片市場 × 情境顆數係數 | B63: US$B | D63: =msx_26 -> 2.025 | E63: =msx_27 -> 7.701 | F63: =msx_28*um28_A -> 9.468 | G63: =msx_29*um29_A -> 10.8882 | K63: AMD、Trainium、其他 ASIC 顆數 × 每顆 scale-up 交換晶片內容（網通模型）；CY2028 起乘顆數係數
A64: Astera Scorpio X 有效份額（FY2026 校準）＝ Scorpio X 營收 ÷ 市場 | B64: % | D64: =a26_x/D63 -> 0.18765432 | K64: Derived
A65: Scorpio X 有效份額相對值（÷ FY2026） | B65: x | D65: =1 -> 1 | E65: =rel_x_27 -> 1 | F65: =rel_x_28 -> 1.1 | G65: =rel_x_29 -> 1.15
A66: Scorpio X 有效份額 | B66: % | D66: =$D$64*D65 -> 0.18765432 | E66: =$D$64*E65 -> 0.18765432 | F66: =$D$64*F65 -> 0.20641975 | G66: =$D$64*G65 -> 0.21580247
A67: Scorpio X 營收 | B67: US$B | C67: =a25_x -> 0 | D67: =a26_x -> 0.38 | E67: =E63*E66 -> 1.4451259 | F67: =F63*F66 -> 1.9543822 | G67: =G63*G66 -> 2.3497004
A68: B. PCIe 與訊號調節（Aries、Scorpio P、Taurus、Leo）
A69: AI 加速器顆數 × 情境顆數係數 | B69: 百萬顆 | D69: =u_26 -> 15.2 | E69: =u_27 -> 23.7 | F69: =u_28*um28_A -> 26.5 | G69: =u_29*um29_A -> 30.15
A70: PCIe／CXL／AEC 可服務市場＝顆數 × 每顆內容（c_pcie） | B70: US$B | D70: =D69*c_pcie/1000 -> 3.8 | E70: =E69*c_pcie/1000 -> 5.925 | F70: =F69*c_pcie/1000 -> 6.625 | G70: =G69*c_pcie/1000 -> 7.5375 | K70: c_pcie 只影響份額顯示，校準時抵銷
A71: Astera PCIe 等有效份額（FY2026 校準）＝ 營收 ÷ 可服務市場 | B71: % | D71: =a26_p/D70 -> 0.395595
A72: PCIe 等有效份額 × 每顆內容相對值（÷ FY2026） | B72: x | D72: =1 -> 1 | E72: =rel_p_27 -> 0.8 | F72: =rel_p_28 -> 0.75 | G72: =rel_p_29 -> 0.7
A73: PCIe 與訊號調節營收 | B73: US$B | C73: =a25_p -> 0.852525 | D73: =a26_p -> 1.503261 | E73: =E70*$D$71*E72 -> 1.8751203 | F73: =F70*$D$71*F72 -> 1.9656127 | G73: =G70*$D$71*G72 -> 2.0872581
A74: C. 合計
A75: 營收 | B75: US$B | C75: =a25_rev -> 0.852525 | D75: =D67+D73 -> 1.883261 | E75: =E67+E73 -> 3.3202462 | F75: =F67+F73 -> 3.9199949 | G75: =G67+G73 -> 4.4369586 | H75: =G75*(1+H76) -> 4.9157912 | I75: =H75*(1+I76) -> 5.3285188 | J75: =I75*(1+J76) -> 5.6482299
A76: 營收年增 | B76: % | D76: =D75/C75-1 -> 1.209039 | E76: =E75/D75-1 -> 0.76303031 | F76: =F75/E75-1 -> 0.18063379 | G76: =G75/F75-1 -> 0.13187866 | H76: =$G76+(fade_gA-$G76)*1/3 -> 0.10791911 | I76: =$G76+(fade_gA-$G76)*2/3 -> 0.083959554 | J76: =$G76+(fade_gA-$G76)*3/3 -> 0.06
A77: Scorpio X ÷ 營收 | B77: % | C77: =C67/C75 -> 0 | D77: =D67/D75 -> 0.20177766 | E77: =E67/E75 -> 0.43524661 | F77: =F67/F75 -> 0.49856754 | G77: =G67/G75 -> 0.52957457
A78: D. 損益（non-GAAP）
A79: 毛利率 | B79: % | C79: =a25_gp/a25_rev -> 0.75819947 | D79: =a26_gp/a26_rev -> 0.72912703 | E79: =gm_27 -> 0.7 | F79: =gm_28 -> 0.695 | G79: =gm_29 -> 0.69 | K79: FY2027 起為輸入路徑（公司長期目標 70%；交換晶片硬體占比上升）
A80: 毛利 | B80: US$B | C80: =C75*C79 -> 0.646384 | D80: =D75*D79 -> 1.3731365 | E80: =E75*E79 -> 2.3241724 | F80: =F75*F79 -> 2.7243964 | G80: =G75*G79 -> 3.0615014
A81: 營業費用（基準路徑） | B81: US$B | C81: =a25_opx -> 0.311978 | D81: =a26_opx -> 0.585698 | E81: =D81*(1+MAX(0,phi*E76)) -> 0.91000608 | F81: =E81*(1+MAX(0,phi*F76)) -> 1.029291 | G81: =F81*(1+MAX(0,phi*G76)) -> 1.1277952
A82: 營業費用 | B82: US$B | C82: =C81 -> 0.311978 | D82: =D81 -> 0.585698 | E82: =E81+0*E75 -> 0.91000608 | F82: =F81+0*F75 -> 1.029291 | G82: =G81+0*G75 -> 1.1277952
A83: 營業利益 | B83: US$B | C83: =C80-C82 -> 0.334406 | D83: =D80-D82 -> 0.7874385 | E83: =E80-E82 -> 1.4141663 | F83: =F80-F82 -> 1.6951054 | G83: =G80-G82 -> 1.9337062
A84: 營業利益率 | B84: % | C84: =C83/C75 -> 0.3922536 | D84: =D83/D75 -> 0.418125 | E84: =E83/E75 -> 0.42592211 | F84: =F83/F75 -> 0.43242542 | G84: =G83/G75 -> 0.43581795
A85: 利息與其他收益 | B85: US$B | C85: =a25_ninc -> 0.04473 | D85: =a26_ninc -> 0.048658 | E85: =oth_f -> 0.05 | F85: =oth_f -> 0.05 | G85: =oth_f -> 0.05
A86: 有效稅率 | B86: % | C86: =a25_tx -> 0.12692279 | D86: =a26_tx -> 0.1179798 | E86: =tx_27 -> 0.12 | F86: =tx_28 -> 0.12 | G86: =tx_29 -> 0.12 | K86: 公司 non-GAAP 稅率約 12%
A87: 淨利 | B87: US$B | C87: =a25_ni -> 0.331015 | D87: =a26_ni -> 0.737454 | E87: =(E83+E85)*(1-E86) -> 1.2884663 | F87: =(F83+F85)*(1-F86) -> 1.5356928 | G87: =(G83+G85)*(1-G86) -> 1.7456614 | H87: =H75*H88 -> 1.9340517 | I87: =I75*I88 -> 2.0964338 | J87: =J75*J88 -> 2.2222198
A88: 淨利率 | B88: % | C88: =C87/C75 -> 0.388276 | D88: =D87/D75 -> 0.39158354 | E88: =E87/E75 -> 0.38806349 | F88: =F87/F75 -> 0.39175888 | G88: =G87/G75 -> 0.3934365 | H88: =$G88+(fade_mA-$G88)*1/3 -> 0.3934365 | I88: =$G88+(fade_mA-$G88)*2/3 -> 0.3934365 | J88: =$G88+(fade_mA-$G88)*3/3 -> 0.3934365
A89: 稀釋股數 | B89: 十億股 | C89: =a25_sh -> 0.179551 | D89: =a26_sh -> 0.18399925 | E89: =D89*(1+sh_g) -> 0.18675924 | F89: =E89*(1+sh_g) -> 0.18956063 | G89: =F89*(1+sh_g) -> 0.19240404 | H89: =G89*(1+sh_g) -> 0.1952901 | I89: =H89*(1+sh_g) -> 0.19821945 | J89: =I89*(1+sh_g) -> 0.20119274
A90: EPS（non-GAAP） | B90: US$ | C90: =C87/C89 -> 1.8435709 | D90: =D87/D89 -> 4.0079185 | E90: =E87/E89 -> 6.8990768 | F90: =F87/F89 -> 8.1013279 | G90: =G87/G89 -> 9.072894 | H90: =H87/H89 -> 9.9034804 | I90: =I87/I89 -> 10.576327 | J90: =J87/J89 -> 11.045229
A91: EPS 年增 | B91: % | D91: =D90/C90-1 -> 1.1739975 | E91: =E90/D90-1 -> 0.72136153 | F91: =F90/E90-1 -> 0.17426261 | G91: =G90/F90-1 -> 0.11992677 | H91: =H90/G90-1 -> 0.09154592 | I91: =I90/H90-1 -> 0.067940448 | J91: =J90/I90-1 -> 0.044334975
A94: 情境 B：平平（CY2028 顆數 ×0.8、CY2029 ×0.85）
A95: 項目 | B95: 單位 | C95: FY2025A | D95: FY2026（錨點） | E95: FY2027 | F95: FY2028 | G95: FY2029 | H95: FY2030（收斂） | I95: FY2031（收斂） | J95: FY2032（收斂） | K95: 說明
A96: A. Scorpio X（D 欄＝FY2026 校準年；E–G＝FY2027–FY2029；市場為日曆年＝會計年度）
A97: 非 NVIDIA scale-up 交換晶片市場 × 情境顆數係數 | B97: US$B | D97: =msx_26 -> 2.025 | E97: =msx_27 -> 7.701 | F97: =msx_28*um28_B -> 7.5744 | G97: =msx_29*um29_B -> 9.25497 | K97: AMD、Trainium、其他 ASIC 顆數 × 每顆 scale-up 交換晶片內容（網通模型）；CY2028 起乘顆數係數
A98: Astera Scorpio X 有效份額（FY2026 校準）＝ Scorpio X 營收 ÷ 市場 | B98: % | D98: =a26_x/D97 -> 0.18765432 | K98: Derived
A99: Scorpio X 有效份額相對值（÷ FY2026） | B99: x | D99: =1 -> 1 | E99: =rel_x_27 -> 1 | F99: =rel_x_28 -> 1.1 | G99: =rel_x_29 -> 1.15
A100: Scorpio X 有效份額 | B100: % | D100: =$D$98*D99 -> 0.18765432 | E100: =$D$98*E99 -> 0.18765432 | F100: =$D$98*F99 -> 0.20641975 | G100: =$D$98*G99 -> 0.21580247
A101: Scorpio X 營收 | B101: US$B | C101: =a25_x -> 0 | D101: =a26_x -> 0.38 | E101: =E97*E100 -> 1.4451259 | F101: =F97*F100 -> 1.5635058 | G101: =G97*G100 -> 1.9972454
A102: B. PCIe 與訊號調節（Aries、Scorpio P、Taurus、Leo）
A103: AI 加速器顆數 × 情境顆數係數 | B103: 百萬顆 | D103: =u_26 -> 15.2 | E103: =u_27 -> 23.7 | F103: =u_28*um28_B -> 21.2 | G103: =u_29*um29_B -> 25.6275
A104: PCIe／CXL／AEC 可服務市場＝顆數 × 每顆內容（c_pcie） | B104: US$B | D104: =D103*c_pcie/1000 -> 3.8 | E104: =E103*c_pcie/1000 -> 5.925 | F104: =F103*c_pcie/1000 -> 5.3 | G104: =G103*c_pcie/1000 -> 6.406875 | K104: c_pcie 只影響份額顯示，校準時抵銷
A105: Astera PCIe 等有效份額（FY2026 校準）＝ 營收 ÷ 可服務市場 | B105: % | D105: =a26_p/D104 -> 0.395595
A106: PCIe 等有效份額 × 每顆內容相對值（÷ FY2026） | B106: x | D106: =1 -> 1 | E106: =rel_p_27 -> 0.8 | F106: =rel_p_28 -> 0.75 | G106: =rel_p_29 -> 0.7
A107: PCIe 與訊號調節營收 | B107: US$B | C107: =a25_p -> 0.852525 | D107: =a26_p -> 1.503261 | E107: =E104*$D$105*E106 -> 1.8751203 | F107: =F104*$D$105*F106 -> 1.5724901 | G107: =G104*$D$105*G106 -> 1.7741694
A108: C. 合計
A109: 營收 | B109: US$B | C109: =a25_rev -> 0.852525 | D109: =D101+D107 -> 1.883261 | E109: =E101+E107 -> 3.3202462 | F109: =F101+F107 -> 3.1359959 | G109: =G101+G107 -> 3.7714148 | H109: =G109*(1+H110) -> 4.3311457 | I109: =H109*(1+I110) -> 4.7391701 | J109: =I109*(1+J110) -> 4.9287369
A110: 營收年增 | B110: % | D110: =D109/C109-1 -> 1.209039 | E110: =E109/D109-1 -> 0.76303031 | F110: =F109/E109-1 -> -0.05549297 | G110: =G109/F109-1 -> 0.20262108 | H110: =$G110+(fade_gB-$G110)*1/3 -> 0.14841405 | I110: =$G110+(fade_gB-$G110)*2/3 -> 0.094207027 | J110: =$G110+(fade_gB-$G110)*3/3 -> 0.04
A111: Scorpio X ÷ 營收 | B111: % | C111: =C101/C109 -> 0 | D111: =D101/D109 -> 0.20177766 | E111: =E101/E109 -> 0.43524661 | F111: =F101/F109 -> 0.49856754 | G111: =G101/G109 -> 0.52957457
A112: D. 損益（non-GAAP）
A113: 毛利率 | B113: % | C113: =a25_gp/a25_rev -> 0.75819947 | D113: =a26_gp/a26_rev -> 0.72912703 | E113: =gm_27 -> 0.7 | F113: =gm_28 -> 0.695 | G113: =gm_29 -> 0.69 | K113: FY2027 起為輸入路徑（公司長期目標 70%；交換晶片硬體占比上升）
A114: 毛利 | B114: US$B | C114: =C109*C113 -> 0.646384 | D114: =D109*D113 -> 1.3731365 | E114: =E109*E113 -> 2.3241724 | F114: =F109*F113 -> 2.1795172 | G114: =G109*G113 -> 2.6022762
A115: 營業費用（基準路徑） | B115: US$B | C115: =a25_opx -> 0.311978 | D115: =a26_opx -> 0.585698 | E115: =D115*(1+MAX(0,phi*E110)) -> 0.91000608 | F115: =E115*(1+MAX(0,phi*F110)) -> 0.91000608 | G115: =F115*(1+MAX(0,phi*G110)) -> 1.0438107
A116: 營業費用 | B116: US$B | C116: =C115 -> 0.311978 | D116: =D115 -> 0.585698 | E116: =E115+0*E109 -> 0.91000608 | F116: =F115+0*F109 -> 0.91000608 | G116: =G115+0*G109 -> 1.0438107
A117: 營業利益 | B117: US$B | C117: =C114-C116 -> 0.334406 | D117: =D114-D116 -> 0.7874385 | E117: =E114-E116 -> 1.4141663 | F117: =F114-F116 -> 1.2695111 | G117: =G114-G116 -> 1.5584655
A118: 營業利益率 | B118: % | C118: =C117/C109 -> 0.3922536 | D118: =D117/D109 -> 0.418125 | E118: =E117/E109 -> 0.42592211 | F118: =F117/F109 -> 0.40481911 | G118: =G117/G109 -> 0.41323099
A119: 利息與其他收益 | B119: US$B | C119: =a25_ninc -> 0.04473 | D119: =a26_ninc -> 0.048658 | E119: =oth_f -> 0.05 | F119: =oth_f -> 0.05 | G119: =oth_f -> 0.05
A120: 有效稅率 | B120: % | C120: =a25_tx -> 0.12692279 | D120: =a26_tx -> 0.1179798 | E120: =tx_27 -> 0.12 | F120: =tx_28 -> 0.12 | G120: =tx_29 -> 0.12 | K120: 公司 non-GAAP 稅率約 12%
A121: 淨利 | B121: US$B | C121: =a25_ni -> 0.331015 | D121: =a26_ni -> 0.737454 | E121: =(E117+E119)*(1-E120) -> 1.2884663 | F121: =(F117+F119)*(1-F120) -> 1.1611697 | G121: =(G117+G119)*(1-G120) -> 1.4154496 | H121: =H109*H122 -> 1.5713382 | I121: =I109*I122 -> 1.6600807 | J121: =J109*J122 -> 1.6648238
...

Sheet Val
A1: Val — P/E 估值（美元）。目標價＝DCF 與 Comparable 加權（第 0 節）；舊法規則值情境加權保留參考；另列「現價 ÷ FY2027、FY2028 EPS（模型，non-GAAP）」、市場隱含 EPS 與十年 P/E 規則值。Astera Labs 2024-03 上市，年底 P/E 只有 2024–2025，且 2024 為虧損（負值，不用）：規則值只有 2025 年一個觀測值（兩個來源）
A2: 循環位置：Astera Labs 不是設備股，不套設備市場見頂年；以本模型營收最高的會計年度為見頂年（比照 Arista、Credo）。營收到 FY2029 仍在增加時，見頂年未知，判為中段。規則值基準＝FY2027 GAAP 換算 EPS（non-GAAP × g2n），與年底 P/E 的計算口徑一致
A4: 0. 目標價
A5: 0.1 DCF（股東權益現金流，FY2027–FY2032 明確期＋FY2032 後永續）
A6: 項目 | B6: A（順利） | C6: B（平平） | D6: C（不如預期） | E6: 說明
A7: 情境 EPS（FY2027–FY2032） | E7: PL 頁各情境；FY2030 起為收斂法（PL 頁灰底）
A8: FY2027 | B8: =PL!E13 -> 6.8990768 | C8: =PL!E25 -> 6.8990768 | D8: =PL!E37 -> 6.8990768
A9: FY2028 | B9: =PL!F13 -> 8.1013279 | C9: =PL!F25 -> 6.125585 | D9: =PL!F37 -> 3.5960842
A10: FY2029 | B10: =PL!G13 -> 9.072894 | C10: =PL!G25 -> 7.3566524 | D10: =PL!G37 -> 4.0697143
A11: FY2030 | B11: =PL!H13 -> 9.9034804 | C11: =PL!H25 -> 8.0461743 | D11: =PL!H37 -> 4.0962312
A12: FY2031 | B12: =PL!I13 -> 10.576327 | C12: =PL!I25 -> 8.3749636 | D12: =PL!I37 -> 3.962133
A13: FY2032 | B13: =PL!J13 -> 11.045229 | C13: =PL!J25 -> 8.2747705 | D13: =PL!J37 -> 3.67537
A14: 股東現金流＝EPS ×（1 − tp_g ÷ tp_roe）
A15: 再投資率（tp_g ÷ tp_roe，上限 0.8） | B15: =IF(tp_roe<=tp_g,0.8,MIN(tp_g/tp_roe,0.8)) -> 0.14447401 | E15: ROE＝In 頁 tp_roe；tp_roe ≤ tp_g 時取上限 0.8
A16: FY2027 | B16: =B8*(1-$B$15) -> 5.9023395 | C16: =C8*(1-$B$15) -> 5.9023395 | D16: =D8*(1-$B$15) -> 5.9023395
A17: FY2028 | B17: =B9*(1-$B$15) -> 6.9308965 | C17: =C9*(1-$B$15) -> 5.2405972 | D17: =D9*(1-$B$15) -> 3.0765434
A18: FY2029 | B18: =B10*(1-$B$15) -> 7.7620966 | C18: =C10*(1-$B$15) -> 6.2938073 | D18: =D10*(1-$B$15) -> 3.4817464
A19: FY2030 | B19: =B11*(1-$B$15) -> 8.4726848 | C19: =C11*(1-$B$15) -> 6.8837112 | D19: =D11*(1-$B$15) -> 3.5044322
A20: FY2031 | B20: =B12*(1-$B$15) -> 9.0483228 | C20: =C12*(1-$B$15) -> 7.164999 | D20: =D12*(1-$B$15) -> 3.3897077
A21: FY2032 | B21: =B13*(1-$B$15) -> 9.44948 | C21: =C13*(1-$B$15) -> 7.0792812 | D21: =D13*(1-$B$15) -> 3.1443746
A22: DCF 情境每股價值（折現率 tp_r） | B22: =MAX(0,SUMPRODUCT(B16:B21,1/(1+tp_r)^{1;2;3;4;5;6})+B21*(1+tp_g)/(tp_r-tp_g)/(1+tp_r)^6) -> 126.12054 | C22: =MAX(0,SUMPRODUCT(C16:C21,1/(1+tp_r)^{1;2;3;4;5;6})+C21*(1+tp_g)/(tp_r-tp_g)/(1+tp_r)^6) -> 96.837311 | D22: =MAX(0,SUMPRODUCT(D16:D21,1/(1+tp_r)^{1;2;3;4;5;6})+D21*(1+tp_g)/(tp_r-tp_g)/(1+tp_r)^6) -> 47.562718 | E22: Σ 明確期現金流 ÷ (1＋r)^t ＋ 永續價值 ÷ (1＋r)^6；永續價值＝FY2032 現金流 ×(1＋g)÷(r−g)；基準日 2026 年底，t＝1 對 FY2027；小於 0 時取 0（股東有限責任）
A23: DCF 情境價值推到 12 個月後（×(1＋tp_r)） | B23: =B22*(1+tp_r) -> 138.73259 | C23: =C22*(1+tp_r) -> 106.52104 | D23: =D22*(1+tp_r) -> 52.31899
A24: DCF 目標價（情境加權） | B24: =tp_wA*B23+tp_wB*C23+tp_wC*D23 -> 105.3441 | E24: Σ 權重 × 情境價值 ×(1＋r)；權重見 In 頁
A26: 0.2 Comparable（市場主流同業前瞻 P/E）
A27: 同業與前瞻 P/E | B27: 代號 | C27: 前瞻 12 月 P/E | D27: 日期 | E27: 來源 | F27: 標記
A28: Credo | B28: CRDO | C28: 20.19 | D28: 2026-10-23 | E28: stockanalysis forward PE（分析師共識；價格日期如左） | F28: Interested-party
A29: Marvell | B29: MRVL | C29: 40.44 | D29: 2026-10-23 | E29: stockanalysis forward PE（分析師共識；價格日期如左） | F29: Interested-party
A30: Broadcom | B30: AVGO | C30: 18.52 | D30: 2026-10-23 | E30: stockanalysis forward PE（分析師共識；價格日期如左） | F30: Interested-party
A31: Rambus | B31: RMBS | C31: 25.23 | D31: 2026-10-23 | E31: stockanalysis forward PE（分析師共識；價格日期如左） | F31: Interested-party
A32: MACOM | B32: MTSI | C32: 28.59 | D32: 2026-10-23 | E32: stockanalysis forward PE（分析師共識；價格日期如左） | F32: Interested-party
A33: 同業前瞻 P/E 中位數 | B33: =MEDIAN(C28:C32) -> 25.23 | E33: 美股高速連接晶片同業（Credo、Marvell、Broadcom、Rambus、MACOM；10-K 列名競爭者為主；不放 A 股）
A34: 12 個月後的前瞻 EPS（情境加權） | B34: =tp_wA*(2/12*B8+10/12*B9)+tp_wB*(2/12*C8+10/12*C9)+tp_wC*(2/12*D8+10/12*D9) -> 6.3268525 | E34: 約 2027-10 時的未來 12 月（2027-11～2028-10）≈ 2／12 × FY2027＋10／12 × FY2028（會計年度＝日曆年）
A35: Comparable 目標價 | B35: =B33*B34 -> 159.62649 | E35: 同業中位數 × 前瞻 EPS
A37: 0.3 結論
A38: 項目 | B38: 數值 | E38: 說明
A39: 目標價（DCF 與 Comparable 加權） | B39: =tp_w_dcf*B24+(1-tp_w_dcf)*B35 -> 132.48529 | E39: tp_w_dcf × DCF＋（1 − tp_w_dcf）× Comparable；tp_w_dcf 見 In 頁
A40: Comparable 目標價（市場主流同業法） | B40: =B35 -> 159.62649
A41: 市場共識目標價 | B41: =cons_tp -> 388.36 | E41: In 頁 tp_street：stockanalysis 26 家平均 388.36（資料 2026-10-16；190–500）
A42: 上檔空間：加權目標價 | B42: =B39/px-1 -> -0.48481376 | E42: 現價＝In 頁 px
A43: 上檔空間：Comparable 目標價 | B43: =B40/px-1 -> -0.3792717
A44: 與市場共識目標價的差距：EPS 因素 | B44: =B34/cons_feps-1 -> -0.22929947 | E44: 本模型前瞻 EPS ÷ 共識前瞻 EPS − 1；共識前瞻 EPS＝In 頁 cons_feps（FY2028 共識為推導值）
A45: 與市場共識目標價的差距：倍數因素 | B45: =(cons_tp/cons_feps)/B33-1 -> 0.87506008 | E45: ="共識目標價隱含 "&TEXT(cons_tp/cons_feps,"0.0")&"x，同業中位數 "&TEXT(B33,"0.0")&"x" -> 共識目標價隱含 47.3x，同業中位數 25.2x
A46: 價格帶（DCF 不如預期～順利） | B46: =TEXT(D23,"#,##0.00")&"～"&TEXT(B23,"#,##0.00") -> 52.32～138.73 | E46: C 情境價值～A 情境價值（推到 12 個月後）
A47: 歷史倍數檢查：現價隱含 P/E 的十年分位（A／B／C） | B47: =IF(px/B9>MAX($B$102:$C$111),1,IF(px/B9<MIN($B$102:$C$111),0,PERCENTRANK($B$102:$C$111,px/B9))) -> 0 | C47: =IF(px/C9>MAX($B$102:$C$111),1,IF(px/C9<MIN($B$102:$C$111),0,PERCENTRANK($B$102:$C$111,px/C9))) -> 0 | D47: =IF(px/D9>MAX($B$102:$C$111),1,IF(px/D9<MIN($B$102:$C$111),0,PERCENTRANK($B$102:$C$111,px/D9))) -> 0 | E47: 現價 ÷ 各情境 FY2028 EPS 在 2016–2025 年底 P/E（第 6 節採用來源）的分位；高於十年最大值＝100%、低於最小值＝0%；只作檢查，不進目標價
A48: 目標價方法 | B48: DCF：股東現金流＝EPS（non-GAAP）×（1 − g／ROE），r＝10%、g＝4%、ROE＝non-GAAP 淨利 ÷ 平均股東權益三期平均（Derived，約 28%；淨現金約 12.5 億美元使 ROE 偏低），FY2027–32 明確期＋永續，FY2030 起為收斂法。Comparable：美股高速連接晶片同業（Credo、Marvell、Broadcom、Rambus、MACOM）前瞻 P/E 中位數 × 12 個月後前瞻 EPS（non-GAAP）；Astera 本身前瞻 P/E 約 46 倍、高於所有同業，同業中位數偏誤方向為低估成長溢價。十年 P/E 只有 2025 年一個觀測值（GAAP），分位檢查參考性低。情境對應：顆數情境 A＝順利、B＝平平、C＝不如預期。
A51: 舊法：規則值情境加權（參考）
A52: 項目 | B52: 數值 | E52: 說明
A53: 規則值情境加權價（參考，非目標價） | B53: =tp_wA*F81+tp_wB*F82+tp_wC*F83 -> 616.32212 | E53: 權重 × 各情境隱含價（第 3 節規則值）
A54: 規則值情境加權價 ÷ 現價 − 1（參考） | B54: =B53/px-1 -> 1.3966485 | E54: 現價＝In 頁 px（2026-10-23 收盤）
A55: 情境 A 隱含價（順利） | B55: =F81 -> 616.32212 | E55: ="FY2027 GAAP 換算 EPS "&TEXT(D81,"0.00")&" × "&TEXT(E81,"0.0")&" 倍（第 3 節）" -> FY2027 GAAP 換算 EPS 4.83 × 127.6 倍（第 3 節）
A56: 情境 B 隱含價（平平） | B56: =F82 -> 616.32212 | E56: ="FY2027 GAAP 換算 EPS "&TEXT(D82,"0.00")&" × "&TEXT(E82,"0.0")&" 倍（第 3 節）" -> FY2027 GAAP 換算 EPS 4.83 × 127.6 倍（第 3 節）
A57: 情境 C 隱含價（不如預期） | B57: =F83 -> 616.32212 | E57: ="FY2027 GAAP 換算 EPS "&TEXT(D83,"0.00")&" × "&TEXT(E83,"0.0")&" 倍（第 3 節）" -> FY2027 GAAP 換算 EPS 4.83 × 127.6 倍（第 3 節）
A58: 情境權重 A／B／C | B58: =tp_wA -> 0.3 | C58: =tp_wB -> 0.5 | D58: =tp_wC -> 0.2 | E58: ="合計 "&TEXT(B58+C58+D58,"0%")&"；In 頁 tp_wA／tp_wB／tp_wC（Assumed，Andy 可改）" -> 合計 100%；In 頁 tp_wA／tp_wB／tp_wC（Assumed，Andy 可改）
A59: 舊法說明 | B59: P/E：各情境 FY2027 GAAP 換算 EPS（non-GAAP EPS × g2n 0.70）× 十年年底 GAAP P/E 依循環位置取分位（非設備股：以本模型營收最高年判定，三情境皆為中段＝中位數）。Astera Labs 2024-03 上市，十年倍數只有 2025 年一個正值（約 127–128x，FY2025 營收年增 115% 的高成長期；2024 年虧損為負值不用），偏誤方向為明顯高估；隱含價約為 2027 年底價格、未折現。
A61: 1. 價格與市場隱含倍數
A62: 項目 | B62: A | C62: B | D62: C | E62: 說明
A63: 現價（2026-10-23 收盤） | B63: =px -> 257.16
A64: 現價 ÷ FY2026 EPS（錨點） | B64: =px/PL!D13 -> 64.162981 | C64: =px/PL!D25 -> 64.162981 | D64: =px/PL!D37 -> 64.162981
A65: 現價 ÷ FY2027 EPS（模型） | B65: =px/PL!E13 -> 37.274553 | C65: =px/PL!E25 -> 37.274553 | D65: =px/PL!E37 -> 37.274553 | E65: FY2027 三情境相同（顆數係數自 CY2028 起）
A66: 現價 ÷ FY2028 EPS（模型） | B66: =px/PL!F13 -> 31.742944 | C66: =px/PL!F25 -> 41.981296 | D66: =px/PL!F37 -> 71.511118 | E66: B、C 的差異自 FY2028 起
A67: 現價 ÷ FY2029 EPS（模型） | B67: =px/PL!G13 -> 28.343768 | C67: =px/PL!G25 -> 34.956117 | D67: =px/PL!G37 -> 63.18871
A68: 現價 ÷ 共識 FY2026 EPS | B68: =px/cons_eps26 -> 63.811414
A69: 現價 ÷ 共識 FY2027 EPS | B69: =px/cons_eps27 -> 40.18125
A70: 現價 ÷ 52 週高點 − 1 | B70: =px/px_hi-1 -> -0.48514455
A71: 現價 ÷ 賣方平均目標價 − 1 | B71: =px/tp_street-1 -> -0.33783088
A73: 2. 循環位置（本模型營收最高年）
A74: 情境 | B74: 營收最高年（FY2026–FY2029） | C74: FY2027 判定 | D74: 規則倍數（P/E） | E74: 見頂年是否未知 | F74: 說明
A75: A | B75: =INDEX({2026,2027,2028,2029},MATCH(MAX(PL!D75:G75),PL!D75:G75,0)) -> 2029 | C75: =IF(B75=2029,"中段",IF(2027<B75,"中段",IF(2027=B75,"見頂","谷底"))) -> 中段 | D75: =IF(C75="見頂",pe_peak,IF(C75="谷底",pe_trough,pe_mid)) -> 127.62 | E75: =IF(B75=2029,"是：營收到觀測期末仍在增加","否") -> 是：營收到觀測期末仍在增加 | F75: tools/cycle_position.py excel_rule；營收最高年取代設備市場見頂年
A76: B | B76: =INDEX({2026,2027,2028,2029},MATCH(MAX(PL!D109:G109),PL!D109:G109,0)) -> 2029 | C76: =IF(B76=2029,"中段",IF(2027<B76,"中段",IF(2027=B76,"見頂","谷底"))) -> 中段 | D76: =IF(C76="見頂",pe_peak,IF(C76="谷底",pe_trough,pe_mid)) -> 127.62 | E76: =IF(B76=2029,"是：營收到觀測期末仍在增加","否") -> 是：營收到觀測期末仍在增加 | F76: 同上
A77: C | B77: =INDEX({2026,2027,2028,2029},MATCH(MAX(PL!D143:G143),PL!D143:G143,0)) -> 2027 | C77: =IF(B77=2029,"中段",IF(2027<B77,"中段",IF(2027=B77,"見頂","谷底"))) -> 見頂 | D77: =IF(C77="見頂",pe_peak,IF(C77="谷底",pe_trough,pe_mid)) -> 127.62 | E77: =IF(B77=2029,"是：營收到觀測期末仍在增加","否") -> 否 | F77: 同上
A79: 3. 規則值隱含股價（美元；約 2027 年底，未折現）＝ FY2027 GAAP 換算 EPS × 規則倍數
A80: 情境 | B80: FY2027 EPS | C80: FY2028 EPS | D80: FY2027 GAAP 換算 EPS | E80: 規則倍數 | F80: 隱含股價 | G80: 相對現價 | H80: 現價 ÷ FY2027 EPS
A81: A | B81: =PL!E13 -> 6.8990768 | C81: =PL!F13 -> 8.1013279 | D81: =B81*g2n -> 4.8293537 | E81: =D75 -> 127.62 | F81: =D81*E81 -> 616.32212 | G81: =F81/px-1 -> 1.3966485 | H81: =px/B81 -> 37.274553
A82: B | B82: =PL!E25 -> 6.8990768 | C82: =PL!F25 -> 6.125585 | D82: =B82*g2n -> 4.8293537 | E82: =D76 -> 127.62 | F82: =D82*E82 -> 616.32212 | G82: =F82/px-1 -> 1.3966485 | H82: =px/B82 -> 37.274553
A83: C | B83: =PL!E37 -> 6.8990768 | C83: =PL!F37 -> 3.5960842 | D83: =B83*g2n -> 4.8293537 | E83: =D77 -> 127.62 | F83: =D83*E83 -> 616.32212 | G83: =F83/px-1 -> 1.3966485 | H83: =px/B83 -> 37.274553
A84: FY2027＝2027 年底的近 12 月（會計年度＝日曆年）；年底 P/E 資料商以近 12 月 GAAP EPS 計算，故以 g2n 換算
A86: 4. 核心問題：市場隱含的 FY2028 EPS（＝現價 ÷ 假設倍數；non-GAAP）與模型的距離
A87: 假設倍數（÷ FY2028 EPS） | B87: 市場隱含 FY2028 EPS | C87: 模型 FY2028 EPS（A） | D87: 隱含 ÷ 模型 A − 1 | E87: 模型 FY2028 EPS（C） | F87: 隱含 ÷ 模型 C − 1
A88: 20 | B88: =px/A88 -> 12.858 | C88: =PL!F13 -> 8.1013279 | D88: =B88/C88-1 -> 0.58714722 | E88: =PL!F37 -> 3.5960842 | F88: =B88/E88-1 -> 2.5755559
A89: 25 | B89: =px/A89 -> 10.2864 | C89: =PL!F13 -> 8.1013279 | D89: =B89/C89-1 -> 0.26971778 | E89: =PL!F37 -> 3.5960842 | F89: =B89/E89-1 -> 1.8604447
A90: 35 | B90: =px/A90 -> 7.3474286 | C90: =PL!F13 -> 8.1013279 | D90: =B90/C90-1 -> -0.09305873 | E90: =PL!F37 -> 3.5960842 | F90: =B90/E90-1 -> 1.0431748
A91: 45 | B91: =px/A91 -> 5.7146667 | C91: =PL!F13 -> 8.1013279 | D91: =B91/C91-1 -> -0.29460123 | E91: =PL!F37 -> 3.5960842 | F91: =B91/E91-1 -> 0.58913597
A92: 讀法：以 25 倍（同業前瞻 P/E 中位數附近）計，現價隱含的 FY2028 EPS 高於模型 A 約三成，需要 Scorpio X 份額上升（Sens「Scorpio X 份額 高」）才達得到；以 35 倍計約等於模型 A；以 45 倍（Astera 現行前瞻 P/E 附近）計略低於模型 B。現價隱含的是情境 A（顆數不下修）且 Scorpio X 份額維持，並給成長溢價。
A93: 本版未做先驗，無 Andy 合理 P/E 對照。
A97: 6. 十年倍數與規則值（2016–2025 年底；見頂年 25 分位、中段中位數、谷底 75 分位）
A98: 規則（Andy 2026-10-13）：合理倍數＝年底 P/E 依循環位置取分位。Astera Labs 只有 2025 年一個正值（約 127–128x，營收年增 115% 的高成長期），三個分位相同；歷史倍數為 GAAP 落後 P/E，規則值偏高的方向明確。前瞻 P/E 歷史待 Bloomberg。
A100: P/E：十年歷史倍數
A101: 年底 | B101: companiesmarketcap（年底 P/E） | C101: StockAnalysis（會計年度末 P/E） | D101: 標記／說明
A102: 2016 | D102: companiesmarketcap（年底 P/E）：Interested-party（資料商；只有 2025 年一個正值；2024 −77.0x 為虧損，不用）；StockAnalysis（會計年度末 P/E）：Interested-party（資料商；會計年度＝日曆年，日期口徑與年底相同；2024 虧損無值）
A103: 2017
A104: 2018
A105: 2019
A106: 2020
A107: 2021
A108: 2022
A109: 2023
A110: 2024
A111: 2025 | B111: 127 | C111: 128.23
A112: 25 分位（各來源） | B112: =PERCENTILE(B102:B111,0.25) -> 127 | C112: =PERCENTILE(C102:C111,0.25) -> 128.23
A113: 中位數（各來源） | B113: =MEDIAN(B102:B111) -> 127 | C113: =MEDIAN(C102:C111) -> 128.23
...

Sheet Recon
A1: Recon — 本模型 vs 共識、公司說法、市場層。只作事後對照，不為對上數字而調參數。共識 FY2027 EPS 區間 4.35–8.80
A3: 項目 | B3: 對照值 | C3: 模型 A | D3: 差距 A | E3: 模型 B | F3: 差距 B | G3: 模型 C | H3: 差距 C | I3: 對照來源 | J3: 說明
A4: A. 共識與指引（校準未使用共識）
A5: 3Q26 營收（指引中點）vs 共識 | B5: =cons_q3 -> 0.5508 | C5: =Q!F4 -> 0.55 | D5: =C5/B5-1 -> -0.0014524328 | E5: =Q!F4 -> 0.55 | F5: =E5/B5-1 -> -0.0014524328 | G5: =Q!F4 -> 0.55 | H5: =G5/B5-1 -> -0.0014524328 | I5: Yahoo（18 家） | J5: 指引 5.40–5.60
A6: 4Q26 營收（模型假設）vs 共識 | B6: =cons_q4 -> 0.65571 | C6: =Q!G4 -> 0.6325 | D6: =C6/B6-1 -> -0.035396746 | E6: =Q!G4 -> 0.6325 | F6: =E6/B6-1 -> -0.035396746 | G6: =Q!G4 -> 0.6325 | H6: =G6/B6-1 -> -0.035396746 | I6: Yahoo（18 家；6.09–7.38） | J6: 季增 15%（Assumed）
A7: FY2026 營收 vs 共識 | B7: =cons_rev26 -> 1.91 | C7: =PL!D75 -> 1.883261 | D7: =C7/B7-1 -> -0.013999476 | E7: =PL!D109 -> 1.883261 | F7: =E7/B7-1 -> -0.013999476 | G7: =PL!D143 -> 1.883261 | H7: =G7/B7-1 -> -0.013999476 | I7: Yahoo（21 家；1.86–1.99）
A8: FY2026 EPS vs 共識 | B8: =cons_eps26 -> 4.03 | C8: =PL!D90 -> 4.0079185 | D8: =C8/B8-1 -> -0.0054792778 | E8: =PL!D124 -> 4.0079185 | F8: =E8/B8-1 -> -0.0054792778 | G8: =PL!D158 -> 4.0079185 | H8: =G8/B8-1 -> -0.0054792778 | I8: Yahoo（21 家；3.90–4.33）
A9: FY2027 營收 vs 共識 | B9: =cons_rev27 -> 2.98 | C9: =PL!E75 -> 3.3202462 | D9: =C9/B9-1 -> 0.11417659 | E9: =PL!E109 -> 3.3202462 | F9: =E9/B9-1 -> 0.11417659 | G9: =PL!E143 -> 3.3202462 | H9: =G9/B9-1 -> 0.11417659 | I9: Yahoo（24 家；2.19–3.68）
A10: FY2027 EPS vs 共識 | B10: =cons_eps27 -> 6.4 | C10: =PL!E90 -> 6.8990768 | D10: =C10/B10-1 -> 0.077980743 | E10: =PL!E124 -> 6.8990768 | F10: =E10/B10-1 -> 0.077980743 | G10: =PL!E158 -> 6.8990768 | H10: =G10/B10-1 -> 0.077980743 | I10: Yahoo（23 家；4.35–8.80）
A11: FY2028 營收 vs 共識 | B11: =cons_rev28 -> 3.835 | C11: =PL!F75 -> 3.9199949 | D11: =C11/B11-1 -> 0.022162941 | E11: =PL!F109 -> 3.1359959 | F11: =E11/B11-1 -> -0.18226965 | G11: =PL!F143 -> 2.3519969 | H11: =G11/B11-1 -> -0.38670224 | I11: MarketScreener（26 家）
A12: FY2028 EPS vs 共識（推導） | B12: =cons_eps28 -> 8.5710676 | C12: =PL!F90 -> 8.1013279 | D12: =C12/B12-1 -> -0.054805277 | E12: =PL!F124 -> 6.125585 | F12: =E12/B12-1 -> -0.28531831 | G12: =PL!F158 -> 3.5960842 | H12: =G12/B12-1 -> -0.58043918 | I12: MarketScreener GAAP × non-GAAP／GAAP 比 | J12: 共識 non-GAAP FY2028：未找到
A13: FY2027 毛利率 vs 公司長期目標 70% | B13: 0.7 | C13: =PL!E79 -> 0.7 | D13: =C13-B13 -> 0 | E13: =PL!E113 -> 0.7 | F13: =E13-B13 -> 0 | G13: =PL!E147 -> 0.7 | H13: =G13-B13 -> 0 | I13: 公司 2Q26 法說
A14: B. 份額與市場（機制檢查）
A15: FY2028 Scorpio X 每顆非 NVIDIA 加速器營收（美元／顆）vs 公司「逾 1,000 美元」 | B15: 1000 | C15: =PL!F67*1000/nnu_28 -> 195.43822 | D15: =C15/B15-1 -> -0.80456178 | E15: =PL!F101*1000/nnu_28 -> 156.35058 | F15: =E15/B15-1 -> -0.84364942 | G15: =PL!F135*1000/nnu_28 -> 117.26293 | H15: =G15/B15-1 -> -0.88273707 | I15: 公司 1Q26 法說 | J15: 公司說法為採用平台的每顆內容；本列分母為全部非 NVIDIA、非 TPU 加速器
A16: FY2029 非 NVIDIA scale-up 交換晶片市場（網通模型）vs 公司 2030 年商用 scale-up 交換 200 億美元 | B16: =tam_su -> 20 | C16: =PL!G63 -> 10.8882 | D16: =C16/B16-1 -> -0.45559 | E16: =PL!G97 -> 9.25497 | F16: =E16/B16-1 -> -0.5372515 | G16: =PL!G131 -> 6.53292 | H16: =G16/B16-1 -> -0.673354 | I16: 公司 4Q25 新聞稿（Interested-party） | J16: 口徑不同：公司數字為 2030 年、含所有商用 scale-up 交換
A17: FY2027 Scorpio X 有效份額（÷ 非 NVIDIA scale-up 交換） | C17: =PL!E66 -> 0.18765432 | E17: =PL!E100 -> 0.18765432 | G17: =PL!E134 -> 0.18765432 | I17: —
A18: FY2028 Astera 營收 ÷ AI IT 資本支出 | C18: =PL!F75/itc_28 -> 0.0019755411 | E18: =PL!F109/itc_28 -> 0.0015804329 | G18: =PL!F143/itc_28 -> 0.0011853247 | I18: markets/network | J18: 每 1 美元 AI IT 資本支出分到的 Astera 營收
A19: C. 校準
A20: 2Q26 EPS（模型）vs 公司揭露 0.80 | B20: =q2_eps -> 0.8 | C20: =Q!E17 -> 0.79533108 | D20: =C20/B20-1 -> -0.0058361514 | E20: =Q!E17 -> 0.79533108 | F20: =E20/B20-1 -> -0.0058361514 | G20: =Q!E17 -> 0.79533108 | H20: =G20/B20-1 -> -0.0058361514 | I20: 公司 | J20: 淨利 ÷ 稀釋股數
A21: 3Q26 EPS（模型）vs 指引中點 | B21: =q3_eps -> 1.185 | C21: =Q!F17 -> 1.1915676 | D21: =C21/B21-1 -> 0.0055422511 | E21: =Q!F17 -> 1.1915676 | F21: =E21/B21-1 -> 0.0055422511 | G21: =Q!F17 -> 1.1915676 | H21: =G21/B21-1 -> 0.0055422511 | I21: 公司指引 1.16–1.21
A22: FY2025 EPS（模型）vs 公司揭露 1.84 | B22: =a25_eps_in -> 1.84 | C22: =PL!C90 -> 1.8435709 | D22: =C22/B22-1 -> 0.0019407106 | E22: =PL!C124 -> 1.8435709 | F22: =E22/B22-1 -> 0.0019407106 | G22: =PL!C158 -> 1.8435709 | H22: =G22/B22-1 -> 0.0019407106 | I22: 公司
A23: FY2026 營業費用彈性（Derived） | C23: =Q!B28 -> 0.72567513 | E23: =Q!B28 -> 0.72567513 | G23: =Q!B28 -> 0.72567513 | I23: Q 頁
A24: D. 預留
A25: R4 產業部署路徑（markets/deploy_path/，尚未建立）：上線後以 Astera 營收 ÷ 部署 GW 計算每 GW 營收 | J25: 預留列：本版無數值
A26: 3Q26 財報（2026-11-03）：公布後以實績取代 Q 頁 3Q 指引，並依 4Q26 指引更新 g_q4 | J26: 預留列：本版無數值

Sheet Sens
A1: Sens — 一次動一個輸入（情境 A；有效份額在每個案例內依 FY2026 錨點重算，FY2026 恆等於錨點）：對 FY2027、FY2028 的營收、Scorpio X 營收、毛利率與 EPS 的影響。每個案例是一個完整推導區塊（本頁下方）
A3: 案例 | B3: 設定 | C3: FY2027 營收 | D3: FY2027 Scorpio X 營收 | E3: FY2027 毛利率 | F3: FY2027 EPS | G3: FY2027 EPS 相對基準 | H3: FY2028 營收 | I3: FY2028 Scorpio X 營收 | J3: FY2028 毛利率 | K3: FY2028 EPS | L3: FY2028 EPS 相對基準
A4: 基準（情境 A） | B4: PL 區塊 A | C4: =PL!E75 -> 3.3202462 | D4: =PL!E67 -> 1.4451259 | E4: =PL!E79 -> 0.7 | F4: =PL!E90 -> 6.8990768 | G4: =F4/F$4-1 -> 0 | H4: =PL!F75 -> 3.9199949 | I4: =PL!F67 -> 1.9543822 | J4: =PL!F79 -> 0.695 | K4: =PL!F90 -> 8.1013279 | L4: =K4/K$4-1 -> 0
A5: Scorpio X 份額 低 | B5: Scorpio X 有效份額相對值 FY2027 0.70、FY2028 0.60、FY2029 0.50（Broadcom、NVLink Fusion、其他 UALink 交換晶片搶份額） | C5: =E55 -> 2.8867084 | D5: =E47 -> 1.0115881 | E5: =E59 -> 0.7 | F5: =E70 -> 5.9301453 | G5: =F5/F$4-1 -> -0.14044364 | H5: =F55 -> 3.0316393 | I5: =F47 -> 1.0660267 | J5: =F59 -> 0.695 | K5: =F70 -> 6.1057433 | L5: =K5/K$4-1 -> -0.24632808
A6: Scorpio X 份額 高 | B6: FY2027 1.40、FY2028 1.70、FY2029 2.00（逾 10 家客戶陸續量產） | C6: =E89 -> 3.8982966 | D6: =E81 -> 2.0231763 | E6: =E93 -> 0.7 | F6: =E104 -> 8.1909854 | G6: =F6/F$4-1 -> 0.18725819 | H6: =F89 -> 4.9860215 | I6: =F81 -> 3.0204089 | J6: =F93 -> 0.695 | K6: =F104 -> 10.510875 | L6: =K6/K$4-1 -> 0.29742617
A7: PCIe 等份額 低 | B7: PCIe 等相對值 FY2027 0.65、FY2028 0.55、FY2029 0.45（重定時器價格戰、平台整合） | C7: =E123 -> 2.9686612 | D7: =E115 -> 1.4451259 | E7: =E127 -> 0.7 | F7: =E138 -> 6.1133048 | G7: =F7/F$4-1 -> -0.11389523 | H7: =F123 -> 3.3958315 | I7: =F115 -> 1.9543822 | J7: =F127 -> 0.695 | K7: =F138 -> 6.9296181 | L7: =K7/K$4-1 -> -0.14463182
A8: PCIe 等份額 高 | B8: 相對值 1.00（PCIe 7 單價上升抵銷份額競爭） | C8: =E157 -> 3.7890263 | D8: =E149 -> 1.4451259 | E8: =E161 -> 0.7 | F8: =E172 -> 7.9467727 | G8: =F8/F$4-1 -> 0.15186031 | H8: =F157 -> 4.5751991 | I8: =F149 -> 1.9543822 | J8: =F161 -> 0.695 | K8: =F172 -> 9.5678678 | L8: =K8/K$4-1 -> 0.18102463
A9: 最大客戶部分轉單 | B9: 最大終端客戶（逾 70%）的 PCIe 等內容 30% 轉給他人或自製 | C9: =E191 -> 2.926471 | D9: =E183 -> 1.4451259 | E9: =E195 -> 0.7 | F9: =E206 -> 6.0190122 | G9: =F9/F$4-1 -> -0.12756266 | H9: =F191 -> 3.5072162 | I9: =F183 -> 1.9543822 | J9: =F195 -> 0.695 | K9: =F206 -> 7.1869037 | L9: =K9/K$4-1 -> -0.11287336
A10: 毛利率 低 | B10: 毛利率 FY2027 66%、FY2028 65%、FY2029 64% | C10: =E225 -> 3.3202462 | D10: =E217 -> 1.4451259 | E10: =E229 -> 0.66 | F10: =E240 -> 6.2732835 | G10: =F10/F$4-1 -> -0.090706808 | H10: =F225 -> 3.9199949 | I10: =F217 -> 1.9543822 | J10: =F229 -> 0.65 | K10: =F240 -> 7.2824247 | L10: =K10/K$4-1 -> -0.10108259
A11: 毛利率 高 | B11: 毛利率 72% | C11: =E259 -> 3.3202462 | D11: =E251 -> 1.4451259 | E11: =E263 -> 0.72 | F11: =E274 -> 7.2119734 | G11: =F11/F$4-1 -> 0.045353404 | H11: =F259 -> 3.9199949 | I11: =F251 -> 1.9543822 | J11: =F263 -> 0.72 | K11: =F274 -> 8.5562741 | L11: =K11/K$4-1 -> 0.056156992
A12: 稅率 15% | B12: FY2027 起 non-GAAP 稅率 15% | C12: =E293 -> 3.3202462 | D12: =E285 -> 1.4451259 | E12: =E297 -> 0.7 | F12: =E308 -> 6.663881 | G12: =F12/F$4-1 -> -0.034090909 | H12: =F293 -> 3.9199949 | I12: =F285 -> 1.9543822 | J12: =F297 -> 0.695 | K12: =F308 -> 7.8251462 | L12: =K12/K$4-1 -> -0.034090909
A13: 稅率 10% | B13: FY2027 起 10% | C13: =E327 -> 3.3202462 | D13: =E319 -> 1.4451259 | E13: =E331 -> 0.7 | F13: =E342 -> 7.055874 | G13: =F13/F$4-1 -> 0.022727273 | H13: =F327 -> 3.9199949 | I13: =F319 -> 1.9543822 | J13: =F331 -> 0.695 | K13: =F342 -> 8.2854489 | L13: =K13/K$4-1 -> 0.022727273
A14: 非 NVIDIA scale-up 交換市場 ×0.8 | B14: FY2027 起 ×0.8（NVLink Fusion、乙太網路 scale-up 搶占） | C14: =E361 -> 3.031221 | D14: =E353 -> 1.1561007 | E14: =E365 -> 0.7 | F14: =E376 -> 6.2531224 | G14: =F14/F$4-1 -> -0.093629096 | H14: =F361 -> 3.5291184 | I14: =F353 -> 1.5635058 | J14: =F365 -> 0.695 | K14: =F376 -> 7.2293163 | L14: =K14/K$4-1 -> -0.1076381
A15: 非 NVIDIA scale-up 交換市場 ×1.2 | B15: ×1.2 | C15: =E395 -> 3.6092714 | D15: =E387 -> 1.7341511 | E15: =E399 -> 0.7 | F15: =E410 -> 7.5450311 | G15: =F15/F$4-1 -> 0.093629096 | H15: =F395 -> 4.3108713 | I15: =F387 -> 2.3452587 | J15: =F399 -> 0.695 | K15: =F410 -> 8.9747592 | L15: =K15/K$4-1 -> 0.10781335
A16: 營業費用彈性 0.9 | B16: 營業費用隨營收成長較多 | C16: =E429 -> 3.3202462 | D16: =E421 -> 1.4451259 | E16: =E433 -> 0.7 | F16: =E444 -> 6.5319843 | G16: =F16/F$4-1 -> -0.053208924 | H16: =F429 -> 3.9199949 | I16: =F421 -> 1.9543822 | J16: =F433 -> 0.695 | K16: =F444 -> 7.5478378 | L16: =K16/K$4-1 -> -0.068320906
A17: 營業費用率 +2pt | B17: 營業費用額外 +2% × 營收 | C17: =E463 -> 3.3202462 | D17: =E455 -> 1.4451259 | E17: =E467 -> 0.7 | F17: =E478 -> 6.5861801 | G17: =F17/F$4-1 -> -0.045353404 | H17: =F463 -> 3.9199949 | I17: =F455 -> 1.9543822 | J17: =F467 -> 0.695 | K17: =F478 -> 7.7373709 | L17: =K17/K$4-1 -> -0.044925593
A18: 顆數情境 B | B18: CY2028 ×0.8、CY2029 ×0.85 | C18: =PL!E109 -> 3.3202462 | D18: =PL!E101 -> 1.4451259 | E18: =PL!E113 -> 0.7 | F18: =PL!E124 -> 6.8990768 | G18: =F18/F$4-1 -> 0 | H18: =PL!F109 -> 3.1359959 | I18: =PL!F101 -> 1.5635058 | J18: =PL!F113 -> 0.695 | K18: =PL!F124 -> 6.125585 | L18: =K18/K$4-1 -> -0.24387889
A19: 顆數情境 C | B19: CY2028–29 ×0.6 | C19: =PL!E143 -> 3.3202462 | D19: =PL!E135 -> 1.4451259 | E19: =PL!E147 -> 0.7 | F19: =PL!E158 -> 6.8990768 | G19: =F19/F$4-1 -> 0 | H19: =PL!F143 -> 2.3519969 | I19: =PL!F135 -> 1.1726293 | J19: =PL!F147 -> 0.695 | K19: =PL!F158 -> 3.5960842 | L19: =K19/K$4-1 -> -0.55611176
A21: 讀法：FY2026 為錨點、各案例相同；顆數情境自 CY2028 起，FY2027 不受影響。Scorpio X 份額高／低是 FY2027–FY2028 EPS 最大的單一變數，其次是 PCIe 等份額與毛利率；顆數情境 C 主要打在 FY2028 起。稅率影響較小。
A23: 目標價參數（只改 DCF 參數與權重；PL 收斂法的 fade_g 不隨 tp_g 變動）
A24: 案例 | B24: 設定 | C24: DCF 目標價 | D24: Comparable 目標價 | E24: 加權目標價 | F24: 相對基準
A25: 基準 | B25: r 10%、g 4%、DCF 權重 0.5 | C25: =(tp_wA*MAX(0,Val!B8*(1-IF(tp_roe<=tp_g,0.8,MIN(tp_g/tp_roe,0.8)))/(1+tp_r)^1+Val!B9*(1-IF(tp_roe<=tp_g,0.8,MIN(tp_g/tp_roe,0.8)))/(1+tp_r)^2+Val!B10*(1-IF(tp_roe<=tp_g,0.8,MIN(tp_g/tp_roe,0.8)))/(1+tp_r)^3+Val!B11*(1-IF(tp_roe<=tp_g,0.8,MIN(tp_g/tp_roe,0.8)))/(1+tp_r)^4+Val!B12*(1-IF(tp_roe<=tp_g,0.8,MIN(tp_g/tp_roe,0.8)))/(1+tp_r)^5+Val!B13*(1-IF(tp_roe<=tp_g,0.8,MIN(tp_g/tp_roe,0.8)))/(1+tp_r)^6+Val!B13*(1-IF(tp_roe<=tp_g,0.8,MIN(tp_g/tp_roe,0.8)))*(1+tp_g)/(tp_r-tp_g)/(1+tp_r)^6)+tp_wB*MAX(0,Val!C8*(1-IF(tp_roe<=tp_g,0.8,MIN(tp_g/tp_roe,0.8)))/(1+tp_r)^1+Val!C9*(1-IF(tp_roe<=tp_g,0.8,MIN(tp_g/tp_roe,0.8)))/(1+tp_r)^2+Val!C10*(1-IF(tp_roe<=tp_g,0.8,MIN(tp_g/tp_roe,0.8)))/(1+tp_r)^3+Val!C11*(1-IF(tp_roe<=tp_g,0.8,MIN(tp_g/tp_roe,0.8)))/(1+tp_r)^4+Val!C12*(1-IF(tp_roe<=tp_g,0.8,MIN(tp_g/tp_roe,0.8)))/(1+tp_r)^5+Val!C13*(1-IF(tp_roe<=tp_g,0.8,MIN(tp_g/tp_roe,0.8)))/(1+tp_r)^6+Val!C13*(1-IF(tp_roe<=tp_g,0.8,MIN(tp_g/tp_roe,0.8)))*(1+tp_g)/(tp_r-tp_g)/(1+tp_r)^6)+tp_wC*MAX(0,Val!D8*(1-IF(tp_roe<=tp_g,0.8,MIN(tp_g/tp_roe,0.8)))/(1+tp_r)^1+Val!D9*(1-IF(tp_roe<=tp_g,0.8,MIN(tp_g/tp_roe,0.8)))/(1+tp_r)^2+Val!D10*(1-IF(tp_roe<=tp_g,0.8,MIN(tp_g/tp_roe,0.8)))/(1+tp_r)^3+Val!D11*(1-IF(tp_roe<=tp_g,0.8,MIN(tp_g/tp_roe,0.8)))/(1+tp_r)^4+Val!D12*(1-IF(tp_roe<=tp_g,0.8,MIN(tp_g/tp_roe,0.8)))/(1+tp_r)^5+Val!D13*(1-IF(tp_roe<=tp_g,0.8,MIN(tp_g/tp_roe,0.8)))/(1+tp_r)^6+Val!D13*(1-IF(tp_roe<=tp_g,0.8,MIN(tp_g/tp_roe,0.8)))*(1+tp_g)/(tp_r-tp_g)/(1+tp_r)^6))*(1+tp_r) -> 105.3441 | D25: =Val!B35 -> 159.62649 | E25: =tp_w_dcf*C25+(1-tp_w_dcf)*D25 -> 132.48529 | F25: =E25/E$25-1 -> 0
A26: 折現率 +1pt | B26: r 11% | C26: =(tp_wA*MAX(0,Val!B8*(1-IF(tp_roe<=tp_g,0.8,MIN(tp_g/tp_roe,0.8)))/(1+(tp_r+0.01))^1+Val!B9*(1-IF(tp_roe<=tp_g,0.8,MIN(tp_g/tp_roe,0.8)))/(1+(tp_r+0.01))^2+Val!B10*(1-IF(tp_roe<=tp_g,0.8,MIN(tp_g/tp_roe,0.8)))/(1+(tp_r+0.01))^3+Val!B11*(1-IF(tp_roe<=tp_g,0.8,MIN(tp_g/tp_roe,0.8)))/(1+(tp_r+0.01))^4+Val!B12*(1-IF(tp_roe<=tp_g,0.8,MIN(tp_g/tp_roe,0.8)))/(1+(tp_r+0.01))^5+Val!B13*(1-IF(tp_roe<=tp_g,0.8,MIN(tp_g/tp_roe,0.8)))/(1+(tp_r+0.01))^6+Val!B13*(1-IF(tp_roe<=tp_g,0.8,MIN(tp_g/tp_roe,0.8)))*(1+tp_g)/((tp_r+0.01)-tp_g)/(1+(tp_r+0.01))^6)+tp_wB*MAX(0,Val!C8*(1-IF(tp_roe<=tp_g,0.8,MIN(tp_g/tp_roe,0.8)))/(1+(tp_r+0.01))^1+Val!C9*(1-IF(tp_roe<=tp_g,0.8,MIN(tp_g/tp_roe,0.8)))/(1+(tp_r+0.01))^2+Val!C10*(1-IF(tp_roe<=tp_g,0.8,MIN(tp_g/tp_roe,0.8)))/(1+(tp_r+0.01))^3+Val!C11*(1-IF(tp_roe<=tp_g,0.8,MIN(tp_g/tp_roe,0.8)))/(1+(tp_r+0.01))^4+Val!C12*(1-IF(tp_roe<=tp_g,0.8,MIN(tp_g/tp_roe,0.8)))/(1+(tp_r+0.01))^5+Val!C13*(1-IF(tp_roe<=tp_g,0.8,MIN(tp_g/tp_roe,0.8)))/(1+(tp_r+0.01))^6+Val!C13*(1-IF(tp_roe<=tp_g,0.8,MIN(tp_g/tp_roe,0.8)))*(1+tp_g)/((tp_r+0.01)-tp_g)/(1+(tp_r+0.01))^6)+tp_wC*MAX(0,Val!D8*(1-IF(tp_roe<=tp_g,0.8,MIN(tp_g/tp_roe,0.8)))/(1+(tp_r+0.01))^1+Val!D9*(1-IF(tp_roe<=tp_g,0.8,MIN(tp_g/tp_roe,0.8)))/(1+(tp_r+0.01))^2+Val!D10*(1-IF(tp_roe<=tp_g,0.8,MIN(tp_g/tp_roe,0.8)))/(1+(tp_r+0.01))^3+Val!D11*(1-IF(tp_roe<=tp_g,0.8,MIN(tp_g/tp_roe,0.8)))/(1+(tp_r+0.01))^4+Val!D12*(1-IF(tp_roe<=tp_g,0.8,MIN(tp_g/tp_roe,0.8)))/(1+(tp_r+0.01))^5+Val!D13*(1-IF(tp_roe<=tp_g,0.8,MIN(tp_g/tp_roe,0.8)))/(1+(tp_r+0.01))^6+Val!D13*(1-IF(tp_roe<=tp_g,0.8,MIN(tp_g/tp_roe,0.8)))*(1+tp_g)/((tp_r+0.01)-tp_g)/(1+(tp_r+0.01))^6))*(1+(tp_r+0.01)) -> 91.086757 | D26: =Val!B35 -> 159.62649 | E26: =tp_w_dcf*C26+(1-tp_w_dcf)*D26 -> 125.35662 | F26: =E26/E$25-1 -> -0.053807252
A27: 折現率 −1pt | B27: r 9% | C27: =(tp_wA*MAX(0,Val!B8*(1-IF(tp_roe<=tp_g,0.8,MIN(tp_g/tp_roe,0.8)))/(1+(tp_r-0.01))^1+Val!B9*(1-IF(tp_roe<=tp_g,0.8,MIN(tp_g/tp_roe,0.8)))/(1+(tp_r-0.01))^2+Val!B10*(1-IF(tp_roe<=tp_g,0.8,MIN(tp_g/tp_roe,0.8)))/(1+(tp_r-0.01))^3+Val!B11*(1-IF(tp_roe<=tp_g,0.8,MIN(tp_g/tp_roe,0.8)))/(1+(tp_r-0.01))^4+Val!B12*(1-IF(tp_roe<=tp_g,0.8,MIN(tp_g/tp_roe,0.8)))/(1+(tp_r-0.01))^5+Val!B13*(1-IF(tp_roe<=tp_g,0.8,MIN(tp_g/tp_roe,0.8)))/(1+(tp_r-0.01))^6+Val!B13*(1-IF(tp_roe<=tp_g,0.8,MIN(tp_g/tp_roe,0.8)))*(1+tp_g)/((tp_r-0.01)-tp_g)/(1+(tp_r-0.01))^6)+tp_wB*MAX(0,Val!C8*(1-IF(tp_roe<=tp_g,0.8,MIN(tp_g/tp_roe,0.8)))/(1+(tp_r-0.01))^1+Val!C9*(1-IF(tp_roe<=tp_g,0.8,MIN(tp_g/tp_roe,0.8)))/(1+(tp_r-0.01))^2+Val!C10*(1-IF(tp_roe<=tp_g,0.8,MIN(tp_g/tp_roe,0.8)))/(1+(tp_r-0.01))^3+Val!C11*(1-IF(tp_roe<=tp_g,0.8,MIN(tp_g/tp_roe,0.8)))/(1+(tp_r-0.01))^4+Val!C12*(1-IF(tp_roe<=tp_g,0.8,MIN(tp_g/tp_roe,0.8)))/(1+(tp_r-0.01))^5+Val!C13*(1-IF(tp_roe<=tp_g,0.8,MIN(tp_g/tp_roe,0.8)))/(1+(tp_r-0.01))^6+Val!C13*(1-IF(tp_roe<=tp_g,0.8,MIN(tp_g/tp_roe,0.8)))*(1+tp_g)/((tp_r-0.01)-tp_g)/(1+(tp_r-0.01))^6)+tp_wC*MAX(0,Val!D8*(1-IF(tp_roe<=tp_g,0.8,MIN(tp_g/tp_roe,0.8)))/(1+(tp_r-0.01))^1+Val!D9*(1-IF(tp_roe<=tp_g,0.8,MIN(tp_g/tp_roe,0.8)))/(1+(tp_r-0.01))^2+Val!D10*(1-IF(tp_roe<=tp_g,0.8,MIN(tp_g/tp_roe,0.8)))/(1+(tp_r-0.01))^3+Val!D11*(1-IF(tp_roe<=tp_g,0.8,MIN(tp_g/tp_roe,0.8)))/(1+(tp_r-0.01))^4+Val!D12*(1-IF(tp_roe<=tp_g,0.8,MIN(tp_g/tp_roe,0.8)))/(1+(tp_r-0.01))^5+Val!D13*(1-IF(tp_roe<=tp_g,0.8,MIN(tp_g/tp_roe,0.8)))/(1+(tp_r-0.01))^6+Val!D13*(1-IF(tp_roe<=tp_g,0.8,MIN(tp_g/tp_roe,0.8)))*(1+tp_g)/((tp_r-0.01)-tp_g)/(1+(tp_r-0.01))^6))*(1+(tp_r-0.01)) -> 125.30317 | D27: =Val!B35 -> 159.62649 | E27: =tp_w_dcf*C27+(1-tp_w_dcf)*D27 -> 142.46483 | F27: =E27/E$25-1 -> 0.075325621
A28: 長期成長 +1pt | B28: g 5% | C28: =(tp_wA*MAX(0,Val!B8*(1-IF(tp_roe<=(tp_g+0.01),0.8,MIN((tp_g+0.01)/tp_roe,0.8)))/(1+tp_r)^1+Val!B9*(1-IF(tp_roe<=(tp_g+0.01),0.8,MIN((tp_g+0.01)/tp_roe,0.8)))/(1+tp_r)^2+Val!B10*(1-IF(tp_roe<=(tp_g+0.01),0.8,MIN((tp_g+0.01)/tp_roe,0.8)))/(1+tp_r)^3+Val!B11*(1-IF(tp_roe<=(tp_g+0.01),0.8,MIN((tp_g+0.01)/tp_roe,0.8)))/(1+tp_r)^4+Val!B12*(1-IF(tp_roe<=(tp_g+0.01),0.8,MIN((tp_g+0.01)/tp_roe,0.8)))/(1+tp_r)^5+Val!B13*(1-IF(tp_roe<=(tp_g+0.01),0.8,MIN((tp_g+0.01)/tp_roe,0.8)))/(1+tp_r)^6+Val!B13*(1-IF(tp_roe<=(tp_g+0.01),0.8,MIN((tp_g+0.01)/tp_roe,0.8)))*(1+(tp_g+0.01))/(tp_r-(tp_g+0.01))/(1+tp_r)^6)+tp_wB*MAX(0,Val!C8*(1-IF(tp_roe<=(tp_g+0.01),0.8,MIN((tp_g+0.01)/tp_roe,0.8)))/(1+tp_r)^1+Val!C9*(1-IF(tp_roe<=(tp_g+0.01),0.8,MIN((tp_g+0.01)/tp_roe,0.8)))/(1+tp_r)^2+Val!C10*(1-IF(tp_roe<=(tp_g+0.01),0.8,MIN((tp_g+0.01)/tp_roe,0.8)))/(1+tp_r)^3+Val!C11*(1-IF(tp_roe<=(tp_g+0.01),0.8,MIN((tp_g+0.01)/tp_roe,0.8)))/(1+tp_r)^4+Val!C12*(1-IF(tp_roe<=(tp_g+0.01),0.8,MIN((tp_g+0.01)/tp_roe,0.8)))/(1+tp_r)^5+Val!C13*(1-IF(tp_roe<=(tp_g+0.01),0.8,MIN((tp_g+0.01)/tp_roe,0.8)))/(1+tp_r)^6+Val!C13*(1-IF(tp_roe<=(tp_g+0.01),0.8,MIN((tp_g+0.01)/tp_roe,0.8)))*(1+(tp_g+0.01))/(tp_r-(tp_g+0.01))/(1+tp_r)^6)+tp_wC*MAX(0,Val!D8*(1-IF(tp_roe<=(tp_g+0.01),0.8,MIN((tp_g+0.01)/tp_roe,0.8)))/(1+tp_r)^1+Val!D9*(1-IF(tp_roe<=(tp_g+0.01),0.8,MIN((tp_g+0.01)/tp_roe,0.8)))/(1+tp_r)^2+Val!D10*(1-IF(tp_roe<=(tp_g+0.01),0.8,MIN((tp_g+0.01)/tp_roe,0.8)))/(1+tp_r)^3+Val!D11*(1-IF(tp_roe<=(tp_g+0.01),0.8,MIN((tp_g+0.01)/tp_roe,0.8)))/(1+tp_r)^4+Val!D12*(1-IF(tp_roe<=(tp_g+0.01),0.8,MIN((tp_g+0.01)/tp_roe,0.8)))/(1+tp_r)^5+Val!D13*(1-IF(tp_roe<=(tp_g+0.01),0.8,MIN((tp_g+0.01)/tp_roe,0.8)))/(1+tp_r)^6+Val!D13*(1-IF(tp_roe<=(tp_g+0.01),0.8,MIN((tp_g+0.01)/tp_roe,0.8)))*(1+(tp_g+0.01))/(tp_r-(tp_g+0.01))/(1+tp_r)^6))*(1+tp_r) -> 116.16817 | D28: =Val!B35 -> 159.62649 | E28: =tp_w_dcf*C28+(1-tp_w_dcf)*D28 -> 137.89733 | F28: =E28/E$25-1 -> 0.0408501
A29: 長期成長 −1pt | B29: g 3% | C29: =(tp_wA*MAX(0,Val!B8*(1-IF(tp_roe<=(tp_g-0.01),0.8,MIN((tp_g-0.01)/tp_roe,0.8)))/(1+tp_r)^1+Val!B9*(1-IF(tp_roe<=(tp_g-0.01),0.8,MIN((tp_g-0.01)/tp_roe,0.8)))/(1+tp_r)^2+Val!B10*(1-IF(tp_roe<=(tp_g-0.01),0.8,MIN((tp_g-0.01)/tp_roe,0.8)))/(1+tp_r)^3+Val!B11*(1-IF(tp_roe<=(tp_g-0.01),0.8,MIN((tp_g-0.01)/tp_roe,0.8)))/(1+tp_r)^4+Val!B12*(1-IF(tp_roe<=(tp_g-0.01),0.8,MIN((tp_g-0.01)/tp_roe,0.8)))/(1+tp_r)^5+Val!B13*(1-IF(tp_roe<=(tp_g-0.01),0.8,MIN((tp_g-0.01)/tp_roe,0.8)))/(1+tp_r)^6+Val!B13*(1-IF(tp_roe<=(tp_g-0.01),0.8,MIN((tp_g-0.01)/tp_roe,0.8)))*(1+(tp_g-0.01))/(tp_r-(tp_g-0.01))/(1+tp_r)^6)+tp_wB*MAX(0,Val!C8*(1-IF(tp_roe<=(tp_g-0.01),0.8,MIN((tp_g-0.01)/tp_roe,0.8)))/(1+tp_r)^1+Val!C9*(1-IF(tp_roe<=(tp_g-0.01),0.8,MIN((tp_g-0.01)/tp_roe,0.8)))/(1+tp_r)^2+Val!C10*(1-IF(tp_roe<=(tp_g-0.01),0.8,MIN((tp_g-0.01)/tp_roe,0.8)))/(1+tp_r)^3+Val!C11*(1-IF(tp_roe<=(tp_g-0.01),0.8,MIN((tp_g-0.01)/tp_roe,0.8)))/(1+tp_r)^4+Val!C12*(1-IF(tp_roe<=(tp_g-0.01),0.8,MIN((tp_g-0.01)/tp_roe,0.8)))/(1+tp_r)^5+Val!C13*(1-IF(tp_roe<=(tp_g-0.01),0.8,MIN((tp_g-0.01)/tp_roe,0.8)))/(1+tp_r)^6+Val!C13*(1-IF(tp_roe<=(tp_g-0.01),0.8,MIN((tp_g-0.01)/tp_roe,0.8)))*(1+(tp_g-0.01))/(tp_r-(tp_g-0.01))/(1+tp_r)^6)+tp_wC*MAX(0,Val!D8*(1-IF(tp_roe<=(tp_g-0.01),0.8,MIN((tp_g-0.01)/tp_roe,0.8)))/(1+tp_r)^1+Val!D9*(1-IF(tp_roe<=(tp_g-0.01),0.8,MIN((tp_g-0.01)/tp_roe,0.8)))/(1+tp_r)^2+Val!D10*(1-IF(tp_roe<=(tp_g-0.01),0.8,MIN((tp_g-0.01)/tp_roe,0.8)))/(1+tp_r)^3+Val!D11*(1-IF(tp_roe<=(tp_g-0.01),0.8,MIN((tp_g-0.01)/tp_roe,0.8)))/(1+tp_r)^4+Val!D12*(1-IF(tp_roe<=(tp_g-0.01),0.8,MIN((tp_g-0.01)/tp_roe,0.8)))/(1+tp_r)^5+Val!D13*(1-IF(tp_roe<=(tp_g-0.01),0.8,MIN((tp_g-0.01)/tp_roe,0.8)))/(1+tp_r)^6+Val!D13*(1-IF(tp_roe<=(tp_g-0.01),0.8,MIN((tp_g-0.01)/tp_roe,0.8)))*(1+(tp_g-0.01))/(tp_r-(tp_g-0.01))/(1+tp_r)^6))*(1+tp_r) -> 97.92166 | D29: =Val!B35 -> 159.62649 | E29: =tp_w_dcf*C29+(1-tp_w_dcf)*D29 -> 128.77408 | F29: =E29/E$25-1 -> -0.028012301
A30: DCF 權重 0.3 | B30: Comparable 0.7 | C30: =(tp_wA*MAX(0,Val!B8*(1-IF(tp_roe<=tp_g,0.8,MIN(tp_g/tp_roe,0.8)))/(1+tp_r)^1+Val!B9*(1-IF(tp_roe<=tp_g,0.8,MIN(tp_g/tp_roe,0.8)))/(1+tp_r)^2+Val!B10*(1-IF(tp_roe<=tp_g,0.8,MIN(tp_g/tp_roe,0.8)))/(1+tp_r)^3+Val!B11*(1-IF(tp_roe<=tp_g,0.8,MIN(tp_g/tp_roe,0.8)))/(1+tp_r)^4+Val!B12*(1-IF(tp_roe<=tp_g,0.8,MIN(tp_g/tp_roe,0.8)))/(1+tp_r)^5+Val!B13*(1-IF(tp_roe<=tp_g,0.8,MIN(tp_g/tp_roe,0.8)))/(1+tp_r)^6+Val!B13*(1-IF(tp_roe<=tp_g,0.8,MIN(tp_g/tp_roe,0.8)))*(1+tp_g)/(tp_r-tp_g)/(1+tp_r)^6)+tp_wB*MAX(0,Val!C8*(1-IF(tp_roe<=tp_g,0.8,MIN(tp_g/tp_roe,0.8)))/(1+tp_r)^1+Val!C9*(1-IF(tp_roe<=tp_g,0.8,MIN(tp_g/tp_roe,0.8)))/(1+tp_r)^2+Val!C10*(1-IF(tp_roe<=tp_g,0.8,MIN(tp_g/tp_roe,0.8)))/(1+tp_r)^3+Val!C11*(1-IF(tp_roe<=tp_g,0.8,MIN(tp_g/tp_roe,0.8)))/(1+tp_r)^4+Val!C12*(1-IF(tp_roe<=tp_g,0.8,MIN(tp_g/tp_roe,0.8)))/(1+tp_r)^5+Val!C13*(1-IF(tp_roe<=tp_g,0.8,MIN(tp_g/tp_roe,0.8)))/(1+tp_r)^6+Val!C13*(1-IF(tp_roe<=tp_g,0.8,MIN(tp_g/tp_roe,0.8)))*(1+tp_g)/(tp_r-tp_g)/(1+tp_r)^6)+tp_wC*MAX(0,Val!D8*(1-IF(tp_roe<=tp_g,0.8,MIN(tp_g/tp_roe,0.8)))/(1+tp_r)^1+Val!D9*(1-IF(tp_roe<=tp_g,0.8,MIN(tp_g/tp_roe,0.8)))/(1+tp_r)^2+Val!D10*(1-IF(tp_roe<=tp_g,0.8,MIN(tp_g/tp_roe,0.8)))/(1+tp_r)^3+Val!D11*(1-IF(tp_roe<=tp_g,0.8,MIN(tp_g/tp_roe,0.8)))/(1+tp_r)^4+Val!D12*(1-IF(tp_roe<=tp_g,0.8,MIN(tp_g/tp_roe,0.8)))/(1+tp_r)^5+Val!D13*(1-IF(tp_roe<=tp_g,0.8,MIN(tp_g/tp_roe,0.8)))/(1+tp_r)^6+Val!D13*(1-IF(tp_roe<=tp_g,0.8,MIN(tp_g/tp_roe,0.8)))*(1+tp_g)/(tp_r-tp_g)/(1+tp_r)^6))*(1+tp_r) -> 105.3441 | D30: =Val!B35 -> 159.62649 | E30: =0.3*C30+(1-0.3)*D30 -> 143.34177 | F30: =E30/E$25-1 -> 0.081944784
A31: DCF 權重 0.7 | B31: Comparable 0.3 | C31: =(tp_wA*MAX(0,Val!B8*(1-IF(tp_roe<=tp_g,0.8,MIN(tp_g/tp_roe,0.8)))/(1+tp_r)^1+Val!B9*(1-IF(tp_roe<=tp_g,0.8,MIN(tp_g/tp_roe,0.8)))/(1+tp_r)^2+Val!B10*(1-IF(tp_roe<=tp_g,0.8,MIN(tp_g/tp_roe,0.8)))/(1+tp_r)^3+Val!B11*(1-IF(tp_roe<=tp_g,0.8,MIN(tp_g/tp_roe,0.8)))/(1+tp_r)^4+Val!B12*(1-IF(tp_roe<=tp_g,0.8,MIN(tp_g/tp_roe,0.8)))/(1+tp_r)^5+Val!B13*(1-IF(tp_roe<=tp_g,0.8,MIN(tp_g/tp_roe,0.8)))/(1+tp_r)^6+Val!B13*(1-IF(tp_roe<=tp_g,0.8,MIN(tp_g/tp_roe,0.8)))*(1+tp_g)/(tp_r-tp_g)/(1+tp_r)^6)+tp_wB*MAX(0,Val!C8*(1-IF(tp_roe<=tp_g,0.8,MIN(tp_g/tp_roe,0.8)))/(1+tp_r)^1+Val!C9*(1-IF(tp_roe<=tp_g,0.8,MIN(tp_g/tp_roe,0.8)))/(1+tp_r)^2+Val!C10*(1-IF(tp_roe<=tp_g,0.8,MIN(tp_g/tp_roe,0.8)))/(1+tp_r)^3+Val!C11*(1-IF(tp_roe<=tp_g,0.8,MIN(tp_g/tp_roe,0.8)))/(1+tp_r)^4+Val!C12*(1-IF(tp_roe<=tp_g,0.8,MIN(tp_g/tp_roe,0.8)))/(1+tp_r)^5+Val!C13*(1-IF(tp_roe<=tp_g,0.8,MIN(tp_g/tp_roe,0.8)))/(1+tp_r)^6+Val!C13*(1-IF(tp_roe<=tp_g,0.8,MIN(tp_g/tp_roe,0.8)))*(1+tp_g)/(tp_r-tp_g)/(1+tp_r)^6)+tp_wC*MAX(0,Val!D8*(1-IF(tp_roe<=tp_g,0.8,MIN(tp_g/tp_roe,0.8)))/(1+tp_r)^1+Val!D9*(1-IF(tp_roe<=tp_g,0.8,MIN(tp_g/tp_roe,0.8)))/(1+tp_r)^2+Val!D10*(1-IF(tp_roe<=tp_g,0.8,MIN(tp_g/tp_roe,0.8)))/(1+tp_r)^3+Val!D11*(1-IF(tp_roe<=tp_g,0.8,MIN(tp_g/tp_roe,0.8)))/(1+tp_r)^4+Val!D12*(1-IF(tp_roe<=tp_g,0.8,MIN(tp_g/tp_roe,0.8)))/(1+tp_r)^5+Val!D13*(1-IF(tp_roe<=tp_g,0.8,MIN(tp_g/tp_roe,0.8)))/(1+tp_r)^6+Val!D13*(1-IF(tp_roe<=tp_g,0.8,MIN(tp_g/tp_roe,0.8)))*(1+tp_g)/(tp_r-tp_g)/(1+tp_r)^6))*(1+tp_r) -> 105.3441 | D31: =Val!B35 -> 159.62649 | E31: =0.7*C31+(1-0.7)*D31 -> 121.62881 | F31: =E31/E$25-1 -> -0.081944784
A40: 案例區塊：Scorpio X 份額 低（情境 A）
A41: 項目 | B41: 單位 | C41: FY2025A | D41: FY2026（錨點） | E41: FY2027 | F41: FY2028 | G41: FY2029 | H41: 說明
A42: A. Scorpio X（D 欄＝FY2026 校準年；E–G＝FY2027–FY2029；市場為日曆年＝會計年度）
A43: 非 NVIDIA scale-up 交換晶片市場 × 情境顆數係數 | B43: US$B | D43: =msx_26 -> 2.025 | E43: =msx_27 -> 7.701 | F43: =msx_28*um28_A -> 9.468 | G43: =msx_29*um29_A -> 10.8882 | H43: AMD、Trainium、其他 ASIC 顆數 × 每顆 scale-up 交換晶片內容（網通模型）；CY2028 起乘顆數係數
A44: Astera Scorpio X 有效份額（FY2026 校準）＝ Scorpio X 營收 ÷ 市場 | B44: % | D44: =a26_x/D43 -> 0.18765432 | H44: Derived
A45: Scorpio X 有效份額相對值（÷ FY2026） | B45: x | D45: =1 -> 1 | E45: =XLO_27 -> 0.7 | F45: =XLO_28 -> 0.6 | G45: =XLO_29 -> 0.5
A46: Scorpio X 有效份額 | B46: % | D46: =$D$44*D45 -> 0.18765432 | E46: =$D$44*E45 -> 0.13135802 | F46: =$D$44*F45 -> 0.11259259 | G46: =$D$44*G45 -> 0.09382716
A47: Scorpio X 營收 | B47: US$B | C47: =a25_x -> 0 | D47: =a26_x -> 0.38 | E47: =E43*E46 -> 1.0115881 | F47: =F43*F46 -> 1.0660267 | G47: =G43*G46 -> 1.0216089
A48: B. PCIe 與訊號調節（Aries、Scorpio P、Taurus、Leo）
A49: AI 加速器顆數 × 情境顆數係數 | B49: 百萬顆 | D49: =u_26 -> 15.2 | E49: =u_27 -> 23.7 | F49: =u_28*um28_A -> 26.5 | G49: =u_29*um29_A -> 30.15
A50: PCIe／CXL／AEC 可服務市場＝顆數 × 每顆內容（c_pcie） | B50: US$B | D50: =D49*c_pcie/1000 -> 3.8 | E50: =E49*c_pcie/1000 -> 5.925 | F50: =F49*c_pcie/1000 -> 6.625 | G50: =G49*c_pcie/1000 -> 7.5375 | H50: c_pcie 只影響份額顯示，校準時抵銷
A51: Astera PCIe 等有效份額（FY2026 校準）＝ 營收 ÷ 可服務市場 | B51: % | D51: =a26_p/D50 -> 0.395595
A52: PCIe 等有效份額 × 每顆內容相對值（÷ FY2026） | B52: x | D52: =1 -> 1 | E52: =rel_p_27 -> 0.8 | F52: =rel_p_28 -> 0.75 | G52: =rel_p_29 -> 0.7
A53: PCIe 與訊號調節營收 | B53: US$B | C53: =a25_p -> 0.852525 | D53: =a26_p -> 1.503261 | E53: =E50*$D$51*E52 -> 1.8751203 | F53: =F50*$D$51*F52 -> 1.9656127 | G53: =G50*$D$51*G52 -> 2.0872581
A54: C. 合計
A55: 營收 | B55: US$B | C55: =a25_rev -> 0.852525 | D55: =D47+D53 -> 1.883261 | E55: =E47+E53 -> 2.8867084 | F55: =F47+F53 -> 3.0316393 | G55: =G47+G53 -> 3.108867
A56: 營收年增 | B56: % | D56: =D55/C55-1 -> 1.209039 | E56: =E55/D55-1 -> 0.53282442 | F56: =F55/E55-1 -> 0.050206274 | G56: =G55/F55-1 -> 0.025473903
A57: Scorpio X ÷ 營收 | B57: % | C57: =C47/C55 -> 0 | D57: =D47/D55 -> 0.20177766 | E57: =E47/E55 -> 0.35042962 | F57: =F47/F55 -> 0.35163374 | G57: =G47/G55 -> 0.32861132
A58: D. 損益（non-GAAP）
A59: 毛利率 | B59: % | C59: =a25_gp/a25_rev -> 0.75819947 | D59: =a26_gp/a26_rev -> 0.72912703 | E59: =gm_27 -> 0.7 | F59: =gm_28 -> 0.695 | G59: =gm_29 -> 0.69 | H59: FY2027 起為輸入路徑（公司長期目標 70%；交換晶片硬體占比上升）
A60: 毛利 | B60: US$B | C60: =C55*C59 -> 0.646384 | D60: =D55*D59 -> 1.3731365 | E60: =E55*E59 -> 2.0206959 | F60: =F55*F59 -> 2.1069893 | G60: =G55*G59 -> 2.1451182
A61: 營業費用（基準路徑） | B61: US$B | C61: =a25_opx -> 0.311978 | D61: =a26_opx -> 0.585698 | E61: =D61*(1+MAX(0,phi*E56)) -> 0.81216248 | F61: =E61*(1+MAX(0,phi*F56)) -> 0.84175236 | G61: =F61*(1+MAX(0,phi*G56)) -> 0.85731281
A62: 營業費用 | B62: US$B | C62: =C61 -> 0.311978 | D62: =D61 -> 0.585698 | E62: =E61+0*E55 -> 0.81216248 | F62: =F61+0*F55 -> 0.84175236 | G62: =G61+0*G55 -> 0.85731281
A63: 營業利益 | B63: US$B | C63: =C60-C62 -> 0.334406 | D63: =D60-D62 -> 0.7874385 | E63: =E60-E62 -> 1.2085334 | F63: =F60-F62 -> 1.265237 | G63: =G60-G62 -> 1.2878054
A64: 營業利益率 | B64: % | C64: =C63/C55 -> 0.3922536 | D64: =D63/D55 -> 0.418125 | E64: =E63/E55 -> 0.41865448 | F64: =F63/F55 -> 0.41734416 | G64: =G63/G55 -> 0.41423626
A65: 利息與其他收益 | B65: US$B | C65: =a25_ninc -> 0.04473 | D65: =a26_ninc -> 0.048658 | E65: =oth_f -> 0.05 | F65: =oth_f -> 0.05 | G65: =oth_f -> 0.05
A66: 有效稅率 | B66: % | C66: =a25_tx -> 0.12692279 | D66: =a26_tx -> 0.1179798 | E66: =tx_27 -> 0.12 | F66: =tx_28 -> 0.12 | G66: =tx_29 -> 0.12 | H66: 公司 non-GAAP 稅率約 12%
A67: 淨利 | B67: US$B | C67: =a25_ni -> 0.331015 | D67: =a26_ni -> 0.737454 | E67: =(E63+E65)*(1-E66) -> 1.1075094 | F67: =(F63+F65)*(1-F66) -> 1.1574085 | G67: =(G63+G65)*(1-G66) -> 1.1772688
A68: 淨利率 | B68: % | C68: =C67/C55 -> 0.388276 | D68: =D67/D55 -> 0.39158354 | E68: =E67/E55 -> 0.38365822 | F68: =F67/F55 -> 0.38177646 | G68: =G67/G55 -> 0.37868097
A69: 稀釋股數 | B69: 十億股 | C69: =a25_sh -> 0.179551 | D69: =a26_sh -> 0.18399925 | E69: =D69*(1+sh_g) -> 0.18675924 | F69: =E69*(1+sh_g) -> 0.18956063 | G69: =F69*(1+sh_g) -> 0.19240404
A70: EPS（non-GAAP） | B70: US$ | C70: =C67/C69 -> 1.8435709 | D70: =D67/D69 -> 4.0079185 | E70: =E67/E69 -> 5.9301453 | F70: =F67/F69 -> 6.1057433 | G70: =G67/G69 -> 6.1187322
A71: EPS 年增 | B71: % | D71: =D70/C70-1 -> 1.1739975 | E71: =E70/D70-1 -> 0.47960725 | F71: =F70/E70-1 -> 0.029611084 | G71: =G70/F70-1 -> 0.0021273241
A74: 案例區塊：Scorpio X 份額 高（情境 A）
A75: 項目 | B75: 單位 | C75: FY2025A | D75: FY2026（錨點） | E75: FY2027 | F75: FY2028 | G75: FY2029 | H75: 說明
A76: A. Scorpio X（D 欄＝FY2026 校準年；E–G＝FY2027–FY2029；市場為日曆年＝會計年度）
A77: 非 NVIDIA scale-up 交換晶片市場 × 情境顆數係數 | B77: US$B | D77: =msx_26 -> 2.025 | E77: =msx_27 -> 7.701 | F77: =msx_28*um28_A -> 9.468 | G77: =msx_29*um29_A -> 10.8882 | H77: AMD、Trainium、其他 ASIC 顆數 × 每顆 scale-up 交換晶片內容（網通模型）；CY2028 起乘顆數係數
A78: Astera Scorpio X 有效份額（FY2026 校準）＝ Scorpio X 營收 ÷ 市場 | B78: % | D78: =a26_x/D77 -> 0.18765432 | H78: Derived
A79: Scorpio X 有效份額相對值（÷ FY2026） | B79: x | D79: =1 -> 1 | E79: =XHI_27 -> 1.4 | F79: =XHI_28 -> 1.7 | G79: =XHI_29 -> 2
A80: Scorpio X 有效份額 | B80: % | D80: =$D$78*D79 -> 0.18765432 | E80: =$D$78*E79 -> 0.26271605 | F80: =$D$78*F79 -> 0.31901235 | G80: =$D$78*G79 -> 0.37530864
A81: Scorpio X 營收 | B81: US$B | C81: =a25_x -> 0 | D81: =a26_x -> 0.38 | E81: =E77*E80 -> 2.0231763 | F81: =F77*F80 -> 3.0204089 | G81: =G77*G80 -> 4.0864356
A82: B. PCIe 與訊號調節（Aries、Scorpio P、Taurus、Leo）
A83: AI 加速器顆數 × 情境顆數係數 | B83: 百萬顆 | D83: =u_26 -> 15.2 | E83: =u_27 -> 23.7 | F83: =u_28*um28_A -> 26.5 | G83: =u_29*um29_A -> 30.15
A84: PCIe／CXL／AEC 可服務市場＝顆數 × 每顆內容（c_pcie） | B84: US$B | D84: =D83*c_pcie/1000 -> 3.8 | E84: =E83*c_pcie/1000 -> 5.925 | F84: =F83*c_pcie/1000 -> 6.625 | G84: =G83*c_pcie/1000 -> 7.5375 | H84: c_pcie 只影響份額顯示，校準時抵銷
A85: Astera PCIe 等有效份額（FY2026 校準）＝ 營收 ÷ 可服務市場 | B85: % | D85: =a26_p/D84 -> 0.395595
A86: PCIe 等有效份額 × 每顆內容相對值（÷ FY2026） | B86: x | D86: =1 -> 1 | E86: =rel_p_27 -> 0.8 | F86: =rel_p_28 -> 0.75 | G86: =rel_p_29 -> 0.7
A87: PCIe 與訊號調節營收 | B87: US$B | C87: =a25_p -> 0.852525 | D87: =a26_p -> 1.503261 | E87: =E84*$D$85*E86 -> 1.8751203 | F87: =F84*$D$85*F86 -> 1.9656127 | G87: =G84*$D$85*G86 -> 2.0872581
A88: C. 合計
A89: 營收 | B89: US$B | C89: =a25_rev -> 0.852525 | D89: =D81+D87 -> 1.883261 | E89: =E81+E87 -> 3.8982966 | F89: =F81+F87 -> 4.9860215 | G89: =G81+G87 -> 6.1736937
A90: 營收年增 | B90: % | D90: =D89/C89-1 -> 1.209039 | E90: =E89/D89-1 -> 1.0699715 | F90: =F89/E89-1 -> 0.2790257 | G90: =G89/F89-1 -> 0.23820036
A91: Scorpio X ÷ 營收 | B91: % | C91: =C81/C89 -> 0 | D91: =D81/D89 -> 0.20177766 | E91: =E81/E89 -> 0.51898983 | F91: =F81/F89 -> 0.60577534 | G91: =G81/G89 -> 0.66191097
A92: D. 損益（non-GAAP）
A93: 毛利率 | B93: % | C93: =a25_gp/a25_rev -> 0.75819947 | D93: =a26_gp/a26_rev -> 0.72912703 | E93: =gm_27 -> 0.7 | F93: =gm_28 -> 0.695 | G93: =gm_29 -> 0.69 | H93: FY2027 起為輸入路徑（公司長期目標 70%；交換晶片硬體占比上升）
A94: 毛利 | B94: US$B | C94: =C89*C93 -> 0.646384 | D94: =D89*D93 -> 1.3731365 | E94: =E89*E93 -> 2.7288076 | F94: =F89*F93 -> 3.465285 | G94: =G89*G93 -> 4.2598486
A95: 營業費用（基準路徑） | B95: US$B | C95: =a25_opx -> 0.311978 | D95: =a26_opx -> 0.585698 | E95: =D95*(1+MAX(0,phi*E90)) -> 1.0404642 | F95: =E95*(1+MAX(0,phi*F90)) -> 1.2511395 | G95: =F95*(1+MAX(0,phi*G90)) -> 1.4674066
A96: 營業費用 | B96: US$B | C96: =C95 -> 0.311978 | D96: =D95 -> 0.585698 | E96: =E95+0*E89 -> 1.0404642 | F96: =F95+0*F89 -> 1.2511395 | G96: =G95+0*G89 -> 1.4674066
A97: 營業利益 | B97: US$B | C97: =C94-C96 -> 0.334406 | D97: =D94-D96 -> 0.7874385 | E97: =E94-E96 -> 1.6883434 | F97: =F94-F96 -> 2.2141455 | G97: =G94-G96 -> 2.7924421
A98: 營業利益率 | B98: % | C98: =C97/C89 -> 0.3922536 | D98: =D97/D89 -> 0.418125 | E98: =E97/E89 -> 0.43309773 | F98: =F97/F89 -> 0.44407058 | G98: =G97/G89 -> 0.45231303
A99: 利息與其他收益 | B99: US$B | C99: =a25_ninc -> 0.04473 | D99: =a26_ninc -> 0.048658 | E99: =oth_f -> 0.05 | F99: =oth_f -> 0.05 | G99: =oth_f -> 0.05
A100: 有效稅率 | B100: % | C100: =a25_tx -> 0.12692279 | D100: =a26_tx -> 0.1179798 | E100: =tx_27 -> 0.12 | F100: =tx_28 -> 0.12 | G100: =tx_29 -> 0.12 | H100: 公司 non-GAAP 稅率約 12%
A101: 淨利 | B101: US$B | C101: =a25_ni -> 0.331015 | D101: =a26_ni -> 0.737454 | E101: =(E97+E99)*(1-E100) -> 1.5297422 | F101: =(F97+F99)*(1-F100) -> 1.992448 | G101: =(G97+G99)*(1-G100) -> 2.501349
A102: 淨利率 | B102: % | C102: =C101/C89 -> 0.388276 | D102: =D101/D89 -> 0.39158354 | E102: =E101/E89 -> 0.39241298 | F102: =F101/F89 -> 0.39960678 | G102: =G101/G89 -> 0.40516248
A103: 稀釋股數 | B103: 十億股 | C103: =a25_sh -> 0.179551 | D103: =a26_sh -> 0.18399925 | E103: =D103*(1+sh_g) -> 0.18675924 | F103: =E103*(1+sh_g) -> 0.18956063 | G103: =F103*(1+sh_g) -> 0.19240404
A104: EPS（non-GAAP） | B104: US$ | C104: =C101/C103 -> 1.8435709 | D104: =D101/D103 -> 4.0079185 | E104: =E101/E103 -> 8.1909854 | F104: =F101/F103 -> 10.510875 | G104: =G101/G103 -> 13.000502
A105: EPS 年增 | B105: % | D105: =D104/C104-1 -> 1.1739975 | E105: =E104/D104-1 -> 1.0437006 | F105: =F104/E104-1 -> 0.2832247 | G105: =G104/F104-1 -> 0.23686202
A108: 案例區塊：PCIe 等份額 低（情境 A）
A109: 項目 | B109: 單位 | C109: FY2025A | D109: FY2026（錨點） | E109: FY2027 | F109: FY2028 | G109: FY2029 | H109: 說明
A110: A. Scorpio X（D 欄＝FY2026 校準年；E–G＝FY2027–FY2029；市場為日曆年＝會計年度）
A111: 非 NVIDIA scale-up 交換晶片市場 × 情境顆數係數 | B111: US$B | D111: =msx_26 -> 2.025 | E111: =msx_27 -> 7.701 | F111: =msx_28*um28_A -> 9.468 | G111: =msx_29*um29_A -> 10.8882 | H111: AMD、Trainium、其他 ASIC 顆數 × 每顆 scale-up 交換晶片內容（網通模型）；CY2028 起乘顆數係數
A112: Astera Scorpio X 有效份額（FY2026 校準）＝ Scorpio X 營收 ÷ 市場 | B112: % | D112: =a26_x/D111 -> 0.18765432 | H112: Derived
A113: Scorpio X 有效份額相對值（÷ FY2026） | B113: x | D113: =1 -> 1 | E113: =rel_x_27 -> 1 | F113: =rel_x_28 -> 1.1 | G113: =rel_x_29 -> 1.15
A114: Scorpio X 有效份額 | B114: % | D114: =$D$112*D113 -> 0.18765432 | E114: =$D$112*E113 -> 0.18765432 | F114: =$D$112*F113 -> 0.20641975 | G114: =$D$112*G113 -> 0.21580247
A115: Scorpio X 營收 | B115: US$B | C115: =a25_x -> 0 | D115: =a26_x -> 0.38 | E115: =E111*E114 -> 1.4451259 | F115: =F111*F114 -> 1.9543822 | G115: =G111*G114 -> 2.3497004
...

Sheet Sources
A1: 來源（公司原文＝SEC 8-K 新聞稿與 10-K）
A2: 公司：2Q26 實績、3Q26 指引（8-K 附件 99.1；含 1Q26、1H 比較欄與資產負債表） | B2: https://www.sec.gov/Archives/edgar/data/0001736297/000173629726000033/q226exhibit991.htm
A3: 公司：2Q26 新聞稿（IR 網站） | B3: https://ir.asteralabs.com/news-releases/news-release-details/astera-labs-reports-second-quarter-2026-financial-results
A4: 公司：4Q25 與 FY2025 實績、1Q26 指引、2030 年商用 scale-up 交換市場 200 億美元（8-K 附件 99.1） | B4: https://www.sec.gov/Archives/edgar/data/1736297/000173629726000005/q425exhibit991.htm
A5: 公司：FY2025 10-K（客戶集中、競爭者、股數） | B5: https://www.sec.gov/Archives/edgar/data/1736297/000173629726000010/alab-20251231.htm
A6: 二手：2Q26 法說摘要（Scorpio 3Q26 成為最大產品線、X 超過 P、逾 10 家客戶、長期毛利率 70%、Taurus 2030 年逾 40 億美元） | B6: https://www.marketbeat.com/instant-alerts/astera-labs-q2-earnings-call-highlights-2026-08-04/
A7: 二手：2Q26 分析（Futurum；毛利率下滑原因、客戶集中） | B7: https://futurumgroup.com/insights/astera-labs-q2-fy-2026-earnings-pull-scorpio-switch-leadership-forward/
A8: 二手：1Q26 法說逐字稿（每顆加速器內容逾 1,000 美元、Scorpio 1Q26 約 20% 為分析師引述） | B8: https://www.fool.com/earnings/call-transcripts/2026/05/05/astera-labs-alab-q1-2026-earnings-transcript/
A9: 二手：TIKR（2026-03；Scorpio 逾 FY2025 營收 15%、Amazon 認股權證） | B9: https://www.tikr.com/blog/astera-labs-what-a-224-bull-case-looks-like
A10: 共識：Yahoo Finance 分析師預估（2026-10-23 頁面） | B10: https://finance.yahoo.com/quote/ALAB/analysis/
A11: 共識：StockAnalysis 預估與目標價（資料 2026-10-16） | B11: https://stockanalysis.com/stocks/alab/forecast/
A12: 共識：MarketScreener 年度預估（FY2028 營收、GAAP EPS） | B12: https://uk.marketscreener.com/quote/stock/ASTERA-LABS-INC-167508773/finances/
A13: 共識：Tickflow（目標價第二來源；頁面數字前後不一致） | B13: https://www.tickflow.io/stock/ALAB/forecast
... A18: 同業前瞻 P/E：StockAnalysis statistics 頁（CRDO、MRVL、AVGO、RMBS、MTSI；2026-10-23） | B18: https://stockanalysis.com/stocks/crdo/statistics/
A19: 市場層：markets/network、tsmc 成品（本 repo，唯讀）
A20: 待補（人工）：3Q26 財報；產品線營收拆分（Aries、Taurus、Leo、Scorpio P／X）；客戶名稱第一手出處；每顆加速器 PCIe 內容第一手來源；FY2028 non-GAAP 共識；前瞻 P/E 歷史（Bloomberg） | B20: 未找到
A21: SemiAnalysis | B21: 未使用
