Workbook

Sheet README
A1: Siliconomics v0.10 — AI 半導體產業基準庫（20261031）
A2: 用途：AI 半導體各子產業的『唯一事實』——加速器顆數、HBM 與記憶體價格、網通內容、CoWoS、載板、伺服器組裝、電源散熱、設備等行業變數只有一個值；各公司模型只讀本庫 Interface 的 SIF_ 名稱。
A3: 與 Tokenomics 的分工：每 GW 硬體量、機架價、每 GW 資本支出、NonNV 比例、產業年度部署路徑（R4）權威在 Tokenomics／算力收支，本庫只在 TK_In 頁鏡像（綠字、不得修改）；晶片產業資訊（HBM 單價與容量、每顆內容、網通內容、份額、出貨顆數、ASIC 規格、晶圓與設備）權威在本庫（《情境卡產生規則》第 13 條）。
A4: v0.1 範圍：(1) Tokenomics v21.7 鏡像（22 個名稱）與下游舊快照差異；(2) 加速器顆數層、記憶體價格路徑、HBM 市場（由 markets/memory/market.py 逐字搬入，數值不變）；(3) 跨模型衝突登錄；(4) Interface、Checks、Decisions。網通、CoWoS、載板、組裝電源散熱、設備依規劃書分段併入。
A5: v0.2：In 頁 Assumed 列全部補上區間、缺來源列補來源；新增 M5 節 2029 平台別顆數成長（單一來源，取代台積電、網通模型的寫死值與 NAND 模型的合計年增）與 Units 頁；Interface 新增 SIF_UnitsPlat_*、SIF_UnitsGrowth29。
A6: v0.3：新增 M6 節（加速器每顆售價、ASIC 核心價、HBM 代購比例；原在 nvidia、avgo 模型）與 M7 節（ASIC 設計服務份額；原在 avgo、mrvl、mediatek、alchip 模型）、ShareTbl 頁（同一平台份額加總 ≤ 100%）；In 頁新增 J 欄第二來源。
A7: v0.10：NAND 季價 2026Q3 改用公司實現平均售價 +25%（原合約價 +15%；Kioxia、SK 海力士實績 mid-20%），2026Q4 改為兩季累計不變的餘額 +8.1%（原 +17.5%）；2027 起價格水準不變。決策 S30。
A8: v0.9：CY2026 SoC 測試機市場 ts_mk_soc26 由 11.0 改為 11.5（Advantest 2026-10-28 稱約 115 億美元；Advantest＋泰瑞達 CY2026 SoC 營收合計約 113 億美元已高於舊值）；每加權顆測試支出與 CY2027 起 SoC 市場隨之上升。決策 S29。
A9: v0.8.4：來源複核後修正標記與來源文字：DRAM／NAND 情境季價路徑 2027–28 改標 Derived、2029 改標 Assumed（區間＝情境 A、B）；Advantest 測試機市場來源改為 2026-07-29 原文；輸入值不變。
A10: v0.8.3：衝突登錄清理（CF02、CF05–08、CF16 結案；CF01 移到南電分部重建）；無新增輸入。
A11: v0.8.2：新增 M26（共用匯率：新台幣 32.0、人民幣 6.72、韓元 1,420；台、陸、韓 21 個模型改讀；日圓為公司財測前提，不共用）。
A12: v0.8.1：新增 M25（AI 伺服器組裝：廣達、鴻海、緯創本體、緯穎 FY2026 有效份額快照與 2027–29 份額相對值、緯穎 ASIC 比重；原在 quanta、foxconn、wistron、wiwynn）、ShareTbl 的組裝份額表（含緯穎 ASIC 傾斜係數）、Checks K6-asm、Interface SIF_AsmShareSum、SIF_AsmWyTilt、SIF_AsmShare_wy；CF23 登錄（緯創模型的緯穎份額路徑與緯穎模型不同）。
... A28: 版本命名：YYYYMMDD_Siliconomics_vX.Y.xlsx；model/CURRENT 記錄現行檔名。只改證據或標記為修補版；輸入值或公式改變為次版；Interface 名稱刪除或定義改變為主版（v1.0 前只新增名稱以次版處理）。

Sheet Scen
A1: Scen — 行業情境定義（A＝順利、B＝平平、C＝不如預期）。各公司模型的 A／B／C 一律讀同字母行業情境（Andy 2026-10-25 13:13）
A3: 情境 | B3: 名稱 | C3: 定義（顆數與部署） | D3: 記憶體價格路徑 | E3: 2028 顆數 ÷ 基準 | F3: 2029 顆數 ÷ 基準 | G3: 2030–2032
A4: A | B4: 順利 | C4: 基準顆數（市場層 2026–2028 預測）；部署順利、新技術導入快 | D4: 2027–28 高檔持平、2029 緩降（BofA、TrendForce 型） | E4: =um28_A -> 1 | F4: =um29_A -> 1 | G4: 未定：待算力收支 R4 產業部署路徑（預計 10-31 後）；各公司模型目前以收斂法自推
A5: B | B5: 平平 | C5: AI 資本支出消化：2028 顆數約為基準 0.8、2029 約 0.85 | D5: 2027 Q2 見頂、2028 回落約一半、2029 溫和回升（Citi、Bernstein 型） | E5: =um28_B -> 0.8 | F5: =um29_B -> 0.85 | G5: 未定：待算力收支 R4 產業部署路徑（預計 10-31 後）；各公司模型目前以收斂法自推
A6: C | B6: 不如預期 | C6: 明顯下修：2028、2029 顆數約為基準 0.6 | D6: 2028 回到 2025 年價格水準、2029 自谷底回升（完整循環） | E6: =um28_C -> 0.6 | F6: =um29_C -> 0.6 | G6: 未定：待算力收支 R4 產業部署路徑（預計 10-31 後）；各公司模型目前以收斂法自推
A9: 說明
A10: 情境係數只定義 2028–29（Assumed，無外部預測可校準；B、C 區間 ±0.1，見 In 頁 M2b）。R4 上線後，2026–2030 的部署 GW 三情境改讀算力收支（權威在算力收支，第 13 條），本頁的係數改為由部署路徑推導。

Sheet In
A1: In — 產業輸入（藍字＝輸入，由本活頁簿擁有；要改值直接改本頁，builder 重建時讀回）。每列具名範圍＝鍵（指向 E 欄），另有 _lo／_hi（D、F 欄）
A2: 標記：Verified／Interested-party（寫明是誰）／Analogy／Assumed（給低／高區間）／Derived（寫明換算）。v0.1 內容由 markets/memory/market.py 逐字搬入（數值、標記、來源文字不變）
A4: 鍵 | B4: 項目 | C4: 單位 | D4: 低 | E4: 基準 | F4: 高 | G4: 標記 | H4: 來源／說明 | I4: Interface 名稱 | J4: 第二來源／說明
A5: M1. 記憶體價格路徑（季增，共用市場層 markets/memory）
A6: cq_1 | B6: 一般 DRAM 合約價季增 2025Q2 | C6: % | E6: -0.025 | G6: Interested-party | H6: TrendForce 合約價：2Q25 0~−5%、3Q25 +10~15%、4Q25 實際 +45~50%、1Q26 實際約 +93~98%、2Q26 +58~63%、3Q26 +13~18%（MS 實際約 +15%）、4Q26 +10~15% | I6: SIF_cq_1
A7: cq_2 | B7: 一般 DRAM 合約價季增 2025Q3 | C7: % | E7: 0.125 | G7: Interested-party | H7: 同上 | I7: SIF_cq_2
A8: cq_3 | B8: 一般 DRAM 合約價季增 2025Q4 | C8: % | E8: 0.475 | G8: Interested-party | H8: 同上 | I8: SIF_cq_3
A9: cq_4 | B9: 一般 DRAM 合約價季增 2026Q1 | C9: % | E9: 0.95 | G9: Interested-party | H9: 同上 | I9: SIF_cq_4
A10: cq_5 | B10: 一般 DRAM 合約價季增 2026Q2 | C10: % | E10: 0.605 | G10: Interested-party | H10: 同上 | I10: SIF_cq_5
A11: cq_6 | B11: 一般 DRAM 合約價季增 2026Q3 | C11: % | E11: 0.155 | G11: Interested-party | H11: 同上 | I11: SIF_cq_6
A12: cq_7 | B12: 一般 DRAM 合約價季增 2026Q4 | C12: % | E12: 0.125 | G12: Interested-party | H12: 同上 | I12: SIF_cq_7
A13: cqA_8 | B13: 一般 DRAM 合約價季增 2027Q1（A） | C13: % | E13: 0.03 | G13: Derived | H13: 本庫情境路徑，依據：BofA：2027 持平略降、2027 均價仍高於 2026；2028 溫和修正（年均約 −10%）；2029 Assumed 緩降（2026-10-28 來源複核：來源無逐季數字，逐季值為本庫拆分） | I13: SIF_cqA_8
A14: cqA_9 | B14: 一般 DRAM 合約價季增 2027Q2（A） | C14: % | E14: 0 | G14: Derived | H14: 同上 | I14: SIF_cqA_9
A15: cqA_10 | B15: 一般 DRAM 合約價季增 2027Q3（A） | C15: % | E15: -0.02 | G15: Derived | H15: 同上 | I15: SIF_cqA_10
A16: cqA_11 | B16: 一般 DRAM 合約價季增 2027Q4（A） | C16: % | E16: -0.03 | G16: Derived | H16: 同上 | I16: SIF_cqA_11
A17: cqA_12 | B17: 一般 DRAM 合約價季增 2028Q1（A） | C17: % | E17: -0.03 | G17: Derived | H17: 同上 | I17: SIF_cqA_12
... A20: cqA_15 | B20: 一般 DRAM 合約價季增 2028Q4（A） | C20: % | E20: -0.02 | G20: Derived | H20: 同上 | I20: SIF_cqA_15
A21: cqA_16 | B21: 一般 DRAM 合約價季增 2029Q1（A） | C21: % | D21: -0.03 | E21: -0.03 | F21: 0.05 | G21: Assumed | H21: 2029 為本庫外推：標示來源只涵蓋到 2028（2026-10-28 來源複核）；區間＝情境 A、B 同季值 | I21: SIF_cqA_16
A22: cqA_17 | B22: 一般 DRAM 合約價季增 2029Q2（A） | C22: % | D22: -0.03 | E22: -0.03 | F22: 0.05 | G22: Assumed | H22: 同上 | I22: SIF_cqA_17
A23: cqA_18 | B23: 一般 DRAM 合約價季增 2029Q3（A） | C23: % | D23: -0.02 | E23: -0.02 | F23: 0.03 | G23: Assumed | H23: 同上 | I23: SIF_cqA_18
A24: cqA_19 | B24: 一般 DRAM 合約價季增 2029Q4（A） | C24: % | D24: -0.02 | E24: -0.02 | F24: 0.03 | G24: Assumed | H24: 同上 | I24: SIF_cqA_19
A25: cqB_8 | B25: 一般 DRAM 合約價季增 2027Q1（B） | C25: % | E25: 0.05 | G25: Derived | H25: 本庫情境路徑，依據：Citi：2027 Q2 見頂；Bernstein：2028 DRAM $/GB −52.9%（本路徑 2028 年均約 −47%）；2029 Assumed 溫和回升（2026-10-28 來源複核：來源無逐季數字，逐季值為本庫拆分） | I25: SIF_cqB_8
A26: cqB_9 | B26: 一般 DRAM 合約價季增 2027Q2（B） | C26: % | E26: 0.02 | G26: Derived | H26: 同上 | I26: SIF_cqB_9
A27: cqB_10 | B27: 一般 DRAM 合約價季增 2027Q3（B） | C27: % | E27: -0.08 | G27: Derived | H27: 同上 | I27: SIF_cqB_10
A28: cqB_11 | B28: 一般 DRAM 合約價季增 2027Q4（B） | C28: % | E28: -0.15 | G28: Derived | H28: 同上 | I28: SIF_cqB_11
A29: cqB_12 | B29: 一般 DRAM 合約價季增 2028Q1（B） | C29: % | E29: -0.25 | G29: Derived | H29: 同上 | I29: SIF_cqB_12
A30: cqB_13 | B30: 一般 DRAM 合約價季增 2028Q2（B） | C30: % | E30: -0.15 | G30: Derived | H30: 同上 | I30: SIF_cqB_13
A31: cqB_14 | B31: 一般 DRAM 合約價季增 2028Q3（B） | C31: % | E31: -0.1 | G31: Derived | H31: 同上 | I31: SIF_cqB_14
A32: cqB_15 | B32: 一般 DRAM 合約價季增 2028Q4（B） | C32: % | E32: -0.05 | G32: Derived | H32: 同上 | I32: SIF_cqB_15
A33: cqB_16 | B33: 一般 DRAM 合約價季增 2029Q1（B） | C33: % | D33: -0.03 | E33: 0.05 | F33: 0.05 | G33: Assumed | H33: 2029 為本庫外推：標示來源只涵蓋到 2028（2026-10-28 來源複核）；區間＝情境 A、B 同季值 | I33: SIF_cqB_16
A34: cqB_17 | B34: 一般 DRAM 合約價季增 2029Q2（B） | C34: % | D34: -0.03 | E34: 0.05 | F34: 0.05 | G34: Assumed | H34: 同上 | I34: SIF_cqB_17
A35: cqB_18 | B35: 一般 DRAM 合約價季增 2029Q3（B） | C35: % | D35: -0.02 | E35: 0.03 | F35: 0.03 | G35: Assumed | H35: 同上 | I35: SIF_cqB_18
A36: cqB_19 | B36: 一般 DRAM 合約價季增 2029Q4（B） | C36: % | D36: -0.02 | E36: 0.03 | F36: 0.03 | G36: Assumed | H36: 同上 | I36: SIF_cqB_19
A37: cqC_8 | B37: 一般 DRAM 合約價季增 2027Q1（C） | C37: % | D37: 0 | E37: 0.05 | F37: 0.1 | G37: Assumed | H37: Assumed：2028 年底回到約 2025Q4 水準（自高點約 −79%），比照 2019、2023 年谷底；2029 自谷底回升。區間（v0.2）：2027 各季 ±5pt、2028–29 各季 ±10pt，表示路徑形狀的不確定（Assumed），不是另一個情境 | I37: SIF_cqC_8
A38: cqC_9 | B38: 一般 DRAM 合約價季增 2027Q2（C） | C38: % | D38: -0.03 | E38: 0.02 | F38: 0.07 | G38: Assumed | H38: 同上 | I38: SIF_cqC_9
A39: cqC_10 | B39: 一般 DRAM 合約價季增 2027Q3（C） | C39: % | D39: -0.13 | E39: -0.08 | F39: -0.03 | G39: Assumed | H39: 同上 | I39: SIF_cqC_10
A40: cqC_11 | B40: 一般 DRAM 合約價季增 2027Q4（C） | C40: % | D40: -0.2 | E40: -0.15 | F40: -0.1 | G40: Assumed | H40: 同上 | I40: SIF_cqC_11
A41: cqC_12 | B41: 一般 DRAM 合約價季增 2028Q1（C） | C41: % | D41: -0.45 | E41: -0.35 | F41: -0.25 | G41: Assumed | H41: 同上 | I41: SIF_cqC_12
A42: cqC_13 | B42: 一般 DRAM 合約價季增 2028Q2（C） | C42: % | D42: -0.4 | E42: -0.3 | F42: -0.2 | G42: Assumed | H42: 同上 | I42: SIF_cqC_13
A43: cqC_14 | B43: 一般 DRAM 合約價季增 2028Q3（C） | C43: % | D43: -0.35 | E43: -0.25 | F43: -0.15 | G43: Assumed | H43: 同上 | I43: SIF_cqC_14
A44: cqC_15 | B44: 一般 DRAM 合約價季增 2028Q4（C） | C44: % | D44: -0.3 | E44: -0.2 | F44: -0.1 | G44: Assumed | H44: 同上 | I44: SIF_cqC_15
... A48: cqC_19 | B48: 一般 DRAM 合約價季增 2029Q4（C） | C48: % | D48: 0 | E48: 0.1 | F48: 0.2 | G48: Assumed | H48: 同上 | I48: SIF_cqC_19
A49: nq_1 | B49: NAND 合約價季增 2025Q2 | C49: % | E49: 0 | G49: Interested-party | H49: TrendForce：1Q26 +85~90%、2Q26 +70~75%、3Q26 +10~15%（MS 實際約 +20%）、4Q26 +15~20%；2025Q2–Q4 為 Assumed | I49: SIF_nq_1
A50: nq_2 | B50: NAND 合約價季增 2025Q3 | C50: % | E50: 0.05 | G50: Interested-party | H50: 同上 | I50: SIF_nq_2
A51: nq_3 | B51: NAND 合約價季增 2025Q4 | C51: % | E51: 0.3 | G51: Interested-party | H51: 同上 | I51: SIF_nq_3
A52: nq_4 | B52: NAND 合約價季增 2026Q1 | C52: % | E52: 0.875 | G52: Interested-party | H52: 同上 | I52: SIF_nq_4
A53: nq_5 | B53: NAND 合約價季增 2026Q2 | C53: % | E53: 0.725 | G53: Interested-party | H53: 同上 | I53: SIF_nq_5
A54: nq_6 | B54: NAND 合約價季增 2026Q3 | C54: % | E54: 0.25 | G54: Verified | H54: 2026Q3 改用公司實現平均售價（2026-10-31 NAND 第四季對帳）：Kioxia 第二季（7–9 月）NAND 平均售價季增 mid-20%（Investing.com、Bloomberg 2026-10-30）、SK 海力士 3Q26 NAND 平均售價季增 mid-20%（法說 2026-10-28）；TrendForce 合約價 +10~15%（MS 約 +20%）只作對照 | I54: SIF_nq_6
A55: nq_7 | B55: NAND 合約價季增 2026Q4 | C55: % | D55: 0.032 | E55: =(1+0.15)*(1+0.175)/(1+0.25)-1 -> 0.081 | F55: 0.175 | G55: Derived | H55: 保留 TrendForce 合約價兩季累計（3Q26 +15%、4Q26 +17.5%）＝1.351，扣除 2026Q3 實現 +25% 後的餘額＝+8.1%（實現價提前一季）；對照：SanDisk FQ2 FY27 指引隱含約 +7%（位元同市場時）、Kioxia 第三季指引平均售價季增低個位數（產品組合轉差）。低＝Kioxia 實現兩季累計 1.25×1.032（2027 起價格水準約 −4.5%）；高＝TrendForce 4Q26 合約價 +17.5% | I55: SIF_nq_7
A56: nqA_8 | B56: NAND 合約價季增 2027Q1（A） | C56: % | E56: 0.03 | G56: Derived | H56: 本庫情境路徑，依據：TrendForce：2027 下半年供需平衡、價格面臨下修壓力（2026-10-28 來源複核：來源無逐季數字，逐季值為本庫拆分） | I56: SIF_nqA_8
A57: nqA_9 | B57: NAND 合約價季增 2027Q2（A） | C57: % | E57: 0 | G57: Derived | H57: 同上 | I57: SIF_nqA_9
A58: nqA_10 | B58: NAND 合約價季增 2027Q3（A） | C58: % | E58: -0.05 | G58: Derived | H58: 同上 | I58: SIF_nqA_10
A59: nqA_11 | B59: NAND 合約價季增 2027Q4（A） | C59: % | E59: -0.07 | G59: Derived | H59: 同上 | I59: SIF_nqA_11
A60: nqA_12 | B60: NAND 合約價季增 2028Q1（A） | C60: % | E60: -0.05 | G60: Derived | H60: 同上 | I60: SIF_nqA_12
A61: nqA_13 | B61: NAND 合約價季增 2028Q2（A） | C61: % | E61: -0.05 | G61: Derived | H61: 同上 | I61: SIF_nqA_13
A62: nqA_14 | B62: NAND 合約價季增 2028Q3（A） | C62: % | E62: -0.05 | G62: Derived | H62: 同上 | I62: SIF_nqA_14
A63: nqA_15 | B63: NAND 合約價季增 2028Q4（A） | C63: % | E63: -0.05 | G63: Derived | H63: 同上 | I63: SIF_nqA_15
A64: nqA_16 | B64: NAND 合約價季增 2029Q1（A） | C64: % | D64: -0.03 | E64: -0.03 | F64: 0.05 | G64: Assumed | H64: 2029 為本庫外推：標示來源只涵蓋到 2028（2026-10-28 來源複核）；區間＝情境 A、B 同季值 | I64: SIF_nqA_16
A65: nqA_17 | B65: NAND 合約價季增 2029Q2（A） | C65: % | D65: -0.03 | E65: -0.03 | F65: 0.05 | G65: Assumed | H65: 同上 | I65: SIF_nqA_17
A66: nqA_18 | B66: NAND 合約價季增 2029Q3（A） | C66: % | D66: -0.03 | E66: -0.03 | F66: 0.03 | G66: Assumed | H66: 同上 | I66: SIF_nqA_18
A67: nqA_19 | B67: NAND 合約價季增 2029Q4（A） | C67: % | D67: -0.03 | E67: -0.03 | F67: 0.03 | G67: Assumed | H67: 同上 | I67: SIF_nqA_19
A68: nqB_8 | B68: NAND 合約價季增 2027Q1（B） | C68: % | E68: 0.05 | G68: Derived | H68: 本庫情境路徑，依據：Citi：2027 Q2 見頂；Bernstein：NAND $/GB 2028 −68.8%（2026-10-28 來源複核：來源無逐季數字，逐季值為本庫拆分） | I68: SIF_nqB_8
A69: nqB_9 | B69: NAND 合約價季增 2027Q2（B） | C69: % | E69: 0.02 | G69: Derived | H69: 同上 | I69: SIF_nqB_9
A70: nqB_10 | B70: NAND 合約價季增 2027Q3（B） | C70: % | E70: -0.1 | G70: Derived | H70: 同上 | I70: SIF_nqB_10
A71: nqB_11 | B71: NAND 合約價季增 2027Q4（B） | C71: % | E71: -0.2 | G71: Derived | H71: 同上 | I71: SIF_nqB_11
A72: nqB_12 | B72: NAND 合約價季增 2028Q1（B） | C72: % | E72: -0.3 | G72: Derived | H72: 同上 | I72: SIF_nqB_12
A73: nqB_13 | B73: NAND 合約價季增 2028Q2（B） | C73: % | E73: -0.25 | G73: Derived | H73: 同上 | I73: SIF_nqB_13
A74: nqB_14 | B74: NAND 合約價季增 2028Q3（B） | C74: % | E74: -0.2 | G74: Derived | H74: 同上 | I74: SIF_nqB_14
A75: nqB_15 | B75: NAND 合約價季增 2028Q4（B） | C75: % | E75: -0.1 | G75: Derived | H75: 同上 | I75: SIF_nqB_15
A76: nqB_16 | B76: NAND 合約價季增 2029Q1（B） | C76: % | D76: -0.03 | E76: 0.05 | F76: 0.05 | G76: Assumed | H76: 2029 為本庫外推：標示來源只涵蓋到 2028（2026-10-28 來源複核）；區間＝情境 A、B 同季值 | I76: SIF_nqB_16
A77: nqB_17 | B77: NAND 合約價季增 2029Q2（B） | C77: % | D77: -0.03 | E77: 0.05 | F77: 0.05 | G77: Assumed | H77: 同上 | I77: SIF_nqB_17
A78: nqB_18 | B78: NAND 合約價季增 2029Q3（B） | C78: % | D78: -0.03 | E78: 0.03 | F78: 0.03 | G78: Assumed | H78: 同上 | I78: SIF_nqB_18
A79: nqB_19 | B79: NAND 合約價季增 2029Q4（B） | C79: % | D79: -0.03 | E79: 0.03 | F79: 0.03 | G79: Assumed | H79: 同上 | I79: SIF_nqB_19
A80: nqC_8 | B80: NAND 合約價季增 2027Q1（C） | C80: % | D80: 0 | E80: 0.05 | F80: 0.1 | G80: Assumed | H80: Assumed：回到約 2025 年水準。區間（v0.2）：2027 各季 ±5pt、2028–29 各季 ±10pt，表示路徑形狀的不確定（Assumed），不是另一個情境 | I80: SIF_nqC_8
A81: nqC_9 | B81: NAND 合約價季增 2027Q2（C） | C81: % | D81: -0.03 | E81: 0.02 | F81: 0.07 | G81: Assumed | H81: 同上 | I81: SIF_nqC_9
A82: nqC_10 | B82: NAND 合約價季增 2027Q3（C） | C82: % | D82: -0.15 | E82: -0.1 | F82: -0.05 | G82: Assumed | H82: 同上 | I82: SIF_nqC_10
A83: nqC_11 | B83: NAND 合約價季增 2027Q4（C） | C83: % | D83: -0.25 | E83: -0.2 | F83: -0.15 | G83: Assumed | H83: 同上 | I83: SIF_nqC_11
A84: nqC_12 | B84: NAND 合約價季增 2028Q1（C） | C84: % | D84: -0.45 | E84: -0.35 | F84: -0.25 | G84: Assumed | H84: 同上 | I84: SIF_nqC_12
A85: nqC_13 | B85: NAND 合約價季增 2028Q2（C） | C85: % | D85: -0.45 | E85: -0.35 | F85: -0.25 | G85: Assumed | H85: 同上 | I85: SIF_nqC_13
A86: nqC_14 | B86: NAND 合約價季增 2028Q3（C） | C86: % | D86: -0.35 | E86: -0.25 | F86: -0.15 | G86: Assumed | H86: 同上 | I86: SIF_nqC_14
A87: nqC_15 | B87: NAND 合約價季增 2028Q4（C） | C87: % | D87: -0.3 | E87: -0.2 | F87: -0.1 | G87: Assumed | H87: 同上 | I87: SIF_nqC_15
... A91: nqC_19 | B91: NAND 合約價季增 2029Q4（C） | C91: % | D91: 0 | E91: 0.1 | F91: 0.2 | G91: Assumed | H91: 同上 | I91: SIF_nqC_19
A92: M2. 加速器數量層（百萬顆）與每顆 HBM（GB）
A93: u_bw_26 | B93: NVIDIA Blackwell（B200／B300） 顆數 2026 | C93: 百萬顆 | E93: 5.4 | G93: Interested-party | H93: 顆數：Morgan Stanley 2026-07（2026 5.4M）；AC Research 2027 約 2.4M；2028 Assumed。GB：B200 186、B300 288 組合 [Derived] | I93: SIF_u_bw_26
A94: u_bw_27 | B94: NVIDIA Blackwell（B200／B300） 顆數 2027 | C94: 百萬顆 | E94: 2.4 | G94: Interested-party | H94: 同上 | I94: SIF_u_bw_27
A95: u_bw_28 | B95: NVIDIA Blackwell（B200／B300） 顆數 2028 | C95: 百萬顆 | E95: 0.5 | G95: Interested-party | H95: 同上 | I95: SIF_u_bw_28
A96: g_bw_26 | B96: NVIDIA Blackwell（B200／B300） 每顆 HBM 2026 | C96: GB | E96: 260 | G96: Interested-party | H96: 同上 | I96: SIF_g_bw_26
A97: g_bw_27 | B97: NVIDIA Blackwell（B200／B300） 每顆 HBM 2027 | C97: GB | E97: 280 | G97: Interested-party | H97: 同上 | I97: SIF_g_bw_27
A98: g_bw_28 | B98: NVIDIA Blackwell（B200／B300） 每顆 HBM 2028 | C98: GB | E98: 288 | G98: Interested-party | H98: 同上 | I98: SIF_g_bw_28
A99: u_rb_26 | B99: NVIDIA Rubin 顆數 2026 | C99: 百萬顆 | E99: 1.7 | G99: Interested-party | H99: 2026：TrendForce 組合 Rubin 22% × 約 7.6M [Derived]；2027：Morgan Stanley 約 7.0M；2028 Assumed | I99: SIF_u_rb_26
A100: u_rb_27 | B100: NVIDIA Rubin 顆數 2027 | C100: 百萬顆 | E100: 7 | G100: Interested-party | H100: 同上 | I100: SIF_u_rb_27
A101: u_rb_28 | B101: NVIDIA Rubin 顆數 2028 | C101: 百萬顆 | E101: 7 | G101: Interested-party | H101: 同上 | I101: SIF_u_rb_28
A102: g_rb_26 | B102: NVIDIA Rubin 每顆 HBM 2026 | C102: GB | E102: 288 | G102: Interested-party | H102: 同上 | I102: SIF_g_rb_26
A103: g_rb_27 | B103: NVIDIA Rubin 每顆 HBM 2027 | C103: GB | E103: 288 | G103: Interested-party | H103: 同上 | I103: SIF_g_rb_27
A104: g_rb_28 | B104: NVIDIA Rubin 每顆 HBM 2028 | C104: GB | E104: 288 | G104: Interested-party | H104: 同上 | I104: SIF_g_rb_28
A105: u_ru_26 | B105: NVIDIA Rubin Ultra 顆數 2026 | C105: 百萬顆 | D105: 0 | E105: 0 | F105: 0 | G105: Assumed | H105: 時程 Assumed；GB：NVIDIA 1 TB／封裝。區間（v0.2）：顆數 2027 0–0.6、2028 1.0–3.0（Assumed：時程提前／延後一年） | I105: SIF_u_ru_26
A106: u_ru_27 | B106: NVIDIA Rubin Ultra 顆數 2027 | C106: 百萬顆 | D106: 0 | E106: 0.3 | F106: 0.6 | G106: Assumed | H106: 同上 | I106: SIF_u_ru_27
A107: u_ru_28 | B107: NVIDIA Rubin Ultra 顆數 2028 | C107: 百萬顆 | D107: 1 | E107: 2 | F107: 3 | G107: Assumed | H107: 同上 | I107: SIF_u_ru_28
A108: g_ru_26 | B108: NVIDIA Rubin Ultra 每顆 HBM 2026 | C108: GB | E108: 1024 | G108: Interested-party | H108: NVIDIA：Rubin Ultra 每封裝 1 TB HBM（產品路線圖，v0.2 標記由 Assumed 改為 Interested-party：規格為公司公布，不是假設） | I108: SIF_g_ru_26
A109: g_ru_27 | B109: NVIDIA Rubin Ultra 每顆 HBM 2027 | C109: GB | E109: 1024 | G109: Interested-party | H109: 同上 | I109: SIF_g_ru_27
...

Sheet Units
A1: Units — 加速器平台別顆數（百萬顆；情境 A 基準）。2026–2028＝In 頁 M2；2029＝2028 ×（1＋In 頁 M5 平台別成長率）。情境 B、C 再乘 Scen 頁係數（2028–29）
A3: 平台 | B3: 鍵 | C3: 2026 | D3: 2027 | E3: 2028 | F3: 2029 | G3: 2029 成長
A4: NVIDIA Blackwell（B200／B300） | B4: bw | C4: =u_bw_26 -> 5.4 | D4: =u_bw_27 -> 2.4 | E4: =u_bw_28 -> 0.5 | F4: =E4*(1+g29_bw) -> 0.25 | G4: =g29_bw -> -0.5
A5: NVIDIA Rubin | B5: rb | C5: =u_rb_26 -> 1.7 | D5: =u_rb_27 -> 7 | E5: =u_rb_28 -> 7 | F5: =E5*(1+g29_rb) -> 8.05 | G5: =g29_rb -> 0.15
A6: NVIDIA Rubin Ultra | B6: ru | C6: =u_ru_26 -> 0 | D6: =u_ru_27 -> 0.3 | E6: =u_ru_28 -> 2 | F6: =E6*(1+g29_ru) -> 2.3 | G6: =g29_ru -> 0.15
A7: NVIDIA Hopper（H200 等） | B7: hp | C7: =u_hp_26 -> 0.5 | D7: =u_hp_27 -> 0 | E7: =u_hp_28 -> 0 | F7: =E7*(1+g29_hp) -> 0 | G7: =g29_hp -> 0
A8: AMD Instinct | B8: amd | C8: =u_amd_26 -> 0.75 | D8: =u_amd_27 -> 1.5 | E8: =u_amd_28 -> 2 | F8: =E8*(1+g29_amd) -> 2.3 | G8: =g29_amd -> 0.15
A9: Google TPU | B9: tpu | C9: =u_tpu_26 -> 3.85 | D9: =u_tpu_27 -> 5.5 | E9: =u_tpu_28 -> 7 | F9: =E9*(1+g29_tpu) -> 8.05 | G9: =g29_tpu -> 0.15
A10: AWS Trainium | B10: trn | C10: =u_trn_26 -> 2 | D10: =u_trn_27 -> 2.5 | E10: =u_trn_28 -> 3 | F10: =E10*(1+g29_trn) -> 3.45 | G10: =g29_trn -> 0.15
A11: 其他 ASIC（MTIA、Maia、Ascend 等） | B11: oth | C11: =u_oth_26 -> 1 | D11: =u_oth_27 -> 4.5 | E11: =u_oth_28 -> 5 | F11: =E11*(1+g29_oth) -> 5.75 | G11: =g29_oth -> 0.15
A12: 合計（基準＝情境 A，未乘係數） | C12: =SUM(C4:C11) -> 15.2 | D12: =SUM(D4:D11) -> 23.7 | E12: =SUM(E4:E11) -> 26.5 | F12: =SUM(F4:F11) -> 30.15 | G12: =F12/E12-1 -> 0.13773585
A13: 合計（情境 A） | C13: =C12 -> 15.2 | D13: =D12 -> 23.7 | E13: =E12*um28_A -> 26.5 | F13: =F12*um29_A -> 30.15
A14: 合計（情境 B） | C14: =C12 -> 15.2 | D14: =D12 -> 23.7 | E14: =E12*um28_B -> 21.2 | F14: =F12*um29_B -> 25.6275
A15: 合計（情境 C） | C15: =C12 -> 15.2 | D15: =D12 -> 23.7 | E15: =E12*um28_C -> 15.9 | F15: =F12*um29_C -> 18.09

Sheet ShareTbl
A1: ShareTbl — ASIC 設計服務顆數份額表（基準值；In 頁 M7）。同一平台各設計夥伴份額加總須 ≤ 100%，餘額＝客戶自行設計或未建模的夥伴。Trainium 的世芯份額隨情境（公司特有：A 最有利、C 最不利），三情境各列一次
A3: 平台 | B3: 夥伴 | C3: 鍵（2026／2027／2028） | D3: 2026 | E3: 2027 | F3: 2028 | G3: 說明
A4: Google TPU | B4: Broadcom | C4: sh_tpu_26／sh_tpu_27／sh_tpu_28 | D4: =sh_tpu_26 -> 0.9 | E4: =sh_tpu_27 -> 0.8 | F4: =sh_tpu_28 -> 0.75
A5: Google TPU | B5: Marvell | C5: msh_tpu_26／msh_tpu_27／msh_tpu_28 | D5: =msh_tpu_26 -> 0 | E5: =msh_tpu_27 -> 0 | F5: =msh_tpu_28 -> 0.05
A6: Google TPU | B6: 聯發科 | C6: mtk_tpu_26／mtk_tpu_27／mtk_tpu_28 | D6: =mtk_tpu_26 -> 0.05 | E6: =mtk_tpu_27 -> 0.15 | F6: =mtk_tpu_28 -> 0.18
A7: Google TPU | B7: 合計 | D7: =SUM(D4:D6) -> 0.95 | E7: =SUM(E4:E6) -> 0.95 | F7: =SUM(F4:F6) -> 0.98
A8: Google TPU | B8: 餘額（客戶自行設計或未建模） | D8: =1-D7 -> 0.05 | E8: =1-E7 -> 0.05 | F8: =1-F7 -> 0.02
A10: 其他 ASIC（MTIA、Maia、OpenAI 等） | B10: Broadcom | C10: sh_oth_26／sh_oth_27／sh_oth_28 | D10: =sh_oth_26 -> 0.35 | E10: =sh_oth_27 -> 0.55 | F10: =sh_oth_28 -> 0.55
A11: 其他 ASIC（MTIA、Maia、OpenAI 等） | B11: Marvell | C11: msh_oth_26／msh_oth_27／msh_oth_28 | D11: =msh_oth_26 -> 0.05 | E11: =msh_oth_27 -> 0.06 | F11: =msh_oth_28 -> 0.15
A12: 其他 ASIC（MTIA、Maia、OpenAI 等） | B12: 聯發科 | C12: mtk_oth_26／mtk_oth_27／mtk_oth_28 | D12: =mtk_oth_26 -> 0 | E12: =mtk_oth_27 -> 0 | F12: =mtk_oth_28 -> 0
A13: 其他 ASIC（MTIA、Maia、OpenAI 等） | B13: 合計 | D13: =SUM(D10:D12) -> 0.4 | E13: =SUM(E10:E12) -> 0.61 | F13: =SUM(F10:F12) -> 0.7
A14: 其他 ASIC（MTIA、Maia、OpenAI 等） | B14: 餘額（客戶自行設計或未建模） | D14: =1-D13 -> 0.6 | E14: =1-E13 -> 0.39 | F14: =1-F13 -> 0.3
A16: AWS Trainium（情境 A） | B16: Marvell | C16: msh_trn_26／msh_trn_27／msh_trn_28 | D16: =msh_trn_26 -> 0.1 | E16: =msh_trn_27 -> 0.1 | F16: =msh_trn_28 -> 0.08
A17: AWS Trainium（情境 A） | B17: 世芯 | C17: al_trn_26／al27_A／al28_A | D17: =al_trn_26 -> 0.3 | E17: =al27_A -> 0.55 | F17: =al28_A -> 0.55
A18: AWS Trainium（情境 A） | B18: 合計 | D18: =SUM(D16:D17) -> 0.4 | E18: =SUM(E16:E17) -> 0.65 | F18: =SUM(F16:F17) -> 0.63
A19: AWS Trainium（情境 A） | B19: 餘額（客戶自行設計或未建模） | D19: =1-D18 -> 0.6 | E19: =1-E18 -> 0.35 | F19: =1-F18 -> 0.37
A21: AWS Trainium（情境 B） | B21: Marvell | C21: msh_trn_26／msh_trn_27／msh_trn_28 | D21: =msh_trn_26 -> 0.1 | E21: =msh_trn_27 -> 0.1 | F21: =msh_trn_28 -> 0.08
A22: AWS Trainium（情境 B） | B22: 世芯 | C22: al_trn_26／al27_B／al28_B | D22: =al_trn_26 -> 0.3 | E22: =al27_B -> 0.5 | F22: =al28_B -> 0.45
A23: AWS Trainium（情境 B） | B23: 合計 | D23: =SUM(D21:D22) -> 0.4 | E23: =SUM(E21:E22) -> 0.6 | F23: =SUM(F21:F22) -> 0.53
A24: AWS Trainium（情境 B） | B24: 餘額（客戶自行設計或未建模） | D24: =1-D23 -> 0.6 | E24: =1-E23 -> 0.4 | F24: =1-F23 -> 0.47
A26: AWS Trainium（情境 C） | B26: Marvell | C26: msh_trn_26／msh_trn_27／msh_trn_28 | D26: =msh_trn_26 -> 0.1 | E26: =msh_trn_27 -> 0.1 | F26: =msh_trn_28 -> 0.08
A27: AWS Trainium（情境 C） | B27: 世芯 | C27: al_trn_26／al27_C／al28_C | D27: =al_trn_26 -> 0.3 | E27: =al27_C -> 0.4 | F27: =al28_C -> 0.35
A28: AWS Trainium（情境 C） | B28: 合計 | D28: =SUM(D26:D27) -> 0.4 | E28: =SUM(E26:E27) -> 0.5 | F28: =SUM(F26:F27) -> 0.43
A29: AWS Trainium（情境 C） | B29: 餘額（客戶自行設計或未建模） | D29: =1-D28 -> 0.6 | E29: =1-E28 -> 0.5 | F29: =1-F28 -> 0.57
A31: CPO 光學金額份額（欄 D–F＝2027／2028／2029；Fabrinet 為代工，與模組廠重疊，不計入合計）
A32: CPO 光學 | B32: Lumentum | C32: cposh_lite_27／28／29 | D32: =cposh_lite_27 -> 0.25 | E32: =cposh_lite_28 -> 0.25 | F32: =cposh_lite_29 -> 0.2
A33: CPO 光學 | B33: Coherent | C33: cposh_cohr_27／28／29 | D33: =cposh_cohr_27 -> 0.1 | E33: =cposh_cohr_28 -> 0.15 | F33: =cposh_cohr_29 -> 0.2
A34: CPO 光學 | B34: 中際旭創 | C34: cposh_innolight_27／28／29 | D34: =cposh_innolight_27 -> 0.1 | E34: =cposh_innolight_28 -> 0.15 | F34: =cposh_innolight_29 -> 0.2
A35: CPO 光學 | B35: 新易盛 | C35: cposh_eoptolink_27／28／29 | D35: =cposh_eoptolink_27 -> 0.05 | E35: =cposh_eoptolink_28 -> 0.1 | F35: =cposh_eoptolink_29 -> 0.15
A36: CPO 光學 | B36: 合計（模組與雷射廠） | D36: =SUM(D32:D35) -> 0.5 | E36: =SUM(E32:E35) -> 0.65 | F36: =SUM(F32:F35) -> 0.75
A37: CPO 光學 | B37: 餘額（NVIDIA、Broadcom 交換器端自製光引擎與其他，未建模） | D37: =1-D36 -> 0.5 | E37: =1-E36 -> 0.35 | F37: =1-F36 -> 0.25
A38: CPO 光學 | B38: Fabrinet（代工；參考，不計入） | C38: cposh_fabrinet_27／28／29 | D38: =cposh_fabrinet_27 -> 0.05 | E38: =cposh_fabrinet_28 -> 0.1 | F38: =cposh_fabrinet_29 -> 0.15
A40: 加速器 ABF 載板份額（欄 D–G＝2026／2027／2028／2029；NVIDIA 為顆數份額，非 NVIDIA 為金額份額）
A41: NVIDIA 加速器 | B41: Ibiden | C41: abf_ibsh26 × abf_ibrel | D41: =abf_ibsh26*1 -> 0.7 | E41: =abf_ibsh26*abf_ibrel_27 -> 0.665 | F41: =abf_ibsh26*abf_ibrel_28 -> 0.616 | G41: =abf_ibsh26*abf_ibrel_29 -> 0.595
A42: NVIDIA 加速器 | B42: 欣興 | C42: abf_un_nv_26／27／28／29 | D42: =abf_un_nv_26 -> 0.25 | E42: =abf_un_nv_27 -> 0.27 | F42: =abf_un_nv_28 -> 0.29 | G42: =abf_un_nv_29 -> 0.3
A43: NVIDIA 加速器 | B43: 南電 | C43: abf_np_nv_26／27／28／29 | D43: =abf_np_nv_26 -> 0.02 | E43: =abf_np_nv_27 -> 0.03 | F43: =abf_np_nv_28 -> 0.04 | G43: =abf_np_nv_29 -> 0.04
A44: NVIDIA 加速器 | B44: 景碩 | C44: abf_ks_nv_26／27／28／29 | D44: =abf_ks_nv_26 -> 0.02 | E44: =abf_ks_nv_27 -> 0.03 | F44: =abf_ks_nv_28 -> 0.05 | G44: =abf_ks_nv_29 -> 0.06
A45: NVIDIA 加速器 | B45: 合計 | D45: =SUM(D41:D44) -> 0.99 | E45: =SUM(E41:E44) -> 0.995 | F45: =SUM(F41:F44) -> 0.996 | G45: =SUM(G41:G44) -> 0.995
A46: NVIDIA 加速器 | B46: 餘額（三星電機、AT&S、Shinko 等，未建模） | D46: =1-D45 -> 0.01 | E46: =1-E45 -> 0.005 | F46: =1-F45 -> 0.004 | G46: =1-G45 -> 0.005
A48: 非 NVIDIA 加速器 | B48: Ibiden | C48: abf_wot_ib × abf_ibrel ÷ abf_vot | D48: =abf_wot_ib*1/abf_vot -> 0.5 | E48: =abf_wot_ib*abf_ibrel_27/abf_vot -> 0.475 | F48: =abf_wot_ib*abf_ibrel_28/abf_vot -> 0.44 | G48: =abf_wot_ib*abf_ibrel_29/abf_vot -> 0.425
A49: 非 NVIDIA 加速器 | B49: 欣興 | C49: abf_un_ot_26／27／28／29 | D49: =abf_un_ot_26 -> 0.3 | E49: =abf_un_ot_27 -> 0.31 | F49: =abf_un_ot_28 -> 0.32 | G49: =abf_un_ot_29 -> 0.33
A50: 非 NVIDIA 加速器 | B50: 南電 | C50: abf_np_ot_26／27／28／29 | D50: =abf_np_ot_26 -> 0.05 | E50: =abf_np_ot_27 -> 0.06 | F50: =abf_np_ot_28 -> 0.07 | G50: =abf_np_ot_29 -> 0.07
A51: 非 NVIDIA 加速器 | B51: 景碩 | C51: abf_ks_ot_26／27／28／29 | D51: =abf_ks_ot_26 -> 0.03 | E51: =abf_ks_ot_27 -> 0.05 | F51: =abf_ks_ot_28 -> 0.06 | G51: =abf_ks_ot_29 -> 0.06
A52: 非 NVIDIA 加速器 | B52: 合計 | D52: =SUM(D48:D51) -> 0.88 | E52: =SUM(E48:E51) -> 0.895 | F52: =SUM(F48:F51) -> 0.89 | G52: =SUM(G48:G51) -> 0.885
A53: 非 NVIDIA 加速器 | B53: 餘額（三星電機、AT&S、Shinko 等，未建模） | D53: =1-D52 -> 0.12 | E53: =1-E52 -> 0.105 | F53: =1-F52 -> 0.11 | G53: =1-G52 -> 0.115
A55: AI 電源有效份額（欄 D–G＝2026／2027／2028／2029；分母＝Rack 頁 AI 電源市場；2026＝公司模型校準值，之後 × 份額相對值；光寶相對值隨情境：A 高、B 基準、C 低）
A56: AI 電源（情境 A） | B56: 台達電 | C56: pwr_dsh_26 × pwr_drel_27／28／29（不隨情境） | D56: =pwr_dsh_26 -> 0.58367194 | E56: =pwr_dsh_26*pwr_drel_27 -> 0.55448834 | F56: =pwr_dsh_26*pwr_drel_28 -> 0.52530475 | G56: =pwr_dsh_26*pwr_drel_29 -> 0.49612115
A57: AI 電源（情境 A） | B57: 光寶 | C57: pwr_lsh_26 × pwr_lrel_27／28／29_hi | D57: =pwr_lsh_26 -> 0.17614332 | E57: =pwr_lsh_26*pwr_lrel_27_hi -> 0.19375765 | F57: =pwr_lsh_26*pwr_lrel_28_hi -> 0.21137198 | G57: =pwr_lsh_26*pwr_lrel_29_hi -> 0.22017915
A58: AI 電源（情境 A） | B58: 合計 | D58: =SUM(D56:D57) -> 0.75981526 | E58: =SUM(E56:E57) -> 0.74824599 | F58: =SUM(F56:F57) -> 0.73667673 | G58: =SUM(G56:G57) -> 0.71630029
A59: AI 電源（情境 A） | B59: 餘額（Flex、群電、康舒、Vertiv、麥格米特等，未建模） | D59: =1-D58 -> 0.24018474 | E59: =1-E58 -> 0.25175401 | F59: =1-F58 -> 0.26332327 | G59: =1-G58 -> 0.28369971
A61: AI 電源（情境 B） | B61: 台達電 | C61: pwr_dsh_26 × pwr_drel_27／28／29（不隨情境） | D61: =pwr_dsh_26 -> 0.58367194 | E61: =pwr_dsh_26*pwr_drel_27 -> 0.55448834 | F61: =pwr_dsh_26*pwr_drel_28 -> 0.52530475 | G61: =pwr_dsh_26*pwr_drel_29 -> 0.49612115
A62: AI 電源（情境 B） | B62: 光寶 | C62: pwr_lsh_26 × pwr_lrel_27／28／29 | D62: =pwr_lsh_26 -> 0.17614332 | E62: =pwr_lsh_26*pwr_lrel_27 -> 0.17614332 | F62: =pwr_lsh_26*pwr_lrel_28 -> 0.17614332 | G62: =pwr_lsh_26*pwr_lrel_29 -> 0.17614332
A63: AI 電源（情境 B） | B63: 合計 | D63: =SUM(D61:D62) -> 0.75981526 | E63: =SUM(E61:E62) -> 0.73063166 | F63: =SUM(F61:F62) -> 0.70144806 | G63: =SUM(G61:G62) -> 0.67226446
A64: AI 電源（情境 B） | B64: 餘額（Flex、群電、康舒、Vertiv、麥格米特等，未建模） | D64: =1-D63 -> 0.24018474 | E64: =1-E63 -> 0.26936834 | F64: =1-F63 -> 0.29855194 | G64: =1-G63 -> 0.32773554
A66: AI 電源（情境 C） | B66: 台達電 | C66: pwr_dsh_26 × pwr_drel_27／28／29（不隨情境） | D66: =pwr_dsh_26 -> 0.58367194 | E66: =pwr_dsh_26*pwr_drel_27 -> 0.55448834 | F66: =pwr_dsh_26*pwr_drel_28 -> 0.52530475 | G66: =pwr_dsh_26*pwr_drel_29 -> 0.49612115
A67: AI 電源（情境 C） | B67: 光寶 | C67: pwr_lsh_26 × pwr_lrel_27／28／29_lo | D67: =pwr_lsh_26 -> 0.17614332 | E67: =pwr_lsh_26*pwr_lrel_27_lo -> 0.14972182 | F67: =pwr_lsh_26*pwr_lrel_28_lo -> 0.14091465 | G67: =pwr_lsh_26*pwr_lrel_29_lo -> 0.13210749
A68: AI 電源（情境 C） | B68: 合計 | D68: =SUM(D66:D67) -> 0.75981526 | E68: =SUM(E66:E67) -> 0.70421016 | F68: =SUM(F66:F67) -> 0.6662194 | G68: =SUM(G66:G67) -> 0.62822864
A69: AI 電源（情境 C） | B69: 餘額（Flex、群電、康舒、Vertiv、麥格米特等，未建模） | D69: =1-D68 -> 0.24018474 | E69: =1-E68 -> 0.29578984 | F69: =1-F68 -> 0.3337806 | G69: =1-G68 -> 0.37177136
A71: AI 液冷有效份額（欄 D–G＝2026／2027／2028／2029；分母＝Rack 頁 AI 液冷市場〔機架內＋分歧管〕；奇鋐相對值不隨情境，雙鴻與健策 A 高、B 基準、C 低）
A72: AI 液冷（情境 A） | B72: 奇鋐 | C72: lc_avsh_26 × lc_avrel_27／28／29（不隨情境） | D72: =lc_avsh_26 -> 0.49892764 | E72: =lc_avsh_26*lc_avrel_27 -> 0.47398126 | F72: =lc_avsh_26*lc_avrel_28 -> 0.44903488 | G72: =lc_avsh_26*lc_avrel_29 -> 0.42408849
A73: AI 液冷（情境 A） | B73: 雙鴻 | C73: lc_aush_26 × lc_avrel_27／28／29_hi | D73: =lc_aush_26 -> 0.15870078 | E73: =lc_aush_26*lc_avrel_27_hi -> 0.16663582 | F73: =lc_aush_26*lc_avrel_28_hi -> 0.16663582 | G73: =lc_aush_26*lc_avrel_29_hi -> 0.16663582
A74: AI 液冷（情境 A） | B74: 健策（MCL／MLCP 冷板元件） | C74: lc_jtsh_27／28／29_hi（2026 含在其他散熱） | D74: =0 -> 0 | E74: =lc_jtsh_27_hi -> 0.015 | F74: =lc_jtsh_28_hi -> 0.03 | G74: =lc_jtsh_29_hi -> 0.045
A75: AI 液冷（情境 A） | B75: 合計 | D75: =SUM(D72:D74) -> 0.65762842 | E75: =SUM(E72:E74) -> 0.65561707 | F75: =SUM(F72:F74) -> 0.64567069 | G75: =SUM(G72:G74) -> 0.63572431
A76: AI 液冷（情境 A） | B76: 餘額（酷碼、富世達、Boyd、CoolIT、Vertiv 等，未建模） | D76: =1-D75 -> 0.34237158 | E76: =1-E75 -> 0.34438293 | F76: =1-F75 -> 0.35432931 | G76: =1-G75 -> 0.36427569
A78: AI 液冷（情境 B） | B78: 奇鋐 | C78: lc_avsh_26 × lc_avrel_27／28／29（不隨情境） | D78: =lc_avsh_26 -> 0.49892764 | E78: =lc_avsh_26*lc_avrel_27 -> 0.47398126 | F78: =lc_avsh_26*lc_avrel_28 -> 0.44903488 | G78: =lc_avsh_26*lc_avrel_29 -> 0.42408849
A79: AI 液冷（情境 B） | B79: 雙鴻 | C79: lc_aush_26 × lc_avrel_27／28／29 | D79: =lc_aush_26 -> 0.15870078 | E79: =lc_aush_26*lc_avrel_27 -> 0.15076574 | F79: =lc_aush_26*lc_avrel_28 -> 0.1428307 | G79: =lc_aush_26*lc_avrel_29 -> 0.13489566
A80: AI 液冷（情境 B） | B80: 健策（MCL／MLCP 冷板元件） | C80: lc_jtsh_27／28／29（2026 含在其他散熱） | D80: =0 -> 0 | E80: =lc_jtsh_27 -> 0.008 | F80: =lc_jtsh_28 -> 0.015 | G80: =lc_jtsh_29 -> 0.025
A81: AI 液冷（情境 B） | B81: 合計 | D81: =SUM(D78:D80) -> 0.65762842 | E81: =SUM(E78:E80) -> 0.632747 | F81: =SUM(F78:F80) -> 0.60686558 | G81: =SUM(G78:G80) -> 0.58398415
A82: AI 液冷（情境 B） | B82: 餘額（酷碼、富世達、Boyd、CoolIT、Vertiv 等，未建模） | D82: =1-D81 -> 0.34237158 | E82: =1-E81 -> 0.367253 | F82: =1-F81 -> 0.39313442 | G82: =1-G81 -> 0.41601585
A84: AI 液冷（情境 C） | B84: 奇鋐 | C84: lc_avsh_26 × lc_avrel_27／28／29（不隨情境） | D84: =lc_avsh_26 -> 0.49892764 | E84: =lc_avsh_26*lc_avrel_27 -> 0.47398126 | F84: =lc_avsh_26*lc_avrel_28 -> 0.44903488 | G84: =lc_avsh_26*lc_avrel_29 -> 0.42408849
A85: AI 液冷（情境 C） | B85: 雙鴻 | C85: lc_aush_26 × lc_avrel_27／28／29_lo | D85: =lc_aush_26 -> 0.15870078 | E85: =lc_aush_26*lc_avrel_27_lo -> 0.13489566 | F85: =lc_aush_26*lc_avrel_28_lo -> 0.11902558 | G85: =lc_aush_26*lc_avrel_29_lo -> 0.11109054
A86: AI 液冷（情境 C） | B86: 健策（MCL／MLCP 冷板元件） | C86: lc_jtsh_27／28／29_lo（2026 含在其他散熱） | D86: =0 -> 0 | E86: =lc_jtsh_27_lo -> 0.003 | F86: =lc_jtsh_28_lo -> 0.006 | G86: =lc_jtsh_29_lo -> 0.01
A87: AI 液冷（情境 C） | B87: 合計 | D87: =SUM(D84:D86) -> 0.65762842 | E87: =SUM(E84:E86) -> 0.61187692 | F87: =SUM(F84:F86) -> 0.57406046 | G87: =SUM(G84:G86) -> 0.54517904
A88: AI 液冷（情境 C） | B88: 餘額（酷碼、富世達、Boyd、CoolIT、Vertiv 等，未建模） | D88: =1-D87 -> 0.34237158 | E88: =1-E87 -> 0.38812308 | F88: =1-F87 -> 0.42593954 | G88: =1-G87 -> 0.45482096
A90: 註：台達電液冷營收多在機架外（CDU、Liquid-to-Air），不屬本市場，不入表（CF12）；奇鋐、雙鴻分子含部分 CDU，份額可能高估
A92: 對照：凱基台達電份額（只作對照，不入表；CF11 待 Andy） | B92: 2025-07 Blackwell PSU／2025-09 AI 伺服器電源 | D92: =pwr_kgi_0701 -> 0.7 | E92: =pwr_kgi_0926 -> 0.625
A94: HBM 營收份額（欄 D–H＝2025／2026／2027／2028／2029；In 頁 M24；份額不隨情境；餘額＝長鑫等其他）
A95: HBM | B95: SK 海力士 | C95: hbmsh_skh_25…29 | D95: =hbmsh_skh_25 -> 0.58 | E95: =hbmsh_skh_26 -> 0.52 | F95: =hbmsh_skh_27 -> 0.42 | G95: =hbmsh_skh_28 -> 0.4 | H95: =hbmsh_skh_29 -> 0.4
A96: HBM | B96: 三星 | C96: hbmsh_ss_25…29 | D96: =hbmsh_ss_25 -> 0.17 | E96: =hbmsh_ss_26 -> 0.29 | F96: =hbmsh_ss_27 -> 0.38 | G96: =hbmsh_ss_28 -> 0.4 | H96: =hbmsh_ss_29 -> 0.4
A97: HBM | B97: 美光 | C97: hbmsh_mu_25…29 | D97: =hbmsh_mu_25 -> 0.21 | E97: =hbmsh_mu_26 -> 0.19 | F97: =hbmsh_mu_27 -> 0.2 | G97: =hbmsh_mu_28 -> 0.2 | H97: =hbmsh_mu_29 -> 0.2
A98: HBM | B98: 合計 | D98: =SUM(D95:D97) -> 0.96 | E98: =SUM(E95:E97) -> 1 | F98: =SUM(F95:F97) -> 1 | G98: =SUM(G95:G97) -> 1 | H98: =SUM(H95:H97) -> 1
A99: HBM | B99: 餘額（長鑫等，未建模） | D99: =1-D98 -> 0.04 | E99: =1-E98 -> 0 | F99: =1-F98 -> 0 | G99: =1-G98 -> 0 | H99: =1-H98 -> 0
A101: AI 伺服器組裝有效份額（欄 D–G＝2026／2027／2028／2029；分母＝Rack 頁 AI 伺服器組裝市場〔ODM 價〕；2026＝公司模型校準快照，之後 × 份額相對值；不隨情境）
A102: AI 伺服器組裝 | B102: 緯穎 ASIC 傾斜係數（x） | C102: asm_wyam ×（Trainium＋其他 ASIC 顆數指數 ÷ 全部顆數指數）＋（1 − asm_wyam） | D102: =1 -> 1 | E102: =asm_wyam*((u_trn_27+u_oth_27)/(u_trn_26+u_oth_26))/((u_bw_27+u_rb_27+u_ru_27+u_hp_27+u_amd_27+u_tpu_27+u_trn_27+u_oth_27)/(u_bw_26+u_rb_26+u_ru_26+u_hp_26+u_amd_26+u_tpu_26+u_trn_26+u_oth_26))+(1-asm_wyam) -> 1.4468354 | F102: =asm_wyam*((u_trn_28+u_oth_28)/(u_trn_26+u_oth_26))/((u_bw_28+u_rb_28+u_ru_28+u_hp_28+u_amd_28+u_tpu_28+u_trn_28+u_oth_28)/(u_bw_26+u_rb_26+u_ru_26+u_hp_26+u_amd_26+u_tpu_26+u_trn_26+u_oth_26))+(1-asm_wyam) -> 1.4766038 | G102: =asm_wyam*((u_trn_28*(1+g29_trn)+u_oth_28*(1+g29_oth))/(u_trn_26+u_oth_26))/((u_bw_28*(1+g29_bw)+u_rb_28*(1+g29_rb)+u_ru_28*(1+g29_ru)+u_hp_28*(1+g29_hp)+u_amd_28*(1+g29_amd)+u_tpu_28*(1+g29_tpu)+u_trn_28*(1+g29_trn)+u_oth_28*(1+g29_oth))/(u_bw_26+u_rb_26+u_ru_26+u_hp_26+u_amd_26+u_tpu_26+u_trn_26+u_oth_26))+(1-asm_wyam) -> 1.4914428
A103: AI 伺服器組裝 | B103: 廣達 | C103: asm_qush_26 × asm_qurel_27／28／29 | D103: =asm_qush_26 -> 0.13389612 | E103: =asm_qush_26*asm_qurel_27 -> 0.13389612 | F103: =asm_qush_26*asm_qurel_28 -> 0.12720132 | G103: =asm_qush_26*asm_qurel_29 -> 0.12050651
A104: AI 伺服器組裝 | B104: 鴻海 | C104: asm_fxsh_26 × asm_fxrel_27／28／29 | D104: =asm_fxsh_26 -> 0.17461006 | E104: =asm_fxsh_26*asm_fxrel_27 -> 0.17461006 | F104: =asm_fxsh_26*asm_fxrel_28 -> 0.17461006 | G104: =asm_fxsh_26*asm_fxrel_29 -> 0.16587955
A105: AI 伺服器組裝 | B105: 緯創本體 | C105: asm_wish_26 × asm_wirel_27／28／29 | D105: =asm_wish_26 -> 0.08750965 | E105: =asm_wish_26*asm_wirel_27 -> 0.08750965 | F105: =asm_wish_26*asm_wirel_28 -> 0.083134168 | G105: =asm_wish_26*asm_wirel_29 -> 0.078758685
A106: AI 伺服器組裝 | B106: 緯穎（× ASIC 傾斜） | C106: asm_wysh_26 × asm_wyrel_27／28／29 × 傾斜係數 | D106: =asm_wysh_26 -> 0.034477508 | E106: =asm_wysh_26*asm_wyrel_27*E102 -> 0.049883281 | F106: =asm_wysh_26*asm_wyrel_28*F102 -> 0.050909619 | G106: =asm_wysh_26*asm_wyrel_29*G102 -> 0.048850169
A107: AI 伺服器組裝 | B107: 合計 | D107: =SUM(D103:D106) -> 0.43049334 | E107: =SUM(E103:E106) -> 0.44589911 | F107: =SUM(F103:F106) -> 0.43585516 | G107: =SUM(G103:G106) -> 0.41399492
A108: AI 伺服器組裝 | B108: 餘額（英業達、Celestica、Dell、美超微、HPE 等，未建模） | D108: =1-D107 -> 0.56950666 | E108: =1-E107 -> 0.55410089 | F108: =1-F107 -> 0.56414484 | G108: =1-G107 -> 0.58600508
A109: 註：Dell、美超微以整櫃售價計（Rack 頁 B 節商用 GPU 系統市場），分母不同，不入本表；緯創模型自算的緯穎份額路徑與本表不同（CF23）

Sheet Deploy
A1: Deploy — AI IT 資本支出＝Σ 平台顆數（Units 頁）× 每顆 IT capex（In 頁 M9）× 情境顆數係數；部署 GW＝AI IT 資本支出 ÷ 每 GW IT 資本支出（Tokenomics IF_CapexIT；2026 依 vr26 混合 GB300 與 VR200，2027 起 VR200）。公式與 markets/network、各公司模型相同；R4 產業部署路徑上線後改讀算力收支
A3: 項目 | B3: 情境 | C3: 2026 | D3: 2027 | E3: 2028 | F3: 2029
A4: AI IT 資本支出（基準，未乘係數） | C4: =Units!C4*it_GB+Units!C5*it_VR+Units!C6*it_RU+Units!C7*it_HP+Units!C8*it_AMD8+Units!C9*it_TPU+Units!C10*it_TRN+Units!C11*it_ASIC -> 781.87292 | D4: =Units!D4*it_GB+Units!D5*it_VR+Units!D6*it_RU+Units!D7*it_HP+Units!D8*it_AMDR+Units!D9*it_TPU+Units!D10*it_TRN+Units!D11*it_ASIC -> 1565.35 | E4: =Units!E4*it_GB+Units!E5*it_VR+Units!E6*it_RU+Units!E7*it_HP+Units!E8*it_AMDR+Units!E9*it_TPU+Units!E10*it_TRN+Units!E11*it_ASIC -> 1984.2639 | F4: =Units!F4*it_GB+Units!F5*it_VR+Units!F6*it_RU+Units!F7*it_HP+Units!F8*it_AMDR+Units!F9*it_TPU+Units!F10*it_TRN+Units!F11*it_ASIC -> 2260.3903
A5: AI IT 資本支出 × 情境顆數係數 | B5: A | C5: =C4 -> 781.87292 | D5: =D4 -> 1565.35 | E5: =E4*um28_A -> 1984.2639 | F5: =F4*um29_A -> 2260.3903
A6: AI IT 資本支出 × 情境顆數係數 | B6: B | C6: =C4 -> 781.87292 | D6: =D4 -> 1565.35 | E6: =E4*um28_B -> 1587.4111 | F6: =F4*um29_B -> 1921.3317
A7: AI IT 資本支出 × 情境顆數係數 | B7: C | C7: =C4 -> 781.87292 | D7: =D4 -> 1565.35 | E7: =E4*um28_C -> 1190.5583 | F7: =F4*um29_C -> 1356.2342
A8: 每 GW IT 資本支出（$B／GW） | C8: =TK_CapexIT_GB300*(1-vr26)+TK_CapexIT_VR200*vr26 -> 33.414032 | D8: =TK_CapexIT_VR200 -> 37.586352 | E8: =TK_CapexIT_VR200 -> 37.586352 | F8: =TK_CapexIT_VR200 -> 37.586352
A9: 部署 GW（IT 電力） | B9: A | C9: =C5/C8 -> 23.399538 | D9: =D5/D8 -> 41.646766 | E9: =E5/E8 -> 52.792138 | F9: =F5/F8 -> 60.138592
A10: 部署 GW（IT 電力） | B10: B | C10: =C6/C8 -> 23.399538 | D10: =D6/D8 -> 41.646766 | E10: =E6/E8 -> 42.233711 | F10: =F6/F8 -> 51.117803
A11: 部署 GW（IT 電力） | B11: C | C11: =C7/C8 -> 23.399538 | D11: =D7/D8 -> 41.646766 | E11: =E7/E8 -> 31.675283 | F11: =F7/F8 -> 36.083155

Sheet ABF
A1: ABF — 載板供需表。需求（面積 × 層數口徑，2026＝1）＝加速器（顆數 ×（NVIDIA 1、非 NVIDIA v_ot）×（1＋g_asp）^t）、其他 AI（AI IT 資本支出成長 ^ 彈性）、非 AI（年增 g_nai），以 2026 金額權重加總；供給＝各載板廠產能指數 × 2026 營收權重，再與味之素 ABF 膜可出貨量上限取小；缺口＝（1＋2026 外部缺口）× 需求 ÷ 有效供給 − 1。價格溢價不計入（只量）
A3: 項目 | B3: 情境 | C3: 2026 | D3: 2027 | E3: 2028 | F3: 2029 | G3: 說明
A4: A. 需求
A5: 2026 ABF 載板產值（US$B） | C5: =abfm_25*(1+abfm_g26) -> 10.1904 | G5: TPCA 2025 × 2026 年增
A6: 2026 權重：加速器 | C6: =abf_ai26*abf_accsh26 -> 0.288
A7: 2026 權重：其他 AI（交換器、CPU、網通） | C7: =abf_ai26*(1-abf_accsh26) -> 0.162
A8: 2026 權重：非 AI | C8: =1-abf_ai26 -> 0.55
A9: 加速器有效顆數（NVIDIA ＋ 非 NVIDIA × v_ot；百萬顆） | B9: A | C9: =(Units!C4+Units!C5+Units!C6+Units!C7+abf_vot*(Units!C8+Units!C9+Units!C10+Units!C11)) -> 13.68 | D9: =(Units!D4+Units!D5+Units!D6+Units!D7+abf_vot*(Units!D8+Units!D9+Units!D10+Units!D11)) -> 20.9 | E9: =(Units!E4+Units!E5+Units!E6+Units!E7+abf_vot*(Units!E8+Units!E9+Units!E10+Units!E11))*um28_A -> 23.1 | F9: =(Units!F4+Units!F5+Units!F6+Units!F7+abf_vot*(Units!F8+Units!F9+Units!F10+Units!F11))*um29_A -> 26.24
A10: 加速器有效顆數（NVIDIA ＋ 非 NVIDIA × v_ot；百萬顆） | B10: B | C10: =(Units!C4+Units!C5+Units!C6+Units!C7+abf_vot*(Units!C8+Units!C9+Units!C10+Units!C11)) -> 13.68 | D10: =(Units!D4+Units!D5+Units!D6+Units!D7+abf_vot*(Units!D8+Units!D9+Units!D10+Units!D11)) -> 20.9 | E10: =(Units!E4+Units!E5+Units!E6+Units!E7+abf_vot*(Units!E8+Units!E9+Units!E10+Units!E11))*um28_B -> 18.48 | F10: =(Units!F4+Units!F5+Units!F6+Units!F7+abf_vot*(Units!F8+Units!F9+Units!F10+Units!F11))*um29_B -> 22.304
A11: 加速器有效顆數（NVIDIA ＋ 非 NVIDIA × v_ot；百萬顆） | B11: C | C11: =(Units!C4+Units!C5+Units!C6+Units!C7+abf_vot*(Units!C8+Units!C9+Units!C10+Units!C11)) -> 13.68 | D11: =(Units!D4+Units!D5+Units!D6+Units!D7+abf_vot*(Units!D8+Units!D9+Units!D10+Units!D11)) -> 20.9 | E11: =(Units!E4+Units!E5+Units!E6+Units!E7+abf_vot*(Units!E8+Units!E9+Units!E10+Units!E11))*um28_C -> 13.86 | F11: =(Units!F4+Units!F5+Units!F6+Units!F7+abf_vot*(Units!F8+Units!F9+Units!F10+Units!F11))*um29_C -> 15.744
A12: 需求指數：加速器（× 面積層數） | B12: A | C12: =C9/$C9*(1+abf_gasp)^0 -> 1 | D12: =D9/$C9*(1+abf_gasp)^1 -> 1.8027778 | E12: =E9/$C9*(1+abf_gasp)^2 -> 2.3512018 | F12: =F9/$C9*(1+abf_gasp)^3 -> 3.1515468
A13: 需求指數：加速器（× 面積層數） | B13: B | C13: =C10/$C10*(1+abf_gasp)^0 -> 1 | D13: =D10/$C10*(1+abf_gasp)^1 -> 1.8027778 | E13: =E10/$C10*(1+abf_gasp)^2 -> 1.8809614 | F13: =F10/$C10*(1+abf_gasp)^3 -> 2.6788147
A14: 需求指數：加速器（× 面積層數） | B14: C | C14: =C11/$C11*(1+abf_gasp)^0 -> 1 | D14: =D11/$C11*(1+abf_gasp)^1 -> 1.8027778 | E14: =E11/$C11*(1+abf_gasp)^2 -> 1.4107211 | F14: =F11/$C11*(1+abf_gasp)^3 -> 1.8909281
A15: 需求指數：其他 AI（AI IT 資本支出成長 ^ 彈性） | B15: A | C15: =(Deploy!C5/Deploy!$C5)^abf_oai_el -> 1 | D15: =(Deploy!D5/Deploy!$C5)^abf_oai_el -> 1.4149388 | E15: =(Deploy!E5/Deploy!$C5)^abf_oai_el -> 1.5930582 | F15: =(Deploy!F5/Deploy!$C5)^abf_oai_el -> 1.7002925
A16: 需求指數：其他 AI（AI IT 資本支出成長 ^ 彈性） | B16: B | C16: =(Deploy!C6/Deploy!$C6)^abf_oai_el -> 1 | D16: =(Deploy!D6/Deploy!$C6)^abf_oai_el -> 1.4149388 | E16: =(Deploy!E6/Deploy!$C6)^abf_oai_el -> 1.4248745 | F16: =(Deploy!F6/Deploy!$C6)^abf_oai_el -> 1.5675922
A17: 需求指數：其他 AI（AI IT 資本支出成長 ^ 彈性） | B17: C | C17: =(Deploy!C7/Deploy!$C7)^abf_oai_el -> 1 | D17: =(Deploy!D7/Deploy!$C7)^abf_oai_el -> 1.4149388 | E17: =(Deploy!E7/Deploy!$C7)^abf_oai_el -> 1.2339775 | F17: =(Deploy!F7/Deploy!$C7)^abf_oai_el -> 1.3170409
A18: 需求指數：非 AI | C18: =(1+abf_gnai)^0 -> 1 | D18: =(1+abf_gnai)^1 -> 1.03 | E18: =(1+abf_gnai)^2 -> 1.0609 | F18: =(1+abf_gnai)^3 -> 1.092727
A19: 需求指數合計（2026＝1） | B19: A | C19: =$C$6*C12+$C$7*C15+$C$8*C18 -> 1 | D19: =$C$6*D12+$C$7*D15+$C$8*D18 -> 1.3149201 | E19: =$C$6*E12+$C$7*E15+$C$8*E18 -> 1.5187165 | F19: =$C$6*F12+$C$7*F15+$C$8*F18 -> 1.7840927
A20: 需求指數合計（2026＝1） | B20: B | C20: =$C$6*C13+$C$7*C16+$C$8*C18 -> 1 | D20: =$C$6*D13+$C$7*D16+$C$8*D18 -> 1.3149201 | E20: =$C$6*E13+$C$7*E16+$C$8*E18 -> 1.3560416 | F20: =$C$6*F13+$C$7*F16+$C$8*F18 -> 1.6264484
A21: 需求指數合計（2026＝1） | B21: C | C21: =$C$6*C14+$C$7*C17+$C$8*C18 -> 1 | D21: =$C$6*D14+$C$7*D17+$C$8*D18 -> 1.3149201 | E21: =$C$6*E14+$C$7*E17+$C$8*E18 -> 1.189687 | F21: =$C$6*F14+$C$7*F17+$C$8*F18 -> 1.3589478
A23: B. 供給
A24: 2026 供給權重：Ibiden | C24: =abfrev_ib26/$C$5 -> 0.20607631
A25: 2026 供給權重：欣興 | C25: =abfrev_un26/$C$5 -> 0.30126393
A26: 2026 供給權重：南電 | C26: =abfrev_np26/$C$5 -> 0.10401947
A27: 2026 供給權重：景碩 | C27: =abfrev_ks26/$C$5 -> 0.068692102
A28: 2026 供給權重：其他（三星電機、AT&S、Shinko、臻鼎等） | C28: =1-C24-C25-C26-C27 -> 0.31994819
A29: 產能指數：Ibiden | C29: =1 -> 1 | D29: =abfcap_ib_27 -> 1.25 | E29: =abfcap_ib_28 -> 1.55 | F29: =abfcap_ib_29 -> 1.8
A30: 產能指數：欣興 | C30: =1 -> 1 | D30: =abfcap_un_27 -> 1.35 | E30: =abfcap_un_28 -> 1.7 | F30: =abfcap_un_29 -> 2
A31: 產能指數：南電 | C31: =1 -> 1 | D31: =abfcap_np_27 -> 1.2 | E31: =abfcap_np_28 -> 1.35 | F31: =abfcap_np_29 -> 1.6
A32: 產能指數：景碩 | C32: =1 -> 1 | D32: =abfcap_ks_27 -> 1.2 | E32: =abfcap_ks_28 -> 1.5 | F32: =abfcap_ks_29 -> 1.85
A33: 產能指數：其他 | C33: =1 -> 1 | D33: =abfcap_oth_27 -> 1.15 | E33: =abfcap_oth_28 -> 1.3 | F33: =abfcap_oth_29 -> 1.45
A34: 載板產能指數（加權） | C34: =$C$24*C29+$C$25*C30+$C$26*C31+$C$27*C32+$C$28*C33 -> 1 | D34: =$C$24*D29+$C$25*D30+$C$26*D31+$C$27*D32+$C$28*D33 -> 1.239496 | E34: =$C$24*E29+$C$25*E30+$C$26*E31+$C$27*E32+$C$28*E33 -> 1.490964 | F34: =$C$24*F29+$C$25*F30+$C$26*F31+$C$27*F32+$C$28*F33 -> 1.7309016
A35: 味之素 ABF 膜可出貨量上限（2026＝1） | C35: =1 -> 1 | D35: =abffilm_27 -> 1.3 | E35: =abffilm_28 -> 1.55 | F35: =abffilm_29 -> 1.8
A36: 有效供給指數（取小） | C36: =MIN(C34,C35) -> 1 | D36: =MIN(D34,D35) -> 1.239496 | E36: =MIN(E34,E35) -> 1.490964 | F36: =MIN(F34,F35) -> 1.7309016 | G36: 膜上限低於載板產能時，膜為瓶頸
A38: C. 缺口（缺口 ÷ 供給；2026 以外部缺口校準）
A39: ABF 供需缺口 | B39: A | C39: =(1+abf_gap_26)*C19/C36-1 -> 0.09 | D39: =(1+abf_gap_26)*D19/D36-1 -> 0.15632716 | E39: =(1+abf_gap_26)*E19/E36-1 -> 0.11028902 | F39: =(1+abf_gap_26)*F19/F36-1 -> 0.12349599
A40: ABF 供需缺口 | B40: B | C40: =(1+abf_gap_26)*C20/C36-1 -> 0.09 | D40: =(1+abf_gap_26)*D20/D36-1 -> 0.15632716 | E40: =(1+abf_gap_26)*E20/E36-1 -> -0.0086378653 | F40: =(1+abf_gap_26)*F20/F36-1 -> 0.024222728
A41: ABF 供需缺口 | B41: C | C41: =(1+abf_gap_26)*C21/C36-1 -> 0.09 | D41: =(1+abf_gap_26)*D21/D36-1 -> 0.15632716 | E41: =(1+abf_gap_26)*E21/E36-1 -> -0.13025478 | F41: =(1+abf_gap_26)*F21/F36-1 -> -0.14423037
A42: 對照：外部缺口（In 頁 abf_gap_*；兩來源中點） | C42: =abf_gap_26 -> 0.09 | D42: =abf_gap_27 -> 0.24 | E42: =abf_gap_28 -> 0.37
A43: 對照：外部缺口低／高 | C43: =TEXT(abf_gap_26_lo,"0%")&"–"&TEXT(abf_gap_26_hi,"0%") -> 8%–10% | D43: =TEXT(abf_gap_27_lo,"0%")&"–"&TEXT(abf_gap_27_hi,"0%") -> 21%–27% | E43: =TEXT(abf_gap_28_lo,"0%")&"–"&TEXT(abf_gap_28_hi,"0%") -> 29%–42%

Sheet PGW
A1: PGW — 每 GW AI 高速 PCB 與 CCL 金額（US$M／GW，不含價格指數）＝ 2026 元件金額 × 2027–29 指數；市場＝每 GW × 部署 GW（Deploy 頁）。PCB 口徑權威原在勝宏模型、CCL 口徑原在台光電模型；兩者口徑不同，不可相加
A3: 項目 | B3: 情境 | C3: 2026 | D3: 2027 | E3: 2028 | F3: 2029 | G3: 說明
A4: 每 GW PCB
A5: 每 GW PCB：加速器卡／運算板 | C5: =pcb_cmp_26 -> 280 | D5: =pcb_cmp_26*pcb_cmpx_27 -> 420 | E5: =pcb_cmp_26*pcb_cmpx_28 -> 462 | F5: =pcb_cmp_26*pcb_cmpx_29 -> 504
A6: 每 GW PCB：交換器板 | C6: =pcb_sw_26 -> 120 | D6: =pcb_sw_26*pcb_swx_27 -> 162 | E6: =pcb_sw_26*pcb_swx_28 -> 180 | F6: =pcb_sw_26*pcb_swx_29 -> 198
A7: 每 GW PCB：中板／背板／其他 | C7: =pcb_mid_26 -> 50 | D7: =pcb_mid_26*pcb_midx_27 -> 100 | E7: =pcb_mid_26*pcb_midx_28 -> 150 | F7: =pcb_mid_26*pcb_midx_29 -> 175
A8: 每 GW PCB 合計（US$M／GW） | C8: =SUM(C5:C7) -> 450 | D8: =SUM(D5:D7) -> 682 | E8: =SUM(E5:E7) -> 792 | F8: =SUM(F5:F7) -> 877
A9: AI 高速 PCB 市場（不含價格指數；US$B） | B9: A | C9: =C8*Deploy!C9/1000 -> 10.529792 | D9: =D8*Deploy!D9/1000 -> 28.403094 | E9: =E8*Deploy!E9/1000 -> 41.811373 | F9: =F8*Deploy!F9/1000 -> 52.741545
A10: AI 高速 PCB 市場（不含價格指數；US$B） | B10: B | C10: =C8*Deploy!C10/1000 -> 10.529792 | D10: =D8*Deploy!D10/1000 -> 28.403094 | E10: =E8*Deploy!E10/1000 -> 33.449099 | F10: =F8*Deploy!F10/1000 -> 44.830313
A11: AI 高速 PCB 市場（不含價格指數；US$B） | B11: C | C11: =C8*Deploy!C11/1000 -> 10.529792 | D11: =D8*Deploy!D11/1000 -> 28.403094 | E11: =E8*Deploy!E11/1000 -> 25.086824 | F11: =F8*Deploy!F11/1000 -> 31.644927
A13: 每 GW CCL
A14: 每 GW CCL：加速器／運算板 | C14: =ccl_cmp_26 -> 190 | D14: =ccl_cmp_26*ccl_cmpx_27 -> 275.5 | E14: =ccl_cmp_26*ccl_cmpx_28 -> 304 | F14: =ccl_cmp_26*ccl_cmpx_29 -> 323
A15: 每 GW CCL：交換器板 | C15: =ccl_sw_26 -> 90 | D15: =ccl_sw_26*ccl_swx_27 -> 126 | E15: =ccl_sw_26*ccl_swx_28 -> 144 | F15: =ccl_sw_26*ccl_swx_29 -> 157.5
A16: 每 GW CCL：UBB／中板／背板 | C16: =ccl_ubb_26 -> 70 | D16: =ccl_ubb_26*ccl_ubbx_27 -> 126 | E16: =ccl_ubb_26*ccl_ubbx_28 -> 161 | F16: =ccl_ubb_26*ccl_ubbx_29 -> 182
A17: 每 GW CCL 合計（US$M／GW） | C17: =SUM(C14:C16) -> 350 | D17: =SUM(D14:D16) -> 527.5 | E17: =SUM(E14:E16) -> 609 | F17: =SUM(F14:F16) -> 662.5
A18: AI 高速 CCL 市場（不含價格指數；US$B） | B18: A | C18: =C17*Deploy!C9/1000 -> 8.1898383 | D18: =D17*Deploy!D9/1000 -> 21.968669 | E18: =E17*Deploy!E9/1000 -> 32.150412 | F18: =F17*Deploy!F9/1000 -> 39.841817
A19: AI 高速 CCL 市場（不含價格指數；US$B） | B19: B | C19: =C17*Deploy!C10/1000 -> 8.1898383 | D19: =D17*Deploy!D10/1000 -> 21.968669 | E19: =E17*Deploy!E10/1000 -> 25.72033 | F19: =F17*Deploy!F10/1000 -> 33.865544
A20: AI 高速 CCL 市場（不含價格指數；US$B） | B20: C | C20: =C17*Deploy!C11/1000 -> 8.1898383 | D20: =D17*Deploy!D11/1000 -> 21.968669 | E20: =E17*Deploy!E11/1000 -> 19.290247 | F20: =F17*Deploy!F11/1000 -> 23.90509
A22: 每 GW PCB ÷ 每 GW CCL | C22: =C8/C17 -> 1.2857143 | D22: =D8/D17 -> 1.292891 | E22: =E8/E17 -> 1.3004926 | F22: =F8/F17 -> 1.3237736

Sheet Rack
A1: Rack — 機架層市場（2026–2029；情境 A／B／C）：(1) AI 伺服器組裝市場（ODM 價）＝部署 GW × 每 GW 架數（Tokenomics）× ODM 每櫃價格；(2) 商用 GPU 系統市場（OEM／整櫃售價，含 GPU）＝商用 GPU 顆數 × 每顆系統價值（Tokenomics 機架價 ÷ 每架 GPU 數）；(3) AI 電源市場＝部署 GW × 每 kW 電源內容。2026 部署依 vr26 混合 GB300 與 VR200，2027 起 VR200（ASIC 機架假設每 GW 價值相同）
A3: 項目 | B3: 情境 | C3: 2026 | D3: 2027 | E3: 2028 | F3: 2029 | G3: 說明
A4: A. AI 伺服器組裝市場（ODM 價；quanta、foxconn、wistron、wiwynn 同讀）
A5: 每 GW ODM 整櫃價值（US$B／GW） | C5: =(TK_RacksPerGW_GB300*asm_odm_gb*(1-vr26)+TK_RacksPerGW_VR200*asm_odm_vr*vr26)/1000 -> 27.1209 | D5: =TK_RacksPerGW_VR200*asm_odm_vr/1000 -> 27.351 | E5: =TK_RacksPerGW_VR200*asm_odm_vr/1000 -> 27.351 | F5: =TK_RacksPerGW_VR200*asm_odm_vr/1000 -> 27.351 | G5: Tokenomics 每 GW 架數 × ODM 每櫃價格（In 頁 M18）
A6: AI 伺服器組裝市場（US$B） | B6: A | C6: =Deploy!C9*C5 -> 634.61653 | D6: =Deploy!D9*D5 -> 1139.0807 | E6: =Deploy!E9*E5 -> 1443.9178 | F6: =Deploy!F9*F5 -> 1644.8506
A7: AI 伺服器組裝市場（US$B） | B7: B | C7: =Deploy!C10*C5 -> 634.61653 | D7: =Deploy!D10*D5 -> 1139.0807 | E7: =Deploy!E10*E5 -> 1155.1342 | F7: =Deploy!F10*F5 -> 1398.123
A8: AI 伺服器組裝市場（US$B） | B8: C | C8: =Deploy!C11*C5 -> 634.61653 | D8: =Deploy!D11*D5 -> 1139.0807 | E8: =Deploy!E11*E5 -> 866.35066 | F8: =Deploy!F11*F5 -> 986.91037
A10: B. 商用 GPU 系統市場（OEM／整櫃售價；dell、smci 同讀；CF10）
A11: 每顆系統價值：GB300 世代（US$K／顆） | C11: =TK_RackPrice_GB300/(TK_GPUsPerGW_GB300/TK_RacksPerGW_GB300)*1000 -> 59.722222 | D11: =TK_RackPrice_GB300/(TK_GPUsPerGW_GB300/TK_RacksPerGW_GB300)*1000 -> 59.722222 | E11: =TK_RackPrice_GB300/(TK_GPUsPerGW_GB300/TK_RacksPerGW_GB300)*1000 -> 59.722222 | F11: =TK_RackPrice_GB300/(TK_GPUsPerGW_GB300/TK_RacksPerGW_GB300)*1000 -> 59.722222 | G11: Tokenomics 機架價 ÷ 每架 GPU 數；HGX 八卡與 AMD MI355 以同值近似（Analogy）
A12: 每顆系統價值：Rubin 世代（US$K／顆） | C12: =TK_RackPrice_VR200/(TK_GPUsPerGW_VR200/TK_RacksPerGW_VR200)*1000 -> 116.66667 | D12: =TK_RackPrice_VR200/(TK_GPUsPerGW_VR200/TK_RacksPerGW_VR200)*1000 -> 116.66667 | E12: =TK_RackPrice_VR200/(TK_GPUsPerGW_VR200/TK_RacksPerGW_VR200)*1000 -> 116.66667 | F12: =TK_RackPrice_VR200/(TK_GPUsPerGW_VR200/TK_RacksPerGW_VR200)*1000 -> 116.66667 | G12: Rubin Ultra 與 AMD MI450 整櫃以 VR200 同值近似（Analogy）
A13: GB300 世代商用 GPU 顆數（Blackwell＋Hopper；2026 另含 AMD MI355；百萬顆，情境 A） | C13: =Units!C4+Units!C7+Units!C8 -> 6.65 | D13: =Units!D4+Units!D7 -> 2.4 | E13: =Units!E4+Units!E7 -> 0.5 | F13: =Units!F4+Units!F7 -> 0.25 | G13: 世代分組依 AMD 實際產品：2026 MI355（八卡，GB300 世代）、2027 起 MI450 Helios 整櫃（Rubin 世代）
A14: Rubin 世代商用 GPU 顆數（Rubin＋Rubin Ultra；2027 起另含 AMD MI450；百萬顆，情境 A） | C14: =Units!C5+Units!C6 -> 1.7 | D14: =Units!D5+Units!D6+Units!D8 -> 8.8 | E14: =Units!E5+Units!E6+Units!E8 -> 11 | F14: =Units!F5+Units!F6+Units!F8 -> 12.65
A15: 商用 GPU 系統市場（US$B） | B15: A | C15: =(C13*C11+C14*C12) -> 595.48611 | D15: =(D13*D11+D14*D12) -> 1170 | E15: =(E13*E11+E14*E12)*um28_A -> 1313.1944 | F15: =(F13*F11+F14*F12)*um29_A -> 1490.7639
A16: 商用 GPU 系統市場（US$B） | B16: B | C16: =(C13*C11+C14*C12) -> 595.48611 | D16: =(D13*D11+D14*D12) -> 1170 | E16: =(E13*E11+E14*E12)*um28_B -> 1050.5556 | F16: =(F13*F11+F14*F12)*um29_B -> 1267.1493
A17: 商用 GPU 系統市場（US$B） | B17: C | C17: =(C13*C11+C14*C12) -> 595.48611 | D17: =(D13*D11+D14*D12) -> 1170 | E17: =(E13*E11+E14*E12)*um28_C -> 787.91667 | F17: =(F13*F11+F14*F12)*um29_C -> 894.45833
A19: C. AI 電源市場（delta、liteon 同讀）
A20: AI 電源每 kW 內容（US$/kW） | C20: =pwr_pkw_26 -> 450 | D20: =pwr_pkw_27 -> 600 | E20: =pwr_pkw_28 -> 680 | F20: =pwr_pkw_29 -> 720 | G20: 機架電源櫃、PSU、BBU、HVDC 電源櫃（In 頁 M17）
A21: AI 電源市場（US$B） | B21: A | C21: =Deploy!C9*C20/1000 -> 10.529792 | D21: =Deploy!D9*D20/1000 -> 24.988059 | E21: =Deploy!E9*E20/1000 -> 35.898654 | F21: =Deploy!F9*F20/1000 -> 43.299786
A22: AI 電源市場（US$B） | B22: B | C22: =Deploy!C10*C20/1000 -> 10.529792 | D22: =Deploy!D10*D20/1000 -> 24.988059 | E22: =Deploy!E10*E20/1000 -> 28.718923 | F22: =Deploy!F10*F20/1000 -> 36.804818
A23: AI 電源市場（US$B） | B23: C | C23: =Deploy!C11*C20/1000 -> 10.529792 | D23: =Deploy!D11*D20/1000 -> 24.988059 | E23: =Deploy!E11*E20/1000 -> 21.539192 | F23: =Deploy!F11*F20/1000 -> 25.979872
A24: 對照：UBS 全球 AI 伺服器電源市場（US$B；口徑未找到） | C24: =pwr_ubs_26 -> 17.7 | D24: =pwr_ubs_27 -> 38.2
A25: 本庫情境 A ÷ UBS | C25: =C21/C24 -> 0.59490351 | D25: =D21/D24 -> 0.65413768 | G25: UBS 高出約五到七成：口徑（是否含 BBU、HVDC、非 AI）未找到，只作對照
A27: D. AI 液冷市場（機架內液冷＋分歧管；avc、auras、jentech 同讀；不含 CDU、Liquid-to-Air 等機架外冷卻）
A28: 每 GW 液冷內容（US$M／GW） | C28: =((1-vr26)*TK_RacksPerGW_GB300*(lc_cool_gb+lc_mani)+vr26*TK_RacksPerGW_VR200*(lc_cool_vr+lc_mani))/1000 -> 350.7208 | D28: =TK_RacksPerGW_VR200*(lc_cool_vr+lc_mani)*lc_adj_27/1000 -> 326.5912 | E28: =TK_RacksPerGW_VR200*(lc_cool_vr+lc_mani)*lc_adj_28/1000 -> 351.7136 | F28: =TK_RacksPerGW_VR200*(lc_cool_vr+lc_mani)*lc_adj_29/1000 -> 351.7136 | G28: 每架機架內液冷（Morgan Stanley BOM）＋分歧管，× 每 GW 架數；2027 起 × 內容調整（Rubin 全液冷、ASIC 液冷）
A29: 液冷滲透率（部署 GW 中液冷占比） | B29: A | C29: =lc_pen_26 -> 0.55 | D29: =lc_pen_27_hi -> 0.85 | E29: =lc_pen_28_hi -> 0.95 | F29: =lc_pen_29_hi -> 0.95
A30: 液冷滲透率（部署 GW 中液冷占比） | B30: B | C30: =lc_pen_26 -> 0.55 | D30: =lc_pen_27 -> 0.75 | E30: =lc_pen_28 -> 0.85 | F30: =lc_pen_29 -> 0.9
A31: 液冷滲透率（部署 GW 中液冷占比） | B31: C | C31: =lc_pen_26 -> 0.55 | D31: =lc_pen_27_lo -> 0.6 | E31: =lc_pen_28_lo -> 0.7 | F31: =lc_pen_29_lo -> 0.75
A32: AI 液冷市場（US$B） | B32: A | C32: =Deploy!C9*C29*C28/1000 -> 4.5136876 | D32: =Deploy!D9*D29*D28/1000 -> 11.561247 | E32: =Deploy!E9*E29*E28/1000 -> 17.639327 | F32: =Deploy!F9*F29*F28/1000 -> 20.093983
A33: AI 液冷市場（US$B） | B33: B | C33: =Deploy!C10*C30*C28/1000 -> 4.5136876 | D33: =Deploy!D10*D30*D28/1000 -> 10.2011 | E33: =Deploy!E10*E30*E28/1000 -> 12.626045 | F33: =Deploy!F10*F30*F28/1000 -> 16.180944
A34: AI 液冷市場（US$B） | B34: C | C34: =Deploy!C11*C31*C28/1000 -> 4.5136876 | D34: =Deploy!D11*D31*D28/1000 -> 8.1608803 | E34: =Deploy!E11*E31*E28/1000 -> 7.7984394 | F34: =Deploy!F11*F31*F28/1000 -> 9.5182023
A35: 對照：TrendForce AI 晶片液冷滲透率（顆數口徑） | C35: =lc_tf_26 -> 0.53 | D35: =lc_tf_27 -> 0.6 | G35: 以 GW 計高於顆數計（液冷晶片功耗較高）

Sheet Equip
A1: Equip — (1) SEMI 設備分項路徑（2026 新聞稿值；2025 由年增回推；2027、2028 年增連乘，測試與封裝 2027 為 2026、2028 的幾何內插；2029 × (1＋g29)）；(2) SoC 測試機市場三情境＝AI（加速器顆數 × 每顆測試時間係數 × 每加權顆支出，以 CY2026 公司市場校準）＋非 AI；(3) 測試 ÷ WFE（CF15）。記憶體測試機市場依 DRAM 設備支出（公司資本支出推導，markets/equipment），留在 advantest 模型
A3: 項目 | B3: 情境 | C3: 2025 | D3: 2026 | E3: 2027 | F3: 2028 | G3: 2029 | H3: 說明
A4: A. SEMI 設備分項（US$B；SEMI 為設備商協會，Interested-party）
A5: SEMI DRAM 設備 | C5: =eq_s_dram_26/(1+eq_g_dram_26) -> 27.913669 | D5: =eq_s_dram_26 -> 38.8 | E5: =D5*(1+eq_g_dram_27) -> 49.4312 | F5: =E5*(1+eq_g_dram_28) -> 56.84588 | G5: =F5*(1+eq_g29) -> 61.39355
A6: SEMI NAND 設備 | C6: =eq_s_nand_26/(1+eq_g_nand_26) -> 10.635042 | D6: =eq_s_nand_26 -> 13.9 | E6: =D6*(1+eq_g_nand_27) -> 18.2229 | F6: =E6*(1+eq_g_nand_28) -> 20.86522 | G6: =F6*(1+eq_g29) -> 22.534438
A7: SEMI 代工與邏輯設備 | C7: =eq_s_fd_26/(1+eq_g_fd_26) -> 65.601346 | D7: =eq_s_fd_26 -> 78 | E7: =D7*(1+eq_g_fd_27) -> 92.118 | F7: =E7*(1+eq_g_fd_28) -> 104.64605 | G7: =F7*(1+eq_g29) -> 113.01773
A8: SEMI 晶圓前段設備（WFE） | C8: =eq_s_wfe_26/(1+eq_g_wfe_26) -> 116.89683 | D8: =eq_s_wfe_26 -> 143.9 | E8: =D8*(1+eq_g_wfe_27) -> 175.2702 | F8: =E8*(1+eq_g_wfe_28) -> 199.9833 | G8: =F8*(1+eq_g29) -> 215.98196
A9: SEMI 測試設備 | C9: =eq_s_test_26/(1+eq_g_test_26) -> 11.679389 | D9: =eq_s_test_26 -> 15.3 | E9: =SQRT(eq_s_test_26*eq_s_test_28) -> 17.839282 | F9: =eq_s_test_28 -> 20.8 | G9: =F9*(1+eq_g29) -> 22.464 | H9: 2027 幾何內插（Derived；SEMI 年中預測未給 2027）
A10: SEMI 組裝與封裝設備 | C10: =eq_s_pkg_26/(1+eq_g_pkg_26) -> 6.1131387 | D10: =eq_s_pkg_26 -> 6.7 | E10: =SQRT(eq_s_pkg_26*eq_s_pkg_28) -> 7.5907839 | F10: =eq_s_pkg_28 -> 8.6 | G10: =F10*(1+eq_g29) -> 9.288 | H10: 2027 幾何內插（Derived；SEMI 年中預測未給 2027）
A11: SEMI 設備合計（WFE＋測試＋封裝） | C11: =C8+C9+C10 -> 134.68936 | D11: =D8+D9+D10 -> 165.9 | E11: =E8+E9+E10 -> 200.70027 | F11: =F8+F9+F10 -> 229.3833 | G11: =G8+G9+G10 -> 247.73396
A13: B. SoC 測試機市場（日曆年，US$B）
A14: 測試時間加權顆數（百萬顆） | B14: A | D14: =(Units!C4*ts_tt_bw+Units!C5*ts_tt_rb+Units!C6*ts_tt_ru+Units!C7*ts_tt_hp+Units!C8*ts_tt_amd+Units!C9*ts_tt_tpu+Units!C10*ts_tt_trn+Units!C11*ts_tt_oth) -> 14.885 | E14: =(Units!D4*ts_tt_bw+Units!D5*ts_tt_rb+Units!D6*ts_tt_ru+Units!D7*ts_tt_hp+Units!D8*ts_tt_amd+Units!D9*ts_tt_tpu+Units!D10*ts_tt_trn+Units!D11*ts_tt_oth) -> 24.31 | F14: =(Units!E4*ts_tt_bw+Units!E5*ts_tt_rb+Units!E6*ts_tt_ru+Units!E7*ts_tt_hp+Units!E8*ts_tt_amd+Units!E9*ts_tt_tpu+Units!E10*ts_tt_trn+Units!E11*ts_tt_oth)*um28_A -> 28.1 | G14: =(Units!F4*ts_tt_bw+Units!F5*ts_tt_rb+Units!F6*ts_tt_ru+Units!F7*ts_tt_hp+Units!F8*ts_tt_amd+Units!F9*ts_tt_tpu+Units!F10*ts_tt_trn+Units!F11*ts_tt_oth)*um29_A -> 31.99
A15: 測試時間加權顆數（百萬顆） | B15: B | D15: =(Units!C4*ts_tt_bw+Units!C5*ts_tt_rb+Units!C6*ts_tt_ru+Units!C7*ts_tt_hp+Units!C8*ts_tt_amd+Units!C9*ts_tt_tpu+Units!C10*ts_tt_trn+Units!C11*ts_tt_oth) -> 14.885 | E15: =(Units!D4*ts_tt_bw+Units!D5*ts_tt_rb+Units!D6*ts_tt_ru+Units!D7*ts_tt_hp+Units!D8*ts_tt_amd+Units!D9*ts_tt_tpu+Units!D10*ts_tt_trn+Units!D11*ts_tt_oth) -> 24.31 | F15: =(Units!E4*ts_tt_bw+Units!E5*ts_tt_rb+Units!E6*ts_tt_ru+Units!E7*ts_tt_hp+Units!E8*ts_tt_amd+Units!E9*ts_tt_tpu+Units!E10*ts_tt_trn+Units!E11*ts_tt_oth)*um28_B -> 22.48 | G15: =(Units!F4*ts_tt_bw+Units!F5*ts_tt_rb+Units!F6*ts_tt_ru+Units!F7*ts_tt_hp+Units!F8*ts_tt_amd+Units!F9*ts_tt_tpu+Units!F10*ts_tt_trn+Units!F11*ts_tt_oth)*um29_B -> 27.1915
A16: 測試時間加權顆數（百萬顆） | B16: C | D16: =(Units!C4*ts_tt_bw+Units!C5*ts_tt_rb+Units!C6*ts_tt_ru+Units!C7*ts_tt_hp+Units!C8*ts_tt_amd+Units!C9*ts_tt_tpu+Units!C10*ts_tt_trn+Units!C11*ts_tt_oth) -> 14.885 | E16: =(Units!D4*ts_tt_bw+Units!D5*ts_tt_rb+Units!D6*ts_tt_ru+Units!D7*ts_tt_hp+Units!D8*ts_tt_amd+Units!D9*ts_tt_tpu+Units!D10*ts_tt_trn+Units!D11*ts_tt_oth) -> 24.31 | F16: =(Units!E4*ts_tt_bw+Units!E5*ts_tt_rb+Units!E6*ts_tt_ru+Units!E7*ts_tt_hp+Units!E8*ts_tt_amd+Units!E9*ts_tt_tpu+Units!E10*ts_tt_trn+Units!E11*ts_tt_oth)*um28_C -> 16.86 | G16: =(Units!F4*ts_tt_bw+Units!F5*ts_tt_rb+Units!F6*ts_tt_ru+Units!F7*ts_tt_hp+Units!F8*ts_tt_amd+Units!F9*ts_tt_tpu+Units!F10*ts_tt_trn+Units!F11*ts_tt_oth)*um29_C -> 19.194
A17: 每加權顆測試支出（以 CY2026 校準；US$B／百萬顆） | D17: =(ts_mk_soc26-ts_nonai26)/D14 -> 0.48370843 | H17: （公司 CY2026 SoC 市場 − 非 AI）÷ 加權顆數；平行測試效率提升基準為 0
A18: 非 AI SoC 測試機市場 | D18: =ts_nonai26*(1+ts_g_nonai)^0 -> 4.3 | E18: =ts_nonai26*(1+ts_g_nonai)^1 -> 4.472 | F18: =ts_nonai26*(1+ts_g_nonai)^2 -> 4.65088 | G18: =ts_nonai26*(1+ts_g_nonai)^3 -> 4.8369152
A19: SoC 測試機市場 | B19: A | C19: =ts_mk_soc25 -> 6.9 | D19: =$D$17*D14+D18 -> 11.5 | E19: =$D$17*E14+E18 -> 16.230952 | F19: =$D$17*F14+F18 -> 18.243087 | G19: =$D$17*G14+G18 -> 20.310748
A20: SoC 測試機市場 | B20: B | C20: =ts_mk_soc25 -> 6.9 | D20: =$D$17*D15+D18 -> 11.5 | E20: =$D$17*E15+E18 -> 16.230952 | F20: =$D$17*F15+F18 -> 15.524646 | G20: =$D$17*G15+G18 -> 17.989673
A21: SoC 測試機市場 | B21: C | C21: =ts_mk_soc25 -> 6.9 | D21: =$D$17*D16+D18 -> 11.5 | E21: =$D$17*E16+E18 -> 16.230952 | F21: =$D$17*F16+F18 -> 12.806204 | G21: =$D$17*G16+G18 -> 14.121215
A23: C. 測試 ÷ WFE（CF15；泰瑞達長期 7–9% 是其 ATE 口徑，SEMI 測試設備另含探針台、分選機等）
A24: SEMI 測試設備 ÷ SEMI WFE | C24: =C9/C8 -> 0.099911941 | D24: =D9/D8 -> 0.10632384 | E24: =E9/E8 -> 0.10178161 | F24: =F9/F8 -> 0.10400869 | G24: =G9/G8 -> 0.10400869
A25: SoC 測試機市場（情境 A）÷ SEMI WFE | C25: =C19/C8 -> 0.059026407 | D25: =D19/D8 -> 0.079916609 | E25: =E19/E8 -> 0.092605314 | F25: =F19/F8 -> 0.091223053 | G25: =G19/G8 -> 0.094039093
A26: 對照：泰瑞達測試 ÷ WFE 長期區間 | D26: =TEXT(ts_tw_lo,"0%")&"–"&TEXT(ts_tw_hi,"0%") -> 7%–9%
A28: D. 混合鍵合占 HBM 工序比例（行業技術情境：CY2028 起 A 高、B 基準、C 低；disco、hanmi、besi 同讀）
A29: 混合鍵合占 HBM 工序比例 | B29: A | C29: =hbm_hbp_25 -> 0 | D29: =hbm_hbp_26 -> 0 | E29: =hbm_hbp_27 -> 0 | F29: =hbm_hbp_28_hi -> 0.15 | G29: =hbm_hbp_29_hi -> 0.3
A30: 混合鍵合占 HBM 工序比例 | B30: B | C30: =hbm_hbp_25 -> 0 | D30: =hbm_hbp_26 -> 0 | E30: =hbm_hbp_27 -> 0 | F30: =hbm_hbp_28 -> 0.05 | G30: =hbm_hbp_29 -> 0.15
A31: 混合鍵合占 HBM 工序比例 | B31: C | C31: =hbm_hbp_25 -> 0 | D31: =hbm_hbp_26 -> 0 | E31: =hbm_hbp_27 -> 0 | F31: =hbm_hbp_28_lo -> 0 | G31: =hbm_hbp_29_lo -> 0.05
A32: HBM 平均堆疊層數（基準） | C32: =hbm_stk_25 -> 10 | D32: =hbm_stk_26 -> 12 | E32: =hbm_stk_27 -> 12.5 | F32: =hbm_stk_28 -> 14 | G32: =hbm_stk_29 -> 15

Sheet Path
A1: Path — 記憶體合約價指數（2025Q1＝1；季增來自 In 頁 M1）。共用市場層：所有記憶體公司用同一條路徑，再依各自會計年度取平均
A3: 路徑 | B3: 情境 | C3: 2025Q1 | D3: 2025Q2 | E3: 2025Q3 | F3: 2025Q4 | G3: 2026Q1 | H3: 2026Q2 | I3: 2026Q3 | J3: 2026Q4 | K3: 2027Q1 | L3: 2027Q2 | M3: 2027Q3 | N3: 2027Q4 | O3: 2028Q1 | P3: 2028Q2 | Q3: 2028Q3 | R3: 2028Q4 | S3: 2029Q1 | T3: 2029Q2 | U3: 2029Q3 | V3: 2029Q4
A4: 一般 DRAM | B4: A | C4: 1 | D4: =C4*(1+cq_1) -> 0.975 | E4: =D4*(1+cq_2) -> 1.096875 | F4: =E4*(1+cq_3) -> 1.6178906 | G4: =F4*(1+cq_4) -> 3.1548867 | H4: =G4*(1+cq_5) -> 5.0635932 | I4: =H4*(1+cq_6) -> 5.8484501 | J4: =I4*(1+cq_7) -> 6.5795064 | K4: =J4*(1+cqA_8) -> 6.7768916 | L4: =K4*(1+cqA_9) -> 6.7768916 | M4: =L4*(1+cqA_10) -> 6.6413538 | N4: =M4*(1+cqA_11) -> 6.4421131 | O4: =N4*(1+cqA_12) -> 6.2488497 | P4: =O4*(1+cqA_13) -> 6.0613843 | Q4: =P4*(1+cqA_14) -> 5.9401566 | R4: =Q4*(1+cqA_15) -> 5.8213534 | S4: =R4*(1+cqA_16) -> 5.6467128 | T4: =S4*(1+cqA_17) -> 5.4773114 | U4: =T4*(1+cqA_18) -> 5.3677652 | V4: =U4*(1+cqA_19) -> 5.2604099
A5: 一般 DRAM | B5: B | C5: 1 | D5: =C5*(1+cq_1) -> 0.975 | E5: =D5*(1+cq_2) -> 1.096875 | F5: =E5*(1+cq_3) -> 1.6178906 | G5: =F5*(1+cq_4) -> 3.1548867 | H5: =G5*(1+cq_5) -> 5.0635932 | I5: =H5*(1+cq_6) -> 5.8484501 | J5: =I5*(1+cq_7) -> 6.5795064 | K5: =J5*(1+cqB_8) -> 6.9084817 | L5: =K5*(1+cqB_9) -> 7.0466513 | M5: =L5*(1+cqB_10) -> 6.4829192 | N5: =M5*(1+cqB_11) -> 5.5104814 | O5: =N5*(1+cqB_12) -> 4.132861 | P5: =O5*(1+cqB_13) -> 3.5129319 | Q5: =P5*(1+cqB_14) -> 3.1616387 | R5: =Q5*(1+cqB_15) -> 3.0035567 | S5: =R5*(1+cqB_16) -> 3.1537346 | T5: =S5*(1+cqB_17) -> 3.3114213 | U5: =T5*(1+cqB_18) -> 3.4107639 | V5: =U5*(1+cqB_19) -> 3.5130869
A6: 一般 DRAM | B6: C | C6: 1 | D6: =C6*(1+cq_1) -> 0.975 | E6: =D6*(1+cq_2) -> 1.096875 | F6: =E6*(1+cq_3) -> 1.6178906 | G6: =F6*(1+cq_4) -> 3.1548867 | H6: =G6*(1+cq_5) -> 5.0635932 | I6: =H6*(1+cq_6) -> 5.8484501 | J6: =I6*(1+cq_7) -> 6.5795064 | K6: =J6*(1+cqC_8) -> 6.9084817 | L6: =K6*(1+cqC_9) -> 7.0466513 | M6: =L6*(1+cqC_10) -> 6.4829192 | N6: =M6*(1+cqC_11) -> 5.5104814 | O6: =N6*(1+cqC_12) -> 3.5818129 | P6: =O6*(1+cqC_13) -> 2.507269 | Q6: =P6*(1+cqC_14) -> 1.8804518 | R6: =Q6*(1+cqC_15) -> 1.5043614 | S6: =R6*(1+cqC_16) -> 1.5043614 | T6: =S6*(1+cqC_17) -> 1.5795795 | U6: =T6*(1+cqC_18) -> 1.7059458 | V6: =U6*(1+cqC_19) -> 1.8765404
A8: NAND | B8: A | C8: 1 | D8: =C8*(1+nq_1) -> 1 | E8: =D8*(1+nq_2) -> 1.05 | F8: =E8*(1+nq_3) -> 1.365 | G8: =F8*(1+nq_4) -> 2.559375 | H8: =G8*(1+nq_5) -> 4.4149219 | I8: =H8*(1+nq_6) -> 5.5186523 | J8: =I8*(1+nq_7) -> 5.9656632 | K8: =J8*(1+nqA_8) -> 6.1446331 | L8: =K8*(1+nqA_9) -> 6.1446331 | M8: =L8*(1+nqA_10) -> 5.8374014 | N8: =M8*(1+nqA_11) -> 5.4287833 | O8: =N8*(1+nqA_12) -> 5.1573442 | P8: =O8*(1+nqA_13) -> 4.899477 | Q8: =P8*(1+nqA_14) -> 4.6545031 | R8: =Q8*(1+nqA_15) -> 4.4217779 | S8: =R8*(1+nqA_16) -> 4.2891246 | T8: =S8*(1+nqA_17) -> 4.1604509 | U8: =T8*(1+nqA_18) -> 4.0356373 | V8: =U8*(1+nqA_19) -> 3.9145682
A9: NAND | B9: B | C9: 1 | D9: =C9*(1+nq_1) -> 1 | E9: =D9*(1+nq_2) -> 1.05 | F9: =E9*(1+nq_3) -> 1.365 | G9: =F9*(1+nq_4) -> 2.559375 | H9: =G9*(1+nq_5) -> 4.4149219 | I9: =H9*(1+nq_6) -> 5.5186523 | J9: =I9*(1+nq_7) -> 5.9656632 | K9: =J9*(1+nqB_8) -> 6.2639463 | L9: =K9*(1+nqB_9) -> 6.3892253 | M9: =L9*(1+nqB_10) -> 5.7503027 | N9: =M9*(1+nqB_11) -> 4.6002422 | O9: =N9*(1+nqB_12) -> 3.2201695 | P9: =O9*(1+nqB_13) -> 2.4151272 | Q9: =P9*(1+nqB_14) -> 1.9321017 | R9: =Q9*(1+nqB_15) -> 1.7388915 | S9: =R9*(1+nqB_16) -> 1.8258361 | T9: =S9*(1+nqB_17) -> 1.9171279 | U9: =T9*(1+nqB_18) -> 1.9746418 | V9: =U9*(1+nqB_19) -> 2.033881
A10: NAND | B10: C | C10: 1 | D10: =C10*(1+nq_1) -> 1 | E10: =D10*(1+nq_2) -> 1.05 | F10: =E10*(1+nq_3) -> 1.365 | G10: =F10*(1+nq_4) -> 2.559375 | H10: =G10*(1+nq_5) -> 4.4149219 | I10: =H10*(1+nq_6) -> 5.5186523 | J10: =I10*(1+nq_7) -> 5.9656632 | K10: =J10*(1+nqC_8) -> 6.2639463 | L10: =K10*(1+nqC_9) -> 6.3892253 | M10: =L10*(1+nqC_10) -> 5.7503027 | N10: =M10*(1+nqC_11) -> 4.6002422 | O10: =N10*(1+nqC_12) -> 2.9901574 | P10: =O10*(1+nqC_13) -> 1.9436023 | Q10: =P10*(1+nqC_14) -> 1.4577017 | R10: =Q10*(1+nqC_15) -> 1.1661614 | S10: =R10*(1+nqC_16) -> 1.1661614 | T10: =S10*(1+nqC_17) -> 1.2244695 | U10: =T10*(1+nqC_18) -> 1.322427 | V10: =U10*(1+nqC_19) -> 1.4546697
A12: 年均指數
A13: 路徑 | B13: 情境 | C13: 2025 | D13: 2026 | E13: 2027 | F13: 2028 | G13: 2029 | H13: 2026÷2025 | I13: 2027÷2026 | J13: 2028÷2027 | K13: 2029÷2028
A14: 一般 DRAM | B14: A | C14: =AVERAGE(C4:F4) -> 1.1724414 | D14: =AVERAGE(G4:J4) -> 5.1616091 | E14: =AVERAGE(K4:N4) -> 6.6593125 | F14: =AVERAGE(O4:R4) -> 6.017936 | G14: =AVERAGE(S4:V4) -> 5.4380499 | H14: =D14/C14-1 -> 3.4024453 | I14: =E14/D14-1 -> 0.29016211 | J14: =F14/E14-1 -> -0.096312722 | K14: =G14/F14-1 -> -0.09635964
A15: 一般 DRAM | B15: B | C15: =AVERAGE(C5:F5) -> 1.1724414 | D15: =AVERAGE(G5:J5) -> 5.1616091 | E15: =AVERAGE(K5:N5) -> 6.4871334 | F15: =AVERAGE(O5:R5) -> 3.4527471 | G15: =AVERAGE(S5:V5) -> 3.3472517 | H15: =D15/C15-1 -> 3.4024453 | I15: =E15/D15-1 -> 0.25680447 | J15: =F15/E15-1 -> -0.46775458 | K15: =G15/F15-1 -> -0.030554048
A16: 一般 DRAM | B16: C | C16: =AVERAGE(C6:F6) -> 1.1724414 | D16: =AVERAGE(G6:J6) -> 5.1616091 | E16: =AVERAGE(K6:N6) -> 6.4871334 | F16: =AVERAGE(O6:R6) -> 2.3684738 | G16: =AVERAGE(S6:V6) -> 1.6666068 | H16: =D16/C16-1 -> 3.4024453 | I16: =E16/D16-1 -> 0.25680447 | J16: =F16/E16-1 -> -0.63489671 | K16: =G16/F16-1 -> -0.29633724
A17: NAND | B17: A | C17: =AVERAGE(C8:F8) -> 1.10375 | D17: =AVERAGE(G8:J8) -> 4.6146531 | E17: =AVERAGE(K8:N8) -> 5.8888627 | F17: =AVERAGE(O8:R8) -> 4.7832755 | G17: =AVERAGE(S8:V8) -> 4.0999453 | H17: =D17/C17-1 -> 3.1808862 | I17: =E17/D17-1 -> 0.27612252 | J17: =F17/E17-1 -> -0.18774205 | K17: =G17/F17-1 -> -0.14285823
A18: NAND | B18: B | C18: =AVERAGE(C9:F9) -> 1.10375 | D18: =AVERAGE(G9:J9) -> 4.6146531 | E18: =AVERAGE(K9:N9) -> 5.7509291 | F18: =AVERAGE(O9:R9) -> 2.3265725 | G18: =AVERAGE(S9:V9) -> 1.9378717 | H18: =D18/C18-1 -> 3.1808862 | I18: =E18/D18-1 -> 0.24623217 | J18: =F18/E18-1 -> -0.59544407 | K18: =G18/F18-1 -> -0.16707013
A19: NAND | B19: C | C19: =AVERAGE(C10:F10) -> 1.10375 | D19: =AVERAGE(G10:J10) -> 4.6146531 | E19: =AVERAGE(K10:N10) -> 5.7509291 | F19: =AVERAGE(O10:R10) -> 1.8894057 | G19: =AVERAGE(S10:V10) -> 1.2919319 | H19: =D19/C19-1 -> 3.1808862 | I19: =E19/D19-1 -> 0.24623217 | J19: =F19/E19-1 -> -0.67146079 | K19: =G19/F19-1 -> -0.31622315

Sheet Mkt
A1: Mkt — 加速器數量層（最小版）與 HBM 市場（日曆年）。需求＝顆數 × GB × 情境顆數係數（2028–29）；供給三情境相同；出貨＝MIN(需求, 供給)；市場＝出貨 × 單價（單價依情境）
A2: 公式由 markets/memory/market.py write() 產生（與各記憶體公司模型的 Mkt 頁同一份）；輸入讀本活頁簿 In 頁
A3: 項目 | B3: 單位 | C3: 2025 | D3: 2026 | E3: 2027 | F3: 2028 | G3: 2029 | H3: 說明
A4: 需求：加速器裝載的 HBM（PB）
A5: NVIDIA Blackwell（B200／B300） | B5: PB | D5: =u_bw_26*g_bw_26 -> 1404 | E5: =u_bw_27*g_bw_27 -> 672 | F5: =u_bw_28*g_bw_28 -> 144
A6: NVIDIA Rubin | B6: PB | D6: =u_rb_26*g_rb_26 -> 489.6 | E6: =u_rb_27*g_rb_27 -> 2016 | F6: =u_rb_28*g_rb_28 -> 2016
A7: NVIDIA Rubin Ultra | B7: PB | D7: =u_ru_26*g_ru_26 -> 0 | E7: =u_ru_27*g_ru_27 -> 307.2 | F7: =u_ru_28*g_ru_28 -> 2048
A8: NVIDIA Hopper（H200 等） | B8: PB | D8: =u_hp_26*g_hp_26 -> 70.5 | E8: =u_hp_27*g_hp_27 -> 0 | F8: =u_hp_28*g_hp_28 -> 0
A9: AMD Instinct | B9: PB | D9: =u_amd_26*g_amd_26 -> 216 | E9: =u_amd_27*g_amd_27 -> 540 | F9: =u_amd_28*g_amd_28 -> 864
A10: Google TPU | B10: PB | D10: =u_tpu_26*g_tpu_26 -> 739.2 | E10: =u_tpu_27*g_tpu_27 -> 1375 | F10: =u_tpu_28*g_tpu_28 -> 2016
A11: AWS Trainium | B11: PB | D11: =u_trn_26*g_trn_26 -> 220 | E11: =u_trn_27*g_trn_27 -> 360 | F11: =u_trn_28*g_trn_28 -> 600
A12: 其他 ASIC（MTIA、Maia、Ascend 等） | B12: PB | D12: =u_oth_26*g_oth_26 -> 150 | E12: =u_oth_27*g_oth_27 -> 900 | F12: =u_oth_28*g_oth_28 -> 1250
A13: 需求合計（裝載） | B13: EB | D13: =SUM(D5:D12)/1000 -> 3.2893 | E13: =SUM(E5:E12)/1000 -> 6.1702 | F13: =SUM(F5:F12)/1000 -> 8.938 | G13: =F13*(1+hbm_dem29) -> 11.6194
A14: 需求 × 出貨係數（基準＝情境 A） | B14: EB | D14: =D13*hbm_gross -> 3.782695 | E14: =E13*hbm_gross -> 7.09573 | F14: =F13*hbm_gross -> 10.2787 | G14: =G13*hbm_gross -> 13.36231
A15: 加速器顆數合計 | B15: 百萬顆 | D15: =u_bw_26+u_rb_26+u_ru_26+u_hp_26+u_amd_26+u_tpu_26+u_trn_26+u_oth_26 -> 15.2 | E15: =u_bw_27+u_rb_27+u_ru_27+u_hp_27+u_amd_27+u_tpu_27+u_trn_27+u_oth_27 -> 23.7 | F15: =u_bw_28+u_rb_28+u_ru_28+u_hp_28+u_amd_28+u_tpu_28+u_trn_28+u_oth_28 -> 26.5 | H15: JPMorgan 2027：GPU 10.9M、ASIC 12.5M；情境 A 基準
A16: 每顆平均 HBM | B16: GB | D16: =D13*1000/D15 -> 216.40132 | E16: =E13*1000/E15 -> 260.34599 | F16: =F13*1000/F15 -> 337.28302
A17: 供給（三情境相同） | B17: EB | C17: =D17/(1+hbm_g26) -> 2.2251147 | D17: =D14 -> 3.782695 | E17: =D17*(1+hbm_sup27) -> 5.8631772 | F17: =E17*(1+hbm_sup28) -> 8.501607 | G17: =F17*(1+hbm_sup29) -> 11.477169 | H17: 2026 供給＝需求出貨（年中已成交）；供給不隨需求情境變（產能 2027 前已訂定）
A18: 顆數係數（A；2028–29 ÷ 基準，與台積電、Advantest 同一套） | B18: x | D18: 1 | E18: 1 | F18: =um28_A -> 1 | G18: =um29_A -> 1 | H18: 2026–27 無情境差異
A19: 顆數係數（B；2028–29 ÷ 基準，與台積電、Advantest 同一套） | B19: x | D19: 1 | E19: 1 | F19: =um28_B -> 0.8 | G19: =um29_B -> 0.85 | H19: 2026–27 無情境差異
A20: 顆數係數（C；2028–29 ÷ 基準，與台積電、Advantest 同一套） | B20: x | D20: 1 | E20: 1 | F20: =um28_C -> 0.6 | G20: =um29_C -> 0.6 | H20: 2026–27 無情境差異
A21: 需求 × 出貨係數（A） | B21: EB | D21: =D14*D18 -> 3.782695 | E21: =E14*E18 -> 7.09573 | F21: =F14*F18 -> 10.2787 | G21: =G14*G18 -> 13.36231
A22: 需求 × 出貨係數（B） | B22: EB | D22: =D14*D19 -> 3.782695 | E22: =E14*E19 -> 7.09573 | F22: =F14*F19 -> 8.22296 | G22: =G14*G19 -> 11.357964
A23: 需求 × 出貨係數（C） | B23: EB | D23: =D14*D20 -> 3.782695 | E23: =E14*E20 -> 7.09573 | F23: =F14*F20 -> 6.16722 | G23: =G14*G20 -> 8.017386
A24: 出貨＝MIN(需求, 供給)（A） | B24: EB | C24: =C17 -> 2.2251147 | D24: =MIN(D21,D17) -> 3.782695 | E24: =MIN(E21,E17) -> 5.8631772 | F24: =MIN(F21,F17) -> 8.501607 | G24: =MIN(G21,G17) -> 11.477169 | H24: 需求低於供給時出貨＝需求（閒置產能）
A25: 出貨＝MIN(需求, 供給)（B） | B25: EB | C25: =C17 -> 2.2251147 | D25: =MIN(D22,D17) -> 3.782695 | E25: =MIN(E22,E17) -> 5.8631772 | F25: =MIN(F22,F17) -> 8.22296 | G25: =MIN(G22,G17) -> 11.357964
A26: 出貨＝MIN(需求, 供給)（C） | B26: EB | C26: =C17 -> 2.2251147 | D26: =MIN(D23,D17) -> 3.782695 | E26: =MIN(E23,E17) -> 5.8631772 | F26: =MIN(F23,F17) -> 6.16722 | G26: =MIN(G23,G17) -> 8.017386
A27: 需求 − 供給（A；>0＝短缺） | B27: EB | D27: =D21-D17 -> 0 | E27: =E21-E17 -> 1.2325527 | F27: =F21-F17 -> 1.777093 | G27: =G21-G17 -> 1.8851405
A28: 需求 − 供給（B；>0＝短缺） | B28: EB | D28: =D22-D17 -> 0 | E28: =E22-E17 -> 1.2325527 | F28: =F22-F17 -> -0.27864701 | G28: =G22-G17 -> -0.11920597
A29: 需求 − 供給（C；>0＝短缺） | B29: EB | D29: =D23-D17 -> 0 | E29: =E23-E17 -> 1.2325527 | F29: =F23-F17 -> -2.334387 | G29: =G23-G17 -> -3.4597835
A30: HBM 單價（A） | B30: $/GB | C30: =hbm_mkt25/C24 -> 15.729526 | D30: =hbm_p26 -> 14.6 | E30: =D30*(1+hbm_p27) -> 26.28 | F30: =E30*(1+hbm_p28_A) -> 28.908 | G30: =F30*(1+hbm_p29_A) -> 27.4626
A31: HBM 單價（B） | B31: $/GB | C31: =hbm_mkt25/C24 -> 15.729526 | D31: =hbm_p26 -> 14.6 | E31: =D31*(1+hbm_p27) -> 26.28 | F31: =E31*(1+hbm_p28_B) -> 19.71 | G31: =F31*(1+hbm_p29_B) -> 19.71
A32: HBM 單價（C） | B32: $/GB | C32: =hbm_mkt25/C24 -> 15.729526 | D32: =hbm_p26 -> 14.6 | E32: =D32*(1+hbm_p27) -> 26.28 | F32: =E32*(1+hbm_p28_C) -> 15.768 | G32: =F32*(1+hbm_p29_C) -> 16.5564
A33: HBM 市場（A） | B33: $B | C33: =C24*C30 -> 35 | D33: =D24*D30 -> 55.227347 | E33: =E24*E30 -> 154.0843 | F33: =F24*F30 -> 245.76446 | G33: =G24*G30 -> 315.19291
A34: HBM 市場（B） | B34: $B | C34: =C25*C31 -> 35 | D34: =D25*D31 -> 55.227347 | E34: =E25*E31 -> 154.0843 | F34: =F25*F31 -> 162.07454 | G34: =G25*G31 -> 223.86546
A35: HBM 市場（C） | B35: $B | C35: =C26*C32 -> 35 | D35: =D26*D32 -> 55.227347 | E35: =E26*E32 -> 154.0843 | F35: =F26*F32 -> 97.244725 | G35: =G26*G32 -> 132.73905
A37: 對帳（樣板驗收 2）
A38: 由下而上：NVIDIA 裝載 HBM × 單價（2026） | B38: $B | D38: =(D5+D6+D7+D8)/1000*hbm_p26 -> 28.67586
A39: 由上而下：NVIDIA 資料中心營收 × 每顆 HBM ÷ 每顆 NVIDIA 內容（2026） | B39: $B | D39: =nv_dc26*nv_hbm/nv_content -> 38.972897 | H39: 橋接表 v0.2；與顆數預測獨立
A40: 差距 | B40: % | D40: =D38/D39-1 -> -0.26421021
A41: 由營收推得 NVIDIA 顆數 vs 顆數預測 | B41: 百萬顆 | D41: =nv_dc26/nv_content -> 8.7383178 | E41: =u_bw_26+u_rb_26+u_hp_26 -> 7.6 | H41: D＝營收推得；E＝顆數預測（2026）
A42: 已發布：SK 海力士自估 2026／BofA 2026／BofA 2027 | B42: $B | D42: =pub26_lo -> 54.6 | E42: =pub26_hi -> 77.4 | F42: =pub27 -> 152.8
A43: 本模型 2026 ÷ SK 海力士自估、2027 ÷ BofA | B43: % | D43: =D33/pub26_lo-1 -> 0.011489872 | F43: =E33/pub27-1 -> 0.0084050925

Sheet TK_In
A1: TK_In — Tokenomics 取數（只讀鏡像；權威在算力收支）：20261025_Tokenomics_v21.7.xlsx（v21.7，commit 91d541f，擷取 2026-10-27）。綠字＝外部連結值，不得在本頁修改；Tokenomics 升版時以 tools/tokenomics/import_tokenomics.py 重抽快照再重建
A2: 右側 J–L 欄：company-models 下游目前讀的舊版快照（markets/chip_bridge v20.1）；M 欄＝與現行 TK 不同的格數（>0 表示下游用的值已過時）
A4: 名稱（TK） | B4: 世代／項目 | C4: 本庫名稱 | D4: 低 | E4: 基準 | F4: 高 | G4: 單位 | H4: TK 位置 | I4: 取用者 | J4: 舊快照 低 | K4: 舊快照 基準 | L4: 舊快照 高 | M4: 差異格數
A5: IF_RacksPerGW | B5: Hopper H100 | C5: TK_RacksPerGW_H100 | D5: 22439 | E5: 22439 | F5: 22439 | G5: 架 | H5: Interface!C6:Q6 | I5: chip_bridge、network（經橋接表） | J5: 22439 | K5: 22439 | L5: 22439 | M5: =(ABS(D5-J5)>0.000000001)+(ABS(E5-K5)>0.000000001)+(ABS(F5-L5)>0.000000001) -> 0
A6: IF_RacksPerGW | B6: GB200 NVL72 | C6: TK_RacksPerGW_GB200 | D6: 6969 | E6: 6969 | F6: 6969 | G6: 架 | H6: Interface!C6:Q6 | I6: chip_bridge、network（經橋接表） | J6: 6969 | K6: 6969 | L6: 6969 | M6: =(ABS(D6-J6)>0.000000001)+(ABS(E6-K6)>0.000000001)+(ABS(F6-L6)>0.000000001) -> 0
A7: IF_RacksPerGW | B7: GB300 NVL72 | C7: TK_RacksPerGW_GB300 | D7: 6764 | E7: 6764 | F7: 6764 | G7: 架 | H7: Interface!C6:Q6 | I7: chip_bridge、network（經橋接表） | J7: 6764 | K7: 6764 | L7: 6764 | M7: =(ABS(D7-J7)>0.000000001)+(ABS(E7-K7)>0.000000001)+(ABS(F7-L7)>0.000000001) -> 0
A8: IF_RacksPerGW | B8: VR200 NVL72 | C8: TK_RacksPerGW_VR200 | D8: 4052 | E8: 4052 | F8: 4052 | G8: 架 | H8: Interface!C6:Q6 | I8: chip_bridge、network（經橋接表） | J8: 4052 | K8: 4052 | L8: 4052 | M8: =(ABS(D8-J8)>0.000000001)+(ABS(E8-K8)>0.000000001)+(ABS(F8-L8)>0.000000001) -> 0
A9: IF_RacksPerGW | B9: Rubin Ultra（MGX NVL 單架，72 GPU） | C9: TK_RacksPerGW_RU | D9: 2705 | E9: 2705 | F9: 2705 | G9: 架 | H9: Interface!C6:Q6 | I9: chip_bridge、network（經橋接表） | J9: 2705 | K9: 2705 | L9: 2705 | M9: =(ABS(D9-J9)>0.000000001)+(ABS(E9-K9)>0.000000001)+(ABS(F9-L9)>0.000000001) -> 0
A10: IF_GPUsPerGW | B10: Hopper H100 | C10: TK_GPUsPerGW_H100 | D10: 718048 | E10: 718048 | F10: 718048 | G10: 顆 | H10: Interface!C7:Q7 | I10: chip_bridge | J10: 718048 | K10: 718048 | L10: 718048 | M10: =(ABS(D10-J10)>0.000000001)+(ABS(E10-K10)>0.000000001)+(ABS(F10-L10)>0.000000001) -> 0
A11: IF_GPUsPerGW | B11: GB200 NVL72 | C11: TK_GPUsPerGW_GB200 | D11: 501768 | E11: 501768 | F11: 501768 | G11: 顆 | H11: Interface!C7:Q7 | I11: chip_bridge | J11: 501768 | K11: 501768 | L11: 501768 | M11: =(ABS(D11-J11)>0.000000001)+(ABS(E11-K11)>0.000000001)+(ABS(F11-L11)>0.000000001) -> 0
A12: IF_GPUsPerGW | B12: GB300 NVL72 | C12: TK_GPUsPerGW_GB300 | D12: 487008 | E12: 487008 | F12: 487008 | G12: 顆 | H12: Interface!C7:Q7 | I12: chip_bridge | J12: 487008 | K12: 487008 | L12: 487008 | M12: =(ABS(D12-J12)>0.000000001)+(ABS(E12-K12)>0.000000001)+(ABS(F12-L12)>0.000000001) -> 0
A13: IF_GPUsPerGW | B13: VR200 NVL72 | C13: TK_GPUsPerGW_VR200 | D13: 291744 | E13: 291744 | F13: 291744 | G13: 顆 | H13: Interface!C7:Q7 | I13: chip_bridge | J13: 291744 | K13: 291744 | L13: 291744 | M13: =(ABS(D13-J13)>0.000000001)+(ABS(E13-K13)>0.000000001)+(ABS(F13-L13)>0.000000001) -> 0
A14: IF_GPUsPerGW | B14: Rubin Ultra（MGX NVL 單架，72 GPU） | C14: TK_GPUsPerGW_RU | D14: 194760 | E14: 194760 | F14: 194760 | G14: 顆 | H14: Interface!C7:Q7 | I14: chip_bridge | J14: 194760 | K14: 194760 | L14: 194760 | M14: =(ABS(D14-J14)>0.000000001)+(ABS(E14-K14)>0.000000001)+(ABS(F14-L14)>0.000000001) -> 0
A15: IF_CapexIT | B15: Hopper H100 | C15: TK_CapexIT_H100 | D15: 21.420269 | E15: 27.510214 | F15: 34.120743 | G15: $B | H15: Interface!C9:Q9 | I15: chip_bridge、network、delta、quanta 等（部署 GW 換算） | J15: 21.420269 | K15: 27.510214 | L15: 34.120743 | M15: =(ABS(D15-J15)>0.000000001)+(ABS(E15-K15)>0.000000001)+(ABS(F15-L15)>0.000000001) -> 0
A16: IF_CapexIT | B16: GB200 NVL72 | C16: TK_CapexIT_GB200 | D16: 20.63939 | E16: 24.015174 | F16: 27.650204 | G16: $B | H16: Interface!C9:Q9 | I16: chip_bridge、network、delta、quanta 等（部署 GW 換算） | J16: 20.63939 | K16: 24.015174 | L16: 27.650204 | M16: =(ABS(D16-J16)>0.000000001)+(ABS(E16-K16)>0.000000001)+(ABS(F16-L16)>0.000000001) -> 0
... A44: IF_StoragePerGPU | B44: Rubin Ultra（MGX NVL 單架，72 GPU） | C44: TK_StoragePerGPU_RU | D44: 300 | E44: 500 | F44: 800 | G44: $/GPU | H44: Interface!C366:Q366 | I44: chip_bridge（目前抄錄值） | J44: 300 | K44: 500 | L44: 800 | M44: =(ABS(D44-J44)>0.000000001)+(ABS(E44-K44)>0.000000001)+(ABS(F44-L44)>0.000000001) -> 0
A45: IF_NonNV_Out_AMD | B45: AMD MI455X（Helios）：產出比（每 GW 產出 ÷ VR200）（NonNV 第 5 列 B:D；同層級、同 SLO；Assumed；C＝低、D＝基準、E＝高） | C45: TK_NonNV_Out_AMD | D45: 0.7 | E45: 0.8 | F45: 1.15 | G45: 比（÷ VR200） | H45: Interface!C369:E369 | I45: avgo、mrvl、amd 等（目前各自假設，待改接）
A46: IF_NonNV_Out_TPU | B46: Google TPU v7 Ironwood：產出比（每 GW 產出 ÷ VR200）（NonNV 第 6 列 B:D；同層級、同 SLO；Assumed；C＝低、D＝基準、E＝高） | C46: TK_NonNV_Out_TPU | D46: 0.6 | E46: 0.8 | F46: 1.1 | G46: 比（÷ VR200） | H46: Interface!C370:E370 | I46: avgo、mrvl、amd 等（目前各自假設，待改接）
A47: IF_NonNV_Out_Trn | B47: AWS Trainium3：產出比（每 GW 產出 ÷ VR200）（NonNV 第 7 列 B:D；同層級、同 SLO；Assumed；C＝低、D＝基準、E＝高） | C47: TK_NonNV_Out_Trn | D47: 0.3 | E47: 0.5 | F47: 0.8 | G47: 比（÷ VR200） | H47: Interface!C371:E371 | I47: avgo、mrvl、amd 等（目前各自假設，待改接）
A48: IF_NonNV_Out_CS | B48: Cerebras WSE-3：產出比（每 GW 產出 ÷ VR200）（NonNV 第 8 列 B:D；同層級、同 SLO；Assumed；C＝低、D＝基準、E＝高） | C48: TK_NonNV_Out_CS | D48: 0.2 | E48: 0.4 | F48: 0.8 | G48: 比（÷ VR200） | H48: Interface!C372:E372 | I48: avgo、mrvl、amd 等（目前各自假設，待改接）
A49: IF_NonNV_Out_OAI | B49: OpenAI／Broadcom 客製：產出比（每 GW 產出 ÷ VR200）（NonNV 第 9 列 B:D；同層級、同 SLO；Assumed；C＝低、D＝基準、E＝高） | C49: TK_NonNV_Out_OAI | D49: 0.4 | E49: 0.6 | F49: 0.9 | G49: 比（÷ VR200） | H49: Interface!C373:E373 | I49: avgo、mrvl、amd 等（目前各自假設，待改接）
A50: IF_NonNV_Out_Ascend | B50: 華為昇騰 910C（CloudMatrix 384）：產出比（每 GW 產出 ÷ VR200）（NonNV 第 10 列 B:D；同層級、同 SLO；Assumed；C＝低、D＝基準、E＝高） | C50: TK_NonNV_Out_Ascend | D50: 0.05 | E50: 0.08 | F50: 0.15 | G50: 比（÷ VR200） | H50: Interface!C379:E379 | I50: avgo、mrvl、amd 等（目前各自假設，待改接）
A51: IF_NonNV_Out_Maia | B51: Microsoft Maia 200：產出比（每 GW 產出 ÷ VR200）（NonNV 第 11 列 B:D；同層級、同 SLO；Assumed；C＝低、D＝基準、E＝高） | C51: TK_NonNV_Out_Maia | D51: 0.25 | E51: 0.55 | F51: 0.75 | G51: 比（÷ VR200） | H51: Interface!C380:E380 | I51: avgo、mrvl、amd 等（目前各自假設，待改接）
A52: IF_NonNV_Hold_AMD | B52: AMD MI455X（Helios）：持有成本比（每 GW 持有成本 ÷ VR200）（NonNV 第 5 列 E:G；同層級、同 SLO；Assumed；C＝低、D＝基準、E＝高） | C52: TK_NonNV_Hold_AMD | D52: 0.67 | E52: 0.85 | F52: 1.12 | G52: 比（÷ VR200） | H52: Interface!C374:E374 | I52: avgo、mrvl、amd 等（目前各自假設，待改接）
A53: IF_NonNV_Hold_TPU | B53: Google TPU v7 Ironwood：持有成本比（每 GW 持有成本 ÷ VR200）（NonNV 第 6 列 E:G；同層級、同 SLO；Assumed；C＝低、D＝基準、E＝高） | C53: TK_NonNV_Hold_TPU | D53: 0.65 | E53: 0.7 | F53: 0.9 | G53: 比（÷ VR200） | H53: Interface!C375:E375 | I53: avgo、mrvl、amd 等（目前各自假設，待改接）
A54: IF_NonNV_Hold_Trn | B54: AWS Trainium3：持有成本比（每 GW 持有成本 ÷ VR200）（NonNV 第 7 列 E:G；同層級、同 SLO；Assumed；C＝低、D＝基準、E＝高） | C54: TK_NonNV_Hold_Trn | D54: 0.45 | E54: 0.61 | F54: 0.7 | G54: 比（÷ VR200） | H54: Interface!C376:E376 | I54: avgo、mrvl、amd 等（目前各自假設，待改接）
A55: IF_NonNV_Hold_CS | B55: Cerebras WSE-3：持有成本比（每 GW 持有成本 ÷ VR200）（NonNV 第 8 列 E:G；同層級、同 SLO；Assumed；C＝低、D＝基準、E＝高） | C55: TK_NonNV_Hold_CS | D55: 0.8 | E55: 1 | F55: 1.2 | G55: 比（÷ VR200） | H55: Interface!C377:E377 | I55: avgo、mrvl、amd 等（目前各自假設，待改接）
A56: IF_NonNV_Hold_OAI | B56: OpenAI／Broadcom 客製：持有成本比（每 GW 持有成本 ÷ VR200）（NonNV 第 9 列 E:G；同層級、同 SLO；Assumed；C＝低、D＝基準、E＝高） | C56: TK_NonNV_Hold_OAI | D56: 0.7 | E56: 0.8 | F56: 1 | G56: 比（÷ VR200） | H56: Interface!C378:E378 | I56: avgo、mrvl、amd 等（目前各自假設，待改接）
... A58: IF_NonNV_Hold_Maia | B58: Microsoft Maia 200：持有成本比（每 GW 持有成本 ÷ VR200）（NonNV 第 11 列 E:G；同層級、同 SLO；Assumed；C＝低、D＝基準、E＝高） | C58: TK_NonNV_Hold_Maia | D58: 0.4 | E58: 0.5 | F58: 0.6 | G58: 比（÷ VR200） | H58: Interface!C382:E382 | I58: avgo、mrvl、amd 等（目前各自假設，待改接）
A60: 下游舊快照與現行 TK 不同的格數 | M60: =SUM(M5:M58) -> 0

Sheet Conflicts
A1: Conflicts — 跨模型衝突登錄：同一個行業變數在兩個以上公司模型有不同值。本庫的任務是讓每個變數只有一個值；建議值為 Claude 預設（判斷類，Andy 可改），在對應子產業併入本庫的版本生效，生效前各公司模型維持現值
A3: ID | B3: 子產業 | C3: 變數 | D3: 單位 | E3: 模型甲（位置） | F3: 甲值 | G3: 模型乙（位置） | H3: 乙值 | I3: 性質 | J3: 建議單一值與理由 | K3: 生效版本 | L3: 狀態 | M3: 來源
A4: CF01 | B4: 載板 | C4: 南電 2027–29 資本支出（新廠是否已核准） | D4: NT$億 | E4: nanya_pcb In!I104（待董事會決議） | F4: 140／180／120 | G4: 工商時報 2026-08-07：董事會已通過高階載板新廠 | H4: 新廠 468 | I4: 過時（公司變數） | J4: 屬公司變數，不入本庫；南電模型下次改版更新為已核准，資本支出依新廠時程重排 | K4: 南電下版 | L4: 移到南電分部重建（部分符合 25 檔，預計 11-07）：屬公司變數，新廠 468 億的時程排入南電資本支出；本庫不收 | M4: 算力收支 2026-10-25 A1
A5: CF02 | B5: 載板 | C5: 欣興 2026 資本支出 | D5: NT$億 | E5: unimicron In!E99 | F5: 537 | G5: ibiden In!H52（同業對照） | H5: 340 | I5: 過時 | J5: 以欣興模型 537（較新）為準；Ibiden 對照列下版改讀欣興成品 | K5: v0.4 | L5: 已併入 v0.8.3（Ibiden 份額相對值 abf_ibrel_28 的來源文字改以欣興 537 億為準；數值不變） | M5: 算力收支 2026-10-25 A2
A6: CF03 | B6: 載板 | C6: ABF 供需缺口 2026／27／28 | D6: % | E6: unimicron In!E131（永豐） | F6: 8／27／35 | G6: ibiden 模型與比對 I9 | H6: —／約 21／逾 40 | I6: 行業變數（兩來源） | J6: 本庫設單一路徑：基準取兩來源中點（2027 約 24%、2028 約 37%），低／高為兩來源；Ibiden、欣興、南電、景碩、味之素改讀 | K6: v0.4 | L6: 待 Andy（各載板與膜模型的滿足率是否改讀本庫缺口；預設不改）：v0.5.1 ABF 供需表已建（ABF 頁）：本庫推導缺口情境 A 2027／28／29＝15.6／11.0／12.3%（外部 24／37%、各公司自算 1.6–14.1%）；味之素膜上限取低值時為 24.6／27.3／34.1%。待 Andy：各載板與膜模型是否改讀本庫缺口（會改變 EPS）；未改前各公司仍用自身滿足率 | M6: 算力收支 2026-10-25 A3
A7: CF04 | B7: 散熱 | C7: 液冷份額合計（健策是否已納入雙鴻） | D7: % | E7: jentech README、Units!G18 | F7: 未含雙鴻 | G7: auras（2026 約 15.9%） | H7: 15.9 | I7: 份額表不完整 | J7: 本庫建液冷份額表（奇鋐、雙鴻、台達電、其他），合計＝100%；各公司讀自己的列 | K7: v0.5 | L7: 已併入 v0.6.1（ShareTbl AI 液冷份額表：奇鋐、雙鴻、健策三情境，K6-lc 全部 ≤100%；雙鴻份額相對值與奇鋐同一組，A 高、B 基準、C 低） | M7: 算力收支 2026-10-25 A4
A8: CF05 | B8: 運算 | C8: AMD README 結果表過時 | D8: — | E8: amd/README.md（v0.2） | F8: FY2028 EPS A 10.44 | G8: amd xlsx v0.2.1 PL!F17 | H8: 11.39 | I8: 文件過時（非數值） | J8: README 依 xlsx 重產（工程類，下次改版） | K8: AMD 下版 | L8: 已釐清（v0.8.3 核對：amd/README.md 已有修正前後對照表 10.44 → 11.39，與成品一致） | M8: 算力收支 2026-10-25 B5
A9: CF06 | B9: 設備 | C9: Hanmi README 與敏感度頁情境 C 定義 | D9: — | E9: hanmi README（v0.2）、Sens!B33 | F9: 3,380／2,835／1,465；C＝高值 | G9: hanmi xlsx v0.2.1 | H9: 3,098 三情境；C＝低值 | I9: 文件過時、標籤相反 | J9: README 重產、Sens!B33 標籤更正（工程類）；混合鍵合滲透率移入本庫 v0.6 | K9: Hanmi 下版／v0.6 | L9: 已併入 v0.8.3（README 已於 v0.2.1 重寫；Sens 頁情境 C 標籤更正為「混合鍵合低值（導入慢）」） | M9: 算力收支 2026-10-25 B6
A10: CF07 | B10: 設備 | C10: BESI README『跨模型注意』過時 | D10: — | E10: besi README | F10: Hanmi A 不含混合鍵合 | G10: hanmi v0.2.1、besi In!I35 | H10: 已同向（A＝高值） | I10: 文件過時 | J10: README 更正（工程類） | K10: BESI 下版 | L10: 已併入 v0.8.3（besi/README.md 跨模型注意更正：三家同向） | M10: 算力收支 2026-10-25 B7
A11: CF08 | B11: 設備 | C11: Lam Research 遠期本益比文字 | D11: x | E11: lrcx/README.md | F11: 約 24 | G11: lrcx xlsx README!A2 | H11: 約 25 | I11: 文件不一致 | J11: 以 xlsx 為準（工程類） | K11: Lam 下版 | L11: 已併入 v0.8.3（lrcx/README.md 改為約 25 倍，與 xlsx 一致） | M11: 算力收支 2026-10-25 B8
A12: CF09 | B12: 伺服器組裝 | C12: 緯穎 2026 AI 占營收、AI 有效份額、AI 營收 | D12: %／US$B | E12: wistron In!E52 | F12: 55%；3.92%；24.85 | G12: wiwynn In!E44 | H12: 48%；3.45%；21.88 | I12: 行業變數（組裝份額表） | J12: 本庫建 AI 伺服器組裝份額表（鴻海、廣達、緯穎、緯創、美超微、戴爾、其他），以緯穎模型（公司自身錨點，較直接）為準；緯創改讀 | K12: v0.5 | L12: 已併入 v0.6（M18 asm_wyai_26＝緯穎模型值 48%〔45–52%〕；緯創改讀，v0.6 前 55%；組裝市場由 Rack 頁單一推導） | M12: 算力收支 2026-10-25 C9
A13: CF10 | B13: 伺服器組裝 | C13: 2026 商用 GPU 系統市場 | D13: US$B | E13: dell Units!C8（AMD 按 VR200 計價） | F13: 638.2 | G13: smci Units!C8（按 GB300） | H13: 595.5 | I13: 口徑（每顆計價世代） | J13: 本庫只留一個系統市場（每顆計價依各平台實際世代，AMD 依 TK NonNV 持有比換算），戴爾、美超微、廣達、鴻海同讀 | K13: v0.5 | L13: 已併入 v0.6（Rack 頁商用 GPU 系統市場：AMD 2026 MI355 計 GB300 世代、2027 起 MI450 計 Rubin 世代；2026＝595.5，戴爾由 638.2 改為同值，美超微不變。AMD 依 TK NonNV 持有比換算的細化未採用，列為後續選項） | M13: 算力收支 2026-10-25 C10
A14: CF11 | B14: 電源 | C14: 台達電 AI 電源市占 | D14: % | E14: delta In!E67（凱基 2025-07） | F14: 約 70 | G14: liteon In!E75（凱基 2025-09） | H14: 60–65 | I14: 行業變數（份額表） | J14: 本庫建 AI 電源份額表（台達電、光寶、其他），基準採較新的凱基 2025-09：台達電 62.5%（60–65），兩家改讀；台達電 EPS 會下修 | K14: v0.5 | L14: 待 Andy（v0.6 已建 AI 電源份額表與 K6-pwr；預設：凱基 70%／62.5% 只作對照，有效份額維持公司營收校準，下游不變。若改為下修台達電份額路徑 ×0.893：台達電 FY2027 EPS −5.6%、目標價 −5.9%、評等中立→放空；見報告 20261027_v0.6） | M14: 算力收支 2026-10-25 C11
... A26: CF23 | B26: 伺服器組裝 | C26: 緯穎 AI 有效份額路徑（2027–29） | D26: % | E26: wistron PL「緯穎 AI 有效份額」（wsh0 × wrel_*） | F26: 3.42／3.42／3.42／3.25（2026–29） | G26: wiwynn PL「緯穎有效份額」（sh0 × rel × ASIC 傾斜係數）；本庫 ShareTbl | H26: 3.45／4.99／5.09／4.89 | I26: 同一變數、兩模型不同路徑 | J26: 單一來源應為緯穎模型（含 ASIC 傾斜與客供）：緯創模型的緯穎部分改讀緯穎模型，或至少 wrel 改讀本庫緯穎份額相對值。會改變緯創 EPS；v0.8.1 只登錄並試算，預設暫不改 | K26: 待 Andy | L26: 待 Andy（v0.8.1 已試算；預設暫不改） | M26: Siliconomics v0.8.1 盤點

Sheet Interface
A1: Interface — 下游唯一連結點（各公司模型與市場層只讀本頁 SIF_ 具名範圍，經 tools/export_snapshot.py 匯成版本固定快照）。A 節＝輸入（純量，含低／高）；B 節＝推導（年度）；C 節＝Tokenomics 鏡像（SIF_TK_*，值＝TK_In）
A2: 版本：Siliconomics v0.10（20261031）；Tokenomics v21.7
A4: 名稱 | B4: 項目 | C4: 單位 | D4: 低 | E4: 基準 | F4: 高 | G4: 標記 | H4: 來源位置
A5: A. 輸入（純量）
A6: SIF_cq_1 | B6: 一般 DRAM 合約價季增 2025Q2 | C6: % | E6: =In!E6 -> -0.025 | G6: =In!G6 -> Interested-party | H6: In!E6
A7: SIF_cq_2 | B7: 一般 DRAM 合約價季增 2025Q3 | C7: % | E7: =In!E7 -> 0.125 | G7: =In!G7 -> Interested-party | H7: In!E7
A8: SIF_cq_3 | B8: 一般 DRAM 合約價季增 2025Q4 | C8: % | E8: =In!E8 -> 0.475 | G8: =In!G8 -> Interested-party | H8: In!E8
A9: SIF_cq_4 | B9: 一般 DRAM 合約價季增 2026Q1 | C9: % | E9: =In!E9 -> 0.95 | G9: =In!G9 -> Interested-party | H9: In!E9
A10: SIF_cq_5 | B10: 一般 DRAM 合約價季增 2026Q2 | C10: % | E10: =In!E10 -> 0.605 | G10: =In!G10 -> Interested-party | H10: In!E10
A11: SIF_cq_6 | B11: 一般 DRAM 合約價季增 2026Q3 | C11: % | E11: =In!E11 -> 0.155 | G11: =In!G11 -> Interested-party | H11: In!E11
A12: SIF_cq_7 | B12: 一般 DRAM 合約價季增 2026Q4 | C12: % | E12: =In!E12 -> 0.125 | G12: =In!G12 -> Interested-party | H12: In!E12
A13: SIF_cqA_8 | B13: 一般 DRAM 合約價季增 2027Q1（A） | C13: % | E13: =In!E13 -> 0.03 | G13: =In!G13 -> Derived | H13: In!E13
A14: SIF_cqA_9 | B14: 一般 DRAM 合約價季增 2027Q2（A） | C14: % | E14: =In!E14 -> 0 | G14: =In!G14 -> Derived | H14: In!E14
A15: SIF_cqA_10 | B15: 一般 DRAM 合約價季增 2027Q3（A） | C15: % | E15: =In!E15 -> -0.02 | G15: =In!G15 -> Derived | H15: In!E15
A16: SIF_cqA_11 | B16: 一般 DRAM 合約價季增 2027Q4（A） | C16: % | E16: =In!E16 -> -0.03 | G16: =In!G16 -> Derived | H16: In!E16
A17: SIF_cqA_12 | B17: 一般 DRAM 合約價季增 2028Q1（A） | C17: % | E17: =In!E17 -> -0.03 | G17: =In!G17 -> Derived | H17: In!E17
... A20: SIF_cqA_15 | B20: 一般 DRAM 合約價季增 2028Q4（A） | C20: % | E20: =In!E20 -> -0.02 | G20: =In!G20 -> Derived | H20: In!E20
A21: SIF_cqA_16 | B21: 一般 DRAM 合約價季增 2029Q1（A） | C21: % | D21: =In!D21 -> -0.03 | E21: =In!E21 -> -0.03 | F21: =In!F21 -> 0.05 | G21: =In!G21 -> Assumed | H21: In!E21
A22: SIF_cqA_17 | B22: 一般 DRAM 合約價季增 2029Q2（A） | C22: % | D22: =In!D22 -> -0.03 | E22: =In!E22 -> -0.03 | F22: =In!F22 -> 0.05 | G22: =In!G22 -> Assumed | H22: In!E22
A23: SIF_cqA_18 | B23: 一般 DRAM 合約價季增 2029Q3（A） | C23: % | D23: =In!D23 -> -0.02 | E23: =In!E23 -> -0.02 | F23: =In!F23 -> 0.03 | G23: =In!G23 -> Assumed | H23: In!E23
A24: SIF_cqA_19 | B24: 一般 DRAM 合約價季增 2029Q4（A） | C24: % | D24: =In!D24 -> -0.02 | E24: =In!E24 -> -0.02 | F24: =In!F24 -> 0.03 | G24: =In!G24 -> Assumed | H24: In!E24
A25: SIF_cqB_8 | B25: 一般 DRAM 合約價季增 2027Q1（B） | C25: % | E25: =In!E25 -> 0.05 | G25: =In!G25 -> Derived | H25: In!E25
A26: SIF_cqB_9 | B26: 一般 DRAM 合約價季增 2027Q2（B） | C26: % | E26: =In!E26 -> 0.02 | G26: =In!G26 -> Derived | H26: In!E26
A27: SIF_cqB_10 | B27: 一般 DRAM 合約價季增 2027Q3（B） | C27: % | E27: =In!E27 -> -0.08 | G27: =In!G27 -> Derived | H27: In!E27
A28: SIF_cqB_11 | B28: 一般 DRAM 合約價季增 2027Q4（B） | C28: % | E28: =In!E28 -> -0.15 | G28: =In!G28 -> Derived | H28: In!E28
A29: SIF_cqB_12 | B29: 一般 DRAM 合約價季增 2028Q1（B） | C29: % | E29: =In!E29 -> -0.25 | G29: =In!G29 -> Derived | H29: In!E29
A30: SIF_cqB_13 | B30: 一般 DRAM 合約價季增 2028Q2（B） | C30: % | E30: =In!E30 -> -0.15 | G30: =In!G30 -> Derived | H30: In!E30
A31: SIF_cqB_14 | B31: 一般 DRAM 合約價季增 2028Q3（B） | C31: % | E31: =In!E31 -> -0.1 | G31: =In!G31 -> Derived | H31: In!E31
A32: SIF_cqB_15 | B32: 一般 DRAM 合約價季增 2028Q4（B） | C32: % | E32: =In!E32 -> -0.05 | G32: =In!G32 -> Derived | H32: In!E32
A33: SIF_cqB_16 | B33: 一般 DRAM 合約價季增 2029Q1（B） | C33: % | D33: =In!D33 -> -0.03 | E33: =In!E33 -> 0.05 | F33: =In!F33 -> 0.05 | G33: =In!G33 -> Assumed | H33: In!E33
A34: SIF_cqB_17 | B34: 一般 DRAM 合約價季增 2029Q2（B） | C34: % | D34: =In!D34 -> -0.03 | E34: =In!E34 -> 0.05 | F34: =In!F34 -> 0.05 | G34: =In!G34 -> Assumed | H34: In!E34
A35: SIF_cqB_18 | B35: 一般 DRAM 合約價季增 2029Q3（B） | C35: % | D35: =In!D35 -> -0.02 | E35: =In!E35 -> 0.03 | F35: =In!F35 -> 0.03 | G35: =In!G35 -> Assumed | H35: In!E35
A36: SIF_cqB_19 | B36: 一般 DRAM 合約價季增 2029Q4（B） | C36: % | D36: =In!D36 -> -0.02 | E36: =In!E36 -> 0.03 | F36: =In!F36 -> 0.03 | G36: =In!G36 -> Assumed | H36: In!E36
A37: SIF_cqC_8 | B37: 一般 DRAM 合約價季增 2027Q1（C） | C37: % | D37: =In!D37 -> 0 | E37: =In!E37 -> 0.05 | F37: =In!F37 -> 0.1 | G37: =In!G37 -> Assumed | H37: In!E37
A38: SIF_cqC_9 | B38: 一般 DRAM 合約價季增 2027Q2（C） | C38: % | D38: =In!D38 -> -0.03 | E38: =In!E38 -> 0.02 | F38: =In!F38 -> 0.07 | G38: =In!G38 -> Assumed | H38: In!E38
A39: SIF_cqC_10 | B39: 一般 DRAM 合約價季增 2027Q3（C） | C39: % | D39: =In!D39 -> -0.13 | E39: =In!E39 -> -0.08 | F39: =In!F39 -> -0.03 | G39: =In!G39 -> Assumed | H39: In!E39
A40: SIF_cqC_11 | B40: 一般 DRAM 合約價季增 2027Q4（C） | C40: % | D40: =In!D40 -> -0.2 | E40: =In!E40 -> -0.15 | F40: =In!F40 -> -0.1 | G40: =In!G40 -> Assumed | H40: In!E40
A41: SIF_cqC_12 | B41: 一般 DRAM 合約價季增 2028Q1（C） | C41: % | D41: =In!D41 -> -0.45 | E41: =In!E41 -> -0.35 | F41: =In!F41 -> -0.25 | G41: =In!G41 -> Assumed | H41: In!E41
A42: SIF_cqC_13 | B42: 一般 DRAM 合約價季增 2028Q2（C） | C42: % | D42: =In!D42 -> -0.4 | E42: =In!E42 -> -0.3 | F42: =In!F42 -> -0.2 | G42: =In!G42 -> Assumed | H42: In!E42
A43: SIF_cqC_14 | B43: 一般 DRAM 合約價季增 2028Q3（C） | C43: % | D43: =In!D43 -> -0.35 | E43: =In!E43 -> -0.25 | F43: =In!F43 -> -0.15 | G43: =In!G43 -> Assumed | H43: In!E43
A44: SIF_cqC_15 | B44: 一般 DRAM 合約價季增 2028Q4（C） | C44: % | D44: =In!D44 -> -0.3 | E44: =In!E44 -> -0.2 | F44: =In!F44 -> -0.1 | G44: =In!G44 -> Assumed | H44: In!E44
... A48: SIF_cqC_19 | B48: 一般 DRAM 合約價季增 2029Q4（C） | C48: % | D48: =In!D48 -> 0 | E48: =In!E48 -> 0.1 | F48: =In!F48 -> 0.2 | G48: =In!G48 -> Assumed | H48: In!E48
A49: SIF_nq_1 | B49: NAND 合約價季增 2025Q2 | C49: % | E49: =In!E49 -> 0 | G49: =In!G49 -> Interested-party | H49: In!E49
A50: SIF_nq_2 | B50: NAND 合約價季增 2025Q3 | C50: % | E50: =In!E50 -> 0.05 | G50: =In!G50 -> Interested-party | H50: In!E50
A51: SIF_nq_3 | B51: NAND 合約價季增 2025Q4 | C51: % | E51: =In!E51 -> 0.3 | G51: =In!G51 -> Interested-party | H51: In!E51
A52: SIF_nq_4 | B52: NAND 合約價季增 2026Q1 | C52: % | E52: =In!E52 -> 0.875 | G52: =In!G52 -> Interested-party | H52: In!E52
A53: SIF_nq_5 | B53: NAND 合約價季增 2026Q2 | C53: % | E53: =In!E53 -> 0.725 | G53: =In!G53 -> Interested-party | H53: In!E53
A54: SIF_nq_6 | B54: NAND 合約價季增 2026Q3 | C54: % | E54: =In!E54 -> 0.25 | G54: =In!G54 -> Verified | H54: In!E54
A55: SIF_nq_7 | B55: NAND 合約價季增 2026Q4 | C55: % | D55: =In!D55 -> 0.032 | E55: =In!E55 -> 0.081 | F55: =In!F55 -> 0.175 | G55: =In!G55 -> Derived | H55: In!E55
A56: SIF_nqA_8 | B56: NAND 合約價季增 2027Q1（A） | C56: % | E56: =In!E56 -> 0.03 | G56: =In!G56 -> Derived | H56: In!E56
A57: SIF_nqA_9 | B57: NAND 合約價季增 2027Q2（A） | C57: % | E57: =In!E57 -> 0 | G57: =In!G57 -> Derived | H57: In!E57
A58: SIF_nqA_10 | B58: NAND 合約價季增 2027Q3（A） | C58: % | E58: =In!E58 -> -0.05 | G58: =In!G58 -> Derived | H58: In!E58
A59: SIF_nqA_11 | B59: NAND 合約價季增 2027Q4（A） | C59: % | E59: =In!E59 -> -0.07 | G59: =In!G59 -> Derived | H59: In!E59
A60: SIF_nqA_12 | B60: NAND 合約價季增 2028Q1（A） | C60: % | E60: =In!E60 -> -0.05 | G60: =In!G60 -> Derived | H60: In!E60
A61: SIF_nqA_13 | B61: NAND 合約價季增 2028Q2（A） | C61: % | E61: =In!E61 -> -0.05 | G61: =In!G61 -> Derived | H61: In!E61
A62: SIF_nqA_14 | B62: NAND 合約價季增 2028Q3（A） | C62: % | E62: =In!E62 -> -0.05 | G62: =In!G62 -> Derived | H62: In!E62
A63: SIF_nqA_15 | B63: NAND 合約價季增 2028Q4（A） | C63: % | E63: =In!E63 -> -0.05 | G63: =In!G63 -> Derived | H63: In!E63
A64: SIF_nqA_16 | B64: NAND 合約價季增 2029Q1（A） | C64: % | D64: =In!D64 -> -0.03 | E64: =In!E64 -> -0.03 | F64: =In!F64 -> 0.05 | G64: =In!G64 -> Assumed | H64: In!E64
A65: SIF_nqA_17 | B65: NAND 合約價季增 2029Q2（A） | C65: % | D65: =In!D65 -> -0.03 | E65: =In!E65 -> -0.03 | F65: =In!F65 -> 0.05 | G65: =In!G65 -> Assumed | H65: In!E65
A66: SIF_nqA_18 | B66: NAND 合約價季增 2029Q3（A） | C66: % | D66: =In!D66 -> -0.03 | E66: =In!E66 -> -0.03 | F66: =In!F66 -> 0.03 | G66: =In!G66 -> Assumed | H66: In!E66
A67: SIF_nqA_19 | B67: NAND 合約價季增 2029Q4（A） | C67: % | D67: =In!D67 -> -0.03 | E67: =In!E67 -> -0.03 | F67: =In!F67 -> 0.03 | G67: =In!G67 -> Assumed | H67: In!E67
A68: SIF_nqB_8 | B68: NAND 合約價季增 2027Q1（B） | C68: % | E68: =In!E68 -> 0.05 | G68: =In!G68 -> Derived | H68: In!E68
A69: SIF_nqB_9 | B69: NAND 合約價季增 2027Q2（B） | C69: % | E69: =In!E69 -> 0.02 | G69: =In!G69 -> Derived | H69: In!E69
A70: SIF_nqB_10 | B70: NAND 合約價季增 2027Q3（B） | C70: % | E70: =In!E70 -> -0.1 | G70: =In!G70 -> Derived | H70: In!E70
A71: SIF_nqB_11 | B71: NAND 合約價季增 2027Q4（B） | C71: % | E71: =In!E71 -> -0.2 | G71: =In!G71 -> Derived | H71: In!E71
A72: SIF_nqB_12 | B72: NAND 合約價季增 2028Q1（B） | C72: % | E72: =In!E72 -> -0.3 | G72: =In!G72 -> Derived | H72: In!E72
A73: SIF_nqB_13 | B73: NAND 合約價季增 2028Q2（B） | C73: % | E73: =In!E73 -> -0.25 | G73: =In!G73 -> Derived | H73: In!E73
A74: SIF_nqB_14 | B74: NAND 合約價季增 2028Q3（B） | C74: % | E74: =In!E74 -> -0.2 | G74: =In!G74 -> Derived | H74: In!E74
A75: SIF_nqB_15 | B75: NAND 合約價季增 2028Q4（B） | C75: % | E75: =In!E75 -> -0.1 | G75: =In!G75 -> Derived | H75: In!E75
A76: SIF_nqB_16 | B76: NAND 合約價季增 2029Q1（B） | C76: % | D76: =In!D76 -> -0.03 | E76: =In!E76 -> 0.05 | F76: =In!F76 -> 0.05 | G76: =In!G76 -> Assumed | H76: In!E76
A77: SIF_nqB_17 | B77: NAND 合約價季增 2029Q2（B） | C77: % | D77: =In!D77 -> -0.03 | E77: =In!E77 -> 0.05 | F77: =In!F77 -> 0.05 | G77: =In!G77 -> Assumed | H77: In!E77
A78: SIF_nqB_18 | B78: NAND 合約價季增 2029Q3（B） | C78: % | D78: =In!D78 -> -0.03 | E78: =In!E78 -> 0.03 | F78: =In!F78 -> 0.03 | G78: =In!G78 -> Assumed | H78: In!E78
A79: SIF_nqB_19 | B79: NAND 合約價季增 2029Q4（B） | C79: % | D79: =In!D79 -> -0.03 | E79: =In!E79 -> 0.03 | F79: =In!F79 -> 0.03 | G79: =In!G79 -> Assumed | H79: In!E79
A80: SIF_nqC_8 | B80: NAND 合約價季增 2027Q1（C） | C80: % | D80: =In!D80 -> 0 | E80: =In!E80 -> 0.05 | F80: =In!F80 -> 0.1 | G80: =In!G80 -> Assumed | H80: In!E80
A81: SIF_nqC_9 | B81: NAND 合約價季增 2027Q2（C） | C81: % | D81: =In!D81 -> -0.03 | E81: =In!E81 -> 0.02 | F81: =In!F81 -> 0.07 | G81: =In!G81 -> Assumed | H81: In!E81
A82: SIF_nqC_10 | B82: NAND 合約價季增 2027Q3（C） | C82: % | D82: =In!D82 -> -0.15 | E82: =In!E82 -> -0.1 | F82: =In!F82 -> -0.05 | G82: =In!G82 -> Assumed | H82: In!E82
A83: SIF_nqC_11 | B83: NAND 合約價季增 2027Q4（C） | C83: % | D83: =In!D83 -> -0.25 | E83: =In!E83 -> -0.2 | F83: =In!F83 -> -0.15 | G83: =In!G83 -> Assumed | H83: In!E83
A84: SIF_nqC_12 | B84: NAND 合約價季增 2028Q1（C） | C84: % | D84: =In!D84 -> -0.45 | E84: =In!E84 -> -0.35 | F84: =In!F84 -> -0.25 | G84: =In!G84 -> Assumed | H84: In!E84
A85: SIF_nqC_13 | B85: NAND 合約價季增 2028Q2（C） | C85: % | D85: =In!D85 -> -0.45 | E85: =In!E85 -> -0.35 | F85: =In!F85 -> -0.25 | G85: =In!G85 -> Assumed | H85: In!E85
A86: SIF_nqC_14 | B86: NAND 合約價季增 2028Q3（C） | C86: % | D86: =In!D86 -> -0.35 | E86: =In!E86 -> -0.25 | F86: =In!F86 -> -0.15 | G86: =In!G86 -> Assumed | H86: In!E86
A87: SIF_nqC_15 | B87: NAND 合約價季增 2028Q4（C） | C87: % | D87: =In!D87 -> -0.3 | E87: =In!E87 -> -0.2 | F87: =In!F87 -> -0.1 | G87: =In!G87 -> Assumed | H87: In!E87
... A91: SIF_nqC_19 | B91: NAND 合約價季增 2029Q4（C） | C91: % | D91: =In!D91 -> 0 | E91: =In!E91 -> 0.1 | F91: =In!F91 -> 0.2 | G91: =In!G91 -> Assumed | H91: In!E91
A92: SIF_u_bw_26 | B92: NVIDIA Blackwell（B200／B300） 顆數 2026 | C92: 百萬顆 | E92: =In!E93 -> 5.4 | G92: =In!G93 -> Interested-party | H92: In!E93
A93: SIF_u_bw_27 | B93: NVIDIA Blackwell（B200／B300） 顆數 2027 | C93: 百萬顆 | E93: =In!E94 -> 2.4 | G93: =In!G94 -> Interested-party | H93: In!E94
A94: SIF_u_bw_28 | B94: NVIDIA Blackwell（B200／B300） 顆數 2028 | C94: 百萬顆 | E94: =In!E95 -> 0.5 | G94: =In!G95 -> Interested-party | H94: In!E95
A95: SIF_g_bw_26 | B95: NVIDIA Blackwell（B200／B300） 每顆 HBM 2026 | C95: GB | E95: =In!E96 -> 260 | G95: =In!G96 -> Interested-party | H95: In!E96
A96: SIF_g_bw_27 | B96: NVIDIA Blackwell（B200／B300） 每顆 HBM 2027 | C96: GB | E96: =In!E97 -> 280 | G96: =In!G97 -> Interested-party | H96: In!E97
A97: SIF_g_bw_28 | B97: NVIDIA Blackwell（B200／B300） 每顆 HBM 2028 | C97: GB | E97: =In!E98 -> 288 | G97: =In!G98 -> Interested-party | H97: In!E98
A98: SIF_u_rb_26 | B98: NVIDIA Rubin 顆數 2026 | C98: 百萬顆 | E98: =In!E99 -> 1.7 | G98: =In!G99 -> Interested-party | H98: In!E99
A99: SIF_u_rb_27 | B99: NVIDIA Rubin 顆數 2027 | C99: 百萬顆 | E99: =In!E100 -> 7 | G99: =In!G100 -> Interested-party | H99: In!E100
A100: SIF_u_rb_28 | B100: NVIDIA Rubin 顆數 2028 | C100: 百萬顆 | E100: =In!E101 -> 7 | G100: =In!G101 -> Interested-party | H100: In!E101
A101: SIF_g_rb_26 | B101: NVIDIA Rubin 每顆 HBM 2026 | C101: GB | E101: =In!E102 -> 288 | G101: =In!G102 -> Interested-party | H101: In!E102
A102: SIF_g_rb_27 | B102: NVIDIA Rubin 每顆 HBM 2027 | C102: GB | E102: =In!E103 -> 288 | G102: =In!G103 -> Interested-party | H102: In!E103
A103: SIF_g_rb_28 | B103: NVIDIA Rubin 每顆 HBM 2028 | C103: GB | E103: =In!E104 -> 288 | G103: =In!G104 -> Interested-party | H103: In!E104
A104: SIF_u_ru_26 | B104: NVIDIA Rubin Ultra 顆數 2026 | C104: 百萬顆 | D104: =In!D105 -> 0 | E104: =In!E105 -> 0 | F104: =In!F105 -> 0 | G104: =In!G105 -> Assumed | H104: In!E105
A105: SIF_u_ru_27 | B105: NVIDIA Rubin Ultra 顆數 2027 | C105: 百萬顆 | D105: =In!D106 -> 0 | E105: =In!E106 -> 0.3 | F105: =In!F106 -> 0.6 | G105: =In!G106 -> Assumed | H105: In!E106
A106: SIF_u_ru_28 | B106: NVIDIA Rubin Ultra 顆數 2028 | C106: 百萬顆 | D106: =In!D107 -> 1 | E106: =In!E107 -> 2 | F106: =In!F107 -> 3 | G106: =In!G107 -> Assumed | H106: In!E107
A107: SIF_g_ru_26 | B107: NVIDIA Rubin Ultra 每顆 HBM 2026 | C107: GB | E107: =In!E108 -> 1024 | G107: =In!G108 -> Interested-party | H107: In!E108
A108: SIF_g_ru_27 | B108: NVIDIA Rubin Ultra 每顆 HBM 2027 | C108: GB | E108: =In!E109 -> 1024 | G108: =In!G109 -> Interested-party | H108: In!E109
A109: SIF_g_ru_28 | B109: NVIDIA Rubin Ultra 每顆 HBM 2028 | C109: GB | E109: =In!E110 -> 1024 | G109: =In!G110 -> Interested-party | H109: In!E110
...

Sheet Checks
A1: Checks — 交叉檢查與治理（ERROR 計入 SGOV_Errors，須為 0；WARN 計入 SGOV_Warn，列為待補）
A3: ID | B3: 項目 | C3: 本庫值 | D3: 參照值 | E3: 差 | F3: 判讀 | G3: 性質 | H3: 說明
A4: K1-A2025 | B4: HBM 市場（A） 2025：本庫 vs SK 海力士模型成品 | C4: =Mkt!C33 -> 35 | D4: 35 | E4: =IF(ISNUMBER(D4),C4-D4,"") -> 0 | F4: =IF(NOT(ISNUMBER(D4)),"WARN",IF(ABS(E4)<0.000000001,"OK","ERROR")) -> OK | G4: 驗證（搬移忠實度） | H4: skhynix/dist/20261030_SK海力士個股模型_v0.6.1.xlsx
A5: K1-A2026 | B5: HBM 市場（A） 2026：本庫 vs SK 海力士模型成品 | C5: =Mkt!D33 -> 55.227347 | D5: 55.227347 | E5: =IF(ISNUMBER(D5),C5-D5,"") -> 0 | F5: =IF(NOT(ISNUMBER(D5)),"WARN",IF(ABS(E5)<0.000000001,"OK","ERROR")) -> OK | G5: 驗證（搬移忠實度） | H5: skhynix/dist/20261030_SK海力士個股模型_v0.6.1.xlsx
A6: K1-A2027 | B6: HBM 市場（A） 2027：本庫 vs SK 海力士模型成品 | C6: =Mkt!E33 -> 154.0843 | D6: 154.0843 | E6: =IF(ISNUMBER(D6),C6-D6,"") -> 0 | F6: =IF(NOT(ISNUMBER(D6)),"WARN",IF(ABS(E6)<0.000000001,"OK","ERROR")) -> OK | G6: 驗證（搬移忠實度） | H6: skhynix/dist/20261030_SK海力士個股模型_v0.6.1.xlsx
A7: K1-A2028 | B7: HBM 市場（A） 2028：本庫 vs SK 海力士模型成品 | C7: =Mkt!F33 -> 245.76446 | D7: 245.76446 | E7: =IF(ISNUMBER(D7),C7-D7,"") -> 0 | F7: =IF(NOT(ISNUMBER(D7)),"WARN",IF(ABS(E7)<0.000000001,"OK","ERROR")) -> OK | G7: 驗證（搬移忠實度） | H7: skhynix/dist/20261030_SK海力士個股模型_v0.6.1.xlsx
A8: K1-A2029 | B8: HBM 市場（A） 2029：本庫 vs SK 海力士模型成品 | C8: =Mkt!G33 -> 315.19291 | D8: 315.19291 | E8: =IF(ISNUMBER(D8),C8-D8,"") -> 0 | F8: =IF(NOT(ISNUMBER(D8)),"WARN",IF(ABS(E8)<0.000000001,"OK","ERROR")) -> OK | G8: 驗證（搬移忠實度） | H8: skhynix/dist/20261030_SK海力士個股模型_v0.6.1.xlsx
A9: K1-B2025 | B9: HBM 市場（B） 2025：本庫 vs SK 海力士模型成品 | C9: =Mkt!C34 -> 35 | D9: 35 | E9: =IF(ISNUMBER(D9),C9-D9,"") -> 0 | F9: =IF(NOT(ISNUMBER(D9)),"WARN",IF(ABS(E9)<0.000000001,"OK","ERROR")) -> OK | G9: 驗證（搬移忠實度） | H9: skhynix/dist/20261030_SK海力士個股模型_v0.6.1.xlsx
A10: K1-B2026 | B10: HBM 市場（B） 2026：本庫 vs SK 海力士模型成品 | C10: =Mkt!D34 -> 55.227347 | D10: 55.227347 | E10: =IF(ISNUMBER(D10),C10-D10,"") -> 0 | F10: =IF(NOT(ISNUMBER(D10)),"WARN",IF(ABS(E10)<0.000000001,"OK","ERROR")) -> OK | G10: 驗證（搬移忠實度） | H10: skhynix/dist/20261030_SK海力士個股模型_v0.6.1.xlsx
A11: K1-B2027 | B11: HBM 市場（B） 2027：本庫 vs SK 海力士模型成品 | C11: =Mkt!E34 -> 154.0843 | D11: 154.0843 | E11: =IF(ISNUMBER(D11),C11-D11,"") -> 0 | F11: =IF(NOT(ISNUMBER(D11)),"WARN",IF(ABS(E11)<0.000000001,"OK","ERROR")) -> OK | G11: 驗證（搬移忠實度） | H11: skhynix/dist/20261030_SK海力士個股模型_v0.6.1.xlsx
A12: K1-B2028 | B12: HBM 市場（B） 2028：本庫 vs SK 海力士模型成品 | C12: =Mkt!F34 -> 162.07454 | D12: 162.07454 | E12: =IF(ISNUMBER(D12),C12-D12,"") -> 0 | F12: =IF(NOT(ISNUMBER(D12)),"WARN",IF(ABS(E12)<0.000000001,"OK","ERROR")) -> OK | G12: 驗證（搬移忠實度） | H12: skhynix/dist/20261030_SK海力士個股模型_v0.6.1.xlsx
A13: K1-B2029 | B13: HBM 市場（B） 2029：本庫 vs SK 海力士模型成品 | C13: =Mkt!G34 -> 223.86546 | D13: 223.86546 | E13: =IF(ISNUMBER(D13),C13-D13,"") -> 0 | F13: =IF(NOT(ISNUMBER(D13)),"WARN",IF(ABS(E13)<0.000000001,"OK","ERROR")) -> OK | G13: 驗證（搬移忠實度） | H13: skhynix/dist/20261030_SK海力士個股模型_v0.6.1.xlsx
A14: K1-C2025 | B14: HBM 市場（C） 2025：本庫 vs SK 海力士模型成品 | C14: =Mkt!C35 -> 35 | D14: 35 | E14: =IF(ISNUMBER(D14),C14-D14,"") -> 0 | F14: =IF(NOT(ISNUMBER(D14)),"WARN",IF(ABS(E14)<0.000000001,"OK","ERROR")) -> OK | G14: 驗證（搬移忠實度） | H14: skhynix/dist/20261030_SK海力士個股模型_v0.6.1.xlsx
A15: K1-C2026 | B15: HBM 市場（C） 2026：本庫 vs SK 海力士模型成品 | C15: =Mkt!D35 -> 55.227347 | D15: 55.227347 | E15: =IF(ISNUMBER(D15),C15-D15,"") -> 0 | F15: =IF(NOT(ISNUMBER(D15)),"WARN",IF(ABS(E15)<0.000000001,"OK","ERROR")) -> OK | G15: 驗證（搬移忠實度） | H15: skhynix/dist/20261030_SK海力士個股模型_v0.6.1.xlsx
A16: K1-C2027 | B16: HBM 市場（C） 2027：本庫 vs SK 海力士模型成品 | C16: =Mkt!E35 -> 154.0843 | D16: 154.0843 | E16: =IF(ISNUMBER(D16),C16-D16,"") -> 0 | F16: =IF(NOT(ISNUMBER(D16)),"WARN",IF(ABS(E16)<0.000000001,"OK","ERROR")) -> OK | G16: 驗證（搬移忠實度） | H16: skhynix/dist/20261030_SK海力士個股模型_v0.6.1.xlsx
A17: K1-C2028 | B17: HBM 市場（C） 2028：本庫 vs SK 海力士模型成品 | C17: =Mkt!F35 -> 97.244725 | D17: 97.244725 | E17: =IF(ISNUMBER(D17),C17-D17,"") -> 0 | F17: =IF(NOT(ISNUMBER(D17)),"WARN",IF(ABS(E17)<0.000000001,"OK","ERROR")) -> OK | G17: 驗證（搬移忠實度） | H17: skhynix/dist/20261030_SK海力士個股模型_v0.6.1.xlsx
A18: K1-C2029 | B18: HBM 市場（C） 2029：本庫 vs SK 海力士模型成品 | C18: =Mkt!G35 -> 132.73905 | D18: 132.73905 | E18: =IF(ISNUMBER(D18),C18-D18,"") -> 0 | F18: =IF(NOT(ISNUMBER(D18)),"WARN",IF(ABS(E18)<0.000000001,"OK","ERROR")) -> OK | G18: 驗證（搬移忠實度） | H18: skhynix/dist/20261030_SK海力士個股模型_v0.6.1.xlsx
A19: K2-A28 | B19: 情境 A 2028 顆數係數：A＝1；B、C 在區間內 | C19: =um28_A -> 1 | F19: =IF(ABS(C19-1)<0.000000001,"OK","ERROR") -> OK | G19: 驗證
A20: K2-A29 | B20: 情境 A 2029 顆數係數：A＝1；B、C 在區間內 | C20: =um29_A -> 1 | F20: =IF(ABS(C20-1)<0.000000001,"OK","ERROR") -> OK | G20: 驗證
A21: K2-B28 | B21: 情境 B 2028 顆數係數：A＝1；B、C 在區間內 | C21: =um28_B -> 0.8 | D21: =um28_B_lo&"–"&um28_B_hi -> 0.7–0.9 | F21: =IF(AND(C21>=um28_B_lo,C21<=um28_B_hi),"OK","ERROR") -> OK | G21: 驗證
A22: K2-B29 | B22: 情境 B 2029 顆數係數：A＝1；B、C 在區間內 | C22: =um29_B -> 0.85 | D22: =um29_B_lo&"–"&um29_B_hi -> 0.75–0.95 | F22: =IF(AND(C22>=um29_B_lo,C22<=um29_B_hi),"OK","ERROR") -> OK | G22: 驗證
A23: K2-C28 | B23: 情境 C 2028 顆數係數：A＝1；B、C 在區間內 | C23: =um28_C -> 0.6 | D23: =um28_C_lo&"–"&um28_C_hi -> 0.5–0.7 | F23: =IF(AND(C23>=um28_C_lo,C23<=um28_C_hi),"OK","ERROR") -> OK | G23: 驗證
A24: K2-C29 | B24: 情境 C 2029 顆數係數：A＝1；B、C 在區間內 | C24: =um29_C -> 0.6 | D24: =um29_C_lo&"–"&um29_C_hi -> 0.5–0.7 | F24: =IF(AND(C24>=um29_C_lo,C24<=um29_C_hi),"OK","ERROR") -> OK | G24: 驗證
A25: K2-ord28 | B25: 2028 顆數係數 A ≥ B ≥ C | F25: =IF(AND(um28_A>=um28_B,um28_B>=um28_C),"OK","ERROR") -> OK | G25: 驗證
A26: K2-ord29 | B26: 2029 顆數係數 A ≥ B ≥ C | F26: =IF(AND(um29_A>=um29_B,um29_B>=um29_C),"OK","ERROR") -> OK | G26: 驗證
A27: K3 | B27: 下游（chip_bridge 等）讀的 Tokenomics 快照與現行 TK 不同的格數 | C27: =TK_In!$M$60 -> 0 | F27: =IF(C27=0,"OK","WARN") -> OK | G27: 治理（TK 一致） | H27: WARN＝下游仍用舊版 TK；本庫已用現行版；差異明細見 TK_In 頁 M 欄
A28: K4-2026 | B28: 2026 平台別顆數合計（Units）＝ HBM 市場頁顆數合計（Mkt） | C28: =Units!C12 -> 15.2 | D28: =Mkt!D15 -> 15.2 | E28: =C28-D28 -> 0 | F28: =IF(ABS(E28)<0.000000001,"OK","ERROR") -> OK | G28: 恆等式（結構）
A29: K4-2027 | B29: 2027 平台別顆數合計（Units）＝ HBM 市場頁顆數合計（Mkt） | C29: =Units!D12 -> 23.7 | D29: =Mkt!E15 -> 23.7 | E29: =C29-D29 -> 0 | F29: =IF(ABS(E29)<0.000000001,"OK","ERROR") -> OK | G29: 恆等式（結構）
A30: K4-2028 | B30: 2028 平台別顆數合計（Units）＝ HBM 市場頁顆數合計（Mkt） | C30: =Units!E12 -> 26.5 | D30: =Mkt!F15 -> 26.5 | E30: =C30-D30 -> 0 | F30: =IF(ABS(E30)<0.000000001,"OK","ERROR") -> OK | G30: 恆等式（結構）
A31: K5-bw | B31: 2029 成長率在區間內：NVIDIA Blackwell（B200／B300） | C31: =g29_bw -> -0.5 | D31: =g29_bw_lo&"–"&g29_bw_hi -> -0.7–-0.3 | F31: =IF(AND(C31>=g29_bw_lo,C31<=g29_bw_hi),"OK","ERROR") -> OK | G31: 驗證
A32: K5-rb | B32: 2029 成長率在區間內：NVIDIA Rubin | C32: =g29_rb -> 0.15 | D32: =g29_rb_lo&"–"&g29_rb_hi -> 0.05–0.25 | F32: =IF(AND(C32>=g29_rb_lo,C32<=g29_rb_hi),"OK","ERROR") -> OK | G32: 驗證
A33: K5-ru | B33: 2029 成長率在區間內：NVIDIA Rubin Ultra | C33: =g29_ru -> 0.15 | D33: =g29_ru_lo&"–"&g29_ru_hi -> 0.05–0.25 | F33: =IF(AND(C33>=g29_ru_lo,C33<=g29_ru_hi),"OK","ERROR") -> OK | G33: 驗證
A34: K5-hp | B34: 2029 成長率在區間內：NVIDIA Hopper（H200 等） | C34: =g29_hp -> 0 | D34: =g29_hp_lo&"–"&g29_hp_hi -> 0–0 | F34: =IF(AND(C34>=g29_hp_lo,C34<=g29_hp_hi),"OK","ERROR") -> OK | G34: 驗證
A35: K5-amd | B35: 2029 成長率在區間內：AMD Instinct | C35: =g29_amd -> 0.15 | D35: =g29_amd_lo&"–"&g29_amd_hi -> 0.05–0.25 | F35: =IF(AND(C35>=g29_amd_lo,C35<=g29_amd_hi),"OK","ERROR") -> OK | G35: 驗證
A36: K5-tpu | B36: 2029 成長率在區間內：Google TPU | C36: =g29_tpu -> 0.15 | D36: =g29_tpu_lo&"–"&g29_tpu_hi -> 0.05–0.25 | F36: =IF(AND(C36>=g29_tpu_lo,C36<=g29_tpu_hi),"OK","ERROR") -> OK | G36: 驗證
A37: K5-trn | B37: 2029 成長率在區間內：AWS Trainium | C37: =g29_trn -> 0.15 | D37: =g29_trn_lo&"–"&g29_trn_hi -> 0.05–0.25 | F37: =IF(AND(C37>=g29_trn_lo,C37<=g29_trn_hi),"OK","ERROR") -> OK | G37: 驗證
A38: K5-oth | B38: 2029 成長率在區間內：其他 ASIC（MTIA、Maia、Ascend 等） | C38: =g29_oth -> 0.15 | D38: =g29_oth_lo&"–"&g29_oth_hi -> 0.05–0.25 | F38: =IF(AND(C38>=g29_oth_lo,C38<=g29_oth_hi),"OK","ERROR") -> OK | G38: 驗證
A39: K6-tpu2026 | B39: Google TPU 2026 設計夥伴份額合計 ≤ 100% | C39: =ShareTbl!D7 -> 0.95 | D39: 1 | F39: =IF(C39<=1+0.000000001,"OK","ERROR") -> OK | G39: 驗證（加總受限）
A40: K6-tpu2027 | B40: Google TPU 2027 設計夥伴份額合計 ≤ 100% | C40: =ShareTbl!E7 -> 0.95 | D40: 1 | F40: =IF(C40<=1+0.000000001,"OK","ERROR") -> OK | G40: 驗證（加總受限）
A41: K6-tpu2028 | B41: Google TPU 2028 設計夥伴份額合計 ≤ 100% | C41: =ShareTbl!F7 -> 0.98 | D41: 1 | F41: =IF(C41<=1+0.000000001,"OK","ERROR") -> OK | G41: 驗證（加總受限）
A42: K6-oth2026 | B42: 其他 ASIC 2026 設計夥伴份額合計 ≤ 100% | C42: =ShareTbl!D13 -> 0.4 | D42: 1 | F42: =IF(C42<=1+0.000000001,"OK","ERROR") -> OK | G42: 驗證（加總受限）
A43: K6-oth2027 | B43: 其他 ASIC 2027 設計夥伴份額合計 ≤ 100% | C43: =ShareTbl!E13 -> 0.61 | D43: 1 | F43: =IF(C43<=1+0.000000001,"OK","ERROR") -> OK | G43: 驗證（加總受限）
A44: K6-oth2028 | B44: 其他 ASIC 2028 設計夥伴份額合計 ≤ 100% | C44: =ShareTbl!F13 -> 0.7 | D44: 1 | F44: =IF(C44<=1+0.000000001,"OK","ERROR") -> OK | G44: 驗證（加總受限）
A45: K6-trnA2026 | B45: AWS Trainium（情境 A） 2026 設計夥伴份額合計 ≤ 100% | C45: =ShareTbl!D18 -> 0.4 | D45: 1 | F45: =IF(C45<=1+0.000000001,"OK","ERROR") -> OK | G45: 驗證（加總受限）
A46: K6-trnA2027 | B46: AWS Trainium（情境 A） 2027 設計夥伴份額合計 ≤ 100% | C46: =ShareTbl!E18 -> 0.65 | D46: 1 | F46: =IF(C46<=1+0.000000001,"OK","ERROR") -> OK | G46: 驗證（加總受限）
A47: K6-trnA2028 | B47: AWS Trainium（情境 A） 2028 設計夥伴份額合計 ≤ 100% | C47: =ShareTbl!F18 -> 0.63 | D47: 1 | F47: =IF(C47<=1+0.000000001,"OK","ERROR") -> OK | G47: 驗證（加總受限）
A48: K6-trnB2026 | B48: AWS Trainium（情境 B） 2026 設計夥伴份額合計 ≤ 100% | C48: =ShareTbl!D23 -> 0.4 | D48: 1 | F48: =IF(C48<=1+0.000000001,"OK","ERROR") -> OK | G48: 驗證（加總受限）
A49: K6-trnB2027 | B49: AWS Trainium（情境 B） 2027 設計夥伴份額合計 ≤ 100% | C49: =ShareTbl!E23 -> 0.6 | D49: 1 | F49: =IF(C49<=1+0.000000001,"OK","ERROR") -> OK | G49: 驗證（加總受限）
A50: K6-trnB2028 | B50: AWS Trainium（情境 B） 2028 設計夥伴份額合計 ≤ 100% | C50: =ShareTbl!F23 -> 0.53 | D50: 1 | F50: =IF(C50<=1+0.000000001,"OK","ERROR") -> OK | G50: 驗證（加總受限）
A51: K6-trnC2026 | B51: AWS Trainium（情境 C） 2026 設計夥伴份額合計 ≤ 100% | C51: =ShareTbl!D28 -> 0.4 | D51: 1 | F51: =IF(C51<=1+0.000000001,"OK","ERROR") -> OK | G51: 驗證（加總受限）
A52: K6-trnC2027 | B52: AWS Trainium（情境 C） 2027 設計夥伴份額合計 ≤ 100% | C52: =ShareTbl!E28 -> 0.5 | D52: 1 | F52: =IF(C52<=1+0.000000001,"OK","ERROR") -> OK | G52: 驗證（加總受限）
A53: K6-trnC2028 | B53: AWS Trainium（情境 C） 2028 設計夥伴份額合計 ≤ 100% | C53: =ShareTbl!F28 -> 0.43 | D53: 1 | F53: =IF(C53<=1+0.000000001,"OK","ERROR") -> OK | G53: 驗證（加總受限）
A54: K6-cpo2027 | B54: CPO 光學（模組與雷射廠） 2027 光學金額份額合計 ≤ 100% | C54: =ShareTbl!D36 -> 0.5 | D54: 1 | F54: =IF(C54<=1+0.000000001,"OK","ERROR") -> OK | G54: 驗證（加總受限）
A55: K6-cpo2028 | B55: CPO 光學（模組與雷射廠） 2028 光學金額份額合計 ≤ 100% | C55: =ShareTbl!E36 -> 0.65 | D55: 1 | F55: =IF(C55<=1+0.000000001,"OK","ERROR") -> OK | G55: 驗證（加總受限）
A56: K6-cpo2029 | B56: CPO 光學（模組與雷射廠） 2029 光學金額份額合計 ≤ 100% | C56: =ShareTbl!F36 -> 0.75 | D56: 1 | F56: =IF(C56<=1+0.000000001,"OK","ERROR") -> OK | G56: 驗證（加總受限）
A57: K6-abfnv2026 | B57: NVIDIA 加速器 ABF 載板 2026 載板份額合計 ≤ 100% | C57: =ShareTbl!D45 -> 0.99 | D57: 1 | F57: =IF(C57<=1+0.000000001,"OK","ERROR") -> OK | G57: 驗證（加總受限）
A58: K6-abfnv2027 | B58: NVIDIA 加速器 ABF 載板 2027 載板份額合計 ≤ 100% | C58: =ShareTbl!E45 -> 0.995 | D58: 1 | F58: =IF(C58<=1+0.000000001,"OK","ERROR") -> OK | G58: 驗證（加總受限）
A59: K6-abfnv2028 | B59: NVIDIA 加速器 ABF 載板 2028 載板份額合計 ≤ 100% | C59: =ShareTbl!F45 -> 0.996 | D59: 1 | F59: =IF(C59<=1+0.000000001,"OK","ERROR") -> OK | G59: 驗證（加總受限）
A60: K6-abfnv2029 | B60: NVIDIA 加速器 ABF 載板 2029 載板份額合計 ≤ 100% | C60: =ShareTbl!G45 -> 0.995 | D60: 1 | F60: =IF(C60<=1+0.000000001,"OK","ERROR") -> OK | G60: 驗證（加總受限）
A61: K6-abfot2026 | B61: 非 NVIDIA 加速器 ABF 載板 2026 載板份額合計 ≤ 100% | C61: =ShareTbl!D52 -> 0.88 | D61: 1 | F61: =IF(C61<=1+0.000000001,"OK","ERROR") -> OK | G61: 驗證（加總受限）
A62: K6-abfot2027 | B62: 非 NVIDIA 加速器 ABF 載板 2027 載板份額合計 ≤ 100% | C62: =ShareTbl!E52 -> 0.895 | D62: 1 | F62: =IF(C62<=1+0.000000001,"OK","ERROR") -> OK | G62: 驗證（加總受限）
A63: K6-abfot2028 | B63: 非 NVIDIA 加速器 ABF 載板 2028 載板份額合計 ≤ 100% | C63: =ShareTbl!F52 -> 0.89 | D63: 1 | F63: =IF(C63<=1+0.000000001,"OK","ERROR") -> OK | G63: 驗證（加總受限）
A64: K6-abfot2029 | B64: 非 NVIDIA 加速器 ABF 載板 2029 載板份額合計 ≤ 100% | C64: =ShareTbl!G52 -> 0.885 | D64: 1 | F64: =IF(C64<=1+0.000000001,"OK","ERROR") -> OK | G64: 驗證（加總受限）
A65: K6-pwrA2026 | B65: AI 電源 2026 台達電＋光寶有效份額合計 ≤ 100%（情境 A） | C65: =ShareTbl!D58 -> 0.75981526 | D65: 1 | F65: =IF(C65<=1+0.000000001,"OK","ERROR") -> OK | G65: 驗證（加總受限）
A66: K6-pwrA2027 | B66: AI 電源 2027 台達電＋光寶有效份額合計 ≤ 100%（情境 A） | C66: =ShareTbl!E58 -> 0.74824599 | D66: 1 | F66: =IF(C66<=1+0.000000001,"OK","ERROR") -> OK | G66: 驗證（加總受限）
A67: K6-pwrA2028 | B67: AI 電源 2028 台達電＋光寶有效份額合計 ≤ 100%（情境 A） | C67: =ShareTbl!F58 -> 0.73667673 | D67: 1 | F67: =IF(C67<=1+0.000000001,"OK","ERROR") -> OK | G67: 驗證（加總受限）
A68: K6-pwrA2029 | B68: AI 電源 2029 台達電＋光寶有效份額合計 ≤ 100%（情境 A） | C68: =ShareTbl!G58 -> 0.71630029 | D68: 1 | F68: =IF(C68<=1+0.000000001,"OK","ERROR") -> OK | G68: 驗證（加總受限）
A69: K6-pwrB2026 | B69: AI 電源 2026 台達電＋光寶有效份額合計 ≤ 100%（情境 B） | C69: =ShareTbl!D63 -> 0.75981526 | D69: 1 | F69: =IF(C69<=1+0.000000001,"OK","ERROR") -> OK | G69: 驗證（加總受限）
A70: K6-pwrB2027 | B70: AI 電源 2027 台達電＋光寶有效份額合計 ≤ 100%（情境 B） | C70: =ShareTbl!E63 -> 0.73063166 | D70: 1 | F70: =IF(C70<=1+0.000000001,"OK","ERROR") -> OK | G70: 驗證（加總受限）
A71: K6-pwrB2028 | B71: AI 電源 2028 台達電＋光寶有效份額合計 ≤ 100%（情境 B） | C71: =ShareTbl!F63 -> 0.70144806 | D71: 1 | F71: =IF(C71<=1+0.000000001,"OK","ERROR") -> OK | G71: 驗證（加總受限）
A72: K6-pwrB2029 | B72: AI 電源 2029 台達電＋光寶有效份額合計 ≤ 100%（情境 B） | C72: =ShareTbl!G63 -> 0.67226446 | D72: 1 | F72: =IF(C72<=1+0.000000001,"OK","ERROR") -> OK | G72: 驗證（加總受限）
A73: K6-pwrC2026 | B73: AI 電源 2026 台達電＋光寶有效份額合計 ≤ 100%（情境 C） | C73: =ShareTbl!D68 -> 0.75981526 | D73: 1 | F73: =IF(C73<=1+0.000000001,"OK","ERROR") -> OK | G73: 驗證（加總受限）
A74: K6-pwrC2027 | B74: AI 電源 2027 台達電＋光寶有效份額合計 ≤ 100%（情境 C） | C74: =ShareTbl!E68 -> 0.70421016 | D74: 1 | F74: =IF(C74<=1+0.000000001,"OK","ERROR") -> OK | G74: 驗證（加總受限）
A75: K6-pwrC2028 | B75: AI 電源 2028 台達電＋光寶有效份額合計 ≤ 100%（情境 C） | C75: =ShareTbl!F68 -> 0.6662194 | D75: 1 | F75: =IF(C75<=1+0.000000001,"OK","ERROR") -> OK | G75: 驗證（加總受限）
A76: K6-pwrC2029 | B76: AI 電源 2029 台達電＋光寶有效份額合計 ≤ 100%（情境 C） | C76: =ShareTbl!G68 -> 0.62822864 | D76: 1 | F76: =IF(C76<=1+0.000000001,"OK","ERROR") -> OK | G76: 驗證（加總受限）
A77: K6-lcA2026 | B77: AI 液冷 2026 奇鋐＋雙鴻＋健策有效份額合計 ≤ 100%（情境 A） | C77: =ShareTbl!D75 -> 0.65762842 | D77: 1 | F77: =IF(C77<=1+0.000000001,"OK","ERROR") -> OK | G77: 驗證（加總受限）
A78: K6-lcA2027 | B78: AI 液冷 2027 奇鋐＋雙鴻＋健策有效份額合計 ≤ 100%（情境 A） | C78: =ShareTbl!E75 -> 0.65561707 | D78: 1 | F78: =IF(C78<=1+0.000000001,"OK","ERROR") -> OK | G78: 驗證（加總受限）
A79: K6-lcA2028 | B79: AI 液冷 2028 奇鋐＋雙鴻＋健策有效份額合計 ≤ 100%（情境 A） | C79: =ShareTbl!F75 -> 0.64567069 | D79: 1 | F79: =IF(C79<=1+0.000000001,"OK","ERROR") -> OK | G79: 驗證（加總受限）
A80: K6-lcA2029 | B80: AI 液冷 2029 奇鋐＋雙鴻＋健策有效份額合計 ≤ 100%（情境 A） | C80: =ShareTbl!G75 -> 0.63572431 | D80: 1 | F80: =IF(C80<=1+0.000000001,"OK","ERROR") -> OK | G80: 驗證（加總受限）
A81: K6-lcB2026 | B81: AI 液冷 2026 奇鋐＋雙鴻＋健策有效份額合計 ≤ 100%（情境 B） | C81: =ShareTbl!D81 -> 0.65762842 | D81: 1 | F81: =IF(C81<=1+0.000000001,"OK","ERROR") -> OK | G81: 驗證（加總受限）
A82: K6-lcB2027 | B82: AI 液冷 2027 奇鋐＋雙鴻＋健策有效份額合計 ≤ 100%（情境 B） | C82: =ShareTbl!E81 -> 0.632747 | D82: 1 | F82: =IF(C82<=1+0.000000001,"OK","ERROR") -> OK | G82: 驗證（加總受限）
A83: K6-lcB2028 | B83: AI 液冷 2028 奇鋐＋雙鴻＋健策有效份額合計 ≤ 100%（情境 B） | C83: =ShareTbl!F81 -> 0.60686558 | D83: 1 | F83: =IF(C83<=1+0.000000001,"OK","ERROR") -> OK | G83: 驗證（加總受限）
A84: K6-lcB2029 | B84: AI 液冷 2029 奇鋐＋雙鴻＋健策有效份額合計 ≤ 100%（情境 B） | C84: =ShareTbl!G81 -> 0.58398415 | D84: 1 | F84: =IF(C84<=1+0.000000001,"OK","ERROR") -> OK | G84: 驗證（加總受限）
A85: K6-lcC2026 | B85: AI 液冷 2026 奇鋐＋雙鴻＋健策有效份額合計 ≤ 100%（情境 C） | C85: =ShareTbl!D87 -> 0.65762842 | D85: 1 | F85: =IF(C85<=1+0.000000001,"OK","ERROR") -> OK | G85: 驗證（加總受限）
A86: K6-lcC2027 | B86: AI 液冷 2027 奇鋐＋雙鴻＋健策有效份額合計 ≤ 100%（情境 C） | C86: =ShareTbl!E87 -> 0.61187692 | D86: 1 | F86: =IF(C86<=1+0.000000001,"OK","ERROR") -> OK | G86: 驗證（加總受限）
A87: K6-lcC2028 | B87: AI 液冷 2028 奇鋐＋雙鴻＋健策有效份額合計 ≤ 100%（情境 C） | C87: =ShareTbl!F87 -> 0.57406046 | D87: 1 | F87: =IF(C87<=1+0.000000001,"OK","ERROR") -> OK | G87: 驗證（加總受限）
A88: K6-lcC2029 | B88: AI 液冷 2029 奇鋐＋雙鴻＋健策有效份額合計 ≤ 100%（情境 C） | C88: =ShareTbl!G87 -> 0.54517904 | D88: 1 | F88: =IF(C88<=1+0.000000001,"OK","ERROR") -> OK | G88: 驗證（加總受限）
A89: K6-asm2026 | B89: AI 伺服器組裝 2026 廣達＋鴻海＋緯創本體＋緯穎有效份額合計 ≤ 100% | C89: =ShareTbl!D107 -> 0.43049334 | D89: 1 | F89: =IF(C89<=1+0.000000001,"OK","ERROR") -> OK | G89: 驗證（加總受限）
A90: K6-asm2027 | B90: AI 伺服器組裝 2027 廣達＋鴻海＋緯創本體＋緯穎有效份額合計 ≤ 100% | C90: =ShareTbl!E107 -> 0.44589911 | D90: 1 | F90: =IF(C90<=1+0.000000001,"OK","ERROR") -> OK | G90: 驗證（加總受限）
A91: K6-asm2028 | B91: AI 伺服器組裝 2028 廣達＋鴻海＋緯創本體＋緯穎有效份額合計 ≤ 100% | C91: =ShareTbl!F107 -> 0.43585516 | D91: 1 | F91: =IF(C91<=1+0.000000001,"OK","ERROR") -> OK | G91: 驗證（加總受限）
A92: K6-asm2029 | B92: AI 伺服器組裝 2029 廣達＋鴻海＋緯創本體＋緯穎有效份額合計 ≤ 100% | C92: =ShareTbl!G107 -> 0.41399492 | D92: 1 | F92: =IF(C92<=1+0.000000001,"OK","ERROR") -> OK | G92: 驗證（加總受限）
A93: K6-hbm2025 | B93: HBM 2025 SK 海力士＋三星＋美光營收份額合計 ≤ 100% | C93: =ShareTbl!D98 -> 0.96 | D93: 1 | F93: =IF(C93<=1+0.000000001,"OK","ERROR") -> OK | G93: 驗證（加總受限）
A94: K6-hbm2026 | B94: HBM 2026 SK 海力士＋三星＋美光營收份額合計 ≤ 100% | C94: =ShareTbl!E98 -> 1 | D94: 1 | F94: =IF(C94<=1+0.000000001,"OK","ERROR") -> OK | G94: 驗證（加總受限）
A95: K6-hbm2027 | B95: HBM 2027 SK 海力士＋三星＋美光營收份額合計 ≤ 100% | C95: =ShareTbl!F98 -> 1 | D95: 1 | F95: =IF(C95<=1+0.000000001,"OK","ERROR") -> OK | G95: 驗證（加總受限）
A96: K6-hbm2028 | B96: HBM 2028 SK 海力士＋三星＋美光營收份額合計 ≤ 100% | C96: =ShareTbl!G98 -> 1 | D96: 1 | F96: =IF(C96<=1+0.000000001,"OK","ERROR") -> OK | G96: 驗證（加總受限）
A97: K6-hbm2029 | B97: HBM 2029 SK 海力士＋三星＋美光營收份額合計 ≤ 100% | C97: =ShareTbl!H98 -> 1 | D97: 1 | F97: =IF(C97<=1+0.000000001,"OK","ERROR") -> OK | G97: 驗證（加總受限）
A98: K8-2026 | B98: 2026 SoC 測試機市場（A）÷ SEMI WFE 在泰瑞達長期區間內（7–9%；CF15） | C98: =Equip!D25 -> 0.079916609 | D98: =TEXT(ts_tw_lo,"0%")&"–"&TEXT(ts_tw_hi,"0%") -> 7%–9% | F98: =IF(AND(C98>=ts_tw_lo,C98<=ts_tw_hi),"OK","WARN") -> OK | G98: 驗證（量級；口徑不同，只列 WARN）
A99: K8-2027 | B99: 2027 SoC 測試機市場（A）÷ SEMI WFE 在泰瑞達長期區間內（7–9%；CF15） | C99: =Equip!E25 -> 0.092605314 | D99: =TEXT(ts_tw_lo,"0%")&"–"&TEXT(ts_tw_hi,"0%") -> 7%–9% | F99: =IF(AND(C99>=ts_tw_lo,C99<=ts_tw_hi),"OK","WARN") -> WARN | G99: 驗證（量級；口徑不同，只列 WARN）
A100: K8-2028 | B100: 2028 SoC 測試機市場（A）÷ SEMI WFE 在泰瑞達長期區間內（7–9%；CF15） | C100: =Equip!F25 -> 0.091223053 | D100: =TEXT(ts_tw_lo,"0%")&"–"&TEXT(ts_tw_hi,"0%") -> 7%–9% | F100: =IF(AND(C100>=ts_tw_lo,C100<=ts_tw_hi),"OK","WARN") -> WARN | G100: 驗證（量級；口徑不同，只列 WARN）
A101: K7 | B101: Rack 頁：商用 GPU 系統市場 2026 ≤ AI IT 資本支出 2026（系統售價不應超過全部 IT 資本支出） | C101: =Rack!C15 -> 595.48611 | D101: =Deploy!C5 -> 781.87292 | F101: =IF(C101<=D101+0.000000001,"OK","ERROR") -> OK | G101: 驗證（量級）
...

Sheet Decisions
A1: Decisions — 決策登錄（Excel 擁有）。判斷類由 Andy 決定；Claude 依預設執行者標『預設、可撤回』
A3: 決策 ID | B3: 類別 | C3: 項目 | D3: 決議 | E3: 日期 | F3: Andy 原話／依據 | G3: 狀態
A4: S1 | B4: 範圍 | C4: 建立產業基準庫 | D4: 本專案建立自己的產業事實庫 Excel，規格比照 Tokenomics（Excel 唯一事實來源、builder 只產生公式頁、輸入由 Excel 擁有、Interface 具名範圍為下游唯一連結點、Checks、Decisions、證據登錄、版本固定快照）；與 TK 相關數據與 TK 一致；為各公司模型的基準事實來源 | E4: 2026-10-25 13:26；2026-10-27 07:59 | F4: 請開始規畫並建置AI半導體的次產業(唯一事實)excel(名稱另取較貼切的)，他的規格如同算力收支專案中的Tokenomics，與TK相關數據要與TK一致，只是負責領域不同，是相關個股模型的基準事實來源。 | G4: 生效
A5: S2 | B5: 命名 | C5: 名稱 | D5: Siliconomics（中文：AI 半導體產業基準庫），與 Tokenomics 對稱：一個管 token 的經濟，一個管矽的經濟。檔名 YYYYMMDD_Siliconomics_vX.Y.xlsx；下游名稱前綴 SIF_（Interface）、SGOV_（治理計數）；Tokenomics 鏡像為 TK_<名稱>_<世代>／SIF_TK_* | E5: 2026-10-27 | F5: 名稱另取較貼切的 | G5: 預設、可撤回
A6: S3 | B6: 工程 | C6: 位置 | D6: repo company-models 的 siliconomics/ 資料夾（model、builder、tools、data、docs），不另開 repo：下游 38 個建檔程式在同一 repo，可直接讀快照、CI 同一條；Tokenomics 是另一 repo 是因為服務跨專案 | E6: 2026-10-27 | F6: （工程類，Claude 決定） | G6: 生效
A7: S4 | B7: 範圍 | C7: 行業變數與公司變數的界線 | D7: 行業變數（本庫）＝跨公司共用或加總受限的量：加速器顆數與每顆內容、各市場規模與價格路徑、技術替代滲透率（CPO、銅轉光、液冷、混合鍵合）、同一市場各供應商份額表（合計 ≤ 100%）、供需缺口、情境 A／B／C 定義。公司變數（各公司模型）＝會計年度錨點、毛利率與費用、資本支出、股數、估值參數、公司特有的份額相對值 | E7: 2026-10-27 | F7: 依據 Andy 2026-10-25 13:13：個股 A／B／C 一律讀同字母行業情境（技術替代屬行業變數） | G7: 預設、可撤回
A8: S5 | B8: 工程 | C8: 下游改接方式 | D8: markets/memory/market.py 改為只讀 Siliconomics 快照（保留原 Python 名稱），38 個下游建檔程式不需修改；驗收＝全部 58 個 CI 目標重建後與 dist 逐格相同。其他市場層與公司模型依子產業分段改接 | E8: 2026-10-27 | F8: （工程類，Claude 決定） | G8: 生效
A9: S6 | B9: 範圍 | C9: 預測期間 | D9: v0.1 維持現有市場層的 2025–2029；2030–2032 的行業路徑不在 v0.1 自訂（目前各公司以收斂法自推），待算力收支 R4 三情境部署路徑（CY2026–2030）上線後由部署路徑推導並延伸到 2032 | E9: 2026-10-27 | F9: 依據 Andy 2026-10-25：預估延長到 FY2032；R4 回執：預計 10-31 後動工 | G9: 預設、可撤回
A10: S7 | B10: 治理 | C10: 衝突處理 | D10: 跨模型同一變數不同值者登錄於 Conflicts 頁；每項給建議單一值（判斷類標待 Andy），在該子產業併入本庫的版本生效；生效前各公司模型維持現值，不另做局部修補 | E10: 2026-10-27 | F10: （工程類流程；個別建議值屬判斷類） | G10: 生效
A11: S8 | B11: 範圍 | C11: v0.2 範圍 | D11: v0.2 只做：(1) In 頁 Assumed 列全部補區間、缺來源列補來源（區間為 Claude 預設，標 Assumed；C 情境季價區間 2027 ±5pt、2028–29 ±10pt）；(2) 2029 平台別顆數成長改為本庫單一來源（CF18）。ASIC 每顆規格、部署 GW、TPU 份額表（CF13、CF14、CF19、CF22）延到 v0.3（運算層一起做），網通與橋接表順延為 v0.4 | E11: 2026-10-27 | F11: （工程類分段；區間值屬判斷類預設） | G11: 預設、可撤回
A12: S9 | B12: 治理 | C12: G2、G3 升為 ERROR | D12: v0.2 起 In 頁缺來源、Assumed／Analogy 缺區間計入 SGOV_Errors（比照 Tokenomics：Analogy 與 Assumed 一律給區間） | E12: 2026-10-27 | F12: （工程類） | G12: 生效
A13: S10 | B13: 工程 | C13: 記憶體公司模型 In 頁不加新節 | D13: market.py 的 inputs() 只重播 M1–M3、ref_inputs() 只重播 M4；M5 起的新節（2029 平台別成長）不寫進記憶體公司模型，由需要的模型經 market.G29、G_U29 取用，避免既有儲存格位移 | E13: 2026-10-27 | F13: （工程類） | G13: 生效
A14: S11 | B14: 範圍 | C14: v0.3 範圍 | D14: v0.3（運算層第一段）：(1) 加速器每顆售價（nvidia pa_*）、ASIC 核心價與 HBM 代購比例（avgo core_*、f_hbm）移入 In 頁 M6；(2) ASIC 設計服務份額（Broadcom、Marvell、聯發科、世芯）移入 M7，新增 ShareTbl 頁與加總檢查 K6。原模型改讀本庫，數值與文字逐字搬入（下游應不變）。部署 GW 單一路徑（CF22）依賴網通市場層，與網通一起在 v0.4 做 | E14: 2026-10-27 | F14: （工程類） | G14: 生效
... A33: S30 | B33: 輸入 | C33: v0.10：NAND 季價 2026Q3 nq_6 0.15 → 0.25、2026Q4 nq_7 0.175 → +8.1%（兩季累計不變） | D33: NAND 第四季對帳：SanDisk、Kioxia 模型 2026Q4 營收比公司指引高 9.6%／21.5%。拆解：市場層把 TrendForce 合約價當成實現售價；2026Q3 實現售價（Kioxia、SK 海力士皆 mid-20%）高於合約價輸入 15%，使兩家 2026Q3 份額被高估約 8%，第四季再乘合約價 +17.5%。修正：2026Q3 改實現 +25%（Verified）；2026Q4 取兩季累計 1.15×1.175 不變的餘額 +8.1%（Derived），2027 起價格水準不變。另在 markets/nand v0.3 把兩家 2026Q4 起的份額改為 2026Q3 實績與 2026Q4 指引的平均（平滑 Kioxia 揭露的出貨季別移動）。結果：SanDisk 差距 +9.6% → +0.4%；Kioxia（日圓）+21.5% → +6.8%（餘差＝匯率假設 160 對 157 約 +1.9%，其餘為同一會計年度內的季別移動與產品組合）。區間：低＝Kioxia 實現兩季累計（2027 起水準約 −4.5%）、高＝合約價 +17.5%。 | E33: 2026-10-31 | F33: Andy 2026-10-31「NAND 第四季差距查證……做法比照 SoC 測試機那次，先拆解原因，屬於模型或市場層的錯誤才修正」 | G33: 預設、可撤回

Sheet DB_Evidence
A1: DB_Evidence — 證據登錄（所有比對過的新資訊，含不採納者）；先與本庫現值比對，再判定採納／部分採納／不採納／待查
A3: ID | B3: 日期 | C3: 主張（摘要） | D3: 來源 | E3: 標記 | F3: 對應鍵 | G3: 本庫當時值 | H3: 新資訊值 | I3: 判定 | J3: 處理版本 | K3: 立場 | L3: 備註
A4: （v0.1 尚無；跨模型衝突先登錄於 Conflicts 頁，判定後再轉入本頁）
