Workbook

Sheet README
A1: 台積電模型 v0.2.2（AI 半導體 Project 步驟 4） 2026-10-25 2026 年改為 1–3Q 實績＋4Q 指引中點；2027 起假設未變
A2: 模型命題：台積電在 AI 算力中的意義是供給上限而非分到的金額比例——AI 加速器只占其營收約兩成；2027 年加速器出貨受 HBM 而非 CoWoS 限制，台積電的獲利成長由「AI 顆數 × 每顆內容 × 漲價」與「非 AI 八成的穩定成長」共同決定。
A4: 驅動因子 → 推導量
A5: CoWoS：加速器顆數（markets/memory）÷ 每片封裝數 → CoWoS 需求；月產能年均 × 12 × (1＋委外) → 可用產能；需求 ÷ 產能 → 是否為瓶頸；與 HBM 缺口比較
A6: PL：顆數 × 每顆台積電內容（橋接表）× 價格調升 × (1＋其他 AI) → AI 營收；非 AI 前一年 × (1＋成長)；× 毛利率 − 營業費用 → 營業利益 → 淨利 → EPS
A7: 情境：A 基準；B 2028 顆數 −20%、毛利率降至 58%；C 2028 顆數 −40%、毛利率 54%（AI 資本支出明顯下修）
A8: Val：EPS × P/E（15x、10 年中位 20.5x、10 年最高 32.7x）
A9: Recon、Sens：見各頁
A11: 標記：Verified、Interested-party、Analogy、Assumed、Derived。SemiAnalysis 未使用。
A12: v0.2.1 變更（2026-10-23）：Val 頁新增「十年倍數與規則值」區塊（十年 P/E 歷史、分位、規則值與隱含股價；原放在 markets/overview/extract.py），總覽與 HTML 展示層改讀此處；損益、EPS 與原有儲存格不變。
A13: v0.2 變更（2026-10-22，3Q26 財報後）：2026 營收 172→176.1 $B（1–3Q 實績＋4Q 指引中點 53.3）；毛利率 66.0%→66.5%（四季加權）；EPS 114.2→112.1（新舊對照見 tsmc/README.md）。新增 2026 專屬參數 opex_26、ni_op_26、fx_26（來自實績）；2027 起淨利÷營業利益由 0.92 改為推導值（NI_OI 頁；區間 0.864–0.909）；毛利率、價格調升、非 AI 成長、CoWoS 產能全部未改（公司未給新的明確指引）。
A14: 公司 3Q26 說法未取得：AI 加速器營收占比、CoWoS 產能的新數字（搜尋未找到逐字稿原文），故 CoWoS 頁不動。
... A16: v0.2.2（2026-10-25）：Val 頁新增「0. 目標價與上檔空間」（放在 Val 既有內容之後，不位移既有儲存格）與 In 頁目標價情境權重 tp_wA／tp_wB／tp_wC（0.3／0.5／0.2，Assumed）。各情境隱含價＝十年 P/E 中位數（規則值：2027 中段）× 各情境 2027 EPS；其餘儲存格不變。

Sheet In
A1: In — 輸入（藍字；基準欄 E）。金額：十億美元；台積電內容：千美元／顆；CoWoS：千片
A3: 鍵 | B3: 項目 | C3: 單位 | D3: 低 | E3: 基準 | F3: 高 | G3: 標記 | H3: 來源／說明
A4: A. 加速器顆數（markets/memory，與 HBM、網通同一份）
A5: u_bw_26 | B5: NVIDIA Blackwell（B200／B300） 顆數 2026 | C5: 百萬顆 | E5: 5.4 | G5: Interested-party | H5: markets/memory：顆數：Morgan Stanley 2026-07（2026 5.4M）；AC Research 2027 約 2.4M；2028 Assumed。GB：B200 186、B300 288 組合 [Derived]
A6: u_bw_27 | B6: NVIDIA Blackwell（B200／B300） 顆數 2027 | C6: 百萬顆 | E6: 2.4 | G6: Interested-party | H6: 同上
A7: u_bw_28 | B7: NVIDIA Blackwell（B200／B300） 顆數 2028 | C7: 百萬顆 | E7: 0.5 | G7: Interested-party | H7: 同上
A8: g29_bw | B8: NVIDIA Blackwell（B200／B300） 2029 顆數成長 | C8: % | E8: -0.5 | G8: Assumed
A9: u_rb_26 | B9: NVIDIA Rubin 顆數 2026 | C9: 百萬顆 | E9: 1.7 | G9: Interested-party | H9: markets/memory：2026：TrendForce 組合 Rubin 22% × 約 7.6M [Derived]；2027：Morgan Stanley 約 7.0M；2028 Assumed
A10: u_rb_27 | B10: NVIDIA Rubin 顆數 2027 | C10: 百萬顆 | E10: 7 | G10: Interested-party | H10: 同上
A11: u_rb_28 | B11: NVIDIA Rubin 顆數 2028 | C11: 百萬顆 | E11: 7 | G11: Interested-party | H11: 同上
A12: g29_rb | B12: NVIDIA Rubin 2029 顆數成長 | C12: % | E12: 0.15 | G12: Assumed
A13: u_ru_26 | B13: NVIDIA Rubin Ultra 顆數 2026 | C13: 百萬顆 | E13: 0 | G13: Assumed | H13: markets/memory：時程 Assumed；GB：NVIDIA 1 TB／封裝
A14: u_ru_27 | B14: NVIDIA Rubin Ultra 顆數 2027 | C14: 百萬顆 | E14: 0.3 | G14: Assumed | H14: 同上
A15: u_ru_28 | B15: NVIDIA Rubin Ultra 顆數 2028 | C15: 百萬顆 | E15: 2 | G15: Assumed | H15: 同上
A16: g29_ru | B16: NVIDIA Rubin Ultra 2029 顆數成長 | C16: % | E16: 0.15 | G16: Assumed
A17: u_hp_26 | B17: NVIDIA Hopper（H200 等） 顆數 2026 | C17: 百萬顆 | E17: 0.5 | G17: Interested-party | H17: markets/memory：TrendForce 2026 組合 Hopper 7%
A18: u_hp_27 | B18: NVIDIA Hopper（H200 等） 顆數 2027 | C18: 百萬顆 | E18: 0 | G18: Interested-party | H18: 同上
A19: u_hp_28 | B19: NVIDIA Hopper（H200 等） 顆數 2028 | C19: 百萬顆 | E19: 0 | G19: Interested-party | H19: 同上
A20: g29_hp | B20: NVIDIA Hopper（H200 等） 2029 顆數成長 | C20: % | E20: 0 | G20: Assumed
A21: u_amd_26 | B21: AMD Instinct 顆數 2026 | C21: 百萬顆 | E21: 0.75 | G21: Interested-party／Assumed | H21: markets/memory：2027：Morgan Stanley MI455X 1.0M＋MI450 0.5M；其餘 Assumed
A22: u_amd_27 | B22: AMD Instinct 顆數 2027 | C22: 百萬顆 | E22: 1.5 | G22: Interested-party／Assumed | H22: 同上
A23: u_amd_28 | B23: AMD Instinct 顆數 2028 | C23: 百萬顆 | E23: 2 | G23: Interested-party／Assumed | H23: 同上
A24: g29_amd | B24: AMD Instinct 2029 顆數成長 | C24: % | E24: 0.15 | G24: Assumed
A25: u_tpu_26 | B25: Google TPU 顆數 2026 | C25: 百萬顆 | E25: 3.85 | G25: Interested-party | H25: markets/memory：MS 3.2／5.0、GF 4.5／8.84（2026／2027）取中間偏 MS；2028 Assumed
A26: u_tpu_27 | B26: Google TPU 顆數 2027 | C26: 百萬顆 | E26: 5.5 | G26: Interested-party | H26: 同上
A27: u_tpu_28 | B27: Google TPU 顆數 2028 | C27: 百萬顆 | E27: 7 | G27: Interested-party | H27: 同上
A28: g29_tpu | B28: Google TPU 2029 顆數成長 | C28: % | E28: 0.15 | G28: Assumed
A29: u_trn_26 | B29: AWS Trainium 顆數 2026 | C29: 百萬顆 | E29: 2 | G29: Assumed | H29: markets/memory：年出貨未找到；GB：Trn2 96、Trn3 144
A30: u_trn_27 | B30: AWS Trainium 顆數 2027 | C30: 百萬顆 | E30: 2.5 | G30: Assumed | H30: 同上
A31: u_trn_28 | B31: AWS Trainium 顆數 2028 | C31: 百萬顆 | E31: 3 | G31: Assumed | H31: 同上
A32: g29_trn | B32: AWS Trainium 2029 顆數成長 | C32: % | E32: 0.15 | G32: Assumed
A33: u_oth_26 | B33: 其他 ASIC（MTIA、Maia、Ascend 等） 顆數 2026 | C33: 百萬顆 | E33: 1 | G33: Derived／Assumed | H33: markets/memory：2027：JPMorgan ASIC 12.5M − TPU − Trainium
A34: u_oth_27 | B34: 其他 ASIC（MTIA、Maia、Ascend 等） 顆數 2027 | C34: 百萬顆 | E34: 4.5 | G34: Derived／Assumed | H34: 同上
A35: u_oth_28 | B35: 其他 ASIC（MTIA、Maia、Ascend 等） 顆數 2028 | C35: 百萬顆 | E35: 5 | G35: Derived／Assumed | H35: 同上
A36: g29_oth | B36: 其他 ASIC（MTIA、Maia、Ascend 等） 2029 顆數成長 | C36: % | E36: 0.15 | G36: Assumed
A37: um28_A | B37: 情境 A：2028 顆數 ÷ 基準 | C37: x | E37: 1 | G37: Assumed | H37: A＝基準；B＝AI 資本支出消化；C＝明顯下修
A38: um29_A | B38: 情境 A：2029 顆數 ÷ 基準 | C38: x | E38: 1 | G38: Assumed
A39: um28_B | B39: 情境 B：2028 顆數 ÷ 基準 | C39: x | E39: 0.8 | G39: Assumed
A40: um29_B | B40: 情境 B：2029 顆數 ÷ 基準 | C40: x | E40: 0.85 | G40: Assumed
A41: um28_C | B41: 情境 C：2028 顆數 ÷ 基準 | C41: x | E41: 0.6 | G41: Assumed
A42: um29_C | B42: 情境 C：2029 顆數 ÷ 基準 | C42: x | E42: 0.6 | G42: Assumed
A43: B. 每片 CoWoS 晶圓封裝數、每顆台積電內容
A44: pp_GB | B44: GB：每片 CoWoS 封裝數 | C44: 顆／片 | D44: 11.2 | E44: 14 | F44: 16.8 | G44: Derived | H44: 每片封裝數：36Kr 2026 NVIDIA 約 66 萬片 ÷ NVIDIA 約 7.6M 顆 ≈ 11.5（組合）；台積電內容：橋接表 v0.2（台積電內容與 v0.1 相同）（Silicon Analysts、Epoch：邏輯＋CoWoS 約 $1.9K，B300 封裝溢價）
A45: ct_GB | B45: GB：每顆台積電內容（邏輯晶圓＋CoWoS） | C45: $K／顆 | D45: 1.84 | E45: 2.3 | F45: 2.76 | G45: Derived | H45: 同上
A46: pp_VR | B46: VR：每片 CoWoS 封裝數 | C46: 顆／片 | D46: 6.4 | E46: 8 | F46: 9.6 | G46: Derived | H46: Morgan Stanley 2027 NVIDIA 122.2 萬片 ÷ 約 9.7M 顆 ≈ 7.9（組合）；內容：橋接表 v0.2（台積電內容與 v0.1 相同）
A47: ct_VR | B47: VR：每顆台積電內容（邏輯晶圓＋CoWoS） | C47: $K／顆 | D47: 2.24 | E47: 2.8 | F47: 3.36 | G47: Derived | H47: 同上
A48: pp_RU | B48: RU：每片 CoWoS 封裝數 | C48: 顆／片 | D48: 3.2 | E48: 4 | F48: 4.8 | G48: Assumed | H48: 4 顆光罩尺寸晶粒＋16 疊 HBM4E
A49: ct_RU | B49: RU：每顆台積電內容（邏輯晶圓＋CoWoS） | C49: $K／顆 | D49: 4.8 | E49: 6 | F49: 7.2 | G49: Assumed | H49: 同上
A50: pp_HP | B50: HP：每片 CoWoS 封裝數 | C50: 顆／片 | D50: 23.2 | E50: 29 | F50: 34.8 | G50: Analogy | H50: CoWoS-S 單晶粒；Silicon Analysts H100 邏輯 $300＋封裝 $750
A51: ct_HP | B51: HP：每顆台積電內容（邏輯晶圓＋CoWoS） | C51: $K／顆 | D51: 0.88 | E51: 1.1 | F51: 1.32 | G51: Analogy | H51: 同上
A52: pp_AMD8 | B52: AMD8：每片 CoWoS 封裝數 | C52: 顆／片 | D52: 6.8 | E52: 8.5 | F52: 10.2 | G52: Derived／Analogy | H52: 36Kr 2026 AMD 約 9 萬片 ÷ 約 0.75M 顆
A53: ct_AMD8 | B53: AMD8：每顆台積電內容（邏輯晶圓＋CoWoS） | C53: $K／顆 | D53: 1.6 | E53: 2 | F53: 2.4 | G53: Derived／Analogy | H53: 同上
A54: pp_AMDR | B54: AMDR：每片 CoWoS 封裝數 | C54: 顆／片 | D54: 4.8 | E54: 6 | F54: 7.2 | G54: Assumed | H54: MI455X 12 疊 HBM4
A55: ct_AMDR | B55: AMDR：每顆台積電內容（邏輯晶圓＋CoWoS） | C55: $K／顆 | D55: 2.4 | E55: 3 | F55: 3.6 | G55: Assumed | H55: 同上
... A61: ct_TRN | B61: TRN：每顆台積電內容（邏輯晶圓＋CoWoS） | C61: $K／顆 | D61: 0.96 | E61: 1.2 | F61: 1.44 | G61: Derived／Assumed | H61: 同上
A62: pp_ASIC | B62: ASIC：每片 CoWoS 封裝數 | C62: 顆／片 | D62: 16 | E62: 20 | F62: 24 | G62: Assumed
A63: ct_ASIC | B63: ASIC：每顆台積電內容（邏輯晶圓＋CoWoS） | C63: $K／顆 | D63: 0.96 | E63: 1.2 | F63: 1.44 | G63: Assumed | H63: 同上
A64: cow_oth26 | B64: 其他 CoWoS 用途 2026（網通 ASIC、FPGA、中國 AI 晶片等） | C64: 千片 | E64: 150 | G64: Assumed | H64: MS 全球需求 139.4 萬片 − 本表加速器
A65: cow_oth_g | B65: 其他 CoWoS 用途年增 | C65: % | E65: 0.25 | G65: Assumed
A66: C. CoWoS 產能（台積電，月產能年底值，千片）
A67: cap_end25 | B67: CoWoS 月產能 2025 年底 | C67: 千片／月 | E67: 77.5 | G67: Interested-party | H67: TrendForce（工商時報）2025-12：7.5–8 萬
A68: cap_end26 | B68: CoWoS 月產能 2026 年底 | C68: 千片／月 | E68: 130 | G68: Interested-party | H68: TrendForce 12–14 萬；Morgan Stanley 約 13 萬
A69: cap_end27 | B69: CoWoS 月產能 2027 年底 | C69: 千片／月 | E69: 200 | G69: Interested-party | H69: Morgan Stanley 20 萬；KGI 17 萬
A70: cap_end28 | B70: CoWoS 月產能 2028 年底 | C70: 千片／月 | E70: 260 | G70: Interested-party | H70: Morgan Stanley 26 萬
A71: cap_end29 | B71: CoWoS 月產能 2029 年底 | C71: 千片／月 | E71: 320 | G71: Assumed | H71: Assumed
A72: osat | B72: 委外封測（日月光、艾克爾）補充產能 ÷ 台積電 | C72: % | D72: 0.05 | E72: 0.1 | F72: 0.2 | G72: Assumed | H72: 日月光 CoWoP 等
A73: ms_dem26 | B73: Morgan Stanley 全球 CoWoS 需求 2026 | C73: 千片 | E73: 1394 | G73: Interested-party | H73: Morgan Stanley 2026-07
A74: ms_dem27 | B74: Morgan Stanley 全球 CoWoS 需求 2027 | C74: 千片 | E74: 2509 | G74: Interested-party | H74: Morgan Stanley 2026-09（2.694M 為較早版本）
A75: hbm_gap27 | B75: HBM 2027 需求缺口 ÷ 供給（markets/memory） | C75: % | E75: 0.21 | G75: Derived | H75: markets/memory Mkt：需求 7.10 EB vs 供給 5.86 EB
A76: D. 台積電營收
A77: fx | B77: 美元兌新台幣（2027 起） | C77: NT$/US$ | D77: 30 | E77: 32 | F77: 33 | G77: Assumed | H77: v0.1.1 標 Verified（當時 Q3 指引匯率）；4Q26 指引匯率為 31.8，2027 起未獲公司指引，數值不變
A78: rev25 | B78: 營收 2025 | C78: $B | E78: 122.43 | G78: Verified | H78: 四季加總
A79: rev26_1q | B79: 營收 1Q26 | C79: $B | E79: 35.9 | G79: Verified | H79: 公司：1Q26 新聞稿；NT$1,134.10B
A80: rev26_2q | B80: 營收 2Q26 | C80: $B | E80: 40.2 | G80: Verified | H80: 公司：2Q26 新聞稿；NT$1,270.38B
A81: rev26_3q | B81: 營收 3Q26 | C81: $B | E81: 46.72 | G81: Verified | H81: 公司：3Q26 新聞稿 pr.tsmc.com/english/news/3346（6-K a3q26e）｜媒體：見 Sources 頁｜NT$1,494.24B；多數媒體 46.7（個別媒體 46.13、46.87 與公司數不符，不採）
A82: rev26_4q | B82: 營收 4Q26（指引低／中／高） | C82: $B | D82: 52.3 | E82: 53.3 | F82: 54.3 | G82: Interested-party | H82: 公司 4Q26 指引 US$52.3–54.3B（匯率 31.8）｜媒體：BigGo、民視財經；中點為本模型取值，公司歷來常高於指引上緣
A83: fx26_4q | B83: 4Q26 指引匯率 | C83: NT$/US$ | E83: 31.8 | G83: Interested-party | H83: 公司 4Q26 指引假設
A84: ntd26_1q | B84: 營收 1Q26（新台幣） | C84: NT$B | E84: 1134.1 | G84: Verified | H84: 公司：1Q26 新聞稿
A85: ntd26_2q | B85: 營收 2Q26（新台幣） | C85: NT$B | E85: 1270.38 | G85: Verified | H85: 公司：2Q26 新聞稿
A86: ntd26_3q | B86: 營收 3Q26（新台幣） | C86: NT$B | E86: 1494.24 | G86: Verified | H86: 公司：3Q26 新聞稿 pr.tsmc.com/english/news/3346（6-K a3q26e）｜媒體：見 Sources 頁
A87: ntd26_4q | B87: 營收 4Q26（新台幣；指引美元 × 指引匯率） | C87: NT$B | D87: =rev26_4q_lo*fx26_4q -> 1663.14 | E87: =rev26_4q*fx26_4q -> 1694.94 | F87: =rev26_4q_hi*fx26_4q -> 1726.74 | G87: Derived
A88: gm26_1q | B88: 毛利率 1Q26 | C88: % | E88: 0.662 | G88: Verified | H88: 公司：1Q26 新聞稿
A89: gm26_2q | B89: 毛利率 2Q26 | C89: % | E89: 0.677 | G89: Verified | H89: 公司：2Q26 新聞稿
A90: gm26_3q | B90: 毛利率 3Q26 | C90: % | E90: 0.664 | G90: Verified | H90: 公司：3Q26 新聞稿 pr.tsmc.com/english/news/3346（6-K a3q26e）｜媒體：見 Sources 頁｜2Q26 的 67.7% 下滑 1.3 個百分點，公司歸因 2 奈米初期爬坡稀釋
A91: gm26_4q | B91: 毛利率 4Q26（指引低／中／高） | C91: % | D91: 0.65 | E91: 0.66 | F91: 0.67 | G91: Interested-party | H91: 公司 4Q26 指引 65–67%｜媒體：民視財經（中值 66%）
A92: opm26_1q | B92: 營業利益率 1Q26 | C92: % | E92: 0.581 | G92: Verified | H92: 公司：1Q26 新聞稿
A93: opm26_2q | B93: 營業利益率 2Q26 | C93: % | E93: 0.603 | G93: Verified | H93: 公司：2Q26 新聞稿
A94: opm26_3q | B94: 營業利益率 3Q26 | C94: % | E94: 0.587 | G94: Verified | H94: 公司：3Q26 新聞稿 pr.tsmc.com/english/news/3346（6-K a3q26e）｜媒體：見 Sources 頁
A95: opm26_4q | B95: 營業利益率 4Q26（指引低／中／高） | C95: % | D95: 0.565 | E95: 0.575 | F95: 0.585 | G95: Interested-party | H95: 公司 4Q26 指引 56.5–58.5%｜媒體：BigGo
A96: ni26_1q | B96: 淨利 1Q26 | C96: NT$B | E96: 572.48 | G96: Verified | H96: 公司：1Q26 新聞稿（EPS NT$22.08）
A97: ni26_2q | B97: 淨利 2Q26 | C97: NT$B | E97: 706.56 | G97: Verified | H97: 公司：2Q26 新聞稿（EPS NT$27.25）
A98: ni26_3q | B98: 淨利 3Q26 | C98: NT$B | E98: 763.06 | G98: Verified | H98: 公司：3Q26 新聞稿 pr.tsmc.com/english/news/3346（6-K a3q26e）｜媒體：見 Sources 頁（EPS NT$29.43）
A99: eps26_1to3q | B99: EPS 1–3Q26 實績合計 | C99: NT$ | E99: =22.08+27.25+29.43 -> 78.76 | G99: Verified | H99: 公司：各季新聞稿 22.08、27.25、29.43
A100: hpc_3q | B100: HPC 占營收 3Q26（備忘，未進入公式） | C100: % | E100: 0.68 | G100: Verified | H100: 公司：3Q26 簡報／逐字稿，2Q26 為 66%｜媒體：vestedfinance、Quest Review
A101: g26_guid | B101: 公司 2026 全年美元營收成長指引 | C101: % | E101: 0.44 | G101: Interested-party | H101: 公司：由「略高於 40%」上修至約 44%｜媒體：StockFeel、民視財經；僅作 Recon 對照，不驅動營收
A102: rev26 | B102: 營收 2026（1–3Q 實績＋4Q 指引中點；低／高＝4Q 指引下／上緣） | C102: $B | D102: =rev26_1q+rev26_2q+rev26_3q+rev26_4q_lo -> 175.12 | E102: =rev26_1q+rev26_2q+rev26_3q+rev26_4q -> 176.12 | F102: =rev26_1q+rev26_2q+rev26_3q+rev26_4q_hi -> 177.12 | G102: Derived | H102: v0.1.1 為 172（全年指引「略高於 40%」推算）
A103: ntd26 | B103: 營收 2026（新台幣） | C103: NT$B | E103: =ntd26_1q+ntd26_2q+ntd26_3q+ntd26_4q -> 5593.66 | G103: Derived
A104: fx_26 | B104: 2026 平均匯率（新台幣營收 ÷ 美元營收） | C104: NT$/US$ | E104: =ntd26/rev26 -> 31.760504 | G104: Derived | H104: 僅用於 2026 EPS；2027 起用 fx
A105: ai_oth | B105: 其他 AI 相關 ÷ 加速器內容（網通 ASIC、HBM 基底晶粒、CPU） | C105: % | D105: 0 | E105: 0.2 | F105: 0.4 | G105: Assumed | H105: 使 2026 AI 營收約等於台積電口徑推算（2025 十幾%後段 × CAGR 約 57%）
A106: px27 | B106: AI 內容價格調升 2027 | C106: % | E106: 0.12 | G106: Interested-party／Derived | H106: 2027 先進製程 +5–10%（Nikkei、MS）、CoWoS 混合單價 +23%（JPMorgan）
...

Sheet CoWoS
A1: CoWoS — 需求（加速器顆數 ÷ 每片封裝數＋其他用途）vs 產能（台積電月產能年均 × 12 × (1＋委外)）；千片。2028–29 用情境 A 顆數
A3: 項目 | B3: 2026 | C3: 2027 | D3: 2028 | E3: 2029 | F3: 說明
A4: NVIDIA Blackwell（B200／B300） | B4: =u_bw_26/pp_GB*1000 -> 385.71429 | C4: =u_bw_27/pp_GB*1000 -> 171.42857 | D4: =u_bw_28*um28_A/pp_GB*1000 -> 35.714286 | E4: =u_bw_28*(1+g29_bw)*um29_A/pp_GB*1000 -> 17.857143
A5: NVIDIA Rubin | B5: =u_rb_26/pp_VR*1000 -> 212.5 | C5: =u_rb_27/pp_VR*1000 -> 875 | D5: =u_rb_28*um28_A/pp_VR*1000 -> 875 | E5: =u_rb_28*(1+g29_rb)*um29_A/pp_VR*1000 -> 1006.25
A6: NVIDIA Rubin Ultra | B6: =u_ru_26/pp_RU*1000 -> 0 | C6: =u_ru_27/pp_RU*1000 -> 75 | D6: =u_ru_28*um28_A/pp_RU*1000 -> 500 | E6: =u_ru_28*(1+g29_ru)*um29_A/pp_RU*1000 -> 575
A7: NVIDIA Hopper（H200 等） | B7: =u_hp_26/pp_HP*1000 -> 17.241379 | C7: =u_hp_27/pp_HP*1000 -> 0 | D7: =u_hp_28*um28_A/pp_HP*1000 -> 0 | E7: =u_hp_28*(1+g29_hp)*um29_A/pp_HP*1000 -> 0
A8: AMD Instinct | B8: =u_amd_26/pp_AMD8*1000 -> 88.235294 | C8: =u_amd_27/pp_AMDR*1000 -> 250 | D8: =u_amd_28*um28_A/pp_AMDR*1000 -> 333.33333 | E8: =u_amd_28*(1+g29_amd)*um29_A/pp_AMDR*1000 -> 383.33333
A9: Google TPU | B9: =u_tpu_26/pp_TPU7*1000 -> 137.5 | C9: =u_tpu_27/pp_TPU8*1000 -> 229.16667 | D9: =u_tpu_28*um28_A/pp_TPU8*1000 -> 291.66667 | E9: =u_tpu_28*(1+g29_tpu)*um29_A/pp_TPU8*1000 -> 335.41667
A10: AWS Trainium | B10: =u_trn_26/pp_TRN*1000 -> 66.666667 | C10: =u_trn_27/pp_TRN*1000 -> 83.333333 | D10: =u_trn_28*um28_A/pp_TRN*1000 -> 100 | E10: =u_trn_28*(1+g29_trn)*um29_A/pp_TRN*1000 -> 115
A11: 其他 ASIC（MTIA、Maia、Ascend 等） | B11: =u_oth_26/pp_ASIC*1000 -> 50 | C11: =u_oth_27/pp_ASIC*1000 -> 225 | D11: =u_oth_28*um28_A/pp_ASIC*1000 -> 250 | E11: =u_oth_28*(1+g29_oth)*um29_A/pp_ASIC*1000 -> 287.5
A12: 其他 CoWoS 用途 | B12: =cow_oth26 -> 150 | C12: =B12*(1+cow_oth_g) -> 187.5 | D12: =C12*(1+cow_oth_g) -> 234.375 | E12: =D12*(1+cow_oth_g) -> 292.96875
A13: 需求合計 | B13: =SUM(B4:B12) -> 1107.8576 | C13: =SUM(C4:C12) -> 2096.4286 | D13: =SUM(D4:D12) -> 2620.0893 | E13: =SUM(E4:E12) -> 3013.3259
A14: 其中 NVIDIA | B14: =B4+B5+B6+B7 -> 615.45567 | C14: =C4+C5+C6+C7 -> 1121.4286 | D14: =D4+D5+D6+D7 -> 1410.7143 | E14: =E4+E5+E6+E7 -> 1599.1071
A15: 台積電產能（月產能年均 × 12） | B15: =(cap_end25+cap_end26)/2*12 -> 1245 | C15: =(cap_end26+cap_end27)/2*12 -> 1980 | D15: =(cap_end27+cap_end28)/2*12 -> 2760 | E15: =(cap_end28+cap_end29)/2*12 -> 3480
A16: 可用產能（含委外） | B16: =B15*(1+osat) -> 1369.5 | C16: =C15*(1+osat) -> 2178 | D16: =D15*(1+osat) -> 3036 | E16: =E15*(1+osat) -> 3828
A17: 需求 ÷ 可用產能 | B17: =B13/B16 -> 0.80895044 | C17: =C13/C16 -> 0.96254755 | D17: =D13/D16 -> 0.86300701 | E17: =E13/E16 -> 0.78718022 | F17: >100%＝CoWoS 為瓶頸
A18: 對照：HBM 需求缺口 ÷ 供給（2027） | C18: =hbm_gap27 -> 0.21 | F18: markets/memory；與上一列比，數字大者為較緊的瓶頸
A19: 對照：Morgan Stanley 全球需求 | B19: =ms_dem26 -> 1394 | C19: =ms_dem27 -> 2509
A20: 本模型 ÷ MS | B20: =B13/B19-1 -> -0.20526713 | C20: =C13/C19-1 -> -0.1644366
A21: NVIDIA：本模型 vs 36Kr 66 萬片（2026）、MS 122.2 萬片（2027） | B21: =B14/660-1 -> -0.067491417 | C21: =C14/1222-1 -> -0.082300678

Sheet PL
A1: PL — 台積電損益（十億美元；EPS 新台幣）。AI 營收＝Σ 顆數 × 每顆內容 × 價格調升 × (1＋其他 AI)；非 AI＝前一年 × (1＋成長)
A3: 項目 | B3: 2026 | C3: 2027 A | D3: 2028 A | E3: 2029 A | F3: 2027 B | G3: 2028 B | H3: 2029 B | I3: 2027 C | J3: 2028 C | K3: 2029 C
A4: AI 加速器內容（Σ 顆數 × 每顆內容 × 價格） | B4: =(u_bw_26*ct_GB+u_rb_26*ct_VR+u_ru_26*ct_RU+u_hp_26*ct_HP+u_amd_26*ct_AMD8+u_tpu_26*ct_TPU7+u_trn_26*ct_TRN+u_oth_26*ct_ASIC)*1 -> 28.605 | C4: =(u_bw_27*ct_GB+u_rb_27*ct_VR+u_ru_27*ct_RU+u_hp_27*ct_HP+u_amd_27*ct_AMDR+u_tpu_27*ct_TPU8+u_trn_27*ct_TRN+u_oth_27*ct_ASIC)*(1+px27) -> 55.6864 | D4: =(u_bw_28*um28_A*ct_GB+u_rb_28*um28_A*ct_VR+u_ru_28*um28_A*ct_RU+u_hp_28*um28_A*ct_HP+u_amd_28*um28_A*ct_AMDR+u_tpu_28*um28_A*ct_TPU8+u_trn_28*um28_A*ct_TRN+u_oth_28*um28_A*ct_ASIC)*(1+px27)*(1+px28) -> 73.72512 | E4: =(u_bw_28*(1+g29_bw)*um29_A*ct_GB+u_rb_28*(1+g29_rb)*um29_A*ct_VR+u_ru_28*(1+g29_ru)*um29_A*ct_RU+u_hp_28*(1+g29_hp)*um29_A*ct_HP+u_amd_28*(1+g29_amd)*um29_A*ct_AMDR+u_tpu_28*(1+g29_tpu)*um29_A*ct_TPU8+u_trn_28*(1+g29_trn)*um29_A*ct_TRN+u_oth_28*(1+g29_oth)*um29_A*ct_ASIC)*(1+px27)*(1+px28)*(1+px29) -> 88.073698 | F4: =(u_bw_27*ct_GB+u_rb_27*ct_VR+u_ru_27*ct_RU+u_hp_27*ct_HP+u_amd_27*ct_AMDR+u_tpu_27*ct_TPU8+u_trn_27*ct_TRN+u_oth_27*ct_ASIC)*(1+px27) -> 55.6864 | G4: =(u_bw_28*um28_B*ct_GB+u_rb_28*um28_B*ct_VR+u_ru_28*um28_B*ct_RU+u_hp_28*um28_B*ct_HP+u_amd_28*um28_B*ct_AMDR+u_tpu_28*um28_B*ct_TPU8+u_trn_28*um28_B*ct_TRN+u_oth_28*um28_B*ct_ASIC)*(1+px27)*(1+px28) -> 58.980096 | H4: =(u_bw_28*(1+g29_bw)*um29_B*ct_GB+u_rb_28*(1+g29_rb)*um29_B*ct_VR+u_ru_28*(1+g29_ru)*um29_B*ct_RU+u_hp_28*(1+g29_hp)*um29_B*ct_HP+u_amd_28*(1+g29_amd)*um29_B*ct_AMDR+u_tpu_28*(1+g29_tpu)*um29_B*ct_TPU8+u_trn_28*(1+g29_trn)*um29_B*ct_TRN+u_oth_28*(1+g29_oth)*um29_B*ct_ASIC)*(1+px27)*(1+px28)*(1+px29) -> 74.862643 | I4: =(u_bw_27*ct_GB+u_rb_27*ct_VR+u_ru_27*ct_RU+u_hp_27*ct_HP+u_amd_27*ct_AMDR+u_tpu_27*ct_TPU8+u_trn_27*ct_TRN+u_oth_27*ct_ASIC)*(1+px27) -> 55.6864 | J4: =(u_bw_28*um28_C*ct_GB+u_rb_28*um28_C*ct_VR+u_ru_28*um28_C*ct_RU+u_hp_28*um28_C*ct_HP+u_amd_28*um28_C*ct_AMDR+u_tpu_28*um28_C*ct_TPU8+u_trn_28*um28_C*ct_TRN+u_oth_28*um28_C*ct_ASIC)*(1+px27)*(1+px28) -> 44.235072 | K4: =(u_bw_28*(1+g29_bw)*um29_C*ct_GB+u_rb_28*(1+g29_rb)*um29_C*ct_VR+u_ru_28*(1+g29_ru)*um29_C*ct_RU+u_hp_28*(1+g29_hp)*um29_C*ct_HP+u_amd_28*(1+g29_amd)*um29_C*ct_AMDR+u_tpu_28*(1+g29_tpu)*um29_C*ct_TPU8+u_trn_28*(1+g29_trn)*um29_C*ct_TRN+u_oth_28*(1+g29_oth)*um29_C*ct_ASIC)*(1+px27)*(1+px28)*(1+px29) -> 52.844219
A5: AI 相關營收（含其他 AI） | B5: =B4*(1+ai_oth) -> 34.326 | C5: =C4*(1+ai_oth) -> 66.82368 | D5: =D4*(1+ai_oth) -> 88.470144 | E5: =E4*(1+ai_oth) -> 105.68844 | F5: =F4*(1+ai_oth) -> 66.82368 | G5: =G4*(1+ai_oth) -> 70.776115 | H5: =H4*(1+ai_oth) -> 89.835172 | I5: =I4*(1+ai_oth) -> 66.82368 | ... K5: =K4*(1+ai_oth) -> 63.413062
A6: 非 AI 營收 | B6: =B7-B5 -> 141.794 | C6: =B6*(1+na27_A) -> 158.80928 | D6: =C6*(1+na28_A) -> 174.69021 | E6: =D6*(1+na29_A) -> 188.66542 | F6: =B6*(1+na27_B) -> 158.80928 | G6: =F6*(1+na28_B) -> 166.74974 | H6: =G6*(1+na29_B) -> 171.75224 | I6: =B6*(1+na27_C) -> 158.80928 | J6: =I6*(1+na28_C) -> 158.80928 | K6: =J6*(1+na29_C) -> 154.045
A7: 營收 | B7: =rev26 -> 176.12 | C7: =C5+C6 -> 225.63296 | D7: =D5+D6 -> 263.16035 | E7: =E5+E6 -> 294.35386 | F7: =F5+F6 -> 225.63296 | G7: =G5+G6 -> 237.52586 | H7: =H5+H6 -> 261.58741 | I7: =I5+I6 -> 225.63296 | J7: =J5+J6 -> 211.89137 | K7: =K5+K6 -> 217.45806
A8: AI ÷ 營收 | B8: =B5/B7 -> 0.1949012 | C8: =C5/C7 -> 0.29616099 | D8: =D5/D7 -> 0.33618341 | E8: =E5/E7 -> 0.35905232 | F8: =F5/F7 -> 0.29616099 | G8: =G5/G7 -> 0.29797225 | H8: =H5/H7 -> 0.34342315 | I8: =I5/I7 -> 0.29616099 | ... K8: =K5/K7 -> 0.29161053
A9: 毛利率 | B9: =gm26 -> 0.6653349 | C9: =gm27_A -> 0.64 | D9: =gm28_A -> 0.63 | E9: =gm29_A -> 0.62 | F9: =gm27_B -> 0.64 | G9: =gm28_B -> 0.58 | H9: =gm29_B -> 0.56 | I9: =gm27_C -> 0.64 | J9: =gm28_C -> 0.54 | K9: =gm29_C -> 0.52
A10: 毛利 | B10: =B7*B9 -> 117.17878 | C10: =C7*C9 -> 144.40509 | D10: =D7*D9 -> 165.79102 | E10: =E7*E9 -> 182.49939 | F10: =F7*F9 -> 144.40509 | G10: =G7*G9 -> 137.765 | H10: =H7*H9 -> 146.48895 | I10: =I7*I9 -> 144.40509 | ... K10: =K7*K9 -> 113.07819
A11: 營業利益 | B11: =B7*(B9-opex_26) -> 103.16778 | C11: =C7*(C9-opex) -> 127.48262 | D11: =D7*(D9-opex) -> 146.054 | E11: =E7*(E9-opex) -> 160.42285 | F11: =F7*(F9-opex) -> 127.48262 | G11: =G7*(G9-opex) -> 119.95056 | H11: =H7*(H9-opex) -> 126.86989 | I11: =I7*(I9-opex) -> 127.48262 | J11: =J7*(J9-opex) -> 98.529485 | K11: =K7*(K9-opex) -> 96.768838
A12: 淨利 | B12: =B11*ni_op_26 -> 91.517159 | C12: =C11*ni_op -> 111.49549 | D12: =D11*ni_op -> 127.73789 | E12: =E11*ni_op -> 140.30481 | F12: =F11*ni_op -> 111.49549 | G12: =G11*ni_op -> 104.90799 | H12: =H11*ni_op -> 110.9596 | I12: =I11*ni_op -> 111.49549 | J12: =J11*ni_op -> 86.17326 | K12: =K11*ni_op -> 84.633409
A13: EPS（新台幣） | B13: =B12*fx_26/shares -> 112.0953 | C13: =C12*fx/shares -> 137.59567 | D13: =D12*fx/shares -> 157.64029 | E13: =E12*fx/shares -> 173.14901 | F13: =F12*fx/shares -> 137.59567 | G13: =G12*fx/shares -> 129.46609 | H13: =H12*fx/shares -> 136.93433 | I13: =I12*fx/shares -> 137.59567 | J13: =J12*fx/shares -> 106.34571 | K13: =K12*fx/shares -> 104.4454
A14: 目前股價 ÷ EPS | B14: =px/B13 -> 23.060735 | C14: =px/C13 -> 18.786929 | D14: =px/D13 -> 16.398093 | E14: =px/E13 -> 14.929338 | F14: =px/F13 -> 18.786929 | G14: =px/G13 -> 19.966618 | H14: =px/H13 -> 18.877662 | I14: =px/I13 -> 18.786929 | ... K14: =px/K13 -> 24.749775
A15: 資本支出 | B15: =capex26 -> 62 | C15: =capex27 -> 77 | D15: =capex28 -> 90 | E15: =capex29 -> 95 | F15: =capex27 -> 77 | G15: =capex28 -> 90 | H15: =capex29 -> 95 | I15: =capex27 -> 77 | J15: =capex28 -> 90 | K15: =capex29 -> 95
A16: 淨利 − 資本支出（不含折舊，粗估） | B16: =B12-B15 -> 29.517159 | C16: =C12-C15 -> 34.495489 | D16: =D12-D15 -> 37.737894 | E16: =E12-E15 -> 45.304806 | F16: =F12-F15 -> 34.495489 | G16: =G12-G15 -> 14.907994 | H16: =H12-H15 -> 15.9596 | I16: =I12-I15 -> 34.495489 | ... K16: =K12-K15 -> -10.366591
A18: 註：B 欄 2026 ＝1–3Q 實績＋4Q 指引中點（匯率、營業費用、淨利比用 2026 專屬參數）；非 AI 營收＝營收 − AI（由下而上）。2027 起兩者分開推。

Sheet Val
A1: Val — P/E 估值（新台幣）。隱含股價 ÷ 目前股價 − 1
A3: 方法 | B3: 倍數 | C3: EPS 年度 | D3: 情境 | E3: EPS | F3: 隱含股價 | G3: 相對目前
A4: P/E | B4: =pe_1 -> 15 | C4: 2027 | D4: A | E4: =PL!C13 -> 137.59567 | F4: =B4*E4 -> 2063.935 | G4: =F4/px-1 -> -0.20157253
A5: P/E | B5: =pe_2 -> 20.5 | C5: 2027 | D5: A | E5: =PL!C13 -> 137.59567 | F5: =B5*E5 -> 2820.7112 | G5: =F5/px-1 -> 0.091184208
A6: P/E | B6: =pe_3 -> 32.7 | C6: 2027 | D6: A | E6: =PL!C13 -> 137.59567 | F6: =B6*E6 -> 4499.3783 | G6: =F6/px-1 -> 0.74057188
A7: P/E | B7: =pe_1 -> 15 | C7: 2028 | D7: A | E7: =PL!D13 -> 157.64029 | F7: =B7*E7 -> 2364.6043 | G7: =F7/px-1 -> -0.085259467
A8: P/E | B8: =pe_2 -> 20.5 | C8: 2028 | D8: A | E8: =PL!D13 -> 157.64029 | F8: =B8*E8 -> 3231.6258 | G8: =F8/px-1 -> 0.25014539
A9: P/E | B9: =pe_3 -> 32.7 | C9: 2028 | D9: A | E9: =PL!D13 -> 157.64029 | F9: =B9*E9 -> 5154.8373 | G9: =F9/px-1 -> 0.99413436
A10: P/E | B10: =pe_1 -> 15 | C10: 2027 | D10: B | E10: =PL!F13 -> 137.59567 | F10: =B10*E10 -> 2063.935 | G10: =F10/px-1 -> -0.20157253
A11: P/E | B11: =pe_2 -> 20.5 | C11: 2027 | D11: B | E11: =PL!F13 -> 137.59567 | F11: =B11*E11 -> 2820.7112 | G11: =F11/px-1 -> 0.091184208
A12: P/E | B12: =pe_3 -> 32.7 | C12: 2027 | D12: B | E12: =PL!F13 -> 137.59567 | F12: =B12*E12 -> 4499.3783 | G12: =F12/px-1 -> 0.74057188
A13: P/E | B13: =pe_1 -> 15 | C13: 2028 | D13: B | E13: =PL!G13 -> 129.46609 | F13: =B13*E13 -> 1941.9914 | G13: =F13/px-1 -> -0.24874607
A14: P/E | B14: =pe_2 -> 20.5 | C14: 2028 | D14: B | E14: =PL!G13 -> 129.46609 | F14: =B14*E14 -> 2654.0549 | G14: =F14/px-1 -> 0.026713705
A15: P/E | B15: =pe_3 -> 32.7 | C15: 2028 | D15: B | E15: =PL!G13 -> 129.46609 | F15: =B15*E15 -> 4233.5413 | G15: =F15/px-1 -> 0.63773357
A16: P/E | B16: =pe_1 -> 15 | C16: 2027 | D16: C | E16: =PL!I13 -> 137.59567 | F16: =B16*E16 -> 2063.935 | G16: =F16/px-1 -> -0.20157253
A17: P/E | B17: =pe_2 -> 20.5 | C17: 2027 | D17: C | E17: =PL!I13 -> 137.59567 | F17: =B17*E17 -> 2820.7112 | G17: =F17/px-1 -> 0.091184208
A18: P/E | B18: =pe_3 -> 32.7 | C18: 2027 | D18: C | E18: =PL!I13 -> 137.59567 | F18: =B18*E18 -> 4499.3783 | G18: =F18/px-1 -> 0.74057188
A19: P/E | B19: =pe_1 -> 15 | C19: 2028 | D19: C | E19: =PL!J13 -> 106.34571 | F19: =B19*E19 -> 1595.1857 | G19: =F19/px-1 -> -0.38290689
A20: P/E | B20: =pe_2 -> 20.5 | C20: 2028 | D20: C | E20: =PL!J13 -> 106.34571 | F20: =B20*E20 -> 2180.0871 | G20: =F20/px-1 -> -0.15663942
A21: P/E | B21: =pe_3 -> 32.7 | C21: 2028 | D21: C | E21: =PL!J13 -> 106.34571 | F21: =B21*E21 -> 3477.5048 | G21: =F21/px-1 -> 0.34526298
A23: 讀法：目前股價 ÷ 2027 EPS 即市場給的遠期 P/E；與 10 年中位 20.5x 比，看市場是否已提前反映 2027–28 的成長與情境 B／C 風險
A26: 6. 十年倍數與規則值（2016–2025 年底；見頂年 25 分位、中段中位數、谷底 75 分位）
A27: 規則（Andy 2026-10-13）：合理倍數＝2016–2025 年底 P/E 依循環位置取分位；台積電 2027 為中段，取中位數，區間為 25 與 75 分位。兩個來源各自取分位再平均、四捨五入到兩位。倍數歷史為輸入（藍字）。
A29: P/E：十年歷史倍數
A30: 年底 | B30: FullRatio | C30: companiesmarketcap | D30: 標記／說明
A31: 2016 | B31: 14.5 | C31: 11.6 | D31: FullRatio：Interested-party；companiesmarketcap：Verified
A32: 2017 | B32: 17.71 | C32: 14.8
A33: 2018 | B33: 16.13 | C33: 14.2
A34: 2019 | B34: 25.62 | C34: 23.5
A35: 2020 | B35: 31.11 | C35: 28.3
A36: 2021 | B36: 29.18 | C36: 27.2
A37: 2022 | B37: 11.94 | C37: 11.2
A38: 2023 | B38: 19.46 | C38: 19.3
A39: 2024 | B39: 28.72 | C39: 28.8
A40: 2025 | B40: 29.03 | C40: 28.3
A41: 25 分位（各來源） | B41: =PERCENTILE(B31:B40,0.25) -> 16.525 | C41: =PERCENTILE(C31:C40,0.25) -> 14.35
A42: 中位數（各來源） | B42: =MEDIAN(B31:B40) -> 22.54 | C42: =MEDIAN(C31:C40) -> 21.4
A43: 75 分位（各來源） | B43: =PERCENTILE(B31:B40,0.75) -> 28.9525 | C43: =PERCENTILE(C31:C40,0.75) -> 28.025
A44: 最小（各來源） | B44: =MIN(B31:B40) -> 11.94 | C44: =MIN(C31:C40) -> 11.2
A45: 最大（各來源） | B45: =MAX(B31:B40) -> 31.11 | C45: =MAX(C31:C40) -> 28.8
A46: 採用 25 分位（P/E） | B46: =ROUND(AVERAGE(B41,C41),2) -> 15.44
A47: 採用 中位數（P/E） | B47: =ROUND(AVERAGE(B42,C42),2) -> 21.97
A48: 採用 75 分位（P/E） | B48: =ROUND(AVERAGE(B43,C43),2) -> 28.49
A49: 採用 最小（P/E） | B49: =ROUND(MIN(B44,C44),2) -> 11.2
A50: 採用 最大（P/E） | B50: =ROUND(MAX(B45,C45),2) -> 31.11
A52: P/E：規則值
A53: 情形 | B53: 循環位置 | C53: 倍數 | D53: 基準 | E53: 每股基準 | F53: 隱含股價 | G53: 相對目前 | H53: 現價 ÷ 基準
A54: 規則值：中段（P/E） | B54: 中段 → 中位數 | C54: =B47 -> 21.97 | D54: 2027 EPS（A） | E54: =PL!C13 -> 137.59567 | F54: =C54*E54 -> 3022.9768 | G54: =F54/px-1 -> 0.1694301 | H54: =px/E54 -> 18.786929
A55: 規則值：低（P/E） | B55: 25 分位（區間下緣） | C55: =B46 -> 15.44 | D55: 2027 EPS（A） | E55: =PL!C13 -> 137.59567 | F55: =C55*E55 -> 2124.4771 | G55: =F55/px-1 -> -0.17815199 | H55: =px/E55 -> 18.786929
A56: 規則值：高（P/E） | B56: 75 分位（區間上緣） | C56: =B48 -> 28.49 | D56: 2027 EPS（A） | E56: =PL!C13 -> 137.59567 | F56: =C56*E56 -> 3920.1006 | G56: =F56/px-1 -> 0.51647991 | H56: =px/E56 -> 18.786929
A57: 規則值：2028 C（P/E） | B57: 參考：2028 情境 C × 75 分位 | C57: =B48 -> 28.49 | D57: 2028 EPS（C） | E57: =PL!J13 -> 106.34571 | F57: =C57*E57 -> 3029.7893 | G57: =F57/px-1 -> 0.17206551 | H57: =px/E57 -> 24.307515
A59: 0. 目標價與上檔空間
A60: 項目 | B60: 數值 | E60: 說明
A61: 目標價（12 個月，情境加權） | B61: =tp_wA*B63+tp_wB*B64+tp_wC*B65 -> 3022.9768 | E61: 權重 × 各情境隱含價
A62: 上檔空間（目標價 ÷ 現價 − 1） | B62: =B61/px-1 -> 0.1694301 | E62: 現價＝In 頁 px（2026-10-07 收盤）
A63: 情境 A 隱含價（樂觀） | B63: =$C$54*PL!C13 -> 3022.9768 | E63: 情境 A 2027 EPS（PL 頁）× 十年 P/E 中位數（第 6 節規則值：中段）
A64: 情境 B 隱含價（基準） | B64: =$C$54*PL!F13 -> 3022.9768 | E64: 情境 B 2027 EPS（PL 頁）× 十年 P/E 中位數（第 6 節規則值：中段）
A65: 情境 C 隱含價（下檔） | B65: =$C$54*PL!I13 -> 3022.9768 | E65: 情境 C 2027 EPS（PL 頁）× 十年 P/E 中位數（第 6 節規則值：中段）
A66: 情境權重 A／B／C | B66: =tp_wA -> 0.3 | C66: =tp_wB -> 0.5 | D66: =tp_wC -> 0.2 | E66: ="合計 "&TEXT(B66+C66+D66,"0%")&"；In 頁 tp_wA／tp_wB／tp_wC（Assumed，Andy 可改）" -> 合計 100%；In 頁 tp_wA／tp_wB／tp_wC（Assumed，Andy 可改）
A67: 目標價方法 | B67: P/E：各情境 2027 EPS × 十年（2016–2025 年底）P/E 中位數（FullRatio 與 companiesmarketcap 兩來源平均；規則值：2027 為中段，取中位數，第 6 節）。2027 三情境 EPS 相同（情境差從 2028 起），故三情境隱含價相同；十年倍數兼含 2022 年低谷（11–12x）與 2020、2024–2025 年（28–31x），中位數無明顯單向偏誤；隱含價約為 2027 年底的價格、未折現，當作 12 個月目標價時偏高；現價為 2026-10-07 收盤（本版未更新）。

Sheet Recon
A1: Recon — 本模型 vs 公司口徑、共識（只作事後對照）
A3: 項目 | B3: 本模型 | C3: 對照值 | D3: 差距 | E3: 對照來源
A4: 2026 AI 相關營收 vs 公司口徑推算 | B4: =PL!B5 -> 34.326 | C4: =rev25*ai25_share*(1+ai_cagr) -> 34.598718 | D4: =B4/C4-1 -> -0.0078823152 | E4: 2025 AI 加速器十幾%後段 × CAGR 57%（公司）
A5: 2026 AI 加速器內容（不含其他 AI）vs 同上 | B5: =PL!B4 -> 28.605 | C5: =rev25*ai25_share*(1+ai_cagr) -> 34.598718 | D5: =B5/C5-1 -> -0.17323526 | E5: 其他 AI 相關（ai_oth）為 Assumed
A6: 2026 EPS vs 共識 | B6: =PL!B13 -> 112.0953 | C6: =cons_eps26 -> 107.6 | D6: =B6/C6-1 -> 0.041777878 | E6: MarketScreener
A7: 2026 營收 vs 公司全年成長指引（2025 × (1＋44%)） | B7: =PL!B7 -> 176.12 | C7: =rev25*(1+g26_guid) -> 176.2992 | D7: =B7/C7-1 -> -0.0010164538 | E7: 公司 3Q26 法說：全年美元成長約 44%
A8: 2026 EPS vs 1–3Q 實績＋4Q 指引推算 | B8: =PL!B13 -> 112.0953 | C8: =eps26_1to3q+ntd26_4q*opm26_4q*ni_op_26/shares -> 112.10096 | D8: =B8/C8-1 -> -5.0502654e-05 | E8: 公司各季 EPS 22.08／27.25／29.43＋4Q 指引中點
A9: 2027 營收（A）vs 共識 | B9: =PL!C7 -> 225.63296 | C9: =cons_rev27 -> 229 | D9: =B9/C9-1 -> -0.014703231 | E9: MarketScreener
A10: 2027 EPS（A）vs 共識 | B10: =PL!C13 -> 137.59567 | C10: =cons_eps27 -> 142 | D10: =B10/C10-1 -> -0.031016428 | E10: MarketScreener
A11: 2026 CoWoS 需求 vs Morgan Stanley | B11: =CoWoS!B13 -> 1107.8576 | C11: =ms_dem26 -> 1394 | D11: =B11/C11-1 -> -0.20526713 | E11: 千片
A12: 2027 CoWoS 需求 vs Morgan Stanley | B12: =CoWoS!C13 -> 2096.4286 | C12: =ms_dem27 -> 2509 | D12: =B12/C12-1 -> -0.1644366 | E12: 千片

Sheet Sens
A1: Sens — 2027 情境 A：一次動一個輸入
A3: 輸入 | B3: 2027 EPS | C3: 相對基準 | D3: 2027 CoWoS 需求 ÷ 產能
A4: 基準 | B4: =(PL!C7)*(gm27_A-opex)*ni_op*fx/shares -> 137.59567 | C4: =B4/B$4-1 -> 0 | D4: =CoWoS!C17 -> 0.96254755
A5: Rubin 顆數 −30% | B5: =(PL!C7-0.3*u_rb_27*ct_VR*(1+px27)*(1+ai_oth))*(gm27_A-opex)*ni_op*fx/shares -> 132.77642 | C5: =B5/B$4-1 -> -0.03502467 | D5: =(CoWoS!C13-0.3*CoWoS!C5)/CoWoS!C16 -> 0.84202414
A6: AI 內容價格 2027 +0%（不漲） | B6: =(PL!C7-PL!C5*px27/(1+px27))*(gm27_A-opex)*ni_op*fx/shares -> 133.22955 | C6: =B6/B$4-1 -> -0.031731534 | D6: =CoWoS!C17 -> 0.96254755
A7: 毛利率 2027 60% | B7: =(PL!C7)*(0.6-opex)*ni_op*fx/shares -> 127.85438 | C7: =B7/B$4-1 -> -0.07079646 | D7: =CoWoS!C17 -> 0.96254755
A8: 毛利率 2027 67% | B8: =(PL!C7)*(0.67-opex)*ni_op*fx/shares -> 144.90163 | C8: =B8/B$4-1 -> 0.053097345 | D8: =CoWoS!C17 -> 0.96254755
A9: 非 AI 營收 2027 +0% | B9: =(PL!C7-PL!B6*na27_A)*(gm27_A-opex)*ni_op*fx/shares -> 127.2194 | C9: =B9/B$4-1 -> -0.075411323 | D9: =CoWoS!C17 -> 0.96254755
A10: CoWoS 2027 年底產能 17 萬片（KGI） | B10: =(PL!C7)*(gm27_A-opex)*ni_op*fx/shares -> 137.59567 | C10: =B10/B$4-1 -> 0 | D10: =CoWoS!C13/((cap_end26+170)/2*12*(1+osat)) -> 1.0588023
A13: 淨利 ÷ 營業利益 對 EPS 的影響（情境 A）
A14: 設定 | B14: 比值 | C14: 2027 EPS | D14: 相對基準 | E14: 2028 EPS | F14: 相對基準
A15: 基準（推導值） | B15: =ni_op -> 0.87459363 | C15: =PL!C11*B15*fx/shares -> 137.59567 | D15: =C15/C$15-1 -> 0 | E15: =PL!D11*B15*fx/shares -> 157.64029 | F15: =E15/E$15-1 -> 0
A16: 淨利 ÷ 營業利益 0.864（低） | B16: =ni_op_lo -> 0.86441453 | C16: =PL!C11*B16*fx/shares -> 135.99424 | D16: =C16/C$15-1 -> -0.011638655 | E16: =PL!D11*B16*fx/shares -> 155.80556 | F16: =E16/E$15-1 -> -0.011638655
A17: 淨利 ÷ 營業利益 0.909（高） | B17: =ni_op_hi -> 0.90916687 | C17: =PL!C11*B17*fx/shares -> 143.03491 | D17: =C17/C$15-1 -> 0.039530642 | E17: =PL!D11*B17*fx/shares -> 163.87191 | F17: =E17/E$15-1 -> 0.039530642

Sheet NI_OI
A1: NI_OI — 淨利 ÷ 營業利益拆解（新台幣十億）。淨利÷營業利益 ＝ (1＋營業外÷營業利益) × (1－有效稅率) × 少數股權等調整。藍字＝輸入
A3: 期間 | B3: 營業利益 | C3: 營業外收支 | D3: 稅前淨利 | E3: 所得稅 | F3: 淨利 | G3: 利息收入 | H3: 匯兌損益 | I3: 一次性項目 | J3: 有效稅率 | K3: 營業外÷營業利益 | L3: 少數股權等調整 | M3: 淨利÷營業利益 | N3: 獨立來源數 | O3: 標記 | P3: 來源／說明
A4: 2022 | B4: 1121.28 | C4: 22.91 | D4: =B4+C4 -> 1144.19 | E4: =D4-F4 -> 127.29 | F4: 1016.9 | I4: 0 | J4: =E4/D4 -> 0.11124901 | K4: =C4/B4 -> 0.020432006 | L4: =F4/(D4-E4) -> 1 | M4: =F4/B4 -> 0.90690996 | N4: 1 | O4: Verified（單一來源） | P4: 公司年報（經搜尋摘錄）；稅額＝稅前淨利－淨利（Derived）；媒體僅能核對淨利（歸屬母公司 1,016.53，股東會資料）；利息、匯兌明細未找到。待複核：另一搜尋結果的稅前淨利 1,140.7 疑為還原表欄位誤讀
A5: 2023 | B5: 921.47 | C5: 57.71 | D5: =B5+C5 -> 979.18 | E5: 141.4 | F5: 837.77 | G5: 60.29 | I5: 0 | J5: =E5/D5 -> 0.14440654 | K5: =C5/B5 -> 0.062628192 | L5: =F5/(D5-E5) -> 0.99998806 | M5: =F5/B5 -> 0.90916687 | N5: 2 | O5: Verified | P5: 公司：2023 年報（6-K 2023-02）｜媒體：MoneyDJ 113 年損益表的前期欄；利息 60.29 僅 2025 20-F 一個來源；匯兌未找到
A6: 2024 | B6: 1322.05 | C6: 83.79 | D6: =B6+C6 -> 1405.84 | E6: 233.41 | F6: 1172.43 | G6: 87.21 | H6: 10 | I6: 0 | J6: =E6/D6 -> 0.16602885 | K6: =C6/B6 -> 0.063378843 | L6: =F6/(D6-E6) -> 1 | M6: =F6/B6 -> 0.88682728 | N6: 2 | O6: Verified | P6: 公司：2024 年報、2025 20-F｜媒體：MoneyDJ、中央社；匯兌 10.00 僅 20-F／財報一個來源
A7: 2025 | B7: 1936.09 | C7: 105.56 | D7: =B7+C7 -> 2041.65 | E7: 326.25 | F7: 1715.4 | G7: 105.74 | H7: 13.83 | I7: 0 | J7: =E7/D7 -> 0.15979722 | K7: =C7/B7 -> 0.054522259 | L7: =F7/(D7-E7) -> 1 | M7: =F7/B7 -> 0.88601253 | N7: 2 | O7: Verified | P7: 公司：2025 年報、2025 20-F｜媒體：工商時報（營業外約 1,056 億、稅前 2 兆 417 億、稅 3,263 億）；匯兌 13.83 僅 20-F／財報一個來源；其他利益及損失未拆
A8: 1Q26 | B8: =ntd26_1q*opm26_1q -> 658.9121 | C8: 28.83 | D8: =B8+C8 -> 687.7421 | E8: =D8-F8 -> 115.2621 | F8: 572.48 | I8: 0 | J8: =E8/D8 -> 0.16759495 | K8: =C8/B8 -> 0.043753939 | L8: =F8/(D8-E8) -> 1 | M8: =F8/B8 -> 0.86882605 | N8: 1 | O8: Derived | P8: 營業利益＝新台幣營收×營益率（Derived）；營業外 28.83 取自 2Q26 簡報比較欄，欄位標籤未能直接確認；稅額＝稅前淨利－淨利（Derived）
A9: 2Q26 | B9: =ntd26_2q*opm26_2q -> 766.03914 | C9: 95.83 | D9: =B9+C9 -> 861.86914 | E9: 155.65 | F9: 706.56 | I9: 63.2 | J9: =E9/D9 -> 0.18059586 | K9: =C9/B9 -> 0.12509805 | L9: =F9/(D9-E9) -> 1.0004827 | M9: =F9/B9 -> 0.92235496 | N9: 2 | O9: Verified／Derived | P9: 公司：2Q26 簡報、3Q26 Management Report（稅 155.65、有效稅率 18.1%）；SEC 3Q26 6-K（含 2Q26 比較欄）核對營業利益、稅前淨利、淨利相符｜媒體：鉅亨（營業外 958.27 億）；營業利益 NT$ 欄為 Derived。一次性項目 63.20 的出處見下方「一次性利益出處」
A10: 3Q26 | B10: 876.45 | C10: 34.59 | D10: =B10+C10 -> 911.04 | E10: 147.7 | F10: 763.06 | I10: 0 | J10: =E10/D10 -> 0.16212241 | K10: =C10/B10 -> 0.039466028 | L10: =F10/(D10-E10) -> 0.99963319 | M10: =F10/B10 -> 0.87062582 | N10: 2 | O10: Verified | P10: 公司：3Q26 Management Report（營業外 34.59、稅 147.70、有效稅率 16.2%；較 2Q26 降，主因無 VIS 處分與評價利益）｜SEC 3Q26 6-K a3q26e（營業利益、稅前淨利、淨利核對相符；使用者提供的核對）
A11: 1–3Q26 合計 | B11: =SUM(B8:B10) -> 2301.4012 | C11: =SUM(C8:C10) -> 159.25 | D11: =SUM(D8:D10) -> 2460.6512 | E11: =SUM(E8:E10) -> 418.6121 | F11: =SUM(F8:F10) -> 2042.1 | I11: =SUM(I8:I10) -> 63.2 | J11: =E11/D11 -> 0.17012248 | K11: =C11/B11 -> 0.069196973 | L11: =F11/(D11-E11) -> 1.0000298 | M11: =F11/B11 -> 0.88732897 | O11: Derived | P11: 三季加總；一次性項目＝2Q26 VIS 處分利益（含股權評價利益未另拆）
A13: 基準值推導（In!ni_op）
A14: 新稅率＝2024 起各期所得稅合計 ÷ 稅前淨利合計（2024、2025、1–3Q26） | B14: =(E6+E7+E11)/(D6+D7+D11) -> 0.16558035 | P14: 取 2024 起：2024 年起全球最低稅負生效，有效稅率由 2022 年約 11% 升到 14–18%（2024 16.6%、2025 16.0%、2Q26 18.1%、3Q26 16.2%）；視為長期性變化
A15: 歷史營業外比率＝2022–2025 加 1–3Q26（扣除一次性項目）的營業外合計 ÷ 營業利益合計 | B15: =(SUM(C4:C7)+C11-I11)/(SUM(B4:B7)+B11) -> 0.048146011 | P15: 營業外收支主體是利息收入（2024 87.2、2025 105.7，占營業外 100% 以上）；匯兌 2024 +10.0、2025 +13.8，量級小且為收益；2Q26 VIS 處分利益 63.2 為一次性，已扣除
A16: 基準＝(1＋歷史營業外比率) × (1－新稅率) | B16: =(1+B15)*(1-B14) -> 0.87459363 | P16: 少數股權等調整各期約 1.000，略去
A17: 對照：2024、2025 實績比（前版低值 0.887） | B17: =(F6+F7)/(B6+B7) -> 0.88634313
A18: 對照：1–3Q26 實績比 | B18: =M11 -> 0.88732897 | P18: 含 2Q26 一次性利益
A19: 區間低值＝1–3Q26 扣除一次性利益（按新稅率稅後） | B19: =(F11-I11*(1-B14))/B11 -> 0.86441453 | P19: 2026 年的內含水準；1Q26、3Q26 單季分別 0.869、0.871
A20: 區間高值＝2023 年年度值（稅率上升前、2022–2025 年度最高） | B20: =M5 -> 0.90916687 | P20: 2022 0.907、2023 0.909、2024 0.887、2025 0.886
A21: 敏感：63.2 若非一次性（不扣除）→ 歷史營業外比率 | B21: =(SUM(C4:C7)+C11)/(SUM(B4:B7)+B11) -> 0.056459295 | P21: 分子不扣 63.2
A22: 敏感：63.2 若非一次性 → 基準 | B22: =(1+B21)*(1-B14) -> 0.88153039 | P22: 相對基準 0.875 的變化見 README
A25: 判定：差距兩個來源都有——(a) 稅率由 2022 年 11% 升至 2024 年起約 16.6%，屬長期；(b) 營業外比率 2022 年 2.0% → 2023–25 年 5.5–6.3%（利息收入墊高），2Q26 另有一次性處分利益使 0.92 偏高。依規則取「新稅率 × 歷史平均營業外比率」。
A27: 一次性利益出處（2Q26 VIS 處分與評價利益 63.20）：公司 2Q26 合併財務報告（SEC 6-K）載明處分利益 NT$63,202,285 千元，其中含對剩餘持股改按公允價值衡量的非現金重新衡量利益 56,398,783 千元（喪失重大影響力）；公司 2026-05-15 公告表示近期無進一步出售計畫；3Q26 Management Report 說明營業外由 95.83 降至 34.59 主因無該項處分與評價利益；媒體：中央社、東森財經、鉅亨。頁碼：搜尋摘錄未含頁碼，未取得（文件與段落見 Sources 頁）。SEC 3Q26 6-K 本身未標註一次性項目。

Sheet Sources
A1: 來源
A2: 台積電 2Q26 新聞稿 | B2: https://pr.tsmc.com/english/news/3326
A3: 台積電 2Q26 法說逐字稿 | B3: https://investor.tsmc.com/english/encrypt/files/encrypt_file/reports/2026-08/3e494f0c14dd0890f897aa044415e21d93486cc4/TSMC%202Q26%20Transcript.pdf
A4: 台積電 4Q25 法說逐字稿 | B4: https://investor.tsmc.com/japanese/encrypt/files/encrypt_file/reports/2026-01/51d09df96cd89ac19d65af39032b038dc2896a24/TSMC%204Q25%20Transcript.pdf
A5: 台積電 2026-09 營收（6-K） | B5: https://www.sec.gov/Archives/edgar/data/0001046179/000104617926000680/tsm-revenue20261008.htm
A6: TrendForce CoWoS 2025-12-08 | B6: https://www.trendforce.com/news/2025/12/08/news-tsmcs-cowos-l-s-reportedly-fully-booked-osat-partners-step-up-with-ases-cowop-in-focus
A7: TrendForce CoWoS 2026-06-15 | B7: https://www.trendforce.com/news/2026/06/15/news-tsmc-cowos-supply-demand-gap-reportedly-seen-narrowing-from-20-to-10-by-end-2026-as-capacity-expands/
A8: 經濟日報／Morgan Stanley 2026-09-13 | B8: https://money.udn.com/money/story/5607/9752236
A9: 36Kr CoWoS 分配 2026-01-09 | B9: https://eu.36kr.com/en/p/3631956080985095
A10: 經濟日報／JPMorgan 2026-09-29 | B10: https://money.udn.com/money/amp/story/5607/9783752
A11: Tom's Hardware／Nikkei 2027 漲價 | B11: https://www.tomshardware.com/tech-industry/semiconductors/tsmc-eyes-price-hikes-of-up-to-25-percent-on-chip-production-services-in-2027-report-claims-plans-to-raise-baseline-prices-by-5-percent-to-10-percent-on-advanced-nodes
A12: MarketScreener 共識 | B12: https://in.marketscreener.com/quote/stock/TSMC-TAIWAN-SEMICONDUCTOR-6492349/valuation/
A13: GuruFocus P/E | B13: https://www.gurufocus.com/term/pettm/TSM
... A39: 【v0.2】查證方式說明 | B39: 公司原文頁面在本次建置環境無法直接開啟（網路限制），3Q26 數字取自搜尋引擎對公司新聞稿的摘錄，並與至少兩則獨立媒體交叉；公司逐字稿原文待人工複核
A40: markets/chip_bridge v0.2、markets/memory（本 repo）
