Workbook

Sheet README
A1: 聯電（2303.TW；ADR UMC）個股模型 v0.1（AI 半導體 Project：代工層，成熟製程晶圓代工；樣板 guc/、營收結構參考 tsmc/） 2026-10-31
A2: 版本：v0.1（初版）。營收＝成熟製程晶圓（產能 × 稼動率 × 美元售價 × 匯率）＋AI 相關（先進封裝矽中介層、矽光子）＋Intel 12 奈米合作。滾入 3Q26 實績（2026-10-28 財報）與 4Q26 指引。本版未做先驗。
A3: 模型命題：聯電的獲利由成熟製程（22／28 奈米以上）的稼動率與價格循環決定。3Q26 稼動率回到 92%、毛利率 34.0%，公司估 2027 年平均售價年增約一成；AI 帶動的周邊（先進封裝矽中介層、矽光子，以及 OLED 驅動 IC、Wi-Fi 7、車用雷達等 22／28 奈米需求）與 Intel 12 奈米合作是增量，中國成熟製程擴產是價格的下行風險。
A4: 核心問題：稼動率與美元售價回升能走多遠（情境 A 稼動率 95%、售價 +10%），AI 相關與 Intel 合作在 FY2029 能補多少（模型情境 A 約 10 億＋5 億美元，不到營收一成）；現價約 20 倍前瞻 P/E，比聯電自己 10 年 Bloomberg 前瞻 P/E 中位數 15.2 倍高多少。
A6: 會計年度＝日曆年，FY(t)＝CY(t)，不平移。FY2025A 實績、FY2026 錨點（1Q–3Q26 實績＋4Q26 指引）、FY2027–FY2029 驅動因子推導、FY2030–FY2032 收斂法。金額：十億新台幣；EPS：新台幣（基本）；口徑：歸屬母公司淨利（TIFRS）。晶圓：千片 12 吋約當。
A8: 驅動因子 → 推導量（行業變數讀 Siliconomics；成熟製程稼動率與售價為公司層級，待併入 Siliconomics）
A9: 成熟製程晶圓：產能（FY2026 由各季出貨 ÷ 稼動率推得約 5,230 千片；FY2027–29 年增 4%／7%／7%，新加坡 P4 與台南新廠）× 稼動率（A／B／C：FY2027 95%／90%／82%、FY2028 94%／87%／76%、FY2029 93%／88%／80%）× 美元售價（FY2026 約 1,878 美元；FY2027 +10%／+5%／0、FY2028 +3%／0／−6%、FY2029 +2%／0／−3%）× 匯率 32（Siliconomics fx_twd）。
A10: 新業務：AI 相關 FY2026 3 億美元（公司）、FY2027 +60%／+40%／+20%、之後年增 45% 再乘 Siliconomics 同字母顆數係數（um28、um29）；Intel 12 奈米 FY2028 2.5／1.2／0 億美元、FY2029 5／3／0.8 億美元；新業務邊際貢獻率 45%（Assumed）。
A11: 成本：銷貨成本內折舊（FY2026 約 562 億元＝9M26 折舊年化 × 0.9；年增 12%／10%／8%）＋每片現金成本（FY2026 殘差，年增 2%）；營業費用彈性 0.5、年增下限 3%；營業外每年 40 億元（不外推 2Q26 一次性約 302 億元）、稅率 15%、股數 124.5 億股。
A12: 校準：FY2026 ＝ 1Q–3Q26 實績（公司 6-K）＋4Q26 公司指引（出貨 +2%、售價持穩、毛利率 34%、稼動率 92%）。成熟製程售價與每片現金成本以 FY2026 校準；不用券商數字（只在 Recon 對帳）。
A13: 估值：Val 第 0 節目標價＝0.5 × DCF 目標價（股東現金流＝EPS ×（1 − g／ROE），FY2027–32 明確期＋永續，r 10%、g 4%，三情境權重 0.3／0.5／0.2，情境價值負值取 0）＋0.5 × Comparable 目標價（台積電、格芯、中芯港股、高塔、世界先進前瞻 P/E 中位數 × 12 個月後前瞻 EPS，再乘相對倍數調整係數；不含 A 股）；另列 Comparable 單獨目標價、市場共識目標價與差距拆解。十年 P/E 規則值 × FY2027 EPS 保留為參考（不是目標價）。本版未做先驗，無 Andy 合理 P/E 對照。
A14: 預估期間：FY2027–FY2029 由驅動因子推導；FY2030 起為收斂法，非驅動因子推導（營收年增由 FY2029 線性收斂到 fade_g、淨利率收斂到 fade_m，FY2032 達到；PL 頁灰底）。十年平均淨利率未找到，B、C 依工作單以 FY2029 × 0.8 代替。
... A21: 公司特有：稼動率 FY2027 95%／90%／82%、FY2028 94%／87%／76%、FY2029 93%／88%／80%；售價 FY2027 +10%／+5%／0、FY2028 +3%／0／−6%、FY2029 +2%／0／−3%（C＝中國成熟製程擴產的價格壓力）；AI 相關 FY2027 +60%／+40%／+20%；Intel 12 奈米 FY2028 2.5／1.2／0、FY2029 5／3／0.8 億美元。
A23: ="投資建議："&Val!B135&"（依上檔空間固定規則）" -> 投資建議：放空（依上檔空間固定規則）
A24: ="重點觀察 1：目標價 NT$"&TEXT(Val!$B$39,"#,##0.00")&"（DCF "&TEXT(Val!$B$24,"#,##0.00")&"、Comparable（相對倍數調整後）"&TEXT(tp_comp_adj,"#,##0.00")&"；DCF 權重 "&TEXT(tp_w_dcf,"0%")&"），比現價 "&TEXT(px,"#,##0.00")&"（2026-10-22）"&IF(Val!$B$42>=0,"高 "&TEXT(Val!$B$42,"0.0%"),"低 "&TEXT(-Val!$B$42,"0.0%"))&"，級距 "&Val!$B$134&"、投資建議 "&Val!$B$135&"。相對倍數調整係數 "&TEXT(rm_factor,"0.00")&"（本公司 10 年前瞻倍數中位數 ÷ 同業的中位數，夾在 0.5–2.0；Val 第 0.5 節），調整前加權上檔空間 "&TEXT((tp_w_dcf*Val!$B$24+(1-tp_w_dcf)*Val!$B$35)/px-1,"+0.0%;−0.0%")&"；Comparable 單獨（市場主流同業法、未調整）為 "&TEXT(Val!$B$43,"+0.0%;−0.0%")&"。" -> 重點觀察 1：目標價 NT$76.40（DCF 82.47、Comparable（相對倍數調整後）70.34；DCF 權重 50%），比現價 125.50（2026-10-22）低 39.1%，級距 −25%～−50%、投資建議 放空。相對倍數調整係數 0.50（本公司 10 年前瞻倍數中位數 ÷ 同業的中位數，夾在 0.5–2.0；Val 第 0.5 節），調整前加權上檔空間 −11.1%；Comparable 單獨（市場主流同業法、未調整）為 +12.1%。
A25: 重點觀察 2：下檔主因有二：(1) 相對倍數調整係數 0.5——聯電 10 年 Bloomberg 前瞻 P/E 中位數 15.2 倍，只有台積電與中芯（港股）中位數的中位數 32.3 倍的 0.47（觸及下限 0.5；格芯、高塔、世界先進資料不足未納入），Comparable 因此由 140.7 減半為 70.3；若不調整，加權目標價約 111.6（−11%，中立）。(2) DCF 82.5 偏低：ROE 近三年平均 13.9%、再投資率 29%，情境 B 的 FY2027–29 EPS 只有 5.95／5.85／6.53（FY2026 的 7.36 含 2Q26 一次性投資收益約 2.0 元）。EPS 因素與倍數因素都只有 −3%，與市場共識的差距不在獲利預估，而在相對倍數調整與 DCF。
A26: 重點觀察 3：稼動率與售價是承重變數：3Q26 稼動率 92%、4Q26 指引低 90% 區間，公司估 2027 年平均售價年增約一成（情境 A 照用、B 取 +5%、C 持平）；售價 ±3% 使加權目標價 ±10.2%、匯率 30.5 使 −16.5%，AI 相關營收 ±30% 只有 ±2.9%。下一個檢驗點是 2027-01 下旬的 4Q26 法說（2027 年售價、折舊與資本支出指引；日期未公告）與 Intel 12 奈米 2027 年試產進度。
A28: 相對倍數調整（tools/relative_multiple.py；Val 第 0.5 節）已含在加權目標價：Comparable（相對倍數調整後）＝同業前瞻倍數中位數 × 本公司 10 年相對同業的倍數比（Bloomberg 前瞻倍數）。「Comparable 目標價（市場主流同業法）」維持不調整。重點觀察的數字以本版重算值撰寫（第 1 點第一句為公式）。
A30: v0.1（2026-10-31）：依個股模型原則第 8 節調整 In 頁呈現（數值不變）。In 頁 D／F 欄名改「敏感度低」「敏感度高」（只用於 Sens 頁、不進目標價）；In 頁最後新增「情境驅動對照」一節，把上方各情境專屬輸入三情境並排（只引用上方各列，純展示）；HTML 驅動因子一節分「情境驅動」與「單一參數」兩張表。

Sheet In
A1: In — 輸入（藍字；基準欄 E，低 D、高 F）。金額：十億新台幣（NT$B）；晶圓：千片（12 吋約當）；售價：美元／片；匯率：新台幣／美元。公司財報與法說為 Interested-party（公司說法）或 Verified（財報數字）；券商、資料商、媒體為 Interested-party。【v0.1】基準欄 E 進主模型；D／F＝敏感度低／高，只用於 Sens 頁（一次動一個參數）、不進目標價；情境 A／B／C 的驅動見本頁最後一節「情境驅動對照」。
A2: 標記：Verified／Interested-party／Analogy／Assumed／Derived；Analogy、Assumed 以情境或 Sens 區間呈現，不當點估計。行業變數讀 Siliconomics v0.10（siliconomics/data/siliconomics_snapshot_v0.10.json）；成熟製程稼動率與售價屬公司層級，說明欄標「待併入 Siliconomics」。SemiAnalysis 未使用
A3: 鍵 | B3: 項目 | C3: 單位 | D3: 敏感度低 | E3: 基準 | F3: 敏感度高 | G3: 標記 | H3: 來源1 | I3: 來源2／說明
A4: A. 行業變數（Siliconomics v0.10（siliconomics/data/siliconomics_snapshot_v0.10.json）；A／B／C 讀同字母上游，不自訂行業路徑）
A5: fx | B5: 匯率（FY2027 起；美元售價換算） | C5: NT$/US$ | D5: 30.5 | E5: 32 | F5: 33 | G5: Assumed | H5: Siliconomics v0.10（siliconomics/data/siliconomics_snapshot_v0.10.json）｜fx_twd | I5: Siliconomics 共用匯率（2026–2029）；與台積電、聯發科等台股模型同值
A6: um28_A | B6: 情境 A：CY2028 AI 加速器顆數 ÷ 基準 | C6: x | E6: 1 | G6: Derived | H6: Siliconomics v0.10（siliconomics/data/siliconomics_snapshot_v0.10.json）｜um28_A | I6: AI 相關營收 CY2028–29 依同字母顆數係數縮放（行業情境；A＝基準）
A7: um29_A | B7: 情境 A：CY2029 AI 加速器顆數 ÷ 基準 | C7: x | E7: 1 | G7: Derived | H7: Siliconomics v0.10（siliconomics/data/siliconomics_snapshot_v0.10.json）｜um29_A | I7: 同上
A8: um28_B | B8: 情境 B：CY2028 AI 加速器顆數 ÷ 基準 | C8: x | E8: 0.8 | G8: Assumed | H8: Siliconomics v0.10（siliconomics/data/siliconomics_snapshot_v0.10.json）｜um28_B | I8: 同上
A9: um29_B | B9: 情境 B：CY2029 AI 加速器顆數 ÷ 基準 | C9: x | E9: 0.85 | G9: Assumed | H9: Siliconomics v0.10（siliconomics/data/siliconomics_snapshot_v0.10.json）｜um29_B | I9: 同上
A10: um28_C | B10: 情境 C：CY2028 AI 加速器顆數 ÷ 基準 | C10: x | E10: 0.6 | G10: Assumed | H10: Siliconomics v0.10（siliconomics/data/siliconomics_snapshot_v0.10.json）｜um28_C | I10: 同上
A11: um29_C | B11: 情境 C：CY2029 AI 加速器顆數 ÷ 基準 | C11: x | E11: 0.6 | G11: Assumed | H11: Siliconomics v0.10（siliconomics/data/siliconomics_snapshot_v0.10.json）｜um29_C | I11: 同上
A12: B. 產能與稼動率（12 吋約當；公司層級，待併入 Siliconomics：Siliconomics 尚無成熟製程稼動率）
A13: cap_26 | B13: FY2026 產能（12 吋約當，千片／年） | C13: 千片 | E13: =Q!G7 -> 5230.4685 | G13: Derived | H13: Q 頁：各季出貨 ÷ 稼動率（1Q–3Q26 實績、4Q26 指引） | I13: 公司未揭露產能；以出貨與稼動率推得（Derived）
A14: capg27 | B14: FY2027 產能年增 | C14: % | E14: 0.04 | G14: Assumed | H14: 公司：董事會核准新加坡 P4、台南新廠擴產預算約 1,487 億元（2026-07-29）與約 1,028 億元（2026-10-28；6-K） | I14: 三情境相同（產能為公司已核准的擴產；待併入 Siliconomics）
A15: capg28 | B15: FY2028 產能年增 | C15: % | E15: 0.07 | G15: Assumed | H15: 同上；Fab12i P3 量產時程：未找到 | I15: 三情境相同（產能為公司已核准的擴產；待併入 Siliconomics）
A16: capg29 | B16: FY2029 產能年增 | C16: % | E16: 0.07 | G16: Assumed | H16: 同上 | I16: 三情境相同（產能為公司已核准的擴產；待併入 Siliconomics）
A17: cap_adj | B17: 產能係數（Sens 用；FY2027 起各年同乘） | C17: x | D17: 0.95 | E17: 1 | F17: 1.05 | G17: Assumed | H17: 無 | I17: ±5%：擴產時程提前或延後
A18: ut27_A | B18: FY2027 平均稼動率（情境 A） | C18: % | E18: 0.95 | G18: Assumed | H18: 公司：3Q26 稼動率 92%、4Q26 指引低 90% 區間（6-K）；1Q26 79%、2Q26 85% | I18: A 最有利、C 最不利（C＝中國成熟製程擴產的價格與份額壓力）；待併入 Siliconomics
A19: ut27_B | B19: FY2027 平均稼動率（情境 B） | C19: % | E19: 0.9 | G19: Assumed | H19: 同上 | I19: 待併入 Siliconomics
A20: ut27_C | B20: FY2027 平均稼動率（情境 C） | C20: % | E20: 0.82 | G20: Assumed | H20: 同上 | I20: 待併入 Siliconomics
A21: ut28_A | B21: FY2028 平均稼動率（情境 A） | C21: % | E21: 0.94 | G21: Assumed | H21: 同上 | I21: A 最有利、C 最不利（C＝中國成熟製程擴產的價格與份額壓力）；待併入 Siliconomics
A22: ut28_B | B22: FY2028 平均稼動率（情境 B） | C22: % | E22: 0.87 | G22: Assumed | H22: 同上 | I22: 待併入 Siliconomics
A23: ut28_C | B23: FY2028 平均稼動率（情境 C） | C23: % | E23: 0.76 | G23: Assumed | H23: 同上 | I23: 待併入 Siliconomics
A24: ut29_A | B24: FY2029 平均稼動率（情境 A） | C24: % | E24: 0.93 | G24: Assumed | H24: 同上 | I24: A 最有利、C 最不利（C＝中國成熟製程擴產的價格與份額壓力）；待併入 Siliconomics
A25: ut29_B | B25: FY2029 平均稼動率（情境 B） | C25: % | E25: 0.88 | G25: Assumed | H25: 同上 | I25: 待併入 Siliconomics
A26: ut29_C | B26: FY2029 平均稼動率（情境 C） | C26: % | E26: 0.8 | G26: Assumed | H26: 同上 | I26: 待併入 Siliconomics
A27: ut_adj | B27: 稼動率調整（Sens 用；FY2027 起各年加減，上限 98%） | C27: pt | D27: -0.03 | E27: 0 | F27: 0.03 | G27: Assumed | H27: 無 | I27: ±3 個百分點
A28: C. 平均售價（美元，每片 12 吋約當；公司層級，待併入 Siliconomics：Siliconomics 尚無成熟製程價格）
A29: asp_26 | B29: FY2026 平均售價（成熟製程晶圓；美元／片） | C29: US$/片 | E29: =(a26_rev-ai_26*fx_26)/a26_ship/fx_26*1000000 -> 1878.1749 | G29: Derived | H29: （FY2026 營收 − AI 相關）÷ 出貨 ÷ 匯率 | I29: 校準年；FY2027 起依情境年增
A30: asp27_A | B30: FY2027 平均售價年增（美元；情境 A） | C30: % | E30: 0.1 | G30: Assumed | H30: 優分析 2026-10-28（3Q26 法說轉述）：公司估 2027 年平均售價年增約一成（22 奈米份額與產品組合）；摩根士丹利：8 吋代工 2027 年漲價 | I30: A＝漲價延續；C＝中國成熟製程擴產造成價格壓力；待併入 Siliconomics
A31: asp27_B | B31: FY2027 平均售價年增（美元；情境 B） | C31: % | E31: 0.05 | G31: Assumed | H31: 同上 | I31: 待併入 Siliconomics
A32: asp27_C | B32: FY2027 平均售價年增（美元；情境 C） | C32: % | E32: 0 | G32: Assumed | H32: 同上 | I32: 待併入 Siliconomics
A33: asp28_A | B33: FY2028 平均售價年增（美元；情境 A） | C33: % | E33: 0.03 | G33: Assumed | H33: 同上 | I33: A＝漲價延續；C＝中國成熟製程擴產造成價格壓力；待併入 Siliconomics
A34: asp28_B | B34: FY2028 平均售價年增（美元；情境 B） | C34: % | E34: 0 | G34: Assumed | H34: 同上 | I34: 待併入 Siliconomics
A35: asp28_C | B35: FY2028 平均售價年增（美元；情境 C） | C35: % | E35: -0.06 | G35: Assumed | H35: 同上 | I35: 待併入 Siliconomics
A36: asp29_A | B36: FY2029 平均售價年增（美元；情境 A） | C36: % | E36: 0.02 | G36: Assumed | H36: 同上 | I36: A＝漲價延續；C＝中國成熟製程擴產造成價格壓力；待併入 Siliconomics
A37: asp29_B | B37: FY2029 平均售價年增（美元；情境 B） | C37: % | E37: 0 | G37: Assumed | H37: 同上 | I37: 待併入 Siliconomics
A38: asp29_C | B38: FY2029 平均售價年增（美元；情境 C） | C38: % | E38: -0.03 | G38: Assumed | H38: 同上 | I38: 待併入 Siliconomics
A39: asp_adj | B39: 售價水準調整（Sens 用；FY2027 起各年同乘 1＋x） | C39: % | D39: -0.03 | E39: 0 | F39: 0.03 | G39: Assumed | H39: 無 | I39: ±3%
A40: D. 新業務：AI 相關（先進封裝矽中介層、矽光子）與 Intel 12 奈米合作（美元營收；毛利以邊際貢獻率計）
A41: ai_26 | B41: FY2026 AI 相關營收（先進封裝、矽光子） | C41: US$B | E41: 0.3 | G41: Interested-party | H41: 科技新報 2026-10-06（摩根士丹利）：公司說 2026 年 AI 相關營收約 3 億美元（營收 3–5%）、2029 年 10 億美元 | I41: 公司未揭露金額與毛利率；本模型把它從晶圓營收拆出
A42: aig27_A | B42: FY2027 AI 相關營收年增（情境 A） | C42: % | E42: 0.6 | G42: Assumed | H42: Finsee 3Q26 財報摘要：先進封裝與矽光子客戶接洽「強勁」；公司 2029 年 AI 相關 10 億美元目標（大摩轉述） | I42: A 最有利、C 最不利
A43: aig27_B | B43: FY2027 AI 相關營收年增（情境 B） | C43: % | E43: 0.4 | G43: Assumed | H43: 同上 | I43: —
A44: aig27_C | B44: FY2027 AI 相關營收年增（情境 C） | C44: % | E44: 0.2 | G44: Assumed | H44: 同上 | I44: —
A45: aig_L | B45: FY2028–29 AI 相關營收年增（情境 A 路徑；B、C 再乘同字母顆數係數） | C45: % | E45: 0.45 | G45: Assumed | H45: Finsee 3Q26 財報摘要：先進封裝與矽光子客戶接洽「強勁」；公司 2029 年 AI 相關 10 億美元目標（大摩轉述） | I45: 情境 A 到 FY2029 約 US$1.0B（公司目標）
A46: ai_adj | B46: AI 相關營收係數（Sens 用；FY2027 起） | C46: x | D46: 0.7 | E46: 1 | F46: 1.3 | G46: Assumed | H46: 無 | I46: ±30%
A47: m_new | B47: 新業務（AI 相關、Intel 12 奈米）邊際貢獻率（毛利 ÷ 營收） | C47: % | D47: 0.35 | E47: 0.45 | F47: 0.55 | G47: Assumed | H47: 公司未揭露；先進封裝中介層、矽光子屬特殊製程 | I47: 成熟製程晶圓的現金成本以 FY2026 校準，新業務另計
A48: int_27 | B48: FY2027 Intel 12 奈米營收（試產） | C48: US$B | E48: 0 | G48: Assumed | H48: Finsee 3Q26 財報摘要：設計套件 2026 年底、2027 年試產（先前說法）；旺得富 2026-10-17：驗證中、未來幾年貢獻營收 | I48: 三情境相同
A49: int28_A | B49: FY2028 Intel 12 奈米營收（情境 A） | C49: US$B | E49: 0.25 | G49: Assumed | H49: Finsee 3Q26 財報摘要：設計套件 2026 年底、2027 年試產（先前說法）；旺得富 2026-10-17：驗證中、未來幾年貢獻營收 | I49: 營收分配方式未找到；A 最有利、C 最不利
A50: int28_B | B50: FY2028 Intel 12 奈米營收（情境 B） | C50: US$B | E50: 0.12 | G50: Assumed | H50: 同上 | I50: —
A51: int28_C | B51: FY2028 Intel 12 奈米營收（情境 C） | C51: US$B | E51: 0 | G51: Assumed | H51: 同上 | I51: —
A52: int29_A | B52: FY2029 Intel 12 奈米營收（情境 A） | C52: US$B | E52: 0.5 | G52: Assumed | H52: 同上 | I52: 營收分配方式未找到；A 最有利、C 最不利
A53: int29_B | B53: FY2029 Intel 12 奈米營收（情境 B） | C53: US$B | E53: 0.3 | G53: Assumed | H53: 同上 | I53: —
A54: int29_C | B54: FY2029 Intel 12 奈米營收（情境 C） | C54: US$B | E54: 0.08 | G54: Assumed | H54: 同上 | I54: —
A55: E. 成本：折舊（銷貨成本內）、每片現金成本、營業費用、營業外、稅、股數
A56: da_tot26 | B56: FY2026 折舊與攤銷（全公司） | C56: NT$B | E56: =46.81/3*4 -> 62.413333 | G56: Derived | H56: Finsee 3Q26 財報摘要：9M26 折舊 468.1 億元（年增 12.7%）× 4／3 | I56: 第四季折舊：未找到，以前三季平均推估
A57: da_sh | B57: 折舊中計入銷貨成本的比例 | C57: % | E57: 0.9 | G57: Assumed | H57: 公司未揭露拆分；晶圓廠折舊多數計入銷貨成本 | I57: —
A58: dag_27 | B58: FY2027 銷貨成本內折舊年增 | C58: % | E58: 0.12 | G58: Assumed | H58: 公司財務長：未來 1–2 年折舊與原物料成本上升（優分析 2026-10-28） | I58: 三情境相同（擴產已核准）
A59: dag_28 | B59: FY2028 銷貨成本內折舊年增 | C59: % | E59: 0.1 | G59: Assumed | H59: 同上；P4、台南新廠 | I59: 三情境相同（擴產已核准）
A60: dag_29 | B60: FY2029 銷貨成本內折舊年增 | C60: % | E60: 0.08 | G60: Assumed | H60: 同上 | I60: 三情境相同（擴產已核准）
A61: dag_adj | B61: 折舊年增調整（Sens 用；FY2027 起各年加減） | C61: pt | D61: -0.05 | E61: 0 | F61: 0.05 | G61: Assumed | H61: 無 | I61: ±5 個百分點
A62: cc_g | B62: 每片現金成本年增（FY2027 起） | C62: % | D62: 0 | E62: 0.02 | F62: 0.04 | G62: Assumed | H62: 原物料、電價、人力（Assumed） | I62: 每片現金成本為 FY2026 殘差（Derived），之後依本列成長
A63: phi | B63: 營業費用成長對營收成長的彈性 | C63: x | D63: 0.3 | E63: 0.5 | F63: 0.8 | G63: Assumed | H63: FY2025 營業費用 250.6 億、9M26 約 204.8 億（Q 頁） | I63: —
A64: g_opx_min | B64: 營業費用年增下限 | C64: % | E64: 0.03 | G64: Assumed | H64: 研發、新業務投入 | I64: —
A65: nonop_f | B65: 營業外淨額（FY2027 起每年） | C65: NT$B | D65: 2 | E65: 4 | F65: 8 | G65: Assumed | H65: FY2025 約 58 億、1Q26 約 54 億、3Q26 約 13 億（Q 頁 Derived） | I65: 2Q26 業外約 302 億（投資與股利收益，優分析）為一次性，不外推
A66: tax | B66: 有效稅率（FY2027 起） | C66: % | D66: 0.12 | E66: 0.15 | F66: 0.2 | G66: Assumed | H66: FY2025 約 16%、3Q26 約 18%（Q 頁 Derived） | I66: —
A67: sh_g | B67: 加權股數年變動 | C67: % | E67: 0 | G67: Assumed | H67: 3Q26 淨利 ÷ EPS 推得約 124.5 億股（Q 頁） | I67: 海外可轉債約 18 億美元（旺得富 2026-10-17）的轉換稀釋未建模：轉換價未找到
A68: F. FY2026 錨點（1Q、2Q26 實績＋3Q26＋4Q26 指引或假設）
A69: fx_26 | B69: FY2026 平均匯率 | C69: NT$/US$ | E69: 31.6 | G69: Assumed | H69: 公司：3Q26 營收 742.4 億元＝23.2 億美元（6-K，約 32.0）；2Q26 淨利換算約 31.5 | I69: 實際平均匯率：未找到
A70: q4_ship | B70: 4Q26 晶圓出貨季增 | C70: % | E70: 0.02 | G70: Interested-party | H70: 公司 4Q26 指引：出貨低個位數成長（6-K 2026-10-28） | I70: 取 2%
A71: q4_asp | B71: 4Q26 平均售價季變動（美元） | C71: % | E71: 0 | G71: Interested-party | H71: 公司 4Q26 指引：美元平均售價持穩 | I71: —
A72: q4_ut | B72: 4Q26 稼動率 | C72: % | E72: 0.92 | G72: Interested-party | H72: 公司 4Q26 指引：低 90% 區間 | I72: 取 92%
A73: q4_gm | B73: 4Q26 毛利率 | C73: % | E73: 0.34 | G73: Interested-party | H73: 公司 4Q26 指引：與上季相當（3Q26 34.0%） | I73: —
A74: q4_opx | B74: 4Q26 營業費用（3Q26 × 1.03） | C74: NT$B | E74: =Q!E11*1.03 -> 6.75886 | G74: Assumed | H74: 3Q26 營業費用（Q 頁） | I74: —
A75: q4_nonop | B75: 4Q26 營業外淨額 | C75: NT$B | E75: 1.5 | G75: Assumed | H75: 3Q26 約 12.7 億（Q 頁） | I75: —
A76: q4_tax | B76: 4Q26 有效稅率 | C76: % | E76: 0.17 | G76: Assumed | H76: 3Q26 約 17.7%（Q 頁） | I76: —
A77: q_sh | B77: 加權股數（3Q26） | C77: 十億股 | E77: =Q!E19 -> 12.45 | G77: Derived | H77: 3Q26 淨利 ÷ EPS | I77: stockanalysis 流通股數 125.8 億股
A78: G. 公司說法、共識與券商（只作 Recon 對帳，不作校準）
A79: cons_rev26 | B79: 共識營收 FY2026（只作對照，不進模型） | C79: NT$B | E79: 283.2 | G79: Interested-party | H79: stockanalysis.comforecast/（21 位；2026-10-08 擷取，早於 3Q26 財報） | I79: 區間 271.5–291.8；FY2027 起共識為付費資料：未找到
A80: cons_eps26 | B80: 共識 EPS FY2026（只作對照，不進模型） | C80: NT$ | E80: 7.02 | G80: Interested-party | H80: stockanalysis.comforecast/（2026-10-08 擷取） | I80: 區間 4.55–8.15
A81: us_eps26 | B81: 美系外資 FY2026 EPS（中點） | C81: NT$ | E81: 7.57 | G81: Interested-party | H81: 旺得富 2026-10-17：7.46–7.68 | I81: 目標價 130
A82: loc_eps27 | B82: 本土投顧 FY2027 EPS | C82: NT$ | E82: 9.2 | G82: Interested-party | H82: 旺得富 2026-10-17 | I82: 目標價 185（強力買進）；FY2027 共識：未找到
A83: co_asp27 | B83: 公司：FY2027 平均售價年增約一成 | C83: % | E83: 0.1 | G83: Interested-party | H83: 優分析 2026-10-28（3Q26 法說轉述） | I83: —
A84: co_ai29 | B84: 公司：FY2029 AI 相關營收約 10 億美元 | C84: US$B | E84: 1 | G84: Interested-party | H84: 科技新報 2026-10-06（摩根士丹利） | I84: 大摩轉述
A85: H. 價格與市場倍數
A86: px | B86: 股價（2026-10-22 收盤） | C86: NT$ | E86: 125.5 | G86: Interested-party | H86: stockanalysis.comhistory/：10-22 收盤 125.50 | I86: 10-23 以後收盤：未找到（stockanalysis 歷史頁只到 10-22；10-28 法說後股價未取得）
A87: pe_ttm | B87: 近 12 月 P/E（現價 ÷ 近 12 月 EPS 6.81） | C87: x | E87: =px/6.81 -> 18.428781 | G87: Derived | H87: 4Q25 0.81＋1Q–3Q26 6.00（公司 6-K）；含 2Q26 一次性業外 | I87: —
A88: fpe | B88: 前瞻 P/E（stockanalysis，2026-10-22；股價 125.5） | C88: x | E88: 20.22 | G88: Interested-party | H88: stockanalysis.com | I88: —
A89: cons_feps | B89: 共識前瞻 12 月 EPS（2026-10-22 股價 ÷ 前瞻 P/E） | C89: NT$ | E89: =125.5/fpe -> 6.206726 | G89: Derived | H89: stockanalysis 前瞻 P/E 20.22（股價 125.5） | I89: 共識前瞻 EPS 的直接數字：未找到
A90: cons_tp | B90: 市場共識目標價（賣方平均） | C90: NT$ | E90: 140.69 | G90: Interested-party | H90: stockanalysis：25 位分析師平均 140.69（2026-10-08 擷取；中位數 135、區間 41–258） | I90: 旺得富 2026-10-17：法人目標價 130–185；FactSet 共識均值 84（口徑不同，未採用）
A91: nim_5 | B91: 近五年平均淨利率（FY2021–25；對照用） | C91: % | E91: =AVERAGE(51.246/213.011,89.479/278.705,60.99/222.533,47.211/232.303,41.716/237.553) -> 0.24290819 | G91: Derived | H91: stockanalysis 財報頁：FY2021–25 營收與淨利 | I91: 十年平均（2016–2025）：未找到（2016–2020 未取得）；收斂法依工作單改用最後一年 × 0.8
A92: I. 目標價與收斂法參數（黃底；Assumed，Andy 可改）
A93: tp_wA | B93: 目標價情境權重 A（A 順利／B 平平／C 不如預期） | C93: % | E93: 0.3 | G93: Assumed | H93: Andy 可改（工作單 2026-10-25 預設 A 0.3／B 0.5／C 0.2） | I93: 三者合計應為 100%
A94: tp_wB | B94: 目標價情境權重 B（A 順利／B 平平／C 不如預期） | C94: % | E94: 0.5 | G94: Assumed | H94: Andy 可改（工作單 2026-10-25 預設 A 0.3／B 0.5／C 0.2） | I94: 三者合計應為 100%
A95: tp_wC | B95: 目標價情境權重 C（A 順利／B 平平／C 不如預期） | C95: % | E95: 0.2 | G95: Assumed | H95: Andy 可改（工作單 2026-10-25 預設 A 0.3／B 0.5／C 0.2） | I95: 三者合計應為 100%
A96: tp_r | B96: 折現率／要求報酬 | C96: % | E96: 0.1 | G96: Assumed | H96: Andy 可改（工作單預設 10%） | I96: 美、台、日、韓同一值
A97: tp_g | B97: 長期成長率 | C97: % | E97: 0.04 | G97: Assumed | H97: Andy 可改（工作單預設 4%） | I97: 永續成長與 FY2032 收斂目標（情境 B）
A98: tp_roe | B98: ROE（近三年平均，FY2023–25） | C98: % | E98: =AVERAGE(0.1801,0.1277,0.1096) -> 0.13913333 | G98: Derived | H98: stockanalysis 比率頁：FY2023 18.01%、FY2024 12.77%、FY2025 10.96% | I98: 單一來源
A99: tp_w_dcf | B99: 目標價中 DCF 的權重；其餘為 Comparable | C99: % | E99: 0.5 | G99: Assumed | H99: Andy 可改（2026-10-25 11:53 定 DCF／Comparable 各半） | I99: —
A100: fade_gA | B100: 情境 A：FY2032 營收年增收斂目標（tp_g＋2pt） | C100: % | E100: =tp_g+0.02 -> 0.06 | G100: Assumed | H100: 工作單 2026-10-25 11:20 收斂法 | I100: FY2030 起由 FY2029 年增線性收斂
...

Sheet Q
A1: Q — 實績與 FY2026 錨點（十億新台幣；EPS 為新台幣、基本；股數為十億股；晶圓為千片 12 吋約當）。藍字＝輸入（公司 6-K、stockanalysis）；黑字＝公式
A2: FY2026 錨點＝1Q、2Q、3Q26 實績（3Q26 財報 2026-10-28 公布；季值＝累計 − 上半年）＋4Q26 公司指引（出貨低個位數成長、售價持穩、毛利率與上季相當、稼動率低 90%）
A3: 項目 | B3: FY2025A | C3: 1Q26（實績） | D3: 2Q26（實績） | E3: 3Q26（實績） | F3: 4Q26（模型） | G3: FY2026 錨點 | H3: 標記 | I3: 來源1 | J3: 來源2／說明
A4: 營收 | B4: 237.553 | C4: 61.038 | D4: =129.771-C4 -> 68.733 | E4: =204.01-129.771 -> 74.239 | F4: =E4*(1+q4_ship)*(1+q4_asp) -> 75.72378 | G4: =SUM(C4:F4) -> 279.73378 | H4: Verified／Interested-party（4Q 指引） | I4: 公司 6-K：FY2025 與 4Q25（2026-01-28）、1Q26、2Q26（2026-07-29）、3Q26（2026-10-28）；FY2025 損益：stockanalysis 財報頁 | J4: 1H26 1,297.71 億、9M26 2,040.10 億（6-K）；4Q26＝3Q26 ×（1＋出貨季增）×（1＋售價變動）
A5: 晶圓出貨（千片，12 吋約當） | C5: =D5/(1+0.106) -> 1011.1752 | D5: =E5/(1+0.073) -> 1118.3597 | E5: 1200 | F5: =E5*(1+q4_ship) -> 1224 | G5: =SUM(C5:F5) -> 4553.5349 | H5: Interested-party／Derived | I5: 公司：3Q26 出貨超過 120 萬片 12 吋約當（創新高，季增 7.3%）；2Q26 季增 10.6%；1Q26 季增 2.7% | J5: 3Q26 取下限 1,200 千片；前兩季以季增率回推（Derived）
A6: 稼動率 | C6: 0.79 | D6: 0.85 | E6: 0.92 | F6: =q4_ut -> 0.92 | G6: =G5/G7 -> 0.87057878 | H6: Verified | I6: 公司 6-K：1Q26 79%、2Q26 85%、3Q26 92% | J6: FY2026 欄＝出貨合計 ÷ 產能合計
A7: 產能（千片，12 吋約當） | C7: =C5/C6 -> 1279.9686 | D7: =D5/D6 -> 1315.7173 | E7: =E5/E6 -> 1304.3478 | F7: =F5/F6 -> 1330.4348 | G7: =SUM(C7:F7) -> 5230.4685 | H7: Derived | I7: 出貨 ÷ 稼動率 | J7: 公司未揭露產能
A8: 平均售價（全部營收 ÷ 出貨；美元／片） | C8: =C4/C5/fx_26*1000000 -> 1910.2351 | D8: =D4/D5/fx_26*1000000 -> 1944.8974 | E8: =E4/E5/fx_26*1000000 -> 1957.7795 | F8: =F4/F5/fx_26*1000000 -> 1957.7795 | G8: =G4/G5/fx_26*1000000 -> 1944.0577 | H8: Derived | I8: 營收 ÷ 出貨 ÷ 匯率 | J8: 含 AI 相關營收；模型的成熟製程售價另扣 AI 相關（In 頁 asp_26）
A9: 毛利 | B9: 68.906 | C9: 17.818 | D9: =40.141-C9 -> 22.323 | E9: =65.346-40.141 -> 25.205 | F9: =F4*q4_gm -> 25.746085 | G9: =SUM(C9:F9) -> 91.092085 | H9: Verified／Interested-party（4Q 指引） | I9: 公司 6-K：FY2025 與 4Q25（2026-01-28）、1Q26、2Q26（2026-07-29）、3Q26（2026-10-28）；FY2025 損益：stockanalysis 財報頁 | J9: 1H26 毛利 401.41 億、9M26 653.46 億（6-K）
A10: 毛利率 | B10: =B9/B4 -> 0.2900658 | C10: =C9/C4 -> 0.29191651 | D10: =D9/D4 -> 0.32477849 | E10: =E9/E4 -> 0.33951158 | F10: =F9/F4 -> 0.34 | G10: =G9/G4 -> 0.32563849 | H10: Derived | I10: — | J10: 公司：1Q26 29.2%、2Q26 32.5%、3Q26 34.0%
A11: 營業費用 | B11: =B9-B12 -> 25.056 | C11: =C9-C12 -> 6.542 | D11: =D9-D12 -> 7.373 | E11: =E9-E12 -> 6.562 | F11: =q4_opx -> 6.75886 | G11: =SUM(C11:F11) -> 27.23586 | H11: Derived／Assumed | I11: 公司 6-K：FY2025 與 4Q25（2026-01-28）、1Q26、2Q26（2026-07-29）、3Q26（2026-10-28）；FY2025 損益：stockanalysis 財報頁 | J11: 毛利 − 營業利益
A12: 營業利益 | B12: 43.85 | C12: 11.276 | D12: =26.226-C12 -> 14.95 | E12: =44.869-26.226 -> 18.643 | F12: =F9-F11 -> 18.987225 | G12: =SUM(C12:F12) -> 63.856225 | H12: Verified／Derived | I12: 公司 6-K：FY2025 與 4Q25（2026-01-28）、1Q26、2Q26（2026-07-29）、3Q26（2026-10-28）；FY2025 損益：stockanalysis 財報頁 | J12: 1H26 262.26 億、9M26 448.69 億（6-K）
A13: 營業外淨額 | B13: =B14-B12 -> 5.805 | C13: =C14-C12 -> 5.368 | D13: =D14-D12 -> 30.236 | E13: =E14-E12 -> 1.268 | F13: =q4_nonop -> 1.5 | G13: =SUM(C13:F13) -> 38.372 | H13: Derived／Assumed | I13: 公司 6-K：FY2025 與 4Q25（2026-01-28）、1Q26、2Q26（2026-07-29）、3Q26（2026-10-28）；FY2025 損益：stockanalysis 財報頁 | J13: 稅前 − 營業利益；2Q26 含投資與股利收益約 302 億（優分析）
A14: 稅前利益 | B14: 49.655 | C14: 16.644 | D14: =61.83-C14 -> 45.186 | E14: =81.741-61.83 -> 19.911 | F14: =F12+F13 -> 20.487225 | G14: =SUM(C14:F14) -> 102.22823 | H14: Verified／Derived | I14: 公司 6-K：FY2025 與 4Q25（2026-01-28）、1Q26、2Q26（2026-07-29）、3Q26（2026-10-28）；FY2025 損益：stockanalysis 財報頁 | J14: FY2025 由 stockanalysis 稅前淨利率推得；1H26 618.30 億、9M26 817.41 億（6-K）
A15: 所得稅 | B15: =B14-B17-B18 -> 7.939 | C15: =C14-C17-C18 -> 0.527 | D15: =D14-D17-D18 -> 2.962 | E15: =E14-E17-E18 -> 3.522 | F15: =F14*q4_tax -> 3.4828283 | G15: =SUM(C15:F15) -> 10.493828 | H15: Derived／Assumed | I15: 公司 6-K：FY2025 與 4Q25（2026-01-28）、1Q26、2Q26（2026-07-29）、3Q26（2026-10-28）；FY2025 損益：stockanalysis 財報頁 | J15: 稅前 −（歸屬母公司淨利＋非控制權益）
A16: 有效稅率 | B16: =B15/B14 -> 0.15988319 | C16: =C15/C14 -> 0.031663062 | D16: =D15/D14 -> 0.065551277 | E16: =E15/E14 -> 0.17688715 | F16: =F15/F14 -> 0.17 | G16: =G15/G14 -> 0.10265099 | H16: Derived | I16: — | J16: —
A17: 歸屬母公司淨利 | B17: 41.716 | C17: 16.171 | D17: =58.431-C17 -> 42.26 | E17: =74.865-58.431 -> 16.434 | F17: =F14-F15-F18 -> 17.004397 | G17: =SUM(C17:F17) -> 91.869397 | H17: Verified／Derived | I17: 公司 6-K：FY2025 與 4Q25（2026-01-28）、1Q26、2Q26（2026-07-29）、3Q26（2026-10-28）；FY2025 損益：stockanalysis 財報頁 | J17: 1H26 584.31 億、9M26 748.65 億（6-K）
A18: 非控制權益 | B18: 0 | C18: =16.117-C17 -> -0.054 | D18: =(58.341-16.117)-D17 -> -0.036 | E18: =(74.73-58.341)-E17 -> -0.045 | F18: 0 | G18: =SUM(C18:F18) -> -0.135 | H18: Derived／Assumed | I18: 公司 6-K：FY2025 與 4Q25（2026-01-28）、1Q26、2Q26（2026-07-29）、3Q26（2026-10-28）；FY2025 損益：stockanalysis 財報頁 | J18: 本期淨利（含非控制權益）− 歸屬母公司；1H26 本期淨利 583.41 億、9M26 747.30 億；FY2025 未找到，取 0
A19: 加權股數（十億股） | B19: =41.716/3.34 -> 12.48982 | C19: =16.171/1.29 -> 12.535659 | D19: =42.26/3.39 -> 12.466077 | E19: =16.434/1.32 -> 12.45 | F19: =q_sh -> 12.45 | G19: =AVERAGE(C19:F19) -> 12.475434 | H19: Derived | I19: 淨利 ÷ EPS（公司） | J19: —
A20: EPS（基本） | B20: =B17/B19 -> 3.34 | C20: =C17/C19 -> 1.29 | D20: =D17/D19 -> 3.39 | E20: =E17/E19 -> 1.32 | F20: =F17/F19 -> 1.365815 | G20: =G17/G19 -> 7.3640242 | H20: Derived | I20: 淨利 ÷ 股數 | J20: —
A21: 公司揭露 EPS | B21: 3.34 | C21: 1.29 | D21: 3.39 | E21: 1.32 | H21: Verified | I21: 公司 6-K：FY2025 3.34（stockanalysis 3.31）、1Q26 1.29、2Q26 3.39、3Q26 1.32 | J21: 9M26 6.00
A23: FY2026 錨點的檢查（參考；校準未使用券商數字）
A24: FY2026 營收年增 | B24: =G4/B4-1 -> 0.17756366
A25: 3Q26 營收季增（公司 8.0%） | B25: =E4/D4-1 -> 0.080107081
A26: FY2026 毛利率 | B26: =G10 -> 0.32563849
A27: FY2026 營業利益率 | B27: =G12/G4 -> 0.22827499
A28: 檢查：9M26 EPS 自算 − 公司 6.00（應約為 0） | B28: =SUM(C20:E20)-6 -> 0
A29: 檢查：9M26 營收 自算 − 公司 204.01（應約為 0） | B29: =SUM(C4:E4)-204.01 -> 0
A30: FY2026 EPS 不含 2Q26 一次性業外（業外以 3Q26 水準代入，稅率 17%；參考） | B30: =G20-(D13-E13)*(1-0.17)/G19 -> 5.4367614
A34: 官方報告分部與製程別（最近完整年度＋最近四季 4Q25–3Q26；分部原則第 3 條）
A35: 項目 | B35: FY2025A | C35: 4Q25 | D35: 1Q26 | E35: 2Q26 | F35: 3Q26 | G35: 最近四季合計 | H35: 標記 | I35: 來源1 | J35: 來源2／說明
A36: 晶圓代工營收（單一主要部門） | B36: 237.553 | C36: 61.81 | D36: =C4 -> 61.038 | E36: =D4 -> 68.733 | F36: =E4 -> 74.239 | G36: =SUM(C36:F36) -> 265.82 | H36: Verified | I36: 公司 6-K 各季合併營收；20-F 部門資訊以晶圓製造為主要部門 | J36: 其他部門金額：未找到（本模型併入晶圓代工）
A37: 22／28 奈米 | C37: =C36*0.36 -> 22.2516 | D37: =D36*0.34 -> 20.75292 | E37: =E36*0.37 -> 25.43121 | F37: =F36*0.35 -> 25.98365 | G37: =SUM(C37:F37) -> 94.41938 | H37: Verified | I37: 公司 6-K：22／28 奈米占營收 4Q25 36%、1Q26 34%、2Q26 37%、3Q26 35% | J37: FY2025 全年比重：未找到
A38: 其他製程（14 奈米與 40 奈米以上） | C38: =C36-C37 -> 39.5584 | D38: =D36-D37 -> 40.28508 | E38: =E36-E37 -> 43.30179 | F38: =F36-F37 -> 48.25535 | G38: =G36-G37 -> 171.40062 | H38: Derived | I38: 差額 | J38: 40 奈米以上各製程比重：未找到
A39: 檢查：分部合計 − 合併營收 | B39: =B36-B4 -> 0 | C39: =C36-61.81 -> 0 | D39: =D36-C4 -> 0 | E39: =E36-D4 -> 0 | F39: =F36-E4 -> 0 | H39: Derived | I39: — | J39: 應為 0
A40: 檢查：子列合計 − 分部 | C40: =C37+C38-C36 -> 0 | D40: =D37+D38-D36 -> 0 | E40: =E37+E38-E36 -> 0 | F40: =F37+F38-F36 -> 0 | G40: =G37+G38-G36 -> 0 | H40: Derived | I40: — | J40: 應為 0

Sheet Units
A1: Units — 聯電成熟製程晶圓（千片 12 吋約當）、稼動率、售價與新業務（三情境）。產能 FY2026 由出貨 ÷ 稼動率推得；AI 相關營收 FY2028–29 乘 Siliconomics 同字母顆數係數
A3: 項目 | B3: 單位 | C3: FY2026 | D3: FY2027 | E3: FY2028 | F3: FY2029 | G3: 說明
A4: 1. 成熟製程晶圓：三情境稼動率、出貨與售價
A5: 稼動率（情境 A） | B5: % | C5: =PL!D64 -> 0.87057878 | D5: =PL!E64 -> 0.95 | E5: =PL!F64 -> 0.94 | F5: =PL!G64 -> 0.93 | G5: PL 頁各情境推導區塊
A6: 稼動率（情境 B） | B6: % | C6: =PL!D103 -> 0.87057878 | D6: =PL!E103 -> 0.9 | E6: =PL!F103 -> 0.87 | F6: =PL!G103 -> 0.88 | G6: 同上
A7: 稼動率（情境 C） | B7: % | C7: =PL!D142 -> 0.87057878 | D7: =PL!E142 -> 0.82 | E7: =PL!F142 -> 0.76 | F7: =PL!G142 -> 0.8 | G7: 同上
A8: 晶圓出貨（情境 A） | B8: 千片 | C8: =PL!D65 -> 4553.5349 | D8: =PL!E65 -> 5167.7029 | E8: =PL!F65 -> 5471.2374 | F8: =PL!G65 -> 5791.9451 | G8: PL 頁各情境推導區塊
A9: 晶圓出貨（情境 B） | B9: 千片 | C9: =PL!D104 -> 4553.5349 | D9: =PL!E104 -> 4895.7185 | E9: =PL!F104 -> 5063.8049 | F9: =PL!G104 -> 5480.5502 | G9: 同上
A10: 晶圓出貨（情境 C） | B10: 千片 | C10: =PL!D143 -> 4553.5349 | D10: =PL!E143 -> 4460.5436 | E10: =PL!F143 -> 4423.5537 | F10: =PL!G143 -> 4982.3184 | G10: 同上
A11: 平均售價（美元）（情境 A） | B11: US$/片 | C11: =PL!D66 -> 1878.1749 | D11: =PL!E66 -> 2065.9924 | E11: =PL!F66 -> 2127.9721 | F11: =PL!G66 -> 2170.5316 | G11: PL 頁各情境推導區塊
A12: 平均售價（美元）（情境 B） | B12: US$/片 | C12: =PL!D105 -> 1878.1749 | D12: =PL!E105 -> 1972.0836 | E12: =PL!F105 -> 1972.0836 | F12: =PL!G105 -> 1972.0836 | G12: 同上
A13: 平均售價（美元）（情境 C） | B13: US$/片 | C13: =PL!D144 -> 1878.1749 | D13: =PL!E144 -> 1878.1749 | E13: =PL!F144 -> 1765.4844 | F13: =PL!G144 -> 1712.5198 | G13: 同上
A14: 晶圓營收（情境 A） | B14: NT$B | C14: =PL!D69 -> 270.25378 | D14: =PL!E69 -> 341.64591 | E14: =PL!F69 -> 372.5645 | F14: =PL!G69 -> 402.29119 | G14: PL 頁各情境推導區塊
A15: 晶圓營收（情境 B） | B15: NT$B | C15: =PL!D108 -> 270.25378 | D15: =PL!E108 -> 308.95252 | E15: =PL!F108 -> 319.55989 | F15: =PL!G108 -> 345.8593 | G15: 同上
A16: 晶圓營收（情境 C） | B16: NT$B | C16: =PL!D147 -> 270.25378 | D16: =PL!E147 -> 268.08579 | E16: =PL!F147 -> 249.91088 | F16: =PL!G147 -> 273.03421 | G16: 同上
A18: 2. 新業務：AI 相關與 Intel 12 奈米（三情境）
A19: AI 相關營收（美元）（情境 A） | B19: US$B | C19: =PL!D71 -> 0.3 | D19: =PL!E71 -> 0.48 | E19: =PL!F71 -> 0.696 | F19: =PL!G71 -> 1.0092 | G19: PL 頁各情境推導區塊
A20: AI 相關營收（美元）（情境 B） | B20: US$B | C20: =PL!D110 -> 0.3 | D20: =PL!E110 -> 0.42 | E20: =PL!F110 -> 0.4872 | F20: =PL!G110 -> 0.7505925 | G20: 同上
A21: AI 相關營收（美元）（情境 C） | B21: US$B | C21: =PL!D149 -> 0.3 | D21: =PL!E149 -> 0.36 | E21: =PL!F149 -> 0.3132 | F21: =PL!G149 -> 0.45414 | G21: 同上
A22: AI 相關 ÷ 營收（情境 A） | B22: % | C22: =PL!D76 -> 0.033889364 | D22: =PL!E76 -> 0.043024498 | E22: =PL!F76 -> 0.055287939 | F22: =PL!G76 -> 0.071672066 | G22: PL 頁各情境推導區塊
A23: AI 相關 ÷ 營收（情境 B） | B23: % | C23: =PL!D115 -> 0.033889364 | D23: =PL!E115 -> 0.041688312 | E23: =PL!F115 -> 0.045990698 | F23: =PL!G115 -> 0.063294693 | G23: 同上
A24: AI 相關 ÷ 營收（情境 C） | B24: % | C24: =PL!D154 -> 0.033889364 | D24: =PL!E154 -> 0.041200864 | E24: =PL!F154 -> 0.038557587 | F24: =PL!G154 -> 0.050090118 | G24: 同上
A25: Intel 12 奈米營收（美元）（情境 A） | B25: US$B | C25: =PL!D73 -> 0 | D25: =PL!E73 -> 0 | E25: =PL!F73 -> 0.25 | F25: =PL!G73 -> 0.5 | G25: PL 頁各情境推導區塊
A26: Intel 12 奈米營收（美元）（情境 B） | B26: US$B | C26: =PL!D112 -> 0 | D26: =PL!E112 -> 0 | E26: =PL!F112 -> 0.12 | F26: =PL!G112 -> 0.3 | G26: 同上
A27: Intel 12 奈米營收（美元）（情境 C） | B27: US$B | C27: =PL!D151 -> 0 | D27: =PL!E151 -> 0 | E27: =PL!F151 -> 0 | F27: =PL!G151 -> 0.08 | G27: 同上
A29: 3. 校準值（只用 FY2026 已發生的實績與錨點；不用共識、不用 FY2027 起的目標）
A30: FY2026 平均售價（美元／片） | C30: =PL!D66 -> 1878.1749 | G30: 晶圓營收 ÷ 出貨 ÷ 匯率
A31: FY2026 每片現金成本（NT$K） | C31: =PL!D80 -> 27.946573 | G31: 讓 FY2026 毛利等於錨點
A32: FY2026 銷貨成本內折舊（NT$B） | C32: =PL!D79 -> 56.172 | G32: 全公司折舊 × da_sh
A34: 讀法：聯電 EPS 主要由稼動率與美元售價決定；AI 相關（先進封裝矽中介層、矽光子）與 Intel 12 奈米在 FY2029 合計仍低於營收一成，影響在情境 A 的上緣。

Sheet PL
A1: PL — 聯電損益（十億新台幣；EPS 新台幣、基本；歸屬母公司）。FY2025A 實績、FY2026 錨點（三情境相同），FY2027–FY2029 由驅動因子推導，FY2030–FY2032 為收斂法。FY(t)＝CY(t)。三情境各一個完整推導區塊（本頁下方），頂端為摘要
A2: 灰底＝FY2030–FY2032 收斂法（上游顆數只到 CY2029）：營收年增線性收斂到 fade_g、淨利率線性收斂到 fade_m（In 頁 I 節），非驅動因子推導
A3: 情境／項目 | B3: 單位 | C3: FY2025A | D3: FY2026（錨點） | E3: FY2027 | F3: FY2028 | G3: FY2029 | H3: FY2030（收斂） | I3: FY2031（收斂） | J3: FY2032（收斂） | K3: 說明
A4: 情境 A
A5: 營收 | B5: NT$B | C5: =C75 -> 237.553 | D5: =D75 -> 279.73378 | E5: =E75 -> 357.00591 | F5: =F75 -> 402.8365 | G5: =G75 -> 450.58559 | H5: =H75 -> 495.20322 | I5: =I75 -> 534.57719 | J5: =J75 -> 566.65182
A6: 營收年增 | B6: % | D6: =D77 -> 0.17756366 | E6: =E77 -> 0.27623453 | F6: =F77 -> 0.12837489 | G6: =G77 -> 0.11853217 | H6: =H77 -> 0.099021445 | I6: =I77 -> 0.079510722 | J6: =J77 -> 0.06
A7: 成熟製程晶圓營收（不含 AI 相關、Intel 12 奈米） | B7: NT$B | D7: =D69 -> 270.25378 | E7: =E69 -> 341.64591 | F7: =F69 -> 372.5645 | G7: =G69 -> 402.29119
A8: AI 相關營收 | B8: NT$B | D8: =D72 -> 9.48 | E8: =E72 -> 15.36 | F8: =F72 -> 22.272 | G8: =G72 -> 32.2944
A9: Intel 12 奈米營收 | B9: NT$B | D9: =D74 -> 0 | E9: =E74 -> 0 | F9: =F74 -> 8 | G9: =G74 -> 16
A10: 稼動率 | B10: % | D10: =D64 -> 0.87057878 | E10: =E64 -> 0.95 | F10: =F64 -> 0.94 | G10: =G64 -> 0.93
A11: 平均售價（美元） | B11: US$/片 | D11: =D66 -> 1878.1749 | E11: =E66 -> 2065.9924 | F11: =F66 -> 2127.9721 | G11: =G66 -> 2170.5316
A12: 毛利率 | B12: % | C12: =C84 -> 0.2900658 | D12: =D84 -> 0.32563849 | E12: =E84 -> 0.387493 | F12: =F84 -> 0.3919789 | G12: =G84 -> 0.39395624
A13: 營業利益率 | B13: % | C13: =C87 -> 0.18459039 | D13: =D87 -> 0.22827499 | E13: =E87 -> 0.30066642 | F13: =F87 -> 0.31009144 | G13: =G87 -> 0.31640763
A14: 歸屬母公司淨利 | B14: NT$B | C14: =C92 -> 41.716 | D14: =D92 -> 91.869397 | E14: =E92 -> 94.638736 | F14: =F92 -> 109.57873 | G14: =G92 -> 124.58341 | H14: =H92 -> 136.91984 | I14: =I92 -> 147.80643 | J14: =J92 -> 156.67482
A15: 淨利率 | B15: % | C15: =C96 -> 0.17560713 | D15: =D96 -> 0.32841724 | E15: =E96 -> 0.26509011 | F15: =F96 -> 0.27201787 | G15: =G96 -> 0.27649222 | H15: =H96 -> 0.27649222 | I15: =I96 -> 0.27649222 | J15: =J96 -> 0.27649222
A16: EPS | B16: NT$ | C16: =C94 -> 3.34 | D16: =D94 -> 7.3640242 | E16: =E94 -> 7.6015049 | F16: =F94 -> 8.8015043 | G16: =G94 -> 10.0067 | H16: =H94 -> 10.997577 | I16: =I94 -> 11.872003 | J16: =J94 -> 12.584323
A17: EPS 年增 | B17: % | D17: =D95 -> 1.2047977 | E17: =E95 -> 0.032248772 | F17: =F95 -> 0.15786339 | G17: =G95 -> 0.13693061 | H17: =H95 -> 0.099021445 | I17: =I95 -> 0.079510722 | J17: =J95 -> 0.06
A19: 情境 B
A20: 營收 | B20: NT$B | C20: =C114 -> 237.553 | D20: =D114 -> 279.73378 | E20: =E114 -> 322.39252 | F20: =F114 -> 338.99029 | G20: =G114 -> 379.47826 | H20: =H114 -> 414.75379 | I20: =I114 -> 442.32621 | J20: =J114 -> 460.01925
A21: 營收年增 | B21: % | D21: =D116 -> 0.17756366 | E21: =E116 -> 0.15249764 | F21: =F116 -> 0.051483111 | G21: =G116 -> 0.11943697 | H21: =H116 -> 0.092957977 | I21: =I116 -> 0.066478989 | J21: =J116 -> 0.04
A22: 成熟製程晶圓營收（不含 AI 相關、Intel 12 奈米） | B22: NT$B | D22: =D108 -> 270.25378 | E22: =E108 -> 308.95252 | F22: =F108 -> 319.55989 | G22: =G108 -> 345.8593
A23: AI 相關營收 | B23: NT$B | D23: =D111 -> 9.48 | E23: =E111 -> 13.44 | F23: =F111 -> 15.5904 | G23: =G111 -> 24.01896
A24: Intel 12 奈米營收 | B24: NT$B | D24: =D113 -> 0 | E24: =E113 -> 0 | F24: =F113 -> 3.84 | G24: =G113 -> 9.6
A25: 稼動率 | B25: % | D25: =D103 -> 0.87057878 | E25: =E103 -> 0.9 | F25: =F103 -> 0.87 | G25: =G103 -> 0.88
A26: 平均售價（美元） | B26: US$/片 | D26: =D105 -> 1878.1749 | E26: =E105 -> 1972.0836 | F26: =F105 -> 1972.0836 | G26: =G105 -> 1972.0836
A27: 毛利率 | B27: % | C27: =C123 -> 0.2900658 | D27: =D123 -> 0.32563849 | E27: =E123 -> 0.34905573 | F27: =F123 -> 0.32999892 | G27: =G123 -> 0.32600088
A28: 營業利益率 | B28: % | C28: =C126 -> 0.18459039 | D28: =D126 -> 0.22827499 | E28: =E126 -> 0.25813376 | F28: =F126 -> 0.2409346 | G28: =G126 -> 0.24168787
A29: 歸屬母公司淨利 | B29: NT$B | C29: =C131 -> 41.716 | D29: =D131 -> 91.869397 | E29: =E131 -> 74.137334 | F29: =F131 -> 72.823316 | G29: =G131 -> 81.357997 | H29: =H131 -> 85.956843 | I29: =I131 -> 88.510092 | J29: =J131 -> 88.762978
A30: 淨利率 | B30: % | C30: =C135 -> 0.17560713 | D30: =D135 -> 0.32841724 | E30: =E135 -> 0.22995984 | F30: =F135 -> 0.2148242 | G30: =G135 -> 0.21439436 | H30: =H135 -> 0.20724788 | I30: =I135 -> 0.2001014 | J30: =J135 -> 0.19295492
A31: EPS | B31: NT$ | C31: =C133 -> 3.34 | D31: =D133 -> 7.3640242 | E31: =E133 -> 5.9548059 | F31: =F133 -> 5.8492624 | G31: =G133 -> 6.5347789 | H31: =H133 -> 6.9041641 | I31: =I133 -> 7.1092444 | J31: =J133 -> 7.1295565
A32: EPS 年增 | B32: % | D32: =D134 -> 1.2047977 | E32: =E134 -> -0.19136524 | F32: =F134 -> -0.0177241 | G32: =G134 -> 0.11719709 | H32: =H134 -> 0.056526045 | I32: =I134 -> 0.029703851 | J32: =J134 -> 0.0028571429
A34: 情境 C
A35: 營收 | B35: NT$B | C35: =C153 -> 237.553 | D35: =D153 -> 279.73378 | E35: =E153 -> 279.60579 | F35: =F153 -> 259.93328 | G35: =G153 -> 290.12669 | H35: =H153 -> 314.52795 | I35: =I153 -> 330.90001 | J35: =J153 -> 337.51801
A36: 營收年增 | B36: % | D36: =D155 -> 0.17756366 | E36: =E155 -> -0.00045755998 | F36: =F155 -> -0.070358017 | G36: =G155 -> 0.11615832 | H36: =H155 -> 0.084105547 | I36: =I155 -> 0.052052773 | J36: =J155 -> 0.02
A37: 成熟製程晶圓營收（不含 AI 相關、Intel 12 奈米） | B37: NT$B | D37: =D147 -> 270.25378 | E37: =E147 -> 268.08579 | F37: =F147 -> 249.91088 | G37: =G147 -> 273.03421
A38: AI 相關營收 | B38: NT$B | D38: =D150 -> 9.48 | E38: =E150 -> 11.52 | F38: =F150 -> 10.0224 | G38: =G150 -> 14.53248
A39: Intel 12 奈米營收 | B39: NT$B | D39: =D152 -> 0 | E39: =E152 -> 0 | F39: =F152 -> 0 | G39: =G152 -> 2.56
A40: 稼動率 | B40: % | D40: =D142 -> 0.87057878 | E40: =E142 -> 0.82 | F40: =F142 -> 0.76 | G40: =G142 -> 0.8
A41: 平均售價（美元） | B41: US$/片 | D41: =D144 -> 1878.1749 | E41: =E144 -> 1878.1749 | F41: =F144 -> 1765.4844 | G41: =G144 -> 1712.5198
A42: 毛利率 | B42: % | C42: =C162 -> 0.2900658 | D42: =D162 -> 0.32563849 | E42: =E162 -> 0.2975872 | F42: =F162 -> 0.21774631 | G42: =G162 -> 0.20068599
A43: 營業利益率 | B43: % | C43: =C165 -> 0.18459039 | D43: =D165 -> 0.22827499 | E43: =E165 -> 0.19725688 | F43: =F165 -> 0.106585 | G43: =G165 -> 0.095308946
A44: 歸屬母公司淨利 | B44: NT$B | C44: =C170 -> 41.716 | D44: =D170 -> 91.869397 | E44: =E170 -> 50.281041 | F44: =F170 -> 26.94924 | G44: =G170 -> 26.903919 | H44: =H170 -> 27.222242 | I44: =I170 -> 26.593575 | J44: =J170 -> 25.038874
A45: 淨利率 | B45: % | C45: =C174 -> 0.17560713 | D45: =D174 -> 0.32841724 | E45: =E174 -> 0.17982833 | F45: =F174 -> 0.10367753 | G45: =G174 -> 0.092731623 | H45: =H174 -> 0.086549515 | I45: =I174 -> 0.080367406 | J45: =J174 -> 0.074185298
A46: EPS | B46: NT$ | C46: =C172 -> 3.34 | D46: =D172 -> 7.3640242 | E46: =E172 -> 4.0386378 | F46: =F172 -> 2.1645976 | G46: =G172 -> 2.1609573 | H46: =H172 -> 2.1865254 | I46: =I172 -> 2.1360301 | J46: =J172 -> 2.0111545
A47: EPS 年增 | B47: % | D47: =D173 -> 1.2047977 | E47: =E173 -> -0.45157189 | F47: =F173 -> -0.46402781 | G47: =G173 -> -0.0016817181 | H47: =H173 -> 0.011831843 | I47: =I173 -> -0.023093853 | J47: =J173 -> -0.058461538
A49: 核對（應為 0）：FY2026 模型 − 錨點
A50: 三情境：營收差（NT$B） | D50: =ABS(D75-a26_rev)+ABS(D114-a26_rev)+ABS(D153-a26_rev) -> 0
A51: 三情境：毛利差（NT$B） | D51: =ABS(D83-a26_gp)+ABS(D122-a26_gp)+ABS(D161-a26_gp) -> 0
A52: 三情境：EPS 差（NT$） | D52: =ABS(D94-a26_eps)+ABS(D133-a26_eps)+ABS(D172-a26_eps) -> 0
A60: 情境 A（順利）：稼動率 95%／94%／93%；售價 +10%／+3%／+2%（公司估 2027 年約一成）；AI 相關 FY2027 +60%、之後 +45% × 顆數 A；Intel 12 奈米 FY2028 2.5 億、FY2029 5 億美元
A61: 項目 | B61: 單位 | C61: FY2025A | D61: FY2026（錨點） | E61: FY2027 | F61: FY2028 | G61: FY2029 | H61: FY2030（收斂） | I61: FY2031（收斂） | J61: FY2032（收斂） | K61: 說明
A62: A. 成熟製程晶圓：產能 × 稼動率 × 平均售價（D 欄＝FY2026 校準年）
A63: 產能（12 吋約當） | B63: 千片 | D63: =cap_26 -> 5230.4685 | E63: =D63*(1+capg27)*cap_adj -> 5439.6873 | F63: =E63*(1+capg28) -> 5820.4654 | G63: =F63*(1+capg29) -> 6227.8979
A64: 平均稼動率 | B64: % | D64: =a26_ship/cap_26 -> 0.87057878 | E64: =MIN(0.98,ut27_A+ut_adj) -> 0.95 | F64: =MIN(0.98,ut28_A+ut_adj) -> 0.94 | G64: =MIN(0.98,ut29_A+ut_adj) -> 0.93
A65: 晶圓出貨（12 吋約當） | B65: 千片 | D65: =D63*D64 -> 4553.5349 | E65: =E63*E64 -> 5167.7029 | F65: =F63*F64 -> 5471.2374 | G65: =G63*G64 -> 5791.9451
A66: 平均售價（成熟製程晶圓） | B66: US$/片 | D66: =asp_26 -> 1878.1749 | E66: =D66*(1+asp27_A)*(1+asp_adj) -> 2065.9924 | F66: =E66*(1+asp28_A) -> 2127.9721 | G66: =F66*(1+asp29_A) -> 2170.5316
A67: 平均售價年增（美元） | B67: % | E67: =E66/D66-1 -> 0.1 | F67: =F66/E66-1 -> 0.03 | G67: =G66/F66-1 -> 0.02
A68: 匯率 | B68: NT$/US$ | D68: =fx_26 -> 31.6 | E68: =fx -> 32 | F68: =fx -> 32 | G68: =fx -> 32
A69: 成熟製程晶圓營收（不含 AI 相關、Intel 12 奈米） | B69: NT$B | D69: =D65*D66*D68/1000000 -> 270.25378 | E69: =E65*E66*E68/1000000 -> 341.64591 | F69: =F65*F66*F68/1000000 -> 372.5645 | G69: =G65*G66*G68/1000000 -> 402.29119
A70: B. 新業務：AI 相關（先進封裝矽中介層、矽光子）與 Intel 12 奈米（美元營收）
A71: AI 相關營收（美元；FY2028 起 × 同字母顆數係數） | B71: US$B | D71: =ai_26 -> 0.3 | E71: =D71*(1+aig27_A)*ai_adj -> 0.48 | F71: =E71*(1+aig_L)*um28_A -> 0.696 | G71: =F71/um28_A*(1+aig_L)*um29_A -> 1.0092
A72: AI 相關營收 | B72: NT$B | D72: =D71*D68 -> 9.48 | E72: =E71*E68 -> 15.36 | F72: =F71*F68 -> 22.272 | G72: =G71*G68 -> 32.2944
A73: Intel 12 奈米營收（美元） | B73: US$B | D73: =0 -> 0 | E73: =int_27 -> 0 | F73: =int28_A -> 0.25 | G73: =int29_A -> 0.5
A74: Intel 12 奈米營收 | B74: NT$B | D74: =D73*D68 -> 0 | E74: =E73*E68 -> 0 | F74: =F73*F68 -> 8 | G74: =G73*G68 -> 16
A75: 營收 | B75: NT$B | C75: =a25_rev -> 237.553 | D75: =D69+D72+D74 -> 279.73378 | E75: =E69+E72+E74 -> 357.00591 | F75: =F69+F72+F74 -> 402.8365 | G75: =G69+G72+G74 -> 450.58559 | H75: =G75*(1+H77) -> 495.20322 | I75: =H75*(1+I77) -> 534.57719 | J75: =I75*(1+J77) -> 566.65182 | K75: FY2030 起為收斂法：營收年增由 FY2029 線性收斂到 fade_g、淨利率收斂到 fade_m（FY2032 達到），非驅動因子推導
A76: AI 相關 ÷ 營收 | B76: % | D76: =D72/D75 -> 0.033889364 | E76: =E72/E75 -> 0.043024498 | F76: =F72/F75 -> 0.055287939 | G76: =G72/G75 -> 0.071672066
A77: 營收年增 | B77: % | D77: =D75/C75-1 -> 0.17756366 | E77: =E75/D75-1 -> 0.27623453 | F77: =F75/E75-1 -> 0.12837489 | G77: =G75/F75-1 -> 0.11853217 | H77: =$G77+(fade_gA-$G77)*1/3 -> 0.099021445 | I77: =$G77+(fade_gA-$G77)*2/3 -> 0.079510722 | J77: =$G77+(fade_gA-$G77)*3/3 -> 0.06
A78: C. 成本與損益
A79: 銷貨成本內折舊 | B79: NT$B | D79: =da_tot26*da_sh -> 56.172 | E79: =D79*(1+dag_27+dag_adj) -> 62.91264 | F79: =E79*(1+dag_28+dag_adj) -> 69.203904 | G79: =F79*(1+dag_29+dag_adj) -> 74.740216
A80: 每片現金成本（FY2026 殘差，之後年增 cc_g） | B80: NT$K/片 | D80: =(D75-a26_gp-D79-(1-m_new)*(D72+D74))/D65*1000 -> 27.946573 | E80: =D80*(1+cc_g) -> 28.505504 | F80: =E80*(1+cc_g) -> 29.075614 | G80: =F80*(1+cc_g) -> 29.657127 | K80: Derived：讓 FY2026 毛利等於錨點；含原物料、人力、電力等變動與固定現金成本
A81: 現金成本合計（每片 × 出貨） | B81: NT$B | D81: =D80*D65/1000 -> 127.25569 | E81: =E80*E65/1000 -> 147.30798 | F81: =F80*F65/1000 -> 159.07959 | G81: =G80*G65/1000 -> 171.77245
A82: 新業務毛利（邊際貢獻率 × AI 相關與 Intel 營收） | B82: NT$B | D82: =m_new*(D72+D74) -> 4.266 | E82: =m_new*(E72+E74) -> 6.912 | F82: =m_new*(F72+F74) -> 13.6224 | G82: =m_new*(G72+G74) -> 21.73248
A83: 毛利 | B83: NT$B | C83: =a25_gp -> 68.906 | D83: =D69-D79-D81+D82 -> 91.092085 | E83: =E69-E79-E81+E82 -> 138.33729 | F83: =F69-F79-F81+F82 -> 157.90341 | G83: =G69-G79-G81+G82 -> 177.511
A84: 毛利率 | B84: % | C84: =C83/C75 -> 0.2900658 | D84: =D83/D75 -> 0.32563849 | E84: =E83/E75 -> 0.387493 | F84: =F83/F75 -> 0.3919789 | G84: =G83/G75 -> 0.39395624
A85: 營業費用 | B85: NT$B | C85: =a25_opx -> 25.056 | D85: =a26_opx -> 27.23586 | E85: =D85*(1+MAX(g_opx_min,phi*E77)) -> 30.997602 | F85: =E85*(1+MAX(g_opx_min,phi*F77)) -> 32.987259 | G85: =F85*(1+MAX(g_opx_min,phi*G77)) -> 34.942285
A86: 營業利益 | B86: NT$B | C86: =C83-C85 -> 43.85 | D86: =D83-D85 -> 63.856225 | E86: =E83-E85 -> 107.33969 | F86: =F83-F85 -> 124.91615 | G86: =G83-G85 -> 142.56872
A87: 營業利益率 | B87: % | C87: =C86/C75 -> 0.18459039 | D87: =D86/D75 -> 0.22827499 | E87: =E86/E75 -> 0.30066642 | F87: =F86/F75 -> 0.31009144 | G87: =G86/G75 -> 0.31640763
A88: 營業外淨額 | B88: NT$B | C88: =a25_nonop -> 5.805 | D88: =a26_nonop -> 38.372 | E88: =nonop_f -> 4 | F88: =nonop_f -> 4 | G88: =nonop_f -> 4
A89: 稅前利益 | B89: NT$B | C89: =C86+C88 -> 49.655 | D89: =D86+D88 -> 102.22823 | E89: =E86+E88 -> 111.33969 | F89: =F86+F88 -> 128.91615 | G89: =G86+G88 -> 146.56872
A90: 所得稅 | B90: NT$B | C90: =a25_tax -> 7.939 | D90: =a26_tax -> 10.493828 | E90: =E89*tax -> 16.700953 | F90: =F89*tax -> 19.337423 | G90: =G89*tax -> 21.985308
A91: 非控制權益 | B91: NT$B | C91: =a25_mi -> 0 | D91: =a26_mi -> -0.135 | E91: =0 -> 0 | F91: =0 -> 0 | G91: =0 -> 0 | K91: FY2027 起假設為 0（歷史上接近 0）
A92: 歸屬母公司淨利 | B92: NT$B | C92: =C89-C90-C91 -> 41.716 | D92: =D89-D90-D91 -> 91.869397 | E92: =E89-E90-E91 -> 94.638736 | F92: =F89-F90-F91 -> 109.57873 | G92: =G89-G90-G91 -> 124.58341 | H92: =H75*H96 -> 136.91984 | I92: =I75*I96 -> 147.80643 | J92: =J75*J96 -> 156.67482
A93: 加權股數 | B93: 十億股 | C93: =a25_sh -> 12.48982 | D93: =a26_sh -> 12.475434 | E93: =q_sh*(1+sh_g) -> 12.45 | F93: =E93*(1+sh_g) -> 12.45 | G93: =F93*(1+sh_g) -> 12.45 | H93: =G93*(1+sh_g) -> 12.45 | I93: =H93*(1+sh_g) -> 12.45 | J93: =I93*(1+sh_g) -> 12.45
A94: EPS（基本） | B94: NT$ | C94: =C92/C93 -> 3.34 | D94: =D92/D93 -> 7.3640242 | E94: =E92/E93 -> 7.6015049 | F94: =F92/F93 -> 8.8015043 | G94: =G92/G93 -> 10.0067 | H94: =H92/H93 -> 10.997577 | I94: =I92/I93 -> 11.872003 | J94: =J92/J93 -> 12.584323
A95: EPS 年增 | B95: % | D95: =D94/C94-1 -> 1.2047977 | E95: =E94/D94-1 -> 0.032248772 | F95: =F94/E94-1 -> 0.15786339 | G95: =G94/F94-1 -> 0.13693061 | H95: =H94/G94-1 -> 0.099021445 | I95: =I94/H94-1 -> 0.079510722 | J95: =J94/I94-1 -> 0.06
A96: 淨利率（歸屬母公司淨利 ÷ 營收） | B96: % | C96: =C92/C75 -> 0.17560713 | D96: =D92/D75 -> 0.32841724 | E96: =E92/E75 -> 0.26509011 | F96: =F92/F75 -> 0.27201787 | G96: =G92/G75 -> 0.27649222 | H96: =$G96+(fade_mA-$G96)*1/3 -> 0.27649222 | I96: =$G96+(fade_mA-$G96)*2/3 -> 0.27649222 | J96: =$G96+(fade_mA-$G96)*3/3 -> 0.27649222
A99: 情境 B（平平）：稼動率 90%／87%／88%；售價 +5%／0／0；AI 相關 +40%、之後 × 顆數 B（0.8／0.85）；Intel 12 奈米 1.2 億、3 億美元
A100: 項目 | B100: 單位 | C100: FY2025A | D100: FY2026（錨點） | E100: FY2027 | F100: FY2028 | G100: FY2029 | H100: FY2030（收斂） | I100: FY2031（收斂） | J100: FY2032（收斂） | K100: 說明
A101: A. 成熟製程晶圓：產能 × 稼動率 × 平均售價（D 欄＝FY2026 校準年）
A102: 產能（12 吋約當） | B102: 千片 | D102: =cap_26 -> 5230.4685 | E102: =D102*(1+capg27)*cap_adj -> 5439.6873 | F102: =E102*(1+capg28) -> 5820.4654 | G102: =F102*(1+capg29) -> 6227.8979
A103: 平均稼動率 | B103: % | D103: =a26_ship/cap_26 -> 0.87057878 | E103: =MIN(0.98,ut27_B+ut_adj) -> 0.9 | F103: =MIN(0.98,ut28_B+ut_adj) -> 0.87 | G103: =MIN(0.98,ut29_B+ut_adj) -> 0.88
A104: 晶圓出貨（12 吋約當） | B104: 千片 | D104: =D102*D103 -> 4553.5349 | E104: =E102*E103 -> 4895.7185 | F104: =F102*F103 -> 5063.8049 | G104: =G102*G103 -> 5480.5502
A105: 平均售價（成熟製程晶圓） | B105: US$/片 | D105: =asp_26 -> 1878.1749 | E105: =D105*(1+asp27_B)*(1+asp_adj) -> 1972.0836 | F105: =E105*(1+asp28_B) -> 1972.0836 | G105: =F105*(1+asp29_B) -> 1972.0836
A106: 平均售價年增（美元） | B106: % | E106: =E105/D105-1 -> 0.05 | F106: =F105/E105-1 -> 0 | G106: =G105/F105-1 -> 0
A107: 匯率 | B107: NT$/US$ | D107: =fx_26 -> 31.6 | E107: =fx -> 32 | F107: =fx -> 32 | G107: =fx -> 32
A108: 成熟製程晶圓營收（不含 AI 相關、Intel 12 奈米） | B108: NT$B | D108: =D104*D105*D107/1000000 -> 270.25378 | E108: =E104*E105*E107/1000000 -> 308.95252 | F108: =F104*F105*F107/1000000 -> 319.55989 | G108: =G104*G105*G107/1000000 -> 345.8593
A109: B. 新業務：AI 相關（先進封裝矽中介層、矽光子）與 Intel 12 奈米（美元營收）
A110: AI 相關營收（美元；FY2028 起 × 同字母顆數係數） | B110: US$B | D110: =ai_26 -> 0.3 | E110: =D110*(1+aig27_B)*ai_adj -> 0.42 | F110: =E110*(1+aig_L)*um28_B -> 0.4872 | G110: =F110/um28_B*(1+aig_L)*um29_B -> 0.7505925
A111: AI 相關營收 | B111: NT$B | D111: =D110*D107 -> 9.48 | E111: =E110*E107 -> 13.44 | F111: =F110*F107 -> 15.5904 | G111: =G110*G107 -> 24.01896
A112: Intel 12 奈米營收（美元） | B112: US$B | D112: =0 -> 0 | E112: =int_27 -> 0 | F112: =int28_B -> 0.12 | G112: =int29_B -> 0.3
...

Sheet Val
A1: Val — P/E 估值（新台幣）。結論用「現價 ÷ FY2027、FY2028 EPS（模型）」；目標價＝DCF 與 Comparable 加權（第 0 節）；十年 P/E 規則值（第 3 節，年底落後 P/E）只作參考
A2: 循環位置：聯電不是設備股，不套設備市場見頂年；以本模型營收最高的會計年度為見頂年（比照創意、聯發科；FY(t)＝CY(t)）。營收到 FY2029 仍在增加時，見頂年未知，判為中段
A4: 0. 目標價
A5: 0.1 DCF（股東權益現金流，FY2027–FY2032 明確期＋FY2032 後永續）
A6: 項目 | B6: A（順利） | C6: B（平平） | D6: C（不如預期） | E6: 說明
A7: 情境 EPS（FY2027–FY2032） | E7: PL 頁各情境；FY2030 起為收斂法
A8: FY2027 | B8: =PL!E16 -> 7.6015049 | C8: =PL!E31 -> 5.9548059 | D8: =PL!E46 -> 4.0386378
A9: FY2028 | B9: =PL!F16 -> 8.8015043 | C9: =PL!F31 -> 5.8492624 | D9: =PL!F46 -> 2.1645976
A10: FY2029 | B10: =PL!G16 -> 10.0067 | C10: =PL!G31 -> 6.5347789 | D10: =PL!G46 -> 2.1609573
A11: FY2030 | B11: =PL!H16 -> 10.997577 | C11: =PL!H31 -> 6.9041641 | D11: =PL!H46 -> 2.1865254
A12: FY2031 | B12: =PL!I16 -> 11.872003 | C12: =PL!I31 -> 7.1092444 | D12: =PL!I46 -> 2.1360301
A13: FY2032 | B13: =PL!J16 -> 12.584323 | C13: =PL!J31 -> 7.1295565 | D13: =PL!J46 -> 2.0111545
A14: 股東現金流＝EPS ×（1 − tp_g ÷ tp_roe）
A15: 再投資率（tp_g ÷ tp_roe，上限 0.8） | B15: =MIN(tp_g/tp_roe,0.8) -> 0.28749401 | E15: ROE 為近三年平均（In 頁 tp_roe）
A16: FY2027 | B16: =B8*(1-$B$15) -> 5.4161178 | C16: =C8*(1-$B$15) -> 4.2428349 | D16: =D8*(1-$B$15) -> 2.8775537
A17: FY2028 | B17: =B9*(1-$B$15) -> 6.2711245 | C17: =C9*(1-$B$15) -> 4.1676345 | D17: =D9*(1-$B$15) -> 1.5422887
A18: FY2029 | B18: =B10*(1-$B$15) -> 7.1298334 | C18: =C10*(1-$B$15) -> 4.6560691 | D18: =D10*(1-$B$15) -> 1.539695
A19: FY2030 | B19: =B11*(1-$B$15) -> 7.8358398 | C19: =C11*(1-$B$15) -> 4.9192583 | D19: =D11*(1-$B$15) -> 1.5579125
A20: FY2031 | B20: =B12*(1-$B$15) -> 8.4588731 | C20: =C12*(1-$B$15) -> 5.0653792 | D20: =D12*(1-$B$15) -> 1.5219343
A21: FY2032 | B21: =B13*(1-$B$15) -> 8.9664055 | C21: =C13*(1-$B$15) -> 5.0798517 | D21: =D13*(1-$B$15) -> 1.4329596
A22: DCF 情境每股價值（折現率 tp_r） | B22: =MAX(0,SUMPRODUCT(B16:B21,1/(1+tp_r)^{1;2;3;4;5;6})+B21*(1+tp_g)/(tp_r-tp_g)/(1+tp_r)^6) -> 118.85806 | C22: =MAX(0,SUMPRODUCT(C16:C21,1/(1+tp_r)^{1;2;3;4;5;6})+C21*(1+tp_g)/(tp_r-tp_g)/(1+tp_r)^6) -> 69.874548 | D22: =MAX(0,SUMPRODUCT(D16:D21,1/(1+tp_r)^{1;2;3;4;5;6})+D21*(1+tp_g)/(tp_r-tp_g)/(1+tp_r)^6) -> 21.885702 | E22: Σ 明確期現金流 ÷ (1＋r)^t ＋ 永續價值 ÷ (1＋r)^6；永續價值＝FY2032 現金流 ×(1＋g)÷(r−g)；基準日 2026 年底；負值取 0
A23: DCF 情境價值推到 12 個月後（×(1＋tp_r)） | B23: =B22*(1+tp_r) -> 130.74386 | C23: =C22*(1+tp_r) -> 76.862003 | D23: =D22*(1+tp_r) -> 24.074272
A24: DCF 目標價（情境加權） | B24: =tp_wA*B23+tp_wB*C23+tp_wC*D23 -> 82.469015 | E24: Σ 權重 × 情境價值 ×(1＋r)；權重見 In 頁
A26: 0.2 Comparable（市場主流同業前瞻 P/E）
A27: 同業與前瞻 P/E | B27: 代號 | C27: 前瞻 12 月 P/E | D27: 日期 | E27: 來源 | F27: 標記
A28: 台積電（TSMC） | B28: 2330.TW | C28: 16.81 | D28: 2026-10-22 | E28: stockanalysis.com forward PE（分析師共識；價格日期如左） | F28: Interested-party
A29: 格芯（GlobalFoundries） | B29: GFS | C29: 20.04 | D29: 2026-10-22 | E29: stockanalysis.com forward PE（抄自台積電模型 Val 頁同業表） | F29: Interested-party
A30: 中芯國際（SMIC，港股） | B30: 0981.HK | C30: 37.14 | D30: 2026-10-16 | E30: stockanalysis.com forward PE（抄自台積電模型 Val 頁同業表） | F30: Interested-party
A31: 高塔半導體（Tower） | B31: TSEM | C31: 34.63 | D31: 2026-10-26 | E31: stockanalysis.com forward PE（分析師共識；價格日期如左） | F31: Interested-party
A32: 世界先進（VIS） | B32: 5347.TWO | C32: 23.41 | D32: 2026-09-11 | E32: stockanalysis.com forward PE（價格日期如左；10 月值未取得） | F32: Interested-party
A33: 同業前瞻 P/E 中位數 | B33: =MEDIAN(C28:C32) -> 23.41 | E33: 晶圓代工同業（台積電、格芯、中芯港股、高塔、世界先進）；不含 A 股（非 A 股公司，Andy 2026-10-25 11:53）；華虹（1347.HK）前瞻 P/E 133.5 倍且資料日 2026-08-07，未列
A34: 12 個月後的前瞻 EPS（情境加權） | B34: =tp_wA*(2/12*B8+10/12*B9)+tp_wB*(2/12*C8+10/12*C9)+tp_wC*(2/12*D8+10/12*D9) -> 6.0092653 | E34: 約 2027-10 時的未來 12 月 EPS ≈ 2／12 × FY2027＋10／12 × FY2028（會計年度＝日曆年）
A35: Comparable 目標價 | B35: =B33*B34 -> 140.6769 | E35: 同業中位數 × 前瞻 EPS
A37: 0.3 結論
A38: 項目 | B38: 數值 | E38: 說明
A39: 目標價（DCF 與 Comparable 加權） | B39: =tp_w_dcf*B24+(1-tp_w_dcf)*tp_comp_adj -> 76.403733 | E39: tp_w_dcf × DCF＋（1 − tp_w_dcf）× Comparable（相對倍數調整後，見第 0.5 節）
A40: Comparable 目標價（市場主流同業法） | B40: =B35 -> 140.6769
A41: 市場共識目標價 | B41: =cons_tp -> 140.69 | E41: stockanalysis：25 位分析師平均 140.69（2026-10-08 擷取；中位數 135、區間 41–258）
A42: 上檔空間：加權目標價 | B42: =B39/px-1 -> -0.39120532 | E42: 現價＝In 頁 px（2026-10-22 收盤）
A43: 上檔空間：Comparable 目標價 | B43: =B40/px-1 -> 0.12093148
A44: 與市場共識目標價的差距：EPS 因素 | B44: =B34/cons_feps-1 -> -0.031813986 | E44: 本模型前瞻 EPS ÷ 共識前瞻 EPS − 1；共識前瞻 EPS 見 In 頁 cons_feps
A45: 與市場共識目標價的差距：倍數因素 | B45: =(cons_tp/cons_feps)/B33-1 -> -0.031723835 | E45: ="共識目標價隱含 "&TEXT(cons_tp/cons_feps,"0.0")&"x，同業中位數 "&TEXT(B33,"0.0")&"x" -> 共識目標價隱含 22.7x，同業中位數 23.4x
A46: 價格帶（DCF 不如預期～順利） | B46: =TEXT(D23,"#,##0")&"～"&TEXT(B23,"#,##0") -> 24～131 | E46: C 情境價值～A 情境價值（推到 12 個月後）
A47: 歷史倍數檢查：現價隱含 P/E 的十年分位（A／B／C） | B47: =IF(px/B9>=MAX($B$86:$B$95),1,IF(px/B9<=MIN($B$86:$B$95),0,PERCENTRANK($B$86:$B$95,px/B9))) -> 0.801 | C47: =IF(px/C9>=MAX($B$86:$B$95),1,IF(px/C9<=MIN($B$86:$B$95),0,PERCENTRANK($B$86:$B$95,px/C9))) -> 1 | D47: =IF(px/D9>=MAX($B$86:$B$95),1,IF(px/D9<=MIN($B$86:$B$95),0,PERCENTRANK($B$86:$B$95,px/D9))) -> 1 | E47: 現價 ÷ 各情境 FY2028 EPS 在 2016–2025 年底 P/E（第 5 節兩來源平均）的分位；高於十年最大值記為 100%、低於最小值記為 0%；只作檢查，不進目標價
A48: 目標價方法 | B48: DCF：股東現金流＝EPS ×（1 − g／ROE），r＝10%、g＝4%、ROE 為近三年平均約 13.9%（再投資率約 29%），FY2027–32 明確期＋永續；聯電資本密集，但本模型只有折舊路徑、沒有資本支出推導，未改用淨利＋折舊－資本支出（若擴產資本支出持續高於折舊，DCF 偏高估）；情境價值負值取 0。Comparable：台積電、格芯、中芯（港股）、高塔、世界先進前瞻 P/E 中位數，再乘相對倍數調整係數（第 0.5 節；聯電 10 年前瞻 P/E 長期低於同業，係數觸及下限 0.5）。主要偏誤：稼動率與售價屬公司層級假設（待併入 Siliconomics）；AI 相關與 Intel 12 奈米為 Assumed 路徑；FY2030 起只用收斂法。情境對應：A＝順利（稼動率 95%、售價 +10%）、B＝平平、C＝不如預期（中國成熟製程擴產、稼動率 76–82%、售價下跌）
A51: 1. 價格與市場隱含倍數
A52: 項目 | B52: A | C52: B | D52: C | E52: 說明
A53: 現價（2026-10-22 收盤） | B53: =px -> 125.5
A54: 現價 ÷ FY2026 EPS（錨點） | B54: =px/PL!D16 -> 17.042312 | C54: =px/PL!D31 -> 17.042312 | D54: =px/PL!D46 -> 17.042312 | E54: FY2026 三情境相同（錨點）
A55: 現價 ÷ FY2027 EPS（模型） | B55: =px/PL!E16 -> 16.509889 | C55: =px/PL!E31 -> 21.075414 | D55: =px/PL!E46 -> 31.074834 | E55: FY2027 三情境差在稼動率、售價與新業務；顆數情境係數從 CY2028 開始
A56: 現價 ÷ FY2028 EPS（模型） | B56: =px/PL!F16 -> 14.258926 | C56: =px/PL!F31 -> 21.455697 | D56: =px/PL!F46 -> 57.978445
A57: 現價 ÷ FY2029 EPS（模型） | B57: =px/PL!G16 -> 12.541598 | C57: =px/PL!G31 -> 19.204934 | D57: =px/PL!G46 -> 58.076112
A58: 未來 12 月 EPS（模型 B）≈ 0.2 × FY2026＋0.8 × FY2027 | B58: =0.2*PL!D31+0.8*PL!E31 -> 6.2366496
A59: 現價 ÷ 未來 12 月 EPS（模型 B） | B59: =px/B58 -> 20.122984
A60: 近 12 月 P/E（現價 ÷ 近 12 月 EPS） | B60: =pe_ttm -> 18.428781
A61: 前瞻 P/E（stockanalysis，2026-10-22；股價 125.5） | B61: =fpe -> 20.22
A63: 2. 循環位置（本模型營收最高年；FY(t)＝CY(t)）
A64: 情境 | B64: 營收最高年（FY2026–FY2029） | C64: FY2027 判定 | D64: 規則倍數（P/E） | E64: 見頂年是否未知 | F64: 說明
A65: A | B65: =INDEX({2026,2027,2028,2029},MATCH(MAX(PL!D75:G75),PL!D75:G75,0)) -> 2029 | C65: =IF(B65=2029,"中段",IF(2027<B65,"中段",IF(2027=B65,"見頂","谷底"))) -> 中段 | D65: =IF(C65="見頂",pe_peak,IF(C65="谷底",pe_trough,pe_mid)) -> 11.4 | E65: =IF(B65=2029,"是：營收到觀測期末仍在增加","否") -> 是：營收到觀測期末仍在增加 | F65: tools/cycle_position.py excel_rule；營收最高年取代設備市場見頂年
A66: B | B66: =INDEX({2026,2027,2028,2029},MATCH(MAX(PL!D114:G114),PL!D114:G114,0)) -> 2029 | C66: =IF(B66=2029,"中段",IF(2027<B66,"中段",IF(2027=B66,"見頂","谷底"))) -> 中段 | D66: =IF(C66="見頂",pe_peak,IF(C66="谷底",pe_trough,pe_mid)) -> 11.4 | E66: =IF(B66=2029,"是：營收到觀測期末仍在增加","否") -> 是：營收到觀測期末仍在增加 | F66: 同上
A67: C | B67: =INDEX({2026,2027,2028,2029},MATCH(MAX(PL!D153:G153),PL!D153:G153,0)) -> 2029 | C67: =IF(B67=2029,"中段",IF(2027<B67,"中段",IF(2027=B67,"見頂","谷底"))) -> 中段 | D67: =IF(C67="見頂",pe_peak,IF(C67="谷底",pe_trough,pe_mid)) -> 11.4 | E67: =IF(B67=2029,"是：營收到觀測期末仍在增加","否") -> 是：營收到觀測期末仍在增加 | F67: 同上
A69: 3. 規則值隱含股價（新台幣；約 FY2027 年底，未折現）＝ FY2027 EPS × 規則倍數
A70: 情境 | B70: FY2027 EPS | C70: （同左） | D70: 規則倍數 | E70: 隱含股價 | F70: 相對現價 | G70: 現價 ÷ FY2027 EPS
A71: A | B71: =PL!E16 -> 7.6015049 | C71: =B71 -> 7.6015049 | D71: =D65 -> 11.4 | E71: =C71*D71 -> 86.657156 | F71: =E71/px-1 -> -0.30950473 | G71: =px/C71 -> 16.509889
A72: B | B72: =PL!E31 -> 5.9548059 | C72: =B72 -> 5.9548059 | D72: =D66 -> 11.4 | E72: =C72*D72 -> 67.884788 | F72: =E72/px-1 -> -0.45908536 | G72: =px/C72 -> 21.075414
A73: C | B73: =PL!E46 -> 4.0386378 | C73: =B73 -> 4.0386378 | D73: =D67 -> 11.4 | E73: =C73*D73 -> 46.040471 | F73: =E73/px-1 -> -0.63314365 | G73: =px/C73 -> 31.074834
A75: 4. What must be true：FY2027 年底價 ＝ 現價 ×（1＋報酬）所需的倍數（FY2028 EPS；約 2027 年底的價格看下一年 EPS）
A76: FY2027 年底價 ÷ 現價 | B76: 所需倍數（÷ FY2028 EPS，A） | C76: 所需倍數（÷ FY2028 EPS，B） | D76: 所需倍數（÷ FY2028 EPS，C） | E76: 對照：十年中位數
A77: 1 | B77: =px*A77/PL!F16 -> 14.258926 | C77: =px*A77/PL!F31 -> 21.455697 | D77: =px*A77/PL!F46 -> 57.978445 | E77: =pe_mid -> 11.4
A78: 1.1 | B78: =px*A78/PL!F16 -> 15.684819 | C78: =px*A78/PL!F31 -> 23.601267 | D78: =px*A78/PL!F46 -> 63.776289 | E78: =pe_mid -> 11.4
A79: 1.21 | B79: =px*A79/PL!F16 -> 17.253301 | C79: =px*A79/PL!F31 -> 25.961393 | D79: =px*A79/PL!F46 -> 70.153918 | E79: =pe_mid -> 11.4
A80: 1.5 | B80: =px*A80/PL!F16 -> 21.388389 | C80: =px*A80/PL!F31 -> 32.183545 | D80: =px*A80/PL!F46 -> 86.967667 | E80: =pe_mid -> 11.4
A81: 2 | B81: =px*A81/PL!F16 -> 28.517852 | C81: =px*A81/PL!F31 -> 42.911394 | D81: =px*A81/PL!F46 -> 115.95689 | E81: =pe_mid -> 11.4
A82: 讀法：1.00＝價格不變、1.21＝一年約 21%。所需倍數低於歷史中位數時，現價相對便宜；倍數是否合理，另看前瞻 P/E 歷史（Bloomberg）。本版未做先驗，無 Andy 合理 P/E 對照。
A84: 5. 十年 P/E（2016–2025 年底；兩來源平均，分位排名用；無負值或 >200 需剔除）
A85: 年底 | B85: 兩來源平均 P/E | C85: companiesmarketcap | D85: stockanalysis
A86: 2016 | B86: =IF(COUNT(C86:D86)=0,"",AVERAGE(C86:D86)) -> 10.6 | C86: =IF(B105="","",B105) -> 10.6 | D86: =IF(C105="","",C105)
A87: 2017 | B87: =IF(COUNT(C87:D87)=0,"",AVERAGE(C87:D87)) -> 11.8 | C87: =IF(B106="","",B106) -> 11.8 | D87: =IF(C106="","",C106)
A88: 2018 | B88: =IF(COUNT(C88:D88)=0,"",AVERAGE(C88:D88)) -> 12.8 | C88: =IF(B107="","",B107) -> 12.8 | D88: =IF(C107="","",C107)
A89: 2019 | B89: =IF(COUNT(C89:D89)=0,"",AVERAGE(C89:D89)) -> 14.1 | C89: =IF(B108="","",B108) -> 14.1 | D89: =IF(C108="","",C108)
A90: 2020 | B90: =IF(COUNT(C90:D90)=0,"",AVERAGE(C90:D90)) -> 15.1 | C90: =IF(B109="","",B109) -> 15.1 | D90: =IF(C109="","",C109)
A91: 2021 | B91: =IF(COUNT(C91:D91)=0,"",AVERAGE(C91:D91)) -> 13.355 | C91: =IF(B110="","",B110) -> 10.9 | D91: =IF(C110="","",C110) -> 15.81
A92: 2022 | B92: =IF(COUNT(C92:D92)=0,"",AVERAGE(C92:D92)) -> 5.185 | C92: =IF(B111="","",B111) -> 4.68 | D92: =IF(C111="","",C111) -> 5.69
A93: 2023 | B93: =IF(COUNT(C93:D93)=0,"",AVERAGE(C93:D93)) -> 10.095 | C93: =IF(B112="","",B112) -> 9.38 | D93: =IF(C112="","",C112) -> 10.81
A94: 2024 | B94: =IF(COUNT(C94:D94)=0,"",AVERAGE(C94:D94)) -> 11.025 | C94: =IF(B113="","",B113) -> 10.6 | D94: =IF(C113="","",C113) -> 11.45
A95: 2025 | B95: =IF(COUNT(C95:D95)=0,"",AVERAGE(C95:D95)) -> 14.86 | C95: =IF(B114="","",B114) -> 14.9 | D95: =IF(C114="","",C114) -> 14.82
A96: 年數 | B96: =COUNT($B$86:$B$95) -> 10
A100: 6. 十年倍數與規則值（2016–2025 年底；見頂年 25 分位、中段中位數、谷底 75 分位）
A101: 規則（Andy 2026-10-13）：合理倍數＝2016–2025 年底 P/E 依循環位置取分位，兩個來源分別取分位再平均。stockanalysis 年度 P/E 只有 FY2021–25。十年中位數約 11 倍；2022 年 EPS 高峰時 P/E 只有 5–6 倍，典型的成熟製程循環股。
A103: P/E：十年歷史倍數
A104: 年底 | B104: companiesmarketcap（年底 P/E） | C104: stockanalysis（年度 P/E） | D104: 標記／說明
A105: 2016 | B105: 10.6 | D105: companiesmarketcap（年底 P/E）：Interested-party（資料商；2016–2025 共 10 年）；stockanalysis（年度 P/E）：Interested-party（資料商；只有 FY2021–25，2016–2020 未找到）
A106: 2017 | B106: 11.8
A107: 2018 | B107: 12.8
A108: 2019 | B108: 14.1
A109: 2020 | B109: 15.1
A110: 2021 | B110: 10.9 | C110: 15.81
A111: 2022 | B111: 4.68 | C111: 5.69
A112: 2023 | B112: 9.38 | C112: 10.81
A113: 2024 | B113: 10.6 | C113: 11.45
...

Sheet Recon
A1: Recon — 本模型 vs 公司說法、共識、券商。只作事後對照，不為對上數字而調參數。券商與資料商數字為 Interested-party，不用於校準
A3: 項目 | B3: 對照值 | C3: 模型 A | D3: 差距 A | E3: 模型 B | F3: 差距 B | G3: 模型 C | H3: 差距 C | I3: 對照來源 | J3: 說明
A4: A. FY2026 錨點 vs 共識與券商
A5: FY2026 營收 vs 共識 | B5: =cons_rev26 -> 283.2 | C5: =PL!D75 -> 279.73378 | D5: =C5/B5-1 -> -0.012239477 | E5: =PL!D114 -> 279.73378 | F5: =E5/B5-1 -> -0.012239477 | G5: =PL!D153 -> 279.73378 | H5: =G5/B5-1 -> -0.012239477 | I5: stockanalysis（21 位；2026-10-08） | J5: 共識資料日早於 3Q26 財報
A6: FY2026 EPS vs 共識 | B6: =cons_eps26 -> 7.02 | C6: =PL!D94 -> 7.3640242 | D6: =C6/B6-1 -> 0.049006293 | E6: =PL!D133 -> 7.3640242 | F6: =E6/B6-1 -> 0.049006293 | G6: =PL!D172 -> 7.3640242 | H6: =G6/B6-1 -> 0.049006293 | I6: stockanalysis（2026-10-08） | J6: 共識區間 4.55–8.15；模型含 2Q26 一次性業外（約 2.0 元）
A7: FY2026 EPS vs 美系外資中點 | B7: =us_eps26 -> 7.57 | C7: =PL!D94 -> 7.3640242 | D7: =C7/B7-1 -> -0.027209487 | E7: =PL!D133 -> 7.3640242 | F7: =E7/B7-1 -> -0.027209487 | G7: =PL!D172 -> 7.3640242 | H7: =G7/B7-1 -> -0.027209487 | I7: 旺得富 2026-10-17 | J7: 7.46–7.68
A8: 4Q26 毛利率 vs 公司指引（百分點） | B8: =q4_gm -> 0.34 | C8: =Q!F10 -> 0.34 | D8: =C8-B8 -> 0 | E8: =Q!F10 -> 0.34 | F8: =E8-B8 -> 0 | G8: =Q!F10 -> 0.34 | H8: =G8-B8 -> 0 | I8: 公司 6-K（2026-10-28） | J8: 三欄同值（FY2026 錨點）
A9: B. FY2027–29 vs 公司說法與券商（校準未使用）
A10: FY2027 平均售價年增 vs 公司約一成（百分點） | B10: =co_asp27 -> 0.1 | C10: =PL!E67 -> 0.1 | D10: =C10-B10 -> 0 | E10: =PL!E106 -> 0.05 | F10: =E10-B10 -> -0.05 | G10: =PL!E145 -> 0 | H10: =G10-B10 -> -0.1 | I10: 優分析 2026-10-28（法說） | J10: A＝公司說法；B、C 低於公司
A11: FY2027 EPS vs 本土投顧 | B11: =loc_eps27 -> 9.2 | C11: =PL!E94 -> 7.6015049 | D11: =C11/B11-1 -> -0.17374947 | E11: =PL!E133 -> 5.9548059 | F11: =E11/B11-1 -> -0.35273848 | G11: =PL!E172 -> 4.0386378 | H11: =G11/B11-1 -> -0.56101763 | I11: 旺得富 2026-10-17 | J11: FY2027 共識：未找到
A12: FY2029 AI 相關營收 vs 公司目標（US$B） | B12: =co_ai29 -> 1 | C12: =PL!G71 -> 1.0092 | D12: =C12/B12-1 -> 0.0092 | E12: =PL!G110 -> 0.7505925 | F12: =E12/B12-1 -> -0.2494075 | G12: =PL!G149 -> 0.45414 | H12: =G12/B12-1 -> -0.54586 | I12: 科技新報 2026-10-06（大摩轉述） | J12: B、C 乘同字母顆數係數
A13: 共識前瞻 12 月 EPS vs 模型（情境加權 2／12 × FY2027＋10／12 × FY2028） | B13: =cons_feps -> 6.206726 | C13: =Val!B34 -> 6.0092653 | D13: =C13/B13-1 -> -0.031813986 | E13: =Val!B34 -> 6.0092653 | F13: =E13/B13-1 -> -0.031813986 | G13: =Val!B34 -> 6.0092653 | H13: =G13/B13-1 -> -0.031813986 | I13: stockanalysis 前瞻 P/E 推得 | J13: 三欄同值（情境加權）
A14: 預留
A15: 成熟製程稼動率與價格的行業層（Siliconomics）尚未建立：上線後以本模型稼動率、售價情境對照行業路徑 | J15: 預留列：本版無數值

Sheet Sens
A1: Sens — 一次動一個輸入（In 頁敏感度低／高值），三情境都在本頁下方逐案重算（FY2026 恆等於錨點，每片現金成本在每個案例內重算），表內為情境加權後的 DCF、Comparable（相對倍數調整後）與加權目標價；另列 FY2027、FY2028 情境 A 的 EPS
A2: 相對基準＝案例加權目標價 ÷ 基準加權目標價 − 1。目標價參數（tp_r、tp_g、tp_w_dcf）三案只改 DCF 參數，PL 收斂法的 fade_g 不隨 tp_g 變動
A3: 案例 | B3: 設定 | C3: 鍵 | D3: FY2027 EPS（A） | E3: FY2028 EPS（A） | F3: FY2028 EPS 相對基準（A） | G3: DCF 目標價 | H3: Comparable（調整後）目標價 | I3: 加權目標價 | J3: 相對基準
A4: 基準（三情境加權） | B4: PL 頁三個推導區塊 | C4: — | D4: =PL!E94 -> 7.6015049 | E4: =PL!F94 -> 8.8015043 | F4: =E4/E$4-1 -> 0 | G4: =(tp_wA*MAX(0,PL!E94*(1-MIN(tp_g/tp_roe,0.8))/(1+tp_r)^1+PL!F94*(1-MIN(tp_g/tp_roe,0.8))/(1+tp_r)^2+PL!G94*(1-MIN(tp_g/tp_roe,0.8))/(1+tp_r)^3+PL!H94*(1-MIN(tp_g/tp_roe,0.8))/(1+tp_r)^4+PL!I94*(1-MIN(tp_g/tp_roe,0.8))/(1+tp_r)^5+PL!J94*(1-MIN(tp_g/tp_roe,0.8))/(1+tp_r)^6+PL!J94*(1-MIN(tp_g/tp_roe,0.8))*(1+tp_g)/(tp_r-tp_g)/(1+tp_r)^6)+tp_wB*MAX(0,PL!E133*(1-MIN(tp_g/tp_roe,0.8))/(1+tp_r)^1+PL!F133*(1-MIN(tp_g/tp_roe,0.8))/(1+tp_r)^2+PL!G133*(1-MIN(tp_g/tp_roe,0.8))/(1+tp_r)^3+PL!H133*(1-MIN(tp_g/tp_roe,0.8))/(1+tp_r)^4+PL!I133*(1-MIN(tp_g/tp_roe,0.8))/(1+tp_r)^5+PL!J133*(1-MIN(tp_g/tp_roe,0.8))/(1+tp_r)^6+PL!J133*(1-MIN(tp_g/tp_roe,0.8))*(1+tp_g)/(tp_r-tp_g)/(1+tp_r)^6)+tp_wC*MAX(0,PL!E172*(1-MIN(tp_g/tp_roe,0.8))/(1+tp_r)^1+PL!F172*(1-MIN(tp_g/tp_roe,0.8))/(1+tp_r)^2+PL!G172*(1-MIN(tp_g/tp_roe,0.8))/(1+tp_r)^3+PL!H172*(1-MIN(tp_g/tp_roe,0.8))/(1+tp_r)^4+PL!I172*(1-MIN(tp_g/tp_roe,0.8))/(1+tp_r)^5+PL!J172*(1-MIN(tp_g/tp_roe,0.8))/(1+tp_r)^6+PL!J172*(1-MIN(tp_g/tp_roe,0.8))*(1+tp_g)/(tp_r-tp_g)/(1+tp_r)^6))*(1+tp_r) -> 82.469015 | H4: =Val!$B$33*(tp_wA*(2/12*PL!E94+10/12*PL!F94)+tp_wB*(2/12*PL!E133+10/12*PL!F133)+tp_wC*(2/12*PL!E172+10/12*PL!F172))*rm_factor -> 70.338451 | I4: =tp_w_dcf*G4+(1-tp_w_dcf)*H4 -> 76.403733 | J4: =I4/I$4-1 -> 0
A5: 匯率：低 | B5: =TEXT(fx_lo,"0.0")&"（基準 "&TEXT(fx,"0.0")&"）" -> 30.5（基準 32.0） | C5: fx | D5: =E72 -> 6.5416348 | E5: =F72 -> 7.6247802 | F5: =E5/E$4-1 -> -0.13369579 | G5: =(tp_wA*MAX(0,E72*(1-MIN(tp_g/tp_roe,0.8))/(1+tp_r)^1+F72*(1-MIN(tp_g/tp_roe,0.8))/(1+tp_r)^2+G72*(1-MIN(tp_g/tp_roe,0.8))/(1+tp_r)^3+H72*(1-MIN(tp_g/tp_roe,0.8))/(1+tp_r)^4+I72*(1-MIN(tp_g/tp_roe,0.8))/(1+tp_r)^5+J72*(1-MIN(tp_g/tp_roe,0.8))/(1+tp_r)^6+J72*(1-MIN(tp_g/tp_roe,0.8))*(1+tp_g)/(tp_r-tp_g)/(1+tp_r)^6)+tp_wB*MAX(0,E111*(1-MIN(tp_g/tp_roe,0.8))/(1+tp_r)^1+F111*(1-MIN(tp_g/tp_roe,0.8))/(1+tp_r)^2+G111*(1-MIN(tp_g/tp_roe,0.8))/(1+tp_r)^3+H111*(1-MIN(tp_g/tp_roe,0.8))/(1+tp_r)^4+I111*(1-MIN(tp_g/tp_roe,0.8))/(1+tp_r)^5+J111*(1-MIN(tp_g/tp_roe,0.8))/(1+tp_r)^6+J111*(1-MIN(tp_g/tp_roe,0.8))*(1+tp_g)/(tp_r-tp_g)/(1+tp_r)^6)+tp_wC*MAX(0,E150*(1-MIN(tp_g/tp_roe,0.8))/(1+tp_r)^1+F150*(1-MIN(tp_g/tp_roe,0.8))/(1+tp_r)^2+G150*(1-MIN(tp_g/tp_roe,0.8))/(1+tp_r)^3+H150*(1-MIN(tp_g/tp_roe,0.8))/(1+tp_r)^4+I150*(1-MIN(tp_g/tp_roe,0.8))/(1+tp_r)^5+J150*(1-MIN(tp_g/tp_roe,0.8))/(1+tp_r)^6+J150*(1-MIN(tp_g/tp_roe,0.8))*(1+tp_g)/(tp_r-tp_g)/(1+tp_r)^6))*(1+tp_r) -> 69.035674 | H5: =Val!$B$33*(tp_wA*(2/12*E72+10/12*F72)+tp_wB*(2/12*E111+10/12*F111)+tp_wC*(2/12*E150+10/12*F150))*rm_factor -> 58.538924 | I5: =tp_w_dcf*G5+(1-tp_w_dcf)*H5 -> 63.787299 | J5: =I5/I$4-1 -> -0.1651285
A6: 匯率：高 | B6: =TEXT(fx_hi,"0.0")&"（基準 "&TEXT(fx,"0.0")&"）" -> 33.0（基準 32.0） | C6: fx | D6: =E189 -> 8.308085 | E6: =F189 -> 9.585987 | F6: =E6/E$4-1 -> 0.08913053 | G6: =(tp_wA*MAX(0,E189*(1-MIN(tp_g/tp_roe,0.8))/(1+tp_r)^1+F189*(1-MIN(tp_g/tp_roe,0.8))/(1+tp_r)^2+G189*(1-MIN(tp_g/tp_roe,0.8))/(1+tp_r)^3+H189*(1-MIN(tp_g/tp_roe,0.8))/(1+tp_r)^4+I189*(1-MIN(tp_g/tp_roe,0.8))/(1+tp_r)^5+J189*(1-MIN(tp_g/tp_roe,0.8))/(1+tp_r)^6+J189*(1-MIN(tp_g/tp_roe,0.8))*(1+tp_g)/(tp_r-tp_g)/(1+tp_r)^6)+tp_wB*MAX(0,E228*(1-MIN(tp_g/tp_roe,0.8))/(1+tp_r)^1+F228*(1-MIN(tp_g/tp_roe,0.8))/(1+tp_r)^2+G228*(1-MIN(tp_g/tp_roe,0.8))/(1+tp_r)^3+H228*(1-MIN(tp_g/tp_roe,0.8))/(1+tp_r)^4+I228*(1-MIN(tp_g/tp_roe,0.8))/(1+tp_r)^5+J228*(1-MIN(tp_g/tp_roe,0.8))/(1+tp_r)^6+J228*(1-MIN(tp_g/tp_roe,0.8))*(1+tp_g)/(tp_r-tp_g)/(1+tp_r)^6)+tp_wC*MAX(0,E267*(1-MIN(tp_g/tp_roe,0.8))/(1+tp_r)^1+F267*(1-MIN(tp_g/tp_roe,0.8))/(1+tp_r)^2+G267*(1-MIN(tp_g/tp_roe,0.8))/(1+tp_r)^3+H267*(1-MIN(tp_g/tp_roe,0.8))/(1+tp_r)^4+I267*(1-MIN(tp_g/tp_roe,0.8))/(1+tp_r)^5+J267*(1-MIN(tp_g/tp_roe,0.8))/(1+tp_r)^6+J267*(1-MIN(tp_g/tp_roe,0.8))*(1+tp_g)/(tp_r-tp_g)/(1+tp_r)^6))*(1+tp_r) -> 91.424576 | H6: =Val!$B$33*(tp_wA*(2/12*E189+10/12*F189)+tp_wB*(2/12*E228+10/12*F228)+tp_wC*(2/12*E267+10/12*F267))*rm_factor -> 78.204801 | I6: =tp_w_dcf*G6+(1-tp_w_dcf)*H6 -> 84.814689 | J6: =I6/I$4-1 -> 0.11008567
A7: 產能係數：低 | B7: =TEXT(cap_adj_lo,"0.00")&"（基準 "&TEXT(cap_adj,"0.00")&"）" -> 0.95（基準 1.00） | C7: cap_adj | D7: =E306 -> 6.994878 | E7: =F306 -> 8.1312004 | F7: =E7/E$4-1 -> -0.076157878 | G7: =(tp_wA*MAX(0,E306*(1-MIN(tp_g/tp_roe,0.8))/(1+tp_r)^1+F306*(1-MIN(tp_g/tp_roe,0.8))/(1+tp_r)^2+G306*(1-MIN(tp_g/tp_roe,0.8))/(1+tp_r)^3+H306*(1-MIN(tp_g/tp_roe,0.8))/(1+tp_r)^4+I306*(1-MIN(tp_g/tp_roe,0.8))/(1+tp_r)^5+J306*(1-MIN(tp_g/tp_roe,0.8))/(1+tp_r)^6+J306*(1-MIN(tp_g/tp_roe,0.8))*(1+tp_g)/(tp_r-tp_g)/(1+tp_r)^6)+tp_wB*MAX(0,E345*(1-MIN(tp_g/tp_roe,0.8))/(1+tp_r)^1+F345*(1-MIN(tp_g/tp_roe,0.8))/(1+tp_r)^2+G345*(1-MIN(tp_g/tp_roe,0.8))/(1+tp_r)^3+H345*(1-MIN(tp_g/tp_roe,0.8))/(1+tp_r)^4+I345*(1-MIN(tp_g/tp_roe,0.8))/(1+tp_r)^5+J345*(1-MIN(tp_g/tp_roe,0.8))/(1+tp_r)^6+J345*(1-MIN(tp_g/tp_roe,0.8))*(1+tp_g)/(tp_r-tp_g)/(1+tp_r)^6)+tp_wC*MAX(0,E384*(1-MIN(tp_g/tp_roe,0.8))/(1+tp_r)^1+F384*(1-MIN(tp_g/tp_roe,0.8))/(1+tp_r)^2+G384*(1-MIN(tp_g/tp_roe,0.8))/(1+tp_r)^3+H384*(1-MIN(tp_g/tp_roe,0.8))/(1+tp_r)^4+I384*(1-MIN(tp_g/tp_roe,0.8))/(1+tp_r)^5+J384*(1-MIN(tp_g/tp_roe,0.8))/(1+tp_r)^6+J384*(1-MIN(tp_g/tp_roe,0.8))*(1+tp_g)/(tp_r-tp_g)/(1+tp_r)^6))*(1+tp_r) -> 75.428388 | H7: =Val!$B$33*(tp_wA*(2/12*E306+10/12*F306)+tp_wB*(2/12*E345+10/12*F345)+tp_wC*(2/12*E384+10/12*F384))*rm_factor -> 63.901419 | I7: =tp_w_dcf*G7+(1-tp_w_dcf)*H7 -> 69.664903 | J7: =I7/I$4-1 -> -0.088200263
A8: 產能係數：高 | B8: =TEXT(cap_adj_hi,"0.00")&"（基準 "&TEXT(cap_adj,"0.00")&"）" -> 1.05（基準 1.00） | C8: cap_adj | D8: =E423 -> 8.2081319 | E8: =F423 -> 9.4717274 | F8: =E8/E$4-1 -> 0.076148697 | G8: =(tp_wA*MAX(0,E423*(1-MIN(tp_g/tp_roe,0.8))/(1+tp_r)^1+F423*(1-MIN(tp_g/tp_roe,0.8))/(1+tp_r)^2+G423*(1-MIN(tp_g/tp_roe,0.8))/(1+tp_r)^3+H423*(1-MIN(tp_g/tp_roe,0.8))/(1+tp_r)^4+I423*(1-MIN(tp_g/tp_roe,0.8))/(1+tp_r)^5+J423*(1-MIN(tp_g/tp_roe,0.8))/(1+tp_r)^6+J423*(1-MIN(tp_g/tp_roe,0.8))*(1+tp_g)/(tp_r-tp_g)/(1+tp_r)^6)+tp_wB*MAX(0,E462*(1-MIN(tp_g/tp_roe,0.8))/(1+tp_r)^1+F462*(1-MIN(tp_g/tp_roe,0.8))/(1+tp_r)^2+G462*(1-MIN(tp_g/tp_roe,0.8))/(1+tp_r)^3+H462*(1-MIN(tp_g/tp_roe,0.8))/(1+tp_r)^4+I462*(1-MIN(tp_g/tp_roe,0.8))/(1+tp_r)^5+J462*(1-MIN(tp_g/tp_roe,0.8))/(1+tp_r)^6+J462*(1-MIN(tp_g/tp_roe,0.8))*(1+tp_g)/(tp_r-tp_g)/(1+tp_r)^6)+tp_wC*MAX(0,E501*(1-MIN(tp_g/tp_roe,0.8))/(1+tp_r)^1+F501*(1-MIN(tp_g/tp_roe,0.8))/(1+tp_r)^2+G501*(1-MIN(tp_g/tp_roe,0.8))/(1+tp_r)^3+H501*(1-MIN(tp_g/tp_roe,0.8))/(1+tp_r)^4+I501*(1-MIN(tp_g/tp_roe,0.8))/(1+tp_r)^5+J501*(1-MIN(tp_g/tp_roe,0.8))/(1+tp_r)^6+J501*(1-MIN(tp_g/tp_roe,0.8))*(1+tp_g)/(tp_r-tp_g)/(1+tp_r)^6))*(1+tp_r) -> 89.500269 | H8: =Val!$B$33*(tp_wA*(2/12*E423+10/12*F423)+tp_wB*(2/12*E462+10/12*F462)+tp_wC*(2/12*E501+10/12*F501))*rm_factor -> 76.775246 | I8: =tp_w_dcf*G8+(1-tp_w_dcf)*H8 -> 83.137757 | J8: =I8/I$4-1 -> 0.088137376
A9: 稼動率調整：低 | B9: =TEXT(ut_adj_lo,"0.0%")&"（基準 "&TEXT(ut_adj,"0.0%")&"）" -> -3.0%（基準 0.0%） | C9: ut_adj | D9: =E540 -> 7.2183721 | E9: =F540 -> 8.3736441 | F9: =E9/E$4-1 -> -0.048612159 | G9: =(tp_wA*MAX(0,E540*(1-MIN(tp_g/tp_roe,0.8))/(1+tp_r)^1+F540*(1-MIN(tp_g/tp_roe,0.8))/(1+tp_r)^2+G540*(1-MIN(tp_g/tp_roe,0.8))/(1+tp_r)^3+H540*(1-MIN(tp_g/tp_roe,0.8))/(1+tp_r)^4+I540*(1-MIN(tp_g/tp_roe,0.8))/(1+tp_r)^5+J540*(1-MIN(tp_g/tp_roe,0.8))/(1+tp_r)^6+J540*(1-MIN(tp_g/tp_roe,0.8))*(1+tp_g)/(tp_r-tp_g)/(1+tp_r)^6)+tp_wB*MAX(0,E579*(1-MIN(tp_g/tp_roe,0.8))/(1+tp_r)^1+F579*(1-MIN(tp_g/tp_roe,0.8))/(1+tp_r)^2+G579*(1-MIN(tp_g/tp_roe,0.8))/(1+tp_r)^3+H579*(1-MIN(tp_g/tp_roe,0.8))/(1+tp_r)^4+I579*(1-MIN(tp_g/tp_roe,0.8))/(1+tp_r)^5+J579*(1-MIN(tp_g/tp_roe,0.8))/(1+tp_r)^6+J579*(1-MIN(tp_g/tp_roe,0.8))*(1+tp_g)/(tp_r-tp_g)/(1+tp_r)^6)+tp_wC*MAX(0,E618*(1-MIN(tp_g/tp_roe,0.8))/(1+tp_r)^1+F618*(1-MIN(tp_g/tp_roe,0.8))/(1+tp_r)^2+G618*(1-MIN(tp_g/tp_roe,0.8))/(1+tp_r)^3+H618*(1-MIN(tp_g/tp_roe,0.8))/(1+tp_r)^4+I618*(1-MIN(tp_g/tp_roe,0.8))/(1+tp_r)^5+J618*(1-MIN(tp_g/tp_roe,0.8))/(1+tp_r)^6+J618*(1-MIN(tp_g/tp_roe,0.8))*(1+tp_g)/(tp_r-tp_g)/(1+tp_r)^6))*(1+tp_r) -> 77.710611 | H9: =Val!$B$33*(tp_wA*(2/12*E540+10/12*F540)+tp_wB*(2/12*E579+10/12*F579)+tp_wC*(2/12*E618+10/12*F618))*rm_factor -> 65.937818 | I9: =tp_w_dcf*G9+(1-tp_w_dcf)*H9 -> 71.824214 | J9: =I9/I$4-1 -> -0.059938413
A10: 稼動率調整：高 | B10: =TEXT(ut_adj_hi,"0.0%")&"（基準 "&TEXT(ut_adj,"0.0%")&"）" -> 3.0%（基準 0.0%） | C10: ut_adj | D10: =E657 -> 7.9846377 | E10: =F657 -> 9.2293421 | F10: =E10/E$4-1 -> 0.048609622 | G10: =(tp_wA*MAX(0,E657*(1-MIN(tp_g/tp_roe,0.8))/(1+tp_r)^1+F657*(1-MIN(tp_g/tp_roe,0.8))/(1+tp_r)^2+G657*(1-MIN(tp_g/tp_roe,0.8))/(1+tp_r)^3+H657*(1-MIN(tp_g/tp_roe,0.8))/(1+tp_r)^4+I657*(1-MIN(tp_g/tp_roe,0.8))/(1+tp_r)^5+J657*(1-MIN(tp_g/tp_roe,0.8))/(1+tp_r)^6+J657*(1-MIN(tp_g/tp_roe,0.8))*(1+tp_g)/(tp_r-tp_g)/(1+tp_r)^6)+tp_wB*MAX(0,E696*(1-MIN(tp_g/tp_roe,0.8))/(1+tp_r)^1+F696*(1-MIN(tp_g/tp_roe,0.8))/(1+tp_r)^2+G696*(1-MIN(tp_g/tp_roe,0.8))/(1+tp_r)^3+H696*(1-MIN(tp_g/tp_roe,0.8))/(1+tp_r)^4+I696*(1-MIN(tp_g/tp_roe,0.8))/(1+tp_r)^5+J696*(1-MIN(tp_g/tp_roe,0.8))/(1+tp_r)^6+J696*(1-MIN(tp_g/tp_roe,0.8))*(1+tp_g)/(tp_r-tp_g)/(1+tp_r)^6)+tp_wC*MAX(0,E735*(1-MIN(tp_g/tp_roe,0.8))/(1+tp_r)^1+F735*(1-MIN(tp_g/tp_roe,0.8))/(1+tp_r)^2+G735*(1-MIN(tp_g/tp_roe,0.8))/(1+tp_r)^3+H735*(1-MIN(tp_g/tp_roe,0.8))/(1+tp_r)^4+I735*(1-MIN(tp_g/tp_roe,0.8))/(1+tp_r)^5+J735*(1-MIN(tp_g/tp_roe,0.8))/(1+tp_r)^6+J735*(1-MIN(tp_g/tp_roe,0.8))*(1+tp_g)/(tp_r-tp_g)/(1+tp_r)^6))*(1+tp_r) -> 87.220934 | H10: =Val!$B$33*(tp_wA*(2/12*E657+10/12*F657)+tp_wB*(2/12*E696+10/12*F696)+tp_wC*(2/12*E735+10/12*F735))*rm_factor -> 74.739018 | I10: =tp_w_dcf*G10+(1-tp_w_dcf)*H10 -> 80.979976 | J10: =I10/I$4-1 -> 0.059895545
A11: 售價水準調整：低 | B11: =TEXT(asp_adj_lo,"0.0%")&"（基準 "&TEXT(asp_adj,"0.0%")&"）" -> -3.0%（基準 0.0%） | C11: asp_adj | D11: =E774 -> 6.9358136 | E11: =F774 -> 8.0735067 | F11: =E11/E$4-1 -> -0.082712854 | G11: =(tp_wA*MAX(0,E774*(1-MIN(tp_g/tp_roe,0.8))/(1+tp_r)^1+F774*(1-MIN(tp_g/tp_roe,0.8))/(1+tp_r)^2+G774*(1-MIN(tp_g/tp_roe,0.8))/(1+tp_r)^3+H774*(1-MIN(tp_g/tp_roe,0.8))/(1+tp_r)^4+I774*(1-MIN(tp_g/tp_roe,0.8))/(1+tp_r)^5+J774*(1-MIN(tp_g/tp_roe,0.8))/(1+tp_r)^6+J774*(1-MIN(tp_g/tp_roe,0.8))*(1+tp_g)/(tp_r-tp_g)/(1+tp_r)^6)+tp_wB*MAX(0,E813*(1-MIN(tp_g/tp_roe,0.8))/(1+tp_r)^1+F813*(1-MIN(tp_g/tp_roe,0.8))/(1+tp_r)^2+G813*(1-MIN(tp_g/tp_roe,0.8))/(1+tp_r)^3+H813*(1-MIN(tp_g/tp_roe,0.8))/(1+tp_r)^4+I813*(1-MIN(tp_g/tp_roe,0.8))/(1+tp_r)^5+J813*(1-MIN(tp_g/tp_roe,0.8))/(1+tp_r)^6+J813*(1-MIN(tp_g/tp_roe,0.8))*(1+tp_g)/(tp_r-tp_g)/(1+tp_r)^6)+tp_wC*MAX(0,E852*(1-MIN(tp_g/tp_roe,0.8))/(1+tp_r)^1+F852*(1-MIN(tp_g/tp_roe,0.8))/(1+tp_r)^2+G852*(1-MIN(tp_g/tp_roe,0.8))/(1+tp_r)^3+H852*(1-MIN(tp_g/tp_roe,0.8))/(1+tp_r)^4+I852*(1-MIN(tp_g/tp_roe,0.8))/(1+tp_r)^5+J852*(1-MIN(tp_g/tp_roe,0.8))/(1+tp_r)^6+J852*(1-MIN(tp_g/tp_roe,0.8))*(1+tp_g)/(tp_r-tp_g)/(1+tp_r)^6))*(1+tp_r) -> 74.27469 | H11: =Val!$B$33*(tp_wA*(2/12*E774+10/12*F774)+tp_wB*(2/12*E813+10/12*F813)+tp_wC*(2/12*E852+10/12*F852))*rm_factor -> 62.981159 | I11: =tp_w_dcf*G11+(1-tp_w_dcf)*H11 -> 68.627925 | J11: =I11/I$4-1 -> -0.10177262
A12: 售價水準調整：高 | B12: =TEXT(asp_adj_hi,"0.0%")&"（基準 "&TEXT(asp_adj,"0.0%")&"）" -> 3.0%（基準 0.0%） | C12: asp_adj | D12: =E891 -> 8.2671962 | E12: =F891 -> 9.5294728 | F12: =E12/E$4-1 -> 0.082709554 | G12: =(tp_wA*MAX(0,E891*(1-MIN(tp_g/tp_roe,0.8))/(1+tp_r)^1+F891*(1-MIN(tp_g/tp_roe,0.8))/(1+tp_r)^2+G891*(1-MIN(tp_g/tp_roe,0.8))/(1+tp_r)^3+H891*(1-MIN(tp_g/tp_roe,0.8))/(1+tp_r)^4+I891*(1-MIN(tp_g/tp_roe,0.8))/(1+tp_r)^5+J891*(1-MIN(tp_g/tp_roe,0.8))/(1+tp_r)^6+J891*(1-MIN(tp_g/tp_roe,0.8))*(1+tp_g)/(tp_r-tp_g)/(1+tp_r)^6)+tp_wB*MAX(0,E930*(1-MIN(tp_g/tp_roe,0.8))/(1+tp_r)^1+F930*(1-MIN(tp_g/tp_roe,0.8))/(1+tp_r)^2+G930*(1-MIN(tp_g/tp_roe,0.8))/(1+tp_r)^3+H930*(1-MIN(tp_g/tp_roe,0.8))/(1+tp_r)^4+I930*(1-MIN(tp_g/tp_roe,0.8))/(1+tp_r)^5+J930*(1-MIN(tp_g/tp_roe,0.8))/(1+tp_r)^6+J930*(1-MIN(tp_g/tp_roe,0.8))*(1+tp_g)/(tp_r-tp_g)/(1+tp_r)^6)+tp_wC*MAX(0,E969*(1-MIN(tp_g/tp_roe,0.8))/(1+tp_r)^1+F969*(1-MIN(tp_g/tp_roe,0.8))/(1+tp_r)^2+G969*(1-MIN(tp_g/tp_roe,0.8))/(1+tp_r)^3+H969*(1-MIN(tp_g/tp_roe,0.8))/(1+tp_r)^4+I969*(1-MIN(tp_g/tp_roe,0.8))/(1+tp_r)^5+J969*(1-MIN(tp_g/tp_roe,0.8))/(1+tp_r)^6+J969*(1-MIN(tp_g/tp_roe,0.8))*(1+tp_g)/(tp_r-tp_g)/(1+tp_r)^6))*(1+tp_r) -> 90.653855 | H12: =Val!$B$33*(tp_wA*(2/12*E891+10/12*F891)+tp_wB*(2/12*E930+10/12*F930)+tp_wC*(2/12*E969+10/12*F969))*rm_factor -> 77.695657 | I12: =tp_w_dcf*G12+(1-tp_w_dcf)*H12 -> 84.174756 | J12: =I12/I$4-1 -> 0.10171
A13: 折舊年增調整：低 | B13: =TEXT(dag_adj_lo,"0.0%")&"（基準 "&TEXT(dag_adj,"0.0%")&"）" -> -5.0%（基準 0.0%） | C13: dag_adj | D13: =E1008 -> 7.7932567 | E13: =F1008 -> 9.2176057 | F13: =E13/E$4-1 -> 0.047276171 | G13: =(tp_wA*MAX(0,E1008*(1-MIN(tp_g/tp_roe,0.8))/(1+tp_r)^1+F1008*(1-MIN(tp_g/tp_roe,0.8))/(1+tp_r)^2+G1008*(1-MIN(tp_g/tp_roe,0.8))/(1+tp_r)^3+H1008*(1-MIN(tp_g/tp_roe,0.8))/(1+tp_r)^4+I1008*(1-MIN(tp_g/tp_roe,0.8))/(1+tp_r)^5+J1008*(1-MIN(tp_g/tp_roe,0.8))/(1+tp_r)^6+J1008*(1-MIN(tp_g/tp_roe,0.8))*(1+tp_g)/(tp_r-tp_g)/(1+tp_r)^6)+tp_wB*MAX(0,E1047*(1-MIN(tp_g/tp_roe,0.8))/(1+tp_r)^1+F1047*(1-MIN(tp_g/tp_roe,0.8))/(1+tp_r)^2+G1047*(1-MIN(tp_g/tp_roe,0.8))/(1+tp_r)^3+H1047*(1-MIN(tp_g/tp_roe,0.8))/(1+tp_r)^4+I1047*(1-MIN(tp_g/tp_roe,0.8))/(1+tp_r)^5+J1047*(1-MIN(tp_g/tp_roe,0.8))/(1+tp_r)^6+J1047*(1-MIN(tp_g/tp_roe,0.8))*(1+tp_g)/(tp_r-tp_g)/(1+tp_r)^6)+tp_wC*MAX(0,E1086*(1-MIN(tp_g/tp_roe,0.8))/(1+tp_r)^1+F1086*(1-MIN(tp_g/tp_roe,0.8))/(1+tp_r)^2+G1086*(1-MIN(tp_g/tp_roe,0.8))/(1+tp_r)^3+H1086*(1-MIN(tp_g/tp_roe,0.8))/(1+tp_r)^4+I1086*(1-MIN(tp_g/tp_roe,0.8))/(1+tp_r)^5+J1086*(1-MIN(tp_g/tp_roe,0.8))/(1+tp_r)^6+J1086*(1-MIN(tp_g/tp_roe,0.8))*(1+tp_g)/(tp_r-tp_g)/(1+tp_r)^6))*(1+tp_r) -> 89.978721 | H13: =Val!$B$33*(tp_wA*(2/12*E1008+10/12*F1008)+tp_wB*(2/12*E1047+10/12*F1047)+tp_wC*(2/12*E1086+10/12*F1086))*rm_factor -> 74.771249 | I13: =tp_w_dcf*G13+(1-tp_w_dcf)*H13 -> 82.374985 | J13: =I13/I$4-1 -> 0.078153929
A14: 折舊年增調整：高 | B14: =TEXT(dag_adj_hi,"0.0%")&"（基準 "&TEXT(dag_adj,"0.0%")&"）" -> 5.0%（基準 0.0%） | C14: dag_adj | D14: =E1125 -> 7.4097531 | E14: =F1125 -> 8.3662277 | F14: =E14/E$4-1 -> -0.049454796 | G14: =(tp_wA*MAX(0,E1125*(1-MIN(tp_g/tp_roe,0.8))/(1+tp_r)^1+F1125*(1-MIN(tp_g/tp_roe,0.8))/(1+tp_r)^2+G1125*(1-MIN(tp_g/tp_roe,0.8))/(1+tp_r)^3+H1125*(1-MIN(tp_g/tp_roe,0.8))/(1+tp_r)^4+I1125*(1-MIN(tp_g/tp_roe,0.8))/(1+tp_r)^5+J1125*(1-MIN(tp_g/tp_roe,0.8))/(1+tp_r)^6+J1125*(1-MIN(tp_g/tp_roe,0.8))*(1+tp_g)/(tp_r-tp_g)/(1+tp_r)^6)+tp_wB*MAX(0,E1164*(1-MIN(tp_g/tp_roe,0.8))/(1+tp_r)^1+F1164*(1-MIN(tp_g/tp_roe,0.8))/(1+tp_r)^2+G1164*(1-MIN(tp_g/tp_roe,0.8))/(1+tp_r)^3+H1164*(1-MIN(tp_g/tp_roe,0.8))/(1+tp_r)^4+I1164*(1-MIN(tp_g/tp_roe,0.8))/(1+tp_r)^5+J1164*(1-MIN(tp_g/tp_roe,0.8))/(1+tp_r)^6+J1164*(1-MIN(tp_g/tp_roe,0.8))*(1+tp_g)/(tp_r-tp_g)/(1+tp_r)^6)+tp_wC*MAX(0,E1203*(1-MIN(tp_g/tp_roe,0.8))/(1+tp_r)^1+F1203*(1-MIN(tp_g/tp_roe,0.8))/(1+tp_r)^2+G1203*(1-MIN(tp_g/tp_roe,0.8))/(1+tp_r)^3+H1203*(1-MIN(tp_g/tp_roe,0.8))/(1+tp_r)^4+I1203*(1-MIN(tp_g/tp_roe,0.8))/(1+tp_r)^5+J1203*(1-MIN(tp_g/tp_roe,0.8))/(1+tp_r)^6+J1203*(1-MIN(tp_g/tp_roe,0.8))*(1+tp_g)/(tp_r-tp_g)/(1+tp_r)^6))*(1+tp_r) -> 74.27077 | H14: =Val!$B$33*(tp_wA*(2/12*E1125+10/12*F1125)+tp_wB*(2/12*E1164+10/12*F1164)+tp_wC*(2/12*E1203+10/12*F1203))*rm_factor -> 65.718614 | I14: =tp_w_dcf*G14+(1-tp_w_dcf)*H14 -> 69.994692 | J14: =I14/I$4-1 -> -0.083883871
A15: 每片現金成本年增：低 | B15: =TEXT(cc_g_lo,"0.0%")&"（基準 "&TEXT(cc_g,"0.0%")&"）" -> 0.0%（基準 2.0%） | C15: cc_g | D15: =E1242 -> 7.7987043 | E15: =F1242 -> 9.2232445 | F15: =E15/E$4-1 -> 0.047916838 | G15: =(tp_wA*MAX(0,E1242*(1-MIN(tp_g/tp_roe,0.8))/(1+tp_r)^1+F1242*(1-MIN(tp_g/tp_roe,0.8))/(1+tp_r)^2+G1242*(1-MIN(tp_g/tp_roe,0.8))/(1+tp_r)^3+H1242*(1-MIN(tp_g/tp_roe,0.8))/(1+tp_r)^4+I1242*(1-MIN(tp_g/tp_roe,0.8))/(1+tp_r)^5+J1242*(1-MIN(tp_g/tp_roe,0.8))/(1+tp_r)^6+J1242*(1-MIN(tp_g/tp_roe,0.8))*(1+tp_g)/(tp_r-tp_g)/(1+tp_r)^6)+tp_wB*MAX(0,E1281*(1-MIN(tp_g/tp_roe,0.8))/(1+tp_r)^1+F1281*(1-MIN(tp_g/tp_roe,0.8))/(1+tp_r)^2+G1281*(1-MIN(tp_g/tp_roe,0.8))/(1+tp_r)^3+H1281*(1-MIN(tp_g/tp_roe,0.8))/(1+tp_r)^4+I1281*(1-MIN(tp_g/tp_roe,0.8))/(1+tp_r)^5+J1281*(1-MIN(tp_g/tp_roe,0.8))/(1+tp_r)^6+J1281*(1-MIN(tp_g/tp_roe,0.8))*(1+tp_g)/(tp_r-tp_g)/(1+tp_r)^6)+tp_wC*MAX(0,E1320*(1-MIN(tp_g/tp_roe,0.8))/(1+tp_r)^1+F1320*(1-MIN(tp_g/tp_roe,0.8))/(1+tp_r)^2+G1320*(1-MIN(tp_g/tp_roe,0.8))/(1+tp_r)^3+H1320*(1-MIN(tp_g/tp_roe,0.8))/(1+tp_r)^4+I1320*(1-MIN(tp_g/tp_roe,0.8))/(1+tp_r)^5+J1320*(1-MIN(tp_g/tp_roe,0.8))/(1+tp_r)^6+J1320*(1-MIN(tp_g/tp_roe,0.8))*(1+tp_g)/(tp_r-tp_g)/(1+tp_r)^6))*(1+tp_r) -> 89.717156 | H15: =Val!$B$33*(tp_wA*(2/12*E1242+10/12*F1242)+tp_wB*(2/12*E1281+10/12*F1281)+tp_wC*(2/12*E1320+10/12*F1320))*rm_factor -> 74.505509 | I15: =tp_w_dcf*G15+(1-tp_w_dcf)*H15 -> 82.111332 | J15: =I15/I$4-1 -> 0.074703151
A16: 每片現金成本年增：高 | B16: =TEXT(cc_g_hi,"0.0%")&"（基準 "&TEXT(cc_g,"0.0%")&"）" -> 4.0%（基準 2.0%） | C16: cc_g | D16: =E1359 -> 7.4043055 | E16: =F1359 -> 8.3714127 | F16: =E16/E$4-1 -> -0.048865687 | G16: =(tp_wA*MAX(0,E1359*(1-MIN(tp_g/tp_roe,0.8))/(1+tp_r)^1+F1359*(1-MIN(tp_g/tp_roe,0.8))/(1+tp_r)^2+G1359*(1-MIN(tp_g/tp_roe,0.8))/(1+tp_r)^3+H1359*(1-MIN(tp_g/tp_roe,0.8))/(1+tp_r)^4+I1359*(1-MIN(tp_g/tp_roe,0.8))/(1+tp_r)^5+J1359*(1-MIN(tp_g/tp_roe,0.8))/(1+tp_r)^6+J1359*(1-MIN(tp_g/tp_roe,0.8))*(1+tp_g)/(tp_r-tp_g)/(1+tp_r)^6)+tp_wB*MAX(0,E1398*(1-MIN(tp_g/tp_roe,0.8))/(1+tp_r)^1+F1398*(1-MIN(tp_g/tp_roe,0.8))/(1+tp_r)^2+G1398*(1-MIN(tp_g/tp_roe,0.8))/(1+tp_r)^3+H1398*(1-MIN(tp_g/tp_roe,0.8))/(1+tp_r)^4+I1398*(1-MIN(tp_g/tp_roe,0.8))/(1+tp_r)^5+J1398*(1-MIN(tp_g/tp_roe,0.8))/(1+tp_r)^6+J1398*(1-MIN(tp_g/tp_roe,0.8))*(1+tp_g)/(tp_r-tp_g)/(1+tp_r)^6)+tp_wC*MAX(0,E1437*(1-MIN(tp_g/tp_roe,0.8))/(1+tp_r)^1+F1437*(1-MIN(tp_g/tp_roe,0.8))/(1+tp_r)^2+G1437*(1-MIN(tp_g/tp_roe,0.8))/(1+tp_r)^3+H1437*(1-MIN(tp_g/tp_roe,0.8))/(1+tp_r)^4+I1437*(1-MIN(tp_g/tp_roe,0.8))/(1+tp_r)^5+J1437*(1-MIN(tp_g/tp_roe,0.8))/(1+tp_r)^6+J1437*(1-MIN(tp_g/tp_roe,0.8))*(1+tp_g)/(tp_r-tp_g)/(1+tp_r)^6))*(1+tp_r) -> 74.941403 | H16: =Val!$B$33*(tp_wA*(2/12*E1359+10/12*F1359)+tp_wB*(2/12*E1398+10/12*F1398)+tp_wC*(2/12*E1437+10/12*F1437))*rm_factor -> 66.096085 | I16: =tp_w_dcf*G16+(1-tp_w_dcf)*H16 -> 70.518744 | J16: =I16/I$4-1 -> -0.07702488
A17: 營業費用彈性：低 | B17: =TEXT(phi_lo,"0.00")&"（基準 "&TEXT(phi,"0.00")&"）" -> 0.30（基準 0.50） | C17: phi | D17: =E1476 -> 7.7042352 | E17: =F1476 -> 8.962527 | F17: =E17/E$4-1 -> 0.01829491 | G17: =(tp_wA*MAX(0,E1476*(1-MIN(tp_g/tp_roe,0.8))/(1+tp_r)^1+F1476*(1-MIN(tp_g/tp_roe,0.8))/(1+tp_r)^2+G1476*(1-MIN(tp_g/tp_roe,0.8))/(1+tp_r)^3+H1476*(1-MIN(tp_g/tp_roe,0.8))/(1+tp_r)^4+I1476*(1-MIN(tp_g/tp_roe,0.8))/(1+tp_r)^5+J1476*(1-MIN(tp_g/tp_roe,0.8))/(1+tp_r)^6+J1476*(1-MIN(tp_g/tp_roe,0.8))*(1+tp_g)/(tp_r-tp_g)/(1+tp_r)^6)+tp_wB*MAX(0,E1515*(1-MIN(tp_g/tp_roe,0.8))/(1+tp_r)^1+F1515*(1-MIN(tp_g/tp_roe,0.8))/(1+tp_r)^2+G1515*(1-MIN(tp_g/tp_roe,0.8))/(1+tp_r)^3+H1515*(1-MIN(tp_g/tp_roe,0.8))/(1+tp_r)^4+I1515*(1-MIN(tp_g/tp_roe,0.8))/(1+tp_r)^5+J1515*(1-MIN(tp_g/tp_roe,0.8))/(1+tp_r)^6+J1515*(1-MIN(tp_g/tp_roe,0.8))*(1+tp_g)/(tp_r-tp_g)/(1+tp_r)^6)+tp_wC*MAX(0,E1554*(1-MIN(tp_g/tp_roe,0.8))/(1+tp_r)^1+F1554*(1-MIN(tp_g/tp_roe,0.8))/(1+tp_r)^2+G1554*(1-MIN(tp_g/tp_roe,0.8))/(1+tp_r)^3+H1554*(1-MIN(tp_g/tp_roe,0.8))/(1+tp_r)^4+I1554*(1-MIN(tp_g/tp_roe,0.8))/(1+tp_r)^5+J1554*(1-MIN(tp_g/tp_roe,0.8))/(1+tp_r)^6+J1554*(1-MIN(tp_g/tp_roe,0.8))*(1+tp_g)/(tp_r-tp_g)/(1+tp_r)^6))*(1+tp_r) -> 84.01283 | H17: =Val!$B$33*(tp_wA*(2/12*E1476+10/12*F1476)+tp_wB*(2/12*E1515+10/12*F1515)+tp_wC*(2/12*E1554+10/12*F1554))*rm_factor -> 71.209978 | I17: =tp_w_dcf*G17+(1-tp_w_dcf)*H17 -> 77.611404 | J17: =I17/I$4-1 -> 0.015806443
A18: 營業費用彈性：高 | B18: =TEXT(phi_hi,"0.00")&"（基準 "&TEXT(phi,"0.00")&"）" -> 0.80（基準 0.50） | C18: phi | D18: =E1593 -> 7.4474094 | E18: =F1593 -> 8.5500792 | F18: =E18/E$4-1 -> -0.028566149 | G18: =(tp_wA*MAX(0,E1593*(1-MIN(tp_g/tp_roe,0.8))/(1+tp_r)^1+F1593*(1-MIN(tp_g/tp_roe,0.8))/(1+tp_r)^2+G1593*(1-MIN(tp_g/tp_roe,0.8))/(1+tp_r)^3+H1593*(1-MIN(tp_g/tp_roe,0.8))/(1+tp_r)^4+I1593*(1-MIN(tp_g/tp_roe,0.8))/(1+tp_r)^5+J1593*(1-MIN(tp_g/tp_roe,0.8))/(1+tp_r)^6+J1593*(1-MIN(tp_g/tp_roe,0.8))*(1+tp_g)/(tp_r-tp_g)/(1+tp_r)^6)+tp_wB*MAX(0,E1632*(1-MIN(tp_g/tp_roe,0.8))/(1+tp_r)^1+F1632*(1-MIN(tp_g/tp_roe,0.8))/(1+tp_r)^2+G1632*(1-MIN(tp_g/tp_roe,0.8))/(1+tp_r)^3+H1632*(1-MIN(tp_g/tp_roe,0.8))/(1+tp_r)^4+I1632*(1-MIN(tp_g/tp_roe,0.8))/(1+tp_r)^5+J1632*(1-MIN(tp_g/tp_roe,0.8))/(1+tp_r)^6+J1632*(1-MIN(tp_g/tp_roe,0.8))*(1+tp_g)/(tp_r-tp_g)/(1+tp_r)^6)+tp_wC*MAX(0,E1671*(1-MIN(tp_g/tp_roe,0.8))/(1+tp_r)^1+F1671*(1-MIN(tp_g/tp_roe,0.8))/(1+tp_r)^2+G1671*(1-MIN(tp_g/tp_roe,0.8))/(1+tp_r)^3+H1671*(1-MIN(tp_g/tp_roe,0.8))/(1+tp_r)^4+I1671*(1-MIN(tp_g/tp_roe,0.8))/(1+tp_r)^5+J1671*(1-MIN(tp_g/tp_roe,0.8))/(1+tp_r)^6+J1671*(1-MIN(tp_g/tp_roe,0.8))*(1+tp_g)/(tp_r-tp_g)/(1+tp_r)^6))*(1+tp_r) -> 79.891422 | H18: =Val!$B$33*(tp_wA*(2/12*E1593+10/12*F1593)+tp_wB*(2/12*E1632+10/12*F1632)+tp_wC*(2/12*E1671+10/12*F1671))*rm_factor -> 68.888391 | I18: =tp_w_dcf*G18+(1-tp_w_dcf)*H18 -> 74.389907 | J18: =I18/I$4-1 -> -0.026357693
A19: 營業外淨額：低 | B19: =TEXT(nonop_f_lo,"0.0")&"（基準 "&TEXT(nonop_f,"0.0")&"）" -> 2.0（基準 4.0） | C19: nonop_f | D19: =E1710 -> 7.4649587 | E19: =F1710 -> 8.6649581 | F19: =E19/E$4-1 -> -0.01551396 | G19: =(tp_wA*MAX(0,E1710*(1-MIN(tp_g/tp_roe,0.8))/(1+tp_r)^1+F1710*(1-MIN(tp_g/tp_roe,0.8))/(1+tp_r)^2+G1710*(1-MIN(tp_g/tp_roe,0.8))/(1+tp_r)^3+H1710*(1-MIN(tp_g/tp_roe,0.8))/(1+tp_r)^4+I1710*(1-MIN(tp_g/tp_roe,0.8))/(1+tp_r)^5+J1710*(1-MIN(tp_g/tp_roe,0.8))/(1+tp_r)^6+J1710*(1-MIN(tp_g/tp_roe,0.8))*(1+tp_g)/(tp_r-tp_g)/(1+tp_r)^6)+tp_wB*MAX(0,E1749*(1-MIN(tp_g/tp_roe,0.8))/(1+tp_r)^1+F1749*(1-MIN(tp_g/tp_roe,0.8))/(1+tp_r)^2+G1749*(1-MIN(tp_g/tp_roe,0.8))/(1+tp_r)^3+H1749*(1-MIN(tp_g/tp_roe,0.8))/(1+tp_r)^4+I1749*(1-MIN(tp_g/tp_roe,0.8))/(1+tp_r)^5+J1749*(1-MIN(tp_g/tp_roe,0.8))/(1+tp_r)^6+J1749*(1-MIN(tp_g/tp_roe,0.8))*(1+tp_g)/(tp_r-tp_g)/(1+tp_r)^6)+tp_wC*MAX(0,E1788*(1-MIN(tp_g/tp_roe,0.8))/(1+tp_r)^1+F1788*(1-MIN(tp_g/tp_roe,0.8))/(1+tp_r)^2+G1788*(1-MIN(tp_g/tp_roe,0.8))/(1+tp_r)^3+H1788*(1-MIN(tp_g/tp_roe,0.8))/(1+tp_r)^4+I1788*(1-MIN(tp_g/tp_roe,0.8))/(1+tp_r)^5+J1788*(1-MIN(tp_g/tp_roe,0.8))/(1+tp_r)^6+J1788*(1-MIN(tp_g/tp_roe,0.8))*(1+tp_g)/(tp_r-tp_g)/(1+tp_r)^6))*(1+tp_r) -> 80.824298 | H19: =Val!$B$33*(tp_wA*(2/12*E1710+10/12*F1710)+tp_wB*(2/12*E1749+10/12*F1749)+tp_wC*(2/12*E1788+10/12*F1788))*rm_factor -> 68.740177 | I19: =tp_w_dcf*G19+(1-tp_w_dcf)*H19 -> 74.782238 | J19: =I19/I$4-1 -> -0.021222718
A20: 營業外淨額：高 | B20: =TEXT(nonop_f_hi,"0.0")&"（基準 "&TEXT(nonop_f,"0.0")&"）" -> 8.0（基準 4.0） | C20: nonop_f | D20: =E1827 -> 7.8745973 | E20: =F1827 -> 9.0745966 | F20: =E20/E$4-1 -> 0.03102792 | G20: =(tp_wA*MAX(0,E1827*(1-MIN(tp_g/tp_roe,0.8))/(1+tp_r)^1+F1827*(1-MIN(tp_g/tp_roe,0.8))/(1+tp_r)^2+G1827*(1-MIN(tp_g/tp_roe,0.8))/(1+tp_r)^3+H1827*(1-MIN(tp_g/tp_roe,0.8))/(1+tp_r)^4+I1827*(1-MIN(tp_g/tp_roe,0.8))/(1+tp_r)^5+J1827*(1-MIN(tp_g/tp_roe,0.8))/(1+tp_r)^6+J1827*(1-MIN(tp_g/tp_roe,0.8))*(1+tp_g)/(tp_r-tp_g)/(1+tp_r)^6)+tp_wB*MAX(0,E1866*(1-MIN(tp_g/tp_roe,0.8))/(1+tp_r)^1+F1866*(1-MIN(tp_g/tp_roe,0.8))/(1+tp_r)^2+G1866*(1-MIN(tp_g/tp_roe,0.8))/(1+tp_r)^3+H1866*(1-MIN(tp_g/tp_roe,0.8))/(1+tp_r)^4+I1866*(1-MIN(tp_g/tp_roe,0.8))/(1+tp_r)^5+J1866*(1-MIN(tp_g/tp_roe,0.8))/(1+tp_r)^6+J1866*(1-MIN(tp_g/tp_roe,0.8))*(1+tp_g)/(tp_r-tp_g)/(1+tp_r)^6)+tp_wC*MAX(0,E1905*(1-MIN(tp_g/tp_roe,0.8))/(1+tp_r)^1+F1905*(1-MIN(tp_g/tp_roe,0.8))/(1+tp_r)^2+G1905*(1-MIN(tp_g/tp_roe,0.8))/(1+tp_r)^3+H1905*(1-MIN(tp_g/tp_roe,0.8))/(1+tp_r)^4+I1905*(1-MIN(tp_g/tp_roe,0.8))/(1+tp_r)^5+J1905*(1-MIN(tp_g/tp_roe,0.8))/(1+tp_r)^6+J1905*(1-MIN(tp_g/tp_roe,0.8))*(1+tp_g)/(tp_r-tp_g)/(1+tp_r)^6))*(1+tp_r) -> 85.758448 | H20: =Val!$B$33*(tp_wA*(2/12*E1827+10/12*F1827)+tp_wB*(2/12*E1866+10/12*F1866)+tp_wC*(2/12*E1905+10/12*F1905))*rm_factor -> 73.534997 | I20: =tp_w_dcf*G20+(1-tp_w_dcf)*H20 -> 79.646723 | J20: =I20/I$4-1 -> 0.042445436
A21: 稅率：低 | B21: =TEXT(tax_lo,"0%")&"（基準 "&TEXT(tax,"0%")&"）" -> 12%（基準 15%） | C21: tax | D21: =E1944 -> 7.8697933 | E21: =F1944 -> 9.1121456 | F21: =E21/E$4-1 -> 0.035294118 | G21: =(tp_wA*MAX(0,E1944*(1-MIN(tp_g/tp_roe,0.8))/(1+tp_r)^1+F1944*(1-MIN(tp_g/tp_roe,0.8))/(1+tp_r)^2+G1944*(1-MIN(tp_g/tp_roe,0.8))/(1+tp_r)^3+H1944*(1-MIN(tp_g/tp_roe,0.8))/(1+tp_r)^4+I1944*(1-MIN(tp_g/tp_roe,0.8))/(1+tp_r)^5+J1944*(1-MIN(tp_g/tp_roe,0.8))/(1+tp_r)^6+J1944*(1-MIN(tp_g/tp_roe,0.8))*(1+tp_g)/(tp_r-tp_g)/(1+tp_r)^6)+tp_wB*MAX(0,E1983*(1-MIN(tp_g/tp_roe,0.8))/(1+tp_r)^1+F1983*(1-MIN(tp_g/tp_roe,0.8))/(1+tp_r)^2+G1983*(1-MIN(tp_g/tp_roe,0.8))/(1+tp_r)^3+H1983*(1-MIN(tp_g/tp_roe,0.8))/(1+tp_r)^4+I1983*(1-MIN(tp_g/tp_roe,0.8))/(1+tp_r)^5+J1983*(1-MIN(tp_g/tp_roe,0.8))/(1+tp_r)^6+J1983*(1-MIN(tp_g/tp_roe,0.8))*(1+tp_g)/(tp_r-tp_g)/(1+tp_r)^6)+tp_wC*MAX(0,E2022*(1-MIN(tp_g/tp_roe,0.8))/(1+tp_r)^1+F2022*(1-MIN(tp_g/tp_roe,0.8))/(1+tp_r)^2+G2022*(1-MIN(tp_g/tp_roe,0.8))/(1+tp_r)^3+H2022*(1-MIN(tp_g/tp_roe,0.8))/(1+tp_r)^4+I2022*(1-MIN(tp_g/tp_roe,0.8))/(1+tp_r)^5+J2022*(1-MIN(tp_g/tp_roe,0.8))/(1+tp_r)^6+J2022*(1-MIN(tp_g/tp_roe,0.8))*(1+tp_g)/(tp_r-tp_g)/(1+tp_r)^6))*(1+tp_r) -> 85.379686 | H21: =Val!$B$33*(tp_wA*(2/12*E1944+10/12*F1944)+tp_wB*(2/12*E1983+10/12*F1983)+tp_wC*(2/12*E2022+10/12*F2022))*rm_factor -> 72.820984 | I21: =tp_w_dcf*G21+(1-tp_w_dcf)*H21 -> 79.100335 | J21: =I21/I$4-1 -> 0.035294118
A22: 稅率：高 | B22: =TEXT(tax_hi,"0%")&"（基準 "&TEXT(tax,"0%")&"）" -> 20%（基準 15%） | C22: tax | D22: =E2061 -> 7.1543576 | E22: =F2061 -> 8.2837687 | F22: =E22/E$4-1 -> -0.058823529 | G22: =(tp_wA*MAX(0,E2061*(1-MIN(tp_g/tp_roe,0.8))/(1+tp_r)^1+F2061*(1-MIN(tp_g/tp_roe,0.8))/(1+tp_r)^2+G2061*(1-MIN(tp_g/tp_roe,0.8))/(1+tp_r)^3+H2061*(1-MIN(tp_g/tp_roe,0.8))/(1+tp_r)^4+I2061*(1-MIN(tp_g/tp_roe,0.8))/(1+tp_r)^5+J2061*(1-MIN(tp_g/tp_roe,0.8))/(1+tp_r)^6+J2061*(1-MIN(tp_g/tp_roe,0.8))*(1+tp_g)/(tp_r-tp_g)/(1+tp_r)^6)+tp_wB*MAX(0,E2100*(1-MIN(tp_g/tp_roe,0.8))/(1+tp_r)^1+F2100*(1-MIN(tp_g/tp_roe,0.8))/(1+tp_r)^2+G2100*(1-MIN(tp_g/tp_roe,0.8))/(1+tp_r)^3+H2100*(1-MIN(tp_g/tp_roe,0.8))/(1+tp_r)^4+I2100*(1-MIN(tp_g/tp_roe,0.8))/(1+tp_r)^5+J2100*(1-MIN(tp_g/tp_roe,0.8))/(1+tp_r)^6+J2100*(1-MIN(tp_g/tp_roe,0.8))*(1+tp_g)/(tp_r-tp_g)/(1+tp_r)^6)+tp_wC*MAX(0,E2139*(1-MIN(tp_g/tp_roe,0.8))/(1+tp_r)^1+F2139*(1-MIN(tp_g/tp_roe,0.8))/(1+tp_r)^2+G2139*(1-MIN(tp_g/tp_roe,0.8))/(1+tp_r)^3+H2139*(1-MIN(tp_g/tp_roe,0.8))/(1+tp_r)^4+I2139*(1-MIN(tp_g/tp_roe,0.8))/(1+tp_r)^5+J2139*(1-MIN(tp_g/tp_roe,0.8))/(1+tp_r)^6+J2139*(1-MIN(tp_g/tp_roe,0.8))*(1+tp_g)/(tp_r-tp_g)/(1+tp_r)^6))*(1+tp_r) -> 77.617897 | H22: =Val!$B$33*(tp_wA*(2/12*E2061+10/12*F2061)+tp_wB*(2/12*E2100+10/12*F2100)+tp_wC*(2/12*E2139+10/12*F2139))*rm_factor -> 66.200895 | I22: =tp_w_dcf*G22+(1-tp_w_dcf)*H22 -> 71.909396 | J22: =I22/I$4-1 -> -0.058823529
A23: AI 相關營收係數：低 | B23: =TEXT(ai_adj_lo,"0.00")&"（基準 "&TEXT(ai_adj,"0.00")&"）" -> 0.70（基準 1.00） | C23: ai_adj | D23: =E2178 -> 7.4752492 | E23: =F2178 -> 8.6169426 | F23: =E23/E$4-1 -> -0.020969331 | G23: =(tp_wA*MAX(0,E2178*(1-MIN(tp_g/tp_roe,0.8))/(1+tp_r)^1+F2178*(1-MIN(tp_g/tp_roe,0.8))/(1+tp_r)^2+G2178*(1-MIN(tp_g/tp_roe,0.8))/(1+tp_r)^3+H2178*(1-MIN(tp_g/tp_roe,0.8))/(1+tp_r)^4+I2178*(1-MIN(tp_g/tp_roe,0.8))/(1+tp_r)^5+J2178*(1-MIN(tp_g/tp_roe,0.8))/(1+tp_r)^6+J2178*(1-MIN(tp_g/tp_roe,0.8))*(1+tp_g)/(tp_r-tp_g)/(1+tp_r)^6)+tp_wB*MAX(0,E2217*(1-MIN(tp_g/tp_roe,0.8))/(1+tp_r)^1+F2217*(1-MIN(tp_g/tp_roe,0.8))/(1+tp_r)^2+G2217*(1-MIN(tp_g/tp_roe,0.8))/(1+tp_r)^3+H2217*(1-MIN(tp_g/tp_roe,0.8))/(1+tp_r)^4+I2217*(1-MIN(tp_g/tp_roe,0.8))/(1+tp_r)^5+J2217*(1-MIN(tp_g/tp_roe,0.8))/(1+tp_r)^6+J2217*(1-MIN(tp_g/tp_roe,0.8))*(1+tp_g)/(tp_r-tp_g)/(1+tp_r)^6)+tp_wC*MAX(0,E2256*(1-MIN(tp_g/tp_roe,0.8))/(1+tp_r)^1+F2256*(1-MIN(tp_g/tp_roe,0.8))/(1+tp_r)^2+G2256*(1-MIN(tp_g/tp_roe,0.8))/(1+tp_r)^3+H2256*(1-MIN(tp_g/tp_roe,0.8))/(1+tp_r)^4+I2256*(1-MIN(tp_g/tp_roe,0.8))/(1+tp_r)^5+J2256*(1-MIN(tp_g/tp_roe,0.8))/(1+tp_r)^6+J2256*(1-MIN(tp_g/tp_roe,0.8))*(1+tp_g)/(tp_r-tp_g)/(1+tp_r)^6))*(1+tp_r) -> 79.688946 | H23: =Val!$B$33*(tp_wA*(2/12*E2178+10/12*F2178)+tp_wB*(2/12*E2217+10/12*F2217)+tp_wC*(2/12*E2256+10/12*F2256))*rm_factor -> 68.7616 | I23: =tp_w_dcf*G23+(1-tp_w_dcf)*H23 -> 74.225273 | J23: =I23/I$4-1 -> -0.028512479
A24: AI 相關營收係數：高 | B24: =TEXT(ai_adj_hi,"0.00")&"（基準 "&TEXT(ai_adj,"0.00")&"）" -> 1.30（基準 1.00） | C24: ai_adj | D24: =E2295 -> 7.7277606 | E24: =F2295 -> 8.9861157 | F24: =E24/E$4-1 -> 0.020974992 | G24: =(tp_wA*MAX(0,E2295*(1-MIN(tp_g/tp_roe,0.8))/(1+tp_r)^1+F2295*(1-MIN(tp_g/tp_roe,0.8))/(1+tp_r)^2+G2295*(1-MIN(tp_g/tp_roe,0.8))/(1+tp_r)^3+H2295*(1-MIN(tp_g/tp_roe,0.8))/(1+tp_r)^4+I2295*(1-MIN(tp_g/tp_roe,0.8))/(1+tp_r)^5+J2295*(1-MIN(tp_g/tp_roe,0.8))/(1+tp_r)^6+J2295*(1-MIN(tp_g/tp_roe,0.8))*(1+tp_g)/(tp_r-tp_g)/(1+tp_r)^6)+tp_wB*MAX(0,E2334*(1-MIN(tp_g/tp_roe,0.8))/(1+tp_r)^1+F2334*(1-MIN(tp_g/tp_roe,0.8))/(1+tp_r)^2+G2334*(1-MIN(tp_g/tp_roe,0.8))/(1+tp_r)^3+H2334*(1-MIN(tp_g/tp_roe,0.8))/(1+tp_r)^4+I2334*(1-MIN(tp_g/tp_roe,0.8))/(1+tp_r)^5+J2334*(1-MIN(tp_g/tp_roe,0.8))/(1+tp_r)^6+J2334*(1-MIN(tp_g/tp_roe,0.8))*(1+tp_g)/(tp_r-tp_g)/(1+tp_r)^6)+tp_wC*MAX(0,E2373*(1-MIN(tp_g/tp_roe,0.8))/(1+tp_r)^1+F2373*(1-MIN(tp_g/tp_roe,0.8))/(1+tp_r)^2+G2373*(1-MIN(tp_g/tp_roe,0.8))/(1+tp_r)^3+H2373*(1-MIN(tp_g/tp_roe,0.8))/(1+tp_r)^4+I2373*(1-MIN(tp_g/tp_roe,0.8))/(1+tp_r)^5+J2373*(1-MIN(tp_g/tp_roe,0.8))/(1+tp_r)^6+J2373*(1-MIN(tp_g/tp_roe,0.8))*(1+tp_g)/(tp_r-tp_g)/(1+tp_r)^6))*(1+tp_r) -> 85.261548 | H24: =Val!$B$33*(tp_wA*(2/12*E2295+10/12*F2295)+tp_wB*(2/12*E2334+10/12*F2334)+tp_wC*(2/12*E2373+10/12*F2373))*rm_factor -> 71.915447 | I24: =tp_w_dcf*G24+(1-tp_w_dcf)*H24 -> 78.588498 | J24: =I24/I$4-1 -> 0.028595002
A25: 新業務邊際貢獻率：低 | B25: =TEXT(m_new_lo,"0%")&"（基準 "&TEXT(m_new,"0%")&"）" -> 35%（基準 45%） | C25: m_new | D25: =E2412 -> 7.571559 | E25: =F2412 -> 8.6757367 | F25: =E25/E$4-1 -> -0.014289332 | G25: =(tp_wA*MAX(0,E2412*(1-MIN(tp_g/tp_roe,0.8))/(1+tp_r)^1+F2412*(1-MIN(tp_g/tp_roe,0.8))/(1+tp_r)^2+G2412*(1-MIN(tp_g/tp_roe,0.8))/(1+tp_r)^3+H2412*(1-MIN(tp_g/tp_roe,0.8))/(1+tp_r)^4+I2412*(1-MIN(tp_g/tp_roe,0.8))/(1+tp_r)^5+J2412*(1-MIN(tp_g/tp_roe,0.8))/(1+tp_r)^6+J2412*(1-MIN(tp_g/tp_roe,0.8))*(1+tp_g)/(tp_r-tp_g)/(1+tp_r)^6)+tp_wB*MAX(0,E2451*(1-MIN(tp_g/tp_roe,0.8))/(1+tp_r)^1+F2451*(1-MIN(tp_g/tp_roe,0.8))/(1+tp_r)^2+G2451*(1-MIN(tp_g/tp_roe,0.8))/(1+tp_r)^3+H2451*(1-MIN(tp_g/tp_roe,0.8))/(1+tp_r)^4+I2451*(1-MIN(tp_g/tp_roe,0.8))/(1+tp_r)^5+J2451*(1-MIN(tp_g/tp_roe,0.8))/(1+tp_r)^6+J2451*(1-MIN(tp_g/tp_roe,0.8))*(1+tp_g)/(tp_r-tp_g)/(1+tp_r)^6)+tp_wC*MAX(0,E2490*(1-MIN(tp_g/tp_roe,0.8))/(1+tp_r)^1+F2490*(1-MIN(tp_g/tp_roe,0.8))/(1+tp_r)^2+G2490*(1-MIN(tp_g/tp_roe,0.8))/(1+tp_r)^3+H2490*(1-MIN(tp_g/tp_roe,0.8))/(1+tp_r)^4+I2490*(1-MIN(tp_g/tp_roe,0.8))/(1+tp_r)^5+J2490*(1-MIN(tp_g/tp_roe,0.8))/(1+tp_r)^6+J2490*(1-MIN(tp_g/tp_roe,0.8))*(1+tp_g)/(tp_r-tp_g)/(1+tp_r)^6))*(1+tp_r) -> 80.690951 | H25: =Val!$B$33*(tp_wA*(2/12*E2412+10/12*F2412)+tp_wB*(2/12*E2451+10/12*F2451)+tp_wC*(2/12*E2490+10/12*F2490))*rm_factor -> 69.639532 | I25: =tp_w_dcf*G25+(1-tp_w_dcf)*H25 -> 75.165241 | J25: =I25/I$4-1 -> -0.016209831
A26: 新業務邊際貢獻率：高 | B26: =TEXT(m_new_hi,"0%")&"（基準 "&TEXT(m_new,"0%")&"）" -> 55%（基準 45%） | C26: m_new | D26: =E2529 -> 7.6314508 | E26: =F2529 -> 8.9272719 | F26: =E26/E$4-1 -> 0.014289332 | G26: =(tp_wA*MAX(0,E2529*(1-MIN(tp_g/tp_roe,0.8))/(1+tp_r)^1+F2529*(1-MIN(tp_g/tp_roe,0.8))/(1+tp_r)^2+G2529*(1-MIN(tp_g/tp_roe,0.8))/(1+tp_r)^3+H2529*(1-MIN(tp_g/tp_roe,0.8))/(1+tp_r)^4+I2529*(1-MIN(tp_g/tp_roe,0.8))/(1+tp_r)^5+J2529*(1-MIN(tp_g/tp_roe,0.8))/(1+tp_r)^6+J2529*(1-MIN(tp_g/tp_roe,0.8))*(1+tp_g)/(tp_r-tp_g)/(1+tp_r)^6)+tp_wB*MAX(0,E2568*(1-MIN(tp_g/tp_roe,0.8))/(1+tp_r)^1+F2568*(1-MIN(tp_g/tp_roe,0.8))/(1+tp_r)^2+G2568*(1-MIN(tp_g/tp_roe,0.8))/(1+tp_r)^3+H2568*(1-MIN(tp_g/tp_roe,0.8))/(1+tp_r)^4+I2568*(1-MIN(tp_g/tp_roe,0.8))/(1+tp_r)^5+J2568*(1-MIN(tp_g/tp_roe,0.8))/(1+tp_r)^6+J2568*(1-MIN(tp_g/tp_roe,0.8))*(1+tp_g)/(tp_r-tp_g)/(1+tp_r)^6)+tp_wC*MAX(0,E2607*(1-MIN(tp_g/tp_roe,0.8))/(1+tp_r)^1+F2607*(1-MIN(tp_g/tp_roe,0.8))/(1+tp_r)^2+G2607*(1-MIN(tp_g/tp_roe,0.8))/(1+tp_r)^3+H2607*(1-MIN(tp_g/tp_roe,0.8))/(1+tp_r)^4+I2607*(1-MIN(tp_g/tp_roe,0.8))/(1+tp_r)^5+J2607*(1-MIN(tp_g/tp_roe,0.8))/(1+tp_r)^6+J2607*(1-MIN(tp_g/tp_roe,0.8))*(1+tp_g)/(tp_r-tp_g)/(1+tp_r)^6))*(1+tp_r) -> 84.247079 | H26: =Val!$B$33*(tp_wA*(2/12*E2529+10/12*F2529)+tp_wB*(2/12*E2568+10/12*F2568)+tp_wC*(2/12*E2607+10/12*F2607))*rm_factor -> 71.037369 | I26: =tp_w_dcf*G26+(1-tp_w_dcf)*H26 -> 77.642224 | J26: =I26/I$4-1 -> 0.016209831
A27: 折現率 +1pt | B27: r 11% | C27: tp_r | D27: =PL!E94 -> 7.6015049 | E27: =PL!F94 -> 8.8015043 | F27: =E27/E$4-1 -> 0 | G27: =(tp_wA*MAX(0,PL!E94*(1-MIN(tp_g/tp_roe,0.8))/(1+(tp_r+0.01))^1+PL!F94*(1-MIN(tp_g/tp_roe,0.8))/(1+(tp_r+0.01))^2+PL!G94*(1-MIN(tp_g/tp_roe,0.8))/(1+(tp_r+0.01))^3+PL!H94*(1-MIN(tp_g/tp_roe,0.8))/(1+(tp_r+0.01))^4+PL!I94*(1-MIN(tp_g/tp_roe,0.8))/(1+(tp_r+0.01))^5+PL!J94*(1-MIN(tp_g/tp_roe,0.8))/(1+(tp_r+0.01))^6+PL!J94*(1-MIN(tp_g/tp_roe,0.8))*(1+tp_g)/((tp_r+0.01)-tp_g)/(1+(tp_r+0.01))^6)+tp_wB*MAX(0,PL!E133*(1-MIN(tp_g/tp_roe,0.8))/(1+(tp_r+0.01))^1+PL!F133*(1-MIN(tp_g/tp_roe,0.8))/(1+(tp_r+0.01))^2+PL!G133*(1-MIN(tp_g/tp_roe,0.8))/(1+(tp_r+0.01))^3+PL!H133*(1-MIN(tp_g/tp_roe,0.8))/(1+(tp_r+0.01))^4+PL!I133*(1-MIN(tp_g/tp_roe,0.8))/(1+(tp_r+0.01))^5+PL!J133*(1-MIN(tp_g/tp_roe,0.8))/(1+(tp_r+0.01))^6+PL!J133*(1-MIN(tp_g/tp_roe,0.8))*(1+tp_g)/((tp_r+0.01)-tp_g)/(1+(tp_r+0.01))^6)+tp_wC*MAX(0,PL!E172*(1-MIN(tp_g/tp_roe,0.8))/(1+(tp_r+0.01))^1+PL!F172*(1-MIN(tp_g/tp_roe,0.8))/(1+(tp_r+0.01))^2+PL!G172*(1-MIN(tp_g/tp_roe,0.8))/(1+(tp_r+0.01))^3+PL!H172*(1-MIN(tp_g/tp_roe,0.8))/(1+(tp_r+0.01))^4+PL!I172*(1-MIN(tp_g/tp_roe,0.8))/(1+(tp_r+0.01))^5+PL!J172*(1-MIN(tp_g/tp_roe,0.8))/(1+(tp_r+0.01))^6+PL!J172*(1-MIN(tp_g/tp_roe,0.8))*(1+tp_g)/((tp_r+0.01)-tp_g)/(1+(tp_r+0.01))^6))*(1+(tp_r+0.01)) -> 71.245078 | H27: =Val!$B$33*(tp_wA*(2/12*PL!E94+10/12*PL!F94)+tp_wB*(2/12*PL!E133+10/12*PL!F133)+tp_wC*(2/12*PL!E172+10/12*PL!F172))*rm_factor -> 70.338451 | I27: =tp_w_dcf*G27+(1-tp_w_dcf)*H27 -> 70.791764 | J27: =I27/I$4-1 -> -0.073451496
A28: 折現率 −1pt | B28: r 9% | C28: tp_r | D28: =PL!E94 -> 7.6015049 | E28: =PL!F94 -> 8.8015043 | F28: =E28/E$4-1 -> 0 | G28: =(tp_wA*MAX(0,PL!E94*(1-MIN(tp_g/tp_roe,0.8))/(1+(tp_r-0.01))^1+PL!F94*(1-MIN(tp_g/tp_roe,0.8))/(1+(tp_r-0.01))^2+PL!G94*(1-MIN(tp_g/tp_roe,0.8))/(1+(tp_r-0.01))^3+PL!H94*(1-MIN(tp_g/tp_roe,0.8))/(1+(tp_r-0.01))^4+PL!I94*(1-MIN(tp_g/tp_roe,0.8))/(1+(tp_r-0.01))^5+PL!J94*(1-MIN(tp_g/tp_roe,0.8))/(1+(tp_r-0.01))^6+PL!J94*(1-MIN(tp_g/tp_roe,0.8))*(1+tp_g)/((tp_r-0.01)-tp_g)/(1+(tp_r-0.01))^6)+tp_wB*MAX(0,PL!E133*(1-MIN(tp_g/tp_roe,0.8))/(1+(tp_r-0.01))^1+PL!F133*(1-MIN(tp_g/tp_roe,0.8))/(1+(tp_r-0.01))^2+PL!G133*(1-MIN(tp_g/tp_roe,0.8))/(1+(tp_r-0.01))^3+PL!H133*(1-MIN(tp_g/tp_roe,0.8))/(1+(tp_r-0.01))^4+PL!I133*(1-MIN(tp_g/tp_roe,0.8))/(1+(tp_r-0.01))^5+PL!J133*(1-MIN(tp_g/tp_roe,0.8))/(1+(tp_r-0.01))^6+PL!J133*(1-MIN(tp_g/tp_roe,0.8))*(1+tp_g)/((tp_r-0.01)-tp_g)/(1+(tp_r-0.01))^6)+tp_wC*MAX(0,PL!E172*(1-MIN(tp_g/tp_roe,0.8))/(1+(tp_r-0.01))^1+PL!F172*(1-MIN(tp_g/tp_roe,0.8))/(1+(tp_r-0.01))^2+PL!G172*(1-MIN(tp_g/tp_roe,0.8))/(1+(tp_r-0.01))^3+PL!H172*(1-MIN(tp_g/tp_roe,0.8))/(1+(tp_r-0.01))^4+PL!I172*(1-MIN(tp_g/tp_roe,0.8))/(1+(tp_r-0.01))^5+PL!J172*(1-MIN(tp_g/tp_roe,0.8))/(1+(tp_r-0.01))^6+PL!J172*(1-MIN(tp_g/tp_roe,0.8))*(1+tp_g)/((tp_r-0.01)-tp_g)/(1+(tp_r-0.01))^6))*(1+(tp_r-0.01)) -> 98.183858 | H28: =Val!$B$33*(tp_wA*(2/12*PL!E94+10/12*PL!F94)+tp_wB*(2/12*PL!E133+10/12*PL!F133)+tp_wC*(2/12*PL!E172+10/12*PL!F172))*rm_factor -> 70.338451 | I28: =tp_w_dcf*G28+(1-tp_w_dcf)*H28 -> 84.261154 | J28: =I28/I$4-1 -> 0.1028408
A29: 長期成長 +1pt | B29: g 5% | C29: tp_g | D29: =PL!E94 -> 7.6015049 | E29: =PL!F94 -> 8.8015043 | F29: =E29/E$4-1 -> 0 | G29: =(tp_wA*MAX(0,PL!E94*(1-MIN((tp_g+0.01)/tp_roe,0.8))/(1+tp_r)^1+PL!F94*(1-MIN((tp_g+0.01)/tp_roe,0.8))/(1+tp_r)^2+PL!G94*(1-MIN((tp_g+0.01)/tp_roe,0.8))/(1+tp_r)^3+PL!H94*(1-MIN((tp_g+0.01)/tp_roe,0.8))/(1+tp_r)^4+PL!I94*(1-MIN((tp_g+0.01)/tp_roe,0.8))/(1+tp_r)^5+PL!J94*(1-MIN((tp_g+0.01)/tp_roe,0.8))/(1+tp_r)^6+PL!J94*(1-MIN((tp_g+0.01)/tp_roe,0.8))*(1+(tp_g+0.01))/(tp_r-(tp_g+0.01))/(1+tp_r)^6)+tp_wB*MAX(0,PL!E133*(1-MIN((tp_g+0.01)/tp_roe,0.8))/(1+tp_r)^1+PL!F133*(1-MIN((tp_g+0.01)/tp_roe,0.8))/(1+tp_r)^2+PL!G133*(1-MIN((tp_g+0.01)/tp_roe,0.8))/(1+tp_r)^3+PL!H133*(1-MIN((tp_g+0.01)/tp_roe,0.8))/(1+tp_r)^4+PL!I133*(1-MIN((tp_g+0.01)/tp_roe,0.8))/(1+tp_r)^5+PL!J133*(1-MIN((tp_g+0.01)/tp_roe,0.8))/(1+tp_r)^6+PL!J133*(1-MIN((tp_g+0.01)/tp_roe,0.8))*(1+(tp_g+0.01))/(tp_r-(tp_g+0.01))/(1+tp_r)^6)+tp_wC*MAX(0,PL!E172*(1-MIN((tp_g+0.01)/tp_roe,0.8))/(1+tp_r)^1+PL!F172*(1-MIN((tp_g+0.01)/tp_roe,0.8))/(1+tp_r)^2+PL!G172*(1-MIN((tp_g+0.01)/tp_roe,0.8))/(1+tp_r)^3+PL!H172*(1-MIN((tp_g+0.01)/tp_roe,0.8))/(1+tp_r)^4+PL!I172*(1-MIN((tp_g+0.01)/tp_roe,0.8))/(1+tp_r)^5+PL!J172*(1-MIN((tp_g+0.01)/tp_roe,0.8))/(1+tp_r)^6+PL!J172*(1-MIN((tp_g+0.01)/tp_roe,0.8))*(1+(tp_g+0.01))/(tp_r-(tp_g+0.01))/(1+tp_r)^6))*(1+tp_r) -> 85.442443 | H29: =Val!$B$33*(tp_wA*(2/12*PL!E94+10/12*PL!F94)+tp_wB*(2/12*PL!E133+10/12*PL!F133)+tp_wC*(2/12*PL!E172+10/12*PL!F172))*rm_factor -> 70.338451 | I29: =tp_w_dcf*G29+(1-tp_w_dcf)*H29 -> 77.890447 | J29: =I29/I$4-1 -> 0.019458654
A30: 長期成長 −1pt | B30: g 3% | C30: tp_g | D30: =PL!E94 -> 7.6015049 | E30: =PL!F94 -> 8.8015043 | F30: =E30/E$4-1 -> 0 | G30: =(tp_wA*MAX(0,PL!E94*(1-MIN((tp_g-0.01)/tp_roe,0.8))/(1+tp_r)^1+PL!F94*(1-MIN((tp_g-0.01)/tp_roe,0.8))/(1+tp_r)^2+PL!G94*(1-MIN((tp_g-0.01)/tp_roe,0.8))/(1+tp_r)^3+PL!H94*(1-MIN((tp_g-0.01)/tp_roe,0.8))/(1+tp_r)^4+PL!I94*(1-MIN((tp_g-0.01)/tp_roe,0.8))/(1+tp_r)^5+PL!J94*(1-MIN((tp_g-0.01)/tp_roe,0.8))/(1+tp_r)^6+PL!J94*(1-MIN((tp_g-0.01)/tp_roe,0.8))*(1+(tp_g-0.01))/(tp_r-(tp_g-0.01))/(1+tp_r)^6)+tp_wB*MAX(0,PL!E133*(1-MIN((tp_g-0.01)/tp_roe,0.8))/(1+tp_r)^1+PL!F133*(1-MIN((tp_g-0.01)/tp_roe,0.8))/(1+tp_r)^2+PL!G133*(1-MIN((tp_g-0.01)/tp_roe,0.8))/(1+tp_r)^3+PL!H133*(1-MIN((tp_g-0.01)/tp_roe,0.8))/(1+tp_r)^4+PL!I133*(1-MIN((tp_g-0.01)/tp_roe,0.8))/(1+tp_r)^5+PL!J133*(1-MIN((tp_g-0.01)/tp_roe,0.8))/(1+tp_r)^6+PL!J133*(1-MIN((tp_g-0.01)/tp_roe,0.8))*(1+(tp_g-0.01))/(tp_r-(tp_g-0.01))/(1+tp_r)^6)+tp_wC*MAX(0,PL!E172*(1-MIN((tp_g-0.01)/tp_roe,0.8))/(1+tp_r)^1+PL!F172*(1-MIN((tp_g-0.01)/tp_roe,0.8))/(1+tp_r)^2+PL!G172*(1-MIN((tp_g-0.01)/tp_roe,0.8))/(1+tp_r)^3+PL!H172*(1-MIN((tp_g-0.01)/tp_roe,0.8))/(1+tp_r)^4+PL!I172*(1-MIN((tp_g-0.01)/tp_roe,0.8))/(1+tp_r)^5+PL!J172*(1-MIN((tp_g-0.01)/tp_roe,0.8))/(1+tp_r)^6+PL!J172*(1-MIN((tp_g-0.01)/tp_roe,0.8))*(1+(tp_g-0.01))/(tp_r-(tp_g-0.01))/(1+tp_r)^6))*(1+tp_r) -> 80.912118 | H30: =Val!$B$33*(tp_wA*(2/12*PL!E94+10/12*PL!F94)+tp_wB*(2/12*PL!E133+10/12*PL!F133)+tp_wC*(2/12*PL!E172+10/12*PL!F172))*rm_factor -> 70.338451 | I30: =tp_w_dcf*G30+(1-tp_w_dcf)*H30 -> 75.625284 | J30: =I30/I$4-1 -> -0.010188619
A31: DCF 權重 0.3 | B31: Comparable 0.7 | C31: tp_w_dcf | D31: =PL!E94 -> 7.6015049 | E31: =PL!F94 -> 8.8015043 | F31: =E31/E$4-1 -> 0 | G31: =(tp_wA*MAX(0,PL!E94*(1-MIN(tp_g/tp_roe,0.8))/(1+tp_r)^1+PL!F94*(1-MIN(tp_g/tp_roe,0.8))/(1+tp_r)^2+PL!G94*(1-MIN(tp_g/tp_roe,0.8))/(1+tp_r)^3+PL!H94*(1-MIN(tp_g/tp_roe,0.8))/(1+tp_r)^4+PL!I94*(1-MIN(tp_g/tp_roe,0.8))/(1+tp_r)^5+PL!J94*(1-MIN(tp_g/tp_roe,0.8))/(1+tp_r)^6+PL!J94*(1-MIN(tp_g/tp_roe,0.8))*(1+tp_g)/(tp_r-tp_g)/(1+tp_r)^6)+tp_wB*MAX(0,PL!E133*(1-MIN(tp_g/tp_roe,0.8))/(1+tp_r)^1+PL!F133*(1-MIN(tp_g/tp_roe,0.8))/(1+tp_r)^2+PL!G133*(1-MIN(tp_g/tp_roe,0.8))/(1+tp_r)^3+PL!H133*(1-MIN(tp_g/tp_roe,0.8))/(1+tp_r)^4+PL!I133*(1-MIN(tp_g/tp_roe,0.8))/(1+tp_r)^5+PL!J133*(1-MIN(tp_g/tp_roe,0.8))/(1+tp_r)^6+PL!J133*(1-MIN(tp_g/tp_roe,0.8))*(1+tp_g)/(tp_r-tp_g)/(1+tp_r)^6)+tp_wC*MAX(0,PL!E172*(1-MIN(tp_g/tp_roe,0.8))/(1+tp_r)^1+PL!F172*(1-MIN(tp_g/tp_roe,0.8))/(1+tp_r)^2+PL!G172*(1-MIN(tp_g/tp_roe,0.8))/(1+tp_r)^3+PL!H172*(1-MIN(tp_g/tp_roe,0.8))/(1+tp_r)^4+PL!I172*(1-MIN(tp_g/tp_roe,0.8))/(1+tp_r)^5+PL!J172*(1-MIN(tp_g/tp_roe,0.8))/(1+tp_r)^6+PL!J172*(1-MIN(tp_g/tp_roe,0.8))*(1+tp_g)/(tp_r-tp_g)/(1+tp_r)^6))*(1+tp_r) -> 82.469015 | H31: =Val!$B$33*(tp_wA*(2/12*PL!E94+10/12*PL!F94)+tp_wB*(2/12*PL!E133+10/12*PL!F133)+tp_wC*(2/12*PL!E172+10/12*PL!F172))*rm_factor -> 70.338451 | I31: =0.3*G31+(1-0.3)*H31 -> 73.97762 | J31: =I31/I$4-1 -> -0.031753853
A32: DCF 權重 0.7 | B32: Comparable 0.3 | C32: tp_w_dcf | D32: =PL!E94 -> 7.6015049 | E32: =PL!F94 -> 8.8015043 | F32: =E32/E$4-1 -> 0 | G32: =(tp_wA*MAX(0,PL!E94*(1-MIN(tp_g/tp_roe,0.8))/(1+tp_r)^1+PL!F94*(1-MIN(tp_g/tp_roe,0.8))/(1+tp_r)^2+PL!G94*(1-MIN(tp_g/tp_roe,0.8))/(1+tp_r)^3+PL!H94*(1-MIN(tp_g/tp_roe,0.8))/(1+tp_r)^4+PL!I94*(1-MIN(tp_g/tp_roe,0.8))/(1+tp_r)^5+PL!J94*(1-MIN(tp_g/tp_roe,0.8))/(1+tp_r)^6+PL!J94*(1-MIN(tp_g/tp_roe,0.8))*(1+tp_g)/(tp_r-tp_g)/(1+tp_r)^6)+tp_wB*MAX(0,PL!E133*(1-MIN(tp_g/tp_roe,0.8))/(1+tp_r)^1+PL!F133*(1-MIN(tp_g/tp_roe,0.8))/(1+tp_r)^2+PL!G133*(1-MIN(tp_g/tp_roe,0.8))/(1+tp_r)^3+PL!H133*(1-MIN(tp_g/tp_roe,0.8))/(1+tp_r)^4+PL!I133*(1-MIN(tp_g/tp_roe,0.8))/(1+tp_r)^5+PL!J133*(1-MIN(tp_g/tp_roe,0.8))/(1+tp_r)^6+PL!J133*(1-MIN(tp_g/tp_roe,0.8))*(1+tp_g)/(tp_r-tp_g)/(1+tp_r)^6)+tp_wC*MAX(0,PL!E172*(1-MIN(tp_g/tp_roe,0.8))/(1+tp_r)^1+PL!F172*(1-MIN(tp_g/tp_roe,0.8))/(1+tp_r)^2+PL!G172*(1-MIN(tp_g/tp_roe,0.8))/(1+tp_r)^3+PL!H172*(1-MIN(tp_g/tp_roe,0.8))/(1+tp_r)^4+PL!I172*(1-MIN(tp_g/tp_roe,0.8))/(1+tp_r)^5+PL!J172*(1-MIN(tp_g/tp_roe,0.8))/(1+tp_r)^6+PL!J172*(1-MIN(tp_g/tp_roe,0.8))*(1+tp_g)/(tp_r-tp_g)/(1+tp_r)^6))*(1+tp_r) -> 82.469015 | H32: =Val!$B$33*(tp_wA*(2/12*PL!E94+10/12*PL!F94)+tp_wB*(2/12*PL!E133+10/12*PL!F133)+tp_wC*(2/12*PL!E172+10/12*PL!F172))*rm_factor -> 70.338451 | I32: =0.7*G32+(1-0.7)*H32 -> 78.829846 | J32: =I32/I$4-1 -> 0.031753853
A34: 讀法：稼動率與售價是加權目標價最敏感的兩個輸入（固定成本高，稼動率每 3 個百分點、售價每 3% 都直接落到毛利）；AI 相關與 Intel 12 奈米的影響小於售價 1%。
A36: 敏感度「逐案推導區塊」：以下每個案例三個情境各一個完整推導區塊（不是案例列）
A38: 案例區塊：匯率：低（情境 A）
A39: 項目 | B39: 單位 | C39: FY2025A | D39: FY2026（錨點） | E39: FY2027 | F39: FY2028 | G39: FY2029 | H39: FY2030（收斂） | I39: FY2031（收斂） | J39: FY2032（收斂） | K39: 說明
A40: A. 成熟製程晶圓：產能 × 稼動率 × 平均售價（D 欄＝FY2026 校準年）
A41: 產能（12 吋約當） | B41: 千片 | D41: =cap_26 -> 5230.4685 | E41: =D41*(1+capg27)*cap_adj -> 5439.6873 | F41: =E41*(1+capg28) -> 5820.4654 | G41: =F41*(1+capg29) -> 6227.8979
A42: 平均稼動率 | B42: % | D42: =a26_ship/cap_26 -> 0.87057878 | E42: =MIN(0.98,ut27_A+ut_adj) -> 0.95 | F42: =MIN(0.98,ut28_A+ut_adj) -> 0.94 | G42: =MIN(0.98,ut29_A+ut_adj) -> 0.93
A43: 晶圓出貨（12 吋約當） | B43: 千片 | D43: =D41*D42 -> 4553.5349 | E43: =E41*E42 -> 5167.7029 | F43: =F41*F42 -> 5471.2374 | G43: =G41*G42 -> 5791.9451
A44: 平均售價（成熟製程晶圓） | B44: US$/片 | D44: =asp_26 -> 1878.1749 | E44: =D44*(1+asp27_A)*(1+asp_adj) -> 2065.9924 | F44: =E44*(1+asp28_A) -> 2127.9721 | G44: =F44*(1+asp29_A) -> 2170.5316
A45: 平均售價年增（美元） | B45: % | E45: =E44/D44-1 -> 0.1 | F45: =F44/E44-1 -> 0.03 | G45: =G44/F44-1 -> 0.02
A46: 匯率 | B46: NT$/US$ | D46: =fx_26 -> 31.6 | E46: =fx_lo -> 30.5 | F46: =fx_lo -> 30.5 | G46: =fx_lo -> 30.5
A47: 成熟製程晶圓營收（不含 AI 相關、Intel 12 奈米） | B47: NT$B | D47: =D43*D44*D46/1000000 -> 270.25378 | E47: =E43*E44*E46/1000000 -> 325.63126 | F47: =F43*F44*F46/1000000 -> 355.10054 | G47: =G43*G44*G46/1000000 -> 383.43379
A48: B. 新業務：AI 相關（先進封裝矽中介層、矽光子）與 Intel 12 奈米（美元營收）
A49: AI 相關營收（美元；FY2028 起 × 同字母顆數係數） | B49: US$B | D49: =ai_26 -> 0.3 | E49: =D49*(1+aig27_A)*ai_adj -> 0.48 | F49: =E49*(1+aig_L)*um28_A -> 0.696 | G49: =F49/um28_A*(1+aig_L)*um29_A -> 1.0092
A50: AI 相關營收 | B50: NT$B | D50: =D49*D46 -> 9.48 | E50: =E49*E46 -> 14.64 | F50: =F49*F46 -> 21.228 | G50: =G49*G46 -> 30.7806
A51: Intel 12 奈米營收（美元） | B51: US$B | D51: =0 -> 0 | E51: =int_27 -> 0 | F51: =int28_A -> 0.25 | G51: =int29_A -> 0.5
A52: Intel 12 奈米營收 | B52: NT$B | D52: =D51*D46 -> 0 | E52: =E51*E46 -> 0 | F52: =F51*F46 -> 7.625 | G52: =G51*G46 -> 15.25
A53: 營收 | B53: NT$B | C53: =a25_rev -> 237.553 | D53: =D47+D50+D52 -> 279.73378 | E53: =E47+E50+E52 -> 340.27126 | F53: =F47+F50+F52 -> 383.95354 | G53: =G47+G50+G52 -> 429.46439 | H53: =G53*(1+H55) -> 471.99057 | I53: =H53*(1+I55) -> 509.51888 | J53: =I53*(1+J55) -> 540.09002 | K53: FY2030 起為收斂法：營收年增由 FY2029 線性收斂到 fade_g、淨利率收斂到 fade_m（FY2032 達到），非驅動因子推導
A54: AI 相關 ÷ 營收 | B54: % | D54: =D50/D53 -> 0.033889364 | E54: =E50/E53 -> 0.043024498 | F54: =F50/F53 -> 0.055287939 | G54: =G50/G53 -> 0.071672066
A55: 營收年增 | B55: % | D55: =D53/C53-1 -> 0.17756366 | E55: =E53/D53-1 -> 0.21641104 | F55: =F53/E53-1 -> 0.12837489 | G55: =G53/F53-1 -> 0.11853217 | H55: =$G55+(fade_gA-$G55)*1/3 -> 0.099021445 | I55: =$G55+(fade_gA-$G55)*2/3 -> 0.079510722 | J55: =$G55+(fade_gA-$G55)*3/3 -> 0.06
A56: C. 成本與損益
A57: 銷貨成本內折舊 | B57: NT$B | D57: =da_tot26*da_sh -> 56.172 | E57: =D57*(1+dag_27+dag_adj) -> 62.91264 | F57: =E57*(1+dag_28+dag_adj) -> 69.203904 | G57: =F57*(1+dag_29+dag_adj) -> 74.740216
A58: 每片現金成本（FY2026 殘差，之後年增 cc_g） | B58: NT$K/片 | D58: =(D53-a26_gp-D57-(1-m_new)*(D50+D52))/D43*1000 -> 27.946573 | E58: =D58*(1+cc_g) -> 28.505504 | F58: =E58*(1+cc_g) -> 29.075614 | G58: =F58*(1+cc_g) -> 29.657127 | K58: Derived：讓 FY2026 毛利等於錨點；含原物料、人力、電力等變動與固定現金成本
A59: 現金成本合計（每片 × 出貨） | B59: NT$B | D59: =D58*D43/1000 -> 127.25569 | E59: =E58*E43/1000 -> 147.30798 | F59: =F58*F43/1000 -> 159.07959 | G59: =G58*G43/1000 -> 171.77245
A60: 新業務毛利（邊際貢獻率 × AI 相關與 Intel 營收） | B60: NT$B | D60: =m_new*(D50+D52) -> 4.266 | E60: =m_new*(E50+E52) -> 6.588 | F60: =m_new*(F50+F52) -> 12.98385 | G60: =m_new*(G50+G52) -> 20.71377
A61: 毛利 | B61: NT$B | C61: =a25_gp -> 68.906 | D61: =D47-D57-D59+D60 -> 91.092085 | E61: =E47-E57-E59+E60 -> 121.99864 | F61: =F47-F57-F59+F60 -> 139.8009 | G61: =G47-G57-G59+G60 -> 157.63489
A62: 毛利率 | B62: % | C62: =C61/C53 -> 0.2900658 | D62: =D61/D53 -> 0.32563849 | E62: =E61/E53 -> 0.35853349 | F62: =F61/F53 -> 0.36410889 | G62: =G61/G53 -> 0.36704998
A63: 營業費用 | B63: NT$B | C63: =a25_opx -> 25.056 | D63: =a26_opx -> 27.23586 | E63: =D63*(1+MAX(g_opx_min,phi*E55)) -> 30.18293 | F63: =E63*(1+MAX(g_opx_min,phi*F55)) -> 32.120296 | G63: =F63*(1+MAX(g_opx_min,phi*G55)) -> 34.02394
A64: 營業利益 | B64: NT$B | C64: =C61-C63 -> 43.85 | D64: =D61-D63 -> 63.856225 | E64: =E61-E63 -> 91.81571 | F64: =F61-F63 -> 107.6806 | G64: =G61-G63 -> 123.61095
A65: 營業利益率 | B65: % | C65: =C64/C53 -> 0.18459039 | D65: =D64/D53 -> 0.22827499 | E65: =E64/E53 -> 0.26983093 | F65: =F64/F53 -> 0.28045217 | G65: =G64/G53 -> 0.28782585
A66: 營業外淨額 | B66: NT$B | C66: =a25_nonop -> 5.805 | D66: =a26_nonop -> 38.372 | E66: =nonop_f -> 4 | F66: =nonop_f -> 4 | G66: =nonop_f -> 4
A67: 稅前利益 | B67: NT$B | C67: =C64+C66 -> 49.655 | D67: =D64+D66 -> 102.22823 | E67: =E64+E66 -> 95.81571 | F67: =F64+F66 -> 111.6806 | G67: =G64+G66 -> 127.61095
A68: 所得稅 | B68: NT$B | C68: =a25_tax -> 7.939 | D68: =a26_tax -> 10.493828 | E68: =E67*tax -> 14.372356 | F68: =F67*tax -> 16.752091 | G68: =G67*tax -> 19.141643
A69: 非控制權益 | B69: NT$B | C69: =a25_mi -> 0 | D69: =a26_mi -> -0.135 | E69: =0 -> 0 | F69: =0 -> 0 | G69: =0 -> 0 | K69: FY2027 起假設為 0（歷史上接近 0）
A70: 歸屬母公司淨利 | B70: NT$B | C70: =C67-C68-C69 -> 41.716 | D70: =D67-D68-D69 -> 91.869397 | E70: =E67-E68-E69 -> 81.443353 | F70: =F67-F68-F69 -> 94.928513 | G70: =G67-G68-G69 -> 108.46931 | H70: =H53*H74 -> 119.2101 | I70: =I53*I74 -> 128.68858 | J70: =J53*J74 -> 136.40989
A71: 加權股數 | B71: 十億股 | C71: =a25_sh -> 12.48982 | D71: =a26_sh -> 12.475434 | E71: =q_sh*(1+sh_g) -> 12.45 | F71: =E71*(1+sh_g) -> 12.45 | G71: =F71*(1+sh_g) -> 12.45 | H71: =G71*(1+sh_g) -> 12.45 | I71: =H71*(1+sh_g) -> 12.45 | J71: =I71*(1+sh_g) -> 12.45
A72: EPS（基本） | B72: NT$ | C72: =C70/C71 -> 3.34 | D72: =D70/D71 -> 7.3640242 | E72: =E70/E71 -> 6.5416348 | F72: =F70/F71 -> 7.6247802 | G72: =G70/G71 -> 8.7123944 | H72: =H70/H71 -> 9.5751083 | I72: =I70/I71 -> 10.336432 | J72: =J70/J71 -> 10.956618
A73: EPS 年增 | B73: % | D73: =D72/C72-1 -> 1.2047977 | E73: =E72/D72-1 -> -0.11167663 | F73: =F72/E72-1 -> 0.16557717 | G73: =G72/F72-1 -> 0.14264205 | H73: =H72/G72-1 -> 0.099021445 | I73: =I72/H72-1 -> 0.079510722 | J73: =J72/I72-1 -> 0.06
A74: 淨利率（歸屬母公司淨利 ÷ 營收） | B74: % | C74: =C70/C53 -> 0.17560713 | D74: =D70/D53 -> 0.32841724 | E74: =E70/E53 -> 0.23934832 | F74: =F70/F53 -> 0.24723958 | G74: =G70/G53 -> 0.25256881 | H74: =$G74+($G$74*1-$G74)*1/3 -> 0.25256881 | I74: =$G74+($G$74*1-$G74)*2/3 -> 0.25256881 | J74: =$G74+($G$74*1-$G74)*3/3 -> 0.25256881
A77: 案例區塊：匯率：低（情境 B）
A78: 項目 | B78: 單位 | C78: FY2025A | D78: FY2026（錨點） | E78: FY2027 | F78: FY2028 | G78: FY2029 | H78: FY2030（收斂） | I78: FY2031（收斂） | J78: FY2032（收斂） | K78: 說明
A79: A. 成熟製程晶圓：產能 × 稼動率 × 平均售價（D 欄＝FY2026 校準年）
A80: 產能（12 吋約當） | B80: 千片 | D80: =cap_26 -> 5230.4685 | E80: =D80*(1+capg27)*cap_adj -> 5439.6873 | F80: =E80*(1+capg28) -> 5820.4654 | G80: =F80*(1+capg29) -> 6227.8979
A81: 平均稼動率 | B81: % | D81: =a26_ship/cap_26 -> 0.87057878 | E81: =MIN(0.98,ut27_B+ut_adj) -> 0.9 | F81: =MIN(0.98,ut28_B+ut_adj) -> 0.87 | G81: =MIN(0.98,ut29_B+ut_adj) -> 0.88
A82: 晶圓出貨（12 吋約當） | B82: 千片 | D82: =D80*D81 -> 4553.5349 | E82: =E80*E81 -> 4895.7185 | F82: =F80*F81 -> 5063.8049 | G82: =G80*G81 -> 5480.5502
A83: 平均售價（成熟製程晶圓） | B83: US$/片 | D83: =asp_26 -> 1878.1749 | E83: =D83*(1+asp27_B)*(1+asp_adj) -> 1972.0836 | F83: =E83*(1+asp28_B) -> 1972.0836 | G83: =F83*(1+asp29_B) -> 1972.0836
A84: 平均售價年增（美元） | B84: % | E84: =E83/D83-1 -> 0.05 | F84: =F83/E83-1 -> 0 | G84: =G83/F83-1 -> 0
A85: 匯率 | B85: NT$/US$ | D85: =fx_26 -> 31.6 | E85: =fx_lo -> 30.5 | F85: =fx_lo -> 30.5 | G85: =fx_lo -> 30.5
A86: 成熟製程晶圓營收（不含 AI 相關、Intel 12 奈米） | B86: NT$B | D86: =D82*D83*D85/1000000 -> 270.25378 | E86: =E82*E83*E85/1000000 -> 294.47037 | F86: =F82*F83*F85/1000000 -> 304.58052 | G86: =G82*G83*G85/1000000 -> 329.64715
A87: B. 新業務：AI 相關（先進封裝矽中介層、矽光子）與 Intel 12 奈米（美元營收）
A88: AI 相關營收（美元；FY2028 起 × 同字母顆數係數） | B88: US$B | D88: =ai_26 -> 0.3 | E88: =D88*(1+aig27_B)*ai_adj -> 0.42 | F88: =E88*(1+aig_L)*um28_B -> 0.4872 | G88: =F88/um28_B*(1+aig_L)*um29_B -> 0.7505925
A89: AI 相關營收 | B89: NT$B | D89: =D88*D85 -> 9.48 | E89: =E88*E85 -> 12.81 | F89: =F88*F85 -> 14.8596 | G89: =G88*G85 -> 22.893071
A90: Intel 12 奈米營收（美元） | B90: US$B | D90: =0 -> 0 | E90: =int_27 -> 0 | F90: =int28_B -> 0.12 | G90: =int29_B -> 0.3
A91: Intel 12 奈米營收 | B91: NT$B | D91: =D90*D85 -> 0 | E91: =E90*E85 -> 0 | F91: =F90*F85 -> 3.66 | G91: =G90*G85 -> 9.15
A92: 營收 | B92: NT$B | C92: =a25_rev -> 237.553 | D92: =D86+D89+D91 -> 279.73378 | E92: =E86+E89+E91 -> 307.28037 | F92: =F86+F89+F91 -> 323.10012 | G92: =G86+G89+G91 -> 361.69022 | H92: =G92*(1+H94) -> 395.31221 | I92: =H92*(1+I94) -> 421.59217 | J92: =I92*(1+J94) -> 438.45585 | K92: FY2030 起為收斂法：營收年增由 FY2029 線性收斂到 fade_g、淨利率收斂到 fade_m（FY2032 達到），非驅動因子推導
A93: AI 相關 ÷ 營收 | B93: % | D93: =D89/D92 -> 0.033889364 | E93: =E89/E92 -> 0.041688312 | F93: =F89/F92 -> 0.045990698 | G93: =G89/G92 -> 0.063294693
A94: 營收年增 | B94: % | D94: =D92/C92-1 -> 0.17756366 | E94: =E92/D92-1 -> 0.098474311 | F94: =F92/E92-1 -> 0.051483111 | G94: =G92/F92-1 -> 0.11943697 | H94: =$G94+(fade_gB-$G94)*1/3 -> 0.092957977 | I94: =$G94+(fade_gB-$G94)*2/3 -> 0.066478989 | J94: =$G94+(fade_gB-$G94)*3/3 -> 0.04
A95: C. 成本與損益
A96: 銷貨成本內折舊 | B96: NT$B | D96: =da_tot26*da_sh -> 56.172 | E96: =D96*(1+dag_27+dag_adj) -> 62.91264 | F96: =E96*(1+dag_28+dag_adj) -> 69.203904 | G96: =F96*(1+dag_29+dag_adj) -> 74.740216
A97: 每片現金成本（FY2026 殘差，之後年增 cc_g） | B97: NT$K/片 | D97: =(D92-a26_gp-D96-(1-m_new)*(D89+D91))/D82*1000 -> 27.946573 | E97: =D97*(1+cc_g) -> 28.505504 | F97: =E97*(1+cc_g) -> 29.075614 | G97: =F97*(1+cc_g) -> 29.657127 | K97: Derived：讓 FY2026 毛利等於錨點；含原物料、人力、電力等變動與固定現金成本
A98: 現金成本合計（每片 × 出貨） | B98: NT$B | D98: =D97*D82/1000 -> 127.25569 | E98: =E97*E82/1000 -> 139.55493 | F98: =F97*F82/1000 -> 147.23324 | G98: =G97*G82/1000 -> 162.53737
A99: 新業務毛利（邊際貢獻率 × AI 相關與 Intel 營收） | B99: NT$B | D99: =m_new*(D89+D91) -> 4.266 | E99: =m_new*(E89+E91) -> 5.7645 | F99: =m_new*(F89+F91) -> 8.33382 | G99: =m_new*(G89+G91) -> 14.419382
A100: 毛利 | B100: NT$B | C100: =a25_gp -> 68.906 | D100: =D86-D96-D98+D99 -> 91.092085 | E100: =E86-E96-E98+E99 -> 97.767306 | F100: =F86-F96-F98+F99 -> 96.477199 | G100: =G86-G96-G98+G99 -> 106.78894
A101: 毛利率 | B101: % | C101: =C100/C92 -> 0.2900658 | D101: =D100/D92 -> 0.32563849 | E101: =E100/E92 -> 0.31816971 | F101: =F100/F92 -> 0.29859846 | G101: =G100/G92 -> 0.29524974
A102: 營業費用 | B102: NT$B | C102: =a25_opx -> 25.056 | D102: =a26_opx -> 27.23586 | E102: =D102*(1+MAX(g_opx_min,phi*E94)) -> 28.576876 | F102: =E102*(1+MAX(g_opx_min,phi*F94)) -> 29.434183 | G102: =F102*(1+MAX(g_opx_min,phi*G94)) -> 31.191947
A103: 營業利益 | B103: NT$B | C103: =C100-C102 -> 43.85 | D103: =D100-D102 -> 63.856225 | E103: =E100-E102 -> 69.190429 | F103: =F100-F102 -> 67.043017 | G103: =G100-G102 -> 75.596995
A104: 營業利益率 | B104: % | C104: =C103/C92 -> 0.18459039 | D104: =D103/D92 -> 0.22827499 | E104: =E103/E92 -> 0.22517035 | F104: =F103/F92 -> 0.2074992 | G104: =G103/G92 -> 0.20901034
A105: 營業外淨額 | B105: NT$B | C105: =a25_nonop -> 5.805 | D105: =a26_nonop -> 38.372 | E105: =nonop_f -> 4 | F105: =nonop_f -> 4 | G105: =nonop_f -> 4
...

Sheet Sources
A1: 來源（公司財報與法說內容部分為媒體轉述；券商、資料商、媒體皆為 Interested-party）
A2: 公司：6-K 3Q26 財報（2026-10-28；營收、毛利率、營業利益、9M26 累計、稼動率 92%、出貨逾 120 萬片、4Q26 指引、資本預算約 1,028 億元） | B2: https://www.sec.gov/Archives/edgar/data/0001033767/000119312526434992/umc-ex99.htm
A3: 公司：6-K 2Q26 財報（2026-07-29；1H26 累計、稼動率 85%、22 奈米 17.5%、2026 資本支出 20 億美元、P4／台南擴產預算 1,487 億元） | B3: https://www.sec.gov/Archives/edgar/data/0001033767/000119312526322027/umc-ex99.htm
A4: 公司：6-K 1Q26 財報（稼動率 79%、22／28 奈米 34%） | B4: https://www.sec.gov/Archives/edgar/data/0001033767/000119312526188788/umc-ex99.htm
A5: 公司：6-K 4Q25 財報（2026-01-28；4Q25 營收 618.1 億、稼動率 78%、22／28 奈米 36%、FY2025 EPS 3.34） | B5: https://www.sec.gov/Archives/edgar/data/1033767/000119312526025557/umc-ex99_1.htm
A6: 媒體：優分析 2026-10-28（3Q26 法說轉述：2027 年平均售價年增約一成、折舊與原物料成本上升） | B6: https://uanalyze.com.tw/articles/9109557881
A7: 媒體：優分析 2026-07-29（2Q26 投資與股利收益約 302 億） | B7: https://uanalyze.com.tw/articles/6783952429
A8: 資料商：Finsee 3Q26 財報摘要（9M26 折舊 468.1 億、Intel 12 奈米先前時程、AI 相關 3 億美元目標） | B8: https://finsee.ai/earnings/umc/2026/q3/en/
A9: 券商轉述：科技新報 2026-10-06（摩根士丹利：目標價 188、AI 相關 2026 年 3 億、2029 年 10 億美元；8 吋 2027 年漲價） | B9: https://finance.technews.tw/2026/10/06/morgan-stanley-increases-its-support-for-the-two-leading-semiconductor-foundries/
A10: 媒體：旺得富 2026-10-17（法人目標價 130–185、FY2026 EPS 7.46–7.68、FY2027 EPS 9.2、海外可轉債 18 億美元） | B10: https://wantrich.chinatimes.com/news/20261017900003-420101
A11: 資料商：stockanalysis（股價、前瞻 P/E、共識目標價、FY2021–25 損益、ROE、年度 P/E） | B11: https://stockanalysis.com/quote/tpe/2303/；https://stockanalysis.com/quote/tpe/2303/forecast/；https://stockanalysis.com/quote/tpe/2303/financials/；https://stockanalysis.com/quote/tpe/2303/financials/ratios/；https://stockanalysis.com/quote/tpe/2303/history/
A12: 資料商：stockanalysis 同業前瞻 P/E（2330、GFS、0981、TSEM、5347） | B12: https://stockanalysis.com/quote/tpe/2330/；https://stockanalysis.com/stocks/gfs/；https://stockanalysis.com/quote/hkg/0981/；https://stockanalysis.com/stocks/tsem/；https://stockanalysis.com/quote/tpex/5347/
A13: 資料商：companiesmarketcap 年底 P/E | B13: https://companiesmarketcap.com/united-microelectronics/pe-ratio/
... A16: SemiAnalysis | B16: 未使用
