Workbook

Sheet README
A1: TOWA（6315.T）收支與估值模型 v0.1.1（AI 半導體 Project 步驟 5：設備與材料） 2026-10-25
A2: 模型命題：TOWA 握有封膠設備約 2/3 市占，但營收只有約兩成來自 AI（HBM 與 CoWoS 封膠），FY2025 營益率僅 12.7%；問題是 HBM 堆疊與 2.5D 封裝的封膠增量，能否在 FY2027 以後延續並把營益率拉回 16% 以上，撐住約 21 倍的指引本益比？
A3: 註：21 倍＝現價 ¥1,968（2026-10-23）÷ 公司 FY2026 指引 EPS ¥93.30；÷ FY2025 EPS ¥61.22 為 32.1 倍（Val 第 5 節）。
A5: 驅動因子 → 推導量（因果方向：左邊決定右邊）
A6: PL 區塊｜HBM 出貨位元（skhynix 成品，同字母情境）÷（晶粒容量 × 層數）→ HBM 堆疊數 → 下一年增量＋汰換 → 新機需求 × kH（以 FY2025 AI 錨點校準）→ HBM 封膠營收
A7: PL 區塊｜CoWoS 片數（台積電成品；B、C × 同字母顆數係數）→ 下一年增量＋汰換 → 新機需求 × kL → 2.5D 封膠營收
A8: PL 區塊｜SEMI 組裝與封裝設備 ×（情境 s 非 AI 設備 ÷ 情境 A 非 AI 設備）（markets/equipment）→ 非 AI 封膠設備與模具；設備總額 → 切割與雷射；新事業、醫療以自身歷史年增
A9: PL（D 節）｜FY2026 錨點＝公司全年指引（營收 640、營業利益 102.4、淨利 70.0 億）×（1＋g_anc）；各組成同比例縮放，FY2027 起 AI 兩項回到驅動推導、非 AI 以錨定水準（情境 A 的 sc）為基期
A10: PL（E 節）｜營業利益＝FY2026 錨點＋（Hist 迴歸增量營益率＋情境調整）×（營收 − FY2026 營收）；淨利＝營業利益 × 0.684（公司指引比例）
A11: Val｜第 0 節目標價（DCF 與 Comparable 各半）；第 1–6 節十年 P/E、循環位置（設備股共用規則：見頂年度 A 2029、B 2028、C 2027 → FY2027：A 中段、B 中段、C 見頂）、規則值與目前倍數
A13: 會計年度：4 月到隔年 3 月（FY2025＝2025-04～2026-03，公司「2026年3月期」）。日曆年轉會計年度：FY(t)＝3/4 × CY(t)＋1/4 × CY(t+1)。金額為日圓，未建匯率。
A14: 情境：A＝順利、B＝平平、C＝不如預期，各讀同字母的上游情境（HBM 位元、顆數係數、設備市場）；公司特有變數（AI 封膠市占流失、增量營益率調整）A 最有利、C 最不利。FY2030 起為收斂法，非驅動因子推導。
... A18: v0.1.1（2026-10-25）：補上檔空間級距、投資建議、重點觀察（數值不變）。Val 頁最後新增「上檔空間級距」「投資建議」兩列（依「上檔空間：加權目標價」固定規則）；README 頁最後新增投資建議與重點觀察三點。
A19: ="投資建議："&Val!B125&"（依上檔空間固定規則）" -> 投資建議：放空（依上檔空間固定規則）
A20: ="重點觀察 1：目標價 ¥"&TEXT(Val!$B$39,"#,##0")&"（DCF "&TEXT(Val!$B$24,"#,##0")&"、Comparable（相對倍數調整後）"&TEXT(tp_comp_adj,"#,##0")&"；DCF 權重 "&TEXT(tp_w_dcf,"0%")&"），比現價 "&TEXT(px,"#,##0")&"（2026-10-23）"&IF(Val!$B$42>=0,"高 "&TEXT(Val!$B$42,"0.0%"),"低 "&TEXT(-Val!$B$42,"0.0%"))&"，級距 "&Val!$B$124&"、投資建議 "&Val!$B$125&"。相對倍數調整係數 "&TEXT(rm_factor,"0.00")&"（本公司 10 年前瞻倍數中位數 ÷ 同業的中位數，夾在 0.5–2.0；Val 第 0.5 節），調整前加權上檔空間 "&TEXT((tp_w_dcf*Val!$B$24+(1-tp_w_dcf)*Val!$B$35)/px-1,"+0.0%;−0.0%")&"；Comparable 單獨（市場主流同業法、未調整）為 "&TEXT(Val!$B$43,"+0.0%;−0.0%")&"。"&"以下為 2026-10-29 相對倍數調整前撰寫的說明，其中數字為調整前：DCF 只有現價的 0.52 倍：ROE 近三年平均 10.9% 只略高於折現率 10%，再投資率 36.7%，股東現金流只有 EPS 的六成多。" -> 重點觀察 1：目標價 ¥1,382（DCF 1,015、Comparable（相對倍數調整後）1,748；DCF 權重 50%），比現價 1,968（2026-10-23）低 29.8%，級距 −25%～−50%、投資建議 放空。相對倍數調整係數 0.72（本公司 10 年前瞻倍數中位數 ÷ 同業的中位數，夾在 0.5–2.0；Val 第 0.5 節），調整前加權上檔空間 −12.3%；Comparable 單獨（市場主流同業法、未調整）為 +23.8%。以下為 2026-10-29 相對倍數調整前撰寫的說明，其中數字為調整前：DCF 只有現價的 0.52 倍：ROE 近三年平均 10.9% 只略高於折現率 10%，再投資率 36.7%，股東現金流只有 EPS 的六成多。
A21: 重點觀察 2：本模型 12 個月後前瞻 EPS 94.4 比共識前瞻 EPS 116.0 低 18.6%；共識目標價 3,300 隱含 28.5 倍，同業中位數 25.8 倍（倍數因素 +10.2%）。情境 B、C 的 FY2027 EPS 比 A 低 12.5%、22.6%（AI 封膠市占流失 3pt／8pt 與上游下修）。
A22: 重點觀察 3：FY2027 EPS 對堆疊層數（低值 → +8.9%）、淨利 ÷ 營業利益（0.65／0.72 → −4.9%／+5.3%）與 FY2026 錨點（−5%／+8% → −3.5%／+5.7%）最敏感。下一個檢驗事件是第二季財報（預計 2026-11 上旬，日期未確認），FY2026 錨點將改為上半年實績加下半年指引。
A24: 2026-10-29：加權目標價中的 Comparable 改用相對倍數調整後的值（Val 第 0.5 節：同業前瞻倍數中位數 × 本公司 10 年相對同業的倍數比，Bloomberg 前瞻倍數；Andy 2026-10-27「照建議做」、10-29 資料取回）。「Comparable 目標價（市場主流同業法）」維持不調整。重點觀察 1 的第一句已改為公式；重點觀察 2、3 與其他說明中的目標價與上檔空間數字為調整前撰寫，以 Val 頁為準。
A26: v0.2.1（2026-10-30）：依個股模型原則第 8 節調整 In 頁呈現（數值不變）。In 頁 D／F 欄名改「敏感度低」「敏感度高」（只用於 Sens 頁、不進目標價）；In 頁最後新增「情境驅動對照」一節，把上方各情境專屬輸入三情境並排（只引用上方各列，純展示）；HTML 驅動因子一節分「情境驅動」與「單一參數」兩張表。

Sheet In
A1: In — 輸入（藍字；基準欄 E，低 D、高 F）。金額：十億日圓（¥B）；HBM 位元：EB；CoWoS：千片；設備市場：十億美元。每個輸入附標記與來源；找不到者寫「未找到」，公司未揭露者寫「公司不揭露」。【v0.2.1】基準欄 E 進主模型；D／F＝敏感度低／高，只用於 Sens 頁（一次動一個參數）、不進目標價；情境 A／B／C 的驅動見本頁最後一節「情境驅動對照」。
A2: 標記：Verified（公司文件、交易所資料）／Interested-party（寫明是誰、立場）／Analogy（寫明對照與差異）／Assumed（一律給低／高區間）／Derived（寫明換算）。SemiAnalysis 未使用。公司原文（JPX 決算短信 iXBRL、towajapan.co.jp 說明資料 PDF）以網頁擷取工具讀取；圖表數字擷取錯位處未採用，待人工複核
A3: 鍵 | B3: 項目 | C3: 單位 | D3: 敏感度低 | E3: 基準 | F3: 敏感度高 | G3: 標記 | H3: 來源1 | I3: 來源2／說明
A4: A. FY2025 實績（2025-04～2026-03）與事業別營收（校準錨）
A5: a25_rev | B5: 營收 FY2025 | C5: ¥B | E5: 54.365 | G5: Verified | H5: 公司 2026年3月期 決算短信（2026-04-22 登錄，JPX iXBRL 081220260422508001）：54,365 百萬日圓（+1.7%） | I5: 松井證券 決算情報（finance.matsui.co.jp/stock/6315/settlement）：54,365
A6: a25_gp | B6: 毛利 FY2025 | C6: ¥B | E6: 18.372 | G6: Verified | H6: kabutore 財務分析（轉載公司損益表）：売上総利益 18,371,561 千日圓（毛利率 33.8%） | I6: edinetdb（2026-10-24 讀取）：毛利率 33.8%。決算短信摘要頁未列毛利
A7: a25_oi | B7: 營業利益 FY2025 | C7: ¥B | E7: 6.917 | G7: Verified | H7: 公司 2026年3月期 決算短信（2026-04-22 登錄，JPX iXBRL 081220260422508001）：6,917（−22.1%；營益率 12.7%） | I7: 松井證券 決算情報（finance.matsui.co.jp/stock/6315/settlement）：6,917
A8: a25_ni | B8: 淨利（歸屬母公司）FY2025 | C8: ¥B | E8: 4.593 | G8: Verified | H8: 公司 2026年3月期 決算短信（2026-04-22 登錄，JPX iXBRL 081220260422508001）：4,593（−43.4%） | I8: 松井證券 決算情報（finance.matsui.co.jp/stock/6315/settlement）：4,593
A9: a25_eps | B9: 基本 EPS FY2025 | C9: ¥ | E9: 61.22 | G9: Verified | H9: 公司 2026年3月期 決算短信（2026-04-22 登錄，JPX iXBRL 081220260422508001）：61.22 | I9: 松井證券 決算情報（finance.matsui.co.jp/stock/6315/settlement）：61.22
A10: seg_semi | B10: 半導體事業營收 FY2025 | C10: ¥B | E10: 40.39 | G10: Verified | H10: 公司 2026年3月期 決算說明資料（2026-05，2025FY_end_presentation.pdf）：403.9 億日圓（+2.2%） | I10: tousaiblog（2026-05-12）：403.9
A11: seg_mold | B11: 其中：封膠設備與模具（モールディング装置・金型） | C11: ¥B | E11: 36.46 | G11: Verified | H11: 公司 2026年3月期 決算說明資料（2026-05，2025FY_end_presentation.pdf）：364.6 億日圓（擷取文字；版面待複核） | I11: 第二來源：未找到。設備與模具未分開揭露（公司不揭露）
A12: seg_osemi | B12: 其中：其他半導體（切割 singulation 等） | C12: ¥B | E12: =seg_semi-seg_mold -> 3.93 | G12: Derived | H12: 403.9 − 364.6 ＝ 39.3 | I12: 公司：記憶體投資使切割設備大增（tousaiblog 摘要，無金額）
A13: seg_new | B13: 新事業營收 FY2025（含 TSS：售後、翻新、二手機、零件） | C13: ¥B | E13: 9.47 | G13: Verified | H13: 公司 2026年3月期 決算說明資料（2026-05，2025FY_end_presentation.pdf）：94.7 億日圓（+0.6%） | I13: tousaiblog：94.7
A14: seg_med | B14: 醫療器材事業營收 FY2025（BANDIC，精密塑膠成形品） | C14: ¥B | E14: 2.48 | G14: Verified | H14: 公司 2026年3月期 決算說明資料（2026-05，2025FY_end_presentation.pdf）：24.8 億日圓（+9.9%） | I14: tousaiblog：24.8
A15: seg_las | B15: 雷射事業營收 FY2025 | C15: ¥B | E15: 2 | G15: Verified | H15: 公司 2026年3月期 決算說明資料（2026-05，2025FY_end_presentation.pdf）：20.0 億日圓（−11.0%） | I15: tousaiblog：20.0
A16: seg_adj | B16: 事業合計與營收的差額（取整與調整） | C16: ¥B | E16: =a25_rev-seg_semi-seg_new-seg_med-seg_las -> 0.025 | G16: Derived | H16: 營收 − 四事業合計 | I16: FY2025 以後設為 0
A17: ord_25 | B17: 受注高 FY2025 | C17: ¥B | E17: 59.56 | G17: Verified | H17: 公司 2026年3月期 決算說明資料（2026-05，2025FY_end_presentation.pdf）：595.6 億日圓（+25.6%，史上第二高） | I17: tousaiblog：595.6
A18: bl_25 | B18: 受注殘高 2026-03 末 | C18: ¥B | E18: 30.14 | G18: Verified | H18: 公司 2026年3月期 決算說明資料（2026-05，2025FY_end_presentation.pdf）：301.4 億日圓 | I18: 2025-09 末 267.4（公司 2026年3月期 第2四半期 決算說明會資料（2025-11-07））
A19: sh | B19: TOWA 封膠設備全球市占（2024 年，TechInsights） | C19: % | D19: 0.6 | E19: 0.648 | F19: 0.7 | G19: Interested-party | H19: 公司 2026年3月期 第2四半期 決算說明會資料（2025-11-07） 第 14 頁、公司 2026年3月期 決算說明資料（2026-05，2025FY_end_presentation.pdf）：TechInsights 數據，世界市占 No.1；圓餅最大塊 64.8%（標籤 A–D 未明示哪塊是公司） | I19: 本專案候選表：市占約 2/3（markets/invest_map universe，非獨立來源）。只透過「市占流失」進入模型；FY2025 水準已含在校準中
A20: B. AI 錨點（校準用；公司不揭露 AI 或 HBM 金額）
A21: ai_25 | B21: FY2025 AI 相關封膠設備與模具營收（HBM＋CoWoS 等 2.5D／晶圓級） | C21: ¥B | D21: 7 | E21: 10 | F21: 13 | G21: Assumed | H21: 公司不揭露。推估：說明資料圓餅「移轉成形 59%／壓縮成形 41%」（標籤對應未確認）× 封膠 36.5 ≈ 壓縮成形 15.0；AI（HBM、AI 加速器、先進封裝）約占壓縮成形三分之二 → 約 10.0（約占營收 18%） | I21: 第二來源：未找到。公司說法（Interested-party）：壓縮成形占比上升改善組合；AI／資料中心帶動第二季後的接單。低／高 ±30%
A22: w_hbm | B22: AI 相關中 HBM 比重 FY2025（其餘為 CoWoS 等 2.5D／晶圓級封膠） | C22: % | D22: 0.35 | E22: 0.5 | F22: 0.65 | G22: Assumed | H22: 公司 2026年3月期 第2四半期 決算說明會資料（2025-11-07）：HBM 封膠設備（含同業）累計約 30 台，數年內需再增 30–45 台；已取得 HBM4 客戶認證 | I22: 比重未找到；取一半。HBM 與 CoWoS 的成長形狀不同，Sens 列 35%／65%
A23: C. HBM 封膠需求（skhynix 成品 Mkt 頁，情境 A／B／C 各一列；唯讀）
A24: hsA_25 | B24: HBM 出貨位元 2025（EB；A） | C24: EB | E24: 2.2251147 | G24: Derived | H24: skhynix/dist/20261030_SK海力士個股模型_v0.6.1.xlsx｜Mkt!C24:G24 | I24: markets/memory：出貨＝MIN(需求 × 情境顆數係數, 供給)；2028–29 隨同字母情境
A25: hsA_26 | B25: HBM 出貨位元 2026（EB；A） | C25: EB | E25: 3.782695 | G25: Derived | H25: skhynix/dist/20261030_SK海力士個股模型_v0.6.1.xlsx｜Mkt!C24:G24 | I25: 同上
A26: hsA_27 | B26: HBM 出貨位元 2027（EB；A） | C26: EB | E26: 5.8631772 | G26: Derived | H26: skhynix/dist/20261030_SK海力士個股模型_v0.6.1.xlsx｜Mkt!C24:G24 | I26: 同上
A27: hsA_28 | B27: HBM 出貨位元 2028（EB；A） | C27: EB | E27: 8.501607 | G27: Derived | H27: skhynix/dist/20261030_SK海力士個股模型_v0.6.1.xlsx｜Mkt!C24:G24 | I27: 同上
A28: hsA_29 | B28: HBM 出貨位元 2029（EB；A） | C28: EB | E28: 11.477169 | G28: Derived | H28: skhynix/dist/20261030_SK海力士個股模型_v0.6.1.xlsx｜Mkt!C24:G24 | I28: 同上
A29: hsB_25 | B29: HBM 出貨位元 2025（EB；B） | C29: EB | E29: 2.2251147 | G29: Derived | H29: skhynix/dist/20261030_SK海力士個股模型_v0.6.1.xlsx｜Mkt!C25:G25 | I29: markets/memory：出貨＝MIN(需求 × 情境顆數係數, 供給)；2028–29 隨同字母情境
A30: hsB_26 | B30: HBM 出貨位元 2026（EB；B） | C30: EB | E30: 3.782695 | G30: Derived | H30: skhynix/dist/20261030_SK海力士個股模型_v0.6.1.xlsx｜Mkt!C25:G25 | I30: 同上
A31: hsB_27 | B31: HBM 出貨位元 2027（EB；B） | C31: EB | E31: 5.8631772 | G31: Derived | H31: skhynix/dist/20261030_SK海力士個股模型_v0.6.1.xlsx｜Mkt!C25:G25 | I31: 同上
A32: hsB_28 | B32: HBM 出貨位元 2028（EB；B） | C32: EB | E32: 8.22296 | G32: Derived | H32: skhynix/dist/20261030_SK海力士個股模型_v0.6.1.xlsx｜Mkt!C25:G25 | I32: 同上
A33: hsB_29 | B33: HBM 出貨位元 2029（EB；B） | C33: EB | E33: 11.357964 | G33: Derived | H33: skhynix/dist/20261030_SK海力士個股模型_v0.6.1.xlsx｜Mkt!C25:G25 | I33: 同上
A34: hsC_25 | B34: HBM 出貨位元 2025（EB；C） | C34: EB | E34: 2.2251147 | G34: Derived | H34: skhynix/dist/20261030_SK海力士個股模型_v0.6.1.xlsx｜Mkt!C26:G26 | I34: markets/memory：出貨＝MIN(需求 × 情境顆數係數, 供給)；2028–29 隨同字母情境
A35: hsC_26 | B35: HBM 出貨位元 2026（EB；C） | C35: EB | E35: 3.782695 | G35: Derived | H35: skhynix/dist/20261030_SK海力士個股模型_v0.6.1.xlsx｜Mkt!C26:G26 | I35: 同上
... A38: hsC_29 | B38: HBM 出貨位元 2029（EB；C） | C38: EB | E38: 8.017386 | G38: Derived | H38: skhynix/dist/20261030_SK海力士個股模型_v0.6.1.xlsx｜Mkt!C26:G26 | I38: 同上
A39: den_25 | B39: DRAM 核心晶粒容量（組合平均）2025 | C39: Gb／顆 | D39: 22 | E39: 24 | F39: 24 | G39: Assumed | H39: 沿用 disco/ 的假設（JEDEC HBM4：24Gb 或 32Gb 晶粒，TrendForce 2025-04-28） | I39: 組合比例未找到
A40: den_26 | B40: DRAM 核心晶粒容量（組合平均）2026 | C40: Gb／顆 | D40: 24 | E40: 24 | F40: 26 | G40: Assumed | H40: 沿用 disco/ 的假設（JEDEC HBM4：24Gb 或 32Gb 晶粒，TrendForce 2025-04-28） | I40: 同上
A41: den_27 | B41: DRAM 核心晶粒容量（組合平均）2027 | C41: Gb／顆 | D41: 24 | E41: 26 | F41: 28 | G41: Assumed | H41: 沿用 disco/ 的假設（JEDEC HBM4：24Gb 或 32Gb 晶粒，TrendForce 2025-04-28） | I41: 同上
A42: den_28 | B42: DRAM 核心晶粒容量（組合平均）2028 | C42: Gb／顆 | D42: 24 | E42: 28 | F42: 32 | G42: Assumed | H42: 沿用 disco/ 的假設（JEDEC HBM4：24Gb 或 32Gb 晶粒，TrendForce 2025-04-28） | I42: 同上
A43: den_29 | B43: DRAM 核心晶粒容量（組合平均）2029 | C43: Gb／顆 | D43: 26 | E43: 30 | F43: 32 | G43: Assumed | H43: 沿用 disco/ 的假設（JEDEC HBM4：24Gb 或 32Gb 晶粒，TrendForce 2025-04-28） | I43: 同上
A44: stk_25 | B44: HBM 平均堆疊層數 2025 | C44: 層 | D44: 8 | E44: 10 | F44: 12 | G44: Assumed | H44: 沿用 disco/ 的假設（JEDEC HBM4：4／8／12／16 層） | I44: 封膠以「堆疊」為單位：每個 HBM 堆疊封一次；層數愈高、同位元的堆疊數愈少
A45: stk_26 | B45: HBM 平均堆疊層數 2026 | C45: 層 | D45: 10 | E45: 12 | F45: 12 | G45: Assumed | H45: 沿用 disco/ 的假設（JEDEC HBM4：4／8／12／16 層） | I45: 同上
A46: stk_27 | B46: HBM 平均堆疊層數 2027 | C46: 層 | D46: 12 | E46: 12.5 | F46: 14 | G46: Assumed | H46: 沿用 disco/ 的假設（JEDEC HBM4：4／8／12／16 層） | I46: 同上
A47: stk_28 | B47: HBM 平均堆疊層數 2028 | C47: 層 | D47: 12 | E47: 14 | F47: 16 | G47: Assumed | H47: 沿用 disco/ 的假設（JEDEC HBM4：4／8／12／16 層） | I47: 同上
A48: stk_29 | B48: HBM 平均堆疊層數 2029 | C48: 層 | D48: 12 | E48: 15 | F48: 16 | G48: Assumed | H48: 沿用 disco/ 的假設（JEDEC HBM4：4／8／12／16 層） | I48: 同上
A49: dlt | B49: 已裝機封膠產能每年汰換／升級比例（新機需求＝下一年產能增量＋汰換） | C49: %/年 | D49: 0.05 | E49: 0.1 | F49: 0.15 | G49: Assumed | H49: 公司：高性能化的汰換需求（公司 2026年3月期 第2四半期 決算說明會資料（2025-11-07），無數字） | I49: 與校準係數一起只能識別乘積的形狀；Sens 列 5%／15%
A50: g_tail | B50: CY2030–31 HBM 堆疊數與 CoWoS 片數年增（上游只到 2029；三情境同值） | C50: % | D50: 0 | E50: 0.1 | F50: 0.2 | G50: Assumed | H50: 無：上游只到 2029；設備比產能早一年買，FY2029 需要 CY2030–31 | I50: 三情境同值，不自訂行業路徑
A51: D. CoWoS 等 2.5D 封膠需求：台積電模型 CoWoS 需求（唯讀）
A52: cw_25 | B52: CoWoS 需求 CY2025 | C52: 千片 | D52: 600 | E52: 670 | F52: 700 | G52: Interested-party | H52: 36Kr／半導體產業縱橫（2025-12-04）：2025 全球 CoWoS 需求約 67 萬片（disco/ 同值） | I52: TrendForce 月產能 2024 年底 3.5–4 萬、2025 年底 7.5–8 萬（Derived 年均約 66 萬）
A53: cw_26 | B53: CoWoS 需求 CY2026（台積電模型，情境 A 顆數） | C53: 千片 | E53: 1107.8576 | G53: Derived | H53: tsmc/dist/20261030_台積電個股模型_v0.4.1.xlsx｜CoWoS!B13:E13 | I53: B、C 的 2028–29 乘以同字母情境顆數係數（下列 um）
A54: cw_27 | B54: CoWoS 需求 CY2027（台積電模型，情境 A 顆數） | C54: 千片 | E54: 2096.4286 | G54: Derived | H54: tsmc/dist/20261030_台積電個股模型_v0.4.1.xlsx｜CoWoS!B13:E13 | I54: 同上
A55: cw_28 | B55: CoWoS 需求 CY2028（台積電模型，情境 A 顆數） | C55: 千片 | E55: 2620.0893 | G55: Derived | H55: tsmc/dist/20261030_台積電個股模型_v0.4.1.xlsx｜CoWoS!B13:E13 | I55: 同上
A56: cw_29 | B56: CoWoS 需求 CY2029（台積電模型，情境 A 顆數） | C56: 千片 | E56: 3013.3259 | G56: Derived | H56: tsmc/dist/20261030_台積電個股模型_v0.4.1.xlsx｜CoWoS!B13:E13 | I56: 同上
A57: um28_A | B57: 情境 A：2028 顆數 ÷ 基準（CoWoS 片數同比例） | C57: x | E57: 1 | G57: Derived | H57: tsmc/dist/20261030_台積電個股模型_v0.4.1.xlsx｜In!E37 | I57: markets/memory SCEN_UNITS（單一來源；建置時檢查與台積電 In 頁相同）
A58: um29_A | B58: 情境 A：2029 顆數 ÷ 基準（CoWoS 片數同比例） | C58: x | E58: 1 | G58: Derived | H58: tsmc/dist/20261030_台積電個股模型_v0.4.1.xlsx｜In!E38 | I58: 同上
A59: um28_B | B59: 情境 B：2028 顆數 ÷ 基準（CoWoS 片數同比例） | C59: x | E59: 0.8 | G59: Derived | H59: tsmc/dist/20261030_台積電個股模型_v0.4.1.xlsx｜In!E39 | I59: 同上
A60: um29_B | B60: 情境 B：2029 顆數 ÷ 基準（CoWoS 片數同比例） | C60: x | E60: 0.85 | G60: Derived | H60: tsmc/dist/20261030_台積電個股模型_v0.4.1.xlsx｜In!E40 | I60: 同上
A61: um28_C | B61: 情境 C：2028 顆數 ÷ 基準（CoWoS 片數同比例） | C61: x | E61: 0.6 | G61: Derived | H61: tsmc/dist/20261030_台積電個股模型_v0.4.1.xlsx｜In!E41 | I61: 同上
A62: um29_C | B62: 情境 C：2029 顆數 ÷ 基準（CoWoS 片數同比例） | C62: x | E62: 0.6 | G62: Derived | H62: tsmc/dist/20261030_台積電個股模型_v0.4.1.xlsx｜In!E42 | I62: 同上
A63: E. 非 AI 後段需求：SEMI 組裝與封裝設備 × 同字母情境的非 AI 設備比例（markets/equipment，唯讀）
A64: pk_25 | B64: SEMI 組裝與封裝設備 CY2025（情境 A 路徑） | C64: US$B | E64: 6.1131387 | G64: Derived | H64: markets/equipment/dist/20261023_半導體設備市場模型_v0.1.3.xlsx｜Mkt!C46:G46 | I64: SEMI 2026-07；2027 幾何內插（markets/equipment）
A65: pk_26 | B65: SEMI 組裝與封裝設備 CY2026（情境 A 路徑） | C65: US$B | E65: 6.7 | G65: Derived | H65: markets/equipment/dist/20261023_半導體設備市場模型_v0.1.3.xlsx｜Mkt!C46:G46 | I65: 同上
A66: pk_27 | B66: SEMI 組裝與封裝設備 CY2027（情境 A 路徑） | C66: US$B | E66: 7.5907839 | G66: Derived | H66: markets/equipment/dist/20261023_半導體設備市場模型_v0.1.3.xlsx｜Mkt!C46:G46 | I66: 同上
A67: pk_28 | B67: SEMI 組裝與封裝設備 CY2028（情境 A 路徑） | C67: US$B | E67: 8.6 | G67: Derived | H67: markets/equipment/dist/20261023_半導體設備市場模型_v0.1.3.xlsx｜Mkt!C46:G46 | I67: 同上
A68: pk_29 | B68: SEMI 組裝與封裝設備 CY2029（情境 A 路徑） | C68: US$B | E68: 9.288 | G68: Derived | H68: markets/equipment/dist/20261023_半導體設備市場模型_v0.1.3.xlsx｜Mkt!C46:G46 | I68: 同上
A69: eqtA_25 | B69: 設備總額 CY2025（情境 A） | C69: US$B | E69: 134.68936 | G69: Derived | H69: markets/equipment/dist/20261023_半導體設備市場模型_v0.1.3.xlsx｜Mkt!C6:G6 | I69: markets/equipment Mkt 頁「設備總額」
A70: eqtA_26 | B70: 設備總額 CY2026（情境 A） | C70: US$B | E70: 178.15705 | G70: Derived | H70: markets/equipment/dist/20261023_半導體設備市場模型_v0.1.3.xlsx｜Mkt!C6:G6 | I70: 同上
A71: eqtA_27 | B71: 設備總額 CY2027（情境 A） | C71: US$B | E71: 218.22554 | G71: Derived | H71: markets/equipment/dist/20261023_半導體設備市場模型_v0.1.3.xlsx｜Mkt!C6:G6 | I71: 同上
A72: eqtA_28 | B72: 設備總額 CY2028（情境 A） | C72: US$B | E72: 246.02863 | G72: Derived | H72: markets/equipment/dist/20261023_半導體設備市場模型_v0.1.3.xlsx｜Mkt!C6:G6 | I72: 同上
A73: eqtA_29 | B73: 設備總額 CY2029（情境 A） | C73: US$B | E73: 260.65569 | G73: Derived | H73: markets/equipment/dist/20261023_半導體設備市場模型_v0.1.3.xlsx｜Mkt!C6:G6 | I73: 同上
A74: eqaA_25 | B74: AI 相關設備 CY2025（情境 A） | C74: US$B | E74: 65.465015 | G74: Derived | H74: markets/equipment/dist/20261023_半導體設備市場模型_v0.1.3.xlsx｜Mkt!C9:G9 | I74: 非 AI 設備＝設備總額 − AI 相關設備；情境 s 的封裝設備＝SEMI 封裝 ×（非 AI 設備 s ÷ 非 AI 設備 A）
A75: eqaA_26 | B75: AI 相關設備 CY2026（情境 A） | C75: US$B | E75: 93.04079 | G75: Derived | H75: markets/equipment/dist/20261023_半導體設備市場模型_v0.1.3.xlsx｜Mkt!C9:G9 | I75: 同上
... A98: eqaC_29 | B98: AI 相關設備 CY2029（情境 C） | C98: US$B | E98: 94.264444 | G98: Derived | H98: markets/equipment/dist/20261023_半導體設備市場模型_v0.1.3.xlsx｜Mkt!C25:G25 | I98: 同上
A99: g_pk_tail | B99: CY2030 非 AI 封裝設備與設備總額年增（上游只到 2029；三情境同值） | C99: % | D99: 0 | E99: 0.05 | F99: 0.1 | G99: Assumed | H99: 無：上游只到 2029 | I99: 三情境同值
A100: F. 其他事業（Analogy：公司自己的歷史與計畫）
A101: g_tss | B101: 新事業（TSS 售後等）年增 | C101: % | D101: 0 | E101: 0.03 | F101: 0.06 | G101: Analogy | H101: FY2025 +0.6%、公司 FY2026 計畫 +3.1%（公司 2026年3月期 決算說明資料（2026-05，2025FY_end_presentation.pdf）） | I101: 售後隨裝機量，但含二手機與翻新（波動大）
A102: g_med | B102: 醫療器材事業年增 | C102: % | D102: 0 | E102: 0.03 | F102: 0.06 | G102: Analogy | H102: FY2025 +9.9%、公司 FY2026 計畫 +2.5% | I102: 與半導體循環無關
A103: G. 公司特有變數（隨情境；方向：A 最有利、C 最不利）
A104: shl_A | B104: 情境 A：FY2029 AI 封膠市占流失（相對 2025，線性；pt） | C104: pt | D104: 0 | E104: 0 | F104: 0.03 | G104: Assumed | H104: 競爭：ASMPT、Yamada（Apic Yamada）、韓國與中國本土廠的壓縮成形機；公司稱 HBM 客戶基礎擴大（Interested-party） | I104: 只作用在 AI 封膠（校準已含 FY2025 水準）
A105: shl_B | B105: 情境 B：FY2029 AI 封膠市占流失（相對 2025，線性；pt） | C105: pt | D105: 0 | E105: 0.03 | F105: 0.06 | G105: Assumed | H105: B：小幅流失 | I105: 只作用在 AI 封膠（校準已含 FY2025 水準）
A106: shl_C | B106: 情境 C：FY2029 AI 封膠市占流失（相對 2025，線性；pt） | C106: pt | D106: 0.04 | E106: 0.08 | F106: 0.12 | G106: Assumed | H106: C：HBM／CoWoS 降速時價格競爭加劇 | I106: 只作用在 AI 封膠（校準已含 FY2025 水準）
A107: ima_A | B107: 情境 A：增量營益率調整（相對 Hist 迴歸斜率；pt） | C107: pt | D107: 0.01 | E107: 0.03 | F107: 0.05 | G107: Assumed | H107: A：壓縮成形占比上升、首台成本不再（公司說法） | I107: 增量營益率＝營業利益變動 ÷ 營收變動
A108: ima_B | B108: 情境 B：增量營益率調整（相對 Hist 迴歸斜率；pt） | C108: pt | D108: -0.02 | E108: 0 | F108: 0.02 | G108: Assumed | H108: B：迴歸斜率 | I108: 增量營益率＝營業利益變動 ÷ 營收變動
A109: ima_C | B109: 情境 C：增量營益率調整（相對 Hist 迴歸斜率；pt） | C109: pt | D109: -0.08 | E109: -0.05 | F109: -0.02 | G109: Assumed | H109: C：低毛利案件與首台成本延續（FY2025 營益率 12.7% 的原因） | I109: 增量營益率＝營業利益變動 ÷ 營收變動
A110: H. 利潤率（由 Hist 頁 FY2016–FY2025 推得，不寫死）
A111: im | B111: 增量營益率（營業利益 ＝ 截距 ＋ 斜率 × 營收 的斜率） | C111: x | D111: =SLOPE(Hist!E6:E15,Hist!B6:B15)-0.05 -> 0.21952113 | E111: =SLOPE(Hist!E6:E15,Hist!B6:B15) -> 0.26952113 | F111: =SLOPE(Hist!E6:E15,Hist!B6:B15)+0.05 -> 0.31952113 | G111: Derived | H111: Hist 頁 10 年（FY2016–FY2025）最小平方法；低／高 ±5pt（Assumed） | I111: FY2027 起：營業利益＝FY2026 錨點營業利益＋（斜率＋情境調整）×（營收 − FY2026 營收）
A112: nioi | B112: 淨利 ÷ 營業利益（FY2027 起） | C112: x | D112: 0.65 | E112: =g26_ni/g26_oi -> 0.68359375 | F112: 0.72 | G112: Derived | H112: 基準＝公司 FY2026 指引 7,000 ÷ 10,240 ＝ 0.684 | I112: FY2025 0.664（4,593 ÷ 6,917）；FY2024 0.915（含特別利益）；低 0.65、高 0.72（Assumed）
A113: shares | B113: 加權平均股數 | C113: 百萬股 | E113: 75.029892 | G113: Verified | H113: 公司 2027年3月期 第1四半期 決算短信（2026-08-06，JPX iXBRL 081220260702586673）：第一季期中平均 75,029,892 股（不含 J-ESOP 信託持股） | I113: FY2025 平均 75,020,506（公司 2026年3月期 決算短信（2026-04-22 登錄，JPX iXBRL 081220260422508001））
A114: I. FY2026 實績、公司指引與對帳參考
A115: q1_rev | B115: FY2026 第一季營收（2026-04～06） | C115: ¥B | E115: 16.183 | G115: Verified | H115: 公司 2027年3月期 第1四半期 決算短信（2026-08-06，JPX iXBRL 081220260702586673）：16,183（+100.3%） | I115: 松井證券 決算情報（finance.matsui.co.jp/stock/6315/settlement）：16,183
A116: q1_oi | B116: FY2026 第一季營業利益 | C116: ¥B | E116: 2.212 | G116: Verified | H116: 公司 2027年3月期 第1四半期 決算短信（2026-08-06，JPX iXBRL 081220260702586673）：2,212（前年同期 −581） | I116: 松井證券 決算情報（finance.matsui.co.jp/stock/6315/settlement）
A117: q1_ni | B117: FY2026 第一季淨利 | C117: ¥B | E117: 1.657 | G117: Verified | H117: 公司 2027年3月期 第1四半期 決算短信（2026-08-06，JPX iXBRL 081220260702586673）：1,657 | I117: 松井證券 決算情報（finance.matsui.co.jp/stock/6315/settlement）
A118: q1_eps | B118: FY2026 第一季 EPS | C118: ¥ | E118: 22.09 | G118: Verified | H118: 公司 2027年3月期 第1四半期 決算短信（2026-08-06，JPX iXBRL 081220260702586673）：22.09 | I118: 松井證券 決算情報（finance.matsui.co.jp/stock/6315/settlement）
A119: h1g_rev | B119: 公司指引：FY2026 上半營收 | C119: ¥B | E119: 32 | G119: Interested-party | H119: 公司 2027年3月期 第1四半期 決算短信（2026-08-06，JPX iXBRL 081220260702586673）：32,000（未修正） | I119: 公司 2026年3月期 決算短信（2026-04-22 登錄，JPX iXBRL 081220260422508001） 同值
A120: h1g_oi | B120: 公司指引：FY2026 上半營業利益 | C120: ¥B | E120: 5.12 | G120: Interested-party | H120: 公司 2027年3月期 第1四半期 決算短信（2026-08-06，JPX iXBRL 081220260702586673）：5,120 | I120: 同上
A121: g26_rev | B121: 公司指引：FY2026 營收 | C121: ¥B | E121: 64 | G121: Interested-party | H121: 公司 2027年3月期 第1四半期 決算短信（2026-08-06，JPX iXBRL 081220260702586673）：64,000（+17.7%；2026-08-06 未修正） | I121: 公司 2026年3月期 決算說明資料（2026-05，2025FY_end_presentation.pdf）：640.0 億日圓
A122: g26_oi | B122: 公司指引：FY2026 營業利益 | C122: ¥B | E122: 10.24 | G122: Interested-party | H122: 公司 2027年3月期 第1四半期 決算短信（2026-08-06，JPX iXBRL 081220260702586673）：10,240（營益率 16.0%） | I122: 公司 2026年3月期 決算說明資料（2026-05，2025FY_end_presentation.pdf）
A123: g26_ni | B123: 公司指引：FY2026 淨利 | C123: ¥B | E123: 7 | G123: Interested-party | H123: 公司 2027年3月期 第1四半期 決算短信（2026-08-06，JPX iXBRL 081220260702586673）：7,000；EPS 93.30 | I123: 公司 2026年3月期 決算說明資料（2026-05，2025FY_end_presentation.pdf）
A124: g26_eps | B124: 公司指引：FY2026 EPS | C124: ¥ | E124: 93.3 | G124: Interested-party | H124: 公司 2027年3月期 第1四半期 決算短信（2026-08-06，JPX iXBRL 081220260702586673）：93.30 | I124: kabutan 同值
...

Sheet Q
A1: Q — 季度實績（十億日圓；EPS 為日圓）。會計年度 4–3 月。來源1：松井證券季度表（百萬日圓）；來源2：公司決算短信與說明資料
A3: 項目 | B3: FY25 Q1 | C3: FY25 Q2 | D3: FY25 Q3 | E3: FY25 Q4 | F3: FY2025 | G3: FY26 Q1 | H3: FY26 上半（公司指引） | I3: FY2026（公司指引） | J3: 標記 | K3: 來源1 | L3: 來源2／說明
A4: 營收 | B4: 8.08 | C4: 15.369 | D4: 13.481 | E4: 17.435 | F4: =SUM(B4:E4) -> 54.365 | G4: 16.183 | H4: =h1g_rev -> 32 | I4: =g26_rev -> 64 | J4: Verified／Interested-party（指引） | K4: 松井：8,080／15,369／13,481／17,435；FY26 Q1 16,183 | L4: 公司：上半 234.4 億（說明資料 2025-11-07）＝8.08＋15.37
A5: 營業利益 | B5: -0.581 | C5: 3.074 | D5: 1.192 | E5: 3.232 | F5: =SUM(B5:E5) -> 6.917 | G5: 2.212 | H5: =h1g_oi -> 5.12 | I5: =g26_oi -> 10.24 | J5: Verified／Interested-party（指引） | K5: 松井：−581／3,074／1,192／3,232；2,212 | L5: 公司：上半 24.9 億
A6: 淨利 | B6: -0.528 | C6: 2.377 | D6: 0.778 | E6: 1.966 | F6: =SUM(B6:E6) -> 4.593 | G6: 1.657 | H6: 3.5 | I6: =g26_ni -> 7 | J6: Verified／Interested-party（指引） | K6: 松井：−528／2,377／778／1,966；1,657 | L6: 上半指引 3,500（決算短信）
A7: EPS（基本） | B7: -7.05 | C7: 31.7 | D7: 10.37 | E7: 26.2 | F7: =SUM(B7:E7) -> 61.22 | G7: 22.09 | H7: 46.65 | I7: =g26_eps -> 93.3 | J7: Verified／Interested-party（指引） | K7: 松井 | L7: 上半指引 46.65
A8: 受注高 | B8: 10.43 | C8: 14.61 | F8: =ord_25 -> 59.56 | J8: Verified／Interested-party（指引） | K8: 說明資料 2025-11-07：上半 250.3、第二季 146.1（第一季＝差額 104.3，Derived） | L8: FY2025 全年 595.6 → 下半 345.3（Derived）；FY2026 計畫每季 150–170
A9: 營業利益率 | B9: =B5/B4 -> -0.071905941 | C9: =C5/C4 -> 0.20001301 | D9: =D5/D4 -> 0.08842074 | E9: =E5/E4 -> 0.18537425 | F9: =F5/F4 -> 0.12723259 | G9: =G5/G4 -> 0.13668665 | H9: =H5/H4 -> 0.16 | I9: =I5/I4 -> 0.16
A10: 檢查：FY2025 四季合計 − 年度（營收、營業利益、淨利；應約為 0） | B10: =F4-a25_rev -> 0 | C10: =F5-a25_oi -> 0 | D10: =F6-a25_ni -> 0
A11: FY2026 第一季占全年指引（營收／營業利益） | B11: =G4/I4 -> 0.25285937 | C11: =G5/I5 -> 0.21601562
A13: 第二季（2026-07～09）財報尚未公布（去年為 11-07 公布）；本版 FY2026 錨定公司全年指引。FY2025 第一季虧損、第三季因記憶體量產投資延後而下修（公司第三季說明資料）

Sheet Hist
A1: Hist — 年度實績（十億日圓；EPS 為日圓）。來源：公司決算短信（JPX）、四半期報告書（EDINET）、松井證券（FY2021 起）、the-shashi（轉載有價證券報告書）。用途：增量營益率迴歸、十年平均淨利率、10 年 P/E 的 EPS
A2: 股票分割：2024-10-01 一股分三股（基準日 2024-09-30；tipranks 轉載公司公告；Yahoo Finance 分割紀錄 2024-09-27）。FY2023（2024年3月期）以前公司公布的 EPS 除以 3；FY2021–FY2023 的松井、kabutan 數字已調整
A5: 會計年度 | B5: 營收 | C5: 毛利 | D5: 銷管費 | E5: 營業利益 | F5: 淨利 | G5: EPS（公司公布） | H5: 淨利率 | I5: 分割係數 | J5: EPS（分割調整後） | K5: 營業利益率 | L5: 來源1 | M5: 來源2
A6: FY2016（2017-03） | B6: 27.632 | E6: 3.831 | F6: 3.867 | G6: 154.64 | H6: =F6/B6 -> 0.13994644 | I6: 3 | J6: =G6/I6 -> 51.546667 | K6: =E6/B6 -> 0.1386436 | L6: 決算短信 2018-05-10（前期欄） | M6: the-shashi：38.3／38.7
A7: FY2017（2018-03） | B7: 31.01 | E7: 3.682 | F7: 3.026 | G7: 121.02 | H7: =F7/B7 -> 0.097581425 | I7: 3 | J7: =G7/I7 -> 40.34 | K7: =E7/B7 -> 0.11873589 | L7: 決算短信 2018-05-10（JPX 140120180422416748） | M7: 決算短信 2019-05（前期欄）同值
A8: FY2018（2019-03） | B8: 28.272 | C8: 6.986 | D8: =C8-E8 -> 6.049 | E8: 0.937 | F8: 0.877 | G8: 35.09 | H8: =F8/B8 -> 0.031020091 | I8: 3 | J8: =G8/I8 -> 11.696667 | K8: =E8/B8 -> 0.033142332 | L8: 決算短信 2019-05（JPX 140120190511422405） | M8: 決算短信 2020-05-07（前期欄，毛利 6,986）
A9: FY2019（2020-03） | B9: 25.255 | C9: 6.588 | D9: =C9-E9 -> 5.776 | E9: 0.812 | F9: 0.368 | G9: 14.75 | H9: =F9/B9 -> 0.014571372 | I9: 3 | J9: =G9/I9 -> 4.9166667 | K9: =E9/B9 -> 0.032152049 | L9: 決算短信 2020-05-07（JPX 140120200507404921） | M9: the-shashi：8.1／3.7
A10: FY2020（2021-03） | B10: 29.707 | E10: 3.62 | F10: 2.663 | G10: 106.49 | H10: =F10/B10 -> 0.089642172 | I10: 3 | J10: =G10/I10 -> 35.496667 | K10: =E10/B10 -> 0.1218568 | L10: 四半期報告書 第44期第3四半期（EDINET S100NDD0，前期通期欄：營收 29,707、淨利 2,663、EPS 106.49） | M10: 營業利益：the-shashi 36.2 億（單一來源；營收以外未見第二來源）
A11: FY2021（2022-03） | B11: 50.666 | E11: 11.505 | F11: 8.129 | G11: 108.36 | H11: =F11/B11 -> 0.1604429 | I11: 1 | J11: =G11/I11 -> 108.36 | K11: =E11/B11 -> 0.22707536 | L11: 松井證券 決算情報（finance.matsui.co.jp/stock/6315/settlement）（分割調整後） | M11: the-shashi：115／81.3
A12: FY2022（2023-03） | B12: 53.822 | E12: 10.037 | F12: 7.346 | G12: 97.9 | H12: =F12/B12 -> 0.13648694 | I12: 1 | J12: =G12/I12 -> 97.9 | K12: =E12/B12 -> 0.18648508 | L12: 松井證券 決算情報（finance.matsui.co.jp/stock/6315/settlement） | M12: kabutan：同值
A13: FY2023（2024-03） | B13: 50.471 | E13: 8.661 | F13: 6.444 | G13: 85.9 | H13: =F13/B13 -> 0.12767728 | I13: 1 | J13: =G13/I13 -> 85.9 | K13: =E13/B13 -> 0.1716035 | L13: 松井證券 決算情報（finance.matsui.co.jp/stock/6315/settlement） | M13: kabutan：同值
A14: FY2024（2025-03） | B14: 53.479 | E14: 8.88 | F14: 8.121 | G14: 108.28 | H14: =F14/B14 -> 0.151854 | I14: 1 | J14: =G14/I14 -> 108.28 | K14: =E14/B14 -> 0.16604649 | L14: 公司 2026年3月期 決算短信（2026-04-22 登錄，JPX iXBRL 081220260422508001）（前期欄） | M14: 松井證券 決算情報（finance.matsui.co.jp/stock/6315/settlement）
A15: FY2025（2026-03） | B15: 54.365 | C15: 18.372 | D15: =C15-E15 -> 11.455 | E15: 6.917 | F15: 4.593 | G15: 61.22 | H15: =F15/B15 -> 0.084484503 | I15: 1 | J15: =G15/I15 -> 61.22 | K15: =E15/B15 -> 0.12723259 | L15: 公司 2026年3月期 決算短信（2026-04-22 登錄，JPX iXBRL 081220260422508001） | M15: 松井證券 決算情報（finance.matsui.co.jp/stock/6315/settlement）
A17: 檢查：FY2025 列 − In 頁 a25_*（應為 0） | B17: =ABS(B15-a25_rev)+ABS(C15-a25_gp)+ABS(E15-a25_oi)+ABS(F15-a25_ni)+ABS(G15-a25_eps) -> 0
A19: 迴歸與統計
A20: 營業利益 ＝ 截距 ＋ 斜率 × 營收：斜率（增量營益率） | B20: =SLOPE(E6:E15,B6:B15) -> 0.26952113
A21: 截距 ¥B | B21: =INTERCEPT(E6:E15,B6:B15) -> -5.018754
A22: R² | B22: =RSQ(E6:E15,B6:B15) -> 0.82909389
A23: FY2025 營業利益：迴歸值 − 實績（¥B） | B23: =INTERCEPT(E6:E15,B6:B15)+SLOPE(E6:E15,B6:B15)*B15-E15 -> 2.716762
A24: 十年平均淨利率 | B24: =AVERAGE(H6:H15) -> 0.10337071
A25: 十年平均營業利益率 | B25: =AVERAGE(K6:K15) -> 0.13229737
A26: FY2021–FY2025 平均營業利益率（AI 前後的高營收期） | B26: =AVERAGE(K11:K15) -> 0.1756886
A27: 毛利率 FY2018／FY2019／FY2025（其餘年度未找到） | B27: =C8/B8 -> 0.2470996 | C27: =C9/B9 -> 0.26085924 | D27: =C15/B15 -> 0.33793801

Sheet PL
A1: PL — TOWA 損益（¥B；FY2025 實績；FY2026 錨定公司全年指引；FY2027–FY2029 驅動推導；FY2030–FY2032 收斂法見底部）。頂端為摘要，下方為三情境各一個完整推導區塊
A3: 情境／項目 | B3: 單位 | C3: FY2025A | D3: FY2026 | E3: FY2027 | F3: FY2028 | G3: FY2029 | H3: 說明
A4: 情境 A（順利）
A5: 營收 | B5: ¥B | C5: =C101 -> 54.365 | D5: =D101 -> 64 | E5: =E101 -> 66.938645 | F5: =F101 -> 71.971111 | G5: =G101 -> 74.976624
A6: 半導體製造裝置事業 | B6: ¥B | C6: =C100 -> 40.39 | D6: =D100 -> 48.821956 | E6: =E100 -> 50.866189 | F6: =F100 -> 55.167886 | G6: =G100 -> 57.574955
A7: AI 封膠（HBM＋2.5D） | B7: ¥B | C7: =C99 -> 10 | D7: =D99 -> 13.824744 | E7: =E99 -> 10.886268 | F7: =F99 -> 10.512298 | G7: =G99 -> 9.8050901
A8: 非 AI 封膠設備與模具 | B8: ¥B | C8: =C94 -> 26.46 | D8: =D94 -> 29.81967 | E8: =E94 -> 33.78428 | F8: =F94 -> 37.78559 | G8: =G94 -> 40.508375
A9: 其他半導體（切割等） | B9: ¥B | C9: =C95 -> 3.93 | D9: =D95 -> 5.1775411 | E9: =E95 -> 6.1956409 | F9: =F95 -> 6.869999 | G9: =G95 -> 7.2614905
A10: 新事業（TSS 等） | B10: ¥B | C10: =C96 -> 9.47 | D10: =D96 -> 9.9400633 | E10: =E96 -> 10.238265 | F10: =F96 -> 10.545413 | G10: =G96 -> 10.861776
A11: 醫療器材 | B11: ¥B | C11: =C97 -> 2.48 | D11: =D97 -> 2.6031 | E11: =E97 -> 2.681193 | F11: =F97 -> 2.7616288 | G11: =G97 -> 2.8444776
A12: 雷射 | B12: ¥B | C12: =C98 -> 2 | D12: =D98 -> 2.634881 | E12: =E98 -> 3.1529979 | F12: =F98 -> 3.4961827 | G12: =G98 -> 3.695415
A13: AI 封膠占營收 | B13: % | C13: =C103 -> 0.18394187 | D13: =D103 -> 0.21601163 | E13: =E103 -> 0.16263054 | F13: =F103 -> 0.14606274 | G13: =G103 -> 0.1307753
A14: 營業利益 | B14: ¥B | C14: =C104 -> 6.917 | D14: =D104 -> 10.24 | E14: =E104 -> 11.120186 | F14: =F104 -> 12.627516 | G14: =G104 -> 13.527731
A15: 營業利益率 | B15: % | C15: =C105 -> 0.12723259 | D15: =D105 -> 0.16 | E15: =E105 -> 0.16612506 | F15: =F105 -> 0.17545257 | G15: =G105 -> 0.18042598
A16: 淨利 | B16: ¥B | C16: =C106 -> 4.593 | D16: =D106 -> 7 | E16: =E106 -> 7.6016898 | F16: =F106 -> 8.6320911 | G16: =G106 -> 9.2474721
A17: EPS | B17: ¥ | C17: =C107 -> 61.22 | D17: =D107 -> 93.296149 | E17: =E107 -> 101.31548 | F17: =F107 -> 115.04869 | G17: =G107 -> 123.25051
A18: 對照：營收（只用驅動，無錨點） | B18: ¥B | C18: =C84 -> 54.365 | D18: =D84 -> 62.802659 | E18: =E84 -> 65.889991 | F18: =F84 -> 70.821311 | G18: =G84 -> 73.757365
A20: 情境 B（平平）
A21: 營收 | B21: ¥B | C21: =C152 -> 54.365 | D21: =D152 -> 64 | E21: =E152 -> 62.111502 | F21: =F152 -> 65.41661 | G21: =G152 -> 63.249191
A22: 半導體製造裝置事業 | B22: ¥B | C22: =C151 -> 40.39 | D22: =D151 -> 48.496668 | E22: =E151 -> 46.136373 | F22: =F151 -> 49.092093 | G22: =G151 -> 46.603764
A23: AI 封膠（HBM＋2.5D） | B23: ¥B | C23: =C150 -> 10 | D23: =D150 -> 12.749415 | E23: =E150 -> 7.3185286 | F23: =F150 -> 10.340214 | G23: =G150 -> 8.6246979
A24: 非 AI 封膠設備與模具 | B24: ¥B | C24: =C145 -> 26.46 | D24: =D145 -> 30.458749 | E24: =E145 -> 32.813451 | F24: =F145 -> 32.822541 | G24: =G145 -> 32.203591
A25: 其他半導體（切割等） | B25: ¥B | C25: =C146 -> 3.93 | D25: =D146 -> 5.2885034 | E25: =E146 -> 6.004393 | F25: =F146 -> 5.9293381 | G25: =G146 -> 5.7754755
A26: 新事業（TSS 等） | B26: ¥B | C26: =C147 -> 9.47 | D26: =D147 -> 10.153093 | E26: =E147 -> 10.238265 | F26: =F147 -> 10.545413 | G26: =G147 -> 10.861776
A27: 醫療器材 | B27: ¥B | C27: =C148 -> 2.48 | D27: =D148 -> 2.6588882 | E27: =E148 -> 2.681193 | F27: =F148 -> 2.7616288 | G27: =G148 -> 2.8444776
A28: 雷射 | B28: ¥B | C28: =C149 -> 2 | D28: =D149 -> 2.6913503 | E28: =E149 -> 3.0556707 | F28: =F149 -> 3.0174748 | G28: =G149 -> 2.9391733
A29: AI 封膠占營收 | B29: % | C29: =C154 -> 0.18394187 | D29: =D154 -> 0.19920961 | E29: =E154 -> 0.11782888 | F29: =F154 -> 0.15806711 | G29: =G154 -> 0.1363606
A30: 營業利益 | B30: ¥B | C30: =C155 -> 6.917 | D30: =D155 -> 10.24 | E30: =E155 -> 9.7310098 | F30: =F155 -> 10.621806 | G30: =G155 -> 10.037641
A31: 營業利益率 | B31: % | C31: =C156 -> 0.12723259 | D31: =D156 -> 0.16 | E31: =E156 -> 0.15667001 | F31: =F156 -> 0.1623717 | G31: =G156 -> 0.15869991
A32: 淨利 | B32: ¥B | C32: =C157 -> 4.593 | D32: =D157 -> 7 | E32: =E157 -> 6.6520575 | F32: =F157 -> 7.2610004 | G32: =G157 -> 6.8616687
A33: EPS | B33: ¥ | C33: =C158 -> 61.22 | D33: =D158 -> 93.296149 | E33: =E158 -> 88.658764 | F33: =F158 -> 96.774768 | G33: =G158 -> 91.452467
A34: 對照：營收（只用驅動，無錨點） | B34: ¥B | C34: =C135 -> 54.365 | D34: =D135 -> 61.484946 | E34: =E135 -> 61.08641 | F34: =F135 -> 64.386215 | G34: =G135 -> 62.227251
A36: 情境 C（不如預期）
A37: 營收 | B37: ¥B | C37: =C203 -> 54.365 | D37: =D203 -> 64 | E37: =E203 -> 56.582631 | F37: =F203 -> 53.025347 | G37: =G203 -> 53.759182
A38: 半導體製造裝置事業 | B38: ¥B | C38: =C202 -> 40.39 | D38: =D202 -> 48.258545 | E38: =E202 -> 40.760286 | F38: =F202 -> 37.273769 | G38: =G202 -> 37.577835
A39: AI 封膠（HBM＋2.5D） | B39: ¥B | C39: =C201 -> 10 | D39: =D201 -> 11.962234 | E39: =E201 -> 3.9007301 | F39: =F201 -> 5.8774213 | G39: =G201 -> 5.5954636
A40: 非 AI 封膠設備與模具 | B40: ¥B | C40: =C196 -> 26.46 | D40: =D196 -> 30.926579 | E40: =E196 -> 31.155382 | F40: =F196 -> 26.592833 | G40: =G196 -> 27.118814
A41: 其他半導體（切割等） | B41: ¥B | C41: =C197 -> 3.93 | D41: =D197 -> 5.3697319 | E41: =E197 -> 5.7041733 | F41: =F197 -> 4.8035144 | G41: =G197 -> 4.8635583
A42: 新事業（TSS 等） | B42: ¥B | C42: =C198 -> 9.47 | D42: =D198 -> 10.309039 | E42: =E198 -> 10.238265 | F42: =F198 -> 10.545413 | G42: =G198 -> 10.861776
A43: 醫療器材 | B43: ¥B | C43: =C199 -> 2.48 | D43: =D199 -> 2.6997273 | E43: =E199 -> 2.681193 | F43: =F199 -> 2.7616288 | G43: =G199 -> 2.8444776
A44: 雷射 | B44: ¥B | C44: =C200 -> 2 | D44: =D200 -> 2.732688 | E44: =E200 -> 2.9028872 | F44: =F200 -> 2.4445366 | G44: =G200 -> 2.4750933
A45: AI 封膠占營收 | B45: % | C45: =C205 -> 0.18394187 | D45: =D205 -> 0.18690991 | E45: =E205 -> 0.068938648 | F45: =F205 -> 0.11084173 | G45: =G205 -> 0.10408387
A46: 營業利益 | B46: ¥B | C46: =C206 -> 6.917 | D46: =D206 -> 10.24 | E46: =E206 -> 8.6117308 | F46: =F206 -> 7.8308318 | G46: =G206 -> 7.9919241
A47: 營業利益率 | B47: % | C47: =C207 -> 0.12723259 | D47: =D207 -> 0.16 | E47: =E207 -> 0.15219743 | F47: =F207 -> 0.14768092 | G47: =G207 -> 0.14866156
A48: 淨利 | B48: ¥B | C48: =C208 -> 4.593 | D48: =D208 -> 7 | E48: =E208 -> 5.8869254 | F48: =F208 -> 5.3531077 | G48: =G208 -> 5.4632294
A49: EPS | B49: ¥ | C49: =C209 -> 61.22 | D49: =D209 -> 93.296149 | E49: =E209 -> 78.461067 | F49: =F209 -> 71.346333 | G49: =G209 -> 72.814037
A50: 對照：營收（只用驅動，無錨點） | B50: ¥B | C50: =C186 -> 54.365 | D50: =D186 -> 60.554857 | E50: =E186 -> 55.597034 | F50: =F186 -> 52.143282 | G50: =G186 -> 52.858113
A52: 核對：三情境 FY2025 − 實績、FY2026 − 錨點（應為 0） | C52: =C108+C159+C210 -> 0
A60: 情境 A（順利）：上游 A（HBM 位元 A、顆數係數 A、設備市場 A）；AI 封膠市占不流失；增量營益率 +3pt
A61: 項目 | B61: 單位 | C61: CY2025／FY2025 | D61: CY2026／FY2026 | E61: CY2027／FY2027 | F61: CY2028／FY2028 | G61: CY2029／FY2029 | H61: CY2030 | I61: CY2031 | J61: 說明
A62: A. 日曆年（C＝CY2025 … I＝CY2031）
A63: HBM 出貨位元（同字母情境） | B63: EB | C63: =hsA_25 -> 2.2251147 | D63: =hsA_26 -> 3.782695 | E63: =hsA_27 -> 5.8631772 | F63: =hsA_28 -> 8.501607 | G63: =hsA_29 -> 11.477169 | J63: skhynix 成品 Mkt 頁
A64: DRAM 晶粒容量 | B64: Gb | C64: =den_25 -> 24 | D64: =den_26 -> 24 | E64: =den_27 -> 26 | F64: =den_28 -> 28 | G64: =den_29 -> 30
A65: 平均堆疊層數 | B65: 層 | C65: =stk_25 -> 10 | D65: =stk_26 -> 12 | E65: =stk_27 -> 12.5 | F65: =stk_28 -> 14 | G65: =stk_29 -> 15
A66: HBM 堆疊數（每個堆疊封膠一次） | B66: 十億個 | C66: =C63*8/(C64*C65) -> 0.07417049 | D66: =D63*8/(D64*D65) -> 0.10507486 | E66: =E63*8/(E64*E65) -> 0.14432436 | F66: =F63*8/(F64*F65) -> 0.17350218 | G66: =G63*8/(G64*G65) -> 0.20403857 | H66: =G66*(1+g_tail) -> 0.22444243 | I66: =H66*(1+g_tail) -> 0.24688667 | J66: EB × 8 ÷（晶粒容量 × 層數）；CY2030–31 以 g_tail 外推
A67: HBM 封膠新機需求（下一年堆疊增量＋汰換） | B67: 十億個 | C67: =MAX(0,D66-C66)+dlt*C66 -> 0.03832142 | D67: =MAX(0,E66-D66)+dlt*D66 -> 0.049756988 | E67: =MAX(0,F66-E66)+dlt*E66 -> 0.043610257 | F67: =MAX(0,G66-F66)+dlt*F66 -> 0.047886603 | G67: =MAX(0,H66-G66)+dlt*G66 -> 0.040807714 | H67: =MAX(0,I66-H66)+dlt*H66 -> 0.044888485 | J67: 設備比產能早一年買
A68: CoWoS 片數需求（同字母情境顆數係數） | B68: 千片 | C68: =cw_25 -> 670 | D68: =cw_26 -> 1107.8576 | E68: =cw_27 -> 2096.4286 | F68: =cw_28*um28_A -> 2620.0893 | G68: =cw_29*um29_A -> 3013.3259 | H68: =G68*(1+g_tail) -> 3314.6585 | I68: =H68*(1+g_tail) -> 3646.1243 | J68: 台積電成品；2028–29 × 情境係數
A69: 2.5D 封膠新機需求（下一年片數增量＋汰換） | B69: 千片 | C69: =MAX(0,D68-C68)+dlt*C68 -> 504.85763 | D69: =MAX(0,E68-D68)+dlt*D68 -> 1099.3567 | E69: =MAX(0,F68-E68)+dlt*E68 -> 733.30357 | F69: =MAX(0,G68-F68)+dlt*F68 -> 655.24554 | G69: =MAX(0,H68-G68)+dlt*G68 -> 602.66518 | H69: =MAX(0,I68-H68)+dlt*H68 -> 662.9317
A70: 非 AI 封裝設備指數（SEMI 封裝 × 非 AI 設備 s ÷ 非 AI 設備 A） | B70: US$B | C70: =pk_25*(eqtA_25-eqaA_25)/(eqtA_25-eqaA_25) -> 6.1131387 | D70: =pk_26*(eqtA_26-eqaA_26)/(eqtA_26-eqaA_26) -> 6.7 | E70: =pk_27*(eqtA_27-eqaA_27)/(eqtA_27-eqaA_27) -> 7.5907839 | F70: =pk_28*(eqtA_28-eqaA_28)/(eqtA_28-eqaA_28) -> 8.6 | G70: =pk_29*(eqtA_29-eqaA_29)/(eqtA_29-eqaA_29) -> 9.288 | H70: =G70*(1+g_pk_tail) -> 9.7524 | J70: markets/equipment；CY2030 以 g_pk_tail 外推
A71: 設備總額（同字母情境） | B71: US$B | C71: =eqtA_25 -> 134.68936 | D71: =eqtA_26 -> 178.15705 | E71: =eqtA_27 -> 218.22554 | F71: =eqtA_28 -> 246.02863 | G71: =eqtA_29 -> 260.65569 | H71: =G71*(1+g_pk_tail) -> 273.68847 | J71: 切割與雷射用
A72: B. 校準（只用 FY2025 AI 錨點；FY(t)＝3/4×CY(t)＋1/4×CY(t+1)）
A73: HBM：每單位新機需求的封膠營收 kH | B73: ¥B／十億個 | C73: =ai_25*w_hbm/(0.75*C67+0.25*D67) -> 121.41724 | J73: ＝AI 錨點 × HBM 比重 ÷ FY2025 新機需求
A74: 2.5D：每千片新機需求的封膠營收 kL | B74: ¥B／千片 | C74: =ai_25*(1-w_hbm)/(0.75*C69+0.25*D69) -> 0.0076513155
A75: C. 會計年度驅動推導（C＝FY2025 … G＝FY2029）
A76: AI 封膠市占係數（相對 2025） | B76: x | C76: =1-shl_A/sh*0 -> 1 | D76: =1-shl_A/sh*0.25 -> 1 | E76: =1-shl_A/sh*0.5 -> 1 | F76: =1-shl_A/sh*0.75 -> 1 | G76: =1-shl_A/sh*1 -> 1 | J76: 公司特有：A 最有利、C 最不利
A77: HBM 封膠（驅動推導） | B77: ¥B | C77: =$C$73*(0.75*C67+0.25*D67)*C76 -> 5 | D77: =$C$73*(0.75*D67+0.25*E67)*D76 -> 5.8547766 | E77: =$C$73*(0.75*E67+0.25*F67)*E76 -> 5.4248428 | F77: =$C$73*(0.75*F67+0.25*G67)*F76 -> 5.5993845 | G77: =$C$73*(0.75*G67+0.25*H67)*G76 -> 5.0786291
A78: CoWoS 等 2.5D 封膠（驅動推導） | B78: ¥B | C78: =$C$74*(0.75*C69+0.25*D69)*C76 -> 5 | D78: =$C$74*(0.75*D69+0.25*E69)*D76 -> 7.711328 | E78: =$C$74*(0.75*E69+0.25*F69)*E76 -> 5.4614253 | F78: =$C$74*(0.75*F69+0.25*G69)*F76 -> 4.9129131 | G78: =$C$74*(0.75*G69+0.25*H69)*G76 -> 4.726461
A79: 非 AI 封膠設備與模具（驅動推導） | B79: ¥B | C79: =(seg_mold-ai_25)*(0.75*C70+0.25*D70)/(0.75*C70+0.25*D70) -> 26.46 | D79: =(seg_mold-ai_25)*(0.75*D70+0.25*E70)/(0.75*C70+0.25*D70) -> 29.26179 | E79: =(seg_mold-ai_25)*(0.75*E70+0.25*F70)/(0.75*C70+0.25*D70) -> 33.152228 | F79: =(seg_mold-ai_25)*(0.75*F70+0.25*G70)/(0.75*C70+0.25*D70) -> 37.078679 | G79: =(seg_mold-ai_25)*(0.75*G70+0.25*H70)/(0.75*C70+0.25*D70) -> 39.750525 | J79: FY2025 基期＝封膠 − AI 錨點
A80: 其他半導體：切割等（驅動推導） | B80: ¥B | C80: =seg_osemi*(0.75*C71+0.25*D71)/(0.75*C71+0.25*D71) -> 3.93 | D80: =seg_osemi*(0.75*D71+0.25*E71)/(0.75*C71+0.25*D71) -> 5.0806773 | E80: =seg_osemi*(0.75*E71+0.25*F71)/(0.75*C71+0.25*D71) -> 6.07973 | F80: =seg_osemi*(0.75*F71+0.25*G71)/(0.75*C71+0.25*D71) -> 6.7414719 | G80: =seg_osemi*(0.75*G71+0.25*H71)/(0.75*C71+0.25*D71) -> 7.1256392 | J80: 隨設備總額
A81: 新事業：TSS 售後等（驅動推導） | B81: ¥B | C81: =seg_new -> 9.47 | D81: =C81*(1+g_tss) -> 9.7541 | E81: =D81*(1+g_tss) -> 10.046723 | F81: =E81*(1+g_tss) -> 10.348125 | G81: =F81*(1+g_tss) -> 10.658568
A82: 醫療器材（驅動推導） | B82: ¥B | C82: =seg_med -> 2.48 | D82: =C82*(1+g_med) -> 2.5544 | E82: =D82*(1+g_med) -> 2.631032 | F82: =E82*(1+g_med) -> 2.709963 | G82: =F82*(1+g_med) -> 2.7912618
A83: 雷射（驅動推導） | B83: ¥B | C83: =seg_las*(0.75*C71+0.25*D71)/(0.75*C71+0.25*D71) -> 2 | D83: =seg_las*(0.75*D71+0.25*E71)/(0.75*C71+0.25*D71) -> 2.5855864 | E83: =seg_las*(0.75*E71+0.25*F71)/(0.75*C71+0.25*D71) -> 3.0940102 | F83: =seg_las*(0.75*F71+0.25*G71)/(0.75*C71+0.25*D71) -> 3.4307745 | G83: =seg_las*(0.75*G71+0.25*H71)/(0.75*C71+0.25*D71) -> 3.6262795 | J83: 隨設備總額
A84: 營收（驅動推導，無錨點） | B84: ¥B | C84: =C77+C78+C79+C80+C81+C82+C83+seg_adj -> 54.365 | D84: =D77+D78+D79+D80+D81+D82+D83 -> 62.802659 | E84: =E77+E78+E79+E80+E81+E82+E83 -> 65.889991 | F84: =F77+F78+F79+F80+F81+F82+F83 -> 70.821311 | G84: =G77+G78+G79+G80+G81+G82+G83 -> 73.757365
A85: D. FY2026 錨點（公司全年指引 ×（1＋g_anc）；三情境相同）
A86: FY2026 錨點營收 | B86: ¥B | D86: =g26_rev*(1+g_anc) -> 64
A87: FY2026 錨點營業利益（指引營益率 16.0%） | B87: ¥B | D87: =D86*g26_oi/g26_rev -> 10.24
A88: FY2026 錨點淨利（指引淨利 ÷ 營業利益） | B88: ¥B | D88: =D87*g26_ni/g26_oi -> 7
A89: 錨點 ÷ 驅動推導（FY2026） | B89: x | D89: =D86/D84 -> 1.0190651 | J89: FY2026 各組成同比例縮放成錨點
A90: 非 AI 各項的基期調整（FY2027 起；用情境 A 的 sc） | B90: x | D90: =1+1*(D89-1) -> 1.0190651 | J90: AI 兩項 FY2027 起回到驅動推導；B、C 的 sc 差額來自 AI 驅動較低，不算非 AI
A91: E. 損益（FY2025 實績；FY2026 錨點；FY2027 起驅動推導）
A92: HBM 封膠 | B92: ¥B | C92: =C77*1 -> 5 | D92: =D77*$D$89 -> 5.9663987 | E92: =E77*1 -> 5.4248428 | F92: =F77*1 -> 5.5993845 | G92: =G77*1 -> 5.0786291
A93: CoWoS 等 2.5D 封膠 | B93: ¥B | C93: =C78*1 -> 5 | D93: =D78*$D$89 -> 7.8583456 | E93: =E78*1 -> 5.4614253 | F93: =F78*1 -> 4.9129131 | G93: =G78*1 -> 4.726461
A94: 非 AI 封膠設備與模具 | B94: ¥B | C94: =C79*1 -> 26.46 | D94: =D79*$D$89 -> 29.81967 | E94: =E79*$D$90 -> 33.78428 | F94: =F79*$D$90 -> 37.78559 | G94: =G79*$D$90 -> 40.508375
A95: 其他半導體（切割等） | B95: ¥B | C95: =C80*1 -> 3.93 | D95: =D80*$D$89 -> 5.1775411 | E95: =E80*$D$90 -> 6.1956409 | F95: =F80*$D$90 -> 6.869999 | G95: =G80*$D$90 -> 7.2614905
A96: 新事業（TSS 等） | B96: ¥B | C96: =C81*1 -> 9.47 | D96: =D81*$D$89 -> 9.9400633 | E96: =E81*$D$90 -> 10.238265 | F96: =F81*$D$90 -> 10.545413 | G96: =G81*$D$90 -> 10.861776
A97: 醫療器材 | B97: ¥B | C97: =C82*1 -> 2.48 | D97: =D82*$D$89 -> 2.6031 | E97: =E82*$D$90 -> 2.681193 | F97: =F82*$D$90 -> 2.7616288 | G97: =G82*$D$90 -> 2.8444776
A98: 雷射 | B98: ¥B | C98: =C83*1 -> 2 | D98: =D83*$D$89 -> 2.634881 | E98: =E83*$D$90 -> 3.1529979 | F98: =F83*$D$90 -> 3.4961827 | G98: =G83*$D$90 -> 3.695415
A99: AI 封膠合計 | B99: ¥B | C99: =C92+C93 -> 10 | D99: =D92+D93 -> 13.824744 | E99: =E92+E93 -> 10.886268 | F99: =F92+F93 -> 10.512298 | G99: =G92+G93 -> 9.8050901
A100: 半導體製造裝置事業營收（AI 封膠＋非 AI 封膠＋其他半導體） | B100: ¥B | C100: =C99+C94+C95 -> 40.39 | D100: =D99+D94+D95 -> 48.821956 | E100: =E99+E94+E95 -> 50.866189 | F100: =F99+F94+F95 -> 55.167886 | G100: =G99+G94+G95 -> 57.574955 | J100: 官方分部 半導体製造装置事業
A101: 營收 | B101: ¥B | C101: =C100+C96+C97+C98+seg_adj -> 54.365 | D101: =D100+D96+D97+D98 -> 64 | E101: =E100+E96+E97+E98 -> 66.938645 | F101: =F100+F96+F97+F98 -> 71.971111 | G101: =G100+G96+G97+G98 -> 74.976624 | J101: FY2026＝錨點營收
A102: 檢查：分部合計 − 合併營收（FY2025 實績；差額為公司數字四捨五入） | B102: ¥B | C102: =C100+C96+C97+C98-a25_rev -> -0.025
A103: AI 封膠占營收 | B103: % | C103: =C99/C101 -> 0.18394187 | D103: =D99/D101 -> 0.21601163 | E103: =E99/E101 -> 0.16263054 | F103: =F99/F101 -> 0.14606274 | G103: =G99/G101 -> 0.1307753
A104: 營業利益 | B104: ¥B | C104: =a25_oi -> 6.917 | D104: =D87 -> 10.24 | E104: =$D104+(im+ima_A)*(E101-$D101) -> 11.120186 | F104: =$D104+(im+ima_A)*(F101-$D101) -> 12.627516 | G104: =$D104+(im+ima_A)*(G101-$D101) -> 13.527731 | J104: FY2027 起＝FY2026 營業利益＋增量營益率 ×（營收 − FY2026 營收）
A105: 營業利益率（結果） | B105: % | C105: =C104/C101 -> 0.12723259 | D105: =D104/D101 -> 0.16 | E105: =E104/E101 -> 0.16612506 | F105: =F104/F101 -> 0.17545257 | G105: =G104/G101 -> 0.18042598
A106: 淨利 | B106: ¥B | C106: =a25_ni -> 4.593 | D106: =D88 -> 7 | E106: =E104*nioi -> 7.6016898 | F106: =F104*nioi -> 8.6320911 | G106: =G104*nioi -> 9.2474721
A107: EPS | B107: ¥ | C107: =a25_eps -> 61.22 | D107: =D106*1000/shares -> 93.296149 | E107: =E106*1000/shares -> 101.31548 | F107: =F106*1000/shares -> 115.04869 | G107: =G106*1000/shares -> 123.25051
A108: 檢查：FY2025 營收、營業利益 − 實績；FY2026 營收 − 錨點（應為 0） | B108: ¥B | C108: =ABS(C101-a25_rev)+ABS(C104-a25_oi)+ABS(D101-D86) -> 0
A111: 情境 B（平平）：上游 B（2028 顆數 ×0.8、2029 ×0.85；設備市場 B 2028 見頂）；市占流失 3pt；增量營益率＝迴歸
A112: 項目 | B112: 單位 | C112: CY2025／FY2025 | D112: CY2026／FY2026 | E112: CY2027／FY2027 | F112: CY2028／FY2028 | G112: CY2029／FY2029 | H112: CY2030 | I112: CY2031 | J112: 說明
A113: A. 日曆年（C＝CY2025 … I＝CY2031）
...

Sheet Val
A1: Val — 估值。第 0 節為目標價（DCF 與 Comparable 加權）；第 1–6 節為十年 P/E、循環位置規則值（設備股共用規則：見頂年 25 分位、中段中位數、谷底 75 分位）與目前倍數
A2: P/E 定義（自算）：日曆年底收盤價 ÷ 「當期會計年度」公司公布的基本 EPS（例：2025-12 對 FY2025＝2026年3月期）。價格與 EPS 皆以 2024-10-01 一股分三股調整
A4: 0. 目標價
A5: 0.1 DCF（股東權益現金流，FY2027–FY2032 明確期＋FY2032 後永續）
A6: 項目 | B6: A（順利） | C6: B（平平） | D6: C（不如預期） | E6: 說明
A7: 情境 EPS（FY2027–FY2032） | E7: PL 頁延伸區塊；FY2030 起為收斂法
A8: FY2027 | B8: =PL!E221 -> 101.31548 | C8: =PL!E228 -> 88.658764 | D8: =PL!E235 -> 78.461067
A9: FY2028 | B9: =PL!F221 -> 115.04869 | C9: =PL!F228 -> 96.774768 | D9: =PL!F235 -> 71.346333
A10: FY2029 | B10: =PL!G221 -> 123.25051 | C10: =PL!G228 -> 91.452467 | D10: =PL!G235 -> 72.814037
A11: FY2030 | B11: =PL!H221 -> 129.14681 | C11: =PL!H228 -> 89.939366 | D11: =PL!H235 -> 74.395039
A12: FY2031 | B12: =PL!I221 -> 136.1104 | C12: =PL!I228 -> 90.62088 | D12: =PL!I235 -> 76.161548
A13: FY2032 | B13: =PL!J221 -> 144.27703 | C13: =PL!J228 -> 93.493211 | D13: =PL!J235 -> 78.124788
A14: 股東現金流＝EPS ×（1 − tp_g ÷ tp_roe） | E14: 模型無折舊與資本支出項目，故不用（淨利＋折舊－資本支出）；TOWA 資本支出 FY2025 41.9 億、FY2026 計畫 55.0 億（約營收 9%、指引淨利的約八成），高於再投資率 36.7%，此式可能高估現金流
A15: 再投資率（tp_g ÷ tp_roe，上限 0.8） | B15: =MIN(tp_g/tp_roe,0.8) -> 0.36742192 | E15: ROE 為近三年平均（In 頁 tp_roe）
A16: FY2027 | B16: =B8*(1-$B$15) -> 64.089953 | C16: =C8*(1-$B$15) -> 56.083591 | D16: =D8*(1-$B$15) -> 49.632751
A17: FY2028 | B17: =B9*(1-$B$15) -> 72.777282 | C17: =C9*(1-$B$15) -> 61.217597 | D17: =D9*(1-$B$15) -> 45.132126
A18: FY2029 | B18: =B10*(1-$B$15) -> 77.965568 | C18: =C10*(1-$B$15) -> 57.850826 | D18: =D10*(1-$B$15) -> 46.060564
A19: FY2030 | B19: =B11*(1-$B$15) -> 81.69544 | C19: =C11*(1-$B$15) -> 56.893671 | D19: =D11*(1-$B$15) -> 47.060671
A20: FY2031 | B20: =B12*(1-$B$15) -> 86.100458 | C20: =C12*(1-$B$15) -> 57.324782 | D20: =D12*(1-$B$15) -> 48.178125
A21: FY2032 | B21: =B13*(1-$B$15) -> 91.266485 | C21: =C13*(1-$B$15) -> 59.141756 | D21: =D13*(1-$B$15) -> 49.420028
A22: DCF 情境每股價值（折現率 tp_r） | B22: =MAX(0,SUMPRODUCT(B16:B21,1/(1+tp_r)^{1;2;3;4;5;6})+B21*(1+tp_g)/(tp_r-tp_g)/(1+tp_r)^6) -> 1230.7359 | C22: =MAX(0,SUMPRODUCT(C16:C21,1/(1+tp_r)^{1;2;3;4;5;6})+C21*(1+tp_g)/(tp_r-tp_g)/(1+tp_r)^6) -> 831.53526 | D22: =MAX(0,SUMPRODUCT(D16:D21,1/(1+tp_r)^{1;2;3;4;5;6})+D21*(1+tp_g)/(tp_r-tp_g)/(1+tp_r)^6) -> 690.51633 | E22: Σ 明確期現金流 ÷ (1＋r)^t ＋ 永續價值 ÷ (1＋r)^6；永續價值＝FY2032 現金流 ×(1＋g)÷(r−g)；基準日 2026 年底，t＝1 對 FY2027；負值取 0（股東有限責任）；會計年度 4–3 月，FY2027 仍以 t＝1 折現（略高估）
A23: DCF 情境價值推到 12 個月後（×(1＋tp_r)） | B23: =B22*(1+tp_r) -> 1353.8095 | C23: =C22*(1+tp_r) -> 914.68879 | D23: =D22*(1+tp_r) -> 759.56796
A24: DCF 目標價（情境加權） | B24: =tp_wA*B23+tp_wB*C23+tp_wC*D23 -> 1015.4008 | E24: Σ 權重 × 情境價值 ×(1＋r)；權重見 In 頁 tp_wA／tp_wB／tp_wC
A26: 0.2 Comparable（市場主流同業前瞻 P/E）
A27: 同業與前瞻 P/E | B27: 代號 | C27: 前瞻 12 月 P/E | D27: 日期 | E27: 來源 | F27: 標記
A28: Disco | B28: 6146.T | C28: 26.01 | D28: 2026-10-23 | E28: stockanalysis.com statistics：Forward PE（分析師共識；價格日期如左；本 repo hanmi／disco 同值） | F28: Interested-party
A29: 東京精密（Accretech） | B29: 7729.T | C29: 21.86 | D29: 2026-09-29 | E29: stockanalysis.com statistics：Forward PE（分析師共識；價格日期如左；本 repo hanmi／disco 同值） | F29: Interested-party
A30: ASMPT（封膠與鍵合競爭者） | B30: 0522.HK | C30: 30.26 | D30: 2026-09-23 | E30: stockanalysis.com statistics：Forward PE（分析師共識；價格日期如左；本 repo hanmi／disco 同值） | F30: Interested-party
A31: BE Semiconductor（BESI） | B31: BESI.AS | C31: 25.82 | D31: 2026-10-23 | E31: stockanalysis.com statistics：Forward PE（分析師共識；價格日期如左；本 repo hanmi／disco 同值） | F31: Interested-party
A32: Kulicke & Soffa | B32: KLIC | C32: 12.61 | D32: 2026-10-23 | E32: stockanalysis.com statistics：Forward PE（分析師共識；價格日期如左；本 repo hanmi／disco 同值） | F32: Interested-party
A33: 同業前瞻 P/E 中位數 | B33: =MEDIAN(C28:C32) -> 25.82 | E33: 後段設備同業：日本 Disco、東京精密；封裝設備 ASMPT（封膠直接競爭者）、BESI、Kulicke & Soffa。同業名單不含中國 A 股
A34: 12 個月後的前瞻 EPS（情境加權） | B34: =tp_wA*(5/12*B8+7/12*B9)+tp_wB*(5/12*C8+7/12*C9)+tp_wC*(5/12*D8+7/12*D9) -> 94.356668 | E34: 約 2027-10 時的未來 12 月（2027-11～2028-10）≈ 5／12 × FY2027（2027-04～2028-03）＋7／12 × FY2028（會計年度 4–3 月，依月份調整）
A35: Comparable 目標價 | B35: =B33*B34 -> 2436.2892 | E35: 同業中位數 × 上列 EPS
A37: 0.3 結論
A38: 項目 | B38: 數值 | E38: 說明
A39: 目標價（DCF 與 Comparable 加權） | B39: =tp_w_dcf*B24+(1-tp_w_dcf)*tp_comp_adj -> 1381.6029 | E39: tp_w_dcf × DCF 目標價＋（1 − tp_w_dcf）× Comparable 目標價；tp_w_dcf 見 In 頁
A40: Comparable 目標價（市場主流同業法） | B40: =B35 -> 2436.2892 | E40: 引用 0.2
A41: 市場共識目標價 | B41: =cons_tp -> 3300 | E41: stockanalysis：6 位分析師平均 ¥3,300（中位數 3,300；區間 2,600–4,000），2026-09-17 更新
A42: 上檔空間：加權目標價 | B42: =B39/px-1 -> -0.29796602 | E42: 現價＝In 頁 px（2026-10-23 收盤）
A43: 上檔空間：Comparable 目標價 | B43: =B40/px-1 -> 0.23795181
A44: 與市場共識目標價的差距：EPS 因素 | B44: =B34/cons_feps-1 -> -0.18625625 | E44: 本模型 12 個月後前瞻 EPS ÷ 共識前瞻 EPS − 1；共識前瞻 EPS＝FY2026 共識淨利 8.70 ÷ 股數，早約一年半
A45: 與市場共識目標價的差距：倍數因素 | B45: =(cons_tp/cons_feps)/B33-1 -> 0.10223138 | E45: ="共識目標價 ÷ 共識前瞻 EPS 隱含 "&TEXT(cons_tp/cons_feps,"0.0")&"x，同業中位數 "&TEXT(B33,"0.0")&"x" -> 共識目標價 ÷ 共識前瞻 EPS 隱含 28.5x，同業中位數 25.8x
A46: 價格帶（DCF 不如預期～順利） | B46: =TEXT(D23,"#,##0")&"～"&TEXT(B23,"#,##0") -> 760～1,354 | E46: C 情境價值～A 情境價值（推到 12 個月後）
A47: 歷史倍數檢查：現價隱含 P/E 的十年分位（A／B／C） | B47: =IF(px/B9<MIN(F62:F71),0,IF(px/B9>MAX(F62:F71),1,PERCENTRANK(F62:F71,px/B9))) -> 0.481 | C47: =IF(px/C9<MIN(F62:F71),0,IF(px/C9>MAX(F62:F71),1,PERCENTRANK(F62:F71,px/C9))) -> 0.675 | D47: =IF(px/D9<MIN(F62:F71),0,IF(px/D9>MAX(F62:F71),1,PERCENTRANK(F62:F71,px/D9))) -> 0.777 | E47: 現價 ÷ 各情境 FY2028 EPS 在 2016–2025 年底 P/E（第 1 節當期口徑）的分位；只作檢查，不進目標價
A48: 目標價方法 | B48: DCF：股東現金流＝EPS ×（1 − g／ROE）（模型無折舊與資本支出項目），r 10%、g 4%、ROE 近三年平均 10.9%，FY2027–32 明確期（FY2030 起收斂法）＋永續；Comparable：Disco、東京精密、ASMPT、BESI、Kulicke & Soffa 前瞻 P/E 中位數 × 12 個月後前瞻 EPS。偏誤：再投資率低估 TOWA 的資本支出（偏高估 DCF）；同業中 Disco、ASMPT、BESI 的利潤率與 AI 曝險高於 TOWA（偏高估 Comparable）；十年倍數多來自 AI 前的小型股時期。
A60: 1. 10 年 P/E（年底）
A61: 年底 | B61: 收盤價（分割調整後） | C61: 來源2：株探 年足終值 | D61: 兩者差距 | E61: 當期 FY EPS（調整後） | F61: P/E 當期 | I61: 標記 | J61: 說明
A62: 2016-12 | B62: 549 | C62: 548 | D62: =B62/C62-1 -> 0.0018248175 | E62: =Hist!J6 -> 51.546667 | F62: =B62/E62 -> 10.650543 | I62: Verified | J62: 來源1：Yahoo Finance 月線 12 月 Close（已依 2024 年分割調整）；來源2：株探 年足（取整）；EPS：Hist 頁
A63: 2017-12 | B63: 730 | C63: 729 | D63: =B63/C63-1 -> 0.0013717421 | E63: =Hist!J7 -> 40.34 | F63: =B63/E63 -> 18.096182 | I63: Verified
A64: 2018-12 | B64: 194.33 | C64: 194 | D64: =B64/C64-1 -> 0.0017010309 | E64: =Hist!J8 -> 11.696667 | F64: =B64/E64 -> 16.614135 | I64: Verified
A65: 2019-12 | B65: 394 | C65: 393 | D65: =B65/C65-1 -> 0.0025445293 | E65: =Hist!J9 -> 4.9166667 | F65: =B65/E65 -> 80.135593 | I65: Verified | J65: FY2019 EPS 僅 4.92（淨利 3.7 億），P/E 80 倍為極端值
A66: 2020-12 | B66: 700.33 | C66: 700 | D66: =B66/C66-1 -> 0.00047142857 | E66: =Hist!J10 -> 35.496667 | F66: =B66/E66 -> 19.729458 | I66: Verified
A67: 2021-12 | B67: 1081.67 | C67: 1081 | D67: =B67/C67-1 -> 0.00061979648 | E67: =Hist!J11 -> 108.36 | F67: =B67/E67 -> 9.982189 | I67: Verified
A68: 2022-12 | B68: 563.33 | C68: 563 | D68: =B68/C68-1 -> 0.00058614565 | E68: =Hist!J12 -> 97.9 | F68: =B68/E68 -> 5.7541369 | I68: Verified
A69: 2023-12 | B69: 2376.67 | C69: 2376 | D69: =B69/C69-1 -> 0.00028198653 | E69: =Hist!J13 -> 85.9 | F69: =B69/E69 -> 27.66787 | I69: Verified
A70: 2024-12 | B70: 1546 | C70: 1546 | D70: =B70/C70-1 -> 0 | E70: =Hist!J14 -> 108.28 | F70: =B70/E70 -> 14.277798 | I70: Verified
A71: 2025-12 | B71: 2150 | C71: 2150 | D71: =B71/C71-1 -> 0 | E71: =Hist!J15 -> 61.22 | F71: =B71/E71 -> 35.119242 | I71: Verified
A73: 兩個價格來源可能共用同一資料商（不完全獨立）；10 年都有價格，無缺年。
A75: 2. 分位（10 年）
A76: 統計 | B76: P/E 當期 | C76: 用途
A77: 25 分位 | B77: =PERCENTILE(F62:F71,0.25) -> 11.557357 | C77: 見頂年
A78: 中位數 | B78: =PERCENTILE(F62:F71,0.5) -> 17.355159 | C78: 中段
A79: 75 分位 | B79: =PERCENTILE(F62:F71,0.75) -> 25.683267 | C79: 谷底
A80: 年數 | B80: =COUNT(F62:F71) -> 10
A81: 敏感度：去掉 2019 年（極端值）時 25／50／75 分位 | B81: =PERCENTILE((F62:F64~F66:F71),0.25) -> 10.650543 | C81: =PERCENTILE((F62:F64~F66:F71),0.5) -> 16.614135 | D81: =PERCENTILE((F62:F64~F66:F71),0.75) -> 19.729458
A83: 3. FY2027 的循環位置（設備股共用規則；見頂年度讀設備市場模型，不在本模型另訂）
A84: 循環位置（設備股共用規則）：各情境的見頂年度取自設備市場模型（markets/equipment 的 Mkt 頁「見頂年度」：A 2029、B 2028、C 2027）；會計年度 FY(t) 對照日曆年 t（FY(t) 有 3/4 落在 t 年）：t 早於見頂年＝中段（中位數）、等於＝見頂（25 分位）、晚於＝谷底（75 分位）
A85: 情境 | B85: 設備市場見頂年度 | C85: FY2027 對照日曆年 | D85: 判定 | E85: 倍數
A86: A | B86: =pk_A -> 2029 | C86: 2027 | D86: =IF(C86<pk_A,"中段",IF(C86=pk_A,"見頂","谷底")) -> 中段 | E86: =IF(D86="見頂",pe_peak,IF(D86="谷底",pe_trough,pe_mid)) -> 17.355159
A87: B | B87: =pk_B -> 2028 | C87: 2027 | D87: =IF(C87<pk_B,"中段",IF(C87=pk_B,"見頂","谷底")) -> 中段 | E87: =IF(D87="見頂",pe_peak,IF(D87="谷底",pe_trough,pe_mid)) -> 17.355159
A88: C | B88: =pk_C -> 2027 | C88: 2027 | D88: =IF(C88<pk_C,"中段",IF(C88=pk_C,"見頂","谷底")) -> 見頂 | E88: =IF(D88="見頂",pe_peak,IF(D88="谷底",pe_trough,pe_mid)) -> 11.557357
A90: 4. 隱含股價（FY2027 EPS × 依判定的倍數；其餘倍數僅供參考）
A91: 情境 | B91: EPS 年度 | C91: EPS | D91: 倍數類型 | E91: 倍數 | F91: 隱含股價 | G91: 相對現價 | H91: 備註
A92: A | B92: FY2027 | C92: =PL!E17 -> 101.31548 | D92: ="規則值："&D86 -> 規則值：中段 | E92: =E86 -> 17.355159 | F92: =C92*E92 -> 1758.3463 | G92: =F92/px-1 -> -0.10653135
A93: A | B93: FY2027 | C93: =PL!E17 -> 101.31548 | D93: 參考：25 分位 | E93: =pe_peak -> 11.557357 | F93: =C93*E93 -> 1170.9392 | G93: =F93/px-1 -> -0.40501057
A94: A | B94: FY2027 | C94: =PL!E17 -> 101.31548 | D94: 參考：中位數 | E94: =pe_mid -> 17.355159 | F94: =C94*E94 -> 1758.3463 | G94: =F94/px-1 -> -0.10653135
A95: A | B95: FY2027 | C95: =PL!E17 -> 101.31548 | D95: 參考：75 分位 | E95: =pe_trough -> 25.683267 | F95: =C95*E95 -> 2602.1126 | G95: =F95/px-1 -> 0.32221168
A96: A | B96: FY2028 | C96: =PL!F17 -> 115.04869 | D96: 參考：FY2028 × 中位數 | E96: =pe_mid -> 17.355159 | F96: =C96*E96 -> 1996.6883 | G96: =F96/px-1 -> 0.014577412
A97: B | B97: FY2027 | C97: =PL!E33 -> 88.658764 | D97: ="規則值："&D87 -> 規則值：中段 | E97: =E87 -> 17.355159 | F97: =C97*E97 -> 1538.6869 | G97: =F97/px-1 -> -0.21814689
A98: B | B98: FY2027 | C98: =PL!E33 -> 88.658764 | D98: 參考：25 分位 | E98: =pe_peak -> 11.557357 | F98: =C98*E98 -> 1024.661 | G98: =F98/px-1 -> -0.47933893
A99: B | B99: FY2027 | C99: =PL!E33 -> 88.658764 | D99: 參考：中位數 | E99: =pe_mid -> 17.355159 | F99: =C99*E99 -> 1538.6869 | G99: =F99/px-1 -> -0.21814689
A100: B | B100: FY2027 | C100: =PL!E33 -> 88.658764 | D100: 參考：75 分位 | E100: =pe_trough -> 25.683267 | F100: =C100*E100 -> 2277.0467 | G100: =F100/px-1 -> 0.15703592
A101: B | B101: FY2028 | C101: =PL!F33 -> 96.774768 | D101: 參考：FY2028 × 中位數 | E101: =pe_mid -> 17.355159 | F101: =C101*E101 -> 1679.5415 | G101: =F101/px-1 -> -0.14657446
A102: C | B102: FY2027 | C102: =PL!E49 -> 78.461067 | D102: ="規則值："&D88 -> 規則值：見頂 | E102: =E88 -> 11.557357 | F102: =C102*E102 -> 906.80256 | G102: =F102/px-1 -> -0.53922634
A103: C | B103: FY2027 | C103: =PL!E49 -> 78.461067 | D103: 參考：25 分位 | E103: =pe_peak -> 11.557357 | F103: =C103*E103 -> 906.80256 | G103: =F103/px-1 -> -0.53922634
A104: C | B104: FY2027 | C104: =PL!E49 -> 78.461067 | D104: 參考：中位數 | E104: =pe_mid -> 17.355159 | F104: =C104*E104 -> 1361.7043 | G104: =F104/px-1 -> -0.3080771
A105: C | B105: FY2027 | C105: =PL!E49 -> 78.461067 | D105: 參考：75 分位 | E105: =pe_trough -> 25.683267 | F105: =C105*E105 -> 2015.1365 | G105: =F105/px-1 -> 0.023951475
A106: C | B106: FY2028 | C106: =PL!F49 -> 71.346333 | D106: 參考：FY2028 × 中位數 | E106: =pe_mid -> 17.355159 | F106: =C106*E106 -> 1238.2269 | G106: =F106/px-1 -> -0.37081964
A108: 5. 目前倍數（僅供參考）
A109: 項目 | B109: A／數值 | C109: B | D109: C | E109: 備註
A110: 現價（2026-10-23 收盤） | B110: =px -> 1968 | E110: 株探、kabutore
A111: P/E：現價 ÷ FY2025 EPS 61.22 | B111: =px/a25_eps -> 32.146357 | E111: 上一個會計年度（營益率 12.7% 的低點年）
A112: P/E：現價 ÷ 近 12 月 EPS（FY25 Q2–Q4＋FY26 Q1） | B112: =px/(Q!C7+Q!D7+Q!E7+Q!G7) -> 21.779548 | E112: 近 12 月 EPS ＝ 31.70＋10.37＋26.20＋22.09 ＝ 90.36（Derived；與 stockanalysis TTM 相同）
A113: P/E：現價 ÷ 公司 FY2026 指引 EPS 93.30 | B113: =px/g26_eps -> 21.093248 | E113: 命題中的「約 21 倍」
A114: 遠期 P/E：stockanalysis（共識，2026-09-25） | B114: =sa_fpe -> 17.54 | E114: 參考，不用於估值；當時股價 2,193
A115: 現價 ÷ FY2027 EPS（模型） | B115: =px/PL!E17 -> 19.424474 | C115: =px/PL!E33 -> 22.197467 | D115: =px/PL!E49 -> 25.082504 | E115: A／B／C
A116: 現價 ÷ FY2028 EPS（模型） | B116: =px/PL!F17 -> 17.1058 | C116: =px/PL!F33 -> 20.335879 | D116: =px/PL!F49 -> 27.583758 | E116: A／B／C
A118: 6. 舊法：規則值情境加權（參考，不是目標價）
A119: 項目 | B119: 數值 | E119: 說明
A120: 規則值情境加權價（12 個月；參考） | B120: =tp_wA*F92+tp_wB*F97+tp_wC*F102 -> 1478.2079 | E120: 權重 × 各情境規則值（第 4 節）
...

Sheet Recon
A1: Recon — FY2026 錨定公司全年指引（A 節為恆等式）；A2 節列只用驅動推導的結果；B 節共識只作參考，未用於校準或錨點。差距＝模型 ÷ 對照 − 1
A3: 項目 | B3: 對照值 | C3: 模型 A | D3: 差距 A | E3: 模型 B | F3: 差距 B | G3: 模型 C | H3: 差距 C | I3: 對照來源 | J3: 說明
A4: A. FY2026 錨點（公司指引）：差距為 0 是恆等式，不是獨立檢驗
A5: FY2026 營收 vs 公司指引 | B5: =g26_rev -> 64 | C5: =PL!D5 -> 64 | D5: =C5/B5-1 -> 0 | E5: =PL!D21 -> 64 | F5: =E5/B5-1 -> 0 | G5: =PL!D37 -> 64 | H5: =G5/B5-1 -> 0 | I5: 決算短信 2026-08-06（640.0 億） | J5: g_anc＝0
A6: FY2026 營業利益 vs 公司指引 | B6: =g26_oi -> 10.24 | C6: =PL!D14 -> 10.24 | D6: =C6/B6-1 -> 0 | E6: =PL!D30 -> 10.24 | F6: =E6/B6-1 -> 0 | G6: =PL!D46 -> 10.24 | H6: =G6/B6-1 -> 0 | I6: 同上（102.4 億）
A7: FY2026 EPS vs 公司指引 | B7: =g26_eps -> 93.3 | C7: =PL!D17 -> 93.296149 | D7: =C7/B7-1 -> -4.1273096e-05 | E7: =PL!D33 -> 93.296149 | F7: =E7/B7-1 -> -4.1273096e-05 | G7: =PL!D49 -> 93.296149 | H7: =G7/B7-1 -> -4.1273096e-05 | I7: 同上（93.30） | J7: 股數差異造成的小差
A8: FY2026 營收 vs 第一季 × 4 | B8: =q1_rev*4 -> 64.732 | C8: =PL!D5 -> 64 | D8: =C8/B8-1 -> -0.011308163 | E8: =PL!D21 -> 64 | F8: =E8/B8-1 -> -0.011308163 | G8: =PL!D37 -> 64 | H8: =G8/B8-1 -> -0.011308163 | I8: 第一季 16.2（實績） | J8: 第一季占全年指引 25.3%；第二季起計畫每季接單 150–170 億
A9: FY2026 營業利益率 vs 第一季（百分點） | B9: =q1_oi/q1_rev -> 0.13668665 | C9: =PL!D15 -> 0.16 | D9: =C9-B9 -> 0.023313354 | E9: =PL!D31 -> 0.16 | F9: =E9-B9 -> 0.023313354 | G9: =PL!D47 -> 0.16 | H9: =G9-B9 -> 0.023313354 | I9: 第一季 13.7% | J9: 指引隱含第二至四季營益率約 16.8%
A10: FY2026 半導體＋雷射營收 vs 公司事業計畫（484.3＋32.5） | B10: =g26_semi+g26_las -> 51.68 | C10: =PL!D99+PL!D94+PL!D95+PL!D98 -> 51.456837 | D10: =C10/B10-1 -> -0.0043181746 | E10: =PL!D150+PL!D145+PL!D146+PL!D149 -> 51.188018 | F10: =E10/B10-1 -> -0.0095197673 | G10: =PL!D201+PL!D196+PL!D197+PL!D200 -> 50.991233 | H10: =G10/B10-1 -> -0.013327526 | I10: 決算說明資料 2026-05 | J10: 事業組成經錨點同比例縮放（sc），組成比例來自驅動推導
A11: A2. 只用驅動推導時的 FY2026（對照；說明錨點改變了多少）
A12: 驅動推導營收 vs 錨點營收 | B12: =PL!D86 -> 64 | C12: =PL!D84 -> 62.802659 | D12: =C12/B12-1 -> -0.01870846 | E12: =PL!D135 -> 61.484946 | F12: =E12/B12-1 -> -0.039297713 | G12: =PL!D186 -> 60.554857 | H12: =G12/B12-1 -> -0.053830358 | I12: PL 區塊 C、D 節 | J12: 負＝驅動推導低於公司指引
A13: 驅動推導 雷射 vs 公司計畫 32.5 | B13: =g26_las -> 3.25 | C13: =PL!D83 -> 2.5855864 | D13: =C13/B13-1 -> -0.20443496 | E13: =PL!D134 -> 2.5855864 | F13: =E13/B13-1 -> -0.20443496 | G13: =PL!D185 -> 2.5855864 | H13: =G13/B13-1 -> -0.20443496 | I13: 公司計畫 +61.9%（雷射新機） | J13: 本模型雷射隨設備總額，低估公司計畫
A14: B. FY2026 vs 共識（參考）
A15: 營收 vs 共識（stockanalysis 2026-09-17，6 位） | B15: =cons_rev26 -> 69.3 | C15: =PL!D5 -> 64 | D15: =C15/B15-1 -> -0.076479076 | E15: =PL!D21 -> 64 | F15: =E15/B15-1 -> -0.076479076 | G15: =PL!D37 -> 64 | H15: =G15/B15-1 -> -0.076479076 | I15: stockanalysis（69.3；區間 65.3–74.3） | J15: 共識高於公司指引 8%
A16: 營業利益 vs 共識 | B16: =cons_oi26 -> 12.25 | C16: =PL!D14 -> 10.24 | D16: =C16/B16-1 -> -0.16408163 | E16: =PL!D30 -> 10.24 | F16: =E16/B16-1 -> -0.16408163 | G16: =PL!D46 -> 10.24 | H16: =G16/B16-1 -> -0.16408163 | I16: stockanalysis（12.25）
A17: 淨利 vs 共識 | B17: =cons_ni26 -> 8.7 | C17: =PL!D16 -> 7 | D17: =C17/B17-1 -> -0.1954023 | E17: =PL!D32 -> 7 | F17: =E17/B17-1 -> -0.1954023 | G17: =PL!D48 -> 7 | H17: =G17/B17-1 -> -0.1954023 | I17: stockanalysis（8.70）
A18: EPS vs 共識（淨利 ÷ 股數） | B18: =cons_feps -> 115.95379 | C18: =PL!D17 -> 93.296149 | D18: =C18/B18-1 -> -0.1954023 | E18: =PL!D33 -> 93.296149 | F18: =E18/B18-1 -> -0.1954023 | G18: =PL!D49 -> 93.296149 | H18: =G18/B18-1 -> -0.1954023 | I18: Derived（約 116） | J18: 差距約 −20%，未超過 30%：本模型 FY2026 採公司指引
A19: C. 結構檢查
A20: FY2025 AI 封膠占營收（校準結果；命題的「約兩成」） | C20: =PL!C13 -> 0.18394187
A21: FY2027 AI 封膠占營收（A／B／C） | C21: =PL!E13 -> 0.16263054 | E21: =PL!E29 -> 0.11782888 | G21: =PL!E45 -> 0.068938648
A22: FY2025 受注高 ÷ 營收（book-to-bill） | C22: =ord_25/a25_rev -> 1.0955578 | J22: 1.10：接單領先營收，支持 FY2026 指引
A23: FY2026 錨點營收 ÷（期初受注殘高＋計畫接單下限 4 × 150 億） | C23: =PL!D5/(bl_25+4*15) -> 0.71000666 | J23: 營收不超過可出貨量（＜1 表示指引可由殘高與接單支撐）

Sheet Sens
A1: Sens — 一次動一個輸入（情境 A）：對 FY2027、FY2028 營收與 EPS 的影響。每個案例是一個完整推導區塊（本頁下方，與 PL 同一引擎；校準會跟著重算）
A3: 案例 | B3: 設定 | C3: FY2027 營收 ¥B | D3: FY2027 EPS ¥ | E3: 相對基準 | F3: FY2028 營收 ¥B | G3: FY2028 EPS ¥ | H3: 相對基準 | I3: FY2027 AI 占營收 | J3: FY2026 EPS ¥ | K3: 相對基準
A4: 基準（情境 A） | B4: PL 區塊 A | C4: =PL!E101 -> 66.938645 | D4: =PL!E107 -> 101.31548 | E4: =D4/D$4-1 -> 0 | F4: =PL!F101 -> 71.971111 | G4: =PL!F107 -> 115.04869 | H4: =G4/G$4-1 -> 0 | I4: =PL!E103 -> 0.16263054 | J4: =PL!D107 -> 93.296149 | K4: =J4/J$4-1 -> 0
A5: AI 錨點 7.0（−30%） | B5: ai_25 低 | C5: =E111 -> 68.229073 | D5: =E117 -> 104.83696 | E5: =D5/D$4-1 -> 0.03475756 | F5: =F111 -> 73.898429 | G5: =F117 -> 120.3082 | H5: =G5/G$4-1 -> 0.045715442 | I5: =E113 -> 0.11168828 | J5: =D117 -> 93.296149 | K5: =J5/J$4-1 -> 0
A6: AI 錨點 13.0（+30%） | B6: ai_25 高 | C6: =E171 -> 65.756064 | D6: =E177 -> 98.088311 | E6: =D6/D$4-1 -> -0.031852702 | F6: =F171 -> 70.16406 | G6: =F177 -> 110.11739 | H6: =G6/G$4-1 -> -0.042862745 | I6: =E173 -> 0.21522195 | J6: =D177 -> 93.296149 | K6: =J6/J$4-1 -> 0
A7: HBM 比重 35% | B7: w_hbm 低 | C7: =E231 -> 66.456889 | D7: =E237 -> 100.00081 | E7: =D7/D$4-1 -> -0.012976051 | F7: =F231 -> 71.224913 | G7: =F237 -> 113.01238 | H7: =G7/G$4-1 -> -0.017699599 | I7: =E233 -> 0.16397462 | J7: =D237 -> 93.296149 | K7: =J7/J$4-1 -> 0
A8: HBM 比重 65% | B8: w_hbm 高 | C8: =E291 -> 67.429218 | D8: =E297 -> 102.65422 | E8: =D8/D$4-1 -> 0.013213556 | F8: =F291 -> 72.726977 | G8: =F297 -> 117.11139 | H8: =G8/G$4-1 -> 0.017928928 | I8: =E293 -> 0.16128458 | J8: =D297 -> 93.296149 | K8: =J8/J$4-1 -> 0
A9: 汰換／升級比例 5% | B9: dlt 低 | C9: =E351 -> 66.126044 | D9: =E357 -> 99.097958 | E9: =D9/D$4-1 -> -0.021887326 | F9: =F351 -> 70.76066 | G9: =F357 -> 111.74547 | H9: =G9/G$4-1 -> -0.028711546 | I9: =E353 -> 0.14976539 | J9: =D357 -> 93.296149 | K9: =J9/J$4-1 -> 0
A10: 汰換／升級比例 15% | B10: dlt 高 | C10: =E411 -> 67.639495 | D10: =E417 -> 103.22805 | E10: =D10/D$4-1 -> 0.018877336 | F10: =F411 -> 73.013581 | G10: =F417 -> 117.89351 | H10: =G10/G$4-1 -> 0.024727094 | I10: =E413 -> 0.17341346 | J10: =D417 -> 93.296149 | K10: =J10/J$4-1 -> 0
A11: 晶粒容量 低 | B11: den 低欄 | C11: =E471 -> 67.354251 | D11: =E477 -> 102.44964 | E11: =D11/D$4-1 -> 0.011194306 | F11: =F471 -> 71.056409 | G11: =F477 -> 112.55254 | H11: =G11/G$4-1 -> -0.021696478 | I11: =E473 -> 0.19269253 | J11: =D477 -> 93.296149 | K11: =J11/J$4-1 -> 0
A12: 晶粒容量 高 | B12: den 高欄 | C12: =E531 -> 66.570549 | D12: =E537 -> 100.31098 | E12: =D12/D$4-1 -> -0.0099146303 | F12: =F531 -> 73.359129 | G12: =F537 -> 118.83649 | H12: =G12/G$4-1 -> 0.03292341 | I12: =E533 -> 0.16305868 | J12: =D537 -> 93.296149 | K12: =J12/J$4-1 -> 0
A13: 堆疊層數 低（同位元更多堆疊） | B13: stk 低欄 | C13: =E591 -> 70.250487 | D13: =E597 -> 110.35324 | E13: =D13/D$4-1 -> 0.089204138 | F13: =F591 -> 75.009262 | G13: =F597 -> 123.33957 | H13: =G13/G$4-1 -> 0.072064091 | I13: =E593 -> 0.19616999 | J13: =D597 -> 93.296149 | K13: =J13/J$4-1 -> 0
A14: 堆疊層數 高 | B14: stk 高欄 | C14: =E651 -> 67.851675 | D14: =E657 -> 103.80707 | E14: =D14/D$4-1 -> 0.024592383 | F14: =F651 -> 73.988996 | G14: =F657 -> 120.55535 | H14: =G14/G$4-1 -> 0.047863664 | I14: =E653 -> 0.14592429 | J14: =D657 -> 93.296149 | K14: =J14/J$4-1 -> 0
A15: CY2030–31 需求年增 0% | B15: g_tail 低 | C15: =E711 -> 66.938645 | D15: =E717 -> 101.31548 | E15: =D15/D$4-1 -> 0 | F15: =F711 -> 70.775368 | G15: =F717 -> 111.7856 | H15: =G15/G$4-1 -> -0.02836268 | I15: =E713 -> 0.16263054 | J15: =D717 -> 93.296149 | K15: =J15/J$4-1 -> 0
A16: CY2030–31 需求年增 20% | B16: g_tail 高 | C16: =E771 -> 66.938645 | D16: =E777 -> 101.31548 | E16: =D16/D$4-1 -> 0 | F16: =F771 -> 73.166854 | G16: =F777 -> 118.31178 | H16: =G16/G$4-1 -> 0.02836268 | I16: =E773 -> 0.16263054 | J16: =D777 -> 93.296149 | K16: =J16/J$4-1 -> 0
A17: CoWoS 2025 600 千片 | B17: cw_25 低 | C17: =E831 -> 67.03834 | D17: =E837 -> 101.58754 | E17: =D17/D$4-1 -> 0.0026852909 | F17: =F831 -> 72.152928 | G17: =F837 -> 115.54486 | H17: =G17/G$4-1 -> 0.0043126578 | I17: =E833 -> 0.1568954 | J17: =D837 -> 93.296149 | K17: =J17/J$4-1 -> 0
A18: CY2030 封裝設備年增 0% | B18: g_pk_tail 低 | C18: =E891 -> 66.938645 | D18: =E897 -> 101.31548 | E18: =D18/D$4-1 -> 0 | F18: =F891 -> 71.971111 | G18: =F897 -> 115.04869 | H18: =G18/G$4-1 -> 0 | I18: =E893 -> 0.16263054 | J18: =D897 -> 93.296149 | K18: =J18/J$4-1 -> 0
A19: CY2030 封裝設備年增 10% | B19: g_pk_tail 高 | C19: =E951 -> 66.938645 | D19: =E957 -> 101.31548 | E19: =D19/D$4-1 -> 0 | F19: =F951 -> 71.971111 | G19: =F957 -> 115.04869 | H19: =G19/G$4-1 -> 0 | I19: =E953 -> 0.16263054 | J19: =D957 -> 93.296149 | K19: =J19/J$4-1 -> 0
A20: 新事業年增 0% | B20: g_tss 低 | C20: =E1011 -> 66.602972 | D20: =E1017 -> 100.39946 | E20: =D20/D$4-1 -> -0.0090413193 | F20: =F1011 -> 71.351462 | G20: =F1017 -> 113.35772 | H20: =G20/G$4-1 -> -0.014697888 | I20: =E1013 -> 0.16345019 | J20: =D1017 -> 93.296149 | K20: =J20/J$4-1 -> 0
A21: 新事業年增 6% | B21: g_tss 高 | C21: =E1071 -> 67.288587 | D21: =E1077 -> 102.27045 | E21: =D21/D$4-1 -> 0.0094256661 | F21: =F1071 -> 72.638613 | G21: =F1077 -> 116.87026 | H21: =G21/G$4-1 -> 0.015832964 | I21: =E1073 -> 0.16178476 | J21: =D1077 -> 93.296149 | K21: =J21/J$4-1 -> 0
A22: AI 封膠市占流失 8pt（C 的值） | B22: shl_C | C22: =E1131 -> 66.642864 | D22: =E1137 -> 100.50832 | E22: =D22/D$4-1 -> -0.0079668329 | F22: =F1131 -> 71.410248 | G22: =F1137 -> 113.51814 | H22: =G22/G$4-1 -> -0.013303519 | I22: =E1133 -> 0.15326887 | J22: =D1137 -> 93.296149 | K22: =J22/J$4-1 -> 0
A23: AI 封膠市占流失 12pt | B23: shl_C 高 | C23: =E1191 -> 66.496873 | D23: =E1197 -> 100.10992 | E23: =D23/D$4-1 -> -0.011899069 | F23: =F1191 -> 71.131899 | G23: =F1197 -> 112.75855 | H23: =G23/G$4-1 -> -0.01990586 | I23: =E1193 -> 0.14855255 | J23: =D1197 -> 93.296149 | K23: =J23/J$4-1 -> 0
A24: 增量營益率 −5pt | B24: im 低 | C24: =E1251 -> 66.938645 | D24: =E1257 -> 99.976791 | E24: =D24/D$4-1 -> -0.013213109 | F24: =F1251 -> 71.971111 | G24: =F1257 -> 111.41747 | H24: =G24/G$4-1 -> -0.031562466 | I24: =E1253 -> 0.16263054 | J24: =D1257 -> 93.296149 | K24: =J24/J$4-1 -> 0
A25: 增量營益率 +5pt | B25: im 高 | C25: =E1311 -> 66.938645 | D25: =E1317 -> 102.65418 | E25: =D25/D$4-1 -> 0.013213109 | F25: =F1311 -> 71.971111 | G25: =F1317 -> 118.67991 | H25: =G25/G$4-1 -> 0.031562466 | I25: =E1313 -> 0.16263054 | J25: =D1317 -> 93.296149 | K25: =J25/J$4-1 -> 0
A26: 增量營益率調整取 C 的 −5pt | B26: ima_C | C26: =E1371 -> 66.938645 | D26: =E1377 -> 99.173575 | E26: =D26/D$4-1 -> -0.021140974 | F26: =F1371 -> 71.971111 | G26: =F1377 -> 109.23874 | H26: =G26/G$4-1 -> -0.050499945 | I26: =E1373 -> 0.16263054 | J26: =D1377 -> 93.296149 | K26: =J26/J$4-1 -> 0
A27: 淨利÷營業利益 0.65 | B27: nioi 低 | C27: =E1431 -> 66.938645 | D27: =E1437 -> 96.336551 | E27: =D27/D$4-1 -> -0.049142857 | F27: =F1431 -> 71.971111 | G27: =F1437 -> 109.39487 | H27: =G27/G$4-1 -> -0.049142857 | I27: =E1433 -> 0.16263054 | J27: =D1437 -> 93.296149 | K27: =J27/J$4-1 -> 0
A28: 淨利÷營業利益 0.72 | B28: nioi 高 | C28: =E1491 -> 66.938645 | D28: =E1497 -> 106.71126 | E28: =D28/D$4-1 -> 0.053257143 | F28: =F1491 -> 71.971111 | G28: =F1497 -> 121.17586 | H28: =G28/G$4-1 -> 0.053257143 | I28: =E1493 -> 0.16263054 | J28: =D1497 -> 93.296149 | K28: =J28/J$4-1 -> 0
A29: FY2026 錨點 −5% | B29: g_anc 低 | C29: =E1551 -> 64.136026 | D29: =E1557 -> 97.735098 | E29: =D29/D$4-1 -> -0.035338972 | F29: =F1551 -> 68.89817 | G29: =F1557 -> 110.73062 | H29: =G29/G$4-1 -> -0.037532563 | I29: =E1553 -> 0.16973718 | J29: =D1557 -> 88.631342 | K29: =J29/J$4-1 -> -0.05
A30: FY2026 錨點 +8% | B30: g_anc 高 | C30: =E1611 -> 71.422835 | D30: =E1617 -> 107.0441 | E30: =D30/D$4-1 -> 0.056542355 | F30: =F1611 -> 76.887816 | G30: =F1617 -> 121.95761 | H30: =G30/G$4-1 -> 0.060052101 | I30: =E1613 -> 0.15241999 | J30: =D1617 -> 100.75984 | K30: =J30/J$4-1 -> 0.08
A31: 錨點差額不延續到 FY2027 | B31: 非 AI 基期回到驅動推導 | C31: =E1671 -> 65.889991 | D31: =E1677 -> 98.453788 | E31: =D31/D$4-1 -> -0.028245383 | F31: =F1671 -> 70.821311 | G31: =F1677 -> 111.91098 | H31: =G31/G$4-1 -> -0.027272926 | I31: =E1673 -> 0.16521884 | J31: =D1677 -> 93.296149 | K31: =J31/J$4-1 -> 0
A32: 情境 B | B32: 上游 B；市占流失 3pt；增量營益率＝迴歸 | C32: =PL!E152 -> 62.111502 | D32: =PL!E158 -> 88.658764 | E32: =D32/D$4-1 -> -0.12492384 | F32: =PL!F152 -> 65.41661 | G32: =PL!F158 -> 96.774768 | H32: =G32/G$4-1 -> -0.15883645 | I32: =PL!E154 -> 0.11782888 | J32: =PL!D158 -> 93.296149 | K32: =J32/J$4-1 -> 0
A33: 情境 C | B33: 上游 C；市占流失 8pt；增量營益率 −5pt | C33: =PL!E203 -> 56.582631 | D33: =PL!E209 -> 78.461067 | E33: =D33/D$4-1 -> -0.22557674 | F33: =PL!F203 -> 53.025347 | G33: =PL!F209 -> 71.346333 | H33: =G33/G$4-1 -> -0.37985968 | I33: =PL!E205 -> 0.068938648 | J33: =PL!D209 -> 93.296149 | K33: =J33/J$4-1 -> 0
A35: 讀法：校準在 FY2025 進行，所以改變 AI 錨點、HBM 比重、汰換比例等參數時，FY2025 仍等於實績，只改變之後的路徑形狀；FY2026 錨定公司指引，只受 g_anc 影響。
A70: 案例區塊：AI 錨點 7.0（−30%）（情境 A）
A71: 項目 | B71: 單位 | C71: CY2025／FY2025 | D71: CY2026／FY2026 | E71: CY2027／FY2027 | F71: CY2028／FY2028 | G71: CY2029／FY2029 | H71: CY2030 | I71: CY2031 | J71: 說明
A72: A. 日曆年（C＝CY2025 … I＝CY2031）
A73: HBM 出貨位元（同字母情境） | B73: EB | C73: =hsA_25 -> 2.2251147 | D73: =hsA_26 -> 3.782695 | E73: =hsA_27 -> 5.8631772 | F73: =hsA_28 -> 8.501607 | G73: =hsA_29 -> 11.477169 | J73: skhynix 成品 Mkt 頁
A74: DRAM 晶粒容量 | B74: Gb | C74: =den_25 -> 24 | D74: =den_26 -> 24 | E74: =den_27 -> 26 | F74: =den_28 -> 28 | G74: =den_29 -> 30
A75: 平均堆疊層數 | B75: 層 | C75: =stk_25 -> 10 | D75: =stk_26 -> 12 | E75: =stk_27 -> 12.5 | F75: =stk_28 -> 14 | G75: =stk_29 -> 15
A76: HBM 堆疊數（每個堆疊封膠一次） | B76: 十億個 | C76: =C73*8/(C74*C75) -> 0.07417049 | D76: =D73*8/(D74*D75) -> 0.10507486 | E76: =E73*8/(E74*E75) -> 0.14432436 | F76: =F73*8/(F74*F75) -> 0.17350218 | G76: =G73*8/(G74*G75) -> 0.20403857 | H76: =G76*(1+g_tail) -> 0.22444243 | I76: =H76*(1+g_tail) -> 0.24688667 | J76: EB × 8 ÷（晶粒容量 × 層數）；CY2030–31 以 g_tail 外推
A77: HBM 封膠新機需求（下一年堆疊增量＋汰換） | B77: 十億個 | C77: =MAX(0,D76-C76)+dlt*C76 -> 0.03832142 | D77: =MAX(0,E76-D76)+dlt*D76 -> 0.049756988 | E77: =MAX(0,F76-E76)+dlt*E76 -> 0.043610257 | F77: =MAX(0,G76-F76)+dlt*F76 -> 0.047886603 | G77: =MAX(0,H76-G76)+dlt*G76 -> 0.040807714 | H77: =MAX(0,I76-H76)+dlt*H76 -> 0.044888485 | J77: 設備比產能早一年買
A78: CoWoS 片數需求（同字母情境顆數係數） | B78: 千片 | C78: =cw_25 -> 670 | D78: =cw_26 -> 1107.8576 | E78: =cw_27 -> 2096.4286 | F78: =cw_28*um28_A -> 2620.0893 | G78: =cw_29*um29_A -> 3013.3259 | H78: =G78*(1+g_tail) -> 3314.6585 | I78: =H78*(1+g_tail) -> 3646.1243 | J78: 台積電成品；2028–29 × 情境係數
A79: 2.5D 封膠新機需求（下一年片數增量＋汰換） | B79: 千片 | C79: =MAX(0,D78-C78)+dlt*C78 -> 504.85763 | D79: =MAX(0,E78-D78)+dlt*D78 -> 1099.3567 | E79: =MAX(0,F78-E78)+dlt*E78 -> 733.30357 | F79: =MAX(0,G78-F78)+dlt*F78 -> 655.24554 | G79: =MAX(0,H78-G78)+dlt*G78 -> 602.66518 | H79: =MAX(0,I78-H78)+dlt*H78 -> 662.9317
A80: 非 AI 封裝設備指數（SEMI 封裝 × 非 AI 設備 s ÷ 非 AI 設備 A） | B80: US$B | C80: =pk_25*(eqtA_25-eqaA_25)/(eqtA_25-eqaA_25) -> 6.1131387 | D80: =pk_26*(eqtA_26-eqaA_26)/(eqtA_26-eqaA_26) -> 6.7 | E80: =pk_27*(eqtA_27-eqaA_27)/(eqtA_27-eqaA_27) -> 7.5907839 | F80: =pk_28*(eqtA_28-eqaA_28)/(eqtA_28-eqaA_28) -> 8.6 | G80: =pk_29*(eqtA_29-eqaA_29)/(eqtA_29-eqaA_29) -> 9.288 | H80: =G80*(1+g_pk_tail) -> 9.7524 | J80: markets/equipment；CY2030 以 g_pk_tail 外推
A81: 設備總額（同字母情境） | B81: US$B | C81: =eqtA_25 -> 134.68936 | D81: =eqtA_26 -> 178.15705 | E81: =eqtA_27 -> 218.22554 | F81: =eqtA_28 -> 246.02863 | G81: =eqtA_29 -> 260.65569 | H81: =G81*(1+g_pk_tail) -> 273.68847 | J81: 切割與雷射用
A82: B. 校準（只用 FY2025 AI 錨點；FY(t)＝3/4×CY(t)＋1/4×CY(t+1)）
A83: HBM：每單位新機需求的封膠營收 kH | B83: ¥B／十億個 | C83: =ai_25_lo*w_hbm/(0.75*C77+0.25*D77) -> 84.992071 | J83: ＝AI 錨點 × HBM 比重 ÷ FY2025 新機需求
A84: 2.5D：每千片新機需求的封膠營收 kL | B84: ¥B／千片 | C84: =ai_25_lo*(1-w_hbm)/(0.75*C79+0.25*D79) -> 0.0053559209
A85: C. 會計年度驅動推導（C＝FY2025 … G＝FY2029）
A86: AI 封膠市占係數（相對 2025） | B86: x | C86: =1-shl_A/sh*0 -> 1 | D86: =1-shl_A/sh*0.25 -> 1 | E86: =1-shl_A/sh*0.5 -> 1 | F86: =1-shl_A/sh*0.75 -> 1 | G86: =1-shl_A/sh*1 -> 1 | J86: 公司特有：A 最有利、C 最不利
A87: HBM 封膠（驅動推導） | B87: ¥B | C87: =$C$83*(0.75*C77+0.25*D77)*C86 -> 3.5 | D87: =$C$83*(0.75*D77+0.25*E77)*D86 -> 4.0983436 | E87: =$C$83*(0.75*E77+0.25*F77)*E86 -> 3.7973899 | F87: =$C$83*(0.75*F77+0.25*G77)*F86 -> 3.9195692 | G87: =$C$83*(0.75*G77+0.25*H77)*G86 -> 3.5550404
A88: CoWoS 等 2.5D 封膠（驅動推導） | B88: ¥B | C88: =$C$84*(0.75*C79+0.25*D79)*C86 -> 3.5 | D88: =$C$84*(0.75*D79+0.25*E79)*D86 -> 5.3979296 | E88: =$C$84*(0.75*E79+0.25*F79)*E86 -> 3.8229977 | F88: =$C$84*(0.75*F79+0.25*G79)*F86 -> 3.4390392 | G88: =$C$84*(0.75*G79+0.25*H79)*G86 -> 3.3085227
A89: 非 AI 封膠設備與模具（驅動推導） | B89: ¥B | C89: =(seg_mold-ai_25_lo)*(0.75*C80+0.25*D80)/(0.75*C80+0.25*D80) -> 29.46 | D89: =(seg_mold-ai_25_lo)*(0.75*D80+0.25*E80)/(0.75*C80+0.25*D80) -> 32.579454 | E89: =(seg_mold-ai_25_lo)*(0.75*E80+0.25*F80)/(0.75*C80+0.25*D80) -> 36.910984 | F89: =(seg_mold-ai_25_lo)*(0.75*F80+0.25*G80)/(0.75*C80+0.25*D80) -> 41.282611 | G89: =(seg_mold-ai_25_lo)*(0.75*G80+0.25*H80)/(0.75*C80+0.25*D80) -> 44.257388 | J89: FY2025 基期＝封膠 − AI 錨點
A90: 其他半導體：切割等（驅動推導） | B90: ¥B | C90: =seg_osemi*(0.75*C81+0.25*D81)/(0.75*C81+0.25*D81) -> 3.93 | D90: =seg_osemi*(0.75*D81+0.25*E81)/(0.75*C81+0.25*D81) -> 5.0806773 | E90: =seg_osemi*(0.75*E81+0.25*F81)/(0.75*C81+0.25*D81) -> 6.07973 | F90: =seg_osemi*(0.75*F81+0.25*G81)/(0.75*C81+0.25*D81) -> 6.7414719 | G90: =seg_osemi*(0.75*G81+0.25*H81)/(0.75*C81+0.25*D81) -> 7.1256392 | J90: 隨設備總額
A91: 新事業：TSS 售後等（驅動推導） | B91: ¥B | C91: =seg_new -> 9.47 | D91: =C91*(1+g_tss) -> 9.7541 | E91: =D91*(1+g_tss) -> 10.046723 | F91: =E91*(1+g_tss) -> 10.348125 | G91: =F91*(1+g_tss) -> 10.658568
A92: 醫療器材（驅動推導） | B92: ¥B | C92: =seg_med -> 2.48 | D92: =C92*(1+g_med) -> 2.5544 | E92: =D92*(1+g_med) -> 2.631032 | F92: =E92*(1+g_med) -> 2.709963 | G92: =F92*(1+g_med) -> 2.7912618
A93: 雷射（驅動推導） | B93: ¥B | C93: =seg_las*(0.75*C81+0.25*D81)/(0.75*C81+0.25*D81) -> 2 | D93: =seg_las*(0.75*D81+0.25*E81)/(0.75*C81+0.25*D81) -> 2.5855864 | E93: =seg_las*(0.75*E81+0.25*F81)/(0.75*C81+0.25*D81) -> 3.0940102 | F93: =seg_las*(0.75*F81+0.25*G81)/(0.75*C81+0.25*D81) -> 3.4307745 | G93: =seg_las*(0.75*G81+0.25*H81)/(0.75*C81+0.25*D81) -> 3.6262795 | J93: 隨設備總額
A94: 營收（驅動推導，無錨點） | B94: ¥B | C94: =C87+C88+C89+C90+C91+C92+C93+seg_adj -> 54.365 | D94: =D87+D88+D89+D90+D91+D92+D93 -> 62.05049 | E94: =E87+E88+E89+E90+E91+E92+E93 -> 66.382867 | F94: =F87+F88+F89+F90+F91+F92+F93 -> 71.871554 | G94: =G87+G88+G89+G90+G91+G92+G93 -> 75.3227
A95: D. FY2026 錨點（公司全年指引 ×（1＋g_anc）；三情境相同）
A96: FY2026 錨點營收 | B96: ¥B | D96: =g26_rev*(1+g_anc) -> 64
A97: FY2026 錨點營業利益（指引營益率 16.0%） | B97: ¥B | D97: =D96*g26_oi/g26_rev -> 10.24
A98: FY2026 錨點淨利（指引淨利 ÷ 營業利益） | B98: ¥B | D98: =D97*g26_ni/g26_oi -> 7
A99: 錨點 ÷ 驅動推導（FY2026） | B99: x | D99: =D96/D94 -> 1.0314181 | J99: FY2026 各組成同比例縮放成錨點
A100: 非 AI 各項的基期調整（FY2027 起；用情境 A 的 sc） | B100: x | D100: =1+1*(D99-1) -> 1.0314181 | J100: AI 兩項 FY2027 起回到驅動推導；B、C 的 sc 差額來自 AI 驅動較低，不算非 AI
A101: E. 損益（FY2025 實績；FY2026 錨點；FY2027 起驅動推導）
A102: HBM 封膠 | B102: ¥B | C102: =C87*1 -> 3.5 | D102: =D87*$D$99 -> 4.2271059 | E102: =E87*1 -> 3.7973899 | F102: =F87*1 -> 3.9195692 | G102: =G87*1 -> 3.5550404
A103: CoWoS 等 2.5D 封膠 | B103: ¥B | C103: =C88*1 -> 3.5 | D103: =D88*$D$99 -> 5.5675224 | E103: =E88*1 -> 3.8229977 | F103: =F88*1 -> 3.4390392 | G103: =G88*1 -> 3.3085227
A104: 非 AI 封膠設備與模具 | B104: ¥B | C104: =C89*1 -> 29.46 | D104: =D89*$D$99 -> 33.603039 | E104: =E89*$D$100 -> 38.070657 | F104: =F89*$D$100 -> 42.579633 | G104: =G89*$D$100 -> 45.647871
A105: 其他半導體（切割等） | B105: ¥B | C105: =C90*1 -> 3.93 | D105: =D90*$D$99 -> 5.2403026 | E105: =E90*$D$100 -> 6.2707436 | F105: =F90*$D$100 -> 6.9532762 | G105: =G90*$D$100 -> 7.3495134
A106: 新事業（TSS 等） | B106: ¥B | C106: =C91*1 -> 9.47 | D106: =D91*$D$99 -> 10.060555 | E106: =E91*$D$100 -> 10.362372 | F106: =F91*$D$100 -> 10.673243 | G106: =G91*$D$100 -> 10.993441
A107: 醫療器材 | B107: ¥B | C107: =C92*1 -> 2.48 | D107: =D92*$D$99 -> 2.6346544 | E107: =E92*$D$100 -> 2.7136941 | F107: =F92*$D$100 -> 2.7951049 | G107: =G92*$D$100 -> 2.878958
A108: 雷射 | B108: ¥B | C108: =C93*1 -> 2 | D108: =D93*$D$99 -> 2.6668206 | E108: =E93*$D$100 -> 3.1912181 | F108: =F93*$D$100 -> 3.538563 | G108: =G93*$D$100 -> 3.7402104
A109: AI 封膠合計 | B109: ¥B | C109: =C102+C103 -> 7 | D109: =D102+D103 -> 9.7946283 | E109: =E102+E103 -> 7.6203877 | F109: =F102+F103 -> 7.3586084 | G109: =G102+G103 -> 6.8635631
A110: 半導體製造裝置事業營收（AI 封膠＋非 AI 封膠＋其他半導體） | B110: ¥B | C110: =C109+C104+C105 -> 40.39 | D110: =D109+D104+D105 -> 48.637969 | E110: =E109+E104+E105 -> 51.961789 | F110: =F109+F104+F105 -> 56.891518 | G110: =G109+G104+G105 -> 59.860948 | J110: 官方分部 半導体製造装置事業
A111: 營收 | B111: ¥B | C111: =C110+C106+C107+C108+seg_adj -> 54.365 | D111: =D110+D106+D107+D108 -> 64 | E111: =E110+E106+E107+E108 -> 68.229073 | F111: =F110+F106+F107+F108 -> 73.898429 | G111: =G110+G106+G107+G108 -> 77.473557 | J111: FY2026＝錨點營收
A112: 檢查：分部合計 − 合併營收（FY2025 實績；差額為公司數字四捨五入） | B112: ¥B | C112: =C110+C106+C107+C108-a25_rev -> -0.025
A113: AI 封膠占營收 | B113: % | C113: =C109/C111 -> 0.12875931 | D113: =D109/D111 -> 0.15304107 | E113: =E109/E111 -> 0.11168828 | F113: =F109/F111 -> 0.099577332 | G113: =G109/G111 -> 0.088592332
A114: 營業利益 | B114: ¥B | C114: =a25_oi -> 6.917 | D114: =D97 -> 10.24 | E114: =$D114+(im+ima_A)*(E111-$D111) -> 11.506697 | F114: =$D114+(im+ima_A)*(F111-$D111) -> 13.204789 | G114: =$D114+(im+ima_A)*(G111-$D111) -> 14.275615 | J114: FY2027 起＝FY2026 營業利益＋增量營益率 ×（營收 − FY2026 營收）
A115: 營業利益率（結果） | B115: % | C115: =C114/C111 -> 0.12723259 | D115: =D114/D111 -> 0.16 | E115: =E114/E111 -> 0.168648 | F115: =F114/F111 -> 0.17868835 | G115: =G114/G111 -> 0.18426435
A116: 淨利 | B116: ¥B | C116: =a25_ni -> 4.593 | D116: =D98 -> 7 | E116: =E114*nioi -> 7.8659059 | F116: =F114*nioi -> 9.0267109 | G116: =G114*nioi -> 9.7587211
A117: EPS | B117: ¥ | C117: =a25_eps -> 61.22 | D117: =D116*1000/shares -> 93.296149 | E117: =E116*1000/shares -> 104.83696 | F117: =F116*1000/shares -> 120.3082 | G117: =G116*1000/shares -> 130.06444
A118: 檢查：FY2025 營收、營業利益 − 實績；FY2026 營收 − 錨點（應為 0） | B118: ¥B | C118: =ABS(C111-a25_rev)+ABS(C114-a25_oi)+ABS(D111-D96) -> 0
A130: 案例區塊：AI 錨點 13.0（+30%）（情境 A）
A131: 項目 | B131: 單位 | C131: CY2025／FY2025 | D131: CY2026／FY2026 | E131: CY2027／FY2027 | F131: CY2028／FY2028 | G131: CY2029／FY2029 | H131: CY2030 | I131: CY2031 | J131: 說明
A132: A. 日曆年（C＝CY2025 … I＝CY2031）
A133: HBM 出貨位元（同字母情境） | B133: EB | C133: =hsA_25 -> 2.2251147 | D133: =hsA_26 -> 3.782695 | E133: =hsA_27 -> 5.8631772 | F133: =hsA_28 -> 8.501607 | G133: =hsA_29 -> 11.477169 | J133: skhynix 成品 Mkt 頁
A134: DRAM 晶粒容量 | B134: Gb | C134: =den_25 -> 24 | D134: =den_26 -> 24 | E134: =den_27 -> 26 | F134: =den_28 -> 28 | G134: =den_29 -> 30
A135: 平均堆疊層數 | B135: 層 | C135: =stk_25 -> 10 | D135: =stk_26 -> 12 | E135: =stk_27 -> 12.5 | F135: =stk_28 -> 14 | G135: =stk_29 -> 15
A136: HBM 堆疊數（每個堆疊封膠一次） | B136: 十億個 | C136: =C133*8/(C134*C135) -> 0.07417049 | D136: =D133*8/(D134*D135) -> 0.10507486 | E136: =E133*8/(E134*E135) -> 0.14432436 | F136: =F133*8/(F134*F135) -> 0.17350218 | G136: =G133*8/(G134*G135) -> 0.20403857 | H136: =G136*(1+g_tail) -> 0.22444243 | I136: =H136*(1+g_tail) -> 0.24688667 | J136: EB × 8 ÷（晶粒容量 × 層數）；CY2030–31 以 g_tail 外推
A137: HBM 封膠新機需求（下一年堆疊增量＋汰換） | B137: 十億個 | C137: =MAX(0,D136-C136)+dlt*C136 -> 0.03832142 | D137: =MAX(0,E136-D136)+dlt*D136 -> 0.049756988 | E137: =MAX(0,F136-E136)+dlt*E136 -> 0.043610257 | F137: =MAX(0,G136-F136)+dlt*F136 -> 0.047886603 | G137: =MAX(0,H136-G136)+dlt*G136 -> 0.040807714 | H137: =MAX(0,I136-H136)+dlt*H136 -> 0.044888485 | J137: 設備比產能早一年買
A138: CoWoS 片數需求（同字母情境顆數係數） | B138: 千片 | C138: =cw_25 -> 670 | D138: =cw_26 -> 1107.8576 | E138: =cw_27 -> 2096.4286 | F138: =cw_28*um28_A -> 2620.0893 | G138: =cw_29*um29_A -> 3013.3259 | H138: =G138*(1+g_tail) -> 3314.6585 | I138: =H138*(1+g_tail) -> 3646.1243 | J138: 台積電成品；2028–29 × 情境係數
A139: 2.5D 封膠新機需求（下一年片數增量＋汰換） | B139: 千片 | C139: =MAX(0,D138-C138)+dlt*C138 -> 504.85763 | D139: =MAX(0,E138-D138)+dlt*D138 -> 1099.3567 | E139: =MAX(0,F138-E138)+dlt*E138 -> 733.30357 | F139: =MAX(0,G138-F138)+dlt*F138 -> 655.24554 | G139: =MAX(0,H138-G138)+dlt*G138 -> 602.66518 | H139: =MAX(0,I138-H138)+dlt*H138 -> 662.9317
A140: 非 AI 封裝設備指數（SEMI 封裝 × 非 AI 設備 s ÷ 非 AI 設備 A） | B140: US$B | C140: =pk_25*(eqtA_25-eqaA_25)/(eqtA_25-eqaA_25) -> 6.1131387 | D140: =pk_26*(eqtA_26-eqaA_26)/(eqtA_26-eqaA_26) -> 6.7 | E140: =pk_27*(eqtA_27-eqaA_27)/(eqtA_27-eqaA_27) -> 7.5907839 | F140: =pk_28*(eqtA_28-eqaA_28)/(eqtA_28-eqaA_28) -> 8.6 | G140: =pk_29*(eqtA_29-eqaA_29)/(eqtA_29-eqaA_29) -> 9.288 | H140: =G140*(1+g_pk_tail) -> 9.7524 | J140: markets/equipment；CY2030 以 g_pk_tail 外推
A141: 設備總額（同字母情境） | B141: US$B | C141: =eqtA_25 -> 134.68936 | D141: =eqtA_26 -> 178.15705 | E141: =eqtA_27 -> 218.22554 | F141: =eqtA_28 -> 246.02863 | G141: =eqtA_29 -> 260.65569 | H141: =G141*(1+g_pk_tail) -> 273.68847 | J141: 切割與雷射用
A142: B. 校準（只用 FY2025 AI 錨點；FY(t)＝3/4×CY(t)＋1/4×CY(t+1)）
A143: HBM：每單位新機需求的封膠營收 kH | B143: ¥B／十億個 | C143: =ai_25_hi*w_hbm/(0.75*C137+0.25*D137) -> 157.84242 | J143: ＝AI 錨點 × HBM 比重 ÷ FY2025 新機需求
A144: 2.5D：每千片新機需求的封膠營收 kL | B144: ¥B／千片 | C144: =ai_25_hi*(1-w_hbm)/(0.75*C139+0.25*D139) -> 0.0099467102
A145: C. 會計年度驅動推導（C＝FY2025 … G＝FY2029）
A146: AI 封膠市占係數（相對 2025） | B146: x | C146: =1-shl_A/sh*0 -> 1 | D146: =1-shl_A/sh*0.25 -> 1 | E146: =1-shl_A/sh*0.5 -> 1 | F146: =1-shl_A/sh*0.75 -> 1 | G146: =1-shl_A/sh*1 -> 1 | J146: 公司特有：A 最有利、C 最不利
A147: HBM 封膠（驅動推導） | B147: ¥B | C147: =$C$143*(0.75*C137+0.25*D137)*C146 -> 6.5 | D147: =$C$143*(0.75*D137+0.25*E137)*D146 -> 7.6112096 | E147: =$C$143*(0.75*E137+0.25*F137)*E146 -> 7.0522956 | F147: =$C$143*(0.75*F137+0.25*G137)*F146 -> 7.2791999 | G147: =$C$143*(0.75*G137+0.25*H137)*G146 -> 6.6022179
...

Sheet Sources
A1: 來源（公司原文以網頁擷取工具讀取；說明資料圖表擷取錯位處未採用；版面與頁碼待人工複核）
A2: 公司：2026年3月期 決算短信（JPX iXBRL，2026-04-22 登錄） | B2: https://www2.jpx.co.jp/disc/63150/081220260422508001_tse-acedjpsm-63150-20260422508001-ixbrl.htm
A3: 公司：2027年3月期 第1四半期 決算短信（2026-08-06） | B3: https://www2.jpx.co.jp/disc/63150/081220260702586673_tse-qcedjpsm-63150-20260702586673-ixbrl.htm
A4: 公司：2026年3月期 決算說明資料（2026-05） | B4: https://www.towajapan.co.jp/jp/wp-content/uploads/sites/2/2026/05/2025FY_end_presentation.pdf
A5: 公司：2026年3月期 第2四半期 決算說明會資料（2025-11-07；HBM 台數、TechInsights 市占） | B5: https://www.towajapan.co.jp/jp/wp-content/uploads/sites/2/2025/11/2026_secondquarter_presentation.pdf
A6: 公司：2026年3月期 第3四半期 決算說明資料（記憶體量產投資延後） | B6: https://www.towajapan.co.jp/jp/wp-content/uploads/sites/2/2026/02/2026_thirdquarter_presentation.pdf
A7: 公司：歷年決算短信（2018-05-10、2019-05、2020-05-07） | B7: https://www2.jpx.co.jp/disc/63150/140120200507404921.pdf
A8: EDINET：四半期報告書 第44期第3四半期（FY2020 通期數字） | B8: https://disclosure2dl.edinet-fsa.go.jp/searchdocument/pdf/S100NDD0.pdf
A9: 松井證券：決算情報（年度、季度） | B9: https://finance.matsui.co.jp/stock/6315/settlement/index
A10: kabutan：業績（分割調整 EPS）、日足、年足 | B10: https://s.kabutan.jp/stocks/6315/historical_prices/daily/
A11: kabutore：現在株價、財務分析（毛利） | B11: https://www.kabutore.biz/genzaikabuka/6315.html
A12: the-shashi：配當與 EPS、營業利益歷史、股票分割 | B12: https://the-shashi.com/tse/6315/financials/profit/
A13: tipranks：股票分割公告（三分割，2024-10-01） | B13: https://www.tipranks.com/news/company-announcements/towa-corporation-announces-stock-split-and-dividend-revision
... A19: 36Kr／半導體產業縱橫：CoWoS 2025 67 萬片（2025-12-04） | B19: https://eu.36kr.com/en/p/3580962946874242
A20: 市場層與其他模型：skhynix、tsmc、markets/equipment 成品；markets/memory/market.py（本 repo）
A21: 無法開啟：irbank（權限逾時）、limo.media、kabutan 股價頁（桌面版）；kabuyoho 分析師頁（速率限制）
A22: SemiAnalysis | B22: 未使用
