Workbook

Sheet README
A1: 日月光投控（3711.TW；ADR ASX）個股模型 v0.1（AI 半導體 Project：封測次產業） 2026-10-31
A2: 版本：v0.1（2026-10-31：初版）。全球最大封測代工（OSAT）；封測（ATM：封裝、測試、材料）約占營收六成五、EMS（環旭）約三成五。樣板 amkr/；行業變數讀 Siliconomics 快照 v0.10（20261031_Siliconomics_v0.10.xlsx）。
A3: 模型命題：封測（ATM）＝主流封測＋LEAP 先進封裝；LEAP＝AI 加速器顆數（Siliconomics）× 委外與份額相對值 × 每顆內容（隨封裝面積）＋全流程（CoWoS full process）＋CPO（Siliconomics 同字母滲透率）。公司稱 LEAP 2026 逾 US$4B、2027 翻倍；全流程 2026 約 US$0.3B → 2027 逾 US$1B；CPO 2027 逾 US$0.5B（Interested-party）。EMS 用簡單成長率。
A4: 核心問題：LEAP 占封測營收升到三成以上後，前瞻 P/E 應停在歷史中位（約 12.6 倍）與 2026 窗口（約 24.1 倍）之間的哪裡；資本支出約占營收 42% 的報酬能否撐住毛利率與 EPS。
A6: 會計年度＝日曆年，FY(t)＝CY(t)。預測期 FY2027–FY2029（三年）由驅動因子推導，FY2030–32 為收斂法。金額：十億新台幣；EPS：新台幣（基本）。口徑：歸屬母公司淨利（IFRS）。現價 668.00（2026-10-30 收盤）；其他模型仍用 10-22／10-23 收盤。
A8: 驅動因子 → 推導量（全部唯讀上游，不修改）
A9: LEAP：Siliconomics 加速器顆數 × 情境係數（2028–29）× 委外與份額相對值（Assumed，情境專屬）× 每顆 LEAP 核心內容（FY2026 以公司「逾 US$4B」校準，之後 × 封裝面積指數 ^ 0.5）＋全流程（FY2027 依情境，之後隨顆數 × 1.3）＋CPO（公司 2027 逾 US$0.5B × Siliconomics 同字母 CPO 滲透率 ÷ 情境 A 2027）。
A10: 主流封測：FY2027 +15%（公司稱與 2026 相近，逾 20%；本模型保守）、FY2028–29 +7%（Assumed；行業變數待併入 Siliconomics）。EMS：FY2027 +10%、之後 +5%，毛利率 8.5%。
A11: 毛利：封測毛利＝FY2026 錨點＋現金流通率 50% × 封測營收增量 − 折舊增量；折舊＝前一年 × (1 − 1／8)＋前一年資本支出 ÷ 8；資本支出 FY2026 US$11.5B、FY2027 US$13.0B、之後營收 × 30%。營業費用彈性 0.6；營業外每年 −5；稅率 17%。
A12: 校準：FY2026 ＝ 1Q–3Q26 實績＋4Q26 依公司指引（ATM 季增 12%、ATM 毛利率 +1.5pt、EMS 持平）。不用券商數字（只在 Recon 對帳）。
A13: 估值：Val 第 0 節目標價＝0.5 × DCF 目標價（股東現金流＝EPS ×（1 − g／ROE），FY2027–32 明確期＋永續，r 10%、g 4%，三情境權重 0.3／0.5／0.2）＋0.5 × Comparable 目標價（Amkor、力成、京元電、矽格、南茂前瞻 P/E 中位數 × 12 個月後前瞻 EPS × 相對倍數調整係數）。十年 P/E 規則值保留為參考。本版未做先驗，無 Andy 合理 P/E 對照。
A14: 預估期間：FY2027–FY2029 由驅動因子推導；FY2030 起為收斂法，非驅動因子推導（營收年增由 FY2029 線性收斂到 fade_g、淨利率收斂到 fade_m，FY2032 達到；PL 頁灰底）。
... A17: 已知限制：(1) LEAP 季度與分項金額公司未揭露，FY2026 以全年說法校準、季度拆分用 BofA 占比；(2) 委外與份額相對值是 Assumed；(3) 主流封測與 EMS 只用成長率；(4) 折舊全數歸封測、混合年限 8 年；(5) DCF 未扣資本支出高峰（偏高估）但 ROE 用低谷年（偏低估）；(6) 賣方共識未找到，以 BofA 單一券商對照；(7) 十年 P/E 只有一個來源；(8) 下次更新：4Q26 財報（2027-02 上旬）。
A19: ="投資建議："&Val!B50&"（依上檔空間固定規則）" -> 投資建議：中立（依上檔空間固定規則）
A20: ="重點觀察 1：目標價 NT$"&TEXT(Val!$B$39,"0.00")&"（DCF "&TEXT(Val!$B$24,"0.00")&"、Comparable（相對倍數調整後）"&TEXT(tp_comp_adj,"0.00")&"；DCF 權重 "&TEXT(tp_w_dcf,"0%")&"），比現價 "&TEXT(px,"0.00")&"（2026-10-30）"&IF(Val!$B$42>=0,"高 "&TEXT(Val!$B$42,"0.0%"),"低 "&TEXT(-Val!$B$42,"0.0%"))&"，級距 "&Val!$B$49&"、投資建議 "&Val!$B$50&"。相對倍數調整係數 "&TEXT(rm_factor,"0.00")&"（本公司 10 年前瞻倍數中位數 ÷ 同業的中位數，夾在 0.5–2.0；Val 第 0.5 節），調整前加權上檔空間 "&TEXT((tp_w_dcf*Val!$B$24+(1-tp_w_dcf)*Val!$B$35)/px-1,"+0.0%;−0.0%")&"；Comparable 單獨（市場主流同業法、未調整）為 "&TEXT(Val!$B$43,"+0.0%;−0.0%")&"。" -> 重點觀察 1：目標價 NT$503.84（DCF 336.54、Comparable（相對倍數調整後）671.15；DCF 權重 50%），比現價 668.00（2026-10-30）低 24.6%，級距 0%～−25%、投資建議 中立。相對倍數調整係數 1.12（本公司 10 年前瞻倍數中位數 ÷ 同業的中位數，夾在 0.5–2.0；Val 第 0.5 節），調整前加權上檔空間 −29.9%；Comparable 單獨（市場主流同業法、未調整）為 −10.2%。
A21: 重點觀察 2：核心問題一（LEAP 三成以上後的倍數）：LEAP 占封測營收 FY2026 22.8% → FY2027 35.9%／33.9%／31.8%（A／B／C），現價 ÷ FY2027 EPS 21.6／23.0／24.6 倍，已接近 Bloomberg 2026 窗口前瞻 P/E 24.1 倍、約為十年中位 12.6 倍的兩倍；Comparable 等於 22.1 倍 × 相對倍數係數 1.12＝24.7 倍，若倍數回到十年中位，Comparable 目標價約減半。與 BofA 目標價 900 的差距主要在 EPS（本模型 12 個月後前瞻 EPS 27.2 比 BofA 同口徑 47.2 低 42%），倍數因素只 −14%。
A22: 重點觀察 3：核心問題二（資本支出約占營收四成的報酬）：FY2026 資本支出 US$11.5B（營收 42%）、FY2027 假設 US$13.0B，折舊由 FY2026 NT$97B 升到 FY2028 NT$166B（+71%），營業利益增量 ÷ FY2026 起累計資本支出在 FY2028 只有 12.4%／8.4%／4.7%（A／B／C），股東自由現金流到 FY2029 都為負。加權上檔空間 −24.6% 距放空門檻僅 0.4 個百分點（現金流通率 40% 或折舊年限 6 年即跨線）；下一個檢驗點是 4Q26 財報（2027-02 上旬）的封測毛利率能否達指引 31.6–32.6%。
A24: 相對倍數調整（Val 第 0.5 節）：加權目標價中的 Comparable 使用相對倍數調整後的值（同業前瞻 P/E 中位數 × 本公司 10 年相對同業的前瞻 P/E 比，Bloomberg；Andy 2026-10-27「照建議做」）；「Comparable 目標價（市場主流同業法）」不調整。重點觀察 1 的第一句為公式，其餘重點觀察的數字以調整後撰寫。
A26: v0.1（2026-10-31）：依個股模型原則第 8 節調整 In 頁呈現（數值不變）。In 頁 D／F 欄名改「敏感度低」「敏感度高」（只用於 Sens 頁、不進目標價）；In 頁最後新增「情境驅動對照」一節，把上方各情境專屬輸入三情境並排（只引用上方各列，純展示）；HTML 驅動因子一節分「情境驅動」與「單一參數」兩張表。

Sheet In
A1: In — 輸入（藍字；基準欄 E，低 D、高 F）。金額：十億新台幣（NT$B），LEAP 與資本支出為十億美元（US$B）；顆數：百萬顆；比例：%。每個輸入附兩個來源（找不到者寫「未找到」）；公司原文算一個。【v0.1】基準欄 E 進主模型；D／F＝敏感度低／高，只用於 Sens 頁（一次動一個參數）、不進目標價；情境 A／B／C 的驅動見本頁最後一節「情境驅動對照」。
A2: 標記：Verified／Interested-party／Analogy／Assumed／Derived；Analogy、Assumed 給低／高區間（放 Sens），情境專屬列不給區間。SemiAnalysis 未使用。公司原文＝SEC 6-K（季度新聞稿與簡報）；法說內容經 Motley Fool 逐字稿；公司指引與說法為 Interested-party；券商與媒體為 Interested-party
A3: 鍵 | B3: 項目 | C3: 單位 | D3: 敏感度低 | E3: 基準 | F3: 敏感度高 | G3: 標記 | H3: 來源1 | I3: 來源2／說明
A4: A. AI 加速器顆數、情境係數與封裝面積（讀 Siliconomics 快照 v0.10（20261031_Siliconomics_v0.10.xlsx）；唯讀，不自行重估）
A5: units_26 | B5: AI 加速器顆數 2026（情境 A 基準） | C5: 百萬顆 | E5: 15.2 | G5: Derived | H5: Siliconomics SIF_UnitsPlat_Total_A（八類加速器合計） | I5: NVIDIA、AMD、Google TPU、AWS Trainium、其他 ASIC 合計；與台積電、Amkor、京元電模型同一份
A6: units_27 | B6: AI 加速器顆數 2027（情境 A 基準） | C6: 百萬顆 | E6: 23.7 | G6: Derived | H6: 同上 | I6: 同上
A7: units_28 | B7: AI 加速器顆數 2028（情境 A 基準） | C7: 百萬顆 | E7: 26.5 | G7: Derived | H7: 同上 | I7: 同上
A8: units_29 | B8: AI 加速器顆數 2029（情境 A 基準） | C8: 百萬顆 | E8: 30.15 | G8: Derived | H8: 同上 | I8: 同上
A9: um28_A | B9: 情境 A：2028 顆數 ÷ 基準 | C9: x | E9: 1 | G9: Assumed | H9: Siliconomics um28_A（同字母行業情境） | I9: A＝基準；B＝AI 資本支出消化；C＝明顯下修（與台積電、Amkor、NVIDIA 模型相同）
A10: um29_A | B10: 情境 A：2029 顆數 ÷ 基準 | C10: x | E10: 1 | G10: Assumed | H10: Siliconomics um29_A（同字母行業情境） | I10: 同上
A11: um28_B | B11: 情境 B：2028 顆數 ÷ 基準 | C11: x | E11: 0.8 | G11: Assumed | H11: Siliconomics um28_B（同字母行業情境） | I11: 同上
A12: um29_B | B12: 情境 B：2029 顆數 ÷ 基準 | C12: x | E12: 0.85 | G12: Assumed | H12: Siliconomics um29_B（同字母行業情境） | I12: 同上
A13: um28_C | B13: 情境 C：2028 顆數 ÷ 基準 | C13: x | E13: 0.6 | G13: Assumed | H13: Siliconomics um28_C（同字母行業情境） | I13: 同上
A14: um29_C | B14: 情境 C：2029 顆數 ÷ 基準 | C14: x | E14: 0.6 | G14: Assumed | H14: Siliconomics um29_C（同字母行業情境） | I14: 同上
A15: ar_26 | B15: 封裝面積指數 2026（加速器用 CoWoS 片數 ÷ 顆數，2026＝1） | C15: x | E15: 1 | G15: Derived | H15: Siliconomics 平台別顆數 SIF_UnitsPlat_* ÷ 每片封裝數 cw_pp_*（Blackwell→GB、Rubin→VR、Rubin Ultra→RU、AMD 2026 MI3xx→AMD8／之後→AMDR、TPU 2026→TPU7／之後→TPU8） | I15: 平台對應為本模型假設；每片封裝數下降＝單顆封裝面積變大（Rubin、Rubin Ultra）
A16: ar_27 | B16: 封裝面積指數 2027（加速器用 CoWoS 片數 ÷ 顆數，2026＝1） | C16: x | E16: 1.278156 | G16: Derived | H16: 同上 | I16: 同上
... A30: cpo_C_29 | B30: 情境 C：CPO 占 scale-out 光學金額 2029 | C30: % | E30: 0.05 | G30: Assumed | H30: Siliconomics cpo_C_29（技術替代屬行業情境，同字母） | I30: 同上
A31: fx | B31: 匯率：新台幣 ÷ 美元（2027 起換算 LEAP 與資本支出） | C31: NT$/US$ | D31: 30.5 | E31: 32 | F31: 33 | G31: Assumed | H31: Siliconomics fx_twd（v0.10） | I31: 公司 4Q26 指引假設 31.9（3Q26 新聞稿）
A32: B. 封測（ATM）：LEAP 先進封裝＝顆數 × 委外／份額相對值 × 每顆內容（隨封裝面積）＋全流程（CoWoS full process）＋CPO；主流封測另依成長率
A33: leap25 | B33: LEAP 營收 FY2025 | C33: US$B | E33: 1.6 | G33: Interested-party | H33: 公司 4Q25 新聞稿與簡報（SEC 6-K）：LEAP 2025 年 US$1.6B（占 ATM 13%）、2024 年 US$0.6B（公司 4Q25 簡報） | I33: 2026 年初目標 US$3.2B（同上）
A34: fx25 | B34: FY2025 平均匯率（LEAP 換算新台幣用） | C34: NT$/US$ | E34: 31 | G34: Assumed | H34: 公司：2025 年 ATM 美元營收年增 23%、新台幣年增 20%（4Q25 簡報）；4Q25 指引假設 30.9 | I34: 只影響 FY2025 LEAP／主流拆分
A35: leap26 | B35: LEAP 營收 FY2026（公司：逾 US$4B） | C35: US$B | E35: 4 | G35: Interested-party | H35: 3Q26 法說逐字稿（Motley Fool）：LEAP 2026 由 US$3.7B 上調到 over US$4 billion（3Q26 法說） | I35: 2Q26 法說報導（數位時代）：2Q26 法說時為逾 US$3.5B
A36: lsh_1h | B36: LEAP ÷ ATM 營收 1H26 | C36: % | E36: 0.18 | G36: Interested-party | H36: BofA 報告摘要（科技新報 2026-10-14）：BofA 估 1H26 18%、3Q26 22%、全年約 30%（券商） | I36: 公司未揭露季度 LEAP；只影響 Q 頁季度拆分
A37: lsh_3q | B37: LEAP ÷ ATM 營收 3Q26 | C37: % | E37: 0.22 | G37: Interested-party | H37: 同上（BofA 2026-10-14） | I37: 4Q26＝全年 US$4.0B 減前三季（Derived）
A38: fp26 | B38: 全流程（CoWoS full process）營收 FY2026（含在 LEAP） | C38: US$B | E38: 0.3 | G38: Interested-party | H38: 3Q26 法說逐字稿（Motley Fool）：full process 2026 約 US$300M、on track（3Q26 法說） | I38: 2Q26 法說報導（數位時代）：2Q26 法說同（約 3 億美元）
A39: fp27_A | B39: 情境 A：全流程營收 FY2027 | C39: US$B | E39: 1.2 | G39: Assumed | H39: 3Q26 法說逐字稿（Motley Fool）：full process 2027 over US$1 billion（保守；3Q26 法說） | I39: 公司稱逾 US$1B 為保守數字；取高於公司說法
A40: fp27_B | B40: 情境 B：全流程營收 FY2027 | C40: US$B | E40: 1 | G40: Interested-party | H40: 同上 | I40: 公司說法下緣（逾 US$1B）
A41: fp27_C | B41: 情境 C：全流程營收 FY2027 | C41: US$B | E41: 0.7 | G41: Assumed | H41: 同上 | I41: 全流程導入延後、台積電自製比例維持
A42: fp_g | B42: 全流程 FY2028–29：每年隨顆數成長外再加的滲透成長 | C42: % | D42: 0.1 | E42: 0.3 | F42: 0.5 | G42: Assumed | H42: 台積電 CoWoS 2027 需求接近產能（Siliconomics cw_capend27 200 千片／月）；全流程擴大由 OSAT 補充 | I42: 量化資料：未找到
A43: cpo27 | B43: CPO 營收 FY2027（情境 A 滲透率下；含在 LEAP） | C43: US$B | D43: 0.3 | E43: 0.5 | F43: 0.8 | G43: Interested-party | H43: 3Q26 法說逐字稿（Motley Fool）：CPO 2027 over US$0.5 billion，含在 LEAP；4Q26 量產（3Q26 法說） | I43: 2Q26 法說報導（數位時代）：2Q26 時稱 2026 年底小量（媒體）
A44: rel27_A | B44: 情境 A：日月光委外與份額相對值 2027（2026＝1） | C44: x | E44: 1.1 | G44: Assumed | H44: 台積電 CoWoS 吃緊、委外補充（Siliconomics cw_osat 10%）；日月光直接專案擴大（AMD Venice 等；BofA 2026-10-14） | I44: A＝委外擴大、份額上升；B＝小幅上升（公司 LEAP 翻倍的中性路徑）；C＝台積電自製與 Amkor 分食
A45: rel28_A | B45: 情境 A：日月光委外與份額相對值 2028（2026＝1） | C45: x | E45: 1.15 | G45: Assumed | H45: 同上 | I45: 同上
A46: rel29_A | B46: 情境 A：日月光委外與份額相對值 2029（2026＝1） | C46: x | E46: 1.2 | G46: Assumed | H46: 同上 | I46: 同上
A47: rel27_B | B47: 情境 B：日月光委外與份額相對值 2027（2026＝1） | C47: x | E47: 1.05 | G47: Assumed | H47: 同上 | I47: 同上
A48: rel28_B | B48: 情境 B：日月光委外與份額相對值 2028（2026＝1） | C48: x | E48: 1.08 | G48: Assumed | H48: 同上 | I48: 同上
A49: rel29_B | B49: 情境 B：日月光委外與份額相對值 2029（2026＝1） | C49: x | E49: 1.1 | G49: Assumed | H49: 同上 | I49: 同上
A50: rel27_C | B50: 情境 C：日月光委外與份額相對值 2027（2026＝1） | C50: x | E50: 1 | G50: Assumed | H50: 同上 | I50: 同上
A51: rel28_C | B51: 情境 C：日月光委外與份額相對值 2028（2026＝1） | C51: x | E51: 0.95 | G51: Assumed | H51: 同上 | I51: 同上
A52: rel29_C | B52: 情境 C：日月光委外與份額相對值 2029（2026＝1） | C52: x | E52: 0.92 | G52: Assumed | H52: 同上 | I52: 同上
A53: el | B53: 每顆 LEAP 內容對封裝面積的彈性 | C53: x | D53: 0.3 | E53: 0.5 | F53: 1 | G53: Assumed | H53: 封裝面積大 → oS、測試時間與良率成本上升；後段金額不與面積等比例（與 Amkor 模型同值） | I53: 第二來源：未找到
A54: g_ms26 | B54: 主流封測年增 FY2026（參考；錨點已由 Q 頁實績決定） | C54: % | E54: =Q!G7/Q!B7-1 -> 0.27236329 | G54: Derived | H54: Q 頁：FY2026 錨點 ÷ FY2025（主流＝ATM − LEAP） | I54: 3Q26 法說逐字稿（Motley Fool）：公司稱 2026 年 general market 成長逾 20%
A55: g_ms27 | B55: 主流封測年增 FY2027 | C55: % | D55: 0.05 | E55: 0.15 | F55: 0.22 | G55: Interested-party | H55: 3Q26 法說逐字稿（Motley Fool）：公司預期 2027 年 general market 成長與 2026 相近（逾 20%；3Q26 法說） | I55: 本模型基準取 15%（漲價與成熟製程滿載不必然延續）；行業變數，待併入 Siliconomics（非 AI 封測需求）
A56: g_msL | B56: 主流封測年增 FY2028–29 | C56: % | D56: 0.02 | E56: 0.07 | F56: 0.12 | G56: Assumed | H56: 非 AI 半導體封測長期成長；公司 3Q26：運算 +39%、車用工業 +14%、消費 +14%、通訊 +8%（年增） | I56: 行業變數，待併入 Siliconomics（非 AI 封測需求）
A57: C. EMS（環旭電子；簡單成長率）與沖銷
A58: g_ems27 | B58: EMS 年增 FY2027 | C58: % | D58: 0 | E58: 0.1 | F58: 0.15 | G58: Assumed | H58: 3Q26 法說逐字稿（Motley Fool）：EMS 2027 成長，由 HPC 帶動（約占 EMS mid-teens、快速放量）；通訊、消費較弱（3Q26 法說） | I58: 量化指引：未找到
A59: g_emsL | B59: EMS 年增 FY2028–29 | C59: % | D59: 0 | E59: 0.05 | F59: 0.08 | G59: Assumed | H59: FY2024→FY2025 EMS −5%（公司）；2026 年 2H 含 HPC 新案 | I59: —
A60: ems_gm | B60: EMS 毛利率（FY2027 起） | C60: % | D60: 0.075 | E60: 0.085 | F60: 0.095 | G60: Derived | H60: FY2025 9.1%、1Q26 9.5%、2Q26 8.9%、3Q26 8.3%（公司分部表） | I60: 4Q26 指引 EMS 營業利益率約 2%（3Q26 3.3%）
A61: D. 資本支出與折舊（資本支出約占營收四成：核心問題之二）
A62: capex25 | B62: 資本支出 FY2025 | C62: US$B | E62: 5.5 | G62: Interested-party | H62: 公司 4Q25 新聞稿與簡報（SEC 6-K）：機器設備 US$3.4B＋廠房設施與自動化 US$2.1B（公司 4Q25 簡報） | I62: —
A63: capex26 | B63: 資本支出 FY2026（公司：US$11.5B） | C63: US$B | E63: 11.5 | G63: Interested-party | H63: 3Q26 法說逐字稿（Motley Fool）：2026 資本支出由 US$10.5B 上調到 US$11.5B；前三季 US$8B（設備 4.8、廠房 3.2） | I63: 2Q26 法說報導（數位時代）：2Q26 時為 US$10.5B（廠房 4.0、設備 6.5）
A64: capex27 | B64: 資本支出 FY2027 | C64: US$B | D64: 11.5 | E64: 13 | F64: 15 | G64: Interested-party | H64: 3Q26 法說逐字稿（Motley Fool）：2027 資本支出 even larger than this year；2027 現金流為負（3Q26 法說） | I64: BofA 報告摘要（科技新報 2026-10-14）：BofA 估 2027–28 每年逾 US$13B（券商）
A65: capi | B65: 資本支出 ÷ 合併營收（FY2028–29） | C65: % | D65: 0.22 | E65: 0.3 | F65: 0.38 | G65: Assumed | H65: FY2025 US$5.5B × 31.0 ÷ 645.4＝26%；FY2026 約 42%（Q 頁） | I65: LEAP 成長放緩後回落（Assumed）
A66: life | B66: 新增資本支出的平均折舊年限（廠房與設備混合） | C66: 年 | D66: 6 | E66: 8 | F66: 12 | G66: Assumed | H66: 2026 年資本支出約 35% 為廠房設施（公司）；設備 5–7 年、廠房 20 年以上 | I66: 混合年限：未找到
A67: q4_da | B67: 4Q26 折舊攤提 | C67: NT$B | E67: 27 | G67: Assumed | H67: 1Q26 20.7、2Q26 24.6、3Q26 24.8（EBITDA − 營業利益；公司簡報推得）；3Q26 資本支出 US$3.9B | I67: —
A68: E. 毛利率、營業費用與淨利（FY2027 起）
A69: ft | B69: 封測現金毛利增量 ÷ 封測營收增量（現金流通率） | C69: % | D69: 0.4 | E69: 0.5 | F69: 0.6 | G69: Assumed | H69: FY2025→FY2026 錨點實測見 Q 頁（漲價、LEAP 組合、稼動率滿載） | I69: 3Q26 法說逐字稿（Motley Fool）：公司稱 30% 毛利率由天花板變成基準、2027 逐季改善；BofA 估 AI／HPC 專案毛利率 35–45%
A70: phi | B70: 營業費用成長對營收成長的彈性（FY2027 起） | C70: x | D70: 0.3 | E70: 0.6 | F70: 1 | G70: Assumed | H70: FY2026 實測見 Q 頁 | I70: 公司：增加研發、人才與智慧工廠投入（2Q26 簡報）
A71: nonop_f | B71: 營業外淨額（FY2027 起每年） | C71: NT$B | D71: -8 | E71: -5 | F71: -2 | G71: Assumed | H71: 1Q26 +0.7、2Q26 +4.6（含投資評價利益 4.2、匯兌避險 1.5，淨利息 −1.9；媒體）、3Q26 −0.4（公司） | I71: 淨負債 ÷ 權益 3Q26 66%（2Q26 47%），2027 現金流為負（公司）
A72: tax | B72: 有效稅率（FY2027 起） | C72: % | D72: 0.15 | E72: 0.17 | F72: 0.2 | G72: Interested-party | H72: 3Q26 法說逐字稿（Motley Fool）：2026 全年有效稅率 16–17%（3Q26 法說） | I72: FY2025 18.4%（公司損益推得）
A73: nci | B73: 非控制權益（FY2027 起每年） | C73: NT$B | E73: 3 | G73: Derived | H73: FY2025 1.2、1Q–3Q26 0.4／0.5／0.9（公司） | I73: —
A74: sh_g | B74: 基本股數年變動 | C74: % | E74: 0.005 | G74: Assumed | H74: FY2025 4,339 → 3Q26 4,404 百萬股（淨利 ÷ 基本 EPS 推得）；員工認股與可轉債轉換 | I74: —
A75: F. FY2026 錨點（1Q–3Q26 實績＋4Q26 依公司指引）
A76: q4_atm | B76: 4Q26 封測（ATM）季增 | C76: % | E76: 0.12 | G76: Interested-party | H76: 公司 3Q26 新聞稿與簡報（SEC 6-K，2026-10-29）：4Q26 ATM 營收季增 11–13%（新台幣）；取中點 | I76: —
A77: q4_atmgm | B77: 4Q26 封測毛利率增幅（百分點） | C77: % | E77: 0.015 | G77: Interested-party | H77: 公司 3Q26 新聞稿與簡報（SEC 6-K，2026-10-29）：4Q26 ATM 毛利率季增 100–200 bps；取中點 | I77: —
A78: q4_ems | B78: 4Q26 EMS 季增 | C78: % | E78: 0 | G78: Interested-party | H78: 公司 3Q26 新聞稿與簡報（SEC 6-K，2026-10-29）：4Q26 EMS 營收約持平；營業利益率約 2% | I78: —
A79: q4_emsgm | B79: 4Q26 EMS 毛利率 | C79: % | E79: 0.08 | G79: Assumed | H79: 3Q26 8.3%；營業利益率指引由 3.3% 降到約 2% | I79: —
A80: q4_opx | B80: 4Q26 營業費用季增 | C80: % | E80: 0.08 | G80: Assumed | H80: 3Q26 營業費用 20.8（毛利 − 營業利益）；以合併營業利益率指引 14.5–15.5% 校準 | I80: —
A81: q4_nonop | B81: 4Q26 營業外淨額 | C81: NT$B | E81: -0.5 | G81: Assumed | H81: 3Q26 −0.4；淨負債上升 | I81: —
A82: q4_tax | B82: 4Q26 有效稅率 | C82: % | E82: 0.17 | G82: Interested-party | H82: 公司全年 16–17%（3Q26 法說） | I82: 3Q26 14.8%（公司損益推得）
A83: q4_nci | B83: 4Q26 非控制權益 | C83: NT$B | E83: 0.8 | G83: Derived | H83: 3Q26 0.9（公司） | I83: —
A84: G. 公司指引、券商預估（只作 Recon 對帳，不作校準）
A85: g4_rev_lo | B85: 4Q26 合併營收季增指引下緣 | C85: % | E85: 0.06 | G85: Interested-party | H85: 公司 3Q26 新聞稿與簡報（SEC 6-K，2026-10-29） | I85: 上緣 8%
A86: g4_rev_hi | B86: 4Q26 合併營收季增指引上緣 | C86: % | E86: 0.08 | G86: Interested-party | H86: 公司 3Q26 新聞稿與簡報（SEC 6-K，2026-10-29） | I86: —
A87: g4_gm_lo | B87: 4Q26 合併毛利率指引下緣 | C87: % | E87: 0.23 | G87: Interested-party | H87: 公司 3Q26 新聞稿與簡報（SEC 6-K，2026-10-29） | I87: 上緣 24%
A88: g4_gm_hi | B88: 4Q26 合併毛利率指引上緣 | C88: % | E88: 0.24 | G88: Interested-party | H88: 公司 3Q26 新聞稿與簡報（SEC 6-K，2026-10-29） | I88: —
A89: g4_om_lo | B89: 4Q26 合併營業利益率指引下緣 | C89: % | E89: 0.145 | G89: Interested-party | H89: 公司 3Q26 新聞稿與簡報（SEC 6-K，2026-10-29） | I89: 上緣 15.5%
A90: g4_om_hi | B90: 4Q26 合併營業利益率指引上緣 | C90: % | E90: 0.155 | G90: Interested-party | H90: 公司 3Q26 新聞稿與簡報（SEC 6-K，2026-10-29） | I90: —
A91: bofa_eps26 | B91: BofA EPS FY2026 | C91: NT$ | E91: 19.64 | G91: Interested-party | H91: BofA 報告摘要（科技新報 2026-10-14）：BofA 2026-10-14（3Q26 財報前、月營收後；券商） | I91: 賣方共識：未找到（FactSet、stockanalysis 皆未取得）
A92: bofa_eps27 | B92: BofA EPS FY2027 | C92: NT$ | E92: 34.26 | G92: Interested-party | H92: 同上 | I92: —
A93: bofa_eps28 | B93: BofA EPS FY2028 | C93: NT$ | E93: 49.78 | G93: Interested-party | H93: 同上 | I93: —
A94: bofa_gm28 | B94: BofA 封測毛利率 FY2028（約 30% 中段） | C94: % | E94: 0.3 | G94: Interested-party | H94: 同上：2026 29%、2027 約 30%（低段）、2028 約 30%（中段） | I94: —
A95: H. 價格與市場倍數
A96: px | B96: 股價（2026-10-30 收盤，臺灣證券交易所） | C96: NT$ | E96: 668 | G96: Interested-party | H96: 富邦證券 e 點通（3711 日線）：10-30 收盤 668.00（−15.00） | I96: 第二來源：未找到（Yahoo 奇摩股市頁面為 10-27 盤中 652）；ADR ASX 10-26 收盤 US$39.91（stockanalysis；1 ADS＝2 股）
A97: pe_ttm | B97: 近 12 月 P/E（Yahoo 奇摩股市，10-27 盤中） | C97: x | E97: 47.32 | G97: Interested-party | H97: https://tw.stock.yahoo.com/quote/3711 | I97: stockanalysis ADR 49.19（10-26）
A98: fpe | B98: 前瞻 P/E（stockanalysis，ADR，10-26） | C98: x | E98: 26.99 | G98: Interested-party | H98: stockanalysis.com | I98: 3Q26 財報前
A99: cons_feps | B99: 共識前瞻 12 月 EPS（BofA：2／12 × FY2027＋10／12 × FY2028；單一券商） | C99: NT$ | E99: =2/12*bofa_eps27+10/12*bofa_eps28 -> 47.193333 | G99: Derived | H99: BofA 2026-10-14（單一券商；與本模型 12 個月後前瞻 EPS 同口徑） | I99: 賣方共識前瞻 EPS：未找到
A100: cons_tp | B100: 市場共識目標價（以 BofA 單一券商代替） | C100: NT$ | E100: 900 | G100: Interested-party | H100: BofA 報告摘要（科技新報 2026-10-14）：BofA 目標價 800 → 900（20 倍目標 P/E；2026-10-14） | I100: 賣方平均目標價：未找到；經濟日報 2026-10-16：法人目標價調升近一成（無數字）
A101: I. 目標價與收斂法參數（黃底；Assumed，Andy 可改）
A102: tp_wA | B102: 目標價情境權重 A（A 順利／B 平平／C 不如預期） | C102: % | E102: 0.3 | G102: Assumed | H102: Andy 可改（工作單 2026-10-25 預設 A 0.3／B 0.5／C 0.2） | I102: 三者合計應為 100%（Val 頁第 0 節列示）
A103: tp_wB | B103: 目標價情境權重 B（A 順利／B 平平／C 不如預期） | C103: % | E103: 0.5 | G103: Assumed | H103: Andy 可改（工作單 2026-10-25 預設 A 0.3／B 0.5／C 0.2） | I103: 三者合計應為 100%（Val 頁第 0 節列示）
A104: tp_wC | B104: 目標價情境權重 C（A 順利／B 平平／C 不如預期） | C104: % | E104: 0.2 | G104: Assumed | H104: Andy 可改（工作單 2026-10-25 預設 A 0.3／B 0.5／C 0.2） | I104: 三者合計應為 100%（Val 頁第 0 節列示）
A105: tp_r | B105: 折現率／要求報酬 | C105: % | E105: 0.1 | G105: Assumed | H105: Andy 可改（工作單預設 10%；各市場同一值） | I105: DCF 與 Sens
A106: tp_g | B106: 長期成長率 | C106: % | E106: 0.04 | G106: Assumed | H106: Andy 可改（工作單預設 4%） | I106: 成熟倍數與 FY2032 收斂目標（情境 B）
A107: tp_roe | B107: ROE（近三年平均，FY2023–25） | C107: % | E107: =AVERAGE(0.1172,0.0973,0.1015) -> 0.10533333 | G107: Derived | H107: macrotrends ROE：2023 11.72%、2024 9.73%、2025（近 12 月至 2025-03）10.15% | I107: 單一來源；2026 年 ROE 隨獲利倍增明顯上升（未納入）
A108: tp_w_dcf | B108: 目標價中 DCF 的權重；其餘為 Comparable | C108: % | E108: 0.5 | G108: Assumed | H108: Andy 可改（工作單 2026-10-25 11:53 定 DCF／Comparable 各半） | I108: —
A109: fade_gA | B109: 情境 A：FY2032 營收年增收斂目標（tp_g＋2pt） | C109: % | E109: =tp_g+0.02 -> 0.06 | G109: Assumed | H109: 工作單 2026-10-25 11:20 收斂法 | I109: FY2030 起由 FY2029 年增線性收斂
A110: fade_gB | B110: 情境 B：FY2032 營收年增收斂目標（＝tp_g） | C110: % | E110: =tp_g -> 0.04 | G110: Assumed | H110: 同上 | I110: —
A111: fade_gC | B111: 情境 C：FY2032 營收年增收斂目標（tp_g−2pt） | C111: % | E111: =tp_g-0.02 -> 0.02 | G111: Assumed | H111: 同上 | I111: —
A112: fade_mA | B112: 情境 A：FY2032 淨利率收斂目標（＝情境 A FY2029 淨利率） | C112: % | E112: =PL!G16 -> 0.13180583 | G112: Derived | H112: PL 頁情境 A FY2029（公式於建置時連結） | I112: —
A113: fade_mB | B113: 情境 B：FY2032 淨利率收斂目標（情境 B FY2029 與其 × 0.8 的中點） | C113: % | E113: =(PL!G32+PL!G32*0.8)/2 -> 0.09826477 | G113: Assumed | H113: 十年平均淨利率未找到（FY2016–2023 本專案未逐年核對）：工作單規則以 FY2029 × 0.8 代替 | I113: PL 頁情境 B FY2029（公式於建置時連結）
...

Sheet Q
A1: Q — 實績與 FY2026 錨點（十億新台幣；EPS 為新台幣、基本；股數為百萬股）。藍字＝輸入（SEC 6-K 公司新聞稿與簡報，原單位百萬元 ÷ 1,000）；黑字＝公式。分部營收取分部表（含部門間交易），差額列「沖銷及其他」
A2: v0.1（2026-10-31）：FY2026 錨點＝1Q、2Q、3Q26 實績（3Q26：2026-10-29 新聞稿）＋4Q26 依公司指引（ATM 季增 12%、ATM 毛利率 +1.5pt、EMS 持平；合併營收季增約 7%，指引 6–8%）
A3: 項目 | B3: FY2025A | C3: 1Q26（實績） | D3: 2Q26（實績） | E3: 3Q26（實績） | F3: 4Q26（模型） | G3: FY2026 錨點 | H3: 標記 | I3: 來源1（公司） | J3: 來源2／說明
A4: 營收 | B4: 645.388 | C4: 173.662 | D4: 191.064 | E4: 244.161 | F4: =F5+F8+F9 -> 262.28035 | G4: =SUM(C4:F4) -> 871.16735 | H4: Verified | I4: FY2025：4Q25 新聞稿（SEC 6-K 2026-02-05）；1Q、2Q26：2Q26 新聞稿（6-K 2026-07-30）；3Q26：6-K 2026-10-29 | J4: 9M26 608.887（公司月營收）＝三季合計
A5: 封測（ATM；分部表） | B5: 389.228 | C5: 112.434 | D5: 126.148 | E5: 151.485 | F5: =E5*(1+q4_atm) -> 169.6632 | G5: =SUM(C5:F5) -> 559.7302 | H5: Verified／Interested-party（4Q） | I5: FY2025：4Q25 新聞稿（SEC 6-K 2026-02-05）；1Q、2Q26：2Q26 新聞稿（6-K 2026-07-30）；3Q26：6-K 2026-10-29 | J5: ATM＝封裝、測試、材料；合併表口徑 FY2025 385.3、3Q26 150.6（含沖銷）
A6: LEAP 先進封裝（命題子列） | B6: =leap25*fx25 -> 49.6 | C6: =C5*lsh_1h -> 20.23812 | D6: =D5*lsh_1h -> 22.70664 | E6: =E5*lsh_3q -> 33.3267 | F6: =leap26*31.9-SUM(C6:E6) -> 51.32854 | G6: =SUM(C6:F6) -> 127.6 | H6: Interested-party／Derived | I6: FY2025：4Q25 新聞稿（SEC 6-K 2026-02-05）；1Q、2Q26：2Q26 新聞稿（6-K 2026-07-30）；3Q26：6-K 2026-10-29 | J6: FY2025 US$1.6B；1H26、3Q26 依 BofA 占比；4Q26＝全年 US$4.0B × 31.9 − 前三季（Derived）
A7: 主流封測（ATM − LEAP） | B7: =B5-B6 -> 339.628 | C7: =C5-C6 -> 92.19588 | D7: =D5-D6 -> 103.44136 | E7: =E5-E6 -> 118.1583 | F7: =F5-F6 -> 118.33466 | G7: =SUM(C7:F7) -> 432.1302 | H7: Derived | I7: — | J7: —
A8: EMS（環旭；分部表） | B8: 259.079 | C8: 61.875 | D8: 65.789 | E8: 93.469 | F8: =E8*(1+q4_ems) -> 93.469 | G8: =SUM(C8:F8) -> 314.602 | H8: Verified／Interested-party（4Q） | I8: FY2025：4Q25 新聞稿（SEC 6-K 2026-02-05）；1Q、2Q26：2Q26 新聞稿（6-K 2026-07-30）；3Q26：6-K 2026-10-29 | J8: 1Q26 簡報另一頁 61.361（口徑不同）；取分部頁
A9: 沖銷及其他（合併 − 分部合計） | B9: =B4-B5-B8 -> -2.919 | C9: =C4-C5-C8 -> -0.647 | D9: =D4-D5-D8 -> -0.873 | E9: =E4-E5-E8 -> -0.793 | F9: =E9/(E5+E8)*(F5+F8) -> -0.85184906 | G9: =SUM(C9:F9) -> -3.1648491 | H9: Derived | I9: — | J9: 4Q26 依 3Q26 比例
A10: 封測毛利 | B10: 91.38 | C10: 29.198 | D10: 34.487 | E10: 46.412 | F10: =F5*F11 -> 54.526388 | G10: =SUM(C10:F10) -> 164.62339 | H10: Verified | I10: FY2025：4Q25 新聞稿（SEC 6-K 2026-02-05）；1Q、2Q26：2Q26 新聞稿（6-K 2026-07-30）；3Q26：6-K 2026-10-29 | J10: —
A11: 封測毛利率 | B11: =B10/B5 -> 0.23477242 | C11: =C10/C5 -> 0.25969013 | D11: =D10/D5 -> 0.27338523 | E11: =E10/E5 -> 0.30638017 | F11: =E11+q4_atmgm -> 0.32138017 | G11: =G10/G5 -> 0.29411203 | H11: Derived | I11: — | J11: 公司：FY2025 23.5%、3Q26 30.6%
A12: EMS 毛利 | B12: 23.695 | C12: 5.862 | D12: 5.873 | E12: 7.793 | F12: =F8*q4_emsgm -> 7.47752 | G12: =SUM(C12:F12) -> 27.00552 | H12: Verified | I12: FY2025：4Q25 新聞稿（SEC 6-K 2026-02-05）；1Q、2Q26：2Q26 新聞稿（6-K 2026-07-30）；3Q26：6-K 2026-10-29 | J12: —
A13: 沖銷及其他毛利（合併毛利 − 分部毛利） | B13: =B14-B10-B12 -> -0.882 | C13: =C14-C10-C12 -> -0.242 | D13: =D14-D10-D12 -> -0.213 | E13: =E14-E10-E12 -> -0.238 | F13: =E13/E9*F9 -> -0.25566214 | G13: =SUM(C13:F13) -> -0.94866214 | H13: Derived | I13: — | J13: —
A14: 毛利 | B14: 114.193 | C14: 34.818 | D14: 40.147 | E14: 53.967 | F14: =F10+F12+F13 -> 61.748246 | G14: =SUM(C14:F14) -> 190.68025 | H14: Verified | I14: FY2025：4Q25 新聞稿（SEC 6-K 2026-02-05）；1Q、2Q26：2Q26 新聞稿（6-K 2026-07-30）；3Q26：6-K 2026-10-29 | J14: —
A15: 毛利率 | B15: =B14/B4 -> 0.17693697 | C15: =C14/C4 -> 0.20049291 | D15: =D14/D4 -> 0.21012331 | E15: =E14/E4 -> 0.22103039 | F15: =F14/F4 -> 0.23542841 | G15: =G14/G4 -> 0.21887901 | H15: Derived | I15: — | J15: 公司：FY2025 17.7%、3Q26 22.1%
A16: 營業費用（毛利 − 營業利益） | B16: =B14-B17 -> 63.437 | C16: =C14-C17 -> 17.325 | D16: =D14-D17 -> 19.017 | E16: =E14-E17 -> 20.825 | F16: =E16*(1+q4_opx) -> 22.491 | G16: =SUM(C16:F16) -> 79.658 | H16: Derived | I16: — | J16: —
A17: 營業利益 | B17: 50.756 | C17: 17.493 | D17: 21.13 | E17: 33.142 | F17: =F14-F16 -> 39.257246 | G17: =SUM(C17:F17) -> 111.02225 | H17: Verified | I17: FY2025：4Q25 新聞稿（SEC 6-K 2026-02-05）；1Q、2Q26：2Q26 新聞稿（6-K 2026-07-30）；3Q26：6-K 2026-10-29 | J17: —
A18: 營業外淨額 | B18: 0.545 | C18: 0.668 | D18: 4.566 | E18: =E19-E17 -> -0.432 | F18: =q4_nonop -> -0.5 | G18: =SUM(C18:F18) -> 4.302 | H18: Verified／Derived | I18: FY2025：4Q25 新聞稿（SEC 6-K 2026-02-05）；1Q、2Q26：2Q26 新聞稿（6-K 2026-07-30）；3Q26：6-K 2026-10-29 | J18: 2Q26 含投資評價利益 4.2、匯兌避險 1.5（風傳媒）
A19: 稅前利益 | B19: 51.301 | C19: 18.161 | D19: 25.696 | E19: 32.71 | F19: =F17+F18 -> 38.757246 | G19: =SUM(C19:F19) -> 115.32425 | H19: Verified | I19: FY2025：4Q25 新聞稿（SEC 6-K 2026-02-05）；1Q、2Q26：2Q26 新聞稿（6-K 2026-07-30）；3Q26：6-K 2026-10-29 | J19: —
A20: 所得稅 | B20: 9.461 | C20: 3.629 | D20: 4.171 | E20: 4.831 | F20: =F19*q4_tax -> 6.5887318 | G20: =SUM(C20:F20) -> 19.219732 | H20: Verified | I20: FY2025：4Q25 新聞稿（SEC 6-K 2026-02-05）；1Q、2Q26：2Q26 新聞稿（6-K 2026-07-30）；3Q26：6-K 2026-10-29 | J20: —
A21: 非控制權益 | B21: 1.182 | C21: 0.4 | D21: 0.46 | E21: 0.883 | F21: =q4_nci -> 0.8 | G21: =SUM(C21:F21) -> 2.543 | H21: Verified | I21: FY2025：4Q25 新聞稿（SEC 6-K 2026-02-05）；1Q、2Q26：2Q26 新聞稿（6-K 2026-07-30）；3Q26：6-K 2026-10-29 | J21: —
A22: 歸屬母公司淨利 | B22: 40.658 | C22: 14.132 | D22: 21.065 | E22: 26.996 | F22: =F19-F20-F21 -> 31.368514 | G22: =SUM(C22:F22) -> 93.561514 | H22: Verified | I22: FY2025：4Q25 新聞稿（SEC 6-K 2026-02-05）；1Q、2Q26：2Q26 新聞稿（6-K 2026-07-30）；3Q26：6-K 2026-10-29 | J22: —
A23: 基本股數（百萬股） | B23: =B22/B25*1000 -> 4339.1676 | C23: =C22/C25*1000 -> 4375.2322 | D23: =D22/D25*1000 -> 4388.5417 | E23: =E22/E25*1000 -> 4403.9152 | F23: =E23 -> 4403.9152 | G23: =AVERAGE(C23:F23) -> 4392.9011 | H23: Derived | I23: 淨利 ÷ 公司揭露基本 EPS | J23: —
A24: EPS（基本） | B24: =B22/B23*1000 -> 9.37 | C24: =C22/C23*1000 -> 3.23 | D24: =D22/D23*1000 -> 4.8 | E24: =E22/E23*1000 -> 6.13 | F24: =F22/F23*1000 -> 7.1228697 | G24: =SUM(C24:F24) -> 21.28287 | H24: Derived | I24: 淨利 ÷ 股數；FY2026＝四季加總 | J24: —
A25: 公司揭露 EPS（基本） | B25: 9.37 | C25: 3.23 | D25: 4.8 | E25: 6.13 | H25: Verified | I25: FY2025：4Q25 新聞稿（SEC 6-K 2026-02-05）；1Q、2Q26：2Q26 新聞稿（6-K 2026-07-30）；3Q26：6-K 2026-10-29 | J25: 稀釋 EPS：FY2025 8.89、3Q26 5.84（可轉債）
A26: 折舊攤提（EBITDA − 營業利益） | B26: =126.011-B17 -> 75.255 | C26: =38.147-C17 -> 20.654 | D26: =45.779-D17 -> 24.649 | E26: =57.963-E17 -> 24.821 | F26: =q4_da -> 27 | G26: =SUM(C26:F26) -> 97.124 | H26: Derived | I26: FY2025：4Q25 新聞稿（SEC 6-K 2026-02-05）；1Q、2Q26：2Q26 新聞稿（6-K 2026-07-30）；3Q26：6-K 2026-10-29 | J26: EBITDA：FY2025 126.0、1Q26 38.1、2Q26 45.8、3Q26 58.0（公司簡報）
A27: 資本支出（US$B） | B27: =capex25 -> 5.5 | G27: =capex26 -> 11.5 | H27: Interested-party | I27: FY2025：4Q25 新聞稿（SEC 6-K 2026-02-05）；1Q、2Q26：2Q26 新聞稿（6-K 2026-07-30）；3Q26：6-K 2026-10-29 | J27: 公司：2026 前三季 US$8.0B；全年 US$11.5B
A28: 資本支出 ÷ 營收 | B28: =B27*fx25/B4 -> 0.26418217 | G28: =G27*31.9/G4 -> 0.42110164 | H28: Derived | I28: — | J28: FY2026 以 31.9 換算
A29: LEAP ÷ 封測營收 | B29: =B6/B5 -> 0.12743174 | C29: =C6/C5 -> 0.18 | D29: =D6/D5 -> 0.18 | E29: =E6/E5 -> 0.22 | F29: =F6/F5 -> 0.30253196 | G29: =G6/G5 -> 0.22796697 | H29: Derived | I29: — | J29: —
A31: FY2026 錨點的檢查（參考；校準未使用券商數字）
A32: FY2026 營收年增 | B32: =G4/B4-1 -> 0.34983506
A33: FY2026 封測年增（公司 2Q26：逾 35%） | B33: =G5/B5-1 -> 0.43805225
A34: FY2026 主流封測年增（公司：逾 20%） | B34: =G7/B7-1 -> 0.27236329
A35: 封測現金毛利增量 ÷ 封測營收增量（In 頁 ft 的對照；折舊增量全數歸封測） | B35: =((G10+G26)-(B10+B26))/(G5-B5) -> 0.55783672
A36: 營業費用彈性（In 頁 phi 的對照） | B36: =(G16/B16-1)/(G4/B4-1) -> 0.73092304
A37: 4Q26 合併營收季增（指引 6–8%） | B37: =F4/E4-1 -> 0.074210668
A38: 4Q26 合併毛利率（指引 23–24%） | B38: =F15 -> 0.23542841
A39: 4Q26 合併營業利益率（指引 14.5–15.5%） | B39: =F17/F4 -> 0.14967666
A40: FY2025 分部毛利 + 沖銷 − 合併毛利（應為 0） | B40: =B10+B12+B13-B14 -> 0
A41: 3Q26 EPS 自算 − 公司 6.13（應約 0） | B41: =E24-E25 -> 0
A43: 檢查：分部合計 − 合併營收 | B43: =ROUND(B5+B8+B9-B4,6) -> 0 | C43: =ROUND(C5+C8+C9-C4,6) -> 0 | D43: =ROUND(D5+D8+D9-D4,6) -> 0 | E43: =ROUND(E5+E8+E9-E4,6) -> 0 | F43: =ROUND(F5+F8+F9-F4,6) -> 0 | G43: =ROUND(G5+G8+G9-G4,6) -> 0
A44: 分部原則第 3 條：官方分部＝封測（ATM）、EMS（分部表口徑），沖銷及其他為合併與分部合計的差額；分部宣告見 segments.json
A45: 檢查：LEAP＋主流 − 封測（命題子列合計） | B45: =ROUND(B6+B7-B5,6) -> 0 | C45: =ROUND(C6+C7-C5,6) -> 0 | D45: =ROUND(D6+D7-D5,6) -> 0 | E45: =ROUND(E6+E7-E5,6) -> 0 | F45: =ROUND(F6+F7-F5,6) -> 0 | G45: =ROUND(G6+G7-G5,6) -> 0

Sheet Units
A1: Units — AI 加速器顆數（Siliconomics）→ 日月光 LEAP 先進封裝營收（情境 A）。部署 GW 讀 Siliconomics SIF_DeployGW_A，只作 Recon
A3: 項目 | B3: 單位 | C3: CY2026 | D3: CY2027 | E3: CY2028 | F3: CY2029 | G3: 說明
A4: AI 加速器顆數（情境 A） | B4: 百萬顆 | C4: =PL!D73 -> 15.2 | D4: =PL!E73 -> 23.7 | E4: =PL!F73 -> 26.5 | F4: =PL!G73 -> 30.15 | G4: Siliconomics（台積電、Amkor、京元電模型同一份）
A5: 封裝面積指數（2026＝1） | B5: x | C5: =PL!D74 -> 1 | D5: =PL!E74 -> 1.278156 | E5: =PL!F74 -> 1.428615 | F5: =PL!G74 -> 1.431796 | G5: Siliconomics 平台顆數 ÷ CoWoS 每片封裝數
A6: 委外與份額相對值 | B6: x | C6: =PL!D75 -> 1 | D6: =PL!E75 -> 1.1 | E6: =PL!F75 -> 1.15 | F6: =PL!G75 -> 1.2 | G6: Assumed（情境 A）
A7: 每顆 LEAP 核心內容 | B7: US$／顆 | C7: =PL!D76 -> 236.84211 | D7: =PL!E76 -> 267.76317 | E7: =PL!F76 -> 283.08478 | F7: =PL!G76 -> 283.39976 | G7: FY2026 校準；之後隨封裝面積
A8: LEAP 核心 | B8: US$B | C8: =PL!D77 -> 3.6 | D8: =PL!E77 -> 6.9805859 | E8: =PL!F77 -> 8.6270086 | F8: =PL!G77 -> 10.253403 | G8: 顆數 × 相對值 × 每顆內容
A9: 全流程 | B9: US$B | C9: =PL!D78 -> 0.3 | D9: =PL!E78 -> 1.2 | E9: =PL!F78 -> 1.7443038 | F9: =PL!G78 -> 2.5799241 | G9: 公司 2026 約 0.3、2027 逾 1.0
A10: CPO | B10: US$B | C10: =PL!D79 -> 0.1 | D10: =PL!E79 -> 0.5 | E10: =PL!F79 -> 1.1181435 | F10: =PL!G79 -> 2.035443 | G10: 公司 2027 逾 0.5；Siliconomics 滲透率
A11: LEAP 合計 | B11: US$B | C11: =PL!D80 -> 4 | D11: =PL!E80 -> 8.6805859 | E11: =PL!F80 -> 11.489456 | F11: =PL!G80 -> 14.868771 | G11: 公司：2026 逾 4.0、2027 翻倍
A12: 每顆加速器的日月光 LEAP 營收 | B12: US$／顆 | C12: =PL!D80/PL!D73*1000 -> 263.15789 | D12: =PL!E80/PL!E73*1000 -> 366.26945 | E12: =PL!F80/PL!F73*1000 -> 433.56437 | F12: =PL!G80/PL!G73*1000 -> 493.15989 | G12: 含全流程與 CPO
A13: 部署 GW（Siliconomics SIF_DeployGW_A） | B13: GW | C13: 23.399538 | D13: 41.646766 | E13: 52.792138 | F13: 60.138592 | G13: Siliconomics 推導值（唯讀）
A14: 每 GW 的日月光 LEAP 營收 | B14: US$B／GW | C14: =C11/C13 -> 0.17094355 | D14: =D11/D13 -> 0.20843361 | E14: =E11/E13 -> 0.21763574 | F14: =F11/F13 -> 0.24724175 | G14: 對照 Amkor 投資人日：OSAT 先進封裝可服務市場約 US$0.5B／GW
A16: 讀法：LEAP FY2026 以公司「逾 US$4B」校準，不是公司揭露的拆分；委外與份額相對值是 Assumed，只有相對變化影響 FY2027 起的營收。每顆內容隨封裝面積上升（彈性 0.5），全流程與 CPO 另計；CPO 依 Siliconomics 同字母滲透率縮放。

Sheet PL
A1: PL — 日月光投控損益（十億新台幣；EPS 新台幣、基本；歸屬母公司）。FY2025A 實績、FY2026 錨點（1Q–3Q26 實績＋4Q26 依指引；三情境相同），FY2027 起為模型。FY(t)＝CY(t)。三情境各一個完整推導區塊（本頁下方），頂端為摘要
A2: 灰底＝FY2030–FY2032 收斂法（上游只到 2029）：營收年增線性收斂到 fade_g、淨利率線性收斂到 fade_m（In 頁 I 節），非驅動因子推導
A3: 情境／項目 | B3: 單位 | C3: FY2025A | D3: FY2026（錨點） | E3: FY2027 | F3: FY2028 | G3: FY2029 | H3: FY2030（收斂） | I3: FY2031（收斂） | J3: FY2032（收斂） | K3: 說明
A4: 情境 A
A5: 營收 | B5: NT$B | C5: =C88 -> 645.388 | D5: =D88 -> 871.16735 | E5: =E88 -> 1116.7337 | F5: =F88 -> 1258.1932 | G5: =G88 -> 1421.1292 | H5: =H88 -> 1572.2425 | I5: =I88 -> 1703.0007 | J5: =J88 -> 1805.1807
A6: 營收年增 | B6: % | D6: =D89 -> 0.34983506 | E6: =E89 -> 0.28188197 | F6: =F89 -> 0.12667256 | G6: =G89 -> 0.12949994 | H6: =H89 -> 0.10633329 | I6: =I89 -> 0.083166646 | J6: =J89 -> 0.06
A7: 封測（ATM） | B7: NT$B | C7: =C85 -> 389.228 | D7: =D85 -> 559.7302 | E7: =E85 -> 774.72848 | F7: =F85 -> 899.3988 | G7: =G85 -> 1044.7584
A8: LEAP 先進封裝 | B8: NT$B | C8: =C83 -> 49.6 | D8: =D83 -> 127.6 | E8: =E83 -> 277.77875 | F8: =F83 -> 367.66259 | G8: =G83 -> 475.80066
A9: LEAP ÷ 封測營收 | B9: % | C9: =C90 -> 0.12743174 | D9: =D90 -> 0.22796697 | E9: =E90 -> 0.35854981 | F9: =F90 -> 0.40878706 | G9: =G90 -> 0.45541692
A10: EMS | B10: NT$B | C10: =C86 -> 259.079 | D10: =D86 -> 314.602 | E10: =E86 -> 346.0622 | F10: =F86 -> 363.36531 | G10: =G86 -> 381.53358
A11: 封測毛利率 | B11: % | C11: =C98 -> 0.23477242 | D11: =D98 -> 0.29411203 | E11: =E98 -> 0.30772946 | F11: =F98 -> 0.29474901 | G11: =G98 -> 0.29806418
A12: 毛利率 | B12: % | C12: =C102 -> 0.17693697 | D12: =D102 -> 0.21887901 | E12: =E102 -> 0.2387373 | F12: =F102 -> 0.23415548 | G12: =G102 -> 0.24085627
A13: 營業利益率 | B13: % | C13: =C105 -> 0.078644164 | D13: =D105 -> 0.12744078 | E13: =E105 -> 0.15534187 | F13: =F105 -> 0.15451053 | G13: =G105 -> 0.16486391
A14: 資本支出 ÷ 營收 | B14: % | C14: =C95 -> 0.26418217 | D14: =D95 -> 0.42110164 | E14: =E95 -> 0.37251495 | F14: =F95 -> 0.3 | G14: =G95 -> 0.3
A15: 歸屬母公司淨利 | B15: NT$B | C15: =C110 -> 40.658 | D15: =D110 -> 93.561514 | E15: =E110 -> 136.83466 | F15: =F110 -> 154.2054 | G15: =G110 -> 187.31312 | H15: =H110 -> 207.23074 | I15: =I110 -> 224.46542 | J15: =J110 -> 237.93335
A16: 淨利率 | B16: % | C16: =C114 -> 0.062997763 | D16: =D114 -> 0.10739787 | E16: =E114 -> 0.12253115 | F16: =F114 -> 0.12256099 | G16: =G114 -> 0.13180583 | H16: =H114 -> 0.13180583 | I16: =I114 -> 0.13180583 | J16: =J114 -> 0.13180583
A17: EPS | B17: NT$ | C17: =C112 -> 9.37 | D17: =D112 -> 21.28287 | E17: =E112 -> 30.994073 | F17: =F112 -> 34.754901 | G17: =G112 -> 42.006702 | H17: =H112 -> 46.242202 | I17: =I112 -> 49.838817 | J17: =J112 -> 52.566314
A18: EPS 年增 | B18: % | D18: =D113 -> 1.2713842 | E18: =E113 -> 0.45629199 | F18: =F113 -> 0.12134023 | G18: =G113 -> 0.20865551 | H18: =H113 -> 0.10082915 | I18: =I113 -> 0.077777757 | J18: =J113 -> 0.054726368
A20: 情境 B
A21: 營收 | B21: NT$B | C21: =C137 -> 645.388 | D21: =D137 -> 871.16735 | E21: =E137 -> 1093.8632 | F21: =F137 -> 1149.8566 | G21: =G137 -> 1287.6254 | H21: =H137 -> 1407.644 | I21: =I137 -> 1501.3996 | J21: =J137 -> 1561.4556
A22: 營收年增 | B22: % | D22: =D138 -> 0.34983506 | E22: =E138 -> 0.25562927 | F22: =F138 -> 0.051188617 | G22: =G138 -> 0.11981389 | H22: =H138 -> 0.093209263 | I22: =I138 -> 0.066604631 | J22: =J138 -> 0.04
A23: 封測（ATM） | B23: NT$B | C23: =C134 -> 389.228 | D23: =D134 -> 559.7302 | E23: =E134 -> 751.7749 | F23: =F134 -> 790.66855 | G23: =G134 -> 910.76958
A24: LEAP 先進封裝 | B24: NT$B | C24: =C132 -> 49.6 | D24: =D132 -> 127.6 | E24: =E132 -> 254.82517 | F24: =F132 -> 258.93234 | G24: =G132 -> 341.81183
A25: LEAP ÷ 封測營收 | B25: % | C25: =C139 -> 0.12743174 | D25: =D139 -> 0.22796697 | E25: =E139 -> 0.33896472 | F25: =F139 -> 0.32748532 | G25: =G139 -> 0.37530001
A26: EMS | B26: NT$B | C26: =C135 -> 259.079 | D26: =D135 -> 314.602 | E26: =E135 -> 346.0622 | F26: =F135 -> 363.36531 | G26: =G135 -> 381.53358
A27: 封測毛利率 | B27: % | C27: =C147 -> 0.23477242 | D27: =D147 -> 0.29411203 | E27: =E147 -> 0.30185896 | F27: =F147 -> 0.26652354 | G27: =G147 -> 0.27281683
A28: 毛利率 | B28: % | C28: =C151 -> 0.17693697 | D28: =D151 -> 0.21887901 | E28: =E151 -> 0.23325961 | F28: =F151 -> 0.20903972 | G28: =G151 -> 0.21706738
A29: 營業利益率 | B29: % | C29: =C154 -> 0.078644164 | D29: =D154 -> 0.12744078 | E29: =E154 -> 0.14926762 | F29: =F154 -> 0.12668375 | G29: =G154 -> 0.13823607
A30: 資本支出 ÷ 營收 | B30: % | C30: =C144 -> 0.26418217 | D30: =D144 -> 0.42110164 | E30: =E144 -> 0.38030349 | F30: =F144 -> 0.3 | G30: =G144 -> 0.3
A31: 歸屬母公司淨利 | B31: NT$B | C31: =C159 -> 40.658 | D31: =D159 -> 93.561514 | E31: =E159 -> 128.37104 | F31: =F159 -> 113.75456 | G31: =G159 -> 140.5869 | H31: =H159 -> 148.56787 | I31: =I159 -> 152.99893 | J31: =J159 -> 153.43607
A32: 淨利率 | B32: % | C32: =C163 -> 0.062997763 | D32: =D163 -> 0.10739787 | E32: =E163 -> 0.11735566 | F32: =F163 -> 0.098929349 | G32: =G163 -> 0.10918308 | H32: =H163 -> 0.10554364 | I32: =I163 -> 0.10190421 | J32: =J163 -> 0.09826477
A33: EPS | B33: NT$ | C33: =C161 -> 9.37 | D33: =D161 -> 21.28287 | E33: =E161 -> 29.076998 | F33: =F161 -> 25.638067 | G33: =G161 -> 31.527915 | H33: =H161 -> 33.151962 | I33: =I161 -> 33.97087 | J33: =J161 -> 33.898437
A34: EPS 年增 | B34: % | D34: =D162 -> 1.2713842 | E34: =E162 -> 0.36621603 | F34: =F162 -> -0.11826981 | G34: =G162 -> 0.22973058 | H34: =H162 -> 0.051511397 | I34: =I162 -> 0.024701653 | J34: =J162 -> -0.0021321962
A36: 情境 C
A37: 營收 | B37: NT$B | C37: =C186 -> 645.388 | D37: =D186 -> 871.16735 | E37: =E186 -> 1070.9927 | F37: =F186 -> 1054.0807 | G37: =G186 -> 1138.3936 | H37: =H186 -> 1206.6874 | I37: =I186 -> 1254.9497 | J37: =J186 -> 1280.0487
A38: 營收年增 | B38: % | D38: =D187 -> 0.34983506 | E38: =E187 -> 0.22937657 | F38: =F187 -> -0.01579095 | G38: =G187 -> 0.079987082 | H38: =H187 -> 0.059991388 | I38: =I187 -> 0.039995694 | J38: =J187 -> 0.02
A39: 封測（ATM） | B39: NT$B | C39: =C183 -> 389.228 | D39: =D183 -> 559.7302 | E39: =E183 -> 728.82132 | F39: =F183 -> 694.54478 | G39: =G183 -> 760.99565
A40: LEAP 先進封裝 | B40: NT$B | C40: =C181 -> 49.6 | D40: =D181 -> 127.6 | E40: =E181 -> 231.87159 | F40: =F181 -> 162.80857 | G40: =G181 -> 192.03791
A41: LEAP ÷ 封測營收 | B41: % | C41: =C188 -> 0.12743174 | D41: =D188 -> 0.22796697 | E41: =E188 -> 0.318146 | F41: =F188 -> 0.23441047 | G41: =G188 -> 0.25235086
A42: EMS | B42: NT$B | C42: =C184 -> 259.079 | D42: =D184 -> 314.602 | E42: =E184 -> 346.0622 | F42: =F184 -> 363.36531 | G42: =G184 -> 381.53358
A43: 封測毛利率 | B43: % | C43: =C196 -> 0.23477242 | D43: =D196 -> 0.29411203 | E43: =E196 -> 0.29561868 | F43: =F196 -> 0.23421081 | G43: =G196 -> 0.2328238
A44: 毛利率 | B44: % | C44: =C200 -> 0.17693697 | D44: =D200 -> 0.21887901 | E44: =E200 -> 0.22754797 | F44: =F200 -> 0.1825364 | G44: =G200 -> 0.1830374
A45: 營業利益率 | B45: % | C45: =C203 -> 0.078644164 | D45: =D203 -> 0.12744078 | E45: =E203 -> 0.14293394 | F45: =F203 -> 0.097379342 | G45: =G203 -> 0.10040314
A46: 資本支出 ÷ 營收 | B46: % | C46: =C193 -> 0.26418217 | D46: =D193 -> 0.42110164 | E46: =E193 -> 0.38842467 | F46: =F193 -> 0.3 | G46: =G193 -> 0.3
A47: 歸屬母公司淨利 | B47: NT$B | C47: =C208 -> 40.658 | D47: =D208 -> 93.561514 | E47: =E208 -> 119.90741 | F47: =F208 -> 78.045921 | G47: =G208 -> 87.717577 | H47: =H208 -> 86.781218 | I47: =I208 -> 83.805515 | J47: =J208 -> 78.906115
A48: 淨利率 | B48: % | C48: =C212 -> 0.062997763 | D48: =D212 -> 0.10739787 | E48: =E212 -> 0.11195912 | F48: =F212 -> 0.074041692 | G48: =G212 -> 0.077053823 | H48: =H212 -> 0.071916901 | I48: =I212 -> 0.06677998 | J48: =J212 -> 0.061643058
A49: EPS | B49: NT$ | C49: =C210 -> 9.37 | D49: =D210 -> 21.28287 | E49: =E210 -> 27.159923 | F49: =F210 -> 17.590034 | G49: =G210 -> 19.671479 | H49: =H210 -> 19.364669 | I49: =I210 -> 18.607622 | J49: =J210 -> 17.432628
A50: EPS 年增 | B50: % | D50: =D211 -> 1.2713842 | E50: =E211 -> 0.27614007 | F50: =F211 -> -0.35235333 | G50: =G211 -> 0.11833097 | H50: =H211 -> -0.015596721 | I50: =I211 -> -0.039094242 | J50: =J211 -> -0.063145809
A52: 核對（應為 0）：FY2026 模型 − 錨點
A53: 三情境：營收差（NT$B） | D53: =ABS(D88-a26_rev)+ABS(D137-a26_rev)+ABS(D186-a26_rev) -> 0
A54: 三情境：EPS 差（NT$） | D54: =ABS(D112-a26_eps)+ABS(D161-a26_eps)+ABS(D210-a26_eps) -> 0
A55: 情境 A：LEAP＋主流 − Q 頁封測（NT$B） | D55: =D83+D84-a26_atm -> 0
A70: 情境 A：顆數基準；委外與份額相對值 1.10／1.15／1.20；全流程 FY2027 US$1.2B；CPO 依 Siliconomics 情境 A 滲透率
A71: 項目 | B71: 單位 | C71: FY2025A | D71: FY2026（錨點） | E71: FY2027 | F71: FY2028 | G71: FY2029 | H71: FY2030（收斂） | I71: FY2031（收斂） | J71: FY2032（收斂） | K71: 說明
A72: A. AI 加速器 → LEAP 先進封裝（D 欄＝FY2026 校準年；美元）
A73: AI 加速器顆數（含情境係數） | B73: 百萬顆 | D73: =units_26 -> 15.2 | E73: =units_27*1 -> 23.7 | F73: =units_28*um28_A*1 -> 26.5 | G73: =units_29*um29_A*1 -> 30.15
A74: 封裝面積指數（2026＝1） | B74: x | D74: =ar_26 -> 1 | E74: =ar_27 -> 1.278156 | F74: =ar_28 -> 1.428615 | G74: =ar_29 -> 1.431796
A75: 委外與份額相對值（2026＝1） | B75: x | D75: =1 -> 1 | E75: =rel27_A -> 1.1 | F75: =rel28_A -> 1.15 | G75: =rel29_A -> 1.2
A76: 每顆加速器 LEAP 核心內容（不含全流程、CPO） | B76: US$／顆 | D76: =D77*1000/D73 -> 236.84211 | E76: =$D76*E74^el -> 267.76317 | F76: =$D76*F74^el -> 283.08478 | G76: =$D76*G74^el -> 283.39976 | K76: FY2026 校準（Derived）；之後 × 封裝面積指數 ^ 彈性
A77: LEAP 核心（2.5D oS、先進測試等） | B77: US$B | D77: =leap26-D78-D79 -> 3.6 | E77: =E73*E75*E76/1000 -> 6.9805859 | F77: =F73*F75*F76/1000 -> 8.6270086 | G77: =G73*G75*G76/1000 -> 10.253403 | K77: FY2026＝公司 LEAP 逾 US$4B − 全流程 − CPO；之後＝顆數 × 相對值 × 每顆內容
A78: 全流程（CoWoS full process） | B78: US$B | D78: =fp26 -> 0.3 | E78: =fp27_A -> 1.2 | F78: =E78*F73/E73*(1+fp_g) -> 1.7443038 | G78: =F78*G73/F73*(1+fp_g) -> 2.5799241
A79: CPO（共同封裝光學） | B79: US$B | D79: =cpo27*cpo_A_26/cpo_A_27 -> 0.1 | E79: =cpo27*cpo_A_27/cpo_A_27 -> 0.5 | F79: =cpo27*cpo_A_28/cpo_A_27*F73/E73 -> 1.1181435 | G79: =cpo27*cpo_A_29/cpo_A_27*G73/E73 -> 2.035443 | K79: 2027 情境 A＝公司逾 US$0.5B；依 Siliconomics 同字母 CPO 滲透率縮放（2028 起另乘顆數比）
A80: LEAP 合計 | B80: US$B | C80: =leap25 -> 1.6 | D80: =D77+D78+D79 -> 4 | E80: =E77+E78+E79 -> 8.6805859 | F80: =F77+F78+F79 -> 11.489456 | G80: =G77+G78+G79 -> 14.868771
A81: 匯率 | B81: NT$/US$ | C81: =fx25 -> 31 | D81: =a26_leap/D80 -> 31.9 | E81: =fx -> 32 | F81: =fx -> 32 | G81: =fx -> 32 | K81: FY2026＝Q 頁 LEAP 新台幣 ÷ 美元（隱含）
A82: B. 營收分部（十億新台幣）
A83: LEAP 先進封裝（命題子列） | B83: NT$B | C83: =a25_leap -> 49.6 | D83: =a26_leap -> 127.6 | E83: =E80*E81 -> 277.77875 | F83: =F80*F81 -> 367.66259 | G83: =G80*G81 -> 475.80066
A84: 主流封測 | B84: NT$B | C84: =a25_ms -> 339.628 | D84: =a26_ms -> 432.1302 | E84: =D84*(1+g_ms27) -> 496.94973 | F84: =E84*(1+g_msL) -> 531.73621 | G84: =F84*(1+g_msL) -> 568.95775
A85: 封測（ATM） | B85: NT$B | C85: =C83+C84 -> 389.228 | D85: =D83+D84 -> 559.7302 | E85: =E83+E84 -> 774.72848 | F85: =F83+F84 -> 899.3988 | G85: =G83+G84 -> 1044.7584
A86: EMS（環旭） | B86: NT$B | C86: =a25_ems -> 259.079 | D86: =a26_ems -> 314.602 | E86: =D86*(1+g_ems27) -> 346.0622 | F86: =E86*(1+g_emsL) -> 363.36531 | G86: =F86*(1+g_emsL) -> 381.53358
A87: 沖銷及其他 | B87: NT$B | C87: =a25_elim -> -2.919 | D87: =a26_elim -> -3.1648491 | E87: =$D87/($D85+$D86)*(E85+E86) -> -4.0569629 | F87: =$D87/($D85+$D86)*(F85+F86) -> -4.5708688 | G87: =$D87/($D85+$D86)*(G85+G86) -> -5.1627961 | K87: 依 FY2026 比例
A88: 營收 | B88: NT$B | C88: =C85+C86+C87 -> 645.388 | D88: =D85+D86+D87 -> 871.16735 | E88: =E85+E86+E87 -> 1116.7337 | F88: =F85+F86+F87 -> 1258.1932 | G88: =G85+G86+G87 -> 1421.1292 | H88: =G88*(1+H89) -> 1572.2425 | I88: =H88*(1+I89) -> 1703.0007 | J88: =I88*(1+J89) -> 1805.1807 | K88: FY2030 起為收斂法：營收年增由 FY2029 線性收斂到 fade_g、淨利率收斂到 fade_m（FY2032 達到），非驅動因子推導
A89: 營收年增 | B89: % | D89: =D88/C88-1 -> 0.34983506 | E89: =E88/D88-1 -> 0.28188197 | F89: =F88/E88-1 -> 0.12667256 | G89: =G88/F88-1 -> 0.12949994 | H89: =$G89+(fade_gA-$G89)*1/3 -> 0.10633329 | I89: =$G89+(fade_gA-$G89)*2/3 -> 0.083166646 | J89: =$G89+(fade_gA-$G89)*3/3 -> 0.06
A90: LEAP ÷ 封測營收 | B90: % | C90: =C83/C85 -> 0.12743174 | D90: =D83/D85 -> 0.22796697 | E90: =E83/E85 -> 0.35854981 | F90: =F83/F85 -> 0.40878706 | G90: =G83/G85 -> 0.45541692
A91: 封測年增 | B91: % | D91: =D85/C85-1 -> 0.43805225 | E91: =E85/D85-1 -> 0.38411056 | F91: =F85/E85-1 -> 0.16092131 | G91: =G85/F85-1 -> 0.16161864
A92: C. 資本支出、折舊、毛利與損益
A93: 資本支出 | B93: US$B | C93: =capex25 -> 5.5 | D93: =capex26 -> 11.5 | E93: =capex27 -> 13 | F93: =capi*F88/F81 -> 11.795562 | G93: =capi*G88/G81 -> 13.323086 | K93: FY2026 公司 US$11.5B；FY2027 公司「更大」；之後＝營收 × 資本支出率
A94: 資本支出（新台幣） | B94: NT$B | C94: =C93*C81 -> 170.5 | D94: =D93*31.9 -> 366.85 | E94: =E93*E81 -> 416 | F94: =F93*F81 -> 377.45797 | G94: =G93*G81 -> 426.33876
A95: 資本支出 ÷ 營收 | B95: % | C95: =C94/C88 -> 0.26418217 | D95: =D94/D88 -> 0.42110164 | E95: =E94/E88 -> 0.37251495 | F95: =F94/F88 -> 0.3 | G95: =G94/G88 -> 0.3
A96: 折舊攤提 | B96: NT$B | C96: =a25_da -> 75.255 | D96: =a26_da -> 97.124 | E96: =D96*(1-1/life)+D94/life -> 130.83975 | F96: =E96*(1-1/life)+E94/life -> 166.48478 | G96: =F96*(1-1/life)+F94/life -> 192.85643 | K96: 前一年 ×（1 − 1／年限）＋前一年資本支出 ÷ 年限
A97: 封測毛利 ＝ FY2026 ＋ 流通率 × 封測營收增量 − 折舊增量 | B97: NT$B | C97: =a25_agp -> 91.38 | D97: =a26_agp -> 164.62339 | E97: =$D97+ft*(E85-$D85)-(E96-$D96) -> 238.40678 | F97: =$D97+ft*(F85-$D85)-(F96-$D96) -> 265.09691 | G97: =$D97+ft*(G85-$D85)-(G96-$D96) -> 311.40506 | K97: 流通率為現金毛利口徑；折舊增量全數歸封測
A98: 封測毛利率 | B98: % | C98: =C97/C85 -> 0.23477242 | D98: =D97/D85 -> 0.29411203 | E98: =E97/E85 -> 0.30772946 | F98: =F97/F85 -> 0.29474901 | G98: =G97/G85 -> 0.29806418
A99: EMS 毛利 | B99: NT$B | C99: =a25_egp -> 23.695 | D99: =a26_egp -> 27.00552 | E99: =E86*ems_gm -> 29.415287 | F99: =F86*ems_gm -> 30.886051 | G99: =G86*ems_gm -> 32.430354
A100: 沖銷及其他毛利 | B100: NT$B | C100: =a25_lgp -> -0.882 | D100: =a26_lgp -> -0.94866214 | E100: =$D100/$D87*E87 -> -1.2160729 | F100: =$D100/$D87*F87 -> -1.370116 | G100: =$D100/$D87*G87 -> -1.5475459
A101: 毛利 | B101: NT$B | C101: =C97+C99+C100 -> 114.193 | D101: =D97+D99+D100 -> 190.68025 | E101: =E97+E99+E100 -> 266.60599 | F101: =F97+F99+F100 -> 294.61284 | G101: =G97+G99+G100 -> 342.28787
A102: 毛利率 | B102: % | C102: =C101/C88 -> 0.17693697 | D102: =D101/D88 -> 0.21887901 | E102: =E101/E88 -> 0.2387373 | F102: =F101/F88 -> 0.23415548 | G102: =G101/G88 -> 0.24085627
A103: 營業費用 | B103: NT$B | C103: =a25_opx -> 63.437 | D103: =a26_opx -> 79.658 | E103: =D103*(1+phi*E89) -> 93.130492 | F103: =E103*(1+phi*F89) -> 100.20874 | G103: =F103*(1+phi*G89) -> 107.99495
A104: 營業利益 | B104: NT$B | C104: =C101-C103 -> 50.756 | D104: =D101-D103 -> 111.02225 | E104: =E101-E103 -> 173.4755 | F104: =F101-F103 -> 194.4041 | G104: =G101-G103 -> 234.29291
A105: 營業利益率 | B105: % | C105: =C104/C88 -> 0.078644164 | D105: =D104/D88 -> 0.12744078 | E105: =E104/E88 -> 0.15534187 | F105: =F104/F88 -> 0.15451053 | G105: =G104/G88 -> 0.16486391
A106: 營業外淨額 | B106: NT$B | C106: =a25_nonop -> 0.545 | D106: =a26_nonop -> 4.302 | E106: =nonop_f -> -5 | F106: =nonop_f -> -5 | G106: =nonop_f -> -5
A107: 稅前利益 | B107: NT$B | C107: =C104+C106 -> 51.301 | D107: =D104+D106 -> 115.32425 | E107: =E104+E106 -> 168.4755 | F107: =F104+F106 -> 189.4041 | G107: =G104+G106 -> 229.29291
A108: 所得稅 | B108: NT$B | C108: =a25_tax -> 9.461 | D108: =a26_tax -> 19.219732 | E108: =E107*tax -> 28.640835 | F108: =F107*tax -> 32.198697 | G108: =G107*tax -> 38.979795
A109: 非控制權益 | B109: NT$B | C109: =a25_nci -> 1.182 | D109: =a26_nci -> 2.543 | E109: =nci -> 3 | F109: =nci -> 3 | G109: =nci -> 3
A110: 歸屬母公司淨利 | B110: NT$B | C110: =C107-C108-C109 -> 40.658 | D110: =D107-D108-D109 -> 93.561514 | E110: =E107-E108-E109 -> 136.83466 | F110: =F107-F108-F109 -> 154.2054 | G110: =G107-G108-G109 -> 187.31312 | H110: =H88*H114 -> 207.23074 | I110: =I88*I114 -> 224.46542 | J110: =J88*J114 -> 237.93335
A111: 基本股數 | B111: 百萬股 | C111: =a25_sh -> 4339.1676 | D111: =a26_sh -> 4392.9011 | E111: =D111*(1+sh_g) -> 4414.8656 | F111: =E111*(1+sh_g) -> 4436.9399 | G111: =F111*(1+sh_g) -> 4459.1246 | H111: =G111*(1+sh_g) -> 4481.4202 | I111: =H111*(1+sh_g) -> 4503.8273 | J111: =I111*(1+sh_g) -> 4526.3464
A112: EPS（基本） | B112: NT$ | C112: =a25_eps -> 9.37 | D112: =a26_eps -> 21.28287 | E112: =E110/E111*1000 -> 30.994073 | F112: =F110/F111*1000 -> 34.754901 | G112: =G110/G111*1000 -> 42.006702 | H112: =H110/H111*1000 -> 46.242202 | I112: =I110/I111*1000 -> 49.838817 | J112: =J110/J111*1000 -> 52.566314
A113: EPS 年增 | B113: % | D113: =D112/C112-1 -> 1.2713842 | E113: =E112/D112-1 -> 0.45629199 | F113: =F112/E112-1 -> 0.12134023 | G113: =G112/F112-1 -> 0.20865551 | H113: =H112/G112-1 -> 0.10082915 | I113: =I112/H112-1 -> 0.077777757 | J113: =J112/I112-1 -> 0.054726368
A114: 淨利率（歸屬母公司淨利 ÷ 營收） | B114: % | C114: =C110/C88 -> 0.062997763 | D114: =D110/D88 -> 0.10739787 | E114: =E110/E88 -> 0.12253115 | F114: =F110/F88 -> 0.12256099 | G114: =G110/G88 -> 0.13180583 | H114: =$G114+(fade_mA-$G114)*1/3 -> 0.13180583 | I114: =$G114+(fade_mA-$G114)*2/3 -> 0.13180583 | J114: =$G114+(fade_mA-$G114)*3/3 -> 0.13180583
A115: 股東自由現金流（淨利＋折舊 − 資本支出；參考） | B115: NT$B | C115: =C110+C96-C94 -> -54.587 | D115: =D110+D96-D94 -> -176.16449 | E115: =E110+E96-E94 -> -148.32559 | F115: =F110+F96-F94 -> -56.767786 | G115: =G110+G96-G94 -> -46.169207 | K115: 不含營運資金與融資；只作參考，不進 DCF
A116: 營業利益增量（相對 FY2025）÷ FY2026 起累計資本支出 | B116: % | D116: =(D104-$C104)/SUM($D94:D94) -> 0.16428035 | E116: =(E104-$C104)/SUM($D94:E94) -> 0.15675991 | F116: =(F104-$C104)/SUM($D94:F94) -> 0.1238017 | G116: =(G104-$C104)/SUM($D94:G94) -> 0.11567598 | K116: 資本支出的稅前邊際報酬（核心問題之二）
A119: 情境 B：CY2028 顆數 ×0.8、CY2029 ×0.85；相對值 1.05／1.08／1.10；全流程 US$1.0B；CPO 情境 B
...

Sheet Val
A1: Val — P/E 估值（新台幣）。結論用「現價 ÷ FY2027、FY2028 EPS（模型）」；目標價＝DCF 與 Comparable 加權（第 0 節）；十年 P/E 規則值（第 3 節，年底落後 P/E）只作參考
A2: 循環位置：日月光不是設備股，不套設備市場見頂年；以本模型封測（ATM）營收最高的會計年度為見頂年（Andy 前一串定案；FY(t)＝CY(t)）。封測營收到 FY2029 仍在增加時，見頂年未知，判為中段
A4: 0. 目標價
A5: 0.1 DCF（股東權益現金流，FY2027–FY2032 明確期＋FY2032 後永續）
A6: 項目 | B6: A（順利） | C6: B（平平） | D6: C（不如預期） | E6: 說明
A7: 情境 EPS（FY2027–FY2032） | E7: PL 頁各情境；FY2030 起為收斂法
A8: FY2027 | B8: =PL!E17 -> 30.994073 | C8: =PL!E33 -> 29.076998 | D8: =PL!E49 -> 27.159923
A9: FY2028 | B9: =PL!F17 -> 34.754901 | C9: =PL!F33 -> 25.638067 | D9: =PL!F49 -> 17.590034
A10: FY2029 | B10: =PL!G17 -> 42.006702 | C10: =PL!G33 -> 31.527915 | D10: =PL!G49 -> 19.671479
A11: FY2030 | B11: =PL!H17 -> 46.242202 | C11: =PL!H33 -> 33.151962 | D11: =PL!H49 -> 19.364669
A12: FY2031 | B12: =PL!I17 -> 49.838817 | C12: =PL!I33 -> 33.97087 | D12: =PL!I49 -> 18.607622
A13: FY2032 | B13: =PL!J17 -> 52.566314 | C13: =PL!J33 -> 33.898437 | D13: =PL!J49 -> 17.432628
A14: 股東現金流＝EPS ×（1 − tp_g ÷ tp_roe）
A15: 再投資率（tp_g ÷ tp_roe，上限 0.8） | B15: =MIN(tp_g/tp_roe,0.8) -> 0.37974684 | E15: ROE 為近三年平均（In 頁 tp_roe）
A16: FY2027 | B16: =B8*(1-$B$15) -> 19.224172 | C16: =C8*(1-$B$15) -> 18.0351 | D16: =D8*(1-$B$15) -> 16.846028
A17: FY2028 | B17: =B9*(1-$B$15) -> 21.556837 | C17: =C9*(1-$B$15) -> 15.902092 | D17: =D9*(1-$B$15) -> 10.910274
A18: FY2029 | B18: =B10*(1-$B$15) -> 26.05479 | C18: =C10*(1-$B$15) -> 19.555289 | D18: =D10*(1-$B$15) -> 12.201297
A19: FY2030 | B19: =B11*(1-$B$15) -> 28.681872 | C19: =C11*(1-$B$15) -> 20.562609 | D19: =D11*(1-$B$15) -> 12.010997
A20: FY2031 | B20: =B12*(1-$B$15) -> 30.912684 | C20: =C12*(1-$B$15) -> 21.07054 | D20: =D12*(1-$B$15) -> 11.541436
A21: FY2032 | B21: =B13*(1-$B$15) -> 32.604423 | C21: =C13*(1-$B$15) -> 21.025613 | D21: =D13*(1-$B$15) -> 10.812643
A22: DCF 情境每股價值（折現率 tp_r） | B22: =MAX(0,SUMPRODUCT(B16:B21,1/(1+tp_r)^{1;2;3;4;5;6})+B21*(1+tp_g)/(tp_r-tp_g)/(1+tp_r)^6) -> 431.06491 | C22: =MAX(0,SUMPRODUCT(C16:C21,1/(1+tp_r)^{1;2;3;4;5;6})+C21*(1+tp_g)/(tp_r-tp_g)/(1+tp_r)^6) -> 288.94516 | D22: =MAX(0,SUMPRODUCT(D16:D21,1/(1+tp_r)^{1;2;3;4;5;6})+D21*(1+tp_g)/(tp_r-tp_g)/(1+tp_r)^6) -> 160.76501 | E22: Σ 明確期現金流 ÷ (1＋r)^t ＋ 永續價值 ÷ (1＋r)^6；永續價值＝FY2032 現金流 ×(1＋g)÷(r−g)；基準日 2026 年底；下限 0
A23: DCF 情境價值推到 12 個月後（×(1＋tp_r)） | B23: =B22*(1+tp_r) -> 474.1714 | C23: =C22*(1+tp_r) -> 317.83968 | D23: =D22*(1+tp_r) -> 176.84151
A24: DCF 目標價（情境加權） | B24: =tp_wA*B23+tp_wB*C23+tp_wC*D23 -> 336.53956 | E24: Σ 權重 × 情境價值 ×(1＋r)；權重見 In 頁
A26: 0.2 Comparable（市場主流同業前瞻 P/E）
A27: 同業與前瞻 P/E | B27: 代號 | C27: 前瞻 12 月 P/E | D27: 日期 | E27: 來源 | F27: 標記
A28: Amkor Technology（艾克爾） | B28: AMKR | C28: 14.02 | D28: 2026-10-23 | E28: stockanalysis.com forward PE（分析師共識；價格日期如左；與 Amkor、京元電模型同一組數字） | F28: Interested-party
A29: 力成（Powertech） | B29: 6239.TW | C29: 20.6 | D29: 2026-10-02 | E29: stockanalysis.com forward PE（分析師共識；價格日期如左；與 Amkor、京元電模型同一組數字） | F29: Interested-party
A30: 京元電子（KYEC） | B30: 2449.TW | C30: 26.13 | D30: 2026-10-06 | E30: stockanalysis.com forward PE（分析師共識；價格日期如左；與 Amkor、京元電模型同一組數字） | F30: Interested-party
A31: 矽格（Sigurd） | B31: 6257.TW | C31: 23.3 | D31: 2026-10-02 | E31: stockanalysis.com forward PE（分析師共識；價格日期如左；與 Amkor、京元電模型同一組數字） | F31: Interested-party
A32: 南茂（ChipMOS） | B32: 8150.TW | C32: 22.08 | D32: 2026-10-08 | E32: stockanalysis.com forward PE（分析師共識；價格日期如左；與 Amkor、京元電模型同一組數字） | F32: Interested-party
A33: 同業前瞻 P/E 中位數 | B33: =MEDIAN(C28:C32) -> 22.08 | E33: 台美封測同業：Amkor、力成、京元電、矽格、南茂（不放 A 股：長電、通富）
A34: 12 個月後的前瞻 EPS（情境加權） | B34: =tp_wA*(2/12*B8+10/12*B9)+tp_wB*(2/12*C8+10/12*C9)+tp_wC*(2/12*D8+10/12*D9) -> 27.181043 | E34: 約 2027-10 時的未來 12 月 EPS ≈ 2／12 × FY2027＋10／12 × FY2028（會計年度＝日曆年）
A35: Comparable 目標價 | B35: =B33*B34 -> 600.15743 | E35: 同業中位數 × 前瞻 EPS
A37: 0.3 結論
A38: 項目 | B38: 數值 | E38: 說明
A39: 目標價（DCF 與 Comparable 加權） | B39: =tp_w_dcf*B24+(1-tp_w_dcf)*tp_comp_adj -> 503.84483 | E39: tp_w_dcf × DCF＋（1 − tp_w_dcf）× Comparable（相對倍數調整後，Val 第 0.5 節）；tp_w_dcf 見 In 頁
A40: Comparable 目標價（市場主流同業法） | B40: =B35 -> 600.15743
A41: 市場共識目標價 | B41: =cons_tp -> 900 | E41: 賣方平均：未找到；以 BofA 900（2026-10-14，單一券商）代替
A42: 上檔空間：加權目標價 | B42: =B39/px-1 -> -0.24574127 | E42: 現價＝In 頁 px（2026-10-30 收盤）
A43: 上檔空間：Comparable 目標價 | B43: =B40/px-1 -> -0.10156074
A44: 與市場共識目標價的差距：EPS 因素 | B44: =B34/cons_feps-1 -> -0.4240491 | E44: 本模型 12 個月後前瞻 EPS ÷ BofA 同口徑前瞻 EPS − 1（In 頁 cons_feps）
A45: 與市場共識目標價的差距：倍數因素 | B45: =(cons_tp/cons_feps)/B33-1 -> -0.13630026 | E45: ="共識目標價隱含 "&TEXT(cons_tp/cons_feps,"0.0")&"x，同業中位數 "&TEXT(B33,"0.0")&"x" -> 共識目標價隱含 19.1x，同業中位數 22.1x
A46: 價格帶（DCF 不如預期～順利） | B46: =TEXT(D23,"0.00")&"～"&TEXT(B23,"0.00") -> 176.84～474.17 | E46: C 情境價值～A 情境價值（推到 12 個月後）
A47: 歷史倍數檢查：現價隱含 P/E 的十年分位（A／B／C） | B47: =IF(px/B9>=MAX($B$86:$B$95),1,IF(px/B9<=MIN($B$86:$B$95),0,PERCENTRANK($B$86:$B$95,px/B9))) -> 0.795 | C47: =IF(px/C9>=MAX($B$86:$B$95),1,IF(px/C9<=MIN($B$86:$B$95),0,PERCENTRANK($B$86:$B$95,px/C9))) -> 1 | D47: =IF(px/D9>=MAX($B$86:$B$95),1,IF(px/D9<=MIN($B$86:$B$95),0,PERCENTRANK($B$86:$B$95,px/D9))) -> 1 | E47: 現價 ÷ 各情境 FY2028 EPS 在 2016–2025 年底 P/E（第 5 節）的分位；只作檢查，不進目標價
A48: 目標價方法 | B48: DCF：股東現金流＝基本 EPS ×（1 − g／ROE），r＝10%、g＝4%、ROE 為 FY2023–25 平均約 10.5%（再投資率約 38%），FY2027–32 明確期＋永續；日月光資本支出約占營收四成，FY2026–27 股東自由現金流為負（PL 頁參考列），本式未扣資本支出高峰，現金流偏高估；但 ROE 用 2023–25 低谷年，FY2026 起 ROE 明顯上升，再投資率偏高（偏低估）。Comparable：台美封測同業（Amkor、力成、京元電、矽格、南茂）前瞻 P/E 中位數，再乘相對倍數調整係數（Bloomberg 十年前瞻 P/E，日月光相對同業）；不放 A 股。情境對應：A＝順利（顆數基準）、B＝平平（顆數 ×0.8／0.85）、C＝不如預期（顆數 ×0.6）
A49: 上檔空間級距 | B49: =IF(B42>0.5,"大於 50%",IF(B42>0.25,"25%–50%",IF(B42>=0,"0%–25%",IF(B42>=-0.25,"0%～−25%",IF(B42>=-0.5,"−25%～−50%","小於 −50%"))))) -> 0%～−25% | E49: 以「上檔空間：加權目標價」分六級（Andy 2026-10-25 14:00）
A50: 投資建議 | B50: =IF(B42>0.5,"強力買進",IF(B42>0.25,"買進",IF(B42>=-0.25,"中立",IF(B42>=-0.5,"放空","強力放空")))) -> 中立 | E50: 依上檔空間固定規則（Andy 2026-10-25 14:17）：大於 +50% 強力買進、+25%～+50% 買進、−25%～+25% 中立、−50%～−25% 放空、小於 −50% 強力放空
A51: 1. 價格與市場隱含倍數
A52: 項目 | B52: A | C52: B | D52: C | E52: 說明
A53: 現價（2026-10-30 收盤） | B53: =px -> 668
A54: 現價 ÷ FY2026 EPS（錨點） | B54: =px/PL!D17 -> 31.386745 | C54: =px/PL!D33 -> 31.386745 | D54: =px/PL!D49 -> 31.386745 | E54: FY2026 三情境相同（錨點）
A55: 現價 ÷ FY2027 EPS（模型） | B55: =px/PL!E17 -> 21.552508 | C55: =px/PL!E33 -> 22.973486 | D55: =px/PL!E49 -> 24.595062 | E55: FY2027 三情境只差委外相對值、全流程與 CPO
A56: 現價 ÷ FY2028 EPS（模型） | B56: =px/PL!F17 -> 19.220311 | C56: =px/PL!F33 -> 26.055007 | D56: =px/PL!F49 -> 37.97605
A57: 現價 ÷ FY2029 EPS（模型） | B57: =px/PL!G17 -> 15.902224 | C57: =px/PL!G33 -> 21.187573 | D57: =px/PL!G49 -> 33.957792
A58: 未來 12 月 EPS（模型 B）≈ 0.2 × FY2026＋0.8 × FY2027 | B58: =0.2*PL!D33+0.8*PL!E33 -> 27.518172
A59: 現價 ÷ 未來 12 月 EPS（模型 B） | B59: =px/B58 -> 24.274868
A60: 近 12 月 P/E（Yahoo 奇摩股市，10-27） | B60: =pe_ttm -> 47.32
A61: 前瞻 P/E（stockanalysis，ADR，10-26） | B61: =fpe -> 26.99
A63: 2. 循環位置（本模型封測營收最高年；FY(t)＝CY(t)）
A64: 情境 | B64: 封測營收最高年（FY2026–FY2029） | C64: FY2027 判定 | D64: 規則倍數（P/E） | E64: 見頂年是否未知 | F64: 說明
A65: A | B65: =INDEX({2026,2027,2028,2029},MATCH(MAX(PL!D85:G85),PL!D85:G85,0)) -> 2029 | C65: =IF(B65=2029,"中段",IF(2027<B65,"中段",IF(2027=B65,"見頂","谷底"))) -> 中段 | D65: =IF(C65="見頂",pe_peak,IF(C65="谷底",pe_trough,pe_mid)) -> 11.41 | E65: =IF(B65=2029,"是：封測營收到觀測期末仍在增加","否") -> 是：封測營收到觀測期末仍在增加 | F65: tools/cycle_position.py excel_rule；日月光自身封測營收最高年取代設備市場見頂年
A66: B | B66: =INDEX({2026,2027,2028,2029},MATCH(MAX(PL!D134:G134),PL!D134:G134,0)) -> 2029 | C66: =IF(B66=2029,"中段",IF(2027<B66,"中段",IF(2027=B66,"見頂","谷底"))) -> 中段 | D66: =IF(C66="見頂",pe_peak,IF(C66="谷底",pe_trough,pe_mid)) -> 11.41 | E66: =IF(B66=2029,"是：封測營收到觀測期末仍在增加","否") -> 是：封測營收到觀測期末仍在增加 | F66: 同上
A67: C | B67: =INDEX({2026,2027,2028,2029},MATCH(MAX(PL!D183:G183),PL!D183:G183,0)) -> 2029 | C67: =IF(B67=2029,"中段",IF(2027<B67,"中段",IF(2027=B67,"見頂","谷底"))) -> 中段 | D67: =IF(C67="見頂",pe_peak,IF(C67="谷底",pe_trough,pe_mid)) -> 11.41 | E67: =IF(B67=2029,"是：封測營收到觀測期末仍在增加","否") -> 是：封測營收到觀測期末仍在增加 | F67: 同上
A69: 3. 規則值隱含股價（新台幣；約 FY2027 年底，未折現）＝ FY2027 EPS × 規則倍數
A70: 情境 | B70: FY2027 EPS | C70: （同左） | D70: 規則倍數 | E70: 隱含股價 | F70: 相對現價 | G70: 現價 ÷ FY2027 EPS
A71: A | B71: =PL!E17 -> 30.994073 | C71: =B71 -> 30.994073 | D71: =D65 -> 11.41 | E71: =C71*D71 -> 353.64237 | F71: =E71/px-1 -> -0.47059525 | G71: =px/C71 -> 21.552508
A72: B | B72: =PL!E33 -> 29.076998 | C72: =B72 -> 29.076998 | D72: =D66 -> 11.41 | E72: =C72*D72 -> 331.76855 | F72: =E72/px-1 -> -0.5033405 | G72: =px/C72 -> 22.973486
A73: C | B73: =PL!E49 -> 27.159923 | C73: =B73 -> 27.159923 | D73: =D67 -> 11.41 | E73: =C73*D73 -> 309.89472 | F73: =E73/px-1 -> -0.53608575 | G73: =px/C73 -> 24.595062
A75: 4. What must be true：FY2027 年底價 ＝ 現價 ×（1＋報酬）所需的倍數（FY2028 EPS；約 2027 年底的價格看下一年 EPS）
A76: FY2027 年底價 ÷ 現價 | B76: 所需倍數（÷ FY2028 EPS，A） | C76: 所需倍數（÷ FY2028 EPS，B） | D76: 所需倍數（÷ FY2028 EPS，C） | E76: 對照：十年中位數
A77: 1 | B77: =px*A77/PL!F17 -> 19.220311 | C77: =px*A77/PL!F33 -> 26.055007 | D77: =px*A77/PL!F49 -> 37.97605 | E77: =pe_mid -> 11.41
A78: 1.1 | B78: =px*A78/PL!F17 -> 21.142342 | C78: =px*A78/PL!F33 -> 28.660507 | D78: =px*A78/PL!F49 -> 41.773655 | E78: =pe_mid -> 11.41
A79: 1.21 | B79: =px*A79/PL!F17 -> 23.256576 | C79: =px*A79/PL!F33 -> 31.526558 | D79: =px*A79/PL!F49 -> 45.951021 | E79: =pe_mid -> 11.41
A80: 1.5 | B80: =px*A80/PL!F17 -> 28.830467 | C80: =px*A80/PL!F33 -> 39.08251 | D80: =px*A80/PL!F49 -> 56.964076 | E80: =pe_mid -> 11.41
A81: 2 | B81: =px*A81/PL!F17 -> 38.440622 | C81: =px*A81/PL!F33 -> 52.110013 | D81: =px*A81/PL!F49 -> 75.952101 | E81: =pe_mid -> 11.41
A82: 讀法：1.00＝價格不變、1.21＝一年約 21%。所需倍數低於歷史中位數時，現價相對便宜；倍數是否合理，另看前瞻 P/E 歷史（Bloomberg，Val 第 0.5 節）。本版未做先驗，無 Andy 合理 P/E 對照。
A84: 5. 十年 P/E（2016–2025 年底；單一來源，分位排名用；無負值或 >200 需剔除）
A85: 年底 | B85: 採用 P/E | C85: macrotrends（ADR） | D85: （第二來源：未找到）
A86: 2016 | B86: =C86 -> 10.45 | C86: =B105 -> 10.45
A87: 2017 | B87: =C87 -> 12.36 | C87: =B106 -> 12.36
A88: 2018 | B88: =C88 -> 7.02 | C88: =B107 -> 7.02
A89: 2019 | B89: =C89 -> 16.2 | C89: =B108 -> 16.2
A90: 2020 | B90: =C90 -> 10.35 | C90: =B109 -> 10.35
A91: 2021 | B91: =C91 -> 6.11 | C91: =B110 -> 6.11
A92: 2022 | B92: =C92 -> 5.78 | C92: =B111 -> 5.78
A93: 2023 | B93: =C93 -> 18.78 | C93: =B112 -> 18.78
A94: 2024 | B94: =C94 -> 21.59 | C94: =B113 -> 21.59
A95: 2025 | B95: =C95 -> 22.18 | C95: =B114 -> 22.18
A96: 年數 | B96: =COUNT($B$86:$B$95) -> 10
A100: 6. 十年倍數與規則值（2016–2025 年底；見頂年 25 分位、中段中位數、谷底 75 分位）
A101: 規則（Andy 2026-10-13）：合理倍數＝2016–2025 年底 P/E 依循環位置取分位。日月光的落後 P/E 與盈餘反向：盈餘高峰年（2021–2022）約 6x，低谷年（2023–2025）約 19–22x；2016–2017 為合併前的日月光半導體（ADR 代號相同）。
A103: P/E：十年歷史倍數
A104: 年底 | B104: macrotrends（ADR 年底 P/E） | C104: 標記／說明
A105: 2016 | B105: 10.45 | C105: macrotrends（ADR 年底 P/E）：Interested-party（資料商；2016–2024 為 12 月底，2025 為 9 月底值，12 月底未列）
A106: 2017 | B106: 12.36
A107: 2018 | B107: 7.02
A108: 2019 | B108: 16.2
A109: 2020 | B109: 10.35
A110: 2021 | B110: 6.11
A111: 2022 | B111: 5.78
...

Sheet Recon
A1: Recon — 本模型 vs 公司指引、公司說法、券商預估與市場口徑。只作事後對照，不為對上數字而調參數。賣方共識未找到，以 BofA（2026-10-14，單一券商，3Q26 財報前）對照
A3: 項目 | B3: 對照值 | C3: 模型 A | D3: 差距 A | E3: 模型 B | F3: 差距 B | G3: 模型 C | H3: 差距 C | I3: 對照來源 | J3: 說明
A4: A. 4Q26 模型 vs 公司指引（錨點用指引中點，非獨立檢驗）
A5: 4Q26 合併營收季增 vs 指引中點 7%（百分點） | B5: =(g4_rev_lo+g4_rev_hi)/2 -> 0.07 | C5: =Q!F4/Q!E4-1 -> 0.074210668 | D5: =C5-B5 -> 0.0042106681 | E5: =Q!F4/Q!E4-1 -> 0.074210668 | F5: =E5-B5 -> 0.0042106681 | G5: =Q!F4/Q!E4-1 -> 0.074210668 | H5: =G5-B5 -> 0.0042106681 | I5: 3Q26 新聞稿：6–8%
A6: 4Q26 合併毛利率 vs 指引中點 23.5%（百分點） | B6: =(g4_gm_lo+g4_gm_hi)/2 -> 0.235 | C6: =Q!F15 -> 0.23542841 | D6: =C6-B6 -> 0.00042840948 | E6: =Q!F15 -> 0.23542841 | F6: =E6-B6 -> 0.00042840948 | G6: =Q!F15 -> 0.23542841 | H6: =G6-B6 -> 0.00042840948 | I6: 3Q26 新聞稿：23–24%
A7: 4Q26 合併營業利益率 vs 指引中點 15%（百分點） | B7: =(g4_om_lo+g4_om_hi)/2 -> 0.15 | C7: =Q!F17/Q!F4 -> 0.14967666 | D7: =C7-B7 -> -0.00032334401 | E7: =Q!F17/Q!F4 -> 0.14967666 | F7: =E7-B7 -> -0.00032334401 | G7: =Q!F17/Q!F4 -> 0.14967666 | H7: =G7-B7 -> -0.00032334401 | I7: 3Q26 新聞稿：14.5–15.5% | J7: 營業費用季增 8% 校準
A8: B. 公司說法（3Q26 法說 2026-10-29）
A9: FY2027 LEAP ÷ FY2026（公司：翻倍） | B9: 2 | C9: =PL!E80/PL!D80 -> 2.1701465 | D9: =C9/B9-1 -> 0.085073237 | E9: =PL!E129/PL!D129 -> 1.9908216 | F9: =E9/B9-1 -> -0.0045891827 | G9: =PL!E178/PL!D178 -> 1.8114968 | H9: =G9/B9-1 -> -0.094251603 | I9: 3Q26 法說：expecting … to double our LEAP revenue | J9: 情境 A 高於翻倍、B 約翻倍
A10: FY2027 全流程（公司：逾 US$1B） | B10: 1 | C10: =PL!E78 -> 1.2 | D10: =C10/B10-1 -> 0.2 | E10: =PL!E127 -> 1 | F10: =E10/B10-1 -> 0 | G10: =PL!E176 -> 0.7 | H10: =G10/B10-1 -> -0.3 | I10: 3Q26 法說：over US$1 billion（保守）
A11: FY2027 CPO（公司：逾 US$0.5B） | B11: =cpo27 -> 0.5 | C11: =PL!E79 -> 0.5 | D11: =C11/B11-1 -> 0 | E11: =PL!E128 -> 0.3 | F11: =E11/B11-1 -> -0.4 | G11: =PL!E177 -> 0.2 | H11: =G11/B11-1 -> -0.6 | I11: 3Q26 法說：over US$0.5 billion | J11: B、C 依 Siliconomics 較低滲透率
A12: FY2027 主流封測年增 vs 公司「與 2026 相近」（FY2026 實測，百分點） | B12: =Q!G7/Q!B7-1 -> 0.27236329 | C12: =PL!E84/PL!D84-1 -> 0.15 | D12: =C12-B12 -> -0.12236329 | E12: =PL!E133/PL!D133-1 -> 0.15 | F12: =E12-B12 -> -0.12236329 | G12: =PL!E182/PL!D182-1 -> 0.15 | H12: =G12-B12 -> -0.12236329 | I12: 3Q26 法說：general market 2027 similar（逾 20%） | J12: 本模型取 15%（偏保守）
A13: FY2027 資本支出 vs FY2026 US$11.5B（公司：更大） | B13: =capex26 -> 11.5 | C13: =PL!E93 -> 13 | D13: =C13/B13-1 -> 0.13043478 | E13: =PL!E142 -> 13 | F13: =E13/B13-1 -> 0.13043478 | G13: =PL!E191 -> 13 | H13: =G13/B13-1 -> 0.13043478 | I13: 3Q26 法說：even larger than this year
A14: C. 券商（BofA 2026-10-14；3Q26 財報前、單一來源）
A15: FY2026 EPS vs BofA | B15: =bofa_eps26 -> 19.64 | C15: =PL!D112 -> 21.28287 | D15: =C15/B15-1 -> 0.083649172 | E15: =PL!D161 -> 21.28287 | F15: =E15/B15-1 -> 0.083649172 | G15: =PL!D210 -> 21.28287 | H15: =G15/B15-1 -> 0.083649172 | I15: BofA | J15: 錨點含 3Q26 實績（BofA 為財報前）
A16: FY2027 EPS vs BofA | B16: =bofa_eps27 -> 34.26 | C16: =PL!E112 -> 30.994073 | D16: =C16/B16-1 -> -0.095327706 | E16: =PL!E161 -> 29.076998 | F16: =E16/B16-1 -> -0.15128436 | G16: =PL!E210 -> 27.159923 | H16: =G16/B16-1 -> -0.20724101 | I16: BofA
A17: FY2028 EPS vs BofA | B17: =bofa_eps28 -> 49.78 | C17: =PL!F112 -> 34.754901 | D17: =C17/B17-1 -> -0.30183004 | E17: =PL!F161 -> 25.638067 | F17: =E17/B17-1 -> -0.48497254 | G17: =PL!F210 -> 17.590034 | H17: =G17/B17-1 -> -0.64664457 | I17: BofA | J17: 差距超過 30% 時 README 說明
A18: FY2028 封測毛利率 vs BofA 約 30%（百分點） | B18: =bofa_gm28 -> 0.3 | C18: =PL!F98 -> 0.29474901 | D18: =C18-B18 -> -0.0052509895 | E18: =PL!F147 -> 0.26652354 | F18: =E18-B18 -> -0.033476458 | G18: =PL!F196 -> 0.23421081 | H18: =G18-B18 -> -0.065789189 | I18: BofA
A19: D. LEAP 的市場口徑
A20: FY2026 每 GW 的日月光 LEAP 營收（US$B／GW） | C20: =Units!C14 -> 0.17094355 | E20: =Units!C14 -> 0.17094355 | G20: =Units!C14 -> 0.17094355 | I20: Siliconomics 部署 GW | J20: 對照 Amkor 投資人日：OSAT 先進封裝 US$0.5B／GW（全體 OSAT）
A21: FY2027 每 GW 的日月光 LEAP 營收（US$B／GW） | C21: =Units!D14 -> 0.20843361 | E21: =Units!D14 -> 0.20843361 | G21: =Units!D14 -> 0.20843361 | I21: 同上 | J21: 情境 A
A22: FY2028 LEAP ÷ 封測營收（核心問題：三成以上） | B22: 0.3 | C22: =PL!F90 -> 0.40878706 | D22: =C22-B22 -> 0.10878706 | E22: =PL!F139 -> 0.32748532 | F22: =E22-B22 -> 0.027485316 | G22: =PL!F188 -> 0.23441047 | H22: =G22-B22 -> -0.065589532 | I22: 核心問題門檻

Sheet Sens
A1: Sens — 一次動一個輸入（三情境同時重算，再依情境權重求 DCF 與 Comparable 目標價）：對 FY2027、FY2028 EPS（情境 B）與加權目標價的影響。每個案例的三情境推導區塊在本頁下方
A2: 註：情境專屬列（委外相對值、全流程 FY2027、CPO 滲透率、顆數係數）不給敏感度區間，差異見情境 B、C；Comparable 欄已乘相對倍數調整係數（rm_factor），與加權目標價同口徑。
A3: 案例 | B3: 鍵 | C3: 設定 | D3: FY2027 EPS（B） | E3: FY2028 EPS（B） | F3: FY2028 EPS（B）相對基準 | G3: DCF 目標價 | H3: Comparable 目標價 | I3: 加權目標價 | J3: 加權目標價相對基準
A4: 基準 | B4: — | C4: PL 三情境 | D4: =PL!E161 -> 29.076998 | E4: =PL!F161 -> 25.638067 | F4: =E4/E$4-1 -> 0 | G4: =(tp_wA*MAX(0,PL!E112*(1-MIN(tp_g/tp_roe,0.8))/(1+tp_r)^1+PL!F112*(1-MIN(tp_g/tp_roe,0.8))/(1+tp_r)^2+PL!G112*(1-MIN(tp_g/tp_roe,0.8))/(1+tp_r)^3+PL!H112*(1-MIN(tp_g/tp_roe,0.8))/(1+tp_r)^4+PL!I112*(1-MIN(tp_g/tp_roe,0.8))/(1+tp_r)^5+PL!J112*(1-MIN(tp_g/tp_roe,0.8))/(1+tp_r)^6+PL!J112*(1-MIN(tp_g/tp_roe,0.8))*(1+tp_g)/(tp_r-tp_g)/(1+tp_r)^6)+tp_wB*MAX(0,PL!E161*(1-MIN(tp_g/tp_roe,0.8))/(1+tp_r)^1+PL!F161*(1-MIN(tp_g/tp_roe,0.8))/(1+tp_r)^2+PL!G161*(1-MIN(tp_g/tp_roe,0.8))/(1+tp_r)^3+PL!H161*(1-MIN(tp_g/tp_roe,0.8))/(1+tp_r)^4+PL!I161*(1-MIN(tp_g/tp_roe,0.8))/(1+tp_r)^5+PL!J161*(1-MIN(tp_g/tp_roe,0.8))/(1+tp_r)^6+PL!J161*(1-MIN(tp_g/tp_roe,0.8))*(1+tp_g)/(tp_r-tp_g)/(1+tp_r)^6)+tp_wC*MAX(0,PL!E210*(1-MIN(tp_g/tp_roe,0.8))/(1+tp_r)^1+PL!F210*(1-MIN(tp_g/tp_roe,0.8))/(1+tp_r)^2+PL!G210*(1-MIN(tp_g/tp_roe,0.8))/(1+tp_r)^3+PL!H210*(1-MIN(tp_g/tp_roe,0.8))/(1+tp_r)^4+PL!I210*(1-MIN(tp_g/tp_roe,0.8))/(1+tp_r)^5+PL!J210*(1-MIN(tp_g/tp_roe,0.8))/(1+tp_r)^6+PL!J210*(1-MIN(tp_g/tp_roe,0.8))*(1+tp_g)/(tp_r-tp_g)/(1+tp_r)^6))*(1+tp_r) -> 336.53956 | H4: =Val!$B$33*(tp_wA*(2/12*PL!E112+10/12*PL!F112)+tp_wB*(2/12*PL!E161+10/12*PL!F161)+tp_wC*(2/12*PL!E210+10/12*PL!F210))*rm_factor -> 671.1501 | I4: =tp_w_dcf*G4+(1-tp_w_dcf)*H4 -> 503.84483 | J4: =I4/I$4-1 -> 0
A5: AI 部署 ×0.8 | B5: mf | C5: FY2027 起顆數 ×0.8（三情境） | D5: =E211 -> 25.5153 | E5: =F211 -> 22.184187 | F5: =E5/E$4-1 -> -0.13471687 | G5: =(tp_wA*MAX(0,E162*(1-MIN(tp_g/tp_roe,0.8))/(1+tp_r)^1+F162*(1-MIN(tp_g/tp_roe,0.8))/(1+tp_r)^2+G162*(1-MIN(tp_g/tp_roe,0.8))/(1+tp_r)^3+H162*(1-MIN(tp_g/tp_roe,0.8))/(1+tp_r)^4+I162*(1-MIN(tp_g/tp_roe,0.8))/(1+tp_r)^5+J162*(1-MIN(tp_g/tp_roe,0.8))/(1+tp_r)^6+J162*(1-MIN(tp_g/tp_roe,0.8))*(1+tp_g)/(tp_r-tp_g)/(1+tp_r)^6)+tp_wB*MAX(0,E211*(1-MIN(tp_g/tp_roe,0.8))/(1+tp_r)^1+F211*(1-MIN(tp_g/tp_roe,0.8))/(1+tp_r)^2+G211*(1-MIN(tp_g/tp_roe,0.8))/(1+tp_r)^3+H211*(1-MIN(tp_g/tp_roe,0.8))/(1+tp_r)^4+I211*(1-MIN(tp_g/tp_roe,0.8))/(1+tp_r)^5+J211*(1-MIN(tp_g/tp_roe,0.8))/(1+tp_r)^6+J211*(1-MIN(tp_g/tp_roe,0.8))*(1+tp_g)/(tp_r-tp_g)/(1+tp_r)^6)+tp_wC*MAX(0,E260*(1-MIN(tp_g/tp_roe,0.8))/(1+tp_r)^1+F260*(1-MIN(tp_g/tp_roe,0.8))/(1+tp_r)^2+G260*(1-MIN(tp_g/tp_roe,0.8))/(1+tp_r)^3+H260*(1-MIN(tp_g/tp_roe,0.8))/(1+tp_r)^4+I260*(1-MIN(tp_g/tp_roe,0.8))/(1+tp_r)^5+J260*(1-MIN(tp_g/tp_roe,0.8))/(1+tp_r)^6+J260*(1-MIN(tp_g/tp_roe,0.8))*(1+tp_g)/(tp_r-tp_g)/(1+tp_r)^6))*(1+tp_r) -> 316.36624 | H5: =Val!$B$33*(tp_wA*(2/12*E162+10/12*F162)+tp_wB*(2/12*E211+10/12*F211)+tp_wC*(2/12*E260+10/12*F260))*rm_factor -> 583.08261 | I5: =tp_w_dcf*G5+(1-tp_w_dcf)*H5 -> 449.72442 | J5: =I5/I$4-1 -> -0.10741483
A6: AI 部署 ×1.2 | B6: mf | C6: ×1.2 | D6: =E358 -> 32.638696 | E6: =F358 -> 29.091099 | F6: =E6/E$4-1 -> 0.13468378 | G6: =(tp_wA*MAX(0,E309*(1-MIN(tp_g/tp_roe,0.8))/(1+tp_r)^1+F309*(1-MIN(tp_g/tp_roe,0.8))/(1+tp_r)^2+G309*(1-MIN(tp_g/tp_roe,0.8))/(1+tp_r)^3+H309*(1-MIN(tp_g/tp_roe,0.8))/(1+tp_r)^4+I309*(1-MIN(tp_g/tp_roe,0.8))/(1+tp_r)^5+J309*(1-MIN(tp_g/tp_roe,0.8))/(1+tp_r)^6+J309*(1-MIN(tp_g/tp_roe,0.8))*(1+tp_g)/(tp_r-tp_g)/(1+tp_r)^6)+tp_wB*MAX(0,E358*(1-MIN(tp_g/tp_roe,0.8))/(1+tp_r)^1+F358*(1-MIN(tp_g/tp_roe,0.8))/(1+tp_r)^2+G358*(1-MIN(tp_g/tp_roe,0.8))/(1+tp_r)^3+H358*(1-MIN(tp_g/tp_roe,0.8))/(1+tp_r)^4+I358*(1-MIN(tp_g/tp_roe,0.8))/(1+tp_r)^5+J358*(1-MIN(tp_g/tp_roe,0.8))/(1+tp_r)^6+J358*(1-MIN(tp_g/tp_roe,0.8))*(1+tp_g)/(tp_r-tp_g)/(1+tp_r)^6)+tp_wC*MAX(0,E407*(1-MIN(tp_g/tp_roe,0.8))/(1+tp_r)^1+F407*(1-MIN(tp_g/tp_roe,0.8))/(1+tp_r)^2+G407*(1-MIN(tp_g/tp_roe,0.8))/(1+tp_r)^3+H407*(1-MIN(tp_g/tp_roe,0.8))/(1+tp_r)^4+I407*(1-MIN(tp_g/tp_roe,0.8))/(1+tp_r)^5+J407*(1-MIN(tp_g/tp_roe,0.8))/(1+tp_r)^6+J407*(1-MIN(tp_g/tp_roe,0.8))*(1+tp_g)/(tp_r-tp_g)/(1+tp_r)^6))*(1+tp_r) -> 356.72446 | H6: =Val!$B$33*(tp_wA*(2/12*E309+10/12*F309)+tp_wB*(2/12*E358+10/12*F358)+tp_wC*(2/12*E407+10/12*F407))*rm_factor -> 759.20347 | I6: =tp_w_dcf*G6+(1-tp_w_dcf)*H6 -> 557.96397 | J6: =I6/I$4-1 -> 0.10741231
A7: LEAP 每顆內容彈性 0.3 | B7: el | C7: 封裝面積帶動較少 | D7: =E505 -> 28.223997 | E7: =F505 -> 24.446253 | F7: =E7/E$4-1 -> -0.046486096 | G7: =(tp_wA*MAX(0,E456*(1-MIN(tp_g/tp_roe,0.8))/(1+tp_r)^1+F456*(1-MIN(tp_g/tp_roe,0.8))/(1+tp_r)^2+G456*(1-MIN(tp_g/tp_roe,0.8))/(1+tp_r)^3+H456*(1-MIN(tp_g/tp_roe,0.8))/(1+tp_r)^4+I456*(1-MIN(tp_g/tp_roe,0.8))/(1+tp_r)^5+J456*(1-MIN(tp_g/tp_roe,0.8))/(1+tp_r)^6+J456*(1-MIN(tp_g/tp_roe,0.8))*(1+tp_g)/(tp_r-tp_g)/(1+tp_r)^6)+tp_wB*MAX(0,E505*(1-MIN(tp_g/tp_roe,0.8))/(1+tp_r)^1+F505*(1-MIN(tp_g/tp_roe,0.8))/(1+tp_r)^2+G505*(1-MIN(tp_g/tp_roe,0.8))/(1+tp_r)^3+H505*(1-MIN(tp_g/tp_roe,0.8))/(1+tp_r)^4+I505*(1-MIN(tp_g/tp_roe,0.8))/(1+tp_r)^5+J505*(1-MIN(tp_g/tp_roe,0.8))/(1+tp_r)^6+J505*(1-MIN(tp_g/tp_roe,0.8))*(1+tp_g)/(tp_r-tp_g)/(1+tp_r)^6)+tp_wC*MAX(0,E554*(1-MIN(tp_g/tp_roe,0.8))/(1+tp_r)^1+F554*(1-MIN(tp_g/tp_roe,0.8))/(1+tp_r)^2+G554*(1-MIN(tp_g/tp_roe,0.8))/(1+tp_r)^3+H554*(1-MIN(tp_g/tp_roe,0.8))/(1+tp_r)^4+I554*(1-MIN(tp_g/tp_roe,0.8))/(1+tp_r)^5+J554*(1-MIN(tp_g/tp_roe,0.8))/(1+tp_r)^6+J554*(1-MIN(tp_g/tp_roe,0.8))*(1+tp_g)/(tp_r-tp_g)/(1+tp_r)^6))*(1+tp_r) -> 329.76448 | H7: =Val!$B$33*(tp_wA*(2/12*E456+10/12*F456)+tp_wB*(2/12*E505+10/12*F505)+tp_wC*(2/12*E554+10/12*F554))*rm_factor -> 642.31926 | I7: =tp_w_dcf*G7+(1-tp_w_dcf)*H7 -> 486.04187 | J7: =I7/I$4-1 -> -0.035334209
A8: LEAP 每顆內容彈性 1.0 | B8: el | C8: 與面積等比例 | D8: =E652 -> 31.401996 | E8: =F652 -> 29.019524 | F8: =E8/E$4-1 -> 0.13189204 | G8: =(tp_wA*MAX(0,E603*(1-MIN(tp_g/tp_roe,0.8))/(1+tp_r)^1+F603*(1-MIN(tp_g/tp_roe,0.8))/(1+tp_r)^2+G603*(1-MIN(tp_g/tp_roe,0.8))/(1+tp_r)^3+H603*(1-MIN(tp_g/tp_roe,0.8))/(1+tp_r)^4+I603*(1-MIN(tp_g/tp_roe,0.8))/(1+tp_r)^5+J603*(1-MIN(tp_g/tp_roe,0.8))/(1+tp_r)^6+J603*(1-MIN(tp_g/tp_roe,0.8))*(1+tp_g)/(tp_r-tp_g)/(1+tp_r)^6)+tp_wB*MAX(0,E652*(1-MIN(tp_g/tp_roe,0.8))/(1+tp_r)^1+F652*(1-MIN(tp_g/tp_roe,0.8))/(1+tp_r)^2+G652*(1-MIN(tp_g/tp_roe,0.8))/(1+tp_r)^3+H652*(1-MIN(tp_g/tp_roe,0.8))/(1+tp_r)^4+I652*(1-MIN(tp_g/tp_roe,0.8))/(1+tp_r)^5+J652*(1-MIN(tp_g/tp_roe,0.8))/(1+tp_r)^6+J652*(1-MIN(tp_g/tp_roe,0.8))*(1+tp_g)/(tp_r-tp_g)/(1+tp_r)^6)+tp_wC*MAX(0,E701*(1-MIN(tp_g/tp_roe,0.8))/(1+tp_r)^1+F701*(1-MIN(tp_g/tp_roe,0.8))/(1+tp_r)^2+G701*(1-MIN(tp_g/tp_roe,0.8))/(1+tp_r)^3+H701*(1-MIN(tp_g/tp_roe,0.8))/(1+tp_r)^4+I701*(1-MIN(tp_g/tp_roe,0.8))/(1+tp_r)^5+J701*(1-MIN(tp_g/tp_roe,0.8))/(1+tp_r)^6+J701*(1-MIN(tp_g/tp_roe,0.8))*(1+tp_g)/(tp_r-tp_g)/(1+tp_r)^6))*(1+tp_r) -> 355.7263 | H8: =Val!$B$33*(tp_wA*(2/12*E603+10/12*F603)+tp_wB*(2/12*E652+10/12*F652)+tp_wC*(2/12*E701+10/12*F701))*rm_factor -> 752.55663 | I8: =tp_w_dcf*G8+(1-tp_w_dcf)*H8 -> 554.14147 | J8: =I8/I$4-1 -> 0.099825654
A9: 全流程滲透成長 10% | B9: fp_g | C9: 基準 30% | D9: =E799 -> 29.076998 | E9: =F799 -> 25.157537 | F9: =E9/E$4-1 -> -0.018742821 | G9: =(tp_wA*MAX(0,E750*(1-MIN(tp_g/tp_roe,0.8))/(1+tp_r)^1+F750*(1-MIN(tp_g/tp_roe,0.8))/(1+tp_r)^2+G750*(1-MIN(tp_g/tp_roe,0.8))/(1+tp_r)^3+H750*(1-MIN(tp_g/tp_roe,0.8))/(1+tp_r)^4+I750*(1-MIN(tp_g/tp_roe,0.8))/(1+tp_r)^5+J750*(1-MIN(tp_g/tp_roe,0.8))/(1+tp_r)^6+J750*(1-MIN(tp_g/tp_roe,0.8))*(1+tp_g)/(tp_r-tp_g)/(1+tp_r)^6)+tp_wB*MAX(0,E799*(1-MIN(tp_g/tp_roe,0.8))/(1+tp_r)^1+F799*(1-MIN(tp_g/tp_roe,0.8))/(1+tp_r)^2+G799*(1-MIN(tp_g/tp_roe,0.8))/(1+tp_r)^3+H799*(1-MIN(tp_g/tp_roe,0.8))/(1+tp_r)^4+I799*(1-MIN(tp_g/tp_roe,0.8))/(1+tp_r)^5+J799*(1-MIN(tp_g/tp_roe,0.8))/(1+tp_r)^6+J799*(1-MIN(tp_g/tp_roe,0.8))*(1+tp_g)/(tp_r-tp_g)/(1+tp_r)^6)+tp_wC*MAX(0,E848*(1-MIN(tp_g/tp_roe,0.8))/(1+tp_r)^1+F848*(1-MIN(tp_g/tp_roe,0.8))/(1+tp_r)^2+G848*(1-MIN(tp_g/tp_roe,0.8))/(1+tp_r)^3+H848*(1-MIN(tp_g/tp_roe,0.8))/(1+tp_r)^4+I848*(1-MIN(tp_g/tp_roe,0.8))/(1+tp_r)^5+J848*(1-MIN(tp_g/tp_roe,0.8))/(1+tp_r)^6+J848*(1-MIN(tp_g/tp_roe,0.8))*(1+tp_g)/(tp_r-tp_g)/(1+tp_r)^6))*(1+tp_r) -> 328.72162 | H9: =Val!$B$33*(tp_wA*(2/12*E750+10/12*F750)+tp_wB*(2/12*E799+10/12*F799)+tp_wC*(2/12*E848+10/12*F848))*rm_factor -> 660.71596 | I9: =tp_w_dcf*G9+(1-tp_w_dcf)*H9 -> 494.71879 | J9: =I9/I$4-1 -> -0.01811279
A10: 全流程滲透成長 50% | B10: fp_g | D10: =E946 -> 29.076998 | E10: =F946 -> 26.118597 | F10: =E10/E$4-1 -> 0.018742821 | G10: =(tp_wA*MAX(0,E897*(1-MIN(tp_g/tp_roe,0.8))/(1+tp_r)^1+F897*(1-MIN(tp_g/tp_roe,0.8))/(1+tp_r)^2+G897*(1-MIN(tp_g/tp_roe,0.8))/(1+tp_r)^3+H897*(1-MIN(tp_g/tp_roe,0.8))/(1+tp_r)^4+I897*(1-MIN(tp_g/tp_roe,0.8))/(1+tp_r)^5+J897*(1-MIN(tp_g/tp_roe,0.8))/(1+tp_r)^6+J897*(1-MIN(tp_g/tp_roe,0.8))*(1+tp_g)/(tp_r-tp_g)/(1+tp_r)^6)+tp_wB*MAX(0,E946*(1-MIN(tp_g/tp_roe,0.8))/(1+tp_r)^1+F946*(1-MIN(tp_g/tp_roe,0.8))/(1+tp_r)^2+G946*(1-MIN(tp_g/tp_roe,0.8))/(1+tp_r)^3+H946*(1-MIN(tp_g/tp_roe,0.8))/(1+tp_r)^4+I946*(1-MIN(tp_g/tp_roe,0.8))/(1+tp_r)^5+J946*(1-MIN(tp_g/tp_roe,0.8))/(1+tp_r)^6+J946*(1-MIN(tp_g/tp_roe,0.8))*(1+tp_g)/(tp_r-tp_g)/(1+tp_r)^6)+tp_wC*MAX(0,E995*(1-MIN(tp_g/tp_roe,0.8))/(1+tp_r)^1+F995*(1-MIN(tp_g/tp_roe,0.8))/(1+tp_r)^2+G995*(1-MIN(tp_g/tp_roe,0.8))/(1+tp_r)^3+H995*(1-MIN(tp_g/tp_roe,0.8))/(1+tp_r)^4+I995*(1-MIN(tp_g/tp_roe,0.8))/(1+tp_r)^5+J995*(1-MIN(tp_g/tp_roe,0.8))/(1+tp_r)^6+J995*(1-MIN(tp_g/tp_roe,0.8))*(1+tp_g)/(tp_r-tp_g)/(1+tp_r)^6))*(1+tp_r) -> 345.96739 | H10: =Val!$B$33*(tp_wA*(2/12*E897+10/12*F897)+tp_wB*(2/12*E946+10/12*F946)+tp_wC*(2/12*E995+10/12*F995))*rm_factor -> 681.58423 | I10: =tp_w_dcf*G10+(1-tp_w_dcf)*H10 -> 513.77581 | J10: =I10/I$4-1 -> 0.019710395
A11: CPO 2027 US$0.3B | B11: cpo27 | C11: 基準 0.5（公司逾 0.5） | D11: =E1093 -> 28.954155 | E11: =F1093 -> 25.351961 | F11: =E11/E$4-1 -> -0.011159437 | G11: =(tp_wA*MAX(0,E1044*(1-MIN(tp_g/tp_roe,0.8))/(1+tp_r)^1+F1044*(1-MIN(tp_g/tp_roe,0.8))/(1+tp_r)^2+G1044*(1-MIN(tp_g/tp_roe,0.8))/(1+tp_r)^3+H1044*(1-MIN(tp_g/tp_roe,0.8))/(1+tp_r)^4+I1044*(1-MIN(tp_g/tp_roe,0.8))/(1+tp_r)^5+J1044*(1-MIN(tp_g/tp_roe,0.8))/(1+tp_r)^6+J1044*(1-MIN(tp_g/tp_roe,0.8))*(1+tp_g)/(tp_r-tp_g)/(1+tp_r)^6)+tp_wB*MAX(0,E1093*(1-MIN(tp_g/tp_roe,0.8))/(1+tp_r)^1+F1093*(1-MIN(tp_g/tp_roe,0.8))/(1+tp_r)^2+G1093*(1-MIN(tp_g/tp_roe,0.8))/(1+tp_r)^3+H1093*(1-MIN(tp_g/tp_roe,0.8))/(1+tp_r)^4+I1093*(1-MIN(tp_g/tp_roe,0.8))/(1+tp_r)^5+J1093*(1-MIN(tp_g/tp_roe,0.8))/(1+tp_r)^6+J1093*(1-MIN(tp_g/tp_roe,0.8))*(1+tp_g)/(tp_r-tp_g)/(1+tp_r)^6)+tp_wC*MAX(0,E1142*(1-MIN(tp_g/tp_roe,0.8))/(1+tp_r)^1+F1142*(1-MIN(tp_g/tp_roe,0.8))/(1+tp_r)^2+G1142*(1-MIN(tp_g/tp_roe,0.8))/(1+tp_r)^3+H1142*(1-MIN(tp_g/tp_roe,0.8))/(1+tp_r)^4+I1142*(1-MIN(tp_g/tp_roe,0.8))/(1+tp_r)^5+J1142*(1-MIN(tp_g/tp_roe,0.8))/(1+tp_r)^6+J1142*(1-MIN(tp_g/tp_roe,0.8))*(1+tp_g)/(tp_r-tp_g)/(1+tp_r)^6))*(1+tp_r) -> 331.15807 | H11: =Val!$B$33*(tp_wA*(2/12*E1044+10/12*F1044)+tp_wB*(2/12*E1093+10/12*F1093)+tp_wC*(2/12*E1142+10/12*F1142))*rm_factor -> 661.34695 | I11: =tp_w_dcf*G11+(1-tp_w_dcf)*H11 -> 496.25251 | J11: =I11/I$4-1 -> -0.015068771
A12: CPO 2027 US$0.8B | B12: cpo27 | D12: =E1240 -> 29.261263 | E12: =F1240 -> 26.067257 | F12: =E12/E$4-1 -> 0.016740351 | G12: =(tp_wA*MAX(0,E1191*(1-MIN(tp_g/tp_roe,0.8))/(1+tp_r)^1+F1191*(1-MIN(tp_g/tp_roe,0.8))/(1+tp_r)^2+G1191*(1-MIN(tp_g/tp_roe,0.8))/(1+tp_r)^3+H1191*(1-MIN(tp_g/tp_roe,0.8))/(1+tp_r)^4+I1191*(1-MIN(tp_g/tp_roe,0.8))/(1+tp_r)^5+J1191*(1-MIN(tp_g/tp_roe,0.8))/(1+tp_r)^6+J1191*(1-MIN(tp_g/tp_roe,0.8))*(1+tp_g)/(tp_r-tp_g)/(1+tp_r)^6)+tp_wB*MAX(0,E1240*(1-MIN(tp_g/tp_roe,0.8))/(1+tp_r)^1+F1240*(1-MIN(tp_g/tp_roe,0.8))/(1+tp_r)^2+G1240*(1-MIN(tp_g/tp_roe,0.8))/(1+tp_r)^3+H1240*(1-MIN(tp_g/tp_roe,0.8))/(1+tp_r)^4+I1240*(1-MIN(tp_g/tp_roe,0.8))/(1+tp_r)^5+J1240*(1-MIN(tp_g/tp_roe,0.8))/(1+tp_r)^6+J1240*(1-MIN(tp_g/tp_roe,0.8))*(1+tp_g)/(tp_r-tp_g)/(1+tp_r)^6)+tp_wC*MAX(0,E1289*(1-MIN(tp_g/tp_roe,0.8))/(1+tp_r)^1+F1289*(1-MIN(tp_g/tp_roe,0.8))/(1+tp_r)^2+G1289*(1-MIN(tp_g/tp_roe,0.8))/(1+tp_r)^3+H1289*(1-MIN(tp_g/tp_roe,0.8))/(1+tp_r)^4+I1289*(1-MIN(tp_g/tp_roe,0.8))/(1+tp_r)^5+J1289*(1-MIN(tp_g/tp_roe,0.8))/(1+tp_r)^6+J1289*(1-MIN(tp_g/tp_roe,0.8))*(1+tp_g)/(tp_r-tp_g)/(1+tp_r)^6))*(1+tp_r) -> 344.65137 | H12: =Val!$B$33*(tp_wA*(2/12*E1191+10/12*F1191)+tp_wB*(2/12*E1240+10/12*F1240)+tp_wC*(2/12*E1289+10/12*F1289))*rm_factor -> 685.85691 | I12: =tp_w_dcf*G12+(1-tp_w_dcf)*H12 -> 515.25414 | J12: =I12/I$4-1 -> 0.022644497
A13: 主流封測 FY2027 +5% | B13: g_ms27 | C13: 基準 +15%（公司：與 2026 相近，逾 20%） | D13: =E1387 -> 25.467862 | E13: =F1387 -> 21.785888 | F13: =E13/E$4-1 -> -0.15025233 | G13: =(tp_wA*MAX(0,E1338*(1-MIN(tp_g/tp_roe,0.8))/(1+tp_r)^1+F1338*(1-MIN(tp_g/tp_roe,0.8))/(1+tp_r)^2+G1338*(1-MIN(tp_g/tp_roe,0.8))/(1+tp_r)^3+H1338*(1-MIN(tp_g/tp_roe,0.8))/(1+tp_r)^4+I1338*(1-MIN(tp_g/tp_roe,0.8))/(1+tp_r)^5+J1338*(1-MIN(tp_g/tp_roe,0.8))/(1+tp_r)^6+J1338*(1-MIN(tp_g/tp_roe,0.8))*(1+tp_g)/(tp_r-tp_g)/(1+tp_r)^6)+tp_wB*MAX(0,E1387*(1-MIN(tp_g/tp_roe,0.8))/(1+tp_r)^1+F1387*(1-MIN(tp_g/tp_roe,0.8))/(1+tp_r)^2+G1387*(1-MIN(tp_g/tp_roe,0.8))/(1+tp_r)^3+H1387*(1-MIN(tp_g/tp_roe,0.8))/(1+tp_r)^4+I1387*(1-MIN(tp_g/tp_roe,0.8))/(1+tp_r)^5+J1387*(1-MIN(tp_g/tp_roe,0.8))/(1+tp_r)^6+J1387*(1-MIN(tp_g/tp_roe,0.8))*(1+tp_g)/(tp_r-tp_g)/(1+tp_r)^6)+tp_wC*MAX(0,E1436*(1-MIN(tp_g/tp_roe,0.8))/(1+tp_r)^1+F1436*(1-MIN(tp_g/tp_roe,0.8))/(1+tp_r)^2+G1436*(1-MIN(tp_g/tp_roe,0.8))/(1+tp_r)^3+H1436*(1-MIN(tp_g/tp_roe,0.8))/(1+tp_r)^4+I1436*(1-MIN(tp_g/tp_roe,0.8))/(1+tp_r)^5+J1436*(1-MIN(tp_g/tp_roe,0.8))/(1+tp_r)^6+J1436*(1-MIN(tp_g/tp_roe,0.8))*(1+tp_g)/(tp_r-tp_g)/(1+tp_r)^6))*(1+tp_r) -> 318.71198 | H13: =Val!$B$33*(tp_wA*(2/12*E1338+10/12*F1338)+tp_wB*(2/12*E1387+10/12*F1387)+tp_wC*(2/12*E1436+10/12*F1436))*rm_factor -> 577.00723 | I13: =tp_w_dcf*G13+(1-tp_w_dcf)*H13 -> 447.85961 | J13: =I13/I$4-1 -> -0.111116
A14: 主流封測 FY2027 +22% | B14: g_ms27 | D14: =E1534 -> 31.603393 | E14: =F1534 -> 28.334718 | F14: =E14/E$4-1 -> 0.10518153 | G14: =(tp_wA*MAX(0,E1485*(1-MIN(tp_g/tp_roe,0.8))/(1+tp_r)^1+F1485*(1-MIN(tp_g/tp_roe,0.8))/(1+tp_r)^2+G1485*(1-MIN(tp_g/tp_roe,0.8))/(1+tp_r)^3+H1485*(1-MIN(tp_g/tp_roe,0.8))/(1+tp_r)^4+I1485*(1-MIN(tp_g/tp_roe,0.8))/(1+tp_r)^5+J1485*(1-MIN(tp_g/tp_roe,0.8))/(1+tp_r)^6+J1485*(1-MIN(tp_g/tp_roe,0.8))*(1+tp_g)/(tp_r-tp_g)/(1+tp_r)^6)+tp_wB*MAX(0,E1534*(1-MIN(tp_g/tp_roe,0.8))/(1+tp_r)^1+F1534*(1-MIN(tp_g/tp_roe,0.8))/(1+tp_r)^2+G1534*(1-MIN(tp_g/tp_roe,0.8))/(1+tp_r)^3+H1534*(1-MIN(tp_g/tp_roe,0.8))/(1+tp_r)^4+I1534*(1-MIN(tp_g/tp_roe,0.8))/(1+tp_r)^5+J1534*(1-MIN(tp_g/tp_roe,0.8))/(1+tp_r)^6+J1534*(1-MIN(tp_g/tp_roe,0.8))*(1+tp_g)/(tp_r-tp_g)/(1+tp_r)^6)+tp_wC*MAX(0,E1583*(1-MIN(tp_g/tp_roe,0.8))/(1+tp_r)^1+F1583*(1-MIN(tp_g/tp_roe,0.8))/(1+tp_r)^2+G1583*(1-MIN(tp_g/tp_roe,0.8))/(1+tp_r)^3+H1583*(1-MIN(tp_g/tp_roe,0.8))/(1+tp_r)^4+I1583*(1-MIN(tp_g/tp_roe,0.8))/(1+tp_r)^5+J1583*(1-MIN(tp_g/tp_roe,0.8))/(1+tp_r)^6+J1583*(1-MIN(tp_g/tp_roe,0.8))*(1+tp_g)/(tp_r-tp_g)/(1+tp_r)^6))*(1+tp_r) -> 349.01812 | H14: =Val!$B$33*(tp_wA*(2/12*E1485+10/12*F1485)+tp_wB*(2/12*E1534+10/12*F1534)+tp_wC*(2/12*E1583+10/12*F1583))*rm_factor -> 737.05161 | I14: =tp_w_dcf*G14+(1-tp_w_dcf)*H14 -> 543.03487 | J14: =I14/I$4-1 -> 0.077781957
A15: 主流封測 FY2028–29 +2% | B15: g_msL | C15: 基準 +7% | D15: =E1681 -> 29.076998 | E15: =F1681 -> 23.552447 | F15: =E15/E$4-1 -> -0.081348574 | G15: =(tp_wA*MAX(0,E1632*(1-MIN(tp_g/tp_roe,0.8))/(1+tp_r)^1+F1632*(1-MIN(tp_g/tp_roe,0.8))/(1+tp_r)^2+G1632*(1-MIN(tp_g/tp_roe,0.8))/(1+tp_r)^3+H1632*(1-MIN(tp_g/tp_roe,0.8))/(1+tp_r)^4+I1632*(1-MIN(tp_g/tp_roe,0.8))/(1+tp_r)^5+J1632*(1-MIN(tp_g/tp_roe,0.8))/(1+tp_r)^6+J1632*(1-MIN(tp_g/tp_roe,0.8))*(1+tp_g)/(tp_r-tp_g)/(1+tp_r)^6)+tp_wB*MAX(0,E1681*(1-MIN(tp_g/tp_roe,0.8))/(1+tp_r)^1+F1681*(1-MIN(tp_g/tp_roe,0.8))/(1+tp_r)^2+G1681*(1-MIN(tp_g/tp_roe,0.8))/(1+tp_r)^3+H1681*(1-MIN(tp_g/tp_roe,0.8))/(1+tp_r)^4+I1681*(1-MIN(tp_g/tp_roe,0.8))/(1+tp_r)^5+J1681*(1-MIN(tp_g/tp_roe,0.8))/(1+tp_r)^6+J1681*(1-MIN(tp_g/tp_roe,0.8))*(1+tp_g)/(tp_r-tp_g)/(1+tp_r)^6)+tp_wC*MAX(0,E1730*(1-MIN(tp_g/tp_roe,0.8))/(1+tp_r)^1+F1730*(1-MIN(tp_g/tp_roe,0.8))/(1+tp_r)^2+G1730*(1-MIN(tp_g/tp_roe,0.8))/(1+tp_r)^3+H1730*(1-MIN(tp_g/tp_roe,0.8))/(1+tp_r)^4+I1730*(1-MIN(tp_g/tp_roe,0.8))/(1+tp_r)^5+J1730*(1-MIN(tp_g/tp_roe,0.8))/(1+tp_r)^6+J1730*(1-MIN(tp_g/tp_roe,0.8))*(1+tp_g)/(tp_r-tp_g)/(1+tp_r)^6))*(1+tp_r) -> 315.45315 | H15: =Val!$B$33*(tp_wA*(2/12*E1632+10/12*F1632)+tp_wB*(2/12*E1681+10/12*F1681)+tp_wC*(2/12*E1730+10/12*F1730))*rm_factor -> 628.23214 | I15: =tp_w_dcf*G15+(1-tp_w_dcf)*H15 -> 471.84264 | J15: =I15/I$4-1 -> -0.063515951
A16: 主流封測 FY2028–29 +12% | B16: g_msL | D16: =E1828 -> 29.076998 | E16: =F1828 -> 27.723687 | F16: =E16/E$4-1 -> 0.081348574 | G16: =(tp_wA*MAX(0,E1779*(1-MIN(tp_g/tp_roe,0.8))/(1+tp_r)^1+F1779*(1-MIN(tp_g/tp_roe,0.8))/(1+tp_r)^2+G1779*(1-MIN(tp_g/tp_roe,0.8))/(1+tp_r)^3+H1779*(1-MIN(tp_g/tp_roe,0.8))/(1+tp_r)^4+I1779*(1-MIN(tp_g/tp_roe,0.8))/(1+tp_r)^5+J1779*(1-MIN(tp_g/tp_roe,0.8))/(1+tp_r)^6+J1779*(1-MIN(tp_g/tp_roe,0.8))*(1+tp_g)/(tp_r-tp_g)/(1+tp_r)^6)+tp_wB*MAX(0,E1828*(1-MIN(tp_g/tp_roe,0.8))/(1+tp_r)^1+F1828*(1-MIN(tp_g/tp_roe,0.8))/(1+tp_r)^2+G1828*(1-MIN(tp_g/tp_roe,0.8))/(1+tp_r)^3+H1828*(1-MIN(tp_g/tp_roe,0.8))/(1+tp_r)^4+I1828*(1-MIN(tp_g/tp_roe,0.8))/(1+tp_r)^5+J1828*(1-MIN(tp_g/tp_roe,0.8))/(1+tp_r)^6+J1828*(1-MIN(tp_g/tp_roe,0.8))*(1+tp_g)/(tp_r-tp_g)/(1+tp_r)^6)+tp_wC*MAX(0,E1877*(1-MIN(tp_g/tp_roe,0.8))/(1+tp_r)^1+F1877*(1-MIN(tp_g/tp_roe,0.8))/(1+tp_r)^2+G1877*(1-MIN(tp_g/tp_roe,0.8))/(1+tp_r)^3+H1877*(1-MIN(tp_g/tp_roe,0.8))/(1+tp_r)^4+I1877*(1-MIN(tp_g/tp_roe,0.8))/(1+tp_r)^5+J1877*(1-MIN(tp_g/tp_roe,0.8))/(1+tp_r)^6+J1877*(1-MIN(tp_g/tp_roe,0.8))*(1+tp_g)/(tp_r-tp_g)/(1+tp_r)^6))*(1+tp_r) -> 359.19432 | H16: =Val!$B$33*(tp_wA*(2/12*E1779+10/12*F1779)+tp_wB*(2/12*E1828+10/12*F1828)+tp_wC*(2/12*E1877+10/12*F1877))*rm_factor -> 714.06806 | I16: =tp_w_dcf*G16+(1-tp_w_dcf)*H16 -> 536.63119 | J16: =I16/I$4-1 -> 0.065072334
A17: EMS FY2027 0% | B17: g_ems27 | C17: 基準 +10% | D17: =E1975 -> 28.903993 | E17: =F1975 -> 25.450756 | F17: =E17/E$4-1 -> -0.0073059537 | G17: =(tp_wA*MAX(0,E1926*(1-MIN(tp_g/tp_roe,0.8))/(1+tp_r)^1+F1926*(1-MIN(tp_g/tp_roe,0.8))/(1+tp_r)^2+G1926*(1-MIN(tp_g/tp_roe,0.8))/(1+tp_r)^3+H1926*(1-MIN(tp_g/tp_roe,0.8))/(1+tp_r)^4+I1926*(1-MIN(tp_g/tp_roe,0.8))/(1+tp_r)^5+J1926*(1-MIN(tp_g/tp_roe,0.8))/(1+tp_r)^6+J1926*(1-MIN(tp_g/tp_roe,0.8))*(1+tp_g)/(tp_r-tp_g)/(1+tp_r)^6)+tp_wB*MAX(0,E1975*(1-MIN(tp_g/tp_roe,0.8))/(1+tp_r)^1+F1975*(1-MIN(tp_g/tp_roe,0.8))/(1+tp_r)^2+G1975*(1-MIN(tp_g/tp_roe,0.8))/(1+tp_r)^3+H1975*(1-MIN(tp_g/tp_roe,0.8))/(1+tp_r)^4+I1975*(1-MIN(tp_g/tp_roe,0.8))/(1+tp_r)^5+J1975*(1-MIN(tp_g/tp_roe,0.8))/(1+tp_r)^6+J1975*(1-MIN(tp_g/tp_roe,0.8))*(1+tp_g)/(tp_r-tp_g)/(1+tp_r)^6)+tp_wC*MAX(0,E2024*(1-MIN(tp_g/tp_roe,0.8))/(1+tp_r)^1+F2024*(1-MIN(tp_g/tp_roe,0.8))/(1+tp_r)^2+G2024*(1-MIN(tp_g/tp_roe,0.8))/(1+tp_r)^3+H2024*(1-MIN(tp_g/tp_roe,0.8))/(1+tp_r)^4+I2024*(1-MIN(tp_g/tp_roe,0.8))/(1+tp_r)^5+J2024*(1-MIN(tp_g/tp_roe,0.8))/(1+tp_r)^6+J2024*(1-MIN(tp_g/tp_roe,0.8))*(1+tp_g)/(tp_r-tp_g)/(1+tp_r)^6))*(1+tp_r) -> 329.79039 | H17: =Val!$B$33*(tp_wA*(2/12*E1926+10/12*F1926)+tp_wB*(2/12*E1975+10/12*F1975)+tp_wC*(2/12*E2024+10/12*F2024))*rm_factor -> 666.56553 | I17: =tp_w_dcf*G17+(1-tp_w_dcf)*H17 -> 498.17796 | J17: =I17/I$4-1 -> -0.011247246
A18: EMS FY2027 +15% | B18: g_ems27 | D18: =E2122 -> 29.1635 | E18: =F2122 -> 25.73172 | F18: =E18/E$4-1 -> 0.0036528732 | G18: =(tp_wA*MAX(0,E2073*(1-MIN(tp_g/tp_roe,0.8))/(1+tp_r)^1+F2073*(1-MIN(tp_g/tp_roe,0.8))/(1+tp_r)^2+G2073*(1-MIN(tp_g/tp_roe,0.8))/(1+tp_r)^3+H2073*(1-MIN(tp_g/tp_roe,0.8))/(1+tp_r)^4+I2073*(1-MIN(tp_g/tp_roe,0.8))/(1+tp_r)^5+J2073*(1-MIN(tp_g/tp_roe,0.8))/(1+tp_r)^6+J2073*(1-MIN(tp_g/tp_roe,0.8))*(1+tp_g)/(tp_r-tp_g)/(1+tp_r)^6)+tp_wB*MAX(0,E2122*(1-MIN(tp_g/tp_roe,0.8))/(1+tp_r)^1+F2122*(1-MIN(tp_g/tp_roe,0.8))/(1+tp_r)^2+G2122*(1-MIN(tp_g/tp_roe,0.8))/(1+tp_r)^3+H2122*(1-MIN(tp_g/tp_roe,0.8))/(1+tp_r)^4+I2122*(1-MIN(tp_g/tp_roe,0.8))/(1+tp_r)^5+J2122*(1-MIN(tp_g/tp_roe,0.8))/(1+tp_r)^6+J2122*(1-MIN(tp_g/tp_roe,0.8))*(1+tp_g)/(tp_r-tp_g)/(1+tp_r)^6)+tp_wC*MAX(0,E2171*(1-MIN(tp_g/tp_roe,0.8))/(1+tp_r)^1+F2171*(1-MIN(tp_g/tp_roe,0.8))/(1+tp_r)^2+G2171*(1-MIN(tp_g/tp_roe,0.8))/(1+tp_r)^3+H2171*(1-MIN(tp_g/tp_roe,0.8))/(1+tp_r)^4+I2171*(1-MIN(tp_g/tp_roe,0.8))/(1+tp_r)^5+J2171*(1-MIN(tp_g/tp_roe,0.8))/(1+tp_r)^6+J2171*(1-MIN(tp_g/tp_roe,0.8))*(1+tp_g)/(tp_r-tp_g)/(1+tp_r)^6))*(1+tp_r) -> 339.91522 | H18: =Val!$B$33*(tp_wA*(2/12*E2073+10/12*F2073)+tp_wB*(2/12*E2122+10/12*F2122)+tp_wC*(2/12*E2171+10/12*F2171))*rm_factor -> 673.44197 | I18: =tp_w_dcf*G18+(1-tp_w_dcf)*H18 -> 506.6786 | J18: =I18/I$4-1 -> 0.0056242885
A19: EMS FY2028–29 0% | B19: g_emsL | C19: 基準 +5% | D19: =E2269 -> 29.076998 | E19: =F2269 -> 25.528979 | F19: =E19/E$4-1 -> -0.004254924 | G19: =(tp_wA*MAX(0,E2220*(1-MIN(tp_g/tp_roe,0.8))/(1+tp_r)^1+F2220*(1-MIN(tp_g/tp_roe,0.8))/(1+tp_r)^2+G2220*(1-MIN(tp_g/tp_roe,0.8))/(1+tp_r)^3+H2220*(1-MIN(tp_g/tp_roe,0.8))/(1+tp_r)^4+I2220*(1-MIN(tp_g/tp_roe,0.8))/(1+tp_r)^5+J2220*(1-MIN(tp_g/tp_roe,0.8))/(1+tp_r)^6+J2220*(1-MIN(tp_g/tp_roe,0.8))*(1+tp_g)/(tp_r-tp_g)/(1+tp_r)^6)+tp_wB*MAX(0,E2269*(1-MIN(tp_g/tp_roe,0.8))/(1+tp_r)^1+F2269*(1-MIN(tp_g/tp_roe,0.8))/(1+tp_r)^2+G2269*(1-MIN(tp_g/tp_roe,0.8))/(1+tp_r)^3+H2269*(1-MIN(tp_g/tp_roe,0.8))/(1+tp_r)^4+I2269*(1-MIN(tp_g/tp_roe,0.8))/(1+tp_r)^5+J2269*(1-MIN(tp_g/tp_roe,0.8))/(1+tp_r)^6+J2269*(1-MIN(tp_g/tp_roe,0.8))*(1+tp_g)/(tp_r-tp_g)/(1+tp_r)^6)+tp_wC*MAX(0,E2318*(1-MIN(tp_g/tp_roe,0.8))/(1+tp_r)^1+F2318*(1-MIN(tp_g/tp_roe,0.8))/(1+tp_r)^2+G2318*(1-MIN(tp_g/tp_roe,0.8))/(1+tp_r)^3+H2318*(1-MIN(tp_g/tp_roe,0.8))/(1+tp_r)^4+I2318*(1-MIN(tp_g/tp_roe,0.8))/(1+tp_r)^5+J2318*(1-MIN(tp_g/tp_roe,0.8))/(1+tp_r)^6+J2318*(1-MIN(tp_g/tp_roe,0.8))*(1+tp_g)/(tp_r-tp_g)/(1+tp_r)^6))*(1+tp_r) -> 325.68723 | H19: =Val!$B$33*(tp_wA*(2/12*E2220+10/12*F2220)+tp_wB*(2/12*E2269+10/12*F2269)+tp_wC*(2/12*E2318+10/12*F2318))*rm_factor -> 668.90327 | I19: =tp_w_dcf*G19+(1-tp_w_dcf)*H19 -> 497.29525 | J19: =I19/I$4-1 -> -0.012999202
A20: EMS FY2028–29 +8% | B20: g_emsL | D20: =E2416 -> 29.076998 | E20: =F2416 -> 25.70352 | F20: =E20/E$4-1 -> 0.0025529544 | G20: =(tp_wA*MAX(0,E2367*(1-MIN(tp_g/tp_roe,0.8))/(1+tp_r)^1+F2367*(1-MIN(tp_g/tp_roe,0.8))/(1+tp_r)^2+G2367*(1-MIN(tp_g/tp_roe,0.8))/(1+tp_r)^3+H2367*(1-MIN(tp_g/tp_roe,0.8))/(1+tp_r)^4+I2367*(1-MIN(tp_g/tp_roe,0.8))/(1+tp_r)^5+J2367*(1-MIN(tp_g/tp_roe,0.8))/(1+tp_r)^6+J2367*(1-MIN(tp_g/tp_roe,0.8))*(1+tp_g)/(tp_r-tp_g)/(1+tp_r)^6)+tp_wB*MAX(0,E2416*(1-MIN(tp_g/tp_roe,0.8))/(1+tp_r)^1+F2416*(1-MIN(tp_g/tp_roe,0.8))/(1+tp_r)^2+G2416*(1-MIN(tp_g/tp_roe,0.8))/(1+tp_r)^3+H2416*(1-MIN(tp_g/tp_roe,0.8))/(1+tp_r)^4+I2416*(1-MIN(tp_g/tp_roe,0.8))/(1+tp_r)^5+J2416*(1-MIN(tp_g/tp_roe,0.8))/(1+tp_r)^6+J2416*(1-MIN(tp_g/tp_roe,0.8))*(1+tp_g)/(tp_r-tp_g)/(1+tp_r)^6)+tp_wC*MAX(0,E2465*(1-MIN(tp_g/tp_roe,0.8))/(1+tp_r)^1+F2465*(1-MIN(tp_g/tp_roe,0.8))/(1+tp_r)^2+G2465*(1-MIN(tp_g/tp_roe,0.8))/(1+tp_r)^3+H2465*(1-MIN(tp_g/tp_roe,0.8))/(1+tp_r)^4+I2465*(1-MIN(tp_g/tp_roe,0.8))/(1+tp_r)^5+J2465*(1-MIN(tp_g/tp_roe,0.8))/(1+tp_r)^6+J2465*(1-MIN(tp_g/tp_roe,0.8))*(1+tp_g)/(tp_r-tp_g)/(1+tp_r)^6))*(1+tp_r) -> 343.45741 | H20: =Val!$B$33*(tp_wA*(2/12*E2367+10/12*F2367)+tp_wB*(2/12*E2416+10/12*F2416)+tp_wC*(2/12*E2465+10/12*F2465))*rm_factor -> 672.49819 | I20: =tp_w_dcf*G20+(1-tp_w_dcf)*H20 -> 507.9778 | J20: =I20/I$4-1 -> 0.0082028676
A21: EMS 毛利率 7.5% | B21: ems_gm | C21: 基準 8.5% | D21: =E2563 -> 28.426397 | E21: =F2563 -> 24.958334 | F21: =E21/E$4-1 -> -0.026512625 | G21: =(tp_wA*MAX(0,E2514*(1-MIN(tp_g/tp_roe,0.8))/(1+tp_r)^1+F2514*(1-MIN(tp_g/tp_roe,0.8))/(1+tp_r)^2+G2514*(1-MIN(tp_g/tp_roe,0.8))/(1+tp_r)^3+H2514*(1-MIN(tp_g/tp_roe,0.8))/(1+tp_r)^4+I2514*(1-MIN(tp_g/tp_roe,0.8))/(1+tp_r)^5+J2514*(1-MIN(tp_g/tp_roe,0.8))/(1+tp_r)^6+J2514*(1-MIN(tp_g/tp_roe,0.8))*(1+tp_g)/(tp_r-tp_g)/(1+tp_r)^6)+tp_wB*MAX(0,E2563*(1-MIN(tp_g/tp_roe,0.8))/(1+tp_r)^1+F2563*(1-MIN(tp_g/tp_roe,0.8))/(1+tp_r)^2+G2563*(1-MIN(tp_g/tp_roe,0.8))/(1+tp_r)^3+H2563*(1-MIN(tp_g/tp_roe,0.8))/(1+tp_r)^4+I2563*(1-MIN(tp_g/tp_roe,0.8))/(1+tp_r)^5+J2563*(1-MIN(tp_g/tp_roe,0.8))/(1+tp_r)^6+J2563*(1-MIN(tp_g/tp_roe,0.8))*(1+tp_g)/(tp_r-tp_g)/(1+tp_r)^6)+tp_wC*MAX(0,E2612*(1-MIN(tp_g/tp_roe,0.8))/(1+tp_r)^1+F2612*(1-MIN(tp_g/tp_roe,0.8))/(1+tp_r)^2+G2612*(1-MIN(tp_g/tp_roe,0.8))/(1+tp_r)^3+H2612*(1-MIN(tp_g/tp_roe,0.8))/(1+tp_r)^4+I2612*(1-MIN(tp_g/tp_roe,0.8))/(1+tp_r)^5+J2612*(1-MIN(tp_g/tp_roe,0.8))/(1+tp_r)^6+J2612*(1-MIN(tp_g/tp_roe,0.8))*(1+tp_g)/(tp_r-tp_g)/(1+tp_r)^6))*(1+tp_r) -> 335.03384 | H21: =Val!$B$33*(tp_wA*(2/12*E2514+10/12*F2514)+tp_wB*(2/12*E2563+10/12*F2563)+tp_wC*(2/12*E2612+10/12*F2612))*rm_factor -> 654.48613 | I21: =tp_w_dcf*G21+(1-tp_w_dcf)*H21 -> 494.75998 | J21: =I21/I$4-1 -> -0.018031036
A22: EMS 毛利率 9.5% | B22: ems_gm | D22: =E2710 -> 29.727599 | E22: =F2710 -> 26.317799 | F22: =E22/E$4-1 -> 0.026512625 | G22: =(tp_wA*MAX(0,E2661*(1-MIN(tp_g/tp_roe,0.8))/(1+tp_r)^1+F2661*(1-MIN(tp_g/tp_roe,0.8))/(1+tp_r)^2+G2661*(1-MIN(tp_g/tp_roe,0.8))/(1+tp_r)^3+H2661*(1-MIN(tp_g/tp_roe,0.8))/(1+tp_r)^4+I2661*(1-MIN(tp_g/tp_roe,0.8))/(1+tp_r)^5+J2661*(1-MIN(tp_g/tp_roe,0.8))/(1+tp_r)^6+J2661*(1-MIN(tp_g/tp_roe,0.8))*(1+tp_g)/(tp_r-tp_g)/(1+tp_r)^6)+tp_wB*MAX(0,E2710*(1-MIN(tp_g/tp_roe,0.8))/(1+tp_r)^1+F2710*(1-MIN(tp_g/tp_roe,0.8))/(1+tp_r)^2+G2710*(1-MIN(tp_g/tp_roe,0.8))/(1+tp_r)^3+H2710*(1-MIN(tp_g/tp_roe,0.8))/(1+tp_r)^4+I2710*(1-MIN(tp_g/tp_roe,0.8))/(1+tp_r)^5+J2710*(1-MIN(tp_g/tp_roe,0.8))/(1+tp_r)^6+J2710*(1-MIN(tp_g/tp_roe,0.8))*(1+tp_g)/(tp_r-tp_g)/(1+tp_r)^6)+tp_wC*MAX(0,E2759*(1-MIN(tp_g/tp_roe,0.8))/(1+tp_r)^1+F2759*(1-MIN(tp_g/tp_roe,0.8))/(1+tp_r)^2+G2759*(1-MIN(tp_g/tp_roe,0.8))/(1+tp_r)^3+H2759*(1-MIN(tp_g/tp_roe,0.8))/(1+tp_r)^4+I2759*(1-MIN(tp_g/tp_roe,0.8))/(1+tp_r)^5+J2759*(1-MIN(tp_g/tp_roe,0.8))/(1+tp_r)^6+J2759*(1-MIN(tp_g/tp_roe,0.8))*(1+tp_g)/(tp_r-tp_g)/(1+tp_r)^6))*(1+tp_r) -> 338.04528 | H22: =Val!$B$33*(tp_wA*(2/12*E2661+10/12*F2661)+tp_wB*(2/12*E2710+10/12*F2710)+tp_wC*(2/12*E2759+10/12*F2759))*rm_factor -> 687.81406 | I22: =tp_w_dcf*G22+(1-tp_w_dcf)*H22 -> 512.92967 | J22: =I22/I$4-1 -> 0.018031036
A23: 匯率 30.5 | B23: fx | C23: Siliconomics fx_twd 低 | D23: =E2857 -> 28.079361 | E23: =F2857 -> 25.0832 | F23: =E23/E$4-1 -> -0.021642296 | G23: =(tp_wA*MAX(0,E2808*(1-MIN(tp_g/tp_roe,0.8))/(1+tp_r)^1+F2808*(1-MIN(tp_g/tp_roe,0.8))/(1+tp_r)^2+G2808*(1-MIN(tp_g/tp_roe,0.8))/(1+tp_r)^3+H2808*(1-MIN(tp_g/tp_roe,0.8))/(1+tp_r)^4+I2808*(1-MIN(tp_g/tp_roe,0.8))/(1+tp_r)^5+J2808*(1-MIN(tp_g/tp_roe,0.8))/(1+tp_r)^6+J2808*(1-MIN(tp_g/tp_roe,0.8))*(1+tp_g)/(tp_r-tp_g)/(1+tp_r)^6)+tp_wB*MAX(0,E2857*(1-MIN(tp_g/tp_roe,0.8))/(1+tp_r)^1+F2857*(1-MIN(tp_g/tp_roe,0.8))/(1+tp_r)^2+G2857*(1-MIN(tp_g/tp_roe,0.8))/(1+tp_r)^3+H2857*(1-MIN(tp_g/tp_roe,0.8))/(1+tp_r)^4+I2857*(1-MIN(tp_g/tp_roe,0.8))/(1+tp_r)^5+J2857*(1-MIN(tp_g/tp_roe,0.8))/(1+tp_r)^6+J2857*(1-MIN(tp_g/tp_roe,0.8))*(1+tp_g)/(tp_r-tp_g)/(1+tp_r)^6)+tp_wC*MAX(0,E2906*(1-MIN(tp_g/tp_roe,0.8))/(1+tp_r)^1+F2906*(1-MIN(tp_g/tp_roe,0.8))/(1+tp_r)^2+G2906*(1-MIN(tp_g/tp_roe,0.8))/(1+tp_r)^3+H2906*(1-MIN(tp_g/tp_roe,0.8))/(1+tp_r)^4+I2906*(1-MIN(tp_g/tp_roe,0.8))/(1+tp_r)^5+J2906*(1-MIN(tp_g/tp_roe,0.8))/(1+tp_r)^6+J2906*(1-MIN(tp_g/tp_roe,0.8))*(1+tp_g)/(tp_r-tp_g)/(1+tp_r)^6))*(1+tp_r) -> 330.5268 | H23: =Val!$B$33*(tp_wA*(2/12*E2808+10/12*F2808)+tp_wB*(2/12*E2857+10/12*F2857)+tp_wC*(2/12*E2906+10/12*F2906))*rm_factor -> 654.49576 | I23: =tp_w_dcf*G23+(1-tp_w_dcf)*H23 -> 492.51128 | J23: =I23/I$4-1 -> -0.022494119
A24: 匯率 33 | B24: fx | C24: Siliconomics fx_twd 高 | D24: =E3004 -> 29.742089 | E24: =F3004 -> 26.007961 | F24: =E24/E$4-1 -> 0.014427552 | G24: =(tp_wA*MAX(0,E2955*(1-MIN(tp_g/tp_roe,0.8))/(1+tp_r)^1+F2955*(1-MIN(tp_g/tp_roe,0.8))/(1+tp_r)^2+G2955*(1-MIN(tp_g/tp_roe,0.8))/(1+tp_r)^3+H2955*(1-MIN(tp_g/tp_roe,0.8))/(1+tp_r)^4+I2955*(1-MIN(tp_g/tp_roe,0.8))/(1+tp_r)^5+J2955*(1-MIN(tp_g/tp_roe,0.8))/(1+tp_r)^6+J2955*(1-MIN(tp_g/tp_roe,0.8))*(1+tp_g)/(tp_r-tp_g)/(1+tp_r)^6)+tp_wB*MAX(0,E3004*(1-MIN(tp_g/tp_roe,0.8))/(1+tp_r)^1+F3004*(1-MIN(tp_g/tp_roe,0.8))/(1+tp_r)^2+G3004*(1-MIN(tp_g/tp_roe,0.8))/(1+tp_r)^3+H3004*(1-MIN(tp_g/tp_roe,0.8))/(1+tp_r)^4+I3004*(1-MIN(tp_g/tp_roe,0.8))/(1+tp_r)^5+J3004*(1-MIN(tp_g/tp_roe,0.8))/(1+tp_r)^6+J3004*(1-MIN(tp_g/tp_roe,0.8))*(1+tp_g)/(tp_r-tp_g)/(1+tp_r)^6)+tp_wC*MAX(0,E3053*(1-MIN(tp_g/tp_roe,0.8))/(1+tp_r)^1+F3053*(1-MIN(tp_g/tp_roe,0.8))/(1+tp_r)^2+G3053*(1-MIN(tp_g/tp_roe,0.8))/(1+tp_r)^3+H3053*(1-MIN(tp_g/tp_roe,0.8))/(1+tp_r)^4+I3053*(1-MIN(tp_g/tp_roe,0.8))/(1+tp_r)^5+J3053*(1-MIN(tp_g/tp_roe,0.8))/(1+tp_r)^6+J3053*(1-MIN(tp_g/tp_roe,0.8))*(1+tp_g)/(tp_r-tp_g)/(1+tp_r)^6))*(1+tp_r) -> 340.5499 | H24: =Val!$B$33*(tp_wA*(2/12*E2955+10/12*F2955)+tp_wB*(2/12*E3004+10/12*F3004)+tp_wC*(2/12*E3053+10/12*F3053))*rm_factor -> 682.253 | I24: =tp_w_dcf*G24+(1-tp_w_dcf)*H24 -> 511.40145 | J24: =I24/I$4-1 -> 0.014997908
A25: 資本支出 FY2027 US$11.5B | B25: capex27 | C25: 基準 13.0 | D25: =E3151 -> 29.076998 | E25: =F3151 -> 26.760462 | F25: =E25/E$4-1 -> 0.043778464 | G25: =(tp_wA*MAX(0,E3102*(1-MIN(tp_g/tp_roe,0.8))/(1+tp_r)^1+F3102*(1-MIN(tp_g/tp_roe,0.8))/(1+tp_r)^2+G3102*(1-MIN(tp_g/tp_roe,0.8))/(1+tp_r)^3+H3102*(1-MIN(tp_g/tp_roe,0.8))/(1+tp_r)^4+I3102*(1-MIN(tp_g/tp_roe,0.8))/(1+tp_r)^5+J3102*(1-MIN(tp_g/tp_roe,0.8))/(1+tp_r)^6+J3102*(1-MIN(tp_g/tp_roe,0.8))*(1+tp_g)/(tp_r-tp_g)/(1+tp_r)^6)+tp_wB*MAX(0,E3151*(1-MIN(tp_g/tp_roe,0.8))/(1+tp_r)^1+F3151*(1-MIN(tp_g/tp_roe,0.8))/(1+tp_r)^2+G3151*(1-MIN(tp_g/tp_roe,0.8))/(1+tp_r)^3+H3151*(1-MIN(tp_g/tp_roe,0.8))/(1+tp_r)^4+I3151*(1-MIN(tp_g/tp_roe,0.8))/(1+tp_r)^5+J3151*(1-MIN(tp_g/tp_roe,0.8))/(1+tp_r)^6+J3151*(1-MIN(tp_g/tp_roe,0.8))*(1+tp_g)/(tp_r-tp_g)/(1+tp_r)^6)+tp_wC*MAX(0,E3200*(1-MIN(tp_g/tp_roe,0.8))/(1+tp_r)^1+F3200*(1-MIN(tp_g/tp_roe,0.8))/(1+tp_r)^2+G3200*(1-MIN(tp_g/tp_roe,0.8))/(1+tp_r)^3+H3200*(1-MIN(tp_g/tp_roe,0.8))/(1+tp_r)^4+I3200*(1-MIN(tp_g/tp_roe,0.8))/(1+tp_r)^5+J3200*(1-MIN(tp_g/tp_roe,0.8))/(1+tp_r)^6+J3200*(1-MIN(tp_g/tp_roe,0.8))*(1+tp_g)/(tp_r-tp_g)/(1+tp_r)^6))*(1+tp_r) -> 338.16168 | H25: =Val!$B$33*(tp_wA*(2/12*E3102+10/12*F3102)+tp_wB*(2/12*E3151+10/12*F3151)+tp_wC*(2/12*E3200+10/12*F3200))*rm_factor -> 694.2451 | I25: =tp_w_dcf*G25+(1-tp_w_dcf)*H25 -> 516.20339 | J25: =I25/I$4-1 -> 0.024528509
A26: 資本支出 FY2027 US$15B | B26: capex27 | D26: =E3298 -> 29.076998 | E26: =F3298 -> 24.14154 | F26: =E26/E$4-1 -> -0.058371286 | G26: =(tp_wA*MAX(0,E3249*(1-MIN(tp_g/tp_roe,0.8))/(1+tp_r)^1+F3249*(1-MIN(tp_g/tp_roe,0.8))/(1+tp_r)^2+G3249*(1-MIN(tp_g/tp_roe,0.8))/(1+tp_r)^3+H3249*(1-MIN(tp_g/tp_roe,0.8))/(1+tp_r)^4+I3249*(1-MIN(tp_g/tp_roe,0.8))/(1+tp_r)^5+J3249*(1-MIN(tp_g/tp_roe,0.8))/(1+tp_r)^6+J3249*(1-MIN(tp_g/tp_roe,0.8))*(1+tp_g)/(tp_r-tp_g)/(1+tp_r)^6)+tp_wB*MAX(0,E3298*(1-MIN(tp_g/tp_roe,0.8))/(1+tp_r)^1+F3298*(1-MIN(tp_g/tp_roe,0.8))/(1+tp_r)^2+G3298*(1-MIN(tp_g/tp_roe,0.8))/(1+tp_r)^3+H3298*(1-MIN(tp_g/tp_roe,0.8))/(1+tp_r)^4+I3298*(1-MIN(tp_g/tp_roe,0.8))/(1+tp_r)^5+J3298*(1-MIN(tp_g/tp_roe,0.8))/(1+tp_r)^6+J3298*(1-MIN(tp_g/tp_roe,0.8))*(1+tp_g)/(tp_r-tp_g)/(1+tp_r)^6)+tp_wC*MAX(0,E3347*(1-MIN(tp_g/tp_roe,0.8))/(1+tp_r)^1+F3347*(1-MIN(tp_g/tp_roe,0.8))/(1+tp_r)^2+G3347*(1-MIN(tp_g/tp_roe,0.8))/(1+tp_r)^3+H3347*(1-MIN(tp_g/tp_roe,0.8))/(1+tp_r)^4+I3347*(1-MIN(tp_g/tp_roe,0.8))/(1+tp_r)^5+J3347*(1-MIN(tp_g/tp_roe,0.8))/(1+tp_r)^6+J3347*(1-MIN(tp_g/tp_roe,0.8))*(1+tp_g)/(tp_r-tp_g)/(1+tp_r)^6))*(1+tp_r) -> 334.37674 | H26: =Val!$B$33*(tp_wA*(2/12*E3249+10/12*F3249)+tp_wB*(2/12*E3298+10/12*F3298)+tp_wC*(2/12*E3347+10/12*F3347))*rm_factor -> 640.35675 | I26: =tp_w_dcf*G26+(1-tp_w_dcf)*H26 -> 487.36675 | J26: =I26/I$4-1 -> -0.032704678
A27: 資本支出率 22% | B27: capi | C27: FY2028–29；基準 30% | D27: =E3445 -> 29.076998 | E27: =F3445 -> 25.638067 | F27: =E27/E$4-1 -> 0 | G27: =(tp_wA*MAX(0,E3396*(1-MIN(tp_g/tp_roe,0.8))/(1+tp_r)^1+F3396*(1-MIN(tp_g/tp_roe,0.8))/(1+tp_r)^2+G3396*(1-MIN(tp_g/tp_roe,0.8))/(1+tp_r)^3+H3396*(1-MIN(tp_g/tp_roe,0.8))/(1+tp_r)^4+I3396*(1-MIN(tp_g/tp_roe,0.8))/(1+tp_r)^5+J3396*(1-MIN(tp_g/tp_roe,0.8))/(1+tp_r)^6+J3396*(1-MIN(tp_g/tp_roe,0.8))*(1+tp_g)/(tp_r-tp_g)/(1+tp_r)^6)+tp_wB*MAX(0,E3445*(1-MIN(tp_g/tp_roe,0.8))/(1+tp_r)^1+F3445*(1-MIN(tp_g/tp_roe,0.8))/(1+tp_r)^2+G3445*(1-MIN(tp_g/tp_roe,0.8))/(1+tp_r)^3+H3445*(1-MIN(tp_g/tp_roe,0.8))/(1+tp_r)^4+I3445*(1-MIN(tp_g/tp_roe,0.8))/(1+tp_r)^5+J3445*(1-MIN(tp_g/tp_roe,0.8))/(1+tp_r)^6+J3445*(1-MIN(tp_g/tp_roe,0.8))*(1+tp_g)/(tp_r-tp_g)/(1+tp_r)^6)+tp_wC*MAX(0,E3494*(1-MIN(tp_g/tp_roe,0.8))/(1+tp_r)^1+F3494*(1-MIN(tp_g/tp_roe,0.8))/(1+tp_r)^2+G3494*(1-MIN(tp_g/tp_roe,0.8))/(1+tp_r)^3+H3494*(1-MIN(tp_g/tp_roe,0.8))/(1+tp_r)^4+I3494*(1-MIN(tp_g/tp_roe,0.8))/(1+tp_r)^5+J3494*(1-MIN(tp_g/tp_roe,0.8))/(1+tp_r)^6+J3494*(1-MIN(tp_g/tp_roe,0.8))*(1+tp_g)/(tp_r-tp_g)/(1+tp_r)^6))*(1+tp_r) -> 338.73257 | H27: =Val!$B$33*(tp_wA*(2/12*E3396+10/12*F3396)+tp_wB*(2/12*E3445+10/12*F3445)+tp_wC*(2/12*E3494+10/12*F3494))*rm_factor -> 671.1501 | I27: =tp_w_dcf*G27+(1-tp_w_dcf)*H27 -> 504.94133 | J27: =I27/I$4-1 -> 0.002176275
A28: 資本支出率 38% | B28: capi | D28: =E3592 -> 29.076998 | E28: =F3592 -> 25.638067 | F28: =E28/E$4-1 -> 0 | G28: =(tp_wA*MAX(0,E3543*(1-MIN(tp_g/tp_roe,0.8))/(1+tp_r)^1+F3543*(1-MIN(tp_g/tp_roe,0.8))/(1+tp_r)^2+G3543*(1-MIN(tp_g/tp_roe,0.8))/(1+tp_r)^3+H3543*(1-MIN(tp_g/tp_roe,0.8))/(1+tp_r)^4+I3543*(1-MIN(tp_g/tp_roe,0.8))/(1+tp_r)^5+J3543*(1-MIN(tp_g/tp_roe,0.8))/(1+tp_r)^6+J3543*(1-MIN(tp_g/tp_roe,0.8))*(1+tp_g)/(tp_r-tp_g)/(1+tp_r)^6)+tp_wB*MAX(0,E3592*(1-MIN(tp_g/tp_roe,0.8))/(1+tp_r)^1+F3592*(1-MIN(tp_g/tp_roe,0.8))/(1+tp_r)^2+G3592*(1-MIN(tp_g/tp_roe,0.8))/(1+tp_r)^3+H3592*(1-MIN(tp_g/tp_roe,0.8))/(1+tp_r)^4+I3592*(1-MIN(tp_g/tp_roe,0.8))/(1+tp_r)^5+J3592*(1-MIN(tp_g/tp_roe,0.8))/(1+tp_r)^6+J3592*(1-MIN(tp_g/tp_roe,0.8))*(1+tp_g)/(tp_r-tp_g)/(1+tp_r)^6)+tp_wC*MAX(0,E3641*(1-MIN(tp_g/tp_roe,0.8))/(1+tp_r)^1+F3641*(1-MIN(tp_g/tp_roe,0.8))/(1+tp_r)^2+G3641*(1-MIN(tp_g/tp_roe,0.8))/(1+tp_r)^3+H3641*(1-MIN(tp_g/tp_roe,0.8))/(1+tp_r)^4+I3641*(1-MIN(tp_g/tp_roe,0.8))/(1+tp_r)^5+J3641*(1-MIN(tp_g/tp_roe,0.8))/(1+tp_r)^6+J3641*(1-MIN(tp_g/tp_roe,0.8))*(1+tp_g)/(tp_r-tp_g)/(1+tp_r)^6))*(1+tp_r) -> 334.34655 | H28: =Val!$B$33*(tp_wA*(2/12*E3543+10/12*F3543)+tp_wB*(2/12*E3592+10/12*F3592)+tp_wC*(2/12*E3641+10/12*F3641))*rm_factor -> 671.1501 | I28: =tp_w_dcf*G28+(1-tp_w_dcf)*H28 -> 502.74832 | J28: =I28/I$4-1 -> -0.002176275
A29: 折舊年限 6 年 | B29: life | C29: 基準 8 年 | D29: =E3739 -> 26.964131 | E29: =F3739 -> 21.663448 | F29: =E29/E$4-1 -> -0.15502803 | G29: =(tp_wA*MAX(0,E3690*(1-MIN(tp_g/tp_roe,0.8))/(1+tp_r)^1+F3690*(1-MIN(tp_g/tp_roe,0.8))/(1+tp_r)^2+G3690*(1-MIN(tp_g/tp_roe,0.8))/(1+tp_r)^3+H3690*(1-MIN(tp_g/tp_roe,0.8))/(1+tp_r)^4+I3690*(1-MIN(tp_g/tp_roe,0.8))/(1+tp_r)^5+J3690*(1-MIN(tp_g/tp_roe,0.8))/(1+tp_r)^6+J3690*(1-MIN(tp_g/tp_roe,0.8))*(1+tp_g)/(tp_r-tp_g)/(1+tp_r)^6)+tp_wB*MAX(0,E3739*(1-MIN(tp_g/tp_roe,0.8))/(1+tp_r)^1+F3739*(1-MIN(tp_g/tp_roe,0.8))/(1+tp_r)^2+G3739*(1-MIN(tp_g/tp_roe,0.8))/(1+tp_r)^3+H3739*(1-MIN(tp_g/tp_roe,0.8))/(1+tp_r)^4+I3739*(1-MIN(tp_g/tp_roe,0.8))/(1+tp_r)^5+J3739*(1-MIN(tp_g/tp_roe,0.8))/(1+tp_r)^6+J3739*(1-MIN(tp_g/tp_roe,0.8))*(1+tp_g)/(tp_r-tp_g)/(1+tp_r)^6)+tp_wC*MAX(0,E3788*(1-MIN(tp_g/tp_roe,0.8))/(1+tp_r)^1+F3788*(1-MIN(tp_g/tp_roe,0.8))/(1+tp_r)^2+G3788*(1-MIN(tp_g/tp_roe,0.8))/(1+tp_r)^3+H3788*(1-MIN(tp_g/tp_roe,0.8))/(1+tp_r)^4+I3788*(1-MIN(tp_g/tp_roe,0.8))/(1+tp_r)^5+J3788*(1-MIN(tp_g/tp_roe,0.8))/(1+tp_r)^6+J3788*(1-MIN(tp_g/tp_roe,0.8))*(1+tp_g)/(tp_r-tp_g)/(1+tp_r)^6))*(1+tp_r) -> 328.21745 | H29: =Val!$B$33*(tp_wA*(2/12*E3690+10/12*F3690)+tp_wB*(2/12*E3739+10/12*F3739)+tp_wC*(2/12*E3788+10/12*F3788))*rm_factor -> 580.6711 | I29: =tp_w_dcf*G29+(1-tp_w_dcf)*H29 -> 454.44428 | J29: =I29/I$4-1 -> -0.098047154
A30: 折舊年限 12 年 | B30: life | D30: =E3886 -> 31.189865 | E30: =F3886 -> 29.787882 | F30: =E30/E$4-1 -> 0.16186147 | G30: =(tp_wA*MAX(0,E3837*(1-MIN(tp_g/tp_roe,0.8))/(1+tp_r)^1+F3837*(1-MIN(tp_g/tp_roe,0.8))/(1+tp_r)^2+G3837*(1-MIN(tp_g/tp_roe,0.8))/(1+tp_r)^3+H3837*(1-MIN(tp_g/tp_roe,0.8))/(1+tp_r)^4+I3837*(1-MIN(tp_g/tp_roe,0.8))/(1+tp_r)^5+J3837*(1-MIN(tp_g/tp_roe,0.8))/(1+tp_r)^6+J3837*(1-MIN(tp_g/tp_roe,0.8))*(1+tp_g)/(tp_r-tp_g)/(1+tp_r)^6)+tp_wB*MAX(0,E3886*(1-MIN(tp_g/tp_roe,0.8))/(1+tp_r)^1+F3886*(1-MIN(tp_g/tp_roe,0.8))/(1+tp_r)^2+G3886*(1-MIN(tp_g/tp_roe,0.8))/(1+tp_r)^3+H3886*(1-MIN(tp_g/tp_roe,0.8))/(1+tp_r)^4+I3886*(1-MIN(tp_g/tp_roe,0.8))/(1+tp_r)^5+J3886*(1-MIN(tp_g/tp_roe,0.8))/(1+tp_r)^6+J3886*(1-MIN(tp_g/tp_roe,0.8))*(1+tp_g)/(tp_r-tp_g)/(1+tp_r)^6)+tp_wC*MAX(0,E3935*(1-MIN(tp_g/tp_roe,0.8))/(1+tp_r)^1+F3935*(1-MIN(tp_g/tp_roe,0.8))/(1+tp_r)^2+G3935*(1-MIN(tp_g/tp_roe,0.8))/(1+tp_r)^3+H3935*(1-MIN(tp_g/tp_roe,0.8))/(1+tp_r)^4+I3935*(1-MIN(tp_g/tp_roe,0.8))/(1+tp_r)^5+J3935*(1-MIN(tp_g/tp_roe,0.8))/(1+tp_r)^6+J3935*(1-MIN(tp_g/tp_roe,0.8))*(1+tp_g)/(tp_r-tp_g)/(1+tp_r)^6))*(1+tp_r) -> 345.45585 | H30: =Val!$B$33*(tp_wA*(2/12*E3837+10/12*F3837)+tp_wB*(2/12*E3886+10/12*F3886)+tp_wC*(2/12*E3935+10/12*F3935))*rm_factor -> 765.23402 | I30: =tp_w_dcf*G30+(1-tp_w_dcf)*H30 -> 555.34494 | J30: =I30/I$4-1 -> 0.10221422
A31: 現金流通率 40% | B31: ft | C31: 基準 50% | D31: =E4033 -> 25.466535 | E31: =F4033 -> 21.317999 | F31: =E31/E$4-1 -> -0.16850211 | G31: =(tp_wA*MAX(0,E3984*(1-MIN(tp_g/tp_roe,0.8))/(1+tp_r)^1+F3984*(1-MIN(tp_g/tp_roe,0.8))/(1+tp_r)^2+G3984*(1-MIN(tp_g/tp_roe,0.8))/(1+tp_r)^3+H3984*(1-MIN(tp_g/tp_roe,0.8))/(1+tp_r)^4+I3984*(1-MIN(tp_g/tp_roe,0.8))/(1+tp_r)^5+J3984*(1-MIN(tp_g/tp_roe,0.8))/(1+tp_r)^6+J3984*(1-MIN(tp_g/tp_roe,0.8))*(1+tp_g)/(tp_r-tp_g)/(1+tp_r)^6)+tp_wB*MAX(0,E4033*(1-MIN(tp_g/tp_roe,0.8))/(1+tp_r)^1+F4033*(1-MIN(tp_g/tp_roe,0.8))/(1+tp_r)^2+G4033*(1-MIN(tp_g/tp_roe,0.8))/(1+tp_r)^3+H4033*(1-MIN(tp_g/tp_roe,0.8))/(1+tp_r)^4+I4033*(1-MIN(tp_g/tp_roe,0.8))/(1+tp_r)^5+J4033*(1-MIN(tp_g/tp_roe,0.8))/(1+tp_r)^6+J4033*(1-MIN(tp_g/tp_roe,0.8))*(1+tp_g)/(tp_r-tp_g)/(1+tp_r)^6)+tp_wC*MAX(0,E4082*(1-MIN(tp_g/tp_roe,0.8))/(1+tp_r)^1+F4082*(1-MIN(tp_g/tp_roe,0.8))/(1+tp_r)^2+G4082*(1-MIN(tp_g/tp_roe,0.8))/(1+tp_r)^3+H4082*(1-MIN(tp_g/tp_roe,0.8))/(1+tp_r)^4+I4082*(1-MIN(tp_g/tp_roe,0.8))/(1+tp_r)^5+J4082*(1-MIN(tp_g/tp_roe,0.8))/(1+tp_r)^6+J4082*(1-MIN(tp_g/tp_roe,0.8))*(1+tp_g)/(tp_r-tp_g)/(1+tp_r)^6))*(1+tp_r) -> 324.87135 | H31: =Val!$B$33*(tp_wA*(2/12*E3984+10/12*F3984)+tp_wB*(2/12*E4033+10/12*F4033)+tp_wC*(2/12*E4082+10/12*F4082))*rm_factor -> 562.0666 | I31: =tp_w_dcf*G31+(1-tp_w_dcf)*H31 -> 443.46897 | J31: =I31/I$4-1 -> -0.11983026
A32: 現金流通率 60% | B32: ft | D32: =E4180 -> 32.687461 | E32: =F4180 -> 29.958135 | F32: =E32/E$4-1 -> 0.16850211 | G32: =(tp_wA*MAX(0,E4131*(1-MIN(tp_g/tp_roe,0.8))/(1+tp_r)^1+F4131*(1-MIN(tp_g/tp_roe,0.8))/(1+tp_r)^2+G4131*(1-MIN(tp_g/tp_roe,0.8))/(1+tp_r)^3+H4131*(1-MIN(tp_g/tp_roe,0.8))/(1+tp_r)^4+I4131*(1-MIN(tp_g/tp_roe,0.8))/(1+tp_r)^5+J4131*(1-MIN(tp_g/tp_roe,0.8))/(1+tp_r)^6+J4131*(1-MIN(tp_g/tp_roe,0.8))*(1+tp_g)/(tp_r-tp_g)/(1+tp_r)^6)+tp_wB*MAX(0,E4180*(1-MIN(tp_g/tp_roe,0.8))/(1+tp_r)^1+F4180*(1-MIN(tp_g/tp_roe,0.8))/(1+tp_r)^2+G4180*(1-MIN(tp_g/tp_roe,0.8))/(1+tp_r)^3+H4180*(1-MIN(tp_g/tp_roe,0.8))/(1+tp_r)^4+I4180*(1-MIN(tp_g/tp_roe,0.8))/(1+tp_r)^5+J4180*(1-MIN(tp_g/tp_roe,0.8))/(1+tp_r)^6+J4180*(1-MIN(tp_g/tp_roe,0.8))*(1+tp_g)/(tp_r-tp_g)/(1+tp_r)^6)+tp_wC*MAX(0,E4229*(1-MIN(tp_g/tp_roe,0.8))/(1+tp_r)^1+F4229*(1-MIN(tp_g/tp_roe,0.8))/(1+tp_r)^2+G4229*(1-MIN(tp_g/tp_roe,0.8))/(1+tp_r)^3+H4229*(1-MIN(tp_g/tp_roe,0.8))/(1+tp_r)^4+I4229*(1-MIN(tp_g/tp_roe,0.8))/(1+tp_r)^5+J4229*(1-MIN(tp_g/tp_roe,0.8))/(1+tp_r)^6+J4229*(1-MIN(tp_g/tp_roe,0.8))*(1+tp_g)/(tp_r-tp_g)/(1+tp_r)^6))*(1+tp_r) -> 348.20778 | H32: =Val!$B$33*(tp_wA*(2/12*E4131+10/12*F4131)+tp_wB*(2/12*E4180+10/12*F4180)+tp_wC*(2/12*E4229+10/12*F4229))*rm_factor -> 780.2336 | I32: =tp_w_dcf*G32+(1-tp_w_dcf)*H32 -> 564.22069 | J32: =I32/I$4-1 -> 0.11983026
A33: 營業費用彈性 0.3 | B33: phi | C33: 基準 0.6 | D33: =E4327 -> 30.225474 | E33: =F4327 -> 27.062309 | F33: =E33/E$4-1 -> 0.055551836 | G33: =(tp_wA*MAX(0,E4278*(1-MIN(tp_g/tp_roe,0.8))/(1+tp_r)^1+F4278*(1-MIN(tp_g/tp_roe,0.8))/(1+tp_r)^2+G4278*(1-MIN(tp_g/tp_roe,0.8))/(1+tp_r)^3+H4278*(1-MIN(tp_g/tp_roe,0.8))/(1+tp_r)^4+I4278*(1-MIN(tp_g/tp_roe,0.8))/(1+tp_r)^5+J4278*(1-MIN(tp_g/tp_roe,0.8))/(1+tp_r)^6+J4278*(1-MIN(tp_g/tp_roe,0.8))*(1+tp_g)/(tp_r-tp_g)/(1+tp_r)^6)+tp_wB*MAX(0,E4327*(1-MIN(tp_g/tp_roe,0.8))/(1+tp_r)^1+F4327*(1-MIN(tp_g/tp_roe,0.8))/(1+tp_r)^2+G4327*(1-MIN(tp_g/tp_roe,0.8))/(1+tp_r)^3+H4327*(1-MIN(tp_g/tp_roe,0.8))/(1+tp_r)^4+I4327*(1-MIN(tp_g/tp_roe,0.8))/(1+tp_r)^5+J4327*(1-MIN(tp_g/tp_roe,0.8))/(1+tp_r)^6+J4327*(1-MIN(tp_g/tp_roe,0.8))*(1+tp_g)/(tp_r-tp_g)/(1+tp_r)^6)+tp_wC*MAX(0,E4376*(1-MIN(tp_g/tp_roe,0.8))/(1+tp_r)^1+F4376*(1-MIN(tp_g/tp_roe,0.8))/(1+tp_r)^2+G4376*(1-MIN(tp_g/tp_roe,0.8))/(1+tp_r)^3+H4376*(1-MIN(tp_g/tp_roe,0.8))/(1+tp_r)^4+I4376*(1-MIN(tp_g/tp_roe,0.8))/(1+tp_r)^5+J4376*(1-MIN(tp_g/tp_roe,0.8))/(1+tp_r)^6+J4376*(1-MIN(tp_g/tp_roe,0.8))*(1+tp_g)/(tp_r-tp_g)/(1+tp_r)^6))*(1+tp_r) -> 340.28207 | H33: =Val!$B$33*(tp_wA*(2/12*E4278+10/12*F4278)+tp_wB*(2/12*E4327+10/12*F4327)+tp_wC*(2/12*E4376+10/12*F4376))*rm_factor -> 706.6084 | I33: =tp_w_dcf*G33+(1-tp_w_dcf)*H33 -> 523.44524 | J33: =I33/I$4-1 -> 0.038901674
A34: 營業費用彈性 1.0 | B34: phi | D34: =E4474 -> 27.545697 | E34: =F4474 -> 23.684481 | F34: =E34/E$4-1 -> -0.07619863 | G34: =(tp_wA*MAX(0,E4425*(1-MIN(tp_g/tp_roe,0.8))/(1+tp_r)^1+F4425*(1-MIN(tp_g/tp_roe,0.8))/(1+tp_r)^2+G4425*(1-MIN(tp_g/tp_roe,0.8))/(1+tp_r)^3+H4425*(1-MIN(tp_g/tp_roe,0.8))/(1+tp_r)^4+I4425*(1-MIN(tp_g/tp_roe,0.8))/(1+tp_r)^5+J4425*(1-MIN(tp_g/tp_roe,0.8))/(1+tp_r)^6+J4425*(1-MIN(tp_g/tp_roe,0.8))*(1+tp_g)/(tp_r-tp_g)/(1+tp_r)^6)+tp_wB*MAX(0,E4474*(1-MIN(tp_g/tp_roe,0.8))/(1+tp_r)^1+F4474*(1-MIN(tp_g/tp_roe,0.8))/(1+tp_r)^2+G4474*(1-MIN(tp_g/tp_roe,0.8))/(1+tp_r)^3+H4474*(1-MIN(tp_g/tp_roe,0.8))/(1+tp_r)^4+I4474*(1-MIN(tp_g/tp_roe,0.8))/(1+tp_r)^5+J4474*(1-MIN(tp_g/tp_roe,0.8))/(1+tp_r)^6+J4474*(1-MIN(tp_g/tp_roe,0.8))*(1+tp_g)/(tp_r-tp_g)/(1+tp_r)^6)+tp_wC*MAX(0,E4523*(1-MIN(tp_g/tp_roe,0.8))/(1+tp_r)^1+F4523*(1-MIN(tp_g/tp_roe,0.8))/(1+tp_r)^2+G4523*(1-MIN(tp_g/tp_roe,0.8))/(1+tp_r)^3+H4523*(1-MIN(tp_g/tp_roe,0.8))/(1+tp_r)^4+I4523*(1-MIN(tp_g/tp_roe,0.8))/(1+tp_r)^5+J4523*(1-MIN(tp_g/tp_roe,0.8))/(1+tp_r)^6+J4523*(1-MIN(tp_g/tp_roe,0.8))*(1+tp_g)/(tp_r-tp_g)/(1+tp_r)^6))*(1+tp_r) -> 331.26486 | H34: =Val!$B$33*(tp_wA*(2/12*E4425+10/12*F4425)+tp_wB*(2/12*E4474+10/12*F4474)+tp_wC*(2/12*E4523+10/12*F4523))*rm_factor -> 622.45318 | I34: =tp_w_dcf*G34+(1-tp_w_dcf)*H34 -> 476.85902 | J34: =I34/I$4-1 -> -0.053559754
A35: 營業外 −8 | B35: nonop_f | C35: 每年；基準 −5 | D35: =E4621 -> 28.512994 | E35: =F4621 -> 25.076869 | F35: =E35/E$4-1 -> -0.021889232 | G35: =(tp_wA*MAX(0,E4572*(1-MIN(tp_g/tp_roe,0.8))/(1+tp_r)^1+F4572*(1-MIN(tp_g/tp_roe,0.8))/(1+tp_r)^2+G4572*(1-MIN(tp_g/tp_roe,0.8))/(1+tp_r)^3+H4572*(1-MIN(tp_g/tp_roe,0.8))/(1+tp_r)^4+I4572*(1-MIN(tp_g/tp_roe,0.8))/(1+tp_r)^5+J4572*(1-MIN(tp_g/tp_roe,0.8))/(1+tp_r)^6+J4572*(1-MIN(tp_g/tp_roe,0.8))*(1+tp_g)/(tp_r-tp_g)/(1+tp_r)^6)+tp_wB*MAX(0,E4621*(1-MIN(tp_g/tp_roe,0.8))/(1+tp_r)^1+F4621*(1-MIN(tp_g/tp_roe,0.8))/(1+tp_r)^2+G4621*(1-MIN(tp_g/tp_roe,0.8))/(1+tp_r)^3+H4621*(1-MIN(tp_g/tp_roe,0.8))/(1+tp_r)^4+I4621*(1-MIN(tp_g/tp_roe,0.8))/(1+tp_r)^5+J4621*(1-MIN(tp_g/tp_roe,0.8))/(1+tp_r)^6+J4621*(1-MIN(tp_g/tp_roe,0.8))*(1+tp_g)/(tp_r-tp_g)/(1+tp_r)^6)+tp_wC*MAX(0,E4670*(1-MIN(tp_g/tp_roe,0.8))/(1+tp_r)^1+F4670*(1-MIN(tp_g/tp_roe,0.8))/(1+tp_r)^2+G4670*(1-MIN(tp_g/tp_roe,0.8))/(1+tp_r)^3+H4670*(1-MIN(tp_g/tp_roe,0.8))/(1+tp_r)^4+I4670*(1-MIN(tp_g/tp_roe,0.8))/(1+tp_r)^5+J4670*(1-MIN(tp_g/tp_roe,0.8))/(1+tp_r)^6+J4670*(1-MIN(tp_g/tp_roe,0.8))*(1+tp_g)/(tp_r-tp_g)/(1+tp_r)^6))*(1+tp_r) -> 335.30802 | H35: =Val!$B$33*(tp_wA*(2/12*E4572+10/12*F4572)+tp_wB*(2/12*E4621+10/12*F4621)+tp_wC*(2/12*E4670+10/12*F4670))*rm_factor -> 657.28155 | I35: =tp_w_dcf*G35+(1-tp_w_dcf)*H35 -> 496.29478 | J35: =I35/I$4-1 -> -0.014984867
A36: 營業外 −2 | B36: nonop_f | D36: =E4768 -> 29.641001 | E36: =F4768 -> 26.199264 | F36: =E36/E$4-1 -> 0.021889232 | G36: =(tp_wA*MAX(0,E4719*(1-MIN(tp_g/tp_roe,0.8))/(1+tp_r)^1+F4719*(1-MIN(tp_g/tp_roe,0.8))/(1+tp_r)^2+G4719*(1-MIN(tp_g/tp_roe,0.8))/(1+tp_r)^3+H4719*(1-MIN(tp_g/tp_roe,0.8))/(1+tp_r)^4+I4719*(1-MIN(tp_g/tp_roe,0.8))/(1+tp_r)^5+J4719*(1-MIN(tp_g/tp_roe,0.8))/(1+tp_r)^6+J4719*(1-MIN(tp_g/tp_roe,0.8))*(1+tp_g)/(tp_r-tp_g)/(1+tp_r)^6)+tp_wB*MAX(0,E4768*(1-MIN(tp_g/tp_roe,0.8))/(1+tp_r)^1+F4768*(1-MIN(tp_g/tp_roe,0.8))/(1+tp_r)^2+G4768*(1-MIN(tp_g/tp_roe,0.8))/(1+tp_r)^3+H4768*(1-MIN(tp_g/tp_roe,0.8))/(1+tp_r)^4+I4768*(1-MIN(tp_g/tp_roe,0.8))/(1+tp_r)^5+J4768*(1-MIN(tp_g/tp_roe,0.8))/(1+tp_r)^6+J4768*(1-MIN(tp_g/tp_roe,0.8))*(1+tp_g)/(tp_r-tp_g)/(1+tp_r)^6)+tp_wC*MAX(0,E4817*(1-MIN(tp_g/tp_roe,0.8))/(1+tp_r)^1+F4817*(1-MIN(tp_g/tp_roe,0.8))/(1+tp_r)^2+G4817*(1-MIN(tp_g/tp_roe,0.8))/(1+tp_r)^3+H4817*(1-MIN(tp_g/tp_roe,0.8))/(1+tp_r)^4+I4817*(1-MIN(tp_g/tp_roe,0.8))/(1+tp_r)^5+J4817*(1-MIN(tp_g/tp_roe,0.8))/(1+tp_r)^6+J4817*(1-MIN(tp_g/tp_roe,0.8))*(1+tp_g)/(tp_r-tp_g)/(1+tp_r)^6))*(1+tp_r) -> 337.7711 | H36: =Val!$B$33*(tp_wA*(2/12*E4719+10/12*F4719)+tp_wB*(2/12*E4768+10/12*F4768)+tp_wC*(2/12*E4817+10/12*F4817))*rm_factor -> 685.01865 | I36: =tp_w_dcf*G36+(1-tp_w_dcf)*H36 -> 511.39488 | J36: =I36/I$4-1 -> 0.014984867
A37: 稅率 15% | B37: tax | C37: 基準 17% | D37: =E4915 -> 29.794022 | E37: =F4915 -> 26.272144 | F37: =E37/E$4-1 -> 0.024731869 | G37: =(tp_wA*MAX(0,E4866*(1-MIN(tp_g/tp_roe,0.8))/(1+tp_r)^1+F4866*(1-MIN(tp_g/tp_roe,0.8))/(1+tp_r)^2+G4866*(1-MIN(tp_g/tp_roe,0.8))/(1+tp_r)^3+H4866*(1-MIN(tp_g/tp_roe,0.8))/(1+tp_r)^4+I4866*(1-MIN(tp_g/tp_roe,0.8))/(1+tp_r)^5+J4866*(1-MIN(tp_g/tp_roe,0.8))/(1+tp_r)^6+J4866*(1-MIN(tp_g/tp_roe,0.8))*(1+tp_g)/(tp_r-tp_g)/(1+tp_r)^6)+tp_wB*MAX(0,E4915*(1-MIN(tp_g/tp_roe,0.8))/(1+tp_r)^1+F4915*(1-MIN(tp_g/tp_roe,0.8))/(1+tp_r)^2+G4915*(1-MIN(tp_g/tp_roe,0.8))/(1+tp_r)^3+H4915*(1-MIN(tp_g/tp_roe,0.8))/(1+tp_r)^4+I4915*(1-MIN(tp_g/tp_roe,0.8))/(1+tp_r)^5+J4915*(1-MIN(tp_g/tp_roe,0.8))/(1+tp_r)^6+J4915*(1-MIN(tp_g/tp_roe,0.8))*(1+tp_g)/(tp_r-tp_g)/(1+tp_r)^6)+tp_wC*MAX(0,E4964*(1-MIN(tp_g/tp_roe,0.8))/(1+tp_r)^1+F4964*(1-MIN(tp_g/tp_roe,0.8))/(1+tp_r)^2+G4964*(1-MIN(tp_g/tp_roe,0.8))/(1+tp_r)^3+H4964*(1-MIN(tp_g/tp_roe,0.8))/(1+tp_r)^4+I4964*(1-MIN(tp_g/tp_roe,0.8))/(1+tp_r)^5+J4964*(1-MIN(tp_g/tp_roe,0.8))/(1+tp_r)^6+J4964*(1-MIN(tp_g/tp_roe,0.8))*(1+tp_g)/(tp_r-tp_g)/(1+tp_r)^6))*(1+tp_r) -> 338.16607 | H37: =Val!$B$33*(tp_wA*(2/12*E4866+10/12*F4866)+tp_wB*(2/12*E4915+10/12*F4915)+tp_wC*(2/12*E4964+10/12*F4964))*rm_factor -> 687.72502 | I37: =tp_w_dcf*G37+(1-tp_w_dcf)*H37 -> 512.94554 | J37: =I37/I$4-1 -> 0.018062532
A38: 稅率 20% | B38: tax | D38: =E5062 -> 28.001461 | E38: =F5062 -> 24.686951 | F38: =E38/E$4-1 -> -0.037097804 | G38: =(tp_wA*MAX(0,E5013*(1-MIN(tp_g/tp_roe,0.8))/(1+tp_r)^1+F5013*(1-MIN(tp_g/tp_roe,0.8))/(1+tp_r)^2+G5013*(1-MIN(tp_g/tp_roe,0.8))/(1+tp_r)^3+H5013*(1-MIN(tp_g/tp_roe,0.8))/(1+tp_r)^4+I5013*(1-MIN(tp_g/tp_roe,0.8))/(1+tp_r)^5+J5013*(1-MIN(tp_g/tp_roe,0.8))/(1+tp_r)^6+J5013*(1-MIN(tp_g/tp_roe,0.8))*(1+tp_g)/(tp_r-tp_g)/(1+tp_r)^6)+tp_wB*MAX(0,E5062*(1-MIN(tp_g/tp_roe,0.8))/(1+tp_r)^1+F5062*(1-MIN(tp_g/tp_roe,0.8))/(1+tp_r)^2+G5062*(1-MIN(tp_g/tp_roe,0.8))/(1+tp_r)^3+H5062*(1-MIN(tp_g/tp_roe,0.8))/(1+tp_r)^4+I5062*(1-MIN(tp_g/tp_roe,0.8))/(1+tp_r)^5+J5062*(1-MIN(tp_g/tp_roe,0.8))/(1+tp_r)^6+J5062*(1-MIN(tp_g/tp_roe,0.8))*(1+tp_g)/(tp_r-tp_g)/(1+tp_r)^6)+tp_wC*MAX(0,E5111*(1-MIN(tp_g/tp_roe,0.8))/(1+tp_r)^1+F5111*(1-MIN(tp_g/tp_roe,0.8))/(1+tp_r)^2+G5111*(1-MIN(tp_g/tp_roe,0.8))/(1+tp_r)^3+H5111*(1-MIN(tp_g/tp_roe,0.8))/(1+tp_r)^4+I5111*(1-MIN(tp_g/tp_roe,0.8))/(1+tp_r)^5+J5111*(1-MIN(tp_g/tp_roe,0.8))/(1+tp_r)^6+J5111*(1-MIN(tp_g/tp_roe,0.8))*(1+tp_g)/(tp_r-tp_g)/(1+tp_r)^6))*(1+tp_r) -> 334.0998 | H38: =Val!$B$33*(tp_wA*(2/12*E5013+10/12*F5013)+tp_wB*(2/12*E5062+10/12*F5062)+tp_wC*(2/12*E5111+10/12*F5111))*rm_factor -> 646.28772 | I38: =tp_w_dcf*G38+(1-tp_w_dcf)*H38 -> 490.19376 | J38: =I38/I$4-1 -> -0.027093798
A39: 折現率 +1pt | B39: tp_r | C39: r 11% | D39: =D4 -> 29.076998 | E39: =E4 -> 25.638067 | F39: =E39/E$4-1 -> 0 | G39: =(tp_wA*MAX(0,Val!B8*(1-MIN(tp_g/tp_roe,0.8))/(1+(tp_r+0.01))^1+Val!B9*(1-MIN(tp_g/tp_roe,0.8))/(1+(tp_r+0.01))^2+Val!B10*(1-MIN(tp_g/tp_roe,0.8))/(1+(tp_r+0.01))^3+Val!B11*(1-MIN(tp_g/tp_roe,0.8))/(1+(tp_r+0.01))^4+Val!B12*(1-MIN(tp_g/tp_roe,0.8))/(1+(tp_r+0.01))^5+Val!B13*(1-MIN(tp_g/tp_roe,0.8))/(1+(tp_r+0.01))^6+Val!B13*(1-MIN(tp_g/tp_roe,0.8))*(1+tp_g)/((tp_r+0.01)-tp_g)/(1+(tp_r+0.01))^6)+tp_wB*MAX(0,Val!C8*(1-MIN(tp_g/tp_roe,0.8))/(1+(tp_r+0.01))^1+Val!C9*(1-MIN(tp_g/tp_roe,0.8))/(1+(tp_r+0.01))^2+Val!C10*(1-MIN(tp_g/tp_roe,0.8))/(1+(tp_r+0.01))^3+Val!C11*(1-MIN(tp_g/tp_roe,0.8))/(1+(tp_r+0.01))^4+Val!C12*(1-MIN(tp_g/tp_roe,0.8))/(1+(tp_r+0.01))^5+Val!C13*(1-MIN(tp_g/tp_roe,0.8))/(1+(tp_r+0.01))^6+Val!C13*(1-MIN(tp_g/tp_roe,0.8))*(1+tp_g)/((tp_r+0.01)-tp_g)/(1+(tp_r+0.01))^6)+tp_wC*MAX(0,Val!D8*(1-MIN(tp_g/tp_roe,0.8))/(1+(tp_r+0.01))^1+Val!D9*(1-MIN(tp_g/tp_roe,0.8))/(1+(tp_r+0.01))^2+Val!D10*(1-MIN(tp_g/tp_roe,0.8))/(1+(tp_r+0.01))^3+Val!D11*(1-MIN(tp_g/tp_roe,0.8))/(1+(tp_r+0.01))^4+Val!D12*(1-MIN(tp_g/tp_roe,0.8))/(1+(tp_r+0.01))^5+Val!D13*(1-MIN(tp_g/tp_roe,0.8))/(1+(tp_r+0.01))^6+Val!D13*(1-MIN(tp_g/tp_roe,0.8))*(1+tp_g)/((tp_r+0.01)-tp_g)/(1+(tp_r+0.01))^6))*(1+(tp_r+0.01)) -> 290.83159 | H39: =H4 -> 671.1501 | I39: =tp_w_dcf*G39+(1-tp_w_dcf)*H39 -> 480.99084 | J39: =I39/I$4-1 -> -0.045359177
A40: 折現率 −1pt | B40: tp_r | C40: r 9% | D40: =D4 -> 29.076998 | E40: =E4 -> 25.638067 | F40: =E40/E$4-1 -> 0 | G40: =(tp_wA*MAX(0,Val!B8*(1-MIN(tp_g/tp_roe,0.8))/(1+(tp_r-0.01))^1+Val!B9*(1-MIN(tp_g/tp_roe,0.8))/(1+(tp_r-0.01))^2+Val!B10*(1-MIN(tp_g/tp_roe,0.8))/(1+(tp_r-0.01))^3+Val!B11*(1-MIN(tp_g/tp_roe,0.8))/(1+(tp_r-0.01))^4+Val!B12*(1-MIN(tp_g/tp_roe,0.8))/(1+(tp_r-0.01))^5+Val!B13*(1-MIN(tp_g/tp_roe,0.8))/(1+(tp_r-0.01))^6+Val!B13*(1-MIN(tp_g/tp_roe,0.8))*(1+tp_g)/((tp_r-0.01)-tp_g)/(1+(tp_r-0.01))^6)+tp_wB*MAX(0,Val!C8*(1-MIN(tp_g/tp_roe,0.8))/(1+(tp_r-0.01))^1+Val!C9*(1-MIN(tp_g/tp_roe,0.8))/(1+(tp_r-0.01))^2+Val!C10*(1-MIN(tp_g/tp_roe,0.8))/(1+(tp_r-0.01))^3+Val!C11*(1-MIN(tp_g/tp_roe,0.8))/(1+(tp_r-0.01))^4+Val!C12*(1-MIN(tp_g/tp_roe,0.8))/(1+(tp_r-0.01))^5+Val!C13*(1-MIN(tp_g/tp_roe,0.8))/(1+(tp_r-0.01))^6+Val!C13*(1-MIN(tp_g/tp_roe,0.8))*(1+tp_g)/((tp_r-0.01)-tp_g)/(1+(tp_r-0.01))^6)+tp_wC*MAX(0,Val!D8*(1-MIN(tp_g/tp_roe,0.8))/(1+(tp_r-0.01))^1+Val!D9*(1-MIN(tp_g/tp_roe,0.8))/(1+(tp_r-0.01))^2+Val!D10*(1-MIN(tp_g/tp_roe,0.8))/(1+(tp_r-0.01))^3+Val!D11*(1-MIN(tp_g/tp_roe,0.8))/(1+(tp_r-0.01))^4+Val!D12*(1-MIN(tp_g/tp_roe,0.8))/(1+(tp_r-0.01))^5+Val!D13*(1-MIN(tp_g/tp_roe,0.8))/(1+(tp_r-0.01))^6+Val!D13*(1-MIN(tp_g/tp_roe,0.8))*(1+tp_g)/((tp_r-0.01)-tp_g)/(1+(tp_r-0.01))^6))*(1+(tp_r-0.01)) -> 400.53011 | H40: =H4 -> 671.1501 | I40: =tp_w_dcf*G40+(1-tp_w_dcf)*H40 -> 535.8401 | J40: =I40/I$4-1 -> 0.063502237
A41: 長期成長 +1pt | B41: tp_g | C41: g 5% | D41: =D4 -> 29.076998 | E41: =E4 -> 25.638067 | F41: =E41/E$4-1 -> 0 | G41: =(tp_wA*MAX(0,Val!B8*(1-MIN((tp_g+0.01)/tp_roe,0.8))/(1+tp_r)^1+Val!B9*(1-MIN((tp_g+0.01)/tp_roe,0.8))/(1+tp_r)^2+Val!B10*(1-MIN((tp_g+0.01)/tp_roe,0.8))/(1+tp_r)^3+Val!B11*(1-MIN((tp_g+0.01)/tp_roe,0.8))/(1+tp_r)^4+Val!B12*(1-MIN((tp_g+0.01)/tp_roe,0.8))/(1+tp_r)^5+Val!B13*(1-MIN((tp_g+0.01)/tp_roe,0.8))/(1+tp_r)^6+Val!B13*(1-MIN((tp_g+0.01)/tp_roe,0.8))*(1+(tp_g+0.01))/(tp_r-(tp_g+0.01))/(1+tp_r)^6)+tp_wB*MAX(0,Val!C8*(1-MIN((tp_g+0.01)/tp_roe,0.8))/(1+tp_r)^1+Val!C9*(1-MIN((tp_g+0.01)/tp_roe,0.8))/(1+tp_r)^2+Val!C10*(1-MIN((tp_g+0.01)/tp_roe,0.8))/(1+tp_r)^3+Val!C11*(1-MIN((tp_g+0.01)/tp_roe,0.8))/(1+tp_r)^4+Val!C12*(1-MIN((tp_g+0.01)/tp_roe,0.8))/(1+tp_r)^5+Val!C13*(1-MIN((tp_g+0.01)/tp_roe,0.8))/(1+tp_r)^6+Val!C13*(1-MIN((tp_g+0.01)/tp_roe,0.8))*(1+(tp_g+0.01))/(tp_r-(tp_g+0.01))/(1+tp_r)^6)+tp_wC*MAX(0,Val!D8*(1-MIN((tp_g+0.01)/tp_roe,0.8))/(1+tp_r)^1+Val!D9*(1-MIN((tp_g+0.01)/tp_roe,0.8))/(1+tp_r)^2+Val!D10*(1-MIN((tp_g+0.01)/tp_roe,0.8))/(1+tp_r)^3+Val!D11*(1-MIN((tp_g+0.01)/tp_roe,0.8))/(1+tp_r)^4+Val!D12*(1-MIN((tp_g+0.01)/tp_roe,0.8))/(1+tp_r)^5+Val!D13*(1-MIN((tp_g+0.01)/tp_roe,0.8))/(1+tp_r)^6+Val!D13*(1-MIN((tp_g+0.01)/tp_roe,0.8))*(1+(tp_g+0.01))/(tp_r-(tp_g+0.01))/(1+tp_r)^6))*(1+tp_r) -> 328.33013 | H41: =H4 -> 671.1501 | I41: =tp_w_dcf*G41+(1-tp_w_dcf)*H41 -> 499.74011 | J41: =I41/I$4-1 -> -0.0081467837
A42: 長期成長 −1pt | B42: tp_g | C42: g 3% | D42: =D4 -> 29.076998 | E42: =E4 -> 25.638067 | F42: =E42/E$4-1 -> 0 | G42: =(tp_wA*MAX(0,Val!B8*(1-MIN((tp_g-0.01)/tp_roe,0.8))/(1+tp_r)^1+Val!B9*(1-MIN((tp_g-0.01)/tp_roe,0.8))/(1+tp_r)^2+Val!B10*(1-MIN((tp_g-0.01)/tp_roe,0.8))/(1+tp_r)^3+Val!B11*(1-MIN((tp_g-0.01)/tp_roe,0.8))/(1+tp_r)^4+Val!B12*(1-MIN((tp_g-0.01)/tp_roe,0.8))/(1+tp_r)^5+Val!B13*(1-MIN((tp_g-0.01)/tp_roe,0.8))/(1+tp_r)^6+Val!B13*(1-MIN((tp_g-0.01)/tp_roe,0.8))*(1+(tp_g-0.01))/(tp_r-(tp_g-0.01))/(1+tp_r)^6)+tp_wB*MAX(0,Val!C8*(1-MIN((tp_g-0.01)/tp_roe,0.8))/(1+tp_r)^1+Val!C9*(1-MIN((tp_g-0.01)/tp_roe,0.8))/(1+tp_r)^2+Val!C10*(1-MIN((tp_g-0.01)/tp_roe,0.8))/(1+tp_r)^3+Val!C11*(1-MIN((tp_g-0.01)/tp_roe,0.8))/(1+tp_r)^4+Val!C12*(1-MIN((tp_g-0.01)/tp_roe,0.8))/(1+tp_r)^5+Val!C13*(1-MIN((tp_g-0.01)/tp_roe,0.8))/(1+tp_r)^6+Val!C13*(1-MIN((tp_g-0.01)/tp_roe,0.8))*(1+(tp_g-0.01))/(tp_r-(tp_g-0.01))/(1+tp_r)^6)+tp_wC*MAX(0,Val!D8*(1-MIN((tp_g-0.01)/tp_roe,0.8))/(1+tp_r)^1+Val!D9*(1-MIN((tp_g-0.01)/tp_roe,0.8))/(1+tp_r)^2+Val!D10*(1-MIN((tp_g-0.01)/tp_roe,0.8))/(1+tp_r)^3+Val!D11*(1-MIN((tp_g-0.01)/tp_roe,0.8))/(1+tp_r)^4+Val!D12*(1-MIN((tp_g-0.01)/tp_roe,0.8))/(1+tp_r)^5+Val!D13*(1-MIN((tp_g-0.01)/tp_roe,0.8))/(1+tp_r)^6+Val!D13*(1-MIN((tp_g-0.01)/tp_roe,0.8))*(1+(tp_g-0.01))/(tp_r-(tp_g-0.01))/(1+tp_r)^6))*(1+tp_r) -> 345.94146 | H42: =H4 -> 671.1501 | I42: =tp_w_dcf*G42+(1-tp_w_dcf)*H42 -> 508.54578 | J42: =I42/I$4-1 -> 0.0093301584
A43: DCF 權重 0.3 | B43: tp_w_dcf | C43: Comparable 0.7 | D43: =D4 -> 29.076998 | E43: =E4 -> 25.638067 | F43: =E43/E$4-1 -> 0 | G43: =(tp_wA*MAX(0,Val!B8*(1-MIN(tp_g/tp_roe,0.8))/(1+tp_r)^1+Val!B9*(1-MIN(tp_g/tp_roe,0.8))/(1+tp_r)^2+Val!B10*(1-MIN(tp_g/tp_roe,0.8))/(1+tp_r)^3+Val!B11*(1-MIN(tp_g/tp_roe,0.8))/(1+tp_r)^4+Val!B12*(1-MIN(tp_g/tp_roe,0.8))/(1+tp_r)^5+Val!B13*(1-MIN(tp_g/tp_roe,0.8))/(1+tp_r)^6+Val!B13*(1-MIN(tp_g/tp_roe,0.8))*(1+tp_g)/(tp_r-tp_g)/(1+tp_r)^6)+tp_wB*MAX(0,Val!C8*(1-MIN(tp_g/tp_roe,0.8))/(1+tp_r)^1+Val!C9*(1-MIN(tp_g/tp_roe,0.8))/(1+tp_r)^2+Val!C10*(1-MIN(tp_g/tp_roe,0.8))/(1+tp_r)^3+Val!C11*(1-MIN(tp_g/tp_roe,0.8))/(1+tp_r)^4+Val!C12*(1-MIN(tp_g/tp_roe,0.8))/(1+tp_r)^5+Val!C13*(1-MIN(tp_g/tp_roe,0.8))/(1+tp_r)^6+Val!C13*(1-MIN(tp_g/tp_roe,0.8))*(1+tp_g)/(tp_r-tp_g)/(1+tp_r)^6)+tp_wC*MAX(0,Val!D8*(1-MIN(tp_g/tp_roe,0.8))/(1+tp_r)^1+Val!D9*(1-MIN(tp_g/tp_roe,0.8))/(1+tp_r)^2+Val!D10*(1-MIN(tp_g/tp_roe,0.8))/(1+tp_r)^3+Val!D11*(1-MIN(tp_g/tp_roe,0.8))/(1+tp_r)^4+Val!D12*(1-MIN(tp_g/tp_roe,0.8))/(1+tp_r)^5+Val!D13*(1-MIN(tp_g/tp_roe,0.8))/(1+tp_r)^6+Val!D13*(1-MIN(tp_g/tp_roe,0.8))*(1+tp_g)/(tp_r-tp_g)/(1+tp_r)^6))*(1+tp_r) -> 336.53956 | H43: =H4 -> 671.1501 | I43: =0.3*G43+(1-0.3)*H43 -> 570.76694 | J43: =I43/I$4-1 -> 0.13282285
A44: DCF 權重 0.7 | B44: tp_w_dcf | C44: Comparable 0.3 | D44: =D4 -> 29.076998 | E44: =E4 -> 25.638067 | F44: =E44/E$4-1 -> 0 | G44: =(tp_wA*MAX(0,Val!B8*(1-MIN(tp_g/tp_roe,0.8))/(1+tp_r)^1+Val!B9*(1-MIN(tp_g/tp_roe,0.8))/(1+tp_r)^2+Val!B10*(1-MIN(tp_g/tp_roe,0.8))/(1+tp_r)^3+Val!B11*(1-MIN(tp_g/tp_roe,0.8))/(1+tp_r)^4+Val!B12*(1-MIN(tp_g/tp_roe,0.8))/(1+tp_r)^5+Val!B13*(1-MIN(tp_g/tp_roe,0.8))/(1+tp_r)^6+Val!B13*(1-MIN(tp_g/tp_roe,0.8))*(1+tp_g)/(tp_r-tp_g)/(1+tp_r)^6)+tp_wB*MAX(0,Val!C8*(1-MIN(tp_g/tp_roe,0.8))/(1+tp_r)^1+Val!C9*(1-MIN(tp_g/tp_roe,0.8))/(1+tp_r)^2+Val!C10*(1-MIN(tp_g/tp_roe,0.8))/(1+tp_r)^3+Val!C11*(1-MIN(tp_g/tp_roe,0.8))/(1+tp_r)^4+Val!C12*(1-MIN(tp_g/tp_roe,0.8))/(1+tp_r)^5+Val!C13*(1-MIN(tp_g/tp_roe,0.8))/(1+tp_r)^6+Val!C13*(1-MIN(tp_g/tp_roe,0.8))*(1+tp_g)/(tp_r-tp_g)/(1+tp_r)^6)+tp_wC*MAX(0,Val!D8*(1-MIN(tp_g/tp_roe,0.8))/(1+tp_r)^1+Val!D9*(1-MIN(tp_g/tp_roe,0.8))/(1+tp_r)^2+Val!D10*(1-MIN(tp_g/tp_roe,0.8))/(1+tp_r)^3+Val!D11*(1-MIN(tp_g/tp_roe,0.8))/(1+tp_r)^4+Val!D12*(1-MIN(tp_g/tp_roe,0.8))/(1+tp_r)^5+Val!D13*(1-MIN(tp_g/tp_roe,0.8))/(1+tp_r)^6+Val!D13*(1-MIN(tp_g/tp_roe,0.8))*(1+tp_g)/(tp_r-tp_g)/(1+tp_r)^6))*(1+tp_r) -> 336.53956 | H44: =H4 -> 671.1501 | I44: =0.7*G44+(1-0.7)*H44 -> 436.92272 | J44: =I44/I$4-1 -> -0.13282285
A45: 情境 B 全權重 | B45: — | C45: 只看情境 B（對照） | D45: =PL!E161 -> 29.076998 | E45: =PL!F161 -> 25.638067 | F45: =E45/E$4-1 -> 0 | G45: =(tp_wA*MAX(0,PL!E161*(1-MIN(tp_g/tp_roe,0.8))/(1+tp_r)^1+PL!F161*(1-MIN(tp_g/tp_roe,0.8))/(1+tp_r)^2+PL!G161*(1-MIN(tp_g/tp_roe,0.8))/(1+tp_r)^3+PL!H161*(1-MIN(tp_g/tp_roe,0.8))/(1+tp_r)^4+PL!I161*(1-MIN(tp_g/tp_roe,0.8))/(1+tp_r)^5+PL!J161*(1-MIN(tp_g/tp_roe,0.8))/(1+tp_r)^6+PL!J161*(1-MIN(tp_g/tp_roe,0.8))*(1+tp_g)/(tp_r-tp_g)/(1+tp_r)^6)+tp_wB*MAX(0,PL!E161*(1-MIN(tp_g/tp_roe,0.8))/(1+tp_r)^1+PL!F161*(1-MIN(tp_g/tp_roe,0.8))/(1+tp_r)^2+PL!G161*(1-MIN(tp_g/tp_roe,0.8))/(1+tp_r)^3+PL!H161*(1-MIN(tp_g/tp_roe,0.8))/(1+tp_r)^4+PL!I161*(1-MIN(tp_g/tp_roe,0.8))/(1+tp_r)^5+PL!J161*(1-MIN(tp_g/tp_roe,0.8))/(1+tp_r)^6+PL!J161*(1-MIN(tp_g/tp_roe,0.8))*(1+tp_g)/(tp_r-tp_g)/(1+tp_r)^6)+tp_wC*MAX(0,PL!E161*(1-MIN(tp_g/tp_roe,0.8))/(1+tp_r)^1+PL!F161*(1-MIN(tp_g/tp_roe,0.8))/(1+tp_r)^2+PL!G161*(1-MIN(tp_g/tp_roe,0.8))/(1+tp_r)^3+PL!H161*(1-MIN(tp_g/tp_roe,0.8))/(1+tp_r)^4+PL!I161*(1-MIN(tp_g/tp_roe,0.8))/(1+tp_r)^5+PL!J161*(1-MIN(tp_g/tp_roe,0.8))/(1+tp_r)^6+PL!J161*(1-MIN(tp_g/tp_roe,0.8))*(1+tp_g)/(tp_r-tp_g)/(1+tp_r)^6))*(1+tp_r) -> 317.83968 | H45: =Val!$B$33*(tp_wA*(2/12*PL!E161+10/12*PL!F161)+tp_wB*(2/12*PL!E161+10/12*PL!F161)+tp_wC*(2/12*PL!E161+10/12*PL!F161))*rm_factor -> 647.20343 | I45: =tp_w_dcf*G45+(1-tp_w_dcf)*H45 -> 482.52155 | J45: =I45/I$4-1 -> -0.042321115
A46: 情境 C 全權重 | B46: — | C46: 只看情境 C（對照） | D46: =PL!E210 -> 27.159923 | E46: =PL!F210 -> 17.590034 | F46: =E46/E$4-1 -> -0.31390952 | G46: =(tp_wA*MAX(0,PL!E210*(1-MIN(tp_g/tp_roe,0.8))/(1+tp_r)^1+PL!F210*(1-MIN(tp_g/tp_roe,0.8))/(1+tp_r)^2+PL!G210*(1-MIN(tp_g/tp_roe,0.8))/(1+tp_r)^3+PL!H210*(1-MIN(tp_g/tp_roe,0.8))/(1+tp_r)^4+PL!I210*(1-MIN(tp_g/tp_roe,0.8))/(1+tp_r)^5+PL!J210*(1-MIN(tp_g/tp_roe,0.8))/(1+tp_r)^6+PL!J210*(1-MIN(tp_g/tp_roe,0.8))*(1+tp_g)/(tp_r-tp_g)/(1+tp_r)^6)+tp_wB*MAX(0,PL!E210*(1-MIN(tp_g/tp_roe,0.8))/(1+tp_r)^1+PL!F210*(1-MIN(tp_g/tp_roe,0.8))/(1+tp_r)^2+PL!G210*(1-MIN(tp_g/tp_roe,0.8))/(1+tp_r)^3+PL!H210*(1-MIN(tp_g/tp_roe,0.8))/(1+tp_r)^4+PL!I210*(1-MIN(tp_g/tp_roe,0.8))/(1+tp_r)^5+PL!J210*(1-MIN(tp_g/tp_roe,0.8))/(1+tp_r)^6+PL!J210*(1-MIN(tp_g/tp_roe,0.8))*(1+tp_g)/(tp_r-tp_g)/(1+tp_r)^6)+tp_wC*MAX(0,PL!E210*(1-MIN(tp_g/tp_roe,0.8))/(1+tp_r)^1+PL!F210*(1-MIN(tp_g/tp_roe,0.8))/(1+tp_r)^2+PL!G210*(1-MIN(tp_g/tp_roe,0.8))/(1+tp_r)^3+PL!H210*(1-MIN(tp_g/tp_roe,0.8))/(1+tp_r)^4+PL!I210*(1-MIN(tp_g/tp_roe,0.8))/(1+tp_r)^5+PL!J210*(1-MIN(tp_g/tp_roe,0.8))/(1+tp_r)^6+PL!J210*(1-MIN(tp_g/tp_roe,0.8))*(1+tp_g)/(tp_r-tp_g)/(1+tp_r)^6))*(1+tp_r) -> 176.84151 | H46: =Val!$B$33*(tp_wA*(2/12*PL!E210+10/12*PL!F210)+tp_wB*(2/12*PL!E210+10/12*PL!F210)+tp_wC*(2/12*PL!E210+10/12*PL!F210))*rm_factor -> 473.71342 | I46: =tp_w_dcf*G46+(1-tp_w_dcf)*H46 -> 325.27747 | J46: =I46/I$4-1 -> -0.35440944
A48: 讀法：顆數情境 B、C 的差異從 FY2028 起；FY2027 只差委外相對值、全流程與 CPO。主流封測約占封測營收七成、EMS 約占營收三成五，所以主流成長率與現金流通率對 EPS 的影響大於 LEAP 單項；折舊年限與資本支出決定 FY2028 起的毛利率。
A118: 敏感度「逐案推導區塊」（以下每案三個情境各一區塊；不是案例列）
A120: 案例區塊：AI 部署 ×0.8（情境 A）
A121: 項目 | B121: 單位 | C121: FY2025A | D121: FY2026（錨點） | E121: FY2027 | F121: FY2028 | G121: FY2029 | H121: FY2030（收斂） | I121: FY2031（收斂） | J121: FY2032（收斂） | K121: 說明
A122: A. AI 加速器 → LEAP 先進封裝（D 欄＝FY2026 校準年；美元）
A123: AI 加速器顆數（含情境係數） | B123: 百萬顆 | D123: =units_26 -> 15.2 | E123: =units_27*0.8 -> 18.96 | F123: =units_28*um28_A*0.8 -> 21.2 | G123: =units_29*um29_A*0.8 -> 24.12
A124: 封裝面積指數（2026＝1） | B124: x | D124: =ar_26 -> 1 | E124: =ar_27 -> 1.278156 | F124: =ar_28 -> 1.428615 | G124: =ar_29 -> 1.431796
A125: 委外與份額相對值（2026＝1） | B125: x | D125: =1 -> 1 | E125: =rel27_A -> 1.1 | F125: =rel28_A -> 1.15 | G125: =rel29_A -> 1.2
A126: 每顆加速器 LEAP 核心內容（不含全流程、CPO） | B126: US$／顆 | D126: =D127*1000/D123 -> 236.84211 | E126: =$D126*E124^el -> 267.76317 | F126: =$D126*F124^el -> 283.08478 | G126: =$D126*G124^el -> 283.39976 | K126: FY2026 校準（Derived）；之後 × 封裝面積指數 ^ 彈性
A127: LEAP 核心（2.5D oS、先進測試等） | B127: US$B | D127: =leap26-D128-D129 -> 3.6 | E127: =E123*E125*E126/1000 -> 5.5844687 | F127: =F123*F125*F126/1000 -> 6.9016069 | G127: =G123*G125*G126/1000 -> 8.2027228 | K127: FY2026＝公司 LEAP 逾 US$4B − 全流程 − CPO；之後＝顆數 × 相對值 × 每顆內容
A128: 全流程（CoWoS full process） | B128: US$B | D128: =fp26 -> 0.3 | E128: =fp27_A -> 1.2 | F128: =E128*F123/E123*(1+fp_g) -> 1.7443038 | G128: =F128*G123/F123*(1+fp_g) -> 2.5799241
A129: CPO（共同封裝光學） | B129: US$B | D129: =cpo27*cpo_A_26/cpo_A_27 -> 0.1 | E129: =cpo27*cpo_A_27/cpo_A_27 -> 0.5 | F129: =cpo27*cpo_A_28/cpo_A_27*F123/E123 -> 1.1181435 | G129: =cpo27*cpo_A_29/cpo_A_27*G123/E123 -> 2.035443 | K129: 2027 情境 A＝公司逾 US$0.5B；依 Siliconomics 同字母 CPO 滲透率縮放（2028 起另乘顆數比）
A130: LEAP 合計 | B130: US$B | C130: =leap25 -> 1.6 | D130: =D127+D128+D129 -> 4 | E130: =E127+E128+E129 -> 7.2844687 | F130: =F127+F128+F129 -> 9.7640541 | G130: =G127+G128+G129 -> 12.81809
A131: 匯率 | B131: NT$/US$ | C131: =fx25 -> 31 | D131: =a26_leap/D130 -> 31.9 | E131: =fx -> 32 | F131: =fx -> 32 | G131: =fx -> 32 | K131: FY2026＝Q 頁 LEAP 新台幣 ÷ 美元（隱含）
A132: B. 營收分部（十億新台幣）
A133: LEAP 先進封裝（命題子列） | B133: NT$B | C133: =a25_leap -> 49.6 | D133: =a26_leap -> 127.6 | E133: =E130*E131 -> 233.103 | F133: =F130*F131 -> 312.44973 | G133: =G130*G131 -> 410.17888
A134: 主流封測 | B134: NT$B | C134: =a25_ms -> 339.628 | D134: =a26_ms -> 432.1302 | E134: =D134*(1+g_ms27) -> 496.94973 | F134: =E134*(1+g_msL) -> 531.73621 | G134: =F134*(1+g_msL) -> 568.95775
A135: 封測（ATM） | B135: NT$B | C135: =C133+C134 -> 389.228 | D135: =D133+D134 -> 559.7302 | E135: =E133+E134 -> 730.05273 | F135: =F133+F134 -> 844.18594 | G135: =G133+G134 -> 979.13662
A136: EMS（環旭） | B136: NT$B | C136: =a25_ems -> 259.079 | D136: =a26_ems -> 314.602 | E136: =D136*(1+g_ems27) -> 346.0622 | F136: =E136*(1+g_emsL) -> 363.36531 | G136: =F136*(1+g_emsL) -> 381.53358
A137: 沖銷及其他 | B137: NT$B | C137: =a25_elim -> -2.919 | D137: =a26_elim -> -3.1648491 | E137: =$D137/($D135+$D136)*(E135+E136) -> -3.8952486 | F137: =$D137/($D135+$D136)*(F135+F136) -> -4.371013 | G137: =$D137/($D135+$D136)*(G135+G136) -> -4.9252627 | K137: 依 FY2026 比例
A138: 營收 | B138: NT$B | C138: =C135+C136+C137 -> 645.388 | D138: =D135+D136+D137 -> 871.16735 | E138: =E135+E136+E137 -> 1072.2197 | F138: =F135+F136+F137 -> 1203.1802 | G138: =G135+G136+G137 -> 1355.7449 | H138: =G138*(1+H139) -> 1497.4666 | I138: =H138*(1+I139) -> 1620.6587 | J138: =I138*(1+J139) -> 1717.8983 | K138: FY2030 起為收斂法：營收年增由 FY2029 線性收斂到 fade_g、淨利率收斂到 fade_m（FY2032 達到），非驅動因子推導
A139: 營收年增 | B139: % | D139: =D138/C138-1 -> 0.34983506 | E139: =E138/D138-1 -> 0.23078497 | F139: =F138/E138-1 -> 0.12213967 | G139: =G138/F138-1 -> 0.1268012 | H139: =$G139+(fade_gA-$G139)*1/3 -> 0.10453413 | I139: =$G139+(fade_gA-$G139)*2/3 -> 0.082267066 | J139: =$G139+(fade_gA-$G139)*3/3 -> 0.06
A140: LEAP ÷ 封測營收 | B140: % | C140: =C133/C135 -> 0.12743174 | D140: =D133/D135 -> 0.22796697 | E140: =E133/E135 -> 0.31929611 | F140: =F133/F135 -> 0.37011956 | G140: =G133/G135 -> 0.41891894
A141: 封測年增 | B141: % | D141: =D135/C135-1 -> 0.43805225 | E141: =E135/D135-1 -> 0.30429398 | F141: =F135/E135-1 -> 0.15633558 | G141: =G135/F135-1 -> 0.15985895
A142: C. 資本支出、折舊、毛利與損益
A143: 資本支出 | B143: US$B | C143: =capex25 -> 5.5 | D143: =capex26 -> 11.5 | E143: =capex27 -> 13 | F143: =capi*F138/F131 -> 11.279815 | G143: =capi*G138/G131 -> 12.710109 | K143: FY2026 公司 US$11.5B；FY2027 公司「更大」；之後＝營收 × 資本支出率
A144: 資本支出（新台幣） | B144: NT$B | C144: =C143*C131 -> 170.5 | D144: =D143*31.9 -> 366.85 | E144: =E143*E131 -> 416 | F144: =F143*F131 -> 360.95407 | G144: =G143*G131 -> 406.72348
A145: 資本支出 ÷ 營收 | B145: % | C145: =C144/C138 -> 0.26418217 | D145: =D144/D138 -> 0.42110164 | E145: =E144/E138 -> 0.38798019 | F145: =F144/F138 -> 0.3 | G145: =G144/G138 -> 0.3
A146: 折舊攤提 | B146: NT$B | C146: =a25_da -> 75.255 | D146: =a26_da -> 97.124 | E146: =D146*(1-1/life)+D144/life -> 130.83975 | F146: =E146*(1-1/life)+E144/life -> 166.48478 | G146: =F146*(1-1/life)+F144/life -> 190.79344 | K146: 前一年 ×（1 − 1／年限）＋前一年資本支出 ÷ 年限
A147: 封測毛利 ＝ FY2026 ＋ 流通率 × 封測營收增量 − 折舊增量 | B147: NT$B | C147: =a25_agp -> 91.38 | D147: =a26_agp -> 164.62339 | E147: =$D147+ft*(E135-$D135)-(E146-$D146) -> 216.0689 | F147: =$D147+ft*(F135-$D135)-(F146-$D146) -> 237.49048 | G147: =$D147+ft*(G135-$D135)-(G146-$D146) -> 280.65716 | K147: 流通率為現金毛利口徑；折舊增量全數歸封測
A148: 封測毛利率 | B148: % | C148: =C147/C135 -> 0.23477242 | D148: =D147/D135 -> 0.29411203 | E148: =E147/E135 -> 0.29596342 | F148: =F147/F135 -> 0.28132484 | G148: =G147/G135 -> 0.28663738
A149: EMS 毛利 | B149: NT$B | C149: =a25_egp -> 23.695 | D149: =a26_egp -> 27.00552 | E149: =E136*ems_gm -> 29.415287 | F149: =F136*ems_gm -> 30.886051 | G149: =G136*ems_gm -> 32.430354
A150: 沖銷及其他毛利 | B150: NT$B | C150: =a25_lgp -> -0.882 | D150: =a26_lgp -> -0.94866214 | E150: =$D150/$D137*E137 -> -1.1675991 | F150: =$D150/$D137*F137 -> -1.3102093 | G150: =$D150/$D137*G137 -> -1.4763454
A151: 毛利 | B151: NT$B | C151: =C147+C149+C150 -> 114.193 | D151: =D147+D149+D150 -> 190.68025 | E151: =E147+E149+E150 -> 244.31659 | F151: =F147+F149+F150 -> 267.06632 | G151: =G147+G149+G150 -> 311.61116
A152: 毛利率 | B152: % | C152: =C151/C138 -> 0.17693697 | D152: =D151/D138 -> 0.21887901 | E152: =E151/E138 -> 0.22786057 | F152: =F151/F138 -> 0.22196701 | G152: =G151/G138 -> 0.22984498
A153: 營業費用 | B153: NT$B | C153: =a25_opx -> 63.437 | D153: =a26_opx -> 79.658 | E153: =D153*(1+phi*E139) -> 90.688321 | F153: =E153*(1+phi*F139) -> 97.334306 | G153: =F153*(1+phi*G139) -> 104.73957
A154: 營業利益 | B154: NT$B | C154: =C151-C153 -> 50.756 | D154: =D151-D153 -> 111.02225 | E154: =E151-E153 -> 153.62827 | F154: =F151-F153 -> 169.73201 | G154: =G151-G153 -> 206.87159
A155: 營業利益率 | B155: % | C155: =C154/C138 -> 0.078644164 | D155: =D154/D138 -> 0.12744078 | E155: =E154/E138 -> 0.14328059 | F155: =F154/F138 -> 0.14106948 | G155: =G154/G138 -> 0.15258888
A156: 營業外淨額 | B156: NT$B | C156: =a25_nonop -> 0.545 | D156: =a26_nonop -> 4.302 | E156: =nonop_f -> -5 | F156: =nonop_f -> -5 | G156: =nonop_f -> -5
A157: 稅前利益 | B157: NT$B | C157: =C154+C156 -> 51.301 | D157: =D154+D156 -> 115.32425 | E157: =E154+E156 -> 148.62827 | F157: =F154+F156 -> 164.73201 | G157: =G154+G156 -> 201.87159
A158: 所得稅 | B158: NT$B | C158: =a25_tax -> 9.461 | D158: =a26_tax -> 19.219732 | E158: =E157*tax -> 25.266806 | F158: =F157*tax -> 28.004442 | G158: =G157*tax -> 34.318171
A159: 非控制權益 | B159: NT$B | C159: =a25_nci -> 1.182 | D159: =a26_nci -> 2.543 | E159: =nci -> 3 | F159: =nci -> 3 | G159: =nci -> 3
A160: 歸屬母公司淨利 | B160: NT$B | C160: =C157-C158-C159 -> 40.658 | D160: =D157-D158-D159 -> 93.561514 | E160: =E157-E158-E159 -> 120.36146 | F160: =F157-F158-F159 -> 133.72757 | G160: =G157-G158-G159 -> 164.55342 | H160: =H138*H164 -> 186.96152 | I160: =I138*I164 -> 207.97729 | J160: =J138*J164 -> 226.42901
A161: 基本股數 | B161: 百萬股 | C161: =a25_sh -> 4339.1676 | D161: =a26_sh -> 4392.9011 | E161: =D161*(1+sh_g) -> 4414.8656 | F161: =E161*(1+sh_g) -> 4436.9399 | G161: =F161*(1+sh_g) -> 4459.1246 | H161: =G161*(1+sh_g) -> 4481.4202 | I161: =H161*(1+sh_g) -> 4503.8273 | J161: =I161*(1+sh_g) -> 4526.3464
A162: EPS（基本） | B162: NT$ | C162: =a25_eps -> 9.37 | D162: =a26_eps -> 21.28287 | E162: =E160/E161*1000 -> 27.26277 | F162: =F160/F161*1000 -> 30.139595 | G162: =G160/G161*1000 -> 36.90263 | H162: =H160/H161*1000 -> 41.719258 | I162: =I160/I161*1000 -> 46.1779 | J162: =J160/J161*1000 -> 50.024676
A163: EPS 年增 | B163: % | D163: =D162/C162-1 -> 1.2713842 | E163: =E162/D162-1 -> 0.28097245 | F163: =F162/E162-1 -> 0.10552212 | G163: =G162/F162-1 -> 0.22439036 | H163: =H162/G162-1 -> 0.13052262 | I163: =I162/H162-1 -> 0.10687253 | J163: =J162/I162-1 -> 0.083303386
A164: 淨利率（歸屬母公司淨利 ÷ 營收） | B164: % | C164: =C160/C138 -> 0.062997763 | D164: =D160/D138 -> 0.10739787 | E164: =E160/E138 -> 0.11225448 | F164: =F160/F138 -> 0.11114509 | G164: =G160/G138 -> 0.12137491 | H164: =$G164+(fade_mA-$G164)*1/3 -> 0.12485189 | I164: =$G164+(fade_mA-$G164)*2/3 -> 0.12832886 | J164: =$G164+(fade_mA-$G164)*3/3 -> 0.13180583
A165: 股東自由現金流（淨利＋折舊 − 資本支出；參考） | B165: NT$B | C165: =C160+C146-C144 -> -54.587 | D165: =D160+D146-D144 -> -176.16449 | E165: =E160+E146-E144 -> -164.79879 | F165: =F160+F146-F144 -> -60.741719 | G165: =G160+G146-G144 -> -51.376614 | K165: 不含營運資金與融資；只作參考，不進 DCF
A166: 營業利益增量（相對 FY2025）÷ FY2026 起累計資本支出 | B166: % | D166: =(D154-$C154)/SUM($D144:D144) -> 0.16428035 | E166: =(E154-$C154)/SUM($D144:E144) -> 0.13140738 | F166: =(F154-$C154)/SUM($D144:F144) -> 0.10401783 | G166: =(G154-$C154)/SUM($D144:G144) -> 0.10068547 | K166: 資本支出的稅前邊際報酬（核心問題之二）
A169: 案例區塊：AI 部署 ×0.8（情境 B）
A170: 項目 | B170: 單位 | C170: FY2025A | D170: FY2026（錨點） | E170: FY2027 | F170: FY2028 | G170: FY2029 | H170: FY2030（收斂） | I170: FY2031（收斂） | J170: FY2032（收斂） | K170: 說明
A171: A. AI 加速器 → LEAP 先進封裝（D 欄＝FY2026 校準年；美元）
A172: AI 加速器顆數（含情境係數） | B172: 百萬顆 | D172: =units_26 -> 15.2 | E172: =units_27*0.8 -> 18.96 | F172: =units_28*um28_B*0.8 -> 16.96 | G172: =units_29*um29_B*0.8 -> 20.502
A173: 封裝面積指數（2026＝1） | B173: x | D173: =ar_26 -> 1 | E173: =ar_27 -> 1.278156 | F173: =ar_28 -> 1.428615 | G173: =ar_29 -> 1.431796
...

Sheet Sources
A1: 來源（SEC 6-K 為公司原文；法說內容經逐字稿；券商、媒體與資料商皆為 Interested-party）
A2: 公司：3Q26 新聞稿與簡報（SEC 6-K，2026-10-29；3Q26 損益、分部、應用別、4Q26 指引、EBITDA、淨負債） | B2: https://www.sec.gov/Archives/edgar/data/0001122411/000095010326016323/dp255782_6k.htm
A3: 公司：2Q26 新聞稿與簡報（SEC 6-K，2026-07-30；1Q、2Q26 損益與分部、3Q26 指引、1H26 資本支出） | B3: https://www.sec.gov/Archives/edgar/data/0001122411/000095010326011353/dp250875_6k.htm
A4: 公司：4Q25 新聞稿與簡報（SEC 6-K，2026-02-05；FY2025、FY2024 損益與分部、LEAP 2025 US$1.6B、資本支出 US$5.5B） | B4: https://www.sec.gov/Archives/edgar/data/1122411/000095010326001662/dp241167_6k.htm
A5: 公司：3Q26 法說逐字稿（Motley Fool，2026-10-29；LEAP 逾 US$4B、2027 翻倍、全流程、CPO、資本支出 US$11.5B、稅率） | B5: https://www.fool.com/earnings/call-transcripts/2026/10/29/ase-asx-q3-2026-earnings-call-transcript/
A6: 媒體：數位時代 2Q26 法說（2026-07-30；LEAP 逾 3.5B、全流程 3 億美元、資本支出 10.5B 拆分） | B6: https://www.bnext.com.tw/article/91677/ase_leap_revenue_2027_capex
A7: 媒體：風傳媒 2Q26 法說（2026-07-30；營業外項目、3Q26 指引） | B7: https://www.storm.mg/article/11152966
A8: 券商：BofA（科技新報 2026-10-14 摘要；EPS 2026–28、目標價 900、LEAP 占比、資本支出） | B8: https://finance.technews.tw/2026/10/14/ase-technology-holding-co-ltd-reported-better-than-expected-results-for-the-third-quarter-of-2026/
A9: 價格：富邦證券 e 點通 3711 日線（10-30 收盤 668.00） | B9: https://fubon-ebrokerdj.fbs.com.tw/Z/ZC/ZCX/ZCX_3711.djhtm
A10: 資料商：stockanalysis（ADR 價格、前瞻 P/E） | B10: https://stockanalysis.com/stocks/asx/
A11: 資料商：macrotrends（ADR 年底 P/E 2016–2025） | B11: https://www.macrotrends.net/stocks/charts/ASX/ase-technology-holding/pe-ratio
A12: 資料商：macrotrends（ROE 2023–2025） | B12: https://www.macrotrends.net/stocks/charts/ASX/ase-technology-holding/roe
A13: 行業層：Siliconomics 快照 v0.10（20261031_Siliconomics_v0.10.xlsx）（加速器顆數、情境係數、CoWoS 每片封裝數、CPO 滲透率、匯率、部署 GW） | B13: siliconomics/data/siliconomics_snapshot_v0.10.json
... A15: SemiAnalysis | B15: 未使用
