Workbook

Sheet README
A1: Meta（META）個股模型 v0.1.1（2026-10-30）— 命題模組＋官方營收分部 → 損益表（完整 10-Q、法說與 follow-up call 補資料缺口）
A3: 命題：Meta 的 AI 資本支出（2026 指引 1,350–1,450 億美元，含融資租賃本金）能否由廣告現金流支撐，且自用算力（GPU＋自研 MTIA）是否帶來足以回本的廣告變現提升。
A4: 核心問題：FY2028 AI 增量營業利益（讀法 2：自用 AI 影子效益＝自用在役 MW × Tokenomics 每 MW 持有成本）能否覆蓋 AI 資本支出的資金成本；收支關卡＝FY2026–FY2030 自由現金流扣股利合計。
A5: ="投資建議："&Val!B14&"（加權目標價 US$"&TEXT(Val!B8,"0.00")&"，上檔空間 "&TEXT(Val!B11,"+0.0%;-0.0%")&"；現價 "&TEXT(px,"0.00")&"，2026-10-28 收盤；每股為 Class C 股票股利前口徑）" -> 投資建議：買進（加權目標價 US$844.10，上檔空間 +37.8%；現價 612.49，2026-10-28 收盤；每股為 Class C 股票股利前口徑）
A6: ="重點觀察 1：目標價 "&TEXT(Val!B8,"0")&"＝DCF "&TEXT(Val!B6,"0")&"、分部加總 "&TEXT(Val!B7,"0")&" 各半；情境 A／B／C 為 "&TEXT(Val!B17,"0")&"／"&TEXT(Val!C17,"0")&"／"&TEXT(Val!D17,"0")&"；讀法 1 目標價 "&TEXT(Val!B21,"0")&"。市場共識目標價 "&TEXT(cons_tp,"0")&"。" -> 重點觀察 1：目標價 844＝DCF 793、分部加總 896 各半；情境 A／B／C 為 933／844／755；讀法 1 目標價 429。市場共識目標價 833。
A7: ="重點觀察 2：FY2028 自用 AI 影子效益（B）"&TEXT(Thesis!I113,"0.0")&"，對自用 AI 增量成本（營運＋新增 AI 折舊）"&TEXT(Thesis!I108,"0.0")&"；FY2028 Advertising A／B／C 為 "&TEXT(PL!I12,"0")&"／"&TEXT(PL!I59,"0")&"／"&TEXT(PL!I106,"0")&"，合併營業利益率（財報口徑，B）由 FY2025 "&TEXT(PL!D84,"0.0%")&" 變為 FY2028 "&TEXT(PL!I84,"0.0%")&"。" -> 重點觀察 2：FY2028 自用 AI 影子效益（B）107.9，對自用 AI 增量成本（營運＋新增 AI 折舊）70.9；FY2028 Advertising A／B／C 為 381／362／344，合併營業利益率（財報口徑，B）由 FY2025 41.4% 變為 FY2028 24.5%。
A8: ="重點觀察 3：收支關卡（FY2026–2030 自由現金流扣股利合計）A／B／C＝"&TEXT(CF!B6,"0.0")&"／"&TEXT(CF!C6,"0.0")&"／"&TEXT(CF!D6,"0.0")&"；B 情境 "&CF!C9&"。FY2027 資本支出（B）"&TEXT(CF!H54,"0")&"，自用 AI MW 由評價日 "&TEXT(mw_tot0,"#,##0")&" 增至 FY2028 年底 "&TEXT(Thesis!I81,"#,##0")&"。" -> 重點觀察 3：收支關卡（FY2026–2030 自由現金流扣股利合計）A／B／C＝-19.6／15.0／49.0；B 情境 需要舉債。FY2027 資本支出（B）206，自用 AI MW 由評價日 5,038 增至 FY2028 年底 14,678。
A10: 驅動 → 推導對照表（每頁輸入、推導量、因果方向）
A11: 頁 | B11: 輸入（In 頁鍵） | C11: 推導量 | D11: 因果方向
A12: Thesis | B12: capex_g、cx27_A／B／C、cx_na、selfb、a28、cip_0、cip_ai、Tokenomics IF_CapexIT／Facility／OpexGW／HoldEcon | C12: 自用 AI MW、AI 資本支出、新增 AI 折舊、自用 AI 增量營運成本、影子效益 | D12: 資本支出 → MW（C10）→ 折舊與營運成本 → FoA 營業利益；MW → 影子效益（讀法 2）
A13: Seg | B13: 近四季年增（Q 頁）、gl_impr、gl_price、pA／pC、gl_other、gl_rl、conv_n | C13: Advertising（曝光 × 價格）、Other revenue、FoA、RL、合併營收；非 AI 資本支出與折舊 | D13: 近四季年增 → 長期值；Advertising＝B 路徑 ×(1＋價格情境調整)
A14: PL | B14: m_foa（Q 頁）、inc_m、rl_loss26／27／32、rl_da_sh、tax、一次性項目 | C14: 分部 EBITDA、分部營業利益、合併營業利益、EPS（財報／排除一次性／評價口徑） | D14: 分部營收 → EBITDA − 折舊 → 營業利益 → 業外、稅 → EPS
A15: CF | B15: sbc_r、wc_k、ag_pay、dps、bb_t、min_cash、mcps、fwd_cash | C15: 自由現金流、股利、回購、新債、淨現金、收支關卡 | D15: 淨利＋折舊 − 協議付款 − 資本支出 → 自由現金流 → 股利 → 回購／舉債
A16: Val | B16: rf、beta、erp、kd_sp、g_tv、ronic_sp、同業倍數、ads_mode、rl_mode、tp_w*、w_dcf | C16: DCF、分部加總、目標價、上檔空間、投資建議 | D16: 無槓桿 FCF 折現＋分部 EBITDA × 倍數 → 情境加權 → 50／50
A17: Sens | B17: In 頁敏感度低／高 | C17: 加權目標價變動 | D17: 一次改一個輸入、整本重算
A19: 本版要點（v0.1.1）
A20: 架構同 v0.1（Alphabet v0.3.2 範本）：命題（自用 AI MW）＋官方分部 → 損益表 → 現金流 → DCF 50%＋分部加總 50%；情境 25／50／25；讀法 2 主值。v0.1.1 以完整 10-Q（106 頁，入庫）、法說與 follow-up call 逐字稿（不入庫）補資料缺口。
A21: 更正（完整 10-Q）：多州檢察長協議費用前三季合計 11.89（v0.1 只計 Q3 的 9.89）→ 其他法律應計類債 9.99 → 7.99。協議 12.7 原文只寫十年分年支付、未載各年金額 → 維持等額（H3）；前高後低（第一年約 4.04，由流動／非流動應計推論）只進 Sens。
A22: 小修：強制轉換特別股改用淨額 12.46（424B5 承銷折扣）；DCF 的遠期出售現金以 ke 自 FY2027 期中折現；分部加總補扣 FY2028–FY2029 特別股股利。
A23: 資料缺口：10-Q 未單獨揭露融資租賃負債（使用權資產 11.70）→ 基準 0、Sens 上限 11.70；未載伺服器耐用年限 → 維持 6 年；買回授權剩餘 25.03（2026 年未買回）。
A24: 法說與 follow-up call：2027 資本支出未量化（Q4 法說才給）、RL 2027 虧損約 15（已在模型）、未提 MTIA；自建為主、以第三方雲端補近期容量、自建／租用比例未揭露 → 只寫 Recon，不填數值（H2）。
A26: 工作表：README → In → Q → Thesis → Seg → PL → CF → Val → Recon → Sens → Sources。藍字＝輸入、黑字＝公式；黃底＝判斷題。建置：bash meta/make_v01.sh
A27: 數字標記：Verified（公司正式財報或申報文件）／Interested-party（公司指引、賣方、第三方網站）／Analogy／Assumed（給區間）／Derived（換算）。每股數字為 Class C 股票股利（2027-01 下旬，1:1）前的口徑。

Sheet In
A1: In — 輸入（藍字；基準欄 E 進主模型；D／F＝敏感度低／高，只用於 Sens 頁、不進目標價；情境 A／B／C 的驅動見本頁最後一節「情境驅動對照」）。金額 US$B；每股 US$（Class C 股票股利前口徑）；股數十億股；MW＝IT MW。標記：Verified／Interested-party／Analogy／Assumed／Derived（Analogy、Assumed 一律給低／高區間）
A2: 事實總帳：data/meta_facts_2026q3.json（facts_2026q3.py 兩讀核對，648 筆；v0.1.1 加完整 10-Q、424B5、follow-up call）；Tokenomics v21.7 快照（data/tokenomics_snapshot_v21.7.json）；共識 data/consensus_meta_20261030.json；同業 data/peers_ads_20261030.json（五家 2026-10-07 基準＋GOOGL）。評價日 2026-09-30，目標時點 2027-10-30。黃底＝判斷題（Andy 可改）
A3: 鍵 | B3: 項目 | C3: 單位 | D3: 敏感度低 | E3: 基準 | F3: 敏感度高 | G3: 標記 | H3: 來源 | I3: 說明
A4: A. 現價、股數與資產負債（評價日 2026-09-30）
A5: px | B5: 現價（2026-10-28 收盤；10-29 收盤只找到一個來源） | C5: US$ | E5: 612.49 | G5: Verified | H5: StockScan https://stockscan.io/stocks/META/price-history（10-28 −1.24%）；Digrin、TipRanks（10-27 620.19 − 7.70）相符（consensus_meta_20261030.json priceReference） | I5: 工作單 M8：10-29 收盤需兩個來源一致；2026-10-30 再查只有 ChartRow「as of close, Oct 29, 2026」624.55（+1.97%）一個來源（https://chartrow.com/quote/meta），故用 10-28。只影響上檔空間與評等
A6: px_val | B6: 評價日股價（2026-09-30 收盤；WACC 權益權重用） | C6: US$ | E6: 725.18 | G6: Verified | H6: TipRanks 歷史股價 https://www.tipranks.com/stocks/meta/historical-prices（2026-10-30 讀取：9/29 738.79、9/30 725.18）；StockScan 9/30 −1.84%（738.79 × 0.9816＝725.20，相符）
A7: sh_out | B7: 流通股數（2026-10-16，10-Q 封面 Class A＋B） | C7: 十億股 | E7: 2.556241 | G7: Verified | H7: 10-Q 封面兩類相加（2026-10-29；事實總帳 sh.out.20261016）
A8: sh_dil_q3 | B8: 2026Q3 稀釋加權股數 | C8: 十億股 | E8: 2.573 | G8: Verified | H8: Meta 2026Q3 財報新聞稿（8-K 附件 99.1）表格（2026-10-21；事實總帳 is.sh_d.2026q3）
A9: sh_basic_q3 | B9: 2026Q3 基本加權股數 | C9: 十億股 | E9: 2.552 | G9: Verified | H9: Meta 2026Q3 財報新聞稿（8-K 附件 99.1）表格（2026-10-21；事實總帳 is.sh_b.2026q3） | I9: 期末稀釋股數＝Q3 稀釋加權＋(流通股 − Q3 基本加權)
A10: cash_0 | B10: 現金＋有價證券（2026-09-30） | C10: US$B | E10: 82.449 | G10: Verified | H10: 新聞稿資產負債表：現金 11.222＋有價證券 71.227（事實總帳 bs.cash／bs.mktsec.20260930）
A11: cash_ye25 | B11: 現金＋有價證券（2025-12-31） | C11: US$B | E11: 81.592 | G11: Verified | H11: 新聞稿資產負債表 35.873＋45.719
A12: debt_0 | B12: 票據面額（2026-09-30） | C12: US$B | E12: 84 | G12: Verified | H12: Meta 10-Q 2026Q3 長期債務附註（2026-10-29；事實總帳 debt.face.20260930） | I12: 帳面 83.669＝流動 2.747＋非流動 80.922
A13: debt_ye25 | B13: 長期債務帳面（2025-12-31，非流動） | C13: US$B | E13: 58.744 | G13: Verified | H13: Meta 2025Q4 財報新聞稿（8-K 附件 99.1）資產負債表（2026-01-28；事實總帳 bs.ltd.20251231） | I13: 只作 CF 頁期初顯示；9M26 期末直接取 debt_0
A14: fin_lease | B14: 融資租賃負債（類債） | C14: US$B | E14: 0 | F14: 11.704 | G14: Assumed | H14: 完整 10-Q 未單獨揭露融資租賃負債（資產負債表無此科目；附註 8 其他流動 13.993／非流動 5.041 未拆）；融資租賃使用權資產 11.704（Meta 10-Q 2026Q3（完整 PDF 第 19 頁；mag/extract/docs/2026Q3/meta_2026Q3_10-Q.pdf）（2026-10-29；事實總帳 fl.rou.20260930）） | I14: 基準 0：Meta 融資租賃多為預付，本金支付已含在資本支出（公司口徑，收支關卡與 MAG 一致扣本金）；高＝使用權資產 11.704 當上限（只進 Sens）。仍為資料缺口（10-K 租賃附註）
A15: legal_oth | B15: 其他法律相關應計（類債）＝法律應計 19.881 − 協議費用前三季合計 11.89 | C15: US$B | D15: 0 | E15: 7.991 | G15: Derived | H15: Meta 10-Q 2026Q3（2026-10-29；事實總帳 legal.accrual.20260930）；協議費用 Meta 10-Q 2026Q3（完整 PDF 第 47 頁；mag/extract/docs/2026Q3/meta_2026Q3_10-Q.pdf）（2026-10-29；事實總帳 legal.agCharge.ytd9m2026） | I15: 比照 Alphabet 應計罰款（類債）；低＝0（不扣）。v0.1.1 更正：v0.1 只扣 Q3 的 9.89（得 9.991），完整 10-Q 載協議費用前三季合計 11.89（Q3 以前已認列約 2.00），協議應計已由 ag_y1／ag_rest 現金付款計入
A16: mcps | B16: 6.50% 強制轉換特別股募得現金淨額（2026-10-29 交割，評價日後；毛額 12.5 − 承銷折扣 0.0416） | C16: US$B | E16: 12.458375 | G16: Verified | H16: 424B5 封面推算（2026-10-27；事實總帳 eq.mcps.net）；Meta 424B5（Series A 存託股）封面（2026-10-27；事實總帳 eq.mcps.uwDisc） | I16: v0.1.1：改用淨額（v0.1 用毛額 12.5）；發行費用未揭露、不扣；超額配售（約 1.8）未知是否行使，不計
A17: conv_sh | B17: 強制轉換特別股 2029-08 轉換股數（上限） | C17: 十億股 | D17: 0.017025 | E17: 0.02 | F17: 0.02 | G17: Derived | H17: FWP：每股特別股（1,000 美元）轉 1.3620–1.6000 股 Class A；12.5B ÷ 1,000 × 1.6＝20.0M 股（上限） | I17: 取稀釋最大（保守）；轉換前股利照付
A18: pref_2H | B18: 強制轉換特別股股利 Q4 26E | C18: US$B | E18: 0 | G18: Assumed | H18: 6.50% × 12.5B＝0.8125／年；首次付息推定 2027-02，2029-08 轉換前最後一期（FY2029 約三季）
A19: pref_27 | B19: 強制轉換特別股股利 FY2027E | C19: US$B | E19: 0.8125 | G19: Assumed
A20: pref_28 | B20: 強制轉換特別股股利 FY2028E | C20: US$B | E20: 0.8125 | G20: Assumed
A21: pref_29 | B21: 強制轉換特別股股利 FY2029E | C21: US$B | E21: 0.609 | G21: Assumed
A22: fwd_on | B22: Class A 遠期出售於 FY2027 交割（1＝計入；0＝不計） | C22: x | D22: 0 | E22: 1 | G22: Assumed | H22: Meta FWP 定價條款（2026-10-26；事實總帳 eq.fwd.shares）：40M 股、初始遠期價 622.91875、2027-11-19 前由公司選擇交割 | I22: 交割前公司不收款；目標時點 2027-10-30 前推定已交割（判斷）
A23: fwd_sh | B23: 遠期出售股數 | C23: 十億股 | E23: 0.04 | G23: Verified | H23: Meta FWP 定價條款（2026-10-26；事實總帳 eq.fwd.shares）
A24: fwd_cash | B24: 遠期出售淨額（初始遠期價 622.91875 × 40M 股） | C24: US$B | E24: 24.9168 | G24: Derived | H24: Meta FWP 定價條款（2026-10-26；事實總帳 eq.fwd.shares） | I24: 超額配售 6M 股不計
A25: B. 折現率與目標價規則（同 Alphabet v0.3.2）
A26: rf | B26: 無風險利率（10 年美債，2026-10-27） | C26: % | E26: 0.0499 | G26: Verified | H26: 美國財政部每日殖利率曲線（10 Yr）2026-10-27 4.99%（Alphabet v0.3.1 In 頁 rf，2026-10-29 讀取） | I26: 本次重讀財政部網頁被擋（權限逾時），沿用同一讀值
A27: beta_cr | B27: 原始 β：ChartRow（期間未載） | C27: x | E27: 1.24 | G27: Interested-party | H27: https://chartrow.com/quote/meta（2026-10-30 讀取，as of close Oct 29, 2026）
A28: beta_cd | B28: 原始 β：CoinDataFlow「Beta (5Y Monthly)」 | C28: x | E28: 1.185 | G28: Interested-party | H28: https://coindataflow.com/en/stock/META（Updated 2026-10-30 00:37 UTC） | I28: StockAnalysis 統計頁讀取被擋（權限逾時）
A29: blume_a | B29: Blume 調整係數 | C29: x | E29: 0.67 | G29: Derived | H29: Blume（1971）；同 Alphabet
A30: beta | B30: β（Blume 調整後兩個來源的中位數） | C30: x | D30: 1.124 | E30: =MEDIAN(blume_a*beta_cr+1-blume_a,blume_a*beta_cd+1-blume_a) -> 1.142375 | F30: 1.1608 | G30: Derived | H30: 同 Alphabet 修正一 F4 | I30: 低／高＝兩個來源各自的調整值
A31: erp | B31: 股權風險溢酬 | C31: % | D31: 0.04 | E31: 0.05 | F31: 0.06 | G31: Assumed | H31: 同 Alphabet（MAG v0.2.2 val.erp）
A32: kd_sp | B32: 約 10 年期 AA− 公司債利差 | C32: % | D32: 0.004 | E32: 0.007 | F32: 0.01 | G32: Assumed | H32: 判斷：Meta 評等 AA−／Aa3 級（未入事實總帳）；10 年期利差約 50–100bp
A33: kd | B33: 稅前債務成本＝rf＋利差 | C33: % | E33: =rf+kd_sp -> 0.0569 | G33: Derived | H33: 同 Alphabet
A34: wacc_adj | B34: WACC 調整（Sens 格：±1pt） | C34: % | D34: -0.01 | E34: 0 | F34: 0.01 | G34: Assumed | H34: 同 Alphabet
A35: g_tv | B35: 永續成長率（FY2032 後） | C35: % | D35: 0.02 | E35: 0.03 | F35: 0.04 | G35: Assumed | H35: 同 Alphabet
A36: ronic_sp | B36: 永續期 RONIC 相對 WACC 的差 | C36: % | E36: 0 | F36: 0.05 | G36: Assumed | H36: 同 Alphabet 修正一 F5：RONIC＝WACC | I36: Sens：WACC＋5pt
A37: mid | B37: 期中慣例：年度現金流距年初 | C37: 年 | E37: 0.5 | G37: Derived | H37: 同 Alphabet
A38: t_val | B38: 評價日（2026-09-30）的年份小數 | C38: 年 | E38: 2026.75 | G38: Derived | H38: 同 Alphabet
A39: t_q4 | B39: Q4 26 現金流折現年數（期中） | C39: 年 | E39: 0.125 | G39: Derived | H39: 2026-10-01～12-31 中點
A40: tp_wA | B40: 情境權重 A | C40: % | E40: 0.25 | G40: Assumed | H40: 同 Alphabet（A 25%／B 50%／C 25%）
A41: tp_wB | B41: 情境權重 B | C41: % | E41: 0.5 | G41: Assumed | H41: 同上
A42: tp_wC | B42: 情境權重 C | C42: % | E42: 0.25 | G42: Assumed | H42: 同上
A43: w_dcf | B43: 目標價中 DCF 的權重（其餘＝分部加總） | C43: % | D43: 0.3 | E43: 0.5 | F43: 0.7 | G43: Assumed | H43: 同 Alphabet（DCF 50%＋分部加總 50%）
A44: t_tgt | B44: 目標時點距評價日（2026-09-30 → 2027-10-30） | C44: 年 | E44: 1.0822 | G44: Derived | H44: 395 天 ÷ 365
A45: w_ntm27 | B45: 目標時點 NTM 中 FY2027 的權重 | C45: % | E45: 0.1699 | G45: Derived | H45: (2027-12-31 − 2027-10-30) ÷ 365＝62 天
A46: cons_tp | B46: 市場共識目標價（平均） | C46: US$ | E46: 833.12 | G46: Interested-party | H46: MarketBeat https://www.marketbeat.com/stocks/NASDAQ/META/Forecast/（58 位，頁面 2026-10-22；consensus_meta_20261030.json） | I46: TipRanks 851.15（45 位，10-28）、valueinvesting 841.37；賣方有承銷關係（2026-10-26 股權融資），只作對照
A47: dps_tgt | B47: 評價日到目標時點的每股股利（推到目標價時扣除） | C47: US$ | E47: =dps/4+dps*(1+dps_g)*(1-w_ntm27) -> 2.3926078 | G47: Derived | H47: Q4 26 一季＋2027 年至 10-30
A48: internal_ai_reading | B48: 自用 AI 讀法（2＝主值：自用 AI 價值中性，計影子效益；1＝敏感度：只計成本） | C48: x | D48: 1 | E48: 2 | G48: Assumed | H48: 原則第 7 節（Andy 2026-10-27 15:03）：自用增量 MW × Tokenomics IF_HoldEcon（k＝1）＝影子效益（非財報營收），只進評價口徑 | I48: Meta 全部 AI 算力皆自用（無對外雲端）
A49: sbc_add | B49: DCF 加回股權報酬（1＝是；Sens 用） | C49: x | E49: 0 | F49: 1 | G49: Assumed | H49: 同 Alphabet：股權報酬視為真實成本、不加回
A50: tv_alt | B50: 終值改用 FY2032 無槓桿自由現金流 ×(1＋g)（1＝是；Sens 用） | C50: x | E50: 0 | F50: 1 | G50: Assumed | H50: 同 Alphabet
A51: C. 分部加總倍數：數位廣告同業 NTM EV/EBITDA（M7：五家 2026-10-07 基準＋GOOGL；中位數在 Val 頁計算）
A52: pm_ads_googl | B52: 數位廣告：Alphabet（GOOGL）NTM EV/EBITDA | C52: x | E52: 14.71 | G52: Derived | H52: data/peers_ads_20261030.json（GOOGL 由 repo 內 Alphabet 資料推算，2026-10-07） | I52: EV ÷ NTM EBITDA（MarketScreener 共識 FY1／FY2 時間加權）
A53: pm_ads_pins | B53: 數位廣告：Pinterest（PINS）NTM EV/EBITDA | C53: x | E53: 6.91 | G53: Derived | H53: data/peers_ads_20261030.json（2026-10-07 基準，未更新） | I53: EV ÷ NTM EBITDA（MarketScreener 共識 FY1／FY2 時間加權）
A54: pm_ads_ttd | B54: 數位廣告：The Trade Desk（TTD）NTM EV/EBITDA | C54: x | E54: 6.53 | G54: Derived | H54: data/peers_ads_20261030.json（2026-10-07 基準，未更新） | I54: EV ÷ NTM EBITDA（MarketScreener 共識 FY1／FY2 時間加權）
A55: pm_ads_app | B55: 數位廣告：AppLovin（APP）NTM EV/EBITDA | C55: x | E55: 11.38 | G55: Derived | H55: data/peers_ads_20261030.json（2026-10-07 基準，未更新） | I55: EV ÷ NTM EBITDA（MarketScreener 共識 FY1／FY2 時間加權）
A56: pm_ads_rddt | B56: 數位廣告：Reddit（RDDT）NTM EV/EBITDA | C56: x | E56: 13.63 | G56: Derived | H56: data/peers_ads_20261030.json（2026-10-07 基準，未更新） | I56: EV ÷ NTM EBITDA（MarketScreener 共識 FY1／FY2 時間加權）
A57: pm_ads_snap | B57: 數位廣告：Snap（SNAP）NTM EV/EBITDA | C57: x | E57: 7.43 | G57: Derived | H57: data/peers_ads_20261030.json（2026-10-07 基準，未更新） | I57: EV ÷ NTM EBITDA（MarketScreener 共識 FY1／FY2 時間加權）
A58: pm_meta_own | B58: Meta 自身 NTM EV/EBITDA（2026-10-28；只作對照與 Sens） | C58: x | E58: 8.99 | G58: Derived | H58: data/peers_ads_20261030.json selfReference（10-07 為 10.79）
A59: ads_mode | B59: FoA 與 RL 的倍數（0＝六家中位數；1＝GOOGL；2＝Meta 自身） | C59: x | E59: 0 | F59: 2 | G59: Assumed | H59: M7：同業照 A 段檔，預設中位數；Alphabet v0.3.2 對 Alphabet 用大型同業（META）而非小型廣告科技，對應到 Meta 為 GOOGL 14.71×，列 Sens 與判斷題 | I59: Sens：GOOGL 14.71×（高）／Meta 自身 8.99×
A60: rl_mode | B60: Reality Labs 在分部加總的計法（0＝NTM EBITDA × 廣告倍數，虧損為負值；1＝以 0 計） | C60: x | E60: 0 | F60: 1 | G60: Assumed | H60: 判斷：同 Alphabet 對 Alphabet 層級負 EBITDA 的處理（× 倍數）；DCF 已逐年扣 RL 虧損 | I60: Sens：RL 以 0 計
A61: D. 命題模組：自用 AI 容量（M4：由資本支出經 Tokenomics 每 MW 資本支出反推，同 Alphabet C10；MTIA 不套 NonNV 係數）
A62: cx_na | B62: 非 AI 資本支出占營收（辦公室、一般伺服器、網路；其餘＝AI） | C62: % | D62: 0.02 | E62: 0.04 | F62: 0.07 | G62: Assumed | H62: 判斷：Meta 2019（AI 前）資本支出約占營收兩成含一般資料中心；2025 起公司稱資本支出主要為 AI 基礎設施（法說） | I62: 決定歷年資本支出中 AI 的部分與預測期非 AI 資本支出
A63: cx_23 | B63: FY2023 資本支出（含融資租賃本金） | C63: US$B | E63: 28.1 | G63: Interested-party | H63: Meta 2023 年第四季財報新聞稿（全年 28.10B）；未入本版事實總帳（只用於 2029 年汰換 MW）
A64: ai_23 | B64: FY2023 及以前機隊：AI 占資本支出比例（換算 2023 年底以前的 AI MW） | C64: % | D64: 0.5 | E64: 0.7 | F64: 0.9 | G64: Assumed | H64: 判斷：2023 年 H100 採購開始放量 | I64: 只影響 FY2029 汰換資本支出
A65: cx_24 | B65: FY2024 資本支出（購置不動產與設備＋融資租賃本金） | C65: US$B | E65: 39.225 | G65: Verified | H65: 事實總帳 cf.capex_ppe.fy2024＋cf.fl_principal.fy2024
A66: cx_25 | B66: FY2025 資本支出（含融資租賃本金） | C66: US$B | E66: 72.215 | G66: Verified | H66: 購置不動產與設備＋融資租賃本金（推導；事實總帳 cf.capexInclFL.fy2025） | I66: 新聞稿文字 72.22 相符
A67: capex_9m | B67: 2026 年 9M 資本支出（含融資租賃本金） | C67: US$B | E67: 85.824 | G67: Verified | H67: 購置不動產與設備＋融資租賃本金（推導；事實總帳 cf.capexInclFL.ytd9m2026） | I67: 購置不動產與設備 83.055＋融資租賃本金 2.769
A68: capex_g | B68: 2026 資本支出指引中點（含融資租賃本金） | C68: US$B | D68: 135 | E68: 140 | F68: 145 | G68: Interested-party | H68: Meta 2026Q3 財報新聞稿 CFO Outlook Commentary（2026-10-21；事實總帳 txt.guid_capex2026.2026q3） | I68: C10：FY2026＝9M 實績＋Q4 公式＝本值（Q4 新增 MW 以公式反推，不需迭代）
A69: cx27_k | B69: M6：FY2027 資本支出基準值＝2026 指引中點 ×(1＋2026 年增率 × 本係數) | C69: x | D69: 0.25 | E69: 0.5 | F69: 0.75 | G69: Assumed | H69: 工作單 M6：法說 2027 無數字（逐字稿「until we get to the Q4 call」，事實總帳 call.capex2027）→ 2026 年增率的一半 | I69: Sens：1/4／3/4
A70: cx27_up | B70: M6：情境 A／C 的 FY2027 資本支出相對 B 的幅度 | C70: % | E70: 0.15 | G70: Assumed | H70: 工作單 M6：A／C 各 ±15%
A71: cx27_B | B71: 情境 B：FY2027 資本支出（含融資租賃本金） | C71: US$B | E71: =capex_g*(1+(capex_g/cx_25-1)*cx27_k) -> 205.70588 | G71: Assumed | H71: M6；共識 FY2027 購置不動產與設備 193.06（MarketScreener，財報前、不含租賃本金）
A72: cx27_A | B72: 情境 A：FY2027 資本支出（AI 變現提升 → 加碼投資） | C72: US$B | E72: =cx27_B*(1+cx27_up) -> 236.56176 | G72: Assumed | H72: M6：B × 1.15
A73: cx27_C | B73: 情境 C：FY2027 資本支出（變現提升消退 → 放緩） | C73: US$B | E73: =cx27_B*(1-cx27_up) -> 174.85 | G73: Assumed | H73: M6：B × 0.85
A74: a28 | B74: FY2028 新增 MW ÷ FY2027 新增 MW | C74: x | D74: 0.8 | E74: 1 | F74: 1.2 | G74: Assumed | H74: 同 Alphabet（2027、2028 同速）；FY2029 起收斂
A75: conv_mw | B75: FY2029 起 MW 新增速度收斂年數（到 FY2032 只剩 g × 期初 MW） | C75: 年 | E75: 4 | G75: Assumed | H75: 同 Alphabet 修正一 F5
A76: selfb | B76: 自建機房比例（租用部分不計機房資本支出） | C76: % | D76: 0.75 | E76: 0.85 | F76: 0.95 | G76: Assumed | H76: 同 Alphabet（MAG v0.2.2 capexModel.selfBuild）；Meta 合資（Hyperion）與租賃在表外
A77: am_26 | B77: 2026 新增中 GB300 錨占比（其餘 VR200 錨） | C77: % | E77: 1 | G77: Assumed | H77: 同 Alphabet；MTIA 無揭露，全部按 GPU 世代（M4）
A78: am_27 | B78: 2027 新增中 GB300 錨占比（其餘 VR200 錨） | C78: % | E78: 0.5 | G78: Assumed | H78: 同 Alphabet
A79: am_28 | B79: 2028 起新增中 VR200 錨占比（其餘 GB300 錨） | C79: % | E79: 1 | G79: Assumed | H79: 同 Alphabet
A80: cip_0 | B80: 在建工程（2026-09-30） | C80: US$B | E80: 89.499 | G80: Verified | H80: Meta 10-Q 2026Q3 不動產與設備附註（2026-10-29；事實總帳 ppe.cip.20260930） | I80: Q4 26 起轉入在役：折舊同 Alphabet；MW 處理不同——本模型把在建工程對應 MW 計入增量在役 MW（有影子效益與營運成本），Alphabet 修正三不另增 MW（待判斷）
A81: cip_ai | B81: 在建工程中 AI 占比 | C81: % | D81: 0.8 | E81: 0.9 | F81: 1 | G81: Assumed | H81: 判斷：與 2026 年 AI 占資本支出比例（約 9 成，見 Thesis）一致 | I81: 在建工程對應的 MW 在 Q4 26 轉入在役 → 自用增量（影子效益與營運成本）
A82: cip_it | B82: 在建工程中 IT（伺服器與網通）占比 | C82: % | D82: 0.5 | E82: 0.6 | F82: 0.7 | G82: Assumed | H82: 判斷：Meta 未揭露；Alphabet 2026Q2 約 60% | I82: IT 依 life_it、其餘依 life_fac 折舊
A83: life_it | B83: AI IT 折舊年限（年；汰換週期） | C83: 年 | D83: 5 | E83: 6 | F83: 7 | G83: Assumed | H83: Tokenomics IF_DeprLifeIT 6 年；Meta 自 2025 起伺服器耐用年限 5.5 年（公開資訊，未入事實總帳） | I83: 整數年（汰換排程用）。完整 10-Q 未載耐用年限（只寫會計政策與 10-K 相比無重大變動，PDF 第 12 頁）→ 不改；10-Q 隱含：Q3 伺服器折舊 5.34 × 4 ÷ 伺服器毛額 133.6 ≈ 6.3 年（含未滿一年資產，粗估）
A84: life_fac | B84: 機房折舊年限 | C84: 年 | D84: 15 | E84: 20 | F84: 25 | G84: Derived | H84: Tokenomics IF_CapexFacility 12.67 ÷ IF_DeprFac 0.634＝20 年
A85: life_na | B85: 非 AI 資本支出折舊年限 | C85: 年 | D85: 8 | E85: 10 | F85: 15 | G85: Assumed | H85: 同 Alphabet
A86: phi_0 | B86: 資本支出當期折舊比例（年度批次） | C86: x | D86: 0 | E86: 0.25 | F86: 0.5 | G86: Assumed | H86: 同 Alphabet
A87: phi_q4 | B87: Q4 26 批次（在建工程轉入與 Q4 資本支出）當期折舊比例（年） | C87: x | D87: 0.0625 | E87: 0.125 | F87: 0.25 | G87: Assumed | H87: 判斷：季中上線 → 一季的一半（0.125 年）；最後一年補足 1 − 本值（全期合計＝金額） | I87: Alphabet 以 phi_0（0.25）計 Q4 批次，使 Q4 折舊跳升；高＝Alphabet 口徑
A88: da_base | B88: 評價日在役資產年折舊（2026Q3 × 4） | C88: US$B/年 | E88: 28.616 | G88: Derived | H88: Meta 2026Q3 財報新聞稿（8-K 附件 99.1）表格（2026-10-21；事實總帳 cf.da.2026q3） × 4
A89: rent_l | B89: 租用算力年租金滿載值（尚未起租租賃＋第三方雲端；只進 Sens） | C89: US$B/年 | E89: 0 | F89: 17.79 | G89: Assumed | H89: Meta 10-Q 2026Q3 租賃附註（2026-10-29；事實總帳 lease.notCommenced.20260930）：355.73 ÷ 約 20 年租期（假設）＝17.79／年；第三方雲端與 AI token 成本法說未給金額 | I89: M4（chat 端審查第 4 條）：不進基準，只放 Recon 與 Sens；FY2027 起 1/3、FY2028 2/3、FY2029 起全額；讀法 2 下與影子效益同樣價值中性（只影響現金流與收支關卡）
A90: he_h | B90: IF_HoldEcon｜H100（每 MW 年持有成本，經濟口徑） | C90: US$m/MW-年 | D90: 6.7910747 | E90: 9.7030873 | F90: 16.66377 | G90: Derived | H90: data/tokenomics_snapshot_v21.7.json（Interface!C13:Q13） | I90: 讀法 2 影子效益的每 MW 值（k＝1）
A91: he_b2 | B91: IF_HoldEcon｜GB200（每 MW 年持有成本，經濟口徑） | C91: US$m/MW-年 | D91: 6.6118163 | E91: 8.8281656 | F91: 14.318575 | G91: Derived | H91: data/tokenomics_snapshot_v21.7.json（Interface!C13:Q13） | I91: 讀法 2 影子效益的每 MW 值（k＝1）
A92: he_b3 | B92: IF_HoldEcon｜GB300（每 MW 年持有成本，經濟口徑） | C92: US$m/MW-年 | D92: 8.4288991 | E92: 10.886411 | F92: 18.534646 | G92: Derived | H92: data/tokenomics_snapshot_v21.7.json（Interface!C13:Q13） | I92: 讀法 2 影子效益的每 MW 值（k＝1）
A93: he_vr | B93: IF_HoldEcon｜VR200（每 MW 年持有成本，經濟口徑） | C93: US$m/MW-年 | D93: 9.2190715 | E93: 12.225471 | F93: 19.750627 | G93: Derived | H93: data/tokenomics_snapshot_v21.7.json（Interface!C13:Q13） | I93: 讀法 2 影子效益的每 MW 值（k＝1）
A94: opx_h | B94: IF_OpexGW｜H100（每 MW 年營運費用，不含折舊） | C94: US$m/MW-年 | E94: 1.8846675 | G94: Derived | H94: data/tokenomics_snapshot_v21.7.json
A95: opx_b2 | B95: IF_OpexGW｜GB200（每 MW 年營運費用，不含折舊） | C95: US$m/MW-年 | E95: 1.8122327 | G95: Derived | H95: data/tokenomics_snapshot_v21.7.json
A96: opx_b3 | B96: IF_OpexGW｜GB300（每 MW 年營運費用，不含折舊） | C96: US$m/MW-年 | E96: 1.9826348 | G96: Derived | H96: data/tokenomics_snapshot_v21.7.json
A97: opx_vr | B97: IF_OpexGW｜VR200（每 MW 年營運費用，不含折舊） | C97: US$m/MW-年 | E97: 2.0934955 | G97: Derived | H97: data/tokenomics_snapshot_v21.7.json
A98: cit_h | B98: IF_CapexIT｜H100（每 MW IT 資本支出） | C98: US$m/MW | E98: 27.510214 | G98: Derived | H98: data/tokenomics_snapshot_v21.7.json
A99: cit_b2 | B99: IF_CapexIT｜GB200（每 MW IT 資本支出） | C99: US$m/MW | E99: 24.015174 | G99: Derived | H99: data/tokenomics_snapshot_v21.7.json
A100: cit_b3 | B100: IF_CapexIT｜GB300（每 MW IT 資本支出） | C100: US$m/MW | E100: 32.237224 | G100: Derived | H100: data/tokenomics_snapshot_v21.7.json
...

Sheet Q
A1: Q — 實績（US$B；EPS 美元；股數十億股）。資料取自 data/meta_facts_2026q3.json（四季財報新聞稿兩讀核對：SEC 8-K 附件 99.1 與 IR 網站 PDF；比較欄取自後一季新聞稿）[Verified]
A2: 核對列（實績必須為 0）：Advertising＋Other revenue＝Family of Apps、分部合計＝合併營收、分部營業利益合計＝合併營業利益、營收 − 成本費用＝營業利益、FCF＝營運現金 − 資本支出（含租賃本金）；FY2025 四季合計對年報取超出四捨五入容差（0.002）的部分
A3: 項目 | B3: 2024Q4 | C3: 2025Q1 | D3: 2025Q2 | E3: 2025Q3 | F3: 2025Q4 | G3: 2026Q1 | H3: 2026Q2 | I3: 2026Q3 | J3: FY2024 | K3: FY2025 | L3: 9M26 | M3: 近四季 TTM | N3: 前四季 | O3: 標記 | P3: 來源
A4: 營收（官方分部與子列）
A5: Advertising | B5: 46.783 | C5: 41.392 | D5: 46.563 | E5: 50.082 | F5: 58.137 | G5: 55.024 | H5: 59.363 | I5: 63.061 | J5: 160.633 | K5: 196.175 | L5: =G5+H5+I5 -> 177.448 | M5: =SUM(F5:I5) -> 235.585 | N5: =SUM(B5:E5) -> 184.82 | O5: Verified | P5: Meta 各季財報新聞稿（8-K 附件 99.1；事實總帳 data/meta_facts_2026q3.json）
A6: Other revenue | B6: 0.519 | C6: 0.51 | D6: 0.583 | E6: 0.69 | F6: 0.801 | G6: 0.885 | H6: 1.007 | I6: 1.097 | J6: 1.722 | K6: 2.584 | L6: =G6+H6+I6 -> 2.989 | M6: =SUM(F6:I6) -> 3.79 | N6: =SUM(B6:E6) -> 2.302 | O6: Verified | P6: Meta 各季財報新聞稿（8-K 附件 99.1；事實總帳 data/meta_facts_2026q3.json）
A7: Family of Apps（分部） | B7: 47.302 | C7: 41.902 | D7: 47.146 | E7: 50.772 | F7: 58.938 | G7: 55.909 | H7: 60.37 | I7: 64.158 | J7: 162.355 | K7: 198.759 | L7: =G7+H7+I7 -> 180.437 | M7: =SUM(F7:I7) -> 239.375 | N7: =SUM(B7:E7) -> 187.122 | O7: Verified | P7: Meta 各季財報新聞稿（8-K 附件 99.1；事實總帳 data/meta_facts_2026q3.json）
A8: 檢查：Advertising＋Other revenue－Family of Apps | B8: =B5+B6-B7 -> 0 | C8: =C5+C6-C7 -> 0 | D8: =D5+D6-D7 -> 0 | E8: =E5+E6-E7 -> 0 | F8: =F5+F6-F7 -> 0 | G8: =G5+G6-G7 -> 0 | H8: =H5+H6-H7 -> 0 | I8: =I5+I6-I7 -> 0 | ... K8: =K5+K6-K7 -> 0 | L8: =G8+H8+I8 -> 0 | M8: =SUM(F8:I8) -> 0 | N8: =SUM(B8:E8) -> 0 | O8: — | P8: —
A9: Reality Labs（分部） | B9: 1.083 | C9: 0.412 | D9: 0.37 | E9: 0.47 | F9: 0.955 | G9: 0.402 | H9: 0.431 | I9: 0.443 | J9: 2.146 | K9: 2.207 | L9: =G9+H9+I9 -> 1.276 | M9: =SUM(F9:I9) -> 2.231 | N9: =SUM(B9:E9) -> 2.335 | O9: Verified | P9: Meta 各季財報新聞稿（8-K 附件 99.1；事實總帳 data/meta_facts_2026q3.json）
A10: 合併營收 | B10: 48.385 | C10: 42.314 | D10: 47.516 | E10: 51.242 | F10: 59.893 | G10: 56.311 | H10: 60.801 | I10: 64.601 | J10: 164.501 | K10: 200.966 | L10: =G10+H10+I10 -> 181.713 | M10: =SUM(F10:I10) -> 241.606 | N10: =SUM(B10:E10) -> 189.457 | O10: Verified | P10: Meta 各季財報新聞稿（8-K 附件 99.1；事實總帳 data/meta_facts_2026q3.json）
A11: 檢查：分部合計－合併營收 | B11: =B7+B9-B10 -> 0 | C11: =C7+C9-C10 -> 0 | D11: =D7+D9-D10 -> 0 | E11: =E7+E9-E10 -> 0 | F11: =F7+F9-F10 -> 0 | G11: =G7+G9-G10 -> 0 | H11: =H7+H9-H10 -> 0 | I11: =I7+I9-I10 -> 0 | ... K11: =K7+K9-K10 -> 0 | L11: =G11+H11+I11 -> 0 | M11: =SUM(F11:I11) -> 0 | N11: =SUM(B11:E11) -> 0 | O11: — | P11: —
A13: 分部營業利益
A14: Family of Apps 營業利益 | B14: 28.332 | C14: 21.765 | D14: 24.971 | E14: 24.967 | F14: 30.766 | G14: 26.9 | H14: 23.394 | I14: 17.117 | J14: 87.109 | K14: 102.469 | L14: =G14+H14+I14 -> 67.411 | M14: =SUM(F14:I14) -> 98.177 | N14: =SUM(B14:E14) -> 100.035 | O14: Verified | P14: Meta 各季財報新聞稿（8-K 附件 99.1；事實總帳 data/meta_facts_2026q3.json）
A15: Reality Labs 營業損益 | B15: -4.967 | C15: -4.21 | D15: -4.53 | E15: -4.432 | F15: -6.021 | G15: -4.028 | H15: -4.619 | I15: -4.129 | J15: -17.729 | K15: -19.193 | L15: =G15+H15+I15 -> -12.776 | M15: =SUM(F15:I15) -> -18.797 | N15: =SUM(B15:E15) -> -18.139 | O15: Verified | P15: Meta 各季財報新聞稿（8-K 附件 99.1；事實總帳 data/meta_facts_2026q3.json）
A16: 合併營業利益 | B16: 23.365 | C16: 17.555 | D16: 20.441 | E16: 20.535 | F16: 24.745 | G16: 22.872 | H16: 18.775 | I16: 12.988 | J16: 69.38 | K16: 83.276 | L16: =G16+H16+I16 -> 54.635 | M16: =SUM(F16:I16) -> 79.38 | N16: =SUM(B16:E16) -> 81.896 | O16: Verified | P16: Meta 各季財報新聞稿（8-K 附件 99.1；事實總帳 data/meta_facts_2026q3.json）
A17: 檢查：分部營業利益合計－合併營業利益 | B17: =B14+B15-B16 -> 0 | C17: =C14+C15-C16 -> 0 | D17: =D14+D15-D16 -> 0 | E17: =E14+E15-E16 -> 0 | F17: =F14+F15-F16 -> 0 | G17: =G14+G15-G16 -> 0 | H17: =H14+H15-H16 -> 0 | I17: =I14+I15-I16 -> 0 | ... K17: =K14+K15-K16 -> 0 | L17: =G17+H17+I17 -> 0 | M17: =SUM(F17:I17) -> 0 | N17: =SUM(B17:E17) -> 0 | O17: — | P17: —
A19: 合併損益
A20: 營業成本 | B20: 8.839 | C20: 7.572 | D20: 8.491 | E20: 9.206 | F20: 10.905 | G20: 10.218 | H20: 11.33 | I20: 13.369 | J20: 30.161 | K20: 36.175 | L20: =G20+H20+I20 -> 34.917 | M20: =SUM(F20:I20) -> 45.822 | N20: =SUM(B20:E20) -> 34.108 | O20: Verified | P20: Meta 各季財報新聞稿（8-K 附件 99.1；事實總帳 data/meta_facts_2026q3.json）
A21: 研發費用 | B21: 12.18 | C21: 12.15 | D21: 12.942 | E21: 15.144 | F21: 17.136 | G21: 17.699 | H21: 21.656 | I21: 20.054 | J21: 43.873 | K21: 57.372 | L21: =G21+H21+I21 -> 59.409 | M21: =SUM(F21:I21) -> 76.545 | N21: =SUM(B21:E21) -> 52.416 | O21: Verified | P21: Meta 各季財報新聞稿（8-K 附件 99.1；事實總帳 data/meta_facts_2026q3.json）
A22: 行銷費用 | B22: 3.24 | C22: 2.757 | D22: 2.979 | E22: 2.845 | F22: 3.41 | G22: 2.908 | H22: 3.431 | I22: 3.333 | J22: 11.347 | K22: 11.991 | L22: =G22+H22+I22 -> 9.672 | M22: =SUM(F22:I22) -> 13.082 | N22: =SUM(B22:E22) -> 11.821 | O22: Verified | P22: Meta 各季財報新聞稿（8-K 附件 99.1；事實總帳 data/meta_facts_2026q3.json）
A23: 管理費用（含法律費用） | B23: 0.761 | C23: 2.28 | D23: 2.663 | E23: 3.512 | F23: 3.697 | G23: 2.614 | H23: 5.609 | I23: 14.857 | J23: 9.74 | K23: 12.152 | L23: =G23+H23+I23 -> 23.08 | M23: =SUM(F23:I23) -> 26.777 | N23: =SUM(B23:E23) -> 9.216 | O23: Verified | P23: Meta 各季財報新聞稿（8-K 附件 99.1；事實總帳 data/meta_facts_2026q3.json）
A24: 檢查：營收 − 成本費用 − 營業利益 | B24: =B10-B20-B21-B22-B23-B16 -> 0 | C24: =C10-C20-C21-C22-C23-C16 -> 0 | D24: =D10-D20-D21-D22-D23-D16 -> 0 | E24: =E10-E20-E21-E22-E23-E16 -> 0 | F24: =F10-F20-F21-F22-F23-F16 -> 0 | G24: =G10-G20-G21-G22-G23-G16 -> 0 | H24: =H10-H20-H21-H22-H23-H16 -> 0 | I24: =I10-I20-I21-I22-I23-I16 -> 0 | ... K24: =K10-K20-K21-K22-K23-K16 -> 0 | L24: =G24+H24+I24 -> 0 | M24: =SUM(F24:I24) -> 0 | N24: =SUM(B24:E24) -> 0 | O24: — | P24: —
A25: 利息與其他收益淨額 | B25: 0.188 | C25: 0.827 | D25: 0.093 | E25: 1.128 | F25: 0.609 | G25: -1.12 | H25: -0.019 | I25: 0.013 | J25: 1.283 | K25: 2.656 | L25: =G25+H25+I25 -> -1.126 | M25: =SUM(F25:I25) -> -0.517 | N25: =SUM(B25:E25) -> 2.236 | O25: Verified | P25: Meta 各季財報新聞稿（8-K 附件 99.1；事實總帳 data/meta_facts_2026q3.json）
A26: 稅前利益 | B26: 23.553 | C26: 18.382 | D26: 20.534 | E26: 21.663 | F26: 25.354 | G26: 21.752 | H26: 18.756 | I26: 13.001 | J26: 70.663 | K26: 85.932 | L26: =G26+H26+I26 -> 53.509 | M26: =SUM(F26:I26) -> 78.863 | N26: =SUM(B26:E26) -> 84.132 | O26: Verified | P26: Meta 各季財報新聞稿（8-K 附件 99.1；事實總帳 data/meta_facts_2026q3.json）
A27: 檢查：營業利益＋業外 − 稅前利益 | B27: =B16+B25-B26 -> 0 | C27: =C16+C25-C26 -> 0 | D27: =D16+D25-D26 -> 0 | E27: =E16+E25-E26 -> 0 | F27: =F16+F25-F26 -> 0 | G27: =G16+G25-G26 -> 0 | H27: =H16+H25-H26 -> 0 | I27: =I16+I25-I26 -> 0 | ... K27: =K16+K25-K26 -> 0 | L27: =G27+H27+I27 -> 0 | M27: =SUM(F27:I27) -> 0 | N27: =SUM(B27:E27) -> 0 | O27: — | P27: —
A28: 所得稅（負值＝利益） | B28: 2.715 | C28: 1.738 | D28: 2.197 | E28: 18.954 | F28: 2.586 | G28: -5.021 | H28: 2.908 | I28: 3.141 | J28: 8.303 | K28: 25.474 | L28: =G28+H28+I28 -> 1.028 | M28: =SUM(F28:I28) -> 3.614 | N28: =SUM(B28:E28) -> 25.604 | O28: Verified | P28: Meta 各季財報新聞稿（8-K 附件 99.1；事實總帳 data/meta_facts_2026q3.json）
A29: 淨利 | B29: 20.838 | C29: 16.644 | D29: 18.337 | E29: 2.709 | F29: 22.768 | G29: 26.773 | H29: 15.848 | I29: 9.86 | J29: 62.36 | K29: 60.458 | L29: =G29+H29+I29 -> 52.481 | M29: =SUM(F29:I29) -> 75.249 | N29: =SUM(B29:E29) -> 58.528 | O29: Verified | P29: Meta 各季財報新聞稿（8-K 附件 99.1；事實總帳 data/meta_facts_2026q3.json）
A30: 檢查：稅前 − 所得稅 − 淨利 | B30: =B26-B28-B29 -> 0 | C30: =C26-C28-C29 -> 0 | D30: =D26-D28-D29 -> 0 | E30: =E26-E28-E29 -> 0 | F30: =F26-F28-F29 -> 0 | G30: =G26-G28-G29 -> 0 | H30: =H26-H28-H29 -> 0 | I30: =I26-I28-I29 -> 0 | ... K30: =K26-K28-K29 -> 0 | L30: =G30+H30+I30 -> 0 | M30: =SUM(F30:I30) -> 0 | N30: =SUM(B30:E30) -> 0 | O30: — | P30: —
A31: 稀釋加權股數（十億股） | B31: 2.599 | C31: 2.59 | D31: 2.57 | E31: 2.572 | F31: 2.565 | G31: 2.564 | H31: 2.566 | I31: 2.573 | J31: 2.614 | K31: 2.574 | L31: =2.568 -> 2.568 | O31: Verified | P31: Meta 各季財報新聞稿（8-K 附件 99.1；事實總帳 data/meta_facts_2026q3.json）
A32: EPS（GAAP 稀釋，美元） | B32: 8.02 | C32: 6.43 | D32: 7.14 | E32: 1.05 | F32: 8.88 | G32: 10.44 | H32: 6.18 | I32: 3.83 | J32: 23.86 | K32: 23.49 | L32: =20.44 -> 20.44 | M32: =SUM(F32:I32) -> 29.33 | N32: =SUM(B32:E32) -> 22.64 | O32: Verified | P32: Meta 各季財報新聞稿（8-K 附件 99.1；事實總帳 data/meta_facts_2026q3.json）
A34: 現金流與股東回饋
A35: 折舊與攤銷 | B35: 4.46 | C35: 3.9 | D35: 4.342 | E35: 4.963 | F35: 5.411 | G35: 5.999 | H35: 6.356 | I35: 7.154 | J35: 15.498 | K35: 18.616 | L35: =G35+H35+I35 -> 19.509 | M35: =SUM(F35:I35) -> 24.92 | N35: =SUM(B35:E35) -> 17.665 | O35: Verified | P35: Meta 各季財報新聞稿（8-K 附件 99.1；事實總帳 data/meta_facts_2026q3.json）
A36: 股權報酬（SBC） | B36: 4.262 | C36: 4.147 | D36: 4.834 | E36: 5.555 | F36: 5.89 | G36: 6.032 | H36: 7.658 | I36: 7.363 | J36: 16.69 | K36: 20.427 | L36: =G36+H36+I36 -> 21.053 | M36: =SUM(F36:I36) -> 26.943 | N36: =SUM(B36:E36) -> 18.798 | O36: Verified | P36: Meta 各季財報新聞稿（8-K 附件 99.1；事實總帳 data/meta_facts_2026q3.json）
A37: 營運現金流 | B37: 27.988 | C37: 24.026 | D37: 25.561 | E37: 29.999 | F37: 36.214 | G37: 32.226 | H37: 31.862 | I37: 32.786 | J37: 91.328 | K37: 115.8 | L37: =G37+H37+I37 -> 96.874 | M37: =SUM(F37:I37) -> 133.088 | N37: =SUM(B37:E37) -> 107.574 | O37: Verified | P37: Meta 各季財報新聞稿（8-K 附件 99.1；事實總帳 data/meta_facts_2026q3.json）
A38: 購置不動產與設備 | B38: 14.425 | C38: 12.941 | D38: 16.538 | E38: 18.829 | F38: 21.383 | G38: 18.997 | H38: 30.116 | I38: 33.942 | J38: 37.256 | K38: 69.691 | L38: =G38+H38+I38 -> 83.055 | M38: =SUM(F38:I38) -> 104.438 | N38: =SUM(B38:E38) -> 62.733 | O38: Verified | P38: Meta 各季財報新聞稿（8-K 附件 99.1；事實總帳 data/meta_facts_2026q3.json）
A39: 融資租賃本金支付 | B39: 0.411 | C39: 0.751 | D39: 0.474 | E39: 0.545 | F39: 0.754 | G39: 0.843 | H39: 0.962 | I39: 0.964 | J39: 1.969 | K39: 2.524 | L39: =G39+H39+I39 -> 2.769 | M39: =SUM(F39:I39) -> 3.523 | N39: =SUM(B39:E39) -> 2.181 | O39: Verified | P39: Meta 各季財報新聞稿（8-K 附件 99.1；事實總帳 data/meta_facts_2026q3.json）
A40: 資本支出（含融資租賃本金；公司口徑） | B40: =B38+B39 -> 14.836 | C40: =C38+C39 -> 13.692 | D40: =D38+D39 -> 17.012 | E40: =E38+E39 -> 19.374 | F40: =F38+F39 -> 22.137 | G40: =G38+G39 -> 19.84 | H40: =H38+H39 -> 31.078 | I40: =I38+I39 -> 34.906 | ... K40: =K38+K39 -> 72.215 | L40: =G40+H40+I40 -> 85.824 | M40: =SUM(F40:I40) -> 107.961 | N40: =SUM(B40:E40) -> 64.914 | O40: Derived | P40: Meta 各季財報新聞稿（8-K 附件 99.1；事實總帳 data/meta_facts_2026q3.json）
A41: 自由現金流（公司定義） | B41: 13.152 | C41: 10.334 | D41: 8.549 | E41: 10.625 | F41: 14.077 | G41: 12.386 | H41: 0.784 | I41: -2.12 | J41: 52.103 | K41: 43.585 | L41: =G41+H41+I41 -> 11.05 | M41: =SUM(F41:I41) -> 25.127 | N41: =SUM(B41:E41) -> 42.66 | O41: Verified | P41: Meta 各季財報新聞稿（8-K 附件 99.1；事實總帳 data/meta_facts_2026q3.json）
A42: 檢查：營運現金流 − 資本支出（含租賃本金）− 自由現金流 | B42: =B37-B40-B41 -> 0 | C42: =C37-C40-C41 -> 0 | D42: =D37-D40-D41 -> 0 | E42: =E37-E40-E41 -> 0 | F42: =F37-F40-F41 -> 0 | G42: =G37-G40-G41 -> 0 | H42: =H37-H40-H41 -> 0 | I42: =I37-I40-I41 -> 0 | ... K42: =K37-K40-K41 -> 0 | L42: =G42+H42+I42 -> 0 | M42: =SUM(F42:I42) -> 0 | N42: =SUM(B42:E42) -> 0 | O42: — | P42: —
A43: 買回 | B43: 0 | C43: 12.754 | D43: 10.167 | E43: 3.327 | F43: 0 | G43: 0 | H43: 0 | I43: 0 | J43: 30.125 | K43: 26.248 | L43: =G43+H43+I43 -> 0 | M43: =SUM(F43:I43) -> 0 | N43: =SUM(B43:E43) -> 26.248 | O43: Verified | P43: Meta 各季財報新聞稿（8-K 附件 99.1；事實總帳 data/meta_facts_2026q3.json）
A44: 股利 | B44: 1.269 | C44: 1.329 | D44: 1.327 | E44: 1.33 | F44: 1.338 | G44: 1.346 | H44: 1.353 | I44: 1.361 | J44: 5.072 | K44: 5.324 | L44: =G44+H44+I44 -> 4.06 | M44: =SUM(F44:I44) -> 5.398 | N44: =SUM(B44:E44) -> 5.255 | O44: Verified | P44: Meta 各季財報新聞稿（8-K 附件 99.1；事實總帳 data/meta_facts_2026q3.json）
A46: 命題指標與一次性項目（新聞稿文字段；%＝年增）
A47: 廣告曝光數年增 | F47: 0.18 | G47: 0.19 | H47: 0.14 | I47: 0.1 | O47: Verified | P47: Meta 各季財報新聞稿（8-K 附件 99.1；事實總帳 data/meta_facts_2026q3.json）
A48: 每則廣告平均價格年增 | F48: 0.06 | G48: 0.12 | H48: 0.12 | I48: 0.14 | O48: Verified | P48: Meta 各季財報新聞稿（8-K 附件 99.1；事實總帳 data/meta_facts_2026q3.json）
A49: 每日活躍人數 DAP（十億人） | F49: 3.58 | G49: 3.56 | H49: 3.6 | I49: 3.64 | O49: Verified | P49: Meta 各季財報新聞稿（8-K 附件 99.1；事實總帳 data/meta_facts_2026q3.json）
A50: 一次性：法律費用（營業利益內） | H50: 2.4 | I50: 9.89 | L50: =SUM(G50:I50) -> 12.29 | O50: Verified | P50: Meta 各季財報新聞稿（8-K 附件 99.1；事實總帳 data/meta_facts_2026q3.json）
A51: 一次性：遣散費用（營業利益內） | H51: 1.18 | L51: =SUM(G51:I51) -> 1.18 | O51: Verified | P51: Meta 各季財報新聞稿（8-K 附件 99.1；事實總帳 data/meta_facts_2026q3.json）
A52: 一次性：CAMT 所得稅利益 | G52: 8.03 | L52: =SUM(G52:I52) -> 8.03 | O52: Verified | P52: Meta 各季財報新聞稿（8-K 附件 99.1；事實總帳 data/meta_facts_2026q3.json）
A54: 核對彙總（實績必須為 0）
A55: 檢查：上列核對列絕對值合計（8 季＋FY2024＋FY2025） | B55: =SUMPRODUCT(ABS(B8:K8))+SUMPRODUCT(ABS(B11:K11))+SUMPRODUCT(ABS(B17:K17))+SUMPRODUCT(ABS(B24:K24))+SUMPRODUCT(ABS(B27:K27))+SUMPRODUCT(ABS(B30:K30))+SUMPRODUCT(ABS(B42:K42)) -> 0
A56: 檢查：FY2025 四季合計 − 年報（超出四捨五入容差 0.002 的部分） | B56: =MAX(0,ABS(SUM(C5:F5)-K5)-0.002)+MAX(0,ABS(SUM(C6:F6)-K6)-0.002)+MAX(0,ABS(SUM(C7:F7)-K7)-0.002)+MAX(0,ABS(SUM(C9:F9)-K9)-0.002)+MAX(0,ABS(SUM(C14:F14)-K14)-0.002)+MAX(0,ABS(SUM(C15:F15)-K15)-0.002)+MAX(0,ABS(SUM(C20:F20)-K20)-0.002)+MAX(0,ABS(SUM(C21:F21)-K21)-0.002)+MAX(0,ABS(SUM(C22:F22)-K22)-0.002)+MAX(0,ABS(SUM(C23:F23)-K23)-0.002)+MAX(0,ABS(SUM(C37:F37)-K37)-0.002)+MAX(0,ABS(SUM(C35:F35)-K35)-0.002)+MAX(0,ABS(SUM(C36:F36)-K36)-0.002)+MAX(0,ABS(SUM(C38:F38)-K38)-0.002)+MAX(0,ABS(SUM(C39:F39)-K39)-0.002)+MAX(0,ABS(SUM(C29:F29)-K29)-0.002) -> 0
A57: 檢查：9M26（三季合計）− 2026Q3 新聞稿年初至今欄（超出四捨五入容差 0.002 的部分） | B57: =MAX(0,ABS(L5-(177.449))-0.002)+MAX(0,ABS(L6-(2.987))-0.002)+MAX(0,ABS(L9-(1.276))-0.002)+MAX(0,ABS(L10-(181.712))-0.002)+MAX(0,ABS(L14-(67.41))-0.002)+MAX(0,ABS(L15-(-12.775))-0.002)+MAX(0,ABS(L16-(54.635))-0.002)+MAX(0,ABS(L29-(52.481))-0.002)+MAX(0,ABS(L35-(19.509))-0.002)+MAX(0,ABS(L36-(21.053))-0.002)+MAX(0,ABS(L37-(96.873))-0.002)+MAX(0,ABS(L38-(83.055))-0.002)+MAX(0,ABS(L39-(2.769))-0.002) -> 0
A59: 推導量（Seg、PL 頁的起始值；[Derived]）
A60: 項目 | B60: 數值 | C60: 說明
A61: 近四季年增：Advertising（金額） | B61: =M5/N5-1 -> 0.27467265 | C61: (2025Q4–2026Q3) ÷ (2024Q4–2025Q3) − 1
A62: 最新一季年增：Advertising（2026Q3） | B62: =I5/E5-1 -> 0.25915499
A63: 近四季平均：廣告曝光數年增 | B63: =AVERAGE(F47:I47) -> 0.1525 | C63: 公司只揭露年增率；四季簡單平均
A64: 起始：廣告曝光數年增（g0_q＝1 時用 2026Q3） | B64: =IF(g0_q=1,I47,g0_impr_ttm) -> 0.1525
A65: 起始：每則廣告價格年增（＝(1＋廣告金額年增) ÷ (1＋曝光年增) − 1） | B65: =(1+IF(g0_q=1,g0_ads_q,g0_ads_ttm))/(1+g0_impr)-1 -> 0.10600664 | C65: 以金額年增反推，使曝光 × 價格＝廣告金額年增；近四季公司揭露價格年增平均 +11.0%
A66: 近四季年增：Other revenue | B66: =IF(g0_q=1,I6/E6-1,M6/N6-1) -> 0.64639444
A67: 近四季年增：Reality Labs 營收 | B67: =IF(g0_q=1,I9/E9-1,M9/N9-1) -> -0.044539615
A68: 9M26 一次性項目（營業利益內：法律 2.40＋遣散 1.18＋法律 9.89） | B68: =ot_legal_q2+ot_sev_q2+ot_legal_q3 -> 13.47
A69: FoA EBITDA 率（9M26；排除一次性；營業利益＋一次性＋折舊 ×(1 − RL 占比)） | B69: =(L14+ot_oi_9m+L35*(1-rl_da_sh))/L7 -> 0.55096543
A70: FoA EBITDA 率（2026Q3 單季；排除一次性） | B70: =(I14+ot_legal_q3+I35*(1-rl_da_sh))/I7 -> 0.52687584
A71: 對照：FoA EBITDA 率（FY2025） | B71: =(K14+K35*(1-rl_da_sh))/K7 -> 0.60452206
A72: FoA EBITDA 率（預測期採用；自用 AI 增量成本另計） | B72: =IF(mb_q3=1,m_foa_q3,m_foa_9m) -> 0.55096543
A73: 9M26 合併營收 | B73: =L10 -> 181.713

Sheet Thesis
A1: Thesis — 命題模組：Meta 的 AI 算力全部自用。資本支出（指引與 M6）÷ Tokenomics 每 MW 資本支出 → 自用 AI MW（同 Alphabet C10）；MW → 新增 AI 折舊、自用 AI 增量營運成本（相對評價日在役機隊）→ FoA 營業利益；讀法 2：自用增量 MW × IF_HoldEcon（k＝1）＝影子效益（只進評價口徑）
A2: 期初機隊：FY2023（Assumed）、FY2024、FY2025、2026 年 9M 的 AI 資本支出（資本支出 − 營收 × cx_na）各以當年錨世代的每 MW 資本支出（IT＋自建比例 × 機房）換算；在建工程對應的 MW 於 Q4 26 轉入在役。MTIA 無揭露 → 全部按 GPU 世代（M4，不套 NonNV）。不計尚未起租租賃與第三方雲端（M4；Recon、Sens）→ 可能低估自用算力
A4: A. 期初機隊（單一數值，C 欄；三情境共用）
A5: 項目 | B5: 單位 | C5: 數值 | N5: 說明
A6: 每 MW 資本支出：H100 錨（IT＋自建比例 × 機房） | B6: US$m/MW | C6: =cit_h+selfb*cfac -> 38.279714
A7: 每 MW 資本支出：GB200 錨 | B7: US$m/MW | C7: =cit_b2+selfb*cfac -> 34.784674
A8: 每 MW 資本支出：GB300 錨 | B8: US$m/MW | C8: =cit_b3+selfb*cfac -> 43.006724
A9: 每 MW 資本支出：2026 新增組合 | B9: US$m/MW | C9: =am_26*cit_b3+(1-am_26)*cit_vr+selfb*cfac -> 43.006724
A10: 每 MW 資本支出：2027 新增組合 | B10: US$m/MW | C10: =am_27*cit_b3+(1-am_27)*cit_vr+selfb*cfac -> 45.681288
A11: 每 MW 資本支出：2028 起新增組合 | B11: US$m/MW | C11: =(1-am_28)*cit_b3+am_28*cit_vr+selfb*cfac -> 48.355852
A12: FY2024 AI 資本支出（資本支出 − 營收 × cx_na） | B12: US$B | C12: =cx_24-Q!J10*cx_na -> 32.64496
A13: FY2025 AI 資本支出 | B13: US$B | C13: =cx_25-Q!K10*cx_na -> 64.17636
A14: 2026 年 9M AI 資本支出 | B14: US$B | C14: =capex_9m-Q!L10*cx_na -> 78.55548
A15: 2026 年 9M AI 占資本支出 | B15: % | C15: =aicx_9m/capex_9m -> 0.915309 | N15: 對照 cip_ai
A16: 2023 年底以前 AI MW（FY2023 × AI 比例 ÷ H100 錨） | B16: MW | C16: =cx_23*ai_23/pmw_h*1000 -> 513.84919 | N16: 只用於 FY2029 汰換
A17: FY2024 新增 AI MW（H100 錨） | B17: MW | C17: =aicx_24/pmw_h*1000 -> 852.80052
A18: FY2025 新增 AI MW（GB200 錨） | B18: MW | C18: =aicx_25/pmw_b2*1000 -> 1844.9608
A19: 2026 年 9M 新增 AI MW（GB300 錨） | B19: MW | C19: =aicx_9m/pmw_b3*1000 -> 1826.586
A20: 評價日 AI MW（支出口徑，含在建） | B20: MW | C20: =mw_pre24+mw_24+mw_25+mw_9m -> 5038.1965 | N20: Wattonomics 對照：本值為資本支出換算，非實際上線 MW
A21: 在建工程對應 MW（cip_0 × cip_ai ÷ GB300 錨） | B21: MW | C21: =cip_0*cip_ai/pmw_b3*1000 -> 1872.942 | N21: Q4 26 轉入在役
A22: 評價日在役 MW：H100 錨 | B22: MW | C22: =mw_pre24+mw_24 -> 1366.6497
A23: 評價日在役 MW：GB200 錨（在建工程超過 9M 新增的部分自此扣） | B23: MW | C23: =mw_25-MAX(0,mw_cip-mw_9m) -> 1798.6048
A24: 評價日在役 MW：GB300 錨 | B24: MW | C24: =MAX(0,mw_9m-mw_cip) -> 0
A25: 評價日在役 AI MW（基準機隊；其成本已在 FoA 利益率內） | B25: MW | C25: =base_h+base_b2+base_b3 -> 3165.2545
A26: 基準機隊每 MW IT 年折舊（IF_DeprIT 加權） | B26: US$m/MW-年 | C26: =(base_h*dpi_h+base_b2*dpi_b2+base_b3*dpi_b3)/base_tot -> 4.2540357
A27: 基準機隊每 MW 持有成本（IF_HoldEcon 加權） | B27: US$m/MW-年 | C27: =(base_h*he_h+base_b2*he_b2+base_b3*he_b3)/base_tot -> 9.2059271
A28: 基準機隊每 MW 營運費用（IF_OpexGW 加權） | B28: US$m/MW-年 | C28: =(base_h*opx_h+base_b2*opx_b2+base_b3*opx_b3)/base_tot -> 1.8435076
A30: 情境 A（AI 提高每則廣告價格）
A31: 項目 | B31: 單位 | C31: FY2024A | D31: FY2025A | E31: 9M26A | F31: Q4 26E | G31: FY2026E | H31: FY2027E | I31: FY2028E | J31: FY2029E | K31: FY2030E | L31: FY2031E | M31: FY2032E | N31: 說明
A32: B. 自用 AI 容量（MW；期末）
A33: 自用 AI MW 新增（Q4 26、FY2027 由資本支出反推；FY2028＝FY2027 × a28；FY2029 起收斂） | B33: MW | F33: =(capex_g-capex_9m-Seg!F22)/pmw_26*1000 -> 1188.7101 | G33: =F33 -> 1188.7101 | H33: =(cx27_A-Seg!H22)/pmw_27*1000 -> 4894.3519 | I33: =H33*a28 -> 4894.3519 | J33: =$I$33+(g_tv*I38-$I$33)*MIN(1,(2029-2028)/conv_mw) -> 3790.881 | K33: =$I$33+(g_tv*J38-$I$33)*MIN(1,(2030-2028)/conv_mw) -> 2744.2733 | L33: =$I$33+(g_tv*K38-$I$33)*MIN(1,(2031-2028)/conv_mw) -> 1730.9802 | M33: =$I$33+(g_tv*L38-$I$33)*MIN(1,(2032-2028)/conv_mw) -> 728.45235 | N33: C10：Q4 26＝(2026 指引中點 − 9M 實績 − Q4 非 AI) ÷ 每 MW 資本支出；FY2027＝(情境 FY2027 資本支出 − 非 AI) ÷ 每 MW（汰換 0）
A34: 期末 MW：H100 錨 | B34: MW | E34: =mw_pre24+mw_24 -> 1366.6497 | F34: =E34+F33*0 -> 1366.6497 | G34: =F34 -> 1366.6497 | H34: =F34+H33*0 -> 1366.6497 | I34: =H34+I33*0 -> 1366.6497 | J34: =I34+J33*0 -> 1366.6497 | K34: =J34+K33*0 -> 1366.6497 | L34: =K34+L33*0 -> 1366.6497 | M34: =L34+M33*0 -> 1366.6497
A35: 期末 MW：GB200 錨 | B35: MW | E35: =mw_25 -> 1844.9608 | F35: =E35+F33*0 -> 1844.9608 | G35: =F35 -> 1844.9608 | H35: =F35+H33*0 -> 1844.9608 | I35: =H35+I33*0 -> 1844.9608 | J35: =I35+J33*0 -> 1844.9608 | K35: =J35+K33*0 -> 1844.9608 | L35: =K35+L33*0 -> 1844.9608 | M35: =L35+M33*0 -> 1844.9608
A36: 期末 MW：GB300 錨 | B36: MW | E36: =mw_9m -> 1826.586 | F36: =E36+F33*am_26 -> 3015.2961 | G36: =F36 -> 3015.2961 | H36: =F36+H33*am_27 -> 5462.472 | I36: =H36+I33*(1-am_28) -> 5462.472 | J36: =I36+J33*(1-am_28) -> 5462.472 | K36: =J36+K33*(1-am_28) -> 5462.472 | L36: =K36+L33*(1-am_28) -> 5462.472 | M36: =L36+M33*(1-am_28) -> 5462.472
A37: 期末 MW：VR200 錨 | B37: MW | E37: 0 | F37: =E37+F33*(1-am_26) -> 0 | G37: =F37 -> 0 | H37: =F37+H33*(1-am_27) -> 2447.176 | I37: =H37+I33*am_28 -> 7341.5279 | J37: =I37+J33*am_28 -> 11132.409 | K37: =J37+K33*am_28 -> 13876.682 | L37: =K37+L33*am_28 -> 15607.662 | M37: =L37+M33*am_28 -> 16336.115
A38: 期末自用 AI MW（在役；9M26 欄為支出口徑含在建） | B38: MW | E38: =E34+E35+E36+E37 -> 5038.1965 | F38: =F34+F35+F36+F37 -> 6226.9066 | G38: =G34+G35+G36+G37 -> 6226.9066 | H38: =H34+H35+H36+H37 -> 11121.258 | I38: =I34+I35+I36+I37 -> 16015.61 | J38: =J34+J35+J36+J37 -> 19806.491 | K38: =K34+K35+K36+K37 -> 22550.765 | L38: =L34+L35+L36+L37 -> 24281.745 | M38: =M34+M35+M36+M37 -> 25010.197
A39: 平均在役 MW：H100 錨 | B39: MW | F39: =(base_h+F34)/2 -> 1366.6497 | H39: =(F34+H34)/2 -> 1366.6497 | I39: =(H34+I34)/2 -> 1366.6497 | J39: =(I34+J34)/2 -> 1366.6497 | K39: =(J34+K34)/2 -> 1366.6497 | L39: =(K34+L34)/2 -> 1366.6497 | M39: =(L34+M34)/2 -> 1366.6497 | N39: Q4 26：期初＝評價日在役（不含在建），期末含在建轉入
A40: 平均在役 MW：GB200 錨 | B40: MW | F40: =(base_b2+F35)/2 -> 1821.7828 | H40: =(F35+H35)/2 -> 1844.9608 | I40: =(H35+I35)/2 -> 1844.9608 | J40: =(I35+J35)/2 -> 1844.9608 | K40: =(J35+K35)/2 -> 1844.9608 | L40: =(K35+L35)/2 -> 1844.9608 | M40: =(L35+M35)/2 -> 1844.9608
A41: 平均在役 MW：GB300 錨 | B41: MW | F41: =(base_b3+F36)/2 -> 1507.648 | H41: =(F36+H36)/2 -> 4238.884 | I41: =(H36+I36)/2 -> 5462.472 | J41: =(I36+J36)/2 -> 5462.472 | K41: =(J36+K36)/2 -> 5462.472 | L41: =(K36+L36)/2 -> 5462.472 | M41: =(L36+M36)/2 -> 5462.472
A42: 平均在役 MW：VR200 錨 | B42: MW | F42: =(0+F37)/2 -> 0 | H42: =(F37+H37)/2 -> 1223.588 | I42: =(H37+I37)/2 -> 4894.3519 | J42: =(I37+J37)/2 -> 9236.9684 | K42: =(J37+K37)/2 -> 12504.546 | L42: =(K37+L37)/2 -> 14742.172 | M42: =(L37+M37)/2 -> 15971.889
A43: 平均在役自用 AI MW | B43: MW | F43: =F39+F40+F41+F42 -> 4696.0805 | H43: =H39+H40+H41+H42 -> 8674.0825 | I43: =I39+I40+I41+I42 -> 13568.434 | J43: =J39+J40+J41+J42 -> 17911.051 | K43: =K39+K40+K41+K42 -> 21178.628 | L43: =L39+L40+L41+L42 -> 23416.255 | M43: =M39+M40+M41+M42 -> 24645.971
A44: 其中：相對評價日在役機隊的增量 MW | B44: MW | F44: =F43-base_tot -> 1530.826 | H44: =H43-base_tot -> 5508.828 | I44: =I43-base_tot -> 10403.18 | J44: =J43-base_tot -> 14745.796 | K44: =K43-base_tot -> 18013.374 | L44: =L43-base_tot -> 20251 | M44: =M43-base_tot -> 21480.717
A45: C. AI 資本支出（新增 MW × 每 MW；汰換只換 IT，VR200 錨）
A46: AI IT 資本支出（成長） | B46: US$B | F46: =F33*(0*cit_h+0*cit_b2+am_26*cit_b3+(1-am_26)*cit_vr)/1000 -> 38.320712 | G46: =F46 -> 38.320712 | H46: =H33*(0*cit_h+0*cit_b2+am_27*cit_b3+(1-am_27)*cit_vr)/1000 -> 170.87058 | I46: =I33*(0*cit_h+0*cit_b2+(1-am_28)*cit_b3+am_28*cit_vr)/1000 -> 183.96083 | J46: =J33*(0*cit_h+0*cit_b2+(1-am_28)*cit_b3+am_28*cit_vr)/1000 -> 142.48539 | K46: =K33*(0*cit_h+0*cit_b2+(1-am_28)*cit_b3+am_28*cit_vr)/1000 -> 103.14722 | L46: =L33*(0*cit_h+0*cit_b2+(1-am_28)*cit_b3+am_28*cit_vr)/1000 -> 65.061231 | M46: =M33*(0*cit_h+0*cit_b2+(1-am_28)*cit_b3+am_28*cit_vr)/1000 -> 27.379866
A47: AI 機房資本支出（自建比例 × IF_CapexFacility） | B47: US$B | F47: =F33*selfb*cfac/1000 -> 12.801813 | G47: =F47 -> 12.801813 | H47: =H33*selfb*cfac/1000 -> 52.709723 | I47: =I33*selfb*cfac/1000 -> 52.709723 | J47: =J33*selfb*cfac/1000 -> 40.825893 | K47: =K33*selfb*cfac/1000 -> 29.554452 | L47: =L33*selfb*cfac/1000 -> 18.641791 | M47: =M33*selfb*cfac/1000 -> 7.8450676
A48: 汰換 MW（life_it 年前的 MW，換成 VR200 錨 IT） | B48: MW | F48: 0 | G48: =F48 -> 0 | H48: 0 | I48: 0 | J48: =mw_pre24 -> 513.84919 | K48: =mw_24 -> 852.80052 | L48: =mw_25 -> 1844.9608 | M48: =mw_9m+F33 -> 3015.2961 | N48: IT 6 年：2023 年底以前 → 2029、FY2024 → 2030、FY2025 → 2031、2026 → 2032；汰換後 MW 照常在役
A49: AI 汰換資本支出（只含 IT） | B49: US$B | F49: =F48*cit_vr/1000 -> 0 | G49: =F49 -> 0 | H49: =H48*cit_vr/1000 -> 0 | I49: =I48*cit_vr/1000 -> 0 | J49: =J48*cit_vr/1000 -> 19.313716 | K49: =K48*cit_vr/1000 -> 32.053661 | L49: =L48*cit_vr/1000 -> 69.345346 | M49: =M48*cit_vr/1000 -> 113.33398
A50: AI 資本支出合計 | B50: US$B | F50: =F46+F47+F49 -> 51.122525 | G50: =G46+G47+G49 -> 51.122525 | H50: =H46+H47+H49 -> 223.5803 | I50: =I46+I47+I49 -> 236.67056 | J50: =J46+J47+J49 -> 202.625 | K50: =K46+K47+K49 -> 164.75534 | L50: =L46+L47+L49 -> 153.04837 | M50: =M46+M47+M49 -> 148.55891
A51: 資本支出合計（含融資租賃本金）＝AI＋非 AI（Seg） | B51: US$B | E51: =capex_9m -> 85.824 | F51: =F50+Seg!F22 -> 54.176 | G51: =E51+F51 -> 140 | H51: =H50+Seg!H22 -> 236.56176 | I51: =I50+Seg!I22 -> 252.34435 | J51: =J50+Seg!J22 -> 220.76386 | K51: =K50+Seg!K22 -> 184.84398 | L51: =L50+Seg!L22 -> 174.80813 | M51: =M50+Seg!M22 -> 172.13137
A52: 檢查：FY2026 資本支出 − 2026 指引中點（C10） | B52: US$B | G52: =G51-capex_g -> 0
A53: 檢查：FY2027 資本支出 − 情境 FY2027 資本支出（M6） | B53: US$B | H53: =H51-cx27_A -> 0
A54: D. 新增 AI 折舊（在建工程 Q4 26 轉入；新增資本支出依年限直線攤提；當期 × phi_0、最後一年 1 − phi_0；Q4 26 欄 × 0.25）
A55: 在建工程轉入：IT | B55: US$B | F55: =cip_0*cip_it -> 53.6994
A56: 在建工程轉入：機房 | B56: US$B | F56: =cip_0*(1-cip_it) -> 35.7996
A57: IT 批次金額（成長＋汰換） | B57: US$B | F57: =F46+F49 -> 38.320712 | H57: =H46+H49 -> 170.87058 | I57: =I46+I49 -> 183.96083 | J57: =J46+J49 -> 161.79911 | K57: =K46+K49 -> 135.20088 | L57: =L46+L49 -> 134.40658 | M57: =M46+M49 -> 140.71385
A58: 機房批次金額 | B58: US$B | F58: =F47 -> 12.801813 | H58: =H47 -> 52.709723 | I58: =I47 -> 52.709723 | J58: =J47 -> 40.825893 | K58: =K47 -> 29.554452 | L58: =L47 -> 18.641791 | M58: =M47 -> 7.8450676
A59: 新增 AI 折舊：IT（含在建工程） | B59: US$B | F59: =$F$55/life_it*IF((0)<0,0,IF((0)=0,phi_q4,IF((0)<life_it,1,IF((0)=life_it,1-phi_q4,0))))+$F$57/life_it*IF((0)<0,0,IF((0)=0,phi_q4,IF((0)<life_it,1,IF((0)=life_it,1-phi_q4,0)))) -> 1.9170857 | G59: =F59 -> 1.9170857 | H59: =$F$55/life_it*IF((1)<0,0,IF((1)=0,phi_q4,IF((1)<life_it,1,IF((1)=life_it,1-phi_q4,0))))+$F$57/life_it*IF((1)<0,0,IF((1)=0,phi_q4,IF((1)<life_it,1,IF((1)=life_it,1-phi_q4,0))))+$H$57/life_it*IF((0)<0,0,IF((0)=0,phi_0,IF((0)<life_it,1,IF((0)=life_it,1-phi_0,0)))) -> 22.456293 | I59: =$F$55/life_it*IF((2)<0,0,IF((2)=0,phi_q4,IF((2)<life_it,1,IF((2)=life_it,1-phi_q4,0))))+$F$57/life_it*IF((2)<0,0,IF((2)=0,phi_q4,IF((2)<life_it,1,IF((2)=life_it,1-phi_q4,0))))+$H$57/life_it*IF((1)<0,0,IF((1)=0,phi_0,IF((1)<life_it,1,IF((1)=life_it,1-phi_0,0))))+$I$57/life_it*IF((0)<0,0,IF((0)=0,phi_0,IF((0)<life_it,1,IF((0)=life_it,1-phi_0,0)))) -> 51.48015 | J59: =$F$55/life_it*IF((3)<0,0,IF((3)=0,phi_q4,IF((3)<life_it,1,IF((3)=life_it,1-phi_q4,0))))+$F$57/life_it*IF((3)<0,0,IF((3)=0,phi_q4,IF((3)<life_it,1,IF((3)=life_it,1-phi_q4,0))))+$H$57/life_it*IF((2)<0,0,IF((2)=0,phi_0,IF((2)<life_it,1,IF((2)=life_it,1-phi_0,0))))+$I$57/life_it*IF((1)<0,0,IF((1)=0,phi_0,IF((1)<life_it,1,IF((1)=life_it,1-phi_0,0))))+$J$57/life_it*IF((0)<0,0,IF((0)=0,phi_0,IF((0)<life_it,1,IF((0)=life_it,1-phi_0,0)))) -> 81.216883 | K59: =$F$55/life_it*IF((4)<0,0,IF((4)=0,phi_q4,IF((4)<life_it,1,IF((4)=life_it,1-phi_q4,0))))+$F$57/life_it*IF((4)<0,0,IF((4)=0,phi_q4,IF((4)<life_it,1,IF((4)=life_it,1-phi_q4,0))))+$H$57/life_it*IF((3)<0,0,IF((3)=0,phi_0,IF((3)<life_it,1,IF((3)=life_it,1-phi_0,0))))+$I$57/life_it*IF((2)<0,0,IF((2)=0,phi_0,IF((2)<life_it,1,IF((2)=life_it,1-phi_0,0))))+$J$57/life_it*IF((1)<0,0,IF((1)=0,phi_0,IF((1)<life_it,1,IF((1)=life_it,1-phi_0,0))))+$K$57/life_it*IF((0)<0,0,IF((0)=0,phi_0,IF((0)<life_it,1,IF((0)=life_it,1-phi_0,0)))) -> 107.07514 | L59: =$F$55/life_it*IF((5)<0,0,IF((5)=0,phi_q4,IF((5)<life_it,1,IF((5)=life_it,1-phi_q4,0))))+$F$57/life_it*IF((5)<0,0,IF((5)=0,phi_q4,IF((5)<life_it,1,IF((5)=life_it,1-phi_q4,0))))+$H$57/life_it*IF((4)<0,0,IF((4)=0,phi_0,IF((4)<life_it,1,IF((4)=life_it,1-phi_0,0))))+$I$57/life_it*IF((3)<0,0,IF((3)=0,phi_0,IF((3)<life_it,1,IF((3)=life_it,1-phi_0,0))))+$J$57/life_it*IF((2)<0,0,IF((2)=0,phi_0,IF((2)<life_it,1,IF((2)=life_it,1-phi_0,0))))+$K$57/life_it*IF((1)<0,0,IF((1)=0,phi_0,IF((1)<life_it,1,IF((1)=life_it,1-phi_0,0))))+$L$57/life_it*IF((0)<0,0,IF((0)=0,phi_0,IF((0)<life_it,1,IF((0)=life_it,1-phi_0,0)))) -> 129.57553 | M59: =$F$55/life_it*IF((6)<0,0,IF((6)=0,phi_q4,IF((6)<life_it,1,IF((6)=life_it,1-phi_q4,0))))+$F$57/life_it*IF((6)<0,0,IF((6)=0,phi_q4,IF((6)<life_it,1,IF((6)=life_it,1-phi_q4,0))))+$H$57/life_it*IF((5)<0,0,IF((5)=0,phi_0,IF((5)<life_it,1,IF((5)=life_it,1-phi_0,0))))+$I$57/life_it*IF((4)<0,0,IF((4)=0,phi_0,IF((4)<life_it,1,IF((4)=life_it,1-phi_0,0))))+$J$57/life_it*IF((3)<0,0,IF((3)=0,phi_0,IF((3)<life_it,1,IF((3)=life_it,1-phi_0,0))))+$K$57/life_it*IF((2)<0,0,IF((2)=0,phi_0,IF((2)<life_it,1,IF((2)=life_it,1-phi_0,0))))+$L$57/life_it*IF((1)<0,0,IF((1)=0,phi_0,IF((1)<life_it,1,IF((1)=life_it,1-phi_0,0))))+$M$57/life_it*IF((0)<0,0,IF((0)=0,phi_0,IF((0)<life_it,1,IF((0)=life_it,1-phi_0,0)))) -> 150.32234
A60: 新增 AI 折舊：機房（含在建工程） | B60: US$B | F60: =$F$56/life_fac*IF((0)<0,0,IF((0)=0,phi_q4,IF((0)<life_fac,1,IF((0)=life_fac,1-phi_q4,0))))+$F$58/life_fac*IF((0)<0,0,IF((0)=0,phi_q4,IF((0)<life_fac,1,IF((0)=life_fac,1-phi_q4,0)))) -> 0.30375883 | G60: =F60 -> 0.30375883 | H60: =$F$56/life_fac*IF((1)<0,0,IF((1)=0,phi_q4,IF((1)<life_fac,1,IF((1)=life_fac,1-phi_q4,0))))+$F$58/life_fac*IF((1)<0,0,IF((1)=0,phi_q4,IF((1)<life_fac,1,IF((1)=life_fac,1-phi_q4,0))))+$H$58/life_fac*IF((0)<0,0,IF((0)=0,phi_0,IF((0)<life_fac,1,IF((0)=life_fac,1-phi_0,0)))) -> 3.0889422 | I60: =$F$56/life_fac*IF((2)<0,0,IF((2)=0,phi_q4,IF((2)<life_fac,1,IF((2)=life_fac,1-phi_q4,0))))+$F$58/life_fac*IF((2)<0,0,IF((2)=0,phi_q4,IF((2)<life_fac,1,IF((2)=life_fac,1-phi_q4,0))))+$H$58/life_fac*IF((1)<0,0,IF((1)=0,phi_0,IF((1)<life_fac,1,IF((1)=life_fac,1-phi_0,0))))+$I$58/life_fac*IF((0)<0,0,IF((0)=0,phi_0,IF((0)<life_fac,1,IF((0)=life_fac,1-phi_0,0)))) -> 5.7244283 | J60: =$F$56/life_fac*IF((3)<0,0,IF((3)=0,phi_q4,IF((3)<life_fac,1,IF((3)=life_fac,1-phi_q4,0))))+$F$58/life_fac*IF((3)<0,0,IF((3)=0,phi_q4,IF((3)<life_fac,1,IF((3)=life_fac,1-phi_q4,0))))+$H$58/life_fac*IF((2)<0,0,IF((2)=0,phi_0,IF((2)<life_fac,1,IF((2)=life_fac,1-phi_0,0))))+$I$58/life_fac*IF((1)<0,0,IF((1)=0,phi_0,IF((1)<life_fac,1,IF((1)=life_fac,1-phi_0,0))))+$J$58/life_fac*IF((0)<0,0,IF((0)=0,phi_0,IF((0)<life_fac,1,IF((0)=life_fac,1-phi_0,0)))) -> 8.2113666 | K60: =$F$56/life_fac*IF((4)<0,0,IF((4)=0,phi_q4,IF((4)<life_fac,1,IF((4)=life_fac,1-phi_q4,0))))+$F$58/life_fac*IF((4)<0,0,IF((4)=0,phi_q4,IF((4)<life_fac,1,IF((4)=life_fac,1-phi_q4,0))))+$H$58/life_fac*IF((3)<0,0,IF((3)=0,phi_0,IF((3)<life_fac,1,IF((3)=life_fac,1-phi_0,0))))+$I$58/life_fac*IF((2)<0,0,IF((2)=0,phi_0,IF((2)<life_fac,1,IF((2)=life_fac,1-phi_0,0))))+$J$58/life_fac*IF((1)<0,0,IF((1)=0,phi_0,IF((1)<life_fac,1,IF((1)=life_fac,1-phi_0,0))))+$K$58/life_fac*IF((0)<0,0,IF((0)=0,phi_0,IF((0)<life_fac,1,IF((0)=life_fac,1-phi_0,0)))) -> 10.111768 | L60: =$F$56/life_fac*IF((5)<0,0,IF((5)=0,phi_q4,IF((5)<life_fac,1,IF((5)=life_fac,1-phi_q4,0))))+$F$58/life_fac*IF((5)<0,0,IF((5)=0,phi_q4,IF((5)<life_fac,1,IF((5)=life_fac,1-phi_q4,0))))+$H$58/life_fac*IF((4)<0,0,IF((4)=0,phi_0,IF((4)<life_fac,1,IF((4)=life_fac,1-phi_0,0))))+$I$58/life_fac*IF((3)<0,0,IF((3)=0,phi_0,IF((3)<life_fac,1,IF((3)=life_fac,1-phi_0,0))))+$J$58/life_fac*IF((2)<0,0,IF((2)=0,phi_0,IF((2)<life_fac,1,IF((2)=life_fac,1-phi_0,0))))+$K$58/life_fac*IF((1)<0,0,IF((1)=0,phi_0,IF((1)<life_fac,1,IF((1)=life_fac,1-phi_0,0))))+$L$58/life_fac*IF((0)<0,0,IF((0)=0,phi_0,IF((0)<life_fac,1,IF((0)=life_fac,1-phi_0,0)))) -> 11.453083 | M60: =$F$56/life_fac*IF((6)<0,0,IF((6)=0,phi_q4,IF((6)<life_fac,1,IF((6)=life_fac,1-phi_q4,0))))+$F$58/life_fac*IF((6)<0,0,IF((6)=0,phi_q4,IF((6)<life_fac,1,IF((6)=life_fac,1-phi_q4,0))))+$H$58/life_fac*IF((5)<0,0,IF((5)=0,phi_0,IF((5)<life_fac,1,IF((5)=life_fac,1-phi_0,0))))+$I$58/life_fac*IF((4)<0,0,IF((4)=0,phi_0,IF((4)<life_fac,1,IF((4)=life_fac,1-phi_0,0))))+$J$58/life_fac*IF((3)<0,0,IF((3)=0,phi_0,IF((3)<life_fac,1,IF((3)=life_fac,1-phi_0,0))))+$K$58/life_fac*IF((2)<0,0,IF((2)=0,phi_0,IF((2)<life_fac,1,IF((2)=life_fac,1-phi_0,0))))+$L$58/life_fac*IF((1)<0,0,IF((1)=0,phi_0,IF((1)<life_fac,1,IF((1)=life_fac,1-phi_0,0))))+$M$58/life_fac*IF((0)<0,0,IF((0)=0,phi_0,IF((0)<life_fac,1,IF((0)=life_fac,1-phi_0,0)))) -> 12.250213
A61: 新增 AI 折舊合計（含在建工程轉入） | B61: US$B | F61: =F59+F60 -> 2.2208445 | G61: =G59+G60 -> 2.2208445 | H61: =H59+H60 -> 25.545235 | I61: =I59+I60 -> 57.204578 | J61: =J59+J60 -> 89.42825 | K61: =K59+K60 -> 117.18691 | L61: =L59+L60 -> 141.02861 | M61: =M59+M60 -> 162.57255
A62: E. 自用 AI 增量營運成本（相對評價日在役機隊；基準機隊成本已在 FoA 利益率內）
A63: 自用 AI 增量營運費用（Tokenomics IF_OpexGW） | B63: US$B | F63: =((F39*opx_h+F40*opx_b2+F41*opx_b3+F42*opx_vr)-base_tot*opx0)/1000*0.25 -> 0.75777985 | G63: =F63 -> 0.75777985 | H63: =((H39*opx_h+H40*opx_b2+H41*opx_b3+H42*opx_vr)-base_tot*opx0)/1000*1 -> 11.049743 | I63: =((I39*opx_h+I40*opx_b2+I41*opx_b3+I42*opx_vr)-base_tot*opx0)/1000*1 -> 21.160399 | J63: =((J39*opx_h+J40*opx_b2+J41*opx_b3+J42*opx_vr)-base_tot*opx0)/1000*1 -> 30.251647 | K63: =((K39*opx_h+K40*opx_b2+K41*opx_b3+K42*opx_vr)-base_tot*opx0)/1000*1 -> 37.092306 | L63: =((L39*opx_h+L40*opx_b2+L41*opx_b3+L42*opx_vr)-base_tot*opx0)/1000*1 -> 41.776767 | M63: =((M39*opx_h+M40*opx_b2+M41*opx_b3+M42*opx_vr)-base_tot*opx0)/1000*1 -> 44.351173
A64: 租用算力租金（Sens 用；基準 0） | B64: US$B | F64: 0 | G64: =F64 -> 0 | H64: =rent_l/3 -> 0 | I64: =rent_l*2/3 -> 0 | J64: =rent_l -> 0 | K64: =rent_l -> 0 | L64: =rent_l -> 0 | M64: =rent_l -> 0 | N64: M4：尚未起租租賃與第三方雲端只進 Sens；讀法 2 下與影子效益同樣價值中性（DCF、分部加總皆加回）
A65: 自用 AI 增量成本合計（營運＋租金＋新增 AI 折舊） | B65: US$B | F65: =F63+F64+F61 -> 2.9786244 | G65: =G63+G64+G61 -> 2.9786244 | H65: =H63+H64+H61 -> 36.594978 | I65: =I63+I64+I61 -> 78.364977 | J65: =J63+J64+J61 -> 119.6799 | K65: =K63+K64+K61 -> 154.27922 | L65: =L63+L64+L61 -> 182.80538 | M65: =M63+M64+M61 -> 206.92373
A66: F. 評價日在役資產的基礎折舊（隨期初機隊汰換遞減）
A67: 累計已汰換的期初機隊 MW（2025 年以前；當年以半年計） | B67: MW | F67: 0 | G67: =F67 -> 0 | H67: =0+mid*H48 -> 0 | I67: =H48+mid*I48 -> 0 | J67: =H48+I48+mid*J48 -> 256.92459 | K67: =H48+I48+J48+mid*K48 -> 940.24945 | L67: =H48+I48+J48+K48+mid*L48 -> 2289.1301 | M67: =H48+I48+J48+K48+L48 -> 3211.6105 | N67: 2026 年批次（2032 汰換）的折舊在在建工程與新增批次內，不從基礎折舊扣
A68: 基礎折舊＝da_base − MIN(da_base × IT 占比, 累計汰換 MW × 每 MW IT 折舊) | B68: US$B | F68: =(da_base-MIN(da_base*cip_it,F67*dpi0/1000))*0.25 -> 7.154 | G68: =F68 -> 7.154 | H68: =(da_base-MIN(da_base*cip_it,H67*dpi0/1000))*1 -> 28.616 | I68: =(da_base-MIN(da_base*cip_it,I67*dpi0/1000))*1 -> 28.616 | J68: =(da_base-MIN(da_base*cip_it,J67*dpi0/1000))*1 -> 27.523034 | K68: =(da_base-MIN(da_base*cip_it,K67*dpi0/1000))*1 -> 24.616145 | L68: =(da_base-MIN(da_base*cip_it,L67*dpi0/1000))*1 -> 18.877959 | M68: =(da_base-MIN(da_base*cip_it,M67*dpi0/1000))*1 -> 14.953694
A69: G. 自用 AI 影子效益（讀法 2：增量在役 MW × IF_HoldEcon，k＝1；非財報營收）
A70: 自用 AI 影子效益 | B70: US$B | F70: =((F39*he_h+F40*he_b2+F41*he_b3+F42*he_vr)-base_tot*he0)/1000*0.25 -> 4.1543738 | G70: =F70 -> 4.1543738 | H70: =((H39*he_h+H40*he_b2+H41*he_b3+H42*he_vr)-base_tot*he0)/1000*1 -> 61.514412 | I70: =((I39*he_h+I40*he_b2+I41*he_b3+I42*he_vr)-base_tot*he0)/1000*1 -> 119.71171 | J70: =((J39*he_h+J40*he_b2+J41*he_b3+J42*he_vr)-base_tot*he0)/1000*1 -> 172.80224 | K70: =((K39*he_h+K40*he_b2+K41*he_b3+K42*he_vr)-base_tot*he0)/1000*1 -> 212.74991 | L70: =((L39*he_h+L40*he_b2+L41*he_b3+L42*he_vr)-base_tot*he0)/1000*1 -> 240.10595 | M70: =((M39*he_h+M40*he_b2+M41*he_b3+M42*he_vr)-base_tot*he0)/1000*1 -> 255.13982 | N70: 原則第 7 節：只進評價口徑（PL「營業利益（評價口徑）」、Val）；營收列與分部對帳不動
A71: 影子效益 ÷ 自用 AI 增量成本 | B71: x | F71: =F70/F65 -> 1.394729 | H71: =H70/H65 -> 1.6809523 | I71: =I70/I65 -> 1.5276175 | J71: =J70/J65 -> 1.4438703 | K71: =K70/K65 -> 1.3789927 | L71: =L70/L65 -> 1.3134513 | M71: =M70/M65 -> 1.2330138 | N71: 接近 1＝價值中性
A73: 情境 B（近四季成長收斂；基準）
A74: 項目 | B74: 單位 | C74: FY2024A | D74: FY2025A | E74: 9M26A | F74: Q4 26E | G74: FY2026E | H74: FY2027E | I74: FY2028E | J74: FY2029E | K74: FY2030E | L74: FY2031E | M74: FY2032E | N74: 說明
A75: B. 自用 AI 容量（MW；期末）
A76: 自用 AI MW 新增（Q4 26、FY2027 由資本支出反推；FY2028＝FY2027 × a28；FY2029 起收斂） | B76: MW | F76: =(capex_g-capex_9m-Seg!F43)/pmw_26*1000 -> 1188.7101 | G76: =F76 -> 1188.7101 | H76: =(cx27_B-Seg!H43)/pmw_27*1000 -> 4225.6372 | I76: =H76*a28 -> 4225.6372 | J76: =$I$76+(g_tv*I81-$I$76)*MIN(1,(2029-2028)/conv_mw) -> 3279.3143 | K76: =$I$76+(g_tv*J81-$I$76)*MIN(1,(2030-2028)/conv_mw) -> 2382.181 | L76: =$I$76+(g_tv*K81-$I$76)*MIN(1,(2031-2028)/conv_mw) -> 1514.052 | M76: =$I$76+(g_tv*L81-$I$76)*MIN(1,(2032-2028)/conv_mw) -> 655.61185 | N76: C10：Q4 26＝(2026 指引中點 − 9M 實績 − Q4 非 AI) ÷ 每 MW 資本支出；FY2027＝(情境 FY2027 資本支出 − 非 AI) ÷ 每 MW（汰換 0）
A77: 期末 MW：H100 錨 | B77: MW | E77: =mw_pre24+mw_24 -> 1366.6497 | F77: =E77+F76*0 -> 1366.6497 | G77: =F77 -> 1366.6497 | H77: =F77+H76*0 -> 1366.6497 | I77: =H77+I76*0 -> 1366.6497 | J77: =I77+J76*0 -> 1366.6497 | K77: =J77+K76*0 -> 1366.6497 | L77: =K77+L76*0 -> 1366.6497 | M77: =L77+M76*0 -> 1366.6497
A78: 期末 MW：GB200 錨 | B78: MW | E78: =mw_25 -> 1844.9608 | F78: =E78+F76*0 -> 1844.9608 | G78: =F78 -> 1844.9608 | H78: =F78+H76*0 -> 1844.9608 | I78: =H78+I76*0 -> 1844.9608 | J78: =I78+J76*0 -> 1844.9608 | K78: =J78+K76*0 -> 1844.9608 | L78: =K78+L76*0 -> 1844.9608 | M78: =L78+M76*0 -> 1844.9608
A79: 期末 MW：GB300 錨 | B79: MW | E79: =mw_9m -> 1826.586 | F79: =E79+F76*am_26 -> 3015.2961 | G79: =F79 -> 3015.2961 | H79: =F79+H76*am_27 -> 5128.1147 | I79: =H79+I76*(1-am_28) -> 5128.1147 | J79: =I79+J76*(1-am_28) -> 5128.1147 | K79: =J79+K76*(1-am_28) -> 5128.1147 | L79: =K79+L76*(1-am_28) -> 5128.1147 | M79: =L79+M76*(1-am_28) -> 5128.1147
A80: 期末 MW：VR200 錨 | B80: MW | E80: 0 | F80: =E80+F76*(1-am_26) -> 0 | G80: =F80 -> 0 | H80: =F80+H76*(1-am_27) -> 2112.8186 | I80: =H80+I76*am_28 -> 6338.4558 | J80: =I80+J76*am_28 -> 9617.7701 | K80: =J80+K76*am_28 -> 11999.951 | L80: =K80+L76*am_28 -> 13514.003 | M80: =L80+M76*am_28 -> 14169.615
A81: 期末自用 AI MW（在役；9M26 欄為支出口徑含在建） | B81: MW | E81: =E77+E78+E79+E80 -> 5038.1965 | F81: =F77+F78+F79+F80 -> 6226.9066 | G81: =G77+G78+G79+G80 -> 6226.9066 | H81: =H77+H78+H79+H80 -> 10452.544 | I81: =I77+I78+I79+I80 -> 14678.181 | J81: =J77+J78+J79+J80 -> 17957.495 | K81: =K77+K78+K79+K80 -> 20339.676 | L81: =L77+L78+L79+L80 -> 21853.728 | M81: =M77+M78+M79+M80 -> 22509.34
A82: 平均在役 MW：H100 錨 | B82: MW | F82: =(base_h+F77)/2 -> 1366.6497 | H82: =(F77+H77)/2 -> 1366.6497 | I82: =(H77+I77)/2 -> 1366.6497 | J82: =(I77+J77)/2 -> 1366.6497 | K82: =(J77+K77)/2 -> 1366.6497 | L82: =(K77+L77)/2 -> 1366.6497 | M82: =(L77+M77)/2 -> 1366.6497 | N82: Q4 26：期初＝評價日在役（不含在建），期末含在建轉入
A83: 平均在役 MW：GB200 錨 | B83: MW | F83: =(base_b2+F78)/2 -> 1821.7828 | H83: =(F78+H78)/2 -> 1844.9608 | I83: =(H78+I78)/2 -> 1844.9608 | J83: =(I78+J78)/2 -> 1844.9608 | K83: =(J78+K78)/2 -> 1844.9608 | L83: =(K78+L78)/2 -> 1844.9608 | M83: =(L78+M78)/2 -> 1844.9608
A84: 平均在役 MW：GB300 錨 | B84: MW | F84: =(base_b3+F79)/2 -> 1507.648 | H84: =(F79+H79)/2 -> 4071.7054 | I84: =(H79+I79)/2 -> 5128.1147 | J84: =(I79+J79)/2 -> 5128.1147 | K84: =(J79+K79)/2 -> 5128.1147 | L84: =(K79+L79)/2 -> 5128.1147 | M84: =(L79+M79)/2 -> 5128.1147
A85: 平均在役 MW：VR200 錨 | B85: MW | F85: =(0+F80)/2 -> 0 | H85: =(F80+H80)/2 -> 1056.4093 | I85: =(H80+I80)/2 -> 4225.6372 | J85: =(I80+J80)/2 -> 7978.113 | K85: =(J80+K80)/2 -> 10808.861 | L85: =(K80+L80)/2 -> 12756.977 | M85: =(L80+M80)/2 -> 13841.809
A86: 平均在役自用 AI MW | B86: MW | F86: =F82+F83+F84+F85 -> 4696.0805 | H86: =H82+H83+H84+H85 -> 8339.7252 | I86: =I82+I83+I84+I85 -> 12565.362 | J86: =J82+J83+J84+J85 -> 16317.838 | K86: =K82+K83+K84+K85 -> 19148.586 | L86: =L82+L83+L84+L85 -> 21096.702 | M86: =M82+M83+M84+M85 -> 22181.534
A87: 其中：相對評價日在役機隊的增量 MW | B87: MW | F87: =F86-base_tot -> 1530.826 | H87: =H86-base_tot -> 5174.4707 | I87: =I86-base_tot -> 9400.1079 | J87: =J86-base_tot -> 13152.584 | K87: =K86-base_tot -> 15983.331 | L87: =L86-base_tot -> 17931.448 | M87: =M86-base_tot -> 19016.28
A88: C. AI 資本支出（新增 MW × 每 MW；汰換只換 IT，VR200 錨）
A89: AI IT 資本支出（成長） | B89: US$B | F89: =F76*(0*cit_h+0*cit_b2+am_26*cit_b3+(1-am_26)*cit_vr)/1000 -> 38.320712 | G89: =F89 -> 38.320712 | H89: =H76*(0*cit_h+0*cit_b2+am_27*cit_b3+(1-am_27)*cit_vr)/1000 -> 147.52455 | I89: =I76*(0*cit_h+0*cit_b2+(1-am_28)*cit_b3+am_28*cit_vr)/1000 -> 158.82629 | J89: =J76*(0*cit_h+0*cit_b2+(1-am_28)*cit_b3+am_28*cit_vr)/1000 -> 123.25746 | K89: =K76*(0*cit_h+0*cit_b2+(1-am_28)*cit_b3+am_28*cit_vr)/1000 -> 89.537495 | L89: =L76*(0*cit_h+0*cit_b2+(1-am_28)*cit_b3+am_28*cit_vr)/1000 -> 56.907692 | M89: =M76*(0*cit_h+0*cit_b2+(1-am_28)*cit_b3+am_28*cit_vr)/1000 -> 24.642058
A90: AI 機房資本支出（自建比例 × IF_CapexFacility） | B90: US$B | F90: =F76*selfb*cfac/1000 -> 12.801813 | G90: =F90 -> 12.801813 | H90: =H76*selfb*cfac/1000 -> 45.508 | I90: =I76*selfb*cfac/1000 -> 45.508 | J90: =J76*selfb*cfac/1000 -> 35.316575 | K90: =K76*selfb*cfac/1000 -> 25.654899 | L90: =L76*selfb*cfac/1000 -> 16.305583 | M90: =M76*selfb*cfac/1000 -> 7.0606118
A91: 汰換 MW（life_it 年前的 MW，換成 VR200 錨 IT） | B91: MW | F91: 0 | G91: =F91 -> 0 | H91: 0 | I91: 0 | J91: =mw_pre24 -> 513.84919 | K91: =mw_24 -> 852.80052 | L91: =mw_25 -> 1844.9608 | M91: =mw_9m+F76 -> 3015.2961 | N91: IT 6 年：2023 年底以前 → 2029、FY2024 → 2030、FY2025 → 2031、2026 → 2032；汰換後 MW 照常在役
A92: AI 汰換資本支出（只含 IT） | B92: US$B | F92: =F91*cit_vr/1000 -> 0 | G92: =F92 -> 0 | H92: =H91*cit_vr/1000 -> 0 | I92: =I91*cit_vr/1000 -> 0 | J92: =J91*cit_vr/1000 -> 19.313716 | K92: =K91*cit_vr/1000 -> 32.053661 | L92: =L91*cit_vr/1000 -> 69.345346 | M92: =M91*cit_vr/1000 -> 113.33398
A93: AI 資本支出合計 | B93: US$B | F93: =F89+F90+F92 -> 51.122525 | G93: =G89+G90+G92 -> 51.122525 | H93: =H89+H90+H92 -> 193.03255 | I93: =I89+I90+I92 -> 204.33429 | J93: =J89+J90+J92 -> 177.88775 | K93: =K89+K90+K92 -> 147.24605 | L93: =L89+L90+L92 -> 142.55862 | M93: =M89+M90+M92 -> 145.03665
A94: 資本支出合計（含融資租賃本金）＝AI＋非 AI（Seg） | B94: US$B | E94: =capex_9m -> 85.824 | F94: =F93+Seg!F43 -> 54.176 | G94: =E94+F94 -> 140 | H94: =H93+Seg!H43 -> 205.70588 | I94: =I93+Seg!I43 -> 219.28326 | J94: =J93+Seg!J43 -> 194.79986 | K94: =K93+Seg!K43 -> 165.56573 | L94: =L93+Seg!L43 -> 162.40525 | M94: =M93+Seg!M43 -> 166.54004
A95: 檢查：FY2026 資本支出 − 2026 指引中點（C10） | B95: US$B | G95: =G94-capex_g -> 0
A96: 檢查：FY2027 資本支出 − 情境 FY2027 資本支出（M6） | B96: US$B | H96: =H94-cx27_B -> 0
A97: D. 新增 AI 折舊（在建工程 Q4 26 轉入；新增資本支出依年限直線攤提；當期 × phi_0、最後一年 1 − phi_0；Q4 26 欄 × 0.25）
A98: 在建工程轉入：IT | B98: US$B | F98: =cip_0*cip_it -> 53.6994
A99: 在建工程轉入：機房 | B99: US$B | F99: =cip_0*(1-cip_it) -> 35.7996
A100: IT 批次金額（成長＋汰換） | B100: US$B | F100: =F89+F92 -> 38.320712 | H100: =H89+H92 -> 147.52455 | I100: =I89+I92 -> 158.82629 | J100: =J89+J92 -> 142.57118 | K100: =K89+K92 -> 121.59116 | L100: =L89+L92 -> 126.25304 | M100: =M89+M92 -> 137.97604
A101: 機房批次金額 | B101: US$B | F101: =F90 -> 12.801813 | H101: =H90 -> 45.508 | I101: =I90 -> 45.508 | J101: =J90 -> 35.316575 | K101: =K90 -> 25.654899 | L101: =L90 -> 16.305583 | M101: =M90 -> 7.0606118
A102: 新增 AI 折舊：IT（含在建工程） | B102: US$B | F102: =$F$98/life_it*IF((0)<0,0,IF((0)=0,phi_q4,IF((0)<life_it,1,IF((0)=life_it,1-phi_q4,0))))+$F$100/life_it*IF((0)<0,0,IF((0)=0,phi_q4,IF((0)<life_it,1,IF((0)=life_it,1-phi_q4,0)))) -> 1.9170857 | G102: =F102 -> 1.9170857 | H102: =$F$98/life_it*IF((1)<0,0,IF((1)=0,phi_q4,IF((1)<life_it,1,IF((1)=life_it,1-phi_q4,0))))+$F$100/life_it*IF((1)<0,0,IF((1)=0,phi_q4,IF((1)<life_it,1,IF((1)=life_it,1-phi_q4,0))))+$H$100/life_it*IF((0)<0,0,IF((0)=0,phi_0,IF((0)<life_it,1,IF((0)=life_it,1-phi_0,0)))) -> 21.483542 | I102: =$F$98/life_it*IF((2)<0,0,IF((2)=0,phi_q4,IF((2)<life_it,1,IF((2)=life_it,1-phi_q4,0))))+$F$100/life_it*IF((2)<0,0,IF((2)=0,phi_q4,IF((2)<life_it,1,IF((2)=life_it,1-phi_q4,0))))+$H$100/life_it*IF((1)<0,0,IF((1)=0,phi_0,IF((1)<life_it,1,IF((1)=life_it,1-phi_0,0))))+$I$100/life_it*IF((0)<0,0,IF((0)=0,phi_0,IF((0)<life_it,1,IF((0)=life_it,1-phi_0,0)))) -> 46.541873 | J102: =$F$98/life_it*IF((3)<0,0,IF((3)=0,phi_q4,IF((3)<life_it,1,IF((3)=life_it,1-phi_q4,0))))+$F$100/life_it*IF((3)<0,0,IF((3)=0,phi_q4,IF((3)<life_it,1,IF((3)=life_it,1-phi_q4,0))))+$H$100/life_it*IF((2)<0,0,IF((2)=0,phi_0,IF((2)<life_it,1,IF((2)=life_it,1-phi_0,0))))+$I$100/life_it*IF((1)<0,0,IF((1)=0,phi_0,IF((1)<life_it,1,IF((1)=life_it,1-phi_0,0))))+$J$100/life_it*IF((0)<0,0,IF((0)=0,phi_0,IF((0)<life_it,1,IF((0)=life_it,1-phi_0,0)))) -> 72.335624 | K102: =$F$98/life_it*IF((4)<0,0,IF((4)=0,phi_q4,IF((4)<life_it,1,IF((4)=life_it,1-phi_q4,0))))+$F$100/life_it*IF((4)<0,0,IF((4)=0,phi_q4,IF((4)<life_it,1,IF((4)=life_it,1-phi_q4,0))))+$H$100/life_it*IF((3)<0,0,IF((3)=0,phi_0,IF((3)<life_it,1,IF((3)=life_it,1-phi_0,0))))+$I$100/life_it*IF((2)<0,0,IF((2)=0,phi_0,IF((2)<life_it,1,IF((2)=life_it,1-phi_0,0))))+$J$100/life_it*IF((1)<0,0,IF((1)=0,phi_0,IF((1)<life_it,1,IF((1)=life_it,1-phi_0,0))))+$K$100/life_it*IF((0)<0,0,IF((0)=0,phi_0,IF((0)<life_it,1,IF((0)=life_it,1-phi_0,0)))) -> 95.22332 | L102: =$F$98/life_it*IF((5)<0,0,IF((5)=0,phi_q4,IF((5)<life_it,1,IF((5)=life_it,1-phi_q4,0))))+$F$100/life_it*IF((5)<0,0,IF((5)=0,phi_q4,IF((5)<life_it,1,IF((5)=life_it,1-phi_q4,0))))+$H$100/life_it*IF((4)<0,0,IF((4)=0,phi_0,IF((4)<life_it,1,IF((4)=life_it,1-phi_0,0))))+$I$100/life_it*IF((3)<0,0,IF((3)=0,phi_0,IF((3)<life_it,1,IF((3)=life_it,1-phi_0,0))))+$J$100/life_it*IF((2)<0,0,IF((2)=0,phi_0,IF((2)<life_it,1,IF((2)=life_it,1-phi_0,0))))+$K$100/life_it*IF((1)<0,0,IF((1)=0,phi_0,IF((1)<life_it,1,IF((1)=life_it,1-phi_0,0))))+$L$100/life_it*IF((0)<0,0,IF((0)=0,phi_0,IF((0)<life_it,1,IF((0)=life_it,1-phi_0,0)))) -> 115.68276 | M102: =$F$98/life_it*IF((6)<0,0,IF((6)=0,phi_q4,IF((6)<life_it,1,IF((6)=life_it,1-phi_q4,0))))+$F$100/life_it*IF((6)<0,0,IF((6)=0,phi_q4,IF((6)<life_it,1,IF((6)=life_it,1-phi_q4,0))))+$H$100/life_it*IF((5)<0,0,IF((5)=0,phi_0,IF((5)<life_it,1,IF((5)=life_it,1-phi_0,0))))+$I$100/life_it*IF((4)<0,0,IF((4)=0,phi_0,IF((4)<life_it,1,IF((4)=life_it,1-phi_0,0))))+$J$100/life_it*IF((3)<0,0,IF((3)=0,phi_0,IF((3)<life_it,1,IF((3)=life_it,1-phi_0,0))))+$K$100/life_it*IF((2)<0,0,IF((2)=0,phi_0,IF((2)<life_it,1,IF((2)=life_it,1-phi_0,0))))+$L$100/life_it*IF((1)<0,0,IF((1)=0,phi_0,IF((1)<life_it,1,IF((1)=life_it,1-phi_0,0))))+$M$100/life_it*IF((0)<0,0,IF((0)=0,phi_0,IF((0)<life_it,1,IF((0)=life_it,1-phi_0,0)))) -> 135.2963
A103: 新增 AI 折舊：機房（含在建工程） | B103: US$B | F103: =$F$99/life_fac*IF((0)<0,0,IF((0)=0,phi_q4,IF((0)<life_fac,1,IF((0)=life_fac,1-phi_q4,0))))+$F$101/life_fac*IF((0)<0,0,IF((0)=0,phi_q4,IF((0)<life_fac,1,IF((0)=life_fac,1-phi_q4,0)))) -> 0.30375883 | G103: =F103 -> 0.30375883 | H103: =$F$99/life_fac*IF((1)<0,0,IF((1)=0,phi_q4,IF((1)<life_fac,1,IF((1)=life_fac,1-phi_q4,0))))+$F$101/life_fac*IF((1)<0,0,IF((1)=0,phi_q4,IF((1)<life_fac,1,IF((1)=life_fac,1-phi_q4,0))))+$H$101/life_fac*IF((0)<0,0,IF((0)=0,phi_0,IF((0)<life_fac,1,IF((0)=life_fac,1-phi_0,0)))) -> 2.9989206 | I103: =$F$99/life_fac*IF((2)<0,0,IF((2)=0,phi_q4,IF((2)<life_fac,1,IF((2)=life_fac,1-phi_q4,0))))+$F$101/life_fac*IF((2)<0,0,IF((2)=0,phi_q4,IF((2)<life_fac,1,IF((2)=life_fac,1-phi_q4,0))))+$H$101/life_fac*IF((1)<0,0,IF((1)=0,phi_0,IF((1)<life_fac,1,IF((1)=life_fac,1-phi_0,0))))+$I$101/life_fac*IF((0)<0,0,IF((0)=0,phi_0,IF((0)<life_fac,1,IF((0)=life_fac,1-phi_0,0)))) -> 5.2743207 | J103: =$F$99/life_fac*IF((3)<0,0,IF((3)=0,phi_q4,IF((3)<life_fac,1,IF((3)=life_fac,1-phi_q4,0))))+$F$101/life_fac*IF((3)<0,0,IF((3)=0,phi_q4,IF((3)<life_fac,1,IF((3)=life_fac,1-phi_q4,0))))+$H$101/life_fac*IF((2)<0,0,IF((2)=0,phi_0,IF((2)<life_fac,1,IF((2)=life_fac,1-phi_0,0))))+$I$101/life_fac*IF((1)<0,0,IF((1)=0,phi_0,IF((1)<life_fac,1,IF((1)=life_fac,1-phi_0,0))))+$J$101/life_fac*IF((0)<0,0,IF((0)=0,phi_0,IF((0)<life_fac,1,IF((0)=life_fac,1-phi_0,0)))) -> 7.4223278 | K103: =$F$99/life_fac*IF((4)<0,0,IF((4)=0,phi_q4,IF((4)<life_fac,1,IF((4)=life_fac,1-phi_q4,0))))+$F$101/life_fac*IF((4)<0,0,IF((4)=0,phi_q4,IF((4)<life_fac,1,IF((4)=life_fac,1-phi_q4,0))))+$H$101/life_fac*IF((3)<0,0,IF((3)=0,phi_0,IF((3)<life_fac,1,IF((3)=life_fac,1-phi_0,0))))+$I$101/life_fac*IF((2)<0,0,IF((2)=0,phi_0,IF((2)<life_fac,1,IF((2)=life_fac,1-phi_0,0))))+$J$101/life_fac*IF((1)<0,0,IF((1)=0,phi_0,IF((1)<life_fac,1,IF((1)=life_fac,1-phi_0,0))))+$K$101/life_fac*IF((0)<0,0,IF((0)=0,phi_0,IF((0)<life_fac,1,IF((0)=life_fac,1-phi_0,0)))) -> 9.0673857 | L103: =$F$99/life_fac*IF((5)<0,0,IF((5)=0,phi_q4,IF((5)<life_fac,1,IF((5)=life_fac,1-phi_q4,0))))+$F$101/life_fac*IF((5)<0,0,IF((5)=0,phi_q4,IF((5)<life_fac,1,IF((5)=life_fac,1-phi_q4,0))))+$H$101/life_fac*IF((4)<0,0,IF((4)=0,phi_0,IF((4)<life_fac,1,IF((4)=life_fac,1-phi_0,0))))+$I$101/life_fac*IF((3)<0,0,IF((3)=0,phi_0,IF((3)<life_fac,1,IF((3)=life_fac,1-phi_0,0))))+$J$101/life_fac*IF((2)<0,0,IF((2)=0,phi_0,IF((2)<life_fac,1,IF((2)=life_fac,1-phi_0,0))))+$K$101/life_fac*IF((1)<0,0,IF((1)=0,phi_0,IF((1)<life_fac,1,IF((1)=life_fac,1-phi_0,0))))+$L$101/life_fac*IF((0)<0,0,IF((0)=0,phi_0,IF((0)<life_fac,1,IF((0)=life_fac,1-phi_0,0)))) -> 10.233264 | M103: =$F$99/life_fac*IF((6)<0,0,IF((6)=0,phi_q4,IF((6)<life_fac,1,IF((6)=life_fac,1-phi_q4,0))))+$F$101/life_fac*IF((6)<0,0,IF((6)=0,phi_q4,IF((6)<life_fac,1,IF((6)=life_fac,1-phi_q4,0))))+$H$101/life_fac*IF((5)<0,0,IF((5)=0,phi_0,IF((5)<life_fac,1,IF((5)=life_fac,1-phi_0,0))))+$I$101/life_fac*IF((4)<0,0,IF((4)=0,phi_0,IF((4)<life_fac,1,IF((4)=life_fac,1-phi_0,0))))+$J$101/life_fac*IF((3)<0,0,IF((3)=0,phi_0,IF((3)<life_fac,1,IF((3)=life_fac,1-phi_0,0))))+$K$101/life_fac*IF((2)<0,0,IF((2)=0,phi_0,IF((2)<life_fac,1,IF((2)=life_fac,1-phi_0,0))))+$L$101/life_fac*IF((1)<0,0,IF((1)=0,phi_0,IF((1)<life_fac,1,IF((1)=life_fac,1-phi_0,0))))+$M$101/life_fac*IF((0)<0,0,IF((0)=0,phi_0,IF((0)<life_fac,1,IF((0)=life_fac,1-phi_0,0)))) -> 10.932981
...

Sheet Seg
A1: Seg — 營收分部層：官方分部 Family of Apps（子列 Advertising、Other revenue）、Reality Labs。命題模組：Advertising＝廣告曝光數 × 每則廣告平均價格；情境差異只在每則價格（A：AI 提升／B：近四季成長收斂／C：提升消退）
A2: 成長路徑：Q4 26 年增＝近四季年增（Q 頁），之後線性收斂到長期值（conv_n 年，FY2030 到達）。曝光與價格各自收斂；價格情境＝B 路徑 ×(1＋情境調整)，調整自 FY2026 的 0 線性到 FY2030 的 In 頁值。非 AI 資本支出＝營收 × cx_na
A4: 情境 A（AI 提高每則廣告價格）
A5: 項目 | B5: 單位 | C5: FY2024A | D5: FY2025A | E5: 9M26A | F5: Q4 26E | G5: FY2026E | H5: FY2027E | I5: FY2028E | J5: FY2029E | K5: FY2030E | L5: FY2031E | M5: FY2032E | N5: 說明
A6: 廣告曝光數年增（B 路徑） | B6: % | F6: =g0_impr -> 0.1525 | H6: =g0_impr+(gl_impr-g0_impr)*MIN(1,(2027-2026)/conv_n) -> 0.126875 | I6: =g0_impr+(gl_impr-g0_impr)*MIN(1,(2028-2026)/conv_n) -> 0.10125 | J6: =g0_impr+(gl_impr-g0_impr)*MIN(1,(2029-2026)/conv_n) -> 0.075625 | K6: =g0_impr+(gl_impr-g0_impr)*MIN(1,(2030-2026)/conv_n) -> 0.05 | L6: =g0_impr+(gl_impr-g0_impr)*MIN(1,(2031-2026)/conv_n) -> 0.05 | M6: =g0_impr+(gl_impr-g0_impr)*MIN(1,(2032-2026)/conv_n) -> 0.05 | N6: Q4 26＝近四季平均（Q 頁），FY2030 收斂到 gl_impr
A7: 每則廣告價格年增（B 路徑） | B7: % | F7: =g0_price -> 0.10600664 | H7: =g0_price+(gl_price-g0_price)*MIN(1,(2027-2026)/conv_n) -> 0.087004981 | I7: =g0_price+(gl_price-g0_price)*MIN(1,(2028-2026)/conv_n) -> 0.068003321 | J7: =g0_price+(gl_price-g0_price)*MIN(1,(2029-2026)/conv_n) -> 0.04900166 | K7: =g0_price+(gl_price-g0_price)*MIN(1,(2030-2026)/conv_n) -> 0.03 | L7: =g0_price+(gl_price-g0_price)*MIN(1,(2031-2026)/conv_n) -> 0.03 | M7: =g0_price+(gl_price-g0_price)*MIN(1,(2032-2026)/conv_n) -> 0.03 | N7: Q4 26＝由近四季廣告金額年增反推，FY2030 收斂到 gl_price
A8: Advertising：B 路徑（曝光 × 價格） | B8: US$B | C8: =Q!J5 -> 160.633 | D8: =Q!K5 -> 196.175 | E8: =Q!L5 -> 177.448 | F8: =Q!F5*(1+F6)*(1+F7) -> 74.105644 | G8: =E8+F8 -> 251.55364 | H8: =G8*(1+H6)*(1+H7) -> 308.13277 | I8: =H8*(1+I6)*(1+I7) -> 362.40687 | J8: =I8*(1+J6)*(1+J7) -> 408.91541 | K8: =J8*(1+K6)*(1+K7) -> 442.24202 | L8: =K8*(1+L6)*(1+L7) -> 478.28474 | M8: =L8*(1+M6)*(1+M7) -> 517.26495 | N8: Q4 26＝2025Q4 × (1＋曝光年增) × (1＋價格年增)；年度＝前一年 × 同式
A9: 情境爬坡（FY2026 0 → FY2030 1） | B9: x | F9: 0 | H9: =MIN(1,(2027-2026)/conv_n) -> 0.25 | I9: =MIN(1,(2028-2026)/conv_n) -> 0.5 | J9: =MIN(1,(2029-2026)/conv_n) -> 0.75 | K9: =MIN(1,(2030-2026)/conv_n) -> 1 | L9: =MIN(1,(2031-2026)/conv_n) -> 1 | M9: =MIN(1,(2032-2026)/conv_n) -> 1
A10: 每則價格情境調整（相對 B 路徑） | B10: % | F10: =pA*F9 -> 0 | H10: =pA*H9 -> 0.025 | I10: =pA*I9 -> 0.05 | J10: =pA*J9 -> 0.075 | K10: =pA*K9 -> 0.1 | L10: =pA*L9 -> 0.1 | M10: =pA*M9 -> 0.1 | N10: In 頁 pA
A11: Advertising | B11: US$B | C11: =C8 -> 160.633 | D11: =D8 -> 196.175 | E11: =E8 -> 177.448 | F11: =F8*(1+F10) -> 74.105644 | G11: =E11+F11 -> 251.55364 | H11: =H8*(1+H10) -> 315.83609 | I11: =I8*(1+I10) -> 380.52721 | J11: =J8*(1+J10) -> 439.58407 | K11: =K8*(1+K10) -> 486.46622 | L11: =L8*(1+L10) -> 526.11322 | M11: =M8*(1+M10) -> 568.99144
A12: Advertising 年增 | B12: % | D12: =D11/C11-1 -> 0.22126213 | G12: =G11/D11-1 -> 0.28229206 | H12: =H11/G11-1 -> 0.25554171 | I12: =I11/H11-1 -> 0.20482497 | J12: =J11/I11-1 -> 0.15519747 | K12: =K11/J11-1 -> 0.10665116 | L12: =L11/K11-1 -> 0.0815 | M12: =M11/L11-1 -> 0.0815
A13: Other revenue 年增 | B13: % | F13: =g0_other -> 0.64639444 | H13: =g0_other+(gl_other-g0_other)*MIN(1,(2027-2026)/conv_n) -> 0.52229583 | I13: =g0_other+(gl_other-g0_other)*MIN(1,(2028-2026)/conv_n) -> 0.39819722 | J13: =g0_other+(gl_other-g0_other)*MIN(1,(2029-2026)/conv_n) -> 0.27409861 | K13: =g0_other+(gl_other-g0_other)*MIN(1,(2030-2026)/conv_n) -> 0.15 | L13: =g0_other+(gl_other-g0_other)*MIN(1,(2031-2026)/conv_n) -> 0.15 | M13: =g0_other+(gl_other-g0_other)*MIN(1,(2032-2026)/conv_n) -> 0.15 | N13: 三情境相同
A14: Other revenue | B14: US$B | C14: =Q!J6 -> 1.722 | D14: =Q!K6 -> 2.584 | E14: =Q!L6 -> 2.989 | F14: =Q!F6*(1+F13) -> 1.3187619 | G14: =E14+F14 -> 4.3077619 | H14: =G14*(1+H13) -> 6.557688 | I14: =H14*(1+I13) -> 9.1689412 | J14: =I14*(1+J13) -> 11.682135 | K14: =J14*(1+K13) -> 13.434456 | L14: =K14*(1+L13) -> 15.449624 | M14: =L14*(1+M13) -> 17.767067
A15: Family of Apps | B15: US$B | C15: =Q!J7 -> 162.355 | D15: =Q!K7 -> 198.759 | E15: =Q!L7 -> 180.437 | F15: =F11+F14 -> 75.424406 | G15: =E15+F15 -> 255.86141 | H15: =H11+H14 -> 322.39378 | I15: =I11+I14 -> 389.69615 | J15: =J11+J14 -> 451.2662 | K15: =K11+K14 -> 499.90068 | L15: =L11+L14 -> 541.56284 | M15: =M11+M14 -> 586.75851
A16: Reality Labs 營收年增 | B16: % | F16: =g0_rl -> -0.044539615 | H16: =g0_rl+(gl_rl-g0_rl)*MIN(1,(2027-2026)/conv_n) -> -0.020904711 | I16: =g0_rl+(gl_rl-g0_rl)*MIN(1,(2028-2026)/conv_n) -> 0.0027301927 | J16: =g0_rl+(gl_rl-g0_rl)*MIN(1,(2029-2026)/conv_n) -> 0.026365096 | K16: =g0_rl+(gl_rl-g0_rl)*MIN(1,(2030-2026)/conv_n) -> 0.05 | L16: =g0_rl+(gl_rl-g0_rl)*MIN(1,(2031-2026)/conv_n) -> 0.05 | M16: =g0_rl+(gl_rl-g0_rl)*MIN(1,(2032-2026)/conv_n) -> 0.05 | N16: 三情境相同
A17: Reality Labs | B17: US$B | C17: =Q!J9 -> 2.146 | D17: =Q!K9 -> 2.207 | E17: =Q!L9 -> 1.276 | F17: =Q!F9*(1+F16) -> 0.91246467 | G17: =E17+F17 -> 2.1884647 | H17: =G17*(1+H16) -> 2.1427154 | I17: =H17*(1+I16) -> 2.1485655 | J17: =I17*(1+J16) -> 2.2052126 | K17: =J17*(1+K16) -> 2.3154732 | L17: =K17*(1+L16) -> 2.4312469 | M17: =L17*(1+M16) -> 2.5528092
A18: 合併營收 | B18: US$B | C18: =Q!J10 -> 164.501 | D18: =Q!K10 -> 200.966 | E18: =Q!L10 -> 181.713 | F18: =F15+F17 -> 76.336871 | G18: =E18+F18 -> 258.04987 | H18: =H15+H17 -> 324.5365 | I18: =I15+I17 -> 391.84471 | J18: =J15+J17 -> 453.47142 | K18: =K15+K17 -> 502.21615 | L18: =L15+L17 -> 543.99409 | M18: =M15+M17 -> 589.31132
A19: 檢查：Advertising＋Other revenue－Family of Apps | B19: US$B | C19: =C11+C14-C15 -> 0 | D19: =D11+D14-D15 -> 0 | E19: =E11+E14-E15 -> 0 | F19: =F11+F14-F15 -> 0 | G19: =G11+G14-G15 -> 0 | H19: =H11+H14-H15 -> 0 | I19: =I11+I14-I15 -> 0 | J19: =J11+J14-J15 -> 0 | ... M19: =M11+M14-M15 -> 0
A20: 檢查：分部合計－合併營收 | B20: US$B | C20: =C15+C17-C18 -> 0 | D20: =D15+D17-D18 -> 0 | E20: =E15+E17-E18 -> 0 | F20: =F15+F17-F18 -> 0 | G20: =G15+G17-G18 -> 0 | H20: =H15+H17-H18 -> 0 | I20: =I15+I17-I18 -> 0 | J20: =J15+J17-J18 -> 0 | ... M20: =M15+M17-M18 -> 0
A21: 檢查：實績欄合併營收 − Q 頁（FY2024、FY2025、9M26） | B21: US$B | C21: =C18-Q!J10 -> 0 | D21: =D18-Q!K10 -> 0 | E21: =E18-Q!L10 -> 0
A22: 非 AI 資本支出（營收 × cx_na） | B22: US$B | F22: =F18*cx_na -> 3.0534748 | G22: =F22 -> 3.0534748 | H22: =H18*cx_na -> 12.98146 | I22: =I18*cx_na -> 15.673789 | J22: =J18*cx_na -> 18.138857 | K22: =K18*cx_na -> 20.088646 | L22: =L18*cx_na -> 21.759763 | M22: =M18*cx_na -> 23.572453
A23: 新增非 AI 折舊（年限 life_na） | B23: US$B | F23: =$F$22/life_na*IF((0)<0,0,IF((0)=0,phi_q4,IF((0)<life_na,1,IF((0)=life_na,1-phi_q4,0)))) -> 0.038168435 | G23: =F23 -> 0.038168435 | H23: =$F$22/life_na*IF((1)<0,0,IF((1)=0,phi_q4,IF((1)<life_na,1,IF((1)=life_na,1-phi_q4,0))))+$H$22/life_na*IF((0)<0,0,IF((0)=0,phi_0,IF((0)<life_na,1,IF((0)=life_na,1-phi_0,0)))) -> 0.62988398 | I23: =$F$22/life_na*IF((2)<0,0,IF((2)=0,phi_q4,IF((2)<life_na,1,IF((2)=life_na,1-phi_q4,0))))+$H$22/life_na*IF((1)<0,0,IF((1)=0,phi_0,IF((1)<life_na,1,IF((1)=life_na,1-phi_0,0))))+$I$22/life_na*IF((0)<0,0,IF((0)=0,phi_0,IF((0)<life_na,1,IF((0)=life_na,1-phi_0,0)))) -> 1.9953382 | J23: =$F$22/life_na*IF((3)<0,0,IF((3)=0,phi_q4,IF((3)<life_na,1,IF((3)=life_na,1-phi_q4,0))))+$H$22/life_na*IF((2)<0,0,IF((2)=0,phi_0,IF((2)<life_na,1,IF((2)=life_na,1-phi_0,0))))+$I$22/life_na*IF((1)<0,0,IF((1)=0,phi_0,IF((1)<life_na,1,IF((1)=life_na,1-phi_0,0))))+$J$22/life_na*IF((0)<0,0,IF((0)=0,phi_0,IF((0)<life_na,1,IF((0)=life_na,1-phi_0,0)))) -> 3.6243437 | K23: =$F$22/life_na*IF((4)<0,0,IF((4)=0,phi_q4,IF((4)<life_na,1,IF((4)=life_na,1-phi_q4,0))))+$H$22/life_na*IF((3)<0,0,IF((3)=0,phi_0,IF((3)<life_na,1,IF((3)=life_na,1-phi_0,0))))+$I$22/life_na*IF((2)<0,0,IF((2)=0,phi_0,IF((2)<life_na,1,IF((2)=life_na,1-phi_0,0))))+$J$22/life_na*IF((1)<0,0,IF((1)=0,phi_0,IF((1)<life_na,1,IF((1)=life_na,1-phi_0,0))))+$K$22/life_na*IF((0)<0,0,IF((0)=0,phi_0,IF((0)<life_na,1,IF((0)=life_na,1-phi_0,0)))) -> 5.4869741 | L23: =$F$22/life_na*IF((5)<0,0,IF((5)=0,phi_q4,IF((5)<life_na,1,IF((5)=life_na,1-phi_q4,0))))+$H$22/life_na*IF((4)<0,0,IF((4)=0,phi_0,IF((4)<life_na,1,IF((4)=life_na,1-phi_0,0))))+$I$22/life_na*IF((3)<0,0,IF((3)=0,phi_0,IF((3)<life_na,1,IF((3)=life_na,1-phi_0,0))))+$J$22/life_na*IF((2)<0,0,IF((2)=0,phi_0,IF((2)<life_na,1,IF((2)=life_na,1-phi_0,0))))+$K$22/life_na*IF((1)<0,0,IF((1)=0,phi_0,IF((1)<life_na,1,IF((1)=life_na,1-phi_0,0))))+$L$22/life_na*IF((0)<0,0,IF((0)=0,phi_0,IF((0)<life_na,1,IF((0)=life_na,1-phi_0,0)))) -> 7.5376167 | M23: =$F$22/life_na*IF((6)<0,0,IF((6)=0,phi_q4,IF((6)<life_na,1,IF((6)=life_na,1-phi_q4,0))))+$H$22/life_na*IF((5)<0,0,IF((5)=0,phi_0,IF((5)<life_na,1,IF((5)=life_na,1-phi_0,0))))+$I$22/life_na*IF((4)<0,0,IF((4)=0,phi_0,IF((4)<life_na,1,IF((4)=life_na,1-phi_0,0))))+$J$22/life_na*IF((3)<0,0,IF((3)=0,phi_0,IF((3)<life_na,1,IF((3)=life_na,1-phi_0,0))))+$K$22/life_na*IF((2)<0,0,IF((2)=0,phi_0,IF((2)<life_na,1,IF((2)=life_na,1-phi_0,0))))+$L$22/life_na*IF((1)<0,0,IF((1)=0,phi_0,IF((1)<life_na,1,IF((1)=life_na,1-phi_0,0))))+$M$22/life_na*IF((0)<0,0,IF((0)=0,phi_0,IF((0)<life_na,1,IF((0)=life_na,1-phi_0,0)))) -> 9.7589102
A25: 情境 B（近四季成長收斂；基準）
A26: 項目 | B26: 單位 | C26: FY2024A | D26: FY2025A | E26: 9M26A | F26: Q4 26E | G26: FY2026E | H26: FY2027E | I26: FY2028E | J26: FY2029E | K26: FY2030E | L26: FY2031E | M26: FY2032E | N26: 說明
A27: 廣告曝光數年增（B 路徑） | B27: % | F27: =g0_impr -> 0.1525 | H27: =g0_impr+(gl_impr-g0_impr)*MIN(1,(2027-2026)/conv_n) -> 0.126875 | I27: =g0_impr+(gl_impr-g0_impr)*MIN(1,(2028-2026)/conv_n) -> 0.10125 | J27: =g0_impr+(gl_impr-g0_impr)*MIN(1,(2029-2026)/conv_n) -> 0.075625 | K27: =g0_impr+(gl_impr-g0_impr)*MIN(1,(2030-2026)/conv_n) -> 0.05 | L27: =g0_impr+(gl_impr-g0_impr)*MIN(1,(2031-2026)/conv_n) -> 0.05 | M27: =g0_impr+(gl_impr-g0_impr)*MIN(1,(2032-2026)/conv_n) -> 0.05 | N27: Q4 26＝近四季平均（Q 頁），FY2030 收斂到 gl_impr
A28: 每則廣告價格年增（B 路徑） | B28: % | F28: =g0_price -> 0.10600664 | H28: =g0_price+(gl_price-g0_price)*MIN(1,(2027-2026)/conv_n) -> 0.087004981 | I28: =g0_price+(gl_price-g0_price)*MIN(1,(2028-2026)/conv_n) -> 0.068003321 | J28: =g0_price+(gl_price-g0_price)*MIN(1,(2029-2026)/conv_n) -> 0.04900166 | K28: =g0_price+(gl_price-g0_price)*MIN(1,(2030-2026)/conv_n) -> 0.03 | L28: =g0_price+(gl_price-g0_price)*MIN(1,(2031-2026)/conv_n) -> 0.03 | M28: =g0_price+(gl_price-g0_price)*MIN(1,(2032-2026)/conv_n) -> 0.03 | N28: Q4 26＝由近四季廣告金額年增反推，FY2030 收斂到 gl_price
A29: Advertising：B 路徑（曝光 × 價格） | B29: US$B | C29: =Q!J5 -> 160.633 | D29: =Q!K5 -> 196.175 | E29: =Q!L5 -> 177.448 | F29: =Q!F5*(1+F27)*(1+F28) -> 74.105644 | G29: =E29+F29 -> 251.55364 | H29: =G29*(1+H27)*(1+H28) -> 308.13277 | I29: =H29*(1+I27)*(1+I28) -> 362.40687 | J29: =I29*(1+J27)*(1+J28) -> 408.91541 | K29: =J29*(1+K27)*(1+K28) -> 442.24202 | L29: =K29*(1+L27)*(1+L28) -> 478.28474 | M29: =L29*(1+M27)*(1+M28) -> 517.26495 | N29: Q4 26＝2025Q4 × (1＋曝光年增) × (1＋價格年增)；年度＝前一年 × 同式
A30: 情境爬坡（FY2026 0 → FY2030 1） | B30: x | F30: 0 | H30: =MIN(1,(2027-2026)/conv_n) -> 0.25 | I30: =MIN(1,(2028-2026)/conv_n) -> 0.5 | J30: =MIN(1,(2029-2026)/conv_n) -> 0.75 | K30: =MIN(1,(2030-2026)/conv_n) -> 1 | L30: =MIN(1,(2031-2026)/conv_n) -> 1 | M30: =MIN(1,(2032-2026)/conv_n) -> 1
A31: 每則價格情境調整（相對 B 路徑） | B31: % | F31: =0*F30 -> 0 | H31: =0*H30 -> 0 | I31: =0*I30 -> 0 | J31: =0*J30 -> 0 | K31: =0*K30 -> 0 | L31: =0*L30 -> 0 | M31: =0*M30 -> 0 | N31: 基準不另調整
A32: Advertising | B32: US$B | C32: =C29 -> 160.633 | D32: =D29 -> 196.175 | E32: =E29 -> 177.448 | F32: =F29*(1+F31) -> 74.105644 | G32: =E32+F32 -> 251.55364 | H32: =H29*(1+H31) -> 308.13277 | I32: =I29*(1+I31) -> 362.40687 | J32: =J29*(1+J31) -> 408.91541 | K32: =K29*(1+K31) -> 442.24202 | L32: =L29*(1+L31) -> 478.28474 | M32: =M29*(1+M31) -> 517.26495
A33: Advertising 年增 | B33: % | D33: =D32/C32-1 -> 0.22126213 | G33: =G32/D32-1 -> 0.28229206 | H33: =H32/G32-1 -> 0.22491874 | I33: =I32/H32-1 -> 0.17613866 | J33: =J32/I32-1 -> 0.12833241 | K33: =K32/J32-1 -> 0.0815 | L33: =L32/K32-1 -> 0.0815 | M33: =M32/L32-1 -> 0.0815
A34: Other revenue 年增 | B34: % | F34: =g0_other -> 0.64639444 | H34: =g0_other+(gl_other-g0_other)*MIN(1,(2027-2026)/conv_n) -> 0.52229583 | I34: =g0_other+(gl_other-g0_other)*MIN(1,(2028-2026)/conv_n) -> 0.39819722 | J34: =g0_other+(gl_other-g0_other)*MIN(1,(2029-2026)/conv_n) -> 0.27409861 | K34: =g0_other+(gl_other-g0_other)*MIN(1,(2030-2026)/conv_n) -> 0.15 | L34: =g0_other+(gl_other-g0_other)*MIN(1,(2031-2026)/conv_n) -> 0.15 | M34: =g0_other+(gl_other-g0_other)*MIN(1,(2032-2026)/conv_n) -> 0.15 | N34: 三情境相同
A35: Other revenue | B35: US$B | C35: =Q!J6 -> 1.722 | D35: =Q!K6 -> 2.584 | E35: =Q!L6 -> 2.989 | F35: =Q!F6*(1+F34) -> 1.3187619 | G35: =E35+F35 -> 4.3077619 | H35: =G35*(1+H34) -> 6.557688 | I35: =H35*(1+I34) -> 9.1689412 | J35: =I35*(1+J34) -> 11.682135 | K35: =J35*(1+K34) -> 13.434456 | L35: =K35*(1+L34) -> 15.449624 | M35: =L35*(1+M34) -> 17.767067
A36: Family of Apps | B36: US$B | C36: =Q!J7 -> 162.355 | D36: =Q!K7 -> 198.759 | E36: =Q!L7 -> 180.437 | F36: =F32+F35 -> 75.424406 | G36: =E36+F36 -> 255.86141 | H36: =H32+H35 -> 314.69046 | I36: =I32+I35 -> 371.57581 | J36: =J32+J35 -> 420.59755 | K36: =K32+K35 -> 455.67647 | L36: =L32+L35 -> 493.73437 | M36: =M32+M35 -> 535.03202
A37: Reality Labs 營收年增 | B37: % | F37: =g0_rl -> -0.044539615 | H37: =g0_rl+(gl_rl-g0_rl)*MIN(1,(2027-2026)/conv_n) -> -0.020904711 | I37: =g0_rl+(gl_rl-g0_rl)*MIN(1,(2028-2026)/conv_n) -> 0.0027301927 | J37: =g0_rl+(gl_rl-g0_rl)*MIN(1,(2029-2026)/conv_n) -> 0.026365096 | K37: =g0_rl+(gl_rl-g0_rl)*MIN(1,(2030-2026)/conv_n) -> 0.05 | L37: =g0_rl+(gl_rl-g0_rl)*MIN(1,(2031-2026)/conv_n) -> 0.05 | M37: =g0_rl+(gl_rl-g0_rl)*MIN(1,(2032-2026)/conv_n) -> 0.05 | N37: 三情境相同
A38: Reality Labs | B38: US$B | C38: =Q!J9 -> 2.146 | D38: =Q!K9 -> 2.207 | E38: =Q!L9 -> 1.276 | F38: =Q!F9*(1+F37) -> 0.91246467 | G38: =E38+F38 -> 2.1884647 | H38: =G38*(1+H37) -> 2.1427154 | I38: =H38*(1+I37) -> 2.1485655 | J38: =I38*(1+J37) -> 2.2052126 | K38: =J38*(1+K37) -> 2.3154732 | L38: =K38*(1+L37) -> 2.4312469 | M38: =L38*(1+M37) -> 2.5528092
A39: 合併營收 | B39: US$B | C39: =Q!J10 -> 164.501 | D39: =Q!K10 -> 200.966 | E39: =Q!L10 -> 181.713 | F39: =F36+F38 -> 76.336871 | G39: =E39+F39 -> 258.04987 | H39: =H36+H38 -> 316.83318 | I39: =I36+I38 -> 373.72437 | J39: =J36+J38 -> 422.80276 | K39: =K36+K38 -> 457.99195 | L39: =L36+L38 -> 496.16561 | M39: =M36+M38 -> 537.58483
A40: 檢查：Advertising＋Other revenue－Family of Apps | B40: US$B | C40: =C32+C35-C36 -> 0 | D40: =D32+D35-D36 -> 0 | E40: =E32+E35-E36 -> 0 | F40: =F32+F35-F36 -> 0 | G40: =G32+G35-G36 -> 0 | H40: =H32+H35-H36 -> 0 | I40: =I32+I35-I36 -> 0 | J40: =J32+J35-J36 -> 0 | ... M40: =M32+M35-M36 -> 0
A41: 檢查：分部合計－合併營收 | B41: US$B | C41: =C36+C38-C39 -> 0 | D41: =D36+D38-D39 -> 0 | E41: =E36+E38-E39 -> 0 | F41: =F36+F38-F39 -> 0 | G41: =G36+G38-G39 -> 0 | H41: =H36+H38-H39 -> 0 | I41: =I36+I38-I39 -> 0 | J41: =J36+J38-J39 -> 0 | ... M41: =M36+M38-M39 -> 0
A42: 檢查：實績欄合併營收 − Q 頁（FY2024、FY2025、9M26） | B42: US$B | C42: =C39-Q!J10 -> 0 | D42: =D39-Q!K10 -> 0 | E42: =E39-Q!L10 -> 0
A43: 非 AI 資本支出（營收 × cx_na） | B43: US$B | F43: =F39*cx_na -> 3.0534748 | G43: =F43 -> 3.0534748 | H43: =H39*cx_na -> 12.673327 | I43: =I39*cx_na -> 14.948975 | J43: =J39*cx_na -> 16.91211 | K43: =K39*cx_na -> 18.319678 | L43: =L39*cx_na -> 19.846625 | M43: =M39*cx_na -> 21.503393
A44: 新增非 AI 折舊（年限 life_na） | B44: US$B | F44: =$F$43/life_na*IF((0)<0,0,IF((0)=0,phi_q4,IF((0)<life_na,1,IF((0)=life_na,1-phi_q4,0)))) -> 0.038168435 | G44: =F44 -> 0.038168435 | H44: =$F$43/life_na*IF((1)<0,0,IF((1)=0,phi_q4,IF((1)<life_na,1,IF((1)=life_na,1-phi_q4,0))))+$H$43/life_na*IF((0)<0,0,IF((0)=0,phi_0,IF((0)<life_na,1,IF((0)=life_na,1-phi_0,0)))) -> 0.62218066 | I44: =$F$43/life_na*IF((2)<0,0,IF((2)=0,phi_q4,IF((2)<life_na,1,IF((2)=life_na,1-phi_q4,0))))+$H$43/life_na*IF((1)<0,0,IF((1)=0,phi_0,IF((1)<life_na,1,IF((1)=life_na,1-phi_0,0))))+$I$43/life_na*IF((0)<0,0,IF((0)=0,phi_0,IF((0)<life_na,1,IF((0)=life_na,1-phi_0,0)))) -> 1.9464046 | J44: =$F$43/life_na*IF((3)<0,0,IF((3)=0,phi_q4,IF((3)<life_na,1,IF((3)=life_na,1-phi_q4,0))))+$H$43/life_na*IF((2)<0,0,IF((2)=0,phi_0,IF((2)<life_na,1,IF((2)=life_na,1-phi_0,0))))+$I$43/life_na*IF((1)<0,0,IF((1)=0,phi_0,IF((1)<life_na,1,IF((1)=life_na,1-phi_0,0))))+$J$43/life_na*IF((0)<0,0,IF((0)=0,phi_0,IF((0)<life_na,1,IF((0)=life_na,1-phi_0,0)))) -> 3.4903804 | K44: =$F$43/life_na*IF((4)<0,0,IF((4)=0,phi_q4,IF((4)<life_na,1,IF((4)=life_na,1-phi_q4,0))))+$H$43/life_na*IF((3)<0,0,IF((3)=0,phi_0,IF((3)<life_na,1,IF((3)=life_na,1-phi_0,0))))+$I$43/life_na*IF((2)<0,0,IF((2)=0,phi_0,IF((2)<life_na,1,IF((2)=life_na,1-phi_0,0))))+$J$43/life_na*IF((1)<0,0,IF((1)=0,phi_0,IF((1)<life_na,1,IF((1)=life_na,1-phi_0,0))))+$K$43/life_na*IF((0)<0,0,IF((0)=0,phi_0,IF((0)<life_na,1,IF((0)=life_na,1-phi_0,0)))) -> 5.2167807 | L44: =$F$43/life_na*IF((5)<0,0,IF((5)=0,phi_q4,IF((5)<life_na,1,IF((5)=life_na,1-phi_q4,0))))+$H$43/life_na*IF((4)<0,0,IF((4)=0,phi_0,IF((4)<life_na,1,IF((4)=life_na,1-phi_0,0))))+$I$43/life_na*IF((3)<0,0,IF((3)=0,phi_0,IF((3)<life_na,1,IF((3)=life_na,1-phi_0,0))))+$J$43/life_na*IF((2)<0,0,IF((2)=0,phi_0,IF((2)<life_na,1,IF((2)=life_na,1-phi_0,0))))+$K$43/life_na*IF((1)<0,0,IF((1)=0,phi_0,IF((1)<life_na,1,IF((1)=life_na,1-phi_0,0))))+$L$43/life_na*IF((0)<0,0,IF((0)=0,phi_0,IF((0)<life_na,1,IF((0)=life_na,1-phi_0,0)))) -> 7.0869221 | M44: =$F$43/life_na*IF((6)<0,0,IF((6)=0,phi_q4,IF((6)<life_na,1,IF((6)=life_na,1-phi_q4,0))))+$H$43/life_na*IF((5)<0,0,IF((5)=0,phi_0,IF((5)<life_na,1,IF((5)=life_na,1-phi_0,0))))+$I$43/life_na*IF((4)<0,0,IF((4)=0,phi_0,IF((4)<life_na,1,IF((4)=life_na,1-phi_0,0))))+$J$43/life_na*IF((3)<0,0,IF((3)=0,phi_0,IF((3)<life_na,1,IF((3)=life_na,1-phi_0,0))))+$K$43/life_na*IF((2)<0,0,IF((2)=0,phi_0,IF((2)<life_na,1,IF((2)=life_na,1-phi_0,0))))+$L$43/life_na*IF((1)<0,0,IF((1)=0,phi_0,IF((1)<life_na,1,IF((1)=life_na,1-phi_0,0))))+$M$43/life_na*IF((0)<0,0,IF((0)=0,phi_0,IF((0)<life_na,1,IF((0)=life_na,1-phi_0,0)))) -> 9.1130038
A46: 情境 C（AI 價格提升消退）
A47: 項目 | B47: 單位 | C47: FY2024A | D47: FY2025A | E47: 9M26A | F47: Q4 26E | G47: FY2026E | H47: FY2027E | I47: FY2028E | J47: FY2029E | K47: FY2030E | L47: FY2031E | M47: FY2032E | N47: 說明
A48: 廣告曝光數年增（B 路徑） | B48: % | F48: =g0_impr -> 0.1525 | H48: =g0_impr+(gl_impr-g0_impr)*MIN(1,(2027-2026)/conv_n) -> 0.126875 | I48: =g0_impr+(gl_impr-g0_impr)*MIN(1,(2028-2026)/conv_n) -> 0.10125 | J48: =g0_impr+(gl_impr-g0_impr)*MIN(1,(2029-2026)/conv_n) -> 0.075625 | K48: =g0_impr+(gl_impr-g0_impr)*MIN(1,(2030-2026)/conv_n) -> 0.05 | L48: =g0_impr+(gl_impr-g0_impr)*MIN(1,(2031-2026)/conv_n) -> 0.05 | M48: =g0_impr+(gl_impr-g0_impr)*MIN(1,(2032-2026)/conv_n) -> 0.05 | N48: Q4 26＝近四季平均（Q 頁），FY2030 收斂到 gl_impr
A49: 每則廣告價格年增（B 路徑） | B49: % | F49: =g0_price -> 0.10600664 | H49: =g0_price+(gl_price-g0_price)*MIN(1,(2027-2026)/conv_n) -> 0.087004981 | I49: =g0_price+(gl_price-g0_price)*MIN(1,(2028-2026)/conv_n) -> 0.068003321 | J49: =g0_price+(gl_price-g0_price)*MIN(1,(2029-2026)/conv_n) -> 0.04900166 | K49: =g0_price+(gl_price-g0_price)*MIN(1,(2030-2026)/conv_n) -> 0.03 | L49: =g0_price+(gl_price-g0_price)*MIN(1,(2031-2026)/conv_n) -> 0.03 | M49: =g0_price+(gl_price-g0_price)*MIN(1,(2032-2026)/conv_n) -> 0.03 | N49: Q4 26＝由近四季廣告金額年增反推，FY2030 收斂到 gl_price
A50: Advertising：B 路徑（曝光 × 價格） | B50: US$B | C50: =Q!J5 -> 160.633 | D50: =Q!K5 -> 196.175 | E50: =Q!L5 -> 177.448 | F50: =Q!F5*(1+F48)*(1+F49) -> 74.105644 | G50: =E50+F50 -> 251.55364 | H50: =G50*(1+H48)*(1+H49) -> 308.13277 | I50: =H50*(1+I48)*(1+I49) -> 362.40687 | J50: =I50*(1+J48)*(1+J49) -> 408.91541 | K50: =J50*(1+K48)*(1+K49) -> 442.24202 | L50: =K50*(1+L48)*(1+L49) -> 478.28474 | M50: =L50*(1+M48)*(1+M49) -> 517.26495 | N50: Q4 26＝2025Q4 × (1＋曝光年增) × (1＋價格年增)；年度＝前一年 × 同式
A51: 情境爬坡（FY2026 0 → FY2030 1） | B51: x | F51: 0 | H51: =MIN(1,(2027-2026)/conv_n) -> 0.25 | I51: =MIN(1,(2028-2026)/conv_n) -> 0.5 | J51: =MIN(1,(2029-2026)/conv_n) -> 0.75 | K51: =MIN(1,(2030-2026)/conv_n) -> 1 | L51: =MIN(1,(2031-2026)/conv_n) -> 1 | M51: =MIN(1,(2032-2026)/conv_n) -> 1
A52: 每則價格情境調整（相對 B 路徑） | B52: % | F52: =pC*F51 -> 0 | H52: =pC*H51 -> -0.025 | I52: =pC*I51 -> -0.05 | J52: =pC*J51 -> -0.075 | K52: =pC*K51 -> -0.1 | L52: =pC*L51 -> -0.1 | M52: =pC*M51 -> -0.1 | N52: In 頁 pC
A53: Advertising | B53: US$B | C53: =C50 -> 160.633 | D53: =D50 -> 196.175 | E53: =E50 -> 177.448 | F53: =F50*(1+F52) -> 74.105644 | G53: =E53+F53 -> 251.55364 | H53: =H50*(1+H52) -> 300.42945 | I53: =I50*(1+I52) -> 344.28652 | J53: =J50*(1+J52) -> 378.24676 | K53: =K50*(1+K52) -> 398.01782 | L53: =L50*(1+L52) -> 430.45627 | M53: =M50*(1+M52) -> 465.53845
A54: Advertising 年增 | B54: % | D54: =D53/C53-1 -> 0.22126213 | G54: =G53/D53-1 -> 0.28229206 | H54: =H53/G53-1 -> 0.19429577 | I54: =I53/H53-1 -> 0.14598126 | J54: =J53/I53-1 -> 0.098639453 | K54: =K53/J53-1 -> 0.05227027 | L54: =L53/K53-1 -> 0.0815 | M54: =M53/L53-1 -> 0.0815
A55: Other revenue 年增 | B55: % | F55: =g0_other -> 0.64639444 | H55: =g0_other+(gl_other-g0_other)*MIN(1,(2027-2026)/conv_n) -> 0.52229583 | I55: =g0_other+(gl_other-g0_other)*MIN(1,(2028-2026)/conv_n) -> 0.39819722 | J55: =g0_other+(gl_other-g0_other)*MIN(1,(2029-2026)/conv_n) -> 0.27409861 | K55: =g0_other+(gl_other-g0_other)*MIN(1,(2030-2026)/conv_n) -> 0.15 | L55: =g0_other+(gl_other-g0_other)*MIN(1,(2031-2026)/conv_n) -> 0.15 | M55: =g0_other+(gl_other-g0_other)*MIN(1,(2032-2026)/conv_n) -> 0.15 | N55: 三情境相同
A56: Other revenue | B56: US$B | C56: =Q!J6 -> 1.722 | D56: =Q!K6 -> 2.584 | E56: =Q!L6 -> 2.989 | F56: =Q!F6*(1+F55) -> 1.3187619 | G56: =E56+F56 -> 4.3077619 | H56: =G56*(1+H55) -> 6.557688 | I56: =H56*(1+I55) -> 9.1689412 | J56: =I56*(1+J55) -> 11.682135 | K56: =J56*(1+K55) -> 13.434456 | L56: =K56*(1+L55) -> 15.449624 | M56: =L56*(1+M55) -> 17.767067
A57: Family of Apps | B57: US$B | C57: =Q!J7 -> 162.355 | D57: =Q!K7 -> 198.759 | E57: =Q!L7 -> 180.437 | F57: =F53+F56 -> 75.424406 | G57: =E57+F57 -> 255.86141 | H57: =H53+H56 -> 306.98714 | I57: =I53+I56 -> 353.45546 | J57: =J53+J56 -> 389.92889 | K57: =K53+K56 -> 411.45227 | L57: =L53+L56 -> 445.90589 | M57: =M53+M56 -> 483.30552
A58: Reality Labs 營收年增 | B58: % | F58: =g0_rl -> -0.044539615 | H58: =g0_rl+(gl_rl-g0_rl)*MIN(1,(2027-2026)/conv_n) -> -0.020904711 | I58: =g0_rl+(gl_rl-g0_rl)*MIN(1,(2028-2026)/conv_n) -> 0.0027301927 | J58: =g0_rl+(gl_rl-g0_rl)*MIN(1,(2029-2026)/conv_n) -> 0.026365096 | K58: =g0_rl+(gl_rl-g0_rl)*MIN(1,(2030-2026)/conv_n) -> 0.05 | L58: =g0_rl+(gl_rl-g0_rl)*MIN(1,(2031-2026)/conv_n) -> 0.05 | M58: =g0_rl+(gl_rl-g0_rl)*MIN(1,(2032-2026)/conv_n) -> 0.05 | N58: 三情境相同
A59: Reality Labs | B59: US$B | C59: =Q!J9 -> 2.146 | D59: =Q!K9 -> 2.207 | E59: =Q!L9 -> 1.276 | F59: =Q!F9*(1+F58) -> 0.91246467 | G59: =E59+F59 -> 2.1884647 | H59: =G59*(1+H58) -> 2.1427154 | I59: =H59*(1+I58) -> 2.1485655 | J59: =I59*(1+J58) -> 2.2052126 | K59: =J59*(1+K58) -> 2.3154732 | L59: =K59*(1+L58) -> 2.4312469 | M59: =L59*(1+M58) -> 2.5528092
A60: 合併營收 | B60: US$B | C60: =Q!J10 -> 164.501 | D60: =Q!K10 -> 200.966 | E60: =Q!L10 -> 181.713 | F60: =F57+F59 -> 76.336871 | G60: =E60+F60 -> 258.04987 | H60: =H57+H59 -> 309.12986 | I60: =I57+I59 -> 355.60403 | J60: =J57+J59 -> 392.1341 | K60: =K57+K59 -> 413.76774 | L60: =L57+L59 -> 448.33714 | M60: =M57+M59 -> 485.85833
A61: 檢查：Advertising＋Other revenue－Family of Apps | B61: US$B | C61: =C53+C56-C57 -> 0 | D61: =D53+D56-D57 -> 0 | E61: =E53+E56-E57 -> 0 | F61: =F53+F56-F57 -> 0 | G61: =G53+G56-G57 -> 0 | H61: =H53+H56-H57 -> 0 | I61: =I53+I56-I57 -> 0 | J61: =J53+J56-J57 -> 0 | ... M61: =M53+M56-M57 -> 0
A62: 檢查：分部合計－合併營收 | B62: US$B | C62: =C57+C59-C60 -> 0 | D62: =D57+D59-D60 -> 0 | E62: =E57+E59-E60 -> 0 | F62: =F57+F59-F60 -> 0 | G62: =G57+G59-G60 -> 0 | H62: =H57+H59-H60 -> 0 | I62: =I57+I59-I60 -> 0 | J62: =J57+J59-J60 -> 0 | ... M62: =M57+M59-M60 -> 0
A63: 檢查：實績欄合併營收 − Q 頁（FY2024、FY2025、9M26） | B63: US$B | C63: =C60-Q!J10 -> 0 | D63: =D60-Q!K10 -> 0 | E63: =E60-Q!L10 -> 0
A64: 非 AI 資本支出（營收 × cx_na） | B64: US$B | F64: =F60*cx_na -> 3.0534748 | G64: =F64 -> 3.0534748 | H64: =H60*cx_na -> 12.365194 | I64: =I60*cx_na -> 14.224161 | J64: =J60*cx_na -> 15.685364 | K64: =K60*cx_na -> 16.55071 | L64: =L60*cx_na -> 17.933486 | M64: =M60*cx_na -> 19.434333
A65: 新增非 AI 折舊（年限 life_na） | B65: US$B | F65: =$F$64/life_na*IF((0)<0,0,IF((0)=0,phi_q4,IF((0)<life_na,1,IF((0)=life_na,1-phi_q4,0)))) -> 0.038168435 | G65: =F65 -> 0.038168435 | H65: =$F$64/life_na*IF((1)<0,0,IF((1)=0,phi_q4,IF((1)<life_na,1,IF((1)=life_na,1-phi_q4,0))))+$H$64/life_na*IF((0)<0,0,IF((0)=0,phi_0,IF((0)<life_na,1,IF((0)=life_na,1-phi_0,0)))) -> 0.61447734 | I65: =$F$64/life_na*IF((2)<0,0,IF((2)=0,phi_q4,IF((2)<life_na,1,IF((2)=life_na,1-phi_q4,0))))+$H$64/life_na*IF((1)<0,0,IF((1)=0,phi_0,IF((1)<life_na,1,IF((1)=life_na,1-phi_0,0))))+$I$64/life_na*IF((0)<0,0,IF((0)=0,phi_0,IF((0)<life_na,1,IF((0)=life_na,1-phi_0,0)))) -> 1.8974709 | J65: =$F$64/life_na*IF((3)<0,0,IF((3)=0,phi_q4,IF((3)<life_na,1,IF((3)=life_na,1-phi_q4,0))))+$H$64/life_na*IF((2)<0,0,IF((2)=0,phi_0,IF((2)<life_na,1,IF((2)=life_na,1-phi_0,0))))+$I$64/life_na*IF((1)<0,0,IF((1)=0,phi_0,IF((1)<life_na,1,IF((1)=life_na,1-phi_0,0))))+$J$64/life_na*IF((0)<0,0,IF((0)=0,phi_0,IF((0)<life_na,1,IF((0)=life_na,1-phi_0,0)))) -> 3.3564171 | K65: =$F$64/life_na*IF((4)<0,0,IF((4)=0,phi_q4,IF((4)<life_na,1,IF((4)=life_na,1-phi_q4,0))))+$H$64/life_na*IF((3)<0,0,IF((3)=0,phi_0,IF((3)<life_na,1,IF((3)=life_na,1-phi_0,0))))+$I$64/life_na*IF((2)<0,0,IF((2)=0,phi_0,IF((2)<life_na,1,IF((2)=life_na,1-phi_0,0))))+$J$64/life_na*IF((1)<0,0,IF((1)=0,phi_0,IF((1)<life_na,1,IF((1)=life_na,1-phi_0,0))))+$K$64/life_na*IF((0)<0,0,IF((0)=0,phi_0,IF((0)<life_na,1,IF((0)=life_na,1-phi_0,0)))) -> 4.9465872 | L65: =$F$64/life_na*IF((5)<0,0,IF((5)=0,phi_q4,IF((5)<life_na,1,IF((5)=life_na,1-phi_q4,0))))+$H$64/life_na*IF((4)<0,0,IF((4)=0,phi_0,IF((4)<life_na,1,IF((4)=life_na,1-phi_0,0))))+$I$64/life_na*IF((3)<0,0,IF((3)=0,phi_0,IF((3)<life_na,1,IF((3)=life_na,1-phi_0,0))))+$J$64/life_na*IF((2)<0,0,IF((2)=0,phi_0,IF((2)<life_na,1,IF((2)=life_na,1-phi_0,0))))+$K$64/life_na*IF((1)<0,0,IF((1)=0,phi_0,IF((1)<life_na,1,IF((1)=life_na,1-phi_0,0))))+$L$64/life_na*IF((0)<0,0,IF((0)=0,phi_0,IF((0)<life_na,1,IF((0)=life_na,1-phi_0,0)))) -> 6.6362276 | M65: =$F$64/life_na*IF((6)<0,0,IF((6)=0,phi_q4,IF((6)<life_na,1,IF((6)=life_na,1-phi_q4,0))))+$H$64/life_na*IF((5)<0,0,IF((5)=0,phi_0,IF((5)<life_na,1,IF((5)=life_na,1-phi_0,0))))+$I$64/life_na*IF((4)<0,0,IF((4)=0,phi_0,IF((4)<life_na,1,IF((4)=life_na,1-phi_0,0))))+$J$64/life_na*IF((3)<0,0,IF((3)=0,phi_0,IF((3)<life_na,1,IF((3)=life_na,1-phi_0,0))))+$K$64/life_na*IF((2)<0,0,IF((2)=0,phi_0,IF((2)<life_na,1,IF((2)=life_na,1-phi_0,0))))+$L$64/life_na*IF((1)<0,0,IF((1)=0,phi_0,IF((1)<life_na,1,IF((1)=life_na,1-phi_0,0))))+$M$64/life_na*IF((0)<0,0,IF((0)=0,phi_0,IF((0)<life_na,1,IF((0)=life_na,1-phi_0,0)))) -> 8.4670973

Sheet PL
A1: PL — 分部營收 → 分部營業利益 → 合併營業利益 → 業外 → 稅 → 淨利 → EPS（三情境；US$B，EPS 美元）。實績欄（FY2024A、FY2025A、9M26A）取自 Q 頁；FY2026E＝9M 實績＋Q4 模型
A2: FoA EBITDA＝(FoA 營收 − 價格情境差額) × FoA EBITDA 率（9M26，排除一次性）＋差額 × inc_m − 自用 AI 增量營運成本與租金；FoA 折舊＝基礎折舊 ×(1 − RL 占比)＋新增 AI＋新增非 AI。RL 營業損益＝指引與法說路徑。財報口徑保留 2026 年一次性項目；評價口徑排除（M5 擴大）並加讀法 2 影子效益
A4: 分部對帳彙總（三情境 × 全部年度取絕對值最大者；實績欄同列）
A5: 項目 | B5: 單位 | C5: FY2024A | D5: FY2025A | E5: 9M26A | F5: Q4 26E | G5: FY2026E | H5: FY2027E | I5: FY2028E | J5: FY2029E | K5: FY2030E | L5: FY2031E | M5: FY2032E | N5: 說明
A6: 檢查：Advertising＋Other revenue－Family of Apps | B6: US$B | C6: =MAX(ABS(C18),ABS(C65),ABS(C112)) -> 0 | D6: =MAX(ABS(D18),ABS(D65),ABS(D112)) -> 0 | E6: =MAX(ABS(E18),ABS(E65),ABS(E112)) -> 0 | F6: =MAX(ABS(F18),ABS(F65),ABS(F112)) -> 0 | G6: =MAX(ABS(G18),ABS(G65),ABS(G112)) -> 0 | H6: =MAX(ABS(H18),ABS(H65),ABS(H112)) -> 0 | I6: =MAX(ABS(I18),ABS(I65),ABS(I112)) -> 0 | J6: =MAX(ABS(J18),ABS(J65),ABS(J112)) -> 0 | ... M6: =MAX(ABS(M18),ABS(M65),ABS(M112)) -> 0 | N6: 三情境各區塊同名核對列的最大絕對值；必須為 0（tools/segment_check 讀本列）
A7: 檢查：分部合計－合併營收 | B7: US$B | C7: =MAX(ABS(C19),ABS(C66),ABS(C113)) -> 0 | D7: =MAX(ABS(D19),ABS(D66),ABS(D113)) -> 0 | E7: =MAX(ABS(E19),ABS(E66),ABS(E113)) -> 0 | F7: =MAX(ABS(F19),ABS(F66),ABS(F113)) -> 0 | G7: =MAX(ABS(G19),ABS(G66),ABS(G113)) -> 0 | H7: =MAX(ABS(H19),ABS(H66),ABS(H113)) -> 0 | I7: =MAX(ABS(I19),ABS(I66),ABS(I113)) -> 0 | J7: =MAX(ABS(J19),ABS(J66),ABS(J113)) -> 0 | ... M7: =MAX(ABS(M19),ABS(M66),ABS(M113)) -> 0 | N7: 三情境各區塊同名核對列的最大絕對值；必須為 0（tools/segment_check 讀本列）
A8: 檢查：分部營業利益合計－合併營業利益 | B8: US$B | C8: =MAX(ABS(C32),ABS(C79),ABS(C126)) -> 0 | D8: =MAX(ABS(D32),ABS(D79),ABS(D126)) -> 0 | E8: =MAX(ABS(E32),ABS(E79),ABS(E126)) -> 0 | F8: =MAX(ABS(F32),ABS(F79),ABS(F126)) -> 0 | G8: =MAX(ABS(G32),ABS(G79),ABS(G126)) -> 0 | H8: =MAX(ABS(H32),ABS(H79),ABS(H126)) -> 0 | I8: =MAX(ABS(I32),ABS(I79),ABS(I126)) -> 0 | J8: =MAX(ABS(J32),ABS(J79),ABS(J126)) -> 0 | ... M8: =MAX(ABS(M32),ABS(M79),ABS(M126)) -> 0 | N8: 三情境各區塊同名核對列的最大絕對值；必須為 0（tools/segment_check 讀本列）
A10: 情境 A（AI 提高每則廣告價格）
A11: 項目 | B11: 單位 | C11: FY2024A | D11: FY2025A | E11: 9M26A | F11: Q4 26E | G11: FY2026E | H11: FY2027E | I11: FY2028E | J11: FY2029E | K11: FY2030E | L11: FY2031E | M11: FY2032E | N11: 說明
A12: Advertising | B12: US$B | C12: =Seg!C11 -> 160.633 | D12: =Seg!D11 -> 196.175 | E12: =Seg!E11 -> 177.448 | F12: =Seg!F11 -> 74.105644 | G12: =Seg!G11 -> 251.55364 | H12: =Seg!H11 -> 315.83609 | I12: =Seg!I11 -> 380.52721 | J12: =Seg!J11 -> 439.58407 | ... M12: =Seg!M11 -> 568.99144
A13: Other revenue | B13: US$B | C13: =Seg!C14 -> 1.722 | D13: =Seg!D14 -> 2.584 | E13: =Seg!E14 -> 2.989 | F13: =Seg!F14 -> 1.3187619 | G13: =Seg!G14 -> 4.3077619 | H13: =Seg!H14 -> 6.557688 | I13: =Seg!I14 -> 9.1689412 | J13: =Seg!J14 -> 11.682135 | ... M13: =Seg!M14 -> 17.767067
A14: Family of Apps | B14: US$B | C14: =Seg!C15 -> 162.355 | D14: =Seg!D15 -> 198.759 | E14: =Seg!E15 -> 180.437 | F14: =Seg!F15 -> 75.424406 | G14: =Seg!G15 -> 255.86141 | H14: =Seg!H15 -> 322.39378 | I14: =Seg!I15 -> 389.69615 | J14: =Seg!J15 -> 451.2662 | ... M14: =Seg!M15 -> 586.75851
A15: Reality Labs | B15: US$B | C15: =Seg!C17 -> 2.146 | D15: =Seg!D17 -> 2.207 | E15: =Seg!E17 -> 1.276 | F15: =Seg!F17 -> 0.91246467 | G15: =Seg!G17 -> 2.1884647 | H15: =Seg!H17 -> 2.1427154 | I15: =Seg!I17 -> 2.1485655 | J15: =Seg!J17 -> 2.2052126 | ... M15: =Seg!M17 -> 2.5528092
A16: 合併營收 | B16: US$B | C16: =Seg!C18 -> 164.501 | D16: =Seg!D18 -> 200.966 | E16: =Seg!E18 -> 181.713 | F16: =Seg!F18 -> 76.336871 | G16: =Seg!G18 -> 258.04987 | H16: =Seg!H18 -> 324.5365 | I16: =Seg!I18 -> 391.84471 | J16: =Seg!J18 -> 453.47142 | ... M16: =Seg!M18 -> 589.31132
A17: 合併營收年增 | B17: % | D17: =D16/C16-1 -> 0.22167038 | G17: =G16/D16-1 -> 0.2840474 | H17: =H16/G16-1 -> 0.25765029 | I17: =I16/H16-1 -> 0.207398 | J17: =J16/I16-1 -> 0.15727327 | K17: =K16/J16-1 -> 0.1074924 | L17: =L16/K16-1 -> 0.083187168 | M17: =M16/L16-1 -> 0.083304643
A18: 檢查：Advertising＋Other revenue－Family of Apps | B18: US$B | C18: =C12+C13-C14 -> 0 | D18: =D12+D13-D14 -> 0 | E18: =E12+E13-E14 -> 0 | F18: =F12+F13-F14 -> 0 | G18: =G12+G13-G14 -> 0 | H18: =H12+H13-H14 -> 0 | I18: =I12+I13-I14 -> 0 | J18: =J12+J13-J14 -> 0 | ... M18: =M12+M13-M14 -> 0
A19: 檢查：分部合計－合併營收 | B19: US$B | C19: =C14+C15-C16 -> 0 | D19: =D14+D15-D16 -> 0 | E19: =E14+E15-E16 -> 0 | F19: =F14+F15-F16 -> 0 | G19: =G14+G15-G16 -> 0 | H19: =H14+H15-H16 -> 0 | I19: =I14+I15-I16 -> 0 | J19: =J14+J15-J16 -> 0 | ... M19: =M14+M15-M16 -> 0
A20: 價格情境差額（相對 B 路徑） | B20: US$B | F20: =Seg!F11-Seg!F8 -> 0 | G20: =F20 -> 0 | H20: =Seg!H11-Seg!H8 -> 7.7033193 | I20: =Seg!I11-Seg!I8 -> 18.120343 | J20: =Seg!J11-Seg!J8 -> 30.668656 | K20: =Seg!K11-Seg!K8 -> 44.224202 | L20: =Seg!L11-Seg!L8 -> 47.828474 | M20: =Seg!M11-Seg!M8 -> 51.726495
A21: Family of Apps EBITDA（不含一次性） | B21: US$B | F21: =m_foa*(F14-F20)+inc_m*F20-Thesis!F63-Thesis!F64 -> 40.798461 | H21: =m_foa*(H14-H20)+inc_m*H20-Thesis!H63-Thesis!H64 -> 168.88164 | I21: =m_foa*(I14-I20)+inc_m*I20-Thesis!I63-Thesis!I64 -> 198.96732 | J21: =m_foa*(J14-J20)+inc_m*J20-Thesis!J63-Thesis!J64 -> 227.55142 | K21: =m_foa*(K14-K20)+inc_m*K20-Thesis!K63-Thesis!K64 -> 251.56025 | L21: =m_foa*(L14-L20)+inc_m*L20-Thesis!L63-Thesis!L64 -> 270.90801 | M21: =m_foa*(M14-M20)+inc_m*M20-Thesis!M63-Thesis!M64 -> 294.40049
A22: Family of Apps 折舊（基礎 ×(1 − RL 占比)＋新增 AI＋新增非 AI） | B22: US$B | F22: =Thesis!F68*(1-rl_da_sh)+Thesis!F61+Seg!F23 -> 9.0553129 | H22: =Thesis!H68*(1-rl_da_sh)+Thesis!H61+Seg!H23 -> 53.360319 | I22: =Thesis!I68*(1-rl_da_sh)+Thesis!I61+Seg!I23 -> 86.385116 | J22: =Thesis!J68*(1-rl_da_sh)+Thesis!J61+Seg!J23 -> 119.19948 | K22: =Thesis!K68*(1-rl_da_sh)+Thesis!K61+Seg!K23 -> 146.05922 | L22: =Thesis!L68*(1-rl_da_sh)+Thesis!L61+Seg!L23 -> 166.50029 | M22: =Thesis!M68*(1-rl_da_sh)+Thesis!M61+Seg!M23 -> 186.53747
A23: Family of Apps 營業利益 | B23: US$B | C23: =Q!J14 -> 87.109 | D23: =Q!K14 -> 102.469 | E23: =Q!L14 -> 67.411 | F23: =F21-F22 -> 31.743148 | G23: =E23+F23 -> 99.154148 | H23: =H21-H22 -> 115.52133 | I23: =I21-I22 -> 112.5822 | J23: =J21-J22 -> 108.35194 | K23: =K21-K22 -> 105.50103 | L23: =L21-L22 -> 104.40772 | M23: =M21-M22 -> 107.86302 | N23: 9M26 實績含一次性法律 12.29 與遣散 1.18（M5）
A24: Reality Labs 營業損益 | B24: US$B | C24: =Q!J15 -> -17.729 | D24: =Q!K15 -> -19.193 | E24: =Q!L15 -> -12.776 | F24: =-(rl_loss26+Q!L15) -> -5.724 | G24: =E24+F24 -> -18.5 | H24: =-rl_loss27 -> -15 | I24: =-(rl_loss27+(rl_loss32-rl_loss27)*(2028-2027)/5) -> -13 | J24: =-(rl_loss27+(rl_loss32-rl_loss27)*(2029-2027)/5) -> -11 | K24: =-(rl_loss27+(rl_loss32-rl_loss27)*(2030-2027)/5) -> -9 | L24: =-(rl_loss27+(rl_loss32-rl_loss27)*(2031-2027)/5) -> -7 | M24: =-(rl_loss27+(rl_loss32-rl_loss27)*(2032-2027)/5) -> -5 | N24: Q4 26＝2026 指引中點 − 9M 實績；FY2027 約 −15（法說）；之後線性到 FY2032 rl_loss32
A25: Reality Labs 折舊（基礎 × RL 占比） | B25: US$B | F25: =Thesis!F68*rl_da_sh -> 0.3577 | H25: =Thesis!H68*rl_da_sh -> 1.4308 | I25: =Thesis!I68*rl_da_sh -> 1.4308 | J25: =Thesis!J68*rl_da_sh -> 1.3761517 | K25: =Thesis!K68*rl_da_sh -> 1.2308073 | L25: =Thesis!L68*rl_da_sh -> 0.94389794 | M25: =Thesis!M68*rl_da_sh -> 0.74768472
A26: Reality Labs EBITDA | B26: US$B | F26: =F24+F25 -> -5.3663 | H26: =H24+H25 -> -13.5692 | I26: =I24+I25 -> -11.5692 | J26: =J24+J25 -> -9.6238483 | K26: =K24+K25 -> -7.7691927 | L26: =L24+L25 -> -6.0561021 | M26: =M24+M25 -> -4.2523153
A27: 分部營業利益合計 | B27: US$B | C27: =C23+C24 -> 69.38 | D27: =D23+D24 -> 83.276 | E27: =E23+E24 -> 54.635 | F27: =F23+F24 -> 26.019148 | G27: =G23+G24 -> 80.654148 | H27: =H23+H24 -> 100.52133 | I27: =I23+I24 -> 99.582202 | J27: =J23+J24 -> 97.351945 | ... M27: =M23+M24 -> 102.86302
A28: 合併 EBITDA（分部 EBITDA 合計） | B28: US$B | F28: =F21+F26 -> 35.432161 | H28: =H21+H26 -> 155.31244 | I28: =I21+I26 -> 187.39812 | J28: =J21+J26 -> 217.92757 | K28: =K21+K26 -> 243.79106 | L28: =L21+L26 -> 264.8519 | M28: =M21+M26 -> 290.14818
A29: 折舊與攤銷合計（基礎＋新增 AI＋新增非 AI） | B29: US$B | C29: =Q!J35 -> 15.498 | D29: =Q!K35 -> 18.616 | E29: =Q!L35 -> 19.509 | F29: =Thesis!F68+Thesis!F61+Seg!F23 -> 9.4130129 | G29: =E29+F29 -> 28.922013 | H29: =Thesis!H68+Thesis!H61+Seg!H23 -> 54.791119 | I29: =Thesis!I68+Thesis!I61+Seg!I23 -> 87.815916 | J29: =Thesis!J68+Thesis!J61+Seg!J23 -> 120.57563 | K29: =Thesis!K68+Thesis!K61+Seg!K23 -> 147.29003 | L29: =Thesis!L68+Thesis!L61+Seg!L23 -> 167.44418 | M29: =Thesis!M68+Thesis!M61+Seg!M23 -> 187.28516
A30: 其中：新增 AI 折舊 | B30: US$B | F30: =Thesis!F61 -> 2.2208445 | G30: =F30 -> 2.2208445 | H30: =Thesis!H61 -> 25.545235 | I30: =Thesis!I61 -> 57.204578 | J30: =Thesis!J61 -> 89.42825 | K30: =Thesis!K61 -> 117.18691 | L30: =Thesis!L61 -> 141.02861 | M30: =Thesis!M61 -> 162.57255
A31: 合併營業利益（財報口徑） | B31: US$B | C31: =Q!J16 -> 69.38 | D31: =Q!K16 -> 83.276 | E31: =Q!L16 -> 54.635 | F31: =F28-F29 -> 26.019148 | G31: =E31+F31 -> 80.654148 | H31: =H28-H29 -> 100.52133 | I31: =I28-I29 -> 99.582202 | J31: =J28-J29 -> 97.351945 | K31: =K28-K29 -> 96.50103 | L31: =L28-L29 -> 97.407719 | M31: =M28-M29 -> 102.86302 | N31: 預測期＝合併 EBITDA − 折舊合計（與分部合計獨立計算，下一列核對）
A32: 檢查：分部營業利益合計－合併營業利益 | B32: US$B | C32: =C27-C31 -> 0 | D32: =D27-D31 -> 0 | E32: =E27-E31 -> 0 | F32: =F27-F31 -> 0 | G32: =G27-G31 -> 0 | H32: =H27-H31 -> 0 | I32: =I27-I31 -> 0 | J32: =J27-J31 -> 0 | ... M32: =M27-M31 -> 0
A33: 一次性項目（營業利益內；負值＝費用） | B33: US$B | E33: =-ot_oi_9m -> -13.47 | F33: 0 | G33: =E33+F33 -> -13.47 | H33: 0 | I33: 0 | J33: 0 | K33: 0 | L33: 0 | M33: 0 | N33: Q2 法律 2.40＋遣散 1.18、Q3 法律 9.89（新聞稿）；預測期 0
A34: 營業利益（排除一次性） | B34: US$B | E34: =E31-E33 -> 68.105 | F34: =F31-F33 -> 26.019148 | G34: =G31-G33 -> 94.124148 | H34: =H31-H33 -> 100.52133 | I34: =I31-I33 -> 99.582202 | J34: =J31-J33 -> 97.351945 | K34: =K31-K33 -> 96.50103 | L34: =L31-L33 -> 97.407719 | M34: =M31-M33 -> 102.86302
A35: 自用 AI 影子效益（讀法 2；非財報營收） | B35: US$B | F35: =Thesis!F70 -> 4.1543738 | G35: =F35 -> 4.1543738 | H35: =Thesis!H70 -> 61.514412 | I35: =Thesis!I70 -> 119.71171 | J35: =Thesis!J70 -> 172.80224 | K35: =Thesis!K70 -> 212.74991 | L35: =Thesis!L70 -> 240.10595 | M35: =Thesis!M70 -> 255.13982
A36: 營業利益（評價口徑：排除一次性＋讀法 2 影子效益） | B36: US$B | E36: =E34 -> 68.105 | F36: =F34+(internal_ai_reading=2)*F35 -> 30.173522 | G36: =G34+(internal_ai_reading=2)*G35 -> 98.278522 | H36: =H34+(internal_ai_reading=2)*H35 -> 162.03574 | I36: =I34+(internal_ai_reading=2)*I35 -> 219.29391 | J36: =J34+(internal_ai_reading=2)*J35 -> 270.15419 | K36: =K34+(internal_ai_reading=2)*K35 -> 309.25094 | L36: =L34+(internal_ai_reading=2)*L35 -> 337.51367 | M36: =M34+(internal_ai_reading=2)*M35 -> 358.00284
A37: 營業利益率（財報口徑） | B37: % | C37: =C31/C16 -> 0.42176035 | D37: =D31/D16 -> 0.41437855 | E37: =E31/E16 -> 0.30066644 | F37: =F31/F16 -> 0.3408464 | G37: =G31/G16 -> 0.31255256 | H37: =H31/H16 -> 0.30973813 | I37: =I31/I16 -> 0.2541369 | J37: =J31/J16 -> 0.21468155 | ... M37: =M31/M16 -> 0.17454785
A38: 營業利益率（排除一次性） | B38: % | E38: =E34/E16 -> 0.37479432 | F38: =F34/F16 -> 0.3408464 | G38: =G34/G16 -> 0.36475177 | H38: =H34/H16 -> 0.30973813 | I38: =I34/I16 -> 0.2541369 | J38: =J34/J16 -> 0.21468155 | K38: =K34/K16 -> 0.19215039 | L38: =L34/L16 -> 0.17906025 | M38: =M34/M16 -> 0.17454785
A39: Family of Apps 營業利益率 | B39: % | C39: =C23/C14 -> 0.53653414 | D39: =D23/D14 -> 0.51554395 | E39: =E23/E14 -> 0.37359854 | F39: =F23/F14 -> 0.42086043 | G39: =G23/G14 -> 0.38753069 | H39: =H23/H14 -> 0.35832368 | I39: =I23/I14 -> 0.28889739 | J39: =J23/J14 -> 0.24010649 | ... M39: =M23/M14 -> 0.18382865
A40: 利息收入（期初現金 × r_cash） | B40: US$B | F40: =r_cash*CF!F31*0.25 -> 0.82449 | G40: =F40 -> 0.82449 | H40: =r_cash*CF!H31*1 -> 3.1597857 | I40: =r_cash*CF!I31*1 -> 1.6 | J40: =r_cash*CF!J31*1 -> 1.6 | K40: =r_cash*CF!K31*1 -> 2.3758941 | L40: =r_cash*CF!L31*1 -> 5.8770718 | M40: =r_cash*CF!M31*1 -> 10.901779
A41: 利息費用（期初債務 × r_debt） | B41: US$B | F41: =r_debt*CF!F38*0.25 -> 1.008 | G41: =F41 -> 1.008 | H41: =r_debt*CF!H38*1 -> 4.032 | I41: =r_debt*CF!I38*1 -> 4.3124875 | J41: =r_debt*CF!J38*1 -> 6.6074357 | K41: =r_debt*CF!K38*1 -> 6.6074357 | L41: =r_debt*CF!L38*1 -> 6.6074357 | M41: =r_debt*CF!M38*1 -> 6.6074357
A42: 業外收益合計 | B42: US$B | C42: =Q!J25 -> 1.283 | D42: =Q!K25 -> 2.656 | E42: =Q!L25 -> -1.126 | F42: =F40-F41 -> -0.18351 | G42: =E42+F42 -> -1.30951 | H42: =H40-H41 -> -0.87221434 | I42: =I40-I41 -> -2.7124875 | J42: =J40-J41 -> -5.0074357 | K42: =K40-K41 -> -4.2315416 | L42: =L40-L41 -> -0.73036387 | M42: =M40-M41 -> 4.2943436
A43: 稅前利益 | B43: US$B | C43: =C31+C42 -> 70.663 | D43: =D31+D42 -> 85.932 | E43: =E31+E42 -> 53.509 | F43: =F31+F42 -> 25.835638 | G43: =G31+G42 -> 79.344638 | H43: =H31+H42 -> 99.649111 | I43: =I31+I42 -> 96.869714 | J43: =J31+J42 -> 92.344509 | ... M43: =M31+M42 -> 107.15737
A44: 所得稅 | B44: US$B | C44: =Q!J28 -> 8.303 | D44: =Q!K28 -> 25.474 | E44: =Q!L28 -> 1.028 | F44: =F43*tax -> 4.1337021 | G44: =E44+F44 -> 5.1617021 | H44: =H43*tax -> 15.943858 | I44: =I43*tax -> 15.499154 | J44: =J43*tax -> 14.775121 | K44: =K43*tax -> 14.763118 | L44: =L43*tax -> 15.468377 | M44: =M43*tax -> 17.145179 | N44: 9M26 含 Q1 CAMT 稅務利益 −8.03
A45: 淨利（財報口徑） | B45: US$B | C45: =C43-C44 -> 62.36 | D45: =D43-D44 -> 60.458 | E45: =E43-E44 -> 52.481 | F45: =F43-F44 -> 21.701936 | G45: =G43-G44 -> 74.182936 | H45: =H43-H44 -> 83.705253 | I45: =I43-I44 -> 81.37056 | J45: =J43-J44 -> 77.569387 | ... M45: =M43-M44 -> 90.012187
A46: 檢查：實績淨利 − Q 頁 | B46: US$B | C46: =C45-Q!J29 -> 0 | D46: =D45-Q!K29 -> 0 | E46: =E45-Q!L29 -> 0
A47: 一次性項目稅後（法律依 8-K 排除後 EPS 隱含稅盾、遣散按 tax、稅務利益全額） | B47: US$B | E47: =-(ot_legal_q2+ot_legal_q3)*ot_legal_at-ot_sev_q2*(1-tax)+ot_tax_q1 -> -4.3758761 | F47: 0 | G47: =E47+F47 -> -4.3758761 | H47: 0 | I47: 0 | J47: 0 | K47: 0 | L47: 0 | M47: 0
A48: 特別股股利 | B48: US$B | E48: 0 | F48: =pref_2H -> 0 | G48: =E48+F48 -> 0 | H48: =pref_27 -> 0.8125 | I48: =pref_28 -> 0.8125 | J48: =pref_29 -> 0.609 | K48: 0 | L48: 0 | M48: 0
A49: 歸屬普通股淨利 | B49: US$B | E49: =E45-E48 -> 52.481 | F49: =F45-F48 -> 21.701936 | G49: =G45-G48 -> 74.182936 | H49: =H45-H48 -> 82.892753 | I49: =I45-I48 -> 80.55806 | J49: =J45-J48 -> 76.960387 | K49: =K45-K48 -> 77.50637 | L49: =L45-L48 -> 81.208978 | M49: =M45-M48 -> 90.012187
A50: 期末稀釋股數（十億股） | B50: 十億股 | E50: =sh_dil_q3+(sh_out-sh_basic_q3) -> 2.577241 | F50: =E50*(1+dil*0.25)-CF!F34/CF!F41 -> 2.5862613 | H50: =F50*(1+dil*1)-CF!H34/CF!H41+fwd_sh*fwd_on -> 2.662469 | I50: =H50*(1+dil*1)-CF!I34/CF!I41 -> 2.6997436 | J50: =I50*(1+dil*1)-CF!J34/CF!J41+conv_sh -> 2.75754 | K50: =J50*(1+dil*1)-CF!K34/CF!K41 -> 2.7961455 | L50: =K50*(1+dil*1)-CF!L34/CF!L41 -> 2.8352916 | M50: =L50*(1+dil*1)-CF!M34/CF!M41 -> 2.8749857 | N50: 9M26 期末＝Q3 稀釋加權＋(10-16 流通股 − Q3 基本加權)；之後 ×(1＋dil × 期間長度) − 回購 ÷ 回購均價；FY2027 遠期出售 40M（fwd_on）；2029 強制轉換特別股 +conv_sh
A51: 平均稀釋股數（十億股） | B51: 十億股 | C51: =Q!J31 -> 2.614 | D51: =Q!K31 -> 2.574 | E51: =Q!L31 -> 2.568 | F51: =E50*(1+dil*0.125) -> 2.5817512 | G51: =0.75*E51+0.25*F51 -> 2.5714378 | H51: =(F50+H50)/2 -> 2.6243652 | I51: =(H50+I50)/2 -> 2.6811063 | J51: =(I50+J50)/2 -> 2.7286418 | K51: =(J50+K50)/2 -> 2.7768428 | L51: =(K50+L50)/2 -> 2.8157186 | M51: =(L50+M50)/2 -> 2.8551386
A52: EPS（GAAP 稀釋，財報口徑，美元） | B52: US$ | C52: =C45/C51 -> 23.856159 | D52: =D45/D51 -> 23.487956 | E52: =E49/E51 -> 20.436526 | F52: =F49/F51 -> 8.4058975 | G52: =G49/G51 -> 28.848816 | H52: =H49/H51 -> 31.58583 | I52: =I49/I51 -> 30.046575 | J52: =J49/J51 -> 28.20465 | K52: =K49/K51 -> 27.911688 | L52: =L49/L51 -> 28.841298 | M52: =M49/M51 -> 31.526381
A53: EPS（排除一次性，美元） | B53: US$ | E53: =(E49-E47)/E51 -> 22.140528 | F53: =(F49-F47)/F51 -> 8.4058975 | G53: =(G49-G47)/G51 -> 30.55054 | H53: =(H49-H47)/H51 -> 31.58583 | I53: =(I49-I47)/I51 -> 30.046575 | J53: =(J49-J47)/J51 -> 28.20465 | K53: =(K49-K47)/K51 -> 27.911688 | L53: =(L49-L47)/L51 -> 28.841298 | M53: =(M49-M47)/M51 -> 31.526381 | N53: M5 擴大：排除 Q1 稅務利益、Q2 法律與遣散、Q3 法律
A54: EPS（評價口徑：排除一次性＋讀法 2 稅後影子效益，美元） | B54: US$ | F54: =(F49-F47+(internal_ai_reading=2)*F35*(1-tax))/F51 -> 9.7575669 | G54: =(G49-G47+(internal_ai_reading=2)*G35*(1-tax))/G51 -> 31.90763 | H54: =(H49-H47+(internal_ai_reading=2)*H35*(1-tax))/H51 -> 51.275204 | I54: =(I49-I47+(internal_ai_reading=2)*I35*(1-tax))/I51 -> 67.552674 | J54: =(J49-J47+(internal_ai_reading=2)*J35*(1-tax))/J51 -> 81.401038 | K54: =(K49-K47+(internal_ai_reading=2)*K35*(1-tax))/K51 -> 92.268925 | L54: =(L49-L47+(internal_ai_reading=2)*L35*(1-tax))/L51 -> 100.47097 | M54: =(M49-M47+(internal_ai_reading=2)*M35*(1-tax))/M51 -> 106.59014
A55: 股權報酬（已含在分部營業利益內） | B55: US$B | C55: =Q!J36 -> 16.69 | D55: =Q!K36 -> 20.427 | E55: =Q!L36 -> 21.053 | F55: =F16*sbc_r -> 8.5115611 | G55: =E55+F55 -> 29.564561 | H55: =H16*sbc_r -> 36.185819 | I55: =I16*sbc_r -> 43.690686 | J55: =J16*sbc_r -> 50.562063 | K55: =K16*sbc_r -> 55.997101 | L55: =L16*sbc_r -> 60.655341 | M55: =M16*sbc_r -> 65.708212
A57: 情境 B（近四季成長收斂；基準）
A58: 項目 | B58: 單位 | C58: FY2024A | D58: FY2025A | E58: 9M26A | F58: Q4 26E | G58: FY2026E | H58: FY2027E | I58: FY2028E | J58: FY2029E | K58: FY2030E | L58: FY2031E | M58: FY2032E | N58: 說明
A59: Advertising | B59: US$B | C59: =Seg!C32 -> 160.633 | D59: =Seg!D32 -> 196.175 | E59: =Seg!E32 -> 177.448 | F59: =Seg!F32 -> 74.105644 | G59: =Seg!G32 -> 251.55364 | H59: =Seg!H32 -> 308.13277 | I59: =Seg!I32 -> 362.40687 | J59: =Seg!J32 -> 408.91541 | ... M59: =Seg!M32 -> 517.26495
A60: Other revenue | B60: US$B | C60: =Seg!C35 -> 1.722 | D60: =Seg!D35 -> 2.584 | E60: =Seg!E35 -> 2.989 | F60: =Seg!F35 -> 1.3187619 | G60: =Seg!G35 -> 4.3077619 | H60: =Seg!H35 -> 6.557688 | I60: =Seg!I35 -> 9.1689412 | J60: =Seg!J35 -> 11.682135 | ... M60: =Seg!M35 -> 17.767067
A61: Family of Apps | B61: US$B | C61: =Seg!C36 -> 162.355 | D61: =Seg!D36 -> 198.759 | E61: =Seg!E36 -> 180.437 | F61: =Seg!F36 -> 75.424406 | G61: =Seg!G36 -> 255.86141 | H61: =Seg!H36 -> 314.69046 | I61: =Seg!I36 -> 371.57581 | J61: =Seg!J36 -> 420.59755 | ... M61: =Seg!M36 -> 535.03202
A62: Reality Labs | B62: US$B | C62: =Seg!C38 -> 2.146 | D62: =Seg!D38 -> 2.207 | E62: =Seg!E38 -> 1.276 | F62: =Seg!F38 -> 0.91246467 | G62: =Seg!G38 -> 2.1884647 | H62: =Seg!H38 -> 2.1427154 | I62: =Seg!I38 -> 2.1485655 | J62: =Seg!J38 -> 2.2052126 | ... M62: =Seg!M38 -> 2.5528092
A63: 合併營收 | B63: US$B | C63: =Seg!C39 -> 164.501 | D63: =Seg!D39 -> 200.966 | E63: =Seg!E39 -> 181.713 | F63: =Seg!F39 -> 76.336871 | G63: =Seg!G39 -> 258.04987 | H63: =Seg!H39 -> 316.83318 | I63: =Seg!I39 -> 373.72437 | J63: =Seg!J39 -> 422.80276 | ... M63: =Seg!M39 -> 537.58483
A64: 合併營收年增 | B64: % | D64: =D63/C63-1 -> 0.22167038 | G64: =G63/D63-1 -> 0.2840474 | H64: =H63/G63-1 -> 0.22779824 | I64: =I63/H63-1 -> 0.17956199 | J64: =J63/I63-1 -> 0.13132242 | K64: =K63/J63-1 -> 0.083228376 | L64: =L63/K63-1 -> 0.083350082 | M64: =M63/L63-1 -> 0.083478603
A65: 檢查：Advertising＋Other revenue－Family of Apps | B65: US$B | C65: =C59+C60-C61 -> 0 | D65: =D59+D60-D61 -> 0 | E65: =E59+E60-E61 -> 0 | F65: =F59+F60-F61 -> 0 | G65: =G59+G60-G61 -> 0 | H65: =H59+H60-H61 -> 0 | I65: =I59+I60-I61 -> 0 | J65: =J59+J60-J61 -> 0 | ... M65: =M59+M60-M61 -> 0
A66: 檢查：分部合計－合併營收 | B66: US$B | C66: =C61+C62-C63 -> 0 | D66: =D61+D62-D63 -> 0 | E66: =E61+E62-E63 -> 0 | F66: =F61+F62-F63 -> 0 | G66: =G61+G62-G63 -> 0 | H66: =H61+H62-H63 -> 0 | I66: =I61+I62-I63 -> 0 | J66: =J61+J62-J63 -> 0 | ... M66: =M61+M62-M63 -> 0
A67: 價格情境差額（相對 B 路徑） | B67: US$B | F67: =Seg!F32-Seg!F29 -> 0 | G67: =F67 -> 0 | H67: =Seg!H32-Seg!H29 -> 0 | I67: =Seg!I32-Seg!I29 -> 0 | J67: =Seg!J32-Seg!J29 -> 0 | K67: =Seg!K32-Seg!K29 -> 0 | L67: =Seg!L32-Seg!L29 -> 0 | M67: =Seg!M32-Seg!M29 -> 0
A68: Family of Apps EBITDA（不含一次性） | B68: US$B | F68: =m_foa*(F61-F67)+inc_m*F67-Thesis!F106-Thesis!F107 -> 40.798461 | H68: =m_foa*(H61-H67)+inc_m*H67-Thesis!H106-Thesis!H107 -> 163.01527 | I68: =m_foa*(I61-I67)+inc_m*I67-Thesis!I106-Thesis!I107 -> 185.62789 | J68: =m_foa*(J61-J67)+inc_m*J67-Thesis!J106-Thesis!J107 -> 204.78138 | K68: =m_foa*(K61-K67)+inc_m*K67-Thesis!K106-Thesis!K107 -> 218.1825 | L68: =m_foa*(L61-L67)+inc_m*L67-Thesis!L106-Thesis!L107 -> 235.07271 | M68: =m_foa*(M61-M67)+inc_m*M67-Thesis!M106-Thesis!M107 -> 255.55519
A69: Family of Apps 折舊（基礎 ×(1 − RL 占比)＋新增 AI＋新增非 AI） | B69: US$B | F69: =Thesis!F111*(1-rl_da_sh)+Thesis!F104+Seg!F44 -> 9.0553129 | H69: =Thesis!H111*(1-rl_da_sh)+Thesis!H104+Seg!H44 -> 52.289843 | I69: =Thesis!I111*(1-rl_da_sh)+Thesis!I104+Seg!I44 -> 80.947798 | J69: =Thesis!J111*(1-rl_da_sh)+Thesis!J104+Seg!J44 -> 109.39521 | K69: =Thesis!K111*(1-rl_da_sh)+Thesis!K104+Seg!K44 -> 132.89282 | L69: =Thesis!L111*(1-rl_da_sh)+Thesis!L104+Seg!L44 -> 150.937 | M69: =Thesis!M111*(1-rl_da_sh)+Thesis!M104+Seg!M44 -> 169.5483
A70: Family of Apps 營業利益 | B70: US$B | C70: =Q!J14 -> 87.109 | D70: =Q!K14 -> 102.469 | E70: =Q!L14 -> 67.411 | F70: =F68-F69 -> 31.743148 | G70: =E70+F70 -> 99.154148 | H70: =H68-H69 -> 110.72542 | I70: =I68-I69 -> 104.68009 | J70: =J68-J69 -> 95.386165 | K70: =K68-K69 -> 85.289674 | L70: =L68-L69 -> 84.135703 | M70: =M68-M69 -> 86.006897 | N70: 9M26 實績含一次性法律 12.29 與遣散 1.18（M5）
A71: Reality Labs 營業損益 | B71: US$B | C71: =Q!J15 -> -17.729 | D71: =Q!K15 -> -19.193 | E71: =Q!L15 -> -12.776 | F71: =-(rl_loss26+Q!L15) -> -5.724 | G71: =E71+F71 -> -18.5 | H71: =-rl_loss27 -> -15 | I71: =-(rl_loss27+(rl_loss32-rl_loss27)*(2028-2027)/5) -> -13 | J71: =-(rl_loss27+(rl_loss32-rl_loss27)*(2029-2027)/5) -> -11 | K71: =-(rl_loss27+(rl_loss32-rl_loss27)*(2030-2027)/5) -> -9 | L71: =-(rl_loss27+(rl_loss32-rl_loss27)*(2031-2027)/5) -> -7 | M71: =-(rl_loss27+(rl_loss32-rl_loss27)*(2032-2027)/5) -> -5 | N71: Q4 26＝2026 指引中點 − 9M 實績；FY2027 約 −15（法說）；之後線性到 FY2032 rl_loss32
A72: Reality Labs 折舊（基礎 × RL 占比） | B72: US$B | F72: =Thesis!F111*rl_da_sh -> 0.3577 | H72: =Thesis!H111*rl_da_sh -> 1.4308 | I72: =Thesis!I111*rl_da_sh -> 1.4308 | J72: =Thesis!J111*rl_da_sh -> 1.3761517 | K72: =Thesis!K111*rl_da_sh -> 1.2308073 | L72: =Thesis!L111*rl_da_sh -> 0.94389794 | M72: =Thesis!M111*rl_da_sh -> 0.74768472
A73: Reality Labs EBITDA | B73: US$B | F73: =F71+F72 -> -5.3663 | H73: =H71+H72 -> -13.5692 | I73: =I71+I72 -> -11.5692 | J73: =J71+J72 -> -9.6238483 | K73: =K71+K72 -> -7.7691927 | L73: =L71+L72 -> -6.0561021 | M73: =M71+M72 -> -4.2523153
A74: 分部營業利益合計 | B74: US$B | C74: =C70+C71 -> 69.38 | D74: =D70+D71 -> 83.276 | E74: =E70+E71 -> 54.635 | F74: =F70+F71 -> 26.019148 | G74: =G70+G71 -> 80.654148 | H74: =H70+H71 -> 95.725422 | I74: =I70+I71 -> 91.680088 | J74: =J70+J71 -> 84.386165 | ... M74: =M70+M71 -> 81.006897
A75: 合併 EBITDA（分部 EBITDA 合計） | B75: US$B | F75: =F68+F73 -> 35.432161 | H75: =H68+H73 -> 149.44607 | I75: =I68+I73 -> 174.05869 | J75: =J68+J73 -> 195.15753 | K75: =K68+K73 -> 210.4133 | L75: =L68+L73 -> 229.01661 | M75: =M68+M73 -> 251.30288
A76: 折舊與攤銷合計（基礎＋新增 AI＋新增非 AI） | B76: US$B | C76: =Q!J35 -> 15.498 | D76: =Q!K35 -> 18.616 | E76: =Q!L35 -> 19.509 | F76: =Thesis!F111+Thesis!F104+Seg!F44 -> 9.4130129 | G76: =E76+F76 -> 28.922013 | H76: =Thesis!H111+Thesis!H104+Seg!H44 -> 53.720643 | I76: =Thesis!I111+Thesis!I104+Seg!I44 -> 82.378598 | J76: =Thesis!J111+Thesis!J104+Seg!J44 -> 110.77137 | K76: =Thesis!K111+Thesis!K104+Seg!K44 -> 134.12363 | L76: =Thesis!L111+Thesis!L104+Seg!L44 -> 151.8809 | M76: =Thesis!M111+Thesis!M104+Seg!M44 -> 170.29598
A77: 其中：新增 AI 折舊 | B77: US$B | F77: =Thesis!F104 -> 2.2208445 | G77: =F77 -> 2.2208445 | H77: =Thesis!H104 -> 24.482462 | I77: =Thesis!I104 -> 51.816193 | J77: =Thesis!J104 -> 79.757952 | K77: =Thesis!K104 -> 104.29071 | L77: =Thesis!L104 -> 125.91602 | M77: =Thesis!M104 -> 146.22928
A78: 合併營業利益（財報口徑） | B78: US$B | C78: =Q!J16 -> 69.38 | D78: =Q!K16 -> 83.276 | E78: =Q!L16 -> 54.635 | F78: =F75-F76 -> 26.019148 | G78: =E78+F78 -> 80.654148 | H78: =H75-H76 -> 95.725422 | I78: =I75-I76 -> 91.680088 | J78: =J75-J76 -> 84.386165 | K78: =K75-K76 -> 76.289674 | L78: =L75-L76 -> 77.135703 | M78: =M75-M76 -> 81.006897 | N78: 預測期＝合併 EBITDA − 折舊合計（與分部合計獨立計算，下一列核對）
A79: 檢查：分部營業利益合計－合併營業利益 | B79: US$B | C79: =C74-C78 -> 0 | D79: =D74-D78 -> 0 | E79: =E74-E78 -> 0 | F79: =F74-F78 -> 0 | G79: =G74-G78 -> 0 | H79: =H74-H78 -> 0 | I79: =I74-I78 -> 0 | J79: =J74-J78 -> 0 | ... M79: =M74-M78 -> 0
A80: 一次性項目（營業利益內；負值＝費用） | B80: US$B | E80: =-ot_oi_9m -> -13.47 | F80: 0 | G80: =E80+F80 -> -13.47 | H80: 0 | I80: 0 | J80: 0 | K80: 0 | L80: 0 | M80: 0 | N80: Q2 法律 2.40＋遣散 1.18、Q3 法律 9.89（新聞稿）；預測期 0
A81: 營業利益（排除一次性） | B81: US$B | E81: =E78-E80 -> 68.105 | F81: =F78-F80 -> 26.019148 | G81: =G78-G80 -> 94.124148 | H81: =H78-H80 -> 95.725422 | I81: =I78-I80 -> 91.680088 | J81: =J78-J80 -> 84.386165 | K81: =K78-K80 -> 76.289674 | L81: =L78-L80 -> 77.135703 | M81: =M78-M80 -> 81.006897
A82: 自用 AI 影子效益（讀法 2；非財報營收） | B82: US$B | F82: =Thesis!F113 -> 4.1543738 | G82: =F82 -> 4.1543738 | H82: =Thesis!H113 -> 57.650598 | I82: =Thesis!I113 -> 107.89641 | J82: =Thesis!J113 -> 153.77219 | K82: =Thesis!K113 -> 188.37941 | L82: =Thesis!L113 -> 212.19606 | M82: =Thesis!M113 -> 225.45864
A83: 營業利益（評價口徑：排除一次性＋讀法 2 影子效益） | B83: US$B | E83: =E81 -> 68.105 | F83: =F81+(internal_ai_reading=2)*F82 -> 30.173522 | G83: =G81+(internal_ai_reading=2)*G82 -> 98.278522 | H83: =H81+(internal_ai_reading=2)*H82 -> 153.37602 | I83: =I81+(internal_ai_reading=2)*I82 -> 199.5765 | J83: =J81+(internal_ai_reading=2)*J82 -> 238.15836 | K83: =K81+(internal_ai_reading=2)*K82 -> 264.66909 | L83: =L81+(internal_ai_reading=2)*L82 -> 289.33176 | M83: =M81+(internal_ai_reading=2)*M82 -> 306.46554
A84: 營業利益率（財報口徑） | B84: % | C84: =C78/C63 -> 0.42176035 | D84: =D78/D63 -> 0.41437855 | E84: =E78/E63 -> 0.30066644 | F84: =F78/F63 -> 0.3408464 | G84: =G78/G63 -> 0.31255256 | H84: =H78/H63 -> 0.30213194 | I84: =I78/I63 -> 0.24531472 | J84: =J78/J63 -> 0.19958755 | ... M84: =M78/M63 -> 0.15068673
A85: 營業利益率（排除一次性） | B85: % | E85: =E81/E63 -> 0.37479432 | F85: =F81/F63 -> 0.3408464 | G85: =G81/G63 -> 0.36475177 | H85: =H81/H63 -> 0.30213194 | I85: =I81/I63 -> 0.24531472 | J85: =J81/J63 -> 0.19958755 | K85: =K81/K63 -> 0.16657427 | L85: =L81/L63 -> 0.15546362 | M85: =M81/M63 -> 0.15068673
A86: Family of Apps 營業利益率 | B86: % | C86: =C70/C61 -> 0.53653414 | D86: =D70/D61 -> 0.51554395 | E86: =E70/E61 -> 0.37359854 | F86: =F70/F61 -> 0.42086043 | G86: =G70/G61 -> 0.38753069 | H86: =H70/H61 -> 0.35185503 | I86: =I70/I61 -> 0.28171933 | J86: =J70/J61 -> 0.22678726 | ... M86: =M70/M61 -> 0.16075094
A87: 利息收入（期初現金 × r_cash） | B87: US$B | F87: =r_cash*CF!F63*0.25 -> 0.82449 | G87: =F87 -> 0.82449 | H87: =r_cash*CF!H63*1 -> 3.1597857 | I87: =r_cash*CF!I63*1 -> 2.2522975 | J87: =r_cash*CF!J63*1 -> 1.6 | K87: =r_cash*CF!K63*1 -> 2.5220363 | L87: =r_cash*CF!L63*1 -> 5.4684424 | M87: =r_cash*CF!M63*1 -> 9.5307347
A88: 利息費用（期初債務 × r_debt） | B88: US$B | F88: =r_debt*CF!F70*0.25 -> 1.008 | G88: =F88 -> 1.008 | H88: =r_debt*CF!H70*1 -> 4.032 | I88: =r_debt*CF!I70*1 -> 3.900144 | J88: =r_debt*CF!J70*1 -> 4.4590615 | K88: =r_debt*CF!K70*1 -> 4.4590615 | L88: =r_debt*CF!L70*1 -> 4.4590615 | M88: =r_debt*CF!M70*1 -> 4.4590615
A89: 業外收益合計 | B89: US$B | C89: =Q!J25 -> 1.283 | D89: =Q!K25 -> 2.656 | E89: =Q!L25 -> -1.126 | F89: =F87-F88 -> -0.18351 | G89: =E89+F89 -> -1.30951 | H89: =H87-H88 -> -0.87221434 | I89: =I87-I88 -> -1.6478465 | J89: =J87-J88 -> -2.8590615 | K89: =K87-K88 -> -1.9370252 | L89: =L87-L88 -> 1.0093809 | M89: =M87-M88 -> 5.0716732
A90: 稅前利益 | B90: US$B | C90: =C78+C89 -> 70.663 | D90: =D78+D89 -> 85.932 | E90: =E78+E89 -> 53.509 | F90: =F78+F89 -> 25.835638 | G90: =G78+G89 -> 79.344638 | H90: =H78+H89 -> 94.853208 | I90: =I78+I89 -> 90.032242 | J90: =J78+J89 -> 81.527103 | ... M90: =M78+M89 -> 86.07857
A91: 所得稅 | B91: US$B | C91: =Q!J28 -> 8.303 | D91: =Q!K28 -> 25.474 | E91: =Q!L28 -> 1.028 | F91: =F90*tax -> 4.1337021 | G91: =E91+F91 -> 5.1617021 | H91: =H90*tax -> 15.176513 | I91: =I90*tax -> 14.405159 | J91: =J90*tax -> 13.044337 | K91: =K90*tax -> 11.896424 | L91: =L90*tax -> 12.503213 | M91: =M90*tax -> 13.772571 | N91: 9M26 含 Q1 CAMT 稅務利益 −8.03
A92: 淨利（財報口徑） | B92: US$B | C92: =C90-C91 -> 62.36 | D92: =D90-D91 -> 60.458 | E92: =E90-E91 -> 52.481 | F92: =F90-F91 -> 21.701936 | G92: =G90-G91 -> 74.182936 | H92: =H90-H91 -> 79.676695 | I92: =I90-I91 -> 75.627083 | J92: =J90-J91 -> 68.482767 | ... M92: =M90-M91 -> 72.305999
A93: 檢查：實績淨利 − Q 頁 | B93: US$B | C93: =C92-Q!J29 -> 0 | D93: =D92-Q!K29 -> 0 | E93: =E92-Q!L29 -> 0
A94: 一次性項目稅後（法律依 8-K 排除後 EPS 隱含稅盾、遣散按 tax、稅務利益全額） | B94: US$B | E94: =-(ot_legal_q2+ot_legal_q3)*ot_legal_at-ot_sev_q2*(1-tax)+ot_tax_q1 -> -4.3758761 | F94: 0 | G94: =E94+F94 -> -4.3758761 | H94: 0 | I94: 0 | J94: 0 | K94: 0 | L94: 0 | M94: 0
A95: 特別股股利 | B95: US$B | E95: 0 | F95: =pref_2H -> 0 | G95: =E95+F95 -> 0 | H95: =pref_27 -> 0.8125 | I95: =pref_28 -> 0.8125 | J95: =pref_29 -> 0.609 | K95: 0 | L95: 0 | M95: 0
A96: 歸屬普通股淨利 | B96: US$B | E96: =E92-E95 -> 52.481 | F96: =F92-F95 -> 21.701936 | G96: =G92-G95 -> 74.182936 | H96: =H92-H95 -> 78.864195 | I96: =I92-I95 -> 74.814583 | J96: =J92-J95 -> 67.873767 | K96: =K92-K95 -> 62.456225 | L96: =L92-L95 -> 65.641871 | M96: =M92-M95 -> 72.305999
A97: 期末稀釋股數（十億股） | B97: 十億股 | E97: =sh_dil_q3+(sh_out-sh_basic_q3) -> 2.577241 | F97: =E97*(1+dil*0.25)-CF!F66/CF!F73 -> 2.5862613 | H97: =F97*(1+dil*1)-CF!H66/CF!H73+fwd_sh*fwd_on -> 2.662469 | I97: =H97*(1+dil*1)-CF!I66/CF!I73 -> 2.6997436 | J97: =I97*(1+dil*1)-CF!J66/CF!J73+conv_sh -> 2.75754 | K97: =J97*(1+dil*1)-CF!K66/CF!K73 -> 2.7961455 | L97: =K97*(1+dil*1)-CF!L66/CF!L73 -> 2.8352916 | M97: =L97*(1+dil*1)-CF!M66/CF!M73 -> 2.8749857 | N97: 9M26 期末＝Q3 稀釋加權＋(10-16 流通股 − Q3 基本加權)；之後 ×(1＋dil × 期間長度) − 回購 ÷ 回購均價；FY2027 遠期出售 40M（fwd_on）；2029 強制轉換特別股 +conv_sh
A98: 平均稀釋股數（十億股） | B98: 十億股 | C98: =Q!J31 -> 2.614 | D98: =Q!K31 -> 2.574 | E98: =Q!L31 -> 2.568 | F98: =E97*(1+dil*0.125) -> 2.5817512 | G98: =0.75*E98+0.25*F98 -> 2.5714378 | H98: =(F97+H97)/2 -> 2.6243652 | I98: =(H97+I97)/2 -> 2.6811063 | J98: =(I97+J97)/2 -> 2.7286418 | K98: =(J97+K97)/2 -> 2.7768428 | L98: =(K97+L97)/2 -> 2.8157186 | M98: =(L97+M97)/2 -> 2.8551386
A99: EPS（GAAP 稀釋，財報口徑，美元） | B99: US$ | C99: =C92/C98 -> 23.856159 | D99: =D92/D98 -> 23.487956 | E99: =E96/E98 -> 20.436526 | F99: =F96/F98 -> 8.4058975 | G99: =G96/G98 -> 28.848816 | H99: =H96/H98 -> 30.05077 | I99: =I96/I98 -> 27.90437 | J99: =J96/J98 -> 24.874561 | K99: =K96/K98 -> 22.491812 | L99: =L96/L98 -> 23.312653 | M99: =M96/M98 -> 25.324865
A100: EPS（排除一次性，美元） | B100: US$ | E100: =(E96-E94)/E98 -> 22.140528 | F100: =(F96-F94)/F98 -> 8.4058975 | G100: =(G96-G94)/G98 -> 30.55054 | H100: =(H96-H94)/H98 -> 30.05077 | I100: =(I96-I94)/I98 -> 27.90437 | J100: =(J96-J94)/J98 -> 24.874561 | K100: =(K96-K94)/K98 -> 22.491812 | L100: =(L96-L94)/L98 -> 23.312653 | M100: =(M96-M94)/M98 -> 25.324865 | N100: M5 擴大：排除 Q1 稅務利益、Q2 法律與遣散、Q3 法律
A101: EPS（評價口徑：排除一次性＋讀法 2 稅後影子效益，美元） | B101: US$ | F101: =(F96-F94+(internal_ai_reading=2)*F82*(1-tax))/F98 -> 9.7575669 | G101: =(G96-G94+(internal_ai_reading=2)*G82*(1-tax))/G98 -> 31.90763 | H101: =(H96-H94+(internal_ai_reading=2)*H82*(1-tax))/H98 -> 48.503424 | I101: =(I96-I94+(internal_ai_reading=2)*I82*(1-tax))/I98 -> 61.708693 | J101: =(J96-J94+(internal_ai_reading=2)*J82*(1-tax))/J98 -> 72.212633 | K101: =(K96-K94+(internal_ai_reading=2)*K82*(1-tax))/K98 -> 79.476928 | L101: =(L96-L94+(internal_ai_reading=2)*L82*(1-tax))/L98 -> 86.616099 | M101: =(M96-M94+(internal_ai_reading=2)*M82*(1-tax))/M98 -> 91.656235
A102: 股權報酬（已含在分部營業利益內） | B102: US$B | C102: =Q!J36 -> 16.69 | D102: =Q!K36 -> 20.427 | E102: =Q!L36 -> 21.053 | F102: =F63*sbc_r -> 8.5115611 | G102: =E102+F102 -> 29.564561 | H102: =H63*sbc_r -> 35.326899 | I102: =I63*sbc_r -> 41.670267 | J102: =J63*sbc_r -> 47.142508 | K102: =K63*sbc_r -> 51.066102 | L102: =L63*sbc_r -> 55.322466 | M102: =M63*sbc_r -> 59.940708
A104: 情境 C（AI 價格提升消退）
...

Sheet CF
A1: CF — 現金流（US$B）。營運現金＝淨利＋折舊＋股權報酬＋營運資金 − 協議付款；資本支出（含融資租賃本金，公司口徑）＝AI（Thesis）＋非 AI（Seg）；自由現金流＝營運現金 − 資本支出。融資順序：現金 → 減少回購 → 新債（最低現金 40）
A2: 2026-10-29 強制轉換特別股 12.5（Q4 26 流入）；Class A 遠期出售 24.9 推定 FY2027 交割（fwd_on）；回購 2026 暫停、預設 FY2027 起 0；多州檢察長協議 12.7 分 10 年（10-Q 未載各年金額；FY2027 起每年 1.27 等額，第一年 ag_y1 前高後低只進 Sens）
A4: 收支關卡（地圖讀這兩列；模型期間 FY2026–FY2030，FY2026 含 9M 實績）
A5: 項目 | B5: 情境 A | C5: 情境 B | D5: 情境 C | E5: 說明
A6: 收支關卡：自由現金流扣股利（五年合計） | B6: =SUM(G27:K27) -> -19.56229 | C6: =SUM(G59:K59) -> 14.97977 | D6: =SUM(G91:K91) -> 49.007632 | E6: FY2026–FY2030 自由現金流（公司定義，已扣融資租賃本金與協議付款）− 普通股與特別股股利；FY2026 含 9M 實績。負值＝入不敷出
A7: 其中：五年新增舉債 | B7: =SUM(G35:K35) -> 56.40191 | C7: =SUM(G67:K67) -> 11.644114 | D7: =SUM(G99:K99) -> 0
A8: 其中：五年回購合計 | B8: =SUM(G34:K34) -> 0 | C8: =SUM(G66:K66) -> 0 | D8: =SUM(G98:K98) -> 0
A9: 是否需要舉債或停止回購 | B9: =IF(B7>0.001,"需要舉債"&IF(B8<4*bb_t-0.001,"且減少回購",""),IF(B8<4*bb_t-0.001,"不需舉債，但須減少回購","不需舉債，回購照目標")) -> 需要舉債 | C9: =IF(C7>0.001,"需要舉債"&IF(C8<4*bb_t-0.001,"且減少回購",""),IF(C8<4*bb_t-0.001,"不需舉債，但須減少回購","不需舉債，回購照目標")) -> 需要舉債 | D9: =IF(D7>0.001,"需要舉債"&IF(D8<4*bb_t-0.001,"且減少回購",""),IF(D8<4*bb_t-0.001,"不需舉債，但須減少回購","不需舉債，回購照目標")) -> 不需舉債，回購照目標 | E9: 依現金瀑布：現金 → 減少回購 → 新債（最低現金 40）；強制轉換特別股與遠期出售不計入關卡（融資）
A10: 檢查：收支關卡 − 首年起五年逐欄加總（FY2026＋…＋FY2030） | B10: =B6-(G27+H27+I27+J27+K27) -> 0 | C10: =C6-(G59+H59+I59+J59+K59) -> 0 | D10: =D6-(G91+H91+I91+J91+K91) -> 0
A11: 情境 A（AI 提高每則廣告價格）
A12: 項目 | B12: 單位 | C12: FY2024A | D12: FY2025A | E12: 9M26A | F12: Q4 26E | G12: FY2026E | H12: FY2027E | I12: FY2028E | J12: FY2029E | K12: FY2030E | L12: FY2031E | M12: FY2032E | N12: 說明
A13: 淨利 | B13: US$B | C13: =PL!C45 -> 62.36 | D13: =PL!D45 -> 60.458 | E13: =PL!E45 -> 52.481 | F13: =PL!F45 -> 21.701936 | G13: =PL!G45 -> 74.182936 | H13: =PL!H45 -> 83.705253 | I13: =PL!I45 -> 81.37056 | J13: =PL!J45 -> 77.569387 | ... M13: =PL!M45 -> 90.012187
A14: 折舊與攤銷 | B14: US$B | C14: =PL!C29 -> 15.498 | D14: =PL!D29 -> 18.616 | E14: =PL!E29 -> 19.509 | F14: =PL!F29 -> 9.4130129 | G14: =PL!G29 -> 28.922013 | H14: =PL!H29 -> 54.791119 | I14: =PL!I29 -> 87.815916 | J14: =PL!J29 -> 120.57563 | ... M14: =PL!M29 -> 187.28516
A15: 股權報酬（非現金） | B15: US$B | C15: =PL!C55 -> 16.69 | D15: =PL!D55 -> 20.427 | E15: =PL!E55 -> 21.053 | F15: =PL!F55 -> 8.5115611 | G15: =PL!G55 -> 29.564561 | H15: =PL!H55 -> 36.185819 | I15: =PL!I55 -> 43.690686 | J15: =PL!J55 -> 50.562063 | ... M15: =PL!M55 -> 65.708212
A16: 營運資金變動（流入＋） | B16: US$B | F16: 0 | G16: =F16 -> 0 | H16: =wc_k*(PL!H16-PL!G16) -> 0 | I16: =wc_k*(PL!I16-PL!H16) -> 0 | J16: =wc_k*(PL!J16-PL!I16) -> 0 | K16: =wc_k*(PL!K16-PL!J16) -> 0 | L16: =wc_k*(PL!L16-PL!K16) -> 0 | M16: =wc_k*(PL!M16-PL!L16) -> 0
A17: 多州檢察長協議付款（費用已於 2026Q2–Q3 認列 11.89） | B17: US$B | F17: 0 | G17: =F17 -> 0 | H17: =-ag_y1 -> -1.27 | I17: =-ag_rest -> -1.27 | J17: =-ag_rest -> -1.27 | K17: =-ag_rest -> -1.27 | L17: =-ag_rest -> -1.27 | M17: =-ag_rest -> -1.27 | N17: chat 端審查第 3 條：留在現金流與 DCF；FY2027＝ag_y1（基準等額 1.27），FY2028 起 ag_rest
A18: 其他非現金調整（實績差額：應計法律費用、遞延稅、營運資金等） | B18: US$B | C18: =Q!J37-C13-C14-C15 -> -3.22 | D18: =Q!K37-D13-D14-D15 -> 16.299 | E18: =Q!L37-E13-E14-E15 -> 3.831 | F18: 0 | G18: =E18+F18 -> 3.831 | H18: 0 | I18: 0 | J18: 0 | K18: 0 | L18: 0 | M18: 0
A19: 營運現金流 | B19: US$B | C19: =N(C13)+N(C14)+N(C15)+N(C16)+N(C17)+N(C18) -> 91.328 | D19: =N(D13)+N(D14)+N(D15)+N(D16)+N(D17)+N(D18) -> 115.8 | E19: =N(E13)+N(E14)+N(E15)+N(E16)+N(E17)+N(E18) -> 96.874 | F19: =N(F13)+N(F14)+N(F15)+N(F16)+N(F17)+N(F18) -> 39.62651 | G19: =N(G13)+N(G14)+N(G15)+N(G16)+N(G17)+N(G18) -> 136.50051 | H19: =N(H13)+N(H14)+N(H15)+N(H16)+N(H17)+N(H18) -> 173.41219 | I19: =N(I13)+N(I14)+N(I15)+N(I16)+N(I17)+N(I18) -> 211.60716 | J19: =N(J13)+N(J14)+N(J15)+N(J16)+N(J17)+N(J18) -> 247.43708 | ... M19: =N(M13)+N(M14)+N(M15)+N(M16)+N(M17)+N(M18) -> 341.73556
A20: 資本支出：AI（Thesis） | B20: US$B | F20: =Thesis!F50 -> 51.122525 | G20: =F20 -> 51.122525 | H20: =Thesis!H50 -> 223.5803 | I20: =Thesis!I50 -> 236.67056 | J20: =Thesis!J50 -> 202.625 | K20: =Thesis!K50 -> 164.75534 | L20: =Thesis!L50 -> 153.04837 | M20: =Thesis!M50 -> 148.55891
A21: 資本支出：非 AI（Seg） | B21: US$B | F21: =Seg!F22 -> 3.0534748 | G21: =F21 -> 3.0534748 | H21: =Seg!H22 -> 12.98146 | I21: =Seg!I22 -> 15.673789 | J21: =Seg!J22 -> 18.138857 | K21: =Seg!K22 -> 20.088646 | L21: =Seg!L22 -> 21.759763 | M21: =Seg!M22 -> 23.572453
A22: 資本支出合計（含融資租賃本金） | B22: US$B | C22: =Q!J40 -> 39.225 | D22: =Q!K40 -> 72.215 | E22: =Q!L40 -> 85.824 | F22: =F20+F21 -> 54.176 | G22: =E22+F22 -> 140 | H22: =H20+H21 -> 236.56176 | I22: =I20+I21 -> 252.34435 | J22: =J20+J21 -> 220.76386 | K22: =K20+K21 -> 184.84398 | L22: =L20+L21 -> 174.80813 | M22: =M20+M21 -> 172.13137
A23: 自由現金流（營運現金 − 資本支出；公司定義） | B23: US$B | C23: =C19-C22 -> 52.103 | D23: =D19-D22 -> 43.585 | E23: =E19-E22 -> 11.05 | F23: =F19-F22 -> -14.54949 | G23: =G19-G22 -> -3.4994902 | H23: =H19-H22 -> -63.149568 | I23: =I19-I22 -> -40.737184 | J23: =J19-J22 -> 26.673223 | ... M23: =M19-M22 -> 169.60419
A24: 檢查：實績自由現金流 − Q 頁 | B24: US$B | C24: =C23-Q!J41 -> 0 | D24: =D23-Q!K41 -> 0 | E24: =E23-Q!L41 -> 0
A25: 普通股股利 | B25: US$B | C25: =Q!J44 -> 5.072 | D25: =Q!K44 -> 5.324 | E25: =Q!L44 -> 4.06 | F25: =dps/4*sh_out -> 1.3632433 | G25: =E25+F25 -> 5.4232433 | H25: =dps*(1+dps_g)^(2027-2026)*PL!F50 -> 5.7928633 | I25: =dps*(1+dps_g)^(2028-2026)*PL!H50 -> 6.2617357 | J25: =dps*(1+dps_g)^(2029-2026)*PL!I50 -> 6.66687 | K25: =dps*(1+dps_g)^(2030-2026)*PL!J50 -> 7.1500749 | L25: =dps*(1+dps_g)^(2031-2026)*PL!K50 -> 7.6126847 | M25: =dps*(1+dps_g)^(2032-2026)*PL!L50 -> 8.1052254 | N25: Q4 26＝每股年股利 ÷ 4 × 流通股；之後每股 +5%／年 × 期初稀釋股數
A26: 特別股股利 | B26: US$B | E26: =PL!E48 -> 0 | F26: =PL!F48 -> 0 | G26: =PL!G48 -> 0 | H26: =PL!H48 -> 0.8125 | I26: =PL!I48 -> 0.8125 | J26: =PL!J48 -> 0.609 | K26: =PL!K48 -> 0 | L26: =PL!L48 -> 0 | M26: =PL!M48 -> 0
A27: 自由現金流扣股利 | B27: US$B | C27: =C23-C25-N(C26) -> 47.031 | D27: =D23-D25-N(D26) -> 38.261 | E27: =E23-E25-N(E26) -> 6.99 | F27: =F23-F25-N(F26) -> -15.912734 | G27: =G23-G25-N(G26) -> -8.9227335 | H27: =H23-H25-N(H26) -> -69.754932 | I27: =I23-I25-N(I26) -> -47.81142 | J27: =J23-J25-N(J26) -> 19.397353 | ... M27: =M23-M25-N(M26) -> 161.49897
A28: 債務到期償還 | B28: US$B | E28: 0 | F28: 0 | G28: =E28+F28 -> 0 | H28: =mat_27 -> 2.747 | I28: 0 | J28: 0 | K28: 0 | L28: 0 | M28: 0 | N28: 9M26 無償還；其他年度到期即再融資（不建模）
A29: 已發行新債 | B29: US$B | E29: 24.91 | F29: 0 | G29: =E29+F29 -> 24.91 | H29: 0 | I29: 0 | J29: 0 | K29: 0 | L29: 0 | M29: 0 | N29: 9M26：發債淨額 24.910（新聞稿）
A30: 股權發行（Q4 26 強制轉換特別股；FY2027 遠期出售） | B30: US$B | E30: 0 | F30: =mcps -> 12.458375 | G30: =E30+F30 -> 12.458375 | H30: =fwd_cash*fwd_on -> 24.9168 | I30: 0 | J30: 0 | K30: 0 | L30: 0 | M30: 0
A31: 期初現金（現金＋有價證券） | B31: US$B | E31: =cash_ye25 -> 81.592 | F31: =E36 -> 82.449 | H31: =F36 -> 78.994641 | I31: =H36 -> 40 | J31: =I36 -> 40 | K31: =J36 -> 59.397353 | L31: =K36 -> 146.9268 | M31: =L36 -> 272.54448
A32: 其他（9M26 實績差額：投資活動其他、代扣稅、匯率；預測期 0） | B32: US$B | E32: =cash_0-(E31+E23-E25-E26-E28+E29+E30) -> -31.043 | F32: 0 | H32: 0 | I32: 0 | J32: 0 | K32: 0 | L32: 0 | M32: 0
A33: 回購前現金 | B33: US$B | E33: =E31+E23-E25-E26-E28+E29+E30+E32 -> 82.449 | F33: =F31+F23-F25-F26-F28+F29+F30+F32 -> 78.994641 | H33: =H31+H23-H25-H26-H28+H29+H30+H32 -> 31.40951 | I33: =I31+I23-I25-I26-I28+I29+I30+I32 -> -7.8114201 | J33: =J31+J23-J25-J26-J28+J29+J30+J32 -> 59.397353 | K33: =K31+K23-K25-K26-K28+K29+K30+K32 -> 146.9268 | L33: =L31+L23-L25-L26-L28+L29+L30+L32 -> 272.54448 | M33: =M31+M23-M25-M26-M28+M29+M30+M32 -> 434.04345
A34: 回購 | B34: US$B | E34: =Q!L43 -> 0 | F34: 0 | G34: =E34+F34 -> 0 | H34: =MAX(0,MIN(bb_t,H33-min_cash)) -> 0 | I34: =MAX(0,MIN(bb_t,I33-min_cash)) -> 0 | J34: =MAX(0,MIN(bb_t,J33-min_cash)) -> 0 | K34: =MAX(0,MIN(bb_t,K33-min_cash)) -> 0 | L34: =MAX(0,MIN(bb_t,L33-min_cash)) -> 0 | M34: =MAX(0,MIN(bb_t,M33-min_cash)) -> 0 | N34: Q4 26＝0（暫停）；之後＝MIN(回購目標, 回購前現金 − 最低現金)
A35: 新增舉債（現金低於最低現金時） | B35: US$B | E35: 0 | F35: =MAX(0,min_cash-(F33-F34)) -> 0 | G35: =E35+F35 -> 0 | H35: =MAX(0,min_cash-(H33-H34)) -> 8.5904903 | I35: =MAX(0,min_cash-(I33-I34)) -> 47.81142 | J35: =MAX(0,min_cash-(J33-J34)) -> 0 | K35: =MAX(0,min_cash-(K33-K34)) -> 0 | L35: =MAX(0,min_cash-(L33-L34)) -> 0 | M35: =MAX(0,min_cash-(M33-M34)) -> 0
A36: 期末現金（現金＋有價證券） | B36: US$B | E36: =E33-E34+E35 -> 82.449 | F36: =F33-F34+F35 -> 78.994641 | H36: =H33-H34+H35 -> 40 | I36: =I33-I34+I35 -> 40 | J36: =J33-J34+J35 -> 59.397353 | K36: =K33-K34+K35 -> 146.9268 | L36: =L33-L34+L35 -> 272.54448 | M36: =M33-M34+M35 -> 434.04345
A37: 檢查：9M26 期末現金 − 2026-09-30（應為 0） | B37: US$B | E37: =E36-cash_0 -> 0
A38: 期初債務 | B38: US$B | E38: =debt_ye25 -> 58.744 | F38: =E39 -> 84 | H38: =F39 -> 84 | I38: =H39 -> 89.84349 | J38: =I39 -> 137.65491 | K38: =J39 -> 137.65491 | L38: =K39 -> 137.65491 | M38: =L39 -> 137.65491
A39: 期末債務 | B39: US$B | E39: =debt_0 -> 84 | F39: =F38-F28+F29+F35 -> 84 | H39: =H38-H28+H29+H35 -> 89.84349 | I39: =I38-I28+I29+I35 -> 137.65491 | J39: =J38-J28+J29+J35 -> 137.65491 | K39: =K38-K28+K29+K35 -> 137.65491 | L39: =L38-L28+L29+L35 -> 137.65491 | M39: =M38-M28+M29+M35 -> 137.65491 | N39: 9M26＝票據面額 84.0（10-Q）
A40: 淨現金（現金 − 債務） | B40: US$B | E40: =E36-E39 -> -1.551 | F40: =F36-F39 -> -5.0053585 | H40: =H36-H39 -> -49.84349 | I40: =I36-I39 -> -97.65491 | J40: =J36-J39 -> -78.257558 | K40: =K36-K39 -> 9.2718854 | L40: =L36-L39 -> 134.88957 | M40: =M36-M39 -> 296.38854
A41: 回購均價（評價日股價 × (1＋ke)^年數） | B41: US$ | F41: =px_val -> 725.18 | H41: =px_val*(1+ke)^(2027+mid-t_val) -> 782.64002 | I41: =px_val*(1+ke)^(2028+mid-t_val) -> 866.39717 | J41: =px_val*(1+ke)^(2029+mid-t_val) -> 959.11792 | K41: =px_val*(1+ke)^(2030+mid-t_val) -> 1061.7615 | L41: =px_val*(1+ke)^(2031+mid-t_val) -> 1175.3899 | M41: =px_val*(1+ke)^(2032+mid-t_val) -> 1301.1787
A43: 情境 B（近四季成長收斂；基準）
A44: 項目 | B44: 單位 | C44: FY2024A | D44: FY2025A | E44: 9M26A | F44: Q4 26E | G44: FY2026E | H44: FY2027E | I44: FY2028E | J44: FY2029E | K44: FY2030E | L44: FY2031E | M44: FY2032E | N44: 說明
A45: 淨利 | B45: US$B | C45: =PL!C92 -> 62.36 | D45: =PL!D92 -> 60.458 | E45: =PL!E92 -> 52.481 | F45: =PL!F92 -> 21.701936 | G45: =PL!G92 -> 74.182936 | H45: =PL!H92 -> 79.676695 | I45: =PL!I92 -> 75.627083 | J45: =PL!J92 -> 68.482767 | ... M45: =PL!M92 -> 72.305999
A46: 折舊與攤銷 | B46: US$B | C46: =PL!C76 -> 15.498 | D46: =PL!D76 -> 18.616 | E46: =PL!E76 -> 19.509 | F46: =PL!F76 -> 9.4130129 | G46: =PL!G76 -> 28.922013 | H46: =PL!H76 -> 53.720643 | I46: =PL!I76 -> 82.378598 | J46: =PL!J76 -> 110.77137 | ... M46: =PL!M76 -> 170.29598
A47: 股權報酬（非現金） | B47: US$B | C47: =PL!C102 -> 16.69 | D47: =PL!D102 -> 20.427 | E47: =PL!E102 -> 21.053 | F47: =PL!F102 -> 8.5115611 | G47: =PL!G102 -> 29.564561 | H47: =PL!H102 -> 35.326899 | I47: =PL!I102 -> 41.670267 | J47: =PL!J102 -> 47.142508 | ... M47: =PL!M102 -> 59.940708
A48: 營運資金變動（流入＋） | B48: US$B | F48: 0 | G48: =F48 -> 0 | H48: =wc_k*(PL!H63-PL!G63) -> 0 | I48: =wc_k*(PL!I63-PL!H63) -> 0 | J48: =wc_k*(PL!J63-PL!I63) -> 0 | K48: =wc_k*(PL!K63-PL!J63) -> 0 | L48: =wc_k*(PL!L63-PL!K63) -> 0 | M48: =wc_k*(PL!M63-PL!L63) -> 0
A49: 多州檢察長協議付款（費用已於 2026Q2–Q3 認列 11.89） | B49: US$B | F49: 0 | G49: =F49 -> 0 | H49: =-ag_y1 -> -1.27 | I49: =-ag_rest -> -1.27 | J49: =-ag_rest -> -1.27 | K49: =-ag_rest -> -1.27 | L49: =-ag_rest -> -1.27 | M49: =-ag_rest -> -1.27 | N49: chat 端審查第 3 條：留在現金流與 DCF；FY2027＝ag_y1（基準等額 1.27），FY2028 起 ag_rest
A50: 其他非現金調整（實績差額：應計法律費用、遞延稅、營運資金等） | B50: US$B | C50: =Q!J37-C45-C46-C47 -> -3.22 | D50: =Q!K37-D45-D46-D47 -> 16.299 | E50: =Q!L37-E45-E46-E47 -> 3.831 | F50: 0 | G50: =E50+F50 -> 3.831 | H50: 0 | I50: 0 | J50: 0 | K50: 0 | L50: 0 | M50: 0
A51: 營運現金流 | B51: US$B | C51: =N(C45)+N(C46)+N(C47)+N(C48)+N(C49)+N(C50) -> 91.328 | D51: =N(D45)+N(D46)+N(D47)+N(D48)+N(D49)+N(D50) -> 115.8 | E51: =N(E45)+N(E46)+N(E47)+N(E48)+N(E49)+N(E50) -> 96.874 | F51: =N(F45)+N(F46)+N(F47)+N(F48)+N(F49)+N(F50) -> 39.62651 | G51: =N(G45)+N(G46)+N(G47)+N(G48)+N(G49)+N(G50) -> 136.50051 | H51: =N(H45)+N(H46)+N(H47)+N(H48)+N(H49)+N(H50) -> 167.45424 | I51: =N(I45)+N(I46)+N(I47)+N(I48)+N(I49)+N(I50) -> 198.40595 | J51: =N(J45)+N(J46)+N(J47)+N(J48)+N(J49)+N(J50) -> 225.12664 | ... M51: =N(M45)+N(M46)+N(M47)+N(M48)+N(M49)+N(M50) -> 301.27269
A52: 資本支出：AI（Thesis） | B52: US$B | F52: =Thesis!F93 -> 51.122525 | G52: =F52 -> 51.122525 | H52: =Thesis!H93 -> 193.03255 | I52: =Thesis!I93 -> 204.33429 | J52: =Thesis!J93 -> 177.88775 | K52: =Thesis!K93 -> 147.24605 | L52: =Thesis!L93 -> 142.55862 | M52: =Thesis!M93 -> 145.03665
A53: 資本支出：非 AI（Seg） | B53: US$B | F53: =Seg!F43 -> 3.0534748 | G53: =F53 -> 3.0534748 | H53: =Seg!H43 -> 12.673327 | I53: =Seg!I43 -> 14.948975 | J53: =Seg!J43 -> 16.91211 | K53: =Seg!K43 -> 18.319678 | L53: =Seg!L43 -> 19.846625 | M53: =Seg!M43 -> 21.503393
A54: 資本支出合計（含融資租賃本金） | B54: US$B | C54: =Q!J40 -> 39.225 | D54: =Q!K40 -> 72.215 | E54: =Q!L40 -> 85.824 | F54: =F52+F53 -> 54.176 | G54: =E54+F54 -> 140 | H54: =H52+H53 -> 205.70588 | I54: =I52+I53 -> 219.28326 | J54: =J52+J53 -> 194.79986 | K54: =K52+K53 -> 165.56573 | L54: =L52+L53 -> 162.40525 | M54: =M52+M53 -> 166.54004
A55: 自由現金流（營運現金 − 資本支出；公司定義） | B55: US$B | C55: =C51-C54 -> 52.103 | D55: =D51-D54 -> 43.585 | E55: =E51-E54 -> 11.05 | F55: =F51-F54 -> -14.54949 | G55: =G51-G54 -> -3.4994902 | H55: =H51-H54 -> -38.251642 | I55: =I51-I54 -> -20.877315 | J55: =J51-J54 -> 30.326778 | ... M55: =M51-M54 -> 134.73265
A56: 檢查：實績自由現金流 − Q 頁 | B56: US$B | C56: =C55-Q!J41 -> 0 | D56: =D55-Q!K41 -> 0 | E56: =E55-Q!L41 -> 0
A57: 普通股股利 | B57: US$B | C57: =Q!J44 -> 5.072 | D57: =Q!K44 -> 5.324 | E57: =Q!L44 -> 4.06 | F57: =dps/4*sh_out -> 1.3632433 | G57: =E57+F57 -> 5.4232433 | H57: =dps*(1+dps_g)^(2027-2026)*PL!F97 -> 5.7928633 | I57: =dps*(1+dps_g)^(2028-2026)*PL!H97 -> 6.2617357 | J57: =dps*(1+dps_g)^(2029-2026)*PL!I97 -> 6.66687 | K57: =dps*(1+dps_g)^(2030-2026)*PL!J97 -> 7.1500749 | L57: =dps*(1+dps_g)^(2031-2026)*PL!K97 -> 7.6126847 | M57: =dps*(1+dps_g)^(2032-2026)*PL!L97 -> 8.1052254 | N57: Q4 26＝每股年股利 ÷ 4 × 流通股；之後每股 +5%／年 × 期初稀釋股數
A58: 特別股股利 | B58: US$B | E58: =PL!E95 -> 0 | F58: =PL!F95 -> 0 | G58: =PL!G95 -> 0 | H58: =PL!H95 -> 0.8125 | I58: =PL!I95 -> 0.8125 | J58: =PL!J95 -> 0.609 | K58: =PL!K95 -> 0 | L58: =PL!L95 -> 0 | M58: =PL!M95 -> 0
A59: 自由現金流扣股利 | B59: US$B | C59: =C55-C57-N(C58) -> 47.031 | D59: =D55-D57-N(D58) -> 38.261 | E59: =E55-E57-N(E58) -> 6.99 | F59: =F55-F57-N(F58) -> -15.912734 | G59: =G55-G57-N(G58) -> -8.9227335 | H59: =H55-H57-N(H58) -> -44.857005 | I59: =I55-I57-N(I58) -> -27.951551 | J59: =J55-J57-N(J58) -> 23.050908 | ... M59: =M55-M57-N(M58) -> 126.62742
A60: 債務到期償還 | B60: US$B | E60: 0 | F60: 0 | G60: =E60+F60 -> 0 | H60: =mat_27 -> 2.747 | I60: 0 | J60: 0 | K60: 0 | L60: 0 | M60: 0 | N60: 9M26 無償還；其他年度到期即再融資（不建模）
A61: 已發行新債 | B61: US$B | E61: 24.91 | F61: 0 | G61: =E61+F61 -> 24.91 | H61: 0 | I61: 0 | J61: 0 | K61: 0 | L61: 0 | M61: 0 | N61: 9M26：發債淨額 24.910（新聞稿）
A62: 股權發行（Q4 26 強制轉換特別股；FY2027 遠期出售） | B62: US$B | E62: 0 | F62: =mcps -> 12.458375 | G62: =E62+F62 -> 12.458375 | H62: =fwd_cash*fwd_on -> 24.9168 | I62: 0 | J62: 0 | K62: 0 | L62: 0 | M62: 0
A63: 期初現金（現金＋有價證券） | B63: US$B | E63: =cash_ye25 -> 81.592 | F63: =E68 -> 82.449 | H63: =F68 -> 78.994641 | I63: =H68 -> 56.307437 | J63: =I68 -> 40 | K63: =J68 -> 63.050908 | L63: =K68 -> 136.71106 | M63: =L68 -> 238.26837
A64: 其他（9M26 實績差額：投資活動其他、代扣稅、匯率；預測期 0） | B64: US$B | E64: =cash_0-(E63+E55-E57-E58-E60+E61+E62) -> -31.043 | F64: 0 | H64: 0 | I64: 0 | J64: 0 | K64: 0 | L64: 0 | M64: 0
A65: 回購前現金 | B65: US$B | E65: =E63+E55-E57-E58-E60+E61+E62+E64 -> 82.449 | F65: =F63+F55-F57-F58-F60+F61+F62+F64 -> 78.994641 | H65: =H63+H55-H57-H58-H60+H61+H62+H64 -> 56.307437 | I65: =I63+I55-I57-I58-I60+I61+I62+I64 -> 28.355886 | J65: =J63+J55-J57-J58-J60+J61+J62+J64 -> 63.050908 | K65: =K63+K55-K57-K58-K60+K61+K62+K64 -> 136.71106 | L65: =L63+L55-L57-L58-L60+L61+L62+L64 -> 238.26837 | M65: =M63+M55-M57-M58-M60+M61+M62+M64 -> 364.89579
A66: 回購 | B66: US$B | E66: =Q!L43 -> 0 | F66: 0 | G66: =E66+F66 -> 0 | H66: =MAX(0,MIN(bb_t,H65-min_cash)) -> 0 | I66: =MAX(0,MIN(bb_t,I65-min_cash)) -> 0 | J66: =MAX(0,MIN(bb_t,J65-min_cash)) -> 0 | K66: =MAX(0,MIN(bb_t,K65-min_cash)) -> 0 | L66: =MAX(0,MIN(bb_t,L65-min_cash)) -> 0 | M66: =MAX(0,MIN(bb_t,M65-min_cash)) -> 0 | N66: Q4 26＝0（暫停）；之後＝MIN(回購目標, 回購前現金 − 最低現金)
A67: 新增舉債（現金低於最低現金時） | B67: US$B | E67: 0 | F67: =MAX(0,min_cash-(F65-F66)) -> 0 | G67: =E67+F67 -> 0 | H67: =MAX(0,min_cash-(H65-H66)) -> 0 | I67: =MAX(0,min_cash-(I65-I66)) -> 11.644114 | J67: =MAX(0,min_cash-(J65-J66)) -> 0 | K67: =MAX(0,min_cash-(K65-K66)) -> 0 | L67: =MAX(0,min_cash-(L65-L66)) -> 0 | M67: =MAX(0,min_cash-(M65-M66)) -> 0
A68: 期末現金（現金＋有價證券） | B68: US$B | E68: =E65-E66+E67 -> 82.449 | F68: =F65-F66+F67 -> 78.994641 | H68: =H65-H66+H67 -> 56.307437 | I68: =I65-I66+I67 -> 40 | J68: =J65-J66+J67 -> 63.050908 | K68: =K65-K66+K67 -> 136.71106 | L68: =L65-L66+L67 -> 238.26837 | M68: =M65-M66+M67 -> 364.89579
A69: 檢查：9M26 期末現金 − 2026-09-30（應為 0） | B69: US$B | E69: =E68-cash_0 -> 0
A70: 期初債務 | B70: US$B | E70: =debt_ye25 -> 58.744 | F70: =E71 -> 84 | H70: =F71 -> 84 | I70: =H71 -> 81.253 | J70: =I71 -> 92.897114 | K70: =J71 -> 92.897114 | L70: =K71 -> 92.897114 | M70: =L71 -> 92.897114
A71: 期末債務 | B71: US$B | E71: =debt_0 -> 84 | F71: =F70-F60+F61+F67 -> 84 | H71: =H70-H60+H61+H67 -> 81.253 | I71: =I70-I60+I61+I67 -> 92.897114 | J71: =J70-J60+J61+J67 -> 92.897114 | K71: =K70-K60+K61+K67 -> 92.897114 | L71: =L70-L60+L61+L67 -> 92.897114 | M71: =M70-M60+M61+M67 -> 92.897114 | N71: 9M26＝票據面額 84.0（10-Q）
A72: 淨現金（現金 − 債務） | B72: US$B | E72: =E68-E71 -> -1.551 | F72: =F68-F71 -> -5.0053585 | H72: =H68-H71 -> -24.945563 | I72: =I68-I71 -> -52.897114 | J72: =J68-J71 -> -29.846206 | K72: =K68-K71 -> 43.813945 | L72: =L68-L71 -> 145.37125 | M72: =M68-M71 -> 271.99868
A73: 回購均價（評價日股價 × (1＋ke)^年數） | B73: US$ | F73: =px_val -> 725.18 | H73: =px_val*(1+ke)^(2027+mid-t_val) -> 782.64002 | I73: =px_val*(1+ke)^(2028+mid-t_val) -> 866.39717 | J73: =px_val*(1+ke)^(2029+mid-t_val) -> 959.11792 | K73: =px_val*(1+ke)^(2030+mid-t_val) -> 1061.7615 | L73: =px_val*(1+ke)^(2031+mid-t_val) -> 1175.3899 | M73: =px_val*(1+ke)^(2032+mid-t_val) -> 1301.1787
A75: 情境 C（AI 價格提升消退）
A76: 項目 | B76: 單位 | C76: FY2024A | D76: FY2025A | E76: 9M26A | F76: Q4 26E | G76: FY2026E | H76: FY2027E | I76: FY2028E | J76: FY2029E | K76: FY2030E | L76: FY2031E | M76: FY2032E | N76: 說明
A77: 淨利 | B77: US$B | C77: =PL!C139 -> 62.36 | D77: =PL!D139 -> 60.458 | E77: =PL!E139 -> 52.481 | F77: =PL!F139 -> 21.701936 | G77: =PL!G139 -> 74.182936 | H77: =PL!H139 -> 75.648136 | I77: =PL!I139 -> 69.825878 | J77: =PL!J139 -> 59.171683 | ... M77: =PL!M139 -> 54.351952
A78: 折舊與攤銷 | B78: US$B | C78: =PL!C123 -> 15.498 | D78: =PL!D123 -> 18.616 | E78: =PL!E123 -> 19.509 | F78: =PL!F123 -> 9.4130129 | G78: =PL!G123 -> 28.922013 | H78: =PL!H123 -> 52.650167 | I78: =PL!I123 -> 76.941279 | J78: =PL!J123 -> 100.96711 | ... M78: =PL!M123 -> 153.30681
A79: 股權報酬（非現金） | B79: US$B | C79: =PL!C149 -> 16.69 | D79: =PL!D149 -> 20.427 | E79: =PL!E149 -> 21.053 | F79: =PL!F149 -> 8.5115611 | G79: =PL!G149 -> 29.564561 | H79: =PL!H149 -> 34.467979 | I79: =PL!I149 -> 39.649849 | J79: =PL!J149 -> 43.722953 | ... M79: =PL!M149 -> 54.173204
A80: 營運資金變動（流入＋） | B80: US$B | F80: 0 | G80: =F80 -> 0 | H80: =wc_k*(PL!H110-PL!G110) -> 0 | I80: =wc_k*(PL!I110-PL!H110) -> 0 | J80: =wc_k*(PL!J110-PL!I110) -> 0 | K80: =wc_k*(PL!K110-PL!J110) -> 0 | L80: =wc_k*(PL!L110-PL!K110) -> 0 | M80: =wc_k*(PL!M110-PL!L110) -> 0
A81: 多州檢察長協議付款（費用已於 2026Q2–Q3 認列 11.89） | B81: US$B | F81: 0 | G81: =F81 -> 0 | H81: =-ag_y1 -> -1.27 | I81: =-ag_rest -> -1.27 | J81: =-ag_rest -> -1.27 | K81: =-ag_rest -> -1.27 | L81: =-ag_rest -> -1.27 | M81: =-ag_rest -> -1.27 | N81: chat 端審查第 3 條：留在現金流與 DCF；FY2027＝ag_y1（基準等額 1.27），FY2028 起 ag_rest
A82: 其他非現金調整（實績差額：應計法律費用、遞延稅、營運資金等） | B82: US$B | C82: =Q!J37-C77-C78-C79 -> -3.22 | D82: =Q!K37-D77-D78-D79 -> 16.299 | E82: =Q!L37-E77-E78-E79 -> 3.831 | F82: 0 | G82: =E82+F82 -> 3.831 | H82: 0 | I82: 0 | J82: 0 | K82: 0 | L82: 0 | M82: 0
A83: 營運現金流 | B83: US$B | C83: =N(C77)+N(C78)+N(C79)+N(C80)+N(C81)+N(C82) -> 91.328 | D83: =N(D77)+N(D78)+N(D79)+N(D80)+N(D81)+N(D82) -> 115.8 | E83: =N(E77)+N(E78)+N(E79)+N(E80)+N(E81)+N(E82) -> 96.874 | F83: =N(F77)+N(F78)+N(F79)+N(F80)+N(F81)+N(F82) -> 39.62651 | G83: =N(G77)+N(G78)+N(G79)+N(G80)+N(G81)+N(G82) -> 136.50051 | H83: =N(H77)+N(H78)+N(H79)+N(H80)+N(H81)+N(H82) -> 161.49628 | I83: =N(I77)+N(I78)+N(I79)+N(I80)+N(I81)+N(I82) -> 185.14701 | J83: =N(J77)+N(J78)+N(J79)+N(J80)+N(J81)+N(J82) -> 202.59174 | ... M83: =N(M77)+N(M78)+N(M79)+N(M80)+N(M81)+N(M82) -> 260.56196
A84: 資本支出：AI（Thesis） | B84: US$B | F84: =Thesis!F136 -> 51.122525 | G84: =F84 -> 51.122525 | H84: =Thesis!H136 -> 162.4848 | I84: =Thesis!I136 -> 171.99802 | J84: =Thesis!J136 -> 153.15051 | K84: =Thesis!K136 -> 129.73677 | L84: =Thesis!L136 -> 132.06888 | M84: =Thesis!M136 -> 141.51438
A85: 資本支出：非 AI（Seg） | B85: US$B | F85: =Seg!F64 -> 3.0534748 | G85: =F85 -> 3.0534748 | H85: =Seg!H64 -> 12.365194 | I85: =Seg!I64 -> 14.224161 | J85: =Seg!J64 -> 15.685364 | K85: =Seg!K64 -> 16.55071 | L85: =Seg!L64 -> 17.933486 | M85: =Seg!M64 -> 19.434333
A86: 資本支出合計（含融資租賃本金） | B86: US$B | C86: =Q!J40 -> 39.225 | D86: =Q!K40 -> 72.215 | E86: =Q!L40 -> 85.824 | F86: =F84+F85 -> 54.176 | G86: =E86+F86 -> 140 | H86: =H84+H85 -> 174.85 | I86: =I84+I85 -> 186.22218 | J86: =J84+J85 -> 168.83587 | K86: =K84+K85 -> 146.28748 | L86: =L84+L85 -> 150.00236 | M86: =M84+M85 -> 160.94872
A87: 自由現金流（營運現金 − 資本支出；公司定義） | B87: US$B | C87: =C83-C86 -> 52.103 | D87: =D83-D86 -> 43.585 | E87: =E83-E86 -> 11.05 | F87: =F83-F86 -> -14.54949 | G87: =G83-G86 -> -3.4994902 | H87: =H83-H86 -> -13.353715 | I87: =I83-I86 -> -1.0751738 | J87: =J83-J86 -> 33.75587 | ... M87: =M83-M86 -> 99.613246
A88: 檢查：實績自由現金流 − Q 頁 | B88: US$B | C88: =C87-Q!J41 -> 0 | D88: =D87-Q!K41 -> 0 | E88: =E87-Q!L41 -> 0
A89: 普通股股利 | B89: US$B | C89: =Q!J44 -> 5.072 | D89: =Q!K44 -> 5.324 | E89: =Q!L44 -> 4.06 | F89: =dps/4*sh_out -> 1.3632433 | G89: =E89+F89 -> 5.4232433 | H89: =dps*(1+dps_g)^(2027-2026)*PL!F144 -> 5.7928633 | I89: =dps*(1+dps_g)^(2028-2026)*PL!H144 -> 6.2617357 | J89: =dps*(1+dps_g)^(2029-2026)*PL!I144 -> 6.66687 | K89: =dps*(1+dps_g)^(2030-2026)*PL!J144 -> 7.1500749 | L89: =dps*(1+dps_g)^(2031-2026)*PL!K144 -> 7.6126847 | M89: =dps*(1+dps_g)^(2032-2026)*PL!L144 -> 8.1052254 | N89: Q4 26＝每股年股利 ÷ 4 × 流通股；之後每股 +5%／年 × 期初稀釋股數
A90: 特別股股利 | B90: US$B | E90: =PL!E142 -> 0 | F90: =PL!F142 -> 0 | G90: =PL!G142 -> 0 | H90: =PL!H142 -> 0.8125 | I90: =PL!I142 -> 0.8125 | J90: =PL!J142 -> 0.609 | K90: =PL!K142 -> 0 | L90: =PL!L142 -> 0 | M90: =PL!M142 -> 0
A91: 自由現金流扣股利 | B91: US$B | C91: =C87-C89-N(C90) -> 47.031 | D91: =D87-D89-N(D90) -> 38.261 | E91: =E87-E89-N(E90) -> 6.99 | F91: =F87-F89-N(F90) -> -15.912734 | G91: =G87-G89-N(G90) -> -8.9227335 | H91: =H87-H89-N(H90) -> -19.959078 | I91: =I87-I89-N(I90) -> -8.1494095 | J91: =J87-J89-N(J90) -> 26.48 | ... M91: =M87-M89-N(M90) -> 91.508021
A92: 債務到期償還 | B92: US$B | E92: 0 | F92: 0 | G92: =E92+F92 -> 0 | H92: =mat_27 -> 2.747 | I92: 0 | J92: 0 | K92: 0 | L92: 0 | M92: 0 | N92: 9M26 無償還；其他年度到期即再融資（不建模）
A93: 已發行新債 | B93: US$B | E93: 24.91 | F93: 0 | G93: =E93+F93 -> 24.91 | H93: 0 | I93: 0 | J93: 0 | K93: 0 | L93: 0 | M93: 0 | N93: 9M26：發債淨額 24.910（新聞稿）
A94: 股權發行（Q4 26 強制轉換特別股；FY2027 遠期出售） | B94: US$B | E94: 0 | F94: =mcps -> 12.458375 | G94: =E94+F94 -> 12.458375 | H94: =fwd_cash*fwd_on -> 24.9168 | I94: 0 | J94: 0 | K94: 0 | L94: 0 | M94: 0
A95: 期初現金（現金＋有價證券） | B95: US$B | E95: =cash_ye25 -> 81.592 | F95: =E100 -> 82.449 | H95: =F100 -> 78.994641 | I95: =H100 -> 81.205363 | J95: =I100 -> 73.055954 | K95: =J100 -> 99.535954 | L95: =K100 -> 159.09481 | M95: =L100 -> 236.35193
A96: 其他（9M26 實績差額：投資活動其他、代扣稅、匯率；預測期 0） | B96: US$B | E96: =cash_0-(E95+E87-E89-E90-E92+E93+E94) -> -31.043 | F96: 0 | H96: 0 | I96: 0 | J96: 0 | K96: 0 | L96: 0 | M96: 0
A97: 回購前現金 | B97: US$B | E97: =E95+E87-E89-E90-E92+E93+E94+E96 -> 82.449 | F97: =F95+F87-F89-F90-F92+F93+F94+F96 -> 78.994641 | H97: =H95+H87-H89-H90-H92+H93+H94+H96 -> 81.205363 | I97: =I95+I87-I89-I90-I92+I93+I94+I96 -> 73.055954 | J97: =J95+J87-J89-J90-J92+J93+J94+J96 -> 99.535954 | K97: =K95+K87-K89-K90-K92+K93+K94+K96 -> 159.09481 | L97: =L95+L87-L89-L90-L92+L93+L94+L96 -> 236.35193 | M97: =M95+M87-M89-M90-M92+M93+M94+M96 -> 327.85996
A98: 回購 | B98: US$B | E98: =Q!L43 -> 0 | F98: 0 | G98: =E98+F98 -> 0 | H98: =MAX(0,MIN(bb_t,H97-min_cash)) -> 0 | I98: =MAX(0,MIN(bb_t,I97-min_cash)) -> 0 | J98: =MAX(0,MIN(bb_t,J97-min_cash)) -> 0 | K98: =MAX(0,MIN(bb_t,K97-min_cash)) -> 0 | L98: =MAX(0,MIN(bb_t,L97-min_cash)) -> 0 | M98: =MAX(0,MIN(bb_t,M97-min_cash)) -> 0 | N98: Q4 26＝0（暫停）；之後＝MIN(回購目標, 回購前現金 − 最低現金)
A99: 新增舉債（現金低於最低現金時） | B99: US$B | E99: 0 | F99: =MAX(0,min_cash-(F97-F98)) -> 0 | G99: =E99+F99 -> 0 | H99: =MAX(0,min_cash-(H97-H98)) -> 0 | I99: =MAX(0,min_cash-(I97-I98)) -> 0 | J99: =MAX(0,min_cash-(J97-J98)) -> 0 | K99: =MAX(0,min_cash-(K97-K98)) -> 0 | L99: =MAX(0,min_cash-(L97-L98)) -> 0 | M99: =MAX(0,min_cash-(M97-M98)) -> 0
A100: 期末現金（現金＋有價證券） | B100: US$B | E100: =E97-E98+E99 -> 82.449 | F100: =F97-F98+F99 -> 78.994641 | H100: =H97-H98+H99 -> 81.205363 | I100: =I97-I98+I99 -> 73.055954 | J100: =J97-J98+J99 -> 99.535954 | K100: =K97-K98+K99 -> 159.09481 | L100: =L97-L98+L99 -> 236.35193 | M100: =M97-M98+M99 -> 327.85996
A101: 檢查：9M26 期末現金 − 2026-09-30（應為 0） | B101: US$B | E101: =E100-cash_0 -> 0
A102: 期初債務 | B102: US$B | E102: =debt_ye25 -> 58.744 | F102: =E103 -> 84 | H102: =F103 -> 84 | I102: =H103 -> 81.253 | J102: =I103 -> 81.253 | K102: =J103 -> 81.253 | L102: =K103 -> 81.253 | M102: =L103 -> 81.253
A103: 期末債務 | B103: US$B | E103: =debt_0 -> 84 | F103: =F102-F92+F93+F99 -> 84 | H103: =H102-H92+H93+H99 -> 81.253 | I103: =I102-I92+I93+I99 -> 81.253 | J103: =J102-J92+J93+J99 -> 81.253 | K103: =K102-K92+K93+K99 -> 81.253 | L103: =L102-L92+L93+L99 -> 81.253 | M103: =M102-M92+M93+M99 -> 81.253 | N103: 9M26＝票據面額 84.0（10-Q）
...

Sheet Val
A1: Val — 目標價（約 12 個月後，2027-10-30）＝DCF 50%＋分部加總（SOTP）50%；情境權重 A 25%／B 50%／C 25%。主值＝自用 AI 讀法 2，讀法 1 並列。每股為 Class C 股票股利（2027-01，1:1）前的口徑；股票股利後每股數字約 ÷ 2
A2: DCF：無槓桿自由現金流（NOPAT＋折舊 − 資本支出＋營運資金 − 協議付款；股權報酬不加回）以 WACC 折現到評價日 2026-09-30（期中慣例），終值＝NOPAT(FY2033) ×(1 − g ÷ RONIC) ÷ (WACC − g)，RONIC＝WACC；以 ke 推到目標時點並扣期間股利。SOTP：目標時點 NTM EBITDA（股權報酬加回）× 數位廣告同業 NTM EV/EBITDA；讀法 2 加回自用 AI 增量營運成本並按帳面加自用 AI 新增資產
A4: 0.3 結論
A5: 項目 | B5: 數值 | C5: 對照 | D5: 對照 | E5: 說明
A6: DCF 目標價（情境加權） | B6: =tp_wA*B106+tp_wB*C106+tp_wC*D106 -> 792.59008
A7: Comparable 目標價（市場主流同業法） | B7: =tp_wA*B129+tp_wB*C129+tp_wC*D129 -> 895.60426 | E7: ＝分部加總（SOTP）情境加權
A8: 目標價（DCF 與 Comparable 加權） | B8: =w_dcf*B6+(1-w_dcf)*B7 -> 844.09717 | E8: ="DCF 權重 "&TEXT(w_dcf,"0%")&"、分部加總 "&TEXT(1-w_dcf,"0%")&"；自用 AI 讀法 "&internal_ai_reading -> DCF 權重 50%、分部加總 50%；自用 AI 讀法 2
A9: 現價（2026-10-28 收盤） | B9: =px -> 612.49 | E9: StockScan、Digrin、TipRanks（In 頁 px）；10-29 收盤只有 ChartRow 一個來源，未採用
A10: 市場共識目標價 | B10: =cons_tp -> 833.12 | E10: MarketBeat 58 位平均（2026-10-22）；只作對照
A11: 上檔空間：加權目標價 | B11: =B8/px-1 -> 0.37814033
A12: 上檔空間：Comparable 目標價 | B12: =B7/px-1 -> 0.46223491
A13: 上檔空間級距 | B13: =IF(B11>=0.5,"大於 50%",IF(B11>=0.25,"25%–50%",IF(B11>=0,"0%–25%",IF(B11>-0.25,"0%～−25%",IF(B11>-0.5,"−25%～−50%","小於 −50%"))))) -> 25%–50% | E13: 以「上檔空間：加權目標價」分六級（Andy 2026-10-25 14:00）
A14: 投資建議 | B14: =IF(B11>=0.5,"強力買進",IF(B11>=0.25,"買進",IF(B11>-0.25,"中立",IF(B11>-0.5,"放空","強力放空")))) -> 買進 | E14: 五級固定規則：≥ +50% 強力買進、+25%～+50% 買進、−25%～+25% 中立、−50%～−25% 放空、≤ −50% 強力放空
A15: 價格帶（DCF 不如預期～順利） | B15: =D106 -> 671.06614 | C15: =B106 -> 914.11403 | E15: B＝C 情境 DCF、C＝A 情境 DCF
A16: 悲觀情境價（C 情境 DCF） | B16: =D106 -> 671.06614 | E16: 地圖「悲觀情境空間」＝本列 ÷ 現價 − 1
A17: 情境目標價（A／B／C；DCF 與分部加總加權） | B17: =w_dcf*B106+(1-w_dcf)*B129 -> 933.26718 | C17: =w_dcf*C106+(1-w_dcf)*C129 -> 844.09685 | D17: =w_dcf*D106+(1-w_dcf)*D129 -> 754.9278
A18: 情境上檔空間（A／B／C） | B18: =B17/px-1 -> 0.5237264 | C18: =C17/px-1 -> 0.37813981 | D18: =D17/px-1 -> 0.2325553
A19: DCF 終值占 EV（A／B／C） | B19: =B97 -> 0.74357987 | C19: =C97 -> 0.73498471 | D19: =D97 -> 0.72324439
A20: 讀法 2（自用 AI 價值中性）：目標價／上檔空間／投資建議 | B20: =w_dcf*(tp_wA*B105+tp_wB*C105+tp_wC*D105)+(1-w_dcf)*(tp_wA*B128+tp_wB*C128+tp_wC*D128) -> 844.09717 | C20: =B20/px-1 -> 0.37814033 | D20: =IF(C20>=0.5,"強力買進",IF(C20>=0.25,"買進",IF(C20>-0.25,"中立",IF(C20>-0.5,"放空","強力放空")))) -> 買進 | E20: 活公式（主值）
A21: 讀法 1（自用 AI 只計成本）：目標價／上檔空間／投資建議 | B21: =w_dcf*(tp_wA*B104+tp_wB*C104+tp_wC*D104)+(1-w_dcf)*(tp_wA*B127+tp_wB*C127+tp_wC*D127) -> 428.70149 | C21: =B21/px-1 -> -0.30006778 | D21: =IF(C21>=0.5,"強力買進",IF(C21>=0.25,"買進",IF(C21>-0.25,"中立",IF(C21>-0.5,"放空","強力放空")))) -> 放空 | E21: 活公式（下緣敏感度）
A22: 讀法 1／2 的 DCF 目標價（情境加權） | B22: =tp_wA*B104+tp_wB*C104+tp_wC*D104 -> 134.91635 | C22: =tp_wA*B105+tp_wB*C105+tp_wC*D105 -> 792.59008
A23: 讀法 1／2 的分部加總目標價（情境加權） | B23: =tp_wA*B127+tp_wB*C127+tp_wC*D127 -> 722.48662 | C23: =tp_wA*B128+tp_wB*C128+tp_wC*D128 -> 895.60426
A24: 目標價方法 | B24: DCF（無槓桿 FCF、WACC、RONIC＝WACC）50%＋分部加總（數位廣告同業 NTM EV/EBITDA）50%；情境 25／50／25；自用 AI 讀法 2
A25: 檢查：情境權重合計（應為 1） | B25: =ROUND(tp_wA+tp_wB+tp_wC,6) -> 1
A26: 檢查：主值目標價 − 所選讀法的目標價（應為 0） | B26: =B8-IF(internal_ai_reading=2,B20,B21) -> 0
A32: 0.0 折現率（CAPM；Blume β、約 10 年期 kd）
A33: 項目 | B33: 數值 | E33: 說明
A34: 股權市值 E＝評價日股價 × 流通股 | B34: =px_val*sh_out -> 1853.7348 | E34: 評價日 2026-09-30 收盤 725.18
A35: 負債 D（票據面額＋融資租賃） | B35: =debt_0+fin_lease -> 84
A36: 股東權益成本 ke＝rf＋β × ERP | B36: =rf+beta*erp -> 0.10701875 | E36: ="β（Blume 調整、兩來源中位數）"&TEXT(beta,"0.000") -> β（Blume 調整、兩來源中位數）1.142
A37: 稅後債務成本 | B37: =kd*(1-tax) -> 0.047796
A38: WACC（＋wacc_adj，Sens 用） | B38: =(B34*ke+B35*B37)/(B34+B35)+wacc_adj -> 0.10445147
A39: 永續期 RONIC＝WACC＋ronic_sp | B39: =wacc+ronic_sp -> 0.10445147
A41: 0.1 DCF（無槓桿自由現金流；三情境各一區塊；欄 F＝Q4 26、H–M＝FY2027–FY2032）
A42: 情境 A（AI 提高每則廣告價格）
A43: 項目 | E43: 說明 | F43: Q4 26E | H43: FY2027E | I43: FY2028E | J43: FY2029E | K43: FY2030E | L43: FY2031E | M43: FY2032E
A44: 營業利益（財報口徑 EBIT；預測期無一次性） | F44: =PL!F31 -> 26.019148 | H44: =PL!H31 -> 100.52133 | I44: =PL!I31 -> 99.582202 | J44: =PL!J31 -> 97.351945 | K44: =PL!K31 -> 96.50103 | L44: =PL!L31 -> 97.407719 | M44: =PL!M31 -> 102.86302
A45: NOPAT＝(EBIT＋sbc_add × 股權報酬) ×(1 − 稅率) | F45: =(F44+sbc_add*PL!F55)*(1-tax) -> 21.856084 | H45: =(H44+sbc_add*PL!H55)*(1-tax) -> 84.437914 | I45: =(I44+sbc_add*PL!I55)*(1-tax) -> 83.64905 | J45: =(J44+sbc_add*PL!J55)*(1-tax) -> 81.775633 | K45: =(K44+sbc_add*PL!K55)*(1-tax) -> 81.060865 | L45: =(L44+sbc_add*PL!L55)*(1-tax) -> 81.822484 | M45: =(M44+sbc_add*PL!M55)*(1-tax) -> 86.404939
A46: ＋折舊 | F46: =PL!F29 -> 9.4130129 | H46: =PL!H29 -> 54.791119 | I46: =PL!I29 -> 87.815916 | J46: =PL!J29 -> 120.57563 | K46: =PL!K29 -> 147.29003 | L46: =PL!L29 -> 167.44418 | M46: =PL!M29 -> 187.28516
A47: − 資本支出（含融資租賃本金） | F47: =CF!F22 -> 54.176 | H47: =CF!H22 -> 236.56176 | I47: =CF!I22 -> 252.34435 | J47: =CF!J22 -> 220.76386 | K47: =CF!K22 -> 184.84398 | L47: =CF!L22 -> 174.80813 | M47: =CF!M22 -> 172.13137
A48: ＋營運資金變動 | F48: =CF!F16 -> 0 | H48: =CF!H16 -> 0 | I48: =CF!I16 -> 0 | J48: =CF!J16 -> 0 | K48: =CF!K16 -> 0 | L48: =CF!L16 -> 0 | M48: =CF!M16 -> 0
A49: ＋協議付款（負值；不可抵稅） | F49: =CF!F17 -> 0 | H49: =CF!H17 -> -1.27 | I49: =CF!I17 -> -1.27 | J49: =CF!J17 -> -1.27 | K49: =CF!K17 -> -1.27 | L49: =CF!L17 -> -1.27 | M49: =CF!M17 -> -1.27
A50: 無槓桿自由現金流（財報口徑） | F50: =F45+F46-F47+F48+F49 -> -22.906903 | H50: =H45+H46-H47+H48+H49 -> -98.602728 | I50: =I45+I46-I47+I48+I49 -> -82.149381 | J50: =J45+J46-J47+J48+J49 -> -19.682594 | K50: =K45+K46-K47+K48+K49 -> 42.236912 | L50: =L45+L46-L47+L48+L49 -> 73.188537 | M50: =M45+M46-M47+M48+M49 -> 100.28873
A51: 自用 AI 影子效益＋租用算力租金加回（稅後；讀法 2 加入） | F51: =(PL!F35+Thesis!F64)*(1-tax) -> 3.489674 | H51: =(PL!H35+Thesis!H64)*(1-tax) -> 51.672106 | I51: =(PL!I35+Thesis!I64)*(1-tax) -> 100.55784 | J51: =(PL!J35+Thesis!J64)*(1-tax) -> 145.15388 | K51: =(PL!K35+Thesis!K64)*(1-tax) -> 178.70993 | L51: =(PL!L35+Thesis!L64)*(1-tax) -> 201.689 | M51: =(PL!M35+Thesis!M64)*(1-tax) -> 214.31744
A52: 折現年數（評價日 2026-09-30 起，期中） | F52: =t_q4 -> 0.125 | H52: =2027+mid-t_val -> 0.75 | I52: =2028+mid-t_val -> 1.75 | J52: =2029+mid-t_val -> 2.75 | K52: =2030+mid-t_val -> 3.75 | L52: =2031+mid-t_val -> 4.75 | M52: =2032+mid-t_val -> 5.75
A53: 折現因子 1 ÷ (1＋WACC)^年數 | F53: =1/(1+wacc)^F52 -> 0.98765819 | H53: =1/(1+wacc)^H52 -> 0.9281967 | I53: =1/(1+wacc)^I52 -> 0.84041421 | J53: =1/(1+wacc)^J52 -> 0.76093358 | K53: =1/(1+wacc)^K52 -> 0.68896968 | L53: =1/(1+wacc)^L52 -> 0.62381164 | M53: =1/(1+wacc)^M52 -> 0.5648158
A54: 現值（財報口徑） | F54: =F50*F53 -> -22.62419 | H54: =H50*H53 -> -91.522727 | I54: =I50*I53 -> -69.039507 | J54: =J50*J53 -> -14.977147 | K54: =K50*K53 -> 29.099952 | L54: =L50*L53 -> 45.655861 | M54: =M50*M53 -> 56.644659
A55: 現值（影子效益） | F55: =F51*F53 -> 3.4466051 | H55: =H51*H53 -> 47.961878 | I55: =I51*I53 -> 84.510235 | J55: =J51*J53 -> 110.45246 | K55: =K51*K53 -> 123.12572 | L55: =L51*L53 -> 125.81595 | M55: =M51*M53 -> 121.04988
A57: 情境 B（近四季成長收斂；基準）
A58: 項目 | E58: 說明 | F58: Q4 26E | H58: FY2027E | I58: FY2028E | J58: FY2029E | K58: FY2030E | L58: FY2031E | M58: FY2032E
A59: 營業利益（財報口徑 EBIT；預測期無一次性） | F59: =PL!F78 -> 26.019148 | H59: =PL!H78 -> 95.725422 | I59: =PL!I78 -> 91.680088 | J59: =PL!J78 -> 84.386165 | K59: =PL!K78 -> 76.289674 | L59: =PL!L78 -> 77.135703 | M59: =PL!M78 -> 81.006897
A60: NOPAT＝(EBIT＋sbc_add × 股權報酬) ×(1 − 稅率) | F60: =(F59+sbc_add*PL!F102)*(1-tax) -> 21.856084 | H60: =(H59+sbc_add*PL!H102)*(1-tax) -> 80.409355 | I60: =(I59+sbc_add*PL!I102)*(1-tax) -> 77.011274 | J60: =(J59+sbc_add*PL!J102)*(1-tax) -> 70.884379 | K60: =(K59+sbc_add*PL!K102)*(1-tax) -> 64.083326 | L60: =(L59+sbc_add*PL!L102)*(1-tax) -> 64.793991 | M60: =(M59+sbc_add*PL!M102)*(1-tax) -> 68.045793
A61: ＋折舊 | F61: =PL!F76 -> 9.4130129 | H61: =PL!H76 -> 53.720643 | I61: =PL!I76 -> 82.378598 | J61: =PL!J76 -> 110.77137 | K61: =PL!K76 -> 134.12363 | L61: =PL!L76 -> 151.8809 | M61: =PL!M76 -> 170.29598
A62: − 資本支出（含融資租賃本金） | F62: =CF!F54 -> 54.176 | H62: =CF!H54 -> 205.70588 | I62: =CF!I54 -> 219.28326 | J62: =CF!J54 -> 194.79986 | K62: =CF!K54 -> 165.56573 | L62: =CF!L54 -> 162.40525 | M62: =CF!M54 -> 166.54004
A63: ＋營運資金變動 | F63: =CF!F48 -> 0 | H63: =CF!H48 -> 0 | I63: =CF!I48 -> 0 | J63: =CF!J48 -> 0 | K63: =CF!K48 -> 0 | L63: =CF!L48 -> 0 | M63: =CF!M48 -> 0
A64: ＋協議付款（負值；不可抵稅） | F64: =CF!F49 -> 0 | H64: =CF!H49 -> -1.27 | I64: =CF!I49 -> -1.27 | J64: =CF!J49 -> -1.27 | K64: =CF!K49 -> -1.27 | L64: =CF!L49 -> -1.27 | M64: =CF!M49 -> -1.27
A65: 無槓桿自由現金流（財報口徑） | F65: =F60+F61-F62+F63+F64 -> -22.906903 | H65: =H60+H61-H62+H63+H64 -> -72.845881 | I65: =I60+I61-I62+I63+I64 -> -61.163391 | J65: =J60+J61-J62+J63+J64 -> -14.414118 | K65: =K60+K61-K62+K63+K64 -> 31.371225 | L65: =L60+L61-L62+L63+L64 -> 52.999647 | M65: =M60+M61-M62+M63+M64 -> 70.531734
A66: 自用 AI 影子效益＋租用算力租金加回（稅後；讀法 2 加入） | F66: =(PL!F82+Thesis!F107)*(1-tax) -> 3.489674 | H66: =(PL!H82+Thesis!H107)*(1-tax) -> 48.426502 | I66: =(PL!I82+Thesis!I107)*(1-tax) -> 90.632983 | J66: =(PL!J82+Thesis!J107)*(1-tax) -> 129.16864 | K66: =(PL!K82+Thesis!K107)*(1-tax) -> 158.23871 | L66: =(PL!L82+Thesis!L107)*(1-tax) -> 178.24469 | M66: =(PL!M82+Thesis!M107)*(1-tax) -> 189.38526
A67: 折現年數（評價日 2026-09-30 起，期中） | F67: =t_q4 -> 0.125 | H67: =2027+mid-t_val -> 0.75 | I67: =2028+mid-t_val -> 1.75 | J67: =2029+mid-t_val -> 2.75 | K67: =2030+mid-t_val -> 3.75 | L67: =2031+mid-t_val -> 4.75 | M67: =2032+mid-t_val -> 5.75
A68: 折現因子 1 ÷ (1＋WACC)^年數 | F68: =1/(1+wacc)^F67 -> 0.98765819 | H68: =1/(1+wacc)^H67 -> 0.9281967 | I68: =1/(1+wacc)^I67 -> 0.84041421 | J68: =1/(1+wacc)^J67 -> 0.76093358 | K68: =1/(1+wacc)^K67 -> 0.68896968 | L68: =1/(1+wacc)^L67 -> 0.62381164 | M68: =1/(1+wacc)^M67 -> 0.5648158
A69: 現值（財報口徑） | F69: =F65*F68 -> -22.62419 | H69: =H65*H68 -> -67.615306 | I69: =I65*I68 -> -51.402583 | J69: =J65*J68 -> -10.968186 | K69: =K65*K68 -> 21.613823 | L69: =L65*L68 -> 33.061797 | M69: =M65*M68 -> 39.837438
A70: 現值（影子效益） | F70: =F66*F68 -> 3.4466051 | H70: =H66*H68 -> 44.94932 | I70: =I66*I68 -> 76.169246 | J70: =J66*J68 -> 98.288756 | K70: =K66*K68 -> 109.02167 | L70: =L66*L68 -> 111.19111 | M70: =M66*M68 -> 106.96779
A72: 情境 C（AI 價格提升消退）
A73: 項目 | E73: 說明 | F73: Q4 26E | H73: FY2027E | I73: FY2028E | J73: FY2029E | K73: FY2030E | L73: FY2031E | M73: FY2032E
A74: 營業利益（財報口徑 EBIT；預測期無一次性） | F74: =PL!F125 -> 26.019148 | H74: =PL!H125 -> 90.929519 | I74: =PL!I125 -> 83.777975 | J74: =PL!J125 -> 71.420385 | K74: =PL!K125 -> 56.078318 | L74: =PL!L125 -> 56.863688 | M74: =PL!M125 -> 59.150772
A75: NOPAT＝(EBIT＋sbc_add × 股權報酬) ×(1 − 稅率) | F75: =(F74+sbc_add*PL!F149)*(1-tax) -> 21.856084 | H75: =(H74+sbc_add*PL!H149)*(1-tax) -> 76.380796 | I75: =(I74+sbc_add*PL!I149)*(1-tax) -> 70.373499 | J75: =(J74+sbc_add*PL!J149)*(1-tax) -> 59.993124 | K75: =(K74+sbc_add*PL!K149)*(1-tax) -> 47.105787 | L75: =(L74+sbc_add*PL!L149)*(1-tax) -> 47.765498 | M75: =(M74+sbc_add*PL!M149)*(1-tax) -> 49.686648
A76: ＋折舊 | F76: =PL!F123 -> 9.4130129 | H76: =PL!H123 -> 52.650167 | I76: =PL!I123 -> 76.941279 | J76: =PL!J123 -> 100.96711 | K76: =PL!K123 -> 120.95723 | L76: =PL!L123 -> 136.31762 | M76: =PL!M123 -> 153.30681
A77: − 資本支出（含融資租賃本金） | F77: =CF!F86 -> 54.176 | H77: =CF!H86 -> 174.85 | I77: =CF!I86 -> 186.22218 | J77: =CF!J86 -> 168.83587 | K77: =CF!K86 -> 146.28748 | L77: =CF!L86 -> 150.00236 | M77: =CF!M86 -> 160.94872
A78: ＋營運資金變動 | F78: =CF!F80 -> 0 | H78: =CF!H80 -> 0 | I78: =CF!I80 -> 0 | J78: =CF!J80 -> 0 | K78: =CF!K80 -> 0 | L78: =CF!L80 -> 0 | M78: =CF!M80 -> 0
A79: ＋協議付款（負值；不可抵稅） | F79: =CF!F81 -> 0 | H79: =CF!H81 -> -1.27 | I79: =CF!I81 -> -1.27 | J79: =CF!J81 -> -1.27 | K79: =CF!K81 -> -1.27 | L79: =CF!L81 -> -1.27 | M79: =CF!M81 -> -1.27
A80: 無槓桿自由現金流（財報口徑） | F80: =F75+F76-F77+F78+F79 -> -22.906903 | H80: =H75+H76-H77+H78+H79 -> -47.089034 | I80: =I75+I76-I77+I78+I79 -> -40.177402 | J80: =J75+J76-J77+J78+J79 -> -9.1456419 | K80: =K75+K76-K77+K78+K79 -> 20.505537 | L80: =L75+L76-L77+L78+L79 -> 32.810757 | M80: =M75+M76-M77+M78+M79 -> 40.774738
A81: 自用 AI 影子效益＋租用算力租金加回（稅後；讀法 2 加入） | F81: =(PL!F129+Thesis!F150)*(1-tax) -> 3.489674 | H81: =(PL!H129+Thesis!H150)*(1-tax) -> 45.180899 | I81: =(PL!I129+Thesis!I150)*(1-tax) -> 80.708127 | J81: =(PL!J129+Thesis!J150)*(1-tax) -> 113.1834 | K81: =(PL!K129+Thesis!K150)*(1-tax) -> 137.76749 | L81: =(PL!L129+Thesis!L150)*(1-tax) -> 154.80037 | M81: =(PL!M129+Thesis!M150)*(1-tax) -> 164.45307
A82: 折現年數（評價日 2026-09-30 起，期中） | F82: =t_q4 -> 0.125 | H82: =2027+mid-t_val -> 0.75 | I82: =2028+mid-t_val -> 1.75 | J82: =2029+mid-t_val -> 2.75 | K82: =2030+mid-t_val -> 3.75 | L82: =2031+mid-t_val -> 4.75 | M82: =2032+mid-t_val -> 5.75
A83: 折現因子 1 ÷ (1＋WACC)^年數 | F83: =1/(1+wacc)^F82 -> 0.98765819 | H83: =1/(1+wacc)^H82 -> 0.9281967 | I83: =1/(1+wacc)^I82 -> 0.84041421 | J83: =1/(1+wacc)^J82 -> 0.76093358 | K83: =1/(1+wacc)^K82 -> 0.68896968 | L83: =1/(1+wacc)^L82 -> 0.62381164 | M83: =1/(1+wacc)^M82 -> 0.5648158
A84: 現值（財報口徑） | F84: =F80*F83 -> -22.62419 | H84: =H80*H83 -> -43.707886 | I84: =I80*I83 -> -33.76566 | J84: =J80*J83 -> -6.959226 | K84: =K80*K83 -> 14.127693 | L84: =L80*L83 -> 20.467732 | M84: =M80*M83 -> 23.030217
A85: 現值（影子效益） | F85: =F81*F83 -> 3.4466051 | H85: =H81*H83 -> 41.936761 | I85: =I81*I83 -> 67.828257 | J85: =J81*J83 -> 86.125047 | K85: =K81*K83 -> 94.917623 | L85: =L81*L83 -> 96.566275 | M85: =M81*M83 -> 92.885691
A87: DCF 彙總
A88: 項目 | B88: 情境 A | C88: 情境 B | D88: 情境 C | E88: 說明
A89: 明確期現值合計（財報口徑） | B89: =SUM(F54:M54) -> -66.763098 | C89: =SUM(F69:M69) -> -58.097209 | D89: =SUM(F84:M84) -> -49.43132
A90: 終值（FY2032 年底，財報口徑） | B90: =IF(tv_alt=1,(M50-M49)*(1+g_tv)/(wacc-g_tv),M45*(1+g_tv)*(1-g_tv/ronic)/(wacc-g_tv)) -> 852.04247 | C90: =IF(tv_alt=1,(M65-M64)*(1+g_tv)/(wacc-g_tv),M60*(1+g_tv)*(1-g_tv/ronic)/(wacc-g_tv)) -> 671.00222 | D90: =IF(tv_alt=1,(M80-M79)*(1+g_tv)/(wacc-g_tv),M75*(1+g_tv)*(1-g_tv/ronic)/(wacc-g_tv)) -> 489.96197 | E90: 價值驅動：NOPAT(FY2033) ×(1 − g ÷ RONIC) ÷ (WACC − g)；協議付款 FY2033 以後列類債
A91: 終值現值 | B91: =B90/(1+wacc)^($M$52+mid) -> 457.92543 | C91: =C90/(1+wacc)^($M$67+mid) -> 360.62637 | D91: =D90/(1+wacc)^($M$82+mid) -> 263.32731
A92: 企業價值 EV（讀法 1：只計自用 AI 成本） | B92: =B89+B91 -> 391.16233 | C92: =C89+C91 -> 302.52916 | D92: =D89+D91 -> 213.89599
A93: ＋自用 AI 影子效益現值：明確期 | B93: =SUM(F55:M55) -> 616.36273 | C93: =SUM(F70:M70) -> 550.0345 | D93: =SUM(F85:M85) -> 483.70626
A94: ＋自用 AI 影子效益現值：終值 | B94: =IF(tv_alt=1,M51*(1+g_tv)/(wacc-g_tv),M51*(1+g_tv)*(1-g_tv/ronic)/(wacc-g_tv))/(1+wacc)^($M$52+mid) -> 1135.831 | C94: =IF(tv_alt=1,M66*(1+g_tv)/(wacc-g_tv),M66*(1+g_tv)*(1-g_tv/ronic)/(wacc-g_tv))/(1+wacc)^($M$67+mid) -> 1003.6964 | D94: =IF(tv_alt=1,M81*(1+g_tv)/(wacc-g_tv),M81*(1+g_tv)*(1-g_tv/ronic)/(wacc-g_tv))/(1+wacc)^($M$82+mid) -> 871.56177
A95: 企業價值 EV（讀法 2：自用 AI 價值中性） | B95: =B92+B93+B94 -> 2143.3561 | C95: =C92+C93+C94 -> 1856.26 | D95: =D92+D93+D94 -> 1569.164
A96: 企業價值 EV（主值，依 internal_ai_reading） | B96: =IF(internal_ai_reading=2,B95,B92) -> 2143.3561 | C96: =IF(internal_ai_reading=2,C95,C92) -> 1856.26 | D96: =IF(internal_ai_reading=2,D95,D92) -> 1569.164
A97: 其中：終值占 EV（主值） | B97: =(B91+(internal_ai_reading=2)*B94)/B96 -> 0.74357987 | C97: =(C91+(internal_ai_reading=2)*C94)/C96 -> 0.73498471 | D97: =(D91+(internal_ai_reading=2)*D94)/D96 -> 0.72324439
A98: ＋淨現金（評價日：現金 − 票據面額 − 融資租賃） | B98: =cash_0-debt_0-fin_lease -> -1.551 | C98: =cash_0-debt_0-fin_lease -> -1.551 | D98: =cash_0-debt_0-fin_lease -> -1.551
A99: ＋評價日後股權融資（強制轉換特別股淨額 12.46＋遠期出售 × fwd_on，以 ke 自 FY2027 期中折現） | B99: =mcps+fwd_cash*fwd_on/(1+ke)^$H$52 -> 35.545828 | C99: =mcps+fwd_cash*fwd_on/(1+ke)^$H$52 -> 35.545828 | D99: =mcps+fwd_cash*fwd_on/(1+ke)^$H$52 -> 35.545828 | E99: v0.1.1：遠期出售現金於 FY2027 交割（期中，距評價日 0.75 年），以 ke 折現到評價日（同特別股股利）；遠期價每日按隔夜利率減利差增值、按股利調降，未計（保守）
A100: − 協議付款 FY2033–FY2036（4 期，以 WACC 折現到評價日） | B100: =ag_rest*((1+wacc)^-6.75+(1+wacc)^-7.75+(1+wacc)^-8.75+(1+wacc)^-9.75) -> 2.2520567 | C100: =ag_rest*((1+wacc)^-6.75+(1+wacc)^-7.75+(1+wacc)^-8.75+(1+wacc)^-9.75) -> 2.2520567 | D100: =ag_rest*((1+wacc)^-6.75+(1+wacc)^-7.75+(1+wacc)^-8.75+(1+wacc)^-9.75) -> 2.2520567 | E100: FY2027–FY2032 已在無槓桿自由現金流內
A101: − 類債（其他法律應計＋或有金額 contg） | B101: =legal_oth+contg -> 7.991 | C101: =legal_oth+contg -> 7.991 | D101: =legal_oth+contg -> 7.991
A102: − 特別股股利現值（轉換前，以 ke 折現） | B102: =pref_2H/(1+ke)^$F$52+pref_27/(1+ke)^$H$52+pref_28/(1+ke)^$I$52+pref_29/(1+ke)^$J$52 -> 1.8933746 | C102: =pref_2H/(1+ke)^$F$52+pref_27/(1+ke)^$H$52+pref_28/(1+ke)^$I$52+pref_29/(1+ke)^$J$52 -> 1.8933746 | D102: =pref_2H/(1+ke)^$F$52+pref_27/(1+ke)^$H$52+pref_28/(1+ke)^$I$52+pref_29/(1+ke)^$J$52 -> 1.8933746
A103: 股數（評價日期末稀釋＋遠期出售 × fwd_on＋強制轉換特別股） | B103: =PL!E50+fwd_sh*fwd_on+conv_sh -> 2.637241 | C103: =PL!E97+fwd_sh*fwd_on+conv_sh -> 2.637241 | D103: =PL!E144+fwd_sh*fwd_on+conv_sh -> 2.637241
A104: DCF 每股價值推到目標時點（讀法 1） | B104: =MAX(0,(B92+B98+B99-B100-B101-B102)/B103*(1+ke)^t_tgt-dps_tgt) -> 172.4336 | C104: =MAX(0,(C92+C98+C99-C100-C101-C102)/C103*(1+ke)^t_tgt-dps_tgt) -> 134.91635 | D104: =MAX(0,(D92+D98+D99-D100-D101-D102)/D103*(1+ke)^t_tgt-dps_tgt) -> 97.399104 | E104: (EV＋淨現金＋期後融資 − 協議尾款 − 類債 − 特別股股利) ÷ 股數 ×(1＋ke)^t_tgt − 期間每股股利
A105: DCF 每股價值推到目標時點（讀法 2） | B105: =MAX(0,(B95+B98+B99-B100-B101-B102)/B103*(1+ke)^t_tgt-dps_tgt) -> 914.11403 | C105: =MAX(0,(C95+C98+C99-C100-C101-C102)/C103*(1+ke)^t_tgt-dps_tgt) -> 792.59008 | D105: =MAX(0,(D95+D98+D99-D100-D101-D102)/D103*(1+ke)^t_tgt-dps_tgt) -> 671.06614
A106: DCF 情境價值推到 12 個月後（主值） | B106: =IF(internal_ai_reading=2,B105,B104) -> 914.11403 | C106: =IF(internal_ai_reading=2,C105,C104) -> 792.59008 | D106: =IF(internal_ai_reading=2,D105,D104) -> 671.06614
A108: 0.2 分部加總（SOTP；目標時點 NTM EBITDA，股權報酬加回 × 數位廣告同業 NTM EV/EBITDA；＝本模型的 Comparable）
A109: 同業組／倍數 | B109: 倍數 | C109: 家數 | E109: 說明
A110: 數位廣告 NTM EV/EBITDA 中位數（GOOGL、PINS、TTD、APP、RDDT、SNAP） | B110: =MEDIAN(pm_ads_googl,pm_ads_pins,pm_ads_ttd,pm_ads_app,pm_ads_rddt,pm_ads_snap) -> 9.405 | C110: 6 | E110: data/peers_ads_20261030.json：五家 2026-10-07 基準（未更新）＋GOOGL（同基準日）
A111: FoA 與 RL 採用倍數（ads_mode：0 中位數／1 GOOGL／2 Meta 自身） | B111: =CHOOSE(ads_mode+1,mult_ads,pm_ads_googl,pm_meta_own) -> 9.405
...

Sheet Recon
A1: Recon — 口徑對照：合併層對市場共識（MarketScreener，頁面 2026-10-08，Q3 財報前）、公司指引、M4 未入基準的算力（尚未起租租賃、第三方雲端）、一次性項目兩種口徑。只作對照，不作校準
A3: 1. 合併層：本模型 vs 市場共識
A4: 項目 | B4: 年度 | C4: 情境 A | D4: 情境 B | E4: 情境 C | F4: 共識 | G4: B ÷ 共識 − 1 | H4: 說明
A5: 營收 | B5: FY2026 | C5: =PL!G16 -> 258.04987 | D5: =PL!G63 -> 258.04987 | E5: =PL!G110 -> 258.04987 | F5: =c_revenue_26 -> 254.117 | G5: =D5/F5-1 -> 0.015476614
A6: 營收 | B6: FY2027 | C6: =PL!H16 -> 324.5365 | D6: =PL!H63 -> 316.83318 | E6: =PL!H110 -> 309.12986 | F6: =c_revenue_27 -> 306.527 | G6: =D6/F6-1 -> 0.033622408
A7: 營收 | B7: FY2028 | C7: =PL!I16 -> 391.84471 | D7: =PL!I63 -> 373.72437 | E7: =PL!I110 -> 355.60403 | F7: =c_revenue_28 -> 363.046 | G7: =D7/F7-1 -> 0.029413275
A8: 營業利益（財報口徑） | B8: FY2026 | C8: =PL!G31 -> 80.654148 | D8: =PL!G78 -> 80.654148 | E8: =PL!G125 -> 80.654148 | F8: =c_ebit_26 -> 86.862 | G8: =D8/F8-1 -> -0.071467986 | H8: 共識在 Q3 財報前，未含 Q3 法律費用 9.89
A9: 營業利益（財報口徑） | B9: FY2027 | C9: =PL!H31 -> 100.52133 | D9: =PL!H78 -> 95.725422 | E9: =PL!H125 -> 90.929519 | F9: =c_ebit_27 -> 104.105 | G9: =D9/F9-1 -> -0.080491598
A10: 營業利益（財報口徑） | B10: FY2028 | C10: =PL!I31 -> 99.582202 | D10: =PL!I78 -> 91.680088 | E10: =PL!I125 -> 83.777975 | F10: =c_ebit_28 -> 124.141 | G10: =D10/F10-1 -> -0.26148421
A11: EPS（GAAP） | B11: FY2026 | C11: =PL!G52 -> 28.848816 | D11: =PL!G99 -> 28.848816 | E11: =PL!G146 -> 28.848816 | F11: =c_eps_26 -> 31.04 | G11: =D11/F11-1 -> -0.070592268 | H11: 共識在 Q3 財報前，未含 Q3 法律費用 9.89
A12: EPS（GAAP） | B12: FY2027 | C12: =PL!H52 -> 31.58583 | D12: =PL!H99 -> 30.05077 | E12: =PL!H146 -> 28.51571 | F12: =c_eps_27 -> 34.07 | G12: =D12/F12-1 -> -0.11796976
A13: EPS（GAAP） | B13: FY2028 | C13: =PL!I52 -> 30.046575 | D13: =PL!I99 -> 27.90437 | E13: =PL!I146 -> 25.740635 | F13: =c_eps_28 -> 39.53 | G13: =D13/F13-1 -> -0.29409637
A14: 資本支出（本模型含融資租賃本金） | B14: FY2026 | C14: =CF!G22 -> 140 | D14: =CF!G54 -> 140 | E14: =CF!G86 -> 140 | F14: =c_capex_26 -> 139.19 | G14: =D14/F14-1 -> 0.0058193836 | H14: 共識＝購置不動產與設備（不含融資租賃本金，近四季約 3.5）
A15: 資本支出（本模型含融資租賃本金） | B15: FY2027 | C15: =CF!H22 -> 236.56176 | D15: =CF!H54 -> 205.70588 | E15: =CF!H86 -> 174.85 | F15: =c_capex_27 -> 193.057 | G15: =D15/F15-1 -> 0.065518879 | H15: 共識＝購置不動產與設備（不含融資租賃本金，近四季約 3.5）
A16: 資本支出（本模型含融資租賃本金） | B16: FY2028 | C16: =CF!I22 -> 252.34435 | D16: =CF!I54 -> 219.28326 | E16: =CF!I86 -> 186.22218 | F16: =c_capex_28 -> 209.324 | G16: =D16/F16-1 -> 0.04757822 | H16: 共識＝購置不動產與設備（不含融資租賃本金，近四季約 3.5）
A17: 自由現金流 | B17: FY2026 | C17: =CF!G23 -> -3.4994902 | D17: =CF!G55 -> -3.4994902 | E17: =CF!G87 -> -3.4994902 | F17: =c_fcf_26 -> -7.076 | G17: =D17/F17-1 -> -0.50544231
A18: 自由現金流 | B18: FY2027 | C18: =CF!H23 -> -63.149568 | D18: =CF!H55 -> -38.251642 | E18: =CF!H87 -> -13.353715 | F18: =c_fcf_27 -> -23.398 | G18: =D18/F18-1 -> 0.63482527
A19: 自由現金流 | B19: FY2028 | C19: =CF!I23 -> -40.737184 | D19: =CF!I55 -> -20.877315 | E19: =CF!I87 -> -1.0751738 | F19: =c_fcf_28 -> 8.281 | G19: =D19/F19-1 -> -3.5211104
A20: EBITDA（本模型＝財報營業利益＋折舊＋SBC） | B20: FY2026 | C20: =PL!G31+PL!G29+PL!G55 -> 139.14072 | D20: =PL!G78+PL!G76+PL!G102 -> 139.14072 | E20: =PL!G125+PL!G123+PL!G149 -> 139.14072 | F20: =c_ebitda_26 -> 144.544 | G20: =D20/F20-1 -> -0.037381546
A21: EBITDA（本模型＝財報營業利益＋折舊＋SBC） | B21: FY2027 | C21: =PL!H31+PL!H29+PL!H55 -> 191.49826 | D21: =PL!H78+PL!H76+PL!H102 -> 184.77296 | E21: =PL!H125+PL!H123+PL!H149 -> 178.04766 | F21: =c_ebitda_27 -> 180.579 | G21: =D21/F21-1 -> 0.023225094
A22: EBITDA（本模型＝財報營業利益＋折舊＋SBC） | B22: FY2028 | C22: =PL!I31+PL!I29+PL!I55 -> 231.0888 | D22: =PL!I78+PL!I76+PL!I102 -> 215.72895 | E22: =PL!I125+PL!I123+PL!I149 -> 200.3691 | F22: =c_ebitda_28 -> 221.948 | G22: =D22/F22-1 -> -0.028020286
A23: EPS（排除一次性）FY2026 vs valueinvesting 共識（推測排除一次性） | B23: FY2026 | C23: =PL!G53 -> 30.55054 | D23: =PL!G100 -> 30.55054 | E23: =PL!G147 -> 30.55054 | F23: =c_eps26_vi -> 33.59 | G23: =D23/F23-1 -> -0.090487064
A25: 2. 逐分部與公司指引（情境 B）
A26: 項目 | B26: 本模型 | C26: 指引低 | D26: 指引高 | E26: 共識 | F26: 說明
A27: 2026Q4 營收 | B27: =PL!F63 -> 76.336871 | C27: 73 | D27: 76 | E27: =c_q4rev -> 74.93 | F27: 公司指引（匯率約 1% 逆風）；共識 TipRanks；本模型 Q4 年增＝近四季年增
A28: 2026 總費用（營收 − 財報營業利益） | B28: =PL!G63-PL!G78 -> 177.39572 | C28: 175 | D28: 179 | F28: 含 Q3 法律費用 9.89
A29: 2026 資本支出（含融資租賃本金） | B29: =CF!G54 -> 140 | C29: 135 | D29: 145 | E29: =c_capex_26 -> 139.19 | F29: C10：本模型＝指引中點；共識不含租賃本金
A30: 2026 Reality Labs 虧損 | B30: =-PL!G71 -> 18.5 | C30: 18 | D30: 19 | F30: Q4 26 依指引中點倒推
A31: 2027 Reality Labs 虧損 | B31: =-PL!H71 -> 15 | F31: 法說：約 15（事實總帳 call.rlLoss2027）
A32: 2027 資本支出（情境 B，M6） | B32: =CF!H54 -> 205.70588 | E32: =c_capex_27 -> 193.057 | F32: 法說未給數字（Q4 法說提供）；共識財報前、不含租賃本金
A33: Family of Apps：分部營收 FY2026 | B33: =PL!G61 -> 255.86141 | F33: 分部共識：未找到（公開來源只有合併層）
A34: Reality Labs：分部營收 FY2026 | B34: =PL!G62 -> 2.1884647 | F34: 分部共識：未找到
A36: 3. M4：未入基準的算力（只作對照與 Sens；本模型可能低估自用算力）
A37: 項目 | B37: 數值 | C37: 說明
A38: 尚未起租之租賃義務（2026-09-30） | B38: =355.73 -> 355.73 | C38: Meta 10-Q 2026Q3 租賃附註（2026-10-29；事實總帳 lease.notCommenced.20260930）；含 Hyperion、El Paso 合資
A39: 不可取消合約承諾（2026-09-30） | B39: =454.52 -> 454.52 | C39: Meta 10-Q 2026Q3 承諾附註（2026-10-29；事實總帳 commit.noncancel.20260930）
A40: 租用算力年租金滿載值（假設 20 年租期；In 頁 rent_l 高值） | B40: =In!F89 -> 17.79 | C40: Sens「租用算力」案例使用
A41: 換算 MW（÷ VR200 每 MW 持有成本） | B41: =B40/he_vr*1000 -> 1455.1587 | C41: 粗估：租金全部視為算力持有成本
A42: 本模型 FY2027 年底自用 AI MW（情境 B，資本支出口徑） | B42: =Thesis!H81 -> 10452.544
A43: 本模型評價日 AI MW（支出口徑，含在建） | B43: =mw_tot0 -> 5038.1965
A44: 第三方雲端與第三方 AI token 成本 | B44: =0 -> 0 | C44: 法說稱費用成長來自「third party cloud spend」與第三方 AI token 成本，未給金額；follow-up：以第三方雲端補近期容量、自建／租用比例「未揭露」：未找到金額
A45: 或有雲端算力採購義務（五年，最多；2026-09-30） | B45: =14.72 -> 14.72 | C45: Meta 10-Q 2026Q3（完整 PDF 第 21 頁；mag/extract/docs/2026Q3/meta_2026Q3_10-Q.pdf）（2026-10-29；事實總帳 commit.cloudContingent）；雲端供應商轉售他人則可減少
A46: MTIA（自研晶片）占比 | B46: =0 -> 0 | C46: 完整 10-Q、法說與 follow-up call 逐字稿皆未提及（搜尋 MTIA、silicon、chip、ASIC）：未找到；不套 NonNV 係數（M4）
A48: 4. 一次性項目：財報口徑 vs 評價口徑（M5 擴大）
A49: 項目 | B49: 財報口徑 | C49: 排除一次性 | D49: 差額 | E49: 說明
A50: FY2026 營業利益（情境 B） | B50: =PL!G78 -> 80.654148 | C50: =PL!G81 -> 94.124148 | D50: =C50-B50 -> 13.47 | E50: 排除：Q1 CAMT 稅務利益 8.03、Q2 法律 2.40＋遣散 1.18、Q3 法律 9.89；協議現金付款仍在現金流與 DCF
A51: FY2026 EPS（情境 B） | B51: =PL!G99 -> 28.848816 | C51: =PL!G100 -> 30.55054 | D51: =C51-B51 -> 1.7017235 | E51: 排除：Q1 CAMT 稅務利益 8.03、Q2 法律 2.40＋遣散 1.18、Q3 法律 9.89；協議現金付款仍在現金流與 DCF
A52: 9M26 EPS | B52: =PL!E99 -> 20.436526 | C52: =PL!E100 -> 22.140528 | D52: =C52-B52 -> 1.7040016 | E52: 排除：Q1 CAMT 稅務利益 8.03、Q2 法律 2.40＋遣散 1.18、Q3 法律 9.89；協議現金付款仍在現金流與 DCF
A54: 5. v0.1.1：完整 10-Q 新事實與法說方向（只作對照；有量化者已在模型，其餘只寫文字，H2）
A55: 項目 | B55: 數值 | C55: 說明
A56: 多州檢察長協議費用：前三季合計（Q3 9.89） | B56: =11.89 -> 11.89 | C56: Meta 10-Q 2026Q3（完整 PDF 第 47 頁；mag/extract/docs/2026Q3/meta_2026Q3_10-Q.pdf）（2026-10-29；事實總帳 legal.agCharge.ytd9m2026）；模型：其他法律應計＝19.881 − 本值（In legal_oth）
A57: 法律相關應計：流動 2025-12-31 → 2026-09-30 | B57: =11.577-6.867 -> 4.71 | C57: 6.867 → 11.577（+4.71）；含協議一年內到期部分與其他案件（新墨西哥判決約 0.94 已上訴暫緩等）。原文無第一年付款金額 → 等額（H3）；推論第一年約 4.04 只進 Sens（ag_y1 高）
A58: 法律相關應計：非流動 2025-12-31 → 2026-09-30 | B58: =8.304-0.45 -> 7.854 | C58: 0.450 → 8.304（+7.85），與協議分年支付相符
A59: 協議名目付款（12.7＋委員會 0.075）÷ 已認列費用 11.89 | B59: =(12.7+0.075)/11.89 -> 1.0744323 | C59: 比值約 1.07：若按十年等額年金，隱含折現率約 1.4%；v0.1 推論「9.89≈12.7 以約 4.9% 折現的現值」不成立（已撤回）
A60: 融資租賃使用權資產（2026-09-30） | B60: =11.704 -> 11.704 | C60: 10-Q 未單獨揭露融資租賃負債：基準 0、Sens 上限＝本值（In fin_lease）；前三季本金支付 2.769 已在資本支出（公司口徑）
A61: 買回授權剩餘額度 | B61: =25.03 -> 25.03 | C61: Meta 10-Q 2026Q3（完整 PDF 第 29 頁；mag/extract/docs/2026Q3/meta_2026Q3_10-Q.pdf）（2026-10-29；事實總帳 bb.remaining.20260930）；2026 年前三季未買回；模型回購目標 0（Sens 高 26.2／年）
A62: 伺服器與網路設備折舊 2026Q3 | B62: =5.34 -> 5.34 | C62: 5.34 × 4 ÷ 133.6 ≈ 6.3 年（粗估，含未滿一年資產）；10-Q 未載耐用年限，模型 life_it 6 年不改
A63: 受限約當現金（未計入現金＋有價證券 82.45） | B63: =12.826 -> 12.826 | C63: 其中 10.80 為多年期基礎設施採購保證金，預計 2028–2030 隨採購義務完成釋出；屬預付採購，不計入淨現金
A64: 2027 資本支出指引（未量化，無數值） | C64: 未量化：「until we get to the Q4 call」；方向「continue investing aggressively」（主法說）。follow-up：伺服器訂單可「pace … over time」→ 模型沿用 M6（cx27_B）
A65: 2027 Reality Labs 虧損（約） | B65: =-PL!H71 -> 15 | C65: 法說「around $15B next year」、此後「trending towards profitability」→ 已在 rl_loss27（Interested-party）
A66: Class C「數千億」融資上限（無數值） | C66: follow-up：資訊聲明中的金額是「a theoretical maximum」（觸發失去創辦人控制權的門檻），非目前股權融資需求或計畫

Sheet Sens
A1: Sens — 一次改一個輸入（In 頁敏感度低／高值），整本活頁簿以 LibreOffice 重算後的加權目標價（Val 頁）；由 meta/make_v01.sh（SENS=1）產生，建置時寫入（數值）
A2: 相對基準＝案例目標價 ÷ 基準加權目標價 − 1；龍捲風依絕對值排序（HTML）。H、I 欄＝收支關卡 B（五年）與 FY2027 資本支出（B）。inc_m（價格情境差額的增量 EBITDA 率）不列：A、C 對稱且權重相同，對加權目標價結構上恆為 0，只影響情境間距。gl_rl（RL 營收長期年增）亦不列：RL 營業損益依指引路徑設定，營收只經非 AI 資本支出影響目標價，重算變動小於 0.001%（v0.1.1 重算 −5%／15%：844.09／844.10，基準 844.10）
A3: 驅動 | B3: 設定 | C3: 方向 | D3: 加權目標價 | E3: 相對基準 | F3: 鍵 | G3: 說明 | H3: 收支關卡 B（五年） | I3: FY2027 資本支出（B）
A4: 自用 AI 讀法 1（只計成本）：低 | B4: 讀法 2 → 讀法 1 | C4: 低 | D4: 428.70149 | E4: =D4/Val!$B$8-1 -> -0.49211832 | F4: internal_ai_reading | G4: 重算值（make_v01.sh） | H4: 14.97977 | I4: 205.70588
A5: FoA 倍數改用 GOOGL 14.71×：高 | B5: 中位數 9.41× → GOOGL 14.71× | C5: 高 | D5: 1069.633 | E5: =D5/Val!$B$8-1 -> 0.26719173 | F5: ads_mode | G5: 重算值（make_v01.sh） | H5: 14.97977 | I5: 205.70588
A6: FoA 倍數改用 Meta 自身 8.99×：高 | B6: 中位數 9.41× → 8.99× | C6: 高 | D6: 826.45394 | E6: =D6/Val!$B$8-1 -> -0.020901897 | F6: ads_mode | G6: 重算值（make_v01.sh） | H6: 14.97977 | I6: 205.70588
A7: Reality Labs 在分部加總以 0 計：高 | B7: 負 EBITDA × 倍數 → 0 | C7: 高 | D7: 864.97423 | E7: =D7/Val!$B$8-1 -> 0.024733008 | F7: rl_mode | G7: 重算值（make_v01.sh） | H7: 14.97977 | I7: 205.70588
A8: 曝光長期年增：低 | B8: 3%／7% | C8: 低 | D8: 810.97836 | E8: =D8/Val!$B$8-1 -> -0.03923578 | F8: gl_impr | G8: 重算值（make_v01.sh） | H8: -5.8557187 | I8: 205.70588
A9: 曝光長期年增：高 | B9: 3%／7% | C9: 高 | D9: 879.0773 | E9: =D9/Val!$B$8-1 -> 0.041440876 | F9: gl_impr | G9: 重算值（make_v01.sh） | H9: 36.291128 | I9: 205.70588
A10: 每則價格長期年增：低 | B10: 1%／5% | C10: 低 | D10: 810.1838 | E10: =D10/Val!$B$8-1 -> -0.04017709 | F10: gl_price | G10: 重算值（make_v01.sh） | H10: -6.4311469 | I10: 205.70588
A11: 每則價格長期年增：高 | B11: 1%／5% | C11: 高 | D11: 879.95934 | E11: =D11/Val!$B$8-1 -> 0.042485831 | F11: gl_price | G11: 重算值（make_v01.sh） | H11: 36.89275 | I11: 205.70588
A12: 起始年增改用 2026Q3 單季：高 | B12: 近四季 → 2026Q3 | C12: 高 | D12: 825.7642 | E12: =D12/Val!$B$8-1 -> -0.021719032 | F12: g0_q | G12: 重算值（make_v01.sh） | H12: -4.1140143 | I12: 205.70588
A13: 情境 A 價格提升幅度：低 | B13: 5%／15%（只影響 A） | C13: 低 | D13: 832.9939 | E13: =D13/Val!$B$8-1 -> -0.013154016 | F13: pA | G13: 重算值（make_v01.sh） | H13: 14.97977 | I13: 205.70588
A14: 情境 A 價格提升幅度：高 | B14: 5%／15%（只影響 A） | C14: 高 | D14: 855.20044 | E14: =D14/Val!$B$8-1 -> 0.013154016 | F14: pA | G14: 重算值（make_v01.sh） | H14: 14.97977 | I14: 205.70588
A15: 情境 C 價格消退幅度：低 | B15: −15%／−5%（只影響 C） | C15: 低 | D15: 832.9939 | E15: =D15/Val!$B$8-1 -> -0.01315402 | F15: pC | G15: 重算值（make_v01.sh） | H15: 14.97977 | I15: 205.70588
... A85: DCF 加回股權報酬：高 | B85: 不加回 → 加回（稅後） | C85: 高 | D85: 938.90927 | E85: =D85/Val!$B$8-1 -> 0.11232367 | F85: sbc_add | G85: 重算值（make_v01.sh） | H85: 14.97977 | I85: 205.70588
A87: 基準加權目標價（Val 頁） | D87: =Val!B8 -> 844.09717 | H87: =CF!C6 -> 14.97977 | I87: =CF!H54 -> 205.70588
A88: 敏感度重算時的基準值（應與上一列相同；不同表示敏感度已過期） | D88: 844.09717 | E88: =D88-D87 -> 0

Sheet Sources
A1: Sources — 來源（編號、文件、日期、網址、標記）
A3: 編號 | B3: 文件 | C3: 日期 | D3: 網址 | E3: 標記 | F3: 用途
A4: S01 | B4: Meta 2026Q3 財報新聞稿（8-K 附件 99.1） | C4: 2026-10-21 | D4: https://www.sec.gov/Archives/edgar/data/0001326801/000162828026066700/meta-09302026xexhibit991.htm | E4: Verified | F4: 2026Q3、9M 實績、指引、一次性項目
A5: S02 | B5: Meta 2026Q2、Q1、2025Q4 財報新聞稿（8-K 附件 99.1；IR PDF 第二讀） | C5: 2026-07／04／01 | D5: 見事實總帳各筆 url | E5: Verified | F5: 各季實績與比較欄（FY2024、2024Q4–2025Q3）
A6: S03 | B6: Meta 2026Q3 10-Q（完整 106 頁 PDF＋純文字入庫：mag/extract/docs/2026Q3/meta_2026Q3_10-Q.pdf、text/；v0.1.1） | C6: 2026-10-29 | D6: https://www.sec.gov/Archives/edgar/data/0001326801/000162828026066773/meta-20260930.htm | E6: Verified | F6: 債務、在建工程、租賃、承諾、法律應計（前三季協議費用 11.89）、多州檢察長協議 12.7B／5.3B、融資租賃使用權資產、買回剩餘額度、受限現金、股數
A7: S04 | B7: Meta 424B5（Series A 存託股；Class A 遠期出售） | C7: 2026-10-27 | D7: https://www.sec.gov/Archives/edgar/data/0001326801/000119312526436405/d133631d424b5.htm | E7: Verified | F7: 特別股承銷折扣 0.1665／股 → 淨額 12.458；遠期價調整條款
A8: S05 | B8: Meta FWP（Class A 遠期出售、強制轉換特別股） | C8: 2026-10-26 | D8: https://www.sec.gov/Archives/edgar/data/0001326801/000119312526432549/d382225dfwp.htm | E8: Verified | F8: 遠期出售 40M 股、特別股 12.5B 與轉換比例
A9: S06 | B9: Meta 8-K（特別股交割、Class C） | C9: 2026-10-29 | D9: https://www.sec.gov/Archives/edgar/data/0001326801/000119312526438017/d183592d8k.htm | E9: Verified | F9: 特別股 10-29 交割；Class C 股票股利
A10: S07 | B10: Meta 2026Q3 法說逐字稿（Andy 提供，不入庫；推定 2026-10-21） | C10: 2026-10-21 | D10: Drive 02-算力收支/MAG財報下載/Transcript_META_3Q26.pdf | E10: Interested-party | F10: 2027 資本支出無數字、RL 虧損路徑、無融資計畫（通話時）
A11: S08 | B11: Meta 2026Q3 follow-up call 逐字稿（Andy 提供，不入庫） | C11: 2026-10-21 | D11: Drive 02-算力收支/MAG財報下載/Transcript_follow up call_META_3Q26.pdf | E11: Interested-party | F11: 自建為主、第三方雲端補近期容量、比例未揭露；Class C 金額為理論上限；未提 MTIA
A12: S09 | B12: 事實總帳 meta/data/meta_facts_2026q3.json（facts_2026q3.py） | C12: 2026-10-30 | D12: repo 內 | E12: 各筆標記 | F12: Q 頁全部實績與多數輸入
A13: S10 | B13: Tokenomics 快照 meta/data/tokenomics_snapshot_v21.7.json（自 alphabet/data/ 複製） | C13: 2026-10-29 | D13: repo 內（YinchenChang/Tokenomics） | E13: Derived | F13: IF_HoldEcon、IF_OpexGW、IF_CapexIT／Facility、IF_DeprIT
A14: S11 | B14: 共識檔 meta/data/consensus_meta_20261030.json（MarketBeat、TipRanks、MarketScreener、valueinvesting） | C14: 2026-10-30 | D14: repo 內 | E14: Interested-party | F14: 共識目標價、年度與季度共識、現價 612.49
... A20: S17 | B20: 美國財政部每日殖利率曲線（經 Alphabet v0.3.1） | C20: 2026-10-27 | D20: https://home.treasury.gov/resource-center/data-chart-center/interest-rates/TextView?type=daily_treasury_yield_curve&field_tdr_date_value_month=202610 | E20: Verified | F20: rf 4.99%
