Workbook

Sheet README
A1: KLA（KLAC）收支與估值模型 v0.2（AI 半導體 Project 步驟 5：設備與材料——量測與檢測） 2026-10-25
A2: 模型命題：KLA 的系統營收跟著晶圓廠設備支出（WFE）走，再乘上製程控制強度——先進製程與先進封裝每片晶圓需要更多量測與檢測。股價取決於設備市場在 2027 年之後放緩時，強度上升與服務能否撐住盈餘，以及中國（FY2026 占營收 30%）的出口管制風險。
A4: 會計年度：7 月到隔年 6 月（FY2027＝2026-07～2027-06，一半在 CY2026、一半在 CY2027）。FY(t)＝CY(t−1) 下半＋CY(t) 上半。金額百萬美元；EPS 為 GAAP 稀釋、2026-06-12 除權的 10 比 1 分割調整後。FY2027 第一季預定 2026-10-28 公布，建置日（2026-10-25）尚未公布，故不納入。
A6: 驅動因子 → 推導量
A7: 系統營收（日曆年）＝製程控制強度 × 加權前段 WFE（設備模型三情境；代工邏輯＋m × 記憶體）＋先進封裝製程控制（封裝設備成長 × 2 倍）；強度以 CY2026 錨點（上半實績＋公司「下半約高 20%」）校準，之後每年 +pc_u（公司 2030 模型：占 WFE 比重 +150bp）
A8: 服務、SPTS＋PCB：前一年 × 成長率（Assumed，錨在公司長期目標）。毛利＝FY2026 毛利＋增量毛利率（兩點推導 64.6%，公司說 60–65%）× 營收增量；營業費用 FY2027 取公司說法，之後 × 成長率；不寫死利益率
A9: 情境 A／B／C：設備市場模型的三情境（A 續增、B 2028 持平、C 2028 −20%），服務、兩事業與費用成長隨情境；中國出口管制只在 Sens
A10: Val：P/E 規則——10 年（2016–2025 年底）當期 P/E 分位，見頂年 25 分位、中段中位數、谷底 75 分位；循環位置依設備股共用規則（各情境見頂年度讀設備市場模型：A 2029、B 2028、C 2027 → FY2027：A 中段、B 中段、C 見頂）。第 0 節為情境加權目標價。本版未做先驗，無 Andy 合理 P/E 對照
A12: 標記：Verified、Interested-party、Analogy、Assumed、Derived。SemiAnalysis 未使用。
A13: 已知限制：(1) 製程控制強度只有一個校準點（CY2026 錨點），強度上升率來自公司 2030 模型（Interested-party）；(2) 記憶體相對強度由公司「代工邏輯 low-to-mid 60s」一句推得；(3) 系統營收＝產品 − 兩事業（兩事業的服務未揭露）；(4) CY2027 起上下半各 1/2，忽略年內斜率；(5) 中國不在基準內另扣（設備模型 WFE 已含），出口管制只在 Sens；(6) 共識 EPS 為非 GAAP，模型為 GAAP；(7) 2026-10 股價由約 207 跌到 146，原因未查明。
A14: v0.2（2026-10-25）估值 v2：Val 頁新增「0. 目標價」（放在既有內容之後，不位移既有列）＝0.5 × DCF 目標價（股東現金流＝EPS ×（1 − g／ROE），FY2027–32 明確期＋永續，r 10%、g 4%，情境權重 A 0.3／B 0.5／C 0.2）＋0.5 × Comparable 目標價（同業前瞻 P/E 中位數 × 12 個月後前瞻 EPS）；另列 Comparable 單獨目標價、市場共識目標價與差距拆解、歷史分位檢查。原「0. 目標價與上檔空間」改名「舊法：規則值情境加權（參考）」，不再叫目標價。
A15: 預估期間延伸到 FY2032：FY2027–FY2029 由驅動因子推導；FY2030 起為收斂法，非驅動因子推導（PL 頁底部延伸區塊，灰底）。情境對應：A＝順利、B＝平平、C＝不如預期（原為顆數情境）。本版未做先驗，無 Andy 合理 P/E 對照。

Sheet In
A1: In — 輸入（藍字；基準欄 E，低 D、高 F）。金額：百萬美元（US$M）；設備市場：十億美元（US$B）。每個輸入附兩個來源（來源2 找不到者寫「未找到」）；公司原文（SEC 8-K／10-K）算一個
A2: 標記：Verified／Interested-party／Analogy／Assumed／Derived；Analogy、Assumed 給低／高區間，不當點估計用。SemiAnalysis 未使用。共識只放 Recon，不作校準
A3: 鍵 | B3: 項目 | C3: 單位 | D3: 低 | E3: 基準 | F3: 高 | G3: 標記 | H3: 來源1 | I3: 來源2／說明
A4: A. CY2026 錨點（上半年實績＋公司對下半年的說法）
A5: h2up | B5: CY2026 下半年營收較上半年增幅 | C5: % | D5: 0.15 | E5: 0.2 | F5: 0.25 | G5: Interested-party | H5: KLA FQ4-26 法說（2026-07-28；MarketBeat 逐字稿）：下半年約比上半年高 20% | I5: TIKR 2026-07-29 法說摘要（同）；FQ1-27 指引 US$4.0B±0.2B 與共識 FQ2-27 US$4.49B 合計 8.49B＝上半年 7.07B×1.20（Recon）；低／高為 Assumed 區間
A6: g_svc_h2 | B6: CY2026 下半年服務營收較上半年增幅 | C6: % | D6: 0.03 | E6: 0.06 | F6: 0.09 | G6: Assumed | H6: 無：公司稱服務 2026 年成長在長期目標 13–15% 的下緣 | I6: 6%≈年增 13% 的半年版；只影響錨點中系統與服務的拆分
A7: g_oth26 | B7: SPTS＋PCB 兩事業 CY2026 年增 | C7: % | D7: 0.15 | E7: 0.25 | F7: 0.3 | G7: Interested-party | H7: KLA FQ4-26 法說（2026-07-28；MarketBeat 逐字稿）：Orbotech 合計產品 CY2026 成長 25% 以上 | I7: 第二來源：未找到。CY2025 基期取 Q 頁四季合計
A8: ap26 | B8: 先進封裝製程控制營收 CY2026 | C8: US$M | D8: 1000 | E8: 1100 | F8: 1400 | G8: Interested-party | H8: KLA FQ4-26 法說（2026-07-28；MarketBeat 逐字稿）：約 US$1.1B，年增 70% 以上 | I8: handsoff substack（2026-05-31，引公司 FQ3-26）：FY2026 1.3–1.4B（會計年度口徑，與 1.1B 的日曆年口徑不同，未解）；高＝1.4B
A9: ap_g26 | B9: 先進封裝製程控制營收 CY2026 年增 | C9: % | E9: 0.7 | G9: Interested-party | H9: KLA FQ4-26 法說（2026-07-28；MarketBeat 逐字稿）：年增 70% 以上（取 70%） | I9: 用於推 CY2025 基期＝ap26÷1.7
A10: k_ap | B10: 先進封裝製程控制營收成長 ÷ 先進封裝設備市場成長（倍數） | C10: x | D10: 1 | E10: 2 | F10: 2.5 | G10: Interested-party | H10: KLA FQ4-26 法說（2026-07-28；MarketBeat 逐字稿）：成長率接近封裝市場的 2 倍 | I10: 低＝與市場同速、高＝2.5 倍（Assumed）；下滑時同樣放大（β 解讀，Assumed）
A11: B. 製程控制強度（系統營收 ÷ 加權前段 WFE；以 CY2026 錨點校準）
A12: fl26 | B12: CY2026 半導體製程控制系統營收中代工邏輯占比 | C12: % | D12: 0.6 | E12: 0.63 | F12: 0.66 | G12: Interested-party | H12: KLA FQ4-26 法說（2026-07-28；MarketBeat 逐字稿）：2026 年代工邏輯「low to mid-60s」；FQ1-27 為 73%／記憶體 27% | I12: 第二來源：未找到。取 63%；用來推記憶體相對強度
A13: m_mem | B13: 記憶體 WFE 的製程控制強度 ÷ 代工邏輯（相對倍數） | C13: x | D13: =(1-fl26_hi)/fl26_hi*Units!D8/Units!D11 -> 0.89938603 | E13: =(1-fl26)/fl26*Units!D8/Units!D11 -> 1.0253505 | F13: =(1-fl26_lo)/fl26_lo*Units!D8/Units!D11 -> 1.1639113 | G13: Derived | H13: （1−代工邏輯占比）÷ 代工邏輯占比 × CY2026 代工邏輯 WFE ÷ 記憶體 WFE（設備模型情境 A） | I13: 代工邏輯 WFE＝先進邏輯＋其他代工邏輯＋其他前段（含光罩，KLA 光罩檢測歸此）；低欄用 fl26 高值
A14: kla_wfe25 | B14: CY2025 WFE（公司口徑，含先進封裝） | C14: US$B | E14: 120 | G14: Interested-party | H14: KLA FQ4-26 法說（2026-07-28；MarketBeat 逐字稿）：2025 年約 US$120B | I14: 設備模型 2025 前段＋先進封裝＝120.0（相近）
A15: share_up | B15: KLA 占 WFE 比重 2025→2030 的提升 | C15: pt | D15: 0 | E15: 0.015 | F15: 0.03 | G15: Interested-party | H15: KLA FQ4-26 法說（2026-07-28；MarketBeat 逐字稿）：公司 2030 模型稱市占較 2025 提升 150bp（±25） | I15: 第二來源：未找到。低＝不提升、高＝300bp（Assumed）；公司未說明分母，本模型解讀為「半導體製程控制營收 ÷ WFE」
A16: pc_u | B16: 製程控制強度年增（先進製程與先進封裝檢測強度上升） | C16: %/年 | D16: =((s25+share_up_lo)/s25)^(1/5)-1 -> 0 | E16: =((s25+share_up)/s25)^(1/5)-1 -> 0.029460747 | F16: =((s25+share_up_hi)/s25)^(1/5)-1 -> 0.055890495 | G16: Derived | H16: ＝[(CY2025 占比＋提升)÷CY2025 占比]^(1/5)−1；CY2025 占比＝半導體製程控制營收 ÷ 公司 WFE（Units） | I16: 自 CY2027 起套用於 CY2026 校準的強度
A17: kla_sh_pc | B17: KLA 製程控制市占（顯示用：換算製程控制占 WFE） | C17: % | D17: 0.53 | E17: 0.58 | F17: 0.63 | G17: Interested-party | H17: handsoff substack 2026-05-31（引 BofA CY2025）：製程控制市占約 58%、晶圓檢測 81.9%（賣方） | I17: 第二來源：未找到。只用於顯示，不影響營收
A18: C. 中國（重要變數；基準不另扣，風險放 Sens）
A19: chn_sh26 | B19: 中國占營收 FY2026 | C19: % | E19: 0.3 | G19: Verified | H19: KLA FY2026 10-K：中國 30%（FY2025 33%、FY2024 43%） | I19: handsoff substack：FQ3-26 單季 24%（約 US$820M）
A20: chn_sh25 | B20: 中國占營收 FY2025 | C20: % | E20: 0.33 | G20: Verified | H20: KLA FY2026 10-K | I20: —
A21: chn_sh24 | B21: 中國占營收 FY2024 | C21: % | E21: 0.43 | G21: Verified | H21: KLA FY2026 10-K | I21: —
A22: chn_cut | B22: CY2027 起中國系統營收下降比例（出口管制） | C22: % | D22: 0.25 | E22: 0 | F22: 0.5 | G22: Assumed | H22: 無：10-K 稱出口許可未獲准已傷及訂單；BIS 子公司規則暫停一年至 2026-11 | I22: 基準 0（設備模型的 WFE 已含中國）；Sens 列 25%／50%
A23: D. 服務與 SPTS＋PCB（會計年度，前一年 × 成長率）
A24: g_svc_A | B24: 服務營收 FY2027–29 年增（A） | C24: % | D24: 0.12 | E24: 0.14 | F24: 0.16 | G24: Assumed | H24: 公司長期目標 13–15%，2027 年預期在上緣；約 80% 為合約制（KLA FQ4-26 法說（2026-07-28；MarketBeat 逐字稿）） | I24: FY2026 實績 +16.5%（Q 頁）；C 取裝機量成長放緩
A25: g_oth_A | B25: SPTS＋PCB 營收 FY2027–29 年增（A） | C25: % | D25: 0.08 | E25: 0.12 | F25: 0.16 | G25: Assumed | H25: 公司：EPC／PCB 長期成長 high single digit；CY2026 Orbotech 合計 >25% | I25: FY2026 實績 +11.5%（Q 頁）
A26: g_svc_B | B26: 服務營收 FY2027–29 年增（B） | C26: % | D26: 0.1 | E26: 0.12 | F26: 0.14 | G26: Assumed | H26: 公司長期目標 13–15%，2027 年預期在上緣；約 80% 為合約制（KLA FQ4-26 法說（2026-07-28；MarketBeat 逐字稿）） | I26: FY2026 實績 +16.5%（Q 頁）；C 取裝機量成長放緩
A27: g_oth_B | B27: SPTS＋PCB 營收 FY2027–29 年增（B） | C27: % | D27: 0.04 | E27: 0.08 | F27: 0.12 | G27: Assumed | H27: 公司：EPC／PCB 長期成長 high single digit；CY2026 Orbotech 合計 >25% | I27: FY2026 實績 +11.5%（Q 頁）
A28: g_svc_C | B28: 服務營收 FY2027–29 年增（C） | C28: % | D28: 0.08 | E28: 0.1 | F28: 0.12 | G28: Assumed | H28: 公司長期目標 13–15%，2027 年預期在上緣；約 80% 為合約制（KLA FQ4-26 法說（2026-07-28；MarketBeat 逐字稿）） | I28: FY2026 實績 +16.5%（Q 頁）；C 取裝機量成長放緩
A29: g_oth_C | B29: SPTS＋PCB 營收 FY2027–29 年增（C） | C29: % | D29: -0.04 | E29: 0 | F29: 0.04 | G29: Assumed | H29: 公司：EPC／PCB 長期成長 high single digit；CY2026 Orbotech 合計 >25% | I29: FY2026 實績 +11.5%（Q 頁）
A30: E. 毛利與營業費用（不寫死利益率）
A31: gm_inc | B31: 增量毛利率（毛利變動 ÷ 營收變動；相對 FY2026） | C31: % | D31: 0.6 | E31: =(a26_gp-a25_gp)/(a26_rev-a25_rev) -> 0.64646382 | F31: 0.65 | G31: Derived | H31: 兩點：FY2025、FY2026 實績（Q 頁） | I31: 公司：增量毛利率 60–65% 至 2027（非 GAAP；KLA FQ4-26 法說（2026-07-28；MarketBeat 逐字稿））＝低／高；記憶體定價逆風約 100bp
A32: opex_q1 | B32: 營業費用 FQ1-27（R&D＋SG&A） | C32: US$M | E32: 690 | G32: Interested-party | H32: KLA FQ4-26 法說（2026-07-28；MarketBeat 逐字稿）：約 US$690M | I32: 第二來源：未找到
A33: opex_step | B33: 之後每季營業費用增加 | C33: US$M／季 | D33: 15 | E33: 17.5 | F33: 20 | G33: Interested-party | H33: KLA FQ4-26 法說（2026-07-28；MarketBeat 逐字稿）：每季增加約 US$15–20M | I33: 取中點
A34: opex27 | B34: 營業費用 FY2027（4×FQ1＋6×每季增額） | C34: US$M | E34: =4*opex_q1+6*opex_step -> 2865 | G34: Derived | H34: 690＋707.5＋725＋742.5 | I34: 三情境相同（FY2027 已大致決定）
A35: g_opex_A | B35: 營業費用 FY2028–29 年增（A） | C35: % | D35: 0.05 | E35: 0.08 | F35: 0.11 | G35: Assumed | H35: 無：FY2026 +11.4%、FY2027 指引隱含 +7.6% | I35: —
A36: g_opex_B | B36: 營業費用 FY2028–29 年增（B） | C36: % | D36: 0.02 | E36: 0.05 | F36: 0.08 | G36: Assumed | H36: 無：FY2026 +11.4%、FY2027 指引隱含 +7.6% | I36: —
A37: g_opex_C | B37: 營業費用 FY2028–29 年增（C） | C37: % | D37: -0.01 | E37: 0.02 | F37: 0.05 | G37: Assumed | H37: 無：FY2026 +11.4%、FY2027 指引隱含 +7.6% | I37: —
A38: F. 營業外、稅、股數
A39: oth_exp | B39: 營業外淨額（利息與其他）每年 | C39: US$M | D39: -200 | E39: -100 | F39: 0 | G39: Interested-party | H39: KLA FQ4-26 法說（2026-07-28；MarketBeat 逐字稿）：其他收支約每季 US$25M 費用 | I39: FY2026 實績 −54.9（利息 −284.4＋其他 +229.6）；低／高 Assumed
A40: tax | B40: 有效稅率 | C40: % | D40: 0.13 | E40: 0.145 | F40: 0.17 | G40: Interested-party | H40: KLA FQ4-26 法說（2026-07-28；MarketBeat 逐字稿）：規劃稅率 14.5% | I40: FY2026 實績 13.8%（Q 頁）
A41: shares27 | B41: 稀釋股數 FY2027 | C41: 百萬股 | E41: 1312 | G41: Interested-party | H41: KLA FQ4-26 新聞稿（SEC 8-K）：FQ1-27 指引稀釋股數 1,312M | I41: FY2026 稀釋 1,319.6M、FQ4-26 1,315.0M
A42: bb | B42: 稀釋股數年減（買回）FY2028–29 | C42: % | D42: 0 | E42: =1-a26_sh/a25_sh -> 0.01335998 | F42: 0.025 | G42: Derived | H42: FY2025→FY2026 稀釋股數變化（Q 頁） | I42: 低／高 Assumed
A43: G. 公司指引、共識（只供 Recon）、股價、循環位置、目標價權重
A44: g_q1_rev | B44: FQ1-27 營收指引 | C44: US$M | D44: 3800 | E44: 4000 | F44: 4200 | G44: Interested-party | H44: KLA FQ4-26 新聞稿（SEC 8-K，2026-07-28） | I44: TIKR 2026-07-29
A45: g_q1_gm | B45: FQ1-27 GAAP 毛利率指引 | C45: % | D45: 0.606 | E45: 0.616 | F45: 0.626 | G45: Interested-party | H45: 同上 | I45: 非 GAAP 62.5%
A46: g_q1_eps | B46: FQ1-27 GAAP 稀釋 EPS 指引 | C46: US$ | D46: 1.04 | E46: 1.14 | F46: 1.24 | G46: Interested-party | H46: 同上 | I46: 非 GAAP 1.16±0.10
A47: cons_q2_rev | B47: 共識 FQ2-27 營收 | C47: US$M | E47: 4490 | G47: Interested-party | H47: Yahoo Finance（2026-10-25 讀取；21 位分析師） | I47: 第二來源：未找到
A48: cons_rev27 | B48: 共識營收 FY2027 | C48: US$M | E48: 18140 | G48: Interested-party | H48: Yahoo Finance（24 位）：18.14B | I48: stockanalysis（2026-10-20）：18.1B
A49: cons_eps27 | B49: 共識 EPS FY2027（非 GAAP） | C49: US$ | E49: 5.44 | G49: Interested-party | H49: Yahoo Finance（25 位）：5.44 | I49: stockanalysis（2026-10-20，24 位）：5.46
A50: cons_rev28 | B50: 共識營收 FY2028 | C50: US$M | E50: 21570 | G50: Interested-party | H50: Yahoo Finance（21 位）：21.57B | I50: 第二來源：未找到（stockanalysis 需付費）
A51: cons_eps28 | B51: 共識 EPS FY2028（非 GAAP） | C51: US$ | E51: 6.74 | G51: Interested-party | H51: Yahoo Finance（22 位）：6.74 | I51: 第二來源：未找到
A52: pk_A | B52: 情境 A：設備市場見頂年度（日曆年；循環位置規則用） | C52: 年 | E52: 2029 | G52: Derived | H52: markets/equipment/dist/20261023_半導體設備市場模型_v0.1.3.xlsx｜Mkt!C12 | I52: 設備股共用規則（tools/cycle_position.py）：FY(t) 早於見頂年＝中段、等於＝見頂、晚於＝谷底；KLA 的 FY(t) 對照日曆年 t（理由見 Val 第 4 節）
A53: pk_B | B53: 情境 B：設備市場見頂年度（日曆年；循環位置規則用） | C53: 年 | E53: 2028 | G53: Derived | H53: markets/equipment/dist/20261023_半導體設備市場模型_v0.1.3.xlsx｜Mkt!C20 | I53: 同上
A54: pk_C | B54: 情境 C：設備市場見頂年度（日曆年；循環位置規則用） | C54: 年 | E54: 2027 | G54: Derived | H54: markets/equipment/dist/20261023_半導體設備市場模型_v0.1.3.xlsx｜Mkt!C28 | I54: 同上
A55: px | B55: 股價（stockanalysis 2026-10-23 收盤） | C55: US$ | E55: 145.61 | G55: Verified | H55: stockanalysis.com 歷史股價：2026-10-23 收盤 145.61 | I55: digrin：145.61；tipranks：2026-10-22 收盤 147.83（10-22 單日 −9.5%，原因未查明）
A56: tp_wA | B56: 目標價情境權重 A | C56: % | E56: 0.3 | G56: Assumed | H56: Andy 可改 | I56: 三個權重合計應為 100%（Val 第 0 節檢查）
A57: tp_wB | B57: 目標價情境權重 B | C57: % | E57: 0.5 | G57: Assumed | H57: Andy 可改 | I57: —
A58: tp_wC | B58: 目標價情境權重 C | C58: % | E58: 0.2 | G58: Assumed | H58: Andy 可改 | I58: —
A60: J. 目標價（DCF 與 Comparable 加權）與 FY2030–32 收斂法參數（v2 新增；黃底＝Assumed，Andy 可改）
A61: tp_r | B61: 折現率（股東權益要求報酬；美、台、日、韓同一值） | C61: % | E61: 0.1 | G61: Assumed | H61: Andy 可改（工作單 2026-10-25 預設 10%） | I61: —
A62: tp_g | B62: 長期成長率（永續成長；收斂法 FY2032 營收年增的基準） | C62: % | E62: 0.04 | G62: Assumed | H62: Andy 可改（工作單預設 4%） | I62: 情境 A＝tp_g＋2pt、B＝tp_g、C＝tp_g−2pt（PL 頁延伸區塊）
A63: tp_roe | B63: ROE（近三年平均，FY2024–FY2026） | C63: % | E63: =AVERAGE(0.8784,1.0077,0.875) -> 0.92036667 | G63: Derived | H63: stockanalysis 比率頁（2026-10-25 讀取）：FY2024 87.84%、FY2025 100.77%、FY2026 87.50% | I63: 單一來源；高 ROE 來自大量回購使股東權益偏低
A64: tp_w_dcf | B64: 目標價中 DCF 的權重；其餘為 Comparable | C64: % | E64: 0.5 | G64: Assumed | H64: Andy 可改（2026-10-25 11:53：DCF／Comparable 各半） | I64: —
A65: nim10 | B65: 十年平均淨利率（FY2016–FY2025，GAAP，各年淨利 ÷ 營收的平均） | C65: % | E65: =AVERAGE(0.70442/2.98,0.92608/3.48,0.80226/4.04,1.18/4.57,1.22/5.81,2.08/6.92,3.32/9.21,3.39/10.5,2.76/9.81,4.06/12.16) -> 0.27684052 | G65: Derived | H65: vcpscanner.com 年度損益（US$B） | I65: 第二來源：FY2025 與 Q 頁實績核對；其餘年度單一來源（FY2026 淨利率 35.6%，未納入）
A66: cons_tp | B66: 市場共識目標價（賣方平均） | C66: US$ | E66: 232.38 | G66: Interested-party | H66: stockanalysis：30 位分析師平均 US$232.38（中位數 228.50；區間 175–325），資料更新 2026-10-20（10 比 1 分割後） | I66: 第二來源：未找到
A67: cons_feps | B67: 共識前瞻 EPS（差距拆解用） | C67: US$ | E67: =cons_eps28 -> 6.74 | G67: Interested-party | H67: 共識前瞻 EPS＝共識 FY2028 非 GAAP EPS（In 頁 cons_eps28，Yahoo 6.74）；本模型前瞻 EPS 為 8／12 FY2028＋4／12 FY2029（GAAP），約晚四個月 | I67: Derived

Sheet Q
A1: Q — 實績（百萬美元；EPS 為美元，2026-06-12 除權的 10 比 1 分割調整後）。會計年度 7–6 月：FY2026＝2025-07～2026-06。藍字＝輸入（SEC 8-K 新聞稿）；黑字＝公式（Derived）
A2: FY2027 第一季（2026-07～09）：預定 2026-10-28 盤後公布（tipranks 財報行事曆；KLA 去年同季為 10-29）；建置日 2026-10-25 尚未公布，故不納入，指引見下方。公布後更新本頁 I 欄
A3: 項目 | B3: FQ3-25（2025-01～03） | C3: FQ4-25（2025-04～06） | D3: FY26 上半（2025-07～12，FQ1＋FQ2） | E3: FQ3-26（2026-01～03） | F3: FQ4-26（2026-04～06） | G3: FY2025 全年 | H3: FY2026 全年 | I3: FQ1-27（未公布） | J3: 標記 | K3: 來源1（公司） | L3: 來源2／說明
A4: 營收 | B4: 3063 | C4: 3174.741 | D4: =9921.9-3415.1 -> 6506.8 | E4: 3415.1 | F4: 3657.556 | G4: 12156.162 | H4: 13579.476 | I4: 預定 2026-10-28 盤後公布，尚未公布 | J4: Verified | K4: FQ3-25：FQ3-26 新聞稿（SEC 8-K，2026-04-29）前年同期欄；FQ4-25、全年：FQ4-26 新聞稿（SEC 8-K，2026-07-28）；上半＝九個月 9,921.9 − FQ3-26 | L4: stockanalysis 年度：FY2025 12,156、FY2026 13,579；FQ2-26 單季 3,297（FQ3-26 新聞稿）
A5: 產品營收 | B5: 2393.8 | C5: 2472.182 | D5: =7616.4-2640.3 -> 4976.1 | E5: 2640.3 | F5: 2837.151 | G5: 9472.854 | H5: 10453.537 | J5: Verified | K5: 同上 | L5: 第二來源：未找到（年度服務占比 23%，10-K）
A6: 服務營收 | B6: 669.2 | C6: 702.559 | D6: =2305.5-774.8 -> 1530.7 | E6: 774.8 | F6: 820.405 | G6: 2683.308 | H6: 3125.939 | J6: Verified | K6: 同上 | L6: FY2026 10-K：服務約占營收 23%（3,125.9÷13,579.5＝23.0%）
A7: 事業別：半導體製程控制（含服務） | B7: 2738.8 | C7: 2877.647 | D7: =8988-3083.9 -> 5904.1 | E7: 3083.9 | F7: 3256.781 | G7: 10947.359 | H7: 12244.733 | J7: Verified | K7: 同上（事業別表） | L7: —
A8: 事業別：特殊半導體製程（SPTS） | B8: 156.5 | C8: 141.866 | D8: =424.4-164 -> 260.4 | E8: 164 | F8: 159.704 | G8: 587.107 | H8: 584.064 | J8: Verified | K8: 同上 | L8: —
A9: 事業別：PCB 與元件檢測 | B9: 168.6 | C9: 154.106 | D9: =509.3-167.6 -> 341.7 | E9: 167.6 | F9: 241.11 | G9: 621.721 | H9: 750.415 | J9: Verified | K9: 同上 | L9: —
A10: 匯率影響等（營收 − 三事業，Derived） | B10: =B4-B7-B8-B9 -> -0.9 | C10: =C4-C7-C8-C9 -> 1.122 | D10: =D4-D7-D8-D9 -> 0.6 | E10: =E4-E7-E8-E9 -> -0.4 | F10: =F4-F7-F8-F9 -> -0.039 | G10: =G4-G7-G8-G9 -> -0.025 | H10: =H4-H7-H8-H9 -> 0.264 | J10: Derived | K10: — | L10: 公司事業別表另列 FX；四捨五入差
A11: 半導體製程控制系統（產品營收 − SPTS − PCB；Derived） | B11: =B5-B8-B9 -> 2068.7 | C11: =C5-C8-C9 -> 2176.21 | D11: =D5-D8-D9 -> 4374 | E11: =E5-E8-E9 -> 2308.7 | F11: =F5-F8-F9 -> 2436.337 | G11: =G5-G8-G9 -> 8264.026 | H11: =H5-H8-H9 -> 9119.058 | J11: Derived | K11: 產品營收扣兩事業全部營收（其服務部分未揭露，故系統略為低估、與服務合計不變） | L11: 系統＋服務＋兩事業＝營收（恆等）
A12: SPTS＋PCB | B12: =B8+B9 -> 325.1 | C12: =C8+C9 -> 295.972 | D12: =D8+D9 -> 602.1 | E12: =E8+E9 -> 331.6 | F12: =F8+F9 -> 400.814 | G12: =G8+G9 -> 1208.828 | H12: =H8+H9 -> 1334.479 | J12: Derived | K12: — | L12: —
A13: 營業成本 | B13: 1175.7 | C13: 1207.286 | D13: =3842-1327.7 -> 2514.3 | E13: 1327.7 | F13: 1413.108 | G13: 4751.867 | H13: 5255.06 | J13: Verified | K13: 同上 | L13: —
A14: 毛利 | B14: =B4-B13 -> 1887.3 | C14: =C4-C13 -> 1967.455 | D14: =D4-D13 -> 3992.5 | E14: =E4-E13 -> 2087.4 | F14: =F4-F13 -> 2244.448 | G14: =G4-G13 -> 7404.295 | H14: =H4-H13 -> 8324.416 | J14: Derived | K14: — | L14: stockanalysis 年度毛利：FY2025 7,404、FY2026 8,324
A15: 毛利率（GAAP） | B15: =B14/B4 -> 0.61616063 | C15: =C14/C4 -> 0.61972142 | D15: =D14/D4 -> 0.61358886 | E15: =E14/E4 -> 0.61122661 | F15: =F14/F4 -> 0.61364693 | G15: =G14/G4 -> 0.60909809 | H15: =H14/H4 -> 0.61301452 | J15: Derived | K15: — | L15: 公司非 GAAP：FQ4-26 62.4%
A16: 研發費用 | B16: 338 | C16: 352.989 | D16: =1133.1-388.8 -> 744.3 | E16: 388.8 | F16: 399.023 | G16: 1360.334 | H16: 1532.118 | J16: Verified | K16: 同上 | L16: —
A17: 銷管費用 | B17: 248.9 | C17: 262.706 | D17: =840-291.1 -> 548.9 | E17: 291.1 | F17: 291.477 | G17: 1029.734 | H17: 1131.518 | J17: Verified | K17: 同上 | L17: 法說稱 FQ4-26 SG&A 283（非 GAAP）
A18: 商譽與無形資產減損 | B18: 0 | C18: 0 | D18: 0 | E18: 0 | F18: 0 | G18: 239.1 | H18: 0 | J18: Verified | K18: FY2025 減損 239.1（FQ3-26 新聞稿九個月欄、FQ4-26 新聞稿） | L18: —
A19: 營業費用（研發＋銷管；不含減損） | B19: =B16+B17 -> 586.9 | C19: =C16+C17 -> 615.695 | D19: =D16+D17 -> 1293.2 | E19: =E16+E17 -> 679.9 | F19: =F16+F17 -> 690.5 | G19: =G16+G17 -> 2390.068 | H19: =H16+H17 -> 2663.636 | J19: Derived | K19: — | L19: —
A20: 營業利益（毛利 − 營業費用 − 減損） | B20: =B14-B19-B18 -> 1300.4 | C20: =C14-C19-C18 -> 1351.76 | D20: =D14-D19-D18 -> 2699.3 | E20: =E14-E19-E18 -> 1407.5 | F20: =F14-F19-F18 -> 1553.948 | G20: =G14-G19-G18 -> 4775.127 | H20: =H14-H19-H18 -> 5660.78 | J20: Derived | K20: — | L20: stockanalysis 年度營業利益：FY2026 5,661（相符）；FY2025 5,014（不含減損）
A21: 營業外淨額（其他收入 − 利息） | G21: =171.487-302.166 -> -130.679 | H21: =229.585-284.44 -> -54.855 | J21: Verified | K21: FQ4-26 新聞稿（SEC 8-K，2026-07-28）：利息 FY25 302.2／FY26 284.4；其他收入 171.5／229.6 | L21: —
A22: 所得稅 | G22: 582.805 | H22: 775.154 | J22: Verified | K22: 同上 | L22: —
A23: 有效稅率 | G23: =G22/(G20+G21) -> 0.12548423 | H23: =H22/(H20+H21) -> 0.13827406 | J23: Derived | K23: — | L23: —
A24: 淨利（GAAP） | B24: 1088.4 | C24: 1202.849 | D24: =3467.7-1201 -> 2266.7 | E24: 1201 | F24: 1363.059 | G24: 4061.643 | H24: 4830.771 | J24: Verified | K24: 同上 | L24: stockanalysis：FY2025 4,062、FY2026 4,831
A25: 檢查：稅前 − 稅 − 淨利（年度，應約 0） | G25: =G20+G21-G22-G24 -> 0 | H25: =H20+H21-H22-H24 -> 0 | J25: — | K25: — | L25: —
A26: EPS（GAAP 稀釋，分割調整後） | B26: 0.816 | C26: 0.91 | D26: =(26.26-9.12)/10 -> 1.714 | E26: 0.912 | F26: 1.04 | G26: 3.04 | H26: 3.66 | J26: Verified／Derived | K26: FQ4-26 新聞稿（分割後）：FQ4-25 0.91、FY2025 3.04、FY2026 3.66、FQ4-26 1.04；FQ3-26 新聞稿（分割前 ÷10）：FQ3-25 8.16、FQ3-26 9.12、九個月 26.26 | L26: SEC XBRL（10-K）：FY2025 3.04、FY2026 3.66；stockanalysis 同
A27: 稀釋加權股數（百萬股，分割調整後） | B27: 1333 | C27: 1327.341 | E27: 1317.5 | F27: 1314.986 | G27: 1337.502 | H27: 1319.633 | J27: Verified | K27: FQ4-26 新聞稿（SEC 8-K，2026-07-28）；FQ3：分割前 133.30／131.75 ×10 | L27: —
A28: 檢查：FY2026 − (上半＋FQ3＋FQ4)（營收、產品、服務、淨利依序 B–E 欄） | B28: =H4-D4-E4-F4 -> 0.02 | C28: =H5-D5-E5-F5 -> -0.014 | D28: =H6-D6-E6-F6 -> 0.034 | E28: =H24-D24-E24-F24 -> 0.012 | J28: — | K28: 九個月與單季皆取新聞稿四捨五入值，差額為 0.1 以內的捨入差 | L28: —
A30: FQ1-27 公司指引（2026-07-28）
A31: 項目 | B31: 指引 | C31: 低 | D31: 高 | J31: 標記 | K31: 來源1（公司） | L31: 來源2／說明
A32: 營收（US$M） | B32: =g_q1_rev -> 4000 | C32: =g_q1_rev_lo -> 3800 | D32: =g_q1_rev_hi -> 4200 | J32: Interested-party | K32: FQ4-26 新聞稿（SEC 8-K，2026-07-28） | L32: 非 GAAP：毛利率 62.5%、EPS 1.16；稀釋股數 1,312M
A33: GAAP 毛利率 | B33: =g_q1_gm -> 0.616 | C33: =g_q1_gm_lo -> 0.606 | D33: =g_q1_gm_hi -> 0.626 | J33: Interested-party | K33: FQ4-26 新聞稿（SEC 8-K，2026-07-28） | L33: 非 GAAP：毛利率 62.5%、EPS 1.16；稀釋股數 1,312M
A34: GAAP 稀釋 EPS（US$） | B34: =g_q1_eps -> 1.14 | C34: =g_q1_eps_lo -> 1.04 | D34: =g_q1_eps_hi -> 1.24 | J34: Interested-party | K34: FQ4-26 新聞稿（SEC 8-K，2026-07-28） | L34: 非 GAAP：毛利率 62.5%、EPS 1.16；稀釋股數 1,312M

Sheet Units
A1: Units — 設備市場（十億美元，日曆年；讀 markets/equipment 成品三情境）與 KLA 日曆年實績（百萬美元；由 Q 頁各季加總）
A3: 項目 | B3: 單位 | C3: CY2025 | D3: CY2026 | E3: CY2027 | F3: CY2028 | G3: CY2029 | H3: 說明
A4: 情境 A：設備市場（markets/equipment 5A 區塊）
A5: 先進邏輯〔AI〕 | B5: US$B | C5: 36.032336 | D5: 50.324843 | E5: 60.776431 | F5: 70.016145 | G5: 74.209437 | H5: markets/equipment/dist/20261023_半導體設備市場模型_v0.1.3.xlsx｜Mkt!C120:G120
A6: 其他代工與邏輯 | B6: US$B | C6: 29.569009 | D6: 31.93453 | E6: 34.489292 | F6: 37.248436 | G6: 40.228311 | H6: markets/equipment/dist/20261023_半導體設備市場模型_v0.1.3.xlsx｜Mkt!C121:G121
A7: 其他前段（類比、功率、光罩等） | B7: US$B | C7: 12.746775 | D7: 17.027825 | E7: 21.022986 | F7: 23.621824 | G7: 24.960332 | H7: markets/equipment/dist/20261023_半導體設備市場模型_v0.1.3.xlsx｜Mkt!C124:G124
A8: 代工邏輯 WFE 小計（L） | B8: US$B | C8: =C5+C6+C7 -> 78.348121 | D8: =D5+D6+D7 -> 99.287198 | E8: =E5+E6+E7 -> 116.28871 | F8: =F5+F6+F7 -> 130.8864 | G8: =G5+G6+G7 -> 139.39808
A9: DRAM（含 HBM）〔AI〕 | B9: US$B | C9: 26.376109 | D9: 39.365947 | E9: 53.258733 | F9: 59.5609 | G9: 61.831293 | H9: markets/equipment/dist/20261023_半導體設備市場模型_v0.1.3.xlsx｜Mkt!C122:G122
A10: NAND | B10: US$B | C10: 12.172602 | D10: 17.503905 | E10: 23.248027 | F10: 26.181322 | G10: 27.674313 | H10: markets/equipment/dist/20261023_半導體設備市場模型_v0.1.3.xlsx｜Mkt!C123:G123
A11: 記憶體 WFE 小計（M） | B11: US$B | C11: =C9+C10 -> 38.548711 | D11: =D9+D10 -> 56.869852 | E11: =E9+E10 -> 76.50676 | F11: =F9+F10 -> 85.742221 | G11: =G9+G10 -> 89.505606
A12: 先進封裝〔AI〕 | B12: US$B | C12: 3.0565693 | D12: 3.35 | E12: 3.7953919 | F12: 4.3 | G12: 4.644 | H12: markets/equipment/dist/20261023_半導體設備市場模型_v0.1.3.xlsx｜Mkt!C125:G125
A13: 設備總額 | B13: US$B | C13: 134.68936 | D13: 178.15705 | E13: 218.22554 | F13: 246.02863 | G13: 260.65569 | H13: markets/equipment/dist/20261023_半導體設備市場模型_v0.1.3.xlsx｜Mkt!C129:G129
A15: 情境 B：設備市場（markets/equipment 5B 區塊）
A16: 先進邏輯〔AI〕 | B16: US$B | C16: 36.032336 | D16: 50.324843 | E16: 60.776431 | F16: 60.776431 | G16: 57.737609 | H16: markets/equipment/dist/20261023_半導體設備市場模型_v0.1.3.xlsx｜Mkt!C139:G139
A17: 其他代工與邏輯 | B17: US$B | C17: 29.569009 | D17: 31.93453 | E17: 34.489292 | F17: 34.489292 | G17: 32.764828 | H17: markets/equipment/dist/20261023_半導體設備市場模型_v0.1.3.xlsx｜Mkt!C140:G140
A18: 其他前段（類比、功率、光罩等） | B18: US$B | C18: 12.746775 | D18: 17.027825 | E18: 21.022986 | F18: 21.022986 | G18: 19.971837 | H18: markets/equipment/dist/20261023_半導體設備市場模型_v0.1.3.xlsx｜Mkt!C143:G143
A19: 代工邏輯 WFE 小計（L） | B19: US$B | C19: =C16+C17+C18 -> 78.348121 | D19: =D16+D17+D18 -> 99.287198 | E19: =E16+E17+E18 -> 116.28871 | F19: =F16+F17+F18 -> 116.28871 | G19: =G16+G17+G18 -> 110.47427
A20: DRAM（含 HBM）〔AI〕 | B20: US$B | C20: 26.376109 | D20: 39.365947 | E20: 53.258733 | F20: 53.258733 | G20: 50.595796 | H20: markets/equipment/dist/20261023_半導體設備市場模型_v0.1.3.xlsx｜Mkt!C141:G141
A21: NAND | B21: US$B | C21: 12.172602 | D21: 17.503905 | E21: 23.248027 | F21: 23.248027 | G21: 22.085626 | H21: markets/equipment/dist/20261023_半導體設備市場模型_v0.1.3.xlsx｜Mkt!C142:G142
A22: 記憶體 WFE 小計（M） | B22: US$B | C22: =C20+C21 -> 38.548711 | D22: =D20+D21 -> 56.869852 | E22: =E20+E21 -> 76.50676 | F22: =F20+F21 -> 76.50676 | G22: =G20+G21 -> 72.681422
A23: 先進封裝〔AI〕 | B23: US$B | C23: 3.0565693 | D23: 3.35 | E23: 3.7953919 | F23: 3.7953919 | G23: 3.6056223 | H23: markets/equipment/dist/20261023_半導體設備市場模型_v0.1.3.xlsx｜Mkt!C144:G144
A24: 設備總額 | B24: US$B | C24: 134.68936 | D24: 178.15705 | E24: 218.22554 | F24: 218.22554 | G24: 207.31426 | H24: markets/equipment/dist/20261023_半導體設備市場模型_v0.1.3.xlsx｜Mkt!C148:G148
A26: 情境 C：設備市場（markets/equipment 5C 區塊）
A27: 先進邏輯〔AI〕 | B27: US$B | C27: 36.032336 | D27: 50.324843 | E27: 60.776431 | F27: 48.621145 | G27: 48.621145 | H27: markets/equipment/dist/20261023_半導體設備市場模型_v0.1.3.xlsx｜Mkt!C158:G158
A28: 其他代工與邏輯 | B28: US$B | C28: 29.569009 | D28: 31.93453 | E28: 34.489292 | F28: 27.591434 | G28: 27.591434 | H28: markets/equipment/dist/20261023_半導體設備市場模型_v0.1.3.xlsx｜Mkt!C159:G159
A29: 其他前段（類比、功率、光罩等） | B29: US$B | C29: 12.746775 | D29: 17.027825 | E29: 21.022986 | F29: 16.818389 | G29: 16.818389 | H29: markets/equipment/dist/20261023_半導體設備市場模型_v0.1.3.xlsx｜Mkt!C162:G162
A30: 代工邏輯 WFE 小計（L） | B30: US$B | C30: =C27+C28+C29 -> 78.348121 | D30: =D27+D28+D29 -> 99.287198 | E30: =E27+E28+E29 -> 116.28871 | F30: =F27+F28+F29 -> 93.030967 | G30: =G27+G28+G29 -> 93.030967
A31: DRAM（含 HBM）〔AI〕 | B31: US$B | C31: 26.376109 | D31: 39.365947 | E31: 53.258733 | F31: 42.606986 | G31: 42.606986 | H31: markets/equipment/dist/20261023_半導體設備市場模型_v0.1.3.xlsx｜Mkt!C160:G160
A32: NAND | B32: US$B | C32: 12.172602 | D32: 17.503905 | E32: 23.248027 | F32: 18.598422 | G32: 18.598422 | H32: markets/equipment/dist/20261023_半導體設備市場模型_v0.1.3.xlsx｜Mkt!C161:G161
A33: 記憶體 WFE 小計（M） | B33: US$B | C33: =C31+C32 -> 38.548711 | D33: =D31+D32 -> 56.869852 | E33: =E31+E32 -> 76.50676 | F33: =F31+F32 -> 61.205408 | G33: =G31+G32 -> 61.205408
A34: 先進封裝〔AI〕 | B34: US$B | C34: 3.0565693 | D34: 3.35 | E34: 3.7953919 | F34: 3.0363136 | G34: 3.0363136 | H34: markets/equipment/dist/20261023_半導體設備市場模型_v0.1.3.xlsx｜Mkt!C163:G163
A35: 設備總額 | B35: US$B | C35: 134.68936 | D35: 178.15705 | E35: 218.22554 | F35: 174.58043 | G35: 174.58043 | H35: markets/equipment/dist/20261023_半導體設備市場模型_v0.1.3.xlsx｜Mkt!C167:G167
A37: SEMI 晶圓前段設備（WFE；對帳用） | B37: US$B | C37: 116.89683 | D37: 143.9 | E37: 175.2702 | F37: 199.9833 | G37: 215.98196 | H37: markets/equipment/dist/20261023_半導體設備市場模型_v0.1.3.xlsx｜Mkt!C44:G44（SEMI 2026-07；設備商協會，傾向樂觀）
A39: KLA 日曆年實績（百萬美元；CY2025＝FQ3-25＋FQ4-25＋FY26 上半；CY2026 上半＝FQ3-26＋FQ4-26）
A40: 項目 | B40: 單位 | C40: CY2025 | D40: CY2026 上半 | H40: 說明
A41: 營收 | B41: US$M | C41: =Q!B4+Q!C4+Q!D4 -> 12744.541 | D41: =Q!E4+Q!F4 -> 7072.656
A42: 產品 | B42: US$M | C42: =Q!B5+Q!C5+Q!D5 -> 9842.082 | D42: =Q!E5+Q!F5 -> 5477.451
A43: 服務 | B43: US$M | C43: =Q!B6+Q!C6+Q!D6 -> 2902.459 | D43: =Q!E6+Q!F6 -> 1595.205
A44: 半導體製程控制（事業別，含服務） | B44: US$M | C44: =Q!B7+Q!C7+Q!D7 -> 11520.547 | D44: =Q!E7+Q!F7 -> 6340.681
A45: SPTS＋PCB | B45: US$M | C45: =Q!B12+Q!C12+Q!D12 -> 1223.172 | D45: =Q!E12+Q!F12 -> 732.414
A46: 半導體製程控制系統（產品 − SPTS − PCB） | B46: US$M | C46: =Q!B11+Q!C11+Q!D11 -> 8618.91 | D46: =Q!E11+Q!F11 -> 4745.037
A47: CY2025 半導體製程控制營收 ÷ 公司 WFE（s25） | B47: % | C47: =cy25_spc/(kla_wfe25*1000) -> 0.096004558 | H47: pc_u（強度年增）的基期；公司稱 2030 年較 2025 提升 150bp
A49: KLA 會計年度與日曆年：FY(t)＝CY(t−1) 下半＋CY(t) 上半。CY2027 起每年上下半各 1/2（Assumed，忽略年內斜率）；CY2026 的下半＝錨點 − 上半實績。

Sheet PL
A1: PL — KLA 損益（US$M；EPS 為美元）。FY2025、FY2026 為實績，FY2027–FY2029 為模型。三情境各一個完整推導區塊（見下方），本頁頂端為摘要
A3: 情境／項目 | B3: 單位 | C3: FY2025A | D3: FY2026A | E3: FY2027 | F3: FY2028 | G3: FY2029 | H3: 說明
A4: 情境 A | H4: 情境 A：設備市場續增（2029 見頂）
A5: 營收 | B5: US$M | C5: =C62 -> 12156.162 | D5: =D62 -> 13579.476 | E5: =E62 -> 17888.415 | F5: =F62 -> 20543.783 | G5: =G62 -> 23222.763
A6: 半導體製程控制系統 | B6: US$M | C6: =C59 -> 8264.026 | D6: =D59 -> 9119.058 | E6: =E59 -> 12830.228 | F6: =F59 -> 14807.342 | G6: =G59 -> 16716.7
A7: 服務 | B7: US$M | C7: =C60 -> 2683.308 | D7: =D60 -> 3125.939 | E7: =E60 -> 3563.5705 | F7: =F60 -> 4062.4703 | G7: =G60 -> 4631.2162
A8: SPTS＋PCB | B8: US$M | C8: =C61 -> 1208.828 | D8: =D61 -> 1334.479 | E8: =E61 -> 1494.6165 | F8: =F61 -> 1673.9705 | G8: =G61 -> 1874.8469
A9: 毛利率 | B9: % | C9: =C64 -> 0.60909809 | D9: =D64 -> 0.61301452 | E9: =E64 -> 0.62107175 | F9: =F64 -> 0.62435378 | G9: =G64 -> 0.62690439
A10: 營業利益 | B10: US$M | C10: =C66 -> 4775.127 | D10: =D66 -> 5660.78 | E10: =E66 -> 8244.989 | F10: =F66 -> 9732.3884 | G10: =G66 -> 11216.716
A11: 營業利益率 | B11: % | C11: =C67 -> 0.39281535 | D11: =D67 -> 0.41686292 | E11: =E67 -> 0.46091222 | F11: =F67 -> 0.47373887 | G11: =G67 -> 0.48300524
A12: 淨利 | B12: US$M | C12: =C69 -> 4061.643 | D12: =D69 -> 4830.771 | E12: =E69 -> 6963.9656 | F12: =F69 -> 8235.6921 | G12: =G69 -> 9504.7924
A13: EPS（GAAP 稀釋） | B13: US$ | C13: =C71 -> 3.04 | D13: =D71 -> 3.66 | E13: =E71 -> 5.3079006 | F13: =F71 -> 6.3622032 | G13: =G71 -> 7.4420288
A15: 情境 B | H15: 情境 B：設備市場 2028 持平、2029 −5%
A16: 營收 | B16: US$M | C16: =C92 -> 12156.162 | D16: =D92 -> 13579.476 | E16: =E92 -> 17772.517 | F16: =F92 -> 19319.452 | G16: =G92 -> 19886.604
A17: 半導體製程控制系統 | B17: US$M | C17: =C89 -> 8264.026 | D17: =D89 -> 9119.058 | E17: =E89 -> 12830.228 | F17: =F89 -> 13841.738 | G17: =G89 -> 13813.826
A18: 服務 | B18: US$M | C18: =C90 -> 2683.308 | D18: =D90 -> 3125.939 | E18: =E90 -> 3501.0517 | F18: =F90 -> 3921.1779 | G18: =G90 -> 4391.7192
A19: SPTS＋PCB | B19: US$M | C19: =C91 -> 1208.828 | D19: =D91 -> 1334.479 | E19: =E91 -> 1441.2373 | F19: =F91 -> 1556.5363 | G19: =G91 -> 1681.0592
A20: 毛利率 | B20: % | C20: =C94 -> 0.60909809 | D20: =D94 -> 0.61301452 | E20: =E94 -> 0.62090616 | F20: =F94 -> 0.6229526 | G20: =G94 -> 0.62362312
A21: 營業利益 | B21: US$M | C21: =C96 -> 4775.127 | D21: =D96 -> 5660.78 | E21: =E96 -> 8170.0652 | F21: =F96 -> 9026.8527 | G21: =G96 -> 9243.0836
A22: 營業利益率 | B22: % | C22: =C97 -> 0.39281535 | D22: =D97 -> 0.41686292 | E22: =E97 -> 0.4597022 | F22: =F97 -> 0.46724166 | G22: =G97 -> 0.46478944
A23: 淨利 | B23: US$M | C23: =C99 -> 4061.643 | D23: =D99 -> 4830.771 | E23: =E99 -> 6899.9057 | F23: =F99 -> 7632.4591 | G23: =G99 -> 7817.3364
A24: EPS（GAAP 稀釋） | B24: US$ | C24: =C101 -> 3.04 | D24: =D101 -> 3.66 | E24: =E101 -> 5.2590745 | F24: =F101 -> 5.8961961 | G24: =G101 -> 6.1207905
A26: 情境 C | H26: 情境 C：設備市場 2028 −20%（2027 見頂）
A27: 營收 | B27: US$M | C27: =C122 -> 12156.162 | D27: =D122 -> 13579.476 | E27: =E122 -> 17603.24 | F27: =F122 -> 17417.108 | G27: =G122 -> 16583.406
A28: 半導體製程控制系統 | B28: US$M | C28: =C119 -> 8264.026 | D28: =D119 -> 9119.058 | E28: =E119 -> 12830.228 | F28: =F119 -> 12300.242 | G28: =G119 -> 11088.302
A29: 服務 | B29: US$M | C29: =C120 -> 2683.308 | D29: =D120 -> 3125.939 | E29: =E120 -> 3438.5329 | F29: =F120 -> 3782.3862 | G29: =G120 -> 4160.6248
A30: SPTS＋PCB | B30: US$M | C30: =C121 -> 1208.828 | D30: =D121 -> 1334.479 | E30: =E121 -> 1334.479 | F30: =F121 -> 1334.479 | G30: =G121 -> 1334.479
A31: 毛利率 | B31: % | C31: =C124 -> 0.60909809 | D31: =D124 -> 0.61301452 | E31: =E124 -> 0.62066039 | F31: =F124 -> 0.62038464 | G31: =G124 -> 0.61907355
A32: 營業利益 | B32: US$M | C32: =C126 -> 4775.127 | D32: =D126 -> 5660.78 | E32: =E126 -> 8060.6336 | F32: =F126 -> 7883.0059 | G32: =G126 -> 7285.602
A33: 營業利益率 | B33: % | C33: =C127 -> 0.39281535 | D33: =D127 -> 0.41686292 | E33: =E127 -> 0.45790626 | F33: =F127 -> 0.45260132 | G33: =G127 -> 0.43933086
A34: 淨利 | B34: US$M | C34: =C129 -> 4061.643 | D34: =D129 -> 4830.771 | E34: =E129 -> 6806.3418 | F34: =F129 -> 6654.47 | G34: =G129 -> 6143.6897
A35: EPS（GAAP 稀釋） | B35: US$ | C35: =C131 -> 3.04 | D35: =D131 -> 3.66 | E35: =E131 -> 5.1877605 | F35: =F131 -> 5.140684 | G35: =G131 -> 4.8103645
A37: 核對：FY2025、FY2026 模型營收 − 實績（應為 0）
A38: 情境 A | C38: =ABS(C5-a25_rev)+ABS(D5-a26_rev) -> 0
A39: 情境 B | C39: =ABS(C16-a25_rev)+ABS(D16-a26_rev) -> 0
A40: 情境 C | C40: =ABS(C27-a25_rev)+ABS(D27-a26_rev) -> 0
A45: 情境 A：設備市場續增（2029 見頂）
A46: 項目 | B46: 單位 | C46: CY2025／FY2025A | D46: CY2026／FY2026A | E46: CY2027／FY2027 | F46: CY2028／FY2028 | G46: CY2029／FY2029 | H46: 說明
A47: A. 日曆年（C＝CY2025 … G＝CY2029）
A48: 加權前段 WFE（代工邏輯＋m × 記憶體） | B48: US$M | C48: =(Units!C8+m_mem*Units!C11)*1000 -> 117874.06 | D48: =(Units!D8+m_mem*Units!D11)*1000 -> 157598.73 | E48: =(Units!E8+m_mem*Units!E11)*1000 -> 194734.95 | F48: =(Units!F8+m_mem*Units!F11)*1000 -> 218802.23 | G48: =(Units!G8+m_mem*Units!G11)*1000 -> 231172.69 | H48: 設備模型情境 A；m＝記憶體相對強度
A49: 先進封裝設備市場 | B49: US$M | C49: =Units!C12*1000 -> 3056.5693 | D49: =Units!D12*1000 -> 3350 | E49: =Units!E12*1000 -> 3795.3919 | F49: =Units!F12*1000 -> 4300 | G49: =Units!G12*1000 -> 4644
A50: 營收 CY2026 錨點（上半實績 ×（2＋下半增幅）） | B50: US$M | D50: =h1_rev*(2+h2up) -> 15559.843 | H50: 上半實績＋公司說法（下半約高 20%）
A51: 服務 CY2026 錨點 | B51: US$M | D51: =h1_svc*(2+g_svc_h2) -> 3286.1223
A52: SPTS＋PCB CY2026 錨點 | B52: US$M | D52: =cy25_oth*(1+g_oth26) -> 1528.965
A53: 先進封裝製程控制系統營收 | B53: US$M | C53: =ap26/(1+ap_g26) -> 647.05882 | D53: =ap26 -> 1100 | E53: =D53*(1+k_ap*(E49/D49-1)) -> 1392.4962 | F53: =E53*(1+k_ap*(F49/E49-1)) -> 1762.7688 | G53: =F53*(1+k_ap*(G49/F49-1)) -> 2044.8118 | H53: CY2027 起：前一年 ×（1＋k × 封裝設備市場成長）
A54: 前段製程控制系統營收 | B54: US$M | C54: =C56-C53 -> 7971.8512 | D54: =D56-D53 -> 9644.7559 | E54: =E55*E48 -> 12268.522 | F54: =F55*F48 -> 14190.898 | G54: =G55*G48 -> 15434.922 | H54: CY2025／2026＝系統 − 先進封裝；之後＝強度 × 加權 WFE
A55: 製程控制強度（前段系統 ÷ 加權前段 WFE） | B55: % | C55: =C54/C48 -> 0.067630242 | D55: =D54/D48 -> 0.061198184 | E55: =$D55*(1+pc_u)^1 -> 0.063001128 | F55: =$D55*(1+pc_u)^2 -> 0.064857188 | G55: =$D55*(1+pc_u)^3 -> 0.06676793 | H55: CY2026 校準；之後每年 ×（1＋pc_u）
A56: 半導體製程控制系統營收 CY | B56: US$M | C56: =cy25_sys -> 8618.91 | D56: =D50-D51-D52 -> 10744.756 | E56: =(E54+E53)*(1-chn_sh26*chn_cut) -> 13661.018 | F56: =(F54+F53)*(1-chn_sh26*chn_cut) -> 15953.666 | G56: =(G54+G53)*(1-chn_sh26*chn_cut) -> 17479.734 | H56: CY2026＝錨點 − 服務 − 兩事業；CY2027 起 ×（1 − 中國占比 × 中國下降比例）
A57: 顯示：製程控制占前段 WFE（強度 ÷ KLA 市占） | B57: % | C57: =C55/kla_sh_pc -> 0.11660387 | D57: =D55/kla_sh_pc -> 0.10551411 | E57: =E55/kla_sh_pc -> 0.10862263 | F57: =F55/kla_sh_pc -> 0.11182274 | G57: =G55/kla_sh_pc -> 0.11511712 | H57: KLA 市占 58% 為賣方數字，只供顯示
A58: B. 會計年度（C＝FY2025A … G＝FY2029；FY(t)＝CY(t−1) 下半＋CY(t) 上半）
A59: 半導體製程控制系統營收 FY | B59: US$M | C59: =a25_sys -> 8264.026 | D59: =a26_sys -> 9119.058 | E59: =(D56-h1_sys)+0.5*E56 -> 12830.228 | F59: =0.5*E56+0.5*F56 -> 14807.342 | G59: =0.5*F56+0.5*G56 -> 16716.7 | H59: FY2027＝CY2026 下半（錨點 − 上半實績）＋1/2 CY2027
A60: 服務營收 | B60: US$M | C60: =a25_svc -> 2683.308 | D60: =a26_svc -> 3125.939 | E60: =D60*(1+g_svc_A) -> 3563.5705 | F60: =E60*(1+g_svc_A) -> 4062.4703 | G60: =F60*(1+g_svc_A) -> 4631.2162
A61: SPTS＋PCB 營收 | B61: US$M | C61: =a25_oth -> 1208.828 | D61: =a26_oth -> 1334.479 | E61: =D61*(1+g_oth_A) -> 1494.6165 | F61: =E61*(1+g_oth_A) -> 1673.9705 | G61: =F61*(1+g_oth_A) -> 1874.8469
A62: 營收 | B62: US$M | C62: =C59+C60+C61 -> 12156.162 | D62: =D59+D60+D61 -> 13579.476 | E62: =E59+E60+E61 -> 17888.415 | F62: =F59+F60+F61 -> 20543.783 | G62: =G59+G60+G61 -> 23222.763 | H62: FY2025、FY2026＝實績（恆等）
A63: 毛利 | B63: US$M | C63: =a25_gp -> 7404.295 | D63: =a26_gp -> 8324.416 | E63: =a26_gp+gm_inc*(E62-a26_rev) -> 11109.989 | F63: =a26_gp+gm_inc*(F62-a26_rev) -> 12826.588 | G63: =a26_gp+gm_inc*(G62-a26_rev) -> 14558.452 | H63: FY2026 毛利＋增量毛利率 ×（營收 − FY2026 營收）
A64: 毛利率 | B64: % | C64: =C63/C62 -> 0.60909809 | D64: =D63/D62 -> 0.61301452 | E64: =E63/E62 -> 0.62107175 | F64: =F63/F62 -> 0.62435378 | G64: =G63/G62 -> 0.62690439
A65: 營業費用（研發＋銷管） | B65: US$M | C65: =a25_opx -> 2390.068 | D65: =a26_opx -> 2663.636 | E65: =opex27 -> 2865 | F65: =E65*(1+g_opex_A) -> 3094.2 | G65: =F65*(1+g_opex_A) -> 3341.736
A66: 營業利益 | B66: US$M | C66: =a25_oi -> 4775.127 | D66: =D63-D65 -> 5660.78 | E66: =E63-E65 -> 8244.989 | F66: =F63-F65 -> 9732.3884 | G66: =G63-G65 -> 11216.716 | H66: FY2025 含減損 239.1
A67: 營業利益率 | B67: % | C67: =C66/C62 -> 0.39281535 | D67: =D66/D62 -> 0.41686292 | E67: =E66/E62 -> 0.46091222 | F67: =F66/F62 -> 0.47373887 | G67: =G66/G62 -> 0.48300524
A68: 營業外淨額 | B68: US$M | C68: =a25_nonop -> -130.679 | D68: =a26_nonop -> -54.855 | E68: =oth_exp -> -100 | F68: =oth_exp -> -100 | G68: =oth_exp -> -100
A69: 淨利 | B69: US$M | C69: =a25_ni -> 4061.643 | D69: =a26_ni -> 4830.771 | E69: =(E66+E68)*(1-tax) -> 6963.9656 | F69: =(F66+F68)*(1-tax) -> 8235.6921 | G69: =(G66+G68)*(1-tax) -> 9504.7924
A70: 稀釋股數 | B70: 百萬股 | C70: =a25_sh -> 1337.502 | D70: =a26_sh -> 1319.633 | E70: =shares27 -> 1312 | F70: =E70*(1-bb) -> 1294.4717 | G70: =F70*(1-bb) -> 1277.1776
A71: EPS（GAAP 稀釋） | B71: US$ | C71: =a25_eps -> 3.04 | D71: =a26_eps -> 3.66 | E71: =E69/E70 -> 5.3079006 | F71: =F69/F70 -> 6.3622032 | G71: =G69/G70 -> 7.4420288
A72: 顯示：中國營收（× FY2026 中國占比；CY2027 起扣下降） | B72: US$M | D72: =a26_rev*chn_sh26 -> 4073.8428 | E72: =E62*chn_sh26*(1-chn_cut*IF(2027=2027,0.5,1)) -> 5366.5244 | F72: =F62*chn_sh26*(1-chn_cut*IF(2028=2027,0.5,1)) -> 6163.1348 | G72: =G62*chn_sh26*(1-chn_cut*IF(2029=2027,0.5,1)) -> 6966.829 | H72: 只供顯示
A75: 情境 B：設備市場 2028 持平、2029 −5%
A76: 項目 | B76: 單位 | C76: CY2025／FY2025A | D76: CY2026／FY2026A | E76: CY2027／FY2027 | F76: CY2028／FY2028 | G76: CY2029／FY2029 | H76: 說明
A77: A. 日曆年（C＝CY2025 … G＝CY2029）
A78: 加權前段 WFE（代工邏輯＋m × 記憶體） | B78: US$M | C78: =(Units!C19+m_mem*Units!C22)*1000 -> 117874.06 | D78: =(Units!D19+m_mem*Units!D22)*1000 -> 157598.73 | E78: =(Units!E19+m_mem*Units!E22)*1000 -> 194734.95 | F78: =(Units!F19+m_mem*Units!F22)*1000 -> 194734.95 | G78: =(Units!G19+m_mem*Units!G22)*1000 -> 184998.2 | H78: 設備模型情境 B；m＝記憶體相對強度
A79: 先進封裝設備市場 | B79: US$M | C79: =Units!C23*1000 -> 3056.5693 | D79: =Units!D23*1000 -> 3350 | E79: =Units!E23*1000 -> 3795.3919 | F79: =Units!F23*1000 -> 3795.3919 | G79: =Units!G23*1000 -> 3605.6223
A80: 營收 CY2026 錨點（上半實績 ×（2＋下半增幅）） | B80: US$M | D80: =h1_rev*(2+h2up) -> 15559.843 | H80: 上半實績＋公司說法（下半約高 20%）
A81: 服務 CY2026 錨點 | B81: US$M | D81: =h1_svc*(2+g_svc_h2) -> 3286.1223
A82: SPTS＋PCB CY2026 錨點 | B82: US$M | D82: =cy25_oth*(1+g_oth26) -> 1528.965
A83: 先進封裝製程控制系統營收 | B83: US$M | C83: =ap26/(1+ap_g26) -> 647.05882 | D83: =ap26 -> 1100 | E83: =D83*(1+k_ap*(E79/D79-1)) -> 1392.4962 | F83: =E83*(1+k_ap*(F79/E79-1)) -> 1392.4962 | G83: =F83*(1+k_ap*(G79/F79-1)) -> 1253.2466 | H83: CY2027 起：前一年 ×（1＋k × 封裝設備市場成長）
A84: 前段製程控制系統營收 | B84: US$M | C84: =C86-C83 -> 7971.8512 | D84: =D86-D83 -> 9644.7559 | E84: =E85*E78 -> 12268.522 | F84: =F85*F78 -> 12629.961 | G84: =G85*G78 -> 12351.947 | H84: CY2025／2026＝系統 − 先進封裝；之後＝強度 × 加權 WFE
A85: 製程控制強度（前段系統 ÷ 加權前段 WFE） | B85: % | C85: =C84/C78 -> 0.067630242 | D85: =D84/D78 -> 0.061198184 | E85: =$D85*(1+pc_u)^1 -> 0.063001128 | F85: =$D85*(1+pc_u)^2 -> 0.064857188 | G85: =$D85*(1+pc_u)^3 -> 0.06676793 | H85: CY2026 校準；之後每年 ×（1＋pc_u）
A86: 半導體製程控制系統營收 CY | B86: US$M | C86: =cy25_sys -> 8618.91 | D86: =D80-D81-D82 -> 10744.756 | E86: =(E84+E83)*(1-chn_sh26*chn_cut) -> 13661.018 | F86: =(F84+F83)*(1-chn_sh26*chn_cut) -> 14022.458 | G86: =(G84+G83)*(1-chn_sh26*chn_cut) -> 13605.194 | H86: CY2026＝錨點 − 服務 − 兩事業；CY2027 起 ×（1 − 中國占比 × 中國下降比例）
A87: 顯示：製程控制占前段 WFE（強度 ÷ KLA 市占） | B87: % | C87: =C85/kla_sh_pc -> 0.11660387 | D87: =D85/kla_sh_pc -> 0.10551411 | E87: =E85/kla_sh_pc -> 0.10862263 | F87: =F85/kla_sh_pc -> 0.11182274 | G87: =G85/kla_sh_pc -> 0.11511712 | H87: KLA 市占 58% 為賣方數字，只供顯示
A88: B. 會計年度（C＝FY2025A … G＝FY2029；FY(t)＝CY(t−1) 下半＋CY(t) 上半）
A89: 半導體製程控制系統營收 FY | B89: US$M | C89: =a25_sys -> 8264.026 | D89: =a26_sys -> 9119.058 | E89: =(D86-h1_sys)+0.5*E86 -> 12830.228 | F89: =0.5*E86+0.5*F86 -> 13841.738 | G89: =0.5*F86+0.5*G86 -> 13813.826 | H89: FY2027＝CY2026 下半（錨點 − 上半實績）＋1/2 CY2027
A90: 服務營收 | B90: US$M | C90: =a25_svc -> 2683.308 | D90: =a26_svc -> 3125.939 | E90: =D90*(1+g_svc_B) -> 3501.0517 | F90: =E90*(1+g_svc_B) -> 3921.1779 | G90: =F90*(1+g_svc_B) -> 4391.7192
A91: SPTS＋PCB 營收 | B91: US$M | C91: =a25_oth -> 1208.828 | D91: =a26_oth -> 1334.479 | E91: =D91*(1+g_oth_B) -> 1441.2373 | F91: =E91*(1+g_oth_B) -> 1556.5363 | G91: =F91*(1+g_oth_B) -> 1681.0592
A92: 營收 | B92: US$M | C92: =C89+C90+C91 -> 12156.162 | D92: =D89+D90+D91 -> 13579.476 | E92: =E89+E90+E91 -> 17772.517 | F92: =F89+F90+F91 -> 19319.452 | G92: =G89+G90+G91 -> 19886.604 | H92: FY2025、FY2026＝實績（恆等）
A93: 毛利 | B93: US$M | C93: =a25_gp -> 7404.295 | D93: =a26_gp -> 8324.416 | E93: =a26_gp+gm_inc*(E92-a26_rev) -> 11035.065 | F93: =a26_gp+gm_inc*(F92-a26_rev) -> 12035.103 | G93: =a26_gp+gm_inc*(G92-a26_rev) -> 12401.746 | H93: FY2026 毛利＋增量毛利率 ×（營收 − FY2026 營收）
A94: 毛利率 | B94: % | C94: =C93/C92 -> 0.60909809 | D94: =D93/D92 -> 0.61301452 | E94: =E93/E92 -> 0.62090616 | F94: =F93/F92 -> 0.6229526 | G94: =G93/G92 -> 0.62362312
A95: 營業費用（研發＋銷管） | B95: US$M | C95: =a25_opx -> 2390.068 | D95: =a26_opx -> 2663.636 | E95: =opex27 -> 2865 | F95: =E95*(1+g_opex_B) -> 3008.25 | G95: =F95*(1+g_opex_B) -> 3158.6625
A96: 營業利益 | B96: US$M | C96: =a25_oi -> 4775.127 | D96: =D93-D95 -> 5660.78 | E96: =E93-E95 -> 8170.0652 | F96: =F93-F95 -> 9026.8527 | G96: =G93-G95 -> 9243.0836 | H96: FY2025 含減損 239.1
A97: 營業利益率 | B97: % | C97: =C96/C92 -> 0.39281535 | D97: =D96/D92 -> 0.41686292 | E97: =E96/E92 -> 0.4597022 | F97: =F96/F92 -> 0.46724166 | G97: =G96/G92 -> 0.46478944
A98: 營業外淨額 | B98: US$M | C98: =a25_nonop -> -130.679 | D98: =a26_nonop -> -54.855 | E98: =oth_exp -> -100 | F98: =oth_exp -> -100 | G98: =oth_exp -> -100
A99: 淨利 | B99: US$M | C99: =a25_ni -> 4061.643 | D99: =a26_ni -> 4830.771 | E99: =(E96+E98)*(1-tax) -> 6899.9057 | F99: =(F96+F98)*(1-tax) -> 7632.4591 | G99: =(G96+G98)*(1-tax) -> 7817.3364
A100: 稀釋股數 | B100: 百萬股 | C100: =a25_sh -> 1337.502 | D100: =a26_sh -> 1319.633 | E100: =shares27 -> 1312 | F100: =E100*(1-bb) -> 1294.4717 | G100: =F100*(1-bb) -> 1277.1776
A101: EPS（GAAP 稀釋） | B101: US$ | C101: =a25_eps -> 3.04 | D101: =a26_eps -> 3.66 | E101: =E99/E100 -> 5.2590745 | F101: =F99/F100 -> 5.8961961 | G101: =G99/G100 -> 6.1207905
A102: 顯示：中國營收（× FY2026 中國占比；CY2027 起扣下降） | B102: US$M | D102: =a26_rev*chn_sh26 -> 4073.8428 | E102: =E92*chn_sh26*(1-chn_cut*IF(2027=2027,0.5,1)) -> 5331.755 | F102: =F92*chn_sh26*(1-chn_cut*IF(2028=2027,0.5,1)) -> 5795.8356 | G102: =G92*chn_sh26*(1-chn_cut*IF(2029=2027,0.5,1)) -> 5965.9812 | H102: 只供顯示
A105: 情境 C：設備市場 2028 −20%（2027 見頂）
A106: 項目 | B106: 單位 | C106: CY2025／FY2025A | D106: CY2026／FY2026A | E106: CY2027／FY2027 | F106: CY2028／FY2028 | G106: CY2029／FY2029 | H106: 說明
A107: A. 日曆年（C＝CY2025 … G＝CY2029）
A108: 加權前段 WFE（代工邏輯＋m × 記憶體） | B108: US$M | C108: =(Units!C30+m_mem*Units!C33)*1000 -> 117874.06 | D108: =(Units!D30+m_mem*Units!D33)*1000 -> 157598.73 | E108: =(Units!E30+m_mem*Units!E33)*1000 -> 194734.95 | F108: =(Units!F30+m_mem*Units!F33)*1000 -> 155787.96 | G108: =(Units!G30+m_mem*Units!G33)*1000 -> 155787.96 | H108: 設備模型情境 C；m＝記憶體相對強度
A109: 先進封裝設備市場 | B109: US$M | C109: =Units!C34*1000 -> 3056.5693 | D109: =Units!D34*1000 -> 3350 | E109: =Units!E34*1000 -> 3795.3919 | F109: =Units!F34*1000 -> 3036.3136 | G109: =Units!G34*1000 -> 3036.3136
A110: 營收 CY2026 錨點（上半實績 ×（2＋下半增幅）） | B110: US$M | D110: =h1_rev*(2+h2up) -> 15559.843 | H110: 上半實績＋公司說法（下半約高 20%）
A111: 服務 CY2026 錨點 | B111: US$M | D111: =h1_svc*(2+g_svc_h2) -> 3286.1223
A112: SPTS＋PCB CY2026 錨點 | B112: US$M | D112: =cy25_oth*(1+g_oth26) -> 1528.965
...

Sheet Val
A1: Val — P/E 估值。跨公司規則：合理倍數＝10 年（2016–2025 年底）P/E 的分位，依循環位置：見頂年 25 分位、中段中位數、谷底 75 分位。循環位置依設備股共用規則（第 4 節）。EPS 一律 GAAP 稀釋
A2: P/E 定義（自算）：日曆年底收盤價 ÷ 「當期會計年度」GAAP 稀釋 EPS（年底所在會計年度，例如 2025-12 對 FY2026＝2026-06 期）；另列「前期」（上一個已結束會計年度）。價格與 EPS 皆為 2026-06 的 10 比 1 分割調整後
A3: 目標價（DCF 與 Comparable 加權）：見本頁第 94 列起「0. 目標價」（估值 v2 新增，放在既有內容之後以免位移既有列）；原「0. 目標價與上檔空間」改名為「舊法：規則值情境加權（參考）」
A4: 舊法：規則值情境加權（參考）
A5: 項目 | B5: 數值 | C5: 說明
A6: 規則值情境加權價（12 個月；參考） | B6: =tp_wA*B8+tp_wB*B9+tp_wC*B10 -> 102.08226 | C6: 權重 × 各情境隱含價
A7: 相對現價（規則值情境加權價 ÷ 現價 − 1） | B7: =B6/px-1 -> -0.29893371 | C7: 現價見第 6 節
A8: 情境 A 隱含價（樂觀） | B8: =F62 -> 106.75188 | C8: 第 5 節規則值（設備市場續增）
A9: 情境 B 隱含價（基準） | B9: =F69 -> 105.76989 | C9: 第 5 節規則值（設備市場 2028 持平）
A10: 情境 C 隱含價（下檔） | B10: =F76 -> 85.85876 | C10: 第 5 節規則值（設備市場 2028 −20%）
A11: 情境權重 A／B／C | B11: =tp_wA -> 0.3 | C11: =tp_wB -> 0.5 | D11: =tp_wC -> 0.2
A12: 規則值方法 | B12: P/E 規則值：FY2027（2027-06 期）GAAP 稀釋 EPS × 2016–2025 年底當期 P/E 依循環位置取分位（A、B 中段＝中位數，C 見頂＝25 分位；設備股共用規則）。十年倍數含 AI 前（2016–2018）低倍數期，偏誤方向為偏低（壓低目標價）；照規則計算，未另換倍數
A13: 檢查：權重合計（應為 100%） | B13: =tp_wA+tp_wB+tp_wC -> 1
A16: 1. 公司公布 EPS（會計年度，GAAP 稀釋，美元，分割調整後）— 兩個來源
A17: 會計年度（6 月結束） | B17: 來源1：SEC XBRL（10-K；分割前 ÷10） | C17: 來源2：macrotrends（6 月 TTM，÷10） | D17: 兩者差距 | E17: 標記 | F17: 說明
A18: FY2016（2016-06） | B18: 0.449 | C18: 0.449 | D18: =B18/C18-1 -> 0 | E18: Verified | F18: SEC companyconcept EarningsPerShareDiluted（10-K 年度值）
A19: FY2017（2017-06） | B19: 0.588 | C19: 0.588 | D19: =B19/C19-1 -> 0 | E19: Verified | F19: SEC companyconcept EarningsPerShareDiluted（10-K 年度值）
A20: FY2018（2018-06） | B20: 0.51 | C20: 0.51 | D20: =B20/C20-1 -> 0 | E20: Verified | F20: 美國稅改一次性費用使 FY2018 偏低
A21: FY2019（2019-06） | B21: 0.749 | C21: 0.749 | D21: =B21/C21-1 -> 0 | E21: Verified | F21: SEC companyconcept EarningsPerShareDiluted（10-K 年度值）
A22: FY2020（2020-06） | B22: 0.77 | C22: 0.77 | D22: =B22/C22-1 -> 0 | E22: Verified | F22: SEC companyconcept EarningsPerShareDiluted（10-K 年度值）
A23: FY2021（2021-06） | B23: 1.337 | C23: 1.337 | D23: =B23/C23-1 -> 0 | E23: Verified | F23: SEC companyconcept EarningsPerShareDiluted（10-K 年度值）
A24: FY2022（2022-06） | B24: 2.192 | C24: 2.192 | D24: =B24/C24-1 -> 0 | E24: Verified | F24: SEC companyconcept EarningsPerShareDiluted（10-K 年度值）
A25: FY2023（2023-06） | B25: 2.415 | C25: 2.415 | D25: =B25/C25-1 -> 0 | E25: Verified | F25: SEC companyconcept EarningsPerShareDiluted（10-K 年度值）
A26: FY2024（2024-06） | B26: 2.03 | C26: 2.028 | D26: =B26/C26-1 -> 0.00098619329 | E26: Verified | F26: SEC 為 FY2026 10-K 重編的分割後 2.03（分割前 20.28）
A27: FY2025（2025-06） | B27: 3.04 | C27: 3.037 | D27: =B27/C27-1 -> 0.00098781692 | E27: Verified | F27: 分割前 30.37
A28: FY2026（2026-06） | B28: 3.66 | C28: 3.66 | D28: =B28/C28-1 -> 0 | E28: Verified | F28: 來源2 為 stockanalysis（macrotrends 2026-06 列異常，未用）；Q 頁
A29: FY2026 EPS 改由 Q 頁實績帶入第 2 節（＝a26_eps）；其餘年度用來源1。兩來源差距皆來自四捨五入
A30: 2. 10 年 P/E（年底）
A31: 年底 | B31: 收盤價 US$（分割調整） | C31: 當期 FY EPS | D31: 前期 FY EPS | E31: P/E 當期（自算） | F31: P/E 前期（自算） | G31: macrotrends TTM P/E | H31: 自算當期 − macrotrends | I31: 收盤價來源2：macrotrends（÷10，含股利調整） | J31: 標記 | K31: 來源／說明
A32: 2016-12 | B32: =78.68/10 -> 7.868 | C32: =B19 -> 0.588 | D32: =B18 -> 0.449 | E32: =B32/C32 -> 13.380952 | F32: =B32/D32 -> 17.523385 | G32: 14.09 | H32: =E32-G32 -> -0.70904762 | I32: =77.51/10 -> 7.751 | J32: Verified／Derived | K32: 收盤價：digrin「Real price」（未調整）12 月收盤 ÷10
A33: 2017-12 | B33: =105.07/10 -> 10.507 | C33: =B20 -> 0.51 | D33: =B19 -> 0.588 | E33: =B33/C33 -> 20.601961 | F33: =B33/D33 -> 17.869048 | G33: 25 | H33: =E33-G33 -> -4.3980392 | I33: =103.76/10 -> 10.376 | J33: Verified／Derived | K33: 收盤價：digrin「Real price」（未調整）12 月收盤 ÷10
A34: 2018-12 | B34: =89.49/10 -> 8.949 | C34: =B21 -> 0.749 | D34: =B20 -> 0.51 | E34: =B34/C34 -> 11.947931 | F34: =B34/D34 -> 17.547059 | G34: 9.69 | H34: =E34-G34 -> 2.2579306 | I34: =88.61/10 -> 8.861 | J34: Verified／Derived | K34: 當期 P/E 11.9 為十年最低（2018Q4 記憶體循環下修）
A35: 2019-12 | B35: =178.17/10 -> 17.817 | C35: =B22 -> 0.77 | D35: =B21 -> 0.749 | E35: =B35/C35 -> 23.138961 | F35: =B35/D35 -> 23.787717 | G35: 24.94 | H35: =E35-G35 -> -1.801039 | I35: =176.85/10 -> 17.685 | J35: Verified／Derived | K35: 收盤價：digrin「Real price」（未調整）12 月收盤 ÷10
A36: 2020-12 | B36: =258.91/10 -> 25.891 | C36: =B23 -> 1.337 | D36: =B22 -> 0.77 | E36: =B36/C36 -> 19.364996 | F36: =B36/D36 -> 33.624675 | G36: 29.36 | H36: =E36-G36 -> -9.9950037 | I36: =257.45/10 -> 25.745 | J36: Verified／Derived | K36: 收盤價：digrin「Real price」（未調整）12 月收盤 ÷10
A37: 2021-12 | B37: =430.11/10 -> 43.011 | C37: =B24 -> 2.192 | D37: =B23 -> 1.337 | E37: =B37/C37 -> 19.621807 | F37: =B37/D37 -> 32.169783 | G37: 22.06 | H37: =E37-G37 -> -2.4381934 | I37: =428.18/10 -> 42.818 | J37: Verified／Derived | K37: 收盤價：digrin「Real price」（未調整）12 月收盤 ÷10
A38: 2022-12 | B38: =377.03/10 -> 37.703 | C38: =B25 -> 2.415 | D38: =B24 -> 2.192 | E38: =B38/C38 -> 15.612008 | F38: =B38/D38 -> 17.200274 | G38: 15.44 | H38: =E38-G38 -> 0.17200828 | I38: =375.83/10 -> 37.583 | J38: Verified／Derived | K38: 收盤價：digrin「Real price」（未調整）12 月收盤 ÷10
A39: 2023-12 | B39: =581.3/10 -> 58.13 | C39: =B26 -> 2.03 | D39: =B25 -> 2.415 | E39: =B39/C39 -> 28.635468 | F39: =B39/D39 -> 24.070393 | G39: 29.37 | H39: =E39-G39 -> -0.73453202 | I39: =580.14/10 -> 58.014 | J39: Verified／Derived | K39: 收盤價：digrin「Real price」（未調整）12 月收盤 ÷10
A40: 2024-12 | B40: =630.12/10 -> 63.012 | C40: =B27 -> 3.04 | D40: =B26 -> 2.03 | E40: =B40/C40 -> 20.727632 | F40: =B40/D40 -> 31.040394 | G40: 26.49 | H40: =E40-G40 -> -5.7623684 | I40: =629.42/10 -> 62.942 | J40: Verified／Derived | K40: 收盤價：digrin「Real price」（未調整）12 月收盤 ÷10
A41: 2025-12 | B41: =1215.08/10 -> 121.508 | C41: =a26_eps -> 3.66 | D41: =B27 -> 3.04 | E41: =B41/C41 -> 33.198907 | F41: =B41/D41 -> 39.969737 | G41: 35.36 | H41: =E41-G41 -> -2.1610929 | I41: =1214.77/10 -> 121.477 | J41: Verified／Derived | K41: 當期 EPS＝FY2026 實績 3.66；最高 33.2
A43: 收盤價來源1：digrin（Real price，年底收盤，未做股利調整）；來源2：macrotrends（含股利調整，故略低，I 欄）。macrotrends P/E 為 TTM 口徑（年底已公布的近四季 EPS），與自算的當期口徑不同，只作對照。
A45: 3. 分位
A46: 統計 | B46: P/E 當期（自算） | C46: P/E 前期（自算） | D46: macrotrends P/E（參考） | E46: 用途
A47: 25 分位 | B47: =PERCENTILE(E32:E41,0.25) -> 16.550255 | C47: =PERCENTILE(F32:F41,0.25) -> 17.627556 | D47: =PERCENTILE(G32:G41,0.25) -> 17.095 | E47: 見頂年
A48: 中位數 | B48: =PERCENTILE(E32:E41,0.5) -> 20.111884 | C48: =PERCENTILE(F32:F41,0.5) -> 23.929055 | D48: =PERCENTILE(G32:G41,0.5) -> 24.97 | E48: 中段
A49: 75 分位 | B49: =PERCENTILE(E32:E41,0.75) -> 22.536129 | C49: =PERCENTILE(F32:F41,0.75) -> 31.887436 | D49: =PERCENTILE(G32:G41,0.75) -> 28.6425 | E49: 谷底
A50: 年數 | B50: =COUNT(E32:E41) -> 10 | C50: =COUNT(F32:F41) -> 10 | D50: =COUNT(G32:G41) -> 10
A51: 偏誤方向：2016–2018 年（AI 需求出現前）當期 P/E 13.4、20.6、11.9 偏低，拉低 25 分位與中位數；2023、2025 年（28.7、33.2）為 AI 期高倍數。照規則計算，不另換倍數。
A53: 4. 循環位置（設備股共用規則；見頂年度讀設備市場模型，不在本模型另訂）
A54: 循環位置（設備股共用規則）：各情境的見頂年度取自設備市場模型（markets/equipment 的 Mkt 頁「見頂年度」：A 2029、B 2028、C 2027）；會計年度 FY(t) 對照日曆年 t（FY(t) 有 3/4 落在 t 年）：t 早於見頂年＝中段（中位數）、等於＝見頂（25 分位）、晚於＝谷底（75 分位）。KLA 的 FY(t)＝t−1 年 7 月～t 年 6 月，上下半各一半；以 FY(t) 對照日曆年 t（結束年）。驗證：以 FY 加權的設備總額（1/2 CY(t−1)＋1/2 CY(t)）的見頂會計年度與此判定一致（右表）
A55: 情境 | B55: 設備市場見頂年度 | C55: FY2027 對照日曆年 | D55: 判定 | E55: 倍數 | F55: FY 加權設備總額 FY2027 | G55: FY 加權設備總額 FY2028 | H55: FY 加權見頂（FY2027–29）
A56: A | B56: =pk_A -> 2029 | C56: 2027 | D56: =IF(C56<pk_A,"中段",IF(C56=pk_A,"見頂","谷底")) -> 中段 | E56: =IF(D56="見頂",pe_peak,IF(D56="谷底",pe_trough,pe_mid)) -> 20.111884 | F56: =0.5*Units!D13+0.5*Units!E13 -> 198.19129 | G56: =0.5*Units!E13+0.5*Units!F13 -> 232.12708 | H56: =IF(AND(F56>=G56,F56>=0.5*Units!F13+0.5*Units!G13),"FY2027",IF(G56>=0.5*Units!F13+0.5*Units!G13,"FY2028","FY2029 或之後")) -> FY2029 或之後
A57: B | B57: =pk_B -> 2028 | C57: 2027 | D57: =IF(C57<pk_B,"中段",IF(C57=pk_B,"見頂","谷底")) -> 中段 | E57: =IF(D57="見頂",pe_peak,IF(D57="谷底",pe_trough,pe_mid)) -> 20.111884 | F57: =0.5*Units!D24+0.5*Units!E24 -> 198.19129 | G57: =0.5*Units!E24+0.5*Units!F24 -> 218.22554 | H57: =IF(AND(F57>=G57,F57>=0.5*Units!F24+0.5*Units!G24),"FY2027",IF(G57>=0.5*Units!F24+0.5*Units!G24,"FY2028","FY2029 或之後")) -> FY2028
A58: C | B58: =pk_C -> 2027 | C58: 2027 | D58: =IF(C58<pk_C,"中段",IF(C58=pk_C,"見頂","谷底")) -> 見頂 | E58: =IF(D58="見頂",pe_peak,IF(D58="谷底",pe_trough,pe_mid)) -> 16.550255 | F58: =0.5*Units!D35+0.5*Units!E35 -> 198.19129 | G58: =0.5*Units!E35+0.5*Units!F35 -> 196.40298 | H58: =IF(AND(F58>=G58,F58>=0.5*Units!F35+0.5*Units!G35),"FY2027",IF(G58>=0.5*Units!F35+0.5*Units!G35,"FY2028","FY2029 或之後")) -> FY2027
A60: 5. 隱含股價（美元）：規則值＝FY2027 EPS × 依循環位置的倍數；其餘倍數僅供參考
A61: 情境 | B61: EPS 年度 | C61: EPS | D61: 倍數類型 | E61: 倍數 | F61: 隱含股價 | G61: 相對現價 | H61: 備註
A62: A | B62: FY2027 | C62: =PL!E13 -> 5.3079006 | D62: ="規則值："&D56 -> 規則值：中段 | E62: =E56 -> 20.111884 | F62: =C62*E62 -> 106.75188 | G62: =F62/px-1 -> -0.26686437
A63: A | B63: FY2027 | C63: =PL!E13 -> 5.3079006 | D63: 參考：25 分位 | E63: =pe_peak -> 16.550255 | F63: =C63*E63 -> 87.84711 | G63: =F63/px-1 -> -0.3966959
A64: A | B64: FY2027 | C64: =PL!E13 -> 5.3079006 | D64: 參考：中位數 | E64: =pe_mid -> 20.111884 | F64: =C64*E64 -> 106.75188 | G64: =F64/px-1 -> -0.26686437
A65: A | B65: FY2027 | C65: =PL!E13 -> 5.3079006 | D65: 參考：75 分位 | E65: =pe_trough -> 22.536129 | F65: =C65*E65 -> 119.61953 | G65: =F65/px-1 -> -0.17849371
A66: A | B66: FY2028 | C66: =PL!F13 -> 6.3622032 | D66: 參考：25 分位 | E66: =pe_peak -> 16.550255 | F66: =C66*E66 -> 105.29609 | G66: =F66/px-1 -> -0.27686225
A67: A | B67: FY2028 | C67: =PL!F13 -> 6.3622032 | D67: 參考：中位數 | E67: =pe_mid -> 20.111884 | F67: =C67*E67 -> 127.95589 | G67: =F67/px-1 -> -0.12124242
A68: A | B68: FY2028 | C68: =PL!F13 -> 6.3622032 | D68: 參考：75 分位 | E68: =pe_trough -> 22.536129 | F68: =C68*E68 -> 143.37943 | G68: =F68/px-1 -> -0.015318794
A69: B | B69: FY2027 | C69: =PL!E24 -> 5.2590745 | D69: ="規則值："&D57 -> 規則值：中段 | E69: =E57 -> 20.111884 | F69: =C69*E69 -> 105.76989 | G69: =F69/px-1 -> -0.27360831
A70: B | B70: FY2027 | C70: =PL!E24 -> 5.2590745 | D70: 參考：25 分位 | E70: =pe_peak -> 16.550255 | F70: =C70*E70 -> 87.039025 | G70: =F70/px-1 -> -0.40224555
A71: B | B71: FY2027 | C71: =PL!E24 -> 5.2590745 | D71: 參考：中位數 | E71: =pe_mid -> 20.111884 | F71: =C71*E71 -> 105.76989 | G71: =F71/px-1 -> -0.27360831
A72: B | B72: FY2027 | C72: =PL!E24 -> 5.2590745 | D72: 參考：75 分位 | E72: =pe_trough -> 22.536129 | F72: =C72*E72 -> 118.51918 | G72: =F72/px-1 -> -0.18605055
A73: B | B73: FY2028 | C73: =PL!F24 -> 5.8961961 | D73: 參考：25 分位 | E73: =pe_peak -> 16.550255 | F73: =C73*E73 -> 97.583551 | G73: =F73/px-1 -> -0.32982933
A74: B | B74: FY2028 | C74: =PL!F24 -> 5.8961961 | D74: 參考：中位數 | E74: =pe_mid -> 20.111884 | F74: =C74*E74 -> 118.58361 | G74: =F74/px-1 -> -0.18560806
A75: B | B75: FY2028 | C75: =PL!F24 -> 5.8961961 | D75: 參考：75 分位 | E75: =pe_trough -> 22.536129 | F75: =C75*E75 -> 132.87743 | G75: =F75/px-1 -> -0.087442932
A76: C | B76: FY2027 | C76: =PL!E35 -> 5.1877605 | D76: ="規則值："&D58 -> 規則值：見頂 | E76: =E58 -> 16.550255 | F76: =C76*E76 -> 85.85876 | G76: =F76/px-1 -> -0.41035121
A77: C | B77: FY2027 | C77: =PL!E35 -> 5.1877605 | D77: 參考：25 分位 | E77: =pe_peak -> 16.550255 | F77: =C77*E77 -> 85.85876 | G77: =F77/px-1 -> -0.41035121
A78: C | B78: FY2027 | C78: =PL!E35 -> 5.1877605 | D78: 參考：中位數 | E78: =pe_mid -> 20.111884 | F78: =C78*E78 -> 104.33564 | G78: =F78/px-1 -> -0.28345831
A79: C | B79: FY2027 | C79: =PL!E35 -> 5.1877605 | D79: 參考：75 分位 | E79: =pe_trough -> 22.536129 | F79: =C79*E79 -> 116.91204 | G79: =F79/px-1 -> -0.19708785
A80: C | B80: FY2028 | C80: =PL!F35 -> 5.140684 | D80: 參考：25 分位 | E80: =pe_peak -> 16.550255 | F80: =C80*E80 -> 85.079633 | G80: =F80/px-1 -> -0.41570199
A81: C | B81: FY2028 | C81: =PL!F35 -> 5.140684 | D81: 參考：中位數 | E81: =pe_mid -> 20.111884 | F81: =C81*E81 -> 103.38884 | G81: =F81/px-1 -> -0.28996058
A82: C | B82: FY2028 | C82: =PL!F35 -> 5.140684 | D82: 參考：75 分位 | E82: =pe_trough -> 22.536129 | F82: =C82*E82 -> 115.85112 | G82: =F82/px-1 -> -0.20437389
A84: 6. 目前遠期 P/E
A85: 項目 | B85: A | C85: B | D85: C | E85: 備註
A86: 現價（stockanalysis 2026-10-23 收盤） | B86: =px -> 145.61 | E86: 2026-10 月內由 206.89（10-02）跌至 145.61
A87: 遠期 P/E：現價 ÷ 共識 FY2027 EPS（非 GAAP） | B87: =px/cons_eps27 -> 26.766544 | E87: stockanalysis 顯示 26.65x
A88: 現價 ÷ FY2026 EPS（實績） | B88: =px/a26_eps -> 39.784153
A89: 現價 ÷ FY2027 EPS（模型） | B89: =px/PL!E13 -> 27.432692 | C89: =px/PL!E24 -> 27.687381 | D89: =px/PL!E35 -> 28.067988 | E89: A／B／C
A90: 現價 ÷ FY2028 EPS（模型） | B90: =px/PL!F13 -> 22.886726 | C90: =px/PL!F24 -> 24.695583 | D90: =px/PL!F35 -> 28.325024 | E90: A／B／C
A91: 現價隱含倍數 ÷ 規則倍數（情境 A）— 以 FY2027 A EPS | B91: =B89/E56 -> 1.3640041 | E91: >1＝現價高於規則給的倍數
A94: 0. 目標價
A95: 0.1 DCF（股東權益現金流，FY2027–FY2032 明確期＋FY2032 後永續）
A96: 項目 | B96: A（順利） | C96: B（平平） | D96: C（不如預期） | E96: 說明
A97: 情境 EPS（FY2027–FY2032） | E97: PL 頁延伸區塊；FY2030 起為收斂法
A98: FY2027 | B98: =PL!E143 -> 5.3079006 | C98: =PL!E150 -> 5.2590745 | D98: =PL!E157 -> 5.1877605
A99: FY2028 | B99: =PL!F143 -> 6.3622032 | C99: =PL!F150 -> 5.8961961 | D99: =PL!F157 -> 5.140684
A100: FY2029 | B100: =PL!G143 -> 7.4420288 | C100: =PL!G150 -> 6.1207905 | D100: =PL!G157 -> 4.8103645
A101: FY2030 | B101: =PL!H143 -> 8.2378469 | C101: =PL!H150 -> 6.0105677 | D101: =PL!H157 -> 4.2939088
A102: FY2031 | B102: =PL!I143 -> 8.925442 | C102: =PL!I150 -> 5.9066832 | D102: =PL!I157 -> 3.8886646
A103: FY2032 | B103: =PL!J143 -> 9.4609686 | C103: =PL!J150 -> 5.8070485 | D103: =PL!J157 -> 3.5645738
A104: 股東現金流＝EPS ×（1 − tp_g ÷ tp_roe） | E104: 模型無折舊與資本支出項目，故不用（淨利＋折舊－資本支出）；設備股資本支出低（輕資產），此式偏誤小
A105: 再投資率（tp_g ÷ tp_roe，上限 0.8） | B105: =MIN(tp_g/tp_roe,0.8) -> 0.043460939 | E105: ROE 為近三年平均（In 頁 tp_roe）
A106: FY2027 | B106: =B98*(1-$B$105) -> 5.0772142 | C106: =C98*(1-$B$105) -> 5.0305102 | D106: =D98*(1-$B$105) -> 4.9622955
A107: FY2028 | B107: =B99*(1-$B$105) -> 6.0856959 | C107: =C99*(1-$B$105) -> 5.6399419 | D107: =D99*(1-$B$105) -> 4.9172651
A108: FY2029 | B108: =B100*(1-$B$105) -> 7.1185912 | C108: =C100*(1-$B$105) -> 5.8547752 | D108: =D100*(1-$B$105) -> 4.6013015
A109: FY2030 | B109: =B101*(1-$B$105) -> 7.8798223 | C109: =C101*(1-$B$105) -> 5.7493428 | D109: =D101*(1-$B$105) -> 4.1072915
...

Sheet Recon
A1: Recon — 本模型 vs 公司指引、共識、公司的 WFE 說法、SEMI。只作事後對照，不為對上數字而調整參數。差距 > 10% 的原因見 README
A3: 項目 | B3: 對照值 | C3: 模型 A | D3: 差距 A | E3: 模型 B | F3: 差距 B | G3: 模型 C | H3: 差距 C | I3: 對照來源 | J3: 說明
A4: A. CY2026 下半錨點 vs 公司指引＋共識
A5: CY2026 下半營收（錨點 − 上半實績）vs FQ1-27 指引＋共識 FQ2-27 | B5: =g_q1_rev+cons_q2_rev -> 8490 | C5: =PL!D50-h1_rev -> 8487.1872 | D5: =C5/B5-1 -> -0.00033130742 | E5: =PL!D80-h1_rev -> 8487.1872 | F5: =E5/B5-1 -> -0.00033130742 | G5: =PL!D110-h1_rev -> 8487.1872 | H5: =G5/B5-1 -> -0.00033130742 | I5: 公司 8-K（FQ1 4.0B）＋Yahoo 共識（FQ2 4.49B） | J5: 錨點用公司「下半約高 20%」，非共識
A6: B. FY2027、FY2028 vs 共識（Yahoo Finance；共識 EPS 為非 GAAP，模型為 GAAP）
A7: FY2027 營收 | B7: =cons_rev27 -> 18140 | C7: =PL!E5 -> 17888.415 | D7: =C7/B7-1 -> -0.013869089 | E7: =PL!E16 -> 17772.517 | F7: =E7/B7-1 -> -0.02025817 | G7: =PL!E27 -> 17603.24 | H7: =G7/B7-1 -> -0.029589874 | I7: Yahoo（18.14B）；stockanalysis 18.1B
A8: FY2027 EPS | B8: =cons_eps27 -> 5.44 | C8: =PL!E13 -> 5.3079006 | D8: =C8/B8-1 -> -0.02428298 | E8: =PL!E24 -> 5.2590745 | F8: =E8/B8-1 -> -0.033258369 | G8: =PL!E35 -> 5.1877605 | H8: =G8/B8-1 -> -0.046367558 | I8: Yahoo 5.44；stockanalysis 5.46 | J8: GAAP 比非 GAAP 低約 2–3%（FY2026：3.66 vs 3.76）
A9: FY2028 營收 | B9: =cons_rev28 -> 21570 | C9: =PL!F5 -> 20543.783 | D9: =C9/B9-1 -> -0.047576132 | E9: =PL!F16 -> 19319.452 | F9: =E9/B9-1 -> -0.10433696 | G9: =PL!F27 -> 17417.108 | H9: =G9/B9-1 -> -0.19253095 | I9: Yahoo（21.57B）
A10: FY2028 EPS | B10: =cons_eps28 -> 6.74 | C10: =PL!F13 -> 6.3622032 | D10: =C10/B10-1 -> -0.056052935 | E10: =PL!F24 -> 5.8961961 | F10: =E10/B10-1 -> -0.12519345 | G10: =PL!F35 -> 5.140684 | H10: =G10/B10-1 -> -0.23728723 | I10: Yahoo 6.74
A11: C. WFE：設備模型 vs 公司說法、SEMI（US$B）
A12: CY2025 WFE（前段＋先進封裝）vs 公司約 120 | B12: =kla_wfe25 -> 120 | C12: =Units!C8+Units!C11+Units!C12 -> 119.9534 | D12: =C12/B12-1 -> -0.00038832344 | E12: =Units!C19+Units!C22+Units!C23 -> 119.9534 | F12: =E12/B12-1 -> -0.00038832344 | G12: =Units!C30+Units!C33+Units!C34 -> 119.9534 | H12: =G12/B12-1 -> -0.00038832344 | I12: KLA FQ4-26 法說（2026-07-28；MarketBeat 逐字稿） | J12: 設備模型 2025 以 SEMI 實績校準
A13: CY2026 WFE（前段＋先進封裝）vs 公司「low 150s」（取 152） | B13: 152 | C13: =Units!D8+Units!D11+Units!D12 -> 159.50705 | D13: =C13/B13-1 -> 0.049388491 | E13: =Units!D19+Units!D22+Units!D23 -> 159.50705 | F13: =E13/B13-1 -> 0.049388491 | G13: =Units!D30+Units!D33+Units!D34 -> 159.50705 | H13: =G13/B13-1 -> 0.049388491 | I13: KLA FQ4-26 法說（2026-07-28；MarketBeat 逐字稿） | J13: 設備模型 2026 比公司說法高；本模型以 KLA 自身的 CY2026 錨點校準強度，所以這個差異不進入營收
A14: CY2026 前段 WFE vs SEMI WFE | B14: =Units!D37 -> 143.9 | C14: =Units!D8+Units!D11 -> 156.15705 | D14: =C14/B14-1 -> 0.085177558 | E14: =Units!D19+Units!D22 -> 156.15705 | F14: =E14/B14-1 -> 0.085177558 | G14: =Units!D30+Units!D33 -> 156.15705 | H14: =G14/B14-1 -> 0.085177558 | I14: SEMI 2026-07（設備模型成品）
A15: CY2027 前段 WFE vs SEMI WFE（年增連乘） | B15: =Units!E37 -> 175.2702 | C15: =Units!E8+Units!E11 -> 192.79547 | D15: =C15/B15-1 -> 0.099990012 | E15: =Units!E19+Units!E22 -> 192.79547 | F15: =E15/B15-1 -> 0.099990012 | G15: =Units!E30+Units!E33 -> 192.79547 | H15: =G15/B15-1 -> 0.099990012 | I15: 同上 | J15: 公司引述 2027 共識約 190B（含封裝；未確認）
A16: D. 強度與市占（顯示；非獨立檢驗）
A17: 製程控制強度 CY2025（前段系統 ÷ 加權前段 WFE） | C17: =PL!C55 -> 0.067630242 | J17: CY2026 校準值見下一列；兩者差距反映設備模型 2026 WFE 高於公司說法
A18: 製程控制強度 CY2026（校準） | C18: =PL!D55 -> 0.061198184
A19: 製程控制占前段 WFE CY2026（強度 ÷ KLA 市占 58%） | C19: =PL!D57 -> 0.10551411 | J19: 業界常見說法約 11–13%（未找到可引用來源）
A20: E. 其他資訊（非對帳）
A21: FQ1-27 營收指引 ÷ 模型 FY2027（A） | C21: =g_q1_rev/PL!E5 -> 0.22360841 | J21: 營收逐季上升，Q1 低於 25% 屬正常
A22: 模型 FY2027 中國營收（A；× FY2026 占比 30%） | C22: =PL!E72 -> 5366.5244

Sheet Sens
A1: Sens — 一次動一個輸入（情境 A）：對 FY2027、FY2028 營收與 EPS 的影響。每個案例是一個完整的推導區塊（本頁下方，與 PL 同一引擎）
A3: 案例 | B3: 設定 | C3: FY2027 營收 US$M | D3: FY2027 EPS US$ | E3: 相對基準 | F3: FY2028 營收 US$M | G3: FY2028 EPS US$ | H3: 相對基準
A4: 基準（情境 A） | B4: PL 區塊 A | C4: =PL!E62 -> 17888.415 | D4: =PL!E71 -> 5.3079006 | E4: =D4/D$4-1 -> 0 | F4: =PL!F62 -> 20543.783 | G4: =PL!F71 -> 6.3622032 | H4: =G4/G$4-1 -> 0
A5: 中國系統營收 −25%（CY2027 起） | B5: 出口管制擴大（Assumed） | C5: =E67 -> 17376.127 | D5: =E76 -> 5.092081 | E5: =D5/D$4-1 -> -0.040660063 | F5: =F67 -> 19433.232 | G5: =F76 -> 5.8880091 | H5: =G5/G$4-1 -> -0.074533001
A6: 中國系統營收 −50%（CY2027 起） | C6: =E103 -> 16863.838 | D6: =E112 -> 4.8762614 | E6: =D6/D$4-1 -> -0.081320126 | F6: =F103 -> 18322.682 | G6: =F112 -> 5.413815 | H6: =G6/G$4-1 -> -0.149066
A7: 製程控制強度不再提升 | B7: pc_u＝0 | C7: =E139 -> 17712.867 | D7: =E148 -> 5.2339447 | E7: =D7/D$4-1 -> -0.01393317 | F7: =F139 -> 19967.936 | G7: =F148 -> 6.1163221 | H7: =G7/G$4-1 -> -0.038647159
A8: 製程控制強度提升加倍 | B8: 2030 較 2025 +300bp | C8: =E175 -> 18045.902 | D8: =E184 -> 5.3742477 | E8: =D8/D$4-1 -> 0.012499688 | F8: =F175 -> 21070.275 | G8: =F184 -> 6.5870103 | H8: =G8/G$4-1 -> 0.035334783
A9: 下半年增幅 15% | B9: CY2026 錨點較低 | C9: =E211 -> 17309.864 | D9: =E220 -> 5.0641657 | E9: =D9/D$4-1 -> -0.045919268 | F9: =F211 -> 20058.705 | G9: =F220 -> 6.1550797 | H9: =G9/G$4-1 -> -0.032555311
A10: 下半年增幅 25% | C10: =E247 -> 18466.965 | D10: =E256 -> 5.5516355 | E10: =D10/D$4-1 -> 0.045919268 | F10: =F247 -> 21028.861 | G10: =F256 -> 6.5693267 | H10: =G10/G$4-1 -> 0.032555311
A11: 記憶體相對強度 低（代工邏輯占 66%） | C11: =E283 -> 17862.491 | D11: =E292 -> 5.2969795 | E11: =D11/D$4-1 -> -0.002057523 | F11: =F283 -> 20488.816 | G11: =F292 -> 6.3387328 | H11: =G11/G$4-1 -> -0.0036890427
A12: 記憶體相對強度 高（代工邏輯占 60%） | C12: =E319 -> 17914.338 | D12: =E328 -> 5.3188217 | E12: =D12/D$4-1 -> 0.002057523 | F12: =F319 -> 20598.75 | G12: =F328 -> 6.3856737 | H12: =G12/G$4-1 -> 0.0036890427
A13: 先進封裝倍數 1.0x | B13: 與封裝市場同速 | C13: =E355 -> 17815.291 | D13: =E364 -> 5.2770945 | E13: =D13/D$4-1 -> -0.0058038203 | F13: =F355 -> 20295.245 | G13: =F364 -> 6.2560798 | H13: =G13/G$4-1 -> -0.016680288
A14: 先進封裝倍數 2.5x | C14: =E391 -> 17924.977 | D14: =E400 -> 5.3233036 | E14: =D14/D$4-1 -> 0.0029019102 | F14: =F391 -> 20675.344 | G14: =F400 -> 6.4183783 | H14: =G14/G$4-1 -> 0.0088295051
A15: 先進封裝 CY2026 1.4B | B15: 取 substack 會計年度口徑上緣 | C15: =E427 -> 17887.494 | D15: =E436 -> 5.3075129 | E15: =D15/D$4-1 -> -7.3039969e-05 | F15: =F427 -> 20562.536 | G15: =F436 -> 6.3702108 | H15: =G15/G$4-1 -> 0.0012586123
A16: 增量毛利率 60% | B16: 公司 60–65% 下緣 | C16: =E463 -> 17888.415 | D16: =E472 -> 5.1774285 | E16: =D16/D$4-1 -> -0.024580725 | F16: =F463 -> 20543.783 | G16: =F472 -> 6.1484728 | H16: =G16/G$4-1 -> -0.033593773
A17: 增量毛利率 65% | B17: 上緣 | C17: =E499 -> 17888.415 | D17: =E508 -> 5.3178303 | E17: =D17/D$4-1 -> 0.0018707453 | F17: =F499 -> 20543.783 | G17: =F508 -> 6.3784694 | H17: =G17/G$4-1 -> 0.002556694
A18: 營業費用 FY2028–29 年增 5% | C18: =E535 -> 17888.415 | D18: =E544 -> 5.3079006 | E18: =D18/D$4-1 -> 0 | F18: =F535 -> 20543.783 | G18: =F544 -> 6.4189733 | H18: =G18/G$4-1 -> 0.0089230206
A19: 營業費用 FY2028–29 年增 11% | C19: =E571 -> 17888.415 | D19: =E580 -> 5.3079006 | E19: =D19/D$4-1 -> 0 | F19: =F571 -> 20543.783 | G19: =F580 -> 6.3054331 | H19: =G19/G$4-1 -> -0.0089230206
A20: 服務年增 12% | C20: =E607 -> 17825.896 | D20: =E616 -> 5.2815623 | E20: =D20/D$4-1 -> -0.0049620852 | F20: =F607 -> 20402.49 | G20: =F616 -> 6.3018727 | H20: =G20/G$4-1 -> -0.009482638
A21: 服務年增 16% | C21: =E643 -> 17950.934 | D21: =E652 -> 5.3342388 | E21: =D21/D$4-1 -> 0.0049620852 | F21: =F643 -> 20687.576 | G21: =F652 -> 6.4236015 | H21: =G21/G$4-1 -> 0.0096504723
A22: 稅率 13% | C22: =E679 -> 17888.415 | D22: =E688 -> 5.4010217 | E22: =D22/D$4-1 -> 0.01754386 | F22: =F679 -> 20543.783 | G22: =F688 -> 6.4738208 | H22: =G22/G$4-1 -> 0.01754386
A23: 稅率 17% | C23: =E715 -> 17888.415 | D23: =E724 -> 5.1526988 | E23: =D23/D$4-1 -> -0.029239766 | F23: =F715 -> 20543.783 | G23: =F724 -> 6.1761739 | H23: =G23/G$4-1 -> -0.029239766
A24: 營業外 −200 | C24: =E751 -> 17888.415 | D24: =E760 -> 5.2427329 | E24: =D24/D$4-1 -> -0.012277487 | F24: =F751 -> 20543.783 | G24: =F760 -> 6.2961531 | H24: =G24/G$4-1 -> -0.010381641
A25: 股數不減 | B25: 買回停止 | C25: =E787 -> 17888.415 | D25: =E796 -> 5.3079006 | E25: =D25/D$4-1 -> 0 | F25: =F787 -> 20543.783 | G25: =F796 -> 6.2772043 | H25: =G25/G$4-1 -> -0.01335998
A26: 股數年減 2.5% | C26: =E823 -> 17888.415 | D26: =E832 -> 5.3079006 | E26: =D26/D$4-1 -> 0 | F26: =F823 -> 20543.783 | G26: =F832 -> 6.4381583 | H26: =G26/G$4-1 -> 0.011938482
A27: 設備市場情境 B | B27: 2028 持平、2029 −5%；服務、兩事業、費用成長 B | C27: =PL!E92 -> 17772.517 | D27: =PL!E101 -> 5.2590745 | E27: =D27/D$4-1 -> -0.0091987632 | F27: =PL!F92 -> 19319.452 | G27: =PL!F101 -> 5.8961961 | H27: =G27/G$4-1 -> -0.073246181
A28: 設備市場情境 C | B28: 2028 −20%；服務、兩事業、費用成長 C | C28: =PL!E122 -> 17603.24 | D28: =PL!E131 -> 5.1877605 | E28: =D28/D$4-1 -> -0.022634204 | F28: =PL!F122 -> 17417.108 | G28: =PL!F131 -> 5.140684 | H28: =G28/G$4-1 -> -0.19199625
A30: 讀法：FY2027 的一半是 CY2026 下半（錨點，三情境相同），另一半是 CY2027（三情境的設備市場相同），所以情境差異到 FY2028 才明顯；中國與強度假設自 CY2027 起作用，FY2027 只吃一半。
A50: 案例區塊：中國系統營收 −25%（CY2027 起）（情境 A）
A51: 項目 | B51: 單位 | C51: CY2025／FY2025A | D51: CY2026／FY2026A | E51: CY2027／FY2027 | F51: CY2028／FY2028 | G51: CY2029／FY2029 | H51: 說明
A52: A. 日曆年（C＝CY2025 … G＝CY2029）
A53: 加權前段 WFE（代工邏輯＋m × 記憶體） | B53: US$M | C53: =(Units!C8+m_mem*Units!C11)*1000 -> 117874.06 | D53: =(Units!D8+m_mem*Units!D11)*1000 -> 157598.73 | E53: =(Units!E8+m_mem*Units!E11)*1000 -> 194734.95 | F53: =(Units!F8+m_mem*Units!F11)*1000 -> 218802.23 | G53: =(Units!G8+m_mem*Units!G11)*1000 -> 231172.69 | H53: 設備模型情境 A；m＝記憶體相對強度
A54: 先進封裝設備市場 | B54: US$M | C54: =Units!C12*1000 -> 3056.5693 | D54: =Units!D12*1000 -> 3350 | E54: =Units!E12*1000 -> 3795.3919 | F54: =Units!F12*1000 -> 4300 | G54: =Units!G12*1000 -> 4644
A55: 營收 CY2026 錨點（上半實績 ×（2＋下半增幅）） | B55: US$M | D55: =h1_rev*(2+h2up) -> 15559.843 | H55: 上半實績＋公司說法（下半約高 20%）
A56: 服務 CY2026 錨點 | B56: US$M | D56: =h1_svc*(2+g_svc_h2) -> 3286.1223
A57: SPTS＋PCB CY2026 錨點 | B57: US$M | D57: =cy25_oth*(1+g_oth26) -> 1528.965
A58: 先進封裝製程控制系統營收 | B58: US$M | C58: =ap26/(1+ap_g26) -> 647.05882 | D58: =ap26 -> 1100 | E58: =D58*(1+k_ap*(E54/D54-1)) -> 1392.4962 | F58: =E58*(1+k_ap*(F54/E54-1)) -> 1762.7688 | G58: =F58*(1+k_ap*(G54/F54-1)) -> 2044.8118 | H58: CY2027 起：前一年 ×（1＋k × 封裝設備市場成長）
A59: 前段製程控制系統營收 | B59: US$M | C59: =C61-C58 -> 7971.8512 | D59: =D61-D58 -> 9644.7559 | E59: =E60*E53 -> 12268.522 | F59: =F60*F53 -> 14190.898 | G59: =G60*G53 -> 15434.922 | H59: CY2025／2026＝系統 − 先進封裝；之後＝強度 × 加權 WFE
A60: 製程控制強度（前段系統 ÷ 加權前段 WFE） | B60: % | C60: =C59/C53 -> 0.067630242 | D60: =D59/D53 -> 0.061198184 | E60: =$D60*(1+pc_u)^1 -> 0.063001128 | F60: =$D60*(1+pc_u)^2 -> 0.064857188 | G60: =$D60*(1+pc_u)^3 -> 0.06676793 | H60: CY2026 校準；之後每年 ×（1＋pc_u）
A61: 半導體製程控制系統營收 CY | B61: US$M | C61: =cy25_sys -> 8618.91 | D61: =D55-D56-D57 -> 10744.756 | E61: =(E59+E58)*(1-chn_sh26*chn_cut_lo) -> 12636.441 | F61: =(F59+F58)*(1-chn_sh26*chn_cut_lo) -> 14757.141 | G61: =(G59+G58)*(1-chn_sh26*chn_cut_lo) -> 16168.754 | H61: CY2026＝錨點 − 服務 − 兩事業；CY2027 起 ×（1 − 中國占比 × 中國下降比例）
A62: 顯示：製程控制占前段 WFE（強度 ÷ KLA 市占） | B62: % | C62: =C60/kla_sh_pc -> 0.11660387 | D62: =D60/kla_sh_pc -> 0.10551411 | E62: =E60/kla_sh_pc -> 0.10862263 | F62: =F60/kla_sh_pc -> 0.11182274 | G62: =G60/kla_sh_pc -> 0.11511712 | H62: KLA 市占 58% 為賣方數字，只供顯示
A63: B. 會計年度（C＝FY2025A … G＝FY2029；FY(t)＝CY(t−1) 下半＋CY(t) 上半）
A64: 半導體製程控制系統營收 FY | B64: US$M | C64: =a25_sys -> 8264.026 | D64: =a26_sys -> 9119.058 | E64: =(D61-h1_sys)+0.5*E61 -> 12317.94 | F64: =0.5*E61+0.5*F61 -> 13696.791 | G64: =0.5*F61+0.5*G61 -> 15462.948 | H64: FY2027＝CY2026 下半（錨點 − 上半實績）＋1/2 CY2027
A65: 服務營收 | B65: US$M | C65: =a25_svc -> 2683.308 | D65: =a26_svc -> 3125.939 | E65: =D65*(1+g_svc_A) -> 3563.5705 | F65: =E65*(1+g_svc_A) -> 4062.4703 | G65: =F65*(1+g_svc_A) -> 4631.2162
A66: SPTS＋PCB 營收 | B66: US$M | C66: =a25_oth -> 1208.828 | D66: =a26_oth -> 1334.479 | E66: =D66*(1+g_oth_A) -> 1494.6165 | F66: =E66*(1+g_oth_A) -> 1673.9705 | G66: =F66*(1+g_oth_A) -> 1874.8469
A67: 營收 | B67: US$M | C67: =C64+C65+C66 -> 12156.162 | D67: =D64+D65+D66 -> 13579.476 | E67: =E64+E65+E66 -> 17376.127 | F67: =F64+F65+F66 -> 19433.232 | G67: =G64+G65+G66 -> 21969.011 | H67: FY2025、FY2026＝實績（恆等）
A68: 毛利 | B68: US$M | C68: =a25_gp -> 7404.295 | D68: =a26_gp -> 8324.416 | E68: =a26_gp+gm_inc*(E67-a26_rev) -> 10778.813 | F68: =a26_gp+gm_inc*(F67-a26_rev) -> 12108.658 | G68: =a26_gp+gm_inc*(G67-a26_rev) -> 13747.947 | H68: FY2026 毛利＋增量毛利率 ×（營收 − FY2026 營收）
A69: 毛利率 | B69: % | C69: =C68/C67 -> 0.60909809 | D69: =D68/D67 -> 0.61301452 | E69: =E68/E67 -> 0.62032313 | F69: =F68/F67 -> 0.62309025 | G69: =G68/G67 -> 0.62578815
A70: 營業費用（研發＋銷管） | B70: US$M | C70: =a25_opx -> 2390.068 | D70: =a26_opx -> 2663.636 | E70: =opex27 -> 2865 | F70: =E70*(1+g_opex_A) -> 3094.2 | G70: =F70*(1+g_opex_A) -> 3341.736
A71: 營業利益 | B71: US$M | C71: =a25_oi -> 4775.127 | D71: =D68-D70 -> 5660.78 | E71: =E68-E70 -> 7913.8132 | F71: =F68-F70 -> 9014.4576 | G71: =G68-G70 -> 10406.211 | H71: FY2025 含減損 239.1
A72: 營業利益率 | B72: % | C72: =C71/C67 -> 0.39281535 | D72: =D71/D67 -> 0.41686292 | E72: =E71/E67 -> 0.45544173 | F72: =F71/F67 -> 0.46386816 | G72: =G71/G67 -> 0.4736768
A73: 營業外淨額 | B73: US$M | C73: =a25_nonop -> -130.679 | D73: =a26_nonop -> -54.855 | E73: =oth_exp -> -100 | F73: =oth_exp -> -100 | G73: =oth_exp -> -100
A74: 淨利 | B74: US$M | C74: =a25_ni -> 4061.643 | D74: =a26_ni -> 4830.771 | E74: =(E71+E73)*(1-tax) -> 6680.8103 | F74: =(F71+F73)*(1-tax) -> 7621.8612 | G74: =(G71+G73)*(1-tax) -> 8811.8101
A75: 稀釋股數 | B75: 百萬股 | C75: =a25_sh -> 1337.502 | D75: =a26_sh -> 1319.633 | E75: =shares27 -> 1312 | F75: =E75*(1-bb) -> 1294.4717 | G75: =F75*(1-bb) -> 1277.1776
A76: EPS（GAAP 稀釋） | B76: US$ | C76: =a25_eps -> 3.04 | D76: =a26_eps -> 3.66 | E76: =E74/E75 -> 5.092081 | F76: =F74/F75 -> 5.8880091 | G76: =G74/G75 -> 6.8994399
A77: 顯示：中國營收（× FY2026 中國占比；CY2027 起扣下降） | B77: US$M | D77: =a26_rev*chn_sh26 -> 4073.8428 | E77: =E67*chn_sh26*(1-chn_cut_lo*IF(2027=2027,0.5,1)) -> 4561.2332 | F77: =F67*chn_sh26*(1-chn_cut_lo*IF(2028=2027,0.5,1)) -> 4372.4772 | G77: =G67*chn_sh26*(1-chn_cut_lo*IF(2029=2027,0.5,1)) -> 4943.0274 | H77: 只供顯示
A86: 案例區塊：中國系統營收 −50%（CY2027 起）（情境 A）
A87: 項目 | B87: 單位 | C87: CY2025／FY2025A | D87: CY2026／FY2026A | E87: CY2027／FY2027 | F87: CY2028／FY2028 | G87: CY2029／FY2029 | H87: 說明
A88: A. 日曆年（C＝CY2025 … G＝CY2029）
A89: 加權前段 WFE（代工邏輯＋m × 記憶體） | B89: US$M | C89: =(Units!C8+m_mem*Units!C11)*1000 -> 117874.06 | D89: =(Units!D8+m_mem*Units!D11)*1000 -> 157598.73 | E89: =(Units!E8+m_mem*Units!E11)*1000 -> 194734.95 | F89: =(Units!F8+m_mem*Units!F11)*1000 -> 218802.23 | G89: =(Units!G8+m_mem*Units!G11)*1000 -> 231172.69 | H89: 設備模型情境 A；m＝記憶體相對強度
A90: 先進封裝設備市場 | B90: US$M | C90: =Units!C12*1000 -> 3056.5693 | D90: =Units!D12*1000 -> 3350 | E90: =Units!E12*1000 -> 3795.3919 | F90: =Units!F12*1000 -> 4300 | G90: =Units!G12*1000 -> 4644
A91: 營收 CY2026 錨點（上半實績 ×（2＋下半增幅）） | B91: US$M | D91: =h1_rev*(2+h2up) -> 15559.843 | H91: 上半實績＋公司說法（下半約高 20%）
A92: 服務 CY2026 錨點 | B92: US$M | D92: =h1_svc*(2+g_svc_h2) -> 3286.1223
A93: SPTS＋PCB CY2026 錨點 | B93: US$M | D93: =cy25_oth*(1+g_oth26) -> 1528.965
A94: 先進封裝製程控制系統營收 | B94: US$M | C94: =ap26/(1+ap_g26) -> 647.05882 | D94: =ap26 -> 1100 | E94: =D94*(1+k_ap*(E90/D90-1)) -> 1392.4962 | F94: =E94*(1+k_ap*(F90/E90-1)) -> 1762.7688 | G94: =F94*(1+k_ap*(G90/F90-1)) -> 2044.8118 | H94: CY2027 起：前一年 ×（1＋k × 封裝設備市場成長）
A95: 前段製程控制系統營收 | B95: US$M | C95: =C97-C94 -> 7971.8512 | D95: =D97-D94 -> 9644.7559 | E95: =E96*E89 -> 12268.522 | F95: =F96*F89 -> 14190.898 | G95: =G96*G89 -> 15434.922 | H95: CY2025／2026＝系統 − 先進封裝；之後＝強度 × 加權 WFE
A96: 製程控制強度（前段系統 ÷ 加權前段 WFE） | B96: % | C96: =C95/C89 -> 0.067630242 | D96: =D95/D89 -> 0.061198184 | E96: =$D96*(1+pc_u)^1 -> 0.063001128 | F96: =$D96*(1+pc_u)^2 -> 0.064857188 | G96: =$D96*(1+pc_u)^3 -> 0.06676793 | H96: CY2026 校準；之後每年 ×（1＋pc_u）
A97: 半導體製程控制系統營收 CY | B97: US$M | C97: =cy25_sys -> 8618.91 | D97: =D91-D92-D93 -> 10744.756 | E97: =(E95+E94)*(1-chn_sh26*chn_cut_hi) -> 11611.865 | F97: =(F95+F94)*(1-chn_sh26*chn_cut_hi) -> 13560.616 | G97: =(G95+G94)*(1-chn_sh26*chn_cut_hi) -> 14857.774 | H97: CY2026＝錨點 − 服務 − 兩事業；CY2027 起 ×（1 − 中國占比 × 中國下降比例）
A98: 顯示：製程控制占前段 WFE（強度 ÷ KLA 市占） | B98: % | C98: =C96/kla_sh_pc -> 0.11660387 | D98: =D96/kla_sh_pc -> 0.10551411 | E98: =E96/kla_sh_pc -> 0.10862263 | F98: =F96/kla_sh_pc -> 0.11182274 | G98: =G96/kla_sh_pc -> 0.11511712 | H98: KLA 市占 58% 為賣方數字，只供顯示
A99: B. 會計年度（C＝FY2025A … G＝FY2029；FY(t)＝CY(t−1) 下半＋CY(t) 上半）
A100: 半導體製程控制系統營收 FY | B100: US$M | C100: =a25_sys -> 8264.026 | D100: =a26_sys -> 9119.058 | E100: =(D97-h1_sys)+0.5*E97 -> 11805.651 | F100: =0.5*E97+0.5*F97 -> 12586.241 | G100: =0.5*F97+0.5*G97 -> 14209.195 | H100: FY2027＝CY2026 下半（錨點 − 上半實績）＋1/2 CY2027
A101: 服務營收 | B101: US$M | C101: =a25_svc -> 2683.308 | D101: =a26_svc -> 3125.939 | E101: =D101*(1+g_svc_A) -> 3563.5705 | F101: =E101*(1+g_svc_A) -> 4062.4703 | G101: =F101*(1+g_svc_A) -> 4631.2162
A102: SPTS＋PCB 營收 | B102: US$M | C102: =a25_oth -> 1208.828 | D102: =a26_oth -> 1334.479 | E102: =D102*(1+g_oth_A) -> 1494.6165 | F102: =E102*(1+g_oth_A) -> 1673.9705 | G102: =F102*(1+g_oth_A) -> 1874.8469
A103: 營收 | B103: US$M | C103: =C100+C101+C102 -> 12156.162 | D103: =D100+D101+D102 -> 13579.476 | E103: =E100+E101+E102 -> 16863.838 | F103: =F100+F101+F102 -> 18322.682 | G103: =G100+G101+G102 -> 20715.258 | H103: FY2025、FY2026＝實績（恆等）
A104: 毛利 | B104: US$M | C104: =a25_gp -> 7404.295 | D104: =a26_gp -> 8324.416 | E104: =a26_gp+gm_inc*(E103-a26_rev) -> 10447.637 | F104: =a26_gp+gm_inc*(F103-a26_rev) -> 11390.727 | G104: =a26_gp+gm_inc*(G103-a26_rev) -> 12937.441 | H104: FY2026 毛利＋增量毛利率 ×（營收 − FY2026 營收）
A105: 毛利率 | B105: % | C105: =C104/C103 -> 0.60909809 | D105: =D104/D103 -> 0.61301452 | E105: =E104/E103 -> 0.61952903 | F105: =F104/F103 -> 0.62167357 | G105: =G104/G103 -> 0.6245368
A106: 營業費用（研發＋銷管） | B106: US$M | C106: =a25_opx -> 2390.068 | D106: =a26_opx -> 2663.636 | E106: =opex27 -> 2865 | F106: =E106*(1+g_opex_A) -> 3094.2 | G106: =F106*(1+g_opex_A) -> 3341.736
A107: 營業利益 | B107: US$M | C107: =a25_oi -> 4775.127 | D107: =D104-D106 -> 5660.78 | E107: =E104-E106 -> 7582.6375 | F107: =F104-F106 -> 8296.5267 | G107: =G104-G106 -> 9595.705 | H107: FY2025 含減損 239.1
A108: 營業利益率 | B108: % | C108: =C107/C103 -> 0.39281535 | D108: =D107/D103 -> 0.41686292 | E108: =E107/E103 -> 0.44963888 | F108: =F107/F103 -> 0.4528009 | G108: =G107/G103 -> 0.46321918
A109: 營業外淨額 | B109: US$M | C109: =a25_nonop -> -130.679 | D109: =a26_nonop -> -54.855 | E109: =oth_exp -> -100 | F109: =oth_exp -> -100 | G109: =oth_exp -> -100
A110: 淨利 | B110: US$M | C110: =a25_ni -> 4061.643 | D110: =a26_ni -> 4830.771 | E110: =(E107+E109)*(1-tax) -> 6397.655 | F110: =(F107+F109)*(1-tax) -> 7008.0304 | G110: =(G107+G109)*(1-tax) -> 8118.8278
A111: 稀釋股數 | B111: 百萬股 | C111: =a25_sh -> 1337.502 | D111: =a26_sh -> 1319.633 | E111: =shares27 -> 1312 | F111: =E111*(1-bb) -> 1294.4717 | G111: =F111*(1-bb) -> 1277.1776
A112: EPS（GAAP 稀釋） | B112: US$ | C112: =a25_eps -> 3.04 | D112: =a26_eps -> 3.66 | E112: =E110/E111 -> 4.8762614 | F112: =F110/F111 -> 5.413815 | G112: =G110/G111 -> 6.3568511
A113: 顯示：中國營收（× FY2026 中國占比；CY2027 起扣下降） | B113: US$M | D113: =a26_rev*chn_sh26 -> 4073.8428 | E113: =E103*chn_sh26*(1-chn_cut_hi*IF(2027=2027,0.5,1)) -> 3794.3636 | F113: =F103*chn_sh26*(1-chn_cut_hi*IF(2028=2027,0.5,1)) -> 2748.4022 | G113: =G103*chn_sh26*(1-chn_cut_hi*IF(2029=2027,0.5,1)) -> 3107.2887 | H113: 只供顯示
A122: 案例區塊：製程控制強度不再提升（情境 A）
A123: 項目 | B123: 單位 | C123: CY2025／FY2025A | D123: CY2026／FY2026A | E123: CY2027／FY2027 | F123: CY2028／FY2028 | G123: CY2029／FY2029 | H123: 說明
A124: A. 日曆年（C＝CY2025 … G＝CY2029）
A125: 加權前段 WFE（代工邏輯＋m × 記憶體） | B125: US$M | C125: =(Units!C8+m_mem*Units!C11)*1000 -> 117874.06 | D125: =(Units!D8+m_mem*Units!D11)*1000 -> 157598.73 | E125: =(Units!E8+m_mem*Units!E11)*1000 -> 194734.95 | F125: =(Units!F8+m_mem*Units!F11)*1000 -> 218802.23 | G125: =(Units!G8+m_mem*Units!G11)*1000 -> 231172.69 | H125: 設備模型情境 A；m＝記憶體相對強度
A126: 先進封裝設備市場 | B126: US$M | C126: =Units!C12*1000 -> 3056.5693 | D126: =Units!D12*1000 -> 3350 | E126: =Units!E12*1000 -> 3795.3919 | F126: =Units!F12*1000 -> 4300 | G126: =Units!G12*1000 -> 4644
A127: 營收 CY2026 錨點（上半實績 ×（2＋下半增幅）） | B127: US$M | D127: =h1_rev*(2+h2up) -> 15559.843 | H127: 上半實績＋公司說法（下半約高 20%）
A128: 服務 CY2026 錨點 | B128: US$M | D128: =h1_svc*(2+g_svc_h2) -> 3286.1223
A129: SPTS＋PCB CY2026 錨點 | B129: US$M | D129: =cy25_oth*(1+g_oth26) -> 1528.965
A130: 先進封裝製程控制系統營收 | B130: US$M | C130: =ap26/(1+ap_g26) -> 647.05882 | D130: =ap26 -> 1100 | E130: =D130*(1+k_ap*(E126/D126-1)) -> 1392.4962 | F130: =E130*(1+k_ap*(F126/E126-1)) -> 1762.7688 | G130: =F130*(1+k_ap*(G126/F126-1)) -> 2044.8118 | H130: CY2027 起：前一年 ×（1＋k × 封裝設備市場成長）
A131: 前段製程控制系統營收 | B131: US$M | C131: =C133-C130 -> 7971.8512 | D131: =D133-D130 -> 9644.7559 | E131: =E132*E125 -> 11917.425 | F131: =F132*F125 -> 13390.299 | G131: =G132*G125 -> 14147.349 | H131: CY2025／2026＝系統 − 先進封裝；之後＝強度 × 加權 WFE
A132: 製程控制強度（前段系統 ÷ 加權前段 WFE） | B132: % | C132: =C131/C125 -> 0.067630242 | D132: =D131/D125 -> 0.061198184 | E132: =$D132*(1+pc_u_lo)^1 -> 0.061198184 | F132: =$D132*(1+pc_u_lo)^2 -> 0.061198184 | G132: =$D132*(1+pc_u_lo)^3 -> 0.061198184 | H132: CY2026 校準；之後每年 ×（1＋pc_u）
A133: 半導體製程控制系統營收 CY | B133: US$M | C133: =cy25_sys -> 8618.91 | D133: =D127-D128-D129 -> 10744.756 | E133: =(E131+E130)*(1-chn_sh26*chn_cut) -> 13309.922 | F133: =(F131+F130)*(1-chn_sh26*chn_cut) -> 15153.068 | G133: =(G131+G130)*(1-chn_sh26*chn_cut) -> 16192.161 | H133: CY2026＝錨點 − 服務 − 兩事業；CY2027 起 ×（1 − 中國占比 × 中國下降比例）
A134: 顯示：製程控制占前段 WFE（強度 ÷ KLA 市占） | B134: % | C134: =C132/kla_sh_pc -> 0.11660387 | D134: =D132/kla_sh_pc -> 0.10551411 | E134: =E132/kla_sh_pc -> 0.10551411 | F134: =F132/kla_sh_pc -> 0.10551411 | G134: =G132/kla_sh_pc -> 0.10551411 | H134: KLA 市占 58% 為賣方數字，只供顯示
A135: B. 會計年度（C＝FY2025A … G＝FY2029；FY(t)＝CY(t−1) 下半＋CY(t) 上半）
A136: 半導體製程控制系統營收 FY | B136: US$M | C136: =a25_sys -> 8264.026 | D136: =a26_sys -> 9119.058 | E136: =(D133-h1_sys)+0.5*E133 -> 12654.68 | F136: =0.5*E133+0.5*F133 -> 14231.495 | G136: =0.5*F133+0.5*G133 -> 15672.614 | H136: FY2027＝CY2026 下半（錨點 − 上半實績）＋1/2 CY2027
A137: 服務營收 | B137: US$M | C137: =a25_svc -> 2683.308 | D137: =a26_svc -> 3125.939 | E137: =D137*(1+g_svc_A) -> 3563.5705 | F137: =E137*(1+g_svc_A) -> 4062.4703 | G137: =F137*(1+g_svc_A) -> 4631.2162
...

Sheet Sources
A1: 來源（SEC 原文可開啟；法說數字取自逐字稿網站）
A2: KLA FQ4-26 與 FY2026 新聞稿（SEC 8-K Exhibit 99.1，2026-07-28） | B2: https://www.sec.gov/Archives/edgar/data/0000319201/000031920126000024/exhibit991earningsrelease7.htm
A3: KLA FQ3-26 新聞稿（SEC 8-K Exhibit 99.1，2026-04-29） | B3: https://www.sec.gov/Archives/edgar/data/0000319201/000031920126000014/exhibit991earningsrelease3.htm
A4: KLA FY2026 10-K（中國占比、服務占比、訂單、出口管制） | B4: https://www.sec.gov/Archives/edgar/data/0000319201/000031920126000027/klac-20260630.htm
A5: SEC XBRL companyconcept：EarningsPerShareDiluted（歷年 EPS） | B5: https://data.sec.gov/api/xbrl/companyconcept/CIK0000319201/us-gaap/EarningsPerShareDiluted.json
A6: KLA FQ4-26 法說逐字稿（MarketBeat） | B6: https://www.marketbeat.com/earnings/reports/2026-7-28-kla-co-stock/
A7: TIKR：KLA FQ4-26 摘要（2026-07-29） | B7: https://www.tikr.com/blog/kla-corporations-q4-earnings-hit-a-record-3-66-billion-the-guide-points-higher-still
A8: MIAX：KLAC 10 比 1 分割通知（除權 2026-06-12） | B8: https://www.miaxglobal.com/sites/default/files/alert-files/KLAC_Split_58941.pdf
A9: tipranks：財報日 2026-10-28（FQ1-27）、10 月收盤價 | B9: https://www.tipranks.com/stocks/klac/earnings
A10: stockanalysis：股價歷史（2026-10-23 收盤 145.61） | B10: https://stockanalysis.com/stocks/klac/history/
A11: stockanalysis：年度財報（FY2022–26）與共識（2026-10-20） | B11: https://stockanalysis.com/stocks/klac/forecast/
A12: Yahoo Finance：共識（FY2027、FY2028、FQ1、FQ2） | B12: https://finance.yahoo.com/quote/KLAC/analysis/
A13: digrin：年底收盤價（Real price） | B13: https://www.digrin.com/stocks/detail/KLAC/price
... A17: SemiAnalysis | B17: 未使用
