Workbook

Sheet 摘要
A1: OpenAI 收支模型 — 摘要（討論用 v0.5；FY2025A–FY2030E；$B）
A2: ="情境："&輸入!$C$5&"｜付款型態："&輸入!$C$6&"｜檢查未通過："&資金與檢查!C63 -> 情境：base｜付款型態：ramp｜檢查未通過：0
A3: 項目 | B3: 單位 | C3: 2025 | D3: 2026 | E3: 2027 | F3: 2028 | G3: 2029 | H3: 2030 | I3: 2026–30 合計 | J3: 說明
A4: 營收（正向）
A5: 訂閱 | B5: $B | C5: =營收彙總!C18 -> 9.444 | D5: =營收彙總!D18 -> 17.7204 | E5: =營收彙總!E18 -> 26.631339 | F5: =營收彙總!F18 -> 35.564322 | G5: =營收彙總!G18 -> 42.949748 | H5: =營收彙總!H18 -> 49.424817 | I5: =SUM(D5:H5) -> 172.29063
A6: API | B6: $B | C6: =營收彙總!C19 -> 3.626 | D6: =營收彙總!D19 -> 14.440681 | E6: =營收彙總!E19 -> 24.079836 | F6: =營收彙總!F19 -> 36.408712 | G6: =營收彙總!G19 -> 50.061979 | H6: =營收彙總!H19 -> 64.880324 | I6: =SUM(D6:H6) -> 189.87153
A7: 核心（訂閱＋API） | B7: $B | C7: =營收彙總!C20 -> 13.07 | D7: =營收彙總!D20 -> 32.161081 | E7: =營收彙總!E20 -> 50.711175 | F7: =營收彙總!F20 -> 71.973033 | G7: =營收彙總!G20 -> 93.011726 | H7: =營收彙總!H20 -> 114.30514 | I7: =SUM(D7:H7) -> 362.16216
A8: 廣告（不進核心） | B8: $B | C8: =營收彙總!C21 -> 0 | D8: =營收彙總!D21 -> 0.74295 | E8: =營收彙總!E21 -> 1.858427 | F8: =營收彙總!F21 -> 2.9106078 | G8: =營收彙總!G21 -> 4.1568065 | H8: =營收彙總!H21 -> 5.5761571 | I8: =SUM(D8:H8) -> 15.244948
A9: 總額 | B9: $B | C9: =營收彙總!C22 -> 13.07 | D9: =營收彙總!D22 -> 32.904031 | E9: =營收彙總!E22 -> 52.569602 | F9: =營收彙總!F22 -> 74.883641 | G9: =營收彙總!G22 -> 97.168533 | H9: =營收彙總!H22 -> 119.8813 | I9: =SUM(D9:H9) -> 377.40711
A10: Microsoft 分潤 | B10: $B | C10: =營收彙總!C23 -> 2.614 | D10: =營收彙總!D23 -> 6.5808062 | E10: =營收彙總!E23 -> 10.51392 | F10: =營收彙總!F23 -> 14.976728 | G10: =營收彙總!G23 -> 5.9285452 | H10: =營收彙總!H23 -> 0 | I10: =SUM(D10:H10) -> 38
A11: 淨額 | B11: $B | C11: =營收彙總!C25 -> 10.456 | D11: =營收彙總!D25 -> 26.323225 | E11: =營收彙總!E25 -> 42.055681 | F11: =營收彙總!F25 -> 59.906913 | G11: =營收彙總!G25 -> 91.239988 | H11: =營收彙總!H25 -> 119.8813 | I11: =SUM(D11:H11) -> 339.40711
A12: 其中：消費端 | B12: $B | C12: =營收彙總!C10 -> 8.364 | D12: =營收彙總!D10 -> 13.42335 | E12: =營收彙總!E10 -> 19.129766 | F12: =營收彙總!F10 -> 24.79493 | G12: =營收彙總!G10 -> 29.826554 | H12: =營收彙總!H10 -> 34.840974
A13: 其中：企業端 | B13: $B | C13: =營收彙總!C15 -> 4.706 | D13: =營收彙總!D15 -> 19.480681 | E13: =營收彙總!E15 -> 33.439836 | F13: =營收彙總!F15 -> 50.088712 | G13: =營收彙總!G15 -> 67.341979 | H13: =營收彙總!H15 -> 85.040324
A14: 企業端占總額 | B14: % | C14: =營收彙總!C16 -> 0.36006121 | D14: =營收彙總!D16 -> 0.59204543 | E14: =營收彙總!E16 -> 0.63610594 | F14: =營收彙總!F16 -> 0.66888723 | G14: =營收彙總!G16 -> 0.69304307 | H14: =營收彙總!H16 -> 0.70937106
A15: 算力（GW；VR-eq＝Vera Rubin 等值）
A16: 實體 GW（年平均） | B16: GW | C16: =算力MW!C13 -> 1.25 | D16: =算力MW!D13 -> 2.8342063 | E16: =算力MW!E13 -> 9.4017725 | F16: =算力MW!F13 -> 11.70082 | G16: =算力MW!G13 -> 14.34709 | H16: =算力MW!H13 -> 16.593915
A17: VR-eq GW 供給 | B17: GW | C17: =算力MW!C22 -> 0.37614802 | D17: =算力MW!D22 -> 1.1974885 | E17: =算力MW!E22 -> 5.8270608 | F17: =算力MW!F22 -> 9.3102116 | G17: =算力MW!G22 -> 12.990705 | H17: =算力MW!H22 -> 16.805149
A18: 推論 GW | B18: GW | C18: =算力MW!C33 -> 0.15488448 | D18: =算力MW!D33 -> 0.33633783 | E18: =算力MW!E33 -> 0.58922516 | F18: =算力MW!F33 -> 0.99464747 | G18: =算力MW!G33 -> 1.6380119 | H18: =算力MW!H33 -> 2.6782466
A19: 訓練 GW | B19: GW | C19: =算力MW!C34 -> 0.22126354 | D19: =算力MW!D34 -> 0.74140184 | E19: =算力MW!E34 -> 4.6551296 | F19: =算力MW!F34 -> 7.384543 | G19: =算力MW!G34 -> 10.053622 | H19: =算力MW!H34 -> 12.446388
A20: 閒置 GW | B20: GW | C20: =算力MW!C35 -> 0 | D20: =算力MW!D35 -> 0.11974885 | E20: =算力MW!E35 -> 0.58270608 | F20: =算力MW!F35 -> 0.93102116 | G20: =算力MW!G35 -> 1.2990705 | H20: =算力MW!H35 -> 1.6805149
A21: 容量上限係數（1＝未受限） | B21: x | C21: =算力MW!C32 -> 1 | D21: =算力MW!D32 -> 1 | E21: =算力MW!E32 -> 1 | F21: =算力MW!F32 -> 1 | G21: =算力MW!G32 -> 1 | H21: =算力MW!H32 -> 1
A22: 營收 ÷ 實體 GW | B22: $B/GW | C22: =算力MW!C50 -> 10.456 | D22: =算力MW!D50 -> 11.60961 | E22: =算力MW!E50 -> 5.5914565 | F22: =算力MW!F50 -> 6.3998626 | G22: =算力MW!G50 -> 6.7726998 | H22: =算力MW!H50 -> 7.2244131
A23: 算力成本 ÷ VR-eq GW | B23: $B/GW | C23: =算力MW!C42 -> 54.233969 | D23: =算力MW!D42 -> 27.758625 | E23: =算力MW!E42 -> 19.912393 | F23: =算力MW!F42 -> 15.141779 | G23: =算力MW!G42 -> 13.020397 | H23: =算力MW!H42 -> 11.400292
A24: 成本（推論與訓練）
A25: 推論成本 | B25: $B | C25: =營收彙總!C43 -> 8.4 | D25: =營收彙總!D43 -> 9.3362756 | E25: =營收彙總!E43 -> 11.732883 | F25: =營收彙總!F43 -> 15.060732 | G25: =營收彙總!G43 -> 21.327565 | H25: =營收彙總!H43 -> 30.532794 | I25: =SUM(D25:H25) -> 87.990249
A26: 毛利率 | B26: % | C26: =營收彙總!C45 -> 0.35730681 | D26: =營收彙總!D45 -> 0.71625739 | E26: =營收彙總!E45 -> 0.7768124 | F26: =營收彙總!F45 -> 0.79887821 | G26: =營收彙總!G45 -> 0.78050955 | H26: =營收彙總!H45 -> 0.74530812
A27: 訓練成本 | B27: $B | C27: =營收彙總!C46 -> 12 | D27: =營收彙總!D46 -> 20.580296 | E27: =營收彙總!E46 -> 92.694771 | F27: =營收彙總!F46 -> 111.81512 | G27: =營收彙總!G46 -> 130.90215 | H27: =營收彙總!H46 -> 141.89246 | I27: =SUM(D27:H27) -> 497.88479
A28: 扣除訓練後貢獻率 | B28: % | C28: =營收彙總!C49 -> -0.56082632 | D28: =營收彙總!D49 -> -0.010229865 | E28: =營收彙總!E49 -> -1.2071829 | F28: =營收彙總!F49 -> -0.88256293 | G28: =營收彙總!G49 -> -0.74072947 | H28: =營收彙總!H49 -> -0.59811091
A29: 對照管理層目標（反向）
A30: 管理層目標 | B30: $B | C30: =反向!C4 -> 13.07 | D30: =反向!D4 -> 36 | E30: =反向!E4 -> 75.1 | F30: =反向!F4 -> 141.5 | G30: =反向!G4 -> 237.4 | H30: =反向!H4 -> 350 | I30: =SUM(D30:H30) -> 840
A31: 達標所需核心倍數（等比例） | B31: x | D31: =反向!D11 -> 1.0962645 | E31: =反向!E11 -> 1.4442886 | F31: =反向!F11 -> 1.9255739 | G31: =反向!G11 -> 2.5076751 | H31: =反向!H11 -> 3.0131964
A32: 支出與資金
A33: 算力現金（合約＋自有） | B33: $B | C33: =支出!C14 -> 14.755238 | D33: =支出!D14 -> 53.240635 | E33: =支出!E14 -> 141.72603 | F33: =支出!F14 -> 175.21143 | G33: =支出!G14 -> 208.69683 | H33: =支出!H14 -> 228.22222 | I33: =SUM(D33:H33) -> 807.09714
A34: 自由現金流（正向） | B34: $B | D34: =資金與檢查!D9 -> -37.77574 | E34: =資金與檢查!E9 -> -113.60129 | F34: =資金與檢查!F9 -> -131.77892 | G34: =資金與檢查!G9 -> -134.94717 | H34: =資金與檢查!H9 -> -125.12431 | I34: =SUM(D34:H34) -> -543.22743
A35: 累計外部資金需求（正向） | B35: $B | D35: =資金與檢查!D15 -> 0 | E35: =資金與檢查!E15 -> 34.377035 | F35: =資金與檢查!F15 -> 166.15595 | G35: =資金與檢查!G15 -> 301.10313 | H35: =資金與檢查!H15 -> 426.22743
A36: 自由現金流（反向：目標營收） | B36: $B | D36: =資金與檢查!D26 -> -36.320635 | E36: =資金與檢查!E26 -> -101.54753 | F36: =資金與檢查!F26 -> -80.621429 | G36: =資金與檢查!G26 -> -14.028825 | H36: =資金與檢查!H26 -> 72.777778 | I36: =SUM(D36:H36) -> -159.74064
A37: 累計外部資金需求（反向） | B37: $B | D37: =資金與檢查!D32 -> 0 | E37: =資金與檢查!E32 -> 20.868167 | F37: =資金與檢查!F32 -> 101.4896 | G37: =資金與檢查!G32 -> 115.51842 | H37: =資金與檢查!H32 -> 115.51842
A39: 閱讀順序：摘要 → 算力MW → 營收彙總 → 推論成本／訓練成本 → 反向 → 支出 → 資金與檢查；輸入全部在「輸入」頁（藍字）。
A40: 顏色：藍＝輸入；黑＝公式；黃底＝關鍵假設／選單。標記：Verified／Interested-party／Analogy／Assumed／Derived／Decision。
A41: 本檔為討論用；定稿後由 CC 依規格（定稿時改版）以 build 程式產生正式版（company.json → Excel → HTML）。

Sheet 輸入
A1: OpenAI 收支模型 — 輸入（藍字＝可改輸入；數值來源：openai_token_revenue.json v0.5）
A2: 所有輸入集中於此頁；其他頁只放公式。數列不足之年度以最後一值延伸。
A3: 項目 | B3: 單位 | C3: 2025 | D3: 2026 | E3: 2027 | F3: 2028 | G3: 2029 | H3: 2030 | I3: 標記 | J3: 來源／說明 | K3: 查核
A4: 控制
A5: 情境（low／base／high） | B5: 選單 | C5: base | I5: Decision | J5: D11 情境軸：API 彈性、牌價年變動、訂閱每任務 token 成長 | K5: 假設
A6: 未揭露時程合約之付款型態（even／ramp） | B6: 選單 | C6: ramp | I6: Decision | J6: N4(b)：期間內線性爬升（Andy 2026-09-29） | K6: 假設
A7: 計入 Amazon 條件式 $35B（1＝是） | B7: 0/1 | C7: 0 | I7: Decision | J7: 以 IPO 或 AGI 里程碑為條件；base 不計入 | K7: 假設
A8: 實際數與錨點
A9: FY2025 營收 | B9: $B | C9: 13.07 | I9: Interested-party | J9: Fortune/FT 2026-06 報導之 FY2025 認列營收（經查核數字外流） | K9: 待查核-報導
A10: 2026 Q1 營收 | B10: $B | C10: 5.7 | I10: Interested-party | J10: The Information 2026-06-16（股東文件） | K10: 待查核-報導
A11: 2026 Q2 營收 | B11: $B | C11: 6.7 | I11: Interested-party | J11: WSJ 2026-08-18（告知投資人） | K11: 待查核-報導
A12: FY2025 營業成本（含推論） | B12: $B | C12: 7.5 | I12: Interested-party | J12: 同上；cost of revenue 含推論 | K12: 待查核-報導
A13: FY2025 API 處理 token（揭露推估） | B13: T | C13: 2628 | I13: Derived | J13: FY 平均約 5B/min（workbook 列 242 估計）× 525,600 分 | K13: 待查核-workbook
A14: FY2026 獨立推估下限 | B14: $B | C14: 31 | I14: Derived | J14: Q1 5.7 + Q2 6.7（WSJ）+ 下半年以 8 月 ARR $40B 外推；上限放寬至簡報 36（7 月 ARR 月增 20%） | K14: 待查核-報導
A15: FY2026 獨立推估上限 | B15: $B | C15: 36 | I15: Derived | J15: 上限放寬至 7 月簡報 $36B | K15: 待查核-報導
A16: Microsoft 營收分潤
A17: 分潤比率 | B17: % | C17: 0.2 | I17: Interested-party | J17: CNBC 2026-04-27 引述知情人士；VentureBeat 同 | K17: 待查核-報導
A18: 分潤總額上限 | B18: $B | C18: 38 | I18: Interested-party | J18: The Information 2026-05（經 AI Magazine、GuruFocus 轉述） | K18: 待查核-報導
A19: 上限起算年 | B19: 年 | C19: 2026 | I19: Decision | J19: N2(a) | K19: 假設
A20: 分潤付至 | B20: 年 | C20: 2030 | I20: Verified | J20: OpenAI／Microsoft 2026-04-27 公告：付款持續至 2030，受總額上限 | K20: 已核實
A21: API：牌價（FY 平均，$/M tokens；層級角色口徑 N3a）
A22: 頂層 輸入牌價 2025–26 | B22: $/M | C22: 2.5 | D22: 6.6 | I22: Analogy/Derived | J22: 2025 Analogy；2026 依 7–9 月價格事件按月加權 | K22: 待查核-報導
A23: 頂層 輸出牌價 2025–26 | B23: $/M | C23: 14 | D23: 35.8 | I23: Analogy/Derived | J23: openai.com 2026-07-30 GPT-5.6 降價公告；GPT-6 Sol/Luna 2026-09-22 發布（Techzine、MarkTechPost）；GPT-6 Astra 2026-09-03 | K23: 待查核-報導
A24: 中層 輸入牌價 2025–26 | B24: $/M | C24: 1.5 | D24: 2.29 | I24: Analogy/Derived | J24: 2025 Analogy；2026 依 7–9 月價格事件按月加權 | K24: 待查核-報導
A25: 中層 輸出牌價 2025–26 | B25: $/M | C25: 8 | D25: 13.25 | I25: Analogy/Derived | J25: openai.com 2026-07-30 GPT-5.6 降價公告；GPT-6 Sol/Luna 2026-09-22 發布（Techzine、MarkTechPost）；GPT-6 Astra 2026-09-03 | K25: 待查核-報導
A26: 低層 輸入牌價 2025–26 | B26: $/M | C26: 0.2 | D26: 0.64 | I26: Analogy/Derived | J26: 2025 Analogy；2026 依 7–9 月價格事件按月加權 | K26: 待查核-報導
A27: 低層 輸出牌價 2025–26 | B27: $/M | C27: 1 | D27: 3.83 | I27: Analogy/Derived | J27: openai.com 2026-07-30 GPT-5.6 降價公告；GPT-6 Sol/Luna 2026-09-22 發布（Techzine、MarkTechPost）；GPT-6 Astra 2026-09-03 | K27: 待查核-報導
A28: API：情境參數（欄 C＝low、D＝base、E＝high、F＝選用）
C29: low | D29: base | E29: high | F29: 選用
A30: 頂層牌價年變動（2027 起） | B30: %/年 | C30: -0.45 | D30: -0.3 | E30: -0.3 | F30: =INDEX(C30:E30,MATCH($C$5,$C$29:$E$29,0)) -> -0.3 | I30: Assumed | J30: 情境軸 | K30: 假設
A31: 中層牌價年變動（2027 起） | B31: %/年 | C31: -0.6 | D31: -0.4 | E31: -0.4 | F31: =INDEX(C31:E31,MATCH($C$5,$C$29:$E$29,0)) -> -0.4 | I31: Assumed | J31: 情境軸 | K31: 假設
A32: 低層牌價年變動（2027 起） | B32: %/年 | C32: -0.6 | D32: -0.4 | E32: -0.4 | F32: =INDEX(C32:E32,MATCH($C$5,$C$29:$E$29,0)) -> -0.4 | I32: Assumed | J32: 情境軸 | K32: 假設
A33: 彈性：任務數對單價 | B33: ε | C33: -0.35 | D33: -0.7 | E33: -1.05 | F33: =INDEX(C33:E33,MATCH($C$5,$C$29:$E$29,0)) -> -0.7 | I33: Assumed | J33: 無法由公開資料分離（價格與能力同時變動） | K33: 假設
A34: 彈性：每任務 token 對單價 | B34: ε | C34: -0.15 | D34: -0.3 | E34: -0.45 | F34: =INDEX(C34:E34,MATCH($C$5,$C$29:$E$29,0)) -> -0.3 | I34: Assumed | J34: 同上 | K34: 假設
A35: Plus→Go 遷移：公司 2026 計畫幅度之比例 | B35: x | C35: 0 | D35: 0.3 | E35: 0.8 | F35: =INDEX(C35:E35,MATCH($C$5,$C$29:$E$29,0)) -> 0.3 | I35: Decision | J35: T4：low 0、base 30%、high 80% | K35: 假設
A36: 訂閱每任務 token 年成長（2027 起） | B36: %/年 | C36: 0.25 | D36: 0.15 | E36: 0.1 | F36: =INDEX(C36:E36,MATCH($C$5,$C$29:$E$29,0)) -> 0.15 | I36: Assumed | J36: 只影響成本，不影響訂閱營收 | K36: 假設
A37: API：組合、折扣與量
A38: token 組合：頂層占比 | B38: % | C38: 0.4 | D38: 0.15 | E38: 0.15 | F38: 0.15 | G38: 0.15 | H38: 0.15 | I38: Assumed | K38: 假設
A39: token 組合：中層占比 | B39: % | C39: 0.4 | D39: 0.45 | E39: 0.45 | F39: 0.45 | G39: 0.45 | H39: 0.45 | I39: Assumed | J39: 低層＝1−頂層−中層 | K39: 假設
A40: 輸出 token 占比 φ | B40: % | C40: 0.2 | I40: Analogy | J40: workbook API I:O 約 4:1；代理式工作負載使輸出占比上升 | K40: 待查核-workbook
A41: 快取命中率 h | B41: % | C41: 0.55 | I41: Assumed | K41: 假設
A42: 快取輸入價比 r | B42: % | C42: 0.1 | I42: Verified | J42: 定價頁：cached input = 輸入價 10% | K42: 已核實
A43: 加權折扣 d | B43: % | C43: 0.2 | I43: Assumed | J43: Batch/Flex 半價 [Verified]；企業折扣 [Analogy]；兩者合併為加權折扣 | K43: 假設
A44: 每任務 token 基準（2025） | B44: K tok | C44: 10 | I44: Assumed | J44: 層級正規化：只影響 N 與 k 的水準拆分，不影響營收 | K44: 假設
A45: 任務數年成長（未計價格反應） | B45: % | C45: 0 | D45: 1.34 | E45: 0.45 | F45: 0.35 | G45: 0.25 | H45: 0.2 | I45: Assumed | J45: 2026 為校準年 | K45: 假設
A46: 每任務 token 年成長（未計價格反應） | B46: % | C46: 0 | D46: 0.2 | E46: 0.15 | F46: 0.12 | G46: 0.1 | H46: 0.08 | I46: Assumed | K46: 假設
A47: 彈性生效年 | B47: 年 | C47: 2027 | I47: Decision | J47: 2025–26 為校準年 | K47: 假設
A48: 訂閱：人數（FY 平均）、ARPU、使用量
A49: Free 人數 | B49: M | C49: 600 | D49: 950 | E49: 1250 | F49: 1500 | G49: 1700 | H49: 1850 | I49: Analogy | J49: WAU 900M（2026-02，OpenAI）；2027+ Assumed | K49: 待查核-報導
A50: Go 人數（無遷移基準） | B50: M | C50: 2 | D50: 10 | E50: 22 | F50: 35 | G50: 45 | H50: 55 | I50: Assumed | J50: 2025 年 3M（年底，The Information）；2026+ 為無遷移基準 [Assumed] | K50: 待查核-報導
A51: Plus 人數（無遷移基準） | B51: M | C51: 30 | D51: 46 | E51: 52 | F51: 57 | G51: 61 | H51: 64 | I51: Interested-party | J51: 2025：7 月 Plus+Pro 約 35M（Reuters/The Information 2025-11）、OpenAI 內部文件 2025 年 44M（The Information 2026-04-28）→ FY 平均 28–33M；2026+ 為「無遷移」基準 [Assumed] | K51: 待查核-報導
A52: Pro 人數 | B52: M | C52: 0.5 | D52: 1 | E52: 1.5 | F52: 2 | G52: 2.5 | H52: 3 | I52: Interested-party | J52: 內部預測：2026 倍增但 <1% 付費總數（The Information 2026-04-28）；2027+ Assumed | K52: 待查核-報導
A53: 企業席位 人數 | B53: M | C53: 3 | D53: 14 | E53: 26 | F53: 38 | G53: 48 | H53: 56 | I53: Assumed | J53: 逾 9M 付費企業用戶（OpenAI 2026-02）；FY2025 平均 Assumed | K53: 待查核-報導
A54: 公司計畫 2026 Go 人數 | B54: M | C54: 112 | I54: Interested-party | J54: The Information 2026-04-28（年初內部預測） | K54: 待查核-報導
A55: 公司計畫 2026 Plus 人數 | B55: M | C55: 9 | I55: Interested-party | J55: 同上 | K55: 待查核-報導
A56: Go 實收 ARPU | B56: $/月 | C56: 6 | D56: 6 | E56: 6 | F56: 6 | G56: 6 | H56: 6 | I56: Assumed | K56: 假設
A57: Plus 實收 ARPU | B57: $/月 | C57: 19.5 | D57: 19 | E57: 19 | F57: 19 | G57: 19 | H57: 19 | I57: Assumed | J57: $20 美國、僅月繳（2026-09 定價頁）；區間反映含稅地區與促銷 | K57: 假設
A58: Pro 實收 ARPU | B58: $/月 | C58: 200 | D58: 150 | E58: 150 | F58: 150 | G58: 150 | H58: 150 | I58: Assumed | J58: 2026 起兩檔 $100/$200 加權 | K58: 假設
A59: 企業席位 實收 ARPU | B59: $/月 | C59: 30 | D59: 30 | E59: 30 | F59: 30 | G59: 30 | H59: 30 | I59: Assumed | J59: Business $20-25 [Verified]；Enterprise 議價 $60+ [Analogy] | K59: 假設
A60: Free 每日任務數 2025–26 | B60: 次/日 | C60: 1.7 | D60: 1.7 | I60: Assumed | J60: Tokenomics workbook 8B-ii 註記（未經查核）；總量對照：2025-07 每日 2.5B 則訊息（OpenAI） | K60: 待查核-workbook
A61: Go 每日任務數 2025–26 | B61: 次/日 | C61: 5.3 | D61: 5.7 | I61: Assumed | J61: Tokenomics workbook 8B-ii 註記（未經查核）；總量對照：2025-07 每日 2.5B 則訊息（OpenAI） | K61: 待查核-workbook
A62: Plus 每日任務數 2025–26 | B62: 次/日 | C62: 13.4 | D62: 17.9 | I62: Assumed | J62: Tokenomics workbook 8B-ii 註記（未經查核）；總量對照：2025-07 每日 2.5B 則訊息（OpenAI） | K62: 待查核-workbook
A63: Pro 每日任務數 2025–26 | B63: 次/日 | C63: 41 | D63: 51.4 | I63: Assumed | J63: Tokenomics workbook 8B-ii 註記（未經查核）；總量對照：2025-07 每日 2.5B 則訊息（OpenAI） | K63: 待查核-workbook
A64: 企業席位 每日任務數 2025–26 | B64: 次/日 | C64: 10.7 | D64: 14.3 | I64: Assumed | J64: Tokenomics workbook 8B-ii 註記（未經查核）；總量對照：2025-07 每日 2.5B 則訊息（OpenAI） | K64: 待查核-workbook
A65: Free 每任務 token 2025–26 | B65: K tok | C65: 2 | D65: 2.94 | I65: Assumed | J65: Tokenomics workbook（未經查核）；於「推論成本」頁以 FY2025 成本分拆反推校正倍數 k | K65: 待查核-workbook
A66: Go 每任務 token 2025–26 | B66: K tok | C66: 3 | D66: 4.39 | I66: Assumed | J66: Tokenomics workbook（未經查核）；於「推論成本」頁以 FY2025 成本分拆反推校正倍數 k | K66: 待查核-workbook
A67: Plus 每任務 token 2025–26 | B67: K tok | C67: 4 | D67: 6.15 | I67: Assumed | J67: Tokenomics workbook（未經查核）；於「推論成本」頁以 FY2025 成本分拆反推校正倍數 k | K67: 待查核-workbook
A68: Pro 每任務 token 2025–26 | B68: K tok | C68: 10 | D68: 15.6 | I68: Assumed | J68: Tokenomics workbook（未經查核）；於「推論成本」頁以 FY2025 成本分拆反推校正倍數 k | K68: 待查核-workbook
A69: 企業席位 每任務 token 2025–26 | B69: K tok | C69: 4 | D69: 5.94 | I69: Assumed | J69: Tokenomics workbook（未經查核）；於「推論成本」頁以 FY2025 成本分拆反推校正倍數 k | K69: 待查核-workbook
A70: 每日任務數年成長（2027 起） | B70: % | C70: 0.1 | I70: Assumed | K70: 假設
A71: Vera Rubin NVL72 規格（預設沿用 Tokenomics v4；要改一起改）與推論物理參數
A72: 機架 HBM 頻寬 | B72: TB/s | C72: 1580 | I72: Derived | J72: Tokenomics v4（Config F 欄 VR NVL72 預設；要改一起改） Config!F18 | K72: 待查核-workbook
A73: 機架 FP4 推論算力 | B73: PFLOPS | C73: 3600 | I73: Derived | J73: Tokenomics v4（Config F 欄 VR NVL72 預設；要改一起改） Config!F19 | K73: 待查核-workbook
A74: 機架 HBM 容量 | B74: TB | C74: 20.7 | I74: Derived | J74: Tokenomics v4（Config F 欄 VR NVL72 預設；要改一起改） Config!F17 | K74: 待查核-workbook
A75: MFU（prefill） | B75: % | C75: 0.35 | I75: Analogy | J75: Tokenomics v4（Config F 欄 VR NVL72 預設；要改一起改） Config!B46 | K75: 待查核-workbook
A76: 每架年營運費用（含折舊） | B76: $M/年 | C76: 1.7667 | I76: Derived | J76: Tokenomics v4（Config F 欄 VR NVL72 預設；要改一起改） DC_Cost_Model!D88 ÷ D9；DC_Cost_Model：年營運費用 $9,298M ÷ 5,263 架（含折舊） | K76: 待查核-workbook
A77: 推測解碼每步接受 token | B77: tok | C77: 2.94 | I77: Analogy | J77: Tokenomics v4（Config F 欄 VR NVL72 預設；要改一起改） Config!B59 | K77: 待查核-workbook
A78: 機架平均利用率 | B78: % | C78: 0.6 | I78: Assumed | J78: 區間 40–80% | K78: 假設
A79: decode 批次上限 | B79: 序列 | C79: 256 | I79: Assumed | J79: 區間 64–1,024；決定權重讀取的攤提 | K79: 假設
A80: 平均上下文長度 | B80: K tok | C80: 8 | I80: Assumed | J80: 區間 4–32K；決定 KV 快取讀取量 | K80: 假設
A81: prefill 注意力額外計算倍數 | B81: x | C81: 1.1 | I81: Assumed | K81: 假設
A82: 快取輸入成本 ÷ 新鮮輸入成本 | B82: % | C82: 0.1 | I82: Analogy | J82: 牌價快取讀取比 0.05–0.1 代理 | K82: 待查核-報導
A83: Luna（低層） 總參數 | B83: B | C83: 284 | I83: Analogy | J83: Tokenomics 預設架構類比：DeepSeek V4-Flash | K83: 待查核-workbook
A84: Luna（低層） 啟用參數 | B84: B | C84: 13 | I84: Analogy | J84: Tokenomics 預設架構類比：DeepSeek V4-Flash | K84: 待查核-workbook
A85: Luna（低層） 每 token KV 快取 | B85: bytes | C85: 2795 | I85: Analogy | J85: Tokenomics 預設架構類比：DeepSeek V4-Flash | K85: 待查核-workbook
A86: Luna（低層） 每參數位元組 | B86: bytes | C86: 0.51 | I86: Analogy | J86: Tokenomics 預設架構類比：DeepSeek V4-Flash | K86: 待查核-workbook
A87: Sol（中層） 總參數 | B87: B | C87: 1600 | I87: Analogy | J87: Tokenomics 預設架構類比：DeepSeek V4-Pro | K87: 待查核-workbook
A88: Sol（中層） 啟用參數 | B88: B | C88: 49 | I88: Analogy | J88: Tokenomics 預設架構類比：DeepSeek V4-Pro | K88: 待查核-workbook
A89: Sol（中層） 每 token KV 快取 | B89: bytes | C89: 3965 | I89: Analogy | J89: Tokenomics 預設架構類比：DeepSeek V4-Pro | K89: 待查核-workbook
A90: Sol（中層） 每參數位元組 | B90: bytes | C90: 0.507 | I90: Analogy | J90: Tokenomics 預設架構類比：DeepSeek V4-Pro | K90: 待查核-workbook
A91: Astra（頂層） 總參數 | B91: B | C91: 4000 | I91: Analogy | J91: Tokenomics 預設架構類比：Closed-frontier proxy | K91: 待查核-workbook
A92: Astra（頂層） 啟用參數 | B92: B | C92: 180 | I92: Analogy | J92: Tokenomics 預設架構類比：Closed-frontier proxy | K92: 待查核-workbook
A93: Astra（頂層） 每 token KV 快取 | B93: bytes | C93: 204800 | I93: Analogy | J93: Tokenomics 預設架構類比：Closed-frontier proxy | K93: 待查核-workbook
A94: Astra（頂層） 每參數位元組 | B94: bytes | C94: 0.53 | I94: Analogy | J94: Tokenomics 預設架構類比：Closed-frontier proxy | K94: 待查核-workbook
A95: 推論成本：各方案使用型態（模型組合 Luna／Sol／Astra、輸出占比含思考、快取命中）
A96: Free Luna 占比 | B96: % | C96: 0.9 | I96: Assumed | J96: T6／分層成本假設 | K96: 假設
A97: Free Sol 占比 | B97: % | C97: 0.1 | I97: Assumed | J97: T6／分層成本假設 | K97: 假設
A98: Free Astra 占比 | B98: % | C98: 0 | I98: Assumed | J98: T6／分層成本假設 | K98: 假設
A99: Free 輸出占比 | B99: % | C99: 0.25 | I99: Assumed | K99: 假設
A100: Free 快取命中 | B100: % | C100: 0.4 | I100: Assumed | K100: 假設
...

Sheet 查核清單
A1: 查核清單：輸入頁每一項的來源與查核狀態（workbook 來源值未經查核前不視為可用）
A2: ="待查核-workbook："&COUNTIF(E4:E164,"待查核-workbook")&" 待查核-報導："&COUNTIF(E4:E164,"待查核-報導")&" 假設："&COUNTIF(E4:E164,"假設")&" 已核實："&COUNTIF(E4:E164,"已核實") -> 待查核-workbook：38 待查核-報導：54 假設：66 已核實：3
A3: 項目 | B3: 單位 | C3: 目前值（首欄） | D3: 標記 | E3: 查核狀態 | F3: 來源 | G3: 建議查核方式
A4: 情境（low／base／high） | B4: 選單 | C4: =輸入!C5 -> base | D4: Decision | E4: 假設 | F4: D11 情境軸：API 彈性、牌價年變動、訂閱每任務 token 成長 | G4: 判斷題：檢視區間與敏感度，不需外部查核
A5: 未揭露時程合約之付款型態（even／ramp） | B5: 選單 | C5: =輸入!C6 -> ramp | D5: Decision | E5: 假設 | F5: N4(b)：期間內線性爬升（Andy 2026-09-29） | G5: 判斷題：檢視區間與敏感度，不需外部查核
A6: 計入 Amazon 條件式 $35B（1＝是） | B6: 0/1 | C6: =輸入!C7 -> 0 | D6: Decision | E6: 假設 | F6: 以 IPO 或 AGI 里程碑為條件；base 不計入 | G6: 判斷題：檢視區間與敏感度，不需外部查核
A7: FY2025 營收 | B7: $B | C7: =輸入!C9 -> 13.07 | D7: Interested-party | E7: 待查核-報導 | F7: Fortune/FT 2026-06 報導之 FY2025 認列營收（經查核數字外流） | G7: 取得原始報導或文件；確認口徑（年底或全年平均、總額或淨額、年化或認列）
A8: 2026 Q1 營收 | B8: $B | C8: =輸入!C10 -> 5.7 | D8: Interested-party | E8: 待查核-報導 | F8: The Information 2026-06-16（股東文件） | G8: 取得原始報導或文件；確認口徑（年底或全年平均、總額或淨額、年化或認列）
A9: 2026 Q2 營收 | B9: $B | C9: =輸入!C11 -> 6.7 | D9: Interested-party | E9: 待查核-報導 | F9: WSJ 2026-08-18（告知投資人） | G9: 取得原始報導或文件；確認口徑（年底或全年平均、總額或淨額、年化或認列）
A10: FY2025 營業成本（含推論） | B10: $B | C10: =輸入!C12 -> 7.5 | D10: Interested-party | E10: 待查核-報導 | F10: 同上；cost of revenue 含推論 | G10: 取得原始報導或文件；確認口徑（年底或全年平均、總額或淨額、年化或認列）
A11: FY2025 API 處理 token（揭露推估） | B11: T | C11: =輸入!C13 -> 2628 | D11: Derived | E11: 待查核-workbook | F11: FY 平均約 5B/min（workbook 列 242 估計）× 525,600 分 | G11: 回溯 Tokenomics workbook 原儲存格，找出原始出處並逐一核對；無出處者改標 Assumed
A12: FY2026 獨立推估下限 | B12: $B | C12: =輸入!C14 -> 31 | D12: Derived | E12: 待查核-報導 | F12: Q1 5.7 + Q2 6.7（WSJ）+ 下半年以 8 月 ARR $40B 外推；上限放寬至簡報 36（7 月 ARR 月增 20%） | G12: 取得原始報導或文件；確認口徑（年底或全年平均、總額或淨額、年化或認列）
A13: FY2026 獨立推估上限 | B13: $B | C13: =輸入!C15 -> 36 | D13: Derived | E13: 待查核-報導 | F13: 上限放寬至 7 月簡報 $36B | G13: 取得原始報導或文件；確認口徑（年底或全年平均、總額或淨額、年化或認列）
A14: 分潤比率 | B14: % | C14: =輸入!C17 -> 0.2 | D14: Interested-party | E14: 待查核-報導 | F14: CNBC 2026-04-27 引述知情人士；VentureBeat 同 | G14: 取得原始報導或文件；確認口徑（年底或全年平均、總額或淨額、年化或認列）
A15: 分潤總額上限 | B15: $B | C15: =輸入!C18 -> 38 | D15: Interested-party | E15: 待查核-報導 | F15: The Information 2026-05（經 AI Magazine、GuruFocus 轉述） | G15: 取得原始報導或文件；確認口徑（年底或全年平均、總額或淨額、年化或認列）
A16: 上限起算年 | B16: 年 | C16: =輸入!C19 -> 2026 | D16: Decision | E16: 假設 | F16: N2(a) | G16: 判斷題：檢視區間與敏感度，不需外部查核
A17: 分潤付至 | B17: 年 | C17: =輸入!C20 -> 2030 | D17: Verified | E17: 已核實 | F17: OpenAI／Microsoft 2026-04-27 公告：付款持續至 2030，受總額上限 | G17: —
A18: 頂層 輸入牌價 2025–26 | B18: $/M | C18: =輸入!C22 -> 2.5 | D18: Analogy/Derived | E18: 待查核-報導 | F18: 2025 Analogy；2026 依 7–9 月價格事件按月加權 | G18: 取得原始報導或文件；確認口徑（年底或全年平均、總額或淨額、年化或認列）
A19: 頂層 輸出牌價 2025–26 | B19: $/M | C19: =輸入!C23 -> 14 | D19: Analogy/Derived | E19: 待查核-報導 | F19: openai.com 2026-07-30 GPT-5.6 降價公告；GPT-6 Sol/Luna 2026-09-22 發布（Techzine、MarkTechPost）；GPT-6 Astra 2026-09-03 | G19: 取得原始報導或文件；確認口徑（年底或全年平均、總額或淨額、年化或認列）
A20: 中層 輸入牌價 2025–26 | B20: $/M | C20: =輸入!C24 -> 1.5 | D20: Analogy/Derived | E20: 待查核-報導 | F20: 2025 Analogy；2026 依 7–9 月價格事件按月加權 | G20: 取得原始報導或文件；確認口徑（年底或全年平均、總額或淨額、年化或認列）
A21: 中層 輸出牌價 2025–26 | B21: $/M | C21: =輸入!C25 -> 8 | D21: Analogy/Derived | E21: 待查核-報導 | F21: openai.com 2026-07-30 GPT-5.6 降價公告；GPT-6 Sol/Luna 2026-09-22 發布（Techzine、MarkTechPost）；GPT-6 Astra 2026-09-03 | G21: 取得原始報導或文件；確認口徑（年底或全年平均、總額或淨額、年化或認列）
A22: 低層 輸入牌價 2025–26 | B22: $/M | C22: =輸入!C26 -> 0.2 | D22: Analogy/Derived | E22: 待查核-報導 | F22: 2025 Analogy；2026 依 7–9 月價格事件按月加權 | G22: 取得原始報導或文件；確認口徑（年底或全年平均、總額或淨額、年化或認列）
A23: 低層 輸出牌價 2025–26 | B23: $/M | C23: =輸入!C27 -> 1 | D23: Analogy/Derived | E23: 待查核-報導 | F23: openai.com 2026-07-30 GPT-5.6 降價公告；GPT-6 Sol/Luna 2026-09-22 發布（Techzine、MarkTechPost）；GPT-6 Astra 2026-09-03 | G23: 取得原始報導或文件；確認口徑（年底或全年平均、總額或淨額、年化或認列）
A24: 頂層牌價年變動（2027 起） | B24: %/年 | C24: =輸入!C30 -> -0.45 | D24: Assumed | E24: 假設 | F24: 情境軸 | G24: 判斷題：檢視區間與敏感度，不需外部查核
A25: 中層牌價年變動（2027 起） | B25: %/年 | C25: =輸入!C31 -> -0.6 | D25: Assumed | E25: 假設 | F25: 情境軸 | G25: 判斷題：檢視區間與敏感度，不需外部查核
A26: 低層牌價年變動（2027 起） | B26: %/年 | C26: =輸入!C32 -> -0.6 | D26: Assumed | E26: 假設 | F26: 情境軸 | G26: 判斷題：檢視區間與敏感度，不需外部查核
A27: 彈性：任務數對單價 | B27: ε | C27: =輸入!C33 -> -0.35 | D27: Assumed | E27: 假設 | F27: 無法由公開資料分離（價格與能力同時變動） | G27: 判斷題：檢視區間與敏感度，不需外部查核
A28: 彈性：每任務 token 對單價 | B28: ε | C28: =輸入!C34 -> -0.15 | D28: Assumed | E28: 假設 | F28: 同上 | G28: 判斷題：檢視區間與敏感度，不需外部查核
A29: Plus→Go 遷移：公司 2026 計畫幅度之比例 | B29: x | C29: =輸入!C35 -> 0 | D29: Decision | E29: 假設 | F29: T4：low 0、base 30%、high 80% | G29: 判斷題：檢視區間與敏感度，不需外部查核
A30: 訂閱每任務 token 年成長（2027 起） | B30: %/年 | C30: =輸入!C36 -> 0.25 | D30: Assumed | E30: 假設 | F30: 只影響成本，不影響訂閱營收 | G30: 判斷題：檢視區間與敏感度，不需外部查核
A31: token 組合：頂層占比 | B31: % | C31: =輸入!C38 -> 0.4 | D31: Assumed | E31: 假設 | G31: 判斷題：檢視區間與敏感度，不需外部查核
A32: token 組合：中層占比 | B32: % | C32: =輸入!C39 -> 0.4 | D32: Assumed | E32: 假設 | F32: 低層＝1−頂層−中層 | G32: 判斷題：檢視區間與敏感度，不需外部查核
A33: 輸出 token 占比 φ | B33: % | C33: =輸入!C40 -> 0.2 | D33: Analogy | E33: 待查核-workbook | F33: workbook API I:O 約 4:1；代理式工作負載使輸出占比上升 | G33: 回溯 Tokenomics workbook 原儲存格，找出原始出處並逐一核對；無出處者改標 Assumed
A34: 快取命中率 h | B34: % | C34: =輸入!C41 -> 0.55 | D34: Assumed | E34: 假設 | G34: 判斷題：檢視區間與敏感度，不需外部查核
A35: 快取輸入價比 r | B35: % | C35: =輸入!C42 -> 0.1 | D35: Verified | E35: 已核實 | F35: 定價頁：cached input = 輸入價 10% | G35: —
A36: 加權折扣 d | B36: % | C36: =輸入!C43 -> 0.2 | D36: Assumed | E36: 假設 | F36: Batch/Flex 半價 [Verified]；企業折扣 [Analogy]；兩者合併為加權折扣 | G36: 判斷題：檢視區間與敏感度，不需外部查核
A37: 每任務 token 基準（2025） | B37: K tok | C37: =輸入!C44 -> 10 | D37: Assumed | E37: 假設 | F37: 層級正規化：只影響 N 與 k 的水準拆分，不影響營收 | G37: 判斷題：檢視區間與敏感度，不需外部查核
A38: 任務數年成長（未計價格反應） | B38: % | C38: =輸入!C45 -> 0 | D38: Assumed | E38: 假設 | F38: 2026 為校準年 | G38: 判斷題：檢視區間與敏感度，不需外部查核
A39: 每任務 token 年成長（未計價格反應） | B39: % | C39: =輸入!C46 -> 0 | D39: Assumed | E39: 假設 | G39: 判斷題：檢視區間與敏感度，不需外部查核
A40: 彈性生效年 | B40: 年 | C40: =輸入!C47 -> 2027 | D40: Decision | E40: 假設 | F40: 2025–26 為校準年 | G40: 判斷題：檢視區間與敏感度，不需外部查核
A41: Free 人數 | B41: M | C41: =輸入!C49 -> 600 | D41: Analogy | E41: 待查核-報導 | F41: WAU 900M（2026-02，OpenAI）；2027+ Assumed | G41: 取得原始報導或文件；確認口徑（年底或全年平均、總額或淨額、年化或認列）
A42: Go 人數（無遷移基準） | B42: M | C42: =輸入!C50 -> 2 | D42: Assumed | E42: 待查核-報導 | F42: 2025 年 3M（年底，The Information）；2026+ 為無遷移基準 [Assumed] | G42: 取得原始報導或文件；確認口徑（年底或全年平均、總額或淨額、年化或認列）
A43: Plus 人數（無遷移基準） | B43: M | C43: =輸入!C51 -> 30 | D43: Interested-party | E43: 待查核-報導 | F43: 2025：7 月 Plus+Pro 約 35M（Reuters/The Information 2025-11）、OpenAI 內部文件 2025 年 44M（The Information 2026-04-28）→ FY 平均 28–33M；2026+ 為「無遷移」基準 [Assumed] | G43: 取得原始報導或文件；確認口徑（年底或全年平均、總額或淨額、年化或認列）
A44: Pro 人數 | B44: M | C44: =輸入!C52 -> 0.5 | D44: Interested-party | E44: 待查核-報導 | F44: 內部預測：2026 倍增但 <1% 付費總數（The Information 2026-04-28）；2027+ Assumed | G44: 取得原始報導或文件；確認口徑（年底或全年平均、總額或淨額、年化或認列）
A45: 企業席位 人數 | B45: M | C45: =輸入!C53 -> 3 | D45: Assumed | E45: 待查核-報導 | F45: 逾 9M 付費企業用戶（OpenAI 2026-02）；FY2025 平均 Assumed | G45: 取得原始報導或文件；確認口徑（年底或全年平均、總額或淨額、年化或認列）
A46: 公司計畫 2026 Go 人數 | B46: M | C46: =輸入!C54 -> 112 | D46: Interested-party | E46: 待查核-報導 | F46: The Information 2026-04-28（年初內部預測） | G46: 取得原始報導或文件；確認口徑（年底或全年平均、總額或淨額、年化或認列）
A47: 公司計畫 2026 Plus 人數 | B47: M | C47: =輸入!C55 -> 9 | D47: Interested-party | E47: 待查核-報導 | F47: 同上 | G47: 取得原始報導或文件；確認口徑（年底或全年平均、總額或淨額、年化或認列）
A48: Go 實收 ARPU | B48: $/月 | C48: =輸入!C56 -> 6 | D48: Assumed | E48: 假設 | G48: 判斷題：檢視區間與敏感度，不需外部查核
A49: Plus 實收 ARPU | B49: $/月 | C49: =輸入!C57 -> 19.5 | D49: Assumed | E49: 假設 | F49: $20 美國、僅月繳（2026-09 定價頁）；區間反映含稅地區與促銷 | G49: 判斷題：檢視區間與敏感度，不需外部查核
A50: Pro 實收 ARPU | B50: $/月 | C50: =輸入!C58 -> 200 | D50: Assumed | E50: 假設 | F50: 2026 起兩檔 $100/$200 加權 | G50: 判斷題：檢視區間與敏感度，不需外部查核
A51: 企業席位 實收 ARPU | B51: $/月 | C51: =輸入!C59 -> 30 | D51: Assumed | E51: 假設 | F51: Business $20-25 [Verified]；Enterprise 議價 $60+ [Analogy] | G51: 判斷題：檢視區間與敏感度，不需外部查核
A52: Free 每日任務數 2025–26 | B52: 次/日 | C52: =輸入!C60 -> 1.7 | D52: Assumed | E52: 待查核-workbook | F52: Tokenomics workbook 8B-ii 註記（未經查核）；總量對照：2025-07 每日 2.5B 則訊息（OpenAI） | G52: 回溯 Tokenomics workbook 原儲存格，找出原始出處並逐一核對；無出處者改標 Assumed
A53: Go 每日任務數 2025–26 | B53: 次/日 | C53: =輸入!C61 -> 5.3 | D53: Assumed | E53: 待查核-workbook | F53: Tokenomics workbook 8B-ii 註記（未經查核）；總量對照：2025-07 每日 2.5B 則訊息（OpenAI） | G53: 回溯 Tokenomics workbook 原儲存格，找出原始出處並逐一核對；無出處者改標 Assumed
A54: Plus 每日任務數 2025–26 | B54: 次/日 | C54: =輸入!C62 -> 13.4 | D54: Assumed | E54: 待查核-workbook | F54: Tokenomics workbook 8B-ii 註記（未經查核）；總量對照：2025-07 每日 2.5B 則訊息（OpenAI） | G54: 回溯 Tokenomics workbook 原儲存格，找出原始出處並逐一核對；無出處者改標 Assumed
A55: Pro 每日任務數 2025–26 | B55: 次/日 | C55: =輸入!C63 -> 41 | D55: Assumed | E55: 待查核-workbook | F55: Tokenomics workbook 8B-ii 註記（未經查核）；總量對照：2025-07 每日 2.5B 則訊息（OpenAI） | G55: 回溯 Tokenomics workbook 原儲存格，找出原始出處並逐一核對；無出處者改標 Assumed
A56: 企業席位 每日任務數 2025–26 | B56: 次/日 | C56: =輸入!C64 -> 10.7 | D56: Assumed | E56: 待查核-workbook | F56: Tokenomics workbook 8B-ii 註記（未經查核）；總量對照：2025-07 每日 2.5B 則訊息（OpenAI） | G56: 回溯 Tokenomics workbook 原儲存格，找出原始出處並逐一核對；無出處者改標 Assumed
A57: Free 每任務 token 2025–26 | B57: K tok | C57: =輸入!C65 -> 2 | D57: Assumed | E57: 待查核-workbook | F57: Tokenomics workbook（未經查核）；於「推論成本」頁以 FY2025 成本分拆反推校正倍數 k | G57: 回溯 Tokenomics workbook 原儲存格，找出原始出處並逐一核對；無出處者改標 Assumed
A58: Go 每任務 token 2025–26 | B58: K tok | C58: =輸入!C66 -> 3 | D58: Assumed | E58: 待查核-workbook | F58: Tokenomics workbook（未經查核）；於「推論成本」頁以 FY2025 成本分拆反推校正倍數 k | G58: 回溯 Tokenomics workbook 原儲存格，找出原始出處並逐一核對；無出處者改標 Assumed
A59: Plus 每任務 token 2025–26 | B59: K tok | C59: =輸入!C67 -> 4 | D59: Assumed | E59: 待查核-workbook | F59: Tokenomics workbook（未經查核）；於「推論成本」頁以 FY2025 成本分拆反推校正倍數 k | G59: 回溯 Tokenomics workbook 原儲存格，找出原始出處並逐一核對；無出處者改標 Assumed
A60: Pro 每任務 token 2025–26 | B60: K tok | C60: =輸入!C68 -> 10 | D60: Assumed | E60: 待查核-workbook | F60: Tokenomics workbook（未經查核）；於「推論成本」頁以 FY2025 成本分拆反推校正倍數 k | G60: 回溯 Tokenomics workbook 原儲存格，找出原始出處並逐一核對；無出處者改標 Assumed
A61: 企業席位 每任務 token 2025–26 | B61: K tok | C61: =輸入!C69 -> 4 | D61: Assumed | E61: 待查核-workbook | F61: Tokenomics workbook（未經查核）；於「推論成本」頁以 FY2025 成本分拆反推校正倍數 k | G61: 回溯 Tokenomics workbook 原儲存格，找出原始出處並逐一核對；無出處者改標 Assumed
A62: 每日任務數年成長（2027 起） | B62: % | C62: =輸入!C70 -> 0.1 | D62: Assumed | E62: 假設 | G62: 判斷題：檢視區間與敏感度，不需外部查核
A63: 機架 HBM 頻寬 | B63: TB/s | C63: =輸入!C72 -> 1580 | D63: Derived | E63: 待查核-workbook | F63: Tokenomics v4（Config F 欄 VR NVL72 預設；要改一起改） Config!F18 | G63: 回溯 Tokenomics workbook 原儲存格，找出原始出處並逐一核對；無出處者改標 Assumed
A64: 機架 FP4 推論算力 | B64: PFLOPS | C64: =輸入!C73 -> 3600 | D64: Derived | E64: 待查核-workbook | F64: Tokenomics v4（Config F 欄 VR NVL72 預設；要改一起改） Config!F19 | G64: 回溯 Tokenomics workbook 原儲存格，找出原始出處並逐一核對；無出處者改標 Assumed
A65: 機架 HBM 容量 | B65: TB | C65: =輸入!C74 -> 20.7 | D65: Derived | E65: 待查核-workbook | F65: Tokenomics v4（Config F 欄 VR NVL72 預設；要改一起改） Config!F17 | G65: 回溯 Tokenomics workbook 原儲存格，找出原始出處並逐一核對；無出處者改標 Assumed
A66: MFU（prefill） | B66: % | C66: =輸入!C75 -> 0.35 | D66: Analogy | E66: 待查核-workbook | F66: Tokenomics v4（Config F 欄 VR NVL72 預設；要改一起改） Config!B46 | G66: 回溯 Tokenomics workbook 原儲存格，找出原始出處並逐一核對；無出處者改標 Assumed
A67: 每架年營運費用（含折舊） | B67: $M/年 | C67: =輸入!C76 -> 1.7667 | D67: Derived | E67: 待查核-workbook | F67: Tokenomics v4（Config F 欄 VR NVL72 預設；要改一起改） DC_Cost_Model!D88 ÷ D9；DC_Cost_Model：年營運費用 $9,298M ÷ 5,263 架（含折舊） | G67: 回溯 Tokenomics workbook 原儲存格，找出原始出處並逐一核對；無出處者改標 Assumed
A68: 推測解碼每步接受 token | B68: tok | C68: =輸入!C77 -> 2.94 | D68: Analogy | E68: 待查核-workbook | F68: Tokenomics v4（Config F 欄 VR NVL72 預設；要改一起改） Config!B59 | G68: 回溯 Tokenomics workbook 原儲存格，找出原始出處並逐一核對；無出處者改標 Assumed
A69: 機架平均利用率 | B69: % | C69: =輸入!C78 -> 0.6 | D69: Assumed | E69: 假設 | F69: 區間 40–80% | G69: 判斷題：檢視區間與敏感度，不需外部查核
A70: decode 批次上限 | B70: 序列 | C70: =輸入!C79 -> 256 | D70: Assumed | E70: 假設 | F70: 區間 64–1,024；決定權重讀取的攤提 | G70: 判斷題：檢視區間與敏感度，不需外部查核
A71: 平均上下文長度 | B71: K tok | C71: =輸入!C80 -> 8 | D71: Assumed | E71: 假設 | F71: 區間 4–32K；決定 KV 快取讀取量 | G71: 判斷題：檢視區間與敏感度，不需外部查核
A72: prefill 注意力額外計算倍數 | B72: x | C72: =輸入!C81 -> 1.1 | D72: Assumed | E72: 假設 | G72: 判斷題：檢視區間與敏感度，不需外部查核
A73: 快取輸入成本 ÷ 新鮮輸入成本 | B73: % | C73: =輸入!C82 -> 0.1 | D73: Analogy | E73: 待查核-報導 | F73: 牌價快取讀取比 0.05–0.1 代理 | G73: 取得原始報導或文件；確認口徑（年底或全年平均、總額或淨額、年化或認列）
A74: Luna（低層） 總參數 | B74: B | C74: =輸入!C83 -> 284 | D74: Analogy | E74: 待查核-workbook | F74: Tokenomics 預設架構類比：DeepSeek V4-Flash | G74: 回溯 Tokenomics workbook 原儲存格，找出原始出處並逐一核對；無出處者改標 Assumed
A75: Luna（低層） 啟用參數 | B75: B | C75: =輸入!C84 -> 13 | D75: Analogy | E75: 待查核-workbook | F75: Tokenomics 預設架構類比：DeepSeek V4-Flash | G75: 回溯 Tokenomics workbook 原儲存格，找出原始出處並逐一核對；無出處者改標 Assumed
A76: Luna（低層） 每 token KV 快取 | B76: bytes | C76: =輸入!C85 -> 2795 | D76: Analogy | E76: 待查核-workbook | F76: Tokenomics 預設架構類比：DeepSeek V4-Flash | G76: 回溯 Tokenomics workbook 原儲存格，找出原始出處並逐一核對；無出處者改標 Assumed
A77: Luna（低層） 每參數位元組 | B77: bytes | C77: =輸入!C86 -> 0.51 | D77: Analogy | E77: 待查核-workbook | F77: Tokenomics 預設架構類比：DeepSeek V4-Flash | G77: 回溯 Tokenomics workbook 原儲存格，找出原始出處並逐一核對；無出處者改標 Assumed
A78: Sol（中層） 總參數 | B78: B | C78: =輸入!C87 -> 1600 | D78: Analogy | E78: 待查核-workbook | F78: Tokenomics 預設架構類比：DeepSeek V4-Pro | G78: 回溯 Tokenomics workbook 原儲存格，找出原始出處並逐一核對；無出處者改標 Assumed
A79: Sol（中層） 啟用參數 | B79: B | C79: =輸入!C88 -> 49 | D79: Analogy | E79: 待查核-workbook | F79: Tokenomics 預設架構類比：DeepSeek V4-Pro | G79: 回溯 Tokenomics workbook 原儲存格，找出原始出處並逐一核對；無出處者改標 Assumed
A80: Sol（中層） 每 token KV 快取 | B80: bytes | C80: =輸入!C89 -> 3965 | D80: Analogy | E80: 待查核-workbook | F80: Tokenomics 預設架構類比：DeepSeek V4-Pro | G80: 回溯 Tokenomics workbook 原儲存格，找出原始出處並逐一核對；無出處者改標 Assumed
A81: Sol（中層） 每參數位元組 | B81: bytes | C81: =輸入!C90 -> 0.507 | D81: Analogy | E81: 待查核-workbook | F81: Tokenomics 預設架構類比：DeepSeek V4-Pro | G81: 回溯 Tokenomics workbook 原儲存格，找出原始出處並逐一核對；無出處者改標 Assumed
A82: Astra（頂層） 總參數 | B82: B | C82: =輸入!C91 -> 4000 | D82: Analogy | E82: 待查核-workbook | F82: Tokenomics 預設架構類比：Closed-frontier proxy | G82: 回溯 Tokenomics workbook 原儲存格，找出原始出處並逐一核對；無出處者改標 Assumed
A83: Astra（頂層） 啟用參數 | B83: B | C83: =輸入!C92 -> 180 | D83: Analogy | E83: 待查核-workbook | F83: Tokenomics 預設架構類比：Closed-frontier proxy | G83: 回溯 Tokenomics workbook 原儲存格，找出原始出處並逐一核對；無出處者改標 Assumed
A84: Astra（頂層） 每 token KV 快取 | B84: bytes | C84: =輸入!C93 -> 204800 | D84: Analogy | E84: 待查核-workbook | F84: Tokenomics 預設架構類比：Closed-frontier proxy | G84: 回溯 Tokenomics workbook 原儲存格，找出原始出處並逐一核對；無出處者改標 Assumed
A85: Astra（頂層） 每參數位元組 | B85: bytes | C85: =輸入!C94 -> 0.53 | D85: Analogy | E85: 待查核-workbook | F85: Tokenomics 預設架構類比：Closed-frontier proxy | G85: 回溯 Tokenomics workbook 原儲存格，找出原始出處並逐一核對；無出處者改標 Assumed
A86: Free Luna 占比 | B86: % | C86: =輸入!C96 -> 0.9 | D86: Assumed | E86: 假設 | F86: T6／分層成本假設 | G86: 判斷題：檢視區間與敏感度，不需外部查核
A87: Free Sol 占比 | B87: % | C87: =輸入!C97 -> 0.1 | D87: Assumed | E87: 假設 | F87: T6／分層成本假設 | G87: 判斷題：檢視區間與敏感度，不需外部查核
A88: Free Astra 占比 | B88: % | C88: =輸入!C98 -> 0 | D88: Assumed | E88: 假設 | F88: T6／分層成本假設 | G88: 判斷題：檢視區間與敏感度，不需外部查核
A89: Free 輸出占比 | B89: % | C89: =輸入!C99 -> 0.25 | D89: Assumed | E89: 假設 | G89: 判斷題：檢視區間與敏感度，不需外部查核
A90: Free 快取命中 | B90: % | C90: =輸入!C100 -> 0.4 | D90: Assumed | E90: 假設 | G90: 判斷題：檢視區間與敏感度，不需外部查核
A91: Go Luna 占比 | B91: % | C91: =輸入!C101 -> 0.85 | D91: Assumed | E91: 假設 | F91: T6／分層成本假設 | G91: 判斷題：檢視區間與敏感度，不需外部查核
A92: Go Sol 占比 | B92: % | C92: =輸入!C102 -> 0.15 | D92: Assumed | E92: 假設 | F92: T6／分層成本假設 | G92: 判斷題：檢視區間與敏感度，不需外部查核
A93: Go Astra 占比 | B93: % | C93: =輸入!C103 -> 0 | D93: Assumed | E93: 假設 | F93: T6／分層成本假設 | G93: 判斷題：檢視區間與敏感度，不需外部查核
A94: Go 輸出占比 | B94: % | C94: =輸入!C104 -> 0.25 | D94: Assumed | E94: 假設 | G94: 判斷題：檢視區間與敏感度，不需外部查核
A95: Go 快取命中 | B95: % | C95: =輸入!C105 -> 0.4 | D95: Assumed | E95: 假設 | G95: 判斷題：檢視區間與敏感度，不需外部查核
A96: Plus Luna 占比 | B96: % | C96: =輸入!C106 -> 0.35 | D96: Assumed | E96: 假設 | F96: T6／分層成本假設 | G96: 判斷題：檢視區間與敏感度，不需外部查核
A97: Plus Sol 占比 | B97: % | C97: =輸入!C107 -> 0.6 | D97: Assumed | E97: 假設 | F97: T6／分層成本假設 | G97: 判斷題：檢視區間與敏感度，不需外部查核
A98: Plus Astra 占比 | B98: % | C98: =輸入!C108 -> 0.05 | D98: Assumed | E98: 假設 | F98: T6／分層成本假設 | G98: 判斷題：檢視區間與敏感度，不需外部查核
A99: Plus 輸出占比 | B99: % | C99: =輸入!C109 -> 0.4 | D99: Assumed | E99: 假設 | G99: 判斷題：檢視區間與敏感度，不需外部查核
A100: Plus 快取命中 | B100: % | C100: =輸入!C110 -> 0.5 | D100: Assumed | E100: 假設 | G100: 判斷題：檢視區間與敏感度，不需外部查核
...

Sheet 算力MW
A1: 算力 MW 核心（GW；VR-eq＝Vera Rubin NVL72 等值）：供給（合約＋自建）→ 需求（token→推論 GW）→ 容量上限 → 每 GW 營收與成本
A3: 項目 | B3: 單位 | C3: 2025 | D3: 2026 | E3: 2027 | F3: 2028 | G3: 2029 | H3: 2030 | I3: 2026–30 合計 | J3: 說明／資金來源
A4: 一、供給：實體 GW（年平均）＝合約付款 ÷ 每 GW 價格（已揭露 GW 者依揭露值隨付款爬升）＋自建
A5: Microsoft Azure | B5: GW | C5: =IF(輸入!$G$164<>"",輸入!$G$164*支出!C5/IF(輸入!$F$164<>"",輸入!$F$164,IF(輸入!$C$6="even",輸入!$C$164/(輸入!$E$164-輸入!$D$164+1),2*輸入!$C$164/((輸入!$E$164-輸入!$D$164+1)+1))),支出!C5/輸入!$C$151) -> 0.99206349 | D5: =IF(輸入!$G$164<>"",輸入!$G$164*支出!D5/IF(輸入!$F$164<>"",輸入!$F$164,IF(輸入!$C$6="even",輸入!$C$164/(輸入!$E$164-輸入!$D$164+1),2*輸入!$C$164/((輸入!$E$164-輸入!$D$164+1)+1))),支出!D5/輸入!$C$151) -> 1.984127 | E5: =IF(輸入!$G$164<>"",輸入!$G$164*支出!E5/IF(輸入!$F$164<>"",輸入!$F$164,IF(輸入!$C$6="even",輸入!$C$164/(輸入!$E$164-輸入!$D$164+1),2*輸入!$C$164/((輸入!$E$164-輸入!$D$164+1)+1))),支出!E5/輸入!$C$151) -> 2.9761905 | F5: =IF(輸入!$G$164<>"",輸入!$G$164*支出!F5/IF(輸入!$F$164<>"",輸入!$F$164,IF(輸入!$C$6="even",輸入!$C$164/(輸入!$E$164-輸入!$D$164+1),2*輸入!$C$164/((輸入!$E$164-輸入!$D$164+1)+1))),支出!F5/輸入!$C$151) -> 3.968254 | G5: =IF(輸入!$G$164<>"",輸入!$G$164*支出!G5/IF(輸入!$F$164<>"",輸入!$F$164,IF(輸入!$C$6="even",輸入!$C$164/(輸入!$E$164-輸入!$D$164+1),2*輸入!$C$164/((輸入!$E$164-輸入!$D$164+1)+1))),支出!G5/輸入!$C$151) -> 4.9603175 | H5: =IF(輸入!$G$164<>"",輸入!$G$164*支出!H5/IF(輸入!$F$164<>"",輸入!$F$164,IF(輸入!$C$6="even",輸入!$C$164/(輸入!$E$164-輸入!$D$164+1),2*輸入!$C$164/((輸入!$E$164-輸入!$D$164+1)+1))),支出!H5/輸入!$C$151) -> 5.952381
A6: Oracle | B6: GW | C6: =IF(輸入!$G$165<>"",輸入!$G$165*支出!C6/IF(輸入!$F$165<>"",輸入!$F$165,IF(輸入!$C$6="even",輸入!$C$165/(輸入!$E$165-輸入!$D$165+1),2*輸入!$C$165/((輸入!$E$165-輸入!$D$165+1)+1))),支出!C6/輸入!$C$151) -> 0 | D6: =IF(輸入!$G$165<>"",輸入!$G$165*支出!D6/IF(輸入!$F$165<>"",輸入!$F$165,IF(輸入!$C$6="even",輸入!$C$165/(輸入!$E$165-輸入!$D$165+1),2*輸入!$C$165/((輸入!$E$165-輸入!$D$165+1)+1))),支出!D6/輸入!$C$151) -> 0 | E6: =IF(輸入!$G$165<>"",輸入!$G$165*支出!E6/IF(輸入!$F$165<>"",輸入!$F$165,IF(輸入!$C$6="even",輸入!$C$165/(輸入!$E$165-輸入!$D$165+1),2*輸入!$C$165/((輸入!$E$165-輸入!$D$165+1)+1))),支出!E6/輸入!$C$151) -> 4.5 | F6: =IF(輸入!$G$165<>"",輸入!$G$165*支出!F6/IF(輸入!$F$165<>"",輸入!$F$165,IF(輸入!$C$6="even",輸入!$C$165/(輸入!$E$165-輸入!$D$165+1),2*輸入!$C$165/((輸入!$E$165-輸入!$D$165+1)+1))),支出!F6/輸入!$C$151) -> 4.5 | G6: =IF(輸入!$G$165<>"",輸入!$G$165*支出!G6/IF(輸入!$F$165<>"",輸入!$F$165,IF(輸入!$C$6="even",輸入!$C$165/(輸入!$E$165-輸入!$D$165+1),2*輸入!$C$165/((輸入!$E$165-輸入!$D$165+1)+1))),支出!G6/輸入!$C$151) -> 4.5 | H6: =IF(輸入!$G$165<>"",輸入!$G$165*支出!H6/IF(輸入!$F$165<>"",輸入!$F$165,IF(輸入!$C$6="even",輸入!$C$165/(輸入!$E$165-輸入!$D$165+1),2*輸入!$C$165/((輸入!$E$165-輸入!$D$165+1)+1))),支出!H6/輸入!$C$151) -> 4.5
A7: AWS（Nvidia GPU） | B7: GW | C7: =IF(輸入!$G$166<>"",輸入!$G$166*支出!C7/IF(輸入!$F$166<>"",輸入!$F$166,IF(輸入!$C$6="even",輸入!$C$166/(輸入!$E$166-輸入!$D$166+1),2*輸入!$C$166/((輸入!$E$166-輸入!$D$166+1)+1))),支出!C7/輸入!$C$151) -> 0.11309524 | D7: =IF(輸入!$G$166<>"",輸入!$G$166*支出!D7/IF(輸入!$F$166<>"",輸入!$F$166,IF(輸入!$C$6="even",輸入!$C$166/(輸入!$E$166-輸入!$D$166+1),2*輸入!$C$166/((輸入!$E$166-輸入!$D$166+1)+1))),支出!D7/輸入!$C$151) -> 0.22619048 | E7: =IF(輸入!$G$166<>"",輸入!$G$166*支出!E7/IF(輸入!$F$166<>"",輸入!$F$166,IF(輸入!$C$6="even",輸入!$C$166/(輸入!$E$166-輸入!$D$166+1),2*輸入!$C$166/((輸入!$E$166-輸入!$D$166+1)+1))),支出!E7/輸入!$C$151) -> 0.33928571 | F7: =IF(輸入!$G$166<>"",輸入!$G$166*支出!F7/IF(輸入!$F$166<>"",輸入!$F$166,IF(輸入!$C$6="even",輸入!$C$166/(輸入!$E$166-輸入!$D$166+1),2*輸入!$C$166/((輸入!$E$166-輸入!$D$166+1)+1))),支出!F7/輸入!$C$151) -> 0.45238095 | G7: =IF(輸入!$G$166<>"",輸入!$G$166*支出!G7/IF(輸入!$F$166<>"",輸入!$F$166,IF(輸入!$C$6="even",輸入!$C$166/(輸入!$E$166-輸入!$D$166+1),2*輸入!$C$166/((輸入!$E$166-輸入!$D$166+1)+1))),支出!G7/輸入!$C$151) -> 0.56547619 | H7: =IF(輸入!$G$166<>"",輸入!$G$166*支出!H7/IF(輸入!$F$166<>"",輸入!$F$166,IF(輸入!$C$6="even",輸入!$C$166/(輸入!$E$166-輸入!$D$166+1),2*輸入!$C$166/((輸入!$E$166-輸入!$D$166+1)+1))),支出!H7/輸入!$C$151) -> 0.67857143
A8: AWS 擴約（Trainium／VR） | B8: GW | C8: =IF(輸入!$G$167<>"",輸入!$G$167*支出!C8/IF(輸入!$F$167<>"",輸入!$F$167,IF(輸入!$C$6="even",輸入!$C$167/(輸入!$E$167-輸入!$D$167+1),2*輸入!$C$167/((輸入!$E$167-輸入!$D$167+1)+1))),支出!C8/輸入!$C$151) -> 0 | D8: =IF(輸入!$G$167<>"",輸入!$G$167*支出!D8/IF(輸入!$F$167<>"",輸入!$F$167,IF(輸入!$C$6="even",輸入!$C$167/(輸入!$E$167-輸入!$D$167+1),2*輸入!$C$167/((輸入!$E$167-輸入!$D$167+1)+1))),支出!D8/輸入!$C$151) -> 0.25 | E8: =IF(輸入!$G$167<>"",輸入!$G$167*支出!E8/IF(輸入!$F$167<>"",輸入!$F$167,IF(輸入!$C$6="even",輸入!$C$167/(輸入!$E$167-輸入!$D$167+1),2*輸入!$C$167/((輸入!$E$167-輸入!$D$167+1)+1))),支出!E8/輸入!$C$151) -> 0.5 | F8: =IF(輸入!$G$167<>"",輸入!$G$167*支出!F8/IF(輸入!$F$167<>"",輸入!$F$167,IF(輸入!$C$6="even",輸入!$C$167/(輸入!$E$167-輸入!$D$167+1),2*輸入!$C$167/((輸入!$E$167-輸入!$D$167+1)+1))),支出!F8/輸入!$C$151) -> 0.75 | G8: =IF(輸入!$G$167<>"",輸入!$G$167*支出!G8/IF(輸入!$F$167<>"",輸入!$F$167,IF(輸入!$C$6="even",輸入!$C$167/(輸入!$E$167-輸入!$D$167+1),2*輸入!$C$167/((輸入!$E$167-輸入!$D$167+1)+1))),支出!G8/輸入!$C$151) -> 1 | H8: =IF(輸入!$G$167<>"",輸入!$G$167*支出!H8/IF(輸入!$F$167<>"",輸入!$F$167,IF(輸入!$C$6="even",輸入!$C$167/(輸入!$E$167-輸入!$D$167+1),2*輸入!$C$167/((輸入!$E$167-輸入!$D$167+1)+1))),支出!H8/輸入!$C$151) -> 1.25
A9: CoreWeave | B9: GW | C9: =IF(輸入!$G$168<>"",輸入!$G$168*支出!C9/IF(輸入!$F$168<>"",輸入!$F$168,IF(輸入!$C$6="even",輸入!$C$168/(輸入!$E$168-輸入!$D$168+1),2*輸入!$C$168/((輸入!$E$168-輸入!$D$168+1)+1))),支出!C9/輸入!$C$151) -> 0.12444444 | D9: =IF(輸入!$G$168<>"",輸入!$G$168*支出!D9/IF(輸入!$F$168<>"",輸入!$F$168,IF(輸入!$C$6="even",輸入!$C$168/(輸入!$E$168-輸入!$D$168+1),2*輸入!$C$168/((輸入!$E$168-輸入!$D$168+1)+1))),支出!D9/輸入!$C$151) -> 0.24888889 | E9: =IF(輸入!$G$168<>"",輸入!$G$168*支出!E9/IF(輸入!$F$168<>"",輸入!$F$168,IF(輸入!$C$6="even",輸入!$C$168/(輸入!$E$168-輸入!$D$168+1),2*輸入!$C$168/((輸入!$E$168-輸入!$D$168+1)+1))),支出!E9/輸入!$C$151) -> 0.37333333 | F9: =IF(輸入!$G$168<>"",輸入!$G$168*支出!F9/IF(輸入!$F$168<>"",輸入!$F$168,IF(輸入!$C$6="even",輸入!$C$168/(輸入!$E$168-輸入!$D$168+1),2*輸入!$C$168/((輸入!$E$168-輸入!$D$168+1)+1))),支出!F9/輸入!$C$151) -> 0.49777778 | G9: =IF(輸入!$G$168<>"",輸入!$G$168*支出!G9/IF(輸入!$F$168<>"",輸入!$F$168,IF(輸入!$C$6="even",輸入!$C$168/(輸入!$E$168-輸入!$D$168+1),2*輸入!$C$168/((輸入!$E$168-輸入!$D$168+1)+1))),支出!G9/輸入!$C$151) -> 0.62222222 | H9: =IF(輸入!$G$168<>"",輸入!$G$168*支出!H9/IF(輸入!$F$168<>"",輸入!$F$168,IF(輸入!$C$6="even",輸入!$C$168/(輸入!$E$168-輸入!$D$168+1),2*輸入!$C$168/((輸入!$E$168-輸入!$D$168+1)+1))),支出!H9/輸入!$C$151) -> 0
A10: Cerebras | B10: GW | C10: =IF(輸入!$G$169<>"",輸入!$G$169*支出!C10/IF(輸入!$F$169<>"",輸入!$F$169,IF(輸入!$C$6="even",輸入!$C$169/(輸入!$E$169-輸入!$D$169+1),2*輸入!$C$169/((輸入!$E$169-輸入!$D$169+1)+1))),支出!C10/輸入!$C$151) -> 0 | D10: =IF(輸入!$G$169<>"",輸入!$G$169*支出!D10/IF(輸入!$F$169<>"",輸入!$F$169,IF(輸入!$C$6="even",輸入!$C$169/(輸入!$E$169-輸入!$D$169+1),2*輸入!$C$169/((輸入!$E$169-輸入!$D$169+1)+1))),支出!D10/輸入!$C$151) -> 0.125 | E10: =IF(輸入!$G$169<>"",輸入!$G$169*支出!E10/IF(輸入!$F$169<>"",輸入!$F$169,IF(輸入!$C$6="even",輸入!$C$169/(輸入!$E$169-輸入!$D$169+1),2*輸入!$C$169/((輸入!$E$169-輸入!$D$169+1)+1))),支出!E10/輸入!$C$151) -> 0.25 | F10: =IF(輸入!$G$169<>"",輸入!$G$169*支出!F10/IF(輸入!$F$169<>"",輸入!$F$169,IF(輸入!$C$6="even",輸入!$C$169/(輸入!$E$169-輸入!$D$169+1),2*輸入!$C$169/((輸入!$E$169-輸入!$D$169+1)+1))),支出!F10/輸入!$C$151) -> 0.375 | G10: =IF(輸入!$G$169<>"",輸入!$G$169*支出!G10/IF(輸入!$F$169<>"",輸入!$F$169,IF(輸入!$C$6="even",輸入!$C$169/(輸入!$E$169-輸入!$D$169+1),2*輸入!$C$169/((輸入!$E$169-輸入!$D$169+1)+1))),支出!G10/輸入!$C$151) -> 0.5 | H10: =IF(輸入!$G$169<>"",輸入!$G$169*支出!H10/IF(輸入!$F$169<>"",輸入!$F$169,IF(輸入!$C$6="even",輸入!$C$169/(輸入!$E$169-輸入!$D$169+1),2*輸入!$C$169/((輸入!$E$169-輸入!$D$169+1)+1))),支出!H10/輸入!$C$151) -> 0.625
A11: 自建（累計自有資本支出 ÷ 每 GW 資本支出，落後一年） | B11: GW | C11: =0 -> 0 | D11: =SUM(輸入!$C$171:C$171)/輸入!$C$140 -> 0 | E11: =SUM(輸入!$C$171:D$171)/輸入!$C$140 -> 0.46296296 | F11: =SUM(輸入!$C$171:E$171)/輸入!$C$140 -> 1.1574074 | G11: =SUM(輸入!$C$171:F$171)/輸入!$C$140 -> 2.1990741 | H11: =SUM(輸入!$C$171:G$171)/輸入!$C$140 -> 3.587963
A12: 實體 GW（模型推得） | B12: GW | C12: =SUM(C5:C11) -> 1.2296032 | D12: =SUM(D5:D11) -> 2.8342063 | E12: =SUM(E5:E11) -> 9.4017725 | F12: =SUM(F5:F11) -> 11.70082 | G12: =SUM(G5:G11) -> 14.34709 | H12: =SUM(H5:H11) -> 16.593915
A13: 實體 GW（2025＝實際年平均；其後＝模型） | B13: GW | C13: =(輸入!$C$148+輸入!$C$149)/2 -> 1.25 | D13: =D12 -> 2.8342063 | E13: =E12 -> 9.4017725 | F13: =F12 -> 11.70082 | G13: =G12 -> 14.34709 | H13: =H12 -> 16.593915 | J13: 2025：CFO 年底 0.6→1.9 GW 之平均
A14: 二、艦隊換算：實體 GW → VR-eq GW（每 MW 輸出 token 相對 Vera Rubin）
A15: Blackwell（GB200）÷ VR（Tokenomics 推得） | B15: x | C15: =輸入!$C$139*輸入!$C$137/(輸入!$C$138*輸入!$C$136) -> 0.52729604 | D15: =輸入!$C$139*輸入!$C$137/(輸入!$C$138*輸入!$C$136) -> 0.52729604 | E15: =輸入!$C$139*輸入!$C$137/(輸入!$C$138*輸入!$C$136) -> 0.52729604 | F15: =輸入!$C$139*輸入!$C$137/(輸入!$C$138*輸入!$C$136) -> 0.52729604 | G15: =輸入!$C$139*輸入!$C$137/(輸入!$C$138*輸入!$C$136) -> 0.52729604 | H15: =輸入!$C$139*輸入!$C$137/(輸入!$C$138*輸入!$C$136) -> 0.52729604
A16: 組合：Hopper | B16: % | C16: =輸入!C$144 -> 0.6 | D16: =輸入!D$144 -> 0.35 | E16: =輸入!E$144 -> 0.15 | F16: =輸入!F$144 -> 0.05 | G16: =輸入!G$144 -> 0 | H16: =輸入!H$144 -> 0
A17: 組合：Blackwell | B17: % | C17: =輸入!C$145 -> 0.4 | D17: =輸入!D$145 -> 0.55 | E17: =輸入!E$145 -> 0.45 | F17: =輸入!F$145 -> 0.3 | G17: =輸入!G$145 -> 0.2 | H17: =輸入!H$145 -> 0.1
A18: 組合：Vera Rubin | B18: % | C18: =輸入!C$146 -> 0 | D18: =輸入!D$146 -> 0.05 | E18: =輸入!E$146 -> 0.3 | F18: =輸入!F$146 -> 0.45 | G18: =輸入!G$146 -> 0.5 | H18: =輸入!H$146 -> 0.45
A19: 組合：次世代 | B19: % | C19: =輸入!C$147 -> 0 | D19: =輸入!D$147 -> 0 | E19: =輸入!E$147 -> 0 | F19: =輸入!F$147 -> 0.05 | G19: =輸入!G$147 -> 0.1 | H19: =輸入!H$147 -> 0.2
A20: 組合：自研／其他 | B20: % | C20: =1-C16-C17-C18-C19 -> 0 | D20: =1-D16-D17-D18-D19 -> 0.05 | E20: =1-E16-E17-E18-E19 -> 0.1 | F20: =1-F16-F17-F18-F19 -> 0.15 | G20: =1-G16-G17-G18-G19 -> 0.2 | H20: =1-H16-H17-H18-H19 -> 0.25
A21: 艦隊 VR-eq 係數 | B21: x | C21: =C16*輸入!$C$141+C17*C15+C18+C19*輸入!$C$143+C20*輸入!$C$142 -> 0.30091841 | D21: =D16*輸入!$C$141+D17*D15+D18+D19*輸入!$C$143+D20*輸入!$C$142 -> 0.42251282 | E21: =E16*輸入!$C$141+E17*E15+E18+E19*輸入!$C$143+E20*輸入!$C$142 -> 0.61978322 | F21: =F16*輸入!$C$141+F17*F15+F18+F19*輸入!$C$143+F20*輸入!$C$142 -> 0.79568881 | G21: =G16*輸入!$C$141+G17*G15+G18+G19*輸入!$C$143+G20*輸入!$C$142 -> 0.90545921 | H21: =H16*輸入!$C$141+H17*H15+H18+H19*輸入!$C$143+H20*輸入!$C$142 -> 1.0127296
A22: VR-eq GW 供給 | B22: GW | C22: =C13*C21 -> 0.37614802 | D22: =D13*D21 -> 1.1974885 | E22: =E13*E21 -> 5.8270608 | F22: =F13*F21 -> 9.3102116 | G22: =G13*G21 -> 12.990705 | H22: =H13*H21 -> 16.805149
A23: 三、需求：token → 推論 VR-eq GW（2025 以實際推論占算力成本比例校準）
A24: 訂閱＋Free 文字理想量（×k） | B24: $B-ideal | C24: =推論成本!$C$56*(推論成本!C44*訂閱與廣告!C31+推論成本!C45*訂閱與廣告!C32+推論成本!C46*訂閱與廣告!C33+推論成本!C47*訂閱與廣告!C34+推論成本!C48*訂閱與廣告!C35) -> 0.09201308 | D24: =推論成本!$C$56*(推論成本!D44*訂閱與廣告!D31+推論成本!D45*訂閱與廣告!D32+推論成本!D46*訂閱與廣告!D33+推論成本!D47*訂閱與廣告!D34+推論成本!D48*訂閱與廣告!D35) -> 0.28175473 | E24: =推論成本!$C$56*(推論成本!E44*訂閱與廣告!E31+推論成本!E45*訂閱與廣告!E32+推論成本!E46*訂閱與廣告!E33+推論成本!E47*訂閱與廣告!E34+推論成本!E48*訂閱與廣告!E35) -> 0.48720051 | F24: =推論成本!$C$56*(推論成本!F44*訂閱與廣告!F31+推論成本!F45*訂閱與廣告!F32+推論成本!F46*訂閱與廣告!F33+推論成本!F47*訂閱與廣告!F34+推論成本!F48*訂閱與廣告!F35) -> 0.77507576 | G24: =推論成本!$C$56*(推論成本!G44*訂閱與廣告!G31+推論成本!G45*訂閱與廣告!G32+推論成本!G46*訂閱與廣告!G33+推論成本!G47*訂閱與廣告!G34+推論成本!G48*訂閱與廣告!G35) -> 1.1567243 | H24: =推論成本!$C$56*(推論成本!H44*訂閱與廣告!H31+推論成本!H45*訂閱與廣告!H32+推論成本!H46*訂閱與廣告!H33+推論成本!H47*訂閱與廣告!H34+推論成本!H48*訂閱與廣告!H35) -> 1.6602777
A25: API 理想量 | B25: $B-ideal | C25: =推論成本!C49*API!C28+推論成本!C50*API!C30+推論成本!C51*API!C32 -> 0.051120738 | D25: =推論成本!D49*API!D28+推論成本!D50*API!D30+推論成本!D51*API!D32 -> 0.084192218 | E25: =推論成本!E49*API!E28+推論成本!E50*API!E30+推論成本!E51*API!E32 -> 0.21860794 | F25: =推論成本!F49*API!F28+推論成本!F50*API!F30+推論成本!F51*API!F32 -> 0.51166404 | G25: =推論成本!G49*API!G28+推論成本!G50*API!G30+推論成本!G51*API!G32 -> 1.0826233 | H25: =推論成本!H49*API!H28+推論成本!H50*API!H30+推論成本!H51*API!H32 -> 2.1463904
A26: Free 殘差理想量（隨 Free 人數） | B26: $B-ideal | C26: =推論成本!$C$58/推論成本!$C$54*訂閱與廣告!C7/訂閱與廣告!$C$7 -> 0.093719021 | D26: =推論成本!$C$58/推論成本!$C$54*訂閱與廣告!D7/訂閱與廣告!$C$7 -> 0.14838845 | E26: =推論成本!$C$58/推論成本!$C$54*訂閱與廣告!E7/訂閱與廣告!$C$7 -> 0.19524796 | F26: =推論成本!$C$58/推論成本!$C$54*訂閱與廣告!F7/訂閱與廣告!$C$7 -> 0.23429755 | G26: =推論成本!$C$58/推論成本!$C$54*訂閱與廣告!G7/訂閱與廣告!$C$7 -> 0.26553723 | H26: =推論成本!$C$58/推論成本!$C$54*訂閱與廣告!H7/訂閱與廣告!$C$7 -> 0.28896698
A27: 推論理想量合計 | B27: $B-ideal | C27: =C24+C25+C26 -> 0.23685284 | D27: =D24+D25+D26 -> 0.51433539 | E27: =E24+E25+E26 -> 0.90105642 | F27: =F24+F25+F26 -> 1.5210374 | G27: =G24+G25+G26 -> 2.5048848 | H27: =H24+H25+H26 -> 4.0956351 | J27: 以 VR 理想成本表示之 token 工作量；等比於所需機架秒
A28: 2025 推論占算力成本（推論 ÷（推論＋訓練）） | B28: % | C28: =輸入!$C$122/(輸入!$C$122+輸入!$C$132) -> 0.41176471
A29: ρ：每單位理想量所需 VR-eq GW（2025 校準） | B29: GW/$B | C29: =C22*C28/C27 -> 0.65392705 | J29: 實際產出 ÷ 理想產出之倒數含於 ρ；2026 起不再隨艦隊變動（艦隊進步已在供給端換算）
A30: 推論需求 GW（VR-eq） | B30: GW | C30: =$C$29*C27 -> 0.15488448 | D30: =$C$29*D27 -> 0.33633783 | E30: =$C$29*E27 -> 0.58922516 | F30: =$C$29*F27 -> 0.99464747 | G30: =$C$29*G27 -> 1.6380119 | H30: =$C$29*H27 -> 2.6782466
A31: 推論可用 GW＝供給×(1−閒置)×(1−訓練最低占比) | B31: GW | C31: =C22*C28 -> 0.15488448 | D31: =D22*(1-輸入!$C$152)*(1-輸入!$C$153) -> 0.75441777 | E31: =E22*(1-輸入!$C$152)*(1-輸入!$C$153) -> 3.6710483 | F31: =F22*(1-輸入!$C$152)*(1-輸入!$C$153) -> 5.8654333 | G31: =G22*(1-輸入!$C$152)*(1-輸入!$C$153) -> 8.184144 | H31: =H22*(1-輸入!$C$152)*(1-輸入!$C$153) -> 10.587244
A32: 容量上限係數（V1a；1＝未受限） | B32: x | C32: =1 -> 1 | D32: =MIN(1,D31/D30) -> 1 | E32: =MIN(1,E31/E30) -> 1 | F32: =MIN(1,F31/F30) -> 1 | G32: =MIN(1,G31/G30) -> 1 | H32: =MIN(1,H31/H30) -> 1
A33: 推論 GW | B33: GW | C33: =C30*C32 -> 0.15488448 | D33: =D30*D32 -> 0.33633783 | E33: =E30*E32 -> 0.58922516 | F33: =F30*F32 -> 0.99464747 | G33: =G30*G32 -> 1.6380119 | H33: =H30*H32 -> 2.6782466
A34: 訓練 GW（推論優先，其餘歸訓練） | B34: GW | C34: =C22-C33 -> 0.22126354 | D34: =D22*(1-輸入!$C$152)-D33 -> 0.74140184 | E34: =E22*(1-輸入!$C$152)-E33 -> 4.6551296 | F34: =F22*(1-輸入!$C$152)-F33 -> 7.384543 | G34: =G22*(1-輸入!$C$152)-G33 -> 10.053622 | H34: =H22*(1-輸入!$C$152)-H33 -> 12.446388
A35: 閒置 GW | B35: GW | C35: =0 -> 0 | D35: =D22*輸入!$C$152 -> 0.11974885 | E35: =E22*輸入!$C$152 -> 0.58270608 | F35: =F22*輸入!$C$152 -> 0.93102116 | G35: =G22*輸入!$C$152 -> 1.2990705 | H35: =H22*輸入!$C$152 -> 1.6805149
A36: 檢查：推論＋訓練＋閒置 − 供給 | B36: GW | C36: =C33+C34+C35-C22 -> 0 | D36: =D33+D34+D35-D22 -> 0 | E36: =E33+E34+E35-E22 -> 0 | F36: =F33+F34+F35-F22 -> 0 | G36: =G33+G34+G35-G22 -> 0 | H36: =H33+H34+H35-H22 -> 0
A37: 推論占 VR-eq 供給 | B37: % | C37: =C33/C22 -> 0.41176471 | D37: =D33/D22 -> 0.28086935 | E37: =E33/E22 -> 0.10111876 | F37: =F33/F22 -> 0.10683403 | G37: =G33/G22 -> 0.12609107 | H37: =H33/H22 -> 0.15937059
A38: 四、成本（損益口徑）：算力成本 ÷ VR-eq GW → 推論／訓練／閒置
A39: 租用合約付款 | B39: $B | C39: =支出!C11 -> 14.755238 | D39: =支出!D11 -> 33.240635 | E39: =支出!E11 -> 111.72603 | F39: =支出!F11 -> 130.21143 | G39: =支出!G11 -> 148.69683 | H39: =支出!H11 -> 158.22222
A40: 自建營運費用（含折舊；Tokenomics 每架年成本 × 每 GW 架數） | B40: $B | C40: =C11*輸入!$C$76*輸入!$C$136/1000 -> 0 | D40: =D11*輸入!$C$76*輸入!$C$136/1000 -> 0 | E40: =E11*輸入!$C$76*輸入!$C$136/1000 -> 4.3046954 | F40: =F11*輸入!$C$76*輸入!$C$136/1000 -> 10.761739 | G40: =G11*輸入!$C$76*輸入!$C$136/1000 -> 20.447303 | H40: =H11*輸入!$C$76*輸入!$C$136/1000 -> 33.361389
A41: 算力損益成本（2025＝實際推論＋訓練） | B41: $B | C41: =輸入!$C$122+輸入!$C$132 -> 20.4 | D41: =D39+D40 -> 33.240635 | E41: =E39+E40 -> 116.03073 | F41: =F39+F40 -> 140.97317 | G41: =G39+G40 -> 169.14413 | H41: =H39+H40 -> 191.58361 | I41: =SUM(D41:H41) -> 650.97227
A42: 每 VR-eq GW 年成本 | B42: $B/GW | C42: =C41/C22 -> 54.233969 | D42: =D41/D22 -> 27.758625 | E42: =E41/E22 -> 19.912393 | F42: =F41/F22 -> 15.141779 | G42: =G41/G22 -> 13.020397 | H42: =H41/H22 -> 11.400292
A43: 每實體 GW 年成本 | B43: $B/GW | C43: =C41/C13 -> 16.32 | D43: =D41/D13 -> 11.728375 | E43: =E41/E13 -> 12.341367 | F43: =F41/F13 -> 12.048144 | G43: =G41/G13 -> 11.789438 | H43: =H41/H13 -> 11.545413
A44: 推論成本 | B44: $B | C44: =C33*C42 -> 8.4 | D44: =D33*D42 -> 9.3362756 | E44: =E33*E42 -> 11.732883 | F44: =F33*F42 -> 15.060732 | G44: =G33*G42 -> 21.327565 | H44: =H33*H42 -> 30.532794 | I44: =SUM(D44:H44) -> 87.990249
A45: 訓練成本 | B45: $B | C45: =C34*C42 -> 12 | D45: =D34*D42 -> 20.580296 | E45: =E34*E42 -> 92.694771 | F45: =F34*F42 -> 111.81512 | G45: =G34*G42 -> 130.90215 | H45: =H34*H42 -> 141.89246 | I45: =SUM(D45:H45) -> 497.88479
A46: 閒置成本 | B46: $B | C46: =C35*C42 -> 0 | D46: =D35*D42 -> 3.3240635 | E46: =E35*E42 -> 11.603073 | F46: =F35*F42 -> 14.097317 | G46: =G35*G42 -> 16.914413 | H46: =H35*H42 -> 19.158361 | I46: =SUM(D46:H46) -> 65.097227
A47: 檢查：拆分加總 − 算力損益成本 | B47: $B | C47: =C44+C45+C46-C41 -> 0 | D47: =D44+D45+D46-D41 -> 0 | E47: =E44+E45+E46-E41 -> 0 | F47: =F44+F45+F46-F41 -> 0 | G47: =G44+G45+G46-G41 -> 0 | H47: =H44+H45+H46-H41 -> 0
A48: 五、每 GW 營收與支出（比照 CRWV；營收已套容量上限）
A49: 總額營收 | B49: $B | C49: =營收彙總!C22 -> 13.07 | D49: =營收彙總!D22 -> 32.904031 | E49: =營收彙總!E22 -> 52.569602 | F49: =營收彙總!F22 -> 74.883641 | G49: =營收彙總!G22 -> 97.168533 | H49: =營收彙總!H22 -> 119.8813
A50: 營收 ÷ 實體 GW | B50: $B/GW | C50: =C49/C13 -> 10.456 | D50: =D49/D13 -> 11.60961 | E50: =E49/E13 -> 5.5914565 | F50: =F49/F13 -> 6.3998626 | G50: =G49/G13 -> 6.7726998 | H50: =H49/H13 -> 7.2244131 | J50: CFO 2023–25：ARR ÷ 年底 GW 約 $10–10.5B
A51: 營收 ÷ VR-eq GW | B51: $B/GW | C51: =C49/C22 -> 34.74696 | D51: =D49/D22 -> 27.477534 | E51: =E49/E22 -> 9.0216326 | F51: =F49/F22 -> 8.0431728 | G51: =G49/G22 -> 7.4798508 | H51: =H49/H22 -> 7.1336051
A52: 營收 ÷ 推論 GW | B52: $B/GW | C52: =C49/C33 -> 84.385473 | D52: =D49/D33 -> 97.830302 | E52: =E49/E33 -> 89.218189 | F52: =F49/F33 -> 75.286615 | G52: =G49/G33 -> 59.321018 | H52: =H49/H33 -> 44.761113
A53: 推論毛利 ÷ 推論 GW | B53: $B/GW | C53: =(C49-C44)/C33 -> 30.151504 | D53: =(D49-D44)/D33 -> 70.071677 | E53: =(E49-E44)/E33 -> 69.305795 | F53: =(F49-F44)/F33 -> 60.144836 | G53: =(G49-G44)/G33 -> 46.300621 | H53: =(H49-H44)/H33 -> 33.360821
A54: 算力損益成本 ÷ 營收 | B54: x | C54: =C41/C49 -> 1.5608263 | D54: =D41/D49 -> 1.0102299 | E54: =E41/E49 -> 2.2071829 | F54: =F41/F49 -> 1.8825629 | G54: =G41/G49 -> 1.7407295 | H54: =H41/H49 -> 1.5981109
A55: 若維持 2025 營收／實體 GW 之營收 | B55: $B | C55: =C13*$C$50 -> 13.07 | D55: =D13*$C$50 -> 29.634462 | E55: =E13*$C$50 -> 98.304933 | F55: =F13*$C$50 -> 122.34378 | G55: =G13*$C$50 -> 150.01317 | H55: =H13*$C$50 -> 173.50598
A56: 模型營收 − 上列（負＝每 GW 營收下滑） | B56: $B | C56: =C49-C55 -> 0 | D56: =D49-D55 -> 3.2695695 | E56: =E49-E55 -> -45.735331 | F56: =F49-F55 -> -47.460134 | G56: =G49-G55 -> -52.84464 | H56: =H49-H55 -> -53.62468
A57: 管理層營收目標所需實體 GW（維持 2025 營收／GW） | B57: GW | C57: =反向!C4/$C$50 -> 1.25 | D57: =反向!D4/$C$50 -> 3.4429992 | E57: =反向!E4/$C$50 -> 7.182479 | F57: =反向!F4/$C$50 -> 13.5329 | G57: =反向!G4/$C$50 -> 22.704667 | H57: =反向!H4/$C$50 -> 33.473604
A58: 對照：2025 年底 ARR ÷ 年底 GW | B58: $B/GW | C58: =輸入!$C$150/輸入!$C$149 -> 10.526316
A60: 六、依供應方：GW、現金、每 GW 年價格與資金關係（V2a：供應商資金只列或有）
A61: Microsoft Azure：每 GW 年價格 | B61: $B/GW | C61: =IFERROR(支出!C5/C5,0) -> 12 | D61: =IFERROR(支出!D5/D5,0) -> 12 | E61: =IFERROR(支出!E5/E5,0) -> 12 | F61: =IFERROR(支出!F5/F5,0) -> 12 | G61: =IFERROR(支出!G5/G5,0) -> 12 | H61: =IFERROR(支出!H5/H5,0) -> 12 | J61: OpenAI 以營收／股權支付；Microsoft 為股東，營收分潤上限 $38B
A62: Oracle：每 GW 年價格 | B62: $B/GW | C62: =IFERROR(支出!C6/C6,0) -> 0 | D62: =IFERROR(支出!D6/D6,0) -> 0 | E62: =IFERROR(支出!E6/E6,0) -> 13.333333 | F62: =IFERROR(支出!F6/F6,0) -> 13.333333 | G62: =IFERROR(支出!G6/G6,0) -> 13.333333 | H62: =IFERROR(支出!H6/H6,0) -> 13.333333 | J62: OpenAI 支付；Oracle 以自有債務建置（可接 ORCL 模型）
A63: AWS（Nvidia GPU）：每 GW 年價格 | B63: $B/GW | C63: =IFERROR(支出!C7/C7,0) -> 12 | D63: =IFERROR(支出!D7/D7,0) -> 12 | E63: =IFERROR(支出!E7/E7,0) -> 12 | F63: =IFERROR(支出!F7/F7,0) -> 12 | G63: =IFERROR(支出!G7/G7,0) -> 12 | H63: =IFERROR(支出!H7/H7,0) -> 12 | J63: OpenAI 支付；Amazon 條件式股權 $35B（base 不計入）
A64: AWS 擴約（Trainium／VR）：每 GW 年價格 | B64: $B/GW | C64: =IFERROR(支出!C8/C8,0) -> 0 | D64: =IFERROR(支出!D8/D8,0) -> 11.111111 | E64: =IFERROR(支出!E8/E8,0) -> 11.111111 | F64: =IFERROR(支出!F8/F8,0) -> 11.111111 | G64: =IFERROR(支出!G8/G8,0) -> 11.111111 | H64: =IFERROR(支出!H8/H8,0) -> 11.111111 | J64: OpenAI 支付；同上
A65: CoreWeave：每 GW 年價格 | B65: $B/GW | C65: =IFERROR(支出!C9/C9,0) -> 12 | D65: =IFERROR(支出!D9/D9,0) -> 12 | E65: =IFERROR(支出!E9/E9,0) -> 12 | F65: =IFERROR(支出!F9/F9,0) -> 12 | G65: =IFERROR(支出!G9/G9,0) -> 12 | H65: =IFERROR(支出!H9/H9,0) -> 0 | J65: OpenAI 支付；CoreWeave 以 DDTL 等債務融資（可接 CRWV 模型）
A66: Cerebras：每 GW 年價格 | B66: $B/GW | C66: =IFERROR(支出!C10/C10,0) -> 0 | D66: =IFERROR(支出!D10/D10,0) -> 7.6190476 | E66: =IFERROR(支出!E10/E10,0) -> 7.6190476 | F66: =IFERROR(支出!F10/F10,0) -> 7.6190476 | G66: =IFERROR(支出!G10/G10,0) -> 7.6190476 | H66: =IFERROR(支出!H10/H10,0) -> 7.6190476 | J66: OpenAI 支付（take-or-pay）
A67: 自建：每 GW 年營運費用（含折舊） | B67: $B/GW | C67: =輸入!$C$76*輸入!$C$136/1000 -> 9.2981421 | D67: =輸入!$C$76*輸入!$C$136/1000 -> 9.2981421 | E67: =輸入!$C$76*輸入!$C$136/1000 -> 9.2981421 | F67: =輸入!$C$76*輸入!$C$136/1000 -> 9.2981421 | G67: =輸入!$C$76*輸入!$C$136/1000 -> 9.2981421 | H67: =輸入!$C$76*輸入!$C$136/1000 -> 9.2981421 | J67: 資本支出由 OpenAI 股權與外部資金支應；Nvidia／AMD／Broadcom 供應商融資與 Nvidia 按 GW 注資僅列或有（V2a）

Sheet 訂閱與廣告
A1: 訂閱營收＝人數 × ARPU × 12；token 只影響成本（$B）；廣告為獨立一列
A3: 項目 | B3: 單位 | C3: 2025 | D3: 2026 | E3: 2027 | F3: 2028 | G3: 2029 | H3: 2030 | J3: 說明
A4: 人數（M，FY 平均；T4：2026 起 Plus→Go 遷移與 Go 額外新增）
A5: 遷移率 μ（Plus→Go） | B5: % | D5: =輸入!$F$35*(1-輸入!$C$55/輸入!$D$51) -> 0.24130435 | E5: =輸入!$F$35*(1-輸入!$C$55/輸入!$D$51) -> 0.24130435 | F5: =輸入!$F$35*(1-輸入!$C$55/輸入!$D$51) -> 0.24130435 | G5: =輸入!$F$35*(1-輸入!$C$55/輸入!$D$51) -> 0.24130435 | H5: =輸入!$F$35*(1-輸入!$C$55/輸入!$D$51) -> 0.24130435 | J5: 計畫幅度 × (1 − 計畫 Plus ÷ 無遷移 Plus 2026)
A6: Go 額外新增倍數 λ | B6: x | D6: =輸入!$F$35*((輸入!$C$54-輸入!$D$51*(1-輸入!$C$55/輸入!$D$51))/輸入!$D$50-1) -> 1.95 | E6: =輸入!$F$35*((輸入!$C$54-輸入!$D$51*(1-輸入!$C$55/輸入!$D$51))/輸入!$D$50-1) -> 1.95 | F6: =輸入!$F$35*((輸入!$C$54-輸入!$D$51*(1-輸入!$C$55/輸入!$D$51))/輸入!$D$50-1) -> 1.95 | G6: =輸入!$F$35*((輸入!$C$54-輸入!$D$51*(1-輸入!$C$55/輸入!$D$51))/輸入!$D$50-1) -> 1.95 | H6: =輸入!$F$35*((輸入!$C$54-輸入!$D$51*(1-輸入!$C$55/輸入!$D$51))/輸入!$D$50-1) -> 1.95 | J6: 計畫幅度＝1 時，2026 Go 恰等於公司計畫 112M
A7: Free 人數 | B7: M | C7: =輸入!C$49 -> 600 | D7: =輸入!D$49 -> 950 | E7: =輸入!E$49 -> 1250 | F7: =輸入!F$49 -> 1500 | G7: =輸入!G$49 -> 1700 | H7: =輸入!H$49 -> 1850
A8: Go 人數 | B8: M | C8: =輸入!C$50 -> 2 | D8: =輸入!D$50*(1+D6)+輸入!D$51*D5 -> 40.6 | E8: =輸入!E$50*(1+E6)+輸入!E$51*E5 -> 77.447826 | F8: =輸入!F$50*(1+F6)+輸入!F$51*F5 -> 117.00435 | G8: =輸入!G$50*(1+G6)+輸入!G$51*G5 -> 147.46957 | H8: =輸入!H$50*(1+H6)+輸入!H$51*H5 -> 177.69348
A9: Plus 人數 | B9: M | C9: =輸入!C$51 -> 30 | D9: =輸入!D$51*(1-D5) -> 34.9 | E9: =輸入!E$51*(1-E5) -> 39.452174 | F9: =輸入!F$51*(1-F5) -> 43.245652 | G9: =輸入!G$51*(1-G5) -> 46.280435 | H9: =輸入!H$51*(1-H5) -> 48.556522
A10: Pro 人數 | B10: M | C10: =輸入!C$52 -> 0.5 | D10: =輸入!D$52 -> 1 | E10: =輸入!E$52 -> 1.5 | F10: =輸入!F$52 -> 2 | G10: =輸入!G$52 -> 2.5 | H10: =輸入!H$52 -> 3
A11: 企業席位 人數 | B11: M | C11: =輸入!C$53 -> 3 | D11: =輸入!D$53 -> 14 | E11: =輸入!E$53 -> 26 | F11: =輸入!F$53 -> 38 | G11: =輸入!G$53 -> 48 | H11: =輸入!H$53 -> 56
A12: 消費端付費人數（Go＋Plus＋Pro） | B12: M | C12: =C8+C9+C10 -> 32.5 | D12: =D8+D9+D10 -> 76.5 | E12: =E8+E9+E10 -> 118.4 | F12: =F8+F9+F10 -> 162.25 | G12: =G8+G9+G10 -> 196.25 | H12: =H8+H9+H10 -> 229.25
A13: 營收（$B）
A14: Go 營收 | B14: $B | C14: =C8*輸入!C$56*12/1000 -> 0.144 | D14: =D8*輸入!D$56*12/1000 -> 2.9232 | E14: =E8*輸入!E$56*12/1000 -> 5.5762435 | F14: =F8*輸入!F$56*12/1000 -> 8.424313 | G14: =G8*輸入!G$56*12/1000 -> 10.617809 | H14: =H8*輸入!H$56*12/1000 -> 12.79393
A15: Plus 營收 | B15: $B | C15: =C9*輸入!C$57*12/1000 -> 7.02 | D15: =D9*輸入!D$57*12/1000 -> 7.9572 | E15: =E9*輸入!E$57*12/1000 -> 8.9950957 | F15: =F9*輸入!F$57*12/1000 -> 9.8600087 | G15: =G9*輸入!G$57*12/1000 -> 10.551939 | H15: =H9*輸入!H$57*12/1000 -> 11.070887
A16: Pro 營收 | B16: $B | C16: =C10*輸入!C$58*12/1000 -> 1.2 | D16: =D10*輸入!D$58*12/1000 -> 1.8 | E16: =E10*輸入!E$58*12/1000 -> 2.7 | F16: =F10*輸入!F$58*12/1000 -> 3.6 | G16: =G10*輸入!G$58*12/1000 -> 4.5 | H16: =H10*輸入!H$58*12/1000 -> 5.4
A17: 企業席位 營收 | B17: $B | C17: =C11*輸入!C$59*12/1000 -> 1.08 | D17: =D11*輸入!D$59*12/1000 -> 5.04 | E17: =E11*輸入!E$59*12/1000 -> 9.36 | F17: =F11*輸入!F$59*12/1000 -> 13.68 | G17: =G11*輸入!G$59*12/1000 -> 17.28 | H17: =H11*輸入!H$59*12/1000 -> 20.16
A18: 消費端小計（Go＋Plus＋Pro） | B18: $B | C18: =C14+C15+C16 -> 8.364 | D18: =D14+D15+D16 -> 12.6804 | E18: =E14+E15+E16 -> 17.271339 | F18: =F14+F15+F16 -> 21.884322 | G18: =G14+G15+G16 -> 25.669748 | H18: =H14+H15+H16 -> 29.264817
A19: 訂閱合計 | B19: $B | C19: =C18+C17 -> 9.444 | D19: =D18+D17 -> 17.7204 | E19: =E18+E17 -> 26.631339 | F19: =F18+F17 -> 35.564322 | G19: =G18+G17 -> 42.949748 | H19: =H18+H17 -> 49.424817
A20: 使用量與 token（T＝10^12）
A21: Free 每日任務數 | B21: 次/日 | C21: =輸入!C$60 -> 1.7 | D21: =輸入!D$60 -> 1.7 | E21: =D21*(1+輸入!$C$70) -> 1.87 | F21: =E21*(1+輸入!$C$70) -> 2.057 | G21: =F21*(1+輸入!$C$70) -> 2.2627 | H21: =G21*(1+輸入!$C$70) -> 2.48897
A22: Go 每日任務數 | B22: 次/日 | C22: =輸入!C$61 -> 5.3 | D22: =輸入!D$61 -> 5.7 | E22: =D22*(1+輸入!$C$70) -> 6.27 | F22: =E22*(1+輸入!$C$70) -> 6.897 | G22: =F22*(1+輸入!$C$70) -> 7.5867 | H22: =G22*(1+輸入!$C$70) -> 8.34537
A23: Plus 每日任務數 | B23: 次/日 | C23: =輸入!C$62 -> 13.4 | D23: =輸入!D$62 -> 17.9 | E23: =D23*(1+輸入!$C$70) -> 19.69 | F23: =E23*(1+輸入!$C$70) -> 21.659 | G23: =F23*(1+輸入!$C$70) -> 23.8249 | H23: =G23*(1+輸入!$C$70) -> 26.20739
A24: Pro 每日任務數 | B24: 次/日 | C24: =輸入!C$63 -> 41 | D24: =輸入!D$63 -> 51.4 | E24: =D24*(1+輸入!$C$70) -> 56.54 | F24: =E24*(1+輸入!$C$70) -> 62.194 | G24: =F24*(1+輸入!$C$70) -> 68.4134 | H24: =G24*(1+輸入!$C$70) -> 75.25474
A25: 企業席位 每日任務數 | B25: 次/日 | C25: =輸入!C$64 -> 10.7 | D25: =輸入!D$64 -> 14.3 | E25: =D25*(1+輸入!$C$70) -> 15.73 | F25: =E25*(1+輸入!$C$70) -> 17.303 | G25: =F25*(1+輸入!$C$70) -> 19.0333 | H25: =G25*(1+輸入!$C$70) -> 20.93663
A26: Free 每任務 token | B26: K | C26: =輸入!C$65 -> 2 | D26: =輸入!D$65 -> 2.94 | E26: =D26*(1+輸入!$F$36) -> 3.381 | F26: =E26*(1+輸入!$F$36) -> 3.88815 | G26: =F26*(1+輸入!$F$36) -> 4.4713725 | H26: =G26*(1+輸入!$F$36) -> 5.1420784
A27: Go 每任務 token | B27: K | C27: =輸入!C$66 -> 3 | D27: =輸入!D$66 -> 4.39 | E27: =D27*(1+輸入!$F$36) -> 5.0485 | F27: =E27*(1+輸入!$F$36) -> 5.805775 | G27: =F27*(1+輸入!$F$36) -> 6.6766413 | H27: =G27*(1+輸入!$F$36) -> 7.6781374
A28: Plus 每任務 token | B28: K | C28: =輸入!C$67 -> 4 | D28: =輸入!D$67 -> 6.15 | E28: =D28*(1+輸入!$F$36) -> 7.0725 | F28: =E28*(1+輸入!$F$36) -> 8.133375 | G28: =F28*(1+輸入!$F$36) -> 9.3533812 | H28: =G28*(1+輸入!$F$36) -> 10.756388
A29: Pro 每任務 token | B29: K | C29: =輸入!C$68 -> 10 | D29: =輸入!D$68 -> 15.6 | E29: =D29*(1+輸入!$F$36) -> 17.94 | F29: =E29*(1+輸入!$F$36) -> 20.631 | G29: =F29*(1+輸入!$F$36) -> 23.72565 | H29: =G29*(1+輸入!$F$36) -> 27.284498
A30: 企業席位 每任務 token | B30: K | C30: =輸入!C$69 -> 4 | D30: =輸入!D$69 -> 5.94 | E30: =D30*(1+輸入!$F$36) -> 6.831 | F30: =E30*(1+輸入!$F$36) -> 7.85565 | G30: =F30*(1+輸入!$F$36) -> 9.0339975 | H30: =G30*(1+輸入!$F$36) -> 10.389097
A31: Free token | B31: T | C31: =C7*C21*C26*365/1000 -> 744.6 | D31: =D7*D21*D26*365/1000 -> 1733.0565 | E31: =E7*E21*E26*365/1000 -> 2884.6269 | F31: =F7*F21*F26*365/1000 -> 4378.8637 | G31: =G7*G21*G26*365/1000 -> 6277.8309 | H31: =H7*H21*H26*365/1000 -> 8642.1728
A32: Go token | B32: T | C32: =C8*C22*C27*365/1000 -> 11.607 | D32: =D8*D22*D27*365/1000 -> 370.81584 | E32: =E8*E22*E27*365/1000 -> 894.81241 | F32: =F8*F22*F27*365/1000 -> 1710.0755 | G32: =G8*G22*G27*365/1000 -> 2726.5045 | H32: =H8*H22*H27*365/1000 -> 4155.9071
A33: Plus token | B33: T | C33: =C9*C23*C28*365/1000 -> 586.92 | D33: =D9*D23*D28*365/1000 -> 1402.3178 | E33: =E9*E23*E28*365/1000 -> 2005.3144 | F33: =F9*F23*F28*365/1000 -> 2780.6384 | G33: =G9*G23*G28*365/1000 -> 3764.3502 | H33: =H9*H23*H28*365/1000 -> 4996.0949
A34: Pro token | B34: T | C34: =C10*C24*C29*365/1000 -> 74.825 | D34: =D10*D24*D29*365/1000 -> 292.6716 | E34: =E10*E24*E29*365/1000 -> 555.34436 | F34: =F10*F24*F29*365/1000 -> 936.68082 | G34: =G10*G24*G29*365/1000 -> 1481.1266 | H34: =H10*H24*H29*365/1000 -> 2248.3501
A35: 企業席位 token | B35: T | C35: =C11*C25*C30*365/1000 -> 46.866 | D35: =D11*D25*D30*365/1000 -> 434.05362 | E35: =E11*E25*E30*365/1000 -> 1019.716 | F35: =F11*F25*F30*365/1000 -> 1885.2979 | G35: =G11*G25*G30*365/1000 -> 3012.5077 | H35: =H11*H25*H30*365/1000 -> 4445.9592
A36: 訂閱＋Free token 合計（workbook 口徑，未校正） | B36: T | C36: =C31+C32+C33+C34+C35 -> 1464.818 | D36: =D31+D32+D33+D34+D35 -> 4232.9153 | E36: =E31+E32+E33+E34+E35 -> 7359.8141 | F36: =F31+F32+F33+F34+F35 -> 11691.556 | G36: =G31+G32+G33+G34+G35 -> 17262.32 | H36: =H31+H32+H33+H34+H35 -> 24488.484
A37: 隱含收益率（成本見「推論成本」頁）
A38: Go 隱含收益率（營收÷token） | B38: $/M | C38: =IFERROR(C14/C32*1000,0) -> 12.406307 | D38: =IFERROR(D14/D32*1000,0) -> 7.8831585 | E38: =IFERROR(E14/E32*1000,0) -> 6.2317458 | F38: =IFERROR(F14/F32*1000,0) -> 4.9262813 | G38: =IFERROR(G14/G32*1000,0) -> 3.8942935 | H38: =IFERROR(H14/H32*1000,0) -> 3.0784929
A39: Go API 等值單價（low 層） | B39: $/M | C39: =API!C14*(1-輸入!$C$43) -> 0.22464 | D39: =API!D14*(1-輸入!$C$43) -> 0.819648 | E39: =API!E14*(1-輸入!$C$43) -> 0.4917888 | F39: =API!F14*(1-輸入!$C$43) -> 0.29507328 | G39: =API!G14*(1-輸入!$C$43) -> 0.17704397 | H39: =API!H14*(1-輸入!$C$43) -> 0.10622638
A40: Plus 隱含收益率（營收÷token） | B40: $/M | C40: =IFERROR(C15/C33*1000,0) -> 11.960744 | D40: =IFERROR(D15/D33*1000,0) -> 5.6743202 | E40: =IFERROR(E15/E33*1000,0) -> 4.4856286 | F40: =IFERROR(F15/F33*1000,0) -> 3.5459514 | G40: =IFERROR(G15/G33*1000,0) -> 2.8031237 | H40: =IFERROR(H15/H33*1000,0) -> 2.215908
A41: Plus API 等值單價（mid 層） | B41: $/M | C41: =API!C13*(1-輸入!$C$43) -> 1.7648 | D41: =API!D13*(1-輸入!$C$43) -> 2.860128 | E41: =API!E13*(1-輸入!$C$43) -> 1.7160768 | F41: =API!F13*(1-輸入!$C$43) -> 1.0296461 | G41: =API!G13*(1-輸入!$C$43) -> 0.61778765 | H41: =API!H13*(1-輸入!$C$43) -> 0.37067259
A42: Pro 隱含收益率（營收÷token） | B42: $/M | C42: =IFERROR(C16/C34*1000,0) -> 16.037421 | D42: =IFERROR(D16/D34*1000,0) -> 6.150238 | E42: =IFERROR(E16/E34*1000,0) -> 4.8618482 | F42: =IFERROR(F16/F34*1000,0) -> 3.8433583 | G42: =IFERROR(G16/G34*1000,0) -> 3.0382279 | H42: =IFERROR(H16/H34*1000,0) -> 2.4017612
A43: Pro API 等值單價（top 層） | B43: $/M | C43: =API!C12*(1-輸入!$C$43) -> 3.048 | D43: =API!D12*(1-輸入!$C$43) -> 7.86112 | E43: =API!E12*(1-輸入!$C$43) -> 5.502784 | F43: =API!F12*(1-輸入!$C$43) -> 3.8519488 | G43: =API!G12*(1-輸入!$C$43) -> 2.6963642 | H43: =API!H12*(1-輸入!$C$43) -> 1.8874549
A44: 企業席位 隱含收益率（營收÷token） | B44: $/M | C44: =IFERROR(C17/C35*1000,0) -> 23.044425 | D44: =IFERROR(D17/D35*1000,0) -> 11.611469 | E44: =IFERROR(E17/E35*1000,0) -> 9.1790266 | F44: =IFERROR(F17/F35*1000,0) -> 7.2561475 | G44: =IFERROR(G17/G35*1000,0) -> 5.736085 | H44: =IFERROR(H17/H35*1000,0) -> 4.5344545
A45: 企業席位 API 等值單價（mid 層） | B45: $/M | C45: =API!C13*(1-輸入!$C$43) -> 1.7648 | D45: =API!D13*(1-輸入!$C$43) -> 2.860128 | E45: =API!E13*(1-輸入!$C$43) -> 1.7160768 | F45: =API!F13*(1-輸入!$C$43) -> 1.0296461 | G45: =API!G13*(1-輸入!$C$43) -> 0.61778765 | H45: =API!H13*(1-輸入!$C$43) -> 0.37067259
A46: 廣告（不進核心分析）
A47: 廣告曝光用戶 | B47: M | C47: =(C7+C8)*輸入!C$155 -> 0 | D47: =(D7+D8)*輸入!D$155 -> 247.65 | E47: =(E7+E8)*輸入!E$155 -> 464.60674 | F47: =(F7+F8)*輸入!F$155 -> 646.80174 | G47: =(G7+G8)*輸入!G$155 -> 831.3613 | H47: =(H7+H8)*輸入!H$155 -> 1013.8467
A48: 廣告營收 | B48: $B | C48: =C47*輸入!C$156/1000 -> 0 | D48: =D47*輸入!D$156/1000 -> 0.74295 | E48: =E47*輸入!E$156/1000 -> 1.858427 | F48: =F47*輸入!F$156/1000 -> 2.9106078 | G48: =G47*輸入!G$156/1000 -> 4.1568065 | H48: =H47*輸入!H$156/1000 -> 5.5761571

Sheet API
A1: API 營收 = 任務數 × 每任務 token × 每 token 有效單價（$B）
A3: 項目 | B3: 單位 | C3: 2025 | D3: 2026 | E3: 2027 | F3: 2028 | G3: 2029 | H3: 2030 | J3: 說明
A4: 牌價（$/M）
A5: 頂層輸入牌價 | B5: $/M | C5: =輸入!C$22 -> 2.5 | D5: =輸入!D$22 -> 6.6 | E5: =D5*(1+輸入!$F$30) -> 4.62 | F5: =E5*(1+輸入!$F$30) -> 3.234 | G5: =F5*(1+輸入!$F$30) -> 2.2638 | H5: =G5*(1+輸入!$F$30) -> 1.58466
A6: 頂層輸出牌價 | B6: $/M | C6: =輸入!C$23 -> 14 | D6: =輸入!D$23 -> 35.8 | E6: =D6*(1+輸入!$F$30) -> 25.06 | F6: =E6*(1+輸入!$F$30) -> 17.542 | G6: =F6*(1+輸入!$F$30) -> 12.2794 | H6: =G6*(1+輸入!$F$30) -> 8.59558
A7: 中層輸入牌價 | B7: $/M | C7: =輸入!C$24 -> 1.5 | D7: =輸入!D$24 -> 2.29 | E7: =D7*(1+輸入!$F$31) -> 1.374 | F7: =E7*(1+輸入!$F$31) -> 0.8244 | G7: =F7*(1+輸入!$F$31) -> 0.49464 | H7: =G7*(1+輸入!$F$31) -> 0.296784
A8: 中層輸出牌價 | B8: $/M | C8: =輸入!C$25 -> 8 | D8: =輸入!D$25 -> 13.25 | E8: =D8*(1+輸入!$F$31) -> 7.95 | F8: =E8*(1+輸入!$F$31) -> 4.77 | G8: =F8*(1+輸入!$F$31) -> 2.862 | H8: =G8*(1+輸入!$F$31) -> 1.7172
A9: 低層輸入牌價 | B9: $/M | C9: =輸入!C$26 -> 0.2 | D9: =輸入!D$26 -> 0.64 | E9: =D9*(1+輸入!$F$32) -> 0.384 | F9: =E9*(1+輸入!$F$32) -> 0.2304 | G9: =F9*(1+輸入!$F$32) -> 0.13824 | H9: =G9*(1+輸入!$F$32) -> 0.082944
A10: 低層輸出牌價 | B10: $/M | C10: =輸入!C$27 -> 1 | D10: =輸入!D$27 -> 3.83 | E10: =D10*(1+輸入!$F$32) -> 2.298 | F10: =E10*(1+輸入!$F$32) -> 1.3788 | G10: =F10*(1+輸入!$F$32) -> 0.82728 | H10: =G10*(1+輸入!$F$32) -> 0.496368
A11: 有效單價（$/M）
A12: 頂層每 token 單價（含快取、輸出占比） | B12: $/M | C12: =(1-輸入!$C$40)*(輸入!$C$41*輸入!$C$42+(1-輸入!$C$41))*C5+輸入!$C$40*C6 -> 3.81 | D12: =(1-輸入!$C$40)*(輸入!$C$41*輸入!$C$42+(1-輸入!$C$41))*D5+輸入!$C$40*D6 -> 9.8264 | E12: =(1-輸入!$C$40)*(輸入!$C$41*輸入!$C$42+(1-輸入!$C$41))*E5+輸入!$C$40*E6 -> 6.87848 | F12: =(1-輸入!$C$40)*(輸入!$C$41*輸入!$C$42+(1-輸入!$C$41))*F5+輸入!$C$40*F6 -> 4.814936 | G12: =(1-輸入!$C$40)*(輸入!$C$41*輸入!$C$42+(1-輸入!$C$41))*G5+輸入!$C$40*G6 -> 3.3704552 | H12: =(1-輸入!$C$40)*(輸入!$C$41*輸入!$C$42+(1-輸入!$C$41))*H5+輸入!$C$40*H6 -> 2.3593186
A13: 中層每 token 單價（含快取、輸出占比） | B13: $/M | C13: =(1-輸入!$C$40)*(輸入!$C$41*輸入!$C$42+(1-輸入!$C$41))*C7+輸入!$C$40*C8 -> 2.206 | D13: =(1-輸入!$C$40)*(輸入!$C$41*輸入!$C$42+(1-輸入!$C$41))*D7+輸入!$C$40*D8 -> 3.57516 | E13: =(1-輸入!$C$40)*(輸入!$C$41*輸入!$C$42+(1-輸入!$C$41))*E7+輸入!$C$40*E8 -> 2.145096 | F13: =(1-輸入!$C$40)*(輸入!$C$41*輸入!$C$42+(1-輸入!$C$41))*F7+輸入!$C$40*F8 -> 1.2870576 | G13: =(1-輸入!$C$40)*(輸入!$C$41*輸入!$C$42+(1-輸入!$C$41))*G7+輸入!$C$40*G8 -> 0.77223456 | H13: =(1-輸入!$C$40)*(輸入!$C$41*輸入!$C$42+(1-輸入!$C$41))*H7+輸入!$C$40*H8 -> 0.46334074
A14: 低層每 token 單價（含快取、輸出占比） | B14: $/M | C14: =(1-輸入!$C$40)*(輸入!$C$41*輸入!$C$42+(1-輸入!$C$41))*C9+輸入!$C$40*C10 -> 0.2808 | D14: =(1-輸入!$C$40)*(輸入!$C$41*輸入!$C$42+(1-輸入!$C$41))*D9+輸入!$C$40*D10 -> 1.02456 | E14: =(1-輸入!$C$40)*(輸入!$C$41*輸入!$C$42+(1-輸入!$C$41))*E9+輸入!$C$40*E10 -> 0.614736 | F14: =(1-輸入!$C$40)*(輸入!$C$41*輸入!$C$42+(1-輸入!$C$41))*F9+輸入!$C$40*F10 -> 0.3688416 | G14: =(1-輸入!$C$40)*(輸入!$C$41*輸入!$C$42+(1-輸入!$C$41))*G9+輸入!$C$40*G10 -> 0.22130496 | H14: =(1-輸入!$C$40)*(輸入!$C$41*輸入!$C$42+(1-輸入!$C$41))*H9+輸入!$C$40*H10 -> 0.13278298
A15: token 組合：頂層 | B15: % | C15: =輸入!C$38 -> 0.4 | D15: =輸入!D$38 -> 0.15 | E15: =輸入!E$38 -> 0.15 | F15: =輸入!F$38 -> 0.15 | G15: =輸入!G$38 -> 0.15 | H15: =輸入!H$38 -> 0.15
A16: token 組合：中層 | B16: % | C16: =輸入!C$39 -> 0.4 | D16: =輸入!D$39 -> 0.45 | E16: =輸入!E$39 -> 0.45 | F16: =輸入!F$39 -> 0.45 | G16: =輸入!G$39 -> 0.45 | H16: =輸入!H$39 -> 0.45
A17: token 組合：低層 | B17: % | C17: =1-C15-C16 -> 0.2 | D17: =1-D15-D16 -> 0.4 | E17: =1-E15-E16 -> 0.4 | F17: =1-F15-F16 -> 0.4 | G17: =1-G15-G16 -> 0.4 | H17: =1-H15-H16 -> 0.4
A18: 組合有效單價（扣折扣） | B18: $/M | C18: =(C15*C12+C16*C13+C17*C14)*(1-輸入!$C$43) -> 1.970048 | D18: =(D15*D12+D16*D13+D17*D14)*(1-輸入!$C$43) -> 2.7940848 | E18: =(E15*E12+E16*E13+E17*E14)*(1-輸入!$C$43) -> 1.7943677 | F18: =(F15*F12+F16*F13+F17*F14)*(1-輸入!$C$43) -> 1.1591624 | G18: =(G15*G12+G16*G13+G17*G14)*(1-輸入!$C$43) -> 0.75327665 | H18: =(H15*H12+H16*H13+H17*H14)*(1-輸入!$C$43) -> 0.49241145
A19: 反事實單價（沿用上年組合，歸因用） | B19: $/M | D19: =(C15*D12+C16*D13+C17*D14)*(1-輸入!$C$43) -> 4.4524288 | E19: =(D15*E12+D16*E13+D17*E14)*(1-輸入!$C$43) -> 1.7943677 | F19: =(E15*F12+E16*F13+E17*F14)*(1-輸入!$C$43) -> 1.1591624 | G19: =(F15*G12+F16*G13+F17*G14)*(1-輸入!$C$43) -> 0.75327665 | H19: =(G15*H12+G16*H13+G17*H14)*(1-輸入!$C$43) -> 0.49241145
A20: 量與營收
A21: 價格反應項 (p/p前)^ε 之底數 | B21: x | D21: =IF(D$3>=輸入!$C$47,D18/C18,1) -> 1 | E21: =IF(E$3>=輸入!$C$47,E18/D18,1) -> 0.6422023 | F21: =IF(F$3>=輸入!$C$47,F18/E18,1) -> 0.64600047 | G21: =IF(G$3>=輸入!$C$47,G18/F18,1) -> 0.64984568 | H21: =IF(H$3>=輸入!$C$47,H18/G18,1) -> 0.65369271 | J21: 2025–26 為校準年，底數＝1
A22: 每任務 token | B22: K | C22: =輸入!$C$44 -> 10 | D22: =C22*(1+輸入!D$46)*D21^輸入!$F$34 -> 12 | E22: =D22*(1+輸入!E$46)*E21^輸入!$F$34 -> 15.760774 | F22: =E22*(1+輸入!F$46)*F21^輸入!$F$34 -> 20.124528 | G22: =F22*(1+輸入!G$46)*G21^輸入!$F$34 -> 25.192735 | H22: =G22*(1+輸入!H$46)*H21^輸入!$F$34 -> 30.909144 | J22: 水準拆分為正規化，只影響 N 與 k 的比例，不影響營收
A23: 任務數 | B23: 十億 | C23: =C24/C22 -> 184.05643 | D23: =C23*(1+輸入!D$45)*D21^輸入!$F$33 -> 430.69204 | E23: =D23*(1+輸入!E$45)*E21^輸入!$F$33 -> 851.46059 | F23: =E23*(1+輸入!F$45)*F21^輸入!$F$33 -> 1560.7572 | G23: =F23*(1+輸入!G$45)*G21^輸入!$F$33 -> 2638.0206 | H23: =G23*(1+輸入!H$45)*H21^輸入!$F$33 -> 4262.8287
A24: API 計費 token | B24: T | C24: =(輸入!$C$9-訂閱與廣告!C19-訂閱與廣告!C48)/C18*1000 -> 1840.5643 | D24: =D23*D22 -> 5168.3045 | E24: =E23*E22 -> 13419.678 | F24: =F23*F22 -> 31409.501 | G24: =G23*G22 -> 66458.954 | H24: =H23*H22 -> 131760.39 | J24: 2025：由營收倒推（唯一倒推）；之後＝任務數×每任務 token
A25: API 營收 | B25: $B | C25: =C24*C18/1000 -> 3.626 | D25: =D24*D18/1000 -> 14.440681 | E25: =E24*E18/1000 -> 24.079836 | F25: =F24*F18/1000 -> 36.408712 | G25: =G24*G18/1000 -> 50.061979 | H25: =H24*H18/1000 -> 64.880324
A26: API 依模型層級拆分（營收；成本見「推論成本」頁）
A27: API 營收：頂層（Astra） | B27: $B | C27: =C24*C15*C12*(1-輸入!$C$43)/1000 -> 2.244016 | D27: =D24*D15*D12*(1-輸入!$C$43)/1000 -> 6.0942993 | E27: =E24*E15*E12*(1-輸入!$C$43)/1000 -> 11.076838 | F27: =F24*F15*F12*(1-輸入!$C$43)/1000 -> 18.148169 | G27: =G24*G15*G12*(1-輸入!$C$43)/1000 -> 26.879631 | H27: =H24*H15*H12*(1-輸入!$C$43)/1000 -> 37.303769
A28: API token：頂層（Astra） | B28: T | C28: =C24*C15 -> 736.22572 | D28: =D24*D15 -> 775.24568 | E28: =E24*E15 -> 2012.9516 | F28: =F24*F15 -> 4711.4252 | G28: =G24*G15 -> 9968.8431 | H28: =H24*H15 -> 19764.058
A29: API 營收：中層（Sol） | B29: $B | C29: =C24*C16*C13*(1-輸入!$C$43)/1000 -> 1.2992911 | D29: =D24*D16*D13*(1-輸入!$C$43)/1000 -> 6.6519056 | E29: =E24*E16*E13*(1-輸入!$C$43)/1000 -> 10.363139 | F29: =F24*F16*F13*(1-輸入!$C$43)/1000 -> 14.553301 | G29: =G24*G16*G13*(1-輸入!$C$43)/1000 -> 18.475884 | H29: =H24*H16*H13*(1-輸入!$C$43)/1000 -> 21.977984
A30: API token：中層（Sol） | B30: T | C30: =C24*C16 -> 736.22572 | D30: =D24*D16 -> 2325.737 | E30: =E24*E16 -> 6038.8549 | F30: =F24*F16 -> 14134.276 | G30: =G24*G16 -> 29906.529 | H30: =H24*H16 -> 59292.175
A31: API 營收：低層（Luna） | B31: $B | C31: =C24*C17*C14*(1-輸入!$C$43)/1000 -> 0.082692872 | D31: =D24*D17*D14*(1-輸入!$C$43)/1000 -> 1.6944762 | E31: =E24*E17*E14*(1-輸入!$C$43)/1000 -> 2.6398589 | F31: =F24*F17*F14*(1-輸入!$C$43)/1000 -> 3.7072418 | G31: =G24*G17*G14*(1-輸入!$C$43)/1000 -> 4.7064628 | H31: =H24*H17*H14*(1-輸入!$C$43)/1000 -> 5.5985717
A32: API token：低層（Luna） | B32: T | C32: =C24*C17 -> 368.11286 | D32: =D24*D17 -> 2067.3218 | E32: =E24*E17 -> 5367.871 | F32: =F24*F17 -> 12563.8 | G32: =G24*G17 -> 26583.582 | H32: =H24*H17 -> 52704.155
A33: 年度對數歸因（加總＝ln(營收成長)）
A34: 需求量 ln(1+gN)+ln(1+gK) | B34: ln | D34: =LN(1+輸入!D$45)+LN(1+輸入!D$46) -> 1.0324725 | E34: =LN(1+輸入!E$45)+LN(1+輸入!E$46) -> 0.5113255 | F34: =LN(1+輸入!F$45)+LN(1+輸入!F$46) -> 0.41343328 | G34: =LN(1+輸入!G$45)+LN(1+輸入!G$46) -> 0.31845373 | H34: =LN(1+輸入!H$45)+LN(1+輸入!H$46) -> 0.2592826
A35: 牌價 ln(p*/p前) | B35: ln | D35: =LN(D19/C18) -> 0.81539184 | E35: =LN(E19/D18) -> -0.44285192 | F35: =LN(F19/E18) -> -0.43695504 | G35: =LN(G19/F18) -> -0.43102037 | H35: =LN(H19/G18) -> -0.42511791
A36: 組合 ln(p/p*) | B36: ln | D36: =LN(D18/D19) -> -0.46594513 | E36: =LN(E18/E19) -> 0 | F36: =LN(F18/F19) -> 0 | G36: =LN(G18/G19) -> 0 | H36: =LN(H18/H19) -> 0
A37: 價格反應 (εN+εK)·ln(p/p前) | B37: ln | D37: =(輸入!$F$33+輸入!$F$34)*LN(D21) -> 0 | E37: =(輸入!$F$33+輸入!$F$34)*LN(E21) -> 0.44285192 | F37: =(輸入!$F$33+輸入!$F$34)*LN(F21) -> 0.43695504 | G37: =(輸入!$F$33+輸入!$F$34)*LN(G21) -> 0.43102037 | H37: =(輸入!$F$33+輸入!$F$34)*LN(H21) -> 0.42511791
A38: 合計 | B38: ln | D38: =D34+D35+D36+D37 -> 1.3819192 | E38: =E34+E35+E36+E37 -> 0.5113255 | F38: =F34+F35+F36+F37 -> 0.41343328 | G38: =G34+G35+G36+G37 -> 0.31845373 | H38: =H34+H35+H36+H37 -> 0.2592826
A39: 誤差（合計−ln 營收成長） | B39: ln | D39: =D38-LN(D25/C25) -> 0 | E39: =E38-LN(E25/D25) -> 0 | F39: =F38-LN(F25/E25) -> 0 | G39: =G38-LN(G25/F25) -> 0 | H39: =H38-LN(H25/G25) -> 0
A40: 參考：2025 計費比例
A41: API 計費 token ÷ 揭露處理 token（2025） | C41: =C24/輸入!$C$13 -> 0.70036693

Sheet 營收彙總
A1: 營收彙總（$B）：核心＝訂閱＋API；廣告另列；Microsoft 分潤；淨額
A3: 項目 | B3: 單位 | C3: 2025 | D3: 2026 | E3: 2027 | F3: 2028 | G3: 2029 | H3: 2030 | J3: 說明
A4: 容量上限係數（算力MW；1＝未受限） | B4: x | C4: =算力MW!C32 -> 1 | D4: =算力MW!D32 -> 1 | E4: =算力MW!E32 -> 1 | F4: =算力MW!F32 -> 1 | G4: =算力MW!G32 -> 1 | H4: =算力MW!H32 -> 1
A5: 消費端與企業端（訂閱依方案分；API 全數歸企業端，另依模型層級列示）
A6: Go | B6: $B | C6: =訂閱與廣告!C14*C$4 -> 0.144 | D6: =訂閱與廣告!D14*D$4 -> 2.9232 | E6: =訂閱與廣告!E14*E$4 -> 5.5762435 | F6: =訂閱與廣告!F14*F$4 -> 8.424313 | G6: =訂閱與廣告!G14*G$4 -> 10.617809 | H6: =訂閱與廣告!H14*H$4 -> 12.79393
A7: Plus | B7: $B | C7: =訂閱與廣告!C15*C$4 -> 7.02 | D7: =訂閱與廣告!D15*D$4 -> 7.9572 | E7: =訂閱與廣告!E15*E$4 -> 8.9950957 | F7: =訂閱與廣告!F15*F$4 -> 9.8600087 | G7: =訂閱與廣告!G15*G$4 -> 10.551939 | H7: =訂閱與廣告!H15*H$4 -> 11.070887
A8: Pro | B8: $B | C8: =訂閱與廣告!C16*C$4 -> 1.2 | D8: =訂閱與廣告!D16*D$4 -> 1.8 | E8: =訂閱與廣告!E16*E$4 -> 2.7 | F8: =訂閱與廣告!F16*F$4 -> 3.6 | G8: =訂閱與廣告!G16*G$4 -> 4.5 | H8: =訂閱與廣告!H16*H$4 -> 5.4
A9: 廣告（Free＋Go 曝光） | B9: $B | C9: =訂閱與廣告!C48*C$4 -> 0 | D9: =訂閱與廣告!D48*D$4 -> 0.74295 | E9: =訂閱與廣告!E48*E$4 -> 1.858427 | F9: =訂閱與廣告!F48*F$4 -> 2.9106078 | G9: =訂閱與廣告!G48*G$4 -> 4.1568065 | H9: =訂閱與廣告!H48*H$4 -> 5.5761571
A10: 消費端合計 | B10: $B | C10: =SUM(C6:C9) -> 8.364 | D10: =SUM(D6:D9) -> 13.42335 | E10: =SUM(E6:E9) -> 19.129766 | F10: =SUM(F6:F9) -> 24.79493 | G10: =SUM(G6:G9) -> 29.826554 | H10: =SUM(H6:H9) -> 34.840974
A11: 企業席位（Business／Enterprise／Edu） | B11: $B | C11: =訂閱與廣告!C17*C$4 -> 1.08 | D11: =訂閱與廣告!D17*D$4 -> 5.04 | E11: =訂閱與廣告!E17*E$4 -> 9.36 | F11: =訂閱與廣告!F17*F$4 -> 13.68 | G11: =訂閱與廣告!G17*G$4 -> 17.28 | H11: =訂閱與廣告!H17*H$4 -> 20.16
A12: API 頂層（Astra） | B12: $B | C12: =API!C27*C$4 -> 2.244016 | D12: =API!D27*D$4 -> 6.0942993 | E12: =API!E27*E$4 -> 11.076838 | F12: =API!F27*F$4 -> 18.148169 | G12: =API!G27*G$4 -> 26.879631 | H12: =API!H27*H$4 -> 37.303769
A13: API 中層（Sol） | B13: $B | C13: =API!C29*C$4 -> 1.2992911 | D13: =API!D29*D$4 -> 6.6519056 | E13: =API!E29*E$4 -> 10.363139 | F13: =API!F29*F$4 -> 14.553301 | G13: =API!G29*G$4 -> 18.475884 | H13: =API!H29*H$4 -> 21.977984
A14: API 低層（Luna） | B14: $B | C14: =API!C31*C$4 -> 0.082692872 | D14: =API!D31*D$4 -> 1.6944762 | E14: =API!E31*E$4 -> 2.6398589 | F14: =API!F31*F$4 -> 3.7072418 | G14: =API!G31*G$4 -> 4.7064628 | H14: =API!H31*H$4 -> 5.5985717
A15: 企業端合計 | B15: $B | C15: =SUM(C11:C14) -> 4.706 | D15: =SUM(D11:D14) -> 19.480681 | E15: =SUM(E11:E14) -> 33.439836 | F15: =SUM(F11:F14) -> 50.088712 | G15: =SUM(G11:G14) -> 67.341979 | H15: =SUM(H11:H14) -> 85.040324
A16: 企業端占總額 | B16: % | C16: =C15/(C10+C15) -> 0.36006121 | D16: =D15/(D10+D15) -> 0.59204543 | E16: =E15/(E10+E15) -> 0.63610594 | F16: =F15/(F10+F15) -> 0.66888723 | G16: =G15/(G10+G15) -> 0.69304307 | H16: =H15/(H10+H15) -> 0.70937106 | J16: CFO：2026 年初消費端／企業端 60/40，8 月企業端已超過消費端
A17: 依營收線
A18: 訂閱 | B18: $B | C18: =訂閱與廣告!C19*C$4 -> 9.444 | D18: =訂閱與廣告!D19*D$4 -> 17.7204 | E18: =訂閱與廣告!E19*E$4 -> 26.631339 | F18: =訂閱與廣告!F19*F$4 -> 35.564322 | G18: =訂閱與廣告!G19*G$4 -> 42.949748 | H18: =訂閱與廣告!H19*H$4 -> 49.424817
A19: API | B19: $B | C19: =API!C25*C$4 -> 3.626 | D19: =API!D25*D$4 -> 14.440681 | E19: =API!E25*E$4 -> 24.079836 | F19: =API!F25*F$4 -> 36.408712 | G19: =API!G25*G$4 -> 50.061979 | H19: =API!H25*H$4 -> 64.880324
A20: 核心營收（訂閱＋API） | B20: $B | C20: =C18+C19 -> 13.07 | D20: =D18+D19 -> 32.161081 | E20: =E18+E19 -> 50.711175 | F20: =F18+F19 -> 71.973033 | G20: =G18+G19 -> 93.011726 | H20: =H18+H19 -> 114.30514
A21: 廣告 | B21: $B | C21: =訂閱與廣告!C48*C$4 -> 0 | D21: =訂閱與廣告!D48*D$4 -> 0.74295 | E21: =訂閱與廣告!E48*E$4 -> 1.858427 | F21: =訂閱與廣告!F48*F$4 -> 2.9106078 | G21: =訂閱與廣告!G48*G$4 -> 4.1568065 | H21: =訂閱與廣告!H48*H$4 -> 5.5761571
A22: 總額 | B22: $B | C22: =C20+C21 -> 13.07 | D22: =D20+D21 -> 32.904031 | E22: =E20+E21 -> 52.569602 | F22: =F20+F21 -> 74.883641 | G22: =G20+G21 -> 97.168533 | H22: =H20+H21 -> 119.8813
A23: Microsoft 分潤 | B23: $B | C23: =輸入!$C$17*C22 -> 2.614 | D23: =IF(D$3<輸入!$C$19,輸入!$C$17*D22,IF(D$3>輸入!$C$20,0,MIN(輸入!$C$17*D22,輸入!$C$18-C24))) -> 6.5808062 | E23: =IF(E$3<輸入!$C$19,輸入!$C$17*E22,IF(E$3>輸入!$C$20,0,MIN(輸入!$C$17*E22,輸入!$C$18-D24))) -> 10.51392 | F23: =IF(F$3<輸入!$C$19,輸入!$C$17*F22,IF(F$3>輸入!$C$20,0,MIN(輸入!$C$17*F22,輸入!$C$18-E24))) -> 14.976728 | G23: =IF(G$3<輸入!$C$19,輸入!$C$17*G22,IF(G$3>輸入!$C$20,0,MIN(輸入!$C$17*G22,輸入!$C$18-F24))) -> 5.9285452 | H23: =IF(H$3<輸入!$C$19,輸入!$C$17*H22,IF(H$3>輸入!$C$20,0,MIN(輸入!$C$17*H22,輸入!$C$18-G24))) -> 0
A24: 分潤累計（自起算年） | B24: $B | C24: =0 -> 0 | D24: =C24+IF(D$3>=輸入!$C$19,D23,0) -> 6.5808062 | E24: =D24+IF(E$3>=輸入!$C$19,E23,0) -> 17.094727 | F24: =E24+IF(F$3>=輸入!$C$19,F23,0) -> 32.071455 | G24: =F24+IF(G$3>=輸入!$C$19,G23,0) -> 38 | H24: =G24+IF(H$3>=輸入!$C$19,H23,0) -> 38
A25: 淨額（總額−分潤） | B25: $B | C25: =C22-C23 -> 10.456 | D25: =D22-D23 -> 26.323225 | E25: =E22-E23 -> 42.055681 | F25: =F22-F23 -> 59.906913 | G25: =G22-G23 -> 91.239988 | H25: =H22-H23 -> 119.8813
A26: 比率與檢查用
A27: 總額年增率 | B27: % | D27: =D22/C22-1 -> 1.5175234 | E27: =E22/D22-1 -> 0.59766448 | F27: =F22/E22-1 -> 0.42446659 | G27: =G22/F22-1 -> 0.29759359 | H27: =H22/G22-1 -> 0.2337461
A28: 消費端＋企業端 − 總額（應為 0） | B28: $B | C28: =C10+C15-C22 -> 0 | D28: =D10+D15-D22 -> 0 | E28: =E10+E15-E22 -> 0 | F28: =F10+F15-F22 -> 0 | G28: =G10+G15-G22 -> 0 | H28: =H10+H15-H22 -> 0
A29: 廣告占總額 | B29: % | C29: =C21/C22 -> 0 | D29: =D21/D22 -> 0.0225793 | E29: =E21/E22 -> 0.035351741 | F29: =F21/F22 -> 0.038868407 | G29: =G21/G22 -> 0.042779348 | H29: =H21/H22 -> 0.046513986
A30: 2026 下半年（模型全年−上半年實際） | B30: $B | D30: =D22-輸入!$C$10-輸入!$C$11 -> 20.504031
A31: 2026 下半年 ÷ 上半年 | D31: =D30/(輸入!$C$10+輸入!$C$11) -> 1.6535509
A32: 2026 下半年月均營收 | B32: $B/月 | D32: =D30/6 -> 3.4173385
A34: 敏感度：FY2030 核心營收（$B）｜列＝ε 總和、欄＝牌價年變動組（頂/中/低）
A35: ε 總和 ＼ 牌價年變動 | C35: 溫和 −15/−20/−20% | D35: 基準 −30/−40/−40% | E35: 劇烈 −45/−60/−60%
A36: -0.5 | C36: =H18+API!D24*(1+輸入!E$45)*(1+輸入!E$46)*(1+輸入!F$45)*(1+輸入!F$46)*(1+輸入!G$45)*(1+輸入!G$46)*(1+輸入!H$45)*(1+輸入!H$46)*(((API!H15*API!D12*(1+-0.15)^4+API!H16*API!D13*(1+-0.2)^4+API!H17*API!D14*(1+-0.2)^4)*(1-輸入!$C$43))/API!D18)^A36*((API!H15*API!D12*(1+-0.15)^4+API!H16*API!D13*(1+-0.2)^4+API!H17*API!D14*(1+-0.2)^4)*(1-輸入!$C$43))/1000 -> 93.286893 | D36: =H18+API!D24*(1+輸入!E$45)*(1+輸入!E$46)*(1+輸入!F$45)*(1+輸入!F$46)*(1+輸入!G$45)*(1+輸入!G$46)*(1+輸入!H$45)*(1+輸入!H$46)*(((API!H15*API!D12*(1+-0.3)^4+API!H16*API!D13*(1+-0.4)^4+API!H17*API!D14*(1+-0.4)^4)*(1-輸入!$C$43))/API!D18)^A36*((API!H15*API!D12*(1+-0.3)^4+API!H16*API!D13*(1+-0.4)^4+API!H17*API!D14*(1+-0.4)^4)*(1-輸入!$C$43))/1000 -> 76.661693 | E36: =H18+API!D24*(1+輸入!E$45)*(1+輸入!E$46)*(1+輸入!F$45)*(1+輸入!F$46)*(1+輸入!G$45)*(1+輸入!G$46)*(1+輸入!H$45)*(1+輸入!H$46)*(((API!H15*API!D12*(1+-0.45)^4+API!H16*API!D13*(1+-0.6)^4+API!H17*API!D14*(1+-0.6)^4)*(1-輸入!$C$43))/API!D18)^A36*((API!H15*API!D12*(1+-0.45)^4+API!H16*API!D13*(1+-0.6)^4+API!H17*API!D14*(1+-0.6)^4)*(1-輸入!$C$43))/1000 -> 64.419607
A37: -1 | C37: =H18+API!D24*(1+輸入!E$45)*(1+輸入!E$46)*(1+輸入!F$45)*(1+輸入!F$46)*(1+輸入!G$45)*(1+輸入!G$46)*(1+輸入!H$45)*(1+輸入!H$46)*(((API!H15*API!D12*(1+-0.15)^4+API!H16*API!D13*(1+-0.2)^4+API!H17*API!D14*(1+-0.2)^4)*(1-輸入!$C$43))/API!D18)^A37*((API!H15*API!D12*(1+-0.15)^4+API!H16*API!D13*(1+-0.2)^4+API!H17*API!D14*(1+-0.2)^4)*(1-輸入!$C$43))/1000 -> 114.30514 | D37: =H18+API!D24*(1+輸入!E$45)*(1+輸入!E$46)*(1+輸入!F$45)*(1+輸入!F$46)*(1+輸入!G$45)*(1+輸入!G$46)*(1+輸入!H$45)*(1+輸入!H$46)*(((API!H15*API!D12*(1+-0.3)^4+API!H16*API!D13*(1+-0.4)^4+API!H17*API!D14*(1+-0.4)^4)*(1-輸入!$C$43))/API!D18)^A37*((API!H15*API!D12*(1+-0.3)^4+API!H16*API!D13*(1+-0.4)^4+API!H17*API!D14*(1+-0.4)^4)*(1-輸入!$C$43))/1000 -> 114.30514 | E37: =H18+API!D24*(1+輸入!E$45)*(1+輸入!E$46)*(1+輸入!F$45)*(1+輸入!F$46)*(1+輸入!G$45)*(1+輸入!G$46)*(1+輸入!H$45)*(1+輸入!H$46)*(((API!H15*API!D12*(1+-0.45)^4+API!H16*API!D13*(1+-0.6)^4+API!H17*API!D14*(1+-0.6)^4)*(1-輸入!$C$43))/API!D18)^A37*((API!H15*API!D12*(1+-0.45)^4+API!H16*API!D13*(1+-0.6)^4+API!H17*API!D14*(1+-0.6)^4)*(1-輸入!$C$43))/1000 -> 114.30514
A38: -1.5 | C38: =H18+API!D24*(1+輸入!E$45)*(1+輸入!E$46)*(1+輸入!F$45)*(1+輸入!F$46)*(1+輸入!G$45)*(1+輸入!G$46)*(1+輸入!H$45)*(1+輸入!H$46)*(((API!H15*API!D12*(1+-0.15)^4+API!H16*API!D13*(1+-0.2)^4+API!H17*API!D14*(1+-0.2)^4)*(1-輸入!$C$43))/API!D18)^A38*((API!H15*API!D12*(1+-0.15)^4+API!H16*API!D13*(1+-0.2)^4+API!H17*API!D14*(1+-0.2)^4)*(1-輸入!$C$43))/1000 -> 145.39512 | D38: =H18+API!D24*(1+輸入!E$45)*(1+輸入!E$46)*(1+輸入!F$45)*(1+輸入!F$46)*(1+輸入!G$45)*(1+輸入!G$46)*(1+輸入!H$45)*(1+輸入!H$46)*(((API!H15*API!D12*(1+-0.3)^4+API!H16*API!D13*(1+-0.4)^4+API!H17*API!D14*(1+-0.4)^4)*(1-輸入!$C$43))/API!D18)^A38*((API!H15*API!D12*(1+-0.3)^4+API!H16*API!D13*(1+-0.4)^4+API!H17*API!D14*(1+-0.4)^4)*(1-輸入!$C$43))/1000 -> 203.97472 | E38: =H18+API!D24*(1+輸入!E$45)*(1+輸入!E$46)*(1+輸入!F$45)*(1+輸入!F$46)*(1+輸入!G$45)*(1+輸入!G$46)*(1+輸入!H$45)*(1+輸入!H$46)*(((API!H15*API!D12*(1+-0.45)^4+API!H16*API!D13*(1+-0.6)^4+API!H17*API!D14*(1+-0.6)^4)*(1-輸入!$C$43))/API!D18)^A38*((API!H15*API!D12*(1+-0.45)^4+API!H16*API!D13*(1+-0.6)^4+API!H17*API!D14*(1+-0.6)^4)*(1-輸入!$C$43))/1000 -> 330.15277
A39: 註：2027 起彈性生效；表內各格為同一公式之封閉解，與主模型 base 格一致。
A42: 損益口徑（毛利＝總額 − 推論；貢獻＝毛利 − 訓練 − 閒置）
A43: 推論成本 | B43: $B | C43: =算力MW!C44 -> 8.4 | D43: =算力MW!D44 -> 9.3362756 | E43: =算力MW!E44 -> 11.732883 | F43: =算力MW!F44 -> 15.060732 | G43: =算力MW!G44 -> 21.327565 | H43: =算力MW!H44 -> 30.532794
A44: 毛利 | B44: $B | C44: =C22-C43 -> 4.67 | D44: =D22-D43 -> 23.567755 | E44: =E22-E43 -> 40.836719 | F44: =F22-F43 -> 59.822909 | G44: =G22-G43 -> 75.840968 | H44: =H22-H43 -> 89.348505
A45: 毛利率 | B45: % | C45: =C44/C22 -> 0.35730681 | D45: =D44/D22 -> 0.71625739 | E45: =E44/E22 -> 0.7768124 | F45: =F44/F22 -> 0.79887821 | G45: =G44/G22 -> 0.78050955 | H45: =H44/H22 -> 0.74530812 | J45: 2025 報導毛利率 33%；公司 2030 目標約 67%
A46: 訓練成本 | B46: $B | C46: =算力MW!C45 -> 12 | D46: =算力MW!D45 -> 20.580296 | E46: =算力MW!E45 -> 92.694771 | F46: =算力MW!F45 -> 111.81512 | G46: =算力MW!G45 -> 130.90215 | H46: =算力MW!H45 -> 141.89246
A47: 閒置成本 | B47: $B | C47: =算力MW!C46 -> 0 | D47: =算力MW!D46 -> 3.3240635 | E47: =算力MW!E46 -> 11.603073 | F47: =算力MW!F46 -> 14.097317 | G47: =算力MW!G46 -> 16.914413 | H47: =算力MW!H46 -> 19.158361
A48: 扣除訓練與閒置後貢獻 | B48: $B | C48: =C44-C46-C47 -> -7.33 | D48: =D44-D46-D47 -> -0.3366038 | E48: =E44-E46-E47 -> -63.461125 | F48: =F44-F46-F47 -> -66.089526 | G48: =G44-G46-G47 -> -71.975596 | H48: =H44-H46-H47 -> -71.702313
A49: 扣除訓練與閒置後貢獻率 | B49: % | C49: =C48/C22 -> -0.56082632 | D49: =D48/D22 -> -0.010229865 | E49: =E48/E22 -> -1.2071829 | F49: =F48/F22 -> -0.88256293 | G49: =G48/G22 -> -0.74072947 | H49: =H48/H22 -> -0.59811091

Sheet 推論成本
A1: 推論成本（$B）：Tokenomics 物理 roofline → 各模型類別每 token 成本 → 各方案使用型態加權 → FY2025 校準
A3: 項目 | B3: 單位 | C3: 2025 | D3: 2026 | E3: 2027 | F3: 2028 | G3: 2029 | H3: 2030 | J3: 說明
A4: 一、物理單位成本（理想值；Vera Rubin NVL72；欄 C）
A5: 每機架秒成本（含利用率） | B5: $/rack-s | C5: =輸入!$C$76*1000000/(8760*3600)/輸入!$C$78 -> 0.093369482 | J5: DC_Cost_Model 年營運費用（含折舊）÷ 架數 ÷ 秒數 ÷ 利用率
A6: Luna：權重位元組 | B6: GB | C6: =輸入!$C$83*輸入!$C$86 -> 144.84 | J6: MoE 大批次下幾乎所有專家都會被讀取，故以總參數計
A7: Luna：每序列 KV 快取 | B7: MB | C7: =輸入!$C$80*1000*輸入!$C$85/1000000 -> 22.36
A8: Luna：decode 批次 | B8: 序列 | C8: =MIN(輸入!$C$79,(輸入!$C$74*1000*0.9-C6)/(C7/1000)) -> 256 | J8: 受批次上限或 HBM 容量（90%）限制
A9: Luna：每步記憶體時間 | B9: ms | C9: =(C6+C8*C7/1000)/(輸入!$C$72*1000)*1000 -> 0.095293772
A10: Luna：每步計算時間 | B10: ms | C10: =2*輸入!$C$84*1000000000*C8*輸入!$C$77/(輸入!$C$73*1000000000000000*輸入!$C$75)*1000 -> 0.015530667
A11: Luna：輸出 token 成本 | B11: $/M | C11: =MAX(C9,C10)/1000/(C8*輸入!$C$77)*C5*1000000 -> 0.011821761
A12: Luna：新鮮輸入 token 成本 | B12: $/M | C12: =2*輸入!$C$84*1000000000*輸入!$C$81/(輸入!$C$73*1000000000000000*輸入!$C$75)*C5*1000000 -> 0.002119339
A13: Luna：快取輸入 token 成本 | B13: $/M | C13: =C12*輸入!$C$82 -> 0.0002119339
A14: Sol：權重位元組 | B14: GB | C14: =輸入!$C$87*輸入!$C$90 -> 811.2 | J14: MoE 大批次下幾乎所有專家都會被讀取，故以總參數計
A15: Sol：每序列 KV 快取 | B15: MB | C15: =輸入!$C$80*1000*輸入!$C$89/1000000 -> 31.72
A16: Sol：decode 批次 | B16: 序列 | C16: =MIN(輸入!$C$79,(輸入!$C$74*1000*0.9-C14)/(C15/1000)) -> 256 | J16: 受批次上限或 HBM 容量（90%）限制
A17: Sol：每步記憶體時間 | B17: ms | C17: =(C14+C16*C15/1000)/(輸入!$C$72*1000)*1000 -> 0.51855716
A18: Sol：每步計算時間 | B18: ms | C18: =2*輸入!$C$88*1000000000*C16*輸入!$C$77/(輸入!$C$73*1000000000000000*輸入!$C$75)*1000 -> 0.058538667
A19: Sol：輸出 token 成本 | B19: $/M | C19: =MAX(C17,C18)/1000/(C16*輸入!$C$77)*C5*1000000 -> 0.06433011
A20: Sol：新鮮輸入 token 成本 | B20: $/M | C20: =2*輸入!$C$88*1000000000*輸入!$C$81/(輸入!$C$73*1000000000000000*輸入!$C$75)*C5*1000000 -> 0.0079882779
A21: Sol：快取輸入 token 成本 | B21: $/M | C21: =C20*輸入!$C$82 -> 0.00079882779
A22: Astra：權重位元組 | B22: GB | C22: =輸入!$C$91*輸入!$C$94 -> 2120 | J22: MoE 大批次下幾乎所有專家都會被讀取，故以總參數計
A23: Astra：每序列 KV 快取 | B23: MB | C23: =輸入!$C$80*1000*輸入!$C$93/1000000 -> 1638.4
A24: Astra：decode 批次 | B24: 序列 | C24: =MIN(輸入!$C$79,(輸入!$C$74*1000*0.9-C22)/(C23/1000)) -> 256 | J24: 受批次上限或 HBM 容量（90%）限制
A25: Astra：每步記憶體時間 | B25: ms | C25: =(C22+C24*C23/1000)/(輸入!$C$72*1000)*1000 -> 1.6072344
A26: Astra：每步計算時間 | B26: ms | C26: =2*輸入!$C$92*1000000000*C24*輸入!$C$77/(輸入!$C$73*1000000000000000*輸入!$C$75)*1000 -> 0.21504
A27: Astra：輸出 token 成本 | B27: $/M | C27: =MAX(C25,C26)/1000/(C24*輸入!$C$77)*C5*1000000 -> 0.19938702
A28: Astra：新鮮輸入 token 成本 | B28: $/M | C28: =2*輸入!$C$92*1000000000*輸入!$C$81/(輸入!$C$73*1000000000000000*輸入!$C$75)*C5*1000000 -> 0.029344694
A29: Astra：快取輸入 token 成本 | B29: $/M | C29: =C28*輸入!$C$82 -> 0.0029344694
A30: 成本指數（Luna＝1）與牌價指數對照
A31: Luna：輸出成本指數 | B31: x | C31: =C11/C11 -> 1
A32: Luna：輸入成本指數 | B32: x | C32: =C12/C12 -> 1
A33: Luna：輸出 ÷ 輸入成本 | B33: x | C33: =C11/C12 -> 5.5780414
A34: Sol：輸出成本指數 | B34: x | C34: =C19/C11 -> 5.441669
A35: Sol：輸入成本指數 | B35: x | C35: =C20/C12 -> 3.7692308
A36: Sol：輸出 ÷ 輸入成本 | B36: x | C36: =C19/C20 -> 8.0530636
A37: Astra：輸出成本指數 | B37: x | C37: =C27/C11 -> 16.866101
A38: Astra：輸入成本指數 | B38: x | C38: =C28/C12 -> 13.846154
A39: Astra：輸出 ÷ 輸入成本 | B39: x | C39: =C27/C28 -> 6.7946531
A40: Luna：2026 輸出牌價指數（對照） | B40: x | C40: =API!D10/API!D10 -> 1 | J40: 牌價比 ÷ 成本比 > 1 表示該層定價加成較高
A41: Sol：2026 輸出牌價指數（對照） | B41: x | C41: =API!D8/API!D10 -> 3.45953 | J41: 牌價比 ÷ 成本比 > 1 表示該層定價加成較高
A42: Astra：2026 輸出牌價指數（對照） | B42: x | C42: =API!D6/API!D10 -> 9.3472585 | J42: 牌價比 ÷ 成本比 > 1 表示該層定價加成較高
A43: 二、各區隔每兆 token 理想成本（$B/T；依模型組合、輸出占比、快取命中加權）
A44: Free | B44: $B/T | C44: =(輸入!$C$96*((1-輸入!$C$99)*((1-輸入!$C$100)*$C$12+輸入!$C$100*$C$13)+輸入!$C$99*$C$11)+輸入!$C$97*((1-輸入!$C$99)*((1-輸入!$C$100)*$C$20+輸入!$C$100*$C$21)+輸入!$C$99*$C$19)+輸入!$C$98*((1-輸入!$C$99)*((1-輸入!$C$100)*$C$28+輸入!$C$100*$C$29)+輸入!$C$99*$C$27))/1000 -> 5.5671408e-06 | D44: =(輸入!$C$96*((1-輸入!$C$99)*((1-輸入!$C$100)*$C$12+輸入!$C$100*$C$13)+輸入!$C$99*$C$11)+輸入!$C$97*((1-輸入!$C$99)*((1-輸入!$C$100)*$C$20+輸入!$C$100*$C$21)+輸入!$C$99*$C$19)+輸入!$C$98*((1-輸入!$C$99)*((1-輸入!$C$100)*$C$28+輸入!$C$100*$C$29)+輸入!$C$99*$C$27))/1000 -> 5.5671408e-06 | E44: =(輸入!$C$96*((1-輸入!$C$99)*((1-輸入!$C$100)*$C$12+輸入!$C$100*$C$13)+輸入!$C$99*$C$11)+輸入!$C$97*((1-輸入!$C$99)*((1-輸入!$C$100)*$C$20+輸入!$C$100*$C$21)+輸入!$C$99*$C$19)+輸入!$C$98*((1-輸入!$C$99)*((1-輸入!$C$100)*$C$28+輸入!$C$100*$C$29)+輸入!$C$99*$C$27))/1000 -> 5.5671408e-06 | F44: =(輸入!$C$96*((1-輸入!$C$99)*((1-輸入!$C$100)*$C$12+輸入!$C$100*$C$13)+輸入!$C$99*$C$11)+輸入!$C$97*((1-輸入!$C$99)*((1-輸入!$C$100)*$C$20+輸入!$C$100*$C$21)+輸入!$C$99*$C$19)+輸入!$C$98*((1-輸入!$C$99)*((1-輸入!$C$100)*$C$28+輸入!$C$100*$C$29)+輸入!$C$99*$C$27))/1000 -> 5.5671408e-06 | G44: =(輸入!$C$96*((1-輸入!$C$99)*((1-輸入!$C$100)*$C$12+輸入!$C$100*$C$13)+輸入!$C$99*$C$11)+輸入!$C$97*((1-輸入!$C$99)*((1-輸入!$C$100)*$C$20+輸入!$C$100*$C$21)+輸入!$C$99*$C$19)+輸入!$C$98*((1-輸入!$C$99)*((1-輸入!$C$100)*$C$28+輸入!$C$100*$C$29)+輸入!$C$99*$C$27))/1000 -> 5.5671408e-06 | H44: =(輸入!$C$96*((1-輸入!$C$99)*((1-輸入!$C$100)*$C$12+輸入!$C$100*$C$13)+輸入!$C$99*$C$11)+輸入!$C$97*((1-輸入!$C$99)*((1-輸入!$C$100)*$C$20+輸入!$C$100*$C$21)+輸入!$C$99*$C$19)+輸入!$C$98*((1-輸入!$C$99)*((1-輸入!$C$100)*$C$28+輸入!$C$100*$C$29)+輸入!$C$99*$C$27))/1000 -> 5.5671408e-06
A45: Go | B45: $B/T | C45: =(輸入!$C$101*((1-輸入!$C$104)*((1-輸入!$C$105)*$C$12+輸入!$C$105*$C$13)+輸入!$C$104*$C$11)+輸入!$C$102*((1-輸入!$C$104)*((1-輸入!$C$105)*$C$20+輸入!$C$105*$C$21)+輸入!$C$104*$C$19)+輸入!$C$103*((1-輸入!$C$104)*((1-輸入!$C$105)*$C$28+輸入!$C$105*$C$29)+輸入!$C$104*$C$27))/1000 -> 6.3643497e-06 | D45: =(輸入!$C$101*((1-輸入!$C$104)*((1-輸入!$C$105)*$C$12+輸入!$C$105*$C$13)+輸入!$C$104*$C$11)+輸入!$C$102*((1-輸入!$C$104)*((1-輸入!$C$105)*$C$20+輸入!$C$105*$C$21)+輸入!$C$104*$C$19)+輸入!$C$103*((1-輸入!$C$104)*((1-輸入!$C$105)*$C$28+輸入!$C$105*$C$29)+輸入!$C$104*$C$27))/1000 -> 6.3643497e-06 | E45: =(輸入!$C$101*((1-輸入!$C$104)*((1-輸入!$C$105)*$C$12+輸入!$C$105*$C$13)+輸入!$C$104*$C$11)+輸入!$C$102*((1-輸入!$C$104)*((1-輸入!$C$105)*$C$20+輸入!$C$105*$C$21)+輸入!$C$104*$C$19)+輸入!$C$103*((1-輸入!$C$104)*((1-輸入!$C$105)*$C$28+輸入!$C$105*$C$29)+輸入!$C$104*$C$27))/1000 -> 6.3643497e-06 | F45: =(輸入!$C$101*((1-輸入!$C$104)*((1-輸入!$C$105)*$C$12+輸入!$C$105*$C$13)+輸入!$C$104*$C$11)+輸入!$C$102*((1-輸入!$C$104)*((1-輸入!$C$105)*$C$20+輸入!$C$105*$C$21)+輸入!$C$104*$C$19)+輸入!$C$103*((1-輸入!$C$104)*((1-輸入!$C$105)*$C$28+輸入!$C$105*$C$29)+輸入!$C$104*$C$27))/1000 -> 6.3643497e-06 | G45: =(輸入!$C$101*((1-輸入!$C$104)*((1-輸入!$C$105)*$C$12+輸入!$C$105*$C$13)+輸入!$C$104*$C$11)+輸入!$C$102*((1-輸入!$C$104)*((1-輸入!$C$105)*$C$20+輸入!$C$105*$C$21)+輸入!$C$104*$C$19)+輸入!$C$103*((1-輸入!$C$104)*((1-輸入!$C$105)*$C$28+輸入!$C$105*$C$29)+輸入!$C$104*$C$27))/1000 -> 6.3643497e-06 | H45: =(輸入!$C$101*((1-輸入!$C$104)*((1-輸入!$C$105)*$C$12+輸入!$C$105*$C$13)+輸入!$C$104*$C$11)+輸入!$C$102*((1-輸入!$C$104)*((1-輸入!$C$105)*$C$20+輸入!$C$105*$C$21)+輸入!$C$104*$C$19)+輸入!$C$103*((1-輸入!$C$104)*((1-輸入!$C$105)*$C$28+輸入!$C$105*$C$29)+輸入!$C$104*$C$27))/1000 -> 6.3643497e-06
A46: Plus | B46: $B/T | C46: =(輸入!$C$106*((1-輸入!$C$109)*((1-輸入!$C$110)*$C$12+輸入!$C$110*$C$13)+輸入!$C$109*$C$11)+輸入!$C$107*((1-輸入!$C$109)*((1-輸入!$C$110)*$C$20+輸入!$C$110*$C$21)+輸入!$C$109*$C$19)+輸入!$C$108*((1-輸入!$C$109)*((1-輸入!$C$110)*$C$28+輸入!$C$110*$C$29)+輸入!$C$109*$C$27))/1000 -> 2.3392664e-05 | D46: =(輸入!$C$106*((1-輸入!$C$109)*((1-輸入!$C$110)*$C$12+輸入!$C$110*$C$13)+輸入!$C$109*$C$11)+輸入!$C$107*((1-輸入!$C$109)*((1-輸入!$C$110)*$C$20+輸入!$C$110*$C$21)+輸入!$C$109*$C$19)+輸入!$C$108*((1-輸入!$C$109)*((1-輸入!$C$110)*$C$28+輸入!$C$110*$C$29)+輸入!$C$109*$C$27))/1000 -> 2.3392664e-05 | E46: =(輸入!$C$106*((1-輸入!$C$109)*((1-輸入!$C$110)*$C$12+輸入!$C$110*$C$13)+輸入!$C$109*$C$11)+輸入!$C$107*((1-輸入!$C$109)*((1-輸入!$C$110)*$C$20+輸入!$C$110*$C$21)+輸入!$C$109*$C$19)+輸入!$C$108*((1-輸入!$C$109)*((1-輸入!$C$110)*$C$28+輸入!$C$110*$C$29)+輸入!$C$109*$C$27))/1000 -> 2.3392664e-05 | F46: =(輸入!$C$106*((1-輸入!$C$109)*((1-輸入!$C$110)*$C$12+輸入!$C$110*$C$13)+輸入!$C$109*$C$11)+輸入!$C$107*((1-輸入!$C$109)*((1-輸入!$C$110)*$C$20+輸入!$C$110*$C$21)+輸入!$C$109*$C$19)+輸入!$C$108*((1-輸入!$C$109)*((1-輸入!$C$110)*$C$28+輸入!$C$110*$C$29)+輸入!$C$109*$C$27))/1000 -> 2.3392664e-05 | G46: =(輸入!$C$106*((1-輸入!$C$109)*((1-輸入!$C$110)*$C$12+輸入!$C$110*$C$13)+輸入!$C$109*$C$11)+輸入!$C$107*((1-輸入!$C$109)*((1-輸入!$C$110)*$C$20+輸入!$C$110*$C$21)+輸入!$C$109*$C$19)+輸入!$C$108*((1-輸入!$C$109)*((1-輸入!$C$110)*$C$28+輸入!$C$110*$C$29)+輸入!$C$109*$C$27))/1000 -> 2.3392664e-05 | H46: =(輸入!$C$106*((1-輸入!$C$109)*((1-輸入!$C$110)*$C$12+輸入!$C$110*$C$13)+輸入!$C$109*$C$11)+輸入!$C$107*((1-輸入!$C$109)*((1-輸入!$C$110)*$C$20+輸入!$C$110*$C$21)+輸入!$C$109*$C$19)+輸入!$C$108*((1-輸入!$C$109)*((1-輸入!$C$110)*$C$28+輸入!$C$110*$C$29)+輸入!$C$109*$C$27))/1000 -> 2.3392664e-05
A47: Pro | B47: $B/T | C47: =(輸入!$C$111*((1-輸入!$C$114)*((1-輸入!$C$115)*$C$12+輸入!$C$115*$C$13)+輸入!$C$114*$C$11)+輸入!$C$112*((1-輸入!$C$114)*((1-輸入!$C$115)*$C$20+輸入!$C$115*$C$21)+輸入!$C$114*$C$19)+輸入!$C$113*((1-輸入!$C$114)*((1-輸入!$C$115)*$C$28+輸入!$C$115*$C$29)+輸入!$C$114*$C$27))/1000 -> 6.0218128e-05 | D47: =(輸入!$C$111*((1-輸入!$C$114)*((1-輸入!$C$115)*$C$12+輸入!$C$115*$C$13)+輸入!$C$114*$C$11)+輸入!$C$112*((1-輸入!$C$114)*((1-輸入!$C$115)*$C$20+輸入!$C$115*$C$21)+輸入!$C$114*$C$19)+輸入!$C$113*((1-輸入!$C$114)*((1-輸入!$C$115)*$C$28+輸入!$C$115*$C$29)+輸入!$C$114*$C$27))/1000 -> 6.0218128e-05 | E47: =(輸入!$C$111*((1-輸入!$C$114)*((1-輸入!$C$115)*$C$12+輸入!$C$115*$C$13)+輸入!$C$114*$C$11)+輸入!$C$112*((1-輸入!$C$114)*((1-輸入!$C$115)*$C$20+輸入!$C$115*$C$21)+輸入!$C$114*$C$19)+輸入!$C$113*((1-輸入!$C$114)*((1-輸入!$C$115)*$C$28+輸入!$C$115*$C$29)+輸入!$C$114*$C$27))/1000 -> 6.0218128e-05 | F47: =(輸入!$C$111*((1-輸入!$C$114)*((1-輸入!$C$115)*$C$12+輸入!$C$115*$C$13)+輸入!$C$114*$C$11)+輸入!$C$112*((1-輸入!$C$114)*((1-輸入!$C$115)*$C$20+輸入!$C$115*$C$21)+輸入!$C$114*$C$19)+輸入!$C$113*((1-輸入!$C$114)*((1-輸入!$C$115)*$C$28+輸入!$C$115*$C$29)+輸入!$C$114*$C$27))/1000 -> 6.0218128e-05 | G47: =(輸入!$C$111*((1-輸入!$C$114)*((1-輸入!$C$115)*$C$12+輸入!$C$115*$C$13)+輸入!$C$114*$C$11)+輸入!$C$112*((1-輸入!$C$114)*((1-輸入!$C$115)*$C$20+輸入!$C$115*$C$21)+輸入!$C$114*$C$19)+輸入!$C$113*((1-輸入!$C$114)*((1-輸入!$C$115)*$C$28+輸入!$C$115*$C$29)+輸入!$C$114*$C$27))/1000 -> 6.0218128e-05 | H47: =(輸入!$C$111*((1-輸入!$C$114)*((1-輸入!$C$115)*$C$12+輸入!$C$115*$C$13)+輸入!$C$114*$C$11)+輸入!$C$112*((1-輸入!$C$114)*((1-輸入!$C$115)*$C$20+輸入!$C$115*$C$21)+輸入!$C$114*$C$19)+輸入!$C$113*((1-輸入!$C$114)*((1-輸入!$C$115)*$C$28+輸入!$C$115*$C$29)+輸入!$C$114*$C$27))/1000 -> 6.0218128e-05
A48: 企業席位 | B48: $B/T | C48: =(輸入!$C$116*((1-輸入!$C$119)*((1-輸入!$C$120)*$C$12+輸入!$C$120*$C$13)+輸入!$C$119*$C$11)+輸入!$C$117*((1-輸入!$C$119)*((1-輸入!$C$120)*$C$20+輸入!$C$120*$C$21)+輸入!$C$119*$C$19)+輸入!$C$118*((1-輸入!$C$119)*((1-輸入!$C$120)*$C$28+輸入!$C$120*$C$29)+輸入!$C$119*$C$27))/1000 -> 2.1760378e-05 | D48: =(輸入!$C$116*((1-輸入!$C$119)*((1-輸入!$C$120)*$C$12+輸入!$C$120*$C$13)+輸入!$C$119*$C$11)+輸入!$C$117*((1-輸入!$C$119)*((1-輸入!$C$120)*$C$20+輸入!$C$120*$C$21)+輸入!$C$119*$C$19)+輸入!$C$118*((1-輸入!$C$119)*((1-輸入!$C$120)*$C$28+輸入!$C$120*$C$29)+輸入!$C$119*$C$27))/1000 -> 2.1760378e-05 | E48: =(輸入!$C$116*((1-輸入!$C$119)*((1-輸入!$C$120)*$C$12+輸入!$C$120*$C$13)+輸入!$C$119*$C$11)+輸入!$C$117*((1-輸入!$C$119)*((1-輸入!$C$120)*$C$20+輸入!$C$120*$C$21)+輸入!$C$119*$C$19)+輸入!$C$118*((1-輸入!$C$119)*((1-輸入!$C$120)*$C$28+輸入!$C$120*$C$29)+輸入!$C$119*$C$27))/1000 -> 2.1760378e-05 | F48: =(輸入!$C$116*((1-輸入!$C$119)*((1-輸入!$C$120)*$C$12+輸入!$C$120*$C$13)+輸入!$C$119*$C$11)+輸入!$C$117*((1-輸入!$C$119)*((1-輸入!$C$120)*$C$20+輸入!$C$120*$C$21)+輸入!$C$119*$C$19)+輸入!$C$118*((1-輸入!$C$119)*((1-輸入!$C$120)*$C$28+輸入!$C$120*$C$29)+輸入!$C$119*$C$27))/1000 -> 2.1760378e-05 | G48: =(輸入!$C$116*((1-輸入!$C$119)*((1-輸入!$C$120)*$C$12+輸入!$C$120*$C$13)+輸入!$C$119*$C$11)+輸入!$C$117*((1-輸入!$C$119)*((1-輸入!$C$120)*$C$20+輸入!$C$120*$C$21)+輸入!$C$119*$C$19)+輸入!$C$118*((1-輸入!$C$119)*((1-輸入!$C$120)*$C$28+輸入!$C$120*$C$29)+輸入!$C$119*$C$27))/1000 -> 2.1760378e-05 | H48: =(輸入!$C$116*((1-輸入!$C$119)*((1-輸入!$C$120)*$C$12+輸入!$C$120*$C$13)+輸入!$C$119*$C$11)+輸入!$C$117*((1-輸入!$C$119)*((1-輸入!$C$120)*$C$20+輸入!$C$120*$C$21)+輸入!$C$119*$C$19)+輸入!$C$118*((1-輸入!$C$119)*((1-輸入!$C$120)*$C$28+輸入!$C$120*$C$29)+輸入!$C$119*$C$27))/1000 -> 2.1760378e-05
A49: API top（astra） | B49: $B/T | C49: =((1-輸入!$C$40)*((1-輸入!$C$41)*$C$28+輸入!$C$41*$C$29)+輸入!$C$40*$C$27)/1000 -> 5.1732661e-05 | D49: =((1-輸入!$C$40)*((1-輸入!$C$41)*$C$28+輸入!$C$41*$C$29)+輸入!$C$40*$C$27)/1000 -> 5.1732661e-05 | E49: =((1-輸入!$C$40)*((1-輸入!$C$41)*$C$28+輸入!$C$41*$C$29)+輸入!$C$40*$C$27)/1000 -> 5.1732661e-05 | F49: =((1-輸入!$C$40)*((1-輸入!$C$41)*$C$28+輸入!$C$41*$C$29)+輸入!$C$40*$C$27)/1000 -> 5.1732661e-05 | G49: =((1-輸入!$C$40)*((1-輸入!$C$41)*$C$28+輸入!$C$41*$C$29)+輸入!$C$40*$C$27)/1000 -> 5.1732661e-05 | H49: =((1-輸入!$C$40)*((1-輸入!$C$41)*$C$28+輸入!$C$41*$C$29)+輸入!$C$40*$C$27)/1000 -> 5.1732661e-05
A50: API mid（sol） | B50: $B/T | C50: =((1-輸入!$C$40)*((1-輸入!$C$41)*$C$20+輸入!$C$41*$C$21)+輸入!$C$40*$C$19)/1000 -> 1.6093286e-05 | D50: =((1-輸入!$C$40)*((1-輸入!$C$41)*$C$20+輸入!$C$41*$C$21)+輸入!$C$40*$C$19)/1000 -> 1.6093286e-05 | E50: =((1-輸入!$C$40)*((1-輸入!$C$41)*$C$20+輸入!$C$41*$C$21)+輸入!$C$40*$C$19)/1000 -> 1.6093286e-05 | F50: =((1-輸入!$C$40)*((1-輸入!$C$41)*$C$20+輸入!$C$41*$C$21)+輸入!$C$40*$C$19)/1000 -> 1.6093286e-05 | G50: =((1-輸入!$C$40)*((1-輸入!$C$41)*$C$20+輸入!$C$41*$C$21)+輸入!$C$40*$C$19)/1000 -> 1.6093286e-05 | H50: =((1-輸入!$C$40)*((1-輸入!$C$41)*$C$20+輸入!$C$41*$C$21)+輸入!$C$40*$C$19)/1000 -> 1.6093286e-05
A51: API low（luna） | B51: $B/T | C51: =((1-輸入!$C$40)*((1-輸入!$C$41)*$C$12+輸入!$C$41*$C$13)+輸入!$C$40*$C$11)/1000 -> 3.2205652e-06 | D51: =((1-輸入!$C$40)*((1-輸入!$C$41)*$C$12+輸入!$C$41*$C$13)+輸入!$C$40*$C$11)/1000 -> 3.2205652e-06 | E51: =((1-輸入!$C$40)*((1-輸入!$C$41)*$C$12+輸入!$C$41*$C$13)+輸入!$C$40*$C$11)/1000 -> 3.2205652e-06 | F51: =((1-輸入!$C$40)*((1-輸入!$C$41)*$C$12+輸入!$C$41*$C$13)+輸入!$C$40*$C$11)/1000 -> 3.2205652e-06 | G51: =((1-輸入!$C$40)*((1-輸入!$C$41)*$C$12+輸入!$C$41*$C$13)+輸入!$C$40*$C$11)/1000 -> 3.2205652e-06 | H51: =((1-輸入!$C$40)*((1-輸入!$C$41)*$C$12+輸入!$C$41*$C$13)+輸入!$C$40*$C$11)/1000 -> 3.2205652e-06
A52: API 加權（依當年層級組合） | B52: $B/T | C52: =API!C15*C49+API!C16*C50+API!C17*C51 -> 2.7774492e-05 | D52: =API!D15*D49+API!D16*D50+API!D17*D51 -> 1.6290104e-05 | E52: =API!E15*E49+API!E16*E50+API!E17*E51 -> 1.6290104e-05 | F52: =API!F15*F49+API!F16*F50+API!F17*F51 -> 1.6290104e-05 | G52: =API!G15*G49+API!G16*G50+API!G17*G51 -> 1.6290104e-05 | H52: =API!H15*H49+API!H16*H50+API!H17*H51 -> 1.6290104e-05
A53: 三、FY2025 校準（T1a 推論 $8.4B＝非付費 $3.9B＋付費 $4.5B；T5 API 毛利率先驗）
A54: 校準係數 κ（實際 ÷ 理想） | B54: x | C54: =(1-輸入!$C$125)*API!C25/(C52*API!C24) -> 35.465059 | J54: 吸收 2025 艦隊（H100/GB200）與 VR 理想值之差、冗餘、重試、安全分類器等
A55: 付費訂閱理想成本（未校正） | B55: $B | C55: =C45*訂閱與廣告!C32+C46*訂閱與廣告!C33+C47*訂閱與廣告!C34+C48*訂閱與廣告!C35 -> 0.019329136
A56: workbook token 校正倍數 k（訂閱＋Free） | B56: x | C56: =(輸入!$C$124-(1-輸入!$C$125)*API!C25)/(C54*C55) -> 3.9197153 | J56: k≠1 表示 workbook 的每日任務數×每任務 token 與成本分拆不一致；待查核
A57: Free 文字推論成本 2025 | B57: $B | C57: =C54*C56*C44*訂閱與廣告!C31 -> 0.57624935
A58: Free 殘差 2025（非文字生成＋Free 特有 token 低估；無法分離） | B58: $B | C58: =輸入!$C$123-C57 -> 3.3237506 | J58: 負值表示文字推論已超過報導之免費層成本
A59: 列在營業成本以外之推論（推論 − 營業成本） | B59: $B | C59: =輸入!$C$122-輸入!$C$12 -> 0.9 | J59: T1a：$8.4B 與外流財報 $7.5B 之差
A60: Luna：2025 實際輸出 token 成本（κ 後） | B60: $/M | C60: =C11*C54 -> 0.41925945
A61: Sol：2025 實際輸出 token 成本（κ 後） | B61: $/M | C61: =C19*C54 -> 2.2814712
A62: Astra：2025 實際輸出 token 成本（κ 後） | B62: $/M | C62: =C27*C54 -> 7.0712725
A63: 四、推論成本（$B）＝理想量 × 每單位理想量成本（＝每 VR-eq GW 成本 × ρ）；分層列為需求口徑
A64: 每單位理想量實際成本 | B64: x | C64: =算力MW!C42*算力MW!$C$29 -> 35.465059 | D64: =算力MW!D42*算力MW!$C$29 -> 18.152116 | E64: =算力MW!E42*算力MW!$C$29 -> 13.021253 | F64: =算力MW!F42*算力MW!$C$29 -> 9.9016189 | G64: =算力MW!G42*算力MW!$C$29 -> 8.5143896 | H64: =算力MW!H42*算力MW!$C$29 -> 7.4549594 | J64: 2025 等於校準係數 κ
A65: Free（文字） | B65: $B | C65: =C64*$C$56*C44*訂閱與廣告!C31 -> 0.57624935 | D65: =D64*$C$56*D44*訂閱與廣告!D31 -> 0.68647813 | E65: =E64*$C$56*E44*訂閱與廣告!E31 -> 0.81965133 | F65: =F64*$C$56*F44*訂閱與廣告!F31 -> 0.94613773 | G65: =G64*$C$56*G44*訂閱與廣告!G31 -> 1.1664063 | H65: =H64*$C$56*H44*訂閱與廣告!H31 -> 1.4059017
A66: Go（文字） | B66: $B | C66: =C64*$C$56*C45*訂閱與廣告!C32 -> 0.010269026 | D66: =D64*$C$56*D45*訂閱與廣告!D32 -> 0.16791678 | E66: =E64*$C$56*E45*訂閱與廣告!E32 -> 0.29066539 | F66: =F64*$C$56*F45*訂閱與廣告!F32 -> 0.42240598 | G66: =G64*$C$56*G45*訂閱與廣告!G32 -> 0.57911964 | H66: =H64*$C$56*H45*訂閱與廣告!H32 -> 0.77289353
A67: Plus（文字） | B67: $B | C67: =C64*$C$56*C46*訂閱與廣告!C33 -> 1.9085951 | D67: =D64*$C$56*D46*訂閱與廣告!D33 -> 2.3340378 | E67: =E64*$C$56*E46*訂閱與廣告!E33 -> 2.3942497 | F67: =F64*$C$56*F46*訂閱與廣告!F33 -> 2.5245555 | G67: =G64*$C$56*G46*訂閱與廣告!G33 -> 2.9388521 | H67: =H64*$C$56*H46*訂閱與廣告!H33 -> 3.415153
A68: Pro（文字） | B68: $B | C68: =C64*$C$56*C47*訂閱與廣告!C34 -> 0.62636747 | D68: =D64*$C$56*D47*訂閱與廣告!D34 -> 1.2539771 | E68: =E64*$C$56*E47*訂閱與廣告!E34 -> 1.7068561 | F68: =F64*$C$56*F47*訂閱與廣告!F34 -> 2.1891706 | G68: =G64*$C$56*G47*訂閱與廣告!G34 -> 2.9766479 | H68: =H64*$C$56*H47*訂閱與廣告!H34 -> 3.9563162
A69: 企業席位（文字） | B69: $B | C69: =C64*$C$56*C48*訂閱與廣告!C35 -> 0.14176844 | D69: =D64*$C$56*D48*訂閱與廣告!D35 -> 0.67203456 | E69: =E64*$C$56*E48*訂閱與廣告!E35 -> 1.1325385 | F69: =F64*$C$56*F48*訂閱與廣告!F35 -> 1.592235 | G69: =G64*$C$56*G48*訂閱與廣告!G35 -> 2.187775 | H69: =H64*$C$56*H48*訂閱與廣告!H35 -> 2.8270385
A70: Free 殘差（非文字等） | B70: $B | C70: =C64*算力MW!C26 -> 3.3237506 | D70: =D64*算力MW!D26 -> 2.6935643 | E70: =E64*算力MW!E26 -> 2.542373 | F70: =F64*算力MW!F26 -> 2.3199251 | G70: =G64*算力MW!G26 -> 2.2608874 | H70: =H64*算力MW!H26 -> 2.1542371
A71: API top | B71: $B | C71: =C64*C49*API!C28 -> 1.3507547 | D71: =D64*D49*API!D28 -> 0.72800007 | E71: =E64*E49*API!E28 -> 1.3559726 | F71: =F64*F49*API!F28 -> 2.4133667 | G71: =G64*G49*API!G28 -> 4.3909965 | H71: =H64*H49*API!H28 -> 7.6223032
A72: API mid | B72: $B | C72: =C64*C50*API!C30 -> 0.42020035 | D72: =D64*D50*API!D30 -> 0.67941104 | E72: =E64*E50*API!E30 -> 1.2654707 | F72: =F64*F50*API!F30 -> 2.252291 | G72: =G64*G50*API!G30 -> 4.0979275 | H72: =H64*H50*API!H30 -> 7.1135666
A73: API low | B73: $B | C73: =C64*C51*API!C32 -> 0.042044943 | D73: =D64*D51*API!D32 -> 0.12085578 | E73: =E64*E51*API!E32 -> 0.22510593 | F73: =F64*F51*API!F32 -> 0.40064463 | G73: =G64*G51*API!G32 -> 0.72895229 | H73: =H64*H51*API!H32 -> 1.2653837
A74: API 合計 | B74: $B | C74: =C71+C72+C73 -> 1.813 | D74: =D71+D72+D73 -> 1.5282669 | E74: =E71+E72+E73 -> 2.8465493 | F74: =F71+F72+F73 -> 5.0663023 | G74: =G71+G72+G73 -> 9.2178764 | H74: =H71+H72+H73 -> 16.001253
A75: 非付費用戶合計（Free 文字＋殘差） | B75: $B | C75: =C65+C70 -> 3.9 | D75: =D65+D70 -> 3.3800425 | E75: =E65+E70 -> 3.3620244 | F75: =F65+F70 -> 3.2660628 | G75: =G65+G70 -> 3.4272937 | H75: =H65+H70 -> 3.5601388
A76: 付費用戶合計 | B76: $B | C76: =C66+C67+C68+C69+C74 -> 4.5 | D76: =D66+D67+D68+D69+D74 -> 5.9562332 | E76: =E66+E67+E68+E69+E74 -> 8.3708589 | F76: =F66+F67+F68+F69+F74 -> 11.794669 | G76: =G66+G67+G68+G69+G74 -> 17.900271 | H76: =H66+H67+H68+H69+H74 -> 26.972655
A77: 推論成本合計（需求口徑） | B77: $B | C77: =C75+C76 -> 8.4 | D77: =D75+D76 -> 9.3362756 | E77: =E75+E76 -> 11.732883 | F77: =F75+F76 -> 15.060732 | G77: =G75+G76 -> 21.327565 | H77: =H75+H76 -> 30.532794
A78: 推論成本合計（容量上限後＝算力MW 頁） | B78: $B | C78: =算力MW!C44 -> 8.4 | D78: =算力MW!D44 -> 9.3362756 | E78: =算力MW!E44 -> 11.732883 | F78: =算力MW!F44 -> 15.060732 | G78: =算力MW!G44 -> 21.327565 | H78: =算力MW!H44 -> 30.532794
A79: 付費占比 | B79: % | C79: =C76/C77 -> 0.53571429 | D79: =D76/D77 -> 0.63796672 | E79: =E76/E77 -> 0.71345284 | F79: =F76/F77 -> 0.7831405 | G79: =G76/G77 -> 0.83930215 | H79: =H76/H77 -> 0.88339951 | J79: OpenAI 預測 2026 為 66%、2030 為 94%
A80: 五、各層級毛利率（營收 − 推論成本；需求口徑，容量上限對營收與成本同比例，不影響毛利率）
A81: Go | B81: % | C81: =IFERROR(1-C66/訂閱與廣告!C14,0) -> 0.92868732 | D81: =IFERROR(1-D66/訂閱與廣告!D14,0) -> 0.94255721 | E81: =IFERROR(1-E66/訂閱與廣告!E14,0) -> 0.94787434 | F81: =IFERROR(1-F66/訂閱與廣告!F14,0) -> 0.9498587 | G81: =IFERROR(1-G66/訂閱與廣告!G14,0) -> 0.94545771 | H81: =IFERROR(1-H66/訂閱與廣告!H14,0) -> 0.93958905
A82: Plus | B82: % | C82: =IFERROR(1-C67/訂閱與廣告!C15,0) -> 0.72812036 | D82: =IFERROR(1-D67/訂閱與廣告!D15,0) -> 0.70667599 | E82: =IFERROR(1-E67/訂閱與廣告!E15,0) -> 0.73382721 | F82: =IFERROR(1-F67/訂閱與廣告!F15,0) -> 0.74396012 | G82: =IFERROR(1-G67/訂閱與廣告!G15,0) -> 0.72148701 | H82: =IFERROR(1-H67/訂閱與廣告!H15,0) -> 0.69151948
A83: Pro | B83: % | C83: =IFERROR(1-C68/訂閱與廣告!C16,0) -> 0.47802711 | D83: =IFERROR(1-D68/訂閱與廣告!D16,0) -> 0.30334604 | E83: =IFERROR(1-E68/訂閱與廣告!E16,0) -> 0.36783107 | F83: =IFERROR(1-F68/訂閱與廣告!F16,0) -> 0.39189705 | G83: =IFERROR(1-G68/訂閱與廣告!G16,0) -> 0.33852269 | H83: =IFERROR(1-H68/訂閱與廣告!H16,0) -> 0.26734885
A84: 企業席位 | B84: % | C84: =IFERROR(1-C69/訂閱與廣告!C17,0) -> 0.86873293 | D84: =IFERROR(1-D69/訂閱與廣告!D17,0) -> 0.86665981 | E84: =IFERROR(1-E69/訂閱與廣告!E17,0) -> 0.8790023 | F84: =IFERROR(1-F69/訂閱與廣告!F17,0) -> 0.88360855 | G84: =IFERROR(1-G69/訂閱與廣告!G17,0) -> 0.87339265 | H84: =IFERROR(1-H69/訂閱與廣告!H17,0) -> 0.85976991
A85: API top | B85: % | C85: =IFERROR(1-C71/API!C27,0) -> 0.39806369 | D85: =IFERROR(1-D71/API!D27,0) -> 0.88054409 | E85: =IFERROR(1-E71/API!E27,0) -> 0.87758487 | F85: =IFERROR(1-F71/API!F27,0) -> 0.86701872 | G85: =IFERROR(1-G71/API!G27,0) -> 0.83664223 | H85: =IFERROR(1-H71/API!H27,0) -> 0.79566935
A86: API mid | B86: % | C86: =IFERROR(1-C72/API!C29,0) -> 0.67659261 | D86: =IFERROR(1-D72/API!D29,0) -> 0.89786219 | E86: =IFERROR(1-E72/API!E29,0) -> 0.87788731 | F86: =IFERROR(1-F72/API!F29,0) -> 0.84523848 | G86: =IFERROR(1-G72/API!G29,0) -> 0.77820128 | H86: =IFERROR(1-H72/API!H29,0) -> 0.67633216
A87: API low | B87: % | C87: =IFERROR(1-C73/API!C31,0) -> 0.491553 | D87: =IFERROR(1-D73/API!D31,0) -> 0.92867661 | E87: =IFERROR(1-E73/API!E31,0) -> 0.91472804 | F87: =IFERROR(1-F73/API!F31,0) -> 0.89192919 | G87: =IFERROR(1-G73/API!G31,0) -> 0.84511674 | H87: =IFERROR(1-H73/API!H31,0) -> 0.77398098
A88: API 合計 | B88: % | C88: =1-C74/API!C25 -> 0.5 | D88: =1-D74/API!D25 -> 0.89416933 | E88: =1-E74/API!E25 -> 0.88178701 | F88: =1-F74/API!F25 -> 0.86084917 | G88: =1-G74/API!G25 -> 0.81587071 | H88: =1-H74/API!H25 -> 0.75337279
A89: 廣告營收 ÷ 非付費用戶推論成本 | B89: x | C89: =IFERROR(訂閱與廣告!C48/C75,0) -> 0 | D89: =IFERROR(訂閱與廣告!D48/D75,0) -> 0.21980493 | E89: =IFERROR(訂閱與廣告!E48/E75,0) -> 0.55277022 | F89: =IFERROR(訂閱與廣告!F48/F75,0) -> 0.89116714 | G89: =IFERROR(訂閱與廣告!G48/G75,0) -> 1.2128539 | H89: =IFERROR(訂閱與廣告!H48/H75,0) -> 1.5662752
A90: 六、含訓練分攤之全成本毛利率（參考；訓練依各層級推論成本占比分攤）
A91: 訓練 ÷ 推論 | B91: x | C91: =算力MW!C45/算力MW!C44 -> 1.4285714 | D91: =算力MW!D45/算力MW!D44 -> 2.2043368 | E91: =算力MW!E45/算力MW!E44 -> 7.9004256 | F91: =算力MW!F45/算力MW!F44 -> 7.4242817 | G91: =算力MW!G45/算力MW!G44 -> 6.137698 | H91: =算力MW!H45/算力MW!H44 -> 4.647215
A92: Go | B92: % | C92: =IFERROR(1-C66*(1+C91)/訂閱與廣告!C14,0) -> 0.82681207 | D92: =IFERROR(1-D66*(1+D91)/訂閱與廣告!D14,0) -> 0.81593394 | E92: =IFERROR(1-E66*(1+E91)/訂閱與廣告!E14,0) -> 0.53605941 | F92: =IFERROR(1-F66*(1+F91)/訂閱與廣告!F14,0) -> 0.57759559 | G92: =IFERROR(1-G66*(1+G91)/訂閱與廣告!G14,0) -> 0.61069358 | H92: =IFERROR(1-H66*(1+H91)/訂閱與廣告!H14,0) -> 0.65884636
A93: Plus | B93: % | C93: =IFERROR(1-C67*(1+C91)/訂閱與廣告!C15,0) -> 0.33972087 | D93: =IFERROR(1-D67*(1+D91)/訂閱與廣告!D15,0) -> 0.06009108 | E93: =IFERROR(1-E67*(1+E91)/訂閱與廣告!E15,0) -> -1.3690511 | F93: =IFERROR(1-F67*(1+F91)/訂閱與廣告!F15,0) -> -1.1569521 | G93: =IFERROR(1-G67*(1+G91)/訂閱與廣告!G15,0) -> -0.98794162 | H93: =IFERROR(1-H67*(1+H91)/訂閱與廣告!H15,0) -> -0.74205584
A94: Pro | B94: % | C94: =IFERROR(1-C68*(1+C91)/訂閱與廣告!C16,0) -> -0.26764845 | D94: =IFERROR(1-D68*(1+D91)/訂閱與廣告!D16,0) -> -1.2323139 | E94: =IFERROR(1-E68*(1+E91)/訂閱與廣告!E16,0) -> -4.6265725 | F94: =IFERROR(1-F68*(1+F91)/訂閱與廣告!F16,0) -> -4.1228305 | G94: =IFERROR(1-G68*(1+G91)/訂閱與廣告!G16,0) -> -3.7214252 | H94: =IFERROR(1-H68*(1+H91)/訂閱與廣告!H16,0) -> -3.1374386
A95: 企業席位 | B95: % | C95: =IFERROR(1-C69*(1+C91)/訂閱與廣告!C17,0) -> 0.68120854 | D95: =IFERROR(1-D69*(1+D91)/訂閱與廣告!D17,0) -> 0.57273313 | E95: =IFERROR(1-E69*(1+E91)/訂閱與廣告!E17,0) -> -0.076931004 | F95: =IFERROR(1-F69*(1+F91)/訂閱與廣告!F17,0) -> 0.019485654 | G95: =IFERROR(1-G69*(1+G91)/訂閱與廣告!G17,0) -> 0.096314989 | H95: =IFERROR(1-H69*(1+H91)/訂閱與廣告!H17,0) -> 0.20809055
A96: API 合計 | B96: % | C96: =1-C74*(1+C91)/API!C25 -> -0.21428571 | D96: =1-D74*(1+D91)/API!D25 -> 0.66088291 | E96: =1-E74*(1+E91)/API!E25 -> -0.052145879 | F96: =1-F74*(1+F91)/API!F25 -> -0.17224576 | G96: =1-G74*(1+G91)/API!G25 -> -0.31425923 | H96: =1-H74*(1+H91)/API!H25 -> -0.3927569

Sheet 訓練成本
A1: 訓練成本（$B）＝訓練 VR-eq GW × 每 VR-eq GW 成本；列在研發費用、不入營業成本；計畫值僅作檢查
A3: 項目 | B3: 單位 | C3: 2025 | D3: 2026 | E3: 2027 | F3: 2028 | G3: 2029 | H3: 2030 | I3: 2026–30 合計 | J3: 說明
A4: 訓練 GW（VR-eq） | B4: GW | C4: =算力MW!C34 -> 0.22126354 | D4: =算力MW!D34 -> 0.74140184 | E4: =算力MW!E34 -> 4.6551296 | F4: =算力MW!F34 -> 7.384543 | G4: =算力MW!G34 -> 10.053622 | H4: =算力MW!H34 -> 12.446388
A5: 每 VR-eq GW 年成本 | B5: $B/GW | C5: =算力MW!C42 -> 54.233969 | D5: =算力MW!D42 -> 27.758625 | E5: =算力MW!E42 -> 19.912393 | F5: =算力MW!F42 -> 15.141779 | G5: =算力MW!G42 -> 13.020397 | H5: =算力MW!H42 -> 11.400292
A6: 訓練成本 | B6: $B | C6: =算力MW!C45 -> 12 | D6: =算力MW!D45 -> 20.580296 | E6: =算力MW!E45 -> 92.694771 | F6: =算力MW!F45 -> 111.81512 | G6: =算力MW!G45 -> 130.90215 | H6: =算力MW!H45 -> 141.89246 | I6: =SUM(D6:H6) -> 497.88479 | J6: 2025 由校準等於輸入值（$12B）
A7: 檢查：公司計畫口徑（計畫算力 − 計畫推論）
A8: 計畫推論成本 | B8: $B | C8: =輸入!$C$122 -> 8.4 | D8: =輸入!$C$126*(輸入!$C$128/輸入!$C$126)^((D$3-2026)/4) -> 14.1 | E8: =輸入!$C$126*(輸入!$C$128/輸入!$C$126)^((E$3-2026)/4) -> 22.093731 | F8: =輸入!$C$126*(輸入!$C$128/輸入!$C$126)^((F$3-2026)/4) -> 34.619359 | G8: =輸入!$C$126*(輸入!$C$128/輸入!$C$126)^((G$3-2026)/4) -> 54.246156 | H8: =輸入!$C$126*(輸入!$C$128/輸入!$C$126)^((H$3-2026)/4) -> 85 | I8: =SUM(D8:H8) -> 210.05925 | J8: 2025 實際；2026、2030 為公司預測，2027–29 幾何內插
A9: 計畫訓練總額 2026–30（計畫算力 − 計畫推論） | B9: $B | C9: =輸入!$C$134-I8 -> 645.94075
A10: 本模型訓練 2026–30 ÷ 計畫訓練 | C10: =I6/C9 -> 0.77079019
A11: 比率
A12: 訓練 ÷ 推論 | B12: x | C12: =算力MW!C45/算力MW!C44 -> 1.4285714 | D12: =算力MW!D45/算力MW!D44 -> 2.2043368 | E12: =算力MW!E45/算力MW!E44 -> 7.9004256 | F12: =算力MW!F45/算力MW!F44 -> 7.4242817 | G12: =算力MW!G45/算力MW!G44 -> 6.137698 | H12: =算力MW!H45/算力MW!H44 -> 4.647215
A13: 訓練 ÷ 總額營收 | B13: % | C13: =C6/營收彙總!C22 -> 0.91813313 | D13: =D6/營收彙總!D22 -> 0.62546427 | E13: =E6/營收彙總!E22 -> 1.763277 | F13: =F6/營收彙總!F22 -> 1.4931848 | G13: =G6/營收彙總!G22 -> 1.3471661 | H13: =H6/營收彙總!H22 -> 1.1836079
A14: 訓練占 VR-eq 供給 | B14: % | C14: =算力MW!C34/算力MW!C22 -> 0.58823529 | D14: =算力MW!D34/算力MW!D22 -> 0.61913065 | E14: =算力MW!E34/算力MW!E22 -> 0.79888124 | F14: =算力MW!F34/算力MW!F22 -> 0.79316597 | G14: =算力MW!G34/算力MW!G22 -> 0.77390893 | H14: =算力MW!H34/算力MW!H22 -> 0.74062941 | J14: 參考：2024 訓練 $3B、推論 $1.8B（Epoch）
A15: 訓練 ÷ 研發費用總額（2025） | B15: % | C15: =C6/輸入!$C$133 -> 0.62565172

Sheet 反向
A1: 反向模式：假設管理層目標達成，反解充分條件（廣告取正向值，R3）
A3: 項目 | B3: 單位 | C3: 2025 | D3: 2026 | E3: 2027 | F3: 2028 | G3: 2029 | H3: 2030 | J3: 說明
A4: 管理層營收目標 | B4: $B | C4: =輸入!C$158 -> 13.07 | D4: =輸入!D$158 -> 36 | E4: =輸入!E$158 -> 75.1 | F4: =輸入!F$158 -> 141.5 | G4: =輸入!G$158 -> 237.4 | H4: =輸入!H$158 -> 350 | J4: 2027–29 為依五年累計 $840B 擬合 [Derived]
A5: 正向總額 | B5: $B | C5: =營收彙總!C22 -> 13.07 | D5: =營收彙總!D22 -> 32.904031 | E5: =營收彙總!E22 -> 52.569602 | F5: =營收彙總!F22 -> 74.883641 | G5: =營收彙總!G22 -> 97.168533 | H5: =營收彙總!H22 -> 119.8813
A6: 差距（目標−正向） | B6: $B | C6: =C4-C5 -> 0 | D6: =D4-D5 -> 3.0959689 | E6: =E4-E5 -> 22.530398 | F6: =F4-F5 -> 66.616359 | G6: =G4-G5 -> 140.23147 | H6: =H4-H5 -> 230.1187
A7: 核心需求（目標−正向廣告） | B7: $B | C7: =C4-營收彙總!C21 -> 13.07 | D7: =D4-營收彙總!D21 -> 35.25705 | E7: =E4-營收彙總!E21 -> 73.241573 | F7: =F4-營收彙總!F21 -> 138.58939 | G7: =G4-營收彙總!G21 -> 233.24319 | H7: =H4-營收彙總!H21 -> 344.42384
A8: 充分條件組（R2）：所需倍數（相對正向）
A9: 只靠 API | B9: x | C9: =(C7-營收彙總!C18)/營收彙總!C19 -> 1 | D9: =(D7-營收彙總!D18)/營收彙總!D19 -> 1.2143922 | E9: =(E7-營收彙總!E18)/營收彙總!E19 -> 1.9356541 | F9: =(F7-營收彙總!F18)/營收彙總!F19 -> 2.8296818 | G9: =(G7-營收彙總!G18)/營收彙總!G19 -> 3.8011571 | H9: =(H7-營收彙總!H18)/營收彙總!H19 -> 4.546818
A10: 只靠訂閱 | B10: x | C10: =(C7-營收彙總!C19)/營收彙總!C18 -> 1 | D10: =(D7-營收彙總!D19)/營收彙總!D18 -> 1.1747121 | E10: =(E7-營收彙總!E19)/營收彙總!E18 -> 1.8460107 | F10: =(F7-營收彙總!F19)/營收彙總!F18 -> 2.8731233 | G10: =(G7-營收彙總!G19)/營收彙總!G18 -> 4.2650126 | H10: =(H7-營收彙總!H19)/營收彙總!H18 -> 5.6559343
A11: 兩線等比例 | B11: x | C11: =C7/營收彙總!C20 -> 1 | D11: =D7/營收彙總!D20 -> 1.0962645 | E11: =E7/營收彙總!E20 -> 1.4442886 | F11: =F7/營收彙總!F20 -> 1.9255739 | G11: =G7/營收彙總!G20 -> 2.5076751 | H11: =H7/營收彙總!H20 -> 3.0131964
A12: 對照：廣告取內部路徑時之等比例倍數 | B12: x | C12: =(C4-輸入!C$159)/營收彙總!C20 -> 1 | D12: =(D4-輸入!D$159)/營收彙總!D20 -> 1.0416317 | E12: =(E4-輸入!E$159)/營收彙總!E20 -> 1.2640212 | F12: =(F4-輸入!F$159)/營收彙總!F20 -> 1.6186618 | G12: =(G4-輸入!G$159)/營收彙總!G20 -> 1.9825457 | H12: =(H4-輸入!H$159)/營收彙總!H20 -> 2.1871282
A13: 2030 換算為可觀測量
A14: 正向付費用戶（Go＋Plus＋Pro＋席位） | B14: M | H14: =訂閱與廣告!H8+訂閱與廣告!H9+訂閱與廣告!H10+訂閱與廣告!H11 -> 285.25
A15: 正向混合 ARPU | B15: $/月 | H15: =營收彙總!H18*1000/12/H14 -> 14.439035
A16: 只靠訂閱：所需付費用戶（同 ARPU） | B16: M | H16: =(H7-營收彙總!H19)*1000/12/H15 -> 1613.3553
A17: 正向 API 計費 token | B17: T | H17: =API!H24 -> 131760.39
A18: 只靠 API：所需計費 token（同單價路徑） | B18: T | H18: =(H7-營收彙總!H18)/API!H18*1000 -> 599090.5
A20: 橋接 2030（示意；簡報營收組成未揭露，順序不同則各項不同）
A21: 正向總額 | B21: $B | H21: =營收彙總!H22 -> 119.8813
A22: ＋廣告由正向提高至內部路徑 | B22: $B | H22: =輸入!$H$159-營收彙總!H21 -> 94.423843
A23: ＋用戶提高至計畫（訂閱等比放大） | B23: $B | H23: =營收彙總!H18*(輸入!$C$160/(訂閱與廣告!H7+訂閱與廣告!H8+訂閱與廣告!H9+訂閱與廣告!H10+訂閱與廣告!H11)-1) -> 14.229672
A24: ＋核心殘差 | B24: $B | H24: =H4-SUM(H21:H23) -> 121.46519
A25: ＝管理層目標 | B25: $B | H25: =SUM(H21:H24) -> 350
A26: 核心殘差折算：API 所需倍數 | B26: x | H26: =(營收彙總!H19+H24)/營收彙總!H19 -> 2.8721421
A27: 廣告步驟占差距比例 | B27: % | H27: =H22/(H4-H21) -> 0.41032668
A28: 廣告內部路徑占管理層 2030 目標 | B28: % | H28: =輸入!$H$159/H4 -> 0.28571429

Sheet 支出
A1: 支出（$B，名目、現金口徑）：合約付款＋自有資本支出＋營運費用
A3: 項目 | B3: 單位 | C3: 2025 | D3: 2026 | E3: 2027 | F3: 2028 | G3: 2029 | H3: 2030 | I3: 2026–30 合計 | J3: 2030 年後剩餘
A4: 交易對手合約付款（已揭露依年額；未揭露依輸入頁付款型態）
A5: Microsoft Azure | B5: $B | C5: =IF(AND(C$3>=輸入!$D$164,C$3<=輸入!$E$164),IF(輸入!$F$164<>"",輸入!$F$164,IF(輸入!$C$6="even",輸入!$C$164/(輸入!$E$164-輸入!$D$164+1),輸入!$C$164*(C$3-輸入!$D$164+1)/((輸入!$E$164-輸入!$D$164+1)*((輸入!$E$164-輸入!$D$164+1)+1)/2))),0) -> 11.904762 | D5: =IF(AND(D$3>=輸入!$D$164,D$3<=輸入!$E$164),IF(輸入!$F$164<>"",輸入!$F$164,IF(輸入!$C$6="even",輸入!$C$164/(輸入!$E$164-輸入!$D$164+1),輸入!$C$164*(D$3-輸入!$D$164+1)/((輸入!$E$164-輸入!$D$164+1)*((輸入!$E$164-輸入!$D$164+1)+1)/2))),0) -> 23.809524 | E5: =IF(AND(E$3>=輸入!$D$164,E$3<=輸入!$E$164),IF(輸入!$F$164<>"",輸入!$F$164,IF(輸入!$C$6="even",輸入!$C$164/(輸入!$E$164-輸入!$D$164+1),輸入!$C$164*(E$3-輸入!$D$164+1)/((輸入!$E$164-輸入!$D$164+1)*((輸入!$E$164-輸入!$D$164+1)+1)/2))),0) -> 35.714286 | F5: =IF(AND(F$3>=輸入!$D$164,F$3<=輸入!$E$164),IF(輸入!$F$164<>"",輸入!$F$164,IF(輸入!$C$6="even",輸入!$C$164/(輸入!$E$164-輸入!$D$164+1),輸入!$C$164*(F$3-輸入!$D$164+1)/((輸入!$E$164-輸入!$D$164+1)*((輸入!$E$164-輸入!$D$164+1)+1)/2))),0) -> 47.619048 | G5: =IF(AND(G$3>=輸入!$D$164,G$3<=輸入!$E$164),IF(輸入!$F$164<>"",輸入!$F$164,IF(輸入!$C$6="even",輸入!$C$164/(輸入!$E$164-輸入!$D$164+1),輸入!$C$164*(G$3-輸入!$D$164+1)/((輸入!$E$164-輸入!$D$164+1)*((輸入!$E$164-輸入!$D$164+1)+1)/2))),0) -> 59.52381 | H5: =IF(AND(H$3>=輸入!$D$164,H$3<=輸入!$E$164),IF(輸入!$F$164<>"",輸入!$F$164,IF(輸入!$C$6="even",輸入!$C$164/(輸入!$E$164-輸入!$D$164+1),輸入!$C$164*(H$3-輸入!$D$164+1)/((輸入!$E$164-輸入!$D$164+1)*((輸入!$E$164-輸入!$D$164+1)+1)/2))),0) -> 71.428571 | I5: =SUM(D5:H5) -> 238.09524 | J5: =輸入!$C$164-SUM(C5:H5) -> 0
A6: Oracle | B6: $B | C6: =IF(AND(C$3>=輸入!$D$165,C$3<=輸入!$E$165),IF(輸入!$F$165<>"",輸入!$F$165,IF(輸入!$C$6="even",輸入!$C$165/(輸入!$E$165-輸入!$D$165+1),輸入!$C$165*(C$3-輸入!$D$165+1)/((輸入!$E$165-輸入!$D$165+1)*((輸入!$E$165-輸入!$D$165+1)+1)/2))),0) -> 0 | D6: =IF(AND(D$3>=輸入!$D$165,D$3<=輸入!$E$165),IF(輸入!$F$165<>"",輸入!$F$165,IF(輸入!$C$6="even",輸入!$C$165/(輸入!$E$165-輸入!$D$165+1),輸入!$C$165*(D$3-輸入!$D$165+1)/((輸入!$E$165-輸入!$D$165+1)*((輸入!$E$165-輸入!$D$165+1)+1)/2))),0) -> 0 | E6: =IF(AND(E$3>=輸入!$D$165,E$3<=輸入!$E$165),IF(輸入!$F$165<>"",輸入!$F$165,IF(輸入!$C$6="even",輸入!$C$165/(輸入!$E$165-輸入!$D$165+1),輸入!$C$165*(E$3-輸入!$D$165+1)/((輸入!$E$165-輸入!$D$165+1)*((輸入!$E$165-輸入!$D$165+1)+1)/2))),0) -> 60 | F6: =IF(AND(F$3>=輸入!$D$165,F$3<=輸入!$E$165),IF(輸入!$F$165<>"",輸入!$F$165,IF(輸入!$C$6="even",輸入!$C$165/(輸入!$E$165-輸入!$D$165+1),輸入!$C$165*(F$3-輸入!$D$165+1)/((輸入!$E$165-輸入!$D$165+1)*((輸入!$E$165-輸入!$D$165+1)+1)/2))),0) -> 60 | G6: =IF(AND(G$3>=輸入!$D$165,G$3<=輸入!$E$165),IF(輸入!$F$165<>"",輸入!$F$165,IF(輸入!$C$6="even",輸入!$C$165/(輸入!$E$165-輸入!$D$165+1),輸入!$C$165*(G$3-輸入!$D$165+1)/((輸入!$E$165-輸入!$D$165+1)*((輸入!$E$165-輸入!$D$165+1)+1)/2))),0) -> 60 | H6: =IF(AND(H$3>=輸入!$D$165,H$3<=輸入!$E$165),IF(輸入!$F$165<>"",輸入!$F$165,IF(輸入!$C$6="even",輸入!$C$165/(輸入!$E$165-輸入!$D$165+1),輸入!$C$165*(H$3-輸入!$D$165+1)/((輸入!$E$165-輸入!$D$165+1)*((輸入!$E$165-輸入!$D$165+1)+1)/2))),0) -> 60 | I6: =SUM(D6:H6) -> 240 | J6: =輸入!$C$165-SUM(C6:H6) -> 60
A7: AWS（Nvidia GPU） | B7: $B | C7: =IF(AND(C$3>=輸入!$D$166,C$3<=輸入!$E$166),IF(輸入!$F$166<>"",輸入!$F$166,IF(輸入!$C$6="even",輸入!$C$166/(輸入!$E$166-輸入!$D$166+1),輸入!$C$166*(C$3-輸入!$D$166+1)/((輸入!$E$166-輸入!$D$166+1)*((輸入!$E$166-輸入!$D$166+1)+1)/2))),0) -> 1.3571429 | D7: =IF(AND(D$3>=輸入!$D$166,D$3<=輸入!$E$166),IF(輸入!$F$166<>"",輸入!$F$166,IF(輸入!$C$6="even",輸入!$C$166/(輸入!$E$166-輸入!$D$166+1),輸入!$C$166*(D$3-輸入!$D$166+1)/((輸入!$E$166-輸入!$D$166+1)*((輸入!$E$166-輸入!$D$166+1)+1)/2))),0) -> 2.7142857 | E7: =IF(AND(E$3>=輸入!$D$166,E$3<=輸入!$E$166),IF(輸入!$F$166<>"",輸入!$F$166,IF(輸入!$C$6="even",輸入!$C$166/(輸入!$E$166-輸入!$D$166+1),輸入!$C$166*(E$3-輸入!$D$166+1)/((輸入!$E$166-輸入!$D$166+1)*((輸入!$E$166-輸入!$D$166+1)+1)/2))),0) -> 4.0714286 | F7: =IF(AND(F$3>=輸入!$D$166,F$3<=輸入!$E$166),IF(輸入!$F$166<>"",輸入!$F$166,IF(輸入!$C$6="even",輸入!$C$166/(輸入!$E$166-輸入!$D$166+1),輸入!$C$166*(F$3-輸入!$D$166+1)/((輸入!$E$166-輸入!$D$166+1)*((輸入!$E$166-輸入!$D$166+1)+1)/2))),0) -> 5.4285714 | G7: =IF(AND(G$3>=輸入!$D$166,G$3<=輸入!$E$166),IF(輸入!$F$166<>"",輸入!$F$166,IF(輸入!$C$6="even",輸入!$C$166/(輸入!$E$166-輸入!$D$166+1),輸入!$C$166*(G$3-輸入!$D$166+1)/((輸入!$E$166-輸入!$D$166+1)*((輸入!$E$166-輸入!$D$166+1)+1)/2))),0) -> 6.7857143 | H7: =IF(AND(H$3>=輸入!$D$166,H$3<=輸入!$E$166),IF(輸入!$F$166<>"",輸入!$F$166,IF(輸入!$C$6="even",輸入!$C$166/(輸入!$E$166-輸入!$D$166+1),輸入!$C$166*(H$3-輸入!$D$166+1)/((輸入!$E$166-輸入!$D$166+1)*((輸入!$E$166-輸入!$D$166+1)+1)/2))),0) -> 8.1428571 | I7: =SUM(D7:H7) -> 27.142857 | J7: =輸入!$C$166-SUM(C7:H7) -> 9.5
A8: AWS 擴約（Trainium／VR） | B8: $B | C8: =IF(AND(C$3>=輸入!$D$167,C$3<=輸入!$E$167),IF(輸入!$F$167<>"",輸入!$F$167,IF(輸入!$C$6="even",輸入!$C$167/(輸入!$E$167-輸入!$D$167+1),輸入!$C$167*(C$3-輸入!$D$167+1)/((輸入!$E$167-輸入!$D$167+1)*((輸入!$E$167-輸入!$D$167+1)+1)/2))),0) -> 0 | D8: =IF(AND(D$3>=輸入!$D$167,D$3<=輸入!$E$167),IF(輸入!$F$167<>"",輸入!$F$167,IF(輸入!$C$6="even",輸入!$C$167/(輸入!$E$167-輸入!$D$167+1),輸入!$C$167*(D$3-輸入!$D$167+1)/((輸入!$E$167-輸入!$D$167+1)*((輸入!$E$167-輸入!$D$167+1)+1)/2))),0) -> 2.7777778 | E8: =IF(AND(E$3>=輸入!$D$167,E$3<=輸入!$E$167),IF(輸入!$F$167<>"",輸入!$F$167,IF(輸入!$C$6="even",輸入!$C$167/(輸入!$E$167-輸入!$D$167+1),輸入!$C$167*(E$3-輸入!$D$167+1)/((輸入!$E$167-輸入!$D$167+1)*((輸入!$E$167-輸入!$D$167+1)+1)/2))),0) -> 5.5555556 | F8: =IF(AND(F$3>=輸入!$D$167,F$3<=輸入!$E$167),IF(輸入!$F$167<>"",輸入!$F$167,IF(輸入!$C$6="even",輸入!$C$167/(輸入!$E$167-輸入!$D$167+1),輸入!$C$167*(F$3-輸入!$D$167+1)/((輸入!$E$167-輸入!$D$167+1)*((輸入!$E$167-輸入!$D$167+1)+1)/2))),0) -> 8.3333333 | G8: =IF(AND(G$3>=輸入!$D$167,G$3<=輸入!$E$167),IF(輸入!$F$167<>"",輸入!$F$167,IF(輸入!$C$6="even",輸入!$C$167/(輸入!$E$167-輸入!$D$167+1),輸入!$C$167*(G$3-輸入!$D$167+1)/((輸入!$E$167-輸入!$D$167+1)*((輸入!$E$167-輸入!$D$167+1)+1)/2))),0) -> 11.111111 | H8: =IF(AND(H$3>=輸入!$D$167,H$3<=輸入!$E$167),IF(輸入!$F$167<>"",輸入!$F$167,IF(輸入!$C$6="even",輸入!$C$167/(輸入!$E$167-輸入!$D$167+1),輸入!$C$167*(H$3-輸入!$D$167+1)/((輸入!$E$167-輸入!$D$167+1)*((輸入!$E$167-輸入!$D$167+1)+1)/2))),0) -> 13.888889 | I8: =SUM(D8:H8) -> 41.666667 | J8: =輸入!$C$167-SUM(C8:H8) -> 58.333333
A9: CoreWeave | B9: $B | C9: =IF(AND(C$3>=輸入!$D$168,C$3<=輸入!$E$168),IF(輸入!$F$168<>"",輸入!$F$168,IF(輸入!$C$6="even",輸入!$C$168/(輸入!$E$168-輸入!$D$168+1),輸入!$C$168*(C$3-輸入!$D$168+1)/((輸入!$E$168-輸入!$D$168+1)*((輸入!$E$168-輸入!$D$168+1)+1)/2))),0) -> 1.4933333 | D9: =IF(AND(D$3>=輸入!$D$168,D$3<=輸入!$E$168),IF(輸入!$F$168<>"",輸入!$F$168,IF(輸入!$C$6="even",輸入!$C$168/(輸入!$E$168-輸入!$D$168+1),輸入!$C$168*(D$3-輸入!$D$168+1)/((輸入!$E$168-輸入!$D$168+1)*((輸入!$E$168-輸入!$D$168+1)+1)/2))),0) -> 2.9866667 | E9: =IF(AND(E$3>=輸入!$D$168,E$3<=輸入!$E$168),IF(輸入!$F$168<>"",輸入!$F$168,IF(輸入!$C$6="even",輸入!$C$168/(輸入!$E$168-輸入!$D$168+1),輸入!$C$168*(E$3-輸入!$D$168+1)/((輸入!$E$168-輸入!$D$168+1)*((輸入!$E$168-輸入!$D$168+1)+1)/2))),0) -> 4.48 | F9: =IF(AND(F$3>=輸入!$D$168,F$3<=輸入!$E$168),IF(輸入!$F$168<>"",輸入!$F$168,IF(輸入!$C$6="even",輸入!$C$168/(輸入!$E$168-輸入!$D$168+1),輸入!$C$168*(F$3-輸入!$D$168+1)/((輸入!$E$168-輸入!$D$168+1)*((輸入!$E$168-輸入!$D$168+1)+1)/2))),0) -> 5.9733333 | G9: =IF(AND(G$3>=輸入!$D$168,G$3<=輸入!$E$168),IF(輸入!$F$168<>"",輸入!$F$168,IF(輸入!$C$6="even",輸入!$C$168/(輸入!$E$168-輸入!$D$168+1),輸入!$C$168*(G$3-輸入!$D$168+1)/((輸入!$E$168-輸入!$D$168+1)*((輸入!$E$168-輸入!$D$168+1)+1)/2))),0) -> 7.4666667 | H9: =IF(AND(H$3>=輸入!$D$168,H$3<=輸入!$E$168),IF(輸入!$F$168<>"",輸入!$F$168,IF(輸入!$C$6="even",輸入!$C$168/(輸入!$E$168-輸入!$D$168+1),輸入!$C$168*(H$3-輸入!$D$168+1)/((輸入!$E$168-輸入!$D$168+1)*((輸入!$E$168-輸入!$D$168+1)+1)/2))),0) -> 0 | I9: =SUM(D9:H9) -> 20.906667 | J9: =輸入!$C$168-SUM(C9:H9) -> 0
A10: Cerebras | B10: $B | C10: =IF(AND(C$3>=輸入!$D$169,C$3<=輸入!$E$169),IF(輸入!$F$169<>"",輸入!$F$169,IF(輸入!$C$6="even",輸入!$C$169/(輸入!$E$169-輸入!$D$169+1),輸入!$C$169*(C$3-輸入!$D$169+1)/((輸入!$E$169-輸入!$D$169+1)*((輸入!$E$169-輸入!$D$169+1)+1)/2))),0) -> 0 | D10: =IF(AND(D$3>=輸入!$D$169,D$3<=輸入!$E$169),IF(輸入!$F$169<>"",輸入!$F$169,IF(輸入!$C$6="even",輸入!$C$169/(輸入!$E$169-輸入!$D$169+1),輸入!$C$169*(D$3-輸入!$D$169+1)/((輸入!$E$169-輸入!$D$169+1)*((輸入!$E$169-輸入!$D$169+1)+1)/2))),0) -> 0.95238095 | E10: =IF(AND(E$3>=輸入!$D$169,E$3<=輸入!$E$169),IF(輸入!$F$169<>"",輸入!$F$169,IF(輸入!$C$6="even",輸入!$C$169/(輸入!$E$169-輸入!$D$169+1),輸入!$C$169*(E$3-輸入!$D$169+1)/((輸入!$E$169-輸入!$D$169+1)*((輸入!$E$169-輸入!$D$169+1)+1)/2))),0) -> 1.9047619 | F10: =IF(AND(F$3>=輸入!$D$169,F$3<=輸入!$E$169),IF(輸入!$F$169<>"",輸入!$F$169,IF(輸入!$C$6="even",輸入!$C$169/(輸入!$E$169-輸入!$D$169+1),輸入!$C$169*(F$3-輸入!$D$169+1)/((輸入!$E$169-輸入!$D$169+1)*((輸入!$E$169-輸入!$D$169+1)+1)/2))),0) -> 2.8571429 | G10: =IF(AND(G$3>=輸入!$D$169,G$3<=輸入!$E$169),IF(輸入!$F$169<>"",輸入!$F$169,IF(輸入!$C$6="even",輸入!$C$169/(輸入!$E$169-輸入!$D$169+1),輸入!$C$169*(G$3-輸入!$D$169+1)/((輸入!$E$169-輸入!$D$169+1)*((輸入!$E$169-輸入!$D$169+1)+1)/2))),0) -> 3.8095238 | H10: =IF(AND(H$3>=輸入!$D$169,H$3<=輸入!$E$169),IF(輸入!$F$169<>"",輸入!$F$169,IF(輸入!$C$6="even",輸入!$C$169/(輸入!$E$169-輸入!$D$169+1),輸入!$C$169*(H$3-輸入!$D$169+1)/((輸入!$E$169-輸入!$D$169+1)*((輸入!$E$169-輸入!$D$169+1)+1)/2))),0) -> 4.7619048 | I10: =SUM(D10:H10) -> 14.285714 | J10: =輸入!$C$169-SUM(C10:H10) -> 5.7142857
A11: 合約付款合計 | B11: $B | C11: =SUM(C5:C10) -> 14.755238 | D11: =SUM(D5:D10) -> 33.240635 | E11: =SUM(E5:E10) -> 111.72603 | F11: =SUM(F5:F10) -> 130.21143 | G11: =SUM(G5:G10) -> 148.69683 | H11: =SUM(H5:H10) -> 158.22222 | I11: =SUM(I5:I10) -> 582.09714 | J11: =SUM(J5:J10) -> 133.54762
A12: 自有資本支出（扣合作方出資） | B12: $B | C12: =輸入!C$171*(1-輸入!$C$172) -> 0 | D12: =輸入!D$171*(1-輸入!$C$172) -> 20 | E12: =輸入!E$171*(1-輸入!$C$172) -> 30 | F12: =輸入!F$171*(1-輸入!$C$172) -> 45 | G12: =輸入!G$171*(1-輸入!$C$172) -> 60 | H12: =輸入!H$171*(1-輸入!$C$172) -> 70
A13: 租賃（未揭露） | B13: $B | C13: ="不適用" -> 不適用 | D13: ="不適用" -> 不適用 | E13: ="不適用" -> 不適用 | F13: ="不適用" -> 不適用 | G13: ="不適用" -> 不適用 | H13: ="不適用" -> 不適用
A14: 算力現金合計（由上而下） | B14: $B | C14: =C11+C12 -> 14.755238 | D14: =D11+D12 -> 53.240635 | E14: =E11+E12 -> 141.72603 | F14: =F11+F12 -> 175.21143 | G14: =G11+G12 -> 208.69683 | H14: =H11+H12 -> 228.22222 | I14: =SUM(D14:H14) -> 807.09714
A15: 算力口徑對照（S6c）
A16: 算力損益成本（依 MW 拆分；算力MW 頁回填）
A17: 推論成本（MW） | B17: $B | C17: =算力MW!C44 -> 8.4 | D17: =算力MW!D44 -> 9.3362756 | E17: =算力MW!E44 -> 11.732883 | F17: =算力MW!F44 -> 15.060732 | G17: =算力MW!G44 -> 21.327565 | H17: =算力MW!H44 -> 30.532794
A18: 訓練成本（MW） | B18: $B | C18: =算力MW!C45 -> 12 | D18: =算力MW!D45 -> 20.580296 | E18: =算力MW!E45 -> 92.694771 | F18: =算力MW!F45 -> 111.81512 | G18: =算力MW!G45 -> 130.90215 | H18: =算力MW!H45 -> 141.89246
A19: 閒置成本（MW） | B19: $B | C19: =算力MW!C46 -> 0 | D19: =算力MW!D46 -> 3.3240635 | E19: =算力MW!E46 -> 11.603073 | F19: =算力MW!F46 -> 14.097317 | G19: =算力MW!G46 -> 16.914413 | H19: =算力MW!H46 -> 19.158361
A20: 算力損益成本合計 | B20: $B | C20: =C17+C18+C19 -> 20.4 | D20: =D17+D18+D19 -> 33.240635 | E20: =E17+E18+E19 -> 116.03073 | F20: =F17+F18+F19 -> 140.97317 | G20: =G17+G18+G19 -> 169.14413 | H20: =H17+H18+H19 -> 191.58361
A21: 算力現金 − 算力損益成本（自建資本支出與折舊之時間差） | B21: $B | C21: =C14-C20 -> -5.6447619 | D21: =D14-D20 -> 20 | E21: =E14-E20 -> 25.695305 | F21: =F14-F20 -> 34.238261 | G21: =G14-G20 -> 39.552697 | H21: =H14-H20 -> 36.638611
A22: 營運費用（不含算力、股票薪酬）
A23: 正向 | B23: $B | C23: =營收彙總!C22*輸入!C$173 -> 15.89312 | D23: =營收彙總!D22*輸入!D$173 -> 10.85833 | E23: =營收彙總!E22*輸入!E$173 -> 13.930944 | F23: =營收彙總!F22*輸入!F$173 -> 16.474401 | G23: =營收彙總!G22*輸入!G$173 -> 17.490336 | H23: =營收彙總!H22*輸入!H$173 -> 16.783382
A24: 反向（隨目標營收） | B24: $B | C24: =反向!C4*輸入!C$173 -> 15.89312 | D24: =反向!D4*輸入!D$173 -> 11.88 | E24: =反向!E4*輸入!E$173 -> 19.9015 | F24: =反向!F4*輸入!F$173 -> 31.13 | G24: =反向!G4*輸入!G$173 -> 42.732 | H24: =反向!H4*輸入!H$173 -> 49

Sheet 資金與檢查
A1: 資金（$B）：年底現金低於最低現金之差額累計＝外部資金需求
A3: 項目 | B3: 單位 | C3: 2025 | D3: 2026 | E3: 2027 | F3: 2028 | G3: 2029 | H3: 2030 | I3: 2026–30 合計 | J3: 說明
A4: 正向模式
A5: 淨營收 | B5: $B | D5: =營收彙總!D25 -> 26.323225 | E5: =營收彙總!E25 -> 42.055681 | F5: =營收彙總!F25 -> 59.906913 | G5: =營收彙總!G25 -> 91.239988 | H5: =營收彙總!H25 -> 119.8813 | I5: =SUM(D5:H5) -> 339.40711
A6: − 合約付款 | B6: $B | D6: =-支出!D11 -> -33.240635 | E6: =-支出!E11 -> -111.72603 | F6: =-支出!F11 -> -130.21143 | G6: =-支出!G11 -> -148.69683 | H6: =-支出!H11 -> -158.22222 | I6: =SUM(D6:H6) -> -582.09714
A7: − 自有資本支出 | B7: $B | D7: =-支出!D12 -> -20 | E7: =-支出!E12 -> -30 | F7: =-支出!F12 -> -45 | G7: =-支出!G12 -> -60 | H7: =-支出!H12 -> -70 | I7: =SUM(D7:H7) -> -225
A8: − 營運費用 | B8: $B | D8: =-支出!D23 -> -10.85833 | E8: =-支出!E23 -> -13.930944 | F8: =-支出!F23 -> -16.474401 | G8: =-支出!G23 -> -17.490336 | H8: =-支出!H23 -> -16.783382 | I8: =SUM(D8:H8) -> -75.537394
A9: 自由現金流 | B9: $B | D9: =SUM(D5:D8) -> -37.77574 | E9: =SUM(E5:E8) -> -113.60129 | F9: =SUM(F5:F8) -> -131.77892 | G9: =SUM(G5:G8) -> -134.94717 | H9: =SUM(H5:H8) -> -125.12431 | I9: =SUM(D9:H9) -> -543.22743
A10: 股權流入 | B10: $B | D10: =輸入!$C$179+輸入!$C$7*輸入!$C$180 -> 87 | E10: =0 -> 0 | F10: =0 -> 0 | G10: =0 -> 0 | H10: =0 -> 0 | I10: =SUM(D10:H10) -> 87
A11: 期初現金 | B11: $B | D11: =輸入!$C$178 -> 40 | E11: =D14 -> 89.22426 | F11: =E14 -> 10 | G11: =F14 -> 10 | H11: =G14 -> 10
A12: 補足前年底現金 | B12: $B | D12: =D11+D9+D10 -> 89.22426 | E12: =E11+E9+E10 -> -24.377035 | F12: =F11+F9+F10 -> -121.77892 | G12: =G11+G9+G10 -> -124.94717 | H12: =H11+H9+H10 -> -115.12431
A13: 當年外部資金需求 | B13: $B | D13: =MAX(0,輸入!$C$181-D12) -> 0 | E13: =MAX(0,輸入!$C$181-E12) -> 34.377035 | F13: =MAX(0,輸入!$C$181-F12) -> 131.77892 | G13: =MAX(0,輸入!$C$181-G12) -> 134.94717 | H13: =MAX(0,輸入!$C$181-H12) -> 125.12431 | I13: =SUM(D13:H13) -> 426.22743
A14: 年底現金 | B14: $B | D14: =D12+D13 -> 89.22426 | E14: =E12+E13 -> 10 | F14: =F12+F13 -> 10 | G14: =G12+G13 -> 10 | H14: =H12+H13 -> 10
A15: 累計外部資金需求 | B15: $B | D15: =C15+D13 -> 0 | E15: =D15+E13 -> 34.377035 | F15: =E15+F13 -> 166.15595 | G15: =F15+G13 -> 301.10313 | H15: =G15+H13 -> 426.22743
A17: 反向模式：目標營收之 Microsoft 分潤（同上限規則）
A18: 分潤（目標營收） | B18: $B | C18: =輸入!$C$17*反向!C4 -> 2.614 | D18: =IF(D$3<輸入!$C$19,輸入!$C$17*反向!D4,IF(D$3>輸入!$C$20,0,MIN(輸入!$C$17*反向!D4,輸入!$C$18-C19))) -> 7.2 | E18: =IF(E$3<輸入!$C$19,輸入!$C$17*反向!E4,IF(E$3>輸入!$C$20,0,MIN(輸入!$C$17*反向!E4,輸入!$C$18-D19))) -> 15.02 | F18: =IF(F$3<輸入!$C$19,輸入!$C$17*反向!F4,IF(F$3>輸入!$C$20,0,MIN(輸入!$C$17*反向!F4,輸入!$C$18-E19))) -> 15.78 | G18: =IF(G$3<輸入!$C$19,輸入!$C$17*反向!G4,IF(G$3>輸入!$C$20,0,MIN(輸入!$C$17*反向!G4,輸入!$C$18-F19))) -> 0 | H18: =IF(H$3<輸入!$C$19,輸入!$C$17*反向!H4,IF(H$3>輸入!$C$20,0,MIN(輸入!$C$17*反向!H4,輸入!$C$18-G19))) -> 0
A19: 分潤累計 | B19: $B | C19: =0 -> 0 | D19: =C19+IF(D$3>=輸入!$C$19,D18,0) -> 7.2 | E19: =D19+IF(E$3>=輸入!$C$19,E18,0) -> 22.22 | F19: =E19+IF(F$3>=輸入!$C$19,F18,0) -> 38 | G19: =F19+IF(G$3>=輸入!$C$19,G18,0) -> 38 | H19: =G19+IF(H$3>=輸入!$C$19,H18,0) -> 38
A21: 反向模式（管理層目標營收＋同一支出）
A22: 淨營收 | B22: $B | D22: =反向!D4-D18 -> 28.8 | E22: =反向!E4-E18 -> 60.08 | F22: =反向!F4-F18 -> 125.72 | G22: =反向!G4-G18 -> 237.4 | H22: =反向!H4-H18 -> 350 | I22: =SUM(D22:H22) -> 802
A23: − 合約付款 | B23: $B | D23: =-支出!D11 -> -33.240635 | E23: =-支出!E11 -> -111.72603 | F23: =-支出!F11 -> -130.21143 | G23: =-支出!G11 -> -148.69683 | H23: =-支出!H11 -> -158.22222 | I23: =SUM(D23:H23) -> -582.09714
A24: − 自有資本支出 | B24: $B | D24: =-支出!D12 -> -20 | E24: =-支出!E12 -> -30 | F24: =-支出!F12 -> -45 | G24: =-支出!G12 -> -60 | H24: =-支出!H12 -> -70 | I24: =SUM(D24:H24) -> -225
A25: − 營運費用 | B25: $B | D25: =-支出!D24 -> -11.88 | E25: =-支出!E24 -> -19.9015 | F25: =-支出!F24 -> -31.13 | G25: =-支出!G24 -> -42.732 | H25: =-支出!H24 -> -49 | I25: =SUM(D25:H25) -> -154.6435
A26: 自由現金流 | B26: $B | D26: =SUM(D22:D25) -> -36.320635 | E26: =SUM(E22:E25) -> -101.54753 | F26: =SUM(F22:F25) -> -80.621429 | G26: =SUM(G22:G25) -> -14.028825 | H26: =SUM(H22:H25) -> 72.777778 | I26: =SUM(D26:H26) -> -159.74064
A27: 股權流入 | B27: $B | D27: =輸入!$C$179+輸入!$C$7*輸入!$C$180 -> 87 | E27: =0 -> 0 | F27: =0 -> 0 | G27: =0 -> 0 | H27: =0 -> 0 | I27: =SUM(D27:H27) -> 87
A28: 期初現金 | B28: $B | D28: =輸入!$C$178 -> 40 | E28: =D31 -> 90.679365 | F28: =E31 -> 10 | G28: =F31 -> 10 | H28: =G31 -> 10
A29: 補足前年底現金 | B29: $B | D29: =D28+D26+D27 -> 90.679365 | E29: =E28+E26+E27 -> -10.868167 | F29: =F28+F26+F27 -> -70.621429 | G29: =G28+G26+G27 -> -4.0288254 | H29: =H28+H26+H27 -> 82.777778
A30: 當年外部資金需求 | B30: $B | D30: =MAX(0,輸入!$C$181-D29) -> 0 | E30: =MAX(0,輸入!$C$181-E29) -> 20.868167 | F30: =MAX(0,輸入!$C$181-F29) -> 80.621429 | G30: =MAX(0,輸入!$C$181-G29) -> 14.028825 | H30: =MAX(0,輸入!$C$181-H29) -> 0 | I30: =SUM(D30:H30) -> 115.51842
A31: 年底現金 | B31: $B | D31: =D29+D30 -> 90.679365 | E31: =E29+E30 -> 10 | F31: =F29+F30 -> 10 | G31: =G29+G30 -> 10 | H31: =H29+H30 -> 82.777778
A32: 累計外部資金需求 | B32: $B | D32: =C32+D30 -> 0 | E32: =D32+E30 -> 20.868167 | F32: =E32+F30 -> 101.4896 | G32: =F32+G30 -> 115.51842 | H32: =G32+H30 -> 115.51842
A34: 反向模式與簡報累計自由現金流對帳
A35: 本模型反向 Σ自由現金流 2026–30 | C35: =I26 -> -159.74064
A36: 簡報 Σ自由現金流 2026–30 | C36: =輸入!$C$161 -> -278
A37: 差異（本模型−簡報） | C37: =C35-C36 -> 118.25936
A38: 其中：算力（簡報 856 − 本模型由上而下） | C38: =輸入!$C$175-支出!I14 -> 48.902857
A39: 其中：其餘（營運費用、分潤上限、口徑） | C39: =C37-C38 -> 69.3565
A41: 檢查（通過／未通過）
A42: FY2025 總額＝實際（≤0.1%） | C42: =IF(ABS(營收彙總!C22/輸入!$C$9-1)<=0.001,"通過","未通過") -> 通過
A43: 2025 API 計費比例 50–110% | C43: =IF(AND(API!C41>=0.5,API!C41<=1.1),"通過","未通過") -> 通過
A44: FY2026 總額落在獨立推估區間 | C44: =IF(AND(營收彙總!D22>=輸入!$C$14,營收彙總!D22<=輸入!$C$15),"通過","未通過") -> 通過
A45: 2026 下半年 ÷ 上半年 1.0–2.5 | C45: =IF(AND(營收彙總!D31>=1,營收彙總!D31<=2.5),"通過","未通過") -> 通過
A46: 企業端占總額 FY2026 介於 45–60% | C46: =IF(AND(營收彙總!D16>=0.45,營收彙總!D16<=0.6),"通過","未通過") -> 通過
A47: 消費端＋企業端＝總額 | C47: =IF(MAX(ABS(營收彙總!C28),ABS(營收彙總!H28))<0.001,"通過","未通過") -> 通過
A48: FY2025 推論合計＝校準值 8.4 | C48: =IF(ABS(推論成本!C78-輸入!$C$122)<0.01,"通過","未通過") -> 通過
A49: FY2025 API 毛利率＝先驗 | C49: =IF(ABS(推論成本!C88-輸入!$C$125)<0.001,"通過","未通過") -> 通過
A50: Free 殘差 ≥ 0 | C50: =IF(推論成本!C58>=0,"通過","未通過") -> 通過
A51: 2026 推論成本在預測 ±35% | C51: =IF(ABS(推論成本!D78/輸入!$C$126-1)<=0.35,"通過","未通過") -> 通過
A52: 2026 付費占推論 55–80% | C52: =IF(AND(推論成本!D79>=0.55,推論成本!D79<=0.8),"通過","未通過") -> 通過
A53: 2025 合約推得 GW 與實際平均 GW 差距 ≤35% | C53: =IF(ABS(算力MW!C12/算力MW!C13-1)<=0.35,"通過","未通過") -> 通過
A54: 推論＋訓練＋閒置 GW＝VR-eq 供給 | C54: =IF(MAX(ABS(算力MW!C36),ABS(算力MW!H36))<0.000001,"通過","未通過") -> 通過
A55: MW 成本拆分加總＝算力損益成本 | C55: =IF(MAX(ABS(算力MW!D47),ABS(算力MW!H47))<0.000001,"通過","未通過") -> 通過
A56: 容量上限未觸發（2026–30 係數＝1） | C56: =IF(MIN(算力MW!D32:H32)>=1,"通過","未通過") -> 通過
A57: 需求口徑推論成本 × 係數＝MW 推論成本 | C57: =IF(ABS(推論成本!H77*算力MW!H32-推論成本!H78)<0.000001,"通過","未通過") -> 通過
A58: 分潤累計 ≤ 上限 | C58: =IF(營收彙總!H24<=輸入!$C$18+0.0001,"通過","未通過") -> 通過
A59: API 歸因誤差 < 1e−9 | C59: =IF(MAX(ABS(API!D39),ABS(API!E39),ABS(API!F39),ABS(API!G39),ABS(API!H39))<0.000000001,"通過","未通過") -> 通過
A60: 2026 算力現金與證詞差距 ≤25% | C60: =IF(ABS(支出!D14/輸入!$C$176-1)<=0.25,"通過","未通過") -> 通過
A61: Σ算力 2026–30 介於 WSJ×0.9 與 FT×1.1 | C61: =IF(AND(支出!I14>=輸入!$C$174*0.9,支出!I14<=輸入!$C$175*1.1),"通過","未通過") -> 通過
A62: 廣告 2025＝0 | C62: =IF(營收彙總!C21=0,"通過","未通過") -> 通過
A63: 未通過項數 | C63: =COUNTIF(C42:C62,"未通過") -> 0
A65: 或有負債（只列示，不作資金來源）
A66: Nvidia 擔保 | C66: =輸入!$C$182 -> 250
A67: Nvidia 晶片融資（洽談中） | C67: =輸入!$C$183 -> 350
