Workbook

Sheet README
A1: 半導體設備市場模型 v0.1.2（AI 半導體 Project 步驟 5：設備與材料——設備部分） 2026-10-23
A2: 模型命題：設備需求＝為滿足記憶體、代工擴產所需的資本支出 × 設備占比；本模型回答核心問題 1——設備循環在 2027 還是 2028 見頂——並列出核心問題 2、3 的瓶頸表。公司份額與毛利留給公司層，v0.1 不做。
A4: 驅動因子 → 推導量
A5: In：公司資本支出（讀自 skhynix／micron／samsung／tsmc dist，不修改它們）、設備占資本支出比例（兩個來源給低／高）、SEMI 2026-07 分項、情境係數（Assumed）、AI 分類假設
A6: Mkt：2025 年 SK 海力士、三星設備占比以 SEMI 實績校準（Derived），其他記憶體廠 2025 基準＝獨立估計，代工邏輯其他廠＝SEMI 實績殘差；2026 起各廠資本支出 × 占比，其他廠基準 × 成長率（Assumed）；測試與封裝＝SEMI；三情境 A／B／C；AI 增量占比；見頂年度
A7: Recon：對 SEMI、Lam、KLA、Morgan Stanley、Goldman Sachs 的差距；不為對上而調參。Sens：占比、匯率、2025 資本支出、其他廠成長率與基準、情境係數
A9: 結果摘要（v0.1 建置時；見 Mkt 摘要區）
A10: 設備總額（$B）：A 2025–2029＝134.7／178.2／218.2／246.0／260.7（2029 仍增，未在區間內見頂）；B＝134.7／178.2／218.2／218.2／207.3（見頂 2028，與 2027 同水準）；C＝134.7／178.2／218.2／174.6／174.6（見頂 2027）。
A11: 校準（只用 2025 實績）：SK 海力士、三星共用一個設備占比 45.5%（Derived；低 38.5%＝長鑫取 12.0，高 58%＝業界下限），使 2025 年「三家設備＋其他記憶體廠獨立估計」＝SEMI 2025 DRAM＋NAND 實績（38.5）；2026 年以後沿用。美光維持由原文推導的占比（FY26 52.1%、FY27–29 46.0%）；台積電維持 64%（Analogy）。業界值 64% 不再當基準，Sens 保留對照列。
A12: 2026 年以後的前段設備完全沒有參照 SEMI 或券商預測：三家與台積電的資本支出 × 設備占比，加「其他廠＝2025 獨立估計（記憶體）或 SEMI 實績殘差（代工邏輯）× 成長率（Assumed）」；其他前段維持 2025 年占比。測試與封裝為 SEMI 輸入（v0.1 規格）。SEMI 2026 以後的 DRAM、NAND、代工邏輯、前段預測只用於對帳。
A13: AI 相關增量（先進邏輯＋DRAM／HBM＋先進封裝）占總增量（相對 2025 累計）：A 2026–2029＝63／63／61／60%；B 63／63／63／64%；C 63／63／72／72%。結論取決於情境係數（Assumed），不是預測。
A15: 限制
... A25: 瓶頸表（核心問題 2、3；v0.1 只做表，不入模）
A26: 瓶頸 | B26: 現況（v0.1 能找到的證據） | C26: 來源 | D26: 證據強度 | E26: 對本模型的含意
A27: 無塵室空間 | B27: 美光：FY27 資本支出『增量』一半以上為建築（FQ3 稿）、『增量』多數為建築且用於 2028 下半年後的無塵室（FQ4 法說）；KLA 稱客戶受廠房就緒度與廠房外殼限制，壓住 1H 出貨；SK 證券稱記憶體供給成長受無塵室限制至 2027；SK 海力士首座無塵室提前到 2027-02 | C27: Micron FQ3／FQ4 FY26 稿；Futurum（KLA FQ2 2026 摘要）；Cleanroom Technology（三星 P5） | D27: 強（美光一手）／中／弱 | E27: 解釋為何三家資本支出 × 設備占比可能超過 SEMI 記憶體總額；設備認列落後資本支出現金支出一至兩季，v0.1 未建模
A28: 長交期零組件 | B28: TrendForce：設備零組件（閥件管路、陶瓷、RF 電源、氣體箱）交期據報倍增、最長 40 個月；BigGo：日本關鍵零件最長 40 個月，沉積設備零組件由約 4 個月增至約 10 個月 | C28: TrendForce 2026-09-18；BigGo Finance | D28: 中（皆為「據報」）／弱；應用材料、Lam 的一手說法：未找到 | E28: 限制 2027–28 設備出貨上限，不改變需求面；若上限生效，情境 A 的 2028 可能偏高
A29: EUV | B29: ASML：2026 低 NA 產能約 65 台、2027 再增約 30%；2027、2028 需求超過供給（二手摘要）；各來源對 2027 台數不一致（56／80／約 85） | C29: ASML 2026 Q2 6-K；Pomegra、TechPowerUp、Tom's 類二手整理 | D29: 強（產能，一手）／弱（2027 台數與供不應求，二手） | E29: EUV 台數限制先進邏輯與 DRAM 的 2027–28 增量；v0.1 未建模
A30: 量測 | B30: KLA 稱 2026 先進封裝製程控制營收約 $1.1B；交期 18–24 個月僅見於社群貼文轉述 KLA 法說；「量測產能是瓶頸」本身的證據：未找到（搜尋 Onto、KLA 皆無交期或積壓一手數字） | C30: Zacks／TradingView；X（TheValueist）；Futurum | D30: 弱；瓶頸證據：未找到 | E30: 不影響 v0.1 數字；列為待查
A31: HBM 鍵合機 | B31: Hanmi 占 HBM TC 鍵合機營收 71.2%（TechInsights，2025 前三季）；SK 海力士 HBM4 約用 50 組 TC 鍵合機、約半數來自 ASMPT；預期約 100 台訂單（M15X 1b DRAM）；Hanmi 6 月接 SK 海力士約 15 台。供給短缺或交期：未找到 | C31: TrendForce 2025-12-12；The Elec；Techtimes 2026-06 | D31: 中（供應商集中度）；短缺：未找到 | E31: 鍵合機屬後段／封裝，v0.1 以 SEMI 金額為輸入，未建模
A33: 對帳差距說明
A34: 對帳差距 > 15% 的項目與可能原因（v0.1 建置時數值；2025 實績校準之外，2026 年以後完全沒有參照 SEMI 或券商的預測來設定參數）：
A35: (a) 2026 NAND +25.9%（模型 17.5 vs SEMI 13.9）：2025 年三家設備以 SEMI 2025 的 DRAM／NAND 比例（72.4／27.6）拆分，其他 NAND 廠（鎧俠、長江存儲）2025 獨立估計 3.9 $B 已占 SEMI 2025 NAND 10.6 的 37%，再乘 18% 成長；SEMI 2026 NAND 占比降到 26.4%。DRAM 僅 +1.5%，DRAM＋NAND 合計高 4.2 $B（+7.9%）。2025 年 DRAM／NAND 拆分本身就不準（模型 DRAM 26.4 vs SEMI 27.9、NAND 12.2 vs 10.6），合計則因校準而相等。
A36: (b) Goldman Sachs 2028 −22.9%（模型 A 216.6 vs 281）：GS 2027 年增約 +45%（150→218）、2028 +29%，分別高於 SEMI 的 +21.8%、+14.1%；GS 為最高的一組，可能納入不同口徑（KLA 口徑含先進封裝；廠務設備）、更激進的 DRAM／先進代工假設，且發布較晚（2026-08，SEMI 為 2026-07）。
A37: (c) 未超過 15% 的差距：本模型高於 SEMI（2026 前段 +8.5%、2027 +10.0%、2028 +8.3%），低於 Lam／Morgan Stanley／GS 的 2027–2028 數字（−3.6% 到 −11.6%），落在 KLA 190（+1.5%）附近。B、C 在 2028 的差距是情境設計的結果。
A38: (d) 校準：SK 海力士、三星共用一個設備占比（45.5%，區間 38.5–58%），使 2025 年各廠設備加總等於 SEMI 2025 DRAM＋NAND 實績。校準值低於業界下限 58%，表示 SK 海力士、三星的資本支出中建築與無塵室比重高於業界值，與美光「增量多數為建築」的方向一致（方向，不是證明）。校準的前提是其他記憶體廠 2025 獨立估計（8.6 $B，長鑫取 12.0 時校準值降到 38.5%）與三星記憶體資本支出假設（DS 47.5 兆 × 75%，區間 65–90%）。代工邏輯未比照辦理（台積電沒有類似美光的揭露、2025 殘差為正，維持 64%）；代工邏輯是否也有建築比重偏高的問題，待查。
A40: 標記：Verified、Interested-party、Analogy、Assumed、Derived；Analogy 與 Assumed 給區間。SemiAnalysis 未使用。本檔不含任何個人投資部位或個人先驗。

Sheet In
A1: In — 輸入（藍字＝本模型輸入；綠字＝讀自其他模型 dist 成品，不在此修改；基準欄 E）。金額：十億美元（公司資本支出另標幣別）
A2: 每個數字附兩個來源（來源1、來源2）；找不到第二來源者寫「未找到」。SemiAnalysis 未使用。標記：Verified／Interested-party／Analogy／Assumed／Derived；Analogy、Assumed 給低／高區間。
A3: 鍵 | B3: 項目 | C3: 單位 | D3: 低 | E3: 基準 | F3: 高 | G3: 標記 | H3: 來源1 | I3: 來源2／備註
A4: A. 公司資本支出（2026–2029 讀自 dist 成品，三情境相同；2025 為本模型自行輸入——其他模型不含 2025——用於求「其他廠」2025 基準）
A5: fx | B5: 美元兌韓元（2025 亦沿用，Assumed） | C5: KRW/USD | D5: 1350 | E5: 1420 | F5: 1500 | G5: Derived | H5: 讀自 skhynix 模型 In!fx（Q2 2026 營收 79.32 兆 ≈ US$55.2B → 約 1,437） | I5: 三星模型 In!fx 同值（「同 SK 海力士」）；獨立匯率來源：本模型未另查
A6: cap_sk_26 | B6: SK 海力士資本支出 2026 | C6: 兆韓元 | E6: 48.7 | G6: Interested-party | H6: 20261023_SK海力士模型_v0.4.xlsx／Y!C21 | I6: 模型 In 標記：Verified／Interested-party｜指引「40 兆後段」；共識 48.7｜第二來源：未找到（模型只引共識）
A7: cap_sk_27 | B7: SK 海力士資本支出 2027 | C7: 兆韓元 | E7: 62.3 | G7: Interested-party | H7: 20261023_SK海力士模型_v0.4.xlsx／Y!D21 | I7: 模型 In 標記：Interested-party｜MarketScreener 共識 62.3｜第二來源：未找到（模型只引共識）
A8: cap_sk_28 | B8: SK 海力士資本支出 2028 | C8: 兆韓元 | E8: 71.2 | G8: Interested-party | H8: 20261023_SK海力士模型_v0.4.xlsx／Y!E21 | I8: 模型 In 標記：Interested-party｜MarketScreener 共識 71.2｜第二來源：未找到（模型只引共識）
A9: cap_sk_29 | B9: SK 海力士資本支出 2029 | C9: 兆韓元 | E9: 75 | G9: Assumed | H9: 20261023_SK海力士模型_v0.4.xlsx／Y!F21 | I9: 模型 In 標記：Assumed｜龍仁 2–6 期｜第二來源：未找到
A10: cap_mu_26 | B10: 美光資本支出 FY2026（淨；以 FY≈日曆年） | C10: $B | E10: 27.367 | G10: Verified | H10: 20261023_美光模型_v0.3.xlsx／Y!C21 | I10: 模型 In 標記：Verified｜FY26 8-K（毛 30.7）｜美光 FY 於 8–9 月結束，以日曆年近似，未調整（誤差方向：FY 比日曆年早約 4 個月）
A11: cap_mu_27 | B11: 美光資本支出 FY2027（淨；以 FY≈日曆年） | C11: $B | E11: 55 | G11: Derived | H11: 20261023_美光模型_v0.3.xlsx／Y!D21 | I11: 模型 In 標記：Derived｜FQ1 約 11.5、上半年約 25、下半年更高（書面說明）｜美光 FY 於 8–9 月結束，以日曆年近似，未調整（誤差方向：FY 比日曆年早約 4 個月）
A12: cap_mu_28 | B12: 美光資本支出 FY2028（淨；以 FY≈日曆年） | C12: $B | E12: 60 | G12: Assumed | H12: 20261023_美光模型_v0.3.xlsx／Y!E21 | I12: 模型 In 標記：Assumed｜None｜美光 FY 於 8–9 月結束，以日曆年近似，未調整（誤差方向：FY 比日曆年早約 4 個月）
A13: cap_mu_29 | B13: 美光資本支出 FY2029（淨；以 FY≈日曆年） | C13: $B | E13: 60 | G13: Assumed | H13: 20261023_美光模型_v0.3.xlsx／Y!F21 | I13: 模型 In 標記：Assumed｜None｜美光 FY 於 8–9 月結束，以日曆年近似，未調整（誤差方向：FY 比日曆年早約 4 個月）
A14: cap_ss_26 | B14: 三星記憶體資本支出 2026（只取記憶體） | C14: 兆韓元 | E14: 52.5 | G14: Derived／Assumed | H14: 20261023_三星電子模型_v0.2.xlsx／Y!C21 | I14: 口徑（三星模型 In）：Derived／Assumed｜全公司約 70（首爾經濟日報）× 記憶體約 75%（Assumed）；全公司×記憶體約 75% 為 Assumed；第二來源：未找到
A15: cap_ss_27 | B15: 三星記憶體資本支出 2027（只取記憶體） | C15: 兆韓元 | E15: 60 | G15: Assumed | H15: 20261023_三星電子模型_v0.2.xlsx／Y!D21 | I15: 口徑（三星模型 In）：Assumed｜P5 主體工程（>80 兆，多年）；全公司×記憶體約 75% 為 Assumed；第二來源：未找到
A16: cap_ss_28 | B16: 三星記憶體資本支出 2028（只取記憶體） | C16: 兆韓元 | E16: 66 | G16: Assumed | H16: 20261023_三星電子模型_v0.2.xlsx／Y!E21 | I16: 口徑（三星模型 In）：Assumed｜None；全公司×記憶體約 75% 為 Assumed；第二來源：未找到
A17: cap_ss_29 | B17: 三星記憶體資本支出 2029（只取記憶體） | C17: 兆韓元 | E17: 66 | G17: Assumed | H17: 20261023_三星電子模型_v0.2.xlsx／Y!F21 | I17: 口徑（三星模型 In）：Assumed｜None；全公司×記憶體約 75% 為 Assumed；第二來源：未找到
... A21: cap_ts_29 | B21: 台積電資本支出 2029 | C21: $B | E21: 95 | G21: Assumed | H21: 20261022_台積電模型_v0.2.xlsx／PL!E15 | I21: 模型 In 標記：Assumed｜None
A22: cap_sk_25 | B22: SK 海力士資本支出 2025 | C22: 兆韓元 | D22: 28 | E22: 30.2 | F22: 30.2 | G22: Interested-party | H22: Qz 2026-07-29（公司在 2Q26 法說稱 2026 預算相較 2025 的 30.2 兆韓元）https://qz.com/sk-hynix-q2-2026-earnings-record-profit-misses-estimates-072926 | I22: MLQ https://mlq.ai/news/sk-hynix-posts-record-605-trillion-won-operating-profit-raises-capacity-spending/ 同為 2Q26 法說摘要；另有產業估計約 28 兆（X：Jukan，低 28）。皆為搜尋摘要，未開啟原文
A23: cap_mu_25 | B23: 美光資本支出 FY2025（淨） | C23: $B | E23: 13.8 | G23: Verified | H23: 美光 FY25 8-K（淨 13.80）https://www.sec.gov/Archives/edgar/data/723125/000072312525000024/a2025q4ex991-pressrelease.htm | I23: 美光 FY25 10-K（毛 15.86、政府補助 2.01）https://www.sec.gov/Archives/edgar/data/723125/000072312525000028/mu-20250828.htm
A24: cap_ssds_25 | B24: 三星 DS（半導體）資本支出 2025 | C24: 兆韓元 | E24: 47.5 | G24: Verified | H24: 三星 IR：FY2025 CAPEX Results（DS 47.5、顯示 2.8、合計約 52.7）https://www.samsung.com/global/ir/reports-disclosures/public-disclosure-view.84547/ | I24: Korea Herald 合計 52.7 兆（https://koreaherald.com/article/10691933）；DS 47.5 另見 tech-insider（低權威）
A25: ss_mem | B25: 三星 DS 資本支出中記憶體占比（2025） | C25: % | D25: 0.65 | E25: 0.75 | F25: 0.9 | G25: Assumed | H25: 沿用三星模型 In（全公司 × 記憶體約 75%，Assumed）；三星不揭露記憶體分項。區間上修到 90%：2025 年三星晶圓代工投資據報減半至約 5 兆韓元（2024 約 10 兆；Sedaily 轉引，https://www.trendforce.com/news/2025/01/22/news-samsung-faces-struggles-ahead-as-foundry-investment-reportedly-slashed-by-half-for-2025/；https://www.digitimes.com/news/a20250122PD229/samsung-capex-business-plant-investment.html），記憶體占比較可能高於 75% | I25: 未找到記憶體分項的第二來源。算術參考（非來源）：DS 47.5 兆扣除晶圓代工約 5 兆、LSI 未知，記憶體約 85–89%；基準按指示維持 75%。此假設直接影響 2025 三大廠資本支出
A26: cap_ts_25 | B26: 台積電資本支出 2025 | C26: $B | D26: 40 | E26: 40.9 | F26: 42 | G26: Interested-party | H26: Semiconductor Intelligence：台積電 2025 資本支出 40.9B https://www.semiconductorintelligence.com/capex-up-for-foundry-memory/ | I26: 台積電 3Q25 法說：全年指引 40–42B（https://www.fool.com/earnings/call-transcripts/2025/10/17/tsmc-tsm-q3-2025-earnings-call-transcript）
A27: B. 設備占資本支出比例：按公司分開（公司有揭露建築與設備比例者用公司揭露；未找到者用業界 58–70%，Analogy）
A28: sh_mu_25 | B28: 美光：FY25 設備占資本支出比例（建築基數的起點） | C28: % | D28: 0.58 | E28: 0.64 | F28: 0.7 | G28: Analogy | H28: SEMI 2025 WFE 116.9B（年中預測新聞稿）÷ Semiconductor Intelligence 2025 全球半導體資本支出 166B（https://www.semiconductorintelligence.com/capex-up-for-foundry-memory/）＝70.4% → 高 70% | I28: Rebound Capital（Substack）資本支出→晶圓前段設備轉換率約 58%（https://reboundcapital.substack.com/p/industry-deep-dive-semiconductor）→ 低 58%；基準取兩者中點 64%。業界合計值，未找到記憶體／代工分項。美光未揭露 FY25 建築／設備比例
A29: sh_mu_26 | B29: 美光：FY26 設備占資本支出比例 | C29: % | D29: 0.471 | E29: 0.521 | F29: 0.571 | G29: Derived | H29: FQ3 FY26 準備稿（https://s25.q4cdn.com/621799436/files/doc_financials/2026/q3/Q3-FY26-Prepared-Remarks.pdf）：「more than half the increase year over year in fiscal 2027 from construction capex as we pull in cleanroom capacity required to address long-term demand」（引自搜尋摘要，未能開啟全文）｜FQ4 FY26 法說（https://s25.q4cdn.com/621799436/files/doc_financials/2026/q4/Q4-FY26-Prepared-Remarks.pdf；逐字稿 https://www.fool.com/earnings/call-transcripts/2026/10/01/micron-mu-q4-2026-earnings-call-transcript/）：「A majority of the increase is for construction capex, most of which is to help accelerate clean room space availability in late calendar 2028 and beyond」「a meaningfully higher growth rate in construction CapEx as compared to equipment CapEx in fiscal 2027」（引自搜尋摘要）｜FY26 增量多數為無塵室建築（摘要轉述，非逐字） | I29: 注意：公司原文是「資本支出『增量』多數為建築」，不是「FY27 資本支出多數為建築」，故文稿本身不給出設備占比，只給出下限性的建築比例。推導：FY25 淨資本支出 13.80（8-K）× (1−64%) ＝建築基數；之後每年增量中建築占 c（c＝50%「多於一半」為上限情境，60%、70% 為 Assumed 區間）；FY26＝27.37、FY27＝55（美光模型）。FY28–FY29 無揭露，沿用 FY27。 引文為公司一手（Verified），比例為 Derived（FY25 基準 64% 為 Analogy、c 為 Assumed）
A30: sh_mu_27 | B30: 美光：FY27–FY29 設備占資本支出比例 | C30: % | D30: 0.385 | E30: 0.46 | F30: 0.535 | G30: Derived | H30: FQ3 FY26 準備稿（https://s25.q4cdn.com/621799436/files/doc_financials/2026/q3/Q3-FY26-Prepared-Remarks.pdf）：「more than half the increase year over year in fiscal 2027 from construction capex as we pull in cleanroom capacity required to address long-term demand」（引自搜尋摘要，未能開啟全文）；FQ4 FY26 法說（https://s25.q4cdn.com/621799436/files/doc_financials/2026/q4/Q4-FY26-Prepared-Remarks.pdf；逐字稿 https://www.fool.com/earnings/call-transcripts/2026/10/01/micron-mu-q4-2026-earnings-call-transcript/）：「A majority of the increase is for construction capex, most of which is to help accelerate clean room space availability in late calendar 2028 and beyond」「a meaningfully higher growth rate in construction CapEx as compared to equipment CapEx in fiscal 2027」（引自搜尋摘要） | I30: 注意：公司原文是「資本支出『增量』多數為建築」，不是「FY27 資本支出多數為建築」，故文稿本身不給出設備占比，只給出下限性的建築比例。推導：FY25 淨資本支出 13.80（8-K）× (1−64%) ＝建築基數；之後每年增量中建築占 c（c＝50%「多於一半」為上限情境，60%、70% 為 Assumed 區間）；FY26＝27.37、FY27＝55（美光模型）。FY28–FY29 無揭露，沿用 FY27。 高＝c 取 50%（「多於一半」）時的推導上限，約 53%。引文為公司一手（Verified），比例為 Derived
A31: sh_sk | B31: SK 海力士：設備占資本支出比例（2025 實績校準值） | C31: % | D31: =Mkt!$C$79 -> 0.38504085 | E31: =Mkt!$C$78 -> 0.455453 | F31: =Mkt!$C$80 -> 0.58 | G31: Derived | H31: Mkt 頁公式：令 2025 年「SK＋三星＋美光設備＋其他廠獨立估計」＝SEMI 2025 DRAM＋NAND 實績（38.5），解出 SK、三星共用的一個占比；2026 年以後沿用。低＝長鑫取 12.0 時的校準值；高＝58%（業界下限，Rebound Capital） | I31: 校準只用 2025 實績；2026 年以後完全沒有參照 SEMI 或券商的預測。未找到 SK 海力士公司揭露（定性：董事會 2026-02 核准 21.6 兆韓元完成龍仁第一晶圓廠結構工程與二至六期無塵室）。業界值 64% 不再當基準，Sens 保留一列對照
A32: sh_ss | B32: 三星（記憶體）：設備占資本支出比例（同 SK 海力士，校準值） | C32: % | D32: =Mkt!$C$79 -> 0.38504085 | E32: =Mkt!$C$78 -> 0.455453 | F32: =Mkt!$C$80 -> 0.58 | G32: Derived | H32: 同 sh_sk（兩者共用同一個校準值，以 2025 實績校準） | I32: 未找到三星公司揭露（P5 無塵室先行，無建築／設備比例）。三星記憶體 2025 資本支出為 DS 47.5 兆 × ss_mem（Assumed）；ss_mem 改變時校準值隨之改變（Sens）
A33: sh_fd | B33: 台積電（代工與邏輯）：設備占資本支出比例 | C33: % | D33: 0.5 | E33: 0.64 | F33: 0.75 | G33: Analogy | H33: SEMI 2025 WFE 116.9B（年中預測新聞稿）÷ Semiconductor Intelligence 2025 全球半導體資本支出 166B（https://www.semiconductorintelligence.com/capex-up-for-foundry-memory/）＝70.4% → 高 70% | I33: Rebound Capital（Substack）資本支出→晶圓前段設備轉換率約 58%（https://reboundcapital.substack.com/p/industry-deep-dive-semiconductor）→ 低 58%；基準取兩者中點 64%。業界合計值，未找到記憶體／代工分項。v0.1.2 查證（TSMC 頁）：台積電董事會每季資本預算有分「機器設備」與「不動產與資本化租賃資產」（二手摘要，5 次，彙總設備占 60%，單次 47–71%）；元大投顧稱先進製程外商前段設備占資本支出 7～8 成（Interested-party）。兩者都未顯示台積電像 SK 海力士、三星（45.5%）那樣偏低，故基準維持 64%；低 50%＝董事會 2025-08（47%）、2026-02（52%）兩次的水準，高 75%＝元大 7～8 成的中點。年報不動產廠房及設備附註的分類增添：未找到（本環境無法開啟年報 PDF）。台積電資本支出含先進封裝、光罩等（公司稱 10–20%），base 未另扣，見 pk_ts 與 Sens
A34: B1b. 台積電設備占比證據（v0.1.2；明細見 TSMC 頁）
A35: pk_ts | B35: 台積電資本支出中屬先進封裝、測試、光罩及其他的比例 | C35: % | D35: 0.1 | E35: 0.15 | F35: 0.2 | G35: Interested-party | H35: 台積電（3Q25 法說逐字稿，Motley Fool）：2025 資本支出約 10–20% 用於先進封裝、測試、光罩及其他 https://www.fool.com/earnings/call-transcripts/2025/10/17/tsmc-tsm-q3-2025-earnings-call-transcript | I35: 2026 年配置同為 10–20%（搜尋摘要：https://xmy.tw/articles/global-semiconductor-capex-2026/tsmc-capex-2026，未開啟原文）。公司揭露的是「用途」分類，不是設備／建築分類；其設備中有多少被 SEMI 分入後段（測試、組裝封裝）或其他前段（光罩）：未找到。base 不扣，只進 Sens 與 TSMC 頁
A36: cap_smic_25 | B36: 中芯 2025 資本支出（TSMC 頁可識別性檢查用） | C36: $B | D36: 8.1 | E36: 8.1 | F36: 8.1 | G36: Interested-party | H36: TrendForce（2026-03-30）：中芯 2025 約 $8.1B、2026 約持平 https://www.trendforce.com/news/2026/03/30/news-smic-2026-action-plan-points-to-above-industry-growth-capex-held-in-line-with-2025/ | I36: 第二來源：未找到。沿用本模型 g_oth_fd 說明所引數字
A37: cap_intel_25 | B37: Intel 2025 資本支出（毛額；扣抵後淨額約 11.2） | C37: $B | D37: 11.2 | E37: 17.7 | F37: 17.7 | G37: Interested-party | H37: Intel 4Q25 法說摘要（Yahoo Finance／MarketBeat）：毛額 $17.7B、扣抵約 $6.5B → 淨約 $11.2B（Derived）https://finance.yahoo.com/news/intel-q4-earnings-call-highlights-234233695.html | I37: 第二來源：Intel FY2025 10-K（https://www.sec.gov/Archives/edgar/data/50863/000005086326000011/intc-20251227.htm，搜尋結果列出，未開啟核對）；第三方資料站現金流量口徑 14.65（口徑不同）。SEMI 計的是設備出貨，取毛額為基準
A38: B2. 其他廠 2026 年以後成長率（Assumed；每個區塊合併成一個年成長率，套用 2026–2029。依據公司資本支出指引；不參照 SEMI 2026 以後預測）
A39: g_oth_dram | B39: 其他 DRAM 廠（長鑫、南亞、華邦等）設備成長率 | C39: %/年 | D39: 0.1 | E39: 0.18 | F39: 0.6 | G39: Assumed | H39: 長鑫：未揭露資本支出；研究估計月產能 360k／420k／500k 片（2026／27／28）→ +17%／+19%（https://faxiangongchang.com/en/reports/china-memory-chip-2026，弱）；南亞 2026 資本支出上限 NT$69.7B，2027 最高 NT$200B（約 4 倍，https://www.digitimes.com/news/a20260713PD211/nanya-technology-capex-capacity-2027.html）；華邦 2026 NT$42.1B（紀錄高，https://www.gate.com/news/detail/winbond-approves-507b-capex-expands-kaohsiung-fab-production-to-24000-23369791） | I39: 基準取長鑫產能成長（兩年平均約 18%，Analogy：產能成長代替資本支出）；低 10% 假設資本支出增速低於產能；高 60% 取南亞 2027 與鎧俠 FY26 的高增速。長鑫的資本支出指引：未找到；2025 年基準（華邦、南亞）：未找到
A40: g_oth_nand | B40: 其他 NAND 廠（鎧俠、SanDisk 合資、長江存儲等）設備成長率 | C40: %/年 | D40: 0 | E40: 0.18 | F40: 0.6 | G40: Assumed | H40: 鎧俠：FY25 ¥283.7B → FY26 ¥450B（+59%），FY26–28 年均約 ¥470B（https://www.trendforce.com/news/2026/06/03/news-kioxia-targets-%C2%A5470b-yearly-capex-in-fy26-28-up-66-from-fy25-reportedly-weighing-third-kitakami-fab-and-ma/）；SanDisk FY27 毛資本支出約營收 6%（含與鎧俠合資的分攤，與鎧俠重疊，不另加，https://www.fool.com/investing/2026/08/29/sandisk-and-kioxia-plan-to-invest-more-than-usd31-billion-in-japanese-memory-plants-about-60-of-what-they-have-spent-there-in-25-years/）；長江存儲：三廠 2026 底投產，金額未找到 | I40: 基準＝鎧俠 FY25→FY28 年複合 ((470/283.7)^(1/3)−1)≈18%（Derived，單一公司）；低 0% 為 FY27–28 持平；高 60% 為 FY26 單年增速。長江存儲資本支出指引：未找到
A41: g_oth_fd | B41: 其他代工與邏輯（中芯、Intel、三星晶圓代工、華虹、聯電、GlobalFoundries 等）設備成長率 | C41: %/年 | D41: 0 | E41: 0.08 | F41: 0.2 | G41: Assumed | H41: 中芯：2025 約 $8.1B、2026 約持平（https://www.trendforce.com/news/2026/03/30/news-smic-2026-action-plan-points-to-above-industry-growth-capex-held-in-line-with-2025/）；Intel：2026 提高到 >$20B（原約 $17–18B；2027「明顯更高」，https://www.gate.com/news/detail/intel-raises-2026-capex-guidance-to-over-20-billion-q2-earnings-beat-22949346） | I41: 基準＝中芯（0%）與 Intel（約 +11%，18→20）以 2025 金額加權約 +8%（Derived）；低 0%＝中芯持平；高 20% 假設 Intel 2027 大增。三星晶圓代工、華虹、聯電、GlobalFoundries 資本支出指引：未找到（三星僅有半導體合計）
A42: G. 2025 年其他記憶體廠資本支出：獨立估計（用作 2025 其他廠基準，並用於校準 SK 海力士、三星設備占比；只用 2025 實績）
A43: sh_oth | B43: 其他記憶體廠設備占資本支出比例（業界值） | C43: % | D43: 0.58 | E43: 0.64 | F43: 0.7 | G43: Analogy | H43: SEMI 2025 WFE 116.9B（年中預測新聞稿）÷ Semiconductor Intelligence 2025 全球半導體資本支出 166B（https://www.semiconductorintelligence.com/capex-up-for-foundry-memory/）＝70.4% → 高 70% | I43: Rebound Capital（Substack）資本支出→晶圓前段設備轉換率約 58%（https://reboundcapital.substack.com/p/industry-deep-dive-semiconductor）→ 低 58%；基準取兩者中點 64%。業界合計值，未找到記憶體／代工分項
A44: ind_cxmt | B44: 長鑫 2025 資本支出（高值年度未核對） | C44: $B | D44: 6.9 | E44: 6.9 | F44: 12 | G44: Interested-party | H44: TechInsights（Reuters 轉引，2025 初）：2023、2024 約 $6–7B，預期 2025 +5%（≈6.9）https://finance.yahoo.com/news/exclusive-chipmaker-cxmt-plans-shanghai-073043365.html | I44: 高 12.0：BigGo 摘要「CNY 80.5B（約 $12.0B）、+62%」，年度未核對 https://finance.biggo.com/news/5a548f95-479d-4e07-8dd1-af5beb8eea1f。TrendForce、券商的長鑫 2025 資本支出：未找到。基準取低端，無依據偏好
A45: ind_nand_ind | B45: 全球 NAND 資本支出 2025 | C45: $B | E45: 21.1 | G45: Interested-party | H45: TrendForce 2025-11-13：NAND 資本支出 2025 $21.1B、2026 $22.2B https://www.trendforce.com/presscenter/news/20251113-12780.html | I45: StorageNewsletter 轉載 https://www.storagenewsletter.com/2025/12/31/memory-industry-to-maintain-cautious-capex-in-2026/（非獨立）
A46: ind_ymtc_sh | B46: 長江存儲占全球 NAND 資本支出比例（2025） | C46: % | E46: 0.2 | G46: Interested-party | H46: 搜尋摘要稱 YMTC 2025 資本支出約占全球 NAND 投資 20%（出處為 Digitimes 系列報導，確切文章未核對） | I46: 第二來源：未找到
A47: ind_kioxia | B47: 鎧俠 FY2025 資本支出（FY 至 2026-03） | C47: ¥B | E47: 283.7 | G47: Interested-party | H47: TrendForce 2026-06-03（FY26 ¥450B、FY26–28 年均 ¥470B，較 FY25 +66%；FY25 ¥283.7B 為二手整理）https://www.trendforce.com/news/2026/06/03/news-kioxia-targets-%C2%A5470b-yearly-capex-in-fy26-28-up-66-from-fy25-reportedly-weighing-third-kitakami-fab-and-ma/ | I47: 鎧俠 Investor Day 2026 簡報 https://www.kioxia-holdings.com/content/dam/kioxia-hd/en-jp/ir/library/event/asset/Kioxia-Investor-Day-2026-en.pdf（未開啟，未核對 ¥283.7B）
A48: fx_jpy | B48: 日圓兌美元（2025） | C48: JPY/USD | D48: 140 | E48: 150 | F48: 155 | G48: Assumed | H48: 無：未查匯率來源（2025 年大致在 140–155） | I48: —
A49: ind_nanya | B49: 南亞科 2025 資本支出 | C49: NT$B | E49: 13.4 | G49: Verified | H49: 南亞科 IR：2025 預算上限 19.6、實支 13.4、6.2 遞延到 2026 https://www.nanya.com/en/IR/16/?IRId=11068 | I49: 第三方 Q1 簡報摘要同值（見 IR 頁）
A50: fx_twd | B50: 新台幣兌美元（2025） | C50: TWD/USD | D50: 29.5 | E50: 31 | F50: 32.5 | G50: Assumed | H50: 無：未查匯率來源 | I50: —
A51: ind_winbond | B51: 華邦 2025 資本支出 | C51: NT$B | G51: —（未找到） | H51: 未找到（只查到 2026 年 NT$42.1B，https://www.gate.com/news/detail/winbond-approves-507b-capex-expands-kaohsiung-fab-production-to-24000-23369791） | I51: 未找到；估計記為 0（總額偏低）
A52: ind_sandisk | B52: SanDisk 2025 資本支出（JV 分攤） | C52: $B | G52: —（未找到） | H52: FY25 數字未找到；FY26 毛資本支出 $0.562B，其中 JV 分攤 $0.519B（Q4 FY26 簡報 https://investor.sandisk.com/static-files/c75d1bee-c5c9-4e5a-8605-302c1aeac59b） | I52: JV 分攤與鎧俠重疊（Flash Ventures 由鎧俠 50.1％、SanDisk 49.9％持有），不另計；非 JV 部分約 $0.04B（FY26），忽略
A53: C. SEMI 2026-07 年中預測（Interested-party）。2025 為實績（由年增率回推），用於求其他廠基準；2026 以後的 SEMI 分項只用於對帳，不決定本模型總額（測試與封裝除外，v0.1 以 SEMI 為輸入）
A54: s_dram_26 | B54: SEMI DRAM 設備 2026 | C54: $B | E54: 38.8 | G54: Interested-party | H54: SEMI 2026-07-14 年中預測新聞稿 https://www.semi.org/en/semi-press-release/global-semiconductor-equipment-sales-forecast-to-reach-a-record-229-billion-dollars-in-2028-semi-reports | I54: 轉載：PR Newswire／Semiconductor Digest（同一原始發布，非獨立來源）；SEMI 為設備商協會，傾向樂觀（Interested-party）
A55: g_dram_26 | B55: SEMI DRAM 設備 2026 年增 | C55: % | E55: 0.39 | G55: Interested-party | H55: SEMI 2026-07-14 年中預測新聞稿 https://www.semi.org/en/semi-press-release/global-semiconductor-equipment-sales-forecast-to-reach-a-record-229-billion-dollars-in-2028-semi-reports | I55: 轉載：PR Newswire／Semiconductor Digest（同一原始發布，非獨立來源）；SEMI 為設備商協會，傾向樂觀（Interested-party）
A56: g_dram_27 | B56: SEMI DRAM 設備 2027 年增 | C56: % | E56: 0.274 | G56: Interested-party | H56: SEMI 2026-07-14 年中預測新聞稿 https://www.semi.org/en/semi-press-release/global-semiconductor-equipment-sales-forecast-to-reach-a-record-229-billion-dollars-in-2028-semi-reports（2027 前段 +21.8% 與其餘分項年增皆來自 SEMI 新聞稿摘要） | I56: 轉載：PR Newswire／Semiconductor Digest（同一原始發布，非獨立來源）；SEMI 為設備商協會，傾向樂觀（Interested-party）
A57: g_dram_28 | B57: SEMI DRAM 設備 2028 年增 | C57: % | E57: 0.15 | G57: Interested-party | H57: SEMI 2026-07-14 年中預測新聞稿 https://www.semi.org/en/semi-press-release/global-semiconductor-equipment-sales-forecast-to-reach-a-record-229-billion-dollars-in-2028-semi-reports | I57: 轉載：PR Newswire／Semiconductor Digest（同一原始發布，非獨立來源）；SEMI 為設備商協會，傾向樂觀（Interested-party）；DRAM 2028 推得 56.85 vs 報導 56.9、NAND 20.87 vs 20.8（捨入）
A58: s_nand_26 | B58: SEMI NAND 設備 2026 | C58: $B | E58: 13.9 | G58: Interested-party | H58: SEMI 2026-07-14 年中預測新聞稿 https://www.semi.org/en/semi-press-release/global-semiconductor-equipment-sales-forecast-to-reach-a-record-229-billion-dollars-in-2028-semi-reports | I58: 轉載：PR Newswire／Semiconductor Digest（同一原始發布，非獨立來源）；SEMI 為設備商協會，傾向樂觀（Interested-party）
A59: g_nand_26 | B59: SEMI NAND 設備 2026 年增 | C59: % | E59: 0.307 | G59: Interested-party | H59: SEMI 2026-07-14 年中預測新聞稿 https://www.semi.org/en/semi-press-release/global-semiconductor-equipment-sales-forecast-to-reach-a-record-229-billion-dollars-in-2028-semi-reports | I59: 轉載：PR Newswire／Semiconductor Digest（同一原始發布，非獨立來源）；SEMI 為設備商協會，傾向樂觀（Interested-party）
A60: g_nand_27 | B60: SEMI NAND 設備 2027 年增 | C60: % | E60: 0.311 | G60: Interested-party | H60: SEMI 2026-07-14 年中預測新聞稿 https://www.semi.org/en/semi-press-release/global-semiconductor-equipment-sales-forecast-to-reach-a-record-229-billion-dollars-in-2028-semi-reports（2027 前段 +21.8% 與其餘分項年增皆來自 SEMI 新聞稿摘要） | I60: 轉載：PR Newswire／Semiconductor Digest（同一原始發布，非獨立來源）；SEMI 為設備商協會，傾向樂觀（Interested-party）
A61: g_nand_28 | B61: SEMI NAND 設備 2028 年增 | C61: % | E61: 0.145 | G61: Interested-party | H61: SEMI 2026-07-14 年中預測新聞稿 https://www.semi.org/en/semi-press-release/global-semiconductor-equipment-sales-forecast-to-reach-a-record-229-billion-dollars-in-2028-semi-reports | I61: 轉載：PR Newswire／Semiconductor Digest（同一原始發布，非獨立來源）；SEMI 為設備商協會，傾向樂觀（Interested-party）；DRAM 2028 推得 56.85 vs 報導 56.9、NAND 20.87 vs 20.8（捨入）
A62: s_fd_26 | B62: SEMI 代工與邏輯設備 2026 | C62: $B | E62: 78 | G62: Interested-party | H62: SEMI 2026-07-14 年中預測新聞稿 https://www.semi.org/en/semi-press-release/global-semiconductor-equipment-sales-forecast-to-reach-a-record-229-billion-dollars-in-2028-semi-reports | I62: 轉載：PR Newswire／Semiconductor Digest（同一原始發布，非獨立來源）；SEMI 為設備商協會，傾向樂觀（Interested-party）
A63: g_fd_26 | B63: SEMI 代工與邏輯設備 2026 年增 | C63: % | E63: 0.189 | G63: Interested-party | H63: SEMI 2026-07-14 年中預測新聞稿 https://www.semi.org/en/semi-press-release/global-semiconductor-equipment-sales-forecast-to-reach-a-record-229-billion-dollars-in-2028-semi-reports | I63: 轉載：PR Newswire／Semiconductor Digest（同一原始發布，非獨立來源）；SEMI 為設備商協會，傾向樂觀（Interested-party）
A64: g_fd_27 | B64: SEMI 代工與邏輯設備 2027 年增 | C64: % | E64: 0.181 | G64: Interested-party | H64: SEMI 2026-07-14 年中預測新聞稿 https://www.semi.org/en/semi-press-release/global-semiconductor-equipment-sales-forecast-to-reach-a-record-229-billion-dollars-in-2028-semi-reports（2027 前段 +21.8% 與其餘分項年增皆來自 SEMI 新聞稿摘要） | I64: 轉載：PR Newswire／Semiconductor Digest（同一原始發布，非獨立來源）；SEMI 為設備商協會，傾向樂觀（Interested-party）
A65: g_fd_28 | B65: SEMI 代工與邏輯設備 2028 年增 | C65: % | E65: 0.136 | G65: Interested-party | H65: SEMI 2026-07-14 年中預測新聞稿 https://www.semi.org/en/semi-press-release/global-semiconductor-equipment-sales-forecast-to-reach-a-record-229-billion-dollars-in-2028-semi-reports | I65: 轉載：PR Newswire／Semiconductor Digest（同一原始發布，非獨立來源）；SEMI 為設備商協會，傾向樂觀（Interested-party）；DRAM 2028 推得 56.85 vs 報導 56.9、NAND 20.87 vs 20.8（捨入）
... A78: s_tot_28 | B78: SEMI 設備合計 2028（對帳用） | C78: $B | E78: 229.5 | G78: Interested-party | H78: SEMI 2026-07-14 年中預測新聞稿 https://www.semi.org/en/semi-press-release/global-semiconductor-equipment-sales-forecast-to-reach-a-record-229-billion-dollars-in-2028-semi-reports | I78: 轉載：PR Newswire／Semiconductor Digest（同一原始發布，非獨立來源）；SEMI 為設備商協會，傾向樂觀（Interested-party）
A79: g29 | B79: 2029 年 SEMI 測試、封裝設備年增（SEMI 無 2029 預測；僅用於測試與封裝） | C79: % | D79: 0 | E79: 0.08 | F79: 0.12 | G79: Assumed | H79: 無。SEMI 前段年增 2026 +23.1%、2027 +21.8%、2028 +14.1%：逐年減速約 2–7 個百分點，外推 2029 約 +8% | I79: 未找到第二來源；情境 A 的意思是「續增」，B、C 由情境係數覆寫
A80: D. 資本支出情境係數（2028、2029；設備總額相對前一年的倍數；情境 A 沿用上表由下而上路徑，不用係數）
A81: ck_B_28 | B81: 情境 B 2028 係數（持平） | C81: x | D81: 0.95 | E81: 1 | F81: 1.05 | G81: Assumed | H81: 依核心問題 1：B＝2028 持平（循環在 2027 見頂） | I81: 理由：記憶體模型 B 情境 2027 Q2 價格見頂；資本支出滯後約 1–2 季，2028 設備訂單轉為持平。無實證，非預測
A82: ck_C_28 | B82: 情境 C 2028 係數（下滑約兩成） | C82: x | D82: 0.75 | E82: 0.8 | F82: 0.85 | G82: Assumed | H82: 依核心問題 1：C＝2028 下滑約兩成 | I82: 理由：記憶體模型 C 情境 2028 價格回到 2025 水準；WFE 歷史下行年（2019、2023）跌幅較淺，C 為壓力情境。無實證
A83: ck_B_29 | B83: 情境 B 2029 係數 | C83: x | D83: 0.9 | E83: 0.95 | F83: 1.05 | G83: Assumed | H83: 平台後的溫和消化 | I83: 無實證
A84: ck_C_29 | B84: 情境 C 2029 係數 | C84: x | D84: 0.9 | E84: 1 | F84: 1.1 | G84: Assumed | H84: 谷底持平 | I84: 無實證
A85: E. AI 相關分類（用於 AI 增量占比；v0.1 的分類假設，非公開資料）
A86: adv_other | B86: 台積電以外代工邏輯中屬先進邏輯的比例 | C86: % | D86: 0.15 | E86: 0.25 | F86: 0.4 | G86: Assumed | H86: 無：Intel 18A／14A、三星 SF2、Rapidus 相對成熟製程擴產（中芯、華虹等）的占比未找到 | I86: 未找到第二來源
A87: pkg_adv | B87: 組裝與封裝設備中屬先進封裝的比例 | C87: % | D87: 0.35 | E87: 0.5 | F87: 0.65 | G87: Assumed | H87: 無：KLA 稱 2026 先進封裝製程控制營收約 $1.1B，但整體先進封裝設備金額未找到 | I87: 未找到第二來源。台積電資本支出內的先進封裝設備可能與此重疊（見 README 限制）
A88: F. 對帳來源值（本模型不得為對上這些數字而調整；2026 前段口徑各家不同，見 Recon）
A89: rc_lam26 | B89: Lam Research 2026 WFE（低 150B） | C89: $B | E89: 150 | G89: Interested-party | H89: Lam FQ4-26 法說逐字稿（https://www.investing.com/news/transcripts/earnings-call-transcript-lam-research-posts-record-q4-2026-results-stock-rebounds-93CH-4821978）；另：Citi 研討會 CFO 稱「low-$150B」（https://finance.yahoo.com/technology/ai/articles/lam-research-lifts-2026-wfe-180229282.html） | I89: Lam 2026-10-21 法說稿另稱「mid-$150B」（https://www.fool.com/earnings/call-transcripts/2026/10/21/lam-research-lrcx-q1-2027-earnings-call-transcript/）；取 150 為下限
A90: rc_lam27 | B90: Lam Research 2027 WFE（>200B，下限；額外對照） | C90: $B | E90: 200 | G90: Interested-party | H90: 同上法說稿：2027 預估 >$200B | I90: 使用者未列；額外列示
A91: rc_kla26 | B91: KLA 2026 WFE（低 150B；含先進封裝） | C91: $B | E91: 150 | G91: Interested-party | H91: KLA FQ4-26 法說摘要（社群摘要，弱）https://x.com/TheValueist/status/2082235400190640364；BigGo 摘要：https://finance.biggo.com/news/US_KLAC_2026-07-28 | I91: 社群摘要 https://x.com/TheValueist/status/2082235400190640364（弱）；KLA 2025 約 120 vs SEMI 116.9，口徑含先進封裝
A92: rc_kla27 | B92: KLA 2027 規劃（約 190B） | C92: $B | E92: 190 | G92: Interested-party | H92: KLA FQ4-26 法說摘要（社群摘要，弱）https://x.com/TheValueist/status/2082235400190640364 | I92: 同上社群摘要；一手逐字稿未找到
A93: rc_ms27 | B93: Morgan Stanley 2027 WFE | C93: $B | E93: 202 | G93: Interested-party | H93: 二手轉述（itiger，2026-07-06：https://www.itiger.com/news/2649678863——「2027 由 191 上修到 202，2028 由 215 上修到 227」；本環境無法開啟該頁，未直接核對） | I93: 上修前版本 191／215 與 Investing.com 報導一致（2026／27／28＝149／191／215；https://www.investing.com/news/stock-market-news/semicap-stocks-morgan-stanley-raises-wfe-outlook-and-shifts-ratings-4696580），故 202／227 為其上修值
A94: rc_ms28 | B94: Morgan Stanley 2028 WFE | C94: $B | E94: 227 | G94: Interested-party | H94: 同上（itiger，二手轉述） | I94: 同上
A95: rc_gs26 | B95: Goldman Sachs 2026 WFE | C95: $B | E95: 150 | G95: Interested-party | H95: https://www.gate.com/news/detail/goldman-sachs-significantly-raises-wfe-forecasts-through-2028-can-the-ai-23706576 | I95: https://www.kucoin.com/news/flash/goldman-sachs-upgrades-wfe-forecast-to-1-5-trillion-by-2026-dram-and-foundry-drive-growth（標題單位誤植，內文 150）
A96: rc_gs27 | B96: Goldman Sachs 2027 WFE | C96: $B | E96: 218 | G96: Interested-party | H96: https://www.gate.com/news/detail/goldman-sachs-significantly-raises-wfe-forecasts-through-2028-can-the-ai-23706576 | I96: 同上
A97: rc_gs28 | B97: Goldman Sachs 2028 WFE | C97: $B | E97: 281 | G97: Interested-party | H97: https://www.gate.com/news/detail/goldman-sachs-significantly-raises-wfe-forecasts-through-2028-can-the-ai-23706576 | I97: 同上
A98: rc_thr | B98: 差距門檻（README 須說明原因） | C98: % | E98: 0.15 | G98: Verified | H98: 使用者指定 15% | I98: —

Sheet Mkt
A1: Mkt — 半導體設備市場（十億美元）：由下而上（公司資本支出 × 設備占比）＋ 其他廠（2025 基準 × 成長率）＋ SEMI 後段；三情境
A2: 2025＝由下而上（三家＋台積電資本支出 × 設備占比）＋其他廠基準（SEMI 實績減已知廠）；2026 起其他廠＝基準 × 成長率（Assumed），總額由下而上，不由 SEMI 2026 以後預測決定。SEMI 2026 以後的分項只用於對帳。
A3: 項目 | B3: 單位 | C3: 2025 | D3: 2026 | E3: 2027 | F3: 2028 | G3: 2029 | H3: 說明
A4: 摘要（各情境設備總額、年增、AI 增量占比、見頂年度）
A5: 情境 A
A6: 設備總額 | B6: $B | C6: =C129 -> 134.68936 | D6: =D129 -> 178.15705 | E6: =E129 -> 218.22554 | F6: =F129 -> 246.02863 | G6: =G129 -> 260.65569
A7: 年增 | B7: % | D7: =D130 -> 0.3227255 | E7: =E130 -> 0.22490541 | F7: =F130 -> 0.1274053 | G7: =G130 -> 0.059452673
A8: 其中晶圓前段 | B8: $B | C8: =C127 -> 116.89683 | D8: =D127 -> 156.15705 | E8: =E127 -> 192.79547 | F8: =F127 -> 216.62863 | G8: =G127 -> 228.90369
A9: AI 相關設備 | B9: $B | C9: =C132 -> 65.465015 | D9: =D132 -> 93.04079 | E9: =E132 -> 117.83056 | F9: =F132 -> 133.87705 | G9: =G132 -> 140.68473
A10: AI 增量占總增量（相對 2025 累計） | B10: % | D10: =D134 -> 0.63439706 | E10: =E134 -> 0.62686064 | F10: =F134 -> 0.61444657 | G10: =G134 -> 0.59714145
A11: AI 增量占總增量（當年） | B11: % | D11: =D135 -> 0.63439706 | E11: =E135 -> 0.61868487 | F11: =F135 -> 0.57714769 | G11: =G135 -> 0.46541718
A12: 見頂年度 | C12: =C136 -> 2029
A13: 情境 B
A14: 設備總額 | B14: $B | C14: =C148 -> 134.68936 | D14: =D148 -> 178.15705 | E14: =E148 -> 218.22554 | F14: =F148 -> 218.22554 | G14: =G148 -> 207.31426
A15: 年增 | B15: % | D15: =D149 -> 0.3227255 | E15: =E149 -> 0.22490541 | F15: =F149 -> 0 | G15: =G149 -> -0.05
A16: 其中晶圓前段 | B16: $B | C16: =C146 -> 116.89683 | D16: =D146 -> 156.15705 | E16: =E146 -> 192.79547 | F16: =F146 -> 192.79547 | G16: =G146 -> 183.1557
A17: AI 相關設備 | B17: $B | C17: =C151 -> 65.465015 | D17: =D151 -> 93.04079 | E17: =E151 -> 117.83056 | F17: =F151 -> 117.83056 | G17: =G151 -> 111.93903
A18: AI 增量占總增量（相對 2025 累計） | B18: % | D18: =D153 -> 0.63439706 | E18: =E153 -> 0.62686064 | F18: =F153 -> 0.62686064 | G18: =G153 -> 0.63991845
A19: AI 增量占總增量（當年） | B19: % | D19: =D154 -> 0.63439706 | E19: =E154 -> 0.61868487 | F19: =F154 -> n/a | G19: =G154 -> 0.53994852
A20: 見頂年度 | C20: =C155 -> 2028
A21: 情境 C
A22: 設備總額 | B22: $B | C22: =C167 -> 134.68936 | D22: =D167 -> 178.15705 | E22: =E167 -> 218.22554 | F22: =F167 -> 174.58043 | G22: =G167 -> 174.58043
A23: 年增 | B23: % | D23: =D168 -> 0.3227255 | E23: =E168 -> 0.22490541 | F23: =F168 -> -0.2 | G23: =G168 -> 0
A24: 其中晶圓前段 | B24: $B | C24: =C165 -> 116.89683 | D24: =D165 -> 156.15705 | E24: =E165 -> 192.79547 | F24: =F165 -> 154.23638 | G24: =G165 -> 154.23638
A25: AI 相關設備 | B25: $B | C25: =C170 -> 65.465015 | D25: =D170 -> 93.04079 | E25: =E170 -> 117.83056 | F25: =F170 -> 94.264444 | G25: =G170 -> 94.264444
A26: AI 增量占總增量（相對 2025 累計） | B26: % | D26: =D172 -> 0.63439706 | E26: =E172 -> 0.62686064 | F26: =F172 -> 0.72195182 | G26: =G172 -> 0.72195182
A27: AI 增量占總增量（當年） | B27: % | D27: =D173 -> 0.63439706 | E27: =E173 -> 0.61868487 | F27: =F173 -> 0.53994852 | G27: =G173 -> n/a
A28: 見頂年度 | C28: =C174 -> 2027
A40: 1. SEMI 分項金額（A 路徑的天花板與「其他廠」推導基礎）
A41: SEMI DRAM 設備 | B41: $B | C41: =D41/(1+g_dram_26) -> 27.913669 | D41: =s_dram_26 -> 38.8 | E41: =D41*(1+g_dram_27) -> 49.4312 | F41: =E41*(1+g_dram_28) -> 56.84588 | G41: =F41*(1+g29) -> 61.39355 | H41: 2026 新聞稿值；2025 由年增回推；2027、2028 年增連乘；2029 為 g29（Assumed）
A42: SEMI NAND 設備 | B42: $B | C42: =D42/(1+g_nand_26) -> 10.635042 | D42: =s_nand_26 -> 13.9 | E42: =D42*(1+g_nand_27) -> 18.2229 | F42: =E42*(1+g_nand_28) -> 20.86522 | G42: =F42*(1+g29) -> 22.534438 | H42: 2026 新聞稿值；2025 由年增回推；2027、2028 年增連乘；2029 為 g29（Assumed）
A43: SEMI 代工與邏輯設備 | B43: $B | C43: =D43/(1+g_fd_26) -> 65.601346 | D43: =s_fd_26 -> 78 | E43: =D43*(1+g_fd_27) -> 92.118 | F43: =E43*(1+g_fd_28) -> 104.64605 | G43: =F43*(1+g29) -> 113.01773 | H43: 2026 新聞稿值；2025 由年增回推；2027、2028 年增連乘；2029 為 g29（Assumed）
A44: SEMI 晶圓前段設備（WFE） | B44: $B | C44: =D44/(1+g_wfe_26) -> 116.89683 | D44: =s_wfe_26 -> 143.9 | E44: =D44*(1+g_wfe_27) -> 175.2702 | F44: =E44*(1+g_wfe_28) -> 199.9833 | G44: =F44*(1+g29) -> 215.98196 | H44: 2026 新聞稿值；2025 由年增回推；2027、2028 年增連乘；2029 為 g29（Assumed）
A45: SEMI 測試設備 | B45: $B | C45: =D45/(1+g_test_26) -> 11.679389 | D45: =s_test_26 -> 15.3 | E45: =SQRT(D45*F45) -> 17.839282 | F45: =s_test_28 -> 20.8 | G45: =F45*(1+g29) -> 22.464 | H45: 2026、2028 新聞稿值；2027 幾何內插（Derived，未找到年中預測 2027 值）
A46: SEMI 組裝與封裝設備 | B46: $B | C46: =D46/(1+g_pkg_26) -> 6.1131387 | D46: =s_pkg_26 -> 6.7 | E46: =SQRT(D46*F46) -> 7.5907839 | F46: =s_pkg_28 -> 8.6 | G46: =F46*(1+g29) -> 9.288 | H46: 2026、2028 新聞稿值；2027 幾何內插（Derived，未找到年中預測 2027 值）
A47: SEMI 其他前段（WFE − 代工邏輯 − DRAM − NAND） | B47: $B | C47: =C44-C43-C41-C42 -> 12.746775 | D47: =D44-D43-D41-D42 -> 13.2 | E47: =E44-E43-E41-E42 -> 15.4981 | F47: =F44-F43-F41-F42 -> 17.62615 | G47: =G44-G43-G41-G42 -> 19.036242 | H47: Derived：類比、功率、光罩、廠務設備等；v0.1 不由下而上，沿用 SEMI 差額
A48: SEMI 設備合計（WFE＋測試＋封裝） | B48: $B | C48: =C44+C45+C46 -> 134.68936 | D48: =D44+D45+D46 -> 165.9 | E48: =E44+E45+E46 -> 200.70027 | F48: =F44+F45+F46 -> 229.3833 | G48: =G44+G45+G46 -> 247.73396 | H48: 2026 應＝165.9、2028 應＝229.5（捨入差見 Recon）
A49: 2025 年 SEMI DRAM ÷（DRAM＋NAND）（各年沿用，Assumed） | B49: % | C49: =C41/(C41+C42) -> 0.7241142 | D49: =$C49 -> 0.7241142 | E49: =$C49 -> 0.7241142 | F49: =$C49 -> 0.7241142 | G49: =$C49 -> 0.7241142 | H49: 把各廠記憶體設備拆成 DRAM（含 HBM）與 NAND：假設三家組合同 2025 年 SEMI 市場組合
A50: SEMI 其他前段占（記憶體＋代工邏輯）比例（2025；各年沿用，Assumed） | B50: % | C50: =C47/(C41+C42+C43) -> 0.12238856 | D50: =$C50 -> 0.12238856 | E50: =$C50 -> 0.12238856 | F50: =$C50 -> 0.12238856 | G50: =$C50 -> 0.12238856 | H50: 其他前段（類比、功率、光罩等）v0.1 維持 2025 年占比
A52: 2. 記憶體晶圓前段設備（2025 以實績校準；2026 起沿用校準值與成長率）
A53: 2a. 2025 年其他記憶體廠：由下而上獨立估計（資本支出 × sh_oth）＝其他廠 2025 基準
A54: 長鑫資本支出 | B54: $B | C54: =ind_cxmt -> 6.9 | H54: TechInsights（Reuters）；高 12.0 年度未核對，見 In／Sens
A55: 南亞科資本支出 | B55: $B | C55: =ind_nanya/fx_twd -> 0.43225806
A56: 華邦資本支出 | B56: $B | C56: 0 | H56: 未找到，記 0
A57: 其他 DRAM 廠資本支出 | B57: $B | C57: =C54+C55+C56 -> 7.3322581
A58: 鎧俠資本支出（FY25） | B58: $B | C58: =ind_kioxia/fx_jpy -> 1.8913333
A59: 長江存儲資本支出（全球 NAND 資本支出 × 占比） | B59: $B | C59: =ind_nand_ind*ind_ymtc_sh -> 4.22
A60: SanDisk（JV 分攤與鎧俠重疊，不另計） | B60: $B | C60: 0 | H60: FY25 未找到
A61: 其他 NAND 廠資本支出 | B61: $B | C61: =C58+C59+C60 -> 6.1113333
A62: 其他 DRAM 廠設備＝資本支出 × sh_oth | B62: $B | C62: =C57*sh_oth -> 4.6926452
A63: 其他 NAND 廠設備＝資本支出 × sh_oth | B63: $B | C63: =C61*sh_oth -> 3.9112533
A64: 其他記憶體廠設備（獨立估計） | B64: $B | C64: =C62+C63 -> 8.6038985
A66: 2b. 三大廠資本支出
A67: SK 海力士資本支出（美元） | B67: $B | C67: =cap_sk_25*1000/fx -> 21.267606 | D67: =cap_sk_26*1000/fx -> 34.295775 | E67: =cap_sk_27*1000/fx -> 43.873239 | F67: =cap_sk_28*1000/fx -> 50.140845 | G67: =cap_sk_29*1000/fx -> 52.816901 | H67: 兆韓元 × 1000 ÷ KRW/USD ＝ 十億美元（2025 亦用同一匯率，Assumed）
A68: 美光資本支出（淨；FY≈日曆年） | B68: $B | C68: =cap_mu_25 -> 13.8 | D68: =cap_mu_26 -> 27.367 | E68: =cap_mu_27 -> 55 | F68: =cap_mu_28 -> 60 | G68: =cap_mu_29 -> 60
A69: 三星記憶體資本支出（美元） | B69: $B | C69: =cap_ssds_25*ss_mem*1000/fx -> 25.088028 | D69: =cap_ss_26*1000/fx -> 36.971831 | E69: =cap_ss_27*1000/fx -> 42.253521 | F69: =cap_ss_28*1000/fx -> 46.478873 | G69: =cap_ss_29*1000/fx -> 46.478873 | H69: 2025＝DS 47.5 兆 × 記憶體占比（Assumed）
A70: 三家資本支出合計 | B70: $B | C70: =C67+C68+C69 -> 60.155634 | D70: =D67+D68+D69 -> 98.634606 | E70: =E67+E68+E69 -> 141.12676 | F70: =F67+F68+F69 -> 156.61972 | G70: =G67+G68+G69 -> 159.29577
A72: 2c. 校準（只用 2025 實績）：SK 海力士、三星共用一個設備占比，使 2025 年各廠設備加總＝SEMI 2025 DRAM＋NAND
A73: SEMI 2025 DRAM＋NAND 設備（實績） | B73: $B | C73: =C41+C42 -> 38.548711
A74: 減：美光 2025 設備（資本支出 × sh_mu_25） | B74: $B | C74: =C68*sh_mu_25 -> 8.832
A75: 減：其他記憶體廠 2025 設備（獨立估計） | B75: $B | C75: =C64 -> 8.6038985
A76: ＝SK 海力士＋三星 2025 設備（校準目標） | B76: $B | C76: =C73-C74-C75 -> 21.112813
A77: ÷ SK 海力士＋三星 2025 資本支出 | B77: $B | C77: =C67+C69 -> 46.355634
A78: 校準值：SK 海力士、三星設備占比（Derived；2026 年以後沿用） | B78: % | C78: =C76/C77 -> 0.455453 | H78: 用公式算出；In 頁 sh_sk、sh_ss 基準取此值
A79: 低：長鑫取高值（In 高）時的校準值 | B79: % | C79: =(C73-(C57-C54+ind_cxmt_hi+C61)*sh_oth-C74)/C77 -> 0.38504085
A80: 高：業界下限（sh_oth 低） | B80: % | C80: =sh_oth_lo -> 0.58
A81: 對照：業界值（sh_oth 基準，不再當基準） | B81: % | C81: =sh_oth -> 0.64
A83: 2d. 各廠設備與合計
A84: SK 海力士設備＝資本支出 × sh_sk | B84: $B | C84: =C67*sh_sk -> 9.6863949 | D84: =D67*sh_sk -> 15.620114 | E84: =E67*sh_sk -> 19.982199 | F84: =F67*sh_sk -> 22.836798 | G84: =G67*sh_sk -> 24.055616
A85: 美光設備＝資本支出 × sh_mu（FY25／FY26／FY27–29） | B85: $B | C85: =C68*sh_mu_25 -> 8.832 | D85: =D68*sh_mu_26 -> 14.258207 | E85: =E68*sh_mu_27 -> 25.3 | F85: =F68*sh_mu_27 -> 27.6 | G85: =G68*sh_mu_27 -> 27.6
A86: 三星記憶體設備＝資本支出 × sh_ss | B86: $B | C86: =C69*sh_ss -> 11.426418 | D86: =D69*sh_ss -> 16.838931 | E86: =E69*sh_ss -> 19.244493 | F86: =F69*sh_ss -> 21.168942 | G86: =G69*sh_ss -> 21.168942
A87: 三家設備合計 | B87: $B | C87: =C84+C85+C86 -> 29.944813 | D87: =D84+D85+D86 -> 46.717252 | E87: =E84+E85+E86 -> 64.526692 | F87: =F84+F85+F86 -> 71.605741 | G87: =G84+G85+G86 -> 72.824559
A88: 三家加權設備占比 | B88: % | C88: =C87/C70 -> 0.497789 | D88: =D87/D70 -> 0.47363957 | E88: =E87/E70 -> 0.45722506 | F88: =F87/F70 -> 0.45719493 | G88: =G87/G70 -> 0.45716567
A89: 其中 DRAM（× 2025 年 DRAM 占比） | B89: $B | C89: =C87*C49 -> 21.683464 | D89: =D87*D49 -> 33.828626 | E89: =E87*E49 -> 46.724694 | F89: =F87*F49 -> 51.850734 | G89: =G87*G49 -> 52.733297 | H89: 2025 年 DRAM／NAND 拆分為近似（以 SEMI 2025 比例拆三家），合計不受影響
A90: 其中 NAND | B90: $B | C90: =C87-C89 -> 8.2613486 | D90: =D87-D89 -> 12.888627 | E90: =E87-E89 -> 17.801998 | F90: =F87-F89 -> 19.755007 | G90: =G87-G89 -> 20.091262
A91: 其他 DRAM 廠設備（2025＝獨立估計；2026 起 × (1＋g_oth_dram)） | B91: $B | C91: =C62 -> 4.6926452 | D91: =C91*(1+g_oth_dram) -> 5.5373213 | E91: =D91*(1+g_oth_dram) -> 6.5340391 | F91: =E91*(1+g_oth_dram) -> 7.7101662 | G91: =F91*(1+g_oth_dram) -> 9.0979961
A92: 其他 NAND 廠設備（2025＝獨立估計；2026 起 × (1＋g_oth_nand)） | B92: $B | C92: =C63 -> 3.9112533 | D92: =C92*(1+g_oth_nand) -> 4.6152789 | E92: =D92*(1+g_oth_nand) -> 5.4460291 | F92: =E92*(1+g_oth_nand) -> 6.4263144 | G92: =F92*(1+g_oth_nand) -> 7.583051
A93: 記憶體設備合計＝三家＋其他 | B93: $B | C93: =C87+C91+C92 -> 38.548711 | D93: =D87+D91+D92 -> 56.869852 | E93: =E87+E91+E92 -> 76.50676 | F93: =F87+F91+F92 -> 85.742221 | G93: =G87+G91+G92 -> 89.505606
A94: 核對：2025 記憶體合計 − SEMI 實績（應為 0） | B94: $B | C94: =C93-C73 -> 0
A95: 診斷：記憶體合計 − SEMI DRAM＋NAND | B95: $B | C95: =C93-C41-C42 -> 0 | D95: =D93-D41-D42 -> 4.1698523 | E95: =E93-E41-E42 -> 8.8526601 | F95: =F93-F41-F42 -> 8.031121 | G95: =G93-G41-G42 -> 5.5776173 | H95: 診斷值（不是輸入）：2026 起正＝本模型高於 SEMI；2025 為 0（校準）
A97: 3. 代工與邏輯晶圓前段設備（2025：台積電由下而上＋SEMI 殘差求其他廠基準；2026 起：其他廠＝基準 × 成長率）
A98: 台積電資本支出 | B98: $B | C98: =cap_ts_25 -> 40.9 | D98: =cap_ts_26 -> 62 | E98: =cap_ts_27 -> 77 | F98: =cap_ts_28 -> 90 | G98: =cap_ts_29 -> 95
A99: 台積電設備＝資本支出 × sh_fd | B99: $B | C99: =C98*sh_fd -> 26.176 | D99: =D98*sh_fd -> 39.68 | E99: =E98*sh_fd -> 49.28 | F99: =F98*sh_fd -> 57.6 | G99: =G98*sh_fd -> 60.8 | H99: v0.1.2：sh_fd 基準 64% 維持（Analogy），區間改 50–75%；證據與可識別性見 TSMC 頁。未另扣先進封裝／光罩（10–20%），上限影響見 Sens
A100: 2025 殘差：其他代工邏輯＝SEMI 代工邏輯 − 台積電設備（照實顯示） | B100: $B | C100: =C43-C99 -> 39.425346 | H100: Derived：三星晶圓代工、Intel、中芯等。v0.1.2：此殘差無法拆成『台積電占比』與『未列名其他廠』（TSMC 頁可識別性檢查：需 X＝18–30 的未列名設備），所以台積電占比不由 SEMI 校準
A101: 其他代工與邏輯設備（基準＝MAX(殘差, 0)；2026 起 × (1＋g_oth_fd)） | B101: $B | C101: =MAX(C100,0) -> 39.425346 | D101: =C101*(1+g_oth_fd) -> 42.579373 | E101: =D101*(1+g_oth_fd) -> 45.985723 | F101: =E101*(1+g_oth_fd) -> 49.664581 | G101: =F101*(1+g_oth_fd) -> 53.637748
A102: 代工與邏輯設備合計 | B102: $B | C102: =C99+C101 -> 65.601346 | D102: =D99+D101 -> 82.259373 | E102: =E99+E101 -> 95.265723 | F102: =F99+F101 -> 107.26458 | G102: =G99+G101 -> 114.43775
A103: 診斷：代工邏輯合計 − SEMI 代工邏輯 | B103: $B | C103: =C102-C43 -> 0 | D103: =D102-D43 -> 4.2593733 | E103: =E102-E43 -> 3.1477232 | F103: =F102-F43 -> 2.618533 | G103: =G102-G43 -> 1.4200157
A105: 3b. 其他前段（類比、功率、光罩、廠務等）：維持 2025 年占（記憶體＋代工邏輯）的比例
A106: 其他前段設備 | B106: $B | C106: =C47 -> 12.746775 | D106: =D50*(D93+D102) -> 17.027825 | E106: =E50*(E93+E102) -> 21.022986 | F106: =F50*(F93+F102) -> 23.621824 | G106: =G50*(G93+G102) -> 24.960332 | H106: 2025＝SEMI 差額；2026 起＝比例 × 本模型（記憶體＋代工邏輯）
A108: 3c. 診斷：三大廠隱含設備占比（2025）
A109: 三大廠隱含設備占比（獨立估計）＝(SEMI − 其他廠獨立估計) ÷ 三大廠資本支出 | B109: % | C109: =(C73-C64)/C70 -> 0.497789 | H109: ＝三家加權設備占比（校準恆等）
A110: 其中 SK 海力士、三星校準值 | B110: % | C110: =C78 -> 0.455453
A111: 對照：業界值 sh_oth（Sens 保留 64% 對照列） | B111: % | C111: =C81 -> 0.64
A112: 旗標：校準值低於業界下限 58%（1＝是） | C112: =IF(C78<sh_oth_lo,1,0) -> 1 | H112: 低於下限＝SK 海力士、三星資本支出中建築與無塵室比重高於業界值（與美光「增量多數為建築」方向一致，非證明）
A114: 4. 測試與封裝設備（v0.1 以 SEMI 金額為輸入，不做由下而上）
A115: 為何不由下而上：需要「每顆加速器的測試時間（最終測試、燒機 burn-in、系統級測試 SLT 的小時數）」與「每條 CoWoS／HBM 堆疊產線的鍵合機台數」，兩者公開資料皆未找到（Hanmi 等僅有訂單，無台數與產能對照）；以 SEMI 為輸入、並標明為單一來源。
A116: 測試設備 | B116: $B | C116: =C45 -> 11.679389 | D116: =D45 -> 15.3 | E116: =E45 -> 17.839282 | F116: =F45 -> 20.8 | G116: =G45 -> 22.464
A117: 組裝與封裝設備 | B117: $B | C117: =C46 -> 6.1131387 | D117: =D46 -> 6.7 | E117: =E46 -> 7.5907839 | F117: =F46 -> 8.6 | G117: =G46 -> 9.288
A119: 5A. 情境 A：由下而上路徑（資本支出沿用記憶體與台積電模型；其他廠沿 SEMI；2029 沿 g29）
A120: 先進邏輯（台積電設備＋其他代工中屬先進者）〔AI〕 | B120: $B | C120: =C99+adv_other*C101 -> 36.032336 | D120: =D99+adv_other*D101 -> 50.324843 | E120: =E99+adv_other*E101 -> 60.776431 | F120: =F99+adv_other*F101 -> 70.016145 | G120: =G99+adv_other*G101 -> 74.209437
...

Sheet TSMC
A1: TSMC — 台積電設備占資本支出：證據、可識別性、先進封裝／光罩重疊（v0.1.2）。金額：百萬美元（除另註）。藍字＝本頁輸入
A2: 年報／20-F「不動產、廠房及設備」附註的分類增添（房屋及建築、機器設備、待驗設備及未完工程）：未找到——本環境無法開啟年報與 SEC 原文，只能讀搜尋摘錄；該附註公司有揭露，屬檢索缺口，不是公司不揭露。以下改用董事會每季「資本預算」分項（核准額，不是實際支出）；各次分項來自二手摘要，三項加總與公司公告總額相符（核對欄）。
A4: 董事會日期 | B4: 機器設備：先進製程 | C4: 機器設備：先進封裝／成熟／特殊 | D4: 不動產與資本化租賃資產 | E4: 三項合計 | F4: 公司公告總額 | G4: 合計−公告 | H4: 設備占比 | I4: 來源1 | J4: 來源2／備註 | K4: 標記
A5: 2025-05-13 | B5: 9590 | C5: 308 | D5: 5350 | E5: =SUM(B5:D5) -> 15248 | F5: 15247 | G5: =E5-F5 -> 1 | H5: =(B5+C5)/E5 -> 0.64913431 | I5: Investing.com 6-K 摘要（2025-06-25）https://www.investing.com/news/sec-filings/tsmc-reports-board-share-changes-and-new-capital-spending-approvals-93CH-4110161 | J5: 總額：Focus Taiwan https://focustaiwan.tw/business/202505130022；Tom's Hardware 逐季 15.247 | K5: Interested-party（台積電揭露；二手摘要，合計與公告總額核對）
A6: 2025-08-12 | B6: 7800 | C6: 2000 | D6: 10900 | E6: =SUM(B6:D6) -> 20700 | F6: 20657 | G6: =E6-F6 -> 43 | H6: =(B6+C6)/E6 -> 0.47342995 | I6: Panabee 摘要（只到 0.1B）https://www.panabee.com/news/tsmc-commits-us-20-7-billion-to-bolster-advanced-tech-and-manufacturing-capacity | J6: 總額：Tom's Hardware 逐季 20.657；公司 6-K 原文分項：未能開啟核對 | K6: Interested-party（台積電揭露；二手摘要，合計與公告總額核對）
A7: 2026-02-10 | B7: 18921 | C7: 4670 | D7: 21372 | E7: =SUM(B7:D7) -> 44963 | F7: 44962 | G7: =E7-F7 -> 1 | H7: =(B7+C7)/E7 -> 0.52467584 | I7: Investing.com 6-K 摘要 https://www.investing.com/news/sec-filings/tsmc-reports-board-shareholding-changes-and-major-capital-approvals-for-february-93CH-4579333 | J7: 總額：Taipei Times https://www.taipeitimes.com/News/biz/archives/2026/02/11/2003852112；TipRanks 同分項。公司新聞稿決議文只列用途與總額，分項見於 6-K 摘要 | K7: Interested-party（台積電揭露；二手摘要，合計與公告總額核對）
A8: 2026-05-12 | B8: 21013 | C8: 0 | D8: 10271 | E8: =SUM(B8:D8) -> 31284 | F8: 31284 | G8: =E8-F8 -> 0 | H8: =(B8+C8)/E8 -> 0.67168521 | I8: TipRanks 摘要 https://www.tipranks.com/news/company-announcements/tsmc-details-heavy-capex-bond-issuance-and-share-capital-reduction-for-may-2026 | J8: 總額：Focus Taiwan https://focustaiwan.tw/business/202605120026；摘要只列兩項，封裝等機器設備未單獨列（可能併入先進製程） | K8: Interested-party（台積電揭露；二手摘要，合計與公告總額核對）
A9: 2026-08 | B9: 16035 | C9: 4791 | D9: 8616 | E9: =SUM(B9:D9) -> 29442 | F9: 29442.5 | G9: =E9-F9 -> -0.5 | H9: =(B9+C9)/E9 -> 0.70735684 | I9: Stocktitan 6-K 摘要 https://www.stocktitan.net/sec-filings/TSM/6-k-taiwan-semiconductor-manufacturing-co-ltd-current-report-foreign--efeb868a1401.html | J9: 總額：Focus Taiwan https://focustaiwan.tw/business/202608110015（29.44B）；SEC 檔 tsm-monthend6kx20260924（搜尋結果列出，未開啟） | K9: Interested-party（台積電揭露；二手摘要，合計與公告總額核對）
A10: 2025 兩次合計（5、8 月） | B10: =SUM(B5:B6) -> 17390 | C10: =SUM(C5:C6) -> 2308 | D10: =SUM(D5:D6) -> 16250 | E10: =SUM(E5:E6) -> 35948 | F10: =SUM(F5:F6) -> 35904 | H10: =(B10+C10)/E10 -> 0.54795816 | K10: Derived
A11: 2026 三次合計 | B11: =SUM(B7:B9) -> 55969 | C11: =SUM(C7:C9) -> 9461 | D11: =SUM(D7:D9) -> 40259 | E11: =SUM(E7:E9) -> 105689 | F11: =SUM(F7:F9) -> 105688.5 | H11: =(B11+C11)/E11 -> 0.61908051 | K11: Derived
A12: 五次合計 | B12: =SUM(B5:B9) -> 73359 | C12: =SUM(C5:C9) -> 11769 | D12: =SUM(D5:D9) -> 56509 | E12: =SUM(E5:E9) -> 141637 | F12: =SUM(F5:F9) -> 141592.5 | H12: =(B12+C12)/E12 -> 0.60102939 | K12: Derived
A13: 單次最低／最高設備占比 | H13: =MIN(H5:H9) -> 0.47342995 | I13: =MAX(H5:H9) -> 0.70735684
A14: 怎麼讀：(1) 這是核准額，不是支出；核准在前、多年執行，且「資本化租賃資產」含非現金項目（2025 年四次核准合計 68.0B，現金資本支出 40.9B）。(2) 建廠先於裝機，擴廠加速期的不動產占比會領先實際支出占比。(3) SEMI 的 WFE 含「廠務設備」（Fab Facilities），台積電『不動產與廠務系統』裡的廠務機電部分在 SEMI 口徑可能算設備，所以和 SEMI 可比的設備占比 ≥ 本欄。(4) 2025 年只有 2 次、2026 年 3 次找到分項；2025-02、2025-11 與 2021–2024 各次：只找到總額（下表），分項未找到。
A16: 只找到總額的董事會核准（分項未找到） | B16: 核准總額 US$M | I16: 來源 | J16: 備註 | K16: 標記
A17: 2025-02-12 | B17: 17141.4 | I17: TSMC 決議新聞稿 https://pr.tsmc.com/english/news/3207 | K17: Verified（公司公告總額；搜尋摘錄）
A18: 2025-11-11 | B18: 14981 | I18: Tom's Hardware 逐季；Tribune https://www.tribuneindia.com/news/business/tsmc-approved-a-capital-appropriation-plan-of-usd-14-98-bn-company-also-raised-dividend-payout/amp | J18: 此次含 2026 年研發與經常性資本預算、資本化租賃資產 | K18: Verified（公司公告總額；搜尋摘錄）
A19: 2024-02 | B19: 9421.48 | I19: 搜尋摘要（TSMC 決議） | J19: 含資本化租賃資產 | K19: Verified（公司公告總額；搜尋摘錄）
A20: 2024-06-05 | B20: 17356.2 | I20: TSMC 決議 https://pr.tsmc.com/system/files/newspdf/attachment/4f8848e007a8291ca9e5e720193efebc599d0a9e/0605%20board%20meeting%20(E)_final_wmn.pdf | K20: Verified（公司公告總額；搜尋摘錄）
A21: 2024-08-13 | B21: 29615.47 | I21: MarketScreener 6-K 標題頁 | K21: Verified（公司公告總額；搜尋摘錄）
A22: 2024-11-12 | B22: 15479.95 | I22: SEC 6-K https://www.sec.gov/Archives/edgar/data/1046179/000104617924000124/tsm-boardx20241112x6k.htm | K22: Verified（公司公告總額；搜尋摘錄）
A23: 2023-02-14 | B23: 6959.5 | I23: SEC 6-K https://www.sec.gov/Archives/edgar/data/1046179/000156459023001822/tsm-6k_20230214.htm | K23: Verified（公司公告總額；搜尋摘錄）
A24: 2023-05-09 | B24: 366.1 | I24: 搜尋摘要（SEC 6-K） | J24: 僅廠房建設 | K24: Verified（公司公告總額；搜尋摘錄）
A25: 2023-08-08 | B25: 6059.5 | I25: SEC 6-K https://www.sec.gov/Archives/edgar/data/1046179/000162828023027944/tsm-boardx20230808x6k.htm | J25: 2023-11 一次：未找到 | K25: Verified（公司公告總額；搜尋摘錄）
A26: 2022 全年 | B26: 20944.17 | I26: TSMC 2022 年報 https://investor.tsmc.com/sites/ir/annual-report/2022/2022%20Annual%20Report-E.pdf（搜尋摘錄） | J26: 2022-12 摘錄顯示「不動產與資本化租賃資產」曾單列約 1.1B，其餘分項未找到 | K26: Verified（公司公告總額；搜尋摘錄）
A27: 2021-06 | B27: 9290 | I27: Focus Taiwan https://focustaiwan.tw/business/202106100005 | J27: 2021 其他季：未找到 | K27: Verified（公司公告總額；搜尋摘錄）
A29: 現金資本支出（取得不動產、廠房及設備）
A30: 年度 | B30: 新台幣百萬元 | C30: 美元百萬元 | I30: 來源 | J30: 備註 | K30: 標記
A31: 2021 | I31: 未找到（本次搜尋未取得 2021 年數字） | K31: 未找到
A32: 2022 | B32: 1082672 | I32: TSMC 2024 20-F 搜尋摘錄（2022–2024 資本支出）https://investor.tsmc.com/sites/ir/sec-filings/2024%2020-F.pdf | K32: Verified（現金流量表金額）
A33: 2023 | B33: 949817 | I33: 同上 | K33: Verified（現金流量表金額）
A34: 2024 | B34: 956007 | C34: 29755 | I34: 同上；4Q24 Management Report 29.76B | J34: 美元為公司換算 | K34: Verified（現金流量表金額）
A35: 2025 | B35: 1272410.5 | C35: 40900 | I35: Stocktitan 2025 年報 6-K 摘要（PP&E 增添 1,272,410,529 千元）；美元 40.9B：Semiconductor Intelligence https://www.semiconductorintelligence.com/capex-up-for-foundry-memory/ | J35: 新台幣為二手摘要，未開原文 | K35: Verified（現金流量表金額）
A37: 其他證據與業界值
A38: 項目 | B38: 低 | C38: 基準／中 | D38: 高 | I38: 來源 | J38: 備註 | K38: 標記
A39: 元大投顧：先進製程外商前段設備占資本支出 | B39: 0.7 | D39: 0.8 | I39: 自由財經／財富自由（2026-01 法說後）https://stock.ltn.com.tw/article/70szg3dsjge2 | J39: 媒體轉述，原報告全文未找到；只含外商主導的前段設備、限先進製程；投顧報告以設備供應鏈受惠股為主題，立場偏多 | K39: Interested-party（元大投顧）
A40: 業界值：SEMI 2025 WFE ÷ 全球資本支出 | B40: 0.58 | C40: 0.64 | D40: 0.7 | I40: 見 In 頁 SH_SRC1／SH_SRC2（SEMI；Semiconductor Intelligence；Rebound Capital） | J40: 業界合計，非台積電 | K40: Analogy（全產業，差異：含記憶體與 IDM）
A41: SK 海力士、三星校準值（對照） | B41: 0.385 | C41: =sh_sk -> 0.455453 | D41: 0.58 | I41: Mkt 2c | J41: Derived，記憶體廠；用來問「台積電是否也同樣偏低」 | K41: Derived
A43: 可識別性：能不能用 SEMI 2025 代工邏輯實績校準台積電的設備占比？（比照 SK＋三星，但其他廠無法獨立估計）
A44: SEMI 2025 代工與邏輯設備（實績） | B44: =Mkt!C43 -> 65.601346 | C44: $B | J44: In 頁／Mkt 1
A45: 台積電 2025 資本支出 | B45: =cap_ts_25 -> 40.9 | C45: $B | J45: In
A46: 已知其他廠 2025 資本支出：中芯＋Intel（毛額） | B46: =cap_smic_25+cap_intel_25 -> 25.8 | C46: $B | J46: 僅此二家有數字；三星晶圓代工（報導約 5 兆韓元，未核對）、聯電（資料站約 1.5B，弱）、GlobalFoundries、華虹、力積電、世界先進、Rapidus、中國未上市廠：未找到可用的 2025 資本支出
A47: 已知其他廠設備（× 業界值 64%） | B47: =B46*sh_oth -> 16.512 | C47: $B | J47: Analogy：假設同業界值；Intel 含大量建廠，可能偏高
A48: 假設台積電設備占比 s | B48: 台積電設備 | C48: 需要的『未列名其他廠設備』X＝SEMI−台積電−已知其他廠 | D48: X 占 SEMI 代工邏輯 | J48: 說明
A49: =sh_fd_lo -> 0.5 | B49: =B45*A49 -> 20.45 | C49: =B44-B49-B47 -> 28.639346 | D49: =C49/B44 -> 0.43656644
A50: =sh_fd -> 0.64 | B50: =B45*A50 -> 26.176 | C50: =B44-B50-B47 -> 22.913346 | D50: =C50/B44 -> 0.34928164
A51: =sh_fd_hi -> 0.75 | B51: =B45*A51 -> 30.675 | C51: =B44-B51-B47 -> 18.414346 | D51: =C51/B44 -> 0.28070073
A52: =sh_sk -> 0.455453 | B52: =B45*A52 -> 18.628028 | C52: =B44-B52-B47 -> 30.461318 | D52: =C52/B44 -> 0.46433983
A53: s 的上限情況：X＝0 時隱含的 s | B53: =(B44-B47)/B45 -> 1.2002285 | J53: 超過 100% 不可能：SEMI 代工邏輯設備出貨，大於「台積電全部資本支出＋已知其他廠 × 64%」。
A54: 結論：不論 s 取 45.5%、64% 或 75%，都需要 X＝約 18–30 十億美元（占 SEMI 代工邏輯 28–46%）的『未列名其他廠設備』才能湊成 SEMI 實績，而這個 X 沒有任何獨立估計（未找到）。因此與 SK＋三星不同：記憶體校準有 SEMI 實績＋美光（一手揭露）＋其他廠獨立估計三個已知量，只剩一個未知數；代工邏輯是『台積電 s』與『X』兩個未知數、一條方程式，不可識別。SEMI 實績只約束 s×台積電資本支出＋其他廠＝65.6，s 由其他證據決定。可能的來源：SEMI 計設備出貨、資本支出是現金支出（時差，見限制 5）；中國未上市晶圓廠與口徑差異；本表已知其他廠的資本支出不全。
A56: 先進封裝、測試、光罩與 SEMI 分類的重疊
A57: 公司稱用於先進封裝、測試、光罩及其他（pk_ts） | B57: =pk_ts_lo -> 0.1 | C57: =pk_ts -> 0.15 | D57: =pk_ts_hi -> 0.2
A58: 2026 台積電資本支出（Mkt，三情境相同） | B58: =Mkt!D98 -> 62 | C58: =Mkt!D98 -> 62 | D58: =Mkt!D98 -> 62
A59: 該類資本支出 × 設備占比 sh_fd（若全部被 SEMI 分入後段或其他前段） | B59: =B58*B57*sh_fd -> 3.968 | C59: =C58*C57*sh_fd -> 5.952 | D59: =D58*D57*sh_fd -> 7.936
A60: 占情境 A 2026 設備總額 | B60: =B59/Mkt!D129 -> 0.022272484 | C60: =C59/Mkt!D129 -> 0.033408726 | D60: =D59/Mkt!D129 -> 0.044544967
A61: 判斷：SEMI 的口徑——總設備＝WFE（晶圓處理、光罩、廠務）＋測試＋組裝封裝（來源：SEMI 簡報定義，搜尋摘錄）；台積電的先進封裝（CoWoS 等）設備應落在 SEMI『組裝與封裝』或『測試』，光罩設備落在 WFE 的光罩項（本模型的『其他前段』），而本模型把台積電全部資本支出 × 設備占比放進『代工邏輯』，另外再以 SEMI 金額加入測試與封裝——所以有重疊的可能，上表是上限（10–20% 內含測試、光罩與『其他』，且部分封裝用的蝕刻、沉積、微影設備 SEMI 可能算在 WFE）。2025 年因代工邏輯由 SEMI 殘差補平，重疊不影響總額；2026 年以後台積電成長（+52%）遠高於其他廠（+8%），重疊使總額高估；直接扣除為 2026 年設備總額的 2.2–4.5%（上表），但因 2025 殘差補平，Sens 的淨影響較小：情境 A 2026–2029 約 −1.1% 至 −2.2%（扣 15%／20%）。SEMI 是否把 CoWoS 前段工序算在 WFE：未找到。base 不扣，理由：重疊程度無法識別，且扣除方向會被『未列名其他廠』的校準殘差吸收。

Sheet Recon
A1: Recon — 本模型與外部來源對帳。不為對上來源而調整參數；差距 > 15% 的原因見 README。模型欄＝晶圓前段設備（除非另註）；來源口徑各異（SEMI WFE、分析師 WFE、KLA 含先進封裝）
A3: 項目 | B3: 年度 | C3: 來源 | D3: 來源值 | E3: 模型 A | F3: 差距 A | G3: 模型 B | H3: 差距 B | I3: 模型 C | J3: 差距 C | K3: A 差距 > 門檻 | L3: 口徑備註
A4: 設備合計 | B4: 2026 | C4: SEMI 2026-07 | D4: =s_tot_26 -> 165.9 | E4: =Mkt!D129 -> 178.15705 | F4: =E4/D4-1 -> 0.073882161 | G4: =Mkt!D148 -> 178.15705 | H4: =G4/D4-1 -> 0.073882161 | I4: =Mkt!D167 -> 178.15705 | J4: =I4/D4-1 -> 0.073882161 | K4: =IF(ABS(F4)>rc_thr,"超過門檻","") | L4: SEMI 公布 165.9
A5: 晶圓前段 | B5: 2026 | C5: SEMI 2026-07 | D5: =s_wfe_26 -> 143.9 | E5: =Mkt!D127 -> 156.15705 | F5: =E5/D5-1 -> 0.085177558 | G5: =Mkt!D146 -> 156.15705 | H5: =G5/D5-1 -> 0.085177558 | I5: =Mkt!D165 -> 156.15705 | J5: =I5/D5-1 -> 0.085177558 | K5: =IF(ABS(F5)>rc_thr,"超過門檻","")
A6: 代工與邏輯 | B6: 2026 | C6: SEMI 2026-07 | D6: =s_fd_26 -> 78 | E6: =Mkt!D120+Mkt!D121 -> 82.259373 | F6: =E6/D6-1 -> 0.05460735 | G6: =Mkt!D139+Mkt!D140 -> 82.259373 | H6: =G6/D6-1 -> 0.05460735 | I6: =Mkt!D158+Mkt!D159 -> 82.259373 | J6: =I6/D6-1 -> 0.05460735 | K6: =IF(ABS(F6)>rc_thr,"超過門檻","") | L6: 模型＝代工邏輯設備合計（台積電由下而上＋其他殘差）
A7: DRAM | B7: 2026 | C7: SEMI 2026-07 | D7: =s_dram_26 -> 38.8 | E7: =Mkt!D122 -> 39.365947 | F7: =E7/D7-1 -> 0.014586258 | G7: =Mkt!D141 -> 39.365947 | H7: =G7/D7-1 -> 0.014586258 | I7: =Mkt!D160 -> 39.365947 | J7: =I7/D7-1 -> 0.014586258 | K7: =IF(ABS(F7)>rc_thr,"超過門檻","") | L7: 模型記憶體設備 × SEMI DRAM 占比
A8: NAND | B8: 2026 | C8: SEMI 2026-07 | D8: =s_nand_26 -> 13.9 | E8: =Mkt!D123 -> 17.503905 | F8: =E8/D8-1 -> 0.25927377 | G8: =Mkt!D142 -> 17.503905 | H8: =G8/D8-1 -> 0.25927377 | I8: =Mkt!D161 -> 17.503905 | J8: =I8/D8-1 -> 0.25927377 | K8: =IF(ABS(F8)>rc_thr,"超過門檻","") -> 超過門檻
A9: 晶圓前段年增 | B9: 2027 | C9: SEMI 2026-07（+21.8%） | D9: =g_wfe_27 -> 0.218 | E9: =Mkt!E131 -> 0.23462545 | F9: =E9-D9 -> 0.016625454 | G9: =Mkt!E150 -> 0.23462545 | H9: =G9-D9 -> 0.016625454 | I9: =Mkt!E169 -> 0.23462545 | J9: =I9-D9 -> 0.016625454 | K9: =IF(ABS(F9)>0.05,"超過 5 個百分點","") | L9: 年增率之差以百分點計
A10: 晶圓前段 | B10: 2027 | C10: SEMI 2026-07（由 2026 值連乘年增） | D10: =Mkt!E44 -> 175.2702 | E10: =Mkt!E127 -> 192.79547 | F10: =E10/D10-1 -> 0.099990012 | G10: =Mkt!E146 -> 192.79547 | H10: =G10/D10-1 -> 0.099990012 | I10: =Mkt!E165 -> 192.79547 | J10: =I10/D10-1 -> 0.099990012 | K10: =IF(ABS(F10)>rc_thr,"超過門檻","") | L10: SEMI 2027 絕對金額為推得（143.9×1.218）
A11: 晶圓前段 | B11: 2028 | C11: SEMI 2026-07（連乘） | D11: =Mkt!F44 -> 199.9833 | E11: =Mkt!F127 -> 216.62863 | F11: =E11/D11-1 -> 0.083233591 | G11: =Mkt!F146 -> 192.79547 | H11: =G11/D11-1 -> -0.035942146 | I11: =Mkt!F165 -> 154.23638 | J11: =I11/D11-1 -> -0.22875372 | K11: =IF(ABS(F11)>rc_thr,"超過門檻","") | L11: 新聞稿稱「達 200B」
A12: 設備合計 | B12: 2028 | C12: SEMI 2026-07 | D12: =s_tot_28 -> 229.5 | E12: =Mkt!F129 -> 246.02863 | F12: =E12/D12-1 -> 0.072020158 | G12: =Mkt!F148 -> 218.22554 | H12: =G12/D12-1 -> -0.049126206 | I12: =Mkt!F167 -> 174.58043 | J12: =I12/D12-1 -> -0.23930096 | K12: =IF(ABS(F12)>rc_thr,"超過門檻","") | L12: 公布 229.5；分項加總 229.4
A13: 晶圓前段 | B13: 2026 | C13: Lam Research（低 150B） | D13: =rc_lam26 -> 150 | E13: =Mkt!D127 -> 156.15705 | F13: =E13/D13-1 -> 0.041047004 | G13: =Mkt!D146 -> 156.15705 | H13: =G13/D13-1 -> 0.041047004 | I13: =Mkt!D165 -> 156.15705 | J13: =I13/D13-1 -> 0.041047004 | K13: =IF(ABS(F13)>rc_thr,"超過門檻","") | L13: Lam 2026-10 法說另稱 mid-150
A14: 晶圓前段 | B14: 2026 | C14: KLA（低 150B；含先進封裝） | D14: =rc_kla26 -> 150 | E14: =Mkt!D127 -> 156.15705 | F14: =E14/D14-1 -> 0.041047004 | G14: =Mkt!D146 -> 156.15705 | H14: =G14/D14-1 -> 0.041047004 | I14: =Mkt!D165 -> 156.15705 | J14: =I14/D14-1 -> 0.041047004 | K14: =IF(ABS(F14)>rc_thr,"超過門檻","") | L14: KLA 口徑含先進封裝，2025 基準約 120 vs SEMI 116.9
A15: 晶圓前段 | B15: 2027 | C15: KLA 規劃（約 190B） | D15: =rc_kla27 -> 190 | E15: =Mkt!E127 -> 192.79547 | F15: =E15/D15-1 -> 0.014712997 | G15: =Mkt!E146 -> 192.79547 | H15: =G15/D15-1 -> 0.014712997 | I15: =Mkt!E165 -> 192.79547 | J15: =I15/D15-1 -> 0.014712997 | K15: =IF(ABS(F15)>rc_thr,"超過門檻","")
A16: 晶圓前段 | B16: 2027 | C16: Lam Research（>200B；額外對照） | D16: =rc_lam27 -> 200 | E16: =Mkt!E127 -> 192.79547 | F16: =E16/D16-1 -> -0.036022653 | G16: =Mkt!E146 -> 192.79547 | H16: =G16/D16-1 -> -0.036022653 | I16: =Mkt!E165 -> 192.79547 | J16: =I16/D16-1 -> -0.036022653 | K16: =IF(ABS(F16)>rc_thr,"超過門檻","") | L16: 取下限
A17: 晶圓前段 | B17: 2027 | C17: Morgan Stanley（itiger 二手轉述 https://www.itiger.com/news/2649678863） | D17: =rc_ms27 -> 202 | E17: =Mkt!E127 -> 192.79547 | F17: =E17/D17-1 -> -0.045566983 | G17: =Mkt!E146 -> 192.79547 | H17: =G17/D17-1 -> -0.045566983 | I17: =Mkt!E165 -> 192.79547 | J17: =I17/D17-1 -> -0.045566983 | K17: =IF(ABS(F17)>rc_thr,"超過門檻","") | L17: itiger 二手轉述（2026-07-06）：2027 由 191 上修到 202；連結見 In 頁
A18: 晶圓前段 | B18: 2028 | C18: Morgan Stanley（itiger 二手轉述 https://www.itiger.com/news/2649678863） | D18: =rc_ms28 -> 227 | E18: =Mkt!F127 -> 216.62863 | F18: =E18/D18-1 -> -0.045688871 | G18: =Mkt!F146 -> 192.79547 | H18: =G18/D18-1 -> -0.15068075 | I18: =Mkt!F165 -> 154.23638 | J18: =I18/D18-1 -> -0.3205446 | K18: =IF(ABS(F18)>rc_thr,"超過門檻","") | L18: itiger 二手轉述：2028 由 215 上修到 227
A19: 晶圓前段 | B19: 2026 | C19: Goldman Sachs | D19: =rc_gs26 -> 150 | E19: =Mkt!D127 -> 156.15705 | F19: =E19/D19-1 -> 0.041047004 | G19: =Mkt!D146 -> 156.15705 | H19: =G19/D19-1 -> 0.041047004 | I19: =Mkt!D165 -> 156.15705 | J19: =I19/D19-1 -> 0.041047004 | K19: =IF(ABS(F19)>rc_thr,"超過門檻","")
A20: 晶圓前段 | B20: 2027 | C20: Goldman Sachs | D20: =rc_gs27 -> 218 | E20: =Mkt!E127 -> 192.79547 | F20: =E20/D20-1 -> -0.11561711 | G20: =Mkt!E146 -> 192.79547 | H20: =G20/D20-1 -> -0.11561711 | I20: =Mkt!E165 -> 192.79547 | J20: =I20/D20-1 -> -0.11561711 | K20: =IF(ABS(F20)>rc_thr,"超過門檻","")
A21: 晶圓前段 | B21: 2028 | C21: Goldman Sachs | D21: =rc_gs28 -> 281 | E21: =Mkt!F127 -> 216.62863 | F21: =E21/D21-1 -> -0.22907962 | G21: =Mkt!F146 -> 192.79547 | H21: =G21/D21-1 -> -0.31389513 | I21: =Mkt!F165 -> 154.23638 | J21: =I21/D21-1 -> -0.4511161 | K21: =IF(ABS(F21)>rc_thr,"超過門檻","") -> 超過門檻
A23: 核對：SEMI 2026 分項加總
A24: DRAM＋NAND＋代工邏輯＋其他前段 − WFE | D24: =Mkt!D41+Mkt!D42+Mkt!D43+Mkt!D47-Mkt!D44 -> 0
A25: 注意：校準只用 2025 實績；2026 年以後 A 路徑的總額由下而上（其他廠＝2025 基準 × 成長率，Assumed），不由 SEMI 或券商預測決定（測試與封裝除外，v0.1 以 SEMI 為輸入），所以對 SEMI 與各來源的差距有意義。
A27: 台積電設備占比對帳（v0.1.2；不併入上方差距表，單位：占比，差距為百分點）
A28: 項目 | C28: 來源 | D28: 來源值 | E28: 模型 sh_fd 基準 | F28: 差距（模型−來源） | L28: 口徑備註
A29: 董事會資本預算：五次合計設備占比 | C29: 台積電 6-K 二手摘要（TSMC 頁） | D29: =TSMC!H12 -> 0.60102939 | E29: =sh_fd -> 0.64 | F29: =E29-D29 -> 0.038970608 | L29: 核准額，非支出；含資本化租賃資產；單次 47–71%
A30: 董事會資本預算：2025 兩次（5、8 月） | C30: 同上 | D30: =TSMC!H10 -> 0.54795816 | E30: =sh_fd -> 0.64 | F30: =E30-D30 -> 0.092041838 | L30: 只有 2 次找到分項；2025 全年支出占比：未找到
A31: 董事會資本預算：2026 三次（2、5、8 月） | C31: 同上 | D31: =TSMC!H11 -> 0.61908051 | E31: =sh_fd -> 0.64 | F31: =E31-D31 -> 0.02091949
A32: 元大投顧：先進製程外商前段設備（中點） | C32: 自由財經轉述（Interested-party） | D32: =AVERAGE(TSMC!B39,TSMC!D39) -> 0.75 | E32: =sh_fd -> 0.64 | F32: =E32-D32 -> -0.11 | L32: 只含外商前段設備、限先進製程
A33: 業界值（SEMI WFE ÷ 全球資本支出等） | C33: In 頁 sh_oth | D33: =sh_oth -> 0.64 | E33: =sh_fd -> 0.64 | F33: =E33-D33 -> 0 | L33: Analogy，模型基準的來源
A34: SK 海力士、三星校準值（對照，不是台積電的證據） | C34: Mkt 2c | D34: =sh_sk -> 0.455453 | E34: =sh_fd -> 0.64 | F34: =E34-D34 -> 0.184547 | L34: 記憶體廠，Derived

Sheet Sens
A1: Sens — 一次動一個輸入（低／高取 In 的區間）；輸出：情境 A 2027、2028、2029 設備總額（$B）。最後兩組列出「其他記憶體廠 2025 基準」若不為 0 對總額的影響（2025 殘差為負時基準取 0）
A3: 輸入 | B3: 2027 A | C3: 相對基準 | D3: 2028 A | E3: 相對基準 | F3: 2029 A | G3: 相對基準 | H3: 說明
A4: 基準（2025 實績校準） | B4: =((cap_sk_27*1000/fx*sh_sk+cap_mu_27*sh_mu_27+cap_ss_27*1000/fx*sh_ss)+(((Mkt!$C$57-Mkt!$C$54+ind_cxmt)*sh_oth))*(1+g_oth_dram)^2+((Mkt!$C$61*sh_oth))*(1+g_oth_nand)^2)+(cap_ts_27*(1-0)*sh_fd+MAX(Mkt!$C$43-cap_ts_25*(1-0)*sh_fd,0)*(1+g_oth_fd)^2)+Mkt!E50*(((cap_sk_27*1000/fx*sh_sk+cap_mu_27*sh_mu_27+cap_ss_27*1000/fx*sh_ss)+(((Mkt!$C$57-Mkt!$C$54+ind_cxmt)*sh_oth))*(1+g_oth_dram)^2+((Mkt!$C$61*sh_oth))*(1+g_oth_nand)^2)+(cap_ts_27*(1-0)*sh_fd+MAX(Mkt!$C$43-cap_ts_25*(1-0)*sh_fd,0)*(1+g_oth_fd)^2))+Mkt!E116+Mkt!E117 -> 218.22554 | C4: =B4/B$4-1 -> 0 | D4: =((cap_sk_28*1000/fx*sh_sk+cap_mu_28*sh_mu_27+cap_ss_28*1000/fx*sh_ss)+(((Mkt!$C$57-Mkt!$C$54+ind_cxmt)*sh_oth))*(1+g_oth_dram)^3+((Mkt!$C$61*sh_oth))*(1+g_oth_nand)^3)+(cap_ts_28*(1-0)*sh_fd+MAX(Mkt!$C$43-cap_ts_25*(1-0)*sh_fd,0)*(1+g_oth_fd)^3)+Mkt!F50*(((cap_sk_28*1000/fx*sh_sk+cap_mu_28*sh_mu_27+cap_ss_28*1000/fx*sh_ss)+(((Mkt!$C$57-Mkt!$C$54+ind_cxmt)*sh_oth))*(1+g_oth_dram)^3+((Mkt!$C$61*sh_oth))*(1+g_oth_nand)^3)+(cap_ts_28*(1-0)*sh_fd+MAX(Mkt!$C$43-cap_ts_25*(1-0)*sh_fd,0)*(1+g_oth_fd)^3))+Mkt!F116+Mkt!F117 -> 246.02863 | E4: =D4/D$4-1 -> 0 | F4: =((cap_sk_29*1000/fx*sh_sk+cap_mu_29*sh_mu_27+cap_ss_29*1000/fx*sh_ss)+(((Mkt!$C$57-Mkt!$C$54+ind_cxmt)*sh_oth))*(1+g_oth_dram)^4+((Mkt!$C$61*sh_oth))*(1+g_oth_nand)^4)+(cap_ts_29*(1-0)*sh_fd+MAX(Mkt!$C$43-cap_ts_25*(1-0)*sh_fd,0)*(1+g_oth_fd)^4)+Mkt!G50*(((cap_sk_29*1000/fx*sh_sk+cap_mu_29*sh_mu_27+cap_ss_29*1000/fx*sh_ss)+(((Mkt!$C$57-Mkt!$C$54+ind_cxmt)*sh_oth))*(1+g_oth_dram)^4+((Mkt!$C$61*sh_oth))*(1+g_oth_nand)^4)+(cap_ts_29*(1-0)*sh_fd+MAX(Mkt!$C$43-cap_ts_25*(1-0)*sh_fd,0)*(1+g_oth_fd)^4))+Mkt!G116+Mkt!G117 -> 260.65569 | G4: =F4/F$4-1 -> 0 | H4: 同 Mkt 情境 A（公式重算；核對列應為 0）
A5: SK 海力士＋三星設備占比 低（長鑫取 12.0 的校準值） | B5: =((cap_sk_27*1000/fx*sh_sk_lo+cap_mu_27*sh_mu_27+cap_ss_27*1000/fx*sh_ss_lo)+(((Mkt!$C$57-Mkt!$C$54+ind_cxmt_hi)*sh_oth))*(1+g_oth_dram)^2+((Mkt!$C$61*sh_oth))*(1+g_oth_nand)^2)+(cap_ts_27*(1-0)*sh_fd+MAX(Mkt!$C$43-cap_ts_25*(1-0)*sh_fd,0)*(1+g_oth_fd)^2)+Mkt!E50*(((cap_sk_27*1000/fx*sh_sk_lo+cap_mu_27*sh_mu_27+cap_ss_27*1000/fx*sh_ss_lo)+(((Mkt!$C$57-Mkt!$C$54+ind_cxmt_hi)*sh_oth))*(1+g_oth_dram)^2+((Mkt!$C$61*sh_oth))*(1+g_oth_nand)^2)+(cap_ts_27*(1-0)*sh_fd+MAX(Mkt!$C$43-cap_ts_25*(1-0)*sh_fd,0)*(1+g_oth_fd)^2))+Mkt!E116+Mkt!E117 -> 216.51998 | C5: =B5/B$4-1 -> -0.0078155653 | D5: =((cap_sk_28*1000/fx*sh_sk_lo+cap_mu_28*sh_mu_27+cap_ss_28*1000/fx*sh_ss_lo)+(((Mkt!$C$57-Mkt!$C$54+ind_cxmt_hi)*sh_oth))*(1+g_oth_dram)^3+((Mkt!$C$61*sh_oth))*(1+g_oth_nand)^3)+(cap_ts_28*(1-0)*sh_fd+MAX(Mkt!$C$43-cap_ts_25*(1-0)*sh_fd,0)*(1+g_oth_fd)^3)+Mkt!F50*(((cap_sk_28*1000/fx*sh_sk_lo+cap_mu_28*sh_mu_27+cap_ss_28*1000/fx*sh_ss_lo)+(((Mkt!$C$57-Mkt!$C$54+ind_cxmt_hi)*sh_oth))*(1+g_oth_dram)^3+((Mkt!$C$61*sh_oth))*(1+g_oth_nand)^3)+(cap_ts_28*(1-0)*sh_fd+MAX(Mkt!$C$43-cap_ts_25*(1-0)*sh_fd,0)*(1+g_oth_fd)^3))+Mkt!F116+Mkt!F117 -> 244.412 | E5: =D5/D$4-1 -> -0.0065708933 | F5: =((cap_sk_29*1000/fx*sh_sk_lo+cap_mu_29*sh_mu_27+cap_ss_29*1000/fx*sh_ss_lo)+(((Mkt!$C$57-Mkt!$C$54+ind_cxmt_hi)*sh_oth))*(1+g_oth_dram)^4+((Mkt!$C$61*sh_oth))*(1+g_oth_nand)^4)+(cap_ts_29*(1-0)*sh_fd+MAX(Mkt!$C$43-cap_ts_25*(1-0)*sh_fd,0)*(1+g_oth_fd)^4)+Mkt!G50*(((cap_sk_29*1000/fx*sh_sk_lo+cap_mu_29*sh_mu_27+cap_ss_29*1000/fx*sh_ss_lo)+(((Mkt!$C$57-Mkt!$C$54+ind_cxmt_hi)*sh_oth))*(1+g_oth_dram)^4+((Mkt!$C$61*sh_oth))*(1+g_oth_nand)^4)+(cap_ts_29*(1-0)*sh_fd+MAX(Mkt!$C$43-cap_ts_25*(1-0)*sh_fd,0)*(1+g_oth_fd)^4))+Mkt!G116+Mkt!G117 -> 259.91103 | G5: =F5/F$4-1 -> -0.0028568664
A6: SK 海力士＋三星設備占比 高（58%，業界下限） | B6: =((cap_sk_27*1000/fx*sh_sk_hi+cap_mu_27*sh_mu_27+cap_ss_27*1000/fx*sh_ss_hi)+(((Mkt!$C$57-Mkt!$C$54+ind_cxmt)*sh_oth))*(1+g_oth_dram)^2+((Mkt!$C$61*sh_oth))*(1+g_oth_nand)^2)+(cap_ts_27*(1-0)*sh_fd+MAX(Mkt!$C$43-cap_ts_25*(1-0)*sh_fd,0)*(1+g_oth_fd)^2)+Mkt!E50*(((cap_sk_27*1000/fx*sh_sk_hi+cap_mu_27*sh_mu_27+cap_ss_27*1000/fx*sh_ss_hi)+(((Mkt!$C$57-Mkt!$C$54+ind_cxmt)*sh_oth))*(1+g_oth_dram)^2+((Mkt!$C$61*sh_oth))*(1+g_oth_nand)^2)+(cap_ts_27*(1-0)*sh_fd+MAX(Mkt!$C$43-cap_ts_25*(1-0)*sh_fd,0)*(1+g_oth_fd)^2))+Mkt!E116+Mkt!E117 -> 230.26521 | C6: =B6/B$4-1 -> 0.055170768 | D6: =((cap_sk_28*1000/fx*sh_sk_hi+cap_mu_28*sh_mu_27+cap_ss_28*1000/fx*sh_ss_hi)+(((Mkt!$C$57-Mkt!$C$54+ind_cxmt)*sh_oth))*(1+g_oth_dram)^3+((Mkt!$C$61*sh_oth))*(1+g_oth_nand)^3)+(cap_ts_28*(1-0)*sh_fd+MAX(Mkt!$C$43-cap_ts_25*(1-0)*sh_fd,0)*(1+g_oth_fd)^3)+Mkt!F50*(((cap_sk_28*1000/fx*sh_sk_hi+cap_mu_28*sh_mu_27+cap_ss_28*1000/fx*sh_ss_hi)+(((Mkt!$C$57-Mkt!$C$54+ind_cxmt)*sh_oth))*(1+g_oth_dram)^3+((Mkt!$C$61*sh_oth))*(1+g_oth_nand)^3)+(cap_ts_28*(1-0)*sh_fd+MAX(Mkt!$C$43-cap_ts_25*(1-0)*sh_fd,0)*(1+g_oth_fd)^3))+Mkt!F116+Mkt!F117 -> 259.53511 | E6: =D6/D$4-1 -> 0.054898011 | F6: =((cap_sk_29*1000/fx*sh_sk_hi+cap_mu_29*sh_mu_27+cap_ss_29*1000/fx*sh_ss_hi)+(((Mkt!$C$57-Mkt!$C$54+ind_cxmt)*sh_oth))*(1+g_oth_dram)^4+((Mkt!$C$61*sh_oth))*(1+g_oth_nand)^4)+(cap_ts_29*(1-0)*sh_fd+MAX(Mkt!$C$43-cap_ts_25*(1-0)*sh_fd,0)*(1+g_oth_fd)^4)+Mkt!G50*(((cap_sk_29*1000/fx*sh_sk_hi+cap_mu_29*sh_mu_27+cap_ss_29*1000/fx*sh_ss_hi)+(((Mkt!$C$57-Mkt!$C$54+ind_cxmt)*sh_oth))*(1+g_oth_dram)^4+((Mkt!$C$61*sh_oth))*(1+g_oth_nand)^4)+(cap_ts_29*(1-0)*sh_fd+MAX(Mkt!$C$43-cap_ts_25*(1-0)*sh_fd,0)*(1+g_oth_fd)^4))+Mkt!G116+Mkt!G117 -> 274.53625 | G6: =F6/F$4-1 -> 0.053252506
A7: 對照：SK 海力士＋三星設備占比＝業界值 64%（不再當基準） | B7: =((cap_sk_27*1000/fx*sh_oth+cap_mu_27*sh_mu_27+cap_ss_27*1000/fx*sh_oth)+(((Mkt!$C$57-Mkt!$C$54+ind_cxmt)*sh_oth))*(1+g_oth_dram)^2+((Mkt!$C$61*sh_oth))*(1+g_oth_nand)^2)+(cap_ts_27*(1-0)*sh_fd+MAX(Mkt!$C$43-cap_ts_25*(1-0)*sh_fd,0)*(1+g_oth_fd)^2)+Mkt!E50*(((cap_sk_27*1000/fx*sh_oth+cap_mu_27*sh_mu_27+cap_ss_27*1000/fx*sh_oth)+(((Mkt!$C$57-Mkt!$C$54+ind_cxmt)*sh_oth))*(1+g_oth_dram)^2+((Mkt!$C$61*sh_oth))*(1+g_oth_nand)^2)+(cap_ts_27*(1-0)*sh_fd+MAX(Mkt!$C$43-cap_ts_25*(1-0)*sh_fd,0)*(1+g_oth_fd)^2))+Mkt!E116+Mkt!E117 -> 236.06527 | C7: =B7/B$4-1 -> 0.081749058 | D7: =((cap_sk_28*1000/fx*sh_oth+cap_mu_28*sh_mu_27+cap_ss_28*1000/fx*sh_oth)+(((Mkt!$C$57-Mkt!$C$54+ind_cxmt)*sh_oth))*(1+g_oth_dram)^3+((Mkt!$C$61*sh_oth))*(1+g_oth_nand)^3)+(cap_ts_28*(1-0)*sh_fd+MAX(Mkt!$C$43-cap_ts_25*(1-0)*sh_fd,0)*(1+g_oth_fd)^3)+Mkt!F50*(((cap_sk_28*1000/fx*sh_oth+cap_mu_28*sh_mu_27+cap_ss_28*1000/fx*sh_oth)+(((Mkt!$C$57-Mkt!$C$54+ind_cxmt)*sh_oth))*(1+g_oth_dram)^3+((Mkt!$C$61*sh_oth))*(1+g_oth_nand)^3)+(cap_ts_28*(1-0)*sh_fd+MAX(Mkt!$C$43-cap_ts_25*(1-0)*sh_fd,0)*(1+g_oth_fd)^3))+Mkt!F116+Mkt!F117 -> 266.0418 | E7: =D7/D$4-1 -> 0.081344901 | F7: =((cap_sk_29*1000/fx*sh_oth+cap_mu_29*sh_mu_27+cap_ss_29*1000/fx*sh_oth)+(((Mkt!$C$57-Mkt!$C$54+ind_cxmt)*sh_oth))*(1+g_oth_dram)^4+((Mkt!$C$61*sh_oth))*(1+g_oth_nand)^4)+(cap_ts_29*(1-0)*sh_fd+MAX(Mkt!$C$43-cap_ts_25*(1-0)*sh_fd,0)*(1+g_oth_fd)^4)+Mkt!G50*(((cap_sk_29*1000/fx*sh_oth+cap_mu_29*sh_mu_27+cap_ss_29*1000/fx*sh_oth)+(((Mkt!$C$57-Mkt!$C$54+ind_cxmt)*sh_oth))*(1+g_oth_dram)^4+((Mkt!$C$61*sh_oth))*(1+g_oth_nand)^4)+(cap_ts_29*(1-0)*sh_fd+MAX(Mkt!$C$43-cap_ts_25*(1-0)*sh_fd,0)*(1+g_oth_fd)^4))+Mkt!G116+Mkt!G117 -> 281.22316 | G7: =F7/F$4-1 -> 0.078906681
A8: 長鑫 2025 資本支出取高 12.0（年度未核對；重新校準） | B8: =((cap_sk_27*1000/fx*((Mkt!$C$73-((Mkt!$C$57-Mkt!$C$54+ind_cxmt_hi+Mkt!$C$61)*sh_oth)-(cap_mu_25*sh_mu_25))/(cap_sk_25*1000/fx+cap_ssds_25*ss_mem*1000/fx))+cap_mu_27*sh_mu_27+cap_ss_27*1000/fx*((Mkt!$C$73-((Mkt!$C$57-Mkt!$C$54+ind_cxmt_hi+Mkt!$C$61)*sh_oth)-(cap_mu_25*sh_mu_25))/(cap_sk_25*1000/fx+cap_ssds_25*ss_mem*1000/fx)))+(((Mkt!$C$57-Mkt!$C$54+ind_cxmt_hi)*sh_oth))*(1+g_oth_dram)^2+((Mkt!$C$61*sh_oth))*(1+g_oth_nand)^2)+(cap_ts_27*(1-0)*sh_fd+MAX(Mkt!$C$43-cap_ts_25*(1-0)*sh_fd,0)*(1+g_oth_fd)^2)+Mkt!E50*(((cap_sk_27*1000/fx*((Mkt!$C$73-((Mkt!$C$57-Mkt!$C$54+ind_cxmt_hi+Mkt!$C$61)*sh_oth)-(cap_mu_25*sh_mu_25))/(cap_sk_25*1000/fx+cap_ssds_25*ss_mem*1000/fx))+cap_mu_27*sh_mu_27+cap_ss_27*1000/fx*((Mkt!$C$73-((Mkt!$C$57-Mkt!$C$54+ind_cxmt_hi+Mkt!$C$61)*sh_oth)-(cap_mu_25*sh_mu_25))/(cap_sk_25*1000/fx+cap_ssds_25*ss_mem*1000/fx)))+(((Mkt!$C$57-Mkt!$C$54+ind_cxmt_hi)*sh_oth))*(1+g_oth_dram)^2+((Mkt!$C$61*sh_oth))*(1+g_oth_nand)^2)+(cap_ts_27*(1-0)*sh_fd+MAX(Mkt!$C$43-cap_ts_25*(1-0)*sh_fd,0)*(1+g_oth_fd)^2))+Mkt!E116+Mkt!E117 -> 216.51998 | C8: =B8/B$4-1 -> -0.0078155653 | D8: =((cap_sk_28*1000/fx*((Mkt!$C$73-((Mkt!$C$57-Mkt!$C$54+ind_cxmt_hi+Mkt!$C$61)*sh_oth)-(cap_mu_25*sh_mu_25))/(cap_sk_25*1000/fx+cap_ssds_25*ss_mem*1000/fx))+cap_mu_28*sh_mu_27+cap_ss_28*1000/fx*((Mkt!$C$73-((Mkt!$C$57-Mkt!$C$54+ind_cxmt_hi+Mkt!$C$61)*sh_oth)-(cap_mu_25*sh_mu_25))/(cap_sk_25*1000/fx+cap_ssds_25*ss_mem*1000/fx)))+(((Mkt!$C$57-Mkt!$C$54+ind_cxmt_hi)*sh_oth))*(1+g_oth_dram)^3+((Mkt!$C$61*sh_oth))*(1+g_oth_nand)^3)+(cap_ts_28*(1-0)*sh_fd+MAX(Mkt!$C$43-cap_ts_25*(1-0)*sh_fd,0)*(1+g_oth_fd)^3)+Mkt!F50*(((cap_sk_28*1000/fx*((Mkt!$C$73-((Mkt!$C$57-Mkt!$C$54+ind_cxmt_hi+Mkt!$C$61)*sh_oth)-(cap_mu_25*sh_mu_25))/(cap_sk_25*1000/fx+cap_ssds_25*ss_mem*1000/fx))+cap_mu_28*sh_mu_27+cap_ss_28*1000/fx*((Mkt!$C$73-((Mkt!$C$57-Mkt!$C$54+ind_cxmt_hi+Mkt!$C$61)*sh_oth)-(cap_mu_25*sh_mu_25))/(cap_sk_25*1000/fx+cap_ssds_25*ss_mem*1000/fx)))+(((Mkt!$C$57-Mkt!$C$54+ind_cxmt_hi)*sh_oth))*(1+g_oth_dram)^3+((Mkt!$C$61*sh_oth))*(1+g_oth_nand)^3)+(cap_ts_28*(1-0)*sh_fd+MAX(Mkt!$C$43-cap_ts_25*(1-0)*sh_fd,0)*(1+g_oth_fd)^3))+Mkt!F116+Mkt!F117 -> 244.412 | E8: =D8/D$4-1 -> -0.0065708933 | F8: =((cap_sk_29*1000/fx*((Mkt!$C$73-((Mkt!$C$57-Mkt!$C$54+ind_cxmt_hi+Mkt!$C$61)*sh_oth)-(cap_mu_25*sh_mu_25))/(cap_sk_25*1000/fx+cap_ssds_25*ss_mem*1000/fx))+cap_mu_29*sh_mu_27+cap_ss_29*1000/fx*((Mkt!$C$73-((Mkt!$C$57-Mkt!$C$54+ind_cxmt_hi+Mkt!$C$61)*sh_oth)-(cap_mu_25*sh_mu_25))/(cap_sk_25*1000/fx+cap_ssds_25*ss_mem*1000/fx)))+(((Mkt!$C$57-Mkt!$C$54+ind_cxmt_hi)*sh_oth))*(1+g_oth_dram)^4+((Mkt!$C$61*sh_oth))*(1+g_oth_nand)^4)+(cap_ts_29*(1-0)*sh_fd+MAX(Mkt!$C$43-cap_ts_25*(1-0)*sh_fd,0)*(1+g_oth_fd)^4)+Mkt!G50*(((cap_sk_29*1000/fx*((Mkt!$C$73-((Mkt!$C$57-Mkt!$C$54+ind_cxmt_hi+Mkt!$C$61)*sh_oth)-(cap_mu_25*sh_mu_25))/(cap_sk_25*1000/fx+cap_ssds_25*ss_mem*1000/fx))+cap_mu_29*sh_mu_27+cap_ss_29*1000/fx*((Mkt!$C$73-((Mkt!$C$57-Mkt!$C$54+ind_cxmt_hi+Mkt!$C$61)*sh_oth)-(cap_mu_25*sh_mu_25))/(cap_sk_25*1000/fx+cap_ssds_25*ss_mem*1000/fx)))+(((Mkt!$C$57-Mkt!$C$54+ind_cxmt_hi)*sh_oth))*(1+g_oth_dram)^4+((Mkt!$C$61*sh_oth))*(1+g_oth_nand)^4)+(cap_ts_29*(1-0)*sh_fd+MAX(Mkt!$C$43-cap_ts_25*(1-0)*sh_fd,0)*(1+g_oth_fd)^4))+Mkt!G116+Mkt!G117 -> 259.91103 | G8: =F8/F$4-1 -> -0.0028568664
A9: 美光設備占比 低（FY25／26／27–29；重新校準） | B9: =((cap_sk_27*1000/fx*((Mkt!$C$73-((Mkt!$C$57-Mkt!$C$54+ind_cxmt+Mkt!$C$61)*sh_oth)-(cap_mu_25*sh_mu_25_lo))/(cap_sk_25*1000/fx+cap_ssds_25*ss_mem*1000/fx))+cap_mu_27*sh_mu_27_lo+cap_ss_27*1000/fx*((Mkt!$C$73-((Mkt!$C$57-Mkt!$C$54+ind_cxmt+Mkt!$C$61)*sh_oth)-(cap_mu_25*sh_mu_25_lo))/(cap_sk_25*1000/fx+cap_ssds_25*ss_mem*1000/fx)))+(((Mkt!$C$57-Mkt!$C$54+ind_cxmt)*sh_oth))*(1+g_oth_dram)^2+((Mkt!$C$61*sh_oth))*(1+g_oth_nand)^2)+(cap_ts_27*(1-0)*sh_fd+MAX(Mkt!$C$43-cap_ts_25*(1-0)*sh_fd,0)*(1+g_oth_fd)^2)+Mkt!E50*(((cap_sk_27*1000/fx*((Mkt!$C$73-((Mkt!$C$57-Mkt!$C$54+ind_cxmt+Mkt!$C$61)*sh_oth)-(cap_mu_25*sh_mu_25_lo))/(cap_sk_25*1000/fx+cap_ssds_25*ss_mem*1000/fx))+cap_mu_27*sh_mu_27_lo+cap_ss_27*1000/fx*((Mkt!$C$73-((Mkt!$C$57-Mkt!$C$54+ind_cxmt+Mkt!$C$61)*sh_oth)-(cap_mu_25*sh_mu_25_lo))/(cap_sk_25*1000/fx+cap_ssds_25*ss_mem*1000/fx)))+(((Mkt!$C$57-Mkt!$C$54+ind_cxmt)*sh_oth))*(1+g_oth_dram)^2+((Mkt!$C$61*sh_oth))*(1+g_oth_nand)^2)+(cap_ts_27*(1-0)*sh_fd+MAX(Mkt!$C$43-cap_ts_25*(1-0)*sh_fd,0)*(1+g_oth_fd)^2))+Mkt!E116+Mkt!E117 -> 215.32235 | C9: =B9/B$4-1 -> -0.013303592 | D9: =((cap_sk_28*1000/fx*((Mkt!$C$73-((Mkt!$C$57-Mkt!$C$54+ind_cxmt+Mkt!$C$61)*sh_oth)-(cap_mu_25*sh_mu_25_lo))/(cap_sk_25*1000/fx+cap_ssds_25*ss_mem*1000/fx))+cap_mu_28*sh_mu_27_lo+cap_ss_28*1000/fx*((Mkt!$C$73-((Mkt!$C$57-Mkt!$C$54+ind_cxmt+Mkt!$C$61)*sh_oth)-(cap_mu_25*sh_mu_25_lo))/(cap_sk_25*1000/fx+cap_ssds_25*ss_mem*1000/fx)))+(((Mkt!$C$57-Mkt!$C$54+ind_cxmt)*sh_oth))*(1+g_oth_dram)^3+((Mkt!$C$61*sh_oth))*(1+g_oth_nand)^3)+(cap_ts_28*(1-0)*sh_fd+MAX(Mkt!$C$43-cap_ts_25*(1-0)*sh_fd,0)*(1+g_oth_fd)^3)+Mkt!F50*(((cap_sk_28*1000/fx*((Mkt!$C$73-((Mkt!$C$57-Mkt!$C$54+ind_cxmt+Mkt!$C$61)*sh_oth)-(cap_mu_25*sh_mu_25_lo))/(cap_sk_25*1000/fx+cap_ssds_25*ss_mem*1000/fx))+cap_mu_28*sh_mu_27_lo+cap_ss_28*1000/fx*((Mkt!$C$73-((Mkt!$C$57-Mkt!$C$54+ind_cxmt+Mkt!$C$61)*sh_oth)-(cap_mu_25*sh_mu_25_lo))/(cap_sk_25*1000/fx+cap_ssds_25*ss_mem*1000/fx)))+(((Mkt!$C$57-Mkt!$C$54+ind_cxmt)*sh_oth))*(1+g_oth_dram)^3+((Mkt!$C$61*sh_oth))*(1+g_oth_nand)^3)+(cap_ts_28*(1-0)*sh_fd+MAX(Mkt!$C$43-cap_ts_25*(1-0)*sh_fd,0)*(1+g_oth_fd)^3))+Mkt!F116+Mkt!F117 -> 242.91491 | E9: =D9/D$4-1 -> -0.012655911 | F9: =((cap_sk_29*1000/fx*((Mkt!$C$73-((Mkt!$C$57-Mkt!$C$54+ind_cxmt+Mkt!$C$61)*sh_oth)-(cap_mu_25*sh_mu_25_lo))/(cap_sk_25*1000/fx+cap_ssds_25*ss_mem*1000/fx))+cap_mu_29*sh_mu_27_lo+cap_ss_29*1000/fx*((Mkt!$C$73-((Mkt!$C$57-Mkt!$C$54+ind_cxmt+Mkt!$C$61)*sh_oth)-(cap_mu_25*sh_mu_25_lo))/(cap_sk_25*1000/fx+cap_ssds_25*ss_mem*1000/fx)))+(((Mkt!$C$57-Mkt!$C$54+ind_cxmt)*sh_oth))*(1+g_oth_dram)^4+((Mkt!$C$61*sh_oth))*(1+g_oth_nand)^4)+(cap_ts_29*(1-0)*sh_fd+MAX(Mkt!$C$43-cap_ts_25*(1-0)*sh_fd,0)*(1+g_oth_fd)^4)+Mkt!G50*(((cap_sk_29*1000/fx*((Mkt!$C$73-((Mkt!$C$57-Mkt!$C$54+ind_cxmt+Mkt!$C$61)*sh_oth)-(cap_mu_25*sh_mu_25_lo))/(cap_sk_25*1000/fx+cap_ssds_25*ss_mem*1000/fx))+cap_mu_29*sh_mu_27_lo+cap_ss_29*1000/fx*((Mkt!$C$73-((Mkt!$C$57-Mkt!$C$54+ind_cxmt+Mkt!$C$61)*sh_oth)-(cap_mu_25*sh_mu_25_lo))/(cap_sk_25*1000/fx+cap_ssds_25*ss_mem*1000/fx)))+(((Mkt!$C$57-Mkt!$C$54+ind_cxmt)*sh_oth))*(1+g_oth_dram)^4+((Mkt!$C$61*sh_oth))*(1+g_oth_nand)^4)+(cap_ts_29*(1-0)*sh_fd+MAX(Mkt!$C$43-cap_ts_25*(1-0)*sh_fd,0)*(1+g_oth_fd)^4))+Mkt!G116+Mkt!G117 -> 257.59562 | G9: =F9/F$4-1 -> -0.011739881
A10: 美光設備占比 高（重新校準） | B10: =((cap_sk_27*1000/fx*((Mkt!$C$73-((Mkt!$C$57-Mkt!$C$54+ind_cxmt+Mkt!$C$61)*sh_oth)-(cap_mu_25*sh_mu_25_hi))/(cap_sk_25*1000/fx+cap_ssds_25*ss_mem*1000/fx))+cap_mu_27*sh_mu_27_hi+cap_ss_27*1000/fx*((Mkt!$C$73-((Mkt!$C$57-Mkt!$C$54+ind_cxmt+Mkt!$C$61)*sh_oth)-(cap_mu_25*sh_mu_25_hi))/(cap_sk_25*1000/fx+cap_ssds_25*ss_mem*1000/fx)))+(((Mkt!$C$57-Mkt!$C$54+ind_cxmt)*sh_oth))*(1+g_oth_dram)^2+((Mkt!$C$61*sh_oth))*(1+g_oth_nand)^2)+(cap_ts_27*(1-0)*sh_fd+MAX(Mkt!$C$43-cap_ts_25*(1-0)*sh_fd,0)*(1+g_oth_fd)^2)+Mkt!E50*(((cap_sk_27*1000/fx*((Mkt!$C$73-((Mkt!$C$57-Mkt!$C$54+ind_cxmt+Mkt!$C$61)*sh_oth)-(cap_mu_25*sh_mu_25_hi))/(cap_sk_25*1000/fx+cap_ssds_25*ss_mem*1000/fx))+cap_mu_27*sh_mu_27_hi+cap_ss_27*1000/fx*((Mkt!$C$73-((Mkt!$C$57-Mkt!$C$54+ind_cxmt+Mkt!$C$61)*sh_oth)-(cap_mu_25*sh_mu_25_hi))/(cap_sk_25*1000/fx+cap_ssds_25*ss_mem*1000/fx)))+(((Mkt!$C$57-Mkt!$C$54+ind_cxmt)*sh_oth))*(1+g_oth_dram)^2+((Mkt!$C$61*sh_oth))*(1+g_oth_nand)^2)+(cap_ts_27*(1-0)*sh_fd+MAX(Mkt!$C$43-cap_ts_25*(1-0)*sh_fd,0)*(1+g_oth_fd)^2))+Mkt!E116+Mkt!E117 -> 221.12872 | C10: =B10/B$4-1 -> 0.013303592 | D10: =((cap_sk_28*1000/fx*((Mkt!$C$73-((Mkt!$C$57-Mkt!$C$54+ind_cxmt+Mkt!$C$61)*sh_oth)-(cap_mu_25*sh_mu_25_hi))/(cap_sk_25*1000/fx+cap_ssds_25*ss_mem*1000/fx))+cap_mu_28*sh_mu_27_hi+cap_ss_28*1000/fx*((Mkt!$C$73-((Mkt!$C$57-Mkt!$C$54+ind_cxmt+Mkt!$C$61)*sh_oth)-(cap_mu_25*sh_mu_25_hi))/(cap_sk_25*1000/fx+cap_ssds_25*ss_mem*1000/fx)))+(((Mkt!$C$57-Mkt!$C$54+ind_cxmt)*sh_oth))*(1+g_oth_dram)^3+((Mkt!$C$61*sh_oth))*(1+g_oth_nand)^3)+(cap_ts_28*(1-0)*sh_fd+MAX(Mkt!$C$43-cap_ts_25*(1-0)*sh_fd,0)*(1+g_oth_fd)^3)+Mkt!F50*(((cap_sk_28*1000/fx*((Mkt!$C$73-((Mkt!$C$57-Mkt!$C$54+ind_cxmt+Mkt!$C$61)*sh_oth)-(cap_mu_25*sh_mu_25_hi))/(cap_sk_25*1000/fx+cap_ssds_25*ss_mem*1000/fx))+cap_mu_28*sh_mu_27_hi+cap_ss_28*1000/fx*((Mkt!$C$73-((Mkt!$C$57-Mkt!$C$54+ind_cxmt+Mkt!$C$61)*sh_oth)-(cap_mu_25*sh_mu_25_hi))/(cap_sk_25*1000/fx+cap_ssds_25*ss_mem*1000/fx)))+(((Mkt!$C$57-Mkt!$C$54+ind_cxmt)*sh_oth))*(1+g_oth_dram)^3+((Mkt!$C$61*sh_oth))*(1+g_oth_nand)^3)+(cap_ts_28*(1-0)*sh_fd+MAX(Mkt!$C$43-cap_ts_25*(1-0)*sh_fd,0)*(1+g_oth_fd)^3))+Mkt!F116+Mkt!F117 -> 249.14234 | E10: =D10/D$4-1 -> 0.012655911 | F10: =((cap_sk_29*1000/fx*((Mkt!$C$73-((Mkt!$C$57-Mkt!$C$54+ind_cxmt+Mkt!$C$61)*sh_oth)-(cap_mu_25*sh_mu_25_hi))/(cap_sk_25*1000/fx+cap_ssds_25*ss_mem*1000/fx))+cap_mu_29*sh_mu_27_hi+cap_ss_29*1000/fx*((Mkt!$C$73-((Mkt!$C$57-Mkt!$C$54+ind_cxmt+Mkt!$C$61)*sh_oth)-(cap_mu_25*sh_mu_25_hi))/(cap_sk_25*1000/fx+cap_ssds_25*ss_mem*1000/fx)))+(((Mkt!$C$57-Mkt!$C$54+ind_cxmt)*sh_oth))*(1+g_oth_dram)^4+((Mkt!$C$61*sh_oth))*(1+g_oth_nand)^4)+(cap_ts_29*(1-0)*sh_fd+MAX(Mkt!$C$43-cap_ts_25*(1-0)*sh_fd,0)*(1+g_oth_fd)^4)+Mkt!G50*(((cap_sk_29*1000/fx*((Mkt!$C$73-((Mkt!$C$57-Mkt!$C$54+ind_cxmt+Mkt!$C$61)*sh_oth)-(cap_mu_25*sh_mu_25_hi))/(cap_sk_25*1000/fx+cap_ssds_25*ss_mem*1000/fx))+cap_mu_29*sh_mu_27_hi+cap_ss_29*1000/fx*((Mkt!$C$73-((Mkt!$C$57-Mkt!$C$54+ind_cxmt+Mkt!$C$61)*sh_oth)-(cap_mu_25*sh_mu_25_hi))/(cap_sk_25*1000/fx+cap_ssds_25*ss_mem*1000/fx)))+(((Mkt!$C$57-Mkt!$C$54+ind_cxmt)*sh_oth))*(1+g_oth_dram)^4+((Mkt!$C$61*sh_oth))*(1+g_oth_nand)^4)+(cap_ts_29*(1-0)*sh_fd+MAX(Mkt!$C$43-cap_ts_25*(1-0)*sh_fd,0)*(1+g_oth_fd)^4))+Mkt!G116+Mkt!G117 -> 263.71575 | G10: =F10/F$4-1 -> 0.011739881
A11: 其他記憶體廠設備占比 58%（重新校準） | B11: =((cap_sk_27*1000/fx*((Mkt!$C$73-((Mkt!$C$57-Mkt!$C$54+ind_cxmt+Mkt!$C$61)*sh_oth_lo)-(cap_mu_25*sh_mu_25))/(cap_sk_25*1000/fx+cap_ssds_25*ss_mem*1000/fx))+cap_mu_27*sh_mu_27+cap_ss_27*1000/fx*((Mkt!$C$73-((Mkt!$C$57-Mkt!$C$54+ind_cxmt+Mkt!$C$61)*sh_oth_lo)-(cap_mu_25*sh_mu_25))/(cap_sk_25*1000/fx+cap_ssds_25*ss_mem*1000/fx)))+(((Mkt!$C$57-Mkt!$C$54+ind_cxmt)*sh_oth_lo))*(1+g_oth_dram)^2+((Mkt!$C$61*sh_oth_lo))*(1+g_oth_nand)^2)+(cap_ts_27*(1-0)*sh_fd+MAX(Mkt!$C$43-cap_ts_25*(1-0)*sh_fd,0)*(1+g_oth_fd)^2)+Mkt!E50*(((cap_sk_27*1000/fx*((Mkt!$C$73-((Mkt!$C$57-Mkt!$C$54+ind_cxmt+Mkt!$C$61)*sh_oth_lo)-(cap_mu_25*sh_mu_25))/(cap_sk_25*1000/fx+cap_ssds_25*ss_mem*1000/fx))+cap_mu_27*sh_mu_27+cap_ss_27*1000/fx*((Mkt!$C$73-((Mkt!$C$57-Mkt!$C$54+ind_cxmt+Mkt!$C$61)*sh_oth_lo)-(cap_mu_25*sh_mu_25))/(cap_sk_25*1000/fx+cap_ssds_25*ss_mem*1000/fx)))+(((Mkt!$C$57-Mkt!$C$54+ind_cxmt)*sh_oth_lo))*(1+g_oth_dram)^2+((Mkt!$C$61*sh_oth_lo))*(1+g_oth_nand)^2)+(cap_ts_27*(1-0)*sh_fd+MAX(Mkt!$C$43-cap_ts_25*(1-0)*sh_fd,0)*(1+g_oth_fd)^2))+Mkt!E116+Mkt!E117 -> 218.64702 | C11: =B11/B$4-1 -> 0.0019314203 | D11: =((cap_sk_28*1000/fx*((Mkt!$C$73-((Mkt!$C$57-Mkt!$C$54+ind_cxmt+Mkt!$C$61)*sh_oth_lo)-(cap_mu_25*sh_mu_25))/(cap_sk_25*1000/fx+cap_ssds_25*ss_mem*1000/fx))+cap_mu_28*sh_mu_27+cap_ss_28*1000/fx*((Mkt!$C$73-((Mkt!$C$57-Mkt!$C$54+ind_cxmt+Mkt!$C$61)*sh_oth_lo)-(cap_mu_25*sh_mu_25))/(cap_sk_25*1000/fx+cap_ssds_25*ss_mem*1000/fx)))+(((Mkt!$C$57-Mkt!$C$54+ind_cxmt)*sh_oth_lo))*(1+g_oth_dram)^3+((Mkt!$C$61*sh_oth_lo))*(1+g_oth_nand)^3)+(cap_ts_28*(1-0)*sh_fd+MAX(Mkt!$C$43-cap_ts_25*(1-0)*sh_fd,0)*(1+g_oth_fd)^3)+Mkt!F50*(((cap_sk_28*1000/fx*((Mkt!$C$73-((Mkt!$C$57-Mkt!$C$54+ind_cxmt+Mkt!$C$61)*sh_oth_lo)-(cap_mu_25*sh_mu_25))/(cap_sk_25*1000/fx+cap_ssds_25*ss_mem*1000/fx))+cap_mu_28*sh_mu_27+cap_ss_28*1000/fx*((Mkt!$C$73-((Mkt!$C$57-Mkt!$C$54+ind_cxmt+Mkt!$C$61)*sh_oth_lo)-(cap_mu_25*sh_mu_25))/(cap_sk_25*1000/fx+cap_ssds_25*ss_mem*1000/fx)))+(((Mkt!$C$57-Mkt!$C$54+ind_cxmt)*sh_oth_lo))*(1+g_oth_dram)^3+((Mkt!$C$61*sh_oth_lo))*(1+g_oth_nand)^3)+(cap_ts_28*(1-0)*sh_fd+MAX(Mkt!$C$43-cap_ts_25*(1-0)*sh_fd,0)*(1+g_oth_fd)^3))+Mkt!F116+Mkt!F117 -> 246.42814 | E11: =D11/D$4-1 -> 0.001623831 | F11: =((cap_sk_29*1000/fx*((Mkt!$C$73-((Mkt!$C$57-Mkt!$C$54+ind_cxmt+Mkt!$C$61)*sh_oth_lo)-(cap_mu_25*sh_mu_25))/(cap_sk_25*1000/fx+cap_ssds_25*ss_mem*1000/fx))+cap_mu_29*sh_mu_27+cap_ss_29*1000/fx*((Mkt!$C$73-((Mkt!$C$57-Mkt!$C$54+ind_cxmt+Mkt!$C$61)*sh_oth_lo)-(cap_mu_25*sh_mu_25))/(cap_sk_25*1000/fx+cap_ssds_25*ss_mem*1000/fx)))+(((Mkt!$C$57-Mkt!$C$54+ind_cxmt)*sh_oth_lo))*(1+g_oth_dram)^4+((Mkt!$C$61*sh_oth_lo))*(1+g_oth_nand)^4)+(cap_ts_29*(1-0)*sh_fd+MAX(Mkt!$C$43-cap_ts_25*(1-0)*sh_fd,0)*(1+g_oth_fd)^4)+Mkt!G50*(((cap_sk_29*1000/fx*((Mkt!$C$73-((Mkt!$C$57-Mkt!$C$54+ind_cxmt+Mkt!$C$61)*sh_oth_lo)-(cap_mu_25*sh_mu_25))/(cap_sk_25*1000/fx+cap_ssds_25*ss_mem*1000/fx))+cap_mu_29*sh_mu_27+cap_ss_29*1000/fx*((Mkt!$C$73-((Mkt!$C$57-Mkt!$C$54+ind_cxmt+Mkt!$C$61)*sh_oth_lo)-(cap_mu_25*sh_mu_25))/(cap_sk_25*1000/fx+cap_ssds_25*ss_mem*1000/fx)))+(((Mkt!$C$57-Mkt!$C$54+ind_cxmt)*sh_oth_lo))*(1+g_oth_dram)^4+((Mkt!$C$61*sh_oth_lo))*(1+g_oth_nand)^4)+(cap_ts_29*(1-0)*sh_fd+MAX(Mkt!$C$43-cap_ts_25*(1-0)*sh_fd,0)*(1+g_oth_fd)^4))+Mkt!G116+Mkt!G117 -> 260.83971 | G11: =F11/F$4-1 -> 0.00070600265
A12: 其他記憶體廠設備占比 70%（重新校準） | B12: =((cap_sk_27*1000/fx*((Mkt!$C$73-((Mkt!$C$57-Mkt!$C$54+ind_cxmt+Mkt!$C$61)*sh_oth_hi)-(cap_mu_25*sh_mu_25))/(cap_sk_25*1000/fx+cap_ssds_25*ss_mem*1000/fx))+cap_mu_27*sh_mu_27+cap_ss_27*1000/fx*((Mkt!$C$73-((Mkt!$C$57-Mkt!$C$54+ind_cxmt+Mkt!$C$61)*sh_oth_hi)-(cap_mu_25*sh_mu_25))/(cap_sk_25*1000/fx+cap_ssds_25*ss_mem*1000/fx)))+(((Mkt!$C$57-Mkt!$C$54+ind_cxmt)*sh_oth_hi))*(1+g_oth_dram)^2+((Mkt!$C$61*sh_oth_hi))*(1+g_oth_nand)^2)+(cap_ts_27*(1-0)*sh_fd+MAX(Mkt!$C$43-cap_ts_25*(1-0)*sh_fd,0)*(1+g_oth_fd)^2)+Mkt!E50*(((cap_sk_27*1000/fx*((Mkt!$C$73-((Mkt!$C$57-Mkt!$C$54+ind_cxmt+Mkt!$C$61)*sh_oth_hi)-(cap_mu_25*sh_mu_25))/(cap_sk_25*1000/fx+cap_ssds_25*ss_mem*1000/fx))+cap_mu_27*sh_mu_27+cap_ss_27*1000/fx*((Mkt!$C$73-((Mkt!$C$57-Mkt!$C$54+ind_cxmt+Mkt!$C$61)*sh_oth_hi)-(cap_mu_25*sh_mu_25))/(cap_sk_25*1000/fx+cap_ssds_25*ss_mem*1000/fx)))+(((Mkt!$C$57-Mkt!$C$54+ind_cxmt)*sh_oth_hi))*(1+g_oth_dram)^2+((Mkt!$C$61*sh_oth_hi))*(1+g_oth_nand)^2)+(cap_ts_27*(1-0)*sh_fd+MAX(Mkt!$C$43-cap_ts_25*(1-0)*sh_fd,0)*(1+g_oth_fd)^2))+Mkt!E116+Mkt!E117 -> 217.80405 | C12: =B12/B$4-1 -> -0.0019314203 | D12: =((cap_sk_28*1000/fx*((Mkt!$C$73-((Mkt!$C$57-Mkt!$C$54+ind_cxmt+Mkt!$C$61)*sh_oth_hi)-(cap_mu_25*sh_mu_25))/(cap_sk_25*1000/fx+cap_ssds_25*ss_mem*1000/fx))+cap_mu_28*sh_mu_27+cap_ss_28*1000/fx*((Mkt!$C$73-((Mkt!$C$57-Mkt!$C$54+ind_cxmt+Mkt!$C$61)*sh_oth_hi)-(cap_mu_25*sh_mu_25))/(cap_sk_25*1000/fx+cap_ssds_25*ss_mem*1000/fx)))+(((Mkt!$C$57-Mkt!$C$54+ind_cxmt)*sh_oth_hi))*(1+g_oth_dram)^3+((Mkt!$C$61*sh_oth_hi))*(1+g_oth_nand)^3)+(cap_ts_28*(1-0)*sh_fd+MAX(Mkt!$C$43-cap_ts_25*(1-0)*sh_fd,0)*(1+g_oth_fd)^3)+Mkt!F50*(((cap_sk_28*1000/fx*((Mkt!$C$73-((Mkt!$C$57-Mkt!$C$54+ind_cxmt+Mkt!$C$61)*sh_oth_hi)-(cap_mu_25*sh_mu_25))/(cap_sk_25*1000/fx+cap_ssds_25*ss_mem*1000/fx))+cap_mu_28*sh_mu_27+cap_ss_28*1000/fx*((Mkt!$C$73-((Mkt!$C$57-Mkt!$C$54+ind_cxmt+Mkt!$C$61)*sh_oth_hi)-(cap_mu_25*sh_mu_25))/(cap_sk_25*1000/fx+cap_ssds_25*ss_mem*1000/fx)))+(((Mkt!$C$57-Mkt!$C$54+ind_cxmt)*sh_oth_hi))*(1+g_oth_dram)^3+((Mkt!$C$61*sh_oth_hi))*(1+g_oth_nand)^3)+(cap_ts_28*(1-0)*sh_fd+MAX(Mkt!$C$43-cap_ts_25*(1-0)*sh_fd,0)*(1+g_oth_fd)^3))+Mkt!F116+Mkt!F117 -> 245.62912 | E12: =D12/D$4-1 -> -0.001623831 | F12: =((cap_sk_29*1000/fx*((Mkt!$C$73-((Mkt!$C$57-Mkt!$C$54+ind_cxmt+Mkt!$C$61)*sh_oth_hi)-(cap_mu_25*sh_mu_25))/(cap_sk_25*1000/fx+cap_ssds_25*ss_mem*1000/fx))+cap_mu_29*sh_mu_27+cap_ss_29*1000/fx*((Mkt!$C$73-((Mkt!$C$57-Mkt!$C$54+ind_cxmt+Mkt!$C$61)*sh_oth_hi)-(cap_mu_25*sh_mu_25))/(cap_sk_25*1000/fx+cap_ssds_25*ss_mem*1000/fx)))+(((Mkt!$C$57-Mkt!$C$54+ind_cxmt)*sh_oth_hi))*(1+g_oth_dram)^4+((Mkt!$C$61*sh_oth_hi))*(1+g_oth_nand)^4)+(cap_ts_29*(1-0)*sh_fd+MAX(Mkt!$C$43-cap_ts_25*(1-0)*sh_fd,0)*(1+g_oth_fd)^4)+Mkt!G50*(((cap_sk_29*1000/fx*((Mkt!$C$73-((Mkt!$C$57-Mkt!$C$54+ind_cxmt+Mkt!$C$61)*sh_oth_hi)-(cap_mu_25*sh_mu_25))/(cap_sk_25*1000/fx+cap_ssds_25*ss_mem*1000/fx))+cap_mu_29*sh_mu_27+cap_ss_29*1000/fx*((Mkt!$C$73-((Mkt!$C$57-Mkt!$C$54+ind_cxmt+Mkt!$C$61)*sh_oth_hi)-(cap_mu_25*sh_mu_25))/(cap_sk_25*1000/fx+cap_ssds_25*ss_mem*1000/fx)))+(((Mkt!$C$57-Mkt!$C$54+ind_cxmt)*sh_oth_hi))*(1+g_oth_dram)^4+((Mkt!$C$61*sh_oth_hi))*(1+g_oth_nand)^4)+(cap_ts_29*(1-0)*sh_fd+MAX(Mkt!$C$43-cap_ts_25*(1-0)*sh_fd,0)*(1+g_oth_fd)^4))+Mkt!G116+Mkt!G117 -> 260.47166 | G12: =F12/F$4-1 -> -0.00070600265
A13: 台積電設備占比 低（50%） | B13: =((cap_sk_27*1000/fx*sh_sk+cap_mu_27*sh_mu_27+cap_ss_27*1000/fx*sh_ss)+(((Mkt!$C$57-Mkt!$C$54+ind_cxmt)*sh_oth))*(1+g_oth_dram)^2+((Mkt!$C$61*sh_oth))*(1+g_oth_nand)^2)+(cap_ts_27*(1-0)*sh_fd_lo+MAX(Mkt!$C$43-cap_ts_25*(1-0)*sh_fd_lo,0)*(1+g_oth_fd)^2)+Mkt!E50*(((cap_sk_27*1000/fx*sh_sk+cap_mu_27*sh_mu_27+cap_ss_27*1000/fx*sh_ss)+(((Mkt!$C$57-Mkt!$C$54+ind_cxmt)*sh_oth))*(1+g_oth_dram)^2+((Mkt!$C$61*sh_oth))*(1+g_oth_nand)^2)+(cap_ts_27*(1-0)*sh_fd_lo+MAX(Mkt!$C$43-cap_ts_25*(1-0)*sh_fd_lo,0)*(1+g_oth_fd)^2))+Mkt!E116+Mkt!E117 -> 213.6224 | C13: =B13/B$4-1 -> -0.021093465 | D13: =((cap_sk_28*1000/fx*sh_sk+cap_mu_28*sh_mu_27+cap_ss_28*1000/fx*sh_ss)+(((Mkt!$C$57-Mkt!$C$54+ind_cxmt)*sh_oth))*(1+g_oth_dram)^3+((Mkt!$C$61*sh_oth))*(1+g_oth_nand)^3)+(cap_ts_28*(1-0)*sh_fd_lo+MAX(Mkt!$C$43-cap_ts_25*(1-0)*sh_fd_lo,0)*(1+g_oth_fd)^3)+Mkt!F50*(((cap_sk_28*1000/fx*sh_sk+cap_mu_28*sh_mu_27+cap_ss_28*1000/fx*sh_ss)+(((Mkt!$C$57-Mkt!$C$54+ind_cxmt)*sh_oth))*(1+g_oth_dram)^3+((Mkt!$C$61*sh_oth))*(1+g_oth_nand)^3)+(cap_ts_28*(1-0)*sh_fd_lo+MAX(Mkt!$C$43-cap_ts_25*(1-0)*sh_fd_lo,0)*(1+g_oth_fd)^3))+Mkt!F116+Mkt!F117 -> 239.98244 | E13: =D13/D$4-1 -> -0.024575119 | F13: =((cap_sk_29*1000/fx*sh_sk+cap_mu_29*sh_mu_27+cap_ss_29*1000/fx*sh_ss)+(((Mkt!$C$57-Mkt!$C$54+ind_cxmt)*sh_oth))*(1+g_oth_dram)^4+((Mkt!$C$61*sh_oth))*(1+g_oth_nand)^4)+(cap_ts_29*(1-0)*sh_fd_lo+MAX(Mkt!$C$43-cap_ts_25*(1-0)*sh_fd_lo,0)*(1+g_oth_fd)^4)+Mkt!G50*(((cap_sk_29*1000/fx*sh_sk+cap_mu_29*sh_mu_27+cap_ss_29*1000/fx*sh_ss)+(((Mkt!$C$57-Mkt!$C$54+ind_cxmt)*sh_oth))*(1+g_oth_dram)^4+((Mkt!$C$61*sh_oth))*(1+g_oth_nand)^4)+(cap_ts_29*(1-0)*sh_fd_lo+MAX(Mkt!$C$43-cap_ts_25*(1-0)*sh_fd_lo,0)*(1+g_oth_fd)^4))+Mkt!G116+Mkt!G117 -> 254.4715 | G13: =F13/F$4-1 -> -0.023725481
A14: 台積電設備占比 高（75%） | B14: =((cap_sk_27*1000/fx*sh_sk+cap_mu_27*sh_mu_27+cap_ss_27*1000/fx*sh_ss)+(((Mkt!$C$57-Mkt!$C$54+ind_cxmt)*sh_oth))*(1+g_oth_dram)^2+((Mkt!$C$61*sh_oth))*(1+g_oth_nand)^2)+(cap_ts_27*(1-0)*sh_fd_hi+MAX(Mkt!$C$43-cap_ts_25*(1-0)*sh_fd_hi,0)*(1+g_oth_fd)^2)+Mkt!E50*(((cap_sk_27*1000/fx*sh_sk+cap_mu_27*sh_mu_27+cap_ss_27*1000/fx*sh_ss)+(((Mkt!$C$57-Mkt!$C$54+ind_cxmt)*sh_oth))*(1+g_oth_dram)^2+((Mkt!$C$61*sh_oth))*(1+g_oth_nand)^2)+(cap_ts_27*(1-0)*sh_fd_hi+MAX(Mkt!$C$43-cap_ts_25*(1-0)*sh_fd_hi,0)*(1+g_oth_fd)^2))+Mkt!E116+Mkt!E117 -> 221.84228 | C14: =B14/B$4-1 -> 0.016573437 | D14: =((cap_sk_28*1000/fx*sh_sk+cap_mu_28*sh_mu_27+cap_ss_28*1000/fx*sh_ss)+(((Mkt!$C$57-Mkt!$C$54+ind_cxmt)*sh_oth))*(1+g_oth_dram)^3+((Mkt!$C$61*sh_oth))*(1+g_oth_nand)^3)+(cap_ts_28*(1-0)*sh_fd_hi+MAX(Mkt!$C$43-cap_ts_25*(1-0)*sh_fd_hi,0)*(1+g_oth_fd)^3)+Mkt!F50*(((cap_sk_28*1000/fx*sh_sk+cap_mu_28*sh_mu_27+cap_ss_28*1000/fx*sh_ss)+(((Mkt!$C$57-Mkt!$C$54+ind_cxmt)*sh_oth))*(1+g_oth_dram)^3+((Mkt!$C$61*sh_oth))*(1+g_oth_nand)^3)+(cap_ts_28*(1-0)*sh_fd_hi+MAX(Mkt!$C$43-cap_ts_25*(1-0)*sh_fd_hi,0)*(1+g_oth_fd)^3))+Mkt!F116+Mkt!F117 -> 250.7792 | E14: =D14/D$4-1 -> 0.019309022 | F14: =((cap_sk_29*1000/fx*sh_sk+cap_mu_29*sh_mu_27+cap_ss_29*1000/fx*sh_ss)+(((Mkt!$C$57-Mkt!$C$54+ind_cxmt)*sh_oth))*(1+g_oth_dram)^4+((Mkt!$C$61*sh_oth))*(1+g_oth_nand)^4)+(cap_ts_29*(1-0)*sh_fd_hi+MAX(Mkt!$C$43-cap_ts_25*(1-0)*sh_fd_hi,0)*(1+g_oth_fd)^4)+Mkt!G50*(((cap_sk_29*1000/fx*sh_sk+cap_mu_29*sh_mu_27+cap_ss_29*1000/fx*sh_ss)+(((Mkt!$C$57-Mkt!$C$54+ind_cxmt)*sh_oth))*(1+g_oth_dram)^4+((Mkt!$C$61*sh_oth))*(1+g_oth_nand)^4)+(cap_ts_29*(1-0)*sh_fd_hi+MAX(Mkt!$C$43-cap_ts_25*(1-0)*sh_fd_hi,0)*(1+g_oth_fd)^4))+Mkt!G116+Mkt!G117 -> 265.51469 | G14: =F14/F$4-1 -> 0.01864145
A15: 台積電設備占比＝SK 海力士、三星校準值（45.5%；若台積電也同樣偏低） | B15: =((cap_sk_27*1000/fx*sh_sk+cap_mu_27*sh_mu_27+cap_ss_27*1000/fx*sh_ss)+(((Mkt!$C$57-Mkt!$C$54+ind_cxmt)*sh_oth))*(1+g_oth_dram)^2+((Mkt!$C$61*sh_oth))*(1+g_oth_nand)^2)+(cap_ts_27*(1-0)*sh_sk+MAX(Mkt!$C$43-cap_ts_25*(1-0)*sh_sk,0)*(1+g_oth_fd)^2)+Mkt!E50*(((cap_sk_27*1000/fx*sh_sk+cap_mu_27*sh_mu_27+cap_ss_27*1000/fx*sh_ss)+(((Mkt!$C$57-Mkt!$C$54+ind_cxmt)*sh_oth))*(1+g_oth_dram)^2+((Mkt!$C$61*sh_oth))*(1+g_oth_nand)^2)+(cap_ts_27*(1-0)*sh_sk+MAX(Mkt!$C$43-cap_ts_25*(1-0)*sh_sk,0)*(1+g_oth_fd)^2))+Mkt!E116+Mkt!E117 -> 212.15772 | C15: =B15/B$4-1 -> -0.027805255 | D15: =((cap_sk_28*1000/fx*sh_sk+cap_mu_28*sh_mu_27+cap_ss_28*1000/fx*sh_ss)+(((Mkt!$C$57-Mkt!$C$54+ind_cxmt)*sh_oth))*(1+g_oth_dram)^3+((Mkt!$C$61*sh_oth))*(1+g_oth_nand)^3)+(cap_ts_28*(1-0)*sh_sk+MAX(Mkt!$C$43-cap_ts_25*(1-0)*sh_sk,0)*(1+g_oth_fd)^3)+Mkt!F50*(((cap_sk_28*1000/fx*sh_sk+cap_mu_28*sh_mu_27+cap_ss_28*1000/fx*sh_ss)+(((Mkt!$C$57-Mkt!$C$54+ind_cxmt)*sh_oth))*(1+g_oth_dram)^3+((Mkt!$C$61*sh_oth))*(1+g_oth_nand)^3)+(cap_ts_28*(1-0)*sh_sk+MAX(Mkt!$C$43-cap_ts_25*(1-0)*sh_sk,0)*(1+g_oth_fd)^3))+Mkt!F116+Mkt!F117 -> 238.05859 | E15: =D15/D$4-1 -> -0.032394745 | F15: =((cap_sk_29*1000/fx*sh_sk+cap_mu_29*sh_mu_27+cap_ss_29*1000/fx*sh_ss)+(((Mkt!$C$57-Mkt!$C$54+ind_cxmt)*sh_oth))*(1+g_oth_dram)^4+((Mkt!$C$61*sh_oth))*(1+g_oth_nand)^4)+(cap_ts_29*(1-0)*sh_sk+MAX(Mkt!$C$43-cap_ts_25*(1-0)*sh_sk,0)*(1+g_oth_fd)^4)+Mkt!G50*(((cap_sk_29*1000/fx*sh_sk+cap_mu_29*sh_mu_27+cap_ss_29*1000/fx*sh_ss)+(((Mkt!$C$57-Mkt!$C$54+ind_cxmt)*sh_oth))*(1+g_oth_dram)^4+((Mkt!$C$61*sh_oth))*(1+g_oth_nand)^4)+(cap_ts_29*(1-0)*sh_sk+MAX(Mkt!$C$43-cap_ts_25*(1-0)*sh_sk,0)*(1+g_oth_fd)^4))+Mkt!G116+Mkt!G117 -> 252.50374 | G15: =F15/F$4-1 -> -0.031274759
A16: 台積電資本支出扣除先進封裝／光罩等 10%（設備同比例；上限，見 TSMC 頁） | B16: =((cap_sk_27*1000/fx*sh_sk+cap_mu_27*sh_mu_27+cap_ss_27*1000/fx*sh_ss)+(((Mkt!$C$57-Mkt!$C$54+ind_cxmt)*sh_oth))*(1+g_oth_dram)^2+((Mkt!$C$61*sh_oth))*(1+g_oth_nand)^2)+(cap_ts_27*(1-pk_ts_lo)*sh_fd+MAX(Mkt!$C$43-cap_ts_25*(1-pk_ts_lo)*sh_fd,0)*(1+g_oth_fd)^2)+Mkt!E50*(((cap_sk_27*1000/fx*sh_sk+cap_mu_27*sh_mu_27+cap_ss_27*1000/fx*sh_ss)+(((Mkt!$C$57-Mkt!$C$54+ind_cxmt)*sh_oth))*(1+g_oth_dram)^2+((Mkt!$C$61*sh_oth))*(1+g_oth_nand)^2)+(cap_ts_27*(1-pk_ts_lo)*sh_fd+MAX(Mkt!$C$43-cap_ts_25*(1-pk_ts_lo)*sh_fd,0)*(1+g_oth_fd)^2))+Mkt!E116+Mkt!E117 -> 216.12125 | C16: =B16/B$4-1 -> -0.009642727 | D16: =((cap_sk_28*1000/fx*sh_sk+cap_mu_28*sh_mu_27+cap_ss_28*1000/fx*sh_ss)+(((Mkt!$C$57-Mkt!$C$54+ind_cxmt)*sh_oth))*(1+g_oth_dram)^3+((Mkt!$C$61*sh_oth))*(1+g_oth_nand)^3)+(cap_ts_28*(1-pk_ts_lo)*sh_fd+MAX(Mkt!$C$43-cap_ts_25*(1-pk_ts_lo)*sh_fd,0)*(1+g_oth_fd)^3)+Mkt!F50*(((cap_sk_28*1000/fx*sh_sk+cap_mu_28*sh_mu_27+cap_ss_28*1000/fx*sh_ss)+(((Mkt!$C$57-Mkt!$C$54+ind_cxmt)*sh_oth))*(1+g_oth_dram)^3+((Mkt!$C$61*sh_oth))*(1+g_oth_nand)^3)+(cap_ts_28*(1-pk_ts_lo)*sh_fd+MAX(Mkt!$C$43-cap_ts_25*(1-pk_ts_lo)*sh_fd,0)*(1+g_oth_fd)^3))+Mkt!F116+Mkt!F117 -> 243.26466 | E16: =D16/D$4-1 -> -0.01123434 | F16: =((cap_sk_29*1000/fx*sh_sk+cap_mu_29*sh_mu_27+cap_ss_29*1000/fx*sh_ss)+(((Mkt!$C$57-Mkt!$C$54+ind_cxmt)*sh_oth))*(1+g_oth_dram)^4+((Mkt!$C$61*sh_oth))*(1+g_oth_nand)^4)+(cap_ts_29*(1-pk_ts_lo)*sh_fd+MAX(Mkt!$C$43-cap_ts_25*(1-pk_ts_lo)*sh_fd,0)*(1+g_oth_fd)^4)+Mkt!G50*(((cap_sk_29*1000/fx*sh_sk+cap_mu_29*sh_mu_27+cap_ss_29*1000/fx*sh_ss)+(((Mkt!$C$57-Mkt!$C$54+ind_cxmt)*sh_oth))*(1+g_oth_dram)^4+((Mkt!$C$61*sh_oth))*(1+g_oth_nand)^4)+(cap_ts_29*(1-pk_ts_lo)*sh_fd+MAX(Mkt!$C$43-cap_ts_25*(1-pk_ts_lo)*sh_fd,0)*(1+g_oth_fd)^4))+Mkt!G116+Mkt!G117 -> 257.82863 | G16: =F16/F$4-1 -> -0.010845934
A17: 台積電資本支出扣除先進封裝／光罩等 20%（上限） | B17: =((cap_sk_27*1000/fx*sh_sk+cap_mu_27*sh_mu_27+cap_ss_27*1000/fx*sh_ss)+(((Mkt!$C$57-Mkt!$C$54+ind_cxmt)*sh_oth))*(1+g_oth_dram)^2+((Mkt!$C$61*sh_oth))*(1+g_oth_nand)^2)+(cap_ts_27*(1-pk_ts_hi)*sh_fd+MAX(Mkt!$C$43-cap_ts_25*(1-pk_ts_hi)*sh_fd,0)*(1+g_oth_fd)^2)+Mkt!E50*(((cap_sk_27*1000/fx*sh_sk+cap_mu_27*sh_mu_27+cap_ss_27*1000/fx*sh_ss)+(((Mkt!$C$57-Mkt!$C$54+ind_cxmt)*sh_oth))*(1+g_oth_dram)^2+((Mkt!$C$61*sh_oth))*(1+g_oth_nand)^2)+(cap_ts_27*(1-pk_ts_hi)*sh_fd+MAX(Mkt!$C$43-cap_ts_25*(1-pk_ts_hi)*sh_fd,0)*(1+g_oth_fd)^2))+Mkt!E116+Mkt!E117 -> 214.01696 | C17: =B17/B$4-1 -> -0.019285454 | D17: =((cap_sk_28*1000/fx*sh_sk+cap_mu_28*sh_mu_27+cap_ss_28*1000/fx*sh_ss)+(((Mkt!$C$57-Mkt!$C$54+ind_cxmt)*sh_oth))*(1+g_oth_dram)^3+((Mkt!$C$61*sh_oth))*(1+g_oth_nand)^3)+(cap_ts_28*(1-pk_ts_hi)*sh_fd+MAX(Mkt!$C$43-cap_ts_25*(1-pk_ts_hi)*sh_fd,0)*(1+g_oth_fd)^3)+Mkt!F50*(((cap_sk_28*1000/fx*sh_sk+cap_mu_28*sh_mu_27+cap_ss_28*1000/fx*sh_ss)+(((Mkt!$C$57-Mkt!$C$54+ind_cxmt)*sh_oth))*(1+g_oth_dram)^3+((Mkt!$C$61*sh_oth))*(1+g_oth_nand)^3)+(cap_ts_28*(1-pk_ts_hi)*sh_fd+MAX(Mkt!$C$43-cap_ts_25*(1-pk_ts_hi)*sh_fd,0)*(1+g_oth_fd)^3))+Mkt!F116+Mkt!F117 -> 240.50069 | E17: =D17/D$4-1 -> -0.02246868 | F17: =((cap_sk_29*1000/fx*sh_sk+cap_mu_29*sh_mu_27+cap_ss_29*1000/fx*sh_ss)+(((Mkt!$C$57-Mkt!$C$54+ind_cxmt)*sh_oth))*(1+g_oth_dram)^4+((Mkt!$C$61*sh_oth))*(1+g_oth_nand)^4)+(cap_ts_29*(1-pk_ts_hi)*sh_fd+MAX(Mkt!$C$43-cap_ts_25*(1-pk_ts_hi)*sh_fd,0)*(1+g_oth_fd)^4)+Mkt!G50*(((cap_sk_29*1000/fx*sh_sk+cap_mu_29*sh_mu_27+cap_ss_29*1000/fx*sh_ss)+(((Mkt!$C$57-Mkt!$C$54+ind_cxmt)*sh_oth))*(1+g_oth_dram)^4+((Mkt!$C$61*sh_oth))*(1+g_oth_nand)^4)+(cap_ts_29*(1-pk_ts_hi)*sh_fd+MAX(Mkt!$C$43-cap_ts_25*(1-pk_ts_hi)*sh_fd,0)*(1+g_oth_fd)^4))+Mkt!G116+Mkt!G117 -> 255.00158 | G17: =F17/F$4-1 -> -0.021691869
A18: 匯率 低（1,350；重新校準） | B18: =((cap_sk_27*1000/fx_lo*((Mkt!$C$73-((Mkt!$C$57-Mkt!$C$54+ind_cxmt+Mkt!$C$61)*sh_oth)-(cap_mu_25*sh_mu_25))/(cap_sk_25*1000/fx_lo+cap_ssds_25*ss_mem*1000/fx_lo))+cap_mu_27*sh_mu_27+cap_ss_27*1000/fx_lo*((Mkt!$C$73-((Mkt!$C$57-Mkt!$C$54+ind_cxmt+Mkt!$C$61)*sh_oth)-(cap_mu_25*sh_mu_25))/(cap_sk_25*1000/fx_lo+cap_ssds_25*ss_mem*1000/fx_lo)))+(((Mkt!$C$57-Mkt!$C$54+ind_cxmt)*sh_oth))*(1+g_oth_dram)^2+((Mkt!$C$61*sh_oth))*(1+g_oth_nand)^2)+(cap_ts_27*(1-0)*sh_fd+MAX(Mkt!$C$43-cap_ts_25*(1-0)*sh_fd,0)*(1+g_oth_fd)^2)+Mkt!E50*(((cap_sk_27*1000/fx_lo*((Mkt!$C$73-((Mkt!$C$57-Mkt!$C$54+ind_cxmt+Mkt!$C$61)*sh_oth)-(cap_mu_25*sh_mu_25))/(cap_sk_25*1000/fx_lo+cap_ssds_25*ss_mem*1000/fx_lo))+cap_mu_27*sh_mu_27+cap_ss_27*1000/fx_lo*((Mkt!$C$73-((Mkt!$C$57-Mkt!$C$54+ind_cxmt+Mkt!$C$61)*sh_oth)-(cap_mu_25*sh_mu_25))/(cap_sk_25*1000/fx_lo+cap_ssds_25*ss_mem*1000/fx_lo)))+(((Mkt!$C$57-Mkt!$C$54+ind_cxmt)*sh_oth))*(1+g_oth_dram)^2+((Mkt!$C$61*sh_oth))*(1+g_oth_nand)^2)+(cap_ts_27*(1-0)*sh_fd+MAX(Mkt!$C$43-cap_ts_25*(1-0)*sh_fd,0)*(1+g_oth_fd)^2))+Mkt!E116+Mkt!E117 -> 218.22554 | C18: =B18/B$4-1 -> 0 | D18: =((cap_sk_28*1000/fx_lo*((Mkt!$C$73-((Mkt!$C$57-Mkt!$C$54+ind_cxmt+Mkt!$C$61)*sh_oth)-(cap_mu_25*sh_mu_25))/(cap_sk_25*1000/fx_lo+cap_ssds_25*ss_mem*1000/fx_lo))+cap_mu_28*sh_mu_27+cap_ss_28*1000/fx_lo*((Mkt!$C$73-((Mkt!$C$57-Mkt!$C$54+ind_cxmt+Mkt!$C$61)*sh_oth)-(cap_mu_25*sh_mu_25))/(cap_sk_25*1000/fx_lo+cap_ssds_25*ss_mem*1000/fx_lo)))+(((Mkt!$C$57-Mkt!$C$54+ind_cxmt)*sh_oth))*(1+g_oth_dram)^3+((Mkt!$C$61*sh_oth))*(1+g_oth_nand)^3)+(cap_ts_28*(1-0)*sh_fd+MAX(Mkt!$C$43-cap_ts_25*(1-0)*sh_fd,0)*(1+g_oth_fd)^3)+Mkt!F50*(((cap_sk_28*1000/fx_lo*((Mkt!$C$73-((Mkt!$C$57-Mkt!$C$54+ind_cxmt+Mkt!$C$61)*sh_oth)-(cap_mu_25*sh_mu_25))/(cap_sk_25*1000/fx_lo+cap_ssds_25*ss_mem*1000/fx_lo))+cap_mu_28*sh_mu_27+cap_ss_28*1000/fx_lo*((Mkt!$C$73-((Mkt!$C$57-Mkt!$C$54+ind_cxmt+Mkt!$C$61)*sh_oth)-(cap_mu_25*sh_mu_25))/(cap_sk_25*1000/fx_lo+cap_ssds_25*ss_mem*1000/fx_lo)))+(((Mkt!$C$57-Mkt!$C$54+ind_cxmt)*sh_oth))*(1+g_oth_dram)^3+((Mkt!$C$61*sh_oth))*(1+g_oth_nand)^3)+(cap_ts_28*(1-0)*sh_fd+MAX(Mkt!$C$43-cap_ts_25*(1-0)*sh_fd,0)*(1+g_oth_fd)^3))+Mkt!F116+Mkt!F117 -> 246.02863 | E18: =D18/D$4-1 -> 0 | F18: =((cap_sk_29*1000/fx_lo*((Mkt!$C$73-((Mkt!$C$57-Mkt!$C$54+ind_cxmt+Mkt!$C$61)*sh_oth)-(cap_mu_25*sh_mu_25))/(cap_sk_25*1000/fx_lo+cap_ssds_25*ss_mem*1000/fx_lo))+cap_mu_29*sh_mu_27+cap_ss_29*1000/fx_lo*((Mkt!$C$73-((Mkt!$C$57-Mkt!$C$54+ind_cxmt+Mkt!$C$61)*sh_oth)-(cap_mu_25*sh_mu_25))/(cap_sk_25*1000/fx_lo+cap_ssds_25*ss_mem*1000/fx_lo)))+(((Mkt!$C$57-Mkt!$C$54+ind_cxmt)*sh_oth))*(1+g_oth_dram)^4+((Mkt!$C$61*sh_oth))*(1+g_oth_nand)^4)+(cap_ts_29*(1-0)*sh_fd+MAX(Mkt!$C$43-cap_ts_25*(1-0)*sh_fd,0)*(1+g_oth_fd)^4)+Mkt!G50*(((cap_sk_29*1000/fx_lo*((Mkt!$C$73-((Mkt!$C$57-Mkt!$C$54+ind_cxmt+Mkt!$C$61)*sh_oth)-(cap_mu_25*sh_mu_25))/(cap_sk_25*1000/fx_lo+cap_ssds_25*ss_mem*1000/fx_lo))+cap_mu_29*sh_mu_27+cap_ss_29*1000/fx_lo*((Mkt!$C$73-((Mkt!$C$57-Mkt!$C$54+ind_cxmt+Mkt!$C$61)*sh_oth)-(cap_mu_25*sh_mu_25))/(cap_sk_25*1000/fx_lo+cap_ssds_25*ss_mem*1000/fx_lo)))+(((Mkt!$C$57-Mkt!$C$54+ind_cxmt)*sh_oth))*(1+g_oth_dram)^4+((Mkt!$C$61*sh_oth))*(1+g_oth_nand)^4)+(cap_ts_29*(1-0)*sh_fd+MAX(Mkt!$C$43-cap_ts_25*(1-0)*sh_fd,0)*(1+g_oth_fd)^4))+Mkt!G116+Mkt!G117 -> 260.65569 | G18: =F18/F$4-1 -> 0 | H18: 標「重新校準」的列：2025 輸入改變後重新解出 SK、三星共用占比。匯率改變時校準值同比例改變，設備金額不變（匯率對 2026 年以後設備無影響）
A19: 匯率 高（1,500；重新校準） | B19: =((cap_sk_27*1000/fx_hi*((Mkt!$C$73-((Mkt!$C$57-Mkt!$C$54+ind_cxmt+Mkt!$C$61)*sh_oth)-(cap_mu_25*sh_mu_25))/(cap_sk_25*1000/fx_hi+cap_ssds_25*ss_mem*1000/fx_hi))+cap_mu_27*sh_mu_27+cap_ss_27*1000/fx_hi*((Mkt!$C$73-((Mkt!$C$57-Mkt!$C$54+ind_cxmt+Mkt!$C$61)*sh_oth)-(cap_mu_25*sh_mu_25))/(cap_sk_25*1000/fx_hi+cap_ssds_25*ss_mem*1000/fx_hi)))+(((Mkt!$C$57-Mkt!$C$54+ind_cxmt)*sh_oth))*(1+g_oth_dram)^2+((Mkt!$C$61*sh_oth))*(1+g_oth_nand)^2)+(cap_ts_27*(1-0)*sh_fd+MAX(Mkt!$C$43-cap_ts_25*(1-0)*sh_fd,0)*(1+g_oth_fd)^2)+Mkt!E50*(((cap_sk_27*1000/fx_hi*((Mkt!$C$73-((Mkt!$C$57-Mkt!$C$54+ind_cxmt+Mkt!$C$61)*sh_oth)-(cap_mu_25*sh_mu_25))/(cap_sk_25*1000/fx_hi+cap_ssds_25*ss_mem*1000/fx_hi))+cap_mu_27*sh_mu_27+cap_ss_27*1000/fx_hi*((Mkt!$C$73-((Mkt!$C$57-Mkt!$C$54+ind_cxmt+Mkt!$C$61)*sh_oth)-(cap_mu_25*sh_mu_25))/(cap_sk_25*1000/fx_hi+cap_ssds_25*ss_mem*1000/fx_hi)))+(((Mkt!$C$57-Mkt!$C$54+ind_cxmt)*sh_oth))*(1+g_oth_dram)^2+((Mkt!$C$61*sh_oth))*(1+g_oth_nand)^2)+(cap_ts_27*(1-0)*sh_fd+MAX(Mkt!$C$43-cap_ts_25*(1-0)*sh_fd,0)*(1+g_oth_fd)^2))+Mkt!E116+Mkt!E117 -> 218.22554 | C19: =B19/B$4-1 -> 0 | D19: =((cap_sk_28*1000/fx_hi*((Mkt!$C$73-((Mkt!$C$57-Mkt!$C$54+ind_cxmt+Mkt!$C$61)*sh_oth)-(cap_mu_25*sh_mu_25))/(cap_sk_25*1000/fx_hi+cap_ssds_25*ss_mem*1000/fx_hi))+cap_mu_28*sh_mu_27+cap_ss_28*1000/fx_hi*((Mkt!$C$73-((Mkt!$C$57-Mkt!$C$54+ind_cxmt+Mkt!$C$61)*sh_oth)-(cap_mu_25*sh_mu_25))/(cap_sk_25*1000/fx_hi+cap_ssds_25*ss_mem*1000/fx_hi)))+(((Mkt!$C$57-Mkt!$C$54+ind_cxmt)*sh_oth))*(1+g_oth_dram)^3+((Mkt!$C$61*sh_oth))*(1+g_oth_nand)^3)+(cap_ts_28*(1-0)*sh_fd+MAX(Mkt!$C$43-cap_ts_25*(1-0)*sh_fd,0)*(1+g_oth_fd)^3)+Mkt!F50*(((cap_sk_28*1000/fx_hi*((Mkt!$C$73-((Mkt!$C$57-Mkt!$C$54+ind_cxmt+Mkt!$C$61)*sh_oth)-(cap_mu_25*sh_mu_25))/(cap_sk_25*1000/fx_hi+cap_ssds_25*ss_mem*1000/fx_hi))+cap_mu_28*sh_mu_27+cap_ss_28*1000/fx_hi*((Mkt!$C$73-((Mkt!$C$57-Mkt!$C$54+ind_cxmt+Mkt!$C$61)*sh_oth)-(cap_mu_25*sh_mu_25))/(cap_sk_25*1000/fx_hi+cap_ssds_25*ss_mem*1000/fx_hi)))+(((Mkt!$C$57-Mkt!$C$54+ind_cxmt)*sh_oth))*(1+g_oth_dram)^3+((Mkt!$C$61*sh_oth))*(1+g_oth_nand)^3)+(cap_ts_28*(1-0)*sh_fd+MAX(Mkt!$C$43-cap_ts_25*(1-0)*sh_fd,0)*(1+g_oth_fd)^3))+Mkt!F116+Mkt!F117 -> 246.02863 | E19: =D19/D$4-1 -> 0 | F19: =((cap_sk_29*1000/fx_hi*((Mkt!$C$73-((Mkt!$C$57-Mkt!$C$54+ind_cxmt+Mkt!$C$61)*sh_oth)-(cap_mu_25*sh_mu_25))/(cap_sk_25*1000/fx_hi+cap_ssds_25*ss_mem*1000/fx_hi))+cap_mu_29*sh_mu_27+cap_ss_29*1000/fx_hi*((Mkt!$C$73-((Mkt!$C$57-Mkt!$C$54+ind_cxmt+Mkt!$C$61)*sh_oth)-(cap_mu_25*sh_mu_25))/(cap_sk_25*1000/fx_hi+cap_ssds_25*ss_mem*1000/fx_hi)))+(((Mkt!$C$57-Mkt!$C$54+ind_cxmt)*sh_oth))*(1+g_oth_dram)^4+((Mkt!$C$61*sh_oth))*(1+g_oth_nand)^4)+(cap_ts_29*(1-0)*sh_fd+MAX(Mkt!$C$43-cap_ts_25*(1-0)*sh_fd,0)*(1+g_oth_fd)^4)+Mkt!G50*(((cap_sk_29*1000/fx_hi*((Mkt!$C$73-((Mkt!$C$57-Mkt!$C$54+ind_cxmt+Mkt!$C$61)*sh_oth)-(cap_mu_25*sh_mu_25))/(cap_sk_25*1000/fx_hi+cap_ssds_25*ss_mem*1000/fx_hi))+cap_mu_29*sh_mu_27+cap_ss_29*1000/fx_hi*((Mkt!$C$73-((Mkt!$C$57-Mkt!$C$54+ind_cxmt+Mkt!$C$61)*sh_oth)-(cap_mu_25*sh_mu_25))/(cap_sk_25*1000/fx_hi+cap_ssds_25*ss_mem*1000/fx_hi)))+(((Mkt!$C$57-Mkt!$C$54+ind_cxmt)*sh_oth))*(1+g_oth_dram)^4+((Mkt!$C$61*sh_oth))*(1+g_oth_nand)^4)+(cap_ts_29*(1-0)*sh_fd+MAX(Mkt!$C$43-cap_ts_25*(1-0)*sh_fd,0)*(1+g_oth_fd)^4))+Mkt!G116+Mkt!G117 -> 260.65569 | G19: =F19/F$4-1 -> 0
A20: SK 海力士 2025 資本支出 低（28 兆；重新校準） | B20: =((cap_sk_27*1000/fx*((Mkt!$C$73-((Mkt!$C$57-Mkt!$C$54+ind_cxmt+Mkt!$C$61)*sh_oth)-(cap_mu_25*sh_mu_25))/(cap_sk_25_lo*1000/fx+cap_ssds_25*ss_mem*1000/fx))+cap_mu_27*sh_mu_27+cap_ss_27*1000/fx*((Mkt!$C$73-((Mkt!$C$57-Mkt!$C$54+ind_cxmt+Mkt!$C$61)*sh_oth)-(cap_mu_25*sh_mu_25))/(cap_sk_25_lo*1000/fx+cap_ssds_25*ss_mem*1000/fx)))+(((Mkt!$C$57-Mkt!$C$54+ind_cxmt)*sh_oth))*(1+g_oth_dram)^2+((Mkt!$C$61*sh_oth))*(1+g_oth_nand)^2)+(cap_ts_27*(1-0)*sh_fd+MAX(Mkt!$C$43-cap_ts_25*(1-0)*sh_fd,0)*(1+g_oth_fd)^2)+Mkt!E50*(((cap_sk_27*1000/fx*((Mkt!$C$73-((Mkt!$C$57-Mkt!$C$54+ind_cxmt+Mkt!$C$61)*sh_oth)-(cap_mu_25*sh_mu_25))/(cap_sk_25_lo*1000/fx+cap_ssds_25*ss_mem*1000/fx))+cap_mu_27*sh_mu_27+cap_ss_27*1000/fx*((Mkt!$C$73-((Mkt!$C$57-Mkt!$C$54+ind_cxmt+Mkt!$C$61)*sh_oth)-(cap_mu_25*sh_mu_25))/(cap_sk_25_lo*1000/fx+cap_ssds_25*ss_mem*1000/fx)))+(((Mkt!$C$57-Mkt!$C$54+ind_cxmt)*sh_oth))*(1+g_oth_dram)^2+((Mkt!$C$61*sh_oth))*(1+g_oth_nand)^2)+(cap_ts_27*(1-0)*sh_fd+MAX(Mkt!$C$43-cap_ts_25*(1-0)*sh_fd,0)*(1+g_oth_fd)^2))+Mkt!E116+Mkt!E117 -> 219.7479 | C20: =B20/B$4-1 -> 0.0069761246 | D20: =((cap_sk_28*1000/fx*((Mkt!$C$73-((Mkt!$C$57-Mkt!$C$54+ind_cxmt+Mkt!$C$61)*sh_oth)-(cap_mu_25*sh_mu_25))/(cap_sk_25_lo*1000/fx+cap_ssds_25*ss_mem*1000/fx))+cap_mu_28*sh_mu_27+cap_ss_28*1000/fx*((Mkt!$C$73-((Mkt!$C$57-Mkt!$C$54+ind_cxmt+Mkt!$C$61)*sh_oth)-(cap_mu_25*sh_mu_25))/(cap_sk_25_lo*1000/fx+cap_ssds_25*ss_mem*1000/fx)))+(((Mkt!$C$57-Mkt!$C$54+ind_cxmt)*sh_oth))*(1+g_oth_dram)^3+((Mkt!$C$61*sh_oth))*(1+g_oth_nand)^3)+(cap_ts_28*(1-0)*sh_fd+MAX(Mkt!$C$43-cap_ts_25*(1-0)*sh_fd,0)*(1+g_oth_fd)^3)+Mkt!F50*(((cap_sk_28*1000/fx*((Mkt!$C$73-((Mkt!$C$57-Mkt!$C$54+ind_cxmt+Mkt!$C$61)*sh_oth)-(cap_mu_25*sh_mu_25))/(cap_sk_25_lo*1000/fx+cap_ssds_25*ss_mem*1000/fx))+cap_mu_28*sh_mu_27+cap_ss_28*1000/fx*((Mkt!$C$73-((Mkt!$C$57-Mkt!$C$54+ind_cxmt+Mkt!$C$61)*sh_oth)-(cap_mu_25*sh_mu_25))/(cap_sk_25_lo*1000/fx+cap_ssds_25*ss_mem*1000/fx)))+(((Mkt!$C$57-Mkt!$C$54+ind_cxmt)*sh_oth))*(1+g_oth_dram)^3+((Mkt!$C$61*sh_oth))*(1+g_oth_nand)^3)+(cap_ts_28*(1-0)*sh_fd+MAX(Mkt!$C$43-cap_ts_25*(1-0)*sh_fd,0)*(1+g_oth_fd)^3))+Mkt!F116+Mkt!F117 -> 247.73647 | E20: =D20/D$4-1 -> 0.0069416356 | F20: =((cap_sk_29*1000/fx*((Mkt!$C$73-((Mkt!$C$57-Mkt!$C$54+ind_cxmt+Mkt!$C$61)*sh_oth)-(cap_mu_25*sh_mu_25))/(cap_sk_25_lo*1000/fx+cap_ssds_25*ss_mem*1000/fx))+cap_mu_29*sh_mu_27+cap_ss_29*1000/fx*((Mkt!$C$73-((Mkt!$C$57-Mkt!$C$54+ind_cxmt+Mkt!$C$61)*sh_oth)-(cap_mu_25*sh_mu_25))/(cap_sk_25_lo*1000/fx+cap_ssds_25*ss_mem*1000/fx)))+(((Mkt!$C$57-Mkt!$C$54+ind_cxmt)*sh_oth))*(1+g_oth_dram)^4+((Mkt!$C$61*sh_oth))*(1+g_oth_nand)^4)+(cap_ts_29*(1-0)*sh_fd+MAX(Mkt!$C$43-cap_ts_25*(1-0)*sh_fd,0)*(1+g_oth_fd)^4)+Mkt!G50*(((cap_sk_29*1000/fx*((Mkt!$C$73-((Mkt!$C$57-Mkt!$C$54+ind_cxmt+Mkt!$C$61)*sh_oth)-(cap_mu_25*sh_mu_25))/(cap_sk_25_lo*1000/fx+cap_ssds_25*ss_mem*1000/fx))+cap_mu_29*sh_mu_27+cap_ss_29*1000/fx*((Mkt!$C$73-((Mkt!$C$57-Mkt!$C$54+ind_cxmt+Mkt!$C$61)*sh_oth)-(cap_mu_25*sh_mu_25))/(cap_sk_25_lo*1000/fx+cap_ssds_25*ss_mem*1000/fx)))+(((Mkt!$C$57-Mkt!$C$54+ind_cxmt)*sh_oth))*(1+g_oth_dram)^4+((Mkt!$C$61*sh_oth))*(1+g_oth_nand)^4)+(cap_ts_29*(1-0)*sh_fd+MAX(Mkt!$C$43-cap_ts_25*(1-0)*sh_fd,0)*(1+g_oth_fd)^4))+Mkt!G116+Mkt!G117 -> 262.41083 | G20: =F20/F$4-1 -> 0.006733568
A21: 三星 DS 記憶體占比 65%（重新校準） | B21: =((cap_sk_27*1000/fx*((Mkt!$C$73-((Mkt!$C$57-Mkt!$C$54+ind_cxmt+Mkt!$C$61)*sh_oth)-(cap_mu_25*sh_mu_25))/(cap_sk_25*1000/fx+cap_ssds_25*ss_mem_lo*1000/fx))+cap_mu_27*sh_mu_27+cap_ss_27*1000/fx*((Mkt!$C$73-((Mkt!$C$57-Mkt!$C$54+ind_cxmt+Mkt!$C$61)*sh_oth)-(cap_mu_25*sh_mu_25))/(cap_sk_25*1000/fx+cap_ssds_25*ss_mem_lo*1000/fx)))+(((Mkt!$C$57-Mkt!$C$54+ind_cxmt)*sh_oth))*(1+g_oth_dram)^2+((Mkt!$C$61*sh_oth))*(1+g_oth_nand)^2)+(cap_ts_27*(1-0)*sh_fd+MAX(Mkt!$C$43-cap_ts_25*(1-0)*sh_fd,0)*(1+g_oth_fd)^2)+Mkt!E50*(((cap_sk_27*1000/fx*((Mkt!$C$73-((Mkt!$C$57-Mkt!$C$54+ind_cxmt+Mkt!$C$61)*sh_oth)-(cap_mu_25*sh_mu_25))/(cap_sk_25*1000/fx+cap_ssds_25*ss_mem_lo*1000/fx))+cap_mu_27*sh_mu_27+cap_ss_27*1000/fx*((Mkt!$C$73-((Mkt!$C$57-Mkt!$C$54+ind_cxmt+Mkt!$C$61)*sh_oth)-(cap_mu_25*sh_mu_25))/(cap_sk_25*1000/fx+cap_ssds_25*ss_mem_lo*1000/fx)))+(((Mkt!$C$57-Mkt!$C$54+ind_cxmt)*sh_oth))*(1+g_oth_dram)^2+((Mkt!$C$61*sh_oth))*(1+g_oth_nand)^2)+(cap_ts_27*(1-0)*sh_fd+MAX(Mkt!$C$43-cap_ts_25*(1-0)*sh_fd,0)*(1+g_oth_fd)^2))+Mkt!E116+Mkt!E117 -> 221.6497 | C21: =B21/B$4-1 -> 0.015690959 | D21: =((cap_sk_28*1000/fx*((Mkt!$C$73-((Mkt!$C$57-Mkt!$C$54+ind_cxmt+Mkt!$C$61)*sh_oth)-(cap_mu_25*sh_mu_25))/(cap_sk_25*1000/fx+cap_ssds_25*ss_mem_lo*1000/fx))+cap_mu_28*sh_mu_27+cap_ss_28*1000/fx*((Mkt!$C$73-((Mkt!$C$57-Mkt!$C$54+ind_cxmt+Mkt!$C$61)*sh_oth)-(cap_mu_25*sh_mu_25))/(cap_sk_25*1000/fx+cap_ssds_25*ss_mem_lo*1000/fx)))+(((Mkt!$C$57-Mkt!$C$54+ind_cxmt)*sh_oth))*(1+g_oth_dram)^3+((Mkt!$C$61*sh_oth))*(1+g_oth_nand)^3)+(cap_ts_28*(1-0)*sh_fd+MAX(Mkt!$C$43-cap_ts_25*(1-0)*sh_fd,0)*(1+g_oth_fd)^3)+Mkt!F50*(((cap_sk_28*1000/fx*((Mkt!$C$73-((Mkt!$C$57-Mkt!$C$54+ind_cxmt+Mkt!$C$61)*sh_oth)-(cap_mu_25*sh_mu_25))/(cap_sk_25*1000/fx+cap_ssds_25*ss_mem_lo*1000/fx))+cap_mu_28*sh_mu_27+cap_ss_28*1000/fx*((Mkt!$C$73-((Mkt!$C$57-Mkt!$C$54+ind_cxmt+Mkt!$C$61)*sh_oth)-(cap_mu_25*sh_mu_25))/(cap_sk_25*1000/fx+cap_ssds_25*ss_mem_lo*1000/fx)))+(((Mkt!$C$57-Mkt!$C$54+ind_cxmt)*sh_oth))*(1+g_oth_dram)^3+((Mkt!$C$61*sh_oth))*(1+g_oth_nand)^3)+(cap_ts_28*(1-0)*sh_fd+MAX(Mkt!$C$43-cap_ts_25*(1-0)*sh_fd,0)*(1+g_oth_fd)^3))+Mkt!F116+Mkt!F117 -> 249.86997 | E21: =D21/D$4-1 -> 0.015613385 | F21: =((cap_sk_29*1000/fx*((Mkt!$C$73-((Mkt!$C$57-Mkt!$C$54+ind_cxmt+Mkt!$C$61)*sh_oth)-(cap_mu_25*sh_mu_25))/(cap_sk_25*1000/fx+cap_ssds_25*ss_mem_lo*1000/fx))+cap_mu_29*sh_mu_27+cap_ss_29*1000/fx*((Mkt!$C$73-((Mkt!$C$57-Mkt!$C$54+ind_cxmt+Mkt!$C$61)*sh_oth)-(cap_mu_25*sh_mu_25))/(cap_sk_25*1000/fx+cap_ssds_25*ss_mem_lo*1000/fx)))+(((Mkt!$C$57-Mkt!$C$54+ind_cxmt)*sh_oth))*(1+g_oth_dram)^4+((Mkt!$C$61*sh_oth))*(1+g_oth_nand)^4)+(cap_ts_29*(1-0)*sh_fd+MAX(Mkt!$C$43-cap_ts_25*(1-0)*sh_fd,0)*(1+g_oth_fd)^4)+Mkt!G50*(((cap_sk_29*1000/fx*((Mkt!$C$73-((Mkt!$C$57-Mkt!$C$54+ind_cxmt+Mkt!$C$61)*sh_oth)-(cap_mu_25*sh_mu_25))/(cap_sk_25*1000/fx+cap_ssds_25*ss_mem_lo*1000/fx))+cap_mu_29*sh_mu_27+cap_ss_29*1000/fx*((Mkt!$C$73-((Mkt!$C$57-Mkt!$C$54+ind_cxmt+Mkt!$C$61)*sh_oth)-(cap_mu_25*sh_mu_25))/(cap_sk_25*1000/fx+cap_ssds_25*ss_mem_lo*1000/fx)))+(((Mkt!$C$57-Mkt!$C$54+ind_cxmt)*sh_oth))*(1+g_oth_dram)^4+((Mkt!$C$61*sh_oth))*(1+g_oth_nand)^4)+(cap_ts_29*(1-0)*sh_fd+MAX(Mkt!$C$43-cap_ts_25*(1-0)*sh_fd,0)*(1+g_oth_fd)^4))+Mkt!G116+Mkt!G117 -> 264.60342 | G21: =F21/F$4-1 -> 0.015145391
A22: 三星 DS 記憶體占比 90%（重新校準） | B22: =((cap_sk_27*1000/fx*((Mkt!$C$73-((Mkt!$C$57-Mkt!$C$54+ind_cxmt+Mkt!$C$61)*sh_oth)-(cap_mu_25*sh_mu_25))/(cap_sk_25*1000/fx+cap_ssds_25*ss_mem_hi*1000/fx))+cap_mu_27*sh_mu_27+cap_ss_27*1000/fx*((Mkt!$C$73-((Mkt!$C$57-Mkt!$C$54+ind_cxmt+Mkt!$C$61)*sh_oth)-(cap_mu_25*sh_mu_25))/(cap_sk_25*1000/fx+cap_ssds_25*ss_mem_hi*1000/fx)))+(((Mkt!$C$57-Mkt!$C$54+ind_cxmt)*sh_oth))*(1+g_oth_dram)^2+((Mkt!$C$61*sh_oth))*(1+g_oth_nand)^2)+(cap_ts_27*(1-0)*sh_fd+MAX(Mkt!$C$43-cap_ts_25*(1-0)*sh_fd,0)*(1+g_oth_fd)^2)+Mkt!E50*(((cap_sk_27*1000/fx*((Mkt!$C$73-((Mkt!$C$57-Mkt!$C$54+ind_cxmt+Mkt!$C$61)*sh_oth)-(cap_mu_25*sh_mu_25))/(cap_sk_25*1000/fx+cap_ssds_25*ss_mem_hi*1000/fx))+cap_mu_27*sh_mu_27+cap_ss_27*1000/fx*((Mkt!$C$73-((Mkt!$C$57-Mkt!$C$54+ind_cxmt+Mkt!$C$61)*sh_oth)-(cap_mu_25*sh_mu_25))/(cap_sk_25*1000/fx+cap_ssds_25*ss_mem_hi*1000/fx)))+(((Mkt!$C$57-Mkt!$C$54+ind_cxmt)*sh_oth))*(1+g_oth_dram)^2+((Mkt!$C$61*sh_oth))*(1+g_oth_nand)^2)+(cap_ts_27*(1-0)*sh_fd+MAX(Mkt!$C$43-cap_ts_25*(1-0)*sh_fd,0)*(1+g_oth_fd)^2))+Mkt!E116+Mkt!E117 -> 213.92538 | C22: =B22/B$4-1 -> -0.019705112 | D22: =((cap_sk_28*1000/fx*((Mkt!$C$73-((Mkt!$C$57-Mkt!$C$54+ind_cxmt+Mkt!$C$61)*sh_oth)-(cap_mu_25*sh_mu_25))/(cap_sk_25*1000/fx+cap_ssds_25*ss_mem_hi*1000/fx))+cap_mu_28*sh_mu_27+cap_ss_28*1000/fx*((Mkt!$C$73-((Mkt!$C$57-Mkt!$C$54+ind_cxmt+Mkt!$C$61)*sh_oth)-(cap_mu_25*sh_mu_25))/(cap_sk_25*1000/fx+cap_ssds_25*ss_mem_hi*1000/fx)))+(((Mkt!$C$57-Mkt!$C$54+ind_cxmt)*sh_oth))*(1+g_oth_dram)^3+((Mkt!$C$61*sh_oth))*(1+g_oth_nand)^3)+(cap_ts_28*(1-0)*sh_fd+MAX(Mkt!$C$43-cap_ts_25*(1-0)*sh_fd,0)*(1+g_oth_fd)^3)+Mkt!F50*(((cap_sk_28*1000/fx*((Mkt!$C$73-((Mkt!$C$57-Mkt!$C$54+ind_cxmt+Mkt!$C$61)*sh_oth)-(cap_mu_25*sh_mu_25))/(cap_sk_25*1000/fx+cap_ssds_25*ss_mem_hi*1000/fx))+cap_mu_28*sh_mu_27+cap_ss_28*1000/fx*((Mkt!$C$73-((Mkt!$C$57-Mkt!$C$54+ind_cxmt+Mkt!$C$61)*sh_oth)-(cap_mu_25*sh_mu_25))/(cap_sk_25*1000/fx+cap_ssds_25*ss_mem_hi*1000/fx)))+(((Mkt!$C$57-Mkt!$C$54+ind_cxmt)*sh_oth))*(1+g_oth_dram)^3+((Mkt!$C$61*sh_oth))*(1+g_oth_nand)^3)+(cap_ts_28*(1-0)*sh_fd+MAX(Mkt!$C$43-cap_ts_25*(1-0)*sh_fd,0)*(1+g_oth_fd)^3))+Mkt!F116+Mkt!F117 -> 241.20457 | E22: =D22/D$4-1 -> -0.019607693 | F22: =((cap_sk_29*1000/fx*((Mkt!$C$73-((Mkt!$C$57-Mkt!$C$54+ind_cxmt+Mkt!$C$61)*sh_oth)-(cap_mu_25*sh_mu_25))/(cap_sk_25*1000/fx+cap_ssds_25*ss_mem_hi*1000/fx))+cap_mu_29*sh_mu_27+cap_ss_29*1000/fx*((Mkt!$C$73-((Mkt!$C$57-Mkt!$C$54+ind_cxmt+Mkt!$C$61)*sh_oth)-(cap_mu_25*sh_mu_25))/(cap_sk_25*1000/fx+cap_ssds_25*ss_mem_hi*1000/fx)))+(((Mkt!$C$57-Mkt!$C$54+ind_cxmt)*sh_oth))*(1+g_oth_dram)^4+((Mkt!$C$61*sh_oth))*(1+g_oth_nand)^4)+(cap_ts_29*(1-0)*sh_fd+MAX(Mkt!$C$43-cap_ts_25*(1-0)*sh_fd,0)*(1+g_oth_fd)^4)+Mkt!G50*(((cap_sk_29*1000/fx*((Mkt!$C$73-((Mkt!$C$57-Mkt!$C$54+ind_cxmt+Mkt!$C$61)*sh_oth)-(cap_mu_25*sh_mu_25))/(cap_sk_25*1000/fx+cap_ssds_25*ss_mem_hi*1000/fx))+cap_mu_29*sh_mu_27+cap_ss_29*1000/fx*((Mkt!$C$73-((Mkt!$C$57-Mkt!$C$54+ind_cxmt+Mkt!$C$61)*sh_oth)-(cap_mu_25*sh_mu_25))/(cap_sk_25*1000/fx+cap_ssds_25*ss_mem_hi*1000/fx)))+(((Mkt!$C$57-Mkt!$C$54+ind_cxmt)*sh_oth))*(1+g_oth_dram)^4+((Mkt!$C$61*sh_oth))*(1+g_oth_nand)^4)+(cap_ts_29*(1-0)*sh_fd+MAX(Mkt!$C$43-cap_ts_25*(1-0)*sh_fd,0)*(1+g_oth_fd)^4))+Mkt!G116+Mkt!G117 -> 255.69802 | G22: =F22/F$4-1 -> -0.019019975
A23: 台積電 2025 資本支出 低（40） | B23: =((cap_sk_27*1000/fx*sh_sk+cap_mu_27*sh_mu_27+cap_ss_27*1000/fx*sh_ss)+(((Mkt!$C$57-Mkt!$C$54+ind_cxmt)*sh_oth))*(1+g_oth_dram)^2+((Mkt!$C$61*sh_oth))*(1+g_oth_nand)^2)+(cap_ts_27*(1-0)*sh_fd+MAX(Mkt!$C$43-cap_ts_25_lo*(1-0)*sh_fd,0)*(1+g_oth_fd)^2)+Mkt!E50*(((cap_sk_27*1000/fx*sh_sk+cap_mu_27*sh_mu_27+cap_ss_27*1000/fx*sh_ss)+(((Mkt!$C$57-Mkt!$C$54+ind_cxmt)*sh_oth))*(1+g_oth_dram)^2+((Mkt!$C$61*sh_oth))*(1+g_oth_nand)^2)+(cap_ts_27*(1-0)*sh_fd+MAX(Mkt!$C$43-cap_ts_25_lo*(1-0)*sh_fd,0)*(1+g_oth_fd)^2))+Mkt!E116+Mkt!E117 -> 218.97961 | C23: =B23/B$4-1 -> 0.0034554742 | D23: =((cap_sk_28*1000/fx*sh_sk+cap_mu_28*sh_mu_27+cap_ss_28*1000/fx*sh_ss)+(((Mkt!$C$57-Mkt!$C$54+ind_cxmt)*sh_oth))*(1+g_oth_dram)^3+((Mkt!$C$61*sh_oth))*(1+g_oth_nand)^3)+(cap_ts_28*(1-0)*sh_fd+MAX(Mkt!$C$43-cap_ts_25_lo*(1-0)*sh_fd,0)*(1+g_oth_fd)^3)+Mkt!F50*(((cap_sk_28*1000/fx*sh_sk+cap_mu_28*sh_mu_27+cap_ss_28*1000/fx*sh_ss)+(((Mkt!$C$57-Mkt!$C$54+ind_cxmt)*sh_oth))*(1+g_oth_dram)^3+((Mkt!$C$61*sh_oth))*(1+g_oth_nand)^3)+(cap_ts_28*(1-0)*sh_fd+MAX(Mkt!$C$43-cap_ts_25_lo*(1-0)*sh_fd,0)*(1+g_oth_fd)^3))+Mkt!F116+Mkt!F117 -> 246.84302 | E23: =D23/D$4-1 -> 0.0033101779 | F23: =((cap_sk_29*1000/fx*sh_sk+cap_mu_29*sh_mu_27+cap_ss_29*1000/fx*sh_ss)+(((Mkt!$C$57-Mkt!$C$54+ind_cxmt)*sh_oth))*(1+g_oth_dram)^4+((Mkt!$C$61*sh_oth))*(1+g_oth_nand)^4)+(cap_ts_29*(1-0)*sh_fd+MAX(Mkt!$C$43-cap_ts_25_lo*(1-0)*sh_fd,0)*(1+g_oth_fd)^4)+Mkt!G50*(((cap_sk_29*1000/fx*sh_sk+cap_mu_29*sh_mu_27+cap_ss_29*1000/fx*sh_ss)+(((Mkt!$C$57-Mkt!$C$54+ind_cxmt)*sh_oth))*(1+g_oth_dram)^4+((Mkt!$C$61*sh_oth))*(1+g_oth_nand)^4)+(cap_ts_29*(1-0)*sh_fd+MAX(Mkt!$C$43-cap_ts_25_lo*(1-0)*sh_fd,0)*(1+g_oth_fd)^4))+Mkt!G116+Mkt!G117 -> 261.53524 | G23: =F23/F$4-1 -> 0.0033743765
A24: 台積電 2025 資本支出 高（42） | B24: =((cap_sk_27*1000/fx*sh_sk+cap_mu_27*sh_mu_27+cap_ss_27*1000/fx*sh_ss)+(((Mkt!$C$57-Mkt!$C$54+ind_cxmt)*sh_oth))*(1+g_oth_dram)^2+((Mkt!$C$61*sh_oth))*(1+g_oth_nand)^2)+(cap_ts_27*(1-0)*sh_fd+MAX(Mkt!$C$43-cap_ts_25_hi*(1-0)*sh_fd,0)*(1+g_oth_fd)^2)+Mkt!E50*(((cap_sk_27*1000/fx*sh_sk+cap_mu_27*sh_mu_27+cap_ss_27*1000/fx*sh_ss)+(((Mkt!$C$57-Mkt!$C$54+ind_cxmt)*sh_oth))*(1+g_oth_dram)^2+((Mkt!$C$61*sh_oth))*(1+g_oth_nand)^2)+(cap_ts_27*(1-0)*sh_fd+MAX(Mkt!$C$43-cap_ts_25_hi*(1-0)*sh_fd,0)*(1+g_oth_fd)^2))+Mkt!E116+Mkt!E117 -> 217.30389 | C24: =B24/B$4-1 -> -0.0042233574 | D24: =((cap_sk_28*1000/fx*sh_sk+cap_mu_28*sh_mu_27+cap_ss_28*1000/fx*sh_ss)+(((Mkt!$C$57-Mkt!$C$54+ind_cxmt)*sh_oth))*(1+g_oth_dram)^3+((Mkt!$C$61*sh_oth))*(1+g_oth_nand)^3)+(cap_ts_28*(1-0)*sh_fd+MAX(Mkt!$C$43-cap_ts_25_hi*(1-0)*sh_fd,0)*(1+g_oth_fd)^3)+Mkt!F50*(((cap_sk_28*1000/fx*sh_sk+cap_mu_28*sh_mu_27+cap_ss_28*1000/fx*sh_ss)+(((Mkt!$C$57-Mkt!$C$54+ind_cxmt)*sh_oth))*(1+g_oth_dram)^3+((Mkt!$C$61*sh_oth))*(1+g_oth_nand)^3)+(cap_ts_28*(1-0)*sh_fd+MAX(Mkt!$C$43-cap_ts_25_hi*(1-0)*sh_fd,0)*(1+g_oth_fd)^3))+Mkt!F116+Mkt!F117 -> 245.03325 | E24: =D24/D$4-1 -> -0.004045773 | F24: =((cap_sk_29*1000/fx*sh_sk+cap_mu_29*sh_mu_27+cap_ss_29*1000/fx*sh_ss)+(((Mkt!$C$57-Mkt!$C$54+ind_cxmt)*sh_oth))*(1+g_oth_dram)^4+((Mkt!$C$61*sh_oth))*(1+g_oth_nand)^4)+(cap_ts_29*(1-0)*sh_fd+MAX(Mkt!$C$43-cap_ts_25_hi*(1-0)*sh_fd,0)*(1+g_oth_fd)^4)+Mkt!G50*(((cap_sk_29*1000/fx*sh_sk+cap_mu_29*sh_mu_27+cap_ss_29*1000/fx*sh_ss)+(((Mkt!$C$57-Mkt!$C$54+ind_cxmt)*sh_oth))*(1+g_oth_dram)^4+((Mkt!$C$61*sh_oth))*(1+g_oth_nand)^4)+(cap_ts_29*(1-0)*sh_fd+MAX(Mkt!$C$43-cap_ts_25_hi*(1-0)*sh_fd,0)*(1+g_oth_fd)^4))+Mkt!G116+Mkt!G117 -> 259.58068 | G24: =F24/F$4-1 -> -0.0041242379
A25: 其他 DRAM 廠成長 低 | B25: =((cap_sk_27*1000/fx*sh_sk+cap_mu_27*sh_mu_27+cap_ss_27*1000/fx*sh_ss)+(((Mkt!$C$57-Mkt!$C$54+ind_cxmt)*sh_oth))*(1+g_oth_dram_lo)^2+((Mkt!$C$61*sh_oth))*(1+g_oth_nand)^2)+(cap_ts_27*(1-0)*sh_fd+MAX(Mkt!$C$43-cap_ts_25*(1-0)*sh_fd,0)*(1+g_oth_fd)^2)+Mkt!E50*(((cap_sk_27*1000/fx*sh_sk+cap_mu_27*sh_mu_27+cap_ss_27*1000/fx*sh_ss)+(((Mkt!$C$57-Mkt!$C$54+ind_cxmt)*sh_oth))*(1+g_oth_dram_lo)^2+((Mkt!$C$61*sh_oth))*(1+g_oth_nand)^2)+(cap_ts_27*(1-0)*sh_fd+MAX(Mkt!$C$43-cap_ts_25*(1-0)*sh_fd,0)*(1+g_oth_fd)^2))+Mkt!E116+Mkt!E117 -> 217.26484 | C25: =B25/B$4-1 -> -0.0044023058 | D25: =((cap_sk_28*1000/fx*sh_sk+cap_mu_28*sh_mu_27+cap_ss_28*1000/fx*sh_ss)+(((Mkt!$C$57-Mkt!$C$54+ind_cxmt)*sh_oth))*(1+g_oth_dram_lo)^3+((Mkt!$C$61*sh_oth))*(1+g_oth_nand)^3)+(cap_ts_28*(1-0)*sh_fd+MAX(Mkt!$C$43-cap_ts_25*(1-0)*sh_fd,0)*(1+g_oth_fd)^3)+Mkt!F50*(((cap_sk_28*1000/fx*sh_sk+cap_mu_28*sh_mu_27+cap_ss_28*1000/fx*sh_ss)+(((Mkt!$C$57-Mkt!$C$54+ind_cxmt)*sh_oth))*(1+g_oth_dram_lo)^3+((Mkt!$C$61*sh_oth))*(1+g_oth_nand)^3)+(cap_ts_28*(1-0)*sh_fd+MAX(Mkt!$C$43-cap_ts_25*(1-0)*sh_fd,0)*(1+g_oth_fd)^3))+Mkt!F116+Mkt!F117 -> 244.38516 | E25: =D25/D$4-1 -> -0.0066799689 | F25: =((cap_sk_29*1000/fx*sh_sk+cap_mu_29*sh_mu_27+cap_ss_29*1000/fx*sh_ss)+(((Mkt!$C$57-Mkt!$C$54+ind_cxmt)*sh_oth))*(1+g_oth_dram_lo)^4+((Mkt!$C$61*sh_oth))*(1+g_oth_nand)^4)+(cap_ts_29*(1-0)*sh_fd+MAX(Mkt!$C$43-cap_ts_25*(1-0)*sh_fd,0)*(1+g_oth_fd)^4)+Mkt!G50*(((cap_sk_29*1000/fx*sh_sk+cap_mu_29*sh_mu_27+cap_ss_29*1000/fx*sh_ss)+(((Mkt!$C$57-Mkt!$C$54+ind_cxmt)*sh_oth))*(1+g_oth_dram_lo)^4+((Mkt!$C$61*sh_oth))*(1+g_oth_nand)^4)+(cap_ts_29*(1-0)*sh_fd+MAX(Mkt!$C$43-cap_ts_25*(1-0)*sh_fd,0)*(1+g_oth_fd)^4))+Mkt!G116+Mkt!G117 -> 258.15557 | G25: =F25/F$4-1 -> -0.0095916346
A26: 其他 DRAM 廠成長 高 | B26: =((cap_sk_27*1000/fx*sh_sk+cap_mu_27*sh_mu_27+cap_ss_27*1000/fx*sh_ss)+(((Mkt!$C$57-Mkt!$C$54+ind_cxmt)*sh_oth))*(1+g_oth_dram_hi)^2+((Mkt!$C$61*sh_oth))*(1+g_oth_nand)^2)+(cap_ts_27*(1-0)*sh_fd+MAX(Mkt!$C$43-cap_ts_25*(1-0)*sh_fd,0)*(1+g_oth_fd)^2)+Mkt!E50*(((cap_sk_27*1000/fx*sh_sk+cap_mu_27*sh_mu_27+cap_ss_27*1000/fx*sh_ss)+(((Mkt!$C$57-Mkt!$C$54+ind_cxmt)*sh_oth))*(1+g_oth_dram_hi)^2+((Mkt!$C$61*sh_oth))*(1+g_oth_nand)^2)+(cap_ts_27*(1-0)*sh_fd+MAX(Mkt!$C$43-cap_ts_25*(1-0)*sh_fd,0)*(1+g_oth_fd)^2))+Mkt!E116+Mkt!E117 -> 224.37525 | C26: =B26/B$4-1 -> 0.02818055 | D26: =((cap_sk_28*1000/fx*sh_sk+cap_mu_28*sh_mu_27+cap_ss_28*1000/fx*sh_ss)+(((Mkt!$C$57-Mkt!$C$54+ind_cxmt)*sh_oth))*(1+g_oth_dram_hi)^3+((Mkt!$C$61*sh_oth))*(1+g_oth_nand)^3)+(cap_ts_28*(1-0)*sh_fd+MAX(Mkt!$C$43-cap_ts_25*(1-0)*sh_fd,0)*(1+g_oth_fd)^3)+Mkt!F50*(((cap_sk_28*1000/fx*sh_sk+cap_mu_28*sh_mu_27+cap_ss_28*1000/fx*sh_ss)+(((Mkt!$C$57-Mkt!$C$54+ind_cxmt)*sh_oth))*(1+g_oth_dram_hi)^3+((Mkt!$C$61*sh_oth))*(1+g_oth_nand)^3)+(cap_ts_28*(1-0)*sh_fd+MAX(Mkt!$C$43-cap_ts_25*(1-0)*sh_fd,0)*(1+g_oth_fd)^3))+Mkt!F116+Mkt!F117 -> 258.94834 | E26: =D26/D$4-1 -> 0.052513043 | F26: =((cap_sk_29*1000/fx*sh_sk+cap_mu_29*sh_mu_27+cap_ss_29*1000/fx*sh_ss)+(((Mkt!$C$57-Mkt!$C$54+ind_cxmt)*sh_oth))*(1+g_oth_dram_hi)^4+((Mkt!$C$61*sh_oth))*(1+g_oth_nand)^4)+(cap_ts_29*(1-0)*sh_fd+MAX(Mkt!$C$43-cap_ts_25*(1-0)*sh_fd,0)*(1+g_oth_fd)^4)+Mkt!G50*(((cap_sk_29*1000/fx*sh_sk+cap_mu_29*sh_mu_27+cap_ss_29*1000/fx*sh_ss)+(((Mkt!$C$57-Mkt!$C$54+ind_cxmt)*sh_oth))*(1+g_oth_dram_hi)^4+((Mkt!$C$61*sh_oth))*(1+g_oth_nand)^4)+(cap_ts_29*(1-0)*sh_fd+MAX(Mkt!$C$43-cap_ts_25*(1-0)*sh_fd,0)*(1+g_oth_fd)^4))+Mkt!G116+Mkt!G117 -> 284.96182 | G26: =F26/F$4-1 -> 0.093249974
A27: 其他 NAND 廠成長 低 | B27: =((cap_sk_27*1000/fx*sh_sk+cap_mu_27*sh_mu_27+cap_ss_27*1000/fx*sh_ss)+(((Mkt!$C$57-Mkt!$C$54+ind_cxmt)*sh_oth))*(1+g_oth_dram)^2+((Mkt!$C$61*sh_oth))*(1+g_oth_nand_lo)^2)+(cap_ts_27*(1-0)*sh_fd+MAX(Mkt!$C$43-cap_ts_25*(1-0)*sh_fd,0)*(1+g_oth_fd)^2)+Mkt!E50*(((cap_sk_27*1000/fx*sh_sk+cap_mu_27*sh_mu_27+cap_ss_27*1000/fx*sh_ss)+(((Mkt!$C$57-Mkt!$C$54+ind_cxmt)*sh_oth))*(1+g_oth_dram)^2+((Mkt!$C$61*sh_oth))*(1+g_oth_nand_lo)^2)+(cap_ts_27*(1-0)*sh_fd+MAX(Mkt!$C$43-cap_ts_25*(1-0)*sh_fd,0)*(1+g_oth_fd)^2))+Mkt!E116+Mkt!E117 -> 216.50292 | C27: =B27/B$4-1 -> -0.0078937362 | D27: =((cap_sk_28*1000/fx*sh_sk+cap_mu_28*sh_mu_27+cap_ss_28*1000/fx*sh_ss)+(((Mkt!$C$57-Mkt!$C$54+ind_cxmt)*sh_oth))*(1+g_oth_dram)^3+((Mkt!$C$61*sh_oth))*(1+g_oth_nand_lo)^3)+(cap_ts_28*(1-0)*sh_fd+MAX(Mkt!$C$43-cap_ts_25*(1-0)*sh_fd,0)*(1+g_oth_fd)^3)+Mkt!F50*(((cap_sk_28*1000/fx*sh_sk+cap_mu_28*sh_mu_27+cap_ss_28*1000/fx*sh_ss)+(((Mkt!$C$57-Mkt!$C$54+ind_cxmt)*sh_oth))*(1+g_oth_dram)^3+((Mkt!$C$61*sh_oth))*(1+g_oth_nand_lo)^3)+(cap_ts_28*(1-0)*sh_fd+MAX(Mkt!$C$43-cap_ts_25*(1-0)*sh_fd,0)*(1+g_oth_fd)^3))+Mkt!F116+Mkt!F117 -> 243.20575 | E27: =D27/D$4-1 -> -0.011473769 | F27: =((cap_sk_29*1000/fx*sh_sk+cap_mu_29*sh_mu_27+cap_ss_29*1000/fx*sh_ss)+(((Mkt!$C$57-Mkt!$C$54+ind_cxmt)*sh_oth))*(1+g_oth_dram)^4+((Mkt!$C$61*sh_oth))*(1+g_oth_nand_lo)^4)+(cap_ts_29*(1-0)*sh_fd+MAX(Mkt!$C$43-cap_ts_25*(1-0)*sh_fd,0)*(1+g_oth_fd)^4)+Mkt!G50*(((cap_sk_29*1000/fx*sh_sk+cap_mu_29*sh_mu_27+cap_ss_29*1000/fx*sh_ss)+(((Mkt!$C$57-Mkt!$C$54+ind_cxmt)*sh_oth))*(1+g_oth_dram)^4+((Mkt!$C$61*sh_oth))*(1+g_oth_nand_lo)^4)+(cap_ts_29*(1-0)*sh_fd+MAX(Mkt!$C$43-cap_ts_25*(1-0)*sh_fd,0)*(1+g_oth_fd)^4))+Mkt!G116+Mkt!G117 -> 256.5345 | G27: =F27/F$4-1 -> -0.015810834
A28: 其他 NAND 廠成長 高 | B28: =((cap_sk_27*1000/fx*sh_sk+cap_mu_27*sh_mu_27+cap_ss_27*1000/fx*sh_ss)+(((Mkt!$C$57-Mkt!$C$54+ind_cxmt)*sh_oth))*(1+g_oth_dram)^2+((Mkt!$C$61*sh_oth))*(1+g_oth_nand_hi)^2)+(cap_ts_27*(1-0)*sh_fd+MAX(Mkt!$C$43-cap_ts_25*(1-0)*sh_fd,0)*(1+g_oth_fd)^2)+Mkt!E50*(((cap_sk_27*1000/fx*sh_sk+cap_mu_27*sh_mu_27+cap_ss_27*1000/fx*sh_ss)+(((Mkt!$C$57-Mkt!$C$54+ind_cxmt)*sh_oth))*(1+g_oth_dram)^2+((Mkt!$C$61*sh_oth))*(1+g_oth_nand_hi)^2)+(cap_ts_27*(1-0)*sh_fd+MAX(Mkt!$C$43-cap_ts_25*(1-0)*sh_fd,0)*(1+g_oth_fd)^2))+Mkt!E116+Mkt!E117 -> 223.35124 | C28: =B28/B$4-1 -> 0.02348809 | D28: =((cap_sk_28*1000/fx*sh_sk+cap_mu_28*sh_mu_27+cap_ss_28*1000/fx*sh_ss)+(((Mkt!$C$57-Mkt!$C$54+ind_cxmt)*sh_oth))*(1+g_oth_dram)^3+((Mkt!$C$61*sh_oth))*(1+g_oth_nand_hi)^3)+(cap_ts_28*(1-0)*sh_fd+MAX(Mkt!$C$43-cap_ts_25*(1-0)*sh_fd,0)*(1+g_oth_fd)^3)+Mkt!F50*(((cap_sk_28*1000/fx*sh_sk+cap_mu_28*sh_mu_27+cap_ss_28*1000/fx*sh_ss)+(((Mkt!$C$57-Mkt!$C$54+ind_cxmt)*sh_oth))*(1+g_oth_dram)^3+((Mkt!$C$61*sh_oth))*(1+g_oth_nand_hi)^3)+(cap_ts_28*(1-0)*sh_fd+MAX(Mkt!$C$43-cap_ts_25*(1-0)*sh_fd,0)*(1+g_oth_fd)^3))+Mkt!F116+Mkt!F117 -> 256.79702 | E28: =D28/D$4-1 -> 0.043768878 | F28: =((cap_sk_29*1000/fx*sh_sk+cap_mu_29*sh_mu_27+cap_ss_29*1000/fx*sh_ss)+(((Mkt!$C$57-Mkt!$C$54+ind_cxmt)*sh_oth))*(1+g_oth_dram)^4+((Mkt!$C$61*sh_oth))*(1+g_oth_nand_hi)^4)+(cap_ts_29*(1-0)*sh_fd+MAX(Mkt!$C$43-cap_ts_25*(1-0)*sh_fd,0)*(1+g_oth_fd)^4)+Mkt!G50*(((cap_sk_29*1000/fx*sh_sk+cap_mu_29*sh_mu_27+cap_ss_29*1000/fx*sh_ss)+(((Mkt!$C$57-Mkt!$C$54+ind_cxmt)*sh_oth))*(1+g_oth_dram)^4+((Mkt!$C$61*sh_oth))*(1+g_oth_nand_hi)^4)+(cap_ts_29*(1-0)*sh_fd+MAX(Mkt!$C$43-cap_ts_25*(1-0)*sh_fd,0)*(1+g_oth_fd)^4))+Mkt!G116+Mkt!G117 -> 280.91451 | G28: =F28/F$4-1 -> 0.077722534
A29: 其他代工邏輯成長 低 | B29: =((cap_sk_27*1000/fx*sh_sk+cap_mu_27*sh_mu_27+cap_ss_27*1000/fx*sh_ss)+(((Mkt!$C$57-Mkt!$C$54+ind_cxmt)*sh_oth))*(1+g_oth_dram)^2+((Mkt!$C$61*sh_oth))*(1+g_oth_nand)^2)+(cap_ts_27*(1-0)*sh_fd+MAX(Mkt!$C$43-cap_ts_25*(1-0)*sh_fd,0)*(1+g_oth_fd_lo)^2)+Mkt!E50*(((cap_sk_27*1000/fx*sh_sk+cap_mu_27*sh_mu_27+cap_ss_27*1000/fx*sh_ss)+(((Mkt!$C$57-Mkt!$C$54+ind_cxmt)*sh_oth))*(1+g_oth_dram)^2+((Mkt!$C$61*sh_oth))*(1+g_oth_nand)^2)+(cap_ts_27*(1-0)*sh_fd+MAX(Mkt!$C$43-cap_ts_25*(1-0)*sh_fd,0)*(1+g_oth_fd_lo)^2))+Mkt!E116+Mkt!E117 -> 210.86224 | C29: =B29/B$4-1 -> -0.033741664 | D29: =((cap_sk_28*1000/fx*sh_sk+cap_mu_28*sh_mu_27+cap_ss_28*1000/fx*sh_ss)+(((Mkt!$C$57-Mkt!$C$54+ind_cxmt)*sh_oth))*(1+g_oth_dram)^3+((Mkt!$C$61*sh_oth))*(1+g_oth_nand)^3)+(cap_ts_28*(1-0)*sh_fd+MAX(Mkt!$C$43-cap_ts_25*(1-0)*sh_fd,0)*(1+g_oth_fd_lo)^3)+Mkt!F50*(((cap_sk_28*1000/fx*sh_sk+cap_mu_28*sh_mu_27+cap_ss_28*1000/fx*sh_ss)+(((Mkt!$C$57-Mkt!$C$54+ind_cxmt)*sh_oth))*(1+g_oth_dram)^3+((Mkt!$C$61*sh_oth))*(1+g_oth_nand)^3)+(cap_ts_28*(1-0)*sh_fd+MAX(Mkt!$C$43-cap_ts_25*(1-0)*sh_fd,0)*(1+g_oth_fd_lo)^3))+Mkt!F116+Mkt!F117 -> 234.53623 | E29: =D29/D$4-1 -> -0.04671164 | F29: =((cap_sk_29*1000/fx*sh_sk+cap_mu_29*sh_mu_27+cap_ss_29*1000/fx*sh_ss)+(((Mkt!$C$57-Mkt!$C$54+ind_cxmt)*sh_oth))*(1+g_oth_dram)^4+((Mkt!$C$61*sh_oth))*(1+g_oth_nand)^4)+(cap_ts_29*(1-0)*sh_fd+MAX(Mkt!$C$43-cap_ts_25*(1-0)*sh_fd,0)*(1+g_oth_fd_lo)^4)+Mkt!G50*(((cap_sk_29*1000/fx*sh_sk+cap_mu_29*sh_mu_27+cap_ss_29*1000/fx*sh_ss)+(((Mkt!$C$57-Mkt!$C$54+ind_cxmt)*sh_oth))*(1+g_oth_dram)^4+((Mkt!$C$61*sh_oth))*(1+g_oth_nand)^4)+(cap_ts_29*(1-0)*sh_fd+MAX(Mkt!$C$43-cap_ts_25*(1-0)*sh_fd,0)*(1+g_oth_fd_lo)^4))+Mkt!G116+Mkt!G117 -> 244.70385 | G29: =F29/F$4-1 -> -0.061198884
A30: 其他代工邏輯成長 高 | B30: =((cap_sk_27*1000/fx*sh_sk+cap_mu_27*sh_mu_27+cap_ss_27*1000/fx*sh_ss)+(((Mkt!$C$57-Mkt!$C$54+ind_cxmt)*sh_oth))*(1+g_oth_dram)^2+((Mkt!$C$61*sh_oth))*(1+g_oth_nand)^2)+(cap_ts_27*(1-0)*sh_fd+MAX(Mkt!$C$43-cap_ts_25*(1-0)*sh_fd,0)*(1+g_oth_fd_hi)^2)+Mkt!E50*(((cap_sk_27*1000/fx*sh_sk+cap_mu_27*sh_mu_27+cap_ss_27*1000/fx*sh_ss)+(((Mkt!$C$57-Mkt!$C$54+ind_cxmt)*sh_oth))*(1+g_oth_dram)^2+((Mkt!$C$61*sh_oth))*(1+g_oth_nand)^2)+(cap_ts_27*(1-0)*sh_fd+MAX(Mkt!$C$43-cap_ts_25*(1-0)*sh_fd,0)*(1+g_oth_fd_hi)^2))+Mkt!E116+Mkt!E117 -> 230.33249 | C30: =B30/B$4-1 -> 0.055479082 | D30: =((cap_sk_28*1000/fx*sh_sk+cap_mu_28*sh_mu_27+cap_ss_28*1000/fx*sh_ss)+(((Mkt!$C$57-Mkt!$C$54+ind_cxmt)*sh_oth))*(1+g_oth_dram)^3+((Mkt!$C$61*sh_oth))*(1+g_oth_nand)^3)+(cap_ts_28*(1-0)*sh_fd+MAX(Mkt!$C$43-cap_ts_25*(1-0)*sh_fd,0)*(1+g_oth_fd_hi)^3)+Mkt!F50*(((cap_sk_28*1000/fx*sh_sk+cap_mu_28*sh_mu_27+cap_ss_28*1000/fx*sh_ss)+(((Mkt!$C$57-Mkt!$C$54+ind_cxmt)*sh_oth))*(1+g_oth_dram)^3+((Mkt!$C$61*sh_oth))*(1+g_oth_nand)^3)+(cap_ts_28*(1-0)*sh_fd+MAX(Mkt!$C$43-cap_ts_25*(1-0)*sh_fd,0)*(1+g_oth_fd_hi)^3))+Mkt!F116+Mkt!F117 -> 266.75063 | E30: =D30/D$4-1 -> 0.08422599 | F30: =((cap_sk_29*1000/fx*sh_sk+cap_mu_29*sh_mu_27+cap_ss_29*1000/fx*sh_ss)+(((Mkt!$C$57-Mkt!$C$54+ind_cxmt)*sh_oth))*(1+g_oth_dram)^4+((Mkt!$C$61*sh_oth))*(1+g_oth_nand)^4)+(cap_ts_29*(1-0)*sh_fd+MAX(Mkt!$C$43-cap_ts_25*(1-0)*sh_fd,0)*(1+g_oth_fd_hi)^4)+Mkt!G50*(((cap_sk_29*1000/fx*sh_sk+cap_mu_29*sh_mu_27+cap_ss_29*1000/fx*sh_ss)+(((Mkt!$C$57-Mkt!$C$54+ind_cxmt)*sh_oth))*(1+g_oth_dram)^4+((Mkt!$C$61*sh_oth))*(1+g_oth_nand)^4)+(cap_ts_29*(1-0)*sh_fd+MAX(Mkt!$C$43-cap_ts_25*(1-0)*sh_fd,0)*(1+g_oth_fd_hi)^4))+Mkt!G116+Mkt!G117 -> 292.21125 | G30: =F30/F$4-1 -> 0.12106224
A31: 核對：基準 − Mkt 情境 A 總額（應為 0） | B31: =B4-Mkt!E129 -> 0 | D31: =D4-Mkt!F129 -> 0 | F31: =F4-Mkt!G129 -> 0
A33: 情境係數 | B33: 2028 設備總額 | C33: 相對 2027 | D33: 2029 設備總額 | E33: 相對 2028 | H33: 說明
A34: B 係數 低 | B34: =Mkt!E148*ck_B_28_lo -> 207.31426 | C34: =B34/Mkt!E148-1 -> -0.05 | D34: =B34*ck_B_29_lo -> 186.58283 | E34: =D34/B34-1 -> -0.1
A35: B 係數 基準 | B35: =Mkt!E148*ck_B_28 -> 218.22554 | C35: =B35/Mkt!E148-1 -> 0 | D35: =B35*ck_B_29 -> 207.31426 | E35: =D35/B35-1 -> -0.05
A36: B 係數 高 | B36: =Mkt!E148*ck_B_28_hi -> 229.13681 | C36: =B36/Mkt!E148-1 -> 0.05 | D36: =B36*ck_B_29_hi -> 240.59365 | E36: =D36/B36-1 -> 0.05
A37: C 係數 低 | B37: =Mkt!E167*ck_C_28_lo -> 163.66915 | C37: =B37/Mkt!E167-1 -> -0.25 | D37: =B37*ck_C_29_lo -> 147.30224 | E37: =D37/B37-1 -> -0.1
A38: C 係數 基準 | B38: =Mkt!E167*ck_C_28 -> 174.58043 | C38: =B38/Mkt!E167-1 -> -0.2 | D38: =B38*ck_C_29 -> 174.58043 | E38: =D38/B38-1 -> 0
A39: C 係數 高 | B39: =Mkt!E167*ck_C_28_hi -> 185.49171 | C39: =B39/Mkt!E167-1 -> -0.15 | D39: =B39*ck_C_29_hi -> 204.04088 | E39: =D39/B39-1 -> 0.1
A40: 說明：係數為 Assumed，區間無實證；B 的見頂年度對 2029 係數敏感（≥1.00 則 2029 不下滑，見頂年度移到 2029）。
A42: 校準值 vs 業界值 64%（對照）：三情境總額與見頂年度
A43: 情境／占比 | B43: 2025 | C43: 2026 | D43: 2027 | E43: 2028 | F43: 2029 | G43: 見頂年度 | H43: 說明
A44: 情境 A（校準值（基準）） | B44: =((cap_sk_25*1000/fx*sh_sk+cap_mu_25*sh_mu_25+cap_ssds_25*ss_mem*1000/fx*sh_ss)+(((Mkt!$C$57-Mkt!$C$54+ind_cxmt)*sh_oth))*(1+g_oth_dram)^0+((Mkt!$C$61*sh_oth))*(1+g_oth_nand)^0)+(cap_ts_25*(1-0)*sh_fd+MAX(Mkt!$C$43-cap_ts_25*(1-0)*sh_fd,0)*(1+g_oth_fd)^0)+Mkt!C50*(((cap_sk_25*1000/fx*sh_sk+cap_mu_25*sh_mu_25+cap_ssds_25*ss_mem*1000/fx*sh_ss)+(((Mkt!$C$57-Mkt!$C$54+ind_cxmt)*sh_oth))*(1+g_oth_dram)^0+((Mkt!$C$61*sh_oth))*(1+g_oth_nand)^0)+(cap_ts_25*(1-0)*sh_fd+MAX(Mkt!$C$43-cap_ts_25*(1-0)*sh_fd,0)*(1+g_oth_fd)^0))+Mkt!C116+Mkt!C117 -> 134.68936 | C44: =((cap_sk_26*1000/fx*sh_sk+cap_mu_26*sh_mu_26+cap_ss_26*1000/fx*sh_ss)+(((Mkt!$C$57-Mkt!$C$54+ind_cxmt)*sh_oth))*(1+g_oth_dram)^1+((Mkt!$C$61*sh_oth))*(1+g_oth_nand)^1)+(cap_ts_26*(1-0)*sh_fd+MAX(Mkt!$C$43-cap_ts_25*(1-0)*sh_fd,0)*(1+g_oth_fd)^1)+Mkt!D50*(((cap_sk_26*1000/fx*sh_sk+cap_mu_26*sh_mu_26+cap_ss_26*1000/fx*sh_ss)+(((Mkt!$C$57-Mkt!$C$54+ind_cxmt)*sh_oth))*(1+g_oth_dram)^1+((Mkt!$C$61*sh_oth))*(1+g_oth_nand)^1)+(cap_ts_26*(1-0)*sh_fd+MAX(Mkt!$C$43-cap_ts_25*(1-0)*sh_fd,0)*(1+g_oth_fd)^1))+Mkt!D116+Mkt!D117 -> 178.15705 | D44: =((cap_sk_27*1000/fx*sh_sk+cap_mu_27*sh_mu_27+cap_ss_27*1000/fx*sh_ss)+(((Mkt!$C$57-Mkt!$C$54+ind_cxmt)*sh_oth))*(1+g_oth_dram)^2+((Mkt!$C$61*sh_oth))*(1+g_oth_nand)^2)+(cap_ts_27*(1-0)*sh_fd+MAX(Mkt!$C$43-cap_ts_25*(1-0)*sh_fd,0)*(1+g_oth_fd)^2)+Mkt!E50*(((cap_sk_27*1000/fx*sh_sk+cap_mu_27*sh_mu_27+cap_ss_27*1000/fx*sh_ss)+(((Mkt!$C$57-Mkt!$C$54+ind_cxmt)*sh_oth))*(1+g_oth_dram)^2+((Mkt!$C$61*sh_oth))*(1+g_oth_nand)^2)+(cap_ts_27*(1-0)*sh_fd+MAX(Mkt!$C$43-cap_ts_25*(1-0)*sh_fd,0)*(1+g_oth_fd)^2))+Mkt!E116+Mkt!E117 -> 218.22554 | E44: =((cap_sk_28*1000/fx*sh_sk+cap_mu_28*sh_mu_27+cap_ss_28*1000/fx*sh_ss)+(((Mkt!$C$57-Mkt!$C$54+ind_cxmt)*sh_oth))*(1+g_oth_dram)^3+((Mkt!$C$61*sh_oth))*(1+g_oth_nand)^3)+(cap_ts_28*(1-0)*sh_fd+MAX(Mkt!$C$43-cap_ts_25*(1-0)*sh_fd,0)*(1+g_oth_fd)^3)+Mkt!F50*(((cap_sk_28*1000/fx*sh_sk+cap_mu_28*sh_mu_27+cap_ss_28*1000/fx*sh_ss)+(((Mkt!$C$57-Mkt!$C$54+ind_cxmt)*sh_oth))*(1+g_oth_dram)^3+((Mkt!$C$61*sh_oth))*(1+g_oth_nand)^3)+(cap_ts_28*(1-0)*sh_fd+MAX(Mkt!$C$43-cap_ts_25*(1-0)*sh_fd,0)*(1+g_oth_fd)^3))+Mkt!F116+Mkt!F117 -> 246.02863 | F44: =((cap_sk_29*1000/fx*sh_sk+cap_mu_29*sh_mu_27+cap_ss_29*1000/fx*sh_ss)+(((Mkt!$C$57-Mkt!$C$54+ind_cxmt)*sh_oth))*(1+g_oth_dram)^4+((Mkt!$C$61*sh_oth))*(1+g_oth_nand)^4)+(cap_ts_29*(1-0)*sh_fd+MAX(Mkt!$C$43-cap_ts_25*(1-0)*sh_fd,0)*(1+g_oth_fd)^4)+Mkt!G50*(((cap_sk_29*1000/fx*sh_sk+cap_mu_29*sh_mu_27+cap_ss_29*1000/fx*sh_ss)+(((Mkt!$C$57-Mkt!$C$54+ind_cxmt)*sh_oth))*(1+g_oth_dram)^4+((Mkt!$C$61*sh_oth))*(1+g_oth_nand)^4)+(cap_ts_29*(1-0)*sh_fd+MAX(Mkt!$C$43-cap_ts_25*(1-0)*sh_fd,0)*(1+g_oth_fd)^4))+Mkt!G116+Mkt!G117 -> 260.65569 | G44: =IF(ROUND(F44,9)=ROUND(MAX(B44:F44),9),2029,IF(ROUND(E44,9)=ROUND(MAX(B44:F44),9),2028,IF(ROUND(D44,9)=ROUND(MAX(B44:F44),9),2027,IF(ROUND(C44,9)=ROUND(MAX(B44:F44),9),2026,2025)))) -> 2029
A45: 情境 B（校準值（基準）） | B45: =((cap_sk_25*1000/fx*sh_sk+cap_mu_25*sh_mu_25+cap_ssds_25*ss_mem*1000/fx*sh_ss)+(((Mkt!$C$57-Mkt!$C$54+ind_cxmt)*sh_oth))*(1+g_oth_dram)^0+((Mkt!$C$61*sh_oth))*(1+g_oth_nand)^0)+(cap_ts_25*(1-0)*sh_fd+MAX(Mkt!$C$43-cap_ts_25*(1-0)*sh_fd,0)*(1+g_oth_fd)^0)+Mkt!C50*(((cap_sk_25*1000/fx*sh_sk+cap_mu_25*sh_mu_25+cap_ssds_25*ss_mem*1000/fx*sh_ss)+(((Mkt!$C$57-Mkt!$C$54+ind_cxmt)*sh_oth))*(1+g_oth_dram)^0+((Mkt!$C$61*sh_oth))*(1+g_oth_nand)^0)+(cap_ts_25*(1-0)*sh_fd+MAX(Mkt!$C$43-cap_ts_25*(1-0)*sh_fd,0)*(1+g_oth_fd)^0))+Mkt!C116+Mkt!C117 -> 134.68936 | C45: =((cap_sk_26*1000/fx*sh_sk+cap_mu_26*sh_mu_26+cap_ss_26*1000/fx*sh_ss)+(((Mkt!$C$57-Mkt!$C$54+ind_cxmt)*sh_oth))*(1+g_oth_dram)^1+((Mkt!$C$61*sh_oth))*(1+g_oth_nand)^1)+(cap_ts_26*(1-0)*sh_fd+MAX(Mkt!$C$43-cap_ts_25*(1-0)*sh_fd,0)*(1+g_oth_fd)^1)+Mkt!D50*(((cap_sk_26*1000/fx*sh_sk+cap_mu_26*sh_mu_26+cap_ss_26*1000/fx*sh_ss)+(((Mkt!$C$57-Mkt!$C$54+ind_cxmt)*sh_oth))*(1+g_oth_dram)^1+((Mkt!$C$61*sh_oth))*(1+g_oth_nand)^1)+(cap_ts_26*(1-0)*sh_fd+MAX(Mkt!$C$43-cap_ts_25*(1-0)*sh_fd,0)*(1+g_oth_fd)^1))+Mkt!D116+Mkt!D117 -> 178.15705 | D45: =((cap_sk_27*1000/fx*sh_sk+cap_mu_27*sh_mu_27+cap_ss_27*1000/fx*sh_ss)+(((Mkt!$C$57-Mkt!$C$54+ind_cxmt)*sh_oth))*(1+g_oth_dram)^2+((Mkt!$C$61*sh_oth))*(1+g_oth_nand)^2)+(cap_ts_27*(1-0)*sh_fd+MAX(Mkt!$C$43-cap_ts_25*(1-0)*sh_fd,0)*(1+g_oth_fd)^2)+Mkt!E50*(((cap_sk_27*1000/fx*sh_sk+cap_mu_27*sh_mu_27+cap_ss_27*1000/fx*sh_ss)+(((Mkt!$C$57-Mkt!$C$54+ind_cxmt)*sh_oth))*(1+g_oth_dram)^2+((Mkt!$C$61*sh_oth))*(1+g_oth_nand)^2)+(cap_ts_27*(1-0)*sh_fd+MAX(Mkt!$C$43-cap_ts_25*(1-0)*sh_fd,0)*(1+g_oth_fd)^2))+Mkt!E116+Mkt!E117 -> 218.22554 | E45: =D45*ck_B_28 -> 218.22554 | F45: =E45*ck_B_29 -> 207.31426 | G45: =IF(ROUND(F45,9)=ROUND(MAX(B45:F45),9),2029,IF(ROUND(E45,9)=ROUND(MAX(B45:F45),9),2028,IF(ROUND(D45,9)=ROUND(MAX(B45:F45),9),2027,IF(ROUND(C45,9)=ROUND(MAX(B45:F45),9),2026,2025)))) -> 2028
A46: 情境 C（校準值（基準）） | B46: =((cap_sk_25*1000/fx*sh_sk+cap_mu_25*sh_mu_25+cap_ssds_25*ss_mem*1000/fx*sh_ss)+(((Mkt!$C$57-Mkt!$C$54+ind_cxmt)*sh_oth))*(1+g_oth_dram)^0+((Mkt!$C$61*sh_oth))*(1+g_oth_nand)^0)+(cap_ts_25*(1-0)*sh_fd+MAX(Mkt!$C$43-cap_ts_25*(1-0)*sh_fd,0)*(1+g_oth_fd)^0)+Mkt!C50*(((cap_sk_25*1000/fx*sh_sk+cap_mu_25*sh_mu_25+cap_ssds_25*ss_mem*1000/fx*sh_ss)+(((Mkt!$C$57-Mkt!$C$54+ind_cxmt)*sh_oth))*(1+g_oth_dram)^0+((Mkt!$C$61*sh_oth))*(1+g_oth_nand)^0)+(cap_ts_25*(1-0)*sh_fd+MAX(Mkt!$C$43-cap_ts_25*(1-0)*sh_fd,0)*(1+g_oth_fd)^0))+Mkt!C116+Mkt!C117 -> 134.68936 | C46: =((cap_sk_26*1000/fx*sh_sk+cap_mu_26*sh_mu_26+cap_ss_26*1000/fx*sh_ss)+(((Mkt!$C$57-Mkt!$C$54+ind_cxmt)*sh_oth))*(1+g_oth_dram)^1+((Mkt!$C$61*sh_oth))*(1+g_oth_nand)^1)+(cap_ts_26*(1-0)*sh_fd+MAX(Mkt!$C$43-cap_ts_25*(1-0)*sh_fd,0)*(1+g_oth_fd)^1)+Mkt!D50*(((cap_sk_26*1000/fx*sh_sk+cap_mu_26*sh_mu_26+cap_ss_26*1000/fx*sh_ss)+(((Mkt!$C$57-Mkt!$C$54+ind_cxmt)*sh_oth))*(1+g_oth_dram)^1+((Mkt!$C$61*sh_oth))*(1+g_oth_nand)^1)+(cap_ts_26*(1-0)*sh_fd+MAX(Mkt!$C$43-cap_ts_25*(1-0)*sh_fd,0)*(1+g_oth_fd)^1))+Mkt!D116+Mkt!D117 -> 178.15705 | D46: =((cap_sk_27*1000/fx*sh_sk+cap_mu_27*sh_mu_27+cap_ss_27*1000/fx*sh_ss)+(((Mkt!$C$57-Mkt!$C$54+ind_cxmt)*sh_oth))*(1+g_oth_dram)^2+((Mkt!$C$61*sh_oth))*(1+g_oth_nand)^2)+(cap_ts_27*(1-0)*sh_fd+MAX(Mkt!$C$43-cap_ts_25*(1-0)*sh_fd,0)*(1+g_oth_fd)^2)+Mkt!E50*(((cap_sk_27*1000/fx*sh_sk+cap_mu_27*sh_mu_27+cap_ss_27*1000/fx*sh_ss)+(((Mkt!$C$57-Mkt!$C$54+ind_cxmt)*sh_oth))*(1+g_oth_dram)^2+((Mkt!$C$61*sh_oth))*(1+g_oth_nand)^2)+(cap_ts_27*(1-0)*sh_fd+MAX(Mkt!$C$43-cap_ts_25*(1-0)*sh_fd,0)*(1+g_oth_fd)^2))+Mkt!E116+Mkt!E117 -> 218.22554 | E46: =D46*ck_C_28 -> 174.58043 | F46: =E46*ck_C_29 -> 174.58043 | G46: =IF(ROUND(F46,9)=ROUND(MAX(B46:F46),9),2029,IF(ROUND(E46,9)=ROUND(MAX(B46:F46),9),2028,IF(ROUND(D46,9)=ROUND(MAX(B46:F46),9),2027,IF(ROUND(C46,9)=ROUND(MAX(B46:F46),9),2026,2025)))) -> 2027
A47: 情境 A（業界值 64%） | B47: =((cap_sk_25*1000/fx*sh_oth+cap_mu_25*sh_mu_25+cap_ssds_25*ss_mem*1000/fx*sh_oth)+(((Mkt!$C$57-Mkt!$C$54+ind_cxmt)*sh_oth))*(1+g_oth_dram)^0+((Mkt!$C$61*sh_oth))*(1+g_oth_nand)^0)+(cap_ts_25*(1-0)*sh_fd+MAX(Mkt!$C$43-cap_ts_25*(1-0)*sh_fd,0)*(1+g_oth_fd)^0)+Mkt!C50*(((cap_sk_25*1000/fx*sh_oth+cap_mu_25*sh_mu_25+cap_ssds_25*ss_mem*1000/fx*sh_oth)+(((Mkt!$C$57-Mkt!$C$54+ind_cxmt)*sh_oth))*(1+g_oth_dram)^0+((Mkt!$C$61*sh_oth))*(1+g_oth_nand)^0)+(cap_ts_25*(1-0)*sh_fd+MAX(Mkt!$C$43-cap_ts_25*(1-0)*sh_fd,0)*(1+g_oth_fd)^0))+Mkt!C116+Mkt!C117 -> 144.29116 | C47: =((cap_sk_26*1000/fx*sh_oth+cap_mu_26*sh_mu_26+cap_ss_26*1000/fx*sh_oth)+(((Mkt!$C$57-Mkt!$C$54+ind_cxmt)*sh_oth))*(1+g_oth_dram)^1+((Mkt!$C$61*sh_oth))*(1+g_oth_nand)^1)+(cap_ts_26*(1-0)*sh_fd+MAX(Mkt!$C$43-cap_ts_25*(1-0)*sh_fd,0)*(1+g_oth_fd)^1)+Mkt!D50*(((cap_sk_26*1000/fx*sh_oth+cap_mu_26*sh_mu_26+cap_ss_26*1000/fx*sh_oth)+(((Mkt!$C$57-Mkt!$C$54+ind_cxmt)*sh_oth))*(1+g_oth_dram)^1+((Mkt!$C$61*sh_oth))*(1+g_oth_nand)^1)+(cap_ts_26*(1-0)*sh_fd+MAX(Mkt!$C$43-cap_ts_25*(1-0)*sh_fd,0)*(1+g_oth_fd)^1))+Mkt!D116+Mkt!D117 -> 192.91895 | D47: =((cap_sk_27*1000/fx*sh_oth+cap_mu_27*sh_mu_27+cap_ss_27*1000/fx*sh_oth)+(((Mkt!$C$57-Mkt!$C$54+ind_cxmt)*sh_oth))*(1+g_oth_dram)^2+((Mkt!$C$61*sh_oth))*(1+g_oth_nand)^2)+(cap_ts_27*(1-0)*sh_fd+MAX(Mkt!$C$43-cap_ts_25*(1-0)*sh_fd,0)*(1+g_oth_fd)^2)+Mkt!E50*(((cap_sk_27*1000/fx*sh_oth+cap_mu_27*sh_mu_27+cap_ss_27*1000/fx*sh_oth)+(((Mkt!$C$57-Mkt!$C$54+ind_cxmt)*sh_oth))*(1+g_oth_dram)^2+((Mkt!$C$61*sh_oth))*(1+g_oth_nand)^2)+(cap_ts_27*(1-0)*sh_fd+MAX(Mkt!$C$43-cap_ts_25*(1-0)*sh_fd,0)*(1+g_oth_fd)^2))+Mkt!E116+Mkt!E117 -> 236.06527 | E47: =((cap_sk_28*1000/fx*sh_oth+cap_mu_28*sh_mu_27+cap_ss_28*1000/fx*sh_oth)+(((Mkt!$C$57-Mkt!$C$54+ind_cxmt)*sh_oth))*(1+g_oth_dram)^3+((Mkt!$C$61*sh_oth))*(1+g_oth_nand)^3)+(cap_ts_28*(1-0)*sh_fd+MAX(Mkt!$C$43-cap_ts_25*(1-0)*sh_fd,0)*(1+g_oth_fd)^3)+Mkt!F50*(((cap_sk_28*1000/fx*sh_oth+cap_mu_28*sh_mu_27+cap_ss_28*1000/fx*sh_oth)+(((Mkt!$C$57-Mkt!$C$54+ind_cxmt)*sh_oth))*(1+g_oth_dram)^3+((Mkt!$C$61*sh_oth))*(1+g_oth_nand)^3)+(cap_ts_28*(1-0)*sh_fd+MAX(Mkt!$C$43-cap_ts_25*(1-0)*sh_fd,0)*(1+g_oth_fd)^3))+Mkt!F116+Mkt!F117 -> 266.0418 | F47: =((cap_sk_29*1000/fx*sh_oth+cap_mu_29*sh_mu_27+cap_ss_29*1000/fx*sh_oth)+(((Mkt!$C$57-Mkt!$C$54+ind_cxmt)*sh_oth))*(1+g_oth_dram)^4+((Mkt!$C$61*sh_oth))*(1+g_oth_nand)^4)+(cap_ts_29*(1-0)*sh_fd+MAX(Mkt!$C$43-cap_ts_25*(1-0)*sh_fd,0)*(1+g_oth_fd)^4)+Mkt!G50*(((cap_sk_29*1000/fx*sh_oth+cap_mu_29*sh_mu_27+cap_ss_29*1000/fx*sh_oth)+(((Mkt!$C$57-Mkt!$C$54+ind_cxmt)*sh_oth))*(1+g_oth_dram)^4+((Mkt!$C$61*sh_oth))*(1+g_oth_nand)^4)+(cap_ts_29*(1-0)*sh_fd+MAX(Mkt!$C$43-cap_ts_25*(1-0)*sh_fd,0)*(1+g_oth_fd)^4))+Mkt!G116+Mkt!G117 -> 281.22316 | G47: =IF(ROUND(F47,9)=ROUND(MAX(B47:F47),9),2029,IF(ROUND(E47,9)=ROUND(MAX(B47:F47),9),2028,IF(ROUND(D47,9)=ROUND(MAX(B47:F47),9),2027,IF(ROUND(C47,9)=ROUND(MAX(B47:F47),9),2026,2025)))) -> 2029
A48: 情境 B（業界值 64%） | B48: =((cap_sk_25*1000/fx*sh_oth+cap_mu_25*sh_mu_25+cap_ssds_25*ss_mem*1000/fx*sh_oth)+(((Mkt!$C$57-Mkt!$C$54+ind_cxmt)*sh_oth))*(1+g_oth_dram)^0+((Mkt!$C$61*sh_oth))*(1+g_oth_nand)^0)+(cap_ts_25*(1-0)*sh_fd+MAX(Mkt!$C$43-cap_ts_25*(1-0)*sh_fd,0)*(1+g_oth_fd)^0)+Mkt!C50*(((cap_sk_25*1000/fx*sh_oth+cap_mu_25*sh_mu_25+cap_ssds_25*ss_mem*1000/fx*sh_oth)+(((Mkt!$C$57-Mkt!$C$54+ind_cxmt)*sh_oth))*(1+g_oth_dram)^0+((Mkt!$C$61*sh_oth))*(1+g_oth_nand)^0)+(cap_ts_25*(1-0)*sh_fd+MAX(Mkt!$C$43-cap_ts_25*(1-0)*sh_fd,0)*(1+g_oth_fd)^0))+Mkt!C116+Mkt!C117 -> 144.29116 | C48: =((cap_sk_26*1000/fx*sh_oth+cap_mu_26*sh_mu_26+cap_ss_26*1000/fx*sh_oth)+(((Mkt!$C$57-Mkt!$C$54+ind_cxmt)*sh_oth))*(1+g_oth_dram)^1+((Mkt!$C$61*sh_oth))*(1+g_oth_nand)^1)+(cap_ts_26*(1-0)*sh_fd+MAX(Mkt!$C$43-cap_ts_25*(1-0)*sh_fd,0)*(1+g_oth_fd)^1)+Mkt!D50*(((cap_sk_26*1000/fx*sh_oth+cap_mu_26*sh_mu_26+cap_ss_26*1000/fx*sh_oth)+(((Mkt!$C$57-Mkt!$C$54+ind_cxmt)*sh_oth))*(1+g_oth_dram)^1+((Mkt!$C$61*sh_oth))*(1+g_oth_nand)^1)+(cap_ts_26*(1-0)*sh_fd+MAX(Mkt!$C$43-cap_ts_25*(1-0)*sh_fd,0)*(1+g_oth_fd)^1))+Mkt!D116+Mkt!D117 -> 192.91895 | D48: =((cap_sk_27*1000/fx*sh_oth+cap_mu_27*sh_mu_27+cap_ss_27*1000/fx*sh_oth)+(((Mkt!$C$57-Mkt!$C$54+ind_cxmt)*sh_oth))*(1+g_oth_dram)^2+((Mkt!$C$61*sh_oth))*(1+g_oth_nand)^2)+(cap_ts_27*(1-0)*sh_fd+MAX(Mkt!$C$43-cap_ts_25*(1-0)*sh_fd,0)*(1+g_oth_fd)^2)+Mkt!E50*(((cap_sk_27*1000/fx*sh_oth+cap_mu_27*sh_mu_27+cap_ss_27*1000/fx*sh_oth)+(((Mkt!$C$57-Mkt!$C$54+ind_cxmt)*sh_oth))*(1+g_oth_dram)^2+((Mkt!$C$61*sh_oth))*(1+g_oth_nand)^2)+(cap_ts_27*(1-0)*sh_fd+MAX(Mkt!$C$43-cap_ts_25*(1-0)*sh_fd,0)*(1+g_oth_fd)^2))+Mkt!E116+Mkt!E117 -> 236.06527 | E48: =D48*ck_B_28 -> 236.06527 | F48: =E48*ck_B_29 -> 224.262 | G48: =IF(ROUND(F48,9)=ROUND(MAX(B48:F48),9),2029,IF(ROUND(E48,9)=ROUND(MAX(B48:F48),9),2028,IF(ROUND(D48,9)=ROUND(MAX(B48:F48),9),2027,IF(ROUND(C48,9)=ROUND(MAX(B48:F48),9),2026,2025)))) -> 2028
A49: 情境 C（業界值 64%） | B49: =((cap_sk_25*1000/fx*sh_oth+cap_mu_25*sh_mu_25+cap_ssds_25*ss_mem*1000/fx*sh_oth)+(((Mkt!$C$57-Mkt!$C$54+ind_cxmt)*sh_oth))*(1+g_oth_dram)^0+((Mkt!$C$61*sh_oth))*(1+g_oth_nand)^0)+(cap_ts_25*(1-0)*sh_fd+MAX(Mkt!$C$43-cap_ts_25*(1-0)*sh_fd,0)*(1+g_oth_fd)^0)+Mkt!C50*(((cap_sk_25*1000/fx*sh_oth+cap_mu_25*sh_mu_25+cap_ssds_25*ss_mem*1000/fx*sh_oth)+(((Mkt!$C$57-Mkt!$C$54+ind_cxmt)*sh_oth))*(1+g_oth_dram)^0+((Mkt!$C$61*sh_oth))*(1+g_oth_nand)^0)+(cap_ts_25*(1-0)*sh_fd+MAX(Mkt!$C$43-cap_ts_25*(1-0)*sh_fd,0)*(1+g_oth_fd)^0))+Mkt!C116+Mkt!C117 -> 144.29116 | C49: =((cap_sk_26*1000/fx*sh_oth+cap_mu_26*sh_mu_26+cap_ss_26*1000/fx*sh_oth)+(((Mkt!$C$57-Mkt!$C$54+ind_cxmt)*sh_oth))*(1+g_oth_dram)^1+((Mkt!$C$61*sh_oth))*(1+g_oth_nand)^1)+(cap_ts_26*(1-0)*sh_fd+MAX(Mkt!$C$43-cap_ts_25*(1-0)*sh_fd,0)*(1+g_oth_fd)^1)+Mkt!D50*(((cap_sk_26*1000/fx*sh_oth+cap_mu_26*sh_mu_26+cap_ss_26*1000/fx*sh_oth)+(((Mkt!$C$57-Mkt!$C$54+ind_cxmt)*sh_oth))*(1+g_oth_dram)^1+((Mkt!$C$61*sh_oth))*(1+g_oth_nand)^1)+(cap_ts_26*(1-0)*sh_fd+MAX(Mkt!$C$43-cap_ts_25*(1-0)*sh_fd,0)*(1+g_oth_fd)^1))+Mkt!D116+Mkt!D117 -> 192.91895 | D49: =((cap_sk_27*1000/fx*sh_oth+cap_mu_27*sh_mu_27+cap_ss_27*1000/fx*sh_oth)+(((Mkt!$C$57-Mkt!$C$54+ind_cxmt)*sh_oth))*(1+g_oth_dram)^2+((Mkt!$C$61*sh_oth))*(1+g_oth_nand)^2)+(cap_ts_27*(1-0)*sh_fd+MAX(Mkt!$C$43-cap_ts_25*(1-0)*sh_fd,0)*(1+g_oth_fd)^2)+Mkt!E50*(((cap_sk_27*1000/fx*sh_oth+cap_mu_27*sh_mu_27+cap_ss_27*1000/fx*sh_oth)+(((Mkt!$C$57-Mkt!$C$54+ind_cxmt)*sh_oth))*(1+g_oth_dram)^2+((Mkt!$C$61*sh_oth))*(1+g_oth_nand)^2)+(cap_ts_27*(1-0)*sh_fd+MAX(Mkt!$C$43-cap_ts_25*(1-0)*sh_fd,0)*(1+g_oth_fd)^2))+Mkt!E116+Mkt!E117 -> 236.06527 | E49: =D49*ck_C_28 -> 188.85221 | F49: =E49*ck_C_29 -> 188.85221 | G49: =IF(ROUND(F49,9)=ROUND(MAX(B49:F49),9),2029,IF(ROUND(E49,9)=ROUND(MAX(B49:F49),9),2028,IF(ROUND(D49,9)=ROUND(MAX(B49:F49),9),2027,IF(ROUND(C49,9)=ROUND(MAX(B49:F49),9),2026,2025)))) -> 2027
A50: 業界值 64% − 校準值：情境 A | B50: =B47/B44-1 -> 0.071288495 | C50: =C47/C44-1 -> 0.082858938 | D50: =D47/D44-1 -> 0.081749058 | E50: =E47/E44-1 -> 0.081344901 | F50: =F47/F44-1 -> 0.078906681
A51: 業界值 64% − 校準值：情境 B | B51: =B48/B45-1 -> 0.071288495 | C51: =C48/C45-1 -> 0.082858938 | D51: =D48/D45-1 -> 0.081749058 | E51: =E48/E45-1 -> 0.081749058 | F51: =F48/F45-1 -> 0.081749058
A52: 業界值 64% − 校準值：情境 C | B52: =B49/B46-1 -> 0.071288495 | C52: =C49/C46-1 -> 0.082858938 | D52: =D49/D46-1 -> 0.081749058 | E52: =E49/E46-1 -> 0.081749058 | F52: =F49/F46-1 -> 0.081749058
A55: 台積電設備占比／封裝光罩扣除（v0.1.2）：三情境總額與見頂年度（其他參數不動）
A56: 情境／台積電設定 | B56: 2025 | C56: 2026 | D56: 2027 | E56: 2028 | F56: 2029 | G56: 見頂年度 | H56: 說明
A57: 情境 A（台積電 基準 64%） | B57: =((cap_sk_25*1000/fx*sh_sk+cap_mu_25*sh_mu_25+cap_ssds_25*ss_mem*1000/fx*sh_ss)+(((Mkt!$C$57-Mkt!$C$54+ind_cxmt)*sh_oth))*(1+g_oth_dram)^0+((Mkt!$C$61*sh_oth))*(1+g_oth_nand)^0)+(cap_ts_25*(1-0)*sh_fd+MAX(Mkt!$C$43-cap_ts_25*(1-0)*sh_fd,0)*(1+g_oth_fd)^0)+Mkt!C50*(((cap_sk_25*1000/fx*sh_sk+cap_mu_25*sh_mu_25+cap_ssds_25*ss_mem*1000/fx*sh_ss)+(((Mkt!$C$57-Mkt!$C$54+ind_cxmt)*sh_oth))*(1+g_oth_dram)^0+((Mkt!$C$61*sh_oth))*(1+g_oth_nand)^0)+(cap_ts_25*(1-0)*sh_fd+MAX(Mkt!$C$43-cap_ts_25*(1-0)*sh_fd,0)*(1+g_oth_fd)^0))+Mkt!C116+Mkt!C117 -> 134.68936 | C57: =((cap_sk_26*1000/fx*sh_sk+cap_mu_26*sh_mu_26+cap_ss_26*1000/fx*sh_ss)+(((Mkt!$C$57-Mkt!$C$54+ind_cxmt)*sh_oth))*(1+g_oth_dram)^1+((Mkt!$C$61*sh_oth))*(1+g_oth_nand)^1)+(cap_ts_26*(1-0)*sh_fd+MAX(Mkt!$C$43-cap_ts_25*(1-0)*sh_fd,0)*(1+g_oth_fd)^1)+Mkt!D50*(((cap_sk_26*1000/fx*sh_sk+cap_mu_26*sh_mu_26+cap_ss_26*1000/fx*sh_ss)+(((Mkt!$C$57-Mkt!$C$54+ind_cxmt)*sh_oth))*(1+g_oth_dram)^1+((Mkt!$C$61*sh_oth))*(1+g_oth_nand)^1)+(cap_ts_26*(1-0)*sh_fd+MAX(Mkt!$C$43-cap_ts_25*(1-0)*sh_fd,0)*(1+g_oth_fd)^1))+Mkt!D116+Mkt!D117 -> 178.15705 | D57: =((cap_sk_27*1000/fx*sh_sk+cap_mu_27*sh_mu_27+cap_ss_27*1000/fx*sh_ss)+(((Mkt!$C$57-Mkt!$C$54+ind_cxmt)*sh_oth))*(1+g_oth_dram)^2+((Mkt!$C$61*sh_oth))*(1+g_oth_nand)^2)+(cap_ts_27*(1-0)*sh_fd+MAX(Mkt!$C$43-cap_ts_25*(1-0)*sh_fd,0)*(1+g_oth_fd)^2)+Mkt!E50*(((cap_sk_27*1000/fx*sh_sk+cap_mu_27*sh_mu_27+cap_ss_27*1000/fx*sh_ss)+(((Mkt!$C$57-Mkt!$C$54+ind_cxmt)*sh_oth))*(1+g_oth_dram)^2+((Mkt!$C$61*sh_oth))*(1+g_oth_nand)^2)+(cap_ts_27*(1-0)*sh_fd+MAX(Mkt!$C$43-cap_ts_25*(1-0)*sh_fd,0)*(1+g_oth_fd)^2))+Mkt!E116+Mkt!E117 -> 218.22554 | E57: =((cap_sk_28*1000/fx*sh_sk+cap_mu_28*sh_mu_27+cap_ss_28*1000/fx*sh_ss)+(((Mkt!$C$57-Mkt!$C$54+ind_cxmt)*sh_oth))*(1+g_oth_dram)^3+((Mkt!$C$61*sh_oth))*(1+g_oth_nand)^3)+(cap_ts_28*(1-0)*sh_fd+MAX(Mkt!$C$43-cap_ts_25*(1-0)*sh_fd,0)*(1+g_oth_fd)^3)+Mkt!F50*(((cap_sk_28*1000/fx*sh_sk+cap_mu_28*sh_mu_27+cap_ss_28*1000/fx*sh_ss)+(((Mkt!$C$57-Mkt!$C$54+ind_cxmt)*sh_oth))*(1+g_oth_dram)^3+((Mkt!$C$61*sh_oth))*(1+g_oth_nand)^3)+(cap_ts_28*(1-0)*sh_fd+MAX(Mkt!$C$43-cap_ts_25*(1-0)*sh_fd,0)*(1+g_oth_fd)^3))+Mkt!F116+Mkt!F117 -> 246.02863 | F57: =((cap_sk_29*1000/fx*sh_sk+cap_mu_29*sh_mu_27+cap_ss_29*1000/fx*sh_ss)+(((Mkt!$C$57-Mkt!$C$54+ind_cxmt)*sh_oth))*(1+g_oth_dram)^4+((Mkt!$C$61*sh_oth))*(1+g_oth_nand)^4)+(cap_ts_29*(1-0)*sh_fd+MAX(Mkt!$C$43-cap_ts_25*(1-0)*sh_fd,0)*(1+g_oth_fd)^4)+Mkt!G50*(((cap_sk_29*1000/fx*sh_sk+cap_mu_29*sh_mu_27+cap_ss_29*1000/fx*sh_ss)+(((Mkt!$C$57-Mkt!$C$54+ind_cxmt)*sh_oth))*(1+g_oth_dram)^4+((Mkt!$C$61*sh_oth))*(1+g_oth_nand)^4)+(cap_ts_29*(1-0)*sh_fd+MAX(Mkt!$C$43-cap_ts_25*(1-0)*sh_fd,0)*(1+g_oth_fd)^4))+Mkt!G116+Mkt!G117 -> 260.65569 | G57: =IF(ROUND(F57,9)=ROUND(MAX(B57:F57),9),2029,IF(ROUND(E57,9)=ROUND(MAX(B57:F57),9),2028,IF(ROUND(D57,9)=ROUND(MAX(B57:F57),9),2027,IF(ROUND(C57,9)=ROUND(MAX(B57:F57),9),2026,2025)))) -> 2029
A58: 情境 B（台積電 基準 64%） | B58: =((cap_sk_25*1000/fx*sh_sk+cap_mu_25*sh_mu_25+cap_ssds_25*ss_mem*1000/fx*sh_ss)+(((Mkt!$C$57-Mkt!$C$54+ind_cxmt)*sh_oth))*(1+g_oth_dram)^0+((Mkt!$C$61*sh_oth))*(1+g_oth_nand)^0)+(cap_ts_25*(1-0)*sh_fd+MAX(Mkt!$C$43-cap_ts_25*(1-0)*sh_fd,0)*(1+g_oth_fd)^0)+Mkt!C50*(((cap_sk_25*1000/fx*sh_sk+cap_mu_25*sh_mu_25+cap_ssds_25*ss_mem*1000/fx*sh_ss)+(((Mkt!$C$57-Mkt!$C$54+ind_cxmt)*sh_oth))*(1+g_oth_dram)^0+((Mkt!$C$61*sh_oth))*(1+g_oth_nand)^0)+(cap_ts_25*(1-0)*sh_fd+MAX(Mkt!$C$43-cap_ts_25*(1-0)*sh_fd,0)*(1+g_oth_fd)^0))+Mkt!C116+Mkt!C117 -> 134.68936 | C58: =((cap_sk_26*1000/fx*sh_sk+cap_mu_26*sh_mu_26+cap_ss_26*1000/fx*sh_ss)+(((Mkt!$C$57-Mkt!$C$54+ind_cxmt)*sh_oth))*(1+g_oth_dram)^1+((Mkt!$C$61*sh_oth))*(1+g_oth_nand)^1)+(cap_ts_26*(1-0)*sh_fd+MAX(Mkt!$C$43-cap_ts_25*(1-0)*sh_fd,0)*(1+g_oth_fd)^1)+Mkt!D50*(((cap_sk_26*1000/fx*sh_sk+cap_mu_26*sh_mu_26+cap_ss_26*1000/fx*sh_ss)+(((Mkt!$C$57-Mkt!$C$54+ind_cxmt)*sh_oth))*(1+g_oth_dram)^1+((Mkt!$C$61*sh_oth))*(1+g_oth_nand)^1)+(cap_ts_26*(1-0)*sh_fd+MAX(Mkt!$C$43-cap_ts_25*(1-0)*sh_fd,0)*(1+g_oth_fd)^1))+Mkt!D116+Mkt!D117 -> 178.15705 | D58: =((cap_sk_27*1000/fx*sh_sk+cap_mu_27*sh_mu_27+cap_ss_27*1000/fx*sh_ss)+(((Mkt!$C$57-Mkt!$C$54+ind_cxmt)*sh_oth))*(1+g_oth_dram)^2+((Mkt!$C$61*sh_oth))*(1+g_oth_nand)^2)+(cap_ts_27*(1-0)*sh_fd+MAX(Mkt!$C$43-cap_ts_25*(1-0)*sh_fd,0)*(1+g_oth_fd)^2)+Mkt!E50*(((cap_sk_27*1000/fx*sh_sk+cap_mu_27*sh_mu_27+cap_ss_27*1000/fx*sh_ss)+(((Mkt!$C$57-Mkt!$C$54+ind_cxmt)*sh_oth))*(1+g_oth_dram)^2+((Mkt!$C$61*sh_oth))*(1+g_oth_nand)^2)+(cap_ts_27*(1-0)*sh_fd+MAX(Mkt!$C$43-cap_ts_25*(1-0)*sh_fd,0)*(1+g_oth_fd)^2))+Mkt!E116+Mkt!E117 -> 218.22554 | E58: =D58*ck_B_28 -> 218.22554 | F58: =E58*ck_B_29 -> 207.31426 | G58: =IF(ROUND(F58,9)=ROUND(MAX(B58:F58),9),2029,IF(ROUND(E58,9)=ROUND(MAX(B58:F58),9),2028,IF(ROUND(D58,9)=ROUND(MAX(B58:F58),9),2027,IF(ROUND(C58,9)=ROUND(MAX(B58:F58),9),2026,2025)))) -> 2028
A59: 情境 C（台積電 基準 64%） | B59: =((cap_sk_25*1000/fx*sh_sk+cap_mu_25*sh_mu_25+cap_ssds_25*ss_mem*1000/fx*sh_ss)+(((Mkt!$C$57-Mkt!$C$54+ind_cxmt)*sh_oth))*(1+g_oth_dram)^0+((Mkt!$C$61*sh_oth))*(1+g_oth_nand)^0)+(cap_ts_25*(1-0)*sh_fd+MAX(Mkt!$C$43-cap_ts_25*(1-0)*sh_fd,0)*(1+g_oth_fd)^0)+Mkt!C50*(((cap_sk_25*1000/fx*sh_sk+cap_mu_25*sh_mu_25+cap_ssds_25*ss_mem*1000/fx*sh_ss)+(((Mkt!$C$57-Mkt!$C$54+ind_cxmt)*sh_oth))*(1+g_oth_dram)^0+((Mkt!$C$61*sh_oth))*(1+g_oth_nand)^0)+(cap_ts_25*(1-0)*sh_fd+MAX(Mkt!$C$43-cap_ts_25*(1-0)*sh_fd,0)*(1+g_oth_fd)^0))+Mkt!C116+Mkt!C117 -> 134.68936 | C59: =((cap_sk_26*1000/fx*sh_sk+cap_mu_26*sh_mu_26+cap_ss_26*1000/fx*sh_ss)+(((Mkt!$C$57-Mkt!$C$54+ind_cxmt)*sh_oth))*(1+g_oth_dram)^1+((Mkt!$C$61*sh_oth))*(1+g_oth_nand)^1)+(cap_ts_26*(1-0)*sh_fd+MAX(Mkt!$C$43-cap_ts_25*(1-0)*sh_fd,0)*(1+g_oth_fd)^1)+Mkt!D50*(((cap_sk_26*1000/fx*sh_sk+cap_mu_26*sh_mu_26+cap_ss_26*1000/fx*sh_ss)+(((Mkt!$C$57-Mkt!$C$54+ind_cxmt)*sh_oth))*(1+g_oth_dram)^1+((Mkt!$C$61*sh_oth))*(1+g_oth_nand)^1)+(cap_ts_26*(1-0)*sh_fd+MAX(Mkt!$C$43-cap_ts_25*(1-0)*sh_fd,0)*(1+g_oth_fd)^1))+Mkt!D116+Mkt!D117 -> 178.15705 | D59: =((cap_sk_27*1000/fx*sh_sk+cap_mu_27*sh_mu_27+cap_ss_27*1000/fx*sh_ss)+(((Mkt!$C$57-Mkt!$C$54+ind_cxmt)*sh_oth))*(1+g_oth_dram)^2+((Mkt!$C$61*sh_oth))*(1+g_oth_nand)^2)+(cap_ts_27*(1-0)*sh_fd+MAX(Mkt!$C$43-cap_ts_25*(1-0)*sh_fd,0)*(1+g_oth_fd)^2)+Mkt!E50*(((cap_sk_27*1000/fx*sh_sk+cap_mu_27*sh_mu_27+cap_ss_27*1000/fx*sh_ss)+(((Mkt!$C$57-Mkt!$C$54+ind_cxmt)*sh_oth))*(1+g_oth_dram)^2+((Mkt!$C$61*sh_oth))*(1+g_oth_nand)^2)+(cap_ts_27*(1-0)*sh_fd+MAX(Mkt!$C$43-cap_ts_25*(1-0)*sh_fd,0)*(1+g_oth_fd)^2))+Mkt!E116+Mkt!E117 -> 218.22554 | E59: =D59*ck_C_28 -> 174.58043 | F59: =E59*ck_C_29 -> 174.58043 | G59: =IF(ROUND(F59,9)=ROUND(MAX(B59:F59),9),2029,IF(ROUND(E59,9)=ROUND(MAX(B59:F59),9),2028,IF(ROUND(D59,9)=ROUND(MAX(B59:F59),9),2027,IF(ROUND(C59,9)=ROUND(MAX(B59:F59),9),2026,2025)))) -> 2027
A60: 情境 A（台積電 50%（低）） | B60: =((cap_sk_25*1000/fx*sh_sk+cap_mu_25*sh_mu_25+cap_ssds_25*ss_mem*1000/fx*sh_ss)+(((Mkt!$C$57-Mkt!$C$54+ind_cxmt)*sh_oth))*(1+g_oth_dram)^0+((Mkt!$C$61*sh_oth))*(1+g_oth_nand)^0)+(cap_ts_25*(1-0)*sh_fd_lo+MAX(Mkt!$C$43-cap_ts_25*(1-0)*sh_fd_lo,0)*(1+g_oth_fd)^0)+Mkt!C50*(((cap_sk_25*1000/fx*sh_sk+cap_mu_25*sh_mu_25+cap_ssds_25*ss_mem*1000/fx*sh_ss)+(((Mkt!$C$57-Mkt!$C$54+ind_cxmt)*sh_oth))*(1+g_oth_dram)^0+((Mkt!$C$61*sh_oth))*(1+g_oth_nand)^0)+(cap_ts_25*(1-0)*sh_fd_lo+MAX(Mkt!$C$43-cap_ts_25*(1-0)*sh_fd_lo,0)*(1+g_oth_fd)^0))+Mkt!C116+Mkt!C117 -> 134.68936 | C60: =((cap_sk_26*1000/fx*sh_sk+cap_mu_26*sh_mu_26+cap_ss_26*1000/fx*sh_ss)+(((Mkt!$C$57-Mkt!$C$54+ind_cxmt)*sh_oth))*(1+g_oth_dram)^1+((Mkt!$C$61*sh_oth))*(1+g_oth_nand)^1)+(cap_ts_26*(1-0)*sh_fd_lo+MAX(Mkt!$C$43-cap_ts_25*(1-0)*sh_fd_lo,0)*(1+g_oth_fd)^1)+Mkt!D50*(((cap_sk_26*1000/fx*sh_sk+cap_mu_26*sh_mu_26+cap_ss_26*1000/fx*sh_ss)+(((Mkt!$C$57-Mkt!$C$54+ind_cxmt)*sh_oth))*(1+g_oth_dram)^1+((Mkt!$C$61*sh_oth))*(1+g_oth_nand)^1)+(cap_ts_26*(1-0)*sh_fd_lo+MAX(Mkt!$C$43-cap_ts_25*(1-0)*sh_fd_lo,0)*(1+g_oth_fd)^1))+Mkt!D116+Mkt!D117 -> 175.35566 | D60: =((cap_sk_27*1000/fx*sh_sk+cap_mu_27*sh_mu_27+cap_ss_27*1000/fx*sh_ss)+(((Mkt!$C$57-Mkt!$C$54+ind_cxmt)*sh_oth))*(1+g_oth_dram)^2+((Mkt!$C$61*sh_oth))*(1+g_oth_nand)^2)+(cap_ts_27*(1-0)*sh_fd_lo+MAX(Mkt!$C$43-cap_ts_25*(1-0)*sh_fd_lo,0)*(1+g_oth_fd)^2)+Mkt!E50*(((cap_sk_27*1000/fx*sh_sk+cap_mu_27*sh_mu_27+cap_ss_27*1000/fx*sh_ss)+(((Mkt!$C$57-Mkt!$C$54+ind_cxmt)*sh_oth))*(1+g_oth_dram)^2+((Mkt!$C$61*sh_oth))*(1+g_oth_nand)^2)+(cap_ts_27*(1-0)*sh_fd_lo+MAX(Mkt!$C$43-cap_ts_25*(1-0)*sh_fd_lo,0)*(1+g_oth_fd)^2))+Mkt!E116+Mkt!E117 -> 213.6224 | E60: =((cap_sk_28*1000/fx*sh_sk+cap_mu_28*sh_mu_27+cap_ss_28*1000/fx*sh_ss)+(((Mkt!$C$57-Mkt!$C$54+ind_cxmt)*sh_oth))*(1+g_oth_dram)^3+((Mkt!$C$61*sh_oth))*(1+g_oth_nand)^3)+(cap_ts_28*(1-0)*sh_fd_lo+MAX(Mkt!$C$43-cap_ts_25*(1-0)*sh_fd_lo,0)*(1+g_oth_fd)^3)+Mkt!F50*(((cap_sk_28*1000/fx*sh_sk+cap_mu_28*sh_mu_27+cap_ss_28*1000/fx*sh_ss)+(((Mkt!$C$57-Mkt!$C$54+ind_cxmt)*sh_oth))*(1+g_oth_dram)^3+((Mkt!$C$61*sh_oth))*(1+g_oth_nand)^3)+(cap_ts_28*(1-0)*sh_fd_lo+MAX(Mkt!$C$43-cap_ts_25*(1-0)*sh_fd_lo,0)*(1+g_oth_fd)^3))+Mkt!F116+Mkt!F117 -> 239.98244 | F60: =((cap_sk_29*1000/fx*sh_sk+cap_mu_29*sh_mu_27+cap_ss_29*1000/fx*sh_ss)+(((Mkt!$C$57-Mkt!$C$54+ind_cxmt)*sh_oth))*(1+g_oth_dram)^4+((Mkt!$C$61*sh_oth))*(1+g_oth_nand)^4)+(cap_ts_29*(1-0)*sh_fd_lo+MAX(Mkt!$C$43-cap_ts_25*(1-0)*sh_fd_lo,0)*(1+g_oth_fd)^4)+Mkt!G50*(((cap_sk_29*1000/fx*sh_sk+cap_mu_29*sh_mu_27+cap_ss_29*1000/fx*sh_ss)+(((Mkt!$C$57-Mkt!$C$54+ind_cxmt)*sh_oth))*(1+g_oth_dram)^4+((Mkt!$C$61*sh_oth))*(1+g_oth_nand)^4)+(cap_ts_29*(1-0)*sh_fd_lo+MAX(Mkt!$C$43-cap_ts_25*(1-0)*sh_fd_lo,0)*(1+g_oth_fd)^4))+Mkt!G116+Mkt!G117 -> 254.4715 | G60: =IF(ROUND(F60,9)=ROUND(MAX(B60:F60),9),2029,IF(ROUND(E60,9)=ROUND(MAX(B60:F60),9),2028,IF(ROUND(D60,9)=ROUND(MAX(B60:F60),9),2027,IF(ROUND(C60,9)=ROUND(MAX(B60:F60),9),2026,2025)))) -> 2029
A61: 情境 B（台積電 50%（低）） | B61: =((cap_sk_25*1000/fx*sh_sk+cap_mu_25*sh_mu_25+cap_ssds_25*ss_mem*1000/fx*sh_ss)+(((Mkt!$C$57-Mkt!$C$54+ind_cxmt)*sh_oth))*(1+g_oth_dram)^0+((Mkt!$C$61*sh_oth))*(1+g_oth_nand)^0)+(cap_ts_25*(1-0)*sh_fd_lo+MAX(Mkt!$C$43-cap_ts_25*(1-0)*sh_fd_lo,0)*(1+g_oth_fd)^0)+Mkt!C50*(((cap_sk_25*1000/fx*sh_sk+cap_mu_25*sh_mu_25+cap_ssds_25*ss_mem*1000/fx*sh_ss)+(((Mkt!$C$57-Mkt!$C$54+ind_cxmt)*sh_oth))*(1+g_oth_dram)^0+((Mkt!$C$61*sh_oth))*(1+g_oth_nand)^0)+(cap_ts_25*(1-0)*sh_fd_lo+MAX(Mkt!$C$43-cap_ts_25*(1-0)*sh_fd_lo,0)*(1+g_oth_fd)^0))+Mkt!C116+Mkt!C117 -> 134.68936 | C61: =((cap_sk_26*1000/fx*sh_sk+cap_mu_26*sh_mu_26+cap_ss_26*1000/fx*sh_ss)+(((Mkt!$C$57-Mkt!$C$54+ind_cxmt)*sh_oth))*(1+g_oth_dram)^1+((Mkt!$C$61*sh_oth))*(1+g_oth_nand)^1)+(cap_ts_26*(1-0)*sh_fd_lo+MAX(Mkt!$C$43-cap_ts_25*(1-0)*sh_fd_lo,0)*(1+g_oth_fd)^1)+Mkt!D50*(((cap_sk_26*1000/fx*sh_sk+cap_mu_26*sh_mu_26+cap_ss_26*1000/fx*sh_ss)+(((Mkt!$C$57-Mkt!$C$54+ind_cxmt)*sh_oth))*(1+g_oth_dram)^1+((Mkt!$C$61*sh_oth))*(1+g_oth_nand)^1)+(cap_ts_26*(1-0)*sh_fd_lo+MAX(Mkt!$C$43-cap_ts_25*(1-0)*sh_fd_lo,0)*(1+g_oth_fd)^1))+Mkt!D116+Mkt!D117 -> 175.35566 | D61: =((cap_sk_27*1000/fx*sh_sk+cap_mu_27*sh_mu_27+cap_ss_27*1000/fx*sh_ss)+(((Mkt!$C$57-Mkt!$C$54+ind_cxmt)*sh_oth))*(1+g_oth_dram)^2+((Mkt!$C$61*sh_oth))*(1+g_oth_nand)^2)+(cap_ts_27*(1-0)*sh_fd_lo+MAX(Mkt!$C$43-cap_ts_25*(1-0)*sh_fd_lo,0)*(1+g_oth_fd)^2)+Mkt!E50*(((cap_sk_27*1000/fx*sh_sk+cap_mu_27*sh_mu_27+cap_ss_27*1000/fx*sh_ss)+(((Mkt!$C$57-Mkt!$C$54+ind_cxmt)*sh_oth))*(1+g_oth_dram)^2+((Mkt!$C$61*sh_oth))*(1+g_oth_nand)^2)+(cap_ts_27*(1-0)*sh_fd_lo+MAX(Mkt!$C$43-cap_ts_25*(1-0)*sh_fd_lo,0)*(1+g_oth_fd)^2))+Mkt!E116+Mkt!E117 -> 213.6224 | E61: =D61*ck_B_28 -> 213.6224 | F61: =E61*ck_B_29 -> 202.94128 | G61: =IF(ROUND(F61,9)=ROUND(MAX(B61:F61),9),2029,IF(ROUND(E61,9)=ROUND(MAX(B61:F61),9),2028,IF(ROUND(D61,9)=ROUND(MAX(B61:F61),9),2027,IF(ROUND(C61,9)=ROUND(MAX(B61:F61),9),2026,2025)))) -> 2028
A62: 情境 C（台積電 50%（低）） | B62: =((cap_sk_25*1000/fx*sh_sk+cap_mu_25*sh_mu_25+cap_ssds_25*ss_mem*1000/fx*sh_ss)+(((Mkt!$C$57-Mkt!$C$54+ind_cxmt)*sh_oth))*(1+g_oth_dram)^0+((Mkt!$C$61*sh_oth))*(1+g_oth_nand)^0)+(cap_ts_25*(1-0)*sh_fd_lo+MAX(Mkt!$C$43-cap_ts_25*(1-0)*sh_fd_lo,0)*(1+g_oth_fd)^0)+Mkt!C50*(((cap_sk_25*1000/fx*sh_sk+cap_mu_25*sh_mu_25+cap_ssds_25*ss_mem*1000/fx*sh_ss)+(((Mkt!$C$57-Mkt!$C$54+ind_cxmt)*sh_oth))*(1+g_oth_dram)^0+((Mkt!$C$61*sh_oth))*(1+g_oth_nand)^0)+(cap_ts_25*(1-0)*sh_fd_lo+MAX(Mkt!$C$43-cap_ts_25*(1-0)*sh_fd_lo,0)*(1+g_oth_fd)^0))+Mkt!C116+Mkt!C117 -> 134.68936 | C62: =((cap_sk_26*1000/fx*sh_sk+cap_mu_26*sh_mu_26+cap_ss_26*1000/fx*sh_ss)+(((Mkt!$C$57-Mkt!$C$54+ind_cxmt)*sh_oth))*(1+g_oth_dram)^1+((Mkt!$C$61*sh_oth))*(1+g_oth_nand)^1)+(cap_ts_26*(1-0)*sh_fd_lo+MAX(Mkt!$C$43-cap_ts_25*(1-0)*sh_fd_lo,0)*(1+g_oth_fd)^1)+Mkt!D50*(((cap_sk_26*1000/fx*sh_sk+cap_mu_26*sh_mu_26+cap_ss_26*1000/fx*sh_ss)+(((Mkt!$C$57-Mkt!$C$54+ind_cxmt)*sh_oth))*(1+g_oth_dram)^1+((Mkt!$C$61*sh_oth))*(1+g_oth_nand)^1)+(cap_ts_26*(1-0)*sh_fd_lo+MAX(Mkt!$C$43-cap_ts_25*(1-0)*sh_fd_lo,0)*(1+g_oth_fd)^1))+Mkt!D116+Mkt!D117 -> 175.35566 | D62: =((cap_sk_27*1000/fx*sh_sk+cap_mu_27*sh_mu_27+cap_ss_27*1000/fx*sh_ss)+(((Mkt!$C$57-Mkt!$C$54+ind_cxmt)*sh_oth))*(1+g_oth_dram)^2+((Mkt!$C$61*sh_oth))*(1+g_oth_nand)^2)+(cap_ts_27*(1-0)*sh_fd_lo+MAX(Mkt!$C$43-cap_ts_25*(1-0)*sh_fd_lo,0)*(1+g_oth_fd)^2)+Mkt!E50*(((cap_sk_27*1000/fx*sh_sk+cap_mu_27*sh_mu_27+cap_ss_27*1000/fx*sh_ss)+(((Mkt!$C$57-Mkt!$C$54+ind_cxmt)*sh_oth))*(1+g_oth_dram)^2+((Mkt!$C$61*sh_oth))*(1+g_oth_nand)^2)+(cap_ts_27*(1-0)*sh_fd_lo+MAX(Mkt!$C$43-cap_ts_25*(1-0)*sh_fd_lo,0)*(1+g_oth_fd)^2))+Mkt!E116+Mkt!E117 -> 213.6224 | E62: =D62*ck_C_28 -> 170.89792 | F62: =E62*ck_C_29 -> 170.89792 | G62: =IF(ROUND(F62,9)=ROUND(MAX(B62:F62),9),2029,IF(ROUND(E62,9)=ROUND(MAX(B62:F62),9),2028,IF(ROUND(D62,9)=ROUND(MAX(B62:F62),9),2027,IF(ROUND(C62,9)=ROUND(MAX(B62:F62),9),2026,2025)))) -> 2027
A63: 情境 A（台積電 75%（高）） | B63: =((cap_sk_25*1000/fx*sh_sk+cap_mu_25*sh_mu_25+cap_ssds_25*ss_mem*1000/fx*sh_ss)+(((Mkt!$C$57-Mkt!$C$54+ind_cxmt)*sh_oth))*(1+g_oth_dram)^0+((Mkt!$C$61*sh_oth))*(1+g_oth_nand)^0)+(cap_ts_25*(1-0)*sh_fd_hi+MAX(Mkt!$C$43-cap_ts_25*(1-0)*sh_fd_hi,0)*(1+g_oth_fd)^0)+Mkt!C50*(((cap_sk_25*1000/fx*sh_sk+cap_mu_25*sh_mu_25+cap_ssds_25*ss_mem*1000/fx*sh_ss)+(((Mkt!$C$57-Mkt!$C$54+ind_cxmt)*sh_oth))*(1+g_oth_dram)^0+((Mkt!$C$61*sh_oth))*(1+g_oth_nand)^0)+(cap_ts_25*(1-0)*sh_fd_hi+MAX(Mkt!$C$43-cap_ts_25*(1-0)*sh_fd_hi,0)*(1+g_oth_fd)^0))+Mkt!C116+Mkt!C117 -> 134.68936 | C63: =((cap_sk_26*1000/fx*sh_sk+cap_mu_26*sh_mu_26+cap_ss_26*1000/fx*sh_ss)+(((Mkt!$C$57-Mkt!$C$54+ind_cxmt)*sh_oth))*(1+g_oth_dram)^1+((Mkt!$C$61*sh_oth))*(1+g_oth_nand)^1)+(cap_ts_26*(1-0)*sh_fd_hi+MAX(Mkt!$C$43-cap_ts_25*(1-0)*sh_fd_hi,0)*(1+g_oth_fd)^1)+Mkt!D50*(((cap_sk_26*1000/fx*sh_sk+cap_mu_26*sh_mu_26+cap_ss_26*1000/fx*sh_ss)+(((Mkt!$C$57-Mkt!$C$54+ind_cxmt)*sh_oth))*(1+g_oth_dram)^1+((Mkt!$C$61*sh_oth))*(1+g_oth_nand)^1)+(cap_ts_26*(1-0)*sh_fd_hi+MAX(Mkt!$C$43-cap_ts_25*(1-0)*sh_fd_hi,0)*(1+g_oth_fd)^1))+Mkt!D116+Mkt!D117 -> 180.35814 | D63: =((cap_sk_27*1000/fx*sh_sk+cap_mu_27*sh_mu_27+cap_ss_27*1000/fx*sh_ss)+(((Mkt!$C$57-Mkt!$C$54+ind_cxmt)*sh_oth))*(1+g_oth_dram)^2+((Mkt!$C$61*sh_oth))*(1+g_oth_nand)^2)+(cap_ts_27*(1-0)*sh_fd_hi+MAX(Mkt!$C$43-cap_ts_25*(1-0)*sh_fd_hi,0)*(1+g_oth_fd)^2)+Mkt!E50*(((cap_sk_27*1000/fx*sh_sk+cap_mu_27*sh_mu_27+cap_ss_27*1000/fx*sh_ss)+(((Mkt!$C$57-Mkt!$C$54+ind_cxmt)*sh_oth))*(1+g_oth_dram)^2+((Mkt!$C$61*sh_oth))*(1+g_oth_nand)^2)+(cap_ts_27*(1-0)*sh_fd_hi+MAX(Mkt!$C$43-cap_ts_25*(1-0)*sh_fd_hi,0)*(1+g_oth_fd)^2))+Mkt!E116+Mkt!E117 -> 221.84228 | E63: =((cap_sk_28*1000/fx*sh_sk+cap_mu_28*sh_mu_27+cap_ss_28*1000/fx*sh_ss)+(((Mkt!$C$57-Mkt!$C$54+ind_cxmt)*sh_oth))*(1+g_oth_dram)^3+((Mkt!$C$61*sh_oth))*(1+g_oth_nand)^3)+(cap_ts_28*(1-0)*sh_fd_hi+MAX(Mkt!$C$43-cap_ts_25*(1-0)*sh_fd_hi,0)*(1+g_oth_fd)^3)+Mkt!F50*(((cap_sk_28*1000/fx*sh_sk+cap_mu_28*sh_mu_27+cap_ss_28*1000/fx*sh_ss)+(((Mkt!$C$57-Mkt!$C$54+ind_cxmt)*sh_oth))*(1+g_oth_dram)^3+((Mkt!$C$61*sh_oth))*(1+g_oth_nand)^3)+(cap_ts_28*(1-0)*sh_fd_hi+MAX(Mkt!$C$43-cap_ts_25*(1-0)*sh_fd_hi,0)*(1+g_oth_fd)^3))+Mkt!F116+Mkt!F117 -> 250.7792 | F63: =((cap_sk_29*1000/fx*sh_sk+cap_mu_29*sh_mu_27+cap_ss_29*1000/fx*sh_ss)+(((Mkt!$C$57-Mkt!$C$54+ind_cxmt)*sh_oth))*(1+g_oth_dram)^4+((Mkt!$C$61*sh_oth))*(1+g_oth_nand)^4)+(cap_ts_29*(1-0)*sh_fd_hi+MAX(Mkt!$C$43-cap_ts_25*(1-0)*sh_fd_hi,0)*(1+g_oth_fd)^4)+Mkt!G50*(((cap_sk_29*1000/fx*sh_sk+cap_mu_29*sh_mu_27+cap_ss_29*1000/fx*sh_ss)+(((Mkt!$C$57-Mkt!$C$54+ind_cxmt)*sh_oth))*(1+g_oth_dram)^4+((Mkt!$C$61*sh_oth))*(1+g_oth_nand)^4)+(cap_ts_29*(1-0)*sh_fd_hi+MAX(Mkt!$C$43-cap_ts_25*(1-0)*sh_fd_hi,0)*(1+g_oth_fd)^4))+Mkt!G116+Mkt!G117 -> 265.51469 | G63: =IF(ROUND(F63,9)=ROUND(MAX(B63:F63),9),2029,IF(ROUND(E63,9)=ROUND(MAX(B63:F63),9),2028,IF(ROUND(D63,9)=ROUND(MAX(B63:F63),9),2027,IF(ROUND(C63,9)=ROUND(MAX(B63:F63),9),2026,2025)))) -> 2029
A64: 情境 B（台積電 75%（高）） | B64: =((cap_sk_25*1000/fx*sh_sk+cap_mu_25*sh_mu_25+cap_ssds_25*ss_mem*1000/fx*sh_ss)+(((Mkt!$C$57-Mkt!$C$54+ind_cxmt)*sh_oth))*(1+g_oth_dram)^0+((Mkt!$C$61*sh_oth))*(1+g_oth_nand)^0)+(cap_ts_25*(1-0)*sh_fd_hi+MAX(Mkt!$C$43-cap_ts_25*(1-0)*sh_fd_hi,0)*(1+g_oth_fd)^0)+Mkt!C50*(((cap_sk_25*1000/fx*sh_sk+cap_mu_25*sh_mu_25+cap_ssds_25*ss_mem*1000/fx*sh_ss)+(((Mkt!$C$57-Mkt!$C$54+ind_cxmt)*sh_oth))*(1+g_oth_dram)^0+((Mkt!$C$61*sh_oth))*(1+g_oth_nand)^0)+(cap_ts_25*(1-0)*sh_fd_hi+MAX(Mkt!$C$43-cap_ts_25*(1-0)*sh_fd_hi,0)*(1+g_oth_fd)^0))+Mkt!C116+Mkt!C117 -> 134.68936 | C64: =((cap_sk_26*1000/fx*sh_sk+cap_mu_26*sh_mu_26+cap_ss_26*1000/fx*sh_ss)+(((Mkt!$C$57-Mkt!$C$54+ind_cxmt)*sh_oth))*(1+g_oth_dram)^1+((Mkt!$C$61*sh_oth))*(1+g_oth_nand)^1)+(cap_ts_26*(1-0)*sh_fd_hi+MAX(Mkt!$C$43-cap_ts_25*(1-0)*sh_fd_hi,0)*(1+g_oth_fd)^1)+Mkt!D50*(((cap_sk_26*1000/fx*sh_sk+cap_mu_26*sh_mu_26+cap_ss_26*1000/fx*sh_ss)+(((Mkt!$C$57-Mkt!$C$54+ind_cxmt)*sh_oth))*(1+g_oth_dram)^1+((Mkt!$C$61*sh_oth))*(1+g_oth_nand)^1)+(cap_ts_26*(1-0)*sh_fd_hi+MAX(Mkt!$C$43-cap_ts_25*(1-0)*sh_fd_hi,0)*(1+g_oth_fd)^1))+Mkt!D116+Mkt!D117 -> 180.35814 | D64: =((cap_sk_27*1000/fx*sh_sk+cap_mu_27*sh_mu_27+cap_ss_27*1000/fx*sh_ss)+(((Mkt!$C$57-Mkt!$C$54+ind_cxmt)*sh_oth))*(1+g_oth_dram)^2+((Mkt!$C$61*sh_oth))*(1+g_oth_nand)^2)+(cap_ts_27*(1-0)*sh_fd_hi+MAX(Mkt!$C$43-cap_ts_25*(1-0)*sh_fd_hi,0)*(1+g_oth_fd)^2)+Mkt!E50*(((cap_sk_27*1000/fx*sh_sk+cap_mu_27*sh_mu_27+cap_ss_27*1000/fx*sh_ss)+(((Mkt!$C$57-Mkt!$C$54+ind_cxmt)*sh_oth))*(1+g_oth_dram)^2+((Mkt!$C$61*sh_oth))*(1+g_oth_nand)^2)+(cap_ts_27*(1-0)*sh_fd_hi+MAX(Mkt!$C$43-cap_ts_25*(1-0)*sh_fd_hi,0)*(1+g_oth_fd)^2))+Mkt!E116+Mkt!E117 -> 221.84228 | E64: =D64*ck_B_28 -> 221.84228 | F64: =E64*ck_B_29 -> 210.75017 | G64: =IF(ROUND(F64,9)=ROUND(MAX(B64:F64),9),2029,IF(ROUND(E64,9)=ROUND(MAX(B64:F64),9),2028,IF(ROUND(D64,9)=ROUND(MAX(B64:F64),9),2027,IF(ROUND(C64,9)=ROUND(MAX(B64:F64),9),2026,2025)))) -> 2028
A65: 情境 C（台積電 75%（高）） | B65: =((cap_sk_25*1000/fx*sh_sk+cap_mu_25*sh_mu_25+cap_ssds_25*ss_mem*1000/fx*sh_ss)+(((Mkt!$C$57-Mkt!$C$54+ind_cxmt)*sh_oth))*(1+g_oth_dram)^0+((Mkt!$C$61*sh_oth))*(1+g_oth_nand)^0)+(cap_ts_25*(1-0)*sh_fd_hi+MAX(Mkt!$C$43-cap_ts_25*(1-0)*sh_fd_hi,0)*(1+g_oth_fd)^0)+Mkt!C50*(((cap_sk_25*1000/fx*sh_sk+cap_mu_25*sh_mu_25+cap_ssds_25*ss_mem*1000/fx*sh_ss)+(((Mkt!$C$57-Mkt!$C$54+ind_cxmt)*sh_oth))*(1+g_oth_dram)^0+((Mkt!$C$61*sh_oth))*(1+g_oth_nand)^0)+(cap_ts_25*(1-0)*sh_fd_hi+MAX(Mkt!$C$43-cap_ts_25*(1-0)*sh_fd_hi,0)*(1+g_oth_fd)^0))+Mkt!C116+Mkt!C117 -> 134.68936 | C65: =((cap_sk_26*1000/fx*sh_sk+cap_mu_26*sh_mu_26+cap_ss_26*1000/fx*sh_ss)+(((Mkt!$C$57-Mkt!$C$54+ind_cxmt)*sh_oth))*(1+g_oth_dram)^1+((Mkt!$C$61*sh_oth))*(1+g_oth_nand)^1)+(cap_ts_26*(1-0)*sh_fd_hi+MAX(Mkt!$C$43-cap_ts_25*(1-0)*sh_fd_hi,0)*(1+g_oth_fd)^1)+Mkt!D50*(((cap_sk_26*1000/fx*sh_sk+cap_mu_26*sh_mu_26+cap_ss_26*1000/fx*sh_ss)+(((Mkt!$C$57-Mkt!$C$54+ind_cxmt)*sh_oth))*(1+g_oth_dram)^1+((Mkt!$C$61*sh_oth))*(1+g_oth_nand)^1)+(cap_ts_26*(1-0)*sh_fd_hi+MAX(Mkt!$C$43-cap_ts_25*(1-0)*sh_fd_hi,0)*(1+g_oth_fd)^1))+Mkt!D116+Mkt!D117 -> 180.35814 | D65: =((cap_sk_27*1000/fx*sh_sk+cap_mu_27*sh_mu_27+cap_ss_27*1000/fx*sh_ss)+(((Mkt!$C$57-Mkt!$C$54+ind_cxmt)*sh_oth))*(1+g_oth_dram)^2+((Mkt!$C$61*sh_oth))*(1+g_oth_nand)^2)+(cap_ts_27*(1-0)*sh_fd_hi+MAX(Mkt!$C$43-cap_ts_25*(1-0)*sh_fd_hi,0)*(1+g_oth_fd)^2)+Mkt!E50*(((cap_sk_27*1000/fx*sh_sk+cap_mu_27*sh_mu_27+cap_ss_27*1000/fx*sh_ss)+(((Mkt!$C$57-Mkt!$C$54+ind_cxmt)*sh_oth))*(1+g_oth_dram)^2+((Mkt!$C$61*sh_oth))*(1+g_oth_nand)^2)+(cap_ts_27*(1-0)*sh_fd_hi+MAX(Mkt!$C$43-cap_ts_25*(1-0)*sh_fd_hi,0)*(1+g_oth_fd)^2))+Mkt!E116+Mkt!E117 -> 221.84228 | E65: =D65*ck_C_28 -> 177.47383 | F65: =E65*ck_C_29 -> 177.47383 | G65: =IF(ROUND(F65,9)=ROUND(MAX(B65:F65),9),2029,IF(ROUND(E65,9)=ROUND(MAX(B65:F65),9),2028,IF(ROUND(D65,9)=ROUND(MAX(B65:F65),9),2027,IF(ROUND(C65,9)=ROUND(MAX(B65:F65),9),2026,2025)))) -> 2027
A66: 情境 A（台積電 45.5%（比照 SK、三星）） | B66: =((cap_sk_25*1000/fx*sh_sk+cap_mu_25*sh_mu_25+cap_ssds_25*ss_mem*1000/fx*sh_ss)+(((Mkt!$C$57-Mkt!$C$54+ind_cxmt)*sh_oth))*(1+g_oth_dram)^0+((Mkt!$C$61*sh_oth))*(1+g_oth_nand)^0)+(cap_ts_25*(1-0)*sh_sk+MAX(Mkt!$C$43-cap_ts_25*(1-0)*sh_sk,0)*(1+g_oth_fd)^0)+Mkt!C50*(((cap_sk_25*1000/fx*sh_sk+cap_mu_25*sh_mu_25+cap_ssds_25*ss_mem*1000/fx*sh_ss)+(((Mkt!$C$57-Mkt!$C$54+ind_cxmt)*sh_oth))*(1+g_oth_dram)^0+((Mkt!$C$61*sh_oth))*(1+g_oth_nand)^0)+(cap_ts_25*(1-0)*sh_sk+MAX(Mkt!$C$43-cap_ts_25*(1-0)*sh_sk,0)*(1+g_oth_fd)^0))+Mkt!C116+Mkt!C117 -> 134.68936 | C66: =((cap_sk_26*1000/fx*sh_sk+cap_mu_26*sh_mu_26+cap_ss_26*1000/fx*sh_ss)+(((Mkt!$C$57-Mkt!$C$54+ind_cxmt)*sh_oth))*(1+g_oth_dram)^1+((Mkt!$C$61*sh_oth))*(1+g_oth_nand)^1)+(cap_ts_26*(1-0)*sh_sk+MAX(Mkt!$C$43-cap_ts_25*(1-0)*sh_sk,0)*(1+g_oth_fd)^1)+Mkt!D50*(((cap_sk_26*1000/fx*sh_sk+cap_mu_26*sh_mu_26+cap_ss_26*1000/fx*sh_ss)+(((Mkt!$C$57-Mkt!$C$54+ind_cxmt)*sh_oth))*(1+g_oth_dram)^1+((Mkt!$C$61*sh_oth))*(1+g_oth_nand)^1)+(cap_ts_26*(1-0)*sh_sk+MAX(Mkt!$C$43-cap_ts_25*(1-0)*sh_sk,0)*(1+g_oth_fd)^1))+Mkt!D116+Mkt!D117 -> 174.46428 | D66: =((cap_sk_27*1000/fx*sh_sk+cap_mu_27*sh_mu_27+cap_ss_27*1000/fx*sh_ss)+(((Mkt!$C$57-Mkt!$C$54+ind_cxmt)*sh_oth))*(1+g_oth_dram)^2+((Mkt!$C$61*sh_oth))*(1+g_oth_nand)^2)+(cap_ts_27*(1-0)*sh_sk+MAX(Mkt!$C$43-cap_ts_25*(1-0)*sh_sk,0)*(1+g_oth_fd)^2)+Mkt!E50*(((cap_sk_27*1000/fx*sh_sk+cap_mu_27*sh_mu_27+cap_ss_27*1000/fx*sh_ss)+(((Mkt!$C$57-Mkt!$C$54+ind_cxmt)*sh_oth))*(1+g_oth_dram)^2+((Mkt!$C$61*sh_oth))*(1+g_oth_nand)^2)+(cap_ts_27*(1-0)*sh_sk+MAX(Mkt!$C$43-cap_ts_25*(1-0)*sh_sk,0)*(1+g_oth_fd)^2))+Mkt!E116+Mkt!E117 -> 212.15772 | E66: =((cap_sk_28*1000/fx*sh_sk+cap_mu_28*sh_mu_27+cap_ss_28*1000/fx*sh_ss)+(((Mkt!$C$57-Mkt!$C$54+ind_cxmt)*sh_oth))*(1+g_oth_dram)^3+((Mkt!$C$61*sh_oth))*(1+g_oth_nand)^3)+(cap_ts_28*(1-0)*sh_sk+MAX(Mkt!$C$43-cap_ts_25*(1-0)*sh_sk,0)*(1+g_oth_fd)^3)+Mkt!F50*(((cap_sk_28*1000/fx*sh_sk+cap_mu_28*sh_mu_27+cap_ss_28*1000/fx*sh_ss)+(((Mkt!$C$57-Mkt!$C$54+ind_cxmt)*sh_oth))*(1+g_oth_dram)^3+((Mkt!$C$61*sh_oth))*(1+g_oth_nand)^3)+(cap_ts_28*(1-0)*sh_sk+MAX(Mkt!$C$43-cap_ts_25*(1-0)*sh_sk,0)*(1+g_oth_fd)^3))+Mkt!F116+Mkt!F117 -> 238.05859 | F66: =((cap_sk_29*1000/fx*sh_sk+cap_mu_29*sh_mu_27+cap_ss_29*1000/fx*sh_ss)+(((Mkt!$C$57-Mkt!$C$54+ind_cxmt)*sh_oth))*(1+g_oth_dram)^4+((Mkt!$C$61*sh_oth))*(1+g_oth_nand)^4)+(cap_ts_29*(1-0)*sh_sk+MAX(Mkt!$C$43-cap_ts_25*(1-0)*sh_sk,0)*(1+g_oth_fd)^4)+Mkt!G50*(((cap_sk_29*1000/fx*sh_sk+cap_mu_29*sh_mu_27+cap_ss_29*1000/fx*sh_ss)+(((Mkt!$C$57-Mkt!$C$54+ind_cxmt)*sh_oth))*(1+g_oth_dram)^4+((Mkt!$C$61*sh_oth))*(1+g_oth_nand)^4)+(cap_ts_29*(1-0)*sh_sk+MAX(Mkt!$C$43-cap_ts_25*(1-0)*sh_sk,0)*(1+g_oth_fd)^4))+Mkt!G116+Mkt!G117 -> 252.50374 | G66: =IF(ROUND(F66,9)=ROUND(MAX(B66:F66),9),2029,IF(ROUND(E66,9)=ROUND(MAX(B66:F66),9),2028,IF(ROUND(D66,9)=ROUND(MAX(B66:F66),9),2027,IF(ROUND(C66,9)=ROUND(MAX(B66:F66),9),2026,2025)))) -> 2029
A67: 情境 B（台積電 45.5%（比照 SK、三星）） | B67: =((cap_sk_25*1000/fx*sh_sk+cap_mu_25*sh_mu_25+cap_ssds_25*ss_mem*1000/fx*sh_ss)+(((Mkt!$C$57-Mkt!$C$54+ind_cxmt)*sh_oth))*(1+g_oth_dram)^0+((Mkt!$C$61*sh_oth))*(1+g_oth_nand)^0)+(cap_ts_25*(1-0)*sh_sk+MAX(Mkt!$C$43-cap_ts_25*(1-0)*sh_sk,0)*(1+g_oth_fd)^0)+Mkt!C50*(((cap_sk_25*1000/fx*sh_sk+cap_mu_25*sh_mu_25+cap_ssds_25*ss_mem*1000/fx*sh_ss)+(((Mkt!$C$57-Mkt!$C$54+ind_cxmt)*sh_oth))*(1+g_oth_dram)^0+((Mkt!$C$61*sh_oth))*(1+g_oth_nand)^0)+(cap_ts_25*(1-0)*sh_sk+MAX(Mkt!$C$43-cap_ts_25*(1-0)*sh_sk,0)*(1+g_oth_fd)^0))+Mkt!C116+Mkt!C117 -> 134.68936 | C67: =((cap_sk_26*1000/fx*sh_sk+cap_mu_26*sh_mu_26+cap_ss_26*1000/fx*sh_ss)+(((Mkt!$C$57-Mkt!$C$54+ind_cxmt)*sh_oth))*(1+g_oth_dram)^1+((Mkt!$C$61*sh_oth))*(1+g_oth_nand)^1)+(cap_ts_26*(1-0)*sh_sk+MAX(Mkt!$C$43-cap_ts_25*(1-0)*sh_sk,0)*(1+g_oth_fd)^1)+Mkt!D50*(((cap_sk_26*1000/fx*sh_sk+cap_mu_26*sh_mu_26+cap_ss_26*1000/fx*sh_ss)+(((Mkt!$C$57-Mkt!$C$54+ind_cxmt)*sh_oth))*(1+g_oth_dram)^1+((Mkt!$C$61*sh_oth))*(1+g_oth_nand)^1)+(cap_ts_26*(1-0)*sh_sk+MAX(Mkt!$C$43-cap_ts_25*(1-0)*sh_sk,0)*(1+g_oth_fd)^1))+Mkt!D116+Mkt!D117 -> 174.46428 | D67: =((cap_sk_27*1000/fx*sh_sk+cap_mu_27*sh_mu_27+cap_ss_27*1000/fx*sh_ss)+(((Mkt!$C$57-Mkt!$C$54+ind_cxmt)*sh_oth))*(1+g_oth_dram)^2+((Mkt!$C$61*sh_oth))*(1+g_oth_nand)^2)+(cap_ts_27*(1-0)*sh_sk+MAX(Mkt!$C$43-cap_ts_25*(1-0)*sh_sk,0)*(1+g_oth_fd)^2)+Mkt!E50*(((cap_sk_27*1000/fx*sh_sk+cap_mu_27*sh_mu_27+cap_ss_27*1000/fx*sh_ss)+(((Mkt!$C$57-Mkt!$C$54+ind_cxmt)*sh_oth))*(1+g_oth_dram)^2+((Mkt!$C$61*sh_oth))*(1+g_oth_nand)^2)+(cap_ts_27*(1-0)*sh_sk+MAX(Mkt!$C$43-cap_ts_25*(1-0)*sh_sk,0)*(1+g_oth_fd)^2))+Mkt!E116+Mkt!E117 -> 212.15772 | E67: =D67*ck_B_28 -> 212.15772 | F67: =E67*ck_B_29 -> 201.54983 | G67: =IF(ROUND(F67,9)=ROUND(MAX(B67:F67),9),2029,IF(ROUND(E67,9)=ROUND(MAX(B67:F67),9),2028,IF(ROUND(D67,9)=ROUND(MAX(B67:F67),9),2027,IF(ROUND(C67,9)=ROUND(MAX(B67:F67),9),2026,2025)))) -> 2028
A68: 情境 C（台積電 45.5%（比照 SK、三星）） | B68: =((cap_sk_25*1000/fx*sh_sk+cap_mu_25*sh_mu_25+cap_ssds_25*ss_mem*1000/fx*sh_ss)+(((Mkt!$C$57-Mkt!$C$54+ind_cxmt)*sh_oth))*(1+g_oth_dram)^0+((Mkt!$C$61*sh_oth))*(1+g_oth_nand)^0)+(cap_ts_25*(1-0)*sh_sk+MAX(Mkt!$C$43-cap_ts_25*(1-0)*sh_sk,0)*(1+g_oth_fd)^0)+Mkt!C50*(((cap_sk_25*1000/fx*sh_sk+cap_mu_25*sh_mu_25+cap_ssds_25*ss_mem*1000/fx*sh_ss)+(((Mkt!$C$57-Mkt!$C$54+ind_cxmt)*sh_oth))*(1+g_oth_dram)^0+((Mkt!$C$61*sh_oth))*(1+g_oth_nand)^0)+(cap_ts_25*(1-0)*sh_sk+MAX(Mkt!$C$43-cap_ts_25*(1-0)*sh_sk,0)*(1+g_oth_fd)^0))+Mkt!C116+Mkt!C117 -> 134.68936 | C68: =((cap_sk_26*1000/fx*sh_sk+cap_mu_26*sh_mu_26+cap_ss_26*1000/fx*sh_ss)+(((Mkt!$C$57-Mkt!$C$54+ind_cxmt)*sh_oth))*(1+g_oth_dram)^1+((Mkt!$C$61*sh_oth))*(1+g_oth_nand)^1)+(cap_ts_26*(1-0)*sh_sk+MAX(Mkt!$C$43-cap_ts_25*(1-0)*sh_sk,0)*(1+g_oth_fd)^1)+Mkt!D50*(((cap_sk_26*1000/fx*sh_sk+cap_mu_26*sh_mu_26+cap_ss_26*1000/fx*sh_ss)+(((Mkt!$C$57-Mkt!$C$54+ind_cxmt)*sh_oth))*(1+g_oth_dram)^1+((Mkt!$C$61*sh_oth))*(1+g_oth_nand)^1)+(cap_ts_26*(1-0)*sh_sk+MAX(Mkt!$C$43-cap_ts_25*(1-0)*sh_sk,0)*(1+g_oth_fd)^1))+Mkt!D116+Mkt!D117 -> 174.46428 | D68: =((cap_sk_27*1000/fx*sh_sk+cap_mu_27*sh_mu_27+cap_ss_27*1000/fx*sh_ss)+(((Mkt!$C$57-Mkt!$C$54+ind_cxmt)*sh_oth))*(1+g_oth_dram)^2+((Mkt!$C$61*sh_oth))*(1+g_oth_nand)^2)+(cap_ts_27*(1-0)*sh_sk+MAX(Mkt!$C$43-cap_ts_25*(1-0)*sh_sk,0)*(1+g_oth_fd)^2)+Mkt!E50*(((cap_sk_27*1000/fx*sh_sk+cap_mu_27*sh_mu_27+cap_ss_27*1000/fx*sh_ss)+(((Mkt!$C$57-Mkt!$C$54+ind_cxmt)*sh_oth))*(1+g_oth_dram)^2+((Mkt!$C$61*sh_oth))*(1+g_oth_nand)^2)+(cap_ts_27*(1-0)*sh_sk+MAX(Mkt!$C$43-cap_ts_25*(1-0)*sh_sk,0)*(1+g_oth_fd)^2))+Mkt!E116+Mkt!E117 -> 212.15772 | E68: =D68*ck_C_28 -> 169.72618 | F68: =E68*ck_C_29 -> 169.72618 | G68: =IF(ROUND(F68,9)=ROUND(MAX(B68:F68),9),2029,IF(ROUND(E68,9)=ROUND(MAX(B68:F68),9),2028,IF(ROUND(D68,9)=ROUND(MAX(B68:F68),9),2027,IF(ROUND(C68,9)=ROUND(MAX(B68:F68),9),2026,2025)))) -> 2027
A69: 情境 A（台積電 基準 64% 並扣封裝／光罩 15%） | B69: =((cap_sk_25*1000/fx*sh_sk+cap_mu_25*sh_mu_25+cap_ssds_25*ss_mem*1000/fx*sh_ss)+(((Mkt!$C$57-Mkt!$C$54+ind_cxmt)*sh_oth))*(1+g_oth_dram)^0+((Mkt!$C$61*sh_oth))*(1+g_oth_nand)^0)+(cap_ts_25*(1-pk_ts)*sh_fd+MAX(Mkt!$C$43-cap_ts_25*(1-pk_ts)*sh_fd,0)*(1+g_oth_fd)^0)+Mkt!C50*(((cap_sk_25*1000/fx*sh_sk+cap_mu_25*sh_mu_25+cap_ssds_25*ss_mem*1000/fx*sh_ss)+(((Mkt!$C$57-Mkt!$C$54+ind_cxmt)*sh_oth))*(1+g_oth_dram)^0+((Mkt!$C$61*sh_oth))*(1+g_oth_nand)^0)+(cap_ts_25*(1-pk_ts)*sh_fd+MAX(Mkt!$C$43-cap_ts_25*(1-pk_ts)*sh_fd,0)*(1+g_oth_fd)^0))+Mkt!C116+Mkt!C117 -> 134.68936 | C69: =((cap_sk_26*1000/fx*sh_sk+cap_mu_26*sh_mu_26+cap_ss_26*1000/fx*sh_ss)+(((Mkt!$C$57-Mkt!$C$54+ind_cxmt)*sh_oth))*(1+g_oth_dram)^1+((Mkt!$C$61*sh_oth))*(1+g_oth_nand)^1)+(cap_ts_26*(1-pk_ts)*sh_fd+MAX(Mkt!$C$43-cap_ts_25*(1-pk_ts)*sh_fd,0)*(1+g_oth_fd)^1)+Mkt!D50*(((cap_sk_26*1000/fx*sh_sk+cap_mu_26*sh_mu_26+cap_ss_26*1000/fx*sh_ss)+(((Mkt!$C$57-Mkt!$C$54+ind_cxmt)*sh_oth))*(1+g_oth_dram)^1+((Mkt!$C$61*sh_oth))*(1+g_oth_nand)^1)+(cap_ts_26*(1-pk_ts)*sh_fd+MAX(Mkt!$C$43-cap_ts_25*(1-pk_ts)*sh_fd,0)*(1+g_oth_fd)^1))+Mkt!D116+Mkt!D117 -> 176.2361 | D69: =((cap_sk_27*1000/fx*sh_sk+cap_mu_27*sh_mu_27+cap_ss_27*1000/fx*sh_ss)+(((Mkt!$C$57-Mkt!$C$54+ind_cxmt)*sh_oth))*(1+g_oth_dram)^2+((Mkt!$C$61*sh_oth))*(1+g_oth_nand)^2)+(cap_ts_27*(1-pk_ts)*sh_fd+MAX(Mkt!$C$43-cap_ts_25*(1-pk_ts)*sh_fd,0)*(1+g_oth_fd)^2)+Mkt!E50*(((cap_sk_27*1000/fx*sh_sk+cap_mu_27*sh_mu_27+cap_ss_27*1000/fx*sh_ss)+(((Mkt!$C$57-Mkt!$C$54+ind_cxmt)*sh_oth))*(1+g_oth_dram)^2+((Mkt!$C$61*sh_oth))*(1+g_oth_nand)^2)+(cap_ts_27*(1-pk_ts)*sh_fd+MAX(Mkt!$C$43-cap_ts_25*(1-pk_ts)*sh_fd,0)*(1+g_oth_fd)^2))+Mkt!E116+Mkt!E117 -> 215.0691 | E69: =((cap_sk_28*1000/fx*sh_sk+cap_mu_28*sh_mu_27+cap_ss_28*1000/fx*sh_ss)+(((Mkt!$C$57-Mkt!$C$54+ind_cxmt)*sh_oth))*(1+g_oth_dram)^3+((Mkt!$C$61*sh_oth))*(1+g_oth_nand)^3)+(cap_ts_28*(1-pk_ts)*sh_fd+MAX(Mkt!$C$43-cap_ts_25*(1-pk_ts)*sh_fd,0)*(1+g_oth_fd)^3)+Mkt!F50*(((cap_sk_28*1000/fx*sh_sk+cap_mu_28*sh_mu_27+cap_ss_28*1000/fx*sh_ss)+(((Mkt!$C$57-Mkt!$C$54+ind_cxmt)*sh_oth))*(1+g_oth_dram)^3+((Mkt!$C$61*sh_oth))*(1+g_oth_nand)^3)+(cap_ts_28*(1-pk_ts)*sh_fd+MAX(Mkt!$C$43-cap_ts_25*(1-pk_ts)*sh_fd,0)*(1+g_oth_fd)^3))+Mkt!F116+Mkt!F117 -> 241.88267 | F69: =((cap_sk_29*1000/fx*sh_sk+cap_mu_29*sh_mu_27+cap_ss_29*1000/fx*sh_ss)+(((Mkt!$C$57-Mkt!$C$54+ind_cxmt)*sh_oth))*(1+g_oth_dram)^4+((Mkt!$C$61*sh_oth))*(1+g_oth_nand)^4)+(cap_ts_29*(1-pk_ts)*sh_fd+MAX(Mkt!$C$43-cap_ts_25*(1-pk_ts)*sh_fd,0)*(1+g_oth_fd)^4)+Mkt!G50*(((cap_sk_29*1000/fx*sh_sk+cap_mu_29*sh_mu_27+cap_ss_29*1000/fx*sh_ss)+(((Mkt!$C$57-Mkt!$C$54+ind_cxmt)*sh_oth))*(1+g_oth_dram)^4+((Mkt!$C$61*sh_oth))*(1+g_oth_nand)^4)+(cap_ts_29*(1-pk_ts)*sh_fd+MAX(Mkt!$C$43-cap_ts_25*(1-pk_ts)*sh_fd,0)*(1+g_oth_fd)^4))+Mkt!G116+Mkt!G117 -> 256.4151 | G69: =IF(ROUND(F69,9)=ROUND(MAX(B69:F69),9),2029,IF(ROUND(E69,9)=ROUND(MAX(B69:F69),9),2028,IF(ROUND(D69,9)=ROUND(MAX(B69:F69),9),2027,IF(ROUND(C69,9)=ROUND(MAX(B69:F69),9),2026,2025)))) -> 2029
A70: 情境 B（台積電 基準 64% 並扣封裝／光罩 15%） | B70: =((cap_sk_25*1000/fx*sh_sk+cap_mu_25*sh_mu_25+cap_ssds_25*ss_mem*1000/fx*sh_ss)+(((Mkt!$C$57-Mkt!$C$54+ind_cxmt)*sh_oth))*(1+g_oth_dram)^0+((Mkt!$C$61*sh_oth))*(1+g_oth_nand)^0)+(cap_ts_25*(1-pk_ts)*sh_fd+MAX(Mkt!$C$43-cap_ts_25*(1-pk_ts)*sh_fd,0)*(1+g_oth_fd)^0)+Mkt!C50*(((cap_sk_25*1000/fx*sh_sk+cap_mu_25*sh_mu_25+cap_ssds_25*ss_mem*1000/fx*sh_ss)+(((Mkt!$C$57-Mkt!$C$54+ind_cxmt)*sh_oth))*(1+g_oth_dram)^0+((Mkt!$C$61*sh_oth))*(1+g_oth_nand)^0)+(cap_ts_25*(1-pk_ts)*sh_fd+MAX(Mkt!$C$43-cap_ts_25*(1-pk_ts)*sh_fd,0)*(1+g_oth_fd)^0))+Mkt!C116+Mkt!C117 -> 134.68936 | C70: =((cap_sk_26*1000/fx*sh_sk+cap_mu_26*sh_mu_26+cap_ss_26*1000/fx*sh_ss)+(((Mkt!$C$57-Mkt!$C$54+ind_cxmt)*sh_oth))*(1+g_oth_dram)^1+((Mkt!$C$61*sh_oth))*(1+g_oth_nand)^1)+(cap_ts_26*(1-pk_ts)*sh_fd+MAX(Mkt!$C$43-cap_ts_25*(1-pk_ts)*sh_fd,0)*(1+g_oth_fd)^1)+Mkt!D50*(((cap_sk_26*1000/fx*sh_sk+cap_mu_26*sh_mu_26+cap_ss_26*1000/fx*sh_ss)+(((Mkt!$C$57-Mkt!$C$54+ind_cxmt)*sh_oth))*(1+g_oth_dram)^1+((Mkt!$C$61*sh_oth))*(1+g_oth_nand)^1)+(cap_ts_26*(1-pk_ts)*sh_fd+MAX(Mkt!$C$43-cap_ts_25*(1-pk_ts)*sh_fd,0)*(1+g_oth_fd)^1))+Mkt!D116+Mkt!D117 -> 176.2361 | D70: =((cap_sk_27*1000/fx*sh_sk+cap_mu_27*sh_mu_27+cap_ss_27*1000/fx*sh_ss)+(((Mkt!$C$57-Mkt!$C$54+ind_cxmt)*sh_oth))*(1+g_oth_dram)^2+((Mkt!$C$61*sh_oth))*(1+g_oth_nand)^2)+(cap_ts_27*(1-pk_ts)*sh_fd+MAX(Mkt!$C$43-cap_ts_25*(1-pk_ts)*sh_fd,0)*(1+g_oth_fd)^2)+Mkt!E50*(((cap_sk_27*1000/fx*sh_sk+cap_mu_27*sh_mu_27+cap_ss_27*1000/fx*sh_ss)+(((Mkt!$C$57-Mkt!$C$54+ind_cxmt)*sh_oth))*(1+g_oth_dram)^2+((Mkt!$C$61*sh_oth))*(1+g_oth_nand)^2)+(cap_ts_27*(1-pk_ts)*sh_fd+MAX(Mkt!$C$43-cap_ts_25*(1-pk_ts)*sh_fd,0)*(1+g_oth_fd)^2))+Mkt!E116+Mkt!E117 -> 215.0691 | E70: =D70*ck_B_28 -> 215.0691 | F70: =E70*ck_B_29 -> 204.31565 | G70: =IF(ROUND(F70,9)=ROUND(MAX(B70:F70),9),2029,IF(ROUND(E70,9)=ROUND(MAX(B70:F70),9),2028,IF(ROUND(D70,9)=ROUND(MAX(B70:F70),9),2027,IF(ROUND(C70,9)=ROUND(MAX(B70:F70),9),2026,2025)))) -> 2028
A71: 情境 C（台積電 基準 64% 並扣封裝／光罩 15%） | B71: =((cap_sk_25*1000/fx*sh_sk+cap_mu_25*sh_mu_25+cap_ssds_25*ss_mem*1000/fx*sh_ss)+(((Mkt!$C$57-Mkt!$C$54+ind_cxmt)*sh_oth))*(1+g_oth_dram)^0+((Mkt!$C$61*sh_oth))*(1+g_oth_nand)^0)+(cap_ts_25*(1-pk_ts)*sh_fd+MAX(Mkt!$C$43-cap_ts_25*(1-pk_ts)*sh_fd,0)*(1+g_oth_fd)^0)+Mkt!C50*(((cap_sk_25*1000/fx*sh_sk+cap_mu_25*sh_mu_25+cap_ssds_25*ss_mem*1000/fx*sh_ss)+(((Mkt!$C$57-Mkt!$C$54+ind_cxmt)*sh_oth))*(1+g_oth_dram)^0+((Mkt!$C$61*sh_oth))*(1+g_oth_nand)^0)+(cap_ts_25*(1-pk_ts)*sh_fd+MAX(Mkt!$C$43-cap_ts_25*(1-pk_ts)*sh_fd,0)*(1+g_oth_fd)^0))+Mkt!C116+Mkt!C117 -> 134.68936 | C71: =((cap_sk_26*1000/fx*sh_sk+cap_mu_26*sh_mu_26+cap_ss_26*1000/fx*sh_ss)+(((Mkt!$C$57-Mkt!$C$54+ind_cxmt)*sh_oth))*(1+g_oth_dram)^1+((Mkt!$C$61*sh_oth))*(1+g_oth_nand)^1)+(cap_ts_26*(1-pk_ts)*sh_fd+MAX(Mkt!$C$43-cap_ts_25*(1-pk_ts)*sh_fd,0)*(1+g_oth_fd)^1)+Mkt!D50*(((cap_sk_26*1000/fx*sh_sk+cap_mu_26*sh_mu_26+cap_ss_26*1000/fx*sh_ss)+(((Mkt!$C$57-Mkt!$C$54+ind_cxmt)*sh_oth))*(1+g_oth_dram)^1+((Mkt!$C$61*sh_oth))*(1+g_oth_nand)^1)+(cap_ts_26*(1-pk_ts)*sh_fd+MAX(Mkt!$C$43-cap_ts_25*(1-pk_ts)*sh_fd,0)*(1+g_oth_fd)^1))+Mkt!D116+Mkt!D117 -> 176.2361 | D71: =((cap_sk_27*1000/fx*sh_sk+cap_mu_27*sh_mu_27+cap_ss_27*1000/fx*sh_ss)+(((Mkt!$C$57-Mkt!$C$54+ind_cxmt)*sh_oth))*(1+g_oth_dram)^2+((Mkt!$C$61*sh_oth))*(1+g_oth_nand)^2)+(cap_ts_27*(1-pk_ts)*sh_fd+MAX(Mkt!$C$43-cap_ts_25*(1-pk_ts)*sh_fd,0)*(1+g_oth_fd)^2)+Mkt!E50*(((cap_sk_27*1000/fx*sh_sk+cap_mu_27*sh_mu_27+cap_ss_27*1000/fx*sh_ss)+(((Mkt!$C$57-Mkt!$C$54+ind_cxmt)*sh_oth))*(1+g_oth_dram)^2+((Mkt!$C$61*sh_oth))*(1+g_oth_nand)^2)+(cap_ts_27*(1-pk_ts)*sh_fd+MAX(Mkt!$C$43-cap_ts_25*(1-pk_ts)*sh_fd,0)*(1+g_oth_fd)^2))+Mkt!E116+Mkt!E117 -> 215.0691 | E71: =D71*ck_C_28 -> 172.05528 | F71: =E71*ck_C_29 -> 172.05528 | G71: =IF(ROUND(F71,9)=ROUND(MAX(B71:F71),9),2029,IF(ROUND(E71,9)=ROUND(MAX(B71:F71),9),2028,IF(ROUND(D71,9)=ROUND(MAX(B71:F71),9),2027,IF(ROUND(C71,9)=ROUND(MAX(B71:F71),9),2026,2025)))) -> 2027
A72: 情境 A（台積電 基準 64% 並扣 20%（上限）） | B72: =((cap_sk_25*1000/fx*sh_sk+cap_mu_25*sh_mu_25+cap_ssds_25*ss_mem*1000/fx*sh_ss)+(((Mkt!$C$57-Mkt!$C$54+ind_cxmt)*sh_oth))*(1+g_oth_dram)^0+((Mkt!$C$61*sh_oth))*(1+g_oth_nand)^0)+(cap_ts_25*(1-pk_ts_hi)*sh_fd+MAX(Mkt!$C$43-cap_ts_25*(1-pk_ts_hi)*sh_fd,0)*(1+g_oth_fd)^0)+Mkt!C50*(((cap_sk_25*1000/fx*sh_sk+cap_mu_25*sh_mu_25+cap_ssds_25*ss_mem*1000/fx*sh_ss)+(((Mkt!$C$57-Mkt!$C$54+ind_cxmt)*sh_oth))*(1+g_oth_dram)^0+((Mkt!$C$61*sh_oth))*(1+g_oth_nand)^0)+(cap_ts_25*(1-pk_ts_hi)*sh_fd+MAX(Mkt!$C$43-cap_ts_25*(1-pk_ts_hi)*sh_fd,0)*(1+g_oth_fd)^0))+Mkt!C116+Mkt!C117 -> 134.68936 | C72: =((cap_sk_26*1000/fx*sh_sk+cap_mu_26*sh_mu_26+cap_ss_26*1000/fx*sh_ss)+(((Mkt!$C$57-Mkt!$C$54+ind_cxmt)*sh_oth))*(1+g_oth_dram)^1+((Mkt!$C$61*sh_oth))*(1+g_oth_nand)^1)+(cap_ts_26*(1-pk_ts_hi)*sh_fd+MAX(Mkt!$C$43-cap_ts_25*(1-pk_ts_hi)*sh_fd,0)*(1+g_oth_fd)^1)+Mkt!D50*(((cap_sk_26*1000/fx*sh_sk+cap_mu_26*sh_mu_26+cap_ss_26*1000/fx*sh_ss)+(((Mkt!$C$57-Mkt!$C$54+ind_cxmt)*sh_oth))*(1+g_oth_dram)^1+((Mkt!$C$61*sh_oth))*(1+g_oth_nand)^1)+(cap_ts_26*(1-pk_ts_hi)*sh_fd+MAX(Mkt!$C$43-cap_ts_25*(1-pk_ts_hi)*sh_fd,0)*(1+g_oth_fd)^1))+Mkt!D116+Mkt!D117 -> 175.59578 | D72: =((cap_sk_27*1000/fx*sh_sk+cap_mu_27*sh_mu_27+cap_ss_27*1000/fx*sh_ss)+(((Mkt!$C$57-Mkt!$C$54+ind_cxmt)*sh_oth))*(1+g_oth_dram)^2+((Mkt!$C$61*sh_oth))*(1+g_oth_nand)^2)+(cap_ts_27*(1-pk_ts_hi)*sh_fd+MAX(Mkt!$C$43-cap_ts_25*(1-pk_ts_hi)*sh_fd,0)*(1+g_oth_fd)^2)+Mkt!E50*(((cap_sk_27*1000/fx*sh_sk+cap_mu_27*sh_mu_27+cap_ss_27*1000/fx*sh_ss)+(((Mkt!$C$57-Mkt!$C$54+ind_cxmt)*sh_oth))*(1+g_oth_dram)^2+((Mkt!$C$61*sh_oth))*(1+g_oth_nand)^2)+(cap_ts_27*(1-pk_ts_hi)*sh_fd+MAX(Mkt!$C$43-cap_ts_25*(1-pk_ts_hi)*sh_fd,0)*(1+g_oth_fd)^2))+Mkt!E116+Mkt!E117 -> 214.01696 | E72: =((cap_sk_28*1000/fx*sh_sk+cap_mu_28*sh_mu_27+cap_ss_28*1000/fx*sh_ss)+(((Mkt!$C$57-Mkt!$C$54+ind_cxmt)*sh_oth))*(1+g_oth_dram)^3+((Mkt!$C$61*sh_oth))*(1+g_oth_nand)^3)+(cap_ts_28*(1-pk_ts_hi)*sh_fd+MAX(Mkt!$C$43-cap_ts_25*(1-pk_ts_hi)*sh_fd,0)*(1+g_oth_fd)^3)+Mkt!F50*(((cap_sk_28*1000/fx*sh_sk+cap_mu_28*sh_mu_27+cap_ss_28*1000/fx*sh_ss)+(((Mkt!$C$57-Mkt!$C$54+ind_cxmt)*sh_oth))*(1+g_oth_dram)^3+((Mkt!$C$61*sh_oth))*(1+g_oth_nand)^3)+(cap_ts_28*(1-pk_ts_hi)*sh_fd+MAX(Mkt!$C$43-cap_ts_25*(1-pk_ts_hi)*sh_fd,0)*(1+g_oth_fd)^3))+Mkt!F116+Mkt!F117 -> 240.50069 | F72: =((cap_sk_29*1000/fx*sh_sk+cap_mu_29*sh_mu_27+cap_ss_29*1000/fx*sh_ss)+(((Mkt!$C$57-Mkt!$C$54+ind_cxmt)*sh_oth))*(1+g_oth_dram)^4+((Mkt!$C$61*sh_oth))*(1+g_oth_nand)^4)+(cap_ts_29*(1-pk_ts_hi)*sh_fd+MAX(Mkt!$C$43-cap_ts_25*(1-pk_ts_hi)*sh_fd,0)*(1+g_oth_fd)^4)+Mkt!G50*(((cap_sk_29*1000/fx*sh_sk+cap_mu_29*sh_mu_27+cap_ss_29*1000/fx*sh_ss)+(((Mkt!$C$57-Mkt!$C$54+ind_cxmt)*sh_oth))*(1+g_oth_dram)^4+((Mkt!$C$61*sh_oth))*(1+g_oth_nand)^4)+(cap_ts_29*(1-pk_ts_hi)*sh_fd+MAX(Mkt!$C$43-cap_ts_25*(1-pk_ts_hi)*sh_fd,0)*(1+g_oth_fd)^4))+Mkt!G116+Mkt!G117 -> 255.00158 | G72: =IF(ROUND(F72,9)=ROUND(MAX(B72:F72),9),2029,IF(ROUND(E72,9)=ROUND(MAX(B72:F72),9),2028,IF(ROUND(D72,9)=ROUND(MAX(B72:F72),9),2027,IF(ROUND(C72,9)=ROUND(MAX(B72:F72),9),2026,2025)))) -> 2029
A73: 情境 B（台積電 基準 64% 並扣 20%（上限）） | B73: =((cap_sk_25*1000/fx*sh_sk+cap_mu_25*sh_mu_25+cap_ssds_25*ss_mem*1000/fx*sh_ss)+(((Mkt!$C$57-Mkt!$C$54+ind_cxmt)*sh_oth))*(1+g_oth_dram)^0+((Mkt!$C$61*sh_oth))*(1+g_oth_nand)^0)+(cap_ts_25*(1-pk_ts_hi)*sh_fd+MAX(Mkt!$C$43-cap_ts_25*(1-pk_ts_hi)*sh_fd,0)*(1+g_oth_fd)^0)+Mkt!C50*(((cap_sk_25*1000/fx*sh_sk+cap_mu_25*sh_mu_25+cap_ssds_25*ss_mem*1000/fx*sh_ss)+(((Mkt!$C$57-Mkt!$C$54+ind_cxmt)*sh_oth))*(1+g_oth_dram)^0+((Mkt!$C$61*sh_oth))*(1+g_oth_nand)^0)+(cap_ts_25*(1-pk_ts_hi)*sh_fd+MAX(Mkt!$C$43-cap_ts_25*(1-pk_ts_hi)*sh_fd,0)*(1+g_oth_fd)^0))+Mkt!C116+Mkt!C117 -> 134.68936 | C73: =((cap_sk_26*1000/fx*sh_sk+cap_mu_26*sh_mu_26+cap_ss_26*1000/fx*sh_ss)+(((Mkt!$C$57-Mkt!$C$54+ind_cxmt)*sh_oth))*(1+g_oth_dram)^1+((Mkt!$C$61*sh_oth))*(1+g_oth_nand)^1)+(cap_ts_26*(1-pk_ts_hi)*sh_fd+MAX(Mkt!$C$43-cap_ts_25*(1-pk_ts_hi)*sh_fd,0)*(1+g_oth_fd)^1)+Mkt!D50*(((cap_sk_26*1000/fx*sh_sk+cap_mu_26*sh_mu_26+cap_ss_26*1000/fx*sh_ss)+(((Mkt!$C$57-Mkt!$C$54+ind_cxmt)*sh_oth))*(1+g_oth_dram)^1+((Mkt!$C$61*sh_oth))*(1+g_oth_nand)^1)+(cap_ts_26*(1-pk_ts_hi)*sh_fd+MAX(Mkt!$C$43-cap_ts_25*(1-pk_ts_hi)*sh_fd,0)*(1+g_oth_fd)^1))+Mkt!D116+Mkt!D117 -> 175.59578 | D73: =((cap_sk_27*1000/fx*sh_sk+cap_mu_27*sh_mu_27+cap_ss_27*1000/fx*sh_ss)+(((Mkt!$C$57-Mkt!$C$54+ind_cxmt)*sh_oth))*(1+g_oth_dram)^2+((Mkt!$C$61*sh_oth))*(1+g_oth_nand)^2)+(cap_ts_27*(1-pk_ts_hi)*sh_fd+MAX(Mkt!$C$43-cap_ts_25*(1-pk_ts_hi)*sh_fd,0)*(1+g_oth_fd)^2)+Mkt!E50*(((cap_sk_27*1000/fx*sh_sk+cap_mu_27*sh_mu_27+cap_ss_27*1000/fx*sh_ss)+(((Mkt!$C$57-Mkt!$C$54+ind_cxmt)*sh_oth))*(1+g_oth_dram)^2+((Mkt!$C$61*sh_oth))*(1+g_oth_nand)^2)+(cap_ts_27*(1-pk_ts_hi)*sh_fd+MAX(Mkt!$C$43-cap_ts_25*(1-pk_ts_hi)*sh_fd,0)*(1+g_oth_fd)^2))+Mkt!E116+Mkt!E117 -> 214.01696 | E73: =D73*ck_B_28 -> 214.01696 | F73: =E73*ck_B_29 -> 203.31611 | G73: =IF(ROUND(F73,9)=ROUND(MAX(B73:F73),9),2029,IF(ROUND(E73,9)=ROUND(MAX(B73:F73),9),2028,IF(ROUND(D73,9)=ROUND(MAX(B73:F73),9),2027,IF(ROUND(C73,9)=ROUND(MAX(B73:F73),9),2026,2025)))) -> 2028
A74: 情境 C（台積電 基準 64% 並扣 20%（上限）） | B74: =((cap_sk_25*1000/fx*sh_sk+cap_mu_25*sh_mu_25+cap_ssds_25*ss_mem*1000/fx*sh_ss)+(((Mkt!$C$57-Mkt!$C$54+ind_cxmt)*sh_oth))*(1+g_oth_dram)^0+((Mkt!$C$61*sh_oth))*(1+g_oth_nand)^0)+(cap_ts_25*(1-pk_ts_hi)*sh_fd+MAX(Mkt!$C$43-cap_ts_25*(1-pk_ts_hi)*sh_fd,0)*(1+g_oth_fd)^0)+Mkt!C50*(((cap_sk_25*1000/fx*sh_sk+cap_mu_25*sh_mu_25+cap_ssds_25*ss_mem*1000/fx*sh_ss)+(((Mkt!$C$57-Mkt!$C$54+ind_cxmt)*sh_oth))*(1+g_oth_dram)^0+((Mkt!$C$61*sh_oth))*(1+g_oth_nand)^0)+(cap_ts_25*(1-pk_ts_hi)*sh_fd+MAX(Mkt!$C$43-cap_ts_25*(1-pk_ts_hi)*sh_fd,0)*(1+g_oth_fd)^0))+Mkt!C116+Mkt!C117 -> 134.68936 | C74: =((cap_sk_26*1000/fx*sh_sk+cap_mu_26*sh_mu_26+cap_ss_26*1000/fx*sh_ss)+(((Mkt!$C$57-Mkt!$C$54+ind_cxmt)*sh_oth))*(1+g_oth_dram)^1+((Mkt!$C$61*sh_oth))*(1+g_oth_nand)^1)+(cap_ts_26*(1-pk_ts_hi)*sh_fd+MAX(Mkt!$C$43-cap_ts_25*(1-pk_ts_hi)*sh_fd,0)*(1+g_oth_fd)^1)+Mkt!D50*(((cap_sk_26*1000/fx*sh_sk+cap_mu_26*sh_mu_26+cap_ss_26*1000/fx*sh_ss)+(((Mkt!$C$57-Mkt!$C$54+ind_cxmt)*sh_oth))*(1+g_oth_dram)^1+((Mkt!$C$61*sh_oth))*(1+g_oth_nand)^1)+(cap_ts_26*(1-pk_ts_hi)*sh_fd+MAX(Mkt!$C$43-cap_ts_25*(1-pk_ts_hi)*sh_fd,0)*(1+g_oth_fd)^1))+Mkt!D116+Mkt!D117 -> 175.59578 | D74: =((cap_sk_27*1000/fx*sh_sk+cap_mu_27*sh_mu_27+cap_ss_27*1000/fx*sh_ss)+(((Mkt!$C$57-Mkt!$C$54+ind_cxmt)*sh_oth))*(1+g_oth_dram)^2+((Mkt!$C$61*sh_oth))*(1+g_oth_nand)^2)+(cap_ts_27*(1-pk_ts_hi)*sh_fd+MAX(Mkt!$C$43-cap_ts_25*(1-pk_ts_hi)*sh_fd,0)*(1+g_oth_fd)^2)+Mkt!E50*(((cap_sk_27*1000/fx*sh_sk+cap_mu_27*sh_mu_27+cap_ss_27*1000/fx*sh_ss)+(((Mkt!$C$57-Mkt!$C$54+ind_cxmt)*sh_oth))*(1+g_oth_dram)^2+((Mkt!$C$61*sh_oth))*(1+g_oth_nand)^2)+(cap_ts_27*(1-pk_ts_hi)*sh_fd+MAX(Mkt!$C$43-cap_ts_25*(1-pk_ts_hi)*sh_fd,0)*(1+g_oth_fd)^2))+Mkt!E116+Mkt!E117 -> 214.01696 | E74: =D74*ck_C_28 -> 171.21357 | F74: =E74*ck_C_29 -> 171.21357 | G74: =IF(ROUND(F74,9)=ROUND(MAX(B74:F74),9),2029,IF(ROUND(E74,9)=ROUND(MAX(B74:F74),9),2028,IF(ROUND(D74,9)=ROUND(MAX(B74:F74),9),2027,IF(ROUND(C74,9)=ROUND(MAX(B74:F74),9),2026,2025)))) -> 2027
A75: 相對基準 64%：情境 A（50%（低）） | B75: =B60/B57-1 -> 0 | C75: =C60/C57-1 -> -0.015724284 | D75: =D60/D57-1 -> -0.021093465 | E75: =E60/E57-1 -> -0.024575119 | F75: =F60/F57-1 -> -0.023725481
A76: 相對基準 64%：情境 B（50%（低）） | B76: =B61/B58-1 -> 0 | C76: =C61/C58-1 -> -0.015724284 | D76: =D61/D58-1 -> -0.021093465 | E76: =E61/E58-1 -> -0.021093465 | F76: =F61/F58-1 -> -0.021093465
A77: 相對基準 64%：情境 C（50%（低）） | B77: =B62/B59-1 -> 0 | C77: =C62/C59-1 -> -0.015724284 | D77: =D62/D59-1 -> -0.021093465 | E77: =E62/E59-1 -> -0.021093465 | F77: =F62/F59-1 -> -0.021093465
A78: 相對基準 64%：情境 A（75%（高）） | B78: =B63/B57-1 -> 0 | C78: =C63/C57-1 -> 0.012354795 | D78: =D63/D57-1 -> 0.016573437 | E78: =E63/E57-1 -> 0.019309022 | F78: =F63/F57-1 -> 0.01864145
A79: 相對基準 64%：情境 B（75%（高）） | B79: =B64/B58-1 -> 0 | C79: =C64/C58-1 -> 0.012354795 | D79: =D64/D58-1 -> 0.016573437 | E79: =E64/E58-1 -> 0.016573437 | F79: =F64/F58-1 -> 0.016573437
A80: 相對基準 64%：情境 C（75%（高）） | B80: =B65/B59-1 -> 0 | C80: =C65/C59-1 -> 0.012354795 | D80: =D65/D59-1 -> 0.016573437 | E80: =E65/E59-1 -> 0.016573437 | F80: =F65/F59-1 -> 0.016573437
A81: 相對基準 64%：情境 A（45.5%（比照 SK、三星）） | B81: =B66/B57-1 -> 0 | C81: =C66/C57-1 -> -0.020727638 | D81: =D66/D57-1 -> -0.027805255 | E81: =E66/E57-1 -> -0.032394745 | F81: =F66/F57-1 -> -0.031274759
A82: 相對基準 64%：情境 B（45.5%（比照 SK、三星）） | B82: =B67/B58-1 -> 0 | C82: =C67/C58-1 -> -0.020727638 | D82: =D67/D58-1 -> -0.027805255 | E82: =E67/E58-1 -> -0.027805255 | F82: =F67/F58-1 -> -0.027805255
A83: 相對基準 64%：情境 C（45.5%（比照 SK、三星）） | B83: =B68/B59-1 -> 0 | C83: =C68/C59-1 -> -0.020727638 | D83: =D68/D59-1 -> -0.027805255 | E83: =E68/E59-1 -> -0.027805255 | F83: =F68/F59-1 -> -0.027805255
A84: 相對基準 64%：情境 A（基準 64% 並扣封裝／光罩 15%） | B84: =B69/B57-1 -> 0 | C84: =C69/C57-1 -> -0.010782366 | D84: =D69/D57-1 -> -0.01446409 | E84: =E69/E57-1 -> -0.01685151 | F84: =F69/F57-1 -> -0.016268901
A85: 相對基準 64%：情境 B（基準 64% 並扣封裝／光罩 15%） | B85: =B70/B58-1 -> 0 | C85: =C70/C58-1 -> -0.010782366 | D85: =D70/D58-1 -> -0.01446409 | E85: =E70/E58-1 -> -0.01446409 | F85: =F70/F58-1 -> -0.01446409
A86: 相對基準 64%：情境 C（基準 64% 並扣封裝／光罩 15%） | B86: =B71/B59-1 -> 0 | C86: =C71/C59-1 -> -0.010782366 | D86: =D71/D59-1 -> -0.01446409 | E86: =E71/E59-1 -> -0.01446409 | F86: =F71/F59-1 -> -0.01446409
A87: 相對基準 64%：情境 A（基準 64% 並扣 20%（上限）） | B87: =B72/B57-1 -> 0 | C87: =C72/C57-1 -> -0.014376488 | D87: =D72/D57-1 -> -0.019285454 | E87: =E72/E57-1 -> -0.02246868 | F87: =F72/F57-1 -> -0.021691869
A88: 相對基準 64%：情境 B（基準 64% 並扣 20%（上限）） | B88: =B73/B58-1 -> 0 | C88: =C73/C58-1 -> -0.014376488 | D88: =D73/D58-1 -> -0.019285454 | E88: =E73/E58-1 -> -0.019285454 | F88: =F73/F58-1 -> -0.019285454
A89: 相對基準 64%：情境 C（基準 64% 並扣 20%（上限）） | B89: =B74/B59-1 -> 0 | C89: =C74/C59-1 -> -0.014376488 | D89: =D74/D59-1 -> -0.019285454 | E89: =E74/E59-1 -> -0.019285454 | F89: =F74/F59-1 -> -0.019285454
A90: 說明：2025 因代工邏輯由 SEMI 殘差補平，台積電占比不影響 2025 總額；2026 年以後台積電資本支出成長（+52%）遠高於其他廠（+8%，Assumed），占比降低使總額下降。見頂年度由情境係數決定，不受台積電占比影響（三情境見頂年度與基準相同，見 G 欄）。
A92: 說明：業界值 64% 下 2025 本模型總額高於 SEMI 實績（三家 64% 加上其他廠獨立估計超過 SEMI）；校準值使 2025 恰等於 SEMI 實績。單因子列中未標「重新校準」者，校準值固定不變。

Sheet Sources
A1: 來源
A2: 來源 | B2: 網址／位置 | C2: 用途 | D2: 證據強度
A3: SEMI 年中設備預測新聞稿 2026-07-14 | B3: https://www.semi.org/en/semi-press-release/global-semiconductor-equipment-sales-forecast-to-reach-a-record-229-billion-dollars-in-2028-semi-reports | C3: 2026–2028 設備金額、年增 | D3: 中（一手但協會有立場；分項年增取自搜尋摘要，未能直接開啟全文）
A4: SEMI 新聞稿轉載（PR Newswire） | B4: https://www.prnewswire.co.uk/news-releases/global-semiconductor-equipment-sales-forecast-to-reach-a-record-229-billion-in-2028-semi-reports-302824214.html | C4: 同上第二來源（非獨立） | D4: 中
A5: Semiconductor Digest 轉載 | B5: https://www.semiconductor-digest.com/global-semiconductor-equipment-sales-forecast-to-reach-a-record-229-billion-in-2028-semi-reports/ | C5: 同上 | D5: 中
A6: Semiconductor Intelligence：CapEx Up for Foundry, Memory | B6: https://www.semiconductorintelligence.com/capex-up-for-foundry-memory/ | C6: 2025 全球半導體資本支出 166B、台積電 40.9B | D6: 中
A7: Rebound Capital：WFE 產業深度 | B7: https://reboundcapital.substack.com/p/industry-deep-dive-semiconductor | C7: 資本支出→WFE 轉換率約 58% | D7: 弱（Substack）
A8: SK 海力士、美光、三星、台積電模型 dist 成品 | B8: skhynix／micron／samsung／tsmc 的 dist/*.xlsx（Y 或 PL 頁「資本支出」列） | C8: 公司資本支出 | D8: 各模型 In 頁標記
A9: Qz：SK 海力士 2Q26（2025 資本支出 30.2 兆） | B9: https://qz.com/sk-hynix-q2-2026-earnings-record-profit-misses-estimates-072926 | C9: SK 海力士 2025 資本支出 | D9: 弱～中（摘要）
A10: MLQ：SK 海力士 2Q26 | B10: https://mlq.ai/news/sk-hynix-posts-record-605-trillion-won-operating-profit-raises-capacity-spending/ | C10: 同上第二來源 | D10: 弱～中
A11: 三星 IR：FY2025 CAPEX Results | B11: https://www.samsung.com/global/ir/reports-disclosures/public-disclosure-view.84547/ | C11: DS 2025 資本支出 47.5 兆 | D11: 強（公司一手；頁面日期與內文不一致，需核對）
A12: 美光 FY25 8-K／10-K | B12: https://www.sec.gov/Archives/edgar/data/723125/000072312525000024/a2025q4ex991-pressrelease.htm | C12: FY25 淨資本支出 13.80 | D12: 強
A13: TrendForce：鎧俠 FY26–28 資本支出 | B13: https://www.trendforce.com/news/2026/06/03/news-kioxia-targets-%C2%A5470b-yearly-capex-in-fy26-28-up-66-from-fy25-reportedly-weighing-third-kitakami-fab-and-ma/ | C13: 其他 NAND 廠成長率 | D13: 中
... A36: Intel 4Q25 法說摘要（Yahoo Finance） | B36: https://finance.yahoo.com/news/intel-q4-earnings-call-highlights-234233695.html | C36: Intel 2025 資本支出毛額 17.7、扣抵 6.5（TSMC 頁可識別性檢查） | D36: 中（摘要）
