Workbook

Sheet README
A1: Arista Networks（ANET）收支與估值模型 v0.2（AI 半導體 Project：網通系統端樣板） 2026-10-25
A2: 版本：v0.1（初版）。Arista 在 AI 後端乙太網路交換器的份額在本模型 Units 頁建立，為本專案權威資料（規則第 13 條）。
A3: 模型命題：Arista 的 AI 營收＝AI 後端 scale-out 交換器市場（本專案網通模型）× 乙太網路占比 × Arista 份額（含前端與 scale-across 附掛）；非 AI（雲端前端、企業、園區）另依成長率推。股價約 37 倍前瞻 EPS：在 NVIDIA（Spectrum-X）與白牌夾擊下，Arista 的份額路徑能否支撐這個倍數？
A4: 核心問題：2027–28 年 Arista 在 AI 乙太網路的份額每掉一截，EPS 少多少；現價隱含的份額路徑合不合理。
A6: 會計年度＝日曆年，FY(t)＝CY(t)，不平移。預測期 FY2027–FY2029（三年）。口徑：公司 non-GAAP；十年 P/E 規則值用 GAAP 換算 EPS。
A8: 驅動因子 → 推導量（全部唯讀上游，不修改）
A9: AI 營收：markets/network 的 AI 後端 scale-out 交換器市場 × 情境顆數係數 × 乙太網路占比（Assumed）× Arista 有效份額（FY2026 以公司 AI 目標 3.5 校準）× 份額相對值（Assumed）。
A10: 非 AI 營收：FY2026 錨點（營收指引 − AI 目標）× Assumed 成長率。毛利率：AI 比非 AI 低 d_ai（Assumed），非 AI 毛利率為 FY2026 殘差（Derived）。營業費用：彈性 phi（Derived）。
A11: 校準：FY2026 ＝ 1Q–2Q 實績＋3Q 指引＋全年指引（營收 12.6、毛利率 63%、營業利益率 48.5%）。不用共識（只在 Recon 對帳）。
A12: 估值：現價 ÷ FY2027、FY2028 EPS；十年 GAAP P/E 規則值（兩個資料商來源）× FY2027 GAAP 換算 EPS；循環位置以本模型營收最高年判定（Arista 不套設備股見頂年）。
A13: 標記：Verified、Interested-party、Analogy、Assumed、Derived。SemiAnalysis 未使用。公司原文＝SEC EDGAR 8-K；法說內容只經二手轉述（標二手）。
A15: 已知限制：(1) 份額相對值與乙太網路占比皆為 Assumed，是 FY2028 EPS 最敏感的輸入（Sens）；(2) FY2026 AI 用公司目標「至少 3.5」，實際可能較高；(3) 網通模型 2027 年 scale-out 交換器 +90%，公司稱供給吃緊到 2028 年，模型未設供給上限（Sens 用市場 ×0.8）；(4) 2027 共識未找到，只有單一分析師；(5) 十年 P/E 含高成長期溢價；(6) R4 產業部署路徑未建（Recon 預留列）。
... A18: 情境對應（v0.2 延伸期）：A＝順利（基準顆數）、B＝平平（CY2028 ×0.8、CY2029 ×0.85）、C＝不如預期（CY2028–29 ×0.6）；FY2027 三情境相同，情境差從 FY2028 起。

Sheet In
A1: In — 輸入（藍字；基準欄 E，低 D、高 F）。金額：十億美元（US$B）；比例：%。每個輸入附兩個來源（找不到者寫「未找到」）；公司原文算一個
A2: 標記：Verified／Interested-party／Analogy／Assumed／Derived；Analogy、Assumed 給低／高區間。SemiAnalysis 未使用。公司原文＝Arista 8-K 新聞稿（SEC EDGAR）；公司的 AI 營收目標與全年指引為 Interested-party
A3: 鍵 | B3: 項目 | C3: 單位 | D3: 低 | E3: 基準 | F3: 高 | G3: 標記 | H3: 來源1 | I3: 來源2／說明
A4: A. AI 後端 scale-out 交換器市場（讀 markets/network 成品；情境 A 基準，B／C 依顆數係數縮放）
A5: mkt_26 | B5: AI 後端 scale-out 交換器市場 2026 | C5: US$B | E5: 32.0719 | G5: Derived | H5: markets/network/dist/20261023_AI網通市場模型_v0.2.2.xlsx｜Mkt!C7:F7 | I5: 加速器顆數 × 每顆 scale-out 交換器內容（不分乙太網路與 InfiniBand）；只含 AI 後端
A6: mkt_27 | B6: AI 後端 scale-out 交換器市場 2027 | C6: US$B | E6: 61.085 | G6: Derived | H6: markets/network/dist/20261023_AI網通市場模型_v0.2.2.xlsx｜Mkt!C7:F7 | I6: 同上
A7: mkt_28 | B7: AI 後端 scale-out 交換器市場 2028 | C7: US$B | E7: 69.005 | G7: Derived | H7: markets/network/dist/20261023_AI網通市場模型_v0.2.2.xlsx｜Mkt!C7:F7 | I7: 同上
A8: mkt_29 | B8: AI 後端 scale-out 交換器市場 2029 | C8: US$B | E8: 78.48215 | G8: Derived | H8: markets/network/dist/20261023_AI網通市場模型_v0.2.2.xlsx｜Mkt!C7:F7 | I8: 同上
A9: itc_26 | B9: AI IT 資本支出 2026 | C9: US$B | E9: 781.87292 | G9: Derived | H9: markets/network/dist/20261023_AI網通市場模型_v0.2.2.xlsx｜Mkt!C27:F27 | I9: Recon 用：Arista AI 營收 ÷ AI IT 資本支出
A10: itc_27 | B10: AI IT 資本支出 2027 | C10: US$B | E10: 1565.35 | G10: Derived | H10: markets/network/dist/20261023_AI網通市場模型_v0.2.2.xlsx｜Mkt!C27:F27 | I10: 同上
A11: itc_28 | B11: AI IT 資本支出 2028 | C11: US$B | E11: 1984.2639 | G11: Derived | H11: markets/network/dist/20261023_AI網通市場模型_v0.2.2.xlsx｜Mkt!C27:F27 | I11: 同上
A12: itc_29 | B12: AI IT 資本支出 2029 | C12: US$B | E12: 2260.3903 | G12: Derived | H12: markets/network/dist/20261023_AI網通市場模型_v0.2.2.xlsx｜Mkt!C27:F27 | I12: 同上
A13: um28_A | B13: 情境 A：2028 顆數 ÷ 基準 | C13: x | E13: 1 | G13: Assumed | H13: tsmc/dist/20261025_台積電模型_v0.3.xlsx｜In!E37 | I13: A＝基準；B＝AI 資本支出消化；C＝明顯下修（與台積電、NVIDIA、Broadcom 模型相同）
A14: um29_A | B14: 情境 A：2029 顆數 ÷ 基準 | C14: x | E14: 1 | G14: Assumed | H14: tsmc/dist/20261025_台積電模型_v0.3.xlsx｜In!E38 | I14: 同上
A15: um28_B | B15: 情境 B：2028 顆數 ÷ 基準 | C15: x | E15: 0.8 | G15: Assumed | H15: tsmc/dist/20261025_台積電模型_v0.3.xlsx｜In!E39 | I15: A＝基準；B＝AI 資本支出消化；C＝明顯下修（與台積電、NVIDIA、Broadcom 模型相同）
A16: um29_B | B16: 情境 B：2029 顆數 ÷ 基準 | C16: x | E16: 0.85 | G16: Assumed | H16: tsmc/dist/20261025_台積電模型_v0.3.xlsx｜In!E40 | I16: 同上
... A18: um29_C | B18: 情境 C：2029 顆數 ÷ 基準 | C18: x | E18: 0.6 | G18: Assumed | H18: tsmc/dist/20261025_台積電模型_v0.3.xlsx｜In!E42 | I18: 同上
A19: B. 乙太網路占比與 Arista 份額（本專案為權威：晶片商與網通廠份額，規則第 13 條）
A20: eth_26 | B20: 乙太網路 ÷ AI 後端交換器（金額）2026 | C20: % | D20: 0.7 | E20: 0.75 | F20: 0.8 | G20: Assumed | H20: Dell'Oro 2026-03-10：2025 年乙太網路占 AI 叢集交換器三分之二以上、為 InfiniBand 兩倍以上（Interested-party） | I20: IDC 2Q26：NVIDIA 資料中心乙太網路年增 181%（乙太網路取代 InfiniBand 的方向）
A21: eth_27 | B21: 乙太網路 ÷ AI 後端交換器 2027 | C21: % | D21: 0.72 | E21: 0.8 | F21: 0.88 | G21: Assumed | H21: 同上；2027 年無公開預測：未找到 | I21: 外推（Assumed）
A22: eth_28 | B22: 乙太網路 ÷ AI 後端交換器 2028 | C22: % | D22: 0.74 | E22: 0.83 | F22: 0.9 | G22: Assumed | H22: 同上 | I22: —
A23: eth_29 | B23: 乙太網路 ÷ AI 後端交換器 2029 | C23: % | D23: 0.75 | E23: 0.85 | F23: 0.92 | G23: Assumed | H23: 同上 | I23: —
A24: rel_27 | B24: Arista 份額 2027 ÷ 2026（相對值） | C24: x | D24: 0.8 | E24: 0.95 | F24: 1.05 | G24: Assumed | H24: IDC 2Q26：NVIDIA 20.4% 已超過 Arista 18.7%（資料中心乙太網路，全部速率；Interested-party） | I24: Dell'Oro 2025 AI 後端乙太網路：Celestica（白牌）與 NVIDIA 並列第一、合計約 50%，Arista 第三（Interested-party）
A25: rel_28 | B25: Arista 份額 2028 ÷ 2026 | C25: x | D25: 0.7 | E25: 0.9 | F25: 1.05 | G25: Assumed | H25: 同上 | I25: —
A26: rel_29 | B26: Arista 份額 2029 ÷ 2026 | C26: x | D26: 0.65 | E26: 0.88 | F26: 1.05 | G26: Assumed | H26: 同上 | I26: —
A27: C. 非 AI 營收（雲端前端、企業、園區、服務）
A28: g_nai27 | B28: 非 AI 營收年增 2027 | C28: % | D28: 0.03 | E28: 0.1 | F28: 0.15 | G28: Assumed | H28: 2026 錨點非 AI 約 9.1（營收指引 12.6 − AI 目標 3.5）；2025 約 7.4（9.0 − AI 約 1.63）→ 2026 約 +23%（Derived，含記憶體缺貨下的提前拉貨可能） | I28: 園區目標 2026 至少 1.25（公司，Interested-party）
A29: g_nai28 | B29: 非 AI 營收年增 2028 | C29: % | D29: 0.02 | E29: 0.08 | F29: 0.12 | G29: Assumed | H29: 同上 | I29: —
A30: g_nai29 | B30: 非 AI 營收年增 2029 | C30: % | D30: 0.02 | E30: 0.06 | F30: 0.1 | G30: Assumed | H30: 同上 | I30: —
A31: ai25 | B31: 2025 年 AI 營收（參考） | C31: US$B | D31: 1.5 | E31: 1.63 | F31: 1.8 | G31: Derived | H31: Next Platform 2026-02-13：以 2026 目標倒推約 1.63（公司稱超過 1.5 目標） | I31: 公司：2025 年 AI 目標 1.5 已超越（法說）
A32: D. 毛利率
A33: d_ai | B33: AI 營收毛利率低於非 AI 的幅度 | C33: pt | D33: 0.03 | E33: 0.06 | F33: 0.1 | G33: Assumed | H33: 公司：毛利率下滑來自雲端與 AI 大客戶占比（2Q26 毛利率較去年同期 −2.2 個百分點；法說，二手） | I33: 產品別毛利率未揭露：未找到
A34: E. FY2026 錨點（Q1–Q2 實績＋Q3 指引＋全年指引）
A35: fy_rev | B35: FY2026 營收指引 | C35: US$B | E35: 12.6 | G35: Interested-party | H35: 法說轉述：BigGo Finance 摘要（2026-08-04；二手）：約 $12.6B（8 月由 11.5 上修） | I35: StockAnalysis 共識 12.68（27 位）
A36: fy_gm | B36: FY2026 non-GAAP 毛利率指引（中點） | C36: % | D36: 0.62 | E36: 0.63 | F36: 0.64 | G36: Interested-party | H36: 法說轉述：BigGo Finance 摘要（2026-08-04；二手）：62–64% | I36: sec-api 彙整同值
A37: fy_oim | B37: FY2026 non-GAAP 營業利益率指引（中點） | C37: % | D37: 0.48 | E37: 0.485 | F37: 0.49 | G37: Interested-party | H37: 法說轉述：BigGo Finance 摘要（2026-08-04；二手）：48–49% | I37: sec-api 彙整同值
A38: q3_rev | B38: 3Q26 營收指引 | C38: US$B | E38: 3.3 | G38: Interested-party | H38: https://www.sec.gov/Archives/edgar/data/0001596532/000159653226000174/ex991q226-earningsrelease.htm：約 $3.3B | I38: BigGo（二手）同值
A39: q3_gm | B39: 3Q26 non-GAAP 毛利率指引 | C39: % | D39: 0.62 | E39: 0.63 | F39: 0.64 | G39: Interested-party | H39: 法說轉述：BigGo Finance 摘要（2026-08-04；二手）：約 63% | I39: 第二來源：未找到
A40: q3_oim | B40: 3Q26 non-GAAP 營業利益率指引（中點） | C40: % | D40: 0.48 | E40: 0.485 | F40: 0.49 | G40: Interested-party | H40: https://www.sec.gov/Archives/edgar/data/0001596532/000159653226000174/ex991q226-earningsrelease.htm：48–49% | I40: —
A41: q_oth | B41: 3Q、4Q26 non-GAAP 其他收益（每季） | C41: US$B | D41: 0.12 | E41: 0.13 | F41: 0.14 | G41: Derived | H41: 1Q26 0.1136、2Q26 0.1263（公司，GAAP 其他收益） | I41: 現金與有價證券 13.3（2026-06，公司）
A42: q_tx | B42: 3Q、4Q26 non-GAAP 有效稅率 | C42: % | D42: 0.2 | E42: 0.21 | F42: 0.22 | G42: Derived | H42: 2Q26：1 − 1301.7 ÷（1513.7＋126.3）＝20.6%；1Q26 21.3%（推導） | I42: 3Q26 EPS 指引 1.06–1.08 隱含約 21%（推導）
A43: q_sh | B43: 3Q、4Q26 稀釋股數 | C43: 十億股 | E43: 1.277 | G43: Derived | H43: 2Q26 1.2760（公司） | I43: —
A44: ai26 | B44: FY2026 AI 營收（公司目標「至少」） | C44: US$B | D44: 3.5 | E44: 3.5 | F44: 4 | G44: Interested-party | H44: 法說轉述：BigGo Finance 摘要（2026-08-04；二手）：AI 至少 $3.5B（2 月 3.25、8 月 3.5）；其中 scale-across 約 1.2 | I44: sec-api 彙整：至少 $3.50B（2026-08-04 法說）
A45: F. 營業費用、其他收益、稅、股數（FY2027 起）
A46: phi | B46: 營業費用成長對營收成長的彈性 | C46: x | D46: 0.4 | E46: 0.55 | F46: 0.8 | G46: Derived | H46: FY2026 錨點營業費用年增 ÷ 營收年增（Q 頁） | I46: 低／高 Assumed
A47: opx_adj | B47: 營業費用額外占營收比（Sens 用；基準 0） | C47: pt | D47: -0.02 | E47: 0 | F47: 0.02 | G47: Assumed | H47: 無 | I47: Sens 用 ±2 個百分點
A48: oth_f | B48: non-GAAP 其他收益（每年） | C48: US$B | D48: 0.4 | E48: 0.55 | F48: 0.7 | G48: Assumed | H48: FY2026 錨點約 0.50（Q 頁）；現金 13.3 × 約 4% | I48: —
A49: tx_f | B49: non-GAAP 有效稅率 | C49: % | D49: 0.19 | E49: 0.21 | F49: 0.22 | G49: Derived | H49: FY2025 19.5%、1H26 約 21%（推導） | I49: —
A50: sh_g | B50: 稀釋股數年變動 | C50: % | D50: -0.01 | E50: 0 | F50: 0.005 | G50: Derived | H50: FY2025 1.2757 → 2Q26 1.2760（公司）：買回大致抵銷股票薪酬 | I50: 低／高 Assumed
A51: mf | B51: AI 市場係數（Sens 用；FY2027 起） | C51: x | D51: 0.8 | E51: 1 | F51: 1.2 | G51: Assumed | H51: 網通模型 2027 年 scale-out 交換器 +90%；公司稱供給吃緊是「兩年的問題」、2028 年才解除（法說，二手） | I51: ±20%
A52: G. 共識、市場資料（只作 Recon 對帳，不作校準）
A53: cons_rev26 | B53: 共識 FY2026 營收 | C53: US$B | E53: 12.68 | G53: Interested-party | H53: StockAnalysis（27 位，2026-10-23） | I53: MarketBeat：FY2026 EPS 共識 3.79（口徑可能為 GAAP 或舊值）
A54: cons_eps26 | B54: 共識 FY2026 non-GAAP EPS | C54: US$ | E54: 4.12 | G54: Interested-party | H54: StockAnalysis（區間 4.05–4.22） | I54: —
A55: erste_eps27 | B55: Erste Group FY2027 EPS（單一分析師） | C55: US$ | E55: 4.79 | G55: Interested-party | H55: MarketBeat 2026-10-23（10-21 由 4.74 上調） | I55: 2027 共識（StockAnalysis 付費）：未找到
A56: dell_top2 | B56: 2025 AI 後端乙太網路：Celestica＋NVIDIA 合計份額 | C56: % | E56: 0.5 | G56: Interested-party | H56: Dell'Oro 2026-03-10：兩家並列第一、合計約 50%；Arista 第三 | I56: —
A57: idc_anet | B57: 2Q26 資料中心乙太網路交換器：Arista 份額（全部速率） | C57: % | E57: 0.187 | G57: Interested-party | H57: IDC 2026-09-11 | I57: NVIDIA 20.4%、Cisco 18.2%
A58: pe_fair_andy | B58: Andy 先驗：合理 P/E | C58: x | E58: 25 | G58: Assumed | H58: 先驗_Andy_Arista_20261024 A9b（Drive；不在本 repo） | I58: 只作對照
A59: H. 價格與估值
A60: px | B60: 股價（2026-10-23 收盤） | C60: US$ | E60: 172.37 | G60: Interested-party | H60: StockAnalysis（2026-10-23 收盤） | I60: markets/invest_map/data/prices.csv 同值（stockscan；bullfincher 兩來源核對）；MarketBeat：10-23 開盤 170.57
A61: pe_ttm_gaap | B61: 近 12 月 GAAP P/E | C61: x | E61: 54.55 | G61: Interested-party | H61: StockAnalysis | I61: MarketBeat 53.81
A62: pe_fwd_sa | B62: 前瞻 P/E（StockAnalysis） | C62: x | E62: 37.06 | G62: Interested-party | H62: StockAnalysis（口徑：未來 12 個月 non-GAAP，頁面未明示） | I62: 第二來源：未找到
A63: g2n | B63: GAAP EPS ÷ non-GAAP EPS（規則值換算用） | C63: x | E63: =1.75/1.89 -> 0.92592593 | G63: Derived | H63: https://www.sec.gov/Archives/edgar/data/0001596532/000159653226000174/ex991q226-earningsrelease.htm：1H26 GAAP 稀釋 EPS 1.75、non-GAAP 1.89 | I63: FY2025：2.75 ÷ 2.98＝0.923（公司）
A64: I. 目標價情境權重（v0.1.1 新增；Val 頁第 0 節用）
A65: tp_wA | B65: 目標價情境權重 A | C65: % | E65: 0.3 | G65: Assumed | H65: Andy 可改（工作單 2026-10-25 預設 A 0.3／B 0.5／C 0.2） | I65: 三者合計應為 100%（Val 頁第 0 節列示）
A66: tp_wB | B66: 目標價情境權重 B | C66: % | E66: 0.5 | G66: Assumed | H66: Andy 可改（工作單 2026-10-25 預設 A 0.3／B 0.5／C 0.2） | I66: 三者合計應為 100%（Val 頁第 0 節列示）
A67: tp_wC | B67: 目標價情境權重 C | C67: % | E67: 0.2 | G67: Assumed | H67: Andy 可改（工作單 2026-10-25 預設 A 0.3／B 0.5／C 0.2） | I67: 三者合計應為 100%（Val 頁第 0 節列示）
A68: J. 目標價參數（v0.2 新增：DCF 與 Comparable 加權、FY2029 後收斂法；黃底＝Andy 可改）
A69: tp_r | B69: DCF 折現率（股東權益成本） | C69: % | E69: 0.1 | G69: Assumed | H69: Andy 可改（工作單 2026-10-25：美、台、日、韓同一值） | I69: Sens 頁 ±1pt
A70: tp_g | B70: 長期成長率（FY2032 後永續；PL 延伸期 B 情境的收斂目標） | C70: % | E70: 0.04 | G70: Assumed | H70: Andy 可改（工作單 2026-10-25） | I70: Sens 頁 ±1pt（只改 DCF 再投資率與永續成長，不改 PL 收斂路徑）
A71: tp_gd | B71: 延伸期 A／C 情境長期成長相對 tp_g 的差（A＋、C−） | C71: pt | E71: 0.02 | G71: Assumed | H71: 工作單 2026-10-25：A＝tp_g＋2pt、C＝tp_g−2pt | I71: —
A72: tp_roe | B72: 近三年平均 ROE（再投資率＝tp_g ÷ tp_roe） | C72: % | E72: 0.2861 | G72: Derived | H72: stockalarm.io ANET ROE（GAAP，年度）：2023 28.91%、2024 28.54%、2025 28.39%，平均 28.61%（資料商，Interested-party） | I72: stockanalysis 近 12 月 ROE 31.48%；OpenCapital 季度 31.4–33.6%
A73: tp_w_dcf | B73: 目標價中 DCF 的權重（其餘為 Comparable） | C73: % | E73: 0.5 | G73: Assumed | H73: Andy 可改（Andy 2026-10-25 11:53 定 50／50） | I73: Sens 頁 0.3／0.7
A74: nm10_k | B74: 延伸期 C 情境淨利率目標＝FY2029 淨利率 × 本係數（同口徑十年平均未找到） | C74: x | E74: 0.8 | G74: Assumed | H74: 工作單：找不到十年平均用最後一年 × 0.8。本模型為 non-GAAP 口徑；同口徑十年淨利率：未找到 | I74: 參考：GAAP 十年平均 29.51%（valueinvesting.io 2016–2025：16.31%、25.71%、15.25%、35.67%、27.38%、28.52%、30.87%、35.62%、40.73%、38.99%）
A75: cons_tp | B75: 市場共識目標價（賣方平均） | C75: US$ | E75: 243.59 | G75: Interested-party | H75: stockanalysis.com（32 位分析師平均，2026-10-23） | I75: 賣方有目標價誘因；只作對照，不進目標價

Sheet Q
A1: Q — 實績（十億美元；EPS 為美元；股數為十億股）。口徑：公司 non-GAAP。藍字＝輸入；黑字＝公式。實績取自 Arista 8-K 新聞稿（SEC EDGAR、Business Wire）
A2: FY2026 錨點＝1Q26、2Q26 實績＋3Q26 指引＋4Q26（＝全年指引 − 前三季；毛利率、營業利益率同法）。1Q26＝上半年合計 − 2Q26。FY2025 non-GAAP 淨利與 EPS 為 2025 年度新聞稿原報值；公司 2026 年起改 non-GAAP 稅額方法並重編 2025 年各季，重編後的全年值：未找到
A3: 項目 | B3: FY2025A | C3: 1Q26 | D3: 2Q26 | E3: 3Q26（指引） | F3: 4Q26（全年指引 − 前三季） | G3: FY2026 錨點 | H3: 標記 | I3: 來源1（公司） | J3: 來源2／說明
A4: 營收 | B4: 9.0057 | C4: =5.7447-D4 -> 2.709 | D4: 3.0357 | E4: =q3_rev -> 3.3 | F4: =fy_rev-C4-D4-E4 -> 3.5553 | G4: =SUM(C4:F4) -> 12.6 | H4: Verified／Interested-party（3Q、4Q 指引） | I4: FY2025：https://www.businesswire.com/news/home/20260212962784/en/Arista-Networks-Inc.-Reports-Fourth-Quarter-and-Year-End-2025-Financial-Results；1Q26、2Q26：https://www.sec.gov/Archives/edgar/data/0001596532/000159653226000174/ex991q226-earningsrelease.htm（2Q26 與上半年合計） | J4: 1Q26＝上半年 − 2Q26；交叉：sec-api 彙整的 GAAP、non-GAAP 毛利率與營業利益率同值
A5: non-GAAP 毛利 | B5: 5.8154 | C5: =3.6155-D5 -> 1.6908 | D5: 1.9247 | E5: =E4*q3_gm -> 2.079 | F5: =fy_rev*fy_gm-C5-D5-E5 -> 2.2435 | G5: =SUM(C5:F5) -> 7.938 | H5: Verified／Interested-party | I5: FY2025：https://www.businesswire.com/news/home/20260212962784/en/Arista-Networks-Inc.-Reports-Fourth-Quarter-and-Year-End-2025-Financial-Results；1Q26、2Q26：https://www.sec.gov/Archives/edgar/data/0001596532/000159653226000174/ex991q226-earningsrelease.htm（2Q26 與上半年合計） | J5: 1Q26＝上半年 − 2Q26；交叉：sec-api 彙整的 GAAP、non-GAAP 毛利率與營業利益率同值
A6: 毛利率 | B6: =B5/B4 -> 0.64574658 | C6: =C5/C4 -> 0.62414175 | D6: =D5/D4 -> 0.63402181 | E6: =E5/E4 -> 0.63 | F6: =F5/F4 -> 0.63102973 | G6: =G5/G4 -> 0.63 | H6: Derived | I6: — | J6: FY2025 64.6%；FY2026 指引 62–64%
A7: non-GAAP 營業費用 | B7: =B5-B8 -> 1.4784 | C7: =C5-C8 -> 0.3968 | D7: =D5-D8 -> 0.411 | E7: =E5-E8 -> 0.4785 | F7: =F5-F8 -> 0.5407 | G7: =SUM(C7:F7) -> 1.827 | H7: Derived（毛利 − 營業利益） | I7: FY2025：https://www.businesswire.com/news/home/20260212962784/en/Arista-Networks-Inc.-Reports-Fourth-Quarter-and-Year-End-2025-Financial-Results；1Q26、2Q26：https://www.sec.gov/Archives/edgar/data/0001596532/000159653226000174/ex991q226-earningsrelease.htm（2Q26 與上半年合計） | J7: 1Q26＝上半年 − 2Q26；交叉：sec-api 彙整的 GAAP、non-GAAP 毛利率與營業利益率同值
A8: non-GAAP 營業利益 | B8: 4.337 | C8: =2.8077-D8 -> 1.294 | D8: 1.5137 | E8: =E4*q3_oim -> 1.6005 | F8: =fy_rev*fy_oim-C8-D8-E8 -> 1.7028 | G8: =SUM(C8:F8) -> 6.111 | H8: Verified／Interested-party | I8: FY2025：https://www.businesswire.com/news/home/20260212962784/en/Arista-Networks-Inc.-Reports-Fourth-Quarter-and-Year-End-2025-Financial-Results；1Q26、2Q26：https://www.sec.gov/Archives/edgar/data/0001596532/000159653226000174/ex991q226-earningsrelease.htm（2Q26 與上半年合計） | J8: 1Q26＝上半年 − 2Q26；交叉：sec-api 彙整的 GAAP、non-GAAP 毛利率與營業利益率同值
A9: 營業利益率 | B9: =B8/B4 -> 0.48158389 | C9: =C8/C4 -> 0.47766704 | D9: =D8/D4 -> 0.49863293 | E9: =E8/E4 -> 0.485 | F9: =F8/F4 -> 0.47894692 | G9: =G8/G4 -> 0.485 | H9: Derived | I9: — | J9: —
A10: 其他收益（GAAP，non-GAAP 沿用） | B10: 0.3936 | C10: =0.2399-D10 -> 0.1136 | D10: 0.1263 | E10: =q_oth -> 0.13 | F10: =q_oth -> 0.13 | G10: =SUM(C10:F10) -> 0.4999 | H10: Verified／Derived（3Q、4Q） | I10: FY2025：https://www.businesswire.com/news/home/20260212962784/en/Arista-Networks-Inc.-Reports-Fourth-Quarter-and-Year-End-2025-Financial-Results；1Q26、2Q26：https://www.sec.gov/Archives/edgar/data/0001596532/000159653226000174/ex991q226-earningsrelease.htm（2Q26 與上半年合計） | J10: 1Q26＝上半年 − 2Q26；交叉：sec-api 彙整的 GAAP、non-GAAP 毛利率與營業利益率同值
A11: 稅前利益 | B11: =B8+B10 -> 4.7306 | C11: =C8+C10 -> 1.4076 | D11: =D8+D10 -> 1.64 | E11: =E8+E10 -> 1.7305 | F11: =F8+F10 -> 1.8328 | G11: =SUM(C11:F11) -> 6.6109 | H11: Derived | I11: FY2025：https://www.businesswire.com/news/home/20260212962784/en/Arista-Networks-Inc.-Reports-Fourth-Quarter-and-Year-End-2025-Financial-Results；1Q26、2Q26：https://www.sec.gov/Archives/edgar/data/0001596532/000159653226000174/ex991q226-earningsrelease.htm（2Q26 與上半年合計） | J11: 1Q26＝上半年 − 2Q26；交叉：sec-api 彙整的 GAAP、non-GAAP 毛利率與營業利益率同值
A12: non-GAAP 淨利 | B12: 3.806 | C12: =2.4099-D12 -> 1.1082 | D12: 1.3017 | E12: =E11*(1-q_tx) -> 1.367095 | F12: =F11*(1-q_tx) -> 1.447912 | G12: =SUM(C12:F12) -> 5.224907 | H12: Verified／Derived（3Q、4Q） | I12: FY2025：https://www.businesswire.com/news/home/20260212962784/en/Arista-Networks-Inc.-Reports-Fourth-Quarter-and-Year-End-2025-Financial-Results；1Q26、2Q26：https://www.sec.gov/Archives/edgar/data/0001596532/000159653226000174/ex991q226-earningsrelease.htm（2Q26 與上半年合計） | J12: 1Q26＝上半年 − 2Q26；交叉：sec-api 彙整的 GAAP、non-GAAP 毛利率與營業利益率同值
A13: 有效稅率（推導） | B13: =1-B12/B11 -> 0.19545089 | C13: =1-C12/C11 -> 0.21270247 | D13: =1-D12/D11 -> 0.20628049 | E13: =1-E12/E11 -> 0.21 | F13: =1-F12/F11 -> 0.21 | G13: =1-G12/G11 -> 0.20965269 | H13: Derived | I13: — | J13: non-GAAP 稅額未直接揭露：1 − 淨利 ÷ 稅前
A14: 稀釋股數（十億股） | B14: 1.2757 | C14: =(1.2749*2-D14) -> 1.2738 | D14: 1.276 | E14: =q_sh -> 1.277 | F14: =q_sh -> 1.277 | G14: =AVERAGE(C14:F14) -> 1.27595 | H14: Verified／Derived | I14: FY2025：https://www.businesswire.com/news/home/20260212962784/en/Arista-Networks-Inc.-Reports-Fourth-Quarter-and-Year-End-2025-Financial-Results；1Q26、2Q26：https://www.sec.gov/Archives/edgar/data/0001596532/000159653226000174/ex991q226-earningsrelease.htm（2Q26 與上半年合計） | J14: 1Q26＝上半年加權 × 2 − 2Q26（近似）
A15: non-GAAP EPS | B15: =B12/B14 -> 2.9834601 | C15: =C12/C14 -> 0.86999529 | D15: =D12/D14 -> 1.0201411 | E15: =E12/E14 -> 1.0705521 | F15: =F12/F14 -> 1.1338387 | G15: =G12/G14 -> 4.0949152 | H15: Derived | I15: 淨利 ÷ 稀釋股數 | J15: —
A16: 公司揭露 non-GAAP EPS | B16: 2.98 | D16: 1.02 | H16: Verified | I16: FY2025：https://www.businesswire.com/news/home/20260212962784/en/Arista-Networks-Inc.-Reports-Fourth-Quarter-and-Year-End-2025-Financial-Results；1Q26、2Q26：https://www.sec.gov/Archives/edgar/data/0001596532/000159653226000174/ex991q226-earningsrelease.htm（2Q26 與上半年合計） | J16: 1Q26：1.89 − 1.02＝0.87；3Q26 指引 1.06–1.08
A17: AI 營收 | B17: =ai25 -> 1.63 | G17: =ai26 -> 3.5 | H17: Derived／Interested-party | I17: FY2025：In ai25；FY2026：公司目標「至少 3.5」 | J17: 各季 AI 營收未揭露：未找到
A18: 非 AI 營收（＝營收 − AI） | B18: =B4-B17 -> 7.3757 | G18: =G4-G17 -> 9.1 | H18: Derived | I18: — | J18: —
A19: AI ÷ 營收 | B19: =B17/B4 -> 0.18099648 | G19: =G17/G4 -> 0.27777778 | H19: Derived | I19: — | J19: Andy 先驗 A2：2026 年 50%
A21: FY2026 錨點與共識的距離（參考；校準未使用共識）
A22: FY2026 營收 ÷ 共識 − 1 | B22: =G4/cons_rev26-1 -> -0.0063091483
A23: FY2026 EPS ÷ 共識 − 1 | B23: =G15/cons_eps26-1 -> -0.0060885531
A24: FY2026 營收年增 | B24: =G4/B4-1 -> 0.39911389
A25: FY2026 營業費用年增 | B25: =G7/B7-1 -> 0.23579545
A26: 營業費用彈性（營業費用年增 ÷ 營收年增；In 頁 phi 的依據） | B26: =B25/B24 -> 0.59079741
A27: 3Q26 EPS（模型）vs 公司指引中點 1.07 | B27: =E15/1.07-1 -> 0.00051595811

Sheet Units
A1: Units — Arista 在 AI 後端乙太網路交換器的份額（本專案權威，規則第 13 條）。市場取自 markets/network（只含 AI 後端 scale-out 交換器，不分協定）
A3: 項目 | B3: 單位 | C3: CY2026 | D3: CY2027 | E3: CY2028 | F3: CY2029 | G3: 說明
A4: AI 後端 scale-out 交換器市場（情境 A） | B4: US$B | C4: =PL!D63 -> 32.0719 | D4: =PL!E63 -> 61.085 | E4: =PL!F63 -> 69.005 | F4: =PL!G63 -> 78.48215 | G4: markets/network Mkt 頁
A5: 乙太網路占比 | B5: % | C5: =PL!D64 -> 0.75 | D5: =PL!E64 -> 0.8 | E5: =PL!F64 -> 0.83 | F5: =PL!G64 -> 0.85 | G5: In 頁 B 節（Assumed）
A6: AI 後端乙太網路交換器市場 | B6: US$B | C6: =PL!D65 -> 24.053925 | D6: =PL!E65 -> 48.868 | E6: =PL!F65 -> 57.27415 | F6: =PL!G65 -> 66.709828
A7: InfiniBand 等其他協定（＝市場 − 乙太網路） | B7: US$B | C7: =PL!D63-PL!D65 -> 8.017975 | D7: =PL!E63-PL!E65 -> 12.217 | E7: =PL!F63-PL!F65 -> 11.73085 | F7: =PL!G63-PL!G65 -> 11.772322 | G7: 幾乎全為 NVIDIA
A8: Arista 有效份額（含前端與 scale-across） | B8: % | C8: =PL!D68 -> 0.1455064 | D8: =PL!E68 -> 0.13823108 | E8: =PL!F68 -> 0.13095576 | F8: =PL!G68 -> 0.12804563 | G8: FY2026 以公司 AI 目標校準
A9: Arista AI 營收（情境 A） | B9: US$B | C9: =PL!D69 -> 3.5 | D9: =PL!E69 -> 6.7550764 | E9: =PL!F69 -> 7.5003798 | F9: =PL!G69 -> 8.5419019
A10: 其他廠商（NVIDIA Spectrum-X、白牌、Cisco 等）＝ 乙太網路市場 − Arista | B10: US$B | C10: =PL!D65-PL!D69 -> 20.553925 | D10: =PL!E65-PL!E69 -> 42.112924 | E10: =PL!F65-PL!F69 -> 49.77377 | F10: =PL!G65-PL!G69 -> 58.167926 | G10: 上限：Arista AI 含前端，所以此列偏低
A11: Arista AI 營收 ÷ AI IT 資本支出 | B11: % | C11: =PL!D69/itc_26 -> 0.0044764308 | D11: =PL!E69/itc_27 -> 0.0043153776 | E11: =PL!F69/itc_28 -> 0.0037799306 | F11: =PL!G69/itc_29 -> 0.00377895 | G11: markets/network 的 AI IT 資本支出（加速器 × 每顆 IT capex）
A13: 讀法：FY2026 有效份額約 15%，與 Dell'Oro「Celestica＋NVIDIA 合計約 50%、Arista 第三」相容；本模型的份額路徑（相對值）是 Assumed，是最需要每季檢查的輸入。

Sheet PL
A1: PL — Arista 損益（US$B；non-GAAP）。FY2025A 實績、FY2026 錨點（1Q–2Q 實績＋3Q 指引＋全年指引），FY2027 起為模型。FY(t)＝CY(t)。三情境各一個完整推導區塊（本頁下方），頂端為摘要。FY2026–FY2027 三情境相同（顆數係數從 CY2028 開始）
A3: 情境／項目 | B3: 單位 | C3: FY2025A | D3: FY2026（錨點） | E3: FY2027 | F3: FY2028 | G3: FY2029 | H3: 說明
A4: 情境 A
A5: 營收 | B5: US$B | C5: =C72 -> 9.0057 | D5: =D72 -> 12.6 | E5: =E72 -> 16.765076 | F5: =F72 -> 18.31118 | G5: =G72 -> 20.00135
A6: 營收年增 | B6: % | D6: =D73 -> 0.39911389 | E6: =E73 -> 0.33056162 | F6: =F73 -> 0.092221675 | G6: =G73 -> 0.092302637
A7: AI 營收 | B7: US$B | C7: =C69 -> 1.63 | D7: =D69 -> 3.5 | E7: =E69 -> 6.7550764 | F7: =F69 -> 7.5003798 | G7: =G69 -> 8.5419019
A8: 非 AI 營收 | B8: US$B | C8: =C71 -> 7.3757 | D8: =D71 -> 9.1 | E8: =E71 -> 10.01 | F8: =F71 -> 10.8108 | G8: =G71 -> 11.459448
A9: AI ÷ 營收 | B9: % | C9: =C74 -> 0.18099648 | D9: =D74 -> 0.27777778 | E9: =E74 -> 0.40292548 | F9: =F74 -> 0.40960658 | G9: =G74 -> 0.42706627
A10: 毛利率 | B10: % | C10: =C78 -> 0.64574658 | D10: =D78 -> 0.63 | E10: =E78 -> 0.62249114 | F10: =F78 -> 0.62209027 | G10: =G78 -> 0.62104269
A11: 營業利益率 | B11: % | C11: =C82 -> 0.48158389 | D11: =D82 -> 0.485 | E11: =E82 -> 0.4937017 | F11: =F82 -> 0.49819428 | G11: =G82 -> 0.501858
A12: 淨利（non-GAAP） | B12: US$B | C12: =C85 -> 3.806 | D12: =D85 -> 5.224907 | E12: =E85 -> 6.9732878 | F12: =F85 -> 7.6412947 | G12: =G85 -> 8.3643916
A13: EPS（non-GAAP） | B13: US$ | C13: =C87 -> 2.9834601 | D13: =D87 -> 4.0949152 | E13: =E87 -> 5.4651733 | F13: =F87 -> 5.9887102 | G13: =G87 -> 6.5554227
A14: EPS 年增 | B14: % | D14: =D88 -> 0.37253896 | E14: =E88 -> 0.3346243 | F14: =F88 -> 0.095795113 | G14: =G88 -> 0.094630147
A16: 情境 B
A17: 營收 | B17: US$B | C17: =C103 -> 9.0057 | D17: =D103 -> 12.6 | E17: =E103 -> 16.765076 | F17: =F103 -> 16.811104 | G17: =G103 -> 18.720065
A18: 營收年增 | B18: % | D18: =D104 -> 0.39911389 | E18: =E104 -> 0.33056162 | F18: =F104 -> 0.0027454371 | G18: =G104 -> 0.11355357
A19: AI 營收 | B19: US$B | C19: =C100 -> 1.63 | D19: =D100 -> 3.5 | E19: =E100 -> 6.7550764 | F19: =F100 -> 6.0003038 | G19: =G100 -> 7.2606167
A20: 非 AI 營收 | B20: US$B | C20: =C102 -> 7.3757 | D20: =D102 -> 9.1 | E20: =E102 -> 10.01 | F20: =F102 -> 10.8108 | G20: =G102 -> 11.459448
A21: AI ÷ 營收 | B21: % | C21: =C105 -> 0.18099648 | D21: =D105 -> 0.27777778 | E21: =E105 -> 0.40292548 | F21: =F105 -> 0.35692503 | G21: =G105 -> 0.38785211
A22: 毛利率 | B22: % | C22: =C109 -> 0.64574658 | D22: =D109 -> 0.63 | E22: =E109 -> 0.62249114 | F22: =F109 -> 0.62525116 | G22: =G109 -> 0.62339554
A23: 營業利益率 | B23: % | C23: =C113 -> 0.48158389 | D23: =D113 -> 0.485 | E23: =E113 -> 0.4937017 | F23: =F113 -> 0.4966204 | G23: =G113 -> 0.50066742
A24: 淨利（non-GAAP） | B24: US$B | C24: =C116 -> 3.806 | D24: =D116 -> 5.224907 | E24: =E116 -> 6.9732878 | F24: =F116 -> 7.0300023 | G24: =G116 -> 7.838796
A25: EPS（non-GAAP） | B25: US$ | C25: =C118 -> 2.9834601 | D25: =D118 -> 4.0949152 | E25: =E118 -> 5.4651733 | F25: =F118 -> 5.5096221 | G25: =G118 -> 6.1434978
A26: EPS 年增 | B26: % | D26: =D119 -> 0.37253896 | E26: =E119 -> 0.3346243 | F26: =F119 -> 0.0081331023 | G26: =G119 -> 0.11504885
A28: 情境 C
A29: 營收 | B29: US$B | C29: =C134 -> 9.0057 | D29: =D134 -> 12.6 | E29: =E134 -> 16.765076 | F29: =F134 -> 15.311028 | G29: =G134 -> 16.584589
A30: 營收年增 | B30: % | D30: =D135 -> 0.39911389 | E30: =E135 -> 0.33056162 | F30: =F135 -> -0.0867308 | G30: =G135 -> 0.083179347
A31: AI 營收 | B31: US$B | C31: =C131 -> 1.63 | D31: =D131 -> 3.5 | E31: =E131 -> 6.7550764 | F31: =F131 -> 4.5002279 | G31: =G131 -> 5.1251412
A32: 非 AI 營收 | B32: US$B | C32: =C133 -> 7.3757 | D32: =D133 -> 9.1 | E32: =E133 -> 10.01 | F32: =F133 -> 10.8108 | G32: =G133 -> 11.459448
A33: AI ÷ 營收 | B33: % | C33: =C136 -> 0.18099648 | D33: =D136 -> 0.27777778 | E33: =E136 -> 0.40292548 | F33: =F136 -> 0.29392069 | G33: =G136 -> 0.30903034
A34: 毛利率 | B34: % | C34: =C140 -> 0.64574658 | D34: =D140 -> 0.63 | E34: =E140 -> 0.62249114 | F34: =F140 -> 0.62903143 | G34: =G140 -> 0.62812485
A35: 營業利益率 | B35: % | C35: =C144 -> 0.48158389 | D35: =D144 -> 0.485 | E35: =E144 -> 0.4937017 | F35: =F144 -> 0.48801118 | G35: =G144 -> 0.49197775
A36: 淨利（non-GAAP） | B36: US$B | C36: =C147 -> 3.806 | D36: =D147 -> 5.224907 | E36: =E147 -> 6.9732878 | F36: =F147 -> 6.3373427 | G36: =G147 -> 6.8803066
A37: EPS（non-GAAP） | B37: US$ | C37: =C149 -> 2.9834601 | D37: =D149 -> 4.0949152 | E37: =E149 -> 5.4651733 | F37: =F149 -> 4.9667642 | G37: =G149 -> 5.3923011
A38: EPS 年增 | B38: % | D38: =D150 -> 0.37253896 | E38: =E150 -> 0.3346243 | F38: =F150 -> -0.091197309 | G38: =G150 -> 0.085676892
A40: 核對（應為 0）：FY2026 模型營收 − 錨點；FY2026 模型 AI − 公司目標（校準恆等式）
A41: 情境 A：營收差（US$B） | D41: =D72-a26_rev -> 0
A42: 情境 A：AI 差（US$B） | D42: =D69-a26_ai -> 0
A43: 情境 A：毛利差（US$B） | D43: =D76*D71+(D76-d_ai)*D69-a26_gp -> 0
A60: 情境 A：基準（顆數係數 1.0）
A61: 項目 | B61: 單位 | C61: FY2025A | D61: FY2026（錨點） | E61: FY2027 | F61: FY2028 | G61: FY2029 | H61: 說明
A62: A. AI 營收（D 欄＝FY2026 校準年；E–G＝FY2027–FY2029）
A63: AI 後端 scale-out 交換器市場 × 情境顆數係數 | B63: US$B | D63: =mkt_26*1 -> 32.0719 | E63: =mkt_27*1*1 -> 61.085 | F63: =mkt_28*um28_A*1 -> 69.005 | G63: =mkt_29*um29_A*1 -> 78.48215
A64: 乙太網路占比 | B64: % | D64: =eth_26 -> 0.75 | E64: =eth_27 -> 0.8 | F64: =eth_28 -> 0.83 | G64: =eth_29 -> 0.85
A65: AI 後端乙太網路交換器市場 | B65: US$B | D65: =D63*D64 -> 24.053925 | E65: =E63*E64 -> 48.868 | F65: =F63*F64 -> 57.27415 | G65: =G63*G64 -> 66.709828
A66: Arista 有效份額（FY2026 校準）＝ AI 目標 ÷ 乙太網路市場 | B66: % | D66: =a26_ai/D65 -> 0.1455064 | H66: Derived：分子含前端與 scale-across，所以高於純後端份額；FY2027 起乘相對值
A67: 份額相對值（÷ FY2026） | B67: x | D67: =1 -> 1 | E67: =rel_27 -> 0.95 | F67: =rel_28 -> 0.9 | G67: =rel_29 -> 0.88
A68: Arista 有效份額 | B68: % | D68: =$D$66*D67 -> 0.1455064 | E68: =$D$66*E67 -> 0.13823108 | F68: =$D$66*F67 -> 0.13095576 | G68: =$D$66*G67 -> 0.12804563
A69: AI 營收 | B69: US$B | C69: =a25_ai -> 1.63 | D69: =D65*D68 -> 3.5 | E69: =E65*E68 -> 6.7550764 | F69: =F65*F68 -> 7.5003798 | G69: =G65*G68 -> 8.5419019
A70: B. 非 AI 與合計
A71: 非 AI 營收 | B71: US$B | C71: =a25_nai -> 7.3757 | D71: =a26_nai -> 9.1 | E71: =D71*(1+g_nai27) -> 10.01 | F71: =E71*(1+g_nai28) -> 10.8108 | G71: =F71*(1+g_nai29) -> 11.459448
A72: 營收 | B72: US$B | C72: =a25_rev -> 9.0057 | D72: =D69+D71 -> 12.6 | E72: =E69+E71 -> 16.765076 | F72: =F69+F71 -> 18.31118 | G72: =G69+G71 -> 20.00135
A73: 營收年增 | B73: % | D73: =D72/C72-1 -> 0.39911389 | E73: =E72/D72-1 -> 0.33056162 | F73: =F72/E72-1 -> 0.092221675 | G73: =G72/F72-1 -> 0.092302637
A74: AI ÷ 營收 | B74: % | C74: =C69/C72 -> 0.18099648 | D74: =D69/D72 -> 0.27777778 | E74: =E69/E72 -> 0.40292548 | F74: =F69/F72 -> 0.40960658 | G74: =G69/G72 -> 0.42706627
A75: C. 損益
A76: 非 AI 毛利率 ＝ 錨點毛利率 ＋ 差距 × AI 占比（FY2026 校準） | B76: % | D76: =a26_gp/a26_rev+d_ai*D74 -> 0.64666667 | H76: Derived：讓 FY2026 毛利率等於錨點；AI 毛利率＝非 AI − 差距。FY2027 起毛利率隨 AI 占比變動
A77: 毛利 | B77: US$B | C77: =a25_gp -> 5.8154 | D77: =a26_gp -> 7.938 | E77: =$D$76*E71+($D$76-d_ai)*E69 -> 10.436111 | F77: =$D$76*F71+($D$76-d_ai)*F69 -> 11.391207 | G77: =$D$76*G71+($D$76-d_ai)*G69 -> 12.421692
A78: 毛利率 | B78: % | C78: =C77/C72 -> 0.64574658 | D78: =D77/D72 -> 0.63 | E78: =E77/E72 -> 0.62249114 | F78: =F77/F72 -> 0.62209027 | G78: =G77/G72 -> 0.62104269
A79: 營業費用（基準路徑） | B79: US$B | C79: =a25_opx -> 1.4784 | D79: =a26_opx -> 1.827 | E79: =D79*(1+MAX(0,phi*E73)) -> 2.1591648 | F79: =E79*(1+MAX(0,phi*F73)) -> 2.2686818 | G79: =F79*(1+MAX(0,phi*G73)) -> 2.3838548
A80: 營業費用 | B80: US$B | C80: =C79 -> 1.4784 | D80: =D79 -> 1.827 | E80: =E79+0*E72 -> 2.1591648 | F80: =F79+0*F72 -> 2.2686818 | G80: =G79+0*G72 -> 2.3838548
A81: 營業利益 | B81: US$B | C81: =C77-C80 -> 4.337 | D81: =D77-D80 -> 6.111 | E81: =E77-E80 -> 8.2769466 | F81: =F77-F80 -> 9.122525 | G81: =G77-G80 -> 10.037837
A82: 營業利益率 | B82: % | C82: =C81/C72 -> 0.48158389 | D82: =D81/D72 -> 0.485 | E82: =E81/E72 -> 0.4937017 | F82: =F81/F72 -> 0.49819428 | G82: =G81/G72 -> 0.501858
A83: 其他收益 | B83: US$B | C83: =a25_oth -> 0.3936 | D83: =a26_oth -> 0.4999 | E83: =oth_f -> 0.55 | F83: =oth_f -> 0.55 | G83: =oth_f -> 0.55
A84: 有效稅率 | B84: % | C84: =1-a25_ni/(a25_oi+a25_oth) -> 0.19545089 | D84: =1-a26_ni/(a26_oi+a26_oth) -> 0.20965269 | E84: =tx_f -> 0.21 | F84: =tx_f -> 0.21 | G84: =tx_f -> 0.21
A85: 淨利（non-GAAP） | B85: US$B | C85: =a25_ni -> 3.806 | D85: =a26_ni -> 5.224907 | E85: =(E81+E83)*(1-E84) -> 6.9732878 | F85: =(F81+F83)*(1-F84) -> 7.6412947 | G85: =(G81+G83)*(1-G84) -> 8.3643916
A86: 稀釋股數 | B86: 十億股 | C86: =a25_sh -> 1.2757 | D86: =a26_sh -> 1.27595 | E86: =D86*(1+sh_g) -> 1.27595 | F86: =E86*(1+sh_g) -> 1.27595 | G86: =F86*(1+sh_g) -> 1.27595
A87: EPS（non-GAAP） | B87: US$ | C87: =C85/C86 -> 2.9834601 | D87: =D85/D86 -> 4.0949152 | E87: =E85/E86 -> 5.4651733 | F87: =F85/F86 -> 5.9887102 | G87: =G85/G86 -> 6.5554227
A88: EPS 年增 | B88: % | D88: =D87/C87-1 -> 0.37253896 | E88: =E87/D87-1 -> 0.3346243 | F88: =F87/E87-1 -> 0.095795113 | G88: =G87/F87-1 -> 0.094630147
A91: 情境 B：CY2028 顆數 ×0.8、CY2029 ×0.85
A92: 項目 | B92: 單位 | C92: FY2025A | D92: FY2026（錨點） | E92: FY2027 | F92: FY2028 | G92: FY2029 | H92: 說明
A93: A. AI 營收（D 欄＝FY2026 校準年；E–G＝FY2027–FY2029）
A94: AI 後端 scale-out 交換器市場 × 情境顆數係數 | B94: US$B | D94: =mkt_26*1 -> 32.0719 | E94: =mkt_27*1*1 -> 61.085 | F94: =mkt_28*um28_B*1 -> 55.204 | G94: =mkt_29*um29_B*1 -> 66.709828
A95: 乙太網路占比 | B95: % | D95: =eth_26 -> 0.75 | E95: =eth_27 -> 0.8 | F95: =eth_28 -> 0.83 | G95: =eth_29 -> 0.85
A96: AI 後端乙太網路交換器市場 | B96: US$B | D96: =D94*D95 -> 24.053925 | E96: =E94*E95 -> 48.868 | F96: =F94*F95 -> 45.81932 | G96: =G94*G95 -> 56.703353
A97: Arista 有效份額（FY2026 校準）＝ AI 目標 ÷ 乙太網路市場 | B97: % | D97: =a26_ai/D96 -> 0.1455064 | H97: Derived：分子含前端與 scale-across，所以高於純後端份額；FY2027 起乘相對值
A98: 份額相對值（÷ FY2026） | B98: x | D98: =1 -> 1 | E98: =rel_27 -> 0.95 | F98: =rel_28 -> 0.9 | G98: =rel_29 -> 0.88
A99: Arista 有效份額 | B99: % | D99: =$D$97*D98 -> 0.1455064 | E99: =$D$97*E98 -> 0.13823108 | F99: =$D$97*F98 -> 0.13095576 | G99: =$D$97*G98 -> 0.12804563
A100: AI 營收 | B100: US$B | C100: =a25_ai -> 1.63 | D100: =D96*D99 -> 3.5 | E100: =E96*E99 -> 6.7550764 | F100: =F96*F99 -> 6.0003038 | G100: =G96*G99 -> 7.2606167
A101: B. 非 AI 與合計
A102: 非 AI 營收 | B102: US$B | C102: =a25_nai -> 7.3757 | D102: =a26_nai -> 9.1 | E102: =D102*(1+g_nai27) -> 10.01 | F102: =E102*(1+g_nai28) -> 10.8108 | G102: =F102*(1+g_nai29) -> 11.459448
A103: 營收 | B103: US$B | C103: =a25_rev -> 9.0057 | D103: =D100+D102 -> 12.6 | E103: =E100+E102 -> 16.765076 | F103: =F100+F102 -> 16.811104 | G103: =G100+G102 -> 18.720065
A104: 營收年增 | B104: % | D104: =D103/C103-1 -> 0.39911389 | E104: =E103/D103-1 -> 0.33056162 | F104: =F103/E103-1 -> 0.0027454371 | G104: =G103/F103-1 -> 0.11355357
A105: AI ÷ 營收 | B105: % | C105: =C100/C103 -> 0.18099648 | D105: =D100/D103 -> 0.27777778 | E105: =E100/E103 -> 0.40292548 | F105: =F100/F103 -> 0.35692503 | G105: =G100/G103 -> 0.38785211
A106: C. 損益
A107: 非 AI 毛利率 ＝ 錨點毛利率 ＋ 差距 × AI 占比（FY2026 校準） | B107: % | D107: =a26_gp/a26_rev+d_ai*D105 -> 0.64666667 | H107: Derived：讓 FY2026 毛利率等於錨點；AI 毛利率＝非 AI − 差距。FY2027 起毛利率隨 AI 占比變動
A108: 毛利 | B108: US$B | C108: =a25_gp -> 5.8154 | D108: =a26_gp -> 7.938 | E108: =$D$107*E102+($D$107-d_ai)*E100 -> 10.436111 | F108: =$D$107*F102+($D$107-d_ai)*F100 -> 10.511162 | G108: =$D$107*G102+($D$107-d_ai)*G100 -> 11.670005
A109: 毛利率 | B109: % | C109: =C108/C103 -> 0.64574658 | D109: =D108/D103 -> 0.63 | E109: =E108/E103 -> 0.62249114 | F109: =F108/F103 -> 0.62525116 | G109: =G108/G103 -> 0.62339554
A110: 營業費用（基準路徑） | B110: US$B | C110: =a25_opx -> 1.4784 | D110: =a26_opx -> 1.827 | E110: =D110*(1+MAX(0,phi*E104)) -> 2.1591648 | F110: =E110*(1+MAX(0,phi*F104)) -> 2.1624252 | G110: =F110*(1+MAX(0,phi*G104)) -> 2.2974783
A111: 營業費用 | B111: US$B | C111: =C110 -> 1.4784 | D111: =D110 -> 1.827 | E111: =E110+0*E103 -> 2.1591648 | F111: =F110+0*F103 -> 2.1624252 | G111: =G110+0*G103 -> 2.2974783
A112: 營業利益 | B112: US$B | C112: =C108-C111 -> 4.337 | D112: =D108-D111 -> 6.111 | E112: =E108-E111 -> 8.2769466 | F112: =F108-F111 -> 8.3487371 | G112: =G108-G111 -> 9.3725265
A113: 營業利益率 | B113: % | C113: =C112/C103 -> 0.48158389 | D113: =D112/D103 -> 0.485 | E113: =E112/E103 -> 0.4937017 | F113: =F112/F103 -> 0.4966204 | G113: =G112/G103 -> 0.50066742
A114: 其他收益 | B114: US$B | C114: =a25_oth -> 0.3936 | D114: =a26_oth -> 0.4999 | E114: =oth_f -> 0.55 | F114: =oth_f -> 0.55 | G114: =oth_f -> 0.55
A115: 有效稅率 | B115: % | C115: =1-a25_ni/(a25_oi+a25_oth) -> 0.19545089 | D115: =1-a26_ni/(a26_oi+a26_oth) -> 0.20965269 | E115: =tx_f -> 0.21 | F115: =tx_f -> 0.21 | G115: =tx_f -> 0.21
A116: 淨利（non-GAAP） | B116: US$B | C116: =a25_ni -> 3.806 | D116: =a26_ni -> 5.224907 | E116: =(E112+E114)*(1-E115) -> 6.9732878 | F116: =(F112+F114)*(1-F115) -> 7.0300023 | G116: =(G112+G114)*(1-G115) -> 7.838796
A117: 稀釋股數 | B117: 十億股 | C117: =a25_sh -> 1.2757 | D117: =a26_sh -> 1.27595 | E117: =D117*(1+sh_g) -> 1.27595 | F117: =E117*(1+sh_g) -> 1.27595 | G117: =F117*(1+sh_g) -> 1.27595
A118: EPS（non-GAAP） | B118: US$ | C118: =C116/C117 -> 2.9834601 | D118: =D116/D117 -> 4.0949152 | E118: =E116/E117 -> 5.4651733 | F118: =F116/F117 -> 5.5096221 | G118: =G116/G117 -> 6.1434978
A119: EPS 年增 | B119: % | D119: =D118/C118-1 -> 0.37253896 | E119: =E118/D118-1 -> 0.3346243 | F119: =F118/E118-1 -> 0.0081331023 | G119: =G118/F118-1 -> 0.11504885
A122: 情境 C：CY2028–29 顆數 ×0.6
A123: 項目 | B123: 單位 | C123: FY2025A | D123: FY2026（錨點） | E123: FY2027 | F123: FY2028 | G123: FY2029 | H123: 說明
A124: A. AI 營收（D 欄＝FY2026 校準年；E–G＝FY2027–FY2029）
...

Sheet Val
A1: Val — P/E 估值（美元）。結論用「現價 ÷ FY2027、FY2028 EPS（模型）」與十年 P/E 規則值。Arista 的 GAAP 與 non-GAAP 差距小（約 7%），十年 GAAP P/E 適用；規則值以 GAAP 換算 EPS（non-GAAP × g2n）計算
A2: 循環位置：Arista 不是設備股，不套設備市場見頂年；以本模型營收最高的會計年度為見頂年（比照 NVIDIA；FY(t)＝CY(t)，不平移）。營收到 FY2029 仍在增加時，見頂年未知，判為中段
A3: 0. 目標價（DCF 與 Comparable 加權；v0.2 新增，Andy 2026-10-25）
A4: 0.1 DCF（股東權益現金流，FY2027–FY2032 明確期＋FY2032 後永續）
A5: 項目 | B5: A | C5: B | D5: C | E5: 說明 | F5: 折現年數 t | G5: 期內占比（基準日後）
A6: 情境 EPS（FY2027–FY2032） | E6: 引用 PL 頁延伸表（上游結束後為收斂法）；三情境欄 B／C／D＝A／B／C
A7: FY2027 | B7: =PL!E162 -> 5.4651733 | C7: =PL!E171 -> 5.4651733 | D7: =PL!E180 -> 5.4651733 | F7: 1 | G7: 1
A8: FY2028 | B8: =PL!F162 -> 5.9887102 | C8: =PL!F171 -> 5.5096221 | D8: =PL!F180 -> 4.9667642 | F8: 2 | G8: 1
A9: FY2029 | B9: =PL!G162 -> 6.5554227 | C9: =PL!G171 -> 6.1434978 | D9: =PL!G180 -> 5.3923011 | F9: 3 | G9: 1
A10: FY2030 | B10: =PL!H162 -> 7.0899197 | C10: =PL!H171 -> 6.4674722 | D10: =PL!H180 -> 5.3454506 | F10: 4 | G10: 1
A11: FY2031 | B11: =PL!I162 -> 7.5916559 | C11: =PL!I171 -> 6.6473348 | D11: =PL!I180 -> 5.1674384 | F11: 5 | G11: 1
A12: FY2032 | B12: =PL!J162 -> 8.0471552 | C12: =PL!J171 -> 6.6663272 | D12: =PL!J180 -> 4.865342 | F12: 6 | G12: 1
A13: 股東現金流＝EPS ×（1 − tp_g ÷ tp_roe） | B13: =1-MIN(0.8,tp_g/tp_roe) -> 0.86018875 | E13: B 欄＝可發放比例（1 − 再投資率；再投資率＝tp_g ÷ tp_roe，上限 0.8）；下列六列＝EPS × 可發放比例 × 期內占比
A14: FY2027 股東現金流 | B14: =B7*$B$13*$G$7 -> 4.7010805 | C14: =C7*$B$13*$G$7 -> 4.7010805 | D14: =D7*$B$13*$G$7 -> 4.7010805
A15: FY2028 股東現金流 | B15: =B8*$B$13*$G$8 -> 5.1514211 | C15: =C8*$B$13*$G$8 -> 4.7393149 | D15: =D8*$B$13*$G$8 -> 4.2723546
A16: FY2029 股東現金流 | B16: =B9*$B$13*$G$9 -> 5.6389008 | C16: =C9*$B$13*$G$9 -> 5.2845676 | D16: =D9*$B$13*$G$9 -> 4.6383967
A17: FY2030 股東現金流 | B17: =B10*$B$13*$G$10 -> 6.0986691 | C17: =C10*$B$13*$G$10 -> 5.5632468 | D17: =D10*$B$13*$G$10 -> 4.5980964
A18: FY2031 股東現金流 | B18: =B11*$B$13*$G$11 -> 6.5302569 | C18: =C11*$B$13*$G$11 -> 5.7179626 | D18: =D11*$B$13*$G$11 -> 4.4449723
A19: FY2032 股東現金流 | B19: =B12*$B$13*$G$12 -> 6.9220724 | C19: =C12*$B$13*$G$12 -> 5.7342996 | D19: =D12*$B$13*$G$12 -> 4.1851124
A20: 永續價值（FY2032 年底；FY2032 現金流 ×(1＋tp_g) ÷ (tp_r − tp_g)） | B20: =B19*(1+tp_g)/(tp_r-tp_g) -> 119.98259 | C20: =C19*(1+tp_g)/(tp_r-tp_g) -> 99.394527 | D20: =D19*(1+tp_g)/(tp_r-tp_g) -> 72.541948
A21: DCF 情境每股價值（折現率 tp_r） | B21: =MAX(0,B14/(1+tp_r)^$F$7+B15/(1+tp_r)^$F$8+B16/(1+tp_r)^$F$9+B17/(1+tp_r)^$F$10+B18/(1+tp_r)^$F$11+B19/(1+tp_r)^$F$12+B20/(1+tp_r)^$F$12) -> 92.622293 | C21: =MAX(0,C14/(1+tp_r)^$F$7+C15/(1+tp_r)^$F$8+C16/(1+tp_r)^$F$9+C17/(1+tp_r)^$F$10+C18/(1+tp_r)^$F$11+C19/(1+tp_r)^$F$12+C20/(1+tp_r)^$F$12) -> 78.853532 | D21: =MAX(0,D14/(1+tp_r)^$F$7+D15/(1+tp_r)^$F$8+D16/(1+tp_r)^$F$9+D17/(1+tp_r)^$F$10+D18/(1+tp_r)^$F$11+D19/(1+tp_r)^$F$12+D20/(1+tp_r)^$F$12) -> 60.500443 | E21: 基準日 2026 年底；明確期現金流與永續價值依 F 欄年數折現；小於 0 時取 0（Andy 2026-10-25 12:22）
A22: 其中：永續價值現值占比 | B22: =B20/(1+tp_r)^$F$12/B21 -> 0.73121751 | C22: =C20/(1+tp_r)^$F$12/C21 -> 0.71151688 | D22: =D20/(1+tp_r)^$F$12/D21 -> 0.67682213
A23: DCF 目標價（情境加權） | B23: =(tp_wA*B21+tp_wB*C21+tp_wC*D21)*(1+tp_r) -> 87.244897 | E23: Σ 權重 × 情境價值 ×(1＋tp_r)：推到約 12 個月後
A25: 0.2 Comparable（市場主流同業前瞻 P/E）
A26: 同業與前瞻 P/E | B26: 代號 | C26: 前瞻 12 月 P/E | D26: 日期 | E26: 來源 | F26: 標記
A27: Cisco | B27: CSCO | C27: 20.7 | D27: 2026-10-23 | E27: stockanalysis.com 統計頁（Forward PE） | F27: Interested-party（資料商彙整賣方預估）
A28: Ciena | B28: CIEN | C28: 30.77 | D28: 2026-10-23 | E28: 同上 | F28: Interested-party（同上）
A29: Celestica | B29: CLS | C29: 16.65 | D29: 2026-10-23 | E29: 同上 | F29: Interested-party（同上）
A30: Hewlett Packard Enterprise（含 Juniper） | B30: HPE | C30: 12.19 | D30: 2026-10-23 | E30: 同上 | F30: Interested-party（同上）
A31: Credo | B31: CRDO | C31: 20.19 | D31: 2026-10-23 | E31: 同上 | F31: Interested-party（同上）
A32: 同業選擇 | E32: 券商常用的資料中心網通同業（交換器：Cisco、HPE＋Juniper；光傳輸：Ciena；白牌交換器 ODM：Celestica；AI 互連：Credo）；不含 A 股（Andy 11:53）。前瞻 P/E 口徑為資料商的未來 12 個月共識 EPS，各家 GAAP／non-GAAP 口徑不一
A33: 同業前瞻 P/E 中位數 | B33: =MEDIAN(C27:C31) -> 20.19
A34: 各情境 12 個月後的前瞻 EPS | B34: =2/12*PL!E162+10/12*PL!F162 -> 5.901454 | C34: =2/12*PL!E171+10/12*PL!F171 -> 5.5022139 | D34: =2/12*PL!E180+10/12*PL!F180 -> 5.0498324 | E34: 會計年度＝日曆年：約 12 個月後（2027-10 底）的未來 12 個月＝2027-11～2028-10（2/12 × FY2027＋10/12 × FY2028）
A35: 12 個月後的前瞻 EPS（情境加權） | B35: =tp_wA*B34+tp_wB*C34+tp_wC*D34 -> 5.5315096
A36: Comparable 目標價 | B36: =B33*B35 -> 111.68118 | E36: 同業前瞻 P/E 中位數 × 12 個月後的前瞻 EPS（情境加權）
A38: 0.3 結論
A39: 項目 | B39: 數值 | C39: 對照 | D39: 對照 | E39: 說明
A40: 目標價（DCF 與 Comparable 加權） | B40: =tp_w_dcf*B23+(1-tp_w_dcf)*B36 -> 99.463038 | E40: ="DCF 權重 "&TEXT(tp_w_dcf,"0%")&"、Comparable 權重 "&TEXT(1-tp_w_dcf,"0%")&"（In 頁 tp_w_dcf，Andy 可改）" -> DCF 權重 50%、Comparable 權重 50%（In 頁 tp_w_dcf，Andy 可改）
A41: Comparable 目標價（市場主流同業法） | B41: =B36 -> 111.68118
A42: 市場共識目標價 | B42: =cons_tp -> 243.59 | E42: stockanalysis.com：32 位分析師平均目標價（2026-10-23）；Interested-party
A43: 上檔空間：加權目標價 | B43: =B40/px-1 -> -0.42296781
A44: 上檔空間：Comparable 目標價 | B44: =B41/px-1 -> -0.35208459
A45: 與市場共識目標價的差距：EPS 因素 | B45: =(tp_wA*(2/12*PL!D162+10/12*PL!E162)+tp_wB*(2/12*PL!D171+10/12*PL!E171)+tp_wC*(2/12*PL!D180+10/12*PL!E180))/C45-1 -> 0.12592501 | C45: =px/pe_fwd_sa -> 4.6511063 | E45: B＝我們的前瞻 EPS（情境加權）÷ 共識前瞻 EPS − 1；C＝共識前瞻 EPS（共識未來 12 個月 EPS＝現價 ÷ StockAnalysis 前瞻 P/E（FY2027 以後共識未找到）；比較窗為 2026-11～2027-10，故 B 用同窗的情境加權 2/12 × FY2026＋10/12 × FY2027）
A46: 與市場共識目標價的差距：倍數因素 | B46: =C46/B33-1 -> 1.5939815 | C46: =B42/C45 -> 52.372486 | D46: =B33 -> 20.19 | E46: C＝市場共識目標價 ÷ 共識前瞻 EPS 隱含的倍數；D＝同業中位數；B＝C ÷ D − 1
A47: 價格帶（DCF 不如預期～順利） | B47: =D21*(1+tp_r) -> 66.550487 | C47: =B21*(1+tp_r) -> 101.88452 | E47: B＝C 情境 DCF 價值、C＝A 情境 DCF 價值（皆推到 12 個月後）
A48: 檢查用：現價 ÷ 各情境 FY2028 EPS | B48: =px/PL!F162 -> 28.782492 | C48: =px/PL!F171 -> 31.285267 | D48: =px/PL!F180 -> 34.704688
A49: 歷史倍數檢查：現價隱含 P/E 的十年分位（A／B／C） | B49: =IF(B48<MIN(B106:B115),0,IF(B48>MAX(B106:B115),1,PERCENTRANK(B106:B115,B48))) -> 0.242 | C49: =IF(C48<MIN(B106:B115),0,IF(C48>MAX(B106:B115),1,PERCENTRANK(B106:B115,C48))) -> 0.28 | D49: =IF(D48<MIN(B106:B115),0,IF(D48>MAX(B106:B115),1,PERCENTRANK(B106:B115,D48))) -> 0.332 | E49: 上一列在 2016–2025 年底 P/E 分布（Val!B106:B115）的分位（PERCENTRANK；低於最小＝0、高於最大＝1）；只作檢查，不進目標價
A50: 目標價方法 | B50: DCF：股東現金流＝non-GAAP EPS ×（1 − tp_g ÷ tp_roe），tp_r 10%、tp_g 4%、tp_roe 近三年平均 GAAP ROE 28.6%（再投資率約 14%）；基準日 2026 年底，FY2027 起逐年折現，FY2032 後永續。Comparable：Cisco、Ciena、Celestica、HPE、Credo 前瞻 P/E 中位數 × 12 個月後前瞻 EPS。偏誤方向：同業成長低於 Arista，中位數偏低（Comparable 偏保守）；non-GAAP EPS 排除股票薪酬（偏高）；C 情境 FY2030 起淨利率收斂到 FY2029 × 0.8（Assumed）；歷史分位用十年 GAAP 落後 P/E（companiesmarketcap）；永續價值占 DCF 價值過半（Sens 頁）。
A51: 檢查：情境權重合計（應為 1） | B51: =ROUND(tp_wA+tp_wB+tp_wC,6) -> 1
A55: 1. 價格與市場隱含倍數
A56: 項目 | B56: A | C56: B | D56: C | E56: 說明
A57: 現價（2026-10-23 收盤） | B57: =px -> 172.37
A58: 現價 ÷ FY2026 EPS（錨點） | B58: =px/PL!D13 -> 42.093668 | C58: =px/PL!D25 -> 42.093668 | D58: =px/PL!D37 -> 42.093668
A59: 現價 ÷ FY2027 EPS（模型） | B59: =px/PL!E13 -> 31.539714 | C59: =px/PL!E25 -> 31.539714 | D59: =px/PL!E37 -> 31.539714 | E59: FY2027 三情境相同（顆數係數從 CY2028 開始）
A60: 現價 ÷ FY2028 EPS（模型） | B60: =px/PL!F13 -> 28.782492 | C60: =px/PL!F25 -> 31.285267 | D60: =px/PL!F37 -> 34.704688
A61: 現價 ÷ FY2029 EPS（模型） | B61: =px/PL!G13 -> 26.294262 | C61: =px/PL!G25 -> 28.057307 | D61: =px/PL!G37 -> 31.965945
A62: 前瞻 P/E（StockAnalysis） | B62: =pe_fwd_sa -> 37.06 | E62: Andy 先驗 A9a 答 30x（口徑未註明）
A63: 隱含未來 12 月 EPS ＝ 現價 ÷ 前瞻 P/E | B63: =px/pe_fwd_sa -> 4.6511063
A64: 近 12 月 GAAP P/E（StockAnalysis） | B64: =pe_ttm_gaap -> 54.55
A66: 2. 循環位置（本模型營收最高年；FY(t)＝CY(t)）
A67: 情境 | B67: 營收最高年（FY2026–FY2029） | C67: FY2027 判定 | D67: 規則倍數（GAAP P/E） | E67: 見頂年是否未知 | F67: 說明
A68: A | B68: =INDEX({2026,2027,2028,2029},MATCH(MAX(PL!D72:G72),PL!D72:G72,0)) -> 2029 | C68: =IF(B68=2029,"中段",IF(2027<B68,"中段",IF(2027=B68,"見頂","谷底"))) -> 中段 | D68: =IF(C68="見頂",pe_peak,IF(C68="谷底",pe_trough,pe_mid)) -> 35.83 | E68: =IF(B68=2029,"是：營收到觀測期末仍在增加","否") -> 是：營收到觀測期末仍在增加 | F68: tools/cycle_position.py excel_rule；營收最高年取代設備市場見頂年
A69: B | B69: =INDEX({2026,2027,2028,2029},MATCH(MAX(PL!D103:G103),PL!D103:G103,0)) -> 2029 | C69: =IF(B69=2029,"中段",IF(2027<B69,"中段",IF(2027=B69,"見頂","谷底"))) -> 中段 | D69: =IF(C69="見頂",pe_peak,IF(C69="谷底",pe_trough,pe_mid)) -> 35.83 | E69: =IF(B69=2029,"是：營收到觀測期末仍在增加","否") -> 是：營收到觀測期末仍在增加 | F69: 同上
A70: C | B70: =INDEX({2026,2027,2028,2029},MATCH(MAX(PL!D134:G134),PL!D134:G134,0)) -> 2027 | C70: =IF(B70=2029,"中段",IF(2027<B70,"中段",IF(2027=B70,"見頂","谷底"))) -> 見頂 | D70: =IF(C70="見頂",pe_peak,IF(C70="谷底",pe_trough,pe_mid)) -> 28.68 | E70: =IF(B70=2029,"是：營收到觀測期末仍在增加","否") -> 否 | F70: 同上
A72: 3. 規則值隱含股價（美元；約 FY2027 年底，未折現）＝ FY2027 GAAP 換算 EPS × 規則倍數
A73: 情境 | B73: FY2027 non-GAAP EPS | C73: GAAP 換算 EPS | D73: 規則倍數 | E73: 隱含股價 | F73: 相對現價 | G73: 現價 ÷ GAAP 換算 EPS
A74: A | B74: =PL!E13 -> 5.4651733 | C74: =B74*g2n -> 5.0603456 | D74: =D68 -> 35.83 | E74: =C74*D74 -> 181.31218 | F74: =E74/px-1 -> 0.051877841 | G74: =px/C74 -> 34.062891
A75: B | B75: =PL!E25 -> 5.4651733 | C75: =B75*g2n -> 5.0603456 | D75: =D69 -> 35.83 | E75: =C75*D75 -> 181.31218 | F75: =E75/px-1 -> 0.051877841 | G75: =px/C75 -> 34.062891
A76: C | B76: =PL!E37 -> 5.4651733 | C76: =B76*g2n -> 5.0603456 | D76: =D70 -> 28.68 | E76: =C76*D76 -> 145.13071 | F76: =E76/px-1 -> -0.15802801 | G76: =px/C76 -> 34.062891
A77: 4. What must be true：FY2027 年底價 ＝ 現價 ×（1＋報酬）所需的倍數（情境 A 的 FY2028 EPS，non-GAAP；約 2027 年底的價格看下一年 EPS）
A78: FY2027 年底價 ÷ 現價 | B78: 所需倍數（÷ FY2028 EPS，A） | C78: 所需倍數（÷ FY2028 EPS，C） | D78: 對照：Andy 合理 P/E | E78: 對照：十年中位數（GAAP）
A79: 1 | B79: =px*A79/PL!F13 -> 28.782492 | C79: =px*A79/PL!F37 -> 34.704688 | D79: =pe_fair_andy -> 25 | E79: =pe_mid -> 35.83
A80: 1.1 | B80: =px*A80/PL!F13 -> 31.660741 | C80: =px*A80/PL!F37 -> 38.175157 | D80: =pe_fair_andy -> 25 | E80: =pe_mid -> 35.83
A81: 1.21 | B81: =px*A81/PL!F13 -> 34.826815 | C81: =px*A81/PL!F37 -> 41.992672 | D81: =pe_fair_andy -> 25 | E81: =pe_mid -> 35.83
A82: 1.5 | B82: =px*A82/PL!F13 -> 43.173737 | C82: =px*A82/PL!F37 -> 52.057032 | D82: =pe_fair_andy -> 25 | E82: =pe_mid -> 35.83
A83: 2 | B83: =px*A83/PL!F13 -> 57.564983 | C83: =px*A83/PL!F37 -> 69.409376 | D83: =pe_fair_andy -> 25 | E83: =pe_mid -> 35.83
A84: 讀法：1.00＝價格不變、1.21＝一年約 21%。所需倍數低於歷史中位數時，現價相對便宜；倍數是否合理，另看前瞻 P/E 歷史（Bloomberg）。
A86: 5. 對照：以 Andy 合理 P/E 25x 計算的隱含價（non-GAAP EPS；只作對照，非規則值）
A87: 情境 | B87: FY2027 EPS | C87: × 25x | D87: 相對現價 | E87: FY2028 EPS | F87: × 25x | G87: 相對現價
A88: A | B88: =PL!E13 -> 5.4651733 | C88: =B88*pe_fair_andy -> 136.62933 | D88: =C88/px-1 -> -0.20734854 | E88: =PL!F13 -> 5.9887102 | F88: =E88*pe_fair_andy -> 149.71775 | G88: =F88/px-1 -> -0.13141641
A89: B | B89: =PL!E25 -> 5.4651733 | C89: =B89*pe_fair_andy -> 136.62933 | D89: =C89/px-1 -> -0.20734854 | E89: =PL!F25 -> 5.5096221 | F89: =E89*pe_fair_andy -> 137.74055 | G89: =F89/px-1 -> -0.20090183
A90: C | B90: =PL!E37 -> 5.4651733 | C90: =B90*pe_fair_andy -> 136.62933 | D90: =C90/px-1 -> -0.20734854 | E90: =PL!F37 -> 4.9667642 | F90: =E90*pe_fair_andy -> 124.1691 | G90: =F90/px-1 -> -0.27963622
A101: 6. 十年倍數與規則值（2016–2025 年底；見頂年 25 分位、中段中位數、谷底 75 分位）
A102: 規則（Andy 2026-10-13）：合理倍數＝2016–2025 年底 P/E 依循環位置取分位；兩個來源各取分位再平均。歷史倍數為 GAAP 落後 P/E，所以基準用 GAAP 換算 EPS。2016–2025 含高成長期（2021 年 52x），規則值可能高估成長放緩後的倍數。
A104: P/E：十年歷史倍數
A105: 年底 | B105: companiesmarketcap（年底 P/E） | C105: Macrotrends（12 月 31 日 ÷ TTM GAAP EPS） | D105: 標記／說明
A106: 2016 | B106: 36.2 | C106: 38.86 | D106: companiesmarketcap（年底 P/E）：Interested-party（資料商；2016–2025 共 10 年）；Macrotrends（12 月 31 日 ÷ TTM GAAP EPS）：Interested-party（資料商；2016–2023 共 8 年，2024 起頁面無資料：未找到）
A107: 2017 | B107: 40.3 | C107: 46.56
A108: 2018 | B108: 24.8 | C108: 26.91
A109: 2019 | B109: 18.1 | C109: 19.12
A110: 2020 | B110: 34.8 | C110: 36.37
A111: 2021 | B111: 52.4 | C111: 54.5
A112: 2022 | B112: 27.5 | C112: 28.42
A113: 2023 | B113: 34.9 | C113: 35.85
A114: 2024 | B114: 48.6
A115: 2025 | B115: 46.8
A116: 25 分位（各來源） | B116: =PERCENTILE(B106:B115,0.25) -> 29.325 | C116: =PERCENTILE(C106:C115,0.25) -> 28.0425
A117: 中位數（各來源） | B117: =MEDIAN(B106:B115) -> 35.55 | C117: =MEDIAN(C106:C115) -> 36.11
A118: 75 分位（各來源） | B118: =PERCENTILE(B106:B115,0.75) -> 45.175 | C118: =PERCENTILE(C106:C115,0.75) -> 40.785
A119: 最小（各來源） | B119: =MIN(B106:B115) -> 18.1 | C119: =MIN(C106:C115) -> 19.12
...

Sheet Recon
A1: Recon — 本模型 vs 公司指引、共識、研調份額。只作事後對照，不為對上數字而調參數。2027 年共識（StockAnalysis 付費）未找到，只有單一分析師與前瞻 P/E 隱含值
A3: 項目 | B3: 對照值 | C3: 模型 A | D3: 差距 A | E3: 模型 B | F3: 差距 B | G3: 模型 C | H3: 差距 C | I3: 對照來源 | J3: 說明
A4: A. 共識與分析師（校準未使用）
A5: FY2026 營收 vs 共識 | B5: =cons_rev26 -> 12.68 | C5: =PL!D72 -> 12.6 | D5: =C5/B5-1 -> -0.0063091483 | E5: =PL!D103 -> 12.6 | F5: =E5/B5-1 -> -0.0063091483 | G5: =PL!D134 -> 12.6 | H5: =G5/B5-1 -> -0.0063091483 | I5: StockAnalysis | J5: 錨點＝公司全年指引 12.6
A6: FY2026 EPS vs 共識 | B6: =cons_eps26 -> 4.12 | C6: =PL!D87 -> 4.0949152 | D6: =C6/B6-1 -> -0.0060885531 | E6: =PL!D118 -> 4.0949152 | F6: =E6/B6-1 -> -0.0060885531 | G6: =PL!D149 -> 4.0949152 | H6: =G6/B6-1 -> -0.0060885531 | I6: StockAnalysis | J6: 錨點（3Q、4Q 依指引與 In 頁假設）
A7: FY2027 EPS vs Erste Group（單一分析師） | B7: =erste_eps27 -> 4.79 | C7: =PL!E87 -> 5.4651733 | D7: =C7/B7-1 -> 0.14095475 | E7: =PL!E118 -> 5.4651733 | F7: =E7/B7-1 -> 0.14095475 | G7: =PL!E149 -> 5.4651733 | H7: =G7/B7-1 -> 0.14095475 | I7: MarketBeat | J7: 2027 共識：未找到（付費）
A8: FY2027 EPS vs 前瞻 P/E 隱含未來 12 月 EPS | B8: =px/pe_fwd_sa -> 4.6511063 | C8: =PL!E87 -> 5.4651733 | D8: =C8/B8-1 -> 0.17502652 | E8: =PL!E118 -> 5.4651733 | F8: =E8/B8-1 -> 0.17502652 | G8: =PL!E149 -> 5.4651733 | H8: =G8/B8-1 -> 0.17502652 | I8: StockAnalysis（推導） | J8: 未來 12 月 ≈ 4Q26＋¾ FY2027，口徑不同，只作量級比較
A9: FY2027 營收年增（模型） | C9: =PL!E73 -> 0.33056162 | E9: =PL!E104 -> 0.33056162 | G9: =PL!E135 -> 0.33056162 | I9: —
A10: B. 份額與市場（先驗比對的機制檢查）
A11: FY2026 Arista 有效份額 vs IDC 資料中心乙太網路份額（全部速率） | B11: =idc_anet -> 0.187 | C11: =PL!D66 -> 0.1455064 | D11: =C11-B11 -> -0.041493601 | E11: =PL!D97 -> 0.1455064 | F11: =E11-B11 -> -0.041493601 | G11: =PL!D128 -> 0.1455064 | H11: =G11-B11 -> -0.041493601 | I11: IDC 2Q26 | J11: 口徑不同：IDC 含前端與非 AI；本模型分母只含 AI 後端
A12: FY2026 Arista 有效份額 vs 1 − Celestica、NVIDIA 合計（上限） | B12: =1-dell_top2 -> 0.5 | C12: =PL!D66 -> 0.1455064 | D12: =C12-B12 -> -0.3544936 | E12: =PL!D97 -> 0.1455064 | F12: =E12-B12 -> -0.3544936 | G12: =PL!D128 -> 0.1455064 | H12: =G12-B12 -> -0.3544936 | I12: Dell'Oro 2025 | J12: Arista 第三，有效份額應低於上限
A13: FY2027 AI ÷ 營收 vs Andy 先驗（54%） | B13: 0.54 | C13: =PL!E74 -> 0.40292548 | D13: =C13-B13 -> -0.13707452 | E13: =PL!E105 -> 0.40292548 | F13: =E13-B13 -> -0.13707452 | G13: =PL!E136 -> 0.40292548 | H13: =G13-B13 -> -0.13707452 | I13: 先驗_Andy_Arista A2（Drive）
A14: FY2027 Arista AI 營收 ÷ AI IT 資本支出 | C14: =PL!E69/itc_27 -> 0.0043153776 | E14: =PL!E100/itc_27 -> 0.0043153776 | G14: =PL!E131/itc_27 -> 0.0043153776 | I14: markets/network | J14: Andy 先驗 A7：每 GW 4 億美元
A15: FY2028 Arista AI 營收 ÷ AI 後端乙太網路市場（有效份額） | C15: =PL!F68 -> 0.13095576 | E15: =PL!F99 -> 0.13095576 | G15: =PL!F130 -> 0.13095576 | I15: —
A16: C. 校準
A17: 非 AI 毛利率（Derived） | C17: =PL!D76 -> 0.64666667 | E17: =PL!D107 -> 0.64666667 | G17: =PL!D138 -> 0.64666667 | I17: FY2026 錨點 | J17: AI 毛利率＝此值 − d_ai
A18: FY2027 毛利率 vs FY2026（百分點） | B18: =a26_gp/a26_rev -> 0.63 | C18: =PL!E78 -> 0.62249114 | D18: =C18-B18 -> -0.0075088618 | E18: =PL!E109 -> 0.62249114 | F18: =E18-B18 -> -0.0075088618 | G18: =PL!E140 -> 0.62249114 | H18: =G18-B18 -> -0.0075088618 | I18: 錨點 | J18: AI 占比上升使毛利率下滑
A19: 3Q26 EPS（模型）vs 公司指引中點 1.07 | B19: 1.07 | C19: =Q!E15 -> 1.0705521 | D19: =C19/B19-1 -> 0.00051595811 | E19: =Q!E15 -> 1.0705521 | F19: =E19/B19-1 -> 0.00051595811 | G19: =Q!E15 -> 1.0705521 | H19: =G19/B19-1 -> 0.00051595811 | I19: 公司（2Q26 新聞稿）
A20: D. 預留
A21: R4 產業部署路徑（markets/deploy_path/，尚未建立）：上線後以 Arista AI 營收 ÷ 部署 GW 計算每 GW 營收，對照 Andy 先驗 A7 | J21: 預留列：本版無數值

Sheet Sens
A1: Sens — 一次動一個輸入（情境 A；有效份額、非 AI 毛利率在每個案例內依 FY2026 錨點重算，FY2026 恆等於錨點）：對 FY2027、FY2028 的營收、AI 營收、毛利率與 EPS 的影響。每個案例是一個完整推導區塊（本頁下方）
A3: 案例 | B3: 設定 | C3: FY2027 營收 | D3: FY2027 AI 營收 | E3: FY2027 毛利率 | F3: FY2027 EPS | G3: FY2027 EPS 相對基準 | H3: FY2028 營收 | I3: FY2028 AI 營收 | J3: FY2028 毛利率 | K3: FY2028 EPS | L3: FY2028 EPS 相對基準
A4: 基準（情境 A） | B4: PL 區塊 A | C4: =PL!E72 -> 16.765076 | D4: =PL!E69 -> 6.7550764 | E4: =PL!E78 -> 0.62249114 | F4: =PL!E87 -> 5.4651733 | G4: =F4/F$4-1 -> 0 | H4: =PL!F72 -> 18.31118 | I4: =PL!F69 -> 7.5003798 | J4: =PL!F78 -> 0.62209027 | K4: =PL!F87 -> 5.9887102 | L4: =K4/K$4-1 -> 0
A5: 份額流失（低） | B5: 份額相對值 2027 0.80、2028 0.70、2029 0.65（NVIDIA、白牌加速） | C5: =E52 -> 15.698485 | D5: =E49 -> 5.6884854 | E5: =E58 -> 0.62492513 | F5: =E67 -> 5.1304176 | G5: =F5/F$4-1 -> -0.061252524 | H5: =F52 -> 16.644429 | I5: =F49 -> 5.8336287 | J5: =F58 -> 0.62563754 | K5: =F67 -> 5.4612046 | L5: =K5/K$4-1 -> -0.088083335
A6: 份額持平（高） | B6: 份額相對值 1.05 | C6: =E83 -> 17.476137 | D6: =E80 -> 7.466137 | E6: =E89 -> 0.62103353 | F6: =E98 -> 5.6883437 | G6: =F6/F$4-1 -> 0.040835016 | H6: =F83 -> 19.561243 | I6: =F80 -> 8.7504431 | J6: =F89 -> 0.61982652 | K6: =F98 -> 6.3854418 | L6: =K6/K$4-1 -> 0.066246588
A7: 乙太網路占比 低 | B7: 2026 70% → 2029 75% | C7: =E114 -> 16.523824 | D7: =E111 -> 6.5138236 | E7: =E120 -> 0.62301419 | F7: =E129 -> 5.3894547 | G7: =F7/F$4-1 -> -0.013854737 | H7: =F114 -> 17.975535 | I7: =F111 -> 7.1647345 | J7: =F120 -> 0.62275171 | K7: =F129 -> 5.882491 | L7: =K7/K$4-1 -> -0.01773657
A8: 乙太網路占比 高 | B8: 2026 80% → 2029 92% | C8: =E145 -> 16.976172 | D8: =E142 -> 6.9661725 | E8: =E151 -> 0.62204567 | F8: =E160 -> 5.531427 | G8: =F8/F$4-1 -> 0.012122895 | H8: =F145 -> 18.435433 | I8: =F142 -> 7.6246331 | J8: =F151 -> 0.62185152 | K8: =F160 -> 6.0275314 | L8: =K8/K$4-1 -> 0.0064824029
A9: AI 市場 ×0.8 | B9: FY2027 起 scale-out 交換器市場 ×0.8（供給受限或內容不如預期） | C9: =E176 -> 15.414061 | D9: =E173 -> 5.4040611 | E9: =E182 -> 0.62563109 | F9: =E191 -> 5.0411494 | G9: =F9/F$4-1 -> -0.07758653 | H9: =F176 -> 16.811104 | I9: =F173 -> 6.0003038 | J9: =F182 -> 0.62525116 | K9: =F191 -> 5.5150351 | L9: =K9/K$4-1 -> -0.079094667
A10: AI 市場 ×1.2 | B10: ×1.2 | C10: =E207 -> 18.116092 | D10: =E204 -> 8.1060916 | E10: =E213 -> 0.61981951 | F10: =E222 -> 5.8891971 | G10: =F10/F$4-1 -> 0.07758653 | H10: =F207 -> 19.811256 | I10: =F204 -> 9.0004557 | J10: =F213 -> 0.61940805 | K10: =F222 -> 6.4624515 | L10: =K10/K$4-1 -> 0.079105735
A11: 非 AI 成長 低 | B11: 2027 +3%、2028–29 +2% | C11: =E238 -> 16.128076 | D11: =E235 -> 6.7550764 | E11: =E244 -> 0.62153629 | F11: =E253 -> 5.2415834 | G11: =F11/F$4-1 -> -0.040911759 | H11: =F238 -> 17.06084 | I11: =F235 -> 7.5003798 | J11: =F244 -> 0.62028914 | K11: =F253 -> 5.5458342 | L11: =K11/K$4-1 -> -0.073951803
A12: 非 AI 成長 高 | B12: 2027 +15%、2028 +12%、2029 +10% | C12: =E269 -> 17.220076 | D12: =E266 -> 6.7550764 | E12: =E275 -> 0.62312992 | F12: =E284 -> 5.6248803 | G12: =F12/F$4-1 -> 0.029222685 | H12: =F269 -> 19.22118 | I12: =F266 -> 7.5003798 | J12: =F275 -> 0.62325381 | K12: =F284 -> 6.3115189 | L12: =K12/K$4-1 -> 0.053902882
A13: AI 毛利率差距 3pt | B13: AI 毛利率只低 3 個百分點 | C13: =E300 -> 16.765076 | D13: =E297 -> 6.7550764 | E13: =E306 -> 0.62624557 | F13: =E315 -> 5.5041444 | G13: =F13/F$4-1 -> 0.0071308147 | H13: =F300 -> 18.31118 | I13: =F297 -> 7.5003798 | J13: =F306 -> 0.62604514 | K13: =F315 -> 6.0335477 | L13: =K13/K$4-1 -> 0.0074870035
A14: AI 毛利率差距 10pt | B14: 低 10 個百分點 | C14: =E331 -> 16.765076 | D14: =E328 -> 6.7550764 | E14: =E337 -> 0.61748523 | F14: =E346 -> 5.4132118 | G14: =F14/F$4-1 -> -0.009507753 | H14: =F331 -> 18.31118 | I14: =F328 -> 7.5003798 | J14: =F337 -> 0.61681712 | K14: =F346 -> 5.9289268 | L14: =K14/K$4-1 -> -0.0099826713
A15: 營業費用率 +2pt | B15: 營業費用額外 +2% × 營收 | C15: =E362 -> 16.765076 | D15: =E359 -> 6.7550764 | E15: =E368 -> 0.62249114 | F15: =E377 -> 5.2575725 | G15: =F15/F$4-1 -> -0.037986128 | H15: =F362 -> 18.31118 | I15: =F359 -> 7.5003798 | J15: =F368 -> 0.62209027 | K15: =F377 -> 5.7619641 | L15: =K15/K$4-1 -> -0.037862254
A16: 顆數情境 B | B16: CY2028 ×0.8、CY2029 ×0.85 | C16: =PL!E103 -> 16.765076 | D16: =PL!E100 -> 6.7550764 | E16: =PL!E109 -> 0.62249114 | F16: =PL!E118 -> 5.4651733 | G16: =F16/F$4-1 -> 0 | H16: =PL!F103 -> 16.811104 | I16: =PL!F100 -> 6.0003038 | J16: =PL!F109 -> 0.62525116 | K16: =PL!F118 -> 5.5096221 | L16: =K16/K$4-1 -> -0.079998541
A17: 顆數情境 C | B17: CY2028–29 ×0.6 | C17: =PL!E134 -> 16.765076 | D17: =PL!E131 -> 6.7550764 | E17: =PL!E140 -> 0.62249114 | F17: =PL!E149 -> 5.4651733 | G17: =F17/F$4-1 -> 0 | H17: =PL!F134 -> 15.311028 | I17: =PL!F131 -> 4.5002279 | J17: =PL!F140 -> 0.62903143 | K17: =PL!F149 -> 4.9667642 | L17: =K17/K$4-1 -> -0.17064542
A19: 讀法：FY2027 三情境相同；顆數情境 B、C 的差異從 FY2028 起。份額與乙太網路占比的案例中，FY2026 有效份額依新的乙太網路占比重算，所以 FY2026 恆等於錨點。
A21: 目標價參數敏感度（v0.2）：加權目標價（Val 第 0 節）一次動一個參數；PL 延伸期的收斂路徑不隨 tp_g 變動，tp_g 只改再投資率與永續成長
A22: 參數 | B22: 設定（低／高） | C22: 低：加權目標價 | D22: 低：相對基準 | E22: 高：加權目標價 | F22: 高：相對基準 | G22: 基準加權目標價
A23: tp_r ±1pt | B23: 折現率 −1pt／＋1pt | C23: =tp_w_dcf*(tp_wA*(MAX(0,Val!B7*Val!$G$7*(1-MIN(0.8,tp_g/tp_roe))/(1+(tp_r-0.01))^Val!$F$7+Val!B8*Val!$G$8*(1-MIN(0.8,tp_g/tp_roe))/(1+(tp_r-0.01))^Val!$F$8+Val!B9*Val!$G$9*(1-MIN(0.8,tp_g/tp_roe))/(1+(tp_r-0.01))^Val!$F$9+Val!B10*Val!$G$10*(1-MIN(0.8,tp_g/tp_roe))/(1+(tp_r-0.01))^Val!$F$10+Val!B11*Val!$G$11*(1-MIN(0.8,tp_g/tp_roe))/(1+(tp_r-0.01))^Val!$F$11+Val!B12*Val!$G$12*(1-MIN(0.8,tp_g/tp_roe))/(1+(tp_r-0.01))^Val!$F$12+Val!B12*(1-MIN(0.8,tp_g/tp_roe))*(1+tp_g)/((tp_r-0.01)-tp_g)/(1+(tp_r-0.01))^Val!$F$12))+tp_wB*(MAX(0,Val!C7*Val!$G$7*(1-MIN(0.8,tp_g/tp_roe))/(1+(tp_r-0.01))^Val!$F$7+Val!C8*Val!$G$8*(1-MIN(0.8,tp_g/tp_roe))/(1+(tp_r-0.01))^Val!$F$8+Val!C9*Val!$G$9*(1-MIN(0.8,tp_g/tp_roe))/(1+(tp_r-0.01))^Val!$F$9+Val!C10*Val!$G$10*(1-MIN(0.8,tp_g/tp_roe))/(1+(tp_r-0.01))^Val!$F$10+Val!C11*Val!$G$11*(1-MIN(0.8,tp_g/tp_roe))/(1+(tp_r-0.01))^Val!$F$11+Val!C12*Val!$G$12*(1-MIN(0.8,tp_g/tp_roe))/(1+(tp_r-0.01))^Val!$F$12+Val!C12*(1-MIN(0.8,tp_g/tp_roe))*(1+tp_g)/((tp_r-0.01)-tp_g)/(1+(tp_r-0.01))^Val!$F$12))+tp_wC*(MAX(0,Val!D7*Val!$G$7*(1-MIN(0.8,tp_g/tp_roe))/(1+(tp_r-0.01))^Val!$F$7+Val!D8*Val!$G$8*(1-MIN(0.8,tp_g/tp_roe))/(1+(tp_r-0.01))^Val!$F$8+Val!D9*Val!$G$9*(1-MIN(0.8,tp_g/tp_roe))/(1+(tp_r-0.01))^Val!$F$9+Val!D10*Val!$G$10*(1-MIN(0.8,tp_g/tp_roe))/(1+(tp_r-0.01))^Val!$F$10+Val!D11*Val!$G$11*(1-MIN(0.8,tp_g/tp_roe))/(1+(tp_r-0.01))^Val!$F$11+Val!D12*Val!$G$12*(1-MIN(0.8,tp_g/tp_roe))/(1+(tp_r-0.01))^Val!$F$12+Val!D12*(1-MIN(0.8,tp_g/tp_roe))*(1+tp_g)/((tp_r-0.01)-tp_g)/(1+(tp_r-0.01))^Val!$F$12)))*(1+(tp_r-0.01))+(1-tp_w_dcf)*Val!$B$36 -> 107.70283 | D23: =C23/G23-1 -> 0.082842754 | E23: =tp_w_dcf*(tp_wA*(MAX(0,Val!B7*Val!$G$7*(1-MIN(0.8,tp_g/tp_roe))/(1+(tp_r+0.01))^Val!$F$7+Val!B8*Val!$G$8*(1-MIN(0.8,tp_g/tp_roe))/(1+(tp_r+0.01))^Val!$F$8+Val!B9*Val!$G$9*(1-MIN(0.8,tp_g/tp_roe))/(1+(tp_r+0.01))^Val!$F$9+Val!B10*Val!$G$10*(1-MIN(0.8,tp_g/tp_roe))/(1+(tp_r+0.01))^Val!$F$10+Val!B11*Val!$G$11*(1-MIN(0.8,tp_g/tp_roe))/(1+(tp_r+0.01))^Val!$F$11+Val!B12*Val!$G$12*(1-MIN(0.8,tp_g/tp_roe))/(1+(tp_r+0.01))^Val!$F$12+Val!B12*(1-MIN(0.8,tp_g/tp_roe))*(1+tp_g)/((tp_r+0.01)-tp_g)/(1+(tp_r+0.01))^Val!$F$12))+tp_wB*(MAX(0,Val!C7*Val!$G$7*(1-MIN(0.8,tp_g/tp_roe))/(1+(tp_r+0.01))^Val!$F$7+Val!C8*Val!$G$8*(1-MIN(0.8,tp_g/tp_roe))/(1+(tp_r+0.01))^Val!$F$8+Val!C9*Val!$G$9*(1-MIN(0.8,tp_g/tp_roe))/(1+(tp_r+0.01))^Val!$F$9+Val!C10*Val!$G$10*(1-MIN(0.8,tp_g/tp_roe))/(1+(tp_r+0.01))^Val!$F$10+Val!C11*Val!$G$11*(1-MIN(0.8,tp_g/tp_roe))/(1+(tp_r+0.01))^Val!$F$11+Val!C12*Val!$G$12*(1-MIN(0.8,tp_g/tp_roe))/(1+(tp_r+0.01))^Val!$F$12+Val!C12*(1-MIN(0.8,tp_g/tp_roe))*(1+tp_g)/((tp_r+0.01)-tp_g)/(1+(tp_r+0.01))^Val!$F$12))+tp_wC*(MAX(0,Val!D7*Val!$G$7*(1-MIN(0.8,tp_g/tp_roe))/(1+(tp_r+0.01))^Val!$F$7+Val!D8*Val!$G$8*(1-MIN(0.8,tp_g/tp_roe))/(1+(tp_r+0.01))^Val!$F$8+Val!D9*Val!$G$9*(1-MIN(0.8,tp_g/tp_roe))/(1+(tp_r+0.01))^Val!$F$9+Val!D10*Val!$G$10*(1-MIN(0.8,tp_g/tp_roe))/(1+(tp_r+0.01))^Val!$F$10+Val!D11*Val!$G$11*(1-MIN(0.8,tp_g/tp_roe))/(1+(tp_r+0.01))^Val!$F$11+Val!D12*Val!$G$12*(1-MIN(0.8,tp_g/tp_roe))/(1+(tp_r+0.01))^Val!$F$12+Val!D12*(1-MIN(0.8,tp_g/tp_roe))*(1+tp_g)/((tp_r+0.01)-tp_g)/(1+(tp_r+0.01))^Val!$F$12)))*(1+(tp_r+0.01))+(1-tp_w_dcf)*Val!$B$36 -> 93.576482 | F23: =E23/G23-1 -> -0.059183358 | G23: =Val!$B$40 -> 99.463038
A24: tp_g ±1pt | B24: 長期成長 −1pt／＋1pt | C24: =tp_w_dcf*(tp_wA*(MAX(0,Val!B7*Val!$G$7*(1-MIN(0.8,(tp_g-0.01)/tp_roe))/(1+tp_r)^Val!$F$7+Val!B8*Val!$G$8*(1-MIN(0.8,(tp_g-0.01)/tp_roe))/(1+tp_r)^Val!$F$8+Val!B9*Val!$G$9*(1-MIN(0.8,(tp_g-0.01)/tp_roe))/(1+tp_r)^Val!$F$9+Val!B10*Val!$G$10*(1-MIN(0.8,(tp_g-0.01)/tp_roe))/(1+tp_r)^Val!$F$10+Val!B11*Val!$G$11*(1-MIN(0.8,(tp_g-0.01)/tp_roe))/(1+tp_r)^Val!$F$11+Val!B12*Val!$G$12*(1-MIN(0.8,(tp_g-0.01)/tp_roe))/(1+tp_r)^Val!$F$12+Val!B12*(1-MIN(0.8,(tp_g-0.01)/tp_roe))*(1+(tp_g-0.01))/(tp_r-(tp_g-0.01))/(1+tp_r)^Val!$F$12))+tp_wB*(MAX(0,Val!C7*Val!$G$7*(1-MIN(0.8,(tp_g-0.01)/tp_roe))/(1+tp_r)^Val!$F$7+Val!C8*Val!$G$8*(1-MIN(0.8,(tp_g-0.01)/tp_roe))/(1+tp_r)^Val!$F$8+Val!C9*Val!$G$9*(1-MIN(0.8,(tp_g-0.01)/tp_roe))/(1+tp_r)^Val!$F$9+Val!C10*Val!$G$10*(1-MIN(0.8,(tp_g-0.01)/tp_roe))/(1+tp_r)^Val!$F$10+Val!C11*Val!$G$11*(1-MIN(0.8,(tp_g-0.01)/tp_roe))/(1+tp_r)^Val!$F$11+Val!C12*Val!$G$12*(1-MIN(0.8,(tp_g-0.01)/tp_roe))/(1+tp_r)^Val!$F$12+Val!C12*(1-MIN(0.8,(tp_g-0.01)/tp_roe))*(1+(tp_g-0.01))/(tp_r-(tp_g-0.01))/(1+tp_r)^Val!$F$12))+tp_wC*(MAX(0,Val!D7*Val!$G$7*(1-MIN(0.8,(tp_g-0.01)/tp_roe))/(1+tp_r)^Val!$F$7+Val!D8*Val!$G$8*(1-MIN(0.8,(tp_g-0.01)/tp_roe))/(1+tp_r)^Val!$F$8+Val!D9*Val!$G$9*(1-MIN(0.8,(tp_g-0.01)/tp_roe))/(1+tp_r)^Val!$F$9+Val!D10*Val!$G$10*(1-MIN(0.8,(tp_g-0.01)/tp_roe))/(1+tp_r)^Val!$F$10+Val!D11*Val!$G$11*(1-MIN(0.8,(tp_g-0.01)/tp_roe))/(1+tp_r)^Val!$F$11+Val!D12*Val!$G$12*(1-MIN(0.8,(tp_g-0.01)/tp_roe))/(1+tp_r)^Val!$F$12+Val!D12*(1-MIN(0.8,(tp_g-0.01)/tp_roe))*(1+(tp_g-0.01))/(tp_r-(tp_g-0.01))/(1+tp_r)^Val!$F$12)))*(1+tp_r)+(1-tp_w_dcf)*Val!$B$36 -> 96.344162 | D24: =C24/G24-1 -> -0.031357132 | E24: =tp_w_dcf*(tp_wA*(MAX(0,Val!B7*Val!$G$7*(1-MIN(0.8,(tp_g+0.01)/tp_roe))/(1+tp_r)^Val!$F$7+Val!B8*Val!$G$8*(1-MIN(0.8,(tp_g+0.01)/tp_roe))/(1+tp_r)^Val!$F$8+Val!B9*Val!$G$9*(1-MIN(0.8,(tp_g+0.01)/tp_roe))/(1+tp_r)^Val!$F$9+Val!B10*Val!$G$10*(1-MIN(0.8,(tp_g+0.01)/tp_roe))/(1+tp_r)^Val!$F$10+Val!B11*Val!$G$11*(1-MIN(0.8,(tp_g+0.01)/tp_roe))/(1+tp_r)^Val!$F$11+Val!B12*Val!$G$12*(1-MIN(0.8,(tp_g+0.01)/tp_roe))/(1+tp_r)^Val!$F$12+Val!B12*(1-MIN(0.8,(tp_g+0.01)/tp_roe))*(1+(tp_g+0.01))/(tp_r-(tp_g+0.01))/(1+tp_r)^Val!$F$12))+tp_wB*(MAX(0,Val!C7*Val!$G$7*(1-MIN(0.8,(tp_g+0.01)/tp_roe))/(1+tp_r)^Val!$F$7+Val!C8*Val!$G$8*(1-MIN(0.8,(tp_g+0.01)/tp_roe))/(1+tp_r)^Val!$F$8+Val!C9*Val!$G$9*(1-MIN(0.8,(tp_g+0.01)/tp_roe))/(1+tp_r)^Val!$F$9+Val!C10*Val!$G$10*(1-MIN(0.8,(tp_g+0.01)/tp_roe))/(1+tp_r)^Val!$F$10+Val!C11*Val!$G$11*(1-MIN(0.8,(tp_g+0.01)/tp_roe))/(1+tp_r)^Val!$F$11+Val!C12*Val!$G$12*(1-MIN(0.8,(tp_g+0.01)/tp_roe))/(1+tp_r)^Val!$F$12+Val!C12*(1-MIN(0.8,(tp_g+0.01)/tp_roe))*(1+(tp_g+0.01))/(tp_r-(tp_g+0.01))/(1+tp_r)^Val!$F$12))+tp_wC*(MAX(0,Val!D7*Val!$G$7*(1-MIN(0.8,(tp_g+0.01)/tp_roe))/(1+tp_r)^Val!$F$7+Val!D8*Val!$G$8*(1-MIN(0.8,(tp_g+0.01)/tp_roe))/(1+tp_r)^Val!$F$8+Val!D9*Val!$G$9*(1-MIN(0.8,(tp_g+0.01)/tp_roe))/(1+tp_r)^Val!$F$9+Val!D10*Val!$G$10*(1-MIN(0.8,(tp_g+0.01)/tp_roe))/(1+tp_r)^Val!$F$10+Val!D11*Val!$G$11*(1-MIN(0.8,(tp_g+0.01)/tp_roe))/(1+tp_r)^Val!$F$11+Val!D12*Val!$G$12*(1-MIN(0.8,(tp_g+0.01)/tp_roe))/(1+tp_r)^Val!$F$12+Val!D12*(1-MIN(0.8,(tp_g+0.01)/tp_roe))*(1+(tp_g+0.01))/(tp_r-(tp_g+0.01))/(1+tp_r)^Val!$F$12)))*(1+tp_r)+(1-tp_w_dcf)*Val!$B$36 -> 104.00369 | F24: =E24/G24-1 -> 0.045651683 | G24: =Val!$B$40 -> 99.463038
A25: tp_w_dcf 0.3／0.7 | B25: DCF 權重 0.3／0.7 | C25: =0.3*(tp_wA*(MAX(0,Val!B7*Val!$G$7*(1-MIN(0.8,tp_g/tp_roe))/(1+tp_r)^Val!$F$7+Val!B8*Val!$G$8*(1-MIN(0.8,tp_g/tp_roe))/(1+tp_r)^Val!$F$8+Val!B9*Val!$G$9*(1-MIN(0.8,tp_g/tp_roe))/(1+tp_r)^Val!$F$9+Val!B10*Val!$G$10*(1-MIN(0.8,tp_g/tp_roe))/(1+tp_r)^Val!$F$10+Val!B11*Val!$G$11*(1-MIN(0.8,tp_g/tp_roe))/(1+tp_r)^Val!$F$11+Val!B12*Val!$G$12*(1-MIN(0.8,tp_g/tp_roe))/(1+tp_r)^Val!$F$12+Val!B12*(1-MIN(0.8,tp_g/tp_roe))*(1+tp_g)/(tp_r-tp_g)/(1+tp_r)^Val!$F$12))+tp_wB*(MAX(0,Val!C7*Val!$G$7*(1-MIN(0.8,tp_g/tp_roe))/(1+tp_r)^Val!$F$7+Val!C8*Val!$G$8*(1-MIN(0.8,tp_g/tp_roe))/(1+tp_r)^Val!$F$8+Val!C9*Val!$G$9*(1-MIN(0.8,tp_g/tp_roe))/(1+tp_r)^Val!$F$9+Val!C10*Val!$G$10*(1-MIN(0.8,tp_g/tp_roe))/(1+tp_r)^Val!$F$10+Val!C11*Val!$G$11*(1-MIN(0.8,tp_g/tp_roe))/(1+tp_r)^Val!$F$11+Val!C12*Val!$G$12*(1-MIN(0.8,tp_g/tp_roe))/(1+tp_r)^Val!$F$12+Val!C12*(1-MIN(0.8,tp_g/tp_roe))*(1+tp_g)/(tp_r-tp_g)/(1+tp_r)^Val!$F$12))+tp_wC*(MAX(0,Val!D7*Val!$G$7*(1-MIN(0.8,tp_g/tp_roe))/(1+tp_r)^Val!$F$7+Val!D8*Val!$G$8*(1-MIN(0.8,tp_g/tp_roe))/(1+tp_r)^Val!$F$8+Val!D9*Val!$G$9*(1-MIN(0.8,tp_g/tp_roe))/(1+tp_r)^Val!$F$9+Val!D10*Val!$G$10*(1-MIN(0.8,tp_g/tp_roe))/(1+tp_r)^Val!$F$10+Val!D11*Val!$G$11*(1-MIN(0.8,tp_g/tp_roe))/(1+tp_r)^Val!$F$11+Val!D12*Val!$G$12*(1-MIN(0.8,tp_g/tp_roe))/(1+tp_r)^Val!$F$12+Val!D12*(1-MIN(0.8,tp_g/tp_roe))*(1+tp_g)/(tp_r-tp_g)/(1+tp_r)^Val!$F$12)))*(1+tp_r)+(1-0.3)*Val!$B$36 -> 104.35029 | D25: =C25/G25-1 -> 0.04913641 | E25: =0.7*(tp_wA*(MAX(0,Val!B7*Val!$G$7*(1-MIN(0.8,tp_g/tp_roe))/(1+tp_r)^Val!$F$7+Val!B8*Val!$G$8*(1-MIN(0.8,tp_g/tp_roe))/(1+tp_r)^Val!$F$8+Val!B9*Val!$G$9*(1-MIN(0.8,tp_g/tp_roe))/(1+tp_r)^Val!$F$9+Val!B10*Val!$G$10*(1-MIN(0.8,tp_g/tp_roe))/(1+tp_r)^Val!$F$10+Val!B11*Val!$G$11*(1-MIN(0.8,tp_g/tp_roe))/(1+tp_r)^Val!$F$11+Val!B12*Val!$G$12*(1-MIN(0.8,tp_g/tp_roe))/(1+tp_r)^Val!$F$12+Val!B12*(1-MIN(0.8,tp_g/tp_roe))*(1+tp_g)/(tp_r-tp_g)/(1+tp_r)^Val!$F$12))+tp_wB*(MAX(0,Val!C7*Val!$G$7*(1-MIN(0.8,tp_g/tp_roe))/(1+tp_r)^Val!$F$7+Val!C8*Val!$G$8*(1-MIN(0.8,tp_g/tp_roe))/(1+tp_r)^Val!$F$8+Val!C9*Val!$G$9*(1-MIN(0.8,tp_g/tp_roe))/(1+tp_r)^Val!$F$9+Val!C10*Val!$G$10*(1-MIN(0.8,tp_g/tp_roe))/(1+tp_r)^Val!$F$10+Val!C11*Val!$G$11*(1-MIN(0.8,tp_g/tp_roe))/(1+tp_r)^Val!$F$11+Val!C12*Val!$G$12*(1-MIN(0.8,tp_g/tp_roe))/(1+tp_r)^Val!$F$12+Val!C12*(1-MIN(0.8,tp_g/tp_roe))*(1+tp_g)/(tp_r-tp_g)/(1+tp_r)^Val!$F$12))+tp_wC*(MAX(0,Val!D7*Val!$G$7*(1-MIN(0.8,tp_g/tp_roe))/(1+tp_r)^Val!$F$7+Val!D8*Val!$G$8*(1-MIN(0.8,tp_g/tp_roe))/(1+tp_r)^Val!$F$8+Val!D9*Val!$G$9*(1-MIN(0.8,tp_g/tp_roe))/(1+tp_r)^Val!$F$9+Val!D10*Val!$G$10*(1-MIN(0.8,tp_g/tp_roe))/(1+tp_r)^Val!$F$10+Val!D11*Val!$G$11*(1-MIN(0.8,tp_g/tp_roe))/(1+tp_r)^Val!$F$11+Val!D12*Val!$G$12*(1-MIN(0.8,tp_g/tp_roe))/(1+tp_r)^Val!$F$12+Val!D12*(1-MIN(0.8,tp_g/tp_roe))*(1+tp_g)/(tp_r-tp_g)/(1+tp_r)^Val!$F$12)))*(1+tp_r)+(1-0.7)*Val!$B$36 -> 94.575782 | F25: =E25/G25-1 -> -0.04913641 | G25: =Val!$B$40 -> 99.463038
A40: 案例區塊：份額流失（低）（情境 A）
A41: 項目 | B41: 單位 | C41: FY2025A | D41: FY2026（錨點） | E41: FY2027 | F41: FY2028 | G41: FY2029 | H41: 說明
A42: A. AI 營收（D 欄＝FY2026 校準年；E–G＝FY2027–FY2029）
A43: AI 後端 scale-out 交換器市場 × 情境顆數係數 | B43: US$B | D43: =mkt_26*1 -> 32.0719 | E43: =mkt_27*1*1 -> 61.085 | F43: =mkt_28*um28_A*1 -> 69.005 | G43: =mkt_29*um29_A*1 -> 78.48215
A44: 乙太網路占比 | B44: % | D44: =eth_26 -> 0.75 | E44: =eth_27 -> 0.8 | F44: =eth_28 -> 0.83 | G44: =eth_29 -> 0.85
A45: AI 後端乙太網路交換器市場 | B45: US$B | D45: =D43*D44 -> 24.053925 | E45: =E43*E44 -> 48.868 | F45: =F43*F44 -> 57.27415 | G45: =G43*G44 -> 66.709828
A46: Arista 有效份額（FY2026 校準）＝ AI 目標 ÷ 乙太網路市場 | B46: % | D46: =a26_ai/D45 -> 0.1455064 | H46: Derived：分子含前端與 scale-across，所以高於純後端份額；FY2027 起乘相對值
A47: 份額相對值（÷ FY2026） | B47: x | D47: =1 -> 1 | E47: =RLO_27 -> 0.8 | F47: =RLO_28 -> 0.7 | G47: =RLO_29 -> 0.65
A48: Arista 有效份額 | B48: % | D48: =$D$46*D47 -> 0.1455064 | E48: =$D$46*E47 -> 0.11640512 | F48: =$D$46*F47 -> 0.10185448 | G48: =$D$46*G47 -> 0.094579159
A49: AI 營收 | B49: US$B | C49: =a25_ai -> 1.63 | D49: =D45*D48 -> 3.5 | E49: =E45*E48 -> 5.6884854 | F49: =F45*F48 -> 5.8336287 | G49: =G45*G48 -> 6.3093594
A50: B. 非 AI 與合計
A51: 非 AI 營收 | B51: US$B | C51: =a25_nai -> 7.3757 | D51: =a26_nai -> 9.1 | E51: =D51*(1+g_nai27) -> 10.01 | F51: =E51*(1+g_nai28) -> 10.8108 | G51: =F51*(1+g_nai29) -> 11.459448
A52: 營收 | B52: US$B | C52: =a25_rev -> 9.0057 | D52: =D49+D51 -> 12.6 | E52: =E49+E51 -> 15.698485 | F52: =F49+F51 -> 16.644429 | G52: =G49+G51 -> 17.768807
A53: 營收年增 | B53: % | D53: =D52/C52-1 -> 0.39911389 | E53: =E52/D52-1 -> 0.24591154 | F53: =F52/E52-1 -> 0.060256983 | G53: =G52/F52-1 -> 0.067552855
A54: AI ÷ 營收 | B54: % | C54: =C49/C52 -> 0.18099648 | D54: =D49/D52 -> 0.27777778 | E54: =E49/E52 -> 0.36235887 | F54: =F49/F52 -> 0.35048537 | G54: =G49/G52 -> 0.35508063
A55: C. 損益
A56: 非 AI 毛利率 ＝ 錨點毛利率 ＋ 差距 × AI 占比（FY2026 校準） | B56: % | D56: =a26_gp/a26_rev+d_ai*D54 -> 0.64666667 | H56: Derived：讓 FY2026 毛利率等於錨點；AI 毛利率＝非 AI − 差距。FY2027 起毛利率隨 AI 占比變動
A57: 毛利 | B57: US$B | C57: =a25_gp -> 5.8154 | D57: =a26_gp -> 7.938 | E57: =$D$56*E51+($D$56-d_ai)*E49 -> 9.8103781 | F57: =$D$56*F51+($D$56-d_ai)*F49 -> 10.41338 | G57: =$D$56*G51+($D$56-d_ai)*G49 -> 11.111934
A58: 毛利率 | B58: % | C58: =C57/C52 -> 0.64574658 | D58: =D57/D52 -> 0.63 | E58: =E57/E52 -> 0.62492513 | F58: =F57/F52 -> 0.62563754 | G58: =G57/G52 -> 0.62536183
A59: 營業費用（基準路徑） | B59: US$B | C59: =a25_opx -> 1.4784 | D59: =a26_opx -> 1.827 | E59: =D59*(1+MAX(0,phi*E53)) -> 2.0741042 | F59: =E59*(1+MAX(0,phi*F53)) -> 2.1428428 | G59: =F59*(1+MAX(0,phi*G53)) -> 2.2224581
A60: 營業費用 | B60: US$B | C60: =C59 -> 1.4784 | D60: =D59 -> 1.827 | E60: =E59+0*E52 -> 2.0741042 | F60: =F59+0*F52 -> 2.1428428 | G60: =G59+0*G52 -> 2.2224581
A61: 營業利益 | B61: US$B | C61: =C57-C60 -> 4.337 | D61: =D57-D60 -> 6.111 | E61: =E57-E60 -> 7.7362739 | F61: =F57-F60 -> 8.2705367 | G61: =G57-G60 -> 8.8894757
A62: 營業利益率 | B62: % | C62: =C61/C52 -> 0.48158389 | D62: =D61/D52 -> 0.485 | E62: =E61/E52 -> 0.49280384 | F62: =F61/F52 -> 0.4968952 | G62: =G61/G52 -> 0.50028545
A63: 其他收益 | B63: US$B | C63: =a25_oth -> 0.3936 | D63: =a26_oth -> 0.4999 | E63: =oth_f -> 0.55 | F63: =oth_f -> 0.55 | G63: =oth_f -> 0.55
A64: 有效稅率 | B64: % | C64: =1-a25_ni/(a25_oi+a25_oth) -> 0.19545089 | D64: =1-a26_ni/(a26_oi+a26_oth) -> 0.20965269 | E64: =tx_f -> 0.21 | F64: =tx_f -> 0.21 | G64: =tx_f -> 0.21
A65: 淨利（non-GAAP） | B65: US$B | C65: =a25_ni -> 3.806 | D65: =a26_ni -> 5.224907 | E65: =(E61+E63)*(1-E64) -> 6.5461564 | F65: =(F61+F63)*(1-F64) -> 6.968224 | G65: =(G61+G63)*(1-G64) -> 7.4571858
A66: 稀釋股數 | B66: 十億股 | C66: =a25_sh -> 1.2757 | D66: =a26_sh -> 1.27595 | E66: =D66*(1+sh_g) -> 1.27595 | F66: =E66*(1+sh_g) -> 1.27595 | G66: =F66*(1+sh_g) -> 1.27595
A67: EPS（non-GAAP） | B67: US$ | C67: =C65/C66 -> 2.9834601 | D67: =D65/D66 -> 4.0949152 | E67: =E65/E66 -> 5.1304176 | F67: =F65/F66 -> 5.4612046 | G67: =G65/G66 -> 5.8444185
A68: EPS 年增 | B68: % | D68: =D67/C67-1 -> 0.37253896 | E68: =E67/D67-1 -> 0.25287519 | F68: =F67/E67-1 -> 0.064475644 | G68: =G67/F67-1 -> 0.070170224
A71: 案例區塊：份額持平（高）（情境 A）
A72: 項目 | B72: 單位 | C72: FY2025A | D72: FY2026（錨點） | E72: FY2027 | F72: FY2028 | G72: FY2029 | H72: 說明
A73: A. AI 營收（D 欄＝FY2026 校準年；E–G＝FY2027–FY2029）
A74: AI 後端 scale-out 交換器市場 × 情境顆數係數 | B74: US$B | D74: =mkt_26*1 -> 32.0719 | E74: =mkt_27*1*1 -> 61.085 | F74: =mkt_28*um28_A*1 -> 69.005 | G74: =mkt_29*um29_A*1 -> 78.48215
A75: 乙太網路占比 | B75: % | D75: =eth_26 -> 0.75 | E75: =eth_27 -> 0.8 | F75: =eth_28 -> 0.83 | G75: =eth_29 -> 0.85
A76: AI 後端乙太網路交換器市場 | B76: US$B | D76: =D74*D75 -> 24.053925 | E76: =E74*E75 -> 48.868 | F76: =F74*F75 -> 57.27415 | G76: =G74*G75 -> 66.709828
A77: Arista 有效份額（FY2026 校準）＝ AI 目標 ÷ 乙太網路市場 | B77: % | D77: =a26_ai/D76 -> 0.1455064 | H77: Derived：分子含前端與 scale-across，所以高於純後端份額；FY2027 起乘相對值
A78: 份額相對值（÷ FY2026） | B78: x | D78: =1 -> 1 | E78: =RHI_27 -> 1.05 | F78: =RHI_28 -> 1.05 | G78: =RHI_29 -> 1.05
A79: Arista 有效份額 | B79: % | D79: =$D$77*D78 -> 0.1455064 | E79: =$D$77*E78 -> 0.15278172 | F79: =$D$77*F78 -> 0.15278172 | G79: =$D$77*G78 -> 0.15278172
A80: AI 營收 | B80: US$B | C80: =a25_ai -> 1.63 | D80: =D76*D79 -> 3.5 | E80: =E76*E79 -> 7.466137 | F80: =F76*F79 -> 8.7504431 | G80: =G76*G79 -> 10.192042
A81: B. 非 AI 與合計
A82: 非 AI 營收 | B82: US$B | C82: =a25_nai -> 7.3757 | D82: =a26_nai -> 9.1 | E82: =D82*(1+g_nai27) -> 10.01 | F82: =E82*(1+g_nai28) -> 10.8108 | G82: =F82*(1+g_nai29) -> 11.459448
A83: 營收 | B83: US$B | C83: =a25_rev -> 9.0057 | D83: =D80+D82 -> 12.6 | E83: =E80+E82 -> 17.476137 | F83: =F80+F82 -> 19.561243 | G83: =G80+G82 -> 21.65149
A84: 營收年增 | B84: % | D84: =D83/C83-1 -> 0.39911389 | E84: =E83/D83-1 -> 0.386995 | F84: =F83/E83-1 -> 0.11931161 | G84: =G83/F83-1 -> 0.10685655
A85: AI ÷ 營收 | B85: % | C85: =C80/C83 -> 0.18099648 | D85: =D80/D83 -> 0.27777778 | E85: =E80/E83 -> 0.42721896 | F85: =F80/F83 -> 0.44733574 | G85: =G80/G83 -> 0.47073167
A86: C. 損益
A87: 非 AI 毛利率 ＝ 錨點毛利率 ＋ 差距 × AI 占比（FY2026 校準） | B87: % | D87: =a26_gp/a26_rev+d_ai*D85 -> 0.64666667 | H87: Derived：讓 FY2026 毛利率等於錨點；AI 毛利率＝非 AI − 差距。FY2027 起毛利率隨 AI 占比變動
A88: 毛利 | B88: US$B | C88: =a25_gp -> 5.8154 | D88: =a26_gp -> 7.938 | E88: =$D$87*E82+($D$87-d_ai)*E80 -> 10.853267 | F88: =$D$87*F82+($D$87-d_ai)*F80 -> 12.124577 | G88: =$D$87*G82+($D$87-d_ai)*G80 -> 13.389774
A89: 毛利率 | B89: % | C89: =C88/C83 -> 0.64574658 | D89: =D88/D83 -> 0.63 | E89: =E88/E83 -> 0.62103353 | F89: =F88/F83 -> 0.61982652 | G89: =G88/G83 -> 0.61842277
A90: 營業費用（基準路徑） | B90: US$B | C90: =a25_opx -> 1.4784 | D90: =a26_opx -> 1.827 | E90: =D90*(1+MAX(0,phi*E84)) -> 2.2158719 | F90: =E90*(1+MAX(0,phi*F84)) -> 2.3612805 | G90: =F90*(1+MAX(0,phi*G84)) -> 2.5000556
A91: 營業費用 | B91: US$B | C91: =C90 -> 1.4784 | D91: =D90 -> 1.827 | E91: =E90+0*E83 -> 2.2158719 | F91: =F90+0*F83 -> 2.3612805 | G91: =G90+0*G83 -> 2.5000556
A92: 營業利益 | B92: US$B | C92: =C88-C91 -> 4.337 | D92: =D88-D91 -> 6.111 | E92: =E88-E91 -> 8.6373951 | F92: =F88-F91 -> 9.7632968 | G92: =G88-G91 -> 10.889719
A93: 營業利益率 | B93: % | C93: =C92/C83 -> 0.48158389 | D93: =D92/D83 -> 0.485 | E93: =E92/E83 -> 0.49423938 | F93: =F92/F83 -> 0.49911433 | G93: =G92/G83 -> 0.50295471
A94: 其他收益 | B94: US$B | C94: =a25_oth -> 0.3936 | D94: =a26_oth -> 0.4999 | E94: =oth_f -> 0.55 | F94: =oth_f -> 0.55 | G94: =oth_f -> 0.55
A95: 有效稅率 | B95: % | C95: =1-a25_ni/(a25_oi+a25_oth) -> 0.19545089 | D95: =1-a26_ni/(a26_oi+a26_oth) -> 0.20965269 | E95: =tx_f -> 0.21 | F95: =tx_f -> 0.21 | G95: =tx_f -> 0.21
A96: 淨利（non-GAAP） | B96: US$B | C96: =a25_ni -> 3.806 | D96: =a26_ni -> 5.224907 | E96: =(E92+E94)*(1-E95) -> 7.2580421 | F96: =(F92+F94)*(1-F95) -> 8.1475044 | G96: =(G92+G94)*(1-G95) -> 9.0373779
A97: 稀釋股數 | B97: 十億股 | C97: =a25_sh -> 1.2757 | D97: =a26_sh -> 1.27595 | E97: =D97*(1+sh_g) -> 1.27595 | F97: =E97*(1+sh_g) -> 1.27595 | G97: =F97*(1+sh_g) -> 1.27595
A98: EPS（non-GAAP） | B98: US$ | C98: =C96/C97 -> 2.9834601 | D98: =D96/D97 -> 4.0949152 | E98: =E96/E97 -> 5.6883437 | F98: =F96/F97 -> 6.3854418 | G98: =G96/G97 -> 7.0828621
A99: EPS 年增 | B99: % | D99: =D98/C98-1 -> 0.37253896 | E99: =E98/D98-1 -> 0.3891237 | F99: =F98/E98-1 -> 0.12254851 | G99: =G98/F98-1 -> 0.10922037
A102: 案例區塊：乙太網路占比 低（情境 A）
A103: 項目 | B103: 單位 | C103: FY2025A | D103: FY2026（錨點） | E103: FY2027 | F103: FY2028 | G103: FY2029 | H103: 說明
A104: A. AI 營收（D 欄＝FY2026 校準年；E–G＝FY2027–FY2029）
A105: AI 後端 scale-out 交換器市場 × 情境顆數係數 | B105: US$B | D105: =mkt_26*1 -> 32.0719 | E105: =mkt_27*1*1 -> 61.085 | F105: =mkt_28*um28_A*1 -> 69.005 | G105: =mkt_29*um29_A*1 -> 78.48215
A106: 乙太網路占比 | B106: % | D106: =ETLO_26 -> 0.7 | E106: =ETLO_27 -> 0.72 | F106: =ETLO_28 -> 0.74 | G106: =ETLO_29 -> 0.75
A107: AI 後端乙太網路交換器市場 | B107: US$B | D107: =D105*D106 -> 22.45033 | E107: =E105*E106 -> 43.9812 | F107: =F105*F106 -> 51.0637 | G107: =G105*G106 -> 58.861612
A108: Arista 有效份額（FY2026 校準）＝ AI 目標 ÷ 乙太網路市場 | B108: % | D108: =a26_ai/D107 -> 0.15589971 | H108: Derived：分子含前端與 scale-across，所以高於純後端份額；FY2027 起乘相對值
A109: 份額相對值（÷ FY2026） | B109: x | D109: =1 -> 1 | E109: =rel_27 -> 0.95 | F109: =rel_28 -> 0.9 | G109: =rel_29 -> 0.88
A110: Arista 有效份額 | B110: % | D110: =$D$108*D109 -> 0.15589971 | E110: =$D$108*E109 -> 0.14810473 | F110: =$D$108*F109 -> 0.14030974 | G110: =$D$108*G109 -> 0.13719175
A111: AI 營收 | B111: US$B | C111: =a25_ai -> 1.63 | D111: =D107*D110 -> 3.5 | E111: =E107*E110 -> 6.5138236 | F111: =F107*F110 -> 7.1647345 | G111: =G107*G110 -> 8.0753275
A112: B. 非 AI 與合計
A113: 非 AI 營收 | B113: US$B | C113: =a25_nai -> 7.3757 | D113: =a26_nai -> 9.1 | E113: =D113*(1+g_nai27) -> 10.01 | F113: =E113*(1+g_nai28) -> 10.8108 | G113: =F113*(1+g_nai29) -> 11.459448
A114: 營收 | B114: US$B | C114: =a25_rev -> 9.0057 | D114: =D111+D113 -> 12.6 | E114: =E111+E113 -> 16.523824 | F114: =F111+F113 -> 17.975535 | G114: =G111+G113 -> 19.534775
A115: 營收年增 | B115: % | D115: =D114/C114-1 -> 0.39911389 | E115: =E114/D114-1 -> 0.31141457 | F115: =F114/E114-1 -> 0.087855629 | G115: =G114/F114-1 -> 0.086742395
A116: AI ÷ 營收 | B116: % | C116: =C111/C114 -> 0.18099648 | D116: =D111/D114 -> 0.27777778 | E116: =E111/E114 -> 0.39420801 | F116: =F111/F114 -> 0.39858256 | G116: =G111/G114 -> 0.41338215
A117: C. 損益
A118: 非 AI 毛利率 ＝ 錨點毛利率 ＋ 差距 × AI 占比（FY2026 校準） | B118: % | D118: =a26_gp/a26_rev+d_ai*D116 -> 0.64666667 | H118: Derived：讓 FY2026 毛利率等於錨點；AI 毛利率＝非 AI − 差距。FY2027 起毛利率隨 AI 占比變動
A119: 毛利 | B119: US$B | C119: =a25_gp -> 5.8154 | D119: =a26_gp -> 7.938 | E119: =$D$118*E113+($D$118-d_ai)*E111 -> 10.294577 | F119: =$D$118*F113+($D$118-d_ai)*F111 -> 11.194295 | G119: =$D$118*G113+($D$118-d_ai)*G111 -> 12.147968
A120: 毛利率 | B120: % | C120: =C119/C114 -> 0.64574658 | D120: =D119/D114 -> 0.63 | E120: =E119/E114 -> 0.62301419 | F120: =F119/F114 -> 0.62275171 | G120: =G119/G114 -> 0.62186374
A121: 營業費用（基準路徑） | B121: US$B | C121: =a25_opx -> 1.4784 | D121: =a26_opx -> 1.827 | E121: =D121*(1+MAX(0,phi*E115)) -> 2.1399249 | F121: =E121*(1+MAX(0,phi*F115)) -> 2.2433274 | G121: =F121*(1+MAX(0,phi*G115)) -> 2.3503528
...

Sheet Sources
A1: 來源（公司原文＝Arista 8-K 新聞稿，已逐份抓取；法說內容只經二手轉述）
A2: 公司：2Q26 新聞稿（含上半年合計、3Q26 指引） | B2: https://www.sec.gov/Archives/edgar/data/0001596532/000159653226000174/ex991q226-earningsrelease.htm
A3: 公司：4Q25 與 FY2025 新聞稿 | B3: https://www.businesswire.com/news/home/20260212962784/en/Arista-Networks-Inc.-Reports-Fourth-Quarter-and-Year-End-2025-Financial-Results
A4: 二手：BigGo Finance 2Q26 法說摘要（全年指引 12.6、AI 至少 3.5、scale-across 約 1.2、毛利率與營業利益率指引） | B4: https://finance.biggo.com/news/US_ANET_2026-08-04
A5: 二手：sec-api 彙整（客戶集中、遞延收入、GAAP／non-GAAP 毛利率與營業利益率） | B5: https://sec-api.io/insights/arista-networks-anet-stock-analysis-q2-2026-ai-networking-revenue-deferred-revenue-customer-concentration-insider-sales-and-scenarios-to-fy2029
A6: 二手：Next Platform（2025 營收、2025 AI 約 1.63、微軟 26%、Meta 16%） | B6: https://www.nextplatform.com/2026/02/13/the-current-ai-networking-wave-will-be-a-tsunami-of-money-by-2027/
A7: 研調：IDC 2Q26 乙太網路交換器（NVIDIA 20.4%、Arista 18.7%、Cisco 18.2%） | B7: https://www.idc.com/resource-center/blog/ethernet-switch-market-surges-43-4-to-18-9b-in-2q26-as-ai-infrastructure-demand-drives-record-datacenter-spending/
A8: 研調：Dell'Oro 2025 AI 後端（乙太網路超過 InfiniBand 兩倍；Celestica、NVIDIA 並列第一，Arista 第三） | B8: https://www.delloro.com/news/ethernet-more-than-doubles-size-of-infiniband-as-the-leading-fabric-for-ai-scale-out-networks-in-2025/
A9: 二手：StockAnalysis 現價、前瞻 P/E、2026 共識 | B9: https://stockanalysis.com/stocks/anet/forecast/
A10: 二手：MarketBeat（Erste FY2027 EPS 4.79） | B10: https://www.marketbeat.com/instant-alerts/estimates-fy2027-eps-forecast-for-arista-networks-increased-by-analyst-2026-10-23/
A11: 資料商：companiesmarketcap 年底 P/E | B11: https://companiesmarketcap.com/arista-networks/pe-ratio/
A12: 資料商：Macrotrends 季度 P/E（至 2024-04） | B12: https://www.macrotrends.net/stocks/charts/ANET/arista-networks/pe-ratio
A13: 市場層：markets/network、tsmc 成品（本 repo，唯讀）
A14: 待補（人工）：2027 共識（付費）；各季 AI 營收；產品別毛利率；前瞻 P/E 十年歷史（Bloomberg）；重編後 FY2025 non-GAAP 淨利 | B14: 未找到
A15: SemiAnalysis | B15: 未使用
