Workbook

Sheet README
A1: Arista Networks（ANET）收支與估值模型 v0.2.1（AI 半導體 Project：網通系統端樣板） 2026-10-25
A2: 版本：v0.2.1（2026-10-25：補上檔空間級距、投資建議、重點觀察，數值不變）；v0.1（初版）。Arista 在 AI 後端乙太網路交換器的份額在本模型 Units 頁建立，為本專案權威資料（規則第 13 條）。
A3: 模型命題：Arista 的 AI 營收＝AI 後端 scale-out 交換器市場（本專案網通模型）× 乙太網路占比 × Arista 份額（含前端與 scale-across 附掛）；非 AI（雲端前端、企業、園區）另依成長率推。股價約 37 倍前瞻 EPS：在 NVIDIA（Spectrum-X）與白牌夾擊下，Arista 的份額路徑能否支撐這個倍數？
A4: 核心問題：2027–28 年 Arista 在 AI 乙太網路的份額每掉一截，EPS 少多少；現價隱含的份額路徑合不合理。
A6: 會計年度＝日曆年，FY(t)＝CY(t)，不平移。預測期 FY2027–FY2029（三年）。口徑：公司 non-GAAP；十年 P/E 規則值用 GAAP 換算 EPS。
A8: 驅動因子 → 推導量（全部唯讀上游，不修改）
A9: AI 營收：markets/network 的 AI 後端 scale-out 交換器市場 × 情境顆數係數 × 乙太網路占比（Assumed）× Arista 有效份額（FY2026 以公司 AI 目標 3.5 校準）× 份額相對值（Assumed）。
A10: 非 AI 營收：FY2026 錨點（營收指引 − AI 目標）× Assumed 成長率。毛利率：AI 比非 AI 低 d_ai（Assumed），非 AI 毛利率為 FY2026 殘差（Derived）。營業費用：彈性 phi（Derived）。
A11: 校準：FY2026 ＝ 1Q–2Q 實績＋3Q 指引＋全年指引（營收 12.6、毛利率 63%、營業利益率 48.5%）。不用共識（只在 Recon 對帳）。
A12: 估值：現價 ÷ FY2027、FY2028 EPS；十年 GAAP P/E 規則值（兩個資料商來源）× FY2027 GAAP 換算 EPS；循環位置以本模型營收最高年判定（Arista 不套設備股見頂年）。
A13: 標記：Verified、Interested-party、Analogy、Assumed、Derived。SemiAnalysis 未使用。公司原文＝SEC EDGAR 8-K；法說內容只經二手轉述（標二手）。
A15: 已知限制：(1) 份額相對值與乙太網路占比皆為 Assumed，是 FY2028 EPS 最敏感的輸入（Sens）；(2) FY2026 AI 用公司目標「至少 3.5」，實際可能較高；(3) 網通模型 2027 年 scale-out 交換器 +90%，公司稱供給吃緊到 2028 年，模型未設供給上限（Sens 用市場 ×0.8）；(4) 2027 共識未找到，只有單一分析師；(5) 十年 P/E 含高成長期溢價；(6) R4 產業部署路徑未建（Recon 預留列）。
... A19: v0.2.1（2026-10-25）：補上檔空間級距、投資建議、重點觀察（Val 頁 0.3 結論加「上檔空間級距」「投資建議」兩列、README 頁加重點觀察三點；數值不變，既有儲存格位置不變）。另在 PL 頁末新增「自由現金流（淨利＋折舊 − 資本支出；不含營運資金變動）」三情境列（FY2025A–FY2032；算力收支 2026-10-25 請求），In 頁末新增 fcf_da、fcf_capex（FY2025 10-K 比率 0.81%、1.33%）。
A20: ="投資建議："&Val!B53&"（依上檔空間固定規則）" -> 投資建議：中立（依上檔空間固定規則）
A21: ="重點觀察 1：目標價 US$"&TEXT(Val!$B$40,"#,##0.00")&"（DCF "&TEXT(Val!$B$23,"#,##0.00")&"、Comparable（相對倍數調整後）"&TEXT(tp_comp_adj,"#,##0.00")&"；DCF 權重 "&TEXT(tp_w_dcf,"0%")&"），比現價 "&TEXT(px,"#,##0.00")&"（2026-10-23）"&IF(Val!$B$43>=0,"高 "&TEXT(Val!$B$43,"0.0%"),"低 "&TEXT(-Val!$B$43,"0.0%"))&"，級距 "&Val!$B$52&"、投資建議 "&Val!$B$53&"。相對倍數調整係數 "&TEXT(rm_factor,"0.00")&"（本公司 10 年前瞻倍數中位數 ÷ 同業的中位數，夾在 0.5–2.0；Val 第 0.5 節），調整前加權上檔空間 "&TEXT((tp_w_dcf*Val!$B$23+(1-tp_w_dcf)*Val!$B$36)/px-1,"+0.0%;−0.0%")&"；Comparable 單獨（市場主流同業法、未調整）為 "&TEXT(Val!$B$44,"+0.0%;−0.0%")&"。"&"以下為 2026-10-29 相對倍數調整前撰寫的說明，其中數字為調整前：主因是倍數不是 EPS：本模型 12 個月後前瞻 EPS 5.53 比共識前瞻 EPS 4.65 高 12.6%（期間差約一年），但同業（Cisco、Ciena、Celestica、HPE、Credo）前瞻 P/E 中位數 20.2 倍，現價隱含 37.1 倍、共識目標價 243.59 隱含 52.4 倍（比同業高 159%"&"）；市場給 Arista 的 AI 乙太網路份額與高毛利溢價，Comparable 未計入。DCF 87.2 更低，因 ROE 雖有 28.6%，B 情境 FY2028 EPS 5.51 幾乎不成長（+0.8%）。" -> 重點觀察 1：目標價 US$155.30（DCF 87.24、Comparable（相對倍數調整後）223.36；DCF 權重 50%），比現價 172.37（2026-10-23）低 9.9%，級距 0%～−25%、投資建議 中立。相對倍數調整係數 2.00（本公司 10 年前瞻倍數中位數 ÷ 同業的中位數，夾在 0.5–2.0；Val 第 0.5 節），調整前加權上檔空間 −42.3%；Comparable 單獨（市場主流同業法、未調整）為 −35.2%。以下為 2026-10-29 相對倍數調整前撰寫的說明，其中數字為調整前：主因是倍數不是 EPS：本模型 12 個月後前瞻 EPS 5.53 比共識前瞻 EPS 4.65 高 12.6%（期間差約一年），但同業（Cisco、Ciena、Celestica、HPE、Credo）前瞻 P/E 中位數 20.2 倍，現價隱含 37.1 倍、共識目標價 243.59 隱含 52.4 倍（比同業高 159%）；市場給 Arista 的 AI 乙太網路份額與高毛利溢價，Comparable 未計入。DCF 87.2 更低，因 ROE 雖有 28.6%，B 情境 FY2028 EPS 5.51 幾乎不成長（+0.8%）。
A22: 重點觀察 2：最敏感的是份額與市場量：份額相對值降到 0.80／0.70 時 FY2028 EPS −8.8%，AI scale-out 交換器市場 ×0.8 時 −7.9%；情境 C（CY2028–29 顆數 ×0.6）FY2028 EPS 4.97，比情境 A 的 5.99 低 17.1%，營收在 FY2027 見頂。追蹤 3Q26 財報（2026-11-03）的 AI 營收（FY2026 目標至少 35 億美元）與 2027 年指引。
A23: 重點觀察 3：以歷史看不貴：現價 ÷ FY2028 EPS 為 28.8／31.3／34.7 倍（A／B／C），在 2016–2025 年底 P/E 的 24%～33% 分位；目標價偏低是因 Comparable 同業成長較低。DCF 權重改 0.3／0.7 時加權目標價 104.4／94.6（±4.9%）、折現率 ±1pt 時 −5.9%／+8.3%，都不改變放空級距。
A25: 2026-10-29：加權目標價中的 Comparable 改用相對倍數調整後的值（Val 第 0.5 節：同業前瞻倍數中位數 × 本公司 10 年相對同業的倍數比，Bloomberg 前瞻倍數；Andy 2026-10-27「照建議做」、10-29 資料取回）。「Comparable 目標價（市場主流同業法）」維持不調整。重點觀察 1 的第一句已改為公式；重點觀察 2、3 與其他說明中的目標價與上檔空間數字為調整前撰寫，以 Val 頁為準。
A27: v0.3.1（2026-10-30）：依個股模型原則第 8 節調整 In 頁呈現（數值不變）。In 頁 D／F 欄名改「敏感度低」「敏感度高」（只用於 Sens 頁、不進目標價）；In 頁最後新增「情境驅動對照」一節，把上方各情境專屬輸入三情境並排（只引用上方各列，純展示）；HTML 驅動因子一節分「情境驅動」與「單一參數」兩張表。

Sheet In
A1: In — 輸入（藍字；基準欄 E，低 D、高 F）。金額：十億美元（US$B）；比例：%。每個輸入附兩個來源（找不到者寫「未找到」）；公司原文算一個。【v0.3.1】基準欄 E 進主模型；D／F＝敏感度低／高，只用於 Sens 頁（一次動一個參數）、不進目標價；情境 A／B／C 的驅動見本頁最後一節「情境驅動對照」。
A2: 標記：Verified／Interested-party／Analogy／Assumed／Derived；Analogy、Assumed 給低／高區間。SemiAnalysis 未使用。公司原文＝Arista 8-K 新聞稿（SEC EDGAR）；公司的 AI 營收目標與全年指引為 Interested-party
A3: 鍵 | B3: 項目 | C3: 單位 | D3: 敏感度低 | E3: 基準 | F3: 敏感度高 | G3: 標記 | H3: 來源1 | I3: 來源2／說明
A4: A. AI 後端 scale-out 交換器市場（讀 markets/network 成品；情境 A 基準，B／C 依顆數係數縮放）
A5: mkt_26 | B5: AI 後端 scale-out 交換器市場 2026 | C5: US$B | E5: 32.0719 | G5: Derived | H5: markets/network/dist/20261026_AI網通市場模型_v0.2.3.xlsx｜Mkt!C7:F7 | I5: 加速器顆數 × 每顆 scale-out 交換器內容（不分乙太網路與 InfiniBand）；只含 AI 後端
A6: mkt_27 | B6: AI 後端 scale-out 交換器市場 2027 | C6: US$B | E6: 61.085 | G6: Derived | H6: markets/network/dist/20261026_AI網通市場模型_v0.2.3.xlsx｜Mkt!C7:F7 | I6: 同上
A7: mkt_28 | B7: AI 後端 scale-out 交換器市場 2028 | C7: US$B | E7: 69.005 | G7: Derived | H7: markets/network/dist/20261026_AI網通市場模型_v0.2.3.xlsx｜Mkt!C7:F7 | I7: 同上
A8: mkt_29 | B8: AI 後端 scale-out 交換器市場 2029 | C8: US$B | E8: 78.48215 | G8: Derived | H8: markets/network/dist/20261026_AI網通市場模型_v0.2.3.xlsx｜Mkt!C7:F7 | I8: 同上
A9: itc_26 | B9: AI IT 資本支出 2026 | C9: US$B | E9: 781.87292 | G9: Derived | H9: markets/network/dist/20261026_AI網通市場模型_v0.2.3.xlsx｜Mkt!C27:F27 | I9: Recon 用：Arista AI 營收 ÷ AI IT 資本支出
A10: itc_27 | B10: AI IT 資本支出 2027 | C10: US$B | E10: 1565.35 | G10: Derived | H10: markets/network/dist/20261026_AI網通市場模型_v0.2.3.xlsx｜Mkt!C27:F27 | I10: 同上
A11: itc_28 | B11: AI IT 資本支出 2028 | C11: US$B | E11: 1984.2639 | G11: Derived | H11: markets/network/dist/20261026_AI網通市場模型_v0.2.3.xlsx｜Mkt!C27:F27 | I11: 同上
A12: itc_29 | B12: AI IT 資本支出 2029 | C12: US$B | E12: 2260.3903 | G12: Derived | H12: markets/network/dist/20261026_AI網通市場模型_v0.2.3.xlsx｜Mkt!C27:F27 | I12: 同上
A13: um28_A | B13: 情境 A：2028 顆數 ÷ 基準 | C13: x | E13: 1 | G13: Assumed | H13: tsmc/dist/20261030_台積電個股模型_v0.4.1.xlsx｜In!E37 | I13: A＝基準；B＝AI 資本支出消化；C＝明顯下修（與台積電、NVIDIA、Broadcom 模型相同）
A14: um29_A | B14: 情境 A：2029 顆數 ÷ 基準 | C14: x | E14: 1 | G14: Assumed | H14: tsmc/dist/20261030_台積電個股模型_v0.4.1.xlsx｜In!E38 | I14: 同上
A15: um28_B | B15: 情境 B：2028 顆數 ÷ 基準 | C15: x | E15: 0.8 | G15: Assumed | H15: tsmc/dist/20261030_台積電個股模型_v0.4.1.xlsx｜In!E39 | I15: A＝基準；B＝AI 資本支出消化；C＝明顯下修（與台積電、NVIDIA、Broadcom 模型相同）
A16: um29_B | B16: 情境 B：2029 顆數 ÷ 基準 | C16: x | E16: 0.85 | G16: Assumed | H16: tsmc/dist/20261030_台積電個股模型_v0.4.1.xlsx｜In!E40 | I16: 同上
... A18: um29_C | B18: 情境 C：2029 顆數 ÷ 基準 | C18: x | E18: 0.6 | G18: Assumed | H18: tsmc/dist/20261030_台積電個股模型_v0.4.1.xlsx｜In!E42 | I18: 同上
A19: B. 乙太網路占比與 Arista 份額（本專案為權威：晶片商與網通廠份額，規則第 13 條）
A20: eth_26 | B20: 乙太網路 ÷ AI 後端交換器（金額）2026 | C20: % | D20: 0.7 | E20: 0.75 | F20: 0.8 | G20: Assumed | H20: Dell'Oro 2026-03-10：2025 年乙太網路占 AI 叢集交換器三分之二以上、為 InfiniBand 兩倍以上（Interested-party） | I20: IDC 2Q26：NVIDIA 資料中心乙太網路年增 181%（乙太網路取代 InfiniBand 的方向）
A21: eth_27 | B21: 乙太網路 ÷ AI 後端交換器 2027 | C21: % | D21: 0.72 | E21: 0.8 | F21: 0.88 | G21: Assumed | H21: 同上；2027 年無公開預測：未找到 | I21: 外推（Assumed）
A22: eth_28 | B22: 乙太網路 ÷ AI 後端交換器 2028 | C22: % | D22: 0.74 | E22: 0.83 | F22: 0.9 | G22: Assumed | H22: 同上 | I22: —
A23: eth_29 | B23: 乙太網路 ÷ AI 後端交換器 2029 | C23: % | D23: 0.75 | E23: 0.85 | F23: 0.92 | G23: Assumed | H23: 同上 | I23: —
A24: rel_27 | B24: Arista 份額 2027 ÷ 2026（相對值） | C24: x | D24: 0.8 | E24: 0.95 | F24: 1.05 | G24: Assumed | H24: IDC 2Q26：NVIDIA 20.4% 已超過 Arista 18.7%（資料中心乙太網路，全部速率；Interested-party） | I24: Dell'Oro 2025 AI 後端乙太網路：Celestica（白牌）與 NVIDIA 並列第一、合計約 50%，Arista 第三（Interested-party）
A25: rel_28 | B25: Arista 份額 2028 ÷ 2026 | C25: x | D25: 0.7 | E25: 0.9 | F25: 1.05 | G25: Assumed | H25: 同上 | I25: —
A26: rel_29 | B26: Arista 份額 2029 ÷ 2026 | C26: x | D26: 0.65 | E26: 0.88 | F26: 1.05 | G26: Assumed | H26: 同上 | I26: —
A27: C. 非 AI 營收（雲端前端、企業、園區、服務）
A28: g_nai27 | B28: 非 AI 營收年增 2027 | C28: % | D28: 0.03 | E28: 0.1 | F28: 0.15 | G28: Assumed | H28: 2026 錨點非 AI 約 9.1（營收指引 12.6 − AI 目標 3.5）；2025 約 7.4（9.0 − AI 約 1.63）→ 2026 約 +23%（Derived，含記憶體缺貨下的提前拉貨可能） | I28: 園區目標 2026 至少 1.25（公司，Interested-party）
A29: svc25 | B29: FY2025 服務營收 | C29: US$B | E29: 1.4288 | G29: Verified | H29: Arista 4Q25 新聞稿（2026-02-12）：FY2025 Product 7,576.9、Service 1,428.8（US$M） | I29: 分部原則：單一分部，公司固定揭露產品／服務兩條營收線
A30: g_svc26 | B30: 服務營收年增 2026 | C30: % | D30: 0.15 | E30: 0.22 | F30: 0.28 | G30: Assumed | H30: FY2025 +27.7%（1,119.1 → 1,428.8；Arista 新聞稿）；服務隨裝機量與維護合約遞延認列 | I30: 非 AI 產品＝非 AI − 服務（差額）
A31: g_svc27 | B31: 服務營收年增 2027 | C31: % | D31: 0.1 | E31: 0.15 | F31: 0.2 | G31: Assumed | H31: FY2025 +27.7%（1,119.1 → 1,428.8；Arista 新聞稿）；服務隨裝機量與維護合約遞延認列 | I31: 非 AI 產品＝非 AI − 服務（差額）
A32: g_svc28 | B32: 服務營收年增 2028 | C32: % | D32: 0.06 | E32: 0.1 | F32: 0.15 | G32: Assumed | H32: FY2025 +27.7%（1,119.1 → 1,428.8；Arista 新聞稿）；服務隨裝機量與維護合約遞延認列 | I32: 非 AI 產品＝非 AI − 服務（差額）
A33: g_svc29 | B33: 服務營收年增 2029 | C33: % | D33: 0.05 | E33: 0.08 | F33: 0.12 | G33: Assumed | H33: FY2025 +27.7%（1,119.1 → 1,428.8；Arista 新聞稿）；服務隨裝機量與維護合約遞延認列 | I33: 非 AI 產品＝非 AI − 服務（差額）
A34: g_nai28 | B34: 非 AI 營收年增 2028 | C34: % | D34: 0.02 | E34: 0.08 | F34: 0.12 | G34: Assumed | H34: 同上 | I34: —
A35: g_nai29 | B35: 非 AI 營收年增 2029 | C35: % | D35: 0.02 | E35: 0.06 | F35: 0.1 | G35: Assumed | H35: 同上 | I35: —
A36: ai25 | B36: 2025 年 AI 營收（參考） | C36: US$B | D36: 1.5 | E36: 1.63 | F36: 1.8 | G36: Derived | H36: Next Platform 2026-02-13：以 2026 目標倒推約 1.63（公司稱超過 1.5 目標） | I36: 公司：2025 年 AI 目標 1.5 已超越（法說）
A37: D. 毛利率
A38: d_ai | B38: AI 營收毛利率低於非 AI 的幅度 | C38: pt | D38: 0.03 | E38: 0.06 | F38: 0.1 | G38: Assumed | H38: 公司：毛利率下滑來自雲端與 AI 大客戶占比（2Q26 毛利率較去年同期 −2.2 個百分點；法說，二手） | I38: 產品別毛利率未揭露：未找到
A39: E. FY2026 錨點（Q1–Q2 實績＋Q3 指引＋全年指引）
A40: fy_rev | B40: FY2026 營收指引 | C40: US$B | E40: 12.6 | G40: Interested-party | H40: 法說轉述：BigGo Finance 摘要（2026-08-04；二手）：約 $12.6B（8 月由 11.5 上修） | I40: StockAnalysis 共識 12.68（27 位）
A41: fy_gm | B41: FY2026 non-GAAP 毛利率指引（中點） | C41: % | D41: 0.62 | E41: 0.63 | F41: 0.64 | G41: Interested-party | H41: 法說轉述：BigGo Finance 摘要（2026-08-04；二手）：62–64% | I41: sec-api 彙整同值
A42: fy_oim | B42: FY2026 non-GAAP 營業利益率指引（中點） | C42: % | D42: 0.48 | E42: 0.485 | F42: 0.49 | G42: Interested-party | H42: 法說轉述：BigGo Finance 摘要（2026-08-04；二手）：48–49% | I42: sec-api 彙整同值
A43: q3_rev | B43: 3Q26 營收指引 | C43: US$B | E43: 3.3 | G43: Interested-party | H43: https://www.sec.gov/Archives/edgar/data/0001596532/000159653226000174/ex991q226-earningsrelease.htm：約 $3.3B | I43: BigGo（二手）同值
A44: q3_gm | B44: 3Q26 non-GAAP 毛利率指引 | C44: % | D44: 0.62 | E44: 0.63 | F44: 0.64 | G44: Interested-party | H44: 法說轉述：BigGo Finance 摘要（2026-08-04；二手）：約 63% | I44: 第二來源：未找到
A45: q3_oim | B45: 3Q26 non-GAAP 營業利益率指引（中點） | C45: % | D45: 0.48 | E45: 0.485 | F45: 0.49 | G45: Interested-party | H45: https://www.sec.gov/Archives/edgar/data/0001596532/000159653226000174/ex991q226-earningsrelease.htm：48–49% | I45: —
A46: q_oth | B46: 3Q、4Q26 non-GAAP 其他收益（每季） | C46: US$B | D46: 0.12 | E46: 0.13 | F46: 0.14 | G46: Derived | H46: 1Q26 0.1136、2Q26 0.1263（公司，GAAP 其他收益） | I46: 現金與有價證券 13.3（2026-06，公司）
A47: q_tx | B47: 3Q、4Q26 non-GAAP 有效稅率 | C47: % | D47: 0.2 | E47: 0.21 | F47: 0.22 | G47: Derived | H47: 2Q26：1 − 1301.7 ÷（1513.7＋126.3）＝20.6%；1Q26 21.3%（推導） | I47: 3Q26 EPS 指引 1.06–1.08 隱含約 21%（推導）
A48: q_sh | B48: 3Q、4Q26 稀釋股數 | C48: 十億股 | E48: 1.277 | G48: Derived | H48: 2Q26 1.2760（公司） | I48: —
A49: ai26 | B49: FY2026 AI 營收（公司目標「至少」） | C49: US$B | D49: 3.5 | E49: 3.5 | F49: 4 | G49: Interested-party | H49: 法說轉述：BigGo Finance 摘要（2026-08-04；二手）：AI 至少 $3.5B（2 月 3.25、8 月 3.5）；其中 scale-across 約 1.2 | I49: sec-api 彙整：至少 $3.50B（2026-08-04 法說）
A50: F. 營業費用、其他收益、稅、股數（FY2027 起）
A51: phi | B51: 營業費用成長對營收成長的彈性 | C51: x | D51: 0.4 | E51: 0.55 | F51: 0.8 | G51: Derived | H51: FY2026 錨點營業費用年增 ÷ 營收年增（Q 頁） | I51: 低／高 Assumed
A52: opx_adj | B52: 營業費用額外占營收比（Sens 用；基準 0） | C52: pt | D52: -0.02 | E52: 0 | F52: 0.02 | G52: Assumed | H52: 無 | I52: Sens 用 ±2 個百分點
A53: oth_f | B53: non-GAAP 其他收益（每年） | C53: US$B | D53: 0.4 | E53: 0.55 | F53: 0.7 | G53: Assumed | H53: FY2026 錨點約 0.50（Q 頁）；現金 13.3 × 約 4% | I53: —
A54: tx_f | B54: non-GAAP 有效稅率 | C54: % | D54: 0.19 | E54: 0.21 | F54: 0.22 | G54: Derived | H54: FY2025 19.5%、1H26 約 21%（推導） | I54: —
A55: sh_g | B55: 稀釋股數年變動 | C55: % | D55: -0.01 | E55: 0 | F55: 0.005 | G55: Derived | H55: FY2025 1.2757 → 2Q26 1.2760（公司）：買回大致抵銷股票薪酬 | I55: 低／高 Assumed
A56: mf | B56: AI 市場係數（Sens 用；FY2027 起） | C56: x | D56: 0.8 | E56: 1 | F56: 1.2 | G56: Assumed | H56: 網通模型 2027 年 scale-out 交換器 +90%；公司稱供給吃緊是「兩年的問題」、2028 年才解除（法說，二手） | I56: ±20%
A57: G. 共識、市場資料（只作 Recon 對帳，不作校準）
A58: cons_rev26 | B58: 共識 FY2026 營收 | C58: US$B | E58: 12.68 | G58: Interested-party | H58: StockAnalysis（27 位，2026-10-23） | I58: MarketBeat：FY2026 EPS 共識 3.79（口徑可能為 GAAP 或舊值）
A59: cons_eps26 | B59: 共識 FY2026 non-GAAP EPS | C59: US$ | E59: 4.12 | G59: Interested-party | H59: StockAnalysis（區間 4.05–4.22） | I59: —
A60: erste_eps27 | B60: Erste Group FY2027 EPS（單一分析師） | C60: US$ | E60: 4.79 | G60: Interested-party | H60: MarketBeat 2026-10-23（10-21 由 4.74 上調） | I60: 2027 共識（StockAnalysis 付費）：未找到
A61: dell_top2 | B61: 2025 AI 後端乙太網路：Celestica＋NVIDIA 合計份額 | C61: % | E61: 0.5 | G61: Interested-party | H61: Dell'Oro 2026-03-10：兩家並列第一、合計約 50%；Arista 第三 | I61: —
A62: idc_anet | B62: 2Q26 資料中心乙太網路交換器：Arista 份額（全部速率） | C62: % | E62: 0.187 | G62: Interested-party | H62: IDC 2026-09-11 | I62: NVIDIA 20.4%、Cisco 18.2%
A63: pe_fair_andy | B63: Andy 先驗：合理 P/E | C63: x | E63: 25 | G63: Assumed | H63: 先驗_Andy_Arista_20261024 A9b（Drive；不在本 repo） | I63: 只作對照
A64: H. 價格與估值
A65: px | B65: 股價（2026-10-23 收盤） | C65: US$ | E65: 172.37 | G65: Interested-party | H65: StockAnalysis（2026-10-23 收盤） | I65: markets/invest_map/data/prices.csv 同值（stockscan；bullfincher 兩來源核對）；MarketBeat：10-23 開盤 170.57
A66: pe_ttm_gaap | B66: 近 12 月 GAAP P/E | C66: x | E66: 54.55 | G66: Interested-party | H66: StockAnalysis | I66: MarketBeat 53.81
A67: pe_fwd_sa | B67: 前瞻 P/E（StockAnalysis） | C67: x | E67: 37.06 | G67: Interested-party | H67: StockAnalysis（口徑：未來 12 個月 non-GAAP，頁面未明示） | I67: 第二來源：未找到
A68: g2n | B68: GAAP EPS ÷ non-GAAP EPS（規則值換算用） | C68: x | E68: =1.75/1.89 -> 0.92592593 | G68: Derived | H68: https://www.sec.gov/Archives/edgar/data/0001596532/000159653226000174/ex991q226-earningsrelease.htm：1H26 GAAP 稀釋 EPS 1.75、non-GAAP 1.89 | I68: FY2025：2.75 ÷ 2.98＝0.923（公司）
A69: I. 目標價情境權重（v0.1.1 新增；Val 頁第 0 節用）
A70: tp_wA | B70: 目標價情境權重 A | C70: % | E70: 0.3 | G70: Assumed | H70: Andy 可改（工作單 2026-10-25 預設 A 0.3／B 0.5／C 0.2） | I70: 三者合計應為 100%（Val 頁第 0 節列示）
A71: tp_wB | B71: 目標價情境權重 B | C71: % | E71: 0.5 | G71: Assumed | H71: Andy 可改（工作單 2026-10-25 預設 A 0.3／B 0.5／C 0.2） | I71: 三者合計應為 100%（Val 頁第 0 節列示）
A72: tp_wC | B72: 目標價情境權重 C | C72: % | E72: 0.2 | G72: Assumed | H72: Andy 可改（工作單 2026-10-25 預設 A 0.3／B 0.5／C 0.2） | I72: 三者合計應為 100%（Val 頁第 0 節列示）
A73: J. 目標價參數（v0.2 新增：DCF 與 Comparable 加權、FY2029 後收斂法；黃底＝Andy 可改）
A74: tp_r | B74: DCF 折現率（股東權益成本） | C74: % | E74: 0.1 | G74: Assumed | H74: Andy 可改（工作單 2026-10-25：美、台、日、韓同一值） | I74: Sens 頁 ±1pt
A75: tp_g | B75: 長期成長率（FY2032 後永續；PL 延伸期 B 情境的收斂目標） | C75: % | E75: 0.04 | G75: Assumed | H75: Andy 可改（工作單 2026-10-25） | I75: Sens 頁 ±1pt（只改 DCF 再投資率與永續成長，不改 PL 收斂路徑）
A76: tp_gd | B76: 延伸期 A／C 情境長期成長相對 tp_g 的差（A＋、C−） | C76: pt | E76: 0.02 | G76: Assumed | H76: 工作單 2026-10-25：A＝tp_g＋2pt、C＝tp_g−2pt | I76: —
A77: tp_roe | B77: 近三年平均 ROE（再投資率＝tp_g ÷ tp_roe） | C77: % | E77: 0.2861 | G77: Derived | H77: stockalarm.io ANET ROE（GAAP，年度）：2023 28.91%、2024 28.54%、2025 28.39%，平均 28.61%（資料商，Interested-party） | I77: stockanalysis 近 12 月 ROE 31.48%；OpenCapital 季度 31.4–33.6%
A78: tp_w_dcf | B78: 目標價中 DCF 的權重（其餘為 Comparable） | C78: % | E78: 0.5 | G78: Assumed | H78: Andy 可改（Andy 2026-10-25 11:53 定 50／50） | I78: Sens 頁 0.3／0.7
A79: nm10_k | B79: 延伸期 C 情境淨利率目標＝FY2029 淨利率 × 本係數（同口徑十年平均未找到） | C79: x | E79: 0.8 | G79: Assumed | H79: 工作單：找不到十年平均用最後一年 × 0.8。本模型為 non-GAAP 口徑；同口徑十年淨利率：未找到 | I79: 參考：GAAP 十年平均 29.51%（valueinvesting.io 2016–2025：16.31%、25.71%、15.25%、35.67%、27.38%、28.52%、30.87%、35.62%、40.73%、38.99%）
A80: cons_tp | B80: 市場共識目標價（賣方平均） | C80: US$ | E80: 243.59 | G80: Interested-party | H80: stockanalysis.com（32 位分析師平均，2026-10-23） | I80: 賣方有目標價誘因；只作對照，不進目標價
A81: fcf_da | B81: 折舊 ÷ 營收（自由現金流用；各年營收 × 比率） | C81: % | E81: =72.6/9006 -> 0.0080612925 | G81: Assumed | H81: FY2025 10-K：折舊與攤銷 72.6 百萬美元 ÷ 營收 9,006 百萬美元（Verified） | I81: FY2026 起沿用最近一個完整年度（FY2025）年報比率（Assumed）；只用於 PL 頁自由現金流列，不進 EPS 與目標價
A82: fcf_capex | B82: 資本支出 ÷ 營收（自由現金流用；各年營收 × 比率） | C82: % | E82: =119.5/9006 -> 0.013268932 | G82: Assumed | H82: FY2025 10-K：購置不動產、設備與無形資產 119.5 百萬美元 ÷ 營收 9,006 百萬美元（Verified） | I82: FY2026 起沿用最近一個完整年度（FY2025）年報比率（Assumed）；只用於 PL 頁自由現金流列，不進 EPS 與目標價
A84: 情境驅動對照（三情境並排，進主模型的加權目標價；本節只引用上方各列，修改請改上方藍字。上方「敏感度低／高」欄只用於 Sens 頁，不進目標價）
A85: 鍵 | B85: 項目 | C85: 單位 | D85: 情境 A（樂觀） | E85: 情境 B（基準） | F85: 情境 C（保守） | G85: 標記 | H85: 說明
A86: scn_um28 | B86: 2028 顆數 ÷ 基準 | C86: x | D86: =E13 -> 1 | E86: =E15 -> 0.8 | F86: =E17 -> 0.6 | G86: Derived | H86: 引用 In 頁 um28_A／um28_B／um28_C；修改請改上方藍字
A87: scn_um29 | B87: 2029 顆數 ÷ 基準 | C87: x | D87: =E14 -> 1 | E87: =E16 -> 0.85 | F87: =E18 -> 0.6 | G87: Derived | H87: 引用 In 頁 um29_A／um29_B／um29_C；修改請改上方藍字
A88: scn_w | B88: 情境權重 | C88: % | D88: =E70 -> 0.3 | E88: =E71 -> 0.5 | F88: =E72 -> 0.2 | G88: Derived | H88: 引用 In 頁 tp_wA／tp_wB／tp_wC；修改請改上方藍字

Sheet Q
A1: Q — 實績（十億美元；EPS 為美元；股數為十億股）。口徑：公司 non-GAAP。藍字＝輸入；黑字＝公式。實績取自 Arista 8-K 新聞稿（SEC EDGAR、Business Wire）
A2: FY2026 錨點＝1Q26、2Q26 實績＋3Q26 指引＋4Q26（＝全年指引 − 前三季；毛利率、營業利益率同法）。1Q26＝上半年合計 − 2Q26。FY2025 non-GAAP 淨利與 EPS 為 2025 年度新聞稿原報值；公司 2026 年起改 non-GAAP 稅額方法並重編 2025 年各季，重編後的全年值：未找到
A3: 項目 | B3: FY2025A | C3: 1Q26 | D3: 2Q26 | E3: 3Q26（指引） | F3: 4Q26（全年指引 − 前三季） | G3: FY2026 錨點 | H3: 標記 | I3: 來源1（公司） | J3: 來源2／說明
A4: 營收 | B4: 9.0057 | C4: =5.7447-D4 -> 2.709 | D4: 3.0357 | E4: =q3_rev -> 3.3 | F4: =fy_rev-C4-D4-E4 -> 3.5553 | G4: =SUM(C4:F4) -> 12.6 | H4: Verified／Interested-party（3Q、4Q 指引） | I4: FY2025：https://www.businesswire.com/news/home/20260212962784/en/Arista-Networks-Inc.-Reports-Fourth-Quarter-and-Year-End-2025-Financial-Results；1Q26、2Q26：https://www.sec.gov/Archives/edgar/data/0001596532/000159653226000174/ex991q226-earningsrelease.htm（2Q26 與上半年合計） | J4: 1Q26＝上半年 − 2Q26；交叉：sec-api 彙整的 GAAP、non-GAAP 毛利率與營業利益率同值
A5: non-GAAP 毛利 | B5: 5.8154 | C5: =3.6155-D5 -> 1.6908 | D5: 1.9247 | E5: =E4*q3_gm -> 2.079 | F5: =fy_rev*fy_gm-C5-D5-E5 -> 2.2435 | G5: =SUM(C5:F5) -> 7.938 | H5: Verified／Interested-party | I5: FY2025：https://www.businesswire.com/news/home/20260212962784/en/Arista-Networks-Inc.-Reports-Fourth-Quarter-and-Year-End-2025-Financial-Results；1Q26、2Q26：https://www.sec.gov/Archives/edgar/data/0001596532/000159653226000174/ex991q226-earningsrelease.htm（2Q26 與上半年合計） | J5: 1Q26＝上半年 − 2Q26；交叉：sec-api 彙整的 GAAP、non-GAAP 毛利率與營業利益率同值
A6: 毛利率 | B6: =B5/B4 -> 0.64574658 | C6: =C5/C4 -> 0.62414175 | D6: =D5/D4 -> 0.63402181 | E6: =E5/E4 -> 0.63 | F6: =F5/F4 -> 0.63102973 | G6: =G5/G4 -> 0.63 | H6: Derived | I6: — | J6: FY2025 64.6%；FY2026 指引 62–64%
A7: non-GAAP 營業費用 | B7: =B5-B8 -> 1.4784 | C7: =C5-C8 -> 0.3968 | D7: =D5-D8 -> 0.411 | E7: =E5-E8 -> 0.4785 | F7: =F5-F8 -> 0.5407 | G7: =SUM(C7:F7) -> 1.827 | H7: Derived（毛利 − 營業利益） | I7: FY2025：https://www.businesswire.com/news/home/20260212962784/en/Arista-Networks-Inc.-Reports-Fourth-Quarter-and-Year-End-2025-Financial-Results；1Q26、2Q26：https://www.sec.gov/Archives/edgar/data/0001596532/000159653226000174/ex991q226-earningsrelease.htm（2Q26 與上半年合計） | J7: 1Q26＝上半年 − 2Q26；交叉：sec-api 彙整的 GAAP、non-GAAP 毛利率與營業利益率同值
A8: non-GAAP 營業利益 | B8: 4.337 | C8: =2.8077-D8 -> 1.294 | D8: 1.5137 | E8: =E4*q3_oim -> 1.6005 | F8: =fy_rev*fy_oim-C8-D8-E8 -> 1.7028 | G8: =SUM(C8:F8) -> 6.111 | H8: Verified／Interested-party | I8: FY2025：https://www.businesswire.com/news/home/20260212962784/en/Arista-Networks-Inc.-Reports-Fourth-Quarter-and-Year-End-2025-Financial-Results；1Q26、2Q26：https://www.sec.gov/Archives/edgar/data/0001596532/000159653226000174/ex991q226-earningsrelease.htm（2Q26 與上半年合計） | J8: 1Q26＝上半年 − 2Q26；交叉：sec-api 彙整的 GAAP、non-GAAP 毛利率與營業利益率同值
A9: 營業利益率 | B9: =B8/B4 -> 0.48158389 | C9: =C8/C4 -> 0.47766704 | D9: =D8/D4 -> 0.49863293 | E9: =E8/E4 -> 0.485 | F9: =F8/F4 -> 0.47894692 | G9: =G8/G4 -> 0.485 | H9: Derived | I9: — | J9: —
A10: 其他收益（GAAP，non-GAAP 沿用） | B10: 0.3936 | C10: =0.2399-D10 -> 0.1136 | D10: 0.1263 | E10: =q_oth -> 0.13 | F10: =q_oth -> 0.13 | G10: =SUM(C10:F10) -> 0.4999 | H10: Verified／Derived（3Q、4Q） | I10: FY2025：https://www.businesswire.com/news/home/20260212962784/en/Arista-Networks-Inc.-Reports-Fourth-Quarter-and-Year-End-2025-Financial-Results；1Q26、2Q26：https://www.sec.gov/Archives/edgar/data/0001596532/000159653226000174/ex991q226-earningsrelease.htm（2Q26 與上半年合計） | J10: 1Q26＝上半年 − 2Q26；交叉：sec-api 彙整的 GAAP、non-GAAP 毛利率與營業利益率同值
A11: 稅前利益 | B11: =B8+B10 -> 4.7306 | C11: =C8+C10 -> 1.4076 | D11: =D8+D10 -> 1.64 | E11: =E8+E10 -> 1.7305 | F11: =F8+F10 -> 1.8328 | G11: =SUM(C11:F11) -> 6.6109 | H11: Derived | I11: FY2025：https://www.businesswire.com/news/home/20260212962784/en/Arista-Networks-Inc.-Reports-Fourth-Quarter-and-Year-End-2025-Financial-Results；1Q26、2Q26：https://www.sec.gov/Archives/edgar/data/0001596532/000159653226000174/ex991q226-earningsrelease.htm（2Q26 與上半年合計） | J11: 1Q26＝上半年 − 2Q26；交叉：sec-api 彙整的 GAAP、non-GAAP 毛利率與營業利益率同值
A12: non-GAAP 淨利 | B12: 3.806 | C12: =2.4099-D12 -> 1.1082 | D12: 1.3017 | E12: =E11*(1-q_tx) -> 1.367095 | F12: =F11*(1-q_tx) -> 1.447912 | G12: =SUM(C12:F12) -> 5.224907 | H12: Verified／Derived（3Q、4Q） | I12: FY2025：https://www.businesswire.com/news/home/20260212962784/en/Arista-Networks-Inc.-Reports-Fourth-Quarter-and-Year-End-2025-Financial-Results；1Q26、2Q26：https://www.sec.gov/Archives/edgar/data/0001596532/000159653226000174/ex991q226-earningsrelease.htm（2Q26 與上半年合計） | J12: 1Q26＝上半年 − 2Q26；交叉：sec-api 彙整的 GAAP、non-GAAP 毛利率與營業利益率同值
A13: 有效稅率（推導） | B13: =1-B12/B11 -> 0.19545089 | C13: =1-C12/C11 -> 0.21270247 | D13: =1-D12/D11 -> 0.20628049 | E13: =1-E12/E11 -> 0.21 | F13: =1-F12/F11 -> 0.21 | G13: =1-G12/G11 -> 0.20965269 | H13: Derived | I13: — | J13: non-GAAP 稅額未直接揭露：1 − 淨利 ÷ 稅前
A14: 稀釋股數（十億股） | B14: 1.2757 | C14: =(1.2749*2-D14) -> 1.2738 | D14: 1.276 | E14: =q_sh -> 1.277 | F14: =q_sh -> 1.277 | G14: =AVERAGE(C14:F14) -> 1.27595 | H14: Verified／Derived | I14: FY2025：https://www.businesswire.com/news/home/20260212962784/en/Arista-Networks-Inc.-Reports-Fourth-Quarter-and-Year-End-2025-Financial-Results；1Q26、2Q26：https://www.sec.gov/Archives/edgar/data/0001596532/000159653226000174/ex991q226-earningsrelease.htm（2Q26 與上半年合計） | J14: 1Q26＝上半年加權 × 2 − 2Q26（近似）
A15: non-GAAP EPS | B15: =B12/B14 -> 2.9834601 | C15: =C12/C14 -> 0.86999529 | D15: =D12/D14 -> 1.0201411 | E15: =E12/E14 -> 1.0705521 | F15: =F12/F14 -> 1.1338387 | G15: =G12/G14 -> 4.0949152 | H15: Derived | I15: 淨利 ÷ 稀釋股數 | J15: —
A16: 公司揭露 non-GAAP EPS | B16: 2.98 | D16: 1.02 | H16: Verified | I16: FY2025：https://www.businesswire.com/news/home/20260212962784/en/Arista-Networks-Inc.-Reports-Fourth-Quarter-and-Year-End-2025-Financial-Results；1Q26、2Q26：https://www.sec.gov/Archives/edgar/data/0001596532/000159653226000174/ex991q226-earningsrelease.htm（2Q26 與上半年合計） | J16: 1Q26：1.89 − 1.02＝0.87；3Q26 指引 1.06–1.08
A17: AI 營收 | B17: =ai25 -> 1.63 | G17: =ai26 -> 3.5 | H17: Derived／Interested-party | I17: FY2025：In ai25；FY2026：公司目標「至少 3.5」 | J17: 各季 AI 營收未揭露：未找到
A18: 非 AI 營收（＝營收 − AI） | B18: =B4-B17 -> 7.3757 | G18: =G4-G17 -> 9.1 | H18: Derived | I18: — | J18: —
A19: AI ÷ 營收 | B19: =B17/B4 -> 0.18099648 | G19: =G17/G4 -> 0.27777778 | H19: Derived | I19: — | J19: Andy 先驗 A2：2026 年 50%
A21: FY2026 錨點與共識的距離（參考；校準未使用共識）
A22: FY2026 營收 ÷ 共識 − 1 | B22: =G4/cons_rev26-1 -> -0.0063091483
A23: FY2026 EPS ÷ 共識 − 1 | B23: =G15/cons_eps26-1 -> -0.0060885531
A24: FY2026 營收年增 | B24: =G4/B4-1 -> 0.39911389
A25: FY2026 營業費用年增 | B25: =G7/B7-1 -> 0.23579545
A26: 營業費用彈性（營業費用年增 ÷ 營收年增；In 頁 phi 的依據） | B26: =B25/B24 -> 0.59079741
A27: 3Q26 EPS（模型）vs 公司指引中點 1.07 | B27: =E15/1.07-1 -> 0.00051595811

Sheet Units
A1: Units — Arista 在 AI 後端乙太網路交換器的份額（本專案權威，規則第 13 條）。市場取自 markets/network（只含 AI 後端 scale-out 交換器，不分協定）
A3: 項目 | B3: 單位 | C3: CY2026 | D3: CY2027 | E3: CY2028 | F3: CY2029 | G3: 說明
A4: AI 後端 scale-out 交換器市場（情境 A） | B4: US$B | C4: =PL!D63 -> 32.0719 | D4: =PL!E63 -> 61.085 | E4: =PL!F63 -> 69.005 | F4: =PL!G63 -> 78.48215 | G4: markets/network Mkt 頁
A5: 乙太網路占比 | B5: % | C5: =PL!D64 -> 0.75 | D5: =PL!E64 -> 0.8 | E5: =PL!F64 -> 0.83 | F5: =PL!G64 -> 0.85 | G5: In 頁 B 節（Assumed）
A6: AI 後端乙太網路交換器市場 | B6: US$B | C6: =PL!D65 -> 24.053925 | D6: =PL!E65 -> 48.868 | E6: =PL!F65 -> 57.27415 | F6: =PL!G65 -> 66.709828
A7: InfiniBand 等其他協定（＝市場 − 乙太網路） | B7: US$B | C7: =PL!D63-PL!D65 -> 8.017975 | D7: =PL!E63-PL!E65 -> 12.217 | E7: =PL!F63-PL!F65 -> 11.73085 | F7: =PL!G63-PL!G65 -> 11.772322 | G7: 幾乎全為 NVIDIA
A8: Arista 有效份額（含前端與 scale-across） | B8: % | C8: =PL!D68 -> 0.1455064 | D8: =PL!E68 -> 0.13823108 | E8: =PL!F68 -> 0.13095576 | F8: =PL!G68 -> 0.12804563 | G8: FY2026 以公司 AI 目標校準
A9: Arista AI 營收（情境 A） | B9: US$B | C9: =PL!D69 -> 3.5 | D9: =PL!E69 -> 6.7550764 | E9: =PL!F69 -> 7.5003798 | F9: =PL!G69 -> 8.5419019
A10: 其他廠商（NVIDIA Spectrum-X、白牌、Cisco 等）＝ 乙太網路市場 − Arista | B10: US$B | C10: =PL!D65-PL!D69 -> 20.553925 | D10: =PL!E65-PL!E69 -> 42.112924 | E10: =PL!F65-PL!F69 -> 49.77377 | F10: =PL!G65-PL!G69 -> 58.167926 | G10: 上限：Arista AI 含前端，所以此列偏低
A11: Arista AI 營收 ÷ AI IT 資本支出 | B11: % | C11: =PL!D69/itc_26 -> 0.0044764308 | D11: =PL!E69/itc_27 -> 0.0043153776 | E11: =PL!F69/itc_28 -> 0.0037799306 | F11: =PL!G69/itc_29 -> 0.00377895 | G11: markets/network 的 AI IT 資本支出（加速器 × 每顆 IT capex）
A13: 讀法：FY2026 有效份額約 15%，與 Dell'Oro「Celestica＋NVIDIA 合計約 50%、Arista 第三」相容；本模型的份額路徑（相對值）是 Assumed，是最需要每季檢查的輸入。

Sheet PL
A1: PL — Arista 損益（US$B；non-GAAP）。FY2025A 實績、FY2026 錨點（1Q–2Q 實績＋3Q 指引＋全年指引），FY2027 起為模型。FY(t)＝CY(t)。三情境各一個完整推導區塊（本頁下方），頂端為摘要。FY2026–FY2027 三情境相同（顆數係數從 CY2028 開始）
A3: 情境／項目 | B3: 單位 | C3: FY2025A | D3: FY2026（錨點） | E3: FY2027 | F3: FY2028 | G3: FY2029 | H3: 說明
A4: 情境 A
A5: 營收 | B5: US$B | C5: =C72 -> 9.0057 | D5: =D72 -> 12.6 | E5: =E72 -> 16.765076 | F5: =F72 -> 18.31118 | G5: =G72 -> 20.00135
A6: 營收年增 | B6: % | D6: =D77 -> 0.39911389 | E6: =E77 -> 0.33056162 | F6: =F77 -> 0.092221675 | G6: =G77 -> 0.092302637
A7: AI 營收 | B7: US$B | C7: =C69 -> 1.63 | D7: =D69 -> 3.5 | E7: =E69 -> 6.7550764 | F7: =F69 -> 7.5003798 | G7: =G69 -> 8.5419019
A8: 非 AI 營收 | B8: US$B | C8: =C71 -> 7.3757 | D8: =D71 -> 9.1 | E8: =E71 -> 10.01 | F8: =F71 -> 10.8108 | G8: =G71 -> 11.459448
A9: AI ÷ 營收 | B9: % | C9: =C78 -> 0.18099648 | D9: =D78 -> 0.27777778 | E9: =E78 -> 0.40292548 | F9: =F78 -> 0.40960658 | G9: =G78 -> 0.42706627
A10: 毛利率 | B10: % | C10: =C82 -> 0.64574658 | D10: =D82 -> 0.63 | E10: =E82 -> 0.62249114 | F10: =F82 -> 0.62209027 | G10: =G82 -> 0.62104269
A11: 營業利益率 | B11: % | C11: =C86 -> 0.48158389 | D11: =D86 -> 0.485 | E11: =E86 -> 0.4937017 | F11: =F86 -> 0.49819428 | G11: =G86 -> 0.501858
A12: 淨利（non-GAAP） | B12: US$B | C12: =C89 -> 3.806 | D12: =D89 -> 5.224907 | E12: =E89 -> 6.9732878 | F12: =F89 -> 7.6412947 | G12: =G89 -> 8.3643916
A13: EPS（non-GAAP） | B13: US$ | C13: =C91 -> 2.9834601 | D13: =D91 -> 4.0949152 | E13: =E91 -> 5.4651733 | F13: =F91 -> 5.9887102 | G13: =G91 -> 6.5554227
A14: EPS 年增 | B14: % | D14: =D92 -> 0.37253896 | E14: =E92 -> 0.3346243 | F14: =F92 -> 0.095795113 | G14: =G92 -> 0.094630147
A16: 情境 B
A17: 營收 | B17: US$B | C17: =C107 -> 9.0057 | D17: =D107 -> 12.6 | E17: =E107 -> 16.765076 | F17: =F107 -> 16.811104 | G17: =G107 -> 18.720065
A18: 營收年增 | B18: % | D18: =D112 -> 0.39911389 | E18: =E112 -> 0.33056162 | F18: =F112 -> 0.0027454371 | G18: =G112 -> 0.11355357
A19: AI 營收 | B19: US$B | C19: =C104 -> 1.63 | D19: =D104 -> 3.5 | E19: =E104 -> 6.7550764 | F19: =F104 -> 6.0003038 | G19: =G104 -> 7.2606167
A20: 非 AI 營收 | B20: US$B | C20: =C106 -> 7.3757 | D20: =D106 -> 9.1 | E20: =E106 -> 10.01 | F20: =F106 -> 10.8108 | G20: =G106 -> 11.459448
A21: AI ÷ 營收 | B21: % | C21: =C113 -> 0.18099648 | D21: =D113 -> 0.27777778 | E21: =E113 -> 0.40292548 | F21: =F113 -> 0.35692503 | G21: =G113 -> 0.38785211
A22: 毛利率 | B22: % | C22: =C117 -> 0.64574658 | D22: =D117 -> 0.63 | E22: =E117 -> 0.62249114 | F22: =F117 -> 0.62525116 | G22: =G117 -> 0.62339554
A23: 營業利益率 | B23: % | C23: =C121 -> 0.48158389 | D23: =D121 -> 0.485 | E23: =E121 -> 0.4937017 | F23: =F121 -> 0.4966204 | G23: =G121 -> 0.50066742
A24: 淨利（non-GAAP） | B24: US$B | C24: =C124 -> 3.806 | D24: =D124 -> 5.224907 | E24: =E124 -> 6.9732878 | F24: =F124 -> 7.0300023 | G24: =G124 -> 7.838796
A25: EPS（non-GAAP） | B25: US$ | C25: =C126 -> 2.9834601 | D25: =D126 -> 4.0949152 | E25: =E126 -> 5.4651733 | F25: =F126 -> 5.5096221 | G25: =G126 -> 6.1434978
A26: EPS 年增 | B26: % | D26: =D127 -> 0.37253896 | E26: =E127 -> 0.3346243 | F26: =F127 -> 0.0081331023 | G26: =G127 -> 0.11504885
A28: 情境 C
A29: 營收 | B29: US$B | C29: =C142 -> 9.0057 | D29: =D142 -> 12.6 | E29: =E142 -> 16.765076 | F29: =F142 -> 15.311028 | G29: =G142 -> 16.584589
A30: 營收年增 | B30: % | D30: =D147 -> 0.39911389 | E30: =E147 -> 0.33056162 | F30: =F147 -> -0.0867308 | G30: =G147 -> 0.083179347
A31: AI 營收 | B31: US$B | C31: =C139 -> 1.63 | D31: =D139 -> 3.5 | E31: =E139 -> 6.7550764 | F31: =F139 -> 4.5002279 | G31: =G139 -> 5.1251412
A32: 非 AI 營收 | B32: US$B | C32: =C141 -> 7.3757 | D32: =D141 -> 9.1 | E32: =E141 -> 10.01 | F32: =F141 -> 10.8108 | G32: =G141 -> 11.459448
A33: AI ÷ 營收 | B33: % | C33: =C148 -> 0.18099648 | D33: =D148 -> 0.27777778 | E33: =E148 -> 0.40292548 | F33: =F148 -> 0.29392069 | G33: =G148 -> 0.30903034
A34: 毛利率 | B34: % | C34: =C152 -> 0.64574658 | D34: =D152 -> 0.63 | E34: =E152 -> 0.62249114 | F34: =F152 -> 0.62903143 | G34: =G152 -> 0.62812485
A35: 營業利益率 | B35: % | C35: =C156 -> 0.48158389 | D35: =D156 -> 0.485 | E35: =E156 -> 0.4937017 | F35: =F156 -> 0.48801118 | G35: =G156 -> 0.49197775
A36: 淨利（non-GAAP） | B36: US$B | C36: =C159 -> 3.806 | D36: =D159 -> 5.224907 | E36: =E159 -> 6.9732878 | F36: =F159 -> 6.3373427 | G36: =G159 -> 6.8803066
A37: EPS（non-GAAP） | B37: US$ | C37: =C161 -> 2.9834601 | D37: =D161 -> 4.0949152 | E37: =E161 -> 5.4651733 | F37: =F161 -> 4.9667642 | G37: =G161 -> 5.3923011
A38: EPS 年增 | B38: % | D38: =D162 -> 0.37253896 | E38: =E162 -> 0.3346243 | F38: =F162 -> -0.091197309 | G38: =G162 -> 0.085676892
A40: 核對（應為 0）：FY2026 模型營收 − 錨點；FY2026 模型 AI − 公司目標（校準恆等式）
A41: 情境 A：營收差（US$B） | D41: =D72-a26_rev -> 0
A42: 情境 A：AI 差（US$B） | D42: =D69-a26_ai -> 0
A43: 情境 A：毛利差（US$B） | D43: =D80*D71+(D80-d_ai)*D69-a26_gp -> 0
A60: 情境 A：基準（顆數係數 1.0）
A61: 項目 | B61: 單位 | C61: FY2025A | D61: FY2026（錨點） | E61: FY2027 | F61: FY2028 | G61: FY2029 | H61: 說明
A62: A. AI 營收（D 欄＝FY2026 校準年；E–G＝FY2027–FY2029）
A63: AI 後端 scale-out 交換器市場 × 情境顆數係數 | B63: US$B | D63: =mkt_26*1 -> 32.0719 | E63: =mkt_27*1*1 -> 61.085 | F63: =mkt_28*um28_A*1 -> 69.005 | G63: =mkt_29*um29_A*1 -> 78.48215
A64: 乙太網路占比 | B64: % | D64: =eth_26 -> 0.75 | E64: =eth_27 -> 0.8 | F64: =eth_28 -> 0.83 | G64: =eth_29 -> 0.85
A65: AI 後端乙太網路交換器市場 | B65: US$B | D65: =D63*D64 -> 24.053925 | E65: =E63*E64 -> 48.868 | F65: =F63*F64 -> 57.27415 | G65: =G63*G64 -> 66.709828
A66: Arista 有效份額（FY2026 校準）＝ AI 目標 ÷ 乙太網路市場 | B66: % | D66: =a26_ai/D65 -> 0.1455064 | H66: Derived：分子含前端與 scale-across，所以高於純後端份額；FY2027 起乘相對值
A67: 份額相對值（÷ FY2026） | B67: x | D67: =1 -> 1 | E67: =rel_27 -> 0.95 | F67: =rel_28 -> 0.9 | G67: =rel_29 -> 0.88
A68: Arista 有效份額 | B68: % | D68: =$D$66*D67 -> 0.1455064 | E68: =$D$66*E67 -> 0.13823108 | F68: =$D$66*F67 -> 0.13095576 | G68: =$D$66*G67 -> 0.12804563
A69: AI 營收 | B69: US$B | C69: =a25_ai -> 1.63 | D69: =D65*D68 -> 3.5 | E69: =E65*E68 -> 6.7550764 | F69: =F65*F68 -> 7.5003798 | G69: =G65*G68 -> 8.5419019
A70: B. 非 AI 與合計
A71: 非 AI 營收 | B71: US$B | C71: =a25_nai -> 7.3757 | D71: =a26_nai -> 9.1 | E71: =D71*(1+g_nai27) -> 10.01 | F71: =E71*(1+g_nai28) -> 10.8108 | G71: =F71*(1+g_nai29) -> 11.459448
A72: 營收 | B72: US$B | C72: =a25_rev -> 9.0057 | D72: =D69+D71 -> 12.6 | E72: =E69+E71 -> 16.765076 | F72: =F69+F71 -> 18.31118 | G72: =G69+G71 -> 20.00135
A73: 服務營收 | B73: US$B | C73: =svc25 -> 1.4288 | D73: =C73*(1+g_svc26) -> 1.743136 | E73: =D73*(1+g_svc27) -> 2.0046064 | F73: =E73*(1+g_svc28) -> 2.205067 | G73: =F73*(1+g_svc29) -> 2.3814724 | H73: 公司營收線：Service
A74: 產品：非 AI（園區、企業、路由等；＝非 AI − 服務） | B74: US$B | C74: =C71-C73 -> 5.9469 | D74: =D71-D73 -> 7.356864 | E74: =E71-E73 -> 8.0053936 | F74: =F71-F73 -> 8.605733 | G74: =G71-G73 -> 9.0779756
A75: 產品營收（AI＋非 AI 產品） | B75: US$B | C75: =C69+C74 -> 7.5769 | D75: =D69+D74 -> 10.856864 | E75: =E69+E74 -> 14.76047 | F75: =F69+F74 -> 16.106113 | G75: =G69+G74 -> 17.619878 | H75: 公司營收線：Product
A76: 檢查：產品＋服務 − 合併營收 | B76: US$B | C76: =C75+C73-C72 -> 0 | D76: =D75+D73-D72 -> 0 | E76: =E75+E73-E72 -> 0 | F76: =F75+F73-F72 -> 0 | G76: =G75+G73-G72 -> 0
A77: 營收年增 | B77: % | D77: =D72/C72-1 -> 0.39911389 | E77: =E72/D72-1 -> 0.33056162 | F77: =F72/E72-1 -> 0.092221675 | G77: =G72/F72-1 -> 0.092302637
A78: AI ÷ 營收 | B78: % | C78: =C69/C72 -> 0.18099648 | D78: =D69/D72 -> 0.27777778 | E78: =E69/E72 -> 0.40292548 | F78: =F69/F72 -> 0.40960658 | G78: =G69/G72 -> 0.42706627
A79: C. 損益
A80: 非 AI 毛利率 ＝ 錨點毛利率 ＋ 差距 × AI 占比（FY2026 校準） | B80: % | D80: =a26_gp/a26_rev+d_ai*D78 -> 0.64666667 | H80: Derived：讓 FY2026 毛利率等於錨點；AI 毛利率＝非 AI − 差距。FY2027 起毛利率隨 AI 占比變動
A81: 毛利 | B81: US$B | C81: =a25_gp -> 5.8154 | D81: =a26_gp -> 7.938 | E81: =$D$80*E71+($D$80-d_ai)*E69 -> 10.436111 | F81: =$D$80*F71+($D$80-d_ai)*F69 -> 11.391207 | G81: =$D$80*G71+($D$80-d_ai)*G69 -> 12.421692
A82: 毛利率 | B82: % | C82: =C81/C72 -> 0.64574658 | D82: =D81/D72 -> 0.63 | E82: =E81/E72 -> 0.62249114 | F82: =F81/F72 -> 0.62209027 | G82: =G81/G72 -> 0.62104269
A83: 營業費用（基準路徑） | B83: US$B | C83: =a25_opx -> 1.4784 | D83: =a26_opx -> 1.827 | E83: =D83*(1+MAX(0,phi*E77)) -> 2.1591648 | F83: =E83*(1+MAX(0,phi*F77)) -> 2.2686818 | G83: =F83*(1+MAX(0,phi*G77)) -> 2.3838548
A84: 營業費用 | B84: US$B | C84: =C83 -> 1.4784 | D84: =D83 -> 1.827 | E84: =E83+0*E72 -> 2.1591648 | F84: =F83+0*F72 -> 2.2686818 | G84: =G83+0*G72 -> 2.3838548
A85: 營業利益 | B85: US$B | C85: =C81-C84 -> 4.337 | D85: =D81-D84 -> 6.111 | E85: =E81-E84 -> 8.2769466 | F85: =F81-F84 -> 9.122525 | G85: =G81-G84 -> 10.037837
A86: 營業利益率 | B86: % | C86: =C85/C72 -> 0.48158389 | D86: =D85/D72 -> 0.485 | E86: =E85/E72 -> 0.4937017 | F86: =F85/F72 -> 0.49819428 | G86: =G85/G72 -> 0.501858
A87: 其他收益 | B87: US$B | C87: =a25_oth -> 0.3936 | D87: =a26_oth -> 0.4999 | E87: =oth_f -> 0.55 | F87: =oth_f -> 0.55 | G87: =oth_f -> 0.55
A88: 有效稅率 | B88: % | C88: =1-a25_ni/(a25_oi+a25_oth) -> 0.19545089 | D88: =1-a26_ni/(a26_oi+a26_oth) -> 0.20965269 | E88: =tx_f -> 0.21 | F88: =tx_f -> 0.21 | G88: =tx_f -> 0.21
A89: 淨利（non-GAAP） | B89: US$B | C89: =a25_ni -> 3.806 | D89: =a26_ni -> 5.224907 | E89: =(E85+E87)*(1-E88) -> 6.9732878 | F89: =(F85+F87)*(1-F88) -> 7.6412947 | G89: =(G85+G87)*(1-G88) -> 8.3643916
A90: 稀釋股數 | B90: 十億股 | C90: =a25_sh -> 1.2757 | D90: =a26_sh -> 1.27595 | E90: =D90*(1+sh_g) -> 1.27595 | F90: =E90*(1+sh_g) -> 1.27595 | G90: =F90*(1+sh_g) -> 1.27595
A91: EPS（non-GAAP） | B91: US$ | C91: =C89/C90 -> 2.9834601 | D91: =D89/D90 -> 4.0949152 | E91: =E89/E90 -> 5.4651733 | F91: =F89/F90 -> 5.9887102 | G91: =G89/G90 -> 6.5554227
A92: EPS 年增 | B92: % | D92: =D91/C91-1 -> 0.37253896 | E92: =E91/D91-1 -> 0.3346243 | F92: =F91/E91-1 -> 0.095795113 | G92: =G91/F91-1 -> 0.094630147
A95: 情境 B：CY2028 顆數 ×0.8、CY2029 ×0.85
A96: 項目 | B96: 單位 | C96: FY2025A | D96: FY2026（錨點） | E96: FY2027 | F96: FY2028 | G96: FY2029 | H96: 說明
A97: A. AI 營收（D 欄＝FY2026 校準年；E–G＝FY2027–FY2029）
A98: AI 後端 scale-out 交換器市場 × 情境顆數係數 | B98: US$B | D98: =mkt_26*1 -> 32.0719 | E98: =mkt_27*1*1 -> 61.085 | F98: =mkt_28*um28_B*1 -> 55.204 | G98: =mkt_29*um29_B*1 -> 66.709828
A99: 乙太網路占比 | B99: % | D99: =eth_26 -> 0.75 | E99: =eth_27 -> 0.8 | F99: =eth_28 -> 0.83 | G99: =eth_29 -> 0.85
A100: AI 後端乙太網路交換器市場 | B100: US$B | D100: =D98*D99 -> 24.053925 | E100: =E98*E99 -> 48.868 | F100: =F98*F99 -> 45.81932 | G100: =G98*G99 -> 56.703353
A101: Arista 有效份額（FY2026 校準）＝ AI 目標 ÷ 乙太網路市場 | B101: % | D101: =a26_ai/D100 -> 0.1455064 | H101: Derived：分子含前端與 scale-across，所以高於純後端份額；FY2027 起乘相對值
A102: 份額相對值（÷ FY2026） | B102: x | D102: =1 -> 1 | E102: =rel_27 -> 0.95 | F102: =rel_28 -> 0.9 | G102: =rel_29 -> 0.88
A103: Arista 有效份額 | B103: % | D103: =$D$101*D102 -> 0.1455064 | E103: =$D$101*E102 -> 0.13823108 | F103: =$D$101*F102 -> 0.13095576 | G103: =$D$101*G102 -> 0.12804563
A104: AI 營收 | B104: US$B | C104: =a25_ai -> 1.63 | D104: =D100*D103 -> 3.5 | E104: =E100*E103 -> 6.7550764 | F104: =F100*F103 -> 6.0003038 | G104: =G100*G103 -> 7.2606167
A105: B. 非 AI 與合計
A106: 非 AI 營收 | B106: US$B | C106: =a25_nai -> 7.3757 | D106: =a26_nai -> 9.1 | E106: =D106*(1+g_nai27) -> 10.01 | F106: =E106*(1+g_nai28) -> 10.8108 | G106: =F106*(1+g_nai29) -> 11.459448
A107: 營收 | B107: US$B | C107: =a25_rev -> 9.0057 | D107: =D104+D106 -> 12.6 | E107: =E104+E106 -> 16.765076 | F107: =F104+F106 -> 16.811104 | G107: =G104+G106 -> 18.720065
A108: 服務營收 | B108: US$B | C108: =svc25 -> 1.4288 | D108: =C108*(1+g_svc26) -> 1.743136 | E108: =D108*(1+g_svc27) -> 2.0046064 | F108: =E108*(1+g_svc28) -> 2.205067 | G108: =F108*(1+g_svc29) -> 2.3814724 | H108: 公司營收線：Service
A109: 產品：非 AI（園區、企業、路由等；＝非 AI − 服務） | B109: US$B | C109: =C106-C108 -> 5.9469 | D109: =D106-D108 -> 7.356864 | E109: =E106-E108 -> 8.0053936 | F109: =F106-F108 -> 8.605733 | G109: =G106-G108 -> 9.0779756
A110: 產品營收（AI＋非 AI 產品） | B110: US$B | C110: =C104+C109 -> 7.5769 | D110: =D104+D109 -> 10.856864 | E110: =E104+E109 -> 14.76047 | F110: =F104+F109 -> 14.606037 | G110: =G104+G109 -> 16.338592 | H110: 公司營收線：Product
A111: 檢查：產品＋服務 − 合併營收 | B111: US$B | C111: =C110+C108-C107 -> 0 | D111: =D110+D108-D107 -> 0 | E111: =E110+E108-E107 -> 0 | F111: =F110+F108-F107 -> 0 | G111: =G110+G108-G107 -> 0
A112: 營收年增 | B112: % | D112: =D107/C107-1 -> 0.39911389 | E112: =E107/D107-1 -> 0.33056162 | F112: =F107/E107-1 -> 0.0027454371 | G112: =G107/F107-1 -> 0.11355357
A113: AI ÷ 營收 | B113: % | C113: =C104/C107 -> 0.18099648 | D113: =D104/D107 -> 0.27777778 | E113: =E104/E107 -> 0.40292548 | F113: =F104/F107 -> 0.35692503 | G113: =G104/G107 -> 0.38785211
A114: C. 損益
A115: 非 AI 毛利率 ＝ 錨點毛利率 ＋ 差距 × AI 占比（FY2026 校準） | B115: % | D115: =a26_gp/a26_rev+d_ai*D113 -> 0.64666667 | H115: Derived：讓 FY2026 毛利率等於錨點；AI 毛利率＝非 AI − 差距。FY2027 起毛利率隨 AI 占比變動
A116: 毛利 | B116: US$B | C116: =a25_gp -> 5.8154 | D116: =a26_gp -> 7.938 | E116: =$D$115*E106+($D$115-d_ai)*E104 -> 10.436111 | F116: =$D$115*F106+($D$115-d_ai)*F104 -> 10.511162 | G116: =$D$115*G106+($D$115-d_ai)*G104 -> 11.670005
A117: 毛利率 | B117: % | C117: =C116/C107 -> 0.64574658 | D117: =D116/D107 -> 0.63 | E117: =E116/E107 -> 0.62249114 | F117: =F116/F107 -> 0.62525116 | G117: =G116/G107 -> 0.62339554
A118: 營業費用（基準路徑） | B118: US$B | C118: =a25_opx -> 1.4784 | D118: =a26_opx -> 1.827 | E118: =D118*(1+MAX(0,phi*E112)) -> 2.1591648 | F118: =E118*(1+MAX(0,phi*F112)) -> 2.1624252 | G118: =F118*(1+MAX(0,phi*G112)) -> 2.2974783
A119: 營業費用 | B119: US$B | C119: =C118 -> 1.4784 | D119: =D118 -> 1.827 | E119: =E118+0*E107 -> 2.1591648 | F119: =F118+0*F107 -> 2.1624252 | G119: =G118+0*G107 -> 2.2974783
A120: 營業利益 | B120: US$B | C120: =C116-C119 -> 4.337 | D120: =D116-D119 -> 6.111 | E120: =E116-E119 -> 8.2769466 | F120: =F116-F119 -> 8.3487371 | G120: =G116-G119 -> 9.3725265
A121: 營業利益率 | B121: % | C121: =C120/C107 -> 0.48158389 | D121: =D120/D107 -> 0.485 | E121: =E120/E107 -> 0.4937017 | F121: =F120/F107 -> 0.4966204 | G121: =G120/G107 -> 0.50066742
A122: 其他收益 | B122: US$B | C122: =a25_oth -> 0.3936 | D122: =a26_oth -> 0.4999 | E122: =oth_f -> 0.55 | F122: =oth_f -> 0.55 | G122: =oth_f -> 0.55
...

Sheet Val
A1: Val — P/E 估值（美元）。結論用「現價 ÷ FY2027、FY2028 EPS（模型）」與十年 P/E 規則值。Arista 的 GAAP 與 non-GAAP 差距小（約 7%），十年 GAAP P/E 適用；規則值以 GAAP 換算 EPS（non-GAAP × g2n）計算
A2: 循環位置：Arista 不是設備股，不套設備市場見頂年；以本模型營收最高的會計年度為見頂年（比照 NVIDIA；FY(t)＝CY(t)，不平移）。營收到 FY2029 仍在增加時，見頂年未知，判為中段
A3: 0. 目標價（DCF 與 Comparable 加權；v0.2 新增，Andy 2026-10-25）
A4: 0.1 DCF（股東權益現金流，FY2027–FY2032 明確期＋FY2032 後永續）
A5: 項目 | B5: A | C5: B | D5: C | E5: 說明 | F5: 折現年數 t | G5: 期內占比（基準日後）
A6: 情境 EPS（FY2027–FY2032） | E6: 引用 PL 頁延伸表（上游結束後為收斂法）；三情境欄 B／C／D＝A／B／C
A7: FY2027 | B7: =PL!E174 -> 5.4651733 | C7: =PL!E183 -> 5.4651733 | D7: =PL!E192 -> 5.4651733 | F7: 1 | G7: 1
A8: FY2028 | B8: =PL!F174 -> 5.9887102 | C8: =PL!F183 -> 5.5096221 | D8: =PL!F192 -> 4.9667642 | F8: 2 | G8: 1
A9: FY2029 | B9: =PL!G174 -> 6.5554227 | C9: =PL!G183 -> 6.1434978 | D9: =PL!G192 -> 5.3923011 | F9: 3 | G9: 1
A10: FY2030 | B10: =PL!H174 -> 7.0899197 | C10: =PL!H183 -> 6.4674722 | D10: =PL!H192 -> 5.3454506 | F10: 4 | G10: 1
A11: FY2031 | B11: =PL!I174 -> 7.5916559 | C11: =PL!I183 -> 6.6473348 | D11: =PL!I192 -> 5.1674384 | F11: 5 | G11: 1
A12: FY2032 | B12: =PL!J174 -> 8.0471552 | C12: =PL!J183 -> 6.6663272 | D12: =PL!J192 -> 4.865342 | F12: 6 | G12: 1
A13: 股東現金流＝EPS ×（1 − tp_g ÷ tp_roe） | B13: =1-MIN(0.8,tp_g/tp_roe) -> 0.86018875 | E13: B 欄＝可發放比例（1 − 再投資率；再投資率＝tp_g ÷ tp_roe，上限 0.8）；下列六列＝EPS × 可發放比例 × 期內占比
A14: FY2027 股東現金流 | B14: =B7*$B$13*$G$7 -> 4.7010805 | C14: =C7*$B$13*$G$7 -> 4.7010805 | D14: =D7*$B$13*$G$7 -> 4.7010805
A15: FY2028 股東現金流 | B15: =B8*$B$13*$G$8 -> 5.1514211 | C15: =C8*$B$13*$G$8 -> 4.7393149 | D15: =D8*$B$13*$G$8 -> 4.2723546
A16: FY2029 股東現金流 | B16: =B9*$B$13*$G$9 -> 5.6389008 | C16: =C9*$B$13*$G$9 -> 5.2845676 | D16: =D9*$B$13*$G$9 -> 4.6383967
A17: FY2030 股東現金流 | B17: =B10*$B$13*$G$10 -> 6.0986691 | C17: =C10*$B$13*$G$10 -> 5.5632468 | D17: =D10*$B$13*$G$10 -> 4.5980964
A18: FY2031 股東現金流 | B18: =B11*$B$13*$G$11 -> 6.5302569 | C18: =C11*$B$13*$G$11 -> 5.7179626 | D18: =D11*$B$13*$G$11 -> 4.4449723
A19: FY2032 股東現金流 | B19: =B12*$B$13*$G$12 -> 6.9220724 | C19: =C12*$B$13*$G$12 -> 5.7342996 | D19: =D12*$B$13*$G$12 -> 4.1851124
A20: 永續價值（FY2032 年底；FY2032 現金流 ×(1＋tp_g) ÷ (tp_r − tp_g)） | B20: =B19*(1+tp_g)/(tp_r-tp_g) -> 119.98259 | C20: =C19*(1+tp_g)/(tp_r-tp_g) -> 99.394527 | D20: =D19*(1+tp_g)/(tp_r-tp_g) -> 72.541948
A21: DCF 情境每股價值（折現率 tp_r） | B21: =MAX(0,B14/(1+tp_r)^$F$7+B15/(1+tp_r)^$F$8+B16/(1+tp_r)^$F$9+B17/(1+tp_r)^$F$10+B18/(1+tp_r)^$F$11+B19/(1+tp_r)^$F$12+B20/(1+tp_r)^$F$12) -> 92.622293 | C21: =MAX(0,C14/(1+tp_r)^$F$7+C15/(1+tp_r)^$F$8+C16/(1+tp_r)^$F$9+C17/(1+tp_r)^$F$10+C18/(1+tp_r)^$F$11+C19/(1+tp_r)^$F$12+C20/(1+tp_r)^$F$12) -> 78.853532 | D21: =MAX(0,D14/(1+tp_r)^$F$7+D15/(1+tp_r)^$F$8+D16/(1+tp_r)^$F$9+D17/(1+tp_r)^$F$10+D18/(1+tp_r)^$F$11+D19/(1+tp_r)^$F$12+D20/(1+tp_r)^$F$12) -> 60.500443 | E21: 基準日 2026 年底；明確期現金流與永續價值依 F 欄年數折現；小於 0 時取 0（Andy 2026-10-25 12:22）
A22: 其中：永續價值現值占比 | B22: =B20/(1+tp_r)^$F$12/B21 -> 0.73121751 | C22: =C20/(1+tp_r)^$F$12/C21 -> 0.71151688 | D22: =D20/(1+tp_r)^$F$12/D21 -> 0.67682213
A23: DCF 目標價（情境加權） | B23: =(tp_wA*B21+tp_wB*C21+tp_wC*D21)*(1+tp_r) -> 87.244897 | E23: Σ 權重 × 情境價值 ×(1＋tp_r)：推到約 12 個月後
A25: 0.2 Comparable（市場主流同業前瞻 P/E）
A26: 同業與前瞻 P/E | B26: 代號 | C26: 前瞻 12 月 P/E | D26: 日期 | E26: 來源 | F26: 標記
A27: Cisco | B27: CSCO | C27: 20.7 | D27: 2026-10-23 | E27: stockanalysis.com 統計頁（Forward PE） | F27: Interested-party（資料商彙整賣方預估）
A28: Ciena | B28: CIEN | C28: 30.77 | D28: 2026-10-23 | E28: 同上 | F28: Interested-party（同上）
A29: Celestica | B29: CLS | C29: 16.65 | D29: 2026-10-23 | E29: 同上 | F29: Interested-party（同上）
A30: Hewlett Packard Enterprise（含 Juniper） | B30: HPE | C30: 12.19 | D30: 2026-10-23 | E30: 同上 | F30: Interested-party（同上）
A31: Credo | B31: CRDO | C31: 20.19 | D31: 2026-10-23 | E31: 同上 | F31: Interested-party（同上）
A32: 同業選擇 | E32: 券商常用的資料中心網通同業（交換器：Cisco、HPE＋Juniper；光傳輸：Ciena；白牌交換器 ODM：Celestica；AI 互連：Credo）；不含 A 股（Andy 11:53）。前瞻 P/E 口徑為資料商的未來 12 個月共識 EPS，各家 GAAP／non-GAAP 口徑不一
A33: 同業前瞻 P/E 中位數 | B33: =MEDIAN(C27:C31) -> 20.19
A34: 各情境 12 個月後的前瞻 EPS | B34: =2/12*PL!E174+10/12*PL!F174 -> 5.901454 | C34: =2/12*PL!E183+10/12*PL!F183 -> 5.5022139 | D34: =2/12*PL!E192+10/12*PL!F192 -> 5.0498324 | E34: 會計年度＝日曆年：約 12 個月後（2027-10 底）的未來 12 個月＝2027-11～2028-10（2/12 × FY2027＋10/12 × FY2028）
A35: 12 個月後的前瞻 EPS（情境加權） | B35: =tp_wA*B34+tp_wB*C34+tp_wC*D34 -> 5.5315096
A36: Comparable 目標價 | B36: =B33*B35 -> 111.68118 | E36: 同業前瞻 P/E 中位數 × 12 個月後的前瞻 EPS（情境加權）
A38: 0.3 結論
A39: 項目 | B39: 數值 | C39: 對照 | D39: 對照 | E39: 說明
A40: 目標價（DCF 與 Comparable 加權） | B40: =tp_w_dcf*B23+(1-tp_w_dcf)*tp_comp_adj -> 155.30363 | E40: ="DCF 權重 "&TEXT(tp_w_dcf,"0%")&"、Comparable 權重 "&TEXT(1-tp_w_dcf,"0%")&"（In 頁 tp_w_dcf，Andy 可改）" -> DCF 權重 50%、Comparable 權重 50%（In 頁 tp_w_dcf，Andy 可改）
A41: Comparable 目標價（市場主流同業法） | B41: =B36 -> 111.68118
A42: 市場共識目標價 | B42: =cons_tp -> 243.59 | E42: stockanalysis.com：32 位分析師平均目標價（2026-10-23）；Interested-party
A43: 上檔空間：加權目標價 | B43: =B40/px-1 -> -0.099010106
A44: 上檔空間：Comparable 目標價 | B44: =B41/px-1 -> -0.35208459
A45: 與市場共識目標價的差距：EPS 因素 | B45: =(tp_wA*(2/12*PL!D174+10/12*PL!E174)+tp_wB*(2/12*PL!D183+10/12*PL!E183)+tp_wC*(2/12*PL!D192+10/12*PL!E192))/C45-1 -> 0.12592501 | C45: =px/pe_fwd_sa -> 4.6511063 | E45: B＝我們的前瞻 EPS（情境加權）÷ 共識前瞻 EPS − 1；C＝共識前瞻 EPS（共識未來 12 個月 EPS＝現價 ÷ StockAnalysis 前瞻 P/E（FY2027 以後共識未找到）；比較窗為 2026-11～2027-10，故 B 用同窗的情境加權 2/12 × FY2026＋10/12 × FY2027）
A46: 與市場共識目標價的差距：倍數因素 | B46: =C46/B33-1 -> 1.5939815 | C46: =B42/C45 -> 52.372486 | D46: =B33 -> 20.19 | E46: C＝市場共識目標價 ÷ 共識前瞻 EPS 隱含的倍數；D＝同業中位數；B＝C ÷ D − 1
A47: 價格帶（DCF 不如預期～順利） | B47: =D21*(1+tp_r) -> 66.550487 | C47: =B21*(1+tp_r) -> 101.88452 | E47: B＝C 情境 DCF 價值、C＝A 情境 DCF 價值（皆推到 12 個月後）
A48: 檢查用：現價 ÷ 各情境 FY2028 EPS | B48: =px/PL!F174 -> 28.782492 | C48: =px/PL!F183 -> 31.285267 | D48: =px/PL!F192 -> 34.704688
A49: 歷史倍數檢查：現價隱含 P/E 的十年分位（A／B／C） | B49: =IF(B48<MIN(B106:B115),0,IF(B48>MAX(B106:B115),1,PERCENTRANK(B106:B115,B48))) -> 0.242 | C49: =IF(C48<MIN(B106:B115),0,IF(C48>MAX(B106:B115),1,PERCENTRANK(B106:B115,C48))) -> 0.28 | D49: =IF(D48<MIN(B106:B115),0,IF(D48>MAX(B106:B115),1,PERCENTRANK(B106:B115,D48))) -> 0.332 | E49: 上一列在 2016–2025 年底 P/E 分布（Val!B106:B115）的分位（PERCENTRANK；低於最小＝0、高於最大＝1）；只作檢查，不進目標價
A50: 目標價方法 | B50: DCF：股東現金流＝non-GAAP EPS ×（1 − tp_g ÷ tp_roe），tp_r 10%、tp_g 4%、tp_roe 近三年平均 GAAP ROE 28.6%（再投資率約 14%）；基準日 2026 年底，FY2027 起逐年折現，FY2032 後永續。Comparable：Cisco、Ciena、Celestica、HPE、Credo 前瞻 P/E 中位數 × 12 個月後前瞻 EPS。偏誤方向：同業成長低於 Arista，中位數偏低（Comparable 偏保守）；non-GAAP EPS 排除股票薪酬（偏高）；C 情境 FY2030 起淨利率收斂到 FY2029 × 0.8（Assumed）；歷史分位用十年 GAAP 落後 P/E（companiesmarketcap）；永續價值占 DCF 價值過半（Sens 頁）。
A51: 檢查：情境權重合計（應為 1） | B51: =ROUND(tp_wA+tp_wB+tp_wC,6) -> 1
A52: 上檔空間級距 | B52: =IF(B43>0.5,"大於 50%",IF(B43>0.25,"25%–50%",IF(B43>=0,"0%–25%",IF(B43>=-0.25,"0%～−25%",IF(B43>=-0.5,"−25%～−50%","小於 −50%"))))) -> 0%～−25% | E52: 以「上檔空間：加權目標價」分六級（Andy 2026-10-25 14:00）
A53: 投資建議 | B53: =IF(B43>0.5,"強力買進",IF(B43>0.25,"買進",IF(B43>=-0.25,"中立",IF(B43>=-0.5,"放空","強力放空")))) -> 中立 | E53: 依上檔空間固定規則（Andy 2026-10-25 14:17）：大於 +50% 強力買進、+25%～+50% 買進、−25%～+25% 中立、−50%～−25% 放空、小於 −50% 強力放空
A55: 1. 價格與市場隱含倍數
A56: 項目 | B56: A | C56: B | D56: C | E56: 說明
A57: 現價（2026-10-23 收盤） | B57: =px -> 172.37
A58: 現價 ÷ FY2026 EPS（錨點） | B58: =px/PL!D13 -> 42.093668 | C58: =px/PL!D25 -> 42.093668 | D58: =px/PL!D37 -> 42.093668
A59: 現價 ÷ FY2027 EPS（模型） | B59: =px/PL!E13 -> 31.539714 | C59: =px/PL!E25 -> 31.539714 | D59: =px/PL!E37 -> 31.539714 | E59: FY2027 三情境相同（顆數係數從 CY2028 開始）
A60: 現價 ÷ FY2028 EPS（模型） | B60: =px/PL!F13 -> 28.782492 | C60: =px/PL!F25 -> 31.285267 | D60: =px/PL!F37 -> 34.704688
A61: 現價 ÷ FY2029 EPS（模型） | B61: =px/PL!G13 -> 26.294262 | C61: =px/PL!G25 -> 28.057307 | D61: =px/PL!G37 -> 31.965945
A62: 前瞻 P/E（StockAnalysis） | B62: =pe_fwd_sa -> 37.06 | E62: Andy 先驗 A9a 答 30x（口徑未註明）
A63: 隱含未來 12 月 EPS ＝ 現價 ÷ 前瞻 P/E | B63: =px/pe_fwd_sa -> 4.6511063
A64: 近 12 月 GAAP P/E（StockAnalysis） | B64: =pe_ttm_gaap -> 54.55
A66: 2. 循環位置（本模型營收最高年；FY(t)＝CY(t)）
A67: 情境 | B67: 營收最高年（FY2026–FY2029） | C67: FY2027 判定 | D67: 規則倍數（GAAP P/E） | E67: 見頂年是否未知 | F67: 說明
A68: A | B68: =INDEX({2026,2027,2028,2029},MATCH(MAX(PL!D72:G72),PL!D72:G72,0)) -> 2029 | C68: =IF(B68=2029,"中段",IF(2027<B68,"中段",IF(2027=B68,"見頂","谷底"))) -> 中段 | D68: =IF(C68="見頂",pe_peak,IF(C68="谷底",pe_trough,pe_mid)) -> 35.83 | E68: =IF(B68=2029,"是：營收到觀測期末仍在增加","否") -> 是：營收到觀測期末仍在增加 | F68: tools/cycle_position.py excel_rule；營收最高年取代設備市場見頂年
A69: B | B69: =INDEX({2026,2027,2028,2029},MATCH(MAX(PL!D107:G107),PL!D107:G107,0)) -> 2029 | C69: =IF(B69=2029,"中段",IF(2027<B69,"中段",IF(2027=B69,"見頂","谷底"))) -> 中段 | D69: =IF(C69="見頂",pe_peak,IF(C69="谷底",pe_trough,pe_mid)) -> 35.83 | E69: =IF(B69=2029,"是：營收到觀測期末仍在增加","否") -> 是：營收到觀測期末仍在增加 | F69: 同上
A70: C | B70: =INDEX({2026,2027,2028,2029},MATCH(MAX(PL!D142:G142),PL!D142:G142,0)) -> 2027 | C70: =IF(B70=2029,"中段",IF(2027<B70,"中段",IF(2027=B70,"見頂","谷底"))) -> 見頂 | D70: =IF(C70="見頂",pe_peak,IF(C70="谷底",pe_trough,pe_mid)) -> 28.68 | E70: =IF(B70=2029,"是：營收到觀測期末仍在增加","否") -> 否 | F70: 同上
A72: 3. 規則值隱含股價（美元；約 FY2027 年底，未折現）＝ FY2027 GAAP 換算 EPS × 規則倍數
A73: 情境 | B73: FY2027 non-GAAP EPS | C73: GAAP 換算 EPS | D73: 規則倍數 | E73: 隱含股價 | F73: 相對現價 | G73: 現價 ÷ GAAP 換算 EPS
A74: A | B74: =PL!E13 -> 5.4651733 | C74: =B74*g2n -> 5.0603456 | D74: =D68 -> 35.83 | E74: =C74*D74 -> 181.31218 | F74: =E74/px-1 -> 0.051877841 | G74: =px/C74 -> 34.062891
A75: B | B75: =PL!E25 -> 5.4651733 | C75: =B75*g2n -> 5.0603456 | D75: =D69 -> 35.83 | E75: =C75*D75 -> 181.31218 | F75: =E75/px-1 -> 0.051877841 | G75: =px/C75 -> 34.062891
A76: C | B76: =PL!E37 -> 5.4651733 | C76: =B76*g2n -> 5.0603456 | D76: =D70 -> 28.68 | E76: =C76*D76 -> 145.13071 | F76: =E76/px-1 -> -0.15802801 | G76: =px/C76 -> 34.062891
A77: 4. What must be true：FY2027 年底價 ＝ 現價 ×（1＋報酬）所需的倍數（情境 A 的 FY2028 EPS，non-GAAP；約 2027 年底的價格看下一年 EPS）
A78: FY2027 年底價 ÷ 現價 | B78: 所需倍數（÷ FY2028 EPS，A） | C78: 所需倍數（÷ FY2028 EPS，C） | D78: 對照：Andy 合理 P/E | E78: 對照：十年中位數（GAAP）
A79: 1 | B79: =px*A79/PL!F13 -> 28.782492 | C79: =px*A79/PL!F37 -> 34.704688 | D79: =pe_fair_andy -> 25 | E79: =pe_mid -> 35.83
A80: 1.1 | B80: =px*A80/PL!F13 -> 31.660741 | C80: =px*A80/PL!F37 -> 38.175157 | D80: =pe_fair_andy -> 25 | E80: =pe_mid -> 35.83
A81: 1.21 | B81: =px*A81/PL!F13 -> 34.826815 | C81: =px*A81/PL!F37 -> 41.992672 | D81: =pe_fair_andy -> 25 | E81: =pe_mid -> 35.83
A82: 1.5 | B82: =px*A82/PL!F13 -> 43.173737 | C82: =px*A82/PL!F37 -> 52.057032 | D82: =pe_fair_andy -> 25 | E82: =pe_mid -> 35.83
A83: 2 | B83: =px*A83/PL!F13 -> 57.564983 | C83: =px*A83/PL!F37 -> 69.409376 | D83: =pe_fair_andy -> 25 | E83: =pe_mid -> 35.83
A84: 讀法：1.00＝價格不變、1.21＝一年約 21%。所需倍數低於歷史中位數時，現價相對便宜；倍數是否合理，另看前瞻 P/E 歷史（Bloomberg）。
A86: 5. 對照：以 Andy 合理 P/E 25x 計算的隱含價（non-GAAP EPS；只作對照，非規則值）
A87: 情境 | B87: FY2027 EPS | C87: × 25x | D87: 相對現價 | E87: FY2028 EPS | F87: × 25x | G87: 相對現價
A88: A | B88: =PL!E13 -> 5.4651733 | C88: =B88*pe_fair_andy -> 136.62933 | D88: =C88/px-1 -> -0.20734854 | E88: =PL!F13 -> 5.9887102 | F88: =E88*pe_fair_andy -> 149.71775 | G88: =F88/px-1 -> -0.13141641
A89: B | B89: =PL!E25 -> 5.4651733 | C89: =B89*pe_fair_andy -> 136.62933 | D89: =C89/px-1 -> -0.20734854 | E89: =PL!F25 -> 5.5096221 | F89: =E89*pe_fair_andy -> 137.74055 | G89: =F89/px-1 -> -0.20090183
A90: C | B90: =PL!E37 -> 5.4651733 | C90: =B90*pe_fair_andy -> 136.62933 | D90: =C90/px-1 -> -0.20734854 | E90: =PL!F37 -> 4.9667642 | F90: =E90*pe_fair_andy -> 124.1691 | G90: =F90/px-1 -> -0.27963622
A101: 6. 十年倍數與規則值（2016–2025 年底；見頂年 25 分位、中段中位數、谷底 75 分位）
A102: 規則（Andy 2026-10-13）：合理倍數＝2016–2025 年底 P/E 依循環位置取分位；兩個來源各取分位再平均。歷史倍數為 GAAP 落後 P/E，所以基準用 GAAP 換算 EPS。2016–2025 含高成長期（2021 年 52x），規則值可能高估成長放緩後的倍數。
A104: P/E：十年歷史倍數
A105: 年底 | B105: companiesmarketcap（年底 P/E） | C105: Macrotrends（12 月 31 日 ÷ TTM GAAP EPS） | D105: 標記／說明
A106: 2016 | B106: 36.2 | C106: 38.86 | D106: companiesmarketcap（年底 P/E）：Interested-party（資料商；2016–2025 共 10 年）；Macrotrends（12 月 31 日 ÷ TTM GAAP EPS）：Interested-party（資料商；2016–2023 共 8 年，2024 起頁面無資料：未找到）
A107: 2017 | B107: 40.3 | C107: 46.56
A108: 2018 | B108: 24.8 | C108: 26.91
A109: 2019 | B109: 18.1 | C109: 19.12
A110: 2020 | B110: 34.8 | C110: 36.37
A111: 2021 | B111: 52.4 | C111: 54.5
A112: 2022 | B112: 27.5 | C112: 28.42
A113: 2023 | B113: 34.9 | C113: 35.85
A114: 2024 | B114: 48.6
A115: 2025 | B115: 46.8
A116: 25 分位（各來源） | B116: =PERCENTILE(B106:B115,0.25) -> 29.325 | C116: =PERCENTILE(C106:C115,0.25) -> 28.0425
A117: 中位數（各來源） | B117: =MEDIAN(B106:B115) -> 35.55 | C117: =MEDIAN(C106:C115) -> 36.11
...

Sheet Recon
A1: Recon — 本模型 vs 公司指引、共識、研調份額。只作事後對照，不為對上數字而調參數。2027 年共識（StockAnalysis 付費）未找到，只有單一分析師與前瞻 P/E 隱含值
A3: 項目 | B3: 對照值 | C3: 模型 A | D3: 差距 A | E3: 模型 B | F3: 差距 B | G3: 模型 C | H3: 差距 C | I3: 對照來源 | J3: 說明
A4: A. 共識與分析師（校準未使用）
A5: FY2026 營收 vs 共識 | B5: =cons_rev26 -> 12.68 | C5: =PL!D72 -> 12.6 | D5: =C5/B5-1 -> -0.0063091483 | E5: =PL!D107 -> 12.6 | F5: =E5/B5-1 -> -0.0063091483 | G5: =PL!D142 -> 12.6 | H5: =G5/B5-1 -> -0.0063091483 | I5: StockAnalysis | J5: 錨點＝公司全年指引 12.6
A6: FY2026 EPS vs 共識 | B6: =cons_eps26 -> 4.12 | C6: =PL!D91 -> 4.0949152 | D6: =C6/B6-1 -> -0.0060885531 | E6: =PL!D126 -> 4.0949152 | F6: =E6/B6-1 -> -0.0060885531 | G6: =PL!D161 -> 4.0949152 | H6: =G6/B6-1 -> -0.0060885531 | I6: StockAnalysis | J6: 錨點（3Q、4Q 依指引與 In 頁假設）
A7: FY2027 EPS vs Erste Group（單一分析師） | B7: =erste_eps27 -> 4.79 | C7: =PL!E91 -> 5.4651733 | D7: =C7/B7-1 -> 0.14095475 | E7: =PL!E126 -> 5.4651733 | F7: =E7/B7-1 -> 0.14095475 | G7: =PL!E161 -> 5.4651733 | H7: =G7/B7-1 -> 0.14095475 | I7: MarketBeat | J7: 2027 共識：未找到（付費）
A8: FY2027 EPS vs 前瞻 P/E 隱含未來 12 月 EPS | B8: =px/pe_fwd_sa -> 4.6511063 | C8: =PL!E91 -> 5.4651733 | D8: =C8/B8-1 -> 0.17502652 | E8: =PL!E126 -> 5.4651733 | F8: =E8/B8-1 -> 0.17502652 | G8: =PL!E161 -> 5.4651733 | H8: =G8/B8-1 -> 0.17502652 | I8: StockAnalysis（推導） | J8: 未來 12 月 ≈ 4Q26＋¾ FY2027，口徑不同，只作量級比較
A9: FY2027 營收年增（模型） | C9: =PL!E77 -> 0.33056162 | E9: =PL!E112 -> 0.33056162 | G9: =PL!E147 -> 0.33056162 | I9: —
A10: B. 份額與市場（先驗比對的機制檢查）
A11: FY2026 Arista 有效份額 vs IDC 資料中心乙太網路份額（全部速率） | B11: =idc_anet -> 0.187 | C11: =PL!D66 -> 0.1455064 | D11: =C11-B11 -> -0.041493601 | E11: =PL!D101 -> 0.1455064 | F11: =E11-B11 -> -0.041493601 | G11: =PL!D136 -> 0.1455064 | H11: =G11-B11 -> -0.041493601 | I11: IDC 2Q26 | J11: 口徑不同：IDC 含前端與非 AI；本模型分母只含 AI 後端
A12: FY2026 Arista 有效份額 vs 1 − Celestica、NVIDIA 合計（上限） | B12: =1-dell_top2 -> 0.5 | C12: =PL!D66 -> 0.1455064 | D12: =C12-B12 -> -0.3544936 | E12: =PL!D101 -> 0.1455064 | F12: =E12-B12 -> -0.3544936 | G12: =PL!D136 -> 0.1455064 | H12: =G12-B12 -> -0.3544936 | I12: Dell'Oro 2025 | J12: Arista 第三，有效份額應低於上限
A13: FY2027 AI ÷ 營收 vs Andy 先驗（54%） | B13: 0.54 | C13: =PL!E78 -> 0.40292548 | D13: =C13-B13 -> -0.13707452 | E13: =PL!E113 -> 0.40292548 | F13: =E13-B13 -> -0.13707452 | G13: =PL!E148 -> 0.40292548 | H13: =G13-B13 -> -0.13707452 | I13: 先驗_Andy_Arista A2（Drive）
A14: FY2027 Arista AI 營收 ÷ AI IT 資本支出 | C14: =PL!E69/itc_27 -> 0.0043153776 | E14: =PL!E104/itc_27 -> 0.0043153776 | G14: =PL!E139/itc_27 -> 0.0043153776 | I14: markets/network | J14: Andy 先驗 A7：每 GW 4 億美元
A15: FY2028 Arista AI 營收 ÷ AI 後端乙太網路市場（有效份額） | C15: =PL!F68 -> 0.13095576 | E15: =PL!F103 -> 0.13095576 | G15: =PL!F138 -> 0.13095576 | I15: —
A16: C. 校準
A17: 非 AI 毛利率（Derived） | C17: =PL!D80 -> 0.64666667 | E17: =PL!D115 -> 0.64666667 | G17: =PL!D150 -> 0.64666667 | I17: FY2026 錨點 | J17: AI 毛利率＝此值 − d_ai
A18: FY2027 毛利率 vs FY2026（百分點） | B18: =a26_gp/a26_rev -> 0.63 | C18: =PL!E82 -> 0.62249114 | D18: =C18-B18 -> -0.0075088618 | E18: =PL!E117 -> 0.62249114 | F18: =E18-B18 -> -0.0075088618 | G18: =PL!E152 -> 0.62249114 | H18: =G18-B18 -> -0.0075088618 | I18: 錨點 | J18: AI 占比上升使毛利率下滑
A19: 3Q26 EPS（模型）vs 公司指引中點 1.07 | B19: 1.07 | C19: =Q!E15 -> 1.0705521 | D19: =C19/B19-1 -> 0.00051595811 | E19: =Q!E15 -> 1.0705521 | F19: =E19/B19-1 -> 0.00051595811 | G19: =Q!E15 -> 1.0705521 | H19: =G19/B19-1 -> 0.00051595811 | I19: 公司（2Q26 新聞稿）
A20: D. 預留
A21: R4 產業部署路徑（markets/deploy_path/，尚未建立）：上線後以 Arista AI 營收 ÷ 部署 GW 計算每 GW 營收，對照 Andy 先驗 A7 | J21: 預留列：本版無數值

Sheet Sens
A1: Sens — 一次動一個輸入（情境 A；有效份額、非 AI 毛利率在每個案例內依 FY2026 錨點重算，FY2026 恆等於錨點）：對 FY2027、FY2028 的營收、AI 營收、毛利率與 EPS 的影響。每個案例是一個完整推導區塊（本頁下方）
A3: 案例 | B3: 設定 | C3: FY2027 營收 | D3: FY2027 AI 營收 | E3: FY2027 毛利率 | F3: FY2027 EPS | G3: FY2027 EPS 相對基準 | H3: FY2028 營收 | I3: FY2028 AI 營收 | J3: FY2028 毛利率 | K3: FY2028 EPS | L3: FY2028 EPS 相對基準
A4: 基準（情境 A） | B4: PL 區塊 A | C4: =PL!E72 -> 16.765076 | D4: =PL!E69 -> 6.7550764 | E4: =PL!E82 -> 0.62249114 | F4: =PL!E91 -> 5.4651733 | G4: =F4/F$4-1 -> 0 | H4: =PL!F72 -> 18.31118 | I4: =PL!F69 -> 7.5003798 | J4: =PL!F82 -> 0.62209027 | K4: =PL!F91 -> 5.9887102 | L4: =K4/K$4-1 -> 0
A5: 份額流失（低） | B5: 份額相對值 2027 0.80、2028 0.70、2029 0.65（NVIDIA、白牌加速） | C5: =E52 -> 15.698485 | D5: =E49 -> 5.6884854 | E5: =E62 -> 0.62492513 | F5: =E71 -> 5.1304176 | G5: =F5/F$4-1 -> -0.061252524 | H5: =F52 -> 16.644429 | I5: =F49 -> 5.8336287 | J5: =F62 -> 0.62563754 | K5: =F71 -> 5.4612046 | L5: =K5/K$4-1 -> -0.088083335
A6: 份額持平（高） | B6: 份額相對值 1.05 | C6: =E87 -> 17.476137 | D6: =E84 -> 7.466137 | E6: =E97 -> 0.62103353 | F6: =E106 -> 5.6883437 | G6: =F6/F$4-1 -> 0.040835016 | H6: =F87 -> 19.561243 | I6: =F84 -> 8.7504431 | J6: =F97 -> 0.61982652 | K6: =F106 -> 6.3854418 | L6: =K6/K$4-1 -> 0.066246588
A7: 乙太網路占比 低 | B7: 2026 70% → 2029 75% | C7: =E122 -> 16.523824 | D7: =E119 -> 6.5138236 | E7: =E132 -> 0.62301419 | F7: =E141 -> 5.3894547 | G7: =F7/F$4-1 -> -0.013854737 | H7: =F122 -> 17.975535 | I7: =F119 -> 7.1647345 | J7: =F132 -> 0.62275171 | K7: =F141 -> 5.882491 | L7: =K7/K$4-1 -> -0.01773657
A8: 乙太網路占比 高 | B8: 2026 80% → 2029 92% | C8: =E157 -> 16.976172 | D8: =E154 -> 6.9661725 | E8: =E167 -> 0.62204567 | F8: =E176 -> 5.531427 | G8: =F8/F$4-1 -> 0.012122895 | H8: =F157 -> 18.435433 | I8: =F154 -> 7.6246331 | J8: =F167 -> 0.62185152 | K8: =F176 -> 6.0275314 | L8: =K8/K$4-1 -> 0.0064824029
A9: AI 市場 ×0.8 | B9: FY2027 起 scale-out 交換器市場 ×0.8（供給受限或內容不如預期） | C9: =E192 -> 15.414061 | D9: =E189 -> 5.4040611 | E9: =E202 -> 0.62563109 | F9: =E211 -> 5.0411494 | G9: =F9/F$4-1 -> -0.07758653 | H9: =F192 -> 16.811104 | I9: =F189 -> 6.0003038 | J9: =F202 -> 0.62525116 | K9: =F211 -> 5.5150351 | L9: =K9/K$4-1 -> -0.079094667
A10: AI 市場 ×1.2 | B10: ×1.2 | C10: =E227 -> 18.116092 | D10: =E224 -> 8.1060916 | E10: =E237 -> 0.61981951 | F10: =E246 -> 5.8891971 | G10: =F10/F$4-1 -> 0.07758653 | H10: =F227 -> 19.811256 | I10: =F224 -> 9.0004557 | J10: =F237 -> 0.61940805 | K10: =F246 -> 6.4624515 | L10: =K10/K$4-1 -> 0.079105735
A11: 非 AI 成長 低 | B11: 2027 +3%、2028–29 +2% | C11: =E262 -> 16.128076 | D11: =E259 -> 6.7550764 | E11: =E272 -> 0.62153629 | F11: =E281 -> 5.2415834 | G11: =F11/F$4-1 -> -0.040911759 | H11: =F262 -> 17.06084 | I11: =F259 -> 7.5003798 | J11: =F272 -> 0.62028914 | K11: =F281 -> 5.5458342 | L11: =K11/K$4-1 -> -0.073951803
A12: 非 AI 成長 高 | B12: 2027 +15%、2028 +12%、2029 +10% | C12: =E297 -> 17.220076 | D12: =E294 -> 6.7550764 | E12: =E307 -> 0.62312992 | F12: =E316 -> 5.6248803 | G12: =F12/F$4-1 -> 0.029222685 | H12: =F297 -> 19.22118 | I12: =F294 -> 7.5003798 | J12: =F307 -> 0.62325381 | K12: =F316 -> 6.3115189 | L12: =K12/K$4-1 -> 0.053902882
A13: AI 毛利率差距 3pt | B13: AI 毛利率只低 3 個百分點 | C13: =E332 -> 16.765076 | D13: =E329 -> 6.7550764 | E13: =E342 -> 0.62624557 | F13: =E351 -> 5.5041444 | G13: =F13/F$4-1 -> 0.0071308147 | H13: =F332 -> 18.31118 | I13: =F329 -> 7.5003798 | J13: =F342 -> 0.62604514 | K13: =F351 -> 6.0335477 | L13: =K13/K$4-1 -> 0.0074870035
A14: AI 毛利率差距 10pt | B14: 低 10 個百分點 | C14: =E367 -> 16.765076 | D14: =E364 -> 6.7550764 | E14: =E377 -> 0.61748523 | F14: =E386 -> 5.4132118 | G14: =F14/F$4-1 -> -0.009507753 | H14: =F367 -> 18.31118 | I14: =F364 -> 7.5003798 | J14: =F377 -> 0.61681712 | K14: =F386 -> 5.9289268 | L14: =K14/K$4-1 -> -0.0099826713
A15: 營業費用率 +2pt | B15: 營業費用額外 +2% × 營收 | C15: =E402 -> 16.765076 | D15: =E399 -> 6.7550764 | E15: =E412 -> 0.62249114 | F15: =E421 -> 5.2575725 | G15: =F15/F$4-1 -> -0.037986128 | H15: =F402 -> 18.31118 | I15: =F399 -> 7.5003798 | J15: =F412 -> 0.62209027 | K15: =F421 -> 5.7619641 | L15: =K15/K$4-1 -> -0.037862254
A16: 顆數情境 B | B16: CY2028 ×0.8、CY2029 ×0.85 | C16: =PL!E107 -> 16.765076 | D16: =PL!E104 -> 6.7550764 | E16: =PL!E117 -> 0.62249114 | F16: =PL!E126 -> 5.4651733 | G16: =F16/F$4-1 -> 0 | H16: =PL!F107 -> 16.811104 | I16: =PL!F104 -> 6.0003038 | J16: =PL!F117 -> 0.62525116 | K16: =PL!F126 -> 5.5096221 | L16: =K16/K$4-1 -> -0.079998541
A17: 顆數情境 C | B17: CY2028–29 ×0.6 | C17: =PL!E142 -> 16.765076 | D17: =PL!E139 -> 6.7550764 | E17: =PL!E152 -> 0.62249114 | F17: =PL!E161 -> 5.4651733 | G17: =F17/F$4-1 -> 0 | H17: =PL!F142 -> 15.311028 | I17: =PL!F139 -> 4.5002279 | J17: =PL!F152 -> 0.62903143 | K17: =PL!F161 -> 4.9667642 | L17: =K17/K$4-1 -> -0.17064542
A19: 讀法：FY2027 三情境相同；顆數情境 B、C 的差異從 FY2028 起。份額與乙太網路占比的案例中，FY2026 有效份額依新的乙太網路占比重算，所以 FY2026 恆等於錨點。
A21: 目標價參數敏感度（v0.2）：加權目標價（Val 第 0 節）一次動一個參數；PL 延伸期的收斂路徑不隨 tp_g 變動，tp_g 只改再投資率與永續成長
A22: 參數 | B22: 設定（低／高） | C22: 低：加權目標價 | D22: 低：相對基準 | E22: 高：加權目標價 | F22: 高：相對基準 | G22: 基準加權目標價
A23: tp_r ±1pt | B23: 折現率 −1pt／＋1pt | C23: =tp_w_dcf*(tp_wA*(MAX(0,Val!B7*Val!$G$7*(1-MIN(0.8,tp_g/tp_roe))/(1+(tp_r-0.01))^Val!$F$7+Val!B8*Val!$G$8*(1-MIN(0.8,tp_g/tp_roe))/(1+(tp_r-0.01))^Val!$F$8+Val!B9*Val!$G$9*(1-MIN(0.8,tp_g/tp_roe))/(1+(tp_r-0.01))^Val!$F$9+Val!B10*Val!$G$10*(1-MIN(0.8,tp_g/tp_roe))/(1+(tp_r-0.01))^Val!$F$10+Val!B11*Val!$G$11*(1-MIN(0.8,tp_g/tp_roe))/(1+(tp_r-0.01))^Val!$F$11+Val!B12*Val!$G$12*(1-MIN(0.8,tp_g/tp_roe))/(1+(tp_r-0.01))^Val!$F$12+Val!B12*(1-MIN(0.8,tp_g/tp_roe))*(1+tp_g)/((tp_r-0.01)-tp_g)/(1+(tp_r-0.01))^Val!$F$12))+tp_wB*(MAX(0,Val!C7*Val!$G$7*(1-MIN(0.8,tp_g/tp_roe))/(1+(tp_r-0.01))^Val!$F$7+Val!C8*Val!$G$8*(1-MIN(0.8,tp_g/tp_roe))/(1+(tp_r-0.01))^Val!$F$8+Val!C9*Val!$G$9*(1-MIN(0.8,tp_g/tp_roe))/(1+(tp_r-0.01))^Val!$F$9+Val!C10*Val!$G$10*(1-MIN(0.8,tp_g/tp_roe))/(1+(tp_r-0.01))^Val!$F$10+Val!C11*Val!$G$11*(1-MIN(0.8,tp_g/tp_roe))/(1+(tp_r-0.01))^Val!$F$11+Val!C12*Val!$G$12*(1-MIN(0.8,tp_g/tp_roe))/(1+(tp_r-0.01))^Val!$F$12+Val!C12*(1-MIN(0.8,tp_g/tp_roe))*(1+tp_g)/((tp_r-0.01)-tp_g)/(1+(tp_r-0.01))^Val!$F$12))+tp_wC*(MAX(0,Val!D7*Val!$G$7*(1-MIN(0.8,tp_g/tp_roe))/(1+(tp_r-0.01))^Val!$F$7+Val!D8*Val!$G$8*(1-MIN(0.8,tp_g/tp_roe))/(1+(tp_r-0.01))^Val!$F$8+Val!D9*Val!$G$9*(1-MIN(0.8,tp_g/tp_roe))/(1+(tp_r-0.01))^Val!$F$9+Val!D10*Val!$G$10*(1-MIN(0.8,tp_g/tp_roe))/(1+(tp_r-0.01))^Val!$F$10+Val!D11*Val!$G$11*(1-MIN(0.8,tp_g/tp_roe))/(1+(tp_r-0.01))^Val!$F$11+Val!D12*Val!$G$12*(1-MIN(0.8,tp_g/tp_roe))/(1+(tp_r-0.01))^Val!$F$12+Val!D12*(1-MIN(0.8,tp_g/tp_roe))*(1+tp_g)/((tp_r-0.01)-tp_g)/(1+(tp_r-0.01))^Val!$F$12)))*(1+(tp_r-0.01))+(1-tp_w_dcf)*tp_comp_adj -> 163.54342 | D23: =C23/G23-1 -> 0.053056018 | E23: =tp_w_dcf*(tp_wA*(MAX(0,Val!B7*Val!$G$7*(1-MIN(0.8,tp_g/tp_roe))/(1+(tp_r+0.01))^Val!$F$7+Val!B8*Val!$G$8*(1-MIN(0.8,tp_g/tp_roe))/(1+(tp_r+0.01))^Val!$F$8+Val!B9*Val!$G$9*(1-MIN(0.8,tp_g/tp_roe))/(1+(tp_r+0.01))^Val!$F$9+Val!B10*Val!$G$10*(1-MIN(0.8,tp_g/tp_roe))/(1+(tp_r+0.01))^Val!$F$10+Val!B11*Val!$G$11*(1-MIN(0.8,tp_g/tp_roe))/(1+(tp_r+0.01))^Val!$F$11+Val!B12*Val!$G$12*(1-MIN(0.8,tp_g/tp_roe))/(1+(tp_r+0.01))^Val!$F$12+Val!B12*(1-MIN(0.8,tp_g/tp_roe))*(1+tp_g)/((tp_r+0.01)-tp_g)/(1+(tp_r+0.01))^Val!$F$12))+tp_wB*(MAX(0,Val!C7*Val!$G$7*(1-MIN(0.8,tp_g/tp_roe))/(1+(tp_r+0.01))^Val!$F$7+Val!C8*Val!$G$8*(1-MIN(0.8,tp_g/tp_roe))/(1+(tp_r+0.01))^Val!$F$8+Val!C9*Val!$G$9*(1-MIN(0.8,tp_g/tp_roe))/(1+(tp_r+0.01))^Val!$F$9+Val!C10*Val!$G$10*(1-MIN(0.8,tp_g/tp_roe))/(1+(tp_r+0.01))^Val!$F$10+Val!C11*Val!$G$11*(1-MIN(0.8,tp_g/tp_roe))/(1+(tp_r+0.01))^Val!$F$11+Val!C12*Val!$G$12*(1-MIN(0.8,tp_g/tp_roe))/(1+(tp_r+0.01))^Val!$F$12+Val!C12*(1-MIN(0.8,tp_g/tp_roe))*(1+tp_g)/((tp_r+0.01)-tp_g)/(1+(tp_r+0.01))^Val!$F$12))+tp_wC*(MAX(0,Val!D7*Val!$G$7*(1-MIN(0.8,tp_g/tp_roe))/(1+(tp_r+0.01))^Val!$F$7+Val!D8*Val!$G$8*(1-MIN(0.8,tp_g/tp_roe))/(1+(tp_r+0.01))^Val!$F$8+Val!D9*Val!$G$9*(1-MIN(0.8,tp_g/tp_roe))/(1+(tp_r+0.01))^Val!$F$9+Val!D10*Val!$G$10*(1-MIN(0.8,tp_g/tp_roe))/(1+(tp_r+0.01))^Val!$F$10+Val!D11*Val!$G$11*(1-MIN(0.8,tp_g/tp_roe))/(1+(tp_r+0.01))^Val!$F$11+Val!D12*Val!$G$12*(1-MIN(0.8,tp_g/tp_roe))/(1+(tp_r+0.01))^Val!$F$12+Val!D12*(1-MIN(0.8,tp_g/tp_roe))*(1+tp_g)/((tp_r+0.01)-tp_g)/(1+(tp_r+0.01))^Val!$F$12)))*(1+(tp_r+0.01))+(1-tp_w_dcf)*tp_comp_adj -> 149.41707 | F23: =E23/G23-1 -> -0.037903536 | G23: =Val!$B$40 -> 155.30363
A24: tp_g ±1pt | B24: 長期成長 −1pt／＋1pt | C24: =tp_w_dcf*(tp_wA*(MAX(0,Val!B7*Val!$G$7*(1-MIN(0.8,(tp_g-0.01)/tp_roe))/(1+tp_r)^Val!$F$7+Val!B8*Val!$G$8*(1-MIN(0.8,(tp_g-0.01)/tp_roe))/(1+tp_r)^Val!$F$8+Val!B9*Val!$G$9*(1-MIN(0.8,(tp_g-0.01)/tp_roe))/(1+tp_r)^Val!$F$9+Val!B10*Val!$G$10*(1-MIN(0.8,(tp_g-0.01)/tp_roe))/(1+tp_r)^Val!$F$10+Val!B11*Val!$G$11*(1-MIN(0.8,(tp_g-0.01)/tp_roe))/(1+tp_r)^Val!$F$11+Val!B12*Val!$G$12*(1-MIN(0.8,(tp_g-0.01)/tp_roe))/(1+tp_r)^Val!$F$12+Val!B12*(1-MIN(0.8,(tp_g-0.01)/tp_roe))*(1+(tp_g-0.01))/(tp_r-(tp_g-0.01))/(1+tp_r)^Val!$F$12))+tp_wB*(MAX(0,Val!C7*Val!$G$7*(1-MIN(0.8,(tp_g-0.01)/tp_roe))/(1+tp_r)^Val!$F$7+Val!C8*Val!$G$8*(1-MIN(0.8,(tp_g-0.01)/tp_roe))/(1+tp_r)^Val!$F$8+Val!C9*Val!$G$9*(1-MIN(0.8,(tp_g-0.01)/tp_roe))/(1+tp_r)^Val!$F$9+Val!C10*Val!$G$10*(1-MIN(0.8,(tp_g-0.01)/tp_roe))/(1+tp_r)^Val!$F$10+Val!C11*Val!$G$11*(1-MIN(0.8,(tp_g-0.01)/tp_roe))/(1+tp_r)^Val!$F$11+Val!C12*Val!$G$12*(1-MIN(0.8,(tp_g-0.01)/tp_roe))/(1+tp_r)^Val!$F$12+Val!C12*(1-MIN(0.8,(tp_g-0.01)/tp_roe))*(1+(tp_g-0.01))/(tp_r-(tp_g-0.01))/(1+tp_r)^Val!$F$12))+tp_wC*(MAX(0,Val!D7*Val!$G$7*(1-MIN(0.8,(tp_g-0.01)/tp_roe))/(1+tp_r)^Val!$F$7+Val!D8*Val!$G$8*(1-MIN(0.8,(tp_g-0.01)/tp_roe))/(1+tp_r)^Val!$F$8+Val!D9*Val!$G$9*(1-MIN(0.8,(tp_g-0.01)/tp_roe))/(1+tp_r)^Val!$F$9+Val!D10*Val!$G$10*(1-MIN(0.8,(tp_g-0.01)/tp_roe))/(1+tp_r)^Val!$F$10+Val!D11*Val!$G$11*(1-MIN(0.8,(tp_g-0.01)/tp_roe))/(1+tp_r)^Val!$F$11+Val!D12*Val!$G$12*(1-MIN(0.8,(tp_g-0.01)/tp_roe))/(1+tp_r)^Val!$F$12+Val!D12*(1-MIN(0.8,(tp_g-0.01)/tp_roe))*(1+(tp_g-0.01))/(tp_r-(tp_g-0.01))/(1+tp_r)^Val!$F$12)))*(1+tp_r)+(1-tp_w_dcf)*tp_comp_adj -> 152.18475 | D24: =C24/G24-1 -> -0.020082439 | E24: =tp_w_dcf*(tp_wA*(MAX(0,Val!B7*Val!$G$7*(1-MIN(0.8,(tp_g+0.01)/tp_roe))/(1+tp_r)^Val!$F$7+Val!B8*Val!$G$8*(1-MIN(0.8,(tp_g+0.01)/tp_roe))/(1+tp_r)^Val!$F$8+Val!B9*Val!$G$9*(1-MIN(0.8,(tp_g+0.01)/tp_roe))/(1+tp_r)^Val!$F$9+Val!B10*Val!$G$10*(1-MIN(0.8,(tp_g+0.01)/tp_roe))/(1+tp_r)^Val!$F$10+Val!B11*Val!$G$11*(1-MIN(0.8,(tp_g+0.01)/tp_roe))/(1+tp_r)^Val!$F$11+Val!B12*Val!$G$12*(1-MIN(0.8,(tp_g+0.01)/tp_roe))/(1+tp_r)^Val!$F$12+Val!B12*(1-MIN(0.8,(tp_g+0.01)/tp_roe))*(1+(tp_g+0.01))/(tp_r-(tp_g+0.01))/(1+tp_r)^Val!$F$12))+tp_wB*(MAX(0,Val!C7*Val!$G$7*(1-MIN(0.8,(tp_g+0.01)/tp_roe))/(1+tp_r)^Val!$F$7+Val!C8*Val!$G$8*(1-MIN(0.8,(tp_g+0.01)/tp_roe))/(1+tp_r)^Val!$F$8+Val!C9*Val!$G$9*(1-MIN(0.8,(tp_g+0.01)/tp_roe))/(1+tp_r)^Val!$F$9+Val!C10*Val!$G$10*(1-MIN(0.8,(tp_g+0.01)/tp_roe))/(1+tp_r)^Val!$F$10+Val!C11*Val!$G$11*(1-MIN(0.8,(tp_g+0.01)/tp_roe))/(1+tp_r)^Val!$F$11+Val!C12*Val!$G$12*(1-MIN(0.8,(tp_g+0.01)/tp_roe))/(1+tp_r)^Val!$F$12+Val!C12*(1-MIN(0.8,(tp_g+0.01)/tp_roe))*(1+(tp_g+0.01))/(tp_r-(tp_g+0.01))/(1+tp_r)^Val!$F$12))+tp_wC*(MAX(0,Val!D7*Val!$G$7*(1-MIN(0.8,(tp_g+0.01)/tp_roe))/(1+tp_r)^Val!$F$7+Val!D8*Val!$G$8*(1-MIN(0.8,(tp_g+0.01)/tp_roe))/(1+tp_r)^Val!$F$8+Val!D9*Val!$G$9*(1-MIN(0.8,(tp_g+0.01)/tp_roe))/(1+tp_r)^Val!$F$9+Val!D10*Val!$G$10*(1-MIN(0.8,(tp_g+0.01)/tp_roe))/(1+tp_r)^Val!$F$10+Val!D11*Val!$G$11*(1-MIN(0.8,(tp_g+0.01)/tp_roe))/(1+tp_r)^Val!$F$11+Val!D12*Val!$G$12*(1-MIN(0.8,(tp_g+0.01)/tp_roe))/(1+tp_r)^Val!$F$12+Val!D12*(1-MIN(0.8,(tp_g+0.01)/tp_roe))*(1+(tp_g+0.01))/(tp_r-(tp_g+0.01))/(1+tp_r)^Val!$F$12)))*(1+tp_r)+(1-tp_w_dcf)*tp_comp_adj -> 159.84428 | F24: =E24/G24-1 -> 0.029237276 | G24: =Val!$B$40 -> 155.30363
A25: tp_w_dcf 0.3／0.7 | B25: DCF 權重 0.3／0.7 | C25: =0.3*(tp_wA*(MAX(0,Val!B7*Val!$G$7*(1-MIN(0.8,tp_g/tp_roe))/(1+tp_r)^Val!$F$7+Val!B8*Val!$G$8*(1-MIN(0.8,tp_g/tp_roe))/(1+tp_r)^Val!$F$8+Val!B9*Val!$G$9*(1-MIN(0.8,tp_g/tp_roe))/(1+tp_r)^Val!$F$9+Val!B10*Val!$G$10*(1-MIN(0.8,tp_g/tp_roe))/(1+tp_r)^Val!$F$10+Val!B11*Val!$G$11*(1-MIN(0.8,tp_g/tp_roe))/(1+tp_r)^Val!$F$11+Val!B12*Val!$G$12*(1-MIN(0.8,tp_g/tp_roe))/(1+tp_r)^Val!$F$12+Val!B12*(1-MIN(0.8,tp_g/tp_roe))*(1+tp_g)/(tp_r-tp_g)/(1+tp_r)^Val!$F$12))+tp_wB*(MAX(0,Val!C7*Val!$G$7*(1-MIN(0.8,tp_g/tp_roe))/(1+tp_r)^Val!$F$7+Val!C8*Val!$G$8*(1-MIN(0.8,tp_g/tp_roe))/(1+tp_r)^Val!$F$8+Val!C9*Val!$G$9*(1-MIN(0.8,tp_g/tp_roe))/(1+tp_r)^Val!$F$9+Val!C10*Val!$G$10*(1-MIN(0.8,tp_g/tp_roe))/(1+tp_r)^Val!$F$10+Val!C11*Val!$G$11*(1-MIN(0.8,tp_g/tp_roe))/(1+tp_r)^Val!$F$11+Val!C12*Val!$G$12*(1-MIN(0.8,tp_g/tp_roe))/(1+tp_r)^Val!$F$12+Val!C12*(1-MIN(0.8,tp_g/tp_roe))*(1+tp_g)/(tp_r-tp_g)/(1+tp_r)^Val!$F$12))+tp_wC*(MAX(0,Val!D7*Val!$G$7*(1-MIN(0.8,tp_g/tp_roe))/(1+tp_r)^Val!$F$7+Val!D8*Val!$G$8*(1-MIN(0.8,tp_g/tp_roe))/(1+tp_r)^Val!$F$8+Val!D9*Val!$G$9*(1-MIN(0.8,tp_g/tp_roe))/(1+tp_r)^Val!$F$9+Val!D10*Val!$G$10*(1-MIN(0.8,tp_g/tp_roe))/(1+tp_r)^Val!$F$10+Val!D11*Val!$G$11*(1-MIN(0.8,tp_g/tp_roe))/(1+tp_r)^Val!$F$11+Val!D12*Val!$G$12*(1-MIN(0.8,tp_g/tp_roe))/(1+tp_r)^Val!$F$12+Val!D12*(1-MIN(0.8,tp_g/tp_roe))*(1+tp_g)/(tp_r-tp_g)/(1+tp_r)^Val!$F$12)))*(1+tp_r)+(1-0.3)*tp_comp_adj -> 182.52712 | D25: =C25/G25-1 -> 0.17529206 | E25: =0.7*(tp_wA*(MAX(0,Val!B7*Val!$G$7*(1-MIN(0.8,tp_g/tp_roe))/(1+tp_r)^Val!$F$7+Val!B8*Val!$G$8*(1-MIN(0.8,tp_g/tp_roe))/(1+tp_r)^Val!$F$8+Val!B9*Val!$G$9*(1-MIN(0.8,tp_g/tp_roe))/(1+tp_r)^Val!$F$9+Val!B10*Val!$G$10*(1-MIN(0.8,tp_g/tp_roe))/(1+tp_r)^Val!$F$10+Val!B11*Val!$G$11*(1-MIN(0.8,tp_g/tp_roe))/(1+tp_r)^Val!$F$11+Val!B12*Val!$G$12*(1-MIN(0.8,tp_g/tp_roe))/(1+tp_r)^Val!$F$12+Val!B12*(1-MIN(0.8,tp_g/tp_roe))*(1+tp_g)/(tp_r-tp_g)/(1+tp_r)^Val!$F$12))+tp_wB*(MAX(0,Val!C7*Val!$G$7*(1-MIN(0.8,tp_g/tp_roe))/(1+tp_r)^Val!$F$7+Val!C8*Val!$G$8*(1-MIN(0.8,tp_g/tp_roe))/(1+tp_r)^Val!$F$8+Val!C9*Val!$G$9*(1-MIN(0.8,tp_g/tp_roe))/(1+tp_r)^Val!$F$9+Val!C10*Val!$G$10*(1-MIN(0.8,tp_g/tp_roe))/(1+tp_r)^Val!$F$10+Val!C11*Val!$G$11*(1-MIN(0.8,tp_g/tp_roe))/(1+tp_r)^Val!$F$11+Val!C12*Val!$G$12*(1-MIN(0.8,tp_g/tp_roe))/(1+tp_r)^Val!$F$12+Val!C12*(1-MIN(0.8,tp_g/tp_roe))*(1+tp_g)/(tp_r-tp_g)/(1+tp_r)^Val!$F$12))+tp_wC*(MAX(0,Val!D7*Val!$G$7*(1-MIN(0.8,tp_g/tp_roe))/(1+tp_r)^Val!$F$7+Val!D8*Val!$G$8*(1-MIN(0.8,tp_g/tp_roe))/(1+tp_r)^Val!$F$8+Val!D9*Val!$G$9*(1-MIN(0.8,tp_g/tp_roe))/(1+tp_r)^Val!$F$9+Val!D10*Val!$G$10*(1-MIN(0.8,tp_g/tp_roe))/(1+tp_r)^Val!$F$10+Val!D11*Val!$G$11*(1-MIN(0.8,tp_g/tp_roe))/(1+tp_r)^Val!$F$11+Val!D12*Val!$G$12*(1-MIN(0.8,tp_g/tp_roe))/(1+tp_r)^Val!$F$12+Val!D12*(1-MIN(0.8,tp_g/tp_roe))*(1+tp_g)/(tp_r-tp_g)/(1+tp_r)^Val!$F$12)))*(1+tp_r)+(1-0.7)*tp_comp_adj -> 128.08014 | F25: =E25/G25-1 -> -0.17529206 | G25: =Val!$B$40 -> 155.30363
A40: 案例區塊：份額流失（低）（情境 A）
A41: 項目 | B41: 單位 | C41: FY2025A | D41: FY2026（錨點） | E41: FY2027 | F41: FY2028 | G41: FY2029 | H41: 說明
A42: A. AI 營收（D 欄＝FY2026 校準年；E–G＝FY2027–FY2029）
A43: AI 後端 scale-out 交換器市場 × 情境顆數係數 | B43: US$B | D43: =mkt_26*1 -> 32.0719 | E43: =mkt_27*1*1 -> 61.085 | F43: =mkt_28*um28_A*1 -> 69.005 | G43: =mkt_29*um29_A*1 -> 78.48215
A44: 乙太網路占比 | B44: % | D44: =eth_26 -> 0.75 | E44: =eth_27 -> 0.8 | F44: =eth_28 -> 0.83 | G44: =eth_29 -> 0.85
A45: AI 後端乙太網路交換器市場 | B45: US$B | D45: =D43*D44 -> 24.053925 | E45: =E43*E44 -> 48.868 | F45: =F43*F44 -> 57.27415 | G45: =G43*G44 -> 66.709828
A46: Arista 有效份額（FY2026 校準）＝ AI 目標 ÷ 乙太網路市場 | B46: % | D46: =a26_ai/D45 -> 0.1455064 | H46: Derived：分子含前端與 scale-across，所以高於純後端份額；FY2027 起乘相對值
A47: 份額相對值（÷ FY2026） | B47: x | D47: =1 -> 1 | E47: =RLO_27 -> 0.8 | F47: =RLO_28 -> 0.7 | G47: =RLO_29 -> 0.65
A48: Arista 有效份額 | B48: % | D48: =$D$46*D47 -> 0.1455064 | E48: =$D$46*E47 -> 0.11640512 | F48: =$D$46*F47 -> 0.10185448 | G48: =$D$46*G47 -> 0.094579159
A49: AI 營收 | B49: US$B | C49: =a25_ai -> 1.63 | D49: =D45*D48 -> 3.5 | E49: =E45*E48 -> 5.6884854 | F49: =F45*F48 -> 5.8336287 | G49: =G45*G48 -> 6.3093594
A50: B. 非 AI 與合計
A51: 非 AI 營收 | B51: US$B | C51: =a25_nai -> 7.3757 | D51: =a26_nai -> 9.1 | E51: =D51*(1+g_nai27) -> 10.01 | F51: =E51*(1+g_nai28) -> 10.8108 | G51: =F51*(1+g_nai29) -> 11.459448
A52: 營收 | B52: US$B | C52: =a25_rev -> 9.0057 | D52: =D49+D51 -> 12.6 | E52: =E49+E51 -> 15.698485 | F52: =F49+F51 -> 16.644429 | G52: =G49+G51 -> 17.768807
A53: 服務營收 | B53: US$B | C53: =svc25 -> 1.4288 | D53: =C53*(1+g_svc26) -> 1.743136 | E53: =D53*(1+g_svc27) -> 2.0046064 | F53: =E53*(1+g_svc28) -> 2.205067 | G53: =F53*(1+g_svc29) -> 2.3814724 | H53: 公司營收線：Service
A54: 產品：非 AI（園區、企業、路由等；＝非 AI − 服務） | B54: US$B | C54: =C51-C53 -> 5.9469 | D54: =D51-D53 -> 7.356864 | E54: =E51-E53 -> 8.0053936 | F54: =F51-F53 -> 8.605733 | G54: =G51-G53 -> 9.0779756
A55: 產品營收（AI＋非 AI 產品） | B55: US$B | C55: =C49+C54 -> 7.5769 | D55: =D49+D54 -> 10.856864 | E55: =E49+E54 -> 13.693879 | F55: =F49+F54 -> 14.439362 | G55: =G49+G54 -> 15.387335 | H55: 公司營收線：Product
A56: 檢查：產品＋服務 − 合併營收 | B56: US$B | C56: =C55+C53-C52 -> 0 | D56: =D55+D53-D52 -> 0 | E56: =E55+E53-E52 -> 0 | F56: =F55+F53-F52 -> 0 | G56: =G55+G53-G52 -> 0
A57: 營收年增 | B57: % | D57: =D52/C52-1 -> 0.39911389 | E57: =E52/D52-1 -> 0.24591154 | F57: =F52/E52-1 -> 0.060256983 | G57: =G52/F52-1 -> 0.067552855
A58: AI ÷ 營收 | B58: % | C58: =C49/C52 -> 0.18099648 | D58: =D49/D52 -> 0.27777778 | E58: =E49/E52 -> 0.36235887 | F58: =F49/F52 -> 0.35048537 | G58: =G49/G52 -> 0.35508063
A59: C. 損益
A60: 非 AI 毛利率 ＝ 錨點毛利率 ＋ 差距 × AI 占比（FY2026 校準） | B60: % | D60: =a26_gp/a26_rev+d_ai*D58 -> 0.64666667 | H60: Derived：讓 FY2026 毛利率等於錨點；AI 毛利率＝非 AI − 差距。FY2027 起毛利率隨 AI 占比變動
A61: 毛利 | B61: US$B | C61: =a25_gp -> 5.8154 | D61: =a26_gp -> 7.938 | E61: =$D$60*E51+($D$60-d_ai)*E49 -> 9.8103781 | F61: =$D$60*F51+($D$60-d_ai)*F49 -> 10.41338 | G61: =$D$60*G51+($D$60-d_ai)*G49 -> 11.111934
A62: 毛利率 | B62: % | C62: =C61/C52 -> 0.64574658 | D62: =D61/D52 -> 0.63 | E62: =E61/E52 -> 0.62492513 | F62: =F61/F52 -> 0.62563754 | G62: =G61/G52 -> 0.62536183
A63: 營業費用（基準路徑） | B63: US$B | C63: =a25_opx -> 1.4784 | D63: =a26_opx -> 1.827 | E63: =D63*(1+MAX(0,phi*E57)) -> 2.0741042 | F63: =E63*(1+MAX(0,phi*F57)) -> 2.1428428 | G63: =F63*(1+MAX(0,phi*G57)) -> 2.2224581
A64: 營業費用 | B64: US$B | C64: =C63 -> 1.4784 | D64: =D63 -> 1.827 | E64: =E63+0*E52 -> 2.0741042 | F64: =F63+0*F52 -> 2.1428428 | G64: =G63+0*G52 -> 2.2224581
A65: 營業利益 | B65: US$B | C65: =C61-C64 -> 4.337 | D65: =D61-D64 -> 6.111 | E65: =E61-E64 -> 7.7362739 | F65: =F61-F64 -> 8.2705367 | G65: =G61-G64 -> 8.8894757
A66: 營業利益率 | B66: % | C66: =C65/C52 -> 0.48158389 | D66: =D65/D52 -> 0.485 | E66: =E65/E52 -> 0.49280384 | F66: =F65/F52 -> 0.4968952 | G66: =G65/G52 -> 0.50028545
A67: 其他收益 | B67: US$B | C67: =a25_oth -> 0.3936 | D67: =a26_oth -> 0.4999 | E67: =oth_f -> 0.55 | F67: =oth_f -> 0.55 | G67: =oth_f -> 0.55
A68: 有效稅率 | B68: % | C68: =1-a25_ni/(a25_oi+a25_oth) -> 0.19545089 | D68: =1-a26_ni/(a26_oi+a26_oth) -> 0.20965269 | E68: =tx_f -> 0.21 | F68: =tx_f -> 0.21 | G68: =tx_f -> 0.21
A69: 淨利（non-GAAP） | B69: US$B | C69: =a25_ni -> 3.806 | D69: =a26_ni -> 5.224907 | E69: =(E65+E67)*(1-E68) -> 6.5461564 | F69: =(F65+F67)*(1-F68) -> 6.968224 | G69: =(G65+G67)*(1-G68) -> 7.4571858
A70: 稀釋股數 | B70: 十億股 | C70: =a25_sh -> 1.2757 | D70: =a26_sh -> 1.27595 | E70: =D70*(1+sh_g) -> 1.27595 | F70: =E70*(1+sh_g) -> 1.27595 | G70: =F70*(1+sh_g) -> 1.27595
A71: EPS（non-GAAP） | B71: US$ | C71: =C69/C70 -> 2.9834601 | D71: =D69/D70 -> 4.0949152 | E71: =E69/E70 -> 5.1304176 | F71: =F69/F70 -> 5.4612046 | G71: =G69/G70 -> 5.8444185
A72: EPS 年增 | B72: % | D72: =D71/C71-1 -> 0.37253896 | E72: =E71/D71-1 -> 0.25287519 | F72: =F71/E71-1 -> 0.064475644 | G72: =G71/F71-1 -> 0.070170224
A75: 案例區塊：份額持平（高）（情境 A）
A76: 項目 | B76: 單位 | C76: FY2025A | D76: FY2026（錨點） | E76: FY2027 | F76: FY2028 | G76: FY2029 | H76: 說明
A77: A. AI 營收（D 欄＝FY2026 校準年；E–G＝FY2027–FY2029）
A78: AI 後端 scale-out 交換器市場 × 情境顆數係數 | B78: US$B | D78: =mkt_26*1 -> 32.0719 | E78: =mkt_27*1*1 -> 61.085 | F78: =mkt_28*um28_A*1 -> 69.005 | G78: =mkt_29*um29_A*1 -> 78.48215
A79: 乙太網路占比 | B79: % | D79: =eth_26 -> 0.75 | E79: =eth_27 -> 0.8 | F79: =eth_28 -> 0.83 | G79: =eth_29 -> 0.85
A80: AI 後端乙太網路交換器市場 | B80: US$B | D80: =D78*D79 -> 24.053925 | E80: =E78*E79 -> 48.868 | F80: =F78*F79 -> 57.27415 | G80: =G78*G79 -> 66.709828
A81: Arista 有效份額（FY2026 校準）＝ AI 目標 ÷ 乙太網路市場 | B81: % | D81: =a26_ai/D80 -> 0.1455064 | H81: Derived：分子含前端與 scale-across，所以高於純後端份額；FY2027 起乘相對值
A82: 份額相對值（÷ FY2026） | B82: x | D82: =1 -> 1 | E82: =RHI_27 -> 1.05 | F82: =RHI_28 -> 1.05 | G82: =RHI_29 -> 1.05
A83: Arista 有效份額 | B83: % | D83: =$D$81*D82 -> 0.1455064 | E83: =$D$81*E82 -> 0.15278172 | F83: =$D$81*F82 -> 0.15278172 | G83: =$D$81*G82 -> 0.15278172
A84: AI 營收 | B84: US$B | C84: =a25_ai -> 1.63 | D84: =D80*D83 -> 3.5 | E84: =E80*E83 -> 7.466137 | F84: =F80*F83 -> 8.7504431 | G84: =G80*G83 -> 10.192042
A85: B. 非 AI 與合計
A86: 非 AI 營收 | B86: US$B | C86: =a25_nai -> 7.3757 | D86: =a26_nai -> 9.1 | E86: =D86*(1+g_nai27) -> 10.01 | F86: =E86*(1+g_nai28) -> 10.8108 | G86: =F86*(1+g_nai29) -> 11.459448
A87: 營收 | B87: US$B | C87: =a25_rev -> 9.0057 | D87: =D84+D86 -> 12.6 | E87: =E84+E86 -> 17.476137 | F87: =F84+F86 -> 19.561243 | G87: =G84+G86 -> 21.65149
A88: 服務營收 | B88: US$B | C88: =svc25 -> 1.4288 | D88: =C88*(1+g_svc26) -> 1.743136 | E88: =D88*(1+g_svc27) -> 2.0046064 | F88: =E88*(1+g_svc28) -> 2.205067 | G88: =F88*(1+g_svc29) -> 2.3814724 | H88: 公司營收線：Service
A89: 產品：非 AI（園區、企業、路由等；＝非 AI − 服務） | B89: US$B | C89: =C86-C88 -> 5.9469 | D89: =D86-D88 -> 7.356864 | E89: =E86-E88 -> 8.0053936 | F89: =F86-F88 -> 8.605733 | G89: =G86-G88 -> 9.0779756
A90: 產品營收（AI＋非 AI 產品） | B90: US$B | C90: =C84+C89 -> 7.5769 | D90: =D84+D89 -> 10.856864 | E90: =E84+E89 -> 15.471531 | F90: =F84+F89 -> 17.356176 | G90: =G84+G89 -> 19.270018 | H90: 公司營收線：Product
A91: 檢查：產品＋服務 − 合併營收 | B91: US$B | C91: =C90+C88-C87 -> 0 | D91: =D90+D88-D87 -> 0 | E91: =E90+E88-E87 -> 0 | F91: =F90+F88-F87 -> 0 | G91: =G90+G88-G87 -> 0
A92: 營收年增 | B92: % | D92: =D87/C87-1 -> 0.39911389 | E92: =E87/D87-1 -> 0.386995 | F92: =F87/E87-1 -> 0.11931161 | G92: =G87/F87-1 -> 0.10685655
A93: AI ÷ 營收 | B93: % | C93: =C84/C87 -> 0.18099648 | D93: =D84/D87 -> 0.27777778 | E93: =E84/E87 -> 0.42721896 | F93: =F84/F87 -> 0.44733574 | G93: =G84/G87 -> 0.47073167
A94: C. 損益
A95: 非 AI 毛利率 ＝ 錨點毛利率 ＋ 差距 × AI 占比（FY2026 校準） | B95: % | D95: =a26_gp/a26_rev+d_ai*D93 -> 0.64666667 | H95: Derived：讓 FY2026 毛利率等於錨點；AI 毛利率＝非 AI − 差距。FY2027 起毛利率隨 AI 占比變動
A96: 毛利 | B96: US$B | C96: =a25_gp -> 5.8154 | D96: =a26_gp -> 7.938 | E96: =$D$95*E86+($D$95-d_ai)*E84 -> 10.853267 | F96: =$D$95*F86+($D$95-d_ai)*F84 -> 12.124577 | G96: =$D$95*G86+($D$95-d_ai)*G84 -> 13.389774
A97: 毛利率 | B97: % | C97: =C96/C87 -> 0.64574658 | D97: =D96/D87 -> 0.63 | E97: =E96/E87 -> 0.62103353 | F97: =F96/F87 -> 0.61982652 | G97: =G96/G87 -> 0.61842277
A98: 營業費用（基準路徑） | B98: US$B | C98: =a25_opx -> 1.4784 | D98: =a26_opx -> 1.827 | E98: =D98*(1+MAX(0,phi*E92)) -> 2.2158719 | F98: =E98*(1+MAX(0,phi*F92)) -> 2.3612805 | G98: =F98*(1+MAX(0,phi*G92)) -> 2.5000556
A99: 營業費用 | B99: US$B | C99: =C98 -> 1.4784 | D99: =D98 -> 1.827 | E99: =E98+0*E87 -> 2.2158719 | F99: =F98+0*F87 -> 2.3612805 | G99: =G98+0*G87 -> 2.5000556
A100: 營業利益 | B100: US$B | C100: =C96-C99 -> 4.337 | D100: =D96-D99 -> 6.111 | E100: =E96-E99 -> 8.6373951 | F100: =F96-F99 -> 9.7632968 | G100: =G96-G99 -> 10.889719
A101: 營業利益率 | B101: % | C101: =C100/C87 -> 0.48158389 | D101: =D100/D87 -> 0.485 | E101: =E100/E87 -> 0.49423938 | F101: =F100/F87 -> 0.49911433 | G101: =G100/G87 -> 0.50295471
A102: 其他收益 | B102: US$B | C102: =a25_oth -> 0.3936 | D102: =a26_oth -> 0.4999 | E102: =oth_f -> 0.55 | F102: =oth_f -> 0.55 | G102: =oth_f -> 0.55
A103: 有效稅率 | B103: % | C103: =1-a25_ni/(a25_oi+a25_oth) -> 0.19545089 | D103: =1-a26_ni/(a26_oi+a26_oth) -> 0.20965269 | E103: =tx_f -> 0.21 | F103: =tx_f -> 0.21 | G103: =tx_f -> 0.21
A104: 淨利（non-GAAP） | B104: US$B | C104: =a25_ni -> 3.806 | D104: =a26_ni -> 5.224907 | E104: =(E100+E102)*(1-E103) -> 7.2580421 | F104: =(F100+F102)*(1-F103) -> 8.1475044 | G104: =(G100+G102)*(1-G103) -> 9.0373779
A105: 稀釋股數 | B105: 十億股 | C105: =a25_sh -> 1.2757 | D105: =a26_sh -> 1.27595 | E105: =D105*(1+sh_g) -> 1.27595 | F105: =E105*(1+sh_g) -> 1.27595 | G105: =F105*(1+sh_g) -> 1.27595
A106: EPS（non-GAAP） | B106: US$ | C106: =C104/C105 -> 2.9834601 | D106: =D104/D105 -> 4.0949152 | E106: =E104/E105 -> 5.6883437 | F106: =F104/F105 -> 6.3854418 | G106: =G104/G105 -> 7.0828621
A107: EPS 年增 | B107: % | D107: =D106/C106-1 -> 0.37253896 | E107: =E106/D106-1 -> 0.3891237 | F107: =F106/E106-1 -> 0.12254851 | G107: =G106/F106-1 -> 0.10922037
A110: 案例區塊：乙太網路占比 低（情境 A）
A111: 項目 | B111: 單位 | C111: FY2025A | D111: FY2026（錨點） | E111: FY2027 | F111: FY2028 | G111: FY2029 | H111: 說明
A112: A. AI 營收（D 欄＝FY2026 校準年；E–G＝FY2027–FY2029）
A113: AI 後端 scale-out 交換器市場 × 情境顆數係數 | B113: US$B | D113: =mkt_26*1 -> 32.0719 | E113: =mkt_27*1*1 -> 61.085 | F113: =mkt_28*um28_A*1 -> 69.005 | G113: =mkt_29*um29_A*1 -> 78.48215
A114: 乙太網路占比 | B114: % | D114: =ETLO_26 -> 0.7 | E114: =ETLO_27 -> 0.72 | F114: =ETLO_28 -> 0.74 | G114: =ETLO_29 -> 0.75
A115: AI 後端乙太網路交換器市場 | B115: US$B | D115: =D113*D114 -> 22.45033 | E115: =E113*E114 -> 43.9812 | F115: =F113*F114 -> 51.0637 | G115: =G113*G114 -> 58.861612
A116: Arista 有效份額（FY2026 校準）＝ AI 目標 ÷ 乙太網路市場 | B116: % | D116: =a26_ai/D115 -> 0.15589971 | H116: Derived：分子含前端與 scale-across，所以高於純後端份額；FY2027 起乘相對值
A117: 份額相對值（÷ FY2026） | B117: x | D117: =1 -> 1 | E117: =rel_27 -> 0.95 | F117: =rel_28 -> 0.9 | G117: =rel_29 -> 0.88
A118: Arista 有效份額 | B118: % | D118: =$D$116*D117 -> 0.15589971 | E118: =$D$116*E117 -> 0.14810473 | F118: =$D$116*F117 -> 0.14030974 | G118: =$D$116*G117 -> 0.13719175
A119: AI 營收 | B119: US$B | C119: =a25_ai -> 1.63 | D119: =D115*D118 -> 3.5 | E119: =E115*E118 -> 6.5138236 | F119: =F115*F118 -> 7.1647345 | G119: =G115*G118 -> 8.0753275
A120: B. 非 AI 與合計
A121: 非 AI 營收 | B121: US$B | C121: =a25_nai -> 7.3757 | D121: =a26_nai -> 9.1 | E121: =D121*(1+g_nai27) -> 10.01 | F121: =E121*(1+g_nai28) -> 10.8108 | G121: =F121*(1+g_nai29) -> 11.459448
...

Sheet Sources
A1: 來源（公司原文＝Arista 8-K 新聞稿，已逐份抓取；法說內容只經二手轉述）
A2: 公司：2Q26 新聞稿（含上半年合計、3Q26 指引） | B2: https://www.sec.gov/Archives/edgar/data/0001596532/000159653226000174/ex991q226-earningsrelease.htm
A3: 公司：4Q25 與 FY2025 新聞稿 | B3: https://www.businesswire.com/news/home/20260212962784/en/Arista-Networks-Inc.-Reports-Fourth-Quarter-and-Year-End-2025-Financial-Results
A4: 二手：BigGo Finance 2Q26 法說摘要（全年指引 12.6、AI 至少 3.5、scale-across 約 1.2、毛利率與營業利益率指引） | B4: https://finance.biggo.com/news/US_ANET_2026-08-04
A5: 二手：sec-api 彙整（客戶集中、遞延收入、GAAP／non-GAAP 毛利率與營業利益率） | B5: https://sec-api.io/insights/arista-networks-anet-stock-analysis-q2-2026-ai-networking-revenue-deferred-revenue-customer-concentration-insider-sales-and-scenarios-to-fy2029
A6: 二手：Next Platform（2025 營收、2025 AI 約 1.63、微軟 26%、Meta 16%） | B6: https://www.nextplatform.com/2026/02/13/the-current-ai-networking-wave-will-be-a-tsunami-of-money-by-2027/
A7: 研調：IDC 2Q26 乙太網路交換器（NVIDIA 20.4%、Arista 18.7%、Cisco 18.2%） | B7: https://www.idc.com/resource-center/blog/ethernet-switch-market-surges-43-4-to-18-9b-in-2q26-as-ai-infrastructure-demand-drives-record-datacenter-spending/
A8: 研調：Dell'Oro 2025 AI 後端（乙太網路超過 InfiniBand 兩倍；Celestica、NVIDIA 並列第一，Arista 第三） | B8: https://www.delloro.com/news/ethernet-more-than-doubles-size-of-infiniband-as-the-leading-fabric-for-ai-scale-out-networks-in-2025/
A9: 二手：StockAnalysis 現價、前瞻 P/E、2026 共識 | B9: https://stockanalysis.com/stocks/anet/forecast/
A10: 二手：MarketBeat（Erste FY2027 EPS 4.79） | B10: https://www.marketbeat.com/instant-alerts/estimates-fy2027-eps-forecast-for-arista-networks-increased-by-analyst-2026-10-23/
A11: 資料商：companiesmarketcap 年底 P/E | B11: https://companiesmarketcap.com/arista-networks/pe-ratio/
A12: 資料商：Macrotrends 季度 P/E（至 2024-04） | B12: https://www.macrotrends.net/stocks/charts/ANET/arista-networks/pe-ratio
A13: 市場層：markets/network、tsmc 成品（本 repo，唯讀）
A14: 待補（人工）：2027 共識（付費）；各季 AI 營收；產品別毛利率；前瞻 P/E 十年歷史（Bloomberg）；重編後 FY2025 non-GAAP 淨利 | B14: 未找到
A15: SemiAnalysis | B15: 未使用
A16: [Verified] 公司 FY2025 10-K（SEC XBRL）：折舊與攤銷 72.6、購置不動產設備與無形資產 119.5（百萬美元）；營收 9,006 百萬美元——自由現金流比率錨點 | B16: https://data.sec.gov/api/xbrl/companyconcept/CIK0001596532/us-gaap/DepreciationDepletionAndAmortization.json；https://data.sec.gov/api/xbrl/companyconcept/CIK0001596532/us-gaap/PaymentsToAcquireProductiveAssets.json（10-K accession 0001596532-26-000013）
A17: [Assumed] 自由現金流：FY2026 起折舊 ÷ 營收、資本支出 ÷ 營收沿用 FY2025 比率（In 頁 fcf_da、fcf_capex）；不含營運資金變動 | B17: 本模型假設
