Workbook

Sheet 導覽
A1: Amazon 收支與評價模型 — Excel 版 v0.2（更新 2026-10-08；與 HTML v0.2 同步；市價截至 2026-10-07 收盤）
A3: 這個活頁簿在回答什麼
A4: 一句話：AI 資本支出有沒有賺到資金成本：每 MW 收入能否覆蓋每 MW 全成本——Amazon 用客戶預付款支應多少擴張資本支出，剩下的缺口要靠多少債務與新股。
A5: 所有分頁用同一組數字，改任何一個輸入，後面全部會跟著動。
A7: 分頁結構（依模組分組，分頁標籤顏色相同者為同一模組）
A8: 摘要 一頁摘要：結論、與市場共識的差異、現價隱含什麼、驗證點（全部活公式）。
A9: 輸入與假設 所有可調參數（A 情境 → B 產能與收入 → C 利潤率 → D 支出 → E 融資 → F 評價 → G 1H 實際 → H 情境區間運算表 → I 市場共識 → J 季度追蹤輸入）。
A10: 各期收支 類現金流量：來源（含客戶預付）、用途、融資前缺口、期前融資瀑布。
A11: 季度追蹤 焦點季的模型／共識／指引／實際與差距（由年度模型拆分，只用於追蹤；實際數填在輸入與假設 J 區）。
A12: 運營_產能與收入 已連網 MW → 在役 MW → 營收（MW × 每 MW 年收入 × 利用率）；RPO 排程只作對照與產能瓶頸旗標。
A13: 資產負債_既有債務／新債與新股／租賃承諾 類資產負債表：季報債務明細、每期現金與總債務與股數、租賃承諾。
A14: 損益 類損益表（2026＝1H 實際＋下半年模型）。
... A42: DCF 以融資後股數計每股，並加回新股募得現金的現值；EV/EBITDA 用錨定年末淨負債與錨定年末股數。

Sheet 摘要
A1: 一頁摘要 — 結論、與市場的差異、現價隱含什麼、驗證點（全部依輸入連動）
A2: ="模型端＝目前情境：" & CHOOSE(輸入與假設!$C$5,"保守 第三方可辨識站點","基準 依資本支出指引","積極 依公司容量目標") & "（預設＝基準）；共識＝data/consensus_amzn_20261008.json（2026-10-08）" -> 模型端＝目前情境：基準 依資本支出指引（預設＝基準）；共識＝data/consensus_amzn_20261008.json（2026-10-08）
A4: 1｜結論
A5: 結論｜評等代碼（1＝買進、0＝中立、−1＝賣出） | C5: =評價_DCF與目標價!C99 -> -1
A6: 結論｜評等 | C6: =CHOOSE(C5+2,"賣出","中立","買進") -> 賣出
A7: 結論｜點位（加權目標價） | B7: US$ | C7: =評價_DCF與目標價!C51 -> 199.27124
A8: 結論｜現價 | B8: US$ | C8: =輸入與假設!$C$320 -> 259.92
A9: 結論｜空間 | B9: % | C9: =C7/C8-1 -> -0.23333624
A10: 結論｜情境區間（下緣／上緣） | B10: US$ | C10: =評價_DCF與目標價!C104 -> 198.56586 | D10: =評價_DCF與目標價!D104 -> 212.71365
A11: 結論｜方法區間（下緣／上緣） | B11: US$ | C11: =評價_DCF與目標價!C106 -> 195.25159 | D11: =評價_DCF與目標價!D106 -> 199.27124
A12: 結論｜賣出門檻價 | B12: US$ | C12: =評價_DCF與目標價!$C$100 -> 220.932
A13: 結論｜點位 − 賣出門檻 | B13: US$ | C13: =C7-C12 -> -21.660756
A14: 結論｜結論句 | C14: =C6&"：點位 $"&TEXT(C7,"0.0")&"，較現價 $"&TEXT(C8,"0.00")&" "&IF(C9>=0,"高","低")&" "&TEXT(ABS(C9)*100,"0")&"%；情境區間 $"&TEXT(C10,"0.0")&"–$"&TEXT(D10,"0.0")&"，方法區間 $"&TEXT(C11,"0.0")&"–$"&TEXT(D11,"0.0")&"；點位"&IF(C13<0,"低於","高於")&"賣出門檻 $"&TEXT(C12,"0.0")&" 達 $"&TEXT(ABS(C13),"0.0")&"。" -> 賣出：點位 $199.3，較現價 $259.92 低 23%；情境區間 $198.6–$212.7，方法區間 $195.3–$199.3；點位低於賣出門檻 $220.9 達 $21.7。
A15: 結論｜情境判斷句 | C15: =評價_DCF與目標價!C129 -> 情境區間上緣 $212.7 低於現價 $259.92：賣出在三個擴張情境下都成立。保守情境 $212.7，距賣出門檻 $220.9 僅 $8.2。
A16: 結論｜投資級句 | C16: =IF(OR(輸入與假設!$C$288="ebitda",輸入與假設!$C$288="leaseAdj"),"需失去投資級才能融資的金額："&IF(SUM(各期收支!C93:G93)>0.05,"$"&TEXT(SUM(各期收支!C93:G93),"0.0")&"bn（五期高息債溢出）","$0")&"；投資級上限＝"&IF(輸入與假設!$C$288="leaseAdj","(總債務＋租賃負債) ≤ "&IF(輸入與假設!$C$289=INT(輸入與假設!$C$289),TEXT(輸入與假設!$C$289,"0"),TEXT(輸入與假設!$C$289,"0.0"))&"×(EBITDA＋租金)","總債務 ≤ "&IF(輸入與假設!$C$289=INT(輸入與假設!$C$289),TEXT(輸入與假設!$C$289,"0"),TEXT(輸入與假設!$C$289,"0.0"))&"× 當期 EBITDA")&"，股權每年 ≤ 現市值 "&IF(ROUND(ABS(輸入與假設!$C$299)*100,4)=INT(ROUND(ABS(輸入與假設!$C$299)*100,4)),TEXT(ROUND(ABS(輸入與假設!$C$299)*100,4),"0"),TEXT(ROUND(ABS(輸入與假設!$C$299)*100,4),"0.0"))&"%"&"。","") -> 需失去投資級才能融資的金額：$0；投資級上限＝(總債務＋租賃負債) ≤ 3×(EBITDA＋租金)，股權每年 ≤ 現市值 5%。
A17: 結論｜調整後槓桿句 | C17: ="調整後槓桿（(債務＋租賃負債) ÷ (EBITDA＋租金)）路徑 "&TEXT(資產負債_新債與新股!C37,"0.0")&"／"&TEXT(資產負債_新債與新股!D37,"0.0")&"／"&TEXT(資產負債_新債與新股!E37,"0.0")&"／"&TEXT(資產負債_新債與新股!F37,"0.0")&"／"&TEXT(資產負債_新債與新股!G37,"0.0")&"×；上限 "&IF(輸入與假設!$C$289=INT(輸入與假設!$C$289),TEXT(輸入與假設!$C$289,"0"),TEXT(輸入與假設!$C$289,"0.0"))&"×，"&IF(MAX(資產負債_新債與新股!$C$37:$G$37)>輸入與假設!$C$289+0.000000001,CHOOSE(MATCH(MAX(資產負債_新債與新股!$C$37:$G$37),資產負債_新債與新股!$C$37:$G$37,0),"2026","2027","2028","2029","2030")&" 超過 "&TEXT(MAX(資產負債_新債與新股!$C$37:$G$37)-輸入與假設!$C$289,"0.0")&"×：需股權或失去投資級。","最小空間 "&TEXT(輸入與假設!$C$289-MAX(資產負債_新債與新股!$C$37:$G$37),"0.0")&"×（"&CHOOSE(MATCH(MAX(資產負債_新債與新股!$C$37:$G$37),資產負債_新債與新股!$C$37:$G$37,0),"2026","2027","2028","2029","2030")&"）。") -> 調整後槓桿（(債務＋租賃負債) ÷ (EBITDA＋租金)）路徑 1.4／1.6／1.3／1.1／1.1×；上限 3×，最小空間 1.4×（2027）。
A18: 結論｜評價口徑敏感度句 | C18: ="評價口徑敏感度："&"WACC 9% $"&TEXT(評價_DCF與目標價!C114,"0.00")&"（"&CHOOSE(評價_DCF與目標價!D114+2,"賣出","中立","買進")&"）"&"、"&"WACC 10% $"&TEXT(評價_DCF與目標價!C115,"0.00")&"（"&CHOOSE(評價_DCF與目標價!D115+2,"賣出","中立","買進")&"）"&"、"&"WACC 11% $"&TEXT(評價_DCF與目標價!C116,"0.00")&"（"&CHOOSE(評價_DCF與目標價!D116+2,"賣出","中立","買進")&"）"&"；"&"非 AI 分部改用公司自身 NTM EV/EBITDA 11.26× $"&TEXT(評價_DCF與目標價!C119,"0.00")&"（"&CHOOSE(評價_DCF與目標價!D119+2,"賣出","中立","買進")&"）"&"、"&"AI 雲端 15× $"&TEXT(評價_DCF與目標價!C120,"0.00")&"（"&CHOOSE(評價_DCF與目標價!D120+2,"賣出","中立","買進")&"）"&"、"&"組合：WACC 9%＋非 AI 自身倍數＋AI 15× $"&TEXT(評價_DCF與目標價!C121,"0.00")&"（"&CHOOSE(評價_DCF與目標價!D121+2,"賣出","中立","買進")&"）"&"；評等翻轉點："&"WACC 約 "&TEXT(評價_DCF與目標價!C122*100,"0.0")&"%（ERP "&TEXT(評價_DCF與目標價!D122*100,"0.00")&"%）以下由「賣出」轉為「中立」"&"。" -> 評價口徑敏感度：WACC 9% $258.36（中立）、WACC 10% $236.28（中立）、WACC 11% $219.13（賣出）；非 AI 分部改用公司自身 NTM EV/EBITDA 11.26× $183.67（賣出）、AI 雲端 15× $235.45（中立）、組合：WACC 9%＋非 AI 自身倍數＋AI 15× $280.63（中立）；評等翻轉點：WACC 約 10.9%（ERP 3.88%）以下由「賣出」轉為「中立」。
A19: 結論｜終值占比規則句 | C19: ="評等規則：買進須空間 ≥ +"&IF(ROUND(ABS(輸入與假設!$C$405)*100,4)=INT(ROUND(ABS(輸入與假設!$C$405)*100,4)),TEXT(ROUND(ABS(輸入與假設!$C$405)*100,4),"0"),TEXT(ROUND(ABS(輸入與假設!$C$405)*100,4),"0.0"))&"%"&" 且終值占 EV < "&IF(ROUND(ABS(輸入與假設!$C$406)*100,4)=INT(ROUND(ABS(輸入與假設!$C$406)*100,4)),TEXT(ROUND(ABS(輸入與假設!$C$406)*100,4),"0"),TEXT(ROUND(ABS(輸入與假設!$C$406)*100,4),"0.0"))&"%"&"；目前終值占 EV "&TEXT(評價_DCF與目標價!C97*100,"0")&"%"&IF(評價_DCF與目標價!C97>=輸入與假設!$C$406,"，此規則下只可能「賣出」或「中立」","")&"（規則是否修改待 Andy 決定）。" -> 評等規則：買進須空間 ≥ +25% 且終值占 EV < 90%；目前終值占 EV 119%，此規則下只可能「賣出」或「中立」（規則是否修改待 Andy 決定）。
A20: 結論｜兩種讀法句 | C20: ="兩種讀法（自用 AI）：讀法 1（影子收入不進評價）$"&TEXT(評價_DCF與目標價!C51,"0.00")&"；讀法 2（自用 AI 價值中性：自用 MW 以 k＝1 計影子收入並進評價）$"&TEXT(評價_DCF與目標價!C73,"0.00")&"；差額 "&IF(評價_DCF與目標價!C73-評價_DCF與目標價!C51<0,"−","+")&"$"&TEXT(ABS(評價_DCF與目標價!C73-評價_DCF與目標價!C51),"0.00")&"。主值取哪一個是 Andy 的判斷（待決）。" -> 兩種讀法（自用 AI）：讀法 1（影子收入不進評價）$199.27；讀法 2（自用 AI 價值中性：自用 MW 以 k＝1 計影子收入並進評價）$217.62；差額 +$18.35。主值取哪一個是 Andy 的判斷（待決）。
A21: 結論｜對外比例句 | C21: ="對外比例無揭露（目前 "&TEXT(輸入與假設!$C$217*100,"0")&"%，[Assumed]），是最大不確定："&TEXT(評價_DCF與目標價!C112*100,"0")&"% → $"&TEXT(評價_DCF與目標價!D112,"0.00")&"、"&TEXT(評價_DCF與目標價!C113*100,"0")&"% → $"&TEXT(評價_DCF與目標價!D113,"0.00")&"（基準 $"&TEXT(評價_DCF與目標價!C51,"0.00")&"）。" -> 對外比例無揭露（目前 80%，[Assumed]），是最大不確定：60% → $168.24、100% → $215.62（基準 $199.27）。
A22: 結論｜主命題句 | C22: ="主命題（AI 資本支出有沒有賺到資金成本）：2029 對外 AI ROIC "&TEXT(AI增量報酬!F23*100,"0.0")&"% vs WACC "&TEXT(輸入與假設!$C$342*100,"0.0")&"%（"&IF(AI增量報酬!F25<0,"−","+")&TEXT(ABS(AI增量報酬!F25)*100,"0.0")&"pt）；打平 k "&TEXT(AI增量報酬!C29,"0.00")&"（目前 "&TEXT(輸入與假設!$C$56,"0.00")&"）；全 AI（含影子收入）"&TEXT(AI增量報酬!F27*100,"0.0")&"%。" -> 主命題（AI 資本支出有沒有賺到資金成本）：2029 對外 AI ROIC 6.2% vs WACC 12.5%（−6.3pt）；打平 k 1.16（目前 0.95）；全 AI（含影子收入）6.2%。
A23: 結論｜股東回饋與 FCF 句 | C23: ="股東回饋與 FCF：FCF "&IF(各期收支!C44<0,"首次為負 2026（−$"&TEXT(-各期收支!C44,"0.0")&"bn）",IF(各期收支!D44<0,"首次為負 2027（−$"&TEXT(-各期收支!D44,"0.0")&"bn）",IF(各期收支!E44<0,"首次為負 2028（−$"&TEXT(-各期收支!E44,"0.0")&"bn）",IF(各期收支!F44<0,"首次為負 2029（−$"&TEXT(-各期收支!F44,"0.0")&"bn）",IF(各期收支!G44<0,"首次為負 2030（−$"&TEXT(-各期收支!G44,"0.0")&"bn）","五期皆為正")))))&"；"&IF(SUM(各期收支!C75:G75)<=0.05,"無回購計畫（減少回購步驟不適用）",IF(SUM(各期收支!C77:G77)>0,"回購被迫減少："&MID(IF(各期收支!C77>0.05,"、2026 $"&TEXT(各期收支!C77,"0.0"),"")&IF(各期收支!D77>0.05,"、2027 $"&TEXT(各期收支!D77,"0.0"),"")&IF(各期收支!E77>0.05,"、2028 $"&TEXT(各期收支!E77,"0.0"),"")&IF(各期收支!F77>0.05,"、2029 $"&TEXT(各期收支!F77,"0.0"),"")&IF(各期收支!G77>0.05,"、2030 $"&TEXT(各期收支!G77,"0.0"),""),2,999)&"bn","回購未被迫減少"))&"；五期新債 $"&TEXT(SUM(各期收支!C86:G86)+SUM(各期收支!C93:G93),"0.0")&"bn、股權 $"&TEXT(SUM(各期收支!C92:G92),"0.0")&"bn。" -> 股東回饋與 FCF：FCF 首次為負 2026（−$60.1bn）；無回購計畫（減少回購步驟不適用）；五期新債 $206.7bn、股權 $0.0bn。
A24: 結論｜延誤句 | C24: =IF(運營_產能與收入!$C$50>0,"建設延誤 "&IF(運營_產能與收入!$C$50=INT(運營_產能與收入!$C$50),TEXT(運營_產能與收入!$C$50,"0"),TEXT(運營_產能與收入!$C$50,"0.0"))&" 個月（GPU 資本支出照原時程）：閒置資本（已支出、尚未產生收入）峰值 $"&TEXT(MAX(運營_產能與收入!$C$55:$G$55),"0.0")&"bn（"&CHOOSE(MATCH(MAX(運營_產能與收入!$C$55:$G$55),運營_產能與收入!$C$55:$G$55,0),"2026","2027","2028","2029","2030")&" 末）。","建設延誤：本情境 0 個月（無閒置資本）。") -> 建設延誤：本情境 0 個月（無閒置資本）。
A26: 2｜與市場的差異（模型：目前情境 vs 共識；2026–2028）
A27: 項目 | B27: 單位 | C27: 2026 | D27: 2027 | E27: 2028
A28: 差異｜營收｜模型 | B28: US$bn | C28: =損益!C29 -> 834.21909 | D28: =損益!D29 -> 973.5439 | E28: =損益!E29 -> 1113.4726
A29: 差異｜營收｜共識 | B29: US$bn | C29: =輸入與假設!$C$464 -> 828.285 | D29: =輸入與假設!$D$464 -> 947.853 | E29: =輸入與假設!$E$464 -> 1097.389
A30: 差異｜營收｜差距 | B30: % | C30: =C28/C29-1 -> 0.0071643077 | D30: =D28/D29-1 -> 0.027104306 | E30: =E28/E29-1 -> 0.014656256
A31: 差異｜調整後 EBITDA｜模型 | B31: US$bn | C31: =輸入與假設!$C$434+損益!C22 -> 191.64382 | D31: =損益!D34 -> 243.24121 | E31: =損益!E34 -> 300.32364
A32: 差異｜調整後 EBITDA｜共識 | B32: US$bn | C32: =輸入與假設!$C$465 -> 216.957 | D32: =輸入與假設!$D$465 -> 273.452 | E32: =輸入與假設!$E$465 -> 355.29
A33: 差異｜調整後 EBITDA｜差距 | B33: % | C33: =C31/C32-1 -> -0.11667372 | D33: =D31/D32-1 -> -0.11047932 | E33: =E31/E32-1 -> -0.15470845 | I33: 2026 模型＝1H 實際調整後 EBITDA（輸入與假設 G 區，報導轉述 [Verified]）＋2H 模型
A34: 差異｜調整後 EBITDA｜差距（金額） | B34: US$bn | C34: =C31-C32 -> -25.313181 | D34: =D31-D32 -> -30.210792 | E34: =E31-E32 -> -54.966365 | I34: 與 HTML 一頁摘要、市場共識分頁同一呈現；判斷門檻仍用上一列比例
A35: 差異｜EBITDA 率｜模型 | B35: % | C35: =C31/C28 -> 0.2297284 | D35: =D31/D28 -> 0.2498513 | E35: =E31/E28 -> 0.26971803
A36: 差異｜EBITDA 率｜共識 | B36: % | C36: =輸入與假設!$C$466 -> 0.2619352 | D36: =輸入與假設!$D$466 -> 0.28849621 | E36: =輸入與假設!$E$466 -> 0.3237594
A37: 差異｜EBITDA 率｜差距（百分點） | B37: pt | C37: =C35-C36 -> -0.032206801 | D37: =D35-D36 -> -0.038644913 | E37: =E35-E36 -> -0.054041371 | I37: EBITDA 率以百分點列差距，不納入判斷
A38: 差異｜CapEx（毛額）｜模型 | B38: US$bn | C38: =輸入與假設!$C$417+輸入與假設!C$277 -> 220 | D38: =輸入與假設!D$277 -> 276.22582 | E38: =輸入與假設!E$277 -> 291.66355
A39: 差異｜CapEx（毛額）｜共識 | B39: US$bn | C39: =輸入與假設!$C$470 -> 220.5 | D39: =輸入與假設!$D$470 -> 275.063 | E39: =輸入與假設!$E$470 -> 292.927
A40: 差異｜CapEx（毛額）｜差距 | B40: % | C40: =C38/C39-1 -> -0.0022675737 | D40: =D38/D39-1 -> 0.0042274844 | E40: =E38/E39-1 -> -0.0043131828 | I40: 共識 CapEx 口徑未揭露；2026＝1H 實際毛額＋2H 模型毛額
A41: 差異｜淨負債｜模型 | B41: US$bn | C41: =資產負債_新債與新股!C25 -> 68.304423 | D41: =資產負債_新債與新股!D25 -> 141.3376 | E41: =資產負債_新債與新股!E25 -> 178.20337
A42: 差異｜淨負債｜共識 | B42: US$bn | C42: =輸入與假設!$C$472 -> 22.278 | D42: =輸入與假設!$D$472 -> 74.022 | E42: =輸入與假設!$E$472 -> 104.013
A43: 差異｜淨負債｜差距 | B43: % | C43: =C41/C42-1 -> 2.0660034 | D43: =D41/D42-1 -> 0.90939995 | E43: =E41/E42-1 -> 0.71327978 | I43: 共識淨負債不含租賃、口徑未揭露：只列不判斷
A44: 差異｜淨負債｜差距（金額） | B44: US$bn | C44: =C41-C42 -> 46.026423 | D44: =D41-D42 -> 67.315603 | E44: =E41-E42 -> 74.19037 | I44: 與 HTML 一頁摘要、市場共識分頁同一呈現；判斷門檻仍用上一列比例
A45: 差異｜分歧項目（超過門檻者） | C45: =MID(IF(ABS(C30)>輸入與假設!$C$493,"、營收 "&IF(C30<0,"−","+")&TEXT(ABS(C30)*100,"0.0")&"%","")&IF(ABS(C33)>輸入與假設!$C$493,"、EBITDA "&IF(C34<0,"−","+")&"$"&TEXT(ABS(C34),"#,##0.00")&"bn"&"／"&IF(C37<0,"−","+")&TEXT(ABS(C37)*100,"0.0")&"pt","")&IF(ABS(C40)>輸入與假設!$C$493,"、CapEx "&IF(C40<0,"−","+")&TEXT(ABS(C40)*100,"0.0")&"%",""),2,999) -> EBITDA −$25.31bn／−3.2pt | D45: =MID(IF(ABS(D30)>輸入與假設!$C$493,"、營收 "&IF(D30<0,"−","+")&TEXT(ABS(D30)*100,"0.0")&"%","")&IF(ABS(D33)>輸入與假設!$C$493,"、EBITDA "&IF(D34<0,"−","+")&"$"&TEXT(ABS(D34),"#,##0.00")&"bn"&"／"&IF(D37<0,"−","+")&TEXT(ABS(D37)*100,"0.0")&"pt","")&IF(ABS(D40)>輸入與假設!$C$493,"、CapEx "&IF(D40<0,"−","+")&TEXT(ABS(D40)*100,"0.0")&"%",""),2,999) -> EBITDA −$30.21bn／−3.9pt | E45: =MID(IF(ABS(E30)>輸入與假設!$C$493,"、營收 "&IF(E30<0,"−","+")&TEXT(ABS(E30)*100,"0.0")&"%","")&IF(ABS(E33)>輸入與假設!$C$493,"、EBITDA "&IF(E34<0,"−","+")&"$"&TEXT(ABS(E34),"#,##0.00")&"bn"&"／"&IF(E37<0,"−","+")&TEXT(ABS(E37)*100,"0.0")&"pt","")&IF(ABS(E40)>輸入與假設!$C$493,"、CapEx "&IF(E40<0,"−","+")&TEXT(ABS(E40)*100,"0.0")&"%",""),2,999) -> EBITDA −$54.97bn／−5.4pt | I45: 營收、EBITDA、CapEx 任一項差距絕對值超過門檻即列出（與 HTML 判斷句同一規則）
A46: 差異｜分歧起始年（1＝2026…3＝2028；0＝無） | C46: =IF(C45<>"",1,IF(D45<>"",2,IF(E45<>"",3,0))) -> 1
A47: 差異｜判斷句 | C47: =CHOOSE(C46+1,"2026–2028 營收、EBITDA、CapEx 與共識差距皆在 "&IF(ROUND(ABS(輸入與假設!$C$493)*100,4)=INT(ROUND(ABS(輸入與假設!$C$493)*100,4)),TEXT(ROUND(ABS(輸入與假設!$C$493)*100,4),"0"),TEXT(ROUND(ABS(輸入與假設!$C$493)*100,4),"0.0"))&"%"&" 以內。","分歧始於 2026（"&C45&"）"&"；2027 "&IF(D45="","回到 "&IF(ROUND(ABS(輸入與假設!$C$493)*100,4)=INT(ROUND(ABS(輸入與假設!$C$493)*100,4)),TEXT(ROUND(ABS(輸入與假設!$C$493)*100,4),"0"),TEXT(ROUND(ABS(輸入與假設!$C$493)*100,4),"0.0"))&"%"&" 以內",D45)&"；2028 "&IF(E45="","回到 "&IF(ROUND(ABS(輸入與假設!$C$493)*100,4)=INT(ROUND(ABS(輸入與假設!$C$493)*100,4)),TEXT(ROUND(ABS(輸入與假設!$C$493)*100,4),"0"),TEXT(ROUND(ABS(輸入與假設!$C$493)*100,4),"0.0"))&"%"&" 以內",E45)&"。","2026 營收、EBITDA、CapEx 與共識差距在 "&IF(ROUND(ABS(輸入與假設!$C$493)*100,4)=INT(ROUND(ABS(輸入與假設!$C$493)*100,4)),TEXT(ROUND(ABS(輸入與假設!$C$493)*100,4),"0"),TEXT(ROUND(ABS(輸入與假設!$C$493)*100,4),"0.0"))&"%"&" 以內；分歧始於 2027（"&D45&"）"&"；2028 "&IF(E45="","回到 "&IF(ROUND(ABS(輸入與假設!$C$493)*100,4)=INT(ROUND(ABS(輸入與假設!$C$493)*100,4)),TEXT(ROUND(ABS(輸入與假設!$C$493)*100,4),"0"),TEXT(ROUND(ABS(輸入與假設!$C$493)*100,4),"0.0"))&"%"&" 以內",E45)&"。","2026–2027 營收、EBITDA、CapEx 與共識差距在 "&IF(ROUND(ABS(輸入與假設!$C$493)*100,4)=INT(ROUND(ABS(輸入與假設!$C$493)*100,4)),TEXT(ROUND(ABS(輸入與假設!$C$493)*100,4),"0"),TEXT(ROUND(ABS(輸入與假設!$C$493)*100,4),"0.0"))&"%"&" 以內；分歧始於 2028（"&E45&"）。") -> 分歧始於 2026（EBITDA −$25.31bn／−3.2pt）；2027 EBITDA −$30.21bn／−3.9pt；2028 EBITDA −$54.97bn／−5.4pt。
A48: 差異原因｜2026｜營收 | C48: =IF(ABS(C30)>輸入與假設!$C$493,"觀點","") | D48: =IF(ABS(C30)>輸入與假設!$C$493,"營收＝對外 AI 雲端（年底 "&IF((輸入與假設!C$36)<0,"−","")&TEXT(ABS((輸入與假設!C$36)),"#,##0")&" MW-IT × 每 MW 年收入，Tokenomics × k）＋零售／廣告／訂閱／AWS 非 AI（近四季年增率收斂到長期值）；共識未揭露 MW 與單價假設","") | I48: C＝類型、D＝原因（需附原因時顯示；EBITDA 以利潤率差、其餘以比例門檻判斷）
A49: 差異原因｜2026｜EBITDA | C49: =IF(ABS(C37)>輸入與假設!$C$494,"觀點","") -> 觀點 | D49: =IF(ABS(C37)>輸入與假設!$C$494,"營收差距 "&IF((C30)<0,"−","+")&TEXT(ABS((C30))*100,"#,##0.0")&"%"&"；EBITDA 率 "&IF((C35)<0,"−","")&TEXT(ABS((C35))*100,"#,##0.0")&"%"&" 對共識 "&IF((C36)<0,"−","")&TEXT(ABS((C36))*100,"#,##0.0")&"%"&"（分部 EBITDA 率依 C5 放大分攤 D&A，近四季收斂到近三年平均；AI 雲端以 Tokenomics 營運成本推得；共識 EBITDA 口徑未揭露是否扣 SBC）","") -> 營收差距 +0.7%；EBITDA 率 23.0% 對共識 26.2%（分部 EBITDA 率依 C5 放大分攤 D&A，近四季收斂到近三年平均；AI 雲端以 Tokenomics 營運成本推得；共識 EBITDA 口徑未揭露是否扣 SBC）
A50: 差異原因｜2026｜CapEx | C50: =IF(ABS(C40)>輸入與假設!$C$493,"觀點","") | D50: =IF(ABS(C40)>輸入與假設!$C$493,"CapEx：首期取公司指引約 220；公司未給 2027 以後指引 → 依新增 AI MW（"&IF((輸入與假設!C$244)<0,"−","")&TEXT(ABS((輸入與假設!C$244)),"#,##0")&" MW-IT 對外）÷ 對外比例 × 每 MW $"&IF((輸入與假設!C$225)<0,"−","")&TEXT(ABS((輸入與假設!C$225)),"#,##0")&"m＋非 AI 強度推導；對帳列顯示 2026 指引隱含的 AI 建置量約為 MW 路徑的 2 倍（共識口徑未揭露）","")
A51: 差異原因｜2026｜淨負債 | C51: =IF(ABS(C43)>輸入與假設!$C$493,"觀點","") -> 觀點 | D51: =IF(ABS(C43)>輸入與假設!$C$493,"淨負債隨 CapEx、投資與融資瀑布而定（模型 CapEx 差距 "&IF((C40)<0,"−","+")&TEXT(ABS((C40))*100,"#,##0.0")&"%"&"）；共識淨負債不含租賃","") -> 淨負債隨 CapEx、投資與融資瀑布而定（模型 CapEx 差距 −0.2%）；共識淨負債不含租賃
A52: 差異原因｜2027｜營收 | C52: =IF(ABS(D30)>輸入與假設!$C$493,"觀點","") | D52: =IF(ABS(D30)>輸入與假設!$C$493,"營收＝對外 AI 雲端（年底 "&IF((輸入與假設!D$36)<0,"−","")&TEXT(ABS((輸入與假設!D$36)),"#,##0")&" MW-IT × 每 MW 年收入，Tokenomics × k）＋零售／廣告／訂閱／AWS 非 AI（近四季年增率收斂到長期值）；共識未揭露 MW 與單價假設","")
A53: 差異原因｜2027｜EBITDA | C53: =IF(ABS(D37)>輸入與假設!$C$494,"觀點","") -> 觀點 | D53: =IF(ABS(D37)>輸入與假設!$C$494,"營收差距 "&IF((D30)<0,"−","+")&TEXT(ABS((D30))*100,"#,##0.0")&"%"&"；EBITDA 率 "&IF((D35)<0,"−","")&TEXT(ABS((D35))*100,"#,##0.0")&"%"&" 對共識 "&IF((D36)<0,"−","")&TEXT(ABS((D36))*100,"#,##0.0")&"%"&"（分部 EBITDA 率依 C5 放大分攤 D&A，近四季收斂到近三年平均；AI 雲端以 Tokenomics 營運成本推得；共識 EBITDA 口徑未揭露是否扣 SBC）","") -> 營收差距 +2.7%；EBITDA 率 25.0% 對共識 28.8%（分部 EBITDA 率依 C5 放大分攤 D&A，近四季收斂到近三年平均；AI 雲端以 Tokenomics 營運成本推得；共識 EBITDA 口徑未揭露是否扣 SBC）
A54: 差異原因｜2027｜CapEx | C54: =IF(ABS(D40)>輸入與假設!$C$493,"觀點","") | D54: =IF(ABS(D40)>輸入與假設!$C$493,"CapEx：首期取公司指引約 220；公司未給 2027 以後指引 → 依新增 AI MW（"&IF((輸入與假設!D$244)<0,"−","")&TEXT(ABS((輸入與假設!D$244)),"#,##0")&" MW-IT 對外）÷ 對外比例 × 每 MW $"&IF((輸入與假設!D$225)<0,"−","")&TEXT(ABS((輸入與假設!D$225)),"#,##0")&"m＋非 AI 強度推導；對帳列顯示 2026 指引隱含的 AI 建置量約為 MW 路徑的 2 倍（共識口徑未揭露）","")
A55: 差異原因｜2027｜淨負債 | C55: =IF(ABS(D43)>輸入與假設!$C$493,"觀點","") -> 觀點 | D55: =IF(ABS(D43)>輸入與假設!$C$493,"淨負債隨 CapEx、投資與融資瀑布而定（模型 CapEx 差距 "&IF((D40)<0,"−","+")&TEXT(ABS((D40))*100,"#,##0.0")&"%"&"）；共識淨負債不含租賃","") -> 淨負債隨 CapEx、投資與融資瀑布而定（模型 CapEx 差距 +0.4%）；共識淨負債不含租賃
A56: 差異原因｜2028｜營收 | C56: =IF(ABS(E30)>輸入與假設!$C$493,"觀點","") | D56: =IF(ABS(E30)>輸入與假設!$C$493,"營收＝對外 AI 雲端（年底 "&IF((輸入與假設!E$36)<0,"−","")&TEXT(ABS((輸入與假設!E$36)),"#,##0")&" MW-IT × 每 MW 年收入，Tokenomics × k）＋零售／廣告／訂閱／AWS 非 AI（近四季年增率收斂到長期值）；共識未揭露 MW 與單價假設","")
A57: 差異原因｜2028｜EBITDA | C57: =IF(ABS(E37)>輸入與假設!$C$494,"觀點","") -> 觀點 | D57: =IF(ABS(E37)>輸入與假設!$C$494,"營收差距 "&IF((E30)<0,"−","+")&TEXT(ABS((E30))*100,"#,##0.0")&"%"&"；EBITDA 率 "&IF((E35)<0,"−","")&TEXT(ABS((E35))*100,"#,##0.0")&"%"&" 對共識 "&IF((E36)<0,"−","")&TEXT(ABS((E36))*100,"#,##0.0")&"%"&"（分部 EBITDA 率依 C5 放大分攤 D&A，近四季收斂到近三年平均；AI 雲端以 Tokenomics 營運成本推得；共識 EBITDA 口徑未揭露是否扣 SBC）","") -> 營收差距 +1.5%；EBITDA 率 27.0% 對共識 32.4%（分部 EBITDA 率依 C5 放大分攤 D&A，近四季收斂到近三年平均；AI 雲端以 Tokenomics 營運成本推得；共識 EBITDA 口徑未揭露是否扣 SBC）
A58: 差異原因｜2028｜CapEx | C58: =IF(ABS(E40)>輸入與假設!$C$493,"觀點","") | D58: =IF(ABS(E40)>輸入與假設!$C$493,"CapEx：首期取公司指引約 220；公司未給 2027 以後指引 → 依新增 AI MW（"&IF((輸入與假設!E$244)<0,"−","")&TEXT(ABS((輸入與假設!E$244)),"#,##0")&" MW-IT 對外）÷ 對外比例 × 每 MW $"&IF((輸入與假設!E$225)<0,"−","")&TEXT(ABS((輸入與假設!E$225)),"#,##0")&"m＋非 AI 強度推導；對帳列顯示 2026 指引隱含的 AI 建置量約為 MW 路徑的 2 倍（共識口徑未揭露）","")
A59: 差異原因｜2028｜淨負債 | C59: =IF(ABS(E43)>輸入與假設!$C$493,"觀點","") -> 觀點 | D59: =IF(ABS(E43)>輸入與假設!$C$493,"淨負債隨 CapEx、投資與融資瀑布而定（模型 CapEx 差距 "&IF((E40)<0,"−","+")&TEXT(ABS((E40))*100,"#,##0.0")&"%"&"）；共識淨負債不含租賃","") -> 淨負債隨 CapEx、投資與融資瀑布而定（模型 CapEx 差距 −0.4%）；共識淨負債不含租賃
A60: 差異｜需附原因項數 | C60: =SUMPRODUCT(--(ABS(C30:E30)>輸入與假設!$C$493))+SUMPRODUCT(--(ABS(C37:E37)>輸入與假設!$C$494))+SUMPRODUCT(--(ABS(C40:E40)>輸入與假設!$C$493))+SUMPRODUCT(--(ABS(C43:E43)>輸入與假設!$C$493)) -> 6 | I60: 營收、EBITDA（利潤率差）、CapEx、淨負債 × 2026–2028
A61: 差異｜差異原因摘要 | C61: =IF(C60=0,"","需附原因的 "&C60&" 項差距："&MID(IF((COUNTIF(C48,"觀點")+COUNTIF(C49,"觀點")+COUNTIF(C50,"觀點")+COUNTIF(C51,"觀點")+COUNTIF(C52,"觀點")+COUNTIF(C53,"觀點")+COUNTIF(C54,"觀點")+COUNTIF(C55,"觀點")+COUNTIF(C56,"觀點")+COUNTIF(C57,"觀點")+COUNTIF(C58,"觀點")+COUNTIF(C59,"觀點"))>0,"、觀點 "&(COUNTIF(C48,"觀點")+COUNTIF(C49,"觀點")+COUNTIF(C50,"觀點")+COUNTIF(C51,"觀點")+COUNTIF(C52,"觀點")+COUNTIF(C53,"觀點")+COUNTIF(C54,"觀點")+COUNTIF(C55,"觀點")+COUNTIF(C56,"觀點")+COUNTIF(C57,"觀點")+COUNTIF(C58,"觀點")+COUNTIF(C59,"觀點"))&" 項","")&IF((COUNTIF(C48,"拆法")+COUNTIF(C49,"拆法")+COUNTIF(C50,"拆法")+COUNTIF(C51,"拆法")+COUNTIF(C52,"拆法")+COUNTIF(C53,"拆法")+COUNTIF(C54,"拆法")+COUNTIF(C55,"拆法")+COUNTIF(C56,"拆法")+COUNTIF(C57,"拆法")+COUNTIF(C58,"拆法")+COUNTIF(C59,"拆法"))>0,"、拆法 "&(COUNTIF(C48,"拆法")+COUNTIF(C49,"拆法")+COUNTIF(C50,"拆法")+COUNTIF(C51,"拆法")+COUNTIF(C52,"拆法")+COUNTIF(C53,"拆法")+COUNTIF(C54,"拆法")+COUNTIF(C55,"拆法")+COUNTIF(C56,"拆法")+COUNTIF(C57,"拆法")+COUNTIF(C58,"拆法")+COUNTIF(C59,"拆法"))&" 項","")&IF((COUNTIF(C48,"已知限制")+COUNTIF(C49,"已知限制")+COUNTIF(C50,"已知限制")+COUNTIF(C51,"已知限制")+COUNTIF(C52,"已知限制")+COUNTIF(C53,"已知限制")+COUNTIF(C54,"已知限制")+COUNTIF(C55,"已知限制")+COUNTIF(C56,"已知限制")+COUNTIF(C57,"已知限制")+COUNTIF(C58,"已知限制")+COUNTIF(C59,"已知限制"))>0,"、已知限制 "&(COUNTIF(C48,"已知限制")+COUNTIF(C49,"已知限制")+COUNTIF(C50,"已知限制")+COUNTIF(C51,"已知限制")+COUNTIF(C52,"已知限制")+COUNTIF(C53,"已知限制")+COUNTIF(C54,"已知限制")+COUNTIF(C55,"已知限制")+COUNTIF(C56,"已知限制")+COUNTIF(C57,"已知限制")+COUNTIF(C58,"已知限制")+COUNTIF(C59,"已知限制"))&" 項","")&IF((C60-((COUNTIF(C48,"觀點")+COUNTIF(C49,"觀點")+COUNTIF(C50,"觀點")+COUNTIF(C51,"觀點")+COUNTIF(C52,"觀點")+COUNTIF(C53,"觀點")+COUNTIF(C54,"觀點")+COUNTIF(C55,"觀點")+COUNTIF(C56,"觀點")+COUNTIF(C57,"觀點")+COUNTIF(C58,"觀點")+COUNTIF(C59,"觀點"))+(COUNTIF(C48,"拆法")+COUNTIF(C49,"拆法")+COUNTIF(C50,"拆法")+COUNTIF(C51,"拆法")+COUNTIF(C52,"拆法")+COUNTIF(C53,"拆法")+COUNTIF(C54,"拆法")+COUNTIF(C55,"拆法")+COUNTIF(C56,"拆法")+COUNTIF(C57,"拆法")+COUNTIF(C58,"拆法")+COUNTIF(C59,"拆法"))+(COUNTIF(C48,"已知限制")+COUNTIF(C49,"已知限制")+COUNTIF(C50,"已知限制")+COUNTIF(C51,"已知限制")+COUNTIF(C52,"已知限制")+COUNTIF(C53,"已知限制")+COUNTIF(C54,"已知限制")+COUNTIF(C55,"已知限制")+COUNTIF(C56,"已知限制")+COUNTIF(C57,"已知限制")+COUNTIF(C58,"已知限制")+COUNTIF(C59,"已知限制"))))>0,"、未歸類 "&(C60-((COUNTIF(C48,"觀點")+COUNTIF(C49,"觀點")+COUNTIF(C50,"觀點")+COUNTIF(C51,"觀點")+COUNTIF(C52,"觀點")+COUNTIF(C53,"觀點")+COUNTIF(C54,"觀點")+COUNTIF(C55,"觀點")+COUNTIF(C56,"觀點")+COUNTIF(C57,"觀點")+COUNTIF(C58,"觀點")+COUNTIF(C59,"觀點"))+(COUNTIF(C48,"拆法")+COUNTIF(C49,"拆法")+COUNTIF(C50,"拆法")+COUNTIF(C51,"拆法")+COUNTIF(C52,"拆法")+COUNTIF(C53,"拆法")+COUNTIF(C54,"拆法")+COUNTIF(C55,"拆法")+COUNTIF(C56,"拆法")+COUNTIF(C57,"拆法")+COUNTIF(C58,"拆法")+COUNTIF(C59,"拆法"))+(COUNTIF(C48,"已知限制")+COUNTIF(C49,"已知限制")+COUNTIF(C50,"已知限制")+COUNTIF(C51,"已知限制")+COUNTIF(C52,"已知限制")+COUNTIF(C53,"已知限制")+COUNTIF(C54,"已知限制")+COUNTIF(C55,"已知限制")+COUNTIF(C56,"已知限制")+COUNTIF(C57,"已知限制")+COUNTIF(C58,"已知限制")+COUNTIF(C59,"已知限制"))))&" 項",""),2,999)&"；原因見「損益與評價 → 市場共識」。") -> 需附原因的 6 項差距：觀點 6 項；原因見「損益與評價 → 市場共識」。 | I61: 與 HTML 一頁摘要同一句
A63: 3｜現價隱含什麼
A64: 隱含｜共識平均目標價隱含 2028 EV/EBITDA | B64: x | C64: =(輸入與假設!$C$446*輸入與假設!$C$321+輸入與假設!$E$472)/輸入與假設!$E$465 -> 10.585418 | I64: ＝（共識平均目標價 × 股數＋共識 2028 淨負債）÷ 共識 2028 調整後 EBITDA
A65: 隱含｜現價隱含 2028 EV/EBITDA | B65: x | C65: =(輸入與假設!$C$320*輸入與假設!$C$321+輸入與假設!$E$472)/輸入與假設!$E$465 -> 8.3622174 | I65: 同一共識 2028 數字，價格換成現價
A66: 隱含｜模型方法區間上緣 | B66: x | C66: =MAX(輸入與假設!$C$382,輸入與假設!$C$383) -> 6 | I66: 模型 EV/EBITDA 腿（AI 雲端 倍數）錨定 2029 並折回 2027-06-30，錨定年度與此不同
A67: 隱含｜模型 2028 非 AI 事業 EBITDA | B67: US$bn | C67: =輸入與假設!E$195 -> 221.13286 | I67: × 非 AI 事業 EV/EBITDA 倍數，自共識隱含 EV 扣除
A68: 隱含｜共識平均目標價隱含 2028 AI 雲端 EV/EBITDA | B68: x | C68: =IF(ABS((輸入與假設!$C$446*輸入與假設!$C$321+輸入與假設!$E$472-輸入與假設!E$195*輸入與假設!$C$378)/MAX(輸入與假設!$E$465-輸入與假設!E$195,0.01))<0.05,0,(輸入與假設!$C$446*輸入與假設!$C$321+輸入與假設!$E$472-輸入與假設!E$195*輸入與假設!$C$378)/MAX(輸入與假設!$E$465-輸入與假設!E$195,0.01)) -> 6.5401503 | I68: ＝（隱含 EV − 非 AI 事業 EBITDA × 非 AI 事業倍數）÷（共識 EBITDA − 非 AI 事業 EBITDA）
A69: 隱含｜現價隱含 2028 AI 雲端 EV/EBITDA | B69: x | C69: =IF(ABS((輸入與假設!$C$320*輸入與假設!$C$321+輸入與假設!$E$472-輸入與假設!E$195*輸入與假設!$C$378)/MAX(輸入與假設!$E$465-輸入與假設!E$195,0.01))<0.05,0,(輸入與假設!$C$320*輸入與假設!$C$321+輸入與假設!$E$472-輸入與假設!E$195*輸入與假設!$C$378)/MAX(輸入與假設!$E$465-輸入與假設!E$195,0.01)) -> 0.65242187 | I69: 同上，價格換成現價
A70: 隱含｜隱含倍數句 | C70: ="共識平均目標價 $"&TEXT(輸入與假設!$C$446,"0.00")&" 隱含 2028 EV/EBITDA "&TEXT(C64,"0.0")&"x（扣除非 AI 事業 "&TEXT(輸入與假設!$C$378,"0.0")&"x × 模型 EBITDA $"&TEXT(C67,"0.0")&"bn 後，AI 雲端 "&TEXT(C68,"0.0")&"x），AI 雲端 倍數"&IF(ROUND(C68,1)>C66,"高於",IF(ROUND(C68,1)<C66,"低於","等於"))&"模型方法區間上緣 "&IF(C66=INT(C66),TEXT(C66,"0"),TEXT(C66,"0.0"))&"x；現價 $"&TEXT(輸入與假設!$C$320,"0.00")&" 隱含 "&TEXT(C65,"0.0")&"x（AI 雲端 "&TEXT(C69,"0.0")&"x）。" -> 共識平均目標價 $331.53 隱含 2028 EV/EBITDA 10.6x（扣除非 AI 事業 13.0x × 模型 EBITDA $221.1bn 後，AI 雲端 6.5x），AI 雲端 倍數高於模型方法區間上緣 6x；現價 $259.92 隱含 8.4x（AI 雲端 0.7x）。
A71: 反向 DCF｜2030 每 MW 年收入（目前／隱含／變動） | C71: =評價_反向DCF!B18 -> 10.6813 | D71: =評價_反向DCF!C18 -> 27.8436 | E71: =評價_反向DCF!D18 -> 1.6068 | I71: 快照（預設輸入）：見『評價_反向DCF』；改輸入後請以目標搜尋重算
A72: 反向 DCF｜每 MW 建置成本（目前／隱含／變動） | C72: =評價_反向DCF!B19 -> 45.0478 | D72: =評價_反向DCF!C19 -> 無解 | E72: =評價_反向DCF!D19 -> 無解
A73: 反向 DCF｜穩態 EBITDA 率（目前／隱含／變動 pt） | C73: =評價_反向DCF!B20 -> 0.765 | D73: =評價_反向DCF!C20 -> 無解 | E73: =評價_反向DCF!D20 -> 無解
A74: 反向 DCF｜加權目標價＝現價所需每 MW 年收入（目前／隱含／變動） | C74: =評價_反向DCF!B21 -> 10.6813 | D74: =評價_反向DCF!C21 -> 21.3141 | E74: =評價_反向DCF!D21 -> 0.9955
A76: 4｜驗證點與市場看法（賣方與管理層數字標記 Interested-party）
A77: 驗證｜焦點季 | C77: =季度追蹤!C12 -> Q3 2026 | I77: 『輸入與假設』J 區選擇；季度層由年度模型拆分，只用於追蹤
A78: 驗證｜營收（模型／共識／指引低／指引高／實際） | B78: US$bn | C78: =季度追蹤!C6 -> 217.5667 | D78: =季度追蹤!D6 -> 不適用 | E78: =季度追蹤!F6 -> 197 | F78: =季度追蹤!G6 -> 202 | G78: =季度追蹤!I6 -> 待公布 | I78: 共識、指引為 Interested-party
A79: 驗證｜營收｜句 | C79: =INDEX(季度追蹤!$C$129:$H$129,輸入與假設!$C$499) -> 營收：模型 $217.57bn｜指引 $197.00–202.00bn（中點 +9.1%，高於上緣）〔觀點〕
A80: 驗證｜調整後營業利益（模型／共識／指引低／指引高／實際） | B80: US$bn | C80: =季度追蹤!C9 -> 27.386661 | D80: =季度追蹤!D9 -> 不適用 | E80: =季度追蹤!F9 -> 22.5 | F80: =季度追蹤!G9 -> 26.5 | G80: =季度追蹤!I9 -> 待公布 | I80: 共識、指引為 Interested-party
A81: 驗證｜調整後營業利益｜句 | C81: =INDEX(季度追蹤!$C$132:$H$132,輸入與假設!$C$499) -> 調整後營業利益：模型 $27.39bn｜指引 $22.50–26.50bn（中點 +$2.89bn／+0.3pt，高於上緣）〔觀點〕
A82: 驗證｜CapEx（毛額）（模型／共識／指引低／指引高／實際） | B82: US$bn | C82: =季度追蹤!C10 -> 61.845 | D82: =季度追蹤!D10 -> 不適用 | E82: =季度追蹤!F10 -> 不適用 | F82: =季度追蹤!G10 -> 不適用 | G82: =季度追蹤!I10 -> 待公布 | I82: 共識、指引為 Interested-party
A83: 驗證｜CapEx（毛額）｜句 | C83: =INDEX(季度追蹤!$C$133:$H$133,輸入與假設!$C$499) -> CapEx（毛額）：模型 $61.85bn
A84: 驗證｜評等分布（強力買進／買進／持有／賣出／強力賣出） | B84: 家 | C84: =輸入與假設!$C$457 -> 42 | D84: =輸入與假設!$C$458 -> 15 | E84: =輸入與假設!$C$459 -> 2 | F84: =輸入與假設!$C$460 -> 0 | G84: =輸入與假設!$C$461 -> 0 | I84: 2026-10，合計 59 家 [Interested-party]
A85: 驗證｜目標價（平均／中位數／最低／最高） | B85: US$ | C85: =輸入與假設!$C$446 -> 331.53 | D85: =輸入與假設!$C$447 -> 330 | E85: =輸入與假設!$C$448 -> 230 | F85: =輸入與假設!$C$449 -> 405 | I85: 59 家；S&P Global Market Intelligence（經 StockAnalysis.com），擷取 2026-10-08 [Interested-party]
A87: 來源獨立性：StockAnalysis 的目標價、評等、2026–2027 營收與 EPS 引用 S&P Global Market Intelligence。Yahoo Finance Analysis 的 2026／2027 營收（828.44／948.44）與 StockAnalysis 完全相同，推測同源（本次不視為獨立）；Yahoo 的 EPS（12.88／10.51，GAAP 口徑）與 MarketScreener 相同。MarketScreener（S&P Capital IQ 系）營收 828.285／947.853 與 S&P 相差 <0.1%，同一底層的兩個呈現，不算獨立。MarketBeat 目標價與評等為自行彙整（獨立於 S&P），作目標價的獨立交叉。營收與 EBITDA 共識本次只有 S&P 系，找不到第二個獨立供應商。
A88: 共識來源：MarketScreener（S&P Capital IQ 系共識）、S&P Global Market Intelligence（經 StockAnalysis.com）；擷取 2026-10-08。逐筆來源、日期與標記見『輸入與假設』I 區。

Sheet 輸入與假設
A1: 輸入（依類別排序；點左側 ＋／− 展開或收合。藍字可改；黃底為最關鍵假設）
A2: A 情境 → B 產能與收入 → C 利潤率 → D 支出（CapEx／折舊／租賃／JV）→ E 融資 → F 評價 → G 參考：1H26 實際 → H 情境區間運算表 → I 市場共識 → J 季度追蹤輸入。灰底『▸』為明細子區，預設收合
A4: A｜情境與規模（管理層擴張力道）
A5: 情境選擇（1＝保守 第三方可辨識站點、2＝基準 依資本支出指引、3＝積極 依公司容量目標） | C5: 2 | D5: =CHOOSE(C5,"保守 第三方可辨識站點","基準 依資本支出指引","積極 依公司容量目標") -> 基準 依資本支出指引 | I5: 三情境只改容量軸（對外 AI MW 路徑；世代組合隨新增 MW 改變每 MW 年收入）；價格軸另見 B0（對照表 r1 第 5 節第 1 條）
A6: ▸ 情境路徑明細（已連網 MW、在役比例、表外租金基準）
A7: 已連網 MW 路徑 | B7: 單位 | C7: 2026 | D7: 2027 | E7: 2028 | F7: 2029 | G7: 2030 | I7: 2031 新增 MW
A8: 評價日在役 MW（期初計費，三情境共用） | B8: MW | C8: 2080 | I8: company.json → defaults.billableOpen；來源見 scenarios.mwPath.note（第三方估計，不以營收校準）[Derived／Assumed]
A9: 保守 第三方可辨識站點｜合約 MW 上限 | B9: MW | C9: 3700 | D9: 3700 | E9: 3700 | F9: 3700 | G9: 3700 | I9: company.json → scenarios.mwPath.contracted
A10: 保守 第三方可辨識站點｜併網速度 | B10: MW／年 | C10: 720 | I10: company.json → scenarios.mwPath.pace
A11: 保守 第三方可辨識站點 | B11: MW | C11: =MIN(C9,輸入與假設!$C$8+輸入與假設!$C$10*C$34) -> 2440 | D11: =MIN(D9,C11+輸入與假設!$C$10*D$34) -> 3160 | E11: =MIN(E9,D11+輸入與假設!$C$10*E$34) -> 3700 | F11: =MIN(F9,E11+輸入與假設!$C$10*F$34) -> 3700 | G11: =MIN(G9,F11+輸入與假設!$C$10*G$34) -> 3700 | I11: 0 | J11: 對外 AI MW-IT 只計 Epoch AI 追蹤站點的已交付＋在建（三站 1,422 → 2028 預測 3,448，+2,026 × 對外 80%），每年 +720、上限 3,700；I 欄＝2031 新增 MW
A12: 基準 依資本支出指引｜合約 MW 上限 | B12: MW | C12: 99999 | D12: 99999 | E12: 99999 | F12: 99999 | G12: 99999 | I12: company.json → scenarios.mwPath.contracted
A13: 基準 依資本支出指引｜併網速度 | B13: MW／年 | C13: 3628.8 | I13: company.json → scenarios.mwPath.pace
A14: 基準 依資本支出指引 | B14: MW | C14: =MIN(C12,輸入與假設!$C$8+輸入與假設!$C$13*C$34) -> 3894.4 | D14: =MIN(D12,C14+輸入與假設!$C$13*D$34) -> 7523.2 | E14: =MIN(E12,D14+輸入與假設!$C$13*E$34) -> 11152 | F14: =MIN(F12,E14+輸入與假設!$C$13*F$34) -> 14780.8 | G14: =MIN(G12,F14+輸入與假設!$C$13*G$34) -> 18409.6 | I14: 3628.8 | J14: 對外 AI MW 新增速度＝近端資本支出隱含的建置量：2026 全年指引 $220bn −（非 AI 公式值＋GPU 汰換）÷ 每 MW 全成本（Tokenomics IT＋設施）× 對外 80%，依 λ 遞延上線 → 每年 +3,173.5 MW-IT（scripts/calib_pace.js 解，對帳落差＝0）；之後各年資本支出＝MW 路徑 × 每 MW 成本（同一套數字）[Derived]；I 欄＝2031 新增 MW
A15: 積極 依公司容量目標｜合約 MW 上限 | B15: MW | C15: 99999 | D15: 99999 | E15: 99999 | F15: 99999 | G15: 99999 | I15: company.json → scenarios.mwPath.contracted
A16: 積極 依公司容量目標｜併網速度 | B16: MW／年 | C16: 3733 | I16: company.json → scenarios.mwPath.pace
A17: 積極 依公司容量目標 | B17: MW | C17: =MIN(C15,輸入與假設!$C$8+輸入與假設!$C$16*C$34) -> 3946.5 | D17: =MIN(D15,C17+輸入與假設!$C$16*D$34) -> 7679.5 | E17: =MIN(E15,D17+輸入與假設!$C$16*E$34) -> 11412.5 | F17: =MIN(F15,E17+輸入與假設!$C$16*F$34) -> 15145.5 | G17: =MIN(G15,F17+輸入與假設!$C$16*G$34) -> 18878.5 | I17: 3733 | J17: 公司目標：2027 年底電力容量為 2025 年兩倍（2026–2027 合計新增＝2025 年底總容量）。總容量未揭露，以 Morgan Stanley 2026 +6 GW、2027 +8 GW 對照隱含約 14 GW（設施，全部負載）→ 每年 +7 GW × AI 占新增 80%（推估區間 60%–80% 上緣）÷ PUE 1.2 × 對外 80%＝每年 +3,733 MW-IT [Derived；總容量為賣方對照，非公司揭露]；I 欄＝2031 新增 MW
A18: 在役／已連網比例 | B18: % | C18: 1 | D18: 1 | E18: 1 | F18: 1 | G18: 1 | I18: 對外 AI MW 依 MW-year 計價：已連網即計費（在役比例 100%）；期初計費 MW＝第三方估計 2,080，不以 AWS 營收校準（AWS 營收含非 AI）[Assumed]
A19: 未起租租賃總額（未折現） | B19: US$bn | C19: 137.214 | I19: 季報附註已簽約未起租租賃（company.json → leases.facts.notCommenced）[Interested-party]
A20: 未起租：評價日後第幾季開始起租（0＝首期第一季） | B20: 季 | C20: 0 | I20: company.json → leases.uncommenced.startQ
A21: 未起租：平均分攤起租的季數 | B21: 季 | C21: 4 | I21: company.json → leases.uncommenced.quarters（起租時程見該欄說明）[Assumed]
A22: 未起租：每筆租期 | B22: 年 | C22: 14.75 | I22: 季報 15–19 年取中點；敏感度 15／19 年見報告 [Assumed]
A23: B｜產能與收入（MW、每 MW 年收入、利用率、信用；RPO 只作對照）
A24: 6/30 RPO | B24: US$bn | C24: 0 | I24: 季報 RPO 496.0（只作對照與債務上限的 backlog）[Interested-party]
A25: 評價日後新增承諾 | B25: US$bn | C25: 0 | I25: 評價日後新簽、尚未進 RPO 的承諾；未揭露，取 0 [Assumed]
A26: 五期認列比例（至 2030 末） | B26: % | C26: 0 | I26: 季報 RPO 桶線性分攤後五期合計 0% [Derived]
A27: RPO 桶權重合計 | B27: % | C27: 0.703125 | I27: 下方權重列的合計，用於歸一化
A28: 2025-12-31 主動電力 | B28: MW | C28: 1440 | I28: 2025 年底對外 AI MW-IT 未揭露：Trainium2 >140 萬顆 × 0.871 kW ≈ 1,220＋NVIDIA 約 600 ≈ 在役 AI 1,800 × 對外 80% ≈ 1,440 [Derived／Assumed]
A29: 6/30 Billable MW | B29: MW | C29: =輸入與假設!$C$8 -> 2080 | I29: 季末在役 MW 未揭露 [Derived]
A30: 收入用平均在役 MW（1=是） | C30: 1 | I30: 0＝用期末存量全期化；建議 1
A31: 營收驅動（mw＝MW × 每 MW 年收入；rpo＝RPO 排程） | C31: mw | I31: mw：新產能簽約率固定 100%，營收＝容量上限；RPO 只作對照與產能瓶頸旗標（company.json → defaults.revenueDriver）
A32: 每 MW 年收入倍數（整體） | B32: % | C32: 1 | I32: 反向 DCF 與壓力測試用；預設 100%。以『目標搜尋』調整此格即可反解市價隱含單價
A33: 項目 | B33: 單位 | C33: 2026 | D33: 2027 | E33: 2028 | F33: 2029 | G33: 2030 | I33: 來源／標籤
A34: 模型期長度（年） | C34: 0.5 | D34: 1 | E34: 1 | F34: 1 | G34: 1 | I34: 勿改。由 calendar_q.py 推算；只用於容量上限、電力、維護等年率換算 [Derived]
A35: RPO 桶權重 | B35: % | C35: 0.078125 | D35: 0.15625 | E35: 0.15625 | F35: 0.15625 | G35: 0.15625 | H35: =SUM(C35:G35) -> 0.703125 | I35: 季報 RPO 桶（RPO 496B（加權剩餘 6.4 年、未分桶揭露）含 AWS 非 AI 與其他，只作對照（模型排程歸 0：AI 雲端收入＝MW × 每 MW））桶內線性分攤 [Derived]
A36: Accepted MW（期末主動電力） | B36: MW | C36: =CHOOSE(輸入與假設!$C$5,C11,C14,C17) -> 3894.4 | D36: =CHOOSE(輸入與假設!$C$5,D11,D14,D17) -> 7523.2 | E36: =CHOOSE(輸入與假設!$C$5,E11,E14,E17) -> 11152 | F36: =CHOOSE(輸入與假設!$C$5,F11,F14,F17) -> 14780.8 | G36: =CHOOSE(輸入與假設!$C$5,G11,G14,G17) -> 18409.6 | I36: ＝依 A 區情境選擇器（已連網 MW-IT）
A37: Billable MW | B37: MW | C37: =ROUND(C36*C18,0) -> 3894 | D37: =ROUND(D36*D18,0) -> 7523 | E37: =ROUND(E36*E18,0) -> 11152 | F37: =ROUND(F36*F18,0) -> 14781 | G37: =ROUND(G36*G18,0) -> 18410 | I37: ＝已連網 × 在役比例（A 區）
A38: 利用率 | B38: % | C38: 1 | D38: 1 | E38: 1 | F38: 1 | G38: 1 | I38: 100%：按 MW-year 計價，收入端不乘 IF_Util（Tokenomics 下游契約第 3 條）
A39: 每 MW 年收入 | B39: US$bn/MW | C39: =C104*輸入與假設!$C$56/1000 -> 0.0097857081 | D39: =D104*輸入與假設!$C$56/1000 -> 0.010218303 | E39: =E104*輸入與假設!$C$56/1000 -> 0.010473071 | F39: =F104*輸入與假設!$C$56/1000 -> 0.010602745 | G39: =G104*輸入與假設!$C$56/1000 -> 0.010681297 | I39: ＝加權每 MW 年持有成本 × 採用 k ÷ 1000（B0；Tokenomics × k，不以公司營收反推）
A40: 新產能簽約率 | B40: % | C40: 1 | D40: 1 | E40: 1 | F40: 1 | G40: 1 | I40: MW 驅動：100%（RPO 只作對照）
A41: 客戶違約率 | B41: % | C41: 0 | D41: 0 | E41: 0 | F41: 0 | G41: 0 | I41: 前三大客戶約 59% 營收的定價，非預測 [Assumed]
A42: 回收率 | B42: % | C42: 0.5 | D42: 0.5 | E42: 0.5 | F42: 0.5 | G42: 0.5 | I42: [Assumed]
A43: 非算力服務營收 | B43: US$bn | C43: 0 | D43: 0 | E43: 0 | F43: 0 | G43: 0 | I43: 預設 0：AI cloud 軟體已含在每 MW 年收入；其他事業另列 [Assumed]
A44: 其他事業 EBITDA（輸入） | B44: US$bn | C44: 0 | D44: 0 | E44: 0 | F44: 0 | G44: 0 | I44: 未分攤公司層費用（Amazon 分部營業利益已含全部費用，無未分攤項）：0
A45: 租用算力租金（營運成本） | B45: US$bn | C45: =0 -> 0 | D45: =0 -> 0 | E45: =0 -> 0 | F45: =0 -> 0 | G45: =0 -> 0 | I45: 租用算力（向 neocloud 租 GPU）：未見 Amazon 公開合約（Amazon 為出租方；Cipher Black Pearl 為機房租約，已在未起租租賃內）→ 空清單。格式：[{name, start（YYYY-MM）, years, annualRent（US$bn／年）, mw, use（external／internal）}]；租金計入營運成本（扣 EBITDA 與營運現金，不是資本支出；對照表 r1 第 5 節第 7 條、C8 d）
A46: 其他事業 EBITDA | B46: US$bn | C46: =C44-C45 -> 0 | D46: =D44-D45 -> 0 | E46: =E44-E45 -> 0 | F46: =F44-F45 -> 0 | G46: =G44-G45 -> 0 | I46: ＝輸入 − 租用算力租金（下游引用此列）
A47: 股權報酬占營收（SBC，非現金加回） | B47: % | C47: 0.024899 | I47: 股權報酬（SBC）為非現金費用：分部營業利益已扣除，營運現金加回＝SBC 占營收 × 模型期總營收；近四季 SBC 19.314 ÷ 營收 775.680＝2.49%（現金流量表；[Derived]）。股數稀釋沿用模板每年 1%（EBITDA 已扣 SBC，評價略重複計入，偏保守）
A48: 2026 剩餘季度營運資金變動（上年同期實際，流入為正） | B48: US$bn | C48: 1.947 | I48: 首期剩餘季度（2026 下半年）營運資金變動＝上一年度同期實際：2025 全年「營運資產與負債變動」合計 −19.969（10-K）− 2025 上半年 −21.916（2026Q2 10-Q 比較欄）＝+1.947（流入）[Derived]；之後年度沿用營收增量比例（MAG 對照表 r1 C14；已實現的季節模式，非預測）
A49: ▸ B0｜對外 AI 雲端定價：每 MW 年收入＝Σ 在役世代占比 × Tokenomics 持有成本 × 晶片係數 × k（收入端不乘 IF_Util）
A50: 價格軸選擇（1＝低 長約下緣、2＝基準 C1 混合、3＝高 現貨改用 AWS 牌價） | C50: 2 | D50: =CHOOSE(C50,"低 長約下緣","基準 C1 混合","高 現貨改用 AWS 牌價") -> 基準 C1 混合 | I50: 價格軸與容量軸（A 區情境）分離；三容量情境預設都用基準 k，3 × 3 目標價矩陣見「評價_DCF與目標價」（對照表 r1 第 5 節第 1 條）
A51: k 組成（價格軸） | B51: 單位 | C51: 低 | D51: 基準 | E51: 高
A52: k｜長約 | B52: 倍 | C52: 0.55 | D52: 0.75 | E52: 0.75 | I52: 長約 k：OpenAI Trainium 0.70（IT）–0.84（設施）、OpenAI NVIDIA 30 萬顆 0.82 → 基準 0.75；低＝長約區間下緣 0.55（Anthropic 下限 0.22–0.45 只作對照）[Assumed]（kevidence longContracts）
A53: k｜現貨 | B53: 倍 | C53: 1.76 | D53: 1.76 | E53: 4.29 | I53: 現貨 k：基準 1.76＝與 Nebius／CRWV 同一市場現貨指數（對照表 r1 C1）；高＝AWS 牌價換算（p5.48xlarge 隨需 6.88 ÷ IF_GPUhrEcon H100 1.605＝4.29，kevidence price.p5.od）
A54: 長約占比 | B54: % | C54: 0.8 | D54: 0.8 | E54: 0.8 | I54: 長約占比 80%（Anthropic Trainium2 三站＋OpenAI 兩筆占對外容量多數；70%–90% [Assumed]）
A55: 混合 k | B55: 倍 | C55: =C54*C52+(1-C54)*C53 -> 0.792 | D55: =D54*D52+(1-D54)*D53 -> 0.952 | E55: =E54*E52+(1-E54)*E53 -> 1.458 | I55: ＝長約占比 × k_長約＋(1 − 長約占比) × k_現貨
A56: 採用 k（依價格軸） | B56: 倍 | C56: =CHOOSE(輸入與假設!$C$50,C55,D55,E55) -> 0.952 | I56: ＝依上方價格軸選擇
A57: 自研晶片持有成本係數 | B57: 倍 | C57: 1 | I57: 自研晶片（Trainium）每 MW 錨＝同期 NVIDIA 世代 IF_HoldEcon × 1.0（Trainium2 → Hopper、Trainium3 → GB300；對照表 r1 C2）；敏感度 × 0.7。Tokenomics 無 NonNV 具名範圍（IF_NonNVRatio、IF_NonNVCostRatio 為 missing），已列缺口回報。
A58: 自研晶片 IT 資本支出係數 | B58: 倍 | C58: 1 | I58: 自研晶片每 MW IT 資本支出係數：預設 1（Trainium 的資本支出以同期 NVIDIA 世代 TK_CapexIT 計）；雙邊敏感度時與 customFactor 同乘 0.7（收入錨與資本支出同降）；機房成本不變 [Assumed]
A59: 上限檢查門檻（每 MW 年收入 ÷ 參考付費營收） | B59: % | C59: 0.5 | I59: 上限檢查：每 MW 年收入 ÷（Σ 世代占比 × IF_RevGWFleet／1000）> 50% 時示警（工作單 v0.1b 第 2 步）
A60: 項目 | B60: 單位 | C60: 2026 | D60: 2027 | E60: 2028 | F60: 2029 | G60: 2030 | I60: 來源／標籤
A61: 世代｜Trainium2｜每 MW 年持有成本 | B61: US$m/MW | C61: =TK_HoldEcon_H100*輸入與假設!$C$57 -> 9.7030873 | I61: Tokenomics IF_HoldEcon（H100）× 自研晶片係數（對照表 r1 C2）；US$B/GW＝US$m/MW
A62: 世代｜Trainium2｜每 MW 年營運成本 | B62: US$m/MW | C62: =TK_OpexGW_H100 -> 1.8846675 | I62: Tokenomics IF_OpexGW（H100；不含折舊，含電費）
A63: 世代｜Trainium2｜每 MW 參考付費營收（利用率層） | B63: US$m/MW | C63: =TK_IFW_RevGWFleet_Util_H100 -> 4.0048877 | I63: Tokenomics IFW_RevGWFleet_Util（H100；四層瀑布利用率層；上限，不得作預測，只作檢查）
A64: 世代｜Trainium2｜每 MW 參考付費營收（生產折減層） | B64: US$m/MW | C64: =TK_IFW_RevGWFleet_Prod_H100 -> 2.242962 | I64: Tokenomics IFW_RevGWFleet_Prod（H100；利用率層 × 生產折減；硬上限，只作檢查）
A65: 世代｜Trainium2｜期初在役占比 | B65: % | C65: 0.55 | I65: 期初在役（評價日）：Trainium2 55%、Hopper／GB200／GB300 各 15%（v0.1a，[Assumed]）。新增 MW：自研與 NVIDIA 各半（Trainium3 2026 年初出貨且「接近全數認購」；NVIDIA 2026 部署 >100 萬顆、2026-08 追加 200 萬顆於 2027–2028 交付）；NVIDIA 部分 2026 為 GB300、2027 GB300／VR200 各半、2028 起 VR200 [Assumed]。在役占比＝各世代累計 MW ÷ 對外 AI MW（不建模退役後的世代替換）。
A66: 世代｜Trainium2｜新增 MW 占比 | B66: % | C66: 0 | D66: 0 | E66: 0 | F66: 0 | G66: 0 | I66: 各期新增在役 MW 的世代組合 [Assumed]
A67: 世代｜Trainium2｜在役 MW | B67: MW | C67: =輸入與假設!$C$65*輸入與假設!$C$29+MAX(0,C36-輸入與假設!$C$29)*C66 -> 1144 | D67: =C67+MAX(0,D36-C36)*D66 -> 1144 | E67: =D67+MAX(0,E36-D36)*E66 -> 1144 | F67: =E67+MAX(0,F36-E36)*F66 -> 1144 | G67: =F67+MAX(0,G36-F36)*G66 -> 1144 | I67: ＝前期＋本期新增 × 新增占比（首期＝評價日在役 × 期初占比＋新增）
A68: 世代｜Hopper（H100／H200）｜每 MW 年持有成本 | B68: US$m/MW | C68: =TK_HoldEcon_H100 -> 9.7030873 | I68: Tokenomics IF_HoldEcon（H100）；US$B/GW＝US$m/MW
A69: 世代｜Hopper（H100／H200）｜每 MW 年營運成本 | B69: US$m/MW | C69: =TK_OpexGW_H100 -> 1.8846675 | I69: Tokenomics IF_OpexGW（H100；不含折舊，含電費）
A70: 世代｜Hopper（H100／H200）｜每 MW 參考付費營收（利用率層） | B70: US$m/MW | C70: =TK_IFW_RevGWFleet_Util_H100 -> 4.0048877 | I70: Tokenomics IFW_RevGWFleet_Util（H100；四層瀑布利用率層；上限，不得作預測，只作檢查）
A71: 世代｜Hopper（H100／H200）｜每 MW 參考付費營收（生產折減層） | B71: US$m/MW | C71: =TK_IFW_RevGWFleet_Prod_H100 -> 2.242962 | I71: Tokenomics IFW_RevGWFleet_Prod（H100；利用率層 × 生產折減；硬上限，只作檢查）
A72: 世代｜Hopper（H100／H200）｜期初在役占比 | B72: % | C72: 0.15 | I72: 見第一個世代的說明 [Assumed]
A73: 世代｜Hopper（H100／H200）｜新增 MW 占比 | B73: % | C73: 0 | D73: 0 | E73: 0 | F73: 0 | G73: 0 | I73: 各期新增在役 MW 的世代組合 [Assumed]
A74: 世代｜Hopper（H100／H200）｜在役 MW | B74: MW | C74: =輸入與假設!$C$72*輸入與假設!$C$29+MAX(0,C36-輸入與假設!$C$29)*C73 -> 312 | D74: =C74+MAX(0,D36-C36)*D73 -> 312 | E74: =D74+MAX(0,E36-D36)*E73 -> 312 | F74: =E74+MAX(0,F36-E36)*F73 -> 312 | G74: =F74+MAX(0,G36-F36)*G73 -> 312 | I74: ＝前期＋本期新增 × 新增占比（首期＝評價日在役 × 期初占比＋新增）
A75: 世代｜GB200｜每 MW 年持有成本 | B75: US$m/MW | C75: =TK_HoldEcon_GB200 -> 8.8281656 | I75: Tokenomics IF_HoldEcon（GB200）；US$B/GW＝US$m/MW
A76: 世代｜GB200｜每 MW 年營運成本 | B76: US$m/MW | C76: =TK_OpexGW_GB200 -> 1.8122327 | I76: Tokenomics IF_OpexGW（GB200；不含折舊，含電費）
A77: 世代｜GB200｜每 MW 參考付費營收（利用率層） | B77: US$m/MW | C77: =TK_IFW_RevGWFleet_Util_GB200 -> 20.174616 | I77: Tokenomics IFW_RevGWFleet_Util（GB200；四層瀑布利用率層；上限，不得作預測，只作檢查）
A78: 世代｜GB200｜每 MW 參考付費營收（生產折減層） | B78: US$m/MW | C78: =TK_IFW_RevGWFleet_Prod_GB200 -> 15.285161 | I78: Tokenomics IFW_RevGWFleet_Prod（GB200；利用率層 × 生產折減；硬上限，只作檢查）
A79: 世代｜GB200｜期初在役占比 | B79: % | C79: 0.15 | I79: 見第一個世代的說明 [Assumed]
A80: 世代｜GB200｜新增 MW 占比 | B80: % | C80: 0 | D80: 0 | E80: 0 | F80: 0 | G80: 0 | I80: 各期新增在役 MW 的世代組合 [Assumed]
A81: 世代｜GB200｜在役 MW | B81: MW | C81: =輸入與假設!$C$79*輸入與假設!$C$29+MAX(0,C36-輸入與假設!$C$29)*C80 -> 312 | D81: =C81+MAX(0,D36-C36)*D80 -> 312 | E81: =D81+MAX(0,E36-D36)*E80 -> 312 | F81: =E81+MAX(0,F36-E36)*F80 -> 312 | G81: =F81+MAX(0,G36-F36)*G80 -> 312 | I81: ＝前期＋本期新增 × 新增占比（首期＝評價日在役 × 期初占比＋新增）
A82: 世代｜GB300｜每 MW 年持有成本 | B82: US$m/MW | C82: =TK_HoldEcon_GB300 -> 10.886411 | I82: Tokenomics IF_HoldEcon（GB300）；US$B/GW＝US$m/MW
A83: 世代｜GB300｜每 MW 年營運成本 | B83: US$m/MW | C83: =TK_OpexGW_GB300 -> 1.9826348 | I83: Tokenomics IF_OpexGW（GB300；不含折舊，含電費）
A84: 世代｜GB300｜每 MW 參考付費營收（利用率層） | B84: US$m/MW | C84: =TK_IFW_RevGWFleet_Util_GB300 -> 26.265236 | I84: Tokenomics IFW_RevGWFleet_Util（GB300；四層瀑布利用率層；上限，不得作預測，只作檢查）
A85: 世代｜GB300｜每 MW 參考付費營收（生產折減層） | B85: US$m/MW | C85: =TK_IFW_RevGWFleet_Prod_GB300 -> 19.232465 | I85: Tokenomics IFW_RevGWFleet_Prod（GB300；利用率層 × 生產折減；硬上限，只作檢查）
A86: 世代｜GB300｜期初在役占比 | B86: % | C86: 0.15 | I86: 見第一個世代的說明 [Assumed]
A87: 世代｜GB300｜新增 MW 占比 | B87: % | C87: 0.5 | D87: 0.25 | E87: 0 | F87: 0 | G87: 0 | I87: 各期新增在役 MW 的世代組合 [Assumed]
A88: 世代｜GB300｜在役 MW | B88: MW | C88: =輸入與假設!$C$86*輸入與假設!$C$29+MAX(0,C36-輸入與假設!$C$29)*C87 -> 1219.2 | D88: =C88+MAX(0,D36-C36)*D87 -> 2126.4 | E88: =D88+MAX(0,E36-D36)*E87 -> 2126.4 | F88: =E88+MAX(0,F36-E36)*F87 -> 2126.4 | G88: =F88+MAX(0,G36-F36)*G87 -> 2126.4 | I88: ＝前期＋本期新增 × 新增占比（首期＝評價日在役 × 期初占比＋新增）
A89: 世代｜Trainium3｜每 MW 年持有成本 | B89: US$m/MW | C89: =TK_HoldEcon_GB300*輸入與假設!$C$57 -> 10.886411 | I89: Tokenomics IF_HoldEcon（GB300）× 自研晶片係數（對照表 r1 C2）；US$B/GW＝US$m/MW
A90: 世代｜Trainium3｜每 MW 年營運成本 | B90: US$m/MW | C90: =TK_OpexGW_GB300 -> 1.9826348 | I90: Tokenomics IF_OpexGW（GB300；不含折舊，含電費）
A91: 世代｜Trainium3｜每 MW 參考付費營收（利用率層） | B91: US$m/MW | C91: =TK_IFW_RevGWFleet_Util_GB300 -> 26.265236 | I91: Tokenomics IFW_RevGWFleet_Util（GB300；四層瀑布利用率層；上限，不得作預測，只作檢查）
A92: 世代｜Trainium3｜每 MW 參考付費營收（生產折減層） | B92: US$m/MW | C92: =TK_IFW_RevGWFleet_Prod_GB300 -> 19.232465 | I92: Tokenomics IFW_RevGWFleet_Prod（GB300；利用率層 × 生產折減；硬上限，只作檢查）
A93: 世代｜Trainium3｜期初在役占比 | B93: % | C93: 0 | I93: 見第一個世代的說明 [Assumed]
A94: 世代｜Trainium3｜新增 MW 占比 | B94: % | C94: 0.5 | D94: 0.5 | E94: 0.5 | F94: 0.5 | G94: 0.5 | I94: 各期新增在役 MW 的世代組合 [Assumed]
A95: 世代｜Trainium3｜在役 MW | B95: MW | C95: =輸入與假設!$C$93*輸入與假設!$C$29+MAX(0,C36-輸入與假設!$C$29)*C94 -> 907.2 | D95: =C95+MAX(0,D36-C36)*D94 -> 2721.6 | E95: =D95+MAX(0,E36-D36)*E94 -> 4536 | F95: =E95+MAX(0,F36-E36)*F94 -> 6350.4 | G95: =F95+MAX(0,G36-F36)*G94 -> 8164.8 | I95: ＝前期＋本期新增 × 新增占比（首期＝評價日在役 × 期初占比＋新增）
A96: 世代｜Vera Rubin（VR200）｜每 MW 年持有成本 | B96: US$m/MW | C96: =TK_HoldEcon_VR200 -> 12.225471 | I96: Tokenomics IF_HoldEcon（VR200）；US$B/GW＝US$m/MW
A97: 世代｜Vera Rubin（VR200）｜每 MW 年營運成本 | B97: US$m/MW | C97: =TK_OpexGW_VR200 -> 2.0934955 | I97: Tokenomics IF_OpexGW（VR200；不含折舊，含電費）
A98: 世代｜Vera Rubin（VR200）｜每 MW 參考付費營收（利用率層） | B98: US$m/MW | C98: =TK_IFW_RevGWFleet_Util_VR200 -> 48.723702 | I98: Tokenomics IFW_RevGWFleet_Util（VR200；四層瀑布利用率層；上限，不得作預測，只作檢查）
A99: 世代｜Vera Rubin（VR200）｜每 MW 參考付費營收（生產折減層） | B99: US$m/MW | C99: =TK_IFW_RevGWFleet_Prod_VR200 -> 38.114547 | I99: Tokenomics IFW_RevGWFleet_Prod（VR200；利用率層 × 生產折減；硬上限，只作檢查）
A100: 世代｜Vera Rubin（VR200）｜期初在役占比 | B100: % | C100: 0 | I100: 見第一個世代的說明 [Assumed]
A101: 世代｜Vera Rubin（VR200）｜新增 MW 占比 | B101: % | C101: 0 | D101: 0.25 | E101: 0.5 | F101: 0.5 | G101: 0.5 | I101: 各期新增在役 MW 的世代組合 [Assumed]
...

Sheet 各期收支
A1: 支出與資金 — 五層支出、四層來源、現金橋
A2: 2026 欄＝1H 實際（季報現金流量表口徑）＋下半年模型；2027 以後為純模型。瀑布以「融資前現金」決定需求並直接由各支出列加總，因此沒有循環參照
A4: 項目 | B4: 單位 | C4: 2026 | D4: 2027 | E4: 2028 | F4: 2029 | G4: 2030 | I4: 公式／來源說明
A5: 支出（五層）
A6: ① 毛 CapEx（認列，備忘） | B6: US$bn | C6: =輸入與假設!$C$417+輸入與假設!C$277 -> 220 | D6: =輸入與假設!D$277 -> 276.22582 | E6: =輸入與假設!E$277 -> 291.66355 | F6: =輸入與假設!F$277 -> 305.37569 | G6: =輸入與假設!G$277 -> 427.86374 | I6: 2026＝1H 實際認列 96.31＋2H 模型；對照公司全年指引 220–220。備忘列：用途合計採現金口徑，不用這一列
A7: 客戶預付率 | B7: % | C7: =輸入與假設!C$233 -> 0 | D7: =輸入與假設!D$233 -> 0 | E7: =輸入與假設!E$233 -> 0 | F7: =輸入與假設!F$233 -> 0 | G7: =輸入與假設!G$233 -> 0
A8: 客戶預付金額（抵減，2H 起） | B8: US$bn | C8: =輸入與假設!C$253*C7 -> 0 | D8: =輸入與假設!D$253*D7 -> 0 | E8: =輸入與假設!E$253*E7 -> 0 | F8: =輸入與假設!F$253*F7 -> 0 | G8: =輸入與假設!G$253*G7 -> 0 | I8: ＝成長型 CapEx × 預付比率（汰換 CapEx 不計）；1H 的預付已含在實際 CFO 內，不重複計入
A9: 合約負債期初（客戶預付餘額） | B9: US$bn | C9: =輸入與假設!$C$230 -> 0 | D9: =C12 -> 0 | E9: =D12 -> 0 | F9: =E12 -> 0 | G9: =F12 -> 0 | I9: 2026 期初＝6/30 季報遞延營收
A10: 合約負債利息累積（重大財務組成，非現金） | B10: US$bn | C10: =輸入與假設!$C$231*(C9+0.5*C8)*運營_產能與收入!C7 -> 0 | D10: =輸入與假設!$C$231*(D9+0.5*D8)*運營_產能與收入!D7 -> 0 | E10: =輸入與假設!$C$231*(E9+0.5*E8)*運營_產能與收入!E7 -> 0 | F10: =輸入與假設!$C$231*(F9+0.5*F8)*運營_產能與收入!F7 -> 0 | G10: =輸入與假設!$C$231*(G9+0.5*G8)*運營_產能與收入!G7 -> 0 | I10: ＝隱含利率 ×(期初合約負債＋本期預付流入 × ½)× 期間長度；進損益利息、不進現金（v0.1b）
A11: 預付認列（非現金營收） | B11: US$bn | C11: =MIN(C9+C10,(C9+C10)/輸入與假設!$C$229*運營_產能與收入!C7) -> 0 | D11: =MIN(D9+D10,(D9+D10)/輸入與假設!$C$229*運營_產能與收入!D7) -> 0 | E11: =MIN(E9+E10,(E9+E10)/輸入與假設!$C$229*運營_產能與收入!E7) -> 0 | F11: =MIN(F9+F10,(F9+F10)/輸入與假設!$C$229*運營_產能與收入!F7) -> 0 | G11: =MIN(G9+G10,(G9+G10)/輸入與假設!$C$229*運營_產能與收入!G7) -> 0 | I11: ＝(期初合約負債＋累積利息) ÷ 認列年數 × 期間長度；這部分營收已在預付時收現，自營運來源扣除
A12: 合約負債期末 | B12: US$bn | C12: =C9+C8+C10-C11 -> 0 | D12: =D9+D8+D10-D11 -> 0 | E12: =E9+E8+E10-E11 -> 0 | F12: =F9+F8+F10-F11 -> 0 | G12: =G9+G8+G10-G11 -> 0 | I12: ＝期初＋預付流入＋累積利息−認列
A13: ① CapEx（用途用：1H 現金／2H 毛額） | B13: US$bn | C13: =輸入與假設!$C$416+輸入與假設!C$277 -> 220 | D13: =輸入與假設!D$277 -> 276.22582 | E13: =輸入與假設!E$277 -> 291.66355 | F13: =輸入與假設!F$277 -> 305.37569 | G13: =輸入與假設!G$277 -> 427.86374 | I13: 1H 採現金流量表的現金購置 96.31；2H 起採毛額，客戶預付在來源端抵回（避免重複計入）
A14: ② 在帳現金租金（備忘，1H 已含在 CFO） | B14: US$bn | C14: =輸入與假設!C$234 -> 10.776 | D14: =輸入與假設!D$234 -> 17.222 | E14: =輸入與假設!E$234 -> 16.503 | F14: =輸入與假設!F$234 -> 14.787 | G14: =輸入與假設!G$234 -> 13.258 | I14: 見『租賃與承諾』頁；2030 後尚有 71.534。2026 欄僅 2H：1H 租金 9.154 已含在實際 CFO 內
A15: ② 表外現金租金（未起租） | B15: US$bn | C15: =運營_產能與收入!C59 -> 1.7442458 | D15: =運營_產能與收入!D59 -> 8.7212288 | E15: =運營_產能與收入!E59 -> 9.3026441 | F15: =運營_產能與收入!F59 -> 9.3026441 | G15: =運營_產能與收入!G59 -> 9.3026441 | I15: 已簽約未起租租賃 137.214 的現金路徑
A16: 租金合計 | B16: US$bn | C16: =輸入與假設!C$237+C15*輸入與假設!$C$238 -> 1.7734998 | D16: =輸入與假設!D$237+D15*輸入與假設!$C$238 -> 4.1244989 | E16: =輸入與假設!E$237+E15*輸入與假設!$C$238 -> 4.3576655 | F16: =輸入與假設!F$237+F15*輸入與假設!$C$238 -> 3.9666655 | G16: =輸入與假設!G$237+G15*輸入與假設!$C$238 -> 3.7676655 | I16: ＝在帳融資租賃現金＋未起租 × 融資部分比例（MAG v0.1b：營業租賃已含在分部 EBITDA，不重複扣除；AI 雲端 EBITDA 由 Tokenomics 推得、未扣租金）
A17: ③ 存量債務利息（備忘，1H 已含在 CFO） | B17: US$bn | C17: =輸入與假設!C$317 -> 2.7011651 | D17: =輸入與假設!D$317 -> 5.2228482 | E17: =輸入與假設!E$317 -> 4.7936718 | F17: =輸入與假設!F$317 -> 4.3577321 | G17: =輸入與假設!G$317 -> 4.0275885 | I17: ="6/30 債務餘額的利息。2026 全年利息＝1H 實際 2.114＋2H "&TEXT(C17,"0.0")&"＝"&TEXT(2.114+C17,"0.00")&"（見下方備忘）" -> 6/30 債務餘額的利息。2026 全年利息＝1H 實際 2.114＋2H 2.7＝4.82（見下方備忘）
A18: 期初累積現金 | B18: US$bn | C18: =輸入與假設!$C$414 -> 123.029 | D18: =C56 -> 64.690577 | E18: =D56 -> 50 | F18: =E56 -> 50 | G18: =F56 -> 50 | I18: 2026 自 2025-12-31 起算；之後＝前期期末累積現金
A19: 新債利率 | B19: % | C19: =IF(輸入與假設!$C$310=1,輸入與假設!C$316+MAX(0,輸入與假設!$C$309-450)/100*0.004,輸入與假設!C$316) -> 0.05 | D19: =IF(輸入與假設!$C$310=1,輸入與假設!D$316+MAX(0,輸入與假設!$C$309-450)/100*0.004,輸入與假設!D$316) -> 0.05 | E19: =IF(輸入與假設!$C$310=1,輸入與假設!E$316+MAX(0,輸入與假設!$C$309-450)/100*0.004,輸入與假設!E$316) -> 0.05 | F19: =IF(輸入與假設!$C$310=1,輸入與假設!F$316+MAX(0,輸入與假設!$C$309-450)/100*0.004,輸入與假設!F$316) -> 0.05 | G19: =IF(輸入與假設!$C$310=1,輸入與假設!G$316+MAX(0,輸入與假設!$C$309-450)/100*0.004,輸入與假設!G$316) -> 0.05 | I19: CDS 開關：＋MAX(0,CDS−450)×0.4bp/bp
A20: ③ 新債利息（瀑布） | B20: US$bn | C20: =C94 -> 0 | D20: =D94 -> 3.3589802 | E20: =E94 -> 5.8169685 | F20: =F94 -> 6.1840427 | G20: =G94 -> 10.333028 | I20: ＝新債利率×期間長度×(期初新債＋本期舉借)；見下方「期前融資瀑布」
A21: 利息合計 | B21: US$bn | C21: =C17+C20 -> 2.7011651 | D21: =D17+D20 -> 8.5818284 | E21: =E17+E20 -> 10.61064 | F21: =F17+F20 -> 10.541775 | G21: =G17+G20 -> 14.360616
A22: ④ JV／策略投資出資 | B22: US$bn | C22: =輸入與假設!$C$418+輸入與假設!C$241 -> 61.067 | D22: =輸入與假設!D$241 -> 0 | E22: =輸入與假設!E$241 -> 0 | F22: =輸入與假設!F$241 -> 0 | G22: =輸入與假設!G$241 -> 0 | I22: 2026＝1H 實際 39.767（JV 0.000＋策略投資 39.767）＋2H 模型。AMZN 不發股息
A23: ⑧ 股利（普通股＋特別股） | B23: US$bn | C23: =輸入與假設!$C$433+4*輸入與假設!$C$291*(1+輸入與假設!$C$292)^0*運營_產能與收入!C7*(輸入與假設!$C$293+0+SUMPRODUCT(資產負債_既有債務!$D$28:$D$28*資產負債_既有債務!$H$24:$H$24*(資產負債_既有債務!$G$24:$G$24<0)))+輸入與假設!C$314 -> 0 | D23: =4*輸入與假設!$C$291*(1+輸入與假設!$C$292)^1*運營_產能與收入!D7*(輸入與假設!$C$293+C97+SUMPRODUCT(資產負債_既有債務!$D$28:$D$28*資產負債_既有債務!$H$24:$H$24*(資產負債_既有債務!$G$24:$G$24<1)))+輸入與假設!D$314 -> 0 | E23: =4*輸入與假設!$C$291*(1+輸入與假設!$C$292)^2*運營_產能與收入!E7*(輸入與假設!$C$293+D97+SUMPRODUCT(資產負債_既有債務!$D$28:$D$28*資產負債_既有債務!$H$24:$H$24*(資產負債_既有債務!$G$24:$G$24<2)))+輸入與假設!E$314 -> 0 | F23: =4*輸入與假設!$C$291*(1+輸入與假設!$C$292)^3*運營_產能與收入!F7*(輸入與假設!$C$293+E97+SUMPRODUCT(資產負債_既有債務!$D$28:$D$28*資產負債_既有債務!$H$24:$H$24*(資產負債_既有債務!$G$24:$G$24<3)))+輸入與假設!F$314 -> 0 | G23: =4*輸入與假設!$C$291*(1+輸入與假設!$C$292)^4*運營_產能與收入!G7*(輸入與假設!$C$293+F97+SUMPRODUCT(資產負債_既有債務!$D$28:$D$28*資產負債_既有債務!$H$24:$H$24*(資產負債_既有債務!$G$24:$G$24<4)))+輸入與假設!G$314 -> 0 | I23: 普通股＝每股每季 × 4 × 期間長度 ×(基礎股數＋前期累計瀑布新股＋已強制轉換特別股)＋特別股股利；2026＝1H 實際＋2H 模型（v0.1b）
A24: ⑨ 回購（瀑布：現金不足時先減） | B24: US$bn | C24: =輸入與假設!$C$435+C76 -> 0 | D24: =D76 -> 0 | E24: =E76 -> 0 | F24: =F76 -> 0 | G24: =G76 -> 0 | I24: 2026＝1H 實際＋2H 瀑布後實際回購；計畫與被迫減少見下方「期前融資瀑布」（MAG v0.1b）
A25: 電力（overlay） | B25: US$bn | C25: =IF(輸入與假設!$C$207=1,運營_產能與收入!C9*8760*輸入與假設!C$209*輸入與假設!C$208/1000000000*運營_產能與收入!C7,0) -> 0 | D25: =IF(輸入與假設!$C$207=1,運營_產能與收入!D9*8760*輸入與假設!D$209*輸入與假設!D$208/1000000000*運營_產能與收入!D7,0) -> 0 | E25: =IF(輸入與假設!$C$207=1,運營_產能與收入!E9*8760*輸入與假設!E$209*輸入與假設!E$208/1000000000*運營_產能與收入!E7,0) -> 0 | F25: =IF(輸入與假設!$C$207=1,運營_產能與收入!F9*8760*輸入與假設!F$209*輸入與假設!F$208/1000000000*運營_產能與收入!F7,0) -> 0 | G25: =IF(輸入與假設!$C$207=1,運營_產能與收入!G9*8760*輸入與假設!G$209*輸入與假設!G$208/1000000000*運營_產能與收入!G7,0) -> 0 | I25: ＝已連網 MW×8760×PUE×電價÷1e9×期間係數。EBITDA 率已含電費，預設關閉
A26: 維護（overlay） | B26: US$bn | C26: =IF(輸入與假設!$C$207=1,運營_產能與收入!C9*輸入與假設!C$210/1000*運營_產能與收入!C7,0) -> 0 | D26: =IF(輸入與假設!$C$207=1,運營_產能與收入!D9*輸入與假設!D$210/1000*運營_產能與收入!D7,0) -> 0 | E26: =IF(輸入與假設!$C$207=1,運營_產能與收入!E9*輸入與假設!E$210/1000*運營_產能與收入!E7,0) -> 0 | F26: =IF(輸入與假設!$C$207=1,運營_產能與收入!F9*輸入與假設!F$210/1000*運營_產能與收入!F7,0) -> 0 | G26: =IF(輸入與假設!$C$207=1,運營_產能與收入!G9*輸入與假設!G$210/1000*運營_產能與收入!G7,0) -> 0
A27: ⑤ 排程還本（季報到期表） | B27: US$bn | C27: =輸入與假設!$C$420+IF(輸入與假設!$C$286=1,輸入與假設!C$315,0)+資產負債_既有債務!C39 -> 3.048 | D27: =IF(輸入與假設!$C$286=1,輸入與假設!D$315,0)+資產負債_既有債務!D39 -> 8.837 | E27: =IF(輸入與假設!$C$286=1,輸入與假設!E$315,0)+資產負債_既有債務!E39 -> 12.294 | F27: =IF(輸入與假設!$C$286=1,輸入與假設!F$315,0)+資產負債_既有債務!F39 -> 9.17 | G27: =IF(輸入與假設!$C$286=1,輸入與假設!G$315,0)+資產負債_既有債務!G39 -> 7.085 | I27: 2026＝1H 實際還款 3.048＋2H 到期表 0.0
A28: ⑥ capped call 支出（1H 實際） | B28: US$bn | C28: =輸入與假設!$C$421 -> 0 | D28: =0 -> 0 | E28: =0 -> 0 | F28: =0 -> 0 | G28: =0 -> 0 | I28: 可轉債配套 capped call 現金支出（未見揭露，0）
A29: ⑦ 現金稅（2H 起） | B29: US$bn | C29: =輸入與假設!$C$308*MAX(0,運營_產能與收入!C38*輸入與假設!C$204+輸入與假設!C$46+輸入與假設!C$195-輸入與假設!C$196-運營_產能與收入!C62-輸入與假設!C$278-輸入與假設!C$317) -> 9.9271981 | D29: =輸入與假設!$C$308*MAX(0,運營_產能與收入!D38*輸入與假設!D$204+輸入與假設!D$46+輸入與假設!D$195-輸入與假設!D$196-運營_產能與收入!D62-輸入與假設!D$278-輸入與假設!D$317) -> 22.00756 | E29: =輸入與假設!$C$308*MAX(0,運營_產能與收入!E38*輸入與假設!E$204+輸入與假設!E$46+輸入與假設!E$195-輸入與假設!E$196-運營_產能與收入!E62-輸入與假設!E$278-輸入與假設!E$317) -> 25.02374 | F29: =輸入與假設!$C$308*MAX(0,運營_產能與收入!F38*輸入與假設!F$204+輸入與假設!F$46+輸入與假設!F$195-輸入與假設!F$196-運營_產能與收入!F62-輸入與假設!F$278-輸入與假設!F$317) -> 27.388951 | G29: =輸入與假設!$C$308*MAX(0,運營_產能與收入!G38*輸入與假設!G$204+輸入與假設!G$46+輸入與假設!G$195-輸入與假設!G$196-運營_產能與收入!G62-輸入與假設!G$278-輸入與假設!G$317) -> 28.893409 | I29: ＝稅率 × MAX(0, 損益 EBITDA − 車隊 D&A − 存量利息)；1H 的稅已含在 CFO 內（v0.1b）
A30: 用途合計（現金口徑） | B30: US$bn | C30: =C13+C16+C21+C22+C25+C26+C27+C28+C29+C23+C24 -> 298.51686 | D30: =D13+D16+D21+D22+D25+D26+D27+D28+D29+D23+D24 -> 319.77671 | E30: =E13+E16+E21+E22+E25+E26+E27+E28+E29+E23+E24 -> 343.9496 | F30: =F13+F16+F21+F22+F25+F26+F27+F28+F29+F23+F24 -> 356.44308 | G30: =G13+G16+G21+G22+G25+G26+G27+G28+G29+G23+G24 -> 481.97043 | I30: 2026 的 1H 部分採季報現金流量表口徑（現金購置、還款、JV、capped call）；1H 的利息與租金已含在 CFO 內，不重複列
A31: 來源（四層）
A32: Ⓐ0 1H26 實際營運現金流（CFO） | B32: US$bn | C32: =輸入與假設!$C$415 -> 71.419 | D32: =0 -> 0 | E32: =0 -> 0 | F32: =0 -> 0 | G32: =0 -> 0 | I32: 季報實際值，取代模型推算；已含 1H 的利息、租金與客戶預付
A33: Ⓐ RPO 現金（2H 起） | B33: US$bn | C33: =運營_產能與收入!C40 -> 0 | D33: =運營_產能與收入!D40 -> 0 | E33: =運營_產能與收入!E40 -> 0 | F33: =運營_產能與收入!F40 -> 0 | G33: =運營_產能與收入!G40 -> 0
A34: Ⓑ 新簽約現金 | B34: US$bn | C34: =運營_產能與收入!C41 -> 11.728981 | D34: =運營_產能與收入!D41 -> 47.085571 | E34: =運營_產能與收入!E41 -> 79.19077 | F34: =運營_產能與收入!F41 -> 111.50243 | G34: =運營_產能與收入!G41 -> 143.89792
A35: Ⓒ 非算力服務現金 | B35: US$bn | C35: =輸入與假設!C$205 -> 0 | D35: =輸入與假設!D$205 -> 0 | E35: =輸入與假設!E$205 -> 0 | F35: =輸入與假設!F$205 -> 0 | G35: =輸入與假設!G$205 -> 0
A36: Ⓒ2 其他事業 EBITDA（2H 起） | B36: US$bn | C36: =輸入與假設!C$46 -> 0 | D36: =輸入與假設!D$46 -> 0 | E36: =輸入與假設!E$46 -> 0 | F36: =輸入與假設!F$46 -> 0 | G36: =輸入與假設!G$46 -> 0 | I36: 非核心事業 EBITDA（負值＝燒錢），視為現金（v0.1b）
A37: Ⓒ3 非 AI 事業 EBITDA（2H 起） | B37: US$bn | C37: =輸入與假設!C$195-輸入與假設!C$196 -> 76.161768 | D37: =輸入與假設!D$195-輸入與假設!D$196 -> 166.58069 | E37: =輸入與假設!E$195-輸入與假設!E$196 -> 187.87471 | F37: =輸入與假設!F$195-輸入與假設!F$196 -> 206.60353 | G37: =輸入與假設!G$195-輸入與假設!G$196 -> 221.17098 | I37: 各線 EBITDA − 其他攤銷（視為等額現金支出），視為現金（現金稅另列於用途；MAG v0.1b）
A38: Ⓒ4 減：延誤罰則（營業費用） | B38: US$bn | C38: =-運營_產能與收入!C62 -> 0 | D38: =-運營_產能與收入!D62 -> 0 | E38: =-運營_產能與收入!E62 -> 0 | F38: =-運營_產能與收入!F62 -> 0 | G38: =-運營_產能與收入!G62 -> 0 | I38: 建設延誤期間應計費而未計費營收 × 罰則比例（預設 0；v0.2）
A39: Ⓒ5 加回：股權報酬（非現金） | B39: US$bn | C39: =輸入與假設!$C$47*(運營_產能與收入!C38+輸入與假設!C$194) -> 11.256691 | D39: =輸入與假設!$C$47*(運營_產能與收入!D38+輸入與假設!D$194) -> 24.24027 | E39: =輸入與假設!$C$47*(運營_產能與收入!E38+輸入與假設!E$194) -> 27.724355 | F39: =輸入與假設!$C$47*(運營_產能與收入!F38+輸入與假設!F$194) -> 30.995647 | G39: =輸入與假設!$C$47*(運營_產能與收入!G38+輸入與假設!G$194) -> 33.921829 | I39: ＝SBC 占營收 × 模型期總營收（分部營業利益已扣 SBC；1H 已含在實際 CFO；MAG v0.1b）
A40: Ⓒ6 首期營運資金變動（上年同期實際） | B40: US$bn | C40: =IF(ISBLANK(輸入與假設!$C$48),0,輸入與假設!$C$48) -> 1.947 | D40: =0 -> 0 | E40: =0 -> 0 | F40: =0 -> 0 | G40: =0 -> 0 | I40: 2026 剩餘季度＝上一年度同期實際（流入為正；10-Q／10-K 現金流量表 [Derived]）；之後年度資金模型不計營運資金（MAG v0.1b r2 C14）
A41: Ⓓ 客戶預付（2H 起） | B41: US$bn | C41: =C8 -> 0 | D41: =D8 -> 0 | E41: =E8 -> 0 | F41: =F8 -> 0 | G41: =G8 -> 0
A42: Ⓓ2 減：預付認列（非現金營收） | B42: US$bn | C42: =-C11 -> 0 | D42: =-D11 -> 0 | E42: =-E11 -> 0 | F42: =-F11 -> 0 | G42: =-G11 -> 0 | I42: 營收中由合約負債轉入的部分已在預付時收現，不重複計入服務現金（v0.1b）
A43: 營運來源合計 | B43: US$bn | C43: =C32+C33+C34+C35+C36+C37+C38+C39+C40+C41+C42 -> 172.51344 | D43: =D32+D33+D34+D35+D36+D37+D38+D39+D40+D41+D42 -> 237.90653 | E43: =E32+E33+E34+E35+E36+E37+E38+E39+E40+E41+E42 -> 294.78983 | F43: =F32+F33+F34+F35+F36+F37+F38+F39+F40+F41+F42 -> 349.1016 | G43: =G32+G33+G34+G35+G36+G37+G38+G39+G40+G41+G42 -> 398.99073
A44: 自由現金流（FCF＝營運現金 − 現金資本支出） | B44: US$bn | C44: =C43-C29-C21-C13 -> -60.114923 | D44: =D43-D29-D21-D13 -> -68.908682 | E44: =E43-E29-E21-E13 -> -32.508101 | F44: =F43-F29-F21-F13 -> 5.7951824 | G44: =G43-G29-G21-G13 -> -72.127035 | I44: 公司定義近似：營運來源（2026 含 1H 實際 CFO）− 現金稅 − 利息 − 現金資本支出（不扣融資租賃本金）；一頁摘要「FCF 首次為負的年份」（MAG v0.1b）
A45: Ⓔ 股權／可轉債（融資） | B45: US$bn | C45: =輸入與假設!$C$422+IF(輸入與假設!$C$283=1,輸入與假設!$C$282,0) -> 0 | D45: =0 -> 0 | E45: =0 -> 0 | F45: =0 -> 0 | G45: =0 -> 0 | I45: 2026＝1H 股權 0＋2H 期後股權 0（不發股、不配息、不回購）
A46: Ⓕ 1H26 實際借款（融資） | B46: US$bn | C46: =輸入與假設!$C$419 -> 66.998 | D46: =0 -> 0 | E46: =0 -> 0 | F46: =0 -> 0 | G46: =0 -> 0 | I46: 季報：H1 借款 66.998（2026-03 可轉債）
A47: Ⓖ 瀑布：新債（額度＋資產層） | B47: US$bn | C47: =C86 -> 0 | D47: =D86 -> 67.179603 | E47: =E86 -> 49.159767 | F47: =F86 -> 7.3414831 | G47: =G86 -> 82.979701 | I47: 見下方「期前融資瀑布」
A48: Ⓖ2 瀑布：可轉債 | B48: US$bn | C48: =C89 -> 0 | D48: =D89 -> 0 | E48: =E89 -> 0 | F48: =F89 -> 0 | G48: =G89 -> 0 | I48: 資產擔保融資用罄後、股權之前；每年不超過可轉債上限（v0.1b）
A49: Ⓗ 瀑布：股權募資 | B49: US$bn | C49: =C92 -> 0 | D49: =D92 -> 0 | E49: =E92 -> 0 | F49: =F92 -> 0 | G49: =G92 -> 0 | I49: 債務與可轉債用罄後的殘差；每年不超過股權吸收上限
A50: Ⓘ 瀑布：高息債（股權上限溢出） | B50: US$bn | C50: =C93 -> 0 | D50: =D93 -> 0 | E50: =E93 -> 0 | F50: =F93 -> 0 | G50: =G93 -> 0 | I50: 股權超過每年上限的部分；不受 backlog 上限約束
A51: 總來源（含融資） | B51: US$bn | C51: =C43+C45+C46+C47+C48+C49+C50 -> 239.51144 | D51: =D43+D45+D46+D47+D48+D49+D50 -> 305.08613 | E51: =E43+E45+E46+E47+E48+E49+E50 -> 343.9496 | F51: =F43+F45+F46+F47+F48+F49+F50 -> 356.44308 | G51: =G43+G45+G46+G47+G48+G49+G50 -> 481.97043
A52: 缺口與現金橋
A53: 1H 其他／受限現金調節 | B53: US$bn | C53: =輸入與假設!$C$281-(輸入與假設!$C$414+輸入與假設!$C$415+輸入與假設!$C$419+輸入與假設!$C$422-輸入與假設!$C$416-輸入與假設!$C$418-輸入與假設!$C$420-輸入與假設!$C$421-輸入與假設!$C$433-輸入與假設!$C$435) -> 0.667 | D53: =0 -> 0 | E53: =0 -> 0 | F53: =0 -> 0 | G53: =0 -> 0 | I53: 使 1H 實際流量接回 6/30 現金餘額；差額來自受限現金重分類與未逐項列出的項目
A54: 營運缺口（不含融資、不含還本） | B54: US$bn | C54: =C43-(C30-C27-C28) -> -122.95542 | D54: =D43-(D30-D27-D28) -> -73.03318 | E54: =E43-(E30-E27-E28) -> -36.865767 | F54: =F43-(F30-F27-F28) -> 1.8285169 | G54: =G43-(G30-G27-G28) -> -75.894701 | I54: 本業能不能自給：營運來源 −（用途 − 排程還本 − capped call）
A55: 期間缺口（含融資） | B55: US$bn | C55: =C51-C30+C53 -> -58.338423 | D55: =D51-D30+D53 -> -14.690577 | E55: =E51-E30+E53 -> 0 | F55: =F51-F30+F53 -> 0 | G55: =G51-G30+G53 -> 0
A56: 期末累積現金 | B56: US$bn | C56: =C18+C55 -> 64.690577 | D56: =D18+D55 -> 50 | E56: =E18+E55 -> 50 | F56: =F18+F55 -> 50 | G56: =G18+G55 -> 50 | I56: 期前融資：每期末不低於最低現金
A58: 租賃負債（期末剩餘租金現值；調整後槓桿用，v0.2）
A59: 租賃折現率（加權平均） | B59: % | C59: 0.039 | I59: 10-K FY2026 營業／融資租賃加權平均折現率（事實總帳 lease.discRate.fy26）[Verified]；company.json → leases.liability.discRate
A60: 在帳租約：模型期後尾端年數 | B60: 年 | C60: 10 | I60: 到期表 2030 後的未折現付款平均分攤年數（10-K 營業租賃加權平均剩餘期限 12 年）[Derived]
A61: 在帳租賃負債（期末） | B61: US$bn | C61: =輸入與假設!D$234*(1+各期收支!$C$59)^(-(運營_產能與收入!$D$51-運營_產能與收入!$D$7/2-運營_產能與收入!$C$51))+輸入與假設!E$234*(1+各期收支!$C$59)^(-(運營_產能與收入!$E$51-運營_產能與收入!$E$7/2-運營_產能與收入!$C$51))+輸入與假設!F$234*(1+各期收支!$C$59)^(-(運營_產能與收入!$F$51-運營_產能與收入!$F$7/2-運營_產能與收入!$C$51))+輸入與假設!G$234*(1+各期收支!$C$59)^(-(運營_產能與收入!$G$51-運營_產能與收入!$G$7/2-運營_產能與收入!$C$51))+71.534/各期收支!$C$60*(1+各期收支!$C$59)^0.5*(1-(1+各期收支!$C$59)^(-各期收支!$C$60))/各期收支!$C$59*(1+各期收支!$C$59)^(-(運營_產能與收入!$G$51-運營_產能與收入!$C$51)) -> 108.5154 | D61: =輸入與假設!E$234*(1+各期收支!$C$59)^(-(運營_產能與收入!$E$51-運營_產能與收入!$E$7/2-運營_產能與收入!$D$51))+輸入與假設!F$234*(1+各期收支!$C$59)^(-(運營_產能與收入!$F$51-運營_產能與收入!$F$7/2-運營_產能與收入!$D$51))+輸入與假設!G$234*(1+各期收支!$C$59)^(-(運營_產能與收入!$G$51-運營_產能與收入!$G$7/2-運營_產能與收入!$D$51))+71.534/各期收支!$C$60*(1+各期收支!$C$59)^0.5*(1-(1+各期收支!$C$59)^(-各期收支!$C$60))/各期收支!$C$59*(1+各期收支!$C$59)^(-(運營_產能與收入!$G$51-運營_產能與收入!$D$51)) -> 95.192884 | E61: =輸入與假設!F$234*(1+各期收支!$C$59)^(-(運營_產能與收入!$F$51-運營_產能與收入!$F$7/2-運營_產能與收入!$E$51))+輸入與假設!G$234*(1+各期收支!$C$59)^(-(運營_產能與收入!$G$51-運營_產能與收入!$G$7/2-運營_產能與收入!$E$51))+71.534/各期收支!$C$60*(1+各期收支!$C$59)^0.5*(1-(1+各期收支!$C$59)^(-各期收支!$C$60))/各期收支!$C$59*(1+各期收支!$C$59)^(-(運營_產能與收入!$G$51-運營_產能與收入!$E$51)) -> 82.083676 | F61: =輸入與假設!G$234*(1+各期收支!$C$59)^(-(運營_產能與收入!$G$51-運營_產能與收入!$G$7/2-運營_產能與收入!$F$51))+71.534/各期收支!$C$60*(1+各期收支!$C$59)^0.5*(1-(1+各期收支!$C$59)^(-各期收支!$C$60))/各期收支!$C$59*(1+各期收支!$C$59)^(-(運營_產能與收入!$G$51-運營_產能與收入!$F$51)) -> 70.212351 | G61: =71.534/各期收支!$C$60*(1+各期收支!$C$59)^0.5*(1-(1+各期收支!$C$59)^(-各期收支!$C$60))/各期收支!$C$59*(1+各期收支!$C$59)^(-(運營_產能與收入!$G$51-運營_產能與收入!$G$51)) -> 59.436574 | I61: ＝期末之後各期到期表現金（期中付款）＋模型期後尾端 71.534（平均分攤、年中付款）的現值
A62: 未起租租約已起租部分的租賃負債（期末） | B62: US$bn | C62: =IF(OR(運營_產能與收入!$C$50<=0,運營_產能與收入!$C$56<=0),1*輸入與假設!$C$19/輸入與假設!$C$21/輸入與假設!$C$22/4/((1+各期收支!$C$59)^0.25-1)*(MIN(MAX(0,輸入與假設!C$235-(輸入與假設!$C$20)),輸入與假設!$C$21)-(1+各期收支!$C$59)^(-(4*輸入與假設!$C$22-MAX(0,輸入與假設!C$235-(輸入與假設!$C$20)))/4)*(1-(1+各期收支!$C$59)^(-MIN(MAX(0,輸入與假設!C$235-(輸入與假設!$C$20)),輸入與假設!$C$21)/4))/(1-(1+各期收支!$C$59)^(-0.25))),(1-運營_產能與收入!$C$56)*輸入與假設!$C$19/輸入與假設!$C$21/輸入與假設!$C$22/4/((1+各期收支!$C$59)^0.25-1)*(MIN(MAX(0,輸入與假設!C$235-(輸入與假設!$C$20)),輸入與假設!$C$21)-(1+各期收支!$C$59)^(-(4*輸入與假設!$C$22-MAX(0,輸入與假設!C$235-(輸入與假設!$C$20)))/4)*(1-(1+各期收支!$C$59)^(-MIN(MAX(0,輸入與假設!C$235-(輸入與假設!$C$20)),輸入與假設!$C$21)/4))/(1-(1+各期收支!$C$59)^(-0.25)))+運營_產能與收入!$C$56*輸入與假設!$C$19/輸入與假設!$C$21/輸入與假設!$C$22/4/((1+各期收支!$C$59)^0.25-1)*(MIN(MAX(0,輸入與假設!C$235-(輸入與假設!$C$20+運營_產能與收入!$C$50/3)),輸入與假設!$C$21)-(1+各期收支!$C$59)^(-(4*輸入與假設!$C$22-MAX(0,輸入與假設!C$235-(輸入與假設!$C$20+運營_產能與收入!$C$50/3)))/4)*(1-(1+各期收支!$C$59)^(-MIN(MAX(0,輸入與假設!C$235-(輸入與假設!$C$20+運營_產能與收入!$C$50/3)),輸入與假設!$C$21)/4))/(1-(1+各期收支!$C$59)^(-0.25)))) -> 51.183999 | D62: =IF(OR(運營_產能與收入!$C$50<=0,運營_產能與收入!$C$56<=0),1*輸入與假設!$C$19/輸入與假設!$C$21/輸入與假設!$C$22/4/((1+各期收支!$C$59)^0.25-1)*(MIN(MAX(0,輸入與假設!D$235-(輸入與假設!$C$20)),輸入與假設!$C$21)-(1+各期收支!$C$59)^(-(4*輸入與假設!$C$22-MAX(0,輸入與假設!D$235-(輸入與假設!$C$20)))/4)*(1-(1+各期收支!$C$59)^(-MIN(MAX(0,輸入與假設!D$235-(輸入與假設!$C$20)),輸入與假設!$C$21)/4))/(1-(1+各期收支!$C$59)^(-0.25))),(1-運營_產能與收入!$C$56)*輸入與假設!$C$19/輸入與假設!$C$21/輸入與假設!$C$22/4/((1+各期收支!$C$59)^0.25-1)*(MIN(MAX(0,輸入與假設!D$235-(輸入與假設!$C$20)),輸入與假設!$C$21)-(1+各期收支!$C$59)^(-(4*輸入與假設!$C$22-MAX(0,輸入與假設!D$235-(輸入與假設!$C$20)))/4)*(1-(1+各期收支!$C$59)^(-MIN(MAX(0,輸入與假設!D$235-(輸入與假設!$C$20)),輸入與假設!$C$21)/4))/(1-(1+各期收支!$C$59)^(-0.25)))+運營_產能與收入!$C$56*輸入與假設!$C$19/輸入與假設!$C$21/輸入與假設!$C$22/4/((1+各期收支!$C$59)^0.25-1)*(MIN(MAX(0,輸入與假設!D$235-(輸入與假設!$C$20+運營_產能與收入!$C$50/3)),輸入與假設!$C$21)-(1+各期收支!$C$59)^(-(4*輸入與假設!$C$22-MAX(0,輸入與假設!D$235-(輸入與假設!$C$20+運營_產能與收入!$C$50/3)))/4)*(1-(1+各期收支!$C$59)^(-MIN(MAX(0,輸入與假設!D$235-(輸入與假設!$C$20+運營_產能與收入!$C$50/3)),輸入與假設!$C$21)/4))/(1-(1+各期收支!$C$59)^(-0.25)))) -> 98.297074 | E62: =IF(OR(運營_產能與收入!$C$50<=0,運營_產能與收入!$C$56<=0),1*輸入與假設!$C$19/輸入與假設!$C$21/輸入與假設!$C$22/4/((1+各期收支!$C$59)^0.25-1)*(MIN(MAX(0,輸入與假設!E$235-(輸入與假設!$C$20)),輸入與假設!$C$21)-(1+各期收支!$C$59)^(-(4*輸入與假設!$C$22-MAX(0,輸入與假設!E$235-(輸入與假設!$C$20)))/4)*(1-(1+各期收支!$C$59)^(-MIN(MAX(0,輸入與假設!E$235-(輸入與假設!$C$20)),輸入與假設!$C$21)/4))/(1-(1+各期收支!$C$59)^(-0.25))),(1-運營_產能與收入!$C$56)*輸入與假設!$C$19/輸入與假設!$C$21/輸入與假設!$C$22/4/((1+各期收支!$C$59)^0.25-1)*(MIN(MAX(0,輸入與假設!E$235-(輸入與假設!$C$20)),輸入與假設!$C$21)-(1+各期收支!$C$59)^(-(4*輸入與假設!$C$22-MAX(0,輸入與假設!E$235-(輸入與假設!$C$20)))/4)*(1-(1+各期收支!$C$59)^(-MIN(MAX(0,輸入與假設!E$235-(輸入與假設!$C$20)),輸入與假設!$C$21)/4))/(1-(1+各期收支!$C$59)^(-0.25)))+運營_產能與收入!$C$56*輸入與假設!$C$19/輸入與假設!$C$21/輸入與假設!$C$22/4/((1+各期收支!$C$59)^0.25-1)*(MIN(MAX(0,輸入與假設!E$235-(輸入與假設!$C$20+運營_產能與收入!$C$50/3)),輸入與假設!$C$21)-(1+各期收支!$C$59)^(-(4*輸入與假設!$C$22-MAX(0,輸入與假設!E$235-(輸入與假設!$C$20+運營_產能與收入!$C$50/3)))/4)*(1-(1+各期收支!$C$59)^(-MIN(MAX(0,輸入與假設!E$235-(輸入與假設!$C$20+運營_產能與收入!$C$50/3)),輸入與假設!$C$21)/4))/(1-(1+各期收支!$C$59)^(-0.25)))) -> 92.693049 | F62: =IF(OR(運營_產能與收入!$C$50<=0,運營_產能與收入!$C$56<=0),1*輸入與假設!$C$19/輸入與假設!$C$21/輸入與假設!$C$22/4/((1+各期收支!$C$59)^0.25-1)*(MIN(MAX(0,輸入與假設!F$235-(輸入與假設!$C$20)),輸入與假設!$C$21)-(1+各期收支!$C$59)^(-(4*輸入與假設!$C$22-MAX(0,輸入與假設!F$235-(輸入與假設!$C$20)))/4)*(1-(1+各期收支!$C$59)^(-MIN(MAX(0,輸入與假設!F$235-(輸入與假設!$C$20)),輸入與假設!$C$21)/4))/(1-(1+各期收支!$C$59)^(-0.25))),(1-運營_產能與收入!$C$56)*輸入與假設!$C$19/輸入與假設!$C$21/輸入與假設!$C$22/4/((1+各期收支!$C$59)^0.25-1)*(MIN(MAX(0,輸入與假設!F$235-(輸入與假設!$C$20)),輸入與假設!$C$21)-(1+各期收支!$C$59)^(-(4*輸入與假設!$C$22-MAX(0,輸入與假設!F$235-(輸入與假設!$C$20)))/4)*(1-(1+各期收支!$C$59)^(-MIN(MAX(0,輸入與假設!F$235-(輸入與假設!$C$20)),輸入與假設!$C$21)/4))/(1-(1+各期收支!$C$59)^(-0.25)))+運營_產能與收入!$C$56*輸入與假設!$C$19/輸入與假設!$C$21/輸入與假設!$C$22/4/((1+各期收支!$C$59)^0.25-1)*(MIN(MAX(0,輸入與假設!F$235-(輸入與假設!$C$20+運營_產能與收入!$C$50/3)),輸入與假設!$C$21)-(1+各期收支!$C$59)^(-(4*輸入與假設!$C$22-MAX(0,輸入與假設!F$235-(輸入與假設!$C$20+運營_產能與收入!$C$50/3)))/4)*(1-(1+各期收支!$C$59)^(-MIN(MAX(0,輸入與假設!F$235-(輸入與假設!$C$20+運營_產能與收入!$C$50/3)),輸入與假設!$C$21)/4))/(1-(1+各期收支!$C$59)^(-0.25)))) -> 86.870467 | G62: =IF(OR(運營_產能與收入!$C$50<=0,運營_產能與收入!$C$56<=0),1*輸入與假設!$C$19/輸入與假設!$C$21/輸入與假設!$C$22/4/((1+各期收支!$C$59)^0.25-1)*(MIN(MAX(0,輸入與假設!G$235-(輸入與假設!$C$20)),輸入與假設!$C$21)-(1+各期收支!$C$59)^(-(4*輸入與假設!$C$22-MAX(0,輸入與假設!G$235-(輸入與假設!$C$20)))/4)*(1-(1+各期收支!$C$59)^(-MIN(MAX(0,輸入與假設!G$235-(輸入與假設!$C$20)),輸入與假設!$C$21)/4))/(1-(1+各期收支!$C$59)^(-0.25))),(1-運營_產能與收入!$C$56)*輸入與假設!$C$19/輸入與假設!$C$21/輸入與假設!$C$22/4/((1+各期收支!$C$59)^0.25-1)*(MIN(MAX(0,輸入與假設!G$235-(輸入與假設!$C$20)),輸入與假設!$C$21)-(1+各期收支!$C$59)^(-(4*輸入與假設!$C$22-MAX(0,輸入與假設!G$235-(輸入與假設!$C$20)))/4)*(1-(1+各期收支!$C$59)^(-MIN(MAX(0,輸入與假設!G$235-(輸入與假設!$C$20)),輸入與假設!$C$21)/4))/(1-(1+各期收支!$C$59)^(-0.25)))+運營_產能與收入!$C$56*輸入與假設!$C$19/輸入與假設!$C$21/輸入與假設!$C$22/4/((1+各期收支!$C$59)^0.25-1)*(MIN(MAX(0,輸入與假設!G$235-(輸入與假設!$C$20+運營_產能與收入!$C$50/3)),輸入與假設!$C$21)-(1+各期收支!$C$59)^(-(4*輸入與假設!$C$22-MAX(0,輸入與假設!G$235-(輸入與假設!$C$20+運營_產能與收入!$C$50/3)))/4)*(1-(1+各期收支!$C$59)^(-MIN(MAX(0,輸入與假設!G$235-(輸入與假設!$C$20+運營_產能與收入!$C$50/3)),輸入與假設!$C$21)/4))/(1-(1+各期收支!$C$59)^(-0.25)))) -> 80.820804 | I62: 每季起租 總額 ÷ 季數、每筆季末付租：已起租各筆剩餘租金現值合計（延誤連動部分起算季延後 延誤月數 ÷ 3）
A63: 租賃負債合計（期末） | B63: US$bn | C63: =C61+C62 -> 159.6994 | D63: =D61+D62 -> 193.48996 | E63: =E61+E62 -> 174.77673 | F63: =F61+F62 -> 157.08282 | G63: =G61+G62 -> 140.25738
A65: 期前融資瀑布（缺口在需要前一期先融好：額度 → 資產層新債 → 股權）
A66: 用途（不含新債利息） | B66: US$bn | C66: =C13+C16+C17+C22+C25+C26+C27+C28+C29+C23 -> 298.51686 | D66: =D13+D16+D17+D22+D25+D26+D27+D28+D29+D23 -> 316.41773 | E66: =E13+E16+E17+E22+E25+E26+E27+E28+E29+E23 -> 338.13263 | F66: =F13+F16+F17+F22+F25+F26+F27+F28+F29+F23 -> 350.25904 | G66: =G13+G16+G17+G22+G25+G26+G27+G28+G29+G23 -> 471.6374 | I66: 避免循環參照：直接由各支出列加總
A67: 新債期初餘額 | B67: US$bn | C67: =0 -> 0 | D67: =C98 -> 0 | E67: =D98 -> 67.179603 | F67: =E98 -> 116.33937 | G67: =F98 -> 123.68085
A68: 新債利率 × 期間長度 | B68: % | C68: =C19*運營_產能與收入!C7 -> 0.025 | D68: =D19*運營_產能與收入!D7 -> 0.05 | E68: =E19*運營_產能與收入!E7 -> 0.05 | F68: =F19*運營_產能與收入!F7 -> 0.05 | G68: =G19*運營_產能與收入!G7 -> 0.05
A69: 高息債期初餘額 | B69: US$bn | C69: =0 -> 0 | D69: =C100 -> 0 | E69: =D100 -> 0 | F69: =E100 -> 0 | G69: =F100 -> 0
A70: 可轉債（瀑布）期初餘額 | B70: US$bn | C70: =0 -> 0 | D70: =C101 -> 0 | E70: =D101 -> 0 | F70: =E101 -> 0 | G70: =F101 -> 0
A71: 可轉債票息 × 期間長度 | B71: % | C71: =輸入與假設!$C$305*運營_產能與收入!C7 -> 0 | D71: =輸入與假設!$C$305*運營_產能與收入!D7 -> 0 | E71: =輸入與假設!$C$305*運營_產能與收入!E7 -> 0 | F71: =輸入與假設!$C$305*運營_產能與收入!F7 -> 0 | G71: =輸入與假設!$C$305*運營_產能與收入!G7 -> 0
A72: 高息債利率 × 期間長度 | B72: % | C72: =(輸入與假設!$C$307+IF(輸入與假設!$C$310=1,MAX(0,輸入與假設!$C$309-輸入與假設!$C$311)/10000*輸入與假設!$C$312,0))*運營_產能與收入!C7 -> 0.06 | D72: =(輸入與假設!$C$307+IF(輸入與假設!$C$310=1,MAX(0,輸入與假設!$C$309-輸入與假設!$C$311)/10000*輸入與假設!$C$312,0))*運營_產能與收入!D7 -> 0.12 | E72: =(輸入與假設!$C$307+IF(輸入與假設!$C$310=1,MAX(0,輸入與假設!$C$309-輸入與假設!$C$311)/10000*輸入與假設!$C$312,0))*運營_產能與收入!E7 -> 0.12 | F72: =(輸入與假設!$C$307+IF(輸入與假設!$C$310=1,MAX(0,輸入與假設!$C$309-輸入與假設!$C$311)/10000*輸入與假設!$C$312,0))*運營_產能與收入!F7 -> 0.12 | G72: =(輸入與假設!$C$307+IF(輸入與假設!$C$310=1,MAX(0,輸入與假設!$C$309-輸入與假設!$C$311)/10000*輸入與假設!$C$312,0))*運營_產能與收入!G7 -> 0.12
A73: 融資前現金（扣既有新債利息） | B73: US$bn | C73: =C18+C43+C45+C46+C53-C66-C68*C67-C72*C69-C71*C70 -> 64.690577 | D73: =D18+D43+D45+D46+D53-D66-D68*D67-D72*D69-D71*D70 -> -13.820623 | E73: =E18+E43+E45+E46+E53-E66-E68*E67-E72*E69-E71*E70 -> 3.2982214 | F73: =F18+F43+F45+F46+F53-F66-F68*F67-F72*F69-F71*F70 -> 43.025591 | G73: =G18+G43+G45+G46+G53-G66-G68*G67-G72*G69-G71*G70 -> -28.830716
A74: 融資需求（補足至最低現金） | B74: US$bn | C74: =MAX(0,輸入與假設!$C$294-(C73-C76)) -> 0 | D74: =MAX(0,輸入與假設!$C$294-(D73-D76)) -> 63.820623 | E74: =MAX(0,輸入與假設!$C$294-(E73-E76)) -> 46.701779 | F74: =MAX(0,輸入與假設!$C$294-(F73-F76)) -> 6.974409 | G74: =MAX(0,輸入與假設!$C$294-(G73-G76)) -> 78.830716 | I74: ＝MAX(0, 最低現金 −(融資前現金 − 實際回購))
A75: 回購計畫（基準年額 × 期間長度） | B75: US$bn | C75: =輸入與假設!$C$295*運營_產能與收入!C7 -> 0 | D75: =輸入與假設!$C$295*運營_產能與收入!D7 -> 0 | E75: =輸入與假設!$C$295*運營_產能與收入!E7 -> 0 | F75: =輸入與假設!$C$295*運營_產能與收入!F7 -> 0 | G75: =輸入與假設!$C$295*運營_產能與收入!G7 -> 0 | I75: MAG v0.1b：瀑布第二步（現金之後、新債之前）
A76: 回購（實際，減少後） | B76: US$bn | C76: =MIN(C75,MAX(C75*輸入與假設!$C$296,C73-輸入與假設!$C$294)) -> 0 | D76: =MIN(D75,MAX(D75*輸入與假設!$C$296,D73-輸入與假設!$C$294)) -> 0 | E76: =MIN(E75,MAX(E75*輸入與假設!$C$296,E73-輸入與假設!$C$294)) -> 0 | F76: =MIN(F75,MAX(F75*輸入與假設!$C$296,F73-輸入與假設!$C$294)) -> 0 | G76: =MIN(G75,MAX(G75*輸入與假設!$C$296,G73-輸入與假設!$C$294)) -> 0 | I76: ＝MIN(計畫, MAX(下限, 融資前現金 − 最低現金))
A77: 回購被迫減少 | B77: US$bn | C77: =C75-C76 -> 0 | D77: =D75-D76 -> 0 | E77: =E75-E76 -> 0 | F77: =F75-F76 -> 0 | G77: =G75-G76 -> 0 | I77: ＝計畫 − 實際（一頁摘要「回購被迫減少的年份與金額」）
A78: 回購股數 | B78: bn | C78: =C76/MAX(0.01,輸入與假設!$C$297) -> 0 | D78: =D76/MAX(0.01,輸入與假設!$C$297) -> 0 | E78: =E76/MAX(0.01,輸入與假設!$C$297) -> 0 | F78: =F76/MAX(0.01,輸入與假設!$C$297) -> 0 | G78: =G76/MAX(0.01,輸入與假設!$C$297) -> 0 | I78: ＝實際回購 ÷ 發行參考價（現價）
A79: 期初 backlog | B79: US$bn | C79: =輸入與假設!$C$24+輸入與假設!$C$25 -> 0 | D79: =C81 -> 73.074775 | E79: =D81 -> 102.04741 | F79: =E81 -> 122.63847 | G79: =F81 -> 104.22042 | I79: 2026 期初＝6/30 RPO 0.0＋期後新增 0.0
A80: 新簽合約增量（年化增量×年期） | B80: US$bn | C80: =MAX(0,運營_產能與收入!C24/運營_產能與收入!C7-0)*輸入與假設!$C$290 -> 87.68973 | D80: =MAX(0,運營_產能與收入!D24/運營_產能與收入!D7-運營_產能與收入!C24/運營_產能與收入!C7)*輸入與假設!$C$290 -> 87.30381 | E80: =MAX(0,運營_產能與收入!E24/運營_產能與收入!E7-運營_產能與收入!D24/運營_產能與收入!D7)*輸入與假設!$C$290 -> 118.38337 | F80: =MAX(0,運營_產能與收入!F24/運營_產能與收入!F7-運營_產能與收入!E24/運營_產能與收入!E7)*輸入與假設!$C$290 -> 119.06138 | G80: =MAX(0,運營_產能與收入!G24/運營_產能與收入!G7-運營_產能與收入!F24/運營_產能與收入!F7)*輸入與假設!$C$290 -> 119.3365
A81: 期末 backlog | B81: US$bn | C81: =C79-運營_產能與收入!C18-運營_產能與收入!C24+C80 -> 73.074775 | D81: =D79-運營_產能與收入!D18-運營_產能與收入!D24+D80 -> 102.04741 | E81: =E79-運營_產能與收入!E18-運營_產能與收入!E24+E80 -> 122.63847 | F81: =F79-運營_產能與收入!F18-運營_產能與收入!F24+F80 -> 104.22042 | G81: =G79-運營_產能與收入!G18-運營_產能與收入!G24+G80 -> 46.298654 | I81: ＝期初 − 排程認列 − 新簽約認列 ＋ 新簽合約增量
A82: 既有債務＋期後可轉債（期末） | B82: US$bn | C82: =IF(輸入與假設!$C$286=1,資產負債_既有債務!C35,資產負債_既有債務!$E$17)+資產負債_既有債務!$E$20+資產負債_既有債務!C40 -> 132.995 | D82: =IF(輸入與假設!$C$286=1,資產負債_既有債務!D35,資產負債_既有債務!$E$17)+資產負債_既有債務!$E$20+資產負債_既有債務!D40 -> 124.158 | E82: =IF(輸入與假設!$C$286=1,資產負債_既有債務!E35,資產負債_既有債務!$E$17)+資產負債_既有債務!$E$20+資產負債_既有債務!E40 -> 111.864 | F82: =IF(輸入與假設!$C$286=1,資產負債_既有債務!F35,資產負債_既有債務!$E$17)+資產負債_既有債務!$E$20+資產負債_既有債務!F40 -> 102.694 | G82: =IF(輸入與假設!$C$286=1,資產負債_既有債務!G35,資產負債_既有債務!$E$17)+資產負債_既有債務!$E$20+資產負債_既有債務!G40 -> 95.609 | I82: ＝(依到期表遞減的既有本金，若關閉攤還則維持 132.995)＋期後新發可轉債 0
A83: 債務上限（投資級：倍數 × 當期 EBITDA；或債務／backlog） | B83: US$bn | C83: =IF(輸入與假設!$C$288="leaseAdj",輸入與假設!$C$289*(損益!C22+C16)/運營_產能與收入!C7-C63,IF(輸入與假設!$C$288="ebitda",輸入與假設!$C$289*損益!C22/運營_產能與收入!C7,輸入與假設!$C$287*C81)) -> 459.32851 | D83: =IF(輸入與假設!$C$288="leaseAdj",輸入與假設!$C$289*(損益!D22+D16)/運營_產能與收入!D7-D63,IF(輸入與假設!$C$288="ebitda",輸入與假設!$C$289*損益!D22/運營_產能與收入!D7,輸入與假設!$C$287*D81)) -> 548.60716 | E83: =IF(輸入與假設!$C$288="leaseAdj",輸入與假設!$C$289*(損益!E22+E16)/運營_產能與收入!E7-E63,IF(輸入與假設!$C$288="ebitda",輸入與假設!$C$289*損益!E22/運營_產能與收入!E7,輸入與假設!$C$287*E81)) -> 739.26718 | F83: =IF(輸入與假設!$C$288="leaseAdj",輸入與假設!$C$289*(損益!F22+F16)/運營_產能與收入!F7-F63,IF(輸入與假設!$C$288="ebitda",輸入與假設!$C$289*損益!F22/運營_產能與收入!F7,輸入與假設!$C$287*F81)) -> 918.87391 | G83: =IF(輸入與假設!$C$288="leaseAdj",輸入與假設!$C$289*(損益!G22+G16)/運營_產能與收入!G7-G63,IF(輸入與假設!$C$288="ebitda",輸入與假設!$C$289*損益!G22/運營_產能與收入!G7,輸入與假設!$C$287*G81)) -> 1084.1841 | I83: leaseAdj：總債務 ≤ 倍數 ×(損益 EBITDA＋租金)（年化）− 租賃負債（v0.2）；ebitda：總債務 ≤ 倍數 × 損益 EBITDA（年化）；backlog：總債務 ≤ 倍數 × 期末 backlog（模板）
A84: 未動用額度（期初） | B84: US$bn | C84: =IF(輸入與假設!$C$285=1,輸入與假設!$C$284,0) -> 0 | D84: =C99 -> 0 | E84: =D99 -> 0 | F84: =E99 -> 0 | G84: =F99 -> 0
A85: 新債可借上限 | B85: US$bn | C85: =MAX(0,C83-(C82+C67+C70),C84) -> 326.33351 | D85: =MAX(0,D83-(D82+D67+D70),D84) -> 424.44916 | E85: =MAX(0,E83-(E82+E67+E70),E84) -> 560.22357 | F85: =MAX(0,F83-(F82+F67+F70),F84) -> 699.84054 | G85: =MAX(0,G83-(G82+G67+G70),G84) -> 864.89426 | I85: ＝MAX(上限 − 既有債務 − 期初新債 − 期初瀑布可轉債, 未動用額度)
A86: 新債舉借 | B86: US$bn | C86: =MIN(C85,C74/(1-C68)) -> 0 | D86: =MIN(D85,D74/(1-D68)) -> 67.179603 | E86: =MIN(E85,E74/(1-E68)) -> 49.159767 | F86: =MIN(F85,F74/(1-F68)) -> 7.3414831 | G86: =MIN(G85,G74/(1-G68)) -> 82.979701 | I86: 期前融資：期初到位，當期全額計息，所以需求要除以 (1−利率×期間)
A87: 債務後剩餘需求 | B87: US$bn | C87: =MAX(0,C74+C68*C86-C86) -> 0 | D87: =MAX(0,D74+D68*D86-D86) -> 0 | E87: =MAX(0,E74+E68*E86-E86) -> 0 | F87: =MAX(0,F74+F68*F86-F86) -> 0 | G87: =MAX(0,G74+G68*G86-G86) -> 0
A88: 可轉債可發行上限 | B88: US$bn | C88: =MAX(0,輸入與假設!$C$304)*運營_產能與收入!C7 -> 0 | D88: =MAX(0,輸入與假設!$C$304)*運營_產能與收入!D7 -> 0 | E88: =MAX(0,輸入與假設!$C$304)*運營_產能與收入!E7 -> 0 | F88: =MAX(0,輸入與假設!$C$304)*運營_產能與收入!F7 -> 0 | G88: =MAX(0,輸入與假設!$C$304)*運營_產能與收入!G7 -> 0 | I88: ＝每年上限（隨情境）× 期間長度
A89: 可轉債發行 | B89: US$bn | C89: =MIN(C88,C87/(1-C71)) -> 0 | D89: =MIN(D88,D87/(1-D71)) -> 0 | E89: =MIN(E88,E87/(1-E71)) -> 0 | F89: =MIN(F88,F87/(1-F71)) -> 0 | G89: =MIN(G88,G87/(1-G71)) -> 0 | I89: 期前融資：期初到位、當期全額計息
A90: 可轉債後剩餘需求 | B90: US$bn | C90: =MAX(0,C87+C71*C89-C89) -> 0 | D90: =MAX(0,D87+D71*D89-D89) -> 0 | E90: =MAX(0,E87+E71*E89-E89) -> 0 | F90: =MAX(0,F87+F71*F89-F89) -> 0 | G90: =MAX(0,G87+G71*G89-G89) -> 0
A91: 每年股權吸收上限 | B91: US$bn | C91: =IF(輸入與假設!$C$299>=9,1E+099,輸入與假設!$C$299*輸入與假設!$C$297*輸入與假設!$C$300*運營_產能與收入!C7) -> 70.089468 | D91: =IF(輸入與假設!$C$299>=9,1E+099,輸入與假設!$C$299*輸入與假設!$C$297*輸入與假設!$C$300*運營_產能與收入!D7) -> 140.17894 | E91: =IF(輸入與假設!$C$299>=9,1E+099,輸入與假設!$C$299*輸入與假設!$C$297*輸入與假設!$C$300*運營_產能與收入!E7) -> 140.17894 | F91: =IF(輸入與假設!$C$299>=9,1E+099,輸入與假設!$C$299*輸入與假設!$C$297*輸入與假設!$C$300*運營_產能與收入!F7) -> 140.17894 | G91: =IF(輸入與假設!$C$299>=9,1E+099,輸入與假設!$C$299*輸入與假設!$C$297*輸入與假設!$C$300*運營_產能與收入!G7) -> 140.17894 | I91: ＝現市值（發行參考價 × 10.7863bn 股）× 上限 % × 期間長度
A92: 股權募資 | B92: US$bn | C92: =MIN(C90,C91) -> 0 | D92: =MIN(D90,D91) -> 0 | E92: =MIN(E90,E91) -> 0 | F92: =MIN(F90,F91) -> 0 | G92: =MIN(G90,G91) -> 0
A93: 高息債舉借（溢出） | B93: US$bn | C93: =(C90-C92)/(1-C72) -> 0 | D93: =(D90-D92)/(1-D72) -> 0 | E93: =(E90-E92)/(1-E72) -> 0 | F93: =(F90-F92)/(1-F72) -> 0 | G93: =(G90-G92)/(1-G72) -> 0
A94: 新債＋高息債利息（期初餘額＋本期舉借） | B94: US$bn | C94: =C68*(C67+C86)+C72*(C69+C93)+C71*(C70+C89) -> 0 | D94: =D68*(D67+D86)+D72*(D69+D93)+D71*(D70+D89) -> 3.3589802 | E94: =E68*(E67+E86)+E72*(E69+E93)+E71*(E70+E89) -> 5.8169685 | F94: =F68*(F67+F86)+F72*(F69+F93)+F71*(F70+F89) -> 6.1840427 | G94: =G68*(G67+G86)+G72*(G69+G93)+G71*(G70+G89) -> 10.333028 | I94: 含瀑布可轉債票息（v0.1b）
A95: 發行價（現價×(1−折價)） | B95: US$ | C95: =輸入與假設!$C$297*(1-輸入與假設!$C$298) -> 233.928 | D95: =輸入與假設!$C$297*(1-輸入與假設!$C$298) -> 233.928 | E95: =輸入與假設!$C$297*(1-輸入與假設!$C$298) -> 233.928 | F95: =輸入與假設!$C$297*(1-輸入與假設!$C$298) -> 233.928 | G95: =輸入與假設!$C$297*(1-輸入與假設!$C$298) -> 233.928
A96: 新發行股數 | B96: bn | C96: =C92/C95 -> 0 | D96: =D92/D95 -> 0 | E96: =E92/E95 -> 0 | F96: =F92/F95 -> 0 | G96: =G92/G95 -> 0
A97: 累計新股 | B97: bn | C97: =C96-C78 -> 0 | D97: =C97+D96-D78 -> 0 | E97: =D97+E96-E78 -> 0 | F97: =E97+F96-F78 -> 0 | G97: =F97+G96-G78 -> 0
A98: 新債期末餘額 | B98: US$bn | C98: =C67+C86 -> 0 | D98: =D67+D86 -> 67.179603 | E98: =E67+E86 -> 116.33937 | F98: =F67+F86 -> 123.68085 | G98: =G67+G86 -> 206.66055
A99: 未動用額度（期末） | B99: US$bn | C99: =C84-MIN(C84,C86) -> 0 | D99: =D84-MIN(D84,D86) -> 0 | E99: =E84-MIN(E84,E86) -> 0 | F99: =F84-MIN(F84,F86) -> 0 | G99: =G84-MIN(G84,G86) -> 0
A100: 高息債期末餘額 | B100: US$bn | C100: =C69+C93 -> 0 | D100: =D69+D93 -> 0 | E100: =E69+E93 -> 0 | F100: =F69+F93 -> 0 | G100: =G69+G93 -> 0
A101: 可轉債（瀑布）期末餘額 | B101: US$bn | C101: =C70+C89 -> 0 | D101: =D70+D89 -> 0 | E101: =E70+E89 -> 0 | F101: =F70+F89 -> 0 | G101: =G70+G89 -> 0
A102: 期末總債務（既有＋可轉債＋新債＋高息債） | B102: US$bn | C102: =C82+C98+C101+C100 -> 132.995 | D102: =D82+D98+D101+D100 -> 191.3376 | E102: =E82+E98+E101+E100 -> 228.20337 | F102: =F82+F98+F101+F100 -> 226.37485 | G102: =G82+G98+G101+G100 -> 302.26955
A103: 融資前累積現金 | B103: US$bn | C103: =C18+C43+C45+C46+C53-C66 -> 64.690577 | D103: =C103+D43+D45-D66 -> -13.820623 | E103: =D103+E43+E45-E66 -> -57.163422 | F103: =E103+F43+F45-F66 -> -58.320862 | G103: =F103+G43+G45-G66 -> -130.96754 | I103: 若不做任何新融資的累積現金；負值＝外部資金需求
...

Sheet 季度追蹤
A1: 季度追蹤 — 焦點季的模型／共識／指引／實際與差距（由年度模型拆分；只用於追蹤，不影響年度數字與目標價）
A2: 設定與實際數在『輸入與假設』J 區，共識在 I 區；缺資料顯示「不適用」，實際數空白＝待公布。差距超過門檻的項目附差異原因（拆法＝所屬期間合計差距在門檻內）。第 2 區為 6 季路徑與拆分明細（預設收合）。
A4: 1｜焦點季（『輸入與假設』J 區選擇）：模型／共識／指引／實際與差距
A5: 指標 | B5: 單位 | C5: 模型 | D5: 共識 | E5: 模型 vs 共識 | F5: 指引（低） | G5: 指引（高） | H5: 模型 vs 指引中點 | I5: 實際 | J5: 實際 vs 模型 | K5: 實際 vs 共識 | L5: 實際 vs 指引中點 | M5: 利潤率 pt：模型 vs 共識 | N5: 模型 vs 指引 | O5: 實際 vs 模型 | P5: 實際 vs 共識 | Q5: 實際 vs 指引
A6: 焦點｜營收 | B6: US$bn | C6: =INDEX($C$22:$H$22,輸入與假設!$C$499) -> 217.5667 | D6: =INDEX($C$37:$H$37,輸入與假設!$C$499) -> 不適用 | E6: =INDEX($C$47:$H$47,輸入與假設!$C$499) -> 不適用 | F6: =IF(ISNUMBER(INDEX($C$32:$H$32,輸入與假設!$C$499)),INDEX($C$32:$H$32,輸入與假設!$C$499),"不適用") -> 197 | G6: =INDEX($C$33:$H$33,輸入與假設!$C$499) -> 202 | H6: =INDEX($C$48:$H$48,輸入與假設!$C$499) -> 0.090559881 | I6: =IF(ISNUMBER(INDEX($C$41:$H$41,輸入與假設!$C$499)),INDEX($C$41:$H$41,輸入與假設!$C$499),"待公布") -> 待公布 | J6: =INDEX($C$49:$H$49,輸入與假設!$C$499) | K6: =INDEX($C$50:$H$50,輸入與假設!$C$499) | L6: =INDEX($C$51:$H$51,輸入與假設!$C$499)
A7: 焦點｜調整後 EBITDA | B7: US$bn | C7: =INDEX($C$28:$H$28,輸入與假設!$C$499) -> 47.889463 | D7: =INDEX($C$38:$H$38,輸入與假設!$C$499) -> 不適用 | E7: =INDEX($C$52:$H$52,輸入與假設!$C$499) -> 不適用 | F7: 不適用 | G7: 不適用 | H7: =INDEX($C$53:$H$53,輸入與假設!$C$499) -> 不適用 | I7: =IF(ISNUMBER(INDEX($C$42:$H$42,輸入與假設!$C$499)),INDEX($C$42:$H$42,輸入與假設!$C$499),"待公布") -> 待公布 | J7: =INDEX($C$54:$H$54,輸入與假設!$C$499) | K7: =INDEX($C$55:$H$55,輸入與假設!$C$499) | L7: =INDEX($C$56:$H$56,輸入與假設!$C$499) | M7: =INDEX($C$57:$H$57,輸入與假設!$C$499) -> 不適用 | N7: =INDEX($C$58:$H$58,輸入與假設!$C$499) -> 不適用 | O7: =INDEX($C$59:$H$59,輸入與假設!$C$499) | P7: =INDEX($C$60:$H$60,輸入與假設!$C$499) | Q7: =INDEX($C$61:$H$61,輸入與假設!$C$499)
A8: 焦點｜EBITDA 率 | B8: % | C8: =INDEX($C$27:$H$27,輸入與假設!$C$499) -> 0.22011394 | D8: =INDEX($C$39:$H$39,輸入與假設!$C$499) -> 不適用 | E8: =INDEX($C$62:$H$62,輸入與假設!$C$499) -> 不適用 | F8: 不適用 | G8: 不適用 | H8: =INDEX($C$63:$H$63,輸入與假設!$C$499) -> 不適用 | I8: =IF(ISNUMBER(INDEX($C$43:$H$43,輸入與假設!$C$499)),INDEX($C$43:$H$43,輸入與假設!$C$499),"待公布") -> 待公布 | J8: =INDEX($C$64:$H$64,輸入與假設!$C$499) | K8: =INDEX($C$65:$H$65,輸入與假設!$C$499) | L8: =INDEX($C$66:$H$66,輸入與假設!$C$499)
A9: 焦點｜調整後營業利益 | B9: US$bn | C9: =INDEX($C$31:$H$31,輸入與假設!$C$499) -> 27.386661 | D9: 不適用 | E9: =INDEX($C$67:$H$67,輸入與假設!$C$499) -> 不適用 | F9: =IF(ISNUMBER(INDEX($C$34:$H$34,輸入與假設!$C$499)),INDEX($C$34:$H$34,輸入與假設!$C$499),"不適用") -> 22.5 | G9: =INDEX($C$35:$H$35,輸入與假設!$C$499) -> 26.5 | H9: =INDEX($C$68:$H$68,輸入與假設!$C$499) -> 2.8866609 | I9: =IF(ISNUMBER(INDEX($C$44:$H$44,輸入與假設!$C$499)),INDEX($C$44:$H$44,輸入與假設!$C$499),"待公布") -> 待公布 | J9: =INDEX($C$69:$H$69,輸入與假設!$C$499) | K9: =INDEX($C$70:$H$70,輸入與假設!$C$499) | L9: =INDEX($C$71:$H$71,輸入與假設!$C$499) | M9: =INDEX($C$72:$H$72,輸入與假設!$C$499) -> 不適用 | N9: =INDEX($C$73:$H$73,輸入與假設!$C$499) -> 0.0030700647 | O9: =INDEX($C$74:$H$74,輸入與假設!$C$499) | P9: =INDEX($C$75:$H$75,輸入與假設!$C$499) | Q9: =INDEX($C$76:$H$76,輸入與假設!$C$499)
A10: 焦點｜CapEx（毛額） | B10: US$bn | C10: =INDEX($C$36:$H$36,輸入與假設!$C$499) -> 61.845 | D10: 不適用 | E10: =INDEX($C$77:$H$77,輸入與假設!$C$499) -> 不適用 | F10: 不適用 | G10: 不適用 | H10: =INDEX($C$78:$H$78,輸入與假設!$C$499) -> 不適用 | I10: =IF(ISNUMBER(INDEX($C$45:$H$45,輸入與假設!$C$499)),INDEX($C$45:$H$45,輸入與假設!$C$499),"待公布") -> 待公布 | J10: =INDEX($C$79:$H$79,輸入與假設!$C$499) | K10: =INDEX($C$80:$H$80,輸入與假設!$C$499) | L10: =INDEX($C$81:$H$81,輸入與假設!$C$499)
A11: 焦點｜季末已連網 MW-IT | B11: MW | C11: =INDEX($C$19:$H$19,輸入與假設!$C$499) -> 2987.2 | D11: 不適用 | E11: =INDEX($C$82:$H$82,輸入與假設!$C$499) -> 不適用 | F11: 不適用 | G11: 不適用 | H11: =INDEX($C$83:$H$83,輸入與假設!$C$499) -> 不適用 | I11: =IF(ISNUMBER(INDEX($C$46:$H$46,輸入與假設!$C$499)),INDEX($C$46:$H$46,輸入與假設!$C$499),"待公布") -> 待公布 | J11: =INDEX($C$84:$H$84,輸入與假設!$C$499) | K11: =INDEX($C$85:$H$85,輸入與假設!$C$499) | L11: =INDEX($C$86:$H$86,輸入與假設!$C$499)
A12: 焦點｜季度 | C12: =INDEX($C$16:$H$16,輸入與假設!$C$499) -> Q3 2026
A13: 焦點｜差異原因 | C13: =IF(INDEX($C$123:$H$123,輸入與假設!$C$499)="","無（差距皆在 "&IF(ROUND(ABS(輸入與假設!$C$493)*100,4)=INT(ROUND(ABS(輸入與假設!$C$493)*100,4)),TEXT(ROUND(ABS(輸入與假設!$C$493)*100,4),"0"),TEXT(ROUND(ABS(輸入與假設!$C$493)*100,4),"0.0"))&"%"&" 以內）",INDEX($C$123:$H$123,輸入與假設!$C$499)) -> 營收 vs 指引中點 +9.1%：觀點（營收＝對外 AI 雲端（在役 MW × 每 MW 年收入，Tokenomics × k）＋各分部依近四季年增率收斂；年度總額線性分到各季，未建模第四季季節性）；調整後營業利益 vs 指引中點 +$2.89bn／+0.3pt：觀點（模型折舊 14.00 依期初 PP&E 與資本支出推算；營業利益＝EBITDA − 折舊，年度總額線性分到各季）
A15: 2｜6 季路徑、共識、指引、實際與差距（明細；第 1 區以焦點季引用本區）
A16: 項目 | B16: 單位 | C16: Q3 2026 | D16: Q4 2026 | E16: Q1 2027 | F16: Q2 2027 | G16: Q3 2027 | H16: Q4 2027
A17: 所屬期間 | C17: =輸入與假設!C$498 -> 1 | D17: =輸入與假設!D$498 -> 1 | E17: =輸入與假設!E$498 -> 2 | F17: =輸入與假設!F$498 -> 2 | G17: =輸入與假設!G$498 -> 2 | H17: =輸入與假設!H$498 -> 2 | J17: 1＝2H26、2＝2027
A18: 季序 | C18: 1 | D18: 2 | E18: 3 | F18: 4 | G18: 5 | H18: 6 | J18: EBITDA 率直線的 x 軸
A19: 季末已連網 MW-IT（模型） | B19: MW | C19: =輸入與假設!$C$501+(輸入與假設!C$36-輸入與假設!$C$501)*1/2 -> 2987.2 | D19: =輸入與假設!$C$501+(輸入與假設!C$36-輸入與假設!$C$501)*2/2 -> 3894.4 | E19: =輸入與假設!C$36+(輸入與假設!D$36-輸入與假設!C$36)*1/4 -> 4801.6 | F19: =輸入與假設!C$36+(輸入與假設!D$36-輸入與假設!C$36)*2/4 -> 5708.8 | G19: =輸入與假設!C$36+(輸入與假設!D$36-輸入與假設!C$36)*3/4 -> 6616 | H19: =輸入與假設!C$36+(輸入與假設!D$36-輸入與假設!C$36)*4/4 -> 7523.2 | J19: 期初與期末 Accepted 之間線性內插；第 1 期起點見 J 區
A20: 平均在役 MW（Billable，拆分依據） | B20: MW | C20: =輸入與假設!$C$29+(運營_產能與收入!C$11-輸入與假設!$C$29)*1/4 -> 2533.5 | D20: =輸入與假設!$C$29+(運營_產能與收入!C$11-輸入與假設!$C$29)*3/4 -> 3440.5 | E20: =運營_產能與收入!C$11+(運營_產能與收入!D$11-運營_產能與收入!C$11)*1/8 -> 4347.625 | F20: =運營_產能與收入!C$11+(運營_產能與收入!D$11-運營_產能與收入!C$11)*3/8 -> 5254.875 | G20: =運營_產能與收入!C$11+(運營_產能與收入!D$11-運營_產能與收入!C$11)*5/8 -> 6162.125 | H20: =運營_產能與收入!C$11+(運營_產能與收入!D$11-運營_產能與收入!C$11)*7/8 -> 7069.375 | J20: 期初與期末 Billable 之間線性內插的季平均
A21: 季內新增 Accepted MW | B21: MW | C21: =C19-輸入與假設!$C$501 -> 907.2 | D21: =D19-C19 -> 907.2 | E21: =E19-輸入與假設!C$36 -> 907.2 | F21: =F19-E19 -> 907.2 | G21: =G19-F19 -> 907.2 | H21: =H19-G19 -> 907.2 | J21: CapEx 拆分依據
A22: 營收（模型） | B22: US$bn | C22: =輸入與假設!$C$500+1*(損益!C9-2*輸入與假設!$C$500)/3 -> 217.5667 | D22: =輸入與假設!$C$500+2*(損益!C9-2*輸入與假設!$C$500)/3 -> 234.52739 | E22: =損益!D9*E20/(E20+F20+G20+H20) -> 185.3641 | F22: =損益!D9*F20/(E20+F20+G20+H20) -> 224.04535 | G22: =損益!D9*G20/(E20+F20+G20+H20) -> 262.7266 | H22: =損益!D9*H20/(E20+F20+G20+H20) -> 301.40785 | J22: 拆分方法見『輸入與假設』J 區與 HTML「拆分方法」
A23: EBITDA 率直線｜各期營收合計 S | C23: =C22+D22 -> 452.09409 | D23: =E22+F22+G22+H22 -> 973.5439 | J23: 欄＝期間（2H26、2027）
A24: EBITDA 率直線｜營收 × 季序合計 T | C24: =C22*C18+D22*D18 -> 686.62148 | D24: =E22*E18+F22*F18+G22*G18+H22*H18 -> 4574.3538 | J24: 欄＝期間（2H26、2027）
A25: EBITDA 率直線｜年度 EBITDA E | C25: =損益!C22 -> 101.39782 | D25: =損益!D22 -> 243.24121 | J25: 欄＝期間（2H26、2027）
A26: EBITDA 率直線｜截距 a／斜率 b | C26: =(C25*D24-C24*D25)/(C23*D24-C24*D23) -> 0.21207391 | D26: =(C23*D25-D23*C25)/(C23*D24-C24*D23) -> 0.0080400313 | J26: 解兩式：Σ營收×(a＋b×季序)＝各期年度 EBITDA
A27: EBITDA 率（模型） | B27: % | C27: =$C$26+$D$26*C18 -> 0.22011394 | D27: =$C$26+$D$26*D18 -> 0.22815397 | E27: =$C$26+$D$26*E18 -> 0.236194 | F27: =$C$26+$D$26*F18 -> 0.24423403 | G27: =$C$26+$D$26*G18 -> 0.25227407 | H27: =$C$26+$D$26*H18 -> 0.2603141 | J27: 跨季一條直線，季度 EBITDA 加總＝年度
A28: 調整後 EBITDA（模型） | B28: US$bn | C28: =C22*C27 -> 47.889463 | D28: =D22*D27 -> 53.508356 | E28: =E22*E27 -> 43.781888 | F28: =F22*F27 -> 54.719499 | G28: =G22*G27 -> 66.279108 | H28: =H22*H27 -> 78.460713
A29: 車隊折舊（模型） | B29: US$bn | C29: =輸入與假設!C$278/2 -> 14.002632 | D29: =輸入與假設!C$278/2 -> 14.002632 | E29: =輸入與假設!D$278/4 -> 20.417939 | F29: =輸入與假設!D$278/4 -> 20.417939 | G29: =輸入與假設!D$278/4 -> 20.417939 | H29: =輸入與假設!D$278/4 -> 20.417939 | J29: ＝期間 D&A（AI＋非 AI 分池）÷ 期內季數
A30: 其他攤銷（模型） | B30: US$bn | C30: =輸入與假設!C$196*C22/MAX(0.000000001,C23) -> 6.50017 | D30: =輸入與假設!C$196*D22/MAX(0.000000001,C23) -> 7.0068992 | E30: =輸入與假設!D$196*E22/MAX(0.000000001,D23) -> 5.6311104 | F30: =輸入與假設!D$196*F22/MAX(0.000000001,D23) -> 6.8061945 | G30: =輸入與假設!D$196*G22/MAX(0.000000001,D23) -> 7.9812786 | H30: =輸入與假設!D$196*H22/MAX(0.000000001,D23) -> 9.1563627 | J30: ＝期間非 AI 事業其他攤銷 × 季營收占比（MAG v0.1b）
A31: 調整後營業利益（模型） | B31: US$bn | C31: =C28-C29-C30 -> 27.386661 | D31: =D28-D29-D30 -> 32.498825 | E31: =E28-E29-E30 -> 17.732838 | F31: =F28-F29-F30 -> 27.495366 | G31: =G28-G29-G30 -> 37.87989 | H31: =H28-H29-H30 -> 48.886411 | J31: ＝調整後 EBITDA − 車隊折舊 − 其他攤銷（未扣 SBC）
A32: 指引｜營收（低） | B32: US$bn | C32: =IF(ISNUMBER(輸入與假設!C$510),輸入與假設!C$510,"不適用") -> 197 | D32: =IF(ISNUMBER(輸入與假設!D$510),輸入與假設!D$510,"不適用") -> 不適用 | E32: =IF(ISNUMBER(輸入與假設!E$510),輸入與假設!E$510,"不適用") -> 不適用 | F32: =IF(ISNUMBER(輸入與假設!F$510),輸入與假設!F$510,"不適用") -> 不適用 | G32: =IF(ISNUMBER(輸入與假設!G$510),輸入與假設!G$510,"不適用") -> 不適用 | H32: =IF(ISNUMBER(輸入與假設!H$510),輸入與假設!H$510,"不適用") -> 不適用
A33: 指引｜營收（高） | B33: US$bn | C33: =IF(ISNUMBER(輸入與假設!C$511),輸入與假設!C$511,"不適用") -> 202 | D33: =IF(ISNUMBER(輸入與假設!D$511),輸入與假設!D$511,"不適用") -> 不適用 | E33: =IF(ISNUMBER(輸入與假設!E$511),輸入與假設!E$511,"不適用") -> 不適用 | F33: =IF(ISNUMBER(輸入與假設!F$511),輸入與假設!F$511,"不適用") -> 不適用 | G33: =IF(ISNUMBER(輸入與假設!G$511),輸入與假設!G$511,"不適用") -> 不適用 | H33: =IF(ISNUMBER(輸入與假設!H$511),輸入與假設!H$511,"不適用") -> 不適用
A34: 指引｜調整後營業利益（低） | B34: US$bn | C34: =IF(ISNUMBER(輸入與假設!C$512),輸入與假設!C$512,"不適用") -> 22.5 | D34: =IF(ISNUMBER(輸入與假設!D$512),輸入與假設!D$512,"不適用") -> 不適用 | E34: =IF(ISNUMBER(輸入與假設!E$512),輸入與假設!E$512,"不適用") -> 不適用 | F34: =IF(ISNUMBER(輸入與假設!F$512),輸入與假設!F$512,"不適用") -> 不適用 | G34: =IF(ISNUMBER(輸入與假設!G$512),輸入與假設!G$512,"不適用") -> 不適用 | H34: =IF(ISNUMBER(輸入與假設!H$512),輸入與假設!H$512,"不適用") -> 不適用
A35: 指引｜調整後營業利益（高） | B35: US$bn | C35: =IF(ISNUMBER(輸入與假設!C$513),輸入與假設!C$513,"不適用") -> 26.5 | D35: =IF(ISNUMBER(輸入與假設!D$513),輸入與假設!D$513,"不適用") -> 不適用 | E35: =IF(ISNUMBER(輸入與假設!E$513),輸入與假設!E$513,"不適用") -> 不適用 | F35: =IF(ISNUMBER(輸入與假設!F$513),輸入與假設!F$513,"不適用") -> 不適用 | G35: =IF(ISNUMBER(輸入與假設!G$513),輸入與假設!G$513,"不適用") -> 不適用 | H35: =IF(ISNUMBER(輸入與假設!H$513),輸入與假設!H$513,"不適用") -> 不適用
A36: CapEx（毛額）（模型） | B36: US$bn | C36: =IF((C21+D21)>0,輸入與假設!C$277*C21/(C21+D21),輸入與假設!C$277/2) -> 61.845 | D36: =IF((C21+D21)>0,輸入與假設!C$277*D21/(C21+D21),輸入與假設!C$277/2) -> 61.845 | E36: =IF((E21+F21+G21+H21)>0,輸入與假設!D$277*E21/(E21+F21+G21+H21),輸入與假設!D$277/4) -> 69.056456 | F36: =IF((E21+F21+G21+H21)>0,輸入與假設!D$277*F21/(E21+F21+G21+H21),輸入與假設!D$277/4) -> 69.056456 | G36: =IF((E21+F21+G21+H21)>0,輸入與假設!D$277*G21/(E21+F21+G21+H21),輸入與假設!D$277/4) -> 69.056456 | H36: =IF((E21+F21+G21+H21)>0,輸入與假設!D$277*H21/(E21+F21+G21+H21),輸入與假設!D$277/4) -> 69.056456 | J36: 依季內新增 Accepted MW
A37: 共識｜營收 | B37: US$bn | C37: 不適用 | D37: 不適用 | E37: 不適用 | F37: 不適用 | G37: 不適用 | H37: 不適用 | J37: I 區季度共識 [Interested-party]
A38: 共識｜調整後 EBITDA | B38: US$bn | C38: 不適用 | D38: 不適用 | E38: 不適用 | F38: 不適用 | G38: 不適用 | H38: 不適用 | J38: I 區季度共識 [Interested-party]
A39: 共識｜EBITDA 率 [Derived] | B39: % | C39: 不適用 | D39: 不適用 | E39: 不適用 | F39: 不適用 | G39: 不適用 | H39: 不適用 | J39: ＝共識 EBITDA ÷ 共識營收
A40: 共識 EBIT（供應商口徑） | B40: US$bn | C40: 不適用 | D40: 不適用 | E40: 不適用 | F40: 不適用 | G40: 不適用 | H40: 不適用 | J40: 口徑未揭露：只列不比較
A41: 實際｜營收 | B41: US$bn | C41: =IF(ISNUMBER(輸入與假設!C$502),輸入與假設!C$502,"") | D41: =IF(ISNUMBER(輸入與假設!D$502),輸入與假設!D$502,"") | E41: =IF(ISNUMBER(輸入與假設!E$502),輸入與假設!E$502,"") | F41: =IF(ISNUMBER(輸入與假設!F$502),輸入與假設!F$502,"") | G41: =IF(ISNUMBER(輸入與假設!G$502),輸入與假設!G$502,"") | H41: =IF(ISNUMBER(輸入與假設!H$502),輸入與假設!H$502,"")
A42: 實際｜調整後 EBITDA | B42: US$bn | C42: =IF(ISNUMBER(輸入與假設!C$503),輸入與假設!C$503,"") | D42: =IF(ISNUMBER(輸入與假設!D$503),輸入與假設!D$503,"") | E42: =IF(ISNUMBER(輸入與假設!E$503),輸入與假設!E$503,"") | F42: =IF(ISNUMBER(輸入與假設!F$503),輸入與假設!F$503,"") | G42: =IF(ISNUMBER(輸入與假設!G$503),輸入與假設!G$503,"") | H42: =IF(ISNUMBER(輸入與假設!H$503),輸入與假設!H$503,"")
A43: 實際｜EBITDA 率 | B43: % | C43: =IF(AND(ISNUMBER(輸入與假設!C$503),ISNUMBER(輸入與假設!C$502)),輸入與假設!C$503/輸入與假設!C$502,"") | D43: =IF(AND(ISNUMBER(輸入與假設!D$503),ISNUMBER(輸入與假設!D$502)),輸入與假設!D$503/輸入與假設!D$502,"") | E43: =IF(AND(ISNUMBER(輸入與假設!E$503),ISNUMBER(輸入與假設!E$502)),輸入與假設!E$503/輸入與假設!E$502,"") | F43: =IF(AND(ISNUMBER(輸入與假設!F$503),ISNUMBER(輸入與假設!F$502)),輸入與假設!F$503/輸入與假設!F$502,"") | G43: =IF(AND(ISNUMBER(輸入與假設!G$503),ISNUMBER(輸入與假設!G$502)),輸入與假設!G$503/輸入與假設!G$502,"") | H43: =IF(AND(ISNUMBER(輸入與假設!H$503),ISNUMBER(輸入與假設!H$502)),輸入與假設!H$503/輸入與假設!H$502,"") | J43: ＝實際 EBITDA ÷ 實際營收
A44: 實際｜調整後營業利益 | B44: US$bn | C44: =IF(ISNUMBER(輸入與假設!C$504),輸入與假設!C$504,"") | D44: =IF(ISNUMBER(輸入與假設!D$504),輸入與假設!D$504,"") | E44: =IF(ISNUMBER(輸入與假設!E$504),輸入與假設!E$504,"") | F44: =IF(ISNUMBER(輸入與假設!F$504),輸入與假設!F$504,"") | G44: =IF(ISNUMBER(輸入與假設!G$504),輸入與假設!G$504,"") | H44: =IF(ISNUMBER(輸入與假設!H$504),輸入與假設!H$504,"")
A45: 實際｜CapEx（毛額） | B45: US$bn | C45: =IF(ISNUMBER(輸入與假設!C$505),輸入與假設!C$505,"") | D45: =IF(ISNUMBER(輸入與假設!D$505),輸入與假設!D$505,"") | E45: =IF(ISNUMBER(輸入與假設!E$505),輸入與假設!E$505,"") | F45: =IF(ISNUMBER(輸入與假設!F$505),輸入與假設!F$505,"") | G45: =IF(ISNUMBER(輸入與假設!G$505),輸入與假設!G$505,"") | H45: =IF(ISNUMBER(輸入與假設!H$505),輸入與假設!H$505,"")
A46: 實際｜季末對外 AI MW（未揭露） | B46: MW | C46: =IF(ISNUMBER(輸入與假設!C$506),輸入與假設!C$506,"") | D46: =IF(ISNUMBER(輸入與假設!D$506),輸入與假設!D$506,"") | E46: =IF(ISNUMBER(輸入與假設!E$506),輸入與假設!E$506,"") | F46: =IF(ISNUMBER(輸入與假設!F$506),輸入與假設!F$506,"") | G46: =IF(ISNUMBER(輸入與假設!G$506),輸入與假設!G$506,"") | H46: =IF(ISNUMBER(輸入與假設!H$506),輸入與假設!H$506,"")
A47: 差距｜營收｜模型 vs 共識 | B47: % | C47: =IF(AND(ISNUMBER(C22),ISNUMBER(C37),C37<>0),C22/(C37)-1,"不適用") -> 不適用 | D47: =IF(AND(ISNUMBER(D22),ISNUMBER(D37),D37<>0),D22/(D37)-1,"不適用") -> 不適用 | E47: =IF(AND(ISNUMBER(E22),ISNUMBER(E37),E37<>0),E22/(E37)-1,"不適用") -> 不適用 | F47: =IF(AND(ISNUMBER(F22),ISNUMBER(F37),F37<>0),F22/(F37)-1,"不適用") -> 不適用 | G47: =IF(AND(ISNUMBER(G22),ISNUMBER(G37),G37<>0),G22/(G37)-1,"不適用") -> 不適用 | H47: =IF(AND(ISNUMBER(H22),ISNUMBER(H37),H37<>0),H22/(H37)-1,"不適用") -> 不適用
A48: 差距｜營收｜模型 vs 指引中點 | B48: % | C48: =IF(AND(ISNUMBER(C22),ISNUMBER(C32),ISNUMBER(C33)),C22/(((C32+C33)/2))-1,"不適用") -> 0.090559881 | D48: =IF(AND(ISNUMBER(D22),ISNUMBER(D32),ISNUMBER(D33)),D22/(((D32+D33)/2))-1,"不適用") -> 不適用 | E48: =IF(AND(ISNUMBER(E22),ISNUMBER(E32),ISNUMBER(E33)),E22/(((E32+E33)/2))-1,"不適用") -> 不適用 | F48: =IF(AND(ISNUMBER(F22),ISNUMBER(F32),ISNUMBER(F33)),F22/(((F32+F33)/2))-1,"不適用") -> 不適用 | G48: =IF(AND(ISNUMBER(G22),ISNUMBER(G32),ISNUMBER(G33)),G22/(((G32+G33)/2))-1,"不適用") -> 不適用 | H48: =IF(AND(ISNUMBER(H22),ISNUMBER(H32),ISNUMBER(H33)),H22/(((H32+H33)/2))-1,"不適用") -> 不適用
A49: 差距｜營收｜實際 vs 模型 | B49: % | C49: =IF(ISNUMBER(C41),IF(AND(ISNUMBER(C22),C22<>0),C41/(C22)-1,"不適用"),"") | D49: =IF(ISNUMBER(D41),IF(AND(ISNUMBER(D22),D22<>0),D41/(D22)-1,"不適用"),"") | E49: =IF(ISNUMBER(E41),IF(AND(ISNUMBER(E22),E22<>0),E41/(E22)-1,"不適用"),"") | F49: =IF(ISNUMBER(F41),IF(AND(ISNUMBER(F22),F22<>0),F41/(F22)-1,"不適用"),"") | G49: =IF(ISNUMBER(G41),IF(AND(ISNUMBER(G22),G22<>0),G41/(G22)-1,"不適用"),"") | H49: =IF(ISNUMBER(H41),IF(AND(ISNUMBER(H22),H22<>0),H41/(H22)-1,"不適用"),"")
A50: 差距｜營收｜實際 vs 共識 | B50: % | C50: =IF(ISNUMBER(C41),IF(AND(ISNUMBER(C37),C37<>0),C41/(C37)-1,"不適用"),"") | D50: =IF(ISNUMBER(D41),IF(AND(ISNUMBER(D37),D37<>0),D41/(D37)-1,"不適用"),"") | E50: =IF(ISNUMBER(E41),IF(AND(ISNUMBER(E37),E37<>0),E41/(E37)-1,"不適用"),"") | F50: =IF(ISNUMBER(F41),IF(AND(ISNUMBER(F37),F37<>0),F41/(F37)-1,"不適用"),"") | G50: =IF(ISNUMBER(G41),IF(AND(ISNUMBER(G37),G37<>0),G41/(G37)-1,"不適用"),"") | H50: =IF(ISNUMBER(H41),IF(AND(ISNUMBER(H37),H37<>0),H41/(H37)-1,"不適用"),"")
A51: 差距｜營收｜實際 vs 指引中點 | B51: % | C51: =IF(ISNUMBER(C41),IF(AND(ISNUMBER(C32),ISNUMBER(C33)),C41/(((C32+C33)/2))-1,"不適用"),"") | D51: =IF(ISNUMBER(D41),IF(AND(ISNUMBER(D32),ISNUMBER(D33)),D41/(((D32+D33)/2))-1,"不適用"),"") | E51: =IF(ISNUMBER(E41),IF(AND(ISNUMBER(E32),ISNUMBER(E33)),E41/(((E32+E33)/2))-1,"不適用"),"") | F51: =IF(ISNUMBER(F41),IF(AND(ISNUMBER(F32),ISNUMBER(F33)),F41/(((F32+F33)/2))-1,"不適用"),"") | G51: =IF(ISNUMBER(G41),IF(AND(ISNUMBER(G32),ISNUMBER(G33)),G41/(((G32+G33)/2))-1,"不適用"),"") | H51: =IF(ISNUMBER(H41),IF(AND(ISNUMBER(H32),ISNUMBER(H33)),H41/(((H32+H33)/2))-1,"不適用"),"")
A52: 差距｜調整後 EBITDA｜模型 vs 共識 | B52: US$bn | C52: =IF(AND(ISNUMBER(C28),ISNUMBER(C38)),C28-(C38),"不適用") -> 不適用 | D52: =IF(AND(ISNUMBER(D28),ISNUMBER(D38)),D28-(D38),"不適用") -> 不適用 | E52: =IF(AND(ISNUMBER(E28),ISNUMBER(E38)),E28-(E38),"不適用") -> 不適用 | F52: =IF(AND(ISNUMBER(F28),ISNUMBER(F38)),F28-(F38),"不適用") -> 不適用 | G52: =IF(AND(ISNUMBER(G28),ISNUMBER(G38)),G28-(G38),"不適用") -> 不適用 | H52: =IF(AND(ISNUMBER(H28),ISNUMBER(H38)),H28-(H38),"不適用") -> 不適用
A53: 差距｜調整後 EBITDA｜模型 vs 指引中點 | B53: US$bn | C53: 不適用 | D53: 不適用 | E53: 不適用 | F53: 不適用 | G53: 不適用 | H53: 不適用
A54: 差距｜調整後 EBITDA｜實際 vs 模型 | B54: US$bn | C54: =IF(ISNUMBER(C42),IF(AND(ISNUMBER(C28)),C42-(C28),"不適用"),"") | D54: =IF(ISNUMBER(D42),IF(AND(ISNUMBER(D28)),D42-(D28),"不適用"),"") | E54: =IF(ISNUMBER(E42),IF(AND(ISNUMBER(E28)),E42-(E28),"不適用"),"") | F54: =IF(ISNUMBER(F42),IF(AND(ISNUMBER(F28)),F42-(F28),"不適用"),"") | G54: =IF(ISNUMBER(G42),IF(AND(ISNUMBER(G28)),G42-(G28),"不適用"),"") | H54: =IF(ISNUMBER(H42),IF(AND(ISNUMBER(H28)),H42-(H28),"不適用"),"")
A55: 差距｜調整後 EBITDA｜實際 vs 共識 | B55: US$bn | C55: =IF(ISNUMBER(C42),IF(AND(ISNUMBER(C38)),C42-(C38),"不適用"),"") | D55: =IF(ISNUMBER(D42),IF(AND(ISNUMBER(D38)),D42-(D38),"不適用"),"") | E55: =IF(ISNUMBER(E42),IF(AND(ISNUMBER(E38)),E42-(E38),"不適用"),"") | F55: =IF(ISNUMBER(F42),IF(AND(ISNUMBER(F38)),F42-(F38),"不適用"),"") | G55: =IF(ISNUMBER(G42),IF(AND(ISNUMBER(G38)),G42-(G38),"不適用"),"") | H55: =IF(ISNUMBER(H42),IF(AND(ISNUMBER(H38)),H42-(H38),"不適用"),"")
A56: 差距｜調整後 EBITDA｜實際 vs 指引中點 | B56: US$bn | C56: =IF(ISNUMBER(C42),"不適用","") | D56: =IF(ISNUMBER(D42),"不適用","") | E56: =IF(ISNUMBER(E42),"不適用","") | F56: =IF(ISNUMBER(F42),"不適用","") | G56: =IF(ISNUMBER(G42),"不適用","") | H56: =IF(ISNUMBER(H42),"不適用","")
A57: 差距｜調整後 EBITDA｜模型 vs 共識（利潤率 pt） | B57: pt | C57: =IF(AND(ISNUMBER(C28),ISNUMBER(C22),C22<>0,ISNUMBER(C38),ISNUMBER(C37),C37<>0),C28/C22-C38/C37,"不適用") -> 不適用 | D57: =IF(AND(ISNUMBER(D28),ISNUMBER(D22),D22<>0,ISNUMBER(D38),ISNUMBER(D37),D37<>0),D28/D22-D38/D37,"不適用") -> 不適用 | E57: =IF(AND(ISNUMBER(E28),ISNUMBER(E22),E22<>0,ISNUMBER(E38),ISNUMBER(E37),E37<>0),E28/E22-E38/E37,"不適用") -> 不適用 | F57: =IF(AND(ISNUMBER(F28),ISNUMBER(F22),F22<>0,ISNUMBER(F38),ISNUMBER(F37),F37<>0),F28/F22-F38/F37,"不適用") -> 不適用 | G57: =IF(AND(ISNUMBER(G28),ISNUMBER(G22),G22<>0,ISNUMBER(G38),ISNUMBER(G37),G37<>0),G28/G22-G38/G37,"不適用") -> 不適用 | H57: =IF(AND(ISNUMBER(H28),ISNUMBER(H22),H22<>0,ISNUMBER(H38),ISNUMBER(H37),H37<>0),H28/H22-H38/H37,"不適用") -> 不適用
A58: 差距｜調整後 EBITDA｜模型 vs 指引中點（利潤率 pt） | B58: pt | C58: 不適用 | D58: 不適用 | E58: 不適用 | F58: 不適用 | G58: 不適用 | H58: 不適用
A59: 差距｜調整後 EBITDA｜實際 vs 模型（利潤率 pt） | B59: pt | C59: =IF(ISNUMBER(C42),IF(AND(ISNUMBER(C42),ISNUMBER(C41),C41<>0,ISNUMBER(C28),ISNUMBER(C22),C22<>0),C42/C41-C28/C22,"不適用"),"") | D59: =IF(ISNUMBER(D42),IF(AND(ISNUMBER(D42),ISNUMBER(D41),D41<>0,ISNUMBER(D28),ISNUMBER(D22),D22<>0),D42/D41-D28/D22,"不適用"),"") | E59: =IF(ISNUMBER(E42),IF(AND(ISNUMBER(E42),ISNUMBER(E41),E41<>0,ISNUMBER(E28),ISNUMBER(E22),E22<>0),E42/E41-E28/E22,"不適用"),"") | F59: =IF(ISNUMBER(F42),IF(AND(ISNUMBER(F42),ISNUMBER(F41),F41<>0,ISNUMBER(F28),ISNUMBER(F22),F22<>0),F42/F41-F28/F22,"不適用"),"") | G59: =IF(ISNUMBER(G42),IF(AND(ISNUMBER(G42),ISNUMBER(G41),G41<>0,ISNUMBER(G28),ISNUMBER(G22),G22<>0),G42/G41-G28/G22,"不適用"),"") | H59: =IF(ISNUMBER(H42),IF(AND(ISNUMBER(H42),ISNUMBER(H41),H41<>0,ISNUMBER(H28),ISNUMBER(H22),H22<>0),H42/H41-H28/H22,"不適用"),"")
A60: 差距｜調整後 EBITDA｜實際 vs 共識（利潤率 pt） | B60: pt | C60: =IF(ISNUMBER(C42),IF(AND(ISNUMBER(C42),ISNUMBER(C41),C41<>0,ISNUMBER(C38),ISNUMBER(C37),C37<>0),C42/C41-C38/C37,"不適用"),"") | D60: =IF(ISNUMBER(D42),IF(AND(ISNUMBER(D42),ISNUMBER(D41),D41<>0,ISNUMBER(D38),ISNUMBER(D37),D37<>0),D42/D41-D38/D37,"不適用"),"") | E60: =IF(ISNUMBER(E42),IF(AND(ISNUMBER(E42),ISNUMBER(E41),E41<>0,ISNUMBER(E38),ISNUMBER(E37),E37<>0),E42/E41-E38/E37,"不適用"),"") | F60: =IF(ISNUMBER(F42),IF(AND(ISNUMBER(F42),ISNUMBER(F41),F41<>0,ISNUMBER(F38),ISNUMBER(F37),F37<>0),F42/F41-F38/F37,"不適用"),"") | G60: =IF(ISNUMBER(G42),IF(AND(ISNUMBER(G42),ISNUMBER(G41),G41<>0,ISNUMBER(G38),ISNUMBER(G37),G37<>0),G42/G41-G38/G37,"不適用"),"") | H60: =IF(ISNUMBER(H42),IF(AND(ISNUMBER(H42),ISNUMBER(H41),H41<>0,ISNUMBER(H38),ISNUMBER(H37),H37<>0),H42/H41-H38/H37,"不適用"),"")
A61: 差距｜調整後 EBITDA｜實際 vs 指引中點（利潤率 pt） | B61: pt | C61: =IF(ISNUMBER(C42),"不適用","") | D61: =IF(ISNUMBER(D42),"不適用","") | E61: =IF(ISNUMBER(E42),"不適用","") | F61: =IF(ISNUMBER(F42),"不適用","") | G61: =IF(ISNUMBER(G42),"不適用","") | H61: =IF(ISNUMBER(H42),"不適用","")
A62: 差距｜EBITDA 率｜模型 vs 共識 | B62: pt | C62: =IF(AND(ISNUMBER(C27),ISNUMBER(C39)),C27-(C39),"不適用") -> 不適用 | D62: =IF(AND(ISNUMBER(D27),ISNUMBER(D39)),D27-(D39),"不適用") -> 不適用 | E62: =IF(AND(ISNUMBER(E27),ISNUMBER(E39)),E27-(E39),"不適用") -> 不適用 | F62: =IF(AND(ISNUMBER(F27),ISNUMBER(F39)),F27-(F39),"不適用") -> 不適用 | G62: =IF(AND(ISNUMBER(G27),ISNUMBER(G39)),G27-(G39),"不適用") -> 不適用 | H62: =IF(AND(ISNUMBER(H27),ISNUMBER(H39)),H27-(H39),"不適用") -> 不適用
A63: 差距｜EBITDA 率｜模型 vs 指引中點 | B63: pt | C63: 不適用 | D63: 不適用 | E63: 不適用 | F63: 不適用 | G63: 不適用 | H63: 不適用
A64: 差距｜EBITDA 率｜實際 vs 模型 | B64: pt | C64: =IF(ISNUMBER(C43),IF(AND(ISNUMBER(C27)),C43-(C27),"不適用"),"") | D64: =IF(ISNUMBER(D43),IF(AND(ISNUMBER(D27)),D43-(D27),"不適用"),"") | E64: =IF(ISNUMBER(E43),IF(AND(ISNUMBER(E27)),E43-(E27),"不適用"),"") | F64: =IF(ISNUMBER(F43),IF(AND(ISNUMBER(F27)),F43-(F27),"不適用"),"") | G64: =IF(ISNUMBER(G43),IF(AND(ISNUMBER(G27)),G43-(G27),"不適用"),"") | H64: =IF(ISNUMBER(H43),IF(AND(ISNUMBER(H27)),H43-(H27),"不適用"),"")
A65: 差距｜EBITDA 率｜實際 vs 共識 | B65: pt | C65: =IF(ISNUMBER(C43),IF(AND(ISNUMBER(C39)),C43-(C39),"不適用"),"") | D65: =IF(ISNUMBER(D43),IF(AND(ISNUMBER(D39)),D43-(D39),"不適用"),"") | E65: =IF(ISNUMBER(E43),IF(AND(ISNUMBER(E39)),E43-(E39),"不適用"),"") | F65: =IF(ISNUMBER(F43),IF(AND(ISNUMBER(F39)),F43-(F39),"不適用"),"") | G65: =IF(ISNUMBER(G43),IF(AND(ISNUMBER(G39)),G43-(G39),"不適用"),"") | H65: =IF(ISNUMBER(H43),IF(AND(ISNUMBER(H39)),H43-(H39),"不適用"),"")
A66: 差距｜EBITDA 率｜實際 vs 指引中點 | B66: pt | C66: =IF(ISNUMBER(C43),"不適用","") | D66: =IF(ISNUMBER(D43),"不適用","") | E66: =IF(ISNUMBER(E43),"不適用","") | F66: =IF(ISNUMBER(F43),"不適用","") | G66: =IF(ISNUMBER(G43),"不適用","") | H66: =IF(ISNUMBER(H43),"不適用","")
A67: 差距｜調整後營業利益｜模型 vs 共識 | B67: US$bn | C67: 不適用 | D67: 不適用 | E67: 不適用 | F67: 不適用 | G67: 不適用 | H67: 不適用
A68: 差距｜調整後營業利益｜模型 vs 指引中點 | B68: US$bn | C68: =IF(AND(ISNUMBER(C31),ISNUMBER(C34),ISNUMBER(C35)),C31-(((C34+C35)/2)),"不適用") -> 2.8866609 | D68: =IF(AND(ISNUMBER(D31),ISNUMBER(D34),ISNUMBER(D35)),D31-(((D34+D35)/2)),"不適用") -> 不適用 | E68: =IF(AND(ISNUMBER(E31),ISNUMBER(E34),ISNUMBER(E35)),E31-(((E34+E35)/2)),"不適用") -> 不適用 | F68: =IF(AND(ISNUMBER(F31),ISNUMBER(F34),ISNUMBER(F35)),F31-(((F34+F35)/2)),"不適用") -> 不適用 | G68: =IF(AND(ISNUMBER(G31),ISNUMBER(G34),ISNUMBER(G35)),G31-(((G34+G35)/2)),"不適用") -> 不適用 | H68: =IF(AND(ISNUMBER(H31),ISNUMBER(H34),ISNUMBER(H35)),H31-(((H34+H35)/2)),"不適用") -> 不適用
A69: 差距｜調整後營業利益｜實際 vs 模型 | B69: US$bn | C69: =IF(ISNUMBER(C44),IF(AND(ISNUMBER(C31)),C44-(C31),"不適用"),"") | D69: =IF(ISNUMBER(D44),IF(AND(ISNUMBER(D31)),D44-(D31),"不適用"),"") | E69: =IF(ISNUMBER(E44),IF(AND(ISNUMBER(E31)),E44-(E31),"不適用"),"") | F69: =IF(ISNUMBER(F44),IF(AND(ISNUMBER(F31)),F44-(F31),"不適用"),"") | G69: =IF(ISNUMBER(G44),IF(AND(ISNUMBER(G31)),G44-(G31),"不適用"),"") | H69: =IF(ISNUMBER(H44),IF(AND(ISNUMBER(H31)),H44-(H31),"不適用"),"")
A70: 差距｜調整後營業利益｜實際 vs 共識 | B70: US$bn | C70: =IF(ISNUMBER(C44),"不適用","") | D70: =IF(ISNUMBER(D44),"不適用","") | E70: =IF(ISNUMBER(E44),"不適用","") | F70: =IF(ISNUMBER(F44),"不適用","") | G70: =IF(ISNUMBER(G44),"不適用","") | H70: =IF(ISNUMBER(H44),"不適用","")
A71: 差距｜調整後營業利益｜實際 vs 指引中點 | B71: US$bn | C71: =IF(ISNUMBER(C44),IF(AND(ISNUMBER(C34),ISNUMBER(C35)),C44-(((C34+C35)/2)),"不適用"),"") | D71: =IF(ISNUMBER(D44),IF(AND(ISNUMBER(D34),ISNUMBER(D35)),D44-(((D34+D35)/2)),"不適用"),"") | E71: =IF(ISNUMBER(E44),IF(AND(ISNUMBER(E34),ISNUMBER(E35)),E44-(((E34+E35)/2)),"不適用"),"") | F71: =IF(ISNUMBER(F44),IF(AND(ISNUMBER(F34),ISNUMBER(F35)),F44-(((F34+F35)/2)),"不適用"),"") | G71: =IF(ISNUMBER(G44),IF(AND(ISNUMBER(G34),ISNUMBER(G35)),G44-(((G34+G35)/2)),"不適用"),"") | H71: =IF(ISNUMBER(H44),IF(AND(ISNUMBER(H34),ISNUMBER(H35)),H44-(((H34+H35)/2)),"不適用"),"")
A72: 差距｜調整後營業利益｜模型 vs 共識（利潤率 pt） | B72: pt | C72: 不適用 | D72: 不適用 | E72: 不適用 | F72: 不適用 | G72: 不適用 | H72: 不適用
A73: 差距｜調整後營業利益｜模型 vs 指引中點（利潤率 pt） | B73: pt | C73: =IF(AND(ISNUMBER(C31),ISNUMBER(C22),C22<>0,ISNUMBER(C34),ISNUMBER(C35),ISNUMBER(C32),ISNUMBER(C33)),C31/C22-((C34+C35)/2)/((C32+C33)/2),"不適用") -> 0.0030700647 | D73: =IF(AND(ISNUMBER(D31),ISNUMBER(D22),D22<>0,ISNUMBER(D34),ISNUMBER(D35),ISNUMBER(D32),ISNUMBER(D33)),D31/D22-((D34+D35)/2)/((D32+D33)/2),"不適用") -> 不適用 | E73: =IF(AND(ISNUMBER(E31),ISNUMBER(E22),E22<>0,ISNUMBER(E34),ISNUMBER(E35),ISNUMBER(E32),ISNUMBER(E33)),E31/E22-((E34+E35)/2)/((E32+E33)/2),"不適用") -> 不適用 | F73: =IF(AND(ISNUMBER(F31),ISNUMBER(F22),F22<>0,ISNUMBER(F34),ISNUMBER(F35),ISNUMBER(F32),ISNUMBER(F33)),F31/F22-((F34+F35)/2)/((F32+F33)/2),"不適用") -> 不適用 | G73: =IF(AND(ISNUMBER(G31),ISNUMBER(G22),G22<>0,ISNUMBER(G34),ISNUMBER(G35),ISNUMBER(G32),ISNUMBER(G33)),G31/G22-((G34+G35)/2)/((G32+G33)/2),"不適用") -> 不適用 | H73: =IF(AND(ISNUMBER(H31),ISNUMBER(H22),H22<>0,ISNUMBER(H34),ISNUMBER(H35),ISNUMBER(H32),ISNUMBER(H33)),H31/H22-((H34+H35)/2)/((H32+H33)/2),"不適用") -> 不適用
A74: 差距｜調整後營業利益｜實際 vs 模型（利潤率 pt） | B74: pt | C74: =IF(ISNUMBER(C44),IF(AND(ISNUMBER(C44),ISNUMBER(C41),C41<>0,ISNUMBER(C31),ISNUMBER(C22),C22<>0),C44/C41-C31/C22,"不適用"),"") | D74: =IF(ISNUMBER(D44),IF(AND(ISNUMBER(D44),ISNUMBER(D41),D41<>0,ISNUMBER(D31),ISNUMBER(D22),D22<>0),D44/D41-D31/D22,"不適用"),"") | E74: =IF(ISNUMBER(E44),IF(AND(ISNUMBER(E44),ISNUMBER(E41),E41<>0,ISNUMBER(E31),ISNUMBER(E22),E22<>0),E44/E41-E31/E22,"不適用"),"") | F74: =IF(ISNUMBER(F44),IF(AND(ISNUMBER(F44),ISNUMBER(F41),F41<>0,ISNUMBER(F31),ISNUMBER(F22),F22<>0),F44/F41-F31/F22,"不適用"),"") | G74: =IF(ISNUMBER(G44),IF(AND(ISNUMBER(G44),ISNUMBER(G41),G41<>0,ISNUMBER(G31),ISNUMBER(G22),G22<>0),G44/G41-G31/G22,"不適用"),"") | H74: =IF(ISNUMBER(H44),IF(AND(ISNUMBER(H44),ISNUMBER(H41),H41<>0,ISNUMBER(H31),ISNUMBER(H22),H22<>0),H44/H41-H31/H22,"不適用"),"")
A75: 差距｜調整後營業利益｜實際 vs 共識（利潤率 pt） | B75: pt | C75: =IF(ISNUMBER(C44),"不適用","") | D75: =IF(ISNUMBER(D44),"不適用","") | E75: =IF(ISNUMBER(E44),"不適用","") | F75: =IF(ISNUMBER(F44),"不適用","") | G75: =IF(ISNUMBER(G44),"不適用","") | H75: =IF(ISNUMBER(H44),"不適用","")
A76: 差距｜調整後營業利益｜實際 vs 指引中點（利潤率 pt） | B76: pt | C76: =IF(ISNUMBER(C44),IF(AND(ISNUMBER(C44),ISNUMBER(C41),C41<>0,ISNUMBER(C34),ISNUMBER(C35),ISNUMBER(C32),ISNUMBER(C33)),C44/C41-((C34+C35)/2)/((C32+C33)/2),"不適用"),"") | D76: =IF(ISNUMBER(D44),IF(AND(ISNUMBER(D44),ISNUMBER(D41),D41<>0,ISNUMBER(D34),ISNUMBER(D35),ISNUMBER(D32),ISNUMBER(D33)),D44/D41-((D34+D35)/2)/((D32+D33)/2),"不適用"),"") | E76: =IF(ISNUMBER(E44),IF(AND(ISNUMBER(E44),ISNUMBER(E41),E41<>0,ISNUMBER(E34),ISNUMBER(E35),ISNUMBER(E32),ISNUMBER(E33)),E44/E41-((E34+E35)/2)/((E32+E33)/2),"不適用"),"") | F76: =IF(ISNUMBER(F44),IF(AND(ISNUMBER(F44),ISNUMBER(F41),F41<>0,ISNUMBER(F34),ISNUMBER(F35),ISNUMBER(F32),ISNUMBER(F33)),F44/F41-((F34+F35)/2)/((F32+F33)/2),"不適用"),"") | G76: =IF(ISNUMBER(G44),IF(AND(ISNUMBER(G44),ISNUMBER(G41),G41<>0,ISNUMBER(G34),ISNUMBER(G35),ISNUMBER(G32),ISNUMBER(G33)),G44/G41-((G34+G35)/2)/((G32+G33)/2),"不適用"),"") | H76: =IF(ISNUMBER(H44),IF(AND(ISNUMBER(H44),ISNUMBER(H41),H41<>0,ISNUMBER(H34),ISNUMBER(H35),ISNUMBER(H32),ISNUMBER(H33)),H44/H41-((H34+H35)/2)/((H32+H33)/2),"不適用"),"")
A77: 差距｜CapEx（毛額）｜模型 vs 共識 | B77: % | C77: 不適用 | D77: 不適用 | E77: 不適用 | F77: 不適用 | G77: 不適用 | H77: 不適用
A78: 差距｜CapEx（毛額）｜模型 vs 指引中點 | B78: % | C78: 不適用 | D78: 不適用 | E78: 不適用 | F78: 不適用 | G78: 不適用 | H78: 不適用
A79: 差距｜CapEx（毛額）｜實際 vs 模型 | B79: % | C79: =IF(ISNUMBER(C45),IF(AND(ISNUMBER(C36),C36<>0),C45/(C36)-1,"不適用"),"") | D79: =IF(ISNUMBER(D45),IF(AND(ISNUMBER(D36),D36<>0),D45/(D36)-1,"不適用"),"") | E79: =IF(ISNUMBER(E45),IF(AND(ISNUMBER(E36),E36<>0),E45/(E36)-1,"不適用"),"") | F79: =IF(ISNUMBER(F45),IF(AND(ISNUMBER(F36),F36<>0),F45/(F36)-1,"不適用"),"") | G79: =IF(ISNUMBER(G45),IF(AND(ISNUMBER(G36),G36<>0),G45/(G36)-1,"不適用"),"") | H79: =IF(ISNUMBER(H45),IF(AND(ISNUMBER(H36),H36<>0),H45/(H36)-1,"不適用"),"")
A80: 差距｜CapEx（毛額）｜實際 vs 共識 | B80: % | C80: =IF(ISNUMBER(C45),"不適用","") | D80: =IF(ISNUMBER(D45),"不適用","") | E80: =IF(ISNUMBER(E45),"不適用","") | F80: =IF(ISNUMBER(F45),"不適用","") | G80: =IF(ISNUMBER(G45),"不適用","") | H80: =IF(ISNUMBER(H45),"不適用","")
A81: 差距｜CapEx（毛額）｜實際 vs 指引中點 | B81: % | C81: =IF(ISNUMBER(C45),"不適用","") | D81: =IF(ISNUMBER(D45),"不適用","") | E81: =IF(ISNUMBER(E45),"不適用","") | F81: =IF(ISNUMBER(F45),"不適用","") | G81: =IF(ISNUMBER(G45),"不適用","") | H81: =IF(ISNUMBER(H45),"不適用","")
A82: 差距｜季末已連網 MW-IT｜模型 vs 共識 | B82: MW | C82: 不適用 | D82: 不適用 | E82: 不適用 | F82: 不適用 | G82: 不適用 | H82: 不適用
A83: 差距｜季末已連網 MW-IT｜模型 vs 指引中點 | B83: MW | C83: 不適用 | D83: 不適用 | E83: 不適用 | F83: 不適用 | G83: 不適用 | H83: 不適用
A84: 差距｜季末已連網 MW-IT｜實際 vs 模型 | B84: MW | C84: =IF(ISNUMBER(C46),IF(AND(ISNUMBER(C19)),C46-(C19),"不適用"),"") | D84: =IF(ISNUMBER(D46),IF(AND(ISNUMBER(D19)),D46-(D19),"不適用"),"") | E84: =IF(ISNUMBER(E46),IF(AND(ISNUMBER(E19)),E46-(E19),"不適用"),"") | F84: =IF(ISNUMBER(F46),IF(AND(ISNUMBER(F19)),F46-(F19),"不適用"),"") | G84: =IF(ISNUMBER(G46),IF(AND(ISNUMBER(G19)),G46-(G19),"不適用"),"") | H84: =IF(ISNUMBER(H46),IF(AND(ISNUMBER(H19)),H46-(H19),"不適用"),"")
A85: 差距｜季末已連網 MW-IT｜實際 vs 共識 | B85: MW | C85: =IF(ISNUMBER(C46),"不適用","") | D85: =IF(ISNUMBER(D46),"不適用","") | E85: =IF(ISNUMBER(E46),"不適用","") | F85: =IF(ISNUMBER(F46),"不適用","") | G85: =IF(ISNUMBER(G46),"不適用","") | H85: =IF(ISNUMBER(H46),"不適用","")
A86: 差距｜季末已連網 MW-IT｜實際 vs 指引中點 | B86: MW | C86: =IF(ISNUMBER(C46),"不適用","") | D86: =IF(ISNUMBER(D46),"不適用","") | E86: =IF(ISNUMBER(E46),"不適用","") | F86: =IF(ISNUMBER(F46),"不適用","") | G86: =IF(ISNUMBER(G46),"不適用","") | H86: =IF(ISNUMBER(H46),"不適用","")
A87: 合計基準｜營收｜vs 共識 | B87: US$bn | C87: =IF(COUNT(C37,D37)=2,C37+D37,"不適用") -> 不適用 | D87: =IF(COUNT(C37,D37)=2,C37+D37,"不適用") -> 不適用 | E87: =IF(COUNT(E37,F37,G37,H37)=4,E37+F37+G37+H37,"不適用") -> 不適用 | F87: =IF(COUNT(E37,F37,G37,H37)=4,E37+F37+G37+H37,"不適用") -> 不適用 | G87: =IF(COUNT(E37,F37,G37,H37)=4,E37+F37+G37+H37,"不適用") -> 不適用 | H87: =IF(COUNT(E37,F37,G37,H37)=4,E37+F37+G37+H37,"不適用") -> 不適用 | J87: 所屬期間的季度共識合計
A88: 拆解｜營收｜vs 共識｜水準 | B88: US$bn | C88: =IF(AND(ISNUMBER(C87),C87<>0,ISNUMBER(C37),ISNUMBER(C22)),(損益!C9-C87)*(C37)/C87,"不適用") -> 不適用 | D88: =IF(AND(ISNUMBER(D87),D87<>0,ISNUMBER(D37),ISNUMBER(D22)),(損益!C9-D87)*(D37)/D87,"不適用") -> 不適用 | E88: =IF(AND(ISNUMBER(E87),E87<>0,ISNUMBER(E37),ISNUMBER(E22)),(損益!D9-E87)*(E37)/E87,"不適用") -> 不適用 | F88: =IF(AND(ISNUMBER(F87),F87<>0,ISNUMBER(F37),ISNUMBER(F22)),(損益!D9-F87)*(F37)/F87,"不適用") -> 不適用 | G88: =IF(AND(ISNUMBER(G87),G87<>0,ISNUMBER(G37),ISNUMBER(G22)),(損益!D9-G87)*(G37)/G87,"不適用") -> 不適用 | H88: =IF(AND(ISNUMBER(H87),H87<>0,ISNUMBER(H37),ISNUMBER(H22)),(損益!D9-H87)*(H37)/H87,"不適用") -> 不適用 | J88: (模型期間 − 比較期間) × 比較的季占比
A89: 拆解｜營收｜vs 共識｜分配 | B89: US$bn | C89: =IF(AND(ISNUMBER(C87),C87<>0,ISNUMBER(C37),ISNUMBER(C22)),(C22/損益!C9-(C37)/C87)*損益!C9,"不適用") -> 不適用 | D89: =IF(AND(ISNUMBER(D87),D87<>0,ISNUMBER(D37),ISNUMBER(D22)),(D22/損益!C9-(D37)/D87)*損益!C9,"不適用") -> 不適用 | E89: =IF(AND(ISNUMBER(E87),E87<>0,ISNUMBER(E37),ISNUMBER(E22)),(E22/損益!D9-(E37)/E87)*損益!D9,"不適用") -> 不適用 | F89: =IF(AND(ISNUMBER(F87),F87<>0,ISNUMBER(F37),ISNUMBER(F22)),(F22/損益!D9-(F37)/F87)*損益!D9,"不適用") -> 不適用 | G89: =IF(AND(ISNUMBER(G87),G87<>0,ISNUMBER(G37),ISNUMBER(G22)),(G22/損益!D9-(G37)/G87)*損益!D9,"不適用") -> 不適用 | H89: =IF(AND(ISNUMBER(H87),H87<>0,ISNUMBER(H37),ISNUMBER(H22)),(H22/損益!D9-(H37)/H87)*損益!D9,"不適用") -> 不適用 | J89: (模型季占比 − 比較季占比) × 模型期間；水準＋分配＝季度差距
A90: 原因｜營收｜vs 共識 | C90: =IF(ISNUMBER(C47),IF(ABS(C47)>輸入與假設!$C$493,IF(ISNUMBER(C88),IF(ABS(C89)>ABS(C88),"營收 vs 共識 "&IF(C47<0,"−","+")&TEXT(ABS(C47)*100,"#,##0.0")&"%"&"：拆法（分配 "&IF(C89<0,"−","+")&IF(ABS(C89)<0,"−","")&"$"&TEXT(ABS(ABS(C89)),"#,##0.000")&"bn"&"（Q3 2026 占 2H26 "&TEXT((C22/損益!C9)*100,"#,##0.0")&"%"&"，共識合計 "&TEXT(((C37)/C87)*100,"#,##0.0")&"%"&"）；水準 "&IF(C88<0,"−","+")&IF(ABS(C88)<0,"−","")&"$"&TEXT(ABS(ABS(C88)),"#,##0.000")&"bn"&"）","營收 vs 共識 "&IF(C47<0,"−","+")&TEXT(ABS(C47)*100,"#,##0.0")&"%"&"：觀點（水準 "&IF(C88<0,"−","+")&IF(ABS(C88)<0,"−","")&"$"&TEXT(ABS(ABS(C88)),"#,##0.000")&"bn"&"（2H26 模型 "&IF(損益!C9<0,"−","")&"$"&TEXT(ABS(損益!C9),"#,##0.000")&"bn"&"，共識合計 "&IF(C87<0,"−","")&"$"&TEXT(ABS(C87),"#,##0.000")&"bn"&"）；分配 "&IF(C89<0,"−","+")&IF(ABS(C89)<0,"−","")&"$"&TEXT(ABS(ABS(C89)),"#,##0.000")&"bn"&"；"&"營收＝對外 AI 雲端（在役 MW × 每 MW 年收入，Tokenomics × k）＋各分部依近四季年增率收斂；年度總額線性分到各季，未建模第四季季節性"&"）"),"營收 vs 共識 "&IF(C47<0,"−","+")&TEXT(ABS(C47)*100,"#,##0.0")&"%"&"：觀點（"&"營收＝對外 AI 雲端（在役 MW × 每 MW 年收入，Tokenomics × k）＋各分部依近四季年增率收斂；年度總額線性分到各季，未建模第四季季節性"&"）"),""),"") | D90: =IF(ISNUMBER(D47),IF(ABS(D47)>輸入與假設!$C$493,IF(ISNUMBER(D88),IF(ABS(D89)>ABS(D88),"營收 vs 共識 "&IF(D47<0,"−","+")&TEXT(ABS(D47)*100,"#,##0.0")&"%"&"：拆法（分配 "&IF(D89<0,"−","+")&IF(ABS(D89)<0,"−","")&"$"&TEXT(ABS(ABS(D89)),"#,##0.000")&"bn"&"（Q4 2026 占 2H26 "&TEXT((D22/損益!C9)*100,"#,##0.0")&"%"&"，共識合計 "&TEXT(((D37)/D87)*100,"#,##0.0")&"%"&"）；水準 "&IF(D88<0,"−","+")&IF(ABS(D88)<0,"−","")&"$"&TEXT(ABS(ABS(D88)),"#,##0.000")&"bn"&"）","營收 vs 共識 "&IF(D47<0,"−","+")&TEXT(ABS(D47)*100,"#,##0.0")&"%"&"：觀點（水準 "&IF(D88<0,"−","+")&IF(ABS(D88)<0,"−","")&"$"&TEXT(ABS(ABS(D88)),"#,##0.000")&"bn"&"（2H26 模型 "&IF(損益!C9<0,"−","")&"$"&TEXT(ABS(損益!C9),"#,##0.000")&"bn"&"，共識合計 "&IF(D87<0,"−","")&"$"&TEXT(ABS(D87),"#,##0.000")&"bn"&"）；分配 "&IF(D89<0,"−","+")&IF(ABS(D89)<0,"−","")&"$"&TEXT(ABS(ABS(D89)),"#,##0.000")&"bn"&"；"&"營收＝對外 AI 雲端（在役 MW × 每 MW 年收入，Tokenomics × k）＋各分部依近四季年增率收斂；年度總額線性分到各季，未建模第四季季節性"&"）"),"營收 vs 共識 "&IF(D47<0,"−","+")&TEXT(ABS(D47)*100,"#,##0.0")&"%"&"：觀點（"&"營收＝對外 AI 雲端（在役 MW × 每 MW 年收入，Tokenomics × k）＋各分部依近四季年增率收斂；年度總額線性分到各季，未建模第四季季節性"&"）"),""),"") | E90: =IF(ISNUMBER(E47),IF(ABS(E47)>輸入與假設!$C$493,IF(ISNUMBER(E88),IF(ABS(E89)>ABS(E88),"營收 vs 共識 "&IF(E47<0,"−","+")&TEXT(ABS(E47)*100,"#,##0.0")&"%"&"：拆法（分配 "&IF(E89<0,"−","+")&IF(ABS(E89)<0,"−","")&"$"&TEXT(ABS(ABS(E89)),"#,##0.000")&"bn"&"（Q1 2027 占 2027 "&TEXT((E22/損益!D9)*100,"#,##0.0")&"%"&"，共識合計 "&TEXT(((E37)/E87)*100,"#,##0.0")&"%"&"）；水準 "&IF(E88<0,"−","+")&IF(ABS(E88)<0,"−","")&"$"&TEXT(ABS(ABS(E88)),"#,##0.000")&"bn"&"）","營收 vs 共識 "&IF(E47<0,"−","+")&TEXT(ABS(E47)*100,"#,##0.0")&"%"&"：觀點（水準 "&IF(E88<0,"−","+")&IF(ABS(E88)<0,"−","")&"$"&TEXT(ABS(ABS(E88)),"#,##0.000")&"bn"&"（2027 模型 "&IF(損益!D9<0,"−","")&"$"&TEXT(ABS(損益!D9),"#,##0.000")&"bn"&"，共識合計 "&IF(E87<0,"−","")&"$"&TEXT(ABS(E87),"#,##0.000")&"bn"&"）；分配 "&IF(E89<0,"−","+")&IF(ABS(E89)<0,"−","")&"$"&TEXT(ABS(ABS(E89)),"#,##0.000")&"bn"&"；"&"營收＝對外 AI 雲端（在役 MW × 每 MW 年收入，Tokenomics × k）＋各分部依近四季年增率收斂；年度總額線性分到各季，未建模第四季季節性"&"）"),"營收 vs 共識 "&IF(E47<0,"−","+")&TEXT(ABS(E47)*100,"#,##0.0")&"%"&"：觀點（"&"營收＝對外 AI 雲端（在役 MW × 每 MW 年收入，Tokenomics × k）＋各分部依近四季年增率收斂；年度總額線性分到各季，未建模第四季季節性"&"）"),""),"") | F90: =IF(ISNUMBER(F47),IF(ABS(F47)>輸入與假設!$C$493,IF(ISNUMBER(F88),IF(ABS(F89)>ABS(F88),"營收 vs 共識 "&IF(F47<0,"−","+")&TEXT(ABS(F47)*100,"#,##0.0")&"%"&"：拆法（分配 "&IF(F89<0,"−","+")&IF(ABS(F89)<0,"−","")&"$"&TEXT(ABS(ABS(F89)),"#,##0.000")&"bn"&"（Q2 2027 占 2027 "&TEXT((F22/損益!D9)*100,"#,##0.0")&"%"&"，共識合計 "&TEXT(((F37)/F87)*100,"#,##0.0")&"%"&"）；水準 "&IF(F88<0,"−","+")&IF(ABS(F88)<0,"−","")&"$"&TEXT(ABS(ABS(F88)),"#,##0.000")&"bn"&"）","營收 vs 共識 "&IF(F47<0,"−","+")&TEXT(ABS(F47)*100,"#,##0.0")&"%"&"：觀點（水準 "&IF(F88<0,"−","+")&IF(ABS(F88)<0,"−","")&"$"&TEXT(ABS(ABS(F88)),"#,##0.000")&"bn"&"（2027 模型 "&IF(損益!D9<0,"−","")&"$"&TEXT(ABS(損益!D9),"#,##0.000")&"bn"&"，共識合計 "&IF(F87<0,"−","")&"$"&TEXT(ABS(F87),"#,##0.000")&"bn"&"）；分配 "&IF(F89<0,"−","+")&IF(ABS(F89)<0,"−","")&"$"&TEXT(ABS(ABS(F89)),"#,##0.000")&"bn"&"；"&"營收＝對外 AI 雲端（在役 MW × 每 MW 年收入，Tokenomics × k）＋各分部依近四季年增率收斂；年度總額線性分到各季，未建模第四季季節性"&"）"),"營收 vs 共識 "&IF(F47<0,"−","+")&TEXT(ABS(F47)*100,"#,##0.0")&"%"&"：觀點（"&"營收＝對外 AI 雲端（在役 MW × 每 MW 年收入，Tokenomics × k）＋各分部依近四季年增率收斂；年度總額線性分到各季，未建模第四季季節性"&"）"),""),"") | G90: =IF(ISNUMBER(G47),IF(ABS(G47)>輸入與假設!$C$493,IF(ISNUMBER(G88),IF(ABS(G89)>ABS(G88),"營收 vs 共識 "&IF(G47<0,"−","+")&TEXT(ABS(G47)*100,"#,##0.0")&"%"&"：拆法（分配 "&IF(G89<0,"−","+")&IF(ABS(G89)<0,"−","")&"$"&TEXT(ABS(ABS(G89)),"#,##0.000")&"bn"&"（Q3 2027 占 2027 "&TEXT((G22/損益!D9)*100,"#,##0.0")&"%"&"，共識合計 "&TEXT(((G37)/G87)*100,"#,##0.0")&"%"&"）；水準 "&IF(G88<0,"−","+")&IF(ABS(G88)<0,"−","")&"$"&TEXT(ABS(ABS(G88)),"#,##0.000")&"bn"&"）","營收 vs 共識 "&IF(G47<0,"−","+")&TEXT(ABS(G47)*100,"#,##0.0")&"%"&"：觀點（水準 "&IF(G88<0,"−","+")&IF(ABS(G88)<0,"−","")&"$"&TEXT(ABS(ABS(G88)),"#,##0.000")&"bn"&"（2027 模型 "&IF(損益!D9<0,"−","")&"$"&TEXT(ABS(損益!D9),"#,##0.000")&"bn"&"，共識合計 "&IF(G87<0,"−","")&"$"&TEXT(ABS(G87),"#,##0.000")&"bn"&"）；分配 "&IF(G89<0,"−","+")&IF(ABS(G89)<0,"−","")&"$"&TEXT(ABS(ABS(G89)),"#,##0.000")&"bn"&"；"&"營收＝對外 AI 雲端（在役 MW × 每 MW 年收入，Tokenomics × k）＋各分部依近四季年增率收斂；年度總額線性分到各季，未建模第四季季節性"&"）"),"營收 vs 共識 "&IF(G47<0,"−","+")&TEXT(ABS(G47)*100,"#,##0.0")&"%"&"：觀點（"&"營收＝對外 AI 雲端（在役 MW × 每 MW 年收入，Tokenomics × k）＋各分部依近四季年增率收斂；年度總額線性分到各季，未建模第四季季節性"&"）"),""),"") | H90: =IF(ISNUMBER(H47),IF(ABS(H47)>輸入與假設!$C$493,IF(ISNUMBER(H88),IF(ABS(H89)>ABS(H88),"營收 vs 共識 "&IF(H47<0,"−","+")&TEXT(ABS(H47)*100,"#,##0.0")&"%"&"：拆法（分配 "&IF(H89<0,"−","+")&IF(ABS(H89)<0,"−","")&"$"&TEXT(ABS(ABS(H89)),"#,##0.000")&"bn"&"（Q4 2027 占 2027 "&TEXT((H22/損益!D9)*100,"#,##0.0")&"%"&"，共識合計 "&TEXT(((H37)/H87)*100,"#,##0.0")&"%"&"）；水準 "&IF(H88<0,"−","+")&IF(ABS(H88)<0,"−","")&"$"&TEXT(ABS(ABS(H88)),"#,##0.000")&"bn"&"）","營收 vs 共識 "&IF(H47<0,"−","+")&TEXT(ABS(H47)*100,"#,##0.0")&"%"&"：觀點（水準 "&IF(H88<0,"−","+")&IF(ABS(H88)<0,"−","")&"$"&TEXT(ABS(ABS(H88)),"#,##0.000")&"bn"&"（2027 模型 "&IF(損益!D9<0,"−","")&"$"&TEXT(ABS(損益!D9),"#,##0.000")&"bn"&"，共識合計 "&IF(H87<0,"−","")&"$"&TEXT(ABS(H87),"#,##0.000")&"bn"&"）；分配 "&IF(H89<0,"−","+")&IF(ABS(H89)<0,"−","")&"$"&TEXT(ABS(ABS(H89)),"#,##0.000")&"bn"&"；"&"營收＝對外 AI 雲端（在役 MW × 每 MW 年收入，Tokenomics × k）＋各分部依近四季年增率收斂；年度總額線性分到各季，未建模第四季季節性"&"）"),"營收 vs 共識 "&IF(H47<0,"−","+")&TEXT(ABS(H47)*100,"#,##0.0")&"%"&"：觀點（"&"營收＝對外 AI 雲端（在役 MW × 每 MW 年收入，Tokenomics × k）＋各分部依近四季年增率收斂；年度總額線性分到各季，未建模第四季季節性"&"）"),""),"")
A91: 原因類型｜營收｜vs 共識 | C91: =IF(ISNUMBER(C47),IF(ABS(C47)>輸入與假設!$C$493,IF(ISNUMBER(C88),IF(ABS(C89)>ABS(C88),"拆法","觀點"),"觀點"),""),"") | D91: =IF(ISNUMBER(D47),IF(ABS(D47)>輸入與假設!$C$493,IF(ISNUMBER(D88),IF(ABS(D89)>ABS(D88),"拆法","觀點"),"觀點"),""),"") | E91: =IF(ISNUMBER(E47),IF(ABS(E47)>輸入與假設!$C$493,IF(ISNUMBER(E88),IF(ABS(E89)>ABS(E88),"拆法","觀點"),"觀點"),""),"") | F91: =IF(ISNUMBER(F47),IF(ABS(F47)>輸入與假設!$C$493,IF(ISNUMBER(F88),IF(ABS(F89)>ABS(F88),"拆法","觀點"),"觀點"),""),"") | G91: =IF(ISNUMBER(G47),IF(ABS(G47)>輸入與假設!$C$493,IF(ISNUMBER(G88),IF(ABS(G89)>ABS(G88),"拆法","觀點"),"觀點"),""),"") | H91: =IF(ISNUMBER(H47),IF(ABS(H47)>輸入與假設!$C$493,IF(ISNUMBER(H88),IF(ABS(H89)>ABS(H88),"拆法","觀點"),"觀點"),""),"")
A92: 原因｜營收｜vs 指引中點 | C92: =IF(ISNUMBER(C48),IF(OR(ABS(C48)>輸入與假設!$C$493,C22>C33,C22<C32),"營收 vs 指引中點 "&IF(C48<0,"−","+")&TEXT(ABS(C48)*100,"#,##0.0")&"%"&"：觀點（"&"營收＝對外 AI 雲端（在役 MW × 每 MW 年收入，Tokenomics × k）＋各分部依近四季年增率收斂；年度總額線性分到各季，未建模第四季季節性"&"）",""),"") -> 營收 vs 指引中點 +9.1%：觀點（營收＝對外 AI 雲端（在役 MW × 每 MW 年收入，Tokenomics × k）＋各分部依近四季年增率收斂；年度總額線性分到各季，未建模第四季季節性） | D92: =IF(ISNUMBER(D48),IF(OR(ABS(D48)>輸入與假設!$C$493,D22>D33,D22<D32),"營收 vs 指引中點 "&IF(D48<0,"−","+")&TEXT(ABS(D48)*100,"#,##0.0")&"%"&"：觀點（"&"營收＝對外 AI 雲端（在役 MW × 每 MW 年收入，Tokenomics × k）＋各分部依近四季年增率收斂；年度總額線性分到各季，未建模第四季季節性"&"）",""),"") | E92: =IF(ISNUMBER(E48),IF(OR(ABS(E48)>輸入與假設!$C$493,E22>E33,E22<E32),"營收 vs 指引中點 "&IF(E48<0,"−","+")&TEXT(ABS(E48)*100,"#,##0.0")&"%"&"：觀點（"&"營收＝對外 AI 雲端（在役 MW × 每 MW 年收入，Tokenomics × k）＋各分部依近四季年增率收斂；年度總額線性分到各季，未建模第四季季節性"&"）",""),"") | F92: =IF(ISNUMBER(F48),IF(OR(ABS(F48)>輸入與假設!$C$493,F22>F33,F22<F32),"營收 vs 指引中點 "&IF(F48<0,"−","+")&TEXT(ABS(F48)*100,"#,##0.0")&"%"&"：觀點（"&"營收＝對外 AI 雲端（在役 MW × 每 MW 年收入，Tokenomics × k）＋各分部依近四季年增率收斂；年度總額線性分到各季，未建模第四季季節性"&"）",""),"") | G92: =IF(ISNUMBER(G48),IF(OR(ABS(G48)>輸入與假設!$C$493,G22>G33,G22<G32),"營收 vs 指引中點 "&IF(G48<0,"−","+")&TEXT(ABS(G48)*100,"#,##0.0")&"%"&"：觀點（"&"營收＝對外 AI 雲端（在役 MW × 每 MW 年收入，Tokenomics × k）＋各分部依近四季年增率收斂；年度總額線性分到各季，未建模第四季季節性"&"）",""),"") | H92: =IF(ISNUMBER(H48),IF(OR(ABS(H48)>輸入與假設!$C$493,H22>H33,H22<H32),"營收 vs 指引中點 "&IF(H48<0,"−","+")&TEXT(ABS(H48)*100,"#,##0.0")&"%"&"：觀點（"&"營收＝對外 AI 雲端（在役 MW × 每 MW 年收入，Tokenomics × k）＋各分部依近四季年增率收斂；年度總額線性分到各季，未建模第四季季節性"&"）",""),"")
A93: 原因類型｜營收｜vs 指引中點 | C93: =IF(ISNUMBER(C48),IF(OR(ABS(C48)>輸入與假設!$C$493,C22>C33,C22<C32),"觀點",""),"") -> 觀點 | D93: =IF(ISNUMBER(D48),IF(OR(ABS(D48)>輸入與假設!$C$493,D22>D33,D22<D32),"觀點",""),"") | E93: =IF(ISNUMBER(E48),IF(OR(ABS(E48)>輸入與假設!$C$493,E22>E33,E22<E32),"觀點",""),"") | F93: =IF(ISNUMBER(F48),IF(OR(ABS(F48)>輸入與假設!$C$493,F22>F33,F22<F32),"觀點",""),"") | G93: =IF(ISNUMBER(G48),IF(OR(ABS(G48)>輸入與假設!$C$493,G22>G33,G22<G32),"觀點",""),"") | H93: =IF(ISNUMBER(H48),IF(OR(ABS(H48)>輸入與假設!$C$493,H22>H33,H22<H32),"觀點",""),"")
A94: 原因｜營收｜實際 vs 模型 | C94: =IF(ISNUMBER(C49),IF(ABS(C49)>輸入與假設!$C$493,"營收 實際 vs 模型 "&IF(C49<0,"−","+")&TEXT(ABS(C49)*100,"#,##0.0")&"%"&"：觀點（"&"營收＝對外 AI 雲端（在役 MW × 每 MW 年收入，Tokenomics × k）＋各分部依近四季年增率收斂；年度總額線性分到各季，未建模第四季季節性"&"）",""),"") | D94: =IF(ISNUMBER(D49),IF(ABS(D49)>輸入與假設!$C$493,"營收 實際 vs 模型 "&IF(D49<0,"−","+")&TEXT(ABS(D49)*100,"#,##0.0")&"%"&"：觀點（"&"營收＝對外 AI 雲端（在役 MW × 每 MW 年收入，Tokenomics × k）＋各分部依近四季年增率收斂；年度總額線性分到各季，未建模第四季季節性"&"）",""),"") | E94: =IF(ISNUMBER(E49),IF(ABS(E49)>輸入與假設!$C$493,"營收 實際 vs 模型 "&IF(E49<0,"−","+")&TEXT(ABS(E49)*100,"#,##0.0")&"%"&"：觀點（"&"營收＝對外 AI 雲端（在役 MW × 每 MW 年收入，Tokenomics × k）＋各分部依近四季年增率收斂；年度總額線性分到各季，未建模第四季季節性"&"）",""),"") | F94: =IF(ISNUMBER(F49),IF(ABS(F49)>輸入與假設!$C$493,"營收 實際 vs 模型 "&IF(F49<0,"−","+")&TEXT(ABS(F49)*100,"#,##0.0")&"%"&"：觀點（"&"營收＝對外 AI 雲端（在役 MW × 每 MW 年收入，Tokenomics × k）＋各分部依近四季年增率收斂；年度總額線性分到各季，未建模第四季季節性"&"）",""),"") | G94: =IF(ISNUMBER(G49),IF(ABS(G49)>輸入與假設!$C$493,"營收 實際 vs 模型 "&IF(G49<0,"−","+")&TEXT(ABS(G49)*100,"#,##0.0")&"%"&"：觀點（"&"營收＝對外 AI 雲端（在役 MW × 每 MW 年收入，Tokenomics × k）＋各分部依近四季年增率收斂；年度總額線性分到各季，未建模第四季季節性"&"）",""),"") | H94: =IF(ISNUMBER(H49),IF(ABS(H49)>輸入與假設!$C$493,"營收 實際 vs 模型 "&IF(H49<0,"−","+")&TEXT(ABS(H49)*100,"#,##0.0")&"%"&"：觀點（"&"營收＝對外 AI 雲端（在役 MW × 每 MW 年收入，Tokenomics × k）＋各分部依近四季年增率收斂；年度總額線性分到各季，未建模第四季季節性"&"）",""),"")
A95: 原因類型｜營收｜實際 vs 模型 | C95: =IF(ISNUMBER(C49),IF(ABS(C49)>輸入與假設!$C$493,"觀點",""),"") | D95: =IF(ISNUMBER(D49),IF(ABS(D49)>輸入與假設!$C$493,"觀點",""),"") | E95: =IF(ISNUMBER(E49),IF(ABS(E49)>輸入與假設!$C$493,"觀點",""),"") | F95: =IF(ISNUMBER(F49),IF(ABS(F49)>輸入與假設!$C$493,"觀點",""),"") | G95: =IF(ISNUMBER(G49),IF(ABS(G49)>輸入與假設!$C$493,"觀點",""),"") | H95: =IF(ISNUMBER(H49),IF(ABS(H49)>輸入與假設!$C$493,"觀點",""),"")
A96: 合計基準｜調整後 EBITDA｜vs 共識 | B96: US$bn | C96: =IF(COUNT(C38,D38)=2,C38+D38,"不適用") -> 不適用 | D96: =IF(COUNT(C38,D38)=2,C38+D38,"不適用") -> 不適用 | E96: =IF(COUNT(E38,F38,G38,H38)=4,E38+F38+G38+H38,"不適用") -> 不適用 | F96: =IF(COUNT(E38,F38,G38,H38)=4,E38+F38+G38+H38,"不適用") -> 不適用 | G96: =IF(COUNT(E38,F38,G38,H38)=4,E38+F38+G38+H38,"不適用") -> 不適用 | H96: =IF(COUNT(E38,F38,G38,H38)=4,E38+F38+G38+H38,"不適用") -> 不適用 | J96: 所屬期間的季度共識合計
A97: 拆解｜調整後 EBITDA｜vs 共識｜水準 | B97: US$bn | C97: =IF(AND(ISNUMBER(C96),C96<>0,ISNUMBER(C38),ISNUMBER(C28)),(損益!C22-C96)*(C38)/C96,"不適用") -> 不適用 | D97: =IF(AND(ISNUMBER(D96),D96<>0,ISNUMBER(D38),ISNUMBER(D28)),(損益!C22-D96)*(D38)/D96,"不適用") -> 不適用 | E97: =IF(AND(ISNUMBER(E96),E96<>0,ISNUMBER(E38),ISNUMBER(E28)),(損益!D22-E96)*(E38)/E96,"不適用") -> 不適用 | F97: =IF(AND(ISNUMBER(F96),F96<>0,ISNUMBER(F38),ISNUMBER(F28)),(損益!D22-F96)*(F38)/F96,"不適用") -> 不適用 | G97: =IF(AND(ISNUMBER(G96),G96<>0,ISNUMBER(G38),ISNUMBER(G28)),(損益!D22-G96)*(G38)/G96,"不適用") -> 不適用 | H97: =IF(AND(ISNUMBER(H96),H96<>0,ISNUMBER(H38),ISNUMBER(H28)),(損益!D22-H96)*(H38)/H96,"不適用") -> 不適用 | J97: (模型期間 − 比較期間) × 比較的季占比
A98: 拆解｜調整後 EBITDA｜vs 共識｜分配 | B98: US$bn | C98: =IF(AND(ISNUMBER(C96),C96<>0,ISNUMBER(C38),ISNUMBER(C28)),(C28/損益!C22-(C38)/C96)*損益!C22,"不適用") -> 不適用 | D98: =IF(AND(ISNUMBER(D96),D96<>0,ISNUMBER(D38),ISNUMBER(D28)),(D28/損益!C22-(D38)/D96)*損益!C22,"不適用") -> 不適用 | E98: =IF(AND(ISNUMBER(E96),E96<>0,ISNUMBER(E38),ISNUMBER(E28)),(E28/損益!D22-(E38)/E96)*損益!D22,"不適用") -> 不適用 | F98: =IF(AND(ISNUMBER(F96),F96<>0,ISNUMBER(F38),ISNUMBER(F28)),(F28/損益!D22-(F38)/F96)*損益!D22,"不適用") -> 不適用 | G98: =IF(AND(ISNUMBER(G96),G96<>0,ISNUMBER(G38),ISNUMBER(G28)),(G28/損益!D22-(G38)/G96)*損益!D22,"不適用") -> 不適用 | H98: =IF(AND(ISNUMBER(H96),H96<>0,ISNUMBER(H38),ISNUMBER(H28)),(H28/損益!D22-(H38)/H96)*損益!D22,"不適用") -> 不適用 | J98: (模型季占比 − 比較季占比) × 模型期間；水準＋分配＝季度差距
A99: 原因｜調整後 EBITDA｜vs 共識 | C99: =IF(ISNUMBER(C52),IF(IF(ISNUMBER(C57),ABS(C57)>輸入與假設!$C$494,OR(AND(C38<>0,ABS(C52)>輸入與假設!$C$493*ABS(C38)),AND(C38=0,C52<>0))),IF(ISNUMBER(C97),IF(ABS(C98)>ABS(C97),"調整後 EBITDA vs 共識 "&IF(C52<0,"−","+")&IF(ABS(C52)<0,"−","")&"$"&TEXT(ABS(ABS(C52)),"#,##0.00")&"bn"&IF(ISNUMBER(C57),"／"&IF(C57<0,"−","+")&TEXT(ABS(C57)*100,"#,##0.0")&"pt","")&"：拆法（分配 "&IF(C98<0,"−","+")&IF(ABS(C98)<0,"−","")&"$"&TEXT(ABS(ABS(C98)),"#,##0.000")&"bn"&"（Q3 2026 占 2H26 "&TEXT((C28/損益!C22)*100,"#,##0.0")&"%"&"，共識合計 "&TEXT(((C38)/C96)*100,"#,##0.0")&"%"&"）；水準 "&IF(C97<0,"−","+")&IF(ABS(C97)<0,"−","")&"$"&TEXT(ABS(ABS(C97)),"#,##0.000")&"bn"&"）","調整後 EBITDA vs 共識 "&IF(C52<0,"−","+")&IF(ABS(C52)<0,"−","")&"$"&TEXT(ABS(ABS(C52)),"#,##0.00")&"bn"&IF(ISNUMBER(C57),"／"&IF(C57<0,"−","+")&TEXT(ABS(C57)*100,"#,##0.0")&"pt","")&"：觀點（水準 "&IF(C97<0,"−","+")&IF(ABS(C97)<0,"−","")&"$"&TEXT(ABS(ABS(C97)),"#,##0.000")&"bn"&"（2H26 模型 "&IF(損益!C22<0,"−","")&"$"&TEXT(ABS(損益!C22),"#,##0.000")&"bn"&"，共識合計 "&IF(C96<0,"−","")&"$"&TEXT(ABS(C96),"#,##0.000")&"bn"&"）；分配 "&IF(C98<0,"−","+")&IF(ABS(C98)<0,"−","")&"$"&TEXT(ABS(ABS(C98)),"#,##0.000")&"bn"&"；"&"模型 EBITDA 率 "&IF((C27)<0,"−","")&TEXT(ABS((C27))*100,"#,##0.0")&"%"&"；EBITDA＝分部營業利益＋分攤 D&A 與 AI 雲端 Tokenomics 由下而上營運成本"&"）"),"調整後 EBITDA vs 共識 "&IF(C52<0,"−","+")&IF(ABS(C52)<0,"−","")&"$"&TEXT(ABS(ABS(C52)),"#,##0.00")&"bn"&IF(ISNUMBER(C57),"／"&IF(C57<0,"−","+")&TEXT(ABS(C57)*100,"#,##0.0")&"pt","")&"：觀點（"&"模型 EBITDA 率 "&IF((C27)<0,"−","")&TEXT(ABS((C27))*100,"#,##0.0")&"%"&"；EBITDA＝分部營業利益＋分攤 D&A 與 AI 雲端 Tokenomics 由下而上營運成本"&"）"),""),"") | D99: =IF(ISNUMBER(D52),IF(IF(ISNUMBER(D57),ABS(D57)>輸入與假設!$C$494,OR(AND(D38<>0,ABS(D52)>輸入與假設!$C$493*ABS(D38)),AND(D38=0,D52<>0))),IF(ISNUMBER(D97),IF(ABS(D98)>ABS(D97),"調整後 EBITDA vs 共識 "&IF(D52<0,"−","+")&IF(ABS(D52)<0,"−","")&"$"&TEXT(ABS(ABS(D52)),"#,##0.00")&"bn"&IF(ISNUMBER(D57),"／"&IF(D57<0,"−","+")&TEXT(ABS(D57)*100,"#,##0.0")&"pt","")&"：拆法（分配 "&IF(D98<0,"−","+")&IF(ABS(D98)<0,"−","")&"$"&TEXT(ABS(ABS(D98)),"#,##0.000")&"bn"&"（Q4 2026 占 2H26 "&TEXT((D28/損益!C22)*100,"#,##0.0")&"%"&"，共識合計 "&TEXT(((D38)/D96)*100,"#,##0.0")&"%"&"）；水準 "&IF(D97<0,"−","+")&IF(ABS(D97)<0,"−","")&"$"&TEXT(ABS(ABS(D97)),"#,##0.000")&"bn"&"）","調整後 EBITDA vs 共識 "&IF(D52<0,"−","+")&IF(ABS(D52)<0,"−","")&"$"&TEXT(ABS(ABS(D52)),"#,##0.00")&"bn"&IF(ISNUMBER(D57),"／"&IF(D57<0,"−","+")&TEXT(ABS(D57)*100,"#,##0.0")&"pt","")&"：觀點（水準 "&IF(D97<0,"−","+")&IF(ABS(D97)<0,"−","")&"$"&TEXT(ABS(ABS(D97)),"#,##0.000")&"bn"&"（2H26 模型 "&IF(損益!C22<0,"−","")&"$"&TEXT(ABS(損益!C22),"#,##0.000")&"bn"&"，共識合計 "&IF(D96<0,"−","")&"$"&TEXT(ABS(D96),"#,##0.000")&"bn"&"）；分配 "&IF(D98<0,"−","+")&IF(ABS(D98)<0,"−","")&"$"&TEXT(ABS(ABS(D98)),"#,##0.000")&"bn"&"；"&"模型 EBITDA 率 "&IF((D27)<0,"−","")&TEXT(ABS((D27))*100,"#,##0.0")&"%"&"；EBITDA＝分部營業利益＋分攤 D&A 與 AI 雲端 Tokenomics 由下而上營運成本"&"）"),"調整後 EBITDA vs 共識 "&IF(D52<0,"−","+")&IF(ABS(D52)<0,"−","")&"$"&TEXT(ABS(ABS(D52)),"#,##0.00")&"bn"&IF(ISNUMBER(D57),"／"&IF(D57<0,"−","+")&TEXT(ABS(D57)*100,"#,##0.0")&"pt","")&"：觀點（"&"模型 EBITDA 率 "&IF((D27)<0,"−","")&TEXT(ABS((D27))*100,"#,##0.0")&"%"&"；EBITDA＝分部營業利益＋分攤 D&A 與 AI 雲端 Tokenomics 由下而上營運成本"&"）"),""),"") | E99: =IF(ISNUMBER(E52),IF(IF(ISNUMBER(E57),ABS(E57)>輸入與假設!$C$494,OR(AND(E38<>0,ABS(E52)>輸入與假設!$C$493*ABS(E38)),AND(E38=0,E52<>0))),IF(ISNUMBER(E97),IF(ABS(E98)>ABS(E97),"調整後 EBITDA vs 共識 "&IF(E52<0,"−","+")&IF(ABS(E52)<0,"−","")&"$"&TEXT(ABS(ABS(E52)),"#,##0.00")&"bn"&IF(ISNUMBER(E57),"／"&IF(E57<0,"−","+")&TEXT(ABS(E57)*100,"#,##0.0")&"pt","")&"：拆法（分配 "&IF(E98<0,"−","+")&IF(ABS(E98)<0,"−","")&"$"&TEXT(ABS(ABS(E98)),"#,##0.000")&"bn"&"（Q1 2027 占 2027 "&TEXT((E28/損益!D22)*100,"#,##0.0")&"%"&"，共識合計 "&TEXT(((E38)/E96)*100,"#,##0.0")&"%"&"）；水準 "&IF(E97<0,"−","+")&IF(ABS(E97)<0,"−","")&"$"&TEXT(ABS(ABS(E97)),"#,##0.000")&"bn"&"）","調整後 EBITDA vs 共識 "&IF(E52<0,"−","+")&IF(ABS(E52)<0,"−","")&"$"&TEXT(ABS(ABS(E52)),"#,##0.00")&"bn"&IF(ISNUMBER(E57),"／"&IF(E57<0,"−","+")&TEXT(ABS(E57)*100,"#,##0.0")&"pt","")&"：觀點（水準 "&IF(E97<0,"−","+")&IF(ABS(E97)<0,"−","")&"$"&TEXT(ABS(ABS(E97)),"#,##0.000")&"bn"&"（2027 模型 "&IF(損益!D22<0,"−","")&"$"&TEXT(ABS(損益!D22),"#,##0.000")&"bn"&"，共識合計 "&IF(E96<0,"−","")&"$"&TEXT(ABS(E96),"#,##0.000")&"bn"&"）；分配 "&IF(E98<0,"−","+")&IF(ABS(E98)<0,"−","")&"$"&TEXT(ABS(ABS(E98)),"#,##0.000")&"bn"&"；"&"模型 EBITDA 率 "&IF((E27)<0,"−","")&TEXT(ABS((E27))*100,"#,##0.0")&"%"&"；EBITDA＝分部營業利益＋分攤 D&A 與 AI 雲端 Tokenomics 由下而上營運成本"&"）"),"調整後 EBITDA vs 共識 "&IF(E52<0,"−","+")&IF(ABS(E52)<0,"−","")&"$"&TEXT(ABS(ABS(E52)),"#,##0.00")&"bn"&IF(ISNUMBER(E57),"／"&IF(E57<0,"−","+")&TEXT(ABS(E57)*100,"#,##0.0")&"pt","")&"：觀點（"&"模型 EBITDA 率 "&IF((E27)<0,"−","")&TEXT(ABS((E27))*100,"#,##0.0")&"%"&"；EBITDA＝分部營業利益＋分攤 D&A 與 AI 雲端 Tokenomics 由下而上營運成本"&"）"),""),"") | F99: =IF(ISNUMBER(F52),IF(IF(ISNUMBER(F57),ABS(F57)>輸入與假設!$C$494,OR(AND(F38<>0,ABS(F52)>輸入與假設!$C$493*ABS(F38)),AND(F38=0,F52<>0))),IF(ISNUMBER(F97),IF(ABS(F98)>ABS(F97),"調整後 EBITDA vs 共識 "&IF(F52<0,"−","+")&IF(ABS(F52)<0,"−","")&"$"&TEXT(ABS(ABS(F52)),"#,##0.00")&"bn"&IF(ISNUMBER(F57),"／"&IF(F57<0,"−","+")&TEXT(ABS(F57)*100,"#,##0.0")&"pt","")&"：拆法（分配 "&IF(F98<0,"−","+")&IF(ABS(F98)<0,"−","")&"$"&TEXT(ABS(ABS(F98)),"#,##0.000")&"bn"&"（Q2 2027 占 2027 "&TEXT((F28/損益!D22)*100,"#,##0.0")&"%"&"，共識合計 "&TEXT(((F38)/F96)*100,"#,##0.0")&"%"&"）；水準 "&IF(F97<0,"−","+")&IF(ABS(F97)<0,"−","")&"$"&TEXT(ABS(ABS(F97)),"#,##0.000")&"bn"&"）","調整後 EBITDA vs 共識 "&IF(F52<0,"−","+")&IF(ABS(F52)<0,"−","")&"$"&TEXT(ABS(ABS(F52)),"#,##0.00")&"bn"&IF(ISNUMBER(F57),"／"&IF(F57<0,"−","+")&TEXT(ABS(F57)*100,"#,##0.0")&"pt","")&"：觀點（水準 "&IF(F97<0,"−","+")&IF(ABS(F97)<0,"−","")&"$"&TEXT(ABS(ABS(F97)),"#,##0.000")&"bn"&"（2027 模型 "&IF(損益!D22<0,"−","")&"$"&TEXT(ABS(損益!D22),"#,##0.000")&"bn"&"，共識合計 "&IF(F96<0,"−","")&"$"&TEXT(ABS(F96),"#,##0.000")&"bn"&"）；分配 "&IF(F98<0,"−","+")&IF(ABS(F98)<0,"−","")&"$"&TEXT(ABS(ABS(F98)),"#,##0.000")&"bn"&"；"&"模型 EBITDA 率 "&IF((F27)<0,"−","")&TEXT(ABS((F27))*100,"#,##0.0")&"%"&"；EBITDA＝分部營業利益＋分攤 D&A 與 AI 雲端 Tokenomics 由下而上營運成本"&"）"),"調整後 EBITDA vs 共識 "&IF(F52<0,"−","+")&IF(ABS(F52)<0,"−","")&"$"&TEXT(ABS(ABS(F52)),"#,##0.00")&"bn"&IF(ISNUMBER(F57),"／"&IF(F57<0,"−","+")&TEXT(ABS(F57)*100,"#,##0.0")&"pt","")&"：觀點（"&"模型 EBITDA 率 "&IF((F27)<0,"−","")&TEXT(ABS((F27))*100,"#,##0.0")&"%"&"；EBITDA＝分部營業利益＋分攤 D&A 與 AI 雲端 Tokenomics 由下而上營運成本"&"）"),""),"") | G99: =IF(ISNUMBER(G52),IF(IF(ISNUMBER(G57),ABS(G57)>輸入與假設!$C$494,OR(AND(G38<>0,ABS(G52)>輸入與假設!$C$493*ABS(G38)),AND(G38=0,G52<>0))),IF(ISNUMBER(G97),IF(ABS(G98)>ABS(G97),"調整後 EBITDA vs 共識 "&IF(G52<0,"−","+")&IF(ABS(G52)<0,"−","")&"$"&TEXT(ABS(ABS(G52)),"#,##0.00")&"bn"&IF(ISNUMBER(G57),"／"&IF(G57<0,"−","+")&TEXT(ABS(G57)*100,"#,##0.0")&"pt","")&"：拆法（分配 "&IF(G98<0,"−","+")&IF(ABS(G98)<0,"−","")&"$"&TEXT(ABS(ABS(G98)),"#,##0.000")&"bn"&"（Q3 2027 占 2027 "&TEXT((G28/損益!D22)*100,"#,##0.0")&"%"&"，共識合計 "&TEXT(((G38)/G96)*100,"#,##0.0")&"%"&"）；水準 "&IF(G97<0,"−","+")&IF(ABS(G97)<0,"−","")&"$"&TEXT(ABS(ABS(G97)),"#,##0.000")&"bn"&"）","調整後 EBITDA vs 共識 "&IF(G52<0,"−","+")&IF(ABS(G52)<0,"−","")&"$"&TEXT(ABS(ABS(G52)),"#,##0.00")&"bn"&IF(ISNUMBER(G57),"／"&IF(G57<0,"−","+")&TEXT(ABS(G57)*100,"#,##0.0")&"pt","")&"：觀點（水準 "&IF(G97<0,"−","+")&IF(ABS(G97)<0,"−","")&"$"&TEXT(ABS(ABS(G97)),"#,##0.000")&"bn"&"（2027 模型 "&IF(損益!D22<0,"−","")&"$"&TEXT(ABS(損益!D22),"#,##0.000")&"bn"&"，共識合計 "&IF(G96<0,"−","")&"$"&TEXT(ABS(G96),"#,##0.000")&"bn"&"）；分配 "&IF(G98<0,"−","+")&IF(ABS(G98)<0,"−","")&"$"&TEXT(ABS(ABS(G98)),"#,##0.000")&"bn"&"；"&"模型 EBITDA 率 "&IF((G27)<0,"−","")&TEXT(ABS((G27))*100,"#,##0.0")&"%"&"；EBITDA＝分部營業利益＋分攤 D&A 與 AI 雲端 Tokenomics 由下而上營運成本"&"）"),"調整後 EBITDA vs 共識 "&IF(G52<0,"−","+")&IF(ABS(G52)<0,"−","")&"$"&TEXT(ABS(ABS(G52)),"#,##0.00")&"bn"&IF(ISNUMBER(G57),"／"&IF(G57<0,"−","+")&TEXT(ABS(G57)*100,"#,##0.0")&"pt","")&"：觀點（"&"模型 EBITDA 率 "&IF((G27)<0,"−","")&TEXT(ABS((G27))*100,"#,##0.0")&"%"&"；EBITDA＝分部營業利益＋分攤 D&A 與 AI 雲端 Tokenomics 由下而上營運成本"&"）"),""),"") | H99: =IF(ISNUMBER(H52),IF(IF(ISNUMBER(H57),ABS(H57)>輸入與假設!$C$494,OR(AND(H38<>0,ABS(H52)>輸入與假設!$C$493*ABS(H38)),AND(H38=0,H52<>0))),IF(ISNUMBER(H97),IF(ABS(H98)>ABS(H97),"調整後 EBITDA vs 共識 "&IF(H52<0,"−","+")&IF(ABS(H52)<0,"−","")&"$"&TEXT(ABS(ABS(H52)),"#,##0.00")&"bn"&IF(ISNUMBER(H57),"／"&IF(H57<0,"−","+")&TEXT(ABS(H57)*100,"#,##0.0")&"pt","")&"：拆法（分配 "&IF(H98<0,"−","+")&IF(ABS(H98)<0,"−","")&"$"&TEXT(ABS(ABS(H98)),"#,##0.000")&"bn"&"（Q4 2027 占 2027 "&TEXT((H28/損益!D22)*100,"#,##0.0")&"%"&"，共識合計 "&TEXT(((H38)/H96)*100,"#,##0.0")&"%"&"）；水準 "&IF(H97<0,"−","+")&IF(ABS(H97)<0,"−","")&"$"&TEXT(ABS(ABS(H97)),"#,##0.000")&"bn"&"）","調整後 EBITDA vs 共識 "&IF(H52<0,"−","+")&IF(ABS(H52)<0,"−","")&"$"&TEXT(ABS(ABS(H52)),"#,##0.00")&"bn"&IF(ISNUMBER(H57),"／"&IF(H57<0,"−","+")&TEXT(ABS(H57)*100,"#,##0.0")&"pt","")&"：觀點（水準 "&IF(H97<0,"−","+")&IF(ABS(H97)<0,"−","")&"$"&TEXT(ABS(ABS(H97)),"#,##0.000")&"bn"&"（2027 模型 "&IF(損益!D22<0,"−","")&"$"&TEXT(ABS(損益!D22),"#,##0.000")&"bn"&"，共識合計 "&IF(H96<0,"−","")&"$"&TEXT(ABS(H96),"#,##0.000")&"bn"&"）；分配 "&IF(H98<0,"−","+")&IF(ABS(H98)<0,"−","")&"$"&TEXT(ABS(ABS(H98)),"#,##0.000")&"bn"&"；"&"模型 EBITDA 率 "&IF((H27)<0,"−","")&TEXT(ABS((H27))*100,"#,##0.0")&"%"&"；EBITDA＝分部營業利益＋分攤 D&A 與 AI 雲端 Tokenomics 由下而上營運成本"&"）"),"調整後 EBITDA vs 共識 "&IF(H52<0,"−","+")&IF(ABS(H52)<0,"−","")&"$"&TEXT(ABS(ABS(H52)),"#,##0.00")&"bn"&IF(ISNUMBER(H57),"／"&IF(H57<0,"−","+")&TEXT(ABS(H57)*100,"#,##0.0")&"pt","")&"：觀點（"&"模型 EBITDA 率 "&IF((H27)<0,"−","")&TEXT(ABS((H27))*100,"#,##0.0")&"%"&"；EBITDA＝分部營業利益＋分攤 D&A 與 AI 雲端 Tokenomics 由下而上營運成本"&"）"),""),"")
A100: 原因類型｜調整後 EBITDA｜vs 共識 | C100: =IF(ISNUMBER(C52),IF(IF(ISNUMBER(C57),ABS(C57)>輸入與假設!$C$494,OR(AND(C38<>0,ABS(C52)>輸入與假設!$C$493*ABS(C38)),AND(C38=0,C52<>0))),IF(ISNUMBER(C97),IF(ABS(C98)>ABS(C97),"拆法","觀點"),"觀點"),""),"") | D100: =IF(ISNUMBER(D52),IF(IF(ISNUMBER(D57),ABS(D57)>輸入與假設!$C$494,OR(AND(D38<>0,ABS(D52)>輸入與假設!$C$493*ABS(D38)),AND(D38=0,D52<>0))),IF(ISNUMBER(D97),IF(ABS(D98)>ABS(D97),"拆法","觀點"),"觀點"),""),"") | E100: =IF(ISNUMBER(E52),IF(IF(ISNUMBER(E57),ABS(E57)>輸入與假設!$C$494,OR(AND(E38<>0,ABS(E52)>輸入與假設!$C$493*ABS(E38)),AND(E38=0,E52<>0))),IF(ISNUMBER(E97),IF(ABS(E98)>ABS(E97),"拆法","觀點"),"觀點"),""),"") | F100: =IF(ISNUMBER(F52),IF(IF(ISNUMBER(F57),ABS(F57)>輸入與假設!$C$494,OR(AND(F38<>0,ABS(F52)>輸入與假設!$C$493*ABS(F38)),AND(F38=0,F52<>0))),IF(ISNUMBER(F97),IF(ABS(F98)>ABS(F97),"拆法","觀點"),"觀點"),""),"") | G100: =IF(ISNUMBER(G52),IF(IF(ISNUMBER(G57),ABS(G57)>輸入與假設!$C$494,OR(AND(G38<>0,ABS(G52)>輸入與假設!$C$493*ABS(G38)),AND(G38=0,G52<>0))),IF(ISNUMBER(G97),IF(ABS(G98)>ABS(G97),"拆法","觀點"),"觀點"),""),"") | H100: =IF(ISNUMBER(H52),IF(IF(ISNUMBER(H57),ABS(H57)>輸入與假設!$C$494,OR(AND(H38<>0,ABS(H52)>輸入與假設!$C$493*ABS(H38)),AND(H38=0,H52<>0))),IF(ISNUMBER(H97),IF(ABS(H98)>ABS(H97),"拆法","觀點"),"觀點"),""),"")
A101: 原因｜調整後 EBITDA｜vs 指引中點
A102: 原因類型｜調整後 EBITDA｜vs 指引中點
...

Sheet 運營_產能與收入
A1: 產能與收入 — 合約排程 vs 機房產能
A2: 兩條線獨立產生後相減：排程>容量→瓶頸（收不到）；容量>排程→剩餘產能（要靠新簽約賣掉）
A3: 2026 欄口徑：MW 為年底存量；標示「（模型期）」的收入列只含 2026 下半年——RPO 桶自 2026-06-30 起算，1H 收入已實現、不再受產能約束。1H 實際單列，兩者相加即 2026 全年（見本頁「FY26 全年」列）。
A5: 項目 | B5: 單位 | C5: 2026 | D5: 2027 | E5: 2028 | F5: 2029 | G5: 2030 | I5: 公式／來源說明
A6: 模型期間 | C6: ="2026-07-01~12-31" -> 2026-07-01~12-31 | D6: ="2027 全年" -> 2027 全年 | E6: ="2028 全年" -> 2028 全年 | F6: ="2029 全年" -> 2029 全年 | G6: ="2030 全年" -> 2030 全年 | I6: 2026 的模型期只有下半年；1H 已實現的營收單列於下方
A7: 模型期長度（年） | C7: =輸入與假設!C$34 -> 0.5 | D7: =輸入與假設!D$34 -> 1 | E7: =輸入與假設!E$34 -> 1 | F7: =輸入與假設!F$34 -> 1 | G7: =輸入與假設!G$34 -> 1 | I7: 只用於下方三處：容量上限、電力、維護——把年率換算成該期金額
A8: （A）機房：容量上限
A9: Accepted MW（已驗收，單調不減） | B9: MW | C9: =MAX(0,輸入與假設!C$36) -> 3894.4 | D9: =MAX(輸入與假設!D$36,C9) -> 7523.2 | E9: =MAX(輸入與假設!E$36,D9) -> 11152 | F9: =MAX(輸入與假設!F$36,E9) -> 14780.8 | G9: =MAX(輸入與假設!G$36,F9) -> 18409.6 | I9: 引擎規則：不得低於前期（產能不會消失）
A10: Billable MW（上限為 Accepted） | B10: MW | C10: =MIN(MAX(0,輸入與假設!C$37),C9) -> 3894 | D10: =MIN(MAX(0,輸入與假設!D$37),D9) -> 7523 | E10: =MIN(MAX(0,輸入與假設!E$37),E9) -> 11152 | F10: =MIN(MAX(0,輸入與假設!F$37),F9) -> 14780.8 | G10: =MIN(MAX(0,輸入與假設!G$37),G9) -> 18409.6 | I10: 引擎規則：可計費不得超過已驗收
A11: Billable MW（延誤後，計費用） | B11: MW | C11: =IF($C$50<=0,$C$10,輸入與假設!$C$29+($C$10-輸入與假設!$C$29)*MAX(0,MIN(1,($C$51-$C$50/12-0)/$C$7))+($D$10-$C$10)*MAX(0,MIN(1,($C$51-$C$50/12-$C$51)/$D$7))+($E$10-$D$10)*MAX(0,MIN(1,($C$51-$C$50/12-$D$51)/$E$7))+($F$10-$E$10)*MAX(0,MIN(1,($C$51-$C$50/12-$E$51)/$F$7))+($G$10-$F$10)*MAX(0,MIN(1,($C$51-$C$50/12-$F$51)/$G$7))) -> 3894 | D11: =IF($C$50<=0,$D$10,輸入與假設!$C$29+($C$10-輸入與假設!$C$29)*MAX(0,MIN(1,($D$51-$C$50/12-0)/$C$7))+($D$10-$C$10)*MAX(0,MIN(1,($D$51-$C$50/12-$C$51)/$D$7))+($E$10-$D$10)*MAX(0,MIN(1,($D$51-$C$50/12-$D$51)/$E$7))+($F$10-$E$10)*MAX(0,MIN(1,($D$51-$C$50/12-$E$51)/$F$7))+($G$10-$F$10)*MAX(0,MIN(1,($D$51-$C$50/12-$F$51)/$G$7))) -> 7523 | E11: =IF($C$50<=0,$E$10,輸入與假設!$C$29+($C$10-輸入與假設!$C$29)*MAX(0,MIN(1,($E$51-$C$50/12-0)/$C$7))+($D$10-$C$10)*MAX(0,MIN(1,($E$51-$C$50/12-$C$51)/$D$7))+($E$10-$D$10)*MAX(0,MIN(1,($E$51-$C$50/12-$D$51)/$E$7))+($F$10-$E$10)*MAX(0,MIN(1,($E$51-$C$50/12-$E$51)/$F$7))+($G$10-$F$10)*MAX(0,MIN(1,($E$51-$C$50/12-$F$51)/$G$7))) -> 11152 | F11: =IF($C$50<=0,$F$10,輸入與假設!$C$29+($C$10-輸入與假設!$C$29)*MAX(0,MIN(1,($F$51-$C$50/12-0)/$C$7))+($D$10-$C$10)*MAX(0,MIN(1,($F$51-$C$50/12-$C$51)/$D$7))+($E$10-$D$10)*MAX(0,MIN(1,($F$51-$C$50/12-$D$51)/$E$7))+($F$10-$E$10)*MAX(0,MIN(1,($F$51-$C$50/12-$E$51)/$F$7))+($G$10-$F$10)*MAX(0,MIN(1,($F$51-$C$50/12-$F$51)/$G$7))) -> 14780.8 | G11: =IF($C$50<=0,$G$10,輸入與假設!$C$29+($C$10-輸入與假設!$C$29)*MAX(0,MIN(1,($G$51-$C$50/12-0)/$C$7))+($D$10-$C$10)*MAX(0,MIN(1,($G$51-$C$50/12-$C$51)/$D$7))+($E$10-$D$10)*MAX(0,MIN(1,($G$51-$C$50/12-$D$51)/$E$7))+($F$10-$E$10)*MAX(0,MIN(1,($G$51-$C$50/12-$E$51)/$F$7))+($G$10-$F$10)*MAX(0,MIN(1,($G$51-$C$50/12-$F$51)/$G$7))) -> 18409.6 | I11: ＝上列往後平移建設延誤月數（以期間長度線性內插；評價日之前取期初校準值）；延誤 0 時＝上列；見（E）區（v0.2）
A12: 期初在役 MW | B12: MW | C12: =輸入與假設!$C$29 -> 2080 | D12: =C11 -> 3894 | E12: =D11 -> 7523 | F12: =E11 -> 11152 | G12: =F11 -> 14780.8 | I12: 前期期末＝本期期初（延誤後）
A13: 平均在役 MW（2026 欄為下半年平均） | B13: MW | C13: =IF(輸入與假設!$C$30=1,(C12+C11)/2,C11) -> 2987 | D13: =IF(輸入與假設!$C$30=1,(D12+D11)/2,D11) -> 5708.5 | E13: =IF(輸入與假設!$C$30=1,(E12+E11)/2,E11) -> 9337.5 | F13: =IF(輸入與假設!$C$30=1,(F12+F11)/2,F11) -> 12966.4 | G13: =IF(輸入與假設!$C$30=1,(G12+G11)/2,G11) -> 16595.2 | I13: 開關在輸入頁：1＝(期初+期末)/2，0＝期末全期化
A14: 利用率 | B14: % | C14: =輸入與假設!C$38 -> 1 | D14: =輸入與假設!D$38 -> 1 | E14: =輸入與假設!E$38 -> 1 | F14: =輸入與假設!F$38 -> 1 | G14: =輸入與假設!G$38 -> 1
A15: 每 MW 年收入 | B15: US$bn/MW | C15: =輸入與假設!C$39 -> 0.0097857081 | D15: =輸入與假設!D$39 -> 0.010218303 | E15: =輸入與假設!E$39 -> 0.010473071 | F15: =輸入與假設!F$39 -> 0.010602745 | G15: =輸入與假設!G$39 -> 0.010681297
A16: 容量上限（模型期最多能交付的收入） | B16: US$bn | C16: =C13*輸入與假設!C$39*輸入與假設!$C$32*輸入與假設!C$38*C7 -> 14.614955 | D16: =D13*輸入與假設!D$39*輸入與假設!$C$32*輸入與假設!D$38*D7 -> 58.33118 | E16: =E13*輸入與假設!E$39*輸入與假設!$C$32*輸入與假設!E$38*E7 -> 97.792303 | F16: =F13*輸入與假設!F$39*輸入與假設!$C$32*輸入與假設!F$38*F7 -> 137.47943 | G16: =G13*輸入與假設!G$39*輸入與假設!$C$32*輸入與假設!G$38*G7 -> 177.25826 | I16: ＝平均在役 MW × 每 MW 年收入 × 利用率 × 期間係數。只看機房，不看合約
A17: （B）合約：排程 RPO
A18: 排程 RPO（模型期，依季報桶分攤） | B18: US$bn | C18: =(輸入與假設!$C$24+輸入與假設!$C$25)*(輸入與假設!C$35/輸入與假設!$C$27)*輸入與假設!$C$26 -> 0 | D18: =(輸入與假設!$C$24+輸入與假設!$C$25)*(輸入與假設!D$35/輸入與假設!$C$27)*輸入與假設!$C$26 -> 0 | E18: =(輸入與假設!$C$24+輸入與假設!$C$25)*(輸入與假設!E$35/輸入與假設!$C$27)*輸入與假設!$C$26 -> 0 | F18: =(輸入與假設!$C$24+輸入與假設!$C$25)*(輸入與假設!F$35/輸入與假設!$C$27)*輸入與假設!$C$26 -> 0 | G18: =(輸入與假設!$C$24+輸入與假設!$C$25)*(輸入與假設!G$35/輸入與假設!$C$27)*輸入與假設!$C$26 -> 0 | I18: ＝(6/30 RPO＋評價日後新增)×本期權重÷權重合計×五期認列比例。只看合約，不看機房
A19: （C）兩條線相減
A20: 產能瓶頸（模型期：排程 − 容量） | B20: US$bn | C20: =MAX(0,C18-C16) -> 0 | D20: =MAX(0,D18-D16) -> 0 | E20: =MAX(0,E18-E16) -> 0 | F20: =MAX(0,F18-F16) -> 0 | G20: =MAX(0,G18-G16) -> 0 | I20: 合約有、機房沒有 → 本期收不到，且不遞延到下期（保守處理）
A21: 期初 RPO 轉換收入（模型期） | B21: US$bn | C21: =C18-C20 -> 0 | D21: =D18-D20 -> 0 | E21: =E18-E20 -> 0 | F21: =F18-F20 -> 0 | G21: =G18-G20 -> 0 | I21: ＝排程 − 瓶頸。當瓶頸>0 時，此值恆等於容量上限
A22: 未被期初 RPO 占用的產能 | B22: US$bn | C22: =MAX(0,C16-C18) -> 14.614955 | D22: =MAX(0,D16-D18) -> 58.33118 | E22: =MAX(0,E16-E18) -> 97.792303 | F22: =MAX(0,F16-F18) -> 137.47943 | G22: =MAX(0,G16-G18) -> 177.25826 | I22: 容量 − 排程。機房有、期初合約沒占滿 → 要靠新簽約
A23: 新產能簽約率 | B23: % | C23: =IF(輸入與假設!$C$31="mw",1,輸入與假設!C$40) -> 1 | D23: =IF(輸入與假設!$C$31="mw",1,輸入與假設!D$40) -> 1 | E23: =IF(輸入與假設!$C$31="mw",1,輸入與假設!E$40) -> 1 | F23: =IF(輸入與假設!$C$31="mw",1,輸入與假設!F$40) -> 1 | G23: =IF(輸入與假設!$C$31="mw",1,輸入與假設!G$40) -> 1 | I23: MW 驅動時固定 100%
A24: 新簽約收入 | B24: US$bn | C24: =C22*C23 -> 14.614955 | D24: =D22*D23 -> 58.33118 | E24: =E22*E23 -> 97.792303 | F24: =F22*F23 -> 137.47943 | G24: =G22*G23 -> 177.25826 | I24: 超出期初 RPO 的產能收入（MW 驅動，簽約率 100%）
A25: 未售產能（浪費） | B25: US$bn | C25: =MAX(0,C16-C21-C24) -> 0 | D25: =MAX(0,D16-D21-D24) -> 0 | E25: =MAX(0,E16-E21-E24) -> 0 | F25: =MAX(0,F16-F21-F24) -> 0 | G25: =MAX(0,G16-G21-G24) -> 0 | I25: 蓋好但賣不掉（MW 驅動時為 0）
A26: 損益用算力收入（模型期＝RPO 轉換＋新簽約） | B26: US$bn | C26: =C21+C24 -> 14.614955 | D26: =D21+D24 -> 58.33118 | E26: =E21+E24 -> 97.792303 | F26: =F21+F24 -> 137.47943 | G26: =G21+G24 -> 177.25826 | I26: 損益與評價頁的算力收入由此連結，確保現金與損益同一組數字
A27: 核對：算力收入 − 平均在役 MW × 每 MW × 利用率 × 期間 | B27: US$bn | C27: =C26-C13*輸入與假設!C$39*輸入與假設!$C$32*輸入與假設!C$38*C7 -> 0 | D27: =D26-D13*輸入與假設!D$39*輸入與假設!$C$32*輸入與假設!D$38*D7 -> 0 | E27: =E26-E13*輸入與假設!E$39*輸入與假設!$C$32*輸入與假設!E$38*E7 -> 0 | F27: =F26-F13*輸入與假設!F$39*輸入與假設!$C$32*輸入與假設!F$38*F7 -> 0 | G27: =G26-G13*輸入與假設!G$39*輸入與假設!$C$32*輸入與假設!G$38*G7 -> 0 | I27: MW 驅動時應為 0：營收可追溯為 MW × 每 MW 年收入 × 利用率（v0.1b）
A28: 對照：評價日起 36 個月營收權重 | B28: % | C28: 1 | D28: 1 | E28: 1 | F28: 0.5 | G28: 0 | I28: RPO 36 個月內轉換的對照用（只作對照，不驅動營收）
A29: 對照：評價日起 36 個月 MW 驅動營收 | B29: US$bn | C29: =C26*C28 -> 14.614955 | D29: =D26*D28 -> 58.33118 | E29: =E26*E28 -> 97.792303 | F29: =F26*F28 -> 68.739714 | G29: =G26*G28 -> 0 | I29: 合計對照季報 RPO 496 × 36 個月內 46.875%（含非 AI 事業 RPO）；差額不回推每 MW 單價
A30: 1H26 實際營收（季報，已實現） | B30: US$bn | C30: =輸入與假設!$C$425 -> 382.125 | D30: =0 -> 0 | E30: =0 -> 0 | F30: =0 -> 0 | G30: =0 -> 0 | I30: 2026-01-01 至 06-30 已認列營收。已實現，不受下半年產能約束，故不進入上方的瓶頸計算
A31: 2026 全年總營收（1H 實際＋模型期算力＋服務＋非 AI 事業） | B31: US$bn | C31: =C30+C26+輸入與假設!C$43+輸入與假設!C$194 -> 834.21909 | D31: =D30+D26+輸入與假設!D$43+輸入與假設!D$194 -> 973.5439 | E31: =E30+E26+輸入與假設!E$43+輸入與假設!E$194 -> 1113.4726 | F31: =F30+F26+輸入與假設!F$43+輸入與假設!F$194 -> 1244.8551 | G31: =G30+G26+輸入與假設!G$43+輸入與假設!G$194 -> 1362.3771 | I31: 2026 欄對照公司全年指引 未給全年營收指引；2027 以後即為該年度總營收
A32: （D）收入 → 現金：三道折扣
A33: 客戶違約率 | B33: % | C33: =輸入與假設!C$41 -> 0 | D33: =輸入與假設!D$41 -> 0 | E33: =輸入與假設!E$41 -> 0 | F33: =輸入與假設!F$41 -> 0 | G33: =輸入與假設!G$41 -> 0
A34: 回收率 | B34: % | C34: =輸入與假設!C$42 -> 0.5 | D34: =輸入與假設!D$42 -> 0.5 | E34: =輸入與假設!E$42 -> 0.5 | F34: =輸入與假設!F$42 -> 0.5 | G34: =輸入與假設!G$42 -> 0.5
A35: 信用損失（期初 RPO 部分） | B35: US$bn | C35: =C21*輸入與假設!C$41*(1-輸入與假設!C$42) -> 0 | D35: =D21*輸入與假設!D$41*(1-輸入與假設!D$42) -> 0 | E35: =E21*輸入與假設!E$41*(1-輸入與假設!E$42) -> 0 | F35: =F21*輸入與假設!F$41*(1-輸入與假設!F$42) -> 0 | G35: =G21*輸入與假設!G$41*(1-輸入與假設!G$42) -> 0 | I35: ＝收入 × 違約率 × (1−回收率)
A36: 收現（期初 RPO 部分） | B36: US$bn | C36: =C21-C35 -> 0 | D36: =D21-D35 -> 0 | E36: =E21-E35 -> 0 | F36: =F21-F35 -> 0 | G36: =G21-G35 -> 0
A37: EBITDA 率（損益與資金共用） | B37: % | C37: =輸入與假設!C$204 -> 0.80253284 | D37: =輸入與假設!D$204 -> 0.80721101 | E37: =輸入與假設!E$204 -> 0.80978531 | F37: =輸入與假設!F$204 -> 0.81104808 | G37: =輸入與假設!G$204 -> 0.81179812 | I37: 起始→穩態線性爬升
A38: 模型期總營收（算力＋服務） | B38: US$bn | C38: =C26+輸入與假設!C$43 -> 14.614955 | D38: =D26+輸入與假設!D$43 -> 58.33118 | E38: =E26+輸入與假設!E$43 -> 97.792303 | F38: =F26+輸入與假設!F$43 -> 137.47943 | G38: =G26+輸入與假設!G$43 -> 177.25826
A39: EBITDAR 率（EBITDA 率＋租金÷營收） | B39: % | C39: =輸入與假設!C$204 -> 0.80253284 | D39: =輸入與假設!D$204 -> 0.80721101 | E39: =輸入與假設!E$204 -> 0.80978531 | F39: =輸入與假設!F$204 -> 0.81104808 | G39: =輸入與假設!G$204 -> 0.81179812 | I39: 租金前的 EBITDA 率。EBITDA 已扣租金，而資金模型把租金列在支出端，所以要加回，避免重複扣除
A40: RPO 現金（可支應資本用途） | B40: US$bn | C40: =C36*C39 -> 0 | D40: =D36*D39 -> 0 | E40: =E36*E39 -> 0 | F40: =F36*F39 -> 0 | G40: =G36*G39 -> 0 | I40: ×EBITDAR 率。租金與利息在支出頁單獨列示
A41: 新簽約現金 | B41: US$bn | C41: =C24*(1-輸入與假設!C$41*(1-輸入與假設!C$42))*C39 -> 11.728981 | D41: =D24*(1-輸入與假設!D$41*(1-輸入與假設!D$42))*D39 -> 47.085571 | E41: =E24*(1-輸入與假設!E$41*(1-輸入與假設!E$42))*E39 -> 79.19077 | F41: =F24*(1-輸入與假設!F$41*(1-輸入與假設!F$42))*F39 -> 111.50243 | G41: =G24*(1-輸入與假設!G$41*(1-輸入與假設!G$42))*G39 -> 143.89792 | I41: 同樣扣信用損失、乘 EBITDAR 率
A43: 讀法：2026（2H）與 2027 瓶頸>0，合約多於機房；2028 起反轉，收入愈來愈靠『新簽約收入』這一列。
A44: 把『新產能簽約率』調到 0，就能看到只靠期初 RPO 的資金缺口有多大——這是最重要的一個壓力測試。
A46: （E）建設延誤（v0.2）：計費 MW 往後平移；GPU 資本支出與客戶出資照原時程；折舊自投入使用時點起算
A47: 建設延誤月數｜保守 第三方可辨識站點 | B47: 月 | C47: 0 | I47: company.json → scenarios.delayMonths；依據見該欄 note [Assumed]
A48: 建設延誤月數｜基準 依資本支出指引 | B48: 月 | C48: 0 | I48: company.json → scenarios.delayMonths；依據見該欄 note [Assumed]
A49: 建設延誤月數｜積極 依公司容量目標 | B49: 月 | C49: 0 | I49: company.json → scenarios.delayMonths；依據見該欄 note [Assumed]
A50: 建設延誤月數（目前情境） | B50: 月 | C50: =CHOOSE(輸入與假設!$C$5,運營_產能與收入!$C$47,運營_產能與收入!$C$48,運營_產能與收入!$C$49) -> 0 | I50: ＝依『輸入與假設』A 區情境選擇器；0＝不延誤（＝v0.1）
A51: 期末時點（評價日起，年） | B51: 年 | C51: =SUM($C$7:C7) -> 0.5 | D51: =SUM($C$7:D7) -> 1.5 | E51: =SUM($C$7:E7) -> 2.5 | F51: =SUM($C$7:F7) -> 3.5 | G51: =SUM($C$7:G7) -> 4.5 | I51: ＝累計期間長度
A52: 成長型 CapEx 累計（原時程，評價日起） | B52: US$bn | C52: =SUM(輸入與假設!$C$253:C$253) -> 123.69 | D52: =SUM(輸入與假設!$C$253:D$253) -> 399.91582 | E52: =SUM(輸入與假設!$C$253:E$253) -> 691.57938 | F52: =SUM(輸入與假設!$C$253:F$253) -> 991.7183 | G52: =SUM(輸入與假設!$C$253:G$253) -> 1298.8803 | I52: GPU 與網通照原併網時程採購、交貨等電（客戶出資覆蓋比同樣依原時程）
A53: 已投入使用累計（延誤後） | B53: US$bn | C53: =IF($C$50<=0,$C$52,0+($C$52-0)*MAX(0,MIN(1,($C$51-$C$50/12-0)/$C$7))+($D$52-$C$52)*MAX(0,MIN(1,($C$51-$C$50/12-$C$51)/$D$7))+($E$52-$D$52)*MAX(0,MIN(1,($C$51-$C$50/12-$D$51)/$E$7))+($F$52-$E$52)*MAX(0,MIN(1,($C$51-$C$50/12-$E$51)/$F$7))+($G$52-$F$52)*MAX(0,MIN(1,($C$51-$C$50/12-$F$51)/$G$7))) -> 123.69 | D53: =IF($C$50<=0,$D$52,0+($C$52-0)*MAX(0,MIN(1,($D$51-$C$50/12-0)/$C$7))+($D$52-$C$52)*MAX(0,MIN(1,($D$51-$C$50/12-$C$51)/$D$7))+($E$52-$D$52)*MAX(0,MIN(1,($D$51-$C$50/12-$D$51)/$E$7))+($F$52-$E$52)*MAX(0,MIN(1,($D$51-$C$50/12-$E$51)/$F$7))+($G$52-$F$52)*MAX(0,MIN(1,($D$51-$C$50/12-$F$51)/$G$7))) -> 399.91582 | E53: =IF($C$50<=0,$E$52,0+($C$52-0)*MAX(0,MIN(1,($E$51-$C$50/12-0)/$C$7))+($D$52-$C$52)*MAX(0,MIN(1,($E$51-$C$50/12-$C$51)/$D$7))+($E$52-$D$52)*MAX(0,MIN(1,($E$51-$C$50/12-$D$51)/$E$7))+($F$52-$E$52)*MAX(0,MIN(1,($E$51-$C$50/12-$E$51)/$F$7))+($G$52-$F$52)*MAX(0,MIN(1,($E$51-$C$50/12-$F$51)/$G$7))) -> 691.57938 | F53: =IF($C$50<=0,$F$52,0+($C$52-0)*MAX(0,MIN(1,($F$51-$C$50/12-0)/$C$7))+($D$52-$C$52)*MAX(0,MIN(1,($F$51-$C$50/12-$C$51)/$D$7))+($E$52-$D$52)*MAX(0,MIN(1,($F$51-$C$50/12-$D$51)/$E$7))+($F$52-$E$52)*MAX(0,MIN(1,($F$51-$C$50/12-$E$51)/$F$7))+($G$52-$F$52)*MAX(0,MIN(1,($F$51-$C$50/12-$F$51)/$G$7))) -> 991.7183 | G53: =IF($C$50<=0,$G$52,0+($C$52-0)*MAX(0,MIN(1,($G$51-$C$50/12-0)/$C$7))+($D$52-$C$52)*MAX(0,MIN(1,($G$51-$C$50/12-$C$51)/$D$7))+($E$52-$D$52)*MAX(0,MIN(1,($G$51-$C$50/12-$D$51)/$E$7))+($F$52-$E$52)*MAX(0,MIN(1,($G$51-$C$50/12-$E$51)/$F$7))+($G$52-$F$52)*MAX(0,MIN(1,($G$51-$C$50/12-$F$51)/$G$7))) -> 1298.8803 | I53: ＝上列往後平移建設延誤月數（線性內插）；延誤 0 時＝上列
A54: 本期投入使用的成長型 CapEx（折舊基礎） | B54: US$bn | C54: =C53 -> 123.69 | D54: =D53-C53 -> 276.22582 | E54: =E53-D53 -> 291.66355 | F54: =F53-E53 -> 300.13892 | G54: =G53-F53 -> 307.16205 | I54: 車隊折舊自投入使用時點起算（『輸入與假設』期初毛 PP&E 與 D&A 引用此列）
A55: 閒置資本（已支出未產生收入，期末） | B55: US$bn | C55: =C52-C53 -> 0 | D55: =D52-D53 -> 0 | E55: =E52-E53 -> 0 | F55: =F52-F53 -> 0 | G55: =G52-G53 -> 0 | I55: ＝原時程累計 − 已投入使用累計；延誤 0 時為 0。一頁摘要以一句呈現峰值
A56: 未起租租約起租連動比例（delayLink） | B56: % | C56: 0 | I56: 未起租租金中此比例的起租時點隨延誤月數後移（開發商交付晚），其餘照原時程（company.json → leases.uncommenced.delayLink）[Assumed]；替代 0／1
A57: 延誤罰則（應計費而未計費營收的 %） | B57: % | C57: 0 | I57: 公司未揭露合約條款：預設 0（不存在／未揭露）；敏感度 5%／10%（company.json → defaults.delayPenalty）[Assumed]
A58: 表外現金租金：全部隨延誤平移（對照） | B58: US$bn | C58: =輸入與假設!$C$19/輸入與假設!$C$21/輸入與假設!$C$22/4*((MIN(MAX(0,輸入與假設!C$235-(輸入與假設!$C$20+運營_產能與收入!$C$50/3)),輸入與假設!$C$21)*(MIN(MAX(0,輸入與假設!C$235-(輸入與假設!$C$20+運營_產能與收入!$C$50/3)),輸入與假設!$C$21)+1)/2+輸入與假設!$C$21*MAX(0,MAX(0,輸入與假設!C$235-(輸入與假設!$C$20+運營_產能與收入!$C$50/3))-輸入與假設!$C$21))-(MIN(MAX(0,0-(輸入與假設!$C$20+運營_產能與收入!$C$50/3)),輸入與假設!$C$21)*(MIN(MAX(0,0-(輸入與假設!$C$20+運營_產能與收入!$C$50/3)),輸入與假設!$C$21)+1)/2+輸入與假設!$C$21*MAX(0,MAX(0,0-(輸入與假設!$C$20+運營_產能與收入!$C$50/3))-輸入與假設!$C$21))) -> 1.7442458 | D58: =輸入與假設!$C$19/輸入與假設!$C$21/輸入與假設!$C$22/4*((MIN(MAX(0,輸入與假設!D$235-(輸入與假設!$C$20+運營_產能與收入!$C$50/3)),輸入與假設!$C$21)*(MIN(MAX(0,輸入與假設!D$235-(輸入與假設!$C$20+運營_產能與收入!$C$50/3)),輸入與假設!$C$21)+1)/2+輸入與假設!$C$21*MAX(0,MAX(0,輸入與假設!D$235-(輸入與假設!$C$20+運營_產能與收入!$C$50/3))-輸入與假設!$C$21))-(MIN(MAX(0,輸入與假設!C$235-(輸入與假設!$C$20+運營_產能與收入!$C$50/3)),輸入與假設!$C$21)*(MIN(MAX(0,輸入與假設!C$235-(輸入與假設!$C$20+運營_產能與收入!$C$50/3)),輸入與假設!$C$21)+1)/2+輸入與假設!$C$21*MAX(0,MAX(0,輸入與假設!C$235-(輸入與假設!$C$20+運營_產能與收入!$C$50/3))-輸入與假設!$C$21))) -> 8.7212288 | E58: =輸入與假設!$C$19/輸入與假設!$C$21/輸入與假設!$C$22/4*((MIN(MAX(0,輸入與假設!E$235-(輸入與假設!$C$20+運營_產能與收入!$C$50/3)),輸入與假設!$C$21)*(MIN(MAX(0,輸入與假設!E$235-(輸入與假設!$C$20+運營_產能與收入!$C$50/3)),輸入與假設!$C$21)+1)/2+輸入與假設!$C$21*MAX(0,MAX(0,輸入與假設!E$235-(輸入與假設!$C$20+運營_產能與收入!$C$50/3))-輸入與假設!$C$21))-(MIN(MAX(0,輸入與假設!D$235-(輸入與假設!$C$20+運營_產能與收入!$C$50/3)),輸入與假設!$C$21)*(MIN(MAX(0,輸入與假設!D$235-(輸入與假設!$C$20+運營_產能與收入!$C$50/3)),輸入與假設!$C$21)+1)/2+輸入與假設!$C$21*MAX(0,MAX(0,輸入與假設!D$235-(輸入與假設!$C$20+運營_產能與收入!$C$50/3))-輸入與假設!$C$21))) -> 9.3026441 | F58: =輸入與假設!$C$19/輸入與假設!$C$21/輸入與假設!$C$22/4*((MIN(MAX(0,輸入與假設!F$235-(輸入與假設!$C$20+運營_產能與收入!$C$50/3)),輸入與假設!$C$21)*(MIN(MAX(0,輸入與假設!F$235-(輸入與假設!$C$20+運營_產能與收入!$C$50/3)),輸入與假設!$C$21)+1)/2+輸入與假設!$C$21*MAX(0,MAX(0,輸入與假設!F$235-(輸入與假設!$C$20+運營_產能與收入!$C$50/3))-輸入與假設!$C$21))-(MIN(MAX(0,輸入與假設!E$235-(輸入與假設!$C$20+運營_產能與收入!$C$50/3)),輸入與假設!$C$21)*(MIN(MAX(0,輸入與假設!E$235-(輸入與假設!$C$20+運營_產能與收入!$C$50/3)),輸入與假設!$C$21)+1)/2+輸入與假設!$C$21*MAX(0,MAX(0,輸入與假設!E$235-(輸入與假設!$C$20+運營_產能與收入!$C$50/3))-輸入與假設!$C$21))) -> 9.3026441 | G58: =輸入與假設!$C$19/輸入與假設!$C$21/輸入與假設!$C$22/4*((MIN(MAX(0,輸入與假設!G$235-(輸入與假設!$C$20+運營_產能與收入!$C$50/3)),輸入與假設!$C$21)*(MIN(MAX(0,輸入與假設!G$235-(輸入與假設!$C$20+運營_產能與收入!$C$50/3)),輸入與假設!$C$21)+1)/2+輸入與假設!$C$21*MAX(0,MAX(0,輸入與假設!G$235-(輸入與假設!$C$20+運營_產能與收入!$C$50/3))-輸入與假設!$C$21))-(MIN(MAX(0,輸入與假設!F$235-(輸入與假設!$C$20+運營_產能與收入!$C$50/3)),輸入與假設!$C$21)*(MIN(MAX(0,輸入與假設!F$235-(輸入與假設!$C$20+運營_產能與收入!$C$50/3)),輸入與假設!$C$21)+1)/2+輸入與假設!$C$21*MAX(0,MAX(0,輸入與假設!F$235-(輸入與假設!$C$20+運營_產能與收入!$C$50/3))-輸入與假設!$C$21))) -> 9.3026441 | I58: ＝未起租排程的起算季延後 延誤月數 ÷ 3 季（其餘同『輸入與假設』表外現金租金）
A59: 表外現金租金（未起租，延誤連動後） | B59: US$bn | C59: =IF(OR(運營_產能與收入!$C$50<=0,運營_產能與收入!$C$56<=0),輸入與假設!C$236,(1-運營_產能與收入!$C$56)*輸入與假設!C$236+運營_產能與收入!$C$56*C58) -> 1.7442458 | D59: =IF(OR(運營_產能與收入!$C$50<=0,運營_產能與收入!$C$56<=0),輸入與假設!D$236,(1-運營_產能與收入!$C$56)*輸入與假設!D$236+運營_產能與收入!$C$56*D58) -> 8.7212288 | E59: =IF(OR(運營_產能與收入!$C$50<=0,運營_產能與收入!$C$56<=0),輸入與假設!E$236,(1-運營_產能與收入!$C$56)*輸入與假設!E$236+運營_產能與收入!$C$56*E58) -> 9.3026441 | F59: =IF(OR(運營_產能與收入!$C$50<=0,運營_產能與收入!$C$56<=0),輸入與假設!F$236,(1-運營_產能與收入!$C$56)*輸入與假設!F$236+運營_產能與收入!$C$56*F58) -> 9.3026441 | G59: =IF(OR(運營_產能與收入!$C$50<=0,運營_產能與收入!$C$56<=0),輸入與假設!G$236,(1-運營_產能與收入!$C$56)*輸入與假設!G$236+運營_產能與收入!$C$56*G58) -> 9.3026441 | I59: ＝(1 − 連動比例)× 原排程＋連動比例 × 平移後排程；延誤 0 時＝原排程（『各期收支』租金引用此列）
A60: 容量上限（未延誤，對照） | B60: US$bn | C60: =IF(輸入與假設!$C$30=1,(輸入與假設!$C$29+C10)/2,C10)*輸入與假設!C$39*輸入與假設!$C$32*輸入與假設!C$38*C7 -> 14.614955 | D60: =IF(輸入與假設!$C$30=1,(C10+D10)/2,D10)*輸入與假設!D$39*輸入與假設!$C$32*輸入與假設!D$38*D7 -> 58.33118 | E60: =IF(輸入與假設!$C$30=1,(D10+E10)/2,E10)*輸入與假設!E$39*輸入與假設!$C$32*輸入與假設!E$38*E7 -> 97.792303 | F60: =IF(輸入與假設!$C$30=1,(E10+F10)/2,F10)*輸入與假設!F$39*輸入與假設!$C$32*輸入與假設!F$38*F7 -> 137.47943 | G60: =IF(輸入與假設!$C$30=1,(F10+G10)/2,G10)*輸入與假設!G$39*輸入與假設!$C$32*輸入與假設!G$38*G7 -> 177.25826 | I60: ＝未延誤的平均可計費 MW × 每 MW 年收入 × 利用率 × 期間長度
A61: 應計費而未計費營收（延誤造成） | B61: US$bn | C61: =IF(運營_產能與收入!$C$50<=0,0,MAX(0,C60-C16)) -> 0 | D61: =IF(運營_產能與收入!$C$50<=0,0,MAX(0,D60-D16)) -> 0 | E61: =IF(運營_產能與收入!$C$50<=0,0,MAX(0,E60-E16)) -> 0 | F61: =IF(運營_產能與收入!$C$50<=0,0,MAX(0,F60-F16)) -> 0 | G61: =IF(運營_產能與收入!$C$50<=0,0,MAX(0,G60-G16)) -> 0 | I61: ＝未延誤容量上限 − 延誤後容量上限
A62: 延誤罰則（營業費用） | B62: US$bn | C62: =運營_產能與收入!$C$57*C61 -> 0 | D62: =運營_產能與收入!$C$57*D61 -> 0 | E62: =運營_產能與收入!$C$57*E61 -> 0 | F62: =運營_產能與收入!$C$57*F61 -> 0 | G62: =運營_產能與收入!$C$57*G61 -> 0 | I62: ＝罰則比例 × 應計費而未計費營收；扣 EBITDA、營運來源、稅基與債務上限。客戶預付不因延誤退還（已知限制）

Sheet 運營_站點
A1: 站點租賃 — 公司揭露 vs 季報總額（檢驗租金路徑用）
A2: 季報不揭露逐站租金；下表為具名站點（company.json → defaults.sites），有租約金額者用來檢驗『每 MW 年租金』與模型租金路徑是否一致
A4: 站點 | B4: 營運方 | C4: 契約 MW | D4: 已驗收 MW | E4: 合約總值 $bn | F4: 年期 | G4: 年租金 $bn | H4: 每 MW 年租金 $m | I4: 時程 | J4: 季報對應 | K4: 說明
A5: New Carlisle, IN（Project Rainier） | B5: Amazon 自建（Anthropic，Trainium2） | C5: 910 | D5: 910 | E5: 未揭露 | F5: 未揭露 | I5: 2026 | J5: — | K5: Epoch AI：目前 IT 電力 910 MW（2026-03-23 起；事實總帳 mw.epoch.newCarlisle）[Interested-party／第三方]
A6: Ridgeland, MS | B6: Amazon 自建（Trainium2） | C6: 228 | D6: 228 | E6: 未揭露 | F6: 未揭露 | I6: 2026 | J6: — | K6: Epoch AI：目前 IT 電力 228 MW（2026-05-15 起）
A7: Madison Mega Site, MS | B7: Amazon 自建（Trainium2） | C7: 284 | D7: 284 | E7: 未揭露 | F7: 未揭露 | I7: 2025 | J7: — | K7: Epoch AI：目前 IT 電力 284 MW（2025-06-23 起）
A8: 具名站點合計 | C8: =SUM(C5:C7) -> 1422 | D8: =SUM(D5:D7) -> 1422 | E8: =SUM(E5:E7) -> 0 | G8: =SUM(G5:G7) -> 0 | H8: =IF(I8>0,G8/I8*1000,0) -> 0 | I8: =SUMPRODUCT(ISNUMBER(G5:G7)*C5:C7) -> 0 | K8: 加權每 MW 年租金＝具名站點的市場基準（I 欄＝有租約金額站點的契約 MW；沒有時為 0，不適用）
A10: 對帳：具名站點 vs 季報租賃承諾總額
A11: 季報在帳租賃（未折現，已起租） | E11: 144.08 | K11: company.json → leases.facts.onBal
A12: 季報未起租租賃（未折現） | E12: 137.214 | K12: company.json → leases.facts.notCommenced
A13: 季報單站按造價計租上限 | E13: 0 | K13: company.json → leases.facts.singleCap（無則 0）
A14: 季報已揭露租賃承諾合計 | E14: =SUM(E11:E13) -> 281.294 | K14: 未折現金額
A15: 減：具名站點合約總值 | E15: =-E8 -> 0
A16: ＝ 未具名站點（殘差） | E16: =E14+E15 -> 281.294 | K16: 未具名站點；公司不揭露逐站租金，殘差大是必然
A17: 殘差占季報總額 | E17: =IF(E14<>0,E16/E14,0) -> 1
A19: 檢驗：模型租金路徑 ÷ 在役 MW vs 市場基準
A20: 項目 | B20: 單位 | C20: 2026 | D20: 2027 | E20: 2028 | F20: 2029 | G20: 2030
A21: 模型租金（在帳＋表外） | B21: US$bn | C21: =各期收支!C16 -> 1.7734998 | D21: =各期收支!D16 -> 4.1244989 | E21: =各期收支!E16 -> 4.3576655 | F21: =各期收支!F16 -> 3.9666655 | G21: =各期收支!G16 -> 3.7676655
A22: 平均在役 MW（已連網） | B22: MW | C22: =(輸入與假設!C$243+輸入與假設!C$36)/2 -> 2667.2 | D22: =(輸入與假設!D$243+輸入與假設!D$36)/2 -> 5708.8 | E22: =(輸入與假設!E$243+輸入與假設!E$36)/2 -> 9337.6 | F22: =(輸入與假設!F$243+輸入與假設!F$36)/2 -> 12966.4 | G22: =(輸入與假設!G$243+輸入與假設!G$36)/2 -> 16595.2
A23: 模型期長度（年） | B23: 年 | C23: =輸入與假設!C$34 -> 0.5 | D23: =輸入與假設!D$34 -> 1 | E23: =輸入與假設!E$34 -> 1 | F23: =輸入與假設!F$34 -> 1 | G23: =輸入與假設!G$34 -> 1
A24: 模型每 MW 年租金 | B24: US$m/MW | C24: =C21/C23/C22*1000 -> 1.3298589 | D24: =D21/D23/D22*1000 -> 0.7224809 | E24: =E21/E23/E22*1000 -> 0.4666794 | F24: =F21/F23/F22*1000 -> 0.3059188 | G24: =G21/G23/G22*1000 -> 0.22703345 | K24: 2026 欄只含下半年租金、MW 取全期平均，略有低估
A25: 第三方租賃占比 | C25: 1 | K25: 其餘為自建，成本走 CapEx（company.json → leases.facts.share）[Assumed]
A26: 基準租金（MW×市場基準×占比） | B26: US$bn | C26: =C22*運營_站點!$H$8/1000*$C$25*C23 -> 0 | D26: =D22*運營_站點!$H$8/1000*$C$25*D23 -> 0 | E26: =E22*運營_站點!$H$8/1000*$C$25*E23 -> 0 | F26: =F22*運營_站點!$H$8/1000*$C$25*F23 -> 0 | G26: =G22*運營_站點!$H$8/1000*$C$25*G23 -> 0 | K26: 具名站點有租約金額時才有意義；否則為 0
A27: 差額（基準 − 模型） | B27: US$bn | C27: =C26-C21 -> -1.7734998 | D27: =D26-D21 -> -4.1244989 | E27: =E26-E21 -> -4.3576655 | F27: =F26-F21 -> -3.9666655 | G27: =G26-G21 -> -3.7676655 | K27: 正值＝模型租金可能低估的金額
A28: 五期差額合計 | C28: =SUM(C27:G27) -> -17.989995

Sheet 資產負債_既有債務
A1: 債務明細 — 季報（2026-06-30）逐筆＋存量利息推導
A2: 有效利率為現金票息口徑（可轉債＝票息 ÷ 到期累積倍數，本金以到期累積本金計）。本頁算出的存量利息連回『輸入』頁，再進入支出與資金頁
A4: 工具 | B4: 類別 | C4: 到期 | D4: 有效利率 | E4: 6/30 本金 | F4: 年化利息 | I4: 備註
A5: 2014 票據（發行 6.0B） | B5: 無擔保 | C5: 2040-06 | D5: 0.05025 | E5: 2.75 | F5: =D5*E5 -> 0.1381875 | I5: 10-Q 2026Q2 附註 5：面額 2,750、有效利率 4.93%–5.12%（取中點）、到期 2034–2044；到期日以加權剩餘年限 13.9 年推估 [Derived]
A6: 2017 票據（17.0B） | B6: 無擔保 | C6: 2041-06 | D6: 0.0379 | E6: 12 | F6: =D6*E6 -> 0.4548 | I6: 10-Q 2026Q2 附註 5：面額 12,000、有效利率 3.25%–4.33%（取中點）、到期 2027–2057；到期日以加權剩餘年限 14.9 年推估 [Derived]
A7: 2020 票據（10.0B） | B7: 無擔保 | C7: 2044-02 | D7: 0.02015 | E7: 7.75 | F7: =D7*E7 -> 0.1561625 | I7: 10-Q 2026Q2 附註 5：面額 7,750、有效利率 1.26%–2.77%（取中點）、到期 2027–2060；到期日以加權剩餘年限 17.6 年推估 [Derived]
A8: 2021 票據（18.5B） | B8: 無擔保 | C8: 2042-02 | D8: 0.02505 | E8: 12.25 | F8: =D8*E8 -> 0.3068625 | I8: 10-Q 2026Q2 附註 5：面額 12,250、有效利率 1.70%–3.31%（取中點）、到期 2028–2061；到期日以加權剩餘年限 15.6 年推估 [Derived]
A9: 2022-04 票據（12.8B） | B9: 無擔保 | C9: 2039-11 | D9: 0.03775 | E9: 9.75 | F9: =D9*E9 -> 0.3680625 | I9: 10-Q 2026Q2 附註 5：面額 9,750、有效利率 3.40%–4.15%（取中點）、到期 2027–2062；到期日以加權剩餘年限 13.3 年推估 [Derived]
A10: 2022-12 票據（8.3B） | B10: 無擔保 | C10: 2030-06 | D10: 0.04675 | E10: 5.75 | F10: =D10*E10 -> 0.2688125 | I10: 10-Q 2026Q2 附註 5：面額 5,750、有效利率 4.61%–4.74%（取中點）、到期 2027–2032；到期日以加權剩餘年限 3.9 年推估 [Derived]
A11: 2025 票據（15.0B） | B11: 無擔保 | C11: 2041-08 | D11: 0.04805 | E11: 15 | F11: =D11*E11 -> 0.72075 | I11: 10-Q 2026Q2 附註 5：面額 15,000、有效利率 3.99%–5.62%（取中點）、到期 2028–2065；到期日以加權剩餘年限 15.1 年推估 [Derived]
A12: 2026-03 美元票據（37.0B；含浮動 2.8B） | B12: 無擔保 | C12: 2042-12 | D12: 0.0504 | E12: 37 | F12: =D12*E12 -> 1.8648 | I12: 10-Q 2026Q2 附註 5：面額 37,000、有效利率 3.96%–6.12%（取中點）、到期 2028–2076；到期日以加權剩餘年限 16.4 年推估 [Derived]
A13: 2026-03 歐元票據（€14.5B；含浮動 €1.8B） | B13: 無擔保 | C13: 2036-08 | D13: 0.03735 | E13: 16.55 | F13: =D13*E13 -> 0.6181425 | I13: 10-Q 2026Q2 附註 5：面額 16,550、有效利率 2.59%–4.88%（取中點）、到期 2028–2064；到期日以加權剩餘年限 10.1 年推估 [Derived]
A14: 2026-05 瑞士法郎票據（CHF2.8B） | B14: 無擔保 | C14: 2035-06 | D14: 0.015 | E14: 3.487 | F14: =D14*E14 -> 0.052305 | I14: 10-Q 2026Q2 附註 5：面額 3,487、有效利率 0.90%–2.10%（取中點）、到期 2029–2051；到期日以加權剩餘年限 8.9 年推估 [Derived]
A15: 2026-06 加幣票據（C$14.0B） | B15: 無擔保 | C15: 2041-05 | D15: 0.04255 | E15: 9.853 | F15: =D15*E15 -> 0.41924515 | I15: 10-Q 2026Q2 附註 5：面額 9,853、有效利率 3.46%–5.05%（取中點）、到期 2029–2056；到期日以加權剩餘年限 14.8 年推估 [Derived]
A16: 其他長期債 | B16: 無擔保 | C16: 2036-06 | D16: 0.04 | E16: 0.855 | F16: =D16*E16 -> 0.0342 | I16: 其他長期債 855（利率未揭露，取 4.0% [Assumed]）
A17: 合計（6/30） | E17: =SUM(E5:E16) -> 132.995 | F17: =SUM(F5:F16) -> 5.4023302 | I17: 應等於最新季報本金合計 132.995（company.json → latestQuarter.debtPrincipal）
A18: 加權有效利率 | D18: =F17/E17 -> 0.040620551 | I18: ＝年化利息 ÷ 本金（company.json → debt.instruments 的有效利率）
A20: 評價日後新發可轉債 | D20: 0 | E20: 0 | F20: =D20*E20 -> 0 | I20: company.json → debt.convertible（期後新發；不在五期還本表內，只計利息）
A22: 可轉債逐檔（若轉換法：有效轉換價 < 判斷價 → 視為轉股，不計利息與還本）
A23: 可轉債 | B23: 到期 | C23: 票息 | D23: 原始本金 | E23: 到期累積倍數 | F23: 轉換價 | G23: 到期所屬模型期 | H23: 強制轉換（1＝是） | I23: 備註
A24: （無可轉債，不適用） | B24: 2099-12 | C24: 0 | D24: 0 | E24: 1 | F24: 1 | G24: 5 | H24: 0 | I24: company.json → debt.convertibles 為空清單
I25: 到期所屬模型期：0＝首期 … 4＝末期、5＝模型期後（建置時依期末日推算）
A27: 可轉債（推導） | C27: 到期本金 | D27: 若轉換股數 | E27: 有效轉換價 | F27: 融資分類 | G27: 評價第一輪 | H27: 評價第二輪 | I27: 說明
A28: =A24 -> （無可轉債，不適用） | C28: =D24*E24 -> 0 | D28: =D24/F24 -> 0 | E28: =F24*E24 -> 1 | F28: =IF(OR(H24=1,E28<輸入與假設!$C$297),1,0) -> 1 | G28: =IF(OR(H24=1,E28<輸入與假設!$C$320),1,0) -> 1 | H28: =IF(OR(H24=1,E28<評價_DCF與目標價!$C$87),1,0) -> 1
A29: 合計 | C29: =SUM(C28:C28) -> 0 | D29: =SUM(D28:D28) -> 0 | I29: 分類 1＝轉股（若轉換法）、0＝債務。強制轉換者一律為 1。融資分類判斷價＝股權發行價；評價第一輪＝現價；第二輪＝MIN(現價, 第一輪加權目標價)
A31: 存量利息推導（本金依季報到期表遞減）
A32: 項目 | B32: 單位 | C32: 2026 | D32: 2027 | E32: 2028 | F32: 2029 | G32: 2030 | I32: 公式／來源說明
A33: 期初本金 | B33: US$bn | C33: =E17 -> 132.995 | D33: =C35 -> 132.995 | E33: =D35 -> 124.158 | F33: =E35 -> 111.864 | G33: =F35 -> 102.694 | I33: 2026 期初為 6/30 本金（模型期起點）
A34: 排程還本 | B34: US$bn | C34: =輸入與假設!C$315 -> 0 | D34: =輸入與假設!D$315 -> 8.837 | E34: =輸入與假設!E$315 -> 12.294 | F34: =輸入與假設!F$315 -> 9.17 | G34: =輸入與假設!G$315 -> 7.085 | I34: 季報到期表
A35: 期末本金 | B35: US$bn | C35: =C33-C34 -> 132.995 | D35: =D33-D34 -> 124.158 | E35: =E33-E34 -> 111.864 | F35: =F33-F34 -> 102.694 | G35: =G33-G34 -> 95.609
A36: 平均本金 | B36: US$bn | C36: =(C33+C35)/2 -> 132.995 | D36: =(D33+D35)/2 -> 128.5765 | E36: =(E33+E35)/2 -> 118.011 | F36: =(F33+F35)/2 -> 107.279 | G36: =(G33+G35)/2 -> 99.1515
A37: 存量債務利息 | B37: US$bn | C37: =C36*資產負債_既有債務!$D$18*輸入與假設!C$34 -> 2.7011651 | D37: =D36*資產負債_既有債務!$D$18*輸入與假設!D$34 -> 5.2228482 | E37: =E36*資產負債_既有債務!$D$18*輸入與假設!E$34 -> 4.7936718 | F37: =F36*資產負債_既有債務!$D$18*輸入與假設!F$34 -> 4.3577321 | G37: =G36*資產負債_既有債務!$D$18*輸入與假設!G$34 -> 4.0275885 | I37: ＝平均本金×加權有效利率×期間長度。限制：假設利率組合不變；可轉債折價攤銷（非現金）不計
A38: 期後新發可轉債利息 | B38: US$bn | C38: =資產負債_既有債務!$F$20*輸入與假設!C$34 -> 0 | D38: =資產負債_既有債務!$F$20*輸入與假設!D$34 -> 0 | E38: =資產負債_既有債務!$F$20*輸入與假設!E$34 -> 0 | F38: =資產負債_既有債務!$F$20*輸入與假設!F$34 -> 0 | G38: =資產負債_既有債務!$F$20*輸入與假設!G$34 -> 0
A39: 可轉債到期還本（債務處理） | B39: US$bn | C39: =IF(輸入與假設!$C$286=1,SUMPRODUCT((1-資產負債_既有債務!$F$28:$F$28)*資產負債_既有債務!$C$28:$C$28*(資產負債_既有債務!$G$24:$G$24=0)),0) -> 0 | D39: =IF(輸入與假設!$C$286=1,SUMPRODUCT((1-資產負債_既有債務!$F$28:$F$28)*資產負債_既有債務!$C$28:$C$28*(資產負債_既有債務!$G$24:$G$24=1)),0) -> 0 | E39: =IF(輸入與假設!$C$286=1,SUMPRODUCT((1-資產負債_既有債務!$F$28:$F$28)*資產負債_既有債務!$C$28:$C$28*(資產負債_既有債務!$G$24:$G$24=2)),0) -> 0 | F39: =IF(輸入與假設!$C$286=1,SUMPRODUCT((1-資產負債_既有債務!$F$28:$F$28)*資產負債_既有債務!$C$28:$C$28*(資產負債_既有債務!$G$24:$G$24=3)),0) -> 0 | G39: =IF(輸入與假設!$C$286=1,SUMPRODUCT((1-資產負債_既有債務!$F$28:$F$28)*資產負債_既有債務!$C$28:$C$28*(資產負債_既有債務!$G$24:$G$24=4)),0) -> 0 | I39: 融資分類為債務的可轉債，到期當期以到期累積本金現金還本
A40: 可轉債期末餘額（債務處理） | B40: US$bn | C40: =IF(輸入與假設!$C$286=1,SUMPRODUCT((1-資產負債_既有債務!$F$28:$F$28)*資產負債_既有債務!$C$28:$C$28*(資產負債_既有債務!$G$24:$G$24>0)),SUMPRODUCT((1-資產負債_既有債務!$F$28:$F$28)*資產負債_既有債務!$C$28:$C$28)) -> 0 | D40: =IF(輸入與假設!$C$286=1,SUMPRODUCT((1-資產負債_既有債務!$F$28:$F$28)*資產負債_既有債務!$C$28:$C$28*(資產負債_既有債務!$G$24:$G$24>1)),SUMPRODUCT((1-資產負債_既有債務!$F$28:$F$28)*資產負債_既有債務!$C$28:$C$28)) -> 0 | E40: =IF(輸入與假設!$C$286=1,SUMPRODUCT((1-資產負債_既有債務!$F$28:$F$28)*資產負債_既有債務!$C$28:$C$28*(資產負債_既有債務!$G$24:$G$24>2)),SUMPRODUCT((1-資產負債_既有債務!$F$28:$F$28)*資產負債_既有債務!$C$28:$C$28)) -> 0 | F40: =IF(輸入與假設!$C$286=1,SUMPRODUCT((1-資產負債_既有債務!$F$28:$F$28)*資產負債_既有債務!$C$28:$C$28*(資產負債_既有債務!$G$24:$G$24>3)),SUMPRODUCT((1-資產負債_既有債務!$F$28:$F$28)*資產負債_既有債務!$C$28:$C$28)) -> 0 | G40: =IF(輸入與假設!$C$286=1,SUMPRODUCT((1-資產負債_既有債務!$F$28:$F$28)*資產負債_既有債務!$C$28:$C$28*(資產負債_既有債務!$G$24:$G$24>4)),SUMPRODUCT((1-資產負債_既有債務!$F$28:$F$28)*資產負債_既有債務!$C$28:$C$28)) -> 0 | I40: 到期累積本金；關閉攤還時維持全額
A41: 可轉債票息（債務處理） | B41: US$bn | C41: =IF(輸入與假設!$C$286=1,SUMPRODUCT((1-資產負債_既有債務!$F$28:$F$28)*資產負債_既有債務!$D$24:$D$24*資產負債_既有債務!$C$24:$C$24*((資產負債_既有債務!$G$24:$G$24>0)+0.5*(資產負債_既有債務!$G$24:$G$24=0))),SUMPRODUCT((1-資產負債_既有債務!$F$28:$F$28)*資產負債_既有債務!$D$24:$D$24*資產負債_既有債務!$C$24:$C$24))*輸入與假設!C$34 -> 0 | D41: =IF(輸入與假設!$C$286=1,SUMPRODUCT((1-資產負債_既有債務!$F$28:$F$28)*資產負債_既有債務!$D$24:$D$24*資產負債_既有債務!$C$24:$C$24*((資產負債_既有債務!$G$24:$G$24>1)+0.5*(資產負債_既有債務!$G$24:$G$24=1))),SUMPRODUCT((1-資產負債_既有債務!$F$28:$F$28)*資產負債_既有債務!$D$24:$D$24*資產負債_既有債務!$C$24:$C$24))*輸入與假設!D$34 -> 0 | E41: =IF(輸入與假設!$C$286=1,SUMPRODUCT((1-資產負債_既有債務!$F$28:$F$28)*資產負債_既有債務!$D$24:$D$24*資產負債_既有債務!$C$24:$C$24*((資產負債_既有債務!$G$24:$G$24>2)+0.5*(資產負債_既有債務!$G$24:$G$24=2))),SUMPRODUCT((1-資產負債_既有債務!$F$28:$F$28)*資產負債_既有債務!$D$24:$D$24*資產負債_既有債務!$C$24:$C$24))*輸入與假設!E$34 -> 0 | F41: =IF(輸入與假設!$C$286=1,SUMPRODUCT((1-資產負債_既有債務!$F$28:$F$28)*資產負債_既有債務!$D$24:$D$24*資產負債_既有債務!$C$24:$C$24*((資產負債_既有債務!$G$24:$G$24>3)+0.5*(資產負債_既有債務!$G$24:$G$24=3))),SUMPRODUCT((1-資產負債_既有債務!$F$28:$F$28)*資產負債_既有債務!$D$24:$D$24*資產負債_既有債務!$C$24:$C$24))*輸入與假設!F$34 -> 0 | G41: =IF(輸入與假設!$C$286=1,SUMPRODUCT((1-資產負債_既有債務!$F$28:$F$28)*資產負債_既有債務!$D$24:$D$24*資產負債_既有債務!$C$24:$C$24*((資產負債_既有債務!$G$24:$G$24>4)+0.5*(資產負債_既有債務!$G$24:$G$24=4))),SUMPRODUCT((1-資產負債_既有債務!$F$28:$F$28)*資產負債_既有債務!$D$24:$D$24*資產負債_既有債務!$C$24:$C$24))*輸入與假設!G$34 -> 0 | I41: ＝原始本金 × 票息 × 期間長度；到期當期計半期
A42: 首期新增借款利息校準 | B42: US$bn | C42: =0 -> 0 | D42: =0 -> 0 | E42: =0 -> 0 | F42: =0 -> 0 | G42: =0 -> 0 | I42: 讓首期模型利息對上公司季度利息指引的校準值（company.json → defaults.intCal）；無指引時為 0
A43: 存量利息合計（連回輸入頁） | B43: US$bn | C43: =C37+C38+C41+C42 -> 2.7011651 | D43: =D37+D38+D41+D42 -> 5.2228482 | E43: =E37+E38+E41+E42 -> 4.7936718 | F43: =F37+F38+F41+F42 -> 4.3577321 | G43: =G37+G38+G41+G42 -> 4.0275885 | I43: ＝存量債務利息＋期後新發可轉債利息＋可轉債票息＋首期校準

Sheet 資產負債_新債與新股
A1: 新債與新股（類資產負債表：現金、債務、股本、槓桿）
A2: 全部為連結公式。2026 欄的現金自 2026-06-30 起算（模型期），與 HTML『資產與負債 → 新債與新股』同口徑
A4: 項目 | B4: 單位 | C4: 2026 | D4: 2027 | E4: 2028 | F4: 2029 | G4: 2030 | I4: 公式／來源說明
A5: 現金
A6: 期初現金 | B6: US$bn | C6: =輸入與假設!$C$281 -> 122.988 | D6: =各期收支!C56 -> 64.690577 | E6: =各期收支!D56 -> 50 | F6: =各期收支!E56 -> 50 | G6: =各期收支!F56 -> 50 | I6: 2026＝6/30 現金（模型期起點）
A7: 營運收支淨額（含期後股權／可轉債，不含瀑布） | B7: US$bn | C7: =各期收支!C103-輸入與假設!$C$281 -> -58.297423 | D7: =各期收支!D103-各期收支!C103 -> -78.5112 | E7: =各期收支!E103-各期收支!D103 -> -43.342798 | F7: =各期收支!F103-各期收支!E103 -> -1.1574405 | G7: =各期收支!G103-各期收支!F103 -> -72.646673 | I7: ＝融資前累積現金的當期變動；負值即當期外部資金需求
A8: ＋ 瀑布：新債（額度＋資產層） | B8: US$bn | C8: =各期收支!C86 -> 0 | D8: =各期收支!D86 -> 67.179603 | E8: =各期收支!E86 -> 49.159767 | F8: =各期收支!F86 -> 7.3414831 | G8: =各期收支!G86 -> 82.979701
A9: ＋ 瀑布：可轉債 | B9: US$bn | C9: =各期收支!C89 -> 0 | D9: =各期收支!D89 -> 0 | E9: =各期收支!E89 -> 0 | F9: =各期收支!F89 -> 0 | G9: =各期收支!G89 -> 0
A10: ＋ 瀑布：高息債 | B10: US$bn | C10: =各期收支!C93 -> 0 | D10: =各期收支!D93 -> 0 | E10: =各期收支!E93 -> 0 | F10: =各期收支!F93 -> 0 | G10: =各期收支!G93 -> 0
A11: ＋ 瀑布：股權募資 | B11: US$bn | C11: =各期收支!C92 -> 0 | D11: =各期收支!D92 -> 0 | E11: =各期收支!E92 -> 0 | F11: =各期收支!F92 -> 0 | G11: =各期收支!G92 -> 0
A12: − 回購（瀑布第二步） | B12: US$bn | C12: =-各期收支!C76 -> 0 | D12: =-各期收支!D76 -> 0 | E12: =-各期收支!E76 -> 0 | F12: =-各期收支!F76 -> 0 | G12: =-各期收支!G76 -> 0
A13: − 新融資利息（新債＋可轉債＋高息債） | B13: US$bn | C13: =-各期收支!C94 -> 0 | D13: =-各期收支!D94 -> -3.3589802 | E13: =-各期收支!E94 -> -5.8169685 | F13: =-各期收支!F94 -> -6.1840427 | G13: =-各期收支!G94 -> -10.333028
A14: 期末現金 | B14: US$bn | C14: =SUM(C6:C13) -> 64.690577 | D14: =SUM(D6:D13) -> 50 | E14: =SUM(E6:E13) -> 50 | F14: =SUM(F6:F13) -> 50 | G14: =SUM(G6:G13) -> 50 | I14: 應等於『各期收支』期末累積現金（見下列驗算）
A15: 驗算：與各期收支期末現金差異 | B15: US$bn | C15: =C14-各期收支!C56 -> 0 | D15: =D14-各期收支!D56 -> 0 | E15: =E14-各期收支!E56 -> 0 | F15: =F14-各期收支!F56 -> 0 | G15: =G14-各期收支!G56 -> 0 | I15: 應為 0
A16: 債務
A17: 既有債務期初（季報本金） | B17: US$bn | C17: =資產負債_既有債務!$E$17+SUMPRODUCT((1-資產負債_既有債務!$F$28:$F$28)*資產負債_既有債務!$C$28:$C$28) -> 132.995 | D17: =C19 -> 132.995 | E17: =D19 -> 124.158 | F17: =E19 -> 111.864 | G17: =F19 -> 102.694 | I17: 2026＝其他借款＋債務處理可轉債到期本金（轉股處理者不列）
A18: − 排程還本（模型期） | B18: US$bn | C18: =-IF(輸入與假設!$C$286=1,輸入與假設!C$315,0)-資產負債_既有債務!C39 -> 0 | D18: =-IF(輸入與假設!$C$286=1,輸入與假設!D$315,0)-資產負債_既有債務!D39 -> -8.837 | E18: =-IF(輸入與假設!$C$286=1,輸入與假設!E$315,0)-資產負債_既有債務!E39 -> -12.294 | F18: =-IF(輸入與假設!$C$286=1,輸入與假設!F$315,0)-資產負債_既有債務!F39 -> -9.17 | G18: =-IF(輸入與假設!$C$286=1,輸入與假設!G$315,0)-資產負債_既有債務!G39 -> -7.085
A19: 既有債務期末 | B19: US$bn | C19: =各期收支!C82-0 -> 132.995 | D19: =各期收支!D82-0 -> 124.158 | E19: =各期收支!E82-0 -> 111.864 | F19: =各期收支!F82-0 -> 102.694 | G19: =各期收支!G82-0 -> 95.609 | I19: ＝依到期表遞減（關閉攤還時維持期初）
A20: ＋ 期後新發可轉債 | B20: US$bn | C20: =0 -> 0 | D20: =0 -> 0 | E20: =0 -> 0 | F20: =0 -> 0 | G20: =0 -> 0
A21: ＋ 瀑布新債餘額 | B21: US$bn | C21: =各期收支!C98 -> 0 | D21: =各期收支!D98 -> 67.179603 | E21: =各期收支!E98 -> 116.33937 | F21: =各期收支!F98 -> 123.68085 | G21: =各期收支!G98 -> 206.66055
A22: ＋ 瀑布可轉債餘額 | B22: US$bn | C22: =各期收支!C101 -> 0 | D22: =各期收支!D101 -> 0 | E22: =各期收支!E101 -> 0 | F22: =各期收支!F101 -> 0 | G22: =各期收支!G101 -> 0
A23: ＋ 高息債餘額 | B23: US$bn | C23: =各期收支!C100 -> 0 | D23: =各期收支!D100 -> 0 | E23: =各期收支!E100 -> 0 | F23: =各期收支!F100 -> 0 | G23: =各期收支!G100 -> 0
A24: 總債務 | B24: US$bn | C24: =SUM(C19:C23) -> 132.995 | D24: =SUM(D19:D23) -> 191.3376 | E24: =SUM(E19:E23) -> 228.20337 | F24: =SUM(F19:F23) -> 226.37485 | G24: =SUM(G19:G23) -> 302.26955 | I24: 應等於『各期收支』期末總債務
A25: 淨負債（總債務 − 期末現金） | B25: US$bn | C25: =C24-C14 -> 68.304423 | D25: =D24-D14 -> 141.3376 | E25: =E24-E14 -> 178.20337 | F25: =F24-F14 -> 176.37485 | G25: =G24-G14 -> 252.26955
A26: 股本
A27: 基礎股數（含 ATM 上限、SBC 稀釋） | B27: bn | C27: =損益!C23 -> 11.030314 | D27: =損益!D23 -> 11.140617 | E27: =損益!E23 -> 11.252023 | F27: =損益!F23 -> 11.364544 | G27: =損益!G23 -> 11.478189
A28: ＋ 本期新股 | B28: bn | C28: =各期收支!C96 -> 0 | D28: =各期收支!D96 -> 0 | E28: =各期收支!E96 -> 0 | F28: =各期收支!F96 -> 0 | G28: =各期收支!G96 -> 0
A29: 總股數（期末） | B29: bn | C29: =損益!C24 -> 11.030314 | D29: =損益!D24 -> 11.140617 | E29: =損益!E24 -> 11.252023 | F29: =損益!F24 -> 11.364544 | G29: =損益!G24 -> 11.478189 | I29: ＝基礎股數＋累計新股
A30: 槓桿
A31: 期末 backlog | B31: US$bn | C31: =各期收支!C81 -> 73.074775 | D31: =各期收支!D81 -> 102.04741 | E31: =各期收支!E81 -> 122.63847 | F31: =各期收支!F81 -> 104.22042 | G31: =各期收支!G81 -> 46.298654
A32: 債務上限（債務／backlog × 期末 backlog） | B32: US$bn | C32: =各期收支!C83 -> 459.32851 | D32: =各期收支!D83 -> 548.60716 | E32: =各期收支!E83 -> 739.26718 | F32: =各期收支!F83 -> 918.87391 | G32: =各期收支!G83 -> 1084.1841
A33: 總債務 ÷ 期末 backlog | B33: x | C33: =C24/MAX(0.01,C31) -> 1.8199851 | D33: =D24/MAX(0.01,D31) -> 1.8749874 | E33: =E24/MAX(0.01,E31) -> 1.8607813 | F33: =F24/MAX(0.01,F31) -> 2.1720778 | G33: =G24/MAX(0.01,G31) -> 6.52869 | I33: 高息債不受 backlog 上限約束
A34: 總債務 ÷ EBITDA（年化） | B34: x | C34: =C24/MAX(0.01,損益!C22/輸入與假設!C$34) -> 0.65580799 | D34: =D24/MAX(0.01,損益!D22/輸入與假設!D$34) -> 0.78661673 | E34: =E24/MAX(0.01,損益!E22/輸入與假設!E$34) -> 0.75985818 | F34: =F24/MAX(0.01,損益!F22/輸入與假設!F$34) -> 0.63824093 | G34: =G24/MAX(0.01,損益!G22/輸入與假設!G$34) -> 0.74748981 | I34: 2026 模型期 EBITDA 以模型期長度年化
A35: 租賃負債（期末） | B35: US$bn | C35: =各期收支!C63 -> 159.6994 | D35: =各期收支!D63 -> 193.48996 | E35: =各期收支!E63 -> 174.77673 | F35: =各期收支!F63 -> 157.08282 | G35: =各期收支!G63 -> 140.25738 | I35: 見『各期收支』租賃負債（期末剩餘租金現值，5.7%）
A36: EBITDAR（年化＝(EBITDA＋租金) ÷ 期間長度） | B36: US$bn | C36: =(損益!C22+各期收支!C16)/輸入與假設!C$34 -> 206.34264 | D36: =(損益!D22+各期收支!D16)/輸入與假設!D$34 -> 247.36571 | E36: =(損益!E22+各期收支!E16)/輸入與假設!E$34 -> 304.6813 | F36: =(損益!F22+各期收支!F16)/輸入與假設!F$34 -> 358.65224 | G36: =(損益!G22+各期收支!G16)/輸入與假設!G$34 -> 408.14716
A37: 調整後槓桿（(總債務＋租賃負債) ÷ EBITDAR） | B37: x | C37: =(C24+C35)/MAX(0.01,C36) -> 1.4184872 | D37: =(D24+D35)/MAX(0.01,D36) -> 1.555703 | E37: =(E24+E35)/MAX(0.01,E36) -> 1.3226282 | F37: =(F24+F35)/MAX(0.01,F36) -> 1.0691629 | G37: =(G24+G35)/MAX(0.01,G36) -> 1.0842338 | I37: S&P 降評門檻 >4.5×（[Interested-party] 二手轉述）；S&P 自身口徑另含全部未起租承諾與無條件採購義務，較本列高（見報告）
A38: 距投資級上限的空間（上限 − 調整後槓桿） | B38: x | C38: =輸入與假設!$C$289-C37 -> 1.5815128 | D38: =輸入與假設!$C$289-D37 -> 1.444297 | E38: =輸入與假設!$C$289-E37 -> 1.6773718 | F38: =輸入與假設!$C$289-F37 -> 1.9308371 | G38: =輸入與假設!$C$289-G37 -> 1.9157662 | I38: 負值＝超過上限：需股權或失去投資級

Sheet 資產負債_租賃承諾
A1: 租賃與承諾 — 季報（2026-06-30）原始揭露
A2: 本頁為硬編碼的申報數字（藍字），支出與資金頁的租金與還本列由此而來
A4: 在帳租賃到期表（未折現）
A5: 項目 | B5: 單位 | C5: 2026 下半 | D5: 2027 | E5: 2028 | F5: 2029 | G5: 2030 | H5: 其後
A6: 營業租賃付款 | B6: US$bn | C6: 9.336 | D6: 14.765 | E6: 13.924 | F6: 12.599 | G6: 11.269 | H6: 54.457
A7: 融資租賃付款 | B7: US$bn | C7: 1.44 | D7: 2.457 | E7: 2.579 | F7: 2.188 | G7: 1.989 | H7: 17.077
A8: 合計（＝支出頁「在帳現金租金」） | C8: =SUM(C6:C7) -> 10.776 | D8: =SUM(D6:D7) -> 17.222 | E8: =SUM(E6:E7) -> 16.503 | F8: =SUM(F6:F7) -> 14.787 | G8: =SUM(G6:G7) -> 13.258 | H8: =SUM(H6:H7) -> 71.534 | I8: 營業租賃負債現值 96.32、融資租賃 13.451；年報加權剩餘租期 12／14 年、折現率 5.7% [Verified]
A10: 債務本金到期表
A11: 項目 | B11: 單位 | C11: 2026 下半 | D11: 2027 | E11: 2028 | F11: 2029 | G11: 2030 | H11: 其後
A12: 本金（＝支出頁「排程還本」） | B12: US$bn | C12: 0 | D12: 8.837 | E12: 12.294 | F12: 9.17 | G12: 7.085 | H12: 95.609 | I12: 其他借款到期表（company.json → debt.amortization）；可轉債到期還本依融資分類另計，見『資產負債_既有債務』逐檔表
A13: 合計 | C13: =SUM(C12:H12) -> 132.995
A15: 表外與契約性承諾（未入表）
A16: 項目 | B16: 單位 | C16: 金額 | D16: 時程 | E16: 入表？ | F16: 模型位置
A17: 未起租租賃（未折現） | B17: US$bn | C17: 137.214 | D17: 季報揭露之已簽約未起租租賃 | E17: 否 | F17: 表外現金租金
A18: 單站按造價計租，上限 | B18: US$bn | C18: 0 | D18: 無此類揭露時為 0 | E18: 否 | F18: 表外現金租金
A19: 未動用信用額度 | B19: US$bn | C19: 20 | D19: company.json → defaults.facility（循環信用額度 20B，未動用） | E19: 否（來源） | F19: 瀑布：未動用額度
A20: 已揭露金額之承諾合計（未起租＋單站上限） | C20: =C17+C18 -> 137.214
A21: 模型表外租金五期合計 | C21: =SUM(各期收支!C15:G15) -> 38.373407
A22: 模型表外租金尾端（模型期後未付＝總額 − 五期） | C22: =MAX(0,輸入與假設!$C$19-C21) -> 98.840593
A23: 模型路徑合計 ÷ 已承諾（≥0.8 為合理） | C23: =(C21+C22)/C20 -> 1 | I23: 起租排程依季報附註（起租期間與期限）平均分攤；五期＋尾端＝未起租總額

Sheet 損益
A1: 損益（類損益表）— 與資金模型同一組收入
A2: 算力收入、Cash CapEx、利息皆由前面分頁連結而來；改資金假設，此頁會跟著動
A4: 項目 | B4: 單位 | C4: 2026 | D4: 2027 | E4: 2028 | F4: 2029 | G4: 2030 | I4: 公式／來源說明
A5: 損益表
A6: 算力收入 | B6: US$bn | C6: =運營_產能與收入!C26 -> 14.614955 | D6: =運營_產能與收入!D26 -> 58.33118 | E6: =運營_產能與收入!E26 -> 97.792303 | F6: =運營_產能與收入!F26 -> 137.47943 | G6: =運營_產能與收入!G26 -> 177.25826 | I6: ＝RPO 轉換＋新簽約
A7: 非算力服務 | B7: US$bn | C7: =輸入與假設!C$43 -> 0 | D7: =輸入與假設!D$43 -> 0 | E7: =輸入與假設!E$43 -> 0 | F7: =輸入與假設!F$43 -> 0 | G7: =輸入與假設!G$43 -> 0
A8: 非 AI 事業 | B8: US$bn | C8: =輸入與假設!C$194 -> 437.47913 | D8: =輸入與假設!D$194 -> 915.21272 | E8: =輸入與假設!E$194 -> 1015.6803 | F8: =輸入與假設!F$194 -> 1107.3757 | G8: =輸入與假設!G$194 -> 1185.1189 | I8: 非 AI 事業各線合計（B2）
A9: 總營收 | B9: US$bn | C9: =C6+C7+C8 -> 452.09409 | D9: =D6+D7+D8 -> 973.5439 | E9: =E6+E7+E8 -> 1113.4726 | F9: =F6+F7+F8 -> 1244.8551 | G9: =G6+G7+G8 -> 1362.3771
A10: EBITDA 率 | B10: % | C10: =輸入與假設!C$204 -> 0.80253284 | D10: =輸入與假設!D$204 -> 0.80721101 | E10: =輸入與假設!E$204 -> 0.80978531 | F10: =輸入與假設!F$204 -> 0.81104808 | G10: =輸入與假設!G$204 -> 0.81179812
A11: 延誤罰則（服務抵減，營業費用） | B11: US$bn | C11: =運營_產能與收入!C62 -> 0 | D11: =運營_產能與收入!D62 -> 0 | E11: =運營_產能與收入!E62 -> 0 | F11: =運營_產能與收入!F62 -> 0 | G11: =運營_產能與收入!G62 -> 0 | I11: 建設延誤期間應計費而未計費營收 × 罰則比例（預設 0；v0.2）
A12: 營業利益（EBIT） | B12: US$bn | C12: =(C6+C7)*輸入與假設!C$204+輸入與假設!C$46+輸入與假設!C$195-輸入與假設!C$196-C11-輸入與假設!C$278 -> 59.885486 | D12: =(D6+D7)*輸入與假設!D$204+輸入與假設!D$46+輸入與假設!D$195-輸入與假設!D$196-D11-輸入與假設!D$278 -> 131.9945 | E12: =(E6+E7)*輸入與假設!E$204+輸入與假設!E$46+輸入與假設!E$195-輸入與假設!E$196-E11-輸入與假設!E$278 -> 148.93964 | F12: =(F6+F7)*輸入與假設!F$204+輸入與假設!F$46+輸入與假設!F$195-輸入與假設!F$196-F11-輸入與假設!F$278 -> 162.12819 | G12: =(G6+G7)*輸入與假設!G$204+輸入與假設!G$46+輸入與假設!G$195-輸入與假設!G$196-G11-輸入與假設!G$278 -> 170.46428 | I12: ＝(算力＋服務營收)×EBITDA 率＋其他事業 EBITDA＋非 AI 事業 EBITDA − 非 AI 事業其他攤銷 − 延誤罰則 − 車隊 D&A
A13: 利息（含瀑布新債） | B13: US$bn | C13: =各期收支!C21 -> 2.7011651 | D13: =各期收支!D21 -> 8.5818284 | E13: =各期收支!E21 -> 10.61064 | F13: =各期收支!F21 -> 10.541775 | G13: =各期收支!G21 -> 14.360616
A14: 預付財務組成利息（非現金） | B14: US$bn | C14: =各期收支!C10 -> 0 | D14: =各期收支!D10 -> 0 | E14: =各期收支!E10 -> 0 | F14: =各期收支!F10 -> 0 | G14: =各期收支!G10 -> 0 | I14: 客戶預付的重大財務組成：合約負債以隱含利率累積的利息（v0.1b）
A15: 稅前損益 | B15: US$bn | C15: =C12-C13-C14 -> 57.184321 | D15: =D12-D13-D14 -> 123.41268 | E15: =E12-E13-E14 -> 138.329 | F15: =F12-F13-F14 -> 151.58641 | G15: =G12-G13-G14 -> 156.10366
A16: NOL 期初餘額 | B16: US$bn | C16: =輸入與假設!$C$345 -> 0 | D16: =C18 -> 0 | E16: =D18 -> 0 | F16: =E18 -> 0 | G16: =F18 -> 0 | I16: 6/30 累積虧損約 0.0
A17: 本期動用 NOL | B17: US$bn | C17: =MIN(C16,MAX(0,C15)*輸入與假設!$C$346) -> 0 | D17: =MIN(D16,MAX(0,D15)*輸入與假設!$C$346) -> 0 | E17: =MIN(E16,MAX(0,E15)*輸入與假設!$C$346) -> 0 | F17: =MIN(F16,MAX(0,F15)*輸入與假設!$C$346) -> 0 | G17: =MIN(G16,MAX(0,G15)*輸入與假設!$C$346) -> 0 | I17: 美國規定：抵扣上限為應稅所得 80%
A18: NOL 期末餘額 | B18: US$bn | C18: =C16-C17+MAX(0,-C15) -> 0 | D18: =D16-D17+MAX(0,-D15) -> 0 | E18: =E16-E17+MAX(0,-E15) -> 0 | F18: =F16-F17+MAX(0,-F15) -> 0 | G18: =G16-G17+MAX(0,-G15) -> 0
A19: 所得稅 | B19: US$bn | C19: =MAX(0,C15-C17)*輸入與假設!$C$332 -> 9.9271981 | D19: =MAX(0,D15-D17)*輸入與假設!$C$332 -> 21.424441 | E19: =MAX(0,E15-E17)*輸入與假設!$C$332 -> 24.013915 | F19: =MAX(0,F15-F17)*輸入與假設!$C$332 -> 26.315401 | G19: =MAX(0,G15-G17)*輸入與假設!$C$332 -> 27.099596 | I19: 虧損年不認列稅盾（與公司評價備抵一致）
A20: 淨利 | B20: US$bn | C20: =C15-C19 -> 47.257123 | D20: =D15-D19 -> 101.98824 | E20: =E15-E19 -> 114.31509 | F20: =F15-F19 -> 125.27101 | G20: =G15-G19 -> 129.00407
A21: D&A | B21: US$bn | C21: =輸入與假設!C$278+輸入與假設!C$196 -> 41.512333 | D21: =輸入與假設!D$278+輸入與假設!D$196 -> 111.2467 | E21: =輸入與假設!E$278+輸入與假設!E$196 -> 151.38399 | F21: =輸入與假設!F$278+輸入與假設!F$196 -> 192.55739 | G21: =輸入與假設!G$278+輸入與假設!G$196 -> 233.91522 | I21: 車隊折舊＋非 AI 事業其他攤銷，見輸入頁
A22: EBITDA | B22: US$bn | C22: =C12+C21 -> 101.39782 | D22: =D12+D21 -> 243.24121 | E22: =E12+E21 -> 300.32364 | F22: =F12+F21 -> 354.68558 | G22: =G12+G21 -> 404.3795
A23: 基礎股數（每年 +SBC 稀釋） | B23: bn | C23: =評價_DCF與目標價!$C$90 -> 11.030314 | D23: =C23*(1+輸入與假設!$C$384) -> 11.140617 | E23: =D23*(1+輸入與假設!$C$384) -> 11.252023 | F23: =E23*(1+輸入與假設!$C$384) -> 11.364544 | G23: =F23*(1+輸入與假設!$C$384) -> 11.478189 | I23: 2026＝評價股數（含價內可轉債轉股，見『評價_DCF與目標價』可轉債區）；之後每年 ×(1＋股數年增)
A24: 股數（含瀑布新股） | B24: bn | C24: =C23+各期收支!C97 -> 11.030314 | D24: =D23+各期收支!D97 -> 11.140617 | E24: =E23+各期收支!E97 -> 11.252023 | F24: =F23+各期收支!F97 -> 11.364544 | G24: =G23+各期收支!G97 -> 11.478189 | I24: ＝基礎股數＋累計瀑布新股
A25: 每股盈餘（EPS，模型期） | B25: US$ | C25: =C20/C24 -> 4.2842953 | D25: =D20/D24 -> 9.1546307 | E25: =E20/E24 -> 10.159514 | F25: =F20/F24 -> 11.022969 | G25: =G20/G24 -> 11.239061 | I25: 2026 欄只含下半年；全年口徑見下方
A27: 損益表（全年口徑；2026＝1H 實際＋下半年模型；與 HTML 損益簡表一致）
A28: 1H26 實際營收（已實現） | B28: US$bn | C28: =輸入與假設!$C$425 -> 382.125 | D28: =0 -> 0 | E28: =0 -> 0 | F28: =0 -> 0 | G28: =0 -> 0
A29: 全年總營收 | B29: US$bn | C29: =C28+C9 -> 834.21909 | D29: =D28+D9 -> 973.5439 | E29: =E28+E9 -> 1113.4726 | F29: =F28+F9 -> 1244.8551 | G29: =G28+G9 -> 1362.3771 | I29: 2026 可對照指引 未給全年營收指引
A30: 營收 YoY | B30: % | C30: =C29/716.924-1 -> 0.16360882 | D30: =D29/C29-1 -> 0.16701225 | E30: =E29/D29-1 -> 0.14373129 | F30: =F29/E29-1 -> 0.11799346 | G30: =G29/F29-1 -> 0.094406201 | I30: 2025 實際 716.924
A31: 全年 GAAP 營業利益 | B31: US$bn | C31: =輸入與假設!$C$426+C12 -> 111.19849 | D31: =D12 -> 131.9945 | E31: =E12 -> 148.93964 | F31: =F12 -> 162.12819 | G31: =G12 -> 170.46428
A32: 營利率 | B32: % | C32: =C31/C29 -> 0.1332965 | D32: =D31/D29 -> 0.13558146 | E32: =E31/E29 -> 0.13376139 | F32: =F31/F29 -> 0.1302386 | G32: =G31/G29 -> 0.12512268
A33: 全年 D&A | B33: US$bn | C33: =輸入與假設!$C$429+C21 -> 80.445333 | D33: =D21 -> 111.2467 | E33: =E21 -> 151.38399 | F33: =F21 -> 192.55739 | G33: =G21 -> 233.91522 | I33: 1H 實際 38.933
A34: 全年 EBITDA | B34: US$bn | C34: =C31+C33 -> 191.64382 | D34: =D31+D33 -> 243.24121 | E34: =E31+E33 -> 300.32364 | F34: =F31+F33 -> 354.68558 | G34: =G31+G33 -> 404.3795
A35: 全年利息（含瀑布新債） | B35: US$bn | C35: =輸入與假設!$C$423+C13 -> 4.8151651 | D35: =D13 -> 8.5818284 | E35: =E13 -> 10.61064 | F35: =F13 -> 10.541775 | G35: =G13 -> 14.360616 | I35: 2027 起瀑布新債利息與新股同時影響 EPS
A36: 全年淨利 | B36: US$bn | C36: =輸入與假設!$C$427+C20 -> 140.15912 | D36: =D20 -> 101.98824 | E36: =E20 -> 114.31509 | F36: =F20 -> 125.27101 | G36: =G20 -> 129.00407
A37: 淨利率 | B37: % | C37: =C36/C29 -> 0.16801237 | D37: =D36/D29 -> 0.10475977 | E37: =E36/E29 -> 0.10266538 | F37: =F36/F29 -> 0.100631 | G37: =G36/G29 -> 0.094690421
A38: 全年 GAAP EPS | B38: US$ | C38: =輸入與假設!$C$431+C20/C24 -> 12.814295 | D38: =D20/D24 -> 9.1546307 | E38: =E20/E24 -> 10.159514 | F38: =F20/F24 -> 11.022969 | G38: =G20/G24 -> 11.239061 | I38: 2026＝1H 實際 EPS 8.53＋下半年淨利÷股數
A39: 全年 EPS（加回 SBC） | B39: US$ | C39: =輸入與假設!$C$432+(C20+輸入與假設!$C$385*輸入與假設!C$34)/C24 -> 14.619792 | D39: =(D20+輸入與假設!$C$385*輸入與假設!D$34)/D24 -> 10.888287 | E39: =(E20+輸入與假設!$C$385*輸入與假設!E$34)/E24 -> 11.876005 | F39: =(F20+輸入與假設!$C$385*輸入與假設!F$34)/F24 -> 12.722465 | G39: =(G20+輸入與假設!$C$385*輸入與假設!G$34)/G24 -> 12.921731 | I39: ＝(淨利＋SBC)÷股數；NOL 狀態無現金稅，SBC 全額加回

Sheet 評價_DCF與目標價
A1: 評價 — DCF、EV/EBITDA、加權目標價
A2: 營收、營業利益、D&A、EBITDA、股數引用『損益』頁；Cash CapEx 與融資引用『各期收支』頁
A4: 項目 | B4: 單位 | C4: 2026 | D4: 2027 | E4: 2028 | F4: 2029 | G4: 2030 | I4: 公式／來源說明
A5: DCF（無槓桿自由現金流；起點為 2026-06-30）
A6: 現金 CapEx（2026-06-30 之後） | B6: US$bn | C6: =輸入與假設!C$277-各期收支!C8 -> 123.69 | D6: =輸入與假設!D$277-各期收支!D8 -> 276.22582 | E6: =輸入與假設!E$277-各期收支!E8 -> 291.66355 | F6: =輸入與假設!F$277-各期收支!F8 -> 305.37569 | G6: =輸入與假設!G$277-各期收支!G8 -> 427.86374 | I6: DCF 起點為 6/30，故 2026 欄只含 2H 的建置支出，不含 1H 已發生的 96.31
A7: 比較基期營收 | B7: US$bn | C7: =716.924 -> 716.924 | D7: =382.125+損益!C9 -> 834.21909 | E7: =損益!D9 -> 973.5439 | F7: =損益!E9 -> 1113.4726 | G7: =損益!F9 -> 1244.8551 | I7: 2025 實際 716.924；2027 基期＝1H 實際 382.125＋2026 模型期營收
A8: 預付認列（非現金營收，扣除） | B8: US$bn | C8: =各期收支!C11 -> 0 | D8: =各期收支!D11 -> 0 | E8: =各期收支!E11 -> 0 | F8: =各期收支!F11 -> 0 | G8: =各期收支!G11 -> 0 | I8: 營收中由合約負債轉入的部分已在預付時收現（預付流入已自現金 CapEx 抵減），UFCF 扣除以免重複（v0.1b）
A9: 營運資金變動 | B9: US$bn | C9: =IF(ISBLANK(輸入與假設!$C$48),輸入與假設!$C$347*MAX(0,損益!C9-C7),-輸入與假設!$C$48) -> -1.947 | D9: =輸入與假設!$C$347*MAX(0,損益!D9-D7) -> 0 | E9: =輸入與假設!$C$347*MAX(0,損益!E9-E7) -> 0 | F9: =輸入與假設!$C$347*MAX(0,損益!F9-F7) -> 0 | G9: =輸入與假設!$C$347*MAX(0,損益!G9-G7) -> 0 | I9: 2026＝−上年同期實際（輸入非空白時；MAG v0.1b r2 C14）；之後＝營收增量的 0%
A10: 無槓桿 NOL 期初 | B10: US$bn | C10: =輸入與假設!$C$345 -> 0 | D10: =C12 -> 0 | E10: =D12 -> 0 | F10: =E12 -> 0 | G10: =F12 -> 0 | I10: DCF 用無槓桿稅（利息不可抵稅，否則稅盾被計兩次：一次在 UFCF、一次在 WACC）
A11: 本期動用（無槓桿） | B11: US$bn | C11: =MIN(C10,MAX(0,損益!C12)*輸入與假設!$C$346) -> 0 | D11: =MIN(D10,MAX(0,損益!D12)*輸入與假設!$C$346) -> 0 | E11: =MIN(E10,MAX(0,損益!E12)*輸入與假設!$C$346) -> 0 | F11: =MIN(F10,MAX(0,損益!F12)*輸入與假設!$C$346) -> 0 | G11: =MIN(G10,MAX(0,損益!G12)*輸入與假設!$C$346) -> 0
A12: 無槓桿 NOL 期末 | B12: US$bn | C12: =C10-C11+MAX(0,-損益!C12) -> 0 | D12: =D10-D11+MAX(0,-損益!D12) -> 0 | E12: =E10-E11+MAX(0,-損益!E12) -> 0 | F12: =F10-F11+MAX(0,-損益!F12) -> 0 | G12: =G10-G11+MAX(0,-損益!G12) -> 0
A13: 無槓桿所得稅（DCF 用） | B13: US$bn | C13: =MAX(0,損益!C12-C11)*輸入與假設!$C$332 -> 10.39612 | D13: =MAX(0,損益!D12-D11)*輸入與假設!$C$332 -> 22.914246 | E13: =MAX(0,損益!E12-E11)*輸入與假設!$C$332 -> 25.855922 | F13: =MAX(0,損益!F12-F11)*輸入與假設!$C$332 -> 28.145453 | G13: =MAX(0,損益!G12-G11)*輸入與假設!$C$332 -> 29.592599 | I13: 與損益表的所得稅不同：此處不扣利息，數字較高，這是 DCF 的正確口徑
A14: UFCF | B14: US$bn | C14: =損益!C12-C13+損益!C21-輸入與假設!C$196-C6-C9-C8 -> -44.248371 | D14: =損益!D12-D13+損益!D21-輸入與假設!D$196-D6-D9-D8 -> -85.473809 | E14: =損益!E12-E13+損益!E21-輸入與假設!E$196-E6-E9-E8 -> -50.453997 | F14: =損益!F12-F13+損益!F21-輸入與假設!F$196-F6-F9-F8 -> -15.415192 | G14: =損益!G12-G13+損益!G21-輸入與假設!G$196-G6-G9-G8 -> -92.387437 | I14: ＝EBIT−無槓桿稅＋D&A−現金 CapEx（已扣客戶預付）−營運資金−預付認列。建置期全為負是正常的
A15: 折現期數 | B15: 年 | C15: =輸入與假設!$C$402 -> 0.5 | D15: =輸入與假設!$D$402 -> 1.5 | E15: =輸入與假設!$E$402 -> 2.5 | F15: =輸入與假設!$F$402 -> 3.5 | G15: =輸入與假設!$G$402 -> 4.5 | I15: 自 2026-06-30 起算；2026 模型期（下半年）的現金流平均落在 0.5 年
A16: 折現因子 | C16: =1/(1+輸入與假設!$C$342)^C15 -> 0.94279831 | D16: =1/(1+輸入與假設!$C$342)^D15 -> 0.83802388 | E16: =1/(1+輸入與假設!$C$342)^E15 -> 0.74489316 | F16: =1/(1+輸入與假設!$C$342)^F15 -> 0.66211219 | G16: =1/(1+輸入與假設!$C$342)^G15 -> 0.58853077
A17: UFCF 現值 | B17: US$bn | C17: =C14*C16 -> -41.717289 | D17: =D14*D16 -> -71.629093 | E17: =E14*E16 -> -37.582837 | F17: =F14*F16 -> -10.206587 | G17: =G14*G16 -> -54.37285
A19: 五期 UFCF 現值合計 | C19: =SUM(C17:G17) -> -215.50866 | I19: 建置期現金流現值
A20: 終值基準 FCF（2030 UFCF，含汰換 CapEx） | C20: =G14+輸入與假設!G253*(1-各期收支!G7) -> 214.77461 | I20: v0.1c：終值基準＝末期 UFCF（含穩態汰換 CapEx，已扣客戶預付覆蓋）＋加回末期成長型 CapEx（扣預付後；成長由 g 表達，預設情境為 0）；GPU 不是永續資產，終值年須持續再投資
A21: 終值（Gordon） | C21: =IF(C30=1,0,C20*(1+輸入與假設!$C$343)/(輸入與假設!$C$342-輸入與假設!$C$343)) -> 2327.9816 | I21: ＝常態化 FCF×(1+g)÷(WACC−g)
A22: 終值現值 | C22: =C21*G16 -> 1370.0888
A23: 企業價值 EV | C23: =C19+C22 -> 1154.5801
A24: 減：淨負債 | C24: =-評價_DCF與目標價!$C$91 -> 168.937 | I24: ＝評價淨負債（不含可轉債的淨負債＋債務處理可轉債到期本金＋調整項；見下方可轉債區）
A25: 股權價值 | C25: =C23+C24 -> 1323.5171
A26: DCF 每股 | C26: =IF(C30=1,0,IF(輸入與假設!$C$387=2,C32,C31)) -> 119.98907 | I26: 採用值：失效時為 0 且權重歸零；否則依「DCF 下限方式」取 0 截斷或選擇權
A27: 終值占 EV 比重 | C27: =C22/C23 -> 1.1866554 | I27: ="超過 "&IF(ROUND(ABS(輸入與假設!$C$411)*100,4)=INT(ROUND(ABS(輸入與假設!$C$411)*100,4)),TEXT(ROUND(ABS(輸入與假設!$C$411)*100,4),"0"),TEXT(ROUND(ABS(輸入與假設!$C$411)*100,4),"0.0"))&"%"&" 表示結論由終值假設決定，不由現金流決定" -> 超過 85% 表示結論由終值假設決定，不由現金流決定
A28: 新股募得現金（現值） | C28: =(各期收支!C92-各期收支!C76)/(1+輸入與假設!$C$342)^輸入與假設!$C$403+(各期收支!D92-各期收支!D76)/(1+輸入與假設!$C$342)^輸入與假設!$D$403+(各期收支!E92-各期收支!E76)/(1+輸入與假設!$C$342)^輸入與假設!$E$403+(各期收支!F92-各期收支!F76)/(1+輸入與假設!$C$342)^輸入與假設!$F$403+(各期收支!G92-各期收支!G76)/(1+輸入與假設!$C$342)^輸入與假設!$G$403 -> 0 | I28: 期初到位，折現期數 0／0.5／1.5／2.5／3.5 年；MAG v0.1b：扣瀑布回購現金（淨股權）
A29: 融資後股數（含瀑布新股） | C29: =評價_DCF與目標價!$C$90+各期收支!G97 -> 11.030314
A30: DCF 失效？（WACC ≤ g 或常態化 FCF ≤ 0） | C30: =IF(OR(輸入與假設!$C$342<=輸入與假設!$C$343,C20<=0),1,0) -> 0 | I30: 1＝失效：DCF 權重歸零、EV/EBITDA 100%。股權為負不算失效
A31: DCF 每股：0 截斷 | C31: =MAX(0,(C25+C28)/C29) -> 119.98907
A32: DCF 每股：選擇權（Merton） | C32: =IF((C23+C28)<=0,0,IF(評價_DCF與目標價!$C$91<=0,(C23+C28),(C23+C28)*NORMSDIST(C33)-評價_DCF與目標價!$C$91*EXP(-輸入與假設!$C$333*輸入與假設!$C$389)*NORMSDIST(C34))/C29) -> 104.67337 | I32: Black-Scholes：S＝企業價值＋新股現值、K＝淨負債
A33: d1 | C33: =IF(OR((C23+C28)<=0,評價_DCF與目標價!$C$91<=0),0,(LN((C23+C28)/評價_DCF與目標價!$C$91)+(輸入與假設!$C$333+輸入與假設!$C$388^2/2)*輸入與假設!$C$389)/(輸入與假設!$C$388*SQRT(輸入與假設!$C$389))) -> 0
A34: d2 | C34: =C33-輸入與假設!$C$388*SQRT(輸入與假設!$C$389) -> -1.0606602
A36: 倍數法（錨定年度，預設 2029；折回 2027-06-30）
A37: 錨定年度 | C37: =CHOOSE(輸入與假設!$C$379,"2027","2028","2029","2030") -> 2029 | I37: 輸入與假設 F 區可改
A38: 錨定年度 EBITDA | C38: =INDEX(損益!$D$22:$G$22,1,輸入與假設!$C$379) -> 354.68558
A39: 錨定年度企業價值（倍數 × EBITDA） | C39: =C45*輸入與假設!$C$348+C44*輸入與假設!$C$378 -> 3840.0267 | I39: 分部加總：AI 雲端 EBITDA × EV/EBITDA 倍數＋非 AI 事業 EBITDA × 非 AI 事業倍數（下方兩列）
A40: 錨定年度末淨負債（總債務 − 現金） | C40: =INDEX(各期收支!$D$102:$G$102,1,輸入與假設!$C$379)-INDEX(各期收支!$D$56:$G$56,1,輸入與假設!$C$379)+評價_DCF與目標價!$C$92 -> -2.5691466 | I40: 含瀑布新債；加可轉債分類調整與淨負債調整項（見下方可轉債區）
A41: 錨定年度末股數（含瀑布新股） | C41: =INDEX(損益!$D$24:$G$24,1,輸入與假設!$C$379) -> 11.364544 | I41: 損益股數：SBC 逐年稀釋＋瀑布新股
A42: 折回 2027-06-30 的折現因子 | C42: =1/(1+輸入與假設!$C$342)^(輸入與假設!$C$379-輸入與假設!$C$399) -> 0.74489316 | I42: 以 WACC 折現 [Assumed]
A43: EV/EBITDA 每股（融資後） | C43: =MAX(0,(C39-C40)/C41)*C42 -> 251.86435 | I43: 以 0 為下限
A44: 錨定年度非 AI 事業 EBITDA | C44: =INDEX(輸入與假設!$D$195:$G$195,1,輸入與假設!$C$379) -> 243.18315 | I44: × 非 AI 事業 EV/EBITDA 倍數（同業 NTM 中位數）
A45: 錨定年度 AI 雲端 EBITDA（算力＋服務＋其他） | C45: =C38-C44 -> 111.50243 | I45: ＝錨定年度 EBITDA − 非 AI 事業；× EV/EBITDA 倍數
A47: 加權目標價
A48: DCF 每股（推到目標價時點） | C48: =C26*(1+輸入與假設!$C$342)^輸入與假設!$C$395 -> 134.99078 | I48: ＝DCF 每股 ×（1＋WACC）^（評價日至目標價時點的年數）
A49: DCF 每股 × 有效權重 | C49: =C48*IF(C30=1,0,輸入與假設!$C$380) -> 60.74585
A50: EV/EBITDA（融資後）× 有效權重 | C50: =C43*IF(C30=1,1,1-輸入與假設!$C$380) -> 138.52539
A51: 加權目標價 | C51: =SUM(C49:C50) -> 199.27124 | I51: 期前融資瀑布：缺口先由額度與資產層新債支應，殘差以股權募足；估值不再扣缺口本金
A52: 現價 | C52: =輸入與假設!$C$320 -> 259.92
A53: 潛在空間 | C53: =C51/C52-1 -> -0.23333624
A55: 讀法 2｜自用 AI 價值中性（自用 MW 以 k＝1 計影子收入進評價；讀法 1＝影子收入不進評價，主值不變）
A56: 讀法 2｜自用 AI 影子 EBITDA（k＝1） | B56: US$bn | C56: =運營_產能與收入!C26*(1/輸入與假設!$C$56-(1-輸入與假設!C$204))*(1/輸入與假設!$C$217-1) -> 3.1164675 | D56: =運營_產能與收入!D26*(1/輸入與假設!$C$56-(1-輸入與假設!D$204))*(1/輸入與假設!$C$217-1) -> 12.50666 | E56: =運營_產能與收入!E26*(1/輸入與假設!$C$56-(1-輸入與假設!E$204))*(1/輸入與假設!$C$217-1) -> 21.030369 | F56: =運營_產能與收入!F26*(1/輸入與假設!$C$56-(1-輸入與假設!F$204))*(1/輸入與假設!$C$217-1) -> 29.608541 | G56: =運營_產能與收入!G26*(1/輸入與假設!$C$56-(1-輸入與假設!G$204))*(1/輸入與假設!$C$217-1) -> 38.208828 | I56: ＝對外 AI 營收 ÷ k ×(1 ÷ 對外比例 − 1) − 同口徑營運成本：自用 AI 剛好回收 Tokenomics 持有成本（不創造也不毀損價值）
A57: 讀法 2｜EBIT | B57: US$bn | C57: =損益!C12+C56 -> 63.001953 | D57: =損益!D12+D56 -> 144.50116 | E57: =損益!E12+E56 -> 169.97001 | F57: =損益!F12+F56 -> 191.73673 | G57: =損益!G12+G56 -> 208.67311
A58: 讀法 2｜無槓桿 NOL 期初 | B58: US$bn | C58: =輸入與假設!$C$345 -> 0 | D58: =C60 -> 0 | E58: =D60 -> 0 | F58: =E60 -> 0 | G58: =F60 -> 0
A59: 讀法 2｜本期動用（無槓桿） | B59: US$bn | C59: =MIN(C58,MAX(0,C57)*輸入與假設!$C$346) -> 0 | D59: =MIN(D58,MAX(0,D57)*輸入與假設!$C$346) -> 0 | E59: =MIN(E58,MAX(0,E57)*輸入與假設!$C$346) -> 0 | F59: =MIN(F58,MAX(0,F57)*輸入與假設!$C$346) -> 0 | G59: =MIN(G58,MAX(0,G57)*輸入與假設!$C$346) -> 0
A60: 讀法 2｜無槓桿 NOL 期末 | B60: US$bn | C60: =C58-C59+MAX(0,-C57) -> 0 | D60: =D58-D59+MAX(0,-D57) -> 0 | E60: =E58-E59+MAX(0,-E57) -> 0 | F60: =F58-F59+MAX(0,-F57) -> 0 | G60: =G58-G59+MAX(0,-G57) -> 0
A61: 讀法 2｜無槓桿所得稅 | B61: US$bn | C61: =MAX(0,C57-C59)*輸入與假設!$C$332 -> 10.937139 | D61: =MAX(0,D57-D59)*輸入與假設!$C$332 -> 25.085402 | E61: =MAX(0,E57-E59)*輸入與假設!$C$332 -> 29.506794 | F61: =MAX(0,F57-F59)*輸入與假設!$C$332 -> 33.285496 | G61: =MAX(0,G57-G59)*輸入與假設!$C$332 -> 36.225651
A62: 讀法 2｜UFCF | B62: US$bn | C62: =C14+C56-(C61-C13) -> -41.672922 | D62: =D14+D56-(D61-D13) -> -75.138306 | E62: =E14+E56-(E61-E13) -> -33.0745 | F62: =F14+F56-(F61-F13) -> 9.0533055 | G62: =G14+G56-(G61-G13) -> -60.811661 | I62: ＝讀法 1 UFCF＋影子 EBITDA − 稅差
A63: 讀法 2｜UFCF 現值 | B63: US$bn | C63: =C62*C16 -> -39.289161 | D63: =D62*D16 -> -62.967694 | E63: =E62*E16 -> -24.636969 | F63: =F62*F16 -> 5.9943039 | G63: =G62*G16 -> -35.789534
A64: 讀法 2｜五期 UFCF 現值合計 | C64: =SUM(C63:G63) -> -156.68905
A65: 讀法 2｜終值基準 FCF | C65: =C20-G14+G62 -> 246.35039 | I65: ＝讀法 1 終值基準＋末期影子現金流差
A66: 讀法 2｜DCF 失效？ | C66: =IF(OR(輸入與假設!$C$342<=輸入與假設!$C$343,C65<=0),1,0) -> 0
A67: 讀法 2｜終值現值 | C67: =IF(C66=1,0,C65*(1+輸入與假設!$C$343)/(輸入與假設!$C$342-輸入與假設!$C$343))*G16 -> 1571.5168
A68: 讀法 2｜企業價值 EV | C68: =C64+C67 -> 1414.8277
A69: 讀法 2｜d1 | C69: =IF(OR((C68+C28)<=0,評價_DCF與目標價!$C$91<=0),0,(LN((C68+C28)/評價_DCF與目標價!$C$91)+(輸入與假設!$C$333+輸入與假設!$C$388^2/2)*輸入與假設!$C$389)/(輸入與假設!$C$388*SQRT(輸入與假設!$C$389))) -> 0
A70: 讀法 2｜DCF 每股（評價日） | C70: =IF(C66=1,0,IF(輸入與假設!$C$387=2,IF((C68+C28)<=0,0,IF(評價_DCF與目標價!$C$91<=0,(C68+C28),(C68+C28)*NORMSDIST(C69)-評價_DCF與目標價!$C$91*EXP(-輸入與假設!$C$333*輸入與假設!$C$389)*NORMSDIST(C69-輸入與假設!$C$388*SQRT(輸入與假設!$C$389)))/C29),MAX(0,(C68-評價_DCF與目標價!$C$91+C28)/C29))) -> 143.58292 | I70: 與讀法 1 同股數、同淨負債
A71: 讀法 2｜DCF 每股（推到目標價時點） | C71: =C70*(1+輸入與假設!$C$342)^輸入與假設!$C$395 -> 161.53446
A72: 讀法 2｜EV/EBITDA 每股（融資後） | C72: =MAX(0,(C39+INDEX($D$56:$G$56,1,輸入與假設!$C$379)*輸入與假設!$C$348-C40)/C41)*C42 -> 263.50857 | I72: 錨定年 AI 雲端 EBITDA 加影子 EBITDA × AI 雲端倍數
A73: 讀法 2｜加權目標價 | C73: =C71*IF(C66=1,0,輸入與假設!$C$380)+C72*IF(C66=1,1,1-輸入與假設!$C$380) -> 217.62022 | I73: 只有對外 AI 的超額報酬影響目標價（對照表 r1 C16）
A74: 讀法 2 − 讀法 1（目標價差額） | C74: =C73-C51 -> 18.348978 | I74: 主值取哪一個是 Andy 的判斷（待決）
A76: 可轉債稀釋（若轉換法；第一輪判斷價＝現價，第二輪＝MIN(現價, 第一輪目標價)）
A77: 第一輪：轉股股數 | C77: =SUMPRODUCT(資產負債_既有債務!$D$28:$D$28*資產負債_既有債務!$G$28:$G$28) -> 0 | I77: 有效轉換價 < 現價的可轉債：原始本金 ÷ 轉換價
A78: 第一輪：評價股數 | C78: =輸入與假設!$C$321+C77 -> 11.030314
A79: 第一輪：評價淨負債 | C79: =輸入與假設!$C$322+SUMPRODUCT(資產負債_既有債務!$C$28:$C$28*(1-資產負債_既有債務!$G$28:$G$28))+輸入與假設!$C$331 -> -168.937 | I79: ＝不含可轉債的淨負債＋債務處理可轉債到期本金＋調整項
A80: 第一輪：DCF 融資後股數 | C80: =C78+各期收支!G97 -> 11.030314
A81: 第一輪：d1 | C81: =IF(OR((C23+C28)<=0,C79<=0),0,(LN((C23+C28)/C79)+(輸入與假設!$C$333+輸入與假設!$C$388^2/2)*輸入與假設!$C$389)/(輸入與假設!$C$388*SQRT(輸入與假設!$C$389))) -> 0
A82: 第一輪：DCF 每股（評價日） | C82: =IF(C30=1,0,IF(輸入與假設!$C$387=2,IF((C23+C28)<=0,0,IF(C79<=0,(C23+C28),(C23+C28)*NORMSDIST(C81)-C79*EXP(-輸入與假設!$C$333*輸入與假設!$C$389)*NORMSDIST(C81-輸入與假設!$C$388*SQRT(輸入與假設!$C$389)))/C80),MAX(0,(C23-C79+C28)/C80))) -> 119.98907 | I82: 與上方 DCF 同算法，只換股數與淨負債
A83: 第一輪：錨定年末淨負債 | C83: =INDEX(各期收支!$D$102:$G$102,1,輸入與假設!$C$379)-INDEX(各期收支!$D$56:$G$56,1,輸入與假設!$C$379)+SUMPRODUCT(資產負債_既有債務!$C$28:$C$28*(資產負債_既有債務!$F$28:$F$28-資產負債_既有債務!$G$28:$G$28))+輸入與假設!$C$331 -> -2.5691466 | I83: ＝融資表錨定年末淨負債＋（融資分類為轉股、評價分類為債務的到期本金）＋調整項
A84: 第一輪：錨定年末股數 | C84: =C78*(1+輸入與假設!$C$384)^輸入與假設!$C$379+INDEX(各期收支!$D$97:$G$97,1,輸入與假設!$C$379) -> 11.364544
A85: 第一輪：EV/EBITDA 每股 | C85: =MAX(0,(C39-C83)/C84)*C42 -> 251.86435
A86: 第一輪：加權目標價 | C86: =C82*(1+輸入與假設!$C$342)^輸入與假設!$C$395*IF(C30=1,0,輸入與假設!$C$380)+C85*IF(C30=1,1,1-輸入與假設!$C$380) -> 199.27124
A87: 第二輪判斷價 | C87: =MIN(輸入與假設!$C$320,C86) -> 199.27124 | I87: ＝MIN(現價, 第一輪加權目標價)：以較保守者判斷是否價內
A88: 第二輪：轉股股數 | C88: =SUMPRODUCT(資產負債_既有債務!$D$28:$D$28*資產負債_既有債務!$H$28:$H$28) -> 0 | I88: 有效轉換價 < 第二輪判斷價的可轉債
A89: 第二輪：債務處理到期本金 | C89: =SUMPRODUCT(資產負債_既有債務!$C$28:$C$28*(1-資產負債_既有債務!$H$28:$H$28)) -> 0
A90: 評價股數（含可轉債轉股） | C90: =輸入與假設!$C$321+C88 -> 11.030314 | I90: DCF、損益股數與錨定年末股數的起點
A91: 評價淨負債（含可轉債與調整項） | C91: =輸入與假設!$C$322+C89+輸入與假設!$C$331 -> -168.937 | I91: DCF 減項與 Merton 履約價
A92: 錨定年末淨負債調整（可轉債分類差＋調整項） | C92: =SUMPRODUCT(資產負債_既有債務!$C$28:$C$28*(資產負債_既有債務!$F$28:$F$28-資產負債_既有債務!$H$28:$H$28))+輸入與假設!$C$331 -> -178.944 | I92: 融資現金流依『融資分類』（判斷價＝股權發行價）；評價依第二輪分類，差額在錨定年末淨負債補回
A93: DCF 權重說明 | C93: =IF(C30=1,"DCF 失效，已以 EV/EBITDA 100% 計。",IF(AND(輸入與假設!$C$387<>2,C108<0),"DCF 為 $0 仍計 "&TEXT(輸入與假設!$C$380,"0%")&" 權重的原因：DCF 沒有失效，而是算出的股權價值為負（每股約 −$"&TEXT(ABS(C108),"0.0")&"），代表自由現金流折現後的企業價值不足以償還淨負債。EV/EBITDA 沒有扣除 GPU 汰換與擴張支出，保留 DCF 權重，是為了讓目標價反映「EBITDA 付不起資本成本」。若不計 DCF，目標價為 $"&TEXT(C43,"0.0")&"（"&CHOOSE(D107+2,"賣出","中立","買進")&"）；"&TEXT(輸入與假設!$C$380,"0%")&"／"&TEXT(1-輸入與假設!$C$380,"0%")&" 為判斷值。","")) | I93: 只在 DCF 被 0 截斷時顯示；DCF 失效時改為一句；DCF 為正時空白（與 HTML 同一字串）
A95: 目標價區間（情境區間、方法區間；評等仍依點位）
A96: 目標價區間｜點位（目前輸入的加權目標價） | C96: =C51 -> 199.27124 | I96: ="評等規則不變：空間 ≥"&IF(ROUND(ABS(輸入與假設!$C$405)*100,4)=INT(ROUND(ABS(輸入與假設!$C$405)*100,4)),TEXT(ROUND(ABS(輸入與假設!$C$405)*100,4),"0"),TEXT(ROUND(ABS(輸入與假設!$C$405)*100,4),"0.0"))&"%"&" 且終值占比 <"&IF(ROUND(ABS(輸入與假設!$C$406)*100,4)=INT(ROUND(ABS(輸入與假設!$C$406)*100,4)),TEXT(ROUND(ABS(輸入與假設!$C$406)*100,4),"0"),TEXT(ROUND(ABS(輸入與假設!$C$406)*100,4),"0.0"))&"%"&"、股權募資 ≤"&IF(輸入與假設!$C$408=INT(輸入與假設!$C$408),TEXT(輸入與假設!$C$408,"0"),TEXT(輸入與假設!$C$408,"0.0"))&" 倍現市值 → 買進；空間 ≤−"&IF(ROUND(ABS(輸入與假設!$C$407)*100,4)=INT(ROUND(ABS(輸入與假設!$C$407)*100,4)),TEXT(ROUND(ABS(輸入與假設!$C$407)*100,4),"0"),TEXT(ROUND(ABS(輸入與假設!$C$407)*100,4),"0.0"))&"%"&"，或股權募資 >"&IF(輸入與假設!$C$408=INT(輸入與假設!$C$408),TEXT(輸入與假設!$C$408,"0"),TEXT(輸入與假設!$C$408,"0.0"))&" 倍且空間 ≤−"&IF(ROUND(ABS(輸入與假設!$C$409)*100,4)=INT(ROUND(ABS(輸入與假設!$C$409)*100,4)),TEXT(ROUND(ABS(輸入與假設!$C$409)*100,4),"0"),TEXT(ROUND(ABS(輸入與假設!$C$409)*100,4),"0.0"))&"%"&" → 賣出；其餘中立" -> 評等規則不變：空間 ≥25% 且終值占比 <90%、股權募資 ≤1.5 倍現市值 → 買進；空間 ≤−15%，或股權募資 >1.5 倍且空間 ≤−8% → 賣出；其餘中立
A97: 目標價區間｜終值占 EV（評等用） | C97: =C22/MAX(ABS(C23),1)*IF(C23=0,1,SIGN(C23)) -> 1.1866554
A98: 目標價區間｜股權募資 ÷ 現市值（評等用） | C98: =SUM(各期收支!C92:G92)/(輸入與假設!$C$320*輸入與假設!$C$321) -> 0
A99: 目標價區間｜點位評等代碼（1＝買進、0＝中立、−1＝賣出） | C99: =IF(AND((C51/MAX(輸入與假設!$C$320,0.01)-1)>=輸入與假設!$C$405,$C$97<輸入與假設!$C$406,$C$98<=輸入與假設!$C$408),1,IF(OR((C51/MAX(輸入與假設!$C$320,0.01)-1)<=輸入與假設!$C$407,AND($C$98>輸入與假設!$C$408,(C51/MAX(輸入與假設!$C$320,0.01)-1)<=輸入與假設!$C$409)),-1,0)) -> -1 | D99: =CHOOSE(C99+2,"賣出","中立","買進") -> 賣出
A100: 目標價區間｜賣出門檻價（現價 × (1 − 15%)） | C100: =輸入與假設!$C$320*(1+輸入與假設!$C$407) -> 220.932
A101: 目標價區間｜保守 第三方可辨識站點（加權目標價／評等代碼／距賣出門檻） | C101: =輸入與假設!D439 -> 212.71365 | D101: =輸入與假設!E439 -> -1 | E101: =C101-$C$100 -> -8.2183547 | I101: 引用『輸入與假設』底部模擬運算表（情境選擇 1／2／3），保留其餘手動輸入
A102: 目標價區間｜基準 依資本支出指引（加權目標價／評等代碼／距賣出門檻） | C102: =輸入與假設!D440 -> 199.27124 | D102: =輸入與假設!E440 -> -1 | E102: =C102-$C$100 -> -21.660756
A103: 目標價區間｜積極 依公司容量目標（加權目標價／評等代碼／距賣出門檻） | C103: =輸入與假設!D441 -> 198.56586 | D103: =輸入與假設!E441 -> -1 | E103: =C103-$C$100 -> -22.366143
A104: 目標價區間｜情境區間（下緣／上緣） | C104: =MIN(C101,C103) -> 198.56586 | D104: =MAX(C101,C103) -> 212.71365
A105: 目標價區間｜方法區間倍數（下端／上端） | C105: =MIN(輸入與假設!$C$382,輸入與假設!$C$383) -> 5 | D105: =MAX(輸入與假設!$C$382,輸入與假設!$C$383) -> 6
A106: 目標價區間｜方法區間（下緣／上緣） | C106: =MIN(C48*IF(C30=1,0,輸入與假設!$C$380)+MAX(0,(C45*C105+C44*輸入與假設!$C$378-C40)/C41)*C42*IF(C30=1,1,1-輸入與假設!$C$380),C48*IF(C30=1,0,輸入與假設!$C$380)+MAX(0,(C45*D105+C44*輸入與假設!$C$378-C40)/C41)*C42*IF(C30=1,1,1-輸入與假設!$C$380)) -> 195.25159 | D106: =MAX(C48*IF(C30=1,0,輸入與假設!$C$380)+MAX(0,(C45*C105+C44*輸入與假設!$C$378-C40)/C41)*C42*IF(C30=1,1,1-輸入與假設!$C$380),C48*IF(C30=1,0,輸入與假設!$C$380)+MAX(0,(C45*D105+C44*輸入與假設!$C$378-C40)/C41)*C42*IF(C30=1,1,1-輸入與假設!$C$380)) -> 199.27124 | I106: ＝DCF 採用值 × 有效權重 ＋ EV/EBITDA 腿（倍數換成兩端）× 有效權重
A107: 目標價區間｜100% EV/EBITDA 目標價（價位／評等代碼） | C107: =C43 -> 251.86435 | D107: =IF(AND((C43/MAX(輸入與假設!$C$320,0.01)-1)>=輸入與假設!$C$405,$C$97<輸入與假設!$C$406,$C$98<=輸入與假設!$C$408),1,IF(OR((C43/MAX(輸入與假設!$C$320,0.01)-1)<=輸入與假設!$C$407,AND($C$98>輸入與假設!$C$408,(C43/MAX(輸入與假設!$C$320,0.01)-1)<=輸入與假設!$C$409)),-1,0)) -> 0 | E107: =CHOOSE(D107+2,"賣出","中立","買進") -> 中立
...

Sheet 評價_反向DCF
A1: 反向 DCF — 現價隱含什麼樣的收入與成本
A2: 不是問「值多少」，而是問「要值現價，營運要長什麼樣」。Excel 以『目標搜尋』反解；下方另附 HTML 即時計算結果的快照（v4.0 預設輸入）
A4: 即時：目前 DCF 與現價的差距
A5: 現價 | B5: =輸入與假設!$C$320 -> 259.92
A6: 目前 DCF 每股（依下限方式） | B6: =評價_DCF與目標價!C26 -> 119.98907
A7: 差距（DCF − 現價）＝目標搜尋的『設定儲存格』 | B7: =B6-B5 -> -139.93093
A8: 目前每 MW 年收入倍數／建置成本倍數 | B8: =輸入與假設!$C$32 -> 1 | C8: =輸入與假設!$C$223 -> 1
A10: 操作：用『目標搜尋』反解（資料 → 模擬分析 → 目標搜尋）
A11: ① 設定儲存格：本頁 B7；目標值：0
A12: ② 變數儲存格（擇一）：輸入與假設 B 區『每 MW 年收入倍數』→ 市價隱含單價；或 D 區『每 MW 建置成本倍數』→ 市價隱含建置成本；或 C 區『穩態 EBITDA 率』
A13: ③ 解完請記下結果，再把倍數改回 100%（或按 Ctrl+Z）。DCF 以 0 截斷時，負值區域斜率為 0，請從 100% 以上開始搜尋
A14: ④ 組合分析：先把 D 區建置成本倍數與 C 區穩態 EBITDA 率設為想測的值，再對『每 MW 年收入倍數』做目標搜尋，即得下方矩陣中的一格
A16: 快照：單一槓桿（HTML v4.0 預設輸入，DCF 0 截斷）
A17: 單一槓桿（其他不變） | B17: 目前 | C17: 市價隱含 | D17: 變動 | G17: 對照
A18: 2030 每 MW 年收入（US$m） | B18: 10.6813 | C18: 27.8436 | D18: 1.6068 | G18: Amazon 對照：OpenAI Trainium 合約隱含 6.25（IT）US$m/MW-年
A19: 每 MW 建置成本（US$m） | B19: 45.0478 | C19: 無解 | D19: 無解 | G19: Tokenomics 每 MW 全成本（IT＋自建機房）約 $47.6m/MW-IT
A20: 穩態 EBITDA 率（2030） | B20: 0.765 | C20: 無解 | D20: 無解 | G20: AI 雲端（算力）EBITDA 率；非 AI 事業 EBITDA 率固定不動。可觀察 neocloud 區間 IREN 約 35%、CRWV 約 59%（變動為百分點）
A21: （對照）加權目標價＝現價所需每 MW 年收入 | B21: 10.6813 | C21: 21.3141 | D21: 0.9955 | G21: 含 EV/EBITDA 腿（2029 錨定）；非純反向 DCF
A23: 快照：收入與成本的綜合影響——要值現價，2030 每 MW 年收入需要多少（US$m）
A24: 建置成本 ＼ 穩態 EBITDA 率 | B24: 0.35 | C24: 0.47 | D24: 0.59 | E24: 0.7 | I24: 矩陣保留 AI 雲端 EBITDA 率維度：非 AI 事業（EBITDA 率與同業倍數）不隨此表變動，表內只測算力業務的單位經濟
A25: $31.5m（-30%） | B25: 23.68 | C25: 23.68 | D25: 23.68 | E25: 23.68
A26: $36.0m（-20%） | B26: 25.07 | C26: 25.07 | D26: 25.07 | E26: 25.07
A27: $40.5m（-10%） | B27: 26.46 | C27: 26.46 | D27: 26.46 | E27: 26.46
A28: $45.0m（目前） | B28: 27.84 | C28: 27.84 | D28: 27.84 | E28: 27.84
A29: $49.6m（+10%） | B29: 29.27 | C29: 29.27 | D29: 29.27 | E29: 29.27
A30: 快照為靜態數值（HTML 以同一引擎即時計算）；改變輸入後請以目標搜尋重算，或參考 HTML『評價 → 反向 DCF』

Sheet 評價_可比公司
A1: 可比公司 — 以 EV/Sales 為主（市值：2026-09-21 收盤）
A2: EV＝市值＋（有息負債−非受限現金）；含租賃＝EV＋營業租賃負債。EV/EBITDA 僅供參考（GAAP EBITDA 為負者顯示 n/m）。此表不進入目標價。與 HTML Comps 分頁同一組數字
A4: 公司 | B4: 市值 | C4: 淨負債 | D4: EV | E4: TTM 營收 | F4: EV/Sales（TTM） | G4: 含租賃 EV/Sales | H4: TTM EBITDA | I4: EV/EBITDA | J4: 資料期 | K4: 備註
A5: CRWV CoreWeave | B5: 49.11 | C5: 46.03 | D5: =B5+C5 -> 95.14 | E5: 7.59 | F5: =D5/E5 -> 12.534914 | G5: =(D5+16.54)/E5 -> 14.714097 | H5: =-0.231+3.991 -> 3.76 | I5: =IF(H5>0,D5/H5,"n/m") -> 25.303191 | J5: TTM 至 Q2（6/30，10-Q）；市值與 EV 2026-10-07 | K5: 營業租賃負債 16.54；GAAP 營業損益 -0.231＋D&A 3.991。CRWV 市值與 EV 2026-10-07；TTM 至 Q2；租賃負債 16.54
A6: NBIS Nebius | B6: 68.49 | C6: 2.15 | D6: =B6+C6 -> 70.64 | E6: 1.36 | F6: =D6/E6 -> 51.941176 | G6: =(D6+1.6253)/E6 -> 53.13625 | H6: =-0.612+0.418 -> -0.194 | I6: =IF(H6>0,D6/H6,"n/m") -> n/m | J6: 營收 TTM 至 Q2；營業損益與 D&A 為 FY2025（20-F）；市值與 EV 2026-10-06 | K6: 營業租賃負債 1.6253；GAAP 營業損益 -0.612＋D&A 0.418。NBIS 市值與 EV 2026-10-06；EBITDA 用 FY2025
A7: IREN | B7: 18.61 | C7: 1.7 | D7: =B7+C7 -> 20.31 | E7: 0.707 | F7: =D7/E7 -> 28.727016 | G7: =(D7+0.003)/E7 -> 28.731259 | H7: =-1.047+0.418 -> -0.629 | I7: =IF(H7>0,D7/H7,"n/m") -> n/m | J7: FY26 10-K（6/30）；未更新，日期 2026-09-21 | K7: 營業租賃負債 0.003；GAAP 營業損益 -1.047＋D&A 0.418。自有電廠、營業租賃負債僅 0.003bn；FY26 合約 ARR 4.0bn
A8: APLD Applied Digital | B8: 8.22 | C8: 3.37 | D8: =B8+C8 -> 11.59 | E8: 0.6113 | F8: =D8/E8 -> 18.959594 | G8: =(D8+0.066)/E8 -> 19.067561 | H8: =-0.236+0.067 -> -0.169 | I8: =IF(H8>0,D8/H8,"n/m") -> n/m | J8: FY26 10-K（5/31）；未更新，日期 2026-09-21 | K8: 營業租賃負債 0.066；GAAP 營業損益 -0.236＋D&A 0.067。租約多未起租，營收尚未反映約 36bn 合約
A9: CORZ Core Scientific | B9: 5.9 | C9: 2.53 | D9: =B9+C9 -> 8.43 | E9: 0.4403 | F9: =D9/E9 -> 19.146037 | G9: =(D9+0.109)/E9 -> 19.393595 | H9: =-0.561+0.063 -> -0.498 | I9: =IF(H9>0,D9/H9,"n/m") -> n/m | J9: TTM 至 Q2（6/30）；未更新，日期 2026-09-21 | K9: 營業租賃負債 0.109；GAAP 營業損益 -0.561＋D&A 0.063。託管轉型期
A10: 同業中位數 | F10: =MEDIAN(F5:F9) -> 19.146037 | G10: =MEDIAN(G5:G9) -> 19.393595
A11: AMZN（TTM 至 Q2 2026） | B11: 2803.579 | C11: =輸入與假設!$C$322+SUMPRODUCT(資產負債_既有債務!$C$28:$C$28*(1-資產負債_既有債務!$H$24:$H$24))+輸入與假設!$C$331 -> -168.937 | D11: =B11+C11 -> 2634.642 | E11: 775.68 | F11: =D11/E11 -> 3.3965579 | G11: =(D11+96.32)/E11 -> 3.5207328 | H11: =93.712+75.2 -> 168.912 | I11: =IF(H11>0,D11/H11,"n/m") -> 15.59772 | J11: TTM 至 Q2 2026 | K11: EV 用 2026-09-21 市值（基本股）與評價日淨負債（可轉債全數以到期本金計入）；含租賃再加營業租賃負債 96.32
A12: AMZN 模型 2027E | B12: =輸入與假設!$C$320*評價_DCF與目標價!$C$90 -> 2866.9992 | C12: =評價_DCF與目標價!$C$91 -> -168.937 | D12: =B12+C12 -> 2698.0622 | E12: =損益!D9 -> 973.5439 | F12: =D12/E12 -> 2.7713822 | G12: =(D12+96.32)/E12 -> 2.8703197 | H12: =損益!D22 -> 243.24121 | I12: =D12/H12 -> 11.092126 | K12: 市值用評價股數（含價內可轉債轉股）、淨負債用評價淨負債；分母為模型 2027 營收
A14: 讀法：AMZN 為整體公司（零售＋AWS），倍數不可直接與純 AI 基礎設施同業比較；
A15: CRWV 以租約取得機房，加入營業租賃負債後倍數上升；AMZN 以自建為主（另有未起租承諾 137.2B 尚未入表）。
A16: 前瞻：見下方 AMZN 模型列。此表為市場比較用，不進入目標價。

Sheet AI增量報酬
A1: AI 增量報酬：對外 AI ROIC ＝(對外 AI 雲端 EBITDA − AI 折舊 × 對外比例)×(1 − 稅率) ÷ (平均 AI 投入資本 × 對外比例)，對 WACC
A2: 年化＝模型期 ÷ 期間長度（2026 只含 2H）；投入資本（全 AI）＝AI 期初毛額 × 淨額比＋累計 AI 成長型與汰換 − 累計 AI 折舊；對外口徑＝投入資本與折舊 × 對外比例（主值）；全 AI 口徑（含影子收入）只作對照；打平 k＝使錨定期對外 AI ROIC＝WACC 的 k（解出的門檻，不是輸入）
A4: 項目 | B4: 單位 | C4: 2026 | D4: 2027 | E4: 2028 | F4: 2029 | G4: 2030 | I4: 公式／來源說明
A5: 對外 AI 雲端營收（年化） | B5: US$bn | C5: =運營_產能與收入!C26/輸入與假設!C$34 -> 29.22991 | D5: =運營_產能與收入!D26/輸入與假設!D$34 -> 58.33118 | E5: =運營_產能與收入!E26/輸入與假設!E$34 -> 97.792303 | F5: =運營_產能與收入!F26/輸入與假設!F$34 -> 137.47943 | G5: =運營_產能與收入!G26/輸入與假設!G$34 -> 177.25826
A6: AI 雲端 EBITDA 率 | B6: % | C6: =輸入與假設!C$204 -> 0.80253284 | D6: =輸入與假設!D$204 -> 0.80721101 | E6: =輸入與假設!E$204 -> 0.80978531 | F6: =輸入與假設!F$204 -> 0.81104808 | G6: =輸入與假設!G$204 -> 0.81179812 | I6: Tokenomics 營運成本推得（輸入與假設 C 區）
A7: AI 雲端 EBITDA（年化） | B7: US$bn | C7: =C5*C6 -> 23.457963 | D7: =D5*D6 -> 47.085571 | E7: =E5*E6 -> 79.19077 | F7: =F5*F6 -> 111.50243 | G7: =G5*G6 -> 143.89792
A8: AI 營運成本（年化） | B8: US$bn | C8: =C5-C7 -> 5.7719473 | D8: =D5-D7 -> 11.245609 | E8: =E5-E7 -> 18.601533 | F8: =F5-F7 -> 25.977002 | G8: =G5-G7 -> 33.360338
A9: AI 折舊（年化） | B9: US$bn | C9: =輸入與假設!C$273/輸入與假設!C$34 -> 19.536327 | D9: =輸入與假設!D$273/輸入與假設!D$34 -> 39.594145 | E9: =輸入與假設!E$273/輸入與假設!E$34 -> 67.784135 | F9: =輸入與假設!F$273/輸入與假設!F$34 -> 96.479618 | G9: =輸入與假設!G$273/輸入與假設!G$34 -> 125.1751 | I9: D&A 分池（輸入與假設 D 區）
A10: 有效在役對外 MW（＝營收 ÷ 每 MW 年收入） | B10: MW | C10: =C5/MAX(0.000000000001,輸入與假設!C104*輸入與假設!$C$56/1000) -> 2987 | D10: =D5/MAX(0.000000000001,輸入與假設!D104*輸入與假設!$C$56/1000) -> 5708.5 | E10: =E5/MAX(0.000000000001,輸入與假設!E104*輸入與假設!$C$56/1000) -> 9337.5 | F10: =F5/MAX(0.000000000001,輸入與假設!F104*輸入與假設!$C$56/1000) -> 12966.4 | G10: =G5/MAX(0.000000000001,輸入與假設!G104*輸入與假設!$C$56/1000) -> 16595.2
A11: 租用對外 MW（平均） | B11: MW | C11: =(輸入與假設!$C$246+輸入與假設!C$247)/2 -> 0 | D11: =(輸入與假設!C$247+輸入與假設!D$247)/2 -> 0 | E11: =(輸入與假設!D$247+輸入與假設!E$247)/2 -> 0 | F11: =(輸入與假設!E$247+輸入與假設!F$247)/2 -> 0 | G11: =(輸入與假設!F$247+輸入與假設!G$247)/2 -> 0 | I11: capexModel.rentedExt（C20）：收入照算、投入資本與折舊不計
A12: 自有對外占自有 AI MW 比例 | B12: % | C12: =MAX(0,C10-C11)/MAX(0.000000001,C10/輸入與假設!$C$217-C11) -> 0.8 | D12: =MAX(0,D10-D11)/MAX(0.000000001,D10/輸入與假設!$C$217-D11) -> 0.8 | E12: =MAX(0,E10-E11)/MAX(0.000000001,E10/輸入與假設!$C$217-E11) -> 0.8 | F12: =MAX(0,F10-F11)/MAX(0.000000001,F10/輸入與假設!$C$217-F11) -> 0.8 | G12: =MAX(0,G10-G11)/MAX(0.000000001,G10/輸入與假設!$C$217-G11) -> 0.8 | I12: 投入資本與折舊按此比例分攤（無租用時＝對外比例；C11、C20）
A13: 每 MW 機房年租金（Tokenomics 機房成本 × 資本回收係數） | B13: US$bn/MW | C13: =(輸入與假設!C67*TK_CapexFacility_H100+輸入與假設!C74*TK_CapexFacility_H100+輸入與假設!C81*TK_CapexFacility_GB200+輸入與假設!C88*TK_CapexFacility_GB300+輸入與假設!C95*TK_CapexFacility_GB300+輸入與假設!C102*TK_CapexFacility_VR200)/MAX(0.000000001,輸入與假設!C103)/1000*0.1/(1-(1+0.1)^(-輸入與假設!$C$264)) -> 0.0014889304 | D13: =(輸入與假設!D67*TK_CapexFacility_H100+輸入與假設!D74*TK_CapexFacility_H100+輸入與假設!D81*TK_CapexFacility_GB200+輸入與假設!D88*TK_CapexFacility_GB300+輸入與假設!D95*TK_CapexFacility_GB300+輸入與假設!D102*TK_CapexFacility_VR200)/MAX(0.000000001,輸入與假設!D103)/1000*0.1/(1-(1+0.1)^(-輸入與假設!$C$264)) -> 0.0014889304 | E13: =(輸入與假設!E67*TK_CapexFacility_H100+輸入與假設!E74*TK_CapexFacility_H100+輸入與假設!E81*TK_CapexFacility_GB200+輸入與假設!E88*TK_CapexFacility_GB300+輸入與假設!E95*TK_CapexFacility_GB300+輸入與假設!E102*TK_CapexFacility_VR200)/MAX(0.000000001,輸入與假設!E103)/1000*0.1/(1-(1+0.1)^(-輸入與假設!$C$264)) -> 0.0014889304 | F13: =(輸入與假設!F67*TK_CapexFacility_H100+輸入與假設!F74*TK_CapexFacility_H100+輸入與假設!F81*TK_CapexFacility_GB200+輸入與假設!F88*TK_CapexFacility_GB300+輸入與假設!F95*TK_CapexFacility_GB300+輸入與假設!F102*TK_CapexFacility_VR200)/MAX(0.000000001,輸入與假設!F103)/1000*0.1/(1-(1+0.1)^(-輸入與假設!$C$264)) -> 0.0014889304 | G13: =(輸入與假設!G67*TK_CapexFacility_H100+輸入與假設!G74*TK_CapexFacility_H100+輸入與假設!G81*TK_CapexFacility_GB200+輸入與假設!G88*TK_CapexFacility_GB300+輸入與假設!G95*TK_CapexFacility_GB300+輸入與假設!G102*TK_CapexFacility_VR200)/MAX(0.000000001,輸入與假設!G103)/1000*0.1/(1-(1+0.1)^(-輸入與假設!$C$264)) -> 0.0014889304 | I13: 出租方打平租金＝在役世代加權 TK_CapexFacility × 10% 資本回收係數（機房年限）[Derived]（C22）
A14: 機房租金（自有對外 MW ×(1 − 自建比例)） | B14: US$bn | C14: =(1-輸入與假設!$C$218)*MAX(0,C10-C11)*C13 -> 0.88948704 | D14: =(1-輸入與假設!$C$218)*MAX(0,D10-D11)*D13 -> 1.6999119 | E14: =(1-輸入與假設!$C$218)*MAX(0,E10-E11)*E13 -> 2.7805776 | F14: =(1-輸入與假設!$C$218)*MAX(0,F10-F11)*F13 -> 3.8612135 | G14: =(1-輸入與假設!$C$218)*MAX(0,G10-G11)*G13 -> 4.9418197 | I14: 只進 AI 增量報酬（資金與評價的租金現金已在租賃承諾內，不重複扣；C22）
A15: 租用對外 MW 租金 | B15: US$bn | C15: =C11*0/1000 -> 0 | D15: =D11*0/1000 -> 0 | E15: =E11*0/1000 -> 0 | F15: =F11*0/1000 -> 0 | G15: =G11*0/1000 -> 0 | I15: ＝租用對外 MW × 每 MW 年租金（capexModel.rentedExt.rentMW；C20）
A16: 對外 AI EBITDA（扣租金） | B16: US$bn | C16: =C7-C14-C15 -> 22.568476 | D16: =D7-D14-D15 -> 45.385659 | E16: =E7-E14-E15 -> 76.410193 | F16: =F7-F14-F15 -> 107.64121 | G16: =G7-G14-G15 -> 138.9561
A17: 對外 AI 折舊（年化，按對外比例分攤） | B17: US$bn | C17: =C9*C12 -> 15.629061 | D17: =D9*D12 -> 31.675316 | E17: =E9*E12 -> 54.227308 | F17: =F9*F12 -> 77.183695 | G17: =G9*G12 -> 100.14008
A18: 對外 AI NOPAT（年化） | B18: US$bn | C18: =(C16-C17)*(1-輸入與假設!$C$332) -> 5.734732 | D18: =(D16-D17)*(1-輸入與假設!$C$332) -> 11.330227 | E18: =(E16-E17)*(1-輸入與假設!$C$332) -> 18.331936 | F18: =(F16-F17)*(1-輸入與假設!$C$332) -> 25.170093 | G18: =(G16-G17)*(1-輸入與假設!$C$332) -> 32.07756 | I18: ＝(對外 EBITDA − 對外折舊)×(1 − 稅率)
A19: AI 投入資本（期初） | B19: US$bn | C19: =(輸入與假設!$C$262+輸入與假設!$C$263)*輸入與假設!$C$267 -> 73.770469 | D19: =C21 -> 153.57905 | E19: =D21 -> 312.25576 | F19: =E21 -> 448.80839 | G19: =F21 -> 561.9023 | I19: 2026＝AI 期初毛額 × 淨額比；之後＝前期期末
A20: AI 投入（成長型＋汰換，模型期） | B20: US$bn | C20: =輸入與假設!C$254+輸入與假設!C$258 -> 89.57674 | D20: =輸入與假設!D$254+輸入與假設!D$258 -> 198.27086 | E20: =輸入與假設!E$254+輸入與假設!E$258 -> 204.33677 | F20: =輸入與假設!F$254+輸入與假設!F$258 -> 209.57353 | G20: =輸入與假設!G$254+輸入與假設!G$258 -> 325.03845
A21: AI 投入資本（期末） | B21: US$bn | C21: =C19+C20-輸入與假設!C$273 -> 153.57905 | D21: =D19+D20-輸入與假設!D$273 -> 312.25576 | E21: =E19+E20-輸入與假設!E$273 -> 448.80839 | F21: =F19+F20-輸入與假設!F$273 -> 561.9023 | G21: =G19+G20-輸入與假設!G$273 -> 761.76566 | I21: ＝期初＋投入 − AI 折舊
A22: 對外 AI 平均投入資本（按對外比例分攤） | B22: US$bn | C22: =(C19+C21)/2*C12 -> 90.939806 | D22: =(D19+D21)/2*D12 -> 186.33392 | E22: =(E19+E21)/2*E12 -> 304.42566 | F22: =(F19+F21)/2*F12 -> 404.28428 | G22: =(G19+G21)/2*G12 -> 529.46718
A23: 對外 AI ROIC（主值） | B23: % | C23: =C18/MAX(0.000000001,C22) -> 0.063060746 | D23: =D18/MAX(0.000000001,D22) -> 0.060806038 | E23: =E18/MAX(0.000000001,E22) -> 0.060218104 | F23: =F18/MAX(0.000000001,F22) -> 0.062258402 | G23: =G18/MAX(0.000000001,G22) -> 0.060584605 | I23: ＝對外 NOPAT ÷ 對外平均投入資本（對照表 r1 C11）
A24: WACC | B24: % | C24: =輸入與假設!$C$342 -> 0.1250256 | D24: =輸入與假設!$C$342 -> 0.1250256 | E24: =輸入與假設!$C$342 -> 0.1250256 | F24: =輸入與假設!$C$342 -> 0.1250256 | G24: =輸入與假設!$C$342 -> 0.1250256
A25: 對外 AI ROIC − WACC | B25: % | C25: =C23-C24 -> -0.061964854 | D25: =D23-D24 -> -0.064219563 | E25: =E23-E24 -> -0.064807497 | F25: =F23-F24 -> -0.062767198 | G25: =G23-G24 -> -0.064440996 | I25: 負值＝AI 投資未賺到資金成本
A26: 影子收入（自用 AI MW × 每 MW 年收入，年化） | B26: US$bn | C26: =C5*(1/輸入與假設!$C$217-1) -> 7.3074775 | D26: =D5*(1/輸入與假設!$C$217-1) -> 14.582795 | E26: =E5*(1/輸入與假設!$C$217-1) -> 24.448076 | F26: =F5*(1/輸入與假設!$C$217-1) -> 34.369857 | G26: =G5*(1/輸入與假設!$C$217-1) -> 44.314565 | I26: 自用 AI MW＝對外 ×(1 ÷ 對外比例 − 1)；只作對照，不進評價（對照表 r1 D2）
A27: 全 AI ROIC（含影子收入，對照） | B27: % | C27: =(C7+C26*C6-(1-輸入與假設!$C$218)*MAX(0.000000001,C10/輸入與假設!$C$217-C11)*C13-C15-C9)*(1-輸入與假設!$C$332)/MAX(0.000000001,(C19+C21)/2) -> 0.063060746 | D27: =(D7+D26*D6-(1-輸入與假設!$C$218)*MAX(0.000000001,D10/輸入與假設!$C$217-D11)*D13-D15-D9)*(1-輸入與假設!$C$332)/MAX(0.000000001,(D19+D21)/2) -> 0.060806038 | E27: =(E7+E26*E6-(1-輸入與假設!$C$218)*MAX(0.000000001,E10/輸入與假設!$C$217-E11)*E13-E15-E9)*(1-輸入與假設!$C$332)/MAX(0.000000001,(E19+E21)/2) -> 0.060218104 | F27: =(F7+F26*F6-(1-輸入與假設!$C$218)*MAX(0.000000001,F10/輸入與假設!$C$217-F11)*F13-F15-F9)*(1-輸入與假設!$C$332)/MAX(0.000000001,(F19+F21)/2) -> 0.062258402 | G27: =(G7+G26*G6-(1-輸入與假設!$C$218)*MAX(0.000000001,G10/輸入與假設!$C$217-G11)*G13-G15-G9)*(1-輸入與假設!$C$332)/MAX(0.000000001,(G19+G21)/2) -> 0.060584605 | I27: 全 AI 機房租金＝(1 − 自建)× 自有 AI 總 MW × 每 MW 機房年租金（C22）
A29: 打平 k（使 2029 對外 AI ROIC＝WACC） | C29: =輸入與假設!$C$56*(輸入與假設!$C$342*F22/(1-輸入與假設!$C$332)+F8+F14+F15+F17)/MAX(0.000000001,F5) -> 1.1646319 | I29: ＝k ×(WACC × 對外平均投入資本 ÷ (1 − 稅率)＋營運成本＋租金＋對外折舊) ÷ 營收（AI EBITDA 對 k 線性，閉式解；對外口徑）
A30: 目前採用 k | C30: =輸入與假設!$C$56 -> 0.952
A32: C15 一致性檢查（2029，對外口徑；序列拆解，各步差額加總＝總差距）
A33: IF_HoldEcon 隱含報酬（Tokenomics WACC，經濟口徑） | C33: 0.1 | I33: IF_HoldEcon 的資本回收年金折現率：Tokenomics Inputs!E28「WACC（經濟口徑）」基準 10%（builder v5：L1_HoldEconGW＝資本回收年金（WACC 10%）＋營運費用）；非具名範圍，換 Tokenomics 版本時核對 [Verified]；只用於一致性檢查（對照表 r1 C15）
A34: 在役對外 MW（有效，＝營收 ÷ 每 MW 年收入） | C34: =F10 -> 12966.4
A35: 自有在役對外 MW（有效 − 租用） | C35: =MAX(0,C34-F11) -> 12966.4
