Workbook

Sheet README
A1: Amazon（AMZN）個股模型 v0.3（命題模組＋官方營收分部 → 損益表） 2026-10-27
A2: 版本：v0.3（架構重建；取代 v0.2.2 的 CoreWeave 式收支引擎，舊引擎移至 legacy_v0.2/）。資料截至 2026Q2（10-Q 2026-07-31）；FY2026＝上半年實績＋下半年模型；2026Q3 財報 2026-10-29 公布後以 v0.3.1 滾入。
A3: 命題：AWS 的 AI 容量（Trainium＋NVIDIA）能否以高於資金成本的報酬變現，零售與廣告的現金流能否支應資本支出。
A4: 核心問題：FY2028 AWS 營業利益率與自由現金流（扣股利後）是否轉正並維持。
A5: ="投資建議："&Val!B24&"（加權目標價 US$"&TEXT(Val!B19,"0.00")&"，現價 US$"&TEXT(px,"0.00")&"〔2026-10-26〕，上檔空間 "&TEXT(Val!B21,"+0.0%;-0.0%")&"；依五級固定規則）" -> 投資建議：中立（加權目標價 US$210.79，現價 US$249.09〔2026-10-26〕，上檔空間 -15.4%；依五級固定規則）
A6: ="命題答案（情境 B）：FY2028 對外 AI ROIC "&TEXT(Thesis!$I$114,"0.0%")&"，低於 WACC "&TEXT(wacc,"0.0%")&"；打平所需機隊平均 k "&TEXT(Thesis!$I$116,"0.00")&"，模型 k "&TEXT(Thesis!$I$115,"0.00")&"。FY2028 AWS 營業利益率 "&TEXT(PL!$I$123,"0.0%")&"（FY2025 "&TEXT(PL!$D$123,"0.0%")&"）；FY2028 自由現金流扣股利 "&TEXT(CF!$I$60,"#,##0.0")&"；收支關卡（FY2026–FY2030 合計，情境加權）"&TEXT(CF!E6,"#,##0.0")&"。" -> 命題答案（情境 B）：FY2028 對外 AI ROIC 6.6%，低於 WACC 11.3%；打平所需機隊平均 k 1.21，模型 k 0.99。FY2028 AWS 營業利益率 34.7%（FY2025 35.4%）；FY2028 自由現金流扣股利 -15.5；收支關卡（FY2026–FY2030 合計，情境加權）40.4。
A7: ="重點觀察 1：目標價 US$"&TEXT(Val!B19,"0.00")&"＝DCF "&TEXT(Val!B17,"0.00")&"（永續價值占 EV "&TEXT(Val!C8,"0%")&"）與分部加總 "&TEXT(Val!B18,"0.00")&" 各半；DCF 低是因為 WACC "&TEXT(wacc,"0.0%")&" 下，2027–2029 的 AI 資本支出（情境 B FY2027 "&TEXT(CF!$H$55,"#,##0")&"）讓 FCFF 為負，而 AI 增量報酬低於資金成本。" -> 重點觀察 1：目標價 US$210.79＝DCF 150.74（永續價值占 EV 79%）與分部加總 270.83 各半；DCF 低是因為 WACC 11.3% 下，2027–2029 的 AI 資本支出（情境 B FY2027 273）讓 FCFF 為負，而 AI 增量報酬低於資金成本。
A8: ="重點觀察 2：分部加總中 AWS 其他（非 AI 雲端）占 "&TEXT(Val!$C$167/Val!$C$175,"0%")&"、廣告占 "&TEXT(Val!$C$161/Val!$C$175,"0%")&"；零售本業未來 12 個月 EBITDA（SBC 加回）僅 "&TEXT(Val!$C$162,"#,##0")&"，廣告利潤（m_ad 50%）幾乎是零售分部的全部利潤；AWS AI 以自身 DCF 計只值 "&TEXT(Val!$C$174,"#,##0")&"。" -> 重點觀察 2：分部加總中 AWS 其他（非 AI 雲端）占 47%、廣告占 19%；零售本業未來 12 個月 EBITDA（SBC 加回）僅 52，廣告利潤（m_ad 50%）幾乎是零售分部的全部利潤；AWS AI 以自身 DCF 計只值 29。
A9: ="重點觀察 3：三情境目標價 A "&TEXT(Val!B7,"0")&"／B "&TEXT(Val!C7,"0")&"／C "&TEXT(Val!D7,"0")&"；新產能 k 是最大的命題驅動（Sens：k_C "&TEXT(Sens!D5,"+0%;-0%")&"、k_A "&TEXT(Sens!D6,"+0%;-0%")&"），對外比例 ±20pt 為 "&TEXT(Sens!D7,"+0%;-0%")&"／"&TEXT(Sens!D8,"+0%;-0%")&"；市場共識目標價 "&TEXT(cons_tp,"0")&"。" -> 重點觀察 3：三情境目標價 A 265／B 199／C 179；新產能 k 是最大的命題驅動（Sens：k_C -10%、k_A +32%），對外比例 ±20pt 為 -0%／-1%；市場共識目標價 332。
A11: 驅動 → 推導對照表（每頁輸入、推導量、因果方向）
A12: In → Thesis：對外 AI MW（期初 2,080 MW、每年新增 pace）× Tokenomics IF_HoldEcon × k → AWS AI 營收；新增 MW ÷ 對外比例 ×（IT＋自建機房成本）→ AI 資本支出 → IT 6 年／機房 20 年折舊 → AWS AI 營業利益（對外）與自用 AI 成本（零售）。
A13: In → Seg：零售六條營收線（2H26＝2H25 ×（1＋2H25 年增）× 校準係數〔隱含 2026Q3＝指引中點〕，之後收斂到長期年增）→ 零售合計 × 北美比例 → North America／International；AWS＝AWS AI＋AWS 其他（殘差起算、收斂到 8%）。
A14: Seg、Thesis → PL：北美／國際營業利益＝廣告營收 × 50%＋零售本業營收 × 本業利益率（實績殘差＋每年改善）− 自用 AI 成本；AWS 營業利益＝AWS AI＋AWS 其他 × 近四季利益率 → 合併營業利益 → 利息（CF）、稅 17.4% → 淨利 → EPS。
A15: PL → CF：淨利＋分部折舊＋SBC＋其他 − 資本支出（AI＋AWS 其他 20%＋零售 5.9%）− 融資租賃本金 → 自由現金流；股利 0、回購 0；現金低於 50 即舉債 → 利息費用回到 PL。
A16: PL、CF → Val：DCF（FCFF、WACC、RONIC 永續）＋分部加總（廣告、零售本業、AWS 其他、AWS AI × 同業倍數）＋持股（Anthropic、OpenAI）→ 情境目標價 → 情境加權 → 上檔空間 → 投資建議。
A18: 工作表：README → In（輸入）→ Q（實績與核對）→ Thesis（命題模組）→ Seg（營收分部）→ PL → CF → Val → Recon（共識、指引、v0.2.2）→ Sens（敏感度）→ Sources。
A19: 標記：Verified、Interested-party、Analogy、Assumed、Derived。沿用 v0.2.2：k 規格（kspec.py）、C10 基準速度、對外比例、Tokenomics v21.4 快照、WACC 輸入、持股與同業倍數。SemiAnalysis 未使用。
A20: 已知限制：(1) 公司未揭露 AI 在役 MW、對外比例與 AI 營收，AWS AI／AWS 其他的歷史分拆為估計；(2) 分部共識未找到；(3) 同業倍數與 WACC 輸入沿用 2026-10-07；(4) 到期債務假設全數再融資；(5) 自用 AI 讀法 1 為主值（C16 待決）。

Sheet In
A1: In — 輸入（藍字；基準欄 E，低 D、高 F）。金額 US$bn、每股 US$、MW＝IT 關鍵電力 MW。每列一個鍵（定義名稱＝鍵）；Analogy、Assumed 一律給低／高區間
A2: 標記：Verified／Interested-party／Analogy／Assumed／Derived。「沿用 v0.2.2」＝v0.2.2 已核准的參數與證據（k 規格 kspec.py、C10 基準速度、對外比例、Tokenomics v21.4 快照），出處見 legacy_v0.2/ 與 docs/handoff。不以公司雲端營收、RPO、AI run-rate 反推 k 或每 MW 價格（共同規則第 4 節）；公司說法只作 Recon 驗證列。SemiAnalysis 未使用
A3: 鍵 | B3: 項目 | C3: 單位 | D3: 低 | E3: 基準 | F3: 高 | G3: 標記 | H3: 來源 | I3: 說明
A4: A. 價格、股數與共識目標價
A5: px | B5: AMZN 現價（2026-10-26 收盤） | C5: US$ | E5: 249.09 | G5: Verified | H5: S13；S14 | I5: 前收 248.00（10-23）；市值約 2.69T（Yahoo 盤中）
A6: sh_out | B6: 流通股數（2026-07-22，10-Q 封面） | C6: 十億股 | E6: 10.786314 | G6: Verified | H6: S02 | I6: 10,786,313,572 股
A7: sh_awd | B7: 未歸屬股份獎勵（2026-06-30） | C7: 十億股 | E7: 0.244 | G7: Verified | H7: S02 | I7: 244 百萬股
A8: sh_val | B8: 分部加總用稀釋股數＝流通股數＋未歸屬獎勵（倍數為 SBC 加回口徑，故計入稀釋） | C8: 十億股 | E8: =sh_out+sh_awd -> 11.030314 | G8: Derived | H8: 修正一（F2） | I8: DCF 視 SBC 為現金成本，改用流通股數 sh_out，不另計稀釋
A9: cons_tp | B9: 市場共識目標價（S&P Global，60 位平均） | C9: US$ | D9: 230 | E9: 332.24 | F9: 405 | G9: Interested-party | H9: S15 | I9: 中位數 330；Strong Buy 42、Buy 16、Hold 2（2026-10）；MarketBeat 2026-10-07 平均 322.86（獨立彙整）
A10: B. 折現率（CAPM；沿用 v0.2.2 輸入，現價更新）
A11: rf | B11: 無風險利率（10 年美債，2026-10-26） | C11: % | E11: 0.05 | G11: Verified | H11: S28 | I11: 美國財政部每日殖利率曲線：10-26 5.00%、10-23 5.00%、10-22 4.96%（v0.2.2 用 10-07 5.28%）
A12: beta_sa | B12: 原始 Beta：StockAnalysis 5 年月資料（Yahoo 同值，推測同源） | C12: x | E12: 1.46 | G12: Verified | H12: 沿用 v0.2.2（事實總帳 val.beta.sa）
A13: beta_gf | B13: 原始 Beta：GuruFocus 3 年 | C13: x | E13: 1.567 | G13: Verified | H13: 沿用 v0.2.2（事實總帳 val.beta.gurufocus） | I13: 不同資料商、不同期間（C13 獨立來源）
A14: beta | B14: Beta（Blume 調整 0.67 × 原始＋0.33，兩個獨立來源的中位數） | C14: x | D14: =MIN(0.67*beta_sa+0.33,0.67*beta_gf+0.33) -> 1.3082 | E14: =MEDIAN(0.67*beta_sa+0.33,0.67*beta_gf+0.33) -> 1.344045 | F14: =MAX(0.67*beta_sa+0.33,0.67*beta_gf+0.33) -> 1.37989 | G14: Derived | H14: 修正一（F4） | I14: v0.2.2 為原始平均 1.5135
A15: erp | B15: 股權風險溢酬 | C15: % | D15: 0.04 | E15: 0.05 | F15: 0.06 | G15: Assumed | H15: 沿用 v0.2.2（對照表預設 10）
A16: kd_new | B16: 新增借款利率（2026-07 新發 2066 票據有效利率；只用於利息費用） | C16: % | E16: 0.0633 | G16: Interested-party | H16: S02 | I16: 期後事項：固定票面 4.60%–6.25%、有效 4.67%–6.33%
A17: kd_spr | B17: AA 級公司債約 10 年期利差（相對 10 年美債） | C17: % | D17: 0.005 | E17: 0.0065 | F17: 0.01 | G17: Assumed | H17: 修正一（F4）：kd＝約 10 年期公司債殖利率 | I17: Amazon 各期票據的 10 年期殖利率：未找到（本輪網路搜尋額度用盡）
A18: kd | B18: 稅前債務成本（WACC 用）＝rf＋利差 | C18: % | E18: =rf+kd_spr -> 0.0565 | G18: Derived | H18: 修正一（F4）
A19: tax | B19: 稅率（2023–2025 有效稅率平均） | C19: % | D19: 0.135 | E19: =AVERAGE(Q!$C$40,Q!$D$40,Q!$E$40) -> 0.17358453 | F19: 0.23 | G19: Derived | H19: S01 | I19: 18.96%、13.50%、19.61%；沿用 v0.2.2（17.36%）；2026 上半年不含一次性項目 23%
A20: debt_q2 | B20: 債務面額（2026-06-30） | C20: US$bn | E20: 132.995 | G20: Verified | H20: S02 | I20: 附註 5
A21: fl_pv | B21: 融資租賃負債現值（2026-06-30） | C21: US$bn | E21: 13.451 | G21: Verified | H21: S02 | I21: 附註 4
A22: fin_obl | B22: 融資義務（financing obligations，2026-06-30） | C22: US$bn | E22: 11.07 | G22: Verified | H22: S02
A23: fin_debt | B23: 類債務（融資租賃＋融資義務；淨負債與 WACC 的 D 皆計入，模型期間持平） | C23: US$bn | E23: =fl_pv+fin_obl -> 24.521 | G23: Derived | H23: 修正一（F6、核對第 4 點）
A24: ke | B24: 股權成本＝rf＋β × ERP | C24: % | E24: =rf+beta*erp -> 0.11720225 | G24: Derived | H24: CAPM
A25: wacc | B25: WACC＝E/(D+E) × ke＋D/(D+E) × kd ×（1 − 稅率）；E＝現價 × 流通股數；D＝債務面額＋類債務 | C25: % | E25: =px*sh_out/(px*sh_out+debt_q2+fin_debt)*ke+(debt_q2+fin_debt)/(px*sh_out+debt_q2+fin_debt)*kd*(1-tax) -> 0.11329742 | G25: Derived | H25: 修正一（F4） | I25: v0.2.2 為 12.5%
A26: tg | B26: 永續成長率 g | C26: % | D26: 0.02 | E26: 0.03 | F26: 0.04 | G26: Assumed | H26: 工作單第 2 節（g 3%）
A27: ronic | B27: 永續期新投資報酬率（RONIC；預設＝WACC：永續成長不創造價值） | C27: % | E27: =wacc -> 0.11329742 | F27: =wacc+0.05 -> 0.16329742 | G27: Assumed | H27: 判斷（報告第 5 節；F5） | I27: 高值＝WACC＋5pt（Sens）
A28: w_dcf | B28: 目標價中 DCF 的權重；其餘為分部加總（SOTP） | C28: % | E28: 0.5 | G28: Assumed | H28: 工作單第 2 節（[判斷] 預設 DCF 50%＋分部加總 50%） | I28: Andy 可改
A29: w_A | B29: 情境權重 A（樂觀） | C29: % | E29: 0.25 | G29: Assumed | H29: 工作單第 2 節（[判斷] 預設 A 25%／B 50%／C 25%） | I29: 三者合計 100%
A30: w_B | B30: 情境權重 B（基準） | C30: % | E30: 0.5 | G30: Assumed | H30: 工作單第 2 節（[判斷] 預設 A 25%／B 50%／C 25%） | I30: 三者合計 100%
A31: w_C | B31: 情境權重 C（保守） | C31: % | E31: 0.25 | G31: Assumed | H31: 工作單第 2 節（[判斷] 預設 A 25%／B 50%／C 25%） | I31: 三者合計 100%
A32: tp_yf | B32: 目標價時點（2027-10-27）距評價基準日（2026-12-31）年數 | C32: 年 | E32: =(DATE(2027,10,27)-DATE(2026,12,31))/365 -> 0.82191781 | G32: Derived | H32: 目標價約 12 個月後 | I32: DCF 情境價值以 ke 推到目標價時點
A33: C. 命題模組：AWS AI（對外 AI 在役 MW × 每 MW 年收入；沿用 v0.2.2）
A34: mw_ye23 | B34: 對外 AI 在役 MW（2023 年底） | C34: MW | E34: 120 | G34: Assumed | H34: 沿用 v0.2.2（defaults.mwYearEnd） | I34: 公司未揭露 AI 在役 MW；只用於歷史分拆與折舊年份
A35: mw_ye24 | B35: 對外 AI 在役 MW（2024 年底） | C35: MW | E35: 360 | G35: Assumed | H35: 沿用 v0.2.2（defaults.mwYearEnd） | I35: 同上
A36: mw_ye25 | B36: 對外 AI 在役 MW（2025 年底） | C36: MW | D36: 1100 | E36: 1440 | F36: 1800 | G36: Assumed | H36: 沿用 v0.2.2（defaults.mwYearEnd） | I36: Trainium2 1.4M 顆 × 0.871 kW ≈ 1,220 MW-IT（事實總帳 chip.trn2.mwFromLanded）
A37: mw_open | B37: 對外 AI 在役 MW（期初 2026-06-30）＝在役 AI 2,600 × 對外 80% | C37: MW | D37: 1400 | E37: 2080 | F37: 2970 | G37: Derived | H37: S19；S20 | I37: Epoch 三站 1,422 MW（Trainium2）＋NVIDIA 推估；第三方估計，區間見事實總帳 mw.ai.ext.2026q2
A38: pace_A | B38: 情境 A：對外 AI MW 每年新增（公司「2027 年底容量為 2025 年兩倍」，以 MS 6＋8 GW 對照） | C38: MW/年 | E38: 3733 | G38: Derived | H38: 沿用 v0.2.2（scenarios.mwPath.pace.high）；S30 | I38: 每年 +7 GW × AI 占新增 80% ÷ PUE 1.2 × 對外 80%
A39: pace_B | B39: 情境 B：對外 AI MW 每年新增（2026 資本支出指引 220 隱含的建置量，C10） | C39: MW/年 | E39: 3634.3 | G39: Derived | H39: 沿用 v0.2.2（scripts/calib_pace.js 解出，C10） | I39: 這是把支出換成實體產能（物理換算），不是以營收反推單價
A40: pace_C | B40: 情境 C：對外 AI MW 每年新增（與 B 相同：資本支出照指引投入，下檔在變現） | C40: MW/年 | E40: =pace_B -> 3634.3 | G40: Assumed | H40: 判斷（報告第 5 節） | I40: v0.2.2 的保守情境為 Epoch 站點速度 720／年；本版改為變現不如預期
A41: ext_sh | B41: 對外比例（AI MW 中租給客戶的比例） | C41: % | D41: 0.6 | E41: 0.8 | F41: 1 | G41: Assumed | H41: 沿用 v0.2.2（對照表 r1 C23：公司未揭露、最大不確定） | I41: Anthropic Trainium2 三站全為對外；自用（Alexa+、Rufus、Nova、廣告）未揭露；Sens ±20pt
A42: long_sh | B42: 長約占對外容量比例 | C42: % | D42: 0.7 | E42: 0.8 | F42: 0.9 | G42: Assumed | H42: 沿用 v0.2.2（pricing.longShare） | I42: Anthropic Trainium2 三站＋OpenAI 兩筆占多數
A43: p_spot | B43: H100 現貨價（Silicon Data 指數） | C43: US$/GPU-hr | E43: 2.82 | G43: Verified | H43: S18 | I43: 2026-10-06；MAG 三家共用（C1）
A44: p_list | B44: AWS p5.48xlarge 隨需（每 GPU 小時） | C44: US$/GPU-hr | E44: 6.88 | G44: Verified | H44: S18 | I44: 公開牌價（賣價，非成交價）；k 高軸
A45: p_long | B45: 長約等值價格（判斷倍數 0.75 × v5.27 VR200 成本 12.762） | C45: US$m/MW-年 | E45: 9.5715 | G45: Assumed | H45: 沿用 v0.2.2（legacy_v0.2/kspec.py long.base） | I45: 判斷值，不是觀察到的市場價格
A46: p_long_lo | B46: 長約等值價格下緣（判斷倍數 0.55 × 12.762） | C46: US$m/MW-年 | E46: 7.0191 | G46: Assumed | H46: 沿用 v0.2.2（legacy_v0.2/kspec.py long.low） | I46: Anthropic 下限 0.22–0.45 只作對照
A47: tk_he_h100 | B47: Tokenomics IF_HoldEcon｜Hopper H100（每 MW 年持有成本，經濟口徑、基準） | C47: US$m/MW-年 | E47: 9.7030873 | G47: Derived | H47: S17 | I47: WACC 10% 下的打平持有成本（資本回收年金＋營運費用）
A48: tk_he_gb200 | B48: Tokenomics IF_HoldEcon｜GB200 NVL72（每 MW 年持有成本，經濟口徑、基準） | C48: US$m/MW-年 | E48: 8.8281656 | G48: Derived | H48: S17 | I48: WACC 10% 下的打平持有成本（資本回收年金＋營運費用）
A49: tk_he_gb300 | B49: Tokenomics IF_HoldEcon｜GB300 NVL72（每 MW 年持有成本，經濟口徑、基準） | C49: US$m/MW-年 | E49: 10.886411 | G49: Derived | H49: S17 | I49: WACC 10% 下的打平持有成本（資本回收年金＋營運費用）
A50: tk_he_vr200 | B50: Tokenomics IF_HoldEcon｜VR200 NVL72（每 MW 年持有成本，經濟口徑、基準） | C50: US$m/MW-年 | E50: 12.225471 | G50: Derived | H50: S17 | I50: WACC 10% 下的打平持有成本（資本回收年金＋營運費用）
A51: tk_cx_h100 | B51: Tokenomics IF_CapexIT｜Hopper H100（每 MW IT 資本支出） | C51: US$m/MW | E51: 27.510214 | G51: Derived | H51: S17
A52: tk_cx_gb200 | B52: Tokenomics IF_CapexIT｜GB200 NVL72（每 MW IT 資本支出） | C52: US$m/MW | E52: 24.015174 | G52: Derived | H52: S17
A53: tk_cx_gb300 | B53: Tokenomics IF_CapexIT｜GB300 NVL72（每 MW IT 資本支出） | C53: US$m/MW | E53: 32.237224 | G53: Derived | H53: S17
A54: tk_cx_vr200 | B54: Tokenomics IF_CapexIT｜VR200 NVL72（每 MW IT 資本支出） | C54: US$m/MW | E54: 37.586352 | G54: Derived | H54: S17
A55: tk_ox_h100 | B55: Tokenomics IF_OpexGW｜Hopper H100（每 MW 年營運費用，不含折舊、含電費） | C55: US$m/MW-年 | E55: 1.8846675 | G55: Derived | H55: S17
A56: tk_ox_gb200 | B56: Tokenomics IF_OpexGW｜GB200 NVL72（每 MW 年營運費用，不含折舊、含電費） | C56: US$m/MW-年 | E56: 1.8122327 | G56: Derived | H56: S17
A57: tk_ox_gb300 | B57: Tokenomics IF_OpexGW｜GB300 NVL72（每 MW 年營運費用，不含折舊、含電費） | C57: US$m/MW-年 | E57: 1.9826348 | G57: Derived | H57: S17
A58: tk_ox_vr200 | B58: Tokenomics IF_OpexGW｜VR200 NVL72（每 MW 年營運費用，不含折舊、含電費） | C58: US$m/MW-年 | E58: 2.0934955 | G58: Derived | H58: S17
A59: tk_gpuhr | B59: Tokenomics IF_GPUhrEcon｜Hopper H100（每 GPU 小時持有成本） | C59: US$/GPU-hr | E59: 1.5425965 | G59: Derived | H59: S17 | I59: k_現貨的分母
A60: tk_fac | B60: Tokenomics L1_FacCapexMW（每 MW 機房資本支出） | C60: US$m/MW | E60: 12.67 | G60: Derived | H60: S17
A61: tk_life | B61: AI IT 設備折舊年限（Tokenomics IF_DeprLifeIT） | C61: 年 | D61: 5 | E61: 6 | F61: 7 | G61: Derived | H61: S17 | I61: 管理層口述伺服器 5–6 年（事實總帳 guide.server.life）
A62: fac_life | B62: 機房折舊年限 | C62: 年 | D62: 15 | E62: 20 | F62: 30 | G62: Assumed | H62: 沿用 v0.2.2（AI 機房 20 年） | I62: 管理層：資料中心建築 30 年以上
A63: tk_pq | B63: Tokenomics L1_RevGW_PQ_VR200（模型商每 MW 年實收 P×Q；只作上限檢查） | C63: US$m/MW-年 | D63: 36.2296 | E63: 49.513784 | F63: 78.4975 | G63: Derived | H63: S17 | I63: 上限，不得作預測
A64: k_long | B64: k_長約＝長約等值價格 ÷ 目前 VR200 IF_HoldEcon | C64: x | D64: =p_long_lo/tk_he_vr200 -> 0.57413739 | E64: =p_long/tk_he_vr200 -> 0.78291462 | G64: Derived | H64: legacy_v0.2/kspec.py（v0.2.1 起隨目前快照重算） | I64: v0.2.2 為 0.783／0.574
A65: k_spot | B65: k_現貨＝現貨價 ÷ IF_GPUhrEcon｜H100 | C65: x | E65: =p_spot/tk_gpuhr -> 1.8280865 | F65: =p_list/tk_gpuhr -> 4.4600126 | G65: Derived | H65: legacy_v0.2/kspec.py（三家一致，C1） | I65: 高＝AWS 牌價（v0.2.2 價格軸高）
A66: k_A | B66: 情境 A：新產能 k（價格軸高：現貨改用 AWS 牌價） | C66: x | E66: =long_sh*k_long+(1-long_sh)*k_spot_hi -> 1.5183342 | G66: Derived | H66: 沿用 v0.2.2 價格軸（pricing.kSpot.high）
A67: k_B | B67: 情境 B：k（價格軸基準：長約 80% × k_長約＋現貨 20% × k_現貨） | C67: x | E67: =long_sh*k_long+(1-long_sh)*k_spot -> 0.99194901 | G67: Derived | H67: 沿用 v0.2.2（C1 混合 k） | I67: 期初機隊三情境皆用本列
A68: k_C | B68: 情境 C：新產能 k（價格軸低：長約下緣） | C68: x | E68: =long_sh*k_long_lo+(1-long_sh)*k_spot -> 0.82492722 | G68: Derived | H68: 沿用 v0.2.2 價格軸（pricing.kLong.low）
A69: mo_trn2 | B69: 期初世代占比：Trainium2（以 Hopper 計價，C2） | C69: % | E69: 0.55 | G69: Assumed | H69: S20 | I69: Epoch 三站 1,422 ÷ 在役 2,600
A70: mo_h100 | B70: 期初世代占比：Hopper | C70: % | E70: 0.15 | G70: Assumed | H70: S20
A71: mo_gb200 | B71: 期初世代占比：GB200 | C71: % | E71: 0.15 | G71: Assumed | H71: S20
A72: mo_gb300 | B72: 期初世代占比：GB300 | C72: % | E72: 0.15 | G72: Assumed | H72: S20
A73: he_open | B73: 期初機隊加權 IF_HoldEcon | C73: US$m/MW-年 | E73: =(mo_trn2+mo_h100)*tk_he_h100+mo_gb200*tk_he_gb200+mo_gb300*tk_he_gb300 -> 9.7493476 | G73: Derived | H73: 上列加權
A74: ox_open | B74: 期初機隊加權營運費用 | C74: US$m/MW-年 | E74: =(mo_trn2+mo_h100)*tk_ox_h100+mo_gb200*tk_ox_gb200+mo_gb300*tk_ox_gb300 -> 1.8884974 | G74: Derived | H74: 上列加權
A75: rpm_open | B75: 期初機隊每 MW 年收入＝加權 IF_HoldEcon × k_B（收入端不乘 IF_Util，MW-year 計價） | C75: US$m/MW-年 | E75: =he_open*k_B -> 9.6708557 | G75: Derived | H75: 沿用 v0.2.2 口徑
A76: cust_sh | B76: 新增 MW 中自研晶片（Trainium3 → GB300 計價）比例 | C76: % | D76: 0.4 | E76: 0.5 | F76: 0.6 | G76: Assumed | H76: 沿用 v0.2.2（pricing.chips mixAdds） | I76: Trainium3 2026 年初出貨且「接近全數認購」
A77: na_vr26 | B77: NVIDIA 新增中 VR200 比例（2026；其餘 GB300） | C77: % | E77: 0 | G77: Assumed | H77: 沿用 v0.2.2
A78: na_vr27 | B78: NVIDIA 新增中 VR200 比例（2027） | C78: % | E78: 0.5 | G78: Assumed | H78: 沿用 v0.2.2
A79: na_vr28 | B79: NVIDIA 新增中 VR200 比例（2028 起） | C79: % | E79: 1 | G79: Assumed | H79: 沿用 v0.2.2
A80: cf_chip | B80: 自研晶片每 MW 收入係數（C2：同期 NVIDIA 世代 × 1.0） | C80: x | D80: 0.7 | E80: 1 | G80: Assumed | H80: 對照表 r1 C2 | I80: 敏感度 × 0.7（Tokenomics IF_NonNV_Hold_Trn 基準 0.7）
A81: cf_cx | B81: 自研晶片每 MW IT 資本支出係數 | C81: x | D81: 0.7 | E81: 1 | G81: Assumed | H81: 沿用 v0.2.2（customCapexFactor） | I81: 雙邊敏感度時與收入係數同乘 0.7
A82: colo_sh | B82: 機房租用比例（第三方託管） | C82: % | D82: 0.1 | E82: 0.2 | F82: 0.3 | G82: Interested-party | H82: S29 | I82: 自建比例＝1 − 本列；租用部分不計機房資本支出
A83: rent_rec | B83: 租用機房年租金 ÷ 機房資本支出（資本回收係數，C22） | C83: % | E83: 0.1 | G83: Assumed | H83: 對照表 r1 C22
A84: rent_mw | B84: 每 MW 年機房租金（攤到全部 AI MW）＝租用比例 × 機房成本 × 回收係數 | C84: US$m/MW-年 | E84: =colo_sh*tk_fac*rent_rec -> 0.2534 | G84: Derived | H84: 上列
A85: capex_g26 | B85: 2026 現金資本支出指引（下限） | C85: US$bn | E85: 220 | G85: Interested-party | H85: S11 | I85: 上調自約 200；首期 AI 資本支出＝MAX(MW 公式, 指引 − 上半年實際 − 非 AI)
A86: internal_ai_reading | B86: 自用 AI 讀法（2＝讀法 2 主值：自用 MW 以 k＝1 計影子效益、價值中性；1＝讀法 1：只計成本） | C86: 1/2 | D86: 1 | E86: 2 | G86: Assumed | H86: 修正一（F1；對照表 r1 C16，chat 端預設讀法 2 為主值） | I86: 讀法 1 列 Sens 與 Val 第 0 節
A87: ai_rr | B87: 公司 AI 營收年化（AWS AI run-rate，>25） | C87: US$bn | E87: 25 | G87: Interested-party | H87: S04 | I87: 只作 Recon 驗證列（C3）；不用於校準
A88: D. AWS 其他（非 AI 雲端）
A89: g_awso_lt | B89: AWS 其他長期年增（2030 起） | C89: % | D89: 0.05 | E89: 0.08 | F89: 0.11 | G89: Assumed | H89: 沿用 v0.2.2（gLT 8%） | I89: 2027–2030 由近期年增（1H26 對 1H25，Derived）線性收斂
A90: cx_awso | B90: AWS 其他資本支出 ÷ AWS 其他營收 | C90: % | D90: 0.15 | E90: 0.2 | F90: 0.27 | G90: Assumed | H90: 沿用 v0.2.2（cx 20%） | I90: 上緣＝2023 年 AWS PP&E 淨增加 ÷ AWS 營收 27.4%
A91: E. 零售各營收線（10-K 營收類別；北美＋國際）
A92: g_os | B92: Online stores 長期年增（2030 起） | C92: % | D92: 0.03 | E92: 0.05 | F92: 0.07 | G92: Assumed | H92: 判斷（報告第 5 節） | I92: 2H26＝2H25 ×（1＋2H25 年增）× 校準係數（隱含 2026Q3＝指引中點）；2027–2030 由 2H25 年增線性收斂到本列
A93: g_ps | B93: Physical stores 長期年增（2030 起） | C93: % | D93: 0.01 | E93: 0.03 | F93: 0.05 | G93: Assumed | H93: 判斷（報告第 5 節） | I93: 2H26＝2H25 ×（1＋2H25 年增）× 校準係數（隱含 2026Q3＝指引中點）；2027–2030 由 2H25 年增線性收斂到本列
A94: g_sp | B94: Third-party seller services 長期年增（2030 起） | C94: % | D94: 0.05 | E94: 0.07 | F94: 0.09 | G94: Assumed | H94: 判斷（報告第 5 節） | I94: 2H26＝2H25 ×（1＋2H25 年增）× 校準係數（隱含 2026Q3＝指引中點）；2027–2030 由 2H25 年增線性收斂到本列
A95: g_ad | B95: Advertising services 長期年增（2030 起） | C95: % | D95: 0.07 | E95: 0.1 | F95: 0.13 | G95: Assumed | H95: 判斷（報告第 5 節） | I95: 2H26＝2H25 ×（1＋2H25 年增）× 校準係數（隱含 2026Q3＝指引中點）；2027–2030 由 2H25 年增線性收斂到本列
A96: g_sub | B96: Subscription services 長期年增（2030 起） | C96: % | D96: 0.05 | E96: 0.07 | F96: 0.09 | G96: Assumed | H96: 判斷（報告第 5 節） | I96: 2H26＝2H25 ×（1＋2H25 年增）× 校準係數（隱含 2026Q3＝指引中點）；2027–2030 由 2H25 年增線性收斂到本列
A97: g_ot | B97: Other 長期年增（2030 起） | C97: % | D97: 0.02 | E97: 0.05 | F97: 0.08 | G97: Assumed | H97: 判斷（報告第 5 節） | I97: 2H26＝2H25 ×（1＋2H25 年增）× 校準係數（隱含 2026Q3＝指引中點）；2027–2030 由 2H25 年增線性收斂到本列
A98: m_ad | B98: 廣告營業利益率（分攤到北美／國際的方法：見 PL 頁） | C98: % | D98: 0.4 | E98: 0.5 | F98: 0.6 | G98: Assumed | H98: 沿用 v0.2.2（廣告 EBITDA 率 50%，分部未揭露） | I98: 數位廣告同業 META、GOOGL EBITDA 率 50%–60%；零售本業利益率＝分部利益扣廣告利潤後的殘差
A99: step_na | B99: 北美零售本業利益率每年改善（2027–2030） | C99: pt | D99: 0 | E99: 0.003 | F99: 0.006 | G99: Assumed | H99: 判斷：1H26 對 1H25 改善約 0.5pt（Q 頁推導）
A100: step_in | B100: 國際零售本業利益率每年改善（2027–2030） | C100: pt | D100: -0.003 | E100: 0 | F100: 0.003 | G100: Assumed | H100: 判斷：1H26 對 1H25 約 −0.3pt
...

Sheet Q
A1: Q — 實績（US$bn；股數十億股）：FY2023–FY2025、最近 8 季（2024Q3–2026Q2）與半年合計。資料取自 data/amazon_facts_20261008.json（10-K、10-Q、財報新聞稿逐季補充表），藍字＝事實值、黑字＝加總或換算。2026Q3 財報 2026-10-29（美國時間）公布，本版未納入
A2: 核對列（綠底）：零售營收線合計＝北美＋國際、營收線合計＝合併營收、分部合計＝合併營收、分部營業利益合計＋未分攤＝合併營業利益；實績皆須為 0
A3: 項目 | B3: 單位 | C3: FY2023A | D3: FY2024A | E3: FY2025A | F3: 2024Q3 | G3: 2024Q4 | H3: 2025Q1 | I3: 2025Q2 | J3: 2025Q3 | K3: 2025Q4 | L3: 2026Q1 | M3: 2026Q2 | N3: 1H25 | O3: 2H25 | P3: 1H26 | Q3: 近四季（2025Q3–2026Q2） | R3: 標記 | S3: 來源
A4: 1. 官方報告分部營收（10-K 附註：North America、International、AWS）
A5: North America | B5: US$bn | C5: 352.828 | D5: 387.497 | E5: 426.305 | F5: 95.537 | G5: 115.586 | H5: 92.887 | I5: 100.068 | J5: 106.267 | K5: 127.083 | L5: 104.143 | M5: 116.177 | N5: =H5+I5 -> 192.955 | O5: =J5+K5 -> 233.35 | P5: =L5+M5 -> 220.32 | Q5: =J5+K5+L5+M5 -> 453.67 | R5: Verified／Interested-party | S5: S01（FY）；S04、S08（逐季補充表）
A6: International | B6: US$bn | C6: 131.2 | D6: 142.906 | E6: 161.894 | F6: 35.888 | G6: 43.42 | H6: 33.513 | I6: 36.761 | J6: 40.896 | K6: 50.724 | L6: 39.789 | M6: 42.197 | N6: =H6+I6 -> 70.274 | O6: =J6+K6 -> 91.62 | P6: =L6+M6 -> 81.986 | Q6: =J6+K6+L6+M6 -> 173.606 | R6: Verified／Interested-party | S6: S01（FY）；S04、S08（逐季補充表）
A7: AWS | B7: US$bn | C7: 90.757 | D7: 107.556 | E7: 128.725 | F7: 27.452 | G7: 28.786 | H7: 29.267 | I7: 30.873 | J7: 33.006 | K7: 35.579 | L7: 37.587 | M7: 42.232 | N7: =H7+I7 -> 60.14 | O7: =J7+K7 -> 68.585 | P7: =L7+M7 -> 79.819 | Q7: =J7+K7+L7+M7 -> 148.404 | R7: Verified／Interested-party | S7: S01（FY）；S04、S08（逐季補充表）
A8: 合併營收 | B8: US$bn | C8: 574.785 | D8: 637.959 | E8: 716.924 | F8: 158.877 | G8: 187.792 | H8: 155.667 | I8: 167.702 | J8: 180.169 | K8: 213.386 | L8: 181.519 | M8: 200.606 | N8: =H8+I8 -> 323.369 | O8: =J8+K8 -> 393.555 | P8: =L8+M8 -> 382.125 | Q8: =J8+K8+L8+M8 -> 775.68 | R8: Verified／Interested-party | S8: S01（FY）；S04、S08（逐季補充表）
A9: 2. 營收線（10-K 營收類別；零售各線＝北美＋國際，AWS 線＝AWS 分部）
A10: Online stores | B10: US$bn | C10: 231.872 | D10: 247.029 | E10: 269.287 | F10: 61.411 | G10: 75.556 | H10: 57.407 | I10: 61.485 | J10: 67.407 | K10: 82.988 | L10: 64.254 | M10: 70.432 | N10: =H10+I10 -> 118.892 | O10: =J10+K10 -> 150.395 | P10: =L10+M10 -> 134.686 | Q10: =J10+K10+L10+M10 -> 285.081 | R10: Verified／Interested-party | S10: S01（FY）；S04、S08（逐季補充表）
A11: Physical stores | B11: US$bn | C11: 20.03 | D11: 21.215 | E11: 22.561 | F11: 5.228 | G11: 5.579 | H11: 5.533 | I11: 5.595 | J11: 5.578 | K11: 5.855 | L11: 5.785 | M11: 5.794 | N11: =H11+I11 -> 11.128 | O11: =J11+K11 -> 11.433 | P11: =L11+M11 -> 11.579 | Q11: =J11+K11+L11+M11 -> 23.012 | R11: Verified／Interested-party | S11: S01（FY）；S04、S08（逐季補充表）
A12: Third-party seller services | B12: US$bn | C12: 140.053 | D12: 156.146 | E12: 172.162 | F12: 37.864 | G12: 47.485 | H12: 36.512 | I12: 40.348 | J12: 42.486 | K12: 52.816 | L12: 41.578 | M12: 46.78 | N12: =H12+I12 -> 76.86 | O12: =J12+K12 -> 95.302 | P12: =L12+M12 -> 88.358 | Q12: =J12+K12+L12+M12 -> 183.66 | R12: Verified／Interested-party | S12: S01（FY）；S04、S08（逐季補充表）
A13: Advertising services | B13: US$bn | C13: 46.906 | D13: 56.214 | E13: 68.635 | F13: 14.331 | G13: 17.288 | H13: 13.921 | I13: 15.694 | J13: 17.703 | K13: 21.317 | L13: 17.243 | M13: 19.809 | N13: =H13+I13 -> 29.615 | O13: =J13+K13 -> 39.02 | P13: =L13+M13 -> 37.052 | Q13: =J13+K13+L13+M13 -> 76.072 | R13: Verified／Interested-party | S13: S01（FY）；S04、S08（逐季補充表）
A14: Subscription services | B14: US$bn | C14: 40.209 | D14: 44.374 | E14: 49.619 | F14: 11.278 | G14: 11.508 | H14: 11.715 | I14: 12.208 | J14: 12.574 | K14: 13.122 | L14: 13.427 | M14: 13.73 | N14: =H14+I14 -> 23.923 | O14: =J14+K14 -> 25.696 | P14: =L14+M14 -> 27.157 | Q14: =J14+K14+L14+M14 -> 52.853 | R14: Verified／Interested-party | S14: S01（FY）；S04、S08（逐季補充表）
A15: Other | B15: US$bn | C15: 4.958 | D15: 5.425 | E15: 5.935 | F15: 1.313 | G15: 1.59 | H15: 1.312 | I15: 1.499 | J15: 1.415 | K15: 1.709 | L15: 1.645 | M15: 1.829 | N15: =H15+I15 -> 2.811 | O15: =J15+K15 -> 3.124 | P15: =L15+M15 -> 3.474 | Q15: =J15+K15+L15+M15 -> 6.598 | R15: Verified／Interested-party | S15: S01（FY）；S04、S08（逐季補充表）
A16: 零售營收線合計（不含 AWS） | B16: US$bn | C16: =C10+C11+C12+C13+C14+C15 -> 484.028 | D16: =D10+D11+D12+D13+D14+D15 -> 530.403 | E16: =E10+E11+E12+E13+E14+E15 -> 588.199 | F16: =F10+F11+F12+F13+F14+F15 -> 131.425 | G16: =G10+G11+G12+G13+G14+G15 -> 159.006 | H16: =H10+H11+H12+H13+H14+H15 -> 126.4 | I16: =I10+I11+I12+I13+I14+I15 -> 136.829 | J16: =J10+J11+J12+J13+J14+J15 -> 147.163 | ... Q16: =Q10+Q11+Q12+Q13+Q14+Q15 -> 627.276 | R16: Derived
A17: AWS（營收線） | B17: US$bn | C17: =C7 -> 90.757 | D17: =D7 -> 107.556 | E17: =E7 -> 128.725 | F17: =F7 -> 27.452 | G17: =G7 -> 28.786 | H17: =H7 -> 29.267 | I17: =I7 -> 30.873 | J17: =J7 -> 33.006 | ... Q17: =Q7 -> 148.404 | R17: Derived
A18: 檢查：零售營收線合計 − (North America＋International) | B18: US$bn | C18: =C16-(C5+C6) -> 0 | D18: =D16-(D5+D6) -> 0 | E18: =E16-(E5+E6) -> 0 | F18: =F16-(F5+F6) -> 0 | G18: =G16-(G5+G6) -> 0 | H18: =H16-(H5+H6) -> 0 | I18: =I16-(I5+I6) -> 0 | J18: =J16-(J5+J6) -> 0 | ... Q18: =Q16-(Q5+Q6) -> 0 | R18: Derived
A19: 檢查：營收線合計（含 AWS）− 合併營收 | B19: US$bn | C19: =C16+C17-C8 -> 0 | D19: =D16+D17-D8 -> 0 | E19: =E16+E17-E8 -> 0 | F19: =F16+F17-F8 -> 0 | G19: =G16+G17-G8 -> 0 | H19: =H16+H17-H8 -> 0 | I19: =I16+I17-I8 -> 0 | J19: =J16+J17-J8 -> 0 | ... Q19: =Q16+Q17-Q8 -> 0 | R19: Derived
A20: 檢查：分部合計 − 合併營收 | B20: US$bn | C20: =C5+C6+C7-C8 -> 0 | D20: =D5+D6+D7-D8 -> 0 | E20: =E5+E6+E7-E8 -> 0 | F20: =F5+F6+F7-F8 -> 0 | G20: =G5+G6+G7-G8 -> 0 | H20: =H5+H6+H7-H8 -> 0 | I20: =I5+I6+I7-I8 -> 0 | J20: =J5+J6+J7-J8 -> 0 | ... Q20: =Q5+Q6+Q7-Q8 -> 0 | R20: Derived
A21: 3. 分部營業利益
A22: North America 營業利益 | B22: US$bn | C22: 14.877 | D22: 24.967 | E22: 29.619 | F22: 5.663 | G22: 9.256 | H22: 5.841 | I22: 7.517 | J22: 4.789 | K22: 11.472 | L22: 8.267 | M22: 9.123 | N22: =H22+I22 -> 13.358 | O22: =J22+K22 -> 16.261 | P22: =L22+M22 -> 17.39 | Q22: =J22+K22+L22+M22 -> 33.651 | R22: Verified／Interested-party | S22: S01（FY）；S04、S08（逐季補充表）
A23: International 營業利益 | B23: US$bn | C23: -2.656 | D23: 3.792 | E23: 4.75 | F23: 1.301 | G23: 1.315 | H23: 1.017 | I23: 1.494 | J23: 1.199 | K23: 1.04 | L23: 1.424 | M23: 1.717 | N23: =H23+I23 -> 2.511 | O23: =J23+K23 -> 2.239 | P23: =L23+M23 -> 3.141 | Q23: =J23+K23+L23+M23 -> 5.38 | R23: Verified／Interested-party | S23: S01（FY）；S04、S08（逐季補充表）
A24: AWS 營業利益 | B24: US$bn | C24: 24.631 | D24: 39.834 | E24: 45.606 | F24: 10.447 | G24: 10.632 | H24: 11.547 | I24: 10.16 | J24: 11.434 | K24: 12.465 | L24: 14.161 | M24: 16.621 | N24: =H24+I24 -> 21.707 | O24: =J24+K24 -> 23.899 | P24: =L24+M24 -> 30.782 | Q24: =J24+K24+L24+M24 -> 54.681 | R24: Verified／Interested-party | S24: S01（FY）；S04、S08（逐季補充表）
A25: 合併營業利益 | B25: US$bn | C25: 36.852 | D25: 68.593 | E25: 79.975 | F25: 17.411 | G25: 21.203 | H25: 18.405 | I25: 19.171 | J25: 17.422 | K25: 24.977 | L25: 23.852 | M25: 27.461 | N25: =H25+I25 -> 37.576 | O25: =J25+K25 -> 42.399 | P25: =L25+M25 -> 51.313 | Q25: =J25+K25+L25+M25 -> 93.712 | R25: Verified／Interested-party | S25: S01（FY）；S04、S08（逐季補充表）
A26: 未分攤（合併 − 分部合計；Amazon 分部已含全部費用） | B26: US$bn | C26: =C25-(C22+C23+C24) -> 0 | D26: =D25-(D22+D23+D24) -> 0 | E26: =E25-(E22+E23+E24) -> 0 | F26: =F25-(F22+F23+F24) -> 0 | G26: =G25-(G22+G23+G24) -> 0 | H26: =H25-(H22+H23+H24) -> 0 | I26: =I25-(I22+I23+I24) -> 0 | J26: =J25-(J22+J23+J24) -> 0 | ... Q26: =Q25-(Q22+Q23+Q24) -> 0 | R26: Derived
A27: 檢查：分部營業利益合計＋未分攤 − 合併營業利益 | B27: US$bn | C27: =C22+C23+C24+C26-C25 -> 0 | D27: =D22+D23+D24+D26-D25 -> 0 | E27: =E22+E23+E24+E26-E25 -> 0 | F27: =F22+F23+F24+F26-F25 -> 0 | G27: =G22+G23+G24+G26-G25 -> 0 | H27: =H22+H23+H24+H26-H25 -> 0 | I27: =I22+I23+I24+I26-I25 -> 0 | J27: =J22+J23+J24+J26-J25 -> 0 | ... Q27: =Q22+Q23+Q24+Q26-Q25 -> 0 | R27: Derived
A28: 4. 分部折舊攤銷（不含影音內容與營業租賃資產攤銷；2024 季度 facts 未收；2025Q4＝全年 − 前三季）
A29: North America 折舊攤銷 | B29: US$bn | C29: 13.678 | D29: 14.285 | E29: 15.503 | H29: 3.53 | I29: 3.742 | J29: 4.001 | K29: =E29-H29-I29-J29 -> 4.23 | L29: 4.28 | M29: 4.5 | N29: =H29+I29 -> 7.272 | O29: =J29+K29 -> 8.231 | P29: =L29+M29 -> 8.78 | Q29: =J29+K29+L29+M29 -> 17.011 | R29: Verified | S29: S01；S02；S03
A30: International 折舊攤銷 | B30: US$bn | C30: 4.016 | D30: 4.462 | E30: 4.907 | H30: 1.136 | I30: 1.18 | J30: 1.276 | K30: =E30-H30-I30-J30 -> 1.315 | L30: 1.277 | M30: 1.293 | N30: =H30+I30 -> 2.316 | O30: =J30+K30 -> 2.591 | P30: =L30+M30 -> 2.57 | Q30: =J30+K30+L30+M30 -> 5.161 | R30: Verified | S30: S01；S02；S03
A31: AWS 折舊攤銷 | B31: US$bn | C31: 12.531 | D31: 13.32 | E31: 21.45 | H31: 4.39 | I31: 4.844 | J31: 5.648 | K31: =E31-H31-I31-J31 -> 6.568 | L31: 7.277 | M31: 8.076 | N31: =H31+I31 -> 9.234 | O31: =J31+K31 -> 12.216 | P31: =L31+M31 -> 15.353 | Q31: =J31+K31+L31+M31 -> 27.569 | R31: Verified | S31: S01；S02；S03
A32: 分部折舊攤銷合計 | B32: US$bn | C32: =IF(COUNT(C29:C31)=3,C29+C30+C31,"") -> 30.225 | D32: =IF(COUNT(D29:D31)=3,D29+D30+D31,"") -> 32.067 | E32: =IF(COUNT(E29:E31)=3,E29+E30+E31,"") -> 41.86 | F32: =IF(COUNT(F29:F31)=3,F29+F30+F31,"") | G32: =IF(COUNT(G29:G31)=3,G29+G30+G31,"") | H32: =IF(COUNT(H29:H31)=3,H29+H30+H31,"") -> 9.056 | I32: =IF(COUNT(I29:I31)=3,I29+I30+I31,"") -> 9.766 | J32: =IF(COUNT(J29:J31)=3,J29+J30+J31,"") -> 10.925 | ... Q32: =IF(COUNT(Q29:Q31)=3,Q29+Q30+Q31,"") -> 49.741 | R32: Derived
A33: 5. 損益（業外、稅、淨利）
A34: 利息費用 | B34: US$bn | C34: 3.182 | D34: 2.406 | E34: 2.274 | F34: 0.603 | G34: 0.57 | H34: 0.541 | I34: 0.516 | J34: 0.538 | K34: 0.679 | L34: 0.8 | M34: 1.314 | N34: =H34+I34 -> 1.057 | O34: =J34+K34 -> 1.217 | P34: =L34+M34 -> 2.114 | Q34: =J34+K34+L34+M34 -> 3.331 | R34: Verified | S34: S01；S04
A35: 利息收入（2026Q2） | B35: US$bn | M35: 1.295 | R35: Verified | S35: S02
A36: 稅前淨利 | B36: US$bn | C36: 37.557 | D36: 68.614 | E36: 97.311 | F36: 18.037 | G36: 22.349 | H36: 21.679 | I36: 20.857 | J36: 28.17 | K36: 26.605 | L36: 39.834 | M36: 80.857 | N36: =H36+I36 -> 42.536 | O36: =J36+K36 -> 54.775 | P36: =L36+M36 -> 120.691 | Q36: =J36+K36+L36+M36 -> 175.466 | R36: Verified | S36: S01；S04
A37: 所得稅 | B37: US$bn | C37: 7.12 | D37: 9.265 | E37: 19.087 | F37: 2.706 | G37: 2.325 | H37: 4.553 | I37: 2.678 | J37: 6.91 | K37: 4.946 | L37: 9.56 | M37: 18.199 | N37: =H37+I37 -> 7.231 | O37: =J37+K37 -> 11.856 | P37: =L37+M37 -> 27.759 | Q37: =J37+K37+L37+M37 -> 39.615 | R37: Verified | S37: S01；S04
A38: 淨利 | B38: US$bn | C38: 30.425 | D38: 59.248 | E38: 77.67 | F38: 15.328 | G38: 20.004 | H38: 17.127 | I38: 18.164 | J38: 21.187 | K38: 21.192 | L38: 30.255 | M38: 62.647 | N38: =H38+I38 -> 35.291 | O38: =J38+K38 -> 42.379 | P38: =L38+M38 -> 92.902 | Q38: =J38+K38+L38+M38 -> 135.281 | R38: Verified | S38: S01；S04
A39: 業外淨額（稅前 − 營業利益＋利息費用；含 Anthropic 等持股評價利益） | B39: US$bn | C39: =IF(AND(ISNUMBER(C36),ISNUMBER(C34)),C36-C25+C34,"") -> 3.887 | D39: =IF(AND(ISNUMBER(D36),ISNUMBER(D34)),D36-D25+D34,"") -> 2.427 | E39: =IF(AND(ISNUMBER(E36),ISNUMBER(E34)),E36-E25+E34,"") -> 19.61 | F39: =IF(AND(ISNUMBER(F36),ISNUMBER(F34)),F36-F25+F34,"") -> 1.229 | G39: =IF(AND(ISNUMBER(G36),ISNUMBER(G34)),G36-G25+G34,"") -> 1.716 | H39: =IF(AND(ISNUMBER(H36),ISNUMBER(H34)),H36-H25+H34,"") -> 3.815 | I39: =IF(AND(ISNUMBER(I36),ISNUMBER(I34)),I36-I25+I34,"") -> 2.202 | J39: =IF(AND(ISNUMBER(J36),ISNUMBER(J34)),J36-J25+J34,"") -> 11.286 | ... Q39: =IF(AND(ISNUMBER(Q36),ISNUMBER(Q34)),Q36-Q25+Q34,"") -> 85.085 | R39: Derived
A40: 有效稅率 | B40: US$bn | C40: =C37/C36 -> 0.18957851 | D40: =D37/D36 -> 0.13503075 | E40: =E37/E36 -> 0.19614432 | R40: Derived
A41: 稀釋加權股數 | B41: 十億股 | C41: 10.492 | D41: 10.721 | E41: 10.827 | F41: 10.735 | H41: 10.793 | I41: 10.806 | J41: 10.845 | L41: 10.874 | M41: 10.903 | R41: Verified | S41: S10
A42: 稀釋 EPS（淨利 ÷ 稀釋加權股數） | B42: US$ | C42: =IF(ISNUMBER(C41),C38/C41,"") -> 2.8998284 | D42: =IF(ISNUMBER(D41),D38/D41,"") -> 5.5263502 | E42: =IF(ISNUMBER(E41),E38/E41,"") -> 7.1737323 | F42: =IF(ISNUMBER(F41),F38/F41,"") -> 1.4278528 | G42: =IF(ISNUMBER(G41),G38/G41,"") | H42: =IF(ISNUMBER(H41),H38/H41,"") -> 1.5868619 | I42: =IF(ISNUMBER(I41),I38/I41,"") -> 1.680918 | J42: =IF(ISNUMBER(J41),J38/J41,"") -> 1.9536192 | ... M42: =IF(ISNUMBER(M41),M38/M41,"") -> 5.7458498 | R42: Derived
A43: 6. 現金流量、資本支出與股東回饋
A44: 營運現金流 | B44: US$bn | C44: 84.946 | D44: 115.877 | E44: 139.514 | F44: 25.971 | G44: 45.636 | H44: 17.015 | I44: 32.515 | J44: 35.525 | K44: 54.459 | L44: 26.032 | M44: 45.387 | N44: =H44+I44 -> 49.53 | O44: =J44+K44 -> 89.984 | P44: =L44+M44 -> 71.419 | Q44: =J44+K44+L44+M44 -> 161.403 | R44: Verified | S44: S01；S04；S05；S06；S07；S09
A45: 資本支出（購置 PP&E，總額） | B45: US$bn | C45: 52.729 | D45: 82.999 | E45: 131.819 | F45: 22.62 | G45: 27.834 | H45: 25.019 | I45: 32.183 | J45: 35.095 | K45: 39.522 | L45: 44.203 | M45: 54.208 | N45: =H45+I45 -> 57.202 | O45: =J45+K45 -> 74.617 | P45: =L45+M45 -> 98.411 | Q45: =J45+K45+L45+M45 -> 173.028 | R45: Verified | S45: S01；S04
A46: 資本支出（現金，淨額＝購置 − 出售及獎勵） | B46: US$bn | C46: 48.133 | D46: 77.658 | E46: 128.32 | F46: 21.278 | G46: 26.052 | H46: 24.255 | I46: 31.368 | J46: 34.228 | K46: 38.469 | L46: 43.234 | M46: 53.076 | N46: =H46+I46 -> 55.623 | O46: =J46+K46 -> 72.697 | P46: =L46+M46 -> 96.31 | Q46: =J46+K46+L46+M46 -> 169.007 | R46: Derived | S46: 由同季新聞稿現金流量表換算
A47: 折舊攤銷（現金流量表；含影音內容與營業租賃資產） | B47: US$bn | C47: 48.663 | D47: 52.795 | E47: 65.756 | F47: 13.442 | G47: 15.631 | H47: 14.262 | I47: 15.227 | J47: 16.796 | K47: 19.471 | L47: 18.945 | M47: 19.988 | N47: =H47+I47 -> 29.489 | O47: =J47+K47 -> 36.267 | P47: =L47+M47 -> 38.933 | Q47: =J47+K47+L47+M47 -> 75.2 | R47: Verified | S47: S01；S04
A48: 股份基礎給付 | B48: US$bn | C48: 24.023 | D48: 22.011 | E48: 19.467 | F48: 5.333 | G48: 4.995 | H48: 3.689 | I48: 6.534 | J48: 4.847 | K48: 4.397 | L48: 4.032 | M48: 6.038 | N48: =H48+I48 -> 10.223 | O48: =J48+K48 -> 9.244 | P48: =L48+M48 -> 10.07 | Q48: =J48+K48+L48+M48 -> 19.314 | R48: Verified | S48: S01；S04
A49: 自由現金流（公司口徑＝營運現金流 − 資本支出淨額） | B49: US$bn | C49: =C44-C46 -> 36.813 | D49: =D44-D46 -> 38.219 | E49: =E44-E46 -> 11.194 | F49: =F44-F46 -> 4.693 | G49: =G44-G46 -> 19.584 | H49: =H44-H46 -> -7.24 | I49: =I44-I46 -> 1.147 | J49: =J44-J46 -> 1.297 | ... Q49: =Q44-Q46 -> -7.604 | R49: Derived
A50: 融資租賃本金償還 | B50: US$bn | C50: 4.384 | D50: 2.043 | E50: 1.557 | R50: Verified | S50: S01
A51: 買回庫藏股 | B51: US$bn | C51: 0 | D51: 0 | E51: 0 | P51: 0 | R51: Verified | S51: S01
A52: 現金股利 | B52: US$bn | C52: 0 | D52: 0 | E52: 0 | P52: 0 | R52: Verified | S52: S01
A53: 策略投資（收購與投資；2026 上半年含 OpenAI、Anthropic） | B53: US$bn | P53: 39.767 | R53: Verified | S53: S02
A54: 7. 資本支出分布（PP&E 淨增加，含融資租賃取得與已取得未付款；10-K／10-Q 分部附註）
A55: North America PP&E 淨增加 | B55: US$bn | C55: 17.529 | D55: 24.348 | E55: 35.919 | P55: 23.265 | R55: Verified | S55: S01；S02
A56: International PP&E 淨增加 | B56: US$bn | C56: 4.144 | D56: 6.643 | E56: 7.617 | P56: 4.267 | R56: Verified | S56: S01；S02
A57: AWS PP&E 淨增加 | B57: US$bn | C57: 24.843 | D57: 53.267 | E57: 96.496 | P57: 90.12 | R57: Verified | S57: S01；S02
A58: 公司層 PP&E 淨增加 | B58: US$bn | C58: 1.828 | D58: 1.494 | E58: 2.32 | P58: 0.996 | R58: Verified | S58: S01；S02
A59: PP&E 淨增加合計 | B59: US$bn | C59: 48.344 | D59: 85.752 | E59: 142.352 | P59: 118.648 | R59: Verified | S59: S01；S02
A60: 8. 期末餘額
A61: 現金、約當現金與有價證券 | B61: US$bn | E61: 123.029 | M61: 122.988 | R61: Verified | S61: S01；S02
A62: 債務面額 | B62: US$bn | E62: 68.836 | M62: 132.995 | R62: Verified | S62: S01；S02

Sheet Thesis
A1: Thesis — 命題模組：AWS AI＝對外 AI 在役 MW × 每 MW 年收入（Tokenomics v21.4 IF_HoldEcon × k；Trainium 以同期 NVIDIA 世代計價，C2）。AI 資本支出（含自用）→ IT 6 年／機房 20 年折舊（次年起提列）→ 對外部分進 AWS 營業利益、自用部分進北美／國際營業利益。三情境 A／B／C 依序排列
A2: 情境差異集中在命題驅動：A＝公司容量目標速度＋新產能 k 價格軸高；B＝資本支出指引隱含速度（C10）＋基準 k；C＝與 B 同速度（資本支出照指引）＋新產能 k 價格軸低。非 AI 業務三情境相同
A4: Thesis｜情境 A（樂觀）：命題模組 AWS AI＝對外 AI 在役 MW × 每 MW 年收入（Tokenomics 持有成本 × k）；AI 資本支出 → 折舊 → 分部營業利益
A5: 項目 | B5: 單位 | C5: FY2024A | D5: FY2025A | E5: 1H26A | F5: 2H26E | G5: FY2026E（1H 實績＋2H 模型） | H5: FY2027E | I5: FY2028E | J5: FY2029E | K5: FY2030E | L5: FY2031E | M5: FY2032E | N5: 1H25A | O5: 2H25A | P5: 說明 | R5: 2023 | S5: 2024 | T5: 2025 | U5: 2026 | V5: 2027 | W5: 2028 | X5: 2029 | Y5: 2030 | Z5: 2031 | AA5: 2032
A6: 1. 容量（對外 AI 在役 MW-IT；期末）
A7: 對外 AI MW 每年新增（2030–2032 線性收斂到 FY2029 年底 MW × g，F5） | B7: MW/年 | H7: =pace_A -> 3733 | I7: =pace_A -> 3733 | J7: =pace_A -> 3733 | K7: =pace_A+(Thesis!$J$8*tg-pace_A)*1/3 -> 2640.1217 | L7: =pace_A+(Thesis!$J$8*tg-pace_A)*2/3 -> 1547.2433 | M7: =pace_A+(Thesis!$J$8*tg-pace_A)*3/3 -> 454.365 | P7: 終值不落在建置高峰（共同修正 F5）
A8: 對外 AI 在役 MW（期末） | B8: MW | C8: =mw_ye24 -> 360 | D8: =mw_ye25 -> 1440 | E8: =mw_open -> 2080 | F8: =Thesis!$E$8+pace_A*0.5 -> 3946.5 | G8: =Thesis!$F$8 -> 3946.5 | H8: =Thesis!$G$8+Thesis!$H$7 -> 7679.5 | I8: =Thesis!$H$8+Thesis!$I$7 -> 11412.5 | J8: =Thesis!$I$8+Thesis!$J$7 -> 15145.5 | K8: =Thesis!$J$8+Thesis!$K$7 -> 17785.622 | L8: =Thesis!$K$8+Thesis!$L$7 -> 19332.865 | M8: =Thesis!$L$8+Thesis!$M$7 -> 19787.23 | N8: =(mw_ye24+mw_ye25)/2 -> 900 | O8: =mw_ye25 -> 1440 | P8: 期初 2026-06-30＝In 頁 mw_open；每年新增＝In 頁 pace（情境）；歷史年底值只用於分拆與折舊年份
A9: 對外 AI 平均在役 MW（期間） | B9: MW | C9: =(mw_ye23+mw_ye24)/2 -> 240 | D9: =(Thesis!$C$8+Thesis!$D$8)/2 -> 900 | E9: =(Thesis!$D$8+Thesis!$E$8)/2 -> 1760 | F9: =(Thesis!$E$8+Thesis!$F$8)/2 -> 3013.25 | G9: =(Thesis!$E$9+Thesis!$F$9)/2 -> 2386.625 | H9: =(Thesis!$G$8+Thesis!$H$8)/2 -> 5813 | I9: =(Thesis!$H$8+Thesis!$I$8)/2 -> 9546 | J9: =(Thesis!$I$8+Thesis!$J$8)/2 -> 13279 | K9: =(Thesis!$J$8+Thesis!$K$8)/2 -> 16465.561 | L9: =(Thesis!$K$8+Thesis!$L$8)/2 -> 18559.243 | M9: =(Thesis!$L$8+Thesis!$M$8)/2 -> 19560.048 | N9: =(Thesis!$C$8+Thesis!$N$8)/2 -> 630 | O9: =(Thesis!$N$8+Thesis!$O$8)/2 -> 1170
A10: 期間長度 | B10: 年 | C10: 1 | D10: 1 | E10: 0.5 | F10: 0.5 | G10: 1 | H10: 1 | I10: 1 | J10: 1 | K10: 1 | L10: 1 | M10: 1 | N10: 0.5 | O10: 0.5
A11: 新增對外 AI MW | B11: MW | C11: =Thesis!$C$8-mw_ye23 -> 240 | D11: =Thesis!$D$8-Thesis!$C$8 -> 1080 | E11: =Thesis!$E$8-Thesis!$D$8 -> 640 | F11: =Thesis!$F$8-Thesis!$E$8 -> 1866.5 | G11: =Thesis!$E$11+Thesis!$F$11 -> 2506.5 | H11: =Thesis!$H$8-Thesis!$G$8 -> 3733 | I11: =Thesis!$I$8-Thesis!$H$8 -> 3733 | J11: =Thesis!$J$8-Thesis!$I$8 -> 3733 | K11: =Thesis!$K$8-Thesis!$J$8 -> 2640.1217 | L11: =Thesis!$L$8-Thesis!$K$8 -> 1547.2433 | M11: =Thesis!$M$8-Thesis!$L$8 -> 454.365 | N11: =Thesis!$N$8-Thesis!$C$8 -> 540 | O11: =Thesis!$O$8-Thesis!$N$8 -> 540
A12: 新增 AI 總 MW（含自用＝對外 ÷ 對外比例） | B12: MW | C12: =Thesis!$C$11/ext_sh -> 300 | D12: =Thesis!$D$11/ext_sh -> 1350 | E12: =Thesis!$E$11/ext_sh -> 800 | F12: =Thesis!$F$11/ext_sh -> 2333.125 | G12: =Thesis!$G$11/ext_sh -> 3133.125 | H12: =Thesis!$H$11/ext_sh -> 4666.25 | I12: =Thesis!$I$11/ext_sh -> 4666.25 | J12: =Thesis!$J$11/ext_sh -> 4666.25 | K12: =Thesis!$K$11/ext_sh -> 3300.1521 | L12: =Thesis!$L$11/ext_sh -> 1934.0542 | M12: =Thesis!$M$11/ext_sh -> 567.95625 | N12: =Thesis!$N$11/ext_sh -> 675 | O12: =Thesis!$O$11/ext_sh -> 675 | P12: R–AA 欄：依年份（折舊與汰換用） | R12: =mw_ye23/ext_sh -> 150 | S12: =Thesis!$C$12 -> 300 | T12: =Thesis!$D$12 -> 1350 | U12: =Thesis!$G$12 -> 3133.125 | V12: =Thesis!$H$12 -> 4666.25 | W12: =Thesis!$I$12 -> 4666.25 | X12: =Thesis!$J$12 -> 4666.25 | Y12: =Thesis!$K$12 -> 3300.1521 | Z12: =Thesis!$L$12 -> 1934.0542 | AA12: =Thesis!$M$12 -> 567.95625
A13: 2. 新增產能的世代與單位經濟（Tokenomics v21.4 基準成本；自研晶片以同期 NVIDIA 世代計價，C2）
A14: NVIDIA 新增中 VR200 比例 | B14: % | F14: =na_vr26 -> 0 | G14: =na_vr26 -> 0 | H14: =na_vr27 -> 0.5 | I14: =na_vr28 -> 1 | J14: =na_vr28 -> 1 | K14: =na_vr28 -> 1 | L14: =na_vr28 -> 1 | M14: =na_vr28 -> 1
A15: 新增 MW 加權 IF_HoldEcon（含自研晶片係數） | B15: US$m/MW-年 | F15: =cust_sh*tk_he_gb300*cf_chip+(1-cust_sh)*((1-Thesis!$F$14)*tk_he_gb300+Thesis!$F$14*tk_he_vr200) -> 10.886411 | G15: =cust_sh*tk_he_gb300*cf_chip+(1-cust_sh)*((1-Thesis!$G$14)*tk_he_gb300+Thesis!$G$14*tk_he_vr200) -> 10.886411 | H15: =cust_sh*tk_he_gb300*cf_chip+(1-cust_sh)*((1-Thesis!$H$14)*tk_he_gb300+Thesis!$H$14*tk_he_vr200) -> 11.221176 | I15: =cust_sh*tk_he_gb300*cf_chip+(1-cust_sh)*((1-Thesis!$I$14)*tk_he_gb300+Thesis!$I$14*tk_he_vr200) -> 11.555941 | J15: =cust_sh*tk_he_gb300*cf_chip+(1-cust_sh)*((1-Thesis!$J$14)*tk_he_gb300+Thesis!$J$14*tk_he_vr200) -> 11.555941 | K15: =cust_sh*tk_he_gb300*cf_chip+(1-cust_sh)*((1-Thesis!$K$14)*tk_he_gb300+Thesis!$K$14*tk_he_vr200) -> 11.555941 | L15: =cust_sh*tk_he_gb300*cf_chip+(1-cust_sh)*((1-Thesis!$L$14)*tk_he_gb300+Thesis!$L$14*tk_he_vr200) -> 11.555941 | M15: =cust_sh*tk_he_gb300*cf_chip+(1-cust_sh)*((1-Thesis!$M$14)*tk_he_gb300+Thesis!$M$14*tk_he_vr200) -> 11.555941
A16: 新增 MW 加權營運費用（IF_OpexGW） | B16: US$m/MW-年 | F16: =cust_sh*tk_ox_gb300+(1-cust_sh)*((1-Thesis!$F$14)*tk_ox_gb300+Thesis!$F$14*tk_ox_vr200) -> 1.9826348 | G16: =cust_sh*tk_ox_gb300+(1-cust_sh)*((1-Thesis!$G$14)*tk_ox_gb300+Thesis!$G$14*tk_ox_vr200) -> 1.9826348 | H16: =cust_sh*tk_ox_gb300+(1-cust_sh)*((1-Thesis!$H$14)*tk_ox_gb300+Thesis!$H$14*tk_ox_vr200) -> 2.01035 | I16: =cust_sh*tk_ox_gb300+(1-cust_sh)*((1-Thesis!$I$14)*tk_ox_gb300+Thesis!$I$14*tk_ox_vr200) -> 2.0380652 | J16: =cust_sh*tk_ox_gb300+(1-cust_sh)*((1-Thesis!$J$14)*tk_ox_gb300+Thesis!$J$14*tk_ox_vr200) -> 2.0380652 | K16: =cust_sh*tk_ox_gb300+(1-cust_sh)*((1-Thesis!$K$14)*tk_ox_gb300+Thesis!$K$14*tk_ox_vr200) -> 2.0380652 | L16: =cust_sh*tk_ox_gb300+(1-cust_sh)*((1-Thesis!$L$14)*tk_ox_gb300+Thesis!$L$14*tk_ox_vr200) -> 2.0380652 | M16: =cust_sh*tk_ox_gb300+(1-cust_sh)*((1-Thesis!$M$14)*tk_ox_gb300+Thesis!$M$14*tk_ox_vr200) -> 2.0380652
A17: 新增 MW 加權 IT 資本支出（IF_CapexIT；含自研晶片資本支出係數） | B17: US$m/MW | F17: =cust_sh*tk_cx_gb300*cf_cx+(1-cust_sh)*((1-Thesis!$F$14)*tk_cx_gb300+Thesis!$F$14*tk_cx_vr200) -> 32.237224 | G17: =cust_sh*tk_cx_gb300*cf_cx+(1-cust_sh)*((1-Thesis!$G$14)*tk_cx_gb300+Thesis!$G$14*tk_cx_vr200) -> 32.237224 | H17: =cust_sh*tk_cx_gb300*cf_cx+(1-cust_sh)*((1-Thesis!$H$14)*tk_cx_gb300+Thesis!$H$14*tk_cx_vr200) -> 33.574506 | I17: =cust_sh*tk_cx_gb300*cf_cx+(1-cust_sh)*((1-Thesis!$I$14)*tk_cx_gb300+Thesis!$I$14*tk_cx_vr200) -> 34.911788 | J17: =cust_sh*tk_cx_gb300*cf_cx+(1-cust_sh)*((1-Thesis!$J$14)*tk_cx_gb300+Thesis!$J$14*tk_cx_vr200) -> 34.911788 | K17: =cust_sh*tk_cx_gb300*cf_cx+(1-cust_sh)*((1-Thesis!$K$14)*tk_cx_gb300+Thesis!$K$14*tk_cx_vr200) -> 34.911788 | L17: =cust_sh*tk_cx_gb300*cf_cx+(1-cust_sh)*((1-Thesis!$L$14)*tk_cx_gb300+Thesis!$L$14*tk_cx_vr200) -> 34.911788 | M17: =cust_sh*tk_cx_gb300*cf_cx+(1-cust_sh)*((1-Thesis!$M$14)*tk_cx_gb300+Thesis!$M$14*tk_cx_vr200) -> 34.911788
A18: 期初後新增對外 MW 累計（期末） | B18: MW | F18: =Thesis!$F$8-mw_open -> 1866.5 | G18: =Thesis!$F$18 -> 1866.5 | H18: =Thesis!$H$8-mw_open -> 5599.5 | I18: =Thesis!$I$8-mw_open -> 9332.5 | J18: =Thesis!$J$8-mw_open -> 13065.5 | K18: =Thesis!$K$8-mw_open -> 15705.622 | L18: =Thesis!$L$8-mw_open -> 17252.865 | M18: =Thesis!$M$8-mw_open -> 17707.23
A19: Σ 新增 MW × HoldEcon | B19: US$m | F19: =Thesis!$F$11*Thesis!$F$15 -> 20319.486 | G19: =Thesis!$F$19 -> 20319.486 | H19: =Thesis!$G$19+Thesis!$H$11*Thesis!$H$15 -> 62208.136 | I19: =Thesis!$H$19+Thesis!$I$11*Thesis!$I$15 -> 105346.46 | J19: =Thesis!$I$19+Thesis!$J$11*Thesis!$J$15 -> 148484.79 | K19: =Thesis!$J$19+Thesis!$K$11*Thesis!$K$15 -> 178993.88 | L19: =Thesis!$K$19+Thesis!$L$11*Thesis!$L$15 -> 196873.73 | M19: =Thesis!$L$19+Thesis!$M$11*Thesis!$M$15 -> 202124.35
A20: Σ 新增 MW × 營運費用 | B20: US$m | F20: =Thesis!$F$11*Thesis!$F$16 -> 3700.5879 | G20: =Thesis!$F$20 -> 3700.5879 | H20: =Thesis!$G$20+Thesis!$H$11*Thesis!$H$16 -> 11205.224 | I20: =Thesis!$H$20+Thesis!$I$11*Thesis!$I$16 -> 18813.322 | J20: =Thesis!$I$20+Thesis!$J$11*Thesis!$J$16 -> 26421.419 | K20: =Thesis!$J$20+Thesis!$K$11*Thesis!$K$16 -> 31802.159 | L20: =Thesis!$K$20+Thesis!$L$11*Thesis!$L$16 -> 34955.542 | M20: =Thesis!$L$20+Thesis!$M$11*Thesis!$M$16 -> 35881.567
A21: 新增機隊加權 HoldEcon | B21: US$m/MW-年 | F21: =IF(Thesis!$F$18>0,Thesis!$F$19/Thesis!$F$18,Thesis!$F$15) -> 10.886411 | G21: =IF(Thesis!$G$18>0,Thesis!$G$19/Thesis!$G$18,Thesis!$G$15) -> 10.886411 | H21: =IF(Thesis!$H$18>0,Thesis!$H$19/Thesis!$H$18,Thesis!$H$15) -> 11.109588 | I21: =IF(Thesis!$I$18>0,Thesis!$I$19/Thesis!$I$18,Thesis!$I$15) -> 11.288129 | J21: =IF(Thesis!$J$18>0,Thesis!$J$19/Thesis!$J$18,Thesis!$J$15) -> 11.364647 | K21: =IF(Thesis!$K$18>0,Thesis!$K$19/Thesis!$K$18,Thesis!$K$15) -> 11.396803 | L21: =IF(Thesis!$L$18>0,Thesis!$L$19/Thesis!$L$18,Thesis!$L$15) -> 11.411075 | M21: =IF(Thesis!$M$18>0,Thesis!$M$19/Thesis!$M$18,Thesis!$M$15) -> 11.414792
A22: 新增機隊加權營運費用 | B22: US$m/MW-年 | F22: =IF(Thesis!$F$18>0,Thesis!$F$20/Thesis!$F$18,Thesis!$F$16) -> 1.9826348 | G22: =IF(Thesis!$G$18>0,Thesis!$G$20/Thesis!$G$18,Thesis!$G$16) -> 1.9826348 | H22: =IF(Thesis!$H$18>0,Thesis!$H$20/Thesis!$H$18,Thesis!$H$16) -> 2.0011116 | I22: =IF(Thesis!$I$18>0,Thesis!$I$20/Thesis!$I$18,Thesis!$I$16) -> 2.015893 | J22: =IF(Thesis!$J$18>0,Thesis!$J$20/Thesis!$J$18,Thesis!$J$16) -> 2.0222279 | K22: =IF(Thesis!$K$18>0,Thesis!$K$20/Thesis!$K$18,Thesis!$K$16) -> 2.0248902 | L22: =IF(Thesis!$L$18>0,Thesis!$L$20/Thesis!$L$18,Thesis!$L$16) -> 2.0260717 | M22: =IF(Thesis!$M$18>0,Thesis!$M$20/Thesis!$M$18,Thesis!$M$16) -> 2.0263795
A23: 新增產能每 MW 年收入＝新增機隊 HoldEcon × 情境 k | B23: US$m/MW-年 | F23: =Thesis!$F$21*k_A -> 16.52921 | G23: =Thesis!$G$21*k_A -> 16.52921 | H23: =Thesis!$H$21*k_A -> 16.868067 | I23: =Thesis!$I$21*k_A -> 17.139152 | J23: =Thesis!$J$21*k_A -> 17.255332 | K23: =Thesis!$K$21*k_A -> 17.304156 | L23: =Thesis!$L$21*k_A -> 17.325825 | M23: =Thesis!$M$21*k_A -> 17.331469 | P23: 期初機隊 2,080 MW 三情境同用 rpm_open（k_B）；情境 k 只用於新產能
A24: 新增產能平均在役 MW（期間） | B24: MW | F24: =Thesis!$F$18/2 -> 933.25 | H24: =(Thesis!$G$18+Thesis!$H$18)/2 -> 3733 | I24: =(Thesis!$H$18+Thesis!$I$18)/2 -> 7466 | J24: =(Thesis!$I$18+Thesis!$J$18)/2 -> 11199 | K24: =(Thesis!$J$18+Thesis!$K$18)/2 -> 14385.561 | L24: =(Thesis!$K$18+Thesis!$L$18)/2 -> 16479.243 | M24: =(Thesis!$L$18+Thesis!$M$18)/2 -> 17480.048
A25: 3. AWS AI 損益（收入端不乘 IF_Util：MW-year 計價）
A26: AWS AI 營收（命題子列） | B26: US$bn | C26: =Thesis!$C$9*rpm_open*Thesis!$C$10/1000 -> 2.3210054 | D26: =Thesis!$D$9*rpm_open*Thesis!$D$10/1000 -> 8.7037701 | E26: =Thesis!$E$9*rpm_open*Thesis!$E$10/1000 -> 8.510353 | F26: =(mw_open*rpm_open+Thesis!$F$24*Thesis!$F$23)*Thesis!$F$10/1000 -> 17.770633 | G26: =Thesis!$E$26+Thesis!$F$26 -> 26.280986 | H26: =(mw_open*rpm_open+Thesis!$H$24*Thesis!$H$23)/1000 -> 83.083874 | I26: =(mw_open*rpm_open+Thesis!$I$24*Thesis!$I$23)/1000 -> 148.07629 | J26: =(mw_open*rpm_open+Thesis!$J$24*Thesis!$J$23)/1000 -> 213.35784 | K26: =(mw_open*rpm_open+Thesis!$K$24*Thesis!$K$23)/1000 -> 269.04538 | L26: =(mw_open*rpm_open+Thesis!$L$24*Thesis!$L$23)/1000 -> 305.63187 | M26: =(mw_open*rpm_open+Thesis!$M$24*Thesis!$M$23)/1000 -> 323.07029 | N26: =Thesis!$N$9*rpm_open*Thesis!$N$10/1000 -> 3.0463195 | O26: =Thesis!$O$9*rpm_open*Thesis!$O$10/1000 -> 5.6574506 | P26: 實績欄為分拆估計（期初 k，Derived），不是公司揭露值
A27: 全機隊每 MW 年收入 | B27: US$m/MW-年 | C27: =Thesis!$C$26*1000/(Thesis!$C$9*Thesis!$C$10) -> 9.6708557 | D27: =Thesis!$D$26*1000/(Thesis!$D$9*Thesis!$D$10) -> 9.6708557 | E27: =Thesis!$E$26*1000/(Thesis!$E$9*Thesis!$E$10) -> 9.6708557 | F27: =Thesis!$F$26*1000/(Thesis!$F$9*Thesis!$F$10) -> 11.794994 | G27: =Thesis!$G$26*1000/(Thesis!$G$9*Thesis!$G$10) -> 11.011778 | H27: =Thesis!$H$26*1000/(Thesis!$H$9*Thesis!$H$10) -> 14.29277 | I27: =Thesis!$I$26*1000/(Thesis!$I$9*Thesis!$I$10) -> 15.511868 | J27: =Thesis!$J$26*1000/(Thesis!$J$9*Thesis!$J$10) -> 16.067312 | K27: =Thesis!$K$26*1000/(Thesis!$K$9*Thesis!$K$10) -> 16.339885 | L27: =Thesis!$L$26*1000/(Thesis!$L$9*Thesis!$L$10) -> 16.467906 | M27: =Thesis!$M$26*1000/(Thesis!$M$9*Thesis!$M$10) -> 16.516846 | N27: =Thesis!$N$26*1000/(Thesis!$N$9*Thesis!$N$10) -> 9.6708557 | O27: =Thesis!$O$26*1000/(Thesis!$O$9*Thesis!$O$10) -> 9.6708557
A28: AI 營運成本（含自用 MW、租用機房租金 C22） | B28: US$bn | C28: =Thesis!$C$9/ext_sh*(ox_open+rent_mw)*Thesis!$C$10/1000 -> 0.64256921 | D28: =Thesis!$D$9/ext_sh*(ox_open+rent_mw)*Thesis!$D$10/1000 -> 2.4096345 | E28: =Thesis!$E$9/ext_sh*(ox_open+rent_mw)*Thesis!$E$10/1000 -> 2.3560871 | F28: =((mw_open*ox_open+Thesis!$F$24*Thesis!$F$22)/ext_sh+Thesis!$F$9/ext_sh*rent_mw)*Thesis!$F$10/1000 -> 4.0887038 | G28: =Thesis!$E$28+Thesis!$F$28 -> 6.4447909 | H28: =((mw_open*ox_open+Thesis!$H$24*Thesis!$H$22)/ext_sh+Thesis!$H$9/ext_sh*rent_mw)*Thesis!$H$10/1000 -> 16.089048 | I28: =((mw_open*ox_open+Thesis!$I$24*Thesis!$I$22)/ext_sh+Thesis!$I$9/ext_sh*rent_mw)*Thesis!$I$10/1000 -> 26.74711 | J28: =((mw_open*ox_open+Thesis!$J$24*Thesis!$J$22)/ext_sh+Thesis!$J$9/ext_sh*rent_mw)*Thesis!$J$10/1000 -> 37.42488 | K28: =((mw_open*ox_open+Thesis!$K$24*Thesis!$K$22)/ext_sh+Thesis!$K$9/ext_sh*rent_mw)*Thesis!$K$10/1000 -> 46.537036 | L28: =((mw_open*ox_open+Thesis!$L$24*Thesis!$L$22)/ext_sh+Thesis!$L$9/ext_sh*rent_mw)*Thesis!$L$10/1000 -> 52.523895 | M28: =((mw_open*ox_open+Thesis!$M$24*Thesis!$M$22)/ext_sh+Thesis!$M$9/ext_sh*rent_mw)*Thesis!$M$10/1000 -> 55.38225 | N28: =Thesis!$N$9/ext_sh*(ox_open+rent_mw)*Thesis!$N$10/1000 -> 0.84337209 | O28: =Thesis!$O$9/ext_sh*(ox_open+rent_mw)*Thesis!$O$10/1000 -> 1.5662625
A29: AWS 營收（實績，Q 頁） | B29: US$bn | C29: =Q!$D$7 -> 107.556 | D29: =Q!$E$7 -> 128.725 | E29: =Q!$P$7 -> 79.819 | N29: =Q!$N$7 -> 60.14 | O29: =Q!$O$7 -> 68.585
A30: AWS 其他營收（非 AI 雲端） | B30: US$bn | C30: =Thesis!$C$29-Thesis!$C$26 -> 105.23499 | D30: =Thesis!$D$29-Thesis!$D$26 -> 120.02123 | E30: =Thesis!$E$29-Thesis!$E$26 -> 71.308647 | F30: =Thesis!$O$30*(1+Thesis!$F$31) -> 71.7693 | G30: =Thesis!$E$30+Thesis!$F$30 -> 143.07795 | H30: =Thesis!$G$30*(1+Thesis!$H$31) -> 161.01708 | I30: =Thesis!$H$30*(1+Thesis!$I$31) -> 178.76976 | J30: =Thesis!$I$30*(1+Thesis!$J$31) -> 195.77554 | K30: =Thesis!$J$30*(1+Thesis!$K$31) -> 211.43758 | L30: =Thesis!$K$30*(1+Thesis!$L$31) -> 228.35259 | M30: =Thesis!$L$30*(1+Thesis!$M$31) -> 246.62079 | N30: =Thesis!$N$29-Thesis!$N$26 -> 57.09368 | O30: =Thesis!$O$29-Thesis!$O$26 -> 62.927549 | P30: 實績＝AWS 實績 − AWS AI 分拆估計（殘差，Derived）
A31: AWS 其他年增 | B31: % | D31: =Thesis!$D$30/Thesis!$C$30-1 -> 0.14050683 | E31: =Thesis!$E$30/Thesis!$N$30-1 -> 0.24897618 | F31: =Thesis!$D$31 -> 0.14050683 | G31: =Thesis!$G$30/Thesis!$D$30-1 -> 0.19210532 | H31: =Thesis!$F$31+(g_awso_lt-Thesis!$F$31)*1/4 -> 0.12538012 | I31: =Thesis!$F$31+(g_awso_lt-Thesis!$F$31)*2/4 -> 0.11025341 | J31: =Thesis!$F$31+(g_awso_lt-Thesis!$F$31)*3/4 -> 0.095126707 | K31: =Thesis!$F$31+(g_awso_lt-Thesis!$F$31)*4/4 -> 0.08 | L31: =g_awso_lt -> 0.08 | M31: =g_awso_lt -> 0.08 | P31: 起點＝FY2025 年增（D 欄，Derived）；1H26 年增（E 欄）受 AI 分拆低估影響偏高，只列不用；收斂到 g_awso_lt
A32: 4. AI 資本支出（現金）→ 折舊（IT 6 年、機房 20 年；次年起提列）
A33: 2H26 非 AI 資本支出（零售＋AWS 其他） | B33: US$bn | F33: =cx_rt*Seg!$F$20+cx_awso*Thesis!$F$30 -> 34.807618
A34: AI 資本支出中 IT 比例 | B34: % | C34: =tk_cx_h100/(tk_cx_h100+tk_fac*(1-colo_sh)) -> 0.73075646 | D34: =tk_cx_h100/(tk_cx_h100+tk_fac*(1-colo_sh)) -> 0.73075646 | E34: =Thesis!$F$34 -> 0.76079233 | F34: =Thesis!$F$17/(Thesis!$F$17+tk_fac*(1-colo_sh)) -> 0.76079233 | G34: =Thesis!$G$17/(Thesis!$G$17+tk_fac*(1-colo_sh)) -> 0.76079233 | H34: =Thesis!$H$17/(Thesis!$H$17+tk_fac*(1-colo_sh)) -> 0.76811067 | I34: =Thesis!$I$17/(Thesis!$I$17+tk_fac*(1-colo_sh)) -> 0.7749945 | J34: =Thesis!$J$17/(Thesis!$J$17+tk_fac*(1-colo_sh)) -> 0.7749945 | K34: =Thesis!$K$17/(Thesis!$K$17+tk_fac*(1-colo_sh)) -> 0.7749945 | L34: =Thesis!$L$17/(Thesis!$L$17+tk_fac*(1-colo_sh)) -> 0.7749945 | M34: =Thesis!$M$17/(Thesis!$M$17+tk_fac*(1-colo_sh)) -> 0.7749945
A35: AI 資本支出（現金，含自用） | B35: US$bn | C35: =Q!$D$46-cx_rt*Q!$D$16-cx_awso*Thesis!$C$30 -> 25.278105 | D35: =Q!$E$46-cx_rt*Q!$E$16-cx_awso*Thesis!$D$30 -> 69.568632 | E35: =Q!$P$46-cx_rt*Q!$P$16-cx_awso*Thesis!$E$30 -> 64.189921 | F35: =MAX(Thesis!$F$12*(Thesis!$F$17+tk_fac*(1-colo_sh))/1000,capex_g26-Q!$P$46-Thesis!$F$33) -> 98.862028 | G35: =Thesis!$E$35+Thesis!$F$35 -> 163.05195 | H35: =Thesis!$H$12*(Thesis!$H$17+tk_fac*(1-colo_sh))/1000+Thesis!$H$36 -> 203.96415 | I35: =Thesis!$I$12*(Thesis!$I$17+tk_fac*(1-colo_sh))/1000+Thesis!$I$36 -> 210.20424 | J35: =Thesis!$J$12*(Thesis!$J$17+tk_fac*(1-colo_sh))/1000+Thesis!$J$36 -> 215.44101 | K35: =Thesis!$K$12*(Thesis!$K$17+tk_fac*(1-colo_sh))/1000+Thesis!$K$36 -> 159.13809 | L35: =Thesis!$L$12*(Thesis!$L$17+tk_fac*(1-colo_sh))/1000+Thesis!$L$36 -> 134.25578 | M35: =Thesis!$M$12*(Thesis!$M$17+tk_fac*(1-colo_sh))/1000+Thesis!$M$36 -> 134.96817 | P35: 實績＝公司資本支出淨額 − 非 AI（零售 cx_rt、AWS 其他 cx_awso）；2H26＝MAX(MW 公式, 指引 220 − 上半年 − 非 AI)；之後＝新增 MW ×（IT＋自建機房）＋汰換 | R35: =Q!$C$46-cx_rt*Q!$C$16-cx_awso*(Q!$C$7-mw_ye23/2*rpm_open/1000) -> 1.5042998 | S35: =Thesis!$C$35 -> 25.278105 | T35: =Thesis!$D$35 -> 69.568632 | U35: =Thesis!$G$35 -> 163.05195 | V35: =Thesis!$H$35 -> 203.96415 | W35: =Thesis!$I$35 -> 210.20424 | X35: =Thesis!$J$35 -> 215.44101 | Y35: =Thesis!$K$35 -> 159.13809 | Z35: =Thesis!$L$35 -> 134.25578 | AA35: =Thesis!$M$35 -> 134.96817
A36: IT 汰換（折舊年限前新增的總 MW × 當年 IT 每 MW） | B36: US$bn | H36: =SUMPRODUCT(--(Thesis!$R$5:$AA$5=2027-tk_life),Thesis!$R$12:$AA$12)*Thesis!$H$17/1000 -> 0 | I36: =SUMPRODUCT(--(Thesis!$R$5:$AA$5=2028-tk_life),Thesis!$R$12:$AA$12)*Thesis!$I$17/1000 -> 0 | J36: =SUMPRODUCT(--(Thesis!$R$5:$AA$5=2029-tk_life),Thesis!$R$12:$AA$12)*Thesis!$J$17/1000 -> 5.2367682 | K36: =SUMPRODUCT(--(Thesis!$R$5:$AA$5=2030-tk_life),Thesis!$R$12:$AA$12)*Thesis!$K$17/1000 -> 10.473536 | L36: =SUMPRODUCT(--(Thesis!$R$5:$AA$5=2031-tk_life),Thesis!$R$12:$AA$12)*Thesis!$L$17/1000 -> 47.130914 | M36: =SUMPRODUCT(--(Thesis!$R$5:$AA$5=2032-tk_life),Thesis!$R$12:$AA$12)*Thesis!$M$17/1000 -> 109.383
A37: 其中 IT 設備 | B37: US$bn | C37: =Thesis!$C$35*Thesis!$C$34 -> 18.472139 | D37: =Thesis!$D$35*Thesis!$D$34 -> 50.837727 | E37: =Thesis!$E$35*Thesis!$E$34 -> 48.8352 | F37: =Thesis!$F$35*Thesis!$F$34 -> 75.213473 | G37: =Thesis!$E$37+Thesis!$F$37 -> 124.04867 | H37: =(Thesis!$H$35-Thesis!$H$36)*Thesis!$H$34+Thesis!$H$36 -> 156.66704 | I37: =(Thesis!$I$35-Thesis!$I$36)*Thesis!$I$34+Thesis!$I$36 -> 162.90713 | J37: =(Thesis!$J$35-Thesis!$J$36)*Thesis!$J$34+Thesis!$J$36 -> 168.1439 | K37: =(Thesis!$K$35-Thesis!$K$36)*Thesis!$K$34+Thesis!$K$36 -> 125.68775 | L37: =(Thesis!$L$35-Thesis!$L$36)*Thesis!$L$34+Thesis!$L$36 -> 114.6522 | M37: =(Thesis!$M$35-Thesis!$M$36)*Thesis!$M$34+Thesis!$M$36 -> 129.21136 | R37: =Thesis!$R$35*Thesis!$C$34 -> 1.0992768 | S37: =Thesis!$C$37 -> 18.472139 | T37: =Thesis!$D$37 -> 50.837727 | U37: =Thesis!$G$37 -> 124.04867 | V37: =Thesis!$H$37 -> 156.66704 | W37: =Thesis!$I$37 -> 162.90713 | X37: =Thesis!$J$37 -> 168.1439 | Y37: =Thesis!$K$37 -> 125.68775 | Z37: =Thesis!$L$37 -> 114.6522 | AA37: =Thesis!$M$37 -> 129.21136
A38: 其中機房（自建部分） | B38: US$bn | C38: =Thesis!$C$35-Thesis!$C$37 -> 6.8059666 | D38: =Thesis!$D$35-Thesis!$D$37 -> 18.730905 | E38: =Thesis!$E$35-Thesis!$E$37 -> 15.354721 | F38: =Thesis!$F$35-Thesis!$F$37 -> 23.648555 | G38: =Thesis!$G$35-Thesis!$G$37 -> 39.003276 | H38: =Thesis!$H$35-Thesis!$H$37 -> 47.29711 | I38: =Thesis!$I$35-Thesis!$I$37 -> 47.29711 | J38: =Thesis!$J$35-Thesis!$J$37 -> 47.29711 | K38: =Thesis!$K$35-Thesis!$K$37 -> 33.450342 | L38: =Thesis!$L$35-Thesis!$L$37 -> 19.603573 | M38: =Thesis!$M$35-Thesis!$M$37 -> 5.7568045 | R38: =Thesis!$R$35-Thesis!$R$37 -> 0.40502301 | S38: =Thesis!$S$35-Thesis!$S$37 -> 6.8059666 | T38: =Thesis!$T$35-Thesis!$T$37 -> 18.730905 | U38: =Thesis!$U$35-Thesis!$U$37 -> 39.003276 | V38: =Thesis!$V$35-Thesis!$V$37 -> 47.29711 | W38: =Thesis!$W$35-Thesis!$W$37 -> 47.29711 | X38: =Thesis!$X$35-Thesis!$X$37 -> 47.29711 | Y38: =Thesis!$Y$35-Thesis!$Y$37 -> 33.450342 | Z38: =Thesis!$Z$35-Thesis!$Z$37 -> 19.603573 | AA38: =Thesis!$AA$35-Thesis!$AA$37 -> 5.7568045
A39: AI 資本支出占公司資本支出 | B39: % | C39: =Thesis!$C$35/CF!$C$24 -> 0.32550549 | D39: =Thesis!$D$35/CF!$D$24 -> 0.54214956 | E39: =Thesis!$E$35/CF!$E$24 -> 0.66649279 | F39: =Thesis!$F$35/CF!$F$24 -> 0.73959969 | G39: =Thesis!$G$35/CF!$G$24 -> 0.70898426 | H39: =Thesis!$H$35/CF!$H$24 -> 0.73215175 | I39: =Thesis!$I$35/CF!$I$24 -> 0.71904358 | J39: =Thesis!$J$35/CF!$J$24 -> 0.70715839 | K39: =Thesis!$K$35/CF!$K$24 -> 0.62474261 | L39: =Thesis!$L$35/CF!$L$24 -> 0.56721746 | M39: =Thesis!$M$35/CF!$M$24 -> 0.5514156
A40: AI IT 折舊 | B40: US$bn | C40: =Thesis!$S$40 -> 0.1832128 | D40: =Thesis!$T$40 -> 3.2619026 | E40: =Thesis!$G$40/2 -> 5.8674285 | F40: =Thesis!$G$40/2 -> 5.8674285 | G40: =Thesis!$U$40 -> 11.734857 | H40: =Thesis!$V$40 -> 32.409636 | I40: =Thesis!$W$40 -> 58.520809 | J40: =Thesis!$X$40 -> 85.671997 | K40: =Thesis!$Y$40 -> 113.51277 | L40: =Thesis!$Z$40 -> 131.38204 | M40: =Thesis!$AA$40 -> 142.01778 | N40: =Thesis!$D$40/2 -> 1.6309513 | O40: =Thesis!$D$40/2 -> 1.6309513 | R40: =SUMPRODUCT(--(Thesis!$R$5:$AA$5<Thesis!R$5),--(Thesis!$R$5:$AA$5>=Thesis!R$5-tk_life),Thesis!$R$37:$AA$37)/tk_life -> 0 | S40: =SUMPRODUCT(--(Thesis!$R$5:$AA$5<Thesis!S$5),--(Thesis!$R$5:$AA$5>=Thesis!S$5-tk_life),Thesis!$R$37:$AA$37)/tk_life -> 0.1832128 | T40: =SUMPRODUCT(--(Thesis!$R$5:$AA$5<Thesis!T$5),--(Thesis!$R$5:$AA$5>=Thesis!T$5-tk_life),Thesis!$R$37:$AA$37)/tk_life -> 3.2619026 | U40: =SUMPRODUCT(--(Thesis!$R$5:$AA$5<Thesis!U$5),--(Thesis!$R$5:$AA$5>=Thesis!U$5-tk_life),Thesis!$R$37:$AA$37)/tk_life -> 11.734857 | V40: =SUMPRODUCT(--(Thesis!$R$5:$AA$5<Thesis!V$5),--(Thesis!$R$5:$AA$5>=Thesis!V$5-tk_life),Thesis!$R$37:$AA$37)/tk_life -> 32.409636 | W40: =SUMPRODUCT(--(Thesis!$R$5:$AA$5<Thesis!W$5),--(Thesis!$R$5:$AA$5>=Thesis!W$5-tk_life),Thesis!$R$37:$AA$37)/tk_life -> 58.520809 | X40: =SUMPRODUCT(--(Thesis!$R$5:$AA$5<Thesis!X$5),--(Thesis!$R$5:$AA$5>=Thesis!X$5-tk_life),Thesis!$R$37:$AA$37)/tk_life -> 85.671997 | Y40: =SUMPRODUCT(--(Thesis!$R$5:$AA$5<Thesis!Y$5),--(Thesis!$R$5:$AA$5>=Thesis!Y$5-tk_life),Thesis!$R$37:$AA$37)/tk_life -> 113.51277 | ... AA40: =SUMPRODUCT(--(Thesis!$R$5:$AA$5<Thesis!AA$5),--(Thesis!$R$5:$AA$5>=Thesis!AA$5-tk_life),Thesis!$R$37:$AA$37)/tk_life -> 142.01778
A41: AI 機房折舊 | B41: US$bn | C41: =Thesis!$S$41 -> 0.02025115 | D41: =Thesis!$T$41 -> 0.36054948 | E41: =Thesis!$G$41/2 -> 0.64854736 | F41: =Thesis!$G$41/2 -> 0.64854736 | G41: =Thesis!$U$41 -> 1.2970947 | H41: =Thesis!$V$41 -> 3.2472585 | I41: =Thesis!$W$41 -> 5.612114 | J41: =Thesis!$X$41 -> 7.9769695 | K41: =Thesis!$Y$41 -> 10.341825 | L41: =Thesis!$Z$41 -> 12.014342 | M41: =Thesis!$AA$41 -> 12.994521 | N41: =Thesis!$D$41/2 -> 0.18027474 | O41: =Thesis!$D$41/2 -> 0.18027474 | R41: =SUMPRODUCT(--(Thesis!$R$5:$AA$5<Thesis!R$5),Thesis!$R$38:$AA$38)/fac_life -> 0 | S41: =SUMPRODUCT(--(Thesis!$R$5:$AA$5<Thesis!S$5),Thesis!$R$38:$AA$38)/fac_life -> 0.02025115 | T41: =SUMPRODUCT(--(Thesis!$R$5:$AA$5<Thesis!T$5),Thesis!$R$38:$AA$38)/fac_life -> 0.36054948 | U41: =SUMPRODUCT(--(Thesis!$R$5:$AA$5<Thesis!U$5),Thesis!$R$38:$AA$38)/fac_life -> 1.2970947 | V41: =SUMPRODUCT(--(Thesis!$R$5:$AA$5<Thesis!V$5),Thesis!$R$38:$AA$38)/fac_life -> 3.2472585 | W41: =SUMPRODUCT(--(Thesis!$R$5:$AA$5<Thesis!W$5),Thesis!$R$38:$AA$38)/fac_life -> 5.612114 | X41: =SUMPRODUCT(--(Thesis!$R$5:$AA$5<Thesis!X$5),Thesis!$R$38:$AA$38)/fac_life -> 7.9769695 | Y41: =SUMPRODUCT(--(Thesis!$R$5:$AA$5<Thesis!Y$5),Thesis!$R$38:$AA$38)/fac_life -> 10.341825 | ... AA41: =SUMPRODUCT(--(Thesis!$R$5:$AA$5<Thesis!AA$5),Thesis!$R$38:$AA$38)/fac_life -> 12.994521
A42: AI 折舊合計（對外 → AWS；自用 → 零售分部） | B42: US$bn | C42: =Thesis!$C$40+Thesis!$C$41 -> 0.20346395 | D42: =Thesis!$D$40+Thesis!$D$41 -> 3.6224521 | E42: =Thesis!$E$40+Thesis!$E$41 -> 6.5159759 | F42: =Thesis!$F$40+Thesis!$F$41 -> 6.5159759 | G42: =Thesis!$G$40+Thesis!$G$41 -> 13.031952 | H42: =Thesis!$H$40+Thesis!$H$41 -> 35.656894 | I42: =Thesis!$I$40+Thesis!$I$41 -> 64.132923 | J42: =Thesis!$J$40+Thesis!$J$41 -> 93.648967 | K42: =Thesis!$K$40+Thesis!$K$41 -> 123.85459 | L42: =Thesis!$L$40+Thesis!$L$41 -> 143.39638 | M42: =Thesis!$M$40+Thesis!$M$41 -> 155.0123 | N42: =Thesis!$N$40+Thesis!$N$41 -> 1.811226 | O42: =Thesis!$O$40+Thesis!$O$41 -> 1.811226 | R42: =Thesis!$R$40+Thesis!$R$41 -> 0 | S42: =Thesis!$S$40+Thesis!$S$41 -> 0.20346395 | T42: =Thesis!$T$40+Thesis!$T$41 -> 3.6224521 | U42: =Thesis!$U$40+Thesis!$U$41 -> 13.031952 | V42: =Thesis!$V$40+Thesis!$V$41 -> 35.656894 | W42: =Thesis!$W$40+Thesis!$W$41 -> 64.132923 | X42: =Thesis!$X$40+Thesis!$X$41 -> 93.648967 | Y42: =Thesis!$Y$40+Thesis!$Y$41 -> 123.85459 | Z42: =Thesis!$Z$40+Thesis!$Z$41 -> 143.39638 | AA42: =Thesis!$AA$40+Thesis!$AA$41 -> 155.0123
A43: AI 淨 PP&E（期末） | B43: US$bn | C43: =Thesis!$S$43 -> 26.578941 | D43: =Thesis!$T$43 -> 92.525121 | G43: =Thesis!$U$43 -> 242.54512 | H43: =Thesis!$V$43 -> 410.85237 | I43: =Thesis!$W$43 -> 556.92369 | J43: =Thesis!$X$43 -> 678.71573 | K43: =Thesis!$Y$43 -> 713.99923 | L43: =Thesis!$Z$43 -> 704.85862 | M43: =Thesis!$AA$43 -> 684.81449 | R43: =SUM(Thesis!$R$35:$R$35)-SUM(Thesis!$R$42:$R$42) -> 1.5042998 | S43: =SUM(Thesis!$R$35:$S$35)-SUM(Thesis!$R$42:$S$42) -> 26.578941 | T43: =SUM(Thesis!$R$35:$T$35)-SUM(Thesis!$R$42:$T$42) -> 92.525121 | U43: =SUM(Thesis!$R$35:$U$35)-SUM(Thesis!$R$42:$U$42) -> 242.54512 | V43: =SUM(Thesis!$R$35:$V$35)-SUM(Thesis!$R$42:$V$42) -> 410.85237 | W43: =SUM(Thesis!$R$35:$W$35)-SUM(Thesis!$R$42:$W$42) -> 556.92369 | X43: =SUM(Thesis!$R$35:$X$35)-SUM(Thesis!$R$42:$X$42) -> 678.71573 | Y43: =SUM(Thesis!$R$35:$Y$35)-SUM(Thesis!$R$42:$Y$42) -> 713.99923 | Z43: =SUM(Thesis!$R$35:$Z$35)-SUM(Thesis!$R$42:$Z$42) -> 704.85862 | AA43: =SUM(Thesis!$R$35:$AA$35)-SUM(Thesis!$R$42:$AA$42) -> 684.81449
A44: 5. AWS AI 營業利益、自用 AI 成本、AWS 其他
A45: AWS AI EBITDA＝營收 − 對外比例 × 營運成本 | B45: US$bn | C45: =Thesis!$C$26-ext_sh*Thesis!$C$28 -> 1.80695 | D45: =Thesis!$D$26-ext_sh*Thesis!$D$28 -> 6.7760625 | E45: =Thesis!$E$26-ext_sh*Thesis!$E$28 -> 6.6254833 | F45: =Thesis!$F$26-ext_sh*Thesis!$F$28 -> 14.49967 | G45: =Thesis!$G$26-ext_sh*Thesis!$G$28 -> 21.125153 | H45: =Thesis!$H$26-ext_sh*Thesis!$H$28 -> 70.212636 | I45: =Thesis!$I$26-ext_sh*Thesis!$I$28 -> 126.6786 | J45: =Thesis!$J$26-ext_sh*Thesis!$J$28 -> 183.41794 | K45: =Thesis!$K$26-ext_sh*Thesis!$K$28 -> 231.81575 | L45: =Thesis!$L$26-ext_sh*Thesis!$L$28 -> 263.61276 | M45: =Thesis!$M$26-ext_sh*Thesis!$M$28 -> 278.76449 | N45: =Thesis!$N$26-ext_sh*Thesis!$N$28 -> 2.3716219 | O45: =Thesis!$O$26-ext_sh*Thesis!$O$28 -> 4.4044406
A46: AWS AI 營業利益＝EBITDA − 對外比例 × AI 折舊 | B46: US$bn | C46: =Thesis!$C$45-ext_sh*Thesis!$C$42 -> 1.6441788 | D46: =Thesis!$D$45-ext_sh*Thesis!$D$42 -> 3.8781008 | E46: =Thesis!$E$45-ext_sh*Thesis!$E$42 -> 1.4127026 | F46: =Thesis!$F$45-ext_sh*Thesis!$F$42 -> 9.2868889 | G46: =Thesis!$G$45-ext_sh*Thesis!$G$42 -> 10.699591 | H46: =Thesis!$H$45-ext_sh*Thesis!$H$42 -> 41.68712 | I46: =Thesis!$I$45-ext_sh*Thesis!$I$42 -> 75.372265 | J46: =Thesis!$J$45-ext_sh*Thesis!$J$42 -> 108.49876 | K46: =Thesis!$K$45-ext_sh*Thesis!$K$42 -> 132.73207 | L46: =Thesis!$L$45-ext_sh*Thesis!$L$42 -> 148.89565 | M46: =Thesis!$M$45-ext_sh*Thesis!$M$42 -> 154.75465 | N46: =Thesis!$N$45-ext_sh*Thesis!$N$42 -> 0.92264103 | O46: =Thesis!$O$45-ext_sh*Thesis!$O$42 -> 2.9554598
A47: AWS AI 營業利益率 | B47: % | C47: =Thesis!$C$46/Thesis!$C$26 -> 0.70839079 | D47: =Thesis!$D$46/Thesis!$D$26 -> 0.44556563 | E47: =Thesis!$E$46/Thesis!$E$26 -> 0.16599812 | F47: =Thesis!$F$46/Thesis!$F$26 -> 0.52259754 | G47: =Thesis!$G$46/Thesis!$G$26 -> 0.40712292 | H47: =Thesis!$H$46/Thesis!$H$26 -> 0.50174743 | I47: =Thesis!$I$46/Thesis!$I$26 -> 0.50900968 | J47: =Thesis!$J$46/Thesis!$J$26 -> 0.50852954 | K47: =Thesis!$K$46/Thesis!$K$26 -> 0.49334456 | L47: =Thesis!$L$46/Thesis!$L$26 -> 0.48717319 | M47: =Thesis!$M$46/Thesis!$M$26 -> 0.47901231 | N47: =Thesis!$N$46/Thesis!$N$26 -> 0.30287073 | O47: =Thesis!$O$46/Thesis!$O$26 -> 0.52240134
A48: 自用 AI 影子效益（讀法 2：自用 MW × HoldEcon × k＝1；讀法 1 為 0；非財報營收） | B48: US$bn | C48: 0 | D48: 0 | E48: 0 | F48: =IF(internal_ai_reading=2,1,0)*(1-ext_sh)/ext_sh*(mw_open*he_open+Thesis!$F$24*Thesis!$F$21)*Thesis!$F$10/1000 -> 3.8047983 | G48: =Thesis!$E$48+Thesis!$F$48 -> 3.8047983 | H48: =IF(internal_ai_reading=2,1,0)*(1-ext_sh)/ext_sh*(mw_open*he_open+Thesis!$H$24*Thesis!$H$21)*Thesis!$H$10/1000 -> 15.437683 | I48: =IF(internal_ai_reading=2,1,0)*(1-ext_sh)/ext_sh*(mw_open*he_open+Thesis!$I$24*Thesis!$I$21)*Thesis!$I$10/1000 -> 26.138954 | J48: =IF(internal_ai_reading=2,1,0)*(1-ext_sh)/ext_sh*(mw_open*he_open+Thesis!$J$24*Thesis!$J$21)*Thesis!$J$10/1000 -> 36.88783 | K48: =IF(internal_ai_reading=2,1,0)*(1-ext_sh)/ext_sh*(mw_open*he_open+Thesis!$K$24*Thesis!$K$21)*Thesis!$K$10/1000 -> 46.057013 | L48: =IF(internal_ai_reading=2,1,0)*(1-ext_sh)/ext_sh*(mw_open*he_open+Thesis!$L$24*Thesis!$L$21)*Thesis!$L$10/1000 -> 52.081131 | M48: =IF(internal_ai_reading=2,1,0)*(1-ext_sh)/ext_sh*(mw_open*he_open+Thesis!$M$24*Thesis!$M$21)*Thesis!$M$10/1000 -> 54.952438 | N48: 0 | O48: 0 | P48: In 頁 internal_ai_reading＝2（主值）；只進評價口徑（NOPAT、EPS 評價口徑、分部加總零售本業）；實績欄為 0
A49: 自用 AI 成本（營運＋折舊；分攤到北美／國際，財報口徑） | B49: US$bn | C49: =(1-ext_sh)*(Thesis!$C$28+Thesis!$C$42) -> 0.16920663 | D49: =(1-ext_sh)*(Thesis!$D$28+Thesis!$D$42) -> 1.2064173 | E49: =(1-ext_sh)*(Thesis!$E$28+Thesis!$E$42) -> 1.7744126 | F49: =(1-ext_sh)*(Thesis!$F$28+Thesis!$F$42) -> 2.1209359 | G49: =(1-ext_sh)*(Thesis!$G$28+Thesis!$G$42) -> 3.8953485 | H49: =(1-ext_sh)*(Thesis!$H$28+Thesis!$H$42) -> 10.349188 | I49: =(1-ext_sh)*(Thesis!$I$28+Thesis!$I$42) -> 18.176007 | J49: =(1-ext_sh)*(Thesis!$J$28+Thesis!$J$42) -> 26.214769 | K49: =(1-ext_sh)*(Thesis!$K$28+Thesis!$K$42) -> 34.078326 | L49: =(1-ext_sh)*(Thesis!$L$28+Thesis!$L$42) -> 39.184054 | M49: =(1-ext_sh)*(Thesis!$M$28+Thesis!$M$42) -> 42.07891 | N49: =(1-ext_sh)*(Thesis!$N$28+Thesis!$N$42) -> 0.53091962 | O49: =(1-ext_sh)*(Thesis!$O$28+Thesis!$O$42) -> 0.6754977
A50: AWS 營業利益（實績，Q 頁） | B50: US$bn | C50: =Q!$D$24 -> 39.834 | D50: =Q!$E$24 -> 45.606 | E50: =Q!$P$24 -> 30.782 | N50: =Q!$N$24 -> 21.707 | O50: =Q!$O$24 -> 23.899
A51: AWS 其他營業利益 | B51: US$bn | C51: =Thesis!$C$50-Thesis!$C$46 -> 38.189821 | D51: =Thesis!$D$50-Thesis!$D$46 -> 41.727899 | E51: =Thesis!$E$50-Thesis!$E$46 -> 29.369297 | F51: =Thesis!$F$30*Thesis!$F$52 -> 26.899728 | G51: =Thesis!$E$51+Thesis!$F$51 -> 56.269025 | H51: =Thesis!$H$30*Thesis!$H$52 -> 60.350533 | I51: =Thesis!$I$30*Thesis!$I$52 -> 67.004386 | J51: =Thesis!$J$30*Thesis!$J$52 -> 73.378292 | K51: =Thesis!$K$30*Thesis!$K$52 -> 79.248556 | L51: =Thesis!$L$30*Thesis!$L$52 -> 85.58844 | M51: =Thesis!$M$30*Thesis!$M$52 -> 92.435515 | N51: =Thesis!$N$50-Thesis!$N$46 -> 20.784359 | O51: =Thesis!$O$50-Thesis!$O$46 -> 20.94354 | P51: 實績＝AWS 營業利益 − AWS AI 營業利益（殘差）
A52: AWS 其他營業利益率 | B52: % | C52: =Thesis!$C$51/Thesis!$C$30 -> 0.3629004 | D52: =Thesis!$D$51/Thesis!$D$30 -> 0.34767098 | E52: =Thesis!$E$51/Thesis!$E$30 -> 0.41186166 | F52: =(Thesis!$O$51+Thesis!$E$51)/(Thesis!$O$30+Thesis!$E$30) -> 0.37480828 | G52: =Thesis!$G$51/Thesis!$G$30 -> 0.39327532 | H52: =Thesis!$F$52 -> 0.37480828 | I52: =Thesis!$F$52 -> 0.37480828 | J52: =Thesis!$F$52 -> 0.37480828 | K52: =Thesis!$F$52 -> 0.37480828 | L52: =Thesis!$F$52 -> 0.37480828 | M52: =Thesis!$F$52 -> 0.37480828 | N52: =Thesis!$N$51/Thesis!$N$30 -> 0.36403957 | O52: =Thesis!$O$51/Thesis!$O$30 -> 0.33281989 | P52: 2H26 起固定為近四季（2H25＋1H26）殘差利益率（Derived）
A53: AWS 非 AI 折舊 ÷ AWS 其他營收（FY2025 校準） | B53: % | D53: =(Q!$E$31-ext_sh*Thesis!$D$42)/Thesis!$D$30 -> 0.15457297
A54: AWS 折舊攤銷（分部） | B54: US$bn | C54: =Q!$D$31 -> 13.32 | D54: =Q!$E$31 -> 21.45 | E54: =Q!$P$31 -> 15.353 | F54: =ext_sh*Thesis!$F$42+Thesis!$D$53*Thesis!$F$30 -> 16.306375 | G54: =Thesis!$E$54+Thesis!$F$54 -> 31.659375 | H54: =ext_sh*Thesis!$H$42+Thesis!$D$53*Thesis!$H$30 -> 53.414404 | I54: =ext_sh*Thesis!$I$42+Thesis!$D$53*Thesis!$I$30 -> 78.939312 | J54: =ext_sh*Thesis!$J$42+Thesis!$D$53*Thesis!$J$30 -> 105.18078 | K54: =ext_sh*Thesis!$K$42+Thesis!$D$53*Thesis!$K$30 -> 131.76621 | L54: =ext_sh*Thesis!$L$42+Thesis!$D$53*Thesis!$L$30 -> 150.01424 | M54: =ext_sh*Thesis!$M$42+Thesis!$D$53*Thesis!$M$30 -> 162.13075 | N54: =Q!$N$31 -> 9.234 | O54: =Q!$O$31 -> 12.216
A55: 6. 命題指標
A56: 對外 AI ROIC（稅後營業利益 ÷ 對外分攤的平均 AI 淨 PP&E） | B56: % | G56: =Thesis!$G$46*(1-tax)/(ext_sh*(Thesis!$D$43+Thesis!$G$43)/2) -> 0.06597354 | H56: =Thesis!$H$46*(1-tax)/(ext_sh*(Thesis!$G$43+Thesis!$H$43)/2) -> 0.13181441 | I56: =Thesis!$I$46*(1-tax)/(ext_sh*(Thesis!$H$43+Thesis!$I$43)/2) -> 0.16090708 | J56: =Thesis!$J$46*(1-tax)/(ext_sh*(Thesis!$I$43+Thesis!$J$43)/2) -> 0.18141429 | K56: =Thesis!$K$46*(1-tax)/(ext_sh*(Thesis!$J$43+Thesis!$K$43)/2) -> 0.19690289 | L56: =Thesis!$L$46*(1-tax)/(ext_sh*(Thesis!$K$43+Thesis!$L$43)/2) -> 0.21681114 | M56: =Thesis!$M$46*(1-tax)/(ext_sh*(Thesis!$L$43+Thesis!$M$43)/2) -> 0.23007503 | P56: C11：分子分母同口徑（對外）
A57: 機隊平均 k（營收 ÷ 持有成本） | B57: x | H57: =Thesis!$H$26*1000/(mw_open*he_open+Thesis!$H$24*Thesis!$H$21) -> 1.3454719 | I57: =Thesis!$I$26*1000/(mw_open*he_open+Thesis!$I$24*Thesis!$I$21) -> 1.4162416 | J57: =Thesis!$J$26*1000/(mw_open*he_open+Thesis!$J$24*Thesis!$J$21) -> 1.4459907 | K57: =Thesis!$K$26*1000/(mw_open*he_open+Thesis!$K$24*Thesis!$K$21) -> 1.4603931 | L57: =Thesis!$L$26*1000/(mw_open*he_open+Thesis!$L$24*Thesis!$L$21) -> 1.467095 | M57: =Thesis!$M$26*1000/(mw_open*he_open+Thesis!$M$24*Thesis!$M$21) -> 1.4697723
A58: 打平 k（對外 AI ROIC＝WACC 所需的機隊平均 k） | B58: x | H58: =Thesis!$H$57*(Thesis!$H$26+wacc*ext_sh*(Thesis!$G$43+Thesis!$H$43)/2/(1-tax)-Thesis!$H$46)/Thesis!$H$26 -> 1.2506372 | I58: =Thesis!$I$57*(Thesis!$I$26+wacc*ext_sh*(Thesis!$H$43+Thesis!$I$43)/2/(1-tax)-Thesis!$I$46)/Thesis!$I$26 -> 1.2029453 | J58: =Thesis!$J$57*(Thesis!$J$26+wacc*ext_sh*(Thesis!$I$43+Thesis!$J$43)/2/(1-tax)-Thesis!$J$46)/Thesis!$J$26 -> 1.1698917 | K58: =Thesis!$K$57*(Thesis!$K$26+wacc*ext_sh*(Thesis!$J$43+Thesis!$K$43)/2/(1-tax)-Thesis!$K$46)/Thesis!$K$26 -> 1.1544767 | L58: =Thesis!$L$57*(Thesis!$L$26+wacc*ext_sh*(Thesis!$K$43+Thesis!$L$43)/2/(1-tax)-Thesis!$L$46)/Thesis!$L$26 -> 1.1258566 | M58: =Thesis!$M$57*(Thesis!$M$26+wacc*ext_sh*(Thesis!$L$43+Thesis!$M$43)/2/(1-tax)-Thesis!$M$46)/Thesis!$M$26 -> 1.112428
A59: 上限檢查：全機隊每 MW 年收入 ÷ Tokenomics P×Q（VR200） | B59: % | C59: =Thesis!$C$27/tk_pq -> 0.19531643 | D59: =Thesis!$D$27/tk_pq -> 0.19531643 | E59: =Thesis!$E$27/tk_pq -> 0.19531643 | F59: =Thesis!$F$27/tk_pq -> 0.23821637 | G59: =Thesis!$G$27/tk_pq -> 0.22239824 | H59: =Thesis!$H$27/tk_pq -> 0.28866245 | I59: =Thesis!$I$27/tk_pq -> 0.31328383 | J59: =Thesis!$J$27/tk_pq -> 0.32450181 | K59: =Thesis!$K$27/tk_pq -> 0.3300068 | L59: =Thesis!$L$27/tk_pq -> 0.33259235 | M59: =Thesis!$M$27/tk_pq -> 0.33358076 | N59: =Thesis!$N$27/tk_pq -> 0.19531643 | O59: =Thesis!$O$27/tk_pq -> 0.19531643 | P59: 上限，不得作預測；只作檢查
A62: Thesis｜情境 B（基準）：命題模組 AWS AI＝對外 AI 在役 MW × 每 MW 年收入（Tokenomics 持有成本 × k）；AI 資本支出 → 折舊 → 分部營業利益
A63: 項目 | B63: 單位 | C63: FY2024A | D63: FY2025A | E63: 1H26A | F63: 2H26E | G63: FY2026E（1H 實績＋2H 模型） | H63: FY2027E | I63: FY2028E | J63: FY2029E | K63: FY2030E | L63: FY2031E | M63: FY2032E | N63: 1H25A | O63: 2H25A | P63: 說明 | R63: 2023 | S63: 2024 | T63: 2025 | U63: 2026 | V63: 2027 | W63: 2028 | X63: 2029 | Y63: 2030 | Z63: 2031 | AA63: 2032
A64: 1. 容量（對外 AI 在役 MW-IT；期末）
A65: 對外 AI MW 每年新增（2030–2032 線性收斂到 FY2029 年底 MW × g，F5） | B65: MW/年 | H65: =pace_B -> 3634.3 | I65: =pace_B -> 3634.3 | J65: =pace_B -> 3634.3 | K65: =pace_B+(Thesis!$J$66*tg-pace_B)*1/3 -> 2570.8672 | L65: =pace_B+(Thesis!$J$66*tg-pace_B)*2/3 -> 1507.4343 | M65: =pace_B+(Thesis!$J$66*tg-pace_B)*3/3 -> 444.0015 | P65: 終值不落在建置高峰（共同修正 F5）
A66: 對外 AI 在役 MW（期末） | B66: MW | C66: =mw_ye24 -> 360 | D66: =mw_ye25 -> 1440 | E66: =mw_open -> 2080 | F66: =Thesis!$E$66+pace_B*0.5 -> 3897.15 | G66: =Thesis!$F$66 -> 3897.15 | H66: =Thesis!$G$66+Thesis!$H$65 -> 7531.45 | I66: =Thesis!$H$66+Thesis!$I$65 -> 11165.75 | J66: =Thesis!$I$66+Thesis!$J$65 -> 14800.05 | K66: =Thesis!$J$66+Thesis!$K$65 -> 17370.917 | L66: =Thesis!$K$66+Thesis!$L$65 -> 18878.352 | M66: =Thesis!$L$66+Thesis!$M$65 -> 19322.353 | N66: =(mw_ye24+mw_ye25)/2 -> 900 | O66: =mw_ye25 -> 1440 | P66: 期初 2026-06-30＝In 頁 mw_open；每年新增＝In 頁 pace（情境）；歷史年底值只用於分拆與折舊年份
A67: 對外 AI 平均在役 MW（期間） | B67: MW | C67: =(mw_ye23+mw_ye24)/2 -> 240 | D67: =(Thesis!$C$66+Thesis!$D$66)/2 -> 900 | E67: =(Thesis!$D$66+Thesis!$E$66)/2 -> 1760 | F67: =(Thesis!$E$66+Thesis!$F$66)/2 -> 2988.575 | G67: =(Thesis!$E$67+Thesis!$F$67)/2 -> 2374.2875 | H67: =(Thesis!$G$66+Thesis!$H$66)/2 -> 5714.3 | I67: =(Thesis!$H$66+Thesis!$I$66)/2 -> 9348.6 | J67: =(Thesis!$I$66+Thesis!$J$66)/2 -> 12982.9 | K67: =(Thesis!$J$66+Thesis!$K$66)/2 -> 16085.484 | L67: =(Thesis!$K$66+Thesis!$L$66)/2 -> 18124.634 | M67: =(Thesis!$L$66+Thesis!$M$66)/2 -> 19100.352 | N67: =(Thesis!$C$66+Thesis!$N$66)/2 -> 630 | O67: =(Thesis!$N$66+Thesis!$O$66)/2 -> 1170
A68: 期間長度 | B68: 年 | C68: 1 | D68: 1 | E68: 0.5 | F68: 0.5 | G68: 1 | H68: 1 | I68: 1 | J68: 1 | K68: 1 | L68: 1 | M68: 1 | N68: 0.5 | O68: 0.5
A69: 新增對外 AI MW | B69: MW | C69: =Thesis!$C$66-mw_ye23 -> 240 | D69: =Thesis!$D$66-Thesis!$C$66 -> 1080 | E69: =Thesis!$E$66-Thesis!$D$66 -> 640 | F69: =Thesis!$F$66-Thesis!$E$66 -> 1817.15 | G69: =Thesis!$E$69+Thesis!$F$69 -> 2457.15 | H69: =Thesis!$H$66-Thesis!$G$66 -> 3634.3 | I69: =Thesis!$I$66-Thesis!$H$66 -> 3634.3 | J69: =Thesis!$J$66-Thesis!$I$66 -> 3634.3 | K69: =Thesis!$K$66-Thesis!$J$66 -> 2570.8672 | L69: =Thesis!$L$66-Thesis!$K$66 -> 1507.4343 | M69: =Thesis!$M$66-Thesis!$L$66 -> 444.0015 | N69: =Thesis!$N$66-Thesis!$C$66 -> 540 | O69: =Thesis!$O$66-Thesis!$N$66 -> 540
A70: 新增 AI 總 MW（含自用＝對外 ÷ 對外比例） | B70: MW | C70: =Thesis!$C$69/ext_sh -> 300 | D70: =Thesis!$D$69/ext_sh -> 1350 | E70: =Thesis!$E$69/ext_sh -> 800 | F70: =Thesis!$F$69/ext_sh -> 2271.4375 | G70: =Thesis!$G$69/ext_sh -> 3071.4375 | H70: =Thesis!$H$69/ext_sh -> 4542.875 | I70: =Thesis!$I$69/ext_sh -> 4542.875 | J70: =Thesis!$J$69/ext_sh -> 4542.875 | K70: =Thesis!$K$69/ext_sh -> 3213.584 | L70: =Thesis!$L$69/ext_sh -> 1884.2929 | M70: =Thesis!$M$69/ext_sh -> 555.00187 | N70: =Thesis!$N$69/ext_sh -> 675 | O70: =Thesis!$O$69/ext_sh -> 675 | P70: R–AA 欄：依年份（折舊與汰換用） | R70: =mw_ye23/ext_sh -> 150 | S70: =Thesis!$C$70 -> 300 | T70: =Thesis!$D$70 -> 1350 | U70: =Thesis!$G$70 -> 3071.4375 | V70: =Thesis!$H$70 -> 4542.875 | W70: =Thesis!$I$70 -> 4542.875 | X70: =Thesis!$J$70 -> 4542.875 | Y70: =Thesis!$K$70 -> 3213.584 | Z70: =Thesis!$L$70 -> 1884.2929 | AA70: =Thesis!$M$70 -> 555.00187
A71: 2. 新增產能的世代與單位經濟（Tokenomics v21.4 基準成本；自研晶片以同期 NVIDIA 世代計價，C2）
A72: NVIDIA 新增中 VR200 比例 | B72: % | F72: =na_vr26 -> 0 | G72: =na_vr26 -> 0 | H72: =na_vr27 -> 0.5 | I72: =na_vr28 -> 1 | J72: =na_vr28 -> 1 | K72: =na_vr28 -> 1 | L72: =na_vr28 -> 1 | M72: =na_vr28 -> 1
A73: 新增 MW 加權 IF_HoldEcon（含自研晶片係數） | B73: US$m/MW-年 | F73: =cust_sh*tk_he_gb300*cf_chip+(1-cust_sh)*((1-Thesis!$F$72)*tk_he_gb300+Thesis!$F$72*tk_he_vr200) -> 10.886411 | G73: =cust_sh*tk_he_gb300*cf_chip+(1-cust_sh)*((1-Thesis!$G$72)*tk_he_gb300+Thesis!$G$72*tk_he_vr200) -> 10.886411 | H73: =cust_sh*tk_he_gb300*cf_chip+(1-cust_sh)*((1-Thesis!$H$72)*tk_he_gb300+Thesis!$H$72*tk_he_vr200) -> 11.221176 | I73: =cust_sh*tk_he_gb300*cf_chip+(1-cust_sh)*((1-Thesis!$I$72)*tk_he_gb300+Thesis!$I$72*tk_he_vr200) -> 11.555941 | J73: =cust_sh*tk_he_gb300*cf_chip+(1-cust_sh)*((1-Thesis!$J$72)*tk_he_gb300+Thesis!$J$72*tk_he_vr200) -> 11.555941 | K73: =cust_sh*tk_he_gb300*cf_chip+(1-cust_sh)*((1-Thesis!$K$72)*tk_he_gb300+Thesis!$K$72*tk_he_vr200) -> 11.555941 | L73: =cust_sh*tk_he_gb300*cf_chip+(1-cust_sh)*((1-Thesis!$L$72)*tk_he_gb300+Thesis!$L$72*tk_he_vr200) -> 11.555941 | M73: =cust_sh*tk_he_gb300*cf_chip+(1-cust_sh)*((1-Thesis!$M$72)*tk_he_gb300+Thesis!$M$72*tk_he_vr200) -> 11.555941
A74: 新增 MW 加權營運費用（IF_OpexGW） | B74: US$m/MW-年 | F74: =cust_sh*tk_ox_gb300+(1-cust_sh)*((1-Thesis!$F$72)*tk_ox_gb300+Thesis!$F$72*tk_ox_vr200) -> 1.9826348 | G74: =cust_sh*tk_ox_gb300+(1-cust_sh)*((1-Thesis!$G$72)*tk_ox_gb300+Thesis!$G$72*tk_ox_vr200) -> 1.9826348 | H74: =cust_sh*tk_ox_gb300+(1-cust_sh)*((1-Thesis!$H$72)*tk_ox_gb300+Thesis!$H$72*tk_ox_vr200) -> 2.01035 | I74: =cust_sh*tk_ox_gb300+(1-cust_sh)*((1-Thesis!$I$72)*tk_ox_gb300+Thesis!$I$72*tk_ox_vr200) -> 2.0380652 | J74: =cust_sh*tk_ox_gb300+(1-cust_sh)*((1-Thesis!$J$72)*tk_ox_gb300+Thesis!$J$72*tk_ox_vr200) -> 2.0380652 | K74: =cust_sh*tk_ox_gb300+(1-cust_sh)*((1-Thesis!$K$72)*tk_ox_gb300+Thesis!$K$72*tk_ox_vr200) -> 2.0380652 | L74: =cust_sh*tk_ox_gb300+(1-cust_sh)*((1-Thesis!$L$72)*tk_ox_gb300+Thesis!$L$72*tk_ox_vr200) -> 2.0380652 | M74: =cust_sh*tk_ox_gb300+(1-cust_sh)*((1-Thesis!$M$72)*tk_ox_gb300+Thesis!$M$72*tk_ox_vr200) -> 2.0380652
A75: 新增 MW 加權 IT 資本支出（IF_CapexIT；含自研晶片資本支出係數） | B75: US$m/MW | F75: =cust_sh*tk_cx_gb300*cf_cx+(1-cust_sh)*((1-Thesis!$F$72)*tk_cx_gb300+Thesis!$F$72*tk_cx_vr200) -> 32.237224 | G75: =cust_sh*tk_cx_gb300*cf_cx+(1-cust_sh)*((1-Thesis!$G$72)*tk_cx_gb300+Thesis!$G$72*tk_cx_vr200) -> 32.237224 | H75: =cust_sh*tk_cx_gb300*cf_cx+(1-cust_sh)*((1-Thesis!$H$72)*tk_cx_gb300+Thesis!$H$72*tk_cx_vr200) -> 33.574506 | I75: =cust_sh*tk_cx_gb300*cf_cx+(1-cust_sh)*((1-Thesis!$I$72)*tk_cx_gb300+Thesis!$I$72*tk_cx_vr200) -> 34.911788 | J75: =cust_sh*tk_cx_gb300*cf_cx+(1-cust_sh)*((1-Thesis!$J$72)*tk_cx_gb300+Thesis!$J$72*tk_cx_vr200) -> 34.911788 | K75: =cust_sh*tk_cx_gb300*cf_cx+(1-cust_sh)*((1-Thesis!$K$72)*tk_cx_gb300+Thesis!$K$72*tk_cx_vr200) -> 34.911788 | L75: =cust_sh*tk_cx_gb300*cf_cx+(1-cust_sh)*((1-Thesis!$L$72)*tk_cx_gb300+Thesis!$L$72*tk_cx_vr200) -> 34.911788 | M75: =cust_sh*tk_cx_gb300*cf_cx+(1-cust_sh)*((1-Thesis!$M$72)*tk_cx_gb300+Thesis!$M$72*tk_cx_vr200) -> 34.911788
A76: 期初後新增對外 MW 累計（期末） | B76: MW | F76: =Thesis!$F$66-mw_open -> 1817.15 | G76: =Thesis!$F$76 -> 1817.15 | H76: =Thesis!$H$66-mw_open -> 5451.45 | I76: =Thesis!$I$66-mw_open -> 9085.75 | J76: =Thesis!$J$66-mw_open -> 12720.05 | K76: =Thesis!$K$66-mw_open -> 15290.917 | L76: =Thesis!$L$66-mw_open -> 16798.352 | M76: =Thesis!$M$66-mw_open -> 17242.353
A77: Σ 新增 MW × HoldEcon | B77: US$m | F77: =Thesis!$F$69*Thesis!$F$73 -> 19782.242 | G77: =Thesis!$F$77 -> 19782.242 | H77: =Thesis!$G$77+Thesis!$H$69*Thesis!$H$73 -> 60563.362 | I77: =Thesis!$H$77+Thesis!$I$69*Thesis!$I$73 -> 102561.12 | J77: =Thesis!$I$77+Thesis!$J$69*Thesis!$J$73 -> 144558.87 | K77: =Thesis!$J$77+Thesis!$K$69*Thesis!$K$73 -> 174267.66 | L77: =Thesis!$K$77+Thesis!$L$69*Thesis!$L$73 -> 191687.49 | M77: =Thesis!$L$77+Thesis!$M$69*Thesis!$M$73 -> 196818.34
A78: Σ 新增 MW × 營運費用 | B78: US$m | F78: =Thesis!$F$69*Thesis!$F$74 -> 3602.7449 | G78: =Thesis!$F$78 -> 3602.7449 | H78: =Thesis!$G$78+Thesis!$H$69*Thesis!$H$74 -> 10908.96 | I78: =Thesis!$H$78+Thesis!$I$69*Thesis!$I$74 -> 18315.9 | J78: =Thesis!$I$78+Thesis!$J$69*Thesis!$J$74 -> 25722.84 | K78: =Thesis!$J$78+Thesis!$K$69*Thesis!$K$74 -> 30962.435 | L78: =Thesis!$K$78+Thesis!$L$69*Thesis!$L$74 -> 34034.685 | M78: =Thesis!$L$78+Thesis!$M$69*Thesis!$M$74 -> 34939.589
A79: 新增機隊加權 HoldEcon | B79: US$m/MW-年 | F79: =IF(Thesis!$F$76>0,Thesis!$F$77/Thesis!$F$76,Thesis!$F$73) -> 10.886411 | G79: =IF(Thesis!$G$76>0,Thesis!$G$77/Thesis!$G$76,Thesis!$G$73) -> 10.886411 | H79: =IF(Thesis!$H$76>0,Thesis!$H$77/Thesis!$H$76,Thesis!$H$73) -> 11.109588 | I79: =IF(Thesis!$I$76>0,Thesis!$I$77/Thesis!$I$76,Thesis!$I$73) -> 11.288129 | J79: =IF(Thesis!$J$76>0,Thesis!$J$77/Thesis!$J$76,Thesis!$J$73) -> 11.364647 | K79: =IF(Thesis!$K$76>0,Thesis!$K$77/Thesis!$K$76,Thesis!$K$73) -> 11.396809 | L79: =IF(Thesis!$L$76>0,Thesis!$L$77/Thesis!$L$76,Thesis!$L$73) -> 11.411089 | M79: =IF(Thesis!$M$76>0,Thesis!$M$77/Thesis!$M$76,Thesis!$M$73) -> 11.414819
A80: 新增機隊加權營運費用 | B80: US$m/MW-年 | F80: =IF(Thesis!$F$76>0,Thesis!$F$78/Thesis!$F$76,Thesis!$F$74) -> 1.9826348 | G80: =IF(Thesis!$G$76>0,Thesis!$G$78/Thesis!$G$76,Thesis!$G$74) -> 1.9826348 | H80: =IF(Thesis!$H$76>0,Thesis!$H$78/Thesis!$H$76,Thesis!$H$74) -> 2.0011116 | I80: =IF(Thesis!$I$76>0,Thesis!$I$78/Thesis!$I$76,Thesis!$I$74) -> 2.015893 | J80: =IF(Thesis!$J$76>0,Thesis!$J$78/Thesis!$J$76,Thesis!$J$74) -> 2.0222279 | K80: =IF(Thesis!$K$76>0,Thesis!$K$78/Thesis!$K$76,Thesis!$K$74) -> 2.0248907 | L80: =IF(Thesis!$L$76>0,Thesis!$L$78/Thesis!$L$76,Thesis!$L$74) -> 2.0260729 | M80: =IF(Thesis!$M$76>0,Thesis!$M$78/Thesis!$M$76,Thesis!$M$74) -> 2.0263817
A81: 新增產能每 MW 年收入＝新增機隊 HoldEcon × 情境 k | B81: US$m/MW-年 | F81: =Thesis!$F$79*k_B -> 10.798765 | G81: =Thesis!$G$79*k_B -> 10.798765 | H81: =Thesis!$H$79*k_B -> 11.020144 | I81: =Thesis!$I$79*k_B -> 11.197248 | J81: =Thesis!$J$79*k_B -> 11.27315 | K81: =Thesis!$K$79*k_B -> 11.305053 | L81: =Thesis!$L$79*k_B -> 11.319219 | M81: =Thesis!$M$79*k_B -> 11.322919 | P81: 期初機隊 2,080 MW 三情境同用 rpm_open（k_B）；情境 k 只用於新產能
A82: 新增產能平均在役 MW（期間） | B82: MW | F82: =Thesis!$F$76/2 -> 908.575 | H82: =(Thesis!$G$76+Thesis!$H$76)/2 -> 3634.3 | I82: =(Thesis!$H$76+Thesis!$I$76)/2 -> 7268.6 | J82: =(Thesis!$I$76+Thesis!$J$76)/2 -> 10902.9 | K82: =(Thesis!$J$76+Thesis!$K$76)/2 -> 14005.484 | L82: =(Thesis!$K$76+Thesis!$L$76)/2 -> 16044.634 | M82: =(Thesis!$L$76+Thesis!$M$76)/2 -> 17020.352
A83: 3. AWS AI 損益（收入端不乘 IF_Util：MW-year 計價）
A84: AWS AI 營收（命題子列） | B84: US$bn | C84: =Thesis!$C$67*rpm_open*Thesis!$C$68/1000 -> 2.3210054 | D84: =Thesis!$D$67*rpm_open*Thesis!$D$68/1000 -> 8.7037701 | E84: =Thesis!$E$67*rpm_open*Thesis!$E$68/1000 -> 8.510353 | F84: =(mw_open*rpm_open+Thesis!$F$82*Thesis!$F$81)*Thesis!$F$68/1000 -> 14.963434 | G84: =Thesis!$E$84+Thesis!$F$84 -> 23.473787 | H84: =(mw_open*rpm_open+Thesis!$H$82*Thesis!$H$81)/1000 -> 60.165891 | I84: =(mw_open*rpm_open+Thesis!$I$82*Thesis!$I$81)/1000 -> 101.5037 | J84: =(mw_open*rpm_open+Thesis!$J$82*Thesis!$J$81)/1000 -> 143.02541 | K84: =(mw_open*rpm_open+Thesis!$K$82*Thesis!$K$81)/1000 -> 178.44812 | L84: =(mw_open*rpm_open+Thesis!$L$82*Thesis!$L$81)/1000 -> 201.7281 | M84: =(mw_open*rpm_open+Thesis!$M$82*Thesis!$M$81)/1000 -> 212.83544 | N84: =Thesis!$N$67*rpm_open*Thesis!$N$68/1000 -> 3.0463195 | O84: =Thesis!$O$67*rpm_open*Thesis!$O$68/1000 -> 5.6574506 | P84: 實績欄為分拆估計（期初 k，Derived），不是公司揭露值
A85: 全機隊每 MW 年收入 | B85: US$m/MW-年 | C85: =Thesis!$C$84*1000/(Thesis!$C$67*Thesis!$C$68) -> 9.6708557 | D85: =Thesis!$D$84*1000/(Thesis!$D$67*Thesis!$D$68) -> 9.6708557 | E85: =Thesis!$E$84*1000/(Thesis!$E$67*Thesis!$E$68) -> 9.6708557 | F85: =Thesis!$F$84*1000/(Thesis!$F$67*Thesis!$F$68) -> 10.013758 | G85: =Thesis!$G$84*1000/(Thesis!$G$67*Thesis!$G$68) -> 9.8866656 | H85: =Thesis!$H$84*1000/(Thesis!$H$67*Thesis!$H$68) -> 10.529005 | I85: =Thesis!$I$84*1000/(Thesis!$I$67*Thesis!$I$68) -> 10.857636 | J85: =Thesis!$J$84*1000/(Thesis!$J$67*Thesis!$J$68) -> 11.016445 | K85: =Thesis!$K$84*1000/(Thesis!$K$67*Thesis!$K$68) -> 11.093737 | L85: =Thesis!$L$84*1000/(Thesis!$L$67*Thesis!$L$68) -> 11.130051 | M85: =Thesis!$M$84*1000/(Thesis!$M$67*Thesis!$M$68) -> 11.143011 | N85: =Thesis!$N$84*1000/(Thesis!$N$67*Thesis!$N$68) -> 9.6708557 | O85: =Thesis!$O$84*1000/(Thesis!$O$67*Thesis!$O$68) -> 9.6708557
A86: AI 營運成本（含自用 MW、租用機房租金 C22） | B86: US$bn | C86: =Thesis!$C$67/ext_sh*(ox_open+rent_mw)*Thesis!$C$68/1000 -> 0.64256921 | D86: =Thesis!$D$67/ext_sh*(ox_open+rent_mw)*Thesis!$D$68/1000 -> 2.4096345 | E86: =Thesis!$E$67/ext_sh*(ox_open+rent_mw)*Thesis!$E$68/1000 -> 2.3560871 | F86: =((mw_open*ox_open+Thesis!$F$82*Thesis!$F$80)/ext_sh+Thesis!$F$67/ext_sh*rent_mw)*Thesis!$F$68/1000 -> 4.0542199 | G86: =Thesis!$E$86+Thesis!$F$86 -> 6.410307 | H86: =((mw_open*ox_open+Thesis!$H$82*Thesis!$H$80)/ext_sh+Thesis!$H$67/ext_sh*rent_mw)*Thesis!$H$68/1000 -> 15.810898 | I86: =((mw_open*ox_open+Thesis!$I$82*Thesis!$I$80)/ext_sh+Thesis!$I$67/ext_sh*rent_mw)*Thesis!$I$68/1000 -> 26.187162 | J86: =((mw_open*ox_open+Thesis!$J$82*Thesis!$J$80)/ext_sh+Thesis!$J$67/ext_sh*rent_mw)*Thesis!$J$68/1000 -> 36.582613 | K86: =((mw_open*ox_open+Thesis!$K$82*Thesis!$K$80)/ext_sh+Thesis!$K$67/ext_sh*rent_mw)*Thesis!$K$68/1000 -> 45.454636 | L86: =((mw_open*ox_open+Thesis!$L$82*Thesis!$L$80)/ext_sh+Thesis!$L$67/ext_sh*rent_mw)*Thesis!$L$68/1000 -> 51.28557 | M86: =((mw_open*ox_open+Thesis!$M$82*Thesis!$M$80)/ext_sh+Thesis!$M$67/ext_sh*rent_mw)*Thesis!$M$68/1000 -> 54.072293 | N86: =Thesis!$N$67/ext_sh*(ox_open+rent_mw)*Thesis!$N$68/1000 -> 0.84337209 | O86: =Thesis!$O$67/ext_sh*(ox_open+rent_mw)*Thesis!$O$68/1000 -> 1.5662625
A87: AWS 營收（實績，Q 頁） | B87: US$bn | C87: =Q!$D$7 -> 107.556 | D87: =Q!$E$7 -> 128.725 | E87: =Q!$P$7 -> 79.819 | N87: =Q!$N$7 -> 60.14 | O87: =Q!$O$7 -> 68.585
A88: AWS 其他營收（非 AI 雲端） | B88: US$bn | C88: =Thesis!$C$87-Thesis!$C$84 -> 105.23499 | D88: =Thesis!$D$87-Thesis!$D$84 -> 120.02123 | E88: =Thesis!$E$87-Thesis!$E$84 -> 71.308647 | F88: =Thesis!$O$88*(1+Thesis!$F$89) -> 71.7693 | G88: =Thesis!$E$88+Thesis!$F$88 -> 143.07795 | H88: =Thesis!$G$88*(1+Thesis!$H$89) -> 161.01708 | I88: =Thesis!$H$88*(1+Thesis!$I$89) -> 178.76976 | J88: =Thesis!$I$88*(1+Thesis!$J$89) -> 195.77554 | K88: =Thesis!$J$88*(1+Thesis!$K$89) -> 211.43758 | L88: =Thesis!$K$88*(1+Thesis!$L$89) -> 228.35259 | M88: =Thesis!$L$88*(1+Thesis!$M$89) -> 246.62079 | N88: =Thesis!$N$87-Thesis!$N$84 -> 57.09368 | O88: =Thesis!$O$87-Thesis!$O$84 -> 62.927549 | P88: 實績＝AWS 實績 − AWS AI 分拆估計（殘差，Derived）
A89: AWS 其他年增 | B89: % | D89: =Thesis!$D$88/Thesis!$C$88-1 -> 0.14050683 | E89: =Thesis!$E$88/Thesis!$N$88-1 -> 0.24897618 | F89: =Thesis!$D$89 -> 0.14050683 | G89: =Thesis!$G$88/Thesis!$D$88-1 -> 0.19210532 | H89: =Thesis!$F$89+(g_awso_lt-Thesis!$F$89)*1/4 -> 0.12538012 | I89: =Thesis!$F$89+(g_awso_lt-Thesis!$F$89)*2/4 -> 0.11025341 | J89: =Thesis!$F$89+(g_awso_lt-Thesis!$F$89)*3/4 -> 0.095126707 | K89: =Thesis!$F$89+(g_awso_lt-Thesis!$F$89)*4/4 -> 0.08 | L89: =g_awso_lt -> 0.08 | M89: =g_awso_lt -> 0.08 | P89: 起點＝FY2025 年增（D 欄，Derived）；1H26 年增（E 欄）受 AI 分拆低估影響偏高，只列不用；收斂到 g_awso_lt
A90: 4. AI 資本支出（現金）→ 折舊（IT 6 年、機房 20 年；次年起提列）
A91: 2H26 非 AI 資本支出（零售＋AWS 其他） | B91: US$bn | F91: =cx_rt*Seg!$F$55+cx_awso*Thesis!$F$88 -> 34.97345
A92: AI 資本支出中 IT 比例 | B92: % | C92: =tk_cx_h100/(tk_cx_h100+tk_fac*(1-colo_sh)) -> 0.73075646 | D92: =tk_cx_h100/(tk_cx_h100+tk_fac*(1-colo_sh)) -> 0.73075646 | E92: =Thesis!$F$92 -> 0.76079233 | F92: =Thesis!$F$75/(Thesis!$F$75+tk_fac*(1-colo_sh)) -> 0.76079233 | G92: =Thesis!$G$75/(Thesis!$G$75+tk_fac*(1-colo_sh)) -> 0.76079233 | H92: =Thesis!$H$75/(Thesis!$H$75+tk_fac*(1-colo_sh)) -> 0.76811067 | I92: =Thesis!$I$75/(Thesis!$I$75+tk_fac*(1-colo_sh)) -> 0.7749945 | J92: =Thesis!$J$75/(Thesis!$J$75+tk_fac*(1-colo_sh)) -> 0.7749945 | K92: =Thesis!$K$75/(Thesis!$K$75+tk_fac*(1-colo_sh)) -> 0.7749945 | L92: =Thesis!$L$75/(Thesis!$L$75+tk_fac*(1-colo_sh)) -> 0.7749945 | M92: =Thesis!$M$75/(Thesis!$M$75+tk_fac*(1-colo_sh)) -> 0.7749945
A93: AI 資本支出（現金，含自用） | B93: US$bn | C93: =Q!$D$46-cx_rt*Q!$D$16-cx_awso*Thesis!$C$88 -> 25.278105 | D93: =Q!$E$46-cx_rt*Q!$E$16-cx_awso*Thesis!$D$88 -> 69.568632 | E93: =Q!$P$46-cx_rt*Q!$P$16-cx_awso*Thesis!$E$88 -> 64.189921 | F93: =MAX(Thesis!$F$70*(Thesis!$F$75+tk_fac*(1-colo_sh))/1000,capex_g26-Q!$P$46-Thesis!$F$91) -> 96.24813 | G93: =Thesis!$E$93+Thesis!$F$93 -> 160.43805 | H93: =Thesis!$H$70*(Thesis!$H$75+tk_fac*(1-colo_sh))/1000+Thesis!$H$94 -> 198.57136 | I93: =Thesis!$I$70*(Thesis!$I$75+tk_fac*(1-colo_sh))/1000+Thesis!$I$94 -> 204.64647 | J93: =Thesis!$J$70*(Thesis!$J$75+tk_fac*(1-colo_sh))/1000+Thesis!$J$94 -> 209.88324 | K93: =Thesis!$K$70*(Thesis!$K$75+tk_fac*(1-colo_sh))/1000+Thesis!$K$94 -> 155.23839 | L93: =Thesis!$L$70*(Thesis!$L$75+tk_fac*(1-colo_sh))/1000+Thesis!$L$94 -> 132.01414 | M93: =Thesis!$M$70*(Thesis!$M$75+tk_fac*(1-colo_sh))/1000+Thesis!$M$94 -> 132.23098 | P93: 實績＝公司資本支出淨額 − 非 AI（零售 cx_rt、AWS 其他 cx_awso）；2H26＝MAX(MW 公式, 指引 220 − 上半年 − 非 AI)；之後＝新增 MW ×（IT＋自建機房）＋汰換 | R93: =Q!$C$46-cx_rt*Q!$C$16-cx_awso*(Q!$C$7-mw_ye23/2*rpm_open/1000) -> 1.5042998 | S93: =Thesis!$C$93 -> 25.278105 | T93: =Thesis!$D$93 -> 69.568632 | U93: =Thesis!$G$93 -> 160.43805 | V93: =Thesis!$H$93 -> 198.57136 | W93: =Thesis!$I$93 -> 204.64647 | X93: =Thesis!$J$93 -> 209.88324 | Y93: =Thesis!$K$93 -> 155.23839 | Z93: =Thesis!$L$93 -> 132.01414 | AA93: =Thesis!$M$93 -> 132.23098
A94: IT 汰換（折舊年限前新增的總 MW × 當年 IT 每 MW） | B94: US$bn | H94: =SUMPRODUCT(--(Thesis!$R$63:$AA$63=2027-tk_life),Thesis!$R$70:$AA$70)*Thesis!$H$75/1000 -> 0 | I94: =SUMPRODUCT(--(Thesis!$R$63:$AA$63=2028-tk_life),Thesis!$R$70:$AA$70)*Thesis!$I$75/1000 -> 0 | J94: =SUMPRODUCT(--(Thesis!$R$63:$AA$63=2029-tk_life),Thesis!$R$70:$AA$70)*Thesis!$J$75/1000 -> 5.2367682 | K94: =SUMPRODUCT(--(Thesis!$R$63:$AA$63=2030-tk_life),Thesis!$R$70:$AA$70)*Thesis!$K$75/1000 -> 10.473536 | L94: =SUMPRODUCT(--(Thesis!$R$63:$AA$63=2031-tk_life),Thesis!$R$70:$AA$70)*Thesis!$L$75/1000 -> 47.130914 | M94: =SUMPRODUCT(--(Thesis!$R$63:$AA$63=2032-tk_life),Thesis!$R$70:$AA$70)*Thesis!$M$75/1000 -> 107.22937
A95: 其中 IT 設備 | B95: US$bn | C95: =Thesis!$C$93*Thesis!$C$92 -> 18.472139 | D95: =Thesis!$D$93*Thesis!$D$92 -> 50.837727 | E95: =Thesis!$E$93*Thesis!$E$92 -> 48.8352 | F95: =Thesis!$F$93*Thesis!$F$92 -> 73.224839 | G95: =Thesis!$E$95+Thesis!$F$95 -> 122.06004 | H95: =(Thesis!$H$93-Thesis!$H$94)*Thesis!$H$92+Thesis!$H$94 -> 152.52478 | I95: =(Thesis!$I$93-Thesis!$I$94)*Thesis!$I$92+Thesis!$I$94 -> 158.59989 | J95: =(Thesis!$J$93-Thesis!$J$94)*Thesis!$J$92+Thesis!$J$94 -> 163.83666 | K95: =(Thesis!$K$93-Thesis!$K$94)*Thesis!$K$92+Thesis!$K$94 -> 122.6655 | L95: =(Thesis!$L$93-Thesis!$L$94)*Thesis!$L$92+Thesis!$L$94 -> 112.91495 | M95: =(Thesis!$M$93-Thesis!$M$94)*Thesis!$M$92+Thesis!$M$94 -> 126.60548 | R95: =Thesis!$R$93*Thesis!$C$92 -> 1.0992768 | S95: =Thesis!$C$95 -> 18.472139 | T95: =Thesis!$D$95 -> 50.837727 | U95: =Thesis!$G$95 -> 122.06004 | V95: =Thesis!$H$95 -> 152.52478 | W95: =Thesis!$I$95 -> 158.59989 | X95: =Thesis!$J$95 -> 163.83666 | Y95: =Thesis!$K$95 -> 122.6655 | Z95: =Thesis!$L$95 -> 112.91495 | AA95: =Thesis!$M$95 -> 126.60548
A96: 其中機房（自建部分） | B96: US$bn | C96: =Thesis!$C$93-Thesis!$C$95 -> 6.8059666 | D96: =Thesis!$D$93-Thesis!$D$95 -> 18.730905 | E96: =Thesis!$E$93-Thesis!$E$95 -> 15.354721 | F96: =Thesis!$F$93-Thesis!$F$95 -> 23.023291 | G96: =Thesis!$G$93-Thesis!$G$95 -> 38.378012 | H96: =Thesis!$H$93-Thesis!$H$95 -> 46.046581 | I96: =Thesis!$I$93-Thesis!$I$95 -> 46.046581 | J96: =Thesis!$J$93-Thesis!$J$95 -> 46.046581 | K96: =Thesis!$K$93-Thesis!$K$95 -> 32.572887 | L96: =Thesis!$L$93-Thesis!$L$95 -> 19.099193 | M96: =Thesis!$M$93-Thesis!$M$95 -> 5.625499 | R96: =Thesis!$R$93-Thesis!$R$95 -> 0.40502301 | S96: =Thesis!$S$93-Thesis!$S$95 -> 6.8059666 | T96: =Thesis!$T$93-Thesis!$T$95 -> 18.730905 | U96: =Thesis!$U$93-Thesis!$U$95 -> 38.378012 | V96: =Thesis!$V$93-Thesis!$V$95 -> 46.046581 | W96: =Thesis!$W$93-Thesis!$W$95 -> 46.046581 | X96: =Thesis!$X$93-Thesis!$X$95 -> 46.046581 | Y96: =Thesis!$Y$93-Thesis!$Y$95 -> 32.572887 | Z96: =Thesis!$Z$93-Thesis!$Z$95 -> 19.099193 | AA96: =Thesis!$AA$93-Thesis!$AA$95 -> 5.625499
A97: AI 資本支出占公司資本支出 | B97: % | C97: =Thesis!$C$93/CF!$C$55 -> 0.32550549 | D97: =Thesis!$D$93/CF!$D$55 -> 0.54214956 | E97: =Thesis!$E$93/CF!$E$55 -> 0.66649279 | F97: =Thesis!$F$93/CF!$F$55 -> 0.73347791 | G97: =Thesis!$G$93/CF!$G$55 -> 0.70512432 | H97: =Thesis!$H$93/CF!$H$55 -> 0.72637604 | I97: =Thesis!$I$93/CF!$I$55 -> 0.71309909 | J97: =Thesis!$J$93/CF!$J$55 -> 0.70120835 | K97: =Thesis!$K$93/CF!$K$55 -> 0.61833884 | L97: =Thesis!$L$93/CF!$L$55 -> 0.56248916 | M97: =Thesis!$M$93/CF!$M$55 -> 0.54575119
A98: AI IT 折舊 | B98: US$bn | C98: =Thesis!$S$98 -> 0.1832128 | D98: =Thesis!$T$98 -> 3.2619026 | E98: =Thesis!$G$98/2 -> 5.8674285 | F98: =Thesis!$G$98/2 -> 5.8674285 | G98: =Thesis!$U$98 -> 11.734857 | H98: =Thesis!$V$98 -> 32.078197 | I98: =Thesis!$W$98 -> 57.498994 | J98: =Thesis!$X$98 -> 83.932309 | K98: =Thesis!$Y$98 -> 111.05521 | L98: =Thesis!$Z$98 -> 128.42077 | M98: =Thesis!$AA$98 -> 138.76697 | N98: =Thesis!$D$98/2 -> 1.6309513 | O98: =Thesis!$D$98/2 -> 1.6309513 | R98: =SUMPRODUCT(--(Thesis!$R$63:$AA$63<Thesis!R$63),--(Thesis!$R$63:$AA$63>=Thesis!R$63-tk_life),Thesis!$R$95:$AA$95)/tk_life -> 0 | S98: =SUMPRODUCT(--(Thesis!$R$63:$AA$63<Thesis!S$63),--(Thesis!$R$63:$AA$63>=Thesis!S$63-tk_life),Thesis!$R$95:$AA$95)/tk_life -> 0.1832128 | T98: =SUMPRODUCT(--(Thesis!$R$63:$AA$63<Thesis!T$63),--(Thesis!$R$63:$AA$63>=Thesis!T$63-tk_life),Thesis!$R$95:$AA$95)/tk_life -> 3.2619026 | U98: =SUMPRODUCT(--(Thesis!$R$63:$AA$63<Thesis!U$63),--(Thesis!$R$63:$AA$63>=Thesis!U$63-tk_life),Thesis!$R$95:$AA$95)/tk_life -> 11.734857 | V98: =SUMPRODUCT(--(Thesis!$R$63:$AA$63<Thesis!V$63),--(Thesis!$R$63:$AA$63>=Thesis!V$63-tk_life),Thesis!$R$95:$AA$95)/tk_life -> 32.078197 | W98: =SUMPRODUCT(--(Thesis!$R$63:$AA$63<Thesis!W$63),--(Thesis!$R$63:$AA$63>=Thesis!W$63-tk_life),Thesis!$R$95:$AA$95)/tk_life -> 57.498994 | X98: =SUMPRODUCT(--(Thesis!$R$63:$AA$63<Thesis!X$63),--(Thesis!$R$63:$AA$63>=Thesis!X$63-tk_life),Thesis!$R$95:$AA$95)/tk_life -> 83.932309 | Y98: =SUMPRODUCT(--(Thesis!$R$63:$AA$63<Thesis!Y$63),--(Thesis!$R$63:$AA$63>=Thesis!Y$63-tk_life),Thesis!$R$95:$AA$95)/tk_life -> 111.05521 | ... AA98: =SUMPRODUCT(--(Thesis!$R$63:$AA$63<Thesis!AA$63),--(Thesis!$R$63:$AA$63>=Thesis!AA$63-tk_life),Thesis!$R$95:$AA$95)/tk_life -> 138.76697
A99: AI 機房折舊 | B99: US$bn | C99: =Thesis!$S$99 -> 0.02025115 | D99: =Thesis!$T$99 -> 0.36054948 | E99: =Thesis!$G$99/2 -> 0.64854736 | F99: =Thesis!$G$99/2 -> 0.64854736 | G99: =Thesis!$U$99 -> 1.2970947 | H99: =Thesis!$V$99 -> 3.2159953 | I99: =Thesis!$W$99 -> 5.5183243 | J99: =Thesis!$X$99 -> 7.8206534 | K99: =Thesis!$Y$99 -> 10.122982 | L99: =Thesis!$Z$99 -> 11.751627 | M99: =Thesis!$AA$99 -> 12.706586 | N99: =Thesis!$D$99/2 -> 0.18027474 | O99: =Thesis!$D$99/2 -> 0.18027474 | R99: =SUMPRODUCT(--(Thesis!$R$63:$AA$63<Thesis!R$63),Thesis!$R$96:$AA$96)/fac_life -> 0 | S99: =SUMPRODUCT(--(Thesis!$R$63:$AA$63<Thesis!S$63),Thesis!$R$96:$AA$96)/fac_life -> 0.02025115 | T99: =SUMPRODUCT(--(Thesis!$R$63:$AA$63<Thesis!T$63),Thesis!$R$96:$AA$96)/fac_life -> 0.36054948 | U99: =SUMPRODUCT(--(Thesis!$R$63:$AA$63<Thesis!U$63),Thesis!$R$96:$AA$96)/fac_life -> 1.2970947 | V99: =SUMPRODUCT(--(Thesis!$R$63:$AA$63<Thesis!V$63),Thesis!$R$96:$AA$96)/fac_life -> 3.2159953 | W99: =SUMPRODUCT(--(Thesis!$R$63:$AA$63<Thesis!W$63),Thesis!$R$96:$AA$96)/fac_life -> 5.5183243 | X99: =SUMPRODUCT(--(Thesis!$R$63:$AA$63<Thesis!X$63),Thesis!$R$96:$AA$96)/fac_life -> 7.8206534 | Y99: =SUMPRODUCT(--(Thesis!$R$63:$AA$63<Thesis!Y$63),Thesis!$R$96:$AA$96)/fac_life -> 10.122982 | ... AA99: =SUMPRODUCT(--(Thesis!$R$63:$AA$63<Thesis!AA$63),Thesis!$R$96:$AA$96)/fac_life -> 12.706586
A100: AI 折舊合計（對外 → AWS；自用 → 零售分部） | B100: US$bn | C100: =Thesis!$C$98+Thesis!$C$99 -> 0.20346395 | D100: =Thesis!$D$98+Thesis!$D$99 -> 3.6224521 | E100: =Thesis!$E$98+Thesis!$E$99 -> 6.5159759 | F100: =Thesis!$F$98+Thesis!$F$99 -> 6.5159759 | G100: =Thesis!$G$98+Thesis!$G$99 -> 13.031952 | H100: =Thesis!$H$98+Thesis!$H$99 -> 35.294192 | I100: =Thesis!$I$98+Thesis!$I$99 -> 63.017319 | J100: =Thesis!$J$98+Thesis!$J$99 -> 91.752962 | K100: =Thesis!$K$98+Thesis!$K$99 -> 121.17819 | L100: =Thesis!$L$98+Thesis!$L$99 -> 140.17239 | M100: =Thesis!$M$98+Thesis!$M$99 -> 151.47356 | N100: =Thesis!$N$98+Thesis!$N$99 -> 1.811226 | O100: =Thesis!$O$98+Thesis!$O$99 -> 1.811226 | R100: =Thesis!$R$98+Thesis!$R$99 -> 0 | S100: =Thesis!$S$98+Thesis!$S$99 -> 0.20346395 | T100: =Thesis!$T$98+Thesis!$T$99 -> 3.6224521 | U100: =Thesis!$U$98+Thesis!$U$99 -> 13.031952 | V100: =Thesis!$V$98+Thesis!$V$99 -> 35.294192 | W100: =Thesis!$W$98+Thesis!$W$99 -> 63.017319 | X100: =Thesis!$X$98+Thesis!$X$99 -> 91.752962 | Y100: =Thesis!$Y$98+Thesis!$Y$99 -> 121.17819 | Z100: =Thesis!$Z$98+Thesis!$Z$99 -> 140.17239 | AA100: =Thesis!$AA$98+Thesis!$AA$99 -> 151.47356
A101: AI 淨 PP&E（期末） | B101: US$bn | C101: =Thesis!$S$101 -> 26.578941 | D101: =Thesis!$T$101 -> 92.525121 | G101: =Thesis!$U$101 -> 239.93122 | H101: =Thesis!$V$101 -> 403.20839 | I101: =Thesis!$W$101 -> 544.83754 | J101: =Thesis!$X$101 -> 662.96782 | K101: =Thesis!$Y$101 -> 697.02802 | L101: =Thesis!$Z$101 -> 688.86977 | M101: =Thesis!$AA$101 -> 669.62719 | R101: =SUM(Thesis!$R$93:$R$93)-SUM(Thesis!$R$100:$R$100) -> 1.5042998 | S101: =SUM(Thesis!$R$93:$S$93)-SUM(Thesis!$R$100:$S$100) -> 26.578941 | T101: =SUM(Thesis!$R$93:$T$93)-SUM(Thesis!$R$100:$T$100) -> 92.525121 | U101: =SUM(Thesis!$R$93:$U$93)-SUM(Thesis!$R$100:$U$100) -> 239.93122 | V101: =SUM(Thesis!$R$93:$V$93)-SUM(Thesis!$R$100:$V$100) -> 403.20839 | W101: =SUM(Thesis!$R$93:$W$93)-SUM(Thesis!$R$100:$W$100) -> 544.83754 | X101: =SUM(Thesis!$R$93:$X$93)-SUM(Thesis!$R$100:$X$100) -> 662.96782 | Y101: =SUM(Thesis!$R$93:$Y$93)-SUM(Thesis!$R$100:$Y$100) -> 697.02802 | Z101: =SUM(Thesis!$R$93:$Z$93)-SUM(Thesis!$R$100:$Z$100) -> 688.86977 | AA101: =SUM(Thesis!$R$93:$AA$93)-SUM(Thesis!$R$100:$AA$100) -> 669.62719
A102: 5. AWS AI 營業利益、自用 AI 成本、AWS 其他
A103: AWS AI EBITDA＝營收 − 對外比例 × 營運成本 | B103: US$bn | C103: =Thesis!$C$84-ext_sh*Thesis!$C$86 -> 1.80695 | D103: =Thesis!$D$84-ext_sh*Thesis!$D$86 -> 6.7760625 | E103: =Thesis!$E$84-ext_sh*Thesis!$E$86 -> 6.6254833 | F103: =Thesis!$F$84-ext_sh*Thesis!$F$86 -> 11.720058 | G103: =Thesis!$G$84-ext_sh*Thesis!$G$86 -> 18.345541 | H103: =Thesis!$H$84-ext_sh*Thesis!$H$86 -> 47.517173 | I103: =Thesis!$I$84-ext_sh*Thesis!$I$86 -> 80.553969 | J103: =Thesis!$J$84-ext_sh*Thesis!$J$86 -> 113.75932 | K103: =Thesis!$K$84-ext_sh*Thesis!$K$86 -> 142.08441 | L103: =Thesis!$L$84-ext_sh*Thesis!$L$86 -> 160.69965 | M103: =Thesis!$M$84-ext_sh*Thesis!$M$86 -> 169.57761 | N103: =Thesis!$N$84-ext_sh*Thesis!$N$86 -> 2.3716219 | O103: =Thesis!$O$84-ext_sh*Thesis!$O$86 -> 4.4044406
...

Sheet Seg
A1: Seg — 營收分部層：官方分部 North America、International、AWS；10-K 營收線 Online stores、Physical stores、Third-party seller services、Advertising services、Subscription services、Other（零售各線合計＝北美＋國際）與 AWS。AWS＝AWS AI（命題子列，Thesis）＋AWS 其他。核對列（綠底）每情境每年度皆須為 0
A4: Seg｜情境 A（樂觀）：營收分部層（官方分部 North America、International、AWS；10-K 營收線）
A5: 項目 | B5: 單位 | C5: FY2024A | D5: FY2025A | E5: 1H26A | F5: 2H26E | G5: FY2026E（1H 實績＋2H 模型） | H5: FY2027E | I5: FY2028E | J5: FY2029E | K5: FY2030E | L5: FY2031E | M5: FY2032E | N5: 1H25A | O5: 2H25A | P5: 說明 | R5: 2023 | S5: 2024 | T5: 2025 | U5: 2026 | V5: 2027 | W5: 2028 | X5: 2029 | Y5: 2030 | Z5: 2031 | AA5: 2032
A6: 1. 零售各營收線（2H26＝2H25 ×（1＋2H25 年增）× 校準係數；2027–2030 年增由 2H25 年增線性收斂到長期值；2031–2032＝長期值）
A7: Online stores | B7: US$bn | C7: =Q!$D$10 -> 247.029 | D7: =Q!$E$10 -> 269.287 | E7: =Q!$P$10 -> 134.686 | F7: =Seg!$O$7*(1+Seg!$F$8)*Seg!$F$19 -> 157.02081 | G7: =Seg!$E$7+Seg!$F$7 -> 291.70681 | H7: =Seg!$G$7*(1+Seg!$H$8) -> 316.80195 | I7: =Seg!$H$7*(1+Seg!$I$8) -> 340.25135 | J7: =Seg!$I$7*(1+Seg!$J$8) -> 361.35019 | K7: =Seg!$J$7*(1+Seg!$K$8) -> 379.4177 | L7: =Seg!$K$7*(1+Seg!$L$8) -> 398.38858 | M7: =Seg!$L$7*(1+Seg!$M$8) -> 418.30801 | N7: =Q!$N$10 -> 118.892 | O7: =Q!$O$10 -> 150.395 | P7: Q 頁實績；預測＝前期 ×（1＋年增）
A8: Online stores 年增 | B8: % | E8: =Seg!$E$7/Seg!$N$7-1 -> 0.13284325 | F8: =Seg!$O$7/(Q!$F$10+Q!$G$10)-1 -> 0.098038214 | G8: =Seg!$G$7/Seg!$D$7-1 -> 0.083256184 | H8: =Seg!$F$8+(g_os-Seg!$F$8)*1/4 -> 0.08602866 | I8: =Seg!$F$8+(g_os-Seg!$F$8)*2/4 -> 0.074019107 | J8: =Seg!$F$8+(g_os-Seg!$F$8)*3/4 -> 0.062009553 | K8: =Seg!$F$8+(g_os-Seg!$F$8)*4/4 -> 0.05 | L8: =g_os -> 0.05 | M8: =g_os -> 0.05 | P8: E＝1H26 對 1H25（含 Prime Day 移入 Q2）；F＝2H25 對 2H24（2H26 成長基準，Derived）；收斂到 In 頁 g_os
A9: Physical stores | B9: US$bn | C9: =Q!$D$11 -> 21.215 | D9: =Q!$E$11 -> 22.561 | E9: =Q!$P$11 -> 11.579 | F9: =Seg!$O$9*(1+Seg!$F$10)*Seg!$F$19 -> 11.500629 | G9: =Seg!$E$9+Seg!$F$9 -> 23.079629 | H9: =Seg!$G$9*(1+Seg!$H$10) -> 24.2554 | I9: =Seg!$H$9*(1+Seg!$I$10) -> 25.321733 | J9: =Seg!$I$9*(1+Seg!$J$10) -> 26.258165 | K9: =Seg!$J$9*(1+Seg!$K$10) -> 27.04591 | L9: =Seg!$K$9*(1+Seg!$L$10) -> 27.857287 | M9: =Seg!$L$9*(1+Seg!$M$10) -> 28.693005 | N9: =Q!$N$11 -> 11.128 | O9: =Q!$O$11 -> 11.433 | P9: Q 頁實績；預測＝前期 ×（1＋年增）
A10: Physical stores 年增 | B10: % | E10: =Seg!$E$9/Seg!$N$9-1 -> 0.040528397 | F10: =Seg!$O$9/(Q!$F$11+Q!$G$11)-1 -> 0.057925419 | G10: =Seg!$G$9/Seg!$D$9-1 -> 0.022987875 | H10: =Seg!$F$10+(g_ps-Seg!$F$10)*1/4 -> 0.050944064 | I10: =Seg!$F$10+(g_ps-Seg!$F$10)*2/4 -> 0.043962709 | J10: =Seg!$F$10+(g_ps-Seg!$F$10)*3/4 -> 0.036981355 | K10: =Seg!$F$10+(g_ps-Seg!$F$10)*4/4 -> 0.03 | L10: =g_ps -> 0.03 | M10: =g_ps -> 0.03 | P10: E＝1H26 對 1H25（含 Prime Day 移入 Q2）；F＝2H25 對 2H24（2H26 成長基準，Derived）；收斂到 In 頁 g_ps
A11: Third-party seller services | B11: US$bn | C11: =Q!$D$12 -> 156.146 | D11: =Q!$E$12 -> 172.162 | E11: =Q!$P$12 -> 88.358 | F11: =Seg!$O$11*(1+Seg!$F$12)*Seg!$F$19 -> 101.18402 | G11: =Seg!$E$11+Seg!$F$11 -> 189.54202 | H11: =Seg!$G$11*(1+Seg!$H$12) -> 209.43664 | I11: =Seg!$H$11*(1+Seg!$I$12) -> 228.97868 | J11: =Seg!$I$11*(1+Seg!$J$12) -> 247.67566 | K11: =Seg!$J$11*(1+Seg!$K$12) -> 265.01296 | L11: =Seg!$K$11*(1+Seg!$L$12) -> 283.56387 | M11: =Seg!$L$11*(1+Seg!$M$12) -> 303.41334 | N11: =Q!$N$12 -> 76.86 | O11: =Q!$O$12 -> 95.302 | P11: Q 頁實績；預測＝前期 ×（1＋年增）
A12: Third-party seller services 年增 | B12: % | E12: =Seg!$E$11/Seg!$N$11-1 -> 0.14959667 | F12: =Seg!$O$11/(Q!$F$12+Q!$G$12)-1 -> 0.11661531 | G12: =Seg!$G$11/Seg!$D$11-1 -> 0.10095157 | H12: =Seg!$F$12+(g_sp-Seg!$F$12)*1/4 -> 0.10496148 | I12: =Seg!$F$12+(g_sp-Seg!$F$12)*2/4 -> 0.093307654 | J12: =Seg!$F$12+(g_sp-Seg!$F$12)*3/4 -> 0.081653827 | K12: =Seg!$F$12+(g_sp-Seg!$F$12)*4/4 -> 0.07 | L12: =g_sp -> 0.07 | M12: =g_sp -> 0.07 | P12: E＝1H26 對 1H25（含 Prime Day 移入 Q2）；F＝2H25 對 2H24（2H26 成長基準，Derived）；收斂到 In 頁 g_sp
A13: Advertising services | B13: US$bn | C13: =Q!$D$13 -> 56.214 | D13: =Q!$E$13 -> 68.635 | E13: =Q!$P$13 -> 37.052 | F13: =Seg!$O$13*(1+Seg!$F$14)*Seg!$F$19 -> 45.786005 | G13: =Seg!$E$13+Seg!$F$13 -> 82.838005 | H13: =Seg!$G$13*(1+Seg!$H$14) -> 99.451258 | I13: =Seg!$H$13*(1+Seg!$I$14) -> 116.06301 | J13: =Seg!$I$13*(1+Seg!$J$14) -> 131.55939 | K13: =Seg!$J$13*(1+Seg!$K$14) -> 144.71533 | L13: =Seg!$K$13*(1+Seg!$L$14) -> 159.18687 | M13: =Seg!$L$13*(1+Seg!$M$14) -> 175.10555 | N13: =Q!$N$13 -> 29.615 | O13: =Q!$O$13 -> 39.02 | P13: Q 頁實績；預測＝前期 ×（1＋年增）
A14: Advertising services 年增 | B14: % | E14: =Seg!$E$13/Seg!$N$13-1 -> 0.25112274 | F14: =Seg!$O$13/(Q!$F$13+Q!$G$13)-1 -> 0.23406812 | G14: =Seg!$G$13/Seg!$D$13-1 -> 0.20693532 | H14: =Seg!$F$14+(g_ad-Seg!$F$14)*1/4 -> 0.20055109 | I14: =Seg!$F$14+(g_ad-Seg!$F$14)*2/4 -> 0.16703406 | J14: =Seg!$F$14+(g_ad-Seg!$F$14)*3/4 -> 0.13351703 | K14: =Seg!$F$14+(g_ad-Seg!$F$14)*4/4 -> 0.1 | L14: =g_ad -> 0.1 | M14: =g_ad -> 0.1 | P14: E＝1H26 對 1H25（含 Prime Day 移入 Q2）；F＝2H25 對 2H24（2H26 成長基準，Derived）；收斂到 In 頁 g_ad
A15: Subscription services | B15: US$bn | C15: =Q!$D$14 -> 44.374 | D15: =Q!$E$14 -> 49.619 | E15: =Q!$P$14 -> 27.157 | F15: =Seg!$O$15*(1+Seg!$F$16)*Seg!$F$19 -> 27.553026 | G15: =Seg!$E$15+Seg!$F$15 -> 54.710026 | H15: =Seg!$G$15*(1+Seg!$H$16) -> 60.907715 | I15: =Seg!$H$15*(1+Seg!$I$16) -> 66.928747 | J15: =Seg!$I$15*(1+Seg!$J$16) -> 72.579374 | K15: =Seg!$J$15*(1+Seg!$K$16) -> 77.65993 | L15: =Seg!$K$15*(1+Seg!$L$16) -> 83.096125 | M15: =Seg!$L$15*(1+Seg!$M$16) -> 88.912854 | N15: =Q!$N$14 -> 23.923 | O15: =Q!$O$14 -> 25.696 | P15: Q 頁實績；預測＝前期 ×（1＋年增）
A16: Subscription services 年增 | B16: % | E16: =Seg!$E$15/Seg!$N$15-1 -> 0.13518371 | F16: =Seg!$O$15/(Q!$F$14+Q!$G$14)-1 -> 0.12771 | G16: =Seg!$G$15/Seg!$D$15-1 -> 0.10260236 | H16: =Seg!$F$16+(g_sub-Seg!$F$16)*1/4 -> 0.1132825 | I16: =Seg!$F$16+(g_sub-Seg!$F$16)*2/4 -> 0.098854999 | J16: =Seg!$F$16+(g_sub-Seg!$F$16)*3/4 -> 0.084427499 | K16: =Seg!$F$16+(g_sub-Seg!$F$16)*4/4 -> 0.07 | L16: =g_sub -> 0.07 | M16: =g_sub -> 0.07 | P16: E＝1H26 對 1H25（含 Prime Day 移入 Q2）；F＝2H25 對 2H24（2H26 成長基準，Derived）；收斂到 In 頁 g_sub
A17: Other | B17: US$bn | C17: =Q!$D$15 -> 5.425 | D17: =Q!$E$15 -> 5.935 | E17: =Q!$P$15 -> 3.474 | F17: =Seg!$O$17*(1+Seg!$F$18)*Seg!$F$19 -> 3.196549 | G17: =Seg!$E$17+Seg!$F$17 -> 6.670549 | H17: =Seg!$G$17*(1+Seg!$H$18) -> 7.1347933 | I17: =Seg!$H$17*(1+Seg!$I$18) -> 7.5847424 | J17: =Seg!$I$17*(1+Seg!$J$18) -> 8.0135233 | K17: =Seg!$J$17*(1+Seg!$K$18) -> 8.4141995 | L17: =Seg!$K$17*(1+Seg!$L$18) -> 8.8349095 | M17: =Seg!$L$17*(1+Seg!$M$18) -> 9.2766549 | N17: =Q!$N$15 -> 2.811 | O17: =Q!$O$15 -> 3.124 | P17: Q 頁實績；預測＝前期 ×（1＋年增）
A18: Other 年增 | B18: % | E18: =Seg!$E$17/Seg!$N$17-1 -> 0.23585912 | F18: =Seg!$O$17/(Q!$F$15+Q!$G$15)-1 -> 0.076128143 | G18: =Seg!$G$17/Seg!$D$17-1 -> 0.12393412 | H18: =Seg!$F$18+(g_ot-Seg!$F$18)*1/4 -> 0.069596107 | I18: =Seg!$F$18+(g_ot-Seg!$F$18)*2/4 -> 0.063064072 | J18: =Seg!$F$18+(g_ot-Seg!$F$18)*3/4 -> 0.056532036 | K18: =Seg!$F$18+(g_ot-Seg!$F$18)*4/4 -> 0.05 | L18: =g_ot -> 0.05 | M18: =g_ot -> 0.05 | P18: E＝1H26 對 1H25（含 Prime Day 移入 Q2）；F＝2H25 對 2H24（2H26 成長基準，Derived）；收斂到 In 頁 g_ot
A19: 2H26 零售營收校準係數（使隱含 2026Q3 營收＝指引中點） | B19: x | F19: =(g26q3_mid*Q!$O$8/Q!$J$8-Thesis!$F$26-Thesis!$F$30)/(Seg!$O$7*(1+Seg!$F$8)+Seg!$O$9*(1+Seg!$F$10)+Seg!$O$11*(1+Seg!$F$12)+Seg!$O$13*(1+Seg!$F$14)+Seg!$O$15*(1+Seg!$F$16)+Seg!$O$17*(1+Seg!$F$18)) -> 0.95083762 | P19: 2H26 合併營收目標＝Q3 指引中點 ÷（2025Q3 占 2H25 比例）；AWS 由命題模組決定，零售六線同比例校準（Prime Day 時點已含在指引中）
A20: 零售營收線合計（＝North America＋International） | B20: US$bn | C20: =Seg!$C$7+Seg!$C$9+Seg!$C$11+Seg!$C$13+Seg!$C$15+Seg!$C$17 -> 530.403 | D20: =Seg!$D$7+Seg!$D$9+Seg!$D$11+Seg!$D$13+Seg!$D$15+Seg!$D$17 -> 588.199 | E20: =Seg!$E$7+Seg!$E$9+Seg!$E$11+Seg!$E$13+Seg!$E$15+Seg!$E$17 -> 302.306 | F20: =Seg!$F$7+Seg!$F$9+Seg!$F$11+Seg!$F$13+Seg!$F$15+Seg!$F$17 -> 346.24104 | G20: =Seg!$G$7+Seg!$G$9+Seg!$G$11+Seg!$G$13+Seg!$G$15+Seg!$G$17 -> 648.54704 | H20: =Seg!$H$7+Seg!$H$9+Seg!$H$11+Seg!$H$13+Seg!$H$15+Seg!$H$17 -> 717.98776 | I20: =Seg!$I$7+Seg!$I$9+Seg!$I$11+Seg!$I$13+Seg!$I$15+Seg!$I$17 -> 785.12826 | J20: =Seg!$J$7+Seg!$J$9+Seg!$J$11+Seg!$J$13+Seg!$J$15+Seg!$J$17 -> 847.4363 | K20: =Seg!$K$7+Seg!$K$9+Seg!$K$11+Seg!$K$13+Seg!$K$15+Seg!$K$17 -> 902.26603 | L20: =Seg!$L$7+Seg!$L$9+Seg!$L$11+Seg!$L$13+Seg!$L$15+Seg!$L$17 -> 960.92763 | M20: =Seg!$M$7+Seg!$M$9+Seg!$M$11+Seg!$M$13+Seg!$M$15+Seg!$M$17 -> 1023.7094 | N20: =Seg!$N$7+Seg!$N$9+Seg!$N$11+Seg!$N$13+Seg!$N$15+Seg!$N$17 -> 263.229 | O20: =Seg!$O$7+Seg!$O$9+Seg!$O$11+Seg!$O$13+Seg!$O$15+Seg!$O$17 -> 324.97
A21: 北美占零售營收比例（地區分攤） | B21: % | C21: =Q!$D$5/(Q!$D$5+Q!$D$6) -> 0.73057091 | D21: =Q!$E$5/(Q!$E$5+Q!$E$6) -> 0.72476322 | E21: =Q!$P$5/(Q!$P$5+Q!$P$6) -> 0.72879797 | F21: =Seg!$O$21 -> 0.71806628 | G21: =Seg!$G$22/Seg!$G$20 -> 0.72306863 | H21: =Seg!$G$21 -> 0.72306863 | I21: =Seg!$G$21 -> 0.72306863 | J21: =Seg!$G$21 -> 0.72306863 | K21: =Seg!$G$21 -> 0.72306863 | L21: =Seg!$G$21 -> 0.72306863 | M21: =Seg!$G$21 -> 0.72306863 | N21: =Q!$N$5/(Q!$N$5+Q!$N$6) -> 0.73303094 | O21: =Q!$O$5/(Q!$O$5+Q!$O$6) -> 0.71806628 | P21: 2H26＝2H25 比例；2027 起固定為 FY2026（Derived）；各營收線不分地區揭露，故以本列分攤
A22: North America | B22: US$bn | C22: =Q!$D$5 -> 387.497 | D22: =Q!$E$5 -> 426.305 | E22: =Q!$P$5 -> 220.32 | F22: =Seg!$F$20*Seg!$F$21 -> 248.62402 | G22: =Seg!$E$22+Seg!$F$22 -> 468.94402 | H22: =Seg!$H$20*Seg!$H$21 -> 519.15442 | I22: =Seg!$I$20*Seg!$I$21 -> 567.70161 | J22: =Seg!$J$20*Seg!$J$21 -> 612.7546 | K22: =Seg!$K$20*Seg!$K$21 -> 652.40025 | L22: =Seg!$L$20*Seg!$L$21 -> 694.81662 | M22: =Seg!$M$20*Seg!$M$21 -> 740.21216 | N22: =Q!$N$5 -> 192.955 | O22: =Q!$O$5 -> 233.35 | P22: 官方分部；預測＝零售營收線合計 × 北美比例
A23: International | B23: US$bn | C23: =Q!$D$6 -> 142.906 | D23: =Q!$E$6 -> 161.894 | E23: =Q!$P$6 -> 81.986 | F23: =Seg!$F$20*(1-Seg!$F$21) -> 97.617024 | G23: =Seg!$E$23+Seg!$F$23 -> 179.60302 | H23: =Seg!$H$20*(1-Seg!$H$21) -> 198.83334 | I23: =Seg!$I$20*(1-Seg!$I$21) -> 217.42665 | J23: =Seg!$J$20*(1-Seg!$J$21) -> 234.6817 | K23: =Seg!$K$20*(1-Seg!$K$21) -> 249.86577 | L23: =Seg!$L$20*(1-Seg!$L$21) -> 266.11101 | M23: =Seg!$M$20*(1-Seg!$M$21) -> 283.49725 | N23: =Q!$N$6 -> 70.274 | O23: =Q!$O$6 -> 91.62 | P23: 官方分部；預測＝零售營收線合計 ×（1 − 北美比例）
A24: 廣告營收歸北美（＝廣告 × 北美比例） | B24: US$bn | C24: =Seg!$C$13*Seg!$C$21 -> 41.068313 | D24: =Seg!$D$13*Seg!$D$21 -> 49.744123 | E24: =Seg!$E$13*Seg!$E$21 -> 27.003422 | F24: =Seg!$F$13*Seg!$F$21 -> 32.877387 | G24: =Seg!$G$13*Seg!$G$21 -> 59.897563 | H24: =Seg!$H$13*Seg!$H$21 -> 71.910084 | I24: =Seg!$I$13*Seg!$I$21 -> 83.921518 | J24: =Seg!$J$13*Seg!$J$21 -> 95.12647 | K24: =Seg!$K$13*Seg!$K$21 -> 104.63912 | L24: =Seg!$L$13*Seg!$L$21 -> 115.10303 | M24: =Seg!$M$13*Seg!$M$21 -> 126.61333 | N24: =Seg!$N$13*Seg!$N$21 -> 21.708711 | O24: =Seg!$O$13*Seg!$O$21 -> 28.018946 | P24: 廣告營收依零售營收的地區比例分攤（Assumed；公司未分地區揭露）
A25: 廣告營收歸國際 | B25: US$bn | C25: =Seg!$C$13-Seg!$C$24 -> 15.145687 | D25: =Seg!$D$13-Seg!$D$24 -> 18.890877 | E25: =Seg!$E$13-Seg!$E$24 -> 10.048578 | F25: =Seg!$F$13-Seg!$F$24 -> 12.908619 | G25: =Seg!$G$13-Seg!$G$24 -> 22.940443 | H25: =Seg!$H$13-Seg!$H$24 -> 27.541174 | I25: =Seg!$I$13-Seg!$I$24 -> 32.141488 | J25: =Seg!$J$13-Seg!$J$24 -> 36.432924 | K25: =Seg!$K$13-Seg!$K$24 -> 40.076216 | L25: =Seg!$L$13-Seg!$L$24 -> 44.083838 | M25: =Seg!$M$13-Seg!$M$24 -> 48.492221 | N25: =Seg!$N$13-Seg!$N$24 -> 7.9062889 | O25: =Seg!$O$13-Seg!$O$24 -> 11.001054
A26: 2. AWS（命題子列＋AWS 其他）與合併營收
A27: AWS AI（命題子列） | B27: US$bn | C27: =Thesis!$C$26 -> 2.3210054 | D27: =Thesis!$D$26 -> 8.7037701 | E27: =Thesis!$E$26 -> 8.510353 | F27: =Thesis!$F$26 -> 17.770633 | G27: =Thesis!$G$26 -> 26.280986 | H27: =Thesis!$H$26 -> 83.083874 | I27: =Thesis!$I$26 -> 148.07629 | J27: =Thesis!$J$26 -> 213.35784 | K27: =Thesis!$K$26 -> 269.04538 | L27: =Thesis!$L$26 -> 305.63187 | M27: =Thesis!$M$26 -> 323.07029 | N27: =Thesis!$N$26 -> 3.0463195 | O27: =Thesis!$O$26 -> 5.6574506 | P27: Thesis 頁
A28: AWS 其他 | B28: US$bn | C28: =Thesis!$C$30 -> 105.23499 | D28: =Thesis!$D$30 -> 120.02123 | E28: =Thesis!$E$30 -> 71.308647 | F28: =Thesis!$F$30 -> 71.7693 | G28: =Thesis!$G$30 -> 143.07795 | H28: =Thesis!$H$30 -> 161.01708 | I28: =Thesis!$I$30 -> 178.76976 | J28: =Thesis!$J$30 -> 195.77554 | K28: =Thesis!$K$30 -> 211.43758 | L28: =Thesis!$L$30 -> 228.35259 | M28: =Thesis!$M$30 -> 246.62079 | N28: =Thesis!$N$30 -> 57.09368 | O28: =Thesis!$O$30 -> 62.927549 | P28: Thesis 頁
A29: AWS | B29: US$bn | C29: =Q!$D$7 -> 107.556 | D29: =Q!$E$7 -> 128.725 | E29: =Q!$P$7 -> 79.819 | F29: =Seg!$F$27+Seg!$F$28 -> 89.539932 | G29: =Seg!$G$27+Seg!$G$28 -> 169.35893 | H29: =Seg!$H$27+Seg!$H$28 -> 244.10095 | I29: =Seg!$I$27+Seg!$I$28 -> 326.84605 | J29: =Seg!$J$27+Seg!$J$28 -> 409.13338 | K29: =Seg!$K$27+Seg!$K$28 -> 480.48296 | L29: =Seg!$L$27+Seg!$L$28 -> 533.98446 | M29: =Seg!$M$27+Seg!$M$28 -> 569.69108 | N29: =Q!$N$7 -> 60.14 | O29: =Q!$O$7 -> 68.585 | P29: 官方分部＝AWS 營收線
A30: 合併營收（實績＝公司揭露；預測＝營收線加總） | B30: US$bn | C30: =Q!$D$8 -> 637.959 | D30: =Q!$E$8 -> 716.924 | E30: =Q!$P$8 -> 382.125 | F30: =Seg!$F$20+Seg!$F$29 -> 435.78098 | G30: =Seg!$G$20+Seg!$G$29 -> 817.90598 | H30: =Seg!$H$20+Seg!$H$29 -> 962.08871 | I30: =Seg!$I$20+Seg!$I$29 -> 1111.9743 | J30: =Seg!$J$20+Seg!$J$29 -> 1256.5697 | K30: =Seg!$K$20+Seg!$K$29 -> 1382.749 | L30: =Seg!$L$20+Seg!$L$29 -> 1494.9121 | M30: =Seg!$M$20+Seg!$M$29 -> 1593.4005 | N30: =Q!$N$8 -> 323.369 | O30: =Q!$O$8 -> 393.555
A31: 檢查（情境 A）：零售營收線合計 − (North America＋International) | B31: US$bn | C31: =Seg!$C$20-(Seg!$C$22+Seg!$C$23) -> 0 | D31: =Seg!$D$20-(Seg!$D$22+Seg!$D$23) -> 0 | E31: =Seg!$E$20-(Seg!$E$22+Seg!$E$23) -> 0 | F31: =Seg!$F$20-(Seg!$F$22+Seg!$F$23) -> 0 | G31: =Seg!$G$20-(Seg!$G$22+Seg!$G$23) -> 0 | H31: =Seg!$H$20-(Seg!$H$22+Seg!$H$23) -> 0 | I31: =Seg!$I$20-(Seg!$I$22+Seg!$I$23) -> 0 | J31: =Seg!$J$20-(Seg!$J$22+Seg!$J$23) -> 0 | K31: =Seg!$K$20-(Seg!$K$22+Seg!$K$23) -> 0 | L31: =Seg!$L$20-(Seg!$L$22+Seg!$L$23) -> 0 | M31: =Seg!$M$20-(Seg!$M$22+Seg!$M$23) -> 0 | N31: =Seg!$N$20-(Seg!$N$22+Seg!$N$23) -> 0 | O31: =Seg!$O$20-(Seg!$O$22+Seg!$O$23) -> 0
A32: 檢查（情境 A）：AWS AI＋AWS 其他 − AWS | B32: US$bn | C32: =Seg!$C$27+Seg!$C$28-Seg!$C$29 -> 0 | D32: =Seg!$D$27+Seg!$D$28-Seg!$D$29 -> 0 | E32: =Seg!$E$27+Seg!$E$28-Seg!$E$29 -> 0 | F32: =Seg!$F$27+Seg!$F$28-Seg!$F$29 -> 0 | G32: =Seg!$G$27+Seg!$G$28-Seg!$G$29 -> 0 | H32: =Seg!$H$27+Seg!$H$28-Seg!$H$29 -> 0 | I32: =Seg!$I$27+Seg!$I$28-Seg!$I$29 -> 0 | J32: =Seg!$J$27+Seg!$J$28-Seg!$J$29 -> 0 | K32: =Seg!$K$27+Seg!$K$28-Seg!$K$29 -> 0 | L32: =Seg!$L$27+Seg!$L$28-Seg!$L$29 -> 0 | M32: =Seg!$M$27+Seg!$M$28-Seg!$M$29 -> 0 | N32: =Seg!$N$27+Seg!$N$28-Seg!$N$29 -> 0 | O32: =Seg!$O$27+Seg!$O$28-Seg!$O$29 -> 0
A33: 檢查（情境 A）：分部合計 − 合併營收 | B33: US$bn | C33: =Seg!$C$22+Seg!$C$23+Seg!$C$29-Seg!$C$30 -> 0 | D33: =Seg!$D$22+Seg!$D$23+Seg!$D$29-Seg!$D$30 -> 0 | E33: =Seg!$E$22+Seg!$E$23+Seg!$E$29-Seg!$E$30 -> 0 | F33: =Seg!$F$22+Seg!$F$23+Seg!$F$29-Seg!$F$30 -> 0 | G33: =Seg!$G$22+Seg!$G$23+Seg!$G$29-Seg!$G$30 -> 0 | H33: =Seg!$H$22+Seg!$H$23+Seg!$H$29-Seg!$H$30 -> 0 | I33: =Seg!$I$22+Seg!$I$23+Seg!$I$29-Seg!$I$30 -> 0 | J33: =Seg!$J$22+Seg!$J$23+Seg!$J$29-Seg!$J$30 -> 0 | K33: =Seg!$K$22+Seg!$K$23+Seg!$K$29-Seg!$K$30 -> 0 | L33: =Seg!$L$22+Seg!$L$23+Seg!$L$29-Seg!$L$30 -> 0 | M33: =Seg!$M$22+Seg!$M$23+Seg!$M$29-Seg!$M$30 -> 0 | N33: =Seg!$N$22+Seg!$N$23+Seg!$N$29-Seg!$N$30 -> 0 | O33: =Seg!$O$22+Seg!$O$23+Seg!$O$29-Seg!$O$30 -> 0
A34: 合併營收年增 | B34: % | G34: =Seg!$G$30/Seg!$D$30-1 -> 0.1408545 | H34: =Seg!$H$30/Seg!$G$30-1 -> 0.17628277 | I34: =Seg!$I$30/Seg!$H$30-1 -> 0.15579187 | J34: =Seg!$J$30/Seg!$I$30-1 -> 0.13003482 | K34: =Seg!$K$30/Seg!$J$30-1 -> 0.10041568 | L34: =Seg!$L$30/Seg!$K$30-1 -> 0.081116032 | M34: =Seg!$M$30/Seg!$L$30-1 -> 0.065882404
A35: AWS 占合併營收 | B35: % | C35: =Seg!$C$29/Seg!$C$30 -> 0.16859391 | D35: =Seg!$D$29/Seg!$D$30 -> 0.17955181 | E35: =Seg!$E$29/Seg!$E$30 -> 0.20888191 | F35: =Seg!$F$29/Seg!$F$30 -> 0.20547004 | G35: =Seg!$G$29/Seg!$G$30 -> 0.20706406 | H35: =Seg!$H$29/Seg!$H$30 -> 0.2537198 | I35: =Seg!$I$29/Seg!$I$30 -> 0.2939331 | J35: =Seg!$J$29/Seg!$J$30 -> 0.32559546 | K35: =Seg!$K$29/Seg!$K$30 -> 0.34748386 | L35: =Seg!$L$29/Seg!$L$30 -> 0.35720124 | M35: =Seg!$M$29/Seg!$M$30 -> 0.35753163 | N35: =Seg!$N$29/Seg!$N$30 -> 0.18597948 | O35: =Seg!$O$29/Seg!$O$30 -> 0.17427043
A36: AWS AI 占 AWS | B36: % | C36: =Seg!$C$27/Seg!$C$29 -> 0.021579506 | D36: =Seg!$D$27/Seg!$D$29 -> 0.067615227 | E36: =Seg!$E$27/Seg!$E$29 -> 0.10662064 | F36: =Seg!$F$27/Seg!$F$29 -> 0.198466 | G36: =Seg!$G$27/Seg!$G$29 -> 0.15517921 | H36: =Seg!$H$27/Seg!$H$29 -> 0.34036686 | I36: =Seg!$I$27/Seg!$I$29 -> 0.45304599 | J36: =Seg!$J$27/Seg!$J$29 -> 0.52148725 | K36: =Seg!$K$27/Seg!$K$29 -> 0.5599478 | L36: =Seg!$L$27/Seg!$L$29 -> 0.57236099 | M36: =Seg!$M$27/Seg!$M$29 -> 0.56709732 | N36: =Seg!$N$27/Seg!$N$29 -> 0.0506538 | O36: =Seg!$O$27/Seg!$O$29 -> 0.082488162
A39: Seg｜情境 B（基準）：營收分部層（官方分部 North America、International、AWS；10-K 營收線）
A40: 項目 | B40: 單位 | C40: FY2024A | D40: FY2025A | E40: 1H26A | F40: 2H26E | G40: FY2026E（1H 實績＋2H 模型） | H40: FY2027E | I40: FY2028E | J40: FY2029E | K40: FY2030E | L40: FY2031E | M40: FY2032E | N40: 1H25A | O40: 2H25A | P40: 說明 | R40: 2023 | S40: 2024 | T40: 2025 | U40: 2026 | V40: 2027 | W40: 2028 | X40: 2029 | Y40: 2030 | Z40: 2031 | AA40: 2032
A41: 1. 零售各營收線（2H26＝2H25 ×（1＋2H25 年增）× 校準係數；2027–2030 年增由 2H25 年增線性收斂到長期值；2031–2032＝長期值）
A42: Online stores | B42: US$bn | C42: =Q!$D$10 -> 247.029 | D42: =Q!$E$10 -> 269.287 | E42: =Q!$P$10 -> 134.686 | F42: =Seg!$O$42*(1+Seg!$F$43)*Seg!$F$54 -> 158.29388 | G42: =Seg!$E$42+Seg!$F$42 -> 292.97988 | H42: =Seg!$G$42*(1+Seg!$H$43) -> 318.18454 | I42: =Seg!$H$42*(1+Seg!$I$43) -> 341.73628 | J42: =Seg!$I$42*(1+Seg!$J$43) -> 362.92719 | K42: =Seg!$J$42*(1+Seg!$K$43) -> 381.07355 | L42: =Seg!$K$42*(1+Seg!$L$43) -> 400.12723 | M42: =Seg!$L$42*(1+Seg!$M$43) -> 420.13359 | N42: =Q!$N$10 -> 118.892 | O42: =Q!$O$10 -> 150.395 | P42: Q 頁實績；預測＝前期 ×（1＋年增）
A43: Online stores 年增 | B43: % | E43: =Seg!$E$42/Seg!$N$42-1 -> 0.13284325 | F43: =Seg!$O$42/(Q!$F$10+Q!$G$10)-1 -> 0.098038214 | G43: =Seg!$G$42/Seg!$D$42-1 -> 0.087983738 | H43: =Seg!$F$43+(g_os-Seg!$F$43)*1/4 -> 0.08602866 | I43: =Seg!$F$43+(g_os-Seg!$F$43)*2/4 -> 0.074019107 | J43: =Seg!$F$43+(g_os-Seg!$F$43)*3/4 -> 0.062009553 | K43: =Seg!$F$43+(g_os-Seg!$F$43)*4/4 -> 0.05 | L43: =g_os -> 0.05 | M43: =g_os -> 0.05 | P43: E＝1H26 對 1H25（含 Prime Day 移入 Q2）；F＝2H25 對 2H24（2H26 成長基準，Derived）；收斂到 In 頁 g_os
A44: Physical stores | B44: US$bn | C44: =Q!$D$11 -> 21.215 | D44: =Q!$E$11 -> 22.561 | E44: =Q!$P$11 -> 11.579 | F44: =Seg!$O$44*(1+Seg!$F$45)*Seg!$F$54 -> 11.593872 | G44: =Seg!$E$44+Seg!$F$44 -> 23.172872 | H44: =Seg!$G$44*(1+Seg!$H$45) -> 24.353393 | I44: =Seg!$H$44*(1+Seg!$I$45) -> 25.424034 | J44: =Seg!$I$44*(1+Seg!$J$45) -> 26.364249 | K44: =Seg!$J$44*(1+Seg!$K$45) -> 27.155177 | L44: =Seg!$K$44*(1+Seg!$L$45) -> 27.969832 | M44: =Seg!$L$44*(1+Seg!$M$45) -> 28.808927 | N44: =Q!$N$11 -> 11.128 | O44: =Q!$O$11 -> 11.433 | P44: Q 頁實績；預測＝前期 ×（1＋年增）
A45: Physical stores 年增 | B45: % | E45: =Seg!$E$44/Seg!$N$44-1 -> 0.040528397 | F45: =Seg!$O$44/(Q!$F$11+Q!$G$11)-1 -> 0.057925419 | G45: =Seg!$G$44/Seg!$D$44-1 -> 0.027120804 | H45: =Seg!$F$45+(g_ps-Seg!$F$45)*1/4 -> 0.050944064 | I45: =Seg!$F$45+(g_ps-Seg!$F$45)*2/4 -> 0.043962709 | J45: =Seg!$F$45+(g_ps-Seg!$F$45)*3/4 -> 0.036981355 | K45: =Seg!$F$45+(g_ps-Seg!$F$45)*4/4 -> 0.03 | L45: =g_ps -> 0.03 | M45: =g_ps -> 0.03 | P45: E＝1H26 對 1H25（含 Prime Day 移入 Q2）；F＝2H25 對 2H24（2H26 成長基準，Derived）；收斂到 In 頁 g_ps
A46: Third-party seller services | B46: US$bn | C46: =Q!$D$12 -> 156.146 | D46: =Q!$E$12 -> 172.162 | E46: =Q!$P$12 -> 88.358 | F46: =Seg!$O$46*(1+Seg!$F$47)*Seg!$F$54 -> 102.00439 | G46: =Seg!$E$46+Seg!$F$46 -> 190.36239 | H46: =Seg!$G$46*(1+Seg!$H$47) -> 210.34311 | I46: =Seg!$H$46*(1+Seg!$I$47) -> 229.96973 | J46: =Seg!$I$46*(1+Seg!$J$47) -> 248.74764 | K46: =Seg!$J$46*(1+Seg!$K$47) -> 266.15997 | L46: =Seg!$K$46*(1+Seg!$L$47) -> 284.79117 | M46: =Seg!$L$46*(1+Seg!$M$47) -> 304.72655 | N46: =Q!$N$12 -> 76.86 | O46: =Q!$O$12 -> 95.302 | P46: Q 頁實績；預測＝前期 ×（1＋年增）
A47: Third-party seller services 年增 | B47: % | E47: =Seg!$E$46/Seg!$N$46-1 -> 0.14959667 | F47: =Seg!$O$46/(Q!$F$12+Q!$G$12)-1 -> 0.11661531 | G47: =Seg!$G$46/Seg!$D$46-1 -> 0.10571664 | H47: =Seg!$F$47+(g_sp-Seg!$F$47)*1/4 -> 0.10496148 | I47: =Seg!$F$47+(g_sp-Seg!$F$47)*2/4 -> 0.093307654 | J47: =Seg!$F$47+(g_sp-Seg!$F$47)*3/4 -> 0.081653827 | K47: =Seg!$F$47+(g_sp-Seg!$F$47)*4/4 -> 0.07 | L47: =g_sp -> 0.07 | M47: =g_sp -> 0.07 | P47: E＝1H26 對 1H25（含 Prime Day 移入 Q2）；F＝2H25 對 2H24（2H26 成長基準，Derived）；收斂到 In 頁 g_sp
A48: Advertising services | B48: US$bn | C48: =Q!$D$13 -> 56.214 | D48: =Q!$E$13 -> 68.635 | E48: =Q!$P$13 -> 37.052 | F48: =Seg!$O$48*(1+Seg!$F$49)*Seg!$F$54 -> 46.157222 | G48: =Seg!$E$48+Seg!$F$48 -> 83.209222 | H48: =Seg!$G$48*(1+Seg!$H$49) -> 99.896922 | I48: =Seg!$H$48*(1+Seg!$I$49) -> 116.58311 | J48: =Seg!$I$48*(1+Seg!$J$49) -> 132.14894 | K48: =Seg!$J$48*(1+Seg!$K$49) -> 145.36384 | L48: =Seg!$K$48*(1+Seg!$L$49) -> 159.90022 | M48: =Seg!$L$48*(1+Seg!$M$49) -> 175.89024 | N48: =Q!$N$13 -> 29.615 | O48: =Q!$O$13 -> 39.02 | P48: Q 頁實績；預測＝前期 ×（1＋年增）
A49: Advertising services 年增 | B49: % | E49: =Seg!$E$48/Seg!$N$48-1 -> 0.25112274 | F49: =Seg!$O$48/(Q!$F$13+Q!$G$13)-1 -> 0.23406812 | G49: =Seg!$G$48/Seg!$D$48-1 -> 0.21234388 | H49: =Seg!$F$49+(g_ad-Seg!$F$49)*1/4 -> 0.20055109 | I49: =Seg!$F$49+(g_ad-Seg!$F$49)*2/4 -> 0.16703406 | J49: =Seg!$F$49+(g_ad-Seg!$F$49)*3/4 -> 0.13351703 | K49: =Seg!$F$49+(g_ad-Seg!$F$49)*4/4 -> 0.1 | L49: =g_ad -> 0.1 | M49: =g_ad -> 0.1 | P49: E＝1H26 對 1H25（含 Prime Day 移入 Q2）；F＝2H25 對 2H24（2H26 成長基準，Derived）；收斂到 In 頁 g_ad
A50: Subscription services | B50: US$bn | C50: =Q!$D$14 -> 44.374 | D50: =Q!$E$14 -> 49.619 | E50: =Q!$P$14 -> 27.157 | F50: =Seg!$O$50*(1+Seg!$F$51)*Seg!$F$54 -> 27.776417 | G50: =Seg!$E$50+Seg!$F$50 -> 54.933417 | H50: =Seg!$G$50*(1+Seg!$H$51) -> 61.156411 | I50: =Seg!$H$50*(1+Seg!$I$51) -> 67.202028 | J50: =Seg!$I$50*(1+Seg!$J$51) -> 72.875727 | K50: =Seg!$J$50*(1+Seg!$K$51) -> 77.977028 | L50: =Seg!$K$50*(1+Seg!$L$51) -> 83.43542 | M50: =Seg!$L$50*(1+Seg!$M$51) -> 89.2759 | N50: =Q!$N$14 -> 23.923 | O50: =Q!$O$14 -> 25.696 | P50: Q 頁實績；預測＝前期 ×（1＋年增）
A51: Subscription services 年增 | B51: % | E51: =Seg!$E$50/Seg!$N$50-1 -> 0.13518371 | F51: =Seg!$O$50/(Q!$F$14+Q!$G$14)-1 -> 0.12771 | G51: =Seg!$G$50/Seg!$D$50-1 -> 0.10710447 | H51: =Seg!$F$51+(g_sub-Seg!$F$51)*1/4 -> 0.1132825 | I51: =Seg!$F$51+(g_sub-Seg!$F$51)*2/4 -> 0.098854999 | J51: =Seg!$F$51+(g_sub-Seg!$F$51)*3/4 -> 0.084427499 | K51: =Seg!$F$51+(g_sub-Seg!$F$51)*4/4 -> 0.07 | L51: =g_sub -> 0.07 | M51: =g_sub -> 0.07 | P51: E＝1H26 對 1H25（含 Prime Day 移入 Q2）；F＝2H25 對 2H24（2H26 成長基準，Derived）；收斂到 In 頁 g_sub
A52: Other | B52: US$bn | C52: =Q!$D$15 -> 5.425 | D52: =Q!$E$15 -> 5.935 | E52: =Q!$P$15 -> 3.474 | F52: =Seg!$O$52*(1+Seg!$F$53)*Seg!$F$54 -> 3.2224655 | G52: =Seg!$E$52+Seg!$F$52 -> 6.6964655 | H52: =Seg!$G$52*(1+Seg!$H$53) -> 7.1625134 | I52: =Seg!$H$52*(1+Seg!$I$53) -> 7.6142107 | J52: =Seg!$I$52*(1+Seg!$J$53) -> 8.0446575 | K52: =Seg!$J$52*(1+Seg!$K$53) -> 8.4468904 | L52: =Seg!$K$52*(1+Seg!$L$53) -> 8.8692349 | M52: =Seg!$L$52*(1+Seg!$M$53) -> 9.3126967 | N52: =Q!$N$15 -> 2.811 | O52: =Q!$O$15 -> 3.124 | P52: Q 頁實績；預測＝前期 ×（1＋年增）
A53: Other 年增 | B53: % | E53: =Seg!$E$52/Seg!$N$52-1 -> 0.23585912 | F53: =Seg!$O$52/(Q!$F$15+Q!$G$15)-1 -> 0.076128143 | G53: =Seg!$G$52/Seg!$D$52-1 -> 0.12830084 | H53: =Seg!$F$53+(g_ot-Seg!$F$53)*1/4 -> 0.069596107 | I53: =Seg!$F$53+(g_ot-Seg!$F$53)*2/4 -> 0.063064072 | J53: =Seg!$F$53+(g_ot-Seg!$F$53)*3/4 -> 0.056532036 | K53: =Seg!$F$53+(g_ot-Seg!$F$53)*4/4 -> 0.05 | L53: =g_ot -> 0.05 | M53: =g_ot -> 0.05 | P53: E＝1H26 對 1H25（含 Prime Day 移入 Q2）；F＝2H25 對 2H24（2H26 成長基準，Derived）；收斂到 In 頁 g_ot
A54: 2H26 零售營收校準係數（使隱含 2026Q3 營收＝指引中點） | B54: x | F54: =(g26q3_mid*Q!$O$8/Q!$J$8-Thesis!$F$84-Thesis!$F$88)/(Seg!$O$42*(1+Seg!$F$43)+Seg!$O$44*(1+Seg!$F$45)+Seg!$O$46*(1+Seg!$F$47)+Seg!$O$48*(1+Seg!$F$49)+Seg!$O$50*(1+Seg!$F$51)+Seg!$O$52*(1+Seg!$F$53)) -> 0.95854667 | P54: 2H26 合併營收目標＝Q3 指引中點 ÷（2025Q3 占 2H25 比例）；AWS 由命題模組決定，零售六線同比例校準（Prime Day 時點已含在指引中）
A55: 零售營收線合計（＝North America＋International） | B55: US$bn | C55: =Seg!$C$42+Seg!$C$44+Seg!$C$46+Seg!$C$48+Seg!$C$50+Seg!$C$52 -> 530.403 | D55: =Seg!$D$42+Seg!$D$44+Seg!$D$46+Seg!$D$48+Seg!$D$50+Seg!$D$52 -> 588.199 | E55: =Seg!$E$42+Seg!$E$44+Seg!$E$46+Seg!$E$48+Seg!$E$50+Seg!$E$52 -> 302.306 | F55: =Seg!$F$42+Seg!$F$44+Seg!$F$46+Seg!$F$48+Seg!$F$50+Seg!$F$52 -> 349.04824 | G55: =Seg!$G$42+Seg!$G$44+Seg!$G$46+Seg!$G$48+Seg!$G$50+Seg!$G$52 -> 651.35424 | H55: =Seg!$H$42+Seg!$H$44+Seg!$H$46+Seg!$H$48+Seg!$H$50+Seg!$H$52 -> 721.09689 | I55: =Seg!$I$42+Seg!$I$44+Seg!$I$46+Seg!$I$48+Seg!$I$50+Seg!$I$52 -> 788.52939 | J55: =Seg!$J$42+Seg!$J$44+Seg!$J$46+Seg!$J$48+Seg!$J$50+Seg!$J$52 -> 851.10841 | K55: =Seg!$K$42+Seg!$K$44+Seg!$K$46+Seg!$K$48+Seg!$K$50+Seg!$K$52 -> 906.17646 | L55: =Seg!$L$42+Seg!$L$44+Seg!$L$46+Seg!$L$48+Seg!$L$50+Seg!$L$52 -> 965.09311 | M55: =Seg!$M$42+Seg!$M$44+Seg!$M$46+Seg!$M$48+Seg!$M$50+Seg!$M$52 -> 1028.1479 | N55: =Seg!$N$42+Seg!$N$44+Seg!$N$46+Seg!$N$48+Seg!$N$50+Seg!$N$52 -> 263.229 | O55: =Seg!$O$42+Seg!$O$44+Seg!$O$46+Seg!$O$48+Seg!$O$50+Seg!$O$52 -> 324.97
A56: 北美占零售營收比例（地區分攤） | B56: % | C56: =Q!$D$5/(Q!$D$5+Q!$D$6) -> 0.73057091 | D56: =Q!$E$5/(Q!$E$5+Q!$E$6) -> 0.72476322 | E56: =Q!$P$5/(Q!$P$5+Q!$P$6) -> 0.72879797 | F56: =Seg!$O$56 -> 0.71806628 | G56: =Seg!$G$57/Seg!$G$55 -> 0.72304707 | H56: =Seg!$G$56 -> 0.72304707 | I56: =Seg!$G$56 -> 0.72304707 | J56: =Seg!$G$56 -> 0.72304707 | K56: =Seg!$G$56 -> 0.72304707 | L56: =Seg!$G$56 -> 0.72304707 | M56: =Seg!$G$56 -> 0.72304707 | N56: =Q!$N$5/(Q!$N$5+Q!$N$6) -> 0.73303094 | O56: =Q!$O$5/(Q!$O$5+Q!$O$6) -> 0.71806628 | P56: 2H26＝2H25 比例；2027 起固定為 FY2026（Derived）；各營收線不分地區揭露，故以本列分攤
A57: North America | B57: US$bn | C57: =Q!$D$5 -> 387.497 | D57: =Q!$E$5 -> 426.305 | E57: =Q!$P$5 -> 220.32 | F57: =Seg!$F$55*Seg!$F$56 -> 250.63977 | G57: =Seg!$E$57+Seg!$F$57 -> 470.95977 | H57: =Seg!$H$55*Seg!$H$56 -> 521.38699 | I57: =Seg!$I$55*Seg!$I$56 -> 570.14386 | J57: =Seg!$J$55*Seg!$J$56 -> 615.39144 | K57: =Seg!$K$55*Seg!$K$56 -> 655.20823 | L57: =Seg!$L$55*Seg!$L$56 -> 697.80774 | M57: =Seg!$M$55*Seg!$M$56 -> 743.39933 | N57: =Q!$N$5 -> 192.955 | O57: =Q!$O$5 -> 233.35 | P57: 官方分部；預測＝零售營收線合計 × 北美比例
A58: International | B58: US$bn | C58: =Q!$D$6 -> 142.906 | D58: =Q!$E$6 -> 161.894 | E58: =Q!$P$6 -> 81.986 | F58: =Seg!$F$55*(1-Seg!$F$56) -> 98.408468 | G58: =Seg!$E$58+Seg!$F$58 -> 180.39447 | H58: =Seg!$H$55*(1-Seg!$H$56) -> 199.7099 | I58: =Seg!$I$55*(1-Seg!$I$56) -> 218.38553 | J58: =Seg!$J$55*(1-Seg!$J$56) -> 235.71697 | K58: =Seg!$K$55*(1-Seg!$K$56) -> 250.96823 | L58: =Seg!$L$55*(1-Seg!$L$56) -> 267.28537 | M58: =Seg!$M$55*(1-Seg!$M$56) -> 284.74858 | N58: =Q!$N$6 -> 70.274 | O58: =Q!$O$6 -> 91.62 | P58: 官方分部；預測＝零售營收線合計 ×（1 − 北美比例）
A59: 廣告營收歸北美（＝廣告 × 北美比例） | B59: US$bn | C59: =Seg!$C$48*Seg!$C$56 -> 41.068313 | D59: =Seg!$D$48*Seg!$D$56 -> 49.744123 | E59: =Seg!$E$48*Seg!$E$56 -> 27.003422 | F59: =Seg!$F$48*Seg!$F$56 -> 33.143945 | G59: =Seg!$G$48*Seg!$G$56 -> 60.164184 | H59: =Seg!$H$48*Seg!$H$56 -> 72.230177 | I59: =Seg!$I$48*Seg!$I$56 -> 84.295076 | J59: =Seg!$J$48*Seg!$J$56 -> 95.549905 | K59: =Seg!$K$48*Seg!$K$56 -> 105.1049 | L59: =Seg!$L$48*Seg!$L$56 -> 115.61538 | M59: =Seg!$M$48*Seg!$M$56 -> 127.17692 | N59: =Seg!$N$48*Seg!$N$56 -> 21.708711 | O59: =Seg!$O$48*Seg!$O$56 -> 28.018946 | P59: 廣告營收依零售營收的地區比例分攤（Assumed；公司未分地區揭露）
A60: 廣告營收歸國際 | B60: US$bn | C60: =Seg!$C$48-Seg!$C$59 -> 15.145687 | D60: =Seg!$D$48-Seg!$D$59 -> 18.890877 | E60: =Seg!$E$48-Seg!$E$59 -> 10.048578 | F60: =Seg!$F$48-Seg!$F$59 -> 13.013277 | G60: =Seg!$G$48-Seg!$G$59 -> 23.045038 | H60: =Seg!$H$48-Seg!$H$59 -> 27.666746 | I60: =Seg!$I$48-Seg!$I$59 -> 32.288035 | J60: =Seg!$J$48-Seg!$J$59 -> 36.599037 | K60: =Seg!$K$48-Seg!$K$59 -> 40.258941 | L60: =Seg!$L$48-Seg!$L$59 -> 44.284835 | M60: =Seg!$M$48-Seg!$M$59 -> 48.713318 | N60: =Seg!$N$48-Seg!$N$59 -> 7.9062889 | O60: =Seg!$O$48-Seg!$O$59 -> 11.001054
A61: 2. AWS（命題子列＋AWS 其他）與合併營收
A62: AWS AI（命題子列） | B62: US$bn | C62: =Thesis!$C$84 -> 2.3210054 | D62: =Thesis!$D$84 -> 8.7037701 | E62: =Thesis!$E$84 -> 8.510353 | F62: =Thesis!$F$84 -> 14.963434 | G62: =Thesis!$G$84 -> 23.473787 | H62: =Thesis!$H$84 -> 60.165891 | I62: =Thesis!$I$84 -> 101.5037 | J62: =Thesis!$J$84 -> 143.02541 | K62: =Thesis!$K$84 -> 178.44812 | L62: =Thesis!$L$84 -> 201.7281 | M62: =Thesis!$M$84 -> 212.83544 | N62: =Thesis!$N$84 -> 3.0463195 | O62: =Thesis!$O$84 -> 5.6574506 | P62: Thesis 頁
A63: AWS 其他 | B63: US$bn | C63: =Thesis!$C$88 -> 105.23499 | D63: =Thesis!$D$88 -> 120.02123 | E63: =Thesis!$E$88 -> 71.308647 | F63: =Thesis!$F$88 -> 71.7693 | G63: =Thesis!$G$88 -> 143.07795 | H63: =Thesis!$H$88 -> 161.01708 | I63: =Thesis!$I$88 -> 178.76976 | J63: =Thesis!$J$88 -> 195.77554 | K63: =Thesis!$K$88 -> 211.43758 | L63: =Thesis!$L$88 -> 228.35259 | M63: =Thesis!$M$88 -> 246.62079 | N63: =Thesis!$N$88 -> 57.09368 | O63: =Thesis!$O$88 -> 62.927549 | P63: Thesis 頁
A64: AWS | B64: US$bn | C64: =Q!$D$7 -> 107.556 | D64: =Q!$E$7 -> 128.725 | E64: =Q!$P$7 -> 79.819 | F64: =Seg!$F$62+Seg!$F$63 -> 86.732733 | G64: =Seg!$G$62+Seg!$G$63 -> 166.55173 | H64: =Seg!$H$62+Seg!$H$63 -> 221.18297 | I64: =Seg!$I$62+Seg!$I$63 -> 280.27346 | J64: =Seg!$J$62+Seg!$J$63 -> 338.80095 | K64: =Seg!$K$62+Seg!$K$63 -> 389.8857 | L64: =Seg!$L$62+Seg!$L$63 -> 430.08069 | M64: =Seg!$M$62+Seg!$M$63 -> 459.45624 | N64: =Q!$N$7 -> 60.14 | O64: =Q!$O$7 -> 68.585 | P64: 官方分部＝AWS 營收線
A65: 合併營收（實績＝公司揭露；預測＝營收線加總） | B65: US$bn | C65: =Q!$D$8 -> 637.959 | D65: =Q!$E$8 -> 716.924 | E65: =Q!$P$8 -> 382.125 | F65: =Seg!$F$55+Seg!$F$64 -> 435.78098 | G65: =Seg!$G$55+Seg!$G$64 -> 817.90598 | H65: =Seg!$H$55+Seg!$H$64 -> 942.27986 | I65: =Seg!$I$55+Seg!$I$64 -> 1068.8028 | J65: =Seg!$J$55+Seg!$J$64 -> 1189.9094 | K65: =Seg!$K$55+Seg!$K$64 -> 1296.0622 | L65: =Seg!$L$55+Seg!$L$64 -> 1395.1738 | M65: =Seg!$M$55+Seg!$M$64 -> 1487.6041 | N65: =Q!$N$8 -> 323.369 | O65: =Q!$O$8 -> 393.555
A66: 檢查（情境 B）：零售營收線合計 − (North America＋International) | B66: US$bn | C66: =Seg!$C$55-(Seg!$C$57+Seg!$C$58) -> 0 | D66: =Seg!$D$55-(Seg!$D$57+Seg!$D$58) -> 0 | E66: =Seg!$E$55-(Seg!$E$57+Seg!$E$58) -> 0 | F66: =Seg!$F$55-(Seg!$F$57+Seg!$F$58) -> 0 | G66: =Seg!$G$55-(Seg!$G$57+Seg!$G$58) -> 0 | H66: =Seg!$H$55-(Seg!$H$57+Seg!$H$58) -> 0 | I66: =Seg!$I$55-(Seg!$I$57+Seg!$I$58) -> 0 | J66: =Seg!$J$55-(Seg!$J$57+Seg!$J$58) -> 0 | K66: =Seg!$K$55-(Seg!$K$57+Seg!$K$58) -> 0 | L66: =Seg!$L$55-(Seg!$L$57+Seg!$L$58) -> 0 | M66: =Seg!$M$55-(Seg!$M$57+Seg!$M$58) -> 0 | N66: =Seg!$N$55-(Seg!$N$57+Seg!$N$58) -> 0 | O66: =Seg!$O$55-(Seg!$O$57+Seg!$O$58) -> 0
A67: 檢查（情境 B）：AWS AI＋AWS 其他 − AWS | B67: US$bn | C67: =Seg!$C$62+Seg!$C$63-Seg!$C$64 -> 0 | D67: =Seg!$D$62+Seg!$D$63-Seg!$D$64 -> 0 | E67: =Seg!$E$62+Seg!$E$63-Seg!$E$64 -> 0 | F67: =Seg!$F$62+Seg!$F$63-Seg!$F$64 -> 0 | G67: =Seg!$G$62+Seg!$G$63-Seg!$G$64 -> 0 | H67: =Seg!$H$62+Seg!$H$63-Seg!$H$64 -> 0 | I67: =Seg!$I$62+Seg!$I$63-Seg!$I$64 -> 0 | J67: =Seg!$J$62+Seg!$J$63-Seg!$J$64 -> 0 | K67: =Seg!$K$62+Seg!$K$63-Seg!$K$64 -> 0 | L67: =Seg!$L$62+Seg!$L$63-Seg!$L$64 -> 0 | M67: =Seg!$M$62+Seg!$M$63-Seg!$M$64 -> 0 | N67: =Seg!$N$62+Seg!$N$63-Seg!$N$64 -> 0 | O67: =Seg!$O$62+Seg!$O$63-Seg!$O$64 -> 0
A68: 檢查（情境 B）：分部合計 − 合併營收 | B68: US$bn | C68: =Seg!$C$57+Seg!$C$58+Seg!$C$64-Seg!$C$65 -> 0 | D68: =Seg!$D$57+Seg!$D$58+Seg!$D$64-Seg!$D$65 -> 0 | E68: =Seg!$E$57+Seg!$E$58+Seg!$E$64-Seg!$E$65 -> 0 | F68: =Seg!$F$57+Seg!$F$58+Seg!$F$64-Seg!$F$65 -> 0 | G68: =Seg!$G$57+Seg!$G$58+Seg!$G$64-Seg!$G$65 -> 0 | H68: =Seg!$H$57+Seg!$H$58+Seg!$H$64-Seg!$H$65 -> 0 | I68: =Seg!$I$57+Seg!$I$58+Seg!$I$64-Seg!$I$65 -> 0 | J68: =Seg!$J$57+Seg!$J$58+Seg!$J$64-Seg!$J$65 -> 0 | K68: =Seg!$K$57+Seg!$K$58+Seg!$K$64-Seg!$K$65 -> 0 | L68: =Seg!$L$57+Seg!$L$58+Seg!$L$64-Seg!$L$65 -> 0 | M68: =Seg!$M$57+Seg!$M$58+Seg!$M$64-Seg!$M$65 -> 0 | N68: =Seg!$N$57+Seg!$N$58+Seg!$N$64-Seg!$N$65 -> 0 | O68: =Seg!$O$57+Seg!$O$58+Seg!$O$64-Seg!$O$65 -> 0
A69: 合併營收年增 | B69: % | G69: =Seg!$G$65/Seg!$D$65-1 -> 0.1408545 | H69: =Seg!$H$65/Seg!$G$65-1 -> 0.15206379 | I69: =Seg!$I$65/Seg!$H$65-1 -> 0.13427326 | J69: =Seg!$J$65/Seg!$I$65-1 -> 0.11331042 | K69: =Seg!$K$65/Seg!$J$65-1 -> 0.089210834 | L69: =Seg!$L$65/Seg!$K$65-1 -> 0.076471362 | M69: =Seg!$M$65/Seg!$L$65-1 -> 0.06625006
A70: AWS 占合併營收 | B70: % | C70: =Seg!$C$64/Seg!$C$65 -> 0.16859391 | D70: =Seg!$D$64/Seg!$D$65 -> 0.17955181 | E70: =Seg!$E$64/Seg!$E$65 -> 0.20888191 | F70: =Seg!$F$64/Seg!$F$65 -> 0.19902827 | G70: =Seg!$G$64/Seg!$G$65 -> 0.20363188 | H70: =Seg!$H$64/Seg!$H$65 -> 0.23473172 | I70: =Seg!$I$64/Seg!$I$65 -> 0.2622312 | J70: =Seg!$J$64/Seg!$J$65 -> 0.28472837 | K70: =Seg!$K$64/Seg!$K$65 -> 0.3008233 | L70: =Seg!$L$64/Seg!$L$65 -> 0.30826316 | M70: =Seg!$M$64/Seg!$M$65 -> 0.30885652 | N70: =Seg!$N$64/Seg!$N$65 -> 0.18597948 | O70: =Seg!$O$64/Seg!$O$65 -> 0.17427043
A71: AWS AI 占 AWS | B71: % | C71: =Seg!$C$62/Seg!$C$64 -> 0.021579506 | D71: =Seg!$D$62/Seg!$D$64 -> 0.067615227 | E71: =Seg!$E$62/Seg!$E$64 -> 0.10662064 | F71: =Seg!$F$62/Seg!$F$64 -> 0.17252349 | G71: =Seg!$G$62/Seg!$G$64 -> 0.14093991 | H71: =Seg!$H$62/Seg!$H$64 -> 0.27201864 | I71: =Seg!$I$62/Seg!$I$64 -> 0.36215951 | J71: =Seg!$J$62/Seg!$J$64 -> 0.42215174 | K71: =Seg!$K$62/Seg!$K$64 -> 0.45769342 | L71: =Seg!$L$62/Seg!$L$64 -> 0.4690471 | M71: =Seg!$M$62/Seg!$M$64 -> 0.46323333 | N71: =Seg!$N$62/Seg!$N$64 -> 0.0506538 | O71: =Seg!$O$62/Seg!$O$64 -> 0.082488162
A74: Seg｜情境 C（保守）：營收分部層（官方分部 North America、International、AWS；10-K 營收線）
A75: 項目 | B75: 單位 | C75: FY2024A | D75: FY2025A | E75: 1H26A | F75: 2H26E | G75: FY2026E（1H 實績＋2H 模型） | H75: FY2027E | I75: FY2028E | J75: FY2029E | K75: FY2030E | L75: FY2031E | M75: FY2032E | N75: 1H25A | O75: 2H25A | P75: 說明 | R75: 2023 | S75: 2024 | T75: 2025 | U75: 2026 | V75: 2027 | W75: 2028 | X75: 2029 | Y75: 2030 | Z75: 2031 | AA75: 2032
A76: 1. 零售各營收線（2H26＝2H25 ×（1＋2H25 年增）× 校準係數；2027–2030 年增由 2H25 年增線性收斂到長期值；2031–2032＝長期值）
A77: Online stores | B77: US$bn | C77: =Q!$D$10 -> 247.029 | D77: =Q!$E$10 -> 269.287 | E77: =Q!$P$10 -> 134.686 | F77: =Seg!$O$77*(1+Seg!$F$78)*Seg!$F$89 -> 158.66848 | G77: =Seg!$E$77+Seg!$F$77 -> 293.35448 | H77: =Seg!$G$77*(1+Seg!$H$78) -> 318.59137 | I77: =Seg!$H$77*(1+Seg!$I$78) -> 342.17322 | J77: =Seg!$I$77*(1+Seg!$J$78) -> 363.39123 | K77: =Seg!$J$77*(1+Seg!$K$78) -> 381.56079 | L77: =Seg!$K$77*(1+Seg!$L$78) -> 400.63883 | M77: =Seg!$L$77*(1+Seg!$M$78) -> 420.67077 | N77: =Q!$N$10 -> 118.892 | O77: =Q!$O$10 -> 150.395 | P77: Q 頁實績；預測＝前期 ×（1＋年增）
A78: Online stores 年增 | B78: % | E78: =Seg!$E$77/Seg!$N$77-1 -> 0.13284325 | F78: =Seg!$O$77/(Q!$F$10+Q!$G$10)-1 -> 0.098038214 | G78: =Seg!$G$77/Seg!$D$77-1 -> 0.089374817 | H78: =Seg!$F$78+(g_os-Seg!$F$78)*1/4 -> 0.08602866 | I78: =Seg!$F$78+(g_os-Seg!$F$78)*2/4 -> 0.074019107 | J78: =Seg!$F$78+(g_os-Seg!$F$78)*3/4 -> 0.062009553 | K78: =Seg!$F$78+(g_os-Seg!$F$78)*4/4 -> 0.05 | L78: =g_os -> 0.05 | M78: =g_os -> 0.05 | P78: E＝1H26 對 1H25（含 Prime Day 移入 Q2）；F＝2H25 對 2H24（2H26 成長基準，Derived）；收斂到 In 頁 g_os
A79: Physical stores | B79: US$bn | C79: =Q!$D$11 -> 21.215 | D79: =Q!$E$11 -> 22.561 | E79: =Q!$P$11 -> 11.579 | F79: =Seg!$O$79*(1+Seg!$F$80)*Seg!$F$89 -> 11.621309 | G79: =Seg!$E$79+Seg!$F$79 -> 23.200309 | H79: =Seg!$G$79*(1+Seg!$H$80) -> 24.382227 | I79: =Seg!$H$79*(1+Seg!$I$80) -> 25.454136 | J79: =Seg!$I$79*(1+Seg!$J$80) -> 26.395464 | K79: =Seg!$J$79*(1+Seg!$K$80) -> 27.187328 | L79: =Seg!$K$79*(1+Seg!$L$80) -> 28.002948 | M79: =Seg!$L$79*(1+Seg!$M$80) -> 28.843037 | N79: =Q!$N$11 -> 11.128 | O79: =Q!$O$11 -> 11.433 | P79: Q 頁實績；預測＝前期 ×（1＋年增）
A80: Physical stores 年增 | B80: % | E80: =Seg!$E$79/Seg!$N$79-1 -> 0.040528397 | F80: =Seg!$O$79/(Q!$F$11+Q!$G$11)-1 -> 0.057925419 | G80: =Seg!$G$79/Seg!$D$79-1 -> 0.028336915 | H80: =Seg!$F$80+(g_ps-Seg!$F$80)*1/4 -> 0.050944064 | I80: =Seg!$F$80+(g_ps-Seg!$F$80)*2/4 -> 0.043962709 | J80: =Seg!$F$80+(g_ps-Seg!$F$80)*3/4 -> 0.036981355 | K80: =Seg!$F$80+(g_ps-Seg!$F$80)*4/4 -> 0.03 | L80: =g_ps -> 0.03 | M80: =g_ps -> 0.03 | P80: E＝1H26 對 1H25（含 Prime Day 移入 Q2）；F＝2H25 對 2H24（2H26 成長基準，Derived）；收斂到 In 頁 g_ps
A81: Third-party seller services | B81: US$bn | C81: =Q!$D$12 -> 156.146 | D81: =Q!$E$12 -> 172.162 | E81: =Q!$P$12 -> 88.358 | F81: =Seg!$O$81*(1+Seg!$F$82)*Seg!$F$89 -> 102.24578 | G81: =Seg!$E$81+Seg!$F$81 -> 190.60378 | H81: =Seg!$G$81*(1+Seg!$H$82) -> 210.60983 | I81: =Seg!$H$81*(1+Seg!$I$82) -> 230.26134 | J81: =Seg!$I$81*(1+Seg!$J$82) -> 249.06306 | K81: =Seg!$J$81*(1+Seg!$K$82) -> 266.49748 | L81: =Seg!$K$81*(1+Seg!$L$82) -> 285.1523 | M81: =Seg!$L$81*(1+Seg!$M$82) -> 305.11296 | N81: =Q!$N$12 -> 76.86 | O81: =Q!$O$12 -> 95.302 | P81: Q 頁實績；預測＝前期 ×（1＋年增）
A82: Third-party seller services 年增 | B82: % | E82: =Seg!$E$81/Seg!$N$81-1 -> 0.14959667 | F82: =Seg!$O$81/(Q!$F$12+Q!$G$12)-1 -> 0.11661531 | G82: =Seg!$G$81/Seg!$D$81-1 -> 0.10711876 | H82: =Seg!$F$82+(g_sp-Seg!$F$82)*1/4 -> 0.10496148 | I82: =Seg!$F$82+(g_sp-Seg!$F$82)*2/4 -> 0.093307654 | J82: =Seg!$F$82+(g_sp-Seg!$F$82)*3/4 -> 0.081653827 | K82: =Seg!$F$82+(g_sp-Seg!$F$82)*4/4 -> 0.07 | L82: =g_sp -> 0.07 | M82: =g_sp -> 0.07 | P82: E＝1H26 對 1H25（含 Prime Day 移入 Q2）；F＝2H25 對 2H24（2H26 成長基準，Derived）；收斂到 In 頁 g_sp
A83: Advertising services | B83: US$bn | C83: =Q!$D$13 -> 56.214 | D83: =Q!$E$13 -> 68.635 | E83: =Q!$P$13 -> 37.052 | F83: =Seg!$O$83*(1+Seg!$F$84)*Seg!$F$89 -> 46.266452 | G83: =Seg!$E$83+Seg!$F$83 -> 83.318452 | H83: =Seg!$G$83*(1+Seg!$H$84) -> 100.02806 | I83: =Seg!$H$83*(1+Seg!$I$84) -> 116.73615 | J83: =Seg!$I$83*(1+Seg!$J$84) -> 132.32242 | K83: =Seg!$J$83*(1+Seg!$K$84) -> 145.55466 | L83: =Seg!$K$83*(1+Seg!$L$84) -> 160.11012 | M83: =Seg!$L$83*(1+Seg!$M$84) -> 176.12114 | N83: =Q!$N$13 -> 29.615 | O83: =Q!$O$13 -> 39.02 | P83: Q 頁實績；預測＝前期 ×（1＋年增）
A84: Advertising services 年增 | B84: % | E84: =Seg!$E$83/Seg!$N$83-1 -> 0.25112274 | F84: =Seg!$O$83/(Q!$F$13+Q!$G$13)-1 -> 0.23406812 | G84: =Seg!$G$83/Seg!$D$83-1 -> 0.21393534 | H84: =Seg!$F$84+(g_ad-Seg!$F$84)*1/4 -> 0.20055109 | I84: =Seg!$F$84+(g_ad-Seg!$F$84)*2/4 -> 0.16703406 | J84: =Seg!$F$84+(g_ad-Seg!$F$84)*3/4 -> 0.13351703 | K84: =Seg!$F$84+(g_ad-Seg!$F$84)*4/4 -> 0.1 | L84: =g_ad -> 0.1 | M84: =g_ad -> 0.1 | P84: E＝1H26 對 1H25（含 Prime Day 移入 Q2）；F＝2H25 對 2H24（2H26 成長基準，Derived）；收斂到 In 頁 g_ad
A85: Subscription services | B85: US$bn | C85: =Q!$D$14 -> 44.374 | D85: =Q!$E$14 -> 49.619 | E85: =Q!$P$14 -> 27.157 | F85: =Seg!$O$85*(1+Seg!$F$86)*Seg!$F$89 -> 27.842149 | G85: =Seg!$E$85+Seg!$F$85 -> 54.999149 | H85: =Seg!$G$85*(1+Seg!$H$86) -> 61.22959 | I85: =Seg!$H$85*(1+Seg!$I$86) -> 67.282441 | J85: =Seg!$I$85*(1+Seg!$J$86) -> 72.962929 | K85: =Seg!$J$85*(1+Seg!$K$86) -> 78.070334 | L85: =Seg!$K$85*(1+Seg!$L$86) -> 83.535258 | M85: =Seg!$L$85*(1+Seg!$M$86) -> 89.382726 | N85: =Q!$N$14 -> 23.923 | O85: =Q!$O$14 -> 25.696 | P85: Q 頁實績；預測＝前期 ×（1＋年增）
A86: Subscription services 年增 | B86: % | E86: =Seg!$E$85/Seg!$N$85-1 -> 0.13518371 | F86: =Seg!$O$85/(Q!$F$14+Q!$G$14)-1 -> 0.12771 | G86: =Seg!$G$85/Seg!$D$85-1 -> 0.10842921 | H86: =Seg!$F$86+(g_sub-Seg!$F$86)*1/4 -> 0.1132825 | I86: =Seg!$F$86+(g_sub-Seg!$F$86)*2/4 -> 0.098854999 | J86: =Seg!$F$86+(g_sub-Seg!$F$86)*3/4 -> 0.084427499 | K86: =Seg!$F$86+(g_sub-Seg!$F$86)*4/4 -> 0.07 | L86: =g_sub -> 0.07 | M86: =g_sub -> 0.07 | P86: E＝1H26 對 1H25（含 Prime Day 移入 Q2）；F＝2H25 對 2H24（2H26 成長基準，Derived）；收斂到 In 頁 g_sub
A87: Other | B87: US$bn | C87: =Q!$D$15 -> 5.425 | D87: =Q!$E$15 -> 5.935 | E87: =Q!$P$15 -> 3.474 | F87: =Seg!$O$87*(1+Seg!$F$88)*Seg!$F$89 -> 3.2300914 | G87: =Seg!$E$87+Seg!$F$87 -> 6.7040914 | H87: =Seg!$G$87*(1+Seg!$H$88) -> 7.1706701 | I87: =Seg!$H$87*(1+Seg!$I$88) -> 7.6228817 | J87: =Seg!$I$87*(1+Seg!$J$88) -> 8.0538188 | K87: =Seg!$J$87*(1+Seg!$K$88) -> 8.4565097 | L87: =Seg!$K$87*(1+Seg!$L$88) -> 8.8793352 | M87: =Seg!$L$87*(1+Seg!$M$88) -> 9.3233019 | N87: =Q!$N$15 -> 2.811 | O87: =Q!$O$15 -> 3.124 | P87: Q 頁實績；預測＝前期 ×（1＋年增）
A88: Other 年增 | B88: % | E88: =Seg!$E$87/Seg!$N$87-1 -> 0.23585912 | F88: =Seg!$O$87/(Q!$F$15+Q!$G$15)-1 -> 0.076128143 | G88: =Seg!$G$87/Seg!$D$87-1 -> 0.12958575 | H88: =Seg!$F$88+(g_ot-Seg!$F$88)*1/4 -> 0.069596107 | I88: =Seg!$F$88+(g_ot-Seg!$F$88)*2/4 -> 0.063064072 | J88: =Seg!$F$88+(g_ot-Seg!$F$88)*3/4 -> 0.056532036 | K88: =Seg!$F$88+(g_ot-Seg!$F$88)*4/4 -> 0.05 | L88: =g_ot -> 0.05 | M88: =g_ot -> 0.05 | P88: E＝1H26 對 1H25（含 Prime Day 移入 Q2）；F＝2H25 對 2H24（2H26 成長基準，Derived）；收斂到 In 頁 g_ot
A89: 2H26 零售營收校準係數（使隱含 2026Q3 營收＝指引中點） | B89: x | F89: =(g26q3_mid*Q!$O$8/Q!$J$8-Thesis!$F$142-Thesis!$F$146)/(Seg!$O$77*(1+Seg!$F$78)+Seg!$O$79*(1+Seg!$F$80)+Seg!$O$81*(1+Seg!$F$82)+Seg!$O$83*(1+Seg!$F$84)+Seg!$O$85*(1+Seg!$F$86)+Seg!$O$87*(1+Seg!$F$88)) -> 0.96081505 | P89: 2H26 合併營收目標＝Q3 指引中點 ÷（2025Q3 占 2H25 比例）；AWS 由命題模組決定，零售六線同比例校準（Prime Day 時點已含在指引中）
A90: 零售營收線合計（＝North America＋International） | B90: US$bn | C90: =Seg!$C$77+Seg!$C$79+Seg!$C$81+Seg!$C$83+Seg!$C$85+Seg!$C$87 -> 530.403 | D90: =Seg!$D$77+Seg!$D$79+Seg!$D$81+Seg!$D$83+Seg!$D$85+Seg!$D$87 -> 588.199 | E90: =Seg!$E$77+Seg!$E$79+Seg!$E$81+Seg!$E$83+Seg!$E$85+Seg!$E$87 -> 302.306 | F90: =Seg!$F$77+Seg!$F$79+Seg!$F$81+Seg!$F$83+Seg!$F$85+Seg!$F$87 -> 349.87426 | G90: =Seg!$G$77+Seg!$G$79+Seg!$G$81+Seg!$G$83+Seg!$G$85+Seg!$G$87 -> 652.18026 | H90: =Seg!$H$77+Seg!$H$79+Seg!$H$81+Seg!$H$83+Seg!$H$85+Seg!$H$87 -> 722.01175 | I90: =Seg!$I$77+Seg!$I$79+Seg!$I$81+Seg!$I$83+Seg!$I$85+Seg!$I$87 -> 789.53017 | J90: =Seg!$J$77+Seg!$J$79+Seg!$J$81+Seg!$J$83+Seg!$J$85+Seg!$J$87 -> 852.18892 | K90: =Seg!$K$77+Seg!$K$79+Seg!$K$81+Seg!$K$83+Seg!$K$85+Seg!$K$87 -> 907.3271 | L90: =Seg!$L$77+Seg!$L$79+Seg!$L$81+Seg!$L$83+Seg!$L$85+Seg!$L$87 -> 966.31879 | M90: =Seg!$M$77+Seg!$M$79+Seg!$M$81+Seg!$M$83+Seg!$M$85+Seg!$M$87 -> 1029.4539 | N90: =Seg!$N$77+Seg!$N$79+Seg!$N$81+Seg!$N$83+Seg!$N$85+Seg!$N$87 -> 263.229 | O90: =Seg!$O$77+Seg!$O$79+Seg!$O$81+Seg!$O$83+Seg!$O$85+Seg!$O$87 -> 324.97
A91: 北美占零售營收比例（地區分攤） | B91: % | C91: =Q!$D$5/(Q!$D$5+Q!$D$6) -> 0.73057091 | D91: =Q!$E$5/(Q!$E$5+Q!$E$6) -> 0.72476322 | E91: =Q!$P$5/(Q!$P$5+Q!$P$6) -> 0.72879797 | F91: =Seg!$O$91 -> 0.71806628 | G91: =Seg!$G$92/Seg!$G$90 -> 0.72304076 | H91: =Seg!$G$91 -> 0.72304076 | I91: =Seg!$G$91 -> 0.72304076 | J91: =Seg!$G$91 -> 0.72304076 | K91: =Seg!$G$91 -> 0.72304076 | L91: =Seg!$G$91 -> 0.72304076 | M91: =Seg!$G$91 -> 0.72304076 | N91: =Q!$N$5/(Q!$N$5+Q!$N$6) -> 0.73303094 | O91: =Q!$O$5/(Q!$O$5+Q!$O$6) -> 0.71806628 | P91: 2H26＝2H25 比例；2027 起固定為 FY2026（Derived）；各營收線不分地區揭露，故以本列分攤
A92: North America | B92: US$bn | C92: =Q!$D$5 -> 387.497 | D92: =Q!$E$5 -> 426.305 | E92: =Q!$P$5 -> 220.32 | F92: =Seg!$F$90*Seg!$F$91 -> 251.23291 | G92: =Seg!$E$92+Seg!$F$92 -> 471.55291 | H92: =Seg!$H$90*Seg!$H$91 -> 522.04392 | I92: =Seg!$I$90*Seg!$I$91 -> 570.86249 | J92: =Seg!$J$90*Seg!$J$91 -> 616.16732 | K92: =Seg!$K$90*Seg!$K$91 -> 656.03447 | L92: =Seg!$L$90*Seg!$L$91 -> 698.68787 | M92: =Seg!$M$90*Seg!$M$91 -> 744.33715 | N92: =Q!$N$5 -> 192.955 | O92: =Q!$O$5 -> 233.35 | P92: 官方分部；預測＝零售營收線合計 × 北美比例
A93: International | B93: US$bn | C93: =Q!$D$6 -> 142.906 | D93: =Q!$E$6 -> 161.894 | E93: =Q!$P$6 -> 81.986 | F93: =Seg!$F$90*(1-Seg!$F$91) -> 98.64135 | G93: =Seg!$E$93+Seg!$F$93 -> 180.62735 | H93: =Seg!$H$90*(1-Seg!$H$91) -> 199.96783 | I93: =Seg!$I$90*(1-Seg!$I$91) -> 218.66768 | J93: =Seg!$J$90*(1-Seg!$J$91) -> 236.0216 | K93: =Seg!$K$90*(1-Seg!$K$91) -> 251.29263 | L93: =Seg!$L$90*(1-Seg!$L$91) -> 267.63092 | M93: =Seg!$M$90*(1-Seg!$M$91) -> 285.11678 | N93: =Q!$N$6 -> 70.274 | O93: =Q!$O$6 -> 91.62 | P93: 官方分部；預測＝零售營收線合計 ×（1 − 北美比例）
A94: 廣告營收歸北美（＝廣告 × 北美比例） | B94: US$bn | C94: =Seg!$C$83*Seg!$C$91 -> 41.068313 | D94: =Seg!$D$83*Seg!$D$91 -> 49.744123 | E94: =Seg!$E$83*Seg!$E$91 -> 27.003422 | F94: =Seg!$F$83*Seg!$F$91 -> 33.222379 | G94: =Seg!$G$83*Seg!$G$91 -> 60.242637 | H94: =Seg!$H$83*Seg!$H$91 -> 72.324363 | I94: =Seg!$I$83*Seg!$I$91 -> 84.404996 | J94: =Seg!$J$83*Seg!$J$91 -> 95.6745 | K94: =Seg!$K$83*Seg!$K$91 -> 105.24195 | L94: =Seg!$L$83*Seg!$L$91 -> 115.76615 | M94: =Seg!$M$83*Seg!$M$91 -> 127.34276 | N94: =Seg!$N$83*Seg!$N$91 -> 21.708711 | O94: =Seg!$O$83*Seg!$O$91 -> 28.018946 | P94: 廣告營收依零售營收的地區比例分攤（Assumed；公司未分地區揭露）
A95: 廣告營收歸國際 | B95: US$bn | C95: =Seg!$C$83-Seg!$C$94 -> 15.145687 | D95: =Seg!$D$83-Seg!$D$94 -> 18.890877 | E95: =Seg!$E$83-Seg!$E$94 -> 10.048578 | F95: =Seg!$F$83-Seg!$F$94 -> 13.044073 | G95: =Seg!$G$83-Seg!$G$94 -> 23.075815 | H95: =Seg!$H$83-Seg!$H$94 -> 27.703695 | I95: =Seg!$I$83-Seg!$I$94 -> 32.331156 | J95: =Seg!$J$83-Seg!$J$94 -> 36.647916 | K95: =Seg!$K$83-Seg!$K$94 -> 40.312708 | L95: =Seg!$L$83-Seg!$L$94 -> 44.343979 | M95: =Seg!$M$83-Seg!$M$94 -> 48.778376 | N95: =Seg!$N$83-Seg!$N$94 -> 7.9062889 | O95: =Seg!$O$83-Seg!$O$94 -> 11.001054
A96: 2. AWS（命題子列＋AWS 其他）與合併營收
A97: AWS AI（命題子列） | B97: US$bn | C97: =Thesis!$C$142 -> 2.3210054 | D97: =Thesis!$D$142 -> 8.7037701 | E97: =Thesis!$E$142 -> 8.510353 | F97: =Thesis!$F$142 -> 14.137417 | G97: =Thesis!$G$142 -> 22.64777 | H97: =Thesis!$H$142 -> 53.42229 | I97: =Thesis!$I$142 -> 87.799746 | J97: =Thesis!$J$142 -> 122.33014 | K97: =Thesis!$K$142 -> 151.78847 | L97: =Thesis!$L$142 -> 171.14863 | M97: =Thesis!$M$142 -> 180.38574 | N97: =Thesis!$N$142 -> 3.0463195 | O97: =Thesis!$O$142 -> 5.6574506 | P97: Thesis 頁
A98: AWS 其他 | B98: US$bn | C98: =Thesis!$C$146 -> 105.23499 | D98: =Thesis!$D$146 -> 120.02123 | E98: =Thesis!$E$146 -> 71.308647 | F98: =Thesis!$F$146 -> 71.7693 | G98: =Thesis!$G$146 -> 143.07795 | H98: =Thesis!$H$146 -> 161.01708 | I98: =Thesis!$I$146 -> 178.76976 | J98: =Thesis!$J$146 -> 195.77554 | K98: =Thesis!$K$146 -> 211.43758 | L98: =Thesis!$L$146 -> 228.35259 | M98: =Thesis!$M$146 -> 246.62079 | N98: =Thesis!$N$146 -> 57.09368 | O98: =Thesis!$O$146 -> 62.927549 | P98: Thesis 頁
A99: AWS | B99: US$bn | C99: =Q!$D$7 -> 107.556 | D99: =Q!$E$7 -> 128.725 | E99: =Q!$P$7 -> 79.819 | F99: =Seg!$F$97+Seg!$F$98 -> 85.906717 | G99: =Seg!$G$97+Seg!$G$98 -> 165.72572 | H99: =Seg!$H$97+Seg!$H$98 -> 214.43937 | I99: =Seg!$I$97+Seg!$I$98 -> 266.56951 | J99: =Seg!$J$97+Seg!$J$98 -> 318.10568 | K99: =Seg!$K$97+Seg!$K$98 -> 363.22605 | L99: =Seg!$L$97+Seg!$L$98 -> 399.50121 | M99: =Seg!$M$97+Seg!$M$98 -> 427.00653 | N99: =Q!$N$7 -> 60.14 | O99: =Q!$O$7 -> 68.585 | P99: 官方分部＝AWS 營收線
A100: 合併營收（實績＝公司揭露；預測＝營收線加總） | B100: US$bn | C100: =Q!$D$8 -> 637.959 | D100: =Q!$E$8 -> 716.924 | E100: =Q!$P$8 -> 382.125 | F100: =Seg!$F$90+Seg!$F$99 -> 435.78098 | G100: =Seg!$G$90+Seg!$G$99 -> 817.90598 | H100: =Seg!$H$90+Seg!$H$99 -> 936.45112 | I100: =Seg!$I$90+Seg!$I$99 -> 1056.0997 | J100: =Seg!$J$90+Seg!$J$99 -> 1170.2946 | K100: =Seg!$K$90+Seg!$K$99 -> 1270.5531 | L100: =Seg!$L$90+Seg!$L$99 -> 1365.82 | M100: =Seg!$M$90+Seg!$M$99 -> 1456.4605 | N100: =Q!$N$8 -> 323.369 | O100: =Q!$O$8 -> 393.555
A101: 檢查（情境 C）：零售營收線合計 − (North America＋International) | B101: US$bn | C101: =Seg!$C$90-(Seg!$C$92+Seg!$C$93) -> 0 | D101: =Seg!$D$90-(Seg!$D$92+Seg!$D$93) -> 0 | E101: =Seg!$E$90-(Seg!$E$92+Seg!$E$93) -> 0 | F101: =Seg!$F$90-(Seg!$F$92+Seg!$F$93) -> 0 | G101: =Seg!$G$90-(Seg!$G$92+Seg!$G$93) -> 0 | H101: =Seg!$H$90-(Seg!$H$92+Seg!$H$93) -> 0 | I101: =Seg!$I$90-(Seg!$I$92+Seg!$I$93) -> 0 | J101: =Seg!$J$90-(Seg!$J$92+Seg!$J$93) -> 0 | K101: =Seg!$K$90-(Seg!$K$92+Seg!$K$93) -> 0 | L101: =Seg!$L$90-(Seg!$L$92+Seg!$L$93) -> 0 | M101: =Seg!$M$90-(Seg!$M$92+Seg!$M$93) -> 0 | N101: =Seg!$N$90-(Seg!$N$92+Seg!$N$93) -> 0 | O101: =Seg!$O$90-(Seg!$O$92+Seg!$O$93) -> 0
A102: 檢查（情境 C）：AWS AI＋AWS 其他 − AWS | B102: US$bn | C102: =Seg!$C$97+Seg!$C$98-Seg!$C$99 -> 0 | D102: =Seg!$D$97+Seg!$D$98-Seg!$D$99 -> 0 | E102: =Seg!$E$97+Seg!$E$98-Seg!$E$99 -> 0 | F102: =Seg!$F$97+Seg!$F$98-Seg!$F$99 -> 0 | G102: =Seg!$G$97+Seg!$G$98-Seg!$G$99 -> 0 | H102: =Seg!$H$97+Seg!$H$98-Seg!$H$99 -> 0 | I102: =Seg!$I$97+Seg!$I$98-Seg!$I$99 -> 0 | J102: =Seg!$J$97+Seg!$J$98-Seg!$J$99 -> 0 | K102: =Seg!$K$97+Seg!$K$98-Seg!$K$99 -> 0 | L102: =Seg!$L$97+Seg!$L$98-Seg!$L$99 -> 0 | M102: =Seg!$M$97+Seg!$M$98-Seg!$M$99 -> 0 | N102: =Seg!$N$97+Seg!$N$98-Seg!$N$99 -> 0 | O102: =Seg!$O$97+Seg!$O$98-Seg!$O$99 -> 0
A103: 檢查（情境 C）：分部合計 − 合併營收 | B103: US$bn | C103: =Seg!$C$92+Seg!$C$93+Seg!$C$99-Seg!$C$100 -> 0 | D103: =Seg!$D$92+Seg!$D$93+Seg!$D$99-Seg!$D$100 -> 0 | E103: =Seg!$E$92+Seg!$E$93+Seg!$E$99-Seg!$E$100 -> 0 | F103: =Seg!$F$92+Seg!$F$93+Seg!$F$99-Seg!$F$100 -> 0 | G103: =Seg!$G$92+Seg!$G$93+Seg!$G$99-Seg!$G$100 -> 0 | H103: =Seg!$H$92+Seg!$H$93+Seg!$H$99-Seg!$H$100 -> 0 | I103: =Seg!$I$92+Seg!$I$93+Seg!$I$99-Seg!$I$100 -> 0 | J103: =Seg!$J$92+Seg!$J$93+Seg!$J$99-Seg!$J$100 -> 0 | K103: =Seg!$K$92+Seg!$K$93+Seg!$K$99-Seg!$K$100 -> 0 | L103: =Seg!$L$92+Seg!$L$93+Seg!$L$99-Seg!$L$100 -> 0 | M103: =Seg!$M$92+Seg!$M$93+Seg!$M$99-Seg!$M$100 -> 0 | N103: =Seg!$N$92+Seg!$N$93+Seg!$N$99-Seg!$N$100 -> 0 | O103: =Seg!$O$92+Seg!$O$93+Seg!$O$99-Seg!$O$100 -> 0
A104: 合併營收年增 | B104: % | G104: =Seg!$G$100/Seg!$D$100-1 -> 0.1408545 | H104: =Seg!$H$100/Seg!$G$100-1 -> 0.14493737 | I104: =Seg!$I$100/Seg!$H$100-1 -> 0.12776808 | J104: =Seg!$J$100/Seg!$I$100-1 -> 0.10812892 | K104: =Seg!$K$100/Seg!$J$100-1 -> 0.085669497 | L104: =Seg!$L$100/Seg!$K$100-1 -> 0.07498062 | M104: =Seg!$M$100/Seg!$L$100-1 -> 0.0663634
A105: AWS 占合併營收 | B105: % | C105: =Seg!$C$99/Seg!$C$100 -> 0.16859391 | D105: =Seg!$D$99/Seg!$D$100 -> 0.17955181 | E105: =Seg!$E$99/Seg!$E$100 -> 0.20888191 | F105: =Seg!$F$99/Seg!$F$100 -> 0.19713278 | G105: =Seg!$G$99/Seg!$G$100 -> 0.20262197 | H105: =Seg!$H$99/Seg!$H$100 -> 0.22899152 | I105: =Seg!$I$99/Seg!$I$100 -> 0.25240942 | J105: =Seg!$J$99/Seg!$J$100 -> 0.27181675 | K105: =Seg!$K$99/Seg!$K$100 -> 0.28588025 | L105: =Seg!$L$99/Seg!$L$100 -> 0.29249917 | M105: =Seg!$M$99/Seg!$M$100 -> 0.293181 | N105: =Seg!$N$99/Seg!$N$100 -> 0.18597948 | O105: =Seg!$O$99/Seg!$O$100 -> 0.17427043
A106: AWS AI 占 AWS | B106: % | C106: =Seg!$C$97/Seg!$C$99 -> 0.021579506 | D106: =Seg!$D$97/Seg!$D$99 -> 0.067615227 | E106: =Seg!$E$97/Seg!$E$99 -> 0.10662064 | F106: =Seg!$F$97/Seg!$F$99 -> 0.16456708 | G106: =Seg!$G$97/Seg!$G$99 -> 0.13665815 | H106: =Seg!$H$97/Seg!$H$99 -> 0.24912539 | I106: =Seg!$I$97/Seg!$I$99 -> 0.32936906 | J106: =Seg!$J$97/Seg!$J$99 -> 0.38455817 | K106: =Seg!$K$97/Seg!$K$99 -> 0.41788982 | L106: =Seg!$L$97/Seg!$L$99 -> 0.42840577 | M106: =Seg!$M$97/Seg!$M$99 -> 0.42244258 | N106: =Seg!$N$97/Seg!$N$99 -> 0.0506538 | O106: =Seg!$O$97/Seg!$O$99 -> 0.082488162

Sheet PL
A1: PL — 分部營收 → 分部營業利益 → 合併營業利益 → 業外、稅 → 淨利 → EPS。廣告利潤率 m_ad 驅動北美／國際利益率（廣告營收依零售地區比例分攤；零售本業利益率＝分部利益扣廣告利潤後的殘差）
A2: 第 4–10 列：跨情境核對（三情境絕對值合計；tools/segment_check 讀本區）；實績欄為公司揭露值的核對
A4: 跨情境核對（三情境絕對值合計；應全為 0）
A5: 項目 | B5: 單位 | C5: FY2024A | D5: FY2025A | E5: 1H26A | F5: 2H26E | G5: FY2026E（1H 實績＋2H 模型） | H5: FY2027E | I5: FY2028E | J5: FY2029E | K5: FY2030E | L5: FY2031E | M5: FY2032E | N5: 1H25A | O5: 2H25A | P5: 說明
A6: 檢查：零售營收線合計 − (North America＋International) | B6: US$bn | C6: =ABS(PL!$C$28)+ABS(PL!$C$98)+ABS(PL!$C$168) -> 0 | D6: =ABS(PL!$D$28)+ABS(PL!$D$98)+ABS(PL!$D$168) -> 0 | E6: =ABS(PL!$E$28)+ABS(PL!$E$98)+ABS(PL!$E$168) -> 0 | F6: =ABS(PL!$F$28)+ABS(PL!$F$98)+ABS(PL!$F$168) -> 0 | G6: =ABS(PL!$G$28)+ABS(PL!$G$98)+ABS(PL!$G$168) -> 0 | H6: =ABS(PL!$H$28)+ABS(PL!$H$98)+ABS(PL!$H$168) -> 0 | I6: =ABS(PL!$I$28)+ABS(PL!$I$98)+ABS(PL!$I$168) -> 0 | J6: =ABS(PL!$J$28)+ABS(PL!$J$98)+ABS(PL!$J$168) -> 0 | K6: =ABS(PL!$K$28)+ABS(PL!$K$98)+ABS(PL!$K$168) -> 0 | L6: =ABS(PL!$L$28)+ABS(PL!$L$98)+ABS(PL!$L$168) -> 0 | M6: =ABS(PL!$M$28)+ABS(PL!$M$98)+ABS(PL!$M$168) -> 0 | N6: =ABS(PL!$N$28)+ABS(PL!$N$98)+ABS(PL!$N$168) -> 0 | O6: =ABS(PL!$O$28)+ABS(PL!$O$98)+ABS(PL!$O$168) -> 0
A7: 檢查：AWS AI＋AWS 其他 − AWS | B7: US$bn | C7: =ABS(PL!$C$29)+ABS(PL!$C$99)+ABS(PL!$C$169) -> 0 | D7: =ABS(PL!$D$29)+ABS(PL!$D$99)+ABS(PL!$D$169) -> 0 | E7: =ABS(PL!$E$29)+ABS(PL!$E$99)+ABS(PL!$E$169) -> 0 | F7: =ABS(PL!$F$29)+ABS(PL!$F$99)+ABS(PL!$F$169) -> 0 | G7: =ABS(PL!$G$29)+ABS(PL!$G$99)+ABS(PL!$G$169) -> 0 | H7: =ABS(PL!$H$29)+ABS(PL!$H$99)+ABS(PL!$H$169) -> 0 | I7: =ABS(PL!$I$29)+ABS(PL!$I$99)+ABS(PL!$I$169) -> 0 | J7: =ABS(PL!$J$29)+ABS(PL!$J$99)+ABS(PL!$J$169) -> 0 | K7: =ABS(PL!$K$29)+ABS(PL!$K$99)+ABS(PL!$K$169) -> 0 | L7: =ABS(PL!$L$29)+ABS(PL!$L$99)+ABS(PL!$L$169) -> 0 | M7: =ABS(PL!$M$29)+ABS(PL!$M$99)+ABS(PL!$M$169) -> 0 | N7: =ABS(PL!$N$29)+ABS(PL!$N$99)+ABS(PL!$N$169) -> 0 | O7: =ABS(PL!$O$29)+ABS(PL!$O$99)+ABS(PL!$O$169) -> 0
A8: 檢查：營收線合計（含 AWS）− 合併營收 | B8: US$bn | C8: =ABS(PL!$C$30)+ABS(PL!$C$100)+ABS(PL!$C$170) -> 0 | D8: =ABS(PL!$D$30)+ABS(PL!$D$100)+ABS(PL!$D$170) -> 0 | E8: =ABS(PL!$E$30)+ABS(PL!$E$100)+ABS(PL!$E$170) -> 0 | F8: =ABS(PL!$F$30)+ABS(PL!$F$100)+ABS(PL!$F$170) -> 0 | G8: =ABS(PL!$G$30)+ABS(PL!$G$100)+ABS(PL!$G$170) -> 0 | H8: =ABS(PL!$H$30)+ABS(PL!$H$100)+ABS(PL!$H$170) -> 0 | I8: =ABS(PL!$I$30)+ABS(PL!$I$100)+ABS(PL!$I$170) -> 0 | J8: =ABS(PL!$J$30)+ABS(PL!$J$100)+ABS(PL!$J$170) -> 0 | K8: =ABS(PL!$K$30)+ABS(PL!$K$100)+ABS(PL!$K$170) -> 0 | L8: =ABS(PL!$L$30)+ABS(PL!$L$100)+ABS(PL!$L$170) -> 0 | M8: =ABS(PL!$M$30)+ABS(PL!$M$100)+ABS(PL!$M$170) -> 0 | N8: =ABS(PL!$N$30)+ABS(PL!$N$100)+ABS(PL!$N$170) -> 0 | O8: =ABS(PL!$O$30)+ABS(PL!$O$100)+ABS(PL!$O$170) -> 0
A9: 檢查：分部合計 − 合併營收 | B9: US$bn | C9: =ABS(PL!$C$31)+ABS(PL!$C$101)+ABS(PL!$C$171) -> 0 | D9: =ABS(PL!$D$31)+ABS(PL!$D$101)+ABS(PL!$D$171) -> 0 | E9: =ABS(PL!$E$31)+ABS(PL!$E$101)+ABS(PL!$E$171) -> 0 | F9: =ABS(PL!$F$31)+ABS(PL!$F$101)+ABS(PL!$F$171) -> 0 | G9: =ABS(PL!$G$31)+ABS(PL!$G$101)+ABS(PL!$G$171) -> 0 | H9: =ABS(PL!$H$31)+ABS(PL!$H$101)+ABS(PL!$H$171) -> 0 | I9: =ABS(PL!$I$31)+ABS(PL!$I$101)+ABS(PL!$I$171) -> 0 | J9: =ABS(PL!$J$31)+ABS(PL!$J$101)+ABS(PL!$J$171) -> 0 | K9: =ABS(PL!$K$31)+ABS(PL!$K$101)+ABS(PL!$K$171) -> 0 | L9: =ABS(PL!$L$31)+ABS(PL!$L$101)+ABS(PL!$L$171) -> 0 | M9: =ABS(PL!$M$31)+ABS(PL!$M$101)+ABS(PL!$M$171) -> 0 | N9: =ABS(PL!$N$31)+ABS(PL!$N$101)+ABS(PL!$N$171) -> 0 | O9: =ABS(PL!$O$31)+ABS(PL!$O$101)+ABS(PL!$O$171) -> 0
A10: 檢查：分部營業利益合計 − 合併營業利益 | B10: US$bn | C10: =ABS(PL!$C$48)+ABS(PL!$C$118)+ABS(PL!$C$188) -> 0 | D10: =ABS(PL!$D$48)+ABS(PL!$D$118)+ABS(PL!$D$188) -> 0 | E10: =ABS(PL!$E$48)+ABS(PL!$E$118)+ABS(PL!$E$188) -> 0 | F10: =ABS(PL!$F$48)+ABS(PL!$F$118)+ABS(PL!$F$188) -> 0 | G10: =ABS(PL!$G$48)+ABS(PL!$G$118)+ABS(PL!$G$188) -> 0 | H10: =ABS(PL!$H$48)+ABS(PL!$H$118)+ABS(PL!$H$188) -> 0 | I10: =ABS(PL!$I$48)+ABS(PL!$I$118)+ABS(PL!$I$188) -> 0 | J10: =ABS(PL!$J$48)+ABS(PL!$J$118)+ABS(PL!$J$188) -> 0 | K10: =ABS(PL!$K$48)+ABS(PL!$K$118)+ABS(PL!$K$188) -> 0 | L10: =ABS(PL!$L$48)+ABS(PL!$L$118)+ABS(PL!$L$188) -> 0 | M10: =ABS(PL!$M$48)+ABS(PL!$M$118)+ABS(PL!$M$188) -> 0 | N10: =ABS(PL!$N$48)+ABS(PL!$N$118)+ABS(PL!$N$188) -> 0 | O10: =ABS(PL!$O$48)+ABS(PL!$O$118)+ABS(PL!$O$188) -> 0
A12: PL｜情境 A（樂觀）：分部營收 → 分部營業利益 → 合併營業利益 → 業外、稅 → 淨利 → EPS
A13: 項目 | B13: 單位 | C13: FY2024A | D13: FY2025A | E13: 1H26A | F13: 2H26E | G13: FY2026E（1H 實績＋2H 模型） | H13: FY2027E | I13: FY2028E | J13: FY2029E | K13: FY2030E | L13: FY2031E | M13: FY2032E | N13: 1H25A | O13: 2H25A | P13: 說明 | R13: 2023 | S13: 2024 | T13: 2025 | U13: 2026 | V13: 2027 | W13: 2028 | X13: 2029 | Y13: 2030 | Z13: 2031 | AA13: 2032
A14: 1. 營收（10-K 營收線與官方分部）
A15: Online stores | B15: US$bn | C15: =Seg!$C$7 -> 247.029 | D15: =Seg!$D$7 -> 269.287 | E15: =Seg!$E$7 -> 134.686 | F15: =Seg!$F$7 -> 157.02081 | G15: =Seg!$G$7 -> 291.70681 | H15: =Seg!$H$7 -> 316.80195 | I15: =Seg!$I$7 -> 340.25135 | J15: =Seg!$J$7 -> 361.35019 | K15: =Seg!$K$7 -> 379.4177 | L15: =Seg!$L$7 -> 398.38858 | M15: =Seg!$M$7 -> 418.30801 | N15: =Seg!$N$7 -> 118.892 | O15: =Seg!$O$7 -> 150.395
A16: Physical stores | B16: US$bn | C16: =Seg!$C$9 -> 21.215 | D16: =Seg!$D$9 -> 22.561 | E16: =Seg!$E$9 -> 11.579 | F16: =Seg!$F$9 -> 11.500629 | G16: =Seg!$G$9 -> 23.079629 | H16: =Seg!$H$9 -> 24.2554 | I16: =Seg!$I$9 -> 25.321733 | J16: =Seg!$J$9 -> 26.258165 | K16: =Seg!$K$9 -> 27.04591 | L16: =Seg!$L$9 -> 27.857287 | M16: =Seg!$M$9 -> 28.693005 | N16: =Seg!$N$9 -> 11.128 | O16: =Seg!$O$9 -> 11.433
A17: Third-party seller services | B17: US$bn | C17: =Seg!$C$11 -> 156.146 | D17: =Seg!$D$11 -> 172.162 | E17: =Seg!$E$11 -> 88.358 | F17: =Seg!$F$11 -> 101.18402 | G17: =Seg!$G$11 -> 189.54202 | H17: =Seg!$H$11 -> 209.43664 | I17: =Seg!$I$11 -> 228.97868 | J17: =Seg!$J$11 -> 247.67566 | K17: =Seg!$K$11 -> 265.01296 | L17: =Seg!$L$11 -> 283.56387 | M17: =Seg!$M$11 -> 303.41334 | N17: =Seg!$N$11 -> 76.86 | O17: =Seg!$O$11 -> 95.302
A18: Advertising services | B18: US$bn | C18: =Seg!$C$13 -> 56.214 | D18: =Seg!$D$13 -> 68.635 | E18: =Seg!$E$13 -> 37.052 | F18: =Seg!$F$13 -> 45.786005 | G18: =Seg!$G$13 -> 82.838005 | H18: =Seg!$H$13 -> 99.451258 | I18: =Seg!$I$13 -> 116.06301 | J18: =Seg!$J$13 -> 131.55939 | K18: =Seg!$K$13 -> 144.71533 | L18: =Seg!$L$13 -> 159.18687 | M18: =Seg!$M$13 -> 175.10555 | N18: =Seg!$N$13 -> 29.615 | O18: =Seg!$O$13 -> 39.02
A19: Subscription services | B19: US$bn | C19: =Seg!$C$15 -> 44.374 | D19: =Seg!$D$15 -> 49.619 | E19: =Seg!$E$15 -> 27.157 | F19: =Seg!$F$15 -> 27.553026 | G19: =Seg!$G$15 -> 54.710026 | H19: =Seg!$H$15 -> 60.907715 | I19: =Seg!$I$15 -> 66.928747 | J19: =Seg!$J$15 -> 72.579374 | K19: =Seg!$K$15 -> 77.65993 | L19: =Seg!$L$15 -> 83.096125 | M19: =Seg!$M$15 -> 88.912854 | N19: =Seg!$N$15 -> 23.923 | O19: =Seg!$O$15 -> 25.696
A20: Other | B20: US$bn | C20: =Seg!$C$17 -> 5.425 | D20: =Seg!$D$17 -> 5.935 | E20: =Seg!$E$17 -> 3.474 | F20: =Seg!$F$17 -> 3.196549 | G20: =Seg!$G$17 -> 6.670549 | H20: =Seg!$H$17 -> 7.1347933 | I20: =Seg!$I$17 -> 7.5847424 | J20: =Seg!$J$17 -> 8.0135233 | K20: =Seg!$K$17 -> 8.4141995 | L20: =Seg!$L$17 -> 8.8349095 | M20: =Seg!$M$17 -> 9.2766549 | N20: =Seg!$N$17 -> 2.811 | O20: =Seg!$O$17 -> 3.124
A21: AWS（營收線＝分部） | B21: US$bn | C21: =Seg!$C$29 -> 107.556 | D21: =Seg!$D$29 -> 128.725 | E21: =Seg!$E$29 -> 79.819 | F21: =Seg!$F$29 -> 89.539932 | G21: =Seg!$G$29 -> 169.35893 | H21: =Seg!$H$29 -> 244.10095 | I21: =Seg!$I$29 -> 326.84605 | J21: =Seg!$J$29 -> 409.13338 | K21: =Seg!$K$29 -> 480.48296 | L21: =Seg!$L$29 -> 533.98446 | M21: =Seg!$M$29 -> 569.69108 | N21: =Seg!$N$29 -> 60.14 | O21: =Seg!$O$29 -> 68.585
A22: North America | B22: US$bn | C22: =Seg!$C$22 -> 387.497 | D22: =Seg!$D$22 -> 426.305 | E22: =Seg!$E$22 -> 220.32 | F22: =Seg!$F$22 -> 248.62402 | G22: =Seg!$G$22 -> 468.94402 | H22: =Seg!$H$22 -> 519.15442 | I22: =Seg!$I$22 -> 567.70161 | J22: =Seg!$J$22 -> 612.7546 | K22: =Seg!$K$22 -> 652.40025 | L22: =Seg!$L$22 -> 694.81662 | M22: =Seg!$M$22 -> 740.21216 | N22: =Seg!$N$22 -> 192.955 | O22: =Seg!$O$22 -> 233.35
A23: International | B23: US$bn | C23: =Seg!$C$23 -> 142.906 | D23: =Seg!$D$23 -> 161.894 | E23: =Seg!$E$23 -> 81.986 | F23: =Seg!$F$23 -> 97.617024 | G23: =Seg!$G$23 -> 179.60302 | H23: =Seg!$H$23 -> 198.83334 | I23: =Seg!$I$23 -> 217.42665 | J23: =Seg!$J$23 -> 234.6817 | K23: =Seg!$K$23 -> 249.86577 | L23: =Seg!$L$23 -> 266.11101 | M23: =Seg!$M$23 -> 283.49725 | N23: =Seg!$N$23 -> 70.274 | O23: =Seg!$O$23 -> 91.62
A24: AWS | B24: US$bn | C24: =Seg!$C$29 -> 107.556 | D24: =Seg!$D$29 -> 128.725 | E24: =Seg!$E$29 -> 79.819 | F24: =Seg!$F$29 -> 89.539932 | G24: =Seg!$G$29 -> 169.35893 | H24: =Seg!$H$29 -> 244.10095 | I24: =Seg!$I$29 -> 326.84605 | J24: =Seg!$J$29 -> 409.13338 | K24: =Seg!$K$29 -> 480.48296 | L24: =Seg!$L$29 -> 533.98446 | M24: =Seg!$M$29 -> 569.69108 | N24: =Seg!$N$29 -> 60.14 | O24: =Seg!$O$29 -> 68.585
A25: AWS AI（命題子列） | B25: US$bn | C25: =Seg!$C$27 -> 2.3210054 | D25: =Seg!$D$27 -> 8.7037701 | E25: =Seg!$E$27 -> 8.510353 | F25: =Seg!$F$27 -> 17.770633 | G25: =Seg!$G$27 -> 26.280986 | H25: =Seg!$H$27 -> 83.083874 | I25: =Seg!$I$27 -> 148.07629 | J25: =Seg!$J$27 -> 213.35784 | K25: =Seg!$K$27 -> 269.04538 | L25: =Seg!$L$27 -> 305.63187 | M25: =Seg!$M$27 -> 323.07029 | N25: =Seg!$N$27 -> 3.0463195 | O25: =Seg!$O$27 -> 5.6574506
A26: AWS 其他 | B26: US$bn | C26: =Seg!$C$28 -> 105.23499 | D26: =Seg!$D$28 -> 120.02123 | E26: =Seg!$E$28 -> 71.308647 | F26: =Seg!$F$28 -> 71.7693 | G26: =Seg!$G$28 -> 143.07795 | H26: =Seg!$H$28 -> 161.01708 | I26: =Seg!$I$28 -> 178.76976 | J26: =Seg!$J$28 -> 195.77554 | K26: =Seg!$K$28 -> 211.43758 | L26: =Seg!$L$28 -> 228.35259 | M26: =Seg!$M$28 -> 246.62079 | N26: =Seg!$N$28 -> 57.09368 | O26: =Seg!$O$28 -> 62.927549
A27: 合併營收 | B27: US$bn | C27: =Seg!$C$30 -> 637.959 | D27: =Seg!$D$30 -> 716.924 | E27: =Seg!$E$30 -> 382.125 | F27: =Seg!$F$30 -> 435.78098 | G27: =Seg!$G$30 -> 817.90598 | H27: =Seg!$H$30 -> 962.08871 | I27: =Seg!$I$30 -> 1111.9743 | J27: =Seg!$J$30 -> 1256.5697 | K27: =Seg!$K$30 -> 1382.749 | L27: =Seg!$L$30 -> 1494.9121 | M27: =Seg!$M$30 -> 1593.4005 | N27: =Seg!$N$30 -> 323.369 | O27: =Seg!$O$30 -> 393.555
A28: 檢查（情境 A）：零售營收線合計 − (North America＋International) | B28: US$bn | C28: =PL!$C$15+PL!$C$16+PL!$C$17+PL!$C$18+PL!$C$19+PL!$C$20-(PL!$C$22+PL!$C$23) -> 0 | D28: =PL!$D$15+PL!$D$16+PL!$D$17+PL!$D$18+PL!$D$19+PL!$D$20-(PL!$D$22+PL!$D$23) -> 0 | E28: =PL!$E$15+PL!$E$16+PL!$E$17+PL!$E$18+PL!$E$19+PL!$E$20-(PL!$E$22+PL!$E$23) -> 0 | F28: =PL!$F$15+PL!$F$16+PL!$F$17+PL!$F$18+PL!$F$19+PL!$F$20-(PL!$F$22+PL!$F$23) -> 0 | G28: =PL!$G$15+PL!$G$16+PL!$G$17+PL!$G$18+PL!$G$19+PL!$G$20-(PL!$G$22+PL!$G$23) -> 0 | H28: =PL!$H$15+PL!$H$16+PL!$H$17+PL!$H$18+PL!$H$19+PL!$H$20-(PL!$H$22+PL!$H$23) -> 0 | I28: =PL!$I$15+PL!$I$16+PL!$I$17+PL!$I$18+PL!$I$19+PL!$I$20-(PL!$I$22+PL!$I$23) -> 0 | J28: =PL!$J$15+PL!$J$16+PL!$J$17+PL!$J$18+PL!$J$19+PL!$J$20-(PL!$J$22+PL!$J$23) -> 0 | K28: =PL!$K$15+PL!$K$16+PL!$K$17+PL!$K$18+PL!$K$19+PL!$K$20-(PL!$K$22+PL!$K$23) -> 0 | L28: =PL!$L$15+PL!$L$16+PL!$L$17+PL!$L$18+PL!$L$19+PL!$L$20-(PL!$L$22+PL!$L$23) -> 0 | M28: =PL!$M$15+PL!$M$16+PL!$M$17+PL!$M$18+PL!$M$19+PL!$M$20-(PL!$M$22+PL!$M$23) -> 0 | N28: =PL!$N$15+PL!$N$16+PL!$N$17+PL!$N$18+PL!$N$19+PL!$N$20-(PL!$N$22+PL!$N$23) -> 0 | O28: =PL!$O$15+PL!$O$16+PL!$O$17+PL!$O$18+PL!$O$19+PL!$O$20-(PL!$O$22+PL!$O$23) -> 0
A29: 檢查（情境 A）：AWS AI＋AWS 其他 − AWS | B29: US$bn | C29: =PL!$C$25+PL!$C$26-PL!$C$24 -> 0 | D29: =PL!$D$25+PL!$D$26-PL!$D$24 -> 0 | E29: =PL!$E$25+PL!$E$26-PL!$E$24 -> 0 | F29: =PL!$F$25+PL!$F$26-PL!$F$24 -> 0 | G29: =PL!$G$25+PL!$G$26-PL!$G$24 -> 0 | H29: =PL!$H$25+PL!$H$26-PL!$H$24 -> 0 | I29: =PL!$I$25+PL!$I$26-PL!$I$24 -> 0 | J29: =PL!$J$25+PL!$J$26-PL!$J$24 -> 0 | K29: =PL!$K$25+PL!$K$26-PL!$K$24 -> 0 | L29: =PL!$L$25+PL!$L$26-PL!$L$24 -> 0 | M29: =PL!$M$25+PL!$M$26-PL!$M$24 -> 0 | N29: =PL!$N$25+PL!$N$26-PL!$N$24 -> 0 | O29: =PL!$O$25+PL!$O$26-PL!$O$24 -> 0
A30: 檢查（情境 A）：營收線合計（含 AWS）− 合併營收 | B30: US$bn | C30: =PL!$C$15+PL!$C$16+PL!$C$17+PL!$C$18+PL!$C$19+PL!$C$20+PL!$C$21-PL!$C$27 -> 0 | D30: =PL!$D$15+PL!$D$16+PL!$D$17+PL!$D$18+PL!$D$19+PL!$D$20+PL!$D$21-PL!$D$27 -> 0 | E30: =PL!$E$15+PL!$E$16+PL!$E$17+PL!$E$18+PL!$E$19+PL!$E$20+PL!$E$21-PL!$E$27 -> 0 | F30: =PL!$F$15+PL!$F$16+PL!$F$17+PL!$F$18+PL!$F$19+PL!$F$20+PL!$F$21-PL!$F$27 -> 0 | G30: =PL!$G$15+PL!$G$16+PL!$G$17+PL!$G$18+PL!$G$19+PL!$G$20+PL!$G$21-PL!$G$27 -> 0 | H30: =PL!$H$15+PL!$H$16+PL!$H$17+PL!$H$18+PL!$H$19+PL!$H$20+PL!$H$21-PL!$H$27 -> 0 | I30: =PL!$I$15+PL!$I$16+PL!$I$17+PL!$I$18+PL!$I$19+PL!$I$20+PL!$I$21-PL!$I$27 -> 0 | J30: =PL!$J$15+PL!$J$16+PL!$J$17+PL!$J$18+PL!$J$19+PL!$J$20+PL!$J$21-PL!$J$27 -> 0 | K30: =PL!$K$15+PL!$K$16+PL!$K$17+PL!$K$18+PL!$K$19+PL!$K$20+PL!$K$21-PL!$K$27 -> 0 | L30: =PL!$L$15+PL!$L$16+PL!$L$17+PL!$L$18+PL!$L$19+PL!$L$20+PL!$L$21-PL!$L$27 -> 0 | M30: =PL!$M$15+PL!$M$16+PL!$M$17+PL!$M$18+PL!$M$19+PL!$M$20+PL!$M$21-PL!$M$27 -> 0 | N30: =PL!$N$15+PL!$N$16+PL!$N$17+PL!$N$18+PL!$N$19+PL!$N$20+PL!$N$21-PL!$N$27 -> 0 | O30: =PL!$O$15+PL!$O$16+PL!$O$17+PL!$O$18+PL!$O$19+PL!$O$20+PL!$O$21-PL!$O$27 -> 0
A31: 檢查（情境 A）：分部合計 − 合併營收 | B31: US$bn | C31: =PL!$C$22+PL!$C$23+PL!$C$24-PL!$C$27 -> 0 | D31: =PL!$D$22+PL!$D$23+PL!$D$24-PL!$D$27 -> 0 | E31: =PL!$E$22+PL!$E$23+PL!$E$24-PL!$E$27 -> 0 | F31: =PL!$F$22+PL!$F$23+PL!$F$24-PL!$F$27 -> 0 | G31: =PL!$G$22+PL!$G$23+PL!$G$24-PL!$G$27 -> 0 | H31: =PL!$H$22+PL!$H$23+PL!$H$24-PL!$H$27 -> 0 | I31: =PL!$I$22+PL!$I$23+PL!$I$24-PL!$I$27 -> 0 | J31: =PL!$J$22+PL!$J$23+PL!$J$24-PL!$J$27 -> 0 | K31: =PL!$K$22+PL!$K$23+PL!$K$24-PL!$K$27 -> 0 | L31: =PL!$L$22+PL!$L$23+PL!$L$24-PL!$L$27 -> 0 | M31: =PL!$M$22+PL!$M$23+PL!$M$24-PL!$M$27 -> 0 | N31: =PL!$N$22+PL!$N$23+PL!$N$24-PL!$N$27 -> 0 | O31: =PL!$O$22+PL!$O$23+PL!$O$24-PL!$O$27 -> 0
A32: 2. 分部營業利益（廣告利潤率 m_ad 計入北美／國際；零售本業利益率＝殘差；自用 AI 成本按北美比例分攤）
A33: North America：廣告利潤（廣告營收 × m_ad） | B33: US$bn | C33: =Seg!$C$24*m_ad -> 20.534156 | D33: =Seg!$D$24*m_ad -> 24.872062 | E33: =Seg!$E$24*m_ad -> 13.501711 | F33: =Seg!$F$24*m_ad -> 16.438693 | G33: =Seg!$G$24*m_ad -> 29.948781 | H33: =Seg!$H$24*m_ad -> 35.955042 | I33: =Seg!$I$24*m_ad -> 41.960759 | J33: =Seg!$J$24*m_ad -> 47.563235 | K33: =Seg!$K$24*m_ad -> 52.319558 | L33: =Seg!$L$24*m_ad -> 57.551514 | M33: =Seg!$M$24*m_ad -> 63.306666 | N33: =Seg!$N$24*m_ad -> 10.854356 | O33: =Seg!$O$24*m_ad -> 14.009473
A34: North America：零售本業營收（分部 − 廣告） | B34: US$bn | C34: =Seg!$C$22-Seg!$C$24 -> 346.42869 | D34: =Seg!$D$22-Seg!$D$24 -> 376.56088 | E34: =Seg!$E$22-Seg!$E$24 -> 193.31658 | F34: =Seg!$F$22-Seg!$F$24 -> 215.74663 | G34: =Seg!$G$22-Seg!$G$24 -> 409.04646 | H34: =Seg!$H$22-Seg!$H$24 -> 447.24434 | I34: =Seg!$I$22-Seg!$I$24 -> 483.78009 | J34: =Seg!$J$22-Seg!$J$24 -> 517.62813 | K34: =Seg!$K$22-Seg!$K$24 -> 547.76114 | L34: =Seg!$L$22-Seg!$L$24 -> 579.71359 | M34: =Seg!$M$22-Seg!$M$24 -> 613.59883 | N34: =Seg!$N$22-Seg!$N$24 -> 171.24629 | O34: =Seg!$O$22-Seg!$O$24 -> 205.33105
A35: North America：自用 AI 成本淨額分攤 | B35: US$bn | C35: =Thesis!$C$49*Seg!$C$21 -> 0.12361744 | D35: =Thesis!$D$49*Seg!$D$21 -> 0.8743669 | E35: =Thesis!$E$49*Seg!$E$21 -> 1.2931883 | F35: =Thesis!$F$49*Seg!$F$21 -> 1.5229726 | G35: =Thesis!$G$49*Seg!$G$21 -> 2.8166043 | H35: =Thesis!$H$49*Seg!$H$21 -> 7.4831735 | I35: =Thesis!$I$49*Seg!$I$21 -> 13.1425 | J35: =Thesis!$J$49*Seg!$J$21 -> 18.955077 | K35: =Thesis!$K$49*Seg!$K$21 -> 24.640968 | L35: =Thesis!$L$49*Seg!$L$21 -> 28.33276 | M35: =Thesis!$M$49*Seg!$M$21 -> 30.42594 | N35: =Thesis!$N$49*Seg!$N$21 -> 0.38918051 | O35: =Thesis!$O$49*Seg!$O$21 -> 0.48505212
A36: North America：零售本業利益率（實績＝殘差，Derived） | B36: % | C36: =(PL!$C$37-PL!$C$33+PL!$C$35)/PL!$C$34 -> 0.013152667 | D36: =(PL!$D$37-PL!$D$33+PL!$D$35)/PL!$D$34 -> 0.014928012 | E36: =(PL!$E$37-PL!$E$33+PL!$E$35)/PL!$E$34 -> 0.026803066 | F36: =PL!$O$36+(PL!$E$36-PL!$N$36) -> 0.023237935 | G36: =(PL!$G$37-PL!$G$33+PL!$G$35)/PL!$G$34 -> 0.024904384 | H36: =PL!$G$36+step_na -> 0.027904384 | I36: =PL!$H$36+step_na -> 0.030904384 | J36: =PL!$I$36+step_na -> 0.033904384 | K36: =PL!$J$36+step_na -> 0.036904384 | L36: =PL!$K$36 -> 0.036904384 | M36: =PL!$L$36 -> 0.036904384 | N36: =(PL!$N$37-PL!$N$33+PL!$N$35)/PL!$N$34 -> 0.016892774 | O36: =(PL!$O$37-PL!$O$33+PL!$O$35)/PL!$O$34 -> 0.013327643 | P36: 2H26＝2H25＋(1H26 − 1H25)；2027–2030 每年＋In 頁 step；之後持平
A37: North America 營業利益 | B37: US$bn | C37: =Q!$D$22 -> 24.967 | D37: =Q!$E$22 -> 29.619 | E37: =Q!$P$22 -> 17.39 | F37: =PL!$F$33+PL!$F$34*PL!$F$36-PL!$F$35 -> 19.929227 | G37: =PL!$E$37+PL!$F$37 -> 37.319227 | H37: =PL!$H$33+PL!$H$34*PL!$H$36-PL!$H$35 -> 40.951946 | I37: =PL!$I$33+PL!$I$34*PL!$I$36-PL!$I$35 -> 43.769184 | J37: =PL!$J$33+PL!$J$34*PL!$J$36-PL!$J$35 -> 46.15802 | K37: =PL!$K$33+PL!$K$34*PL!$K$36-PL!$K$35 -> 47.893377 | L37: =PL!$L$33+PL!$L$34*PL!$L$36-PL!$L$35 -> 50.612727 | M37: =PL!$M$33+PL!$M$34*PL!$M$36-PL!$M$35 -> 55.525212 | N37: =Q!$N$22 -> 13.358 | O37: =Q!$O$22 -> 16.261
A38: International：廣告利潤（廣告營收 × m_ad） | B38: US$bn | C38: =Seg!$C$25*m_ad -> 7.5728436 | D38: =Seg!$D$25*m_ad -> 9.4454383 | E38: =Seg!$E$25*m_ad -> 5.0242888 | F38: =Seg!$F$25*m_ad -> 6.4543093 | G38: =Seg!$G$25*m_ad -> 11.470221 | H38: =Seg!$H$25*m_ad -> 13.770587 | I38: =Seg!$I$25*m_ad -> 16.070744 | J38: =Seg!$J$25*m_ad -> 18.216462 | K38: =Seg!$K$25*m_ad -> 20.038108 | L38: =Seg!$L$25*m_ad -> 22.041919 | M38: =Seg!$M$25*m_ad -> 24.246111 | N38: =Seg!$N$25*m_ad -> 3.9531444 | O38: =Seg!$O$25*m_ad -> 5.5005268
A39: International：零售本業營收（分部 − 廣告） | B39: US$bn | C39: =Seg!$C$23-Seg!$C$25 -> 127.76031 | D39: =Seg!$D$23-Seg!$D$25 -> 143.00312 | E39: =Seg!$E$23-Seg!$E$25 -> 71.937422 | F39: =Seg!$F$23-Seg!$F$25 -> 84.708405 | G39: =Seg!$G$23-Seg!$G$25 -> 156.66258 | H39: =Seg!$H$23-Seg!$H$25 -> 171.29216 | I39: =Seg!$I$23-Seg!$I$25 -> 185.28516 | J39: =Seg!$J$23-Seg!$J$25 -> 198.24878 | K39: =Seg!$K$23-Seg!$K$25 -> 209.78955 | L39: =Seg!$L$23-Seg!$L$25 -> 222.02717 | M39: =Seg!$M$23-Seg!$M$25 -> 235.00503 | N39: =Seg!$N$23-Seg!$N$25 -> 62.367711 | O39: =Seg!$O$23-Seg!$O$25 -> 80.618946
A40: International：自用 AI 成本淨額分攤 | B40: US$bn | C40: =Thesis!$C$49*(1-Seg!$C$21) -> 0.04558919 | D40: =Thesis!$D$49*(1-Seg!$D$21) -> 0.33205042 | E40: =Thesis!$E$49*(1-Seg!$E$21) -> 0.48122429 | F40: =Thesis!$F$49*(1-Seg!$F$21) -> 0.59796335 | G40: =Thesis!$G$49*(1-Seg!$G$21) -> 1.0787442 | H40: =Thesis!$H$49*(1-Seg!$H$21) -> 2.866015 | I40: =Thesis!$I$49*(1-Seg!$I$21) -> 5.0335065 | J40: =Thesis!$J$49*(1-Seg!$J$21) -> 7.2596921 | K40: =Thesis!$K$49*(1-Seg!$K$21) -> 9.4373576 | L40: =Thesis!$L$49*(1-Seg!$L$21) -> 10.851294 | M40: =Thesis!$M$49*(1-Seg!$M$21) -> 11.652971 | N40: =Thesis!$N$49*(1-Seg!$N$21) -> 0.14173912 | O40: =Thesis!$O$49*(1-Seg!$O$21) -> 0.19044558
A41: International：零售本業利益率（實績＝殘差，Derived） | B41: % | C41: =(PL!$C$42-PL!$C$38+PL!$C$40)/PL!$C$39 -> -0.029236422 | D41: =(PL!$D$42-PL!$D$38+PL!$D$40)/PL!$D$39 -> -0.030512535 | E41: =(PL!$E$42-PL!$E$38+PL!$E$40)/PL!$E$39 -> -0.019490057 | F41: =PL!$O$41+(PL!$E$41-PL!$N$41) -> -0.036733229 | G41: =(PL!$G$42-PL!$G$38+PL!$G$40)/PL!$G$39 -> -0.028760821 | H41: =PL!$G$41+step_in -> -0.028760821 | I41: =PL!$H$41+step_in -> -0.028760821 | J41: =PL!$I$41+step_in -> -0.028760821 | K41: =PL!$J$41+step_in -> -0.028760821 | L41: =PL!$K$41 -> -0.028760821 | M41: =PL!$L$41 -> -0.028760821 | N41: =(PL!$N$42-PL!$N$38+PL!$N$40)/PL!$N$39 -> -0.020850618 | O41: =(PL!$O$42-PL!$O$38+PL!$O$40)/PL!$O$39 -> -0.03809379 | P41: 2H26＝2H25＋(1H26 − 1H25)；2027–2030 每年＋In 頁 step；之後持平
A42: International 營業利益 | B42: US$bn | C42: =Q!$D$23 -> 3.792 | D42: =Q!$E$23 -> 4.75 | E42: =Q!$P$23 -> 3.141 | F42: =PL!$F$38+PL!$F$39*PL!$F$41-PL!$F$40 -> 2.7447327 | G42: =PL!$E$42+PL!$F$42 -> 5.8857327 | H42: =PL!$H$38+PL!$H$39*PL!$H$41-PL!$H$40 -> 5.9780686 | I42: =PL!$I$38+PL!$I$39*PL!$I$41-PL!$I$40 -> 5.708284 | J42: =PL!$J$38+PL!$J$39*PL!$J$41-PL!$J$40 -> 5.2549722 | K42: =PL!$K$38+PL!$K$39*PL!$K$41-PL!$K$40 -> 4.5670306 | L42: =PL!$L$38+PL!$L$39*PL!$L$41-PL!$L$40 -> 4.804941 | M42: =PL!$M$38+PL!$M$39*PL!$M$41-PL!$M$40 -> 5.8342025 | N42: =Q!$N$23 -> 2.511 | O42: =Q!$O$23 -> 2.239
A43: AWS AI 營業利益（命題子列） | B43: US$bn | C43: =Thesis!$C$46 -> 1.6441788 | D43: =Thesis!$D$46 -> 3.8781008 | E43: =Thesis!$E$46 -> 1.4127026 | F43: =Thesis!$F$46 -> 9.2868889 | G43: =Thesis!$G$46 -> 10.699591 | H43: =Thesis!$H$46 -> 41.68712 | I43: =Thesis!$I$46 -> 75.372265 | J43: =Thesis!$J$46 -> 108.49876 | K43: =Thesis!$K$46 -> 132.73207 | L43: =Thesis!$L$46 -> 148.89565 | M43: =Thesis!$M$46 -> 154.75465 | N43: =Thesis!$N$46 -> 0.92264103 | O43: =Thesis!$O$46 -> 2.9554598
A44: AWS 其他營業利益 | B44: US$bn | C44: =Thesis!$C$51 -> 38.189821 | D44: =Thesis!$D$51 -> 41.727899 | E44: =Thesis!$E$51 -> 29.369297 | F44: =Thesis!$F$51 -> 26.899728 | G44: =Thesis!$G$51 -> 56.269025 | H44: =Thesis!$H$51 -> 60.350533 | I44: =Thesis!$I$51 -> 67.004386 | J44: =Thesis!$J$51 -> 73.378292 | K44: =Thesis!$K$51 -> 79.248556 | L44: =Thesis!$L$51 -> 85.58844 | M44: =Thesis!$M$51 -> 92.435515 | N44: =Thesis!$N$51 -> 20.784359 | O44: =Thesis!$O$51 -> 20.94354
A45: AWS 營業利益 | B45: US$bn | C45: =Q!$D$24 -> 39.834 | D45: =Q!$E$24 -> 45.606 | E45: =Q!$P$24 -> 30.782 | F45: =PL!$F$43+PL!$F$44 -> 36.186617 | G45: =PL!$G$43+PL!$G$44 -> 66.968617 | H45: =PL!$H$43+PL!$H$44 -> 102.03765 | I45: =PL!$I$43+PL!$I$44 -> 142.37665 | J45: =PL!$J$43+PL!$J$44 -> 181.87706 | K45: =PL!$K$43+PL!$K$44 -> 211.98063 | L45: =PL!$L$43+PL!$L$44 -> 234.48409 | M45: =PL!$M$43+PL!$M$44 -> 247.19016 | N45: =Q!$N$24 -> 21.707 | O45: =Q!$O$24 -> 23.899
A46: 未分攤（公司層；Amazon 為 0） | B46: US$bn | C46: =Q!$D$26 -> 0 | D46: =Q!$E$26 -> 0 | E46: =Q!$P$26 -> 0 | F46: 0 | G46: =PL!$E$46+PL!$F$46 -> 0 | H46: 0 | I46: 0 | J46: 0 | K46: 0 | L46: 0 | M46: 0 | N46: =Q!$N$26 -> 0 | O46: =Q!$O$26 -> 0
A47: 合併營業利益 | B47: US$bn | C47: =Q!$D$25 -> 68.593 | D47: =Q!$E$25 -> 79.975 | E47: =Q!$P$25 -> 51.313 | F47: =PL!$F$37+PL!$F$42+PL!$F$45+PL!$F$46 -> 58.860576 | G47: =PL!$G$37+PL!$G$42+PL!$G$45+PL!$G$46 -> 110.17358 | H47: =PL!$H$37+PL!$H$42+PL!$H$45+PL!$H$46 -> 148.96767 | I47: =PL!$I$37+PL!$I$42+PL!$I$45+PL!$I$46 -> 191.85412 | J47: =PL!$J$37+PL!$J$42+PL!$J$45+PL!$J$46 -> 233.29005 | K47: =PL!$K$37+PL!$K$42+PL!$K$45+PL!$K$46 -> 264.44104 | L47: =PL!$L$37+PL!$L$42+PL!$L$45+PL!$L$46 -> 289.90176 | M47: =PL!$M$37+PL!$M$42+PL!$M$45+PL!$M$46 -> 308.54958 | N47: =Q!$N$25 -> 37.576 | O47: =Q!$O$25 -> 42.399
A48: 檢查（情境 A）：分部營業利益合計 − 合併營業利益 | B48: US$bn | C48: =PL!$C$37+PL!$C$42+PL!$C$45+PL!$C$46-PL!$C$47 -> 0 | D48: =PL!$D$37+PL!$D$42+PL!$D$45+PL!$D$46-PL!$D$47 -> 0 | E48: =PL!$E$37+PL!$E$42+PL!$E$45+PL!$E$46-PL!$E$47 -> 0 | F48: =PL!$F$37+PL!$F$42+PL!$F$45+PL!$F$46-PL!$F$47 -> 0 | G48: =PL!$G$37+PL!$G$42+PL!$G$45+PL!$G$46-PL!$G$47 -> 0 | H48: =PL!$H$37+PL!$H$42+PL!$H$45+PL!$H$46-PL!$H$47 -> 0 | I48: =PL!$I$37+PL!$I$42+PL!$I$45+PL!$I$46-PL!$I$47 -> 0 | J48: =PL!$J$37+PL!$J$42+PL!$J$45+PL!$J$46-PL!$J$47 -> 0 | K48: =PL!$K$37+PL!$K$42+PL!$K$45+PL!$K$46-PL!$K$47 -> 0 | L48: =PL!$L$37+PL!$L$42+PL!$L$45+PL!$L$46-PL!$L$47 -> 0 | M48: =PL!$M$37+PL!$M$42+PL!$M$45+PL!$M$46-PL!$M$47 -> 0 | N48: =PL!$N$37+PL!$N$42+PL!$N$45+PL!$N$46-PL!$N$47 -> 0 | O48: =PL!$O$37+PL!$O$42+PL!$O$45+PL!$O$46-PL!$O$47 -> 0
A49: 自用 AI 影子效益（讀法 2；非財報營收；按北美比例分攤到北美／國際） | B49: US$bn | C49: =Thesis!$C$48 -> 0 | D49: =Thesis!$D$48 -> 0 | E49: =Thesis!$E$48 -> 0 | F49: =Thesis!$F$48 -> 3.8047983 | G49: =Thesis!$G$48 -> 3.8047983 | H49: =Thesis!$H$48 -> 15.437683 | I49: =Thesis!$I$48 -> 26.138954 | J49: =Thesis!$J$48 -> 36.88783 | K49: =Thesis!$K$48 -> 46.057013 | L49: =Thesis!$L$48 -> 52.081131 | M49: =Thesis!$M$48 -> 54.952438 | N49: =Thesis!$N$48 -> 0 | O49: =Thesis!$O$48 -> 0 | P49: 營收列與分部對帳不動
A50: 營業利益（評價口徑＝合併營業利益＋自用 AI 影子效益） | B50: US$bn | C50: =PL!$C$47+PL!$C$49 -> 68.593 | D50: =PL!$D$47+PL!$D$49 -> 79.975 | E50: =PL!$E$47+PL!$E$49 -> 51.313 | F50: =PL!$F$47+PL!$F$49 -> 62.665374 | G50: =PL!$G$47+PL!$G$49 -> 113.97837 | H50: =PL!$H$47+PL!$H$49 -> 164.40535 | I50: =PL!$I$47+PL!$I$49 -> 217.99307 | J50: =PL!$J$47+PL!$J$49 -> 270.17788 | K50: =PL!$K$47+PL!$K$49 -> 310.49805 | L50: =PL!$L$47+PL!$L$49 -> 341.98289 | M50: =PL!$M$47+PL!$M$49 -> 363.50201 | N50: =PL!$N$47+PL!$N$49 -> 37.576 | O50: =PL!$O$47+PL!$O$49 -> 42.399
A51: North America 營業利益率 | B51: % | C51: =PL!$C$37/PL!$C$22 -> 0.064431467 | D51: =PL!$D$37/PL!$D$22 -> 0.069478425 | E51: =PL!$E$37/PL!$E$22 -> 0.078930646 | F51: =PL!$F$37/PL!$F$22 -> 0.080158092 | G51: =PL!$G$37/PL!$G$22 -> 0.079581412 | H51: =PL!$H$37/PL!$H$22 -> 0.078882014 | I51: =PL!$I$37/PL!$I$22 -> 0.077098926 | J51: =PL!$J$37/PL!$J$22 -> 0.075328721 | K51: =PL!$K$37/PL!$K$22 -> 0.073411034 | L51: =PL!$L$37/PL!$L$22 -> 0.072843287 | M51: =PL!$M$37/PL!$M$22 -> 0.075012564 | N51: =PL!$N$37/PL!$N$22 -> 0.069228577 | O51: =PL!$O$37/PL!$O$22 -> 0.069685022
A52: International 營業利益率 | B52: % | C52: =PL!$C$42/PL!$C$23 -> 0.026534925 | D52: =PL!$D$42/PL!$D$23 -> 0.029340186 | E52: =PL!$E$42/PL!$E$23 -> 0.038311419 | F52: =PL!$F$42/PL!$F$23 -> 0.028117357 | G52: =PL!$G$42/PL!$G$23 -> 0.032770788 | H52: =PL!$H$42/PL!$H$23 -> 0.030065726 | I52: =PL!$I$42/PL!$I$23 -> 0.026253838 | J52: =PL!$J$42/PL!$J$23 -> 0.022391913 | K52: =PL!$K$42/PL!$K$23 -> 0.018277936 | L52: =PL!$L$42/PL!$L$23 -> 0.018056153 | M52: =PL!$M$42/PL!$M$23 -> 0.020579397 | N52: =PL!$N$42/PL!$N$23 -> 0.035731565 | O52: =PL!$O$42/PL!$O$23 -> 0.024437896
A53: AWS 營業利益率 | B53: % | C53: =PL!$C$45/PL!$C$24 -> 0.37035591 | D53: =PL!$D$45/PL!$D$24 -> 0.35429015 | E53: =PL!$E$45/PL!$E$24 -> 0.38564753 | F53: =PL!$F$45/PL!$F$24 -> 0.40413942 | G53: =PL!$G$45/PL!$G$24 -> 0.39542418 | H53: =PL!$H$45/PL!$H$24 -> 0.41801416 | I53: =PL!$I$45/PL!$I$24 -> 0.43560768 | J53: =PL!$J$45/PL!$J$24 -> 0.44454221 | K53: =PL!$K$45/PL!$K$24 -> 0.44118241 | L53: =PL!$L$45/PL!$L$24 -> 0.43912157 | M53: =PL!$M$45/PL!$M$24 -> 0.43390211 | N53: =PL!$N$45/PL!$N$24 -> 0.36094114 | O53: =PL!$O$45/PL!$O$24 -> 0.34845812
A54: AWS AI 營業利益率 | B54: % | C54: =PL!$C$43/PL!$C$25 -> 0.70839079 | D54: =PL!$D$43/PL!$D$25 -> 0.44556563 | E54: =PL!$E$43/PL!$E$25 -> 0.16599812 | F54: =PL!$F$43/PL!$F$25 -> 0.52259754 | G54: =PL!$G$43/PL!$G$25 -> 0.40712292 | H54: =PL!$H$43/PL!$H$25 -> 0.50174743 | I54: =PL!$I$43/PL!$I$25 -> 0.50900968 | J54: =PL!$J$43/PL!$J$25 -> 0.50852954 | K54: =PL!$K$43/PL!$K$25 -> 0.49334456 | L54: =PL!$L$43/PL!$L$25 -> 0.48717319 | M54: =PL!$M$43/PL!$M$25 -> 0.47901231 | N54: =PL!$N$43/PL!$N$25 -> 0.30287073 | O54: =PL!$O$43/PL!$O$25 -> 0.52240134
A55: 合併營業利益率 | B55: % | C55: =PL!$C$47/PL!$C$27 -> 0.10751945 | D55: =PL!$D$47/PL!$D$27 -> 0.11155297 | E55: =PL!$E$47/PL!$E$27 -> 0.13428328 | F55: =PL!$F$47/PL!$F$27 -> 0.13506917 | G55: =PL!$G$47/PL!$G$27 -> 0.13470201 | H55: =PL!$H$47/PL!$H$27 -> 0.15483777 | I55: =PL!$I$47/PL!$I$27 -> 0.17253467 | J55: =PL!$J$47/PL!$J$27 -> 0.18565628 | K55: =PL!$K$47/PL!$K$27 -> 0.19124298 | L55: =PL!$L$47/PL!$L$27 -> 0.19392563 | M55: =PL!$M$47/PL!$M$27 -> 0.1936422 | N55: =PL!$N$47/PL!$N$27 -> 0.11620161 | O55: =PL!$O$47/PL!$O$27 -> 0.10773335
A56: 3. 分部折舊攤銷（PP&E）與 EBITDA（分部加總評價用）
A57: 零售非 AI 折舊 ÷ 零售營收（FY2025 校準） | B57: % | D57: =(Q!$E$29+Q!$E$30-(1-ext_sh)*Thesis!$D$42)/Seg!$D$20 -> 0.033467431
A58: North America 折舊攤銷 | B58: US$bn | C58: =Q!$D$29 -> 14.285 | D58: =Q!$E$29 -> 15.503 | E58: =Q!$P$29 -> 8.78 | F58: =(PL!$D$57*Seg!$F$20+(1-ext_sh)*Thesis!$F$42)*Seg!$F$21 -> 9.2565878 | G58: =PL!$E$58+PL!$F$58 -> 18.036588 | H58: =(PL!$D$57*Seg!$H$20+(1-ext_sh)*Thesis!$H$42)*Seg!$H$21 -> 22.531241 | I58: =(PL!$D$57*Seg!$I$20+(1-ext_sh)*Thesis!$I$42)*Seg!$I$21 -> 28.274015 | J58: =(PL!$D$57*Seg!$J$20+(1-ext_sh)*Thesis!$J$42)*Seg!$J$21 -> 34.050248 | K58: =(PL!$D$57*Seg!$K$20+(1-ext_sh)*Thesis!$K$42)*Seg!$K$21 -> 39.745235 | L58: =(PL!$D$57*Seg!$L$20+(1-ext_sh)*Thesis!$L$42)*Seg!$L$21 -> 43.990812 | M58: =(PL!$D$57*Seg!$M$20+(1-ext_sh)*Thesis!$M$42)*Seg!$M$21 -> 47.189906 | N58: =Q!$N$29 -> 7.272 | O58: =Q!$O$29 -> 8.231
A59: International 折舊攤銷 | B59: US$bn | C59: =Q!$D$30 -> 4.462 | D59: =Q!$E$30 -> 4.907 | E59: =Q!$P$30 -> 2.57 | F59: =(PL!$D$57*Seg!$F$20+(1-ext_sh)*Thesis!$F$42)*(1-Seg!$F$21) -> 3.6344057 | G59: =PL!$E$59+PL!$F$59 -> 6.2044057 | H59: =(PL!$D$57*Seg!$H$20+(1-ext_sh)*Thesis!$H$42)*(1-Seg!$H$21) -> 8.6293436 | I59: =(PL!$D$57*Seg!$I$20+(1-ext_sh)*Thesis!$I$42)*(1-Seg!$I$21) -> 10.828795 | J59: =(PL!$D$57*Seg!$J$20+(1-ext_sh)*Thesis!$J$42)*(1-Seg!$J$21) -> 13.041061 | K59: =(PL!$D$57*Seg!$K$20+(1-ext_sh)*Thesis!$K$42)*(1-Seg!$K$21) -> 15.22221 | L59: =(PL!$D$57*Seg!$L$20+(1-ext_sh)*Thesis!$L$42)*(1-Seg!$L$21) -> 16.848243 | M59: =(PL!$D$57*Seg!$M$20+(1-ext_sh)*Thesis!$M$42)*(1-Seg!$M$21) -> 18.073479 | N59: =Q!$N$30 -> 2.316 | O59: =Q!$O$30 -> 2.591
A60: AWS 折舊攤銷 | B60: US$bn | C60: =Thesis!$C$54 -> 13.32 | D60: =Thesis!$D$54 -> 21.45 | E60: =Thesis!$E$54 -> 15.353 | F60: =Thesis!$F$54 -> 16.306375 | G60: =Thesis!$G$54 -> 31.659375 | H60: =Thesis!$H$54 -> 53.414404 | I60: =Thesis!$I$54 -> 78.939312 | J60: =Thesis!$J$54 -> 105.18078 | K60: =Thesis!$K$54 -> 131.76621 | L60: =Thesis!$L$54 -> 150.01424 | M60: =Thesis!$M$54 -> 162.13075 | N60: =Thesis!$N$54 -> 9.234 | O60: =Thesis!$O$54 -> 12.216
A61: 分部折舊攤銷合計（PP&E；不含影音內容與營業租賃資產） | B61: US$bn | C61: =PL!$C$58+PL!$C$59+PL!$C$60 -> 32.067 | D61: =PL!$D$58+PL!$D$59+PL!$D$60 -> 41.86 | E61: =PL!$E$58+PL!$E$59+PL!$E$60 -> 26.703 | F61: =PL!$F$58+PL!$F$59+PL!$F$60 -> 29.197368 | G61: =PL!$G$58+PL!$G$59+PL!$G$60 -> 55.900368 | H61: =PL!$H$58+PL!$H$59+PL!$H$60 -> 84.574989 | I61: =PL!$I$58+PL!$I$59+PL!$I$60 -> 118.04212 | J61: =PL!$J$58+PL!$J$59+PL!$J$60 -> 152.27209 | K61: =PL!$K$58+PL!$K$59+PL!$K$60 -> 186.73365 | L61: =PL!$L$58+PL!$L$59+PL!$L$60 -> 210.8533 | M61: =PL!$M$58+PL!$M$59+PL!$M$60 -> 227.39414 | N61: =PL!$N$58+PL!$N$59+PL!$N$60 -> 18.822 | O61: =PL!$O$58+PL!$O$59+PL!$O$60 -> 23.038
A62: EBITDA：廣告（＝廣告利潤，未分攤折舊） | B62: US$bn | C62: =PL!$C$33+PL!$C$38 -> 28.107 | D62: =PL!$D$33+PL!$D$38 -> 34.3175 | E62: =PL!$E$33+PL!$E$38 -> 18.526 | F62: =PL!$F$33+PL!$F$38 -> 22.893003 | G62: =PL!$G$33+PL!$G$38 -> 41.419003 | H62: =PL!$H$33+PL!$H$38 -> 49.725629 | I62: =PL!$I$33+PL!$I$38 -> 58.031503 | J62: =PL!$J$33+PL!$J$38 -> 65.779697 | K62: =PL!$K$33+PL!$K$38 -> 72.357666 | L62: =PL!$L$33+PL!$L$38 -> 79.593433 | M62: =PL!$M$33+PL!$M$38 -> 87.552776 | N62: =PL!$N$33+PL!$N$38 -> 14.8075 | O62: =PL!$O$33+PL!$O$38 -> 19.51
A63: EBITDA：零售本業（北美＋國際 營業利益＋折舊 − 廣告利潤；含自用 AI 成本） | B63: US$bn | C63: =PL!$C$37+PL!$C$42+PL!$C$58+PL!$C$59-PL!$C$62 -> 19.399 | D63: =PL!$D$37+PL!$D$42+PL!$D$58+PL!$D$59-PL!$D$62 -> 20.4615 | E63: =PL!$E$37+PL!$E$42+PL!$E$58+PL!$E$59-PL!$E$62 -> 13.355 | F63: =PL!$F$37+PL!$F$42+PL!$F$58+PL!$F$59-PL!$F$62 -> 12.67195 | G63: =PL!$G$37+PL!$G$42+PL!$G$58+PL!$G$59-PL!$G$62 -> 26.02695 | H63: =PL!$H$37+PL!$H$42+PL!$H$58+PL!$H$59-PL!$H$62 -> 28.364971 | I63: =PL!$I$37+PL!$I$42+PL!$I$58+PL!$I$59-PL!$I$62 -> 30.548776 | J63: =PL!$J$37+PL!$J$42+PL!$J$58+PL!$J$59-PL!$J$62 -> 32.724606 | K63: =PL!$K$37+PL!$K$42+PL!$K$58+PL!$K$59-PL!$K$62 -> 35.070186 | L63: =PL!$L$37+PL!$L$42+PL!$L$58+PL!$L$59-PL!$L$62 -> 36.66329 | M63: =PL!$M$37+PL!$M$42+PL!$M$58+PL!$M$59-PL!$M$62 -> 39.070023 | N63: =PL!$N$37+PL!$N$42+PL!$N$58+PL!$N$59-PL!$N$62 -> 10.6495 | O63: =PL!$O$37+PL!$O$42+PL!$O$58+PL!$O$59-PL!$O$62 -> 9.812
A64: EBITDA：AWS 其他 | B64: US$bn | C64: =PL!$C$44+PL!$C$60-ext_sh*Thesis!$C$42 -> 51.34705 | D64: =PL!$D$44+PL!$D$60-ext_sh*Thesis!$D$42 -> 60.279938 | E64: =PL!$E$44+PL!$E$60-ext_sh*Thesis!$E$42 -> 39.509517 | F64: =PL!$F$44+PL!$F$60-ext_sh*Thesis!$F$42 -> 37.993322 | G64: =PL!$G$44+PL!$G$60-ext_sh*Thesis!$G$42 -> 77.502838 | H64: =PL!$H$44+PL!$H$60-ext_sh*Thesis!$H$42 -> 85.239422 | I64: =PL!$I$44+PL!$I$60-ext_sh*Thesis!$I$42 -> 94.637359 | J64: =PL!$J$44+PL!$J$60-ext_sh*Thesis!$J$42 -> 103.6399 | K64: =PL!$K$44+PL!$K$60-ext_sh*Thesis!$K$42 -> 111.93109 | L64: =PL!$L$44+PL!$L$60-ext_sh*Thesis!$L$42 -> 120.88558 | M64: =PL!$M$44+PL!$M$60-ext_sh*Thesis!$M$42 -> 130.55642 | N64: =PL!$N$44+PL!$N$60-ext_sh*Thesis!$N$42 -> 28.569378 | O64: =PL!$O$44+PL!$O$60-ext_sh*Thesis!$O$42 -> 31.710559
A65: EBITDA：AWS AI | B65: US$bn | C65: =Thesis!$C$45 -> 1.80695 | D65: =Thesis!$D$45 -> 6.7760625 | E65: =Thesis!$E$45 -> 6.6254833 | F65: =Thesis!$F$45 -> 14.49967 | G65: =Thesis!$G$45 -> 21.125153 | H65: =Thesis!$H$45 -> 70.212636 | I65: =Thesis!$I$45 -> 126.6786 | J65: =Thesis!$J$45 -> 183.41794 | K65: =Thesis!$K$45 -> 231.81575 | L65: =Thesis!$L$45 -> 263.61276 | M65: =Thesis!$M$45 -> 278.76449 | N65: =Thesis!$N$45 -> 2.3716219 | O65: =Thesis!$O$45 -> 4.4044406
A66: EBITDA（營業利益＋分部折舊攤銷） | B66: US$bn | C66: =PL!$C$47+PL!$C$61 -> 100.66 | D66: =PL!$D$47+PL!$D$61 -> 121.835 | E66: =PL!$E$47+PL!$E$61 -> 78.016 | F66: =PL!$F$47+PL!$F$61 -> 88.057944 | G66: =PL!$G$47+PL!$G$61 -> 166.07394 | H66: =PL!$H$47+PL!$H$61 -> 233.54266 | I66: =PL!$I$47+PL!$I$61 -> 309.89624 | J66: =PL!$J$47+PL!$J$61 -> 385.56214 | K66: =PL!$K$47+PL!$K$61 -> 451.17469 | L66: =PL!$L$47+PL!$L$61 -> 500.75506 | M66: =PL!$M$47+PL!$M$61 -> 535.94371 | N66: =PL!$N$47+PL!$N$61 -> 56.398 | O66: =PL!$O$47+PL!$O$61 -> 65.437
A67: 4. 業外、稅、淨利、EPS
A68: 利息費用 | B68: US$bn | C68: =Q!$D$34 -> 2.406 | D68: =Q!$E$34 -> 2.274 | E68: =Q!$P$34 -> 2.114 | F68: =CF!$F$38 -> 3.2488896 | G68: =PL!$E$68+PL!$F$68 -> 5.3628896 | H68: =CF!$H$38 -> 7.4235417 | I68: =CF!$I$38 -> 7.4350634 | J68: =CF!$J$38 -> 7.4350634 | K68: =CF!$K$38 -> 7.4350634 | L68: =CF!$L$38 -> 7.4350634 | M68: =CF!$M$38 -> 7.4350634 | N68: =Q!$N$34 -> 1.057 | O68: =Q!$O$34 -> 1.217
A69: 利息收入（預測；實績含在業外其他） | B69: US$bn | F69: =CF!$F$39 -> 2.59 | H69: =CF!$H$39 -> 3.7837844 | I69: =CF!$I$39 -> 2.1058965 | J69: =CF!$J$39 -> 2.9172837 | K69: =CF!$K$39 -> 6.3466529 | L69: =CF!$L$39 -> 14.730136 | M69: =CF!$M$39 -> 26.241296
A70: 業外其他（含利息收入與 Anthropic 等持股評價損益；預測期設 0） | B70: US$bn | C70: =Q!$D$39 -> 2.427 | D70: =Q!$E$39 -> 19.61 | E70: =Q!$P$39 -> 71.492 | F70: 0 | G70: =PL!$E$70+PL!$F$70 -> 71.492 | H70: 0 | I70: 0 | J70: 0 | K70: 0 | L70: 0 | M70: 0 | N70: =Q!$N$39 -> 6.017 | O70: =Q!$O$39 -> 13.593 | P70: 持股價值另在 Val 頁加入（不重複計算）
A71: 稅前淨利 | B71: US$bn | C71: =Q!$D$36 -> 68.614 | D71: =Q!$E$36 -> 97.311 | E71: =Q!$P$36 -> 120.691 | F71: =PL!$F$47-PL!$F$68+PL!$F$69+PL!$F$70 -> 58.201687 | G71: =PL!$E$71+PL!$F$71 -> 178.89269 | H71: =PL!$H$47-PL!$H$68+PL!$H$69+PL!$H$70 -> 145.32791 | I71: =PL!$I$47-PL!$I$68+PL!$I$69+PL!$I$70 -> 186.52495 | J71: =PL!$J$47-PL!$J$68+PL!$J$69+PL!$J$70 -> 228.77227 | K71: =PL!$K$47-PL!$K$68+PL!$K$69+PL!$K$70 -> 263.35263 | L71: =PL!$L$47-PL!$L$68+PL!$L$69+PL!$L$70 -> 297.19683 | M71: =PL!$M$47-PL!$M$68+PL!$M$69+PL!$M$70 -> 327.35581 | N71: =Q!$N$36 -> 42.536 | O71: =Q!$O$36 -> 54.775
A72: 所得稅 | B72: US$bn | C72: =Q!$D$37 -> 9.265 | D72: =Q!$E$37 -> 19.087 | E72: =Q!$P$37 -> 27.759 | F72: =PL!$F$71*tax -> 10.102912 | G72: =PL!$E$72+PL!$F$72 -> 37.861912 | H72: =PL!$H$71*tax -> 25.226677 | I72: =PL!$I$71*tax -> 32.377846 | J72: =PL!$J$71*tax -> 39.711326 | K72: =PL!$K$71*tax -> 45.713941 | L72: =PL!$L$71*tax -> 51.588772 | M72: =PL!$M$71*tax -> 56.823903 | N72: =Q!$N$37 -> 7.231 | O72: =Q!$O$37 -> 11.856
A73: 淨利 | B73: US$bn | C73: =Q!$D$38 -> 59.248 | D73: =Q!$E$38 -> 77.67 | E73: =Q!$P$38 -> 92.902 | F73: =PL!$F$71-PL!$F$72 -> 48.098774 | G73: =PL!$E$73+PL!$F$73 -> 141.00077 | H73: =PL!$H$71-PL!$H$72 -> 120.10123 | I73: =PL!$I$71-PL!$I$72 -> 154.14711 | J73: =PL!$J$71-PL!$J$72 -> 189.06094 | K73: =PL!$K$71-PL!$K$72 -> 217.63868 | L73: =PL!$L$71-PL!$L$72 -> 245.60806 | M73: =PL!$M$71-PL!$M$72 -> 270.53191 | N73: =Q!$N$38 -> 35.291 | O73: =Q!$O$38 -> 42.379
A74: 稀釋加權股數 | B74: 十億股 | C74: =Q!$D$41 -> 10.721 | D74: =Q!$E$41 -> 10.827 | E74: =(Q!$L$41+Q!$M$41)/2 -> 10.8885 | F74: =PL!$G$74 -> 10.924806 | G74: =Q!$M$41*(1+sh_g*0.25) -> 10.924806 | H74: =PL!$G$74*(1+sh_g) -> 11.012204 | I74: =PL!$H$74*(1+sh_g) -> 11.100302 | J74: =PL!$I$74*(1+sh_g) -> 11.189105 | K74: =PL!$J$74*(1+sh_g) -> 11.278617 | L74: =PL!$K$74*(1+sh_g) -> 11.368846 | M74: =PL!$L$74*(1+sh_g) -> 11.459797 | P74: 無回購；SBC 稀釋每年 sh_g
A75: 淨利（評價口徑＝淨利＋影子效益 ×（1 − 稅率）） | B75: US$bn | C75: =PL!$C$73+PL!$C$49*(1-tax) -> 59.248 | D75: =PL!$D$73+PL!$D$49*(1-tax) -> 77.67 | E75: =PL!$E$73+PL!$E$49*(1-tax) -> 92.902 | F75: =PL!$F$73+PL!$F$49*(1-tax) -> 51.243119 | G75: =PL!$G$73+PL!$G$49*(1-tax) -> 144.14512 | H75: =PL!$H$73+PL!$H$49*(1-tax) -> 132.85917 | I75: =PL!$I$73+PL!$I$49*(1-tax) -> 175.74874 | J75: =PL!$J$73+PL!$J$49*(1-tax) -> 219.54562 | K75: =PL!$K$73+PL!$K$49*(1-tax) -> 255.70091 | L75: =PL!$L$73+PL!$L$49*(1-tax) -> 288.64872 | M75: =PL!$M$73+PL!$M$49*(1-tax) -> 315.94545 | N75: =PL!$N$73+PL!$N$49*(1-tax) -> 35.291 | O75: =PL!$O$73+PL!$O$49*(1-tax) -> 42.379
A76: EPS（評價口徑，稀釋） | B76: US$ | C76: =PL!$C$75/PL!$C$74 -> 5.5263502 | D76: =PL!$D$75/PL!$D$74 -> 7.1737323 | E76: =PL!$E$75/PL!$E$74 -> 8.532121 | G76: =PL!$G$75/PL!$G$74 -> 13.194295 | H76: =PL!$H$75/PL!$H$74 -> 12.064721 | I76: =PL!$I$75/PL!$I$74 -> 15.832789 | J76: =PL!$J$75/PL!$J$74 -> 19.621375 | K76: =PL!$K$75/PL!$K$74 -> 22.6713 | L76: =PL!$L$75/PL!$L$74 -> 25.389447 | M76: =PL!$M$75/PL!$M$74 -> 27.569899
A77: EPS（財報口徑，稀釋） | B77: US$ | C77: =PL!$C$73/PL!$C$74 -> 5.5263502 | D77: =PL!$D$73/PL!$D$74 -> 7.1737323 | E77: =PL!$E$73/PL!$E$74 -> 8.532121 | G77: =PL!$G$73/PL!$G$74 -> 12.906479 | H77: =PL!$H$73/PL!$H$74 -> 10.906194 | I77: =PL!$I$73/PL!$I$74 -> 13.886749 | J77: =PL!$J$73/PL!$J$74 -> 16.896879 | K77: =PL!$K$73/PL!$K$74 -> 19.296575 | L77: =PL!$L$73/PL!$L$74 -> 21.603605 | M77: =PL!$M$73/PL!$M$74 -> 23.607042
A78: EPS（不含業外其他，近似：扣除業外其他 ×（1 − 稅率）） | B78: US$ | C78: =(PL!$C$73-PL!$C$70*(1-tax))/PL!$C$74 -> 5.3392678 | D78: =(PL!$D$73-PL!$D$70*(1-tax))/PL!$D$74 -> 5.6769181 | E78: =(PL!$E$73-PL!$E$70*(1-tax))/PL!$E$74 -> 3.1060206 | G78: =(PL!$G$73-PL!$G$70*(1-tax))/PL!$G$74 -> 7.4984104 | H78: =(PL!$H$73-PL!$H$70*(1-tax))/PL!$H$74 -> 10.906194 | I78: =(PL!$I$73-PL!$I$70*(1-tax))/PL!$I$74 -> 13.886749 | J78: =(PL!$J$73-PL!$J$70*(1-tax))/PL!$J$74 -> 16.896879 | K78: =(PL!$K$73-PL!$K$70*(1-tax))/PL!$K$74 -> 19.296575 | L78: =(PL!$L$73-PL!$L$70*(1-tax))/PL!$L$74 -> 21.603605 | M78: =(PL!$M$73-PL!$M$70*(1-tax))/PL!$M$74 -> 23.607042 | P78: 對照 S&P 調整後 EPS；2026 上半年業外含 Anthropic 評價利益約 69
A79: EPS 年增 | B79: % | H79: =PL!$H$76/PL!$G$76-1 -> -0.085610818 | I79: =PL!$I$76/PL!$H$76-1 -> 0.3123212 | J79: =PL!$J$76/PL!$I$76-1 -> 0.23928734 | K79: =PL!$K$76/PL!$J$76-1 -> 0.15543887 | L79: =PL!$L$76/PL!$K$76-1 -> 0.11989374 | M79: =PL!$M$76/PL!$L$76-1 -> 0.08588028
A82: PL｜情境 B（基準）：分部營收 → 分部營業利益 → 合併營業利益 → 業外、稅 → 淨利 → EPS
A83: 項目 | B83: 單位 | C83: FY2024A | D83: FY2025A | E83: 1H26A | F83: 2H26E | G83: FY2026E（1H 實績＋2H 模型） | H83: FY2027E | I83: FY2028E | J83: FY2029E | K83: FY2030E | L83: FY2031E | M83: FY2032E | N83: 1H25A | O83: 2H25A | P83: 說明 | R83: 2023 | S83: 2024 | T83: 2025 | U83: 2026 | V83: 2027 | W83: 2028 | X83: 2029 | Y83: 2030 | Z83: 2031 | AA83: 2032
A84: 1. 營收（10-K 營收線與官方分部）
A85: Online stores | B85: US$bn | C85: =Seg!$C$42 -> 247.029 | D85: =Seg!$D$42 -> 269.287 | E85: =Seg!$E$42 -> 134.686 | F85: =Seg!$F$42 -> 158.29388 | G85: =Seg!$G$42 -> 292.97988 | H85: =Seg!$H$42 -> 318.18454 | I85: =Seg!$I$42 -> 341.73628 | J85: =Seg!$J$42 -> 362.92719 | K85: =Seg!$K$42 -> 381.07355 | L85: =Seg!$L$42 -> 400.12723 | M85: =Seg!$M$42 -> 420.13359 | N85: =Seg!$N$42 -> 118.892 | O85: =Seg!$O$42 -> 150.395
A86: Physical stores | B86: US$bn | C86: =Seg!$C$44 -> 21.215 | D86: =Seg!$D$44 -> 22.561 | E86: =Seg!$E$44 -> 11.579 | F86: =Seg!$F$44 -> 11.593872 | G86: =Seg!$G$44 -> 23.172872 | H86: =Seg!$H$44 -> 24.353393 | I86: =Seg!$I$44 -> 25.424034 | J86: =Seg!$J$44 -> 26.364249 | K86: =Seg!$K$44 -> 27.155177 | L86: =Seg!$L$44 -> 27.969832 | M86: =Seg!$M$44 -> 28.808927 | N86: =Seg!$N$44 -> 11.128 | O86: =Seg!$O$44 -> 11.433
A87: Third-party seller services | B87: US$bn | C87: =Seg!$C$46 -> 156.146 | D87: =Seg!$D$46 -> 172.162 | E87: =Seg!$E$46 -> 88.358 | F87: =Seg!$F$46 -> 102.00439 | G87: =Seg!$G$46 -> 190.36239 | H87: =Seg!$H$46 -> 210.34311 | I87: =Seg!$I$46 -> 229.96973 | J87: =Seg!$J$46 -> 248.74764 | K87: =Seg!$K$46 -> 266.15997 | L87: =Seg!$L$46 -> 284.79117 | M87: =Seg!$M$46 -> 304.72655 | N87: =Seg!$N$46 -> 76.86 | O87: =Seg!$O$46 -> 95.302
A88: Advertising services | B88: US$bn | C88: =Seg!$C$48 -> 56.214 | D88: =Seg!$D$48 -> 68.635 | E88: =Seg!$E$48 -> 37.052 | F88: =Seg!$F$48 -> 46.157222 | G88: =Seg!$G$48 -> 83.209222 | H88: =Seg!$H$48 -> 99.896922 | I88: =Seg!$I$48 -> 116.58311 | J88: =Seg!$J$48 -> 132.14894 | K88: =Seg!$K$48 -> 145.36384 | L88: =Seg!$L$48 -> 159.90022 | M88: =Seg!$M$48 -> 175.89024 | N88: =Seg!$N$48 -> 29.615 | O88: =Seg!$O$48 -> 39.02
A89: Subscription services | B89: US$bn | C89: =Seg!$C$50 -> 44.374 | D89: =Seg!$D$50 -> 49.619 | E89: =Seg!$E$50 -> 27.157 | F89: =Seg!$F$50 -> 27.776417 | G89: =Seg!$G$50 -> 54.933417 | H89: =Seg!$H$50 -> 61.156411 | I89: =Seg!$I$50 -> 67.202028 | J89: =Seg!$J$50 -> 72.875727 | K89: =Seg!$K$50 -> 77.977028 | L89: =Seg!$L$50 -> 83.43542 | M89: =Seg!$M$50 -> 89.2759 | N89: =Seg!$N$50 -> 23.923 | O89: =Seg!$O$50 -> 25.696
A90: Other | B90: US$bn | C90: =Seg!$C$52 -> 5.425 | D90: =Seg!$D$52 -> 5.935 | E90: =Seg!$E$52 -> 3.474 | F90: =Seg!$F$52 -> 3.2224655 | G90: =Seg!$G$52 -> 6.6964655 | H90: =Seg!$H$52 -> 7.1625134 | I90: =Seg!$I$52 -> 7.6142107 | J90: =Seg!$J$52 -> 8.0446575 | K90: =Seg!$K$52 -> 8.4468904 | L90: =Seg!$L$52 -> 8.8692349 | M90: =Seg!$M$52 -> 9.3126967 | N90: =Seg!$N$52 -> 2.811 | O90: =Seg!$O$52 -> 3.124
A91: AWS（營收線＝分部） | B91: US$bn | C91: =Seg!$C$64 -> 107.556 | D91: =Seg!$D$64 -> 128.725 | E91: =Seg!$E$64 -> 79.819 | F91: =Seg!$F$64 -> 86.732733 | G91: =Seg!$G$64 -> 166.55173 | H91: =Seg!$H$64 -> 221.18297 | I91: =Seg!$I$64 -> 280.27346 | J91: =Seg!$J$64 -> 338.80095 | K91: =Seg!$K$64 -> 389.8857 | L91: =Seg!$L$64 -> 430.08069 | M91: =Seg!$M$64 -> 459.45624 | N91: =Seg!$N$64 -> 60.14 | O91: =Seg!$O$64 -> 68.585
A92: North America | B92: US$bn | C92: =Seg!$C$57 -> 387.497 | D92: =Seg!$D$57 -> 426.305 | E92: =Seg!$E$57 -> 220.32 | F92: =Seg!$F$57 -> 250.63977 | G92: =Seg!$G$57 -> 470.95977 | H92: =Seg!$H$57 -> 521.38699 | I92: =Seg!$I$57 -> 570.14386 | J92: =Seg!$J$57 -> 615.39144 | K92: =Seg!$K$57 -> 655.20823 | L92: =Seg!$L$57 -> 697.80774 | M92: =Seg!$M$57 -> 743.39933 | N92: =Seg!$N$57 -> 192.955 | O92: =Seg!$O$57 -> 233.35
A93: International | B93: US$bn | C93: =Seg!$C$58 -> 142.906 | D93: =Seg!$D$58 -> 161.894 | E93: =Seg!$E$58 -> 81.986 | F93: =Seg!$F$58 -> 98.408468 | G93: =Seg!$G$58 -> 180.39447 | H93: =Seg!$H$58 -> 199.7099 | I93: =Seg!$I$58 -> 218.38553 | J93: =Seg!$J$58 -> 235.71697 | K93: =Seg!$K$58 -> 250.96823 | L93: =Seg!$L$58 -> 267.28537 | M93: =Seg!$M$58 -> 284.74858 | N93: =Seg!$N$58 -> 70.274 | O93: =Seg!$O$58 -> 91.62
A94: AWS | B94: US$bn | C94: =Seg!$C$64 -> 107.556 | D94: =Seg!$D$64 -> 128.725 | E94: =Seg!$E$64 -> 79.819 | F94: =Seg!$F$64 -> 86.732733 | G94: =Seg!$G$64 -> 166.55173 | H94: =Seg!$H$64 -> 221.18297 | I94: =Seg!$I$64 -> 280.27346 | J94: =Seg!$J$64 -> 338.80095 | K94: =Seg!$K$64 -> 389.8857 | L94: =Seg!$L$64 -> 430.08069 | M94: =Seg!$M$64 -> 459.45624 | N94: =Seg!$N$64 -> 60.14 | O94: =Seg!$O$64 -> 68.585
A95: AWS AI（命題子列） | B95: US$bn | C95: =Seg!$C$62 -> 2.3210054 | D95: =Seg!$D$62 -> 8.7037701 | E95: =Seg!$E$62 -> 8.510353 | F95: =Seg!$F$62 -> 14.963434 | G95: =Seg!$G$62 -> 23.473787 | H95: =Seg!$H$62 -> 60.165891 | I95: =Seg!$I$62 -> 101.5037 | J95: =Seg!$J$62 -> 143.02541 | K95: =Seg!$K$62 -> 178.44812 | L95: =Seg!$L$62 -> 201.7281 | M95: =Seg!$M$62 -> 212.83544 | N95: =Seg!$N$62 -> 3.0463195 | O95: =Seg!$O$62 -> 5.6574506
A96: AWS 其他 | B96: US$bn | C96: =Seg!$C$63 -> 105.23499 | D96: =Seg!$D$63 -> 120.02123 | E96: =Seg!$E$63 -> 71.308647 | F96: =Seg!$F$63 -> 71.7693 | G96: =Seg!$G$63 -> 143.07795 | H96: =Seg!$H$63 -> 161.01708 | I96: =Seg!$I$63 -> 178.76976 | J96: =Seg!$J$63 -> 195.77554 | K96: =Seg!$K$63 -> 211.43758 | L96: =Seg!$L$63 -> 228.35259 | M96: =Seg!$M$63 -> 246.62079 | N96: =Seg!$N$63 -> 57.09368 | O96: =Seg!$O$63 -> 62.927549
A97: 合併營收 | B97: US$bn | C97: =Seg!$C$65 -> 637.959 | D97: =Seg!$D$65 -> 716.924 | E97: =Seg!$E$65 -> 382.125 | F97: =Seg!$F$65 -> 435.78098 | G97: =Seg!$G$65 -> 817.90598 | H97: =Seg!$H$65 -> 942.27986 | I97: =Seg!$I$65 -> 1068.8028 | J97: =Seg!$J$65 -> 1189.9094 | K97: =Seg!$K$65 -> 1296.0622 | L97: =Seg!$L$65 -> 1395.1738 | M97: =Seg!$M$65 -> 1487.6041 | N97: =Seg!$N$65 -> 323.369 | O97: =Seg!$O$65 -> 393.555
A98: 檢查（情境 B）：零售營收線合計 − (North America＋International) | B98: US$bn | C98: =PL!$C$85+PL!$C$86+PL!$C$87+PL!$C$88+PL!$C$89+PL!$C$90-(PL!$C$92+PL!$C$93) -> 0 | D98: =PL!$D$85+PL!$D$86+PL!$D$87+PL!$D$88+PL!$D$89+PL!$D$90-(PL!$D$92+PL!$D$93) -> 0 | E98: =PL!$E$85+PL!$E$86+PL!$E$87+PL!$E$88+PL!$E$89+PL!$E$90-(PL!$E$92+PL!$E$93) -> 0 | F98: =PL!$F$85+PL!$F$86+PL!$F$87+PL!$F$88+PL!$F$89+PL!$F$90-(PL!$F$92+PL!$F$93) -> 0 | G98: =PL!$G$85+PL!$G$86+PL!$G$87+PL!$G$88+PL!$G$89+PL!$G$90-(PL!$G$92+PL!$G$93) -> 0 | H98: =PL!$H$85+PL!$H$86+PL!$H$87+PL!$H$88+PL!$H$89+PL!$H$90-(PL!$H$92+PL!$H$93) -> 0 | I98: =PL!$I$85+PL!$I$86+PL!$I$87+PL!$I$88+PL!$I$89+PL!$I$90-(PL!$I$92+PL!$I$93) -> 0 | J98: =PL!$J$85+PL!$J$86+PL!$J$87+PL!$J$88+PL!$J$89+PL!$J$90-(PL!$J$92+PL!$J$93) -> 0 | K98: =PL!$K$85+PL!$K$86+PL!$K$87+PL!$K$88+PL!$K$89+PL!$K$90-(PL!$K$92+PL!$K$93) -> 0 | L98: =PL!$L$85+PL!$L$86+PL!$L$87+PL!$L$88+PL!$L$89+PL!$L$90-(PL!$L$92+PL!$L$93) -> 0 | M98: =PL!$M$85+PL!$M$86+PL!$M$87+PL!$M$88+PL!$M$89+PL!$M$90-(PL!$M$92+PL!$M$93) -> 0 | N98: =PL!$N$85+PL!$N$86+PL!$N$87+PL!$N$88+PL!$N$89+PL!$N$90-(PL!$N$92+PL!$N$93) -> 0 | O98: =PL!$O$85+PL!$O$86+PL!$O$87+PL!$O$88+PL!$O$89+PL!$O$90-(PL!$O$92+PL!$O$93) -> 0
A99: 檢查（情境 B）：AWS AI＋AWS 其他 − AWS | B99: US$bn | C99: =PL!$C$95+PL!$C$96-PL!$C$94 -> 0 | D99: =PL!$D$95+PL!$D$96-PL!$D$94 -> 0 | E99: =PL!$E$95+PL!$E$96-PL!$E$94 -> 0 | F99: =PL!$F$95+PL!$F$96-PL!$F$94 -> 0 | G99: =PL!$G$95+PL!$G$96-PL!$G$94 -> 0 | H99: =PL!$H$95+PL!$H$96-PL!$H$94 -> 0 | I99: =PL!$I$95+PL!$I$96-PL!$I$94 -> 0 | J99: =PL!$J$95+PL!$J$96-PL!$J$94 -> 0 | K99: =PL!$K$95+PL!$K$96-PL!$K$94 -> 0 | L99: =PL!$L$95+PL!$L$96-PL!$L$94 -> 0 | M99: =PL!$M$95+PL!$M$96-PL!$M$94 -> 0 | N99: =PL!$N$95+PL!$N$96-PL!$N$94 -> 0 | O99: =PL!$O$95+PL!$O$96-PL!$O$94 -> 0
A100: 檢查（情境 B）：營收線合計（含 AWS）− 合併營收 | B100: US$bn | C100: =PL!$C$85+PL!$C$86+PL!$C$87+PL!$C$88+PL!$C$89+PL!$C$90+PL!$C$91-PL!$C$97 -> 0 | D100: =PL!$D$85+PL!$D$86+PL!$D$87+PL!$D$88+PL!$D$89+PL!$D$90+PL!$D$91-PL!$D$97 -> 0 | E100: =PL!$E$85+PL!$E$86+PL!$E$87+PL!$E$88+PL!$E$89+PL!$E$90+PL!$E$91-PL!$E$97 -> 0 | F100: =PL!$F$85+PL!$F$86+PL!$F$87+PL!$F$88+PL!$F$89+PL!$F$90+PL!$F$91-PL!$F$97 -> 0 | G100: =PL!$G$85+PL!$G$86+PL!$G$87+PL!$G$88+PL!$G$89+PL!$G$90+PL!$G$91-PL!$G$97 -> 0 | H100: =PL!$H$85+PL!$H$86+PL!$H$87+PL!$H$88+PL!$H$89+PL!$H$90+PL!$H$91-PL!$H$97 -> 0 | I100: =PL!$I$85+PL!$I$86+PL!$I$87+PL!$I$88+PL!$I$89+PL!$I$90+PL!$I$91-PL!$I$97 -> 0 | J100: =PL!$J$85+PL!$J$86+PL!$J$87+PL!$J$88+PL!$J$89+PL!$J$90+PL!$J$91-PL!$J$97 -> 0 | K100: =PL!$K$85+PL!$K$86+PL!$K$87+PL!$K$88+PL!$K$89+PL!$K$90+PL!$K$91-PL!$K$97 -> 0 | L100: =PL!$L$85+PL!$L$86+PL!$L$87+PL!$L$88+PL!$L$89+PL!$L$90+PL!$L$91-PL!$L$97 -> 0 | M100: =PL!$M$85+PL!$M$86+PL!$M$87+PL!$M$88+PL!$M$89+PL!$M$90+PL!$M$91-PL!$M$97 -> 0 | N100: =PL!$N$85+PL!$N$86+PL!$N$87+PL!$N$88+PL!$N$89+PL!$N$90+PL!$N$91-PL!$N$97 -> 0 | O100: =PL!$O$85+PL!$O$86+PL!$O$87+PL!$O$88+PL!$O$89+PL!$O$90+PL!$O$91-PL!$O$97 -> 0
A101: 檢查（情境 B）：分部合計 − 合併營收 | B101: US$bn | C101: =PL!$C$92+PL!$C$93+PL!$C$94-PL!$C$97 -> 0 | D101: =PL!$D$92+PL!$D$93+PL!$D$94-PL!$D$97 -> 0 | E101: =PL!$E$92+PL!$E$93+PL!$E$94-PL!$E$97 -> 0 | F101: =PL!$F$92+PL!$F$93+PL!$F$94-PL!$F$97 -> 0 | G101: =PL!$G$92+PL!$G$93+PL!$G$94-PL!$G$97 -> 0 | H101: =PL!$H$92+PL!$H$93+PL!$H$94-PL!$H$97 -> 0 | I101: =PL!$I$92+PL!$I$93+PL!$I$94-PL!$I$97 -> 0 | J101: =PL!$J$92+PL!$J$93+PL!$J$94-PL!$J$97 -> 0 | K101: =PL!$K$92+PL!$K$93+PL!$K$94-PL!$K$97 -> 0 | L101: =PL!$L$92+PL!$L$93+PL!$L$94-PL!$L$97 -> 0 | M101: =PL!$M$92+PL!$M$93+PL!$M$94-PL!$M$97 -> 0 | N101: =PL!$N$92+PL!$N$93+PL!$N$94-PL!$N$97 -> 0 | O101: =PL!$O$92+PL!$O$93+PL!$O$94-PL!$O$97 -> 0
A102: 2. 分部營業利益（廣告利潤率 m_ad 計入北美／國際；零售本業利益率＝殘差；自用 AI 成本按北美比例分攤）
A103: North America：廣告利潤（廣告營收 × m_ad） | B103: US$bn | C103: =Seg!$C$59*m_ad -> 20.534156 | D103: =Seg!$D$59*m_ad -> 24.872062 | E103: =Seg!$E$59*m_ad -> 13.501711 | F103: =Seg!$F$59*m_ad -> 16.571972 | G103: =Seg!$G$59*m_ad -> 30.082092 | H103: =Seg!$H$59*m_ad -> 36.115088 | I103: =Seg!$I$59*m_ad -> 42.147538 | J103: =Seg!$J$59*m_ad -> 47.774952 | K103: =Seg!$K$59*m_ad -> 52.552448 | L103: =Seg!$L$59*m_ad -> 57.807692 | M103: =Seg!$M$59*m_ad -> 63.588462 | N103: =Seg!$N$59*m_ad -> 10.854356 | O103: =Seg!$O$59*m_ad -> 14.009473
A104: North America：零售本業營收（分部 − 廣告） | B104: US$bn | C104: =Seg!$C$57-Seg!$C$59 -> 346.42869 | D104: =Seg!$D$57-Seg!$D$59 -> 376.56088 | E104: =Seg!$E$57-Seg!$E$59 -> 193.31658 | F104: =Seg!$F$57-Seg!$F$59 -> 217.49583 | G104: =Seg!$G$57-Seg!$G$59 -> 410.79559 | H104: =Seg!$H$57-Seg!$H$59 -> 449.15681 | I104: =Seg!$I$57-Seg!$I$59 -> 485.84879 | J104: =Seg!$J$57-Seg!$J$59 -> 519.84153 | K104: =Seg!$K$57-Seg!$K$59 -> 550.10333 | L104: =Seg!$L$57-Seg!$L$59 -> 582.19235 | M104: =Seg!$M$57-Seg!$M$59 -> 616.22241 | N104: =Seg!$N$57-Seg!$N$59 -> 171.24629 | O104: =Seg!$O$57-Seg!$O$59 -> 205.33105
...

Sheet CF
A1: CF — 營運現金（淨利＋分部折舊＋SBC＋其他）− 資本支出（AI＋AWS 其他＋零售）− 融資租賃本金 → 自由現金流；股利 0、回購 0（Amazon 無）；現金低於最低現金即舉債
A4: 收支關卡（地圖讀取；列標籤固定）
A5: 項目 | B5: A（樂觀） | C5: B（基準） | D5: C（保守） | E5: 情境加權 | F5: 說明
A6: 收支關卡：自由現金流扣股利（五年合計） | B6: =CF!$G$40 -> 192.9245 | C6: =CF!$G$71 -> 10.193991 | D6: =CF!$G$102 -> -51.594154 | E6: =w_A*B6+w_B*C6+w_C*D6 -> 40.429582 | F6: FY2026–FY2030（首年起五年；FY2026＝1H 實績＋2H 模型）自由現金流扣股利合計；負值＝入不敷出（地圖收支關卡）
A7: FY2026–FY2030 新增借款合計（不含已發行債券） | B7: =CF!$G$41 -> 0.18201744 | C7: =CF!$G$72 -> 29.283413 | D7: =CF!$G$103 -> 47.797832
A8: 是否需要舉債 | B8: =IF(B7>=1,"需要舉債",IF(B7>0,"幾乎不需要（新增借款少於 1）","不需要（現金足以支應）")) -> 幾乎不需要（新增借款少於 1） | C8: =IF(C7>=1,"需要舉債",IF(C7>0,"幾乎不需要（新增借款少於 1）","不需要（現金足以支應）")) -> 需要舉債 | D8: =IF(D7>=1,"需要舉債",IF(D7>0,"幾乎不需要（新增借款少於 1）","不需要（現金足以支應）")) -> 需要舉債 | F8: 已發行的 2026 下半年債券 29.25 不計；現金低於最低現金 50 時舉債
A9: 回購是否需停止 | B9: 無回購可減（2023–2026H1 皆為 0） | C9: 無回購可減（2023–2026H1 皆為 0） | D9: 無回購可減（2023–2026H1 皆為 0）
A10: FY2028 自由現金流（扣股利） | B10: =CF!$I$29 -> 19.264651 | C10: =CF!$I$60 -> -15.545135 | D10: =CF!$I$91 -> -27.630111
A11: 檢查：收支關卡＝首年起五年自由現金流扣股利（逐欄加總；三情境絕對值合計） | B11: =ABS(CF!$G$42)+ABS(CF!$G$73)+ABS(CF!$G$104) -> 0
A14: CF｜情境 A（樂觀）：營運現金 − 資本支出 − 租賃本金 → 自由現金流；股利、回購、借款與淨現金
A15: 項目 | B15: 單位 | C15: FY2024A | D15: FY2025A | E15: 1H26A | F15: 2H26E | G15: FY2026E（1H 實績＋2H 模型） | H15: FY2027E | I15: FY2028E | J15: FY2029E | K15: FY2030E | L15: FY2031E | M15: FY2032E | N15: 1H25A | O15: 2H25A | P15: 說明 | R15: 2023 | S15: 2024 | T15: 2025 | U15: 2026 | V15: 2027 | W15: 2028 | X15: 2029 | Y15: 2030 | Z15: 2031 | AA15: 2032
A16: 淨利 | B16: US$bn | C16: =PL!$C$73 -> 59.248 | D16: =PL!$D$73 -> 77.67 | E16: =PL!$E$73 -> 92.902 | F16: =PL!$F$73 -> 48.098774 | G16: =PL!$G$73 -> 141.00077 | H16: =PL!$H$73 -> 120.10123 | I16: =PL!$I$73 -> 154.14711 | J16: =PL!$J$73 -> 189.06094 | K16: =PL!$K$73 -> 217.63868 | L16: =PL!$L$73 -> 245.60806 | M16: =PL!$M$73 -> 270.53191
A17: 分部折舊攤銷（PP&E） | B17: US$bn | C17: =PL!$C$61 -> 32.067 | D17: =PL!$D$61 -> 41.86 | E17: =PL!$E$61 -> 26.703 | F17: =PL!$F$61 -> 29.197368 | G17: =PL!$G$61 -> 55.900368 | H17: =PL!$H$61 -> 84.574989 | I17: =PL!$I$61 -> 118.04212 | J17: =PL!$J$61 -> 152.27209 | K17: =PL!$K$61 -> 186.73365 | L17: =PL!$L$61 -> 210.8533 | M17: =PL!$M$61 -> 227.39414
A18: 股份基礎給付（加回） | B18: US$bn | C18: =Q!$D$48 -> 22.011 | D18: =Q!$E$48 -> 19.467 | E18: =Q!$P$48 -> 10.07 | F18: =sbc_r*Seg!$F$30 -> 10.850704 | G18: =CF!$E$18+CF!$F$18 -> 20.920704 | H18: =sbc_r*Seg!$H$30 -> 23.955473 | I18: =sbc_r*Seg!$I$30 -> 27.687541 | J18: =sbc_r*Seg!$J$30 -> 31.287885 | K18: =sbc_r*Seg!$K$30 -> 34.42968 | L18: =sbc_r*Seg!$L$30 -> 37.222479 | M18: =sbc_r*Seg!$M$30 -> 39.674785
A19: 其他營運項目（營運資金、影音內容與租賃現金支出、非現金業外） | B19: US$bn | C19: =Q!$D$44-CF!$C$16-CF!$C$17-CF!$C$18 -> 2.551 | D19: =Q!$E$44-CF!$D$16-CF!$D$17-CF!$D$18 -> 0.517 | E19: =Q!$P$44-CF!$E$16-CF!$E$17-CF!$E$18 -> -58.256 | F19: =oth_r*Seg!$F$30 -> 5.2226525 | G19: =CF!$E$19+CF!$F$19 -> -53.033347 | H19: =oth_r*Seg!$H$30 -> 11.53023 | I19: =oth_r*Seg!$I$30 -> 13.326546 | J19: =oth_r*Seg!$J$30 -> 15.059461 | K19: =oth_r*Seg!$K$30 -> 16.571668 | L19: =oth_r*Seg!$L$30 -> 17.915895 | M19: =oth_r*Seg!$M$30 -> 19.096238 | P19: oth_r 已含營運資金（修正一：不再另加 2H25 營運資金，避免重複）；實績含持股評價利益的扣除
A20: 營運現金流 | B20: US$bn | C20: =Q!$D$44 -> 115.877 | D20: =Q!$E$44 -> 139.514 | E20: =Q!$P$44 -> 71.419 | F20: =CF!$F$16+CF!$F$17+CF!$F$18+CF!$F$19 -> 93.369499 | G20: =CF!$E$20+CF!$F$20 -> 164.7885 | H20: =CF!$H$16+CF!$H$17+CF!$H$18+CF!$H$19 -> 240.16193 | I20: =CF!$I$16+CF!$I$17+CF!$I$18+CF!$I$19 -> 313.20332 | J20: =CF!$J$16+CF!$J$17+CF!$J$18+CF!$J$19 -> 387.68038 | K20: =CF!$K$16+CF!$K$17+CF!$K$18+CF!$K$19 -> 455.37369 | L20: =CF!$L$16+CF!$L$17+CF!$L$18+CF!$L$19 -> 511.59973 | M20: =CF!$M$16+CF!$M$17+CF!$M$18+CF!$M$19 -> 556.69707
A21: 資本支出：AI（Thesis） | B21: US$bn | C21: =Thesis!$C$35 -> 25.278105 | D21: =Thesis!$D$35 -> 69.568632 | E21: =Thesis!$E$35 -> 64.189921 | F21: =Thesis!$F$35 -> 98.862028 | G21: =Thesis!$G$35 -> 163.05195 | H21: =Thesis!$H$35 -> 203.96415 | I21: =Thesis!$I$35 -> 210.20424 | J21: =Thesis!$J$35 -> 215.44101 | K21: =Thesis!$K$35 -> 159.13809 | L21: =Thesis!$L$35 -> 134.25578 | M21: =Thesis!$M$35 -> 134.96817
A22: 資本支出：AWS 其他（cx_awso × AWS 其他營收） | B22: US$bn | C22: =cx_awso*Seg!$C$28 -> 21.046999 | D22: =cx_awso*Seg!$D$28 -> 24.004246 | E22: =cx_awso*Seg!$E$28 -> 14.261729 | F22: =cx_awso*Seg!$F$28 -> 14.35386 | G22: =CF!$E$22+CF!$F$22 -> 28.615589 | H22: =cx_awso*Seg!$H$28 -> 32.203415 | I22: =cx_awso*Seg!$I$28 -> 35.753952 | J22: =cx_awso*Seg!$J$28 -> 39.155108 | K22: =cx_awso*Seg!$K$28 -> 42.287516 | L22: =cx_awso*Seg!$L$28 -> 45.670518 | M22: =cx_awso*Seg!$M$28 -> 49.324159
A23: 資本支出：零售（cx_rt × 零售營收） | B23: US$bn | C23: =Q!$D$46-CF!$C$21-CF!$C$22 -> 31.332896 | D23: =Q!$E$46-CF!$D$21-CF!$D$22 -> 34.747122 | E23: =Q!$P$46-CF!$E$21-CF!$E$22 -> 17.85835 | F23: =cx_rt*Seg!$F$20 -> 20.453758 | G23: =CF!$E$23+CF!$F$23 -> 38.312108 | H23: =cx_rt*Seg!$H$20 -> 42.414231 | I23: =cx_rt*Seg!$I$20 -> 46.380473 | J23: =cx_rt*Seg!$J$20 -> 50.061243 | K23: =cx_rt*Seg!$K$20 -> 53.30024 | L23: =cx_rt*Seg!$L$20 -> 56.765602 | M23: =cx_rt*Seg!$M$20 -> 60.474357
A24: 資本支出（現金，淨額） | B24: US$bn | C24: =Q!$D$46 -> 77.658 | D24: =Q!$E$46 -> 128.32 | E24: =Q!$P$46 -> 96.31 | F24: =CF!$F$21+CF!$F$22+CF!$F$23 -> 133.66965 | G24: =CF!$E$24+CF!$F$24 -> 229.97965 | H24: =CF!$H$21+CF!$H$22+CF!$H$23 -> 278.5818 | I24: =CF!$I$21+CF!$I$22+CF!$I$23 -> 292.33867 | J24: =CF!$J$21+CF!$J$22+CF!$J$23 -> 304.65736 | K24: =CF!$K$21+CF!$K$22+CF!$K$23 -> 254.72584 | L24: =CF!$L$21+CF!$L$22+CF!$L$23 -> 236.69189 | M24: =CF!$M$21+CF!$M$22+CF!$M$23 -> 244.76668
