Workbook

Sheet README
A1: Amazon（AMZN）個股模型 v0.3.1（命題模組＋官方營收分部 → 損益表；2026Q3 季度滾動） 2026-10-31
A2: 版本：v0.3.1（2026Q3 財報 2026-10-29 滾入；v0.3 為 2026-10-27）。資料截至 2026-09-30（2026Q3 新聞稿；10-Q 未取得，附註數字沿用 2026Q2）；FY2026＝9M 實績＋Q4 模型；Tokenomics v21.7（Trainium 改讀 IF_NonNV_Hold_Trn）。
A3: 命題：AWS 的 AI 容量（Trainium＋NVIDIA）能否以高於資金成本的報酬變現，零售與廣告的現金流能否支應資本支出。
A4: 核心問題：FY2028 AWS 營業利益率與自由現金流（扣股利後）是否轉正並維持。
A5: ="投資建議："&Val!B24&"（加權目標價 US$"&TEXT(Val!B19,"0.00")&"，現價 US$"&TEXT(px,"0.00")&"〔2026-10-30〕，上檔空間 "&TEXT(Val!B21,"+0.0%;-0.0%")&"；依五級固定規則）" -> 投資建議：中立（加權目標價 US$217.65，現價 US$240.35〔2026-10-30〕，上檔空間 -9.4%；依五級固定規則）
A6: ="命題答案（情境 B）：FY2028 對外 AI ROIC "&TEXT(Thesis!$I$130,"0.0%")&"，WACC "&TEXT(wacc,"0.0%")&"；打平所需機隊平均 k "&TEXT(Thesis!$I$132,"0.00")&"，模型 k "&TEXT(Thesis!$I$131,"0.00")&"。FY2028 AWS 營業利益率 "&TEXT(PL!$I$123,"0.0%")&"（FY2025 "&TEXT(PL!$D$123,"0.0%")&"）；FY2028 自由現金流扣股利 "&TEXT(CF!$I$59,"#,##0.0")&"；收支關卡（FY2026–FY2030 合計，情境加權）"&TEXT(CF!E6,"#,##0.0")&"。" -> 命題答案（情境 B）：FY2028 對外 AI ROIC 4.9%，WACC 11.2%；打平所需機隊平均 k 1.30，模型 k 0.99。FY2028 AWS 營業利益率 32.8%（FY2025 35.4%）；FY2028 自由現金流扣股利 0.6；收支關卡（FY2026–FY2030 合計，情境加權）118.8。
A7: ="重點觀察 1：目標價 US$"&TEXT(Val!B19,"0.00")&"＝DCF "&TEXT(Val!B17,"0.00")&"（永續價值占 EV "&TEXT(Val!C8,"0%")&"）與分部加總 "&TEXT(Val!B18,"0.00")&" 各半；DCF 低是因為 WACC "&TEXT(wacc,"0.0%")&" 下，2027–2029 的 AI 資本支出（情境 B FY2027 "&TEXT(CF!$H$54,"#,##0")&"）讓 FCFF 偏低，而 AI 增量報酬接近資金成本。" -> 重點觀察 1：目標價 US$217.65＝DCF 147.30（永續價值占 EV 77%）與分部加總 288.00 各半；DCF 低是因為 WACC 11.2% 下，2027–2029 的 AI 資本支出（情境 B FY2027 253）讓 FCFF 偏低，而 AI 增量報酬接近資金成本。
A8: ="重點觀察 2：分部加總中 AWS 其他（非 AI 雲端）占 "&TEXT(Val!$C$166/Val!$C$174,"0%")&"、廣告占 "&TEXT(Val!$C$160/Val!$C$174,"0%")&"；零售本業未來 12 個月 EBITDA（SBC 加回）"&TEXT(Val!$C$161,"#,##0")&"；AWS AI 以自身 DCF 計 "&TEXT(Val!$C$173,"#,##0")&"。" -> 重點觀察 2：分部加總中 AWS 其他（非 AI 雲端）占 47%、廣告占 17%；零售本業未來 12 個月 EBITDA（SBC 加回）58；AWS AI 以自身 DCF 計 58。
A9: ="重點觀察 3：三情境目標價 A "&TEXT(Val!B7,"0")&"／B "&TEXT(Val!C7,"0")&"／C "&TEXT(Val!D7,"0")&"（差異來自新產能 k 與 MW 速度，In 頁 J 節）；讀法 1 加權 "&TEXT(Val!B33,"0.00")&"；市場共識目標價 "&TEXT(cons_tp,"0")&"；v0.3 加權目標價 "&TEXT(v03_tp,"0.00")&"（拆解見 Recon D 節）。" -> 重點觀察 3：三情境目標價 A 263／B 208／C 191（差異來自新產能 k 與 MW 速度，In 頁 J 節）；讀法 1 加權 198.51；市場共識目標價 332；v0.3 加權目標價 215.58（拆解見 Recon D 節）。
A11: 驅動 → 推導對照表（每頁輸入、推導量、因果方向）
A12: In → Thesis：對外 AI MW（6/30 機隊 2,080 MW、評價日 9/30 加一季 C10 速度、之後每年新增 pace）× Tokenomics IF_HoldEcon × k → AWS AI 營收；新增 MW ÷ 對外比例 ×（IT＋自建機房成本）→ AI 資本支出 → IT 6 年／機房 20 年折舊 → AWS AI 營業利益（對外）與自用 AI 成本（零售）。
A13: In → Seg：零售六條營收線（Q4 26＝Q4 25 ×（1＋9M26 年增）× 校準係數〔Q4 合併營收＝指引中點〕，之後收斂到長期年增）→ 零售合計 × 北美比例 → North America／International；AWS＝AWS AI＋AWS 其他（殘差起算、收斂到 8%）。
A14: Seg、Thesis → PL：北美／國際營業利益＝廣告營收 × 50%＋零售本業營收 × 本業利益率（實績殘差＋每年改善）− 自用 AI 成本；AWS 營業利益＝AWS AI＋AWS 其他 × 近四季利益率 → 合併營業利益 → 利息（CF）、稅 17.4% → 淨利 → EPS。
A15: PL → CF：淨利＋分部折舊＋SBC＋其他 − 資本支出（AI＋AWS 其他 20%＋零售 5.9%）− 融資租賃本金 → 自由現金流；股利 0、回購 0；現金低於 50 即舉債 → 利息費用回到 PL。
A16: PL、CF → Val：DCF（FCFF、WACC、RONIC 永續）＋分部加總（廣告、零售本業、AWS 其他、AWS AI × 同業倍數）＋持股（Anthropic、OpenAI）→ 情境目標價 → 情境加權 → 上檔空間 → 投資建議。
A18: 工作表：README → In（輸入；J 節情境驅動對照）→ Q（實績與核對）→ Thesis（命題模組）→ Seg（營收分部）→ PL → CF → Val → Recon（共識、指引、v0.3 拆解）→ Sens（敏感度）→ Sources。
A19: 標記：Verified、Interested-party、Analogy、Assumed、Derived。沿用 v0.2.2：k 規格（kspec.py）、對外比例、WACC 輸入、持股與同業倍數。SemiAnalysis 未使用。In 頁 D／F＝敏感度低／高，只用於 Sens 頁；共識區間只作對照。
A20: 已知限制：(1) 公司未揭露 AI 在役 MW、對外比例與 AI 營收，AWS AI／AWS 其他的歷史分拆為估計；(2) 分部共識未找到，合併共識為財報前；(3) 同業倍數沿用 2026-10-07；(4) 到期債務假設全數再融資；(5) 10-Q 未取得：債務面額、在建、分部折舊、租賃為推導或沿用 2026Q2。

Sheet In
A1: In — 輸入（藍字；基準欄 E 進主模型；D／F＝敏感度低／高，只用於 Sens 頁〔一次動一個參數〕、不進目標價；情境 A／B／C 的驅動見本頁最後一節「J. 情境驅動對照」〔v0.3.1〕）。金額 US$bn、每股 US$、MW＝IT 關鍵電力 MW。每列一個鍵（定義名稱＝鍵）；Analogy、Assumed 一律給低／高區間
A2: 標記：Verified／Interested-party／Analogy／Assumed／Derived。「沿用 v0.2.2」＝v0.2.2 已核准的參數與證據（k 規格 kspec.py、對外比例），出處見 legacy_v0.2/ 與 docs/handoff。不以公司 AWS 營收、backlog、run-rate 反推 k 或每 MW 價格（共同規則第 4 節）；公司說法只作 Recon 驗證列。SemiAnalysis 未使用。資料截至 2026-09-30（2026Q3 新聞稿；10-Q 未取得）
A3: 鍵 | B3: 項目 | C3: 單位 | D3: 敏感度低 | E3: 基準 | F3: 敏感度高 | G3: 標記 | H3: 來源 | I3: 說明
A4: A. 價格、股數與共識目標價
A5: px | B5: AMZN 現價（2026-10-30 收盤） | C5: US$ | E5: 240.35 | G5: Verified | H5: S15；S16 | I5: 10-29 收盤 243.79（財報日，−4.3%）；只影響上檔空間與評等
A6: px_val | B6: WACC 權益權重用股價（最近收盤；評價日 2026-09-30 收盤本輪未取得） | C6: US$ | E6: 240.35 | G6: Verified | H6: S15 | I6: 與現價分開：現價變動只影響上檔空間（拆解 (e)），本列變動歸 (f)
A7: sh_out | B7: 流通股數（2026-09-30，資產負債表股本說明） | C7: 十億股 | E7: 10.811 | G7: Interested-party | H7: S13 | I7: 10-Q 封面股數未取得；Supplemental 同值 10,811 百萬股
A8: sh_awd | B8: 未歸屬股份獎勵（2026-09-30） | C8: 十億股 | E8: 0.223 | G8: Interested-party | H8: S13 | I8: 223 百萬股（Supplemental）
A9: sh_val | B9: 分部加總用稀釋股數＝流通股數＋未歸屬獎勵（倍數為 SBC 加回口徑，故計入稀釋） | C9: 十億股 | E9: =sh_out+sh_awd -> 11.034 | G9: Derived | H9: 修正一（F2） | I9: DCF 視 SBC 為現金成本，改用流通股數 sh_out，不另計稀釋
A10: cons_tp | B10: 市場共識目標價（Koyfin 60 位平均，2026-10-30 財報後） | C10: US$ | D10: 230 | E10: 332.41 | F10: 405 | G10: Interested-party | H10: S17；S18 | I10: MarketBeat 60 位 325.12（10-29）；區間為最低／最高目標價；只作對照，不進模型
A11: B. 折現率（CAPM）
A12: rf | B12: 無風險利率（10 年美債，2026-10-28） | C12: % | E12: 0.0499 | G12: Verified | H12: S33 | I12: v0.3 為 5.00%（10-26）
A13: beta_sa | B13: 原始 Beta：StockAnalysis 5 年月資料（Yahoo 同值，推測同源） | C13: x | E13: 1.46 | G13: Verified | H13: 沿用 v0.2.2（事實總帳 val.beta.sa）
A14: beta_gf | B14: 原始 Beta：GuruFocus 3 年 | C14: x | E14: 1.567 | G14: Verified | H14: 沿用 v0.2.2（事實總帳 val.beta.gurufocus） | I14: 不同資料商、不同期間（C13 獨立來源）
A15: beta | B15: Beta（Blume 調整 0.67 × 原始＋0.33，兩個獨立來源的中位數） | C15: x | D15: =MIN(0.67*beta_sa+0.33,0.67*beta_gf+0.33) -> 1.3082 | E15: =MEDIAN(0.67*beta_sa+0.33,0.67*beta_gf+0.33) -> 1.344045 | F15: =MAX(0.67*beta_sa+0.33,0.67*beta_gf+0.33) -> 1.37989 | G15: Derived | H15: 修正一（F4） | I15: 低／高＝單一來源
A16: erp | B16: 股權風險溢酬 | C16: % | D16: 0.04 | E16: 0.05 | F16: 0.06 | G16: Assumed | H16: 沿用 v0.2.2（對照表預設 10）
A17: kd_new | B17: 新增借款利率（2026-07 新發 2066 票據有效利率；只用於利息費用） | C17: % | E17: 0.0633 | G17: Interested-party | H17: S02 | I17: 期後事項：固定票面 4.60%–6.25%、有效 4.67%–6.33%
A18: kd_spr | B18: AA 級公司債約 10 年期利差（相對 10 年美債） | C18: % | D18: 0.005 | E18: 0.0065 | F18: 0.01 | G18: Assumed | H18: 修正一（F4）：kd＝約 10 年期公司債殖利率 | I18: Amazon 各期票據的 10 年期殖利率：未找到
A19: kd | B19: 稅前債務成本（WACC 用）＝rf＋利差 | C19: % | E19: =rf+kd_spr -> 0.0564 | G19: Derived | H19: 修正一（F4）
A20: tax | B20: 稅率（2023–2025 有效稅率平均） | C20: % | D20: 0.135 | E20: =AVERAGE(Q!$C$42,Q!$D$42,Q!$E$42) -> 0.17358453 | F20: 0.23 | G20: Derived | H20: S01 | I20: 18.96%、13.50%、19.61%；9M26 有效稅率 23.0%（含 Anthropic 評價利益的遞延稅）
A21: debt_q3 | B21: 債務面額（2026-09-30，推導：6/30 面額 133.0＋Q3 長期借款收入 48.1 − 償還） | C21: US$bn | E21: 181.09 | G21: Derived | H21: S02；S13 | I21: 10-Q 附註未取得；帳面法（長期債帳面變動）為 177.2，差額主要是 2027 年到期票據轉入流動部分
A22: fl_pv | B22: 融資租賃負債現值（沿用 2026-06-30；10-Q 未取得） | C22: US$bn | E22: 13.451 | G22: Verified | H22: S02 | I22: 附註 4；Q3 新增融資租賃取得 1.47、本金償還 0.43
A23: fin_obl | B23: 融資義務（financing obligations；沿用 2026-06-30） | C23: US$bn | E23: 11.07 | G23: Verified | H23: S02
A24: fin_debt | B24: 類債務（融資租賃＋融資義務；淨負債與 WACC 的 D 皆計入，模型期間持平） | C24: US$bn | E24: =fl_pv+fin_obl -> 24.521 | G24: Derived | H24: 修正一（F6、核對第 4 點）
A25: ke | B25: 股權成本＝rf＋β × ERP | C25: % | E25: =rf+beta*erp -> 0.11710225 | G25: Derived | H25: CAPM
A26: wacc_adj | B26: WACC 調整（Sens 用；基準 0） | C26: pt | D26: -0.01 | E26: 0 | F26: 0.01 | G26: Assumed | H26: Sens
A27: wacc | B27: WACC＝E/(D+E) × ke＋D/(D+E) × kd ×（1 − 稅率）＋調整；E＝評價用股價 × 流通股數；D＝債務面額＋類債務 | C27: % | E27: =px_val*sh_out/(px_val*sh_out+debt_q3+fin_debt)*ke+(debt_q3+fin_debt)/(px_val*sh_out+debt_q3+fin_debt)*kd*(1-tax)+wacc_adj -> 0.11193326 | G27: Derived | H27: 修正一（F4）
A28: tg | B28: 永續成長率 g | C28: % | D28: 0.02 | E28: 0.03 | F28: 0.04 | G28: Assumed | H28: 工作單第 2 節（g 3%）
A29: ronic | B29: 永續期新投資報酬率（RONIC；預設＝WACC：永續成長不創造價值） | C29: % | E29: =wacc -> 0.11193326 | F29: =wacc+0.05 -> 0.16193326 | G29: Assumed | H29: 判斷（v0.3 報告第 5 節；F5） | I29: 高值＝WACC＋5pt（Sens）
A30: w_dcf | B30: 目標價中 DCF 的權重；其餘為分部加總（SOTP） | C30: % | D30: 0.3 | E30: 0.5 | F30: 0.7 | G30: Assumed | H30: 工作單第 2 節（[判斷] 預設 DCF 50%＋分部加總 50%） | I30: Andy 可改；低／高只用於 Sens
A31: w_A | B31: 情境權重 A（樂觀） | C31: % | E31: 0.25 | G31: Assumed | H31: 工作單第 2 節（[判斷] 預設 A 25%／B 50%／C 25%） | I31: 三者合計 100%
A32: w_B | B32: 情境權重 B（基準） | C32: % | E32: 0.5 | G32: Assumed | H32: 工作單第 2 節（[判斷] 預設 A 25%／B 50%／C 25%） | I32: 三者合計 100%
A33: w_C | B33: 情境權重 C（保守） | C33: % | E33: 0.25 | G33: Assumed | H33: 工作單第 2 節（[判斷] 預設 A 25%／B 50%／C 25%） | I33: 三者合計 100%
A34: tp_yf | B34: 目標價時點（2027-10-31，約 12 個月後）距 DCF 基準日（2026-12-31）年數 | C34: 年 | E34: =(DATE(2027,10,31)-DATE(2026,12,31))/365 -> 0.83287671 | G34: Derived | H34: 目標價約 12 個月後 | I34: v0.3 為 2027-10-27；DCF 情境價值以 ke 推到目標價時點
A35: C. 命題模組：AWS AI（對外 AI 在役 MW × 每 MW 年收入）
A36: mw_ye23 | B36: 對外 AI 在役 MW（2023 年底） | C36: MW | E36: 120 | G36: Assumed | H36: 沿用 v0.2.2（defaults.mwYearEnd） | I36: 公司未揭露 AI 在役 MW；只用於歷史分拆與折舊年份
A37: mw_ye24 | B37: 對外 AI 在役 MW（2024 年底） | C37: MW | E37: 360 | G37: Assumed | H37: 沿用 v0.2.2（defaults.mwYearEnd） | I37: 同上
A38: mw_ye25 | B38: 對外 AI 在役 MW（2025 年底） | C38: MW | D38: 1100 | E38: 1440 | F38: 1800 | G38: Assumed | H38: 沿用 v0.2.2（defaults.mwYearEnd） | I38: Trainium2 1.4M 顆 × 0.871 kW ≈ 1,220 MW-IT（事實總帳 chip.trn2.mwFromLanded）
A39: mw_open | B39: 對外 AI 在役 MW（2026-06-30；期初機隊錨點）＝在役 AI 2,600 × 對外 80% | C39: MW | D39: 1400 | E39: 2080 | F39: 2970 | G39: Derived | H39: S24；S25 | I39: Epoch 三站 1,422 MW（Trainium2）＋NVIDIA 推估；第三方估計
A40: pace_A | B40: 情境 A：對外 AI MW 每年新增（公司「2027 年底容量為 2025 年兩倍」，以 MS 6＋8 GW 對照） | C40: MW/年 | E40: 3733 | G40: Derived | H40: 沿用 v0.2.2（scenarios.mwPath.pace.high）；S35 | I40: 每年 +7 GW × AI 占新增 80% ÷ PUE 1.2 × 對外 80%
A41: pace_B | B41: 情境 B：對外 AI MW 每年新增（C10：2026 資本支出指引約 220 隱含的建置速度；下半年視窗） | C41: MW/年 | E41: 3788.9 | G41: Derived | H41: amazon/calib_pace_v031.py → data/pace_v031.json（C10 重解） | I41: （指引 − 上半年實績）÷ 2＝Q4 26 公式資本支出（AI＋非 AI）；把支出換成實體產能，不是以營收反推單價；v0.3 為 3,634.3
A42: pace_C | B42: 情境 C：對外 AI MW 每年新增（與 B 相同：資本支出照指引投入，下檔在變現） | C42: MW/年 | E42: =pace_B -> 3788.9 | G42: Assumed | H42: 判斷（v0.3 報告第 5 節）
A43: pace_x | B43: MW 速度乘數（Sens 用；三情境同乘，評價日前實績不變） | C43: x | D43: 0.75 | E43: 1 | F43: 1.25 | G43: Assumed | H43: Sens
A44: mw_q3 | B44: 對外 AI 在役 MW（評價日 2026-09-30）＝6/30 機隊＋情境 B 速度 × 1 季 | C44: MW | E44: =mw_open+pace_B*0.25 -> 3027.225 | G44: Derived | H44: C10 速度（實績期三情境相同） | I44: 公司未揭露；Q3 現金資本支出 75.9
A45: ext_sh | B45: 對外比例（AI MW 中租給客戶的比例） | C45: % | D45: 0.6 | E45: 0.8 | F45: 1 | G45: Assumed | H45: 沿用 v0.2.2（對照表 r1 C23：公司未揭露、最大不確定） | I45: Sens ±20pt
A46: long_sh | B46: 長約占對外容量比例 | C46: % | D46: 0.7 | E46: 0.8 | F46: 0.9 | G46: Assumed | H46: 沿用 v0.2.2（pricing.longShare） | I46: Anthropic Trainium2 三站＋OpenAI 兩筆占多數
A47: p_spot | B47: H100 現貨價（Silicon Data 指數） | C47: US$/GPU-hr | E47: 2.82 | G47: Verified | H47: S23 | I47: 2026-10-06；MAG 三家共用（C1）
A48: p_list | B48: AWS p5.48xlarge 隨需（每 GPU 小時） | C48: US$/GPU-hr | E48: 6.88 | G48: Verified | H48: S23 | I48: 公開牌價（賣價，非成交價）；k 高軸
A49: p_long | B49: 長約等值價格（判斷倍數 0.75 × v5.27 VR200 成本 12.762） | C49: US$m/MW-年 | E49: 9.5715 | G49: Assumed | H49: 沿用 v0.2.2（legacy_v0.2/kspec.py long.base） | I49: 判斷值，不是觀察到的市場價格
A50: p_long_lo | B50: 長約等值價格下緣（判斷倍數 0.55 × 12.762） | C50: US$m/MW-年 | E50: 7.0191 | G50: Assumed | H50: 沿用 v0.2.2（legacy_v0.2/kspec.py long.low） | I50: Anthropic 下限 0.22–0.45 只作對照
A51: tk_he_h100 | B51: Tokenomics IF_HoldEcon｜Hopper H100（每 MW 年持有成本，經濟口徑） | C51: US$m/MW-年 | D51: 6.7910747 | E51: 9.7030873 | F51: 16.66377 | G51: Derived | H51: S21 | I51: WACC 10% 下的打平持有成本；低／高＝Tokenomics 低成本／高成本欄（Sens 四世代同時，鍵 he_all）
A52: tk_he_gb200 | B52: Tokenomics IF_HoldEcon｜GB200 NVL72（每 MW 年持有成本，經濟口徑） | C52: US$m/MW-年 | D52: 6.6118163 | E52: 8.8281656 | F52: 14.318575 | G52: Derived | H52: S21 | I52: WACC 10% 下的打平持有成本；低／高＝Tokenomics 低成本／高成本欄（Sens 四世代同時，鍵 he_all）
A53: tk_he_gb300 | B53: Tokenomics IF_HoldEcon｜GB300 NVL72（每 MW 年持有成本，經濟口徑） | C53: US$m/MW-年 | D53: 8.4288991 | E53: 10.886411 | F53: 18.534646 | G53: Derived | H53: S21 | I53: WACC 10% 下的打平持有成本；低／高＝Tokenomics 低成本／高成本欄（Sens 四世代同時，鍵 he_all）
A54: tk_he_vr200 | B54: Tokenomics IF_HoldEcon｜VR200 NVL72（每 MW 年持有成本，經濟口徑） | C54: US$m/MW-年 | D54: 9.2190715 | E54: 12.225471 | F54: 19.750627 | G54: Derived | H54: S21 | I54: WACC 10% 下的打平持有成本；低／高＝Tokenomics 低成本／高成本欄（Sens 四世代同時，鍵 he_all）
A55: tk_cx_h100 | B55: Tokenomics IF_CapexIT｜Hopper H100（每 MW IT 資本支出） | C55: US$m/MW | E55: 27.510214 | G55: Derived | H55: S21
A56: tk_cx_gb200 | B56: Tokenomics IF_CapexIT｜GB200 NVL72（每 MW IT 資本支出） | C56: US$m/MW | E56: 24.015174 | G56: Derived | H56: S21
A57: tk_cx_gb300 | B57: Tokenomics IF_CapexIT｜GB300 NVL72（每 MW IT 資本支出） | C57: US$m/MW | E57: 32.237224 | G57: Derived | H57: S21
A58: tk_cx_vr200 | B58: Tokenomics IF_CapexIT｜VR200 NVL72（每 MW IT 資本支出） | C58: US$m/MW | E58: 37.586352 | G58: Derived | H58: S21
A59: tk_ox_h100 | B59: Tokenomics IF_OpexGW｜Hopper H100（每 MW 年營運費用，不含折舊、含電費） | C59: US$m/MW-年 | E59: 1.8846675 | G59: Derived | H59: S21
A60: tk_ox_gb200 | B60: Tokenomics IF_OpexGW｜GB200 NVL72（每 MW 年營運費用，不含折舊、含電費） | C60: US$m/MW-年 | E60: 1.8122327 | G60: Derived | H60: S21
A61: tk_ox_gb300 | B61: Tokenomics IF_OpexGW｜GB300 NVL72（每 MW 年營運費用，不含折舊、含電費） | C61: US$m/MW-年 | E61: 1.9826348 | G61: Derived | H61: S21
A62: tk_ox_vr200 | B62: Tokenomics IF_OpexGW｜VR200 NVL72（每 MW 年營運費用，不含折舊、含電費） | C62: US$m/MW-年 | E62: 2.0934955 | G62: Derived | H62: S21
A63: tk_gpuhr | B63: Tokenomics IF_GPUhrEcon｜Hopper H100（每 GPU 小時持有成本） | C63: US$/GPU-hr | E63: 1.5425965 | G63: Derived | H63: S21 | I63: k_現貨的分母
A64: tk_fac | B64: Tokenomics L1_FacCapexMW（每 MW 機房資本支出） | C64: US$m/MW | E64: 12.67 | G64: Derived | H64: S21
A65: tk_life | B65: AI IT 設備折舊年限（Tokenomics IF_DeprLifeIT） | C65: 年 | D65: 5 | E65: 6 | F65: 7 | G65: Derived | H65: S21 | I65: 管理層：伺服器使用 5–6 年（2026Q3 法說）
A66: fac_life | B66: 機房折舊年限 | C66: 年 | D66: 15 | E66: 20 | F66: 30 | G66: Assumed | H66: 沿用 v0.2.2（AI 機房 20 年） | I66: 管理層：資料中心建築 30 年以上
A67: tk_pq | B67: Tokenomics L1_RevGW_PQ_VR200（模型商每 MW 年實收 P×Q；只作上限檢查） | C67: US$m/MW-年 | D67: 36.2296 | E67: 49.513784 | F67: 78.4975 | G67: Derived | H67: S21 | I67: 上限，不得作預測
A68: k_long | B68: k_長約＝長約等值價格 ÷ 目前 VR200 IF_HoldEcon | C68: x | D68: =p_long_lo/tk_he_vr200 -> 0.57413739 | E68: =p_long/tk_he_vr200 -> 0.78291462 | G68: Derived | H68: legacy_v0.2/kspec.py（隨目前快照重算） | I68: 低＝長約下緣（Sens）
A69: k_spot | B69: k_現貨＝現貨價 ÷ IF_GPUhrEcon｜H100 | C69: x | E69: =p_spot/tk_gpuhr -> 1.8280865 | F69: =p_list/tk_gpuhr -> 4.4600126 | G69: Derived | H69: legacy_v0.2/kspec.py（三家一致，C1） | I69: 高＝AWS 牌價（Sens）
A70: k_long_lo2 | B70: k_長約下緣＝長約下緣價格 ÷ VR200 IF_HoldEcon（情境 C 用） | C70: x | E70: =p_long_lo/tk_he_vr200 -> 0.57413739 | G70: Derived | H70: v0.3.1：情境值改用專屬列（原則第 8 節，不讀敏感度欄）
A71: k_spot_lst | B71: k_現貨（AWS 牌價）＝牌價 ÷ IF_GPUhrEcon｜H100（情境 A 用） | C71: x | E71: =p_list/tk_gpuhr -> 4.4600126 | G71: Derived | H71: 同上
A72: k_A | B72: 情境 A：新產能 k（價格軸高：現貨改用 AWS 牌價） | C72: x | E72: =long_sh*k_long+(1-long_sh)*k_spot_lst -> 1.5183342 | G72: Derived | H72: 沿用 v0.2.2 價格軸（pricing.kSpot.high）
A73: k_B | B73: 情境 B：k（價格軸基準：長約 80% × k_長約＋現貨 20% × k_現貨） | C73: x | E73: =long_sh*k_long+(1-long_sh)*k_spot -> 0.99194901 | G73: Derived | H73: 沿用 v0.2.2（C1 混合 k） | I73: 期初機隊三情境皆用本列
A74: k_C | B74: 情境 C：新產能 k（價格軸低：長約下緣） | C74: x | E74: =long_sh*k_long_lo2+(1-long_sh)*k_spot -> 0.82492722 | G74: Derived | H74: 沿用 v0.2.2 價格軸（pricing.kLong.low）
A75: mo_trn2 | B75: 期初世代占比：Trainium2（以 Hopper 計價，C2；期初機隊不套 NonNV 係數） | C75: % | E75: 0.55 | G75: Assumed | H75: S25 | I75: Epoch 三站 1,422 ÷ 在役 2,600；Tokenomics NonNV 係數只定義 Trainium3 對 VR200
A76: mo_h100 | B76: 期初世代占比：Hopper | C76: % | E76: 0.15 | G76: Assumed | H76: S25
A77: mo_gb200 | B77: 期初世代占比：GB200 | C77: % | E77: 0.15 | G77: Assumed | H77: S25
A78: mo_gb300 | B78: 期初世代占比：GB300 | C78: % | E78: 0.15 | G78: Assumed | H78: S25
A79: he_open | B79: 期初機隊加權 IF_HoldEcon | C79: US$m/MW-年 | E79: =(mo_trn2+mo_h100)*tk_he_h100+mo_gb200*tk_he_gb200+mo_gb300*tk_he_gb300 -> 9.7493476 | G79: Derived | H79: 上列加權
A80: ox_open | B80: 期初機隊加權營運費用 | C80: US$m/MW-年 | E80: =(mo_trn2+mo_h100)*tk_ox_h100+mo_gb200*tk_ox_gb200+mo_gb300*tk_ox_gb300 -> 1.8884974 | G80: Derived | H80: 上列加權
A81: rpm_open | B81: 期初機隊每 MW 年收入＝加權 IF_HoldEcon × k_B（收入端不乘 IF_Util，MW-year 計價） | C81: US$m/MW-年 | E81: =he_open*k_B -> 9.6708557 | G81: Derived | H81: 沿用 v0.2.2 口徑
A82: cust_sh | B82: 新增 MW 中自研晶片（Trainium3 → 以 GB300 為錨乘 NonNV 係數）比例 | C82: % | D82: 0.4 | E82: 0.5 | F82: 0.6 | G82: Assumed | H82: 沿用 v0.2.2（pricing.chips mixAdds） | I82: Trainium3 2026 年初出貨；2026Q3 法說：Trainium 2027 年底起對外銷售晶片（本版不建模）
A83: na_vr26 | B83: NVIDIA 新增中 VR200 比例（2026；其餘 GB300） | C83: % | E83: 0 | G83: Assumed | H83: 沿用 v0.2.2
A84: na_vr27 | B84: NVIDIA 新增中 VR200 比例（2027） | C84: % | E84: 0.5 | G84: Assumed | H84: 沿用 v0.2.2
A85: na_vr28 | B85: NVIDIA 新增中 VR200 比例（2028 起） | C85: % | E85: 1 | G85: Assumed | H85: 沿用 v0.2.2
A86: trn_hold | B86: Tokenomics IF_NonNV_Hold_Trn（Trainium3 每 GW 持有成本 ÷ VR200；低／基準／高） | C86: x | D86: 0.45 | E86: 0.61 | F86: 0.7 | G86: Assumed | H86: S21 | I86: Tokenomics 內為 Assumed；v21.4 為 0.6／0.7／0.9
A87: trn_out | B87: Tokenomics IF_NonNV_Out_Trn（Trainium3 每 GW 產出 ÷ VR200；只用於 Sens：收入改按產出比） | C87: x | D87: 0.3 | E87: 0.5 | F87: 0.8 | G87: Assumed | H87: S21 | I87: Tokenomics PR #172 Q1（收入口徑）未決
A88: cf_chip | B88: 自研晶片每 MW 收入係數（v0.3.1：改讀 IF_NonNV_Hold_Trn；舊 C2 口徑＝同期 NVIDIA 世代 × 1.0） | C88: x | E88: =trn_hold -> 0.61 | F88: 1 | G88: Derived | H88: S21；工作單第 1 節第 3 項（權威在 Tokenomics） | I88: 高＝舊 C2 口徑 1.0（Sens，與 cf_cx 同改）；比照 Alphabet TPU
A89: cf_cx | B89: 自研晶片每 MW IT 資本支出係數（v0.3.1：改讀 IF_NonNV_Hold_Trn） | C89: x | E89: =trn_hold -> 0.61 | F89: 1 | G89: Derived | H89: S21 | I89: 持有成本比同時作資本支出比（近似：Tokenomics 比值相對 VR200，模型套到 GB300 錨）
A90: colo_sh | B90: 機房租用比例（第三方託管） | C90: % | D90: 0.1 | E90: 0.2 | F90: 0.3 | G90: Interested-party | H90: S34 | I90: 自建比例＝1 − 本列；租用部分不計機房資本支出
A91: rent_rec | B91: 租用機房年租金 ÷ 機房資本支出（資本回收係數，C22） | C91: % | E91: 0.1 | G91: Assumed | H91: 對照表 r1 C22
A92: rent_mw | B92: 每 MW 年機房租金（攤到全部 AI MW）＝租用比例 × 機房成本 × 回收係數 | C92: US$m/MW-年 | E92: =colo_sh*tk_fac*rent_rec -> 0.2534 | G92: Derived | H92: 上列
A93: capex_g26 | B93: 2026 現金資本支出指引（約 220，維持） | C93: US$bn | E93: 220 | G93: Interested-party | H93: S13；S14 | I93: Q4 26 AI 資本支出＝指引 − 9M 實績 − Q4 非 AI（FY2026 錨定指引，修正三）；隱含 Q4 47.8，Q3 為 75.9
A94: internal_ai_reading | B94: 自用 AI 讀法（2＝讀法 2 主值：自用 MW 以 k＝1 計影子效益、價值中性；1＝讀法 1：只計成本） | C94: 1/2 | D94: 1 | E94: 2 | G94: Assumed | H94: 修正一（F1；對照表 r1 C16；Andy 2026-10-27 15:03 決定讀法 2 為主值） | I94: 讀法 1 列 Sens 與 Val 第 0 節
A95: cip_lag | B95: 實績期 AI 在建（CIP）轉入在役的延後年數 | C95: 年 | E95: 1 | F95: 2 | G95: Assumed | H95: 修正三（獨立核對：AWS 折舊 2024→2025→1H26 年化 13.3→21.5→30.7） | I95: Sens：2 年
A96: ai_rr | B96: 公司 AI 營收年化（AWS AI run-rate，2026Q2 >25；Q3 只說年增三位數） | C96: US$bn | E96: 25 | G96: Interested-party | H96: S04 | I96: 只作 Recon 驗證列（C3）；不用於校準
A97: aws_rr | B97: AWS 年化營收 run-rate（2026Q3） | C97: US$bn | E97: 184 | G97: Interested-party | H97: S13；S14 | I97: 只作 Recon 驗證列
A98: aws_bl | B98: AWS backlog（2026-09-30） | C98: US$bn | E98: 578 | G98: Interested-party | H98: S14 | I98: 年增三位數；只作 Recon 驗證列（不反推 k）
A99: aws_g40 | B99: 公司說法：AWS 2027、2028 年各成長 40% 以上 | C99: % | E99: 0.4 | G99: Interested-party | H99: S13；S14 | I99: 只作 Recon 驗證列（不校準）
A100: D. AWS 其他（非 AI 雲端）
...

Sheet Q
A1: Q — 實績（US$bn；股數十億股）：FY2023–FY2025、最近 8 季（2024Q4–2026Q3）、9M25、9M26、1H26 與近四季。資料取自 data/amazon_facts_20261008.json（10-K、10-Q、財報新聞稿逐季補充表）與 data/amazon_facts_2026q3.json（2026Q3 新聞稿，兩讀核對；10-Q 未取得），藍字＝事實值、黑字＝加總或換算
A2: 核對列（綠底）：零售營收線合計＝北美＋國際、營收線合計＝合併營收、分部合計＝合併營收、分部營業利益合計＋未分攤＝合併營業利益、9M26＝事實總帳九個月值；實績皆須為 0
A3: 項目 | B3: 單位 | C3: FY2023A | D3: FY2024A | E3: FY2025A | F3: 2024Q4 | G3: 2025Q1 | H3: 2025Q2 | I3: 2025Q3 | J3: 2025Q4 | K3: 2026Q1 | L3: 2026Q2 | M3: 2026Q3 | N3: 9M25 | O3: 9M26 | P3: 1H26 | Q3: 近四季（2025Q4–2026Q3） | R3: 標記 | S3: 來源
A4: 1. 官方報告分部營收（10-K 附註：North America、International、AWS）
A5: North America | B5: US$bn | C5: 352.828 | D5: 387.497 | E5: 426.305 | F5: 115.586 | G5: 92.887 | H5: 100.068 | I5: 106.267 | J5: 127.083 | K5: 104.143 | L5: 116.177 | M5: 112.852 | N5: =G5+H5+I5 -> 299.222 | O5: =K5+L5+M5 -> 333.172 | P5: =K5+L5 -> 220.32 | Q5: =J5+K5+L5+M5 -> 460.255 | R5: Verified／Interested-party | S5: S01（FY）；S13、S04、S08（逐季補充表）
A6: International | B6: US$bn | C6: 131.2 | D6: 142.906 | E6: 161.894 | F6: 43.42 | G6: 33.513 | H6: 36.761 | I6: 40.896 | J6: 50.724 | K6: 39.789 | L6: 42.197 | M6: 43.108 | N6: =G6+H6+I6 -> 111.17 | O6: =K6+L6+M6 -> 125.094 | P6: =K6+L6 -> 81.986 | Q6: =J6+K6+L6+M6 -> 175.818 | R6: Verified／Interested-party | S6: S01（FY）；S13、S04、S08（逐季補充表）
A7: AWS | B7: US$bn | C7: 90.757 | D7: 107.556 | E7: 128.725 | F7: 28.786 | G7: 29.267 | H7: 30.873 | I7: 33.006 | J7: 35.579 | K7: 37.587 | L7: 42.232 | M7: 45.984 | N7: =G7+H7+I7 -> 93.146 | O7: =K7+L7+M7 -> 125.803 | P7: =K7+L7 -> 79.819 | Q7: =J7+K7+L7+M7 -> 161.382 | R7: Verified／Interested-party | S7: S01（FY）；S13、S04、S08（逐季補充表）
A8: 合併營收 | B8: US$bn | C8: 574.785 | D8: 637.959 | E8: 716.924 | F8: 187.792 | G8: 155.667 | H8: 167.702 | I8: 180.169 | J8: 213.386 | K8: 181.519 | L8: 200.606 | M8: 201.944 | N8: =G8+H8+I8 -> 503.538 | O8: =K8+L8+M8 -> 584.069 | P8: =K8+L8 -> 382.125 | Q8: =J8+K8+L8+M8 -> 797.455 | R8: Verified／Interested-party | S8: S01（FY）；S13、S04、S08（逐季補充表）
A9: 2. 營收線（10-K 營收類別；零售各線＝北美＋國際，AWS 線＝AWS 分部）
A10: Online stores | B10: US$bn | C10: 231.872 | D10: 247.029 | E10: 269.287 | F10: 75.556 | G10: 57.407 | H10: 61.485 | I10: 67.407 | J10: 82.988 | K10: 64.254 | L10: 70.432 | M10: 68.47 | N10: =G10+H10+I10 -> 186.299 | O10: =K10+L10+M10 -> 203.156 | P10: =K10+L10 -> 134.686 | Q10: =J10+K10+L10+M10 -> 286.144 | R10: Verified／Interested-party | S10: S01（FY）；S13、S04、S08（逐季補充表）
A11: Physical stores | B11: US$bn | C11: 20.03 | D11: 21.215 | E11: 22.561 | F11: 5.579 | G11: 5.533 | H11: 5.595 | I11: 5.578 | J11: 5.855 | K11: 5.785 | L11: 5.794 | M11: 5.71 | N11: =G11+H11+I11 -> 16.706 | O11: =K11+L11+M11 -> 17.289 | P11: =K11+L11 -> 11.579 | Q11: =J11+K11+L11+M11 -> 23.144 | R11: Verified／Interested-party | S11: S01（FY）；S13、S04、S08（逐季補充表）
A12: Third-party seller services | B12: US$bn | C12: 140.053 | D12: 156.146 | E12: 172.162 | F12: 47.485 | G12: 36.512 | H12: 40.348 | I12: 42.486 | J12: 52.816 | K12: 41.578 | L12: 46.78 | M12: 46.492 | N12: =G12+H12+I12 -> 119.346 | O12: =K12+L12+M12 -> 134.85 | P12: =K12+L12 -> 88.358 | Q12: =J12+K12+L12+M12 -> 187.666 | R12: Verified／Interested-party | S12: S01（FY）；S13、S04、S08（逐季補充表）
A13: Advertising services | B13: US$bn | C13: 46.906 | D13: 56.214 | E13: 68.635 | F13: 17.288 | G13: 13.921 | H13: 15.694 | I13: 17.703 | J13: 21.317 | K13: 17.243 | L13: 19.809 | M13: 19.637 | N13: =G13+H13+I13 -> 47.318 | O13: =K13+L13+M13 -> 56.689 | P13: =K13+L13 -> 37.052 | Q13: =J13+K13+L13+M13 -> 78.006 | R13: Verified／Interested-party | S13: S01（FY）；S13、S04、S08（逐季補充表）
A14: Subscription services | B14: US$bn | C14: 40.209 | D14: 44.374 | E14: 49.619 | F14: 11.508 | G14: 11.715 | H14: 12.208 | I14: 12.574 | J14: 13.122 | K14: 13.427 | L14: 13.73 | M14: 14.006 | N14: =G14+H14+I14 -> 36.497 | O14: =K14+L14+M14 -> 41.163 | P14: =K14+L14 -> 27.157 | Q14: =J14+K14+L14+M14 -> 54.285 | R14: Verified／Interested-party | S14: S01（FY）；S13、S04、S08（逐季補充表）
A15: Other | B15: US$bn | C15: 4.958 | D15: 5.425 | E15: 5.935 | F15: 1.59 | G15: 1.312 | H15: 1.499 | I15: 1.415 | J15: 1.709 | K15: 1.645 | L15: 1.829 | M15: 1.645 | N15: =G15+H15+I15 -> 4.226 | O15: =K15+L15+M15 -> 5.119 | P15: =K15+L15 -> 3.474 | Q15: =J15+K15+L15+M15 -> 6.828 | R15: Verified／Interested-party | S15: S01（FY）；S13、S04、S08（逐季補充表）
A16: 零售營收線合計（不含 AWS） | B16: US$bn | C16: =C10+C11+C12+C13+C14+C15 -> 484.028 | D16: =D10+D11+D12+D13+D14+D15 -> 530.403 | E16: =E10+E11+E12+E13+E14+E15 -> 588.199 | F16: =F10+F11+F12+F13+F14+F15 -> 159.006 | G16: =G10+G11+G12+G13+G14+G15 -> 126.4 | H16: =H10+H11+H12+H13+H14+H15 -> 136.829 | I16: =I10+I11+I12+I13+I14+I15 -> 147.163 | J16: =J10+J11+J12+J13+J14+J15 -> 177.807 | ... Q16: =Q10+Q11+Q12+Q13+Q14+Q15 -> 636.073 | R16: Derived
A17: AWS（營收線） | B17: US$bn | C17: =C7 -> 90.757 | D17: =D7 -> 107.556 | E17: =E7 -> 128.725 | F17: =F7 -> 28.786 | G17: =G7 -> 29.267 | H17: =H7 -> 30.873 | I17: =I7 -> 33.006 | J17: =J7 -> 35.579 | ... Q17: =Q7 -> 161.382 | R17: Derived
A18: 檢查：零售營收線合計 − (North America＋International) | B18: US$bn | C18: =C16-(C5+C6) -> 0 | D18: =D16-(D5+D6) -> 0 | E18: =E16-(E5+E6) -> 0 | F18: =F16-(F5+F6) -> 0 | G18: =G16-(G5+G6) -> 0 | H18: =H16-(H5+H6) -> 0 | I18: =I16-(I5+I6) -> 0 | J18: =J16-(J5+J6) -> 0 | ... Q18: =Q16-(Q5+Q6) -> 0 | R18: Derived
A19: 檢查：營收線合計（含 AWS）− 合併營收 | B19: US$bn | C19: =C16+C17-C8 -> 0 | D19: =D16+D17-D8 -> 0 | E19: =E16+E17-E8 -> 0 | F19: =F16+F17-F8 -> 0 | G19: =G16+G17-G8 -> 0 | H19: =H16+H17-H8 -> 0 | I19: =I16+I17-I8 -> 0 | J19: =J16+J17-J8 -> 0 | ... Q19: =Q16+Q17-Q8 -> 0 | R19: Derived
A20: 檢查：分部合計 − 合併營收 | B20: US$bn | C20: =C5+C6+C7-C8 -> 0 | D20: =D5+D6+D7-D8 -> 0 | E20: =E5+E6+E7-E8 -> 0 | F20: =F5+F6+F7-F8 -> 0 | G20: =G5+G6+G7-G8 -> 0 | H20: =H5+H6+H7-H8 -> 0 | I20: =I5+I6+I7-I8 -> 0 | J20: =J5+J6+J7-J8 -> 0 | ... Q20: =Q5+Q6+Q7-Q8 -> 0 | R20: Derived
A21: 檢查：9M26 合併營收 − 新聞稿九個月值（事實 is.TOT.rev.2026m9） | B21: US$bn | O21: =O8-584.069 -> 0 | R21: Derived
A22: 3. 分部營業利益
A23: North America 營業利益 | B23: US$bn | C23: 14.877 | D23: 24.967 | E23: 29.619 | F23: 9.256 | G23: 5.841 | H23: 7.517 | I23: 4.789 | J23: 11.472 | K23: 8.267 | L23: 9.123 | M23: 8.723 | N23: =G23+H23+I23 -> 18.147 | O23: =K23+L23+M23 -> 26.113 | P23: =K23+L23 -> 17.39 | Q23: =J23+K23+L23+M23 -> 37.585 | R23: Verified／Interested-party | S23: S01（FY）；S13、S04、S08（逐季補充表）
A24: International 營業利益 | B24: US$bn | C24: -2.656 | D24: 3.792 | E24: 4.75 | F24: 1.315 | G24: 1.017 | H24: 1.494 | I24: 1.199 | J24: 1.04 | K24: 1.424 | L24: 1.717 | M24: 1.58 | N24: =G24+H24+I24 -> 3.71 | O24: =K24+L24+M24 -> 4.721 | P24: =K24+L24 -> 3.141 | Q24: =J24+K24+L24+M24 -> 5.761 | R24: Verified／Interested-party | S24: S01（FY）；S13、S04、S08（逐季補充表）
A25: AWS 營業利益 | B25: US$bn | C25: 24.631 | D25: 39.834 | E25: 45.606 | F25: 10.632 | G25: 11.547 | H25: 10.16 | I25: 11.434 | J25: 12.465 | K25: 14.161 | L25: 16.621 | M25: 17.773 | N25: =G25+H25+I25 -> 33.141 | O25: =K25+L25+M25 -> 48.555 | P25: =K25+L25 -> 30.782 | Q25: =J25+K25+L25+M25 -> 61.02 | R25: Verified／Interested-party | S25: S01（FY）；S13、S04、S08（逐季補充表）
A26: 合併營業利益 | B26: US$bn | C26: 36.852 | D26: 68.593 | E26: 79.975 | F26: 21.203 | G26: 18.405 | H26: 19.171 | I26: 17.422 | J26: 24.977 | K26: 23.852 | L26: 27.461 | M26: 28.076 | N26: =G26+H26+I26 -> 54.998 | O26: =K26+L26+M26 -> 79.389 | P26: =K26+L26 -> 51.313 | Q26: =J26+K26+L26+M26 -> 104.366 | R26: Verified／Interested-party | S26: S01（FY）；S13、S04、S08（逐季補充表）
A27: 未分攤（合併 − 分部合計；Amazon 分部已含全部費用） | B27: US$bn | C27: =C26-(C23+C24+C25) -> 0 | D27: =D26-(D23+D24+D25) -> 0 | E27: =E26-(E23+E24+E25) -> 0 | F27: =F26-(F23+F24+F25) -> 0 | G27: =G26-(G23+G24+G25) -> 0 | H27: =H26-(H23+H24+H25) -> 0 | I27: =I26-(I23+I24+I25) -> 0 | J27: =J26-(J23+J24+J25) -> 0 | ... Q27: =Q26-(Q23+Q24+Q25) -> 0 | R27: Derived
A28: 檢查：分部營業利益合計＋未分攤 − 合併營業利益 | B28: US$bn | C28: =C23+C24+C25+C27-C26 -> 0 | D28: =D23+D24+D25+D27-D26 -> 0 | E28: =E23+E24+E25+E27-E26 -> 0 | F28: =F23+F24+F25+F27-F26 -> 0 | G28: =G23+G24+G25+G27-G26 -> 0 | H28: =H23+H24+H25+H27-H26 -> 0 | I28: =I23+I24+I25+I27-I26 -> 0 | J28: =J23+J24+J25+J27-J26 -> 0 | ... Q28: =Q23+Q24+Q25+Q27-Q26 -> 0 | R28: Derived
A29: 檢查：9M26 合併營業利益 − 新聞稿九個月值（事實 is.TOT.oi.2026m9） | B29: US$bn | O29: =O26-79.389 -> 0 | R29: Derived
A30: 4. 分部折舊攤銷（不含影音內容與營業租賃資產攤銷；2024 季度未收；2025Q4＝全年 − 前三季；2026Q3＝2026Q2 × 現金流量表 D&A 季增比〔推導，10-Q 未取得〕）
A31: North America 折舊攤銷 | B31: US$bn | C31: 13.678 | D31: 14.285 | E31: 15.503 | G31: 3.53 | H31: 3.742 | I31: 4.001 | J31: =E31-G31-H31-I31 -> 4.23 | K31: 4.28 | L31: 4.5 | M31: =L31*M49/L49 -> 4.7163548 | N31: =G31+H31+I31 -> 11.273 | O31: =K31+L31+M31 -> 13.496355 | P31: =K31+L31 -> 8.78 | Q31: =J31+K31+L31+M31 -> 17.726355 | R31: Verified／Derived（2026Q3） | S31: S01；S02；S03
A32: International 折舊攤銷 | B32: US$bn | C32: 4.016 | D32: 4.462 | E32: 4.907 | G32: 1.136 | H32: 1.18 | I32: 1.276 | J32: =E32-G32-H32-I32 -> 1.315 | K32: 1.277 | L32: 1.293 | M32: =L32*M49/L49 -> 1.3551659 | N32: =G32+H32+I32 -> 3.592 | O32: =K32+L32+M32 -> 3.9251659 | P32: =K32+L32 -> 2.57 | Q32: =J32+K32+L32+M32 -> 5.2401659 | R32: Verified／Derived（2026Q3） | S32: S01；S02；S03
A33: AWS 折舊攤銷 | B33: US$bn | C33: 12.531 | D33: 13.32 | E33: 21.45 | G33: 4.39 | H33: 4.844 | I33: 5.648 | J33: =E33-G33-H33-I33 -> 6.568 | K33: 7.277 | L33: 8.076 | M33: =L33*M49/L49 -> 8.4642848 | N33: =G33+H33+I33 -> 14.882 | O33: =K33+L33+M33 -> 23.817285 | P33: =K33+L33 -> 15.353 | Q33: =J33+K33+L33+M33 -> 30.385285 | R33: Verified／Derived（2026Q3） | S33: S01；S02；S03
A34: 分部折舊攤銷合計 | B34: US$bn | C34: =IF(COUNT(C31:C33)=3,C31+C32+C33,"") -> 30.225 | D34: =IF(COUNT(D31:D33)=3,D31+D32+D33,"") -> 32.067 | E34: =IF(COUNT(E31:E33)=3,E31+E32+E33,"") -> 41.86 | F34: =IF(COUNT(F31:F33)=3,F31+F32+F33,"") | G34: =IF(COUNT(G31:G33)=3,G31+G32+G33,"") -> 9.056 | H34: =IF(COUNT(H31:H33)=3,H31+H32+H33,"") -> 9.766 | I34: =IF(COUNT(I31:I33)=3,I31+I32+I33,"") -> 10.925 | J34: =IF(COUNT(J31:J33)=3,J31+J32+J33,"") -> 12.113 | ... Q34: =IF(COUNT(Q31:Q33)=3,Q31+Q32+Q33,"") -> 53.351806 | R34: Derived
A35: 5. 損益（業外、稅、淨利）
A36: 利息費用 | B36: US$bn | C36: 3.182 | D36: 2.406 | E36: 2.274 | F36: 0.57 | G36: 0.541 | H36: 0.516 | I36: 0.538 | J36: 0.679 | K36: 0.8 | L36: 1.314 | M36: 1.691 | N36: =G36+H36+I36 -> 1.595 | O36: =K36+L36+M36 -> 3.805 | P36: =K36+L36 -> 2.114 | Q36: =J36+K36+L36+M36 -> 4.484 | R36: Verified／Interested-party | S36: S01；S13
A37: 利息收入 | B37: US$bn | L37: 1.295 | M37: 1.187 | R37: Interested-party | S37: S02；S13
A38: 稅前淨利 | B38: US$bn | C38: 37.557 | D38: 68.614 | E38: 97.311 | F38: 22.349 | G38: 21.679 | H38: 20.857 | I38: 28.17 | J38: 26.605 | K38: 39.834 | L38: 80.857 | M38: 26.869 | N38: =G38+H38+I38 -> 70.706 | O38: =K38+L38+M38 -> 147.56 | P38: =K38+L38 -> 120.691 | Q38: =J38+K38+L38+M38 -> 174.165 | R38: Verified／Interested-party | S38: S01；S13
A39: 所得稅 | B39: US$bn | C39: 7.12 | D39: 9.265 | E39: 19.087 | F39: 2.325 | G39: 4.553 | H39: 2.678 | I39: 6.91 | J39: 4.946 | K39: 9.56 | L39: 18.199 | M39: 6.18 | N39: =G39+H39+I39 -> 14.141 | O39: =K39+L39+M39 -> 33.939 | P39: =K39+L39 -> 27.759 | Q39: =J39+K39+L39+M39 -> 38.885 | R39: Verified／Interested-party | S39: S01；S13
A40: 淨利 | B40: US$bn | C40: 30.425 | D40: 59.248 | E40: 77.67 | F40: 20.004 | G40: 17.127 | H40: 18.164 | I40: 21.187 | J40: 21.192 | K40: 30.255 | L40: 62.647 | M40: 20.685 | N40: =G40+H40+I40 -> 56.478 | O40: =K40+L40+M40 -> 113.587 | P40: =K40+L40 -> 92.902 | Q40: =J40+K40+L40+M40 -> 134.779 | R40: Verified／Interested-party | S40: S01；S13
A41: 業外淨額（稅前 − 營業利益＋利息費用；含 Anthropic 等持股評價利益） | B41: US$bn | C41: =IF(AND(ISNUMBER(C38),ISNUMBER(C36)),C38-C26+C36,"") -> 3.887 | D41: =IF(AND(ISNUMBER(D38),ISNUMBER(D36)),D38-D26+D36,"") -> 2.427 | E41: =IF(AND(ISNUMBER(E38),ISNUMBER(E36)),E38-E26+E36,"") -> 19.61 | F41: =IF(AND(ISNUMBER(F38),ISNUMBER(F36)),F38-F26+F36,"") -> 1.716 | G41: =IF(AND(ISNUMBER(G38),ISNUMBER(G36)),G38-G26+G36,"") -> 3.815 | H41: =IF(AND(ISNUMBER(H38),ISNUMBER(H36)),H38-H26+H36,"") -> 2.202 | I41: =IF(AND(ISNUMBER(I38),ISNUMBER(I36)),I38-I26+I36,"") -> 11.286 | J41: =IF(AND(ISNUMBER(J38),ISNUMBER(J36)),J38-J26+J36,"") -> 2.307 | ... Q41: =IF(AND(ISNUMBER(Q38),ISNUMBER(Q36)),Q38-Q26+Q36,"") -> 74.283 | R41: Derived
A42: 有效稅率 | B42: US$bn | C42: =C39/C38 -> 0.18957851 | D42: =D39/D38 -> 0.13503075 | E42: =E39/E38 -> 0.19614432 | O42: =O39/O38 -> 0.23000136 | R42: Derived
A43: 稀釋加權股數 | B43: 十億股 | C43: 10.492 | D43: 10.721 | E43: 10.827 | G43: 10.793 | H43: 10.806 | I43: 10.845 | K43: 10.874 | L43: 10.903 | M43: 10.929 | N43: 10.815 | O43: 10.903 | R43: Verified／Interested-party | S43: S10；S13
A44: 稀釋 EPS（淨利 ÷ 稀釋加權股數） | B44: US$ | C44: =IF(ISNUMBER(C43),C40/C43,"") -> 2.8998284 | D44: =IF(ISNUMBER(D43),D40/D43,"") -> 5.5263502 | E44: =IF(ISNUMBER(E43),E40/E43,"") -> 7.1737323 | F44: =IF(ISNUMBER(F43),F40/F43,"") | G44: =IF(ISNUMBER(G43),G40/G43,"") -> 1.5868619 | H44: =IF(ISNUMBER(H43),H40/H43,"") -> 1.680918 | I44: =IF(ISNUMBER(I43),I40/I43,"") -> 1.9536192 | J44: =IF(ISNUMBER(J43),J40/J43,"") | ... O44: =IF(ISNUMBER(O43),O40/O43,"") -> 10.417958 | R44: Derived
A45: 6. 現金流量、資本支出與股東回饋
A46: 營運現金流 | B46: US$bn | C46: 84.946 | D46: 115.877 | E46: 139.514 | F46: 45.636 | G46: 17.015 | H46: 32.515 | I46: 35.525 | J46: 54.459 | K46: 26.032 | L46: 45.387 | M46: 42.422 | N46: =G46+H46+I46 -> 85.055 | O46: =K46+L46+M46 -> 113.841 | P46: =K46+L46 -> 71.419 | Q46: =J46+K46+L46+M46 -> 168.3 | R46: Verified／Interested-party | S46: S01；S13；S04；S05；S06；S07
A47: 資本支出（購置 PP&E，總額） | B47: US$bn | C47: 52.729 | D47: 82.999 | E47: 131.819 | F47: 27.834 | G47: 25.019 | H47: 32.183 | I47: 35.095 | J47: 39.522 | K47: 44.203 | L47: 54.208 | M47: 77.259 | N47: =G47+H47+I47 -> 92.297 | O47: =K47+L47+M47 -> 175.67 | P47: =K47+L47 -> 98.411 | Q47: =J47+K47+L47+M47 -> 215.192 | R47: Verified／Interested-party | S47: S01；S13
A48: 資本支出（現金，淨額＝購置 − 出售及獎勵） | B48: US$bn | C48: 48.133 | D48: 77.658 | E48: 128.32 | F48: 26.052 | G48: 24.255 | H48: 31.368 | I48: 34.228 | J48: 38.469 | K48: 43.234 | L48: 53.076 | M48: 75.878 | N48: =G48+H48+I48 -> 89.851 | O48: =K48+L48+M48 -> 172.188 | P48: =K48+L48 -> 96.31 | Q48: =J48+K48+L48+M48 -> 210.657 | R48: Derived | S48: 由同季新聞稿現金流量表換算
A49: 折舊攤銷（現金流量表；含影音內容與營業租賃資產） | B49: US$bn | C49: 48.663 | D49: 52.795 | E49: 65.756 | F49: 15.631 | G49: 14.262 | H49: 15.227 | I49: 16.796 | J49: 19.471 | K49: 18.945 | L49: 19.988 | M49: 20.949 | N49: =G49+H49+I49 -> 46.285 | O49: =K49+L49+M49 -> 59.882 | P49: =K49+L49 -> 38.933 | Q49: =J49+K49+L49+M49 -> 79.353 | R49: Verified／Interested-party | S49: S01；S13
A50: 股份基礎給付 | B50: US$bn | C50: 24.023 | D50: 22.011 | E50: 19.467 | F50: 4.995 | G50: 3.689 | H50: 6.534 | I50: 4.847 | J50: 4.397 | K50: 4.032 | L50: 6.038 | M50: 5.406 | N50: =G50+H50+I50 -> 15.07 | O50: =K50+L50+M50 -> 15.476 | P50: =K50+L50 -> 10.07 | Q50: =J50+K50+L50+M50 -> 19.873 | R50: Verified／Interested-party | S50: S01；S13
A51: 自由現金流（公司口徑＝營運現金流 − 資本支出淨額） | B51: US$bn | C51: =C46-C48 -> 36.813 | D51: =D46-D48 -> 38.219 | E51: =E46-E48 -> 11.194 | F51: =F46-F48 -> 19.584 | G51: =G46-G48 -> -7.24 | H51: =H46-H48 -> 1.147 | I51: =I46-I48 -> 1.297 | J51: =J46-J48 -> 15.99 | ... Q51: =Q46-Q48 -> -42.357 | R51: Derived
A52: 融資租賃本金償還 | B52: US$bn | C52: 4.384 | D52: 2.043 | E52: 1.557 | M52: 0.433 | N52: 1.172 | O52: 1.296 | R52: Verified／Interested-party | S52: S01；S13
A53: 買回庫藏股 | B53: US$bn | C53: 0 | D53: 0 | E53: 0 | O53: 0 | R53: Verified | S53: S01；S13
A54: 現金股利 | B54: US$bn | C54: 0 | D54: 0 | E54: 0 | O54: 0 | R54: Verified | S54: S01；S13
A55: 策略投資（收購與非上市投資淨額；2026 含 OpenAI、Anthropic） | B55: US$bn | O55: 63.753 | P55: 39.767 | R55: Interested-party | S55: S02；S13
A56: 7. 資本支出分布（PP&E 淨增加，含融資租賃取得與已取得未付款；10-K／10-Q 分部附註；2026Q3 未取得）
A57: North America PP&E 淨增加 | B57: US$bn | C57: 17.529 | D57: 24.348 | E57: 35.919 | P57: 23.265 | R57: Verified | S57: S01；S02
A58: International PP&E 淨增加 | B58: US$bn | C58: 4.144 | D58: 6.643 | E58: 7.617 | P58: 4.267 | R58: Verified | S58: S01；S02
A59: AWS PP&E 淨增加 | B59: US$bn | C59: 24.843 | D59: 53.267 | E59: 96.496 | P59: 90.12 | R59: Verified | S59: S01；S02
A60: 公司層 PP&E 淨增加 | B60: US$bn | C60: 1.828 | D60: 1.494 | E60: 2.32 | P60: 0.996 | R60: Verified | S60: S01；S02
A61: PP&E 淨增加合計 | B61: US$bn | C61: 48.344 | D61: 85.752 | E61: 142.352 | P61: 118.648 | R61: Verified | S61: S01；S02
A62: 8. 期末餘額
A63: 現金、約當現金與有價證券 | B63: US$bn | E63: 123.029 | L63: 122.988 | M63: 114.226 | R63: Verified／Interested-party | S63: S01；S02；S13
A64: 債務面額（2026-09-30 為推導值：6/30 面額＋Q3 長期借款收入 − 償還；10-Q 未取得） | B64: US$bn | E64: 68.836 | L64: 132.995 | M64: 181.09 | R64: Verified／Derived | S64: S01；S02；S13

Sheet Thesis
A1: Thesis — 命題模組：AWS AI＝對外 AI 在役 MW × 每 MW 年收入（Tokenomics v21.7 IF_HoldEcon × k；新增 Trainium＝GB300 錨 × IF_NonNV_Hold_Trn 0.61，v0.3.1）。AI 資本支出（含自用）→ IT 6 年／機房 20 年折舊（次年起提列）→ 對外部分進 AWS 營業利益、自用部分進北美／國際營業利益。三情境 A／B／C 依序排列
A2: 情境差異集中在命題驅動（In 頁 J 節）：A＝公司容量目標速度＋新產能 k 價格軸高；B＝資本支出指引隱含速度（C10，下半年視窗）＋基準 k；C＝與 B 同速度（資本支出照指引）＋新產能 k 價格軸低。非 AI 業務三情境相同
A4: Thesis｜情境 A（樂觀）：命題模組 AWS AI＝對外 AI 在役 MW × 每 MW 年收入（Tokenomics 持有成本 × k）；AI 資本支出 → 折舊 → 分部營業利益
A5: 項目 | B5: 單位 | C5: FY2024A | D5: FY2025A | E5: 9M26A | F5: Q4 26E | G5: FY2026E（9M 實績＋Q4 模型） | H5: FY2027E | I5: FY2028E | J5: FY2029E | K5: FY2030E | L5: FY2031E | M5: FY2032E | N5: 9M25A | O5: Q4 25A | P5: 說明 | R5: 2023 | S5: 2024 | T5: 2025 | U5: 2026 | V5: 2027 | W5: 2028 | X5: 2029 | Y5: 2030 | Z5: 2031 | AA5: 2032
A6: 1. 容量（對外 AI 在役 MW-IT；期末）
A7: 對外 AI MW 每年新增（2030–2032 線性收斂到 FY2029 年底 MW × g，F5） | B7: MW/年 | H7: =(pace_A*pace_x) -> 3733 | I7: =(pace_A*pace_x) -> 3733 | J7: =(pace_A*pace_x) -> 3733 | K7: =(pace_A*pace_x)+(Thesis!$J$8*tg-(pace_A*pace_x))*1/3 -> 2640.2614 | L7: =(pace_A*pace_x)+(Thesis!$J$8*tg-(pace_A*pace_x))*2/3 -> 1547.5228 | M7: =(pace_A*pace_x)+(Thesis!$J$8*tg-(pace_A*pace_x))*3/3 -> 454.78425 | P7: 終值不落在建置高峰（共同修正 F5）
A8: 對外 AI 在役 MW（期末） | B8: MW | C8: =mw_ye24 -> 360 | D8: =mw_ye25 -> 1440 | E8: =mw_q3 -> 3027.225 | F8: =Thesis!$E$8+(pace_A*pace_x)*0.25 -> 3960.475 | G8: =Thesis!$F$8 -> 3960.475 | H8: =Thesis!$G$8+Thesis!$H$7 -> 7693.475 | I8: =Thesis!$H$8+Thesis!$I$7 -> 11426.475 | J8: =Thesis!$I$8+Thesis!$J$7 -> 15159.475 | K8: =Thesis!$J$8+Thesis!$K$7 -> 17799.736 | L8: =Thesis!$K$8+Thesis!$L$7 -> 19347.259 | M8: =Thesis!$L$8+Thesis!$M$7 -> 19802.043 | N8: =mw_ye24+(mw_ye25-mw_ye24)*0.75 -> 1170 | O8: =mw_ye25 -> 1440 | P8: 評價日 2026-09-30＝In 頁 mw_q3（6/30 機隊＋C10 速度一季）；之後每年新增＝In 頁 pace（情境）× pace_x；歷史年底值只用於分拆與折舊年份
A9: 對外 AI 平均在役 MW（期間） | B9: MW | C9: =(mw_ye23+mw_ye24)/2 -> 240 | D9: =(Thesis!$C$8+Thesis!$D$8)/2 -> 900 | E9: =(Thesis!$D$8+Thesis!$E$8)/2 -> 2233.6125 | F9: =(Thesis!$E$8+Thesis!$F$8)/2 -> 3493.85 | G9: =Thesis!$E$9*0.75+Thesis!$F$9*0.25 -> 2548.6719 | H9: =(Thesis!$G$8+Thesis!$H$8)/2 -> 5826.975 | I9: =(Thesis!$H$8+Thesis!$I$8)/2 -> 9559.975 | J9: =(Thesis!$I$8+Thesis!$J$8)/2 -> 13292.975 | K9: =(Thesis!$J$8+Thesis!$K$8)/2 -> 16479.606 | L9: =(Thesis!$K$8+Thesis!$L$8)/2 -> 18573.498 | M9: =(Thesis!$L$8+Thesis!$M$8)/2 -> 19574.651 | N9: =(Thesis!$C$8+Thesis!$N$8)/2 -> 765 | O9: =(Thesis!$N$8+Thesis!$O$8)/2 -> 1305
A10: 期間長度 | B10: 年 | C10: 1 | D10: 1 | E10: 0.75 | F10: 0.25 | G10: 1 | H10: 1 | I10: 1 | J10: 1 | K10: 1 | L10: 1 | M10: 1 | N10: 0.75 | O10: 0.25
A11: 新增對外 AI MW | B11: MW | C11: =Thesis!$C$8-mw_ye23 -> 240 | D11: =Thesis!$D$8-Thesis!$C$8 -> 1080 | E11: =Thesis!$E$8-Thesis!$D$8 -> 1587.225 | F11: =Thesis!$F$8-Thesis!$E$8 -> 933.25 | G11: =Thesis!$E$11+Thesis!$F$11 -> 2520.475 | H11: =Thesis!$H$8-Thesis!$G$8 -> 3733 | I11: =Thesis!$I$8-Thesis!$H$8 -> 3733 | J11: =Thesis!$J$8-Thesis!$I$8 -> 3733 | K11: =Thesis!$K$8-Thesis!$J$8 -> 2640.2614 | L11: =Thesis!$L$8-Thesis!$K$8 -> 1547.5228 | M11: =Thesis!$M$8-Thesis!$L$8 -> 454.78425 | N11: =Thesis!$N$8-Thesis!$C$8 -> 810 | O11: =Thesis!$O$8-Thesis!$N$8 -> 270
A12: 新增 AI 總 MW（含自用＝對外 ÷ 對外比例） | B12: MW | C12: =Thesis!$C$11/ext_sh -> 300 | D12: =Thesis!$D$11/ext_sh -> 1350 | E12: =Thesis!$E$11/ext_sh -> 1984.0312 | F12: =Thesis!$F$11/ext_sh -> 1166.5625 | G12: =Thesis!$G$11/ext_sh -> 3150.5938 | H12: =Thesis!$H$11/ext_sh -> 4666.25 | I12: =Thesis!$I$11/ext_sh -> 4666.25 | J12: =Thesis!$J$11/ext_sh -> 4666.25 | K12: =Thesis!$K$11/ext_sh -> 3300.3268 | L12: =Thesis!$L$11/ext_sh -> 1934.4035 | M12: =Thesis!$M$11/ext_sh -> 568.48031 | N12: =Thesis!$N$11/ext_sh -> 1012.5 | O12: =Thesis!$O$11/ext_sh -> 337.5 | P12: R–AA 欄：依年份（折舊與汰換用） | R12: =mw_ye23/ext_sh -> 150 | S12: =Thesis!$C$12 -> 300 | T12: =Thesis!$D$12 -> 1350 | U12: =Thesis!$G$12 -> 3150.5938 | V12: =Thesis!$H$12 -> 4666.25 | W12: =Thesis!$I$12 -> 4666.25 | X12: =Thesis!$J$12 -> 4666.25 | Y12: =Thesis!$K$12 -> 3300.3268 | Z12: =Thesis!$L$12 -> 1934.4035 | AA12: =Thesis!$M$12 -> 568.48031
A13: 2. 新增產能的世代與單位經濟（Tokenomics v21.7 基準成本；自研晶片＝GB300 錨 × IF_NonNV_Hold_Trn，v0.3.1）
A14: NVIDIA 新增中 VR200 比例 | B14: % | F14: =na_vr26 -> 0 | G14: =na_vr26 -> 0 | H14: =na_vr27 -> 0.5 | I14: =na_vr28 -> 1 | J14: =na_vr28 -> 1 | K14: =na_vr28 -> 1 | L14: =na_vr28 -> 1 | M14: =na_vr28 -> 1
A15: 新增 MW 加權 IF_HoldEcon（含自研晶片係數） | B15: US$m/MW-年 | F15: =cust_sh*tk_he_gb300*cf_chip+(1-cust_sh)*((1-Thesis!$F$14)*tk_he_gb300+Thesis!$F$14*tk_he_vr200) -> 8.7635609 | G15: =cust_sh*tk_he_gb300*cf_chip+(1-cust_sh)*((1-Thesis!$G$14)*tk_he_gb300+Thesis!$G$14*tk_he_vr200) -> 8.7635609 | H15: =cust_sh*tk_he_gb300*cf_chip+(1-cust_sh)*((1-Thesis!$H$14)*tk_he_gb300+Thesis!$H$14*tk_he_vr200) -> 9.0983259 | I15: =cust_sh*tk_he_gb300*cf_chip+(1-cust_sh)*((1-Thesis!$I$14)*tk_he_gb300+Thesis!$I$14*tk_he_vr200) -> 9.4330909 | J15: =cust_sh*tk_he_gb300*cf_chip+(1-cust_sh)*((1-Thesis!$J$14)*tk_he_gb300+Thesis!$J$14*tk_he_vr200) -> 9.4330909 | K15: =cust_sh*tk_he_gb300*cf_chip+(1-cust_sh)*((1-Thesis!$K$14)*tk_he_gb300+Thesis!$K$14*tk_he_vr200) -> 9.4330909 | L15: =cust_sh*tk_he_gb300*cf_chip+(1-cust_sh)*((1-Thesis!$L$14)*tk_he_gb300+Thesis!$L$14*tk_he_vr200) -> 9.4330909 | M15: =cust_sh*tk_he_gb300*cf_chip+(1-cust_sh)*((1-Thesis!$M$14)*tk_he_gb300+Thesis!$M$14*tk_he_vr200) -> 9.4330909
A16: 新增 MW 加權營運費用（IF_OpexGW） | B16: US$m/MW-年 | F16: =cust_sh*tk_ox_gb300+(1-cust_sh)*((1-Thesis!$F$14)*tk_ox_gb300+Thesis!$F$14*tk_ox_vr200) -> 1.9826348 | G16: =cust_sh*tk_ox_gb300+(1-cust_sh)*((1-Thesis!$G$14)*tk_ox_gb300+Thesis!$G$14*tk_ox_vr200) -> 1.9826348 | H16: =cust_sh*tk_ox_gb300+(1-cust_sh)*((1-Thesis!$H$14)*tk_ox_gb300+Thesis!$H$14*tk_ox_vr200) -> 2.01035 | I16: =cust_sh*tk_ox_gb300+(1-cust_sh)*((1-Thesis!$I$14)*tk_ox_gb300+Thesis!$I$14*tk_ox_vr200) -> 2.0380652 | J16: =cust_sh*tk_ox_gb300+(1-cust_sh)*((1-Thesis!$J$14)*tk_ox_gb300+Thesis!$J$14*tk_ox_vr200) -> 2.0380652 | K16: =cust_sh*tk_ox_gb300+(1-cust_sh)*((1-Thesis!$K$14)*tk_ox_gb300+Thesis!$K$14*tk_ox_vr200) -> 2.0380652 | L16: =cust_sh*tk_ox_gb300+(1-cust_sh)*((1-Thesis!$L$14)*tk_ox_gb300+Thesis!$L$14*tk_ox_vr200) -> 2.0380652 | M16: =cust_sh*tk_ox_gb300+(1-cust_sh)*((1-Thesis!$M$14)*tk_ox_gb300+Thesis!$M$14*tk_ox_vr200) -> 2.0380652
A17: 新增 MW 加權 IT 資本支出（IF_CapexIT；含自研晶片資本支出係數） | B17: US$m/MW | F17: =cust_sh*tk_cx_gb300*cf_cx+(1-cust_sh)*((1-Thesis!$F$14)*tk_cx_gb300+Thesis!$F$14*tk_cx_vr200) -> 25.950965 | G17: =cust_sh*tk_cx_gb300*cf_cx+(1-cust_sh)*((1-Thesis!$G$14)*tk_cx_gb300+Thesis!$G$14*tk_cx_vr200) -> 25.950965 | H17: =cust_sh*tk_cx_gb300*cf_cx+(1-cust_sh)*((1-Thesis!$H$14)*tk_cx_gb300+Thesis!$H$14*tk_cx_vr200) -> 27.288247 | I17: =cust_sh*tk_cx_gb300*cf_cx+(1-cust_sh)*((1-Thesis!$I$14)*tk_cx_gb300+Thesis!$I$14*tk_cx_vr200) -> 28.625529 | J17: =cust_sh*tk_cx_gb300*cf_cx+(1-cust_sh)*((1-Thesis!$J$14)*tk_cx_gb300+Thesis!$J$14*tk_cx_vr200) -> 28.625529 | K17: =cust_sh*tk_cx_gb300*cf_cx+(1-cust_sh)*((1-Thesis!$K$14)*tk_cx_gb300+Thesis!$K$14*tk_cx_vr200) -> 28.625529 | L17: =cust_sh*tk_cx_gb300*cf_cx+(1-cust_sh)*((1-Thesis!$L$14)*tk_cx_gb300+Thesis!$L$14*tk_cx_vr200) -> 28.625529 | M17: =cust_sh*tk_cx_gb300*cf_cx+(1-cust_sh)*((1-Thesis!$M$14)*tk_cx_gb300+Thesis!$M$14*tk_cx_vr200) -> 28.625529
A18: 期初後新增對外 MW 累計（期末） | B18: MW | E18: =Thesis!$E$8-mw_open -> 947.225 | F18: =Thesis!$F$8-mw_open -> 1880.475 | G18: =Thesis!$F$18 -> 1880.475 | H18: =Thesis!$H$8-mw_open -> 5613.475 | I18: =Thesis!$I$8-mw_open -> 9346.475 | J18: =Thesis!$J$8-mw_open -> 13079.475 | K18: =Thesis!$K$8-mw_open -> 15719.736 | L18: =Thesis!$L$8-mw_open -> 17267.259 | M18: =Thesis!$M$8-mw_open -> 17722.043
A19: Σ 新增 MW × HoldEcon | B19: US$m | E19: =Thesis!$E$18*Thesis!$F$15 -> 8301.0639 | F19: =Thesis!$E$19+Thesis!$F$11*Thesis!$F$15 -> 16479.657 | G19: =Thesis!$F$19 -> 16479.657 | H19: =Thesis!$G$19+Thesis!$H$11*Thesis!$H$15 -> 50443.708 | I19: =Thesis!$H$19+Thesis!$I$11*Thesis!$I$15 -> 85657.436 | J19: =Thesis!$I$19+Thesis!$J$11*Thesis!$J$15 -> 120871.16 | K19: =Thesis!$J$19+Thesis!$K$11*Thesis!$K$15 -> 145776.99 | L19: =Thesis!$K$19+Thesis!$L$11*Thesis!$L$15 -> 160374.91 | M19: =Thesis!$L$19+Thesis!$M$11*Thesis!$M$15 -> 164664.93
A20: Σ 新增 MW × 營運費用 | B20: US$m | E20: =Thesis!$E$18*Thesis!$F$16 -> 1878.0013 | F20: =Thesis!$E$20+Thesis!$F$11*Thesis!$F$16 -> 3728.2952 | G20: =Thesis!$F$20 -> 3728.2952 | H20: =Thesis!$G$20+Thesis!$H$11*Thesis!$H$16 -> 11232.932 | I20: =Thesis!$H$20+Thesis!$I$11*Thesis!$I$16 -> 18841.029 | J20: =Thesis!$I$20+Thesis!$J$11*Thesis!$J$16 -> 26449.126 | K20: =Thesis!$J$20+Thesis!$K$11*Thesis!$K$16 -> 31830.151 | L20: =Thesis!$K$20+Thesis!$L$11*Thesis!$L$16 -> 34984.104 | M20: =Thesis!$L$20+Thesis!$M$11*Thesis!$M$16 -> 35910.984
A21: 新增機隊加權 HoldEcon | B21: US$m/MW-年 | F21: =IF(Thesis!$F$18>0,Thesis!$F$19/Thesis!$F$18,Thesis!$F$15) -> 8.7635609 | G21: =IF(Thesis!$G$18>0,Thesis!$G$19/Thesis!$G$18,Thesis!$G$15) -> 8.7635609 | H21: =IF(Thesis!$H$18>0,Thesis!$H$19/Thesis!$H$18,Thesis!$H$15) -> 8.9861819 | I21: =IF(Thesis!$I$18>0,Thesis!$I$19/Thesis!$I$18,Thesis!$I$15) -> 9.1646782 | J21: =IF(Thesis!$J$18>0,Thesis!$J$19/Thesis!$J$18,Thesis!$J$15) -> 9.2412856 | K21: =IF(Thesis!$K$18>0,Thesis!$K$19/Thesis!$K$18,Thesis!$K$15) -> 9.2735009 | L21: =IF(Thesis!$L$18>0,Thesis!$L$19/Thesis!$L$18,Thesis!$L$15) -> 9.2878036 | M21: =IF(Thesis!$M$18>0,Thesis!$M$19/Thesis!$M$18,Thesis!$M$15) -> 9.291532
A22: 新增機隊加權營運費用 | B22: US$m/MW-年 | F22: =IF(Thesis!$F$18>0,Thesis!$F$20/Thesis!$F$18,Thesis!$F$16) -> 1.9826348 | G22: =IF(Thesis!$G$18>0,Thesis!$G$20/Thesis!$G$18,Thesis!$G$16) -> 1.9826348 | H22: =IF(Thesis!$H$18>0,Thesis!$H$20/Thesis!$H$18,Thesis!$H$16) -> 2.0010656 | I22: =IF(Thesis!$I$18>0,Thesis!$I$20/Thesis!$I$18,Thesis!$I$16) -> 2.0158433 | J22: =IF(Thesis!$J$18>0,Thesis!$J$20/Thesis!$J$18,Thesis!$J$16) -> 2.0221856 | K22: =IF(Thesis!$K$18>0,Thesis!$K$20/Thesis!$K$18,Thesis!$K$16) -> 2.0248527 | L22: =IF(Thesis!$L$18>0,Thesis!$L$20/Thesis!$L$18,Thesis!$L$16) -> 2.0260369 | M22: =IF(Thesis!$M$18>0,Thesis!$M$20/Thesis!$M$18,Thesis!$M$16) -> 2.0263455
A23: 新增產能每 MW 年收入＝新增機隊 HoldEcon × 情境 k | B23: US$m/MW-年 | F23: =Thesis!$F$21*k_A -> 13.306014 | G23: =Thesis!$G$21*k_A -> 13.306014 | H23: =Thesis!$H$21*k_A -> 13.644027 | I23: =Thesis!$I$21*k_A -> 13.915044 | J23: =Thesis!$J$21*k_A -> 14.03136 | K23: =Thesis!$K$21*k_A -> 14.080274 | L23: =Thesis!$L$21*k_A -> 14.10199 | M23: =Thesis!$M$21*k_A -> 14.107651 | P23: 6/30 機隊 2,080 MW 三情境同用 rpm_open（k_B）；情境 k 用於 6/30 之後的新產能（含 Q3 新增）
A24: 新增產能平均在役 MW（期間） | B24: MW | F24: =(Thesis!$E$18+Thesis!$F$18)/2 -> 1413.85 | H24: =(Thesis!$G$18+Thesis!$H$18)/2 -> 3746.975 | I24: =(Thesis!$H$18+Thesis!$I$18)/2 -> 7479.975 | J24: =(Thesis!$I$18+Thesis!$J$18)/2 -> 11212.975 | K24: =(Thesis!$J$18+Thesis!$K$18)/2 -> 14399.606 | L24: =(Thesis!$K$18+Thesis!$L$18)/2 -> 16493.498 | M24: =(Thesis!$L$18+Thesis!$M$18)/2 -> 17494.651
A25: 3. AWS AI 損益（收入端不乘 IF_Util：MW-year 計價）
A26: AWS AI 營收（命題子列） | B26: US$bn | C26: =Thesis!$C$9*rpm_open*Thesis!$C$10/1000 -> 2.3210054 | D26: =Thesis!$D$9*rpm_open*Thesis!$D$10/1000 -> 8.7037701 | E26: =Thesis!$E$9*rpm_open*Thesis!$E$10/1000 -> 16.200708 | F26: =(mw_open*rpm_open+Thesis!$F$24*Thesis!$F$23)*Thesis!$F$10/1000 -> 9.732022 | G26: =Thesis!$E$26+Thesis!$F$26 -> 25.93273 | H26: =(mw_open*rpm_open+Thesis!$H$24*Thesis!$H$23)/1000 -> 71.239209 | I26: =(mw_open*rpm_open+Thesis!$I$24*Thesis!$I$23)/1000 -> 124.19956 | J26: =(mw_open*rpm_open+Thesis!$J$24*Thesis!$J$23)/1000 -> 177.44867 | K26: =(mw_open*rpm_open+Thesis!$K$24*Thesis!$K$23)/1000 -> 222.86577 | L26: =(mw_open*rpm_open+Thesis!$L$24*Thesis!$L$23)/1000 -> 252.70652 | M26: =(mw_open*rpm_open+Thesis!$M$24*Thesis!$M$23)/1000 -> 266.92381 | N26: =Thesis!$N$9*rpm_open*Thesis!$N$10/1000 -> 5.5486534 | O26: =Thesis!$O$9*rpm_open*Thesis!$O$10/1000 -> 3.1551167 | P26: 實績欄為分拆估計（期初 k，Derived），不是公司揭露值
A27: 全機隊每 MW 年收入 | B27: US$m/MW-年 | C27: =Thesis!$C$26*1000/(Thesis!$C$9*Thesis!$C$10) -> 9.6708557 | D27: =Thesis!$D$26*1000/(Thesis!$D$9*Thesis!$D$10) -> 9.6708557 | E27: =Thesis!$E$26*1000/(Thesis!$E$9*Thesis!$E$10) -> 9.6708557 | F27: =Thesis!$F$26*1000/(Thesis!$F$9*Thesis!$F$10) -> 11.141889 | G27: =Thesis!$G$26*1000/(Thesis!$G$9*Thesis!$G$10) -> 10.174998 | H27: =Thesis!$H$26*1000/(Thesis!$H$9*Thesis!$H$10) -> 12.225762 | I27: =Thesis!$I$26*1000/(Thesis!$I$9*Thesis!$I$10) -> 12.99162 | J27: =Thesis!$J$26*1000/(Thesis!$J$9*Thesis!$J$10) -> 13.349056 | K27: =Thesis!$K$26*1000/(Thesis!$K$9*Thesis!$K$10) -> 13.523732 | L27: =Thesis!$L$26*1000/(Thesis!$L$9*Thesis!$L$10) -> 13.605758 | M27: =Thesis!$M$26*1000/(Thesis!$M$9*Thesis!$M$10) -> 13.636198 | N27: =Thesis!$N$26*1000/(Thesis!$N$9*Thesis!$N$10) -> 9.6708557 | O27: =Thesis!$O$26*1000/(Thesis!$O$9*Thesis!$O$10) -> 9.6708557
A28: AI 營運成本（含自用 MW、租用機房租金 C22） | B28: US$bn | C28: =Thesis!$C$9/ext_sh*(ox_open+rent_mw)*Thesis!$C$10/1000 -> 0.64256921 | D28: =Thesis!$D$9/ext_sh*(ox_open+rent_mw)*Thesis!$D$10/1000 -> 2.4096345 | E28: =Thesis!$E$9/ext_sh*(ox_open+rent_mw)*Thesis!$E$10/1000 -> 4.4851582 | F28: =((mw_open*ox_open+Thesis!$F$24*Thesis!$F$22)/ext_sh+Thesis!$F$9/ext_sh*rent_mw)*Thesis!$F$10/1000 -> 2.3801764 | G28: =Thesis!$E$28+Thesis!$F$28 -> 6.8653345 | H28: =((mw_open*ox_open+Thesis!$H$24*Thesis!$H$22)/ext_sh+Thesis!$H$9/ext_sh*rent_mw)*Thesis!$H$10/1000 -> 16.128216 | I28: =((mw_open*ox_open+Thesis!$I$24*Thesis!$I$22)/ext_sh+Thesis!$I$9/ext_sh*rent_mw)*Thesis!$I$10/1000 -> 26.786287 | J28: =((mw_open*ox_open+Thesis!$J$24*Thesis!$J$22)/ext_sh+Thesis!$J$9/ext_sh*rent_mw)*Thesis!$J$10/1000 -> 37.464039 | K28: =((mw_open*ox_open+Thesis!$K$24*Thesis!$K$22)/ext_sh+Thesis!$K$9/ext_sh*rent_mw)*Thesis!$K$10/1000 -> 46.576359 | L28: =((mw_open*ox_open+Thesis!$L$24*Thesis!$L$22)/ext_sh+Thesis!$L$9/ext_sh*rent_mw)*Thesis!$L$10/1000 -> 52.563792 | M28: =((mw_open*ox_open+Thesis!$M$24*Thesis!$M$22)/ext_sh+Thesis!$M$9/ext_sh*rent_mw)*Thesis!$M$10/1000 -> 55.423125 | N28: =Thesis!$N$9/ext_sh*(ox_open+rent_mw)*Thesis!$N$10/1000 -> 1.536142 | O28: =Thesis!$O$9/ext_sh*(ox_open+rent_mw)*Thesis!$O$10/1000 -> 0.87349252
A29: AWS 營收（實績，Q 頁） | B29: US$bn | C29: =Q!$D$7 -> 107.556 | D29: =Q!$E$7 -> 128.725 | E29: =Q!$O$7 -> 125.803 | N29: =Q!$N$7 -> 93.146 | O29: =Q!$J$7 -> 35.579
A30: AWS 其他營收（非 AI 雲端） | B30: US$bn | C30: =Thesis!$C$29-Thesis!$C$26 -> 105.23499 | D30: =Thesis!$D$29-Thesis!$D$26 -> 120.02123 | E30: =Thesis!$E$29-Thesis!$E$26 -> 109.60229 | F30: =Thesis!$O$30*(1+Thesis!$F$31) -> 36.97966 | G30: =Thesis!$E$30+Thesis!$F$30 -> 146.58195 | H30: =Thesis!$G$30*(1+Thesis!$H$31) -> 164.96042 | I30: =Thesis!$H$30*(1+Thesis!$I$31) -> 183.14786 | J30: =Thesis!$I$30*(1+Thesis!$J$31) -> 200.57012 | K30: =Thesis!$J$30*(1+Thesis!$K$31) -> 216.61573 | L30: =Thesis!$K$30*(1+Thesis!$L$31) -> 233.94498 | M30: =Thesis!$L$30*(1+Thesis!$M$31) -> 252.66058 | N30: =Thesis!$N$29-Thesis!$N$26 -> 87.597347 | O30: =Thesis!$O$29-Thesis!$O$26 -> 32.423883 | P30: 實績＝AWS 實績 − AWS AI 分拆估計（殘差，Derived）
A31: AWS 其他年增 | B31: % | D31: =Thesis!$D$30/Thesis!$C$30-1 -> 0.14050683 | E31: =Thesis!$E$30/Thesis!$N$30-1 -> 0.25120562 | F31: =IF(awso_g0=1,Thesis!$E$31,Thesis!$D$31) -> 0.14050683 | G31: =Thesis!$G$30/Thesis!$D$30-1 -> 0.2213002 | H31: =Thesis!$F$31+(g_awso_lt-Thesis!$F$31)*1/4 -> 0.12538012 | I31: =Thesis!$F$31+(g_awso_lt-Thesis!$F$31)*2/4 -> 0.11025341 | J31: =Thesis!$F$31+(g_awso_lt-Thesis!$F$31)*3/4 -> 0.095126707 | K31: =Thesis!$F$31+(g_awso_lt-Thesis!$F$31)*4/4 -> 0.08 | L31: =g_awso_lt -> 0.08 | M31: =g_awso_lt -> 0.08 | P31: 起點＝FY2025 年增（D 欄，Derived；In 頁 awso_g0＝0）；9M26 年增（E 欄）受 AI 分拆低估影響偏高，只列不用（awso_g0＝1 時改用，Sens）；收斂到 g_awso_lt
A32: 4. AI 資本支出（現金）→ 折舊（IT 6 年、機房 20 年；次年起提列）
A33: Q4 26 非 AI 資本支出（零售＋AWS 其他） | B33: US$bn | F33: =cx_rt*Seg!$F$20+cx_awso*Thesis!$F$30 -> 19.116381
A34: AI 資本支出中 IT 比例 | B34: % | C34: =tk_cx_h100/(tk_cx_h100+tk_fac*(1-colo_sh)) -> 0.73075646 | D34: =tk_cx_h100/(tk_cx_h100+tk_fac*(1-colo_sh)) -> 0.73075646 | E34: =Thesis!$F$34 -> 0.71912296 | F34: =Thesis!$F$17/(Thesis!$F$17+tk_fac*(1-colo_sh)) -> 0.71912296 | G34: =Thesis!$G$17/(Thesis!$G$17+tk_fac*(1-colo_sh)) -> 0.71912296 | H34: =Thesis!$H$17/(Thesis!$H$17+tk_fac*(1-colo_sh)) -> 0.72915955 | I34: =Thesis!$I$17/(Thesis!$I$17+tk_fac*(1-colo_sh)) -> 0.73850361 | J34: =Thesis!$J$17/(Thesis!$J$17+tk_fac*(1-colo_sh)) -> 0.73850361 | K34: =Thesis!$K$17/(Thesis!$K$17+tk_fac*(1-colo_sh)) -> 0.73850361 | L34: =Thesis!$L$17/(Thesis!$L$17+tk_fac*(1-colo_sh)) -> 0.73850361 | M34: =Thesis!$M$17/(Thesis!$M$17+tk_fac*(1-colo_sh)) -> 0.73850361
A35: AI 資本支出（現金，含自用） | B35: US$bn | C35: =Q!$D$48-cx_rt*Q!$D$16-cx_awso*Thesis!$C$30 -> 25.278105 | D35: =Q!$E$48-cx_rt*Q!$E$16-cx_awso*Thesis!$D$30 -> 69.568632 | E35: =Q!$O$48-cx_rt*Q!$O$16-cx_awso*Thesis!$E$30 -> 123.19605 | F35: =capex_g26-Q!$O$48-Thesis!$F$33 -> 28.695619 | G35: =Thesis!$E$35+Thesis!$F$35 -> 151.89167 | H35: =Thesis!$H$12*(Thesis!$H$17+tk_fac*(1-colo_sh))/1000+Thesis!$H$39 -> 174.63089 | I35: =Thesis!$I$12*(Thesis!$I$17+tk_fac*(1-colo_sh))/1000+Thesis!$I$39 -> 180.87099 | J35: =Thesis!$J$12*(Thesis!$J$17+tk_fac*(1-colo_sh))/1000+Thesis!$J$39 -> 185.16482 | K35: =Thesis!$K$12*(Thesis!$K$17+tk_fac*(1-colo_sh))/1000+Thesis!$K$39 -> 136.51337 | L35: =Thesis!$L$12*(Thesis!$L$17+tk_fac*(1-colo_sh))/1000+Thesis!$L$39 -> 113.6249 | M35: =Thesis!$M$12*(Thesis!$M$17+tk_fac*(1-colo_sh))/1000+Thesis!$M$39 -> 112.22258 | P35: 實績＝公司資本支出淨額 − 非 AI（零售 cx_rt、AWS 其他 cx_awso）；Q4 26＝指引 220 − 9M 實績 − 非 AI（修正三：FY2026 現金資本支出錨定指引；Q4 新增 MW 部分由已投入的在建資本支出支應）；之後＝新增 MW ×（IT＋自建機房）＋汰換 | R35: =Q!$C$48-cx_rt*Q!$C$16-cx_awso*(Q!$C$7-mw_ye23/2*rpm_open/1000) -> 1.5042998 | S35: =Thesis!$C$35 -> 25.278105 | T35: =Thesis!$D$35 -> 69.568632 | U35: =Thesis!$G$35 -> 151.89167 | V35: =Thesis!$H$35 -> 174.63089 | W35: =Thesis!$I$35 -> 180.87099 | X35: =Thesis!$J$35 -> 185.16482 | Y35: =Thesis!$K$35 -> 136.51337 | Z35: =Thesis!$L$35 -> 113.6249 | AA35: =Thesis!$M$35 -> 112.22258
A36: C10：Q4 26 AI 資本支出公式值＝新增總 MW ×（IT＋自建機房） | B36: US$bn | F36: =Thesis!$F$12*(Thesis!$F$17+tk_fac*(1-colo_sh))/1000 -> 42.0977
A37: C10 對帳（下半年視窗）：（指引 − 上半年實績）÷ 2 −（Q4 公式 AI＋Q4 非 AI） | B37: US$bn | F37: =(capex_g26-Q!$P$48)/2-(Thesis!$F$36+Thesis!$F$33) -> 0.6309188 | P37: 情境 B 以 calib_pace_v031.py 解 pace_B 使本列＝0；A／C 情境速度不同，本列不為 0
A38: 對照：Q4 26 指引補足額＝Q4 錨定值 − Q4 公式值（負值＝Q4 公式高於指引隱含） | B38: US$bn | F38: =Thesis!$F$35-Thesis!$F$36 -> -13.402081
A39: IT 汰換（折舊年限前新增的總 MW × 當年 IT 每 MW） | B39: US$bn | H39: =SUMPRODUCT(--(Thesis!$R$5:$AA$5=2027-tk_life),Thesis!$R$12:$AA$12)*Thesis!$H$17/1000 -> 0 | I39: =SUMPRODUCT(--(Thesis!$R$5:$AA$5=2028-tk_life),Thesis!$R$12:$AA$12)*Thesis!$I$17/1000 -> 0 | J39: =SUMPRODUCT(--(Thesis!$R$5:$AA$5=2029-tk_life),Thesis!$R$12:$AA$12)*Thesis!$J$17/1000 -> 4.2938294 | K39: =SUMPRODUCT(--(Thesis!$R$5:$AA$5=2030-tk_life),Thesis!$R$12:$AA$12)*Thesis!$K$17/1000 -> 8.5876588 | L39: =SUMPRODUCT(--(Thesis!$R$5:$AA$5=2031-tk_life),Thesis!$R$12:$AA$12)*Thesis!$L$17/1000 -> 38.644465 | M39: =SUMPRODUCT(--(Thesis!$R$5:$AA$5=2032-tk_life),Thesis!$R$12:$AA$12)*Thesis!$M$17/1000 -> 90.187414
A40: AI 資本支出：折舊基礎（實績期以新增在役 MW × 每 MW 成本為上限） | B40: US$bn | C40: =MIN(Thesis!$C$35,Thesis!$C$12*(tk_cx_h100+tk_fac*(1-colo_sh))/1000) -> 11.293864 | D40: =MIN(Thesis!$D$35,Thesis!$D$12*(tk_cx_h100+tk_fac*(1-colo_sh))/1000) -> 50.822389 | E40: =MIN(Thesis!$E$35,Thesis!$E$12*(Thesis!$F$17+tk_fac*(1-colo_sh))/1000) -> 71.597667 | F40: =Thesis!$F$35 -> 28.695619 | G40: =Thesis!$E$40+Thesis!$F$40 -> 100.29329 | H40: =Thesis!$H$35 -> 174.63089 | I40: =Thesis!$I$35 -> 180.87099 | J40: =Thesis!$J$35 -> 185.16482 | K40: =Thesis!$K$35 -> 136.51337 | L40: =Thesis!$L$35 -> 113.6249 | M40: =Thesis!$M$35 -> 112.22258 | P40: 實績期以新增在役 MW × 每 MW 成本為上限；超出部分見下列在建（修正三：延後轉入在役後提列折舊） | R40: =MIN(Thesis!$R$35,Thesis!$R$12*(tk_cx_h100+tk_fac*(1-colo_sh))/1000) -> 1.5042998 | S40: =Thesis!$C$40 -> 11.293864 | T40: =Thesis!$D$40 -> 50.822389 | U40: =Thesis!$G$40 -> 100.29329 | V40: =Thesis!$H$40 -> 174.63089 | W40: =Thesis!$I$40 -> 180.87099 | X40: =Thesis!$J$40 -> 185.16482 | Y40: =Thesis!$K$40 -> 136.51337 | Z40: =Thesis!$L$40 -> 113.6249 | AA40: =Thesis!$M$40 -> 112.22258
A41: 在建（CIP）：實績期超出新增在役 MW 成本的 AI 資本支出 | B41: US$bn | C41: =Thesis!$C$35-Thesis!$C$40 -> 13.984241 | D41: =Thesis!$D$35-Thesis!$D$40 -> 18.746243 | E41: =Thesis!$E$35-Thesis!$E$40 -> 51.598382 | F41: =Thesis!$F$35-Thesis!$F$40 -> 0 | G41: =Thesis!$G$35-Thesis!$G$40 -> 51.598382 | H41: =Thesis!$H$35-Thesis!$H$40 -> 0 | I41: =Thesis!$I$35-Thesis!$I$40 -> 0 | J41: =Thesis!$J$35-Thesis!$J$40 -> 0 | K41: =Thesis!$K$35-Thesis!$K$40 -> 0 | L41: =Thesis!$L$35-Thesis!$L$40 -> 0 | M41: =Thesis!$M$35-Thesis!$M$40 -> 0 | P41: 修正三：視為在建，延後 cip_lag 年轉入在役後提列折舊（仍計入 AI 投入資本）；AWS 分部折舊 2024→2025→1H26 年化 13.3→21.5→30.7 支持此處理 | R41: =Thesis!$R$35-Thesis!$R$40 -> 0 | S41: =Thesis!$S$35-Thesis!$S$40 -> 13.984241 | T41: =Thesis!$T$35-Thesis!$T$40 -> 18.746243 | U41: =Thesis!$U$35-Thesis!$U$40 -> 51.598382 | V41: =Thesis!$V$35-Thesis!$V$40 -> 0 | W41: =Thesis!$W$35-Thesis!$W$40 -> 0 | X41: =Thesis!$X$35-Thesis!$X$40 -> 0 | Y41: =Thesis!$Y$35-Thesis!$Y$40 -> 0 | Z41: =Thesis!$Z$35-Thesis!$Z$40 -> 0 | AA41: =Thesis!$AA$35-Thesis!$AA$40 -> 0
A42: 在建中 IT 設備（依支出年份） | B42: US$bn | R42: =Thesis!$R$41*Thesis!$C$34 -> 0 | S42: =Thesis!$S$41*Thesis!$C$34 -> 10.219074 | T42: =Thesis!$T$41*Thesis!$C$34 -> 13.698938 | U42: =Thesis!$U$41*Thesis!$E$34 -> 37.105581 | V42: =Thesis!$V$41*Thesis!$E$34 -> 0 | W42: =Thesis!$W$41*Thesis!$E$34 -> 0 | X42: =Thesis!$X$41*Thesis!$E$34 -> 0 | Y42: =Thesis!$Y$41*Thesis!$E$34 -> 0 | Z42: =Thesis!$Z$41*Thesis!$E$34 -> 0 | AA42: =Thesis!$AA$41*Thesis!$E$34 -> 0
A43: 在建轉入在役：IT（依轉入年份） | B43: US$bn | R43: =SUMPRODUCT(--(Thesis!$R$5:$AA$5=2023-cip_lag),Thesis!$R$42:$AA$42) -> 0 | S43: =SUMPRODUCT(--(Thesis!$R$5:$AA$5=2024-cip_lag),Thesis!$R$42:$AA$42) -> 0 | T43: =SUMPRODUCT(--(Thesis!$R$5:$AA$5=2025-cip_lag),Thesis!$R$42:$AA$42) -> 10.219074 | U43: =SUMPRODUCT(--(Thesis!$R$5:$AA$5=2026-cip_lag),Thesis!$R$42:$AA$42) -> 13.698938 | V43: =SUMPRODUCT(--(Thesis!$R$5:$AA$5=2027-cip_lag),Thesis!$R$42:$AA$42) -> 37.105581 | W43: =SUMPRODUCT(--(Thesis!$R$5:$AA$5=2028-cip_lag),Thesis!$R$42:$AA$42) -> 0 | X43: =SUMPRODUCT(--(Thesis!$R$5:$AA$5=2029-cip_lag),Thesis!$R$42:$AA$42) -> 0 | Y43: =SUMPRODUCT(--(Thesis!$R$5:$AA$5=2030-cip_lag),Thesis!$R$42:$AA$42) -> 0 | Z43: =SUMPRODUCT(--(Thesis!$R$5:$AA$5=2031-cip_lag),Thesis!$R$42:$AA$42) -> 0 | AA43: =SUMPRODUCT(--(Thesis!$R$5:$AA$5=2032-cip_lag),Thesis!$R$42:$AA$42) -> 0
A44: 在建轉入在役：機房（依轉入年份） | B44: US$bn | R44: =SUMPRODUCT(--(Thesis!$R$5:$AA$5=2023-cip_lag),Thesis!$R$41:$AA$41)-Thesis!$R$43 -> 0 | S44: =SUMPRODUCT(--(Thesis!$R$5:$AA$5=2024-cip_lag),Thesis!$R$41:$AA$41)-Thesis!$S$43 -> 0 | T44: =SUMPRODUCT(--(Thesis!$R$5:$AA$5=2025-cip_lag),Thesis!$R$41:$AA$41)-Thesis!$T$43 -> 3.7651666 | U44: =SUMPRODUCT(--(Thesis!$R$5:$AA$5=2026-cip_lag),Thesis!$R$41:$AA$41)-Thesis!$U$43 -> 5.0473048 | V44: =SUMPRODUCT(--(Thesis!$R$5:$AA$5=2027-cip_lag),Thesis!$R$41:$AA$41)-Thesis!$V$43 -> 14.492801 | W44: =SUMPRODUCT(--(Thesis!$R$5:$AA$5=2028-cip_lag),Thesis!$R$41:$AA$41)-Thesis!$W$43 -> 0 | X44: =SUMPRODUCT(--(Thesis!$R$5:$AA$5=2029-cip_lag),Thesis!$R$41:$AA$41)-Thesis!$X$43 -> 0 | Y44: =SUMPRODUCT(--(Thesis!$R$5:$AA$5=2030-cip_lag),Thesis!$R$41:$AA$41)-Thesis!$Y$43 -> 0 | Z44: =SUMPRODUCT(--(Thesis!$R$5:$AA$5=2031-cip_lag),Thesis!$R$41:$AA$41)-Thesis!$Z$43 -> 0 | AA44: =SUMPRODUCT(--(Thesis!$R$5:$AA$5=2032-cip_lag),Thesis!$R$41:$AA$41)-Thesis!$AA$43 -> 0
A45: 其中 IT 設備 | B45: US$bn | C45: =Thesis!$C$40*Thesis!$C$34 -> 8.2530642 | D45: =Thesis!$D$40*Thesis!$D$34 -> 37.138789 | E45: =Thesis!$E$40*Thesis!$E$34 -> 51.487526 | F45: =Thesis!$F$40*Thesis!$F$34 -> 20.635679 | G45: =Thesis!$E$45+Thesis!$F$45 -> 72.123205 | H45: =(Thesis!$H$40-Thesis!$H$39)*Thesis!$H$34+Thesis!$H$39 -> 127.33378 | I45: =(Thesis!$I$40-Thesis!$I$39)*Thesis!$I$34+Thesis!$I$39 -> 133.57388 | J45: =(Thesis!$J$40-Thesis!$J$39)*Thesis!$J$34+Thesis!$J$39 -> 137.86771 | K45: =(Thesis!$K$40-Thesis!$K$39)*Thesis!$K$34+Thesis!$K$39 -> 103.06126 | L45: =(Thesis!$L$40-Thesis!$L$39)*Thesis!$L$34+Thesis!$L$39 -> 94.01779 | M45: =(Thesis!$M$40-Thesis!$M$39)*Thesis!$M$34+Thesis!$M$39 -> 106.46046 | R45: =Thesis!$R$40*Thesis!$C$34 -> 1.0992768 | S45: =Thesis!$C$45 -> 8.2530642 | T45: =Thesis!$D$45 -> 37.138789 | U45: =Thesis!$G$45 -> 72.123205 | V45: =Thesis!$H$45 -> 127.33378 | W45: =Thesis!$I$45 -> 133.57388 | X45: =Thesis!$J$45 -> 137.86771 | Y45: =Thesis!$K$45 -> 103.06126 | Z45: =Thesis!$L$45 -> 94.01779 | AA45: =Thesis!$M$45 -> 106.46046
A46: 其中機房（自建部分） | B46: US$bn | C46: =Thesis!$C$40-Thesis!$C$45 -> 3.0408 | D46: =Thesis!$D$40-Thesis!$D$45 -> 13.6836 | E46: =Thesis!$E$40-Thesis!$E$45 -> 20.110141 | F46: =Thesis!$F$40-Thesis!$F$45 -> 8.0599406 | G46: =Thesis!$G$40-Thesis!$G$45 -> 28.170081 | H46: =Thesis!$H$40-Thesis!$H$45 -> 47.29711 | I46: =Thesis!$I$40-Thesis!$I$45 -> 47.29711 | J46: =Thesis!$J$40-Thesis!$J$45 -> 47.29711 | K46: =Thesis!$K$40-Thesis!$K$45 -> 33.452112 | L46: =Thesis!$L$40-Thesis!$L$45 -> 19.607114 | M46: =Thesis!$M$40-Thesis!$M$45 -> 5.7621164 | R46: =Thesis!$R$40-Thesis!$R$45 -> 0.40502301 | S46: =Thesis!$S$40-Thesis!$S$45 -> 3.0408 | T46: =Thesis!$T$40-Thesis!$T$45 -> 13.6836 | U46: =Thesis!$U$40-Thesis!$U$45 -> 28.170081 | V46: =Thesis!$V$40-Thesis!$V$45 -> 47.29711 | W46: =Thesis!$W$40-Thesis!$W$45 -> 47.29711 | X46: =Thesis!$X$40-Thesis!$X$45 -> 47.29711 | Y46: =Thesis!$Y$40-Thesis!$Y$45 -> 33.452112 | Z46: =Thesis!$Z$40-Thesis!$Z$45 -> 19.607114 | AA46: =Thesis!$AA$40-Thesis!$AA$45 -> 5.7621164
A47: AI 資本支出占公司資本支出 | B47: % | C47: =Thesis!$C$35/CF!$C$24 -> 0.32550549 | D47: =Thesis!$D$35/CF!$D$24 -> 0.54214956 | E47: =Thesis!$E$35/CF!$E$24 -> 0.71547407 | F47: =Thesis!$F$35/CF!$F$24 -> 0.60017609 | G47: =Thesis!$G$35/CF!$G$24 -> 0.69041667 | H47: =Thesis!$H$35/CF!$H$24 -> 0.69722655 | I47: =Thesis!$I$35/CF!$I$24 -> 0.68443525 | J47: =Thesis!$J$35/CF!$J$24 -> 0.6716233 | K47: =Thesis!$K$35/CF!$K$24 -> 0.58462163 | L47: =Thesis!$L$35/CF!$L$24 -> 0.52226265 | M47: =Thesis!$M$35/CF!$M$24 -> 0.50183458
A48: AI IT 折舊（含在建轉入） | B48: US$bn | C48: =Thesis!$S$48 -> 0.1832128 | D48: =Thesis!$T$48 -> 1.5587235 | E48: =Thesis!$G$48*0.75 -> 7.0887755 | F48: =Thesis!$G$48*0.25 -> 2.3629252 | G48: =Thesis!$U$48 -> 9.4517007 | H48: =Thesis!$V$48 -> 23.755391 | I48: =Thesis!$W$48 -> 51.161952 | J48: =Thesis!$X$48 -> 73.424265 | K48: =Thesis!$Y$48 -> 96.219003 | L48: =Thesis!$Z$48 -> 112.02037 | M48: =Thesis!$AA$48 -> 119.79702 | N48: =Thesis!$D$48*0.75 -> 1.1690426 | O48: =Thesis!$D$48*0.25 -> 0.38968087 | R48: =(SUMPRODUCT(--(Thesis!$R$5:$AA$5<Thesis!R$5),--(Thesis!$R$5:$AA$5>=Thesis!R$5-tk_life),Thesis!$R$45:$AA$45)+SUMPRODUCT(--(Thesis!$R$5:$AA$5<Thesis!R$5),--(Thesis!$R$5:$AA$5>=Thesis!R$5-tk_life),Thesis!$R$43:$AA$43))/tk_life -> 0 | S48: =(SUMPRODUCT(--(Thesis!$R$5:$AA$5<Thesis!S$5),--(Thesis!$R$5:$AA$5>=Thesis!S$5-tk_life),Thesis!$R$45:$AA$45)+SUMPRODUCT(--(Thesis!$R$5:$AA$5<Thesis!S$5),--(Thesis!$R$5:$AA$5>=Thesis!S$5-tk_life),Thesis!$R$43:$AA$43))/tk_life -> 0.1832128 | T48: =(SUMPRODUCT(--(Thesis!$R$5:$AA$5<Thesis!T$5),--(Thesis!$R$5:$AA$5>=Thesis!T$5-tk_life),Thesis!$R$45:$AA$45)+SUMPRODUCT(--(Thesis!$R$5:$AA$5<Thesis!T$5),--(Thesis!$R$5:$AA$5>=Thesis!T$5-tk_life),Thesis!$R$43:$AA$43))/tk_life -> 1.5587235 | U48: =(SUMPRODUCT(--(Thesis!$R$5:$AA$5<Thesis!U$5),--(Thesis!$R$5:$AA$5>=Thesis!U$5-tk_life),Thesis!$R$45:$AA$45)+SUMPRODUCT(--(Thesis!$R$5:$AA$5<Thesis!U$5),--(Thesis!$R$5:$AA$5>=Thesis!U$5-tk_life),Thesis!$R$43:$AA$43))/tk_life -> 9.4517007 | V48: =(SUMPRODUCT(--(Thesis!$R$5:$AA$5<Thesis!V$5),--(Thesis!$R$5:$AA$5>=Thesis!V$5-tk_life),Thesis!$R$45:$AA$45)+SUMPRODUCT(--(Thesis!$R$5:$AA$5<Thesis!V$5),--(Thesis!$R$5:$AA$5>=Thesis!V$5-tk_life),Thesis!$R$43:$AA$43))/tk_life -> 23.755391 | W48: =(SUMPRODUCT(--(Thesis!$R$5:$AA$5<Thesis!W$5),--(Thesis!$R$5:$AA$5>=Thesis!W$5-tk_life),Thesis!$R$45:$AA$45)+SUMPRODUCT(--(Thesis!$R$5:$AA$5<Thesis!W$5),--(Thesis!$R$5:$AA$5>=Thesis!W$5-tk_life),Thesis!$R$43:$AA$43))/tk_life -> 51.161952 | X48: =(SUMPRODUCT(--(Thesis!$R$5:$AA$5<Thesis!X$5),--(Thesis!$R$5:$AA$5>=Thesis!X$5-tk_life),Thesis!$R$45:$AA$45)+SUMPRODUCT(--(Thesis!$R$5:$AA$5<Thesis!X$5),--(Thesis!$R$5:$AA$5>=Thesis!X$5-tk_life),Thesis!$R$43:$AA$43))/tk_life -> 73.424265 | Y48: =(SUMPRODUCT(--(Thesis!$R$5:$AA$5<Thesis!Y$5),--(Thesis!$R$5:$AA$5>=Thesis!Y$5-tk_life),Thesis!$R$45:$AA$45)+SUMPRODUCT(--(Thesis!$R$5:$AA$5<Thesis!Y$5),--(Thesis!$R$5:$AA$5>=Thesis!Y$5-tk_life),Thesis!$R$43:$AA$43))/tk_life -> 96.219003 | ... AA48: =(SUMPRODUCT(--(Thesis!$R$5:$AA$5<Thesis!AA$5),--(Thesis!$R$5:$AA$5>=Thesis!AA$5-tk_life),Thesis!$R$45:$AA$45)+SUMPRODUCT(--(Thesis!$R$5:$AA$5<Thesis!AA$5),--(Thesis!$R$5:$AA$5>=Thesis!AA$5-tk_life),Thesis!$R$43:$AA$43))/tk_life -> 119.79702
A49: AI 機房折舊（含在建轉入） | B49: US$bn | C49: =Thesis!$S$49 -> 0.02025115 | D49: =Thesis!$T$49 -> 0.17229115 | E49: =Thesis!$G$49*0.75 -> 0.78354711 | F49: =Thesis!$G$49*0.25 -> 0.26118237 | G49: =Thesis!$U$49 -> 1.0447295 | H49: =Thesis!$V$49 -> 2.7055988 | I49: =Thesis!$W$49 -> 5.7950943 | J49: =Thesis!$X$49 -> 8.1599498 | K49: =Thesis!$Y$49 -> 10.524805 | L49: =Thesis!$Z$49 -> 12.197411 | M49: =Thesis!$AA$49 -> 13.177767 | N49: =Thesis!$D$49*0.75 -> 0.12921836 | O49: =Thesis!$D$49*0.25 -> 0.043072788 | R49: =(SUMPRODUCT(--(Thesis!$R$5:$AA$5<Thesis!R$5),Thesis!$R$46:$AA$46)+SUMPRODUCT(--(Thesis!$R$5:$AA$5<Thesis!R$5),Thesis!$R$44:$AA$44))/fac_life -> 0 | S49: =(SUMPRODUCT(--(Thesis!$R$5:$AA$5<Thesis!S$5),Thesis!$R$46:$AA$46)+SUMPRODUCT(--(Thesis!$R$5:$AA$5<Thesis!S$5),Thesis!$R$44:$AA$44))/fac_life -> 0.02025115 | T49: =(SUMPRODUCT(--(Thesis!$R$5:$AA$5<Thesis!T$5),Thesis!$R$46:$AA$46)+SUMPRODUCT(--(Thesis!$R$5:$AA$5<Thesis!T$5),Thesis!$R$44:$AA$44))/fac_life -> 0.17229115 | U49: =(SUMPRODUCT(--(Thesis!$R$5:$AA$5<Thesis!U$5),Thesis!$R$46:$AA$46)+SUMPRODUCT(--(Thesis!$R$5:$AA$5<Thesis!U$5),Thesis!$R$44:$AA$44))/fac_life -> 1.0447295 | V49: =(SUMPRODUCT(--(Thesis!$R$5:$AA$5<Thesis!V$5),Thesis!$R$46:$AA$46)+SUMPRODUCT(--(Thesis!$R$5:$AA$5<Thesis!V$5),Thesis!$R$44:$AA$44))/fac_life -> 2.7055988 | W49: =(SUMPRODUCT(--(Thesis!$R$5:$AA$5<Thesis!W$5),Thesis!$R$46:$AA$46)+SUMPRODUCT(--(Thesis!$R$5:$AA$5<Thesis!W$5),Thesis!$R$44:$AA$44))/fac_life -> 5.7950943 | X49: =(SUMPRODUCT(--(Thesis!$R$5:$AA$5<Thesis!X$5),Thesis!$R$46:$AA$46)+SUMPRODUCT(--(Thesis!$R$5:$AA$5<Thesis!X$5),Thesis!$R$44:$AA$44))/fac_life -> 8.1599498 | Y49: =(SUMPRODUCT(--(Thesis!$R$5:$AA$5<Thesis!Y$5),Thesis!$R$46:$AA$46)+SUMPRODUCT(--(Thesis!$R$5:$AA$5<Thesis!Y$5),Thesis!$R$44:$AA$44))/fac_life -> 10.524805 | ... AA49: =(SUMPRODUCT(--(Thesis!$R$5:$AA$5<Thesis!AA$5),Thesis!$R$46:$AA$46)+SUMPRODUCT(--(Thesis!$R$5:$AA$5<Thesis!AA$5),Thesis!$R$44:$AA$44))/fac_life -> 13.177767
A50: AI 折舊合計（對外 → AWS；自用 → 零售分部） | B50: US$bn | C50: =Thesis!$C$48+Thesis!$C$49 -> 0.20346395 | D50: =Thesis!$D$48+Thesis!$D$49 -> 1.7310146 | E50: =Thesis!$E$48+Thesis!$E$49 -> 7.8723227 | F50: =Thesis!$F$48+Thesis!$F$49 -> 2.6241076 | G50: =Thesis!$G$48+Thesis!$G$49 -> 10.49643 | H50: =Thesis!$H$48+Thesis!$H$49 -> 26.46099 | I50: =Thesis!$I$48+Thesis!$I$49 -> 56.957046 | J50: =Thesis!$J$48+Thesis!$J$49 -> 81.584215 | K50: =Thesis!$K$48+Thesis!$K$49 -> 106.74381 | L50: =Thesis!$L$48+Thesis!$L$49 -> 124.21778 | M50: =Thesis!$M$48+Thesis!$M$49 -> 132.97479 | N50: =Thesis!$N$48+Thesis!$N$49 -> 1.298261 | O50: =Thesis!$O$48+Thesis!$O$49 -> 0.43275366 | R50: =Thesis!$R$48+Thesis!$R$49 -> 0 | S50: =Thesis!$S$48+Thesis!$S$49 -> 0.20346395 | T50: =Thesis!$T$48+Thesis!$T$49 -> 1.7310146 | U50: =Thesis!$U$48+Thesis!$U$49 -> 10.49643 | V50: =Thesis!$V$48+Thesis!$V$49 -> 26.46099 | W50: =Thesis!$W$48+Thesis!$W$49 -> 56.957046 | X50: =Thesis!$X$48+Thesis!$X$49 -> 81.584215 | Y50: =Thesis!$Y$48+Thesis!$Y$49 -> 106.74381 | Z50: =Thesis!$Z$48+Thesis!$Z$49 -> 124.21778 | AA50: =Thesis!$AA$48+Thesis!$AA$49 -> 132.97479
A51: AI 淨 PP&E（期末） | B51: US$bn | C51: =Thesis!$S$51 -> 26.578941 | D51: =Thesis!$T$51 -> 94.416558 | G51: =Thesis!$U$51 -> 235.8118 | H51: =Thesis!$V$51 -> 383.9817 | I51: =Thesis!$W$51 -> 507.89564 | J51: =Thesis!$X$51 -> 611.47624 | K51: =Thesis!$Y$51 -> 641.2458 | L51: =Thesis!$Z$51 -> 630.65293 | M51: =Thesis!$AA$51 -> 609.90072 | R51: =SUM(Thesis!$R$35:$R$35)-SUM(Thesis!$R$50:$R$50) -> 1.5042998 | S51: =SUM(Thesis!$R$35:$S$35)-SUM(Thesis!$R$50:$S$50) -> 26.578941 | T51: =SUM(Thesis!$R$35:$T$35)-SUM(Thesis!$R$50:$T$50) -> 94.416558 | U51: =SUM(Thesis!$R$35:$U$35)-SUM(Thesis!$R$50:$U$50) -> 235.8118 | V51: =SUM(Thesis!$R$35:$V$35)-SUM(Thesis!$R$50:$V$50) -> 383.9817 | W51: =SUM(Thesis!$R$35:$W$35)-SUM(Thesis!$R$50:$W$50) -> 507.89564 | X51: =SUM(Thesis!$R$35:$X$35)-SUM(Thesis!$R$50:$X$50) -> 611.47624 | Y51: =SUM(Thesis!$R$35:$Y$35)-SUM(Thesis!$R$50:$Y$50) -> 641.2458 | Z51: =SUM(Thesis!$R$35:$Z$35)-SUM(Thesis!$R$50:$Z$50) -> 630.65293 | AA51: =SUM(Thesis!$R$35:$AA$35)-SUM(Thesis!$R$50:$AA$50) -> 609.90072
A52: 5. AWS AI 營業利益、自用 AI 成本、AWS 其他
A53: AWS AI EBITDA＝營收 − 對外比例 × 營運成本 | B53: US$bn | C53: =Thesis!$C$26-ext_sh*Thesis!$C$28 -> 1.80695 | D53: =Thesis!$D$26-ext_sh*Thesis!$D$28 -> 6.7760625 | E53: =Thesis!$E$26-ext_sh*Thesis!$E$28 -> 12.612582 | F53: =Thesis!$F$26-ext_sh*Thesis!$F$28 -> 7.8278809 | G53: =Thesis!$G$26-ext_sh*Thesis!$G$28 -> 20.440462 | H53: =Thesis!$H$26-ext_sh*Thesis!$H$28 -> 58.336637 | I53: =Thesis!$I$26-ext_sh*Thesis!$I$28 -> 102.77053 | J53: =Thesis!$J$26-ext_sh*Thesis!$J$28 -> 147.47744 | K53: =Thesis!$K$26-ext_sh*Thesis!$K$28 -> 185.60468 | L53: =Thesis!$L$26-ext_sh*Thesis!$L$28 -> 210.65549 | M53: =Thesis!$M$26-ext_sh*Thesis!$M$28 -> 222.58531 | N53: =Thesis!$N$26-ext_sh*Thesis!$N$28 -> 4.3197398 | O53: =Thesis!$O$26-ext_sh*Thesis!$O$28 -> 2.4563226
A54: AWS AI 營業利益＝EBITDA − 對外比例 × AI 折舊 | B54: US$bn | C54: =Thesis!$C$53-ext_sh*Thesis!$C$50 -> 1.6441788 | D54: =Thesis!$D$53-ext_sh*Thesis!$D$50 -> 5.3912507 | E54: =Thesis!$E$53-ext_sh*Thesis!$E$50 -> 6.3147234 | F54: =Thesis!$F$53-ext_sh*Thesis!$F$50 -> 5.7285949 | G54: =Thesis!$G$53-ext_sh*Thesis!$G$50 -> 12.043318 | H54: =Thesis!$H$53-ext_sh*Thesis!$H$50 -> 37.167845 | I54: =Thesis!$I$53-ext_sh*Thesis!$I$50 -> 57.204898 | J54: =Thesis!$J$53-ext_sh*Thesis!$J$50 -> 82.210066 | K54: =Thesis!$K$53-ext_sh*Thesis!$K$50 -> 100.20963 | L54: =Thesis!$L$53-ext_sh*Thesis!$L$50 -> 111.28126 | M54: =Thesis!$M$53-ext_sh*Thesis!$M$50 -> 116.20548 | N54: =Thesis!$N$53-ext_sh*Thesis!$N$50 -> 3.281131 | O54: =Thesis!$O$53-ext_sh*Thesis!$O$50 -> 2.1101197
A55: AWS AI 營業利益率 | B55: % | C55: =Thesis!$C$54/Thesis!$C$26 -> 0.70839079 | D55: =Thesis!$D$54/Thesis!$D$26 -> 0.61941557 | E55: =Thesis!$E$54/Thesis!$E$26 -> 0.3897807 | F55: =Thesis!$F$54/Thesis!$F$26 -> 0.58863357 | G55: =Thesis!$G$54/Thesis!$G$26 -> 0.46440611 | H55: =Thesis!$H$54/Thesis!$H$26 -> 0.52173298 | I55: =Thesis!$I$54/Thesis!$I$26 -> 0.46058855 | J55: =Thesis!$J$54/Thesis!$J$26 -> 0.46328928 | K55: =Thesis!$K$54/Thesis!$K$26 -> 0.44964121 | L55: =Thesis!$L$54/Thesis!$L$26 -> 0.44035771 | M55: =Thesis!$M$54/Thesis!$M$26 -> 0.43535075 | N55: =Thesis!$N$54/Thesis!$N$26 -> 0.59133825 | O55: =Thesis!$O$54/Thesis!$O$26 -> 0.66879293
A56: 自用 AI 影子效益（讀法 2：自用 MW × HoldEcon × k＝1；讀法 1 為 0；非財報營收） | B56: US$bn | C56: 0 | D56: 0 | E56: 0 | F56: =IF(internal_ai_reading=2,1,0)*(1-ext_sh)/ext_sh*(mw_open*he_open+Thesis!$F$24*Thesis!$F$21)*Thesis!$F$10/1000 -> 2.0418127 | G56: =Thesis!$E$56+Thesis!$F$56 -> 2.0418127 | H56: =IF(internal_ai_reading=2,1,0)*(1-ext_sh)/ext_sh*(mw_open*he_open+Thesis!$H$24*Thesis!$H$21)*Thesis!$H$10/1000 -> 13.48741 | I56: =IF(internal_ai_reading=2,1,0)*(1-ext_sh)/ext_sh*(mw_open*he_open+Thesis!$I$24*Thesis!$I$21)*Thesis!$I$10/1000 -> 22.207552 | J56: =IF(internal_ai_reading=2,1,0)*(1-ext_sh)/ext_sh*(mw_open*he_open+Thesis!$J$24*Thesis!$J$21)*Thesis!$J$10/1000 -> 30.975237 | K56: =IF(internal_ai_reading=2,1,0)*(1-ext_sh)/ext_sh*(mw_open*he_open+Thesis!$K$24*Thesis!$K$21)*Thesis!$K$10/1000 -> 38.45335 | L56: =IF(internal_ai_reading=2,1,0)*(1-ext_sh)/ext_sh*(mw_open*he_open+Thesis!$L$24*Thesis!$L$21)*Thesis!$L$10/1000 -> 43.366753 | M56: =IF(internal_ai_reading=2,1,0)*(1-ext_sh)/ext_sh*(mw_open*he_open+Thesis!$M$24*Thesis!$M$21)*Thesis!$M$10/1000 -> 45.707689 | N56: 0 | O56: 0 | P56: In 頁 internal_ai_reading＝2（主值）；只進評價口徑（NOPAT、EPS 評價口徑、分部加總零售本業）；實績欄為 0
A57: 自用 AI 成本（營運＋折舊；分攤到北美／國際，財報口徑） | B57: US$bn | C57: =(1-ext_sh)*(Thesis!$C$28+Thesis!$C$50) -> 0.16920663 | D57: =(1-ext_sh)*(Thesis!$D$28+Thesis!$D$50) -> 0.82812984 | E57: =(1-ext_sh)*(Thesis!$E$28+Thesis!$E$50) -> 2.4714962 | F57: =(1-ext_sh)*(Thesis!$F$28+Thesis!$F$50) -> 1.0008568 | G57: =(1-ext_sh)*(Thesis!$G$28+Thesis!$G$50) -> 3.472353 | H57: =(1-ext_sh)*(Thesis!$H$28+Thesis!$H$50) -> 8.5178412 | I57: =(1-ext_sh)*(Thesis!$I$28+Thesis!$I$50) -> 16.748667 | J57: =(1-ext_sh)*(Thesis!$J$28+Thesis!$J$50) -> 23.809651 | K57: =(1-ext_sh)*(Thesis!$K$28+Thesis!$K$50) -> 30.664034 | L57: =(1-ext_sh)*(Thesis!$L$28+Thesis!$L$50) -> 35.356314 | M57: =(1-ext_sh)*(Thesis!$M$28+Thesis!$M$50) -> 37.679583 | N57: =(1-ext_sh)*(Thesis!$N$28+Thesis!$N$50) -> 0.5668806 | O57: =(1-ext_sh)*(Thesis!$O$28+Thesis!$O$50) -> 0.26124924
A58: AWS 營業利益（實績，Q 頁） | B58: US$bn | C58: =Q!$D$25 -> 39.834 | D58: =Q!$E$25 -> 45.606 | E58: =Q!$O$25 -> 48.555 | N58: =Q!$N$25 -> 33.141 | O58: =Q!$J$25 -> 12.465
A59: AWS 其他營業利益 | B59: US$bn | C59: =Thesis!$C$58-Thesis!$C$54 -> 38.189821 | D59: =Thesis!$D$58-Thesis!$D$54 -> 40.214749 | E59: =Thesis!$E$58-Thesis!$E$54 -> 42.240277 | F59: =Thesis!$F$30*Thesis!$F$60 -> 13.694314 | G59: =Thesis!$E$59+Thesis!$F$59 -> 55.934591 | H59: =Thesis!$H$30*Thesis!$H$60 -> 61.088168 | I59: =Thesis!$I$30*Thesis!$I$60 -> 67.823348 | J59: =Thesis!$J$30*Thesis!$J$60 -> 74.275159 | K59: =Thesis!$K$30*Thesis!$K$60 -> 80.217172 | L59: =Thesis!$L$30*Thesis!$L$60 -> 86.634546 | M59: =Thesis!$M$30*Thesis!$M$60 -> 93.565309 | N59: =Thesis!$N$58-Thesis!$N$54 -> 29.859869 | O59: =Thesis!$O$58-Thesis!$O$54 -> 10.35488 | P59: 實績＝AWS 營業利益 − AWS AI 營業利益（殘差）
A60: AWS 其他營業利益率 | B60: % | C60: =Thesis!$C$59/Thesis!$C$30 -> 0.3629004 | D60: =Thesis!$D$59/Thesis!$D$30 -> 0.33506363 | E60: =Thesis!$E$59/Thesis!$E$30 -> 0.38539592 | F60: =(Thesis!$O$59+Thesis!$E$59)/(Thesis!$O$30+Thesis!$E$30) -> 0.37032017 | G60: =Thesis!$G$59/Thesis!$G$30 -> 0.38159262 | H60: =Thesis!$F$60 -> 0.37032017 | I60: =Thesis!$F$60 -> 0.37032017 | J60: =Thesis!$F$60 -> 0.37032017 | K60: =Thesis!$F$60 -> 0.37032017 | L60: =Thesis!$F$60 -> 0.37032017 | M60: =Thesis!$F$60 -> 0.37032017 | N60: =Thesis!$N$59/Thesis!$N$30 -> 0.34087641 | O60: =Thesis!$O$59/Thesis!$O$30 -> 0.31935966 | P60: Q4 26 起固定為近四季（2025Q4＋9M26）殘差利益率（Derived）
A61: AWS 非 AI 折舊 ÷ AWS 其他營收（FY2025 校準） | B61: % | D61: =(Q!$E$33-ext_sh*Thesis!$D$50)/Thesis!$D$30 -> 0.16718033
A62: AWS 折舊攤銷（分部） | B62: US$bn | C62: =Q!$D$33 -> 13.32 | D62: =Q!$E$33 -> 21.45 | E62: =Q!$O$33 -> 23.817285 | F62: =ext_sh*Thesis!$F$50+Thesis!$D$61*Thesis!$F$30 -> 8.2815577 | G62: =Thesis!$E$62+Thesis!$F$62 -> 32.098842 | H62: =ext_sh*Thesis!$H$50+Thesis!$D$61*Thesis!$H$30 -> 48.746928 | I62: =ext_sh*Thesis!$I$50+Thesis!$D$61*Thesis!$I$30 -> 76.184357 | J62: =ext_sh*Thesis!$J$50+Thesis!$D$61*Thesis!$J$30 -> 98.798749 | K62: =ext_sh*Thesis!$K$50+Thesis!$D$61*Thesis!$K$30 -> 121.60893 | L62: =ext_sh*Thesis!$L$50+Thesis!$D$61*Thesis!$L$30 -> 138.48522 | M62: =ext_sh*Thesis!$M$50+Thesis!$D$61*Thesis!$M$30 -> 148.61971 | N62: =Q!$N$33 -> 14.882 | O62: =Q!$J$33 -> 6.568
A63: 6. 命題指標
A64: 對外 AI ROIC（稅後營業利益 ÷ 對外分攤的平均 AI 淨 PP&E） | B64: % | G64: =Thesis!$G$54*(1-tax)/(ext_sh*(Thesis!$D$51+Thesis!$G$51)/2) -> 0.075347744 | H64: =Thesis!$H$54*(1-tax)/(ext_sh*(Thesis!$G$51+Thesis!$H$51)/2) -> 0.12389644 | I64: =Thesis!$I$54*(1-tax)/(ext_sh*(Thesis!$H$51+Thesis!$I$51)/2) -> 0.13251545 | J64: =Thesis!$J$54*(1-tax)/(ext_sh*(Thesis!$I$51+Thesis!$J$51)/2) -> 0.15173615 | K64: =Thesis!$K$54*(1-tax)/(ext_sh*(Thesis!$J$51+Thesis!$K$51)/2) -> 0.16526969 | L64: =Thesis!$L$54*(1-tax)/(ext_sh*(Thesis!$K$51+Thesis!$L$51)/2) -> 0.18076234 | M64: =Thesis!$M$54*(1-tax)/(ext_sh*(Thesis!$L$51+Thesis!$M$51)/2) -> 0.19353054 | P64: C11：分子分母同口徑（對外）
A65: 機隊平均 k（營收 ÷ 持有成本） | B65: x | H65: =Thesis!$H$26*1000/(mw_open*he_open+Thesis!$H$24*Thesis!$H$21) -> 1.320476 | I65: =Thesis!$I$26*1000/(mw_open*he_open+Thesis!$I$24*Thesis!$I$21) -> 1.3981681 | J65: =Thesis!$J$26*1000/(mw_open*he_open+Thesis!$J$24*Thesis!$J$21) -> 1.4321817 | K65: =Thesis!$K$26*1000/(mw_open*he_open+Thesis!$K$24*Thesis!$K$21) -> 1.448936 | L65: =Thesis!$L$26*1000/(mw_open*he_open+Thesis!$L$24*Thesis!$L$21) -> 1.4567987 | M65: =Thesis!$M$26*1000/(mw_open*he_open+Thesis!$M$24*Thesis!$M$21) -> 1.4599503
A66: 打平 k（對外 AI ROIC＝WACC 所需的機隊平均 k） | B66: x | H66: =Thesis!$H$65*(Thesis!$H$26+wacc*ext_sh*(Thesis!$G$51+Thesis!$H$51)/2/(1-tax)-Thesis!$H$54)/Thesis!$H$26 -> 1.2539539 | I66: =Thesis!$I$65*(Thesis!$I$26+wacc*ext_sh*(Thesis!$H$51+Thesis!$I$51)/2/(1-tax)-Thesis!$I$54)/Thesis!$I$26 -> 1.2981457 | J66: =Thesis!$J$65*(Thesis!$J$26+wacc*ext_sh*(Thesis!$I$51+Thesis!$J$51)/2/(1-tax)-Thesis!$J$54)/Thesis!$J$26 -> 1.258131 | K66: =Thesis!$K$65*(Thesis!$K$26+wacc*ext_sh*(Thesis!$J$51+Thesis!$K$51)/2/(1-tax)-Thesis!$K$54)/Thesis!$K$26 -> 1.2386811 | L66: =Thesis!$L$65*(Thesis!$L$26+wacc*ext_sh*(Thesis!$K$51+Thesis!$L$51)/2/(1-tax)-Thesis!$L$54)/Thesis!$L$26 -> 1.2125293 | M66: =Thesis!$M$65*(Thesis!$M$26+wacc*ext_sh*(Thesis!$L$51+Thesis!$M$51)/2/(1-tax)-Thesis!$M$54)/Thesis!$M$26 -> 1.1919696
A67: 上限檢查：全機隊每 MW 年收入 ÷ Tokenomics P×Q（VR200） | B67: % | C67: =Thesis!$C$27/tk_pq -> 0.19531643 | D67: =Thesis!$D$27/tk_pq -> 0.19531643 | E67: =Thesis!$E$27/tk_pq -> 0.19531643 | F67: =Thesis!$F$27/tk_pq -> 0.225026 | G67: =Thesis!$G$27/tk_pq -> 0.20549828 | H67: =Thesis!$H$27/tk_pq -> 0.24691633 | I67: =Thesis!$I$27/tk_pq -> 0.26238391 | J67: =Thesis!$J$27/tk_pq -> 0.26960283 | K67: =Thesis!$K$27/tk_pq -> 0.27313065 | L67: =Thesis!$L$27/tk_pq -> 0.27478728 | M67: =Thesis!$M$27/tk_pq -> 0.27540205 | N67: =Thesis!$N$27/tk_pq -> 0.19531643 | O67: =Thesis!$O$27/tk_pq -> 0.19531643 | P67: 上限，不得作預測；只作檢查
A70: Thesis｜情境 B（基準）：命題模組 AWS AI＝對外 AI 在役 MW × 每 MW 年收入（Tokenomics 持有成本 × k）；AI 資本支出 → 折舊 → 分部營業利益
A71: 項目 | B71: 單位 | C71: FY2024A | D71: FY2025A | E71: 9M26A | F71: Q4 26E | G71: FY2026E（9M 實績＋Q4 模型） | H71: FY2027E | I71: FY2028E | J71: FY2029E | K71: FY2030E | L71: FY2031E | M71: FY2032E | N71: 9M25A | O71: Q4 25A | P71: 說明 | R71: 2023 | S71: 2024 | T71: 2025 | U71: 2026 | V71: 2027 | W71: 2028 | X71: 2029 | Y71: 2030 | Z71: 2031 | AA71: 2032
A72: 1. 容量（對外 AI 在役 MW-IT；期末）
A73: 對外 AI MW 每年新增（2030–2032 線性收斂到 FY2029 年底 MW × g，F5） | B73: MW/年 | H73: =(pace_B*pace_x) -> 3788.9 | I73: =(pace_B*pace_x) -> 3788.9 | J73: =(pace_B*pace_x) -> 3788.9 | K73: =(pace_B*pace_x)+(Thesis!$J$74*tg-(pace_B*pace_x))*1/3 -> 2679.3448 | L73: =(pace_B*pace_x)+(Thesis!$J$74*tg-(pace_B*pace_x))*2/3 -> 1569.7897 | M73: =(pace_B*pace_x)+(Thesis!$J$74*tg-(pace_B*pace_x))*3/3 -> 460.2345 | P73: 終值不落在建置高峰（共同修正 F5）
A74: 對外 AI 在役 MW（期末） | B74: MW | C74: =mw_ye24 -> 360 | D74: =mw_ye25 -> 1440 | E74: =mw_q3 -> 3027.225 | F74: =Thesis!$E$74+(pace_B*pace_x)*0.25 -> 3974.45 | G74: =Thesis!$F$74 -> 3974.45 | H74: =Thesis!$G$74+Thesis!$H$73 -> 7763.35 | I74: =Thesis!$H$74+Thesis!$I$73 -> 11552.25 | J74: =Thesis!$I$74+Thesis!$J$73 -> 15341.15 | K74: =Thesis!$J$74+Thesis!$K$73 -> 18020.495 | L74: =Thesis!$K$74+Thesis!$L$73 -> 19590.285 | M74: =Thesis!$L$74+Thesis!$M$73 -> 20050.519 | N74: =mw_ye24+(mw_ye25-mw_ye24)*0.75 -> 1170 | O74: =mw_ye25 -> 1440 | P74: 評價日 2026-09-30＝In 頁 mw_q3（6/30 機隊＋C10 速度一季）；之後每年新增＝In 頁 pace（情境）× pace_x；歷史年底值只用於分拆與折舊年份
A75: 對外 AI 平均在役 MW（期間） | B75: MW | C75: =(mw_ye23+mw_ye24)/2 -> 240 | D75: =(Thesis!$C$74+Thesis!$D$74)/2 -> 900 | E75: =(Thesis!$D$74+Thesis!$E$74)/2 -> 2233.6125 | F75: =(Thesis!$E$74+Thesis!$F$74)/2 -> 3500.8375 | G75: =Thesis!$E$75*0.75+Thesis!$F$75*0.25 -> 2550.4187 | H75: =(Thesis!$G$74+Thesis!$H$74)/2 -> 5868.9 | I75: =(Thesis!$H$74+Thesis!$I$74)/2 -> 9657.8 | J75: =(Thesis!$I$74+Thesis!$J$74)/2 -> 13446.7 | K75: =(Thesis!$J$74+Thesis!$K$74)/2 -> 16680.822 | L75: =(Thesis!$K$74+Thesis!$L$74)/2 -> 18805.39 | M75: =(Thesis!$L$74+Thesis!$M$74)/2 -> 19820.402 | N75: =(Thesis!$C$74+Thesis!$N$74)/2 -> 765 | O75: =(Thesis!$N$74+Thesis!$O$74)/2 -> 1305
A76: 期間長度 | B76: 年 | C76: 1 | D76: 1 | E76: 0.75 | F76: 0.25 | G76: 1 | H76: 1 | I76: 1 | J76: 1 | K76: 1 | L76: 1 | M76: 1 | N76: 0.75 | O76: 0.25
A77: 新增對外 AI MW | B77: MW | C77: =Thesis!$C$74-mw_ye23 -> 240 | D77: =Thesis!$D$74-Thesis!$C$74 -> 1080 | E77: =Thesis!$E$74-Thesis!$D$74 -> 1587.225 | F77: =Thesis!$F$74-Thesis!$E$74 -> 947.225 | G77: =Thesis!$E$77+Thesis!$F$77 -> 2534.45 | H77: =Thesis!$H$74-Thesis!$G$74 -> 3788.9 | I77: =Thesis!$I$74-Thesis!$H$74 -> 3788.9 | J77: =Thesis!$J$74-Thesis!$I$74 -> 3788.9 | K77: =Thesis!$K$74-Thesis!$J$74 -> 2679.3448 | L77: =Thesis!$L$74-Thesis!$K$74 -> 1569.7897 | M77: =Thesis!$M$74-Thesis!$L$74 -> 460.2345 | N77: =Thesis!$N$74-Thesis!$C$74 -> 810 | O77: =Thesis!$O$74-Thesis!$N$74 -> 270
A78: 新增 AI 總 MW（含自用＝對外 ÷ 對外比例） | B78: MW | C78: =Thesis!$C$77/ext_sh -> 300 | D78: =Thesis!$D$77/ext_sh -> 1350 | E78: =Thesis!$E$77/ext_sh -> 1984.0312 | F78: =Thesis!$F$77/ext_sh -> 1184.0312 | G78: =Thesis!$G$77/ext_sh -> 3168.0625 | H78: =Thesis!$H$77/ext_sh -> 4736.125 | I78: =Thesis!$I$77/ext_sh -> 4736.125 | J78: =Thesis!$J$77/ext_sh -> 4736.125 | K78: =Thesis!$K$77/ext_sh -> 3349.181 | L78: =Thesis!$L$77/ext_sh -> 1962.2371 | M78: =Thesis!$M$77/ext_sh -> 575.29312 | N78: =Thesis!$N$77/ext_sh -> 1012.5 | O78: =Thesis!$O$77/ext_sh -> 337.5 | P78: R–AA 欄：依年份（折舊與汰換用） | R78: =mw_ye23/ext_sh -> 150 | S78: =Thesis!$C$78 -> 300 | T78: =Thesis!$D$78 -> 1350 | U78: =Thesis!$G$78 -> 3168.0625 | V78: =Thesis!$H$78 -> 4736.125 | W78: =Thesis!$I$78 -> 4736.125 | X78: =Thesis!$J$78 -> 4736.125 | Y78: =Thesis!$K$78 -> 3349.181 | Z78: =Thesis!$L$78 -> 1962.2371 | AA78: =Thesis!$M$78 -> 575.29312
A79: 2. 新增產能的世代與單位經濟（Tokenomics v21.7 基準成本；自研晶片＝GB300 錨 × IF_NonNV_Hold_Trn，v0.3.1）
A80: NVIDIA 新增中 VR200 比例 | B80: % | F80: =na_vr26 -> 0 | G80: =na_vr26 -> 0 | H80: =na_vr27 -> 0.5 | I80: =na_vr28 -> 1 | J80: =na_vr28 -> 1 | K80: =na_vr28 -> 1 | L80: =na_vr28 -> 1 | M80: =na_vr28 -> 1
A81: 新增 MW 加權 IF_HoldEcon（含自研晶片係數） | B81: US$m/MW-年 | F81: =cust_sh*tk_he_gb300*cf_chip+(1-cust_sh)*((1-Thesis!$F$80)*tk_he_gb300+Thesis!$F$80*tk_he_vr200) -> 8.7635609 | G81: =cust_sh*tk_he_gb300*cf_chip+(1-cust_sh)*((1-Thesis!$G$80)*tk_he_gb300+Thesis!$G$80*tk_he_vr200) -> 8.7635609 | H81: =cust_sh*tk_he_gb300*cf_chip+(1-cust_sh)*((1-Thesis!$H$80)*tk_he_gb300+Thesis!$H$80*tk_he_vr200) -> 9.0983259 | I81: =cust_sh*tk_he_gb300*cf_chip+(1-cust_sh)*((1-Thesis!$I$80)*tk_he_gb300+Thesis!$I$80*tk_he_vr200) -> 9.4330909 | J81: =cust_sh*tk_he_gb300*cf_chip+(1-cust_sh)*((1-Thesis!$J$80)*tk_he_gb300+Thesis!$J$80*tk_he_vr200) -> 9.4330909 | K81: =cust_sh*tk_he_gb300*cf_chip+(1-cust_sh)*((1-Thesis!$K$80)*tk_he_gb300+Thesis!$K$80*tk_he_vr200) -> 9.4330909 | L81: =cust_sh*tk_he_gb300*cf_chip+(1-cust_sh)*((1-Thesis!$L$80)*tk_he_gb300+Thesis!$L$80*tk_he_vr200) -> 9.4330909 | M81: =cust_sh*tk_he_gb300*cf_chip+(1-cust_sh)*((1-Thesis!$M$80)*tk_he_gb300+Thesis!$M$80*tk_he_vr200) -> 9.4330909
A82: 新增 MW 加權營運費用（IF_OpexGW） | B82: US$m/MW-年 | F82: =cust_sh*tk_ox_gb300+(1-cust_sh)*((1-Thesis!$F$80)*tk_ox_gb300+Thesis!$F$80*tk_ox_vr200) -> 1.9826348 | G82: =cust_sh*tk_ox_gb300+(1-cust_sh)*((1-Thesis!$G$80)*tk_ox_gb300+Thesis!$G$80*tk_ox_vr200) -> 1.9826348 | H82: =cust_sh*tk_ox_gb300+(1-cust_sh)*((1-Thesis!$H$80)*tk_ox_gb300+Thesis!$H$80*tk_ox_vr200) -> 2.01035 | I82: =cust_sh*tk_ox_gb300+(1-cust_sh)*((1-Thesis!$I$80)*tk_ox_gb300+Thesis!$I$80*tk_ox_vr200) -> 2.0380652 | J82: =cust_sh*tk_ox_gb300+(1-cust_sh)*((1-Thesis!$J$80)*tk_ox_gb300+Thesis!$J$80*tk_ox_vr200) -> 2.0380652 | K82: =cust_sh*tk_ox_gb300+(1-cust_sh)*((1-Thesis!$K$80)*tk_ox_gb300+Thesis!$K$80*tk_ox_vr200) -> 2.0380652 | L82: =cust_sh*tk_ox_gb300+(1-cust_sh)*((1-Thesis!$L$80)*tk_ox_gb300+Thesis!$L$80*tk_ox_vr200) -> 2.0380652 | M82: =cust_sh*tk_ox_gb300+(1-cust_sh)*((1-Thesis!$M$80)*tk_ox_gb300+Thesis!$M$80*tk_ox_vr200) -> 2.0380652
A83: 新增 MW 加權 IT 資本支出（IF_CapexIT；含自研晶片資本支出係數） | B83: US$m/MW | F83: =cust_sh*tk_cx_gb300*cf_cx+(1-cust_sh)*((1-Thesis!$F$80)*tk_cx_gb300+Thesis!$F$80*tk_cx_vr200) -> 25.950965 | G83: =cust_sh*tk_cx_gb300*cf_cx+(1-cust_sh)*((1-Thesis!$G$80)*tk_cx_gb300+Thesis!$G$80*tk_cx_vr200) -> 25.950965 | H83: =cust_sh*tk_cx_gb300*cf_cx+(1-cust_sh)*((1-Thesis!$H$80)*tk_cx_gb300+Thesis!$H$80*tk_cx_vr200) -> 27.288247 | I83: =cust_sh*tk_cx_gb300*cf_cx+(1-cust_sh)*((1-Thesis!$I$80)*tk_cx_gb300+Thesis!$I$80*tk_cx_vr200) -> 28.625529 | J83: =cust_sh*tk_cx_gb300*cf_cx+(1-cust_sh)*((1-Thesis!$J$80)*tk_cx_gb300+Thesis!$J$80*tk_cx_vr200) -> 28.625529 | K83: =cust_sh*tk_cx_gb300*cf_cx+(1-cust_sh)*((1-Thesis!$K$80)*tk_cx_gb300+Thesis!$K$80*tk_cx_vr200) -> 28.625529 | L83: =cust_sh*tk_cx_gb300*cf_cx+(1-cust_sh)*((1-Thesis!$L$80)*tk_cx_gb300+Thesis!$L$80*tk_cx_vr200) -> 28.625529 | M83: =cust_sh*tk_cx_gb300*cf_cx+(1-cust_sh)*((1-Thesis!$M$80)*tk_cx_gb300+Thesis!$M$80*tk_cx_vr200) -> 28.625529
A84: 期初後新增對外 MW 累計（期末） | B84: MW | E84: =Thesis!$E$74-mw_open -> 947.225 | F84: =Thesis!$F$74-mw_open -> 1894.45 | G84: =Thesis!$F$84 -> 1894.45 | H84: =Thesis!$H$74-mw_open -> 5683.35 | I84: =Thesis!$I$74-mw_open -> 9472.25 | J84: =Thesis!$J$74-mw_open -> 13261.15 | K84: =Thesis!$K$74-mw_open -> 15940.495 | L84: =Thesis!$L$74-mw_open -> 17510.285 | M84: =Thesis!$M$74-mw_open -> 17970.519
A85: Σ 新增 MW × HoldEcon | B85: US$m | E85: =Thesis!$E$84*Thesis!$F$81 -> 8301.0639 | F85: =Thesis!$E$85+Thesis!$F$77*Thesis!$F$81 -> 16602.128 | G85: =Thesis!$F$85 -> 16602.128 | H85: =Thesis!$G$85+Thesis!$H$77*Thesis!$H$81 -> 51074.775 | I85: =Thesis!$H$85+Thesis!$I$77*Thesis!$I$81 -> 86815.813 | J85: =Thesis!$I$85+Thesis!$J$77*Thesis!$J$81 -> 122556.85 | K85: =Thesis!$J$85+Thesis!$K$77*Thesis!$K$81 -> 147831.35 | L85: =Thesis!$K$85+Thesis!$L$77*Thesis!$L$81 -> 162639.32 | M85: =Thesis!$L$85+Thesis!$M$77*Thesis!$M$81 -> 166980.76
A86: Σ 新增 MW × 營運費用 | B86: US$m | E86: =Thesis!$E$84*Thesis!$F$82 -> 1878.0013 | F86: =Thesis!$E$86+Thesis!$F$77*Thesis!$F$82 -> 3756.0025 | G86: =Thesis!$F$86 -> 3756.0025 | H86: =Thesis!$G$86+Thesis!$H$77*Thesis!$H$82 -> 11373.018 | I86: =Thesis!$H$86+Thesis!$I$77*Thesis!$I$82 -> 19095.043 | J86: =Thesis!$I$86+Thesis!$J$77*Thesis!$J$82 -> 26817.068 | K86: =Thesis!$J$86+Thesis!$K$77*Thesis!$K$82 -> 32277.747 | L86: =Thesis!$K$86+Thesis!$L$77*Thesis!$L$82 -> 35477.081 | M86: =Thesis!$L$86+Thesis!$M$77*Thesis!$M$82 -> 36415.069
A87: 新增機隊加權 HoldEcon | B87: US$m/MW-年 | F87: =IF(Thesis!$F$84>0,Thesis!$F$85/Thesis!$F$84,Thesis!$F$81) -> 8.7635609 | G87: =IF(Thesis!$G$84>0,Thesis!$G$85/Thesis!$G$84,Thesis!$G$81) -> 8.7635609 | H87: =IF(Thesis!$H$84>0,Thesis!$H$85/Thesis!$H$84,Thesis!$H$81) -> 8.9867375 | I87: =IF(Thesis!$I$84>0,Thesis!$I$85/Thesis!$I$84,Thesis!$I$81) -> 9.1652789 | J87: =IF(Thesis!$J$84>0,Thesis!$J$85/Thesis!$J$84,Thesis!$J$81) -> 9.2417966 | K87: =IF(Thesis!$K$84>0,Thesis!$K$85/Thesis!$K$84,Thesis!$K$81) -> 9.2739501 | L87: =IF(Thesis!$L$84>0,Thesis!$L$85/Thesis!$L$84,Thesis!$L$81) -> 9.288217 | M87: =IF(Thesis!$M$84>0,Thesis!$M$85/Thesis!$M$84,Thesis!$M$81) -> 9.2919273
A88: 新增機隊加權營運費用 | B88: US$m/MW-年 | F88: =IF(Thesis!$F$84>0,Thesis!$F$86/Thesis!$F$84,Thesis!$F$82) -> 1.9826348 | G88: =IF(Thesis!$G$84>0,Thesis!$G$86/Thesis!$G$84,Thesis!$G$82) -> 1.9826348 | H88: =IF(Thesis!$H$84>0,Thesis!$H$86/Thesis!$H$84,Thesis!$H$82) -> 2.0011116 | I88: =IF(Thesis!$I$84>0,Thesis!$I$86/Thesis!$I$84,Thesis!$I$82) -> 2.015893 | J88: =IF(Thesis!$J$84>0,Thesis!$J$86/Thesis!$J$84,Thesis!$J$82) -> 2.0222279 | K88: =IF(Thesis!$K$84>0,Thesis!$K$86/Thesis!$K$84,Thesis!$K$82) -> 2.0248899 | L88: =IF(Thesis!$L$84>0,Thesis!$L$86/Thesis!$L$84,Thesis!$L$82) -> 2.0260711 | M88: =IF(Thesis!$M$84>0,Thesis!$M$86/Thesis!$M$84,Thesis!$M$82) -> 2.0263783
A89: 新增產能每 MW 年收入＝新增機隊 HoldEcon × 情境 k | B89: US$m/MW-年 | F89: =Thesis!$F$87*k_B -> 8.6930055 | G89: =Thesis!$G$87*k_B -> 8.6930055 | H89: =Thesis!$H$87*k_B -> 8.9143854 | I89: =Thesis!$I$87*k_B -> 9.0914893 | J89: =Thesis!$J$87*k_B -> 9.1673909 | K89: =Thesis!$K$87*k_B -> 9.1992856 | L89: =Thesis!$L$87*k_B -> 9.2134376 | M89: =Thesis!$M$87*k_B -> 9.2171181 | P89: 6/30 機隊 2,080 MW 三情境同用 rpm_open（k_B）；情境 k 用於 6/30 之後的新產能（含 Q3 新增）
A90: 新增產能平均在役 MW（期間） | B90: MW | F90: =(Thesis!$E$84+Thesis!$F$84)/2 -> 1420.8375 | H90: =(Thesis!$G$84+Thesis!$H$84)/2 -> 3788.9 | I90: =(Thesis!$H$84+Thesis!$I$84)/2 -> 7577.8 | J90: =(Thesis!$I$84+Thesis!$J$84)/2 -> 11366.7 | K90: =(Thesis!$J$84+Thesis!$K$84)/2 -> 14600.822 | L90: =(Thesis!$K$84+Thesis!$L$84)/2 -> 16725.39 | M90: =(Thesis!$L$84+Thesis!$M$84)/2 -> 17740.402
A91: 3. AWS AI 損益（收入端不乘 IF_Util：MW-year 計價）
A92: AWS AI 營收（命題子列） | B92: US$bn | C92: =Thesis!$C$75*rpm_open*Thesis!$C$76/1000 -> 2.3210054 | D92: =Thesis!$D$75*rpm_open*Thesis!$D$76/1000 -> 8.7037701 | E92: =Thesis!$E$75*rpm_open*Thesis!$E$76/1000 -> 16.200708 | F92: =(mw_open*rpm_open+Thesis!$F$90*Thesis!$F$89)*Thesis!$F$76/1000 -> 8.116682 | G92: =Thesis!$E$92+Thesis!$F$92 -> 24.31739 | H92: =(mw_open*rpm_open+Thesis!$H$90*Thesis!$H$89)/1000 -> 53.891094 | I92: =(mw_open*rpm_open+Thesis!$I$90*Thesis!$I$89)/1000 -> 89.008867 | J92: =(mw_open*rpm_open+Thesis!$J$90*Thesis!$J$89)/1000 -> 124.31836 | K92: =(mw_open*rpm_open+Thesis!$K$90*Thesis!$K$89)/1000 -> 154.43252 | L92: =(mw_open*rpm_open+Thesis!$L$90*Thesis!$L$89)/1000 -> 174.21371 | M92: =(mw_open*rpm_open+Thesis!$M$90*Thesis!$M$89)/1000 -> 183.63076 | N92: =Thesis!$N$75*rpm_open*Thesis!$N$76/1000 -> 5.5486534 | O92: =Thesis!$O$75*rpm_open*Thesis!$O$76/1000 -> 3.1551167 | P92: 實績欄為分拆估計（期初 k，Derived），不是公司揭露值
A93: 全機隊每 MW 年收入 | B93: US$m/MW-年 | C93: =Thesis!$C$92*1000/(Thesis!$C$75*Thesis!$C$76) -> 9.6708557 | D93: =Thesis!$D$92*1000/(Thesis!$D$75*Thesis!$D$76) -> 9.6708557 | E93: =Thesis!$E$92*1000/(Thesis!$E$75*Thesis!$E$76) -> 9.6708557 | F93: =Thesis!$F$92*1000/(Thesis!$F$75*Thesis!$F$76) -> 9.2739889 | G93: =Thesis!$G$92*1000/(Thesis!$G$75*Thesis!$G$76) -> 9.5346656 | H93: =Thesis!$H$92*1000/(Thesis!$H$75*Thesis!$H$76) -> 9.1824864 | I93: =Thesis!$I$92*1000/(Thesis!$I$75*Thesis!$I$76) -> 9.2162674 | J93: =Thesis!$J$92*1000/(Thesis!$J$75*Thesis!$J$76) -> 9.2452693 | K93: =Thesis!$K$92*1000/(Thesis!$K$75*Thesis!$K$76) -> 9.2580876 | L93: =Thesis!$L$92*1000/(Thesis!$L$75*Thesis!$L$76) -> 9.2640311 | M93: =Thesis!$M$92*1000/(Thesis!$M$75*Thesis!$M$76) -> 9.2647344 | N93: =Thesis!$N$92*1000/(Thesis!$N$75*Thesis!$N$76) -> 9.6708557 | O93: =Thesis!$O$92*1000/(Thesis!$O$75*Thesis!$O$76) -> 9.6708557
A94: AI 營運成本（含自用 MW、租用機房租金 C22） | B94: US$bn | C94: =Thesis!$C$75/ext_sh*(ox_open+rent_mw)*Thesis!$C$76/1000 -> 0.64256921 | D94: =Thesis!$D$75/ext_sh*(ox_open+rent_mw)*Thesis!$D$76/1000 -> 2.4096345 | E94: =Thesis!$E$75/ext_sh*(ox_open+rent_mw)*Thesis!$E$76/1000 -> 4.4851582 | F94: =((mw_open*ox_open+Thesis!$F$90*Thesis!$F$88)/ext_sh+Thesis!$F$75/ext_sh*rent_mw)*Thesis!$F$76/1000 -> 2.385059 | G94: =Thesis!$E$94+Thesis!$F$94 -> 6.8702171 | H94: =((mw_open*ox_open+Thesis!$H$90*Thesis!$H$88)/ext_sh+Thesis!$H$75/ext_sh*rent_mw)*Thesis!$H$76/1000 -> 16.246582 | I94: =((mw_open*ox_open+Thesis!$I$90*Thesis!$I$88)/ext_sh+Thesis!$I$75/ext_sh*rent_mw)*Thesis!$I$76/1000 -> 27.064244 | J94: =((mw_open*ox_open+Thesis!$J$90*Thesis!$J$88)/ext_sh+Thesis!$J$75/ext_sh*rent_mw)*Thesis!$J$76/1000 -> 37.901908 | K94: =((mw_open*ox_open+Thesis!$K$90*Thesis!$K$88)/ext_sh+Thesis!$K$75/ext_sh*rent_mw)*Thesis!$K$76/1000 -> 47.150066 | L94: =((mw_open*ox_open+Thesis!$L$90*Thesis!$L$88)/ext_sh+Thesis!$L$75/ext_sh*rent_mw)*Thesis!$L$76/1000 -> 53.225236 | M94: =((mw_open*ox_open+Thesis!$M$90*Thesis!$M$88)/ext_sh+Thesis!$M$75/ext_sh*rent_mw)*Thesis!$M$76/1000 -> 56.124161 | N94: =Thesis!$N$75/ext_sh*(ox_open+rent_mw)*Thesis!$N$76/1000 -> 1.536142 | O94: =Thesis!$O$75/ext_sh*(ox_open+rent_mw)*Thesis!$O$76/1000 -> 0.87349252
A95: AWS 營收（實績，Q 頁） | B95: US$bn | C95: =Q!$D$7 -> 107.556 | D95: =Q!$E$7 -> 128.725 | E95: =Q!$O$7 -> 125.803 | N95: =Q!$N$7 -> 93.146 | O95: =Q!$J$7 -> 35.579
A96: AWS 其他營收（非 AI 雲端） | B96: US$bn | C96: =Thesis!$C$95-Thesis!$C$92 -> 105.23499 | D96: =Thesis!$D$95-Thesis!$D$92 -> 120.02123 | E96: =Thesis!$E$95-Thesis!$E$92 -> 109.60229 | F96: =Thesis!$O$96*(1+Thesis!$F$97) -> 36.97966 | G96: =Thesis!$E$96+Thesis!$F$96 -> 146.58195 | H96: =Thesis!$G$96*(1+Thesis!$H$97) -> 164.96042 | I96: =Thesis!$H$96*(1+Thesis!$I$97) -> 183.14786 | J96: =Thesis!$I$96*(1+Thesis!$J$97) -> 200.57012 | K96: =Thesis!$J$96*(1+Thesis!$K$97) -> 216.61573 | L96: =Thesis!$K$96*(1+Thesis!$L$97) -> 233.94498 | M96: =Thesis!$L$96*(1+Thesis!$M$97) -> 252.66058 | N96: =Thesis!$N$95-Thesis!$N$92 -> 87.597347 | O96: =Thesis!$O$95-Thesis!$O$92 -> 32.423883 | P96: 實績＝AWS 實績 − AWS AI 分拆估計（殘差，Derived）
A97: AWS 其他年增 | B97: % | D97: =Thesis!$D$96/Thesis!$C$96-1 -> 0.14050683 | E97: =Thesis!$E$96/Thesis!$N$96-1 -> 0.25120562 | F97: =IF(awso_g0=1,Thesis!$E$97,Thesis!$D$97) -> 0.14050683 | G97: =Thesis!$G$96/Thesis!$D$96-1 -> 0.2213002 | H97: =Thesis!$F$97+(g_awso_lt-Thesis!$F$97)*1/4 -> 0.12538012 | I97: =Thesis!$F$97+(g_awso_lt-Thesis!$F$97)*2/4 -> 0.11025341 | J97: =Thesis!$F$97+(g_awso_lt-Thesis!$F$97)*3/4 -> 0.095126707 | K97: =Thesis!$F$97+(g_awso_lt-Thesis!$F$97)*4/4 -> 0.08 | L97: =g_awso_lt -> 0.08 | M97: =g_awso_lt -> 0.08 | P97: 起點＝FY2025 年增（D 欄，Derived；In 頁 awso_g0＝0）；9M26 年增（E 欄）受 AI 分拆低估影響偏高，只列不用（awso_g0＝1 時改用，Sens）；收斂到 g_awso_lt
A98: 4. AI 資本支出（現金）→ 折舊（IT 6 年、機房 20 年；次年起提列）
A99: Q4 26 非 AI 資本支出（零售＋AWS 其他） | B99: US$bn | F99: =cx_rt*Seg!$F$55+cx_awso*Thesis!$F$96 -> 19.116381
A100: AI 資本支出中 IT 比例 | B100: % | C100: =tk_cx_h100/(tk_cx_h100+tk_fac*(1-colo_sh)) -> 0.73075646 | D100: =tk_cx_h100/(tk_cx_h100+tk_fac*(1-colo_sh)) -> 0.73075646 | E100: =Thesis!$F$100 -> 0.71912296 | F100: =Thesis!$F$83/(Thesis!$F$83+tk_fac*(1-colo_sh)) -> 0.71912296 | G100: =Thesis!$G$83/(Thesis!$G$83+tk_fac*(1-colo_sh)) -> 0.71912296 | H100: =Thesis!$H$83/(Thesis!$H$83+tk_fac*(1-colo_sh)) -> 0.72915955 | I100: =Thesis!$I$83/(Thesis!$I$83+tk_fac*(1-colo_sh)) -> 0.73850361 | J100: =Thesis!$J$83/(Thesis!$J$83+tk_fac*(1-colo_sh)) -> 0.73850361 | K100: =Thesis!$K$83/(Thesis!$K$83+tk_fac*(1-colo_sh)) -> 0.73850361 | L100: =Thesis!$L$83/(Thesis!$L$83+tk_fac*(1-colo_sh)) -> 0.73850361 | M100: =Thesis!$M$83/(Thesis!$M$83+tk_fac*(1-colo_sh)) -> 0.73850361
A101: AI 資本支出（現金，含自用） | B101: US$bn | C101: =Q!$D$48-cx_rt*Q!$D$16-cx_awso*Thesis!$C$96 -> 25.278105 | D101: =Q!$E$48-cx_rt*Q!$E$16-cx_awso*Thesis!$D$96 -> 69.568632 | E101: =Q!$O$48-cx_rt*Q!$O$16-cx_awso*Thesis!$E$96 -> 123.19605 | F101: =capex_g26-Q!$O$48-Thesis!$F$99 -> 28.695619 | G101: =Thesis!$E$101+Thesis!$F$101 -> 151.89167 | H101: =Thesis!$H$78*(Thesis!$H$83+tk_fac*(1-colo_sh))/1000+Thesis!$H$105 -> 177.24591 | I101: =Thesis!$I$78*(Thesis!$I$83+tk_fac*(1-colo_sh))/1000+Thesis!$I$105 -> 183.57945 | J101: =Thesis!$J$78*(Thesis!$J$83+tk_fac*(1-colo_sh))/1000+Thesis!$J$105 -> 187.87328 | K101: =Thesis!$K$78*(Thesis!$K$83+tk_fac*(1-colo_sh))/1000+Thesis!$K$105 -> 138.40704 | L101: =Thesis!$L$78*(Thesis!$L$83+tk_fac*(1-colo_sh))/1000+Thesis!$L$105 -> 114.70377 | M101: =Thesis!$M$78*(Thesis!$M$83+tk_fac*(1-colo_sh))/1000+Thesis!$M$105 -> 112.98671 | P101: 實績＝公司資本支出淨額 − 非 AI（零售 cx_rt、AWS 其他 cx_awso）；Q4 26＝指引 220 − 9M 實績 − 非 AI（修正三：FY2026 現金資本支出錨定指引；Q4 新增 MW 部分由已投入的在建資本支出支應）；之後＝新增 MW ×（IT＋自建機房）＋汰換 | R101: =Q!$C$48-cx_rt*Q!$C$16-cx_awso*(Q!$C$7-mw_ye23/2*rpm_open/1000) -> 1.5042998 | S101: =Thesis!$C$101 -> 25.278105 | T101: =Thesis!$D$101 -> 69.568632 | U101: =Thesis!$G$101 -> 151.89167 | V101: =Thesis!$H$101 -> 177.24591 | W101: =Thesis!$I$101 -> 183.57945 | X101: =Thesis!$J$101 -> 187.87328 | Y101: =Thesis!$K$101 -> 138.40704 | Z101: =Thesis!$L$101 -> 114.70377 | AA101: =Thesis!$M$101 -> 112.98671
A102: C10：Q4 26 AI 資本支出公式值＝新增總 MW ×（IT＋自建機房） | B102: US$bn | F102: =Thesis!$F$78*(Thesis!$F$83+tk_fac*(1-colo_sh))/1000 -> 42.728095
A103: C10 對帳（下半年視窗）：（指引 − 上半年實績）÷ 2 −（Q4 公式 AI＋Q4 非 AI） | B103: US$bn | F103: =(capex_g26-Q!$P$48)/2-(Thesis!$F$102+Thesis!$F$99) -> 0.00052462662 | P103: 情境 B 以 calib_pace_v031.py 解 pace_B 使本列＝0；A／C 情境速度不同，本列不為 0
...

Sheet Seg
A1: Seg — 營收分部層：官方分部 North America、International、AWS；10-K 營收線 Online stores、Physical stores、Third-party seller services、Advertising services、Subscription services、Other（零售各線合計＝北美＋國際）與 AWS。AWS＝AWS AI（命題子列，Thesis）＋AWS 其他。核對列（綠底）每情境每年度皆須為 0
A4: Seg｜情境 A（樂觀）：營收分部層（官方分部 North America、International、AWS；10-K 營收線）
A5: 項目 | B5: 單位 | C5: FY2024A | D5: FY2025A | E5: 9M26A | F5: Q4 26E | G5: FY2026E（9M 實績＋Q4 模型） | H5: FY2027E | I5: FY2028E | J5: FY2029E | K5: FY2030E | L5: FY2031E | M5: FY2032E | N5: 9M25A | O5: Q4 25A | P5: 說明 | R5: 2023 | S5: 2024 | T5: 2025 | U5: 2026 | V5: 2027 | W5: 2028 | X5: 2029 | Y5: 2030 | Z5: 2031 | AA5: 2032
A6: 1. 零售各營收線（Q4 26＝Q4 25 ×（1＋9M26 年增）× 校準係數；2027–2030 年增由 9M26 年增線性收斂到長期值；2031–2032＝長期值）
A7: Online stores | B7: US$bn | C7: =Q!$D$10 -> 247.029 | D7: =Q!$E$10 -> 269.287 | E7: =Q!$O$10 -> 203.156 | F7: =Seg!$O$7*(1+Seg!$F$8)*Seg!$F$19 -> 90.388464 | G7: =Seg!$E$7+Seg!$F$7 -> 293.54446 | H7: =Seg!$G$7*(1+Seg!$H$8) -> 317.13448 | I7: =Seg!$H$7*(1+Seg!$I$8) -> 339.41058 | J7: =Seg!$I$7*(1+Seg!$J$8) -> 359.81625 | K7: =Seg!$J$7*(1+Seg!$K$8) -> 377.80706 | L7: =Seg!$K$7*(1+Seg!$L$8) -> 396.69741 | M7: =Seg!$L$7*(1+Seg!$M$8) -> 416.53228 | N7: =Q!$N$10 -> 186.299 | O7: =Q!$J$10 -> 82.988 | P7: Q 頁實績；預測＝前期 ×（1＋年增）
A8: Online stores 年增 | B8: % | E8: =Seg!$E$7/Seg!$N$7-1 -> 0.090483577 | F8: =Seg!$E$8 -> 0.090483577 | G8: =Seg!$G$7/Seg!$D$7-1 -> 0.090080337 | H8: =Seg!$F$8+(g_os-Seg!$F$8)*1/4 -> 0.080362683 | I8: =Seg!$F$8+(g_os-Seg!$F$8)*2/4 -> 0.070241789 | J8: =Seg!$F$8+(g_os-Seg!$F$8)*3/4 -> 0.060120894 | K8: =Seg!$F$8+(g_os-Seg!$F$8)*4/4 -> 0.05 | L8: =g_os -> 0.05 | M8: =g_os -> 0.05 | P8: E＝9M26 對 9M25（Prime Day 移入 Q2 的時點影響在九個月內抵銷）；F＝Q4 26 成長基準＝E（Derived）；收斂到 In 頁 g_os
A9: Physical stores | B9: US$bn | C9: =Q!$D$11 -> 21.215 | D9: =Q!$E$11 -> 22.561 | E9: =Q!$O$11 -> 17.289 | F9: =Seg!$O$9*(1+Seg!$F$10)*Seg!$F$19 -> 6.0520551 | G9: =Seg!$E$9+Seg!$F$9 -> 23.341055 | H9: =Seg!$G$9*(1+Seg!$H$10) -> 24.127024 | I9: =Seg!$H$9*(1+Seg!$I$10) -> 24.909917 | J9: =Seg!$I$9*(1+Seg!$J$10) -> 25.687715 | K9: =Seg!$J$9*(1+Seg!$K$10) -> 26.458346 | L9: =Seg!$K$9*(1+Seg!$L$10) -> 27.252097 | M9: =Seg!$L$9*(1+Seg!$M$10) -> 28.06966 | N9: =Q!$N$11 -> 16.706 | O9: =Q!$J$11 -> 5.855 | P9: Q 頁實績；預測＝前期 ×（1＋年增）
A10: Physical stores 年增 | B10: % | E10: =Seg!$E$9/Seg!$N$9-1 -> 0.034897642 | F10: =Seg!$E$10 -> 0.034897642 | G10: =Seg!$G$9/Seg!$D$9-1 -> 0.034575378 | H10: =Seg!$F$10+(g_ps-Seg!$F$10)*1/4 -> 0.033673231 | I10: =Seg!$F$10+(g_ps-Seg!$F$10)*2/4 -> 0.032448821 | J10: =Seg!$F$10+(g_ps-Seg!$F$10)*3/4 -> 0.03122441 | K10: =Seg!$F$10+(g_ps-Seg!$F$10)*4/4 -> 0.03 | L10: =g_ps -> 0.03 | M10: =g_ps -> 0.03 | P10: E＝9M26 對 9M25（Prime Day 移入 Q2 的時點影響在九個月內抵銷）；F＝Q4 26 成長基準＝E（Derived）；收斂到 In 頁 g_ps
A11: Third-party seller services | B11: US$bn | C11: =Q!$D$12 -> 156.146 | D11: =Q!$E$12 -> 172.162 | E11: =Q!$O$12 -> 134.85 | F11: =Seg!$O$11*(1+Seg!$F$12)*Seg!$F$19 -> 59.605614 | G11: =Seg!$E$11+Seg!$F$11 -> 194.45561 | H11: =Seg!$G$11*(1+Seg!$H$12) -> 216.80459 | I11: =Seg!$H$11*(1+Seg!$I$12) -> 238.47508 | J11: =Seg!$I$11*(1+Seg!$J$12) -> 258.73997 | K11: =Seg!$J$11*(1+Seg!$K$12) -> 276.85177 | L11: =Seg!$K$11*(1+Seg!$L$12) -> 296.2314 | M11: =Seg!$L$11*(1+Seg!$M$12) -> 316.9676 | N11: =Q!$N$12 -> 119.346 | O11: =Q!$J$12 -> 52.816 | P11: Q 頁實績；預測＝前期 ×（1＋年增）
A12: Third-party seller services 年增 | B12: % | E12: =Seg!$E$11/Seg!$N$11-1 -> 0.129908 | F12: =Seg!$E$12 -> 0.129908 | G12: =Seg!$G$11/Seg!$D$11-1 -> 0.12949207 | H12: =Seg!$F$12+(g_sp-Seg!$F$12)*1/4 -> 0.114931 | I12: =Seg!$F$12+(g_sp-Seg!$F$12)*2/4 -> 0.099953999 | J12: =Seg!$F$12+(g_sp-Seg!$F$12)*3/4 -> 0.084977 | K12: =Seg!$F$12+(g_sp-Seg!$F$12)*4/4 -> 0.07 | L12: =g_sp -> 0.07 | M12: =g_sp -> 0.07 | P12: E＝9M26 對 9M25（Prime Day 移入 Q2 的時點影響在九個月內抵銷）；F＝Q4 26 成長基準＝E（Derived）；收斂到 In 頁 g_sp
A13: Advertising services | B13: US$bn | C13: =Q!$D$13 -> 56.214 | D13: =Q!$E$13 -> 68.635 | E13: =Q!$O$13 -> 56.689 | F13: =Seg!$O$13*(1+Seg!$F$14)*Seg!$F$19 -> 25.508039 | G13: =Seg!$E$13+Seg!$F$13 -> 82.197039 | H13: =Seg!$G$13*(1+Seg!$H$14) -> 96.460878 | I13: =Seg!$H$13*(1+Seg!$I$14) -> 110.83562 | J13: =Seg!$I$13*(1+Seg!$J$14) -> 124.63585 | K13: =Seg!$J$13*(1+Seg!$K$14) -> 137.09944 | L13: =Seg!$K$13*(1+Seg!$L$14) -> 150.80938 | M13: =Seg!$L$13*(1+Seg!$M$14) -> 165.89032 | N13: =Q!$N$13 -> 47.318 | O13: =Q!$J$13 -> 21.317 | P13: Q 頁實績；預測＝前期 ×（1＋年增）
A14: Advertising services 年增 | B14: % | E14: =Seg!$E$13/Seg!$N$13-1 -> 0.19804303 | F14: =Seg!$E$14 -> 0.19804303 | G14: =Seg!$G$13/Seg!$D$13-1 -> 0.19759655 | H14: =Seg!$F$14+(g_ad-Seg!$F$14)*1/4 -> 0.17353227 | I14: =Seg!$F$14+(g_ad-Seg!$F$14)*2/4 -> 0.14902151 | J14: =Seg!$F$14+(g_ad-Seg!$F$14)*3/4 -> 0.12451076 | K14: =Seg!$F$14+(g_ad-Seg!$F$14)*4/4 -> 0.1 | L14: =g_ad -> 0.1 | M14: =g_ad -> 0.1 | P14: E＝9M26 對 9M25（Prime Day 移入 Q2 的時點影響在九個月內抵銷）；F＝Q4 26 成長基準＝E（Derived）；收斂到 In 頁 g_ad
A15: Subscription services | B15: US$bn | C15: =Q!$D$14 -> 44.374 | D15: =Q!$E$14 -> 49.619 | E15: =Q!$O$14 -> 41.163 | F15: =Seg!$O$15*(1+Seg!$F$16)*Seg!$F$19 -> 14.781839 | G15: =Seg!$E$15+Seg!$F$15 -> 55.944839 | H15: =Seg!$G$15*(1+Seg!$H$16) -> 62.288122 | I15: =Seg!$H$15*(1+Seg!$I$16) -> 68.449853 | J15: =Seg!$I$15*(1+Seg!$J$16) -> 74.231233 | K15: =Seg!$J$15*(1+Seg!$K$16) -> 79.427419 | L15: =Seg!$K$15*(1+Seg!$L$16) -> 84.987338 | M15: =Seg!$L$15*(1+Seg!$M$16) -> 90.936452 | N15: =Q!$N$14 -> 36.497 | O15: =Q!$J$14 -> 13.122 | P15: Q 頁實績；預測＝前期 ×（1＋年增）
A16: Subscription services 年增 | B16: % | E16: =Seg!$E$15/Seg!$N$15-1 -> 0.12784612 | F16: =Seg!$E$16 -> 0.12784612 | G16: =Seg!$G$15/Seg!$D$15-1 -> 0.12748824 | H16: =Seg!$F$16+(g_sub-Seg!$F$16)*1/4 -> 0.11338459 | I16: =Seg!$F$16+(g_sub-Seg!$F$16)*2/4 -> 0.098923062 | J16: =Seg!$F$16+(g_sub-Seg!$F$16)*3/4 -> 0.084461531 | K16: =Seg!$F$16+(g_sub-Seg!$F$16)*4/4 -> 0.07 | L16: =g_sub -> 0.07 | M16: =g_sub -> 0.07 | P16: E＝9M26 對 9M25（Prime Day 移入 Q2 的時點影響在九個月內抵銷）；F＝Q4 26 成長基準＝E（Derived）；收斂到 In 頁 g_sub
A17: Other | B17: US$bn | C17: =Q!$D$15 -> 5.425 | D17: =Q!$E$15 -> 5.935 | E17: =Q!$O$15 -> 5.119 | F17: =Seg!$O$17*(1+Seg!$F$18)*Seg!$F$19 -> 2.0676464 | G17: =Seg!$E$17+Seg!$F$17 -> 7.1866464 | H17: =Seg!$G$17*(1+Seg!$H$18) -> 8.4154422 | I17: =Seg!$H$17*(1+Seg!$I$18) -> 9.5149658 | J17: =Seg!$I$17*(1+Seg!$J$18) -> 10.374431 | K17: =Seg!$J$17*(1+Seg!$K$18) -> 10.893153 | L17: =Seg!$K$17*(1+Seg!$L$18) -> 11.43781 | M17: =Seg!$L$17*(1+Seg!$M$18) -> 12.009701 | N17: =Q!$N$15 -> 4.226 | O17: =Q!$J$15 -> 1.709 | P17: Q 頁實績；預測＝前期 ×（1＋年增）
A18: Other 年增 | B18: % | E18: =Seg!$E$17/Seg!$N$17-1 -> 0.21131093 | F18: =Seg!$E$18 -> 0.21131093 | G18: =Seg!$G$17/Seg!$D$17-1 -> 0.21089241 | H18: =Seg!$F$18+(g_ot-Seg!$F$18)*1/4 -> 0.1709832 | I18: =Seg!$F$18+(g_ot-Seg!$F$18)*2/4 -> 0.13065547 | J18: =Seg!$F$18+(g_ot-Seg!$F$18)*3/4 -> 0.090327733 | K18: =Seg!$F$18+(g_ot-Seg!$F$18)*4/4 -> 0.05 | L18: =g_ot -> 0.05 | M18: =g_ot -> 0.05 | P18: E＝9M26 對 9M25（Prime Day 移入 Q2 的時點影響在九個月內抵銷）；F＝Q4 26 成長基準＝E（Derived）；收斂到 In 頁 g_ot
A19: Q4 26 零售營收校準係數（使情境 B 的 Q4 26 合併營收＝指引中點） | B19: x | F19: =(g26q4_mid-Thesis!$F$92-Thesis!$F$96)/(Seg!$O$7*(1+Seg!$F$8)+Seg!$O$9*(1+Seg!$F$10)+Seg!$O$11*(1+Seg!$F$12)+Seg!$O$13*(1+Seg!$F$14)+Seg!$O$15*(1+Seg!$F$16)+Seg!$O$17*(1+Seg!$F$18)) -> 0.9988001 | P19: Q4 26 合併營收目標＝指引中點 243.5 − 主頁情境 B 的 AWS Q4 26；三情境共用同一係數（修正二），零售不隨 AI 分拆變動
A20: 零售營收線合計（＝North America＋International） | B20: US$bn | C20: =Seg!$C$7+Seg!$C$9+Seg!$C$11+Seg!$C$13+Seg!$C$15+Seg!$C$17 -> 530.403 | D20: =Seg!$D$7+Seg!$D$9+Seg!$D$11+Seg!$D$13+Seg!$D$15+Seg!$D$17 -> 588.199 | E20: =Seg!$E$7+Seg!$E$9+Seg!$E$11+Seg!$E$13+Seg!$E$15+Seg!$E$17 -> 458.266 | F20: =Seg!$F$7+Seg!$F$9+Seg!$F$11+Seg!$F$13+Seg!$F$15+Seg!$F$17 -> 198.40366 | G20: =Seg!$G$7+Seg!$G$9+Seg!$G$11+Seg!$G$13+Seg!$G$15+Seg!$G$17 -> 656.66966 | H20: =Seg!$H$7+Seg!$H$9+Seg!$H$11+Seg!$H$13+Seg!$H$15+Seg!$H$17 -> 725.23054 | I20: =Seg!$I$7+Seg!$I$9+Seg!$I$11+Seg!$I$13+Seg!$I$15+Seg!$I$17 -> 791.59602 | J20: =Seg!$J$7+Seg!$J$9+Seg!$J$11+Seg!$J$13+Seg!$J$15+Seg!$J$17 -> 853.48545 | K20: =Seg!$K$7+Seg!$K$9+Seg!$K$11+Seg!$K$13+Seg!$K$15+Seg!$K$17 -> 908.53719 | L20: =Seg!$L$7+Seg!$L$9+Seg!$L$11+Seg!$L$13+Seg!$L$15+Seg!$L$17 -> 967.41543 | M20: =Seg!$M$7+Seg!$M$9+Seg!$M$11+Seg!$M$13+Seg!$M$15+Seg!$M$17 -> 1030.406 | N20: =Seg!$N$7+Seg!$N$9+Seg!$N$11+Seg!$N$13+Seg!$N$15+Seg!$N$17 -> 410.392 | O20: =Seg!$O$7+Seg!$O$9+Seg!$O$11+Seg!$O$13+Seg!$O$15+Seg!$O$17 -> 177.807
A21: 北美占零售營收比例（地區分攤） | B21: % | C21: =Q!$D$5/(Q!$D$5+Q!$D$6) -> 0.73057091 | D21: =Q!$E$5/(Q!$E$5+Q!$E$6) -> 0.72476322 | E21: =Q!$O$5/(Q!$O$5+Q!$O$6) -> 0.72702753 | F21: =Seg!$O$21 -> 0.71472439 | G21: =Seg!$G$22/Seg!$G$20 -> 0.72331031 | H21: =Seg!$G$21 -> 0.72331031 | I21: =Seg!$G$21 -> 0.72331031 | J21: =Seg!$G$21 -> 0.72331031 | K21: =Seg!$G$21 -> 0.72331031 | L21: =Seg!$G$21 -> 0.72331031 | M21: =Seg!$G$21 -> 0.72331031 | N21: =Q!$N$5/(Q!$N$5+Q!$N$6) -> 0.72911265 | O21: =Q!$J$5/(Q!$J$5+Q!$J$6) -> 0.71472439 | P21: Q4 26＝Q4 25 比例；2027 起固定為 FY2026（Derived）；各營收線不分地區揭露，故以本列分攤
A22: North America | B22: US$bn | C22: =Q!$D$5 -> 387.497 | D22: =Q!$E$5 -> 426.305 | E22: =Q!$O$5 -> 333.172 | F22: =Seg!$F$20*Seg!$F$21 -> 141.80393 | G22: =Seg!$E$22+Seg!$F$22 -> 474.97593 | H22: =Seg!$H$20*Seg!$H$21 -> 524.56673 | I22: =Seg!$I$20*Seg!$I$21 -> 572.56956 | J22: =Seg!$J$20*Seg!$J$21 -> 617.33483 | K22: =Seg!$K$20*Seg!$K$21 -> 657.15431 | L22: =Seg!$L$20*Seg!$L$21 -> 699.74156 | M22: =Seg!$M$20*Seg!$M$21 -> 745.30329 | N22: =Q!$N$5 -> 299.222 | O22: =Q!$J$5 -> 127.083 | P22: 官方分部；預測＝零售營收線合計 × 北美比例
A23: International | B23: US$bn | C23: =Q!$D$6 -> 142.906 | D23: =Q!$E$6 -> 161.894 | E23: =Q!$O$6 -> 125.094 | F23: =Seg!$F$20*(1-Seg!$F$21) -> 56.599724 | G23: =Seg!$E$23+Seg!$F$23 -> 181.69372 | H23: =Seg!$H$20*(1-Seg!$H$21) -> 200.66381 | I23: =Seg!$I$20*(1-Seg!$I$21) -> 219.02646 | J23: =Seg!$J$20*(1-Seg!$J$21) -> 236.15062 | K23: =Seg!$K$20*(1-Seg!$K$21) -> 251.38287 | L23: =Seg!$L$20*(1-Seg!$L$21) -> 267.67388 | M23: =Seg!$M$20*(1-Seg!$M$21) -> 285.10272 | N23: =Q!$N$6 -> 111.17 | O23: =Q!$J$6 -> 50.724 | P23: 官方分部；預測＝零售營收線合計 ×（1 − 北美比例）
A24: 廣告營收歸北美（＝廣告 × 北美比例） | B24: US$bn | C24: =Seg!$C$13*Seg!$C$21 -> 41.068313 | D24: =Seg!$D$13*Seg!$D$21 -> 49.744123 | E24: =Seg!$E$13*Seg!$E$21 -> 41.214464 | F24: =Seg!$F$13*Seg!$F$21 -> 18.231218 | G24: =Seg!$G$13*Seg!$G$21 -> 59.453966 | H24: =Seg!$H$13*Seg!$H$21 -> 69.771148 | I24: =Seg!$I$13*Seg!$I$21 -> 80.16855 | J24: =Seg!$J$13*Seg!$J$21 -> 90.150397 | K24: =Seg!$K$13*Seg!$K$21 -> 99.165436 | L24: =Seg!$L$13*Seg!$L$21 -> 109.08198 | M24: =Seg!$M$13*Seg!$M$21 -> 119.99018 | N24: =Seg!$N$13*Seg!$N$21 -> 34.500153 | O24: =Seg!$O$13*Seg!$O$21 -> 15.23578 | P24: 廣告營收依零售營收的地區比例分攤（Assumed；公司未分地區揭露）
A25: 廣告營收歸國際 | B25: US$bn | C25: =Seg!$C$13-Seg!$C$24 -> 15.145687 | D25: =Seg!$D$13-Seg!$D$24 -> 18.890877 | E25: =Seg!$E$13-Seg!$E$24 -> 15.474536 | F25: =Seg!$F$13-Seg!$F$24 -> 7.2768214 | G25: =Seg!$G$13-Seg!$G$24 -> 22.743073 | H25: =Seg!$H$13-Seg!$H$24 -> 26.689731 | I25: =Seg!$I$13-Seg!$I$24 -> 30.667075 | J25: =Seg!$J$13-Seg!$J$24 -> 34.485455 | K25: =Seg!$K$13-Seg!$K$24 -> 37.934001 | L25: =Seg!$L$13-Seg!$L$24 -> 41.727401 | M25: =Seg!$M$13-Seg!$M$24 -> 45.900141 | N25: =Seg!$N$13-Seg!$N$24 -> 12.817847 | O25: =Seg!$O$13-Seg!$O$24 -> 6.0812201
A26: 2. AWS（命題子列＋AWS 其他）與合併營收
A27: AWS AI（命題子列） | B27: US$bn | C27: =Thesis!$C$26 -> 2.3210054 | D27: =Thesis!$D$26 -> 8.7037701 | E27: =Thesis!$E$26 -> 16.200708 | F27: =Thesis!$F$26 -> 9.732022 | G27: =Thesis!$G$26 -> 25.93273 | H27: =Thesis!$H$26 -> 71.239209 | I27: =Thesis!$I$26 -> 124.19956 | J27: =Thesis!$J$26 -> 177.44867 | K27: =Thesis!$K$26 -> 222.86577 | L27: =Thesis!$L$26 -> 252.70652 | M27: =Thesis!$M$26 -> 266.92381 | N27: =Thesis!$N$26 -> 5.5486534 | O27: =Thesis!$O$26 -> 3.1551167 | P27: Thesis 頁
A28: AWS 其他 | B28: US$bn | C28: =Thesis!$C$30 -> 105.23499 | D28: =Thesis!$D$30 -> 120.02123 | E28: =Thesis!$E$30 -> 109.60229 | F28: =Thesis!$F$30 -> 36.97966 | G28: =Thesis!$G$30 -> 146.58195 | H28: =Thesis!$H$30 -> 164.96042 | I28: =Thesis!$I$30 -> 183.14786 | J28: =Thesis!$J$30 -> 200.57012 | K28: =Thesis!$K$30 -> 216.61573 | L28: =Thesis!$L$30 -> 233.94498 | M28: =Thesis!$M$30 -> 252.66058 | N28: =Thesis!$N$30 -> 87.597347 | O28: =Thesis!$O$30 -> 32.423883 | P28: Thesis 頁
A29: AWS | B29: US$bn | C29: =Q!$D$7 -> 107.556 | D29: =Q!$E$7 -> 128.725 | E29: =Q!$O$7 -> 125.803 | F29: =Seg!$F$27+Seg!$F$28 -> 46.711682 | G29: =Seg!$G$27+Seg!$G$28 -> 172.51468 | H29: =Seg!$H$27+Seg!$H$28 -> 236.19962 | I29: =Seg!$I$27+Seg!$I$28 -> 307.34743 | J29: =Seg!$J$27+Seg!$J$28 -> 378.01879 | K29: =Seg!$K$27+Seg!$K$28 -> 439.4815 | L29: =Seg!$L$27+Seg!$L$28 -> 486.65151 | M29: =Seg!$M$27+Seg!$M$28 -> 519.5844 | N29: =Q!$N$7 -> 93.146 | O29: =Q!$J$7 -> 35.579 | P29: 官方分部＝AWS 營收線
A30: 合併營收（實績＝公司揭露；預測＝營收線加總） | B30: US$bn | C30: =Q!$D$8 -> 637.959 | D30: =Q!$E$8 -> 716.924 | E30: =Q!$O$8 -> 584.069 | F30: =Seg!$F$20+Seg!$F$29 -> 245.11534 | G30: =Seg!$G$20+Seg!$G$29 -> 829.18434 | H30: =Seg!$H$20+Seg!$H$29 -> 961.43017 | I30: =Seg!$I$20+Seg!$I$29 -> 1098.9434 | J30: =Seg!$J$20+Seg!$J$29 -> 1231.5042 | K30: =Seg!$K$20+Seg!$K$29 -> 1348.0187 | L30: =Seg!$L$20+Seg!$L$29 -> 1454.0669 | M30: =Seg!$M$20+Seg!$M$29 -> 1549.9904 | N30: =Q!$N$8 -> 503.538 | O30: =Q!$J$8 -> 213.386
A31: 檢查（情境 A）：零售營收線合計 − (North America＋International) | B31: US$bn | C31: =Seg!$C$20-(Seg!$C$22+Seg!$C$23) -> 0 | D31: =Seg!$D$20-(Seg!$D$22+Seg!$D$23) -> 0 | E31: =Seg!$E$20-(Seg!$E$22+Seg!$E$23) -> 0 | F31: =Seg!$F$20-(Seg!$F$22+Seg!$F$23) -> 0 | G31: =Seg!$G$20-(Seg!$G$22+Seg!$G$23) -> 0 | H31: =Seg!$H$20-(Seg!$H$22+Seg!$H$23) -> 0 | I31: =Seg!$I$20-(Seg!$I$22+Seg!$I$23) -> 0 | J31: =Seg!$J$20-(Seg!$J$22+Seg!$J$23) -> 0 | K31: =Seg!$K$20-(Seg!$K$22+Seg!$K$23) -> 0 | L31: =Seg!$L$20-(Seg!$L$22+Seg!$L$23) -> 0 | M31: =Seg!$M$20-(Seg!$M$22+Seg!$M$23) -> 0 | N31: =Seg!$N$20-(Seg!$N$22+Seg!$N$23) -> 0 | O31: =Seg!$O$20-(Seg!$O$22+Seg!$O$23) -> 0
A32: 檢查（情境 A）：AWS AI＋AWS 其他 − AWS | B32: US$bn | C32: =Seg!$C$27+Seg!$C$28-Seg!$C$29 -> 0 | D32: =Seg!$D$27+Seg!$D$28-Seg!$D$29 -> 0 | E32: =Seg!$E$27+Seg!$E$28-Seg!$E$29 -> 0 | F32: =Seg!$F$27+Seg!$F$28-Seg!$F$29 -> 0 | G32: =Seg!$G$27+Seg!$G$28-Seg!$G$29 -> 0 | H32: =Seg!$H$27+Seg!$H$28-Seg!$H$29 -> 0 | I32: =Seg!$I$27+Seg!$I$28-Seg!$I$29 -> 0 | J32: =Seg!$J$27+Seg!$J$28-Seg!$J$29 -> 0 | K32: =Seg!$K$27+Seg!$K$28-Seg!$K$29 -> 0 | L32: =Seg!$L$27+Seg!$L$28-Seg!$L$29 -> 0 | M32: =Seg!$M$27+Seg!$M$28-Seg!$M$29 -> 0 | N32: =Seg!$N$27+Seg!$N$28-Seg!$N$29 -> 0 | O32: =Seg!$O$27+Seg!$O$28-Seg!$O$29 -> 0
A33: 檢查（情境 A）：分部合計 − 合併營收 | B33: US$bn | C33: =Seg!$C$22+Seg!$C$23+Seg!$C$29-Seg!$C$30 -> 0 | D33: =Seg!$D$22+Seg!$D$23+Seg!$D$29-Seg!$D$30 -> 0 | E33: =Seg!$E$22+Seg!$E$23+Seg!$E$29-Seg!$E$30 -> 0 | F33: =Seg!$F$22+Seg!$F$23+Seg!$F$29-Seg!$F$30 -> 0 | G33: =Seg!$G$22+Seg!$G$23+Seg!$G$29-Seg!$G$30 -> 0 | H33: =Seg!$H$22+Seg!$H$23+Seg!$H$29-Seg!$H$30 -> 0 | I33: =Seg!$I$22+Seg!$I$23+Seg!$I$29-Seg!$I$30 -> 0 | J33: =Seg!$J$22+Seg!$J$23+Seg!$J$29-Seg!$J$30 -> 0 | K33: =Seg!$K$22+Seg!$K$23+Seg!$K$29-Seg!$K$30 -> 0 | L33: =Seg!$L$22+Seg!$L$23+Seg!$L$29-Seg!$L$30 -> 0 | M33: =Seg!$M$22+Seg!$M$23+Seg!$M$29-Seg!$M$30 -> 0 | N33: =Seg!$N$22+Seg!$N$23+Seg!$N$29-Seg!$N$30 -> 0 | O33: =Seg!$O$22+Seg!$O$23+Seg!$O$29-Seg!$O$30 -> 0
A34: 合併營收年增 | B34: % | G34: =Seg!$G$30/Seg!$D$30-1 -> 0.15658611 | H34: =Seg!$H$30/Seg!$G$30-1 -> 0.15948906 | I34: =Seg!$I$30/Seg!$H$30-1 -> 0.14302992 | J34: =Seg!$J$30/Seg!$I$30-1 -> 0.12062567 | K34: =Seg!$K$30/Seg!$J$30-1 -> 0.094611484 | L34: =Seg!$L$30/Seg!$K$30-1 -> 0.078669725 | M34: =Seg!$M$30/Seg!$L$30-1 -> 0.065969085
A35: AWS 占合併營收 | B35: % | C35: =Seg!$C$29/Seg!$C$30 -> 0.16859391 | D35: =Seg!$D$29/Seg!$D$30 -> 0.17955181 | E35: =Seg!$E$29/Seg!$E$30 -> 0.21539065 | F35: =Seg!$F$29/Seg!$F$30 -> 0.19057021 | G35: =Seg!$G$29/Seg!$G$30 -> 0.20805347 | H35: =Seg!$H$29/Seg!$H$30 -> 0.24567528 | I35: =Seg!$I$29/Seg!$I$30 -> 0.27967538 | J35: =Seg!$J$29/Seg!$J$30 -> 0.30695695 | K35: =Seg!$K$29/Seg!$K$30 -> 0.32602033 | L35: =Seg!$L$29/Seg!$L$30 -> 0.33468301 | M35: =Seg!$M$29/Seg!$M$30 -> 0.33521782 | N35: =Seg!$N$29/Seg!$N$30 -> 0.18498306 | O35: =Seg!$O$29/Seg!$O$30 -> 0.1667354
A36: AWS AI 占 AWS | B36: % | C36: =Seg!$C$27/Seg!$C$29 -> 0.021579506 | D36: =Seg!$D$27/Seg!$D$29 -> 0.067615227 | E36: =Seg!$E$27/Seg!$E$29 -> 0.12877839 | F36: =Seg!$F$27/Seg!$F$29 -> 0.20834236 | G36: =Seg!$G$27/Seg!$G$29 -> 0.15032187 | H36: =Seg!$H$27/Seg!$H$29 -> 0.30160594 | I36: =Seg!$I$27/Seg!$I$29 -> 0.40410152 | J36: =Seg!$J$27/Seg!$J$29 -> 0.46941759 | K36: =Seg!$K$27/Seg!$K$29 -> 0.5071107 | L36: =Seg!$L$27/Seg!$L$29 -> 0.51927615 | M36: =Seg!$M$27/Seg!$M$29 -> 0.51372561 | N36: =Seg!$N$27/Seg!$N$29 -> 0.059569423 | O36: =Seg!$O$27/Seg!$O$29 -> 0.088679183
A39: Seg｜情境 B（基準）：營收分部層（官方分部 North America、International、AWS；10-K 營收線）
A40: 項目 | B40: 單位 | C40: FY2024A | D40: FY2025A | E40: 9M26A | F40: Q4 26E | G40: FY2026E（9M 實績＋Q4 模型） | H40: FY2027E | I40: FY2028E | J40: FY2029E | K40: FY2030E | L40: FY2031E | M40: FY2032E | N40: 9M25A | O40: Q4 25A | P40: 說明 | R40: 2023 | S40: 2024 | T40: 2025 | U40: 2026 | V40: 2027 | W40: 2028 | X40: 2029 | Y40: 2030 | Z40: 2031 | AA40: 2032
A41: 1. 零售各營收線（Q4 26＝Q4 25 ×（1＋9M26 年增）× 校準係數；2027–2030 年增由 9M26 年增線性收斂到長期值；2031–2032＝長期值）
A42: Online stores | B42: US$bn | C42: =Q!$D$10 -> 247.029 | D42: =Q!$E$10 -> 269.287 | E42: =Q!$O$10 -> 203.156 | F42: =Seg!$O$42*(1+Seg!$F$43)*Seg!$F$54 -> 90.388464 | G42: =Seg!$E$42+Seg!$F$42 -> 293.54446 | H42: =Seg!$G$42*(1+Seg!$H$43) -> 317.13448 | I42: =Seg!$H$42*(1+Seg!$I$43) -> 339.41058 | J42: =Seg!$I$42*(1+Seg!$J$43) -> 359.81625 | K42: =Seg!$J$42*(1+Seg!$K$43) -> 377.80706 | L42: =Seg!$K$42*(1+Seg!$L$43) -> 396.69741 | M42: =Seg!$L$42*(1+Seg!$M$43) -> 416.53228 | N42: =Q!$N$10 -> 186.299 | O42: =Q!$J$10 -> 82.988 | P42: Q 頁實績；預測＝前期 ×（1＋年增）
A43: Online stores 年增 | B43: % | E43: =Seg!$E$42/Seg!$N$42-1 -> 0.090483577 | F43: =Seg!$E$43 -> 0.090483577 | G43: =Seg!$G$42/Seg!$D$42-1 -> 0.090080337 | H43: =Seg!$F$43+(g_os-Seg!$F$43)*1/4 -> 0.080362683 | I43: =Seg!$F$43+(g_os-Seg!$F$43)*2/4 -> 0.070241789 | J43: =Seg!$F$43+(g_os-Seg!$F$43)*3/4 -> 0.060120894 | K43: =Seg!$F$43+(g_os-Seg!$F$43)*4/4 -> 0.05 | L43: =g_os -> 0.05 | M43: =g_os -> 0.05 | P43: E＝9M26 對 9M25（Prime Day 移入 Q2 的時點影響在九個月內抵銷）；F＝Q4 26 成長基準＝E（Derived）；收斂到 In 頁 g_os
A44: Physical stores | B44: US$bn | C44: =Q!$D$11 -> 21.215 | D44: =Q!$E$11 -> 22.561 | E44: =Q!$O$11 -> 17.289 | F44: =Seg!$O$44*(1+Seg!$F$45)*Seg!$F$54 -> 6.0520551 | G44: =Seg!$E$44+Seg!$F$44 -> 23.341055 | H44: =Seg!$G$44*(1+Seg!$H$45) -> 24.127024 | I44: =Seg!$H$44*(1+Seg!$I$45) -> 24.909917 | J44: =Seg!$I$44*(1+Seg!$J$45) -> 25.687715 | K44: =Seg!$J$44*(1+Seg!$K$45) -> 26.458346 | L44: =Seg!$K$44*(1+Seg!$L$45) -> 27.252097 | M44: =Seg!$L$44*(1+Seg!$M$45) -> 28.06966 | N44: =Q!$N$11 -> 16.706 | O44: =Q!$J$11 -> 5.855 | P44: Q 頁實績；預測＝前期 ×（1＋年增）
A45: Physical stores 年增 | B45: % | E45: =Seg!$E$44/Seg!$N$44-1 -> 0.034897642 | F45: =Seg!$E$45 -> 0.034897642 | G45: =Seg!$G$44/Seg!$D$44-1 -> 0.034575378 | H45: =Seg!$F$45+(g_ps-Seg!$F$45)*1/4 -> 0.033673231 | I45: =Seg!$F$45+(g_ps-Seg!$F$45)*2/4 -> 0.032448821 | J45: =Seg!$F$45+(g_ps-Seg!$F$45)*3/4 -> 0.03122441 | K45: =Seg!$F$45+(g_ps-Seg!$F$45)*4/4 -> 0.03 | L45: =g_ps -> 0.03 | M45: =g_ps -> 0.03 | P45: E＝9M26 對 9M25（Prime Day 移入 Q2 的時點影響在九個月內抵銷）；F＝Q4 26 成長基準＝E（Derived）；收斂到 In 頁 g_ps
A46: Third-party seller services | B46: US$bn | C46: =Q!$D$12 -> 156.146 | D46: =Q!$E$12 -> 172.162 | E46: =Q!$O$12 -> 134.85 | F46: =Seg!$O$46*(1+Seg!$F$47)*Seg!$F$54 -> 59.605614 | G46: =Seg!$E$46+Seg!$F$46 -> 194.45561 | H46: =Seg!$G$46*(1+Seg!$H$47) -> 216.80459 | I46: =Seg!$H$46*(1+Seg!$I$47) -> 238.47508 | J46: =Seg!$I$46*(1+Seg!$J$47) -> 258.73997 | K46: =Seg!$J$46*(1+Seg!$K$47) -> 276.85177 | L46: =Seg!$K$46*(1+Seg!$L$47) -> 296.2314 | M46: =Seg!$L$46*(1+Seg!$M$47) -> 316.9676 | N46: =Q!$N$12 -> 119.346 | O46: =Q!$J$12 -> 52.816 | P46: Q 頁實績；預測＝前期 ×（1＋年增）
A47: Third-party seller services 年增 | B47: % | E47: =Seg!$E$46/Seg!$N$46-1 -> 0.129908 | F47: =Seg!$E$47 -> 0.129908 | G47: =Seg!$G$46/Seg!$D$46-1 -> 0.12949207 | H47: =Seg!$F$47+(g_sp-Seg!$F$47)*1/4 -> 0.114931 | I47: =Seg!$F$47+(g_sp-Seg!$F$47)*2/4 -> 0.099953999 | J47: =Seg!$F$47+(g_sp-Seg!$F$47)*3/4 -> 0.084977 | K47: =Seg!$F$47+(g_sp-Seg!$F$47)*4/4 -> 0.07 | L47: =g_sp -> 0.07 | M47: =g_sp -> 0.07 | P47: E＝9M26 對 9M25（Prime Day 移入 Q2 的時點影響在九個月內抵銷）；F＝Q4 26 成長基準＝E（Derived）；收斂到 In 頁 g_sp
A48: Advertising services | B48: US$bn | C48: =Q!$D$13 -> 56.214 | D48: =Q!$E$13 -> 68.635 | E48: =Q!$O$13 -> 56.689 | F48: =Seg!$O$48*(1+Seg!$F$49)*Seg!$F$54 -> 25.508039 | G48: =Seg!$E$48+Seg!$F$48 -> 82.197039 | H48: =Seg!$G$48*(1+Seg!$H$49) -> 96.460878 | I48: =Seg!$H$48*(1+Seg!$I$49) -> 110.83562 | J48: =Seg!$I$48*(1+Seg!$J$49) -> 124.63585 | K48: =Seg!$J$48*(1+Seg!$K$49) -> 137.09944 | L48: =Seg!$K$48*(1+Seg!$L$49) -> 150.80938 | M48: =Seg!$L$48*(1+Seg!$M$49) -> 165.89032 | N48: =Q!$N$13 -> 47.318 | O48: =Q!$J$13 -> 21.317 | P48: Q 頁實績；預測＝前期 ×（1＋年增）
A49: Advertising services 年增 | B49: % | E49: =Seg!$E$48/Seg!$N$48-1 -> 0.19804303 | F49: =Seg!$E$49 -> 0.19804303 | G49: =Seg!$G$48/Seg!$D$48-1 -> 0.19759655 | H49: =Seg!$F$49+(g_ad-Seg!$F$49)*1/4 -> 0.17353227 | I49: =Seg!$F$49+(g_ad-Seg!$F$49)*2/4 -> 0.14902151 | J49: =Seg!$F$49+(g_ad-Seg!$F$49)*3/4 -> 0.12451076 | K49: =Seg!$F$49+(g_ad-Seg!$F$49)*4/4 -> 0.1 | L49: =g_ad -> 0.1 | M49: =g_ad -> 0.1 | P49: E＝9M26 對 9M25（Prime Day 移入 Q2 的時點影響在九個月內抵銷）；F＝Q4 26 成長基準＝E（Derived）；收斂到 In 頁 g_ad
A50: Subscription services | B50: US$bn | C50: =Q!$D$14 -> 44.374 | D50: =Q!$E$14 -> 49.619 | E50: =Q!$O$14 -> 41.163 | F50: =Seg!$O$50*(1+Seg!$F$51)*Seg!$F$54 -> 14.781839 | G50: =Seg!$E$50+Seg!$F$50 -> 55.944839 | H50: =Seg!$G$50*(1+Seg!$H$51) -> 62.288122 | I50: =Seg!$H$50*(1+Seg!$I$51) -> 68.449853 | J50: =Seg!$I$50*(1+Seg!$J$51) -> 74.231233 | K50: =Seg!$J$50*(1+Seg!$K$51) -> 79.427419 | L50: =Seg!$K$50*(1+Seg!$L$51) -> 84.987338 | M50: =Seg!$L$50*(1+Seg!$M$51) -> 90.936452 | N50: =Q!$N$14 -> 36.497 | O50: =Q!$J$14 -> 13.122 | P50: Q 頁實績；預測＝前期 ×（1＋年增）
A51: Subscription services 年增 | B51: % | E51: =Seg!$E$50/Seg!$N$50-1 -> 0.12784612 | F51: =Seg!$E$51 -> 0.12784612 | G51: =Seg!$G$50/Seg!$D$50-1 -> 0.12748824 | H51: =Seg!$F$51+(g_sub-Seg!$F$51)*1/4 -> 0.11338459 | I51: =Seg!$F$51+(g_sub-Seg!$F$51)*2/4 -> 0.098923062 | J51: =Seg!$F$51+(g_sub-Seg!$F$51)*3/4 -> 0.084461531 | K51: =Seg!$F$51+(g_sub-Seg!$F$51)*4/4 -> 0.07 | L51: =g_sub -> 0.07 | M51: =g_sub -> 0.07 | P51: E＝9M26 對 9M25（Prime Day 移入 Q2 的時點影響在九個月內抵銷）；F＝Q4 26 成長基準＝E（Derived）；收斂到 In 頁 g_sub
A52: Other | B52: US$bn | C52: =Q!$D$15 -> 5.425 | D52: =Q!$E$15 -> 5.935 | E52: =Q!$O$15 -> 5.119 | F52: =Seg!$O$52*(1+Seg!$F$53)*Seg!$F$54 -> 2.0676464 | G52: =Seg!$E$52+Seg!$F$52 -> 7.1866464 | H52: =Seg!$G$52*(1+Seg!$H$53) -> 8.4154422 | I52: =Seg!$H$52*(1+Seg!$I$53) -> 9.5149658 | J52: =Seg!$I$52*(1+Seg!$J$53) -> 10.374431 | K52: =Seg!$J$52*(1+Seg!$K$53) -> 10.893153 | L52: =Seg!$K$52*(1+Seg!$L$53) -> 11.43781 | M52: =Seg!$L$52*(1+Seg!$M$53) -> 12.009701 | N52: =Q!$N$15 -> 4.226 | O52: =Q!$J$15 -> 1.709 | P52: Q 頁實績；預測＝前期 ×（1＋年增）
A53: Other 年增 | B53: % | E53: =Seg!$E$52/Seg!$N$52-1 -> 0.21131093 | F53: =Seg!$E$53 -> 0.21131093 | G53: =Seg!$G$52/Seg!$D$52-1 -> 0.21089241 | H53: =Seg!$F$53+(g_ot-Seg!$F$53)*1/4 -> 0.1709832 | I53: =Seg!$F$53+(g_ot-Seg!$F$53)*2/4 -> 0.13065547 | J53: =Seg!$F$53+(g_ot-Seg!$F$53)*3/4 -> 0.090327733 | K53: =Seg!$F$53+(g_ot-Seg!$F$53)*4/4 -> 0.05 | L53: =g_ot -> 0.05 | M53: =g_ot -> 0.05 | P53: E＝9M26 對 9M25（Prime Day 移入 Q2 的時點影響在九個月內抵銷）；F＝Q4 26 成長基準＝E（Derived）；收斂到 In 頁 g_ot
A54: Q4 26 零售營收校準係數（使情境 B 的 Q4 26 合併營收＝指引中點） | B54: x | F54: =(g26q4_mid-Thesis!$F$92-Thesis!$F$96)/(Seg!$O$42*(1+Seg!$F$43)+Seg!$O$44*(1+Seg!$F$45)+Seg!$O$46*(1+Seg!$F$47)+Seg!$O$48*(1+Seg!$F$49)+Seg!$O$50*(1+Seg!$F$51)+Seg!$O$52*(1+Seg!$F$53)) -> 0.9988001 | P54: Q4 26 合併營收目標＝指引中點 243.5 − 主頁情境 B 的 AWS Q4 26；三情境共用同一係數（修正二），零售不隨 AI 分拆變動
A55: 零售營收線合計（＝North America＋International） | B55: US$bn | C55: =Seg!$C$42+Seg!$C$44+Seg!$C$46+Seg!$C$48+Seg!$C$50+Seg!$C$52 -> 530.403 | D55: =Seg!$D$42+Seg!$D$44+Seg!$D$46+Seg!$D$48+Seg!$D$50+Seg!$D$52 -> 588.199 | E55: =Seg!$E$42+Seg!$E$44+Seg!$E$46+Seg!$E$48+Seg!$E$50+Seg!$E$52 -> 458.266 | F55: =Seg!$F$42+Seg!$F$44+Seg!$F$46+Seg!$F$48+Seg!$F$50+Seg!$F$52 -> 198.40366 | G55: =Seg!$G$42+Seg!$G$44+Seg!$G$46+Seg!$G$48+Seg!$G$50+Seg!$G$52 -> 656.66966 | H55: =Seg!$H$42+Seg!$H$44+Seg!$H$46+Seg!$H$48+Seg!$H$50+Seg!$H$52 -> 725.23054 | I55: =Seg!$I$42+Seg!$I$44+Seg!$I$46+Seg!$I$48+Seg!$I$50+Seg!$I$52 -> 791.59602 | J55: =Seg!$J$42+Seg!$J$44+Seg!$J$46+Seg!$J$48+Seg!$J$50+Seg!$J$52 -> 853.48545 | K55: =Seg!$K$42+Seg!$K$44+Seg!$K$46+Seg!$K$48+Seg!$K$50+Seg!$K$52 -> 908.53719 | L55: =Seg!$L$42+Seg!$L$44+Seg!$L$46+Seg!$L$48+Seg!$L$50+Seg!$L$52 -> 967.41543 | M55: =Seg!$M$42+Seg!$M$44+Seg!$M$46+Seg!$M$48+Seg!$M$50+Seg!$M$52 -> 1030.406 | N55: =Seg!$N$42+Seg!$N$44+Seg!$N$46+Seg!$N$48+Seg!$N$50+Seg!$N$52 -> 410.392 | O55: =Seg!$O$42+Seg!$O$44+Seg!$O$46+Seg!$O$48+Seg!$O$50+Seg!$O$52 -> 177.807
A56: 北美占零售營收比例（地區分攤） | B56: % | C56: =Q!$D$5/(Q!$D$5+Q!$D$6) -> 0.73057091 | D56: =Q!$E$5/(Q!$E$5+Q!$E$6) -> 0.72476322 | E56: =Q!$O$5/(Q!$O$5+Q!$O$6) -> 0.72702753 | F56: =Seg!$O$56 -> 0.71472439 | G56: =Seg!$G$57/Seg!$G$55 -> 0.72331031 | H56: =Seg!$G$56 -> 0.72331031 | I56: =Seg!$G$56 -> 0.72331031 | J56: =Seg!$G$56 -> 0.72331031 | K56: =Seg!$G$56 -> 0.72331031 | L56: =Seg!$G$56 -> 0.72331031 | M56: =Seg!$G$56 -> 0.72331031 | N56: =Q!$N$5/(Q!$N$5+Q!$N$6) -> 0.72911265 | O56: =Q!$J$5/(Q!$J$5+Q!$J$6) -> 0.71472439 | P56: Q4 26＝Q4 25 比例；2027 起固定為 FY2026（Derived）；各營收線不分地區揭露，故以本列分攤
A57: North America | B57: US$bn | C57: =Q!$D$5 -> 387.497 | D57: =Q!$E$5 -> 426.305 | E57: =Q!$O$5 -> 333.172 | F57: =Seg!$F$55*Seg!$F$56 -> 141.80393 | G57: =Seg!$E$57+Seg!$F$57 -> 474.97593 | H57: =Seg!$H$55*Seg!$H$56 -> 524.56673 | I57: =Seg!$I$55*Seg!$I$56 -> 572.56956 | J57: =Seg!$J$55*Seg!$J$56 -> 617.33483 | K57: =Seg!$K$55*Seg!$K$56 -> 657.15431 | L57: =Seg!$L$55*Seg!$L$56 -> 699.74156 | M57: =Seg!$M$55*Seg!$M$56 -> 745.30329 | N57: =Q!$N$5 -> 299.222 | O57: =Q!$J$5 -> 127.083 | P57: 官方分部；預測＝零售營收線合計 × 北美比例
A58: International | B58: US$bn | C58: =Q!$D$6 -> 142.906 | D58: =Q!$E$6 -> 161.894 | E58: =Q!$O$6 -> 125.094 | F58: =Seg!$F$55*(1-Seg!$F$56) -> 56.599724 | G58: =Seg!$E$58+Seg!$F$58 -> 181.69372 | H58: =Seg!$H$55*(1-Seg!$H$56) -> 200.66381 | I58: =Seg!$I$55*(1-Seg!$I$56) -> 219.02646 | J58: =Seg!$J$55*(1-Seg!$J$56) -> 236.15062 | K58: =Seg!$K$55*(1-Seg!$K$56) -> 251.38287 | L58: =Seg!$L$55*(1-Seg!$L$56) -> 267.67388 | M58: =Seg!$M$55*(1-Seg!$M$56) -> 285.10272 | N58: =Q!$N$6 -> 111.17 | O58: =Q!$J$6 -> 50.724 | P58: 官方分部；預測＝零售營收線合計 ×（1 − 北美比例）
A59: 廣告營收歸北美（＝廣告 × 北美比例） | B59: US$bn | C59: =Seg!$C$48*Seg!$C$56 -> 41.068313 | D59: =Seg!$D$48*Seg!$D$56 -> 49.744123 | E59: =Seg!$E$48*Seg!$E$56 -> 41.214464 | F59: =Seg!$F$48*Seg!$F$56 -> 18.231218 | G59: =Seg!$G$48*Seg!$G$56 -> 59.453966 | H59: =Seg!$H$48*Seg!$H$56 -> 69.771148 | I59: =Seg!$I$48*Seg!$I$56 -> 80.16855 | J59: =Seg!$J$48*Seg!$J$56 -> 90.150397 | K59: =Seg!$K$48*Seg!$K$56 -> 99.165436 | L59: =Seg!$L$48*Seg!$L$56 -> 109.08198 | M59: =Seg!$M$48*Seg!$M$56 -> 119.99018 | N59: =Seg!$N$48*Seg!$N$56 -> 34.500153 | O59: =Seg!$O$48*Seg!$O$56 -> 15.23578 | P59: 廣告營收依零售營收的地區比例分攤（Assumed；公司未分地區揭露）
A60: 廣告營收歸國際 | B60: US$bn | C60: =Seg!$C$48-Seg!$C$59 -> 15.145687 | D60: =Seg!$D$48-Seg!$D$59 -> 18.890877 | E60: =Seg!$E$48-Seg!$E$59 -> 15.474536 | F60: =Seg!$F$48-Seg!$F$59 -> 7.2768214 | G60: =Seg!$G$48-Seg!$G$59 -> 22.743073 | H60: =Seg!$H$48-Seg!$H$59 -> 26.689731 | I60: =Seg!$I$48-Seg!$I$59 -> 30.667075 | J60: =Seg!$J$48-Seg!$J$59 -> 34.485455 | K60: =Seg!$K$48-Seg!$K$59 -> 37.934001 | L60: =Seg!$L$48-Seg!$L$59 -> 41.727401 | M60: =Seg!$M$48-Seg!$M$59 -> 45.900141 | N60: =Seg!$N$48-Seg!$N$59 -> 12.817847 | O60: =Seg!$O$48-Seg!$O$59 -> 6.0812201
A61: 2. AWS（命題子列＋AWS 其他）與合併營收
A62: AWS AI（命題子列） | B62: US$bn | C62: =Thesis!$C$92 -> 2.3210054 | D62: =Thesis!$D$92 -> 8.7037701 | E62: =Thesis!$E$92 -> 16.200708 | F62: =Thesis!$F$92 -> 8.116682 | G62: =Thesis!$G$92 -> 24.31739 | H62: =Thesis!$H$92 -> 53.891094 | I62: =Thesis!$I$92 -> 89.008867 | J62: =Thesis!$J$92 -> 124.31836 | K62: =Thesis!$K$92 -> 154.43252 | L62: =Thesis!$L$92 -> 174.21371 | M62: =Thesis!$M$92 -> 183.63076 | N62: =Thesis!$N$92 -> 5.5486534 | O62: =Thesis!$O$92 -> 3.1551167 | P62: Thesis 頁
A63: AWS 其他 | B63: US$bn | C63: =Thesis!$C$96 -> 105.23499 | D63: =Thesis!$D$96 -> 120.02123 | E63: =Thesis!$E$96 -> 109.60229 | F63: =Thesis!$F$96 -> 36.97966 | G63: =Thesis!$G$96 -> 146.58195 | H63: =Thesis!$H$96 -> 164.96042 | I63: =Thesis!$I$96 -> 183.14786 | J63: =Thesis!$J$96 -> 200.57012 | K63: =Thesis!$K$96 -> 216.61573 | L63: =Thesis!$L$96 -> 233.94498 | M63: =Thesis!$M$96 -> 252.66058 | N63: =Thesis!$N$96 -> 87.597347 | O63: =Thesis!$O$96 -> 32.423883 | P63: Thesis 頁
A64: AWS | B64: US$bn | C64: =Q!$D$7 -> 107.556 | D64: =Q!$E$7 -> 128.725 | E64: =Q!$O$7 -> 125.803 | F64: =Seg!$F$62+Seg!$F$63 -> 45.096342 | G64: =Seg!$G$62+Seg!$G$63 -> 170.89934 | H64: =Seg!$H$62+Seg!$H$63 -> 218.85151 | I64: =Seg!$I$62+Seg!$I$63 -> 272.15673 | J64: =Seg!$J$62+Seg!$J$63 -> 324.88848 | K64: =Seg!$K$62+Seg!$K$63 -> 371.04824 | L64: =Seg!$L$62+Seg!$L$63 -> 408.1587 | M64: =Seg!$M$62+Seg!$M$63 -> 436.29134 | N64: =Q!$N$7 -> 93.146 | O64: =Q!$J$7 -> 35.579 | P64: 官方分部＝AWS 營收線
A65: 合併營收（實績＝公司揭露；預測＝營收線加總） | B65: US$bn | C65: =Q!$D$8 -> 637.959 | D65: =Q!$E$8 -> 716.924 | E65: =Q!$O$8 -> 584.069 | F65: =Seg!$F$55+Seg!$F$64 -> 243.5 | G65: =Seg!$G$55+Seg!$G$64 -> 827.569 | H65: =Seg!$H$55+Seg!$H$64 -> 944.08205 | I65: =Seg!$I$55+Seg!$I$64 -> 1063.7527 | J65: =Seg!$J$55+Seg!$J$64 -> 1178.3739 | K65: =Seg!$K$55+Seg!$K$64 -> 1279.5854 | L65: =Seg!$L$55+Seg!$L$64 -> 1375.5741 | M65: =Seg!$M$55+Seg!$M$64 -> 1466.6973 | N65: =Q!$N$8 -> 503.538 | O65: =Q!$J$8 -> 213.386
A66: 檢查（情境 B）：零售營收線合計 − (North America＋International) | B66: US$bn | C66: =Seg!$C$55-(Seg!$C$57+Seg!$C$58) -> 0 | D66: =Seg!$D$55-(Seg!$D$57+Seg!$D$58) -> 0 | E66: =Seg!$E$55-(Seg!$E$57+Seg!$E$58) -> 0 | F66: =Seg!$F$55-(Seg!$F$57+Seg!$F$58) -> 0 | G66: =Seg!$G$55-(Seg!$G$57+Seg!$G$58) -> 0 | H66: =Seg!$H$55-(Seg!$H$57+Seg!$H$58) -> 0 | I66: =Seg!$I$55-(Seg!$I$57+Seg!$I$58) -> 0 | J66: =Seg!$J$55-(Seg!$J$57+Seg!$J$58) -> 0 | K66: =Seg!$K$55-(Seg!$K$57+Seg!$K$58) -> 0 | L66: =Seg!$L$55-(Seg!$L$57+Seg!$L$58) -> 0 | M66: =Seg!$M$55-(Seg!$M$57+Seg!$M$58) -> 0 | N66: =Seg!$N$55-(Seg!$N$57+Seg!$N$58) -> 0 | O66: =Seg!$O$55-(Seg!$O$57+Seg!$O$58) -> 0
A67: 檢查（情境 B）：AWS AI＋AWS 其他 − AWS | B67: US$bn | C67: =Seg!$C$62+Seg!$C$63-Seg!$C$64 -> 0 | D67: =Seg!$D$62+Seg!$D$63-Seg!$D$64 -> 0 | E67: =Seg!$E$62+Seg!$E$63-Seg!$E$64 -> 0 | F67: =Seg!$F$62+Seg!$F$63-Seg!$F$64 -> 0 | G67: =Seg!$G$62+Seg!$G$63-Seg!$G$64 -> 0 | H67: =Seg!$H$62+Seg!$H$63-Seg!$H$64 -> 0 | I67: =Seg!$I$62+Seg!$I$63-Seg!$I$64 -> 0 | J67: =Seg!$J$62+Seg!$J$63-Seg!$J$64 -> 0 | K67: =Seg!$K$62+Seg!$K$63-Seg!$K$64 -> 0 | L67: =Seg!$L$62+Seg!$L$63-Seg!$L$64 -> 0 | M67: =Seg!$M$62+Seg!$M$63-Seg!$M$64 -> 0 | N67: =Seg!$N$62+Seg!$N$63-Seg!$N$64 -> 0 | O67: =Seg!$O$62+Seg!$O$63-Seg!$O$64 -> 0
A68: 檢查（情境 B）：分部合計 − 合併營收 | B68: US$bn | C68: =Seg!$C$57+Seg!$C$58+Seg!$C$64-Seg!$C$65 -> 0 | D68: =Seg!$D$57+Seg!$D$58+Seg!$D$64-Seg!$D$65 -> 0 | E68: =Seg!$E$57+Seg!$E$58+Seg!$E$64-Seg!$E$65 -> 0 | F68: =Seg!$F$57+Seg!$F$58+Seg!$F$64-Seg!$F$65 -> 0 | G68: =Seg!$G$57+Seg!$G$58+Seg!$G$64-Seg!$G$65 -> 0 | H68: =Seg!$H$57+Seg!$H$58+Seg!$H$64-Seg!$H$65 -> 0 | I68: =Seg!$I$57+Seg!$I$58+Seg!$I$64-Seg!$I$65 -> 0 | J68: =Seg!$J$57+Seg!$J$58+Seg!$J$64-Seg!$J$65 -> 0 | K68: =Seg!$K$57+Seg!$K$58+Seg!$K$64-Seg!$K$65 -> 0 | L68: =Seg!$L$57+Seg!$L$58+Seg!$L$64-Seg!$L$65 -> 0 | M68: =Seg!$M$57+Seg!$M$58+Seg!$M$64-Seg!$M$65 -> 0 | N68: =Seg!$N$57+Seg!$N$58+Seg!$N$64-Seg!$N$65 -> 0 | O68: =Seg!$O$57+Seg!$O$58+Seg!$O$64-Seg!$O$65 -> 0
A69: 合併營收年增 | B69: % | G69: =Seg!$G$65/Seg!$D$65-1 -> 0.15433296 | H69: =Seg!$H$65/Seg!$G$65-1 -> 0.14078953 | I69: =Seg!$I$65/Seg!$H$65-1 -> 0.12675879 | J69: =Seg!$J$65/Seg!$I$65-1 -> 0.10775171 | K69: =Seg!$K$65/Seg!$J$65-1 -> 0.085890815 | L69: =Seg!$L$65/Seg!$K$65-1 -> 0.075015473 | M69: =Seg!$M$65/Seg!$L$65-1 -> 0.066243769
A70: AWS 占合併營收 | B70: % | C70: =Seg!$C$64/Seg!$C$65 -> 0.16859391 | D70: =Seg!$D$64/Seg!$D$65 -> 0.17955181 | E70: =Seg!$E$64/Seg!$E$65 -> 0.21539065 | F70: =Seg!$F$64/Seg!$F$65 -> 0.18520058 | G70: =Seg!$G$64/Seg!$G$65 -> 0.20650767 | H70: =Seg!$H$64/Seg!$H$65 -> 0.23181408 | I70: =Seg!$I$64/Seg!$I$65 -> 0.25584585 | J70: =Seg!$J$64/Seg!$J$65 -> 0.27570915 | K70: =Seg!$K$64/Seg!$K$65 -> 0.28997536 | L70: =Seg!$L$64/Seg!$L$65 -> 0.2967188 | M70: =Seg!$M$64/Seg!$M$65 -> 0.29746515 | N70: =Seg!$N$64/Seg!$N$65 -> 0.18498306 | O70: =Seg!$O$64/Seg!$O$65 -> 0.1667354
A71: AWS AI 占 AWS | B71: % | C71: =Seg!$C$62/Seg!$C$64 -> 0.021579506 | D71: =Seg!$D$62/Seg!$D$64 -> 0.067615227 | E71: =Seg!$E$62/Seg!$E$64 -> 0.12877839 | F71: =Seg!$F$62/Seg!$F$64 -> 0.17998537 | G71: =Seg!$G$62/Seg!$G$64 -> 0.14229072 | H71: =Seg!$H$62/Seg!$H$64 -> 0.24624502 | I71: =Seg!$I$62/Seg!$I$64 -> 0.32705003 | J71: =Seg!$J$62/Seg!$J$64 -> 0.38264934 | K71: =Seg!$K$62/Seg!$K$64 -> 0.41620603 | L71: =Seg!$L$62/Seg!$L$64 -> 0.42682838 | M71: =Seg!$M$62/Seg!$M$64 -> 0.42089022 | N71: =Seg!$N$62/Seg!$N$64 -> 0.059569423 | O71: =Seg!$O$62/Seg!$O$64 -> 0.088679183
A74: Seg｜情境 C（保守）：營收分部層（官方分部 North America、International、AWS；10-K 營收線）
A75: 項目 | B75: 單位 | C75: FY2024A | D75: FY2025A | E75: 9M26A | F75: Q4 26E | G75: FY2026E（9M 實績＋Q4 模型） | H75: FY2027E | I75: FY2028E | J75: FY2029E | K75: FY2030E | L75: FY2031E | M75: FY2032E | N75: 9M25A | O75: Q4 25A | P75: 說明 | R75: 2023 | S75: 2024 | T75: 2025 | U75: 2026 | V75: 2027 | W75: 2028 | X75: 2029 | Y75: 2030 | Z75: 2031 | AA75: 2032
A76: 1. 零售各營收線（Q4 26＝Q4 25 ×（1＋9M26 年增）× 校準係數；2027–2030 年增由 9M26 年增線性收斂到長期值；2031–2032＝長期值）
A77: Online stores | B77: US$bn | C77: =Q!$D$10 -> 247.029 | D77: =Q!$E$10 -> 269.287 | E77: =Q!$O$10 -> 203.156 | F77: =Seg!$O$77*(1+Seg!$F$78)*Seg!$F$89 -> 90.388464 | G77: =Seg!$E$77+Seg!$F$77 -> 293.54446 | H77: =Seg!$G$77*(1+Seg!$H$78) -> 317.13448 | I77: =Seg!$H$77*(1+Seg!$I$78) -> 339.41058 | J77: =Seg!$I$77*(1+Seg!$J$78) -> 359.81625 | K77: =Seg!$J$77*(1+Seg!$K$78) -> 377.80706 | L77: =Seg!$K$77*(1+Seg!$L$78) -> 396.69741 | M77: =Seg!$L$77*(1+Seg!$M$78) -> 416.53228 | N77: =Q!$N$10 -> 186.299 | O77: =Q!$J$10 -> 82.988 | P77: Q 頁實績；預測＝前期 ×（1＋年增）
A78: Online stores 年增 | B78: % | E78: =Seg!$E$77/Seg!$N$77-1 -> 0.090483577 | F78: =Seg!$E$78 -> 0.090483577 | G78: =Seg!$G$77/Seg!$D$77-1 -> 0.090080337 | H78: =Seg!$F$78+(g_os-Seg!$F$78)*1/4 -> 0.080362683 | I78: =Seg!$F$78+(g_os-Seg!$F$78)*2/4 -> 0.070241789 | J78: =Seg!$F$78+(g_os-Seg!$F$78)*3/4 -> 0.060120894 | K78: =Seg!$F$78+(g_os-Seg!$F$78)*4/4 -> 0.05 | L78: =g_os -> 0.05 | M78: =g_os -> 0.05 | P78: E＝9M26 對 9M25（Prime Day 移入 Q2 的時點影響在九個月內抵銷）；F＝Q4 26 成長基準＝E（Derived）；收斂到 In 頁 g_os
A79: Physical stores | B79: US$bn | C79: =Q!$D$11 -> 21.215 | D79: =Q!$E$11 -> 22.561 | E79: =Q!$O$11 -> 17.289 | F79: =Seg!$O$79*(1+Seg!$F$80)*Seg!$F$89 -> 6.0520551 | G79: =Seg!$E$79+Seg!$F$79 -> 23.341055 | H79: =Seg!$G$79*(1+Seg!$H$80) -> 24.127024 | I79: =Seg!$H$79*(1+Seg!$I$80) -> 24.909917 | J79: =Seg!$I$79*(1+Seg!$J$80) -> 25.687715 | K79: =Seg!$J$79*(1+Seg!$K$80) -> 26.458346 | L79: =Seg!$K$79*(1+Seg!$L$80) -> 27.252097 | M79: =Seg!$L$79*(1+Seg!$M$80) -> 28.06966 | N79: =Q!$N$11 -> 16.706 | O79: =Q!$J$11 -> 5.855 | P79: Q 頁實績；預測＝前期 ×（1＋年增）
A80: Physical stores 年增 | B80: % | E80: =Seg!$E$79/Seg!$N$79-1 -> 0.034897642 | F80: =Seg!$E$80 -> 0.034897642 | G80: =Seg!$G$79/Seg!$D$79-1 -> 0.034575378 | H80: =Seg!$F$80+(g_ps-Seg!$F$80)*1/4 -> 0.033673231 | I80: =Seg!$F$80+(g_ps-Seg!$F$80)*2/4 -> 0.032448821 | J80: =Seg!$F$80+(g_ps-Seg!$F$80)*3/4 -> 0.03122441 | K80: =Seg!$F$80+(g_ps-Seg!$F$80)*4/4 -> 0.03 | L80: =g_ps -> 0.03 | M80: =g_ps -> 0.03 | P80: E＝9M26 對 9M25（Prime Day 移入 Q2 的時點影響在九個月內抵銷）；F＝Q4 26 成長基準＝E（Derived）；收斂到 In 頁 g_ps
A81: Third-party seller services | B81: US$bn | C81: =Q!$D$12 -> 156.146 | D81: =Q!$E$12 -> 172.162 | E81: =Q!$O$12 -> 134.85 | F81: =Seg!$O$81*(1+Seg!$F$82)*Seg!$F$89 -> 59.605614 | G81: =Seg!$E$81+Seg!$F$81 -> 194.45561 | H81: =Seg!$G$81*(1+Seg!$H$82) -> 216.80459 | I81: =Seg!$H$81*(1+Seg!$I$82) -> 238.47508 | J81: =Seg!$I$81*(1+Seg!$J$82) -> 258.73997 | K81: =Seg!$J$81*(1+Seg!$K$82) -> 276.85177 | L81: =Seg!$K$81*(1+Seg!$L$82) -> 296.2314 | M81: =Seg!$L$81*(1+Seg!$M$82) -> 316.9676 | N81: =Q!$N$12 -> 119.346 | O81: =Q!$J$12 -> 52.816 | P81: Q 頁實績；預測＝前期 ×（1＋年增）
A82: Third-party seller services 年增 | B82: % | E82: =Seg!$E$81/Seg!$N$81-1 -> 0.129908 | F82: =Seg!$E$82 -> 0.129908 | G82: =Seg!$G$81/Seg!$D$81-1 -> 0.12949207 | H82: =Seg!$F$82+(g_sp-Seg!$F$82)*1/4 -> 0.114931 | I82: =Seg!$F$82+(g_sp-Seg!$F$82)*2/4 -> 0.099953999 | J82: =Seg!$F$82+(g_sp-Seg!$F$82)*3/4 -> 0.084977 | K82: =Seg!$F$82+(g_sp-Seg!$F$82)*4/4 -> 0.07 | L82: =g_sp -> 0.07 | M82: =g_sp -> 0.07 | P82: E＝9M26 對 9M25（Prime Day 移入 Q2 的時點影響在九個月內抵銷）；F＝Q4 26 成長基準＝E（Derived）；收斂到 In 頁 g_sp
A83: Advertising services | B83: US$bn | C83: =Q!$D$13 -> 56.214 | D83: =Q!$E$13 -> 68.635 | E83: =Q!$O$13 -> 56.689 | F83: =Seg!$O$83*(1+Seg!$F$84)*Seg!$F$89 -> 25.508039 | G83: =Seg!$E$83+Seg!$F$83 -> 82.197039 | H83: =Seg!$G$83*(1+Seg!$H$84) -> 96.460878 | I83: =Seg!$H$83*(1+Seg!$I$84) -> 110.83562 | J83: =Seg!$I$83*(1+Seg!$J$84) -> 124.63585 | K83: =Seg!$J$83*(1+Seg!$K$84) -> 137.09944 | L83: =Seg!$K$83*(1+Seg!$L$84) -> 150.80938 | M83: =Seg!$L$83*(1+Seg!$M$84) -> 165.89032 | N83: =Q!$N$13 -> 47.318 | O83: =Q!$J$13 -> 21.317 | P83: Q 頁實績；預測＝前期 ×（1＋年增）
A84: Advertising services 年增 | B84: % | E84: =Seg!$E$83/Seg!$N$83-1 -> 0.19804303 | F84: =Seg!$E$84 -> 0.19804303 | G84: =Seg!$G$83/Seg!$D$83-1 -> 0.19759655 | H84: =Seg!$F$84+(g_ad-Seg!$F$84)*1/4 -> 0.17353227 | I84: =Seg!$F$84+(g_ad-Seg!$F$84)*2/4 -> 0.14902151 | J84: =Seg!$F$84+(g_ad-Seg!$F$84)*3/4 -> 0.12451076 | K84: =Seg!$F$84+(g_ad-Seg!$F$84)*4/4 -> 0.1 | L84: =g_ad -> 0.1 | M84: =g_ad -> 0.1 | P84: E＝9M26 對 9M25（Prime Day 移入 Q2 的時點影響在九個月內抵銷）；F＝Q4 26 成長基準＝E（Derived）；收斂到 In 頁 g_ad
A85: Subscription services | B85: US$bn | C85: =Q!$D$14 -> 44.374 | D85: =Q!$E$14 -> 49.619 | E85: =Q!$O$14 -> 41.163 | F85: =Seg!$O$85*(1+Seg!$F$86)*Seg!$F$89 -> 14.781839 | G85: =Seg!$E$85+Seg!$F$85 -> 55.944839 | H85: =Seg!$G$85*(1+Seg!$H$86) -> 62.288122 | I85: =Seg!$H$85*(1+Seg!$I$86) -> 68.449853 | J85: =Seg!$I$85*(1+Seg!$J$86) -> 74.231233 | K85: =Seg!$J$85*(1+Seg!$K$86) -> 79.427419 | L85: =Seg!$K$85*(1+Seg!$L$86) -> 84.987338 | M85: =Seg!$L$85*(1+Seg!$M$86) -> 90.936452 | N85: =Q!$N$14 -> 36.497 | O85: =Q!$J$14 -> 13.122 | P85: Q 頁實績；預測＝前期 ×（1＋年增）
A86: Subscription services 年增 | B86: % | E86: =Seg!$E$85/Seg!$N$85-1 -> 0.12784612 | F86: =Seg!$E$86 -> 0.12784612 | G86: =Seg!$G$85/Seg!$D$85-1 -> 0.12748824 | H86: =Seg!$F$86+(g_sub-Seg!$F$86)*1/4 -> 0.11338459 | I86: =Seg!$F$86+(g_sub-Seg!$F$86)*2/4 -> 0.098923062 | J86: =Seg!$F$86+(g_sub-Seg!$F$86)*3/4 -> 0.084461531 | K86: =Seg!$F$86+(g_sub-Seg!$F$86)*4/4 -> 0.07 | L86: =g_sub -> 0.07 | M86: =g_sub -> 0.07 | P86: E＝9M26 對 9M25（Prime Day 移入 Q2 的時點影響在九個月內抵銷）；F＝Q4 26 成長基準＝E（Derived）；收斂到 In 頁 g_sub
A87: Other | B87: US$bn | C87: =Q!$D$15 -> 5.425 | D87: =Q!$E$15 -> 5.935 | E87: =Q!$O$15 -> 5.119 | F87: =Seg!$O$87*(1+Seg!$F$88)*Seg!$F$89 -> 2.0676464 | G87: =Seg!$E$87+Seg!$F$87 -> 7.1866464 | H87: =Seg!$G$87*(1+Seg!$H$88) -> 8.4154422 | I87: =Seg!$H$87*(1+Seg!$I$88) -> 9.5149658 | J87: =Seg!$I$87*(1+Seg!$J$88) -> 10.374431 | K87: =Seg!$J$87*(1+Seg!$K$88) -> 10.893153 | L87: =Seg!$K$87*(1+Seg!$L$88) -> 11.43781 | M87: =Seg!$L$87*(1+Seg!$M$88) -> 12.009701 | N87: =Q!$N$15 -> 4.226 | O87: =Q!$J$15 -> 1.709 | P87: Q 頁實績；預測＝前期 ×（1＋年增）
A88: Other 年增 | B88: % | E88: =Seg!$E$87/Seg!$N$87-1 -> 0.21131093 | F88: =Seg!$E$88 -> 0.21131093 | G88: =Seg!$G$87/Seg!$D$87-1 -> 0.21089241 | H88: =Seg!$F$88+(g_ot-Seg!$F$88)*1/4 -> 0.1709832 | I88: =Seg!$F$88+(g_ot-Seg!$F$88)*2/4 -> 0.13065547 | J88: =Seg!$F$88+(g_ot-Seg!$F$88)*3/4 -> 0.090327733 | K88: =Seg!$F$88+(g_ot-Seg!$F$88)*4/4 -> 0.05 | L88: =g_ot -> 0.05 | M88: =g_ot -> 0.05 | P88: E＝9M26 對 9M25（Prime Day 移入 Q2 的時點影響在九個月內抵銷）；F＝Q4 26 成長基準＝E（Derived）；收斂到 In 頁 g_ot
A89: Q4 26 零售營收校準係數（使情境 B 的 Q4 26 合併營收＝指引中點） | B89: x | F89: =(g26q4_mid-Thesis!$F$92-Thesis!$F$96)/(Seg!$O$77*(1+Seg!$F$78)+Seg!$O$79*(1+Seg!$F$80)+Seg!$O$81*(1+Seg!$F$82)+Seg!$O$83*(1+Seg!$F$84)+Seg!$O$85*(1+Seg!$F$86)+Seg!$O$87*(1+Seg!$F$88)) -> 0.9988001 | P89: Q4 26 合併營收目標＝指引中點 243.5 − 主頁情境 B 的 AWS Q4 26；三情境共用同一係數（修正二），零售不隨 AI 分拆變動
A90: 零售營收線合計（＝North America＋International） | B90: US$bn | C90: =Seg!$C$77+Seg!$C$79+Seg!$C$81+Seg!$C$83+Seg!$C$85+Seg!$C$87 -> 530.403 | D90: =Seg!$D$77+Seg!$D$79+Seg!$D$81+Seg!$D$83+Seg!$D$85+Seg!$D$87 -> 588.199 | E90: =Seg!$E$77+Seg!$E$79+Seg!$E$81+Seg!$E$83+Seg!$E$85+Seg!$E$87 -> 458.266 | F90: =Seg!$F$77+Seg!$F$79+Seg!$F$81+Seg!$F$83+Seg!$F$85+Seg!$F$87 -> 198.40366 | G90: =Seg!$G$77+Seg!$G$79+Seg!$G$81+Seg!$G$83+Seg!$G$85+Seg!$G$87 -> 656.66966 | H90: =Seg!$H$77+Seg!$H$79+Seg!$H$81+Seg!$H$83+Seg!$H$85+Seg!$H$87 -> 725.23054 | I90: =Seg!$I$77+Seg!$I$79+Seg!$I$81+Seg!$I$83+Seg!$I$85+Seg!$I$87 -> 791.59602 | J90: =Seg!$J$77+Seg!$J$79+Seg!$J$81+Seg!$J$83+Seg!$J$85+Seg!$J$87 -> 853.48545 | K90: =Seg!$K$77+Seg!$K$79+Seg!$K$81+Seg!$K$83+Seg!$K$85+Seg!$K$87 -> 908.53719 | L90: =Seg!$L$77+Seg!$L$79+Seg!$L$81+Seg!$L$83+Seg!$L$85+Seg!$L$87 -> 967.41543 | M90: =Seg!$M$77+Seg!$M$79+Seg!$M$81+Seg!$M$83+Seg!$M$85+Seg!$M$87 -> 1030.406 | N90: =Seg!$N$77+Seg!$N$79+Seg!$N$81+Seg!$N$83+Seg!$N$85+Seg!$N$87 -> 410.392 | O90: =Seg!$O$77+Seg!$O$79+Seg!$O$81+Seg!$O$83+Seg!$O$85+Seg!$O$87 -> 177.807
A91: 北美占零售營收比例（地區分攤） | B91: % | C91: =Q!$D$5/(Q!$D$5+Q!$D$6) -> 0.73057091 | D91: =Q!$E$5/(Q!$E$5+Q!$E$6) -> 0.72476322 | E91: =Q!$O$5/(Q!$O$5+Q!$O$6) -> 0.72702753 | F91: =Seg!$O$91 -> 0.71472439 | G91: =Seg!$G$92/Seg!$G$90 -> 0.72331031 | H91: =Seg!$G$91 -> 0.72331031 | I91: =Seg!$G$91 -> 0.72331031 | J91: =Seg!$G$91 -> 0.72331031 | K91: =Seg!$G$91 -> 0.72331031 | L91: =Seg!$G$91 -> 0.72331031 | M91: =Seg!$G$91 -> 0.72331031 | N91: =Q!$N$5/(Q!$N$5+Q!$N$6) -> 0.72911265 | O91: =Q!$J$5/(Q!$J$5+Q!$J$6) -> 0.71472439 | P91: Q4 26＝Q4 25 比例；2027 起固定為 FY2026（Derived）；各營收線不分地區揭露，故以本列分攤
A92: North America | B92: US$bn | C92: =Q!$D$5 -> 387.497 | D92: =Q!$E$5 -> 426.305 | E92: =Q!$O$5 -> 333.172 | F92: =Seg!$F$90*Seg!$F$91 -> 141.80393 | G92: =Seg!$E$92+Seg!$F$92 -> 474.97593 | H92: =Seg!$H$90*Seg!$H$91 -> 524.56673 | I92: =Seg!$I$90*Seg!$I$91 -> 572.56956 | J92: =Seg!$J$90*Seg!$J$91 -> 617.33483 | K92: =Seg!$K$90*Seg!$K$91 -> 657.15431 | L92: =Seg!$L$90*Seg!$L$91 -> 699.74156 | M92: =Seg!$M$90*Seg!$M$91 -> 745.30329 | N92: =Q!$N$5 -> 299.222 | O92: =Q!$J$5 -> 127.083 | P92: 官方分部；預測＝零售營收線合計 × 北美比例
A93: International | B93: US$bn | C93: =Q!$D$6 -> 142.906 | D93: =Q!$E$6 -> 161.894 | E93: =Q!$O$6 -> 125.094 | F93: =Seg!$F$90*(1-Seg!$F$91) -> 56.599724 | G93: =Seg!$E$93+Seg!$F$93 -> 181.69372 | H93: =Seg!$H$90*(1-Seg!$H$91) -> 200.66381 | I93: =Seg!$I$90*(1-Seg!$I$91) -> 219.02646 | J93: =Seg!$J$90*(1-Seg!$J$91) -> 236.15062 | K93: =Seg!$K$90*(1-Seg!$K$91) -> 251.38287 | L93: =Seg!$L$90*(1-Seg!$L$91) -> 267.67388 | M93: =Seg!$M$90*(1-Seg!$M$91) -> 285.10272 | N93: =Q!$N$6 -> 111.17 | O93: =Q!$J$6 -> 50.724 | P93: 官方分部；預測＝零售營收線合計 ×（1 − 北美比例）
A94: 廣告營收歸北美（＝廣告 × 北美比例） | B94: US$bn | C94: =Seg!$C$83*Seg!$C$91 -> 41.068313 | D94: =Seg!$D$83*Seg!$D$91 -> 49.744123 | E94: =Seg!$E$83*Seg!$E$91 -> 41.214464 | F94: =Seg!$F$83*Seg!$F$91 -> 18.231218 | G94: =Seg!$G$83*Seg!$G$91 -> 59.453966 | H94: =Seg!$H$83*Seg!$H$91 -> 69.771148 | I94: =Seg!$I$83*Seg!$I$91 -> 80.16855 | J94: =Seg!$J$83*Seg!$J$91 -> 90.150397 | K94: =Seg!$K$83*Seg!$K$91 -> 99.165436 | L94: =Seg!$L$83*Seg!$L$91 -> 109.08198 | M94: =Seg!$M$83*Seg!$M$91 -> 119.99018 | N94: =Seg!$N$83*Seg!$N$91 -> 34.500153 | O94: =Seg!$O$83*Seg!$O$91 -> 15.23578 | P94: 廣告營收依零售營收的地區比例分攤（Assumed；公司未分地區揭露）
A95: 廣告營收歸國際 | B95: US$bn | C95: =Seg!$C$83-Seg!$C$94 -> 15.145687 | D95: =Seg!$D$83-Seg!$D$94 -> 18.890877 | E95: =Seg!$E$83-Seg!$E$94 -> 15.474536 | F95: =Seg!$F$83-Seg!$F$94 -> 7.2768214 | G95: =Seg!$G$83-Seg!$G$94 -> 22.743073 | H95: =Seg!$H$83-Seg!$H$94 -> 26.689731 | I95: =Seg!$I$83-Seg!$I$94 -> 30.667075 | J95: =Seg!$J$83-Seg!$J$94 -> 34.485455 | K95: =Seg!$K$83-Seg!$K$94 -> 37.934001 | L95: =Seg!$L$83-Seg!$L$94 -> 41.727401 | M95: =Seg!$M$83-Seg!$M$94 -> 45.900141 | N95: =Seg!$N$83-Seg!$N$94 -> 12.817847 | O95: =Seg!$O$83-Seg!$O$94 -> 6.0812201
A96: 2. AWS（命題子列＋AWS 其他）與合併營收
A97: AWS AI（命題子列） | B97: US$bn | C97: =Thesis!$C$158 -> 2.3210054 | D97: =Thesis!$D$158 -> 8.7037701 | E97: =Thesis!$E$158 -> 16.200708 | F97: =Thesis!$F$158 -> 7.59676 | G97: =Thesis!$G$158 -> 23.797468 | H97: =Thesis!$H$158 -> 48.204028 | I97: =Thesis!$I$158 -> 77.408761 | J97: =Thesis!$J$158 -> 106.77294 | K97: =Thesis!$K$158 -> 131.81655 | L97: =Thesis!$L$158 -> 148.26704 | M97: =Thesis!$M$158 -> 156.09846 | N97: =Thesis!$N$158 -> 5.5486534 | O97: =Thesis!$O$158 -> 3.1551167 | P97: Thesis 頁
A98: AWS 其他 | B98: US$bn | C98: =Thesis!$C$162 -> 105.23499 | D98: =Thesis!$D$162 -> 120.02123 | E98: =Thesis!$E$162 -> 109.60229 | F98: =Thesis!$F$162 -> 36.97966 | G98: =Thesis!$G$162 -> 146.58195 | H98: =Thesis!$H$162 -> 164.96042 | I98: =Thesis!$I$162 -> 183.14786 | J98: =Thesis!$J$162 -> 200.57012 | K98: =Thesis!$K$162 -> 216.61573 | L98: =Thesis!$L$162 -> 233.94498 | M98: =Thesis!$M$162 -> 252.66058 | N98: =Thesis!$N$162 -> 87.597347 | O98: =Thesis!$O$162 -> 32.423883 | P98: Thesis 頁
A99: AWS | B99: US$bn | C99: =Q!$D$7 -> 107.556 | D99: =Q!$E$7 -> 128.725 | E99: =Q!$O$7 -> 125.803 | F99: =Seg!$F$97+Seg!$F$98 -> 44.57642 | G99: =Seg!$G$97+Seg!$G$98 -> 170.37942 | H99: =Seg!$H$97+Seg!$H$98 -> 213.16444 | I99: =Seg!$I$97+Seg!$I$98 -> 260.55663 | J99: =Seg!$J$97+Seg!$J$98 -> 307.34305 | K99: =Seg!$K$97+Seg!$K$98 -> 348.43227 | L99: =Seg!$L$97+Seg!$L$98 -> 382.21202 | M99: =Seg!$M$97+Seg!$M$98 -> 408.75905 | N99: =Q!$N$7 -> 93.146 | O99: =Q!$J$7 -> 35.579 | P99: 官方分部＝AWS 營收線
A100: 合併營收（實績＝公司揭露；預測＝營收線加總） | B100: US$bn | C100: =Q!$D$8 -> 637.959 | D100: =Q!$E$8 -> 716.924 | E100: =Q!$O$8 -> 584.069 | F100: =Seg!$F$90+Seg!$F$99 -> 242.98008 | G100: =Seg!$G$90+Seg!$G$99 -> 827.04908 | H100: =Seg!$H$90+Seg!$H$99 -> 938.39499 | I100: =Seg!$I$90+Seg!$I$99 -> 1052.1526 | J100: =Seg!$J$90+Seg!$J$99 -> 1160.8285 | K100: =Seg!$K$90+Seg!$K$99 -> 1256.9695 | L100: =Seg!$L$90+Seg!$L$99 -> 1349.6275 | M100: =Seg!$M$90+Seg!$M$99 -> 1439.1651 | N100: =Q!$N$8 -> 503.538 | O100: =Q!$J$8 -> 213.386
A101: 檢查（情境 C）：零售營收線合計 − (North America＋International) | B101: US$bn | C101: =Seg!$C$90-(Seg!$C$92+Seg!$C$93) -> 0 | D101: =Seg!$D$90-(Seg!$D$92+Seg!$D$93) -> 0 | E101: =Seg!$E$90-(Seg!$E$92+Seg!$E$93) -> 0 | F101: =Seg!$F$90-(Seg!$F$92+Seg!$F$93) -> 0 | G101: =Seg!$G$90-(Seg!$G$92+Seg!$G$93) -> 0 | H101: =Seg!$H$90-(Seg!$H$92+Seg!$H$93) -> 0 | I101: =Seg!$I$90-(Seg!$I$92+Seg!$I$93) -> 0 | J101: =Seg!$J$90-(Seg!$J$92+Seg!$J$93) -> 0 | K101: =Seg!$K$90-(Seg!$K$92+Seg!$K$93) -> 0 | L101: =Seg!$L$90-(Seg!$L$92+Seg!$L$93) -> 0 | M101: =Seg!$M$90-(Seg!$M$92+Seg!$M$93) -> 0 | N101: =Seg!$N$90-(Seg!$N$92+Seg!$N$93) -> 0 | O101: =Seg!$O$90-(Seg!$O$92+Seg!$O$93) -> 0
A102: 檢查（情境 C）：AWS AI＋AWS 其他 − AWS | B102: US$bn | C102: =Seg!$C$97+Seg!$C$98-Seg!$C$99 -> 0 | D102: =Seg!$D$97+Seg!$D$98-Seg!$D$99 -> 0 | E102: =Seg!$E$97+Seg!$E$98-Seg!$E$99 -> 0 | F102: =Seg!$F$97+Seg!$F$98-Seg!$F$99 -> 0 | G102: =Seg!$G$97+Seg!$G$98-Seg!$G$99 -> 0 | H102: =Seg!$H$97+Seg!$H$98-Seg!$H$99 -> 0 | I102: =Seg!$I$97+Seg!$I$98-Seg!$I$99 -> 0 | J102: =Seg!$J$97+Seg!$J$98-Seg!$J$99 -> 0 | K102: =Seg!$K$97+Seg!$K$98-Seg!$K$99 -> 0 | L102: =Seg!$L$97+Seg!$L$98-Seg!$L$99 -> 0 | M102: =Seg!$M$97+Seg!$M$98-Seg!$M$99 -> 0 | N102: =Seg!$N$97+Seg!$N$98-Seg!$N$99 -> 0 | O102: =Seg!$O$97+Seg!$O$98-Seg!$O$99 -> 0
A103: 檢查（情境 C）：分部合計 − 合併營收 | B103: US$bn | C103: =Seg!$C$92+Seg!$C$93+Seg!$C$99-Seg!$C$100 -> 0 | D103: =Seg!$D$92+Seg!$D$93+Seg!$D$99-Seg!$D$100 -> 0 | E103: =Seg!$E$92+Seg!$E$93+Seg!$E$99-Seg!$E$100 -> 0 | F103: =Seg!$F$92+Seg!$F$93+Seg!$F$99-Seg!$F$100 -> 0 | G103: =Seg!$G$92+Seg!$G$93+Seg!$G$99-Seg!$G$100 -> 0 | H103: =Seg!$H$92+Seg!$H$93+Seg!$H$99-Seg!$H$100 -> 0 | I103: =Seg!$I$92+Seg!$I$93+Seg!$I$99-Seg!$I$100 -> 0 | J103: =Seg!$J$92+Seg!$J$93+Seg!$J$99-Seg!$J$100 -> 0 | K103: =Seg!$K$92+Seg!$K$93+Seg!$K$99-Seg!$K$100 -> 0 | L103: =Seg!$L$92+Seg!$L$93+Seg!$L$99-Seg!$L$100 -> 0 | M103: =Seg!$M$92+Seg!$M$93+Seg!$M$99-Seg!$M$100 -> 0 | N103: =Seg!$N$92+Seg!$N$93+Seg!$N$99-Seg!$N$100 -> 0 | O103: =Seg!$O$92+Seg!$O$93+Seg!$O$99-Seg!$O$100 -> 0
A104: 合併營收年增 | B104: % | G104: =Seg!$G$100/Seg!$D$100-1 -> 0.15360774 | H104: =Seg!$H$100/Seg!$G$100-1 -> 0.13463035 | I104: =Seg!$I$100/Seg!$H$100-1 -> 0.12122577 | J104: =Seg!$J$100/Seg!$I$100-1 -> 0.10328906 | K104: =Seg!$K$100/Seg!$J$100-1 -> 0.08282098 | L104: =Seg!$L$100/Seg!$K$100-1 -> 0.073715394 | M104: =Seg!$M$100/Seg!$L$100-1 -> 0.066342454
A105: AWS 占合併營收 | B105: % | C105: =Seg!$C$99/Seg!$C$100 -> 0.16859391 | D105: =Seg!$D$99/Seg!$D$100 -> 0.17955181 | E105: =Seg!$E$99/Seg!$E$100 -> 0.21539065 | F105: =Seg!$F$99/Seg!$F$100 -> 0.1834571 | G105: =Seg!$G$99/Seg!$G$100 -> 0.20600884 | H105: =Seg!$H$99/Seg!$H$100 -> 0.22715855 | I105: =Seg!$I$99/Seg!$I$100 -> 0.24764147 | J105: =Seg!$J$99/Seg!$J$100 -> 0.26476181 | K105: =Seg!$K$99/Seg!$K$100 -> 0.27720027 | L105: =Seg!$L$99/Seg!$L$100 -> 0.28319817 | M105: =Seg!$M$99/Seg!$M$100 -> 0.28402513 | N105: =Seg!$N$99/Seg!$N$100 -> 0.18498306 | O105: =Seg!$O$99/Seg!$O$100 -> 0.1667354
A106: AWS AI 占 AWS | B106: % | C106: =Seg!$C$97/Seg!$C$99 -> 0.021579506 | D106: =Seg!$D$97/Seg!$D$99 -> 0.067615227 | E106: =Seg!$E$97/Seg!$E$99 -> 0.12877839 | F106: =Seg!$F$97/Seg!$F$99 -> 0.17042104 | G106: =Seg!$G$97/Seg!$G$99 -> 0.13967337 | H106: =Seg!$H$97/Seg!$H$99 -> 0.22613541 | I106: =Seg!$I$97/Seg!$I$99 -> 0.29708998 | J106: =Seg!$J$97/Seg!$J$99 -> 0.34740637 | K106: =Seg!$K$97/Seg!$K$99 -> 0.37831325 | L106: =Seg!$L$97/Seg!$L$99 -> 0.3879183 | M106: =Seg!$M$97/Seg!$M$99 -> 0.38188381 | N106: =Seg!$N$97/Seg!$N$99 -> 0.059569423 | O106: =Seg!$O$97/Seg!$O$99 -> 0.088679183

Sheet PL
A1: PL — 分部營收 → 分部營業利益 → 合併營業利益 → 業外、稅 → 淨利 → EPS。廣告利潤率 m_ad 驅動北美／國際利益率（廣告營收依零售地區比例分攤；零售本業利益率＝分部利益扣廣告利潤後的殘差）
A2: 第 4–10 列：跨情境核對（三情境絕對值合計；tools/segment_check 讀本區）；實績欄為公司揭露值的核對
A4: 跨情境核對（三情境絕對值合計；應全為 0）
A5: 項目 | B5: 單位 | C5: FY2024A | D5: FY2025A | E5: 9M26A | F5: Q4 26E | G5: FY2026E（9M 實績＋Q4 模型） | H5: FY2027E | I5: FY2028E | J5: FY2029E | K5: FY2030E | L5: FY2031E | M5: FY2032E | N5: 9M25A | O5: Q4 25A | P5: 說明
A6: 檢查：零售營收線合計 − (North America＋International) | B6: US$bn | C6: =ABS(PL!$C$28)+ABS(PL!$C$98)+ABS(PL!$C$168) -> 0 | D6: =ABS(PL!$D$28)+ABS(PL!$D$98)+ABS(PL!$D$168) -> 0 | E6: =ABS(PL!$E$28)+ABS(PL!$E$98)+ABS(PL!$E$168) -> 0 | F6: =ABS(PL!$F$28)+ABS(PL!$F$98)+ABS(PL!$F$168) -> 0 | G6: =ABS(PL!$G$28)+ABS(PL!$G$98)+ABS(PL!$G$168) -> 0 | H6: =ABS(PL!$H$28)+ABS(PL!$H$98)+ABS(PL!$H$168) -> 0 | I6: =ABS(PL!$I$28)+ABS(PL!$I$98)+ABS(PL!$I$168) -> 0 | J6: =ABS(PL!$J$28)+ABS(PL!$J$98)+ABS(PL!$J$168) -> 0 | K6: =ABS(PL!$K$28)+ABS(PL!$K$98)+ABS(PL!$K$168) -> 0 | L6: =ABS(PL!$L$28)+ABS(PL!$L$98)+ABS(PL!$L$168) -> 0 | M6: =ABS(PL!$M$28)+ABS(PL!$M$98)+ABS(PL!$M$168) -> 0 | N6: =ABS(PL!$N$28)+ABS(PL!$N$98)+ABS(PL!$N$168) -> 0 | O6: =ABS(PL!$O$28)+ABS(PL!$O$98)+ABS(PL!$O$168) -> 0
A7: 檢查：AWS AI＋AWS 其他 − AWS | B7: US$bn | C7: =ABS(PL!$C$29)+ABS(PL!$C$99)+ABS(PL!$C$169) -> 0 | D7: =ABS(PL!$D$29)+ABS(PL!$D$99)+ABS(PL!$D$169) -> 0 | E7: =ABS(PL!$E$29)+ABS(PL!$E$99)+ABS(PL!$E$169) -> 0 | F7: =ABS(PL!$F$29)+ABS(PL!$F$99)+ABS(PL!$F$169) -> 0 | G7: =ABS(PL!$G$29)+ABS(PL!$G$99)+ABS(PL!$G$169) -> 0 | H7: =ABS(PL!$H$29)+ABS(PL!$H$99)+ABS(PL!$H$169) -> 0 | I7: =ABS(PL!$I$29)+ABS(PL!$I$99)+ABS(PL!$I$169) -> 0 | J7: =ABS(PL!$J$29)+ABS(PL!$J$99)+ABS(PL!$J$169) -> 0 | K7: =ABS(PL!$K$29)+ABS(PL!$K$99)+ABS(PL!$K$169) -> 0 | L7: =ABS(PL!$L$29)+ABS(PL!$L$99)+ABS(PL!$L$169) -> 0 | M7: =ABS(PL!$M$29)+ABS(PL!$M$99)+ABS(PL!$M$169) -> 0 | N7: =ABS(PL!$N$29)+ABS(PL!$N$99)+ABS(PL!$N$169) -> 0 | O7: =ABS(PL!$O$29)+ABS(PL!$O$99)+ABS(PL!$O$169) -> 0
A8: 檢查：營收線合計（含 AWS）− 合併營收 | B8: US$bn | C8: =ABS(PL!$C$30)+ABS(PL!$C$100)+ABS(PL!$C$170) -> 0 | D8: =ABS(PL!$D$30)+ABS(PL!$D$100)+ABS(PL!$D$170) -> 0 | E8: =ABS(PL!$E$30)+ABS(PL!$E$100)+ABS(PL!$E$170) -> 0 | F8: =ABS(PL!$F$30)+ABS(PL!$F$100)+ABS(PL!$F$170) -> 0 | G8: =ABS(PL!$G$30)+ABS(PL!$G$100)+ABS(PL!$G$170) -> 0 | H8: =ABS(PL!$H$30)+ABS(PL!$H$100)+ABS(PL!$H$170) -> 0 | I8: =ABS(PL!$I$30)+ABS(PL!$I$100)+ABS(PL!$I$170) -> 0 | J8: =ABS(PL!$J$30)+ABS(PL!$J$100)+ABS(PL!$J$170) -> 0 | K8: =ABS(PL!$K$30)+ABS(PL!$K$100)+ABS(PL!$K$170) -> 0 | L8: =ABS(PL!$L$30)+ABS(PL!$L$100)+ABS(PL!$L$170) -> 0 | M8: =ABS(PL!$M$30)+ABS(PL!$M$100)+ABS(PL!$M$170) -> 0 | N8: =ABS(PL!$N$30)+ABS(PL!$N$100)+ABS(PL!$N$170) -> 0 | O8: =ABS(PL!$O$30)+ABS(PL!$O$100)+ABS(PL!$O$170) -> 0
A9: 檢查：分部合計 − 合併營收 | B9: US$bn | C9: =ABS(PL!$C$31)+ABS(PL!$C$101)+ABS(PL!$C$171) -> 0 | D9: =ABS(PL!$D$31)+ABS(PL!$D$101)+ABS(PL!$D$171) -> 0 | E9: =ABS(PL!$E$31)+ABS(PL!$E$101)+ABS(PL!$E$171) -> 0 | F9: =ABS(PL!$F$31)+ABS(PL!$F$101)+ABS(PL!$F$171) -> 0 | G9: =ABS(PL!$G$31)+ABS(PL!$G$101)+ABS(PL!$G$171) -> 0 | H9: =ABS(PL!$H$31)+ABS(PL!$H$101)+ABS(PL!$H$171) -> 0 | I9: =ABS(PL!$I$31)+ABS(PL!$I$101)+ABS(PL!$I$171) -> 0 | J9: =ABS(PL!$J$31)+ABS(PL!$J$101)+ABS(PL!$J$171) -> 0 | K9: =ABS(PL!$K$31)+ABS(PL!$K$101)+ABS(PL!$K$171) -> 0 | L9: =ABS(PL!$L$31)+ABS(PL!$L$101)+ABS(PL!$L$171) -> 0 | M9: =ABS(PL!$M$31)+ABS(PL!$M$101)+ABS(PL!$M$171) -> 0 | N9: =ABS(PL!$N$31)+ABS(PL!$N$101)+ABS(PL!$N$171) -> 0 | O9: =ABS(PL!$O$31)+ABS(PL!$O$101)+ABS(PL!$O$171) -> 0
A10: 檢查：分部營業利益合計 − 合併營業利益 | B10: US$bn | C10: =ABS(PL!$C$48)+ABS(PL!$C$118)+ABS(PL!$C$188) -> 0 | D10: =ABS(PL!$D$48)+ABS(PL!$D$118)+ABS(PL!$D$188) -> 0 | E10: =ABS(PL!$E$48)+ABS(PL!$E$118)+ABS(PL!$E$188) -> 0 | F10: =ABS(PL!$F$48)+ABS(PL!$F$118)+ABS(PL!$F$188) -> 0 | G10: =ABS(PL!$G$48)+ABS(PL!$G$118)+ABS(PL!$G$188) -> 0 | H10: =ABS(PL!$H$48)+ABS(PL!$H$118)+ABS(PL!$H$188) -> 0 | I10: =ABS(PL!$I$48)+ABS(PL!$I$118)+ABS(PL!$I$188) -> 0 | J10: =ABS(PL!$J$48)+ABS(PL!$J$118)+ABS(PL!$J$188) -> 0 | K10: =ABS(PL!$K$48)+ABS(PL!$K$118)+ABS(PL!$K$188) -> 0 | L10: =ABS(PL!$L$48)+ABS(PL!$L$118)+ABS(PL!$L$188) -> 0 | M10: =ABS(PL!$M$48)+ABS(PL!$M$118)+ABS(PL!$M$188) -> 0 | N10: =ABS(PL!$N$48)+ABS(PL!$N$118)+ABS(PL!$N$188) -> 0 | O10: =ABS(PL!$O$48)+ABS(PL!$O$118)+ABS(PL!$O$188) -> 0
A12: PL｜情境 A（樂觀）：分部營收 → 分部營業利益 → 合併營業利益 → 業外、稅 → 淨利 → EPS
A13: 項目 | B13: 單位 | C13: FY2024A | D13: FY2025A | E13: 9M26A | F13: Q4 26E | G13: FY2026E（9M 實績＋Q4 模型） | H13: FY2027E | I13: FY2028E | J13: FY2029E | K13: FY2030E | L13: FY2031E | M13: FY2032E | N13: 9M25A | O13: Q4 25A | P13: 說明 | R13: 2023 | S13: 2024 | T13: 2025 | U13: 2026 | V13: 2027 | W13: 2028 | X13: 2029 | Y13: 2030 | Z13: 2031 | AA13: 2032
A14: 1. 營收（10-K 營收線與官方分部）
A15: Online stores | B15: US$bn | C15: =Seg!$C$7 -> 247.029 | D15: =Seg!$D$7 -> 269.287 | E15: =Seg!$E$7 -> 203.156 | F15: =Seg!$F$7 -> 90.388464 | G15: =Seg!$G$7 -> 293.54446 | H15: =Seg!$H$7 -> 317.13448 | I15: =Seg!$I$7 -> 339.41058 | J15: =Seg!$J$7 -> 359.81625 | K15: =Seg!$K$7 -> 377.80706 | L15: =Seg!$L$7 -> 396.69741 | M15: =Seg!$M$7 -> 416.53228 | N15: =Seg!$N$7 -> 186.299 | O15: =Seg!$O$7 -> 82.988
A16: Physical stores | B16: US$bn | C16: =Seg!$C$9 -> 21.215 | D16: =Seg!$D$9 -> 22.561 | E16: =Seg!$E$9 -> 17.289 | F16: =Seg!$F$9 -> 6.0520551 | G16: =Seg!$G$9 -> 23.341055 | H16: =Seg!$H$9 -> 24.127024 | I16: =Seg!$I$9 -> 24.909917 | J16: =Seg!$J$9 -> 25.687715 | K16: =Seg!$K$9 -> 26.458346 | L16: =Seg!$L$9 -> 27.252097 | M16: =Seg!$M$9 -> 28.06966 | N16: =Seg!$N$9 -> 16.706 | O16: =Seg!$O$9 -> 5.855
A17: Third-party seller services | B17: US$bn | C17: =Seg!$C$11 -> 156.146 | D17: =Seg!$D$11 -> 172.162 | E17: =Seg!$E$11 -> 134.85 | F17: =Seg!$F$11 -> 59.605614 | G17: =Seg!$G$11 -> 194.45561 | H17: =Seg!$H$11 -> 216.80459 | I17: =Seg!$I$11 -> 238.47508 | J17: =Seg!$J$11 -> 258.73997 | K17: =Seg!$K$11 -> 276.85177 | L17: =Seg!$L$11 -> 296.2314 | M17: =Seg!$M$11 -> 316.9676 | N17: =Seg!$N$11 -> 119.346 | O17: =Seg!$O$11 -> 52.816
A18: Advertising services | B18: US$bn | C18: =Seg!$C$13 -> 56.214 | D18: =Seg!$D$13 -> 68.635 | E18: =Seg!$E$13 -> 56.689 | F18: =Seg!$F$13 -> 25.508039 | G18: =Seg!$G$13 -> 82.197039 | H18: =Seg!$H$13 -> 96.460878 | I18: =Seg!$I$13 -> 110.83562 | J18: =Seg!$J$13 -> 124.63585 | K18: =Seg!$K$13 -> 137.09944 | L18: =Seg!$L$13 -> 150.80938 | M18: =Seg!$M$13 -> 165.89032 | N18: =Seg!$N$13 -> 47.318 | O18: =Seg!$O$13 -> 21.317
A19: Subscription services | B19: US$bn | C19: =Seg!$C$15 -> 44.374 | D19: =Seg!$D$15 -> 49.619 | E19: =Seg!$E$15 -> 41.163 | F19: =Seg!$F$15 -> 14.781839 | G19: =Seg!$G$15 -> 55.944839 | H19: =Seg!$H$15 -> 62.288122 | I19: =Seg!$I$15 -> 68.449853 | J19: =Seg!$J$15 -> 74.231233 | K19: =Seg!$K$15 -> 79.427419 | L19: =Seg!$L$15 -> 84.987338 | M19: =Seg!$M$15 -> 90.936452 | N19: =Seg!$N$15 -> 36.497 | O19: =Seg!$O$15 -> 13.122
A20: Other | B20: US$bn | C20: =Seg!$C$17 -> 5.425 | D20: =Seg!$D$17 -> 5.935 | E20: =Seg!$E$17 -> 5.119 | F20: =Seg!$F$17 -> 2.0676464 | G20: =Seg!$G$17 -> 7.1866464 | H20: =Seg!$H$17 -> 8.4154422 | I20: =Seg!$I$17 -> 9.5149658 | J20: =Seg!$J$17 -> 10.374431 | K20: =Seg!$K$17 -> 10.893153 | L20: =Seg!$L$17 -> 11.43781 | M20: =Seg!$M$17 -> 12.009701 | N20: =Seg!$N$17 -> 4.226 | O20: =Seg!$O$17 -> 1.709
A21: AWS（營收線＝分部） | B21: US$bn | C21: =Seg!$C$29 -> 107.556 | D21: =Seg!$D$29 -> 128.725 | E21: =Seg!$E$29 -> 125.803 | F21: =Seg!$F$29 -> 46.711682 | G21: =Seg!$G$29 -> 172.51468 | H21: =Seg!$H$29 -> 236.19962 | I21: =Seg!$I$29 -> 307.34743 | J21: =Seg!$J$29 -> 378.01879 | K21: =Seg!$K$29 -> 439.4815 | L21: =Seg!$L$29 -> 486.65151 | M21: =Seg!$M$29 -> 519.5844 | N21: =Seg!$N$29 -> 93.146 | O21: =Seg!$O$29 -> 35.579
A22: North America | B22: US$bn | C22: =Seg!$C$22 -> 387.497 | D22: =Seg!$D$22 -> 426.305 | E22: =Seg!$E$22 -> 333.172 | F22: =Seg!$F$22 -> 141.80393 | G22: =Seg!$G$22 -> 474.97593 | H22: =Seg!$H$22 -> 524.56673 | I22: =Seg!$I$22 -> 572.56956 | J22: =Seg!$J$22 -> 617.33483 | K22: =Seg!$K$22 -> 657.15431 | L22: =Seg!$L$22 -> 699.74156 | M22: =Seg!$M$22 -> 745.30329 | N22: =Seg!$N$22 -> 299.222 | O22: =Seg!$O$22 -> 127.083
A23: International | B23: US$bn | C23: =Seg!$C$23 -> 142.906 | D23: =Seg!$D$23 -> 161.894 | E23: =Seg!$E$23 -> 125.094 | F23: =Seg!$F$23 -> 56.599724 | G23: =Seg!$G$23 -> 181.69372 | H23: =Seg!$H$23 -> 200.66381 | I23: =Seg!$I$23 -> 219.02646 | J23: =Seg!$J$23 -> 236.15062 | K23: =Seg!$K$23 -> 251.38287 | L23: =Seg!$L$23 -> 267.67388 | M23: =Seg!$M$23 -> 285.10272 | N23: =Seg!$N$23 -> 111.17 | O23: =Seg!$O$23 -> 50.724
A24: AWS | B24: US$bn | C24: =Seg!$C$29 -> 107.556 | D24: =Seg!$D$29 -> 128.725 | E24: =Seg!$E$29 -> 125.803 | F24: =Seg!$F$29 -> 46.711682 | G24: =Seg!$G$29 -> 172.51468 | H24: =Seg!$H$29 -> 236.19962 | I24: =Seg!$I$29 -> 307.34743 | J24: =Seg!$J$29 -> 378.01879 | K24: =Seg!$K$29 -> 439.4815 | L24: =Seg!$L$29 -> 486.65151 | M24: =Seg!$M$29 -> 519.5844 | N24: =Seg!$N$29 -> 93.146 | O24: =Seg!$O$29 -> 35.579
A25: AWS AI（命題子列） | B25: US$bn | C25: =Seg!$C$27 -> 2.3210054 | D25: =Seg!$D$27 -> 8.7037701 | E25: =Seg!$E$27 -> 16.200708 | F25: =Seg!$F$27 -> 9.732022 | G25: =Seg!$G$27 -> 25.93273 | H25: =Seg!$H$27 -> 71.239209 | I25: =Seg!$I$27 -> 124.19956 | J25: =Seg!$J$27 -> 177.44867 | K25: =Seg!$K$27 -> 222.86577 | L25: =Seg!$L$27 -> 252.70652 | M25: =Seg!$M$27 -> 266.92381 | N25: =Seg!$N$27 -> 5.5486534 | O25: =Seg!$O$27 -> 3.1551167
A26: AWS 其他 | B26: US$bn | C26: =Seg!$C$28 -> 105.23499 | D26: =Seg!$D$28 -> 120.02123 | E26: =Seg!$E$28 -> 109.60229 | F26: =Seg!$F$28 -> 36.97966 | G26: =Seg!$G$28 -> 146.58195 | H26: =Seg!$H$28 -> 164.96042 | I26: =Seg!$I$28 -> 183.14786 | J26: =Seg!$J$28 -> 200.57012 | K26: =Seg!$K$28 -> 216.61573 | L26: =Seg!$L$28 -> 233.94498 | M26: =Seg!$M$28 -> 252.66058 | N26: =Seg!$N$28 -> 87.597347 | O26: =Seg!$O$28 -> 32.423883
A27: 合併營收 | B27: US$bn | C27: =Seg!$C$30 -> 637.959 | D27: =Seg!$D$30 -> 716.924 | E27: =Seg!$E$30 -> 584.069 | F27: =Seg!$F$30 -> 245.11534 | G27: =Seg!$G$30 -> 829.18434 | H27: =Seg!$H$30 -> 961.43017 | I27: =Seg!$I$30 -> 1098.9434 | J27: =Seg!$J$30 -> 1231.5042 | K27: =Seg!$K$30 -> 1348.0187 | L27: =Seg!$L$30 -> 1454.0669 | M27: =Seg!$M$30 -> 1549.9904 | N27: =Seg!$N$30 -> 503.538 | O27: =Seg!$O$30 -> 213.386
A28: 檢查（情境 A）：零售營收線合計 − (North America＋International) | B28: US$bn | C28: =PL!$C$15+PL!$C$16+PL!$C$17+PL!$C$18+PL!$C$19+PL!$C$20-(PL!$C$22+PL!$C$23) -> 0 | D28: =PL!$D$15+PL!$D$16+PL!$D$17+PL!$D$18+PL!$D$19+PL!$D$20-(PL!$D$22+PL!$D$23) -> 0 | E28: =PL!$E$15+PL!$E$16+PL!$E$17+PL!$E$18+PL!$E$19+PL!$E$20-(PL!$E$22+PL!$E$23) -> 0 | F28: =PL!$F$15+PL!$F$16+PL!$F$17+PL!$F$18+PL!$F$19+PL!$F$20-(PL!$F$22+PL!$F$23) -> 0 | G28: =PL!$G$15+PL!$G$16+PL!$G$17+PL!$G$18+PL!$G$19+PL!$G$20-(PL!$G$22+PL!$G$23) -> 0 | H28: =PL!$H$15+PL!$H$16+PL!$H$17+PL!$H$18+PL!$H$19+PL!$H$20-(PL!$H$22+PL!$H$23) -> 0 | I28: =PL!$I$15+PL!$I$16+PL!$I$17+PL!$I$18+PL!$I$19+PL!$I$20-(PL!$I$22+PL!$I$23) -> 0 | J28: =PL!$J$15+PL!$J$16+PL!$J$17+PL!$J$18+PL!$J$19+PL!$J$20-(PL!$J$22+PL!$J$23) -> 0 | K28: =PL!$K$15+PL!$K$16+PL!$K$17+PL!$K$18+PL!$K$19+PL!$K$20-(PL!$K$22+PL!$K$23) -> 0 | L28: =PL!$L$15+PL!$L$16+PL!$L$17+PL!$L$18+PL!$L$19+PL!$L$20-(PL!$L$22+PL!$L$23) -> 0 | M28: =PL!$M$15+PL!$M$16+PL!$M$17+PL!$M$18+PL!$M$19+PL!$M$20-(PL!$M$22+PL!$M$23) -> 0 | N28: =PL!$N$15+PL!$N$16+PL!$N$17+PL!$N$18+PL!$N$19+PL!$N$20-(PL!$N$22+PL!$N$23) -> 0 | O28: =PL!$O$15+PL!$O$16+PL!$O$17+PL!$O$18+PL!$O$19+PL!$O$20-(PL!$O$22+PL!$O$23) -> 0
A29: 檢查（情境 A）：AWS AI＋AWS 其他 − AWS | B29: US$bn | C29: =PL!$C$25+PL!$C$26-PL!$C$24 -> 0 | D29: =PL!$D$25+PL!$D$26-PL!$D$24 -> 0 | E29: =PL!$E$25+PL!$E$26-PL!$E$24 -> 0 | F29: =PL!$F$25+PL!$F$26-PL!$F$24 -> 0 | G29: =PL!$G$25+PL!$G$26-PL!$G$24 -> 0 | H29: =PL!$H$25+PL!$H$26-PL!$H$24 -> 0 | I29: =PL!$I$25+PL!$I$26-PL!$I$24 -> 0 | J29: =PL!$J$25+PL!$J$26-PL!$J$24 -> 0 | K29: =PL!$K$25+PL!$K$26-PL!$K$24 -> 0 | L29: =PL!$L$25+PL!$L$26-PL!$L$24 -> 0 | M29: =PL!$M$25+PL!$M$26-PL!$M$24 -> 0 | N29: =PL!$N$25+PL!$N$26-PL!$N$24 -> 0 | O29: =PL!$O$25+PL!$O$26-PL!$O$24 -> 0
A30: 檢查（情境 A）：營收線合計（含 AWS）− 合併營收 | B30: US$bn | C30: =PL!$C$15+PL!$C$16+PL!$C$17+PL!$C$18+PL!$C$19+PL!$C$20+PL!$C$21-PL!$C$27 -> 0 | D30: =PL!$D$15+PL!$D$16+PL!$D$17+PL!$D$18+PL!$D$19+PL!$D$20+PL!$D$21-PL!$D$27 -> 0 | E30: =PL!$E$15+PL!$E$16+PL!$E$17+PL!$E$18+PL!$E$19+PL!$E$20+PL!$E$21-PL!$E$27 -> 0 | F30: =PL!$F$15+PL!$F$16+PL!$F$17+PL!$F$18+PL!$F$19+PL!$F$20+PL!$F$21-PL!$F$27 -> 0 | G30: =PL!$G$15+PL!$G$16+PL!$G$17+PL!$G$18+PL!$G$19+PL!$G$20+PL!$G$21-PL!$G$27 -> 0 | H30: =PL!$H$15+PL!$H$16+PL!$H$17+PL!$H$18+PL!$H$19+PL!$H$20+PL!$H$21-PL!$H$27 -> 0 | I30: =PL!$I$15+PL!$I$16+PL!$I$17+PL!$I$18+PL!$I$19+PL!$I$20+PL!$I$21-PL!$I$27 -> 0 | J30: =PL!$J$15+PL!$J$16+PL!$J$17+PL!$J$18+PL!$J$19+PL!$J$20+PL!$J$21-PL!$J$27 -> 0 | K30: =PL!$K$15+PL!$K$16+PL!$K$17+PL!$K$18+PL!$K$19+PL!$K$20+PL!$K$21-PL!$K$27 -> 0 | L30: =PL!$L$15+PL!$L$16+PL!$L$17+PL!$L$18+PL!$L$19+PL!$L$20+PL!$L$21-PL!$L$27 -> 0 | M30: =PL!$M$15+PL!$M$16+PL!$M$17+PL!$M$18+PL!$M$19+PL!$M$20+PL!$M$21-PL!$M$27 -> 0 | N30: =PL!$N$15+PL!$N$16+PL!$N$17+PL!$N$18+PL!$N$19+PL!$N$20+PL!$N$21-PL!$N$27 -> 0 | O30: =PL!$O$15+PL!$O$16+PL!$O$17+PL!$O$18+PL!$O$19+PL!$O$20+PL!$O$21-PL!$O$27 -> 0
A31: 檢查（情境 A）：分部合計 − 合併營收 | B31: US$bn | C31: =PL!$C$22+PL!$C$23+PL!$C$24-PL!$C$27 -> 0 | D31: =PL!$D$22+PL!$D$23+PL!$D$24-PL!$D$27 -> 0 | E31: =PL!$E$22+PL!$E$23+PL!$E$24-PL!$E$27 -> 0 | F31: =PL!$F$22+PL!$F$23+PL!$F$24-PL!$F$27 -> 0 | G31: =PL!$G$22+PL!$G$23+PL!$G$24-PL!$G$27 -> 0 | H31: =PL!$H$22+PL!$H$23+PL!$H$24-PL!$H$27 -> 0 | I31: =PL!$I$22+PL!$I$23+PL!$I$24-PL!$I$27 -> 0 | J31: =PL!$J$22+PL!$J$23+PL!$J$24-PL!$J$27 -> 0 | K31: =PL!$K$22+PL!$K$23+PL!$K$24-PL!$K$27 -> 0 | L31: =PL!$L$22+PL!$L$23+PL!$L$24-PL!$L$27 -> 0 | M31: =PL!$M$22+PL!$M$23+PL!$M$24-PL!$M$27 -> 0 | N31: =PL!$N$22+PL!$N$23+PL!$N$24-PL!$N$27 -> 0 | O31: =PL!$O$22+PL!$O$23+PL!$O$24-PL!$O$27 -> 0
A32: 2. 分部營業利益（廣告利潤率 m_ad 計入北美／國際；零售本業利益率＝殘差；自用 AI 成本按北美比例分攤）
A33: North America：廣告利潤（廣告營收 × m_ad） | B33: US$bn | C33: =Seg!$C$24*m_ad -> 20.534156 | D33: =Seg!$D$24*m_ad -> 24.872062 | E33: =Seg!$E$24*m_ad -> 20.607232 | F33: =Seg!$F$24*m_ad -> 9.115609 | G33: =Seg!$G$24*m_ad -> 29.726983 | H33: =Seg!$H$24*m_ad -> 34.885574 | I33: =Seg!$I$24*m_ad -> 40.084275 | J33: =Seg!$J$24*m_ad -> 45.075198 | K33: =Seg!$K$24*m_ad -> 49.582718 | L33: =Seg!$L$24*m_ad -> 54.54099 | M33: =Seg!$M$24*m_ad -> 59.995089 | N33: =Seg!$N$24*m_ad -> 17.250076 | O33: =Seg!$O$24*m_ad -> 7.6178899
A34: North America：零售本業營收（分部 − 廣告） | B34: US$bn | C34: =Seg!$C$22-Seg!$C$24 -> 346.42869 | D34: =Seg!$D$22-Seg!$D$24 -> 376.56088 | E34: =Seg!$E$22-Seg!$E$24 -> 291.95754 | F34: =Seg!$F$22-Seg!$F$24 -> 123.57272 | G34: =Seg!$G$22-Seg!$G$24 -> 415.52197 | H34: =Seg!$H$22-Seg!$H$24 -> 454.79558 | I34: =Seg!$I$22-Seg!$I$24 -> 492.40101 | J34: =Seg!$J$22-Seg!$J$24 -> 527.18443 | K34: =Seg!$K$22-Seg!$K$24 -> 557.98888 | L34: =Seg!$L$22-Seg!$L$24 -> 590.65958 | M34: =Seg!$M$22-Seg!$M$24 -> 625.31311 | N34: =Seg!$N$22-Seg!$N$24 -> 264.72185 | O34: =Seg!$O$22-Seg!$O$24 -> 111.84722
A35: North America：自用 AI 成本淨額分攤 | B35: US$bn | C35: =Thesis!$C$57*Seg!$C$21 -> 0.12361744 | D35: =Thesis!$D$57*Seg!$D$21 -> 0.60019805 | E35: =Thesis!$E$57*Seg!$E$21 -> 1.7968458 | F35: =Thesis!$F$57*Seg!$F$21 -> 0.71533676 | G35: =Thesis!$G$57*Seg!$G$21 -> 2.5115887 | H35: =Thesis!$H$57*Seg!$H$21 -> 6.1610424 | I35: =Thesis!$I$57*Seg!$I$21 -> 12.114483 | J35: =Thesis!$J$57*Seg!$J$21 -> 17.221766 | K35: =Thesis!$K$57*Seg!$K$21 -> 22.179612 | L35: =Thesis!$L$57*Seg!$L$21 -> 25.573587 | M35: =Thesis!$M$57*Seg!$M$21 -> 27.254031 | N35: =Thesis!$N$57*Seg!$N$21 -> 0.41331982 | O35: =Thesis!$O$57*Seg!$O$21 -> 0.1867212
A36: North America：零售本業利益率（實績＝殘差，Derived） | B36: % | C36: =(PL!$C$37-PL!$C$33+PL!$C$35)/PL!$C$34 -> 0.013152667 | D36: =(PL!$D$37-PL!$D$33+PL!$D$35)/PL!$D$34 -> 0.014199925 | E36: =(PL!$E$37-PL!$E$33+PL!$E$35)/PL!$E$34 -> 0.025012589 | F36: =PL!$O$36+(PL!$E$36-PL!$N$36) -> 0.056191212 | G36: =(PL!$G$37-PL!$G$33+PL!$G$35)/PL!$G$34 -> 0.034273948 | H36: =PL!$G$36+step_na -> 0.037273948 | I36: =PL!$H$36+step_na -> 0.040273948 | J36: =PL!$I$36+step_na -> 0.043273948 | K36: =PL!$J$36+step_na -> 0.046273948 | L36: =PL!$K$36 -> 0.046273948 | M36: =PL!$L$36 -> 0.046273948 | N36: =(PL!$N$37-PL!$N$33+PL!$N$35)/PL!$N$34 -> 0.0049495105 | O36: =(PL!$O$37-PL!$O$33+PL!$O$35)/PL!$O$34 -> 0.036128133 | P36: Q4 26＝Q4 25＋(9M26 − 9M25)；2027–2030 每年＋In 頁 step；之後持平
A37: North America 營業利益 | B37: US$bn | C37: =Q!$D$23 -> 24.967 | D37: =Q!$E$23 -> 29.619 | E37: =Q!$O$23 -> 26.113 | F37: =PL!$F$33+PL!$F$34*PL!$F$36-PL!$F$35 -> 15.343973 | G37: =PL!$E$37+PL!$F$37 -> 41.456973 | H37: =PL!$H$33+PL!$H$34*PL!$H$36-PL!$H$35 -> 45.676559 | I37: =PL!$I$33+PL!$I$34*PL!$I$36-PL!$I$35 -> 47.800725 | J37: =PL!$J$33+PL!$J$34*PL!$J$36-PL!$J$35 -> 50.666784 | K37: =PL!$K$33+PL!$K$34*PL!$K$36-PL!$K$35 -> 53.223455 | L37: =PL!$L$33+PL!$L$34*PL!$L$36-PL!$L$35 -> 56.299554 | M37: =PL!$M$33+PL!$M$34*PL!$M$36-PL!$M$35 -> 61.676765 | N37: =Q!$N$23 -> 18.147 | O37: =Q!$J$23 -> 11.472
A38: International：廣告利潤（廣告營收 × m_ad） | B38: US$bn | C38: =Seg!$C$25*m_ad -> 7.5728436 | D38: =Seg!$D$25*m_ad -> 9.4454383 | E38: =Seg!$E$25*m_ad -> 7.7372681 | F38: =Seg!$F$25*m_ad -> 3.6384107 | G38: =Seg!$G$25*m_ad -> 11.371537 | H38: =Seg!$H$25*m_ad -> 13.344865 | I38: =Seg!$I$25*m_ad -> 15.333537 | J38: =Seg!$J$25*m_ad -> 17.242728 | K38: =Seg!$K$25*m_ad -> 18.967 | L38: =Seg!$L$25*m_ad -> 20.8637 | M38: =Seg!$M$25*m_ad -> 22.95007 | N38: =Seg!$N$25*m_ad -> 6.4089237 | O38: =Seg!$O$25*m_ad -> 3.0406101
A39: International：零售本業營收（分部 − 廣告） | B39: US$bn | C39: =Seg!$C$23-Seg!$C$25 -> 127.76031 | D39: =Seg!$D$23-Seg!$D$25 -> 143.00312 | E39: =Seg!$E$23-Seg!$E$25 -> 109.61946 | F39: =Seg!$F$23-Seg!$F$25 -> 49.322903 | G39: =Seg!$G$23-Seg!$G$25 -> 158.95065 | H39: =Seg!$H$23-Seg!$H$25 -> 173.97408 | I39: =Seg!$I$23-Seg!$I$25 -> 188.35938 | J39: =Seg!$J$23-Seg!$J$25 -> 201.66517 | K39: =Seg!$K$23-Seg!$K$25 -> 213.44887 | L39: =Seg!$L$23-Seg!$L$25 -> 225.94648 | M39: =Seg!$M$23-Seg!$M$25 -> 239.20258 | N39: =Seg!$N$23-Seg!$N$25 -> 98.352153 | O39: =Seg!$O$23-Seg!$O$25 -> 44.64278
A40: International：自用 AI 成本淨額分攤 | B40: US$bn | C40: =Thesis!$C$57*(1-Seg!$C$21) -> 0.04558919 | D40: =Thesis!$D$57*(1-Seg!$D$21) -> 0.22793179 | E40: =Thesis!$E$57*(1-Seg!$E$21) -> 0.6746504 | F40: =Thesis!$F$57*(1-Seg!$F$21) -> 0.28552003 | G40: =Thesis!$G$57*(1-Seg!$G$21) -> 0.96076426 | H40: =Thesis!$H$57*(1-Seg!$H$21) -> 2.3567988 | I40: =Thesis!$I$57*(1-Seg!$I$21) -> 4.6341834 | J40: =Thesis!$J$57*(1-Seg!$J$21) -> 6.5878849 | K40: =Thesis!$K$57*(1-Seg!$K$21) -> 8.4844219 | L40: =Thesis!$L$57*(1-Seg!$L$21) -> 9.7827276 | M40: =Thesis!$M$57*(1-Seg!$M$21) -> 10.425552 | N40: =Thesis!$N$57*(1-Seg!$N$21) -> 0.15356078 | O40: =Thesis!$O$57*(1-Seg!$O$21) -> 0.074528035
A41: International：零售本業利益率（實績＝殘差，Derived） | B41: % | C41: =(PL!$C$42-PL!$C$38+PL!$C$40)/PL!$C$39 -> -0.029236422 | D41: =(PL!$D$42-PL!$D$38+PL!$D$40)/PL!$D$39 -> -0.031240622 | E41: =(PL!$E$42-PL!$E$38+PL!$E$40)/PL!$E$39 -> -0.021361331 | F41: =PL!$O$41+(PL!$E$41-PL!$N$41) -> -0.038625549 | G41: =(PL!$G$42-PL!$G$38+PL!$G$40)/PL!$G$39 -> -0.026687566 | H41: =PL!$G$41+step_in -> -0.026687566 | I41: =PL!$H$41+step_in -> -0.026687566 | J41: =PL!$I$41+step_in -> -0.026687566 | K41: =PL!$J$41+step_in -> -0.026687566 | L41: =PL!$K$41 -> -0.026687566 | M41: =PL!$L$41 -> -0.026687566 | N41: =(PL!$N$42-PL!$N$38+PL!$N$40)/PL!$N$39 -> -0.025880094 | O41: =(PL!$O$42-PL!$O$38+PL!$O$40)/PL!$O$39 -> -0.043144312 | P41: Q4 26＝Q4 25＋(9M26 − 9M25)；2027–2030 每年＋In 頁 step；之後持平
A42: International 營業利益 | B42: US$bn | C42: =Q!$D$24 -> 3.792 | D42: =Q!$E$24 -> 4.75 | E42: =Q!$O$24 -> 4.721 | F42: =PL!$F$38+PL!$F$39*PL!$F$41-PL!$F$40 -> 1.4477665 | G42: =PL!$E$42+PL!$F$42 -> 6.1687665 | H42: =PL!$H$38+PL!$H$39*PL!$H$41-PL!$H$40 -> 6.3451216 | I42: =PL!$I$38+PL!$I$39*PL!$I$41-PL!$I$40 -> 5.6725005 | J42: =PL!$J$38+PL!$J$39*PL!$J$41-PL!$J$40 -> 5.2728903 | K42: =PL!$K$38+PL!$K$39*PL!$K$41-PL!$K$40 -> 4.7861477 | L42: =PL!$L$38+PL!$L$39*PL!$L$41-PL!$L$40 -> 5.0510114 | M42: =PL!$M$38+PL!$M$39*PL!$M$41-PL!$M$40 -> 6.1407838 | N42: =Q!$N$24 -> 3.71 | O42: =Q!$J$24 -> 1.04
A43: AWS AI 營業利益（命題子列） | B43: US$bn | C43: =Thesis!$C$54 -> 1.6441788 | D43: =Thesis!$D$54 -> 5.3912507 | E43: =Thesis!$E$54 -> 6.3147234 | F43: =Thesis!$F$54 -> 5.7285949 | G43: =Thesis!$G$54 -> 12.043318 | H43: =Thesis!$H$54 -> 37.167845 | I43: =Thesis!$I$54 -> 57.204898 | J43: =Thesis!$J$54 -> 82.210066 | K43: =Thesis!$K$54 -> 100.20963 | L43: =Thesis!$L$54 -> 111.28126 | M43: =Thesis!$M$54 -> 116.20548 | N43: =Thesis!$N$54 -> 3.281131 | O43: =Thesis!$O$54 -> 2.1101197
A44: AWS 其他營業利益 | B44: US$bn | C44: =Thesis!$C$59 -> 38.189821 | D44: =Thesis!$D$59 -> 40.214749 | E44: =Thesis!$E$59 -> 42.240277 | F44: =Thesis!$F$59 -> 13.694314 | G44: =Thesis!$G$59 -> 55.934591 | H44: =Thesis!$H$59 -> 61.088168 | I44: =Thesis!$I$59 -> 67.823348 | J44: =Thesis!$J$59 -> 74.275159 | K44: =Thesis!$K$59 -> 80.217172 | L44: =Thesis!$L$59 -> 86.634546 | M44: =Thesis!$M$59 -> 93.565309 | N44: =Thesis!$N$59 -> 29.859869 | O44: =Thesis!$O$59 -> 10.35488
A45: AWS 營業利益 | B45: US$bn | C45: =Q!$D$25 -> 39.834 | D45: =Q!$E$25 -> 45.606 | E45: =Q!$O$25 -> 48.555 | F45: =PL!$F$43+PL!$F$44 -> 19.422909 | G45: =PL!$G$43+PL!$G$44 -> 67.977909 | H45: =PL!$H$43+PL!$H$44 -> 98.256013 | I45: =PL!$I$43+PL!$I$44 -> 125.02825 | J45: =PL!$J$43+PL!$J$44 -> 156.48523 | K45: =PL!$K$43+PL!$K$44 -> 180.42681 | L45: =PL!$L$43+PL!$L$44 -> 197.91581 | M45: =PL!$M$43+PL!$M$44 -> 209.77079 | N45: =Q!$N$25 -> 33.141 | O45: =Q!$J$25 -> 12.465
A46: 未分攤（公司層；Amazon 為 0） | B46: US$bn | C46: =Q!$D$27 -> 0 | D46: =Q!$E$27 -> 0 | E46: =Q!$O$27 -> 0 | F46: 0 | G46: =PL!$E$46+PL!$F$46 -> 0 | H46: 0 | I46: 0 | J46: 0 | K46: 0 | L46: 0 | M46: 0 | N46: =Q!$N$27 -> 0 | O46: =Q!$J$27 -> 0
A47: 合併營業利益 | B47: US$bn | C47: =Q!$D$26 -> 68.593 | D47: =Q!$E$26 -> 79.975 | E47: =Q!$O$26 -> 79.389 | F47: =PL!$F$37+PL!$F$42+PL!$F$45+PL!$F$46 -> 36.214648 | G47: =PL!$G$37+PL!$G$42+PL!$G$45+PL!$G$46 -> 115.60365 | H47: =PL!$H$37+PL!$H$42+PL!$H$45+PL!$H$46 -> 150.27769 | I47: =PL!$I$37+PL!$I$42+PL!$I$45+PL!$I$46 -> 178.50147 | J47: =PL!$J$37+PL!$J$42+PL!$J$45+PL!$J$46 -> 212.4249 | K47: =PL!$K$37+PL!$K$42+PL!$K$45+PL!$K$46 -> 238.43641 | L47: =PL!$L$37+PL!$L$42+PL!$L$45+PL!$L$46 -> 259.26638 | M47: =PL!$M$37+PL!$M$42+PL!$M$45+PL!$M$46 -> 277.58834 | N47: =Q!$N$26 -> 54.998 | O47: =Q!$J$26 -> 24.977
A48: 檢查（情境 A）：分部營業利益合計 − 合併營業利益 | B48: US$bn | C48: =PL!$C$37+PL!$C$42+PL!$C$45+PL!$C$46-PL!$C$47 -> 0 | D48: =PL!$D$37+PL!$D$42+PL!$D$45+PL!$D$46-PL!$D$47 -> 0 | E48: =PL!$E$37+PL!$E$42+PL!$E$45+PL!$E$46-PL!$E$47 -> 0 | F48: =PL!$F$37+PL!$F$42+PL!$F$45+PL!$F$46-PL!$F$47 -> 0 | G48: =PL!$G$37+PL!$G$42+PL!$G$45+PL!$G$46-PL!$G$47 -> 0 | H48: =PL!$H$37+PL!$H$42+PL!$H$45+PL!$H$46-PL!$H$47 -> 0 | I48: =PL!$I$37+PL!$I$42+PL!$I$45+PL!$I$46-PL!$I$47 -> 0 | J48: =PL!$J$37+PL!$J$42+PL!$J$45+PL!$J$46-PL!$J$47 -> 0 | K48: =PL!$K$37+PL!$K$42+PL!$K$45+PL!$K$46-PL!$K$47 -> 0 | L48: =PL!$L$37+PL!$L$42+PL!$L$45+PL!$L$46-PL!$L$47 -> 0 | M48: =PL!$M$37+PL!$M$42+PL!$M$45+PL!$M$46-PL!$M$47 -> 0 | N48: =PL!$N$37+PL!$N$42+PL!$N$45+PL!$N$46-PL!$N$47 -> 0 | O48: =PL!$O$37+PL!$O$42+PL!$O$45+PL!$O$46-PL!$O$47 -> 0
A49: 自用 AI 影子效益（讀法 2；非財報營收；按北美比例分攤到北美／國際） | B49: US$bn | C49: =Thesis!$C$56 -> 0 | D49: =Thesis!$D$56 -> 0 | E49: =Thesis!$E$56 -> 0 | F49: =Thesis!$F$56 -> 2.0418127 | G49: =Thesis!$G$56 -> 2.0418127 | H49: =Thesis!$H$56 -> 13.48741 | I49: =Thesis!$I$56 -> 22.207552 | J49: =Thesis!$J$56 -> 30.975237 | K49: =Thesis!$K$56 -> 38.45335 | L49: =Thesis!$L$56 -> 43.366753 | M49: =Thesis!$M$56 -> 45.707689 | N49: =Thesis!$N$56 -> 0 | O49: =Thesis!$O$56 -> 0 | P49: 營收列與分部對帳不動
A50: 營業利益（評價口徑＝合併營業利益＋自用 AI 影子效益） | B50: US$bn | C50: =PL!$C$47+PL!$C$49 -> 68.593 | D50: =PL!$D$47+PL!$D$49 -> 79.975 | E50: =PL!$E$47+PL!$E$49 -> 79.389 | F50: =PL!$F$47+PL!$F$49 -> 38.256461 | G50: =PL!$G$47+PL!$G$49 -> 117.64546 | H50: =PL!$H$47+PL!$H$49 -> 163.7651 | I50: =PL!$I$47+PL!$I$49 -> 200.70902 | J50: =PL!$J$47+PL!$J$49 -> 243.40014 | K50: =PL!$K$47+PL!$K$49 -> 276.88976 | L50: =PL!$L$47+PL!$L$49 -> 302.63313 | M50: =PL!$M$47+PL!$M$49 -> 323.29603 | N50: =PL!$N$47+PL!$N$49 -> 54.998 | O50: =PL!$O$47+PL!$O$49 -> 24.977
A51: North America 營業利益率 | B51: % | C51: =PL!$C$37/PL!$C$22 -> 0.064431467 | D51: =PL!$D$37/PL!$D$22 -> 0.069478425 | E51: =PL!$E$37/PL!$E$22 -> 0.078376934 | F51: =PL!$F$37/PL!$F$22 -> 0.10820555 | G51: =PL!$G$37/PL!$G$22 -> 0.08728226 | H51: =PL!$H$37/PL!$H$22 -> 0.08707483 | I51: =PL!$I$37/PL!$I$22 -> 0.083484572 | J51: =PL!$J$37/PL!$J$22 -> 0.082073426 | K51: =PL!$K$37/PL!$K$22 -> 0.080990802 | L51: =PL!$L$37/PL!$L$22 -> 0.08045764 | M51: =PL!$M$37/PL!$M$22 -> 0.082753915 | N51: =PL!$N$37/PL!$N$22 -> 0.060647279 | O51: =PL!$O$37/PL!$O$22 -> 0.090271712
A52: International 營業利益率 | B52: % | C52: =PL!$C$42/PL!$C$23 -> 0.026534925 | D52: =PL!$D$42/PL!$D$23 -> 0.029340186 | E52: =PL!$E$42/PL!$E$23 -> 0.03773962 | F52: =PL!$F$42/PL!$F$23 -> 0.025579038 | G52: =PL!$G$42/PL!$G$23 -> 0.033951456 | H52: =PL!$H$42/PL!$H$23 -> 0.031620657 | I52: =PL!$I$42/PL!$I$23 -> 0.0258987 | J52: =PL!$J$42/PL!$J$23 -> 0.022328504 | K52: =PL!$K$42/PL!$K$23 -> 0.019039275 | L52: =PL!$L$42/PL!$L$23 -> 0.01887002 | M52: =PL!$M$42/PL!$M$23 -> 0.021538847 | N52: =PL!$N$42/PL!$N$23 -> 0.033372313 | O52: =PL!$O$42/PL!$O$23 -> 0.020503115
A53: AWS 營業利益率 | B53: % | C53: =PL!$C$45/PL!$C$24 -> 0.37035591 | D53: =PL!$D$45/PL!$D$24 -> 0.35429015 | E53: =PL!$E$45/PL!$E$24 -> 0.38596059 | F53: =PL!$F$45/PL!$F$24 -> 0.4158041 | G53: =PL!$G$45/PL!$G$24 -> 0.3940413 | H53: =PL!$H$45/PL!$H$24 -> 0.41598717 | I53: =PL!$I$45/PL!$I$24 -> 0.40679776 | J53: =PL!$J$45/PL!$J$24 -> 0.4139615 | K53: =PL!$K$45/PL!$K$24 -> 0.41054472 | L53: =PL!$L$45/PL!$L$24 -> 0.40668899 | M53: =PL!$M$45/PL!$M$24 -> 0.40372804 | N53: =PL!$N$45/PL!$N$24 -> 0.35579628 | O53: =PL!$O$45/PL!$O$24 -> 0.35034711
A54: AWS AI 營業利益率 | B54: % | C54: =PL!$C$43/PL!$C$25 -> 0.70839079 | D54: =PL!$D$43/PL!$D$25 -> 0.61941557 | E54: =PL!$E$43/PL!$E$25 -> 0.3897807 | F54: =PL!$F$43/PL!$F$25 -> 0.58863357 | G54: =PL!$G$43/PL!$G$25 -> 0.46440611 | H54: =PL!$H$43/PL!$H$25 -> 0.52173298 | I54: =PL!$I$43/PL!$I$25 -> 0.46058855 | J54: =PL!$J$43/PL!$J$25 -> 0.46328928 | K54: =PL!$K$43/PL!$K$25 -> 0.44964121 | L54: =PL!$L$43/PL!$L$25 -> 0.44035771 | M54: =PL!$M$43/PL!$M$25 -> 0.43535075 | N54: =PL!$N$43/PL!$N$25 -> 0.59133825 | O54: =PL!$O$43/PL!$O$25 -> 0.66879293
A55: 合併營業利益率 | B55: % | C55: =PL!$C$47/PL!$C$27 -> 0.10751945 | D55: =PL!$D$47/PL!$D$27 -> 0.11155297 | E55: =PL!$E$47/PL!$E$27 -> 0.13592401 | F55: =PL!$F$47/PL!$F$27 -> 0.14774534 | G55: =PL!$G$47/PL!$G$27 -> 0.13941851 | H55: =PL!$H$47/PL!$H$27 -> 0.15630641 | I55: =PL!$I$47/PL!$I$27 -> 0.16243008 | J55: =PL!$J$47/PL!$J$27 -> 0.17249222 | K55: =PL!$K$47/PL!$K$27 -> 0.17687916 | L55: =PL!$L$47/PL!$L$27 -> 0.17830429 | M55: =PL!$M$47/PL!$M$27 -> 0.17909036 | N55: =PL!$N$47/PL!$N$27 -> 0.10922314 | O55: =PL!$O$47/PL!$O$27 -> 0.11705079
A56: 3. 分部折舊攤銷（PP&E）與 EBITDA（分部加總評價用）
A57: 零售非 AI 折舊 ÷ 零售營收（FY2025 校準） | B57: % | D57: =(Q!$E$31+Q!$E$32-(1-ext_sh)*Thesis!$D$50)/Seg!$D$20 -> 0.03411056
A58: North America 折舊攤銷 | B58: US$bn | C58: =Q!$D$31 -> 14.285 | D58: =Q!$E$31 -> 15.503 | E58: =Q!$O$31 -> 13.496355 | F58: =(PL!$D$57*Seg!$F$20+(1-ext_sh)*Thesis!$F$50)*Seg!$F$21 -> 5.2121143 | G58: =PL!$E$58+PL!$F$58 -> 18.708469 | H58: =(PL!$D$57*Seg!$H$20+(1-ext_sh)*Thesis!$H$50)*Seg!$H$21 -> 21.721166 | I58: =(PL!$D$57*Seg!$I$20+(1-ext_sh)*Thesis!$I$50)*Seg!$I$21 -> 27.770192 | J58: =(PL!$D$57*Seg!$J$20+(1-ext_sh)*Thesis!$J$50)*Seg!$J$21 -> 32.859777 | K58: =(PL!$D$57*Seg!$K$20+(1-ext_sh)*Thesis!$K$50)*Seg!$K$21 -> 37.857681 | L58: =(PL!$D$57*Seg!$L$20+(1-ext_sh)*Thesis!$L$50)*Seg!$L$21 -> 41.838176 | M58: =(PL!$D$57*Seg!$M$20+(1-ext_sh)*Thesis!$M$50)*Seg!$M$21 -> 44.65912 | N58: =Q!$N$31 -> 11.273 | O58: =Q!$J$31 -> 4.23
A59: International 折舊攤銷 | B59: US$bn | C59: =Q!$D$32 -> 4.462 | D59: =Q!$E$32 -> 4.907 | E59: =Q!$O$32 -> 3.9251659 | F59: =(PL!$D$57*Seg!$F$20+(1-ext_sh)*Thesis!$F$50)*(1-Seg!$F$21) -> 2.080367 | G59: =PL!$E$59+PL!$F$59 -> 6.005533 | H59: =(PL!$D$57*Seg!$H$20+(1-ext_sh)*Thesis!$H$50)*(1-Seg!$H$21) -> 8.3090516 | I59: =(PL!$D$57*Seg!$I$20+(1-ext_sh)*Thesis!$I$50)*(1-Seg!$I$21) -> 10.623001 | J59: =(PL!$D$57*Seg!$J$20+(1-ext_sh)*Thesis!$J$50)*(1-Seg!$J$21) -> 12.569932 | K59: =(PL!$D$57*Seg!$K$20+(1-ext_sh)*Thesis!$K$50)*(1-Seg!$K$21) -> 14.481793 | L59: =(PL!$D$57*Seg!$L$20+(1-ext_sh)*Thesis!$L$50)*(1-Seg!$L$21) -> 16.004462 | M59: =(PL!$D$57*Seg!$M$20+(1-ext_sh)*Thesis!$M$50)*(1-Seg!$M$21) -> 17.083564 | N59: =Q!$N$32 -> 3.592 | O59: =Q!$J$32 -> 1.315
A60: AWS 折舊攤銷 | B60: US$bn | C60: =Thesis!$C$62 -> 13.32 | D60: =Thesis!$D$62 -> 21.45 | E60: =Thesis!$E$62 -> 23.817285 | F60: =Thesis!$F$62 -> 8.2815577 | G60: =Thesis!$G$62 -> 32.098842 | H60: =Thesis!$H$62 -> 48.746928 | I60: =Thesis!$I$62 -> 76.184357 | J60: =Thesis!$J$62 -> 98.798749 | K60: =Thesis!$K$62 -> 121.60893 | L60: =Thesis!$L$62 -> 138.48522 | M60: =Thesis!$M$62 -> 148.61971 | N60: =Thesis!$N$62 -> 14.882 | O60: =Thesis!$O$62 -> 6.568
A61: 分部折舊攤銷合計（PP&E；不含影音內容與營業租賃資產） | B61: US$bn | C61: =PL!$C$58+PL!$C$59+PL!$C$60 -> 32.067 | D61: =PL!$D$58+PL!$D$59+PL!$D$60 -> 41.86 | E61: =PL!$E$58+PL!$E$59+PL!$E$60 -> 41.238806 | F61: =PL!$F$58+PL!$F$59+PL!$F$60 -> 15.574039 | G61: =PL!$G$58+PL!$G$59+PL!$G$60 -> 56.812845 | H61: =PL!$H$58+PL!$H$59+PL!$H$60 -> 78.777146 | I61: =PL!$I$58+PL!$I$59+PL!$I$60 -> 114.57755 | J61: =PL!$J$58+PL!$J$59+PL!$J$60 -> 144.22846 | K61: =PL!$K$58+PL!$K$59+PL!$K$60 -> 173.94841 | L61: =PL!$L$58+PL!$L$59+PL!$L$60 -> 196.32786 | M61: =PL!$M$58+PL!$M$59+PL!$M$60 -> 210.36239 | N61: =PL!$N$58+PL!$N$59+PL!$N$60 -> 29.747 | O61: =PL!$O$58+PL!$O$59+PL!$O$60 -> 12.113
A62: EBITDA：廣告（＝廣告利潤，未分攤折舊） | B62: US$bn | C62: =PL!$C$33+PL!$C$38 -> 28.107 | D62: =PL!$D$33+PL!$D$38 -> 34.3175 | E62: =PL!$E$33+PL!$E$38 -> 28.3445 | F62: =PL!$F$33+PL!$F$38 -> 12.75402 | G62: =PL!$G$33+PL!$G$38 -> 41.09852 | H62: =PL!$H$33+PL!$H$38 -> 48.230439 | I62: =PL!$I$33+PL!$I$38 -> 55.417812 | J62: =PL!$J$33+PL!$J$38 -> 62.317926 | K62: =PL!$K$33+PL!$K$38 -> 68.549719 | L62: =PL!$L$33+PL!$L$38 -> 75.40469 | M62: =PL!$M$33+PL!$M$38 -> 82.945159 | N62: =PL!$N$33+PL!$N$38 -> 23.659 | O62: =PL!$O$33+PL!$O$38 -> 10.6585
A63: EBITDA：零售本業（北美＋國際 營業利益＋折舊 − 廣告利潤；含自用 AI 成本） | B63: US$bn | C63: =PL!$C$37+PL!$C$42+PL!$C$58+PL!$C$59-PL!$C$62 -> 19.399 | D63: =PL!$D$37+PL!$D$42+PL!$D$58+PL!$D$59-PL!$D$62 -> 20.4615 | E63: =PL!$E$37+PL!$E$42+PL!$E$58+PL!$E$59-PL!$E$62 -> 19.911021 | F63: =PL!$F$37+PL!$F$42+PL!$F$58+PL!$F$59-PL!$F$62 -> 11.330201 | G63: =PL!$G$37+PL!$G$42+PL!$G$58+PL!$G$59-PL!$G$62 -> 31.241222 | H63: =PL!$H$37+PL!$H$42+PL!$H$58+PL!$H$59-PL!$H$62 -> 33.821459 | I63: =PL!$I$37+PL!$I$42+PL!$I$58+PL!$I$59-PL!$I$62 -> 36.448605 | J63: =PL!$J$37+PL!$J$42+PL!$J$58+PL!$J$59-PL!$J$62 -> 39.051458 | K63: =PL!$K$37+PL!$K$42+PL!$K$58+PL!$K$59-PL!$K$62 -> 41.799358 | L63: =PL!$L$37+PL!$L$42+PL!$L$58+PL!$L$59-PL!$L$62 -> 43.788513 | M63: =PL!$M$37+PL!$M$42+PL!$M$58+PL!$M$59-PL!$M$62 -> 46.615073 | N63: =PL!$N$37+PL!$N$42+PL!$N$58+PL!$N$59-PL!$N$62 -> 13.063 | O63: =PL!$O$37+PL!$O$42+PL!$O$58+PL!$O$59-PL!$O$62 -> 7.3985
A64: EBITDA：AWS 其他 | B64: US$bn | C64: =PL!$C$44+PL!$C$60-ext_sh*Thesis!$C$50 -> 51.34705 | D64: =PL!$D$44+PL!$D$60-ext_sh*Thesis!$D$50 -> 60.279938 | E64: =PL!$E$44+PL!$E$60-ext_sh*Thesis!$E$50 -> 59.759703 | F64: =PL!$F$44+PL!$F$60-ext_sh*Thesis!$F$50 -> 19.876586 | G64: =PL!$G$44+PL!$G$60-ext_sh*Thesis!$G$50 -> 79.636289 | H64: =PL!$H$44+PL!$H$60-ext_sh*Thesis!$H$50 -> 88.666304 | I64: =PL!$I$44+PL!$I$60-ext_sh*Thesis!$I$50 -> 98.442067 | J64: =PL!$J$44+PL!$J$60-ext_sh*Thesis!$J$50 -> 107.80654 | K64: =PL!$K$44+PL!$K$60-ext_sh*Thesis!$K$50 -> 116.43106 | L64: =PL!$L$44+PL!$L$60-ext_sh*Thesis!$L$50 -> 125.74554 | M64: =PL!$M$44+PL!$M$60-ext_sh*Thesis!$M$50 -> 135.80519 | N64: =PL!$N$44+PL!$N$60-ext_sh*Thesis!$N$50 -> 43.70326 | O64: =PL!$O$44+PL!$O$60-ext_sh*Thesis!$O$50 -> 16.576677
A65: EBITDA：AWS AI | B65: US$bn | C65: =Thesis!$C$53 -> 1.80695 | D65: =Thesis!$D$53 -> 6.7760625 | E65: =Thesis!$E$53 -> 12.612582 | F65: =Thesis!$F$53 -> 7.8278809 | G65: =Thesis!$G$53 -> 20.440462 | H65: =Thesis!$H$53 -> 58.336637 | I65: =Thesis!$I$53 -> 102.77053 | J65: =Thesis!$J$53 -> 147.47744 | K65: =Thesis!$K$53 -> 185.60468 | L65: =Thesis!$L$53 -> 210.65549 | M65: =Thesis!$M$53 -> 222.58531 | N65: =Thesis!$N$53 -> 4.3197398 | O65: =Thesis!$O$53 -> 2.4563226
A66: EBITDA（營業利益＋分部折舊攤銷） | B66: US$bn | C66: =PL!$C$47+PL!$C$61 -> 100.66 | D66: =PL!$D$47+PL!$D$61 -> 121.835 | E66: =PL!$E$47+PL!$E$61 -> 120.62781 | F66: =PL!$F$47+PL!$F$61 -> 51.788687 | G66: =PL!$G$47+PL!$G$61 -> 172.41649 | H66: =PL!$H$47+PL!$H$61 -> 229.05484 | I66: =PL!$I$47+PL!$I$61 -> 293.07902 | J66: =PL!$J$47+PL!$J$61 -> 356.65336 | K66: =PL!$K$47+PL!$K$61 -> 412.38482 | L66: =PL!$L$47+PL!$L$61 -> 455.59424 | M66: =PL!$M$47+PL!$M$61 -> 487.95073 | N66: =PL!$N$47+PL!$N$61 -> 84.745 | O66: =PL!$O$47+PL!$O$61 -> 37.09
A67: 4. 業外、稅、淨利、EPS
A68: 利息費用 | B68: US$bn | C68: =Q!$D$36 -> 2.406 | D68: =Q!$E$36 -> 2.274 | E68: =Q!$O$36 -> 3.805 | F68: =CF!$F$37 -> 1.9499383 | G68: =PL!$E$68+PL!$F$68 -> 5.7549383 | H68: =CF!$H$37 -> 7.7997533 | I68: =CF!$I$37 -> 7.7997533 | J68: =CF!$J$37 -> 7.7997533 | K68: =CF!$K$37 -> 7.7997533 | L68: =CF!$L$37 -> 7.7997533 | M68: =CF!$M$37 -> 7.7997533 | N68: =Q!$N$36 -> 1.595 | O68: =Q!$J$36 -> 0.679
A69: 利息收入（預測；實績含在業外其他） | B69: US$bn | F69: =CF!$F$38 -> 1.187 | H69: =CF!$H$38 -> 5.7517202 | I69: =CF!$I$38 -> 5.1154605 | J69: =CF!$J$38 -> 6.5523848 | K69: =CF!$K$38 -> 10.164541 | L69: =CF!$L$38 -> 17.962117 | M69: =CF!$M$38 -> 28.498768
A70: 業外其他（含利息收入與 Anthropic 等持股評價損益；預測期設 0） | B70: US$bn | C70: =Q!$D$41 -> 2.427 | D70: =Q!$E$41 -> 19.61 | E70: =Q!$O$41 -> 71.976 | F70: 0 | G70: =PL!$E$70+PL!$F$70 -> 71.976 | H70: 0 | I70: 0 | J70: 0 | K70: 0 | L70: 0 | M70: 0 | N70: =Q!$N$41 -> 17.303 | O70: =Q!$J$41 -> 2.307 | P70: 持股價值另在 Val 頁加入（不重複計算）
A71: 稅前淨利 | B71: US$bn | C71: =Q!$D$38 -> 68.614 | D71: =Q!$E$38 -> 97.311 | E71: =Q!$O$38 -> 147.56 | F71: =PL!$F$47-PL!$F$68+PL!$F$69+PL!$F$70 -> 35.45171 | G71: =PL!$E$71+PL!$F$71 -> 183.01171 | H71: =PL!$H$47-PL!$H$68+PL!$H$69+PL!$H$70 -> 148.22966 | I71: =PL!$I$47-PL!$I$68+PL!$I$69+PL!$I$70 -> 175.81718 | J71: =PL!$J$47-PL!$J$68+PL!$J$69+PL!$J$70 -> 211.17753 | K71: =PL!$K$47-PL!$K$68+PL!$K$69+PL!$K$70 -> 240.8012 | L71: =PL!$L$47-PL!$L$68+PL!$L$69+PL!$L$70 -> 269.42874 | M71: =PL!$M$47-PL!$M$68+PL!$M$69+PL!$M$70 -> 298.28736 | N71: =Q!$N$38 -> 70.706 | O71: =Q!$J$38 -> 26.605
A72: 所得稅 | B72: US$bn | C72: =Q!$D$39 -> 9.265 | D72: =Q!$E$39 -> 19.087 | E72: =Q!$O$39 -> 33.939 | F72: =PL!$F$71*tax -> 6.1538683 | G72: =PL!$E$72+PL!$F$72 -> 40.092868 | H72: =PL!$H$71*tax -> 25.730375 | I72: =PL!$I$71*tax -> 30.519141 | J72: =PL!$J$71*tax -> 36.657152 | K72: =PL!$K$71*tax -> 41.799362 | L72: =PL!$L$71*tax -> 46.76866 | M72: =PL!$M$71*tax -> 51.778069 | N72: =Q!$N$39 -> 14.141 | O72: =Q!$J$39 -> 4.946
A73: 淨利 | B73: US$bn | C73: =Q!$D$40 -> 59.248 | D73: =Q!$E$40 -> 77.67 | E73: =Q!$O$40 -> 113.587 | F73: =PL!$F$71-PL!$F$72 -> 29.297842 | G73: =PL!$E$73+PL!$F$73 -> 142.88484 | H73: =PL!$H$71-PL!$H$72 -> 122.49928 | I73: =PL!$I$71-PL!$I$72 -> 145.29804 | J73: =PL!$J$71-PL!$J$72 -> 174.52038 | K73: =PL!$K$71-PL!$K$72 -> 199.00184 | L73: =PL!$L$71-PL!$L$72 -> 222.66008 | M73: =PL!$M$71-PL!$M$72 -> 246.50929 | N73: =Q!$N$40 -> 56.478 | O73: =Q!$J$40 -> 21.192
A74: 稀釋加權股數 | B74: 十億股 | C74: =Q!$D$43 -> 10.721 | D74: =Q!$E$43 -> 10.827 | E74: =Q!$O$43 -> 10.903 | F74: =Q!$M$43*(1+sh_g*0.25) -> 10.950858 | G74: =(3*PL!$E$74+PL!$F$74)/4 -> 10.914964 | H74: =PL!$G$74*(1+sh_g) -> 11.002284 | I74: =PL!$H$74*(1+sh_g) -> 11.090302 | J74: =PL!$I$74*(1+sh_g) -> 11.179025 | K74: =PL!$J$74*(1+sh_g) -> 11.268457 | L74: =PL!$K$74*(1+sh_g) -> 11.358605 | M74: =PL!$L$74*(1+sh_g) -> 11.449474 | P74: 無回購；SBC 稀釋每年 sh_g
A75: 淨利（評價口徑＝淨利＋影子效益 ×（1 − 稅率）） | B75: US$bn | C75: =PL!$C$73+PL!$C$49*(1-tax) -> 59.248 | D75: =PL!$D$73+PL!$D$49*(1-tax) -> 77.67 | E75: =PL!$E$73+PL!$E$49*(1-tax) -> 113.587 | F75: =PL!$F$73+PL!$F$49*(1-tax) -> 30.985227 | G75: =PL!$G$73+PL!$G$49*(1-tax) -> 144.57223 | H75: =PL!$H$73+PL!$H$49*(1-tax) -> 133.64549 | I75: =PL!$I$73+PL!$I$49*(1-tax) -> 163.6507 | J75: =PL!$J$73+PL!$J$49*(1-tax) -> 200.11879 | K75: =PL!$K$73+PL!$K$49*(1-tax) -> 230.78028 | L75: =PL!$L$73+PL!$L$49*(1-tax) -> 258.49903 | M75: =PL!$M$73+PL!$M$49*(1-tax) -> 284.28283 | N75: =PL!$N$73+PL!$N$49*(1-tax) -> 56.478 | O75: =PL!$O$73+PL!$O$49*(1-tax) -> 21.192
A76: EPS（評價口徑，稀釋） | B76: US$ | C76: =PL!$C$75/PL!$C$74 -> 5.5263502 | D76: =PL!$D$75/PL!$D$74 -> 7.1737323 | E76: =PL!$E$75/PL!$E$74 -> 10.417958 | G76: =PL!$G$75/PL!$G$74 -> 13.245323 | H76: =PL!$H$75/PL!$H$74 -> 12.147068 | I76: =PL!$I$75/PL!$I$74 -> 14.756198 | J76: =PL!$J$75/PL!$J$74 -> 17.901275 | K76: =PL!$K$75/PL!$K$74 -> 20.480202 | L76: =PL!$L$75/PL!$L$74 -> 22.757992 | M76: =PL!$M$75/PL!$M$74 -> 24.829336
A77: EPS（財報口徑，稀釋） | B77: US$ | C77: =PL!$C$73/PL!$C$74 -> 5.5263502 | D77: =PL!$D$73/PL!$D$74 -> 7.1737323 | E77: =PL!$E$73/PL!$E$74 -> 10.417958 | G77: =PL!$G$73/PL!$G$74 -> 13.090729 | H77: =PL!$H$73/PL!$H$74 -> 11.133987 | I77: =PL!$I$73/PL!$I$74 -> 13.101359 | J77: =PL!$J$73/PL!$J$74 -> 15.611413 | K77: =PL!$K$73/PL!$K$74 -> 17.660078 | L77: =PL!$L$73/PL!$L$74 -> 19.602767 | M77: =PL!$M$73/PL!$M$74 -> 21.530185
A78: EPS（不含業外其他，近似：扣除業外其他 ×（1 − 稅率）） | B78: US$ | C78: =(PL!$C$73-PL!$C$70*(1-tax))/PL!$C$74 -> 5.3392678 | D78: =(PL!$D$73-PL!$D$70*(1-tax))/PL!$D$74 -> 5.6769181 | E78: =(PL!$E$73-PL!$E$70*(1-tax))/PL!$E$74 -> 4.9623883 | G78: =(PL!$G$73-PL!$G$70*(1-tax))/PL!$G$74 -> 7.641139 | H78: =(PL!$H$73-PL!$H$70*(1-tax))/PL!$H$74 -> 11.133987 | I78: =(PL!$I$73-PL!$I$70*(1-tax))/PL!$I$74 -> 13.101359 | J78: =(PL!$J$73-PL!$J$70*(1-tax))/PL!$J$74 -> 15.611413 | K78: =(PL!$K$73-PL!$K$70*(1-tax))/PL!$K$74 -> 17.660078 | L78: =(PL!$L$73-PL!$L$70*(1-tax))/PL!$L$74 -> 19.602767 | M78: =(PL!$M$73-PL!$M$70*(1-tax))/PL!$M$74 -> 21.530185 | P78: 對照 S&P 調整後 EPS；9M26 業外含 Anthropic 評價利益約 68
A79: EPS 年增 | B79: % | H79: =PL!$H$76/PL!$G$76-1 -> -0.082916452 | I79: =PL!$I$76/PL!$H$76-1 -> 0.21479509 | J79: =PL!$J$76/PL!$I$76-1 -> 0.21313597 | K79: =PL!$K$76/PL!$J$76-1 -> 0.1440639 | L79: =PL!$L$76/PL!$K$76-1 -> 0.11121911 | M79: =PL!$M$76/PL!$L$76-1 -> 0.091016122
A82: PL｜情境 B（基準）：分部營收 → 分部營業利益 → 合併營業利益 → 業外、稅 → 淨利 → EPS
A83: 項目 | B83: 單位 | C83: FY2024A | D83: FY2025A | E83: 9M26A | F83: Q4 26E | G83: FY2026E（9M 實績＋Q4 模型） | H83: FY2027E | I83: FY2028E | J83: FY2029E | K83: FY2030E | L83: FY2031E | M83: FY2032E | N83: 9M25A | O83: Q4 25A | P83: 說明 | R83: 2023 | S83: 2024 | T83: 2025 | U83: 2026 | V83: 2027 | W83: 2028 | X83: 2029 | Y83: 2030 | Z83: 2031 | AA83: 2032
A84: 1. 營收（10-K 營收線與官方分部）
A85: Online stores | B85: US$bn | C85: =Seg!$C$42 -> 247.029 | D85: =Seg!$D$42 -> 269.287 | E85: =Seg!$E$42 -> 203.156 | F85: =Seg!$F$42 -> 90.388464 | G85: =Seg!$G$42 -> 293.54446 | H85: =Seg!$H$42 -> 317.13448 | I85: =Seg!$I$42 -> 339.41058 | J85: =Seg!$J$42 -> 359.81625 | K85: =Seg!$K$42 -> 377.80706 | L85: =Seg!$L$42 -> 396.69741 | M85: =Seg!$M$42 -> 416.53228 | N85: =Seg!$N$42 -> 186.299 | O85: =Seg!$O$42 -> 82.988
A86: Physical stores | B86: US$bn | C86: =Seg!$C$44 -> 21.215 | D86: =Seg!$D$44 -> 22.561 | E86: =Seg!$E$44 -> 17.289 | F86: =Seg!$F$44 -> 6.0520551 | G86: =Seg!$G$44 -> 23.341055 | H86: =Seg!$H$44 -> 24.127024 | I86: =Seg!$I$44 -> 24.909917 | J86: =Seg!$J$44 -> 25.687715 | K86: =Seg!$K$44 -> 26.458346 | L86: =Seg!$L$44 -> 27.252097 | M86: =Seg!$M$44 -> 28.06966 | N86: =Seg!$N$44 -> 16.706 | O86: =Seg!$O$44 -> 5.855
A87: Third-party seller services | B87: US$bn | C87: =Seg!$C$46 -> 156.146 | D87: =Seg!$D$46 -> 172.162 | E87: =Seg!$E$46 -> 134.85 | F87: =Seg!$F$46 -> 59.605614 | G87: =Seg!$G$46 -> 194.45561 | H87: =Seg!$H$46 -> 216.80459 | I87: =Seg!$I$46 -> 238.47508 | J87: =Seg!$J$46 -> 258.73997 | K87: =Seg!$K$46 -> 276.85177 | L87: =Seg!$L$46 -> 296.2314 | M87: =Seg!$M$46 -> 316.9676 | N87: =Seg!$N$46 -> 119.346 | O87: =Seg!$O$46 -> 52.816
A88: Advertising services | B88: US$bn | C88: =Seg!$C$48 -> 56.214 | D88: =Seg!$D$48 -> 68.635 | E88: =Seg!$E$48 -> 56.689 | F88: =Seg!$F$48 -> 25.508039 | G88: =Seg!$G$48 -> 82.197039 | H88: =Seg!$H$48 -> 96.460878 | I88: =Seg!$I$48 -> 110.83562 | J88: =Seg!$J$48 -> 124.63585 | K88: =Seg!$K$48 -> 137.09944 | L88: =Seg!$L$48 -> 150.80938 | M88: =Seg!$M$48 -> 165.89032 | N88: =Seg!$N$48 -> 47.318 | O88: =Seg!$O$48 -> 21.317
A89: Subscription services | B89: US$bn | C89: =Seg!$C$50 -> 44.374 | D89: =Seg!$D$50 -> 49.619 | E89: =Seg!$E$50 -> 41.163 | F89: =Seg!$F$50 -> 14.781839 | G89: =Seg!$G$50 -> 55.944839 | H89: =Seg!$H$50 -> 62.288122 | I89: =Seg!$I$50 -> 68.449853 | J89: =Seg!$J$50 -> 74.231233 | K89: =Seg!$K$50 -> 79.427419 | L89: =Seg!$L$50 -> 84.987338 | M89: =Seg!$M$50 -> 90.936452 | N89: =Seg!$N$50 -> 36.497 | O89: =Seg!$O$50 -> 13.122
A90: Other | B90: US$bn | C90: =Seg!$C$52 -> 5.425 | D90: =Seg!$D$52 -> 5.935 | E90: =Seg!$E$52 -> 5.119 | F90: =Seg!$F$52 -> 2.0676464 | G90: =Seg!$G$52 -> 7.1866464 | H90: =Seg!$H$52 -> 8.4154422 | I90: =Seg!$I$52 -> 9.5149658 | J90: =Seg!$J$52 -> 10.374431 | K90: =Seg!$K$52 -> 10.893153 | L90: =Seg!$L$52 -> 11.43781 | M90: =Seg!$M$52 -> 12.009701 | N90: =Seg!$N$52 -> 4.226 | O90: =Seg!$O$52 -> 1.709
A91: AWS（營收線＝分部） | B91: US$bn | C91: =Seg!$C$64 -> 107.556 | D91: =Seg!$D$64 -> 128.725 | E91: =Seg!$E$64 -> 125.803 | F91: =Seg!$F$64 -> 45.096342 | G91: =Seg!$G$64 -> 170.89934 | H91: =Seg!$H$64 -> 218.85151 | I91: =Seg!$I$64 -> 272.15673 | J91: =Seg!$J$64 -> 324.88848 | K91: =Seg!$K$64 -> 371.04824 | L91: =Seg!$L$64 -> 408.1587 | M91: =Seg!$M$64 -> 436.29134 | N91: =Seg!$N$64 -> 93.146 | O91: =Seg!$O$64 -> 35.579
A92: North America | B92: US$bn | C92: =Seg!$C$57 -> 387.497 | D92: =Seg!$D$57 -> 426.305 | E92: =Seg!$E$57 -> 333.172 | F92: =Seg!$F$57 -> 141.80393 | G92: =Seg!$G$57 -> 474.97593 | H92: =Seg!$H$57 -> 524.56673 | I92: =Seg!$I$57 -> 572.56956 | J92: =Seg!$J$57 -> 617.33483 | K92: =Seg!$K$57 -> 657.15431 | L92: =Seg!$L$57 -> 699.74156 | M92: =Seg!$M$57 -> 745.30329 | N92: =Seg!$N$57 -> 299.222 | O92: =Seg!$O$57 -> 127.083
A93: International | B93: US$bn | C93: =Seg!$C$58 -> 142.906 | D93: =Seg!$D$58 -> 161.894 | E93: =Seg!$E$58 -> 125.094 | F93: =Seg!$F$58 -> 56.599724 | G93: =Seg!$G$58 -> 181.69372 | H93: =Seg!$H$58 -> 200.66381 | I93: =Seg!$I$58 -> 219.02646 | J93: =Seg!$J$58 -> 236.15062 | K93: =Seg!$K$58 -> 251.38287 | L93: =Seg!$L$58 -> 267.67388 | M93: =Seg!$M$58 -> 285.10272 | N93: =Seg!$N$58 -> 111.17 | O93: =Seg!$O$58 -> 50.724
A94: AWS | B94: US$bn | C94: =Seg!$C$64 -> 107.556 | D94: =Seg!$D$64 -> 128.725 | E94: =Seg!$E$64 -> 125.803 | F94: =Seg!$F$64 -> 45.096342 | G94: =Seg!$G$64 -> 170.89934 | H94: =Seg!$H$64 -> 218.85151 | I94: =Seg!$I$64 -> 272.15673 | J94: =Seg!$J$64 -> 324.88848 | K94: =Seg!$K$64 -> 371.04824 | L94: =Seg!$L$64 -> 408.1587 | M94: =Seg!$M$64 -> 436.29134 | N94: =Seg!$N$64 -> 93.146 | O94: =Seg!$O$64 -> 35.579
A95: AWS AI（命題子列） | B95: US$bn | C95: =Seg!$C$62 -> 2.3210054 | D95: =Seg!$D$62 -> 8.7037701 | E95: =Seg!$E$62 -> 16.200708 | F95: =Seg!$F$62 -> 8.116682 | G95: =Seg!$G$62 -> 24.31739 | H95: =Seg!$H$62 -> 53.891094 | I95: =Seg!$I$62 -> 89.008867 | J95: =Seg!$J$62 -> 124.31836 | K95: =Seg!$K$62 -> 154.43252 | L95: =Seg!$L$62 -> 174.21371 | M95: =Seg!$M$62 -> 183.63076 | N95: =Seg!$N$62 -> 5.5486534 | O95: =Seg!$O$62 -> 3.1551167
A96: AWS 其他 | B96: US$bn | C96: =Seg!$C$63 -> 105.23499 | D96: =Seg!$D$63 -> 120.02123 | E96: =Seg!$E$63 -> 109.60229 | F96: =Seg!$F$63 -> 36.97966 | G96: =Seg!$G$63 -> 146.58195 | H96: =Seg!$H$63 -> 164.96042 | I96: =Seg!$I$63 -> 183.14786 | J96: =Seg!$J$63 -> 200.57012 | K96: =Seg!$K$63 -> 216.61573 | L96: =Seg!$L$63 -> 233.94498 | M96: =Seg!$M$63 -> 252.66058 | N96: =Seg!$N$63 -> 87.597347 | O96: =Seg!$O$63 -> 32.423883
A97: 合併營收 | B97: US$bn | C97: =Seg!$C$65 -> 637.959 | D97: =Seg!$D$65 -> 716.924 | E97: =Seg!$E$65 -> 584.069 | F97: =Seg!$F$65 -> 243.5 | G97: =Seg!$G$65 -> 827.569 | H97: =Seg!$H$65 -> 944.08205 | I97: =Seg!$I$65 -> 1063.7527 | J97: =Seg!$J$65 -> 1178.3739 | K97: =Seg!$K$65 -> 1279.5854 | L97: =Seg!$L$65 -> 1375.5741 | M97: =Seg!$M$65 -> 1466.6973 | N97: =Seg!$N$65 -> 503.538 | O97: =Seg!$O$65 -> 213.386
A98: 檢查（情境 B）：零售營收線合計 − (North America＋International) | B98: US$bn | C98: =PL!$C$85+PL!$C$86+PL!$C$87+PL!$C$88+PL!$C$89+PL!$C$90-(PL!$C$92+PL!$C$93) -> 0 | D98: =PL!$D$85+PL!$D$86+PL!$D$87+PL!$D$88+PL!$D$89+PL!$D$90-(PL!$D$92+PL!$D$93) -> 0 | E98: =PL!$E$85+PL!$E$86+PL!$E$87+PL!$E$88+PL!$E$89+PL!$E$90-(PL!$E$92+PL!$E$93) -> 0 | F98: =PL!$F$85+PL!$F$86+PL!$F$87+PL!$F$88+PL!$F$89+PL!$F$90-(PL!$F$92+PL!$F$93) -> 0 | G98: =PL!$G$85+PL!$G$86+PL!$G$87+PL!$G$88+PL!$G$89+PL!$G$90-(PL!$G$92+PL!$G$93) -> 0 | H98: =PL!$H$85+PL!$H$86+PL!$H$87+PL!$H$88+PL!$H$89+PL!$H$90-(PL!$H$92+PL!$H$93) -> 0 | I98: =PL!$I$85+PL!$I$86+PL!$I$87+PL!$I$88+PL!$I$89+PL!$I$90-(PL!$I$92+PL!$I$93) -> 0 | J98: =PL!$J$85+PL!$J$86+PL!$J$87+PL!$J$88+PL!$J$89+PL!$J$90-(PL!$J$92+PL!$J$93) -> 0 | K98: =PL!$K$85+PL!$K$86+PL!$K$87+PL!$K$88+PL!$K$89+PL!$K$90-(PL!$K$92+PL!$K$93) -> 0 | L98: =PL!$L$85+PL!$L$86+PL!$L$87+PL!$L$88+PL!$L$89+PL!$L$90-(PL!$L$92+PL!$L$93) -> 0 | M98: =PL!$M$85+PL!$M$86+PL!$M$87+PL!$M$88+PL!$M$89+PL!$M$90-(PL!$M$92+PL!$M$93) -> 0 | N98: =PL!$N$85+PL!$N$86+PL!$N$87+PL!$N$88+PL!$N$89+PL!$N$90-(PL!$N$92+PL!$N$93) -> 0 | O98: =PL!$O$85+PL!$O$86+PL!$O$87+PL!$O$88+PL!$O$89+PL!$O$90-(PL!$O$92+PL!$O$93) -> 0
A99: 檢查（情境 B）：AWS AI＋AWS 其他 − AWS | B99: US$bn | C99: =PL!$C$95+PL!$C$96-PL!$C$94 -> 0 | D99: =PL!$D$95+PL!$D$96-PL!$D$94 -> 0 | E99: =PL!$E$95+PL!$E$96-PL!$E$94 -> 0 | F99: =PL!$F$95+PL!$F$96-PL!$F$94 -> 0 | G99: =PL!$G$95+PL!$G$96-PL!$G$94 -> 0 | H99: =PL!$H$95+PL!$H$96-PL!$H$94 -> 0 | I99: =PL!$I$95+PL!$I$96-PL!$I$94 -> 0 | J99: =PL!$J$95+PL!$J$96-PL!$J$94 -> 0 | K99: =PL!$K$95+PL!$K$96-PL!$K$94 -> 0 | L99: =PL!$L$95+PL!$L$96-PL!$L$94 -> 0 | M99: =PL!$M$95+PL!$M$96-PL!$M$94 -> 0 | N99: =PL!$N$95+PL!$N$96-PL!$N$94 -> 0 | O99: =PL!$O$95+PL!$O$96-PL!$O$94 -> 0
A100: 檢查（情境 B）：營收線合計（含 AWS）− 合併營收 | B100: US$bn | C100: =PL!$C$85+PL!$C$86+PL!$C$87+PL!$C$88+PL!$C$89+PL!$C$90+PL!$C$91-PL!$C$97 -> 0 | D100: =PL!$D$85+PL!$D$86+PL!$D$87+PL!$D$88+PL!$D$89+PL!$D$90+PL!$D$91-PL!$D$97 -> 0 | E100: =PL!$E$85+PL!$E$86+PL!$E$87+PL!$E$88+PL!$E$89+PL!$E$90+PL!$E$91-PL!$E$97 -> 0 | F100: =PL!$F$85+PL!$F$86+PL!$F$87+PL!$F$88+PL!$F$89+PL!$F$90+PL!$F$91-PL!$F$97 -> 0 | G100: =PL!$G$85+PL!$G$86+PL!$G$87+PL!$G$88+PL!$G$89+PL!$G$90+PL!$G$91-PL!$G$97 -> 0 | H100: =PL!$H$85+PL!$H$86+PL!$H$87+PL!$H$88+PL!$H$89+PL!$H$90+PL!$H$91-PL!$H$97 -> 0 | I100: =PL!$I$85+PL!$I$86+PL!$I$87+PL!$I$88+PL!$I$89+PL!$I$90+PL!$I$91-PL!$I$97 -> 0 | J100: =PL!$J$85+PL!$J$86+PL!$J$87+PL!$J$88+PL!$J$89+PL!$J$90+PL!$J$91-PL!$J$97 -> 0 | K100: =PL!$K$85+PL!$K$86+PL!$K$87+PL!$K$88+PL!$K$89+PL!$K$90+PL!$K$91-PL!$K$97 -> 0 | L100: =PL!$L$85+PL!$L$86+PL!$L$87+PL!$L$88+PL!$L$89+PL!$L$90+PL!$L$91-PL!$L$97 -> 0 | M100: =PL!$M$85+PL!$M$86+PL!$M$87+PL!$M$88+PL!$M$89+PL!$M$90+PL!$M$91-PL!$M$97 -> 0 | N100: =PL!$N$85+PL!$N$86+PL!$N$87+PL!$N$88+PL!$N$89+PL!$N$90+PL!$N$91-PL!$N$97 -> 0 | O100: =PL!$O$85+PL!$O$86+PL!$O$87+PL!$O$88+PL!$O$89+PL!$O$90+PL!$O$91-PL!$O$97 -> 0
A101: 檢查（情境 B）：分部合計 − 合併營收 | B101: US$bn | C101: =PL!$C$92+PL!$C$93+PL!$C$94-PL!$C$97 -> 0 | D101: =PL!$D$92+PL!$D$93+PL!$D$94-PL!$D$97 -> 0 | E101: =PL!$E$92+PL!$E$93+PL!$E$94-PL!$E$97 -> 0 | F101: =PL!$F$92+PL!$F$93+PL!$F$94-PL!$F$97 -> 0 | G101: =PL!$G$92+PL!$G$93+PL!$G$94-PL!$G$97 -> 0 | H101: =PL!$H$92+PL!$H$93+PL!$H$94-PL!$H$97 -> 0 | I101: =PL!$I$92+PL!$I$93+PL!$I$94-PL!$I$97 -> 0 | J101: =PL!$J$92+PL!$J$93+PL!$J$94-PL!$J$97 -> 0 | K101: =PL!$K$92+PL!$K$93+PL!$K$94-PL!$K$97 -> 0 | L101: =PL!$L$92+PL!$L$93+PL!$L$94-PL!$L$97 -> 0 | M101: =PL!$M$92+PL!$M$93+PL!$M$94-PL!$M$97 -> 0 | N101: =PL!$N$92+PL!$N$93+PL!$N$94-PL!$N$97 -> 0 | O101: =PL!$O$92+PL!$O$93+PL!$O$94-PL!$O$97 -> 0
A102: 2. 分部營業利益（廣告利潤率 m_ad 計入北美／國際；零售本業利益率＝殘差；自用 AI 成本按北美比例分攤）
A103: North America：廣告利潤（廣告營收 × m_ad） | B103: US$bn | C103: =Seg!$C$59*m_ad -> 20.534156 | D103: =Seg!$D$59*m_ad -> 24.872062 | E103: =Seg!$E$59*m_ad -> 20.607232 | F103: =Seg!$F$59*m_ad -> 9.115609 | G103: =Seg!$G$59*m_ad -> 29.726983 | H103: =Seg!$H$59*m_ad -> 34.885574 | I103: =Seg!$I$59*m_ad -> 40.084275 | J103: =Seg!$J$59*m_ad -> 45.075198 | K103: =Seg!$K$59*m_ad -> 49.582718 | L103: =Seg!$L$59*m_ad -> 54.54099 | M103: =Seg!$M$59*m_ad -> 59.995089 | N103: =Seg!$N$59*m_ad -> 17.250076 | O103: =Seg!$O$59*m_ad -> 7.6178899
A104: North America：零售本業營收（分部 − 廣告） | B104: US$bn | C104: =Seg!$C$57-Seg!$C$59 -> 346.42869 | D104: =Seg!$D$57-Seg!$D$59 -> 376.56088 | E104: =Seg!$E$57-Seg!$E$59 -> 291.95754 | F104: =Seg!$F$57-Seg!$F$59 -> 123.57272 | G104: =Seg!$G$57-Seg!$G$59 -> 415.52197 | H104: =Seg!$H$57-Seg!$H$59 -> 454.79558 | I104: =Seg!$I$57-Seg!$I$59 -> 492.40101 | J104: =Seg!$J$57-Seg!$J$59 -> 527.18443 | K104: =Seg!$K$57-Seg!$K$59 -> 557.98888 | L104: =Seg!$L$57-Seg!$L$59 -> 590.65958 | M104: =Seg!$M$57-Seg!$M$59 -> 625.31311 | N104: =Seg!$N$57-Seg!$N$59 -> 264.72185 | O104: =Seg!$O$57-Seg!$O$59 -> 111.84722
...

Sheet CF
A1: CF — 營運現金（淨利＋分部折舊＋SBC＋其他）− 資本支出（AI＋AWS 其他＋零售）− 融資租賃本金 → 自由現金流；股利 0、回購 0（Amazon 無）；現金低於最低現金即舉債。FY2026＝9M 實績＋Q4 模型
A4: 收支關卡（地圖讀取；列標籤固定）
A5: 項目 | B5: A（樂觀） | C5: B（基準） | D5: C（保守） | E5: 情境加權 | F5: 說明
A6: 收支關卡：自由現金流扣股利（五年合計） | B6: =CF!$G$39 -> 258.25838 | C6: =CF!$G$69 -> 89.611765 | D6: =CF!$G$99 -> 37.712942 | E6: =w_A*B6+w_B*C6+w_C*D6 -> 118.79871 | F6: FY2026–FY2030（首年起五年；FY2026＝9M 實績＋Q4 模型）自由現金流扣股利合計；負值＝入不敷出（地圖收支關卡）
A7: FY2026–FY2030 新增借款合計（不含已發行債券） | B7: =CF!$G$40 -> 0 | C7: =CF!$G$70 -> 0 | D7: =CF!$G$100 -> 0
A8: 是否需要舉債 | B8: =IF(B7>=1,"需要舉債",IF(B7>0,"幾乎不需要（新增借款少於 1）","不需要（現金足以支應）")) -> 不需要（現金足以支應） | C8: =IF(C7>=1,"需要舉債",IF(C7>0,"幾乎不需要（新增借款少於 1）","不需要（現金足以支應）")) -> 不需要（現金足以支應） | D8: =IF(D7>=1,"需要舉債",IF(D7>0,"幾乎不需要（新增借款少於 1）","不需要（現金足以支應）")) -> 不需要（現金足以支應） | F8: 9M26 已發行債券（長期借款收入 115.1）在實績期內，不計；現金低於最低現金 50 時舉債
A9: 回購是否需停止 | B9: 無回購可減（2023–9M26 皆為 0） | C9: 無回購可減（2023–9M26 皆為 0） | D9: 無回購可減（2023–9M26 皆為 0）
A10: FY2028 自由現金流（扣股利） | B10: =CF!$I$29 -> 34.569107 | C10: =CF!$I$59 -> 0.64971308 | D10: =CF!$I$89 -> -9.5508924
A11: 檢查：收支關卡＝首年起五年自由現金流扣股利（逐欄加總；三情境絕對值合計） | B11: =ABS(CF!$G$41)+ABS(CF!$G$71)+ABS(CF!$G$101) -> 0
A14: CF｜情境 A（樂觀）：營運現金 − 資本支出 − 租賃本金 → 自由現金流；股利、回購、借款與淨現金
A15: 項目 | B15: 單位 | C15: FY2024A | D15: FY2025A | E15: 9M26A | F15: Q4 26E | G15: FY2026E（9M 實績＋Q4 模型） | H15: FY2027E | I15: FY2028E | J15: FY2029E | K15: FY2030E | L15: FY2031E | M15: FY2032E | N15: 9M25A | O15: Q4 25A | P15: 說明 | R15: 2023 | S15: 2024 | T15: 2025 | U15: 2026 | V15: 2027 | W15: 2028 | X15: 2029 | Y15: 2030 | Z15: 2031 | AA15: 2032
A16: 淨利 | B16: US$bn | C16: =PL!$C$73 -> 59.248 | D16: =PL!$D$73 -> 77.67 | E16: =PL!$E$73 -> 113.587 | F16: =PL!$F$73 -> 29.297842 | G16: =PL!$G$73 -> 142.88484 | H16: =PL!$H$73 -> 122.49928 | I16: =PL!$I$73 -> 145.29804 | J16: =PL!$J$73 -> 174.52038 | K16: =PL!$K$73 -> 199.00184 | L16: =PL!$L$73 -> 222.66008 | M16: =PL!$M$73 -> 246.50929
A17: 分部折舊攤銷（PP&E） | B17: US$bn | C17: =PL!$C$61 -> 32.067 | D17: =PL!$D$61 -> 41.86 | E17: =PL!$E$61 -> 41.238806 | F17: =PL!$F$61 -> 15.574039 | G17: =PL!$G$61 -> 56.812845 | H17: =PL!$H$61 -> 78.777146 | I17: =PL!$I$61 -> 114.57755 | J17: =PL!$J$61 -> 144.22846 | K17: =PL!$K$61 -> 173.94841 | L17: =PL!$L$61 -> 196.32786 | M17: =PL!$M$61 -> 210.36239
A18: 股份基礎給付（加回） | B18: US$bn | C18: =Q!$D$50 -> 22.011 | D18: =Q!$E$50 -> 19.467 | E18: =Q!$O$50 -> 15.476 | F18: =sbc_r*Seg!$F$30 -> 6.1084038 | G18: =CF!$E$18+CF!$F$18 -> 21.584404 | H18: =sbc_r*Seg!$H$30 -> 23.959348 | I18: =sbc_r*Seg!$I$30 -> 27.386251 | J18: =sbc_r*Seg!$J$30 -> 30.689736 | K18: =sbc_r*Seg!$K$30 -> 33.593338 | L18: =sbc_r*Seg!$L$30 -> 36.236117 | M18: =sbc_r*Seg!$M$30 -> 38.62658
A19: 其他營運項目（營運資金、影音內容與租賃現金支出、非現金業外） | B19: US$bn | C19: =Q!$D$46-CF!$C$16-CF!$C$17-CF!$C$18 -> 2.551 | D19: =Q!$E$46-CF!$D$16-CF!$D$17-CF!$D$18 -> 0.517 | E19: =Q!$O$46-CF!$E$16-CF!$E$17-CF!$E$18 -> -56.460806 | F19: =oth_q4*Seg!$F$30 -> 21.378923 | G19: =CF!$E$19+CF!$F$19 -> -35.081882 | H19: =oth_r*Seg!$H$30 -> 11.522338 | I19: =oth_r*Seg!$I$30 -> 13.170377 | J19: =oth_r*Seg!$J$30 -> 14.759063 | K19: =oth_r*Seg!$K$30 -> 16.155439 | L19: =oth_r*Seg!$L$30 -> 17.426383 | M19: =oth_r*Seg!$M$30 -> 18.575986 | P19: Q4 26＝oth_q4（2025Q4 同期比例，C14）× 營收；FY2027 起 oth_r（已含營運資金）；實績含持股評價利益的扣除
A20: 營運現金流 | B20: US$bn | C20: =Q!$D$46 -> 115.877 | D20: =Q!$E$46 -> 139.514 | E20: =Q!$O$46 -> 113.841 | F20: =CF!$F$16+CF!$F$17+CF!$F$18+CF!$F$19 -> 72.359208 | G20: =CF!$E$20+CF!$F$20 -> 186.20021 | H20: =CF!$H$16+CF!$H$17+CF!$H$18+CF!$H$19 -> 236.75812 | I20: =CF!$I$16+CF!$I$17+CF!$I$18+CF!$I$19 -> 300.43221 | J20: =CF!$J$16+CF!$J$17+CF!$J$18+CF!$J$19 -> 364.19764 | K20: =CF!$K$16+CF!$K$17+CF!$K$18+CF!$K$19 -> 422.69902 | L20: =CF!$L$16+CF!$L$17+CF!$L$18+CF!$L$19 -> 472.65044 | M20: =CF!$M$16+CF!$M$17+CF!$M$18+CF!$M$19 -> 514.07425
A21: 資本支出：AI（Thesis） | B21: US$bn | C21: =Thesis!$C$35 -> 25.278105 | D21: =Thesis!$D$35 -> 69.568632 | E21: =Thesis!$E$35 -> 123.19605 | F21: =Thesis!$F$35 -> 28.695619 | G21: =Thesis!$G$35 -> 151.89167 | H21: =Thesis!$H$35 -> 174.63089 | I21: =Thesis!$I$35 -> 180.87099 | J21: =Thesis!$J$35 -> 185.16482 | K21: =Thesis!$K$35 -> 136.51337 | L21: =Thesis!$L$35 -> 113.6249 | M21: =Thesis!$M$35 -> 112.22258
A22: 資本支出：AWS 其他（cx_awso × AWS 其他營收） | B22: US$bn | C22: =cx_awso*Seg!$C$28 -> 21.046999 | D22: =cx_awso*Seg!$D$28 -> 24.004246 | E22: =cx_awso*Seg!$E$28 -> 21.920458 | F22: =cx_awso*Seg!$F$28 -> 7.3959321 | G22: =CF!$E$22+CF!$F$22 -> 29.31639 | H22: =cx_awso*Seg!$H$28 -> 32.992083 | I22: =cx_awso*Seg!$I$28 -> 36.629573 | J22: =cx_awso*Seg!$J$28 -> 40.114023 | K22: =cx_awso*Seg!$K$28 -> 43.323145 | L22: =cx_awso*Seg!$L$28 -> 46.788997 | M22: =cx_awso*Seg!$M$28 -> 50.532117
A23: 資本支出：零售（cx_rt × 零售營收） | B23: US$bn | C23: =Q!$D$48-CF!$C$21-CF!$C$22 -> 31.332896 | D23: =Q!$E$48-CF!$D$21-CF!$D$22 -> 34.747122 | E23: =Q!$O$48-CF!$E$21-CF!$E$22 -> 27.071492 | F23: =cx_rt*Seg!$F$20 -> 11.720449 | G23: =CF!$E$23+CF!$F$23 -> 38.791941 | H23: =cx_rt*Seg!$H$20 -> 42.84209 | I23: =cx_rt*Seg!$I$20 -> 46.762548 | J23: =cx_rt*Seg!$J$20 -> 50.418589 | K23: =cx_rt*Seg!$K$20 -> 53.670701 | L23: =cx_rt*Seg!$L$20 -> 57.14886 | M23: =cx_rt*Seg!$M$20 -> 60.86995
A24: 資本支出（現金，淨額） | B24: US$bn | C24: =Q!$D$48 -> 77.658 | D24: =Q!$E$48 -> 128.32 | E24: =Q!$O$48 -> 172.188 | F24: =CF!$F$21+CF!$F$22+CF!$F$23 -> 47.812 | G24: =CF!$E$24+CF!$F$24 -> 220 | H24: =CF!$H$21+CF!$H$22+CF!$H$23 -> 250.46507 | I24: =CF!$I$21+CF!$I$22+CF!$I$23 -> 264.26311 | J24: =CF!$J$21+CF!$J$22+CF!$J$23 -> 275.69743 | K24: =CF!$K$21+CF!$K$22+CF!$K$23 -> 233.50722 | L24: =CF!$L$21+CF!$L$22+CF!$L$23 -> 217.56276 | M24: =CF!$M$21+CF!$M$22+CF!$M$23 -> 223.62465
