Workbook

Sheet README
A1: Dell Technologies（DELL US）收支與估值模型 v0.1.1（AI 半導體 Project：AI 伺服器品牌，樣板＝wiwynn/） 2026-10-25
A2: 版本：v0.1（初版）。Dell 是企業與 neocloud 的 AI 伺服器品牌（ISG：AI 伺服器、傳統伺服器與網通、儲存）兼 PC 大廠（CSG）。AI 伺服器以加速器顆數 × 每顆系統價值 × Dell 份額推；傳統伺服器、儲存、PC 另列，不隨 AI 情境。
A3: 模型命題：Dell 的 AI 伺服器營收＝商用 GPU 顆數（NVIDIA、AMD；tsmc 成品，同字母情境係數）× 每顆系統價值（橋接表機架價 ÷ 72）× Dell 有效份額（FY2027 以公司 AI 營收指引 740 億美元校準）× 份額相對值；營業利益＝AI 營益率（FY2027 殘差校準）× AI 營收＋非 AI ISG 與 CSG 營益率 × 營收。
A4: 核心問題：FY2027 指引 EPS 25.50 美元已比年初指引高一倍；在手訂單 950 億美元能否在 FY2028 轉成 AI 營收再成長、同時守住約 10% 的 AI 營益率？現價約 16 倍前瞻 P/E，高於 OEM 同業約 11 倍，隱含什麼路徑？
A5: ="重點觀察 1：目標價 US$"&TEXT(Val!$B$39,"0.00")&"（DCF "&TEXT(Val!$B$24,"0.00")&"、Comparable（相對倍數調整後）"&TEXT(tp_comp_adj,"0.00")&"；DCF 權重 "&TEXT(tp_w_dcf,"0%")&"），比現價 "&TEXT(px,"0.00")&"（2026-10-23）"&IF(Val!$B$42>=0,"高 "&TEXT(Val!$B$42,"0.0%"),"低 "&TEXT(-Val!$B$42,"0.0%"))&"，級距 "&Val!$B$48&"、投資建議 "&Val!$B$49&"。相對倍數調整係數 "&TEXT(rm_factor,"0.00")&"（本公司 10 年前瞻倍數中位數 ÷ 同業的中位數，夾在 0.5–2.0；Val 第 0.5 節），調整前加權上檔空間 "&TEXT((tp_w_dcf*Val!$B$24+(1-tp_w_dcf)*Val!$B$35)/px-1,"+0.0%;−0.0%")&"；Comparable 單獨（市場主流同業法、未調整）為 "&TEXT(Val!$B$43,"+0.0%;−0.0%")&"。"&"以下為 2026-10-29 相對倍數調整前撰寫的說明，其中數字為調整前：主因是倍數不是 EPS：本模型 12 個月後前瞻 EPS 28.54 只比共識前瞻 EPS 28.14 高 1.4%，但同業（HPE、Supermicro、Lenovo、HP Inc.、NetApp）前瞻 P/E 中位數 11.3 倍，現價隱含 16.2 倍、共識目標價 593 隱含 21.1 倍（比同業高 87%）；市場給"&" Dell 的 AI 份額溢價，Comparable 未計入。" -> 重點觀察 1：目標價 US$334.49（DCF 424.95、Comparable（相對倍數調整後）244.04；DCF 權重 50%），比現價 456.44（2026-10-23）低 26.7%，級距 −25%～−50%、投資建議 放空。相對倍數調整係數 0.74（本公司 10 年前瞻倍數中位數 ÷ 同業的中位數，夾在 0.5–2.0；Val 第 0.5 節），調整前加權上檔空間 −17.2%；Comparable 單獨（市場主流同業法、未調整）為 −27.4%。以下為 2026-10-29 相對倍數調整前撰寫的說明，其中數字為調整前：主因是倍數不是 EPS：本模型 12 個月後前瞻 EPS 28.54 只比共識前瞻 EPS 28.14 高 1.4%，但同業（HPE、Supermicro、Lenovo、HP Inc.、NetApp）前瞻 P/E 中位數 11.3 倍，現價隱含 16.2 倍、共識目標價 593 隱含 21.1 倍（比同業高 87%）；市場給 Dell 的 AI 份額溢價，Comparable 未計入。
A6: 重點觀察 2：FY2028 EPS 30.20（三情境相同）比共識 29.93 高 0.9%，前提是 AI 伺服器營收由 FY2027 指引 740 億美元升到 1,221 億美元（+65%；份額相對值 0.90 為 Assumed），2Q FY27 在手訂單 950 億美元可支撐約八成。追蹤 3Q FY27 財報（約 2026-11 下旬）的 AI 訂單、在手訂單與出貨。
A7: 重點觀察 3：AI 伺服器營益率是最大的不確定：公司不揭露，本模型以非 AI ISG 營益率 16% 拆分得 FY2027 約 11.1%（FY2026 約 5.4%）；拆分改用 19% 時 FY2028 EPS −11%，AI 營益率 −3pt 時 −10%。3Q FY27 的 ISG 營益率（2Q 為 15.0%）是第一個檢驗點。
A8: 會計年度：FY(t)＝t−1 年 2 月～t 年 1 月底，FY(t) 直接取 CY(t−1)（FY2027≈CY2026、FY2030≈CY2029）。金額：十億美元。口徑：non-GAAP（公司指引、共識、同業倍數一致）；GAAP EPS 只在 Q 頁對照。
A10: 驅動因子 → 推導量（全部唯讀上游，不修改）
A11: AI 伺服器營收：tsmc 成品的 Blackwell＋Hopper（GB300 級；2026 另含 AMD MI355）與 Rubin＋Rubin Ultra（VR200 級；2027 起另含 AMD MI450）顆數（世代分組與 Siliconomics Rack 頁、美超微模型相同，CF10） × 同字母情境係數 × 每顆系統價值（橋接表 Tokenomics v20.1 機架價 ÷ 72：GB300 約 59.7、VR200 約 116.7 千美元）＝商用 GPU 系統市場；× Dell 份額（FY2027 校準）× 份額相對值（Assumed）× 情境份額乘數（FY2029 起）。
A12: 非 AI：傳統伺服器與網通、儲存、CSG 依成長率推（Assumed，不隨 AI 情境）。營業利益：AI 營益率＝FY2027 殘差（ISG 營業利益 − 非 AI 營益率 16% × 非 AI 營收）＋ai_dm（FY2029 起加情境變動）；非 AI ISG、CSG 營益率為 Assumed。淨利＝分部營業利益 × 淨利係數；股數每年 −3%（回購）。
A13: 校準：FY2027 ＝ 公司全年指引（營收、AI 營收、non-GAAP EPS）＋1H FY27 實績＋2H 假設。不用券商數字（只在 Recon 對帳）。
A14: 估值：Val 第 0 節目標價＝0.5 × DCF 目標價（股東現金流＝EPS ×（1 − g／ROE），ROE 用預設 20%，FY2027 只計一個月，r 10%、g 4%，三情境權重 0.3／0.5／0.2）＋0.5 × Comparable 目標價（HPE、Supermicro、Lenovo、HP Inc.、NetApp 前瞻 P/E 中位數 × 12 個月後前瞻 EPS；不含 A 股）；另列 Comparable 單獨目標價、市場共識目標價、差距拆解與上檔空間級距。十年 P/E 規則值 × FY2027 EPS 保留為參考（不是目標價）。本版未做先驗，無 Andy 合理 P/E 對照。
A15: 預估期間：FY2028–FY2030 由驅動因子推導；FY2031 起為收斂法，非驅動因子推導（上游顆數到 CY2029＝FY2030；營收年增由 FY2030 線性收斂到 fade_g、淨利率收斂到 fade_m，FY2032 達到；PL 頁灰底）。
A16: 標記：Verified、Interested-party、Analogy、Assumed、Derived。SemiAnalysis 未使用。
A18: 已知限制：(1) AI 營益率公司不揭露，以非 AI 營益率 16% 拆分（Sens 有 19% 案例）；(2) 份額相對值、情境份額乘數與營益率變動是 Assumed；(3) AMD Helios、Rubin Ultra 每顆系統價值假設同 VR200；(4) 股東權益為負，ROE 用預設 20%；(5) 十年 P/E 只有 2019–2025，且為 GAAP；(6) 共識 FY2029 EPS 未找到；(7) 3Q FY27 財報（約 2026-11 下旬）後更新錨點；R4 產業部署路徑未建。
A19: v0.1.1（2026-10-28）：分部原則重建（數值不變）。Q 頁最後追加核對列「檢查：分部合計 − 合併營收」；官方分部與子列宣告見 segments.json。
A21: 2026-10-29：加權目標價中的 Comparable 改用相對倍數調整後的值（Val 第 0.5 節：同業前瞻倍數中位數 × 本公司 10 年相對同業的倍數比，Bloomberg 前瞻倍數；Andy 2026-10-27「照建議做」、10-29 資料取回）。「Comparable 目標價（市場主流同業法）」維持不調整。重點觀察 1 的第一句已改為公式；重點觀察 2、3 與其他說明中的目標價與上檔空間數字為調整前撰寫，以 Val 頁為準。

Sheet In
A1: In — 輸入（藍字；基準欄 E，低 D、高 F）。金額：十億美元（US$B）；每顆系統價值：千美元／顆；比例：%。口徑：non-GAAP。每個輸入盡量附兩個來源（找不到者寫「未找到」）；公司原文算一個
A2: 標記：Verified／Interested-party／Analogy／Assumed／Derived；Analogy、Assumed 給低／高區間，不當點估計（放情境或 Sens）。SemiAnalysis 未使用。公司原文＝Dell 8-K 財報新聞稿（SEC）；公司指引與展望為 Interested-party；券商與資料商估計皆為 Interested-party。加速器顆數讀 tsmc 成品、每顆系統價值讀橋接表（唯讀）
A3: 鍵 | B3: 項目 | C3: 單位 | D3: 低 | E3: 基準 | F3: 高 | G3: 標記 | H3: 來源1 | I3: 來源2／說明
A4: A. 加速器顆數與每顆系統價值（讀 tsmc、markets/chip_bridge 成品；情境 A 基準，B／C 依同字母顆數係數縮放）
A5: ug_26 | B5: GB300 級商用 GPU 顆數 CY2026（Blackwell＋Hopper＋AMD MI355） | C5: 百萬顆 | E5: 6.65 | G5: Derived | H5: tsmc/dist/20261028_台積電個股模型_v0.4.xlsx｜In!E5:E24 | I5: tsmc 成品 u_bw、u_hp（2026 另含 u_amd）；CY2029＝CY2028 × (1＋各類成長)；世代分組與 Siliconomics Rack 頁、美超微模型相同（CF10）
A6: ug_27 | B6: GB300 級商用 GPU 顆數 CY2027（Blackwell＋Hopper） | C6: 百萬顆 | E6: 2.4 | G6: Derived | H6: 同上 | I6: 同上
A7: ug_28 | B7: GB300 級商用 GPU 顆數 CY2028（Blackwell＋Hopper） | C7: 百萬顆 | E7: 0.5 | G7: Derived | H7: 同上 | I7: 同上
A8: ug_29 | B8: GB300 級商用 GPU 顆數 CY2029（Blackwell＋Hopper） | C8: 百萬顆 | E8: 0.25 | G8: Derived | H8: 同上 | I8: 同上
A9: uv_26 | B9: VR200 級商用 GPU 顆數 CY2026（Rubin＋Rubin Ultra） | C9: 百萬顆 | E9: 1.7 | G9: Derived | H9: tsmc/dist/20261028_台積電個股模型_v0.4.xlsx｜In!E5:E24 | I9: tsmc 成品 u_rb、u_ru、u_amd；Google TPU、Trainium 與其他 ASIC 不含（雲端自建，Dell 不是主要供應商）
A10: uv_27 | B10: VR200 級商用 GPU 顆數 CY2027（Rubin＋Rubin Ultra＋AMD MI450） | C10: 百萬顆 | E10: 8.8 | G10: Derived | H10: 同上 | I10: 同上
A11: uv_28 | B11: VR200 級商用 GPU 顆數 CY2028（Rubin＋Rubin Ultra＋AMD MI450） | C11: 百萬顆 | E11: 11 | G11: Derived | H11: 同上 | I11: 同上
A12: uv_29 | B12: VR200 級商用 GPU 顆數 CY2029（Rubin＋Rubin Ultra＋AMD MI450） | C12: 百萬顆 | E12: 12.65 | G12: Derived | H12: 同上 | I12: 同上
A13: um28_A | B13: 情境 A：CY2028 顆數 ÷ 基準 | C13: x | E13: 1 | G13: Assumed | H13: tsmc/dist/20261028_台積電個股模型_v0.4.xlsx｜In!E37 | I13: A＝順利（基準）；B＝平平；C＝不如預期；與台積電、廣達、緯穎模型同字母
A14: um29_A | B14: 情境 A：CY2029 顆數 ÷ 基準 | C14: x | E14: 1 | G14: Assumed | H14: tsmc/dist/20261028_台積電個股模型_v0.4.xlsx｜In!E38 | I14: 同上
A15: um28_B | B15: 情境 B：CY2028 顆數 ÷ 基準 | C15: x | E15: 0.8 | G15: Assumed | H15: tsmc/dist/20261028_台積電個股模型_v0.4.xlsx｜In!E39 | I15: A＝順利（基準）；B＝平平；C＝不如預期；與台積電、廣達、緯穎模型同字母
A16: um29_B | B16: 情境 B：CY2029 顆數 ÷ 基準 | C16: x | E16: 0.85 | G16: Assumed | H16: tsmc/dist/20261028_台積電個股模型_v0.4.xlsx｜In!E40 | I16: 同上
... A18: um29_C | B18: 情境 C：CY2029 顆數 ÷ 基準 | C18: x | E18: 0.6 | G18: Assumed | H18: tsmc/dist/20261028_台積電個股模型_v0.4.xlsx｜In!E42 | I18: 同上
A19: v_gb | B19: 每顆系統價值（GB300 NVL72 機架價 ÷ 72） | C19: US$K/顆 | D19: 55.555556 | E19: 59.722222 | F19: 69.444444 | G19: Derived | H19: markets/chip_bridge/dist/20261027_晶片內容橋接表_v0.2.2.xlsx｜In!D5:I5（機架單價）÷ In!E14（每架 GPU 數） | I19: Tokenomics v20.1 機架單價（經橋接表；唯讀）；Dell 為 OEM，營收含整櫃（含 GPU）
A20: v_vr | B20: 每顆系統價值（VR200 NVL72 機架價 ÷ 72；AMD Helios 假設相同） | C20: US$K/顆 | D20: 104.16667 | E20: 116.66667 | F20: 126.38889 | G20: Derived | H20: markets/chip_bridge/dist/20261027_晶片內容橋接表_v0.2.2.xlsx｜In!D5:I5（機架單價）÷ In!E14（每架 GPU 數） | I20: 同上；AMD MI450／Rubin Ultra 每顆價值未另訂（Assumed：同 VR200）
A21: mf | B21: AI 部署係數（Sens 用；FY2028 起） | C21: x | D21: 0.8 | E21: 1 | F21: 1.2 | G21: Assumed | H21: 無 | I21: ±20%
A22: B. Dell 份額（FY2027 以公司 AI 伺服器營收指引校準）
A23: rel_28 | B23: Dell 份額相對值 FY2028 ÷ FY2027（全部情境） | C23: x | D23: 0.75 | E23: 0.9 | F23: 1.05 | G23: Assumed | H23: Dell 8-K 2Q FY27（2026-09-01）：2Q FY27 AI 訂單 609 億美元、在手訂單 950 億美元（公司） | I23: Pulse 2.0 2026-09-01：近四季 AI 訂單 1,317 億美元；份額下檔：雲端與 neocloud 直接向 ODM 採購、Supermicro／HPE 競價
A24: rel_29 | B24: Dell 份額相對值 FY2029 ÷ FY2027 | C24: x | D24: 0.65 | E24: 0.85 | F24: 1 | G24: Assumed | H24: 同上；客戶集中於 neocloud 與大型 AI 實驗室（xAI、CoreWeave 等，媒體） | I24: —
A25: rel_30 | B25: Dell 份額相對值 FY2030 ÷ FY2027 | C25: x | D25: 0.55 | E25: 0.8 | F25: 1 | G25: Assumed | H25: 同上 | I25: —
A26: srel_A | B26: 情境 A：FY2029 起份額額外乘數 | C26: x | E26: 1 | G26: Assumed | H26: 公司特有變數依情境調整，方向 A 最有利 | I26: —
A27: srel_B | B27: 情境 B：FY2029 起份額額外乘數 | C27: x | E27: 0.95 | G27: Assumed | H27: AI 資本支出消化時，neocloud 客戶（信用較弱）先縮 | I27: —
A28: srel_C | B28: 情境 C：FY2029 起份額額外乘數 | C28: x | E28: 0.85 | G28: Assumed | H28: 同上，下修更深 | I28: —
A29: C. FY2027 錨點（1H FY27 實績＋公司全年指引＋2H 假設）
A30: g_rev | B30: FY2027 營收指引 | C30: US$B | D30: 190 | E30: 192 | F30: 194 | G30: Interested-party | H30: Dell 8-K 2Q FY27（2026-09-01）：FY27 營收 1,920 億美元（由 1,670 上修） | I30: Zacks 2026-09：±20 億美元
A31: g_ai | B31: FY2027 AI 伺服器營收指引 | C31: US$B | E31: 74 | G31: Interested-party | H31: Dell 8-K 2Q FY27（2026-09-01）：FY27 AI-Optimized Servers 約 740 億美元（由 600 上修） | I31: Pulse 2.0 2026-09-01：同
A32: g_eps | B32: FY2027 non-GAAP EPS 指引 | C32: US$ | D32: 25.25 | E32: 25.5 | F32: 25.75 | G32: Interested-party | H32: Dell 8-K 2Q FY27（2026-09-01）：non-GAAP 稀釋 EPS 25.50（GAAP 24.37） | I32: Zacks 2026-09：±0.25
A33: g_q3rev | B33: 3Q FY27 營收指引（參考） | C33: US$B | D33: 48.5 | E33: 49 | F33: 49.5 | G33: Interested-party | H33: Dell 8-K 2Q FY27（2026-09-01）：3Q FY27 營收 490 億美元、non-GAAP EPS 6.50 | I33: Zacks 2026-09：±5 億美元
A34: st_h2 | B34: 2H FY27 儲存營收 ÷ 1H | C34: x | D34: 1.05 | E34: 1.12 | F34: 1.2 | G34: Assumed | H34: StorageNewsletter 2026-09-03：3Q 儲存年增約 mid-teens、全年約 200 億美元（媒體轉述） | I34: 1H FY27 91.84 億 × 1.12 ＝ 2H 102.9 億（全年 194.7 億）
A35: csg_h2 | B35: 2H FY27 CSG 營收 ÷ 1H − 1 | C35: % | D35: -0.03 | E35: 0.03 | F35: 0.08 | G35: Assumed | H35: CSG 2Q FY27 年增 20%、季增 6%（公司） | I35: 公司未給 CSG 全年指引：未找到
A36: isg_h2m | B36: 2H FY27 ISG 營業利益率 | C36: % | D36: 0.12 | E36: 0.135 | F36: 0.155 | G36: Assumed | H36: Dell 8-K 2Q FY27（2026-09-01）：2Q FY27 ISG 營益率 15.0%、1H 12.9%（公司） | I36: AI 比重上升稀釋 ISG 營益率（Assumed）
A37: csg_h2m | B37: 2H FY27 CSG 營業利益率 | C37: % | D37: 0.065 | E37: 0.075 | F37: 0.08 | G37: Assumed | H37: Dell 8-K 2Q FY27（2026-09-01）：2Q FY27 CSG 營益率 7.6%、1H 7.8%（公司） | I37: FY26 5.6%
A38: h2_sh | B38: 2H FY27 稀釋股數（3Q、4Q 平均） | C38: 十億股 | D38: 0.635 | E38: 0.642 | F38: 0.65 | G38: Assumed | H38: Dell 8-K 2Q FY27（2026-09-01）：2Q 稀釋股數 6.52 億、1H 6.54 億；2Q 買回 950 萬股（均價 401 美元） | I38: stockanalysis.com（統計）：流通股數 6.3581 億股（2026-10-23）
A39: m_nai | B39: 非 AI ISG（傳統伺服器、網通、儲存）營業利益率（拆分 AI 毛利用） | C39: % | D39: 0.14 | E39: 0.16 | F39: 0.19 | G39: Assumed | H39: 公司不揭露 AI 伺服器營益率：未找到 | I39: FY26：ISG 營益率 11.7%；非 AI 取 16% 時 AI 約 5%（Q 頁檢查列）
A40: D. 營業利益率（FY2028 起）
A41: ai_dm | B41: AI 伺服器營業利益率變動（FY2028 起，相對 FY2027 校準值；全部情境） | C41: pt | D41: -0.03 | E41: -0.01 | F41: 0.01 | G41: Assumed | H41: Rubin 機架單價較高、GPU 轉手比重高，營益率（%）下降；規模效益為上檔 | I41: —
A42: dm_A | B42: 情境 A：FY2029 起 AI 營益率額外變動 | C42: pt | E42: 0 | G42: Assumed | H42: 方向：A 最有利 | I42: —
A43: dm_B | B43: 情境 B：FY2029 起 AI 營益率額外變動 | C43: pt | E43: -0.01 | G43: Assumed | H43: 需求放緩時價格競爭（Supermicro、HPE、ODM 直供） | I43: —
A44: dm_C | B44: 情境 C：FY2029 起 AI 營益率額外變動 | C44: pt | E44: -0.025 | G44: Assumed | H44: 同上，更深 | I44: —
A45: m_naif | B45: 非 AI ISG 營業利益率（FY2028 起） | C45: % | D45: 0.135 | E45: 0.155 | F45: 0.175 | G45: Assumed | H45: FY2027 傳統伺服器受記憶體漲價帶動（2Q 年增 122%），FY2028 起正常化 | I45: —
A46: m_csgf | B46: CSG 營業利益率（FY2028 起） | C46: % | D46: 0.06 | E46: 0.07 | F46: 0.08 | G46: Assumed | H46: FY26 5.6%、1H FY27 7.8%（公司） | I46: 記憶體成本上升為下檔
A47: E. 非 AI 營收成長（不隨 AI 情境）
A48: g_tr28 | B48: 傳統伺服器與網通年增 FY2028 | C48: % | D48: -0.15 | E48: -0.05 | F48: 0.05 | G48: Assumed | H48: FY27 1H 年增約 115%（記憶體轉嫁與換機潮，公司） | I48: —
A49: g_tr29 | B49: 傳統伺服器與網通年增 FY2029 | C49: % | D49: -0.05 | E49: 0.02 | F49: 0.06 | G49: Assumed | H49: 同上 | I49: —
A50: g_tr30 | B50: 傳統伺服器與網通年增 FY2030 | C50: % | D50: -0.03 | E50: 0.03 | F50: 0.06 | G50: Assumed | H50: 同上 | I50: —
A51: g_st28 | B51: 儲存年增 FY2028 | C51: % | D51: -0.03 | E51: 0.04 | F51: 0.1 | G51: Assumed | H51: FY26 +1%、2Q FY27 +26%（公司） | I51: —
A52: g_st29 | B52: 儲存年增 FY2029 | C52: % | D52: -0.02 | E52: 0.04 | F52: 0.08 | G52: Assumed | H52: 同上 | I52: —
A53: g_st30 | B53: 儲存年增 FY2030 | C53: % | D53: -0.02 | E53: 0.04 | F53: 0.08 | G53: Assumed | H53: 同上 | I53: —
A54: g_csg28 | B54: CSG（PC）年增 FY2028 | C54: % | D54: -0.06 | E54: 0.03 | F54: 0.08 | G54: Assumed | H54: FY26 +5%、2Q FY27 +20%（Windows 10 換機、商用；公司） | I54: —
A55: g_csg29 | B55: CSG（PC）年增 FY2029 | C55: % | D55: -0.04 | E55: 0.03 | F55: 0.06 | G55: Assumed | H55: 同上 | I55: —
A56: g_csg30 | B56: CSG（PC）年增 FY2030 | C56: % | D56: -0.04 | E56: 0.03 | F56: 0.06 | G56: Assumed | H56: 同上 | I56: —
A57: F. 淨利係數、股數（FY2028 起）
A58: nio_f | B58: non-GAAP 淨利 ÷ 分部營業利益 | C58: % | D58: 0.7 | E58: 0.75 | F58: 0.78 | G58: Derived | H58: 1H FY27 7.781 ÷ 10.148＝0.767；FY26 7.046 ÷ 9.944＝0.709（公司） | I58: 利息費用、稅率（non-GAAP 固定稅率；數值未找到）
A59: sh_g | B59: 稀釋股數年變動 | C59: % | D59: -0.05 | E59: -0.03 | F59: -0.01 | G59: Assumed | H59: FY26→1H FY27：6.84 → 6.54 億股（−4%，公司） | I59: 回購授權與自由現金流（1H FY27 調整後 113 億美元）
A60: G. 共識（只作 Recon 對帳，不作校準）
A61: c_rev27 | B61: 共識 FY2027 營收（22 位） | C61: US$B | E61: 193.4 | G61: Interested-party | H61: stockanalysis.com（預估）（2026-10-21） | I61: —
A62: c_eps27 | B62: 共識 FY2027 non-GAAP EPS（22 位） | C62: US$ | E62: 25.9 | G62: Interested-party | H62: stockanalysis.com（預估）（2026-10-21；高 28.93、低 25.50） | I62: —
A63: c_rev28 | B63: 共識 FY2028 營收 | C63: US$B | E63: 229.12 | G63: Interested-party | H63: stockanalysis.com（預估）：Revenue Next Year +18.44% | I63: —
A64: c_eps28 | B64: 共識 FY2028 non-GAAP EPS | C64: US$ | E64: 29.93 | G64: Interested-party | H64: stockanalysis.com（預估）：EPS Next Year +15.56% | I64: FY2029 共識 EPS：未找到
A65: H. 價格與市場倍數
A66: px | B66: 股價（2026-10-23 收盤） | C66: US$ | E66: 456.44 | G66: Interested-party | H66: stockanalysis.com（統計）：10-23 收盤 456.44 | I66: MarketScreener：10-23 收盤 456.44
A67: pe_ttm | B67: 近 12 月 P/E（GAAP，stockanalysis） | C67: x | E67: 26.63 | G67: Interested-party | H67: stockanalysis.com（統計） | I67: —
A68: fpe | B68: 前瞻 P/E（stockanalysis，10-23） | C68: x | E68: 16.22 | G68: Interested-party | H68: stockanalysis.com（統計） | I68: —
A69: cons_feps | B69: 共識前瞻 12 月 EPS（現價 ÷ 前瞻 P/E） | C69: US$ | E69: =px/fpe -> 28.140567 | G69: Derived | H69: stockanalysis 前瞻 P/E 16.22（2026-10-23） | I69: 共識前瞻 EPS 的直接數字：未找到
A70: cons_tp | B70: 市場共識目標價（賣方平均） | C70: US$ | D70: 480 | E70: 593 | F70: 735 | G70: Interested-party | H70: stockanalysis.com（預估）：29 位平均 593、中位數 600、最高 735、最低 480（2026-10-21） | I70: MarketScreener：29 位平均 593；Alpha Spread：599.25；Investing.com：23 位 502.78（日期不明）
A71: so | B71: 流通股數 | C71: 十億股 | E71: 0.63581 | G71: Interested-party | H71: stockanalysis.com（統計）（2026-10-23） | I71: —
A72: I. 目標價與收斂法參數（黃底；Assumed，Andy 可改）
A73: tp_wA | B73: 目標價情境權重 A（A 順利／B 平平／C 不如預期） | C73: % | E73: 0.3 | G73: Assumed | H73: Andy 可改（工作單 2026-10-25 預設 A 0.3／B 0.5／C 0.2） | I73: 三者合計應為 100%
A74: tp_wB | B74: 目標價情境權重 B（A 順利／B 平平／C 不如預期） | C74: % | E74: 0.5 | G74: Assumed | H74: Andy 可改（工作單 2026-10-25 預設 A 0.3／B 0.5／C 0.2） | I74: 三者合計應為 100%
A75: tp_wC | B75: 目標價情境權重 C（A 順利／B 平平／C 不如預期） | C75: % | E75: 0.2 | G75: Assumed | H75: Andy 可改（工作單 2026-10-25 預設 A 0.3／B 0.5／C 0.2） | I75: 三者合計應為 100%
A76: tp_r | B76: 折現率／要求報酬 | C76: % | E76: 0.1 | G76: Assumed | H76: Andy 可改（工作單預設 10%；美、台、日、韓同一值） | I76: 淨負債約 237 億美元、股東權益為負，財務槓桿高於同業；未改折現率，只在方法欄說明
A77: tp_g | B77: 長期成長率 | C77: % | E77: 0.04 | G77: Assumed | H77: Andy 可改（工作單預設 4%） | I77: DCF 永續成長率；FY2032 收斂目標（情境 B）
A78: tp_roe | B78: ROE（近三年平均） | C78: % | E78: 0.2 | G78: Assumed | H78: 股東權益為負（FY26 年底 −24.70 億、2Q FY27 −14.27 億美元，公司），ROE 無意義：未找到 | I78: 依工作單用預設 0.20；stockanalysis ROE 顯示 n/a、ROIC 29.36%
A79: tp_w_dcf | B79: 目標價中 DCF 的權重；其餘為 Comparable | C79: % | E79: 0.5 | G79: Assumed | H79: Andy 可改（Andy 2026-10-25 11:53 定各半） | I79: —
A80: nm10_k | B80: 十年平均淨利率替代：最後一年淨利率 × 係數 | C80: x | E80: 0.8 | G80: Assumed | H80: non-GAAP 十年淨利率序列：未找到（FY2017–FY2020 含 EMC 併購虧損，GAAP 不可比） | I80: 工作單：找不到十年平均用最後一年 × 0.8
A81: fade_gA | B81: 情境 A：FY2032 營收年增收斂目標（tp_g＋2pt） | C81: % | E81: =tp_g+0.02 -> 0.06 | G81: Assumed | H81: 工作單 2026-10-25 11:20 收斂法 | I81: FY2031 起由 FY2030 年增線性收斂
A82: fade_gB | B82: 情境 B：FY2032 營收年增收斂目標（＝tp_g） | C82: % | E82: =tp_g -> 0.04 | G82: Assumed | H82: 同上 | I82: —
A83: fade_gC | B83: 情境 C：FY2032 營收年增收斂目標（tp_g−2pt） | C83: % | E83: =tp_g-0.02 -> 0.02 | G83: Assumed | H83: 同上 | I83: —
A84: fade_mA | B84: 情境 A：FY2032 淨利率收斂目標（＝情境 A FY2030 淨利率） | C84: % | E84: =PL!G14 -> 0.07862542 | G84: Derived | H84: PL 頁情境 A FY2030（公式於建置時連結） | I84: —
A85: fade_mB | B85: 情境 B：FY2032 淨利率收斂目標（FY2030 與替代十年平均的中點） | C85: % | E85: =PL!G28*(1+nm10_k)/2 -> 0.067797277 | G85: Derived | H85: PL 頁情境 B FY2030 × (1＋nm10_k) ÷ 2 | I85: —
A86: fade_mC | B86: 情境 C：FY2032 淨利率收斂目標（替代十年平均＝FY2030 × nm10_k） | C86: % | E86: =PL!G42*nm10_k -> 0.058165988 | G86: Assumed | H86: PL 頁情境 C FY2030 × nm10_k | I86: —

Sheet Q
A1: Q — 實績與 FY2027 錨點（十億美元；EPS 美元；股數十億股；non-GAAP）。藍字＝輸入；黑字＝公式。實績取自 Dell 8-K 財報新聞稿（SEC）
A2: FY2027 錨點＝公司全年指引（營收 1,920 億、AI 伺服器 740 億、non-GAAP EPS 25.50）＋1H FY27 實績＋2H 假設（儲存、CSG、ISG 與 CSG 營益率、股數）；傳統伺服器與網通為全年營收殘差。分部營業利益合計約等於 non-GAAP 營業利益（FY26 差 0.05、1H FY27 差 0.02）
A3: 項目 | B3: FY2026A | C3: 1H FY27（實績） | D3: 2H FY27（模型） | E3: FY2027 錨點 | G3: 標記 | H3: 來源1（公司） | I3: 來源2／說明
A4: AI 伺服器（AI-Optimized Servers） | B4: 24.683 | C4: 32.533 | D4: =g_ai-C4 -> 41.467 | E4: =g_ai -> 74 | G4: Verified／Interested-party（全年指引） | H4: FY2026：Dell 8-K 4Q FY26（2026-02-26）；1H FY27：Dell 8-K 2Q FY27（2026-09-01） | I4: 1Q FY27 161.32 億、2Q 164.01 億
A5: 傳統伺服器與網通 | B5: 19.512 | C5: 19.074 | D5: =E5-C5 -> 18.52263 | E5: =g_rev-E4-E6-E8-E9 -> 37.59663 | G5: Verified／Derived（全年殘差） | H5: FY2026：Dell 8-K 4Q FY26（2026-02-26）；1H FY27：Dell 8-K 2Q FY27（2026-09-01） | I5: 1Q 85.43 億、2Q 105.31 億
A6: 儲存 | B6: 16.631 | C6: 9.184 | D6: =C6*st_h2 -> 10.28608 | E6: =C6+D6 -> 19.47008 | G6: Verified／Assumed（2H） | H6: FY2026：Dell 8-K 4Q FY26（2026-02-26）；1H FY27：Dell 8-K 2Q FY27（2026-09-01） | I6: 1Q 43.34 億、2Q 48.50 億
A7: ISG 營收 | B7: =B4+B5+B6 -> 60.826 | C7: =C4+C5+C6 -> 60.791 | D7: =D4+D5+D6 -> 70.27571 | E7: =C7+D7 -> 131.06671 | G7: Derived | H7: FY2026：Dell 8-K 4Q FY26（2026-02-26）；1H FY27：Dell 8-K 2Q FY27（2026-09-01） | I7: FY26 608.26、1H FY27 607.91（公司合計）
A8: CSG 營收（商用＋消費） | B8: 50.984 | C8: 29.643 | D8: =C8*(1+csg_h2) -> 30.53229 | E8: =C8+D8 -> 60.17529 | G8: Verified／Assumed（2H） | H8: FY2026：Dell 8-K 4Q FY26（2026-02-26）；1H FY27：Dell 8-K 2Q FY27（2026-09-01） | I8: FY26 商用 440.62、消費 69.22；1H FY27 商用 262.12、消費 34.31
A9: 其他業務（營收 − ISG − CSG） | B9: =B10-B7-B8 -> 1.728 | C9: =C10-C7-C8 -> 0.379 | D9: =C9 -> 0.379 | E9: =C9+D9 -> 0.758 | G9: Derived／Assumed（2H＝1H） | H9: FY2026：Dell 8-K 4Q FY26（2026-02-26）；1H FY27：Dell 8-K 2Q FY27（2026-09-01） | I9: Secureworks 出售後的剩餘業務、VMware 轉售等；營業利益併入淨利係數
A10: 營收 | B10: 113.538 | C10: 90.813 | D10: =E10-C10 -> 101.187 | E10: =g_rev -> 192 | G10: Verified／Interested-party（全年指引） | H10: FY2026：Dell 8-K 4Q FY26（2026-02-26）；1H FY27：Dell 8-K 2Q FY27（2026-09-01） | I10: FY27 錨點＝全年指引 1,920 億
A11: ISG 營業利益 | B11: 7.111 | C11: 7.836 | D11: =D7*isg_h2m -> 9.4872208 | E11: =C11+D11 -> 17.323221 | G11: Verified／Assumed（2H） | H11: FY2026：Dell 8-K 4Q FY26（2026-02-26）；1H FY27：Dell 8-K 2Q FY27（2026-09-01） | I11: 2Q FY27 47.81 億（營益率 15.0%）
A12: CSG 營業利益 | B12: 2.833 | C12: 2.312 | D12: =D8*csg_h2m -> 2.2899217 | E12: =C12+D12 -> 4.6019217 | G12: Verified／Assumed（2H） | H12: FY2026：Dell 8-K 4Q FY26（2026-02-26）；1H FY27：Dell 8-K 2Q FY27（2026-09-01） | I12: 2Q FY27 11.42 億（7.6%）
A13: 分部營業利益合計 | B13: =B11+B12 -> 9.944 | C13: =C11+C12 -> 10.148 | D13: =D11+D12 -> 11.777143 | E13: =C13+D13 -> 21.925143 | G13: Derived | H13: FY2026：Dell 8-K 4Q FY26（2026-02-26）；1H FY27：Dell 8-K 2Q FY27（2026-09-01） | I13: non-GAAP 營業利益：FY26 99.91、1H FY27 101.64（公司）
A14: non-GAAP 營業利益（公司揭露） | B14: 9.991 | C14: 10.164 | G14: Verified | H14: FY2026：Dell 8-K 4Q FY26（2026-02-26）；1H FY27：Dell 8-K 2Q FY27（2026-09-01） | I14: —
A15: non-GAAP 淨利 | B15: 7.046 | C15: 7.781 | D15: =E15-C15 -> 8.743 | E15: =g_eps*E17 -> 16.524 | G15: Verified／Interested-party（全年＝指引 EPS × 股數） | H15: FY2026：Dell 8-K 4Q FY26（2026-02-26）；1H FY27：Dell 8-K 2Q FY27（2026-09-01） | I15: GAAP 淨利 FY26 59.36、1H FY27 75.71
A16: 淨利 ÷ 分部營業利益 | B16: =B15/B13 -> 0.70856798 | C16: =C15/C13 -> 0.76675207 | D16: =D15/D13 -> 0.74237022 | E16: =E15/E13 -> 0.7536553 | G16: Derived | H16: — | I16: FY2028 起 nio_f 的對照
A17: 稀釋股數（十億股） | B17: =7.046/10.3 -> 0.68407767 | C17: 0.654 | D17: =h2_sh -> 0.642 | E17: =(C17+D17)/2 -> 0.648 | G17: Verified／Derived／Assumed | H17: FY2026：Dell 8-K 4Q FY26（2026-02-26）；1H FY27：Dell 8-K 2Q FY27（2026-09-01） | I17: FY26＝non-GAAP 淨利 ÷ non-GAAP EPS；1H FY27 公司揭露 6.54 億
A18: non-GAAP EPS | B18: =B15/B17 -> 10.3 | C18: =C15/C17 -> 11.897554 | D18: =D15/D17 -> 13.61838 | E18: =E15/E17 -> 25.5 | G18: Derived | H18: 淨利 ÷ 股數 | I18: —
A19: 公司揭露 non-GAAP EPS | B19: 10.3 | C19: 11.9 | E19: =g_eps -> 25.5 | G19: Verified／Interested-party（指引） | H19: FY2026：Dell 8-K 4Q FY26（2026-02-26）；1H FY27：Dell 8-K 2Q FY27（2026-09-01） | I19: GAAP EPS：FY26 8.68、1H FY27 11.58、FY27 指引 24.37
A21: 錨點與拆分的檢查（參考；校準未使用券商數字）
A22: FY2027 營收年增 | B22: =E10/B10-1 -> 0.69106378
A23: 2H FY27 傳統伺服器與網通 ÷ 1H − 1 | B23: =D5/C5-1 -> -0.028906889
A24: FY2026 AI 伺服器營業利益率（隱含；非 AI ISG 取 m_nai） | B24: =(B11-m_nai*(B5+B6))/B4 -> 0.053807074
A25: FY2027 AI 伺服器營業利益率（隱含；PL 校準值） | B25: =(E11-m_nai*(E5+E6))/E4 -> 0.1107101
A26: FY2027 EPS ÷ 共識（25.90）− 1 | B26: =E18/c_eps27-1 -> -0.015444015
A27: 1H FY27 EPS 自算 − 公司揭露（應約為 0） | B27: =C18-C19 -> -0.0024464832
A28: 2H FY27 non-GAAP EPS（隱含；3Q 指引 6.50） | B28: =D18 -> 13.61838
A30: 檢查：分部合計 − 合併營收 | B30: =ROUND(B7+B8+B9-B10,3) -> 0 | C30: =ROUND(C7+C8+C9-C10,3) -> 0 | D30: =ROUND(D7+D8+D9-D10,3) -> 0 | E30: =ROUND(E7+E8+E9-E10,3) -> 0
A31: 分部原則第 3 條（2026-10-28 追加）：其他業務為差額；分部宣告見 segments.json

Sheet Units
A1: Units — 商用 GPU 系統市場（tsmc 顆數 × 橋接表每顆系統價值）、Dell 份額與組裝廠份額對照（情境 A）。FY(t)≈CY(t−1)
A3: 項目 | B3: 單位 | C3: CY2026（FY2027） | D3: CY2027（FY2028） | E3: CY2028（FY2029） | F3: CY2029（FY2030） | G3: 說明
A4: GB300 級 GPU 顆數（Blackwell＋Hopper） | B4: 百萬顆 | C4: =PL!D63 -> 6.65 | D4: =PL!E63 -> 2.4 | E4: =PL!F63 -> 0.5 | F4: =PL!G63 -> 0.25 | G4: tsmc 成品
A5: VR200 級 GPU 顆數（Rubin＋Rubin Ultra；2027 起＋AMD） | B5: 百萬顆 | C5: =PL!D64 -> 1.7 | D5: =PL!E64 -> 8.8 | E5: =PL!F64 -> 11 | F5: =PL!G64 -> 12.65 | G5: tsmc 成品
A6: 每顆系統價值 GB300 級 | B6: US$K/顆 | C6: =v_gb -> 59.722222 | D6: =v_gb -> 59.722222 | E6: =v_gb -> 59.722222 | F6: =v_gb -> 59.722222 | G6: 橋接表機架價 ÷ 72
A7: 每顆系統價值 VR200 級 | B7: US$K/顆 | C7: =v_vr -> 116.66667 | D7: =v_vr -> 116.66667 | E7: =v_vr -> 116.66667 | F7: =v_vr -> 116.66667 | G7: 同上
A8: 商用 GPU 系統市場（整櫃售價） | B8: US$B | C8: =PL!D65 -> 595.48611 | D8: =PL!E65 -> 1170 | E8: =PL!F65 -> 1313.1944 | F8: =PL!G65 -> 1490.7639 | G8: OEM／整櫃售價口徑（含 GPU）
A9: Dell 有效份額 | B9: % | C9: =PL!D69 -> 0.12426822 | D9: =PL!E69 -> 0.1118414 | E9: =PL!F69 -> 0.10562799 | F9: =PL!G69 -> 0.099414577 | G9: FY2027 以 AI 營收指引 740 億校準
A10: Dell AI 伺服器營收 | B10: US$B | C10: =PL!D70 -> 74 | D10: =PL!E70 -> 130.85444 | E10: =PL!F70 -> 138.71009 | F10: =PL!G70 -> 148.20366
A11: 隱含 Dell 出貨櫃數（NVL72 等值，按當年組合） | B11: 千櫃 | C11: =PL!D70/PL!D65*(PL!D63+PL!D64)/72*1000 -> 14.411662 | D11: =PL!E70/PL!E65*(PL!E63+PL!E64)/72*1000 -> 17.397551 | E11: =PL!F70/PL!F65*(PL!F63+PL!F64)/72*1000 -> 16.871137 | F11: =PL!G70/PL!G65*(PL!G63+PL!G64)/72*1000 -> 17.811778 | G11: 營收 ÷ 平均每櫃售價
A12: 對照：AI 伺服器組裝市場（ODM 價，廣達模型；含 ASIC） | B12: US$B | C12: 634.61653 | D12: 1139.0807 | E12: 1443.9178 | F12: 1644.8506 | G12: quanta/dist/20261028_廣達個股模型_v0.3.xlsx｜Units!C6:F6
A13: Dell AI 營收 ÷ 組裝市場（ODM 口徑） | B13: % | C13: =C10/C12 -> 0.11660585 | D13: =D10/D12 -> 0.11487723 | E13: =E10/E12 -> 0.096065088 | F13: =F10/F12 -> 0.090101594 | G13: Dell 為 OEM 售價、含加價，同口徑時份額更低
A14: 對照：鴻海＋廣達＋緯創（含緯穎）合計有效份額（緯創模型） | B14: % | C14: 0.43018513 | D14: 0.43018513 | E14: 0.41911484 | F14: 0.39760559 | G14: wistron/dist/20261028_緯創個股模型_v0.2.xlsx｜Units!C11:F11
A15: 合計：ODM 三家＋Dell（未扣重複） | B15: % | C15: =C14+C13 -> 0.54679098 | D15: =D14+D13 -> 0.54506237 | E15: =E14+E13 -> 0.51517993 | F15: =F14+F13 -> 0.48770718 | G15: Dell 的機架多由鴻海、緯創代工，兩者重複計算；未扣重複仍低於 100%
A17: 讀法：Dell 份額的分母是 NVIDIA 與 AMD 商用 GPU 的整櫃售價（不含 Google TPU、Trainium 等 ASIC，Dell 不是其主要供應商）。FY2027 份額約一成，換算到廣達模型的 ODM 組裝市場（含 ASIC）約 12%；鴻海、廣達、緯創（含緯穎）合計約 44%，加上 Dell 仍約 55%，其餘為 Supermicro、HPE、Lenovo、英業達與雲端自建。Dell 的機架多由 ODM 代工，兩者營收有重複，所以實際份額合計更低，不會超過 100%。

Sheet PL
A1: PL — Dell 損益（十億美元；EPS 美元；non-GAAP）。FY2026A 實績、FY2027 錨點（公司指引＋1H 實績＋2H 假設；三情境相同），FY2028 起為模型。FY(t)≈CY(t−1)。三情境各一個完整推導區塊（本頁下方），頂端為摘要。FY2027–FY2028 三情境相同（顆數係數從 CY2028＝FY2029 開始）
A2: 灰底＝FY2031–FY2032 收斂法（上游顆數只到 CY2029＝FY2030）：營收年增線性收斂到 fade_g、淨利率線性收斂到 fade_m（In 頁 I 節），非驅動因子推導
A3: 情境／項目 | B3: 單位 | C3: FY2026A | D3: FY2027（錨點） | E3: FY2028 | F3: FY2029 | G3: FY2030 | H3: FY2031（收斂） | I3: FY2032（收斂） | J3: 說明
A4: 情境 A
A5: 營收 | B5: US$B | C5: =C77 -> 113.538 | D5: =D77 -> 192 | E5: =E77 -> 249.55867 | F5: =F77 -> 260.79803 | G5: =G77 -> 274.14209 | H5: =H77 -> 289.37976 | I5: =I77 -> 306.74255
A6: 營收年增 | B6: % | D6: =D78 -> 0.69106378 | E6: =E78 -> 0.29978473 | F6: =F78 -> 0.045036937 | G6: =G78 -> 0.051166265 | H6: =H78 -> 0.055583133 | I6: =I78 -> 0.06
A7: AI 伺服器營收 | B7: US$B | C7: =C70 -> 24.683 | D7: =D70 -> 74 | E7: =E70 -> 130.85444 | F7: =F70 -> 138.71009 | G7: =G70 -> 148.20366
A8: 傳統伺服器與網通 | B8: US$B | C8: =C72 -> 19.512 | D8: =D72 -> 37.59663 | E8: =E72 -> 35.716799 | F8: =F72 -> 36.431134 | G8: =G72 -> 37.524069
A9: 儲存 | B9: US$B | C9: =C73 -> 16.631 | D9: =D73 -> 19.47008 | E9: =E73 -> 20.248883 | F9: =F73 -> 21.058839 | G9: =G73 -> 21.901192
A10: CSG（PC） | B10: US$B | C10: =C75 -> 50.984 | D10: =D75 -> 60.17529 | E10: =E75 -> 61.980549 | F10: =F75 -> 63.839965 | G10: =G75 -> 65.755164
A11: AI 伺服器營業利益率 | B11: % | C11: =C81 -> 0.053807074 | D11: =D81 -> 0.1107101 | E11: =E81 -> 0.1007101 | F11: =F81 -> 0.1007101 | G11: =G81 -> 0.1007101
A12: 營業利益率 | B12: % | C12: =C87 -> 0.087583012 | D12: =D87 -> 0.11419345 | E12: =E87 -> 0.104952 | F12: =F87 -> 0.10486755 | G12: =G87 -> 0.10483389
A13: non-GAAP 淨利 | B13: US$B | C13: =C89 -> 7.046 | D13: =D89 -> 16.524 | E13: =E89 -> 19.643762 | F13: =F89 -> 20.511937 | G13: =G89 -> 21.554537 | H13: =H89 -> 22.752605 | I13: =I89 -> 24.117762
A14: 淨利率 | B14: % | C14: =C93 -> 0.062058518 | D14: =D93 -> 0.0860625 | E14: =E93 -> 0.078714003 | F14: =F93 -> 0.078650662 | G14: =G93 -> 0.07862542 | H14: =H93 -> 0.07862542 | I14: =I93 -> 0.07862542
A15: non-GAAP EPS | B15: US$ | C15: =C91 -> 10.3 | D15: =D91 -> 25.5 | E15: =E91 -> 31.252007 | F15: =F91 -> 33.642496 | G15: =G91 -> 36.445884 | H15: =H91 -> 39.661505 | I15: =I91 -> 43.341439
A16: EPS 年增 | B16: % | D16: =D92 -> 1.4757282 | E16: =E92 -> 0.22556892 | F16: =F92 -> 0.076490722 | G16: =G92 -> 0.083328764 | H16: =H92 -> 0.088230034 | I16: =I92 -> 0.092783505
A18: 情境 B
A19: 營收 | B19: US$B | C19: =C114 -> 113.538 | D19: =D114 -> 192 | E19: =E114 -> 249.55867 | F19: =F114 -> 227.50761 | G19: =G114 -> 245.61288 | H19: =H114 -> 260.2982 | I19: =I114 -> 270.71012
A20: 營收年增 | B20: % | D20: =D115 -> 0.69106378 | E20: =E115 -> 0.29978473 | F20: =F115 -> -0.088360237 | G20: =G115 -> 0.079580975 | H20: =H115 -> 0.059790488 | I20: =I115 -> 0.04
A21: AI 伺服器營收 | B21: US$B | C21: =C107 -> 24.683 | D21: =D107 -> 74 | E21: =E107 -> 130.85444 | F21: =F107 -> 105.41967 | G21: =G107 -> 119.67446
A22: 傳統伺服器與網通 | B22: US$B | C22: =C109 -> 19.512 | D22: =D109 -> 37.59663 | E22: =E109 -> 35.716799 | F22: =F109 -> 36.431134 | G22: =G109 -> 37.524069
A23: 儲存 | B23: US$B | C23: =C110 -> 16.631 | D23: =D110 -> 19.47008 | E23: =E110 -> 20.248883 | F23: =F110 -> 21.058839 | G23: =G110 -> 21.901192
A24: CSG（PC） | B24: US$B | C24: =C112 -> 50.984 | D24: =D112 -> 60.17529 | E24: =E112 -> 61.980549 | F24: =F112 -> 63.839965 | G24: =G112 -> 65.755164
A25: AI 伺服器營業利益率 | B25: % | C25: =C118 -> 0.053807074 | D25: =D118 -> 0.1107101 | E25: =E118 -> 0.1007101 | F25: =F118 -> 0.090710098 | G25: =G118 -> 0.090710098
A26: 營業利益率 | B26: % | C26: =C124 -> 0.087583012 | D26: =D124 -> 0.11419345 | E26: =E124 -> 0.104952 | F26: =F124 -> 0.10084222 | G26: =G124 -> 0.10044041
A27: non-GAAP 淨利 | B27: US$B | C27: =C126 -> 7.046 | D27: =D126 -> 16.524 | E27: =E126 -> 19.643762 | F27: =F126 -> 17.206779 | G27: =G126 -> 18.502094 | H27: =H126 -> 18.627926 | I27: =I126 -> 18.353409
A28: 淨利率 | B28: % | C28: =C130 -> 0.062058518 | D28: =D130 -> 0.0860625 | E28: =E130 -> 0.078714003 | F28: =F130 -> 0.075631664 | G28: =G130 -> 0.075330308 | H28: =H130 -> 0.071563792 | I28: =I130 -> 0.067797277
A29: non-GAAP EPS | B29: US$ | C29: =C128 -> 10.3 | D29: =D128 -> 25.5 | E29: =E128 -> 31.252007 | F29: =F128 -> 28.221565 | G29: =G128 -> 31.284605 | H29: =H128 -> 32.471516 | I29: =I128 -> 32.982462
A30: EPS 年增 | B30: % | D30: =D129 -> 1.4757282 | E30: =E129 -> 0.22556892 | F30: =F129 -> -0.096967912 | G30: =G129 -> 0.10853542 | H30: =H129 -> 0.037939137 | I30: =I129 -> 0.015735214
A32: 情境 C
A33: 營收 | B33: US$B | C33: =C151 -> 113.538 | D33: =D151 -> 192 | E33: =E151 -> 249.55867 | F33: =F151 -> 192.83008 | G33: =G151 -> 201.52229 | H33: =H151 -> 208.07953 | I33: =I151 -> 212.24112
A34: 營收年增 | B34: % | D34: =D152 -> 0.69106378 | E34: =E152 -> 0.29978473 | F34: =F152 -> -0.22731563 | G34: =G152 -> 0.045077041 | H34: =H152 -> 0.03253852 | I34: =I152 -> 0.02
A35: AI 伺服器營收 | B35: US$B | C35: =C144 -> 24.683 | D35: =D144 -> 74 | E35: =E144 -> 130.85444 | F35: =F144 -> 70.742145 | G35: =G144 -> 75.583868
A36: 傳統伺服器與網通 | B36: US$B | C36: =C146 -> 19.512 | D36: =D146 -> 37.59663 | E36: =E146 -> 35.716799 | F36: =F146 -> 36.431134 | G36: =G146 -> 37.524069
A37: 儲存 | B37: US$B | C37: =C147 -> 16.631 | D37: =D147 -> 19.47008 | E37: =E147 -> 20.248883 | F37: =F147 -> 21.058839 | G37: =G147 -> 21.901192
A38: CSG（PC） | B38: US$B | C38: =C149 -> 50.984 | D38: =D149 -> 60.17529 | E38: =E149 -> 61.980549 | F38: =F149 -> 63.839965 | G38: =G149 -> 65.755164
A39: AI 伺服器營業利益率 | B39: % | C39: =C155 -> 0.053807074 | D39: =D155 -> 0.1107101 | E39: =E155 -> 0.1007101 | F39: =F155 -> 0.075710098 | G39: =G155 -> 0.075710098
A40: 營業利益率 | B40: % | C40: =C161 -> 0.087583012 | D40: =D161 -> 0.11419345 | E40: =E161 -> 0.104952 | F40: =F161 -> 0.097161386 | G40: =G161 -> 0.096943314
A41: non-GAAP 淨利 | B41: US$B | C41: =C163 -> 7.046 | D41: =D163 -> 16.524 | E41: =E163 -> 19.643762 | F41: =F163 -> 14.051729 | G41: =G163 -> 14.652179 | H41: =H163 -> 13.616045 | I41: =I163 -> 12.345215
A42: 淨利率 | B42: % | C42: =C167 -> 0.062058518 | D42: =D167 -> 0.0860625 | E42: =E167 -> 0.078714003 | F42: =F167 -> 0.072871039 | G42: =G167 -> 0.072707486 | H42: =H167 -> 0.065436737 | I42: =I167 -> 0.058165988
A43: non-GAAP EPS | B43: US$ | C43: =C165 -> 10.3 | D43: =D165 -> 25.5 | E43: =E165 -> 31.252007 | F43: =F165 -> 23.046834 | G43: =G165 -> 24.774906 | H43: =H165 -> 23.73499 | I43: =I165 -> 22.185283
A44: EPS 年增 | B44: % | D44: =D166 -> 1.4757282 | E44: =E166 -> 0.22556892 | F44: =F166 -> -0.26254868 | G44: =G166 -> 0.074980867 | H44: =H166 -> -0.041974569 | I44: =I166 -> -0.065292096
A46: 核對（應為 0）：FY2027 模型 − 錨點
A47: 三情境：營收差（US$B） | D47: =ABS(D77-a27_rev)+ABS(D114-a27_rev)+ABS(D151-a27_rev) -> 0
A48: 三情境：EPS 差（US$） | D48: =ABS(D91-a27_eps)+ABS(D128-a27_eps)+ABS(D165-a27_eps) -> 0
A49: 情境 A：ISG 營業利益差（以 FY2028 公式套用 FY2027） | D49: =D70*D81+(D72+D73)*D82-a27_isgoi -> 0
A60: 情境 A（順利）：顆數係數 1.0
A61: 項目 | B61: 單位 | C61: FY2026A | D61: FY2027（錨點） | E61: FY2028 | F61: FY2029 | G61: FY2030 | H61: FY2031（收斂） | I61: FY2032（收斂） | J61: 說明
A62: A. 商用 GPU 系統市場與 Dell 份額（D 欄＝FY2027 校準年≈CY2026；E–G＝FY2028–FY2030≈CY2027–29）
A63: GB300 級 GPU 顆數 × 情境係數 | B63: 百萬顆 | D63: =ug_26 -> 6.65 | E63: =ug_27*1 -> 2.4 | F63: =ug_28*um28_A*1 -> 0.5 | G63: =ug_29*um29_A*1 -> 0.25
A64: VR200 級 GPU 顆數 × 情境係數 | B64: 百萬顆 | D64: =uv_26 -> 1.7 | E64: =uv_27*1 -> 8.8 | F64: =uv_28*um28_A*1 -> 11 | G64: =uv_29*um29_A*1 -> 12.65
A65: 商用 GPU 系統市場（顆數 × 每顆系統價值） | B65: US$B | D65: =D63*v_gb+D64*v_vr -> 595.48611 | E65: =E63*v_gb+E64*v_vr -> 1170 | F65: =F63*v_gb+F64*v_vr -> 1313.1944 | G65: =G63*v_gb+G64*v_vr -> 1490.7639 | J65: 百萬顆 × 千美元／顆＝十億美元；ASIC（TPU、Trainium 等）不含
A66: Dell 份額（FY2027 校準）＝ AI 伺服器營收指引 ÷ 市場 | B66: % | D66: =a27_ai/D65 -> 0.12426822 | J66: Derived：分子為公司 FY27 AI 伺服器營收指引；分母為 CY2026 全部商用 GPU 系統價值
A67: 份額相對值（÷ FY2027；全部情境） | B67: x | D67: =1 -> 1 | E67: =rel_28 -> 0.9 | F67: =rel_29 -> 0.85 | G67: =rel_30 -> 0.8
A68: 情境 A 份額乘數（FY2029 起） | B68: x | D68: =1 -> 1 | E68: =1 -> 1 | F68: =srel_A -> 1 | G68: =srel_A -> 1
A69: Dell 有效份額 | B69: % | D69: =$D$66*D67*D68 -> 0.12426822 | E69: =$D$66*E67*E68 -> 0.1118414 | F69: =$D$66*F67*F68 -> 0.10562799 | G69: =$D$66*G67*G68 -> 0.099414577
A70: AI 伺服器營收 | B70: US$B | C70: =a26_ai -> 24.683 | D70: =D65*D69 -> 74 | E70: =E65*E69 -> 130.85444 | F70: =F65*F69 -> 138.71009 | G70: =G65*G69 -> 148.20366
A71: B. 非 AI 營收（傳統伺服器、儲存、PC；不隨 AI 情境）
A72: 傳統伺服器與網通 | B72: US$B | C72: =a26_tr -> 19.512 | D72: =a27_tr -> 37.59663 | E72: =D72*(1+g_tr28) -> 35.716799 | F72: =E72*(1+g_tr29) -> 36.431134 | G72: =F72*(1+g_tr30) -> 37.524069
A73: 儲存 | B73: US$B | C73: =a26_st -> 16.631 | D73: =a27_st -> 19.47008 | E73: =D73*(1+g_st28) -> 20.248883 | F73: =E73*(1+g_st29) -> 21.058839 | G73: =F73*(1+g_st30) -> 21.901192
A74: ISG 營收 | B74: US$B | C74: =C70+C72+C73 -> 60.826 | D74: =D70+D72+D73 -> 131.06671 | E74: =E70+E72+E73 -> 186.82012 | F74: =F70+F72+F73 -> 196.20006 | G74: =G70+G72+G73 -> 207.62892
A75: CSG 營收（PC） | B75: US$B | C75: =a26_csg -> 50.984 | D75: =a27_csg -> 60.17529 | E75: =D75*(1+g_csg28) -> 61.980549 | F75: =E75*(1+g_csg29) -> 63.839965 | G75: =F75*(1+g_csg30) -> 65.755164
A76: 其他業務 | B76: US$B | C76: =a26_oth -> 1.728 | D76: =a27_oth -> 0.758 | E76: =D76 -> 0.758 | F76: =E76 -> 0.758 | G76: =F76 -> 0.758 | J76: FY2028 起持平（Assumed）
A77: 營收 | B77: US$B | C77: =C74+C75+C76 -> 113.538 | D77: =D74+D75+D76 -> 192 | E77: =E74+E75+E76 -> 249.55867 | F77: =F74+F75+F76 -> 260.79803 | G77: =G74+G75+G76 -> 274.14209 | H77: =G77*(1+H78) -> 289.37976 | I77: =H77*(1+I78) -> 306.74255 | J77: FY2031 起為收斂法：營收年增由 FY2030 線性收斂到 fade_g、淨利率收斂到 fade_m（FY2032 達到），非驅動因子推導
A78: 營收年增 | B78: % | D78: =D77/C77-1 -> 0.69106378 | E78: =E77/D77-1 -> 0.29978473 | F78: =F77/E77-1 -> 0.045036937 | G78: =G77/F77-1 -> 0.051166265 | H78: =$G78+(fade_gA-$G78)*1/2 -> 0.055583133 | I78: =$G78+(fade_gA-$G78)*2/2 -> 0.06
A79: AI 伺服器 ÷ 營收 | B79: % | C79: =C70/C77 -> 0.21739858 | D79: =D70/D77 -> 0.38541667 | E79: =E70/E77 -> 0.52434339 | F79: =F70/F77 -> 0.53186786 | G79: =G70/G77 -> 0.54060894
A80: C. 損益（non-GAAP）
A81: AI 伺服器營業利益率 | B81: % | C81: =(a26_isgoi-m_nai*(a26_tr+a26_st))/a26_ai -> 0.053807074 | D81: =(a27_isgoi-m_nai*(a27_tr+a27_st))/a27_ai -> 0.1107101 | E81: =$D81+ai_dm -> 0.1007101 | F81: =$D81+ai_dm+dm_A -> 0.1007101 | G81: =$D81+ai_dm+dm_A -> 0.1007101 | J81: FY2026、FY2027 為殘差（ISG 營業利益 − 非 AI 營益率 m_nai × 非 AI 營收）；FY2028 起＝FY2027＋ai_dm（FY2029 起再加情境變動）
A82: 非 AI ISG 營業利益率 | B82: % | C82: =m_nai -> 0.16 | D82: =m_nai -> 0.16 | E82: =m_naif -> 0.155 | F82: =m_naif -> 0.155 | G82: =m_naif -> 0.155
A83: ISG 營業利益 | B83: US$B | C83: =a26_isgoi -> 7.111 | D83: =a27_isgoi -> 17.323221 | E83: =E70*E81+(E72+E73)*E82 -> 21.853044 | F83: =F70*F81+(F72+F73)*F82 -> 22.880452 | G83: =G70*G81+(G72+G73)*G82 -> 24.136521
A84: CSG 營業利益率 | B84: % | C84: =a26_csgoi/C75 -> 0.055566452 | D84: =a27_csgoi/D75 -> 0.076475273 | E84: =m_csgf -> 0.07 | F84: =m_csgf -> 0.07 | G84: =m_csgf -> 0.07
A85: CSG 營業利益 | B85: US$B | C85: =C75*C84 -> 2.833 | D85: =D75*D84 -> 4.6019217 | E85: =E75*E84 -> 4.3386384 | F85: =F75*F84 -> 4.4687976 | G85: =G75*G84 -> 4.6028615
A86: 分部營業利益（≈ non-GAAP 營業利益） | B86: US$B | C86: =C83+C85 -> 9.944 | D86: =D83+D85 -> 21.925143 | E86: =E83+E85 -> 26.191682 | F86: =F83+F85 -> 27.34925 | G86: =G83+G85 -> 28.739382
A87: 營業利益率 | B87: % | C87: =C86/C77 -> 0.087583012 | D87: =D86/D77 -> 0.11419345 | E87: =E86/E77 -> 0.104952 | F87: =F86/F77 -> 0.10486755 | G87: =G86/G77 -> 0.10483389
A88: 淨利 ÷ 營業利益 | B88: % | C88: =a26_ni/a26_oi -> 0.70856798 | D88: =a27_ni/a27_oi -> 0.7536553 | E88: =nio_f -> 0.75 | F88: =nio_f -> 0.75 | G88: =nio_f -> 0.75
A89: non-GAAP 淨利 | B89: US$B | C89: =a26_ni -> 7.046 | D89: =a27_ni -> 16.524 | E89: =E86*E88 -> 19.643762 | F89: =F86*F88 -> 20.511937 | G89: =G86*G88 -> 21.554537 | H89: =H77*H93 -> 22.752605 | I89: =I77*I93 -> 24.117762
A90: 稀釋股數 | B90: 十億股 | C90: =a26_sh -> 0.68407767 | D90: =a27_sh -> 0.648 | E90: =D90*(1+sh_g) -> 0.62856 | F90: =E90*(1+sh_g) -> 0.6097032 | G90: =F90*(1+sh_g) -> 0.5914121 | H90: =G90*(1+sh_g) -> 0.57366974 | I90: =H90*(1+sh_g) -> 0.55645965
A91: non-GAAP EPS | B91: US$ | C91: =C89/C90 -> 10.3 | D91: =D89/D90 -> 25.5 | E91: =E89/E90 -> 31.252007 | F91: =F89/F90 -> 33.642496 | G91: =G89/G90 -> 36.445884 | H91: =H89/H90 -> 39.661505 | I91: =I89/I90 -> 43.341439
A92: EPS 年增 | B92: % | D92: =D91/C91-1 -> 1.4757282 | E92: =E91/D91-1 -> 0.22556892 | F92: =F91/E91-1 -> 0.076490722 | G92: =G91/F91-1 -> 0.083328764 | H92: =H91/G91-1 -> 0.088230034 | I92: =I91/H91-1 -> 0.092783505
A93: 淨利率（non-GAAP 淨利 ÷ 營收） | B93: % | C93: =C89/C77 -> 0.062058518 | D93: =D89/D77 -> 0.0860625 | E93: =E89/E77 -> 0.078714003 | F93: =F89/F77 -> 0.078650662 | G93: =G89/G77 -> 0.07862542 | H93: =$G93+(fade_mA-$G93)*1/2 -> 0.07862542 | I93: =$G93+(fade_mA-$G93)*2/2 -> 0.07862542
A94: Dell AI 營收 ÷ 商用 GPU 顆數（每顆） | B94: US$K/顆 | D94: =D70/(D63+D64) -> 8.8622754 | E94: =E70/(E63+E64) -> 11.683432 | F94: =F70/(F63+F64) -> 12.061747 | G94: =G70/(G63+G64) -> 11.488656
A97: 情境 B（平平）：CY2028 顆數 ×0.8、CY2029 ×0.85；份額 ×0.95、AI 營益率 −1pt
A98: 項目 | B98: 單位 | C98: FY2026A | D98: FY2027（錨點） | E98: FY2028 | F98: FY2029 | G98: FY2030 | H98: FY2031（收斂） | I98: FY2032（收斂） | J98: 說明
A99: A. 商用 GPU 系統市場與 Dell 份額（D 欄＝FY2027 校準年≈CY2026；E–G＝FY2028–FY2030≈CY2027–29）
A100: GB300 級 GPU 顆數 × 情境係數 | B100: 百萬顆 | D100: =ug_26 -> 6.65 | E100: =ug_27*1 -> 2.4 | F100: =ug_28*um28_B*1 -> 0.4 | G100: =ug_29*um29_B*1 -> 0.2125
A101: VR200 級 GPU 顆數 × 情境係數 | B101: 百萬顆 | D101: =uv_26 -> 1.7 | E101: =uv_27*1 -> 8.8 | F101: =uv_28*um28_B*1 -> 8.8 | G101: =uv_29*um29_B*1 -> 10.7525
A102: 商用 GPU 系統市場（顆數 × 每顆系統價值） | B102: US$B | D102: =D100*v_gb+D101*v_vr -> 595.48611 | E102: =E100*v_gb+E101*v_vr -> 1170 | F102: =F100*v_gb+F101*v_vr -> 1050.5556 | G102: =G100*v_gb+G101*v_vr -> 1267.1493 | J102: 百萬顆 × 千美元／顆＝十億美元；ASIC（TPU、Trainium 等）不含
A103: Dell 份額（FY2027 校準）＝ AI 伺服器營收指引 ÷ 市場 | B103: % | D103: =a27_ai/D102 -> 0.12426822 | J103: Derived：分子為公司 FY27 AI 伺服器營收指引；分母為 CY2026 全部商用 GPU 系統價值
A104: 份額相對值（÷ FY2027；全部情境） | B104: x | D104: =1 -> 1 | E104: =rel_28 -> 0.9 | F104: =rel_29 -> 0.85 | G104: =rel_30 -> 0.8
A105: 情境 B 份額乘數（FY2029 起） | B105: x | D105: =1 -> 1 | E105: =1 -> 1 | F105: =srel_B -> 0.95 | G105: =srel_B -> 0.95
A106: Dell 有效份額 | B106: % | D106: =$D$103*D104*D105 -> 0.12426822 | E106: =$D$103*E104*E105 -> 0.1118414 | F106: =$D$103*F104*F105 -> 0.10034659 | G106: =$D$103*G104*G105 -> 0.094443849
A107: AI 伺服器營收 | B107: US$B | C107: =a26_ai -> 24.683 | D107: =D102*D106 -> 74 | E107: =E102*E106 -> 130.85444 | F107: =F102*F106 -> 105.41967 | G107: =G102*G106 -> 119.67446
A108: B. 非 AI 營收（傳統伺服器、儲存、PC；不隨 AI 情境）
A109: 傳統伺服器與網通 | B109: US$B | C109: =a26_tr -> 19.512 | D109: =a27_tr -> 37.59663 | E109: =D109*(1+g_tr28) -> 35.716799 | F109: =E109*(1+g_tr29) -> 36.431134 | G109: =F109*(1+g_tr30) -> 37.524069
A110: 儲存 | B110: US$B | C110: =a26_st -> 16.631 | D110: =a27_st -> 19.47008 | E110: =D110*(1+g_st28) -> 20.248883 | F110: =E110*(1+g_st29) -> 21.058839 | G110: =F110*(1+g_st30) -> 21.901192
A111: ISG 營收 | B111: US$B | C111: =C107+C109+C110 -> 60.826 | D111: =D107+D109+D110 -> 131.06671 | E111: =E107+E109+E110 -> 186.82012 | F111: =F107+F109+F110 -> 162.90964 | G111: =G107+G109+G110 -> 179.09972
A112: CSG 營收（PC） | B112: US$B | C112: =a26_csg -> 50.984 | D112: =a27_csg -> 60.17529 | E112: =D112*(1+g_csg28) -> 61.980549 | F112: =E112*(1+g_csg29) -> 63.839965 | G112: =F112*(1+g_csg30) -> 65.755164
A113: 其他業務 | B113: US$B | C113: =a26_oth -> 1.728 | D113: =a27_oth -> 0.758 | E113: =D113 -> 0.758 | F113: =E113 -> 0.758 | G113: =F113 -> 0.758 | J113: FY2028 起持平（Assumed）
A114: 營收 | B114: US$B | C114: =C111+C112+C113 -> 113.538 | D114: =D111+D112+D113 -> 192 | E114: =E111+E112+E113 -> 249.55867 | F114: =F111+F112+F113 -> 227.50761 | G114: =G111+G112+G113 -> 245.61288 | H114: =G114*(1+H115) -> 260.2982 | I114: =H114*(1+I115) -> 270.71012 | J114: FY2031 起為收斂法：營收年增由 FY2030 線性收斂到 fade_g、淨利率收斂到 fade_m（FY2032 達到），非驅動因子推導
A115: 營收年增 | B115: % | D115: =D114/C114-1 -> 0.69106378 | E115: =E114/D114-1 -> 0.29978473 | F115: =F114/E114-1 -> -0.088360237 | G115: =G114/F114-1 -> 0.079580975 | H115: =$G115+(fade_gB-$G115)*1/2 -> 0.059790488 | I115: =$G115+(fade_gB-$G115)*2/2 -> 0.04
...

Sheet Val
A1: Val — P/E 估值（美元；non-GAAP EPS）。目標價＝DCF 與 Comparable 加權（第 0 節）；結論另列「現價 ÷ FY2027、FY2028 EPS（模型）」；十年 P/E 規則值（第 3 節，年底落後 P/E）只作參考
A2: 循環位置：Dell 不是設備股，不套設備市場見頂年；以本模型營收最高的會計年度為見頂年（比照廣達、緯穎）。營收到 FY2030 仍在增加時，見頂年未知，判為中段
A4: 0. 目標價
A5: 0.1 DCF（股東權益現金流，FY2027–FY2032 明確期＋FY2032 後永續）
A6: 項目 | B6: A（順利） | C6: B（平平） | D6: C（不如預期） | E6: 說明 | F6: 折現年數 t | G6: 期內占比（基準日後）
A7: 情境 EPS（FY2027–FY2032） | E7: PL 頁各情境（non-GAAP）；FY2031 起為收斂法；F 欄＝距 2026 年底的年數（會計年度 1 月底結束）
A8: FY2027 | B8: =PL!D15 -> 25.5 | C8: =PL!D29 -> 25.5 | D8: =PL!D43 -> 25.5 | F8: 0.083333 | G8: 0.083333
A9: FY2028 | B9: =PL!E15 -> 31.252007 | C9: =PL!E29 -> 31.252007 | D9: =PL!E43 -> 31.252007 | F9: 1.083333 | G9: 1
A10: FY2029 | B10: =PL!F15 -> 33.642496 | C10: =PL!F29 -> 28.221565 | D10: =PL!F43 -> 23.046834 | F10: 2.083333 | G10: 1
A11: FY2030 | B11: =PL!G15 -> 36.445884 | C11: =PL!G29 -> 31.284605 | D11: =PL!G43 -> 24.774906 | F11: 3.083333 | G11: 1
A12: FY2031 | B12: =PL!H15 -> 39.661505 | C12: =PL!H29 -> 32.471516 | D12: =PL!H43 -> 23.73499 | F12: 4.083333 | G12: 1
A13: FY2032 | B13: =PL!I15 -> 43.341439 | C13: =PL!I29 -> 32.982462 | D13: =PL!I43 -> 22.185283 | F13: 5.083333 | G13: 1
A14: 股東現金流＝EPS ×（1 − tp_g ÷ tp_roe） | E14: 下列六列＝EPS × (1 − 再投資率) × 期內占比（FY2027 只計 2027-01 一個月）
A15: 再投資率（tp_g ÷ tp_roe，上限 0.8） | B15: =MIN(tp_g/tp_roe,0.8) -> 0.2 | E15: tp_roe 用預設 0.20（股東權益為負，ROE 無意義）
A16: FY2027 | B16: =B8*(1-$B$15)*$G$8 -> 1.6999932 | C16: =C8*(1-$B$15)*$G$8 -> 1.6999932 | D16: =D8*(1-$B$15)*$G$8 -> 1.6999932
A17: FY2028 | B17: =B9*(1-$B$15)*$G$9 -> 25.001606 | C17: =C9*(1-$B$15)*$G$9 -> 25.001606 | D17: =D9*(1-$B$15)*$G$9 -> 25.001606
A18: FY2029 | B18: =B10*(1-$B$15)*$G$10 -> 26.913997 | C18: =C10*(1-$B$15)*$G$10 -> 22.577252 | D18: =D10*(1-$B$15)*$G$10 -> 18.437467
A19: FY2030 | B19: =B11*(1-$B$15)*$G$11 -> 29.156707 | C19: =C11*(1-$B$15)*$G$11 -> 25.027684 | D19: =D11*(1-$B$15)*$G$11 -> 19.819925
A20: FY2031 | B20: =B12*(1-$B$15)*$G$12 -> 31.729204 | C20: =C12*(1-$B$15)*$G$12 -> 25.977213 | D20: =D12*(1-$B$15)*$G$12 -> 18.987992
A21: FY2032 | B21: =B13*(1-$B$15)*$G$13 -> 34.673151 | C21: =C13*(1-$B$15)*$G$13 -> 26.38597 | D21: =D13*(1-$B$15)*$G$13 -> 17.748226
A22: DCF 情境每股價值（折現率 tp_r） | B22: =MAX(0,SUMPRODUCT(B16:B21,1/(1+tp_r)^$F$8:$F$13)+B21*(1+tp_g)/(tp_r-tp_g)/(1+tp_r)^$F$13) -> 481.11637 | C22: =MAX(0,SUMPRODUCT(C16:C21,1/(1+tp_r)^$F$8:$F$13)+C21*(1+tp_g)/(tp_r-tp_g)/(1+tp_r)^$F$13) -> 376.99408 | D22: =MAX(0,SUMPRODUCT(D16:D21,1/(1+tp_r)^$F$8:$F$13)+D21*(1+tp_g)/(tp_r-tp_g)/(1+tp_r)^$F$13) -> 267.43178 | E22: Σ 明確期現金流 ÷ (1＋r)^t ＋ 永續價值 ÷ (1＋r)^t；永續價值＝FY2032 現金流 ×(1＋g)÷(r−g)；基準日 2026 年底；小於 0 時取 0
A23: DCF 情境價值推到 12 個月後（×(1＋tp_r)） | B23: =B22*(1+tp_r) -> 529.22801 | C23: =C22*(1+tp_r) -> 414.69349 | D23: =D22*(1+tp_r) -> 294.17496
A24: DCF 目標價（情境加權） | B24: =tp_wA*B23+tp_wB*C23+tp_wC*D23 -> 424.95014 | E24: Σ 權重 × 情境價值 ×(1＋r)；權重見 In 頁
A26: 0.2 Comparable（市場主流同業前瞻 P/E）
A27: 同業與前瞻 P/E | B27: 代號 | C27: 前瞻 12 月 P/E | D27: 日期 | E27: 來源 | F27: 標記
A28: Hewlett Packard Enterprise | B28: HPE | C28: 12.19 | D28: 2026-10-23 | E28: stockanalysis.com forward PE（分析師共識；價格日期如左） | F28: Interested-party
A29: Super Micro Computer（美超微） | B29: SMCI | C29: 7.06 | D29: 2026-10-23 | E29: stockanalysis.com forward PE（分析師共識；價格日期如左） | F29: Interested-party
A30: Lenovo（聯想） | B30: 0992.HK | C30: 9.6 | D30: 2026-10-20 | E30: stockanalysis.com forward PE（分析師共識；價格日期如左） | F30: Interested-party
A31: HP Inc. | B31: HPQ | C31: 11.26 | D31: 2026-10-23 | E31: stockanalysis.com forward PE（分析師共識；價格日期如左） | F31: Interested-party
A32: NetApp | B32: NTAP | C32: 21.69 | D32: 2026-10-23 | E32: stockanalysis.com forward PE（分析師共識；價格日期如左） | F32: Interested-party
A33: 同業前瞻 P/E 中位數 | B33: =MEDIAN(C28:C32) -> 11.26 | E33: 伺服器、儲存與 PC 品牌同業：HPE、Supermicro、Lenovo、HP Inc.、NetApp（不含 A 股）
A34: 12 個月後的前瞻 EPS（情境加權） | B34: =tp_wA*(3/12*B9+9/12*B10)+tp_wB*(3/12*C9+9/12*C10)+tp_wC*(3/12*D9+9/12*D10) -> 29.422676 | E34: 約 2027-10 時的未來 12 月（2027-11～2028-10）EPS ≈ 3／12 × FY2028＋9／12 × FY2029（會計年度 1 月底結束，依月份調整）
A35: Comparable 目標價 | B35: =B33*B34 -> 331.29933 | E35: 同業中位數 × 前瞻 EPS
A37: 0.3 結論
A38: 項目 | B38: 數值 | C38: 對照 | D38: 對照 | E38: 說明
A39: 目標價（DCF 與 Comparable 加權） | B39: =tp_w_dcf*B24+(1-tp_w_dcf)*tp_comp_adj -> 334.49455 | E39: tp_w_dcf × DCF＋（1 − tp_w_dcf）× Comparable；tp_w_dcf 見 In 頁（0.5）
A40: Comparable 目標價（市場主流同業法） | B40: =B35 -> 331.29933
A41: 市場共識目標價 | B41: =cons_tp -> 593 | E41: stockanalysis：29 位分析師平均 593（中位數 600、最高 735、最低 480），2026-10-21；MarketScreener 29 位 593
A42: 上檔空間：加權目標價 | B42: =B39/px-1 -> -0.26716644 | E42: 現價＝In 頁 px（2026-10-23 收盤）
A43: 上檔空間：Comparable 目標價 | B43: =B40/px-1 -> -0.27416675
A44: 與市場共識目標價的差距：EPS 因素 | B44: =B34/C44-1 -> 0.045560859 | C44: =cons_feps -> 28.140567 | E44: B＝本模型前瞻 EPS ÷ 共識前瞻 EPS − 1；C＝共識前瞻 EPS（現價 ÷ 前瞻 P/E 16.22）；兩者期間差約一年
A45: 與市場共識目標價的差距：倍數因素 | B45: =C45/D45-1 -> 0.87147253 | C45: =cons_tp/cons_feps -> 21.072781 | D45: =B33 -> 11.26 | E45: C＝共識目標價 ÷ 共識前瞻 EPS 隱含的倍數；D＝同業中位數；B＝C ÷ D − 1
A46: 價格帶（DCF 不如預期～順利） | B46: =D23 -> 294.17496 | C46: =B23 -> 529.22801 | E46: B＝C 情境 DCF 價值、C＝A 情境 DCF 價值（皆推到 12 個月後）
A47: 歷史倍數檢查：現價隱含 P/E 的十年分位（A／B／C） | B47: =IF(px/B9<=MIN($B$88:$B$97),0,IF(px/B9>=MAX($B$88:$B$97),1,PERCENTRANK($B$88:$B$97,px/B9))) -> 0.554 | C47: =IF(px/C9<=MIN($B$88:$B$97),0,IF(px/C9>=MAX($B$88:$B$97),1,PERCENTRANK($B$88:$B$97,px/C9))) -> 0.554 | D47: =IF(px/D9<=MIN($B$88:$B$97),0,IF(px/D9>=MAX($B$88:$B$97),1,PERCENTRANK($B$88:$B$97,px/D9))) -> 0.554 | E47: 現價 ÷ 各情境 FY2028 EPS 在 2019–2025 年底 P/E（第 5 節兩來源平均，GAAP）的分位；低於最小記 0%、高於最大記 100%；只作檢查，不進目標價
A48: 上檔空間級距 | B48: =IF(B42>0.5,"大於 50%",IF(B42>0.25,"25%–50%",IF(B42>=0,"0%–25%",IF(B42>=-0.25,"0%～−25%",IF(B42>=-0.5,"−25%～−50%","小於 −50%"))))) -> −25%～−50% | E48: 以「上檔空間：加權目標價」分六級（Andy 2026-10-25 14:00）
A49: 投資建議 | B49: =IF(B42>0.5,"強力買進",IF(B42>0.25,"買進",IF(B42>=-0.25,"中立",IF(B42>=-0.5,"放空","強力放空")))) -> 放空 | E49: 依上檔空間固定規則（Andy 2026-10-25 14:17）：大於 +50% 強力買進、+25%～+50% 買進、−25%～+25% 中立、−50%～−25% 放空、小於 −50% 強力放空
A50: 目標價方法 | B50: DCF：股東現金流＝non-GAAP EPS ×（1 − g／ROE），r＝10%、g＝4%、ROE 用預設 20%（股東權益為負，近三年 ROE 無意義；再投資率 20%），FY2027–32 明確期＋永續；基準日 2026 年底，FY2027 只計 2027-01 一個月，之後逐年折現。組裝型 OEM 資本支出低，未改用淨利＋折舊－資本支出。Comparable：HPE、Supermicro、Lenovo、HP Inc.、NetApp 前瞻 P/E 中位數（不含 A 股）× 2027-11～2028-10 的 EPS（3/12 × FY2028＋9/12 × FY2029）。偏誤：non-GAAP EPS 排除攤銷與股票薪酬（偏高）；同業多為成長較低的 PC／伺服器公司，未給 Dell 的 AI 份額溢價（Comparable 偏低）；淨負債高、股東權益為負未反映在折現率。情境對應：A＝順利（顆數基準）、B＝平平（顆數 ×0.8／0.85）、C＝不如預期（顆數 ×0.6）
A53: 1. 價格與市場隱含倍數
A54: 項目 | B54: A | C54: B | D54: C | E54: 說明
A55: 現價（2026-10-23 收盤） | B55: =px -> 456.44
A56: 現價 ÷ FY2026 EPS（實績） | B56: =px/PL!C15 -> 44.314563 | C56: =px/PL!C29 -> 44.314563 | D56: =px/PL!C43 -> 44.314563
A57: 現價 ÷ FY2027 EPS（模型） | B57: =px/PL!D15 -> 17.899608 | C57: =px/PL!D29 -> 17.899608 | D57: =px/PL!D43 -> 17.899608 | E57: FY2027 三情境相同（錨點）
A58: 現價 ÷ FY2028 EPS（模型） | B58: =px/PL!E15 -> 14.605142 | C58: =px/PL!E29 -> 14.605142 | D58: =px/PL!E43 -> 14.605142 | E58: FY2028 三情境相同（顆數係數從 CY2028＝FY2029 開始）
A59: 現價 ÷ FY2029 EPS（模型） | B59: =px/PL!F15 -> 13.567364 | C59: =px/PL!F29 -> 16.173447 | D59: =px/PL!F43 -> 19.804889
A60: 未來 12 月 EPS（模型 B）≈ 3/12 × FY2027＋9/12 × FY2028（2026-11～2027-10） | B60: =3/12*PL!D29+9/12*PL!E29 -> 29.814006
A61: 現價 ÷ 未來 12 月 EPS（模型 B） | B61: =px/B60 -> 15.309583
A62: 近 12 月 P/E（GAAP，stockanalysis） | B62: =pe_ttm -> 26.63
A63: 前瞻 P/E（stockanalysis，10-23） | B63: =fpe -> 16.22
A65: 2. 循環位置（本模型營收最高年）
A66: 情境 | B66: 營收最高年（FY2027–FY2030） | C66: FY2027 判定 | D66: 規則倍數（P/E） | E66: 見頂年是否未知 | F66: 說明
A67: A | B67: =INDEX({2027,2028,2029,2030},MATCH(MAX(PL!D77:G77),PL!D77:G77,0)) -> 2030 | C67: =IF(B67=2030,"中段",IF(2027<B67,"中段",IF(2027=B67,"見頂","谷底"))) -> 中段 | D67: =IF(C67="見頂",pe_peak,IF(C67="谷底",pe_trough,pe_mid)) -> 12.73 | E67: =IF(B67=2030,"是：營收到觀測期末仍在增加","否") -> 是：營收到觀測期末仍在增加 | F67: tools/cycle_position.py excel_rule；營收最高年取代設備市場見頂年
A68: B | B68: =INDEX({2027,2028,2029,2030},MATCH(MAX(PL!D114:G114),PL!D114:G114,0)) -> 2028 | C68: =IF(B68=2030,"中段",IF(2027<B68,"中段",IF(2027=B68,"見頂","谷底"))) -> 中段 | D68: =IF(C68="見頂",pe_peak,IF(C68="谷底",pe_trough,pe_mid)) -> 12.73 | E68: =IF(B68=2030,"是：營收到觀測期末仍在增加","否") -> 否 | F68: 同上
A69: C | B69: =INDEX({2027,2028,2029,2030},MATCH(MAX(PL!D151:G151),PL!D151:G151,0)) -> 2028 | C69: =IF(B69=2030,"中段",IF(2027<B69,"中段",IF(2027=B69,"見頂","谷底"))) -> 中段 | D69: =IF(C69="見頂",pe_peak,IF(C69="谷底",pe_trough,pe_mid)) -> 12.73 | E69: =IF(B69=2030,"是：營收到觀測期末仍在增加","否") -> 否 | F69: 同上
A71: 3. 規則值隱含股價（美元；約 FY2027 年底＝2027-01，未折現）＝ FY2027 EPS × 規則倍數
A72: 情境 | B72: FY2027 EPS | C72: （同左） | D72: 規則倍數 | E72: 隱含股價 | F72: 相對現價 | G72: 現價 ÷ FY2027 EPS
A73: A | B73: =PL!D15 -> 25.5 | C73: =B73 -> 25.5 | D73: =D67 -> 12.73 | E73: =C73*D73 -> 324.615 | F73: =E73/px-1 -> -0.28881123 | G73: =px/C73 -> 17.899608
A74: B | B74: =PL!D29 -> 25.5 | C74: =B74 -> 25.5 | D74: =D68 -> 12.73 | E74: =C74*D74 -> 324.615 | F74: =E74/px-1 -> -0.28881123 | G74: =px/C74 -> 17.899608
A75: C | B75: =PL!D43 -> 25.5 | C75: =B75 -> 25.5 | D75: =D69 -> 12.73 | E75: =C75*D75 -> 324.615 | F75: =E75/px-1 -> -0.28881123 | G75: =px/C75 -> 17.899608
A77: 4. What must be true：FY2028 年底（2028-01）價 ＝ 現價 ×（1＋報酬）所需的倍數（÷ FY2029 EPS；約一年後的價格看下一年 EPS）
A78: FY2028 年底價 ÷ 現價 | B78: 所需倍數（÷ FY2029 EPS，A） | C78: 所需倍數（÷ FY2029 EPS，B） | D78: 所需倍數（÷ FY2029 EPS，C） | E78: 對照：十年中位數
A79: 1 | B79: =px*A79/PL!F15 -> 13.567364 | C79: =px*A79/PL!F29 -> 16.173447 | D79: =px*A79/PL!F43 -> 19.804889 | E79: =pe_mid -> 12.73
A80: 1.1 | B80: =px*A80/PL!F15 -> 14.924101 | C80: =px*A80/PL!F29 -> 17.790792 | D80: =px*A80/PL!F43 -> 21.785378 | E80: =pe_mid -> 12.73
A81: 1.21 | B81: =px*A81/PL!F15 -> 16.416511 | C81: =px*A81/PL!F29 -> 19.569871 | D81: =px*A81/PL!F43 -> 23.963916 | E81: =pe_mid -> 12.73
A82: 1.5 | B82: =px*A82/PL!F15 -> 20.351047 | C82: =px*A82/PL!F29 -> 24.260171 | D82: =px*A82/PL!F43 -> 29.707334 | E82: =pe_mid -> 12.73
A83: 2 | B83: =px*A83/PL!F15 -> 27.134729 | C83: =px*A83/PL!F29 -> 32.346894 | D83: =px*A83/PL!F43 -> 39.609779 | E83: =pe_mid -> 12.73
A84: 讀法：1.00＝價格不變、1.21＝約 21%。所需倍數低於歷史中位數時，現價相對便宜。歷史倍數為 GAAP 落後 P/E（含一次性稅務與 VMware 利益），與本模型 non-GAAP EPS 口徑不同。本版未做先驗，無 Andy 合理 P/E 對照。
A86: 5. 十年 P/E（2016–2025 年底；兩來源平均，分位排名用；2018-12 重新上市，2016–2018 無可比市價）
A87: 年底 | B87: 兩來源平均 P/E | C87: companiesmarketcap | D87: Macrotrends
A88: 2016
A89: 2017
A90: 2018
A91: 2019 | B91: =AVERAGE(C91:D91) -> 3.815 | C91: =B110 -> 4.12 | D91: =IF(C110="","",C110) -> 3.51
A92: 2020 | B92: =AVERAGE(C92:D92) -> 9.255 | C92: =B111 -> 10.5 | D92: =IF(C111="","",C111) -> 8.01
A93: 2021 | B93: =AVERAGE(C93:D93) -> 6.57 | C93: =B112 -> 5.79 | D93: =IF(C112="","",C112) -> 7.35
A94: 2022 | B94: =AVERAGE(C94:D94) -> 13.695 | C94: =B113 -> 15.5 | D94: =IF(C113="","",C113) -> 11.89
A95: 2023 | B95: =AVERAGE(C95:D95) -> 19.22 | C95: =B114 -> 20.1 | D95: =IF(C114="","",C114) -> 18.34
A96: 2024 | B96: =AVERAGE(C96:D96) -> 17.975 | C96: =B115 -> 19.6 | D96: =IF(C115="","",C115) -> 16.35
A97: 2025 | B97: =AVERAGE(C97:D97) -> 16.5 | C97: =B116 -> 16.5 | D97: =IF(C116="","",C116)
A98: 年數 | B98: =COUNT($B$88:$B$97) -> 7
A102: 6. 十年倍數與規則值（2016–2025 年底；見頂年 25 分位、中段中位數、谷底 75 分位）
A103: 規則（Andy 2026-10-13）：合理倍數＝2016–2025 年底 P/E 依循環位置取分位，兩個來源分別取分位再平均。Dell 2018-12 重新上市，只有 2019–2025。兩來源都是 GAAP P/E：2019–2021 含稅務利益與 VMware 持股利益，倍數偏低（4–8x），規則值偏低。
A105: P/E：十年歷史倍數
A106: 年底 | B106: companiesmarketcap（年底 P/E） | C106: Macrotrends（會計年度年底 P/E） | D106: 標記／說明
A107: 2016 | D107: companiesmarketcap（年底 P/E）：Interested-party（資料商；GAAP；2019–2025 共 7 年）；Macrotrends（會計年度年底 P/E）：Interested-party（資料商；次年 1 月底股價 ÷ 近四季 GAAP EPS；2019–2024 共 6 年，2025 年（2026-01）未列）
A108: 2017
A109: 2018
A110: 2019 | B110: 4.12 | C110: 3.51
A111: 2020 | B111: 10.5 | C111: 8.01
A112: 2021 | B112: 5.79 | C112: 7.35
A113: 2022 | B113: 15.5 | C113: 11.89
...

Sheet Recon
A1: Recon — 本模型 vs 公司指引、共識與組裝廠份額。只作事後對照，不為對上數字而調參數
A3: 項目 | B3: 對照值 | C3: 模型 A | D3: 差距 A | E3: 模型 B | F3: 差距 B | G3: 模型 C | H3: 差距 C | I3: 對照來源 | J3: 說明
A4: A. 共識（校準未使用）
A5: FY2027 營收 vs 共識 | B5: =c_rev27 -> 193.4 | C5: =PL!D77 -> 192 | D5: =C5/B5-1 -> -0.0072388831 | E5: =PL!D114 -> 192 | F5: =E5/B5-1 -> -0.0072388831 | G5: =PL!D151 -> 192 | H5: =G5/B5-1 -> -0.0072388831 | I5: stockanalysis（22 位，10-21） | J5: 錨點＝公司指引 1,920 億
A6: FY2027 EPS vs 共識 | B6: =c_eps27 -> 25.9 | C6: =PL!D91 -> 25.5 | D6: =C6/B6-1 -> -0.015444015 | E6: =PL!D128 -> 25.5 | F6: =E6/B6-1 -> -0.015444015 | G6: =PL!D165 -> 25.5 | H6: =G6/B6-1 -> -0.015444015 | I6: stockanalysis（22 位） | J6: 錨點＝公司指引 25.50
A7: FY2028 營收 vs 共識 | B7: =c_rev28 -> 229.12 | C7: =PL!E77 -> 249.55867 | D7: =C7/B7-1 -> 0.089205081 | E7: =PL!E114 -> 249.55867 | F7: =E7/B7-1 -> 0.089205081 | G7: =PL!E151 -> 249.55867 | H7: =G7/B7-1 -> 0.089205081 | I7: stockanalysis（Revenue Next Year）
A8: FY2028 EPS vs 共識 | B8: =c_eps28 -> 29.93 | C8: =PL!E91 -> 31.252007 | D8: =C8/B8-1 -> 0.044169975 | E8: =PL!E128 -> 31.252007 | F8: =E8/B8-1 -> 0.044169975 | G8: =PL!E165 -> 31.252007 | H8: =G8/B8-1 -> 0.044169975 | I8: stockanalysis（EPS Next Year）
A9: FY2029 EPS vs 共識 | C9: =PL!F91 -> 33.642496 | E9: =PL!F128 -> 28.221565 | G9: =PL!F165 -> 23.046834 | I9: 未找到 | J9: 共識 FY2029 EPS：未找到
A10: B. 公司指引與在手訂單
A11: FY2027 AI 伺服器營收 vs 指引 740 億 | B11: =g_ai -> 74 | C11: =PL!D70 -> 74 | D11: =C11/B11-1 -> 0 | E11: =PL!D107 -> 74 | F11: =E11/B11-1 -> 0 | G11: =PL!D144 -> 74 | H11: =G11/B11-1 -> 0 | I11: Dell 8-K 2Q FY27 | J11: 校準點（差距應為 0）
A12: FY2028 AI 伺服器營收 vs FY2027 指引 | B12: =g_ai -> 74 | C12: =PL!E70 -> 130.85444 | D12: =C12/B12-1 -> 0.76830321 | E12: =PL!E107 -> 130.85444 | F12: =E12/B12-1 -> 0.76830321 | G12: =PL!E144 -> 130.85444 | H12: =G12/B12-1 -> 0.76830321 | I12: Dell 8-K 2Q FY27 | J12: 2Q FY27 在手訂單 950 億美元；近四季訂單 1,317 億美元
A13: C. 份額與組裝廠合計（廣達、鴻海、緯創模型；唯讀）
A14: FY2027 Dell AI 營收 ÷ 組裝市場（ODM 口徑） | C14: =Units!C13 -> 0.11660585 | E14: =Units!C13 -> 0.11660585 | G14: =Units!C13 -> 0.11660585 | I14: quanta Units | J14: Dell 為 OEM 售價，同口徑時更低
A15: FY2027 ODM 三家＋Dell 合計份額（未扣重複） | C15: =Units!C15 -> 0.54679098 | E15: =Units!C15 -> 0.54679098 | G15: =Units!C15 -> 0.54679098 | I15: wistron Units | J15: 應遠低於 100%；其餘為 Supermicro、HPE、Lenovo、英業達、自建
A16: FY2028 Dell 有效份額 | C16: =PL!E69 -> 0.1118414 | E16: =PL!E106 -> 0.1118414 | G16: =PL!E143 -> 0.1118414 | I16: — | J16: 份額相對值 0.90（Assumed）
A17: FY2028 Dell AI 營收 ÷ 商用 GPU 顆數（US$K／顆） | C17: =PL!E94 -> 11.683432 | E17: =PL!E131 -> 11.683432 | G17: =PL!E168 -> 11.683432 | I17: —
A18: D. 校準
A19: FY2027 AI 伺服器營業利益率（Derived） | C19: =PL!D81 -> 0.1107101 | E19: =PL!D118 -> 0.1107101 | G19: =PL!D155 -> 0.1107101 | I19: FY2027 錨點 | J19: ISG 營業利益 − 16% × 非 AI 營收
A20: FY2026 AI 伺服器營業利益率（Derived） | C20: =PL!C81 -> 0.053807074 | E20: =PL!C118 -> 0.053807074 | G20: =PL!C155 -> 0.053807074 | I20: FY2026 實績
A21: 2H FY27 non-GAAP EPS（模型） | C21: =Q!D18 -> 13.61838 | E21: =Q!D18 -> 13.61838 | G21: =Q!D18 -> 13.61838 | I21: 3Q FY27 指引 6.50 | J21: 2H＝全年指引 − 1H 實績
A22: E. 預留
A23: R4 產業部署路徑（markets/deploy_path/，尚未建立）：上線後以部署路徑取代 tsmc 顆數 × 每顆系統價值 | J23: 預留列：本版無數值

Sheet Sens
A1: Sens — 一次動一個輸入（情境 A；Dell 份額、AI 營益率在每個案例內依 FY2027 錨點重算，FY2027 恆等於錨點）：對 FY2028、FY2029 營收、營業利益率與 EPS 的影響。每個案例是一個完整推導區塊（本頁下方）
A3: 案例 | B3: 設定 | C3: FY2028 營收 | D3: FY2028 營益率 | E3: FY2028 EPS | F3: FY2028 EPS 相對基準 | G3: FY2029 營收 | H3: FY2029 營益率 | I3: FY2029 EPS | J3: FY2029 EPS 相對基準
A4: 基準（情境 A） | B4: PL 區塊 A | C4: =PL!E77 -> 249.55867 | D4: =PL!E87 -> 0.104952 | E4: =PL!E91 -> 31.252007 | F4: =E4/E$4-1 -> 0 | G4: =PL!F77 -> 260.79803 | H4: =PL!F87 -> 0.10486755 | I4: =PL!F91 -> 33.642496 | J4: =I4/I$4-1 -> 0
A5: AI 部署 ×0.8 | B5: FY2028 起商用 GPU 顆數 ×0.8 | C5: =E59 -> 223.38778 | D5: =E69 -> 0.10544896 | E5: =E73 -> 28.107113 | F5: =E5/E$4-1 -> -0.10063014 | G5: =F59 -> 233.05601 | H5: =F69 -> 0.10536244 | I5: =F73 -> 30.205699 | J5: =I5/I$4-1 -> -0.10215641
A6: AI 部署 ×1.2 | B6: ×1.2 | C6: =E96 -> 275.72956 | D6: =E106 -> 0.10454938 | E6: =E110 -> 34.396901 | F6: =E6/E$4-1 -> 0.10063014 | G6: =F96 -> 288.54004 | H6: =F106 -> 0.10446783 | I6: =F110 -> 37.079293 | J6: =I6/I$4-1 -> 0.10215641
A7: 份額流失（低） | B7: 份額相對值 FY2028 0.75、FY2029 0.65、FY2030 0.55 | C7: =E133 -> 227.7496 | D7: =E143 -> 0.1053582 | E7: =E147 -> 28.631262 | F7: =E7/E$4-1 -> -0.08385845 | G7: =F133 -> 228.16036 | H7: =F143 -> 0.10546226 | I7: =F147 -> 29.599206 | J7: =I7/I$4-1 -> -0.12018402
A8: 份額維持（高） | B8: 份額相對值 1.05／1.0／1.0 | C8: =E170 -> 271.36774 | D8: =E180 -> 0.10461109 | E8: =E184 -> 33.872752 | F8: =E8/E$4-1 -> 0.08385845 | G8: =F170 -> 285.27628 | H8: =F180 -> 0.10451082 | I8: =F184 -> 36.674964 | J8: =I8/I$4-1 -> 0.090138013
A9: 每顆系統價值 低 | B9: GB300／VR200 機架價取橋接表低值 | C9: =E207 -> 246.65747 | D9: =E217 -> 0.1050019 | E9: =E221 -> 30.903377 | F9: =E9/E$4-1 -> -0.011155447 | G9: =F207 -> 257.15909 | H9: =F217 -> 0.10492638 | I9: =F221 -> 33.19169 | J9: =I9/I$4-1 -> -0.0133999
A10: 每顆系統價值 高 | B10: 取高值 | C10: =E244 -> 244.57714 | D10: =E254 -> 0.1050384 | E10: =E258 -> 30.653389 | F10: =E10/E$4-1 -> -0.019154572 | G10: =F244 -> 254.54976 | H10: =F254 -> 0.1049696 | I10: =F258 -> 32.868435 | J10: =I10/I$4-1 -> -0.023008432
A11: AI 營益率 −3pt | B11: FY2028 起 AI 營益率比 FY2027 低 3 個百分點 | C11: =E281 -> 249.55867 | D11: =E291 -> 0.094465136 | E11: =E295 -> 28.129288 | F11: =E11/E$4-1 -> -0.099920605 | G11: =F281 -> 260.79803 | H11: =F291 -> 0.094230192 | I11: =F295 -> 30.229932 | J11: =I11/I$4-1 -> -0.10143612
A12: AI 營益率 +1pt | B12: 高 1 個百分點 | C12: =E318 -> 249.55867 | D12: =E328 -> 0.11543887 | E12: =E332 -> 34.374727 | F12: =E12/E$4-1 -> 0.099920605 | G12: =F318 -> 260.79803 | H12: =F328 -> 0.11550491 | I12: =F332 -> 37.05506 | J12: =I12/I$4-1 -> 0.10143612
A13: 非 AI 營益率拆分 19% | B13: FY2027 拆分用 m_nai 19%（AI 營益率校準值較低） | C13: =E355 -> 249.55867 | D13: =E365 -> 0.09282124 | E13: =E369 -> 27.639778 | F13: =E13/E$4-1 -> -0.11558392 | G13: =F355 -> 260.79803 | H13: =F365 -> 0.092562705 | I13: =F369 -> 29.694986 | J13: =I13/I$4-1 -> -0.117337
A14: 非 AI ISG 營益率 低 | B14: FY2028 起 13.5% | C14: =E392 -> 249.55867 | D14: =E402 -> 0.10046683 | E14: =E406 -> 29.916438 | F14: =E14/E$4-1 -> -0.042735462 | G14: =F392 -> 260.79803 | H14: =F402 -> 0.10045878 | I14: =F406 -> 32.22812 | J14: =I14/I$4-1 -> -0.042041353
A15: 非 AI ISG 營益率 高 | B15: 17.5% | C15: =E429 -> 249.55867 | D15: =E439 -> 0.10943718 | E15: =E443 -> 32.587576 | F15: =E15/E$4-1 -> 0.042735462 | G15: =F429 -> 260.79803 | H15: =F439 -> 0.10927632 | I15: =F443 -> 35.056872 | J15: =I15/I$4-1 -> 0.042041353
A16: CSG 營益率 低 | B16: 6% | C16: =E466 -> 249.55867 | D16: =E476 -> 0.1024684 | E16: =E480 -> 30.512453 | F16: =E16/E$4-1 -> -0.023664211 | G16: =F466 -> 260.79803 | H16: =F476 -> 0.10241968 | I16: =F480 -> 32.857196 | J16: =I16/I$4-1 -> -0.023342492
A17: CSG 營益率 高 | B17: 8% | C17: =E503 -> 249.55867 | D17: =E513 -> 0.10743561 | E17: =E517 -> 31.991561 | F17: =E17/E$4-1 -> 0.023664211 | G17: =F503 -> 260.79803 | H17: =F513 -> 0.10731542 | I17: =F517 -> 34.427796 | J17: =I17/I$4-1 -> 0.023342492
A18: 傳統伺服器 低 | B18: FY2028 −15%、FY2029 −5%、FY2030 −3% | C18: =E540 -> 245.79901 | D18: =E550 -> 0.10418649 | E18: =E554 -> 30.556671 | F18: =E18/E$4-1 -> -0.022249345 | G18: =F540 -> 254.72617 | H18: =F550 -> 0.10367255 | I18: =F554 -> 32.484796 | J18: =I18/I$4-1 -> -0.034411826
A19: 傳統伺服器 高 | B19: +5%／+6%／+6% | C19: =E577 -> 253.31833 | D19: =E587 -> 0.1056948 | E19: =E591 -> 31.947344 | F19: =E19/E$4-1 -> 0.022249345 | G19: =F577 -> 266.21194 | H19: =F587 -> 0.10588709 | I19: =F591 -> 34.674748 | J19: =I19/I$4-1 -> 0.030682991
A20: PC 成長 低 | B20: FY2028 −6%、之後 −4% | C20: =E614 -> 244.14289 | D20: =E624 -> 0.10572734 | E20: =E628 -> 30.799659 | F20: =E20/E$4-1 -> -0.014474226 | G20: =F614 -> 251.26024 | H20: =F624 -> 0.10619111 | I20: =F628 -> 32.821222 | J20: =I20/I$4-1 -> -0.024411815
A21: PC 成長 高 | B21: +8%／+6%／+6% | C21: =E651 -> 252.56743 | D21: =E661 -> 0.10453563 | E21: =E665 -> 31.503312 | F21: =E21/E$4-1 -> 0.0080412366 | G21: =F651 -> 265.84673 | H21: =F661 -> 0.10420538 | I21: =F665 -> 34.077227 | J21: =I21/I$4-1 -> 0.01292209
A22: 淨利 ÷ 營業利益 0.70 | B22: FY2028 起 0.70 | C22: =E688 -> 249.55867 | D22: =E698 -> 0.104952 | E22: =E702 -> 29.16854 | F22: =E22/E$4-1 -> -0.066666667 | G22: =F688 -> 260.79803 | H22: =F698 -> 0.10486755 | I22: =F702 -> 31.399663 | J22: =I22/I$4-1 -> -0.066666667
A23: 回購 少（−1%） | B23: 股數年變動 −1% | C23: =E725 -> 249.55867 | D23: =E735 -> 0.104952 | E23: =E739 -> 30.620654 | F23: =E23/E$4-1 -> -0.02020202 | G23: =F725 -> 260.79803 | H23: =F735 -> 0.10486755 | I23: =F739 -> 32.296933 | J23: =I23/I$4-1 -> -0.039995919
A24: 情境 B | B24: CY2028 顆數 ×0.8、CY2029 ×0.85；份額 ×0.95、AI 營益率 −1pt | C24: =PL!E114 -> 249.55867 | D24: =PL!E124 -> 0.104952 | E24: =PL!E128 -> 31.252007 | F24: =E24/E$4-1 -> 0 | G24: =PL!F114 -> 227.50761 | H24: =PL!F124 -> 0.10084222 | I24: =PL!F128 -> 28.221565 | J24: =I24/I$4-1 -> -0.16113342
A25: 情境 C | B25: CY2028–29 顆數 ×0.6；份額 ×0.85、AI 營益率 −2.5pt | C25: =PL!E151 -> 249.55867 | D25: =PL!E161 -> 0.104952 | E25: =PL!E165 -> 31.252007 | F25: =E25/E$4-1 -> 0 | G25: =PL!F151 -> 192.83008 | H25: =PL!F161 -> 0.097161386 | I25: =PL!F165 -> 23.046834 | J25: =I25/I$4-1 -> -0.31494874
A27: 讀法：情境 B、C 的差異從 FY2029（CY2028）起。FY2028 EPS 主要受 Dell 份額、每顆系統價值與 AI 營益率影響；非 AI（傳統伺服器、儲存、PC）約占營業利益四成，營益率假設影響也大。每顆系統價值的變動大多被 FY2027 份額校準抵銷（只剩世代組合效果）。
A29: 目標價參數（只改 DCF 參數；PL 收斂法的 fade_g 不隨 tp_g 變動）
A30: 案例 | B30: 設定 | C30: DCF 目標價 | D30: Comparable 目標價（相對倍數調整後） | E30: 加權目標價 | F30: 相對基準
A31: 基準 | B31: r 10%、g 4%、DCF 權重 0.5 | C31: =(tp_wA*MAX(0,Val!B8*(1-MIN(tp_g/tp_roe,0.8))*Val!$G$8/(1+tp_r)^Val!$F$8+Val!B9*(1-MIN(tp_g/tp_roe,0.8))*Val!$G$9/(1+tp_r)^Val!$F$9+Val!B10*(1-MIN(tp_g/tp_roe,0.8))*Val!$G$10/(1+tp_r)^Val!$F$10+Val!B11*(1-MIN(tp_g/tp_roe,0.8))*Val!$G$11/(1+tp_r)^Val!$F$11+Val!B12*(1-MIN(tp_g/tp_roe,0.8))*Val!$G$12/(1+tp_r)^Val!$F$12+Val!B13*(1-MIN(tp_g/tp_roe,0.8))*Val!$G$13/(1+tp_r)^Val!$F$13+Val!B13*(1-MIN(tp_g/tp_roe,0.8))*Val!$G$13*(1+tp_g)/(tp_r-tp_g)/(1+tp_r)^Val!$F$13)+tp_wB*MAX(0,Val!C8*(1-MIN(tp_g/tp_roe,0.8))*Val!$G$8/(1+tp_r)^Val!$F$8+Val!C9*(1-MIN(tp_g/tp_roe,0.8))*Val!$G$9/(1+tp_r)^Val!$F$9+Val!C10*(1-MIN(tp_g/tp_roe,0.8))*Val!$G$10/(1+tp_r)^Val!$F$10+Val!C11*(1-MIN(tp_g/tp_roe,0.8))*Val!$G$11/(1+tp_r)^Val!$F$11+Val!C12*(1-MIN(tp_g/tp_roe,0.8))*Val!$G$12/(1+tp_r)^Val!$F$12+Val!C13*(1-MIN(tp_g/tp_roe,0.8))*Val!$G$13/(1+tp_r)^Val!$F$13+Val!C13*(1-MIN(tp_g/tp_roe,0.8))*Val!$G$13*(1+tp_g)/(tp_r-tp_g)/(1+tp_r)^Val!$F$13)+tp_wC*MAX(0,Val!D8*(1-MIN(tp_g/tp_roe,0.8))*Val!$G$8/(1+tp_r)^Val!$F$8+Val!D9*(1-MIN(tp_g/tp_roe,0.8))*Val!$G$9/(1+tp_r)^Val!$F$9+Val!D10*(1-MIN(tp_g/tp_roe,0.8))*Val!$G$10/(1+tp_r)^Val!$F$10+Val!D11*(1-MIN(tp_g/tp_roe,0.8))*Val!$G$11/(1+tp_r)^Val!$F$11+Val!D12*(1-MIN(tp_g/tp_roe,0.8))*Val!$G$12/(1+tp_r)^Val!$F$12+Val!D13*(1-MIN(tp_g/tp_roe,0.8))*Val!$G$13/(1+tp_r)^Val!$F$13+Val!D13*(1-MIN(tp_g/tp_roe,0.8))*Val!$G$13*(1+tp_g)/(tp_r-tp_g)/(1+tp_r)^Val!$F$13))*(1+tp_r) -> 424.95014 | D31: =tp_comp_adj -> 244.03896 | E31: =tp_w_dcf*C31+(1-tp_w_dcf)*D31 -> 334.49455 | F31: =E31/E$31-1 -> 0
A32: 折現率 +1pt | B32: r 11% | C32: =(tp_wA*MAX(0,Val!B8*(1-MIN(tp_g/tp_roe,0.8))*Val!$G$8/(1+(tp_r+0.01))^Val!$F$8+Val!B9*(1-MIN(tp_g/tp_roe,0.8))*Val!$G$9/(1+(tp_r+0.01))^Val!$F$9+Val!B10*(1-MIN(tp_g/tp_roe,0.8))*Val!$G$10/(1+(tp_r+0.01))^Val!$F$10+Val!B11*(1-MIN(tp_g/tp_roe,0.8))*Val!$G$11/(1+(tp_r+0.01))^Val!$F$11+Val!B12*(1-MIN(tp_g/tp_roe,0.8))*Val!$G$12/(1+(tp_r+0.01))^Val!$F$12+Val!B13*(1-MIN(tp_g/tp_roe,0.8))*Val!$G$13/(1+(tp_r+0.01))^Val!$F$13+Val!B13*(1-MIN(tp_g/tp_roe,0.8))*Val!$G$13*(1+tp_g)/((tp_r+0.01)-tp_g)/(1+(tp_r+0.01))^Val!$F$13)+tp_wB*MAX(0,Val!C8*(1-MIN(tp_g/tp_roe,0.8))*Val!$G$8/(1+(tp_r+0.01))^Val!$F$8+Val!C9*(1-MIN(tp_g/tp_roe,0.8))*Val!$G$9/(1+(tp_r+0.01))^Val!$F$9+Val!C10*(1-MIN(tp_g/tp_roe,0.8))*Val!$G$10/(1+(tp_r+0.01))^Val!$F$10+Val!C11*(1-MIN(tp_g/tp_roe,0.8))*Val!$G$11/(1+(tp_r+0.01))^Val!$F$11+Val!C12*(1-MIN(tp_g/tp_roe,0.8))*Val!$G$12/(1+(tp_r+0.01))^Val!$F$12+Val!C13*(1-MIN(tp_g/tp_roe,0.8))*Val!$G$13/(1+(tp_r+0.01))^Val!$F$13+Val!C13*(1-MIN(tp_g/tp_roe,0.8))*Val!$G$13*(1+tp_g)/((tp_r+0.01)-tp_g)/(1+(tp_r+0.01))^Val!$F$13)+tp_wC*MAX(0,Val!D8*(1-MIN(tp_g/tp_roe,0.8))*Val!$G$8/(1+(tp_r+0.01))^Val!$F$8+Val!D9*(1-MIN(tp_g/tp_roe,0.8))*Val!$G$9/(1+(tp_r+0.01))^Val!$F$9+Val!D10*(1-MIN(tp_g/tp_roe,0.8))*Val!$G$10/(1+(tp_r+0.01))^Val!$F$10+Val!D11*(1-MIN(tp_g/tp_roe,0.8))*Val!$G$11/(1+(tp_r+0.01))^Val!$F$11+Val!D12*(1-MIN(tp_g/tp_roe,0.8))*Val!$G$12/(1+(tp_r+0.01))^Val!$F$12+Val!D13*(1-MIN(tp_g/tp_roe,0.8))*Val!$G$13/(1+(tp_r+0.01))^Val!$F$13+Val!D13*(1-MIN(tp_g/tp_roe,0.8))*Val!$G$13*(1+tp_g)/((tp_r+0.01)-tp_g)/(1+(tp_r+0.01))^Val!$F$13))*(1+(tp_r+0.01)) -> 367.69118 | D32: =tp_comp_adj -> 244.03896 | E32: =tp_w_dcf*C32+(1-tp_w_dcf)*D32 -> 305.86507 | F32: =E32/E$31-1 -> -0.085590278
A33: 折現率 −1pt | B33: r 9% | C33: =(tp_wA*MAX(0,Val!B8*(1-MIN(tp_g/tp_roe,0.8))*Val!$G$8/(1+(tp_r-0.01))^Val!$F$8+Val!B9*(1-MIN(tp_g/tp_roe,0.8))*Val!$G$9/(1+(tp_r-0.01))^Val!$F$9+Val!B10*(1-MIN(tp_g/tp_roe,0.8))*Val!$G$10/(1+(tp_r-0.01))^Val!$F$10+Val!B11*(1-MIN(tp_g/tp_roe,0.8))*Val!$G$11/(1+(tp_r-0.01))^Val!$F$11+Val!B12*(1-MIN(tp_g/tp_roe,0.8))*Val!$G$12/(1+(tp_r-0.01))^Val!$F$12+Val!B13*(1-MIN(tp_g/tp_roe,0.8))*Val!$G$13/(1+(tp_r-0.01))^Val!$F$13+Val!B13*(1-MIN(tp_g/tp_roe,0.8))*Val!$G$13*(1+tp_g)/((tp_r-0.01)-tp_g)/(1+(tp_r-0.01))^Val!$F$13)+tp_wB*MAX(0,Val!C8*(1-MIN(tp_g/tp_roe,0.8))*Val!$G$8/(1+(tp_r-0.01))^Val!$F$8+Val!C9*(1-MIN(tp_g/tp_roe,0.8))*Val!$G$9/(1+(tp_r-0.01))^Val!$F$9+Val!C10*(1-MIN(tp_g/tp_roe,0.8))*Val!$G$10/(1+(tp_r-0.01))^Val!$F$10+Val!C11*(1-MIN(tp_g/tp_roe,0.8))*Val!$G$11/(1+(tp_r-0.01))^Val!$F$11+Val!C12*(1-MIN(tp_g/tp_roe,0.8))*Val!$G$12/(1+(tp_r-0.01))^Val!$F$12+Val!C13*(1-MIN(tp_g/tp_roe,0.8))*Val!$G$13/(1+(tp_r-0.01))^Val!$F$13+Val!C13*(1-MIN(tp_g/tp_roe,0.8))*Val!$G$13*(1+tp_g)/((tp_r-0.01)-tp_g)/(1+(tp_r-0.01))^Val!$F$13)+tp_wC*MAX(0,Val!D8*(1-MIN(tp_g/tp_roe,0.8))*Val!$G$8/(1+(tp_r-0.01))^Val!$F$8+Val!D9*(1-MIN(tp_g/tp_roe,0.8))*Val!$G$9/(1+(tp_r-0.01))^Val!$F$9+Val!D10*(1-MIN(tp_g/tp_roe,0.8))*Val!$G$10/(1+(tp_r-0.01))^Val!$F$10+Val!D11*(1-MIN(tp_g/tp_roe,0.8))*Val!$G$11/(1+(tp_r-0.01))^Val!$F$11+Val!D12*(1-MIN(tp_g/tp_roe,0.8))*Val!$G$12/(1+(tp_r-0.01))^Val!$F$12+Val!D13*(1-MIN(tp_g/tp_roe,0.8))*Val!$G$13/(1+(tp_r-0.01))^Val!$F$13+Val!D13*(1-MIN(tp_g/tp_roe,0.8))*Val!$G$13*(1+tp_g)/((tp_r-0.01)-tp_g)/(1+(tp_r-0.01))^Val!$F$13))*(1+(tp_r-0.01)) -> 505.11651 | D33: =tp_comp_adj -> 244.03896 | E33: =tp_w_dcf*C33+(1-tp_w_dcf)*D33 -> 374.57774 | F33: =E33/E$31-1 -> 0.1198321
A34: 長期成長 +1pt | B34: g 5% | C34: =(tp_wA*MAX(0,Val!B8*(1-MIN((tp_g+0.01)/tp_roe,0.8))*Val!$G$8/(1+tp_r)^Val!$F$8+Val!B9*(1-MIN((tp_g+0.01)/tp_roe,0.8))*Val!$G$9/(1+tp_r)^Val!$F$9+Val!B10*(1-MIN((tp_g+0.01)/tp_roe,0.8))*Val!$G$10/(1+tp_r)^Val!$F$10+Val!B11*(1-MIN((tp_g+0.01)/tp_roe,0.8))*Val!$G$11/(1+tp_r)^Val!$F$11+Val!B12*(1-MIN((tp_g+0.01)/tp_roe,0.8))*Val!$G$12/(1+tp_r)^Val!$F$12+Val!B13*(1-MIN((tp_g+0.01)/tp_roe,0.8))*Val!$G$13/(1+tp_r)^Val!$F$13+Val!B13*(1-MIN((tp_g+0.01)/tp_roe,0.8))*Val!$G$13*(1+(tp_g+0.01))/(tp_r-(tp_g+0.01))/(1+tp_r)^Val!$F$13)+tp_wB*MAX(0,Val!C8*(1-MIN((tp_g+0.01)/tp_roe,0.8))*Val!$G$8/(1+tp_r)^Val!$F$8+Val!C9*(1-MIN((tp_g+0.01)/tp_roe,0.8))*Val!$G$9/(1+tp_r)^Val!$F$9+Val!C10*(1-MIN((tp_g+0.01)/tp_roe,0.8))*Val!$G$10/(1+tp_r)^Val!$F$10+Val!C11*(1-MIN((tp_g+0.01)/tp_roe,0.8))*Val!$G$11/(1+tp_r)^Val!$F$11+Val!C12*(1-MIN((tp_g+0.01)/tp_roe,0.8))*Val!$G$12/(1+tp_r)^Val!$F$12+Val!C13*(1-MIN((tp_g+0.01)/tp_roe,0.8))*Val!$G$13/(1+tp_r)^Val!$F$13+Val!C13*(1-MIN((tp_g+0.01)/tp_roe,0.8))*Val!$G$13*(1+(tp_g+0.01))/(tp_r-(tp_g+0.01))/(1+tp_r)^Val!$F$13)+tp_wC*MAX(0,Val!D8*(1-MIN((tp_g+0.01)/tp_roe,0.8))*Val!$G$8/(1+tp_r)^Val!$F$8+Val!D9*(1-MIN((tp_g+0.01)/tp_roe,0.8))*Val!$G$9/(1+tp_r)^Val!$F$9+Val!D10*(1-MIN((tp_g+0.01)/tp_roe,0.8))*Val!$G$10/(1+tp_r)^Val!$F$10+Val!D11*(1-MIN((tp_g+0.01)/tp_roe,0.8))*Val!$G$11/(1+tp_r)^Val!$F$11+Val!D12*(1-MIN((tp_g+0.01)/tp_roe,0.8))*Val!$G$12/(1+tp_r)^Val!$F$12+Val!D13*(1-MIN((tp_g+0.01)/tp_roe,0.8))*Val!$G$13/(1+tp_r)^Val!$F$13+Val!D13*(1-MIN((tp_g+0.01)/tp_roe,0.8))*Val!$G$13*(1+(tp_g+0.01))/(tp_r-(tp_g+0.01))/(1+tp_r)^Val!$F$13))*(1+tp_r) -> 461.6182 | D34: =tp_comp_adj -> 244.03896 | E34: =tp_w_dcf*C34+(1-tp_w_dcf)*D34 -> 352.82858 | F34: =E34/E$31-1 -> 0.054811151
A35: 長期成長 −1pt | B35: g 3% | C35: =(tp_wA*MAX(0,Val!B8*(1-MIN((tp_g-0.01)/tp_roe,0.8))*Val!$G$8/(1+tp_r)^Val!$F$8+Val!B9*(1-MIN((tp_g-0.01)/tp_roe,0.8))*Val!$G$9/(1+tp_r)^Val!$F$9+Val!B10*(1-MIN((tp_g-0.01)/tp_roe,0.8))*Val!$G$10/(1+tp_r)^Val!$F$10+Val!B11*(1-MIN((tp_g-0.01)/tp_roe,0.8))*Val!$G$11/(1+tp_r)^Val!$F$11+Val!B12*(1-MIN((tp_g-0.01)/tp_roe,0.8))*Val!$G$12/(1+tp_r)^Val!$F$12+Val!B13*(1-MIN((tp_g-0.01)/tp_roe,0.8))*Val!$G$13/(1+tp_r)^Val!$F$13+Val!B13*(1-MIN((tp_g-0.01)/tp_roe,0.8))*Val!$G$13*(1+(tp_g-0.01))/(tp_r-(tp_g-0.01))/(1+tp_r)^Val!$F$13)+tp_wB*MAX(0,Val!C8*(1-MIN((tp_g-0.01)/tp_roe,0.8))*Val!$G$8/(1+tp_r)^Val!$F$8+Val!C9*(1-MIN((tp_g-0.01)/tp_roe,0.8))*Val!$G$9/(1+tp_r)^Val!$F$9+Val!C10*(1-MIN((tp_g-0.01)/tp_roe,0.8))*Val!$G$10/(1+tp_r)^Val!$F$10+Val!C11*(1-MIN((tp_g-0.01)/tp_roe,0.8))*Val!$G$11/(1+tp_r)^Val!$F$11+Val!C12*(1-MIN((tp_g-0.01)/tp_roe,0.8))*Val!$G$12/(1+tp_r)^Val!$F$12+Val!C13*(1-MIN((tp_g-0.01)/tp_roe,0.8))*Val!$G$13/(1+tp_r)^Val!$F$13+Val!C13*(1-MIN((tp_g-0.01)/tp_roe,0.8))*Val!$G$13*(1+(tp_g-0.01))/(tp_r-(tp_g-0.01))/(1+tp_r)^Val!$F$13)+tp_wC*MAX(0,Val!D8*(1-MIN((tp_g-0.01)/tp_roe,0.8))*Val!$G$8/(1+tp_r)^Val!$F$8+Val!D9*(1-MIN((tp_g-0.01)/tp_roe,0.8))*Val!$G$9/(1+tp_r)^Val!$F$9+Val!D10*(1-MIN((tp_g-0.01)/tp_roe,0.8))*Val!$G$10/(1+tp_r)^Val!$F$10+Val!D11*(1-MIN((tp_g-0.01)/tp_roe,0.8))*Val!$G$11/(1+tp_r)^Val!$F$11+Val!D12*(1-MIN((tp_g-0.01)/tp_roe,0.8))*Val!$G$12/(1+tp_r)^Val!$F$12+Val!D13*(1-MIN((tp_g-0.01)/tp_roe,0.8))*Val!$G$13/(1+tp_r)^Val!$F$13+Val!D13*(1-MIN((tp_g-0.01)/tp_roe,0.8))*Val!$G$13*(1+(tp_g-0.01))/(tp_r-(tp_g-0.01))/(1+tp_r)^Val!$F$13))*(1+tp_r) -> 400.3254 | D35: =tp_comp_adj -> 244.03896 | E35: =tp_w_dcf*C35+(1-tp_w_dcf)*D35 -> 322.18218 | F35: =E35/E$31-1 -> -0.03680888
A36: DCF 權重 0.3 | C36: =(tp_wA*MAX(0,Val!B8*(1-MIN(tp_g/tp_roe,0.8))*Val!$G$8/(1+tp_r)^Val!$F$8+Val!B9*(1-MIN(tp_g/tp_roe,0.8))*Val!$G$9/(1+tp_r)^Val!$F$9+Val!B10*(1-MIN(tp_g/tp_roe,0.8))*Val!$G$10/(1+tp_r)^Val!$F$10+Val!B11*(1-MIN(tp_g/tp_roe,0.8))*Val!$G$11/(1+tp_r)^Val!$F$11+Val!B12*(1-MIN(tp_g/tp_roe,0.8))*Val!$G$12/(1+tp_r)^Val!$F$12+Val!B13*(1-MIN(tp_g/tp_roe,0.8))*Val!$G$13/(1+tp_r)^Val!$F$13+Val!B13*(1-MIN(tp_g/tp_roe,0.8))*Val!$G$13*(1+tp_g)/(tp_r-tp_g)/(1+tp_r)^Val!$F$13)+tp_wB*MAX(0,Val!C8*(1-MIN(tp_g/tp_roe,0.8))*Val!$G$8/(1+tp_r)^Val!$F$8+Val!C9*(1-MIN(tp_g/tp_roe,0.8))*Val!$G$9/(1+tp_r)^Val!$F$9+Val!C10*(1-MIN(tp_g/tp_roe,0.8))*Val!$G$10/(1+tp_r)^Val!$F$10+Val!C11*(1-MIN(tp_g/tp_roe,0.8))*Val!$G$11/(1+tp_r)^Val!$F$11+Val!C12*(1-MIN(tp_g/tp_roe,0.8))*Val!$G$12/(1+tp_r)^Val!$F$12+Val!C13*(1-MIN(tp_g/tp_roe,0.8))*Val!$G$13/(1+tp_r)^Val!$F$13+Val!C13*(1-MIN(tp_g/tp_roe,0.8))*Val!$G$13*(1+tp_g)/(tp_r-tp_g)/(1+tp_r)^Val!$F$13)+tp_wC*MAX(0,Val!D8*(1-MIN(tp_g/tp_roe,0.8))*Val!$G$8/(1+tp_r)^Val!$F$8+Val!D9*(1-MIN(tp_g/tp_roe,0.8))*Val!$G$9/(1+tp_r)^Val!$F$9+Val!D10*(1-MIN(tp_g/tp_roe,0.8))*Val!$G$10/(1+tp_r)^Val!$F$10+Val!D11*(1-MIN(tp_g/tp_roe,0.8))*Val!$G$11/(1+tp_r)^Val!$F$11+Val!D12*(1-MIN(tp_g/tp_roe,0.8))*Val!$G$12/(1+tp_r)^Val!$F$12+Val!D13*(1-MIN(tp_g/tp_roe,0.8))*Val!$G$13/(1+tp_r)^Val!$F$13+Val!D13*(1-MIN(tp_g/tp_roe,0.8))*Val!$G$13*(1+tp_g)/(tp_r-tp_g)/(1+tp_r)^Val!$F$13))*(1+tp_r) -> 424.95014 | D36: =tp_comp_adj -> 244.03896 | E36: =0.3*C36+(1-0.3)*D36 -> 298.31231 | F36: =E36/E$31-1 -> -0.10816988
A37: DCF 權重 0.7 | C37: =(tp_wA*MAX(0,Val!B8*(1-MIN(tp_g/tp_roe,0.8))*Val!$G$8/(1+tp_r)^Val!$F$8+Val!B9*(1-MIN(tp_g/tp_roe,0.8))*Val!$G$9/(1+tp_r)^Val!$F$9+Val!B10*(1-MIN(tp_g/tp_roe,0.8))*Val!$G$10/(1+tp_r)^Val!$F$10+Val!B11*(1-MIN(tp_g/tp_roe,0.8))*Val!$G$11/(1+tp_r)^Val!$F$11+Val!B12*(1-MIN(tp_g/tp_roe,0.8))*Val!$G$12/(1+tp_r)^Val!$F$12+Val!B13*(1-MIN(tp_g/tp_roe,0.8))*Val!$G$13/(1+tp_r)^Val!$F$13+Val!B13*(1-MIN(tp_g/tp_roe,0.8))*Val!$G$13*(1+tp_g)/(tp_r-tp_g)/(1+tp_r)^Val!$F$13)+tp_wB*MAX(0,Val!C8*(1-MIN(tp_g/tp_roe,0.8))*Val!$G$8/(1+tp_r)^Val!$F$8+Val!C9*(1-MIN(tp_g/tp_roe,0.8))*Val!$G$9/(1+tp_r)^Val!$F$9+Val!C10*(1-MIN(tp_g/tp_roe,0.8))*Val!$G$10/(1+tp_r)^Val!$F$10+Val!C11*(1-MIN(tp_g/tp_roe,0.8))*Val!$G$11/(1+tp_r)^Val!$F$11+Val!C12*(1-MIN(tp_g/tp_roe,0.8))*Val!$G$12/(1+tp_r)^Val!$F$12+Val!C13*(1-MIN(tp_g/tp_roe,0.8))*Val!$G$13/(1+tp_r)^Val!$F$13+Val!C13*(1-MIN(tp_g/tp_roe,0.8))*Val!$G$13*(1+tp_g)/(tp_r-tp_g)/(1+tp_r)^Val!$F$13)+tp_wC*MAX(0,Val!D8*(1-MIN(tp_g/tp_roe,0.8))*Val!$G$8/(1+tp_r)^Val!$F$8+Val!D9*(1-MIN(tp_g/tp_roe,0.8))*Val!$G$9/(1+tp_r)^Val!$F$9+Val!D10*(1-MIN(tp_g/tp_roe,0.8))*Val!$G$10/(1+tp_r)^Val!$F$10+Val!D11*(1-MIN(tp_g/tp_roe,0.8))*Val!$G$11/(1+tp_r)^Val!$F$11+Val!D12*(1-MIN(tp_g/tp_roe,0.8))*Val!$G$12/(1+tp_r)^Val!$F$12+Val!D13*(1-MIN(tp_g/tp_roe,0.8))*Val!$G$13/(1+tp_r)^Val!$F$13+Val!D13*(1-MIN(tp_g/tp_roe,0.8))*Val!$G$13*(1+tp_g)/(tp_r-tp_g)/(1+tp_r)^Val!$F$13))*(1+tp_r) -> 424.95014 | D37: =tp_comp_adj -> 244.03896 | E37: =0.7*C37+(1-0.7)*D37 -> 370.67679 | F37: =E37/E$31-1 -> 0.10816988
A42: 案例區塊：AI 部署 ×0.8（情境 A）
A43: 項目 | B43: 單位 | C43: FY2026A | D43: FY2027（錨點） | E43: FY2028 | F43: FY2029 | G43: FY2030 | H43: FY2031（收斂） | I43: FY2032（收斂） | J43: 說明
A44: A. 商用 GPU 系統市場與 Dell 份額（D 欄＝FY2027 校準年≈CY2026；E–G＝FY2028–FY2030≈CY2027–29）
A45: GB300 級 GPU 顆數 × 情境係數 | B45: 百萬顆 | D45: =ug_26 -> 6.65 | E45: =ug_27*mf_lo -> 1.92 | F45: =ug_28*um28_A*mf_lo -> 0.4 | G45: =ug_29*um29_A*mf_lo -> 0.2
A46: VR200 級 GPU 顆數 × 情境係數 | B46: 百萬顆 | D46: =uv_26 -> 1.7 | E46: =uv_27*mf_lo -> 7.04 | F46: =uv_28*um28_A*mf_lo -> 8.8 | G46: =uv_29*um29_A*mf_lo -> 10.12
A47: 商用 GPU 系統市場（顆數 × 每顆系統價值） | B47: US$B | D47: =D45*v_gb+D46*v_vr -> 595.48611 | E47: =E45*v_gb+E46*v_vr -> 936 | F47: =F45*v_gb+F46*v_vr -> 1050.5556 | G47: =G45*v_gb+G46*v_vr -> 1192.6111 | J47: 百萬顆 × 千美元／顆＝十億美元；ASIC（TPU、Trainium 等）不含
A48: Dell 份額（FY2027 校準）＝ AI 伺服器營收指引 ÷ 市場 | B48: % | D48: =a27_ai/D47 -> 0.12426822 | J48: Derived：分子為公司 FY27 AI 伺服器營收指引；分母為 CY2026 全部商用 GPU 系統價值
A49: 份額相對值（÷ FY2027；全部情境） | B49: x | D49: =1 -> 1 | E49: =rel_28 -> 0.9 | F49: =rel_29 -> 0.85 | G49: =rel_30 -> 0.8
A50: 情境 A 份額乘數（FY2029 起） | B50: x | D50: =1 -> 1 | E50: =1 -> 1 | F50: =srel_A -> 1 | G50: =srel_A -> 1
A51: Dell 有效份額 | B51: % | D51: =$D$48*D49*D50 -> 0.12426822 | E51: =$D$48*E49*E50 -> 0.1118414 | F51: =$D$48*F49*F50 -> 0.10562799 | G51: =$D$48*G49*G50 -> 0.099414577
A52: AI 伺服器營收 | B52: US$B | C52: =a26_ai -> 24.683 | D52: =D47*D51 -> 74 | E52: =E47*E51 -> 104.68355 | F52: =F47*F51 -> 110.96807 | G52: =G47*G51 -> 118.56293
A53: B. 非 AI 營收（傳統伺服器、儲存、PC；不隨 AI 情境）
A54: 傳統伺服器與網通 | B54: US$B | C54: =a26_tr -> 19.512 | D54: =a27_tr -> 37.59663 | E54: =D54*(1+g_tr28) -> 35.716799 | F54: =E54*(1+g_tr29) -> 36.431134 | G54: =F54*(1+g_tr30) -> 37.524069
A55: 儲存 | B55: US$B | C55: =a26_st -> 16.631 | D55: =a27_st -> 19.47008 | E55: =D55*(1+g_st28) -> 20.248883 | F55: =E55*(1+g_st29) -> 21.058839 | G55: =F55*(1+g_st30) -> 21.901192
A56: ISG 營收 | B56: US$B | C56: =C52+C54+C55 -> 60.826 | D56: =D52+D54+D55 -> 131.06671 | E56: =E52+E54+E55 -> 160.64923 | F56: =F52+F54+F55 -> 168.45804 | G56: =G52+G54+G55 -> 177.98819
A57: CSG 營收（PC） | B57: US$B | C57: =a26_csg -> 50.984 | D57: =a27_csg -> 60.17529 | E57: =D57*(1+g_csg28) -> 61.980549 | F57: =E57*(1+g_csg29) -> 63.839965 | G57: =F57*(1+g_csg30) -> 65.755164
A58: 其他業務 | B58: US$B | C58: =a26_oth -> 1.728 | D58: =a27_oth -> 0.758 | E58: =D58 -> 0.758 | F58: =E58 -> 0.758 | G58: =F58 -> 0.758 | J58: FY2028 起持平（Assumed）
A59: 營收 | B59: US$B | C59: =C56+C57+C58 -> 113.538 | D59: =D56+D57+D58 -> 192 | E59: =E56+E57+E58 -> 223.38778 | F59: =F56+F57+F58 -> 233.05601 | G59: =G56+G57+G58 -> 244.50135 | H59: =G59*(1+H60) -> 257.84011 | I59: =H59*(1+I60) -> 273.31051 | J59: FY2031 起為收斂法：營收年增由 FY2030 線性收斂到 fade_g、淨利率收斂到 fade_m（FY2032 達到），非驅動因子推導
A60: 營收年增 | B60: % | D60: =D59/C59-1 -> 0.69106378 | E60: =E59/D59-1 -> 0.16347802 | F60: =F59/E59-1 -> 0.043280022 | G60: =G59/F59-1 -> 0.049109852 | H60: =$G60+(fade_gA-$G60)*1/2 -> 0.054554926 | I60: =$G60+(fade_gA-$G60)*2/2 -> 0.06
A61: AI 伺服器 ÷ 營收 | B61: % | C61: =C52/C59 -> 0.21739858 | D61: =D52/D59 -> 0.38541667 | E61: =E52/E59 -> 0.46861807 | F61: =F52/F59 -> 0.47614336 | G61: =G52/G59 -> 0.48491727
A62: C. 損益（non-GAAP）
A63: AI 伺服器營業利益率 | B63: % | C63: =(a26_isgoi-m_nai*(a26_tr+a26_st))/a26_ai -> 0.053807074 | D63: =(a27_isgoi-m_nai*(a27_tr+a27_st))/a27_ai -> 0.1107101 | E63: =$D63+ai_dm -> 0.1007101 | F63: =$D63+ai_dm+dm_A -> 0.1007101 | G63: =$D63+ai_dm+dm_A -> 0.1007101 | J63: FY2026、FY2027 為殘差（ISG 營業利益 − 非 AI 營益率 m_nai × 非 AI 營收）；FY2028 起＝FY2027＋ai_dm（FY2029 起再加情境變動）
A64: 非 AI ISG 營業利益率 | B64: % | C64: =m_nai -> 0.16 | D64: =m_nai -> 0.16 | E64: =m_naif -> 0.155 | F64: =m_naif -> 0.155 | G64: =m_naif -> 0.155
A65: ISG 營業利益 | B65: US$B | C65: =a26_isgoi -> 7.111 | D65: =a27_isgoi -> 17.323221 | E65: =E52*E63+(E54+E55)*E64 -> 19.217371 | F65: =F52*F63+(F54+F55)*F64 -> 20.086551 | G65: =G52*G63+(G54+G55)*G64 -> 21.1514
A66: CSG 營業利益率 | B66: % | C66: =a26_csgoi/C57 -> 0.055566452 | D66: =a27_csgoi/D57 -> 0.076475273 | E66: =m_csgf -> 0.07 | F66: =m_csgf -> 0.07 | G66: =m_csgf -> 0.07
A67: CSG 營業利益 | B67: US$B | C67: =C57*C66 -> 2.833 | D67: =D57*D66 -> 4.6019217 | E67: =E57*E66 -> 4.3386384 | F67: =F57*F66 -> 4.4687976 | G67: =G57*G66 -> 4.6028615
A68: 分部營業利益（≈ non-GAAP 營業利益） | B68: US$B | C68: =C65+C67 -> 9.944 | D68: =D65+D67 -> 21.925143 | E68: =E65+E67 -> 23.55601 | F68: =F65+F67 -> 24.555349 | G68: =G65+G67 -> 25.754261
A69: 營業利益率 | B69: % | C69: =C68/C59 -> 0.087583012 | D69: =D68/D59 -> 0.11419345 | E69: =E68/E59 -> 0.10544896 | F69: =F68/F59 -> 0.10536244 | G69: =G68/G59 -> 0.10533382
A70: 淨利 ÷ 營業利益 | B70: % | C70: =a26_ni/a26_oi -> 0.70856798 | D70: =a27_ni/a27_oi -> 0.7536553 | E70: =nio_f -> 0.75 | F70: =nio_f -> 0.75 | G70: =nio_f -> 0.75
A71: non-GAAP 淨利 | B71: US$B | C71: =a26_ni -> 7.046 | D71: =a27_ni -> 16.524 | E71: =E68*E70 -> 17.667007 | F71: =F68*F70 -> 18.416511 | G71: =G68*G70 -> 19.315696 | H71: =H59*H75 -> 20.321124 | I71: =I59*I75 -> 21.489154
A72: 稀釋股數 | B72: 十億股 | C72: =a26_sh -> 0.68407767 | D72: =a27_sh -> 0.648 | E72: =D72*(1+sh_g) -> 0.62856 | F72: =E72*(1+sh_g) -> 0.6097032 | G72: =F72*(1+sh_g) -> 0.5914121 | H72: =G72*(1+sh_g) -> 0.57366974 | I72: =H72*(1+sh_g) -> 0.55645965
A73: non-GAAP EPS | B73: US$ | C73: =C71/C72 -> 10.3 | D73: =D71/D72 -> 25.5 | E73: =E71/E72 -> 28.107113 | F73: =F71/F72 -> 30.205699 | G73: =G71/G72 -> 32.660299 | H73: =H71/H72 -> 35.423037 | I73: =I71/I72 -> 38.617632
A74: EPS 年增 | B74: % | D74: =D73/C73-1 -> 1.4757282 | E74: =E73/D73-1 -> 0.10223974 | F74: =F73/E73-1 -> 0.074663865 | G74: =G73/F73-1 -> 0.081262788 | H74: =H73/G73-1 -> 0.084590118 | I74: =I73/H73-1 -> 0.090184107
A75: 淨利率（non-GAAP 淨利 ÷ 營收） | B75: % | C75: =C71/C59 -> 0.062058518 | D75: =D71/D59 -> 0.0860625 | E75: =E71/E59 -> 0.079086722 | F75: =F71/F59 -> 0.079021826 | G75: =G71/G59 -> 0.079000363 | H75: =$G75+(fade_mA-$G75)*1/2 -> 0.078812892 | I75: =$G75+(fade_mA-$G75)*2/2 -> 0.07862542
A76: Dell AI 營收 ÷ 商用 GPU 顆數（每顆） | B76: US$K/顆 | D76: =D52/(D45+D46) -> 8.8622754 | E76: =E52/(E45+E46) -> 11.683432 | F76: =F52/(F45+F46) -> 12.061747 | G76: =G52/(G45+G46) -> 11.488656
A79: 案例區塊：AI 部署 ×1.2（情境 A）
A80: 項目 | B80: 單位 | C80: FY2026A | D80: FY2027（錨點） | E80: FY2028 | F80: FY2029 | G80: FY2030 | H80: FY2031（收斂） | I80: FY2032（收斂） | J80: 說明
A81: A. 商用 GPU 系統市場與 Dell 份額（D 欄＝FY2027 校準年≈CY2026；E–G＝FY2028–FY2030≈CY2027–29）
A82: GB300 級 GPU 顆數 × 情境係數 | B82: 百萬顆 | D82: =ug_26 -> 6.65 | E82: =ug_27*mf_hi -> 2.88 | F82: =ug_28*um28_A*mf_hi -> 0.6 | G82: =ug_29*um29_A*mf_hi -> 0.3
A83: VR200 級 GPU 顆數 × 情境係數 | B83: 百萬顆 | D83: =uv_26 -> 1.7 | E83: =uv_27*mf_hi -> 10.56 | F83: =uv_28*um28_A*mf_hi -> 13.2 | G83: =uv_29*um29_A*mf_hi -> 15.18
A84: 商用 GPU 系統市場（顆數 × 每顆系統價值） | B84: US$B | D84: =D82*v_gb+D83*v_vr -> 595.48611 | E84: =E82*v_gb+E83*v_vr -> 1404 | F84: =F82*v_gb+F83*v_vr -> 1575.8333 | G84: =G82*v_gb+G83*v_vr -> 1788.9167 | J84: 百萬顆 × 千美元／顆＝十億美元；ASIC（TPU、Trainium 等）不含
A85: Dell 份額（FY2027 校準）＝ AI 伺服器營收指引 ÷ 市場 | B85: % | D85: =a27_ai/D84 -> 0.12426822 | J85: Derived：分子為公司 FY27 AI 伺服器營收指引；分母為 CY2026 全部商用 GPU 系統價值
A86: 份額相對值（÷ FY2027；全部情境） | B86: x | D86: =1 -> 1 | E86: =rel_28 -> 0.9 | F86: =rel_29 -> 0.85 | G86: =rel_30 -> 0.8
A87: 情境 A 份額乘數（FY2029 起） | B87: x | D87: =1 -> 1 | E87: =1 -> 1 | F87: =srel_A -> 1 | G87: =srel_A -> 1
A88: Dell 有效份額 | B88: % | D88: =$D$85*D86*D87 -> 0.12426822 | E88: =$D$85*E86*E87 -> 0.1118414 | F88: =$D$85*F86*F87 -> 0.10562799 | G88: =$D$85*G86*G87 -> 0.099414577
A89: AI 伺服器營收 | B89: US$B | C89: =a26_ai -> 24.683 | D89: =D84*D88 -> 74 | E89: =E84*E88 -> 157.02533 | F89: =F84*F88 -> 166.45211 | G89: =G84*G88 -> 177.84439
A90: B. 非 AI 營收（傳統伺服器、儲存、PC；不隨 AI 情境）
A91: 傳統伺服器與網通 | B91: US$B | C91: =a26_tr -> 19.512 | D91: =a27_tr -> 37.59663 | E91: =D91*(1+g_tr28) -> 35.716799 | F91: =E91*(1+g_tr29) -> 36.431134 | G91: =F91*(1+g_tr30) -> 37.524069
A92: 儲存 | B92: US$B | C92: =a26_st -> 16.631 | D92: =a27_st -> 19.47008 | E92: =D92*(1+g_st28) -> 20.248883 | F92: =E92*(1+g_st29) -> 21.058839 | G92: =F92*(1+g_st30) -> 21.901192
A93: ISG 營收 | B93: US$B | C93: =C89+C91+C92 -> 60.826 | D93: =D89+D91+D92 -> 131.06671 | E93: =E89+E91+E92 -> 212.99101 | F93: =F89+F91+F92 -> 223.94208 | G93: =G89+G91+G92 -> 237.26966
A94: CSG 營收（PC） | B94: US$B | C94: =a26_csg -> 50.984 | D94: =a27_csg -> 60.17529 | E94: =D94*(1+g_csg28) -> 61.980549 | F94: =E94*(1+g_csg29) -> 63.839965 | G94: =F94*(1+g_csg30) -> 65.755164
A95: 其他業務 | B95: US$B | C95: =a26_oth -> 1.728 | D95: =a27_oth -> 0.758 | E95: =D95 -> 0.758 | F95: =E95 -> 0.758 | G95: =F95 -> 0.758 | J95: FY2028 起持平（Assumed）
A96: 營收 | B96: US$B | C96: =C93+C94+C95 -> 113.538 | D96: =D93+D94+D95 -> 192 | E96: =E93+E94+E95 -> 275.72956 | F96: =F93+F94+F95 -> 288.54004 | G96: =G93+G94+G95 -> 303.78282 | H96: =G96*(1+H97) -> 320.92031 | I96: =H96*(1+I97) -> 340.17553 | J96: FY2031 起為收斂法：營收年增由 FY2030 線性收斂到 fade_g、淨利率收斂到 fade_m（FY2032 達到），非驅動因子推導
A97: 營收年增 | B97: % | D97: =D96/C96-1 -> 0.69106378 | E97: =E96/D96-1 -> 0.43609144 | F97: =F96/E96-1 -> 0.046460337 | G97: =G96/F96-1 -> 0.052827246 | H97: =$G97+(fade_gA-$G97)*1/2 -> 0.056413623 | I97: =$G97+(fade_gA-$G97)*2/2 -> 0.06
A98: AI 伺服器 ÷ 營收 | B98: % | C98: =C89/C96 -> 0.21739858 | D98: =D89/D96 -> 0.38541667 | E98: =E89/E96 -> 0.56949037 | F98: =F89/F96 -> 0.57687697 | G98: =G89/G96 -> 0.5854327
A99: C. 損益（non-GAAP）
A100: AI 伺服器營業利益率 | B100: % | C100: =(a26_isgoi-m_nai*(a26_tr+a26_st))/a26_ai -> 0.053807074 | D100: =(a27_isgoi-m_nai*(a27_tr+a27_st))/a27_ai -> 0.1107101 | E100: =$D100+ai_dm -> 0.1007101 | F100: =$D100+ai_dm+dm_A -> 0.1007101 | G100: =$D100+ai_dm+dm_A -> 0.1007101 | J100: FY2026、FY2027 為殘差（ISG 營業利益 − 非 AI 營益率 m_nai × 非 AI 營收）；FY2028 起＝FY2027＋ai_dm（FY2029 起再加情境變動）
A101: 非 AI ISG 營業利益率 | B101: % | C101: =m_nai -> 0.16 | D101: =m_nai -> 0.16 | E101: =m_naif -> 0.155 | F101: =m_naif -> 0.155 | G101: =m_naif -> 0.155
A102: ISG 營業利益 | B102: US$B | C102: =a26_isgoi -> 7.111 | D102: =a27_isgoi -> 17.323221 | E102: =E89*E100+(E91+E92)*E101 -> 24.488717 | F102: =F89*F100+(F91+F92)*F101 -> 25.674354 | G102: =G89*G100+(G91+G92)*G101 -> 27.121642
A103: CSG 營業利益率 | B103: % | C103: =a26_csgoi/C94 -> 0.055566452 | D103: =a27_csgoi/D94 -> 0.076475273 | E103: =m_csgf -> 0.07 | F103: =m_csgf -> 0.07 | G103: =m_csgf -> 0.07
A104: CSG 營業利益 | B104: US$B | C104: =C94*C103 -> 2.833 | D104: =D94*D103 -> 4.6019217 | E104: =E94*E103 -> 4.3386384 | F104: =F94*F103 -> 4.4687976 | G104: =G94*G103 -> 4.6028615
A105: 分部營業利益（≈ non-GAAP 營業利益） | B105: US$B | C105: =C102+C104 -> 9.944 | D105: =D102+D104 -> 21.925143 | E105: =E102+E104 -> 28.827355 | F105: =F102+F104 -> 30.143151 | G105: =G102+G104 -> 31.724503
A106: 營業利益率 | B106: % | C106: =C105/C96 -> 0.087583012 | D106: =D105/D96 -> 0.11419345 | E106: =E105/E96 -> 0.10454938 | F106: =F105/F96 -> 0.10446783 | G106: =G105/G96 -> 0.10443153
A107: 淨利 ÷ 營業利益 | B107: % | C107: =a26_ni/a26_oi -> 0.70856798 | D107: =a27_ni/a27_oi -> 0.7536553 | E107: =nio_f -> 0.75 | F107: =nio_f -> 0.75 | G107: =nio_f -> 0.75
A108: non-GAAP 淨利 | B108: US$B | C108: =a26_ni -> 7.046 | D108: =a27_ni -> 16.524 | E108: =E105*E107 -> 21.620516 | F108: =F105*F107 -> 22.607363 | G108: =G105*G107 -> 23.793377 | H108: =H96*H112 -> 25.184071 | I108: =I96*I112 -> 26.746444
A109: 稀釋股數 | B109: 十億股 | C109: =a26_sh -> 0.68407767 | D109: =a27_sh -> 0.648 | E109: =D109*(1+sh_g) -> 0.62856 | F109: =E109*(1+sh_g) -> 0.6097032 | G109: =F109*(1+sh_g) -> 0.5914121 | H109: =G109*(1+sh_g) -> 0.57366974 | I109: =H109*(1+sh_g) -> 0.55645965
...

Sheet Sources
A1: 來源（公司原文為 SEC 8-K 附件 99.1；指引為 Interested-party；券商與資料商皆為 Interested-party）
A2: 公司：8-K 4Q FY26（FY2026 全年實績、分部、FY27 初始指引；股東權益） | B2: https://www.sec.gov/Archives/edgar/data/1571996/000157199626000003/exhibit991earnings8kq4fy26.htm
A3: 公司：8-K 1Q FY27（1Q 實績、分部、上修指引；股東權益） | B3: https://www.sec.gov/Archives/edgar/data/0001571996/000157199626000021/exhibit991earnings8kq1fy27.htm
A4: 公司：8-K 2Q FY27（2Q、1H 實績、分部、3Q 與全年指引；股東權益） | B4: https://www.sec.gov/Archives/edgar/data/0001571996/000157199626000039/exhibit991earnings8kq2fy27.htm
A5: 媒體：Pulse 2.0 2026-09-01（AI 訂單、在手訂單、近四季訂單、自由現金流） | B5: https://pulse2.com/dell-technologies-q2-revenue-hits-record-47-billion-as-ai-server-backlog-reaches-95-billion-and-fy27-outlook-rises-to-192-billion/
A6: 媒體：StorageNewsletter 2026-09-03（儲存全年約 200 億、3Q 儲存與 ISG 成長） | B6: https://www.storagenewsletter.com/2026/09/03/dell-technologies-fiscal-2q27-financial-results/
A7: 媒體：Zacks 2026-09（non-GAAP 毛利率、指引區間、回購） | B7: https://www.zacks.com/stock/news/2984030/dell-q2-earnings-beat-estimates-strong-ai-demand-aids-revenue-growth
A8: 資料商：stockanalysis 統計（價格、股數、P/E、前瞻 P/E） | B8: https://stockanalysis.com/stocks/dell/statistics/
A9: 資料商：stockanalysis 預估（共識 EPS、營收、目標價） | B9: https://stockanalysis.com/stocks/dell/forecast/
A10: 資料商：MarketScreener（10-23 收盤、目標價 29 位） | B10: https://uk.marketscreener.com/quote/stock/DELL-TECHNOLOGIES-INC-50061235/consensus/
A11: 資料商：Alpha Spread（目標價 599.25） | B11: https://alphaspread.com/security/nyse/dell/analyst-estimates
A12: 資料商：Investing.com（目標價 23 位 502.78） | B12: https://www.investing.com/equities/dell-inc-consensus-estimates
A13: 資料商：companiesmarketcap 年底 P/E | B13: https://companiesmarketcap.com/dell/pe-ratio/
... A18: SemiAnalysis | B18: 未使用
