Workbook

Sheet README
A1: Oracle（ORCL）個股模型 v0.4（命題＋營收分部架構） 2026-10-27
A2: 命題：OCI 已簽約的 backlog（RPO 約 6,640 億美元，約一半來自 OpenAI／Stargate）能否以高於資金成本的報酬轉成營收與現金，同時不把資產負債表撐破。命題模組（已連網 MW × 每 MW 年收入〔Tokenomics 持有成本 × 定價倍數 k〕、延誤、租金、AI 折舊）只驅動 Cloud Infrastructure 營收線的「OCI AI 算力」子列；SaaS、授權、支援、硬體、服務各有自己的成長路徑。
A3: 核心問題：FY2029 的 OCI 營收與營業利益率，相對於資本支出與租約的擴張，以及 Oracle 的資金缺口（自由現金流為負）要如何補。
A4: ="投資建議："&Val!C80&"（加權目標價 US$"&TEXT(Val!C74,"0.0")&"，現價 US$"&TEXT(px,"0.00")&"〔2026-10-26〕，上檔空間 "&TEXT(Val!C77,"+0.0%;-0.0%")&"）" -> 投資建議：放空（加權目標價 US$73.2，現價 US$126.06〔2026-10-26〕，上檔空間 -41.9%）
A5: ="重點觀察 1：情境 B 的 FY2029 OCI 營收 "&TEXT(PL!F50,"0.0")&" 十億美元（其中 AI 算力 "&TEXT(PL!F51,"0.0")&"），只有公司路徑 114 的 "&TEXT(Thesis!D121,"0%")&"；OCI AI 營業利益率 "&TEXT(Thesis!G65,"0.0%")&"，AI 增量 ROIC "&TEXT(Thesis!G72,"0.0%")&"，對照 WACC "&TEXT(wacc,"0.0%")&"。" -> 重點觀察 1：情境 B 的 FY2029 OCI 營收 93.6 十億美元（其中 AI 算力 79.0），只有公司路徑 114 的 82%；OCI AI 營業利益率 6.2%，AI 增量 ROIC 1.7%，對照 WACC 10.5%。
A6: ="重點觀察 2：收支關卡（FY2027–FY2031 自由現金流扣股利合計）情境 A／B／C 為 "&TEXT(CF!C4,"0")&"／"&TEXT(CF!D4,"0")&"／"&TEXT(CF!E4,"0")&" 十億美元；情境 B 需新增投資級債 "&TEXT(CF!D5,"0")&"、新股 "&TEXT(CF!D6,"0")&"、高息債 "&TEXT(CF!D7,"0")&"，調整後槓桿峰值 "&TEXT(CF!D8,"0.00")&" 倍。" -> 重點觀察 2：收支關卡（FY2027–FY2031 自由現金流扣股利合計）情境 A／B／C 為 111／73／8 十億美元；情境 B 需新增投資級債 19、新股 0、高息債 0，調整後槓桿峰值 4.43 倍。
A7: ="重點觀察 3：DCF 情境加權 "&TEXT(Val!C72,"0.0")&"、分部加總 "&TEXT(Val!C73,"0.0")&"（OCI AI 以 AI 模組 DCF 計，只占情境 B 分部企業價值的 "&TEXT(Val!D66,"0%")&"）。若 OCI AI 改用 neocloud 同業倍數，加權目標價為 "&TEXT(Val!C86,"0.0")&"：差額就是 AI 的資本密集度（汰換資本支出幾乎吃掉 EBITDA）；市場共識目標價 "&TEXT(cons_tp,"0")&"，高出本模型 "&TEXT(cons_tp/Val!C74-1,"0%")&"。" -> 重點觀察 3：DCF 情境加權 41.7、分部加總 104.7（OCI AI 以 AI 模組 DCF 計，只占情境 B 分部企業價值的 15%）。若 OCI AI 改用 neocloud 同業倍數，加權目標價為 106.4：差額就是 AI 的資本密集度（汰換資本支出幾乎吃掉 EBITDA）；市場共識目標價 237，高出本模型 224%。
A9: 會計年度：FY(t)＝t−1 年 6 月～t 年 5 月。FY2027＝Q1 實績（2026-06～08）＋Q2–Q4 模型；延伸到 FY2032。金額十億美元，MW 為 IT 口徑。
A10: 營收分部層：官方報告分部（10-K 附註 13）＝Cloud and software（雲端與軟體）、Hardware、Services；其下營收線（新聞稿）＝Cloud Infrastructure（OCI）、Cloud Applications（SaaS）、Software license、Software support（以上屬 Cloud and software）、Hardware、Services。命題子列：OCI＝OCI AI 算力（命題模組）＋OCI 其他（非 AI，成長路徑）；子列合計＝母列（PL 頁核對列）。
A11: 驅動 → 推導對照（每頁輸入、推導量、因果方向）
A12: Thesis：In 頁 MW 速度、上限、延誤、計費比例、世代組合、Tokenomics 每 MW 成本、k → 已連網／計費 MW → OCI AI 營收；營運費用＝在役 MW × IF_OpexGW；租金＝未起租 288B 起租；AI 資本支出（FY27＝指引中點、其後新增 MW × IF_CapexIT、汰換依世代年份）→ AI 折舊 → OCI AI 分部利潤貢獻 → ROIC。
A13: Seg：近四季年增率（Q 頁）→ 線性收斂到長期年增（In 頁 G 節）→ SaaS、授權、支援、硬體、服務；OCI＝Thesis 兩子列 → 三分部 → 合併營收。
A14: PL：分部利潤＝OCI AI 貢獻＋其餘雲端與軟體營收 × m_sw（Q1 FY27 校準，對照 FY2024 64.1%）；硬體、服務 × FY2026 利潤率；− 未分攤費用 → GAAP 營業利益 → 利息（CF 頁）、稅 → 淨利 → EPS。
A15: CF：淨利＋D&A＋SBC＋客戶預付 − 預付認列 → 營運現金；− 資本支出 → 自由現金流；− 股利 → 收支關卡；缺口 → 現金 → 投資級債 → 新股 → 高息債（融資瀑布沿用 v0.3.1）→ 股數、淨借款、槓桿。
A16: Val：DCF（UFCF、WACC、g 3%）50%＋分部加總（OCI AI × neocloud 倍數、其餘 × 軟體倍數，FY2029 EBITDA）50%；情境 25／50／25；五級投資建議。Recon：共識與公司路徑對照；Sens：一次動一個輸入的完整重算。
A18: 與 v0.3.1 的差異：v0.3.1 是 CRWV 樣板（OCI MW × 每 MW 收入＋傳統事業四線壓成成長率），本版改為官方分部與六條營收線；AI 營運費用由 Tokenomics 正向推導（取代 EBITDAR 率校準）、AI 折舊與租金進分部利潤與 EPS；評價改為 DCF 50%＋分部加總 50%。舊引擎保留在 oracle/legacy_v0.3/。
A19: 標記：Verified、Interested-party、Analogy、Assumed、Derived；SemiAnalysis 未使用。SEC 網站在建置環境被擋，SEC 數字取自 v0.1a 事實總帳。
A20: 已知限制：(1) OCI 的 AI／非 AI 拆分不存在公開資料，Q1 非 AI 為殘差；(2) 季度分部利潤只有 Q1 FY27 與 FY26Q1；(3) OCI 同業倍數只有兩家；(4) 預付與營運資金外的營運資金變動不建模；(5) 在帳租賃負債持平、到期借款以原利率展延；(6) 續約價格衰退不建模（公司稱續約 +20%）。

Sheet In
A1: In — 輸入（藍字＝輸入；黑字＝公式；基準欄 E 進主模型；D／F＝敏感度低／高，只用於 Sens 頁、不進目標價；情境 A／B／C 的驅動見本頁最後一節「情境驅動對照」〔v0.4.2〕）。金額：十億美元（US$B）；MW＝IT 口徑（MW-IT）；每 MW 金額：百萬美元／MW·年（＝US$B／GW·年）
A2: 標記：Verified／Interested-party／Analogy／Assumed／Derived；Analogy、Assumed 給低／高區間。SemiAnalysis 未使用。「沿用 v0.3.1」＝沿用 oracle/legacy_v0.3 舊引擎 company.json 已核准的參數（原出處見來源欄）
A3: 鍵 | B3: 項目 | C3: 單位 | D3: 敏感度低 | E3: 基準 | F3: 敏感度高 | G3: 標記 | H3: 來源1 | I3: 來源2／說明
A4: A. 股價、股數
A5: px | B5: 現價（2026-10-26 收盤） | C5: US$ | E5: 126.06 | G5: Verified | H5: stockanalysis.com 歷史股價頁（https://stockanalysis.com/stocks/orcl/history/，2026-10-27 擷取）：2026-10-26 收盤 126.06 | I5: markets/invest_map/data/prices.csv：2026-10-23 收盤 126.16（stockanalysis；stockscan 兩來源），與同頁 10-23 值相同；v0.3.1 為 10-21 收盤 129.13
A6: sh_out | B6: 普通股流通在外（2026-09-07） | C6: 十億股 | E6: 3.023736 | G6: Interested-party | H6: Oracle FY27 Q1 10-Q（2026-09-11） 封面（oracle/data/oracle_facts_20261007.json sh.out.20260907） | I6: Q1 FY27 已含 ATM 發行 1.41 億股
A7: opt_dil | B7: 稀釋股數加項（選擇權等） | C7: 十億股 | E7: 0.034 | G7: Derived | H7: Q1 FY27 稀釋加權 3.000 − 基本加權 2.966（oracle/data/oracle_facts_20261007.json sh.dilW／sh.basicW.fy27q1） | I7: 各年沿用
A8: mcps_sh | B8: 強制轉換特別股轉換股數（2029-01-15，FY2029 計入） | C8: 十億股 | E8: 0.031238 | G8: Derived | H8: Series D 50,000 股 × 轉換比率上限 624.7657（oracle/data/oracle_facts_20261007.json mcps.convShares） | I8: 沿用 v0.3.1：一律轉股、取稀釋最大
A9: B. 命題：已連網 MW 路徑與延誤（沿用 v0.3.1 scenarios.mwPath／delayMonths）
A10: mw_fy26 | B10: 已連網 AI MW-IT（FY2026 年底） | C10: MW | E10: 1835 | G10: Derived | H10: FY26 交付 1.2 GW ÷ PUE 1.2 等（oracle/legacy_v0.3/company.json defaults.mwYearEnd） | I10: Oracle 未揭露累計在役 MW（不存在）；口徑不明者 ÷1.2
A11: mw_q1 | B11: 已連網 AI MW-IT（FY27Q1 末，2026-08-31） | C11: MW | E11: 2543 | G11: Derived | H11: 1,835 ＋ Q1 交付 850 MW ÷ 1.2＝708（oracle/legacy_v0.3/company.json fleet.openMw） | I11: Q1 交付 850 MW：Q1 FY27 法說（二手逐字稿，Interested-party）
A12: pace_A | B12: 情境 A：併網速度 | C12: MW-IT／年 | E12: 3333 | G12: Interested-party／Derived | H12: 公司 Q1 預告每季約 1 GW × 4 ÷ 1.2 | I12: 沿用 v0.3.1（oracle/legacy_v0.3/company.json scenarios.mwPath.pace）
A13: cap_A | B13: 情境 A：合約容量上限（已簽站點） | C13: MW-IT | E13: 8778 | G13: Derived | H13: 2,543 ＋ Oracle 承租五個 Stargate 站點 8.1 GW（Epoch 估計，設施）÷1.2 − 已交付 Abilene 515 | I13: 沿用 v0.3.1（oracle/legacy_v0.3/company.json scenarios.mwPath.contracted）；上限以後不假設新簽站點
A14: delay_A | B14: 情境 A：建設延誤（計費路徑後移月數） | C14: 月 | E14: 0 | G14: Assumed | H14: 沿用 v0.3.1（oracle/legacy_v0.3/company.json scenarios.delayMonths）：保守 6（Jupiter 天然氣管線延後近 6 個月）、基準 3、積極 0 | I14: 敏感度 0／3／6／12 月
A15: pace_B | B15: 情境 B：併網速度 | C15: MW-IT／年 | E15: 2833 | G15: Interested-party／Derived | H15: FY27Q1 實際 850 MW × 4 ÷ 1.2 | I15: 沿用 v0.3.1（oracle/legacy_v0.3/company.json scenarios.mwPath.pace）
A16: cap_B | B16: 情境 B：合約容量上限（已簽站點） | C16: MW-IT | E16: 8778 | G16: Derived | H16: 2,543 ＋ Oracle 承租五個 Stargate 站點 8.1 GW（Epoch 估計，設施）÷1.2 − 已交付 Abilene 515 | I16: 沿用 v0.3.1（oracle/legacy_v0.3/company.json scenarios.mwPath.contracted）；上限以後不假設新簽站點
A17: delay_B | B17: 情境 B：建設延誤（計費路徑後移月數） | C17: 月 | E17: 3 | G17: Assumed | H17: 沿用 v0.3.1（oracle/legacy_v0.3/company.json scenarios.delayMonths）：保守 6（Jupiter 天然氣管線延後近 6 個月）、基準 3、積極 0 | I17: 敏感度 0／3／6／12 月
A18: pace_C | B18: 情境 C：併網速度 | C18: MW-IT／年 | E18: 1000 | G18: Derived | H18: FY26 歷史 1.2 GW ÷ 1.2 | I18: 沿用 v0.3.1（oracle/legacy_v0.3/company.json scenarios.mwPath.pace）
A19: cap_C | B19: 情境 C：合約容量上限（已簽站點） | C19: MW-IT | E19: 6284 | G19: Derived／Assumed | H19: 2,543 ＋ Oracle 承租五個 Stargate 站點 8.1 GW（Epoch 估計，設施）÷1.2 − 已交付 Abilene 515；× OpenAI 相關實現 60%（Project Jupiter 不可抗力，2026-09-24；區間 50–70%） | I19: 沿用 v0.3.1（oracle/legacy_v0.3/company.json scenarios.mwPath.contracted）；上限以後不假設新簽站點
A20: delay_C | B20: 情境 C：建設延誤（計費路徑後移月數） | C20: 月 | E20: 6 | G20: Assumed | H20: 沿用 v0.3.1（oracle/legacy_v0.3/company.json scenarios.delayMonths）：保守 6（Jupiter 天然氣管線延後近 6 個月）、基準 3、積極 0 | I20: 敏感度 0／3／6／12 月
A21: u_bill | B21: 計費比例（計費 MW ÷ 延誤後在役 MW） | C21: x | D21: 0.9 | E21: 0.95 | F21: 1 | G21: Assumed | H21: 公司稱 AI 基礎設施利用率 97.9%（Q1 FY27 法說，Interested-party）；新交付產能約一季後才全額計費 | I21: v0.3.1 以收斂比例 80–90% 處理（不同口徑）
A22: C. 命題：世代組合（沿用 v0.3.1 fleet；Assumed）
A23: om_h100 | B23: Q1 末在役世代占比：Hopper H100 | C23: % | D23: 0.1 | E23: 0.2 | F23: 0.3 | G23: Assumed | H23: Oracle 未揭露機隊世代組合（找不到）；Abilene（已連網約 20%）為 GB200（二手） | I23: 沿用 v0.3.1（oracle/legacy_v0.3/company.json fleet.openMix）
A24: om_gb200 | B24: Q1 末在役世代占比：GB200 NVL72 | C24: % | D24: 0.45 | E24: 0.55 | F24: 0.7 | G24: Assumed | H24: Oracle 未揭露機隊世代組合（找不到）；Abilene（已連網約 20%）為 GB200（二手） | I24: 沿用 v0.3.1（oracle/legacy_v0.3/company.json fleet.openMix）
A25: om_gb300 | B25: Q1 末在役世代占比：GB300 NVL72 | C25: % | D25: 0.1 | E25: 0.25 | F25: 0.35 | G25: Assumed | H25: Oracle 未揭露機隊世代組合（找不到）；Abilene（已連網約 20%）為 GB200（二手） | I25: 沿用 v0.3.1（oracle/legacy_v0.3/company.json fleet.openMix）
A26: nm27_gb300 | B26: FY2027 新增產能中 GB300 占比（其餘 VR200） | C26: % | E26: 1 | G26: Assumed | H26: 沿用 v0.3.1 fleet.newMix：FY27 GB300 100% | I26: VR200 2027 下半年起交付
A27: nm28_gb300 | B27: FY2028 新增產能中 GB300 占比（其餘 VR200） | C27: % | D27: 0 | E27: 0.5 | F27: 1 | G27: Assumed | H27: 沿用 v0.3.1 fleet.newMix：FY28 GB300 50%／VR200 50% | I27: 區間：VR200 提前或延後一年
A28: nm29_gb300 | B28: FY2029 起新增產能中 GB300 占比（其餘 VR200） | C28: % | D28: 0 | E28: 0 | F28: 0.5 | G28: Assumed | H28: 沿用 v0.3.1 fleet.newMix：FY29–FY31 VR200 100% | I28: —
A29: rf_h100_30 | B29: FY2030 汰換：H100 在役量的比例（換成 VR200） | C29: % | E29: 0.5 | G29: Assumed | H29: GPU 經濟壽命 6 年（Tokenomics IF_DeprLifeIT；Oracle 伺服器耐用年限 6 年，10-K）：H100 約 FY24–FY25 上線 | I29: v0.3.1 為觸頂後穩態汰換；本版改依世代年份（判斷，見報告第 5 節）
A30: rf_h100_31 | B30: FY2031 汰換：H100 在役量的比例 | C30: % | E30: 0.5 | G30: Assumed | H30: 同上 | I30: —
A31: rf_gb200_32 | B31: FY2032 汰換：GB200 在役量的比例 | C31: % | E31: 1 | G31: Assumed | H31: GB200 約 FY26 上線 | I31: GB300 以後的汰換落在 FY2033 以後（模型期外；永續價值改用穩態汰換）
A32: D. 命題：每 MW 經濟性（Tokenomics v21.4 快照，基準成本情境；修正一自 v19.0 升級，與 MAG 相同）
A33: he_h100 | B33: 每 MW 年持有成本（經濟口徑）IF_HoldEcon｜Hopper H100 | C33: US$M／MW·年 | D33: 6.7911 | E33: 9.7031 | F33: 16.6638 | G33: Derived | H33: oracle/data/tokenomics_snapshot_v21.4.json（Tokenomics v21.4，3ac70ac；複製自 microsoft/data）Interface!13 列 | I33: 低／高＝Tokenomics 低成本／高成本情境（只作敏感度）
A34: he_gb200 | B34: 每 MW 年持有成本（經濟口徑）IF_HoldEcon｜GB200 NVL72 | C34: US$M／MW·年 | D34: 6.6118 | E34: 8.8282 | F34: 14.3186 | G34: Derived | H34: oracle/data/tokenomics_snapshot_v21.4.json（Tokenomics v21.4，3ac70ac；複製自 microsoft/data）Interface!13 列 | I34: 低／高＝Tokenomics 低成本／高成本情境（只作敏感度）
A35: he_gb300 | B35: 每 MW 年持有成本（經濟口徑）IF_HoldEcon｜GB300 NVL72 | C35: US$M／MW·年 | D35: 8.4289 | E35: 10.8864 | F35: 18.5346 | G35: Derived | H35: oracle/data/tokenomics_snapshot_v21.4.json（Tokenomics v21.4，3ac70ac；複製自 microsoft/data）Interface!13 列 | I35: 低／高＝Tokenomics 低成本／高成本情境（只作敏感度）
A36: he_vr200 | B36: 每 MW 年持有成本（經濟口徑）IF_HoldEcon｜VR200 NVL72 | C36: US$M／MW·年 | D36: 9.2191 | E36: 12.2255 | F36: 19.7506 | G36: Derived | H36: oracle/data/tokenomics_snapshot_v21.4.json（Tokenomics v21.4，3ac70ac；複製自 microsoft/data）Interface!13 列 | I36: 低／高＝Tokenomics 低成本／高成本情境（只作敏感度）
A37: cx_h100 | B37: 每 MW IT 資本支出 IF_CapexIT｜Hopper H100 | C37: US$M／MW | E37: 27.5102 | G37: Derived | H37: 同上 Interface!9 列（只含 IT；機房以租賃取得） | I37: 沿用 v0.3.1 methodology.perMw.capexName
A38: cx_gb200 | B38: 每 MW IT 資本支出 IF_CapexIT｜GB200 NVL72 | C38: US$M／MW | E38: 24.0152 | G38: Derived | H38: 同上 Interface!9 列（只含 IT；機房以租賃取得） | I38: 沿用 v0.3.1 methodology.perMw.capexName
A39: cx_gb300 | B39: 每 MW IT 資本支出 IF_CapexIT｜GB300 NVL72 | C39: US$M／MW | E39: 32.2372 | G39: Derived | H39: 同上 Interface!9 列（只含 IT；機房以租賃取得） | I39: 沿用 v0.3.1 methodology.perMw.capexName
A40: cx_vr200 | B40: 每 MW IT 資本支出 IF_CapexIT｜VR200 NVL72 | C40: US$M／MW | E40: 37.5864 | G40: Derived | H40: 同上 Interface!9 列（只含 IT；機房以租賃取得） | I40: 沿用 v0.3.1 methodology.perMw.capexName
A41: ox_h100 | B41: 每 MW 年營運費用（不含折舊；含電費）IF_OpexGW｜Hopper H100 | C41: US$M／MW·年 | E41: 1.8847 | G41: Derived | H41: 同上 IF_OpexGW（電費、IT 與廠房維護、人員、稅與保險） | I41: 本版新增：AI 營運成本由 Tokenomics 正向推導（v0.3.1 用 EBITDAR 率）
A42: ox_gb200 | B42: 每 MW 年營運費用（不含折舊；含電費）IF_OpexGW｜GB200 NVL72 | C42: US$M／MW·年 | E42: 1.8122 | G42: Derived | H42: 同上 IF_OpexGW（電費、IT 與廠房維護、人員、稅與保險） | I42: 本版新增：AI 營運成本由 Tokenomics 正向推導（v0.3.1 用 EBITDAR 率）
A43: ox_gb300 | B43: 每 MW 年營運費用（不含折舊；含電費）IF_OpexGW｜GB300 NVL72 | C43: US$M／MW·年 | E43: 1.9826 | G43: Derived | H43: 同上 IF_OpexGW（電費、IT 與廠房維護、人員、稅與保險） | I43: 本版新增：AI 營運成本由 Tokenomics 正向推導（v0.3.1 用 EBITDAR 率）
A44: ox_vr200 | B44: 每 MW 年營運費用（不含折舊；含電費）IF_OpexGW｜VR200 NVL72 | C44: US$M／MW·年 | E44: 2.0935 | G44: Derived | H44: 同上 IF_OpexGW（電費、IT 與廠房維護、人員、稅與保險） | I44: 本版新增：AI 營運成本由 Tokenomics 正向推導（v0.3.1 用 EBITDAR 率）
A45: life_ai | B45: AI 設備折舊年限 | C45: 年 | D45: 5 | E45: 6 | F45: 6 | G45: Derived | H45: Tokenomics IF_DeprLifeIT｜GB300 基準 6（高成本 4） | I45: Oracle 伺服器與網通設備耐用年限 6 年（10-K，oracle/data/oracle_facts_20261007.json ppe.serverLife）
A46: p_long | B46: 長約價格證據：IREN–Microsoft GB300 五年約 | C46: US$M／MW·年 | D46: 8.9073 | E46: 9.7 | F46: 12.7247 | G46: Derived | H46: IREN 新聞稿 2025-11-03：$9.7bn ÷ 5 年 ÷ 200 MW（含 20% 預付） | I46: 沿用 v0.3.1 pricing.anchorMultiple（低／高為 v0.3 的 k 0.70／1.00 × v5.27 錨換成固定價格）
A47: p_spot | B47: 現貨價格證據：H100 Silicon Data 指數 | C47: US$／GPU-hr | E47: 2.82 | G47: Verified | H47: Silicon Data H100 Index（2026-10-06） | I47: 沿用 v0.3.1
A48: gh_h100 | B48: 每 GPU 小時持有成本 IF_GPUhrEcon｜Hopper H100 | C48: US$／GPU-hr | E48: 1.5426 | G48: Derived | H48: Tokenomics v21.4 快照 | I48: —
A49: od_share | B49: 隨需（現貨）占計費產能比例 | C49: % | D49: 0 | E49: 0.1 | F49: 0.2 | G49: Assumed | H49: 公司未揭露長約／隨需比例（找不到）；Oracle 以 take-or-pay 大型容量合約為主 | I49: 沿用 v0.3.1 pricing.anchorMultiple.onDemandShare
A50: k_long | B50: 長約定價倍數 k_長約（＝長約價 ÷ GB300 持有成本） | C50: x | D50: =p_long_lo/he_gb300 -> 0.81820437 | E50: =p_long/he_gb300 -> 0.89101999 | F50: =p_long_hi/he_gb300 -> 1.1688621 | G50: Derived | H50: 契約第 4 條預設解讀：長約以略低於打平租金換取預付與五年確定性 | I50: Oracle–OpenAI 合約隱含 k 約 1.22（4.5 GW 視為 IT）／1.47（視為設施），金額未經證實，只作敏感度
A51: k_spot | B51: 現貨定價倍數 k_現貨 | C51: x | E51: =p_spot/gh_h100 -> 1.8280825 | G51: Derived | H51: H100 現貨指數 ÷ H100 每 GPU 小時持有成本 | I51: —
A52: k_mix | B52: 定價倍數 k（隨需占比加權） | C52: x | E52: =od_share*k_spot+(1-od_share)*k_long -> 0.98472624 | G52: Derived | H52: k＝隨需占比 × k_現貨 ＋（1 − 隨需占比）× k_長約 | I52: 每 MW 年收入＝在役世代加權 IF_HoldEcon × k；不以 Oracle 營收、RPO、指引反推
A53: k_adj | B53: k 調整係數（敏感度用；基準 1） | C53: x | D53: 0.9 | E53: 1 | F53: 1.2 | G53: Assumed | H53: 敏感度：k ×0.9／×1.2（1.2 約當 Oracle 自身合約隱含 k 1.22） | I53: —
A54: lam | B54: 成長型資本支出提前比例 λ（次期新增產能的設備在本期付款） | C54: % | E54: 0.35 | G54: Assumed | H54: 沿用 v0.3.1 defaults.lambda | I54: —
A55: E. 命題：租賃（未起租 288B；沿用 v0.3.1 leases.uncommenced）
A56: lease_unc | B56: 未起租租賃承諾（未折現） | C56: US$B | E56: 288 | G56: Interested-party | H56: Oracle FY27 Q1 10-Q（2026-09-11） 附註 6（oracle/data/oracle_facts_20261007.json lease.uncommenced.fy27q1） | I56: FY27Q2 至 FY2029 起租、期限 15–19 年
A57: lease_q | B57: 未起租租約起租季數（FY27Q2 起平均） | C57: 季 | E57: 11 | G57: Interested-party | H57: Oracle FY27 Q1 10-Q（2026-09-11） 附註 6：FY27Q2 至 FY2029 起租 | I57: 沿用 v0.3.1
A58: lease_q0 | B58: FY2027 年底已起租季數（FY27Q2 起每季一批） | C58: 季 | E58: 3 | G58: Derived | H58: FY27Q2、Q3、Q4 三季 | I58: 之後每年＋4 季，至 lease_q 為止
A59: lease_term | B59: 未起租租約期限（直線付租） | C59: 年 | D59: 15 | E59: 17 | F59: 19 | G59: Assumed | H59: 沿用 v0.3.1：區間中點 17 年 | I59: 11 季平均起租（FY27Q2–FY29Q4）；三情境相同（合約性，不隨 MW 縮放）
A60: oplease_q1 | B60: 營業租賃負債（FY27Q1 末） | C60: US$B | E60: 34.621 | G60: Interested-party | H60: Oracle FY27 Q1 10-Q（2026-09-11）（oracle/data/oracle_facts_20261007.json bs.opLease.fy27q1） | I60: —
A61: finlease_q1 | B61: 融資租賃負債（FY27Q1 末；列入淨負債與 WACC 的負債） | C61: US$B | E61: 9.185 | G61: Interested-party | H61: Oracle FY27 Q1 10-Q（2026-09-11）（oracle/data/oracle_facts_20261007.json bs.finLease.fy27q1） | I61: 修正一：列入淨負債（F6）
A62: lease_on | B62: 在帳租賃負債（營業＋融資，FY27Q1 末） | C62: US$B | E62: =oplease_q1+finlease_q1 -> 43.806 | G62: Interested-party | H62: Oracle FY27 Q1 10-Q（2026-09-11）（oracle/data/oracle_facts_20261007.json bs.opLease／bs.finLease.fy27q1） | I62: 不含未起租
A63: lease_r | B63: 租賃折現率 | C63: % | E63: 0.057 | G63: Verified | H63: Oracle FY2026 10-K（2026-06-22；附註 13 分部） 營業／融資租賃加權平均折現率 5.7% | I63: 沿用 v0.3.1
A64: oplcost_q1 | B64: 營業租賃費用（Q1 FY27） | C64: US$B | E64: 1.101 | G64: Interested-party | H64: Oracle FY27 Q1 10-Q（2026-09-11）（oracle/data/oracle_facts_20261007.json lease.opCost.fy27q1） | I64: —
A65: rent_on | B65: 在帳租約年租金（營業租賃費用年化；算槓桿用） | C65: US$B | E65: =oplcost_q1*4 -> 4.404 | G65: Derived | H65: Oracle FY27 Q1 10-Q（2026-09-11） 營業租賃費用 1.101 × 4 | I65: 已含在各分部成本內，只用於調整後槓桿
A66: F. 命題：OCI 其他（非 AI）營收路徑
A67: gna0 | B67: OCI 其他（非 AI）年增：FY2027 | C67: % | D67: 0.1 | E67: 0.2 | F67: 0.3 | G67: Assumed | H67: 公司未揭露 OCI 的 AI／非 AI 拆分（不存在）；FY24 OCI（AI 規模化前）年增約 50%（含早期 AI） | I67: Q1 FY27 的非 AI 部分為殘差（Thesis 頁 C 欄），v0.3.1 非 AI 占比區間 12–30%
A68: gnaLT | B68: OCI 其他（非 AI）年增：FY2032（線性收斂） | C68: % | D68: 0.05 | E68: 0.08 | F68: 0.12 | G68: Assumed | H68: 一般 IaaS 長期成長 | I68: —
A69: G. 其他營收線：長期年增（FY2032；FY2027 起點＝近四季年增率，Q 頁 Derived，線性收斂）
A70: gLT_saas | B70: Cloud Applications（SaaS） 長期年增（FY2032） | C70: % | D70: 0.05 | E70: 0.08 | F70: 0.1 | G70: Assumed | H70: 沿用 v0.3.1 legacyBiz SaaS gLT 8% | I70: FY2028–FY2031 由近四季年增率線性收斂
A71: gLT_lic | B71: Software license 長期年增（FY2032） | C71: % | D71: -0.05 | E71: -0.02 | F71: 0 | G71: Assumed | H71: v0.3.1 為授權＋支援合併 −1%；本版拆開，授權 −2%（判斷） | I71: FY2028–FY2031 由近四季年增率線性收斂
A72: gLT_sup | B72: Software support 長期年增（FY2032） | C72: % | D72: -0.03 | E72: -0.01 | F72: 0.01 | G72: Assumed | H72: v0.3.1 為授權＋支援合併 −1% | I72: FY2028–FY2031 由近四季年增率線性收斂
A73: gLT_hw | B73: Hardware 長期年增（FY2032） | C73: % | D73: -0.03 | E73: 0 | F73: 0.03 | G73: Assumed | H73: 沿用 v0.3.1 legacyBiz 硬體 0% | I73: FY2028–FY2031 由近四季年增率線性收斂
A74: gLT_svc | B74: Services 長期年增（FY2032） | C74: % | D74: 0 | E74: 0.03 | F74: 0.05 | G74: Assumed | H74: 沿用 v0.3.1 legacyBiz 服務 3% | I74: FY2028–FY2031 由近四季年增率線性收斂
A75: H. 分部利潤率、未分攤費用（Q 頁實績推得）
A76: m_hw | B76: Hardware 分部利潤率 | C76: % | E76: =Q!L17/Q!L8 -> 0.65402075 | G76: Derived | H76: Oracle FY2026 10-K（2026-06-22；附註 13 分部）：FY2026 硬體分部利潤 2,017 ÷ 營收 3,084 | I76: Q1 FY27 為 58.4%
A77: m_svc | B77: Services 分部利潤率 | C77: % | E77: =Q!L18/Q!L9 -> 0.26693366 | G77: Derived | H77: Oracle FY2026 10-K（2026-06-22；附註 13 分部）：FY2026 服務分部利潤 1,533 ÷ 營收 5,743 | I77: Q1 FY27 為 31.5%
A78: m_sw | B78: Cloud and software 分部中「OCI AI 以外」的利潤率（以 Q1 FY27 校準） | C78: % | E78: =Thesis!C112 -> 0.64521949 | G78: Derived | H78: （Q1 FY27 分部利潤 9.358 − 命題估計的 Q1 OCI AI 貢獻）÷（Q1 分部營收 17.157 − 命題估計的 Q1 OCI AI 營收）；見 Thesis 頁 C 欄 | I78: 對照：FY2024（AI 規模化前）雲端與軟體分部利潤率 64.1%（Q 頁）
A79: m_adj | B79: 「OCI AI 以外」利潤率調整（敏感度用；基準 0） | C79: pt | D79: -0.03 | E79: 0 | F79: 0.03 | G79: Assumed | H79: SaaS 占比上升、授權與支援下滑的組合效果未分開建模 | I79: —
A80: un_rr | B80: 未分攤費用 FY27 Q2–Q4 每季 ÷ Q1 實績 | C80: x | D80: 1 | E80: =Q!L20/4/Q!I20 -> 1.2341934 | F80: 1.35 | G80: Assumed | H80: 修正一預設：回到 FY2026 季均 4.353（Q1 FY27 3.527 偏低，可能含一次性因素） | I80: 低＝Q1 實績水準（v0.4 原預設）；Sens 頁列示
A81: un_g | B81: 未分攤費用（研發、管理、攤銷、SBC 等）年增（FY2028 起） | C81: % | D81: 0.02 | E81: 0.04 | F81: 0.06 | G81: Assumed | H81: 無：公司不揭露未分攤費用預算 | I81: SBC 同比例
A82: sbc_q1 | B82: 股份基礎給付 SBC（Q1 FY27） | C82: US$B | E82: 1.127 | G82: Interested-party | H82: Oracle FY27 Q1 10-Q（2026-09-11）（oracle/data/oracle_facts_20261007.json is.sbc.fy27q1） | I82: FY2026 4.811
A83: da_q1 | B83: 折舊與攤銷（Q1 FY27） | C83: US$B | E83: =Q!I24 -> 3.358 | G83: Interested-party | H83: Q 頁 | I83: —
A84: amort | B84: 無形資產攤銷（年） | C84: US$B | E84: =(da_q1-dep_q1)*4 -> 0.632 | G84: Derived | H84: Q1 FY27 D&A 3.358 − 折舊 3.200（oracle/data/oracle_facts_20261007.json is.da／dep.fy27q1）× 4 | I84: FY2026 1.671，逐年下降；各年沿用 Q1 年化（偏高）
A85: dep_q1 | B85: PP&E 折舊（Q1 FY27） | C85: US$B | E85: 3.2 | G85: Interested-party | H85: Oracle FY27 Q1 10-Q（2026-09-11）（oracle/data/oracle_facts_20261007.json dep.fy27q1） | I85: —
A86: dep_fy24 | B86: PP&E 折舊（FY2024，AI 規模化前） | C86: US$B | E86: 3.129 | G86: Verified | H86: Oracle FY2026 10-K（2026-06-22；附註 13 分部）（oracle/data/oracle_facts_20261007.json is.dep.fy2024） | I86: —
A87: nonai_dep_q | B87: 非 AI 折舊（每季） | C87: US$B | E87: =dep_fy24/4 -> 0.78225 | G87: Derived | H87: Oracle FY2026 10-K（2026-06-22；附註 13 分部）：FY2024（AI 規模化前）折舊 3.129 ÷ 4 | I87: Q1 其餘折舊視為 AI 在役設備；FY2028 起隨非 AI 營收等比例
A88: cip_q1 | B88: 在建工程（FY27Q1 末；視為 AI 設備，FY27 Q2–Q4 起投入使用） | C88: US$B | E88: 48.546 | G88: Interested-party | H88: Oracle FY27 Q1 10-Q（2026-09-11）（oracle/data/oracle_facts_20261007.json bs.cip.fy27q1） | I88: 判斷：Q1 末之前的支出不是已在 Q1 折舊內，就是在建工程
A89: nonai_cx | B89: 非 AI 資本支出 ÷ 非 AI 營收 | C89: % | D89: 0.05 | E89: 0.08 | F89: 0.12 | G89: Assumed | H89: FY2024 資本支出 6.866 ÷ 營收 52.961＝13%（含早期 OCI 擴建） | I89: 非 AI 折舊另以 FY2024 水準隨非 AI 營收等比例（不隨本參數變動）
A90: I. 現金流、融資（沿用 v0.3.1 defaults；FY27 以 Q1 實績＋指引為錨）
A91: capex_g27 | B91: FY2027 資本支出（公司指引中點） | C91: US$B | D91: 90 | E91: 92.5 | F91: 95 | G91: Interested-party | H91: Q1 FY27 法說：FY27 資本支出 90–95（二手逐字稿；oracle/data/oracle_facts_20261007.json guide.fy27.capex） | I91: C10：近期以實績＋公司指引為錨；FY2028 起由命題推導
A92: prepay_cov | B92: 客戶出資覆蓋比（預付 ÷ AI 資本支出） | C92: % | D92: 0.222 | E92: 0.243 | F92: 0.37 | G92: Derived | H92: FY27 指引：資本支出 90–95、淨現金資本支出 ≤70 → 22.2–26.3% 中點（沿用 v0.3.1 defaults.prepay.capexCover） | I92: 高＝Q1 實際 37.0%
A93: prepay_open | B93: 客戶預付（重大財務組成）累計現金（FY27Q1 末） | C93: US$B | E93: 15.955 | G93: Derived | H93: FY26 4.592 ＋ Q1 FY27 11.363（oracle/data/oracle_facts_20261007.json prepay.cash.cum） | I93: 5 年認列為非現金營收（自營運現金扣除）
A94: prepay_yrs | B94: 預付認列年數 | C94: 年 | D94: 3 | E94: 5 | F94: 5 | G94: Assumed | H94: 沿用 v0.3.1：OpenAI 合約 2027 起 5 年 | I94: —
A95: etr | B95: 有效稅率 | C95: % | D95: 0.126 | E95: 0.151 | F95: 0.17 | G95: Interested-party | H95: Oracle Q1 FY27 財報新聞稿（8-K 2026-09-10 附件 99.1）：Q1 FY27 GAAP 有效稅率 15.1% | I95: FY2026 12.62%（10-K）
A96: debt_q1 | B96: 借款本金（FY27Q1 末） | C96: US$B | E96: 125 | G96: Interested-party | H96: Oracle FY27 Q1 10-Q（2026-09-11） 附註 2（oracle/data/oracle_facts_20261007.json bs.debtPar.fy27q1） | I96: 到期再融資假設以相同利率展延
A97: int_q1 | B97: 利息費用（Q1 FY27） | C97: US$B | E97: =Q!I26 -> 1.428 | G97: Interested-party | H97: Q 頁 | I97: —
A98: ii_q1 | B98: 利息收入（Q1 FY27） | C98: US$B | E98: 0.306 | G98: Interested-party | H98: Oracle Q1 FY27 財報新聞稿（8-K 2026-09-10 附件 99.1）（oracle/data/oracle_facts_20261007.json is.interestIncome.fy27q1） | I98: Q 頁未列（新聞稿只有 Q1）
A99: r_old | B99: 既有借款平均利率（Q1 利息費用年化 ÷ 本金） | C99: % | E99: =int_q1*4/debt_q1 -> 0.045696 | G99: Derived | H99: Oracle Q1 FY27 財報新聞稿（8-K 2026-09-10 附件 99.1）：Q1 利息費用 1.428 | I99: —
A100: r_new | B100: 新增投資級債利率 | C100: % | D100: 0.05 | E100: 0.058 | F100: 0.0811 | G100: Assumed | H100: 沿用 v0.3.1 新債票面 5.8% | I100: 高＝6.55% 2046 票據殖利率 8.11%（2026-10-01，Benzinga）
...

Sheet Q
A1: Q — 實績（十億美元）。會計年度 FY(t)＝t−1 年 6 月～t 年 5 月。藍字＝輸入；黑字＝公式。季度＝公司新聞稿「Supplemental analysis of GAAP revenues」；年度＝10-K（經查核）
A2: 資料取自 oracle/data/oracle_facts_20261007.json（v0.1a 起 SEC 一手資料：10-K [Verified]、10-Q 與新聞稿 [Interested-party]）。官方報告分部（10-K 附註 13）：雲端與軟體（Cloud and software）、硬體、服務；營收線（新聞稿）：Cloud Infrastructure、Cloud Applications、Software license、Software support、Hardware、Services
A3: 項目 | B3: FY25 Q2（2024-09～11） | C3: FY25 Q3（～2025-02） | D3: FY25 Q4（～05） | E3: FY26 Q1（～08） | F3: FY26 Q2（～11） | G3: FY26 Q3（～2026-02） | H3: FY26 Q4（～05） | I3: FY27 Q1（2026-06～08） | J3: FY2024 | K3: FY2025 | L3: FY2026 | M3: 標記 | N3: 來源 | O3: 說明
A4: Cloud Infrastructure（OCI） | B4: 2.434 | C4: 2.652 | D4: 2.995 | E4: 3.347 | F4: 4.079 | G4: 4.888 | H4: 5.787 | I4: 7.388 | J4: 6.84 | K4: 10.234 | L4: 18.101 | M4: Verified（年度）／Interested-party（季度） | N4: 公司財報新聞稿（8-K 附件 99.1，各季）；FY2024–FY2026＝10-K
A5: Cloud Applications（SaaS） | B5: 3.503 | C5: 3.558 | D5: 3.742 | E5: 3.839 | F5: 3.898 | G5: 4.026 | H5: 4.126 | I5: 4.219 | J5: 12.934 | K5: 14.272 | L5: 15.888 | M5: Verified（年度）／Interested-party（季度） | N5: 公司財報新聞稿（8-K 附件 99.1，各季）；FY2024–FY2026＝10-K
A6: Software license | B6: 1.195 | C6: 1.129 | D6: 2.007 | E6: 0.766 | F6: 0.939 | G6: 1.15 | H6: 1.881 | I6: 0.655 | J6: 5.081 | K6: 5.201 | L6: 4.737 | M6: Verified（年度）／Interested-party（季度） | N6: 公司財報新聞稿（8-K 附件 99.1，各季）；FY2024–FY2026＝10-K
A7: Software support | B7: 4.869 | C7: 4.797 | D7: 4.961 | E7: 4.955 | F7: 4.938 | G7: 4.969 | H7: 4.943 | I7: 4.895 | J7: 19.609 | K7: 19.523 | L7: 19.804 | M7: Verified（年度）／Interested-party（季度） | N7: 公司財報新聞稿（8-K 附件 99.1，各季）；FY2024–FY2026＝10-K
A8: Hardware | B8: 0.728 | C8: 0.703 | D8: 0.85 | E8: 0.67 | F8: 0.776 | G8: 0.714 | H8: 0.924 | I8: 0.774 | J8: 3.066 | K8: 2.936 | L8: 3.084 | M8: Verified（年度）／Interested-party（季度） | N8: 公司財報新聞稿（8-K 附件 99.1，各季）；FY2024–FY2026＝10-K
A9: Services | B9: 1.33 | C9: 1.291 | D9: 1.348 | E9: 1.349 | F9: 1.428 | G9: 1.443 | H9: 1.523 | I9: 1.414 | J9: 5.431 | K9: 5.233 | L9: 5.743 | M9: Verified（年度）／Interested-party（季度） | N9: 公司財報新聞稿（8-K 附件 99.1，各季）；FY2024–FY2026＝10-K
A10: 合併營收（公司揭露） | B10: 14.059 | C10: 14.13 | D10: 15.903 | E10: 14.926 | F10: 16.058 | G10: 17.19 | H10: 19.184 | I10: 19.345 | J10: 52.961 | K10: 57.399 | L10: 67.357 | M10: Verified（年度）／Interested-party（季度） | N10: 公司財報新聞稿（8-K 附件 99.1，各季）；FY2024–FY2026＝10-K
A11: 分部：Cloud and software（＝OCI＋SaaS＋授權＋支援） | B11: =SUM(B4:B7) -> 12.001 | C11: =SUM(C4:C7) -> 12.136 | D11: =SUM(D4:D7) -> 13.705 | E11: =SUM(E4:E7) -> 12.907 | F11: =SUM(F4:F7) -> 13.854 | G11: =SUM(G4:G7) -> 15.033 | H11: =SUM(H4:H7) -> 16.737 | I11: =SUM(I4:I7) -> 17.157 | ... L11: =SUM(L4:L7) -> 58.53 | M11: Derived | N11: Oracle FY2026 10-K（2026-06-22；附註 13 分部）：雲端與軟體分部營收＝雲端（IaaS＋SaaS）＋軟體（授權＋支援） | O11: FY2026 58.530、Q1 FY27 17.157（10-K／10-Q 分部表）
A12: 分部：Hardware | B12: =B8 -> 0.728 | C12: =C8 -> 0.703 | D12: =D8 -> 0.85 | E12: =E8 -> 0.67 | F12: =F8 -> 0.776 | G12: =G8 -> 0.714 | H12: =H8 -> 0.924 | I12: =I8 -> 0.774 | ... L12: =L8 -> 3.084 | M12: Derived | N12: Oracle FY2026 10-K（2026-06-22；附註 13 分部）
A13: 分部：Services | B13: =B9 -> 1.33 | C13: =C9 -> 1.291 | D13: =D9 -> 1.348 | E13: =E9 -> 1.349 | F13: =F9 -> 1.428 | G13: =G9 -> 1.443 | H13: =H9 -> 1.523 | I13: =I9 -> 1.414 | ... L13: =L9 -> 5.743 | M13: Derived | N13: Oracle FY2026 10-K（2026-06-22；附註 13 分部）
A14: 檢查：營收線合計 − 合併營收（應為 0） | B14: =SUM(B4:B9)-B10 -> 0 | C14: =SUM(C4:C9)-C10 -> 0 | D14: =SUM(D4:D9)-D10 -> 0 | E14: =SUM(E4:E9)-E10 -> 0 | F14: =SUM(F4:F9)-F10 -> 0 | G14: =SUM(G4:G9)-G10 -> 0 | H14: =SUM(H4:H9)-H10 -> 0 | I14: =SUM(I4:I9)-I10 -> 0 | ... L14: =SUM(L4:L9)-L10 -> 0 | M14: — | N14: —
A15: 檢查：分部合計 − 合併營收（應為 0） | B15: =SUM(B11:B13)-B10 -> 0 | C15: =SUM(C11:C13)-C10 -> 0 | D15: =SUM(D11:D13)-D10 -> 0 | E15: =SUM(E11:E13)-E10 -> 0 | F15: =SUM(F11:F13)-F10 -> 0 | G15: =SUM(G11:G13)-G10 -> 0 | H15: =SUM(H11:H13)-H10 -> 0 | I15: =SUM(I11:I13)-I10 -> 0 | ... L15: =SUM(L11:L13)-L10 -> 0 | M15: — | N15: —
A16: 分部利潤：Cloud and software | E16: 7.691 | I16: 9.358 | J16: 28.514 | K16: 30.93 | L16: 34.468 | M16: Verified（年度）／Interested-party（季度） | N16: 10-K 附註 13（年度）；10-Q 附註 9（Q1 FY27 與去年同季） | O16: 分部利潤只含直接成本，不含研發、管理、無形資產攤銷、重組、SBC、利息。FY25 Q2–Q4、FY26 Q2–Q4 季度分部利潤：未找到（10-Q 在本環境無法開啟）
A17: 分部利潤：Hardware | I17: 0.452 | J17: 1.915 | K17: 1.918 | L17: 2.017 | M17: Verified（年度）／Interested-party（季度） | N17: 10-K 附註 13（年度）；10-Q 附註 9（Q1 FY27 與去年同季） | O17: 季度（除 Q1 FY27）：未找到
A18: 分部利潤：Services | I18: 0.445 | J18: 0.916 | K18: 0.993 | L18: 1.533 | M18: Verified（年度）／Interested-party（季度） | N18: 10-K 附註 13（年度）；10-Q 附註 9（Q1 FY27 與去年同季） | O18: 季度（除 Q1 FY27）：未找到
A19: 分部利潤合計 | I19: =SUM(I16:I18) -> 10.255 | J19: =SUM(J16:J18) -> 31.345 | K19: =SUM(K16:K18) -> 33.841 | L19: =SUM(L16:L18) -> 38.018 | M19: Derived | N19: —
A20: 未分攤費用（＝分部利潤合計 − 營業利益） | I20: =I19-I21 -> 3.527 | J20: =J19-J21 -> 15.992 | K20: =K19-K21 -> 16.163 | L20: =L19-L21 -> 17.412 | M20: Derived | N20: — | O20: 研發、管理、無形資產攤銷、重組、SBC、收購相關等
A21: 營業利益（GAAP） | B21: 4.22 | C21: 4.358 | D21: 5.109 | E21: 4.277 | F21: 4.731 | G21: 5.464 | H21: 6.133 | I21: 6.728 | J21: 15.353 | K21: 17.678 | L21: 20.606 | M21: Verified（年度）／Interested-party（季度） | N21: 公司財報新聞稿（8-K 附件 99.1，各季）；FY2024–FY2026＝10-K
A22: 檢查：分部利潤三項合計 − 公司揭露分部利潤合計（FY2026 38.018，應為 0） | L22: =L19-L51 -> 0 | M22: — | N22: Oracle FY2026 10-K（2026-06-22；附註 13 分部）
A23: 營業利益（非 GAAP） | B23: 6.096 | C23: 6.195 | D23: 7.035 | E23: 6.236 | F23: 6.721 | G23: 7.378 | H23: 8.59 | I23: 8.151 | K23: 25.033 | L23: 28.926 | M23: Interested-party | N23: 公司財報新聞稿（8-K 附件 99.1，各季）；FY2024–FY2026＝10-K
A24: 折舊與攤銷（D&A） | B24: 1.499 | C24: 1.551 | D24: 1.696 | E24: 1.771 | F24: 2.11 | G24: 2.566 | H24: 2.847 | I24: 3.358 | J24: 6.139 | K24: 6.174 | L24: 9.294 | M24: Verified（年度）／Interested-party（季度） | N24: 公司財報新聞稿（8-K 附件 99.1，各季）；FY2024–FY2026＝10-K
A25: 股份基礎給付（SBC） | B25: 1.17 | C25: 1.198 | D25: 1.3 | E25: 1.124 | F25: 1.156 | G25: 1.328 | H25: 1.203 | I25: 1.127 | J25: 3.974 | K25: 4.674 | L25: 4.811 | M25: Verified（年度）／Interested-party（季度） | N25: 公司財報新聞稿（8-K 附件 99.1，各季）；FY2024–FY2026＝10-K
A26: 利息費用 | B26: 0.866 | C26: 0.892 | D26: 0.978 | E26: 0.923 | F26: 1.057 | G26: 1.18 | H26: 1.438 | I26: 1.428 | J26: 3.514 | K26: 3.578 | L26: 4.599 | M26: Verified（年度）／Interested-party（季度） | N26: 公司財報新聞稿（8-K 附件 99.1，各季）；FY2024–FY2026＝10-K
A27: 淨利（GAAP） | B27: 3.151 | C27: 2.936 | D27: 3.427 | E27: 2.927 | F27: 6.135 | G27: 3.721 | H27: 4.304 | I27: 4.76 | J27: 10.467 | K27: 12.443 | L27: 17.087 | M27: Verified（年度）／Interested-party（季度） | N27: 公司財報新聞稿（8-K 附件 99.1，各季）；FY2024–FY2026＝10-K
A28: 營運現金流 | B28: 1.304 | C28: 5.933 | D28: 6.157 | E28: 8.14 | F28: 2.066 | G28: 7.151 | H28: 14.62 | I28: 23.103 | J28: 18.673 | K28: 20.821 | L28: 31.977 | M28: Verified（年度）／Interested-party（季度） | N28: 公司財報新聞稿（8-K 附件 99.1，各季）；FY2024–FY2026＝10-K
A29: 資本支出（現金） | B29: 3.97 | C29: 5.862 | D29: 9.08 | E29: 8.502 | F29: 12.033 | G29: 18.635 | H29: 16.493 | I29: 28.499 | J29: 6.866 | K29: 21.215 | L29: 55.663 | M29: Verified（年度）／Interested-party（季度） | N29: 公司財報新聞稿（8-K 附件 99.1，各季）；FY2024–FY2026＝10-K
A30: 自由現金流（營運現金流 − 資本支出） | B30: =B28-B29 -> -2.666 | C30: =C28-C29 -> 0.071 | D30: =D28-D29 -> -2.923 | E30: =E28-E29 -> -0.362 | F30: =F28-F29 -> -9.967 | G30: =G28-G29 -> -11.484 | H30: =H28-H29 -> -1.873 | I30: =I28-I29 -> -5.396 | ... L30: =L28-L29 -> -23.686 | M30: Derived | N30: —
A31: 股利支付（普通股＋特別股） | I31: 1.565 | J31: 4.391 | K31: 4.743 | L31: 5.787 | M31: Verified（年度）／Interested-party（季度） | N31: 公司財報新聞稿（8-K 附件 99.1，各季）；FY2024–FY2026＝10-K | O31: 季度（除 Q1 FY27）：未找到（只取得年度與 Q1）
A32: 買回普通股 | I32: 0 | J32: 1.202 | K32: 0.6 | L32: 0.095 | M32: Verified（年度）／Interested-party（季度） | N32: 公司財報新聞稿（8-K 附件 99.1，各季）；FY2024–FY2026＝10-K | O32: 季度（除 Q1 FY27）：未找到
A33: 檢查：自由現金流 − 公司揭露值（應為 0） | B33: =B30--2.666 -> 0 | C33: =C30-0.071 -> -2.6367797e-16 | D33: =D30--2.923 -> 0 | E33: =E30--0.362 -> 0 | F33: =F30--9.967 -> 0 | G33: =G30--11.484 -> 0 | H33: =H30--1.873 -> 0 | I33: =I30--5.396 -> 0 | J33: =J30-11.807 -> 0 | K33: =K30--0.394 -> 1.6653345e-15 | L33: =L30--23.686 -> 0 | M33: — | N33: —
A35: 近四季年增率（FY26Q2–FY27Q1 合計 ÷ FY25Q2–FY26Q1 合計 − 1；Seg 頁 FY2027 起點；沿用 v0.3.1 g0 方法）
A36: Cloud Infrastructure（OCI）：近四季年增 | B36: =SUM(F4:I4)/SUM(B4:E4)-1 -> 0.93752188 | M36: Derived
A37: Cloud Applications（SaaS）：近四季年增 | B37: =SUM(F5:I5)/SUM(B5:E5)-1 -> 0.1111187 | M37: Derived
A38: Software license：近四季年增 | B38: =SUM(F6:I6)/SUM(B6:E6)-1 -> -0.092603492 | M38: Derived
A39: Software support：近四季年增 | B39: =SUM(F7:I7)/SUM(B7:E7)-1 -> 0.008323971 | M39: Derived
A40: Hardware：近四季年增 | B40: =SUM(F8:I8)/SUM(B8:E8)-1 -> 0.080311759 | M40: Derived
A41: Services：近四季年增 | B41: =SUM(F9:I9)/SUM(B9:E9)-1 -> 0.092139902 | M41: Derived
A43: 利潤率對照
A44: Cloud and software 分部利潤率 | E44: =E16/E11 -> 0.59587821 | I44: =I16/I11 -> 0.54543335 | J44: =J16/J11 -> 0.64128284 | K44: =K16/K11 -> 0.62827544 | L44: =L16/L11 -> 0.58889458
A45: FY2024 Cloud and software 分部利潤率（AI 規模化前；In 頁 m_sw 的對照） | B45: =J16/J11 -> 0.64128284
A47: 其他實績（PL 頁引用）
A48: 特別股股利 | I48: 0.081 | L48: 0.103 | M48: Verified（年度）／Interested-party（季度） | N48: 公司財報新聞稿（8-K 附件 99.1，各季）；FY2024–FY2026＝10-K | O48: FY2026 特別股股利 103（損益表）；Q1 FY27 81
A49: 稀釋加權股數（十億股） | I49: 3 | J49: 2.823 | K49: 2.866 | L49: 2.914 | M49: Verified（年度）／Interested-party（季度） | N49: 公司財報新聞稿（8-K 附件 99.1，各季）；FY2024–FY2026＝10-K
A50: 稀釋 EPS（GAAP，美元） | I50: 1.56 | J50: 3.71 | K50: 4.34 | L50: 5.83 | M50: Verified（年度）／Interested-party（季度） | N50: 公司財報新聞稿（8-K 附件 99.1，各季）；FY2024–FY2026＝10-K
A51: 公司揭露分部利潤合計 | L51: 38.018 | M51: Verified（年度）／Interested-party（季度） | N51: 公司財報新聞稿（8-K 附件 99.1，各季）；FY2024–FY2026＝10-K | O51: 10-K 附註 13（oracle/data/oracle_facts_20261007.json seg.total.margin.fy2026）

Sheet Thesis
A1: Thesis — 命題模組：OCI 的已簽約 backlog（RPO 664B，OpenAI／Stargate 集中）能否以高於資金成本的報酬轉成營收與現金。只驅動 Cloud Infrastructure 營收線的「OCI AI 算力」子列；AI 資本支出接到 AI 折舊與分部利潤
A2: 已連網 MW（期末）＝MIN(合約上限, 前期＋併網速度 × 期間)；計費 MW＝（平均在役 − 延誤月數 ÷ 12 × 期間新增速度）× 計費比例；每 MW 年收入＝在役世代加權 IF_HoldEcon × k；營運費用＝在役 MW × IF_OpexGW；租金＝未起租 288B 依 11 季起租、17 年直線；折舊＝Q1 在役基數＋在建工程＋新資本支出 ÷ 6 年（當年半年）
A3: 項目 | B3: 單位 | C3: FY27 Q1（估計） | D3: FY27 Q2–Q4（模型） | E3: FY2027 | F3: FY2028 | G3: FY2029 | H3: FY2030 | I3: FY2031 | J3: FY2032 | K3: 說明
A4: 情境 A（樂觀：依公司時程交付、不延誤）
A5: 期間長度 | B5: 年 | C5: 0.25 | D5: 0.75 | E5: 1 | F5: 1 | G5: 1 | H5: 1 | I5: 1 | J5: 1
A6: 已連網 AI MW-IT（期末） | B6: MW | C6: =mw_q1 -> 2543 | D6: =MIN(cap_A,mw_q1+pace_A*D5) -> 5042.75 | E6: =D6 -> 5042.75 | F6: =MIN(cap_A,E6+pace_A*F5) -> 8375.75 | G6: =MIN(cap_A,F6+pace_A*G5) -> 8778 | H6: =G6+MAX(0,MIN(cap_A,G6+pace_A)-G6)+(tp_g*G6-MAX(0,MIN(cap_A,G6+pace_A)-G6))*1/3 -> 8865.78 | I6: =H6+MAX(0,MIN(cap_A,H6+pace_A)-H6)+(tp_g*H6-MAX(0,MIN(cap_A,H6+pace_A)-H6))*2/3 -> 9043.0956 | J6: =I6+MAX(0,MIN(cap_A,I6+pace_A)-I6)+(tp_g*I6-MAX(0,MIN(cap_A,I6+pace_A)-I6))*3/3 -> 9314.3885 | K6: FY2028–29：MIN(上限 cap_A, 前期＋速度)；FY2030–32：新增量線性收斂到「前期 × 永續成長 g」（修正一 F5；超過已簽上限的部分視為新簽約）
A7: 期間新增已連網 MW | B7: MW | C7: =C6-mw_fy26 -> 708 | D7: =D6-C6 -> 2499.75 | E7: =E6-mw_fy26 -> 3207.75 | F7: =F6-E6 -> 3333 | G7: =G6-F6 -> 402.25 | H7: =H6-G6 -> 87.78 | I7: =I6-H6 -> 177.3156 | J7: =J6-I6 -> 271.29287
A8: 平均已連網 MW | B8: MW | C8: =(mw_fy26+C6)/2 -> 2189 | D8: =(C6+D6)/2 -> 3792.875 | E8: =(C8*C5+D8*D5)/E5 -> 3391.9062 | F8: =(E6+F6)/2 -> 6709.25 | G8: =(F6+G6)/2 -> 8576.875 | H8: =(G6+H6)/2 -> 8821.89 | I8: =(H6+I6)/2 -> 8954.4378 | J8: =(I6+J6)/2 -> 9178.742
A9: 延誤後平均在役 MW（Q1 為實績期，不延誤） | B9: MW | C9: =C8 -> 2189 | D9: =MAX(0,D8-delay_A/12*D7/D5) -> 3792.875 | E9: =(C9*C5+D9*D5)/E5 -> 3391.9062 | F9: =MAX(0,F8-delay_A/12*F7/F5) -> 6709.25 | G9: =MAX(0,G8-delay_A/12*G7/G5) -> 8576.875 | H9: =MAX(0,H8-delay_A/12*H7/H5) -> 8821.89 | I9: =MAX(0,I8-delay_A/12*I7/I5) -> 8954.4378 | J9: =MAX(0,J8-delay_A/12*J7/J5) -> 9178.742 | K9: 延誤月數：In 頁 delay_A
A10: 計費 MW（× 計費比例） | B10: MW | C10: =C9*u_bill -> 2079.55 | D10: =D9*u_bill -> 3603.2312 | E10: =E9*u_bill -> 3222.3109 | F10: =F9*u_bill -> 6373.7875 | G10: =G9*u_bill -> 8148.0312 | H10: =H9*u_bill -> 8380.7955 | I10: =I9*u_bill -> 8506.7159 | J10: =J9*u_bill -> 8719.8049
A11: 世代存量（期末，MW）：Q1 末依 In 頁占比；新增依 In 頁新增組合；汰換換成 VR200
A12: Hopper H100 | B12: MW | C12: =C6*om_h100 -> 508.6 | D12: =C12 -> 508.6 | E12: =D12 -> 508.6 | F12: =E12 -> 508.6 | G12: =F12 -> 508.6 | H12: =G12-C12*rf_h100_30 -> 254.3 | I12: =H12-C12*rf_h100_31 -> 0 | J12: =I12 -> 0
A13: GB200 NVL72 | B13: MW | C13: =C6*om_gb200 -> 1398.65 | D13: =C13 -> 1398.65 | E13: =D13 -> 1398.65 | F13: =E13 -> 1398.65 | G13: =F13 -> 1398.65 | H13: =G13 -> 1398.65 | I13: =H13 -> 1398.65 | J13: =I13-C13*rf_gb200_32 -> 0
A14: GB300 NVL72 | B14: MW | C14: =C6*om_gb300 -> 635.75 | D14: =C14+D7*nm27_gb300 -> 3135.5 | E14: =D14 -> 3135.5 | F14: =E14+F7*nm28_gb300 -> 4802 | G14: =F14+G7*nm29_gb300 -> 4802 | H14: =G14+H7*nm29_gb300 -> 4802 | I14: =H14+I7*nm29_gb300 -> 4802 | J14: =I14+J7*nm29_gb300 -> 4802
A15: VR200 NVL72 | B15: MW | C15: =0 -> 0 | D15: =C15+D7*(1-nm27_gb300) -> 0 | E15: =D15 -> 0 | F15: =E15+F7*(1-nm28_gb300) -> 1666.5 | G15: =F15+G7*(1-nm29_gb300) -> 2068.75 | H15: =G15+H7*(1-nm29_gb300)+C12*rf_h100_30 -> 2410.83 | I15: =H15+I7*(1-nm29_gb300)+C12*rf_h100_31 -> 2842.4456 | J15: =I15+J7*(1-nm29_gb300)+C13*rf_gb200_32 -> 4512.3885
A16: 檢查：世代存量合計 − 已連網 MW（應為 0） | B16: MW | C16: =SUM(C12:C15)-C6 -> 0 | D16: =SUM(D12:D15)-D6 -> 0 | E16: =SUM(E12:E15)-E6 -> 0 | F16: =SUM(F12:F15)-F6 -> 0 | G16: =SUM(G12:G15)-G6 -> 0 | H16: =SUM(H12:H15)-H6 -> 0 | I16: =SUM(I12:I15)-I6 -> 0 | J16: =SUM(J12:J15)-J6 -> 0
A17: 每 MW 錨：在役世代加權 IF_HoldEcon | B17: US$M／MW·年 | C17: =om_h100*he_h100+om_gb200*he_gb200+om_gb300*he_gb300 -> 9.51773 | D17: =((C12+D12)*he_h100+(C13+D13)*he_gb200+(C14+D14)*he_gb300+(C15+D15)*he_vr200)/(C6+D6) -> 9.968751 | E17: =(C17*C10*C5+D17*D10*D5)/(C10*C5+D10*D5) -> 9.8959833 | F17: =((E12+F12)*he_h100+(E13+F13)*he_gb200+(E14+F14)*he_gb300+(E15+F15)*he_vr200)/(E6+F6) -> 10.533943 | G17: =((F12+G12)*he_h100+(F13+G13)*he_gb200+(F14+G14)*he_gb300+(F15+G15)*he_vr200)/(F6+G6) -> 10.772187 | H17: =((G12+H12)*he_h100+(G13+H13)*he_gb200+(G14+H14)*he_gb300+(G15+H15)*he_vr200)/(G6+H6) -> 10.848906 | I17: =((H12+I12)*he_h100+(H13+I13)*he_gb200+(H14+I14)*he_gb300+(H15+I15)*he_vr200)/(H6+I6) -> 10.940917 | J17: =((I12+J12)*he_h100+(I13+J13)*he_gb200+(I14+J14)*he_gb300+(I15+J15)*he_vr200)/(I6+J6) -> 11.26609 | K17: 期初＋期末存量平均加權（Tokenomics v21.4 基準成本）
A18: 每 MW 年收入（錨 × k × k 調整） | B18: US$M／MW·年 | C18: =C17*k_mix*k_adj -> 9.3723584 | D18: =D17*k_mix*k_adj -> 9.8164907 | E18: =E17*k_mix*k_adj -> 9.7448344 | F18: =F17*k_mix*k_adj -> 10.37305 | G18: =G17*k_mix*k_adj -> 10.607655 | H18: =H17*k_mix*k_adj -> 10.683202 | I18: =I17*k_mix*k_adj -> 10.773808 | J18: =J17*k_mix*k_adj -> 11.094015 | K18: k：In 頁 k_mix
A19: OCI AI 算力營收（命題子列） | B19: US$B | C19: =C10*C18*C5/1000 -> 4.872572 | D19: =D10*D18*D5/1000 -> 26.528314 | E19: =C19+D19 -> 31.400886 | F19: =F10*F18*F5/1000 -> 66.115616 | G19: =G10*G18*G5/1000 -> 86.431505 | H19: =H10*H18*H5/1000 -> 89.533734 | I19: =I10*I18*I5/1000 -> 91.649727 | J19: =J10*J18*J5/1000 -> 96.737643 | K19: Q1 為估計（Q1 實際 OCI 7.388 的 AI 部分；其餘為非 AI 殘差）
A20: 每 MW 年營運費用：在役世代加權 IF_OpexGW | B20: US$M／MW·年 | C20: =om_h100*ox_h100+om_gb200*ox_gb200+om_gb300*ox_gb300 -> 1.8693 | D20: =((C12+D12)*ox_h100+(C13+D13)*ox_gb200+(C14+D14)*ox_gb300+(C15+D15)*ox_vr200)/(C6+D6) -> 1.906636 | E20: =(C20*C9*C5+D20*D9*D5)/(C9*C5+D9*D5) -> 1.9006122 | F20: =((E12+F12)*ox_h100+(E13+F13)*ox_gb200+(E14+F14)*ox_gb300+(E15+F15)*ox_vr200)/(E6+F6) -> 1.9534292 | G20: =((F12+G12)*ox_h100+(F13+G13)*ox_gb200+(F14+G14)*ox_gb300+(F15+G15)*ox_vr200)/(F6+G6) -> 1.9731557 | H20: =((G12+H12)*ox_h100+(G13+H13)*ox_gb200+(G14+H14)*ox_gb300+(G15+H15)*ox_vr200)/(G6+H6) -> 1.9795076 | I20: =((H12+I12)*ox_h100+(H13+I13)*ox_gb200+(H14+I14)*ox_gb300+(H15+I15)*ox_vr200)/(H6+I6) -> 1.9871247 | J20: =((I12+J12)*ox_h100+(I13+J13)*ox_gb200+(I14+J14)*ox_gb300+(I15+J15)*ox_vr200)/(I6+J6) -> 2.0140488
A21: AI 營運費用（電費、維護、人員、稅與保險；不含折舊、租金） | B21: US$B | C21: =C9*C20*C5/1000 -> 1.0229744 | D21: =D9*D20*D5/1000 -> 5.4237241 | E21: =C21+D21 -> 6.4466985 | F21: =F9*F20*F5/1000 -> 13.106045 | G21: =G9*G20*G5/1000 -> 16.92351 | H21: =H9*H20*H5/1000 -> 17.462998 | I21: =I9*I20*I5/1000 -> 17.793585 | J21: =J9*J20*J5/1000 -> 18.486435 | K21: 延誤後在役 MW × 每 MW 營運費用
A22: AI 機房租金（未起租 288B 依序起租＋超過已簽範圍的新租約） | B22: US$B | C22: =0 -> 0 | D22: =lease_unc/lease_term*IF(lease_q0<=lease_q,(lease_q0)*((lease_q0)+1)/2,lease_q*(lease_q+1)/2+((lease_q0)-lease_q)*lease_q)/(lease_q*4) -> 2.3101604 | E22: =D22 -> 2.3101604 | F22: =lease_unc/lease_term*(IF(lease_q0+4*1<=lease_q,(lease_q0+4*1)*((lease_q0+4*1)+1)/2,lease_q*(lease_q+1)/2+((lease_q0+4*1)-lease_q)*lease_q)-IF(lease_q0+4*0<=lease_q,(lease_q0+4*0)*((lease_q0+4*0)+1)/2,lease_q*(lease_q+1)/2+((lease_q0+4*0)-lease_q)*lease_q))/(lease_q*4)+MAX(0,F8-cap_B)*lease_unc/lease_term/(cap_B-mw_q1) -> 8.4705882 | G22: =lease_unc/lease_term*(IF(lease_q0+4*2<=lease_q,(lease_q0+4*2)*((lease_q0+4*2)+1)/2,lease_q*(lease_q+1)/2+((lease_q0+4*2)-lease_q)*lease_q)-IF(lease_q0+4*1<=lease_q,(lease_q0+4*1)*((lease_q0+4*1)+1)/2,lease_q*(lease_q+1)/2+((lease_q0+4*1)-lease_q)*lease_q))/(lease_q*4)+MAX(0,G8-cap_B)*lease_unc/lease_term/(cap_B-mw_q1) -> 14.631016 | H22: =lease_unc/lease_term*(IF(lease_q0+4*3<=lease_q,(lease_q0+4*3)*((lease_q0+4*3)+1)/2,lease_q*(lease_q+1)/2+((lease_q0+4*3)-lease_q)*lease_q)-IF(lease_q0+4*2<=lease_q,(lease_q0+4*2)*((lease_q0+4*2)+1)/2,lease_q*(lease_q+1)/2+((lease_q0+4*2)-lease_q)*lease_q))/(lease_q*4)+MAX(0,H8-cap_B)*lease_unc/lease_term/(cap_B-mw_q1) -> 17.06043 | I22: =lease_unc/lease_term*(IF(lease_q0+4*4<=lease_q,(lease_q0+4*4)*((lease_q0+4*4)+1)/2,lease_q*(lease_q+1)/2+((lease_q0+4*4)-lease_q)*lease_q)-IF(lease_q0+4*3<=lease_q,(lease_q0+4*3)*((lease_q0+4*3)+1)/2,lease_q*(lease_q+1)/2+((lease_q0+4*3)-lease_q)*lease_q))/(lease_q*4)+MAX(0,I8-cap_B)*lease_unc/lease_term/(cap_B-mw_q1) -> 17.420577 | J22: =lease_unc/lease_term*(IF(lease_q0+4*5<=lease_q,(lease_q0+4*5)*((lease_q0+4*5)+1)/2,lease_q*(lease_q+1)/2+((lease_q0+4*5)-lease_q)*lease_q)-IF(lease_q0+4*4<=lease_q,(lease_q0+4*4)*((lease_q0+4*4)+1)/2,lease_q*(lease_q+1)/2+((lease_q0+4*4)-lease_q)*lease_q))/(lease_q*4)+MAX(0,J8-cap_B)*lease_unc/lease_term/(cap_B-mw_q1) -> 18.030036 | K22: lease_q 季平均起租（第 j 季已起租 MIN(j, lease_q)／lease_q）、lease_term 年直線；平均在役超過 cap_B 的部分以同一每 MW 租金加計（修正一）
A23: AI 成長型資本支出（FY27＝指引中點 − 非 AI；其後＝新增 MW × IF_CapexIT，λ 提前付款） | B23: US$B | C23: =capex_q1-nonai_cx*(q1_rev-C19) -> 27.341206 | D23: =E23-C23 -> 60.18958 | E23: =capex_g27-nonai_cx*(Seg!D28-E19) -> 87.530786 | F23: =(F7*(1-lam)*(nm28_gb300*cx_gb300+(1-nm28_gb300)*cx_vr200)+G7*lam*(nm29_gb300*cx_gb300+(1-nm29_gb300)*cx_vr200))/1000 -> 80.926364 | G23: =(G7*(1-lam)*(nm29_gb300*cx_gb300+(1-nm29_gb300)*cx_vr200)+H7*lam*(nm29_gb300*cx_gb300+(1-nm29_gb300)*cx_vr200))/1000 -> 10.982201 | H23: =(H7*(1-lam)*(nm29_gb300*cx_gb300+(1-nm29_gb300)*cx_vr200)+I7*lam*(nm29_gb300*cx_gb300+(1-nm29_gb300)*cx_vr200))/1000 -> 4.4771965 | I23: =(I7*(1-lam)*(nm29_gb300*cx_gb300+(1-nm29_gb300)*cx_vr200)+J7*lam*(nm29_gb300*cx_gb300+(1-nm29_gb300)*cx_vr200))/1000 -> 7.9009486 | J23: =(J7*(1-lam)*(nm29_gb300*cx_gb300+(1-nm29_gb300)*cx_vr200)+J7*(1+tp_g)*lam*(nm29_gb300*cx_gb300+(1-nm29_gb300)*cx_vr200))/1000 -> 10.30399 | K23: FY2027：In 頁 capex_g27（三情境相同）
A24: AI 汰換資本支出（依世代年份，換成 VR200） | B24: US$B | C24: =0 -> 0 | D24: =0 -> 0 | E24: =0 -> 0 | F24: =0 -> 0 | G24: =0 -> 0 | H24: =C12*rf_h100_30*cx_vr200/1000 -> 9.5582215 | I24: =C12*rf_h100_31*cx_vr200/1000 -> 9.5582215 | J24: =C13*rf_gb200_32*cx_vr200/1000 -> 52.570218
A25: AI 資本支出合計 | B25: US$B | C25: =C23+C24 -> 27.341206 | D25: =D23+D24 -> 60.18958 | E25: =E23+E24 -> 87.530786 | F25: =F23+F24 -> 80.926364 | G25: =G23+G24 -> 10.982201 | H25: =H23+H24 -> 14.035418 | I25: =I23+I24 -> 17.45917 | J25: =J23+J24 -> 62.874208
A26: Q1 在役 AI 設備折舊（年率；扣汰換世代） | B26: US$B／年 | C26: =(dep_q1-nonai_dep_q)*4 -> 9.671 | D26: =(dep_q1-nonai_dep_q)*4 -> 9.671 | E26: =(dep_q1-nonai_dep_q)*4 -> 9.671 | F26: =(dep_q1-nonai_dep_q)*4 -> 9.671 | G26: =(dep_q1-nonai_dep_q)*4 -> 9.671 | H26: =MAX(0,(dep_q1-nonai_dep_q)*4-rf_h100_30*C12*cx_h100/life_ai/1000) -> 8.505026 | I26: =MAX(0,(dep_q1-nonai_dep_q)*4-(rf_h100_30+rf_h100_31)*C12*cx_h100/life_ai/1000) -> 7.339052 | J26: =MAX(0,(dep_q1-nonai_dep_q)*4-(rf_h100_30+rf_h100_31)*C12*cx_h100/life_ai/1000-rf_gb200_32*C13*cx_gb200/life_ai/1000) -> 1.7409088 | K26: Q1 折舊 3.2 − 非 AI 折舊（FY2024 水準）；汰換世代的舊折舊扣除
A27: AI 折舊（進分部利潤與營業利益） | B27: US$B | C27: =C26*C5 -> 2.41775 | D27: =D26*D5+(cip_q1+D25)/life_ai*D5/2 -> 14.049224 | E27: =C27+D27 -> 16.466974 | F27: =F26+(cip_q1+D25)/life_ai+F25/life_ai/2 -> 34.53746 | G27: =G26+(cip_q1+D25+F25)/life_ai+G25/life_ai/2 -> 42.196508 | H27: =H26+(cip_q1+D25+F25+G25)/life_ai+H25/life_ai/2 -> 43.115335 | I27: =I26+(cip_q1+D25+F25+G25+H25)/life_ai+I25/life_ai/2 -> 44.57391 | J27: =J26+(cip_q1+D25+F25+G25+H25+I25)/life_ai+J25/life_ai/2 -> 45.670215 | K27: 在建工程 48.5 與 FY27 Q2–Q4 起的資本支出 ÷ 6 年，當年半年
A28: OCI AI EBITDA（租金後） | B28: US$B | C28: =C19-C21-C22 -> 3.8495976 | D28: =D19-D21-D22 -> 18.79443 | E28: =E19-E21-E22 -> 22.644028 | F28: =F19-F21-F22 -> 44.538983 | G28: =G19-G21-G22 -> 54.876979 | H28: =H19-H21-H22 -> 55.010306 | I28: =I19-I21-I22 -> 56.435565 | J28: =J19-J21-J22 -> 60.221172
A29: OCI AI 分部利潤貢獻（營業利益口徑） | B29: US$B | C29: =C28-C27 -> 1.4318476 | D29: =D28-D27 -> 4.7452062 | E29: =E28-E27 -> 6.1770538 | F29: =F28-F27 -> 10.001523 | G29: =G28-G27 -> 12.680471 | H29: =H28-H27 -> 11.89497 | I29: =I28-I27 -> 11.861655 | J29: =J28-J27 -> 14.550957 | K29: 進 PL 頁 Cloud and software 分部利潤
A30: OCI AI 營業利益率 | B30: % | C30: =IF(C19=0,0,C29/C19) -> 0.29385868 | D30: =IF(D19=0,0,D29/D19) -> 0.17887326 | E30: =IF(E19=0,0,E29/E19) -> 0.1967159 | F30: =IF(F19=0,0,F29/F19) -> 0.15127323 | G30: =IF(G19=0,0,G29/G19) -> 0.14671122 | H30: =IF(H19=0,0,H29/H19) -> 0.13285462 | I30: =IF(I19=0,0,I29/I19) -> 0.12942379 | J30: =IF(J19=0,0,J29/J19) -> 0.1504167
A31: OCI 其他（非 AI）營收（子列） | B31: US$B | C31: =q1_oci-C19 -> 2.515428 | D31: =C31*((1+gna0)^0.25+(1+gna0)^0.5+(1+gna0)^0.75) -> 8.2722657 | E31: =C31+D31 -> 10.787694 | F31: =E31*(1+F32) -> 12.686328 | G31: =F31*(1+G32) -> 14.61465 | H31: =G31*(1+H32) -> 16.485325 | I31: =H31*(1+I32) -> 18.199799 | J31: =I31*(1+J32) -> 19.655782 | K31: Q1＝實際 OCI − 命題 AI 估計（殘差）；之後依成長路徑
A32: OCI 其他年增 | B32: % | F32: =gna0+(gnaLT-gna0)*1/5 -> 0.176 | G32: =gna0+(gnaLT-gna0)*2/5 -> 0.152 | H32: =gna0+(gnaLT-gna0)*3/5 -> 0.128 | I32: =gna0+(gnaLT-gna0)*4/5 -> 0.104 | J32: =gna0+(gnaLT-gna0)*5/5 -> 0.08
A33: Cloud Infrastructure（OCI）營收 | B33: US$B | C33: =C19+C31 -> 7.388 | D33: =D19+D31 -> 34.80058 | E33: =E19+E31 -> 42.18858 | F33: =F19+F31 -> 78.801944 | G33: =G19+G31 -> 101.04615 | H33: =H19+H31 -> 106.01906 | I33: =I19+I31 -> 109.84953 | J33: =J19+J31 -> 116.39343
A34: OCI（含非 AI）營業利益率（非 AI 以 m_sw 計） | B34: % | C34: =(C29+(m_sw+m_adj)*C31)/C33 -> 0.41348819 | D34: =(D29+(m_sw+m_adj)*D31)/D33 -> 0.28972601 | E34: =(E29+(m_sw+m_adj)*E31)/E33 -> 0.31139906 | F34: =(F29+(m_sw+m_adj)*F31)/F33 -> 0.23079366 | G34: =(G29+(m_sw+m_adj)*G31)/G33 -> 0.21881217 | H34: =(H29+(m_sw+m_adj)*H31)/H33 -> 0.21252427 | I34: =(I29+(m_sw+m_adj)*I31)/I33 -> 0.21488049 | J34: =(J29+(m_sw+m_adj)*J31)/J33 -> 0.23397585
A35: OCI AI 稅後營業利益 | B35: US$B | C35: =C29*(1-etr) -> 1.2156386 | D35: =D29*(1-etr) -> 4.0286801 | E35: =E29*(1-etr) -> 5.2443187 | F35: =F29*(1-etr) -> 8.4912929 | G35: =G29*(1-etr) -> 10.76572 | H35: =H29*(1-etr) -> 10.09883 | I35: =I29*(1-etr) -> 10.070545 | J35: =J29*(1-etr) -> 12.353763
A36: AI 累計投入資本（毛額，期末） | B36: US$B | C36: =(dep_q1-nonai_dep_q)*4*life_ai -> 58.026 | D36: =C36+cip_q1 -> 106.572 | E36: =D36+D25 -> 166.76158 | F36: =E36+F25 -> 247.68794 | G36: =F36+G25 -> 258.67015 | H36: =G36+H25 -> 272.70556 | I36: =H36+I25 -> 290.16473 | J36: =I36+J25 -> 353.03894 | K36: Q1 在役基數（年折舊 × 6）＋在建工程＋其後資本支出；機房以租賃取得不計
A37: AI 增量 ROIC（稅後營業利益 ÷ 期初投入資本毛額） | B37: % | F37: =F35/E36 -> 0.05091876 | G37: =G35/F36 -> 0.043464854 | H37: =H35/G36 -> 0.039041343 | I37: =I35/H36 -> 0.036928272 | J37: =J35/I36 -> 0.042574997 | K37: 對照 Val 頁 WACC
A39: 情境 B（基準：依 FY27Q1 交付速度、延誤 3 個月）
A40: 期間長度 | B40: 年 | C40: 0.25 | D40: 0.75 | E40: 1 | F40: 1 | G40: 1 | H40: 1 | I40: 1 | J40: 1
A41: 已連網 AI MW-IT（期末） | B41: MW | C41: =mw_q1 -> 2543 | D41: =MIN(cap_B,mw_q1+pace_B*D40) -> 4667.75 | E41: =D41 -> 4667.75 | F41: =MIN(cap_B,E41+pace_B*F40) -> 7500.75 | G41: =MIN(cap_B,F41+pace_B*G40) -> 8778 | H41: =G41+MAX(0,MIN(cap_B,G41+pace_B)-G41)+(tp_g*G41-MAX(0,MIN(cap_B,G41+pace_B)-G41))*1/3 -> 8865.78 | I41: =H41+MAX(0,MIN(cap_B,H41+pace_B)-H41)+(tp_g*H41-MAX(0,MIN(cap_B,H41+pace_B)-H41))*2/3 -> 9043.0956 | J41: =I41+MAX(0,MIN(cap_B,I41+pace_B)-I41)+(tp_g*I41-MAX(0,MIN(cap_B,I41+pace_B)-I41))*3/3 -> 9314.3885 | K41: FY2028–29：MIN(上限 cap_B, 前期＋速度)；FY2030–32：新增量線性收斂到「前期 × 永續成長 g」（修正一 F5；超過已簽上限的部分視為新簽約）
A42: 期間新增已連網 MW | B42: MW | C42: =C41-mw_fy26 -> 708 | D42: =D41-C41 -> 2124.75 | E42: =E41-mw_fy26 -> 2832.75 | F42: =F41-E41 -> 2833 | G42: =G41-F41 -> 1277.25 | H42: =H41-G41 -> 87.78 | I42: =I41-H41 -> 177.3156 | J42: =J41-I41 -> 271.29287
A43: 平均已連網 MW | B43: MW | C43: =(mw_fy26+C41)/2 -> 2189 | D43: =(C41+D41)/2 -> 3605.375 | E43: =(C43*C40+D43*D40)/E40 -> 3251.2812 | F43: =(E41+F41)/2 -> 6084.25 | G43: =(F41+G41)/2 -> 8139.375 | H43: =(G41+H41)/2 -> 8821.89 | I43: =(H41+I41)/2 -> 8954.4378 | J43: =(I41+J41)/2 -> 9178.742
A44: 延誤後平均在役 MW（Q1 為實績期，不延誤） | B44: MW | C44: =C43 -> 2189 | D44: =MAX(0,D43-delay_B/12*D42/D40) -> 2897.125 | E44: =(C44*C40+D44*D40)/E40 -> 2720.0938 | F44: =MAX(0,F43-delay_B/12*F42/F40) -> 5376 | G44: =MAX(0,G43-delay_B/12*G42/G40) -> 7820.0625 | H44: =MAX(0,H43-delay_B/12*H42/H40) -> 8799.945 | I44: =MAX(0,I43-delay_B/12*I42/I40) -> 8910.1089 | J44: =MAX(0,J43-delay_B/12*J42/J40) -> 9110.9188 | K44: 延誤月數：In 頁 delay_B
A45: 計費 MW（× 計費比例） | B45: MW | C45: =C44*u_bill -> 2079.55 | D45: =D44*u_bill -> 2752.2688 | E45: =E44*u_bill -> 2584.0891 | F45: =F44*u_bill -> 5107.2 | G45: =G44*u_bill -> 7429.0594 | H45: =H44*u_bill -> 8359.9477 | I45: =I44*u_bill -> 8464.6035 | J45: =J44*u_bill -> 8655.3729
A46: 世代存量（期末，MW）：Q1 末依 In 頁占比；新增依 In 頁新增組合；汰換換成 VR200
A47: Hopper H100 | B47: MW | C47: =C41*om_h100 -> 508.6 | D47: =C47 -> 508.6 | E47: =D47 -> 508.6 | F47: =E47 -> 508.6 | G47: =F47 -> 508.6 | H47: =G47-C47*rf_h100_30 -> 254.3 | I47: =H47-C47*rf_h100_31 -> 0 | J47: =I47 -> 0
A48: GB200 NVL72 | B48: MW | C48: =C41*om_gb200 -> 1398.65 | D48: =C48 -> 1398.65 | E48: =D48 -> 1398.65 | F48: =E48 -> 1398.65 | G48: =F48 -> 1398.65 | H48: =G48 -> 1398.65 | I48: =H48 -> 1398.65 | J48: =I48-C48*rf_gb200_32 -> 0
A49: GB300 NVL72 | B49: MW | C49: =C41*om_gb300 -> 635.75 | D49: =C49+D42*nm27_gb300 -> 2760.5 | E49: =D49 -> 2760.5 | F49: =E49+F42*nm28_gb300 -> 4177 | G49: =F49+G42*nm29_gb300 -> 4177 | H49: =G49+H42*nm29_gb300 -> 4177 | I49: =H49+I42*nm29_gb300 -> 4177 | J49: =I49+J42*nm29_gb300 -> 4177
A50: VR200 NVL72 | B50: MW | C50: =0 -> 0 | D50: =C50+D42*(1-nm27_gb300) -> 0 | E50: =D50 -> 0 | F50: =E50+F42*(1-nm28_gb300) -> 1416.5 | G50: =F50+G42*(1-nm29_gb300) -> 2693.75 | H50: =G50+H42*(1-nm29_gb300)+C47*rf_h100_30 -> 3035.83 | I50: =H50+I42*(1-nm29_gb300)+C47*rf_h100_31 -> 3467.4456 | J50: =I50+J42*(1-nm29_gb300)+C48*rf_gb200_32 -> 5137.3885
A51: 檢查：世代存量合計 − 已連網 MW（應為 0） | B51: MW | C51: =SUM(C47:C50)-C41 -> 0 | D51: =SUM(D47:D50)-D41 -> 0 | E51: =SUM(E47:E50)-E41 -> 0 | F51: =SUM(F47:F50)-F41 -> 0 | G51: =SUM(G47:G50)-G41 -> 0 | H51: =SUM(H47:H50)-H41 -> 0 | I51: =SUM(I47:I50)-I41 -> 0 | J51: =SUM(J47:J50)-J41 -> 0
A52: 每 MW 錨：在役世代加權 IF_HoldEcon | B52: US$M／MW·年 | C52: =om_h100*he_h100+om_gb200*he_gb200+om_gb300*he_gb300 -> 9.51773 | D52: =((C47+D47)*he_h100+(C48+D48)*he_gb200+(C49+D49)*he_gb300+(C50+D50)*he_vr200)/(C41+D41) -> 9.9210281 | E52: =(C52*C45*C40+D52*D45*D40)/(C45*C40+D45*D40) -> 9.8398894 | F52: =((E47+F47)*he_h100+(E48+F48)*he_gb200+(E49+F49)*he_gb300+(E50+F50)*he_vr200)/(E41+F41) -> 10.470225 | G52: =((F47+G47)*he_h100+(F48+G48)*he_gb200+(F49+G49)*he_gb300+(F50+G50)*he_vr200)/(F41+G41) -> 10.796896 | H52: =((G47+H47)*he_h100+(G48+H48)*he_gb200+(G49+H49)*he_gb300+(G50+H50)*he_vr200)/(G41+H41) -> 10.943776 | I52: =((H47+I47)*he_h100+(H48+I48)*he_gb200+(H49+I49)*he_gb300+(H50+I50)*he_vr200)/(H41+I41) -> 11.034384 | J52: =((I47+J47)*he_h100+(I48+J48)*he_gb200+(I49+J49)*he_gb300+(I50+J50)*he_vr200)/(I41+J41) -> 11.357272 | K52: 期初＋期末存量平均加權（Tokenomics v21.4 基準成本）
A53: 每 MW 年收入（錨 × k × k 調整） | B53: US$M／MW·年 | C53: =C52*k_mix*k_adj -> 9.3723584 | D53: =D52*k_mix*k_adj -> 9.7694966 | E53: =E52*k_mix*k_adj -> 9.6895972 | F53: =F52*k_mix*k_adj -> 10.310306 | G53: =G52*k_mix*k_adj -> 10.631986 | H53: =H52*k_mix*k_adj -> 10.776624 | I53: =I52*k_mix*k_adj -> 10.865847 | J53: =J52*k_mix*k_adj -> 11.183804 | K53: k：In 頁 k_mix
A54: OCI AI 算力營收（命題子列） | B54: US$B | C54: =C45*C53*C40/1000 -> 4.872572 | D54: =D45*D53*D40/1000 -> 20.16621 | E54: =C54+D54 -> 25.038782 | F54: =F45*F53*F40/1000 -> 52.656793 | G54: =G45*G53*G40/1000 -> 78.985658 | H54: =H45*H53*H40/1000 -> 90.092012 | I54: =I45*I53*I40/1000 -> 91.975086 | J54: =J45*J53*J40/1000 -> 96.799994 | K54: Q1 為估計（Q1 實際 OCI 7.388 的 AI 部分；其餘為非 AI 殘差）
A55: 每 MW 年營運費用：在役世代加權 IF_OpexGW | B55: US$M／MW·年 | C55: =om_h100*ox_h100+om_gb200*ox_gb200+om_gb300*ox_gb300 -> 1.8693 | D55: =((C47+D47)*ox_h100+(C48+D48)*ox_gb200+(C49+D49)*ox_gb300+(C50+D50)*ox_vr200)/(C41+D41) -> 1.9026855 | E55: =(C55*C44*C40+D55*D44*D40)/(C44*C40+D44*D40) -> 1.8959687 | F55: =((E47+F47)*ox_h100+(E48+F48)*ox_gb200+(E49+F49)*ox_gb300+(E50+F50)*ox_vr200)/(E41+F41) -> 1.9481542 | G55: =((F47+G47)*ox_h100+(F48+G48)*ox_gb200+(F49+G49)*ox_gb300+(F50+G50)*ox_vr200)/(F41+G41) -> 1.9752028 | H55: =((G47+H47)*ox_h100+(G48+H48)*ox_gb200+(G49+H49)*ox_gb300+(G50+H50)*ox_vr200)/(G41+H41) -> 1.9873644 | I55: =((H47+I47)*ox_h100+(H48+I48)*ox_gb200+(H49+I49)*ox_gb300+(H50+I50)*ox_vr200)/(H41+I41) -> 1.9948653 | J55: =((I47+J47)*ox_h100+(I48+J48)*ox_gb200+(I49+J49)*ox_gb300+(I50+J50)*ox_vr200)/(I41+J41) -> 2.0216002
A56: AI 營運費用（電費、維護、人員、稅與保險；不含折舊、租金） | B56: US$B | C56: =C44*C55*C40/1000 -> 1.0229744 | D56: =D44*D55*D40/1000 -> 4.1342382 | E56: =C56+D56 -> 5.1572126 | F56: =F44*F55*F40/1000 -> 10.473277 | G56: =G44*G55*G40/1000 -> 15.446209 | H56: =H44*H55*H40/1000 -> 17.488698 | I56: =I44*I55*I40/1000 -> 17.774467 | J56: =J44*J55*J40/1000 -> 18.418636 | K56: 延誤後在役 MW × 每 MW 營運費用
A57: AI 機房租金（未起租 288B 依序起租＋超過已簽範圍的新租約） | B57: US$B | C57: =0 -> 0 | D57: =lease_unc/lease_term*IF(lease_q0<=lease_q,(lease_q0)*((lease_q0)+1)/2,lease_q*(lease_q+1)/2+((lease_q0)-lease_q)*lease_q)/(lease_q*4) -> 2.3101604 | E57: =D57 -> 2.3101604 | F57: =lease_unc/lease_term*(IF(lease_q0+4*1<=lease_q,(lease_q0+4*1)*((lease_q0+4*1)+1)/2,lease_q*(lease_q+1)/2+((lease_q0+4*1)-lease_q)*lease_q)-IF(lease_q0+4*0<=lease_q,(lease_q0+4*0)*((lease_q0+4*0)+1)/2,lease_q*(lease_q+1)/2+((lease_q0+4*0)-lease_q)*lease_q))/(lease_q*4)+MAX(0,F43-cap_B)*lease_unc/lease_term/(cap_B-mw_q1) -> 8.4705882 | G57: =lease_unc/lease_term*(IF(lease_q0+4*2<=lease_q,(lease_q0+4*2)*((lease_q0+4*2)+1)/2,lease_q*(lease_q+1)/2+((lease_q0+4*2)-lease_q)*lease_q)-IF(lease_q0+4*1<=lease_q,(lease_q0+4*1)*((lease_q0+4*1)+1)/2,lease_q*(lease_q+1)/2+((lease_q0+4*1)-lease_q)*lease_q))/(lease_q*4)+MAX(0,G43-cap_B)*lease_unc/lease_term/(cap_B-mw_q1) -> 14.631016 | H57: =lease_unc/lease_term*(IF(lease_q0+4*3<=lease_q,(lease_q0+4*3)*((lease_q0+4*3)+1)/2,lease_q*(lease_q+1)/2+((lease_q0+4*3)-lease_q)*lease_q)-IF(lease_q0+4*2<=lease_q,(lease_q0+4*2)*((lease_q0+4*2)+1)/2,lease_q*(lease_q+1)/2+((lease_q0+4*2)-lease_q)*lease_q))/(lease_q*4)+MAX(0,H43-cap_B)*lease_unc/lease_term/(cap_B-mw_q1) -> 17.06043 | I57: =lease_unc/lease_term*(IF(lease_q0+4*4<=lease_q,(lease_q0+4*4)*((lease_q0+4*4)+1)/2,lease_q*(lease_q+1)/2+((lease_q0+4*4)-lease_q)*lease_q)-IF(lease_q0+4*3<=lease_q,(lease_q0+4*3)*((lease_q0+4*3)+1)/2,lease_q*(lease_q+1)/2+((lease_q0+4*3)-lease_q)*lease_q))/(lease_q*4)+MAX(0,I43-cap_B)*lease_unc/lease_term/(cap_B-mw_q1) -> 17.420577 | J57: =lease_unc/lease_term*(IF(lease_q0+4*5<=lease_q,(lease_q0+4*5)*((lease_q0+4*5)+1)/2,lease_q*(lease_q+1)/2+((lease_q0+4*5)-lease_q)*lease_q)-IF(lease_q0+4*4<=lease_q,(lease_q0+4*4)*((lease_q0+4*4)+1)/2,lease_q*(lease_q+1)/2+((lease_q0+4*4)-lease_q)*lease_q))/(lease_q*4)+MAX(0,J43-cap_B)*lease_unc/lease_term/(cap_B-mw_q1) -> 18.030036 | K57: lease_q 季平均起租（第 j 季已起租 MIN(j, lease_q)／lease_q）、lease_term 年直線；平均在役超過 cap_B 的部分以同一每 MW 租金加計（修正一）
A58: AI 成長型資本支出（FY27＝指引中點 − 非 AI；其後＝新增 MW × IF_CapexIT，λ 提前付款） | B58: US$B | C58: =capex_q1-nonai_cx*(q1_rev-C54) -> 27.341206 | D58: =E58-C58 -> 60.18958 | E58: =capex_g27-nonai_cx*(Seg!D46-E54) -> 87.530786 | F58: =(F42*(1-lam)*(nm28_gb300*cx_gb300+(1-nm28_gb300)*cx_vr200)+G42*lam*(nm29_gb300*cx_gb300+(1-nm29_gb300)*cx_vr200))/1000 -> 81.090864 | G58: =(G42*(1-lam)*(nm29_gb300*cx_gb300+(1-nm29_gb300)*cx_vr200)+H42*lam*(nm29_gb300*cx_gb300+(1-nm29_gb300)*cx_vr200))/1000 -> 32.359466 | H58: =(H42*(1-lam)*(nm29_gb300*cx_gb300+(1-nm29_gb300)*cx_vr200)+I42*lam*(nm29_gb300*cx_gb300+(1-nm29_gb300)*cx_vr200))/1000 -> 4.4771965 | I58: =(I42*(1-lam)*(nm29_gb300*cx_gb300+(1-nm29_gb300)*cx_vr200)+J42*lam*(nm29_gb300*cx_gb300+(1-nm29_gb300)*cx_vr200))/1000 -> 7.9009486 | J58: =(J42*(1-lam)*(nm29_gb300*cx_gb300+(1-nm29_gb300)*cx_vr200)+J42*(1+tp_g)*lam*(nm29_gb300*cx_gb300+(1-nm29_gb300)*cx_vr200))/1000 -> 10.30399 | K58: FY2027：In 頁 capex_g27（三情境相同）
A59: AI 汰換資本支出（依世代年份，換成 VR200） | B59: US$B | C59: =0 -> 0 | D59: =0 -> 0 | E59: =0 -> 0 | F59: =0 -> 0 | G59: =0 -> 0 | H59: =C47*rf_h100_30*cx_vr200/1000 -> 9.5582215 | I59: =C47*rf_h100_31*cx_vr200/1000 -> 9.5582215 | J59: =C48*rf_gb200_32*cx_vr200/1000 -> 52.570218
A60: AI 資本支出合計 | B60: US$B | C60: =C58+C59 -> 27.341206 | D60: =D58+D59 -> 60.18958 | E60: =E58+E59 -> 87.530786 | F60: =F58+F59 -> 81.090864 | G60: =G58+G59 -> 32.359466 | H60: =H58+H59 -> 14.035418 | I60: =I58+I59 -> 17.45917 | J60: =J58+J59 -> 62.874208
A61: Q1 在役 AI 設備折舊（年率；扣汰換世代） | B61: US$B／年 | C61: =(dep_q1-nonai_dep_q)*4 -> 9.671 | D61: =(dep_q1-nonai_dep_q)*4 -> 9.671 | E61: =(dep_q1-nonai_dep_q)*4 -> 9.671 | F61: =(dep_q1-nonai_dep_q)*4 -> 9.671 | G61: =(dep_q1-nonai_dep_q)*4 -> 9.671 | H61: =MAX(0,(dep_q1-nonai_dep_q)*4-rf_h100_30*C47*cx_h100/life_ai/1000) -> 8.505026 | I61: =MAX(0,(dep_q1-nonai_dep_q)*4-(rf_h100_30+rf_h100_31)*C47*cx_h100/life_ai/1000) -> 7.339052 | J61: =MAX(0,(dep_q1-nonai_dep_q)*4-(rf_h100_30+rf_h100_31)*C47*cx_h100/life_ai/1000-rf_gb200_32*C48*cx_gb200/life_ai/1000) -> 1.7409088 | K61: Q1 折舊 3.2 − 非 AI 折舊（FY2024 水準）；汰換世代的舊折舊扣除
A62: AI 折舊（進分部利潤與營業利益） | B62: US$B | C62: =C61*C40 -> 2.41775 | D62: =D61*D40+(cip_q1+D60)/life_ai*D40/2 -> 14.049224 | E62: =C62+D62 -> 16.466974 | F62: =F61+(cip_q1+D60)/life_ai+F60/life_ai/2 -> 34.551169 | G62: =G61+(cip_q1+D60+F60)/life_ai+G60/life_ai/2 -> 44.005363 | H62: =H61+(cip_q1+D60+F60+G60)/life_ai+H60/life_ai/2 -> 46.705629 | I62: =I61+(cip_q1+D60+F60+G60+H60)/life_ai+I60/life_ai/2 -> 48.164204 | J62: =J61+(cip_q1+D60+F60+G60+H60+I60)/life_ai+J60/life_ai/2 -> 49.260509 | K62: 在建工程 48.5 與 FY27 Q2–Q4 起的資本支出 ÷ 6 年，當年半年
A63: OCI AI EBITDA（租金後） | B63: US$B | C63: =C54-C56-C57 -> 3.8495976 | D63: =D54-D56-D57 -> 13.721812 | E63: =E54-E56-E57 -> 17.571409 | F63: =F54-F56-F57 -> 33.712928 | G63: =G54-G56-G57 -> 48.908432 | H63: =H54-H56-H57 -> 55.542884 | I63: =I54-I56-I57 -> 56.780042 | J63: =J54-J56-J57 -> 60.351322
A64: OCI AI 分部利潤貢獻（營業利益口徑） | B64: US$B | C64: =C63-C62 -> 1.4318476 | D64: =D63-D62 -> -0.32741221 | E64: =E63-E62 -> 1.1044354 | F64: =F63-F62 -> -0.83824086 | G64: =G63-G62 -> 4.9030695 | H64: =H63-H62 -> 8.8372546 | I64: =I63-I62 -> 8.6158379 | J64: =J63-J62 -> 11.090813 | K64: 進 PL 頁 Cloud and software 分部利潤
A65: OCI AI 營業利益率 | B65: % | C65: =IF(C54=0,0,C64/C54) -> 0.29385868 | D65: =IF(D54=0,0,D64/D54) -> -0.016235684 | E65: =IF(E54=0,0,E64/E54) -> 0.044108989 | F65: =IF(F54=0,0,F64/F54) -> -0.01591895 | G65: =IF(G54=0,0,G64/G54) -> 0.06207544 | H65: =IF(H54=0,0,H64/H54) -> 0.098091434 | I65: =IF(I54=0,0,I64/I54) -> 0.093675779 | J65: =IF(J54=0,0,J64/J54) -> 0.11457452
A66: OCI 其他（非 AI）營收（子列） | B66: US$B | C66: =q1_oci-C54 -> 2.515428 | D66: =C66*((1+gna0)^0.25+(1+gna0)^0.5+(1+gna0)^0.75) -> 8.2722657 | E66: =C66+D66 -> 10.787694 | F66: =E66*(1+F67) -> 12.686328 | G66: =F66*(1+G67) -> 14.61465 | H66: =G66*(1+H67) -> 16.485325 | I66: =H66*(1+I67) -> 18.199799 | J66: =I66*(1+J67) -> 19.655782 | K66: Q1＝實際 OCI − 命題 AI 估計（殘差）；之後依成長路徑
A67: OCI 其他年增 | B67: % | F67: =gna0+(gnaLT-gna0)*1/5 -> 0.176 | G67: =gna0+(gnaLT-gna0)*2/5 -> 0.152 | H67: =gna0+(gnaLT-gna0)*3/5 -> 0.128 | I67: =gna0+(gnaLT-gna0)*4/5 -> 0.104 | J67: =gna0+(gnaLT-gna0)*5/5 -> 0.08
A68: Cloud Infrastructure（OCI）營收 | B68: US$B | C68: =C54+C66 -> 7.388 | D68: =D54+D66 -> 28.438476 | E68: =E54+E66 -> 35.826476 | F68: =F54+F66 -> 65.343121 | G68: =G54+G66 -> 93.600308 | H68: =H54+H66 -> 106.57734 | I68: =I54+I66 -> 110.17489 | J68: =J54+J66 -> 116.45578
A69: OCI（含非 AI）營業利益率（非 AI 以 m_sw 計） | B69: % | C69: =(C64+(m_sw+m_adj)*C66)/C68 -> 0.41348819 | D69: =(D64+(m_sw+m_adj)*D66)/D68 -> 0.1761703 | E69: =(E64+(m_sw+m_adj)*E66)/E68 -> 0.2251091 | F69: =(F64+(m_sw+m_adj)*F66)/F68 -> 0.11244068 | G69: =(G64+(m_sw+m_adj)*G66)/G68 -> 0.15312691 | H69: =(H64+(m_sw+m_adj)*H66)/H68 -> 0.18272091 | I69: =(I64+(m_sw+m_adj)*I66)/I68 -> 0.18478533 | J69: =(J64+(m_sw+m_adj)*J66)/J68 -> 0.2041385
A70: OCI AI 稅後營業利益 | B70: US$B | C70: =C64*(1-etr) -> 1.2156386 | D70: =D64*(1-etr) -> -0.27797297 | E70: =E64*(1-etr) -> 0.93766562 | F70: =F64*(1-etr) -> -0.71166649 | G70: =G64*(1-etr) -> 4.162706 | H70: =H64*(1-etr) -> 7.5028292 | I70: =I64*(1-etr) -> 7.3148464 | J70: =J64*(1-etr) -> 9.4161002
A71: AI 累計投入資本（毛額，期末） | B71: US$B | C71: =(dep_q1-nonai_dep_q)*4*life_ai -> 58.026 | D71: =C71+cip_q1 -> 106.572 | E71: =D71+D60 -> 166.76158 | F71: =E71+F60 -> 247.85244 | G71: =F71+G60 -> 280.21191 | H71: =G71+H60 -> 294.24733 | I71: =H71+I60 -> 311.7065 | J71: =I71+J60 -> 374.58071 | K71: Q1 在役基數（年折舊 × 6）＋在建工程＋其後資本支出；機房以租賃取得不計
A72: AI 增量 ROIC（稅後營業利益 ÷ 期初投入資本毛額） | B72: % | F72: =F70/E71 -> -0.0042675686 | G72: =G70/F71 -> 0.016795097 | H72: =H70/G71 -> 0.026775554 | I72: =I70/H71 -> 0.024859517 | J72: =J70/I71 -> 0.030208225 | K72: 對照 Val 頁 WACC
A74: 情境 C（保守：OpenAI 相關容量實現 60%、延誤 6 個月）
A75: 期間長度 | B75: 年 | C75: 0.25 | D75: 0.75 | E75: 1 | F75: 1 | G75: 1 | H75: 1 | I75: 1 | J75: 1
A76: 已連網 AI MW-IT（期末） | B76: MW | C76: =mw_q1 -> 2543 | D76: =MIN(cap_C,mw_q1+pace_C*D75) -> 3293 | E76: =D76 -> 3293 | F76: =MIN(cap_C,E76+pace_C*F75) -> 4293 | G76: =MIN(cap_C,F76+pace_C*G75) -> 5293 | H76: =G76+MAX(0,MIN(cap_C,G76+pace_C)-G76)+(tp_g*G76-MAX(0,MIN(cap_C,G76+pace_C)-G76))*1/3 -> 6006.5967 | I76: =H76+MAX(0,MIN(cap_C,H76+pace_C)-H76)+(tp_g*H76-MAX(0,MIN(cap_C,H76+pace_C)-H76))*2/3 -> 6219.1964 | J76: =I76+MAX(0,MIN(cap_C,I76+pace_C)-I76)+(tp_g*I76-MAX(0,MIN(cap_C,I76+pace_C)-I76))*3/3 -> 6405.7723 | K76: FY2028–29：MIN(上限 cap_C, 前期＋速度)；FY2030–32：新增量線性收斂到「前期 × 永續成長 g」（修正一 F5；超過已簽上限的部分視為新簽約）
A77: 期間新增已連網 MW | B77: MW | C77: =C76-mw_fy26 -> 708 | D77: =D76-C76 -> 750 | E77: =E76-mw_fy26 -> 1458 | F77: =F76-E76 -> 1000 | G77: =G76-F76 -> 1000 | H77: =H76-G76 -> 713.59667 | I77: =I76-H76 -> 212.59971 | J77: =J76-I76 -> 186.57589
A78: 平均已連網 MW | B78: MW | C78: =(mw_fy26+C76)/2 -> 2189 | D78: =(C76+D76)/2 -> 2918 | E78: =(C78*C75+D78*D75)/E75 -> 2735.75 | F78: =(E76+F76)/2 -> 3793 | G78: =(F76+G76)/2 -> 4793 | H78: =(G76+H76)/2 -> 5649.7983 | I78: =(H76+I76)/2 -> 6112.8965 | J78: =(I76+J76)/2 -> 6312.4843
A79: 延誤後平均在役 MW（Q1 為實績期，不延誤） | B79: MW | C79: =C78 -> 2189 | D79: =MAX(0,D78-delay_C/12*D77/D75) -> 2418 | E79: =(C79*C75+D79*D75)/E75 -> 2360.75 | F79: =MAX(0,F78-delay_C/12*F77/F75) -> 3293 | G79: =MAX(0,G78-delay_C/12*G77/G75) -> 4293 | H79: =MAX(0,H78-delay_C/12*H77/H75) -> 5293 | I79: =MAX(0,I78-delay_C/12*I77/I75) -> 6006.5967 | J79: =MAX(0,J78-delay_C/12*J77/J75) -> 6219.1964 | K79: 延誤月數：In 頁 delay_C
A80: 計費 MW（× 計費比例） | B80: MW | C80: =C79*u_bill -> 2079.55 | D80: =D79*u_bill -> 2297.1 | E80: =E79*u_bill -> 2242.7125 | F80: =F79*u_bill -> 3128.35 | G80: =G79*u_bill -> 4078.35 | H80: =H79*u_bill -> 5028.35 | I80: =I79*u_bill -> 5706.2668 | J80: =J79*u_bill -> 5908.2366
A81: 世代存量（期末，MW）：Q1 末依 In 頁占比；新增依 In 頁新增組合；汰換換成 VR200
A82: Hopper H100 | B82: MW | C82: =C76*om_h100 -> 508.6 | D82: =C82 -> 508.6 | E82: =D82 -> 508.6 | F82: =E82 -> 508.6 | G82: =F82 -> 508.6 | H82: =G82-C82*rf_h100_30 -> 254.3 | I82: =H82-C82*rf_h100_31 -> 0 | J82: =I82 -> 0
A83: GB200 NVL72 | B83: MW | C83: =C76*om_gb200 -> 1398.65 | D83: =C83 -> 1398.65 | E83: =D83 -> 1398.65 | F83: =E83 -> 1398.65 | G83: =F83 -> 1398.65 | H83: =G83 -> 1398.65 | I83: =H83 -> 1398.65 | J83: =I83-C83*rf_gb200_32 -> 0
A84: GB300 NVL72 | B84: MW | C84: =C76*om_gb300 -> 635.75 | D84: =C84+D77*nm27_gb300 -> 1385.75 | E84: =D84 -> 1385.75 | F84: =E84+F77*nm28_gb300 -> 1885.75 | G84: =F84+G77*nm29_gb300 -> 1885.75 | H84: =G84+H77*nm29_gb300 -> 1885.75 | I84: =H84+I77*nm29_gb300 -> 1885.75 | J84: =I84+J77*nm29_gb300 -> 1885.75
A85: VR200 NVL72 | B85: MW | C85: =0 -> 0 | D85: =C85+D77*(1-nm27_gb300) -> 0 | E85: =D85 -> 0 | F85: =E85+F77*(1-nm28_gb300) -> 500 | G85: =F85+G77*(1-nm29_gb300) -> 1500 | H85: =G85+H77*(1-nm29_gb300)+C82*rf_h100_30 -> 2467.8967 | I85: =H85+I77*(1-nm29_gb300)+C82*rf_h100_31 -> 2934.7964 | J85: =I85+J77*(1-nm29_gb300)+C83*rf_gb200_32 -> 4520.0223
A86: 檢查：世代存量合計 − 已連網 MW（應為 0） | B86: MW | C86: =SUM(C82:C85)-C76 -> 0 | D86: =SUM(D82:D85)-D76 -> 0 | E86: =SUM(E82:E85)-E76 -> 0 | F86: =SUM(F82:F85)-F76 -> 0 | G86: =SUM(G82:G85)-G76 -> 0 | H86: =SUM(H82:H85)-H76 -> 0 | I86: =SUM(I82:I85)-I76 -> 0 | J86: =SUM(J82:J85)-J76 -> 0
A87: 每 MW 錨：在役世代加權 IF_HoldEcon | B87: US$M／MW·年 | C87: =om_h100*he_h100+om_gb200*he_gb200+om_gb300*he_gb300 -> 9.51773 | D87: =((C82+D82)*he_h100+(C83+D83)*he_gb200+(C84+D84)*he_gb300+(C85+D85)*he_vr200)/(C76+D76) -> 9.6936214 | E87: =(C87*C80*C75+D87*D80*D75)/(C80*C75+D80*D75) -> 9.6528477 | F87: =((E82+F82)*he_h100+(E83+F83)*he_gb200+(E84+F84)*he_gb300+(E85+F85)*he_vr200)/(E76+F76) -> 10.057043 | G87: =((F82+G82)*he_h100+(F83+G83)*he_gb200+(F84+G84)*he_gb300+(F85+G85)*he_vr200)/(F76+G76) -> 10.439618 | H87: =((G82+H82)*he_h100+(G83+H83)*he_gb200+(G84+H84)*he_gb300+(G85+H85)*he_vr200)/(G76+H76) -> 10.767216 | I87: =((H82+I82)*he_h100+(H83+I83)*he_gb200+(H84+I84)*he_gb300+(H85+I85)*he_vr200)/(H76+I76) -> 10.982625 | J87: =((I82+J82)*he_h100+(I83+J83)*he_gb200+(I84+J84)*he_gb300+(I85+J85)*he_vr200)/(I76+J76) -> 11.449098 | K87: 期初＋期末存量平均加權（Tokenomics v21.4 基準成本）
A88: 每 MW 年收入（錨 × k × k 調整） | B88: US$M／MW·年 | C88: =C87*k_mix*k_adj -> 9.3723584 | D88: =D87*k_mix*k_adj -> 9.5455634 | E88: =E87*k_mix*k_adj -> 9.5054124 | F88: =F87*k_mix*k_adj -> 9.9034336 | G88: =G87*k_mix*k_adj -> 10.280165 | H88: =H87*k_mix*k_adj -> 10.60276 | I88: =I87*k_mix*k_adj -> 10.814879 | J88: =J87*k_mix*k_adj -> 11.274227 | K88: k：In 頁 k_mix
A89: OCI AI 算力營收（命題子列） | B89: US$B | C89: =C80*C88*C75/1000 -> 4.872572 | D89: =D80*D88*D75/1000 -> 16.445335 | E89: =C89+D89 -> 21.317907 | F89: =F80*F88*F75/1000 -> 30.981407 | G89: =G80*G88*G75/1000 -> 41.926112 | H89: =H80*H88*H75/1000 -> 53.314388 | I89: =I80*I88*I75/1000 -> 61.712587 | J89: =J80*J88*J75/1000 -> 66.610802 | K89: Q1 為估計（Q1 實際 OCI 7.388 的 AI 部分；其餘為非 AI 殘差）
A90: 每 MW 年營運費用：在役世代加權 IF_OpexGW | B90: US$M／MW·年 | C90: =om_h100*ox_h100+om_gb200*ox_gb200+om_gb300*ox_gb300 -> 1.8693 | D90: =((C82+D82)*ox_h100+(C83+D83)*ox_gb200+(C84+D84)*ox_gb300+(C85+D85)*ox_vr200)/(C76+D76) -> 1.8838605 | E90: =(C90*C79*C75+D90*D79*D75)/(C79*C75+D79*D75) -> 1.8804852 | F90: =((E82+F82)*ox_h100+(E83+F83)*ox_gb200+(E84+F84)*ox_gb300+(E85+F85)*ox_vr200)/(E76+F76) -> 1.913948 | G90: =((F82+G82)*ox_h100+(F83+G83)*ox_gb200+(F84+G84)*ox_gb300+(F85+G85)*ox_vr200)/(F76+G76) -> 1.9456248 | H90: =((G82+H82)*ox_h100+(G83+H83)*ox_gb200+(G84+H84)*ox_gb300+(G85+H85)*ox_vr200)/(G76+H76) -> 1.9727494 | I90: =((H82+I82)*ox_h100+(H83+I83)*ox_gb200+(H84+I84)*ox_gb300+(H85+I85)*ox_vr200)/(H76+I76) -> 1.9905833 | J90: =((I82+J82)*ox_h100+(I83+J83)*ox_gb200+(I84+J84)*ox_gb300+(I85+J85)*ox_vr200)/(I76+J76) -> 2.0292068
A91: AI 營運費用（電費、維護、人員、稅與保險；不含折舊、租金） | B91: US$B | C91: =C79*C90*C75/1000 -> 1.0229744 | D91: =D79*D90*D75/1000 -> 3.416381 | E91: =C91+D91 -> 4.4393554 | F91: =F79*F90*F75/1000 -> 6.3026309 | G91: =G79*G90*G75/1000 -> 8.3525675 | H91: =H79*H90*H75/1000 -> 10.441762 | I91: =I79*I90*I75/1000 -> 11.956631 | J91: =J79*J90*J75/1000 -> 12.620036 | K91: 延誤後在役 MW × 每 MW 營運費用
A92: AI 機房租金（未起租 288B 依序起租＋超過已簽範圍的新租約） | B92: US$B | C92: =0 -> 0 | D92: =lease_unc/lease_term*IF(lease_q0<=lease_q,(lease_q0)*((lease_q0)+1)/2,lease_q*(lease_q+1)/2+((lease_q0)-lease_q)*lease_q)/(lease_q*4) -> 2.3101604 | E92: =D92 -> 2.3101604 | F92: =lease_unc/lease_term*(IF(lease_q0+4*1<=lease_q,(lease_q0+4*1)*((lease_q0+4*1)+1)/2,lease_q*(lease_q+1)/2+((lease_q0+4*1)-lease_q)*lease_q)-IF(lease_q0+4*0<=lease_q,(lease_q0+4*0)*((lease_q0+4*0)+1)/2,lease_q*(lease_q+1)/2+((lease_q0+4*0)-lease_q)*lease_q))/(lease_q*4)+MAX(0,F78-cap_B)*lease_unc/lease_term/(cap_B-mw_q1) -> 8.4705882 | G92: =lease_unc/lease_term*(IF(lease_q0+4*2<=lease_q,(lease_q0+4*2)*((lease_q0+4*2)+1)/2,lease_q*(lease_q+1)/2+((lease_q0+4*2)-lease_q)*lease_q)-IF(lease_q0+4*1<=lease_q,(lease_q0+4*1)*((lease_q0+4*1)+1)/2,lease_q*(lease_q+1)/2+((lease_q0+4*1)-lease_q)*lease_q))/(lease_q*4)+MAX(0,G78-cap_B)*lease_unc/lease_term/(cap_B-mw_q1) -> 14.631016 | H92: =lease_unc/lease_term*(IF(lease_q0+4*3<=lease_q,(lease_q0+4*3)*((lease_q0+4*3)+1)/2,lease_q*(lease_q+1)/2+((lease_q0+4*3)-lease_q)*lease_q)-IF(lease_q0+4*2<=lease_q,(lease_q0+4*2)*((lease_q0+4*2)+1)/2,lease_q*(lease_q+1)/2+((lease_q0+4*2)-lease_q)*lease_q))/(lease_q*4)+MAX(0,H78-cap_B)*lease_unc/lease_term/(cap_B-mw_q1) -> 16.941176 | I92: =lease_unc/lease_term*(IF(lease_q0+4*4<=lease_q,(lease_q0+4*4)*((lease_q0+4*4)+1)/2,lease_q*(lease_q+1)/2+((lease_q0+4*4)-lease_q)*lease_q)-IF(lease_q0+4*3<=lease_q,(lease_q0+4*3)*((lease_q0+4*3)+1)/2,lease_q*(lease_q+1)/2+((lease_q0+4*3)-lease_q)*lease_q))/(lease_q*4)+MAX(0,I78-cap_B)*lease_unc/lease_term/(cap_B-mw_q1) -> 16.941176 | J92: =lease_unc/lease_term*(IF(lease_q0+4*5<=lease_q,(lease_q0+4*5)*((lease_q0+4*5)+1)/2,lease_q*(lease_q+1)/2+((lease_q0+4*5)-lease_q)*lease_q)-IF(lease_q0+4*4<=lease_q,(lease_q0+4*4)*((lease_q0+4*4)+1)/2,lease_q*(lease_q+1)/2+((lease_q0+4*4)-lease_q)*lease_q))/(lease_q*4)+MAX(0,J78-cap_B)*lease_unc/lease_term/(cap_B-mw_q1) -> 16.941176 | K92: lease_q 季平均起租（第 j 季已起租 MIN(j, lease_q)／lease_q）、lease_term 年直線；平均在役超過 cap_B 的部分以同一每 MW 租金加計（修正一）
A93: AI 成長型資本支出（FY27＝指引中點 − 非 AI；其後＝新增 MW × IF_CapexIT，λ 提前付款） | B93: US$B | C93: =capex_q1-nonai_cx*(q1_rev-C89) -> 27.341206 | D93: =E93-C93 -> 60.18958 | E93: =capex_g27-nonai_cx*(Seg!D64-E89) -> 87.530786 | F93: =(F77*(1-lam)*(nm28_gb300*cx_gb300+(1-nm28_gb300)*cx_vr200)+G77*lam*(nm29_gb300*cx_gb300+(1-nm29_gb300)*cx_vr200))/1000 -> 35.84791 | G93: =(G77*(1-lam)*(nm29_gb300*cx_gb300+(1-nm29_gb300)*cx_vr200)+H77*lam*(nm29_gb300*cx_gb300+(1-nm29_gb300)*cx_vr200))/1000 -> 33.818695 | H93: =(H77*(1-lam)*(nm29_gb300*cx_gb300+(1-nm29_gb300)*cx_vr200)+I77*lam*(nm29_gb300*cx_gb300+(1-nm29_gb300)*cx_vr200))/1000 -> 20.230795 | I93: =(I77*(1-lam)*(nm29_gb300*cx_gb300+(1-nm29_gb300)*cx_vr200)+J77*lam*(nm29_gb300*cx_gb300+(1-nm29_gb300)*cx_vr200))/1000 -> 7.6485082 | J93: =(J77*(1-lam)*(nm29_gb300*cx_gb300+(1-nm29_gb300)*cx_vr200)+J77*(1+tp_g)*lam*(nm29_gb300*cx_gb300+(1-nm29_gb300)*cx_vr200))/1000 -> 7.0863496 | K93: FY2027：In 頁 capex_g27（三情境相同）
A94: AI 汰換資本支出（依世代年份，換成 VR200） | B94: US$B | C94: =0 -> 0 | D94: =0 -> 0 | E94: =0 -> 0 | F94: =0 -> 0 | G94: =0 -> 0 | H94: =C82*rf_h100_30*cx_vr200/1000 -> 9.5582215 | I94: =C82*rf_h100_31*cx_vr200/1000 -> 9.5582215 | J94: =C83*rf_gb200_32*cx_vr200/1000 -> 52.570218
A95: AI 資本支出合計 | B95: US$B | C95: =C93+C94 -> 27.341206 | D95: =D93+D94 -> 60.18958 | E95: =E93+E94 -> 87.530786 | F95: =F93+F94 -> 35.84791 | G95: =G93+G94 -> 33.818695 | H95: =H93+H94 -> 29.789016 | I95: =I93+I94 -> 17.20673 | J95: =J93+J94 -> 59.656568
A96: Q1 在役 AI 設備折舊（年率；扣汰換世代） | B96: US$B／年 | C96: =(dep_q1-nonai_dep_q)*4 -> 9.671 | D96: =(dep_q1-nonai_dep_q)*4 -> 9.671 | E96: =(dep_q1-nonai_dep_q)*4 -> 9.671 | F96: =(dep_q1-nonai_dep_q)*4 -> 9.671 | G96: =(dep_q1-nonai_dep_q)*4 -> 9.671 | H96: =MAX(0,(dep_q1-nonai_dep_q)*4-rf_h100_30*C82*cx_h100/life_ai/1000) -> 8.505026 | I96: =MAX(0,(dep_q1-nonai_dep_q)*4-(rf_h100_30+rf_h100_31)*C82*cx_h100/life_ai/1000) -> 7.339052 | J96: =MAX(0,(dep_q1-nonai_dep_q)*4-(rf_h100_30+rf_h100_31)*C82*cx_h100/life_ai/1000-rf_gb200_32*C83*cx_gb200/life_ai/1000) -> 1.7409088 | K96: Q1 折舊 3.2 − 非 AI 折舊（FY2024 水準）；汰換世代的舊折舊扣除
A97: AI 折舊（進分部利潤與營業利益） | B97: US$B | C97: =C96*C75 -> 2.41775 | D97: =D96*D75+(cip_q1+D95)/life_ai*D75/2 -> 14.049224 | E97: =C97+D97 -> 16.466974 | F97: =F96+(cip_q1+D95)/life_ai+F95/life_ai/2 -> 30.780923 | G97: =G96+(cip_q1+D95+F95)/life_ai+G95/life_ai/2 -> 36.586473 | H97: =H96+(cip_q1+D95+F95+G95)/life_ai+H95/life_ai/2 -> 40.721142 | I97: =I96+(cip_q1+D95+F95+G95+H95)/life_ai+I95/life_ai/2 -> 43.47148 | J97: =J96+(cip_q1+D95+F95+G95+H95+I95)/life_ai+J95/life_ai/2 -> 44.278611 | K97: 在建工程 48.5 與 FY27 Q2–Q4 起的資本支出 ÷ 6 年，當年半年
A98: OCI AI EBITDA（租金後） | B98: US$B | C98: =C89-C91-C92 -> 3.8495976 | D98: =D89-D91-D92 -> 10.718794 | E98: =E89-E91-E92 -> 14.568391 | F98: =F89-F91-F92 -> 16.208188 | G98: =G89-G91-G92 -> 18.942529 | H98: =H89-H91-H92 -> 25.931449 | I98: =I89-I91-I92 -> 32.814779 | J98: =J89-J91-J92 -> 37.04959
A99: OCI AI 分部利潤貢獻（營業利益口徑） | B99: US$B | C99: =C98-C97 -> 1.4318476 | D99: =D98-D97 -> -3.33043 | E99: =E98-E97 -> -1.8985824 | F99: =F98-F97 -> -14.572735 | G99: =G98-G97 -> -17.643944 | H99: =H98-H97 -> -14.789692 | I99: =I98-I97 -> -10.656701 | J99: =J98-J97 -> -7.2290216 | K99: 進 PL 頁 Cloud and software 分部利潤
A100: OCI AI 營業利益率 | B100: % | C100: =IF(C89=0,0,C99/C89) -> 0.29385868 | D100: =IF(D89=0,0,D99/D89) -> -0.20251518 | E100: =IF(E89=0,0,E99/E89) -> -0.089060452 | F100: =IF(F89=0,0,F99/F89) -> -0.47037035 | G100: =IF(G89=0,0,G99/G89) -> -0.42083425 | H100: =IF(H89=0,0,H99/H89) -> -0.27740527 | I100: =IF(I89=0,0,I99/I89) -> -0.17268278 | J100: =IF(J89=0,0,J99/J89) -> -0.10852627
A101: OCI 其他（非 AI）營收（子列） | B101: US$B | C101: =q1_oci-C89 -> 2.515428 | D101: =C101*((1+gna0)^0.25+(1+gna0)^0.5+(1+gna0)^0.75) -> 8.2722657 | E101: =C101+D101 -> 10.787694 | F101: =E101*(1+F102) -> 12.686328 | G101: =F101*(1+G102) -> 14.61465 | H101: =G101*(1+H102) -> 16.485325 | I101: =H101*(1+I102) -> 18.199799 | J101: =I101*(1+J102) -> 19.655782 | K101: Q1＝實際 OCI − 命題 AI 估計（殘差）；之後依成長路徑
A102: OCI 其他年增 | B102: % | F102: =gna0+(gnaLT-gna0)*1/5 -> 0.176 | G102: =gna0+(gnaLT-gna0)*2/5 -> 0.152 | H102: =gna0+(gnaLT-gna0)*3/5 -> 0.128 | I102: =gna0+(gnaLT-gna0)*4/5 -> 0.104 | J102: =gna0+(gnaLT-gna0)*5/5 -> 0.08
...

Sheet Seg
A1: Seg — 營收分部層：營收線（公司新聞稿）→ 官方報告分部（10-K 附註 13：Cloud and software、Hardware、Services）→ 合併營收。FY2026 為實績（Q 頁）；FY2027＝Q1 實績＋Q2–Q4 模型；延伸到 FY2032
A2: 驅動：OCI AI 算力＝Thesis 頁命題模組；OCI 其他＝成長路徑；SaaS、授權、支援、硬體、服務＝FY2027 為 Q1 實績＋去年 Q2–Q4 ×（1＋近四季年增率），其後線性收斂到 In 頁長期年增（三情境相同）。核對列：子列合計＝母列、分部合計＝合併營收
A3: 項目 | B3: 單位 | C3: FY2026A | D3: FY2027 | E3: FY2028 | F3: FY2029 | G3: FY2030 | H3: FY2031 | I3: FY2032 | J3: 說明
A4: 共同（三情境相同）：OCI 以外的營收線
A5: Cloud Applications（SaaS） | B5: US$B | C5: =a26_saas -> 15.888 | D5: =q1_saas+(a26_saas-q0_saas)*(1+g0_saas) -> 17.606869 | E5: =D5*(1+E6) -> 19.453741 | F5: =E5*(1+F6) -> 21.373265 | G5: =F5*(1+G6) -> 23.34917 | H5: =G5*(1+H6) -> 25.362423 | I5: =H5*(1+I6) -> 27.391417 | J5: FY2027＝Q1 實績＋（FY2026 − FY26Q1）×（1＋近四季年增率 Q 頁）；FY2028 起年增率線性收斂到 In 頁 gLT_saas
A6: Cloud Applications（SaaS） 年增 | B6: % | D6: =D5/C5-1 -> 0.10818663 | E6: =g0_saas+(gLT_saas-g0_saas)*1/5 -> 0.10489496 | F6: =g0_saas+(gLT_saas-g0_saas)*2/5 -> 0.09867122 | G6: =g0_saas+(gLT_saas-g0_saas)*3/5 -> 0.09244748 | H6: =g0_saas+(gLT_saas-g0_saas)*4/5 -> 0.08622374 | I6: =g0_saas+(gLT_saas-g0_saas)*5/5 -> 0.08
A7: Software license | B7: US$B | C7: =a26_lic -> 4.737 | D7: =q1_lic+(a26_lic-q0_lic)*(1+g0_lic) -> 4.2582715 | E7: =D7*(1+E8) -> 3.9257738 | F7: =E7*(1+F8) -> 3.6762434 | G7: =F7*(1+G8) -> 3.4959553 | H7: =G7*(1+H8) -> 3.3752725 | I7: =H7*(1+I8) -> 3.307767 | J7: FY2027＝Q1 實績＋（FY2026 − FY26Q1）×（1＋近四季年增率 Q 頁）；FY2028 起年增率線性收斂到 In 頁 gLT_lic
A8: Software license 年增 | B8: % | D8: =D7/C7-1 -> -0.10106153 | E8: =g0_lic+(gLT_lic-g0_lic)*1/5 -> -0.078082794 | F8: =g0_lic+(gLT_lic-g0_lic)*2/5 -> -0.063562095 | G8: =g0_lic+(gLT_lic-g0_lic)*3/5 -> -0.049041397 | H8: =g0_lic+(gLT_lic-g0_lic)*4/5 -> -0.034520698 | I8: =g0_lic+(gLT_lic-g0_lic)*5/5 -> -0.02
A9: Software support | B9: US$B | C9: =a26_sup -> 19.804 | D9: =q1_sup+(a26_sup-q0_sup)*(1+g0_sup) -> 19.867603 | E9: =D9*(1+E10) -> 19.960169 | F9: =E9*(1+F10) -> 19.980017 | G9: =F9*(1+G10) -> 19.926662 | H9: =G9*(1+H10) -> 19.800423 | I9: =H9*(1+I10) -> 19.602419 | J9: FY2027＝Q1 實績＋（FY2026 − FY26Q1）×（1＋近四季年增率 Q 頁）；FY2028 起年增率線性收斂到 In 頁 gLT_sup
A10: Software support 年增 | B10: % | D10: =D9/C9-1 -> 0.003211606 | E10: =g0_sup+(gLT_sup-g0_sup)*1/5 -> 0.0046591768 | F10: =g0_sup+(gLT_sup-g0_sup)*2/5 -> 0.0009943826 | G10: =g0_sup+(gLT_sup-g0_sup)*3/5 -> -0.0026704116 | H10: =g0_sup+(gLT_sup-g0_sup)*4/5 -> -0.0063352058 | I10: =g0_sup+(gLT_sup-g0_sup)*5/5 -> -0.01
A11: Hardware | B11: US$B | C11: =a26_hw -> 3.084 | D11: =q1_hw+(a26_hw-q0_hw)*(1+g0_hw) -> 3.3818726 | E11: =D11*(1+E12) -> 3.5991559 | F11: =E11*(1+F12) -> 3.7725886 | G11: =F11*(1+G12) -> 3.8937819 | H11: =G11*(1+H12) -> 3.9563252 | I11: =H11*(1+I12) -> 3.9563252 | J11: FY2027＝Q1 實績＋（FY2026 − FY26Q1）×（1＋近四季年增率 Q 頁）；FY2028 起年增率線性收斂到 In 頁 gLT_hw
A12: Hardware 年增 | B12: % | D12: =D11/C11-1 -> 0.096586441 | E12: =g0_hw+(gLT_hw-g0_hw)*1/5 -> 0.064249407 | F12: =g0_hw+(gLT_hw-g0_hw)*2/5 -> 0.048187055 | G12: =g0_hw+(gLT_hw-g0_hw)*3/5 -> 0.032124703 | H12: =g0_hw+(gLT_hw-g0_hw)*4/5 -> 0.016062352 | I12: =g0_hw+(gLT_hw-g0_hw)*5/5 -> 0
A13: Services | B13: US$B | C13: =a26_svc -> 5.743 | D13: =q1_svc+(a26_svc-q0_svc)*(1+g0_svc) -> 6.2128627 | E13: =D13*(1+E14) -> 6.708102 | F13: =E13*(1+F14) -> 7.1594495 | G13: =F13*(1+G14) -> 7.552188 | H13: =G13*(1+H14) -> 7.8726121 | I13: =H13*(1+I14) -> 8.1087904 | J13: FY2027＝Q1 實績＋（FY2026 − FY26Q1）×（1＋近四季年增率 Q 頁）；FY2028 起年增率線性收斂到 In 頁 gLT_svc
A14: Services 年增 | B14: % | D14: =D13/C13-1 -> 0.081814858 | E14: =g0_svc+(gLT_svc-g0_svc)*1/5 -> 0.079711922 | F14: =g0_svc+(gLT_svc-g0_svc)*2/5 -> 0.067283941 | G14: =g0_svc+(gLT_svc-g0_svc)*3/5 -> 0.054855961 | H14: =g0_svc+(gLT_svc-g0_svc)*4/5 -> 0.04242798 | I14: =g0_svc+(gLT_svc-g0_svc)*5/5 -> 0.03
A16: 情境 A（樂觀：依公司時程交付、不延誤）
A17: Cloud Infrastructure（OCI） | B17: US$B | C17: =a26_oci -> 18.101 | D17: =D18+D19 -> 42.18858 | E17: =E18+E19 -> 78.801944 | F17: =F18+F19 -> 101.04615 | G17: =G18+G19 -> 106.01906 | H17: =H18+H19 -> 109.84953 | I17: =I18+I19 -> 116.39343 | J17: FY2026 實績（不拆 AI／非 AI：公司未揭露）
A18: OCI AI 算力（命題子列） | B18: US$B | D18: =Thesis!E19 -> 31.400886 | E18: =Thesis!F19 -> 66.115616 | F18: =Thesis!G19 -> 86.431505 | G18: =Thesis!H19 -> 89.533734 | H18: =Thesis!I19 -> 91.649727 | I18: =Thesis!J19 -> 96.737643 | J18: Thesis 頁命題模組
A19: OCI 其他（非 AI）（子列） | B19: US$B | D19: =Thesis!E31 -> 10.787694 | E19: =Thesis!F31 -> 12.686328 | F19: =Thesis!G31 -> 14.61465 | G19: =Thesis!H31 -> 16.485325 | H19: =Thesis!I31 -> 18.199799 | I19: =Thesis!J31 -> 19.655782
A20: Cloud Applications（SaaS） | B20: US$B | C20: =C5 -> 15.888 | D20: =D5 -> 17.606869 | E20: =E5 -> 19.453741 | F20: =F5 -> 21.373265 | G20: =G5 -> 23.34917 | H20: =H5 -> 25.362423 | I20: =I5 -> 27.391417
A21: Software license | B21: US$B | C21: =C7 -> 4.737 | D21: =D7 -> 4.2582715 | E21: =E7 -> 3.9257738 | F21: =F7 -> 3.6762434 | G21: =G7 -> 3.4959553 | H21: =H7 -> 3.3752725 | I21: =I7 -> 3.307767
A22: Software support | B22: US$B | C22: =C9 -> 19.804 | D22: =D9 -> 19.867603 | E22: =E9 -> 19.960169 | F22: =F9 -> 19.980017 | G22: =G9 -> 19.926662 | H22: =H9 -> 19.800423 | I22: =I9 -> 19.602419
A23: Hardware | B23: US$B | C23: =C11 -> 3.084 | D23: =D11 -> 3.3818726 | E23: =E11 -> 3.5991559 | F23: =F11 -> 3.7725886 | G23: =G11 -> 3.8937819 | H23: =H11 -> 3.9563252 | I23: =I11 -> 3.9563252
A24: Services | B24: US$B | C24: =C13 -> 5.743 | D24: =D13 -> 6.2128627 | E24: =E13 -> 6.708102 | F24: =F13 -> 7.1594495 | G24: =G13 -> 7.552188 | H24: =H13 -> 7.8726121 | I24: =I13 -> 8.1087904
A25: 分部：Cloud and software | B25: US$B | C25: =C17+C20+C21+C22 -> 58.53 | D25: =D17+D20+D21+D22 -> 83.921324 | E25: =E17+E20+E21+E22 -> 122.14163 | F25: =F17+F20+F21+F22 -> 146.07568 | G25: =G17+G20+G21+G22 -> 152.79085 | H25: =H17+H20+H21+H22 -> 158.38764 | I25: =I17+I20+I21+I22 -> 166.69503 | J25: 10-K 官方分部（雲端與軟體）
A26: 分部：Hardware | B26: US$B | C26: =C23 -> 3.084 | D26: =D23 -> 3.3818726 | E26: =E23 -> 3.5991559 | F26: =F23 -> 3.7725886 | G26: =G23 -> 3.8937819 | H26: =H23 -> 3.9563252 | I26: =I23 -> 3.9563252
A27: 分部：Services | B27: US$B | C27: =C24 -> 5.743 | D27: =D24 -> 6.2128627 | E27: =E24 -> 6.708102 | F27: =F24 -> 7.1594495 | G27: =G24 -> 7.552188 | H27: =H24 -> 7.8726121 | I27: =I24 -> 8.1087904
A28: 合併營收 | B28: US$B | C28: =C25+C26+C27 -> 67.357 | D28: =D25+D26+D27 -> 93.516059 | E28: =E25+E26+E27 -> 132.44889 | F28: =F25+F26+F27 -> 157.00772 | G28: =G25+G26+G27 -> 164.23682 | H28: =H25+H26+H27 -> 170.21658 | I28: =I25+I26+I27 -> 178.76014
A29: 合併營收年增 | B29: % | D29: =D28/C28-1 -> 0.38836437 | E29: =E28/D28-1 -> 0.41632237 | F29: =F28/E28-1 -> 0.18542121 | G29: =G28/F28-1 -> 0.046042941 | H29: =H28/G28-1 -> 0.036409407 | I29: =I28/H28-1 -> 0.050192303
A30: 檢查：OCI 子列合計 − OCI（應為 0） | B30: US$B | D30: =D18+D19-D17 -> 0 | E30: =E18+E19-E17 -> 0 | F30: =F18+F19-F17 -> 0 | G30: =G18+G19-G17 -> 0 | H30: =H18+H19-H17 -> 0 | I30: =I18+I19-I17 -> 0
A31: 檢查：營收線合計 − 合併營收（應為 0） | B31: US$B | C31: =C17+C20+C21+C22+C23+C24-C28 -> 0 | D31: =D17+D20+D21+D22+D23+D24-D28 -> 0 | E31: =E17+E20+E21+E22+E23+E24-E28 -> 0 | F31: =F17+F20+F21+F22+F23+F24-F28 -> 0 | G31: =G17+G20+G21+G22+G23+G24-G28 -> 0 | H31: =H17+H20+H21+H22+H23+H24-H28 -> 0 | I31: =I17+I20+I21+I22+I23+I24-I28 -> 0
A32: 檢查：FY2026 合併營收 − 公司揭露（應為 0） | B32: US$B | C32: =C28-a26_rev -> 0
A34: 情境 B（基準：依 FY27Q1 交付速度、延誤 3 個月）
A35: Cloud Infrastructure（OCI） | B35: US$B | C35: =a26_oci -> 18.101 | D35: =D36+D37 -> 35.826476 | E35: =E36+E37 -> 65.343121 | F35: =F36+F37 -> 93.600308 | G35: =G36+G37 -> 106.57734 | H35: =H36+H37 -> 110.17489 | I35: =I36+I37 -> 116.45578 | J35: FY2026 實績（不拆 AI／非 AI：公司未揭露）
A36: OCI AI 算力（命題子列） | B36: US$B | D36: =Thesis!E54 -> 25.038782 | E36: =Thesis!F54 -> 52.656793 | F36: =Thesis!G54 -> 78.985658 | G36: =Thesis!H54 -> 90.092012 | H36: =Thesis!I54 -> 91.975086 | I36: =Thesis!J54 -> 96.799994 | J36: Thesis 頁命題模組
A37: OCI 其他（非 AI）（子列） | B37: US$B | D37: =Thesis!E66 -> 10.787694 | E37: =Thesis!F66 -> 12.686328 | F37: =Thesis!G66 -> 14.61465 | G37: =Thesis!H66 -> 16.485325 | H37: =Thesis!I66 -> 18.199799 | I37: =Thesis!J66 -> 19.655782
A38: Cloud Applications（SaaS） | B38: US$B | C38: =C5 -> 15.888 | D38: =D5 -> 17.606869 | E38: =E5 -> 19.453741 | F38: =F5 -> 21.373265 | G38: =G5 -> 23.34917 | H38: =H5 -> 25.362423 | I38: =I5 -> 27.391417
A39: Software license | B39: US$B | C39: =C7 -> 4.737 | D39: =D7 -> 4.2582715 | E39: =E7 -> 3.9257738 | F39: =F7 -> 3.6762434 | G39: =G7 -> 3.4959553 | H39: =H7 -> 3.3752725 | I39: =I7 -> 3.307767
A40: Software support | B40: US$B | C40: =C9 -> 19.804 | D40: =D9 -> 19.867603 | E40: =E9 -> 19.960169 | F40: =F9 -> 19.980017 | G40: =G9 -> 19.926662 | H40: =H9 -> 19.800423 | I40: =I9 -> 19.602419
A41: Hardware | B41: US$B | C41: =C11 -> 3.084 | D41: =D11 -> 3.3818726 | E41: =E11 -> 3.5991559 | F41: =F11 -> 3.7725886 | G41: =G11 -> 3.8937819 | H41: =H11 -> 3.9563252 | I41: =I11 -> 3.9563252
A42: Services | B42: US$B | C42: =C13 -> 5.743 | D42: =D13 -> 6.2128627 | E42: =E13 -> 6.708102 | F42: =F13 -> 7.1594495 | G42: =G13 -> 7.552188 | H42: =H13 -> 7.8726121 | I42: =I13 -> 8.1087904
A43: 分部：Cloud and software | B43: US$B | C43: =C35+C38+C39+C40 -> 58.53 | D43: =D35+D38+D39+D40 -> 77.559219 | E43: =E35+E38+E39+E40 -> 108.68281 | F43: =F35+F38+F39+F40 -> 138.62983 | G43: =G35+G38+G39+G40 -> 153.34912 | H43: =H35+H38+H39+H40 -> 158.713 | I43: =I35+I38+I39+I40 -> 166.75738 | J43: 10-K 官方分部（雲端與軟體）
A44: 分部：Hardware | B44: US$B | C44: =C41 -> 3.084 | D44: =D41 -> 3.3818726 | E44: =E41 -> 3.5991559 | F44: =F41 -> 3.7725886 | G44: =G41 -> 3.8937819 | H44: =H41 -> 3.9563252 | I44: =I41 -> 3.9563252
A45: 分部：Services | B45: US$B | C45: =C42 -> 5.743 | D45: =D42 -> 6.2128627 | E45: =E42 -> 6.708102 | F45: =F42 -> 7.1594495 | G45: =G42 -> 7.552188 | H45: =H42 -> 7.8726121 | I45: =I42 -> 8.1087904
A46: 合併營收 | B46: US$B | C46: =C43+C44+C45 -> 67.357 | D46: =D43+D44+D45 -> 87.153955 | E46: =E43+E44+E45 -> 118.99006 | F46: =F43+F44+F45 -> 149.56187 | G46: =G43+G44+G45 -> 164.79509 | H46: =H43+H44+H45 -> 170.54194 | I46: =I43+I44+I45 -> 178.82249
A47: 合併營收年增 | B47: % | D47: =D46/C46-1 -> 0.29391087 | E47: =E46/D46-1 -> 0.36528587 | F47: =F46/E46-1 -> 0.25692741 | G47: =G46/F46-1 -> 0.10185231 | H47: =H46/G46-1 -> 0.034872676 | I47: =I46/H46-1 -> 0.048554357
A48: 檢查：OCI 子列合計 − OCI（應為 0） | B48: US$B | D48: =D36+D37-D35 -> 0 | E48: =E36+E37-E35 -> 0 | F48: =F36+F37-F35 -> 0 | G48: =G36+G37-G35 -> 0 | H48: =H36+H37-H35 -> 0 | I48: =I36+I37-I35 -> 0
A49: 檢查：營收線合計 − 合併營收（應為 0） | B49: US$B | C49: =C35+C38+C39+C40+C41+C42-C46 -> 0 | D49: =D35+D38+D39+D40+D41+D42-D46 -> 0 | E49: =E35+E38+E39+E40+E41+E42-E46 -> 0 | F49: =F35+F38+F39+F40+F41+F42-F46 -> 0 | G49: =G35+G38+G39+G40+G41+G42-G46 -> 0 | H49: =H35+H38+H39+H40+H41+H42-H46 -> 0 | I49: =I35+I38+I39+I40+I41+I42-I46 -> 0
A50: 檢查：FY2026 合併營收 − 公司揭露（應為 0） | B50: US$B | C50: =C46-a26_rev -> 0
A52: 情境 C（保守：OpenAI 相關容量實現 60%、延誤 6 個月）
A53: Cloud Infrastructure（OCI） | B53: US$B | C53: =a26_oci -> 18.101 | D53: =D54+D55 -> 32.105601 | E53: =E54+E55 -> 43.667734 | F53: =F54+F55 -> 56.540762 | G53: =G54+G55 -> 69.799713 | H53: =H54+H55 -> 79.912385 | I53: =I54+I55 -> 86.266584 | J53: FY2026 實績（不拆 AI／非 AI：公司未揭露）
A54: OCI AI 算力（命題子列） | B54: US$B | D54: =Thesis!E89 -> 21.317907 | E54: =Thesis!F89 -> 30.981407 | F54: =Thesis!G89 -> 41.926112 | G54: =Thesis!H89 -> 53.314388 | H54: =Thesis!I89 -> 61.712587 | I54: =Thesis!J89 -> 66.610802 | J54: Thesis 頁命題模組
A55: OCI 其他（非 AI）（子列） | B55: US$B | D55: =Thesis!E101 -> 10.787694 | E55: =Thesis!F101 -> 12.686328 | F55: =Thesis!G101 -> 14.61465 | G55: =Thesis!H101 -> 16.485325 | H55: =Thesis!I101 -> 18.199799 | I55: =Thesis!J101 -> 19.655782
A56: Cloud Applications（SaaS） | B56: US$B | C56: =C5 -> 15.888 | D56: =D5 -> 17.606869 | E56: =E5 -> 19.453741 | F56: =F5 -> 21.373265 | G56: =G5 -> 23.34917 | H56: =H5 -> 25.362423 | I56: =I5 -> 27.391417
A57: Software license | B57: US$B | C57: =C7 -> 4.737 | D57: =D7 -> 4.2582715 | E57: =E7 -> 3.9257738 | F57: =F7 -> 3.6762434 | G57: =G7 -> 3.4959553 | H57: =H7 -> 3.3752725 | I57: =I7 -> 3.307767
A58: Software support | B58: US$B | C58: =C9 -> 19.804 | D58: =D9 -> 19.867603 | E58: =E9 -> 19.960169 | F58: =F9 -> 19.980017 | G58: =G9 -> 19.926662 | H58: =H9 -> 19.800423 | I58: =I9 -> 19.602419
A59: Hardware | B59: US$B | C59: =C11 -> 3.084 | D59: =D11 -> 3.3818726 | E59: =E11 -> 3.5991559 | F59: =F11 -> 3.7725886 | G59: =G11 -> 3.8937819 | H59: =H11 -> 3.9563252 | I59: =I11 -> 3.9563252
A60: Services | B60: US$B | C60: =C13 -> 5.743 | D60: =D13 -> 6.2128627 | E60: =E13 -> 6.708102 | F60: =F13 -> 7.1594495 | G60: =G13 -> 7.552188 | H60: =H13 -> 7.8726121 | I60: =I13 -> 8.1087904
A61: 分部：Cloud and software | B61: US$B | C61: =C53+C56+C57+C58 -> 58.53 | D61: =D53+D56+D57+D58 -> 73.838344 | E61: =E53+E56+E57+E58 -> 87.007419 | F61: =F53+F56+F57+F58 -> 101.57029 | G61: =G53+G56+G57+G58 -> 116.5715 | H61: =H53+H56+H57+H58 -> 128.4505 | I61: =I53+I56+I57+I58 -> 136.56819 | J61: 10-K 官方分部（雲端與軟體）
A62: 分部：Hardware | B62: US$B | C62: =C59 -> 3.084 | D62: =D59 -> 3.3818726 | E62: =E59 -> 3.5991559 | F62: =F59 -> 3.7725886 | G62: =G59 -> 3.8937819 | H62: =H59 -> 3.9563252 | I62: =I59 -> 3.9563252
A63: 分部：Services | B63: US$B | C63: =C60 -> 5.743 | D63: =D60 -> 6.2128627 | E63: =E60 -> 6.708102 | F63: =F60 -> 7.1594495 | G63: =G60 -> 7.552188 | H63: =H60 -> 7.8726121 | I63: =I60 -> 8.1087904
A64: 合併營收 | B64: US$B | C64: =C61+C62+C63 -> 67.357 | D64: =D61+D62+D63 -> 83.43308 | E64: =E61+E62+E63 -> 97.314677 | F64: =F61+F62+F63 -> 112.50233 | G64: =G61+G62+G63 -> 128.01747 | H64: =H61+H62+H63 -> 140.27944 | I64: =I61+I62+I63 -> 148.6333
A65: 合併營收年增 | B65: % | D65: =D64/C64-1 -> 0.23866977 | E65: =E64/D64-1 -> 0.16638001 | F65: =F64/E64-1 -> 0.15606741 | G65: =G64/F64-1 -> 0.13790954 | H65: =H64/G64-1 -> 0.095783567 | I65: =I64/H64-1 -> 0.059551575
A66: 檢查：OCI 子列合計 − OCI（應為 0） | B66: US$B | D66: =D54+D55-D53 -> 0 | E66: =E54+E55-E53 -> 0 | F66: =F54+F55-F53 -> 0 | G66: =G54+G55-G53 -> 0 | H66: =H54+H55-H53 -> 0 | I66: =I54+I55-I53 -> 0
A67: 檢查：營收線合計 − 合併營收（應為 0） | B67: US$B | C67: =C53+C56+C57+C58+C59+C60-C64 -> 0 | D67: =D53+D56+D57+D58+D59+D60-D64 -> 0 | E67: =E53+E56+E57+E58+E59+E60-E64 -> 0 | F67: =F53+F56+F57+F58+F59+F60-F64 -> 0 | G67: =G53+G56+G57+G58+G59+G60-G64 -> 0 | H67: =H53+H56+H57+H58+H59+H60-H64 -> 0 | I67: =I53+I56+I57+I58+I59+I60-I64 -> 0
A68: 檢查：FY2026 合併營收 − 公司揭露（應為 0） | B68: US$B | C68: =C64-a26_rev -> 0

Sheet PL
A1: PL — 三情境損益（十億美元；EPS 美元）。分部營收（Seg 頁）→ 分部利潤（Cloud and software＝OCI AI 貢獻〔Thesis 頁，含 AI 折舊與租金〕＋其餘營收 × m_sw；硬體、服務＝營收 × FY2026 利潤率）→ 減未分攤費用＝GAAP 營業利益 → 利息、稅 → 淨利 → EPS（GAAP）
A2: FY2026 為實績；FY2027＝Q1 實績＋Q2–Q4 模型。持股評價損益：預測期設 0。EPS 為 GAAP 稀釋口徑（共識 GAAP EPS 對照見 Recon）
A3: 項目 | B3: 單位 | C3: FY2026A | D3: FY2027 | E3: FY2028 | F3: FY2029 | G3: FY2030 | H3: FY2031 | I3: FY2032 | J3: 說明
A4: 分部核對（三情境合計絕對差；每年度應為 0）
A5: 檢查：分部合計 − 合併營收 | C5: =ABS(C18+C19+C20-C21)+ABS(C58+C59+C60-C61)+ABS(C98+C99+C100-C101) -> 0 | D5: =ABS(D18+D19+D20-D21)+ABS(D58+D59+D60-D61)+ABS(D98+D99+D100-D101) -> 0 | E5: =ABS(E18+E19+E20-E21)+ABS(E58+E59+E60-E61)+ABS(E98+E99+E100-E101) -> 0 | F5: =ABS(F18+F19+F20-F21)+ABS(F58+F59+F60-F61)+ABS(F98+F99+F100-F101) -> 0 | G5: =ABS(G18+G19+G20-G21)+ABS(G58+G59+G60-G61)+ABS(G98+G99+G100-G101) -> 0 | H5: =ABS(H18+H19+H20-H21)+ABS(H58+H59+H60-H61)+ABS(H98+H99+H100-H101) -> 0 | I5: =ABS(I18+I19+I20-I21)+ABS(I58+I59+I60-I61)+ABS(I98+I99+I100-I101) -> 0
A6: 檢查：子列合計 − 母列（OCI 兩子列；Cloud and software 四營收線） | C6: =ABS(C10+C13+C14+C15-C18)+ABS(C50+C53+C54+C55-C58)+ABS(C90+C93+C94+C95-C98) -> 0 | D6: =ABS(D10+D13+D14+D15-D18)+ABS(D50+D53+D54+D55-D58)+ABS(D90+D93+D94+D95-D98)+ABS(D11+D12-D10)+ABS(D51+D52-D50)+ABS(D91+D92-D90) -> 0 | E6: =ABS(E10+E13+E14+E15-E18)+ABS(E50+E53+E54+E55-E58)+ABS(E90+E93+E94+E95-E98)+ABS(E11+E12-E10)+ABS(E51+E52-E50)+ABS(E91+E92-E90) -> 0 | F6: =ABS(F10+F13+F14+F15-F18)+ABS(F50+F53+F54+F55-F58)+ABS(F90+F93+F94+F95-F98)+ABS(F11+F12-F10)+ABS(F51+F52-F50)+ABS(F91+F92-F90) -> 0 | G6: =ABS(G10+G13+G14+G15-G18)+ABS(G50+G53+G54+G55-G58)+ABS(G90+G93+G94+G95-G98)+ABS(G11+G12-G10)+ABS(G51+G52-G50)+ABS(G91+G92-G90) -> 0 | H6: =ABS(H10+H13+H14+H15-H18)+ABS(H50+H53+H54+H55-H58)+ABS(H90+H93+H94+H95-H98)+ABS(H11+H12-H10)+ABS(H51+H52-H50)+ABS(H91+H92-H90) -> 0 | I6: =ABS(I10+I13+I14+I15-I18)+ABS(I50+I53+I54+I55-I58)+ABS(I90+I93+I94+I95-I98)+ABS(I11+I12-I10)+ABS(I51+I52-I50)+ABS(I91+I92-I90) -> 0
A7: 檢查：營收線合計 − 合併營收 | C7: =ABS(C10+C13+C14+C15+C16+C17-C21)+ABS(C50+C53+C54+C55+C56+C57-C61)+ABS(C90+C93+C94+C95+C96+C97-C101) -> 0 | D7: =ABS(D10+D13+D14+D15+D16+D17-D21)+ABS(D50+D53+D54+D55+D56+D57-D61)+ABS(D90+D93+D94+D95+D96+D97-D101) -> 0 | E7: =ABS(E10+E13+E14+E15+E16+E17-E21)+ABS(E50+E53+E54+E55+E56+E57-E61)+ABS(E90+E93+E94+E95+E96+E97-E101) -> 0 | F7: =ABS(F10+F13+F14+F15+F16+F17-F21)+ABS(F50+F53+F54+F55+F56+F57-F61)+ABS(F90+F93+F94+F95+F96+F97-F101) -> 0 | G7: =ABS(G10+G13+G14+G15+G16+G17-G21)+ABS(G50+G53+G54+G55+G56+G57-G61)+ABS(G90+G93+G94+G95+G96+G97-G101) -> 0 | H7: =ABS(H10+H13+H14+H15+H16+H17-H21)+ABS(H50+H53+H54+H55+H56+H57-H61)+ABS(H90+H93+H94+H95+H96+H97-H101) -> 0 | I7: =ABS(I10+I13+I14+I15+I16+I17-I21)+ABS(I50+I53+I54+I55+I56+I57-I61)+ABS(I90+I93+I94+I95+I96+I97-I101) -> 0
A9: 情境 A（樂觀：依公司時程交付、不延誤）
A10: Cloud Infrastructure（OCI） | B10: US$B | C10: =Seg!C17 -> 18.101 | D10: =Seg!D17 -> 42.18858 | E10: =Seg!E17 -> 78.801944 | F10: =Seg!F17 -> 101.04615 | G10: =Seg!G17 -> 106.01906 | H10: =Seg!H17 -> 109.84953 | I10: =Seg!I17 -> 116.39343
A11: OCI AI 算力（命題子列） | B11: US$B | D11: =Seg!D18 -> 31.400886 | E11: =Seg!E18 -> 66.115616 | F11: =Seg!F18 -> 86.431505 | G11: =Seg!G18 -> 89.533734 | H11: =Seg!H18 -> 91.649727 | I11: =Seg!I18 -> 96.737643
A12: OCI 其他（非 AI）（子列） | B12: US$B | D12: =Seg!D19 -> 10.787694 | E12: =Seg!E19 -> 12.686328 | F12: =Seg!F19 -> 14.61465 | G12: =Seg!G19 -> 16.485325 | H12: =Seg!H19 -> 18.199799 | I12: =Seg!I19 -> 19.655782
A13: Cloud Applications（SaaS） | B13: US$B | C13: =Seg!C20 -> 15.888 | D13: =Seg!D20 -> 17.606869 | E13: =Seg!E20 -> 19.453741 | F13: =Seg!F20 -> 21.373265 | G13: =Seg!G20 -> 23.34917 | H13: =Seg!H20 -> 25.362423 | I13: =Seg!I20 -> 27.391417
A14: Software license | B14: US$B | C14: =Seg!C21 -> 4.737 | D14: =Seg!D21 -> 4.2582715 | E14: =Seg!E21 -> 3.9257738 | F14: =Seg!F21 -> 3.6762434 | G14: =Seg!G21 -> 3.4959553 | H14: =Seg!H21 -> 3.3752725 | I14: =Seg!I21 -> 3.307767
A15: Software support | B15: US$B | C15: =Seg!C22 -> 19.804 | D15: =Seg!D22 -> 19.867603 | E15: =Seg!E22 -> 19.960169 | F15: =Seg!F22 -> 19.980017 | G15: =Seg!G22 -> 19.926662 | H15: =Seg!H22 -> 19.800423 | I15: =Seg!I22 -> 19.602419
A16: Hardware | B16: US$B | C16: =Seg!C23 -> 3.084 | D16: =Seg!D23 -> 3.3818726 | E16: =Seg!E23 -> 3.5991559 | F16: =Seg!F23 -> 3.7725886 | G16: =Seg!G23 -> 3.8937819 | H16: =Seg!H23 -> 3.9563252 | I16: =Seg!I23 -> 3.9563252
A17: Services | B17: US$B | C17: =Seg!C24 -> 5.743 | D17: =Seg!D24 -> 6.2128627 | E17: =Seg!E24 -> 6.708102 | F17: =Seg!F24 -> 7.1594495 | G17: =Seg!G24 -> 7.552188 | H17: =Seg!H24 -> 7.8726121 | I17: =Seg!I24 -> 8.1087904
A18: 分部：Cloud and software | B18: US$B | C18: =C10+C13+C14+C15 -> 58.53 | D18: =D10+D13+D14+D15 -> 83.921324 | E18: =E10+E13+E14+E15 -> 122.14163 | F18: =F10+F13+F14+F15 -> 146.07568 | G18: =G10+G13+G14+G15 -> 152.79085 | H18: =H10+H13+H14+H15 -> 158.38764 | I18: =I10+I13+I14+I15 -> 166.69503
A19: 分部：Hardware | B19: US$B | C19: =C16 -> 3.084 | D19: =D16 -> 3.3818726 | E19: =E16 -> 3.5991559 | F19: =F16 -> 3.7725886 | G19: =G16 -> 3.8937819 | H19: =H16 -> 3.9563252 | I19: =I16 -> 3.9563252
A20: 分部：Services | B20: US$B | C20: =C17 -> 5.743 | D20: =D17 -> 6.2128627 | E20: =E17 -> 6.708102 | F20: =F17 -> 7.1594495 | G20: =G17 -> 7.552188 | H20: =H17 -> 7.8726121 | I20: =I17 -> 8.1087904
A21: 合併營收 | B21: US$B | C21: =Seg!C28 -> 67.357 | D21: =Seg!D28 -> 93.516059 | E21: =Seg!E28 -> 132.44889 | F21: =Seg!F28 -> 157.00772 | G21: =Seg!G28 -> 164.23682 | H21: =Seg!H28 -> 170.21658 | I21: =Seg!I28 -> 178.76014
A22: 合併營收年增 | B22: % | D22: =D21/C21-1 -> 0.38836437 | E22: =E21/D21-1 -> 0.41632237 | F22: =F21/E21-1 -> 0.18542121 | G22: =G21/F21-1 -> 0.046042941 | H22: =H21/G21-1 -> 0.036409407 | I22: =I21/H21-1 -> 0.050192303
A23: 分部利潤：Cloud and software | B23: US$B | C23: =Q!L16 -> 34.468 | D23: =Q!I16+Thesis!D29+(m_sw+m_adj)*((D18-Q!I11)-Thesis!D19) -> 40.064264 | E23: =Thesis!F29+(m_sw+m_adj)*(E18-Thesis!F19) -> 46.150598 | F23: =Thesis!G29+(m_sw+m_adj)*(F18-Thesis!G19) -> 51.164056 | G23: =Thesis!H29+(m_sw+m_adj)*(G18-Thesis!H19) -> 52.709693 | H23: =Thesis!I29+(m_sw+m_adj)*(H18-Thesis!I19) -> 54.92226 | I23: =Thesis!J29+(m_sw+m_adj)*(I18-Thesis!J19) -> 59.688826 | J23: OCI AI 貢獻（Thesis，含 AI 折舊與租金）＋（分部營收 − OCI AI 營收）× m_sw
A24: 其中：OCI AI 貢獻（命題） | B24: US$B | D24: =Thesis!E29 -> 6.1770538 | E24: =Thesis!F29 -> 10.001523 | F24: =Thesis!G29 -> 12.680471 | G24: =Thesis!H29 -> 11.89497 | H24: =Thesis!I29 -> 11.861655 | I24: =Thesis!J29 -> 14.550957
A25: 分部利潤：Hardware | B25: US$B | C25: =Q!L17 -> 2.017 | D25: =Q!I17+m_hw*(D19-Q!I12) -> 2.1576028 | E25: =m_hw*E19 -> 2.3539226 | F25: =m_hw*F19 -> 2.4673512 | G25: =m_hw*G19 -> 2.5466142 | H25: =m_hw*H19 -> 2.5875188 | I25: =m_hw*I19 -> 2.5875188
A26: 分部利潤：Services | B26: US$B | C26: =Q!L18 -> 1.533 | D26: =Q!I18+m_svc*(D20-Q!I13) -> 1.725978 | E26: =m_svc*E20 -> 1.7906182 | F26: =m_svc*F20 -> 1.911098 | G26: =m_svc*G20 -> 2.0159332 | H26: =m_svc*H20 -> 2.1014651 | I26: =m_svc*I20 -> 2.1645091
A27: 分部利潤合計 | B27: US$B | C27: =C23+C25+C26 -> 38.018 | D27: =D23+D25+D26 -> 43.947844 | E27: =E23+E25+E26 -> 50.295139 | F27: =F23+F25+F26 -> 55.542506 | G27: =G23+G25+G26 -> 57.27224 | H27: =H23+H25+H26 -> 59.611244 | I27: =I23+I25+I26 -> 64.440853
A28: Cloud and software 分部利潤率 | B28: % | C28: =C23/C18 -> 0.58889458 | D28: =D23/D18 -> 0.47740267 | E28: =E23/E18 -> 0.37784496 | F28: =F23/F18 -> 0.35025718 | G28: =G23/G18 -> 0.34497939 | H28: =H23/H18 -> 0.34675849 | I28: =I23/I18 -> 0.35807202
A29: 未分攤費用（研發、管理、攤銷、SBC 等） | B29: US$B | C29: =Q!L20 -> 17.412 | D29: =Q!I20*(1+3*un_rr) -> 16.586 | E29: =D29*(1+un_g) -> 17.24944 | F29: =E29*(1+un_g) -> 17.939418 | G29: =F29*(1+un_g) -> 18.656994 | H29: =G29*(1+un_g) -> 19.403274 | I29: =H29*(1+un_g) -> 20.179405 | J29: FY2027＝Q1 實績 ×（1＋3 × un_rr）；其後年增 un_g
A30: 營業利益（GAAP） | B30: US$B | C30: =C27-C29 -> 20.606 | D30: =D27-D29 -> 27.361844 | E30: =E27-E29 -> 33.045699 | F30: =F27-F29 -> 37.603088 | G30: =G27-G29 -> 38.615246 | H30: =H27-H29 -> 40.20797 | I30: =I27-I29 -> 44.261448
A31: 營業利益率 | B31: % | C31: =C30/C21 -> 0.30592218 | D31: =D30/D21 -> 0.29258979 | E31: =E30/E21 -> 0.24949775 | F31: =F30/F21 -> 0.23949834 | G31: =G30/G21 -> 0.2351193 | H31: =H30/H21 -> 0.23621653 | I31: =I30/I21 -> 0.24760244
A32: OCI AI 營業利益率（命題） | B32: % | D32: =Thesis!E30 -> 0.1967159 | E32: =Thesis!F30 -> 0.15127323 | F32: =Thesis!G30 -> 0.14671122 | G32: =Thesis!H30 -> 0.13285462 | H32: =Thesis!I30 -> 0.12942379 | I32: =Thesis!J30 -> 0.1504167
A33: 利息費用 | B33: US$B | C33: =Q!L26 -> 4.599 | D33: =CF!D46 -> 5.712 | E33: =CF!E46 -> 5.712 | F33: =CF!F46 -> 5.9945969 | G33: =CF!G46 -> 5.9945969 | H33: =CF!H46 -> 5.9945969 | I33: =CF!I46 -> 5.9945969 | J33: CF 頁：既有借款 × r_old＋期初新債 × r_new＋高息債 × 12%
A34: 利息收入 | B34: US$B | D34: =CF!D47 -> 1.2418708 | E34: =CF!E47 -> 0.54679545 | F34: =CF!F47 -> 0.33655036 | G34: =CF!G47 -> 1.9922606 | H34: =CF!H47 -> 3.6695961 | I34: =CF!I47 -> 5.3839236 | J34: FY2026 含在其他收益（未拆）
A35: 稅前利益 | B35: US$B | D35: =D30-D33+D34 -> 22.891715 | E35: =E30-E33+E34 -> 27.880494 | F35: =F30-F33+F34 -> 31.945042 | G35: =G30-G33+G34 -> 34.612909 | H35: =H30-H33+H34 -> 37.882969 | I35: =I30-I33+I34 -> 43.650775 | J35: 其他收益與持股評價損益：預測期設 0
A36: 所得稅 | B36: US$B | D36: =D35*etr -> 3.456649 | E36: =E35*etr -> 4.2099546 | F36: =F35*etr -> 4.8237013 | G36: =G35*etr -> 5.2265493 | H36: =H35*etr -> 5.7203284 | I36: =I35*etr -> 6.591267
A37: 淨利 | B37: US$B | C37: =Q!L27 -> 17.087 | D37: =D35-D36 -> 19.435066 | E37: =E35-E36 -> 23.67054 | F37: =F35-F36 -> 27.12134 | G37: =G35-G36 -> 29.38636 | H37: =H35-H36 -> 32.162641 | I37: =I35-I36 -> 37.059508
A38: 特別股股利 | B38: US$B | C38: =Q!L48 -> 0.103 | D38: =pref_q1+pref27 -> 0.325 | E38: =pref28 -> 0.325 | F38: =pref29 -> 0.244 | G38: =0 -> 0 | H38: =0 -> 0 | I38: =0 -> 0 | J38: FY27 Q1 實績 0.081＋Q2–Q4；2029-01-15 強制轉換
A39: 歸屬普通股淨利 | B39: US$B | C39: =C37-C38 -> 16.984 | D39: =D37-D38 -> 19.110066 | E39: =E37-E38 -> 23.34554 | F39: =F37-F38 -> 26.87734 | G39: =G37-G38 -> 29.38636 | H39: =H37-H38 -> 32.162641 | I39: =I37-I38 -> 37.059508
A40: 稀釋股數 | B40: 十億股 | C40: =Q!L49 -> 2.914 | D40: =CF!D45 -> 3.043302 | E40: =CF!E45 -> 3.057736 | F40: =CF!F45 -> 3.073355 | G40: =CF!G45 -> 3.088974 | H40: =CF!H45 -> 3.088974 | I40: =CF!I45 -> 3.088974
A41: EPS（GAAP 稀釋） | B41: US$ | C41: =Q!L50 -> 5.83 | D41: =D39/D40 -> 6.2793854 | E41: =E39/E40 -> 7.6349102 | F41: =F39/F40 -> 8.7452768 | G41: =G39/G40 -> 9.5133077 | H41: =H39/H40 -> 10.412079 | I41: =I39/I40 -> 11.997352
A42: EPS 年增 | B42: % | D42: =D41/C41-1 -> 0.077081552 | E42: =E41/D41-1 -> 0.21586901 | F42: =F41/E41-1 -> 0.14543284 | G42: =G41/F41-1 -> 0.087822355 | H42: =H41/G41-1 -> 0.094475154 | I42: =I41/H41-1 -> 0.15225327
A43: 折舊與攤銷（D&A） | B43: US$B | C43: =Q!L24 -> 9.294 | D43: =Q!I24+Thesis!D27+nonai_dep_q*3+amort*0.75 -> 20.227974 | E43: =Thesis!F27+nonai_dep_q*(E21-Thesis!F19)/(q1_rev-Thesis!C19)+amort -> 38.754844 | F43: =Thesis!G27+nonai_dep_q*(F21-Thesis!G19)/(q1_rev-Thesis!C19)+amort -> 46.643226 | G43: =Thesis!H27+nonai_dep_q*(G21-Thesis!H19)/(q1_rev-Thesis!C19)+amort -> 47.785116 | H43: =Thesis!I27+nonai_dep_q*(H21-Thesis!I19)/(q1_rev-Thesis!C19)+amort -> 49.452532 | I43: =Thesis!J27+nonai_dep_q*(I21-Thesis!J19)/(q1_rev-Thesis!C19)+amort -> 50.735618 | J43: AI 折舊（Thesis）＋非 AI 折舊（FY2024 水準每季 0.782，隨非 AI 營收相對 Q1 等比例）＋無形資產攤銷
A44: 股份基礎給付（SBC） | B44: US$B | C44: =Q!L25 -> 4.811 | D44: =sbc_q1*(1+3*un_rr) -> 5.2998078 | E44: =D44*(1+un_g) -> 5.5118001 | F44: =E44*(1+un_g) -> 5.7322721 | G44: =F44*(1+un_g) -> 5.961563 | H44: =G44*(1+un_g) -> 6.2000255 | I44: =H44*(1+un_g) -> 6.4480265
A45: EBITDA（營業利益＋D&A） | B45: US$B | C45: =C30+C43 -> 29.9 | D45: =D30+D43 -> 47.589818 | E45: =E30+E43 -> 71.800542 | F45: =F30+F43 -> 84.246314 | G45: =G30+G43 -> 86.400361 | H45: =H30+H43 -> 89.660502 | I45: =I30+I43 -> 94.997066
A46: 調整後 EBITDA（＋SBC；共識與同業口徑） | B46: US$B | C46: =C45+C44 -> 34.711 | D46: =D45+D44 -> 52.889626 | E46: =E45+E44 -> 77.312343 | F46: =F45+F44 -> 89.978587 | G46: =G45+G44 -> 92.361924 | H46: =H45+H44 -> 95.860527 | I46: =I45+I44 -> 101.44509
A47: 檢查：FY2026 營業利益 − 公司揭露 20.606（應為 0） | B47: US$B | C47: =C30-Q!L21 -> 0
A49: 情境 B（基準：依 FY27Q1 交付速度、延誤 3 個月）
A50: Cloud Infrastructure（OCI） | B50: US$B | C50: =Seg!C35 -> 18.101 | D50: =Seg!D35 -> 35.826476 | E50: =Seg!E35 -> 65.343121 | F50: =Seg!F35 -> 93.600308 | G50: =Seg!G35 -> 106.57734 | H50: =Seg!H35 -> 110.17489 | I50: =Seg!I35 -> 116.45578
A51: OCI AI 算力（命題子列） | B51: US$B | D51: =Seg!D36 -> 25.038782 | E51: =Seg!E36 -> 52.656793 | F51: =Seg!F36 -> 78.985658 | G51: =Seg!G36 -> 90.092012 | H51: =Seg!H36 -> 91.975086 | I51: =Seg!I36 -> 96.799994
A52: OCI 其他（非 AI）（子列） | B52: US$B | D52: =Seg!D37 -> 10.787694 | E52: =Seg!E37 -> 12.686328 | F52: =Seg!F37 -> 14.61465 | G52: =Seg!G37 -> 16.485325 | H52: =Seg!H37 -> 18.199799 | I52: =Seg!I37 -> 19.655782
A53: Cloud Applications（SaaS） | B53: US$B | C53: =Seg!C38 -> 15.888 | D53: =Seg!D38 -> 17.606869 | E53: =Seg!E38 -> 19.453741 | F53: =Seg!F38 -> 21.373265 | G53: =Seg!G38 -> 23.34917 | H53: =Seg!H38 -> 25.362423 | I53: =Seg!I38 -> 27.391417
A54: Software license | B54: US$B | C54: =Seg!C39 -> 4.737 | D54: =Seg!D39 -> 4.2582715 | E54: =Seg!E39 -> 3.9257738 | F54: =Seg!F39 -> 3.6762434 | G54: =Seg!G39 -> 3.4959553 | H54: =Seg!H39 -> 3.3752725 | I54: =Seg!I39 -> 3.307767
A55: Software support | B55: US$B | C55: =Seg!C40 -> 19.804 | D55: =Seg!D40 -> 19.867603 | E55: =Seg!E40 -> 19.960169 | F55: =Seg!F40 -> 19.980017 | G55: =Seg!G40 -> 19.926662 | H55: =Seg!H40 -> 19.800423 | I55: =Seg!I40 -> 19.602419
A56: Hardware | B56: US$B | C56: =Seg!C41 -> 3.084 | D56: =Seg!D41 -> 3.3818726 | E56: =Seg!E41 -> 3.5991559 | F56: =Seg!F41 -> 3.7725886 | G56: =Seg!G41 -> 3.8937819 | H56: =Seg!H41 -> 3.9563252 | I56: =Seg!I41 -> 3.9563252
A57: Services | B57: US$B | C57: =Seg!C42 -> 5.743 | D57: =Seg!D42 -> 6.2128627 | E57: =Seg!E42 -> 6.708102 | F57: =Seg!F42 -> 7.1594495 | G57: =Seg!G42 -> 7.552188 | H57: =Seg!H42 -> 7.8726121 | I57: =Seg!I42 -> 8.1087904
A58: 分部：Cloud and software | B58: US$B | C58: =C50+C53+C54+C55 -> 58.53 | D58: =D50+D53+D54+D55 -> 77.559219 | E58: =E50+E53+E54+E55 -> 108.68281 | F58: =F50+F53+F54+F55 -> 138.62983 | G58: =G50+G53+G54+G55 -> 153.34912 | H58: =H50+H53+H54+H55 -> 158.713 | I58: =I50+I53+I54+I55 -> 166.75738
A59: 分部：Hardware | B59: US$B | C59: =C56 -> 3.084 | D59: =D56 -> 3.3818726 | E59: =E56 -> 3.5991559 | F59: =F56 -> 3.7725886 | G59: =G56 -> 3.8937819 | H59: =H56 -> 3.9563252 | I59: =I56 -> 3.9563252
A60: 分部：Services | B60: US$B | C60: =C57 -> 5.743 | D60: =D57 -> 6.2128627 | E60: =E57 -> 6.708102 | F60: =F57 -> 7.1594495 | G60: =G57 -> 7.552188 | H60: =H57 -> 7.8726121 | I60: =I57 -> 8.1087904
A61: 合併營收 | B61: US$B | C61: =Seg!C46 -> 67.357 | D61: =Seg!D46 -> 87.153955 | E61: =Seg!E46 -> 118.99006 | F61: =Seg!F46 -> 149.56187 | G61: =Seg!G46 -> 164.79509 | H61: =Seg!H46 -> 170.54194 | I61: =Seg!I46 -> 178.82249
A62: 合併營收年增 | B62: % | D62: =D61/C61-1 -> 0.29391087 | E62: =E61/D61-1 -> 0.36528587 | F62: =F61/E61-1 -> 0.25692741 | G62: =G61/F61-1 -> 0.10185231 | H62: =H61/G61-1 -> 0.034872676 | I62: =I61/H61-1 -> 0.048554357
A63: 分部利潤：Cloud and software | B63: US$B | C63: =Q!L16 -> 34.468 | D63: =Q!I16+Thesis!D64+(m_sw+m_adj)*((D58-Q!I11)-Thesis!D54) -> 34.991645 | E63: =Thesis!F64+(m_sw+m_adj)*(E58-Thesis!F54) -> 35.310834 | F63: =Thesis!G64+(m_sw+m_adj)*(F58-Thesis!G54) -> 43.386654 | G63: =Thesis!H64+(m_sw+m_adj)*(G58-Thesis!H54) -> 49.651977 | H63: =Thesis!I64+(m_sw+m_adj)*(H58-Thesis!I54) -> 51.676443 | I63: =Thesis!J64+(m_sw+m_adj)*(I58-Thesis!J54) -> 56.228681 | J63: OCI AI 貢獻（Thesis，含 AI 折舊與租金）＋（分部營收 − OCI AI 營收）× m_sw
A64: 其中：OCI AI 貢獻（命題） | B64: US$B | D64: =Thesis!E64 -> 1.1044354 | E64: =Thesis!F64 -> -0.83824086 | F64: =Thesis!G64 -> 4.9030695 | G64: =Thesis!H64 -> 8.8372546 | H64: =Thesis!I64 -> 8.6158379 | I64: =Thesis!J64 -> 11.090813
A65: 分部利潤：Hardware | B65: US$B | C65: =Q!L17 -> 2.017 | D65: =Q!I17+m_hw*(D59-Q!I12) -> 2.1576028 | E65: =m_hw*E59 -> 2.3539226 | F65: =m_hw*F59 -> 2.4673512 | G65: =m_hw*G59 -> 2.5466142 | H65: =m_hw*H59 -> 2.5875188 | I65: =m_hw*I59 -> 2.5875188
A66: 分部利潤：Services | B66: US$B | C66: =Q!L18 -> 1.533 | D66: =Q!I18+m_svc*(D60-Q!I13) -> 1.725978 | E66: =m_svc*E60 -> 1.7906182 | F66: =m_svc*F60 -> 1.911098 | G66: =m_svc*G60 -> 2.0159332 | H66: =m_svc*H60 -> 2.1014651 | I66: =m_svc*I60 -> 2.1645091
A67: 分部利潤合計 | B67: US$B | C67: =C63+C65+C66 -> 38.018 | D67: =D63+D65+D66 -> 38.875226 | E67: =E63+E65+E66 -> 39.455375 | F67: =F63+F65+F66 -> 47.765104 | G67: =G63+G65+G66 -> 54.214524 | H67: =H63+H65+H66 -> 56.365427 | I67: =I63+I65+I66 -> 60.980709
A68: Cloud and software 分部利潤率 | B68: % | C68: =C63/C58 -> 0.58889458 | D68: =D63/D58 -> 0.45116036 | E68: =E63/E58 -> 0.32489808 | F68: =F63/F58 -> 0.31296766 | G68: =G63/G58 -> 0.32378389 | H68: =H63/H58 -> 0.32559678 | I68: =I63/I58 -> 0.33718857
A69: 未分攤費用（研發、管理、攤銷、SBC 等） | B69: US$B | C69: =Q!L20 -> 17.412 | D69: =Q!I20*(1+3*un_rr) -> 16.586 | E69: =D69*(1+un_g) -> 17.24944 | F69: =E69*(1+un_g) -> 17.939418 | G69: =F69*(1+un_g) -> 18.656994 | H69: =G69*(1+un_g) -> 19.403274 | I69: =H69*(1+un_g) -> 20.179405 | J69: FY2027＝Q1 實績 ×（1＋3 × un_rr）；其後年增 un_g
A70: 營業利益（GAAP） | B70: US$B | C70: =C67-C69 -> 20.606 | D70: =D67-D69 -> 22.289226 | E70: =E67-E69 -> 22.205935 | F70: =F67-F69 -> 29.825686 | G70: =G67-G69 -> 35.55753 | H70: =H67-H69 -> 36.962153 | I70: =I67-I69 -> 40.801304
A71: 營業利益率 | B71: % | C71: =C70/C61 -> 0.30592218 | D71: =D70/D61 -> 0.25574544 | E71: =E70/E61 -> 0.18662008 | F71: =F70/F61 -> 0.19942039 | G71: =G70/G61 -> 0.21576813 | H71: =H70/H61 -> 0.21673351 | I71: =I70/I61 -> 0.22816651
A72: OCI AI 營業利益率（命題） | B72: % | D72: =Thesis!E65 -> 0.044108989 | E72: =Thesis!F65 -> -0.01591895 | F72: =Thesis!G65 -> 0.06207544 | G72: =Thesis!H65 -> 0.098091434 | H72: =Thesis!I65 -> 0.093675779 | I72: =Thesis!J65 -> 0.11457452
A73: 利息費用 | B73: US$B | C73: =Q!L26 -> 4.599 | D73: =CF!D81 -> 5.712 | E73: =CF!E81 -> 5.712 | F73: =CF!F81 -> 6.791719 | G73: =CF!G81 -> 6.791719 | H73: =CF!H81 -> 6.791719 | I73: =CF!I81 -> 6.791719 | J73: CF 頁：既有借款 × r_old＋期初新債 × r_new＋高息債 × 12%
A74: 利息收入 | B74: US$B | D74: =CF!D82 -> 1.2418708 | E74: =CF!E82 -> 0.40185489 | F74: =CF!F82 -> 0.33655036 | G74: =CF!G82 -> 1.2632421 | H74: =CF!H82 -> 2.8951994 | I74: =CF!I82 -> 4.5574777 | J74: FY2026 含在其他收益（未拆）
A75: 稅前利益 | B75: US$B | D75: =D70-D73+D74 -> 17.819097 | E75: =E70-E73+E74 -> 16.89579 | F75: =F70-F73+F74 -> 23.370517 | G75: =G70-G73+G74 -> 30.029053 | H75: =H70-H73+H74 -> 33.065633 | I75: =I70-I73+I74 -> 38.567063 | J75: 其他收益與持股評價損益：預測期設 0
A76: 所得稅 | B76: US$B | D76: =D75*etr -> 2.6906836 | E76: =E75*etr -> 2.5512643 | F76: =F75*etr -> 3.5289481 | G76: =G75*etr -> 4.534387 | H76: =H75*etr -> 4.9929106 | I76: =I75*etr -> 5.8236265
A77: 淨利 | B77: US$B | C77: =Q!L27 -> 17.087 | D77: =D75-D76 -> 15.128413 | E77: =E75-E76 -> 14.344526 | F77: =F75-F76 -> 19.841569 | G77: =G75-G76 -> 25.494666 | H77: =H75-H76 -> 28.072722 | I77: =I75-I76 -> 32.743436
A78: 特別股股利 | B78: US$B | C78: =Q!L48 -> 0.103 | D78: =pref_q1+pref27 -> 0.325 | E78: =pref28 -> 0.325 | F78: =pref29 -> 0.244 | G78: =0 -> 0 | H78: =0 -> 0 | I78: =0 -> 0 | J78: FY27 Q1 實績 0.081＋Q2–Q4；2029-01-15 強制轉換
A79: 歸屬普通股淨利 | B79: US$B | C79: =C77-C78 -> 16.984 | D79: =D77-D78 -> 14.803413 | E79: =E77-E78 -> 14.019526 | F79: =F77-F78 -> 19.597569 | G79: =G77-G78 -> 25.494666 | H79: =H77-H78 -> 28.072722 | I79: =I77-I78 -> 32.743436
A80: 稀釋股數 | B80: 十億股 | C80: =Q!L49 -> 2.914 | D80: =CF!D80 -> 3.043302 | E80: =CF!E80 -> 3.057736 | F80: =CF!F80 -> 3.073355 | G80: =CF!G80 -> 3.088974 | H80: =CF!H80 -> 3.088974 | I80: =CF!I80 -> 3.088974
A81: EPS（GAAP 稀釋） | B81: US$ | C81: =Q!L50 -> 5.83 | D81: =D79/D80 -> 4.8642603 | E81: =E79/E80 -> 4.5849366 | F81: =F79/F80 -> 6.3766045 | G81: =G79/G80 -> 8.2534414 | H81: =H79/H80 -> 9.088041 | I81: =I79/I80 -> 10.600101
A82: EPS 年增 | B82: % | D82: =D81/C81-1 -> -0.16565003 | E82: =E81/D81-1 -> -0.057423681 | F82: =F81/E81-1 -> 0.39077267 | G82: =G81/F81-1 -> 0.29433171 | H82: =H81/G81-1 -> 0.10112141 | I82: =I81/H81-1 -> 0.16637909
A83: 折舊與攤銷（D&A） | B83: US$B | C83: =Q!L24 -> 9.294 | D83: =Q!I24+Thesis!D62+nonai_dep_q*3+amort*0.75 -> 20.227974 | E83: =Thesis!F62+nonai_dep_q*(E61-Thesis!F54)/(q1_rev-Thesis!C54)+amort -> 38.768552 | F83: =Thesis!G62+nonai_dep_q*(F61-Thesis!G54)/(q1_rev-Thesis!C54)+amort -> 48.452082 | G83: =Thesis!H62+nonai_dep_q*(G61-Thesis!H54)/(q1_rev-Thesis!C54)+amort -> 51.37541 | H83: =Thesis!I62+nonai_dep_q*(H61-Thesis!I54)/(q1_rev-Thesis!C54)+amort -> 53.042826 | I83: =Thesis!J62+nonai_dep_q*(I61-Thesis!J54)/(q1_rev-Thesis!C54)+amort -> 54.325912 | J83: AI 折舊（Thesis）＋非 AI 折舊（FY2024 水準每季 0.782，隨非 AI 營收相對 Q1 等比例）＋無形資產攤銷
A84: 股份基礎給付（SBC） | B84: US$B | C84: =Q!L25 -> 4.811 | D84: =sbc_q1*(1+3*un_rr) -> 5.2998078 | E84: =D84*(1+un_g) -> 5.5118001 | F84: =E84*(1+un_g) -> 5.7322721 | G84: =F84*(1+un_g) -> 5.961563 | H84: =G84*(1+un_g) -> 6.2000255 | I84: =H84*(1+un_g) -> 6.4480265
A85: EBITDA（營業利益＋D&A） | B85: US$B | C85: =C70+C83 -> 29.9 | D85: =D70+D83 -> 42.5172 | E85: =E70+E83 -> 60.974487 | F85: =F70+F83 -> 78.277768 | G85: =G70+G83 -> 86.93294 | H85: =H70+H83 -> 90.004978 | I85: =I70+I83 -> 95.127216
A86: 調整後 EBITDA（＋SBC；共識與同業口徑） | B86: US$B | C86: =C85+C84 -> 34.711 | D86: =D85+D84 -> 47.817008 | E86: =E85+E84 -> 66.486287 | F86: =F85+F84 -> 84.01004 | G86: =G85+G84 -> 92.894503 | H86: =H85+H84 -> 96.205004 | I86: =I85+I84 -> 101.57524
A87: 檢查：FY2026 營業利益 − 公司揭露 20.606（應為 0） | B87: US$B | C87: =C70-Q!L21 -> 0
A89: 情境 C（保守：OpenAI 相關容量實現 60%、延誤 6 個月）
A90: Cloud Infrastructure（OCI） | B90: US$B | C90: =Seg!C53 -> 18.101 | D90: =Seg!D53 -> 32.105601 | E90: =Seg!E53 -> 43.667734 | F90: =Seg!F53 -> 56.540762 | G90: =Seg!G53 -> 69.799713 | H90: =Seg!H53 -> 79.912385 | I90: =Seg!I53 -> 86.266584
A91: OCI AI 算力（命題子列） | B91: US$B | D91: =Seg!D54 -> 21.317907 | E91: =Seg!E54 -> 30.981407 | F91: =Seg!F54 -> 41.926112 | G91: =Seg!G54 -> 53.314388 | H91: =Seg!H54 -> 61.712587 | I91: =Seg!I54 -> 66.610802
A92: OCI 其他（非 AI）（子列） | B92: US$B | D92: =Seg!D55 -> 10.787694 | E92: =Seg!E55 -> 12.686328 | F92: =Seg!F55 -> 14.61465 | G92: =Seg!G55 -> 16.485325 | H92: =Seg!H55 -> 18.199799 | I92: =Seg!I55 -> 19.655782
A93: Cloud Applications（SaaS） | B93: US$B | C93: =Seg!C56 -> 15.888 | D93: =Seg!D56 -> 17.606869 | E93: =Seg!E56 -> 19.453741 | F93: =Seg!F56 -> 21.373265 | G93: =Seg!G56 -> 23.34917 | H93: =Seg!H56 -> 25.362423 | I93: =Seg!I56 -> 27.391417
A94: Software license | B94: US$B | C94: =Seg!C57 -> 4.737 | D94: =Seg!D57 -> 4.2582715 | E94: =Seg!E57 -> 3.9257738 | F94: =Seg!F57 -> 3.6762434 | G94: =Seg!G57 -> 3.4959553 | H94: =Seg!H57 -> 3.3752725 | I94: =Seg!I57 -> 3.307767
A95: Software support | B95: US$B | C95: =Seg!C58 -> 19.804 | D95: =Seg!D58 -> 19.867603 | E95: =Seg!E58 -> 19.960169 | F95: =Seg!F58 -> 19.980017 | G95: =Seg!G58 -> 19.926662 | H95: =Seg!H58 -> 19.800423 | I95: =Seg!I58 -> 19.602419
A96: Hardware | B96: US$B | C96: =Seg!C59 -> 3.084 | D96: =Seg!D59 -> 3.3818726 | E96: =Seg!E59 -> 3.5991559 | F96: =Seg!F59 -> 3.7725886 | G96: =Seg!G59 -> 3.8937819 | H96: =Seg!H59 -> 3.9563252 | I96: =Seg!I59 -> 3.9563252
A97: Services | B97: US$B | C97: =Seg!C60 -> 5.743 | D97: =Seg!D60 -> 6.2128627 | E97: =Seg!E60 -> 6.708102 | F97: =Seg!F60 -> 7.1594495 | G97: =Seg!G60 -> 7.552188 | H97: =Seg!H60 -> 7.8726121 | I97: =Seg!I60 -> 8.1087904
A98: 分部：Cloud and software | B98: US$B | C98: =C90+C93+C94+C95 -> 58.53 | D98: =D90+D93+D94+D95 -> 73.838344 | E98: =E90+E93+E94+E95 -> 87.007419 | F98: =F90+F93+F94+F95 -> 101.57029 | G98: =G90+G93+G94+G95 -> 116.5715 | H98: =H90+H93+H94+H95 -> 128.4505 | I98: =I90+I93+I94+I95 -> 136.56819
A99: 分部：Hardware | B99: US$B | C99: =C96 -> 3.084 | D99: =D96 -> 3.3818726 | E99: =E96 -> 3.5991559 | F99: =F96 -> 3.7725886 | G99: =G96 -> 3.8937819 | H99: =H96 -> 3.9563252 | I99: =I96 -> 3.9563252
A100: 分部：Services | B100: US$B | C100: =C97 -> 5.743 | D100: =D97 -> 6.2128627 | E100: =E97 -> 6.708102 | F100: =F97 -> 7.1594495 | G100: =G97 -> 7.552188 | H100: =H97 -> 7.8726121 | I100: =I97 -> 8.1087904
A101: 合併營收 | B101: US$B | C101: =Seg!C64 -> 67.357 | D101: =Seg!D64 -> 83.43308 | E101: =Seg!E64 -> 97.314677 | F101: =Seg!F64 -> 112.50233 | G101: =Seg!G64 -> 128.01747 | H101: =Seg!H64 -> 140.27944 | I101: =Seg!I64 -> 148.6333
A102: 合併營收年增 | B102: % | D102: =D101/C101-1 -> 0.23866977 | E102: =E101/D101-1 -> 0.16638001 | F102: =F101/E101-1 -> 0.15606741 | G102: =G101/F101-1 -> 0.13790954 | H102: =H101/G101-1 -> 0.095783567 | I102: =I101/H101-1 -> 0.059551575
A103: 分部利潤：Cloud and software | B103: US$B | C103: =Q!L16 -> 34.468 | D103: =Q!I16+Thesis!D99+(m_sw+m_adj)*((D98-Q!I11)-Thesis!D89) -> 31.988627 | E103: =Thesis!F99+(m_sw+m_adj)*(E98-Thesis!F89) -> 21.57634 | F103: =Thesis!G99+(m_sw+m_adj)*(F98-Thesis!G89) -> 20.839641 | G103: =Thesis!H99+(m_sw+m_adj)*(G98-Thesis!H89) -> 26.02503 | H103: =Thesis!I99+(m_sw+m_adj)*(H98-Thesis!I89) -> 32.403904 | I103: =Thesis!J99+(m_sw+m_adj)*(I98-Thesis!J89) -> 37.908847 | J103: OCI AI 貢獻（Thesis，含 AI 折舊與租金）＋（分部營收 − OCI AI 營收）× m_sw
...

Sheet CF
A1: CF — 現金流與融資瀑布（收支模組）。營運現金＝淨利＋D&A＋SBC＋客戶預付流入 − 預付認列（非現金營收）；資本支出＝AI（Thesis）＋非 AI；自由現金流扣股利後的缺口依序由現金（保留最低 10）→ 投資級債（租賃調整後槓桿 ≤ 4.5×）→ 新股（每年 ≤ 市值 5%）→ 高息債 補足
A2: FY2027＝Q1 實績＋Q2–Q4 模型（瀑布只計 Q2–Q4，起點為 Q1 末現金）。利息以期初餘額計（不循環）。租賃負債＝在帳 43.8＋已起租的未起租租約現值（17 年、5.7%）
A3: 項目 | B3: 單位 | C3: 情境 A | D3: 情境 B | E3: 情境 C | F3: 說明
A4: 收支關卡：自由現金流扣股利（五年合計） | B4: US$B | C4: =SUM(D26:H26) -> 111.06343 | D4: =SUM(D61:H61) -> 72.763561 | E4: =SUM(D96:H96) -> 8.3534777 | F4: FY2027–FY2031 自由現金流 − 普通股與特別股股利 的合計（負值＝需外部融資；地圖收支關卡讀這一列）
A5: 融資需求（五年合計）：新增投資級債 | B5: US$B | C5: =SUM(D34:H34) -> 4.8723598 | D5: =SUM(D69:H69) -> 18.615845 | E5: =SUM(D104:H104) -> 0
A6: 融資需求（五年合計）：新股 | B6: US$B | C6: =SUM(D35:H35) -> 0 | D6: =SUM(D70:H70) -> 0 | E6: =SUM(D105:H105) -> 2.4135042
A7: 融資需求（五年合計）：高息債 | B7: US$B | C7: =SUM(D36:H36) -> 0 | D7: =SUM(D71:H71) -> 0 | E7: =SUM(D106:H106) -> 0
A8: 調整後槓桿峰值（FY2027–FY2031） | B8: x | C8: =MAX(D41:H41) -> 4.0195256 | D8: =MAX(D76:H76) -> 4.4336828 | E8: =MAX(D111:H111) -> 5.1998972
A9: 是否需要發新股或高息債（五年） | B9: — | C9: =IF(C6+C7>eq_tol,"需要","不需要") -> 不需要 | D9: =IF(D6+D7>eq_tol,"需要","不需要") -> 不需要 | E9: =IF(E6+E7>eq_tol,"需要","不需要") -> 需要
A10: 累計自由現金流（五年合計） | B10: US$B | C10: =SUM(D24:H24) -> 142.29187 | D10: =SUM(D59:H59) -> 103.99201 | E10: =SUM(D94:H94) -> 39.720298
A11: 檢查：收支關卡＝首年起五年自由現金流扣股利（逐欄加總，應為 0） | B11: US$B | C11: =C4-(D26+E26+F26+G26+H26) -> 0 | D11: =D4-(D61+E61+F61+G61+H61) -> 0 | E11: =E4-(D96+E96+F96+G96+H96) -> 0
A13: 項目 | B13: 單位 | C13: FY2026A | D13: FY2027 | E13: FY2028 | F13: FY2029 | G13: FY2030 | H13: FY2031 | I13: FY2032 | J13: 說明
A14: 情境 A（樂觀：依公司時程交付、不延誤）
A15: 淨利 | B15: US$B | C15: =PL!C37 -> 17.087 | D15: =PL!D37 -> 19.435066 | E15: =PL!E37 -> 23.67054 | F15: =PL!F37 -> 27.12134 | G15: =PL!G37 -> 29.38636 | H15: =PL!H37 -> 32.162641 | I15: =PL!I37 -> 37.059508
A16: 折舊與攤銷 | B16: US$B | C16: =PL!C43 -> 9.294 | D16: =PL!D43 -> 20.227974 | E16: =PL!E43 -> 38.754844 | F16: =PL!F43 -> 46.643226 | G16: =PL!G43 -> 47.785116 | H16: =PL!H43 -> 49.452532 | I16: =PL!I43 -> 50.735618
A17: SBC（非現金） | B17: US$B | C17: =PL!C44 -> 4.811 | D17: =PL!D44 -> 5.2998078 | E17: =PL!E44 -> 5.5118001 | F17: =PL!F44 -> 5.7322721 | G17: =PL!G44 -> 5.961563 | H17: =PL!H44 -> 6.2000255 | I17: =PL!I44 -> 6.4480265
A18: 客戶預付流入（AI 資本支出 × 覆蓋比） | B18: US$B | D18: =prepay_cov*Thesis!D25 -> 14.626068 | E18: =prepay_cov*Thesis!F25 -> 19.665107 | F18: =prepay_cov*Thesis!G25 -> 2.6686749 | G18: =prepay_cov*Thesis!H25 -> 3.4106066 | H18: =prepay_cov*Thesis!I25 -> 4.2425783 | I18: =prepay_cov*Thesis!J25 -> 15.278433 | J18: FY2027 只計 Q2–Q4（Q1 實績 11.363 已在營運現金流）
A19: 預付認列（非現金營收，自營運現金扣除） | B19: US$B | D19: =prepay_open/prepay_yrs*MAX(0,MIN(D27,prepay_yrs)-MIN(0,prepay_yrs)) -> 2.39325 | E19: =prepay_open/prepay_yrs*MAX(0,MIN(D27+E27,prepay_yrs)-MIN(D27,prepay_yrs))+D18/prepay_yrs*MAX(0,MIN(1,prepay_yrs)-MIN(0,prepay_yrs)) -> 6.1162136 | F19: =prepay_open/prepay_yrs*MAX(0,MIN(D27+E27+F27,prepay_yrs)-MIN(D27+E27,prepay_yrs))+D18/prepay_yrs*MAX(0,MIN(2,prepay_yrs)-MIN(1,prepay_yrs))+E18/prepay_yrs*MAX(0,MIN(1,prepay_yrs)-MIN(0,prepay_yrs)) -> 10.049235 | G19: =prepay_open/prepay_yrs*MAX(0,MIN(D27+E27+F27+G27,prepay_yrs)-MIN(D27+E27+F27,prepay_yrs))+D18/prepay_yrs*MAX(0,MIN(3,prepay_yrs)-MIN(2,prepay_yrs))+E18/prepay_yrs*MAX(0,MIN(2,prepay_yrs)-MIN(1,prepay_yrs))+F18/prepay_yrs*MAX(0,MIN(1,prepay_yrs)-MIN(0,prepay_yrs)) -> 10.58297 | H19: =prepay_open/prepay_yrs*MAX(0,MIN(D27+E27+F27+G27+H27,prepay_yrs)-MIN(D27+E27+F27+G27,prepay_yrs))+D18/prepay_yrs*MAX(0,MIN(4,prepay_yrs)-MIN(3,prepay_yrs))+E18/prepay_yrs*MAX(0,MIN(3,prepay_yrs)-MIN(2,prepay_yrs))+F18/prepay_yrs*MAX(0,MIN(2,prepay_yrs)-MIN(1,prepay_yrs))+G18/prepay_yrs*MAX(0,MIN(1,prepay_yrs)-MIN(0,prepay_yrs)) -> 11.265091 | I19: =prepay_open/prepay_yrs*MAX(0,MIN(D27+E27+F27+G27+H27+I27,prepay_yrs)-MIN(D27+E27+F27+G27+H27,prepay_yrs))+D18/prepay_yrs*MAX(0,MIN(5,prepay_yrs)-MIN(4,prepay_yrs))+E18/prepay_yrs*MAX(0,MIN(4,prepay_yrs)-MIN(3,prepay_yrs))+F18/prepay_yrs*MAX(0,MIN(3,prepay_yrs)-MIN(2,prepay_yrs))+G18/prepay_yrs*MAX(0,MIN(2,prepay_yrs)-MIN(1,prepay_yrs))+H18/prepay_yrs*MAX(0,MIN(1,prepay_yrs)-MIN(0,prepay_yrs)) -> 9.7203569 | J19: 期初餘額自 FY27Q2 起、各年新流入自次年起，皆依 prepay_yrs 年直線（一般化）
A20: 營運現金流 | B20: US$B | C20: =Q!L28 -> 31.977 | D20: =cfo_q1+(D15-Q!I27)+(D16-Q!I24)+(D17-sbc_q1)+D18-D19 -> 71.053666 | E20: =E15+E16+E17+E18-E19 -> 81.486076 | F20: =F15+F16+F17+F18-F19 -> 72.116279 | G20: =G15+G16+G17+G18-G19 -> 75.960675 | H20: =H15+H16+H17+H18-H19 -> 80.792685 | I20: =I15+I16+I17+I18-I19 -> 99.801228 | J20: FY2027＝Q1 實績 23.103＋Q2–Q4；營運資金變動除預付外不建模
A21: 資本支出：AI（Thesis） | B21: US$B | D21: =Thesis!E25 -> 87.530786 | E21: =Thesis!F25 -> 80.926364 | F21: =Thesis!G25 -> 10.982201 | G21: =Thesis!H25 -> 14.035418 | H21: =Thesis!I25 -> 17.45917 | I21: =Thesis!J25 -> 62.874208
A22: 資本支出：非 AI | B22: US$B | D22: =capex_g27-D21 -> 4.9692138 | E22: =nonai_cx*(PL!E21-Thesis!F19) -> 5.3066616 | F22: =nonai_cx*(PL!F21-Thesis!G19) -> 5.6460971 | G22: =nonai_cx*(PL!G21-Thesis!H19) -> 5.9762466 | H22: =nonai_cx*(PL!H21-Thesis!I19) -> 6.2853483 | I22: =nonai_cx*(PL!I21-Thesis!J19) -> 6.5618
A23: 資本支出合計 | B23: US$B | C23: =Q!L29 -> 55.663 | D23: =D21+D22 -> 92.5 | E23: =E21+E22 -> 86.233026 | F23: =F21+F22 -> 16.628298 | G23: =G21+G22 -> 20.011665 | H23: =H21+H22 -> 23.744518 | I23: =I21+I22 -> 69.436008 | J23: FY2027＝公司指引中點 92.5（含 Q1 實績 28.499）
A24: 自由現金流 | B24: US$B | C24: =C20-C23 -> -23.686 | D24: =D20-D23 -> -21.446334 | E24: =E20-E23 -> -4.7469497 | F24: =F20-F23 -> 55.487981 | G24: =G20-G23 -> 55.949011 | H24: =H20-H23 -> 57.048167 | I24: =I20-I23 -> 30.36522
A25: 股利（普通股＋特別股） | B25: US$B | C25: =Q!L31 -> 5.787 | D25: =div_q1+dps_q*3*D42+pref27 -> 6.344604 | E25: =dps_q*4*E42+PL!E38 -> 6.372472 | F25: =dps_q*4*F42+PL!F38 -> 6.291472 | G25: =dps_q*4*G42+PL!G38 -> 6.109948 | H25: =dps_q*4*H42+PL!H38 -> 6.109948 | I25: =dps_q*4*I42+PL!I38 -> 6.109948
A26: 自由現金流扣股利 | B26: US$B | C26: =C24-C25 -> -29.473 | D26: =D24-D25 -> -27.790938 | E26: =E24-E25 -> -11.119422 | F26: =F24-F25 -> 49.196509 | G26: =G24-G25 -> 49.839063 | H26: =H24-H25 -> 50.938219 | I26: =I24-I25 -> 24.255272
A27: 瀑布期間長度（FY2027 只計 Q2–Q4） | B27: 年 | D27: 0.75 | E27: 1 | F27: 1 | G27: 1 | H27: 1 | I27: 1
A28: 期初現金（FY2027＝Q1 末） | B28: US$B | D28: =cash_q1 -> 37.077 | E28: =D37 -> 16.247062 | F28: =E37 -> 10 | G28: =F37 -> 59.196509 | H28: =G37 -> 109.03557 | I28: =H37 -> 159.97379
A29: 融資前現金流（FY2027 只計 Q2–Q4） | B29: US$B | D29: =D26-(cfo_q1-capex_q1-div_q1) -> -20.829938 | E29: =E26 -> -11.119422 | F29: =F26 -> 49.196509 | G29: =G26 -> 49.839063 | H29: =H26 -> 50.938219 | I29: =I26 -> 24.255272
A30: 外部融資需求（扣除可動用現金後） | B30: US$B | D30: =MAX(0,-(D29+D28-min_cash)) -> 0 | E30: =MAX(0,-(E29+E28-min_cash)) -> 4.8723598 | F30: =MAX(0,-(F29+F28-min_cash)) -> 0 | G30: =MAX(0,-(G29+G28-min_cash)) -> 0 | H30: =MAX(0,-(H29+H28-min_cash)) -> 0 | I30: =MAX(0,-(I29+I28-min_cash)) -> 0
A31: EBITDA＋租金（槓桿分母） | B31: US$B | D31: =PL!D45+Thesis!E22+rent_on -> 54.303979 | E31: =PL!E45+Thesis!F22+rent_on -> 84.675131 | F31: =PL!F45+Thesis!G22+rent_on -> 103.28133 | G31: =PL!G45+Thesis!H22+rent_on -> 107.86479 | H31: =PL!H45+Thesis!I22+rent_on -> 111.48508 | I31: =PL!I45+Thesis!J22+rent_on -> 117.4311 | J31: EBITDA 已扣 AI 租金；加回 AI 租金與在帳租金
A32: 租賃負債（在帳＋已起租的未起租租約現值，期末） | B32: US$B | D32: =lease_on+MIN(1,(lease_q0+4*0)/lease_q)*lease_unc/lease_term*(1-(1+lease_r)^-lease_term)/lease_r -> 93.276234 | E32: =lease_on+MIN(1,(lease_q0+4*1)/lease_q)*lease_unc/lease_term*(1-(1+lease_r)^-lease_term)/lease_r -> 159.23655 | F32: =lease_on+MIN(1,(lease_q0+4*2)/lease_q)*lease_unc/lease_term*(1-(1+lease_r)^-lease_term)/lease_r -> 225.19686 | G32: =lease_on+MIN(1,(lease_q0+4*3)/lease_q)*lease_unc/lease_term*(1-(1+lease_r)^-lease_term)/lease_r -> 225.19686 | H32: =lease_on+MIN(1,(lease_q0+4*4)/lease_q)*lease_unc/lease_term*(1-(1+lease_r)^-lease_term)/lease_r -> 225.19686 | I32: =lease_on+MIN(1,(lease_q0+4*5)/lease_q)*lease_unc/lease_term*(1-(1+lease_r)^-lease_term)/lease_r -> 225.19686 | J32: 期末已起租比例＝MIN(1,(lease_q0＋4 × 年數)÷ lease_q)；在帳部分持平（判斷）
A33: 投資級債可新增額度 | B33: US$B | D33: =MAX(0,lev_max*D31-D32-debt_q1) -> 26.09167 | E33: =MAX(0,lev_max*E31-E32-(debt_q1+D38)) -> 96.801542 | F33: =MAX(0,lev_max*F31-F32-(debt_q1+E38)) -> 109.69677 | G33: =MAX(0,lev_max*G31-G32-(debt_q1+F38)) -> 130.32234 | H33: =MAX(0,lev_max*H31-H32-(debt_q1+G38)) -> 146.61364 | I33: =MAX(0,lev_max*I31-I32-(debt_q1+H38)) -> 173.37074 | J33: lev_max ×（EBITDA＋租金，年化）− 租賃負債 − 既有借款
A34: 新增投資級債 | B34: US$B | D34: =MIN(D30,D33) -> 0 | E34: =MIN(E30,E33) -> 4.8723598 | F34: =MIN(F30,F33) -> 0 | G34: =MIN(G30,G33) -> 0 | H34: =MIN(H30,H33) -> 0 | I34: =MIN(I30,I33) -> 0
A35: 新股 | B35: US$B | D35: =MIN(D30-D34,eq_cap*px*D42*D27) -> 0 | E35: =MIN(E30-E34,eq_cap*px*E42*E27) -> 0 | F35: =MIN(F30-F34,eq_cap*px*F42*F27) -> 0 | G35: =MIN(G30-G34,eq_cap*px*G42*G27) -> 0 | H35: =MIN(H30-H34,eq_cap*px*H42*H27) -> 0 | I35: =MIN(I30-I34,eq_cap*px*I42*I27) -> 0
A36: 高息債 | B36: US$B | D36: =D30-D34-D35 -> 0 | E36: =E30-E34-E35 -> 0 | F36: =F30-F34-F35 -> 0 | G36: =G30-G34-G35 -> 0 | H36: =H30-H34-H35 -> 0 | I36: =I30-I34-I35 -> 0
A37: 期末現金 | B37: US$B | D37: =D28+D29+D34+D35+D36 -> 16.247062 | E37: =E28+E29+E34+E35+E36 -> 10 | F37: =F28+F29+F34+F35+F36 -> 59.196509 | G37: =G28+G29+G34+G35+G36 -> 109.03557 | H37: =H28+H29+H34+H35+H36 -> 159.97379 | I37: =I28+I29+I34+I35+I36 -> 184.22906
A38: 累計新增投資級債（期末） | B38: US$B | D38: =D34 -> 0 | E38: =D38+E34 -> 4.8723598 | F38: =E38+F34 -> 4.8723598 | G38: =F38+G34 -> 4.8723598 | H38: =G38+H34 -> 4.8723598 | I38: =H38+I34 -> 4.8723598
A39: 累計高息債（期末） | B39: US$B | D39: =D36 -> 0 | E39: =D39+E36 -> 0 | F39: =E39+F36 -> 0 | G39: =F39+G36 -> 0 | H39: =G39+H36 -> 0 | I39: =H39+I36 -> 0
A40: 借款合計（期末） | B40: US$B | D40: =debt_q1+D38+D39 -> 125 | E40: =debt_q1+E38+E39 -> 129.87236 | F40: =debt_q1+F38+F39 -> 129.87236 | G40: =debt_q1+G38+G39 -> 129.87236 | H40: =debt_q1+H38+H39 -> 129.87236 | I40: =debt_q1+I38+I39 -> 129.87236
A41: 調整後槓桿（借款＋租賃負債）÷（EBITDA＋租金） | B41: x | D41: =(D40+D32)/D31 -> 4.0195256 | E41: =(E40+E32)/E31 -> 3.4143308 | F41: =(F40+F32)/F31 -> 3.4378838 | G41: =(G40+G32)/G31 -> 3.291799 | H41: =(H40+H32)/H31 -> 3.1849035 | I41: =(I40+I32)/I31 -> 3.0236386
A42: 期初普通股（十億股） | B42: 十億股 | D42: =sh_out -> 3.023736 | E42: =D44 -> 3.023736 | F42: =E44 -> 3.023736 | G42: =F44 -> 3.054974 | H42: =G44 -> 3.054974 | I42: =H44 -> 3.054974
A43: 新發行股數 | B43: 十億股 | D43: =D35/(px*(1-eq_disc)) -> 0 | E43: =E35/(px*(1-eq_disc)) -> 0 | F43: =F35/(px*(1-eq_disc)) -> 0 | G43: =G35/(px*(1-eq_disc)) -> 0 | H43: =H35/(px*(1-eq_disc)) -> 0 | I43: =I35/(px*(1-eq_disc)) -> 0
A44: 期末普通股 | B44: 十億股 | D44: =D42+D43 -> 3.023736 | E44: =E42+E43 -> 3.023736 | F44: =F42+F43+mcps_sh -> 3.054974 | G44: =G42+G43 -> 3.054974 | H44: =H42+H43 -> 3.054974 | I44: =I42+I43 -> 3.054974 | J44: FY2029 加強制轉換特別股 0.031
A45: 稀釋股數（平均＋選擇權） | B45: 十億股 | D45: =(0.75*(D42+D44)/2+0.25*shd_q1)+opt_dil*0.75 -> 3.043302 | E45: =(E42+E44)/2+opt_dil -> 3.057736 | F45: =(F42+F44)/2+opt_dil -> 3.073355 | G45: =(G42+G44)/2+opt_dil -> 3.088974 | H45: =(H42+H44)/2+opt_dil -> 3.088974 | I45: =(I42+I44)/2+opt_dil -> 3.088974 | J45: FY2027 混合 Q1 實績稀釋加權 3.000
A46: 利息費用 | B46: US$B | D46: =int_q1+r_old*debt_q1*0.75 -> 5.712 | E46: =r_old*debt_q1+r_new*D38+r_junk*D39 -> 5.712 | F46: =r_old*debt_q1+r_new*E38+r_junk*E39 -> 5.9945969 | G46: =r_old*debt_q1+r_new*F38+r_junk*F39 -> 5.9945969 | H46: =r_old*debt_q1+r_new*G38+r_junk*G39 -> 5.9945969 | I46: =r_old*debt_q1+r_new*H38+r_junk*H39 -> 5.9945969 | J46: FY2027＝Q1 實績 1.428＋Q2–Q4；新債以期初餘額計息
A47: 利息收入 | B47: US$B | D47: =ii_q1+r_cash*D28*0.75 -> 1.2418708 | E47: =r_cash*E28 -> 0.54679545 | F47: =r_cash*F28 -> 0.33655036 | G47: =r_cash*G28 -> 1.9922606 | H47: =r_cash*H28 -> 3.6695961 | I47: =r_cash*I28 -> 5.3839236
A49: 情境 B（基準：依 FY27Q1 交付速度、延誤 3 個月）
A50: 淨利 | B50: US$B | C50: =PL!C77 -> 17.087 | D50: =PL!D77 -> 15.128413 | E50: =PL!E77 -> 14.344526 | F50: =PL!F77 -> 19.841569 | G50: =PL!G77 -> 25.494666 | H50: =PL!H77 -> 28.072722 | I50: =PL!I77 -> 32.743436
A51: 折舊與攤銷 | B51: US$B | C51: =PL!C83 -> 9.294 | D51: =PL!D83 -> 20.227974 | E51: =PL!E83 -> 38.768552 | F51: =PL!F83 -> 48.452082 | G51: =PL!G83 -> 51.37541 | H51: =PL!H83 -> 53.042826 | I51: =PL!I83 -> 54.325912
A52: SBC（非現金） | B52: US$B | C52: =PL!C84 -> 4.811 | D52: =PL!D84 -> 5.2998078 | E52: =PL!E84 -> 5.5118001 | F52: =PL!F84 -> 5.7322721 | G52: =PL!G84 -> 5.961563 | H52: =PL!H84 -> 6.2000255 | I52: =PL!I84 -> 6.4480265
A53: 客戶預付流入（AI 資本支出 × 覆蓋比） | B53: US$B | D53: =prepay_cov*Thesis!D60 -> 14.626068 | E53: =prepay_cov*Thesis!F60 -> 19.70508 | F53: =prepay_cov*Thesis!G60 -> 7.8633503 | G53: =prepay_cov*Thesis!H60 -> 3.4106066 | H53: =prepay_cov*Thesis!I60 -> 4.2425783 | I53: =prepay_cov*Thesis!J60 -> 15.278433 | J53: FY2027 只計 Q2–Q4（Q1 實績 11.363 已在營運現金流）
A54: 預付認列（非現金營收，自營運現金扣除） | B54: US$B | D54: =prepay_open/prepay_yrs*MAX(0,MIN(D62,prepay_yrs)-MIN(0,prepay_yrs)) -> 2.39325 | E54: =prepay_open/prepay_yrs*MAX(0,MIN(D62+E62,prepay_yrs)-MIN(D62,prepay_yrs))+D53/prepay_yrs*MAX(0,MIN(1,prepay_yrs)-MIN(0,prepay_yrs)) -> 6.1162136 | F54: =prepay_open/prepay_yrs*MAX(0,MIN(D62+E62+F62,prepay_yrs)-MIN(D62+E62,prepay_yrs))+D53/prepay_yrs*MAX(0,MIN(2,prepay_yrs)-MIN(1,prepay_yrs))+E53/prepay_yrs*MAX(0,MIN(1,prepay_yrs)-MIN(0,prepay_yrs)) -> 10.05723 | G54: =prepay_open/prepay_yrs*MAX(0,MIN(D62+E62+F62+G62,prepay_yrs)-MIN(D62+E62+F62,prepay_yrs))+D53/prepay_yrs*MAX(0,MIN(3,prepay_yrs)-MIN(2,prepay_yrs))+E53/prepay_yrs*MAX(0,MIN(2,prepay_yrs)-MIN(1,prepay_yrs))+F53/prepay_yrs*MAX(0,MIN(1,prepay_yrs)-MIN(0,prepay_yrs)) -> 11.6299 | H54: =prepay_open/prepay_yrs*MAX(0,MIN(D62+E62+F62+G62+H62,prepay_yrs)-MIN(D62+E62+F62+G62,prepay_yrs))+D53/prepay_yrs*MAX(0,MIN(4,prepay_yrs)-MIN(3,prepay_yrs))+E53/prepay_yrs*MAX(0,MIN(3,prepay_yrs)-MIN(2,prepay_yrs))+F53/prepay_yrs*MAX(0,MIN(2,prepay_yrs)-MIN(1,prepay_yrs))+G53/prepay_yrs*MAX(0,MIN(1,prepay_yrs)-MIN(0,prepay_yrs)) -> 12.312021 | I54: =prepay_open/prepay_yrs*MAX(0,MIN(D62+E62+F62+G62+H62+I62,prepay_yrs)-MIN(D62+E62+F62+G62+H62,prepay_yrs))+D53/prepay_yrs*MAX(0,MIN(5,prepay_yrs)-MIN(4,prepay_yrs))+E53/prepay_yrs*MAX(0,MIN(4,prepay_yrs)-MIN(3,prepay_yrs))+F53/prepay_yrs*MAX(0,MIN(3,prepay_yrs)-MIN(2,prepay_yrs))+G53/prepay_yrs*MAX(0,MIN(2,prepay_yrs)-MIN(1,prepay_yrs))+H53/prepay_yrs*MAX(0,MIN(1,prepay_yrs)-MIN(0,prepay_yrs)) -> 10.767287 | J54: 期初餘額自 FY27Q2 起、各年新流入自次年起，皆依 prepay_yrs 年直線（一般化）
A55: 營運現金流 | B55: US$B | C55: =Q!L28 -> 31.977 | D55: =cfo_q1+(D50-Q!I27)+(D51-Q!I24)+(D52-sbc_q1)+D53-D54 -> 66.747013 | E55: =E50+E51+E52+E53-E54 -> 72.213744 | F55: =F50+F51+F52+F53-F54 -> 71.832044 | G55: =G50+G51+G52+G53-G54 -> 74.612346 | H55: =H50+H51+H52+H53-H54 -> 79.246131 | I55: =I50+I51+I52+I53-I54 -> 98.028521 | J55: FY2027＝Q1 實績 23.103＋Q2–Q4；營運資金變動除預付外不建模
A56: 資本支出：AI（Thesis） | B56: US$B | D56: =Thesis!E60 -> 87.530786 | E56: =Thesis!F60 -> 81.090864 | F56: =Thesis!G60 -> 32.359466 | G56: =Thesis!H60 -> 14.035418 | H56: =Thesis!I60 -> 17.45917 | I56: =Thesis!J60 -> 62.874208
A57: 資本支出：非 AI | B57: US$B | D57: =capex_g27-D56 -> 4.9692138 | E57: =nonai_cx*(PL!E61-Thesis!F54) -> 5.3066616 | F57: =nonai_cx*(PL!F61-Thesis!G54) -> 5.6460971 | G57: =nonai_cx*(PL!G61-Thesis!H54) -> 5.9762466 | H57: =nonai_cx*(PL!H61-Thesis!I54) -> 6.2853483 | I57: =nonai_cx*(PL!I61-Thesis!J54) -> 6.5618
A58: 資本支出合計 | B58: US$B | C58: =Q!L29 -> 55.663 | D58: =D56+D57 -> 92.5 | E58: =E56+E57 -> 86.397526 | F58: =F56+F57 -> 38.005563 | G58: =G56+G57 -> 20.011665 | H58: =H56+H57 -> 23.744518 | I58: =I56+I57 -> 69.436008 | J58: FY2027＝公司指引中點 92.5（含 Q1 實績 28.499）
A59: 自由現金流 | B59: US$B | C59: =C55-C58 -> -23.686 | D59: =D55-D58 -> -25.752987 | E59: =E55-E58 -> -14.183782 | F59: =F55-F58 -> 33.826481 | G59: =G55-G58 -> 54.600681 | H59: =H55-H58 -> 55.501613 | I59: =I55-I58 -> 28.592513
A60: 股利（普通股＋特別股） | B60: US$B | C60: =Q!L31 -> 5.787 | D60: =div_q1+dps_q*3*D77+pref27 -> 6.344604 | E60: =dps_q*4*E77+PL!E78 -> 6.372472 | F60: =dps_q*4*F77+PL!F78 -> 6.291472 | G60: =dps_q*4*G77+PL!G78 -> 6.109948 | H60: =dps_q*4*H77+PL!H78 -> 6.109948 | I60: =dps_q*4*I77+PL!I78 -> 6.109948
A61: 自由現金流扣股利 | B61: US$B | C61: =C59-C60 -> -29.473 | D61: =D59-D60 -> -32.097591 | E61: =E59-E60 -> -20.556254 | F61: =F59-F60 -> 27.535009 | G61: =G59-G60 -> 48.490733 | H61: =H59-H60 -> 49.391665 | I61: =I59-I60 -> 22.482565
A62: 瀑布期間長度（FY2027 只計 Q2–Q4） | B62: 年 | D62: 0.75 | E62: 1 | F62: 1 | G62: 1 | H62: 1 | I62: 1
A63: 期初現金（FY2027＝Q1 末） | B63: US$B | D63: =cash_q1 -> 37.077 | E63: =D72 -> 11.940409 | F63: =E72 -> 10 | G63: =F72 -> 37.535009 | H63: =G72 -> 86.025742 | I63: =H72 -> 135.41741
A64: 融資前現金流（FY2027 只計 Q2–Q4） | B64: US$B | D64: =D61-(cfo_q1-capex_q1-div_q1) -> -25.136591 | E64: =E61 -> -20.556254 | F64: =F61 -> 27.535009 | G64: =G61 -> 48.490733 | H64: =H61 -> 49.391665 | I64: =I61 -> 22.482565
A65: 外部融資需求（扣除可動用現金後） | B65: US$B | D65: =MAX(0,-(D64+D63-min_cash)) -> 0 | E65: =MAX(0,-(E64+E63-min_cash)) -> 18.615845 | F65: =MAX(0,-(F64+F63-min_cash)) -> 0 | G65: =MAX(0,-(G64+G63-min_cash)) -> 0 | H65: =MAX(0,-(H64+H63-min_cash)) -> 0 | I65: =MAX(0,-(I64+I63-min_cash)) -> 0
A66: EBITDA＋租金（槓桿分母） | B66: US$B | D66: =PL!D85+Thesis!E57+rent_on -> 49.23136 | E66: =PL!E85+Thesis!F57+rent_on -> 73.849075 | F66: =PL!F85+Thesis!G57+rent_on -> 97.312784 | G66: =PL!G85+Thesis!H57+rent_on -> 108.39737 | H66: =PL!H85+Thesis!I57+rent_on -> 111.82956 | I66: =PL!I85+Thesis!J57+rent_on -> 117.56125 | J66: EBITDA 已扣 AI 租金；加回 AI 租金與在帳租金
A67: 租賃負債（在帳＋已起租的未起租租約現值，期末） | B67: US$B | D67: =lease_on+MIN(1,(lease_q0+4*0)/lease_q)*lease_unc/lease_term*(1-(1+lease_r)^-lease_term)/lease_r -> 93.276234 | E67: =lease_on+MIN(1,(lease_q0+4*1)/lease_q)*lease_unc/lease_term*(1-(1+lease_r)^-lease_term)/lease_r -> 159.23655 | F67: =lease_on+MIN(1,(lease_q0+4*2)/lease_q)*lease_unc/lease_term*(1-(1+lease_r)^-lease_term)/lease_r -> 225.19686 | G67: =lease_on+MIN(1,(lease_q0+4*3)/lease_q)*lease_unc/lease_term*(1-(1+lease_r)^-lease_term)/lease_r -> 225.19686 | H67: =lease_on+MIN(1,(lease_q0+4*4)/lease_q)*lease_unc/lease_term*(1-(1+lease_r)^-lease_term)/lease_r -> 225.19686 | I67: =lease_on+MIN(1,(lease_q0+4*5)/lease_q)*lease_unc/lease_term*(1-(1+lease_r)^-lease_term)/lease_r -> 225.19686 | J67: 期末已起租比例＝MIN(1,(lease_q0＋4 × 年數)÷ lease_q)；在帳部分持平（判斷）
A68: 投資級債可新增額度 | B68: US$B | D68: =MAX(0,lev_max*D66-D67-debt_q1) -> 3.2648872 | E68: =MAX(0,lev_max*E66-E67-(debt_q1+D73)) -> 48.084293 | F68: =MAX(0,lev_max*F66-F67-(debt_q1+E73)) -> 69.094825 | G68: =MAX(0,lev_max*G66-G67-(debt_q1+F73)) -> 118.97546 | H68: =MAX(0,lev_max*H66-H67-(debt_q1+G73)) -> 134.4203 | I68: =MAX(0,lev_max*I66-I67-(debt_q1+H73)) -> 160.21293 | J68: lev_max ×（EBITDA＋租金，年化）− 租賃負債 − 既有借款
A69: 新增投資級債 | B69: US$B | D69: =MIN(D65,D68) -> 0 | E69: =MIN(E65,E68) -> 18.615845 | F69: =MIN(F65,F68) -> 0 | G69: =MIN(G65,G68) -> 0 | H69: =MIN(H65,H68) -> 0 | I69: =MIN(I65,I68) -> 0
A70: 新股 | B70: US$B | D70: =MIN(D65-D69,eq_cap*px*D77*D62) -> 0 | E70: =MIN(E65-E69,eq_cap*px*E77*E62) -> 0 | F70: =MIN(F65-F69,eq_cap*px*F77*F62) -> 0 | G70: =MIN(G65-G69,eq_cap*px*G77*G62) -> 0 | H70: =MIN(H65-H69,eq_cap*px*H77*H62) -> 0 | I70: =MIN(I65-I69,eq_cap*px*I77*I62) -> 0
A71: 高息債 | B71: US$B | D71: =D65-D69-D70 -> 0 | E71: =E65-E69-E70 -> 0 | F71: =F65-F69-F70 -> 0 | G71: =G65-G69-G70 -> 0 | H71: =H65-H69-H70 -> 0 | I71: =I65-I69-I70 -> 0
A72: 期末現金 | B72: US$B | D72: =D63+D64+D69+D70+D71 -> 11.940409 | E72: =E63+E64+E69+E70+E71 -> 10 | F72: =F63+F64+F69+F70+F71 -> 37.535009 | G72: =G63+G64+G69+G70+G71 -> 86.025742 | H72: =H63+H64+H69+H70+H71 -> 135.41741 | I72: =I63+I64+I69+I70+I71 -> 157.89997
A73: 累計新增投資級債（期末） | B73: US$B | D73: =D69 -> 0 | E73: =D73+E69 -> 18.615845 | F73: =E73+F69 -> 18.615845 | G73: =F73+G69 -> 18.615845 | H73: =G73+H69 -> 18.615845 | I73: =H73+I69 -> 18.615845
A74: 累計高息債（期末） | B74: US$B | D74: =D71 -> 0 | E74: =D74+E71 -> 0 | F74: =E74+F71 -> 0 | G74: =F74+G71 -> 0 | H74: =G74+H71 -> 0 | I74: =H74+I71 -> 0
A75: 借款合計（期末） | B75: US$B | D75: =debt_q1+D73+D74 -> 125 | E75: =debt_q1+E73+E74 -> 143.61584 | F75: =debt_q1+F73+F74 -> 143.61584 | G75: =debt_q1+G73+G74 -> 143.61584 | H75: =debt_q1+H73+H74 -> 143.61584 | I75: =debt_q1+I73+I74 -> 143.61584
A76: 調整後槓桿（借款＋租賃負債）÷（EBITDA＋租金） | B76: x | D76: =(D75+D67)/D66 -> 4.4336828 | E76: =(E75+E67)/E66 -> 4.1009639 | F76: =(F75+F67)/F66 -> 3.7899718 | G76: =(G75+G67)/G66 -> 3.4024138 | H76: =(H75+H67)/H66 -> 3.2979895 | I76: =(I75+I67)/I66 -> 3.1371961
A77: 期初普通股（十億股） | B77: 十億股 | D77: =sh_out -> 3.023736 | E77: =D79 -> 3.023736 | F77: =E79 -> 3.023736 | G77: =F79 -> 3.054974 | H77: =G79 -> 3.054974 | I77: =H79 -> 3.054974
A78: 新發行股數 | B78: 十億股 | D78: =D70/(px*(1-eq_disc)) -> 0 | E78: =E70/(px*(1-eq_disc)) -> 0 | F78: =F70/(px*(1-eq_disc)) -> 0 | G78: =G70/(px*(1-eq_disc)) -> 0 | H78: =H70/(px*(1-eq_disc)) -> 0 | I78: =I70/(px*(1-eq_disc)) -> 0
A79: 期末普通股 | B79: 十億股 | D79: =D77+D78 -> 3.023736 | E79: =E77+E78 -> 3.023736 | F79: =F77+F78+mcps_sh -> 3.054974 | G79: =G77+G78 -> 3.054974 | H79: =H77+H78 -> 3.054974 | I79: =I77+I78 -> 3.054974 | J79: FY2029 加強制轉換特別股 0.031
A80: 稀釋股數（平均＋選擇權） | B80: 十億股 | D80: =(0.75*(D77+D79)/2+0.25*shd_q1)+opt_dil*0.75 -> 3.043302 | E80: =(E77+E79)/2+opt_dil -> 3.057736 | F80: =(F77+F79)/2+opt_dil -> 3.073355 | G80: =(G77+G79)/2+opt_dil -> 3.088974 | H80: =(H77+H79)/2+opt_dil -> 3.088974 | I80: =(I77+I79)/2+opt_dil -> 3.088974 | J80: FY2027 混合 Q1 實績稀釋加權 3.000
A81: 利息費用 | B81: US$B | D81: =int_q1+r_old*debt_q1*0.75 -> 5.712 | E81: =r_old*debt_q1+r_new*D73+r_junk*D74 -> 5.712 | F81: =r_old*debt_q1+r_new*E73+r_junk*E74 -> 6.791719 | G81: =r_old*debt_q1+r_new*F73+r_junk*F74 -> 6.791719 | H81: =r_old*debt_q1+r_new*G73+r_junk*G74 -> 6.791719 | I81: =r_old*debt_q1+r_new*H73+r_junk*H74 -> 6.791719 | J81: FY2027＝Q1 實績 1.428＋Q2–Q4；新債以期初餘額計息
A82: 利息收入 | B82: US$B | D82: =ii_q1+r_cash*D63*0.75 -> 1.2418708 | E82: =r_cash*E63 -> 0.40185489 | F82: =r_cash*F63 -> 0.33655036 | G82: =r_cash*G63 -> 1.2632421 | H82: =r_cash*H63 -> 2.8951994 | I82: =r_cash*I63 -> 4.5574777
A84: 情境 C（保守：OpenAI 相關容量實現 60%、延誤 6 個月）
A85: 淨利 | B85: US$B | C85: =PL!C117 -> 17.087 | D85: =PL!D117 -> 12.578851 | E85: =PL!E117 -> 2.6284966 | F85: =PL!F117 -> 1.6158363 | G85: =PL!G117 -> 5.6493706 | H85: =PL!H117 -> 10.905119 | I85: =PL!I117 -> 15.803229
A86: 折舊與攤銷 | B86: US$B | C86: =PL!C123 -> 9.294 | D86: =PL!D123 -> 20.227974 | E86: =PL!E123 -> 34.998306 | F86: =PL!F123 -> 41.033192 | G86: =PL!G123 -> 45.390922 | H86: =PL!H123 -> 48.350101 | I86: =PL!I123 -> 49.344014
A87: SBC（非現金） | B87: US$B | C87: =PL!C124 -> 4.811 | D87: =PL!D124 -> 5.2998078 | E87: =PL!E124 -> 5.5118001 | F87: =PL!F124 -> 5.7322721 | G87: =PL!G124 -> 5.961563 | H87: =PL!H124 -> 6.2000255 | I87: =PL!I124 -> 6.4480265
A88: 客戶預付流入（AI 資本支出 × 覆蓋比） | B88: US$B | D88: =prepay_cov*Thesis!D95 -> 14.626068 | E88: =prepay_cov*Thesis!F95 -> 8.7110421 | F88: =prepay_cov*Thesis!G95 -> 8.217943 | G88: =prepay_cov*Thesis!H95 -> 7.2387309 | H88: =prepay_cov*Thesis!I95 -> 4.1812353 | I88: =prepay_cov*Thesis!J95 -> 14.496546 | J88: FY2027 只計 Q2–Q4（Q1 實績 11.363 已在營運現金流）
A89: 預付認列（非現金營收，自營運現金扣除） | B89: US$B | D89: =prepay_open/prepay_yrs*MAX(0,MIN(D97,prepay_yrs)-MIN(0,prepay_yrs)) -> 2.39325 | E89: =prepay_open/prepay_yrs*MAX(0,MIN(D97+E97,prepay_yrs)-MIN(D97,prepay_yrs))+D88/prepay_yrs*MAX(0,MIN(1,prepay_yrs)-MIN(0,prepay_yrs)) -> 6.1162136 | F89: =prepay_open/prepay_yrs*MAX(0,MIN(D97+E97+F97,prepay_yrs)-MIN(D97+E97,prepay_yrs))+D88/prepay_yrs*MAX(0,MIN(2,prepay_yrs)-MIN(1,prepay_yrs))+E88/prepay_yrs*MAX(0,MIN(1,prepay_yrs)-MIN(0,prepay_yrs)) -> 7.858422 | G89: =prepay_open/prepay_yrs*MAX(0,MIN(D97+E97+F97+G97,prepay_yrs)-MIN(D97+E97+F97,prepay_yrs))+D88/prepay_yrs*MAX(0,MIN(3,prepay_yrs)-MIN(2,prepay_yrs))+E88/prepay_yrs*MAX(0,MIN(2,prepay_yrs)-MIN(1,prepay_yrs))+F88/prepay_yrs*MAX(0,MIN(1,prepay_yrs)-MIN(0,prepay_yrs)) -> 9.5020106 | H89: =prepay_open/prepay_yrs*MAX(0,MIN(D97+E97+F97+G97+H97,prepay_yrs)-MIN(D97+E97+F97+G97,prepay_yrs))+D88/prepay_yrs*MAX(0,MIN(4,prepay_yrs)-MIN(3,prepay_yrs))+E88/prepay_yrs*MAX(0,MIN(3,prepay_yrs)-MIN(2,prepay_yrs))+F88/prepay_yrs*MAX(0,MIN(2,prepay_yrs)-MIN(1,prepay_yrs))+G88/prepay_yrs*MAX(0,MIN(1,prepay_yrs)-MIN(0,prepay_yrs)) -> 10.949757 | I89: =prepay_open/prepay_yrs*MAX(0,MIN(D97+E97+F97+G97+H97+I97,prepay_yrs)-MIN(D97+E97+F97+G97+H97,prepay_yrs))+D88/prepay_yrs*MAX(0,MIN(5,prepay_yrs)-MIN(4,prepay_yrs))+E88/prepay_yrs*MAX(0,MIN(4,prepay_yrs)-MIN(3,prepay_yrs))+F88/prepay_yrs*MAX(0,MIN(3,prepay_yrs)-MIN(2,prepay_yrs))+G88/prepay_yrs*MAX(0,MIN(2,prepay_yrs)-MIN(1,prepay_yrs))+H88/prepay_yrs*MAX(0,MIN(1,prepay_yrs)-MIN(0,prepay_yrs)) -> 9.3927539 | J89: 期初餘額自 FY27Q2 起、各年新流入自次年起，皆依 prepay_yrs 年直線（一般化）
A90: 營運現金流 | B90: US$B | C90: =Q!L28 -> 31.977 | D90: =cfo_q1+(D85-Q!I27)+(D86-Q!I24)+(D87-sbc_q1)+D88-D89 -> 64.197451 | E90: =E85+E86+E87+E88-E89 -> 45.733431 | F90: =F85+F86+F87+F88-F89 -> 48.740821 | G90: =G85+G86+G87+G88-G89 -> 54.738576 | H90: =H85+H86+H87+H88-H89 -> 58.686724 | I90: =I85+I86+I87+I88-I89 -> 76.699062 | J90: FY2027＝Q1 實績 23.103＋Q2–Q4；營運資金變動除預付外不建模
A91: 資本支出：AI（Thesis） | B91: US$B | D91: =Thesis!E95 -> 87.530786 | E91: =Thesis!F95 -> 35.84791 | F91: =Thesis!G95 -> 33.818695 | G91: =Thesis!H95 -> 29.789016 | H91: =Thesis!I95 -> 17.20673 | I91: =Thesis!J95 -> 59.656568
A92: 資本支出：非 AI | B92: US$B | D92: =capex_g27-D91 -> 4.9692138 | E92: =nonai_cx*(PL!E101-Thesis!F89) -> 5.3066616 | F92: =nonai_cx*(PL!F101-Thesis!G89) -> 5.6460971 | G92: =nonai_cx*(PL!G101-Thesis!H89) -> 5.9762466 | H92: =nonai_cx*(PL!H101-Thesis!I89) -> 6.2853483 | I92: =nonai_cx*(PL!I101-Thesis!J89) -> 6.5618
A93: 資本支出合計 | B93: US$B | C93: =Q!L29 -> 55.663 | D93: =D91+D92 -> 92.5 | E93: =E91+E92 -> 41.154572 | F93: =F91+F92 -> 39.464793 | G93: =G91+G92 -> 35.765263 | H93: =H91+H92 -> 23.492078 | I93: =I91+I92 -> 66.218368 | J93: FY2027＝公司指引中點 92.5（含 Q1 實績 28.499）
A94: 自由現金流 | B94: US$B | C94: =C90-C93 -> -23.686 | D94: =D90-D93 -> -28.302549 | E94: =E90-E93 -> 4.5788594 | F94: =F90-F93 -> 9.2760287 | G94: =G90-G93 -> 18.973313 | H94: =H90-H93 -> 35.194646 | I94: =I90-I93 -> 10.480694
A95: 股利（普通股＋特別股） | B95: US$B | C95: =Q!L31 -> 5.787 | D95: =div_q1+dps_q*3*D112+pref27 -> 6.344604 | E95: =dps_q*4*E112+PL!E118 -> 6.3832103 | F95: =dps_q*4*F112+PL!F118 -> 6.334018 | G95: =dps_q*4*G112+PL!G118 -> 6.152494 | H95: =dps_q*4*H112+PL!H118 -> 6.152494 | I95: =dps_q*4*I112+PL!I118 -> 6.152494
A96: 自由現金流扣股利 | B96: US$B | C96: =C94-C95 -> -29.473 | D96: =D94-D95 -> -34.647153 | E96: =E94-E95 -> -1.8043509 | F96: =F94-F95 -> 2.9420107 | G96: =G94-G95 -> 12.820819 | H96: =H94-H95 -> 29.042152 | I96: =I94-I95 -> 4.3282002
A97: 瀑布期間長度（FY2027 只計 Q2–Q4） | B97: 年 | D97: 0.75 | E97: 1 | F97: 1 | G97: 1 | H97: 1 | I97: 1
A98: 期初現金（FY2027＝Q1 末） | B98: US$B | D98: =cash_q1 -> 37.077 | E98: =D107 -> 10 | F98: =E107 -> 10 | G98: =F107 -> 12.942011 | H98: =G107 -> 25.76283 | I98: =H107 -> 54.804982
A99: 融資前現金流（FY2027 只計 Q2–Q4） | B99: US$B | D99: =D96-(cfo_q1-capex_q1-div_q1) -> -27.686153 | E99: =E96 -> -1.8043509 | F99: =F96 -> 2.9420107 | G99: =G96 -> 12.820819 | H99: =H96 -> 29.042152 | I99: =I96 -> 4.3282002
A100: 外部融資需求（扣除可動用現金後） | B100: US$B | D100: =MAX(0,-(D99+D98-min_cash)) -> 0.60915328 | E100: =MAX(0,-(E99+E98-min_cash)) -> 1.8043509 | F100: =MAX(0,-(F99+F98-min_cash)) -> 0 | G100: =MAX(0,-(G99+G98-min_cash)) -> 0 | H100: =MAX(0,-(H99+H98-min_cash)) -> 0 | I100: =MAX(0,-(I99+I98-min_cash)) -> 0
A101: EBITDA＋租金（槓桿分母） | B101: US$B | D101: =PL!D125+Thesis!E92+rent_on -> 46.228342 | E101: =PL!E125+Thesis!F92+rent_on -> 56.344335 | F101: =PL!F125+Thesis!G92+rent_on -> 67.346881 | G101: =PL!G125+Thesis!H92+rent_on -> 78.666681 | H101: =PL!H125+Thesis!I92+rent_on -> 87.384891 | I101: =PL!I125+Thesis!J92+rent_on -> 93.17066 | J101: EBITDA 已扣 AI 租金；加回 AI 租金與在帳租金
A102: 租賃負債（在帳＋已起租的未起租租約現值，期末） | B102: US$B | D102: =lease_on+MIN(1,(lease_q0+4*0)/lease_q)*lease_unc/lease_term*(1-(1+lease_r)^-lease_term)/lease_r -> 93.276234 | E102: =lease_on+MIN(1,(lease_q0+4*1)/lease_q)*lease_unc/lease_term*(1-(1+lease_r)^-lease_term)/lease_r -> 159.23655 | F102: =lease_on+MIN(1,(lease_q0+4*2)/lease_q)*lease_unc/lease_term*(1-(1+lease_r)^-lease_term)/lease_r -> 225.19686 | G102: =lease_on+MIN(1,(lease_q0+4*3)/lease_q)*lease_unc/lease_term*(1-(1+lease_r)^-lease_term)/lease_r -> 225.19686 | H102: =lease_on+MIN(1,(lease_q0+4*4)/lease_q)*lease_unc/lease_term*(1-(1+lease_r)^-lease_term)/lease_r -> 225.19686 | I102: =lease_on+MIN(1,(lease_q0+4*5)/lease_q)*lease_unc/lease_term*(1-(1+lease_r)^-lease_term)/lease_r -> 225.19686 | J102: 期末已起租比例＝MIN(1,(lease_q0＋4 × 年數)÷ lease_q)；在帳部分持平（判斷）
A103: 投資級債可新增額度 | B103: US$B | D103: =MAX(0,lev_max*D101-D102-debt_q1) -> 0 | E103: =MAX(0,lev_max*E101-E102-(debt_q1+D108)) -> 0 | F103: =MAX(0,lev_max*F101-F102-(debt_q1+E108)) -> 0 | G103: =MAX(0,lev_max*G101-G102-(debt_q1+F108)) -> 3.8032086 | H103: =MAX(0,lev_max*H101-H102-(debt_q1+G108)) -> 43.035154 | I103: =MAX(0,lev_max*I101-I102-(debt_q1+H108)) -> 69.071113 | J103: lev_max ×（EBITDA＋租金，年化）− 租賃負債 − 既有借款
...

Sheet Val
A1: Val — 目標價（約 12 個月後，2027-10）＝DCF（UFCF、WACC）50%＋分部加總 50%（OCI AI 以 AI 模組自身 DCF 計，同業倍數版列對照；SaaS 與 OCI 非 AI × 軟體同業倍數；授權、支援、硬體、服務 × 成熟軟體倍數）；情境權重 A 25%／B 50%／C 25%（判斷預設，Andy 可改）
A2: 評價日 2026-08-31（FY27Q1 資產負債表）。SBC 口徑（F2）：DCF 以 GAAP 營業利益計（SBC 視為現金成本、股數不另計稀釋）；分部加總的 EBITDA 加回 SBC（與同業倍數同口徑）。淨借款含融資租賃 9.185；營業租賃不列（UFCF 已扣租金）。永續期：RONIC＝WACC（F5），AI 折舊＝穩態汰換
A3: 項目 | B3: 單位 | C3: 數值 | F3: 說明
A4: 現價（2026-10-26 收盤） | B4: US$ | C4: =px -> 126.06 | F4: In 頁 px（stockanalysis.com）
A5: 股權成本 ke（CAPM：rf＋β × ERP；β 為 Blume 調整） | B5: % | C5: =rf+beta*erp -> 0.1248235
A6: 稅後債務成本（約 10 年期） | B6: % | C6: =kd*(1-etr) -> 0.049242
A7: 股權市值（現價 × 流通股） | B7: US$B | C7: =px*sh_out -> 381.17216
A8: 負債（借款本金＋融資租賃，FY27Q1 末） | B8: US$B | C8: =debt_q1+finlease_q1 -> 134.185
A9: WACC（＋wacc_adj，敏感度用，基準 0） | B9: % | C9: =(C7*C5+C8*C6)/(C7+C8)+wacc_adj -> 0.10514413 | F9: 修正一（F4）：Blume β、約 10 年期 kd、負債含融資租賃（強制轉換特別股視為股權）
A10: 淨借款（借款＋融資租賃 − 現金，FY27Q1 末） | B10: US$B | C10: =debt_q1+finlease_q1-cash_q1 -> 97.108 | F10: 修正一：含融資租賃（F6）
A11: 完全稀釋股數（流通＋選擇權＋強制轉換特別股） | B11: 十億股 | C11: =sh_out+opt_dil+mcps_sh -> 3.088974
A12: 目標價時點距評價日 | B12: 年 | C12: =(tp_date-val_date)/365.25 -> 1.1663244 | F12: In 頁 val_date → tp_date
A13: FY2028 年底距目標價時點 | B13: 年 | C13: =(fy28_end-tp_date)/365.25 -> 0.58316222 | F13: 分部加總錨定日 → 目標價時點
A14: 永續期新投資報酬率 RONIC | B14: % | C14: =C9+ronic_adj -> 0.10514413 | F14: RONIC＝WACC：永續成長不創造價值（F5）；Sens：WACC＋5pt
A16: 0.1 DCF（無槓桿自由現金流，WACC；SBC 為現金成本）
A17: 項目 | B17: 折現年數 t | C17: 情境 A | D17: 情境 B | E17: 情境 C | F17: 說明
A18: UFCF FY2027（Q2–Q4） | B18: 0.375 | C18: =(PL!D30-Q!I21)*(1-etr)+(PL!D43-Q!I24)-(CF!D23-capex_q1)+CF!D18-CF!D19 -> -17.380074 | D18: =(PL!D70-Q!I21)*(1-etr)+(PL!D83-Q!I24)-(CF!D58-capex_q1)+CF!D53-CF!D54 -> -21.686727 | E18: =(PL!D110-Q!I21)*(1-etr)+(PL!D123-Q!I24)-(CF!D93-capex_q1)+CF!D88-CF!D89 -> -24.236289
A19: UFCF FY2028 | B19: 1.25 | C19: =PL!E30*(1-etr)+PL!E43-CF!E23+CF!E18-CF!E19 -> -5.8734911 | D19: =PL!E70*(1-etr)+PL!E83-CF!E58+CF!E53-CF!E54 -> -15.187269 | E19: =PL!E110*(1-etr)+PL!E123-CF!E93+CF!E88-CF!E89 -> 3.6308161
A20: UFCF FY2029 | B20: 2.25 | C20: =PL!F30*(1-etr)+PL!F43-CF!F23+CF!F18-CF!F19 -> 54.55939 | D20: =PL!F70*(1-etr)+PL!F83-CF!F58+CF!F53-CF!F54 -> 33.574647 | E20: =PL!F110*(1-etr)+PL!F123-CF!F93+CF!F88-CF!F89 -> 8.1075133
A21: UFCF FY2030 | B21: 3.25 | C21: =PL!G30*(1-etr)+PL!G43-CF!G23+CF!G18-CF!G19 -> 53.385431 | D21: =PL!G70*(1-etr)+PL!G83-CF!G58+CF!G53-CF!G54 -> 53.332795 | E21: =PL!G110*(1-etr)+PL!G123-CF!G93+CF!G88-CF!G89 -> 17.491445
A22: UFCF FY2031 | B22: 4.25 | C22: =PL!H30*(1-etr)+PL!H43-CF!H23+CF!H18-CF!H19 -> 52.822067 | D22: =PL!H70*(1-etr)+PL!H83-CF!H58+CF!H53-CF!H54 -> 52.609732 | E22: =PL!H110*(1-etr)+PL!H123-CF!H93+CF!H88-CF!H89 -> 33.107984
A23: UFCF FY2032 | B23: 5.25 | C23: =PL!I30*(1-etr)+PL!I43-CF!I23+CF!I18-CF!I19 -> 24.435655 | D23: =PL!I70*(1-etr)+PL!I83-CF!I58+CF!I53-CF!I54 -> 24.041357 | E23: =PL!I110*(1-etr)+PL!I123-CF!I93+CF!I88-CF!I89 -> 7.316206
A24: 永續期 NOPAT（FY2032 營業利益，AI 折舊改為穩態汰換；稅後） | C24: =(PL!I30+Thesis!J27-Thesis!J6*cx_vr200/life_ai/1000)*(1-etr) -> 26.813635 | D24: =(PL!I70+Thesis!J62-Thesis!J41*cx_vr200/life_ai/1000)*(1-etr) -> 26.924132 | E24: =(PL!I110+Thesis!J97-Thesis!J76*cx_vr200/life_ai/1000)*(1-etr) -> 22.610365 | F24: 穩態 AI 折舊＝穩態汰換資本支出＝已連網 MW × VR200 每 MW 資本支出 ÷ 年限（修正一：取代 FY2032 帳面 AI 折舊）
A25: 永續價值（FY2032 年底，t＝5.75；NOPAT ×(1＋g)×(1 − g ÷ RONIC) ÷ (WACC − g)） | B25: 5.75 | C25: =C24*(1+tp_g)*(1-tp_g/ronic)/(wacc-tp_g) -> 262.66843 | D25: =D24*(1+tp_g)*(1-tp_g/ronic)/(wacc-tp_g) -> 263.75087 | E25: =E24*(1+tp_g)*(1-tp_g/ronic)/(wacc-tp_g) -> 221.49288 | F25: 再投資率＝g ÷ RONIC（成長所需資本支出與 g 一致，F5）
A26: 企業價值（評價日） | C26: =C18/(1+wacc)^$B$18+C19/(1+wacc)^$B$19+C20/(1+wacc)^$B$20+C21/(1+wacc)^$B$21+C22/(1+wacc)^$B$22+C23/(1+wacc)^$B$23+C25/(1+wacc)^$B$25 -> 257.03968 | D26: =D18/(1+wacc)^$B$18+D19/(1+wacc)^$B$19+D20/(1+wacc)^$B$20+D21/(1+wacc)^$B$21+D22/(1+wacc)^$B$22+D23/(1+wacc)^$B$23+D25/(1+wacc)^$B$25 -> 228.11334 | E26: =E18/(1+wacc)^$B$18+E19/(1+wacc)^$B$19+E20/(1+wacc)^$B$20+E21/(1+wacc)^$B$21+E22/(1+wacc)^$B$22+E23/(1+wacc)^$B$23+E25/(1+wacc)^$B$25 -> 149.6014
A27: 其中：永續價值現值占比 | C27: =C25/(1+wacc)^$B$25/C26 -> 0.57510732 | D27: =D25/(1+wacc)^$B$25/D26 -> 0.65070542 | E27: =E25/(1+wacc)^$B$25/E26 -> 0.83323079
A28: 股權價值（企業價值 − 淨借款〔含融資租賃〕） | C28: =C26-netdebt0 -> 159.93168 | D28: =D26-netdebt0 -> 131.00534 | E28: =E26-netdebt0 -> 52.4934
A29: DCF 每股價值（評價日；小於 0 取 0） | C29: =MAX(0,C28/shfd) -> 51.775018 | D29: =MAX(0,D28/shfd) -> 42.410631 | E29: =MAX(0,E28/shfd) -> 16.993798
A30: DCF 情境價值推到 12 個月後（×(1＋ke)^t − 期間股利） | C30: =MAX(0,C29*(1+ke)^t_tp-dps_q*4*t_tp) -> 57.055696 | D30: =MAX(0,D29*(1+ke)^t_tp-dps_q*4*t_tp) -> 46.31431 | E30: =MAX(0,E29*(1+ke)^t_tp-dps_q*4*t_tp) -> 17.160025
A32: 0.2 分部加總（FY2029 EBITDA × 前瞻倍數；OCI AI 以 AI 模組 DCF）
A33: 同業 | B33: 代號 | C33: EV（US$B） | D33: 前瞻 EV/EBITDA | E33: 日期 | F33: 來源與標記
A34: OCI AI 同業（neocloud）：EV ÷ 2027 年共識 EBITDA（修正一起只作對照列）
A35: CoreWeave | B35: CRWV | C35: =ev_crwv -> 80.12 | D35: =ev_crwv/eb_crwv -> 4.8102786 | E35: 2026-10-21 | F35: In 頁 ev_crwv、eb_crwv（MarketScreener，Interested-party）
A36: Nebius | B36: NBIS | C36: =ev_nbis -> 48.79 | D36: =ev_nbis/eb_nbis -> 7.8769777 | E36: 2026-10-21 | F36: In 頁 ev_nbis、eb_nbis（MarketScreener，Interested-party）
A37: 第三家（IREN、WhiteFiber）：EBITDA 共識未找到——不符合「至少 3 家」規格；本版 OCI AI 主值改用 DCF，倍數只作對照
A38: 其餘業務同業（軟體）：NTM EV/EBITDA（SBC 加回口徑）
A39: Microsoft | B39: MSFT | D39: =pm_msft -> 15.59 | E39: 2026-10-07 | F39: oracle/data/oracle_facts_20261007.json val.peer.msft（EV ÷ 共識 EBITDA 時間加權，Derived；2026-10-22 找不到新值）
A40: SAP | B40: SAP | D40: =pm_sap -> 15.02 | E40: 2026-10-07 | F40: oracle/data/oracle_facts_20261007.json val.peer.sap（EV ÷ 共識 EBITDA 時間加權，Derived；2026-10-22 找不到新值）
A41: Salesforce | B41: CRM | D41: =pm_crm -> 10.8 | E41: 2026-10-07 | F41: oracle/data/oracle_facts_20261007.json val.peer.crm（EV ÷ 共識 EBITDA 時間加權，Derived；2026-10-22 找不到新值）
A42: Adobe | B42: ADBE | D42: =pm_adbe -> 6.6 | E42: 2026-10-07 | F42: oracle/data/oracle_facts_20261007.json val.peer.adbe（EV ÷ 共識 EBITDA 時間加權，Derived；2026-10-22 找不到新值）
A43: ServiceNow | B43: NOW | D43: =pm_now -> 20.65 | E43: 2026-10-07 | F43: oracle/data/oracle_facts_20261007.json val.peer.now（EV ÷ 共識 EBITDA 時間加權，Derived；2026-10-22 找不到新值）
A45: 項目 | B45: 單位 | C45: 情境 A | D45: 情境 B | E45: 情境 C | F45: 說明
A46: FY2029 OCI AI EBITDA（租金後） | B46: US$B | C46: =Thesis!G28 -> 54.876979 | D46: =Thesis!G63 -> 48.908432 | E46: =Thesis!G98 -> 18.942529 | F46: Thesis 頁
A47: OCI AI 自由現金流 FY2029（EBITDA − 稅 − AI 資本支出＋預付淨額） | B47: US$B | C47: =Thesis!G28-etr*Thesis!G29-Thesis!G25+CF!F18-CF!F19 -> 34.599467 | D47: =Thesis!G63-etr*Thesis!G64-Thesis!G60+CF!F53-CF!F54 -> 13.614724 | E47: =Thesis!G98-etr*Thesis!G99-Thesis!G95+CF!F88-CF!F89 -> -11.85241
A48: OCI AI 自由現金流 FY2030（EBITDA − 稅 − AI 資本支出＋預付淨額） | B48: US$B | C48: =Thesis!H28-etr*Thesis!H29-Thesis!H25+CF!G18-CF!G19 -> 32.006384 | D48: =Thesis!H63-etr*Thesis!H64-Thesis!H60+CF!G53-CF!G54 -> 31.953747 | E48: =Thesis!H98-etr*Thesis!H99-Thesis!H95+CF!G88-CF!G89 -> -3.8876029
A49: OCI AI 自由現金流 FY2031（EBITDA − 稅 − AI 資本支出＋預付淨額） | B49: US$B | C49: =Thesis!I28-etr*Thesis!I29-Thesis!I25+CF!H18-CF!H19 -> 30.162773 | D49: =Thesis!I63-etr*Thesis!I64-Thesis!I60+CF!H53-CF!H54 -> 29.950438 | E49: =Thesis!I98-etr*Thesis!I99-Thesis!I95+CF!H88-CF!H89 -> 10.44869
A50: OCI AI 自由現金流 FY2032（EBITDA − 稅 − AI 資本支出＋預付淨額） | B50: US$B | C50: =Thesis!J28-etr*Thesis!J29-Thesis!J25+CF!I18-CF!I19 -> 0.70784518 | D50: =Thesis!J63-etr*Thesis!J64-Thesis!J60+CF!I53-CF!I54 -> 0.3135472 | E50: =Thesis!J98-etr*Thesis!J99-Thesis!J95+CF!I88-CF!I89 -> -16.411604
A51: OCI AI 永續價值（FY2032 年底；穩態汰換、RONIC＝WACC） | B51: US$B | C51: =(Thesis!J28-Thesis!J6*cx_vr200/life_ai/1000)*(1-etr)*(1+tp_g)*(1-tp_g/ronic)/(wacc-tp_g) -> 15.570154 | D51: =(Thesis!J63-Thesis!J41*cx_vr200/life_ai/1000)*(1-etr)*(1+tp_g)*(1-tp_g/ronic)/(wacc-tp_g) -> 16.652594 | E51: =(Thesis!J98-Thesis!J76*cx_vr200/life_ai/1000)*(1-etr)*(1+tp_g)*(1-tp_g/ronic)/(wacc-tp_g) -> -25.605395
A52: OCI AI 企業價值（AI 模組 DCF，FY2028 年底；主值） | B52: US$B | C52: =IF(ai_floor=1,MAX(0,C47/(1+wacc)^0.5+C48/(1+wacc)^1.5+C49/(1+wacc)^2.5+C50/(1+wacc)^3.5+C51/(1+wacc)^4),C47/(1+wacc)^0.5+C48/(1+wacc)^1.5+C49/(1+wacc)^2.5+C50/(1+wacc)^3.5+C51/(1+wacc)^4) -> 94.890646 | D52: =IF(ai_floor=1,MAX(0,D47/(1+wacc)^0.5+D48/(1+wacc)^1.5+D49/(1+wacc)^2.5+D50/(1+wacc)^3.5+D51/(1+wacc)^4),D47/(1+wacc)^0.5+D48/(1+wacc)^1.5+D49/(1+wacc)^2.5+D50/(1+wacc)^3.5+D51/(1+wacc)^4) -> 75.166188 | E52: =IF(ai_floor=1,MAX(0,E47/(1+wacc)^0.5+E48/(1+wacc)^1.5+E49/(1+wacc)^2.5+E50/(1+wacc)^3.5+E51/(1+wacc)^4),E47/(1+wacc)^0.5+E48/(1+wacc)^1.5+E49/(1+wacc)^2.5+E50/(1+wacc)^3.5+E51/(1+wacc)^4) -> -35.214286 | F52: 修正一（F3）：同一 WACC；FY2029–FY2032 期中折現到 FY2028 年底
A53: 對照：OCI AI 企業價值（× neocloud 倍數 mult_oci） | B53: US$B | C53: =C46*mult_oci*mult_adj -> 348.11915 | D53: =D46*mult_oci*mult_adj -> 310.25691 | E53: =E46*mult_oci*mult_adj -> 120.16436 | F53: v0.4 原主值；只作對照
A54: FY2029 其餘業務調整後 EBITDA（合併調整後 EBITDA − OCI AI；SBC 加回） | B54: US$B | C54: =PL!F46-C46 -> 35.101608 | D54: =PL!F86-D46 -> 35.101608 | E54: =PL!F126-E46 -> 35.101608 | F54: SBC 加回（與同業倍數同口徑，F2）
A55: 成長型利潤率（split_mode＝0：m_sw；＝1：由 Q1 分部利潤扣授權＋支援 m_ls 後推得） | B55: % | C55: =IF(split_mode=1,((m_sw+m_adj)*(Q!I11-Thesis!C54)-m_ls*(q1_lic+q1_sup))/(q1_saas+Thesis!C66),m_sw+m_adj) -> 0.64521949 | D55: =IF(split_mode=1,((m_sw+m_adj)*(Q!I11-Thesis!C54)-m_ls*(q1_lic+q1_sup))/(q1_saas+Thesis!C66),m_sw+m_adj) -> 0.64521949 | E55: =IF(split_mode=1,((m_sw+m_adj)*(Q!I11-Thesis!C54)-m_ls*(q1_lic+q1_sup))/(q1_saas+Thesis!C66),m_sw+m_adj) -> 0.64521949
A56: 授權＋支援利潤率（split_mode＝0：m_sw；＝1：m_ls） | B56: % | C56: =IF(split_mode=1,m_ls,m_sw+m_adj) -> 0.64521949 | D56: =IF(split_mode=1,m_ls,m_sw+m_adj) -> 0.64521949 | E56: =IF(split_mode=1,m_ls,m_sw+m_adj) -> 0.64521949
A57: 其中成長型（SaaS＋OCI 非 AI）占比（依分部利潤貢獻分攤） | B57: % | C57: =C55*(PL!F13+PL!F12)/(C55*(PL!F13+PL!F12)+C56*(PL!F14+PL!F15)+m_hw*PL!F16+m_svc*PL!F17) -> 0.5417406 | D57: =D55*(PL!F53+PL!F52)/(D55*(PL!F53+PL!F52)+D56*(PL!F54+PL!F55)+m_hw*PL!F56+m_svc*PL!F57) -> 0.5417406 | E57: =E55*(PL!F93+PL!F92)/(E55*(PL!F93+PL!F92)+E56*(PL!F94+PL!F95)+m_hw*PL!F96+m_svc*PL!F97) -> 0.5417406
A58: 成長型企業價值（× 軟體同業中位數 mult_sw） | B58: US$B | C58: =C54*C57*mult_sw*mult_adj -> 285.61981 | D58: =D54*D57*mult_sw*mult_adj -> 285.61981 | E58: =E54*E57*mult_sw*mult_adj -> 285.61981
A59: 傳統業務企業價值（授權、支援、硬體、服務 × mult_leg） | B59: US$B | C59: =C54*(1-C57)*mult_leg*mult_adj -> 139.94508 | D59: =D54*(1-D57)*mult_leg*mult_adj -> 139.94508 | E59: =E54*(1-E57)*mult_leg*mult_adj -> 139.94508 | F59: 修正一：成熟軟體倍數（Salesforce、Adobe 中位數）
A60: 企業價值（FY2028 年底） | B60: US$B | C60: =C52+C58+C59 -> 520.45554 | D60: =D52+D58+D59 -> 500.73108 | E60: =E52+E58+E59 -> 390.35061
A61: 淨借款（FY2028 年底：借款＋融資租賃 − 現金） | B61: US$B | C61: =CF!E40+finlease_q1-CF!E37 -> 129.05736 | D61: =CF!E75+finlease_q1-CF!E72 -> 142.80084 | E61: =CF!E110+finlease_q1-CF!E107 -> 124.185
A62: 完全稀釋股數（FY2028 年底） | B62: 十億股 | C62: =CF!E44+opt_dil+mcps_sh -> 3.088974 | D62: =CF!E79+opt_dil+mcps_sh -> 3.088974 | E62: =CF!E114+opt_dil+mcps_sh -> 3.110247
A63: 分部加總每股價值（FY2028 年底） | B63: US$ | C63: =MAX(0,(C60-C61)/C62) -> 126.70815 | D63: =MAX(0,(D60-D61)/D62) -> 115.8735 | E63: =MAX(0,(E60-E61)/E62) -> 85.577
A64: 分部加總每股價值（折回目標價時點，加回期間股利） | B64: US$ | C64: =(C63+dps_q*4*t_28)/(1+ke)^t_28 -> 119.39699 | D64: =(D63+dps_q*4*t_28)/(1+ke)^t_28 -> 109.28063 | E64: =(E63+dps_q*4*t_28)/(1+ke)^t_28 -> 80.992645 | F64: FY2028 年底 → 目標價時點（Val 頁 t_28）
A65: 對照：分部加總每股（OCI AI 以同業倍數） | B65: US$ | C65: =(MAX(0,(C60-C52+C53-C61)/C62)+dps_q*4*t_28)/(1+ke)^t_28 -> 195.94041 | D65: =(MAX(0,(D60-D52+D53-D61)/D62)+dps_q*4*t_28)/(1+ke)^t_28 -> 180.34154 | E65: =(MAX(0,(E60-E52+E53-E61)/E62)+dps_q*4*t_28)/(1+ke)^t_28 -> 127.63774
A66: OCI AI 占分部加總企業價值 | B66: % | C66: =C52/C60 -> 0.18232229 | D66: =D52/D60 -> 0.15011289 | E66: =E52/E60 -> -0.090211942
A68: 0.3 結論
A69: 項目 | B69: 單位 | C69: 情境 A | D69: 情境 B | E69: 情境 C | F69: 說明
A70: 情境目標價（DCF × w_dcf＋分部加總 ×（1 − w_dcf）） | B70: US$ | C70: =w_dcf*C30+(1-w_dcf)*C64 -> 88.226343 | D70: =w_dcf*D30+(1-w_dcf)*D64 -> 77.79747 | E70: =w_dcf*E30+(1-w_dcf)*E64 -> 49.076335
A71: 項目 | B71: 單位 | C71: 數值 | D71: 對照 | E71: 對照 | F71: 說明
A72: DCF 目標價（情境加權） | B72: US$ | C72: =wA*C30+wB*D30+wC*E30 -> 41.711085
A73: Comparable 目標價（市場主流同業法） | B73: US$ | C73: =wA*C64+wB*D64+wC*E64 -> 104.73772 | F73: 分部加總（OCI AI 以 AI 模組 DCF；SaaS 與 OCI 非 AI × 軟體倍數；傳統業務 × 成熟軟體倍數）情境加權
A74: 目標價（DCF 與 Comparable 加權） | B74: US$ | C74: =w_dcf*C72+(1-w_dcf)*C73 -> 73.224404 | F74: ="DCF 權重 "&TEXT(w_dcf,"0%")&"、分部加總權重 "&TEXT(1-w_dcf,"0%")&"；情境權重 A／B／C "&TEXT(wA,"0%")&"／"&TEXT(wB,"0%")&"／"&TEXT(wC,"0%") -> DCF 權重 50%、分部加總權重 50%；情境權重 A／B／C 25%／50%／25%
A75: 現價（2026-10-26） | B75: US$ | C75: =px -> 126.06
A76: 市場共識目標價 | B76: US$ | C76: =cons_tp -> 237.36 | F76: S&P（43 家平均，2026-10-20）；Interested-party
A77: 上檔空間：加權目標價 | B77: % | C77: =C74/px-1 -> -0.41913054
A78: 上檔空間：Comparable 目標價 | B78: % | C78: =C73/px-1 -> -0.16914387
A79: 上檔空間級距 | B79: — | C79: =IF(C77>0.5,"大於 50%",IF(C77>0.25,"25%–50%",IF(C77>=0,"0%–25%",IF(C77>=-0.25,"0%～−25%",IF(C77>=-0.5,"−25%～−50%","小於 −50%"))))) -> −25%～−50%
A80: 投資建議 | B80: — | C80: =IF(C77>=0.5,"強力買進",IF(C77>=0.25,"買進",IF(C77>-0.25,"中立",IF(C77>-0.5,"放空","強力放空")))) -> 放空 | F80: 五級固定規則：≥ +50% 強力買進、+25%～+50% 買進、−25%～+25% 中立、−50%～−25% 放空、≤ −50% 強力放空
A81: 價格帶（DCF 不如預期～順利） | B81: US$ | C81: =E30 -> 17.160025 | D81: =C30 -> 57.055696 | F81: C＝情境 C 的 DCF 價值（悲觀情境價）、D＝情境 A 的 DCF 價值（皆推到 12 個月後）
A82: 悲觀情境價（情境 C DCF） | B82: US$ | C82: =E30 -> 17.160025
A83: DCF 情境價值推到 12 個月後（A／B／C） | B83: US$ | C83: =C30 -> 57.055696 | D83: =D30 -> 46.31431 | E83: =E30 -> 17.160025
A84: 與市場共識目標價的差距 | B84: % | C84: =C74/cons_tp-1 -> -0.69150487
A85: DCF 永續價值占比（情境 B） | B85: % | C85: =D27 -> 0.65070542
A86: 對照：加權目標價（分部加總的 OCI AI 改用同業倍數） | B86: US$ | C86: =w_dcf*C72+(1-w_dcf)*(wA*C65+wB*D65+wC*E65) -> 106.3882 | F86: v0.4 原口徑；差額＝AI 資本密集度（F3）
A87: 檢查：情境權重合計（應為 1） | B87: x | C87: =ROUND(wA+wB+wC,6) -> 1
A88: 目標價方法 | B88: — | C88: DCF（UFCF、WACC、永續 g、RONIC＝WACC）與分部加總（FY2029 EBITDA × 同業前瞻倍數；OCI AI 以 AI 模組 DCF）各半；情境 A／B／C 權重 25／50／25。偏誤方向：OCI 同業只有兩家（不符合至少三家，只作對照）；傳統業務倍數取成熟軟體兩家；永續價值占 DCF 比例高，對 WACC 與 g 敏感（Sens 頁）

Sheet Recon
A1: Recon — 逐分部、逐營收線對照市場共識與公司指引（校準時未使用）；另列 v0.4 vs v0.3.1。共識不分部（只有合併營收、EBITDA、EPS）：分部層的共識「未找到」，OCI 以公司營收路徑對照
A3: 項目 | B3: 對照值 | C3: 模型 A | D3: 差距 A | E3: 模型 B | F3: 差距 B | G3: 模型 C | H3: 差距 C | I3: 對照來源 | J3: 說明
A4: A. 合併（共識）
A5: 合併營收 FY2027 vs 共識 | B5: =cr2027 -> 90.423 | C5: =PL!D21 -> 93.516059 | D5: =C5/B5-1 -> 0.034206551 | E5: =PL!D61 -> 87.153955 | F5: =E5/B5-1 -> -0.036152808 | G5: =PL!D101 -> 83.43308 | H5: =G5/B5-1 -> -0.07730246 | I5: MarketScreener（S&P 系）
A6: 合併營收 FY2028 vs 共識 | B6: =cr2028 -> 131.711 | C6: =PL!E21 -> 132.44889 | D6: =C6/B6-1 -> 0.0056023105 | E6: =PL!E61 -> 118.99006 | F6: =E6/B6-1 -> -0.096582192 | G6: =PL!E101 -> 97.314677 | H6: =G6/B6-1 -> -0.26114997 | I6: MarketScreener（S&P 系）
A7: 合併營收 FY2029 vs 共識 | B7: =cr2029 -> 183.655 | C7: =PL!F21 -> 157.00772 | D7: =C7/B7-1 -> -0.14509423 | E7: =PL!F61 -> 149.56187 | F7: =E7/B7-1 -> -0.18563681 | G7: =PL!F101 -> 112.50233 | H7: =G7/B7-1 -> -0.38742574 | I7: MarketScreener（S&P 系）
A8: 調整後 EBITDA FY2027 vs 共識（非 GAAP 營業利益＋折舊） | B8: =ce2027 -> 51.942 | C8: =PL!D46 -> 52.889626 | D8: =C8/B8-1 -> 0.018243926 | E8: =PL!D86 -> 47.817008 | F8: =E8/B8-1 -> -0.079415356 | G8: =PL!D126 -> 44.81399 | H8: =G8/B8-1 -> -0.13723018 | I8: 同上 | J8: 模型＝GAAP 營業利益＋D&A＋SBC；共識口徑不含攤銷，略有差異
A9: 調整後 EBITDA FY2028 vs 共識（非 GAAP 營業利益＋折舊） | B9: =ce2028 -> 74.642 | C9: =PL!E46 -> 77.312343 | D9: =C9/B9-1 -> 0.035775335 | E9: =PL!E86 -> 66.486287 | F9: =E9/B9-1 -> -0.10926439 | G9: =PL!E126 -> 48.981547 | H9: =G9/B9-1 -> -0.34378035 | I9: 同上 | J9: 模型＝GAAP 營業利益＋D&A＋SBC；共識口徑不含攤銷，略有差異
A10: 調整後 EBITDA FY2029 vs 共識（非 GAAP 營業利益＋折舊） | B10: =ce2029 -> 107.543 | C10: =PL!F46 -> 89.978587 | D10: =C10/B10-1 -> -0.16332456 | E10: =PL!F86 -> 84.01004 | F10: =E10/B10-1 -> -0.21882373 | G10: =PL!F126 -> 54.044137 | H10: =G10/B10-1 -> -0.49746486 | I10: 同上 | J10: 模型＝GAAP 營業利益＋D&A＋SBC；共識口徑不含攤銷，略有差異
A11: GAAP EPS FY2027 vs 共識 | B11: =cp2027 -> 6.643 | C11: =PL!D41 -> 6.2793854 | D11: =C11/B11-1 -> -0.054736498 | E11: =PL!D81 -> 4.8642603 | F11: =E11/B11-1 -> -0.2677615 | G11: =PL!D121 -> 4.0238364 | H11: =G11/B11-1 -> -0.39427421 | I11: MarketScreener（2026-10-07 值）
A12: GAAP EPS FY2028 vs 共識 | B12: =cp2028 -> 9.144 | C12: =PL!E41 -> 7.6349102 | D12: =C12/B12-1 -> -0.16503607 | E12: =PL!E81 -> 4.5849366 | F12: =E12/B12-1 -> -0.49858524 | G12: =PL!E121 -> 0.75006637 | H12: =G12/B12-1 -> -0.91797174 | I12: MarketScreener（2026-10-07 值）
A13: GAAP EPS FY2029 vs 共識 | B13: =cp2029 -> 13.43 | C13: =PL!F41 -> 8.7452768 | D13: =C13/B13-1 -> -0.34882525 | E13: =PL!F81 -> 6.3766045 | F13: =E13/B13-1 -> -0.52519698 | G13: =PL!F121 -> 0.44329604 | H13: =G13/B13-1 -> -0.9669921 | I13: MarketScreener（2026-10-07 值）
A14: 資本支出 FY2027 vs 共識 | B14: =cx2027 -> 93.961 | C14: =CF!D23 -> 92.5 | D14: =C14/B14-1 -> -0.015549004 | E14: =CF!D58 -> 92.5 | F14: =E14/B14-1 -> -0.015549004 | G14: =CF!D93 -> 92.5 | H14: =G14/B14-1 -> -0.015549004 | I14: MarketScreener（2026-10-07 值） | J14: 模型只建已簽站點（上限 8,778 MW-IT），FY2029 起資本支出低於共識：觀點（見報告第 5 節）
A15: 資本支出 FY2028 vs 共識 | B15: =cx2028 -> 100.962 | C15: =CF!E23 -> 86.233026 | D15: =C15/B15-1 -> -0.14588631 | E15: =CF!E58 -> 86.397526 | F15: =E15/B15-1 -> -0.14425699 | G15: =CF!E93 -> 41.154572 | H15: =G15/B15-1 -> -0.59237563 | I15: MarketScreener（2026-10-07 值） | J15: 模型只建已簽站點（上限 8,778 MW-IT），FY2029 起資本支出低於共識：觀點（見報告第 5 節）
A16: 資本支出 FY2029 vs 共識 | B16: =cx2029 -> 84.848 | C16: =CF!F23 -> 16.628298 | D16: =C16/B16-1 -> -0.80402251 | E16: =CF!F58 -> 38.005563 | F16: =E16/B16-1 -> -0.55207473 | G16: =CF!F93 -> 39.464793 | H16: =G16/B16-1 -> -0.53487657 | I16: MarketScreener（2026-10-07 值） | J16: 模型只建已簽站點（上限 8,778 MW-IT），FY2029 起資本支出低於共識：觀點（見報告第 5 節）
A17: 自由現金流 FY2027 vs 共識（差距以金額計） | B17: =cf2027 -> -37.32 | C17: =CF!D24 -> -21.446334 | D17: =C17-B17 -> 15.873666 | E17: =CF!D59 -> -25.752987 | F17: =E17-B17 -> 11.567013 | G17: =CF!D94 -> -28.302549 | H17: =G17-B17 -> 9.0174507 | I17: MarketScreener（2026-10-07 值）
A18: 自由現金流 FY2028 vs 共識（差距以金額計） | B18: =cf2028 -> -32.56 | C18: =CF!E24 -> -4.7469497 | D18: =C18-B18 -> 27.81305 | E18: =CF!E59 -> -14.183782 | F18: =E18-B18 -> 18.376218 | G18: =CF!E94 -> 4.5788594 | H18: =G18-B18 -> 37.138859 | I18: MarketScreener（2026-10-07 值）
A19: 自由現金流 FY2029 vs 共識（差距以金額計） | B19: =cf2029 -> 6.154 | C19: =CF!F24 -> 55.487981 | D19: =C19-B19 -> 49.333981 | E19: =CF!F59 -> 33.826481 | F19: =E19-B19 -> 27.672481 | G19: =CF!F94 -> 9.2760287 | H19: =G19-B19 -> 3.1220287 | I19: MarketScreener（2026-10-07 值）
A20: FY2027 營收 vs 公司指引下限 90 | B20: =g_rev27 -> 90 | C20: =PL!D21 -> 93.516059 | D20: =C20/B20-1 -> 0.039067321 | E20: =PL!D61 -> 87.153955 | F20: =E20/B20-1 -> -0.031622726 | G20: =PL!D101 -> 83.43308 | H20: =G20/B20-1 -> -0.072965782 | I20: Q1 FY27 新聞稿 | J20: 指引為下限
A21: FY2027 資本支出 vs 公司指引 90–95 | B21: =capex_g27 -> 92.5 | C21: =CF!D23 -> 92.5 | D21: =C21/B21-1 -> 0 | E21: =CF!D58 -> 92.5 | F21: =E21/B21-1 -> 0 | G21: =CF!D93 -> 92.5 | H21: =G21/B21-1 -> 0 | I21: Q1 FY27 法說（二手） | J21: 本版以指引中點為錨（恆等）
A22: B. 逐分部與營收線（共識未分部：未找到；OCI 對照公司路徑）
A23: Cloud Infrastructure（OCI）FY2027 vs 公司 OCI 營收路徑 | B23: =go2027 -> 32 | C23: =PL!D10 -> 42.18858 | D23: =C23/B23-1 -> 0.31839313 | E23: =PL!D50 -> 35.826476 | F23: =E23/B23-1 -> 0.11957737 | G23: =PL!D90 -> 32.105601 | H23: =G23/B23-1 -> 0.0033000288 | I23: Oracle Q4 FY26 新聞稿（Interested-party） | J23: 公司路徑不作校準
A24: Cloud Infrastructure（OCI）FY2028 vs 公司 OCI 營收路徑 | B24: =go2028 -> 73 | C24: =PL!E10 -> 78.801944 | D24: =C24/B24-1 -> 0.079478684 | E24: =PL!E50 -> 65.343121 | F24: =E24/B24-1 -> -0.10488876 | G24: =PL!E90 -> 43.667734 | H24: =G24/B24-1 -> -0.40181186 | I24: Oracle Q4 FY26 新聞稿（Interested-party） | J24: 公司路徑不作校準
A25: Cloud Infrastructure（OCI）FY2029 vs 公司 OCI 營收路徑 | B25: =go2029 -> 114 | C25: =PL!F10 -> 101.04615 | D25: =C25/B25-1 -> -0.11363022 | E25: =PL!F50 -> 93.600308 | F25: =E25/B25-1 -> -0.17894467 | G25: =PL!F90 -> 56.540762 | H25: =G25/B25-1 -> -0.5040284 | I25: Oracle Q4 FY26 新聞稿（Interested-party） | J25: 公司路徑不作校準
A26: Cloud Infrastructure（OCI）FY2030 vs 公司 OCI 營收路徑 | B26: =go2030 -> 144 | C26: =PL!G10 -> 106.01906 | D26: =C26/B26-1 -> -0.26375654 | E26: =PL!G50 -> 106.57734 | F26: =E26/B26-1 -> -0.2598796 | G26: =PL!G90 -> 69.799713 | H26: =G26/B26-1 -> -0.51527977 | I26: Oracle Q4 FY26 新聞稿（Interested-party） | J26: 公司路徑不作校準
A27: Cloud Applications（SaaS） FY2027：共識未找到（列模型值） | C27: =PL!D13 -> 17.606869 | E27: =PL!D53 -> 17.606869 | G27: =PL!D93 -> 17.606869 | I27: 未找到 | J27: 共識不分營收線
A28: Software license FY2027：共識未找到（列模型值） | C28: =PL!D14 -> 4.2582715 | E28: =PL!D54 -> 4.2582715 | G28: =PL!D94 -> 4.2582715 | I28: 未找到 | J28: 共識不分營收線
A29: Software support FY2027：共識未找到（列模型值） | C29: =PL!D15 -> 19.867603 | E29: =PL!D55 -> 19.867603 | G29: =PL!D95 -> 19.867603 | I29: 未找到 | J29: 共識不分營收線
A30: Hardware FY2027：共識未找到（列模型值） | C30: =PL!D16 -> 3.3818726 | E30: =PL!D56 -> 3.3818726 | G30: =PL!D96 -> 3.3818726 | I30: 未找到 | J30: 共識不分營收線
A31: Services FY2027：共識未找到（列模型值） | C31: =PL!D17 -> 6.2128627 | E31: =PL!D57 -> 6.2128627 | G31: =PL!D97 -> 6.2128627 | I31: 未找到 | J31: 共識不分營收線
A32: 分部：Cloud and software FY2027：共識未找到（列模型值） | C32: =PL!D18 -> 83.921324 | E32: =PL!D58 -> 77.559219 | G32: =PL!D98 -> 73.838344 | I32: 未找到 | J32: 共識不分部
A33: 分部：Hardware FY2027：共識未找到（列模型值） | C33: =PL!D19 -> 3.3818726 | E33: =PL!D59 -> 3.3818726 | G33: =PL!D99 -> 3.3818726 | I33: 未找到 | J33: 共識不分部
A34: 分部：Services FY2027：共識未找到（列模型值） | C34: =PL!D20 -> 6.2128627 | E34: =PL!D60 -> 6.2128627 | G34: =PL!D100 -> 6.2128627 | I34: 未找到 | J34: 共識不分部
A35: C. 命題檢查（不為對上而調參數）
A36: Q1 FY27 OCI 非 AI 殘差占比 vs v0.3.1 區間上緣 30% | B36: 0.3 | C36: =Thesis!C31/q1_oci -> 0.34047482 | D36: =C36-B36 -> 0.040474825 | E36: =Thesis!C66/q1_oci -> 0.34047482 | F36: =E36-B36 -> 0.040474825 | G36: =Thesis!C101/q1_oci -> 0.34047482 | H36: =G36-B36 -> 0.040474825 | I36: v0.3.1 E2 | J36: 殘差包含 Oracle 合約價高於 k 的部分
A37: m_sw（Q1 校準）vs FY2024 雲端與軟體分部利潤率 | B37: =Q!B45 -> 0.64128284 | C37: =m_sw -> 0.64521949 | D37: =C37-B37 -> 0.0039366592 | E37: =m_sw -> 0.64521949 | F37: =E37-B37 -> 0.0039366592 | G37: =m_sw -> 0.64521949 | H37: =G37-B37 -> 0.0039366592 | I37: Q 頁 | J37: 兩者接近＝Q1 的 OCI AI 貢獻估計合理
A38: FY2029 OCI AI 營收 vs OpenAI 合約年額 60 | B38: =oai_annual -> 60 | C38: =Thesis!G19 -> 86.431505 | D38: =C38/B38-1 -> 0.44052509 | E38: =Thesis!G54 -> 78.985658 | F38: =E38/B38-1 -> 0.31642763 | G38: =Thesis!G89 -> 41.926112 | H38: =G38/B38-1 -> -0.30123146 | I38: WSJ 轉述（未證實）
A39: FY2029 OCI AI 營業利益率 vs 公司說法：AI 合約毛利率 30–40% 中點 | B39: 0.35 | C39: =Thesis!G30 -> 0.14671122 | D39: =C39-B39 -> -0.20328878 | E39: =Thesis!G65 -> 0.06207544 | F39: =E39-B39 -> -0.28792456 | G39: =Thesis!G100 -> -0.42083425 | H39: =G39-B39 -> -0.77083425 | I39: 2025-10 分析師日（Interested-party） | J39: 口徑不同：模型為營業利益率（含折舊、租金）；外部報導毛利率 13.9%（The Information）
A40: FY2029 AI 增量 ROIC vs WACC | B40: =wacc -> 0.10514413 | C40: =Thesis!G37 -> 0.043464854 | D40: =C40-B40 -> -0.061679278 | E40: =Thesis!G72 -> 0.016795097 | F40: =E40-B40 -> -0.088349034 | G40: =Thesis!G107 -> -0.073933894 | H40: =G40-B40 -> -0.17907802 | I40: Val 頁 | J40: 低於 WACC＝AI 擴張摧毀價值
A41: D. v0.4 vs v0.3.1（目標價與主要差異來源）
A42: 情境目標價 vs v0.3.1（A 對積極、B 對基準、C 對保守） | C42: =Val!C70 -> 88.226343 | E42: =Val!D70 -> 77.79747 | G42: =Val!E70 -> 49.076335 | I42: v0.3.1 交接檔
A43: v0.3.1 情境目標價（積極／基準／保守） | C43: =tp_v031_hi -> 91.9 | E43: =tp_v031 -> 84.2 | G43: =tp_v031_lo -> 77.4 | J43: v0.3.1：DCF 45%＋分部 EV/EBITDA 55%（OCI 6x、傳統事業 15.02x，錨定 FY29）
A44: 差異來源（定性；數字拆解見報告第 6 節） | J44: (1) 營收結構：SaaS、授權、支援、硬體、服務各自路徑，OCI 拆 AI／非 AI；(2) AI 折舊與租金進分部利潤與 EPS；(3) 評價法：DCF 50%＋分部加總 50%、OCI 倍數改為同業中位數、情境權重 25／50／25；(4) 市場資料：現價 129.13 → 126.06

Sheet Sens
A1: Sens — 一次動一個輸入（低／高），以完整模型重算加權目標價與 FY2029 指標（scripts/sens_v04.py 建置時以 LibreOffice 重算整本活頁簿；數值寫入此頁）
A2: 重算日期 2026-10-30；基準加權目標價 73.2244（應等於 Val 頁加權目標價，見下方檢查列）
A3: 輸入 | B3: 低／高設定 | C3: 低：加權目標價 | D3: 低：相對基準 | E3: 高：加權目標價 | F3: 高：相對基準 | G3: 最大絕對變動 | H3: 低：FY2029 OCI AI 營業利益率（B） | I3: 高：FY2029 OCI AI 營業利益率（B） | J3: 低：收支關卡（B） | K3: 高：收支關卡（B） | L3: 鍵
A4: 定價倍數 k | B4: k ×0.9／×1.2（1.2 約當 Oracle 自身合約） | C4: 59.978325 | D4: =C4/Val!$C$74-1 -> -0.18089706 | E4: 100.04179 | F4: =E4/Val!$C$74-1 -> 0.36623558 | G4: =MAX(ABS(D4),ABS(F4)) -> 0.36623558 | H4: -0.041837849 | I4: 0.21794537 | J4: 53.557192 | K4: 111.32626 | L4: k_adj
A5: 計費比例 | B5: 0.90／1.00 | C5: 66.240609 | D5: =C5/Val!$C$74-1 -> -0.095375237 | E5: 80.236942 | F5: =E5/Val!$C$74-1 -> 0.095767771 | G5: =MAX(ABS(D5),ABS(F5)) -> 0.095767771 | H5: 0.010118796 | I5: 0.10883642 | J5: 62.649342 | K5: 82.891024 | L5: u_bill
A6: 併網速度（三情境） | B6: ×0.8／×1.2 | C6: 67.023399 | D6: =C6/Val!$C$74-1 -> -0.084684957 | E6: 78.596363 | F6: =E6/Val!$C$74-1 -> 0.07336296 | G6: =MAX(ABS(D6),ABS(F6)) -> 0.084684957 | H6: -0.041818668 | I6: 0.14827375 | J6: 43.285708 | K6: 102.2229 | L6: pace_A pace_B pace_C
A7: 合約容量上限（三情境） | B7: ×0.9／×1.1 | C7: 71.130907 | D7: =C7/Val!$C$74-1 -> -0.028590156 | E7: 74.752915 | F7: =E7/Val!$C$74-1 -> 0.02087434 | G7: =MAX(ABS(D7),ABS(F7)) -> 0.028590156 | H7: 0.082867124 | I7: 0.042394525 | J7: 86.101019 | K7: 59.396182 | L7: cap_A cap_B cap_C
A8: 建設延誤（三情境） | B8: 全部 0 月／各加 6 月 | C8: 76.70797 | D8: =C8/Val!$C$74-1 -> 0.047573829 | E8: 65.41049 | F8: =E8/Val!$C$74-1 -> -0.10671188 | G8: =MAX(ABS(D8),ABS(F8)) -> 0.10671188 | H8: 0.091198953 | I8: -0.0039412028 | J8: 84.943519 | K8: 49.051948 | L8: delay_A delay_B delay_C
A9: AI 折舊年限 | B9: 5／7 年 | C9: 56.170548 | D9: =C9/Val!$C$74-1 -> -0.23289853 | E9: 85.401208 | F9: =E9/Val!$C$74-1 -> 0.16629434 | G9: =MAX(ABS(D9),ABS(F9)) -> 0.23289853 | H9: -0.024862781 | I9: 0.12417417 | J9: 77.282228 | K9: 69.535943 | L9: life_ai
A10: AI 每 MW 營運費用 | B10: ×0.8／×1.2 | C10: 78.717396 | D10: =C10/Val!$C$74-1 -> 0.075015856 | E10: 67.732389 | F10: =E10/Val!$C$74-1 -> -0.075002524 | G10: =MAX(ABS(D10),ABS(F10)) -> 0.075015856 | H10: 0.10118687 | I10: 0.022964012 | J10: 80.148661 | K10: 65.378461 | L10: ox_h100 ox_gb200 ox_gb300 ox_vr200
A11: 未起租租約期限 | B11: 15／19 年 | C11: 66.904939 | D11: =C11/Val!$C$74-1 -> -0.086302717 | E11: 78.217058 | F11: =E11/Val!$C$74-1 -> 0.068182923 | G11: =MAX(ABS(D11),ABS(F11)) -> 0.086302717 | H11: 0.037377258 | I11: 0.081574005 | J11: 65.638428 | K11: 78.388666 | L11: lease_term
A12: OCI 其他（非 AI）FY2027 年增 | B12: 10%／30% | C12: 66.846089 | D12: =C12/Val!$C$74-1 -> -0.087106411 | E12: 80.3883 | F12: =E12/Val!$C$74-1 -> 0.097834809 | G12: =MAX(ABS(D12),ABS(F12)) -> 0.097834809 | H12: 0.062015318 | I12: 0.062133537 | J12: 67.237579 | K12: 78.934206 | L12: gna0
A13: SaaS 長期年增 | B13: 5%／10% | C13: 71.158209 | D13: =C13/Val!$C$74-1 -> -0.028217308 | E13: 74.655047 | F13: =E13/Val!$C$74-1 -> 0.019537788 | G13: =MAX(ABS(D13),ABS(F13)) -> 0.028217308 | H13: 0.06207544 | I13: 0.06207544 | J13: 71.387368 | K13: 73.701836 | L13: gLT_saas
A14: Software support 長期年增 | B14: −3%／+1% | C14: 72.156086 | D14: =C14/Val!$C$74-1 -> -0.014589643 | E14: 74.329126 | F14: =E14/Val!$C$74-1 -> 0.015086797 | G14: =MAX(ABS(D14),ABS(F14)) -> 0.015086797 | H14: 0.06207544 | I14: 0.06207544 | J14: 71.920539 | K14: 73.62267 | L14: gLT_sup
A15: 「OCI AI 以外」利潤率 m_sw | B15: −3pt／+3pt | C15: 66.436801 | D15: =C15/Val!$C$74-1 -> -0.092695912 | E15: 80.026823 | F15: =E15/Val!$C$74-1 -> 0.092898244 | G15: =MAX(ABS(D15),ABS(F15)) -> 0.092898244 | H15: 0.06207544 | I15: 0.06207544 | J15: 64.941194 | K15: 80.585928 | L15: m_adj
... A49: 其餘業務（軟體等）前瞻 EV/EBITDA | B49: 10.8x／15.59x | C49: 61.116949 | D49: =C49/Val!$C$74-1 -> -0.16534727 | E49: 74.859771 | F49: =E49/Val!$C$74-1 -> 0.022333636 | G49: =MAX(ABS(D49),ABS(F49)) -> 0.16534727 | H49: 0.06207544 | I49: 0.06207544 | J49: 72.763561 | K49: 72.763561 | L49: mult_sw
A51: 快照檢查：data/sens_v04.json 的基準加權目標價（建置時重算的快照值）− Val 頁現值（應為 0；不為 0＝Sens 已過期，重跑 scripts/sens_v04.py） | C51: =73.2244042213954-Val!C74 -> 0
A53: 說明：tornado 以「低：相對基準」「高：相對基準」兩欄；情境結構（A／B／C）不變，只動一個輸入。容量情境本身的差異見 Val 頁情境目標價。v0.4.2 起依個股模型原則第 9 節：In 頁每個有低／高的鍵都有案例（L 欄「鍵」），IF_HoldEcon 四世代同時一案（he_all）；tp_v031（v0.3.1 目標價）只作對照，不進模型。mult_oci（OCI AI 同業倍數）不列：修正一起分部加總的 OCI AI 以 AI 模組自身 DCF 計，本倍數只進 Val 對照列，重算變動為 0（4.81x／7.88x：73.2244／73.2244）
A55: WACC × 永續成長率 g：加權目標價（完整重算；列＝WACC 調整、欄＝g）
A56: WACC 調整 | C56: g＝2% | D56: g＝3% | E56: g＝4%
A57: WACC −1pt | C57: 79.858758 | D57: 78.345492 | E57: 76.784787
A58: WACC 基準 | C58: 74.657436 | D58: 73.224404 | E58: 71.748381
A59: WACC +1pt | C59: 70.341503 | D59: 68.978912 | E59: 67.577041

Sheet Sources
A1: 來源（每列：編號、文件、日期、網址、標記）。SEC 網站在建置環境被擋（403）：SEC 文件數字取自 v0.1a 事實總帳（oracle/data/oracle_facts_20261007.json，當時直接自 EDGAR 取得）
A2: 編號 | B2: 文件 | C2: 日期 | D2: 網址 | E2: 標記
A3: 1 | B3: Oracle FY2026 10-K（附註 13 分部、經查核財報） | C3: 2026-06-22 | D3: https://www.sec.gov/Archives/edgar/data/1341439/000119312526277521/orcl-20260531.htm | E3: Verified
A4: 2 | B4: Oracle FY27 Q1 10-Q（附註 6 租賃、附註 9 分部） | C4: 2026-09-11 | D4: https://www.sec.gov/Archives/edgar/data/1341439/000119312526389274/orcl-20260831.htm | E4: Interested-party
A5: 3 | B5: Oracle Q1 FY27 財報新聞稿（8-K 附件 99.1） | C5: 2026-09-10 | D5: https://www.sec.gov/Archives/edgar/data/1341439/000119312526387905/orcl-ex99_1.htm | E5: Interested-party
A6: 4 | B6: Oracle Q4 FY26 財報新聞稿（OCI 營收路徑） | C6: 2026-06-10 | D6: https://s23.q4cdn.com/440135859/files/doc_earnings/2026/q4/earnings-result/4q26-pressrelease-final.pdf | E6: Interested-party
A7: 5 | B7: Oracle 事實總帳 v0.1a（434 筆，SEC 一手） | C7: 2026-10-07 | D7: oracle/data/oracle_facts_20261007.json | E7: Verified／Interested-party
A8: 6 | B8: Oracle 事實總帳 v0.3.1 增補（現價、共識、美債、同業 EV） | C8: 2026-10-22 | D8: oracle/data/oracle_facts_20261022.json | E8: Verified／Interested-party
A9: 7 | B9: 市場共識（MarketScreener／S&P、LSEG） | C9: 2026-10-22 | D9: oracle/data/consensus_orcl_20261022.json | E9: Interested-party
A10: 8 | B10: 現價：stockanalysis.com 歷史股價（2026-10-26 收盤 126.06） | C10: 2026-10-27 | D10: https://stockanalysis.com/stocks/orcl/history/ | E10: Verified
A11: 9 | B11: 現價對照：markets/invest_map/data/prices.csv（2026-10-23 收盤 126.16） | C11: 2026-10-23 | D11: markets/invest_map/data/prices.csv | E11: Verified
A12: 10 | B12: Tokenomics v21.4 快照（IF_HoldEcon、IF_CapexIT、IF_OpexGW、IF_DeprLifeIT） | C12: 2026-10-25 | D12: oracle/data/tokenomics_snapshot_v21.4.json（YinchenChang/Tokenomics 3ac70ac；與 microsoft/data 同檔） | E12: Derived
A13: 11 | B13: IREN–Microsoft GB300 五年約 $9.7bn | C13: 2025-11-03 | D13: https://iren.gcs-web.com/news-releases/news-release-details/iren-secures-97bn-ai-cloud-contract-microsoft | E13: Derived
A14: 12 | B14: Silicon Data H100 Index | C14: 2026-10-06 | D14: https://www.silicondata.com/products/silicon-index/h100 | E14: Verified
... A20: 18 | B20: SemiAnalysis | C20: — | D20: 未使用 | E20: —
