Workbook

Sheet 導覽
A1: Oracle 收支與評價模型 — Excel 版 v0.2（更新 2026-10-08；與 HTML v0.2 同步；市價截至 2026-10-06 收盤）
A3: 這個活頁簿在回答什麼
A4: 一句話：客戶預付與投資級債能否把 $664B RPO 變成現金、而不需再發股——Oracle 用客戶預付款支應多少擴張資本支出，剩下的缺口要靠多少債務與新股。
A5: 所有分頁用同一組數字，改任何一個輸入，後面全部會跟著動。
A7: 分頁結構（依模組分組，分頁標籤顏色相同者為同一模組）
A8: 摘要 一頁摘要：結論、與市場共識的差異、現價隱含什麼、驗證點（全部活公式）。
A9: 輸入與假設 所有可調參數（A 情境 → B 產能與收入 → C 利潤率 → D 支出 → E 融資 → F 評價 → G 1Q 實際 → H 情境區間運算表 → I 市場共識 → J 季度追蹤輸入）。
A10: 各期收支 類現金流量：來源（含客戶預付）、用途、融資前缺口、期前融資瀑布。
A11: 季度追蹤 焦點季的模型／共識／指引／實際與差距（由年度模型拆分，只用於追蹤；實際數填在輸入與假設 J 區）。
A12: 運營_產能與收入 已連網 MW → 在役 MW → 營收（MW × 每 MW 年收入 × 利用率）；RPO 排程只作對照與產能瓶頸旗標。
A13: 資產負債_既有債務／新債與新股／租賃承諾 類資產負債表：季報債務明細、每期現金與總債務與股數、租賃承諾。
A14: 損益 類損益表（FY27＝1Q 實際＋第 2–4 季模型）。
... A42: DCF 以融資後股數計每股，並加回新股募得現金的現值；EV/EBITDA 用錨定年末淨負債與錨定年末股數。

Sheet 摘要
A1: 一頁摘要 — 結論、與市場的差異、現價隱含什麼、驗證點（全部依輸入連動）
A2: ="模型端＝目前情境：" & CHOOSE(輸入與假設!$C$5,"保守 OpenAI 相關 60%","基準 已簽約站點依 Q1 速度","積極 依公司時程") & "（預設＝基準）；共識＝data/consensus_orcl_20261007.json（2026-10-07）" -> 模型端＝目前情境：基準 已簽約站點依 Q1 速度（預設＝基準）；共識＝data/consensus_orcl_20261007.json（2026-10-07）
A4: 1｜結論
A5: 結論｜評等代碼（1＝買進、0＝中立、−1＝賣出） | C5: =評價_DCF與目標價!C78 -> 0
A6: 結論｜評等 | C6: =CHOOSE(C5+2,"賣出","中立","買進") -> 中立
A7: 結論｜點位（加權目標價） | B7: US$ | C7: =評價_DCF與目標價!C51 -> 133.90498
A8: 結論｜現價 | B8: US$ | C8: =輸入與假設!$C$175 -> 144.77
A9: 結論｜空間 | B9: % | C9: =C7/C8-1 -> -0.075050216
A10: 結論｜情境區間（下緣／上緣） | B10: US$ | C10: =評價_DCF與目標價!C83 -> 73.988812 | D10: =評價_DCF與目標價!D83 -> 226.60959
A11: 結論｜方法區間（下緣／上緣） | B11: US$ | C11: =評價_DCF與目標價!C85 -> 124.83641 | D11: =評價_DCF與目標價!D85 -> 133.90498
A12: 結論｜賣出門檻價 | B12: US$ | C12: =評價_DCF與目標價!$C$79 -> 123.0545
A13: 結論｜點位 − 賣出門檻 | B13: US$ | C13: =C7-C12 -> 10.85048
A14: 結論｜結論句 | C14: =C6&"：點位 $"&TEXT(C7,"0.0")&"，較現價 $"&TEXT(C8,"0.00")&" "&IF(C9>=0,"高","低")&" "&TEXT(ABS(C9)*100,"0")&"%；情境區間 $"&TEXT(C10,"0.0")&"–$"&TEXT(D10,"0.0")&"，方法區間 $"&TEXT(C11,"0.0")&"–$"&TEXT(D11,"0.0")&"；點位"&IF(C13<0,"低於","高於")&"賣出門檻 $"&TEXT(C12,"0.0")&" 達 $"&TEXT(ABS(C13),"0.0")&"。" -> 中立：點位 $133.9，較現價 $144.77 低 8%；情境區間 $74.0–$226.6，方法區間 $124.8–$133.9；點位高於賣出門檻 $123.1 達 $10.9。
A15: 結論｜情境判斷句 | C15: =評價_DCF與目標價!C91 -> 情境區間上緣 $226.6 不低於現價 $144.77：賣出並非在三個擴張情境下都成立。
A16: 結論｜投資級句 | C16: =IF(OR(輸入與假設!$C$146="ebitda",輸入與假設!$C$146="leaseAdj"),"需失去投資級才能融資的金額："&IF(SUM(各期收支!C85:G85)>0.05,"$"&TEXT(SUM(各期收支!C85:G85),"0.0")&"bn（五期高息債溢出）","$0")&"；投資級上限＝"&IF(輸入與假設!$C$146="leaseAdj","(總債務＋租賃負債) ≤ "&IF(輸入與假設!$C$147=INT(輸入與假設!$C$147),TEXT(輸入與假設!$C$147,"0"),TEXT(輸入與假設!$C$147,"0.0"))&"×(EBITDA＋租金)","總債務 ≤ "&IF(輸入與假設!$C$147=INT(輸入與假設!$C$147),TEXT(輸入與假設!$C$147,"0"),TEXT(輸入與假設!$C$147,"0.0"))&"× 當期 EBITDA")&"，股權每年 ≤ 現市值 "&IF(ROUND(ABS(輸入與假設!$C$154)*100,4)=INT(ROUND(ABS(輸入與假設!$C$154)*100,4)),TEXT(ROUND(ABS(輸入與假設!$C$154)*100,4),"0"),TEXT(ROUND(ABS(輸入與假設!$C$154)*100,4),"0.0"))&"%"&"。","") -> 需失去投資級才能融資的金額：$0；投資級上限＝(總債務＋租賃負債) ≤ 4.5×(EBITDA＋租金)，股權每年 ≤ 現市值 5%。
A17: 結論｜調整後槓桿句 | C17: ="調整後槓桿（(債務＋租賃負債) ÷ (EBITDA＋租金)）路徑 "&TEXT(資產負債_新債與新股!C36,"0.0")&"／"&TEXT(資產負債_新債與新股!D36,"0.0")&"／"&TEXT(資產負債_新債與新股!E36,"0.0")&"／"&TEXT(資產負債_新債與新股!F36,"0.0")&"／"&TEXT(資產負債_新債與新股!G36,"0.0")&"×；上限 "&IF(輸入與假設!$C$147=INT(輸入與假設!$C$147),TEXT(輸入與假設!$C$147,"0"),TEXT(輸入與假設!$C$147,"0.0"))&"×，"&IF(MAX(資產負債_新債與新股!$C$36:$G$36)>輸入與假設!$C$147+0.000000001,CHOOSE(MATCH(MAX(資產負債_新債與新股!$C$36:$G$36),資產負債_新債與新股!$C$36:$G$36,0),"FY27","FY28","FY29","FY30","FY31")&" 超過 "&TEXT(MAX(資產負債_新債與新股!$C$36:$G$36)-輸入與假設!$C$147,"0.0")&"×：需股權或失去投資級。","最小空間 "&TEXT(輸入與假設!$C$147-MAX(資產負債_新債與新股!$C$36:$G$36),"0.0")&"×（"&CHOOSE(MATCH(MAX(資產負債_新債與新股!$C$36:$G$36),資產負債_新債與新股!$C$36:$G$36,0),"FY27","FY28","FY29","FY30","FY31")&"）。") -> 調整後槓桿（(債務＋租賃負債) ÷ (EBITDA＋租金)）路徑 3.6／3.5／3.1／2.8／2.7×；上限 4.5×，最小空間 0.9×（FY27）。
A18: 結論｜延誤句 | C18: =IF(運營_產能與收入!$C$50>0,"建設延誤 "&IF(運營_產能與收入!$C$50=INT(運營_產能與收入!$C$50),TEXT(運營_產能與收入!$C$50,"0"),TEXT(運營_產能與收入!$C$50,"0.0"))&" 個月（GPU 資本支出照原時程）：閒置資本（已支出、尚未產生收入）峰值 $"&TEXT(MAX(運營_產能與收入!$C$55:$G$55),"0.0")&"bn（"&CHOOSE(MATCH(MAX(運營_產能與收入!$C$55:$G$55),運營_產能與收入!$C$55:$G$55,0),"FY27","FY28","FY29","FY30","FY31")&" 末）。","建設延誤：本情境 0 個月（無閒置資本）。") -> 建設延誤 3 個月（GPU 資本支出照原時程）：閒置資本（已支出、尚未產生收入）峰值 $25.9bn（FY27 末）。
A20: 2｜與市場的差異（模型：目前情境 vs 共識；FY27–FY29）
A21: 項目 | B21: 單位 | C21: FY27 | D21: FY28 | E21: FY29
A22: 差異｜營收｜模型 | B22: US$bn | C22: =損益!C29 -> 87.49762 | D22: =損益!D29 -> 125.38525 | E22: =損益!E29 -> 168.28174
A23: 差異｜營收｜共識 | B23: US$bn | C23: =輸入與假設!$C$289 -> 90.449 | D23: =輸入與假設!$D$289 -> 131.711 | E23: =輸入與假設!$E$289 -> 183.569
A24: 差異｜營收｜差距 | B24: % | C24: =C22/C23-1 -> -0.032630324 | D24: =D22/D23-1 -> -0.048027522 | E24: =E22/E23-1 -> -0.083278023
A25: 差異｜調整後 EBITDA｜模型 | B25: US$bn | C25: =輸入與假設!$C$260+損益!C22 -> 51.371417 | D25: =損益!D34 -> 73.113611 | E25: =損益!E34 -> 94.158665
A26: 差異｜調整後 EBITDA｜共識 | B26: US$bn | C26: =輸入與假設!$C$290 -> 51.664 | D26: =輸入與假設!$D$290 -> 74.642 | E26: =輸入與假設!$E$290 -> 107.543
A27: 差異｜調整後 EBITDA｜差距 | B27: % | C27: =C25/C26-1 -> -0.0056631825 | D27: =D25/D26-1 -> -0.02047626 | E27: =E25/E26-1 -> -0.12445566 | I27: FY27 模型＝1Q 實際調整後 EBITDA（輸入與假設 G 區，報導轉述 [Verified]）＋2Q–4Q 模型
A28: 差異｜調整後 EBITDA｜差距（金額） | B28: US$bn | C28: =C25-C26 -> -0.29258266 | D28: =D25-D26 -> -1.528389 | E28: =E25-E26 -> -13.384335 | I28: 與 HTML 一頁摘要、市場共識分頁同一呈現；判斷門檻仍用上一列比例
A29: 差異｜EBITDA 率｜模型 | B29: % | C29: =C25/C22 -> 0.58711788 | D29: =D25/D22 -> 0.58311175 | E29: =E25/E22 -> 0.55952991
A30: 差異｜EBITDA 率｜共識 | B30: % | C30: =輸入與假設!$C$291 -> 0.5712 | D30: =輸入與假設!$D$291 -> 0.5667 | E30: =輸入與假設!$E$291 -> 0.5858
A31: 差異｜EBITDA 率｜差距（百分點） | B31: pt | C31: =C29-C30 -> 0.015917883 | D31: =D29-D30 -> 0.016411751 | E31: =E29-E30 -> -0.026270092 | I31: EBITDA 率以百分點列差距，不納入判斷
A32: 差異｜CapEx（毛額）｜模型 | B32: US$bn | C32: =輸入與假設!$C$243+輸入與假設!C$135 -> 106.09585 | D32: =輸入與假設!D$135 -> 86.020956 | E32: =輸入與假設!E$135 -> 31.20158
A33: 差異｜CapEx（毛額）｜共識 | B33: US$bn | C33: =輸入與假設!$C$296 -> 93.961 | D33: =輸入與假設!$D$296 -> 100.962 | E33: =輸入與假設!$E$296 -> 84.848
A34: 差異｜CapEx（毛額）｜差距 | B34: % | C34: =C32/C33-1 -> 0.12914773 | D34: =D32/D33-1 -> -0.14798681 | E34: =E32/E33-1 -> -0.632265 | I34: 共識 CapEx 口徑未揭露；FY27＝1Q 實際毛額＋2Q–4Q 模型毛額
A35: 差異｜淨負債｜模型 | B35: US$bn | C35: =資產負債_新債與新股!C24 -> 124.09865 | D35: =資產負債_新債與新股!D24 -> 144.11829 | E35: =資產負債_新債與新股!E24 -> 106.58015
A36: 差異｜淨負債｜共識 | B36: US$bn | C36: =輸入與假設!$C$298 -> 117.047 | D36: =輸入與假設!$D$298 -> 147.351 | E36: =輸入與假設!$E$298 -> 146.812
A37: 差異｜淨負債｜差距 | B37: % | C37: =C35/C36-1 -> 0.060246322 | D37: =D35/D36-1 -> -0.02193882 | E37: =E35/E36-1 -> -0.27403654 | I37: 共識淨負債不含租賃、口徑未揭露：只列不判斷
A38: 差異｜淨負債｜差距（金額） | B38: US$bn | C38: =C35-C36 -> 7.0516512 | D38: =D35-D36 -> -3.2327071 | E38: =E35-E36 -> -40.231853 | I38: 與 HTML 一頁摘要、市場共識分頁同一呈現；判斷門檻仍用上一列比例
A39: 差異｜分歧項目（超過門檻者） | C39: =MID(IF(ABS(C24)>輸入與假設!$C$333,"、營收 "&IF(C24<0,"−","+")&TEXT(ABS(C24)*100,"0.0")&"%","")&IF(ABS(C27)>輸入與假設!$C$333,"、EBITDA "&IF(C28<0,"−","+")&"$"&TEXT(ABS(C28),"#,##0.00")&"bn"&"／"&IF(C31<0,"−","+")&TEXT(ABS(C31)*100,"0.0")&"pt","")&IF(ABS(C34)>輸入與假設!$C$333,"、CapEx "&IF(C34<0,"−","+")&TEXT(ABS(C34)*100,"0.0")&"%",""),2,999) -> CapEx +12.9% | D39: =MID(IF(ABS(D24)>輸入與假設!$C$333,"、營收 "&IF(D24<0,"−","+")&TEXT(ABS(D24)*100,"0.0")&"%","")&IF(ABS(D27)>輸入與假設!$C$333,"、EBITDA "&IF(D28<0,"−","+")&"$"&TEXT(ABS(D28),"#,##0.00")&"bn"&"／"&IF(D31<0,"−","+")&TEXT(ABS(D31)*100,"0.0")&"pt","")&IF(ABS(D34)>輸入與假設!$C$333,"、CapEx "&IF(D34<0,"−","+")&TEXT(ABS(D34)*100,"0.0")&"%",""),2,999) -> CapEx −14.8% | E39: =MID(IF(ABS(E24)>輸入與假設!$C$333,"、營收 "&IF(E24<0,"−","+")&TEXT(ABS(E24)*100,"0.0")&"%","")&IF(ABS(E27)>輸入與假設!$C$333,"、EBITDA "&IF(E28<0,"−","+")&"$"&TEXT(ABS(E28),"#,##0.00")&"bn"&"／"&IF(E31<0,"−","+")&TEXT(ABS(E31)*100,"0.0")&"pt","")&IF(ABS(E34)>輸入與假設!$C$333,"、CapEx "&IF(E34<0,"−","+")&TEXT(ABS(E34)*100,"0.0")&"%",""),2,999) -> 營收 −8.3%、EBITDA −$13.38bn／−2.6pt、CapEx −63.2% | I39: 營收、EBITDA、CapEx 任一項差距絕對值超過門檻即列出（與 HTML 判斷句同一規則）
A40: 差異｜分歧起始年（1＝FY27…3＝FY29；0＝無） | C40: =IF(C39<>"",1,IF(D39<>"",2,IF(E39<>"",3,0))) -> 1
A41: 差異｜判斷句 | C41: =CHOOSE(C40+1,"FY27–FY29 營收、EBITDA、CapEx 與共識差距皆在 "&IF(ROUND(ABS(輸入與假設!$C$333)*100,4)=INT(ROUND(ABS(輸入與假設!$C$333)*100,4)),TEXT(ROUND(ABS(輸入與假設!$C$333)*100,4),"0"),TEXT(ROUND(ABS(輸入與假設!$C$333)*100,4),"0.0"))&"%"&" 以內。","分歧始於 FY27（"&C39&"）"&"；FY28 "&IF(D39="","回到 "&IF(ROUND(ABS(輸入與假設!$C$333)*100,4)=INT(ROUND(ABS(輸入與假設!$C$333)*100,4)),TEXT(ROUND(ABS(輸入與假設!$C$333)*100,4),"0"),TEXT(ROUND(ABS(輸入與假設!$C$333)*100,4),"0.0"))&"%"&" 以內",D39)&"；FY29 "&IF(E39="","回到 "&IF(ROUND(ABS(輸入與假設!$C$333)*100,4)=INT(ROUND(ABS(輸入與假設!$C$333)*100,4)),TEXT(ROUND(ABS(輸入與假設!$C$333)*100,4),"0"),TEXT(ROUND(ABS(輸入與假設!$C$333)*100,4),"0.0"))&"%"&" 以內",E39)&"。","FY27 營收、EBITDA、CapEx 與共識差距在 "&IF(ROUND(ABS(輸入與假設!$C$333)*100,4)=INT(ROUND(ABS(輸入與假設!$C$333)*100,4)),TEXT(ROUND(ABS(輸入與假設!$C$333)*100,4),"0"),TEXT(ROUND(ABS(輸入與假設!$C$333)*100,4),"0.0"))&"%"&" 以內；分歧始於 FY28（"&D39&"）"&"；FY29 "&IF(E39="","回到 "&IF(ROUND(ABS(輸入與假設!$C$333)*100,4)=INT(ROUND(ABS(輸入與假設!$C$333)*100,4)),TEXT(ROUND(ABS(輸入與假設!$C$333)*100,4),"0"),TEXT(ROUND(ABS(輸入與假設!$C$333)*100,4),"0.0"))&"%"&" 以內",E39)&"。","FY27–FY28 營收、EBITDA、CapEx 與共識差距在 "&IF(ROUND(ABS(輸入與假設!$C$333)*100,4)=INT(ROUND(ABS(輸入與假設!$C$333)*100,4)),TEXT(ROUND(ABS(輸入與假設!$C$333)*100,4),"0"),TEXT(ROUND(ABS(輸入與假設!$C$333)*100,4),"0.0"))&"%"&" 以內；分歧始於 FY29（"&E39&"）。") -> 分歧始於 FY27（CapEx +12.9%）；FY28 CapEx −14.8%；FY29 營收 −8.3%、EBITDA −$13.38bn／−2.6pt、CapEx −63.2%。
A42: 差異原因｜FY27｜營收 | C42: =IF(ABS(C24)>輸入與假設!$C$333,"觀點","") | D42: =IF(ABS(C24)>輸入與假設!$C$333,"營收＝OCI（在役 MW × 每 MW 年收入，Tokenomics 正向推導；年底已連網 "&IF((輸入與假設!C$43)<0,"−","")&TEXT(ABS((輸入與假設!C$43)),"#,##0")&" MW-IT）＋傳統事業四線（近四季年增率收斂）；共識未揭露 MW 假設","") | I42: C＝類型、D＝原因（需附原因時顯示；EBITDA 以利潤率差、其餘以比例門檻判斷）
A43: 差異原因｜FY27｜EBITDA | C43: =IF(ABS(C31)>輸入與假設!$C$334,"觀點","") | D43: =IF(ABS(C31)>輸入與假設!$C$334,"營收差距 "&IF((C24)<0,"−","+")&TEXT(ABS((C24))*100,"#,##0.0")&"%"&"；EBITDA 率 "&IF((C29)<0,"−","")&TEXT(ABS((C29))*100,"#,##0.0")&"%"&" 對共識 "&IF((C30)<0,"−","")&TEXT(ABS((C30))*100,"#,##0.0")&"%"&"（OCI EBITDA 率由 "&IF((輸入與假設!$C$87)<0,"−","")&TEXT(ABS((輸入與假設!$C$87))*100,"#,##0")&"%"&" 走向穩態 "&IF((輸入與假設!$C$88)<0,"−","")&TEXT(ABS((輸入與假設!$C$88))*100,"#,##0")&"%"&"，取可觀察 neocloud 區間）","")
A44: 差異原因｜FY27｜CapEx | C44: =IF(ABS(C34)>輸入與假設!$C$333,"觀點","") -> 觀點 | D44: =IF(ABS(C34)>輸入與假設!$C$333,"CapEx 依新增 MW 計算：新增 "&IF((輸入與假設!C$125)<0,"−","")&TEXT(ABS((輸入與假設!C$125)),"#,##0")&" MW × 每 MW $"&IF((輸入與假設!C$109)<0,"−","")&TEXT(ABS((輸入與假設!C$109)),"#,##0")&"m（IT 設備，含次年預建）；客戶自帶硬體不建模；共識口徑未揭露","") -> CapEx 依新增 MW 計算：新增 2,833 MW × 每 MW $37m（IT 設備，含次年預建）；客戶自帶硬體不建模；共識口徑未揭露
A45: 差異原因｜FY27｜淨負債 | C45: =IF(ABS(C37)>輸入與假設!$C$333,"觀點","") -> 觀點 | D45: =IF(ABS(C37)>輸入與假設!$C$333,"淨負債隨 CapEx、客戶預付、股利與融資瀑布而定（模型 CapEx 差距 "&IF((C34)<0,"−","+")&TEXT(ABS((C34))*100,"#,##0.0")&"%"&"）；共識淨負債不含租賃","") -> 淨負債隨 CapEx、客戶預付、股利與融資瀑布而定（模型 CapEx 差距 +12.9%）；共識淨負債不含租賃
A46: 差異原因｜FY28｜營收 | C46: =IF(ABS(D24)>輸入與假設!$C$333,"觀點","") | D46: =IF(ABS(D24)>輸入與假設!$C$333,"營收＝OCI（在役 MW × 每 MW 年收入，Tokenomics 正向推導；年底已連網 "&IF((輸入與假設!D$43)<0,"−","")&TEXT(ABS((輸入與假設!D$43)),"#,##0")&" MW-IT）＋傳統事業四線（近四季年增率收斂）；共識未揭露 MW 假設","")
A47: 差異原因｜FY28｜EBITDA | C47: =IF(ABS(D31)>輸入與假設!$C$334,"觀點","") | D47: =IF(ABS(D31)>輸入與假設!$C$334,"營收差距 "&IF((D24)<0,"−","+")&TEXT(ABS((D24))*100,"#,##0.0")&"%"&"；EBITDA 率 "&IF((D29)<0,"−","")&TEXT(ABS((D29))*100,"#,##0.0")&"%"&" 對共識 "&IF((D30)<0,"−","")&TEXT(ABS((D30))*100,"#,##0.0")&"%"&"（OCI EBITDA 率由 "&IF((輸入與假設!$C$87)<0,"−","")&TEXT(ABS((輸入與假設!$C$87))*100,"#,##0")&"%"&" 走向穩態 "&IF((輸入與假設!$C$88)<0,"−","")&TEXT(ABS((輸入與假設!$C$88))*100,"#,##0")&"%"&"，取可觀察 neocloud 區間）","")
A48: 差異原因｜FY28｜CapEx | C48: =IF(ABS(D34)>輸入與假設!$C$333,"觀點","") -> 觀點 | D48: =IF(ABS(D34)>輸入與假設!$C$333,"CapEx 依新增 MW 計算：新增 "&IF((輸入與假設!D$125)<0,"−","")&TEXT(ABS((輸入與假設!D$125)),"#,##0")&" MW × 每 MW $"&IF((輸入與假設!D$109)<0,"−","")&TEXT(ABS((輸入與假設!D$109)),"#,##0")&"m（IT 設備，含次年預建）；客戶自帶硬體不建模；共識口徑未揭露","") -> CapEx 依新增 MW 計算：新增 2,833 MW × 每 MW $38m（IT 設備，含次年預建）；客戶自帶硬體不建模；共識口徑未揭露
A49: 差異原因｜FY28｜淨負債 | C49: =IF(ABS(D37)>輸入與假設!$C$333,"觀點","") | D49: =IF(ABS(D37)>輸入與假設!$C$333,"淨負債隨 CapEx、客戶預付、股利與融資瀑布而定（模型 CapEx 差距 "&IF((D34)<0,"−","+")&TEXT(ABS((D34))*100,"#,##0.0")&"%"&"）；共識淨負債不含租賃","")
A50: 差異原因｜FY29｜營收 | C50: =IF(ABS(E24)>輸入與假設!$C$333,"觀點","") -> 觀點 | D50: =IF(ABS(E24)>輸入與假設!$C$333,"營收＝OCI（在役 MW × 每 MW 年收入，Tokenomics 正向推導；年底已連網 "&IF((輸入與假設!E$43)<0,"−","")&TEXT(ABS((輸入與假設!E$43)),"#,##0")&" MW-IT）＋傳統事業四線（近四季年增率收斂）；共識未揭露 MW 假設","") -> 營收＝OCI（在役 MW × 每 MW 年收入，Tokenomics 正向推導；年底已連網 8,778 MW-IT）＋傳統事業四線（近四季年增率收斂）；共識未揭露 MW 假設
A51: 差異原因｜FY29｜EBITDA | C51: =IF(ABS(E31)>輸入與假設!$C$334,"觀點","") -> 觀點 | D51: =IF(ABS(E31)>輸入與假設!$C$334,"營收差距 "&IF((E24)<0,"−","+")&TEXT(ABS((E24))*100,"#,##0.0")&"%"&"；EBITDA 率 "&IF((E29)<0,"−","")&TEXT(ABS((E29))*100,"#,##0.0")&"%"&" 對共識 "&IF((E30)<0,"−","")&TEXT(ABS((E30))*100,"#,##0.0")&"%"&"（OCI EBITDA 率由 "&IF((輸入與假設!$C$87)<0,"−","")&TEXT(ABS((輸入與假設!$C$87))*100,"#,##0")&"%"&" 走向穩態 "&IF((輸入與假設!$C$88)<0,"−","")&TEXT(ABS((輸入與假設!$C$88))*100,"#,##0")&"%"&"，取可觀察 neocloud 區間）","") -> 營收差距 −8.3%；EBITDA 率 56.0% 對共識 58.6%（OCI EBITDA 率由 65% 走向穩態 47%，取可觀察 neocloud 區間）
A52: 差異原因｜FY29｜CapEx | C52: =IF(ABS(E34)>輸入與假設!$C$333,"觀點","") -> 觀點 | D52: =IF(ABS(E34)>輸入與假設!$C$333,"CapEx 依新增 MW 計算：新增 "&IF((輸入與假設!E$125)<0,"−","")&TEXT(ABS((輸入與假設!E$125)),"#,##0")&" MW × 每 MW $"&IF((輸入與假設!E$109)<0,"−","")&TEXT(ABS((輸入與假設!E$109)),"#,##0")&"m（IT 設備，含次年預建）；客戶自帶硬體不建模；共識口徑未揭露","") -> CapEx 依新增 MW 計算：新增 1,277 MW × 每 MW $38m（IT 設備，含次年預建）；客戶自帶硬體不建模；共識口徑未揭露
A53: 差異原因｜FY29｜淨負債 | C53: =IF(ABS(E37)>輸入與假設!$C$333,"觀點","") -> 觀點 | D53: =IF(ABS(E37)>輸入與假設!$C$333,"淨負債隨 CapEx、客戶預付、股利與融資瀑布而定（模型 CapEx 差距 "&IF((E34)<0,"−","+")&TEXT(ABS((E34))*100,"#,##0.0")&"%"&"）；共識淨負債不含租賃","") -> 淨負債隨 CapEx、客戶預付、股利與融資瀑布而定（模型 CapEx 差距 −63.2%）；共識淨負債不含租賃
A54: 差異｜需附原因項數 | C54: =SUMPRODUCT(--(ABS(C24:E24)>輸入與假設!$C$333))+SUMPRODUCT(--(ABS(C31:E31)>輸入與假設!$C$334))+SUMPRODUCT(--(ABS(C34:E34)>輸入與假設!$C$333))+SUMPRODUCT(--(ABS(C37:E37)>輸入與假設!$C$333)) -> 7 | I54: 營收、EBITDA（利潤率差）、CapEx、淨負債 × FY27–FY29
A55: 差異｜差異原因摘要 | C55: =IF(C54=0,"","需附原因的 "&C54&" 項差距："&MID(IF((COUNTIF(C42,"觀點")+COUNTIF(C43,"觀點")+COUNTIF(C44,"觀點")+COUNTIF(C45,"觀點")+COUNTIF(C46,"觀點")+COUNTIF(C47,"觀點")+COUNTIF(C48,"觀點")+COUNTIF(C49,"觀點")+COUNTIF(C50,"觀點")+COUNTIF(C51,"觀點")+COUNTIF(C52,"觀點")+COUNTIF(C53,"觀點"))>0,"、觀點 "&(COUNTIF(C42,"觀點")+COUNTIF(C43,"觀點")+COUNTIF(C44,"觀點")+COUNTIF(C45,"觀點")+COUNTIF(C46,"觀點")+COUNTIF(C47,"觀點")+COUNTIF(C48,"觀點")+COUNTIF(C49,"觀點")+COUNTIF(C50,"觀點")+COUNTIF(C51,"觀點")+COUNTIF(C52,"觀點")+COUNTIF(C53,"觀點"))&" 項","")&IF((COUNTIF(C42,"拆法")+COUNTIF(C43,"拆法")+COUNTIF(C44,"拆法")+COUNTIF(C45,"拆法")+COUNTIF(C46,"拆法")+COUNTIF(C47,"拆法")+COUNTIF(C48,"拆法")+COUNTIF(C49,"拆法")+COUNTIF(C50,"拆法")+COUNTIF(C51,"拆法")+COUNTIF(C52,"拆法")+COUNTIF(C53,"拆法"))>0,"、拆法 "&(COUNTIF(C42,"拆法")+COUNTIF(C43,"拆法")+COUNTIF(C44,"拆法")+COUNTIF(C45,"拆法")+COUNTIF(C46,"拆法")+COUNTIF(C47,"拆法")+COUNTIF(C48,"拆法")+COUNTIF(C49,"拆法")+COUNTIF(C50,"拆法")+COUNTIF(C51,"拆法")+COUNTIF(C52,"拆法")+COUNTIF(C53,"拆法"))&" 項","")&IF((COUNTIF(C42,"已知限制")+COUNTIF(C43,"已知限制")+COUNTIF(C44,"已知限制")+COUNTIF(C45,"已知限制")+COUNTIF(C46,"已知限制")+COUNTIF(C47,"已知限制")+COUNTIF(C48,"已知限制")+COUNTIF(C49,"已知限制")+COUNTIF(C50,"已知限制")+COUNTIF(C51,"已知限制")+COUNTIF(C52,"已知限制")+COUNTIF(C53,"已知限制"))>0,"、已知限制 "&(COUNTIF(C42,"已知限制")+COUNTIF(C43,"已知限制")+COUNTIF(C44,"已知限制")+COUNTIF(C45,"已知限制")+COUNTIF(C46,"已知限制")+COUNTIF(C47,"已知限制")+COUNTIF(C48,"已知限制")+COUNTIF(C49,"已知限制")+COUNTIF(C50,"已知限制")+COUNTIF(C51,"已知限制")+COUNTIF(C52,"已知限制")+COUNTIF(C53,"已知限制"))&" 項","")&IF((C54-((COUNTIF(C42,"觀點")+COUNTIF(C43,"觀點")+COUNTIF(C44,"觀點")+COUNTIF(C45,"觀點")+COUNTIF(C46,"觀點")+COUNTIF(C47,"觀點")+COUNTIF(C48,"觀點")+COUNTIF(C49,"觀點")+COUNTIF(C50,"觀點")+COUNTIF(C51,"觀點")+COUNTIF(C52,"觀點")+COUNTIF(C53,"觀點"))+(COUNTIF(C42,"拆法")+COUNTIF(C43,"拆法")+COUNTIF(C44,"拆法")+COUNTIF(C45,"拆法")+COUNTIF(C46,"拆法")+COUNTIF(C47,"拆法")+COUNTIF(C48,"拆法")+COUNTIF(C49,"拆法")+COUNTIF(C50,"拆法")+COUNTIF(C51,"拆法")+COUNTIF(C52,"拆法")+COUNTIF(C53,"拆法"))+(COUNTIF(C42,"已知限制")+COUNTIF(C43,"已知限制")+COUNTIF(C44,"已知限制")+COUNTIF(C45,"已知限制")+COUNTIF(C46,"已知限制")+COUNTIF(C47,"已知限制")+COUNTIF(C48,"已知限制")+COUNTIF(C49,"已知限制")+COUNTIF(C50,"已知限制")+COUNTIF(C51,"已知限制")+COUNTIF(C52,"已知限制")+COUNTIF(C53,"已知限制"))))>0,"、未歸類 "&(C54-((COUNTIF(C42,"觀點")+COUNTIF(C43,"觀點")+COUNTIF(C44,"觀點")+COUNTIF(C45,"觀點")+COUNTIF(C46,"觀點")+COUNTIF(C47,"觀點")+COUNTIF(C48,"觀點")+COUNTIF(C49,"觀點")+COUNTIF(C50,"觀點")+COUNTIF(C51,"觀點")+COUNTIF(C52,"觀點")+COUNTIF(C53,"觀點"))+(COUNTIF(C42,"拆法")+COUNTIF(C43,"拆法")+COUNTIF(C44,"拆法")+COUNTIF(C45,"拆法")+COUNTIF(C46,"拆法")+COUNTIF(C47,"拆法")+COUNTIF(C48,"拆法")+COUNTIF(C49,"拆法")+COUNTIF(C50,"拆法")+COUNTIF(C51,"拆法")+COUNTIF(C52,"拆法")+COUNTIF(C53,"拆法"))+(COUNTIF(C42,"已知限制")+COUNTIF(C43,"已知限制")+COUNTIF(C44,"已知限制")+COUNTIF(C45,"已知限制")+COUNTIF(C46,"已知限制")+COUNTIF(C47,"已知限制")+COUNTIF(C48,"已知限制")+COUNTIF(C49,"已知限制")+COUNTIF(C50,"已知限制")+COUNTIF(C51,"已知限制")+COUNTIF(C52,"已知限制")+COUNTIF(C53,"已知限制"))))&" 項",""),2,999)&"；原因見「損益與評價 → 市場共識」。") -> 需附原因的 7 項差距：觀點 7 項；原因見「損益與評價 → 市場共識」。 | I55: 與 HTML 一頁摘要同一句
A57: 3｜現價隱含什麼
A58: 隱含｜共識平均目標價隱含 FY29 EV/EBITDA | B58: x | C58: =(輸入與假設!$C$271*輸入與假設!$C$176+輸入與假設!$E$298)/輸入與假設!$E$290 -> 8.1312725 | I58: ＝（共識平均目標價 × 股數＋共識 FY29 淨負債）÷ 共識 FY29 調整後 EBITDA
A59: 隱含｜現價隱含 FY29 EV/EBITDA | B59: x | C59: =(輸入與假設!$C$175*輸入與假設!$C$176+輸入與假設!$E$298)/輸入與假設!$E$290 -> 5.4813464 | I59: 同一共識 FY29 數字，價格換成現價
A60: 隱含｜模型方法區間上緣 | B60: x | C60: =MAX(輸入與假設!$C$208,輸入與假設!$C$209) -> 6 | I60: 模型 EV/EBITDA 腿（OCI 倍數）錨定 FY29 並折回 2027-08-31，錨定年度與此不同
A61: 隱含｜模型 FY29 傳統事業 EBITDA | B61: US$bn | C61: =輸入與假設!E$83 -> 30.306278 | I61: × 傳統事業 EV/EBITDA 倍數，自共識隱含 EV 扣除
A62: 隱含｜共識平均目標價隱含 FY29 OCI EV/EBITDA | B62: x | C62: =(輸入與假設!$C$271*輸入與假設!$C$176+輸入與假設!$E$298-輸入與假設!E$83*輸入與假設!$C$204)/MAX(輸入與假設!$E$290-輸入與假設!E$83,0.01) -> 5.4282617 | I62: ＝（隱含 EV − 傳統事業 EBITDA × 傳統事業倍數）÷（共識 EBITDA − 傳統事業 EBITDA）
A63: 隱含｜現價隱含 FY29 OCI EV/EBITDA | B63: x | C63: =(輸入與假設!$C$175*輸入與假設!$C$176+輸入與假設!$E$298-輸入與假設!E$83*輸入與假設!$C$204)/MAX(輸入與假設!$E$290-輸入與假設!E$83,0.01) -> 1.7385531 | I63: 同上，價格換成現價
A64: 隱含｜隱含倍數句 | C64: ="共識平均目標價 $"&TEXT(輸入與假設!$C$271,"0.00")&" 隱含 FY29 EV/EBITDA "&TEXT(C58,"0.0")&"x（扣除傳統事業 "&TEXT(輸入與假設!$C$204,"0.0")&"x × 模型 EBITDA $"&TEXT(C61,"0.0")&"bn 後，OCI "&TEXT(C62,"0.0")&"x），OCI 倍數"&IF(ROUND(C62,1)>C60,"高於",IF(ROUND(C62,1)<C60,"低於","等於"))&"模型方法區間上緣 "&IF(C60=INT(C60),TEXT(C60,"0"),TEXT(C60,"0.0"))&"x；現價 $"&TEXT(輸入與假設!$C$175,"0.00")&" 隱含 "&TEXT(C59,"0.0")&"x（OCI "&TEXT(C63,"0.0")&"x）。" -> 共識平均目標價 $237.97 隱含 FY29 EV/EBITDA 8.1x（扣除傳統事業 15.0x × 模型 EBITDA $30.3bn 後，OCI 5.4x），OCI 倍數低於模型方法區間上緣 6x；現價 $144.77 隱含 5.5x（OCI 1.7x）。
A65: 反向 DCF｜FY31 每 MW 年收入（目前／隱含／變動） | C65: =評價_反向DCF!B18 -> 17.4 | D65: =評價_反向DCF!C18 -> 24.3872 | E65: =評價_反向DCF!D18 -> 0.4016 | I65: 快照（預設輸入）：見『評價_反向DCF』；改輸入後請以目標搜尋重算
A66: 反向 DCF｜每 MW 建置成本（目前／隱含／變動） | C66: =評價_反向DCF!B19 -> 37.59 | D66: =評價_反向DCF!C19 -> 14.8903 | E66: =評價_反向DCF!D19 -> -0.6039
A67: 反向 DCF｜穩態 EBITDA 率（目前／隱含／變動 pt） | C67: =評價_反向DCF!B20 -> 0.47 | D67: =評價_反向DCF!C20 -> 0.7625 | E67: =評價_反向DCF!D20 -> 0.2925
A68: 反向 DCF｜加權目標價＝現價所需每 MW 年收入（目前／隱含／變動） | C68: =評價_反向DCF!B21 -> 17.4 | D68: =評價_反向DCF!C21 -> 18.3486 | E68: =評價_反向DCF!D21 -> 0.0545
A70: 4｜驗證點與市場看法（賣方與管理層數字標記 Interested-party）
A71: 驗證｜焦點季 | C71: =季度追蹤!C12 -> Q2 FY27 | I71: 『輸入與假設』J 區選擇；季度層由年度模型拆分，只用於追蹤
A72: 驗證｜營收（模型／共識／指引低／指引高／實際） | B72: US$bn | C72: =季度追蹤!C6 -> 21.03127 | D72: =季度追蹤!D6 -> 21.322 | E72: =季度追蹤!F6 -> 20.875 | F72: =季度追蹤!G6 -> 21.518 | G72: =季度追蹤!I6 -> 待公布 | I72: 共識、指引為 Interested-party
A73: 驗證｜營收｜句 | C73: =INDEX(季度追蹤!$C$129:$H$129,輸入與假設!$C$339) -> 營收：模型 $21.03bn｜共識 $21.32bn（−1.4%）｜指引 $20.88–21.52bn（中點 −0.8%，區間下半部）
A74: 驗證｜調整後 EBITDA（模型／共識／指引低／指引高／實際） | B74: US$bn | C74: =季度追蹤!C7 -> 12.397286 | D74: =季度追蹤!D7 -> 12.359 | E74: =季度追蹤!F7 -> 不適用 | F74: =季度追蹤!G7 -> 不適用 | G74: =季度追蹤!I7 -> 待公布 | I74: 共識、指引為 Interested-party
A75: 驗證｜調整後 EBITDA｜句 | C75: =INDEX(季度追蹤!$C$130:$H$130,輸入與假設!$C$339) -> 調整後 EBITDA：模型 $12.40bn｜共識 $12.36bn（+$0.04bn／+1.0pt）
A76: 驗證｜CapEx（毛額）（模型／共識／指引低／指引高／實際） | B76: US$bn | C76: =季度追蹤!C10 -> 25.865617 | D76: =季度追蹤!D10 -> 不適用 | E76: =季度追蹤!F10 -> 不適用 | F76: =季度追蹤!G10 -> 不適用 | G76: =季度追蹤!I10 -> 待公布 | I76: 共識、指引為 Interested-party
A77: 驗證｜CapEx（毛額）｜句 | C77: =INDEX(季度追蹤!$C$133:$H$133,輸入與假設!$C$339) -> CapEx（毛額）：模型 $25.87bn
A78: 驗證｜評等分布（強力買進／買進／持有／賣出／強力賣出） | B78: 家 | C78: =輸入與假設!$C$282 -> 28 | D78: =輸入與假設!$C$283 -> 7 | E78: =輸入與假設!$C$284 -> 7 | F78: =輸入與假設!$C$285 -> 0 | G78: =輸入與假設!$C$286 -> 1 | I78: 2026-10，合計 43 家 [Interested-party]
A79: 驗證｜目標價（平均／中位數／最低／最高） | B79: US$ | C79: =輸入與假設!$C$271 -> 237.97 | D79: =輸入與假設!$C$272 -> 240 | E79: =輸入與假設!$C$273 -> 110 | F79: =輸入與假設!$C$274 -> 400 | I79: 43 家；S&P Global Market Intelligence（經 StockAnalysis.com），擷取 2026-10-07 [Interested-party]
A81: 來源獨立性：StockAnalysis.com 的目標價、評等、FY27 營收與 EPS 引用 S&P Global Market Intelligence；MarketScreener 的年度與季度預估一般亦屬 S&P Capital IQ 系（與 CRWV、NBIS 共識檔同一判斷），FY27 營收 90.45 對 90.449 幾乎相同，視為同一底層來源的兩個呈現，不算獨立交叉驗證。Yahoo Finance 的營收與 EPS 預估來自 LSEG（獨立於 S&P），FY27 營收 90.48、FY28 131.45 與 MarketScreener 90.449／131.711 一致，可作 FY27–FY28 營收的獨立交叉。MarketBeat 目標價與評等為自行彙整（獨立於 S&P），可作目標價的獨立交叉；Yahoo 目標價 237.97 與 S&P 完全相同，推測同源，不算獨立。
A82: 共識來源：MarketScreener（S&P Capital IQ 系共識）、S&P Global Market Intelligence（經 StockAnalysis.com）；擷取 2026-10-07。逐筆來源、日期與標記見『輸入與假設』I 區。

Sheet 輸入與假設
A1: 輸入（依類別排序；點左側 ＋／− 展開或收合。藍字可改；黃底為最關鍵假設）
A2: A 情境 → B 產能與收入 → C 利潤率 → D 支出（CapEx／折舊／租賃／JV）→ E 融資 → F 評價 → G 參考：1Q27 實際 → H 情境區間運算表 → I 市場共識 → J 季度追蹤輸入。灰底『▸』為明細子區，預設收合
A4: A｜情境與規模（管理層擴張力道）
A5: 情境選擇（1＝保守 OpenAI 相關 60%、2＝基準 已簽約站點依 Q1 速度、3＝積極 依公司時程） | C5: 2 | D5: =CHOOSE(C5,"保守 OpenAI 相關 60%","基準 已簽約站點依 Q1 速度","積極 依公司時程") -> 基準 已簽約站點依 Q1 速度 | I5: 三情境改變擴張力道（已連網 MW 路徑）與每 MW 年收入（Tokenomics 正向推導三情境值）；其餘假設相同（對照表 r1 第 4 節第 1 條）
A6: ▸ 情境路徑明細（已連網 MW、在役比例、表外租金基準）
A7: 已連網 MW 路徑 | B7: 單位 | C7: FY27 | D7: FY28 | E7: FY29 | F7: FY30 | G7: FY31 | I7: FY31 新增 MW
A8: 首期期末已連網 MW（三情境共用） | B8: MW | C8: 4668 | I8: 首期期末＝評價日已連網＋首期剩餘季度依最新季交付速度；推導與來源見 company.json → scenarios.mwPath.note [Derived]
A9: 保守 OpenAI 相關 60%｜合約 MW 上限 | B9: MW | C9: 6284 | D9: 6284 | E9: 6284 | F9: 6284 | G9: 6284 | I9: company.json → scenarios.mwPath.contracted
A10: 保守 OpenAI 相關 60%｜併網速度 | B10: MW／年 | C10: 1000 | I10: company.json → scenarios.mwPath.pace
A11: 保守 OpenAI 相關 60% | B11: MW | C11: =MIN(C9,輸入與假設!$C$8) -> 4668 | D11: =MIN(D9,C11+輸入與假設!$C$10*D$41) -> 5668 | E11: =MIN(E9,D11+輸入與假設!$C$10*E$41) -> 6284 | F11: =MIN(F9,E11+輸入與假設!$C$10*F$41) -> 6284 | G11: =MIN(G9,F11+輸入與假設!$C$10*G$41) -> 6284 | I11: 0 | J11: 只交付已交付＋在建站點，OpenAI 相關容量實現 60%（上限 6,284 MW-IT），依 FY26 歷史速度 1,000 MW-IT／年；I 欄＝FY31 新增 MW
A12: 基準 已簽約站點依 Q1 速度｜合約 MW 上限 | B12: MW | C12: 8778 | D12: 8778 | E12: 8778 | F12: 8778 | G12: 8778 | I12: company.json → scenarios.mwPath.contracted
A13: 基準 已簽約站點依 Q1 速度｜併網速度 | B13: MW／年 | C13: 2833 | I13: company.json → scenarios.mwPath.pace
A14: 基準 已簽約站點依 Q1 速度 | B14: MW | C14: =MIN(C12,輸入與假設!$C$8) -> 4668 | D14: =MIN(D12,C14+輸入與假設!$C$13*D$41) -> 7501 | E14: =MIN(E12,D14+輸入與假設!$C$13*E$41) -> 8778 | F14: =MIN(F12,E14+輸入與假設!$C$13*F$41) -> 8778 | G14: =MIN(G12,F14+輸入與假設!$C$13*G$41) -> 8778 | I14: 0 | J14: Oracle 承租的五個 Stargate 站點全數實現（上限 8,778 MW-IT），依 FY27Q1 交付速度 2,833 MW-IT／年；I 欄＝FY31 新增 MW
A15: 積極 依公司時程｜合約 MW 上限 | B15: MW | C15: 8778 | D15: 8778 | E15: 8778 | F15: 8778 | G15: 8778 | I15: company.json → scenarios.mwPath.contracted
A16: 積極 依公司時程｜併網速度 | B16: MW／年 | C16: 3333 | I16: company.json → scenarios.mwPath.pace
A17: 積極 依公司時程 | B17: MW | C17: =MIN(C15,輸入與假設!$C$8) -> 4668 | D17: =MIN(D15,C17+輸入與假設!$C$16*D$41) -> 8001 | E17: =MIN(E15,D17+輸入與假設!$C$16*E$41) -> 8778 | F17: =MIN(F15,E17+輸入與假設!$C$16*F$41) -> 8778 | G17: =MIN(G15,F17+輸入與假設!$C$16*G$41) -> 8778 | I17: 0 | J17: 同基準上限，依公司時程（每季約 1 GW，3,333 MW-IT／年）；I 欄＝FY31 新增 MW
A18: 每 MW 年收入｜保守 OpenAI 相關 60% | B18: US$bn/MW | C18: 0.01162 | D18: 0.01162 | E18: 0.01162 | F18: 0.01162 | G18: 0.01162 | I18: Tokenomics 正向推導三情境（data/permw_tokenomics_20261007.json）；不用公司 ACV [Derived]
A19: 每 MW 年收入｜基準 已簽約站點依 Q1 速度 | B19: US$bn/MW | C19: 0.0174 | D19: 0.0174 | E19: 0.0174 | F19: 0.0174 | G19: 0.0174 | I19: Tokenomics 正向推導三情境（data/permw_tokenomics_20261007.json）；不用公司 ACV [Derived]
A20: 每 MW 年收入｜積極 依公司時程 | B20: US$bn/MW | C20: 0.0242 | D20: 0.0242 | E20: 0.0242 | F20: 0.0242 | G20: 0.0242 | I20: Tokenomics 正向推導三情境（data/permw_tokenomics_20261007.json）；不用公司 ACV [Derived]
A21: 在役 MW 收斂比例（期初校準值 → 已連網） | B21: % | C21: 0.5 | D21: 0.8 | E21: 0.85 | F21: 0.9 | G21: 0.9 | I21: 期初可計費 MW＝Q1 FY27 實際 OCI 營收 7.388 × 4＝29.552 ÷ 各情境每 MW 年收入（保守 2,543／基準 1,698／積極 1,221 MW-IT），是對齊已實現實際數的校準，不是以公司預測反推參數。各期末可計費 MW＝期初校準值＋(已連網 − 期初校準值)× 收斂比例；首期 50% 取能讓基準 FY27 營收落在公司指引 ≥90 的保守值（40% 時基準 FY27 約 89.1，低於指引），之後 80%→90%（新產能自交付到計費約一季）[Derived／Assumed]。
A22: 期初可計費 MW 校準：Q1 2027 實際營收年化 | B22: US$bn | C22: 29.552 | I22: 最新季實際營收 × 4（company.json → scenarios.billableRatio.openAnnualRevenue）[Derived]
A23: 期初可計費 MW｜保守 OpenAI 相關 60% | B23: MW | C23: =ROUND(輸入與假設!$C$22/C18,0) -> 2543 | I23: ＝實際營收年化 ÷ 該情境每 MW 年收入（對齊已實現實際數的校準）
A24: 期初可計費 MW｜基準 已簽約站點依 Q1 速度 | B24: MW | C24: =ROUND(輸入與假設!$C$22/C19,0) -> 1698 | I24: ＝實際營收年化 ÷ 該情境每 MW 年收入（對齊已實現實際數的校準）
A25: 期初可計費 MW｜積極 依公司時程 | B25: MW | C25: =ROUND(輸入與假設!$C$22/C20,0) -> 1221 | I25: ＝實際營收年化 ÷ 該情境每 MW 年收入（對齊已實現實際數的校準）
A26: 未起租租賃總額（未折現） | B26: US$bn | C26: 288 | I26: 季報附註已簽約未起租租賃（company.json → leases.facts.notCommenced）[Interested-party]
A27: 未起租：評價日後第幾季開始起租（0＝首期第一季） | B27: 季 | C27: 0 | I27: company.json → leases.uncommenced.startQ
A28: 未起租：平均分攤起租的季數 | B28: 季 | C28: 11 | I28: 季報：FY27Q2 至 FY2029 起租 → 11 季 [Assumed]
A29: 未起租：每筆租期 | B29: 年 | C29: 17 | I29: 季報 15–19 年取中點；敏感度 15／19 年見報告 [Assumed]
A30: B｜產能與收入（MW、每 MW 年收入、利用率、信用；RPO 只作對照）
A31: 8/31 RPO | B31: US$bn | C31: 664 | I31: 季報 RPO 664.0（只作對照與債務上限的 backlog）[Interested-party]
A32: 評價日後新增承諾 | B32: US$bn | C32: 0 | I32: 評價日後新簽、尚未進 RPO 的承諾；未揭露，取 0 [Assumed]
A33: 五期認列比例（至 2030 末） | B33: % | C33: 0.7975 | I33: 季報 RPO 桶線性分攤後五期合計 79.75% [Derived]
A34: RPO 桶權重合計 | B34: % | C34: 0.7975 | I34: 下方權重列的合計，用於歸一化
A35: 2026-05-31 主動電力 | B35: MW | C35: 1835 | I35: FY26 年底已連網 MW-IT 未揭露：以各情境校準可計費 MW 的最大值（保守 2,543＝Q1 OCI 年化 29.552 ÷ 11.62）減 Q1 交付 708 推得 1,835，使各情境期初可計費不超過已連網 [Derived]
A36: 8/31 Billable MW | B36: MW | C36: =CHOOSE(輸入與假設!$C$5,輸入與假設!$C$23,輸入與假設!$C$24,輸入與假設!$C$25) -> 1698 | I36: ＝依 A 區情境選擇器（以實際營收校準）
A37: 收入用平均在役 MW（1=是） | C37: 1 | I37: 0＝用期末存量全期化；建議 1
A38: 營收驅動（mw＝MW × 每 MW 年收入；rpo＝RPO 排程） | C38: mw | I38: mw：新產能簽約率固定 100%，營收＝容量上限；RPO 只作對照與產能瓶頸旗標（company.json → defaults.revenueDriver）
A39: 每 MW 年收入倍數（整體） | B39: % | C39: 1 | I39: 反向 DCF 與壓力測試用；預設 100%。以『目標搜尋』調整此格即可反解市價隱含單價
A40: 項目 | B40: 單位 | C40: FY27 | D40: FY28 | E40: FY29 | F40: FY30 | G40: FY31 | I40: 來源／標籤
A41: 模型期長度（年） | C41: 0.75 | D41: 1 | E41: 1 | F41: 1 | G41: 1 | I41: 勿改。由 calendar_q.py 推算；只用於容量上限、電力、維護等年率換算 [Derived]
A42: RPO 桶權重 | B42: % | C42: 0.0975 | D42: 0.17125 | E42: 0.185 | F42: 0.17375 | G42: 0.17 | H42: =SUM(C42:G42) -> 0.7975 | I42: 季報 RPO 桶（12 個月內 13%、36 個月內合計 50%；其餘假設 61–84 個月；含傳統事業 RPO，只作對照）桶內線性分攤 [Derived]
A43: Accepted MW（期末主動電力） | B43: MW | C43: =CHOOSE(輸入與假設!$C$5,C11,C14,C17) -> 4668 | D43: =CHOOSE(輸入與假設!$C$5,D11,D14,D17) -> 7501 | E43: =CHOOSE(輸入與假設!$C$5,E11,E14,E17) -> 8778 | F43: =CHOOSE(輸入與假設!$C$5,F11,F14,F17) -> 8778 | G43: =CHOOSE(輸入與假設!$C$5,G11,G14,G17) -> 8778 | I43: ＝依 A 區情境選擇器（已連網 MW-IT）
A44: Billable MW | B44: MW | C44: =ROUND(輸入與假設!$C$36+(C43-輸入與假設!$C$36)*C21,0) -> 3183 | D44: =ROUND(輸入與假設!$C$36+(D43-輸入與假設!$C$36)*D21,0) -> 6340 | E44: =ROUND(輸入與假設!$C$36+(E43-輸入與假設!$C$36)*E21,0) -> 7716 | F44: =ROUND(輸入與假設!$C$36+(F43-輸入與假設!$C$36)*F21,0) -> 8070 | G44: =ROUND(輸入與假設!$C$36+(G43-輸入與假設!$C$36)*G21,0) -> 8070 | I44: ＝期初校準值＋(已連網 − 期初校準值)× 收斂比例（A 區）
A45: 利用率 | B45: % | C45: 1 | D45: 1 | E45: 1 | F45: 1 | G45: 1 | I45: 100%：每 MW 年收入已含可計費利用率（路徑 B 80／85／90%），不重複扣除 [Derived]
A46: 每 MW 年收入 | B46: US$bn/MW | C46: =CHOOSE(輸入與假設!$C$5,C18,C19,C20) -> 0.0174 | D46: =CHOOSE(輸入與假設!$C$5,D18,D19,D20) -> 0.0174 | E46: =CHOOSE(輸入與假設!$C$5,E18,E19,E20) -> 0.0174 | F46: =CHOOSE(輸入與假設!$C$5,F18,F19,F20) -> 0.0174 | G46: =CHOOSE(輸入與假設!$C$5,G18,G19,G20) -> 0.0174 | I46: ＝依 A 區情境選擇器（Tokenomics 正向推導三情境）
A47: 新產能簽約率 | B47: % | C47: 1 | D47: 1 | E47: 1 | F47: 1 | G47: 1 | I47: MW 驅動：100%（RPO 只作對照）
A48: 客戶違約率 | B48: % | C48: 0.005 | D48: 0.01 | E48: 0.015 | F48: 0.02 | G48: 0.025 | I48: 前三大客戶約 59% 營收的定價，非預測 [Assumed]
A49: 回收率 | B49: % | C49: 0.5 | D49: 0.5 | E49: 0.5 | F49: 0.5 | G49: 0.5 | I49: [Assumed]
A50: 非算力服務營收 | B50: US$bn | C50: 0 | D50: 0 | E50: 0 | F50: 0 | G50: 0 | I50: 預設 0：AI cloud 軟體已含在每 MW 年收入；其他事業另列 [Assumed]
A51: 其他事業 EBITDA | B51: US$bn | C51: 0 | D51: 0 | E51: 0 | F51: 0 | G51: 0 | I51: 不適用（Oracle 無需另列的非核心事業燒錢；傳統事業另列於 defaults.legacyBiz，v0.1b 步驟 3）
A52: ▸ B2｜傳統事業（各線全年營收＝上一財年 ×(1＋年增率)，年增率自起點線性收斂到長期值；FY27 模型期＝全年 − 1Q 實際）
A53: 傳統事業｜SaaS（雲端應用）｜上一財年實際 | B53: US$bn | C53: 15.888 | I53: 上一財年經查核營收（company.json → defaults.legacyBiz）[Verified]
A54: 傳統事業｜SaaS（雲端應用）｜1Q 實際 | B54: US$bn | C54: 4.219 | I54: 年初至今實際營收（10-Q）[Interested-party]
A55: 傳統事業｜SaaS（雲端應用）｜起始年增率 | B55: % | C55: 0.1111 | I55: 近四季對前四季年增率 [Derived]
A56: 傳統事業｜SaaS（雲端應用）｜長期年增率 | B56: % | C56: 0.08 | I56: 長期值 [Assumed]（區間見 company.json → defaults.legacyBiz.note）
A57: 傳統事業｜SaaS（雲端應用）｜年增率 | B57: % | C57: =輸入與假設!$C$55+(輸入與假設!$C$56-輸入與假設!$C$55)*0/4 -> 0.1111 | D57: =輸入與假設!$C$55+(輸入與假設!$C$56-輸入與假設!$C$55)*1/4 -> 0.103325 | E57: =輸入與假設!$C$55+(輸入與假設!$C$56-輸入與假設!$C$55)*2/4 -> 0.09555 | F57: =輸入與假設!$C$55+(輸入與假設!$C$56-輸入與假設!$C$55)*3/4 -> 0.087775 | G57: =輸入與假設!$C$55+(輸入與假設!$C$56-輸入與假設!$C$55)*4/4 -> 0.08 | I57: ＝起始＋(長期 − 起始)×期數÷4
A58: 傳統事業｜SaaS（雲端應用）｜全年營收 | B58: US$bn | C58: =輸入與假設!$C$53*(1+C57) -> 17.653157 | D58: =C58*(1+D57) -> 19.477169 | E58: =D58*(1+E57) -> 21.338213 | F58: =E58*(1+F57) -> 23.211174 | G58: =F58*(1+G57) -> 25.068068 | I58: ＝前一年 ×(1＋年增率)
A59: 傳統事業｜SaaS（雲端應用）｜模型期營收 | B59: US$bn | C59: =C58-輸入與假設!$C$54 -> 13.434157 | D59: =D58 -> 19.477169 | E59: =E58 -> 21.338213 | F59: =F58 -> 23.211174 | G59: =G58 -> 25.068068 | I59: FY27＝全年 − 1Q 實際
A60: 傳統事業｜軟體（授權＋支援）｜上一財年實際 | B60: US$bn | C60: 24.541 | I60: 上一財年經查核營收（company.json → defaults.legacyBiz）[Verified]
A61: 傳統事業｜軟體（授權＋支援）｜1Q 實際 | B61: US$bn | C61: 5.55 | I61: 年初至今實際營收（10-Q）[Interested-party]
A62: 傳統事業｜軟體（授權＋支援）｜起始年增率 | B62: % | C62: -0.0125 | I62: 近四季對前四季年增率 [Derived]
A63: 傳統事業｜軟體（授權＋支援）｜長期年增率 | B63: % | C63: -0.01 | I63: 長期值 [Assumed]（區間見 company.json → defaults.legacyBiz.note）
A64: 傳統事業｜軟體（授權＋支援）｜年增率 | B64: % | C64: =輸入與假設!$C$62+(輸入與假設!$C$63-輸入與假設!$C$62)*0/4 -> -0.0125 | D64: =輸入與假設!$C$62+(輸入與假設!$C$63-輸入與假設!$C$62)*1/4 -> -0.011875 | E64: =輸入與假設!$C$62+(輸入與假設!$C$63-輸入與假設!$C$62)*2/4 -> -0.01125 | F64: =輸入與假設!$C$62+(輸入與假設!$C$63-輸入與假設!$C$62)*3/4 -> -0.010625 | G64: =輸入與假設!$C$62+(輸入與假設!$C$63-輸入與假設!$C$62)*4/4 -> -0.01 | I64: ＝起始＋(長期 − 起始)×期數÷4
A65: 傳統事業｜軟體（授權＋支援）｜全年營收 | B65: US$bn | C65: =輸入與假設!$C$60*(1+C64) -> 24.234237 | D65: =C65*(1+D64) -> 23.946456 | E65: =D65*(1+E64) -> 23.677058 | F65: =E65*(1+F64) -> 23.42549 | G65: =F65*(1+G64) -> 23.191235 | I65: ＝前一年 ×(1＋年增率)
A66: 傳統事業｜軟體（授權＋支援）｜模型期營收 | B66: US$bn | C66: =C65-輸入與假設!$C$61 -> 18.684237 | D66: =D65 -> 23.946456 | E66: =E65 -> 23.677058 | F66: =F65 -> 23.42549 | G66: =G65 -> 23.191235 | I66: FY27＝全年 − 1Q 實際
A67: 傳統事業｜硬體｜上一財年實際 | B67: US$bn | C67: 3.084 | I67: 上一財年經查核營收（company.json → defaults.legacyBiz）[Verified]
A68: 傳統事業｜硬體｜1Q 實際 | B68: US$bn | C68: 0.774 | I68: 年初至今實際營收（10-Q）[Interested-party]
A69: 傳統事業｜硬體｜起始年增率 | B69: % | C69: 0.0803 | I69: 近四季對前四季年增率 [Derived]
A70: 傳統事業｜硬體｜長期年增率 | B70: % | C70: 0 | I70: 長期值 [Assumed]（區間見 company.json → defaults.legacyBiz.note）
A71: 傳統事業｜硬體｜年增率 | B71: % | C71: =輸入與假設!$C$69+(輸入與假設!$C$70-輸入與假設!$C$69)*0/4 -> 0.0803 | D71: =輸入與假設!$C$69+(輸入與假設!$C$70-輸入與假設!$C$69)*1/4 -> 0.060225 | E71: =輸入與假設!$C$69+(輸入與假設!$C$70-輸入與假設!$C$69)*2/4 -> 0.04015 | F71: =輸入與假設!$C$69+(輸入與假設!$C$70-輸入與假設!$C$69)*3/4 -> 0.020075 | G71: =輸入與假設!$C$69+(輸入與假設!$C$70-輸入與假設!$C$69)*4/4 -> 0 | I71: ＝起始＋(長期 − 起始)×期數÷4
A72: 傳統事業｜硬體｜全年營收 | B72: US$bn | C72: =輸入與假設!$C$67*(1+C71) -> 3.3316452 | D72: =C72*(1+D71) -> 3.5322935 | E72: =D72*(1+E71) -> 3.6741151 | F72: =E72*(1+F71) -> 3.747873 | G72: =F72*(1+G71) -> 3.747873 | I72: ＝前一年 ×(1＋年增率)
A73: 傳統事業｜硬體｜模型期營收 | B73: US$bn | C73: =C72-輸入與假設!$C$68 -> 2.5576452 | D73: =D72 -> 3.5322935 | E73: =E72 -> 3.6741151 | F73: =F72 -> 3.747873 | G73: =G72 -> 3.747873 | I73: FY27＝全年 − 1Q 實際
A74: 傳統事業｜服務｜上一財年實際 | B74: US$bn | C74: 5.743 | I74: 上一財年經查核營收（company.json → defaults.legacyBiz）[Verified]
A75: 傳統事業｜服務｜1Q 實際 | B75: US$bn | C75: 1.414 | I75: 年初至今實際營收（10-Q）[Interested-party]
A76: 傳統事業｜服務｜起始年增率 | B76: % | C76: 0.0921 | I76: 近四季對前四季年增率 [Derived]
A77: 傳統事業｜服務｜長期年增率 | B77: % | C77: 0.03 | I77: 長期值 [Assumed]（區間見 company.json → defaults.legacyBiz.note）
A78: 傳統事業｜服務｜年增率 | B78: % | C78: =輸入與假設!$C$76+(輸入與假設!$C$77-輸入與假設!$C$76)*0/4 -> 0.0921 | D78: =輸入與假設!$C$76+(輸入與假設!$C$77-輸入與假設!$C$76)*1/4 -> 0.076575 | E78: =輸入與假設!$C$76+(輸入與假設!$C$77-輸入與假設!$C$76)*2/4 -> 0.06105 | F78: =輸入與假設!$C$76+(輸入與假設!$C$77-輸入與假設!$C$76)*3/4 -> 0.045525 | G78: =輸入與假設!$C$76+(輸入與假設!$C$77-輸入與假設!$C$76)*4/4 -> 0.03 | I78: ＝起始＋(長期 − 起始)×期數÷4
A79: 傳統事業｜服務｜全年營收 | B79: US$bn | C79: =輸入與假設!$C$74*(1+C78) -> 6.2719303 | D79: =C79*(1+D78) -> 6.7522034 | E79: =D79*(1+E78) -> 7.1644254 | F79: =E79*(1+F78) -> 7.4905858 | G79: =F79*(1+G78) -> 7.7153034 | I79: ＝前一年 ×(1＋年增率)
A80: 傳統事業｜服務｜模型期營收 | B80: US$bn | C80: =C79-輸入與假設!$C$75 -> 4.8579303 | D80: =D79 -> 6.7522034 | E80: =E79 -> 7.1644254 | F80: =F79 -> 7.4905858 | G80: =G79 -> 7.7153034 | I80: FY27＝全年 − 1Q 實際
A81: 傳統事業營收（模型期） | B81: US$bn | C81: =C59+C66+C73+C80 -> 39.53397 | D81: =D59+D66+D73+D80 -> 53.708122 | E81: =E59+E66+E73+E80 -> 55.853812 | F81: =F59+F66+F73+F80 -> 57.875123 | G81: =G59+G66+G73+G80 -> 59.722479 | I81: 四線合計（下游引用此列）
A82: 傳統事業 EBITDA 率 | B82: % | C82: 0.5426 | D82: 0.5426 | E82: 0.5426 | F82: 0.5426 | G82: 0.5426 | I82: FY26 合併 EBITDA 率＝非 GAAP 營業利益＋折舊，OCI 無分部揭露無法拆分 [Derived]；不加無形資產攤銷，因非 GAAP 營業利益已排除攤銷
A83: 傳統事業 EBITDA（模型期） | B83: US$bn | C83: =C81*C82 -> 21.451132 | D83: =D81*D82 -> 29.142027 | E83: =E81*E82 -> 30.306278 | F83: =F81*F82 -> 31.403042 | G83: =G81*G82 -> 32.405417 | I83: ＝營收 × EBITDA 率；同時進入損益 EBITDA 與營運來源（現金稅另列）
A84: 傳統事業｜FY27 核對（1Q＋模型期 − 全年） | B84: US$bn | C84: =輸入與假設!$C$54+C59-C58+輸入與假設!$C$61+C66-C65+輸入與假設!$C$68+C73-C72+輸入與假設!$C$75+C80-C79 -> 0 | I84: 應為 0：首期年初至今實際＋模型期＝首期全年（各線合計）
A86: C｜利潤率（EBITDA 率單一來源；損益與資金共用）
A87: 起始 EBITDA 率（FY27） | B87: % | C87: 0.652 | I87: FY27Q1 合併 EBITDA 扣除傳統事業後拆推的 OCI EBITDA 率 [Derived]
A88: 穩態 EBITDA 率（FY31） | B88: % | C88: 0.47 | I88: 可觀察 neocloud 區間 IREN 約 35%／CRWV 約 59% 的中點 47%；不取自每 MW 推導路徑 A 的加成 [Analogy]
A89: 基準情境租金占 OCI 營收（FY27） | B89: % | C89: 0.193075 | I89: EBITDAR 率校準：基準情境首期租金 ÷ OCI 營收，使基準情境起始 EBITDA 率維持上列值；scripts/calib_ebitdar.js 自基準情境計算（verify.sh 檢查）[Derived]
A90: 基準情境租金占 OCI 營收（FY31） | B90: % | C90: 0.156683 | I90: 同上，基準情境末期；保守與積極用同一 EBITDAR 率，因而承擔固定租金 [Derived]
A91: 項目 | B91: 單位 | C91: FY27 | D91: FY28 | E91: FY29 | F91: FY30 | G91: FY31 | I91: 來源／標籤
A92: EBITDAR 率（路徑） | B92: % | C92: =輸入與假設!$C$87+輸入與假設!$C$89+(輸入與假設!$C$88+輸入與假設!$C$90-輸入與假設!$C$87-輸入與假設!$C$89)*0/4 -> 0.845075 | D92: =輸入與假設!$C$87+輸入與假設!$C$89+(輸入與假設!$C$88+輸入與假設!$C$90-輸入與假設!$C$87-輸入與假設!$C$89)*1/4 -> 0.790477 | E92: =輸入與假設!$C$87+輸入與假設!$C$89+(輸入與假設!$C$88+輸入與假設!$C$90-輸入與假設!$C$87-輸入與假設!$C$89)*2/4 -> 0.735879 | F92: =輸入與假設!$C$87+輸入與假設!$C$89+(輸入與假設!$C$88+輸入與假設!$C$90-輸入與假設!$C$87-輸入與假設!$C$89)*3/4 -> 0.681281 | G92: =輸入與假設!$C$87+輸入與假設!$C$89+(輸入與假設!$C$88+輸入與假設!$C$90-輸入與假設!$C$87-輸入與假設!$C$89)*4/4 -> 0.626683 | I92: ＝(起始 EBITDA 率＋基準起點租金比)＋[(穩態＋基準穩態租金比)−(起始＋基準起點租金比)]×期數÷4（公式）
A93: EBITDA 率 | B93: % | C93: =C92-各期收支!C16/MAX(0.01,運營_產能與收入!C38) -> 0.65039005 | D93: =D92-各期收支!D16/MAX(0.01,運營_產能與收入!D38) -> 0.61346746 | E93: =E92-各期收支!E16/MAX(0.01,運營_產能與收入!E38) -> 0.56794063 | F93: =F92-各期收支!F16/MAX(0.01,運營_產能與收入!F38) -> 0.51660121 | G93: =G92-各期收支!G16/MAX(0.01,運營_產能與收入!G38) -> 0.46913568 | I93: ＝EBITDAR 率 − 租金合計 ÷ OCI 營收（公式；租金為固定成本，低營收情境 EBITDA 率較低）
A94: 非算力服務現金 | B94: US$bn | C94: =輸入與假設!C$50*運營_產能與收入!C39 -> 0 | D94: =輸入與假設!D$50*運營_產能與收入!D39 -> 0 | E94: =輸入與假設!E$50*運營_產能與收入!E39 -> 0 | F94: =輸入與假設!F$50*運營_產能與收入!F39 -> 0 | G94: =輸入與假設!G$50*運營_產能與收入!G39 -> 0 | I94: ＝服務營收 × EBITDAR 率（公式）
A95: ▸ 電力／維護 overlay（預設關閉；EBITDA 已含電費）
A96: 電力／維護 overlay（1=開） | C96: 0 | I96: EBITDA 率已含電費，開啟會重複扣除，僅供壓力測試
A97: 電價 | B97: $/MWh | C97: 60 | D97: 62 | E97: 64 | F97: 66 | G97: 68 | I97: overlay 用 [Assumed]
A98: PUE | C98: 1.2 | D98: 1.2 | E98: 1.2 | F98: 1.2 | G98: 1.2 | I98: overlay 用 [Assumed]
A99: 維護成本 | B99: US$m/MW | C99: 0.15 | D99: 0.15 | E99: 0.16 | F99: 0.16 | G99: 0.17 | I99: overlay 用 [Assumed]
A101: D｜支出（CapEx、車隊折舊、租賃、JV）
A102: 提前支出比例 λ | B102: % | C102: 0.35 | I102: 次年才上線的 MW，其建置支出落在前一年的比例 [Assumed]
A103: FY31 新增 MW（FY30 預建用） | B103: MW | C103: =CHOOSE(輸入與假設!$C$5,I11,I14,I17) -> 0 | I103: 隨情境：保守 0／基準 500／積極 1,000 [Assumed]
...

Sheet 各期收支
A1: 支出與資金 — 五層支出、四層來源、現金橋
A2: FY27 欄＝1Q 實際（季報現金流量表口徑）＋第 2–4 季模型；FY28 以後為純模型。瀑布以「融資前現金」決定需求並直接由各支出列加總，因此沒有循環參照
A4: 項目 | B4: 單位 | C4: FY27 | D4: FY28 | E4: FY29 | F4: FY30 | G4: FY31 | I4: 公式／來源說明
A5: 支出（五層）
A6: ① 毛 CapEx（認列，備忘） | B6: US$bn | C6: =輸入與假設!$C$243+輸入與假設!C$135 -> 106.09585 | D6: =輸入與假設!D$135 -> 86.020956 | E6: =輸入與假設!E$135 -> 31.20158 | F6: =輸入與假設!F$135 -> 54.99417 | G6: =輸入與假設!G$135 -> 54.99417 | I6: FY27＝1Q 實際認列 28.499＋2Q–4Q 模型；對照公司全年指引 90–95。備忘列：用途合計採現金口徑，不用這一列
A7: 客戶預付率 | B7: % | C7: =輸入與假設!C$116 -> 0.243 | D7: =輸入與假設!D$116 -> 0.243 | E7: =輸入與假設!E$116 -> 0.243 | F7: =輸入與假設!F$116 -> 0.243 | G7: =輸入與假設!G$116 -> 0.243
A8: 客戶預付金額（抵減，2Q–4Q 起） | B8: US$bn | C8: =(輸入與假設!C$128+輸入與假設!C$132)*C7 -> 18.856035 | D8: =(輸入與假設!D$128+輸入與假設!D$132)*D7 -> 20.903092 | E8: =(輸入與假設!E$128+輸入與假設!E$132)*E7 -> 7.5819838 | F8: =(輸入與假設!F$128+輸入與假設!F$132)*F7 -> 13.363583 | G8: =(輸入與假設!G$128+輸入與假設!G$132)*G7 -> 13.363583 | I8: ＝(成長型＋汰換 CapEx)× 預付比率（v0.1c：汰換同樣適用覆蓋比）；1Q 的預付已含在實際 CFO 內，不重複計入
A9: 合約負債期初（客戶預付餘額） | B9: US$bn | C9: =輸入與假設!$C$113 -> 15.955 | D9: =C12 -> 33.730118 | E9: =D12 -> 50.753693 | F9: =E12 -> 51.723798 | G9: =F12 -> 58.531976 | I9: FY27 期初＝8/31 季報遞延營收
A10: 合約負債利息累積（重大財務組成，非現金） | B10: US$bn | C10: =輸入與假設!$C$114*(C9+0.5*C8)*運營_產能與收入!C7 -> 1.543922 | D10: =輸入與假設!$C$114*(D9+0.5*D8)*運營_產能與收入!D7 -> 3.583133 | E10: =輸入與假設!$C$114*(E9+0.5*E8)*運營_產能與收入!E7 -> 4.423574 | F10: =輸入與假設!$C$114*(F9+0.5*F8)*運營_產能與收入!F7 -> 4.7366933 | G10: =輸入與假設!$C$114*(G9+0.5*G8)*運營_產能與收入!G7 -> 5.2888366 | I10: ＝隱含利率 ×(期初合約負債＋本期預付流入 × ½)× 期間長度；進損益利息、不進現金（v0.1b）
A11: 預付認列（非現金營收） | B11: US$bn | C11: =MIN(C9+C10,(C9+C10)/輸入與假設!$C$112*運營_產能與收入!C7) -> 2.6248383 | D11: =MIN(D9+D10,(D9+D10)/輸入與假設!$C$112*運營_產能與收入!D7) -> 7.4626503 | E11: =MIN(E9+E10,(E9+E10)/輸入與假設!$C$112*運營_產能與收入!E7) -> 11.035453 | F11: =MIN(F9+F10,(F9+F10)/輸入與假設!$C$112*運營_產能與收入!F7) -> 11.292098 | G11: =MIN(G9+G10,(G9+G10)/輸入與假設!$C$112*運營_產能與收入!G7) -> 12.764163 | I11: ＝(期初合約負債＋累積利息) ÷ 認列年數 × 期間長度；這部分營收已在預付時收現，自營運來源扣除
A12: 合約負債期末 | B12: US$bn | C12: =C9+C8+C10-C11 -> 33.730118 | D12: =D9+D8+D10-D11 -> 50.753693 | E12: =E9+E8+E10-E11 -> 51.723798 | F12: =F9+F8+F10-F11 -> 58.531976 | G12: =G9+G8+G10-G11 -> 64.420233 | I12: ＝期初＋預付流入＋累積利息−認列
A13: ① CapEx（用途用：1Q 現金／2Q–4Q 毛額） | B13: US$bn | C13: =輸入與假設!$C$242+輸入與假設!C$135 -> 106.09585 | D13: =輸入與假設!D$135 -> 86.020956 | E13: =輸入與假設!E$135 -> 31.20158 | F13: =輸入與假設!F$135 -> 54.99417 | G13: =輸入與假設!G$135 -> 54.99417 | I13: 1Q 採現金流量表的現金購置 28.499；2Q–4Q 起採毛額，客戶預付在來源端抵回（避免重複計入）
A14: ② 在帳現金租金（備忘，1Q 已含在 CFO） | B14: US$bn | C14: =輸入與假設!C$117 -> 3.839 | D14: =輸入與假設!D$117 -> 4.987 | E14: =輸入與假設!E$117 -> 5.02 | F14: =輸入與假設!F$117 -> 5.056 | G14: =輸入與假設!G$117 -> 5.06 | I14: 見『租賃與承諾』頁；2031 後尚有 39.283。FY27 欄僅 2Q–4Q：1Q 租金 1.136 已含在實際 CFO 內
A15: ② 表外現金租金（未起租） | B15: US$bn | C15: =運營_產能與收入!C59 -> 1.7326203 | D15: =運營_產能與收入!D59 -> 7.7005348 | E15: =運營_產能與收入!E59 -> 13.860963 | F15: =運營_產能與收入!F59 -> 16.941176 | G15: =運營_產能與收入!G59 -> 16.941176 | I15: 已簽約未起租租賃 288.0 的現金路徑
A16: 租金合計 | B16: US$bn | C16: =C14+C15 -> 5.5716203 | D16: =D14+D15 -> 12.687535 | E16: =E14+E15 -> 18.880963 | F16: =F14+F15 -> 21.997176 | G16: =G14+G15 -> 22.001176 | I16: 租金已含在 EBITDA 率內（GAAP 營業租賃費用屬營業費用）：營運來源以 EBITDA 率＋租金÷營收計（租前），此列再扣，淨效果中性
A17: ③ 存量債務利息（備忘，1Q 已含在 CFO） | B17: US$bn | C17: =輸入與假設!C$172 -> 4.4795709 | D17: =輸入與假設!D$172 -> 5.6569839 | E17: =輸入與假設!E$172 -> 5.2813593 | F17: =輸入與假設!F$172 -> 4.9752805 | G17: =輸入與假設!G$172 -> 4.5671755 | I17: ="8/31 債務餘額的利息。FY27 全年利息＝1Q 實際 1.428＋2Q–4Q "&TEXT(C17,"0.0")&"＝"&TEXT(1.428+C17,"0.00")&"（見下方備忘）" -> 8/31 債務餘額的利息。FY27 全年利息＝1Q 實際 1.428＋2Q–4Q 4.5＝5.91（見下方備忘）
A18: 期初累積現金 | B18: US$bn | C18: =輸入與假設!$C$240 -> 31.289 | D18: =C52 -> 10 | E18: =D52 -> 10 | F18: =E52 -> 42.038145 | G18: =F52 -> 60.179667 | I18: FY27 自 2026-05-31 起算；之後＝前期期末累積現金
A19: 新債利率 | B19: % | C19: =IF(輸入與假設!$C$165=1,輸入與假設!C$171+MAX(0,輸入與假設!$C$164-450)/100*0.004,輸入與假設!C$171) -> 0.058 | D19: =IF(輸入與假設!$C$165=1,輸入與假設!D$171+MAX(0,輸入與假設!$C$164-450)/100*0.004,輸入與假設!D$171) -> 0.058 | E19: =IF(輸入與假設!$C$165=1,輸入與假設!E$171+MAX(0,輸入與假設!$C$164-450)/100*0.004,輸入與假設!E$171) -> 0.058 | F19: =IF(輸入與假設!$C$165=1,輸入與假設!F$171+MAX(0,輸入與假設!$C$164-450)/100*0.004,輸入與假設!F$171) -> 0.058 | G19: =IF(輸入與假設!$C$165=1,輸入與假設!G$171+MAX(0,輸入與假設!$C$164-450)/100*0.004,輸入與假設!G$171) -> 0.058 | I19: CDS 開關：＋MAX(0,CDS−450)×0.4bp/bp
A20: ③ 新債利息（瀑布） | B20: US$bn | C20: =C86 -> 0.48727183 | D20: =D86 -> 2.399361 | E20: =E86 -> 2.399361 | F20: =F86 -> 2.399361 | G20: =G86 -> 2.399361 | I20: ＝新債利率×期間長度×(期初新債＋本期舉借)；見下方「期前融資瀑布」
A21: 利息合計 | B21: US$bn | C21: =C17+C20 -> 4.9668427 | D21: =D17+D20 -> 8.0563449 | E21: =E17+E20 -> 7.6807203 | F21: =F17+F20 -> 7.3746415 | G21: =G17+G20 -> 6.9665365
A22: ④ JV／策略投資出資 | B22: US$bn | C22: =輸入與假設!$C$244+輸入與假設!C$122 -> 0 | D22: =輸入與假設!D$122 -> 0 | E22: =輸入與假設!E$122 -> 0 | F22: =輸入與假設!F$122 -> 0 | G22: =輸入與假設!G$122 -> 0 | I22: FY27＝1Q 實際 0.0（JV 0.000＋策略投資 0.000）＋2Q–4Q 模型。ORCL 不發股息
A23: ⑧ 股利（普通股＋特別股） | B23: US$bn | C23: =輸入與假設!$C$259+4*輸入與假設!$C$149*運營_產能與收入!C7*(輸入與假設!$C$150+0+SUMPRODUCT(資產負債_既有債務!$D$73:$D$73*資產負債_既有債務!$H$69:$H$69*(資產負債_既有債務!$G$69:$G$69<0)))+輸入與假設!C$169 -> 6.344604 | D23: =4*輸入與假設!$C$149*運營_產能與收入!D7*(輸入與假設!$C$150+C89+SUMPRODUCT(資產負債_既有債務!$D$73:$D$73*資產負債_既有債務!$H$69:$H$69*(資產負債_既有債務!$G$69:$G$69<1)))+輸入與假設!D$169 -> 6.372472 | E23: =4*輸入與假設!$C$149*運營_產能與收入!E7*(輸入與假設!$C$150+D89+SUMPRODUCT(資產負債_既有債務!$D$73:$D$73*資產負債_既有債務!$H$69:$H$69*(資產負債_既有債務!$G$69:$G$69<2)))+輸入與假設!E$169 -> 6.291472 | F23: =4*輸入與假設!$C$149*運營_產能與收入!F7*(輸入與假設!$C$150+E89+SUMPRODUCT(資產負債_既有債務!$D$73:$D$73*資產負債_既有債務!$H$69:$H$69*(資產負債_既有債務!$G$69:$G$69<3)))+輸入與假設!F$169 -> 6.1099486 | G23: =4*輸入與假設!$C$149*運營_產能與收入!G7*(輸入與假設!$C$150+F89+SUMPRODUCT(資產負債_既有債務!$D$73:$D$73*資產負債_既有債務!$H$69:$H$69*(資產負債_既有債務!$G$69:$G$69<4)))+輸入與假設!G$169 -> 6.1099486 | I23: 普通股＝每股每季 × 4 × 期間長度 ×(基礎股數＋前期累計瀑布新股＋已強制轉換特別股)＋特別股股利；FY27＝1Q 實際＋2Q–4Q 模型（v0.1b）
A24: 電力（overlay） | B24: US$bn | C24: =IF(輸入與假設!$C$96=1,運營_產能與收入!C9*8760*輸入與假設!C$98*輸入與假設!C$97/1000000000*運營_產能與收入!C7,0) -> 0 | D24: =IF(輸入與假設!$C$96=1,運營_產能與收入!D9*8760*輸入與假設!D$98*輸入與假設!D$97/1000000000*運營_產能與收入!D7,0) -> 0 | E24: =IF(輸入與假設!$C$96=1,運營_產能與收入!E9*8760*輸入與假設!E$98*輸入與假設!E$97/1000000000*運營_產能與收入!E7,0) -> 0 | F24: =IF(輸入與假設!$C$96=1,運營_產能與收入!F9*8760*輸入與假設!F$98*輸入與假設!F$97/1000000000*運營_產能與收入!F7,0) -> 0 | G24: =IF(輸入與假設!$C$96=1,運營_產能與收入!G9*8760*輸入與假設!G$98*輸入與假設!G$97/1000000000*運營_產能與收入!G7,0) -> 0 | I24: ＝已連網 MW×8760×PUE×電價÷1e9×期間係數。EBITDA 率已含電費，預設關閉
A25: 維護（overlay） | B25: US$bn | C25: =IF(輸入與假設!$C$96=1,運營_產能與收入!C9*輸入與假設!C$99/1000*運營_產能與收入!C7,0) -> 0 | D25: =IF(輸入與假設!$C$96=1,運營_產能與收入!D9*輸入與假設!D$99/1000*運營_產能與收入!D7,0) -> 0 | E25: =IF(輸入與假設!$C$96=1,運營_產能與收入!E9*輸入與假設!E$99/1000*運營_產能與收入!E7,0) -> 0 | F25: =IF(輸入與假設!$C$96=1,運營_產能與收入!F9*輸入與假設!F$99/1000*運營_產能與收入!F7,0) -> 0 | G25: =IF(輸入與假設!$C$96=1,運營_產能與收入!G9*輸入與假設!G$99/1000*運營_產能與收入!G7,0) -> 0
A26: ⑤ 排程還本（季報到期表） | B26: US$bn | C26: =輸入與假設!$C$246+IF(輸入與假設!$C$144=1,輸入與假設!C$170,0)+資產負債_既有債務!C84 -> 7.209 | D26: =IF(輸入與假設!$C$144=1,輸入與假設!D$170,0)+資產負債_既有債務!D84 -> 10.147 | E26: =IF(輸入與假設!$C$144=1,輸入與假設!E$170,0)+資產負債_既有債務!E84 -> 5.5 | F26: =IF(輸入與假設!$C$144=1,輸入與假設!F$170,0)+資產負債_既有債務!F84 -> 7.25 | G26: =IF(輸入與假設!$C$144=1,輸入與假設!G$170,0)+資產負債_既有債務!G84 -> 9.75 | I26: FY27＝1Q 實際還款 4.202＋2Q–4Q 到期表 3.007
A27: ⑥ capped call 支出（1Q 實際） | B27: US$bn | C27: =輸入與假設!$C$247 -> 0 | D27: =0 -> 0 | E27: =0 -> 0 | F27: =0 -> 0 | G27: =0 -> 0 | I27: 可轉債配套 capped call 現金支出（未見揭露，0）
A28: ⑦ 現金稅（2Q–4Q 起） | B28: US$bn | C28: =輸入與假設!$C$163*MAX(0,運營_產能與收入!C38*輸入與假設!C$93+輸入與假設!C$51+輸入與假設!C$83-運營_產能與收入!C62-輸入與假設!C$136-輸入與假設!C$172) -> 3.4555058 | D28: =輸入與假設!$C$163*MAX(0,運營_產能與收入!D38*輸入與假設!D$93+輸入與假設!D$51+輸入與假設!D$83-運營_產能與收入!D62-輸入與假設!D$136-輸入與假設!D$172) -> 5.8406262 | E28: =輸入與假設!$C$163*MAX(0,運營_產能與收入!E38*輸入與假設!E$93+輸入與假設!E$51+輸入與假設!E$83-運營_產能與收入!E62-輸入與假設!E$136-輸入與假設!E$172) -> 7.3727777 | F28: =輸入與假設!$C$163*MAX(0,運營_產能與收入!F38*輸入與假設!F$93+輸入與假設!F$51+輸入與假設!F$83-運營_產能與收入!F62-輸入與假設!F$136-輸入與假設!F$172) -> 7.6994602 | G28: =輸入與假設!$C$163*MAX(0,運營_產能與收入!G38*輸入與假設!G$93+輸入與假設!G$51+輸入與假設!G$83-運營_產能與收入!G62-輸入與假設!G$136-輸入與假設!G$172) -> 7.2870929 | I28: ＝稅率 × MAX(0, 損益 EBITDA − 車隊 D&A − 存量利息)；1Q 的稅已含在 CFO 內（v0.1b）
A29: 用途合計（現金口徑） | B29: US$bn | C29: =C13+C16+C21+C22+C24+C25+C26+C27+C28+C23 -> 133.64342 | D29: =D13+D16+D21+D22+D24+D25+D26+D27+D28+D23 -> 129.12493 | E29: =E13+E16+E21+E22+E24+E25+E26+E27+E28+E23 -> 76.927512 | F29: =F13+F16+F21+F22+F24+F25+F26+F27+F28+F23 -> 105.4254 | G29: =G13+G16+G21+G22+G24+G25+G26+G27+G28+G23 -> 107.10892 | I29: FY27 的 1Q 部分採季報現金流量表口徑（現金購置、還款、JV、capped call）；1Q 的利息與租金已含在 CFO 內，不重複列
A30: 來源（四層）
A31: Ⓐ0 1Q27 實際營運現金流（CFO） | B31: US$bn | C31: =輸入與假設!$C$241 -> 23.103 | D31: =0 -> 0 | E31: =0 -> 0 | F31: =0 -> 0 | G31: =0 -> 0 | I31: 季報實際值，取代模型推算；已含 1Q 的利息、租金與客戶預付
A32: Ⓐ RPO 現金（2Q–4Q 起） | B32: US$bn | C32: =運營_產能與收入!C40 -> 24.124443 | D32: =運營_產能與收入!D40 -> 56.375823 | E32: =運營_產能與收入!E40 -> 82.112849 | F32: =運營_產能與收入!F40 -> 77.813395 | G32: =運營_產能與收入!G40 -> 69.855727
A33: Ⓑ 新簽約現金 | B33: US$bn | C33: =運營_產能與收入!C41 -> 0 | D33: =運營_產能與收入!D41 -> 0 | E33: =運營_產能與收入!E41 -> 0 | F33: =運營_產能與收入!F41 -> 12.278997 | G33: =運營_產能與收入!G41 -> 16.565393
A34: Ⓒ 非算力服務現金 | B34: US$bn | C34: =輸入與假設!C$94 -> 0 | D34: =輸入與假設!D$94 -> 0 | E34: =輸入與假設!E$94 -> 0 | F34: =輸入與假設!F$94 -> 0 | G34: =輸入與假設!G$94 -> 0
A35: Ⓒ2 其他事業 EBITDA（2Q–4Q 起） | B35: US$bn | C35: =輸入與假設!C$51 -> 0 | D35: =輸入與假設!D$51 -> 0 | E35: =輸入與假設!E$51 -> 0 | F35: =輸入與假設!F$51 -> 0 | G35: =輸入與假設!G$51 -> 0 | I35: 非核心事業 EBITDA（負值＝燒錢），視為現金（v0.1b）
A36: Ⓒ3 傳統事業 EBITDA（2Q–4Q 起） | B36: US$bn | C36: =輸入與假設!C$83 -> 21.451132 | D36: =輸入與假設!D$83 -> 29.142027 | E36: =輸入與假設!E$83 -> 30.306278 | F36: =輸入與假設!F$83 -> 31.403042 | G36: =輸入與假設!G$83 -> 32.405417 | I36: SaaS、軟體、硬體、服務四線 EBITDA，視為現金（現金稅另列於用途；v0.1b）
A37: Ⓒ4 減：延誤罰則（營業費用） | B37: US$bn | C37: =-運營_產能與收入!C62 -> 0 | D37: =-運營_產能與收入!D62 -> 0 | E37: =-運營_產能與收入!E62 -> 0 | F37: =-運營_產能與收入!F62 -> 0 | G37: =-運營_產能與收入!G62 -> 0 | I37: 建設延誤期間應計費而未計費營收 × 罰則比例（預設 0；v0.2）
A38: Ⓓ 客戶預付（2Q–4Q 起） | B38: US$bn | C38: =C8 -> 18.856035 | D38: =D8 -> 20.903092 | E38: =E8 -> 7.5819838 | F38: =F8 -> 13.363583 | G38: =G8 -> 13.363583
A39: Ⓓ2 減：預付認列（非現金營收） | B39: US$bn | C39: =-C11 -> -2.6248383 | D39: =-D11 -> -7.4626503 | E39: =-E11 -> -11.035453 | F39: =-F11 -> -11.292098 | G39: =-G11 -> -12.764163 | I39: 營收中由合約負債轉入的部分已在預付時收現，不重複計入服務現金（v0.1b）
A40: 營運來源合計 | B40: US$bn | C40: =C31+C32+C33+C34+C35+C36+C37+C38+C39 -> 84.909772 | D40: =D31+D32+D33+D34+D35+D36+D37+D38+D39 -> 98.958292 | E40: =E31+E32+E33+E34+E35+E36+E37+E38+E39 -> 108.96566 | F40: =F31+F32+F33+F34+F35+F36+F37+F38+F39 -> 123.56692 | G40: =G31+G32+G33+G34+G35+G36+G37+G38+G39 -> 119.42596
A41: Ⓔ 股權／可轉債（融資） | B41: US$bn | C41: =輸入與假設!$C$248+IF(輸入與假設!$C$141=1,輸入與假設!$C$140,0) -> 19.909 | D41: =0 -> 0 | E41: =0 -> 0 | F41: =0 -> 0 | G41: =0 -> 0 | I41: FY27＝1Q ATM 淨收入 19.909（141m 股、均價約 $141.84）＋2Q–4Q 期後股權 0
A42: Ⓕ 1Q27 實際借款（融資） | B42: US$bn | C42: =輸入與假設!$C$245 -> 0 | D42: =0 -> 0 | E42: =0 -> 0 | F42: =0 -> 0 | G42: =0 -> 0 | I42: 季報：Q1 借款 0.0（2026-03 可轉債）
A43: Ⓖ 瀑布：新債（額度＋資產層） | B43: US$bn | C43: =C78 -> 11.201651 | D43: =D78 -> 30.166642 | E43: =E78 -> 0 | F43: =F78 -> 0 | G43: =G78 -> 0 | I43: 見下方「期前融資瀑布」
A44: Ⓖ2 瀑布：可轉債 | B44: US$bn | C44: =C81 -> 0 | D44: =D81 -> 0 | E44: =E81 -> 0 | F44: =F81 -> 0 | G44: =G81 -> 0 | I44: 資產擔保融資用罄後、股權之前；每年不超過可轉債上限（v0.1b）
A45: Ⓗ 瀑布：股權募資 | B45: US$bn | C45: =C84 -> 0 | D45: =D84 -> 0 | E45: =E84 -> 0 | F45: =F84 -> 0 | G45: =G84 -> 0 | I45: 債務與可轉債用罄後的殘差；每年不超過股權吸收上限
A46: Ⓘ 瀑布：高息債（股權上限溢出） | B46: US$bn | C46: =C85 -> 0 | D46: =D85 -> 0 | E46: =E85 -> 0 | F46: =F85 -> 0 | G46: =G85 -> 0 | I46: 股權超過每年上限的部分；不受 backlog 上限約束
A47: 總來源（含融資） | B47: US$bn | C47: =C40+C41+C42+C43+C44+C45+C46 -> 116.02042 | D47: =D40+D41+D42+D43+D44+D45+D46 -> 129.12493 | E47: =E40+E41+E42+E43+E44+E45+E46 -> 108.96566 | F47: =F40+F41+F42+F43+F44+F45+F46 -> 123.56692 | G47: =G40+G41+G42+G43+G44+G45+G46 -> 119.42596
A48: 缺口與現金橋
A49: 1Q 其他／受限現金調節 | B49: US$bn | C49: =輸入與假設!$C$139-(輸入與假設!$C$240+輸入與假設!$C$241+輸入與假設!$C$245+輸入與假設!$C$248-輸入與假設!$C$242-輸入與假設!$C$244-輸入與假設!$C$246-輸入與假設!$C$247-輸入與假設!$C$259) -> -3.666 | D49: =0 -> 0 | E49: =0 -> 0 | F49: =0 -> 0 | G49: =0 -> 0 | I49: 使 1Q 實際流量接回 8/31 現金餘額；差額來自受限現金重分類與未逐項列出的項目
A50: 營運缺口（不含融資、不含還本） | B50: US$bn | C50: =C40-(C29-C26-C27) -> -41.524651 | D50: =D40-(D29-D26-D27) -> -20.019642 | E50: =E40-(E29-E26-E27) -> 37.538145 | F50: =F40-(F29-F26-F27) -> 25.391522 | G50: =G40-(G29-G26-G27) -> 22.067034 | I50: 本業能不能自給：營運來源 −（用途 − 排程還本 − capped call）
A51: 期間缺口（含融資） | B51: US$bn | C51: =C47-C29+C49 -> -21.289 | D51: =D47-D29+D49 -> 0 | E51: =E47-E29+E49 -> 32.038145 | F51: =F47-F29+F49 -> 18.141522 | G51: =G47-G29+G49 -> 12.317034
A52: 期末累積現金 | B52: US$bn | C52: =C18+C51 -> 10 | D52: =D18+D51 -> 10 | E52: =E18+E51 -> 42.038145 | F52: =F18+F51 -> 60.179667 | G52: =G18+G51 -> 72.496702 | I52: 期前融資：每期末不低於最低現金
A54: 租賃負債（期末剩餘租金現值；調整後槓桿用，v0.2）
A55: 租賃折現率（加權平均） | B55: % | C55: 0.057 | I55: 10-K FY2026 營業／融資租賃加權平均折現率（事實總帳 lease.discRate.fy26）[Verified]；company.json → leases.liability.discRate
A56: 在帳租約：模型期後尾端年數 | B56: 年 | C56: 12 | I56: 到期表 2031 後的未折現付款平均分攤年數（10-K 營業租賃加權平均剩餘期限 12 年）[Derived]
A57: 在帳租賃負債（期末） | B57: US$bn | C57: =輸入與假設!D$117*(1+各期收支!$C$55)^(-(運營_產能與收入!$D$51-運營_產能與收入!$D$7/2-運營_產能與收入!$C$51))+輸入與假設!E$117*(1+各期收支!$C$55)^(-(運營_產能與收入!$E$51-運營_產能與收入!$E$7/2-運營_產能與收入!$C$51))+輸入與假設!F$117*(1+各期收支!$C$55)^(-(運營_產能與收入!$F$51-運營_產能與收入!$F$7/2-運營_產能與收入!$C$51))+輸入與假設!G$117*(1+各期收支!$C$55)^(-(運營_產能與收入!$G$51-運營_產能與收入!$G$7/2-運營_產能與收入!$C$51))+39.283/各期收支!$C$56*(1+各期收支!$C$55)^0.5*(1-(1+各期收支!$C$55)^(-各期收支!$C$56))/各期收支!$C$55*(1+各期收支!$C$55)^(-(運營_產能與收入!$G$51-運營_產能與收入!$C$51)) -> 41.020891 | D57: =輸入與假設!E$117*(1+各期收支!$C$55)^(-(運營_產能與收入!$E$51-運營_產能與收入!$E$7/2-運營_產能與收入!$D$51))+輸入與假設!F$117*(1+各期收支!$C$55)^(-(運營_產能與收入!$F$51-運營_產能與收入!$F$7/2-運營_產能與收入!$D$51))+輸入與假設!G$117*(1+各期收支!$C$55)^(-(運營_產能與收入!$G$51-運營_產能與收入!$G$7/2-運營_產能與收入!$D$51))+39.283/各期收支!$C$56*(1+各期收支!$C$55)^0.5*(1-(1+各期收支!$C$55)^(-各期收支!$C$56))/各期收支!$C$55*(1+各期收支!$C$55)^(-(運營_產能與收入!$G$51-運營_產能與收入!$D$51)) -> 38.231921 | E57: =輸入與假設!F$117*(1+各期收支!$C$55)^(-(運營_產能與收入!$F$51-運營_產能與收入!$F$7/2-運營_產能與收入!$E$51))+輸入與假設!G$117*(1+各期收支!$C$55)^(-(運營_產能與收入!$G$51-運營_產能與收入!$G$7/2-運營_產能與收入!$E$51))+39.283/各期收支!$C$56*(1+各期收支!$C$55)^0.5*(1-(1+各期收支!$C$55)^(-各期收支!$C$56))/各期收支!$C$55*(1+各期收支!$C$55)^(-(運營_產能與收入!$G$51-運營_產能與收入!$E$51)) -> 35.250054 | F57: =輸入與假設!G$117*(1+各期收支!$C$55)^(-(運營_產能與收入!$G$51-運營_產能與收入!$G$7/2-運營_產能與收入!$F$51))+39.283/各期收支!$C$56*(1+各期收支!$C$55)^0.5*(1-(1+各期收支!$C$55)^(-各期收支!$C$56))/各期收支!$C$55*(1+各期收支!$C$55)^(-(運營_產能與收入!$G$51-運營_產能與收入!$F$51)) -> 32.061207 | G57: =39.283/各期收支!$C$56*(1+各期收支!$C$55)^0.5*(1-(1+各期收支!$C$55)^(-各期收支!$C$56))/各期收支!$C$55*(1+各期收支!$C$55)^(-(運營_產能與收入!$G$51-運營_產能與收入!$G$51)) -> 28.686485 | I57: ＝期末之後各期到期表現金（期中付款）＋模型期後尾端 39.283（平均分攤、年中付款）的現值
A58: 未起租租約已起租部分的租賃負債（期末） | B58: US$bn | C58: =IF(OR(運營_產能與收入!$C$50<=0,運營_產能與收入!$C$56<=0),1*輸入與假設!$C$26/輸入與假設!$C$28/輸入與假設!$C$29/4/((1+各期收支!$C$55)^0.25-1)*(MIN(MAX(0,輸入與假設!C$118-(輸入與假設!$C$27)),輸入與假設!$C$28)-(1+各期收支!$C$55)^(-(4*輸入與假設!$C$29-MAX(0,輸入與假設!C$118-(輸入與假設!$C$27)))/4)*(1-(1+各期收支!$C$55)^(-MIN(MAX(0,輸入與假設!C$118-(輸入與假設!$C$27)),輸入與假設!$C$28)/4))/(1-(1+各期收支!$C$55)^(-0.25))),(1-運營_產能與收入!$C$56)*輸入與假設!$C$26/輸入與假設!$C$28/輸入與假設!$C$29/4/((1+各期收支!$C$55)^0.25-1)*(MIN(MAX(0,輸入與假設!C$118-(輸入與假設!$C$27)),輸入與假設!$C$28)-(1+各期收支!$C$55)^(-(4*輸入與假設!$C$29-MAX(0,輸入與假設!C$118-(輸入與假設!$C$27)))/4)*(1-(1+各期收支!$C$55)^(-MIN(MAX(0,輸入與假設!C$118-(輸入與假設!$C$27)),輸入與假設!$C$28)/4))/(1-(1+各期收支!$C$55)^(-0.25)))+運營_產能與收入!$C$56*輸入與假設!$C$26/輸入與假設!$C$28/輸入與假設!$C$29/4/((1+各期收支!$C$55)^0.25-1)*(MIN(MAX(0,輸入與假設!C$118-(輸入與假設!$C$27+運營_產能與收入!$C$50/3)),輸入與假設!$C$28)-(1+各期收支!$C$55)^(-(4*輸入與假設!$C$29-MAX(0,輸入與假設!C$118-(輸入與假設!$C$27+運營_產能與收入!$C$50/3)))/4)*(1-(1+各期收支!$C$55)^(-MIN(MAX(0,輸入與假設!C$118-(輸入與假設!$C$27+運營_產能與收入!$C$50/3)),輸入與假設!$C$28)/4))/(1-(1+各期收支!$C$55)^(-0.25)))) -> 41.415764 | D58: =IF(OR(運營_產能與收入!$C$50<=0,運營_產能與收入!$C$56<=0),1*輸入與假設!$C$26/輸入與假設!$C$28/輸入與假設!$C$29/4/((1+各期收支!$C$55)^0.25-1)*(MIN(MAX(0,輸入與假設!D$118-(輸入與假設!$C$27)),輸入與假設!$C$28)-(1+各期收支!$C$55)^(-(4*輸入與假設!$C$29-MAX(0,輸入與假設!D$118-(輸入與假設!$C$27)))/4)*(1-(1+各期收支!$C$55)^(-MIN(MAX(0,輸入與假設!D$118-(輸入與假設!$C$27)),輸入與假設!$C$28)/4))/(1-(1+各期收支!$C$55)^(-0.25))),(1-運營_產能與收入!$C$56)*輸入與假設!$C$26/輸入與假設!$C$28/輸入與假設!$C$29/4/((1+各期收支!$C$55)^0.25-1)*(MIN(MAX(0,輸入與假設!D$118-(輸入與假設!$C$27)),輸入與假設!$C$28)-(1+各期收支!$C$55)^(-(4*輸入與假設!$C$29-MAX(0,輸入與假設!D$118-(輸入與假設!$C$27)))/4)*(1-(1+各期收支!$C$55)^(-MIN(MAX(0,輸入與假設!D$118-(輸入與假設!$C$27)),輸入與假設!$C$28)/4))/(1-(1+各期收支!$C$55)^(-0.25)))+運營_產能與收入!$C$56*輸入與假設!$C$26/輸入與假設!$C$28/輸入與假設!$C$29/4/((1+各期收支!$C$55)^0.25-1)*(MIN(MAX(0,輸入與假設!D$118-(輸入與假設!$C$27+運營_產能與收入!$C$50/3)),輸入與假設!$C$28)-(1+各期收支!$C$55)^(-(4*輸入與假設!$C$29-MAX(0,輸入與假設!D$118-(輸入與假設!$C$27+運營_產能與收入!$C$50/3)))/4)*(1-(1+各期收支!$C$55)^(-MIN(MAX(0,輸入與假設!D$118-(輸入與假設!$C$27+運營_產能與收入!$C$50/3)),輸入與假設!$C$28)/4))/(1-(1+各期收支!$C$55)^(-0.25)))) -> 105.67726 | E58: =IF(OR(運營_產能與收入!$C$50<=0,運營_產能與收入!$C$56<=0),1*輸入與假設!$C$26/輸入與假設!$C$28/輸入與假設!$C$29/4/((1+各期收支!$C$55)^0.25-1)*(MIN(MAX(0,輸入與假設!E$118-(輸入與假設!$C$27)),輸入與假設!$C$28)-(1+各期收支!$C$55)^(-(4*輸入與假設!$C$29-MAX(0,輸入與假設!E$118-(輸入與假設!$C$27)))/4)*(1-(1+各期收支!$C$55)^(-MIN(MAX(0,輸入與假設!E$118-(輸入與假設!$C$27)),輸入與假設!$C$28)/4))/(1-(1+各期收支!$C$55)^(-0.25))),(1-運營_產能與收入!$C$56)*輸入與假設!$C$26/輸入與假設!$C$28/輸入與假設!$C$29/4/((1+各期收支!$C$55)^0.25-1)*(MIN(MAX(0,輸入與假設!E$118-(輸入與假設!$C$27)),輸入與假設!$C$28)-(1+各期收支!$C$55)^(-(4*輸入與假設!$C$29-MAX(0,輸入與假設!E$118-(輸入與假設!$C$27)))/4)*(1-(1+各期收支!$C$55)^(-MIN(MAX(0,輸入與假設!E$118-(輸入與假設!$C$27)),輸入與假設!$C$28)/4))/(1-(1+各期收支!$C$55)^(-0.25)))+運營_產能與收入!$C$56*輸入與假設!$C$26/輸入與假設!$C$28/輸入與假設!$C$29/4/((1+各期收支!$C$55)^0.25-1)*(MIN(MAX(0,輸入與假設!E$118-(輸入與假設!$C$27+運營_產能與收入!$C$50/3)),輸入與假設!$C$28)-(1+各期收支!$C$55)^(-(4*輸入與假設!$C$29-MAX(0,輸入與假設!E$118-(輸入與假設!$C$27+運營_產能與收入!$C$50/3)))/4)*(1-(1+各期收支!$C$55)^(-MIN(MAX(0,輸入與假設!E$118-(輸入與假設!$C$27+運營_產能與收入!$C$50/3)),輸入與假設!$C$28)/4))/(1-(1+各期收支!$C$55)^(-0.25)))) -> 167.31108 | F58: =IF(OR(運營_產能與收入!$C$50<=0,運營_產能與收入!$C$56<=0),1*輸入與假設!$C$26/輸入與假設!$C$28/輸入與假設!$C$29/4/((1+各期收支!$C$55)^0.25-1)*(MIN(MAX(0,輸入與假設!F$118-(輸入與假設!$C$27)),輸入與假設!$C$28)-(1+各期收支!$C$55)^(-(4*輸入與假設!$C$29-MAX(0,輸入與假設!F$118-(輸入與假設!$C$27)))/4)*(1-(1+各期收支!$C$55)^(-MIN(MAX(0,輸入與假設!F$118-(輸入與假設!$C$27)),輸入與假設!$C$28)/4))/(1-(1+各期收支!$C$55)^(-0.25))),(1-運營_產能與收入!$C$56)*輸入與假設!$C$26/輸入與假設!$C$28/輸入與假設!$C$29/4/((1+各期收支!$C$55)^0.25-1)*(MIN(MAX(0,輸入與假設!F$118-(輸入與假設!$C$27)),輸入與假設!$C$28)-(1+各期收支!$C$55)^(-(4*輸入與假設!$C$29-MAX(0,輸入與假設!F$118-(輸入與假設!$C$27)))/4)*(1-(1+各期收支!$C$55)^(-MIN(MAX(0,輸入與假設!F$118-(輸入與假設!$C$27)),輸入與假設!$C$28)/4))/(1-(1+各期收支!$C$55)^(-0.25)))+運營_產能與收入!$C$56*輸入與假設!$C$26/輸入與假設!$C$28/輸入與假設!$C$29/4/((1+各期收支!$C$55)^0.25-1)*(MIN(MAX(0,輸入與假設!F$118-(輸入與假設!$C$27+運營_產能與收入!$C$50/3)),輸入與假設!$C$28)-(1+各期收支!$C$55)^(-(4*輸入與假設!$C$29-MAX(0,輸入與假設!F$118-(輸入與假設!$C$27+運營_產能與收入!$C$50/3)))/4)*(1-(1+各期收支!$C$55)^(-MIN(MAX(0,輸入與假設!F$118-(輸入與假設!$C$27+運營_產能與收入!$C$50/3)),輸入與假設!$C$28)/4))/(1-(1+各期收支!$C$55)^(-0.25)))) -> 168.44783 | G58: =IF(OR(運營_產能與收入!$C$50<=0,運營_產能與收入!$C$56<=0),1*輸入與假設!$C$26/輸入與假設!$C$28/輸入與假設!$C$29/4/((1+各期收支!$C$55)^0.25-1)*(MIN(MAX(0,輸入與假設!G$118-(輸入與假設!$C$27)),輸入與假設!$C$28)-(1+各期收支!$C$55)^(-(4*輸入與假設!$C$29-MAX(0,輸入與假設!G$118-(輸入與假設!$C$27)))/4)*(1-(1+各期收支!$C$55)^(-MIN(MAX(0,輸入與假設!G$118-(輸入與假設!$C$27)),輸入與假設!$C$28)/4))/(1-(1+各期收支!$C$55)^(-0.25))),(1-運營_產能與收入!$C$56)*輸入與假設!$C$26/輸入與假設!$C$28/輸入與假設!$C$29/4/((1+各期收支!$C$55)^0.25-1)*(MIN(MAX(0,輸入與假設!G$118-(輸入與假設!$C$27)),輸入與假設!$C$28)-(1+各期收支!$C$55)^(-(4*輸入與假設!$C$29-MAX(0,輸入與假設!G$118-(輸入與假設!$C$27)))/4)*(1-(1+各期收支!$C$55)^(-MIN(MAX(0,輸入與假設!G$118-(輸入與假設!$C$27)),輸入與假設!$C$28)/4))/(1-(1+各期收支!$C$55)^(-0.25)))+運營_產能與收入!$C$56*輸入與假設!$C$26/輸入與假設!$C$28/輸入與假設!$C$29/4/((1+各期收支!$C$55)^0.25-1)*(MIN(MAX(0,輸入與假設!G$118-(輸入與假設!$C$27+運營_產能與收入!$C$50/3)),輸入與假設!$C$28)-(1+各期收支!$C$55)^(-(4*輸入與假設!$C$29-MAX(0,輸入與假設!G$118-(輸入與假設!$C$27+運營_產能與收入!$C$50/3)))/4)*(1-(1+各期收支!$C$55)^(-MIN(MAX(0,輸入與假設!G$118-(輸入與假設!$C$27+運營_產能與收入!$C$50/3)),輸入與假設!$C$28)/4))/(1-(1+各期收支!$C$55)^(-0.25)))) -> 160.75025 | I58: 每季起租 總額 ÷ 季數、每筆季末付租：已起租各筆剩餘租金現值合計（延誤連動部分起算季延後 延誤月數 ÷ 3）
A59: 租賃負債合計（期末） | B59: US$bn | C59: =C57+C58 -> 82.436654 | D59: =D57+D58 -> 143.90918 | E59: =E57+E58 -> 202.56113 | F59: =F57+F58 -> 200.50904 | G59: =G57+G58 -> 189.43673
A61: 期前融資瀑布（缺口在需要前一期先融好：額度 → 資產層新債 → 股權）
A62: 用途（不含新債利息） | B62: US$bn | C62: =C13+C16+C17+C22+C24+C25+C26+C27+C28+C23 -> 133.15615 | D62: =D13+D16+D17+D22+D24+D25+D26+D27+D28+D23 -> 126.72557 | E62: =E13+E16+E17+E22+E24+E25+E26+E27+E28+E23 -> 74.528151 | F62: =F13+F16+F17+F22+F24+F25+F26+F27+F28+F23 -> 103.02604 | G62: =G13+G16+G17+G22+G24+G25+G26+G27+G28+G23 -> 104.70956 | I62: 避免循環參照：直接由各支出列加總
A63: 新債期初餘額 | B63: US$bn | C63: =0 -> 0 | D63: =C90 -> 11.201651 | E63: =D90 -> 41.368293 | F63: =E90 -> 41.368293 | G63: =F90 -> 41.368293
A64: 新債利率 × 期間長度 | B64: % | C64: =C19*運營_產能與收入!C7 -> 0.0435 | D64: =D19*運營_產能與收入!D7 -> 0.058 | E64: =E19*運營_產能與收入!E7 -> 0.058 | F64: =F19*運營_產能與收入!F7 -> 0.058 | G64: =G19*運營_產能與收入!G7 -> 0.058
A65: 高息債期初餘額 | B65: US$bn | C65: =0 -> 0 | D65: =C92 -> 0 | E65: =D92 -> 0 | F65: =E92 -> 0 | G65: =F92 -> 0
A66: 可轉債（瀑布）期初餘額 | B66: US$bn | C66: =0 -> 0 | D66: =C93 -> 0 | E66: =D93 -> 0 | F66: =E93 -> 0 | G66: =F93 -> 0
A67: 可轉債票息 × 期間長度 | B67: % | C67: =輸入與假設!$C$160*運營_產能與收入!C7 -> 0 | D67: =輸入與假設!$C$160*運營_產能與收入!D7 -> 0 | E67: =輸入與假設!$C$160*運營_產能與收入!E7 -> 0 | F67: =輸入與假設!$C$160*運營_產能與收入!F7 -> 0 | G67: =輸入與假設!$C$160*運營_產能與收入!G7 -> 0
A68: 高息債利率 × 期間長度 | B68: % | C68: =(輸入與假設!$C$162+IF(輸入與假設!$C$165=1,MAX(0,輸入與假設!$C$164-輸入與假設!$C$166)/10000*輸入與假設!$C$167,0))*運營_產能與收入!C7 -> 0.09 | D68: =(輸入與假設!$C$162+IF(輸入與假設!$C$165=1,MAX(0,輸入與假設!$C$164-輸入與假設!$C$166)/10000*輸入與假設!$C$167,0))*運營_產能與收入!D7 -> 0.12 | E68: =(輸入與假設!$C$162+IF(輸入與假設!$C$165=1,MAX(0,輸入與假設!$C$164-輸入與假設!$C$166)/10000*輸入與假設!$C$167,0))*運營_產能與收入!E7 -> 0.12 | F68: =(輸入與假設!$C$162+IF(輸入與假設!$C$165=1,MAX(0,輸入與假設!$C$164-輸入與假設!$C$166)/10000*輸入與假設!$C$167,0))*運營_產能與收入!F7 -> 0.12 | G68: =(輸入與假設!$C$162+IF(輸入與假設!$C$165=1,MAX(0,輸入與假設!$C$164-輸入與假設!$C$166)/10000*輸入與假設!$C$167,0))*運營_產能與收入!G7 -> 0.12
A69: 融資前現金（扣既有新債利息） | B69: US$bn | C69: =C18+C40+C41+C42+C49-C62-C64*C63-C68*C65-C67*C66 -> -0.71437939 | D69: =D18+D40+D41+D42+D49-D62-D64*D63-D68*D65-D67*D66 -> -18.416976 | E69: =E18+E40+E41+E42+E49-E62-E64*E63-E68*E65-E67*E66 -> 42.038145 | F69: =F18+F40+F41+F42+F49-F62-F64*F63-F68*F65-F67*F66 -> 60.179667 | G69: =G18+G40+G41+G42+G49-G62-G64*G63-G68*G65-G67*G66 -> 72.496702
A70: 融資需求（補足至最低現金） | B70: US$bn | C70: =MAX(0,輸入與假設!$C$151-C69) -> 10.714379 | D70: =MAX(0,輸入與假設!$C$151-D69) -> 28.416976 | E70: =MAX(0,輸入與假設!$C$151-E69) -> 0 | F70: =MAX(0,輸入與假設!$C$151-F69) -> 0 | G70: =MAX(0,輸入與假設!$C$151-G69) -> 0
A71: 期初 backlog | B71: US$bn | C71: =輸入與假設!$C$31+輸入與假設!$C$32 -> 664 | D71: =C73 -> 599.26 | E71: =D73 -> 485.55 | F71: =E73 -> 362.71 | G71: =F73 -> 283.7509 | I71: FY27 期初＝8/31 RPO 664.0＋期後新增 0.0
A72: 新簽合約增量（年化增量×年期） | B72: US$bn | C72: =MAX(0,運營_產能與收入!C24/運營_產能與收入!C7-0)*輸入與假設!$C$148 -> 0 | D72: =MAX(0,運營_產能與收入!D24/運營_產能與收入!D7-運營_產能與收入!C24/運營_產能與收入!C7)*輸入與假設!$C$148 -> 0 | E72: =MAX(0,運營_產能與收入!E24/運營_產能與收入!E7-運營_產能與收入!D24/運營_產能與收入!D7)*輸入與假設!$C$148 -> 0 | F72: =MAX(0,運營_產能與收入!F24/運營_產能與收入!F7-運營_產能與收入!E24/運營_產能與收入!E7)*輸入與假設!$C$148 -> 54.61635 | G72: =MAX(0,運營_產能與收入!G24/運營_產能與收入!G7-運營_產能與收入!F24/運營_產能與收入!F7)*輸入與假設!$C$148 -> 25.6878
A73: 期末 backlog | B73: US$bn | C73: =C71-運營_產能與收入!C18-運營_產能與收入!C24+C72 -> 599.26 | D73: =D71-運營_產能與收入!D18-運營_產能與收入!D24+D72 -> 485.55 | E73: =E71-運營_產能與收入!E18-運營_產能與收入!E24+E72 -> 362.71 | F73: =F71-運營_產能與收入!F18-運營_產能與收入!F24+F72 -> 283.7509 | G73: =G71-運營_產能與收入!G18-運營_產能與收入!G24+G72 -> 169.79065 | I73: ＝期初 − 排程認列 − 新簽約認列 ＋ 新簽合約增量
A74: 既有債務＋期後可轉債（期末） | B74: US$bn | C74: =IF(輸入與假設!$C$144=1,資產負債_既有債務!C80,資產負債_既有債務!$E$62)+資產負債_既有債務!$E$65+資產負債_既有債務!C85 -> 122.897 | D74: =IF(輸入與假設!$C$144=1,資產負債_既有債務!D80,資產負債_既有債務!$E$62)+資產負債_既有債務!$E$65+資產負債_既有債務!D85 -> 112.75 | E74: =IF(輸入與假設!$C$144=1,資產負債_既有債務!E80,資產負債_既有債務!$E$62)+資產負債_既有債務!$E$65+資產負債_既有債務!E85 -> 107.25 | F74: =IF(輸入與假設!$C$144=1,資產負債_既有債務!F80,資產負債_既有債務!$E$62)+資產負債_既有債務!$E$65+資產負債_既有債務!F85 -> 100 | G74: =IF(輸入與假設!$C$144=1,資產負債_既有債務!G80,資產負債_既有債務!$E$62)+資產負債_既有債務!$E$65+資產負債_既有債務!G85 -> 90.25 | I74: ＝(依到期表遞減的既有本金，若關閉攤還則維持 125.904)＋期後新發可轉債 0
A75: 債務上限（投資級：倍數 × 當期 EBITDA；或債務／backlog） | B75: US$bn | C75: =IF(輸入與假設!$C$146="leaseAdj",輸入與假設!$C$147*(損益!C22+C16)/運營_產能與收入!C7-C59,IF(輸入與假設!$C$146="ebitda",輸入與假設!$C$147*損益!C22/運營_產能與收入!C7,輸入與假設!$C$145*C73)) -> 191.37957 | D75: =IF(輸入與假設!$C$146="leaseAdj",輸入與假設!$C$147*(損益!D22+D16)/運營_產能與收入!D7-D59,IF(輸入與假設!$C$146="ebitda",輸入與假設!$C$147*損益!D22/運營_產能與收入!D7,輸入與假設!$C$145*D73)) -> 242.19597 | E75: =IF(輸入與假設!$C$146="leaseAdj",輸入與假設!$C$147*(損益!E22+E16)/運營_產能與收入!E7-E59,IF(輸入與假設!$C$146="ebitda",輸入與假設!$C$147*損益!E22/運營_產能與收入!E7,輸入與假設!$C$145*E73)) -> 306.11719 | F75: =IF(輸入與假設!$C$146="leaseAdj",輸入與假設!$C$147*(損益!F22+F16)/運營_產能與收入!F7-F59,IF(輸入與假設!$C$146="ebitda",輸入與假設!$C$147*損益!F22/運營_產能與收入!F7,輸入與假設!$C$145*F73)) -> 350.31552 | G75: =IF(輸入與假設!$C$146="leaseAdj",輸入與假設!$C$147*(損益!G22+G16)/運營_產能與收入!G7-G59,IF(輸入與假設!$C$146="ebitda",輸入與假設!$C$147*損益!G22/運營_產能與收入!G7,輸入與假設!$C$145*G73)) -> 350.20541 | I75: leaseAdj：總債務 ≤ 倍數 ×(損益 EBITDA＋租金)（年化）− 租賃負債（v0.2）；ebitda：總債務 ≤ 倍數 × 損益 EBITDA（年化）；backlog：總債務 ≤ 倍數 × 期末 backlog（模板）
A76: 未動用額度（期初） | B76: US$bn | C76: =IF(輸入與假設!$C$143=1,輸入與假設!$C$142,0) -> 0 | D76: =C91 -> 0 | E76: =D91 -> 0 | F76: =E91 -> 0 | G76: =F91 -> 0
A77: 新債可借上限 | B77: US$bn | C77: =MAX(0,C75-(C74+C63+C66),C76) -> 68.482571 | D77: =MAX(0,D75-(D74+D63+D66),D76) -> 118.24432 | E77: =MAX(0,E75-(E74+E63+E66),E76) -> 157.4989 | F77: =MAX(0,F75-(F74+F63+F66),F76) -> 208.94722 | G77: =MAX(0,G75-(G74+G63+G66),G76) -> 218.58712 | I77: ＝MAX(上限 − 既有債務 − 期初新債 − 期初瀑布可轉債, 未動用額度)
A78: 新債舉借 | B78: US$bn | C78: =MIN(C77,C70/(1-C64)) -> 11.201651 | D78: =MIN(D77,D70/(1-D64)) -> 30.166642 | E78: =MIN(E77,E70/(1-E64)) -> 0 | F78: =MIN(F77,F70/(1-F64)) -> 0 | G78: =MIN(G77,G70/(1-G64)) -> 0 | I78: 期前融資：期初到位，當期全額計息，所以需求要除以 (1−利率×期間)
A79: 債務後剩餘需求 | B79: US$bn | C79: =MAX(0,C70+C64*C78-C78) -> 0 | D79: =MAX(0,D70+D64*D78-D78) -> 0 | E79: =MAX(0,E70+E64*E78-E78) -> 0 | F79: =MAX(0,F70+F64*F78-F78) -> 0 | G79: =MAX(0,G70+G64*G78-G78) -> 0
A80: 可轉債可發行上限 | B80: US$bn | C80: =MAX(0,輸入與假設!$C$159)*運營_產能與收入!C7 -> 0 | D80: =MAX(0,輸入與假設!$C$159)*運營_產能與收入!D7 -> 0 | E80: =MAX(0,輸入與假設!$C$159)*運營_產能與收入!E7 -> 0 | F80: =MAX(0,輸入與假設!$C$159)*運營_產能與收入!F7 -> 0 | G80: =MAX(0,輸入與假設!$C$159)*運營_產能與收入!G7 -> 0 | I80: ＝每年上限（隨情境）× 期間長度
A81: 可轉債發行 | B81: US$bn | C81: =MIN(C80,C79/(1-C67)) -> 0 | D81: =MIN(D80,D79/(1-D67)) -> 0 | E81: =MIN(E80,E79/(1-E67)) -> 0 | F81: =MIN(F80,F79/(1-F67)) -> 0 | G81: =MIN(G80,G79/(1-G67)) -> 0 | I81: 期前融資：期初到位、當期全額計息
A82: 可轉債後剩餘需求 | B82: US$bn | C82: =MAX(0,C79+C67*C81-C81) -> 0 | D82: =MAX(0,D79+D67*D81-D81) -> 0 | E82: =MAX(0,E79+E67*E81-E81) -> 0 | F82: =MAX(0,F79+F67*F81-F81) -> 0 | G82: =MAX(0,G79+G67*G81-G81) -> 0
A83: 每年股權吸收上限 | B83: US$bn | C83: =IF(輸入與假設!$C$154>=9,1E+099,輸入與假設!$C$154*輸入與假設!$C$152*輸入與假設!$C$155*運營_產能與收入!C7) -> 16.415485 | D83: =IF(輸入與假設!$C$154>=9,1E+099,輸入與假設!$C$154*輸入與假設!$C$152*輸入與假設!$C$155*運營_產能與收入!D7) -> 21.887313 | E83: =IF(輸入與假設!$C$154>=9,1E+099,輸入與假設!$C$154*輸入與假設!$C$152*輸入與假設!$C$155*運營_產能與收入!E7) -> 21.887313 | F83: =IF(輸入與假設!$C$154>=9,1E+099,輸入與假設!$C$154*輸入與假設!$C$152*輸入與假設!$C$155*運營_產能與收入!F7) -> 21.887313 | G83: =IF(輸入與假設!$C$154>=9,1E+099,輸入與假設!$C$154*輸入與假設!$C$152*輸入與假設!$C$155*運營_產能與收入!G7) -> 21.887313 | I83: ＝現市值（發行參考價 × 3.02374bn 股）× 上限 % × 期間長度
A84: 股權募資 | B84: US$bn | C84: =MIN(C82,C83) -> 0 | D84: =MIN(D82,D83) -> 0 | E84: =MIN(E82,E83) -> 0 | F84: =MIN(F82,F83) -> 0 | G84: =MIN(G82,G83) -> 0
A85: 高息債舉借（溢出） | B85: US$bn | C85: =(C82-C84)/(1-C68) -> 0 | D85: =(D82-D84)/(1-D68) -> 0 | E85: =(E82-E84)/(1-E68) -> 0 | F85: =(F82-F84)/(1-F68) -> 0 | G85: =(G82-G84)/(1-G68) -> 0
A86: 新債＋高息債利息（期初餘額＋本期舉借） | B86: US$bn | C86: =C64*(C63+C78)+C68*(C65+C85)+C67*(C66+C81) -> 0.48727183 | D86: =D64*(D63+D78)+D68*(D65+D85)+D67*(D66+D81) -> 2.399361 | E86: =E64*(E63+E78)+E68*(E65+E85)+E67*(E66+E81) -> 2.399361 | F86: =F64*(F63+F78)+F68*(F65+F85)+F67*(F66+F81) -> 2.399361 | G86: =G64*(G63+G78)+G68*(G65+G85)+G67*(G66+G81) -> 2.399361 | I86: 含瀑布可轉債票息（v0.1b）
A87: 發行價（現價×(1−折價)） | B87: US$ | C87: =輸入與假設!$C$152*(1-輸入與假設!$C$153) -> 130.293 | D87: =輸入與假設!$C$152*(1-輸入與假設!$C$153) -> 130.293 | E87: =輸入與假設!$C$152*(1-輸入與假設!$C$153) -> 130.293 | F87: =輸入與假設!$C$152*(1-輸入與假設!$C$153) -> 130.293 | G87: =輸入與假設!$C$152*(1-輸入與假設!$C$153) -> 130.293
A88: 新發行股數 | B88: bn | C88: =C84/C87 -> 0 | D88: =D84/D87 -> 0 | E88: =E84/E87 -> 0 | F88: =F84/F87 -> 0 | G88: =G84/G87 -> 0
A89: 累計新股 | B89: bn | C89: =C88 -> 0 | D89: =C89+D88 -> 0 | E89: =D89+E88 -> 0 | F89: =E89+F88 -> 0 | G89: =F89+G88 -> 0
A90: 新債期末餘額 | B90: US$bn | C90: =C63+C78 -> 11.201651 | D90: =D63+D78 -> 41.368293 | E90: =E63+E78 -> 41.368293 | F90: =F63+F78 -> 41.368293 | G90: =G63+G78 -> 41.368293
A91: 未動用額度（期末） | B91: US$bn | C91: =C76-MIN(C76,C78) -> 0 | D91: =D76-MIN(D76,D78) -> 0 | E91: =E76-MIN(E76,E78) -> 0 | F91: =F76-MIN(F76,F78) -> 0 | G91: =G76-MIN(G76,G78) -> 0
A92: 高息債期末餘額 | B92: US$bn | C92: =C65+C85 -> 0 | D92: =D65+D85 -> 0 | E92: =E65+E85 -> 0 | F92: =F65+F85 -> 0 | G92: =G65+G85 -> 0
A93: 可轉債（瀑布）期末餘額 | B93: US$bn | C93: =C66+C81 -> 0 | D93: =D66+D81 -> 0 | E93: =E66+E81 -> 0 | F93: =F66+F81 -> 0 | G93: =G66+G81 -> 0
A94: 期末總債務（既有＋可轉債＋新債＋高息債） | B94: US$bn | C94: =C74+C90+C93+C92 -> 134.09865 | D94: =D74+D90+D93+D92 -> 154.11829 | E94: =E74+E90+E93+E92 -> 148.61829 | F94: =F74+F90+F93+F92 -> 141.36829 | G94: =G74+G90+G93+G92 -> 131.61829
A95: 融資前累積現金 | B95: US$bn | C95: =C18+C40+C41+C42+C49-C62 -> -0.71437939 | D95: =C95+D40+D41-D62 -> -28.48166 | E95: =D95+E40+E41-E62 -> 5.9558463 | F95: =E95+F40+F41-F62 -> 26.496729 | G95: =F95+G40+G41-G62 -> 41.213125 | I95: 若不做任何新融資的累積現金；負值＝外部資金需求
A97: 四層橋（驗算）
A98: 期初現金（2026-05-31） | C98: =輸入與假設!$C$240 -> 31.289
A99: ＋ 營運缺口合計 | C99: =SUM(C50:G50) -> 23.452409
A100: ＋ 股權／可轉債合計 | C100: =SUM(C41:G41) -> 19.909
A101: ＋ 1Q 實際借款 | C101: =SUM(C42:G42) -> 0
A102: − capped call（1Q） | C102: =-SUM(C27:G27) -> 0
A103: ＋ 1Q 其他／受限現金調節 | C103: =SUM(C49:G49) -> -3.666
A104: ＋ 瀑布新債＋可轉債＋股權＋高息債合計 | C104: =SUM(C43:G43)+SUM(C44:G44)+SUM(C45:G45)+SUM(C46:G46) -> 41.368293
...

Sheet 季度追蹤
A1: 季度追蹤 — 焦點季的模型／共識／指引／實際與差距（由年度模型拆分；只用於追蹤，不影響年度數字與目標價）
A2: 設定與實際數在『輸入與假設』J 區，共識在 I 區；缺資料顯示「不適用」，實際數空白＝待公布。差距超過門檻的項目附差異原因（拆法＝所屬期間合計差距在門檻內）。第 2 區為 6 季路徑與拆分明細（預設收合）。
A4: 1｜焦點季（『輸入與假設』J 區選擇）：模型／共識／指引／實際與差距
A5: 指標 | B5: 單位 | C5: 模型 | D5: 共識 | E5: 模型 vs 共識 | F5: 指引（低） | G5: 指引（高） | H5: 模型 vs 指引中點 | I5: 實際 | J5: 實際 vs 模型 | K5: 實際 vs 共識 | L5: 實際 vs 指引中點 | M5: 利潤率 pt：模型 vs 共識 | N5: 模型 vs 指引 | O5: 實際 vs 模型 | P5: 實際 vs 共識 | Q5: 實際 vs 指引
A6: 焦點｜營收 | B6: US$bn | C6: =INDEX($C$22:$H$22,輸入與假設!$C$339) -> 21.03127 | D6: =INDEX($C$34:$H$34,輸入與假設!$C$339) -> 21.322 | E6: =INDEX($C$44:$H$44,輸入與假設!$C$339) -> -0.013635214 | F6: =IF(ISNUMBER(INDEX($C$31:$H$31,輸入與假設!$C$339)),INDEX($C$31:$H$31,輸入與假設!$C$339),"不適用") -> 20.875 | G6: =INDEX($C$32:$H$32,輸入與假設!$C$339) -> 21.518 | H6: =INDEX($C$45:$H$45,輸入與假設!$C$339) -> -0.0077951564 | I6: =IF(ISNUMBER(INDEX($C$38:$H$38,輸入與假設!$C$339)),INDEX($C$38:$H$38,輸入與假設!$C$339),"待公布") -> 待公布 | J6: =INDEX($C$46:$H$46,輸入與假設!$C$339) | K6: =INDEX($C$47:$H$47,輸入與假設!$C$339) | L6: =INDEX($C$48:$H$48,輸入與假設!$C$339)
A7: 焦點｜調整後 EBITDA | B7: US$bn | C7: =INDEX($C$28:$H$28,輸入與假設!$C$339) -> 12.397286 | D7: =INDEX($C$35:$H$35,輸入與假設!$C$339) -> 12.359 | E7: =INDEX($C$49:$H$49,輸入與假設!$C$339) -> 0.038286149 | F7: 不適用 | G7: 不適用 | H7: =INDEX($C$50:$H$50,輸入與假設!$C$339) -> 不適用 | I7: =IF(ISNUMBER(INDEX($C$39:$H$39,輸入與假設!$C$339)),INDEX($C$39:$H$39,輸入與假設!$C$339),"待公布") -> 待公布 | J7: =INDEX($C$51:$H$51,輸入與假設!$C$339) | K7: =INDEX($C$52:$H$52,輸入與假設!$C$339) | L7: =INDEX($C$53:$H$53,輸入與假設!$C$339) | M7: =INDEX($C$54:$H$54,輸入與假設!$C$339) -> 0.009833156 | N7: =INDEX($C$55:$H$55,輸入與假設!$C$339) -> 不適用 | O7: =INDEX($C$56:$H$56,輸入與假設!$C$339) | P7: =INDEX($C$57:$H$57,輸入與假設!$C$339) | Q7: =INDEX($C$58:$H$58,輸入與假設!$C$339)
A8: 焦點｜EBITDA 率 | B8: % | C8: =INDEX($C$27:$H$27,輸入與假設!$C$339) -> 0.58946921 | D8: =INDEX($C$36:$H$36,輸入與假設!$C$339) -> 0.57963606 | E8: =INDEX($C$59:$H$59,輸入與假設!$C$339) -> 0.009833156 | F8: 不適用 | G8: 不適用 | H8: =INDEX($C$60:$H$60,輸入與假設!$C$339) -> 不適用 | I8: =IF(ISNUMBER(INDEX($C$40:$H$40,輸入與假設!$C$339)),INDEX($C$40:$H$40,輸入與假設!$C$339),"待公布") -> 待公布 | J8: =INDEX($C$61:$H$61,輸入與假設!$C$339) | K8: =INDEX($C$62:$H$62,輸入與假設!$C$339) | L8: =INDEX($C$63:$H$63,輸入與假設!$C$339)
A9: 焦點｜調整後營業利益 | B9: US$bn | C9: =INDEX($C$30:$H$30,輸入與假設!$C$339) -> 8.8822081 | D9: 不適用 | E9: =INDEX($C$64:$H$64,輸入與假設!$C$339) -> 不適用 | F9: 不適用 | G9: 不適用 | H9: =INDEX($C$65:$H$65,輸入與假設!$C$339) -> 不適用 | I9: =IF(ISNUMBER(INDEX($C$41:$H$41,輸入與假設!$C$339)),INDEX($C$41:$H$41,輸入與假設!$C$339),"待公布") -> 待公布 | J9: =INDEX($C$66:$H$66,輸入與假設!$C$339) | K9: =INDEX($C$67:$H$67,輸入與假設!$C$339) | L9: =INDEX($C$68:$H$68,輸入與假設!$C$339) | M9: =INDEX($C$69:$H$69,輸入與假設!$C$339) -> 不適用 | N9: =INDEX($C$70:$H$70,輸入與假設!$C$339) -> 不適用 | O9: =INDEX($C$71:$H$71,輸入與假設!$C$339) | P9: =INDEX($C$72:$H$72,輸入與假設!$C$339) | Q9: =INDEX($C$73:$H$73,輸入與假設!$C$339)
A10: 焦點｜CapEx（毛額） | B10: US$bn | C10: =INDEX($C$33:$H$33,輸入與假設!$C$339) -> 25.865617 | D10: 不適用 | E10: =INDEX($C$74:$H$74,輸入與假設!$C$339) -> 不適用 | F10: 不適用 | G10: 不適用 | H10: =INDEX($C$75:$H$75,輸入與假設!$C$339) -> 不適用 | I10: =IF(ISNUMBER(INDEX($C$42:$H$42,輸入與假設!$C$339)),INDEX($C$42:$H$42,輸入與假設!$C$339),"待公布") -> 待公布 | J10: =INDEX($C$76:$H$76,輸入與假設!$C$339) | K10: =INDEX($C$77:$H$77,輸入與假設!$C$339) | L10: =INDEX($C$78:$H$78,輸入與假設!$C$339)
A11: 焦點｜季末已連網 MW-IT | B11: MW | C11: =INDEX($C$19:$H$19,輸入與假設!$C$339) -> 3251.3333 | D11: 不適用 | E11: =INDEX($C$79:$H$79,輸入與假設!$C$339) -> 不適用 | F11: 不適用 | G11: 不適用 | H11: =INDEX($C$80:$H$80,輸入與假設!$C$339) -> 不適用 | I11: =IF(ISNUMBER(INDEX($C$43:$H$43,輸入與假設!$C$339)),INDEX($C$43:$H$43,輸入與假設!$C$339),"待公布") -> 待公布 | J11: =INDEX($C$81:$H$81,輸入與假設!$C$339) | K11: =INDEX($C$82:$H$82,輸入與假設!$C$339) | L11: =INDEX($C$83:$H$83,輸入與假設!$C$339)
A12: 焦點｜季度 | C12: =INDEX($C$16:$H$16,輸入與假設!$C$339) -> Q2 FY27
A13: 焦點｜差異原因 | C13: =IF(INDEX($C$123:$H$123,輸入與假設!$C$339)="","無（差距皆在 "&IF(ROUND(ABS(輸入與假設!$C$333)*100,4)=INT(ROUND(ABS(輸入與假設!$C$333)*100,4)),TEXT(ROUND(ABS(輸入與假設!$C$333)*100,4),"0"),TEXT(ROUND(ABS(輸入與假設!$C$333)*100,4),"0.0"))&"%"&" 以內）",INDEX($C$123:$H$123,輸入與假設!$C$339)) -> 無（差距皆在 5% 以內）
A15: 2｜6 季路徑、共識、指引、實際與差距（明細；第 1 區以焦點季引用本區）
A16: 項目 | B16: 單位 | C16: Q2 FY27 | D16: Q3 FY27 | E16: Q4 FY27 | F16: Q1 FY28 | G16: Q2 FY28 | H16: Q3 FY28
A17: 所屬期間 | C17: =輸入與假設!C$338 -> 1 | D17: =輸入與假設!D$338 -> 1 | E17: =輸入與假設!E$338 -> 1 | F17: =輸入與假設!F$338 -> 2 | G17: =輸入與假設!G$338 -> 2 | H17: =輸入與假設!H$338 -> 2 | J17: 1＝2Q–4Q27、2＝FY28
A18: 季序 | C18: 1 | D18: 2 | E18: 3 | F18: 4 | G18: 5 | H18: 6 | J18: EBITDA 率直線的 x 軸
A19: 季末已連網 MW-IT（模型） | B19: MW | C19: =輸入與假設!$C$341+(輸入與假設!C$43-輸入與假設!$C$341)*1/3 -> 3251.3333 | D19: =輸入與假設!$C$341+(輸入與假設!C$43-輸入與假設!$C$341)*2/3 -> 3959.6667 | E19: =輸入與假設!$C$341+(輸入與假設!C$43-輸入與假設!$C$341)*3/3 -> 4668 | F19: =輸入與假設!C$43+(輸入與假設!D$43-輸入與假設!C$43)*1/3 -> 5612.3333 | G19: =輸入與假設!C$43+(輸入與假設!D$43-輸入與假設!C$43)*2/3 -> 6556.6667 | H19: =輸入與假設!C$43+(輸入與假設!D$43-輸入與假設!C$43)*3/3 -> 7501 | J19: 期初與期末 Accepted 之間線性內插；第 1 期起點見 J 區
A20: 平均在役 MW（Billable，拆分依據） | B20: MW | C20: =輸入與假設!$C$36+(運營_產能與收入!C$11-輸入與假設!$C$36)*1/6 -> 1863 | D20: =輸入與假設!$C$36+(運營_產能與收入!C$11-輸入與假設!$C$36)*3/6 -> 2193 | E20: =輸入與假設!$C$36+(運營_產能與收入!C$11-輸入與假設!$C$36)*5/6 -> 2523 | F20: =運營_產能與收入!C$11+(運營_產能與收入!D$11-運營_產能與收入!C$11)*1/6 -> 3165.125 | G20: =運營_產能與收入!C$11+(運營_產能與收入!D$11-運營_產能與收入!C$11)*3/6 -> 4119.375 | H20: =運營_產能與收入!C$11+(運營_產能與收入!D$11-運營_產能與收入!C$11)*5/6 -> 5073.625 | J20: 期初與期末 Billable 之間線性內插的季平均
A21: 季內新增 Accepted MW | B21: MW | C21: =C19-輸入與假設!$C$341 -> 708.33333 | D21: =D19-C19 -> 708.33333 | E21: =E19-D19 -> 708.33333 | F21: =F19-輸入與假設!C$43 -> 944.33333 | G21: =G19-F19 -> 944.33333 | H21: =H19-G19 -> 944.33333 | J21: CapEx 拆分依據
A22: 營收（模型） | B22: US$bn | C22: =輸入與假設!$C$340+1*(損益!C9-3*輸入與假設!$C$340)/6 -> 21.03127 | D22: =輸入與假設!$C$340+2*(損益!C9-3*輸入與假設!$C$340)/6 -> 22.71754 | E22: =輸入與假設!$C$340+3*(損益!C9-3*輸入與假設!$C$340)/6 -> 24.40381 | F22: =損益!D9*F20/(F20+G20+H20) -> 32.113284 | G22: =損益!D9*G20/(F20+G20+H20) -> 41.795082 | H22: =損益!D9*H20/(F20+G20+H20) -> 51.476881 | J22: 拆分方法見『輸入與假設』J 區與 HTML「拆分方法」
A23: EBITDA 率直線｜各期營收合計 S | C23: =C22+D22+E22 -> 68.15262 | D23: =F22+G22+H22 -> 125.38525 | J23: 欄＝期間（2Q–4Q27、FY28）
A24: EBITDA 率直線｜營收 × 季序合計 T | C24: =C22*C18+D22*D18+E22*E18 -> 139.67778 | D24: =F22*F18+G22*G18+H22*H18 -> 646.28983 | J24: 欄＝期間（2Q–4Q27、FY28）
A25: EBITDA 率直線｜年度 EBITDA E | C25: =損益!C22 -> 40.064417 | D25: =損益!D22 -> 73.113611 | J25: 欄＝期間（2Q–4Q27、FY28）
A26: EBITDA 率直線｜截距 a／斜率 b | C26: =(C25*D24-C24*D25)/(C23*D24-C24*D23) -> 0.5909995 | D26: =(C23*D25-D23*C25)/(C23*D24-C24*D23) -> -0.0015302838 | J26: 解兩式：Σ營收×(a＋b×季序)＝各期年度 EBITDA
A27: EBITDA 率（模型） | B27: % | C27: =$C$26+$D$26*C18 -> 0.58946921 | D27: =$C$26+$D$26*D18 -> 0.58793893 | E27: =$C$26+$D$26*E18 -> 0.58640865 | F27: =$C$26+$D$26*F18 -> 0.58487836 | G27: =$C$26+$D$26*G18 -> 0.58334808 | H27: =$C$26+$D$26*H18 -> 0.58181779 | J27: 跨季一條直線，季度 EBITDA 加總＝年度
A28: 調整後 EBITDA（模型） | B28: US$bn | C28: =C22*C27 -> 12.397286 | D28: =D22*D27 -> 13.356526 | E28: =E22*E27 -> 14.310605 | F28: =F22*F27 -> 18.782365 | G28: =G22*G27 -> 24.381081 | H28: =H22*H27 -> 29.950165
A29: 車隊折舊（模型） | B29: US$bn | C29: =(輸入與假設!C$133+運營_產能與收入!C$54*1/6)/輸入與假設!$C$105*輸入與假設!C$41/3 -> 3.515078 | D29: =(輸入與假設!C$133+運營_產能與收入!C$54*3/6)/輸入與假設!$C$105*輸入與假設!C$41/3 -> 4.2335674 | E29: =(輸入與假設!C$133+運營_產能與收入!C$54*5/6)/輸入與假設!$C$105*輸入與假設!C$41/3 -> 4.9520567 | F29: =(輸入與假設!D$133+運營_產能與收入!D$54*1/6)/輸入與假設!$C$105*輸入與假設!D$41/3 -> 7.9185994 | G29: =(輸入與假設!D$133+運營_產能與收入!D$54*3/6)/輸入與假設!$C$105*輸入與假設!D$41/3 -> 9.5923278 | H29: =(輸入與假設!D$133+運營_產能與收入!D$54*5/6)/輸入與假設!$C$105*輸入與假設!D$41/3 -> 11.266056 | J29: 依期內平均 PP&E（與年度車隊折舊公式相同）
A30: 調整後營業利益（模型） | B30: US$bn | C30: =C28-C29 -> 8.8822081 | D30: =D28-D29 -> 9.1229587 | E30: =E28-E29 -> 9.3585484 | F30: =F28-F29 -> 10.863766 | G30: =G28-G29 -> 14.788753 | H30: =H28-H29 -> 18.684109 | J30: ＝調整後 EBITDA − 車隊折舊（未扣 SBC）
A31: 指引｜營收（低） | B31: US$bn | C31: =IF(ISNUMBER(輸入與假設!C$350),輸入與假設!C$350,"不適用") -> 20.875 | D31: =IF(ISNUMBER(輸入與假設!D$350),輸入與假設!D$350,"不適用") -> 不適用 | E31: =IF(ISNUMBER(輸入與假設!E$350),輸入與假設!E$350,"不適用") -> 不適用 | F31: =IF(ISNUMBER(輸入與假設!F$350),輸入與假設!F$350,"不適用") -> 不適用 | G31: =IF(ISNUMBER(輸入與假設!G$350),輸入與假設!G$350,"不適用") -> 不適用 | H31: =IF(ISNUMBER(輸入與假設!H$350),輸入與假設!H$350,"不適用") -> 不適用
A32: 指引｜營收（高） | B32: US$bn | C32: =IF(ISNUMBER(輸入與假設!C$351),輸入與假設!C$351,"不適用") -> 21.518 | D32: =IF(ISNUMBER(輸入與假設!D$351),輸入與假設!D$351,"不適用") -> 不適用 | E32: =IF(ISNUMBER(輸入與假設!E$351),輸入與假設!E$351,"不適用") -> 不適用 | F32: =IF(ISNUMBER(輸入與假設!F$351),輸入與假設!F$351,"不適用") -> 不適用 | G32: =IF(ISNUMBER(輸入與假設!G$351),輸入與假設!G$351,"不適用") -> 不適用 | H32: =IF(ISNUMBER(輸入與假設!H$351),輸入與假設!H$351,"不適用") -> 不適用
A33: CapEx（毛額）（模型） | B33: US$bn | C33: =IF((C21+D21+E21)>0,輸入與假設!C$135*C21/(C21+D21+E21),輸入與假設!C$135/3) -> 25.865617 | D33: =IF((C21+D21+E21)>0,輸入與假設!C$135*D21/(C21+D21+E21),輸入與假設!C$135/3) -> 25.865617 | E33: =IF((C21+D21+E21)>0,輸入與假設!C$135*E21/(C21+D21+E21),輸入與假設!C$135/3) -> 25.865617 | F33: =IF((F21+G21+H21)>0,輸入與假設!D$135*F21/(F21+G21+H21),輸入與假設!D$135/3) -> 28.673652 | G33: =IF((F21+G21+H21)>0,輸入與假設!D$135*G21/(F21+G21+H21),輸入與假設!D$135/3) -> 28.673652 | H33: =IF((F21+G21+H21)>0,輸入與假設!D$135*H21/(F21+G21+H21),輸入與假設!D$135/3) -> 28.673652 | J33: 依季內新增 Accepted MW
A34: 共識｜營收 | B34: US$bn | C34: =IF(ISNUMBER(輸入與假設!$C$305),輸入與假設!$C$305,"不適用") -> 21.322 | D34: =IF(ISNUMBER(輸入與假設!$D$305),輸入與假設!$D$305,"不適用") -> 23.38 | E34: 不適用 | F34: 不適用 | G34: 不適用 | H34: 不適用 | J34: I 區季度共識 [Interested-party]
A35: 共識｜調整後 EBITDA | B35: US$bn | C35: =IF(ISNUMBER(輸入與假設!$C$306),輸入與假設!$C$306,"不適用") -> 12.359 | D35: =IF(ISNUMBER(輸入與假設!$D$306),輸入與假設!$D$306,"不適用") -> 13.515 | E35: 不適用 | F35: 不適用 | G35: 不適用 | H35: 不適用 | J35: I 區季度共識 [Interested-party]
A36: 共識｜EBITDA 率 [Derived] | B36: % | C36: =IF(AND(ISNUMBER(輸入與假設!$C$306),ISNUMBER(輸入與假設!$C$305)),輸入與假設!$C$306/輸入與假設!$C$305,"不適用") -> 0.57963606 | D36: =IF(AND(ISNUMBER(輸入與假設!$D$306),ISNUMBER(輸入與假設!$D$305)),輸入與假設!$D$306/輸入與假設!$D$305,"不適用") -> 0.57805817 | E36: 不適用 | F36: 不適用 | G36: 不適用 | H36: 不適用 | J36: ＝共識 EBITDA ÷ 共識營收
A37: 共識非 GAAP 營業利益（含 SBC 調整，口徑不同） | B37: US$bn | C37: =IF(ISNUMBER(輸入與假設!$C$307),輸入與假設!$C$307,"不適用") -> 8.536 | D37: =IF(ISNUMBER(輸入與假設!$D$307),輸入與假設!$D$307,"不適用") -> 9.23 | E37: 不適用 | F37: 不適用 | G37: 不適用 | H37: 不適用 | J37: 口徑未揭露：只列不比較
A38: 實際｜營收 | B38: US$bn | C38: =IF(ISNUMBER(輸入與假設!C$342),輸入與假設!C$342,"") | D38: =IF(ISNUMBER(輸入與假設!D$342),輸入與假設!D$342,"") | E38: =IF(ISNUMBER(輸入與假設!E$342),輸入與假設!E$342,"") | F38: =IF(ISNUMBER(輸入與假設!F$342),輸入與假設!F$342,"") | G38: =IF(ISNUMBER(輸入與假設!G$342),輸入與假設!G$342,"") | H38: =IF(ISNUMBER(輸入與假設!H$342),輸入與假設!H$342,"")
A39: 實際｜調整後 EBITDA | B39: US$bn | C39: =IF(ISNUMBER(輸入與假設!C$343),輸入與假設!C$343,"") | D39: =IF(ISNUMBER(輸入與假設!D$343),輸入與假設!D$343,"") | E39: =IF(ISNUMBER(輸入與假設!E$343),輸入與假設!E$343,"") | F39: =IF(ISNUMBER(輸入與假設!F$343),輸入與假設!F$343,"") | G39: =IF(ISNUMBER(輸入與假設!G$343),輸入與假設!G$343,"") | H39: =IF(ISNUMBER(輸入與假設!H$343),輸入與假設!H$343,"")
A40: 實際｜EBITDA 率 | B40: % | C40: =IF(AND(ISNUMBER(輸入與假設!C$343),ISNUMBER(輸入與假設!C$342)),輸入與假設!C$343/輸入與假設!C$342,"") | D40: =IF(AND(ISNUMBER(輸入與假設!D$343),ISNUMBER(輸入與假設!D$342)),輸入與假設!D$343/輸入與假設!D$342,"") | E40: =IF(AND(ISNUMBER(輸入與假設!E$343),ISNUMBER(輸入與假設!E$342)),輸入與假設!E$343/輸入與假設!E$342,"") | F40: =IF(AND(ISNUMBER(輸入與假設!F$343),ISNUMBER(輸入與假設!F$342)),輸入與假設!F$343/輸入與假設!F$342,"") | G40: =IF(AND(ISNUMBER(輸入與假設!G$343),ISNUMBER(輸入與假設!G$342)),輸入與假設!G$343/輸入與假設!G$342,"") | H40: =IF(AND(ISNUMBER(輸入與假設!H$343),ISNUMBER(輸入與假設!H$342)),輸入與假設!H$343/輸入與假設!H$342,"") | J40: ＝實際 EBITDA ÷ 實際營收
A41: 實際｜調整後營業利益 | B41: US$bn | C41: =IF(ISNUMBER(輸入與假設!C$344),輸入與假設!C$344,"") | D41: =IF(ISNUMBER(輸入與假設!D$344),輸入與假設!D$344,"") | E41: =IF(ISNUMBER(輸入與假設!E$344),輸入與假設!E$344,"") | F41: =IF(ISNUMBER(輸入與假設!F$344),輸入與假設!F$344,"") | G41: =IF(ISNUMBER(輸入與假設!G$344),輸入與假設!G$344,"") | H41: =IF(ISNUMBER(輸入與假設!H$344),輸入與假設!H$344,"")
A42: 實際｜CapEx（毛額） | B42: US$bn | C42: =IF(ISNUMBER(輸入與假設!C$345),輸入與假設!C$345,"") | D42: =IF(ISNUMBER(輸入與假設!D$345),輸入與假設!D$345,"") | E42: =IF(ISNUMBER(輸入與假設!E$345),輸入與假設!E$345,"") | F42: =IF(ISNUMBER(輸入與假設!F$345),輸入與假設!F$345,"") | G42: =IF(ISNUMBER(輸入與假設!G$345),輸入與假設!G$345,"") | H42: =IF(ISNUMBER(輸入與假設!H$345),輸入與假設!H$345,"")
A43: 實際｜季末已交付 MW（口徑不明） | B43: MW | C43: =IF(ISNUMBER(輸入與假設!C$346),輸入與假設!C$346,"") | D43: =IF(ISNUMBER(輸入與假設!D$346),輸入與假設!D$346,"") | E43: =IF(ISNUMBER(輸入與假設!E$346),輸入與假設!E$346,"") | F43: =IF(ISNUMBER(輸入與假設!F$346),輸入與假設!F$346,"") | G43: =IF(ISNUMBER(輸入與假設!G$346),輸入與假設!G$346,"") | H43: =IF(ISNUMBER(輸入與假設!H$346),輸入與假設!H$346,"")
A44: 差距｜營收｜模型 vs 共識 | B44: % | C44: =IF(AND(ISNUMBER(C22),ISNUMBER(C34),C34<>0),C22/(C34)-1,"不適用") -> -0.013635214 | D44: =IF(AND(ISNUMBER(D22),ISNUMBER(D34),D34<>0),D22/(D34)-1,"不適用") -> -0.028334477 | E44: =IF(AND(ISNUMBER(E22),ISNUMBER(E34),E34<>0),E22/(E34)-1,"不適用") -> 不適用 | F44: =IF(AND(ISNUMBER(F22),ISNUMBER(F34),F34<>0),F22/(F34)-1,"不適用") -> 不適用 | G44: =IF(AND(ISNUMBER(G22),ISNUMBER(G34),G34<>0),G22/(G34)-1,"不適用") -> 不適用 | H44: =IF(AND(ISNUMBER(H22),ISNUMBER(H34),H34<>0),H22/(H34)-1,"不適用") -> 不適用
A45: 差距｜營收｜模型 vs 指引中點 | B45: % | C45: =IF(AND(ISNUMBER(C22),ISNUMBER(C31),ISNUMBER(C32)),C22/(((C31+C32)/2))-1,"不適用") -> -0.0077951564 | D45: =IF(AND(ISNUMBER(D22),ISNUMBER(D31),ISNUMBER(D32)),D22/(((D31+D32)/2))-1,"不適用") -> 不適用 | E45: =IF(AND(ISNUMBER(E22),ISNUMBER(E31),ISNUMBER(E32)),E22/(((E31+E32)/2))-1,"不適用") -> 不適用 | F45: =IF(AND(ISNUMBER(F22),ISNUMBER(F31),ISNUMBER(F32)),F22/(((F31+F32)/2))-1,"不適用") -> 不適用 | G45: =IF(AND(ISNUMBER(G22),ISNUMBER(G31),ISNUMBER(G32)),G22/(((G31+G32)/2))-1,"不適用") -> 不適用 | H45: =IF(AND(ISNUMBER(H22),ISNUMBER(H31),ISNUMBER(H32)),H22/(((H31+H32)/2))-1,"不適用") -> 不適用
A46: 差距｜營收｜實際 vs 模型 | B46: % | C46: =IF(ISNUMBER(C38),IF(AND(ISNUMBER(C22),C22<>0),C38/(C22)-1,"不適用"),"") | D46: =IF(ISNUMBER(D38),IF(AND(ISNUMBER(D22),D22<>0),D38/(D22)-1,"不適用"),"") | E46: =IF(ISNUMBER(E38),IF(AND(ISNUMBER(E22),E22<>0),E38/(E22)-1,"不適用"),"") | F46: =IF(ISNUMBER(F38),IF(AND(ISNUMBER(F22),F22<>0),F38/(F22)-1,"不適用"),"") | G46: =IF(ISNUMBER(G38),IF(AND(ISNUMBER(G22),G22<>0),G38/(G22)-1,"不適用"),"") | H46: =IF(ISNUMBER(H38),IF(AND(ISNUMBER(H22),H22<>0),H38/(H22)-1,"不適用"),"")
A47: 差距｜營收｜實際 vs 共識 | B47: % | C47: =IF(ISNUMBER(C38),IF(AND(ISNUMBER(C34),C34<>0),C38/(C34)-1,"不適用"),"") | D47: =IF(ISNUMBER(D38),IF(AND(ISNUMBER(D34),D34<>0),D38/(D34)-1,"不適用"),"") | E47: =IF(ISNUMBER(E38),IF(AND(ISNUMBER(E34),E34<>0),E38/(E34)-1,"不適用"),"") | F47: =IF(ISNUMBER(F38),IF(AND(ISNUMBER(F34),F34<>0),F38/(F34)-1,"不適用"),"") | G47: =IF(ISNUMBER(G38),IF(AND(ISNUMBER(G34),G34<>0),G38/(G34)-1,"不適用"),"") | H47: =IF(ISNUMBER(H38),IF(AND(ISNUMBER(H34),H34<>0),H38/(H34)-1,"不適用"),"")
A48: 差距｜營收｜實際 vs 指引中點 | B48: % | C48: =IF(ISNUMBER(C38),IF(AND(ISNUMBER(C31),ISNUMBER(C32)),C38/(((C31+C32)/2))-1,"不適用"),"") | D48: =IF(ISNUMBER(D38),IF(AND(ISNUMBER(D31),ISNUMBER(D32)),D38/(((D31+D32)/2))-1,"不適用"),"") | E48: =IF(ISNUMBER(E38),IF(AND(ISNUMBER(E31),ISNUMBER(E32)),E38/(((E31+E32)/2))-1,"不適用"),"") | F48: =IF(ISNUMBER(F38),IF(AND(ISNUMBER(F31),ISNUMBER(F32)),F38/(((F31+F32)/2))-1,"不適用"),"") | G48: =IF(ISNUMBER(G38),IF(AND(ISNUMBER(G31),ISNUMBER(G32)),G38/(((G31+G32)/2))-1,"不適用"),"") | H48: =IF(ISNUMBER(H38),IF(AND(ISNUMBER(H31),ISNUMBER(H32)),H38/(((H31+H32)/2))-1,"不適用"),"")
A49: 差距｜調整後 EBITDA｜模型 vs 共識 | B49: US$bn | C49: =IF(AND(ISNUMBER(C28),ISNUMBER(C35)),C28-(C35),"不適用") -> 0.038286149 | D49: =IF(AND(ISNUMBER(D28),ISNUMBER(D35)),D28-(D35),"不適用") -> -0.15847391 | E49: =IF(AND(ISNUMBER(E28),ISNUMBER(E35)),E28-(E35),"不適用") -> 不適用 | F49: =IF(AND(ISNUMBER(F28),ISNUMBER(F35)),F28-(F35),"不適用") -> 不適用 | G49: =IF(AND(ISNUMBER(G28),ISNUMBER(G35)),G28-(G35),"不適用") -> 不適用 | H49: =IF(AND(ISNUMBER(H28),ISNUMBER(H35)),H28-(H35),"不適用") -> 不適用
A50: 差距｜調整後 EBITDA｜模型 vs 指引中點 | B50: US$bn | C50: 不適用 | D50: 不適用 | E50: 不適用 | F50: 不適用 | G50: 不適用 | H50: 不適用
A51: 差距｜調整後 EBITDA｜實際 vs 模型 | B51: US$bn | C51: =IF(ISNUMBER(C39),IF(AND(ISNUMBER(C28)),C39-(C28),"不適用"),"") | D51: =IF(ISNUMBER(D39),IF(AND(ISNUMBER(D28)),D39-(D28),"不適用"),"") | E51: =IF(ISNUMBER(E39),IF(AND(ISNUMBER(E28)),E39-(E28),"不適用"),"") | F51: =IF(ISNUMBER(F39),IF(AND(ISNUMBER(F28)),F39-(F28),"不適用"),"") | G51: =IF(ISNUMBER(G39),IF(AND(ISNUMBER(G28)),G39-(G28),"不適用"),"") | H51: =IF(ISNUMBER(H39),IF(AND(ISNUMBER(H28)),H39-(H28),"不適用"),"")
A52: 差距｜調整後 EBITDA｜實際 vs 共識 | B52: US$bn | C52: =IF(ISNUMBER(C39),IF(AND(ISNUMBER(C35)),C39-(C35),"不適用"),"") | D52: =IF(ISNUMBER(D39),IF(AND(ISNUMBER(D35)),D39-(D35),"不適用"),"") | E52: =IF(ISNUMBER(E39),IF(AND(ISNUMBER(E35)),E39-(E35),"不適用"),"") | F52: =IF(ISNUMBER(F39),IF(AND(ISNUMBER(F35)),F39-(F35),"不適用"),"") | G52: =IF(ISNUMBER(G39),IF(AND(ISNUMBER(G35)),G39-(G35),"不適用"),"") | H52: =IF(ISNUMBER(H39),IF(AND(ISNUMBER(H35)),H39-(H35),"不適用"),"")
A53: 差距｜調整後 EBITDA｜實際 vs 指引中點 | B53: US$bn | C53: =IF(ISNUMBER(C39),"不適用","") | D53: =IF(ISNUMBER(D39),"不適用","") | E53: =IF(ISNUMBER(E39),"不適用","") | F53: =IF(ISNUMBER(F39),"不適用","") | G53: =IF(ISNUMBER(G39),"不適用","") | H53: =IF(ISNUMBER(H39),"不適用","")
A54: 差距｜調整後 EBITDA｜模型 vs 共識（利潤率 pt） | B54: pt | C54: =IF(AND(ISNUMBER(C28),ISNUMBER(C22),C22<>0,ISNUMBER(C35),ISNUMBER(C34),C34<>0),C28/C22-C35/C34,"不適用") -> 0.009833156 | D54: =IF(AND(ISNUMBER(D28),ISNUMBER(D22),D22<>0,ISNUMBER(D35),ISNUMBER(D34),D34<>0),D28/D22-D35/D34,"不適用") -> 0.0098807595 | E54: =IF(AND(ISNUMBER(E28),ISNUMBER(E22),E22<>0,ISNUMBER(E35),ISNUMBER(E34),E34<>0),E28/E22-E35/E34,"不適用") -> 不適用 | F54: =IF(AND(ISNUMBER(F28),ISNUMBER(F22),F22<>0,ISNUMBER(F35),ISNUMBER(F34),F34<>0),F28/F22-F35/F34,"不適用") -> 不適用 | G54: =IF(AND(ISNUMBER(G28),ISNUMBER(G22),G22<>0,ISNUMBER(G35),ISNUMBER(G34),G34<>0),G28/G22-G35/G34,"不適用") -> 不適用 | H54: =IF(AND(ISNUMBER(H28),ISNUMBER(H22),H22<>0,ISNUMBER(H35),ISNUMBER(H34),H34<>0),H28/H22-H35/H34,"不適用") -> 不適用
A55: 差距｜調整後 EBITDA｜模型 vs 指引中點（利潤率 pt） | B55: pt | C55: 不適用 | D55: 不適用 | E55: 不適用 | F55: 不適用 | G55: 不適用 | H55: 不適用
A56: 差距｜調整後 EBITDA｜實際 vs 模型（利潤率 pt） | B56: pt | C56: =IF(ISNUMBER(C39),IF(AND(ISNUMBER(C39),ISNUMBER(C38),C38<>0,ISNUMBER(C28),ISNUMBER(C22),C22<>0),C39/C38-C28/C22,"不適用"),"") | D56: =IF(ISNUMBER(D39),IF(AND(ISNUMBER(D39),ISNUMBER(D38),D38<>0,ISNUMBER(D28),ISNUMBER(D22),D22<>0),D39/D38-D28/D22,"不適用"),"") | E56: =IF(ISNUMBER(E39),IF(AND(ISNUMBER(E39),ISNUMBER(E38),E38<>0,ISNUMBER(E28),ISNUMBER(E22),E22<>0),E39/E38-E28/E22,"不適用"),"") | F56: =IF(ISNUMBER(F39),IF(AND(ISNUMBER(F39),ISNUMBER(F38),F38<>0,ISNUMBER(F28),ISNUMBER(F22),F22<>0),F39/F38-F28/F22,"不適用"),"") | G56: =IF(ISNUMBER(G39),IF(AND(ISNUMBER(G39),ISNUMBER(G38),G38<>0,ISNUMBER(G28),ISNUMBER(G22),G22<>0),G39/G38-G28/G22,"不適用"),"") | H56: =IF(ISNUMBER(H39),IF(AND(ISNUMBER(H39),ISNUMBER(H38),H38<>0,ISNUMBER(H28),ISNUMBER(H22),H22<>0),H39/H38-H28/H22,"不適用"),"")
A57: 差距｜調整後 EBITDA｜實際 vs 共識（利潤率 pt） | B57: pt | C57: =IF(ISNUMBER(C39),IF(AND(ISNUMBER(C39),ISNUMBER(C38),C38<>0,ISNUMBER(C35),ISNUMBER(C34),C34<>0),C39/C38-C35/C34,"不適用"),"") | D57: =IF(ISNUMBER(D39),IF(AND(ISNUMBER(D39),ISNUMBER(D38),D38<>0,ISNUMBER(D35),ISNUMBER(D34),D34<>0),D39/D38-D35/D34,"不適用"),"") | E57: =IF(ISNUMBER(E39),IF(AND(ISNUMBER(E39),ISNUMBER(E38),E38<>0,ISNUMBER(E35),ISNUMBER(E34),E34<>0),E39/E38-E35/E34,"不適用"),"") | F57: =IF(ISNUMBER(F39),IF(AND(ISNUMBER(F39),ISNUMBER(F38),F38<>0,ISNUMBER(F35),ISNUMBER(F34),F34<>0),F39/F38-F35/F34,"不適用"),"") | G57: =IF(ISNUMBER(G39),IF(AND(ISNUMBER(G39),ISNUMBER(G38),G38<>0,ISNUMBER(G35),ISNUMBER(G34),G34<>0),G39/G38-G35/G34,"不適用"),"") | H57: =IF(ISNUMBER(H39),IF(AND(ISNUMBER(H39),ISNUMBER(H38),H38<>0,ISNUMBER(H35),ISNUMBER(H34),H34<>0),H39/H38-H35/H34,"不適用"),"")
A58: 差距｜調整後 EBITDA｜實際 vs 指引中點（利潤率 pt） | B58: pt | C58: =IF(ISNUMBER(C39),"不適用","") | D58: =IF(ISNUMBER(D39),"不適用","") | E58: =IF(ISNUMBER(E39),"不適用","") | F58: =IF(ISNUMBER(F39),"不適用","") | G58: =IF(ISNUMBER(G39),"不適用","") | H58: =IF(ISNUMBER(H39),"不適用","")
A59: 差距｜EBITDA 率｜模型 vs 共識 | B59: pt | C59: =IF(AND(ISNUMBER(C27),ISNUMBER(C36)),C27-(C36),"不適用") -> 0.009833156 | D59: =IF(AND(ISNUMBER(D27),ISNUMBER(D36)),D27-(D36),"不適用") -> 0.0098807595 | E59: =IF(AND(ISNUMBER(E27),ISNUMBER(E36)),E27-(E36),"不適用") -> 不適用 | F59: =IF(AND(ISNUMBER(F27),ISNUMBER(F36)),F27-(F36),"不適用") -> 不適用 | G59: =IF(AND(ISNUMBER(G27),ISNUMBER(G36)),G27-(G36),"不適用") -> 不適用 | H59: =IF(AND(ISNUMBER(H27),ISNUMBER(H36)),H27-(H36),"不適用") -> 不適用
A60: 差距｜EBITDA 率｜模型 vs 指引中點 | B60: pt | C60: 不適用 | D60: 不適用 | E60: 不適用 | F60: 不適用 | G60: 不適用 | H60: 不適用
A61: 差距｜EBITDA 率｜實際 vs 模型 | B61: pt | C61: =IF(ISNUMBER(C40),IF(AND(ISNUMBER(C27)),C40-(C27),"不適用"),"") | D61: =IF(ISNUMBER(D40),IF(AND(ISNUMBER(D27)),D40-(D27),"不適用"),"") | E61: =IF(ISNUMBER(E40),IF(AND(ISNUMBER(E27)),E40-(E27),"不適用"),"") | F61: =IF(ISNUMBER(F40),IF(AND(ISNUMBER(F27)),F40-(F27),"不適用"),"") | G61: =IF(ISNUMBER(G40),IF(AND(ISNUMBER(G27)),G40-(G27),"不適用"),"") | H61: =IF(ISNUMBER(H40),IF(AND(ISNUMBER(H27)),H40-(H27),"不適用"),"")
A62: 差距｜EBITDA 率｜實際 vs 共識 | B62: pt | C62: =IF(ISNUMBER(C40),IF(AND(ISNUMBER(C36)),C40-(C36),"不適用"),"") | D62: =IF(ISNUMBER(D40),IF(AND(ISNUMBER(D36)),D40-(D36),"不適用"),"") | E62: =IF(ISNUMBER(E40),IF(AND(ISNUMBER(E36)),E40-(E36),"不適用"),"") | F62: =IF(ISNUMBER(F40),IF(AND(ISNUMBER(F36)),F40-(F36),"不適用"),"") | G62: =IF(ISNUMBER(G40),IF(AND(ISNUMBER(G36)),G40-(G36),"不適用"),"") | H62: =IF(ISNUMBER(H40),IF(AND(ISNUMBER(H36)),H40-(H36),"不適用"),"")
A63: 差距｜EBITDA 率｜實際 vs 指引中點 | B63: pt | C63: =IF(ISNUMBER(C40),"不適用","") | D63: =IF(ISNUMBER(D40),"不適用","") | E63: =IF(ISNUMBER(E40),"不適用","") | F63: =IF(ISNUMBER(F40),"不適用","") | G63: =IF(ISNUMBER(G40),"不適用","") | H63: =IF(ISNUMBER(H40),"不適用","")
A64: 差距｜調整後營業利益｜模型 vs 共識 | B64: US$bn | C64: 不適用 | D64: 不適用 | E64: 不適用 | F64: 不適用 | G64: 不適用 | H64: 不適用
A65: 差距｜調整後營業利益｜模型 vs 指引中點 | B65: US$bn | C65: 不適用 | D65: 不適用 | E65: 不適用 | F65: 不適用 | G65: 不適用 | H65: 不適用
A66: 差距｜調整後營業利益｜實際 vs 模型 | B66: US$bn | C66: =IF(ISNUMBER(C41),IF(AND(ISNUMBER(C30)),C41-(C30),"不適用"),"") | D66: =IF(ISNUMBER(D41),IF(AND(ISNUMBER(D30)),D41-(D30),"不適用"),"") | E66: =IF(ISNUMBER(E41),IF(AND(ISNUMBER(E30)),E41-(E30),"不適用"),"") | F66: =IF(ISNUMBER(F41),IF(AND(ISNUMBER(F30)),F41-(F30),"不適用"),"") | G66: =IF(ISNUMBER(G41),IF(AND(ISNUMBER(G30)),G41-(G30),"不適用"),"") | H66: =IF(ISNUMBER(H41),IF(AND(ISNUMBER(H30)),H41-(H30),"不適用"),"")
A67: 差距｜調整後營業利益｜實際 vs 共識 | B67: US$bn | C67: =IF(ISNUMBER(C41),"不適用","") | D67: =IF(ISNUMBER(D41),"不適用","") | E67: =IF(ISNUMBER(E41),"不適用","") | F67: =IF(ISNUMBER(F41),"不適用","") | G67: =IF(ISNUMBER(G41),"不適用","") | H67: =IF(ISNUMBER(H41),"不適用","")
A68: 差距｜調整後營業利益｜實際 vs 指引中點 | B68: US$bn | C68: =IF(ISNUMBER(C41),"不適用","") | D68: =IF(ISNUMBER(D41),"不適用","") | E68: =IF(ISNUMBER(E41),"不適用","") | F68: =IF(ISNUMBER(F41),"不適用","") | G68: =IF(ISNUMBER(G41),"不適用","") | H68: =IF(ISNUMBER(H41),"不適用","")
A69: 差距｜調整後營業利益｜模型 vs 共識（利潤率 pt） | B69: pt | C69: 不適用 | D69: 不適用 | E69: 不適用 | F69: 不適用 | G69: 不適用 | H69: 不適用
A70: 差距｜調整後營業利益｜模型 vs 指引中點（利潤率 pt） | B70: pt | C70: 不適用 | D70: 不適用 | E70: 不適用 | F70: 不適用 | G70: 不適用 | H70: 不適用
A71: 差距｜調整後營業利益｜實際 vs 模型（利潤率 pt） | B71: pt | C71: =IF(ISNUMBER(C41),IF(AND(ISNUMBER(C41),ISNUMBER(C38),C38<>0,ISNUMBER(C30),ISNUMBER(C22),C22<>0),C41/C38-C30/C22,"不適用"),"") | D71: =IF(ISNUMBER(D41),IF(AND(ISNUMBER(D41),ISNUMBER(D38),D38<>0,ISNUMBER(D30),ISNUMBER(D22),D22<>0),D41/D38-D30/D22,"不適用"),"") | E71: =IF(ISNUMBER(E41),IF(AND(ISNUMBER(E41),ISNUMBER(E38),E38<>0,ISNUMBER(E30),ISNUMBER(E22),E22<>0),E41/E38-E30/E22,"不適用"),"") | F71: =IF(ISNUMBER(F41),IF(AND(ISNUMBER(F41),ISNUMBER(F38),F38<>0,ISNUMBER(F30),ISNUMBER(F22),F22<>0),F41/F38-F30/F22,"不適用"),"") | G71: =IF(ISNUMBER(G41),IF(AND(ISNUMBER(G41),ISNUMBER(G38),G38<>0,ISNUMBER(G30),ISNUMBER(G22),G22<>0),G41/G38-G30/G22,"不適用"),"") | H71: =IF(ISNUMBER(H41),IF(AND(ISNUMBER(H41),ISNUMBER(H38),H38<>0,ISNUMBER(H30),ISNUMBER(H22),H22<>0),H41/H38-H30/H22,"不適用"),"")
A72: 差距｜調整後營業利益｜實際 vs 共識（利潤率 pt） | B72: pt | C72: =IF(ISNUMBER(C41),"不適用","") | D72: =IF(ISNUMBER(D41),"不適用","") | E72: =IF(ISNUMBER(E41),"不適用","") | F72: =IF(ISNUMBER(F41),"不適用","") | G72: =IF(ISNUMBER(G41),"不適用","") | H72: =IF(ISNUMBER(H41),"不適用","")
A73: 差距｜調整後營業利益｜實際 vs 指引中點（利潤率 pt） | B73: pt | C73: =IF(ISNUMBER(C41),"不適用","") | D73: =IF(ISNUMBER(D41),"不適用","") | E73: =IF(ISNUMBER(E41),"不適用","") | F73: =IF(ISNUMBER(F41),"不適用","") | G73: =IF(ISNUMBER(G41),"不適用","") | H73: =IF(ISNUMBER(H41),"不適用","")
A74: 差距｜CapEx（毛額）｜模型 vs 共識 | B74: % | C74: 不適用 | D74: 不適用 | E74: 不適用 | F74: 不適用 | G74: 不適用 | H74: 不適用
A75: 差距｜CapEx（毛額）｜模型 vs 指引中點 | B75: % | C75: 不適用 | D75: 不適用 | E75: 不適用 | F75: 不適用 | G75: 不適用 | H75: 不適用
A76: 差距｜CapEx（毛額）｜實際 vs 模型 | B76: % | C76: =IF(ISNUMBER(C42),IF(AND(ISNUMBER(C33),C33<>0),C42/(C33)-1,"不適用"),"") | D76: =IF(ISNUMBER(D42),IF(AND(ISNUMBER(D33),D33<>0),D42/(D33)-1,"不適用"),"") | E76: =IF(ISNUMBER(E42),IF(AND(ISNUMBER(E33),E33<>0),E42/(E33)-1,"不適用"),"") | F76: =IF(ISNUMBER(F42),IF(AND(ISNUMBER(F33),F33<>0),F42/(F33)-1,"不適用"),"") | G76: =IF(ISNUMBER(G42),IF(AND(ISNUMBER(G33),G33<>0),G42/(G33)-1,"不適用"),"") | H76: =IF(ISNUMBER(H42),IF(AND(ISNUMBER(H33),H33<>0),H42/(H33)-1,"不適用"),"")
A77: 差距｜CapEx（毛額）｜實際 vs 共識 | B77: % | C77: =IF(ISNUMBER(C42),"不適用","") | D77: =IF(ISNUMBER(D42),"不適用","") | E77: =IF(ISNUMBER(E42),"不適用","") | F77: =IF(ISNUMBER(F42),"不適用","") | G77: =IF(ISNUMBER(G42),"不適用","") | H77: =IF(ISNUMBER(H42),"不適用","")
A78: 差距｜CapEx（毛額）｜實際 vs 指引中點 | B78: % | C78: =IF(ISNUMBER(C42),"不適用","") | D78: =IF(ISNUMBER(D42),"不適用","") | E78: =IF(ISNUMBER(E42),"不適用","") | F78: =IF(ISNUMBER(F42),"不適用","") | G78: =IF(ISNUMBER(G42),"不適用","") | H78: =IF(ISNUMBER(H42),"不適用","")
A79: 差距｜季末已連網 MW-IT｜模型 vs 共識 | B79: MW | C79: 不適用 | D79: 不適用 | E79: 不適用 | F79: 不適用 | G79: 不適用 | H79: 不適用
A80: 差距｜季末已連網 MW-IT｜模型 vs 指引中點 | B80: MW | C80: 不適用 | D80: 不適用 | E80: 不適用 | F80: 不適用 | G80: 不適用 | H80: 不適用
A81: 差距｜季末已連網 MW-IT｜實際 vs 模型 | B81: MW | C81: =IF(ISNUMBER(C43),IF(AND(ISNUMBER(C19)),C43-(C19),"不適用"),"") | D81: =IF(ISNUMBER(D43),IF(AND(ISNUMBER(D19)),D43-(D19),"不適用"),"") | E81: =IF(ISNUMBER(E43),IF(AND(ISNUMBER(E19)),E43-(E19),"不適用"),"") | F81: =IF(ISNUMBER(F43),IF(AND(ISNUMBER(F19)),F43-(F19),"不適用"),"") | G81: =IF(ISNUMBER(G43),IF(AND(ISNUMBER(G19)),G43-(G19),"不適用"),"") | H81: =IF(ISNUMBER(H43),IF(AND(ISNUMBER(H19)),H43-(H19),"不適用"),"")
A82: 差距｜季末已連網 MW-IT｜實際 vs 共識 | B82: MW | C82: =IF(ISNUMBER(C43),"不適用","") | D82: =IF(ISNUMBER(D43),"不適用","") | E82: =IF(ISNUMBER(E43),"不適用","") | F82: =IF(ISNUMBER(F43),"不適用","") | G82: =IF(ISNUMBER(G43),"不適用","") | H82: =IF(ISNUMBER(H43),"不適用","")
A83: 差距｜季末已連網 MW-IT｜實際 vs 指引中點 | B83: MW | C83: =IF(ISNUMBER(C43),"不適用","") | D83: =IF(ISNUMBER(D43),"不適用","") | E83: =IF(ISNUMBER(E43),"不適用","") | F83: =IF(ISNUMBER(F43),"不適用","") | G83: =IF(ISNUMBER(G43),"不適用","") | H83: =IF(ISNUMBER(H43),"不適用","")
A84: 合計基準｜營收｜vs 共識 | B84: US$bn | C84: =IF(COUNT(C34,D34,E34)=3,C34+D34+E34,"不適用") -> 不適用 | D84: =IF(COUNT(C34,D34,E34)=3,C34+D34+E34,"不適用") -> 不適用 | E84: =IF(COUNT(C34,D34,E34)=3,C34+D34+E34,"不適用") -> 不適用 | F84: =IF(COUNT(F34,G34,H34)=3,F34+G34+H34,"不適用") -> 不適用 | G84: =IF(COUNT(F34,G34,H34)=3,F34+G34+H34,"不適用") -> 不適用 | H84: =IF(COUNT(F34,G34,H34)=3,F34+G34+H34,"不適用") -> 不適用 | J84: 所屬期間的季度共識合計
A85: 拆解｜營收｜vs 共識｜水準 | B85: US$bn | C85: =IF(AND(ISNUMBER(C84),C84<>0,ISNUMBER(C34),ISNUMBER(C22)),(損益!C9-C84)*(C34)/C84,"不適用") -> 不適用 | D85: =IF(AND(ISNUMBER(D84),D84<>0,ISNUMBER(D34),ISNUMBER(D22)),(損益!C9-D84)*(D34)/D84,"不適用") -> 不適用 | E85: =IF(AND(ISNUMBER(E84),E84<>0,ISNUMBER(E34),ISNUMBER(E22)),(損益!C9-E84)*(E34)/E84,"不適用") -> 不適用 | F85: =IF(AND(ISNUMBER(F84),F84<>0,ISNUMBER(F34),ISNUMBER(F22)),(損益!D9-F84)*(F34)/F84,"不適用") -> 不適用 | G85: =IF(AND(ISNUMBER(G84),G84<>0,ISNUMBER(G34),ISNUMBER(G22)),(損益!D9-G84)*(G34)/G84,"不適用") -> 不適用 | H85: =IF(AND(ISNUMBER(H84),H84<>0,ISNUMBER(H34),ISNUMBER(H22)),(損益!D9-H84)*(H34)/H84,"不適用") -> 不適用 | J85: (模型期間 − 比較期間) × 比較的季占比
A86: 拆解｜營收｜vs 共識｜分配 | B86: US$bn | C86: =IF(AND(ISNUMBER(C84),C84<>0,ISNUMBER(C34),ISNUMBER(C22)),(C22/損益!C9-(C34)/C84)*損益!C9,"不適用") -> 不適用 | D86: =IF(AND(ISNUMBER(D84),D84<>0,ISNUMBER(D34),ISNUMBER(D22)),(D22/損益!C9-(D34)/D84)*損益!C9,"不適用") -> 不適用 | E86: =IF(AND(ISNUMBER(E84),E84<>0,ISNUMBER(E34),ISNUMBER(E22)),(E22/損益!C9-(E34)/E84)*損益!C9,"不適用") -> 不適用 | F86: =IF(AND(ISNUMBER(F84),F84<>0,ISNUMBER(F34),ISNUMBER(F22)),(F22/損益!D9-(F34)/F84)*損益!D9,"不適用") -> 不適用 | G86: =IF(AND(ISNUMBER(G84),G84<>0,ISNUMBER(G34),ISNUMBER(G22)),(G22/損益!D9-(G34)/G84)*損益!D9,"不適用") -> 不適用 | H86: =IF(AND(ISNUMBER(H84),H84<>0,ISNUMBER(H34),ISNUMBER(H22)),(H22/損益!D9-(H34)/H84)*損益!D9,"不適用") -> 不適用 | J86: (模型季占比 − 比較季占比) × 模型期間；水準＋分配＝季度差距
A87: 合計基準｜營收｜vs 指引 | B87: US$bn | C87: =(輸入與假設!$C$352+輸入與假設!$D$352)/2-輸入與假設!$E$352 -> 70.655 | D87: =(輸入與假設!$C$352+輸入與假設!$D$352)/2-輸入與假設!$E$352 -> 70.655 | E87: =(輸入與假設!$C$352+輸入與假設!$D$352)/2-輸入與假設!$E$352 -> 70.655 | F87: 不適用 | G87: 不適用 | H87: 不適用 | J87: 所屬期間的隱含指引中點（全年指引中點 − 1Q 實際）
A88: 拆解｜營收｜vs 指引｜水準 | B88: US$bn | C88: =IF(AND(ISNUMBER(C87),C87<>0,ISNUMBER(((C31+C32)/2)),ISNUMBER(C22)),(損益!C9-C87)*(((C31+C32)/2))/C87,"不適用") -> -0.75071406 | D88: =IF(AND(ISNUMBER(D87),D87<>0,ISNUMBER(((D31+D32)/2)),ISNUMBER(D22)),(損益!C9-D87)*(((D31+D32)/2))/D87,"不適用") -> 不適用 | E88: =IF(AND(ISNUMBER(E87),E87<>0,ISNUMBER(((E31+E32)/2)),ISNUMBER(E22)),(損益!C9-E87)*(((E31+E32)/2))/E87,"不適用") -> 不適用 | F88: =IF(AND(ISNUMBER(F87),F87<>0,ISNUMBER(((F31+F32)/2)),ISNUMBER(F22)),(損益!D9-F87)*(((F31+F32)/2))/F87,"不適用") -> 不適用 | G88: =IF(AND(ISNUMBER(G87),G87<>0,ISNUMBER(((G31+G32)/2)),ISNUMBER(G22)),(損益!D9-G87)*(((G31+G32)/2))/G87,"不適用") -> 不適用 | H88: =IF(AND(ISNUMBER(H87),H87<>0,ISNUMBER(((H31+H32)/2)),ISNUMBER(H22)),(損益!D9-H87)*(((H31+H32)/2))/H87,"不適用") -> 不適用 | J88: (模型期間 − 比較期間) × 比較的季占比
A89: 拆解｜營收｜vs 指引｜分配 | B89: US$bn | C89: =IF(AND(ISNUMBER(C87),C87<>0,ISNUMBER(((C31+C32)/2)),ISNUMBER(C22)),(C22/損益!C9-(((C31+C32)/2))/C87)*損益!C9,"不適用") -> 0.58548403 | D89: =IF(AND(ISNUMBER(D87),D87<>0,ISNUMBER(((D31+D32)/2)),ISNUMBER(D22)),(D22/損益!C9-(((D31+D32)/2))/D87)*損益!C9,"不適用") -> 不適用 | E89: =IF(AND(ISNUMBER(E87),E87<>0,ISNUMBER(((E31+E32)/2)),ISNUMBER(E22)),(E22/損益!C9-(((E31+E32)/2))/E87)*損益!C9,"不適用") -> 不適用 | F89: =IF(AND(ISNUMBER(F87),F87<>0,ISNUMBER(((F31+F32)/2)),ISNUMBER(F22)),(F22/損益!D9-(((F31+F32)/2))/F87)*損益!D9,"不適用") -> 不適用 | G89: =IF(AND(ISNUMBER(G87),G87<>0,ISNUMBER(((G31+G32)/2)),ISNUMBER(G22)),(G22/損益!D9-(((G31+G32)/2))/G87)*損益!D9,"不適用") -> 不適用 | H89: =IF(AND(ISNUMBER(H87),H87<>0,ISNUMBER(((H31+H32)/2)),ISNUMBER(H22)),(H22/損益!D9-(((H31+H32)/2))/H87)*損益!D9,"不適用") -> 不適用 | J89: (模型季占比 − 比較季占比) × 模型期間；水準＋分配＝季度差距
A90: 原因｜營收｜vs 共識 | C90: =IF(ISNUMBER(C44),IF(ABS(C44)>輸入與假設!$C$333,IF(ISNUMBER(C85),IF(ABS(C86)>ABS(C85),"營收 vs 共識 "&IF(C44<0,"−","+")&TEXT(ABS(C44)*100,"#,##0.0")&"%"&"：拆法（分配 "&IF(C86<0,"−","+")&IF(ABS(C86)<0,"−","")&"$"&TEXT(ABS(ABS(C86)),"#,##0.000")&"bn"&"（Q2 FY27 占 2Q–4Q27 "&TEXT((C22/損益!C9)*100,"#,##0.0")&"%"&"，共識合計 "&TEXT(((C34)/C84)*100,"#,##0.0")&"%"&"）；水準 "&IF(C85<0,"−","+")&IF(ABS(C85)<0,"−","")&"$"&TEXT(ABS(ABS(C85)),"#,##0.000")&"bn"&"）","營收 vs 共識 "&IF(C44<0,"−","+")&TEXT(ABS(C44)*100,"#,##0.0")&"%"&"：觀點（水準 "&IF(C85<0,"−","+")&IF(ABS(C85)<0,"−","")&"$"&TEXT(ABS(ABS(C85)),"#,##0.000")&"bn"&"（2Q–4Q27 模型 "&IF(損益!C9<0,"−","")&"$"&TEXT(ABS(損益!C9),"#,##0.000")&"bn"&"，共識合計 "&IF(C84<0,"−","")&"$"&TEXT(ABS(C84),"#,##0.000")&"bn"&"）；分配 "&IF(C86<0,"−","+")&IF(ABS(C86)<0,"−","")&"$"&TEXT(ABS(ABS(C86)),"#,##0.000")&"bn"&"；"&"OCI 營收＝在役 MW × 每 MW 年收入（Tokenomics 正向推導），期初可計費 MW 以 Q1 實際 OCI 年化校準；傳統事業四線依近四季年增率；共識未揭露 MW 與單價假設"&"）"),"營收 vs 共識 "&IF(C44<0,"−","+")&TEXT(ABS(C44)*100,"#,##0.0")&"%"&"：觀點（"&"OCI 營收＝在役 MW × 每 MW 年收入（Tokenomics 正向推導），期初可計費 MW 以 Q1 實際 OCI 年化校準；傳統事業四線依近四季年增率；共識未揭露 MW 與單價假設"&"）"),""),"") | D90: =IF(ISNUMBER(D44),IF(ABS(D44)>輸入與假設!$C$333,IF(ISNUMBER(D85),IF(ABS(D86)>ABS(D85),"營收 vs 共識 "&IF(D44<0,"−","+")&TEXT(ABS(D44)*100,"#,##0.0")&"%"&"：拆法（分配 "&IF(D86<0,"−","+")&IF(ABS(D86)<0,"−","")&"$"&TEXT(ABS(ABS(D86)),"#,##0.000")&"bn"&"（Q3 FY27 占 2Q–4Q27 "&TEXT((D22/損益!C9)*100,"#,##0.0")&"%"&"，共識合計 "&TEXT(((D34)/D84)*100,"#,##0.0")&"%"&"）；水準 "&IF(D85<0,"−","+")&IF(ABS(D85)<0,"−","")&"$"&TEXT(ABS(ABS(D85)),"#,##0.000")&"bn"&"）","營收 vs 共識 "&IF(D44<0,"−","+")&TEXT(ABS(D44)*100,"#,##0.0")&"%"&"：觀點（水準 "&IF(D85<0,"−","+")&IF(ABS(D85)<0,"−","")&"$"&TEXT(ABS(ABS(D85)),"#,##0.000")&"bn"&"（2Q–4Q27 模型 "&IF(損益!C9<0,"−","")&"$"&TEXT(ABS(損益!C9),"#,##0.000")&"bn"&"，共識合計 "&IF(D84<0,"−","")&"$"&TEXT(ABS(D84),"#,##0.000")&"bn"&"）；分配 "&IF(D86<0,"−","+")&IF(ABS(D86)<0,"−","")&"$"&TEXT(ABS(ABS(D86)),"#,##0.000")&"bn"&"；"&"OCI 營收＝在役 MW × 每 MW 年收入（Tokenomics 正向推導），期初可計費 MW 以 Q1 實際 OCI 年化校準；傳統事業四線依近四季年增率；共識未揭露 MW 與單價假設"&"）"),"營收 vs 共識 "&IF(D44<0,"−","+")&TEXT(ABS(D44)*100,"#,##0.0")&"%"&"：觀點（"&"OCI 營收＝在役 MW × 每 MW 年收入（Tokenomics 正向推導），期初可計費 MW 以 Q1 實際 OCI 年化校準；傳統事業四線依近四季年增率；共識未揭露 MW 與單價假設"&"）"),""),"") | E90: =IF(ISNUMBER(E44),IF(ABS(E44)>輸入與假設!$C$333,IF(ISNUMBER(E85),IF(ABS(E86)>ABS(E85),"營收 vs 共識 "&IF(E44<0,"−","+")&TEXT(ABS(E44)*100,"#,##0.0")&"%"&"：拆法（分配 "&IF(E86<0,"−","+")&IF(ABS(E86)<0,"−","")&"$"&TEXT(ABS(ABS(E86)),"#,##0.000")&"bn"&"（Q4 FY27 占 2Q–4Q27 "&TEXT((E22/損益!C9)*100,"#,##0.0")&"%"&"，共識合計 "&TEXT(((E34)/E84)*100,"#,##0.0")&"%"&"）；水準 "&IF(E85<0,"−","+")&IF(ABS(E85)<0,"−","")&"$"&TEXT(ABS(ABS(E85)),"#,##0.000")&"bn"&"）","營收 vs 共識 "&IF(E44<0,"−","+")&TEXT(ABS(E44)*100,"#,##0.0")&"%"&"：觀點（水準 "&IF(E85<0,"−","+")&IF(ABS(E85)<0,"−","")&"$"&TEXT(ABS(ABS(E85)),"#,##0.000")&"bn"&"（2Q–4Q27 模型 "&IF(損益!C9<0,"−","")&"$"&TEXT(ABS(損益!C9),"#,##0.000")&"bn"&"，共識合計 "&IF(E84<0,"−","")&"$"&TEXT(ABS(E84),"#,##0.000")&"bn"&"）；分配 "&IF(E86<0,"−","+")&IF(ABS(E86)<0,"−","")&"$"&TEXT(ABS(ABS(E86)),"#,##0.000")&"bn"&"；"&"OCI 營收＝在役 MW × 每 MW 年收入（Tokenomics 正向推導），期初可計費 MW 以 Q1 實際 OCI 年化校準；傳統事業四線依近四季年增率；共識未揭露 MW 與單價假設"&"）"),"營收 vs 共識 "&IF(E44<0,"−","+")&TEXT(ABS(E44)*100,"#,##0.0")&"%"&"：觀點（"&"OCI 營收＝在役 MW × 每 MW 年收入（Tokenomics 正向推導），期初可計費 MW 以 Q1 實際 OCI 年化校準；傳統事業四線依近四季年增率；共識未揭露 MW 與單價假設"&"）"),""),"") | F90: =IF(ISNUMBER(F44),IF(ABS(F44)>輸入與假設!$C$333,IF(ISNUMBER(F85),IF(ABS(F86)>ABS(F85),"營收 vs 共識 "&IF(F44<0,"−","+")&TEXT(ABS(F44)*100,"#,##0.0")&"%"&"：拆法（分配 "&IF(F86<0,"−","+")&IF(ABS(F86)<0,"−","")&"$"&TEXT(ABS(ABS(F86)),"#,##0.000")&"bn"&"（Q1 FY28 占 FY28 "&TEXT((F22/損益!D9)*100,"#,##0.0")&"%"&"，共識合計 "&TEXT(((F34)/F84)*100,"#,##0.0")&"%"&"）；水準 "&IF(F85<0,"−","+")&IF(ABS(F85)<0,"−","")&"$"&TEXT(ABS(ABS(F85)),"#,##0.000")&"bn"&"）","營收 vs 共識 "&IF(F44<0,"−","+")&TEXT(ABS(F44)*100,"#,##0.0")&"%"&"：觀點（水準 "&IF(F85<0,"−","+")&IF(ABS(F85)<0,"−","")&"$"&TEXT(ABS(ABS(F85)),"#,##0.000")&"bn"&"（FY28 模型 "&IF(損益!D9<0,"−","")&"$"&TEXT(ABS(損益!D9),"#,##0.000")&"bn"&"，共識合計 "&IF(F84<0,"−","")&"$"&TEXT(ABS(F84),"#,##0.000")&"bn"&"）；分配 "&IF(F86<0,"−","+")&IF(ABS(F86)<0,"−","")&"$"&TEXT(ABS(ABS(F86)),"#,##0.000")&"bn"&"；"&"OCI 營收＝在役 MW × 每 MW 年收入（Tokenomics 正向推導），期初可計費 MW 以 Q1 實際 OCI 年化校準；傳統事業四線依近四季年增率；共識未揭露 MW 與單價假設"&"）"),"營收 vs 共識 "&IF(F44<0,"−","+")&TEXT(ABS(F44)*100,"#,##0.0")&"%"&"：觀點（"&"OCI 營收＝在役 MW × 每 MW 年收入（Tokenomics 正向推導），期初可計費 MW 以 Q1 實際 OCI 年化校準；傳統事業四線依近四季年增率；共識未揭露 MW 與單價假設"&"）"),""),"") | G90: =IF(ISNUMBER(G44),IF(ABS(G44)>輸入與假設!$C$333,IF(ISNUMBER(G85),IF(ABS(G86)>ABS(G85),"營收 vs 共識 "&IF(G44<0,"−","+")&TEXT(ABS(G44)*100,"#,##0.0")&"%"&"：拆法（分配 "&IF(G86<0,"−","+")&IF(ABS(G86)<0,"−","")&"$"&TEXT(ABS(ABS(G86)),"#,##0.000")&"bn"&"（Q2 FY28 占 FY28 "&TEXT((G22/損益!D9)*100,"#,##0.0")&"%"&"，共識合計 "&TEXT(((G34)/G84)*100,"#,##0.0")&"%"&"）；水準 "&IF(G85<0,"−","+")&IF(ABS(G85)<0,"−","")&"$"&TEXT(ABS(ABS(G85)),"#,##0.000")&"bn"&"）","營收 vs 共識 "&IF(G44<0,"−","+")&TEXT(ABS(G44)*100,"#,##0.0")&"%"&"：觀點（水準 "&IF(G85<0,"−","+")&IF(ABS(G85)<0,"−","")&"$"&TEXT(ABS(ABS(G85)),"#,##0.000")&"bn"&"（FY28 模型 "&IF(損益!D9<0,"−","")&"$"&TEXT(ABS(損益!D9),"#,##0.000")&"bn"&"，共識合計 "&IF(G84<0,"−","")&"$"&TEXT(ABS(G84),"#,##0.000")&"bn"&"）；分配 "&IF(G86<0,"−","+")&IF(ABS(G86)<0,"−","")&"$"&TEXT(ABS(ABS(G86)),"#,##0.000")&"bn"&"；"&"OCI 營收＝在役 MW × 每 MW 年收入（Tokenomics 正向推導），期初可計費 MW 以 Q1 實際 OCI 年化校準；傳統事業四線依近四季年增率；共識未揭露 MW 與單價假設"&"）"),"營收 vs 共識 "&IF(G44<0,"−","+")&TEXT(ABS(G44)*100,"#,##0.0")&"%"&"：觀點（"&"OCI 營收＝在役 MW × 每 MW 年收入（Tokenomics 正向推導），期初可計費 MW 以 Q1 實際 OCI 年化校準；傳統事業四線依近四季年增率；共識未揭露 MW 與單價假設"&"）"),""),"") | H90: =IF(ISNUMBER(H44),IF(ABS(H44)>輸入與假設!$C$333,IF(ISNUMBER(H85),IF(ABS(H86)>ABS(H85),"營收 vs 共識 "&IF(H44<0,"−","+")&TEXT(ABS(H44)*100,"#,##0.0")&"%"&"：拆法（分配 "&IF(H86<0,"−","+")&IF(ABS(H86)<0,"−","")&"$"&TEXT(ABS(ABS(H86)),"#,##0.000")&"bn"&"（Q3 FY28 占 FY28 "&TEXT((H22/損益!D9)*100,"#,##0.0")&"%"&"，共識合計 "&TEXT(((H34)/H84)*100,"#,##0.0")&"%"&"）；水準 "&IF(H85<0,"−","+")&IF(ABS(H85)<0,"−","")&"$"&TEXT(ABS(ABS(H85)),"#,##0.000")&"bn"&"）","營收 vs 共識 "&IF(H44<0,"−","+")&TEXT(ABS(H44)*100,"#,##0.0")&"%"&"：觀點（水準 "&IF(H85<0,"−","+")&IF(ABS(H85)<0,"−","")&"$"&TEXT(ABS(ABS(H85)),"#,##0.000")&"bn"&"（FY28 模型 "&IF(損益!D9<0,"−","")&"$"&TEXT(ABS(損益!D9),"#,##0.000")&"bn"&"，共識合計 "&IF(H84<0,"−","")&"$"&TEXT(ABS(H84),"#,##0.000")&"bn"&"）；分配 "&IF(H86<0,"−","+")&IF(ABS(H86)<0,"−","")&"$"&TEXT(ABS(ABS(H86)),"#,##0.000")&"bn"&"；"&"OCI 營收＝在役 MW × 每 MW 年收入（Tokenomics 正向推導），期初可計費 MW 以 Q1 實際 OCI 年化校準；傳統事業四線依近四季年增率；共識未揭露 MW 與單價假設"&"）"),"營收 vs 共識 "&IF(H44<0,"−","+")&TEXT(ABS(H44)*100,"#,##0.0")&"%"&"：觀點（"&"OCI 營收＝在役 MW × 每 MW 年收入（Tokenomics 正向推導），期初可計費 MW 以 Q1 實際 OCI 年化校準；傳統事業四線依近四季年增率；共識未揭露 MW 與單價假設"&"）"),""),"")
A91: 原因類型｜營收｜vs 共識 | C91: =IF(ISNUMBER(C44),IF(ABS(C44)>輸入與假設!$C$333,IF(ISNUMBER(C85),IF(ABS(C86)>ABS(C85),"拆法","觀點"),"觀點"),""),"") | D91: =IF(ISNUMBER(D44),IF(ABS(D44)>輸入與假設!$C$333,IF(ISNUMBER(D85),IF(ABS(D86)>ABS(D85),"拆法","觀點"),"觀點"),""),"") | E91: =IF(ISNUMBER(E44),IF(ABS(E44)>輸入與假設!$C$333,IF(ISNUMBER(E85),IF(ABS(E86)>ABS(E85),"拆法","觀點"),"觀點"),""),"") | F91: =IF(ISNUMBER(F44),IF(ABS(F44)>輸入與假設!$C$333,IF(ISNUMBER(F85),IF(ABS(F86)>ABS(F85),"拆法","觀點"),"觀點"),""),"") | G91: =IF(ISNUMBER(G44),IF(ABS(G44)>輸入與假設!$C$333,IF(ISNUMBER(G85),IF(ABS(G86)>ABS(G85),"拆法","觀點"),"觀點"),""),"") | H91: =IF(ISNUMBER(H44),IF(ABS(H44)>輸入與假設!$C$333,IF(ISNUMBER(H85),IF(ABS(H86)>ABS(H85),"拆法","觀點"),"觀點"),""),"")
A92: 原因｜營收｜vs 指引中點 | C92: =IF(ISNUMBER(C45),IF(OR(ABS(C45)>輸入與假設!$C$333,C22>C32,C22<C31),IF(ISNUMBER(C88),IF(ABS(C89)>ABS(C88),"營收 vs 指引中點 "&IF(C45<0,"−","+")&TEXT(ABS(C45)*100,"#,##0.0")&"%"&"：拆法（分配 "&IF(C89<0,"−","+")&IF(ABS(C89)<0,"−","")&"$"&TEXT(ABS(ABS(C89)),"#,##0.000")&"bn"&"（Q2 FY27 占 2Q–4Q27 "&TEXT((C22/損益!C9)*100,"#,##0.0")&"%"&"，指引隱含 "&TEXT(((((C31+C32)/2))/C87)*100,"#,##0.0")&"%"&"）；水準 "&IF(C88<0,"−","+")&IF(ABS(C88)<0,"−","")&"$"&TEXT(ABS(ABS(C88)),"#,##0.000")&"bn"&"）","營收 vs 指引中點 "&IF(C45<0,"−","+")&TEXT(ABS(C45)*100,"#,##0.0")&"%"&"：觀點（水準 "&IF(C88<0,"−","+")&IF(ABS(C88)<0,"−","")&"$"&TEXT(ABS(ABS(C88)),"#,##0.000")&"bn"&"（2Q–4Q27 模型 "&IF(損益!C9<0,"−","")&"$"&TEXT(ABS(損益!C9),"#,##0.000")&"bn"&"，指引隱含 "&IF(C87<0,"−","")&"$"&TEXT(ABS(C87),"#,##0.000")&"bn"&"）；分配 "&IF(C89<0,"−","+")&IF(ABS(C89)<0,"−","")&"$"&TEXT(ABS(ABS(C89)),"#,##0.000")&"bn"&"；"&"OCI 營收＝在役 MW × 每 MW 年收入（Tokenomics 正向推導），期初可計費 MW 以 Q1 實際 OCI 年化校準；傳統事業四線依近四季年增率；共識未揭露 MW 與單價假設"&"）"),"營收 vs 指引中點 "&IF(C45<0,"−","+")&TEXT(ABS(C45)*100,"#,##0.0")&"%"&"：觀點（"&"OCI 營收＝在役 MW × 每 MW 年收入（Tokenomics 正向推導），期初可計費 MW 以 Q1 實際 OCI 年化校準；傳統事業四線依近四季年增率；共識未揭露 MW 與單價假設"&"）"),""),"") | D92: =IF(ISNUMBER(D45),IF(OR(ABS(D45)>輸入與假設!$C$333,D22>D32,D22<D31),IF(ISNUMBER(D88),IF(ABS(D89)>ABS(D88),"營收 vs 指引中點 "&IF(D45<0,"−","+")&TEXT(ABS(D45)*100,"#,##0.0")&"%"&"：拆法（分配 "&IF(D89<0,"−","+")&IF(ABS(D89)<0,"−","")&"$"&TEXT(ABS(ABS(D89)),"#,##0.000")&"bn"&"（Q3 FY27 占 2Q–4Q27 "&TEXT((D22/損益!C9)*100,"#,##0.0")&"%"&"，指引隱含 "&TEXT(((((D31+D32)/2))/D87)*100,"#,##0.0")&"%"&"）；水準 "&IF(D88<0,"−","+")&IF(ABS(D88)<0,"−","")&"$"&TEXT(ABS(ABS(D88)),"#,##0.000")&"bn"&"）","營收 vs 指引中點 "&IF(D45<0,"−","+")&TEXT(ABS(D45)*100,"#,##0.0")&"%"&"：觀點（水準 "&IF(D88<0,"−","+")&IF(ABS(D88)<0,"−","")&"$"&TEXT(ABS(ABS(D88)),"#,##0.000")&"bn"&"（2Q–4Q27 模型 "&IF(損益!C9<0,"−","")&"$"&TEXT(ABS(損益!C9),"#,##0.000")&"bn"&"，指引隱含 "&IF(D87<0,"−","")&"$"&TEXT(ABS(D87),"#,##0.000")&"bn"&"）；分配 "&IF(D89<0,"−","+")&IF(ABS(D89)<0,"−","")&"$"&TEXT(ABS(ABS(D89)),"#,##0.000")&"bn"&"；"&"OCI 營收＝在役 MW × 每 MW 年收入（Tokenomics 正向推導），期初可計費 MW 以 Q1 實際 OCI 年化校準；傳統事業四線依近四季年增率；共識未揭露 MW 與單價假設"&"）"),"營收 vs 指引中點 "&IF(D45<0,"−","+")&TEXT(ABS(D45)*100,"#,##0.0")&"%"&"：觀點（"&"OCI 營收＝在役 MW × 每 MW 年收入（Tokenomics 正向推導），期初可計費 MW 以 Q1 實際 OCI 年化校準；傳統事業四線依近四季年增率；共識未揭露 MW 與單價假設"&"）"),""),"") | E92: =IF(ISNUMBER(E45),IF(OR(ABS(E45)>輸入與假設!$C$333,E22>E32,E22<E31),IF(ISNUMBER(E88),IF(ABS(E89)>ABS(E88),"營收 vs 指引中點 "&IF(E45<0,"−","+")&TEXT(ABS(E45)*100,"#,##0.0")&"%"&"：拆法（分配 "&IF(E89<0,"−","+")&IF(ABS(E89)<0,"−","")&"$"&TEXT(ABS(ABS(E89)),"#,##0.000")&"bn"&"（Q4 FY27 占 2Q–4Q27 "&TEXT((E22/損益!C9)*100,"#,##0.0")&"%"&"，指引隱含 "&TEXT(((((E31+E32)/2))/E87)*100,"#,##0.0")&"%"&"）；水準 "&IF(E88<0,"−","+")&IF(ABS(E88)<0,"−","")&"$"&TEXT(ABS(ABS(E88)),"#,##0.000")&"bn"&"）","營收 vs 指引中點 "&IF(E45<0,"−","+")&TEXT(ABS(E45)*100,"#,##0.0")&"%"&"：觀點（水準 "&IF(E88<0,"−","+")&IF(ABS(E88)<0,"−","")&"$"&TEXT(ABS(ABS(E88)),"#,##0.000")&"bn"&"（2Q–4Q27 模型 "&IF(損益!C9<0,"−","")&"$"&TEXT(ABS(損益!C9),"#,##0.000")&"bn"&"，指引隱含 "&IF(E87<0,"−","")&"$"&TEXT(ABS(E87),"#,##0.000")&"bn"&"）；分配 "&IF(E89<0,"−","+")&IF(ABS(E89)<0,"−","")&"$"&TEXT(ABS(ABS(E89)),"#,##0.000")&"bn"&"；"&"OCI 營收＝在役 MW × 每 MW 年收入（Tokenomics 正向推導），期初可計費 MW 以 Q1 實際 OCI 年化校準；傳統事業四線依近四季年增率；共識未揭露 MW 與單價假設"&"）"),"營收 vs 指引中點 "&IF(E45<0,"−","+")&TEXT(ABS(E45)*100,"#,##0.0")&"%"&"：觀點（"&"OCI 營收＝在役 MW × 每 MW 年收入（Tokenomics 正向推導），期初可計費 MW 以 Q1 實際 OCI 年化校準；傳統事業四線依近四季年增率；共識未揭露 MW 與單價假設"&"）"),""),"") | F92: =IF(ISNUMBER(F45),IF(OR(ABS(F45)>輸入與假設!$C$333,F22>F32,F22<F31),IF(ISNUMBER(F88),IF(ABS(F89)>ABS(F88),"營收 vs 指引中點 "&IF(F45<0,"−","+")&TEXT(ABS(F45)*100,"#,##0.0")&"%"&"：拆法（分配 "&IF(F89<0,"−","+")&IF(ABS(F89)<0,"−","")&"$"&TEXT(ABS(ABS(F89)),"#,##0.000")&"bn"&"（Q1 FY28 占 FY28 "&TEXT((F22/損益!D9)*100,"#,##0.0")&"%"&"，指引隱含 "&TEXT(((((F31+F32)/2))/F87)*100,"#,##0.0")&"%"&"）；水準 "&IF(F88<0,"−","+")&IF(ABS(F88)<0,"−","")&"$"&TEXT(ABS(ABS(F88)),"#,##0.000")&"bn"&"）","營收 vs 指引中點 "&IF(F45<0,"−","+")&TEXT(ABS(F45)*100,"#,##0.0")&"%"&"：觀點（水準 "&IF(F88<0,"−","+")&IF(ABS(F88)<0,"−","")&"$"&TEXT(ABS(ABS(F88)),"#,##0.000")&"bn"&"（FY28 模型 "&IF(損益!D9<0,"−","")&"$"&TEXT(ABS(損益!D9),"#,##0.000")&"bn"&"，指引隱含 "&IF(F87<0,"−","")&"$"&TEXT(ABS(F87),"#,##0.000")&"bn"&"）；分配 "&IF(F89<0,"−","+")&IF(ABS(F89)<0,"−","")&"$"&TEXT(ABS(ABS(F89)),"#,##0.000")&"bn"&"；"&"OCI 營收＝在役 MW × 每 MW 年收入（Tokenomics 正向推導），期初可計費 MW 以 Q1 實際 OCI 年化校準；傳統事業四線依近四季年增率；共識未揭露 MW 與單價假設"&"）"),"營收 vs 指引中點 "&IF(F45<0,"−","+")&TEXT(ABS(F45)*100,"#,##0.0")&"%"&"：觀點（"&"OCI 營收＝在役 MW × 每 MW 年收入（Tokenomics 正向推導），期初可計費 MW 以 Q1 實際 OCI 年化校準；傳統事業四線依近四季年增率；共識未揭露 MW 與單價假設"&"）"),""),"") | G92: =IF(ISNUMBER(G45),IF(OR(ABS(G45)>輸入與假設!$C$333,G22>G32,G22<G31),IF(ISNUMBER(G88),IF(ABS(G89)>ABS(G88),"營收 vs 指引中點 "&IF(G45<0,"−","+")&TEXT(ABS(G45)*100,"#,##0.0")&"%"&"：拆法（分配 "&IF(G89<0,"−","+")&IF(ABS(G89)<0,"−","")&"$"&TEXT(ABS(ABS(G89)),"#,##0.000")&"bn"&"（Q2 FY28 占 FY28 "&TEXT((G22/損益!D9)*100,"#,##0.0")&"%"&"，指引隱含 "&TEXT(((((G31+G32)/2))/G87)*100,"#,##0.0")&"%"&"）；水準 "&IF(G88<0,"−","+")&IF(ABS(G88)<0,"−","")&"$"&TEXT(ABS(ABS(G88)),"#,##0.000")&"bn"&"）","營收 vs 指引中點 "&IF(G45<0,"−","+")&TEXT(ABS(G45)*100,"#,##0.0")&"%"&"：觀點（水準 "&IF(G88<0,"−","+")&IF(ABS(G88)<0,"−","")&"$"&TEXT(ABS(ABS(G88)),"#,##0.000")&"bn"&"（FY28 模型 "&IF(損益!D9<0,"−","")&"$"&TEXT(ABS(損益!D9),"#,##0.000")&"bn"&"，指引隱含 "&IF(G87<0,"−","")&"$"&TEXT(ABS(G87),"#,##0.000")&"bn"&"）；分配 "&IF(G89<0,"−","+")&IF(ABS(G89)<0,"−","")&"$"&TEXT(ABS(ABS(G89)),"#,##0.000")&"bn"&"；"&"OCI 營收＝在役 MW × 每 MW 年收入（Tokenomics 正向推導），期初可計費 MW 以 Q1 實際 OCI 年化校準；傳統事業四線依近四季年增率；共識未揭露 MW 與單價假設"&"）"),"營收 vs 指引中點 "&IF(G45<0,"−","+")&TEXT(ABS(G45)*100,"#,##0.0")&"%"&"：觀點（"&"OCI 營收＝在役 MW × 每 MW 年收入（Tokenomics 正向推導），期初可計費 MW 以 Q1 實際 OCI 年化校準；傳統事業四線依近四季年增率；共識未揭露 MW 與單價假設"&"）"),""),"") | H92: =IF(ISNUMBER(H45),IF(OR(ABS(H45)>輸入與假設!$C$333,H22>H32,H22<H31),IF(ISNUMBER(H88),IF(ABS(H89)>ABS(H88),"營收 vs 指引中點 "&IF(H45<0,"−","+")&TEXT(ABS(H45)*100,"#,##0.0")&"%"&"：拆法（分配 "&IF(H89<0,"−","+")&IF(ABS(H89)<0,"−","")&"$"&TEXT(ABS(ABS(H89)),"#,##0.000")&"bn"&"（Q3 FY28 占 FY28 "&TEXT((H22/損益!D9)*100,"#,##0.0")&"%"&"，指引隱含 "&TEXT(((((H31+H32)/2))/H87)*100,"#,##0.0")&"%"&"）；水準 "&IF(H88<0,"−","+")&IF(ABS(H88)<0,"−","")&"$"&TEXT(ABS(ABS(H88)),"#,##0.000")&"bn"&"）","營收 vs 指引中點 "&IF(H45<0,"−","+")&TEXT(ABS(H45)*100,"#,##0.0")&"%"&"：觀點（水準 "&IF(H88<0,"−","+")&IF(ABS(H88)<0,"−","")&"$"&TEXT(ABS(ABS(H88)),"#,##0.000")&"bn"&"（FY28 模型 "&IF(損益!D9<0,"−","")&"$"&TEXT(ABS(損益!D9),"#,##0.000")&"bn"&"，指引隱含 "&IF(H87<0,"−","")&"$"&TEXT(ABS(H87),"#,##0.000")&"bn"&"）；分配 "&IF(H89<0,"−","+")&IF(ABS(H89)<0,"−","")&"$"&TEXT(ABS(ABS(H89)),"#,##0.000")&"bn"&"；"&"OCI 營收＝在役 MW × 每 MW 年收入（Tokenomics 正向推導），期初可計費 MW 以 Q1 實際 OCI 年化校準；傳統事業四線依近四季年增率；共識未揭露 MW 與單價假設"&"）"),"營收 vs 指引中點 "&IF(H45<0,"−","+")&TEXT(ABS(H45)*100,"#,##0.0")&"%"&"：觀點（"&"OCI 營收＝在役 MW × 每 MW 年收入（Tokenomics 正向推導），期初可計費 MW 以 Q1 實際 OCI 年化校準；傳統事業四線依近四季年增率；共識未揭露 MW 與單價假設"&"）"),""),"")
A93: 原因類型｜營收｜vs 指引中點 | C93: =IF(ISNUMBER(C45),IF(OR(ABS(C45)>輸入與假設!$C$333,C22>C32,C22<C31),IF(ISNUMBER(C88),IF(ABS(C89)>ABS(C88),"拆法","觀點"),"觀點"),""),"") | D93: =IF(ISNUMBER(D45),IF(OR(ABS(D45)>輸入與假設!$C$333,D22>D32,D22<D31),IF(ISNUMBER(D88),IF(ABS(D89)>ABS(D88),"拆法","觀點"),"觀點"),""),"") | E93: =IF(ISNUMBER(E45),IF(OR(ABS(E45)>輸入與假設!$C$333,E22>E32,E22<E31),IF(ISNUMBER(E88),IF(ABS(E89)>ABS(E88),"拆法","觀點"),"觀點"),""),"") | F93: =IF(ISNUMBER(F45),IF(OR(ABS(F45)>輸入與假設!$C$333,F22>F32,F22<F31),IF(ISNUMBER(F88),IF(ABS(F89)>ABS(F88),"拆法","觀點"),"觀點"),""),"") | G93: =IF(ISNUMBER(G45),IF(OR(ABS(G45)>輸入與假設!$C$333,G22>G32,G22<G31),IF(ISNUMBER(G88),IF(ABS(G89)>ABS(G88),"拆法","觀點"),"觀點"),""),"") | H93: =IF(ISNUMBER(H45),IF(OR(ABS(H45)>輸入與假設!$C$333,H22>H32,H22<H31),IF(ISNUMBER(H88),IF(ABS(H89)>ABS(H88),"拆法","觀點"),"觀點"),""),"")
A94: 原因｜營收｜實際 vs 模型 | C94: =IF(ISNUMBER(C46),IF(ABS(C46)>輸入與假設!$C$333,"營收 實際 vs 模型 "&IF(C46<0,"−","+")&TEXT(ABS(C46)*100,"#,##0.0")&"%"&"：觀點（"&"OCI 營收＝在役 MW × 每 MW 年收入（Tokenomics 正向推導），期初可計費 MW 以 Q1 實際 OCI 年化校準；傳統事業四線依近四季年增率；共識未揭露 MW 與單價假設"&"）",""),"") | D94: =IF(ISNUMBER(D46),IF(ABS(D46)>輸入與假設!$C$333,"營收 實際 vs 模型 "&IF(D46<0,"−","+")&TEXT(ABS(D46)*100,"#,##0.0")&"%"&"：觀點（"&"OCI 營收＝在役 MW × 每 MW 年收入（Tokenomics 正向推導），期初可計費 MW 以 Q1 實際 OCI 年化校準；傳統事業四線依近四季年增率；共識未揭露 MW 與單價假設"&"）",""),"") | E94: =IF(ISNUMBER(E46),IF(ABS(E46)>輸入與假設!$C$333,"營收 實際 vs 模型 "&IF(E46<0,"−","+")&TEXT(ABS(E46)*100,"#,##0.0")&"%"&"：觀點（"&"OCI 營收＝在役 MW × 每 MW 年收入（Tokenomics 正向推導），期初可計費 MW 以 Q1 實際 OCI 年化校準；傳統事業四線依近四季年增率；共識未揭露 MW 與單價假設"&"）",""),"") | F94: =IF(ISNUMBER(F46),IF(ABS(F46)>輸入與假設!$C$333,"營收 實際 vs 模型 "&IF(F46<0,"−","+")&TEXT(ABS(F46)*100,"#,##0.0")&"%"&"：觀點（"&"OCI 營收＝在役 MW × 每 MW 年收入（Tokenomics 正向推導），期初可計費 MW 以 Q1 實際 OCI 年化校準；傳統事業四線依近四季年增率；共識未揭露 MW 與單價假設"&"）",""),"") | G94: =IF(ISNUMBER(G46),IF(ABS(G46)>輸入與假設!$C$333,"營收 實際 vs 模型 "&IF(G46<0,"−","+")&TEXT(ABS(G46)*100,"#,##0.0")&"%"&"：觀點（"&"OCI 營收＝在役 MW × 每 MW 年收入（Tokenomics 正向推導），期初可計費 MW 以 Q1 實際 OCI 年化校準；傳統事業四線依近四季年增率；共識未揭露 MW 與單價假設"&"）",""),"") | H94: =IF(ISNUMBER(H46),IF(ABS(H46)>輸入與假設!$C$333,"營收 實際 vs 模型 "&IF(H46<0,"−","+")&TEXT(ABS(H46)*100,"#,##0.0")&"%"&"：觀點（"&"OCI 營收＝在役 MW × 每 MW 年收入（Tokenomics 正向推導），期初可計費 MW 以 Q1 實際 OCI 年化校準；傳統事業四線依近四季年增率；共識未揭露 MW 與單價假設"&"）",""),"")
A95: 原因類型｜營收｜實際 vs 模型 | C95: =IF(ISNUMBER(C46),IF(ABS(C46)>輸入與假設!$C$333,"觀點",""),"") | D95: =IF(ISNUMBER(D46),IF(ABS(D46)>輸入與假設!$C$333,"觀點",""),"") | E95: =IF(ISNUMBER(E46),IF(ABS(E46)>輸入與假設!$C$333,"觀點",""),"") | F95: =IF(ISNUMBER(F46),IF(ABS(F46)>輸入與假設!$C$333,"觀點",""),"") | G95: =IF(ISNUMBER(G46),IF(ABS(G46)>輸入與假設!$C$333,"觀點",""),"") | H95: =IF(ISNUMBER(H46),IF(ABS(H46)>輸入與假設!$C$333,"觀點",""),"")
A96: 合計基準｜調整後 EBITDA｜vs 共識 | B96: US$bn | C96: =IF(COUNT(C35,D35,E35)=3,C35+D35+E35,"不適用") -> 不適用 | D96: =IF(COUNT(C35,D35,E35)=3,C35+D35+E35,"不適用") -> 不適用 | E96: =IF(COUNT(C35,D35,E35)=3,C35+D35+E35,"不適用") -> 不適用 | F96: =IF(COUNT(F35,G35,H35)=3,F35+G35+H35,"不適用") -> 不適用 | G96: =IF(COUNT(F35,G35,H35)=3,F35+G35+H35,"不適用") -> 不適用 | H96: =IF(COUNT(F35,G35,H35)=3,F35+G35+H35,"不適用") -> 不適用 | J96: 所屬期間的季度共識合計
A97: 拆解｜調整後 EBITDA｜vs 共識｜水準 | B97: US$bn | C97: =IF(AND(ISNUMBER(C96),C96<>0,ISNUMBER(C35),ISNUMBER(C28)),(損益!C22-C96)*(C35)/C96,"不適用") -> 不適用 | D97: =IF(AND(ISNUMBER(D96),D96<>0,ISNUMBER(D35),ISNUMBER(D28)),(損益!C22-D96)*(D35)/D96,"不適用") -> 不適用 | E97: =IF(AND(ISNUMBER(E96),E96<>0,ISNUMBER(E35),ISNUMBER(E28)),(損益!C22-E96)*(E35)/E96,"不適用") -> 不適用 | F97: =IF(AND(ISNUMBER(F96),F96<>0,ISNUMBER(F35),ISNUMBER(F28)),(損益!D22-F96)*(F35)/F96,"不適用") -> 不適用 | G97: =IF(AND(ISNUMBER(G96),G96<>0,ISNUMBER(G35),ISNUMBER(G28)),(損益!D22-G96)*(G35)/G96,"不適用") -> 不適用 | H97: =IF(AND(ISNUMBER(H96),H96<>0,ISNUMBER(H35),ISNUMBER(H28)),(損益!D22-H96)*(H35)/H96,"不適用") -> 不適用 | J97: (模型期間 − 比較期間) × 比較的季占比
A98: 拆解｜調整後 EBITDA｜vs 共識｜分配 | B98: US$bn | C98: =IF(AND(ISNUMBER(C96),C96<>0,ISNUMBER(C35),ISNUMBER(C28)),(C28/損益!C22-(C35)/C96)*損益!C22,"不適用") -> 不適用 | D98: =IF(AND(ISNUMBER(D96),D96<>0,ISNUMBER(D35),ISNUMBER(D28)),(D28/損益!C22-(D35)/D96)*損益!C22,"不適用") -> 不適用 | E98: =IF(AND(ISNUMBER(E96),E96<>0,ISNUMBER(E35),ISNUMBER(E28)),(E28/損益!C22-(E35)/E96)*損益!C22,"不適用") -> 不適用 | F98: =IF(AND(ISNUMBER(F96),F96<>0,ISNUMBER(F35),ISNUMBER(F28)),(F28/損益!D22-(F35)/F96)*損益!D22,"不適用") -> 不適用 | G98: =IF(AND(ISNUMBER(G96),G96<>0,ISNUMBER(G35),ISNUMBER(G28)),(G28/損益!D22-(G35)/G96)*損益!D22,"不適用") -> 不適用 | H98: =IF(AND(ISNUMBER(H96),H96<>0,ISNUMBER(H35),ISNUMBER(H28)),(H28/損益!D22-(H35)/H96)*損益!D22,"不適用") -> 不適用 | J98: (模型季占比 − 比較季占比) × 模型期間；水準＋分配＝季度差距
A99: 原因｜調整後 EBITDA｜vs 共識 | C99: =IF(ISNUMBER(C49),IF(IF(ISNUMBER(C54),ABS(C54)>輸入與假設!$C$334,OR(AND(C35<>0,ABS(C49)>輸入與假設!$C$333*ABS(C35)),AND(C35=0,C49<>0))),IF(ISNUMBER(C97),IF(ABS(C98)>ABS(C97),"調整後 EBITDA vs 共識 "&IF(C49<0,"−","+")&IF(ABS(C49)<0,"−","")&"$"&TEXT(ABS(ABS(C49)),"#,##0.00")&"bn"&IF(ISNUMBER(C54),"／"&IF(C54<0,"−","+")&TEXT(ABS(C54)*100,"#,##0.0")&"pt","")&"：拆法（分配 "&IF(C98<0,"−","+")&IF(ABS(C98)<0,"−","")&"$"&TEXT(ABS(ABS(C98)),"#,##0.000")&"bn"&"（Q2 FY27 占 2Q–4Q27 "&TEXT((C28/損益!C22)*100,"#,##0.0")&"%"&"，共識合計 "&TEXT(((C35)/C96)*100,"#,##0.0")&"%"&"）；水準 "&IF(C97<0,"−","+")&IF(ABS(C97)<0,"−","")&"$"&TEXT(ABS(ABS(C97)),"#,##0.000")&"bn"&"）","調整後 EBITDA vs 共識 "&IF(C49<0,"−","+")&IF(ABS(C49)<0,"−","")&"$"&TEXT(ABS(ABS(C49)),"#,##0.00")&"bn"&IF(ISNUMBER(C54),"／"&IF(C54<0,"−","+")&TEXT(ABS(C54)*100,"#,##0.0")&"pt","")&"：觀點（水準 "&IF(C97<0,"−","+")&IF(ABS(C97)<0,"−","")&"$"&TEXT(ABS(ABS(C97)),"#,##0.000")&"bn"&"（2Q–4Q27 模型 "&IF(損益!C22<0,"−","")&"$"&TEXT(ABS(損益!C22),"#,##0.000")&"bn"&"，共識合計 "&IF(C96<0,"−","")&"$"&TEXT(ABS(C96),"#,##0.000")&"bn"&"）；分配 "&IF(C98<0,"−","+")&IF(ABS(C98)<0,"−","")&"$"&TEXT(ABS(ABS(C98)),"#,##0.000")&"bn"&"；"&"模型 EBITDA 率 "&IF((C27)<0,"−","")&TEXT(ABS((C27))*100,"#,##0.0")&"%"&"；季度共識 EBITDA "&IF((輸入與假設!$C$306)<0,"−","")&TEXT(ABS((輸入與假設!$C$306)),"#,##0.00")&"、營收 "&IF((輸入與假設!$C$305)<0,"−","")&TEXT(ABS((輸入與假設!$C$305)),"#,##0.00")&"（共識 EBITDA＝非 GAAP 營業利益＋折舊）"&"）"),"調整後 EBITDA vs 共識 "&IF(C49<0,"−","+")&IF(ABS(C49)<0,"−","")&"$"&TEXT(ABS(ABS(C49)),"#,##0.00")&"bn"&IF(ISNUMBER(C54),"／"&IF(C54<0,"−","+")&TEXT(ABS(C54)*100,"#,##0.0")&"pt","")&"：觀點（"&"模型 EBITDA 率 "&IF((C27)<0,"−","")&TEXT(ABS((C27))*100,"#,##0.0")&"%"&"；季度共識 EBITDA "&IF((輸入與假設!$C$306)<0,"−","")&TEXT(ABS((輸入與假設!$C$306)),"#,##0.00")&"、營收 "&IF((輸入與假設!$C$305)<0,"−","")&TEXT(ABS((輸入與假設!$C$305)),"#,##0.00")&"（共識 EBITDA＝非 GAAP 營業利益＋折舊）"&"）"),""),"") | D99: =IF(ISNUMBER(D49),IF(IF(ISNUMBER(D54),ABS(D54)>輸入與假設!$C$334,OR(AND(D35<>0,ABS(D49)>輸入與假設!$C$333*ABS(D35)),AND(D35=0,D49<>0))),IF(ISNUMBER(D97),IF(ABS(D98)>ABS(D97),"調整後 EBITDA vs 共識 "&IF(D49<0,"−","+")&IF(ABS(D49)<0,"−","")&"$"&TEXT(ABS(ABS(D49)),"#,##0.00")&"bn"&IF(ISNUMBER(D54),"／"&IF(D54<0,"−","+")&TEXT(ABS(D54)*100,"#,##0.0")&"pt","")&"：拆法（分配 "&IF(D98<0,"−","+")&IF(ABS(D98)<0,"−","")&"$"&TEXT(ABS(ABS(D98)),"#,##0.000")&"bn"&"（Q3 FY27 占 2Q–4Q27 "&TEXT((D28/損益!C22)*100,"#,##0.0")&"%"&"，共識合計 "&TEXT(((D35)/D96)*100,"#,##0.0")&"%"&"）；水準 "&IF(D97<0,"−","+")&IF(ABS(D97)<0,"−","")&"$"&TEXT(ABS(ABS(D97)),"#,##0.000")&"bn"&"）","調整後 EBITDA vs 共識 "&IF(D49<0,"−","+")&IF(ABS(D49)<0,"−","")&"$"&TEXT(ABS(ABS(D49)),"#,##0.00")&"bn"&IF(ISNUMBER(D54),"／"&IF(D54<0,"−","+")&TEXT(ABS(D54)*100,"#,##0.0")&"pt","")&"：觀點（水準 "&IF(D97<0,"−","+")&IF(ABS(D97)<0,"−","")&"$"&TEXT(ABS(ABS(D97)),"#,##0.000")&"bn"&"（2Q–4Q27 模型 "&IF(損益!C22<0,"−","")&"$"&TEXT(ABS(損益!C22),"#,##0.000")&"bn"&"，共識合計 "&IF(D96<0,"−","")&"$"&TEXT(ABS(D96),"#,##0.000")&"bn"&"）；分配 "&IF(D98<0,"−","+")&IF(ABS(D98)<0,"−","")&"$"&TEXT(ABS(ABS(D98)),"#,##0.000")&"bn"&"；"&"模型 EBITDA 率 "&IF((D27)<0,"−","")&TEXT(ABS((D27))*100,"#,##0.0")&"%"&"；季度共識 EBITDA "&IF((輸入與假設!$D$306)<0,"−","")&TEXT(ABS((輸入與假設!$D$306)),"#,##0.00")&"、營收 "&IF((輸入與假設!$D$305)<0,"−","")&TEXT(ABS((輸入與假設!$D$305)),"#,##0.00")&"（共識 EBITDA＝非 GAAP 營業利益＋折舊）"&"）"),"調整後 EBITDA vs 共識 "&IF(D49<0,"−","+")&IF(ABS(D49)<0,"−","")&"$"&TEXT(ABS(ABS(D49)),"#,##0.00")&"bn"&IF(ISNUMBER(D54),"／"&IF(D54<0,"−","+")&TEXT(ABS(D54)*100,"#,##0.0")&"pt","")&"：觀點（"&"模型 EBITDA 率 "&IF((D27)<0,"−","")&TEXT(ABS((D27))*100,"#,##0.0")&"%"&"；季度共識 EBITDA "&IF((輸入與假設!$D$306)<0,"−","")&TEXT(ABS((輸入與假設!$D$306)),"#,##0.00")&"、營收 "&IF((輸入與假設!$D$305)<0,"−","")&TEXT(ABS((輸入與假設!$D$305)),"#,##0.00")&"（共識 EBITDA＝非 GAAP 營業利益＋折舊）"&"）"),""),"") | E99: =IF(ISNUMBER(E49),IF(IF(ISNUMBER(E54),ABS(E54)>輸入與假設!$C$334,OR(AND(E35<>0,ABS(E49)>輸入與假設!$C$333*ABS(E35)),AND(E35=0,E49<>0))),IF(ISNUMBER(E97),IF(ABS(E98)>ABS(E97),"調整後 EBITDA vs 共識 "&IF(E49<0,"−","+")&IF(ABS(E49)<0,"−","")&"$"&TEXT(ABS(ABS(E49)),"#,##0.00")&"bn"&IF(ISNUMBER(E54),"／"&IF(E54<0,"−","+")&TEXT(ABS(E54)*100,"#,##0.0")&"pt","")&"：拆法（分配 "&IF(E98<0,"−","+")&IF(ABS(E98)<0,"−","")&"$"&TEXT(ABS(ABS(E98)),"#,##0.000")&"bn"&"（Q4 FY27 占 2Q–4Q27 "&TEXT((E28/損益!C22)*100,"#,##0.0")&"%"&"，共識合計 "&TEXT(((E35)/E96)*100,"#,##0.0")&"%"&"）；水準 "&IF(E97<0,"−","+")&IF(ABS(E97)<0,"−","")&"$"&TEXT(ABS(ABS(E97)),"#,##0.000")&"bn"&"）","調整後 EBITDA vs 共識 "&IF(E49<0,"−","+")&IF(ABS(E49)<0,"−","")&"$"&TEXT(ABS(ABS(E49)),"#,##0.00")&"bn"&IF(ISNUMBER(E54),"／"&IF(E54<0,"−","+")&TEXT(ABS(E54)*100,"#,##0.0")&"pt","")&"：觀點（水準 "&IF(E97<0,"−","+")&IF(ABS(E97)<0,"−","")&"$"&TEXT(ABS(ABS(E97)),"#,##0.000")&"bn"&"（2Q–4Q27 模型 "&IF(損益!C22<0,"−","")&"$"&TEXT(ABS(損益!C22),"#,##0.000")&"bn"&"，共識合計 "&IF(E96<0,"−","")&"$"&TEXT(ABS(E96),"#,##0.000")&"bn"&"）；分配 "&IF(E98<0,"−","+")&IF(ABS(E98)<0,"−","")&"$"&TEXT(ABS(ABS(E98)),"#,##0.000")&"bn"&"；"&"模型 EBITDA 率 "&IF((E27)<0,"−","")&TEXT(ABS((E27))*100,"#,##0.0")&"%"&"；季度共識 EBITDA "&"不適用"&"、營收 "&"不適用"&"（共識 EBITDA＝非 GAAP 營業利益＋折舊）"&"）"),"調整後 EBITDA vs 共識 "&IF(E49<0,"−","+")&IF(ABS(E49)<0,"−","")&"$"&TEXT(ABS(ABS(E49)),"#,##0.00")&"bn"&IF(ISNUMBER(E54),"／"&IF(E54<0,"−","+")&TEXT(ABS(E54)*100,"#,##0.0")&"pt","")&"：觀點（"&"模型 EBITDA 率 "&IF((E27)<0,"−","")&TEXT(ABS((E27))*100,"#,##0.0")&"%"&"；季度共識 EBITDA "&"不適用"&"、營收 "&"不適用"&"（共識 EBITDA＝非 GAAP 營業利益＋折舊）"&"）"),""),"") | F99: =IF(ISNUMBER(F49),IF(IF(ISNUMBER(F54),ABS(F54)>輸入與假設!$C$334,OR(AND(F35<>0,ABS(F49)>輸入與假設!$C$333*ABS(F35)),AND(F35=0,F49<>0))),IF(ISNUMBER(F97),IF(ABS(F98)>ABS(F97),"調整後 EBITDA vs 共識 "&IF(F49<0,"−","+")&IF(ABS(F49)<0,"−","")&"$"&TEXT(ABS(ABS(F49)),"#,##0.00")&"bn"&IF(ISNUMBER(F54),"／"&IF(F54<0,"−","+")&TEXT(ABS(F54)*100,"#,##0.0")&"pt","")&"：拆法（分配 "&IF(F98<0,"−","+")&IF(ABS(F98)<0,"−","")&"$"&TEXT(ABS(ABS(F98)),"#,##0.000")&"bn"&"（Q1 FY28 占 FY28 "&TEXT((F28/損益!D22)*100,"#,##0.0")&"%"&"，共識合計 "&TEXT(((F35)/F96)*100,"#,##0.0")&"%"&"）；水準 "&IF(F97<0,"−","+")&IF(ABS(F97)<0,"−","")&"$"&TEXT(ABS(ABS(F97)),"#,##0.000")&"bn"&"）","調整後 EBITDA vs 共識 "&IF(F49<0,"−","+")&IF(ABS(F49)<0,"−","")&"$"&TEXT(ABS(ABS(F49)),"#,##0.00")&"bn"&IF(ISNUMBER(F54),"／"&IF(F54<0,"−","+")&TEXT(ABS(F54)*100,"#,##0.0")&"pt","")&"：觀點（水準 "&IF(F97<0,"−","+")&IF(ABS(F97)<0,"−","")&"$"&TEXT(ABS(ABS(F97)),"#,##0.000")&"bn"&"（FY28 模型 "&IF(損益!D22<0,"−","")&"$"&TEXT(ABS(損益!D22),"#,##0.000")&"bn"&"，共識合計 "&IF(F96<0,"−","")&"$"&TEXT(ABS(F96),"#,##0.000")&"bn"&"）；分配 "&IF(F98<0,"−","+")&IF(ABS(F98)<0,"−","")&"$"&TEXT(ABS(ABS(F98)),"#,##0.000")&"bn"&"；"&"模型 EBITDA 率 "&IF((F27)<0,"−","")&TEXT(ABS((F27))*100,"#,##0.0")&"%"&"；季度共識 EBITDA "&"不適用"&"、營收 "&"不適用"&"（共識 EBITDA＝非 GAAP 營業利益＋折舊）"&"）"),"調整後 EBITDA vs 共識 "&IF(F49<0,"−","+")&IF(ABS(F49)<0,"−","")&"$"&TEXT(ABS(ABS(F49)),"#,##0.00")&"bn"&IF(ISNUMBER(F54),"／"&IF(F54<0,"−","+")&TEXT(ABS(F54)*100,"#,##0.0")&"pt","")&"：觀點（"&"模型 EBITDA 率 "&IF((F27)<0,"−","")&TEXT(ABS((F27))*100,"#,##0.0")&"%"&"；季度共識 EBITDA "&"不適用"&"、營收 "&"不適用"&"（共識 EBITDA＝非 GAAP 營業利益＋折舊）"&"）"),""),"") | G99: =IF(ISNUMBER(G49),IF(IF(ISNUMBER(G54),ABS(G54)>輸入與假設!$C$334,OR(AND(G35<>0,ABS(G49)>輸入與假設!$C$333*ABS(G35)),AND(G35=0,G49<>0))),IF(ISNUMBER(G97),IF(ABS(G98)>ABS(G97),"調整後 EBITDA vs 共識 "&IF(G49<0,"−","+")&IF(ABS(G49)<0,"−","")&"$"&TEXT(ABS(ABS(G49)),"#,##0.00")&"bn"&IF(ISNUMBER(G54),"／"&IF(G54<0,"−","+")&TEXT(ABS(G54)*100,"#,##0.0")&"pt","")&"：拆法（分配 "&IF(G98<0,"−","+")&IF(ABS(G98)<0,"−","")&"$"&TEXT(ABS(ABS(G98)),"#,##0.000")&"bn"&"（Q2 FY28 占 FY28 "&TEXT((G28/損益!D22)*100,"#,##0.0")&"%"&"，共識合計 "&TEXT(((G35)/G96)*100,"#,##0.0")&"%"&"）；水準 "&IF(G97<0,"−","+")&IF(ABS(G97)<0,"−","")&"$"&TEXT(ABS(ABS(G97)),"#,##0.000")&"bn"&"）","調整後 EBITDA vs 共識 "&IF(G49<0,"−","+")&IF(ABS(G49)<0,"−","")&"$"&TEXT(ABS(ABS(G49)),"#,##0.00")&"bn"&IF(ISNUMBER(G54),"／"&IF(G54<0,"−","+")&TEXT(ABS(G54)*100,"#,##0.0")&"pt","")&"：觀點（水準 "&IF(G97<0,"−","+")&IF(ABS(G97)<0,"−","")&"$"&TEXT(ABS(ABS(G97)),"#,##0.000")&"bn"&"（FY28 模型 "&IF(損益!D22<0,"−","")&"$"&TEXT(ABS(損益!D22),"#,##0.000")&"bn"&"，共識合計 "&IF(G96<0,"−","")&"$"&TEXT(ABS(G96),"#,##0.000")&"bn"&"）；分配 "&IF(G98<0,"−","+")&IF(ABS(G98)<0,"−","")&"$"&TEXT(ABS(ABS(G98)),"#,##0.000")&"bn"&"；"&"模型 EBITDA 率 "&IF((G27)<0,"−","")&TEXT(ABS((G27))*100,"#,##0.0")&"%"&"；季度共識 EBITDA "&"不適用"&"、營收 "&"不適用"&"（共識 EBITDA＝非 GAAP 營業利益＋折舊）"&"）"),"調整後 EBITDA vs 共識 "&IF(G49<0,"−","+")&IF(ABS(G49)<0,"−","")&"$"&TEXT(ABS(ABS(G49)),"#,##0.00")&"bn"&IF(ISNUMBER(G54),"／"&IF(G54<0,"−","+")&TEXT(ABS(G54)*100,"#,##0.0")&"pt","")&"：觀點（"&"模型 EBITDA 率 "&IF((G27)<0,"−","")&TEXT(ABS((G27))*100,"#,##0.0")&"%"&"；季度共識 EBITDA "&"不適用"&"、營收 "&"不適用"&"（共識 EBITDA＝非 GAAP 營業利益＋折舊）"&"）"),""),"") | H99: =IF(ISNUMBER(H49),IF(IF(ISNUMBER(H54),ABS(H54)>輸入與假設!$C$334,OR(AND(H35<>0,ABS(H49)>輸入與假設!$C$333*ABS(H35)),AND(H35=0,H49<>0))),IF(ISNUMBER(H97),IF(ABS(H98)>ABS(H97),"調整後 EBITDA vs 共識 "&IF(H49<0,"−","+")&IF(ABS(H49)<0,"−","")&"$"&TEXT(ABS(ABS(H49)),"#,##0.00")&"bn"&IF(ISNUMBER(H54),"／"&IF(H54<0,"−","+")&TEXT(ABS(H54)*100,"#,##0.0")&"pt","")&"：拆法（分配 "&IF(H98<0,"−","+")&IF(ABS(H98)<0,"−","")&"$"&TEXT(ABS(ABS(H98)),"#,##0.000")&"bn"&"（Q3 FY28 占 FY28 "&TEXT((H28/損益!D22)*100,"#,##0.0")&"%"&"，共識合計 "&TEXT(((H35)/H96)*100,"#,##0.0")&"%"&"）；水準 "&IF(H97<0,"−","+")&IF(ABS(H97)<0,"−","")&"$"&TEXT(ABS(ABS(H97)),"#,##0.000")&"bn"&"）","調整後 EBITDA vs 共識 "&IF(H49<0,"−","+")&IF(ABS(H49)<0,"−","")&"$"&TEXT(ABS(ABS(H49)),"#,##0.00")&"bn"&IF(ISNUMBER(H54),"／"&IF(H54<0,"−","+")&TEXT(ABS(H54)*100,"#,##0.0")&"pt","")&"：觀點（水準 "&IF(H97<0,"−","+")&IF(ABS(H97)<0,"−","")&"$"&TEXT(ABS(ABS(H97)),"#,##0.000")&"bn"&"（FY28 模型 "&IF(損益!D22<0,"−","")&"$"&TEXT(ABS(損益!D22),"#,##0.000")&"bn"&"，共識合計 "&IF(H96<0,"−","")&"$"&TEXT(ABS(H96),"#,##0.000")&"bn"&"）；分配 "&IF(H98<0,"−","+")&IF(ABS(H98)<0,"−","")&"$"&TEXT(ABS(ABS(H98)),"#,##0.000")&"bn"&"；"&"模型 EBITDA 率 "&IF((H27)<0,"−","")&TEXT(ABS((H27))*100,"#,##0.0")&"%"&"；季度共識 EBITDA "&"不適用"&"、營收 "&"不適用"&"（共識 EBITDA＝非 GAAP 營業利益＋折舊）"&"）"),"調整後 EBITDA vs 共識 "&IF(H49<0,"−","+")&IF(ABS(H49)<0,"−","")&"$"&TEXT(ABS(ABS(H49)),"#,##0.00")&"bn"&IF(ISNUMBER(H54),"／"&IF(H54<0,"−","+")&TEXT(ABS(H54)*100,"#,##0.0")&"pt","")&"：觀點（"&"模型 EBITDA 率 "&IF((H27)<0,"−","")&TEXT(ABS((H27))*100,"#,##0.0")&"%"&"；季度共識 EBITDA "&"不適用"&"、營收 "&"不適用"&"（共識 EBITDA＝非 GAAP 營業利益＋折舊）"&"）"),""),"")
A100: 原因類型｜調整後 EBITDA｜vs 共識 | C100: =IF(ISNUMBER(C49),IF(IF(ISNUMBER(C54),ABS(C54)>輸入與假設!$C$334,OR(AND(C35<>0,ABS(C49)>輸入與假設!$C$333*ABS(C35)),AND(C35=0,C49<>0))),IF(ISNUMBER(C97),IF(ABS(C98)>ABS(C97),"拆法","觀點"),"觀點"),""),"") | D100: =IF(ISNUMBER(D49),IF(IF(ISNUMBER(D54),ABS(D54)>輸入與假設!$C$334,OR(AND(D35<>0,ABS(D49)>輸入與假設!$C$333*ABS(D35)),AND(D35=0,D49<>0))),IF(ISNUMBER(D97),IF(ABS(D98)>ABS(D97),"拆法","觀點"),"觀點"),""),"") | E100: =IF(ISNUMBER(E49),IF(IF(ISNUMBER(E54),ABS(E54)>輸入與假設!$C$334,OR(AND(E35<>0,ABS(E49)>輸入與假設!$C$333*ABS(E35)),AND(E35=0,E49<>0))),IF(ISNUMBER(E97),IF(ABS(E98)>ABS(E97),"拆法","觀點"),"觀點"),""),"") | F100: =IF(ISNUMBER(F49),IF(IF(ISNUMBER(F54),ABS(F54)>輸入與假設!$C$334,OR(AND(F35<>0,ABS(F49)>輸入與假設!$C$333*ABS(F35)),AND(F35=0,F49<>0))),IF(ISNUMBER(F97),IF(ABS(F98)>ABS(F97),"拆法","觀點"),"觀點"),""),"") | G100: =IF(ISNUMBER(G49),IF(IF(ISNUMBER(G54),ABS(G54)>輸入與假設!$C$334,OR(AND(G35<>0,ABS(G49)>輸入與假設!$C$333*ABS(G35)),AND(G35=0,G49<>0))),IF(ISNUMBER(G97),IF(ABS(G98)>ABS(G97),"拆法","觀點"),"觀點"),""),"") | H100: =IF(ISNUMBER(H49),IF(IF(ISNUMBER(H54),ABS(H54)>輸入與假設!$C$334,OR(AND(H35<>0,ABS(H49)>輸入與假設!$C$333*ABS(H35)),AND(H35=0,H49<>0))),IF(ISNUMBER(H97),IF(ABS(H98)>ABS(H97),"拆法","觀點"),"觀點"),""),"")
A101: 原因｜調整後 EBITDA｜vs 指引中點
A102: 原因類型｜調整後 EBITDA｜vs 指引中點
...

Sheet 運營_產能與收入
A1: 產能與收入 — 合約排程 vs 機房產能
A2: 兩條線獨立產生後相減：排程>容量→瓶頸（收不到）；容量>排程→剩餘產能（要靠新簽約賣掉）
A3: FY27 欄口徑：MW 為年底存量；標示「（模型期）」的收入列只含 2027 第 2–4 季——RPO 桶自 2026-08-31 起算，1Q 收入已實現、不再受產能約束。1Q 實際單列，兩者相加即 FY27 全年（見本頁「FY26 全年」列）。
A5: 項目 | B5: 單位 | C5: FY27 | D5: FY28 | E5: FY29 | F5: FY30 | G5: FY31 | I5: 公式／來源說明
A6: 模型期間 | C6: ="2026-09-01~05-31" -> 2026-09-01~05-31 | D6: ="2028 全年" -> 2028 全年 | E6: ="2029 全年" -> 2029 全年 | F6: ="2030 全年" -> 2030 全年 | G6: ="2031 全年" -> 2031 全年 | I6: FY27 的模型期只有第 2–4 季；1Q 已實現的營收單列於下方
A7: 模型期長度（年） | C7: =輸入與假設!C$41 -> 0.75 | D7: =輸入與假設!D$41 -> 1 | E7: =輸入與假設!E$41 -> 1 | F7: =輸入與假設!F$41 -> 1 | G7: =輸入與假設!G$41 -> 1 | I7: 只用於下方三處：容量上限、電力、維護——把年率換算成該期金額
A8: （A）機房：容量上限
A9: Accepted MW（已驗收，單調不減） | B9: MW | C9: =MAX(0,輸入與假設!C$43) -> 4668 | D9: =MAX(輸入與假設!D$43,C9) -> 7501 | E9: =MAX(輸入與假設!E$43,D9) -> 8778 | F9: =MAX(輸入與假設!F$43,E9) -> 8778 | G9: =MAX(輸入與假設!G$43,F9) -> 8778 | I9: 引擎規則：不得低於前期（產能不會消失）
A10: Billable MW（上限為 Accepted） | B10: MW | C10: =MIN(MAX(0,輸入與假設!C$44),C9) -> 3183 | D10: =MIN(MAX(0,輸入與假設!D$44),D9) -> 6340 | E10: =MIN(MAX(0,輸入與假設!E$44),E9) -> 7716 | F10: =MIN(MAX(0,輸入與假設!F$44),F9) -> 8070 | G10: =MIN(MAX(0,輸入與假設!G$44),G9) -> 8070 | I10: 引擎規則：可計費不得超過已驗收
A11: Billable MW（延誤後，計費用） | B11: MW | C11: =IF($C$50<=0,$C$10,輸入與假設!$C$36+($C$10-輸入與假設!$C$36)*MAX(0,MIN(1,($C$51-$C$50/12-0)/$C$7))+($D$10-$C$10)*MAX(0,MIN(1,($C$51-$C$50/12-$C$51)/$D$7))+($E$10-$D$10)*MAX(0,MIN(1,($C$51-$C$50/12-$D$51)/$E$7))+($F$10-$E$10)*MAX(0,MIN(1,($C$51-$C$50/12-$E$51)/$F$7))+($G$10-$F$10)*MAX(0,MIN(1,($C$51-$C$50/12-$F$51)/$G$7))) -> 2688 | D11: =IF($C$50<=0,$D$10,輸入與假設!$C$36+($C$10-輸入與假設!$C$36)*MAX(0,MIN(1,($D$51-$C$50/12-0)/$C$7))+($D$10-$C$10)*MAX(0,MIN(1,($D$51-$C$50/12-$C$51)/$D$7))+($E$10-$D$10)*MAX(0,MIN(1,($D$51-$C$50/12-$D$51)/$E$7))+($F$10-$E$10)*MAX(0,MIN(1,($D$51-$C$50/12-$E$51)/$F$7))+($G$10-$F$10)*MAX(0,MIN(1,($D$51-$C$50/12-$F$51)/$G$7))) -> 5550.75 | E11: =IF($C$50<=0,$E$10,輸入與假設!$C$36+($C$10-輸入與假設!$C$36)*MAX(0,MIN(1,($E$51-$C$50/12-0)/$C$7))+($D$10-$C$10)*MAX(0,MIN(1,($E$51-$C$50/12-$C$51)/$D$7))+($E$10-$D$10)*MAX(0,MIN(1,($E$51-$C$50/12-$D$51)/$E$7))+($F$10-$E$10)*MAX(0,MIN(1,($E$51-$C$50/12-$E$51)/$F$7))+($G$10-$F$10)*MAX(0,MIN(1,($E$51-$C$50/12-$F$51)/$G$7))) -> 7372 | F11: =IF($C$50<=0,$F$10,輸入與假設!$C$36+($C$10-輸入與假設!$C$36)*MAX(0,MIN(1,($F$51-$C$50/12-0)/$C$7))+($D$10-$C$10)*MAX(0,MIN(1,($F$51-$C$50/12-$C$51)/$D$7))+($E$10-$D$10)*MAX(0,MIN(1,($F$51-$C$50/12-$D$51)/$E$7))+($F$10-$E$10)*MAX(0,MIN(1,($F$51-$C$50/12-$E$51)/$F$7))+($G$10-$F$10)*MAX(0,MIN(1,($F$51-$C$50/12-$F$51)/$G$7))) -> 7981.5 | G11: =IF($C$50<=0,$G$10,輸入與假設!$C$36+($C$10-輸入與假設!$C$36)*MAX(0,MIN(1,($G$51-$C$50/12-0)/$C$7))+($D$10-$C$10)*MAX(0,MIN(1,($G$51-$C$50/12-$C$51)/$D$7))+($E$10-$D$10)*MAX(0,MIN(1,($G$51-$C$50/12-$D$51)/$E$7))+($F$10-$E$10)*MAX(0,MIN(1,($G$51-$C$50/12-$E$51)/$F$7))+($G$10-$F$10)*MAX(0,MIN(1,($G$51-$C$50/12-$F$51)/$G$7))) -> 8070 | I11: ＝上列往後平移建設延誤月數（以期間長度線性內插；評價日之前取期初校準值）；延誤 0 時＝上列；見（E）區（v0.2）
A12: 期初在役 MW | B12: MW | C12: =輸入與假設!$C$36 -> 1698 | D12: =C11 -> 2688 | E12: =D11 -> 5550.75 | F12: =E11 -> 7372 | G12: =F11 -> 7981.5 | I12: 前期期末＝本期期初（延誤後）
A13: 平均在役 MW（FY27 欄為第 2–4 季平均） | B13: MW | C13: =IF(輸入與假設!$C$37=1,(C12+C11)/2,C11) -> 2193 | D13: =IF(輸入與假設!$C$37=1,(D12+D11)/2,D11) -> 4119.375 | E13: =IF(輸入與假設!$C$37=1,(E12+E11)/2,E11) -> 6461.375 | F13: =IF(輸入與假設!$C$37=1,(F12+F11)/2,F11) -> 7676.75 | G13: =IF(輸入與假設!$C$37=1,(G12+G11)/2,G11) -> 8025.75 | I13: 開關在輸入頁：1＝(期初+期末)/2，0＝期末全期化
A14: 利用率 | B14: % | C14: =輸入與假設!C$45 -> 1 | D14: =輸入與假設!D$45 -> 1 | E14: =輸入與假設!E$45 -> 1 | F14: =輸入與假設!F$45 -> 1 | G14: =輸入與假設!G$45 -> 1
A15: 每 MW 年收入 | B15: US$bn/MW | C15: =輸入與假設!C$46 -> 0.0174 | D15: =輸入與假設!D$46 -> 0.0174 | E15: =輸入與假設!E$46 -> 0.0174 | F15: =輸入與假設!F$46 -> 0.0174 | G15: =輸入與假設!G$46 -> 0.0174
A16: 容量上限（模型期最多能交付的收入） | B16: US$bn | C16: =C13*輸入與假設!C$46*輸入與假設!$C$39*輸入與假設!C$45*C7 -> 28.61865 | D16: =D13*輸入與假設!D$46*輸入與假設!$C$39*輸入與假設!D$45*D7 -> 71.677125 | E16: =E13*輸入與假設!E$46*輸入與假設!$C$39*輸入與假設!E$45*E7 -> 112.42793 | F16: =F13*輸入與假設!F$46*輸入與假設!$C$39*輸入與假設!F$45*F7 -> 133.57545 | G16: =G13*輸入與假設!G$46*輸入與假設!$C$39*輸入與假設!G$45*G7 -> 139.64805 | I16: ＝平均在役 MW × 每 MW 年收入 × 利用率 × 期間係數。只看機房，不看合約
A17: （B）合約：排程 RPO
A18: 排程 RPO（模型期，依季報桶分攤） | B18: US$bn | C18: =(輸入與假設!$C$31+輸入與假設!$C$32)*(輸入與假設!C$42/輸入與假設!$C$34)*輸入與假設!$C$33 -> 64.74 | D18: =(輸入與假設!$C$31+輸入與假設!$C$32)*(輸入與假設!D$42/輸入與假設!$C$34)*輸入與假設!$C$33 -> 113.71 | E18: =(輸入與假設!$C$31+輸入與假設!$C$32)*(輸入與假設!E$42/輸入與假設!$C$34)*輸入與假設!$C$33 -> 122.84 | F18: =(輸入與假設!$C$31+輸入與假設!$C$32)*(輸入與假設!F$42/輸入與假設!$C$34)*輸入與假設!$C$33 -> 115.37 | G18: =(輸入與假設!$C$31+輸入與假設!$C$32)*(輸入與假設!G$42/輸入與假設!$C$34)*輸入與假設!$C$33 -> 112.88 | I18: ＝(8/31 RPO＋評價日後新增)×本期權重÷權重合計×五期認列比例。只看合約，不看機房
A19: （C）兩條線相減
A20: 產能瓶頸（模型期：排程 − 容量） | B20: US$bn | C20: =MAX(0,C18-C16) -> 36.12135 | D20: =MAX(0,D18-D16) -> 42.032875 | E20: =MAX(0,E18-E16) -> 10.412075 | F20: =MAX(0,F18-F16) -> 0 | G20: =MAX(0,G18-G16) -> 0 | I20: 合約有、機房沒有 → 本期收不到，且不遞延到下期（保守處理）
A21: 期初 RPO 轉換收入（模型期） | B21: US$bn | C21: =C18-C20 -> 28.61865 | D21: =D18-D20 -> 71.677125 | E21: =E18-E20 -> 112.42793 | F21: =F18-F20 -> 115.37 | G21: =G18-G20 -> 112.88 | I21: ＝排程 − 瓶頸。當瓶頸>0 時，此值恆等於容量上限
A22: 未被期初 RPO 占用的產能 | B22: US$bn | C22: =MAX(0,C16-C18) -> 0 | D22: =MAX(0,D16-D18) -> 0 | E22: =MAX(0,E16-E18) -> 0 | F22: =MAX(0,F16-F18) -> 18.20545 | G22: =MAX(0,G16-G18) -> 26.76805 | I22: 容量 − 排程。機房有、期初合約沒占滿 → 要靠新簽約
A23: 新產能簽約率 | B23: % | C23: =IF(輸入與假設!$C$38="mw",1,輸入與假設!C$47) -> 1 | D23: =IF(輸入與假設!$C$38="mw",1,輸入與假設!D$47) -> 1 | E23: =IF(輸入與假設!$C$38="mw",1,輸入與假設!E$47) -> 1 | F23: =IF(輸入與假設!$C$38="mw",1,輸入與假設!F$47) -> 1 | G23: =IF(輸入與假設!$C$38="mw",1,輸入與假設!G$47) -> 1 | I23: MW 驅動時固定 100%
A24: 新簽約收入 | B24: US$bn | C24: =C22*C23 -> 0 | D24: =D22*D23 -> 0 | E24: =E22*E23 -> 0 | F24: =F22*F23 -> 18.20545 | G24: =G22*G23 -> 26.76805 | I24: 超出期初 RPO 的產能收入（MW 驅動，簽約率 100%）
A25: 未售產能（浪費） | B25: US$bn | C25: =MAX(0,C16-C21-C24) -> 0 | D25: =MAX(0,D16-D21-D24) -> 0 | E25: =MAX(0,E16-E21-E24) -> 0 | F25: =MAX(0,F16-F21-F24) -> 0 | G25: =MAX(0,G16-G21-G24) -> 0 | I25: 蓋好但賣不掉（MW 驅動時為 0）
A26: 損益用算力收入（模型期＝RPO 轉換＋新簽約） | B26: US$bn | C26: =C21+C24 -> 28.61865 | D26: =D21+D24 -> 71.677125 | E26: =E21+E24 -> 112.42793 | F26: =F21+F24 -> 133.57545 | G26: =G21+G24 -> 139.64805 | I26: 損益與評價頁的算力收入由此連結，確保現金與損益同一組數字
A27: 核對：算力收入 − 平均在役 MW × 每 MW × 利用率 × 期間 | B27: US$bn | C27: =C26-C13*輸入與假設!C$46*輸入與假設!$C$39*輸入與假設!C$45*C7 -> 0 | D27: =D26-D13*輸入與假設!D$46*輸入與假設!$C$39*輸入與假設!D$45*D7 -> 0 | E27: =E26-E13*輸入與假設!E$46*輸入與假設!$C$39*輸入與假設!E$45*E7 -> 0 | F27: =F26-F13*輸入與假設!F$46*輸入與假設!$C$39*輸入與假設!F$45*F7 -> 0 | G27: =G26-G13*輸入與假設!G$46*輸入與假設!$C$39*輸入與假設!G$45*G7 -> 0 | I27: MW 驅動時應為 0：營收可追溯為 MW × 每 MW 年收入 × 利用率（v0.1b）
A28: 對照：評價日起 36 個月營收權重 | B28: % | C28: 1 | D28: 1 | E28: 1 | F28: 0.25 | G28: 0 | I28: RPO 36 個月內轉換的對照用（只作對照，不驅動營收）
A29: 對照：評價日起 36 個月 MW 驅動營收 | B29: US$bn | C29: =C26*C28 -> 28.61865 | D29: =D26*D28 -> 71.677125 | E29: =E26*E28 -> 112.42793 | F29: =F26*F28 -> 33.393862 | G29: =G26*G28 -> 0 | I29: 合計對照季報 RPO 664 × 36 個月內 50%（含傳統事業 RPO）；差額不回推每 MW 單價
A30: 1Q27 實際營收（季報，已實現） | B30: US$bn | C30: =輸入與假設!$C$251 -> 19.345 | D30: =0 -> 0 | E30: =0 -> 0 | F30: =0 -> 0 | G30: =0 -> 0 | I30: 2026-06-01 至 08-31 已認列營收。已實現，不受第 2–4 季產能約束，故不進入上方的瓶頸計算
A31: FY27 全年總營收（1Q 實際＋模型期算力＋服務＋傳統事業） | B31: US$bn | C31: =C30+C26+輸入與假設!C$50+輸入與假設!C$81 -> 87.49762 | D31: =D30+D26+輸入與假設!D$50+輸入與假設!D$81 -> 125.38525 | E31: =E30+E26+輸入與假設!E$50+輸入與假設!E$81 -> 168.28174 | F31: =F30+F26+輸入與假設!F$50+輸入與假設!F$81 -> 191.45057 | G31: =G30+G26+輸入與假設!G$50+輸入與假設!G$81 -> 199.37053 | I31: FY27 欄對照公司全年指引 ≥90；FY28 以後即為該年度總營收
A32: （D）收入 → 現金：三道折扣
A33: 客戶違約率 | B33: % | C33: =輸入與假設!C$48 -> 0.005 | D33: =輸入與假設!D$48 -> 0.01 | E33: =輸入與假設!E$48 -> 0.015 | F33: =輸入與假設!F$48 -> 0.02 | G33: =輸入與假設!G$48 -> 0.025
A34: 回收率 | B34: % | C34: =輸入與假設!C$49 -> 0.5 | D34: =輸入與假設!D$49 -> 0.5 | E34: =輸入與假設!E$49 -> 0.5 | F34: =輸入與假設!F$49 -> 0.5 | G34: =輸入與假設!G$49 -> 0.5
A35: 信用損失（期初 RPO 部分） | B35: US$bn | C35: =C21*輸入與假設!C$48*(1-輸入與假設!C$49) -> 0.071546625 | D35: =D21*輸入與假設!D$48*(1-輸入與假設!D$49) -> 0.35838562 | E35: =E21*輸入與假設!E$48*(1-輸入與假設!E$49) -> 0.84320944 | F35: =F21*輸入與假設!F$48*(1-輸入與假設!F$49) -> 1.1537 | G35: =G21*輸入與假設!G$48*(1-輸入與假設!G$49) -> 1.411 | I35: ＝收入 × 違約率 × (1−回收率)
A36: 收現（期初 RPO 部分） | B36: US$bn | C36: =C21-C35 -> 28.547103 | D36: =D21-D35 -> 71.318739 | E36: =E21-E35 -> 111.58472 | F36: =F21-F35 -> 114.2163 | G36: =G21-G35 -> 111.469
A37: EBITDA 率（損益與資金共用） | B37: % | C37: =輸入與假設!C$93 -> 0.65039005 | D37: =輸入與假設!D$93 -> 0.61346746 | E37: =輸入與假設!E$93 -> 0.56794063 | F37: =輸入與假設!F$93 -> 0.51660121 | G37: =輸入與假設!G$93 -> 0.46913568 | I37: 起始→穩態線性爬升
A38: 模型期總營收（算力＋服務） | B38: US$bn | C38: =C26+輸入與假設!C$50 -> 28.61865 | D38: =D26+輸入與假設!D$50 -> 71.677125 | E38: =E26+輸入與假設!E$50 -> 112.42793 | F38: =F26+輸入與假設!F$50 -> 133.57545 | G38: =G26+輸入與假設!G$50 -> 139.64805
A39: EBITDAR 率（EBITDA 率＋租金÷營收） | B39: % | C39: =輸入與假設!C$93+各期收支!C16/MAX(0.01,C38) -> 0.845075 | D39: =輸入與假設!D$93+各期收支!D16/MAX(0.01,D38) -> 0.790477 | E39: =輸入與假設!E$93+各期收支!E16/MAX(0.01,E38) -> 0.735879 | F39: =輸入與假設!F$93+各期收支!F16/MAX(0.01,F38) -> 0.681281 | G39: =輸入與假設!G$93+各期收支!G16/MAX(0.01,G38) -> 0.626683 | I39: 租金前的 EBITDA 率。EBITDA 已扣租金，而資金模型把租金列在支出端，所以要加回，避免重複扣除
A40: RPO 現金（可支應資本用途） | B40: US$bn | C40: =C36*C39 -> 24.124443 | D40: =D36*D39 -> 56.375823 | E40: =E36*E39 -> 82.112849 | F40: =F36*F39 -> 77.813395 | G40: =G36*G39 -> 69.855727 | I40: ×EBITDAR 率。租金與利息在支出頁單獨列示
A41: 新簽約現金 | B41: US$bn | C41: =C24*(1-輸入與假設!C$48*(1-輸入與假設!C$49))*C39 -> 0 | D41: =D24*(1-輸入與假設!D$48*(1-輸入與假設!D$49))*D39 -> 0 | E41: =E24*(1-輸入與假設!E$48*(1-輸入與假設!E$49))*E39 -> 0 | F41: =F24*(1-輸入與假設!F$48*(1-輸入與假設!F$49))*F39 -> 12.278997 | G41: =G24*(1-輸入與假設!G$48*(1-輸入與假設!G$49))*G39 -> 16.565393 | I41: 同樣扣信用損失、乘 EBITDAR 率
A43: 讀法：FY27（2Q–4Q）與 FY28 瓶頸>0，合約多於機房；FY28 起反轉，收入愈來愈靠『新簽約收入』這一列。
A44: 把『新產能簽約率』調到 0，就能看到只靠期初 RPO 的資金缺口有多大——這是最重要的一個壓力測試。
A46: （E）建設延誤（v0.2）：計費 MW 往後平移；GPU 資本支出與客戶出資照原時程；折舊自投入使用時點起算
A47: 建設延誤月數｜保守 OpenAI 相關 60% | B47: 月 | C47: 6 | I47: company.json → scenarios.delayMonths；依據見該欄 note [Assumed]
A48: 建設延誤月數｜基準 已簽約站點依 Q1 速度 | B48: 月 | C48: 3 | I48: company.json → scenarios.delayMonths；依據見該欄 note [Assumed]
A49: 建設延誤月數｜積極 依公司時程 | B49: 月 | C49: 0 | I49: company.json → scenarios.delayMonths；依據見該欄 note [Assumed]
A50: 建設延誤月數（目前情境） | B50: 月 | C50: =CHOOSE(輸入與假設!$C$5,運營_產能與收入!$C$47,運營_產能與收入!$C$48,運營_產能與收入!$C$49) -> 3 | I50: ＝依『輸入與假設』A 區情境選擇器；0＝不延誤（＝v0.1）
A51: 期末時點（評價日起，年） | B51: 年 | C51: =SUM($C$7:C7) -> 0.75 | D51: =SUM($C$7:D7) -> 1.75 | E51: =SUM($C$7:E7) -> 2.75 | F51: =SUM($C$7:F7) -> 3.75 | G51: =SUM($C$7:G7) -> 4.75 | I51: ＝累計期間長度
A52: 成長型 CapEx 累計（原時程，評價日起） | B52: US$bn | C52: =SUM(輸入與假設!$C$128:C$128) -> 77.59685 | D52: =SUM(輸入與假設!$C$128:D$128) -> 163.61781 | E52: =SUM(輸入與假設!$C$128:E$128) -> 194.81939 | F52: =SUM(輸入與假設!$C$128:F$128) -> 194.81939 | G52: =SUM(輸入與假設!$C$128:G$128) -> 194.81939 | I52: GPU 與網通照原併網時程採購、交貨等電（客戶出資覆蓋比同樣依原時程）
A53: 已投入使用累計（延誤後） | B53: US$bn | C53: =IF($C$50<=0,$C$52,0+($C$52-0)*MAX(0,MIN(1,($C$51-$C$50/12-0)/$C$7))+($D$52-$C$52)*MAX(0,MIN(1,($C$51-$C$50/12-$C$51)/$D$7))+($E$52-$D$52)*MAX(0,MIN(1,($C$51-$C$50/12-$D$51)/$E$7))+($F$52-$E$52)*MAX(0,MIN(1,($C$51-$C$50/12-$E$51)/$F$7))+($G$52-$F$52)*MAX(0,MIN(1,($C$51-$C$50/12-$F$51)/$G$7))) -> 51.731233 | D53: =IF($C$50<=0,$D$52,0+($C$52-0)*MAX(0,MIN(1,($D$51-$C$50/12-0)/$C$7))+($D$52-$C$52)*MAX(0,MIN(1,($D$51-$C$50/12-$C$51)/$D$7))+($E$52-$D$52)*MAX(0,MIN(1,($D$51-$C$50/12-$D$51)/$E$7))+($F$52-$E$52)*MAX(0,MIN(1,($D$51-$C$50/12-$E$51)/$F$7))+($G$52-$F$52)*MAX(0,MIN(1,($D$51-$C$50/12-$F$51)/$G$7))) -> 142.11257 | E53: =IF($C$50<=0,$E$52,0+($C$52-0)*MAX(0,MIN(1,($E$51-$C$50/12-0)/$C$7))+($D$52-$C$52)*MAX(0,MIN(1,($E$51-$C$50/12-$C$51)/$D$7))+($E$52-$D$52)*MAX(0,MIN(1,($E$51-$C$50/12-$D$51)/$E$7))+($F$52-$E$52)*MAX(0,MIN(1,($E$51-$C$50/12-$E$51)/$F$7))+($G$52-$F$52)*MAX(0,MIN(1,($E$51-$C$50/12-$F$51)/$G$7))) -> 187.01899 | F53: =IF($C$50<=0,$F$52,0+($C$52-0)*MAX(0,MIN(1,($F$51-$C$50/12-0)/$C$7))+($D$52-$C$52)*MAX(0,MIN(1,($F$51-$C$50/12-$C$51)/$D$7))+($E$52-$D$52)*MAX(0,MIN(1,($F$51-$C$50/12-$D$51)/$E$7))+($F$52-$E$52)*MAX(0,MIN(1,($F$51-$C$50/12-$E$51)/$F$7))+($G$52-$F$52)*MAX(0,MIN(1,($F$51-$C$50/12-$F$51)/$G$7))) -> 194.81939 | G53: =IF($C$50<=0,$G$52,0+($C$52-0)*MAX(0,MIN(1,($G$51-$C$50/12-0)/$C$7))+($D$52-$C$52)*MAX(0,MIN(1,($G$51-$C$50/12-$C$51)/$D$7))+($E$52-$D$52)*MAX(0,MIN(1,($G$51-$C$50/12-$D$51)/$E$7))+($F$52-$E$52)*MAX(0,MIN(1,($G$51-$C$50/12-$E$51)/$F$7))+($G$52-$F$52)*MAX(0,MIN(1,($G$51-$C$50/12-$F$51)/$G$7))) -> 194.81939 | I53: ＝上列往後平移建設延誤月數（線性內插）；延誤 0 時＝上列
A54: 本期投入使用的成長型 CapEx（折舊基礎） | B54: US$bn | C54: =C53 -> 51.731233 | D54: =D53-C53 -> 90.381334 | E54: =E53-D53 -> 44.906424 | F54: =F53-E53 -> 7.8003949 | G54: =G53-F53 -> 0 | I54: 車隊折舊自投入使用時點起算（『輸入與假設』期初毛 PP&E 與 D&A 引用此列）
A55: 閒置資本（已支出未產生收入，期末） | B55: US$bn | C55: =C52-C53 -> 25.865617 | D55: =D52-D53 -> 21.505239 | E55: =E52-E53 -> 7.8003949 | F55: =F52-F53 -> 0 | G55: =G52-G53 -> 0 | I55: ＝原時程累計 − 已投入使用累計；延誤 0 時為 0。一頁摘要以一句呈現峰值
A56: 未起租租約起租連動比例（delayLink） | B56: % | C56: 0.5 | I56: 未起租租金中此比例的起租時點隨延誤月數後移（開發商交付晚），其餘照原時程（company.json → leases.uncommenced.delayLink）[Assumed]；替代 0／1
A57: 延誤罰則（應計費而未計費營收的 %） | B57: % | C57: 0 | I57: 公司未揭露合約條款：預設 0（不存在／未揭露）；敏感度 5%／10%（company.json → defaults.delayPenalty）[Assumed]
A58: 表外現金租金：全部隨延誤平移（對照） | B58: US$bn | C58: =輸入與假設!$C$26/輸入與假設!$C$28/輸入與假設!$C$29/4*((MIN(MAX(0,輸入與假設!C$118-(輸入與假設!$C$27+運營_產能與收入!$C$50/3)),輸入與假設!$C$28)*(MIN(MAX(0,輸入與假設!C$118-(輸入與假設!$C$27+運營_產能與收入!$C$50/3)),輸入與假設!$C$28)+1)/2+輸入與假設!$C$28*MAX(0,MAX(0,輸入與假設!C$118-(輸入與假設!$C$27+運營_產能與收入!$C$50/3))-輸入與假設!$C$28))-(MIN(MAX(0,0-(輸入與假設!$C$27+運營_產能與收入!$C$50/3)),輸入與假設!$C$28)*(MIN(MAX(0,0-(輸入與假設!$C$27+運營_產能與收入!$C$50/3)),輸入與假設!$C$28)+1)/2+輸入與假設!$C$28*MAX(0,MAX(0,0-(輸入與假設!$C$27+運營_產能與收入!$C$50/3))-輸入與假設!$C$28))) -> 1.1550802 | D58: =輸入與假設!$C$26/輸入與假設!$C$28/輸入與假設!$C$29/4*((MIN(MAX(0,輸入與假設!D$118-(輸入與假設!$C$27+運營_產能與收入!$C$50/3)),輸入與假設!$C$28)*(MIN(MAX(0,輸入與假設!D$118-(輸入與假設!$C$27+運營_產能與收入!$C$50/3)),輸入與假設!$C$28)+1)/2+輸入與假設!$C$28*MAX(0,MAX(0,輸入與假設!D$118-(輸入與假設!$C$27+運營_產能與收入!$C$50/3))-輸入與假設!$C$28))-(MIN(MAX(0,輸入與假設!C$118-(輸入與假設!$C$27+運營_產能與收入!$C$50/3)),輸入與假設!$C$28)*(MIN(MAX(0,輸入與假設!C$118-(輸入與假設!$C$27+運營_產能與收入!$C$50/3)),輸入與假設!$C$28)+1)/2+輸入與假設!$C$28*MAX(0,MAX(0,輸入與假設!C$118-(輸入與假設!$C$27+運營_產能與收入!$C$50/3))-輸入與假設!$C$28))) -> 6.9304813 | E58: =輸入與假設!$C$26/輸入與假設!$C$28/輸入與假設!$C$29/4*((MIN(MAX(0,輸入與假設!E$118-(輸入與假設!$C$27+運營_產能與收入!$C$50/3)),輸入與假設!$C$28)*(MIN(MAX(0,輸入與假設!E$118-(輸入與假設!$C$27+運營_產能與收入!$C$50/3)),輸入與假設!$C$28)+1)/2+輸入與假設!$C$28*MAX(0,MAX(0,輸入與假設!E$118-(輸入與假設!$C$27+運營_產能與收入!$C$50/3))-輸入與假設!$C$28))-(MIN(MAX(0,輸入與假設!D$118-(輸入與假設!$C$27+運營_產能與收入!$C$50/3)),輸入與假設!$C$28)*(MIN(MAX(0,輸入與假設!D$118-(輸入與假設!$C$27+運營_產能與收入!$C$50/3)),輸入與假設!$C$28)+1)/2+輸入與假設!$C$28*MAX(0,MAX(0,輸入與假設!D$118-(輸入與假設!$C$27+運營_產能與收入!$C$50/3))-輸入與假設!$C$28))) -> 13.090909 | F58: =輸入與假設!$C$26/輸入與假設!$C$28/輸入與假設!$C$29/4*((MIN(MAX(0,輸入與假設!F$118-(輸入與假設!$C$27+運營_產能與收入!$C$50/3)),輸入與假設!$C$28)*(MIN(MAX(0,輸入與假設!F$118-(輸入與假設!$C$27+運營_產能與收入!$C$50/3)),輸入與假設!$C$28)+1)/2+輸入與假設!$C$28*MAX(0,MAX(0,輸入與假設!F$118-(輸入與假設!$C$27+運營_產能與收入!$C$50/3))-輸入與假設!$C$28))-(MIN(MAX(0,輸入與假設!E$118-(輸入與假設!$C$27+運營_產能與收入!$C$50/3)),輸入與假設!$C$28)*(MIN(MAX(0,輸入與假設!E$118-(輸入與假設!$C$27+運營_產能與收入!$C$50/3)),輸入與假設!$C$28)+1)/2+輸入與假設!$C$28*MAX(0,MAX(0,輸入與假設!E$118-(輸入與假設!$C$27+運營_產能與收入!$C$50/3))-輸入與假設!$C$28))) -> 16.941176 | G58: =輸入與假設!$C$26/輸入與假設!$C$28/輸入與假設!$C$29/4*((MIN(MAX(0,輸入與假設!G$118-(輸入與假設!$C$27+運營_產能與收入!$C$50/3)),輸入與假設!$C$28)*(MIN(MAX(0,輸入與假設!G$118-(輸入與假設!$C$27+運營_產能與收入!$C$50/3)),輸入與假設!$C$28)+1)/2+輸入與假設!$C$28*MAX(0,MAX(0,輸入與假設!G$118-(輸入與假設!$C$27+運營_產能與收入!$C$50/3))-輸入與假設!$C$28))-(MIN(MAX(0,輸入與假設!F$118-(輸入與假設!$C$27+運營_產能與收入!$C$50/3)),輸入與假設!$C$28)*(MIN(MAX(0,輸入與假設!F$118-(輸入與假設!$C$27+運營_產能與收入!$C$50/3)),輸入與假設!$C$28)+1)/2+輸入與假設!$C$28*MAX(0,MAX(0,輸入與假設!F$118-(輸入與假設!$C$27+運營_產能與收入!$C$50/3))-輸入與假設!$C$28))) -> 16.941176 | I58: ＝未起租排程的起算季延後 延誤月數 ÷ 3 季（其餘同『輸入與假設』表外現金租金）
A59: 表外現金租金（未起租，延誤連動後） | B59: US$bn | C59: =IF(OR(運營_產能與收入!$C$50<=0,運營_產能與收入!$C$56<=0),輸入與假設!C$119,(1-運營_產能與收入!$C$56)*輸入與假設!C$119+運營_產能與收入!$C$56*C58) -> 1.7326203 | D59: =IF(OR(運營_產能與收入!$C$50<=0,運營_產能與收入!$C$56<=0),輸入與假設!D$119,(1-運營_產能與收入!$C$56)*輸入與假設!D$119+運營_產能與收入!$C$56*D58) -> 7.7005348 | E59: =IF(OR(運營_產能與收入!$C$50<=0,運營_產能與收入!$C$56<=0),輸入與假設!E$119,(1-運營_產能與收入!$C$56)*輸入與假設!E$119+運營_產能與收入!$C$56*E58) -> 13.860963 | F59: =IF(OR(運營_產能與收入!$C$50<=0,運營_產能與收入!$C$56<=0),輸入與假設!F$119,(1-運營_產能與收入!$C$56)*輸入與假設!F$119+運營_產能與收入!$C$56*F58) -> 16.941176 | G59: =IF(OR(運營_產能與收入!$C$50<=0,運營_產能與收入!$C$56<=0),輸入與假設!G$119,(1-運營_產能與收入!$C$56)*輸入與假設!G$119+運營_產能與收入!$C$56*G58) -> 16.941176 | I59: ＝(1 − 連動比例)× 原排程＋連動比例 × 平移後排程；延誤 0 時＝原排程（『各期收支』租金引用此列）
A60: 容量上限（未延誤，對照） | B60: US$bn | C60: =IF(輸入與假設!$C$37=1,(輸入與假設!$C$36+C10)/2,C10)*輸入與假設!C$46*輸入與假設!$C$39*輸入與假設!C$45*C7 -> 31.848525 | D60: =IF(輸入與假設!$C$37=1,(C10+D10)/2,D10)*輸入與假設!D$46*輸入與假設!$C$39*輸入與假設!D$45*D7 -> 82.8501 | E60: =IF(輸入與假設!$C$37=1,(D10+E10)/2,E10)*輸入與假設!E$46*輸入與假設!$C$39*輸入與假設!E$45*E7 -> 122.2872 | F60: =IF(輸入與假設!$C$37=1,(E10+F10)/2,F10)*輸入與假設!F$46*輸入與假設!$C$39*輸入與假設!F$45*F7 -> 137.3382 | G60: =IF(輸入與假設!$C$37=1,(F10+G10)/2,G10)*輸入與假設!G$46*輸入與假設!$C$39*輸入與假設!G$45*G7 -> 140.418 | I60: ＝未延誤的平均可計費 MW × 每 MW 年收入 × 利用率 × 期間長度
A61: 應計費而未計費營收（延誤造成） | B61: US$bn | C61: =IF(運營_產能與收入!$C$50<=0,0,MAX(0,C60-C16)) -> 3.229875 | D61: =IF(運營_產能與收入!$C$50<=0,0,MAX(0,D60-D16)) -> 11.172975 | E61: =IF(運營_產能與收入!$C$50<=0,0,MAX(0,E60-E16)) -> 9.859275 | F61: =IF(運營_產能與收入!$C$50<=0,0,MAX(0,F60-F16)) -> 3.76275 | G61: =IF(運營_產能與收入!$C$50<=0,0,MAX(0,G60-G16)) -> 0.76995 | I61: ＝未延誤容量上限 − 延誤後容量上限
A62: 延誤罰則（營業費用） | B62: US$bn | C62: =運營_產能與收入!$C$57*C61 -> 0 | D62: =運營_產能與收入!$C$57*D61 -> 0 | E62: =運營_產能與收入!$C$57*E61 -> 0 | F62: =運營_產能與收入!$C$57*F61 -> 0 | G62: =運營_產能與收入!$C$57*G61 -> 0 | I62: ＝罰則比例 × 應計費而未計費營收；扣 EBITDA、營運來源、稅基與債務上限。客戶預付不因延誤退還（已知限制）

Sheet 運營_站點
A1: 站點租賃 — 公司揭露 vs 季報總額（檢驗租金路徑用）
A2: 季報不揭露逐站租金；下表為具名站點（company.json → defaults.sites），有租約金額者用來檢驗『每 MW 年租金』與模型租金路徑是否一致
A4: 站點 | B4: 營運方 | C4: 契約 MW | D4: 已驗收 MW | E4: 合約總值 $bn | F4: 年期 | G4: 年租金 $bn | H4: 每 MW 年租金 $m | I4: 時程 | J4: 季報對應 | K4: 說明
A5: Abilene, TX（Stargate 一期） | B5: Crusoe／Blue Owl 開發、Oracle 承租（OpenAI） | C5: 1000 | D5: 515 | E5: 未揭露 | F5: 未揭露 | I5: 2026–2027 | J5: — | K5: 法說：已交付 618 MW＝75%（口徑不明，÷1.2 換 IT 約 515）；Epoch 估設施 1.2 GW [Interested-party／Derived]
A6: Shackelford County, TX（Frontier） | B6: Vantage 開發、Oracle 承租 | C6: 1667 | D6: 0 | E6: 未揭露 | F6: 未揭露 | I6: 2027 起 | J6: — | K6: Epoch 估設施 2.0 GW（÷1.2 約 1,667 MW-IT）；開發商融資 38B（含 Port Washington）[Derived]
A7: Doña Ana County, NM（Project Jupiter） | B7: BorderPlex／STACK 開發、Oracle 承租 | C7: 1833 | D7: 0 | E7: 未揭露 | F7: 未揭露 | I7: 延後 | J7: — | K7: Epoch 估設施 2.2 GW；2026-09-24 Oracle 發不可抗力通知（能源延誤）[Interested-party]
A8: Port Washington, WI | B8: Vantage 開發、Oracle 承租 | C8: 1083 | D8: 0 | E8: 未揭露 | F8: 未揭露 | I8: 2027 起 | J8: — | K8: Epoch 估設施 1.3 GW [Derived]
A9: Saline Township, MI（The Barn） | B9: Related Digital 開發、Oracle 承租 | C9: 1167 | D9: 0 | E9: 未揭露 | F9: 未揭露 | I9: 2027 起 | J9: — | K9: Epoch 估設施 1.4 GW；開發商融資 16B [Derived]
A10: 具名站點合計 | C10: =SUM(C5:C9) -> 6750 | D10: =SUM(D5:D9) -> 515 | E10: =SUM(E5:E9) -> 0 | G10: =SUM(G5:G9) -> 0 | H10: =IF(I10>0,G10/I10*1000,0) -> 0 | I10: =SUMPRODUCT(ISNUMBER(G5:G9)*C5:C9) -> 0 | K10: 加權每 MW 年租金＝具名站點的市場基準（I 欄＝有租約金額站點的契約 MW；沒有時為 0，不適用）
A12: 對帳：具名站點 vs 季報租賃承諾總額
A13: 季報在帳租賃（未折現，已起租） | E13: 63.245 | K13: company.json → leases.facts.onBal
A14: 季報未起租租賃（未折現） | E14: 288 | K14: company.json → leases.facts.notCommenced
A15: 季報單站按造價計租上限 | E15: 0 | K15: company.json → leases.facts.singleCap（無則 0）
A16: 季報已揭露租賃承諾合計 | E16: =SUM(E13:E15) -> 351.245 | K16: 未折現金額
A17: 減：具名站點合約總值 | E17: =-E10 -> 0
A18: ＝ 未具名站點（殘差） | E18: =E16+E17 -> 351.245 | K18: 未具名站點；公司不揭露逐站租金，殘差大是必然
A19: 殘差占季報總額 | E19: =IF(E16<>0,E18/E16,0) -> 1
A21: 檢驗：模型租金路徑 ÷ 在役 MW vs 市場基準
A22: 項目 | B22: 單位 | C22: FY27 | D22: FY28 | E22: FY29 | F22: FY30 | G22: FY31
A23: 模型租金（在帳＋表外） | B23: US$bn | C23: =各期收支!C16 -> 5.5716203 | D23: =各期收支!D16 -> 12.687535 | E23: =各期收支!E16 -> 18.880963 | F23: =各期收支!F16 -> 21.997176 | G23: =各期收支!G16 -> 22.001176
A24: 平均在役 MW（已連網） | B24: MW | C24: =(輸入與假設!C$124+輸入與假設!C$43)/2 -> 3251.5 | D24: =(輸入與假設!D$124+輸入與假設!D$43)/2 -> 6084.5 | E24: =(輸入與假設!E$124+輸入與假設!E$43)/2 -> 8139.5 | F24: =(輸入與假設!F$124+輸入與假設!F$43)/2 -> 8778 | G24: =(輸入與假設!G$124+輸入與假設!G$43)/2 -> 8778
A25: 模型期長度（年） | B25: 年 | C25: =輸入與假設!C$41 -> 0.75 | D25: =輸入與假設!D$41 -> 1 | E25: =輸入與假設!E$41 -> 1 | F25: =輸入與假設!F$41 -> 1 | G25: =輸入與假設!G$41 -> 1
A26: 模型每 MW 年租金 | B26: US$m/MW | C26: =C23/C25/C24*1000 -> 2.2847385 | D26: =D23/D25/D24*1000 -> 2.0852222 | E26: =E23/E25/E24*1000 -> 2.3196711 | F26: =F23/F25/F24*1000 -> 2.505944 | G26: =G23/G25/G24*1000 -> 2.5063997 | K26: FY27 欄只含第 2–4 季租金、MW 取全期平均，略有低估
A27: 第三方租賃占比 | C27: 1 | K27: 其餘為自建，成本走 CapEx（company.json → leases.facts.share）[Assumed]
A28: 基準租金（MW×市場基準×占比） | B28: US$bn | C28: =C24*運營_站點!$H$10/1000*$C$27*C25 -> 0 | D28: =D24*運營_站點!$H$10/1000*$C$27*D25 -> 0 | E28: =E24*運營_站點!$H$10/1000*$C$27*E25 -> 0 | F28: =F24*運營_站點!$H$10/1000*$C$27*F25 -> 0 | G28: =G24*運營_站點!$H$10/1000*$C$27*G25 -> 0 | K28: 具名站點有租約金額時才有意義；否則為 0
A29: 差額（基準 − 模型） | B29: US$bn | C29: =C28-C23 -> -5.5716203 | D29: =D28-D23 -> -12.687535 | E29: =E28-E23 -> -18.880963 | F29: =F28-F23 -> -21.997176 | G29: =G28-G23 -> -22.001176 | K29: 正值＝模型租金可能低估的金額
A30: 五期差額合計 | C30: =SUM(C29:G29) -> -81.138471

Sheet 資產負債_既有債務
A1: 債務明細 — 季報（2026-08-31）逐筆＋存量利息推導
A2: 有效利率為現金票息口徑（可轉債＝票息 ÷ 到期累積倍數，本金以到期累積本金計）。本頁算出的存量利息連回『輸入』頁，再進入支出與資金頁
A4: 工具 | B4: 類別 | C4: 到期 | D4: 有效利率 | E4: 8/31 本金 | F4: 年化利息 | I4: 備註
A5: 2.80% 優先票據 2027-04 | B5: 無擔保 | C5: 2027-04 | D5: 0.028 | E5: 2.25 | F5: =D5*E5 -> 0.063 | I5: 10-K 附註 6（發行 April 2020）[Verified]
A6: 3.25% 優先票據 2027-11 | B6: 無擔保 | C6: 2027-11 | D6: 0.0325 | E6: 2.75 | F6: =D6*E6 -> 0.089375 | I6: 10-K 附註 6（發行 November 2017）[Verified]
A7: 2.30% 優先票據 2028-03 | B7: 無擔保 | C7: 2028-03 | D7: 0.023 | E7: 2 | F7: =D7*E7 -> 0.046 | I7: 10-K 附註 6（發行 March 2021）[Verified]
A8: 4.50% 優先票據 2028-05 | B8: 無擔保 | C8: 2028-05 | D8: 0.045 | E8: 0.75 | F8: =D8*E8 -> 0.03375 | I8: 10-K 附註 6（發行 February 2023）[Verified]
A9: 4.80% 優先票據 2028-08 | B9: 無擔保 | C9: 2028-08 | D9: 0.048 | E9: 1.5 | F9: =D9*E9 -> 0.072 | I9: 10-K 附註 6（發行 February 2025）[Verified]
A10: 4.55% 優先票據 2029-02 | B10: 無擔保 | C10: 2029-02 | D10: 0.0455 | E10: 3 | F10: =D10*E10 -> 0.1365 | I10: 10-K 附註 6（發行 February 2026）[Verified]
A11: 4.20% 優先票據 2029-09 | B11: 無擔保 | C11: 2029-09 | D11: 0.042 | E11: 1.5 | F11: =D11*E11 -> 0.063 | I11: 10-K 附註 6（發行 September 2024）[Verified]
A12: 6.15% 優先票據 2029-11 | B12: 無擔保 | C12: 2029-11 | D12: 0.0615 | E12: 1.25 | F12: =D12*E12 -> 0.076875 | I12: 10-K 附註 6（發行 November 2022）[Verified]
A13: 2.95% 優先票據 2030-04 | B13: 無擔保 | C13: 2030-04 | D13: 0.0295 | E13: 3.25 | F13: =D13*E13 -> 0.095875 | I13: 10-K 附註 6（發行 April 2020）[Verified]
A14: 4.65% 優先票據 2030-05 | B14: 無擔保 | C14: 2030-05 | D14: 0.0465 | E14: 0.75 | F14: =D14*E14 -> 0.034875 | I14: 10-K 附註 6（發行 February 2023）[Verified]
A15: 3.25% 優先票據 2030-05 | B15: 無擔保 | C15: 2030-05 | D15: 0.0325 | E15: 0.5 | F15: =D15*E15 -> 0.01625 | I15: 10-K 附註 6（發行 May 2015）[Verified]
A16: 4.45% 優先票據 2030-09 | B16: 無擔保 | C16: 2030-09 | D16: 0.0445 | E16: 3 | F16: =D16*E16 -> 0.1335 | I16: 10-K 附註 6（發行 September 2025）[Verified]
... A61: 商業本票 | B61: 無擔保 | C61: 2026-11 | D61: 0.0435 | E61: 0.337 | F61: =D61*E61 -> 0.0146595 | I61: 帳面總借款 − 附註 2 不含商本借款推得 [Derived]
A62: 合計（8/31） | E62: =SUM(E5:E61) -> 125.904 | F62: =SUM(F5:F61) -> 6.0449478 | I62: 應等於最新季報本金合計 125.904（company.json → latestQuarter.debtPrincipal）
A63: 加權有效利率 | D63: =F62/E62 -> 0.048012357 | I63: ＝年化利息 ÷ 本金（company.json → debt.instruments 的有效利率）
A65: 評價日後新發可轉債 | D65: 0 | E65: 0 | F65: =D65*E65 -> 0 | I65: company.json → debt.convertible（期後新發；不在五期還本表內，只計利息）
A67: 可轉債逐檔（若轉換法：有效轉換價 < 判斷價 → 視為轉股，不計利息與還本）
A68: 可轉債 | B68: 到期 | C68: 票息 | D68: 原始本金 | E68: 到期累積倍數 | F68: 轉換價 | G68: 到期所屬模型期 | H68: 強制轉換（1＝是） | I68: 備註
A69: 6.50% Series D 強制轉換特別股（2026-02） | B69: 2029-01 | C69: 0.065 | D69: 5 | E69: 1 | F69: 160.06 | G69: 2 | H69: 1 | I69: 清算價 $5B（5,000 萬股 × $100）；2029-01-15 強制轉換為普通股，每股特別股轉 499.8126–624.7657 股（2,499–3,124 萬股）；一律轉股，取稀釋最大 31.238m 股（轉換價下限 $160.06）[Interested-party 8-K 2026-02]；6.50% 股利列於 defaults.dividend.preferred；權益，不列債務本金
I70: 到期所屬模型期：0＝首期 … 4＝末期、5＝模型期後（建置時依期末日推算）
A72: 可轉債（推導） | C72: 到期本金 | D72: 若轉換股數 | E72: 有效轉換價 | F72: 融資分類 | G72: 評價第一輪 | H72: 評價第二輪 | I72: 說明
A73: =A69 -> 6.50% Series D 強制轉換特別股（2026-02） | C73: =D69*E69 -> 5 | D73: =D69/F69 -> 0.031238286 | E73: =F69*E69 -> 160.06 | F73: =IF(OR(H69=1,E73<輸入與假設!$C$152),1,0) -> 1 | G73: =IF(OR(H69=1,E73<輸入與假設!$C$175),1,0) -> 1 | H73: =IF(OR(H69=1,E73<評價_DCF與目標價!$C$66),1,0) -> 1
A74: 合計 | C74: =SUM(C73:C73) -> 5 | D74: =SUM(D73:D73) -> 0.031238286 | I74: 分類 1＝轉股（若轉換法）、0＝債務。強制轉換者一律為 1。融資分類判斷價＝股權發行價；評價第一輪＝現價；第二輪＝MIN(現價, 第一輪加權目標價)
A76: 存量利息推導（本金依季報到期表遞減）
A77: 項目 | B77: 單位 | C77: FY27 | D77: FY28 | E77: FY29 | F77: FY30 | G77: FY31 | I77: 公式／來源說明
A78: 期初本金 | B78: US$bn | C78: =E62 -> 125.904 | D78: =C80 -> 122.897 | E78: =D80 -> 112.75 | F78: =E80 -> 107.25 | G78: =F80 -> 100 | I78: FY27 期初為 8/31 本金（模型期起點）
A79: 排程還本 | B79: US$bn | C79: =輸入與假設!C$170 -> 3.007 | D79: =輸入與假設!D$170 -> 10.147 | E79: =輸入與假設!E$170 -> 5.5 | F79: =輸入與假設!F$170 -> 7.25 | G79: =輸入與假設!G$170 -> 9.75 | I79: 季報到期表
A80: 期末本金 | B80: US$bn | C80: =C78-C79 -> 122.897 | D80: =D78-D79 -> 112.75 | E80: =E78-E79 -> 107.25 | F80: =F78-F79 -> 100 | G80: =G78-G79 -> 90.25
A81: 平均本金 | B81: US$bn | C81: =(C78+C80)/2 -> 124.4005 | D81: =(D78+D80)/2 -> 117.8235 | E81: =(E78+E80)/2 -> 110 | F81: =(F78+F80)/2 -> 103.625 | G81: =(G78+G80)/2 -> 95.125
A82: 存量債務利息 | B82: US$bn | C82: =C81*資產負債_既有債務!$D$63*輸入與假設!C$41 -> 4.4795709 | D82: =D81*資產負債_既有債務!$D$63*輸入與假設!D$41 -> 5.6569839 | E82: =E81*資產負債_既有債務!$D$63*輸入與假設!E$41 -> 5.2813593 | F82: =F81*資產負債_既有債務!$D$63*輸入與假設!F$41 -> 4.9752805 | G82: =G81*資產負債_既有債務!$D$63*輸入與假設!G$41 -> 4.5671755 | I82: ＝平均本金×加權有效利率×期間長度。限制：假設利率組合不變；可轉債折價攤銷（非現金）不計
A83: 期後新發可轉債利息 | B83: US$bn | C83: =資產負債_既有債務!$F$65*輸入與假設!C$41 -> 0 | D83: =資產負債_既有債務!$F$65*輸入與假設!D$41 -> 0 | E83: =資產負債_既有債務!$F$65*輸入與假設!E$41 -> 0 | F83: =資產負債_既有債務!$F$65*輸入與假設!F$41 -> 0 | G83: =資產負債_既有債務!$F$65*輸入與假設!G$41 -> 0
A84: 可轉債到期還本（債務處理） | B84: US$bn | C84: =IF(輸入與假設!$C$144=1,SUMPRODUCT((1-資產負債_既有債務!$F$73:$F$73)*資產負債_既有債務!$C$73:$C$73*(資產負債_既有債務!$G$69:$G$69=0)),0) -> 0 | D84: =IF(輸入與假設!$C$144=1,SUMPRODUCT((1-資產負債_既有債務!$F$73:$F$73)*資產負債_既有債務!$C$73:$C$73*(資產負債_既有債務!$G$69:$G$69=1)),0) -> 0 | E84: =IF(輸入與假設!$C$144=1,SUMPRODUCT((1-資產負債_既有債務!$F$73:$F$73)*資產負債_既有債務!$C$73:$C$73*(資產負債_既有債務!$G$69:$G$69=2)),0) -> 0 | F84: =IF(輸入與假設!$C$144=1,SUMPRODUCT((1-資產負債_既有債務!$F$73:$F$73)*資產負債_既有債務!$C$73:$C$73*(資產負債_既有債務!$G$69:$G$69=3)),0) -> 0 | G84: =IF(輸入與假設!$C$144=1,SUMPRODUCT((1-資產負債_既有債務!$F$73:$F$73)*資產負債_既有債務!$C$73:$C$73*(資產負債_既有債務!$G$69:$G$69=4)),0) -> 0 | I84: 融資分類為債務的可轉債，到期當期以到期累積本金現金還本
A85: 可轉債期末餘額（債務處理） | B85: US$bn | C85: =IF(輸入與假設!$C$144=1,SUMPRODUCT((1-資產負債_既有債務!$F$73:$F$73)*資產負債_既有債務!$C$73:$C$73*(資產負債_既有債務!$G$69:$G$69>0)),SUMPRODUCT((1-資產負債_既有債務!$F$73:$F$73)*資產負債_既有債務!$C$73:$C$73)) -> 0 | D85: =IF(輸入與假設!$C$144=1,SUMPRODUCT((1-資產負債_既有債務!$F$73:$F$73)*資產負債_既有債務!$C$73:$C$73*(資產負債_既有債務!$G$69:$G$69>1)),SUMPRODUCT((1-資產負債_既有債務!$F$73:$F$73)*資產負債_既有債務!$C$73:$C$73)) -> 0 | E85: =IF(輸入與假設!$C$144=1,SUMPRODUCT((1-資產負債_既有債務!$F$73:$F$73)*資產負債_既有債務!$C$73:$C$73*(資產負債_既有債務!$G$69:$G$69>2)),SUMPRODUCT((1-資產負債_既有債務!$F$73:$F$73)*資產負債_既有債務!$C$73:$C$73)) -> 0 | F85: =IF(輸入與假設!$C$144=1,SUMPRODUCT((1-資產負債_既有債務!$F$73:$F$73)*資產負債_既有債務!$C$73:$C$73*(資產負債_既有債務!$G$69:$G$69>3)),SUMPRODUCT((1-資產負債_既有債務!$F$73:$F$73)*資產負債_既有債務!$C$73:$C$73)) -> 0 | G85: =IF(輸入與假設!$C$144=1,SUMPRODUCT((1-資產負債_既有債務!$F$73:$F$73)*資產負債_既有債務!$C$73:$C$73*(資產負債_既有債務!$G$69:$G$69>4)),SUMPRODUCT((1-資產負債_既有債務!$F$73:$F$73)*資產負債_既有債務!$C$73:$C$73)) -> 0 | I85: 到期累積本金；關閉攤還時維持全額
A86: 可轉債票息（債務處理） | B86: US$bn | C86: =IF(輸入與假設!$C$144=1,SUMPRODUCT((1-資產負債_既有債務!$F$73:$F$73)*資產負債_既有債務!$D$69:$D$69*資產負債_既有債務!$C$69:$C$69*((資產負債_既有債務!$G$69:$G$69>0)+0.5*(資產負債_既有債務!$G$69:$G$69=0))),SUMPRODUCT((1-資產負債_既有債務!$F$73:$F$73)*資產負債_既有債務!$D$69:$D$69*資產負債_既有債務!$C$69:$C$69))*輸入與假設!C$41 -> 0 | D86: =IF(輸入與假設!$C$144=1,SUMPRODUCT((1-資產負債_既有債務!$F$73:$F$73)*資產負債_既有債務!$D$69:$D$69*資產負債_既有債務!$C$69:$C$69*((資產負債_既有債務!$G$69:$G$69>1)+0.5*(資產負債_既有債務!$G$69:$G$69=1))),SUMPRODUCT((1-資產負債_既有債務!$F$73:$F$73)*資產負債_既有債務!$D$69:$D$69*資產負債_既有債務!$C$69:$C$69))*輸入與假設!D$41 -> 0 | E86: =IF(輸入與假設!$C$144=1,SUMPRODUCT((1-資產負債_既有債務!$F$73:$F$73)*資產負債_既有債務!$D$69:$D$69*資產負債_既有債務!$C$69:$C$69*((資產負債_既有債務!$G$69:$G$69>2)+0.5*(資產負債_既有債務!$G$69:$G$69=2))),SUMPRODUCT((1-資產負債_既有債務!$F$73:$F$73)*資產負債_既有債務!$D$69:$D$69*資產負債_既有債務!$C$69:$C$69))*輸入與假設!E$41 -> 0 | F86: =IF(輸入與假設!$C$144=1,SUMPRODUCT((1-資產負債_既有債務!$F$73:$F$73)*資產負債_既有債務!$D$69:$D$69*資產負債_既有債務!$C$69:$C$69*((資產負債_既有債務!$G$69:$G$69>3)+0.5*(資產負債_既有債務!$G$69:$G$69=3))),SUMPRODUCT((1-資產負債_既有債務!$F$73:$F$73)*資產負債_既有債務!$D$69:$D$69*資產負債_既有債務!$C$69:$C$69))*輸入與假設!F$41 -> 0 | G86: =IF(輸入與假設!$C$144=1,SUMPRODUCT((1-資產負債_既有債務!$F$73:$F$73)*資產負債_既有債務!$D$69:$D$69*資產負債_既有債務!$C$69:$C$69*((資產負債_既有債務!$G$69:$G$69>4)+0.5*(資產負債_既有債務!$G$69:$G$69=4))),SUMPRODUCT((1-資產負債_既有債務!$F$73:$F$73)*資產負債_既有債務!$D$69:$D$69*資產負債_既有債務!$C$69:$C$69))*輸入與假設!G$41 -> 0 | I86: ＝原始本金 × 票息 × 期間長度；到期當期計半期
A87: FY26 新增借款利息校準 | B87: US$bn | C87: =0 -> 0 | D87: =0 -> 0 | E87: =0 -> 0 | F87: =0 -> 0 | G87: =0 -> 0 | I87: 讓首期模型利息對上公司季度利息指引的校準值（company.json → defaults.intCal）；無指引時為 0
A88: 存量利息合計（連回輸入頁） | B88: US$bn | C88: =C82+C83+C86+C87 -> 4.4795709 | D88: =D82+D83+D86+D87 -> 5.6569839 | E88: =E82+E83+E86+E87 -> 5.2813593 | F88: =F82+F83+F86+F87 -> 4.9752805 | G88: =G82+G83+G86+G87 -> 4.5671755 | I88: ＝存量債務利息＋期後新發可轉債利息＋可轉債票息＋首期校準

Sheet 資產負債_新債與新股
A1: 新債與新股（類資產負債表：現金、債務、股本、槓桿）
A2: 全部為連結公式。FY27 欄的現金自 2026-08-31 起算（模型期），與 HTML『資產與負債 → 新債與新股』同口徑
A4: 項目 | B4: 單位 | C4: FY27 | D4: FY28 | E4: FY29 | F4: FY30 | G4: FY31 | I4: 公式／來源說明
A5: 現金
A6: 期初現金 | B6: US$bn | C6: =輸入與假設!$C$139 -> 36.369 | D6: =各期收支!C52 -> 10 | E6: =各期收支!D52 -> 10 | F6: =各期收支!E52 -> 42.038145 | G6: =各期收支!F52 -> 60.179667 | I6: FY27＝8/31 現金（模型期起點）
A7: 營運收支淨額（含期後股權／可轉債，不含瀑布） | B7: US$bn | C7: =各期收支!C95-輸入與假設!$C$139 -> -37.083379 | D7: =各期收支!D95-各期收支!C95 -> -27.767281 | E7: =各期收支!E95-各期收支!D95 -> 34.437506 | F7: =各期收支!F95-各期收支!E95 -> 20.540883 | G7: =各期收支!G95-各期收支!F95 -> 14.716395 | I7: ＝融資前累積現金的當期變動；負值即當期外部資金需求
A8: ＋ 瀑布：新債（額度＋資產層） | B8: US$bn | C8: =各期收支!C78 -> 11.201651 | D8: =各期收支!D78 -> 30.166642 | E8: =各期收支!E78 -> 0 | F8: =各期收支!F78 -> 0 | G8: =各期收支!G78 -> 0
A9: ＋ 瀑布：可轉債 | B9: US$bn | C9: =各期收支!C81 -> 0 | D9: =各期收支!D81 -> 0 | E9: =各期收支!E81 -> 0 | F9: =各期收支!F81 -> 0 | G9: =各期收支!G81 -> 0
A10: ＋ 瀑布：高息債 | B10: US$bn | C10: =各期收支!C85 -> 0 | D10: =各期收支!D85 -> 0 | E10: =各期收支!E85 -> 0 | F10: =各期收支!F85 -> 0 | G10: =各期收支!G85 -> 0
A11: ＋ 瀑布：股權募資 | B11: US$bn | C11: =各期收支!C84 -> 0 | D11: =各期收支!D84 -> 0 | E11: =各期收支!E84 -> 0 | F11: =各期收支!F84 -> 0 | G11: =各期收支!G84 -> 0
A12: − 新融資利息（新債＋可轉債＋高息債） | B12: US$bn | C12: =-各期收支!C86 -> -0.48727183 | D12: =-各期收支!D86 -> -2.399361 | E12: =-各期收支!E86 -> -2.399361 | F12: =-各期收支!F86 -> -2.399361 | G12: =-各期收支!G86 -> -2.399361
A13: 期末現金 | B13: US$bn | C13: =SUM(C6:C12) -> 10 | D13: =SUM(D6:D12) -> 10 | E13: =SUM(E6:E12) -> 42.038145 | F13: =SUM(F6:F12) -> 60.179667 | G13: =SUM(G6:G12) -> 72.496702 | I13: 應等於『各期收支』期末累積現金（見下列驗算）
A14: 驗算：與各期收支期末現金差異 | B14: US$bn | C14: =C13-各期收支!C52 -> 0 | D14: =D13-各期收支!D52 -> 0 | E14: =E13-各期收支!E52 -> 0 | F14: =F13-各期收支!F52 -> 0 | G14: =G13-各期收支!G52 -> 0 | I14: 應為 0
A15: 債務
A16: 既有債務期初（季報本金） | B16: US$bn | C16: =資產負債_既有債務!$E$62+SUMPRODUCT((1-資產負債_既有債務!$F$73:$F$73)*資產負債_既有債務!$C$73:$C$73) -> 125.904 | D16: =C18 -> 122.897 | E16: =D18 -> 112.75 | F16: =E18 -> 107.25 | G16: =F18 -> 100 | I16: FY27＝其他借款＋債務處理可轉債到期本金（轉股處理者不列）
A17: − 排程還本（模型期） | B17: US$bn | C17: =-IF(輸入與假設!$C$144=1,輸入與假設!C$170,0)-資產負債_既有債務!C84 -> -3.007 | D17: =-IF(輸入與假設!$C$144=1,輸入與假設!D$170,0)-資產負債_既有債務!D84 -> -10.147 | E17: =-IF(輸入與假設!$C$144=1,輸入與假設!E$170,0)-資產負債_既有債務!E84 -> -5.5 | F17: =-IF(輸入與假設!$C$144=1,輸入與假設!F$170,0)-資產負債_既有債務!F84 -> -7.25 | G17: =-IF(輸入與假設!$C$144=1,輸入與假設!G$170,0)-資產負債_既有債務!G84 -> -9.75
A18: 既有債務期末 | B18: US$bn | C18: =各期收支!C74-0 -> 122.897 | D18: =各期收支!D74-0 -> 112.75 | E18: =各期收支!E74-0 -> 107.25 | F18: =各期收支!F74-0 -> 100 | G18: =各期收支!G74-0 -> 90.25 | I18: ＝依到期表遞減（關閉攤還時維持期初）
A19: ＋ 期後新發可轉債 | B19: US$bn | C19: =0 -> 0 | D19: =0 -> 0 | E19: =0 -> 0 | F19: =0 -> 0 | G19: =0 -> 0
A20: ＋ 瀑布新債餘額 | B20: US$bn | C20: =各期收支!C90 -> 11.201651 | D20: =各期收支!D90 -> 41.368293 | E20: =各期收支!E90 -> 41.368293 | F20: =各期收支!F90 -> 41.368293 | G20: =各期收支!G90 -> 41.368293
A21: ＋ 瀑布可轉債餘額 | B21: US$bn | C21: =各期收支!C93 -> 0 | D21: =各期收支!D93 -> 0 | E21: =各期收支!E93 -> 0 | F21: =各期收支!F93 -> 0 | G21: =各期收支!G93 -> 0
A22: ＋ 高息債餘額 | B22: US$bn | C22: =各期收支!C92 -> 0 | D22: =各期收支!D92 -> 0 | E22: =各期收支!E92 -> 0 | F22: =各期收支!F92 -> 0 | G22: =各期收支!G92 -> 0
A23: 總債務 | B23: US$bn | C23: =SUM(C18:C22) -> 134.09865 | D23: =SUM(D18:D22) -> 154.11829 | E23: =SUM(E18:E22) -> 148.61829 | F23: =SUM(F18:F22) -> 141.36829 | G23: =SUM(G18:G22) -> 131.61829 | I23: 應等於『各期收支』期末總債務
A24: 淨負債（總債務 − 期末現金） | B24: US$bn | C24: =C23-C13 -> 124.09865 | D24: =D23-D13 -> 144.11829 | E24: =E23-E13 -> 106.58015 | F24: =F23-F13 -> 81.188626 | G24: =G23-G13 -> 59.121591
A25: 股本
A26: 基礎股數（含 ATM 上限、SBC 稀釋） | B26: bn | C26: =損益!C23 -> 3.0889743 | D26: =損益!D23 -> 3.119864 | E26: =損益!E23 -> 3.1510627 | F26: =損益!F23 -> 3.1825733 | G26: =損益!G23 -> 3.214399
A27: ＋ 本期新股 | B27: bn | C27: =各期收支!C88 -> 0 | D27: =各期收支!D88 -> 0 | E27: =各期收支!E88 -> 0 | F27: =各期收支!F88 -> 0 | G27: =各期收支!G88 -> 0
A28: 總股數（期末） | B28: bn | C28: =損益!C24 -> 3.0889743 | D28: =損益!D24 -> 3.119864 | E28: =損益!E24 -> 3.1510627 | F28: =損益!F24 -> 3.1825733 | G28: =損益!G24 -> 3.214399 | I28: ＝基礎股數＋累計新股
A29: 槓桿
A30: 期末 backlog | B30: US$bn | C30: =各期收支!C73 -> 599.26 | D30: =各期收支!D73 -> 485.55 | E30: =各期收支!E73 -> 362.71 | F30: =各期收支!F73 -> 283.7509 | G30: =各期收支!G73 -> 169.79065
A31: 債務上限（債務／backlog × 期末 backlog） | B31: US$bn | C31: =各期收支!C75 -> 191.37957 | D31: =各期收支!D75 -> 242.19597 | E31: =各期收支!E75 -> 306.11719 | F31: =各期收支!F75 -> 350.31552 | G31: =各期收支!G75 -> 350.20541
A32: 總債務 ÷ 期末 backlog | B32: x | C32: =C23/MAX(0.01,C30) -> 0.22377374 | D32: =D23/MAX(0.01,D30) -> 0.31740973 | E32: =E23/MAX(0.01,E30) -> 0.40974413 | F32: =F23/MAX(0.01,F30) -> 0.49821267 | G32: =G23/MAX(0.01,G30) -> 0.77517986 | I32: 高息債不受 backlog 上限約束
A33: 總債務 ÷ EBITDA（年化） | B33: x | C33: =C23/MAX(0.01,損益!C22/輸入與假設!C$41) -> 2.510307 | D33: =D23/MAX(0.01,損益!D22/輸入與假設!D$41) -> 2.1079289 | E33: =E23/MAX(0.01,損益!E22/輸入與假設!E$41) -> 1.5783815 | F33: =F23/MAX(0.01,損益!F22/輸入與假設!F$41) -> 1.4079346 | G33: =G23/MAX(0.01,損益!G22/輸入與假設!G$41) -> 1.3441507 | I33: FY26 模型期 EBITDA 以半年×2 年化
A34: 租賃負債（期末） | B34: US$bn | C34: =各期收支!C59 -> 82.436654 | D34: =各期收支!D59 -> 143.90918 | E34: =各期收支!E59 -> 202.56113 | F34: =各期收支!F59 -> 200.50904 | G34: =各期收支!G59 -> 189.43673 | I34: 見『各期收支』租賃負債（期末剩餘租金現值，5.7%）
A35: EBITDAR（年化＝(EBITDA＋租金) ÷ 期間長度） | B35: US$bn | C35: =(損益!C22+各期收支!C16)/輸入與假設!C$41 -> 60.84805 | D35: =(損益!D22+各期收支!D16)/輸入與假設!D$41 -> 85.801146 | E35: =(損益!E22+各期收支!E16)/輸入與假設!E$41 -> 113.03963 | F35: =(損益!F22+各期收支!F16)/輸入與假設!F$41 -> 122.40546 | G35: =(損益!G22+各期收支!G16)/輸入與假設!G$41 -> 119.92048
A36: 調整後槓桿（(總債務＋租賃負債) ÷ EBITDAR） | B36: x | C36: =(C23+C34)/MAX(0.01,C35) -> 3.5586236 | D36: =(D23+D34)/MAX(0.01,D35) -> 3.4734673 | E36: =(E23+E34)/MAX(0.01,E35) -> 3.106693 | F36: =(F23+F34)/MAX(0.01,F35) -> 2.7929909 | G36: =(G23+G34)/MAX(0.01,G35) -> 2.6772328 | I36: S&P 降評門檻 >4.5×（[Interested-party] 二手轉述）；S&P 自身口徑另含全部未起租承諾與無條件採購義務，較本列高（見報告）
A37: 距投資級上限的空間（上限 − 調整後槓桿） | B37: x | C37: =輸入與假設!$C$147-C36 -> 0.94137643 | D37: =輸入與假設!$C$147-D36 -> 1.0265327 | E37: =輸入與假設!$C$147-E36 -> 1.393307 | F37: =輸入與假設!$C$147-F36 -> 1.7070091 | G37: =輸入與假設!$C$147-G36 -> 1.8227672 | I37: 負值＝超過上限：需股權或失去投資級

Sheet 資產負債_租賃承諾
A1: 租賃與承諾 — 季報（2026-08-31）原始揭露
A2: 本頁為硬編碼的申報數字（藍字），支出與資金頁的租金與還本列由此而來
A4: 在帳租賃到期表（未折現）
A5: 項目 | B5: 單位 | C5: 2026 下半 | D5: 2027 | E5: 2028 | F5: 2029 | G5: 2030 | H5: 其後
A6: 營業租賃付款 | B6: US$bn | C6: 3.219 | D6: 4.135 | E6: 4.097 | F6: 4.109 | G6: 4.089 | H6: 28.401
A7: 融資租賃付款 | B7: US$bn | C7: 0.62 | D7: 0.852 | E7: 0.923 | F7: 0.947 | G7: 0.971 | H7: 10.882
A8: 合計（＝支出頁「在帳現金租金」） | C8: =SUM(C6:C7) -> 3.839 | D8: =SUM(D6:D7) -> 4.987 | E8: =SUM(E6:E7) -> 5.02 | F8: =SUM(F6:F7) -> 5.056 | G8: =SUM(G6:G7) -> 5.06 | H8: =SUM(H6:H7) -> 39.283 | I8: 營業租賃負債現值 34.621、融資租賃 9.185；年報加權剩餘租期 12／14 年、折現率 5.7% [Verified]
A10: 債務本金到期表
A11: 項目 | B11: 單位 | C11: 2026 下半 | D11: 2027 | E11: 2028 | F11: 2029 | G11: 2030 | H11: 其後
A12: 本金（＝支出頁「排程還本」） | B12: US$bn | C12: 3.007 | D12: 10.147 | E12: 5.5 | F12: 7.25 | G12: 9.75 | H12: 90.25 | I12: 其他借款到期表（company.json → debt.amortization）；可轉債到期還本依融資分類另計，見『資產負債_既有債務』逐檔表
A13: 合計 | C13: =SUM(C12:H12) -> 125.904
A15: 表外與契約性承諾（未入表）
A16: 項目 | B16: 單位 | C16: 金額 | D16: 時程 | E16: 入表？ | F16: 模型位置
A17: 未起租租賃（未折現） | B17: US$bn | C17: 288 | D17: 季報揭露之已簽約未起租租賃 | E17: 否 | F17: 表外現金租金
A18: 單站按造價計租，上限 | B18: US$bn | C18: 0 | D18: 無此類揭露時為 0 | E18: 否 | F18: 表外現金租金
A19: 未動用信用額度 | B19: US$bn | C19: 10 | D19: company.json → defaults.facility（循環信用額度，未動用） | E19: 否（來源） | F19: 瀑布：未動用額度
A20: 已揭露金額之承諾合計（未起租＋單站上限） | C20: =C17+C18 -> 288
A21: 模型表外租金五期合計 | C21: =SUM(各期收支!C15:G15) -> 57.176471
A22: 模型表外租金尾端（模型期後未付＝總額 − 五期） | C22: =MAX(0,輸入與假設!$C$26-C21) -> 230.82353
A23: 模型路徑合計 ÷ 已承諾（≥0.8 為合理） | C23: =(C21+C22)/C20 -> 1 | I23: 起租排程依季報附註（起租期間與期限）平均分攤；五期＋尾端＝未起租總額

Sheet 損益
A1: 損益（類損益表）— 與資金模型同一組收入
A2: 算力收入、Cash CapEx、利息皆由前面分頁連結而來；改資金假設，此頁會跟著動
A4: 項目 | B4: 單位 | C4: FY27 | D4: FY28 | E4: FY29 | F4: FY30 | G4: FY31 | I4: 公式／來源說明
A5: 損益表
A6: 算力收入 | B6: US$bn | C6: =運營_產能與收入!C26 -> 28.61865 | D6: =運營_產能與收入!D26 -> 71.677125 | E6: =運營_產能與收入!E26 -> 112.42793 | F6: =運營_產能與收入!F26 -> 133.57545 | G6: =運營_產能與收入!G26 -> 139.64805 | I6: ＝RPO 轉換＋新簽約
A7: 非算力服務 | B7: US$bn | C7: =輸入與假設!C$50 -> 0 | D7: =輸入與假設!D$50 -> 0 | E7: =輸入與假設!E$50 -> 0 | F7: =輸入與假設!F$50 -> 0 | G7: =輸入與假設!G$50 -> 0
A8: 傳統事業 | B8: US$bn | C8: =輸入與假設!C$81 -> 39.53397 | D8: =輸入與假設!D$81 -> 53.708122 | E8: =輸入與假設!E$81 -> 55.853812 | F8: =輸入與假設!F$81 -> 57.875123 | G8: =輸入與假設!G$81 -> 59.722479 | I8: SaaS、軟體、硬體、服務（v0.1b）
A9: 總營收 | B9: US$bn | C9: =C6+C7+C8 -> 68.15262 | D9: =D6+D7+D8 -> 125.38525 | E9: =E6+E7+E8 -> 168.28174 | F9: =F6+F7+F8 -> 191.45057 | G9: =G6+G7+G8 -> 199.37053
A10: EBITDA 率 | B10: % | C10: =輸入與假設!C$93 -> 0.65039005 | D10: =輸入與假設!D$93 -> 0.61346746 | E10: =輸入與假設!E$93 -> 0.56794063 | F10: =輸入與假設!F$93 -> 0.51660121 | G10: =輸入與假設!G$93 -> 0.46913568
A11: 延誤罰則（服務抵減，營業費用） | B11: US$bn | C11: =運營_產能與收入!C62 -> 0 | D11: =運營_產能與收入!D62 -> 0 | E11: =運營_產能與收入!E62 -> 0 | F11: =運營_產能與收入!F62 -> 0 | G11: =運營_產能與收入!G62 -> 0 | I11: 建設延誤期間應計費而未計費營收 × 罰則比例（預設 0；v0.2）
A12: 營業利益（EBIT） | B12: US$bn | C12: =(C6+C7)*輸入與假設!C$93+輸入與假設!C$51+輸入與假設!C$83-C11-輸入與假設!C$136 -> 27.363715 | D12: =(D6+D7)*輸入與假設!D$93+輸入與假設!D$51+輸入與假設!D$83-D11-輸入與假設!D$136 -> 44.336628 | E12: =(E6+E7)*輸入與假設!E$93+輸入與假設!E$51+輸入與假設!E$83-E11-輸入與假設!E$136 -> 54.107701 | F12: =(F6+F7)*輸入與假設!F$93+輸入與假設!F$51+輸入與假設!F$83-F11-輸入與假設!F$136 -> 55.965083 | G12: =(G6+G7)*輸入與假設!G$93+輸入與假設!G$51+輸入與假設!G$83-G11-輸入與假設!G$136 -> 52.826069 | I12: ＝(算力＋服務營收)×EBITDA 率＋其他事業 EBITDA＋傳統事業 EBITDA − 延誤罰則 − 車隊 D&A
A13: 利息（含瀑布新債） | B13: US$bn | C13: =各期收支!C21 -> 4.9668427 | D13: =各期收支!D21 -> 8.0563449 | E13: =各期收支!E21 -> 7.6807203 | F13: =各期收支!F21 -> 7.3746415 | G13: =各期收支!G21 -> 6.9665365
A14: 預付財務組成利息（非現金） | B14: US$bn | C14: =各期收支!C10 -> 1.543922 | D14: =各期收支!D10 -> 3.583133 | E14: =各期收支!E10 -> 4.423574 | F14: =各期收支!F10 -> 4.7366933 | G14: =各期收支!G10 -> 5.2888366 | I14: 客戶預付的重大財務組成：合約負債以隱含利率累積的利息（v0.1b）
A15: 稅前損益 | B15: US$bn | C15: =C12-C13-C14 -> 20.85295 | D15: =D12-D13-D14 -> 32.69715 | E15: =E12-E13-E14 -> 42.003407 | F15: =F12-F13-F14 -> 43.853748 | G15: =G12-G13-G14 -> 40.570696
A16: NOL 期初餘額 | B16: US$bn | C16: =輸入與假設!$C$193 -> 0 | D16: =C18 -> 0 | E16: =D18 -> 0 | F16: =E18 -> 0 | G16: =F18 -> 0 | I16: 8/31 累積虧損約 0.0
A17: 本期動用 NOL | B17: US$bn | C17: =MIN(C16,MAX(0,C15)*輸入與假設!$C$194) -> 0 | D17: =MIN(D16,MAX(0,D15)*輸入與假設!$C$194) -> 0 | E17: =MIN(E16,MAX(0,E15)*輸入與假設!$C$194) -> 0 | F17: =MIN(F16,MAX(0,F15)*輸入與假設!$C$194) -> 0 | G17: =MIN(G16,MAX(0,G15)*輸入與假設!$C$194) -> 0 | I17: 美國規定：抵扣上限為應稅所得 80%
A18: NOL 期末餘額 | B18: US$bn | C18: =C16-C17+MAX(0,-C15) -> 0 | D18: =D16-D17+MAX(0,-D15) -> 0 | E18: =E16-E17+MAX(0,-E15) -> 0 | F18: =F16-F17+MAX(0,-F15) -> 0 | G18: =G16-G17+MAX(0,-G15) -> 0
A19: 所得稅 | B19: US$bn | C19: =MAX(0,C15-C17)*輸入與假設!$C$180 -> 3.1487955 | D19: =MAX(0,D15-D17)*輸入與假設!$C$180 -> 4.9372696 | E19: =MAX(0,E15-E17)*輸入與假設!$C$180 -> 6.3425145 | F19: =MAX(0,F15-F17)*輸入與假設!$C$180 -> 6.621916 | G19: =MAX(0,G15-G17)*輸入與假設!$C$180 -> 6.1261751 | I19: 虧損年不認列稅盾（與公司評價備抵一致）
A20: 淨利 | B20: US$bn | C20: =C15-C19 -> 17.704155 | D20: =D15-D19 -> 27.75988 | E20: =E15-E19 -> 35.660893 | F20: =F15-F19 -> 37.231832 | G20: =G15-G19 -> 34.444521
A21: D&A | B21: US$bn | C21: =輸入與假設!C$136 -> 12.700702 | D21: =輸入與假設!D$136 -> 28.776983 | E21: =輸入與假設!E$136 -> 40.050963 | F21: =輸入與假設!F$136 -> 44.443198 | G21: =輸入與假設!G$136 -> 45.093231 | I21: 車隊折舊，見輸入頁
A22: EBITDA | B22: US$bn | C22: =C12+C21 -> 40.064417 | D22: =D12+D21 -> 73.113611 | E22: =E12+E21 -> 94.158665 | F22: =F12+F21 -> 100.40828 | G22: =G12+G21 -> 97.9193
A23: 基礎股數（每年 +SBC 稀釋） | B23: bn | C23: =評價_DCF與目標價!$C$69 -> 3.0889743 | D23: =C23*(1+輸入與假設!$C$210) -> 3.119864 | E23: =D23*(1+輸入與假設!$C$210) -> 3.1510627 | F23: =E23*(1+輸入與假設!$C$210) -> 3.1825733 | G23: =F23*(1+輸入與假設!$C$210) -> 3.214399 | I23: FY27＝評價股數（含價內可轉債轉股，見『評價_DCF與目標價』可轉債區）；之後每年 ×(1＋股數年增)
A24: 股數（含瀑布新股） | B24: bn | C24: =C23+各期收支!C89 -> 3.0889743 | D24: =D23+各期收支!D89 -> 3.119864 | E24: =E23+各期收支!E89 -> 3.1510627 | F24: =F23+各期收支!F89 -> 3.1825733 | G24: =G23+各期收支!G89 -> 3.214399 | I24: ＝基礎股數＋累計瀑布新股
A25: 每股盈餘（EPS，模型期） | B25: US$ | C25: =C20/C24 -> 5.7314025 | D25: =D20/D24 -> 8.8977852 | E25: =E20/E24 -> 11.3171 | F25: =F20/F24 -> 11.698657 | G25: =G20/G24 -> 10.715695 | I25: FY27 欄只含第 2–4 季；全年口徑見下方
A27: 損益表（全年口徑；FY27＝1Q 實際＋第 2–4 季模型；與 HTML 損益簡表一致）
A28: 1Q27 實際營收（已實現） | B28: US$bn | C28: =輸入與假設!$C$251 -> 19.345 | D28: =0 -> 0 | E28: =0 -> 0 | F28: =0 -> 0 | G28: =0 -> 0
A29: 全年總營收 | B29: US$bn | C29: =C28+C9 -> 87.49762 | D29: =D28+D9 -> 125.38525 | E29: =E28+E9 -> 168.28174 | F29: =F28+F9 -> 191.45057 | G29: =G28+G9 -> 199.37053 | I29: FY27 可對照指引 ≥90
A30: 營收 YoY | B30: % | C30: =C29/67.357-1 -> 0.29901302 | D30: =D29/C29-1 -> 0.43301323 | E30: =E29/D29-1 -> 0.34211752 | F30: =F29/E29-1 -> 0.13767885 | G30: =G29/F29-1 -> 0.041368153 | I30: FY26 實際 67.357
A31: 全年 GAAP 營業利益 | B31: US$bn | C31: =輸入與假設!$C$252+C12 -> 34.091715 | D31: =D12 -> 44.336628 | E31: =E12 -> 54.107701 | F31: =F12 -> 55.965083 | G31: =G12 -> 52.826069
A32: 營利率 | B32: % | C32: =C31/C29 -> 0.3896302 | D32: =D31/D29 -> 0.35360322 | E32: =E31/E29 -> 0.32153044 | F32: =F31/F29 -> 0.29232132 | G32: =G31/G29 -> 0.26496428
A33: 全年 D&A | B33: US$bn | C33: =輸入與假設!$C$255+C21 -> 16.058702 | D33: =D21 -> 28.776983 | E33: =E21 -> 40.050963 | F33: =F21 -> 44.443198 | G33: =G21 -> 45.093231 | I33: 1Q 實際 3.358
A34: 全年 EBITDA | B34: US$bn | C34: =C31+C33 -> 50.150417 | D34: =D31+D33 -> 73.113611 | E34: =E31+E33 -> 94.158665 | F34: =F31+F33 -> 100.40828 | G34: =G31+G33 -> 97.9193
A35: 全年利息（含瀑布新債） | B35: US$bn | C35: =輸入與假設!$C$249+C13 -> 6.3948427 | D35: =D13 -> 8.0563449 | E35: =E13 -> 7.6807203 | F35: =F13 -> 7.3746415 | G35: =G13 -> 6.9665365 | I35: FY27 起瀑布新債利息（9%）與新股同時影響 EPS
A36: 全年淨利 | B36: US$bn | C36: =輸入與假設!$C$253+C20 -> 22.464155 | D36: =D20 -> 27.75988 | E36: =E20 -> 35.660893 | F36: =F20 -> 37.231832 | G36: =G20 -> 34.444521
A37: 淨利率 | B37: % | C37: =C36/C29 -> 0.25674018 | D37: =D36/D29 -> 0.2213967 | E37: =E36/E29 -> 0.21191184 | F37: =F36/F29 -> 0.1944723 | G37: =G36/G29 -> 0.17276636
A38: 全年 GAAP EPS | B38: US$ | C38: =輸入與假設!$C$257+C20/C24 -> 7.2914025 | D38: =D20/D24 -> 8.8977852 | E38: =E20/E24 -> 11.3171 | F38: =F20/F24 -> 11.698657 | G38: =G20/G24 -> 10.715695 | I38: FY27＝1Q 實際 EPS 1.56＋第 2–4 季淨利÷股數
A39: 全年 EPS（加回 SBC） | B39: US$ | C39: =輸入與假設!$C$258+(C20+輸入與假設!$C$211*輸入與假設!C$41)/C24 -> 8.7859406 | D39: =(D20+輸入與假設!$C$211*輸入與假設!D$41)/D24 -> 10.34272 | E39: =(E20+輸入與假設!$C$211*輸入與假設!E$41)/E24 -> 12.747729 | F39: =(F20+輸入與假設!$C$211*輸入與假設!F$41)/F24 -> 13.115121 | G39: =(G20+輸入與假設!$C$211*輸入與假設!G$41)/G24 -> 12.118135 | I39: ＝(淨利＋SBC)÷股數；NOL 狀態無現金稅，SBC 全額加回

Sheet 評價_DCF與目標價
A1: 評價 — DCF、EV/EBITDA、加權目標價
A2: 營收、營業利益、D&A、EBITDA、股數引用『損益』頁；Cash CapEx 與融資引用『各期收支』頁
A4: 項目 | B4: 單位 | C4: FY27 | D4: FY28 | E4: FY29 | F4: FY30 | G4: FY31 | I4: 公式／來源說明
A5: DCF（無槓桿自由現金流；起點為 2026-08-31）
A6: 現金 CapEx（2026-08-31 之後） | B6: US$bn | C6: =輸入與假設!C$135-各期收支!C8 -> 58.740815 | D6: =輸入與假設!D$135-各期收支!D8 -> 65.117864 | E6: =輸入與假設!E$135-各期收支!E8 -> 23.619596 | F6: =輸入與假設!F$135-各期收支!F8 -> 41.630587 | G6: =輸入與假設!G$135-各期收支!G8 -> 41.630587 | I6: DCF 起點為 8/31，故 FY27 欄只含 2Q–4Q 的建置支出，不含 1Q 已發生的 28.499
A7: 比較基期營收 | B7: US$bn | C7: =67.357 -> 67.357 | D7: =19.345+損益!C9 -> 87.49762 | E7: =損益!D9 -> 125.38525 | F7: =損益!E9 -> 168.28174 | G7: =損益!F9 -> 191.45057 | I7: FY26 實際 67.357；FY28 基期＝1Q 實際 19.345＋FY27 模型期營收
A8: 預付認列（非現金營收，扣除） | B8: US$bn | C8: =各期收支!C11 -> 2.6248383 | D8: =各期收支!D11 -> 7.4626503 | E8: =各期收支!E11 -> 11.035453 | F8: =各期收支!F11 -> 11.292098 | G8: =各期收支!G11 -> 12.764163 | I8: 營收中由合約負債轉入的部分已在預付時收現（預付流入已自現金 CapEx 抵減），UFCF 扣除以免重複（v0.1b）
A9: 營運資金變動 | B9: US$bn | C9: =輸入與假設!$C$195*MAX(0,損益!C9-C7) -> 0.015912396 | D9: =輸入與假設!$C$195*MAX(0,損益!D9-D7) -> 0.75775255 | E9: =輸入與假設!$C$195*MAX(0,損益!E9-E7) -> 0.85792979 | F9: =輸入與假設!$C$195*MAX(0,損益!F9-F7) -> 0.46337672 | G9: =輸入與假設!$C$195*MAX(0,損益!G9-G7) -> 0.15839913 | I9: 營收增量的 2%
A10: 無槓桿 NOL 期初 | B10: US$bn | C10: =輸入與假設!$C$193 -> 0 | D10: =C12 -> 0 | E10: =D12 -> 0 | F10: =E12 -> 0 | G10: =F12 -> 0 | I10: DCF 用無槓桿稅（利息不可抵稅，否則稅盾被計兩次：一次在 UFCF、一次在 WACC）
A11: 本期動用（無槓桿） | B11: US$bn | C11: =MIN(C10,MAX(0,損益!C12)*輸入與假設!$C$194) -> 0 | D11: =MIN(D10,MAX(0,損益!D12)*輸入與假設!$C$194) -> 0 | E11: =MIN(E10,MAX(0,損益!E12)*輸入與假設!$C$194) -> 0 | F11: =MIN(F10,MAX(0,損益!F12)*輸入與假設!$C$194) -> 0 | G11: =MIN(G10,MAX(0,損益!G12)*輸入與假設!$C$194) -> 0
A12: 無槓桿 NOL 期末 | B12: US$bn | C12: =C10-C11+MAX(0,-損益!C12) -> 0 | D12: =D10-D11+MAX(0,-損益!D12) -> 0 | E12: =E10-E11+MAX(0,-損益!E12) -> 0 | F12: =F10-F11+MAX(0,-損益!F12) -> 0 | G12: =G10-G11+MAX(0,-損益!G12) -> 0
A13: 無槓桿所得稅（DCF 用） | B13: US$bn | C13: =MAX(0,損益!C12-C11)*輸入與假設!$C$180 -> 4.131921 | D13: =MAX(0,損益!D12-D11)*輸入與假設!$C$180 -> 6.6948308 | E13: =MAX(0,損益!E12-E11)*輸入與假設!$C$180 -> 8.1702629 | F13: =MAX(0,損益!F12-F11)*輸入與假設!$C$180 -> 8.4507276 | G13: =MAX(0,損益!G12-G11)*輸入與假設!$C$180 -> 7.9767364 | I13: 與損益表的所得稅不同：此處不扣利息，數字較高，這是 DCF 的正確口徑
A14: UFCF | B14: US$bn | C14: =損益!C12-C13+損益!C21-C6-C9-C8 -> -25.44907 | D14: =損益!D12-D13+損益!D21-D6-D9-D8 -> -6.9194863 | E14: =損益!E12-E13+損益!E21-E6-E9-E8 -> 50.475423 | F14: =損益!F12-F13+損益!F21-F6-F9-F8 -> 38.571492 | G14: =損益!G12-G13+損益!G21-G6-G9-G8 -> 35.389415 | I14: ＝EBIT−無槓桿稅＋D&A−現金 CapEx（已扣客戶預付）−營運資金−預付認列。建置期全為負是正常的
A15: 折現期數 | B15: 年 | C15: =輸入與假設!$C$228 -> 0.75 | D15: =輸入與假設!$D$228 -> 1.75 | E15: =輸入與假設!$E$228 -> 2.75 | F15: =輸入與假設!$F$228 -> 3.75 | G15: =輸入與假設!$G$228 -> 4.75 | I15: 自 2026-08-31 起算；FY27 模型期（第 2–4 季）的現金流平均落在 0.75 年
A16: 折現因子 | C16: =1/(1+輸入與假設!$C$190)^C15 -> 0.91542773 | D16: =1/(1+輸入與假設!$C$190)^D15 -> 0.81368471 | E16: =1/(1+輸入與假設!$C$190)^E15 -> 0.72324967 | F16: =1/(1+輸入與假設!$C$190)^F15 -> 0.64286581 | G16: =1/(1+輸入與假設!$C$190)^G15 -> 0.57141603
A17: UFCF 現值 | B17: US$bn | C17: =C14*C16 -> -23.296784 | D17: =D14*D16 -> -5.6302801 | E17: =E14*E16 -> 36.506333 | F17: =F14*F16 -> 24.796294 | G17: =G14*G16 -> 20.222079
A19: 五期 UFCF 現值合計 | C19: =SUM(C17:G17) -> 52.597641 | I19: 建置期現金流現值
A20: 終值基準 FCF（FY31 UFCF，含汰換 CapEx） | C20: =G14+輸入與假設!G128*(1-各期收支!G7) -> 35.389415 | I20: v0.1c：終值基準＝末期 UFCF（含穩態汰換 CapEx，已扣客戶預付覆蓋）＋加回末期成長型 CapEx（扣預付後；成長由 g 表達，預設情境為 0）；GPU 不是永續資產，終值年須持續再投資
A21: 終值（Gordon） | C21: =IF(C30=1,0,C20*(1+輸入與假設!$C$191)/(輸入與假設!$C$190-輸入與假設!$C$191)) -> 383.53481 | I21: ＝常態化 FCF×(1+g)÷(WACC−g)
A22: 終值現值 | C22: =C21*G16 -> 219.15794
A23: 企業價值 EV | C23: =C19+C22 -> 271.75558
A24: 減：淨負債 | C24: =-評價_DCF與目標價!$C$70 -> -88.827 | I24: ＝評價淨負債（不含可轉債的淨負債＋債務處理可轉債到期本金＋調整項；見下方可轉債區）
A25: 股權價值 | C25: =C23+C24 -> 182.92858
A26: DCF 每股 | C26: =IF(C30=1,0,IF(輸入與假設!$C$213=2,C32,C31)) -> 59.219845 | I26: 採用值：失效時為 0 且權重歸零；否則依「DCF 下限方式」取 0 截斷或選擇權
A27: 終值占 EV 比重 | C27: =C22/C23 -> 0.8064524 | I27: ="超過 "&IF(ROUND(ABS(輸入與假設!$C$237)*100,4)=INT(ROUND(ABS(輸入與假設!$C$237)*100,4)),TEXT(ROUND(ABS(輸入與假設!$C$237)*100,4),"0"),TEXT(ROUND(ABS(輸入與假設!$C$237)*100,4),"0.0"))&"%"&" 表示結論由終值假設決定，不由現金流決定" -> 超過 85% 表示結論由終值假設決定，不由現金流決定
A28: 新股募得現金（現值） | C28: =各期收支!C84/(1+輸入與假設!$C$190)^輸入與假設!$C$229+各期收支!D84/(1+輸入與假設!$C$190)^輸入與假設!$D$229+各期收支!E84/(1+輸入與假設!$C$190)^輸入與假設!$E$229+各期收支!F84/(1+輸入與假設!$C$190)^輸入與假設!$F$229+各期收支!G84/(1+輸入與假設!$C$190)^輸入與假設!$G$229 -> 0 | I28: 期初到位，折現期數 0／0.5／1.5／2.5／3.5 年
A29: 融資後股數（含瀑布新股） | C29: =評價_DCF與目標價!$C$69+各期收支!G89 -> 3.0889743
A30: DCF 失效？（WACC ≤ g 或常態化 FCF ≤ 0） | C30: =IF(OR(輸入與假設!$C$190<=輸入與假設!$C$191,C20<=0),1,0) -> 0 | I30: 1＝失效：DCF 權重歸零、EV/EBITDA 100%。股權為負不算失效
A31: DCF 每股：0 截斷 | C31: =MAX(0,(C25+C28)/C29) -> 59.219845
A32: DCF 每股：選擇權（Merton） | C32: =IF((C23+C28)<=0,0,IF(評價_DCF與目標價!$C$70<=0,(C23+C28),(C23+C28)*NORMSDIST(C33)-評價_DCF與目標價!$C$70*EXP(-輸入與假設!$C$181*輸入與假設!$C$215)*NORMSDIST(C34))/C29) -> 67.772474 | I32: Black-Scholes：S＝企業價值＋新股現值、K＝淨負債
A33: d1 | C33: =IF(OR((C23+C28)<=0,評價_DCF與目標價!$C$70<=0),0,(LN((C23+C28)/評價_DCF與目標價!$C$70)+(輸入與假設!$C$181+輸入與假設!$C$214^2/2)*輸入與假設!$C$215)/(輸入與假設!$C$214*SQRT(輸入與假設!$C$215))) -> 1.8007184
A34: d2 | C34: =C33-輸入與假設!$C$214*SQRT(輸入與假設!$C$215) -> 0.71099368
A36: 倍數法（錨定年度，預設 FY29；折回 2027-08-31）
A37: 錨定年度 | C37: =CHOOSE(輸入與假設!$C$205,"FY28","FY29","FY30","FY31") -> FY29 | I37: 輸入與假設 F 區可改
A38: 錨定年度 EBITDA | C38: =INDEX(損益!$D$22:$G$22,1,輸入與假設!$C$205) -> 94.158665
A39: 錨定年度企業價值（倍數 × EBITDA） | C39: =C45*輸入與假設!$C$196+C44*輸入與假設!$C$204 -> 838.31462 | I39: 分部加總：OCI EBITDA × EV/EBITDA 倍數＋傳統事業 EBITDA × 傳統事業倍數（下方兩列）
A40: 錨定年度末淨負債（總債務 − 現金） | C40: =INDEX(各期收支!$D$94:$G$94,1,輸入與假設!$C$205)-INDEX(各期收支!$D$52:$G$52,1,輸入與假設!$C$205)+評價_DCF與目標價!$C$71 -> 106.58015 | I40: 含瀑布新債；加可轉債分類調整與淨負債調整項（見下方可轉債區）
A41: 錨定年度末股數（含瀑布新股） | C41: =INDEX(損益!$D$24:$G$24,1,輸入與假設!$C$205) -> 3.1510627 | I41: 損益股數：SBC 逐年稀釋＋瀑布新股
A42: 折回 2027-08-31 的折現因子 | C42: =1/(1+輸入與假設!$C$190)^(輸入與假設!$C$205-輸入與假設!$C$225) -> 0.81368471 | I42: 以 WACC 折現 [Assumed]
A43: EV/EBITDA 每股（融資後） | C43: =MAX(0,(C39-C40)/C41)*C42 -> 188.95249 | I43: 以 0 為下限
A44: 錨定年度傳統事業 EBITDA | C44: =INDEX(輸入與假設!$D$83:$G$83,1,輸入與假設!$C$205) -> 30.306278 | I44: × 傳統事業 EV/EBITDA 倍數（軟體同業 NTM 中位數）
A45: 錨定年度 OCI EBITDA（算力＋服務＋其他） | C45: =C38-C44 -> 63.852386 | I45: ＝錨定年度 EBITDA − 傳統事業；× EV/EBITDA 倍數
A47: 加權目標價
A48: DCF 每股（推到目標價時點） | C48: =C26*(1+輸入與假設!$C$190)^輸入與假設!$C$221 -> 66.624687 | I48: ＝DCF 每股 ×（1＋WACC）^（評價日至目標價時點的年數）
A49: DCF 每股 × 有效權重 | C49: =C48*IF(C30=1,0,輸入與假設!$C$206) -> 29.981109
A50: EV/EBITDA（融資後）× 有效權重 | C50: =C43*IF(C30=1,1,1-輸入與假設!$C$206) -> 103.92387
A51: 加權目標價 | C51: =SUM(C49:C50) -> 133.90498 | I51: 期前融資瀑布：缺口先由額度與資產層新債支應，殘差以股權募足；估值不再扣缺口本金
A52: 現價 | C52: =輸入與假設!$C$175 -> 144.77
A53: 潛在空間 | C53: =C51/C52-1 -> -0.075050216
A55: 可轉債稀釋（若轉換法；第一輪判斷價＝現價，第二輪＝MIN(現價, 第一輪目標價)）
A56: 第一輪：轉股股數 | C56: =SUMPRODUCT(資產負債_既有債務!$D$73:$D$73*資產負債_既有債務!$G$73:$G$73) -> 0.031238286 | I56: 有效轉換價 < 現價的可轉債：原始本金 ÷ 轉換價
A57: 第一輪：評價股數 | C57: =輸入與假設!$C$176+C56 -> 3.0889743
A58: 第一輪：評價淨負債 | C58: =輸入與假設!$C$177+SUMPRODUCT(資產負債_既有債務!$C$73:$C$73*(1-資產負債_既有債務!$G$73:$G$73))+輸入與假設!$C$179 -> 88.827 | I58: ＝不含可轉債的淨負債＋債務處理可轉債到期本金＋調整項
A59: 第一輪：DCF 融資後股數 | C59: =C57+各期收支!G89 -> 3.0889743
A60: 第一輪：d1 | C60: =IF(OR((C23+C28)<=0,C58<=0),0,(LN((C23+C28)/C58)+(輸入與假設!$C$181+輸入與假設!$C$214^2/2)*輸入與假設!$C$215)/(輸入與假設!$C$214*SQRT(輸入與假設!$C$215))) -> 1.8007184
A61: 第一輪：DCF 每股（評價日） | C61: =IF(C30=1,0,IF(輸入與假設!$C$213=2,IF((C23+C28)<=0,0,IF(C58<=0,(C23+C28),(C23+C28)*NORMSDIST(C60)-C58*EXP(-輸入與假設!$C$181*輸入與假設!$C$215)*NORMSDIST(C60-輸入與假設!$C$214*SQRT(輸入與假設!$C$215)))/C59),MAX(0,(C23-C58+C28)/C59))) -> 59.219845 | I61: 與上方 DCF 同算法，只換股數與淨負債
A62: 第一輪：錨定年末淨負債 | C62: =INDEX(各期收支!$D$94:$G$94,1,輸入與假設!$C$205)-INDEX(各期收支!$D$52:$G$52,1,輸入與假設!$C$205)+SUMPRODUCT(資產負債_既有債務!$C$73:$C$73*(資產負債_既有債務!$F$73:$F$73-資產負債_既有債務!$G$73:$G$73))+輸入與假設!$C$179 -> 106.58015 | I62: ＝融資表錨定年末淨負債＋（融資分類為轉股、評價分類為債務的到期本金）＋調整項
A63: 第一輪：錨定年末股數 | C63: =C57*(1+輸入與假設!$C$210)^輸入與假設!$C$205+INDEX(各期收支!$D$89:$G$89,1,輸入與假設!$C$205) -> 3.1510627
A64: 第一輪：EV/EBITDA 每股 | C64: =MAX(0,(C39-C62)/C63)*C42 -> 188.95249
A65: 第一輪：加權目標價 | C65: =C61*(1+輸入與假設!$C$190)^輸入與假設!$C$221*IF(C30=1,0,輸入與假設!$C$206)+C64*IF(C30=1,1,1-輸入與假設!$C$206) -> 133.90498
A66: 第二輪判斷價 | C66: =MIN(輸入與假設!$C$175,C65) -> 133.90498 | I66: ＝MIN(現價, 第一輪加權目標價)：以較保守者判斷是否價內
A67: 第二輪：轉股股數 | C67: =SUMPRODUCT(資產負債_既有債務!$D$73:$D$73*資產負債_既有債務!$H$73:$H$73) -> 0.031238286 | I67: 有效轉換價 < 第二輪判斷價的可轉債
A68: 第二輪：債務處理到期本金 | C68: =SUMPRODUCT(資產負債_既有債務!$C$73:$C$73*(1-資產負債_既有債務!$H$73:$H$73)) -> 0
A69: 評價股數（含可轉債轉股） | C69: =輸入與假設!$C$176+C67 -> 3.0889743 | I69: DCF、損益股數與錨定年末股數的起點
A70: 評價淨負債（含可轉債與調整項） | C70: =輸入與假設!$C$177+C68+輸入與假設!$C$179 -> 88.827 | I70: DCF 減項與 Merton 履約價
A71: 錨定年末淨負債調整（可轉債分類差＋調整項） | C71: =SUMPRODUCT(資產負債_既有債務!$C$73:$C$73*(資產負債_既有債務!$F$73:$F$73-資產負債_既有債務!$H$73:$H$73))+輸入與假設!$C$179 -> 0 | I71: 融資現金流依『融資分類』（判斷價＝股權發行價）；評價依第二輪分類，差額在錨定年末淨負債補回
A72: DCF 權重說明 | C72: =IF(C30=1,"DCF 失效，已以 EV/EBITDA 100% 計。",IF(AND(輸入與假設!$C$213<>2,C87<0),"DCF 為 $0 仍計 "&TEXT(輸入與假設!$C$206,"0%")&" 權重的原因：DCF 沒有失效，而是算出的股權價值為負（每股約 −$"&TEXT(ABS(C87),"0.0")&"），代表自由現金流折現後的企業價值不足以償還淨負債。EV/EBITDA 沒有扣除 GPU 汰換與擴張支出，保留 DCF 權重，是為了讓目標價反映「EBITDA 付不起資本成本」。若不計 DCF，目標價為 $"&TEXT(C43,"0.0")&"（"&CHOOSE(D86+2,"賣出","中立","買進")&"）；"&TEXT(輸入與假設!$C$206,"0%")&"／"&TEXT(1-輸入與假設!$C$206,"0%")&" 為判斷值。","")) | I72: 只在 DCF 被 0 截斷時顯示；DCF 失效時改為一句；DCF 為正時空白（與 HTML 同一字串）
A74: 目標價區間（情境區間、方法區間；評等仍依點位）
A75: 目標價區間｜點位（目前輸入的加權目標價） | C75: =C51 -> 133.90498 | I75: ="評等規則不變：空間 ≥"&IF(ROUND(ABS(輸入與假設!$C$231)*100,4)=INT(ROUND(ABS(輸入與假設!$C$231)*100,4)),TEXT(ROUND(ABS(輸入與假設!$C$231)*100,4),"0"),TEXT(ROUND(ABS(輸入與假設!$C$231)*100,4),"0.0"))&"%"&" 且終值占比 <"&IF(ROUND(ABS(輸入與假設!$C$232)*100,4)=INT(ROUND(ABS(輸入與假設!$C$232)*100,4)),TEXT(ROUND(ABS(輸入與假設!$C$232)*100,4),"0"),TEXT(ROUND(ABS(輸入與假設!$C$232)*100,4),"0.0"))&"%"&"、股權募資 ≤"&IF(輸入與假設!$C$234=INT(輸入與假設!$C$234),TEXT(輸入與假設!$C$234,"0"),TEXT(輸入與假設!$C$234,"0.0"))&" 倍現市值 → 買進；空間 ≤−"&IF(ROUND(ABS(輸入與假設!$C$233)*100,4)=INT(ROUND(ABS(輸入與假設!$C$233)*100,4)),TEXT(ROUND(ABS(輸入與假設!$C$233)*100,4),"0"),TEXT(ROUND(ABS(輸入與假設!$C$233)*100,4),"0.0"))&"%"&"，或股權募資 >"&IF(輸入與假設!$C$234=INT(輸入與假設!$C$234),TEXT(輸入與假設!$C$234,"0"),TEXT(輸入與假設!$C$234,"0.0"))&" 倍且空間 ≤−"&IF(ROUND(ABS(輸入與假設!$C$235)*100,4)=INT(ROUND(ABS(輸入與假設!$C$235)*100,4)),TEXT(ROUND(ABS(輸入與假設!$C$235)*100,4),"0"),TEXT(ROUND(ABS(輸入與假設!$C$235)*100,4),"0.0"))&"%"&" → 賣出；其餘中立" -> 評等規則不變：空間 ≥25% 且終值占比 <90%、股權募資 ≤1.5 倍現市值 → 買進；空間 ≤−15%，或股權募資 >1.5 倍且空間 ≤−8% → 賣出；其餘中立
A76: 目標價區間｜終值占 EV（評等用） | C76: =C22/MAX(ABS(C23),1)*IF(C23=0,1,SIGN(C23)) -> 0.8064524
A77: 目標價區間｜股權募資 ÷ 現市值（評等用） | C77: =SUM(各期收支!C84:G84)/(輸入與假設!$C$175*輸入與假設!$C$176) -> 0
A78: 目標價區間｜點位評等代碼（1＝買進、0＝中立、−1＝賣出） | C78: =IF(AND((C51/MAX(輸入與假設!$C$175,0.01)-1)>=輸入與假設!$C$231,$C$76<輸入與假設!$C$232,$C$77<=輸入與假設!$C$234),1,IF(OR((C51/MAX(輸入與假設!$C$175,0.01)-1)<=輸入與假設!$C$233,AND($C$77>輸入與假設!$C$234,(C51/MAX(輸入與假設!$C$175,0.01)-1)<=輸入與假設!$C$235)),-1,0)) -> 0 | D78: =CHOOSE(C78+2,"賣出","中立","買進") -> 中立
A79: 目標價區間｜賣出門檻價（現價 × (1 − 15%)） | C79: =輸入與假設!$C$175*(1+輸入與假設!$C$233) -> 123.0545
A80: 目標價區間｜保守 OpenAI 相關 60%（加權目標價／評等代碼／距賣出門檻） | C80: =輸入與假設!D264 -> 73.988812 | D80: =輸入與假設!E264 -> -1 | E80: =C80-$C$79 -> -49.065688 | I80: 引用『輸入與假設』底部模擬運算表（情境選擇 1／2／3），保留其餘手動輸入
A81: 目標價區間｜基準 已簽約站點依 Q1 速度（加權目標價／評等代碼／距賣出門檻） | C81: =輸入與假設!D265 -> 133.90498 | D81: =輸入與假設!E265 -> 0 | E81: =C81-$C$79 -> 10.85048
A82: 目標價區間｜積極 依公司時程（加權目標價／評等代碼／距賣出門檻） | C82: =輸入與假設!D266 -> 226.60959 | D82: =輸入與假設!E266 -> 1 | E82: =C82-$C$79 -> 103.55509
A83: 目標價區間｜情境區間（下緣／上緣） | C83: =MIN(C80,C82) -> 73.988812 | D83: =MAX(C80,C82) -> 226.60959
A84: 目標價區間｜方法區間倍數（下端／上端） | C84: =MIN(輸入與假設!$C$208,輸入與假設!$C$209) -> 5 | D84: =MAX(輸入與假設!$C$208,輸入與假設!$C$209) -> 6
A85: 目標價區間｜方法區間（下緣／上緣） | C85: =MIN(C48*IF(C30=1,0,輸入與假設!$C$206)+MAX(0,(C45*C84+C44*輸入與假設!$C$204-C40)/C41)*C42*IF(C30=1,1,1-輸入與假設!$C$206),C48*IF(C30=1,0,輸入與假設!$C$206)+MAX(0,(C45*D84+C44*輸入與假設!$C$204-C40)/C41)*C42*IF(C30=1,1,1-輸入與假設!$C$206)) -> 124.83641 | D85: =MAX(C48*IF(C30=1,0,輸入與假設!$C$206)+MAX(0,(C45*C84+C44*輸入與假設!$C$204-C40)/C41)*C42*IF(C30=1,1,1-輸入與假設!$C$206),C48*IF(C30=1,0,輸入與假設!$C$206)+MAX(0,(C45*D84+C44*輸入與假設!$C$204-C40)/C41)*C42*IF(C30=1,1,1-輸入與假設!$C$206)) -> 133.90498 | I85: ＝DCF 採用值 × 有效權重 ＋ EV/EBITDA 腿（倍數換成兩端）× 有效權重
A86: 目標價區間｜100% EV/EBITDA 目標價（價位／評等代碼） | C86: =C43 -> 188.95249 | D86: =IF(AND((C43/MAX(輸入與假設!$C$175,0.01)-1)>=輸入與假設!$C$231,$C$76<輸入與假設!$C$232,$C$77<=輸入與假設!$C$234),1,IF(OR((C43/MAX(輸入與假設!$C$175,0.01)-1)<=輸入與假設!$C$233,AND($C$77>輸入與假設!$C$234,(C43/MAX(輸入與假設!$C$175,0.01)-1)<=輸入與假設!$C$235)),-1,0)) -> 1 | E86: =CHOOSE(D86+2,"賣出","中立","買進") -> 買進
A87: 目標價區間｜未截斷 DCF 每股 | C87: =(C25+C28)/C29 -> 59.219845
A88: 目標價區間｜點位摘要 | C88: ="目標價 $"&TEXT(C51,"0.0")&"（情境區間 $"&TEXT(C83,"0.0")&"–$"&TEXT(D83,"0.0")&"）" -> 目標價 $133.9（情境區間 $74.0–$226.6）
A89: 目標價區間｜方法區間標籤 | C89: ="方法區間（目前情境，"&IF(C84=INT(C84),TEXT(C84,"0"),TEXT(C84,"0.0"))&"–"&IF(D84=INT(D84),TEXT(D84,"0"),TEXT(D84,"0.0"))&"x）" -> 方法區間（目前情境，5–6x）
A90: 目標價區間｜點位位置 | C90: =IF(ABS(輸入與假設!$C$196-D84)<0.000000001,"目前點位位於方法區間上緣（"&IF(D84=INT(D84),TEXT(D84,"0"),TEXT(D84,"0.0"))&"x 為穩態倍數上緣）",IF(ABS(輸入與假設!$C$196-C84)<0.000000001,"目前點位位於方法區間下緣（"&IF(C84=INT(C84),TEXT(C84,"0"),TEXT(C84,"0.0"))&"x）","目前點位"&IF(AND(輸入與假設!$C$196>C84,輸入與假設!$C$196<D84),"位於方法區間內",IF(輸入與假設!$C$196>D84,"高於方法區間上緣","低於方法區間下緣"))&"（目前倍數 "&IF(輸入與假設!$C$196=INT(輸入與假設!$C$196),TEXT(輸入與假設!$C$196,"0"),TEXT(輸入與假設!$C$196,"0.0"))&"x）")) -> 目前點位位於方法區間上緣（6x 為穩態倍數上緣）
A91: 目標價區間｜判斷句 | C91: =IF(D83<輸入與假設!$C$175,"情境區間上緣 $"&TEXT(D83,"0.0")&" 低於現價 $"&TEXT(輸入與假設!$C$175,"0.00")&IF((D80<>-1)+(D81<>-1)+(D82<>-1)>0,"，但"&SUBSTITUTE(TRIM(IF(D80<>-1,"保守","")&" "&IF(D81<>-1,"基準","")&" "&IF(D82<>-1,"積極",""))," ","、")&"情境未達賣出門檻 $"&TEXT($C$79,"0.0"),"：賣出在三個擴張情境下都成立"),"情境區間上緣 $"&TEXT(D83,"0.0")&" 不低於現價 $"&TEXT(輸入與假設!$C$175,"0.00")&"：賣出並非在三個擴張情境下都成立")&"。"&IF(ABS(E80)<輸入與假設!$C$236*輸入與假設!$C$175,"保守情境 $"&TEXT(C80,"0.0")&"，"&IF(E80<0,"距賣出門檻","高於賣出門檻")&" $"&TEXT($C$79,"0.0")&" 僅 $"&TEXT(ABS(E80),"0.0")&"。","")&IF(ABS(E81)<輸入與假設!$C$236*輸入與假設!$C$175,"基準情境 $"&TEXT(C81,"0.0")&"，"&IF(E81<0,"距賣出門檻","高於賣出門檻")&" $"&TEXT($C$79,"0.0")&" 僅 $"&TEXT(ABS(E81),"0.0")&"。","")&IF(ABS(E82)<輸入與假設!$C$236*輸入與假設!$C$175,"積極情境 $"&TEXT(C82,"0.0")&"，"&IF(E82<0,"距賣出門檻","高於賣出門檻")&" $"&TEXT($C$79,"0.0")&" 僅 $"&TEXT(ABS(E82),"0.0")&"。","") -> 情境區間上緣 $226.6 不低於現價 $144.77：賣出並非在三個擴張情境下都成立。
A93: 錨定年度 × 倍數矩陣（每股；以 WACC 折回 2027-08-31）
A94: OCI 倍數 ＼ 錨定（EV/EBITDA 腿） | B94: 倍數 | C94: FY28 | D94: FY29 | E94: FY30 | F94: FY31 | I94: EV/EBITDA 腿＝(OCI EBITDA × 倍數＋傳統事業 EBITDA × 傳統事業倍數 − 錨定年末淨負債) ÷ 錨定年末股數 × 折現因子；加權＝DCF 採用值 × 有效權重 ＋ 腿 × 有效權重。綠底＝不低於現價
A95: 錨定×倍數｜EV/EBITDA 腿｜3.4x | B95: 3.4 | C95: =MAX(0,((INDEX(損益!$D$22:$G$22,1,1)-INDEX(輸入與假設!$D$83:$G$83,1,1))*$B95+INDEX(輸入與假設!$D$83:$G$83,1,1)*輸入與假設!$C$204-(INDEX(各期收支!$D$94:$G$94,1,1)-INDEX(各期收支!$D$52:$G$52,1,1)+評價_DCF與目標價!$C$71))/INDEX(損益!$D$24:$G$24,1,1))/(1+輸入與假設!$C$190)^(1-輸入與假設!$C$225) -> 130.01352 | D95: =MAX(0,((INDEX(損益!$D$22:$G$22,1,2)-INDEX(輸入與假設!$D$83:$G$83,1,2))*$B95+INDEX(輸入與假設!$D$83:$G$83,1,2)*輸入與假設!$C$204-(INDEX(各期收支!$D$94:$G$94,1,2)-INDEX(各期收支!$D$52:$G$52,1,2)+評價_DCF與目標價!$C$71))/INDEX(損益!$D$24:$G$24,1,2))/(1+輸入與假設!$C$190)^(2-輸入與假設!$C$225) -> 146.08288 | E95: =MAX(0,((INDEX(損益!$D$22:$G$22,1,3)-INDEX(輸入與假設!$D$83:$G$83,1,3))*$B95+INDEX(輸入與假設!$D$83:$G$83,1,3)*輸入與假設!$C$204-(INDEX(各期收支!$D$94:$G$94,1,3)-INDEX(各期收支!$D$52:$G$52,1,3)+評價_DCF與目標價!$C$71))/INDEX(損益!$D$24:$G$24,1,3))/(1+輸入與假設!$C$190)^(3-輸入與假設!$C$225) -> 142.05657 | F95: =MAX(0,((INDEX(損益!$D$22:$G$22,1,4)-INDEX(輸入與假設!$D$83:$G$83,1,4))*$B95+INDEX(輸入與假設!$D$83:$G$83,1,4)*輸入與假設!$C$204-(INDEX(各期收支!$D$94:$G$94,1,4)-INDEX(各期收支!$D$52:$G$52,1,4)+評價_DCF與目標價!$C$71))/INDEX(損益!$D$24:$G$24,1,4))/(1+輸入與假設!$C$190)^(4-輸入與假設!$C$225) -> 130.06816
A96: 錨定×倍數｜EV/EBITDA 腿｜4.5x | B96: 4.5 | C96: =MAX(0,((INDEX(損益!$D$22:$G$22,1,1)-INDEX(輸入與假設!$D$83:$G$83,1,1))*$B96+INDEX(輸入與假設!$D$83:$G$83,1,1)*輸入與假設!$C$204-(INDEX(各期收支!$D$94:$G$94,1,1)-INDEX(各期收支!$D$52:$G$52,1,1)+評價_DCF與目標價!$C$71))/INDEX(損益!$D$24:$G$24,1,1))/(1+輸入與假設!$C$190)^(1-輸入與假設!$C$225) -> 144.20583 | D96: =MAX(0,((INDEX(損益!$D$22:$G$22,1,2)-INDEX(輸入與假設!$D$83:$G$83,1,2))*$B96+INDEX(輸入與假設!$D$83:$G$83,1,2)*輸入與假設!$C$204-(INDEX(各期收支!$D$94:$G$94,1,2)-INDEX(各期收支!$D$52:$G$52,1,2)+評價_DCF與目標價!$C$71))/INDEX(損益!$D$24:$G$24,1,2))/(1+輸入與假設!$C$190)^(2-輸入與假設!$C$225) -> 164.22002 | E96: =MAX(0,((INDEX(損益!$D$22:$G$22,1,3)-INDEX(輸入與假設!$D$83:$G$83,1,3))*$B96+INDEX(輸入與假設!$D$83:$G$83,1,3)*輸入與假設!$C$204-(INDEX(各期收支!$D$94:$G$94,1,3)-INDEX(各期收支!$D$52:$G$52,1,3)+評價_DCF與目標價!$C$71))/INDEX(損益!$D$24:$G$24,1,3))/(1+輸入與假設!$C$190)^(3-輸入與假設!$C$225) -> 159.30639 | F96: =MAX(0,((INDEX(損益!$D$22:$G$22,1,4)-INDEX(輸入與假設!$D$83:$G$83,1,4))*$B96+INDEX(輸入與假設!$D$83:$G$83,1,4)*輸入與假設!$C$204-(INDEX(各期收支!$D$94:$G$94,1,4)-INDEX(各期收支!$D$52:$G$52,1,4)+評價_DCF與目標價!$C$71))/INDEX(損益!$D$24:$G$24,1,4))/(1+輸入與假設!$C$190)^(4-輸入與假設!$C$225) -> 144.4809
A97: 錨定×倍數｜EV/EBITDA 腿｜5.0x | B97: 5 | C97: =MAX(0,((INDEX(損益!$D$22:$G$22,1,1)-INDEX(輸入與假設!$D$83:$G$83,1,1))*$B97+INDEX(輸入與假設!$D$83:$G$83,1,1)*輸入與假設!$C$204-(INDEX(各期收支!$D$94:$G$94,1,1)-INDEX(各期收支!$D$52:$G$52,1,1)+評價_DCF與目標價!$C$71))/INDEX(損益!$D$24:$G$24,1,1))/(1+輸入與假設!$C$190)^(1-輸入與假設!$C$225) -> 150.65689 | D97: =MAX(0,((INDEX(損益!$D$22:$G$22,1,2)-INDEX(輸入與假設!$D$83:$G$83,1,2))*$B97+INDEX(輸入與假設!$D$83:$G$83,1,2)*輸入與假設!$C$204-(INDEX(各期收支!$D$94:$G$94,1,2)-INDEX(各期收支!$D$52:$G$52,1,2)+評價_DCF與目標價!$C$71))/INDEX(損益!$D$24:$G$24,1,2))/(1+輸入與假設!$C$190)^(2-輸入與假設!$C$225) -> 172.46418 | E97: =MAX(0,((INDEX(損益!$D$22:$G$22,1,3)-INDEX(輸入與假設!$D$83:$G$83,1,3))*$B97+INDEX(輸入與假設!$D$83:$G$83,1,3)*輸入與假設!$C$204-(INDEX(各期收支!$D$94:$G$94,1,3)-INDEX(各期收支!$D$52:$G$52,1,3)+評價_DCF與目標價!$C$71))/INDEX(損益!$D$24:$G$24,1,3))/(1+輸入與假設!$C$190)^(3-輸入與假設!$C$225) -> 167.14722 | F97: =MAX(0,((INDEX(損益!$D$22:$G$22,1,4)-INDEX(輸入與假設!$D$83:$G$83,1,4))*$B97+INDEX(輸入與假設!$D$83:$G$83,1,4)*輸入與假設!$C$204-(INDEX(各期收支!$D$94:$G$94,1,4)-INDEX(各期收支!$D$52:$G$52,1,4)+評價_DCF與目標價!$C$71))/INDEX(損益!$D$24:$G$24,1,4))/(1+輸入與假設!$C$190)^(4-輸入與假設!$C$225) -> 151.03215
A98: 錨定×倍數｜EV/EBITDA 腿｜6.0x | B98: 6 | C98: =MAX(0,((INDEX(損益!$D$22:$G$22,1,1)-INDEX(輸入與假設!$D$83:$G$83,1,1))*$B98+INDEX(輸入與假設!$D$83:$G$83,1,1)*輸入與假設!$C$204-(INDEX(各期收支!$D$94:$G$94,1,1)-INDEX(各期收支!$D$52:$G$52,1,1)+評價_DCF與目標價!$C$71))/INDEX(損益!$D$24:$G$24,1,1))/(1+輸入與假設!$C$190)^(1-輸入與假設!$C$225) -> 163.55899 | D98: =MAX(0,((INDEX(損益!$D$22:$G$22,1,2)-INDEX(輸入與假設!$D$83:$G$83,1,2))*$B98+INDEX(輸入與假設!$D$83:$G$83,1,2)*輸入與假設!$C$204-(INDEX(各期收支!$D$94:$G$94,1,2)-INDEX(各期收支!$D$52:$G$52,1,2)+評價_DCF與目標價!$C$71))/INDEX(損益!$D$24:$G$24,1,2))/(1+輸入與假設!$C$190)^(2-輸入與假設!$C$225) -> 188.95249 | E98: =MAX(0,((INDEX(損益!$D$22:$G$22,1,3)-INDEX(輸入與假設!$D$83:$G$83,1,3))*$B98+INDEX(輸入與假設!$D$83:$G$83,1,3)*輸入與假設!$C$204-(INDEX(各期收支!$D$94:$G$94,1,3)-INDEX(各期收支!$D$52:$G$52,1,3)+評價_DCF與目標價!$C$71))/INDEX(損益!$D$24:$G$24,1,3))/(1+輸入與假設!$C$190)^(3-輸入與假設!$C$225) -> 182.82887 | F98: =MAX(0,((INDEX(損益!$D$22:$G$22,1,4)-INDEX(輸入與假設!$D$83:$G$83,1,4))*$B98+INDEX(輸入與假設!$D$83:$G$83,1,4)*輸入與假設!$C$204-(INDEX(各期收支!$D$94:$G$94,1,4)-INDEX(各期收支!$D$52:$G$52,1,4)+評價_DCF與目標價!$C$71))/INDEX(損益!$D$24:$G$24,1,4))/(1+輸入與假設!$C$190)^(4-輸入與假設!$C$225) -> 164.13464
A99: 錨定×倍數｜EV/EBITDA 腿｜7.0x | B99: 7 | C99: =MAX(0,((INDEX(損益!$D$22:$G$22,1,1)-INDEX(輸入與假設!$D$83:$G$83,1,1))*$B99+INDEX(輸入與假設!$D$83:$G$83,1,1)*輸入與假設!$C$204-(INDEX(各期收支!$D$94:$G$94,1,1)-INDEX(各期收支!$D$52:$G$52,1,1)+評價_DCF與目標價!$C$71))/INDEX(損益!$D$24:$G$24,1,1))/(1+輸入與假設!$C$190)^(1-輸入與假設!$C$225) -> 176.46109 | D99: =MAX(0,((INDEX(損益!$D$22:$G$22,1,2)-INDEX(輸入與假設!$D$83:$G$83,1,2))*$B99+INDEX(輸入與假設!$D$83:$G$83,1,2)*輸入與假設!$C$204-(INDEX(各期收支!$D$94:$G$94,1,2)-INDEX(各期收支!$D$52:$G$52,1,2)+評價_DCF與目標價!$C$71))/INDEX(損益!$D$24:$G$24,1,2))/(1+輸入與假設!$C$190)^(2-輸入與假設!$C$225) -> 205.44081 | E99: =MAX(0,((INDEX(損益!$D$22:$G$22,1,3)-INDEX(輸入與假設!$D$83:$G$83,1,3))*$B99+INDEX(輸入與假設!$D$83:$G$83,1,3)*輸入與假設!$C$204-(INDEX(各期收支!$D$94:$G$94,1,3)-INDEX(各期收支!$D$52:$G$52,1,3)+評價_DCF與目標價!$C$71))/INDEX(損益!$D$24:$G$24,1,3))/(1+輸入與假設!$C$190)^(3-輸入與假設!$C$225) -> 198.51053 | F99: =MAX(0,((INDEX(損益!$D$22:$G$22,1,4)-INDEX(輸入與假設!$D$83:$G$83,1,4))*$B99+INDEX(輸入與假設!$D$83:$G$83,1,4)*輸入與假設!$C$204-(INDEX(各期收支!$D$94:$G$94,1,4)-INDEX(各期收支!$D$52:$G$52,1,4)+評價_DCF與目標價!$C$71))/INDEX(損益!$D$24:$G$24,1,4))/(1+輸入與假設!$C$190)^(4-輸入與假設!$C$225) -> 177.23713
A101: OCI 倍數 ＼ 錨定（加權目標價） | B101: 倍數 | C101: FY28 | D101: FY29 | E101: FY30 | F101: FY31
A102: 錨定×倍數｜加權目標價｜3.4x | B102: 3.4 | C102: =C48*IF(C30=1,0,輸入與假設!$C$206)+C95*IF(C30=1,1,1-輸入與假設!$C$206) -> 101.48855 | D102: =C48*IF(C30=1,0,輸入與假設!$C$206)+D95*IF(C30=1,1,1-輸入與假設!$C$206) -> 110.32669 | E102: =C48*IF(C30=1,0,輸入與假設!$C$206)+E95*IF(C30=1,1,1-輸入與假設!$C$206) -> 108.11222 | F102: =C48*IF(C30=1,0,輸入與假設!$C$206)+F95*IF(C30=1,1,1-輸入與假設!$C$206) -> 101.5186
A103: 錨定×倍數｜加權目標價｜4.5x | B103: 4.5 | C103: =C48*IF(C30=1,0,輸入與假設!$C$206)+C96*IF(C30=1,1,1-輸入與假設!$C$206) -> 109.29432 | D103: =C48*IF(C30=1,0,輸入與假設!$C$206)+D96*IF(C30=1,1,1-輸入與假設!$C$206) -> 120.30212 | E103: =C48*IF(C30=1,0,輸入與假設!$C$206)+E96*IF(C30=1,1,1-輸入與假設!$C$206) -> 117.59962 | F103: =C48*IF(C30=1,0,輸入與假設!$C$206)+F96*IF(C30=1,1,1-輸入與假設!$C$206) -> 109.44561
A104: 錨定×倍數｜加權目標價｜5.0x | B104: 5 | C104: =C48*IF(C30=1,0,輸入與假設!$C$206)+C97*IF(C30=1,1,1-輸入與假設!$C$206) -> 112.8424 | D104: =C48*IF(C30=1,0,輸入與假設!$C$206)+D97*IF(C30=1,1,1-輸入與假設!$C$206) -> 124.83641 | E104: =C48*IF(C30=1,0,輸入與假設!$C$206)+E97*IF(C30=1,1,1-輸入與假設!$C$206) -> 121.91208 | F104: =C48*IF(C30=1,0,輸入與假設!$C$206)+F97*IF(C30=1,1,1-輸入與假設!$C$206) -> 113.04879
A105: 錨定×倍數｜加權目標價｜6.0x | B105: 6 | C105: =C48*IF(C30=1,0,輸入與假設!$C$206)+C98*IF(C30=1,1,1-輸入與假設!$C$206) -> 119.93855 | D105: =C48*IF(C30=1,0,輸入與假設!$C$206)+D98*IF(C30=1,1,1-輸入與假設!$C$206) -> 133.90498 | E105: =C48*IF(C30=1,0,輸入與假設!$C$206)+E98*IF(C30=1,1,1-輸入與假設!$C$206) -> 130.53699 | F105: =C48*IF(C30=1,0,輸入與假設!$C$206)+F98*IF(C30=1,1,1-輸入與假設!$C$206) -> 120.25516
A106: 錨定×倍數｜加權目標價｜7.0x | B106: 7 | C106: =C48*IF(C30=1,0,輸入與假設!$C$206)+C99*IF(C30=1,1,1-輸入與假設!$C$206) -> 127.03471 | D106: =C48*IF(C30=1,0,輸入與假設!$C$206)+D99*IF(C30=1,1,1-輸入與假設!$C$206) -> 142.97355 | E106: =C48*IF(C30=1,0,輸入與假設!$C$206)+E99*IF(C30=1,1,1-輸入與假設!$C$206) -> 139.1619 | F106: =C48*IF(C30=1,0,輸入與假設!$C$206)+F99*IF(C30=1,1,1-輸入與假設!$C$206) -> 127.46153

Sheet 評價_反向DCF
A1: 反向 DCF — 現價隱含什麼樣的收入與成本
A2: 不是問「值多少」，而是問「要值現價，營運要長什麼樣」。Excel 以『目標搜尋』反解；下方另附 HTML 即時計算結果的快照（v4.0 預設輸入）
A4: 即時：目前 DCF 與現價的差距
A5: 現價 | B5: =輸入與假設!$C$175 -> 144.77
A6: 目前 DCF 每股（依下限方式） | B6: =評價_DCF與目標價!C26 -> 59.219845
A7: 差距（DCF − 現價）＝目標搜尋的『設定儲存格』 | B7: =B6-B5 -> -85.550155
A8: 目前每 MW 年收入倍數／建置成本倍數 | B8: =輸入與假設!$C$39 -> 1 | C8: =輸入與假設!$C$107 -> 1
A10: 操作：用『目標搜尋』反解（資料 → 模擬分析 → 目標搜尋）
A11: ① 設定儲存格：本頁 B7；目標值：0
A12: ② 變數儲存格（擇一）：輸入與假設 B 區『每 MW 年收入倍數』→ 市價隱含單價；或 D 區『每 MW 建置成本倍數』→ 市價隱含建置成本；或 C 區『穩態 EBITDA 率』
A13: ③ 解完請記下結果，再把倍數改回 100%（或按 Ctrl+Z）。DCF 以 0 截斷時，負值區域斜率為 0，請從 100% 以上開始搜尋
A14: ④ 組合分析：先把 D 區建置成本倍數與 C 區穩態 EBITDA 率設為想測的值，再對『每 MW 年收入倍數』做目標搜尋，即得下方矩陣中的一格
A16: 快照：單一槓桿（HTML v4.0 預設輸入，DCF 0 截斷）
A17: 單一槓桿（其他不變） | B17: 目前 | C17: 市價隱含 | D17: 變動 | G17: 對照
A18: FY31 每 MW 年收入（US$m） | B18: 17.4 | C18: 24.3872 | D18: 0.4016 | G18: Oracle 對照：OCI 年化 ÷ 新增 MW 14.4、OpenAI 合約隱含 13.3（MW 口徑不明）
A19: 每 MW 建置成本（US$m） | B19: 37.59 | C19: 14.8903 | D19: -0.6039 | G19: FY27 指引 90–95 ÷ 估計新增 MW-IT 約 2,800 ≈ $32–34m（含客戶自帶硬體效果）
A20: 穩態 EBITDA 率（FY31） | B20: 0.47 | C20: 0.7625 | D20: 0.2925 | G20: OCI（算力）EBITDA 率；傳統事業 EBITDA 率固定不動。可觀察 neocloud 區間 IREN 約 35%、CRWV 約 59%（變動為百分點）
A21: （對照）加權目標價＝現價所需每 MW 年收入 | B21: 17.4 | C21: 18.3486 | D21: 0.0545 | G21: 含 EV/EBITDA 腿（FY29 錨定）；非純反向 DCF
A23: 快照：收入與成本的綜合影響——要值現價，FY31 每 MW 年收入需要多少（US$m）
A24: 建置成本 ＼ 穩態 EBITDA 率 | B24: 0.35 | C24: 0.47 | D24: 0.59 | E24: 0.7 | I24: 矩陣保留 OCI EBITDA 率維度：傳統事業（約 54% EBITDA 率、軟體同業倍數）不隨此表變動，表內只測算力業務的單位經濟
A25: $26.3m（-30%） | B25: 24.84 | C25: 20.74 | D25: 17.81 | E25: 15.77
A26: $30.1m（-20%） | B26: 26.15 | C26: 21.84 | D26: 18.75 | E26: 16.6
A27: $33.8m（-10%） | B27: 27.61 | C27: 23.06 | D27: 19.8 | E27: 17.53
A28: $37.6m（目前） | B28: 29.2 | C28: 24.39 | D28: 20.94 | E28: 18.53
A29: $41.3m（+10%） | B29: 30.79 | C29: 25.71 | D29: 22.08 | E29: 19.54
A30: 快照為靜態數值（HTML 以同一引擎即時計算）；改變輸入後請以目標搜尋重算，或參考 HTML『評價 → 反向 DCF』

Sheet 評價_可比公司
A1: 可比公司 — 以 EV/Sales 為主（市值：2026-09-21 收盤）
A2: EV＝市值＋（有息負債−非受限現金）；含租賃＝EV＋營業租賃負債。EV/EBITDA 僅供參考（GAAP EBITDA 為負者顯示 n/m）。此表不進入目標價。與 HTML Comps 分頁同一組數字
A4: 公司 | B4: 市值 | C4: 淨負債 | D4: EV | E4: TTM 營收 | F4: EV/Sales（TTM） | G4: 含租賃 EV/Sales | H4: TTM EBITDA | I4: EV/EBITDA | J4: 資料期 | K4: 備註
A5: CRWV CoreWeave | B5: 49.11 | C5: 46.03 | D5: =B5+C5 -> 95.14 | E5: 7.59 | F5: =D5/E5 -> 12.534914 | G5: =(D5+16.54)/E5 -> 14.714097 | H5: =-0.231+3.991 -> 3.76 | I5: =IF(H5>0,D5/H5,"n/m") -> 25.303191 | J5: TTM 至 Q2（6/30，10-Q）；市值與 EV 2026-10-07 | K5: 營業租賃負債 16.54；GAAP 營業損益 -0.231＋D&A 3.991。CRWV 市值與 EV 2026-10-07；TTM 至 Q2；租賃負債 16.54
A6: NBIS Nebius | B6: 68.49 | C6: 2.15 | D6: =B6+C6 -> 70.64 | E6: 1.36 | F6: =D6/E6 -> 51.941176 | G6: =(D6+1.6253)/E6 -> 53.13625 | H6: =-0.612+0.418 -> -0.194 | I6: =IF(H6>0,D6/H6,"n/m") -> n/m | J6: 營收 TTM 至 Q2；營業損益與 D&A 為 FY2025（20-F）；市值與 EV 2026-10-06 | K6: 營業租賃負債 1.6253；GAAP 營業損益 -0.612＋D&A 0.418。NBIS 市值與 EV 2026-10-06；EBITDA 用 FY2025
A7: IREN | B7: 18.61 | C7: 1.7 | D7: =B7+C7 -> 20.31 | E7: 0.707 | F7: =D7/E7 -> 28.727016 | G7: =(D7+0.003)/E7 -> 28.731259 | H7: =-1.047+0.418 -> -0.629 | I7: =IF(H7>0,D7/H7,"n/m") -> n/m | J7: FY26 10-K（6/30）；未更新，日期 2026-09-21 | K7: 營業租賃負債 0.003；GAAP 營業損益 -1.047＋D&A 0.418。自有電廠、營業租賃負債僅 0.003bn；FY26 合約 ARR 4.0bn
A8: APLD Applied Digital | B8: 8.22 | C8: 3.37 | D8: =B8+C8 -> 11.59 | E8: 0.6113 | F8: =D8/E8 -> 18.959594 | G8: =(D8+0.066)/E8 -> 19.067561 | H8: =-0.236+0.067 -> -0.169 | I8: =IF(H8>0,D8/H8,"n/m") -> n/m | J8: FY26 10-K（5/31）；未更新，日期 2026-09-21 | K8: 營業租賃負債 0.066；GAAP 營業損益 -0.236＋D&A 0.067。租約多未起租，營收尚未反映約 36bn 合約
A9: CORZ Core Scientific | B9: 5.9 | C9: 2.53 | D9: =B9+C9 -> 8.43 | E9: 0.4403 | F9: =D9/E9 -> 19.146037 | G9: =(D9+0.109)/E9 -> 19.393595 | H9: =-0.561+0.063 -> -0.498 | I9: =IF(H9>0,D9/H9,"n/m") -> n/m | J9: TTM 至 Q2（6/30）；未更新，日期 2026-09-21 | K9: 營業租賃負債 0.109；GAAP 營業損益 -0.561＋D&A 0.063。託管轉型期
A10: 同業中位數 | F10: =MEDIAN(F5:F9) -> 19.146037 | G10: =MEDIAN(G5:G9) -> 19.393595
A11: ORCL（TTM 至 Q1 2027） | B11: 437.75 | C11: =輸入與假設!$C$177+SUMPRODUCT(資產負債_既有債務!$C$73:$C$73*(1-資產負債_既有債務!$H$69:$H$69))+輸入與假設!$C$179 -> 88.827 | D11: =B11+C11 -> 526.577 | E11: 71.777 | F11: =D11/E11 -> 7.3362916 | G11: =(D11+34.621)/E11 -> 7.8186327 | H11: =23.056+10.881 -> 33.937 | I11: =IF(H11>0,D11/H11,"n/m") -> 15.51631 | J11: TTM 至 Q1 2027 | K11: EV 用 2026-09-21 市值（基本股）與評價日淨負債（可轉債全數以到期本金計入）；含租賃再加營業租賃負債 34.621
A12: ORCL 模型 FY28E | B12: =輸入與假設!$C$175*評價_DCF與目標價!$C$69 -> 447.19081 | C12: =評價_DCF與目標價!$C$70 -> 88.827 | D12: =B12+C12 -> 536.01781 | E12: =損益!D9 -> 125.38525 | F12: =D12/E12 -> 4.2749671 | G12: =(D12+34.621)/E12 -> 4.5510841 | H12: =損益!D22 -> 73.113611 | I12: =D12/H12 -> 7.3312999 | K12: 市值用評價股數（含價內可轉債轉股）、淨負債用評價淨負債；分母為模型 FY28 營收
A14: 讀法：ORCL 為整體公司（傳統軟體＋OCI），倍數不可直接與純 AI 基礎設施同業比較；
A15: CRWV 以租約取得機房，加入營業租賃負債後倍數上升；ORCL 同樣以租賃為主（未起租承諾 288B 尚未入表）。
A16: 前瞻：見下方 ORCL 模型列。此表為市場比較用，不進入目標價。

Sheet 檢查_連動
A1: 連動檢查 — 恆等式與口徑
A3: 檢查項目 | B3: 實際值 | C3: 標準 | D3: 結果 | E3: 說明
A4: RPO 桶權重合計 | B4: =SUM(輸入與假設!C42:G42) -> 0.7975 | C4: =輸入與假設!$C$34 -> 0.7975 | D4: =IF(ABS(B4-C4)<0.0001,"通過","不一致") -> 通過 | E4: 季報桶線性分攤後應為 79.75%
A5: 現金橋差異 | B5: =各期收支!C108 -> 0 | C5: =0 -> 0 | D5: =IF(ABS(B5)<0.01,"通過","不一致") -> 通過 | E5: 期初＋營運缺口＋股權＋額度−還本 ＝ 期末
A6: Billable ≤ Accepted（FY31） | B6: =運營_產能與收入!G9-運營_產能與收入!G10 -> 708 | C6: ≥0 | D6: =IF(B6>=0,"通過","不一致") -> 通過 | E6: 引擎已以 MIN 截斷；此列驗證截斷有效
A7: FY27 CapEx 認列 vs 指引 | B7: =各期收支!C112 -> 106.09585 | C7: 90–95 | D7: =IF(AND(B7>=90,B7<=95),"通過","觀察") -> 觀察 | E7: 1Q 實際認列 28.499＋2Q–4Q 模型；全年指引 90–95（法說會轉述）
A8: FY27 營收 vs 指引 | B8: =各期收支!C111 -> 87.49762 | C8: ≥90 | D8: =IF(B8>=90,"通過","觀察") -> 觀察 | E8: 1Q 實際 19.345＋2Q–4Q 模型（算力＋非算力服務）
A9: CapEx 強度（模型期合計） | B9: =SUM(各期收支!C6:G6)/((運營_產能與收入!G9-輸入與假設!$C$36)/1000)/1000*1000 -> 47.077221 | C9: $28–51m/MW | D9: =IF(AND(B9>=28,B9<=51),"通過","觀察") -> 通過 | E9: Tokenomics IF_CapexTotal 低／高成本情境（GB300 38.8–67.1 US$m/MW-IT）
A10: 表外租金路徑 ÷ 已承諾 | B10: =資產負債_租賃承諾!C23 -> 1 | C10: ≥0.8x | D10: =IF(B10>=0.8,"通過","不一致") -> 通過 | E10: 表外租金路徑對已簽約未起租租賃
A11: FY27 利息（1Q 實際＋2Q–4Q） | B11: =各期收支!C113 -> 6.3948427 | C11: ≥1.4 | D11: =IF(B11>=1.4,"通過","觀察") -> 通過 | E11: ="1Q 實際 1.428＋2Q–4Q 模型 "&TEXT(各期收支!C17,"0.0")&"；公司未提供季度利息指引（不適用）" -> 1Q 實際 1.428＋2Q–4Q 模型 4.5；公司未提供季度利息指引（不適用）
A12: FY29 起收入是否依賴未簽約 | B12: =SUM(運營_產能與收入!E24:G24)/SUM(運營_產能與收入!E26:G26) -> 0.11661697 | C12: <50% 較穩健 | D12: =IF(B12<0.5,"通過","觀察") -> 通過 | E12: FY29–FY31 超出期初 RPO 的收入 ÷ 同期總算力收入（MW 驅動下為未簽約產能的比重）
A13: 損益營收＝資金營收 | B13: =損益!D6-運營_產能與收入!D26 -> 0 | C13: =0 -> 0 | D13: =IF(ABS(B13)<0.001,"通過","不一致") -> 通過 | E13: FY28 損益算力收入 − 產能頁 isRev。兩邊必須同一組數字
A14: 終值占 EV 比重 | B14: =評價_DCF與目標價!C27 -> 0.8064524 | C14: ="<"&IF(ROUND(ABS(輸入與假設!$C$237)*100,4)=INT(ROUND(ABS(輸入與假設!$C$237)*100,4)),TEXT(ROUND(ABS(輸入與假設!$C$237)*100,4),"0"),TEXT(ROUND(ABS(輸入與假設!$C$237)*100,4),"0.0"))&"%" -> <85% | D14: =IF(B14<輸入與假設!$C$237,"通過","觀察") -> 通過 | E14: 過高表示結論由終值假設決定
A15: EBITDA 單一來源（FY28 算力＋服務 EBITDA÷營收 − 輸入 EBITDA 率） | B15: =(損益!D22+損益!D11-輸入與假設!D83-輸入與假設!D51)/(損益!D6+損益!D7)-輸入與假設!D93 -> 0 | C15: =0 -> 0 | D15: =IF(ABS(B15)<0.0001,"通過","不一致") -> 通過 | E15: 損益與資金引用同一列 EBITDA 率
A16: 現金 EBITDA ＋ 信用調整 − 損益 EBITDA（FY28） | B16: =(運營_產能與收入!D40+運營_產能與收入!D41+輸入與假設!D94+輸入與假設!D51+輸入與假設!D83-運營_產能與收入!D62-各期收支!D16)+(運營_產能與收入!D35+運營_產能與收入!D24*輸入與假設!D48*(1-輸入與假設!D49))*運營_產能與收入!D39-損益!D22 -> 0 | C16: =0 -> 0 | D16: =IF(ABS(B16)<0.001,"通過","不一致") -> 通過 | E16: 現金 EBITDA＝RPO 現金＋新簽約現金＋服務現金−租金；信用調整＝信用損失×EBITDAR 率
A17: DCF 有效性（1＝失效） | B17: =評價_DCF與目標價!C30 -> 0 | C17: 0 | D17: =IF(B17=0,"通過","觀察") -> 通過 | E17: 失效只定義為 WACC ≤ g 或常態化 FCF ≤ 0；股權為負不算失效
A18: 期末現金 ≥ 最低現金（期前融資） | B18: =MIN(各期收支!C52:G52) -> 10 | C18: ≥10.0 | D18: =IF(B18>=9.999,"通過","不一致") -> 通過 | E18: 瀑布每期補足至最低現金；最小值應等於最低現金
A19: 股權募資 ÷ 現市值 | B19: =SUM(各期收支!C84:G84)/(輸入與假設!$C$175*輸入與假設!$C$176) -> 0 | C19: ="≤"&IF(輸入與假設!$C$234=INT(輸入與假設!$C$234),TEXT(輸入與假設!$C$234,"0"),TEXT(輸入與假設!$C$234,"0.0"))&"x" -> ≤1.5x | D19: =IF(B19<=輸入與假設!$C$234,"通過","觀察") -> 通過 | E19: ="超過 "&IF(輸入與假設!$C$234=INT(輸入與假設!$C$234),TEXT(輸入與假設!$C$234,"0"),TEXT(輸入與假設!$C$234,"0.0"))&" 倍：市場吸收能力存疑，結論不得為買進" -> 超過 1.5 倍：市場吸收能力存疑，結論不得為買進
A20: 債務明細合計 = 季報本金 125.904 − 以股換債 ＋ 期後新發 | B20: =資產負債_既有債務!E62+SUMPRODUCT(資產負債_既有債務!$C$73:$C$73*(1-資產負債_既有債務!$H$69:$H$69)) -> 125.904 | C20: 125.904 | D20: =IF(ABS(B20-125.904)<0.01,"通過","不一致") -> 通過 | E20: 其他借款 57 筆＋可轉債 1 檔到期本金（company.json → debt.convertibleBridge）
A21: FY27 全年 CapEx（MW 公式） | B21: =輸入與假設!C127 -> 106.09585 | C21: 90–95 | D21: =IF(AND(B21>=90,B21<=95),"通過","觀察") -> 觀察 | E21: 由已連網 MW 增量與預建次年推得；指引只作對照
