Workbook

Sheet 導覽
A1: Oracle 收支與評價模型 — Excel 版 v0.1（更新 2026-10-08；與 HTML v0.1 同步；市價截至 2026-10-06 收盤）
A3: 這個活頁簿在回答什麼
A4: 一句話：客戶預付與投資級債能否把 $664B RPO 變成現金、而不需再發股——Oracle 用客戶預付款支應多少擴張資本支出，剩下的缺口要靠多少債務與新股。
A5: 所有分頁用同一組數字，改任何一個輸入，後面全部會跟著動。
A7: 分頁結構（依模組分組，分頁標籤顏色相同者為同一模組）
A8: 摘要 一頁摘要：結論、與市場共識的差異、現價隱含什麼、驗證點（全部活公式）。
A9: 輸入與假設 所有可調參數（A 情境 → B 產能與收入 → C 利潤率 → D 支出 → E 融資 → F 評價 → G 1Q 實際 → H 情境區間運算表 → I 市場共識 → J 季度追蹤輸入）。
A10: 各期收支 類現金流量：來源（含客戶預付）、用途、融資前缺口、期前融資瀑布。
A11: 季度追蹤 焦點季的模型／共識／指引／實際與差距（由年度模型拆分，只用於追蹤；實際數填在輸入與假設 J 區）。
A12: 運營_產能與收入 已連網 MW → 在役 MW → 營收（MW × 每 MW 年收入 × 利用率）；RPO 排程只作對照與產能瓶頸旗標。
A13: 資產負債_既有債務／新債與新股／租賃承諾 類資產負債表：季報債務明細、每期現金與總債務與股數、租賃承諾。
A14: 損益 類損益表（FY27＝1Q 實際＋第 2–4 季模型）。
... A42: DCF 以融資後股數計每股，並加回新股募得現金的現值；EV/EBITDA 用錨定年末淨負債與錨定年末股數。

Sheet 摘要
A1: 一頁摘要 — 結論、與市場的差異、現價隱含什麼、驗證點（全部依輸入連動）
A2: ="模型端＝目前情境：" & CHOOSE(輸入與假設!$C$5,"保守 OpenAI 相關 60%","基準 已簽約站點依 Q1 速度","積極 依公司時程") & "（預設＝基準）；共識＝data/consensus_orcl_20261007.json（2026-10-07）" -> 模型端＝目前情境：基準 已簽約站點依 Q1 速度（預設＝基準）；共識＝data/consensus_orcl_20261007.json（2026-10-07）
A4: 1｜結論
A5: 結論｜評等代碼（1＝買進、0＝中立、−1＝賣出） | C5: =評價_DCF與目標價!C78 -> 0
A6: 結論｜評等 | C6: =CHOOSE(C5+2,"賣出","中立","買進") -> 中立
A7: 結論｜點位（加權目標價） | B7: US$ | C7: =評價_DCF與目標價!C51 -> 144.52663
A8: 結論｜現價 | B8: US$ | C8: =輸入與假設!$C$175 -> 144.77
A9: 結論｜空間 | B9: % | C9: =C7/C8-1 -> -0.0016810932
A10: 結論｜情境區間（下緣／上緣） | B10: US$ | C10: =評價_DCF與目標價!C83 -> 79.79295 | D10: =評價_DCF與目標價!D83 -> 226.60959
A11: 結論｜方法區間（下緣／上緣） | B11: US$ | C11: =評價_DCF與目標價!C85 -> 134.537 | D11: =評價_DCF與目標價!D85 -> 144.52663
A12: 結論｜賣出門檻價 | B12: US$ | C12: =評價_DCF與目標價!$C$79 -> 123.0545
A13: 結論｜點位 − 賣出門檻 | B13: US$ | C13: =C7-C12 -> 21.472128
A14: 結論｜結論句 | C14: =C6&"：點位 $"&TEXT(C7,"0.0")&"，較現價 $"&TEXT(C8,"0.00")&" "&IF(C9>=0,"高","低")&" "&TEXT(ABS(C9)*100,"0")&"%；情境區間 $"&TEXT(C10,"0.0")&"–$"&TEXT(D10,"0.0")&"，方法區間 $"&TEXT(C11,"0.0")&"–$"&TEXT(D11,"0.0")&"；點位"&IF(C13<0,"低於","高於")&"賣出門檻 $"&TEXT(C12,"0.0")&" 達 $"&TEXT(ABS(C13),"0.0")&"。" -> 中立：點位 $144.5，較現價 $144.77 低 0%；情境區間 $79.8–$226.6，方法區間 $134.5–$144.5；點位高於賣出門檻 $123.1 達 $21.5。
A15: 結論｜情境判斷句 | C15: =評價_DCF與目標價!C91 -> 情境區間上緣 $226.6 不低於現價 $144.77：賣出並非在三個擴張情境下都成立。
A16: 結論｜投資級句 | C16: =IF(輸入與假設!$C$146="ebitda","需失去投資級才能融資的金額："&IF(SUM(各期收支!C77:G77)>0.05,"$"&TEXT(SUM(各期收支!C77:G77),"0.0")&"bn（五期高息債溢出）","$0")&"；投資級上限＝總債務 ≤ "&IF(輸入與假設!$C$147=INT(輸入與假設!$C$147),TEXT(輸入與假設!$C$147,"0"),TEXT(輸入與假設!$C$147,"0.0"))&"× 當期 EBITDA，股權每年 ≤ 現市值 "&IF(ROUND(ABS(輸入與假設!$C$154)*100,4)=INT(ROUND(ABS(輸入與假設!$C$154)*100,4)),TEXT(ROUND(ABS(輸入與假設!$C$154)*100,4),"0"),TEXT(ROUND(ABS(輸入與假設!$C$154)*100,4),"0.0"))&"%"&"。","") -> 需失去投資級才能融資的金額：$0；投資級上限＝總債務 ≤ 4× 當期 EBITDA，股權每年 ≤ 現市值 5%。
A18: 2｜與市場的差異（模型：目前情境 vs 共識；FY27–FY29）
A19: 項目 | B19: 單位 | C19: FY27 | D19: FY28 | E19: FY29
A20: 差異｜營收｜模型 | B20: US$bn | C20: =損益!C28 -> 90.727495 | D20: =損益!D28 -> 136.55822 | E20: =損益!E28 -> 178.14101
A21: 差異｜營收｜共識 | B21: US$bn | C21: =輸入與假設!$C$289 -> 90.449 | D21: =輸入與假設!$D$289 -> 131.711 | E21: =輸入與假設!$E$289 -> 183.569
A22: 差異｜營收｜差距 | B22: % | C22: =C20/C21-1 -> 0.0030790257 | D22: =D20/D21-1 -> 0.036801953 | E22: =E20/E21-1 -> -0.0295692
A23: 差異｜調整後 EBITDA｜模型 | B23: US$bn | C23: =輸入與假設!$C$260+損益!C21 -> 53.523364 | D23: =損益!D33 -> 81.175537 | E23: =損益!E33 -> 100.64384
A24: 差異｜調整後 EBITDA｜共識 | B24: US$bn | C24: =輸入與假設!$C$290 -> 51.664 | D24: =輸入與假設!$D$290 -> 74.642 | E24: =輸入與假設!$E$290 -> 107.543
A25: 差異｜調整後 EBITDA｜差距 | B25: % | C25: =C23/C24-1 -> 0.035989545 | D25: =D23/D24-1 -> 0.087531648 | E25: =E23/E24-1 -> -0.064152529 | I25: FY27 模型＝1Q 實際調整後 EBITDA（輸入與假設 G 區，報導轉述 [Verified]）＋2Q–4Q 模型
A26: 差異｜調整後 EBITDA｜差距（金額） | B26: US$bn | C26: =C23-C24 -> 1.8593639 | D26: =D23-D24 -> 6.5335373 | E26: =E23-E24 -> -6.8991555 | I26: 與 HTML 一頁摘要、市場共識分頁同一呈現；判斷門檻仍用上一列比例
A27: 差異｜EBITDA 率｜模型 | B27: % | C27: =C23/C20 -> 0.58993543 | D27: =D23/D20 -> 0.59443903 | E27: =E23/E20 -> 0.56496729
A28: 差異｜EBITDA 率｜共識 | B28: % | C28: =輸入與假設!$C$291 -> 0.5712 | D28: =輸入與假設!$D$291 -> 0.5667 | E28: =輸入與假設!$E$291 -> 0.5858
A29: 差異｜EBITDA 率｜差距（百分點） | B29: pt | C29: =C27-C28 -> 0.018735432 | D29: =D27-D28 -> 0.027739032 | E29: =E27-E28 -> -0.02083271 | I29: EBITDA 率以百分點列差距，不納入判斷
A30: 差異｜CapEx（毛額）｜模型 | B30: US$bn | C30: =輸入與假設!$C$243+輸入與假設!C$135 -> 106.09585 | D30: =輸入與假設!D$135 -> 86.020956 | E30: =輸入與假設!E$135 -> 31.20158
A31: 差異｜CapEx（毛額）｜共識 | B31: US$bn | C31: =輸入與假設!$C$296 -> 93.961 | D31: =輸入與假設!$D$296 -> 100.962 | E31: =輸入與假設!$E$296 -> 84.848
A32: 差異｜CapEx（毛額）｜差距 | B32: % | C32: =C30/C31-1 -> 0.12914773 | D32: =D30/D31-1 -> -0.14798681 | E32: =E30/E31-1 -> -0.632265 | I32: 共識 CapEx 口徑未揭露；FY27＝1Q 實際毛額＋2Q–4Q 模型毛額
A33: 差異｜淨負債｜模型 | B33: US$bn | C33: =資產負債_新債與新股!C24 -> 121.94049 | D33: =資產負債_新債與新股!D24 -> 133.97534 | E33: =資產負債_新債與新股!E24 -> 90.028634
A34: 差異｜淨負債｜共識 | B34: US$bn | C34: =輸入與假設!$C$298 -> 117.047 | D34: =輸入與假設!$D$298 -> 147.351 | E34: =輸入與假設!$E$298 -> 146.812
A35: 差異｜淨負債｜差距 | B35: % | C35: =C33/C34-1 -> 0.041807867 | D35: =D33/D34-1 -> -0.09077416 | E35: =E33/E34-1 -> -0.38677605 | I35: 共識淨負債不含租賃、口徑未揭露：只列不判斷
A36: 差異｜淨負債｜差距（金額） | B36: US$bn | C36: =C33-C34 -> 4.8934854 | D36: =D33-D34 -> -13.375663 | E36: =E33-E34 -> -56.783366 | I36: 與 HTML 一頁摘要、市場共識分頁同一呈現；判斷門檻仍用上一列比例
A37: 差異｜分歧項目（超過門檻者） | C37: =MID(IF(ABS(C22)>輸入與假設!$C$333,"、營收 "&IF(C22<0,"−","+")&TEXT(ABS(C22)*100,"0.0")&"%","")&IF(ABS(C25)>輸入與假設!$C$333,"、EBITDA "&IF(C26<0,"−","+")&"$"&TEXT(ABS(C26),"#,##0.00")&"bn"&"／"&IF(C29<0,"−","+")&TEXT(ABS(C29)*100,"0.0")&"pt","")&IF(ABS(C32)>輸入與假設!$C$333,"、CapEx "&IF(C32<0,"−","+")&TEXT(ABS(C32)*100,"0.0")&"%",""),2,999) -> CapEx +12.9% | D37: =MID(IF(ABS(D22)>輸入與假設!$C$333,"、營收 "&IF(D22<0,"−","+")&TEXT(ABS(D22)*100,"0.0")&"%","")&IF(ABS(D25)>輸入與假設!$C$333,"、EBITDA "&IF(D26<0,"−","+")&"$"&TEXT(ABS(D26),"#,##0.00")&"bn"&"／"&IF(D29<0,"−","+")&TEXT(ABS(D29)*100,"0.0")&"pt","")&IF(ABS(D32)>輸入與假設!$C$333,"、CapEx "&IF(D32<0,"−","+")&TEXT(ABS(D32)*100,"0.0")&"%",""),2,999) -> EBITDA +$6.53bn／+2.8pt、CapEx −14.8% | E37: =MID(IF(ABS(E22)>輸入與假設!$C$333,"、營收 "&IF(E22<0,"−","+")&TEXT(ABS(E22)*100,"0.0")&"%","")&IF(ABS(E25)>輸入與假設!$C$333,"、EBITDA "&IF(E26<0,"−","+")&"$"&TEXT(ABS(E26),"#,##0.00")&"bn"&"／"&IF(E29<0,"−","+")&TEXT(ABS(E29)*100,"0.0")&"pt","")&IF(ABS(E32)>輸入與假設!$C$333,"、CapEx "&IF(E32<0,"−","+")&TEXT(ABS(E32)*100,"0.0")&"%",""),2,999) -> EBITDA −$6.90bn／−2.1pt、CapEx −63.2% | I37: 營收、EBITDA、CapEx 任一項差距絕對值超過門檻即列出（與 HTML 判斷句同一規則）
A38: 差異｜分歧起始年（1＝FY27…3＝FY29；0＝無） | C38: =IF(C37<>"",1,IF(D37<>"",2,IF(E37<>"",3,0))) -> 1
A39: 差異｜判斷句 | C39: =CHOOSE(C38+1,"FY27–FY29 營收、EBITDA、CapEx 與共識差距皆在 "&IF(ROUND(ABS(輸入與假設!$C$333)*100,4)=INT(ROUND(ABS(輸入與假設!$C$333)*100,4)),TEXT(ROUND(ABS(輸入與假設!$C$333)*100,4),"0"),TEXT(ROUND(ABS(輸入與假設!$C$333)*100,4),"0.0"))&"%"&" 以內。","分歧始於 FY27（"&C37&"）"&"；FY28 "&IF(D37="","回到 "&IF(ROUND(ABS(輸入與假設!$C$333)*100,4)=INT(ROUND(ABS(輸入與假設!$C$333)*100,4)),TEXT(ROUND(ABS(輸入與假設!$C$333)*100,4),"0"),TEXT(ROUND(ABS(輸入與假設!$C$333)*100,4),"0.0"))&"%"&" 以內",D37)&"；FY29 "&IF(E37="","回到 "&IF(ROUND(ABS(輸入與假設!$C$333)*100,4)=INT(ROUND(ABS(輸入與假設!$C$333)*100,4)),TEXT(ROUND(ABS(輸入與假設!$C$333)*100,4),"0"),TEXT(ROUND(ABS(輸入與假設!$C$333)*100,4),"0.0"))&"%"&" 以內",E37)&"。","FY27 營收、EBITDA、CapEx 與共識差距在 "&IF(ROUND(ABS(輸入與假設!$C$333)*100,4)=INT(ROUND(ABS(輸入與假設!$C$333)*100,4)),TEXT(ROUND(ABS(輸入與假設!$C$333)*100,4),"0"),TEXT(ROUND(ABS(輸入與假設!$C$333)*100,4),"0.0"))&"%"&" 以內；分歧始於 FY28（"&D37&"）"&"；FY29 "&IF(E37="","回到 "&IF(ROUND(ABS(輸入與假設!$C$333)*100,4)=INT(ROUND(ABS(輸入與假設!$C$333)*100,4)),TEXT(ROUND(ABS(輸入與假設!$C$333)*100,4),"0"),TEXT(ROUND(ABS(輸入與假設!$C$333)*100,4),"0.0"))&"%"&" 以內",E37)&"。","FY27–FY28 營收、EBITDA、CapEx 與共識差距在 "&IF(ROUND(ABS(輸入與假設!$C$333)*100,4)=INT(ROUND(ABS(輸入與假設!$C$333)*100,4)),TEXT(ROUND(ABS(輸入與假設!$C$333)*100,4),"0"),TEXT(ROUND(ABS(輸入與假設!$C$333)*100,4),"0.0"))&"%"&" 以內；分歧始於 FY29（"&E37&"）。") -> 分歧始於 FY27（CapEx +12.9%）；FY28 EBITDA +$6.53bn／+2.8pt、CapEx −14.8%；FY29 EBITDA −$6.90bn／−2.1pt、CapEx −63.2%。
A40: 差異原因｜FY27｜營收 | C40: =IF(ABS(C22)>輸入與假設!$C$333,"觀點","") | D40: =IF(ABS(C22)>輸入與假設!$C$333,"營收＝OCI（在役 MW × 每 MW 年收入，Tokenomics 正向推導；年底已連網 "&IF((輸入與假設!C$43)<0,"−","")&TEXT(ABS((輸入與假設!C$43)),"#,##0")&" MW-IT）＋傳統事業四線（近四季年增率收斂）；共識未揭露 MW 假設","") | I40: C＝類型、D＝原因（需附原因時顯示；EBITDA 以利潤率差、其餘以比例門檻判斷）
A41: 差異原因｜FY27｜EBITDA | C41: =IF(ABS(C29)>輸入與假設!$C$334,"觀點","") | D41: =IF(ABS(C29)>輸入與假設!$C$334,"營收差距 "&IF((C22)<0,"−","+")&TEXT(ABS((C22))*100,"#,##0.0")&"%"&"；EBITDA 率 "&IF((C27)<0,"−","")&TEXT(ABS((C27))*100,"#,##0.0")&"%"&" 對共識 "&IF((C28)<0,"−","")&TEXT(ABS((C28))*100,"#,##0.0")&"%"&"（OCI EBITDA 率由 "&IF((輸入與假設!$C$87)<0,"−","")&TEXT(ABS((輸入與假設!$C$87))*100,"#,##0")&"%"&" 走向穩態 "&IF((輸入與假設!$C$88)<0,"−","")&TEXT(ABS((輸入與假設!$C$88))*100,"#,##0")&"%"&"，取可觀察 neocloud 區間）","")
A42: 差異原因｜FY27｜CapEx | C42: =IF(ABS(C32)>輸入與假設!$C$333,"觀點","") -> 觀點 | D42: =IF(ABS(C32)>輸入與假設!$C$333,"CapEx 依新增 MW 計算：新增 "&IF((輸入與假設!C$125)<0,"−","")&TEXT(ABS((輸入與假設!C$125)),"#,##0")&" MW × 每 MW $"&IF((輸入與假設!C$109)<0,"−","")&TEXT(ABS((輸入與假設!C$109)),"#,##0")&"m（IT 設備，含次年預建）；客戶自帶硬體不建模；共識口徑未揭露","") -> CapEx 依新增 MW 計算：新增 2,833 MW × 每 MW $37m（IT 設備，含次年預建）；客戶自帶硬體不建模；共識口徑未揭露
A43: 差異原因｜FY27｜淨負債 | C43: =IF(ABS(C35)>輸入與假設!$C$333,"觀點","") | D43: =IF(ABS(C35)>輸入與假設!$C$333,"淨負債隨 CapEx、客戶預付、股利與融資瀑布而定（模型 CapEx 差距 "&IF((C32)<0,"−","+")&TEXT(ABS((C32))*100,"#,##0.0")&"%"&"）；共識淨負債不含租賃","")
A44: 差異原因｜FY28｜營收 | C44: =IF(ABS(D22)>輸入與假設!$C$333,"觀點","") | D44: =IF(ABS(D22)>輸入與假設!$C$333,"營收＝OCI（在役 MW × 每 MW 年收入，Tokenomics 正向推導；年底已連網 "&IF((輸入與假設!D$43)<0,"−","")&TEXT(ABS((輸入與假設!D$43)),"#,##0")&" MW-IT）＋傳統事業四線（近四季年增率收斂）；共識未揭露 MW 假設","")
A45: 差異原因｜FY28｜EBITDA | C45: =IF(ABS(D29)>輸入與假設!$C$334,"觀點","") -> 觀點 | D45: =IF(ABS(D29)>輸入與假設!$C$334,"營收差距 "&IF((D22)<0,"−","+")&TEXT(ABS((D22))*100,"#,##0.0")&"%"&"；EBITDA 率 "&IF((D27)<0,"−","")&TEXT(ABS((D27))*100,"#,##0.0")&"%"&" 對共識 "&IF((D28)<0,"−","")&TEXT(ABS((D28))*100,"#,##0.0")&"%"&"（OCI EBITDA 率由 "&IF((輸入與假設!$C$87)<0,"−","")&TEXT(ABS((輸入與假設!$C$87))*100,"#,##0")&"%"&" 走向穩態 "&IF((輸入與假設!$C$88)<0,"−","")&TEXT(ABS((輸入與假設!$C$88))*100,"#,##0")&"%"&"，取可觀察 neocloud 區間）","") -> 營收差距 +3.7%；EBITDA 率 59.4% 對共識 56.7%（OCI EBITDA 率由 65% 走向穩態 47%，取可觀察 neocloud 區間）
A46: 差異原因｜FY28｜CapEx | C46: =IF(ABS(D32)>輸入與假設!$C$333,"觀點","") -> 觀點 | D46: =IF(ABS(D32)>輸入與假設!$C$333,"CapEx 依新增 MW 計算：新增 "&IF((輸入與假設!D$125)<0,"−","")&TEXT(ABS((輸入與假設!D$125)),"#,##0")&" MW × 每 MW $"&IF((輸入與假設!D$109)<0,"−","")&TEXT(ABS((輸入與假設!D$109)),"#,##0")&"m（IT 設備，含次年預建）；客戶自帶硬體不建模；共識口徑未揭露","") -> CapEx 依新增 MW 計算：新增 2,833 MW × 每 MW $38m（IT 設備，含次年預建）；客戶自帶硬體不建模；共識口徑未揭露
A47: 差異原因｜FY28｜淨負債 | C47: =IF(ABS(D35)>輸入與假設!$C$333,"觀點","") -> 觀點 | D47: =IF(ABS(D35)>輸入與假設!$C$333,"淨負債隨 CapEx、客戶預付、股利與融資瀑布而定（模型 CapEx 差距 "&IF((D32)<0,"−","+")&TEXT(ABS((D32))*100,"#,##0.0")&"%"&"）；共識淨負債不含租賃","") -> 淨負債隨 CapEx、客戶預付、股利與融資瀑布而定（模型 CapEx 差距 −14.8%）；共識淨負債不含租賃
A48: 差異原因｜FY29｜營收 | C48: =IF(ABS(E22)>輸入與假設!$C$333,"觀點","") | D48: =IF(ABS(E22)>輸入與假設!$C$333,"營收＝OCI（在役 MW × 每 MW 年收入，Tokenomics 正向推導；年底已連網 "&IF((輸入與假設!E$43)<0,"−","")&TEXT(ABS((輸入與假設!E$43)),"#,##0")&" MW-IT）＋傳統事業四線（近四季年增率收斂）；共識未揭露 MW 假設","")
A49: 差異原因｜FY29｜EBITDA | C49: =IF(ABS(E29)>輸入與假設!$C$334,"觀點","") -> 觀點 | D49: =IF(ABS(E29)>輸入與假設!$C$334,"營收差距 "&IF((E22)<0,"−","+")&TEXT(ABS((E22))*100,"#,##0.0")&"%"&"；EBITDA 率 "&IF((E27)<0,"−","")&TEXT(ABS((E27))*100,"#,##0.0")&"%"&" 對共識 "&IF((E28)<0,"−","")&TEXT(ABS((E28))*100,"#,##0.0")&"%"&"（OCI EBITDA 率由 "&IF((輸入與假設!$C$87)<0,"−","")&TEXT(ABS((輸入與假設!$C$87))*100,"#,##0")&"%"&" 走向穩態 "&IF((輸入與假設!$C$88)<0,"−","")&TEXT(ABS((輸入與假設!$C$88))*100,"#,##0")&"%"&"，取可觀察 neocloud 區間）","") -> 營收差距 −3.0%；EBITDA 率 56.5% 對共識 58.6%（OCI EBITDA 率由 65% 走向穩態 47%，取可觀察 neocloud 區間）
A50: 差異原因｜FY29｜CapEx | C50: =IF(ABS(E32)>輸入與假設!$C$333,"觀點","") -> 觀點 | D50: =IF(ABS(E32)>輸入與假設!$C$333,"CapEx 依新增 MW 計算：新增 "&IF((輸入與假設!E$125)<0,"−","")&TEXT(ABS((輸入與假設!E$125)),"#,##0")&" MW × 每 MW $"&IF((輸入與假設!E$109)<0,"−","")&TEXT(ABS((輸入與假設!E$109)),"#,##0")&"m（IT 設備，含次年預建）；客戶自帶硬體不建模；共識口徑未揭露","") -> CapEx 依新增 MW 計算：新增 1,277 MW × 每 MW $38m（IT 設備，含次年預建）；客戶自帶硬體不建模；共識口徑未揭露
A51: 差異原因｜FY29｜淨負債 | C51: =IF(ABS(E35)>輸入與假設!$C$333,"觀點","") -> 觀點 | D51: =IF(ABS(E35)>輸入與假設!$C$333,"淨負債隨 CapEx、客戶預付、股利與融資瀑布而定（模型 CapEx 差距 "&IF((E32)<0,"−","+")&TEXT(ABS((E32))*100,"#,##0.0")&"%"&"）；共識淨負債不含租賃","") -> 淨負債隨 CapEx、客戶預付、股利與融資瀑布而定（模型 CapEx 差距 −63.2%）；共識淨負債不含租賃
A52: 差異｜需附原因項數 | C52: =SUMPRODUCT(--(ABS(C22:E22)>輸入與假設!$C$333))+SUMPRODUCT(--(ABS(C29:E29)>輸入與假設!$C$334))+SUMPRODUCT(--(ABS(C32:E32)>輸入與假設!$C$333))+SUMPRODUCT(--(ABS(C35:E35)>輸入與假設!$C$333)) -> 7 | I52: 營收、EBITDA（利潤率差）、CapEx、淨負債 × FY27–FY29
A53: 差異｜差異原因摘要 | C53: =IF(C52=0,"","需附原因的 "&C52&" 項差距："&MID(IF((COUNTIF(C40,"觀點")+COUNTIF(C41,"觀點")+COUNTIF(C42,"觀點")+COUNTIF(C43,"觀點")+COUNTIF(C44,"觀點")+COUNTIF(C45,"觀點")+COUNTIF(C46,"觀點")+COUNTIF(C47,"觀點")+COUNTIF(C48,"觀點")+COUNTIF(C49,"觀點")+COUNTIF(C50,"觀點")+COUNTIF(C51,"觀點"))>0,"、觀點 "&(COUNTIF(C40,"觀點")+COUNTIF(C41,"觀點")+COUNTIF(C42,"觀點")+COUNTIF(C43,"觀點")+COUNTIF(C44,"觀點")+COUNTIF(C45,"觀點")+COUNTIF(C46,"觀點")+COUNTIF(C47,"觀點")+COUNTIF(C48,"觀點")+COUNTIF(C49,"觀點")+COUNTIF(C50,"觀點")+COUNTIF(C51,"觀點"))&" 項","")&IF((COUNTIF(C40,"拆法")+COUNTIF(C41,"拆法")+COUNTIF(C42,"拆法")+COUNTIF(C43,"拆法")+COUNTIF(C44,"拆法")+COUNTIF(C45,"拆法")+COUNTIF(C46,"拆法")+COUNTIF(C47,"拆法")+COUNTIF(C48,"拆法")+COUNTIF(C49,"拆法")+COUNTIF(C50,"拆法")+COUNTIF(C51,"拆法"))>0,"、拆法 "&(COUNTIF(C40,"拆法")+COUNTIF(C41,"拆法")+COUNTIF(C42,"拆法")+COUNTIF(C43,"拆法")+COUNTIF(C44,"拆法")+COUNTIF(C45,"拆法")+COUNTIF(C46,"拆法")+COUNTIF(C47,"拆法")+COUNTIF(C48,"拆法")+COUNTIF(C49,"拆法")+COUNTIF(C50,"拆法")+COUNTIF(C51,"拆法"))&" 項","")&IF((COUNTIF(C40,"已知限制")+COUNTIF(C41,"已知限制")+COUNTIF(C42,"已知限制")+COUNTIF(C43,"已知限制")+COUNTIF(C44,"已知限制")+COUNTIF(C45,"已知限制")+COUNTIF(C46,"已知限制")+COUNTIF(C47,"已知限制")+COUNTIF(C48,"已知限制")+COUNTIF(C49,"已知限制")+COUNTIF(C50,"已知限制")+COUNTIF(C51,"已知限制"))>0,"、已知限制 "&(COUNTIF(C40,"已知限制")+COUNTIF(C41,"已知限制")+COUNTIF(C42,"已知限制")+COUNTIF(C43,"已知限制")+COUNTIF(C44,"已知限制")+COUNTIF(C45,"已知限制")+COUNTIF(C46,"已知限制")+COUNTIF(C47,"已知限制")+COUNTIF(C48,"已知限制")+COUNTIF(C49,"已知限制")+COUNTIF(C50,"已知限制")+COUNTIF(C51,"已知限制"))&" 項","")&IF((C52-((COUNTIF(C40,"觀點")+COUNTIF(C41,"觀點")+COUNTIF(C42,"觀點")+COUNTIF(C43,"觀點")+COUNTIF(C44,"觀點")+COUNTIF(C45,"觀點")+COUNTIF(C46,"觀點")+COUNTIF(C47,"觀點")+COUNTIF(C48,"觀點")+COUNTIF(C49,"觀點")+COUNTIF(C50,"觀點")+COUNTIF(C51,"觀點"))+(COUNTIF(C40,"拆法")+COUNTIF(C41,"拆法")+COUNTIF(C42,"拆法")+COUNTIF(C43,"拆法")+COUNTIF(C44,"拆法")+COUNTIF(C45,"拆法")+COUNTIF(C46,"拆法")+COUNTIF(C47,"拆法")+COUNTIF(C48,"拆法")+COUNTIF(C49,"拆法")+COUNTIF(C50,"拆法")+COUNTIF(C51,"拆法"))+(COUNTIF(C40,"已知限制")+COUNTIF(C41,"已知限制")+COUNTIF(C42,"已知限制")+COUNTIF(C43,"已知限制")+COUNTIF(C44,"已知限制")+COUNTIF(C45,"已知限制")+COUNTIF(C46,"已知限制")+COUNTIF(C47,"已知限制")+COUNTIF(C48,"已知限制")+COUNTIF(C49,"已知限制")+COUNTIF(C50,"已知限制")+COUNTIF(C51,"已知限制"))))>0,"、未歸類 "&(C52-((COUNTIF(C40,"觀點")+COUNTIF(C41,"觀點")+COUNTIF(C42,"觀點")+COUNTIF(C43,"觀點")+COUNTIF(C44,"觀點")+COUNTIF(C45,"觀點")+COUNTIF(C46,"觀點")+COUNTIF(C47,"觀點")+COUNTIF(C48,"觀點")+COUNTIF(C49,"觀點")+COUNTIF(C50,"觀點")+COUNTIF(C51,"觀點"))+(COUNTIF(C40,"拆法")+COUNTIF(C41,"拆法")+COUNTIF(C42,"拆法")+COUNTIF(C43,"拆法")+COUNTIF(C44,"拆法")+COUNTIF(C45,"拆法")+COUNTIF(C46,"拆法")+COUNTIF(C47,"拆法")+COUNTIF(C48,"拆法")+COUNTIF(C49,"拆法")+COUNTIF(C50,"拆法")+COUNTIF(C51,"拆法"))+(COUNTIF(C40,"已知限制")+COUNTIF(C41,"已知限制")+COUNTIF(C42,"已知限制")+COUNTIF(C43,"已知限制")+COUNTIF(C44,"已知限制")+COUNTIF(C45,"已知限制")+COUNTIF(C46,"已知限制")+COUNTIF(C47,"已知限制")+COUNTIF(C48,"已知限制")+COUNTIF(C49,"已知限制")+COUNTIF(C50,"已知限制")+COUNTIF(C51,"已知限制"))))&" 項",""),2,999)&"；原因見「損益與評價 → 市場共識」。") -> 需附原因的 7 項差距：觀點 7 項；原因見「損益與評價 → 市場共識」。 | I53: 與 HTML 一頁摘要同一句
A55: 3｜現價隱含什麼
A56: 隱含｜共識平均目標價隱含 FY29 EV/EBITDA | B56: x | C56: =(輸入與假設!$C$271*輸入與假設!$C$176+輸入與假設!$E$298)/輸入與假設!$E$290 -> 8.1312725 | I56: ＝（共識平均目標價 × 股數＋共識 FY29 淨負債）÷ 共識 FY29 調整後 EBITDA
A57: 隱含｜現價隱含 FY29 EV/EBITDA | B57: x | C57: =(輸入與假設!$C$175*輸入與假設!$C$176+輸入與假設!$E$298)/輸入與假設!$E$290 -> 5.4813464 | I57: 同一共識 FY29 數字，價格換成現價
A58: 隱含｜模型方法區間上緣 | B58: x | C58: =MAX(輸入與假設!$C$208,輸入與假設!$C$209) -> 6 | I58: 模型 EV/EBITDA 腿（OCI 倍數）錨定 FY29 並折回 2027-08-31，錨定年度與此不同
A59: 隱含｜模型 FY29 傳統事業 EBITDA | B59: US$bn | C59: =輸入與假設!E$83 -> 30.306278 | I59: × 傳統事業 EV/EBITDA 倍數，自共識隱含 EV 扣除
A60: 隱含｜共識平均目標價隱含 FY29 OCI EV/EBITDA | B60: x | C60: =(輸入與假設!$C$271*輸入與假設!$C$176+輸入與假設!$E$298-輸入與假設!E$83*輸入與假設!$C$204)/MAX(輸入與假設!$E$290-輸入與假設!E$83,0.01) -> 5.4282617 | I60: ＝（隱含 EV − 傳統事業 EBITDA × 傳統事業倍數）÷（共識 EBITDA − 傳統事業 EBITDA）
A61: 隱含｜現價隱含 FY29 OCI EV/EBITDA | B61: x | C61: =(輸入與假設!$C$175*輸入與假設!$C$176+輸入與假設!$E$298-輸入與假設!E$83*輸入與假設!$C$204)/MAX(輸入與假設!$E$290-輸入與假設!E$83,0.01) -> 1.7385531 | I61: 同上，價格換成現價
A62: 隱含｜隱含倍數句 | C62: ="共識平均目標價 $"&TEXT(輸入與假設!$C$271,"0.00")&" 隱含 FY29 EV/EBITDA "&TEXT(C56,"0.0")&"x（扣除傳統事業 "&TEXT(輸入與假設!$C$204,"0.0")&"x × 模型 EBITDA $"&TEXT(C59,"0.0")&"bn 後，OCI "&TEXT(C60,"0.0")&"x），OCI 倍數"&IF(ROUND(C60,1)>C58,"高於",IF(ROUND(C60,1)<C58,"低於","等於"))&"模型方法區間上緣 "&IF(C58=INT(C58),TEXT(C58,"0"),TEXT(C58,"0.0"))&"x；現價 $"&TEXT(輸入與假設!$C$175,"0.00")&" 隱含 "&TEXT(C57,"0.0")&"x（OCI "&TEXT(C61,"0.0")&"x）。" -> 共識平均目標價 $237.97 隱含 FY29 EV/EBITDA 8.1x（扣除傳統事業 15.0x × 模型 EBITDA $30.3bn 後，OCI 5.4x），OCI 倍數低於模型方法區間上緣 6x；現價 $144.77 隱含 5.5x（OCI 1.7x）。
A63: 反向 DCF｜FY31 每 MW 年收入（目前／隱含／變動） | C63: =評價_反向DCF!B18 -> 17.4 | D63: =評價_反向DCF!C18 -> 23.7781 | E63: =評價_反向DCF!D18 -> 0.3666 | I63: 快照（預設輸入）：見『評價_反向DCF』；改輸入後請以目標搜尋重算
A64: 反向 DCF｜每 MW 建置成本（目前／隱含／變動） | C64: =評價_反向DCF!B19 -> 37.59 | D64: =評價_反向DCF!C19 -> 16.3658 | E64: =評價_反向DCF!D19 -> -0.5646
A65: 反向 DCF｜穩態 EBITDA 率（目前／隱含／變動 pt） | C65: =評價_反向DCF!B20 -> 0.47 | D65: =評價_反向DCF!C20 -> 0.7407 | E65: =評價_反向DCF!D20 -> 0.2707
A66: 反向 DCF｜加權目標價＝現價所需每 MW 年收入（目前／隱含／變動） | C66: =評價_反向DCF!B21 -> 17.4 | D66: =評價_反向DCF!C21 -> 17.4201 | E66: =評價_反向DCF!D21 -> 0.0012
A68: 4｜驗證點與市場看法（賣方與管理層數字標記 Interested-party）
A69: 驗證｜焦點季 | C69: =季度追蹤!C12 -> Q2 FY27 | I69: 『輸入與假設』J 區選擇；季度層由年度模型拆分，只用於追蹤
A70: 驗證｜營收（模型／共識／指引低／指引高／實際） | B70: US$bn | C70: =季度追蹤!C6 -> 21.569582 | D70: =季度追蹤!D6 -> 21.322 | E70: =季度追蹤!F6 -> 20.875 | F70: =季度追蹤!G6 -> 21.518 | G70: =季度追蹤!I6 -> 待公布 | I70: 共識、指引為 Interested-party
A71: 驗證｜營收｜句 | C71: =INDEX(季度追蹤!$C$129:$H$129,輸入與假設!$C$339) -> 營收：模型 $21.57bn｜共識 $21.32bn（+1.2%）｜指引 $20.88–21.52bn（中點 +1.8%，高於上緣）〔觀點〕
A72: 驗證｜調整後 EBITDA（模型／共識／指引低／指引高／實際） | B72: US$bn | C72: =季度追蹤!C7 -> 12.733986 | D72: =季度追蹤!D7 -> 12.359 | E72: =季度追蹤!F7 -> 不適用 | F72: =季度追蹤!G7 -> 不適用 | G72: =季度追蹤!I7 -> 待公布 | I72: 共識、指引為 Interested-party
A73: 驗證｜調整後 EBITDA｜句 | C73: =INDEX(季度追蹤!$C$130:$H$130,輸入與假設!$C$339) -> 調整後 EBITDA：模型 $12.73bn｜共識 $12.36bn（+$0.37bn／+1.1pt）
A74: 驗證｜CapEx（毛額）（模型／共識／指引低／指引高／實際） | B74: US$bn | C74: =季度追蹤!C10 -> 25.865617 | D74: =季度追蹤!D10 -> 不適用 | E74: =季度追蹤!F10 -> 不適用 | F74: =季度追蹤!G10 -> 不適用 | G74: =季度追蹤!I10 -> 待公布 | I74: 共識、指引為 Interested-party
A75: 驗證｜CapEx（毛額）｜句 | C75: =INDEX(季度追蹤!$C$133:$H$133,輸入與假設!$C$339) -> CapEx（毛額）：模型 $25.87bn
A76: 驗證｜評等分布（強力買進／買進／持有／賣出／強力賣出） | B76: 家 | C76: =輸入與假設!$C$282 -> 28 | D76: =輸入與假設!$C$283 -> 7 | E76: =輸入與假設!$C$284 -> 7 | F76: =輸入與假設!$C$285 -> 0 | G76: =輸入與假設!$C$286 -> 1 | I76: 2026-10，合計 43 家 [Interested-party]
A77: 驗證｜目標價（平均／中位數／最低／最高） | B77: US$ | C77: =輸入與假設!$C$271 -> 237.97 | D77: =輸入與假設!$C$272 -> 240 | E77: =輸入與假設!$C$273 -> 110 | F77: =輸入與假設!$C$274 -> 400 | I77: 43 家；S&P Global Market Intelligence（經 StockAnalysis.com），擷取 2026-10-07 [Interested-party]
A79: 來源獨立性：StockAnalysis.com 的目標價、評等、FY27 營收與 EPS 引用 S&P Global Market Intelligence；MarketScreener 的年度與季度預估一般亦屬 S&P Capital IQ 系（與 CRWV、NBIS 共識檔同一判斷），FY27 營收 90.45 對 90.449 幾乎相同，視為同一底層來源的兩個呈現，不算獨立交叉驗證。Yahoo Finance 的營收與 EPS 預估來自 LSEG（獨立於 S&P），FY27 營收 90.48、FY28 131.45 與 MarketScreener 90.449／131.711 一致，可作 FY27–FY28 營收的獨立交叉。MarketBeat 目標價與評等為自行彙整（獨立於 S&P），可作目標價的獨立交叉；Yahoo 目標價 237.97 與 S&P 完全相同，推測同源，不算獨立。
A80: 共識來源：MarketScreener（S&P Capital IQ 系共識）、S&P Global Market Intelligence（經 StockAnalysis.com）；擷取 2026-10-07。逐筆來源、日期與標記見『輸入與假設』I 區。

Sheet 輸入與假設
A1: 輸入（依類別排序；點左側 ＋／− 展開或收合。藍字可改；黃底為最關鍵假設）
A2: A 情境 → B 產能與收入 → C 利潤率 → D 支出（CapEx／折舊／租賃／JV）→ E 融資 → F 評價 → G 參考：1Q27 實際 → H 情境區間運算表 → I 市場共識 → J 季度追蹤輸入。灰底『▸』為明細子區，預設收合
A4: A｜情境與規模（管理層擴張力道）
A5: 情境選擇（1＝保守 OpenAI 相關 60%、2＝基準 已簽約站點依 Q1 速度、3＝積極 依公司時程） | C5: 2 | D5: =CHOOSE(C5,"保守 OpenAI 相關 60%","基準 已簽約站點依 Q1 速度","積極 依公司時程") -> 基準 已簽約站點依 Q1 速度 | I5: 三情境改變擴張力道（已連網 MW 路徑）與每 MW 年收入（Tokenomics 正向推導三情境值）；其餘假設相同（對照表 r1 第 4 節第 1 條）
A6: ▸ 情境路徑明細（已連網 MW、在役比例、表外租金基準）
A7: 已連網 MW 路徑 | B7: 單位 | C7: FY27 | D7: FY28 | E7: FY29 | F7: FY30 | G7: FY31 | I7: FY31 新增 MW
A8: 首期期末已連網 MW（三情境共用） | B8: MW | C8: 4668 | I8: 首期期末＝評價日已連網＋首期剩餘季度依最新季交付速度；推導與來源見 company.json → scenarios.mwPath.note [Derived]
A9: 保守 OpenAI 相關 60%｜合約 MW 上限 | B9: MW | C9: 6284 | D9: 6284 | E9: 6284 | F9: 6284 | G9: 6284 | I9: company.json → scenarios.mwPath.contracted
A10: 保守 OpenAI 相關 60%｜併網速度 | B10: MW／年 | C10: 1000 | I10: company.json → scenarios.mwPath.pace
A11: 保守 OpenAI 相關 60% | B11: MW | C11: =MIN(C9,輸入與假設!$C$8) -> 4668 | D11: =MIN(D9,C11+輸入與假設!$C$10*D$41) -> 5668 | E11: =MIN(E9,D11+輸入與假設!$C$10*E$41) -> 6284 | F11: =MIN(F9,E11+輸入與假設!$C$10*F$41) -> 6284 | G11: =MIN(G9,F11+輸入與假設!$C$10*G$41) -> 6284 | I11: 0 | J11: 只交付已交付＋在建站點，OpenAI 相關容量實現 60%（上限 6,284 MW-IT），依 FY26 歷史速度 1,000 MW-IT／年；I 欄＝FY31 新增 MW
A12: 基準 已簽約站點依 Q1 速度｜合約 MW 上限 | B12: MW | C12: 8778 | D12: 8778 | E12: 8778 | F12: 8778 | G12: 8778 | I12: company.json → scenarios.mwPath.contracted
A13: 基準 已簽約站點依 Q1 速度｜併網速度 | B13: MW／年 | C13: 2833 | I13: company.json → scenarios.mwPath.pace
A14: 基準 已簽約站點依 Q1 速度 | B14: MW | C14: =MIN(C12,輸入與假設!$C$8) -> 4668 | D14: =MIN(D12,C14+輸入與假設!$C$13*D$41) -> 7501 | E14: =MIN(E12,D14+輸入與假設!$C$13*E$41) -> 8778 | F14: =MIN(F12,E14+輸入與假設!$C$13*F$41) -> 8778 | G14: =MIN(G12,F14+輸入與假設!$C$13*G$41) -> 8778 | I14: 0 | J14: Oracle 承租的五個 Stargate 站點全數實現（上限 8,778 MW-IT），依 FY27Q1 交付速度 2,833 MW-IT／年；I 欄＝FY31 新增 MW
A15: 積極 依公司時程｜合約 MW 上限 | B15: MW | C15: 8778 | D15: 8778 | E15: 8778 | F15: 8778 | G15: 8778 | I15: company.json → scenarios.mwPath.contracted
A16: 積極 依公司時程｜併網速度 | B16: MW／年 | C16: 3333 | I16: company.json → scenarios.mwPath.pace
A17: 積極 依公司時程 | B17: MW | C17: =MIN(C15,輸入與假設!$C$8) -> 4668 | D17: =MIN(D15,C17+輸入與假設!$C$16*D$41) -> 8001 | E17: =MIN(E15,D17+輸入與假設!$C$16*E$41) -> 8778 | F17: =MIN(F15,E17+輸入與假設!$C$16*F$41) -> 8778 | G17: =MIN(G15,F17+輸入與假設!$C$16*G$41) -> 8778 | I17: 0 | J17: 同基準上限，依公司時程（每季約 1 GW，3,333 MW-IT／年）；I 欄＝FY31 新增 MW
A18: 每 MW 年收入｜保守 OpenAI 相關 60% | B18: US$bn/MW | C18: 0.01162 | D18: 0.01162 | E18: 0.01162 | F18: 0.01162 | G18: 0.01162 | I18: Tokenomics 正向推導三情境（data/permw_tokenomics_20261007.json）；不用公司 ACV [Derived]
A19: 每 MW 年收入｜基準 已簽約站點依 Q1 速度 | B19: US$bn/MW | C19: 0.0174 | D19: 0.0174 | E19: 0.0174 | F19: 0.0174 | G19: 0.0174 | I19: Tokenomics 正向推導三情境（data/permw_tokenomics_20261007.json）；不用公司 ACV [Derived]
A20: 每 MW 年收入｜積極 依公司時程 | B20: US$bn/MW | C20: 0.0242 | D20: 0.0242 | E20: 0.0242 | F20: 0.0242 | G20: 0.0242 | I20: Tokenomics 正向推導三情境（data/permw_tokenomics_20261007.json）；不用公司 ACV [Derived]
A21: 在役 MW 收斂比例（期初校準值 → 已連網） | B21: % | C21: 0.5 | D21: 0.8 | E21: 0.85 | F21: 0.9 | G21: 0.9 | I21: 期初可計費 MW＝Q1 FY27 實際 OCI 營收 7.388 × 4＝29.552 ÷ 各情境每 MW 年收入（保守 2,543／基準 1,698／積極 1,221 MW-IT），是對齊已實現實際數的校準，不是以公司預測反推參數。各期末可計費 MW＝期初校準值＋(已連網 − 期初校準值)× 收斂比例；首期 50% 取能讓基準 FY27 營收落在公司指引 ≥90 的保守值（40% 時基準 FY27 約 89.1，低於指引），之後 80%→90%（新產能自交付到計費約一季）[Derived／Assumed]。
A22: 期初可計費 MW 校準：Q1 2027 實際營收年化 | B22: US$bn | C22: 29.552 | I22: 最新季實際營收 × 4（company.json → scenarios.billableRatio.openAnnualRevenue）[Derived]
A23: 期初可計費 MW｜保守 OpenAI 相關 60% | B23: MW | C23: =ROUND(輸入與假設!$C$22/C18,0) -> 2543 | I23: ＝實際營收年化 ÷ 該情境每 MW 年收入（對齊已實現實際數的校準）
A24: 期初可計費 MW｜基準 已簽約站點依 Q1 速度 | B24: MW | C24: =ROUND(輸入與假設!$C$22/C19,0) -> 1698 | I24: ＝實際營收年化 ÷ 該情境每 MW 年收入（對齊已實現實際數的校準）
A25: 期初可計費 MW｜積極 依公司時程 | B25: MW | C25: =ROUND(輸入與假設!$C$22/C20,0) -> 1221 | I25: ＝實際營收年化 ÷ 該情境每 MW 年收入（對齊已實現實際數的校準）
A26: 未起租租賃總額（未折現） | B26: US$bn | C26: 288 | I26: 季報附註已簽約未起租租賃（company.json → leases.facts.notCommenced）[Interested-party]
A27: 未起租：評價日後第幾季開始起租（0＝首期第一季） | B27: 季 | C27: 0 | I27: company.json → leases.uncommenced.startQ
A28: 未起租：平均分攤起租的季數 | B28: 季 | C28: 11 | I28: 季報：FY27Q2 至 FY2029 起租 → 11 季 [Assumed]
A29: 未起租：每筆租期 | B29: 年 | C29: 17 | I29: 季報 15–19 年取中點；敏感度 15／19 年見報告 [Assumed]
A30: B｜產能與收入（MW、每 MW 年收入、利用率、信用；RPO 只作對照）
A31: 8/31 RPO | B31: US$bn | C31: 664 | I31: 季報 RPO 664.0（只作對照與債務上限的 backlog）[Interested-party]
A32: 評價日後新增承諾 | B32: US$bn | C32: 0 | I32: 評價日後新簽、尚未進 RPO 的承諾；未揭露，取 0 [Assumed]
A33: 五期認列比例（至 2030 末） | B33: % | C33: 0.7975 | I33: 季報 RPO 桶線性分攤後五期合計 79.75% [Derived]
A34: RPO 桶權重合計 | B34: % | C34: 0.7975 | I34: 下方權重列的合計，用於歸一化
A35: 2026-05-31 主動電力 | B35: MW | C35: 1835 | I35: FY26 年底已連網 MW-IT 未揭露：以各情境校準可計費 MW 的最大值（保守 2,543＝Q1 OCI 年化 29.552 ÷ 11.62）減 Q1 交付 708 推得 1,835，使各情境期初可計費不超過已連網 [Derived]
A36: 8/31 Billable MW | B36: MW | C36: =CHOOSE(輸入與假設!$C$5,輸入與假設!$C$23,輸入與假設!$C$24,輸入與假設!$C$25) -> 1698 | I36: ＝依 A 區情境選擇器（以實際營收校準）
A37: 收入用平均在役 MW（1=是） | C37: 1 | I37: 0＝用期末存量全期化；建議 1
A38: 營收驅動（mw＝MW × 每 MW 年收入；rpo＝RPO 排程） | C38: mw | I38: mw：新產能簽約率固定 100%，營收＝容量上限；RPO 只作對照與產能瓶頸旗標（company.json → defaults.revenueDriver）
A39: 每 MW 年收入倍數（整體） | B39: % | C39: 1 | I39: 反向 DCF 與壓力測試用；預設 100%。以『目標搜尋』調整此格即可反解市價隱含單價
A40: 項目 | B40: 單位 | C40: FY27 | D40: FY28 | E40: FY29 | F40: FY30 | G40: FY31 | I40: 來源／標籤
A41: 模型期長度（年） | C41: 0.75 | D41: 1 | E41: 1 | F41: 1 | G41: 1 | I41: 勿改。由 calendar_q.py 推算；只用於容量上限、電力、維護等年率換算 [Derived]
A42: RPO 桶權重 | B42: % | C42: 0.0975 | D42: 0.17125 | E42: 0.185 | F42: 0.17375 | G42: 0.17 | H42: =SUM(C42:G42) -> 0.7975 | I42: 季報 RPO 桶（12 個月內 13%、36 個月內合計 50%；其餘假設 61–84 個月；含傳統事業 RPO，只作對照）桶內線性分攤 [Derived]
A43: Accepted MW（期末主動電力） | B43: MW | C43: =CHOOSE(輸入與假設!$C$5,C11,C14,C17) -> 4668 | D43: =CHOOSE(輸入與假設!$C$5,D11,D14,D17) -> 7501 | E43: =CHOOSE(輸入與假設!$C$5,E11,E14,E17) -> 8778 | F43: =CHOOSE(輸入與假設!$C$5,F11,F14,F17) -> 8778 | G43: =CHOOSE(輸入與假設!$C$5,G11,G14,G17) -> 8778 | I43: ＝依 A 區情境選擇器（已連網 MW-IT）
A44: Billable MW | B44: MW | C44: =ROUND(輸入與假設!$C$36+(C43-輸入與假設!$C$36)*C21,0) -> 3183 | D44: =ROUND(輸入與假設!$C$36+(D43-輸入與假設!$C$36)*D21,0) -> 6340 | E44: =ROUND(輸入與假設!$C$36+(E43-輸入與假設!$C$36)*E21,0) -> 7716 | F44: =ROUND(輸入與假設!$C$36+(F43-輸入與假設!$C$36)*F21,0) -> 8070 | G44: =ROUND(輸入與假設!$C$36+(G43-輸入與假設!$C$36)*G21,0) -> 8070 | I44: ＝期初校準值＋(已連網 − 期初校準值)× 收斂比例（A 區）
A45: 利用率 | B45: % | C45: 1 | D45: 1 | E45: 1 | F45: 1 | G45: 1 | I45: 100%：每 MW 年收入已含可計費利用率（路徑 B 80／85／90%），不重複扣除 [Derived]
A46: 每 MW 年收入 | B46: US$bn/MW | C46: =CHOOSE(輸入與假設!$C$5,C18,C19,C20) -> 0.0174 | D46: =CHOOSE(輸入與假設!$C$5,D18,D19,D20) -> 0.0174 | E46: =CHOOSE(輸入與假設!$C$5,E18,E19,E20) -> 0.0174 | F46: =CHOOSE(輸入與假設!$C$5,F18,F19,F20) -> 0.0174 | G46: =CHOOSE(輸入與假設!$C$5,G18,G19,G20) -> 0.0174 | I46: ＝依 A 區情境選擇器（Tokenomics 正向推導三情境）
A47: 新產能簽約率 | B47: % | C47: 1 | D47: 1 | E47: 1 | F47: 1 | G47: 1 | I47: MW 驅動：100%（RPO 只作對照）
A48: 客戶違約率 | B48: % | C48: 0.005 | D48: 0.01 | E48: 0.015 | F48: 0.02 | G48: 0.025 | I48: 前三大客戶約 59% 營收的定價，非預測 [Assumed]
A49: 回收率 | B49: % | C49: 0.5 | D49: 0.5 | E49: 0.5 | F49: 0.5 | G49: 0.5 | I49: [Assumed]
A50: 非算力服務營收 | B50: US$bn | C50: 0 | D50: 0 | E50: 0 | F50: 0 | G50: 0 | I50: 預設 0：AI cloud 軟體已含在每 MW 年收入；其他事業另列 [Assumed]
A51: 其他事業 EBITDA | B51: US$bn | C51: 0 | D51: 0 | E51: 0 | F51: 0 | G51: 0 | I51: 不適用（Oracle 無需另列的非核心事業燒錢；傳統事業另列於 defaults.legacyBiz，v0.1b 步驟 3）
A52: ▸ B2｜傳統事業（各線全年營收＝上一財年 ×(1＋年增率)，年增率自起點線性收斂到長期值；FY27 模型期＝全年 − 1Q 實際）
A53: 傳統事業｜SaaS（雲端應用）｜上一財年實際 | B53: US$bn | C53: 15.888 | I53: 上一財年經查核營收（company.json → defaults.legacyBiz）[Verified]
A54: 傳統事業｜SaaS（雲端應用）｜1Q 實際 | B54: US$bn | C54: 4.219 | I54: 年初至今實際營收（10-Q）[Interested-party]
A55: 傳統事業｜SaaS（雲端應用）｜起始年增率 | B55: % | C55: 0.1111 | I55: 近四季對前四季年增率 [Derived]
A56: 傳統事業｜SaaS（雲端應用）｜長期年增率 | B56: % | C56: 0.08 | I56: 長期值 [Assumed]（區間見 company.json → defaults.legacyBiz.note）
A57: 傳統事業｜SaaS（雲端應用）｜年增率 | B57: % | C57: =輸入與假設!$C$55+(輸入與假設!$C$56-輸入與假設!$C$55)*0/4 -> 0.1111 | D57: =輸入與假設!$C$55+(輸入與假設!$C$56-輸入與假設!$C$55)*1/4 -> 0.103325 | E57: =輸入與假設!$C$55+(輸入與假設!$C$56-輸入與假設!$C$55)*2/4 -> 0.09555 | F57: =輸入與假設!$C$55+(輸入與假設!$C$56-輸入與假設!$C$55)*3/4 -> 0.087775 | G57: =輸入與假設!$C$55+(輸入與假設!$C$56-輸入與假設!$C$55)*4/4 -> 0.08 | I57: ＝起始＋(長期 − 起始)×期數÷4
A58: 傳統事業｜SaaS（雲端應用）｜全年營收 | B58: US$bn | C58: =輸入與假設!$C$53*(1+C57) -> 17.653157 | D58: =C58*(1+D57) -> 19.477169 | E58: =D58*(1+E57) -> 21.338213 | F58: =E58*(1+F57) -> 23.211174 | G58: =F58*(1+G57) -> 25.068068 | I58: ＝前一年 ×(1＋年增率)
A59: 傳統事業｜SaaS（雲端應用）｜模型期營收 | B59: US$bn | C59: =C58-輸入與假設!$C$54 -> 13.434157 | D59: =D58 -> 19.477169 | E59: =E58 -> 21.338213 | F59: =F58 -> 23.211174 | G59: =G58 -> 25.068068 | I59: FY27＝全年 − 1Q 實際
A60: 傳統事業｜軟體（授權＋支援）｜上一財年實際 | B60: US$bn | C60: 24.541 | I60: 上一財年經查核營收（company.json → defaults.legacyBiz）[Verified]
A61: 傳統事業｜軟體（授權＋支援）｜1Q 實際 | B61: US$bn | C61: 5.55 | I61: 年初至今實際營收（10-Q）[Interested-party]
A62: 傳統事業｜軟體（授權＋支援）｜起始年增率 | B62: % | C62: -0.0125 | I62: 近四季對前四季年增率 [Derived]
A63: 傳統事業｜軟體（授權＋支援）｜長期年增率 | B63: % | C63: -0.01 | I63: 長期值 [Assumed]（區間見 company.json → defaults.legacyBiz.note）
A64: 傳統事業｜軟體（授權＋支援）｜年增率 | B64: % | C64: =輸入與假設!$C$62+(輸入與假設!$C$63-輸入與假設!$C$62)*0/4 -> -0.0125 | D64: =輸入與假設!$C$62+(輸入與假設!$C$63-輸入與假設!$C$62)*1/4 -> -0.011875 | E64: =輸入與假設!$C$62+(輸入與假設!$C$63-輸入與假設!$C$62)*2/4 -> -0.01125 | F64: =輸入與假設!$C$62+(輸入與假設!$C$63-輸入與假設!$C$62)*3/4 -> -0.010625 | G64: =輸入與假設!$C$62+(輸入與假設!$C$63-輸入與假設!$C$62)*4/4 -> -0.01 | I64: ＝起始＋(長期 − 起始)×期數÷4
A65: 傳統事業｜軟體（授權＋支援）｜全年營收 | B65: US$bn | C65: =輸入與假設!$C$60*(1+C64) -> 24.234237 | D65: =C65*(1+D64) -> 23.946456 | E65: =D65*(1+E64) -> 23.677058 | F65: =E65*(1+F64) -> 23.42549 | G65: =F65*(1+G64) -> 23.191235 | I65: ＝前一年 ×(1＋年增率)
A66: 傳統事業｜軟體（授權＋支援）｜模型期營收 | B66: US$bn | C66: =C65-輸入與假設!$C$61 -> 18.684237 | D66: =D65 -> 23.946456 | E66: =E65 -> 23.677058 | F66: =F65 -> 23.42549 | G66: =G65 -> 23.191235 | I66: FY27＝全年 − 1Q 實際
A67: 傳統事業｜硬體｜上一財年實際 | B67: US$bn | C67: 3.084 | I67: 上一財年經查核營收（company.json → defaults.legacyBiz）[Verified]
A68: 傳統事業｜硬體｜1Q 實際 | B68: US$bn | C68: 0.774 | I68: 年初至今實際營收（10-Q）[Interested-party]
A69: 傳統事業｜硬體｜起始年增率 | B69: % | C69: 0.0803 | I69: 近四季對前四季年增率 [Derived]
A70: 傳統事業｜硬體｜長期年增率 | B70: % | C70: 0 | I70: 長期值 [Assumed]（區間見 company.json → defaults.legacyBiz.note）
A71: 傳統事業｜硬體｜年增率 | B71: % | C71: =輸入與假設!$C$69+(輸入與假設!$C$70-輸入與假設!$C$69)*0/4 -> 0.0803 | D71: =輸入與假設!$C$69+(輸入與假設!$C$70-輸入與假設!$C$69)*1/4 -> 0.060225 | E71: =輸入與假設!$C$69+(輸入與假設!$C$70-輸入與假設!$C$69)*2/4 -> 0.04015 | F71: =輸入與假設!$C$69+(輸入與假設!$C$70-輸入與假設!$C$69)*3/4 -> 0.020075 | G71: =輸入與假設!$C$69+(輸入與假設!$C$70-輸入與假設!$C$69)*4/4 -> 0 | I71: ＝起始＋(長期 − 起始)×期數÷4
A72: 傳統事業｜硬體｜全年營收 | B72: US$bn | C72: =輸入與假設!$C$67*(1+C71) -> 3.3316452 | D72: =C72*(1+D71) -> 3.5322935 | E72: =D72*(1+E71) -> 3.6741151 | F72: =E72*(1+F71) -> 3.747873 | G72: =F72*(1+G71) -> 3.747873 | I72: ＝前一年 ×(1＋年增率)
A73: 傳統事業｜硬體｜模型期營收 | B73: US$bn | C73: =C72-輸入與假設!$C$68 -> 2.5576452 | D73: =D72 -> 3.5322935 | E73: =E72 -> 3.6741151 | F73: =F72 -> 3.747873 | G73: =G72 -> 3.747873 | I73: FY27＝全年 − 1Q 實際
A74: 傳統事業｜服務｜上一財年實際 | B74: US$bn | C74: 5.743 | I74: 上一財年經查核營收（company.json → defaults.legacyBiz）[Verified]
A75: 傳統事業｜服務｜1Q 實際 | B75: US$bn | C75: 1.414 | I75: 年初至今實際營收（10-Q）[Interested-party]
A76: 傳統事業｜服務｜起始年增率 | B76: % | C76: 0.0921 | I76: 近四季對前四季年增率 [Derived]
A77: 傳統事業｜服務｜長期年增率 | B77: % | C77: 0.03 | I77: 長期值 [Assumed]（區間見 company.json → defaults.legacyBiz.note）
A78: 傳統事業｜服務｜年增率 | B78: % | C78: =輸入與假設!$C$76+(輸入與假設!$C$77-輸入與假設!$C$76)*0/4 -> 0.0921 | D78: =輸入與假設!$C$76+(輸入與假設!$C$77-輸入與假設!$C$76)*1/4 -> 0.076575 | E78: =輸入與假設!$C$76+(輸入與假設!$C$77-輸入與假設!$C$76)*2/4 -> 0.06105 | F78: =輸入與假設!$C$76+(輸入與假設!$C$77-輸入與假設!$C$76)*3/4 -> 0.045525 | G78: =輸入與假設!$C$76+(輸入與假設!$C$77-輸入與假設!$C$76)*4/4 -> 0.03 | I78: ＝起始＋(長期 − 起始)×期數÷4
A79: 傳統事業｜服務｜全年營收 | B79: US$bn | C79: =輸入與假設!$C$74*(1+C78) -> 6.2719303 | D79: =C79*(1+D78) -> 6.7522034 | E79: =D79*(1+E78) -> 7.1644254 | F79: =E79*(1+F78) -> 7.4905858 | G79: =F79*(1+G78) -> 7.7153034 | I79: ＝前一年 ×(1＋年增率)
A80: 傳統事業｜服務｜模型期營收 | B80: US$bn | C80: =C79-輸入與假設!$C$75 -> 4.8579303 | D80: =D79 -> 6.7522034 | E80: =E79 -> 7.1644254 | F80: =F79 -> 7.4905858 | G80: =G79 -> 7.7153034 | I80: FY27＝全年 − 1Q 實際
A81: 傳統事業營收（模型期） | B81: US$bn | C81: =C59+C66+C73+C80 -> 39.53397 | D81: =D59+D66+D73+D80 -> 53.708122 | E81: =E59+E66+E73+E80 -> 55.853812 | F81: =F59+F66+F73+F80 -> 57.875123 | G81: =G59+G66+G73+G80 -> 59.722479 | I81: 四線合計（下游引用此列）
A82: 傳統事業 EBITDA 率 | B82: % | C82: 0.5426 | D82: 0.5426 | E82: 0.5426 | F82: 0.5426 | G82: 0.5426 | I82: FY26 合併 EBITDA 率＝非 GAAP 營業利益＋折舊，OCI 無分部揭露無法拆分 [Derived]；不加無形資產攤銷，因非 GAAP 營業利益已排除攤銷
A83: 傳統事業 EBITDA（模型期） | B83: US$bn | C83: =C81*C82 -> 21.451132 | D83: =D81*D82 -> 29.142027 | E83: =E81*E82 -> 30.306278 | F83: =F81*F82 -> 31.403042 | G83: =G81*G82 -> 32.405417 | I83: ＝營收 × EBITDA 率；同時進入損益 EBITDA 與營運來源（現金稅另列）
A84: 傳統事業｜FY27 核對（1Q＋模型期 − 全年） | B84: US$bn | C84: =輸入與假設!$C$54+C59-C58+輸入與假設!$C$61+C66-C65+輸入與假設!$C$68+C73-C72+輸入與假設!$C$75+C80-C79 -> 0 | I84: 應為 0：首期年初至今實際＋模型期＝首期全年（各線合計）
A86: C｜利潤率（EBITDA 率單一來源；損益與資金共用）
A87: 起始 EBITDA 率（FY27） | B87: % | C87: 0.652 | I87: FY27Q1 合併 EBITDA 扣除傳統事業後拆推的 OCI EBITDA 率 [Derived]
A88: 穩態 EBITDA 率（FY31） | B88: % | C88: 0.47 | I88: 可觀察 neocloud 區間 IREN 約 35%／CRWV 約 59% 的中點 47%；不取自每 MW 推導路徑 A 的加成 [Analogy]
A89: 基準情境租金占 OCI 營收（FY27） | B89: % | C89: 0.193075 | I89: EBITDAR 率校準：基準情境首期租金 ÷ OCI 營收，使基準情境起始 EBITDA 率維持上列值；scripts/calib_ebitdar.js 自基準情境計算（verify.sh 檢查）[Derived]
A90: 基準情境租金占 OCI 營收（FY31） | B90: % | C90: 0.156683 | I90: 同上，基準情境末期；保守與積極用同一 EBITDAR 率，因而承擔固定租金 [Derived]
A91: 項目 | B91: 單位 | C91: FY27 | D91: FY28 | E91: FY29 | F91: FY30 | G91: FY31 | I91: 來源／標籤
A92: EBITDAR 率（路徑） | B92: % | C92: =輸入與假設!$C$87+輸入與假設!$C$89+(輸入與假設!$C$88+輸入與假設!$C$90-輸入與假設!$C$87-輸入與假設!$C$89)*0/4 -> 0.845075 | D92: =輸入與假設!$C$87+輸入與假設!$C$89+(輸入與假設!$C$88+輸入與假設!$C$90-輸入與假設!$C$87-輸入與假設!$C$89)*1/4 -> 0.790477 | E92: =輸入與假設!$C$87+輸入與假設!$C$89+(輸入與假設!$C$88+輸入與假設!$C$90-輸入與假設!$C$87-輸入與假設!$C$89)*2/4 -> 0.735879 | F92: =輸入與假設!$C$87+輸入與假設!$C$89+(輸入與假設!$C$88+輸入與假設!$C$90-輸入與假設!$C$87-輸入與假設!$C$89)*3/4 -> 0.681281 | G92: =輸入與假設!$C$87+輸入與假設!$C$89+(輸入與假設!$C$88+輸入與假設!$C$90-輸入與假設!$C$87-輸入與假設!$C$89)*4/4 -> 0.626683 | I92: ＝(起始 EBITDA 率＋基準起點租金比)＋[(穩態＋基準穩態租金比)−(起始＋基準起點租金比)]×期數÷4（公式）
A93: EBITDA 率 | B93: % | C93: =C92-各期收支!C16/MAX(0.01,運營_產能與收入!C37) -> 0.6519998 | D93: =D92-各期收支!D16/MAX(0.01,運營_產能與收入!D37) -> 0.62804402 | E93: =E92-各期收支!E16/MAX(0.01,運營_產能與收入!E37) -> 0.57518339 | F93: =F92-各期收支!F16/MAX(0.01,運營_產能與收入!F37) -> 0.52111306 | G93: =G92-各期收支!G16/MAX(0.01,運營_產能與收入!G37) -> 0.46999955 | I93: ＝EBITDAR 率 − 租金合計 ÷ OCI 營收（公式；租金為固定成本，低營收情境 EBITDA 率較低）
A94: 非算力服務現金 | B94: US$bn | C94: =輸入與假設!C$50*運營_產能與收入!C38 -> 0 | D94: =輸入與假設!D$50*運營_產能與收入!D38 -> 0 | E94: =輸入與假設!E$50*運營_產能與收入!E38 -> 0 | F94: =輸入與假設!F$50*運營_產能與收入!F38 -> 0 | G94: =輸入與假設!G$50*運營_產能與收入!G38 -> 0 | I94: ＝服務營收 × EBITDAR 率（公式）
A95: ▸ 電力／維護 overlay（預設關閉；EBITDA 已含電費）
A96: 電力／維護 overlay（1=開） | C96: 0 | I96: EBITDA 率已含電費，開啟會重複扣除，僅供壓力測試
A97: 電價 | B97: $/MWh | C97: 60 | D97: 62 | E97: 64 | F97: 66 | G97: 68 | I97: overlay 用 [Assumed]
A98: PUE | C98: 1.2 | D98: 1.2 | E98: 1.2 | F98: 1.2 | G98: 1.2 | I98: overlay 用 [Assumed]
A99: 維護成本 | B99: US$m/MW | C99: 0.15 | D99: 0.15 | E99: 0.16 | F99: 0.16 | G99: 0.17 | I99: overlay 用 [Assumed]
A101: D｜支出（CapEx、車隊折舊、租賃、JV）
A102: 提前支出比例 λ | B102: % | C102: 0.35 | I102: 次年才上線的 MW，其建置支出落在前一年的比例 [Assumed]
A103: FY31 新增 MW（FY30 預建用） | B103: MW | C103: =CHOOSE(輸入與假設!$C$5,I11,I14,I17) -> 0 | I103: 隨情境：保守 0／基準 500／積極 1,000 [Assumed]
...

Sheet 各期收支
A1: 支出與資金 — 五層支出、四層來源、現金橋
A2: FY27 欄＝1Q 實際（季報現金流量表口徑）＋第 2–4 季模型；FY28 以後為純模型。瀑布以「融資前現金」決定需求並直接由各支出列加總，因此沒有循環參照
A4: 項目 | B4: 單位 | C4: FY27 | D4: FY28 | E4: FY29 | F4: FY30 | G4: FY31 | I4: 公式／來源說明
A5: 支出（五層）
A6: ① 毛 CapEx（認列，備忘） | B6: US$bn | C6: =輸入與假設!$C$243+輸入與假設!C$135 -> 106.09585 | D6: =輸入與假設!D$135 -> 86.020956 | E6: =輸入與假設!E$135 -> 31.20158 | F6: =輸入與假設!F$135 -> 54.99417 | G6: =輸入與假設!G$135 -> 54.99417 | I6: FY27＝1Q 實際認列 28.499＋2Q–4Q 模型；對照公司全年指引 90–95。備忘列：用途合計採現金口徑，不用這一列
A7: 客戶預付率 | B7: % | C7: =輸入與假設!C$116 -> 0.243 | D7: =輸入與假設!D$116 -> 0.243 | E7: =輸入與假設!E$116 -> 0.243 | F7: =輸入與假設!F$116 -> 0.243 | G7: =輸入與假設!G$116 -> 0.243
A8: 客戶預付金額（抵減，2Q–4Q 起） | B8: US$bn | C8: =(輸入與假設!C$128+輸入與假設!C$132)*C7 -> 18.856035 | D8: =(輸入與假設!D$128+輸入與假設!D$132)*D7 -> 20.903092 | E8: =(輸入與假設!E$128+輸入與假設!E$132)*E7 -> 7.5819838 | F8: =(輸入與假設!F$128+輸入與假設!F$132)*F7 -> 13.363583 | G8: =(輸入與假設!G$128+輸入與假設!G$132)*G7 -> 13.363583 | I8: ＝(成長型＋汰換 CapEx)× 預付比率（v0.1c：汰換同樣適用覆蓋比）；1Q 的預付已含在實際 CFO 內，不重複計入
A9: 合約負債期初（客戶預付餘額） | B9: US$bn | C9: =輸入與假設!$C$113 -> 15.955 | D9: =C12 -> 33.730118 | E9: =D12 -> 50.753693 | F9: =E12 -> 51.723798 | G9: =F12 -> 58.531976 | I9: FY27 期初＝8/31 季報遞延營收
A10: 合約負債利息累積（重大財務組成，非現金） | B10: US$bn | C10: =輸入與假設!$C$114*(C9+0.5*C8)*運營_產能與收入!C7 -> 1.543922 | D10: =輸入與假設!$C$114*(D9+0.5*D8)*運營_產能與收入!D7 -> 3.583133 | E10: =輸入與假設!$C$114*(E9+0.5*E8)*運營_產能與收入!E7 -> 4.423574 | F10: =輸入與假設!$C$114*(F9+0.5*F8)*運營_產能與收入!F7 -> 4.7366933 | G10: =輸入與假設!$C$114*(G9+0.5*G8)*運營_產能與收入!G7 -> 5.2888366 | I10: ＝隱含利率 ×(期初合約負債＋本期預付流入 × ½)× 期間長度；進損益利息、不進現金（v0.1b）
A11: 預付認列（非現金營收） | B11: US$bn | C11: =MIN(C9+C10,(C9+C10)/輸入與假設!$C$112*運營_產能與收入!C7) -> 2.6248383 | D11: =MIN(D9+D10,(D9+D10)/輸入與假設!$C$112*運營_產能與收入!D7) -> 7.4626503 | E11: =MIN(E9+E10,(E9+E10)/輸入與假設!$C$112*運營_產能與收入!E7) -> 11.035453 | F11: =MIN(F9+F10,(F9+F10)/輸入與假設!$C$112*運營_產能與收入!F7) -> 11.292098 | G11: =MIN(G9+G10,(G9+G10)/輸入與假設!$C$112*運營_產能與收入!G7) -> 12.764163 | I11: ＝(期初合約負債＋累積利息) ÷ 認列年數 × 期間長度；這部分營收已在預付時收現，自營運來源扣除
A12: 合約負債期末 | B12: US$bn | C12: =C9+C8+C10-C11 -> 33.730118 | D12: =D9+D8+D10-D11 -> 50.753693 | E12: =E9+E8+E10-E11 -> 51.723798 | F12: =F9+F8+F10-F11 -> 58.531976 | G12: =G9+G8+G10-G11 -> 64.420233 | I12: ＝期初＋預付流入＋累積利息−認列
A13: ① CapEx（用途用：1Q 現金／2Q–4Q 毛額） | B13: US$bn | C13: =輸入與假設!$C$242+輸入與假設!C$135 -> 106.09585 | D13: =輸入與假設!D$135 -> 86.020956 | E13: =輸入與假設!E$135 -> 31.20158 | F13: =輸入與假設!F$135 -> 54.99417 | G13: =輸入與假設!G$135 -> 54.99417 | I13: 1Q 採現金流量表的現金購置 28.499；2Q–4Q 起採毛額，客戶預付在來源端抵回（避免重複計入）
A14: ② 在帳現金租金（備忘，1Q 已含在 CFO） | B14: US$bn | C14: =輸入與假設!C$117 -> 3.839 | D14: =輸入與假設!D$117 -> 4.987 | E14: =輸入與假設!E$117 -> 5.02 | F14: =輸入與假設!F$117 -> 5.056 | G14: =輸入與假設!G$117 -> 5.06 | I14: 見『租賃與承諾』頁；2031 後尚有 39.283。FY27 欄僅 2Q–4Q：1Q 租金 1.136 已含在實際 CFO 內
A15: ② 表外現金租金（未起租） | B15: US$bn | C15: =輸入與假設!C$119 -> 2.3101604 | D15: =輸入與假設!D$119 -> 8.4705882 | E15: =輸入與假設!E$119 -> 14.631016 | F15: =輸入與假設!F$119 -> 16.941176 | G15: =輸入與假設!G$119 -> 16.941176 | I15: 已簽約未起租租賃 288.0 的現金路徑
A16: 租金合計 | B16: US$bn | C16: =C14+C15 -> 6.1491604 | D16: =D14+D15 -> 13.457588 | E16: =E14+E15 -> 19.651016 | F16: =F14+F15 -> 21.997176 | G16: =G14+G15 -> 22.001176 | I16: 租金已含在 EBITDA 率內（GAAP 營業租賃費用屬營業費用）：營運來源以 EBITDA 率＋租金÷營收計（租前），此列再扣，淨效果中性
A17: ③ 存量債務利息（備忘，1Q 已含在 CFO） | B17: US$bn | C17: =輸入與假設!C$172 -> 4.4795709 | D17: =輸入與假設!D$172 -> 5.6569839 | E17: =輸入與假設!E$172 -> 5.2813593 | F17: =輸入與假設!F$172 -> 4.9752805 | G17: =輸入與假設!G$172 -> 4.5671755 | I17: ="8/31 債務餘額的利息。FY27 全年利息＝1Q 實際 1.428＋2Q–4Q "&TEXT(C17,"0.0")&"＝"&TEXT(1.428+C17,"0.00")&"（見下方備忘）" -> 8/31 債務餘額的利息。FY27 全年利息＝1Q 實際 1.428＋2Q–4Q 4.5＝5.91（見下方備忘）
A18: 期初累積現金 | B18: US$bn | C18: =輸入與假設!$C$240 -> 31.289 | D18: =C51 -> 10 | E18: =D51 -> 10 | F18: =E51 -> 48.446703 | G18: =F51 -> 69.42544 | I18: FY27 自 2026-05-31 起算；之後＝前期期末累積現金
A19: 新債利率 | B19: % | C19: =IF(輸入與假設!$C$165=1,輸入與假設!C$171+MAX(0,輸入與假設!$C$164-450)/100*0.004,輸入與假設!C$171) -> 0.058 | D19: =IF(輸入與假設!$C$165=1,輸入與假設!D$171+MAX(0,輸入與假設!$C$164-450)/100*0.004,輸入與假設!D$171) -> 0.058 | E19: =IF(輸入與假設!$C$165=1,輸入與假設!E$171+MAX(0,輸入與假設!$C$164-450)/100*0.004,輸入與假設!E$171) -> 0.058 | F19: =IF(輸入與假設!$C$165=1,輸入與假設!F$171+MAX(0,輸入與假設!$C$164-450)/100*0.004,輸入與假設!F$171) -> 0.058 | G19: =IF(輸入與假設!$C$165=1,輸入與假設!G$171+MAX(0,輸入與假設!$C$164-450)/100*0.004,輸入與假設!G$171) -> 0.058 | I19: CDS 開關：＋MAX(0,CDS−450)×0.4bp/bp
A20: ③ 新債利息（瀑布） | B20: US$bn | C20: =C78 -> 0.39339161 | D20: =D78 -> 1.8110695 | E20: =E78 -> 1.8110695 | F20: =F78 -> 1.8110695 | G20: =G78 -> 1.8110695 | I20: ＝新債利率×期間長度×(期初新債＋本期舉借)；見下方「期前融資瀑布」
A21: 利息合計 | B21: US$bn | C21: =C17+C20 -> 4.8729625 | D21: =D17+D20 -> 7.4680535 | E21: =E17+E20 -> 7.0924288 | F21: =F17+F20 -> 6.78635 | G21: =G17+G20 -> 6.378245
A22: ④ JV／策略投資出資 | B22: US$bn | C22: =輸入與假設!$C$244+輸入與假設!C$122 -> 0 | D22: =輸入與假設!D$122 -> 0 | E22: =輸入與假設!E$122 -> 0 | F22: =輸入與假設!F$122 -> 0 | G22: =輸入與假設!G$122 -> 0 | I22: FY27＝1Q 實際 0.0（JV 0.000＋策略投資 0.000）＋2Q–4Q 模型。ORCL 不發股息
A23: ⑧ 股利（普通股＋特別股） | B23: US$bn | C23: =輸入與假設!$C$259+4*輸入與假設!$C$149*運營_產能與收入!C7*(輸入與假設!$C$150+0+SUMPRODUCT(資產負債_既有債務!$D$73:$D$73*資產負債_既有債務!$H$69:$H$69*(資產負債_既有債務!$G$69:$G$69<0)))+輸入與假設!C$169 -> 6.344604 | D23: =4*輸入與假設!$C$149*運營_產能與收入!D7*(輸入與假設!$C$150+C81+SUMPRODUCT(資產負債_既有債務!$D$73:$D$73*資產負債_既有債務!$H$69:$H$69*(資產負債_既有債務!$G$69:$G$69<1)))+輸入與假設!D$169 -> 6.372472 | E23: =4*輸入與假設!$C$149*運營_產能與收入!E7*(輸入與假設!$C$150+D81+SUMPRODUCT(資產負債_既有債務!$D$73:$D$73*資產負債_既有債務!$H$69:$H$69*(資產負債_既有債務!$G$69:$G$69<2)))+輸入與假設!E$169 -> 6.291472 | F23: =4*輸入與假設!$C$149*運營_產能與收入!F7*(輸入與假設!$C$150+E81+SUMPRODUCT(資產負債_既有債務!$D$73:$D$73*資產負債_既有債務!$H$69:$H$69*(資產負債_既有債務!$G$69:$G$69<3)))+輸入與假設!F$169 -> 6.1099486 | G23: =4*輸入與假設!$C$149*運營_產能與收入!G7*(輸入與假設!$C$150+F81+SUMPRODUCT(資產負債_既有債務!$D$73:$D$73*資產負債_既有債務!$H$69:$H$69*(資產負債_既有債務!$G$69:$G$69<4)))+輸入與假設!G$169 -> 6.1099486 | I23: 普通股＝每股每季 × 4 × 期間長度 ×(基礎股數＋前期累計瀑布新股＋已強制轉換特別股)＋特別股股利；FY27＝1Q 實際＋2Q–4Q 模型（v0.1b）
A24: 電力（overlay） | B24: US$bn | C24: =IF(輸入與假設!$C$96=1,運營_產能與收入!C9*8760*輸入與假設!C$98*輸入與假設!C$97/1000000000*運營_產能與收入!C7,0) -> 0 | D24: =IF(輸入與假設!$C$96=1,運營_產能與收入!D9*8760*輸入與假設!D$98*輸入與假設!D$97/1000000000*運營_產能與收入!D7,0) -> 0 | E24: =IF(輸入與假設!$C$96=1,運營_產能與收入!E9*8760*輸入與假設!E$98*輸入與假設!E$97/1000000000*運營_產能與收入!E7,0) -> 0 | F24: =IF(輸入與假設!$C$96=1,運營_產能與收入!F9*8760*輸入與假設!F$98*輸入與假設!F$97/1000000000*運營_產能與收入!F7,0) -> 0 | G24: =IF(輸入與假設!$C$96=1,運營_產能與收入!G9*8760*輸入與假設!G$98*輸入與假設!G$97/1000000000*運營_產能與收入!G7,0) -> 0 | I24: ＝已連網 MW×8760×PUE×電價÷1e9×期間係數。EBITDA 率已含電費，預設關閉
A25: 維護（overlay） | B25: US$bn | C25: =IF(輸入與假設!$C$96=1,運營_產能與收入!C9*輸入與假設!C$99/1000*運營_產能與收入!C7,0) -> 0 | D25: =IF(輸入與假設!$C$96=1,運營_產能與收入!D9*輸入與假設!D$99/1000*運營_產能與收入!D7,0) -> 0 | E25: =IF(輸入與假設!$C$96=1,運營_產能與收入!E9*輸入與假設!E$99/1000*運營_產能與收入!E7,0) -> 0 | F25: =IF(輸入與假設!$C$96=1,運營_產能與收入!F9*輸入與假設!F$99/1000*運營_產能與收入!F7,0) -> 0 | G25: =IF(輸入與假設!$C$96=1,運營_產能與收入!G9*輸入與假設!G$99/1000*運營_產能與收入!G7,0) -> 0
A26: ⑤ 排程還本（季報到期表） | B26: US$bn | C26: =輸入與假設!$C$246+IF(輸入與假設!$C$144=1,輸入與假設!C$170,0)+資產負債_既有債務!C84 -> 7.209 | D26: =IF(輸入與假設!$C$144=1,輸入與假設!D$170,0)+資產負債_既有債務!D84 -> 10.147 | E26: =IF(輸入與假設!$C$144=1,輸入與假設!E$170,0)+資產負債_既有債務!E84 -> 5.5 | F26: =IF(輸入與假設!$C$144=1,輸入與假設!F$170,0)+資產負債_既有債務!F84 -> 7.25 | G26: =IF(輸入與假設!$C$144=1,輸入與假設!G$170,0)+資產負債_既有債務!G84 -> 9.75 | I26: FY27＝1Q 實際還款 4.202＋2Q–4Q 到期表 3.007
A27: ⑥ capped call 支出（1Q 實際） | B27: US$bn | C27: =輸入與假設!$C$247 -> 0 | D27: =0 -> 0 | E27: =0 -> 0 | F27: =0 -> 0 | G27: =0 -> 0 | I27: 可轉債配套 capped call 現金支出（未見揭露，0）
A28: ⑦ 現金稅（2Q–4Q 起） | B28: US$bn | C28: =輸入與假設!$C$163*MAX(0,運營_產能與收入!C37*輸入與假設!C$93+輸入與假設!C$51+輸入與假設!C$83-輸入與假設!C$136-輸入與假設!C$172) -> 3.536343 | D28: =輸入與假設!$C$163*MAX(0,運營_產能與收入!D37*輸入與假設!D$93+輸入與假設!D$51+輸入與假設!D$83-輸入與假設!D$136-輸入與假設!D$172) -> 6.4618938 | E28: =輸入與假設!$C$163*MAX(0,運營_產能與收入!E37*輸入與假設!E$93+輸入與假設!E$51+輸入與假設!E$83-輸入與假設!E$136-輸入與假設!E$172) -> 7.9832773 | F28: =輸入與假設!$C$163*MAX(0,運營_產能與收入!F37*輸入與假設!F$93+輸入與假設!F$51+輸入與假設!F$83-輸入與假設!F$136-輸入與假設!F$172) -> 7.9883923 | G28: =輸入與假設!$C$163*MAX(0,運營_產能與收入!G37*輸入與假設!G$93+輸入與假設!G$51+輸入與假設!G$83-輸入與假設!G$136-輸入與假設!G$172) -> 7.3599526 | I28: ＝稅率 × MAX(0, 損益 EBITDA − 車隊 D&A − 存量利息)；1Q 的稅已含在 CFO 內（v0.1b）
A29: 用途合計（現金口徑） | B29: US$bn | C29: =C13+C16+C21+C22+C24+C25+C26+C27+C28+C23 -> 134.20792 | D29: =D13+D16+D21+D22+D24+D25+D26+D27+D28+D23 -> 129.92796 | E29: =E13+E16+E21+E22+E24+E25+E26+E27+E28+E23 -> 77.719774 | F29: =F13+F16+F21+F22+F24+F25+F26+F27+F28+F23 -> 105.12604 | G29: =G13+G16+G21+G22+G24+G25+G26+G27+G28+G23 -> 106.59349 | I29: FY27 的 1Q 部分採季報現金流量表口徑（現金購置、還款、JV、capped call）；1Q 的利息與租金已含在 CFO 內，不重複列
A30: 來源（四層）
A31: Ⓐ0 1Q27 實際營運現金流（CFO） | B31: US$bn | C31: =輸入與假設!$C$241 -> 23.103 | D31: =0 -> 0 | E31: =0 -> 0 | F31: =0 -> 0 | G31: =0 -> 0 | I31: 季報實際值，取代模型推算；已含 1Q 的利息、租金與客戶預付
A32: Ⓐ RPO 現金（2Q–4Q 起） | B32: US$bn | C32: =運營_產能與收入!C39 -> 26.847106 | D32: =運營_產能與收入!D39 -> 65.163643 | E32: =運營_產能與收入!E39 -> 89.313668 | F32: =運營_產能與收入!F39 -> 77.813395 | G32: =運營_產能與收入!G39 -> 69.855727
A33: Ⓑ 新簽約現金 | B33: US$bn | C33: =運營_產能與收入!C40 -> 0 | D33: =運營_產能與收入!D40 -> 0 | E33: =運營_產能與收入!E40 -> 0 | F33: =運營_產能與收入!F40 -> 14.816852 | G33: =運營_產能與收入!G40 -> 17.041876
A34: Ⓒ 非算力服務現金 | B34: US$bn | C34: =輸入與假設!C$94 -> 0 | D34: =輸入與假設!D$94 -> 0 | E34: =輸入與假設!E$94 -> 0 | F34: =輸入與假設!F$94 -> 0 | G34: =輸入與假設!G$94 -> 0
A35: Ⓒ2 其他事業 EBITDA（2Q–4Q 起） | B35: US$bn | C35: =輸入與假設!C$51 -> 0 | D35: =輸入與假設!D$51 -> 0 | E35: =輸入與假設!E$51 -> 0 | F35: =輸入與假設!F$51 -> 0 | G35: =輸入與假設!G$51 -> 0 | I35: 非核心事業 EBITDA（負值＝燒錢），視為現金（v0.1b）
A36: Ⓒ3 傳統事業 EBITDA（2Q–4Q 起） | B36: US$bn | C36: =輸入與假設!C$83 -> 21.451132 | D36: =輸入與假設!D$83 -> 29.142027 | E36: =輸入與假設!E$83 -> 30.306278 | F36: =輸入與假設!F$83 -> 31.403042 | G36: =輸入與假設!G$83 -> 32.405417 | I36: SaaS、軟體、硬體、服務四線 EBITDA，視為現金（現金稅另列於用途；v0.1b）
A37: Ⓓ 客戶預付（2Q–4Q 起） | B37: US$bn | C37: =C8 -> 18.856035 | D37: =D8 -> 20.903092 | E37: =E8 -> 7.5819838 | F37: =F8 -> 13.363583 | G37: =G8 -> 13.363583
A38: Ⓓ2 減：預付認列（非現金營收） | B38: US$bn | C38: =-C11 -> -2.6248383 | D38: =-D11 -> -7.4626503 | E38: =-E11 -> -11.035453 | F38: =-F11 -> -11.292098 | G38: =-G11 -> -12.764163 | I38: 營收中由合約負債轉入的部分已在預付時收現，不重複計入服務現金（v0.1b）
A39: 營運來源合計 | B39: US$bn | C39: =C31+C32+C33+C34+C35+C36+C37+C38 -> 87.632435 | D39: =D31+D32+D33+D34+D35+D36+D37+D38 -> 107.74611 | E39: =E31+E32+E33+E34+E35+E36+E37+E38 -> 116.16648 | F39: =F31+F32+F33+F34+F35+F36+F37+F38 -> 126.10477 | G39: =G31+G32+G33+G34+G35+G36+G37+G38 -> 119.90244
A40: Ⓔ 股權／可轉債（融資） | B40: US$bn | C40: =輸入與假設!$C$248+IF(輸入與假設!$C$141=1,輸入與假設!$C$140,0) -> 19.909 | D40: =0 -> 0 | E40: =0 -> 0 | F40: =0 -> 0 | G40: =0 -> 0 | I40: FY27＝1Q ATM 淨收入 19.909（141m 股、均價約 $141.84）＋2Q–4Q 期後股權 0
A41: Ⓕ 1Q27 實際借款（融資） | B41: US$bn | C41: =輸入與假設!$C$245 -> 0 | D41: =0 -> 0 | E41: =0 -> 0 | F41: =0 -> 0 | G41: =0 -> 0 | I41: 季報：Q1 借款 0.0（2026-03 可轉債）
A42: Ⓖ 瀑布：新債（額度＋資產層） | B42: US$bn | C42: =C70 -> 9.0434854 | D42: =D70 -> 22.181851 | E42: =E70 -> 0 | F42: =F70 -> 0 | G42: =G70 -> 0 | I42: 見下方「期前融資瀑布」
A43: Ⓖ2 瀑布：可轉債 | B43: US$bn | C43: =C73 -> 0 | D43: =D73 -> 0 | E43: =E73 -> 0 | F43: =F73 -> 0 | G43: =G73 -> 0 | I43: 資產擔保融資用罄後、股權之前；每年不超過可轉債上限（v0.1b）
A44: Ⓗ 瀑布：股權募資 | B44: US$bn | C44: =C76 -> 0 | D44: =D76 -> 0 | E44: =E76 -> 0 | F44: =F76 -> 0 | G44: =G76 -> 0 | I44: 債務與可轉債用罄後的殘差；每年不超過股權吸收上限
A45: Ⓘ 瀑布：高息債（股權上限溢出） | B45: US$bn | C45: =C77 -> 0 | D45: =D77 -> 0 | E45: =E77 -> 0 | F45: =F77 -> 0 | G45: =G77 -> 0 | I45: 股權超過每年上限的部分；不受 backlog 上限約束
A46: 總來源（含融資） | B46: US$bn | C46: =C39+C40+C41+C42+C43+C44+C45 -> 116.58492 | D46: =D39+D40+D41+D42+D43+D44+D45 -> 129.92796 | E46: =E39+E40+E41+E42+E43+E44+E45 -> 116.16648 | F46: =F39+F40+F41+F42+F43+F44+F45 -> 126.10477 | G46: =G39+G40+G41+G42+G43+G44+G45 -> 119.90244
A47: 缺口與現金橋
A48: 1Q 其他／受限現金調節 | B48: US$bn | C48: =輸入與假設!$C$139-(輸入與假設!$C$240+輸入與假設!$C$241+輸入與假設!$C$245+輸入與假設!$C$248-輸入與假設!$C$242-輸入與假設!$C$244-輸入與假設!$C$246-輸入與假設!$C$247-輸入與假設!$C$259) -> -3.666 | D48: =0 -> 0 | E48: =0 -> 0 | F48: =0 -> 0 | G48: =0 -> 0 | I48: 使 1Q 實際流量接回 8/31 現金餘額；差額來自受限現金重分類與未逐項列出的項目
A49: 營運缺口（不含融資、不含還本） | B49: US$bn | C49: =C39-(C29-C26-C27) -> -39.366485 | D49: =D39-(D29-D26-D27) -> -12.034851 | E49: =E39-(E29-E26-E27) -> 43.946703 | F49: =F39-(F29-F26-F27) -> 28.228737 | G49: =G39-(G29-G26-G27) -> 23.058949 | I49: 本業能不能自給：營運來源 −（用途 − 排程還本 − capped call）
A50: 期間缺口（含融資） | B50: US$bn | C50: =C46-C29+C48 -> -21.289 | D50: =D46-D29+D48 -> 0 | E50: =E46-E29+E48 -> 38.446703 | F50: =F46-F29+F48 -> 20.978737 | G50: =G46-G29+G48 -> 13.308949
A51: 期末累積現金 | B51: US$bn | C51: =C18+C50 -> 10 | D51: =D18+D50 -> 10 | E51: =E18+E50 -> 48.446703 | F51: =F18+F50 -> 69.42544 | G51: =G18+G50 -> 82.734389 | I51: 期前融資：每期末不低於最低現金
A53: 期前融資瀑布（缺口在需要前一期先融好：額度 → 資產層新債 → 股權）
A54: 用途（不含新債利息） | B54: US$bn | C54: =C13+C16+C17+C22+C24+C25+C26+C27+C28+C23 -> 133.81453 | D54: =D13+D16+D17+D22+D24+D25+D26+D27+D28+D23 -> 128.11689 | E54: =E13+E16+E17+E22+E24+E25+E26+E27+E28+E23 -> 75.908704 | F54: =F13+F16+F17+F22+F24+F25+F26+F27+F28+F23 -> 103.31497 | G54: =G13+G16+G17+G22+G24+G25+G26+G27+G28+G23 -> 104.78242 | I54: 避免循環參照：直接由各支出列加總
A55: 新債期初餘額 | B55: US$bn | C55: =0 -> 0 | D55: =C82 -> 9.0434854 | E55: =D82 -> 31.225337 | F55: =E82 -> 31.225337 | G55: =F82 -> 31.225337
A56: 新債利率 × 期間長度 | B56: % | C56: =C19*運營_產能與收入!C7 -> 0.0435 | D56: =D19*運營_產能與收入!D7 -> 0.058 | E56: =E19*運營_產能與收入!E7 -> 0.058 | F56: =F19*運營_產能與收入!F7 -> 0.058 | G56: =G19*運營_產能與收入!G7 -> 0.058
A57: 高息債期初餘額 | B57: US$bn | C57: =0 -> 0 | D57: =C84 -> 0 | E57: =D84 -> 0 | F57: =E84 -> 0 | G57: =F84 -> 0
A58: 可轉債（瀑布）期初餘額 | B58: US$bn | C58: =0 -> 0 | D58: =C85 -> 0 | E58: =D85 -> 0 | F58: =E85 -> 0 | G58: =F85 -> 0
A59: 可轉債票息 × 期間長度 | B59: % | C59: =輸入與假設!$C$160*運營_產能與收入!C7 -> 0 | D59: =輸入與假設!$C$160*運營_產能與收入!D7 -> 0 | E59: =輸入與假設!$C$160*運營_產能與收入!E7 -> 0 | F59: =輸入與假設!$C$160*運營_產能與收入!F7 -> 0 | G59: =輸入與假設!$C$160*運營_產能與收入!G7 -> 0
A60: 高息債利率 × 期間長度 | B60: % | C60: =(輸入與假設!$C$162+IF(輸入與假設!$C$165=1,MAX(0,輸入與假設!$C$164-輸入與假設!$C$166)/10000*輸入與假設!$C$167,0))*運營_產能與收入!C7 -> 0.09 | D60: =(輸入與假設!$C$162+IF(輸入與假設!$C$165=1,MAX(0,輸入與假設!$C$164-輸入與假設!$C$166)/10000*輸入與假設!$C$167,0))*運營_產能與收入!D7 -> 0.12 | E60: =(輸入與假設!$C$162+IF(輸入與假設!$C$165=1,MAX(0,輸入與假設!$C$164-輸入與假設!$C$166)/10000*輸入與假設!$C$167,0))*運營_產能與收入!E7 -> 0.12 | F60: =(輸入與假設!$C$162+IF(輸入與假設!$C$165=1,MAX(0,輸入與假設!$C$164-輸入與假設!$C$166)/10000*輸入與假設!$C$167,0))*運營_產能與收入!F7 -> 0.12 | G60: =(輸入與假設!$C$162+IF(輸入與假設!$C$165=1,MAX(0,輸入與假設!$C$164-輸入與假設!$C$166)/10000*輸入與假設!$C$167,0))*運營_產能與收入!G7 -> 0.12
A61: 融資前現金（扣既有新債利息） | B61: US$bn | C61: =C18+C39+C40+C41+C48-C54-C56*C55-C60*C57-C59*C58 -> 1.3499062 | D61: =D18+D39+D40+D41+D48-D54-D56*D55-D60*D57-D59*D58 -> -10.895304 | E61: =E18+E39+E40+E41+E48-E54-E56*E55-E60*E57-E59*E58 -> 48.446703 | F61: =F18+F39+F40+F41+F48-F54-F56*F55-F60*F57-F59*F58 -> 69.42544 | G61: =G18+G39+G40+G41+G48-G54-G56*G55-G60*G57-G59*G58 -> 82.734389
A62: 融資需求（補足至最低現金） | B62: US$bn | C62: =MAX(0,輸入與假設!$C$151-C61) -> 8.6500938 | D62: =MAX(0,輸入與假設!$C$151-D61) -> 20.895304 | E62: =MAX(0,輸入與假設!$C$151-E61) -> 0 | F62: =MAX(0,輸入與假設!$C$151-F61) -> 0 | G62: =MAX(0,輸入與假設!$C$151-G61) -> 0
A63: 期初 backlog | B63: US$bn | C63: =輸入與假設!$C$31+輸入與假設!$C$32 -> 664 | D63: =C65 -> 599.26 | E63: =D65 -> 485.55 | F63: =E65 -> 362.71 | G63: =F65 -> 291.2764 | I63: FY27 期初＝8/31 RPO 664.0＋期後新增 0.0
A64: 新簽合約增量（年化增量×年期） | B64: US$bn | C64: =MAX(0,運營_產能與收入!C23/運營_產能與收入!C7-0)*輸入與假設!$C$148 -> 0 | D64: =MAX(0,運營_產能與收入!D23/運營_產能與收入!D7-運營_產能與收入!C23/運營_產能與收入!C7)*輸入與假設!$C$148 -> 0 | E64: =MAX(0,運營_產能與收入!E23/運營_產能與收入!E7-運營_產能與收入!D23/運營_產能與收入!D7)*輸入與假設!$C$148 -> 0 | F64: =MAX(0,運營_產能與收入!F23/運營_產能與收入!F7-運營_產能與收入!E23/運營_產能與收入!E7)*輸入與假設!$C$148 -> 65.9046 | G64: =MAX(0,運營_產能與收入!G23/運營_產能與收入!G7-運營_產能與收入!F23/運營_產能與收入!F7)*輸入與假設!$C$148 -> 16.7094
A65: 期末 backlog | B65: US$bn | C65: =C63-運營_產能與收入!C17-運營_產能與收入!C23+C64 -> 599.26 | D65: =D63-運營_產能與收入!D17-運營_產能與收入!D23+D64 -> 485.55 | E65: =E63-運營_產能與收入!E17-運營_產能與收入!E23+E64 -> 362.71 | F65: =F63-運營_產能與收入!F17-運營_產能與收入!F23+F64 -> 291.2764 | G65: =G63-運營_產能與收入!G17-運營_產能與收入!G23+G64 -> 167.5678 | I65: ＝期初 − 排程認列 − 新簽約認列 ＋ 新簽合約增量
A66: 既有債務＋期後可轉債（期末） | B66: US$bn | C66: =IF(輸入與假設!$C$144=1,資產負債_既有債務!C80,資產負債_既有債務!$E$62)+資產負債_既有債務!$E$65+資產負債_既有債務!C85 -> 122.897 | D66: =IF(輸入與假設!$C$144=1,資產負債_既有債務!D80,資產負債_既有債務!$E$62)+資產負債_既有債務!$E$65+資產負債_既有債務!D85 -> 112.75 | E66: =IF(輸入與假設!$C$144=1,資產負債_既有債務!E80,資產負債_既有債務!$E$62)+資產負債_既有債務!$E$65+資產負債_既有債務!E85 -> 107.25 | F66: =IF(輸入與假設!$C$144=1,資產負債_既有債務!F80,資產負債_既有債務!$E$62)+資產負債_既有債務!$E$65+資產負債_既有債務!F85 -> 100 | G66: =IF(輸入與假設!$C$144=1,資產負債_既有債務!G80,資產負債_既有債務!$E$62)+資產負債_既有債務!$E$65+資產負債_既有債務!G85 -> 90.25 | I66: ＝(依到期表遞減的既有本金，若關閉攤還則維持 125.904)＋期後新發可轉債 0
A67: 債務上限（投資級：倍數 × 當期 EBITDA；或債務／backlog） | B67: US$bn | C67: =IF(輸入與假設!$C$146="ebitda",輸入與假設!$C$147*損益!C21/運營_產能與收入!C7,輸入與假設!$C$145*C65) -> 225.15394 | D67: =IF(輸入與假設!$C$146="ebitda",輸入與假設!$C$147*損益!D21/運營_產能與收入!D7,輸入與假設!$C$145*D65) -> 324.70215 | E67: =IF(輸入與假設!$C$146="ebitda",輸入與假設!$C$147*損益!E21/運營_產能與收入!E7,輸入與假設!$C$145*E65) -> 402.57538 | F67: =IF(輸入與假設!$C$146="ebitda",輸入與假設!$C$147*損益!F21/運營_產能與收入!F7,輸入與假設!$C$145*F65) -> 411.88709 | G67: =IF(輸入與假設!$C$146="ebitda",輸入與假設!$C$147*損益!G21/運營_產能與收入!G7,輸入與假設!$C$145*G65) -> 393.60726 | I67: ebitda：總債務 ≤ 倍數 × 損益 EBITDA（年化）；backlog：總債務 ≤ 倍數 × 期末 backlog（模板）
A68: 未動用額度（期初） | B68: US$bn | C68: =IF(輸入與假設!$C$143=1,輸入與假設!$C$142,0) -> 0 | D68: =C83 -> 0 | E68: =D83 -> 0 | F68: =E83 -> 0 | G68: =F83 -> 0
A69: 新債可借上限 | B69: US$bn | C69: =MAX(0,C67-(C66+C55+C58),C68) -> 102.25694 | D69: =MAX(0,D67-(D66+D55+D58),D68) -> 202.90866 | E69: =MAX(0,E67-(E66+E55+E58),E68) -> 264.10004 | F69: =MAX(0,F67-(F66+F55+F58),F68) -> 280.66175 | G69: =MAX(0,G67-(G66+G55+G58),G68) -> 272.13192 | I69: ＝MAX(上限 − 既有債務 − 期初新債 − 期初瀑布可轉債, 未動用額度)
A70: 新債舉借 | B70: US$bn | C70: =MIN(C69,C62/(1-C56)) -> 9.0434854 | D70: =MIN(D69,D62/(1-D56)) -> 22.181851 | E70: =MIN(E69,E62/(1-E56)) -> 0 | F70: =MIN(F69,F62/(1-F56)) -> 0 | G70: =MIN(G69,G62/(1-G56)) -> 0 | I70: 期前融資：期初到位，當期全額計息，所以需求要除以 (1−利率×期間)
A71: 債務後剩餘需求 | B71: US$bn | C71: =MAX(0,C62+C56*C70-C70) -> 0 | D71: =MAX(0,D62+D56*D70-D70) -> 0 | E71: =MAX(0,E62+E56*E70-E70) -> 0 | F71: =MAX(0,F62+F56*F70-F70) -> 0 | G71: =MAX(0,G62+G56*G70-G70) -> 0
A72: 可轉債可發行上限 | B72: US$bn | C72: =MAX(0,輸入與假設!$C$159)*運營_產能與收入!C7 -> 0 | D72: =MAX(0,輸入與假設!$C$159)*運營_產能與收入!D7 -> 0 | E72: =MAX(0,輸入與假設!$C$159)*運營_產能與收入!E7 -> 0 | F72: =MAX(0,輸入與假設!$C$159)*運營_產能與收入!F7 -> 0 | G72: =MAX(0,輸入與假設!$C$159)*運營_產能與收入!G7 -> 0 | I72: ＝每年上限（隨情境）× 期間長度
A73: 可轉債發行 | B73: US$bn | C73: =MIN(C72,C71/(1-C59)) -> 0 | D73: =MIN(D72,D71/(1-D59)) -> 0 | E73: =MIN(E72,E71/(1-E59)) -> 0 | F73: =MIN(F72,F71/(1-F59)) -> 0 | G73: =MIN(G72,G71/(1-G59)) -> 0 | I73: 期前融資：期初到位、當期全額計息
A74: 可轉債後剩餘需求 | B74: US$bn | C74: =MAX(0,C71+C59*C73-C73) -> 0 | D74: =MAX(0,D71+D59*D73-D73) -> 0 | E74: =MAX(0,E71+E59*E73-E73) -> 0 | F74: =MAX(0,F71+F59*F73-F73) -> 0 | G74: =MAX(0,G71+G59*G73-G73) -> 0
A75: 每年股權吸收上限 | B75: US$bn | C75: =IF(輸入與假設!$C$154>=9,1E+099,輸入與假設!$C$154*輸入與假設!$C$152*輸入與假設!$C$155*運營_產能與收入!C7) -> 16.415485 | D75: =IF(輸入與假設!$C$154>=9,1E+099,輸入與假設!$C$154*輸入與假設!$C$152*輸入與假設!$C$155*運營_產能與收入!D7) -> 21.887313 | E75: =IF(輸入與假設!$C$154>=9,1E+099,輸入與假設!$C$154*輸入與假設!$C$152*輸入與假設!$C$155*運營_產能與收入!E7) -> 21.887313 | F75: =IF(輸入與假設!$C$154>=9,1E+099,輸入與假設!$C$154*輸入與假設!$C$152*輸入與假設!$C$155*運營_產能與收入!F7) -> 21.887313 | G75: =IF(輸入與假設!$C$154>=9,1E+099,輸入與假設!$C$154*輸入與假設!$C$152*輸入與假設!$C$155*運營_產能與收入!G7) -> 21.887313 | I75: ＝現市值（發行參考價 × 3.02374bn 股）× 上限 % × 期間長度
A76: 股權募資 | B76: US$bn | C76: =MIN(C74,C75) -> 0 | D76: =MIN(D74,D75) -> 0 | E76: =MIN(E74,E75) -> 0 | F76: =MIN(F74,F75) -> 0 | G76: =MIN(G74,G75) -> 0
A77: 高息債舉借（溢出） | B77: US$bn | C77: =(C74-C76)/(1-C60) -> 0 | D77: =(D74-D76)/(1-D60) -> 0 | E77: =(E74-E76)/(1-E60) -> 0 | F77: =(F74-F76)/(1-F60) -> 0 | G77: =(G74-G76)/(1-G60) -> 0
A78: 新債＋高息債利息（期初餘額＋本期舉借） | B78: US$bn | C78: =C56*(C55+C70)+C60*(C57+C77)+C59*(C58+C73) -> 0.39339161 | D78: =D56*(D55+D70)+D60*(D57+D77)+D59*(D58+D73) -> 1.8110695 | E78: =E56*(E55+E70)+E60*(E57+E77)+E59*(E58+E73) -> 1.8110695 | F78: =F56*(F55+F70)+F60*(F57+F77)+F59*(F58+F73) -> 1.8110695 | G78: =G56*(G55+G70)+G60*(G57+G77)+G59*(G58+G73) -> 1.8110695 | I78: 含瀑布可轉債票息（v0.1b）
A79: 發行價（現價×(1−折價)） | B79: US$ | C79: =輸入與假設!$C$152*(1-輸入與假設!$C$153) -> 130.293 | D79: =輸入與假設!$C$152*(1-輸入與假設!$C$153) -> 130.293 | E79: =輸入與假設!$C$152*(1-輸入與假設!$C$153) -> 130.293 | F79: =輸入與假設!$C$152*(1-輸入與假設!$C$153) -> 130.293 | G79: =輸入與假設!$C$152*(1-輸入與假設!$C$153) -> 130.293
A80: 新發行股數 | B80: bn | C80: =C76/C79 -> 0 | D80: =D76/D79 -> 0 | E80: =E76/E79 -> 0 | F80: =F76/F79 -> 0 | G80: =G76/G79 -> 0
A81: 累計新股 | B81: bn | C81: =C80 -> 0 | D81: =C81+D80 -> 0 | E81: =D81+E80 -> 0 | F81: =E81+F80 -> 0 | G81: =F81+G80 -> 0
A82: 新債期末餘額 | B82: US$bn | C82: =C55+C70 -> 9.0434854 | D82: =D55+D70 -> 31.225337 | E82: =E55+E70 -> 31.225337 | F82: =F55+F70 -> 31.225337 | G82: =G55+G70 -> 31.225337
A83: 未動用額度（期末） | B83: US$bn | C83: =C68-MIN(C68,C70) -> 0 | D83: =D68-MIN(D68,D70) -> 0 | E83: =E68-MIN(E68,E70) -> 0 | F83: =F68-MIN(F68,F70) -> 0 | G83: =G68-MIN(G68,G70) -> 0
A84: 高息債期末餘額 | B84: US$bn | C84: =C57+C77 -> 0 | D84: =D57+D77 -> 0 | E84: =E57+E77 -> 0 | F84: =F57+F77 -> 0 | G84: =G57+G77 -> 0
A85: 可轉債（瀑布）期末餘額 | B85: US$bn | C85: =C58+C73 -> 0 | D85: =D58+D73 -> 0 | E85: =E58+E73 -> 0 | F85: =F58+F73 -> 0 | G85: =G58+G73 -> 0
A86: 期末總債務（既有＋可轉債＋新債＋高息債） | B86: US$bn | C86: =C66+C82+C85+C84 -> 131.94049 | D86: =D66+D82+D85+D84 -> 143.97534 | E86: =E66+E82+E85+E84 -> 138.47534 | F86: =F66+F82+F85+F84 -> 131.22534 | G86: =G66+G82+G85+G84 -> 121.47534
A87: 融資前累積現金 | B87: US$bn | C87: =C18+C39+C40+C41+C48-C54 -> 1.3499062 | D87: =C87+D39+D40-D54 -> -19.020876 | E87: =D87+E39+E40-E54 -> 21.236897 | F87: =E87+F39+F40-F54 -> 44.026703 | G87: =F87+G39+G40-G54 -> 59.146722 | I87: 若不做任何新融資的累積現金；負值＝外部資金需求
A89: 四層橋（驗算）
A90: 期初現金（2026-05-31） | C90: =輸入與假設!$C$240 -> 31.289
A91: ＋ 營運缺口合計 | C91: =SUM(C49:G49) -> 43.833052
A92: ＋ 股權／可轉債合計 | C92: =SUM(C40:G40) -> 19.909
A93: ＋ 1Q 實際借款 | C93: =SUM(C41:G41) -> 0
A94: − capped call（1Q） | C94: =-SUM(C27:G27) -> 0
A95: ＋ 1Q 其他／受限現金調節 | C95: =SUM(C48:G48) -> -3.666
A96: ＋ 瀑布新債＋可轉債＋股權＋高息債合計 | C96: =SUM(C42:G42)+SUM(C43:G43)+SUM(C44:G44)+SUM(C45:G45) -> 31.225337
A97: − 排程還本合計 | C97: =-SUM(C26:G26) -> -39.856
A98: ＝ 期末現金（橋算） | C98: =SUM(C90:C97) -> 82.734389
A99: 對照：期末累積現金（表算） | C99: =G51 -> 82.734389
A100: 差異（應為 0） | C100: =C98-C99 -> 0 | I100: 若不為 0，表示公式鏈被改壞
A102: FY27 全年備忘（對照公司指引）
A103: FY27 總營收（1Q 實際＋2Q–4Q 模型） | C103: =運營_產能與收入!C30 -> 90.727495 | I103: 公司指引 ≥90
A104: FY27 CapEx 認列（1Q＋2Q–4Q） | C104: =C6 -> 106.09585 | I104: 公司指引 90–95（法說會二手逐字稿；新聞稿與 10-Q 未列 [Interested-party]）
...

Sheet 季度追蹤
A1: 季度追蹤 — 焦點季的模型／共識／指引／實際與差距（由年度模型拆分；只用於追蹤，不影響年度數字與目標價）
A2: 設定與實際數在『輸入與假設』J 區，共識在 I 區；缺資料顯示「不適用」，實際數空白＝待公布。差距超過門檻的項目附差異原因（拆法＝所屬期間合計差距在門檻內）。第 2 區為 6 季路徑與拆分明細（預設收合）。
A4: 1｜焦點季（『輸入與假設』J 區選擇）：模型／共識／指引／實際與差距
A5: 指標 | B5: 單位 | C5: 模型 | D5: 共識 | E5: 模型 vs 共識 | F5: 指引（低） | G5: 指引（高） | H5: 模型 vs 指引中點 | I5: 實際 | J5: 實際 vs 模型 | K5: 實際 vs 共識 | L5: 實際 vs 指引中點 | M5: 利潤率 pt：模型 vs 共識 | N5: 模型 vs 指引 | O5: 實際 vs 模型 | P5: 實際 vs 共識 | Q5: 實際 vs 指引
A6: 焦點｜營收 | B6: US$bn | C6: =INDEX($C$22:$H$22,輸入與假設!$C$339) -> 21.569582 | D6: =INDEX($C$34:$H$34,輸入與假設!$C$339) -> 21.322 | E6: =INDEX($C$44:$H$44,輸入與假設!$C$339) -> 0.011611597 | F6: =IF(ISNUMBER(INDEX($C$31:$H$31,輸入與假設!$C$339)),INDEX($C$31:$H$31,輸入與假設!$C$339),"不適用") -> 20.875 | G6: =INDEX($C$32:$H$32,輸入與假設!$C$339) -> 21.518 | H6: =INDEX($C$45:$H$45,輸入與假設!$C$339) -> 0.017601135 | I6: =IF(ISNUMBER(INDEX($C$38:$H$38,輸入與假設!$C$339)),INDEX($C$38:$H$38,輸入與假設!$C$339),"待公布") -> 待公布 | J6: =INDEX($C$46:$H$46,輸入與假設!$C$339) | K6: =INDEX($C$47:$H$47,輸入與假設!$C$339) | L6: =INDEX($C$48:$H$48,輸入與假設!$C$339)
A7: 焦點｜調整後 EBITDA | B7: US$bn | C7: =INDEX($C$28:$H$28,輸入與假設!$C$339) -> 12.733986 | D7: =INDEX($C$35:$H$35,輸入與假設!$C$339) -> 12.359 | E7: =INDEX($C$49:$H$49,輸入與假設!$C$339) -> 0.37498587 | F7: 不適用 | G7: 不適用 | H7: =INDEX($C$50:$H$50,輸入與假設!$C$339) -> 不適用 | I7: =IF(ISNUMBER(INDEX($C$39:$H$39,輸入與假設!$C$339)),INDEX($C$39:$H$39,輸入與假設!$C$339),"待公布") -> 待公布 | J7: =INDEX($C$51:$H$51,輸入與假設!$C$339) | K7: =INDEX($C$52:$H$52,輸入與假設!$C$339) | L7: =INDEX($C$53:$H$53,輸入與假設!$C$339) | M7: =INDEX($C$54:$H$54,輸入與假設!$C$339) -> 0.010731694 | N7: =INDEX($C$55:$H$55,輸入與假設!$C$339) -> 不適用 | O7: =INDEX($C$56:$H$56,輸入與假設!$C$339) | P7: =INDEX($C$57:$H$57,輸入與假設!$C$339) | Q7: =INDEX($C$58:$H$58,輸入與假設!$C$339)
A8: 焦點｜EBITDA 率 | B8: % | C8: =INDEX($C$27:$H$27,輸入與假設!$C$339) -> 0.59036775 | D8: =INDEX($C$36:$H$36,輸入與假設!$C$339) -> 0.57963606 | E8: =INDEX($C$59:$H$59,輸入與假設!$C$339) -> 0.010731694 | F8: 不適用 | G8: 不適用 | H8: =INDEX($C$60:$H$60,輸入與假設!$C$339) -> 不適用 | I8: =IF(ISNUMBER(INDEX($C$40:$H$40,輸入與假設!$C$339)),INDEX($C$40:$H$40,輸入與假設!$C$339),"待公布") -> 待公布 | J8: =INDEX($C$61:$H$61,輸入與假設!$C$339) | K8: =INDEX($C$62:$H$62,輸入與假設!$C$339) | L8: =INDEX($C$63:$H$63,輸入與假設!$C$339)
A9: 焦點｜調整後營業利益 | B9: US$bn | C9: =INDEX($C$30:$H$30,輸入與假設!$C$339) -> 9.0392855 | D9: 不適用 | E9: =INDEX($C$64:$H$64,輸入與假設!$C$339) -> 不適用 | F9: 不適用 | G9: 不適用 | H9: =INDEX($C$65:$H$65,輸入與假設!$C$339) -> 不適用 | I9: =IF(ISNUMBER(INDEX($C$41:$H$41,輸入與假設!$C$339)),INDEX($C$41:$H$41,輸入與假設!$C$339),"待公布") -> 待公布 | J9: =INDEX($C$66:$H$66,輸入與假設!$C$339) | K9: =INDEX($C$67:$H$67,輸入與假設!$C$339) | L9: =INDEX($C$68:$H$68,輸入與假設!$C$339) | M9: =INDEX($C$69:$H$69,輸入與假設!$C$339) -> 不適用 | N9: =INDEX($C$70:$H$70,輸入與假設!$C$339) -> 不適用 | O9: =INDEX($C$71:$H$71,輸入與假設!$C$339) | P9: =INDEX($C$72:$H$72,輸入與假設!$C$339) | Q9: =INDEX($C$73:$H$73,輸入與假設!$C$339)
A10: 焦點｜CapEx（毛額） | B10: US$bn | C10: =INDEX($C$33:$H$33,輸入與假設!$C$339) -> 25.865617 | D10: 不適用 | E10: =INDEX($C$74:$H$74,輸入與假設!$C$339) -> 不適用 | F10: 不適用 | G10: 不適用 | H10: =INDEX($C$75:$H$75,輸入與假設!$C$339) -> 不適用 | I10: =IF(ISNUMBER(INDEX($C$42:$H$42,輸入與假設!$C$339)),INDEX($C$42:$H$42,輸入與假設!$C$339),"待公布") -> 待公布 | J10: =INDEX($C$76:$H$76,輸入與假設!$C$339) | K10: =INDEX($C$77:$H$77,輸入與假設!$C$339) | L10: =INDEX($C$78:$H$78,輸入與假設!$C$339)
A11: 焦點｜季末已連網 MW-IT | B11: MW | C11: =INDEX($C$19:$H$19,輸入與假設!$C$339) -> 3251.3333 | D11: 不適用 | E11: =INDEX($C$79:$H$79,輸入與假設!$C$339) -> 不適用 | F11: 不適用 | G11: 不適用 | H11: =INDEX($C$80:$H$80,輸入與假設!$C$339) -> 不適用 | I11: =IF(ISNUMBER(INDEX($C$43:$H$43,輸入與假設!$C$339)),INDEX($C$43:$H$43,輸入與假設!$C$339),"待公布") -> 待公布 | J11: =INDEX($C$81:$H$81,輸入與假設!$C$339) | K11: =INDEX($C$82:$H$82,輸入與假設!$C$339) | L11: =INDEX($C$83:$H$83,輸入與假設!$C$339)
A12: 焦點｜季度 | C12: =INDEX($C$16:$H$16,輸入與假設!$C$339) -> Q2 FY27
A13: 焦點｜差異原因 | C13: =IF(INDEX($C$123:$H$123,輸入與假設!$C$339)="","無（差距皆在 "&IF(ROUND(ABS(輸入與假設!$C$333)*100,4)=INT(ROUND(ABS(輸入與假設!$C$333)*100,4)),TEXT(ROUND(ABS(輸入與假設!$C$333)*100,4),"0"),TEXT(ROUND(ABS(輸入與假設!$C$333)*100,4),"0.0"))&"%"&" 以內）",INDEX($C$123:$H$123,輸入與假設!$C$339)) -> 營收 vs 指引中點 +1.8%：觀點（水準 +$0.218bn（2Q–4Q27 模型 $71.382bn，指引隱含 $70.655bn）；分配 +$0.155bn；OCI 營收＝在役 MW × 每 MW 年收入（Tokenomics 正向推導），期初可計費 MW 以 Q1 實際 OCI 年化校準；傳統事業四線依近四季年增率；共識未揭露 MW 與單價假設）
A15: 2｜6 季路徑、共識、指引、實際與差距（明細；第 1 區以焦點季引用本區）
A16: 項目 | B16: 單位 | C16: Q2 FY27 | D16: Q3 FY27 | E16: Q4 FY27 | F16: Q1 FY28 | G16: Q2 FY28 | H16: Q3 FY28
A17: 所屬期間 | C17: =輸入與假設!C$338 -> 1 | D17: =輸入與假設!D$338 -> 1 | E17: =輸入與假設!E$338 -> 1 | F17: =輸入與假設!F$338 -> 2 | G17: =輸入與假設!G$338 -> 2 | H17: =輸入與假設!H$338 -> 2 | J17: 1＝2Q–4Q27、2＝FY28
A18: 季序 | C18: 1 | D18: 2 | E18: 3 | F18: 4 | G18: 5 | H18: 6 | J18: EBITDA 率直線的 x 軸
A19: 季末已連網 MW-IT（模型） | B19: MW | C19: =輸入與假設!$C$341+(輸入與假設!C$43-輸入與假設!$C$341)*1/3 -> 3251.3333 | D19: =輸入與假設!$C$341+(輸入與假設!C$43-輸入與假設!$C$341)*2/3 -> 3959.6667 | E19: =輸入與假設!$C$341+(輸入與假設!C$43-輸入與假設!$C$341)*3/3 -> 4668 | F19: =輸入與假設!C$43+(輸入與假設!D$43-輸入與假設!C$43)*1/3 -> 5612.3333 | G19: =輸入與假設!C$43+(輸入與假設!D$43-輸入與假設!C$43)*2/3 -> 6556.6667 | H19: =輸入與假設!C$43+(輸入與假設!D$43-輸入與假設!C$43)*3/3 -> 7501 | J19: 期初與期末 Accepted 之間線性內插；第 1 期起點見 J 區
A20: 平均在役 MW（Billable，拆分依據） | B20: MW | C20: =輸入與假設!$C$36+(輸入與假設!C$44-輸入與假設!$C$36)*1/6 -> 1945.5 | D20: =輸入與假設!$C$36+(輸入與假設!C$44-輸入與假設!$C$36)*3/6 -> 2440.5 | E20: =輸入與假設!$C$36+(輸入與假設!C$44-輸入與假設!$C$36)*5/6 -> 2935.5 | F20: =輸入與假設!C$44+(輸入與假設!D$44-輸入與假設!C$44)*1/6 -> 3709.1667 | G20: =輸入與假設!C$44+(輸入與假設!D$44-輸入與假設!C$44)*3/6 -> 4761.5 | H20: =輸入與假設!C$44+(輸入與假設!D$44-輸入與假設!C$44)*5/6 -> 5813.8333 | J20: 期初與期末 Billable 之間線性內插的季平均
A21: 季內新增 Accepted MW | B21: MW | C21: =C19-輸入與假設!$C$341 -> 708.33333 | D21: =D19-C19 -> 708.33333 | E21: =E19-D19 -> 708.33333 | F21: =F19-輸入與假設!C$43 -> 944.33333 | G21: =G19-F19 -> 944.33333 | H21: =H19-G19 -> 944.33333 | J21: CapEx 拆分依據
A22: 營收（模型） | B22: US$bn | C22: =輸入與假設!$C$340+1*(損益!C9-3*輸入與假設!$C$340)/6 -> 21.569582 | D22: =輸入與假設!$C$340+2*(損益!C9-3*輸入與假設!$C$340)/6 -> 23.794165 | E22: =輸入與假設!$C$340+3*(損益!C9-3*輸入與假設!$C$340)/6 -> 26.018747 | F22: =損益!D9*F20/(F20+G20+H20) -> 35.459218 | G22: =損益!D9*G20/(F20+G20+H20) -> 45.519407 | H22: =損益!D9*H20/(F20+G20+H20) -> 55.579596 | J22: 拆分方法見『輸入與假設』J 區與 HTML「拆分方法」
A23: EBITDA 率直線｜各期營收合計 S | C23: =C22+D22+E22 -> 71.382495 | D23: =F22+G22+H22 -> 136.55822 | J23: 欄＝期間（2Q–4Q27、FY28）
A24: EBITDA 率直線｜營收 × 季序合計 T | C24: =C22*C18+D22*D18+E22*E18 -> 147.21415 | D24: =F22*F18+G22*G18+H22*H18 -> 702.91149 | J24: 欄＝期間（2Q–4Q27、FY28）
A25: EBITDA 率直線｜年度 EBITDA E | C25: =損益!C21 -> 42.216364 | D25: =損益!D21 -> 81.175537 | J25: 欄＝期間（2Q–4Q27、FY28）
A26: EBITDA 率直線｜截距 a／斜率 b | C26: =(C25*D24-C24*D25)/(C23*D24-C24*D23) -> 0.58938609 | D26: =(C23*D25-D23*C25)/(C23*D24-C24*D23) -> 0.00098166108 | J26: 解兩式：Σ營收×(a＋b×季序)＝各期年度 EBITDA
A27: EBITDA 率（模型） | B27: % | C27: =$C$26+$D$26*C18 -> 0.59036775 | D27: =$C$26+$D$26*D18 -> 0.59134941 | E27: =$C$26+$D$26*E18 -> 0.59233107 | F27: =$C$26+$D$26*F18 -> 0.59331273 | G27: =$C$26+$D$26*G18 -> 0.59429439 | H27: =$C$26+$D$26*H18 -> 0.59527606 | J27: 跨季一條直線，季度 EBITDA 加總＝年度
A28: 調整後 EBITDA（模型） | B28: US$bn | C28: =C22*C27 -> 12.733986 | D28: =D22*D27 -> 14.070665 | E28: =E22*E27 -> 15.411713 | F28: =F22*F27 -> 21.038406 | G28: =G22*G27 -> 27.051929 | H28: =H22*H27 -> 33.085203
A29: 車隊折舊（模型） | B29: US$bn | C29: =(輸入與假設!C$133+輸入與假設!C$128*1/6)/輸入與假設!$C$105*輸入與假設!C$41/3 -> 3.6947003 | D29: =(輸入與假設!C$133+輸入與假設!C$128*3/6)/輸入與假設!$C$105*輸入與假設!C$41/3 -> 4.7724344 | E29: =(輸入與假設!C$133+輸入與假設!C$128*5/6)/輸入與假設!$C$105*輸入與假設!C$41/3 -> 5.8501684 | F29: =(輸入與假設!D$133+輸入與假設!D$128*1/6)/輸入與假設!$C$105*輸入與假設!D$41/3 -> 9.3152042 | G29: =(輸入與假設!D$133+輸入與假設!D$128*3/6)/輸入與假設!$C$105*輸入與假設!D$41/3 -> 10.908185 | H29: =(輸入與假設!D$133+輸入與假設!D$128*5/6)/輸入與假設!$C$105*輸入與假設!D$41/3 -> 12.501166 | J29: 依期內平均 PP&E（與年度車隊折舊公式相同）
A30: 調整後營業利益（模型） | B30: US$bn | C30: =C28-C29 -> 9.0392855 | D30: =D28-D29 -> 9.2982311 | E30: =E28-E29 -> 9.5615441 | F30: =F28-F29 -> 11.723202 | G30: =G28-G29 -> 16.143744 | H30: =H28-H29 -> 20.584037 | J30: ＝調整後 EBITDA − 車隊折舊（未扣 SBC）
A31: 指引｜營收（低） | B31: US$bn | C31: =IF(ISNUMBER(輸入與假設!C$350),輸入與假設!C$350,"不適用") -> 20.875 | D31: =IF(ISNUMBER(輸入與假設!D$350),輸入與假設!D$350,"不適用") -> 不適用 | E31: =IF(ISNUMBER(輸入與假設!E$350),輸入與假設!E$350,"不適用") -> 不適用 | F31: =IF(ISNUMBER(輸入與假設!F$350),輸入與假設!F$350,"不適用") -> 不適用 | G31: =IF(ISNUMBER(輸入與假設!G$350),輸入與假設!G$350,"不適用") -> 不適用 | H31: =IF(ISNUMBER(輸入與假設!H$350),輸入與假設!H$350,"不適用") -> 不適用
A32: 指引｜營收（高） | B32: US$bn | C32: =IF(ISNUMBER(輸入與假設!C$351),輸入與假設!C$351,"不適用") -> 21.518 | D32: =IF(ISNUMBER(輸入與假設!D$351),輸入與假設!D$351,"不適用") -> 不適用 | E32: =IF(ISNUMBER(輸入與假設!E$351),輸入與假設!E$351,"不適用") -> 不適用 | F32: =IF(ISNUMBER(輸入與假設!F$351),輸入與假設!F$351,"不適用") -> 不適用 | G32: =IF(ISNUMBER(輸入與假設!G$351),輸入與假設!G$351,"不適用") -> 不適用 | H32: =IF(ISNUMBER(輸入與假設!H$351),輸入與假設!H$351,"不適用") -> 不適用
A33: CapEx（毛額）（模型） | B33: US$bn | C33: =IF((C21+D21+E21)>0,輸入與假設!C$135*C21/(C21+D21+E21),輸入與假設!C$135/3) -> 25.865617 | D33: =IF((C21+D21+E21)>0,輸入與假設!C$135*D21/(C21+D21+E21),輸入與假設!C$135/3) -> 25.865617 | E33: =IF((C21+D21+E21)>0,輸入與假設!C$135*E21/(C21+D21+E21),輸入與假設!C$135/3) -> 25.865617 | F33: =IF((F21+G21+H21)>0,輸入與假設!D$135*F21/(F21+G21+H21),輸入與假設!D$135/3) -> 28.673652 | G33: =IF((F21+G21+H21)>0,輸入與假設!D$135*G21/(F21+G21+H21),輸入與假設!D$135/3) -> 28.673652 | H33: =IF((F21+G21+H21)>0,輸入與假設!D$135*H21/(F21+G21+H21),輸入與假設!D$135/3) -> 28.673652 | J33: 依季內新增 Accepted MW
A34: 共識｜營收 | B34: US$bn | C34: =IF(ISNUMBER(輸入與假設!$C$305),輸入與假設!$C$305,"不適用") -> 21.322 | D34: =IF(ISNUMBER(輸入與假設!$D$305),輸入與假設!$D$305,"不適用") -> 23.38 | E34: 不適用 | F34: 不適用 | G34: 不適用 | H34: 不適用 | J34: I 區季度共識 [Interested-party]
A35: 共識｜調整後 EBITDA | B35: US$bn | C35: =IF(ISNUMBER(輸入與假設!$C$306),輸入與假設!$C$306,"不適用") -> 12.359 | D35: =IF(ISNUMBER(輸入與假設!$D$306),輸入與假設!$D$306,"不適用") -> 13.515 | E35: 不適用 | F35: 不適用 | G35: 不適用 | H35: 不適用 | J35: I 區季度共識 [Interested-party]
A36: 共識｜EBITDA 率 [Derived] | B36: % | C36: =IF(AND(ISNUMBER(輸入與假設!$C$306),ISNUMBER(輸入與假設!$C$305)),輸入與假設!$C$306/輸入與假設!$C$305,"不適用") -> 0.57963606 | D36: =IF(AND(ISNUMBER(輸入與假設!$D$306),ISNUMBER(輸入與假設!$D$305)),輸入與假設!$D$306/輸入與假設!$D$305,"不適用") -> 0.57805817 | E36: 不適用 | F36: 不適用 | G36: 不適用 | H36: 不適用 | J36: ＝共識 EBITDA ÷ 共識營收
A37: 共識非 GAAP 營業利益（含 SBC 調整，口徑不同） | B37: US$bn | C37: =IF(ISNUMBER(輸入與假設!$C$307),輸入與假設!$C$307,"不適用") -> 8.536 | D37: =IF(ISNUMBER(輸入與假設!$D$307),輸入與假設!$D$307,"不適用") -> 9.23 | E37: 不適用 | F37: 不適用 | G37: 不適用 | H37: 不適用 | J37: 口徑未揭露：只列不比較
A38: 實際｜營收 | B38: US$bn | C38: =IF(ISNUMBER(輸入與假設!C$342),輸入與假設!C$342,"") | D38: =IF(ISNUMBER(輸入與假設!D$342),輸入與假設!D$342,"") | E38: =IF(ISNUMBER(輸入與假設!E$342),輸入與假設!E$342,"") | F38: =IF(ISNUMBER(輸入與假設!F$342),輸入與假設!F$342,"") | G38: =IF(ISNUMBER(輸入與假設!G$342),輸入與假設!G$342,"") | H38: =IF(ISNUMBER(輸入與假設!H$342),輸入與假設!H$342,"")
A39: 實際｜調整後 EBITDA | B39: US$bn | C39: =IF(ISNUMBER(輸入與假設!C$343),輸入與假設!C$343,"") | D39: =IF(ISNUMBER(輸入與假設!D$343),輸入與假設!D$343,"") | E39: =IF(ISNUMBER(輸入與假設!E$343),輸入與假設!E$343,"") | F39: =IF(ISNUMBER(輸入與假設!F$343),輸入與假設!F$343,"") | G39: =IF(ISNUMBER(輸入與假設!G$343),輸入與假設!G$343,"") | H39: =IF(ISNUMBER(輸入與假設!H$343),輸入與假設!H$343,"")
A40: 實際｜EBITDA 率 | B40: % | C40: =IF(AND(ISNUMBER(輸入與假設!C$343),ISNUMBER(輸入與假設!C$342)),輸入與假設!C$343/輸入與假設!C$342,"") | D40: =IF(AND(ISNUMBER(輸入與假設!D$343),ISNUMBER(輸入與假設!D$342)),輸入與假設!D$343/輸入與假設!D$342,"") | E40: =IF(AND(ISNUMBER(輸入與假設!E$343),ISNUMBER(輸入與假設!E$342)),輸入與假設!E$343/輸入與假設!E$342,"") | F40: =IF(AND(ISNUMBER(輸入與假設!F$343),ISNUMBER(輸入與假設!F$342)),輸入與假設!F$343/輸入與假設!F$342,"") | G40: =IF(AND(ISNUMBER(輸入與假設!G$343),ISNUMBER(輸入與假設!G$342)),輸入與假設!G$343/輸入與假設!G$342,"") | H40: =IF(AND(ISNUMBER(輸入與假設!H$343),ISNUMBER(輸入與假設!H$342)),輸入與假設!H$343/輸入與假設!H$342,"") | J40: ＝實際 EBITDA ÷ 實際營收
A41: 實際｜調整後營業利益 | B41: US$bn | C41: =IF(ISNUMBER(輸入與假設!C$344),輸入與假設!C$344,"") | D41: =IF(ISNUMBER(輸入與假設!D$344),輸入與假設!D$344,"") | E41: =IF(ISNUMBER(輸入與假設!E$344),輸入與假設!E$344,"") | F41: =IF(ISNUMBER(輸入與假設!F$344),輸入與假設!F$344,"") | G41: =IF(ISNUMBER(輸入與假設!G$344),輸入與假設!G$344,"") | H41: =IF(ISNUMBER(輸入與假設!H$344),輸入與假設!H$344,"")
A42: 實際｜CapEx（毛額） | B42: US$bn | C42: =IF(ISNUMBER(輸入與假設!C$345),輸入與假設!C$345,"") | D42: =IF(ISNUMBER(輸入與假設!D$345),輸入與假設!D$345,"") | E42: =IF(ISNUMBER(輸入與假設!E$345),輸入與假設!E$345,"") | F42: =IF(ISNUMBER(輸入與假設!F$345),輸入與假設!F$345,"") | G42: =IF(ISNUMBER(輸入與假設!G$345),輸入與假設!G$345,"") | H42: =IF(ISNUMBER(輸入與假設!H$345),輸入與假設!H$345,"")
A43: 實際｜季末已交付 MW（口徑不明） | B43: MW | C43: =IF(ISNUMBER(輸入與假設!C$346),輸入與假設!C$346,"") | D43: =IF(ISNUMBER(輸入與假設!D$346),輸入與假設!D$346,"") | E43: =IF(ISNUMBER(輸入與假設!E$346),輸入與假設!E$346,"") | F43: =IF(ISNUMBER(輸入與假設!F$346),輸入與假設!F$346,"") | G43: =IF(ISNUMBER(輸入與假設!G$346),輸入與假設!G$346,"") | H43: =IF(ISNUMBER(輸入與假設!H$346),輸入與假設!H$346,"")
A44: 差距｜營收｜模型 vs 共識 | B44: % | C44: =IF(AND(ISNUMBER(C22),ISNUMBER(C34),C34<>0),C22/(C34)-1,"不適用") -> 0.011611597 | D44: =IF(AND(ISNUMBER(D22),ISNUMBER(D34),D34<>0),D22/(D34)-1,"不適用") -> 0.017714497 | E44: =IF(AND(ISNUMBER(E22),ISNUMBER(E34),E34<>0),E22/(E34)-1,"不適用") -> 不適用 | F44: =IF(AND(ISNUMBER(F22),ISNUMBER(F34),F34<>0),F22/(F34)-1,"不適用") -> 不適用 | G44: =IF(AND(ISNUMBER(G22),ISNUMBER(G34),G34<>0),G22/(G34)-1,"不適用") -> 不適用 | H44: =IF(AND(ISNUMBER(H22),ISNUMBER(H34),H34<>0),H22/(H34)-1,"不適用") -> 不適用
A45: 差距｜營收｜模型 vs 指引中點 | B45: % | C45: =IF(AND(ISNUMBER(C22),ISNUMBER(C31),ISNUMBER(C32)),C22/(((C31+C32)/2))-1,"不適用") -> 0.017601135 | D45: =IF(AND(ISNUMBER(D22),ISNUMBER(D31),ISNUMBER(D32)),D22/(((D31+D32)/2))-1,"不適用") -> 不適用 | E45: =IF(AND(ISNUMBER(E22),ISNUMBER(E31),ISNUMBER(E32)),E22/(((E31+E32)/2))-1,"不適用") -> 不適用 | F45: =IF(AND(ISNUMBER(F22),ISNUMBER(F31),ISNUMBER(F32)),F22/(((F31+F32)/2))-1,"不適用") -> 不適用 | G45: =IF(AND(ISNUMBER(G22),ISNUMBER(G31),ISNUMBER(G32)),G22/(((G31+G32)/2))-1,"不適用") -> 不適用 | H45: =IF(AND(ISNUMBER(H22),ISNUMBER(H31),ISNUMBER(H32)),H22/(((H31+H32)/2))-1,"不適用") -> 不適用
A46: 差距｜營收｜實際 vs 模型 | B46: % | C46: =IF(ISNUMBER(C38),IF(AND(ISNUMBER(C22),C22<>0),C38/(C22)-1,"不適用"),"") | D46: =IF(ISNUMBER(D38),IF(AND(ISNUMBER(D22),D22<>0),D38/(D22)-1,"不適用"),"") | E46: =IF(ISNUMBER(E38),IF(AND(ISNUMBER(E22),E22<>0),E38/(E22)-1,"不適用"),"") | F46: =IF(ISNUMBER(F38),IF(AND(ISNUMBER(F22),F22<>0),F38/(F22)-1,"不適用"),"") | G46: =IF(ISNUMBER(G38),IF(AND(ISNUMBER(G22),G22<>0),G38/(G22)-1,"不適用"),"") | H46: =IF(ISNUMBER(H38),IF(AND(ISNUMBER(H22),H22<>0),H38/(H22)-1,"不適用"),"")
A47: 差距｜營收｜實際 vs 共識 | B47: % | C47: =IF(ISNUMBER(C38),IF(AND(ISNUMBER(C34),C34<>0),C38/(C34)-1,"不適用"),"") | D47: =IF(ISNUMBER(D38),IF(AND(ISNUMBER(D34),D34<>0),D38/(D34)-1,"不適用"),"") | E47: =IF(ISNUMBER(E38),IF(AND(ISNUMBER(E34),E34<>0),E38/(E34)-1,"不適用"),"") | F47: =IF(ISNUMBER(F38),IF(AND(ISNUMBER(F34),F34<>0),F38/(F34)-1,"不適用"),"") | G47: =IF(ISNUMBER(G38),IF(AND(ISNUMBER(G34),G34<>0),G38/(G34)-1,"不適用"),"") | H47: =IF(ISNUMBER(H38),IF(AND(ISNUMBER(H34),H34<>0),H38/(H34)-1,"不適用"),"")
A48: 差距｜營收｜實際 vs 指引中點 | B48: % | C48: =IF(ISNUMBER(C38),IF(AND(ISNUMBER(C31),ISNUMBER(C32)),C38/(((C31+C32)/2))-1,"不適用"),"") | D48: =IF(ISNUMBER(D38),IF(AND(ISNUMBER(D31),ISNUMBER(D32)),D38/(((D31+D32)/2))-1,"不適用"),"") | E48: =IF(ISNUMBER(E38),IF(AND(ISNUMBER(E31),ISNUMBER(E32)),E38/(((E31+E32)/2))-1,"不適用"),"") | F48: =IF(ISNUMBER(F38),IF(AND(ISNUMBER(F31),ISNUMBER(F32)),F38/(((F31+F32)/2))-1,"不適用"),"") | G48: =IF(ISNUMBER(G38),IF(AND(ISNUMBER(G31),ISNUMBER(G32)),G38/(((G31+G32)/2))-1,"不適用"),"") | H48: =IF(ISNUMBER(H38),IF(AND(ISNUMBER(H31),ISNUMBER(H32)),H38/(((H31+H32)/2))-1,"不適用"),"")
A49: 差距｜調整後 EBITDA｜模型 vs 共識 | B49: US$bn | C49: =IF(AND(ISNUMBER(C28),ISNUMBER(C35)),C28-(C35),"不適用") -> 0.37498587 | D49: =IF(AND(ISNUMBER(D28),ISNUMBER(D35)),D28-(D35),"不適用") -> 0.55566543 | E49: =IF(AND(ISNUMBER(E28),ISNUMBER(E35)),E28-(E35),"不適用") -> 不適用 | F49: =IF(AND(ISNUMBER(F28),ISNUMBER(F35)),F28-(F35),"不適用") -> 不適用 | G49: =IF(AND(ISNUMBER(G28),ISNUMBER(G35)),G28-(G35),"不適用") -> 不適用 | H49: =IF(AND(ISNUMBER(H28),ISNUMBER(H35)),H28-(H35),"不適用") -> 不適用
A50: 差距｜調整後 EBITDA｜模型 vs 指引中點 | B50: US$bn | C50: 不適用 | D50: 不適用 | E50: 不適用 | F50: 不適用 | G50: 不適用 | H50: 不適用
A51: 差距｜調整後 EBITDA｜實際 vs 模型 | B51: US$bn | C51: =IF(ISNUMBER(C39),IF(AND(ISNUMBER(C28)),C39-(C28),"不適用"),"") | D51: =IF(ISNUMBER(D39),IF(AND(ISNUMBER(D28)),D39-(D28),"不適用"),"") | E51: =IF(ISNUMBER(E39),IF(AND(ISNUMBER(E28)),E39-(E28),"不適用"),"") | F51: =IF(ISNUMBER(F39),IF(AND(ISNUMBER(F28)),F39-(F28),"不適用"),"") | G51: =IF(ISNUMBER(G39),IF(AND(ISNUMBER(G28)),G39-(G28),"不適用"),"") | H51: =IF(ISNUMBER(H39),IF(AND(ISNUMBER(H28)),H39-(H28),"不適用"),"")
A52: 差距｜調整後 EBITDA｜實際 vs 共識 | B52: US$bn | C52: =IF(ISNUMBER(C39),IF(AND(ISNUMBER(C35)),C39-(C35),"不適用"),"") | D52: =IF(ISNUMBER(D39),IF(AND(ISNUMBER(D35)),D39-(D35),"不適用"),"") | E52: =IF(ISNUMBER(E39),IF(AND(ISNUMBER(E35)),E39-(E35),"不適用"),"") | F52: =IF(ISNUMBER(F39),IF(AND(ISNUMBER(F35)),F39-(F35),"不適用"),"") | G52: =IF(ISNUMBER(G39),IF(AND(ISNUMBER(G35)),G39-(G35),"不適用"),"") | H52: =IF(ISNUMBER(H39),IF(AND(ISNUMBER(H35)),H39-(H35),"不適用"),"")
A53: 差距｜調整後 EBITDA｜實際 vs 指引中點 | B53: US$bn | C53: =IF(ISNUMBER(C39),"不適用","") | D53: =IF(ISNUMBER(D39),"不適用","") | E53: =IF(ISNUMBER(E39),"不適用","") | F53: =IF(ISNUMBER(F39),"不適用","") | G53: =IF(ISNUMBER(G39),"不適用","") | H53: =IF(ISNUMBER(H39),"不適用","")
A54: 差距｜調整後 EBITDA｜模型 vs 共識（利潤率 pt） | B54: pt | C54: =IF(AND(ISNUMBER(C28),ISNUMBER(C22),C22<>0,ISNUMBER(C35),ISNUMBER(C34),C34<>0),C28/C22-C35/C34,"不適用") -> 0.010731694 | D54: =IF(AND(ISNUMBER(D28),ISNUMBER(D22),D22<>0,ISNUMBER(D35),ISNUMBER(D34),D34<>0),D28/D22-D35/D34,"不適用") -> 0.013291242 | E54: =IF(AND(ISNUMBER(E28),ISNUMBER(E22),E22<>0,ISNUMBER(E35),ISNUMBER(E34),E34<>0),E28/E22-E35/E34,"不適用") -> 不適用 | F54: =IF(AND(ISNUMBER(F28),ISNUMBER(F22),F22<>0,ISNUMBER(F35),ISNUMBER(F34),F34<>0),F28/F22-F35/F34,"不適用") -> 不適用 | G54: =IF(AND(ISNUMBER(G28),ISNUMBER(G22),G22<>0,ISNUMBER(G35),ISNUMBER(G34),G34<>0),G28/G22-G35/G34,"不適用") -> 不適用 | H54: =IF(AND(ISNUMBER(H28),ISNUMBER(H22),H22<>0,ISNUMBER(H35),ISNUMBER(H34),H34<>0),H28/H22-H35/H34,"不適用") -> 不適用
A55: 差距｜調整後 EBITDA｜模型 vs 指引中點（利潤率 pt） | B55: pt | C55: 不適用 | D55: 不適用 | E55: 不適用 | F55: 不適用 | G55: 不適用 | H55: 不適用
A56: 差距｜調整後 EBITDA｜實際 vs 模型（利潤率 pt） | B56: pt | C56: =IF(ISNUMBER(C39),IF(AND(ISNUMBER(C39),ISNUMBER(C38),C38<>0,ISNUMBER(C28),ISNUMBER(C22),C22<>0),C39/C38-C28/C22,"不適用"),"") | D56: =IF(ISNUMBER(D39),IF(AND(ISNUMBER(D39),ISNUMBER(D38),D38<>0,ISNUMBER(D28),ISNUMBER(D22),D22<>0),D39/D38-D28/D22,"不適用"),"") | E56: =IF(ISNUMBER(E39),IF(AND(ISNUMBER(E39),ISNUMBER(E38),E38<>0,ISNUMBER(E28),ISNUMBER(E22),E22<>0),E39/E38-E28/E22,"不適用"),"") | F56: =IF(ISNUMBER(F39),IF(AND(ISNUMBER(F39),ISNUMBER(F38),F38<>0,ISNUMBER(F28),ISNUMBER(F22),F22<>0),F39/F38-F28/F22,"不適用"),"") | G56: =IF(ISNUMBER(G39),IF(AND(ISNUMBER(G39),ISNUMBER(G38),G38<>0,ISNUMBER(G28),ISNUMBER(G22),G22<>0),G39/G38-G28/G22,"不適用"),"") | H56: =IF(ISNUMBER(H39),IF(AND(ISNUMBER(H39),ISNUMBER(H38),H38<>0,ISNUMBER(H28),ISNUMBER(H22),H22<>0),H39/H38-H28/H22,"不適用"),"")
A57: 差距｜調整後 EBITDA｜實際 vs 共識（利潤率 pt） | B57: pt | C57: =IF(ISNUMBER(C39),IF(AND(ISNUMBER(C39),ISNUMBER(C38),C38<>0,ISNUMBER(C35),ISNUMBER(C34),C34<>0),C39/C38-C35/C34,"不適用"),"") | D57: =IF(ISNUMBER(D39),IF(AND(ISNUMBER(D39),ISNUMBER(D38),D38<>0,ISNUMBER(D35),ISNUMBER(D34),D34<>0),D39/D38-D35/D34,"不適用"),"") | E57: =IF(ISNUMBER(E39),IF(AND(ISNUMBER(E39),ISNUMBER(E38),E38<>0,ISNUMBER(E35),ISNUMBER(E34),E34<>0),E39/E38-E35/E34,"不適用"),"") | F57: =IF(ISNUMBER(F39),IF(AND(ISNUMBER(F39),ISNUMBER(F38),F38<>0,ISNUMBER(F35),ISNUMBER(F34),F34<>0),F39/F38-F35/F34,"不適用"),"") | G57: =IF(ISNUMBER(G39),IF(AND(ISNUMBER(G39),ISNUMBER(G38),G38<>0,ISNUMBER(G35),ISNUMBER(G34),G34<>0),G39/G38-G35/G34,"不適用"),"") | H57: =IF(ISNUMBER(H39),IF(AND(ISNUMBER(H39),ISNUMBER(H38),H38<>0,ISNUMBER(H35),ISNUMBER(H34),H34<>0),H39/H38-H35/H34,"不適用"),"")
A58: 差距｜調整後 EBITDA｜實際 vs 指引中點（利潤率 pt） | B58: pt | C58: =IF(ISNUMBER(C39),"不適用","") | D58: =IF(ISNUMBER(D39),"不適用","") | E58: =IF(ISNUMBER(E39),"不適用","") | F58: =IF(ISNUMBER(F39),"不適用","") | G58: =IF(ISNUMBER(G39),"不適用","") | H58: =IF(ISNUMBER(H39),"不適用","")
A59: 差距｜EBITDA 率｜模型 vs 共識 | B59: pt | C59: =IF(AND(ISNUMBER(C27),ISNUMBER(C36)),C27-(C36),"不適用") -> 0.010731694 | D59: =IF(AND(ISNUMBER(D27),ISNUMBER(D36)),D27-(D36),"不適用") -> 0.013291242 | E59: =IF(AND(ISNUMBER(E27),ISNUMBER(E36)),E27-(E36),"不適用") -> 不適用 | F59: =IF(AND(ISNUMBER(F27),ISNUMBER(F36)),F27-(F36),"不適用") -> 不適用 | G59: =IF(AND(ISNUMBER(G27),ISNUMBER(G36)),G27-(G36),"不適用") -> 不適用 | H59: =IF(AND(ISNUMBER(H27),ISNUMBER(H36)),H27-(H36),"不適用") -> 不適用
A60: 差距｜EBITDA 率｜模型 vs 指引中點 | B60: pt | C60: 不適用 | D60: 不適用 | E60: 不適用 | F60: 不適用 | G60: 不適用 | H60: 不適用
A61: 差距｜EBITDA 率｜實際 vs 模型 | B61: pt | C61: =IF(ISNUMBER(C40),IF(AND(ISNUMBER(C27)),C40-(C27),"不適用"),"") | D61: =IF(ISNUMBER(D40),IF(AND(ISNUMBER(D27)),D40-(D27),"不適用"),"") | E61: =IF(ISNUMBER(E40),IF(AND(ISNUMBER(E27)),E40-(E27),"不適用"),"") | F61: =IF(ISNUMBER(F40),IF(AND(ISNUMBER(F27)),F40-(F27),"不適用"),"") | G61: =IF(ISNUMBER(G40),IF(AND(ISNUMBER(G27)),G40-(G27),"不適用"),"") | H61: =IF(ISNUMBER(H40),IF(AND(ISNUMBER(H27)),H40-(H27),"不適用"),"")
A62: 差距｜EBITDA 率｜實際 vs 共識 | B62: pt | C62: =IF(ISNUMBER(C40),IF(AND(ISNUMBER(C36)),C40-(C36),"不適用"),"") | D62: =IF(ISNUMBER(D40),IF(AND(ISNUMBER(D36)),D40-(D36),"不適用"),"") | E62: =IF(ISNUMBER(E40),IF(AND(ISNUMBER(E36)),E40-(E36),"不適用"),"") | F62: =IF(ISNUMBER(F40),IF(AND(ISNUMBER(F36)),F40-(F36),"不適用"),"") | G62: =IF(ISNUMBER(G40),IF(AND(ISNUMBER(G36)),G40-(G36),"不適用"),"") | H62: =IF(ISNUMBER(H40),IF(AND(ISNUMBER(H36)),H40-(H36),"不適用"),"")
A63: 差距｜EBITDA 率｜實際 vs 指引中點 | B63: pt | C63: =IF(ISNUMBER(C40),"不適用","") | D63: =IF(ISNUMBER(D40),"不適用","") | E63: =IF(ISNUMBER(E40),"不適用","") | F63: =IF(ISNUMBER(F40),"不適用","") | G63: =IF(ISNUMBER(G40),"不適用","") | H63: =IF(ISNUMBER(H40),"不適用","")
A64: 差距｜調整後營業利益｜模型 vs 共識 | B64: US$bn | C64: 不適用 | D64: 不適用 | E64: 不適用 | F64: 不適用 | G64: 不適用 | H64: 不適用
A65: 差距｜調整後營業利益｜模型 vs 指引中點 | B65: US$bn | C65: 不適用 | D65: 不適用 | E65: 不適用 | F65: 不適用 | G65: 不適用 | H65: 不適用
A66: 差距｜調整後營業利益｜實際 vs 模型 | B66: US$bn | C66: =IF(ISNUMBER(C41),IF(AND(ISNUMBER(C30)),C41-(C30),"不適用"),"") | D66: =IF(ISNUMBER(D41),IF(AND(ISNUMBER(D30)),D41-(D30),"不適用"),"") | E66: =IF(ISNUMBER(E41),IF(AND(ISNUMBER(E30)),E41-(E30),"不適用"),"") | F66: =IF(ISNUMBER(F41),IF(AND(ISNUMBER(F30)),F41-(F30),"不適用"),"") | G66: =IF(ISNUMBER(G41),IF(AND(ISNUMBER(G30)),G41-(G30),"不適用"),"") | H66: =IF(ISNUMBER(H41),IF(AND(ISNUMBER(H30)),H41-(H30),"不適用"),"")
A67: 差距｜調整後營業利益｜實際 vs 共識 | B67: US$bn | C67: =IF(ISNUMBER(C41),"不適用","") | D67: =IF(ISNUMBER(D41),"不適用","") | E67: =IF(ISNUMBER(E41),"不適用","") | F67: =IF(ISNUMBER(F41),"不適用","") | G67: =IF(ISNUMBER(G41),"不適用","") | H67: =IF(ISNUMBER(H41),"不適用","")
A68: 差距｜調整後營業利益｜實際 vs 指引中點 | B68: US$bn | C68: =IF(ISNUMBER(C41),"不適用","") | D68: =IF(ISNUMBER(D41),"不適用","") | E68: =IF(ISNUMBER(E41),"不適用","") | F68: =IF(ISNUMBER(F41),"不適用","") | G68: =IF(ISNUMBER(G41),"不適用","") | H68: =IF(ISNUMBER(H41),"不適用","")
A69: 差距｜調整後營業利益｜模型 vs 共識（利潤率 pt） | B69: pt | C69: 不適用 | D69: 不適用 | E69: 不適用 | F69: 不適用 | G69: 不適用 | H69: 不適用
A70: 差距｜調整後營業利益｜模型 vs 指引中點（利潤率 pt） | B70: pt | C70: 不適用 | D70: 不適用 | E70: 不適用 | F70: 不適用 | G70: 不適用 | H70: 不適用
A71: 差距｜調整後營業利益｜實際 vs 模型（利潤率 pt） | B71: pt | C71: =IF(ISNUMBER(C41),IF(AND(ISNUMBER(C41),ISNUMBER(C38),C38<>0,ISNUMBER(C30),ISNUMBER(C22),C22<>0),C41/C38-C30/C22,"不適用"),"") | D71: =IF(ISNUMBER(D41),IF(AND(ISNUMBER(D41),ISNUMBER(D38),D38<>0,ISNUMBER(D30),ISNUMBER(D22),D22<>0),D41/D38-D30/D22,"不適用"),"") | E71: =IF(ISNUMBER(E41),IF(AND(ISNUMBER(E41),ISNUMBER(E38),E38<>0,ISNUMBER(E30),ISNUMBER(E22),E22<>0),E41/E38-E30/E22,"不適用"),"") | F71: =IF(ISNUMBER(F41),IF(AND(ISNUMBER(F41),ISNUMBER(F38),F38<>0,ISNUMBER(F30),ISNUMBER(F22),F22<>0),F41/F38-F30/F22,"不適用"),"") | G71: =IF(ISNUMBER(G41),IF(AND(ISNUMBER(G41),ISNUMBER(G38),G38<>0,ISNUMBER(G30),ISNUMBER(G22),G22<>0),G41/G38-G30/G22,"不適用"),"") | H71: =IF(ISNUMBER(H41),IF(AND(ISNUMBER(H41),ISNUMBER(H38),H38<>0,ISNUMBER(H30),ISNUMBER(H22),H22<>0),H41/H38-H30/H22,"不適用"),"")
A72: 差距｜調整後營業利益｜實際 vs 共識（利潤率 pt） | B72: pt | C72: =IF(ISNUMBER(C41),"不適用","") | D72: =IF(ISNUMBER(D41),"不適用","") | E72: =IF(ISNUMBER(E41),"不適用","") | F72: =IF(ISNUMBER(F41),"不適用","") | G72: =IF(ISNUMBER(G41),"不適用","") | H72: =IF(ISNUMBER(H41),"不適用","")
A73: 差距｜調整後營業利益｜實際 vs 指引中點（利潤率 pt） | B73: pt | C73: =IF(ISNUMBER(C41),"不適用","") | D73: =IF(ISNUMBER(D41),"不適用","") | E73: =IF(ISNUMBER(E41),"不適用","") | F73: =IF(ISNUMBER(F41),"不適用","") | G73: =IF(ISNUMBER(G41),"不適用","") | H73: =IF(ISNUMBER(H41),"不適用","")
A74: 差距｜CapEx（毛額）｜模型 vs 共識 | B74: % | C74: 不適用 | D74: 不適用 | E74: 不適用 | F74: 不適用 | G74: 不適用 | H74: 不適用
A75: 差距｜CapEx（毛額）｜模型 vs 指引中點 | B75: % | C75: 不適用 | D75: 不適用 | E75: 不適用 | F75: 不適用 | G75: 不適用 | H75: 不適用
A76: 差距｜CapEx（毛額）｜實際 vs 模型 | B76: % | C76: =IF(ISNUMBER(C42),IF(AND(ISNUMBER(C33),C33<>0),C42/(C33)-1,"不適用"),"") | D76: =IF(ISNUMBER(D42),IF(AND(ISNUMBER(D33),D33<>0),D42/(D33)-1,"不適用"),"") | E76: =IF(ISNUMBER(E42),IF(AND(ISNUMBER(E33),E33<>0),E42/(E33)-1,"不適用"),"") | F76: =IF(ISNUMBER(F42),IF(AND(ISNUMBER(F33),F33<>0),F42/(F33)-1,"不適用"),"") | G76: =IF(ISNUMBER(G42),IF(AND(ISNUMBER(G33),G33<>0),G42/(G33)-1,"不適用"),"") | H76: =IF(ISNUMBER(H42),IF(AND(ISNUMBER(H33),H33<>0),H42/(H33)-1,"不適用"),"")
A77: 差距｜CapEx（毛額）｜實際 vs 共識 | B77: % | C77: =IF(ISNUMBER(C42),"不適用","") | D77: =IF(ISNUMBER(D42),"不適用","") | E77: =IF(ISNUMBER(E42),"不適用","") | F77: =IF(ISNUMBER(F42),"不適用","") | G77: =IF(ISNUMBER(G42),"不適用","") | H77: =IF(ISNUMBER(H42),"不適用","")
A78: 差距｜CapEx（毛額）｜實際 vs 指引中點 | B78: % | C78: =IF(ISNUMBER(C42),"不適用","") | D78: =IF(ISNUMBER(D42),"不適用","") | E78: =IF(ISNUMBER(E42),"不適用","") | F78: =IF(ISNUMBER(F42),"不適用","") | G78: =IF(ISNUMBER(G42),"不適用","") | H78: =IF(ISNUMBER(H42),"不適用","")
A79: 差距｜季末已連網 MW-IT｜模型 vs 共識 | B79: MW | C79: 不適用 | D79: 不適用 | E79: 不適用 | F79: 不適用 | G79: 不適用 | H79: 不適用
A80: 差距｜季末已連網 MW-IT｜模型 vs 指引中點 | B80: MW | C80: 不適用 | D80: 不適用 | E80: 不適用 | F80: 不適用 | G80: 不適用 | H80: 不適用
A81: 差距｜季末已連網 MW-IT｜實際 vs 模型 | B81: MW | C81: =IF(ISNUMBER(C43),IF(AND(ISNUMBER(C19)),C43-(C19),"不適用"),"") | D81: =IF(ISNUMBER(D43),IF(AND(ISNUMBER(D19)),D43-(D19),"不適用"),"") | E81: =IF(ISNUMBER(E43),IF(AND(ISNUMBER(E19)),E43-(E19),"不適用"),"") | F81: =IF(ISNUMBER(F43),IF(AND(ISNUMBER(F19)),F43-(F19),"不適用"),"") | G81: =IF(ISNUMBER(G43),IF(AND(ISNUMBER(G19)),G43-(G19),"不適用"),"") | H81: =IF(ISNUMBER(H43),IF(AND(ISNUMBER(H19)),H43-(H19),"不適用"),"")
A82: 差距｜季末已連網 MW-IT｜實際 vs 共識 | B82: MW | C82: =IF(ISNUMBER(C43),"不適用","") | D82: =IF(ISNUMBER(D43),"不適用","") | E82: =IF(ISNUMBER(E43),"不適用","") | F82: =IF(ISNUMBER(F43),"不適用","") | G82: =IF(ISNUMBER(G43),"不適用","") | H82: =IF(ISNUMBER(H43),"不適用","")
A83: 差距｜季末已連網 MW-IT｜實際 vs 指引中點 | B83: MW | C83: =IF(ISNUMBER(C43),"不適用","") | D83: =IF(ISNUMBER(D43),"不適用","") | E83: =IF(ISNUMBER(E43),"不適用","") | F83: =IF(ISNUMBER(F43),"不適用","") | G83: =IF(ISNUMBER(G43),"不適用","") | H83: =IF(ISNUMBER(H43),"不適用","")
A84: 合計基準｜營收｜vs 共識 | B84: US$bn | C84: =IF(COUNT(C34,D34,E34)=3,C34+D34+E34,"不適用") -> 不適用 | D84: =IF(COUNT(C34,D34,E34)=3,C34+D34+E34,"不適用") -> 不適用 | E84: =IF(COUNT(C34,D34,E34)=3,C34+D34+E34,"不適用") -> 不適用 | F84: =IF(COUNT(F34,G34,H34)=3,F34+G34+H34,"不適用") -> 不適用 | G84: =IF(COUNT(F34,G34,H34)=3,F34+G34+H34,"不適用") -> 不適用 | H84: =IF(COUNT(F34,G34,H34)=3,F34+G34+H34,"不適用") -> 不適用 | J84: 所屬期間的季度共識合計
A85: 拆解｜營收｜vs 共識｜水準 | B85: US$bn | C85: =IF(AND(ISNUMBER(C84),C84<>0,ISNUMBER(C34),ISNUMBER(C22)),(損益!C9-C84)*(C34)/C84,"不適用") -> 不適用 | D85: =IF(AND(ISNUMBER(D84),D84<>0,ISNUMBER(D34),ISNUMBER(D22)),(損益!C9-D84)*(D34)/D84,"不適用") -> 不適用 | E85: =IF(AND(ISNUMBER(E84),E84<>0,ISNUMBER(E34),ISNUMBER(E22)),(損益!C9-E84)*(E34)/E84,"不適用") -> 不適用 | F85: =IF(AND(ISNUMBER(F84),F84<>0,ISNUMBER(F34),ISNUMBER(F22)),(損益!D9-F84)*(F34)/F84,"不適用") -> 不適用 | G85: =IF(AND(ISNUMBER(G84),G84<>0,ISNUMBER(G34),ISNUMBER(G22)),(損益!D9-G84)*(G34)/G84,"不適用") -> 不適用 | H85: =IF(AND(ISNUMBER(H84),H84<>0,ISNUMBER(H34),ISNUMBER(H22)),(損益!D9-H84)*(H34)/H84,"不適用") -> 不適用 | J85: (模型期間 − 比較期間) × 比較的季占比
A86: 拆解｜營收｜vs 共識｜分配 | B86: US$bn | C86: =IF(AND(ISNUMBER(C84),C84<>0,ISNUMBER(C34),ISNUMBER(C22)),(C22/損益!C9-(C34)/C84)*損益!C9,"不適用") -> 不適用 | D86: =IF(AND(ISNUMBER(D84),D84<>0,ISNUMBER(D34),ISNUMBER(D22)),(D22/損益!C9-(D34)/D84)*損益!C9,"不適用") -> 不適用 | E86: =IF(AND(ISNUMBER(E84),E84<>0,ISNUMBER(E34),ISNUMBER(E22)),(E22/損益!C9-(E34)/E84)*損益!C9,"不適用") -> 不適用 | F86: =IF(AND(ISNUMBER(F84),F84<>0,ISNUMBER(F34),ISNUMBER(F22)),(F22/損益!D9-(F34)/F84)*損益!D9,"不適用") -> 不適用 | G86: =IF(AND(ISNUMBER(G84),G84<>0,ISNUMBER(G34),ISNUMBER(G22)),(G22/損益!D9-(G34)/G84)*損益!D9,"不適用") -> 不適用 | H86: =IF(AND(ISNUMBER(H84),H84<>0,ISNUMBER(H34),ISNUMBER(H22)),(H22/損益!D9-(H34)/H84)*損益!D9,"不適用") -> 不適用 | J86: (模型季占比 − 比較季占比) × 模型期間；水準＋分配＝季度差距
A87: 合計基準｜營收｜vs 指引 | B87: US$bn | C87: =(輸入與假設!$C$352+輸入與假設!$D$352)/2-輸入與假設!$E$352 -> 70.655 | D87: =(輸入與假設!$C$352+輸入與假設!$D$352)/2-輸入與假設!$E$352 -> 70.655 | E87: =(輸入與假設!$C$352+輸入與假設!$D$352)/2-輸入與假設!$E$352 -> 70.655 | F87: 不適用 | G87: 不適用 | H87: 不適用 | J87: 所屬期間的隱含指引中點（全年指引中點 − 1Q 實際）
A88: 拆解｜營收｜vs 指引｜水準 | B88: US$bn | C88: =IF(AND(ISNUMBER(C87),C87<>0,ISNUMBER(((C31+C32)/2)),ISNUMBER(C22)),(損益!C9-C87)*(((C31+C32)/2))/C87,"不適用") -> 0.21824844 | D88: =IF(AND(ISNUMBER(D87),D87<>0,ISNUMBER(((D31+D32)/2)),ISNUMBER(D22)),(損益!C9-D87)*(((D31+D32)/2))/D87,"不適用") -> 不適用 | E88: =IF(AND(ISNUMBER(E87),E87<>0,ISNUMBER(((E31+E32)/2)),ISNUMBER(E22)),(損益!C9-E87)*(((E31+E32)/2))/E87,"不適用") -> 不適用 | F88: =IF(AND(ISNUMBER(F87),F87<>0,ISNUMBER(((F31+F32)/2)),ISNUMBER(F22)),(損益!D9-F87)*(((F31+F32)/2))/F87,"不適用") -> 不適用 | G88: =IF(AND(ISNUMBER(G87),G87<>0,ISNUMBER(((G31+G32)/2)),ISNUMBER(G22)),(損益!D9-G87)*(((G31+G32)/2))/G87,"不適用") -> 不適用 | H88: =IF(AND(ISNUMBER(H87),H87<>0,ISNUMBER(((H31+H32)/2)),ISNUMBER(H22)),(損益!D9-H87)*(((H31+H32)/2))/H87,"不適用") -> 不適用 | J88: (模型期間 − 比較期間) × 比較的季占比
A89: 拆解｜營收｜vs 指引｜分配 | B89: US$bn | C89: =IF(AND(ISNUMBER(C87),C87<>0,ISNUMBER(((C31+C32)/2)),ISNUMBER(C22)),(C22/損益!C9-(((C31+C32)/2))/C87)*損益!C9,"不適用") -> 0.15483403 | D89: =IF(AND(ISNUMBER(D87),D87<>0,ISNUMBER(((D31+D32)/2)),ISNUMBER(D22)),(D22/損益!C9-(((D31+D32)/2))/D87)*損益!C9,"不適用") -> 不適用 | E89: =IF(AND(ISNUMBER(E87),E87<>0,ISNUMBER(((E31+E32)/2)),ISNUMBER(E22)),(E22/損益!C9-(((E31+E32)/2))/E87)*損益!C9,"不適用") -> 不適用 | F89: =IF(AND(ISNUMBER(F87),F87<>0,ISNUMBER(((F31+F32)/2)),ISNUMBER(F22)),(F22/損益!D9-(((F31+F32)/2))/F87)*損益!D9,"不適用") -> 不適用 | G89: =IF(AND(ISNUMBER(G87),G87<>0,ISNUMBER(((G31+G32)/2)),ISNUMBER(G22)),(G22/損益!D9-(((G31+G32)/2))/G87)*損益!D9,"不適用") -> 不適用 | H89: =IF(AND(ISNUMBER(H87),H87<>0,ISNUMBER(((H31+H32)/2)),ISNUMBER(H22)),(H22/損益!D9-(((H31+H32)/2))/H87)*損益!D9,"不適用") -> 不適用 | J89: (模型季占比 − 比較季占比) × 模型期間；水準＋分配＝季度差距
A90: 原因｜營收｜vs 共識 | C90: =IF(ISNUMBER(C44),IF(ABS(C44)>輸入與假設!$C$333,IF(ISNUMBER(C85),IF(ABS(C86)>ABS(C85),"營收 vs 共識 "&IF(C44<0,"−","+")&TEXT(ABS(C44)*100,"#,##0.0")&"%"&"：拆法（分配 "&IF(C86<0,"−","+")&IF(ABS(C86)<0,"−","")&"$"&TEXT(ABS(ABS(C86)),"#,##0.000")&"bn"&"（Q2 FY27 占 2Q–4Q27 "&TEXT((C22/損益!C9)*100,"#,##0.0")&"%"&"，共識合計 "&TEXT(((C34)/C84)*100,"#,##0.0")&"%"&"）；水準 "&IF(C85<0,"−","+")&IF(ABS(C85)<0,"−","")&"$"&TEXT(ABS(ABS(C85)),"#,##0.000")&"bn"&"）","營收 vs 共識 "&IF(C44<0,"−","+")&TEXT(ABS(C44)*100,"#,##0.0")&"%"&"：觀點（水準 "&IF(C85<0,"−","+")&IF(ABS(C85)<0,"−","")&"$"&TEXT(ABS(ABS(C85)),"#,##0.000")&"bn"&"（2Q–4Q27 模型 "&IF(損益!C9<0,"−","")&"$"&TEXT(ABS(損益!C9),"#,##0.000")&"bn"&"，共識合計 "&IF(C84<0,"−","")&"$"&TEXT(ABS(C84),"#,##0.000")&"bn"&"）；分配 "&IF(C86<0,"−","+")&IF(ABS(C86)<0,"−","")&"$"&TEXT(ABS(ABS(C86)),"#,##0.000")&"bn"&"；"&"OCI 營收＝在役 MW × 每 MW 年收入（Tokenomics 正向推導），期初可計費 MW 以 Q1 實際 OCI 年化校準；傳統事業四線依近四季年增率；共識未揭露 MW 與單價假設"&"）"),"營收 vs 共識 "&IF(C44<0,"−","+")&TEXT(ABS(C44)*100,"#,##0.0")&"%"&"：觀點（"&"OCI 營收＝在役 MW × 每 MW 年收入（Tokenomics 正向推導），期初可計費 MW 以 Q1 實際 OCI 年化校準；傳統事業四線依近四季年增率；共識未揭露 MW 與單價假設"&"）"),""),"") | D90: =IF(ISNUMBER(D44),IF(ABS(D44)>輸入與假設!$C$333,IF(ISNUMBER(D85),IF(ABS(D86)>ABS(D85),"營收 vs 共識 "&IF(D44<0,"−","+")&TEXT(ABS(D44)*100,"#,##0.0")&"%"&"：拆法（分配 "&IF(D86<0,"−","+")&IF(ABS(D86)<0,"−","")&"$"&TEXT(ABS(ABS(D86)),"#,##0.000")&"bn"&"（Q3 FY27 占 2Q–4Q27 "&TEXT((D22/損益!C9)*100,"#,##0.0")&"%"&"，共識合計 "&TEXT(((D34)/D84)*100,"#,##0.0")&"%"&"）；水準 "&IF(D85<0,"−","+")&IF(ABS(D85)<0,"−","")&"$"&TEXT(ABS(ABS(D85)),"#,##0.000")&"bn"&"）","營收 vs 共識 "&IF(D44<0,"−","+")&TEXT(ABS(D44)*100,"#,##0.0")&"%"&"：觀點（水準 "&IF(D85<0,"−","+")&IF(ABS(D85)<0,"−","")&"$"&TEXT(ABS(ABS(D85)),"#,##0.000")&"bn"&"（2Q–4Q27 模型 "&IF(損益!C9<0,"−","")&"$"&TEXT(ABS(損益!C9),"#,##0.000")&"bn"&"，共識合計 "&IF(D84<0,"−","")&"$"&TEXT(ABS(D84),"#,##0.000")&"bn"&"）；分配 "&IF(D86<0,"−","+")&IF(ABS(D86)<0,"−","")&"$"&TEXT(ABS(ABS(D86)),"#,##0.000")&"bn"&"；"&"OCI 營收＝在役 MW × 每 MW 年收入（Tokenomics 正向推導），期初可計費 MW 以 Q1 實際 OCI 年化校準；傳統事業四線依近四季年增率；共識未揭露 MW 與單價假設"&"）"),"營收 vs 共識 "&IF(D44<0,"−","+")&TEXT(ABS(D44)*100,"#,##0.0")&"%"&"：觀點（"&"OCI 營收＝在役 MW × 每 MW 年收入（Tokenomics 正向推導），期初可計費 MW 以 Q1 實際 OCI 年化校準；傳統事業四線依近四季年增率；共識未揭露 MW 與單價假設"&"）"),""),"") | E90: =IF(ISNUMBER(E44),IF(ABS(E44)>輸入與假設!$C$333,IF(ISNUMBER(E85),IF(ABS(E86)>ABS(E85),"營收 vs 共識 "&IF(E44<0,"−","+")&TEXT(ABS(E44)*100,"#,##0.0")&"%"&"：拆法（分配 "&IF(E86<0,"−","+")&IF(ABS(E86)<0,"−","")&"$"&TEXT(ABS(ABS(E86)),"#,##0.000")&"bn"&"（Q4 FY27 占 2Q–4Q27 "&TEXT((E22/損益!C9)*100,"#,##0.0")&"%"&"，共識合計 "&TEXT(((E34)/E84)*100,"#,##0.0")&"%"&"）；水準 "&IF(E85<0,"−","+")&IF(ABS(E85)<0,"−","")&"$"&TEXT(ABS(ABS(E85)),"#,##0.000")&"bn"&"）","營收 vs 共識 "&IF(E44<0,"−","+")&TEXT(ABS(E44)*100,"#,##0.0")&"%"&"：觀點（水準 "&IF(E85<0,"−","+")&IF(ABS(E85)<0,"−","")&"$"&TEXT(ABS(ABS(E85)),"#,##0.000")&"bn"&"（2Q–4Q27 模型 "&IF(損益!C9<0,"−","")&"$"&TEXT(ABS(損益!C9),"#,##0.000")&"bn"&"，共識合計 "&IF(E84<0,"−","")&"$"&TEXT(ABS(E84),"#,##0.000")&"bn"&"）；分配 "&IF(E86<0,"−","+")&IF(ABS(E86)<0,"−","")&"$"&TEXT(ABS(ABS(E86)),"#,##0.000")&"bn"&"；"&"OCI 營收＝在役 MW × 每 MW 年收入（Tokenomics 正向推導），期初可計費 MW 以 Q1 實際 OCI 年化校準；傳統事業四線依近四季年增率；共識未揭露 MW 與單價假設"&"）"),"營收 vs 共識 "&IF(E44<0,"−","+")&TEXT(ABS(E44)*100,"#,##0.0")&"%"&"：觀點（"&"OCI 營收＝在役 MW × 每 MW 年收入（Tokenomics 正向推導），期初可計費 MW 以 Q1 實際 OCI 年化校準；傳統事業四線依近四季年增率；共識未揭露 MW 與單價假設"&"）"),""),"") | F90: =IF(ISNUMBER(F44),IF(ABS(F44)>輸入與假設!$C$333,IF(ISNUMBER(F85),IF(ABS(F86)>ABS(F85),"營收 vs 共識 "&IF(F44<0,"−","+")&TEXT(ABS(F44)*100,"#,##0.0")&"%"&"：拆法（分配 "&IF(F86<0,"−","+")&IF(ABS(F86)<0,"−","")&"$"&TEXT(ABS(ABS(F86)),"#,##0.000")&"bn"&"（Q1 FY28 占 FY28 "&TEXT((F22/損益!D9)*100,"#,##0.0")&"%"&"，共識合計 "&TEXT(((F34)/F84)*100,"#,##0.0")&"%"&"）；水準 "&IF(F85<0,"−","+")&IF(ABS(F85)<0,"−","")&"$"&TEXT(ABS(ABS(F85)),"#,##0.000")&"bn"&"）","營收 vs 共識 "&IF(F44<0,"−","+")&TEXT(ABS(F44)*100,"#,##0.0")&"%"&"：觀點（水準 "&IF(F85<0,"−","+")&IF(ABS(F85)<0,"−","")&"$"&TEXT(ABS(ABS(F85)),"#,##0.000")&"bn"&"（FY28 模型 "&IF(損益!D9<0,"−","")&"$"&TEXT(ABS(損益!D9),"#,##0.000")&"bn"&"，共識合計 "&IF(F84<0,"−","")&"$"&TEXT(ABS(F84),"#,##0.000")&"bn"&"）；分配 "&IF(F86<0,"−","+")&IF(ABS(F86)<0,"−","")&"$"&TEXT(ABS(ABS(F86)),"#,##0.000")&"bn"&"；"&"OCI 營收＝在役 MW × 每 MW 年收入（Tokenomics 正向推導），期初可計費 MW 以 Q1 實際 OCI 年化校準；傳統事業四線依近四季年增率；共識未揭露 MW 與單價假設"&"）"),"營收 vs 共識 "&IF(F44<0,"−","+")&TEXT(ABS(F44)*100,"#,##0.0")&"%"&"：觀點（"&"OCI 營收＝在役 MW × 每 MW 年收入（Tokenomics 正向推導），期初可計費 MW 以 Q1 實際 OCI 年化校準；傳統事業四線依近四季年增率；共識未揭露 MW 與單價假設"&"）"),""),"") | G90: =IF(ISNUMBER(G44),IF(ABS(G44)>輸入與假設!$C$333,IF(ISNUMBER(G85),IF(ABS(G86)>ABS(G85),"營收 vs 共識 "&IF(G44<0,"−","+")&TEXT(ABS(G44)*100,"#,##0.0")&"%"&"：拆法（分配 "&IF(G86<0,"−","+")&IF(ABS(G86)<0,"−","")&"$"&TEXT(ABS(ABS(G86)),"#,##0.000")&"bn"&"（Q2 FY28 占 FY28 "&TEXT((G22/損益!D9)*100,"#,##0.0")&"%"&"，共識合計 "&TEXT(((G34)/G84)*100,"#,##0.0")&"%"&"）；水準 "&IF(G85<0,"−","+")&IF(ABS(G85)<0,"−","")&"$"&TEXT(ABS(ABS(G85)),"#,##0.000")&"bn"&"）","營收 vs 共識 "&IF(G44<0,"−","+")&TEXT(ABS(G44)*100,"#,##0.0")&"%"&"：觀點（水準 "&IF(G85<0,"−","+")&IF(ABS(G85)<0,"−","")&"$"&TEXT(ABS(ABS(G85)),"#,##0.000")&"bn"&"（FY28 模型 "&IF(損益!D9<0,"−","")&"$"&TEXT(ABS(損益!D9),"#,##0.000")&"bn"&"，共識合計 "&IF(G84<0,"−","")&"$"&TEXT(ABS(G84),"#,##0.000")&"bn"&"）；分配 "&IF(G86<0,"−","+")&IF(ABS(G86)<0,"−","")&"$"&TEXT(ABS(ABS(G86)),"#,##0.000")&"bn"&"；"&"OCI 營收＝在役 MW × 每 MW 年收入（Tokenomics 正向推導），期初可計費 MW 以 Q1 實際 OCI 年化校準；傳統事業四線依近四季年增率；共識未揭露 MW 與單價假設"&"）"),"營收 vs 共識 "&IF(G44<0,"−","+")&TEXT(ABS(G44)*100,"#,##0.0")&"%"&"：觀點（"&"OCI 營收＝在役 MW × 每 MW 年收入（Tokenomics 正向推導），期初可計費 MW 以 Q1 實際 OCI 年化校準；傳統事業四線依近四季年增率；共識未揭露 MW 與單價假設"&"）"),""),"") | H90: =IF(ISNUMBER(H44),IF(ABS(H44)>輸入與假設!$C$333,IF(ISNUMBER(H85),IF(ABS(H86)>ABS(H85),"營收 vs 共識 "&IF(H44<0,"−","+")&TEXT(ABS(H44)*100,"#,##0.0")&"%"&"：拆法（分配 "&IF(H86<0,"−","+")&IF(ABS(H86)<0,"−","")&"$"&TEXT(ABS(ABS(H86)),"#,##0.000")&"bn"&"（Q3 FY28 占 FY28 "&TEXT((H22/損益!D9)*100,"#,##0.0")&"%"&"，共識合計 "&TEXT(((H34)/H84)*100,"#,##0.0")&"%"&"）；水準 "&IF(H85<0,"−","+")&IF(ABS(H85)<0,"−","")&"$"&TEXT(ABS(ABS(H85)),"#,##0.000")&"bn"&"）","營收 vs 共識 "&IF(H44<0,"−","+")&TEXT(ABS(H44)*100,"#,##0.0")&"%"&"：觀點（水準 "&IF(H85<0,"−","+")&IF(ABS(H85)<0,"−","")&"$"&TEXT(ABS(ABS(H85)),"#,##0.000")&"bn"&"（FY28 模型 "&IF(損益!D9<0,"−","")&"$"&TEXT(ABS(損益!D9),"#,##0.000")&"bn"&"，共識合計 "&IF(H84<0,"−","")&"$"&TEXT(ABS(H84),"#,##0.000")&"bn"&"）；分配 "&IF(H86<0,"−","+")&IF(ABS(H86)<0,"−","")&"$"&TEXT(ABS(ABS(H86)),"#,##0.000")&"bn"&"；"&"OCI 營收＝在役 MW × 每 MW 年收入（Tokenomics 正向推導），期初可計費 MW 以 Q1 實際 OCI 年化校準；傳統事業四線依近四季年增率；共識未揭露 MW 與單價假設"&"）"),"營收 vs 共識 "&IF(H44<0,"−","+")&TEXT(ABS(H44)*100,"#,##0.0")&"%"&"：觀點（"&"OCI 營收＝在役 MW × 每 MW 年收入（Tokenomics 正向推導），期初可計費 MW 以 Q1 實際 OCI 年化校準；傳統事業四線依近四季年增率；共識未揭露 MW 與單價假設"&"）"),""),"")
A91: 原因類型｜營收｜vs 共識 | C91: =IF(ISNUMBER(C44),IF(ABS(C44)>輸入與假設!$C$333,IF(ISNUMBER(C85),IF(ABS(C86)>ABS(C85),"拆法","觀點"),"觀點"),""),"") | D91: =IF(ISNUMBER(D44),IF(ABS(D44)>輸入與假設!$C$333,IF(ISNUMBER(D85),IF(ABS(D86)>ABS(D85),"拆法","觀點"),"觀點"),""),"") | E91: =IF(ISNUMBER(E44),IF(ABS(E44)>輸入與假設!$C$333,IF(ISNUMBER(E85),IF(ABS(E86)>ABS(E85),"拆法","觀點"),"觀點"),""),"") | F91: =IF(ISNUMBER(F44),IF(ABS(F44)>輸入與假設!$C$333,IF(ISNUMBER(F85),IF(ABS(F86)>ABS(F85),"拆法","觀點"),"觀點"),""),"") | G91: =IF(ISNUMBER(G44),IF(ABS(G44)>輸入與假設!$C$333,IF(ISNUMBER(G85),IF(ABS(G86)>ABS(G85),"拆法","觀點"),"觀點"),""),"") | H91: =IF(ISNUMBER(H44),IF(ABS(H44)>輸入與假設!$C$333,IF(ISNUMBER(H85),IF(ABS(H86)>ABS(H85),"拆法","觀點"),"觀點"),""),"")
A92: 原因｜營收｜vs 指引中點 | C92: =IF(ISNUMBER(C45),IF(OR(ABS(C45)>輸入與假設!$C$333,C22>C32,C22<C31),IF(ISNUMBER(C88),IF(ABS(C89)>ABS(C88),"營收 vs 指引中點 "&IF(C45<0,"−","+")&TEXT(ABS(C45)*100,"#,##0.0")&"%"&"：拆法（分配 "&IF(C89<0,"−","+")&IF(ABS(C89)<0,"−","")&"$"&TEXT(ABS(ABS(C89)),"#,##0.000")&"bn"&"（Q2 FY27 占 2Q–4Q27 "&TEXT((C22/損益!C9)*100,"#,##0.0")&"%"&"，指引隱含 "&TEXT(((((C31+C32)/2))/C87)*100,"#,##0.0")&"%"&"）；水準 "&IF(C88<0,"−","+")&IF(ABS(C88)<0,"−","")&"$"&TEXT(ABS(ABS(C88)),"#,##0.000")&"bn"&"）","營收 vs 指引中點 "&IF(C45<0,"−","+")&TEXT(ABS(C45)*100,"#,##0.0")&"%"&"：觀點（水準 "&IF(C88<0,"−","+")&IF(ABS(C88)<0,"−","")&"$"&TEXT(ABS(ABS(C88)),"#,##0.000")&"bn"&"（2Q–4Q27 模型 "&IF(損益!C9<0,"−","")&"$"&TEXT(ABS(損益!C9),"#,##0.000")&"bn"&"，指引隱含 "&IF(C87<0,"−","")&"$"&TEXT(ABS(C87),"#,##0.000")&"bn"&"）；分配 "&IF(C89<0,"−","+")&IF(ABS(C89)<0,"−","")&"$"&TEXT(ABS(ABS(C89)),"#,##0.000")&"bn"&"；"&"OCI 營收＝在役 MW × 每 MW 年收入（Tokenomics 正向推導），期初可計費 MW 以 Q1 實際 OCI 年化校準；傳統事業四線依近四季年增率；共識未揭露 MW 與單價假設"&"）"),"營收 vs 指引中點 "&IF(C45<0,"−","+")&TEXT(ABS(C45)*100,"#,##0.0")&"%"&"：觀點（"&"OCI 營收＝在役 MW × 每 MW 年收入（Tokenomics 正向推導），期初可計費 MW 以 Q1 實際 OCI 年化校準；傳統事業四線依近四季年增率；共識未揭露 MW 與單價假設"&"）"),""),"") -> 營收 vs 指引中點 +1.8%：觀點（水準 +$0.218bn（2Q–4Q27 模型 $71.382bn，指引隱含 $70.655bn）；分配 +$0.155bn；OCI 營收＝在役 MW × 每 MW 年收入（Tokenomics 正向推導），期初可計費 MW 以 Q1 實際 OCI 年化校準；傳統事業四線依近四季年增率；共識未揭露 MW 與單價假設） | D92: =IF(ISNUMBER(D45),IF(OR(ABS(D45)>輸入與假設!$C$333,D22>D32,D22<D31),IF(ISNUMBER(D88),IF(ABS(D89)>ABS(D88),"營收 vs 指引中點 "&IF(D45<0,"−","+")&TEXT(ABS(D45)*100,"#,##0.0")&"%"&"：拆法（分配 "&IF(D89<0,"−","+")&IF(ABS(D89)<0,"−","")&"$"&TEXT(ABS(ABS(D89)),"#,##0.000")&"bn"&"（Q3 FY27 占 2Q–4Q27 "&TEXT((D22/損益!C9)*100,"#,##0.0")&"%"&"，指引隱含 "&TEXT(((((D31+D32)/2))/D87)*100,"#,##0.0")&"%"&"）；水準 "&IF(D88<0,"−","+")&IF(ABS(D88)<0,"−","")&"$"&TEXT(ABS(ABS(D88)),"#,##0.000")&"bn"&"）","營收 vs 指引中點 "&IF(D45<0,"−","+")&TEXT(ABS(D45)*100,"#,##0.0")&"%"&"：觀點（水準 "&IF(D88<0,"−","+")&IF(ABS(D88)<0,"−","")&"$"&TEXT(ABS(ABS(D88)),"#,##0.000")&"bn"&"（2Q–4Q27 模型 "&IF(損益!C9<0,"−","")&"$"&TEXT(ABS(損益!C9),"#,##0.000")&"bn"&"，指引隱含 "&IF(D87<0,"−","")&"$"&TEXT(ABS(D87),"#,##0.000")&"bn"&"）；分配 "&IF(D89<0,"−","+")&IF(ABS(D89)<0,"−","")&"$"&TEXT(ABS(ABS(D89)),"#,##0.000")&"bn"&"；"&"OCI 營收＝在役 MW × 每 MW 年收入（Tokenomics 正向推導），期初可計費 MW 以 Q1 實際 OCI 年化校準；傳統事業四線依近四季年增率；共識未揭露 MW 與單價假設"&"）"),"營收 vs 指引中點 "&IF(D45<0,"−","+")&TEXT(ABS(D45)*100,"#,##0.0")&"%"&"：觀點（"&"OCI 營收＝在役 MW × 每 MW 年收入（Tokenomics 正向推導），期初可計費 MW 以 Q1 實際 OCI 年化校準；傳統事業四線依近四季年增率；共識未揭露 MW 與單價假設"&"）"),""),"") | E92: =IF(ISNUMBER(E45),IF(OR(ABS(E45)>輸入與假設!$C$333,E22>E32,E22<E31),IF(ISNUMBER(E88),IF(ABS(E89)>ABS(E88),"營收 vs 指引中點 "&IF(E45<0,"−","+")&TEXT(ABS(E45)*100,"#,##0.0")&"%"&"：拆法（分配 "&IF(E89<0,"−","+")&IF(ABS(E89)<0,"−","")&"$"&TEXT(ABS(ABS(E89)),"#,##0.000")&"bn"&"（Q4 FY27 占 2Q–4Q27 "&TEXT((E22/損益!C9)*100,"#,##0.0")&"%"&"，指引隱含 "&TEXT(((((E31+E32)/2))/E87)*100,"#,##0.0")&"%"&"）；水準 "&IF(E88<0,"−","+")&IF(ABS(E88)<0,"−","")&"$"&TEXT(ABS(ABS(E88)),"#,##0.000")&"bn"&"）","營收 vs 指引中點 "&IF(E45<0,"−","+")&TEXT(ABS(E45)*100,"#,##0.0")&"%"&"：觀點（水準 "&IF(E88<0,"−","+")&IF(ABS(E88)<0,"−","")&"$"&TEXT(ABS(ABS(E88)),"#,##0.000")&"bn"&"（2Q–4Q27 模型 "&IF(損益!C9<0,"−","")&"$"&TEXT(ABS(損益!C9),"#,##0.000")&"bn"&"，指引隱含 "&IF(E87<0,"−","")&"$"&TEXT(ABS(E87),"#,##0.000")&"bn"&"）；分配 "&IF(E89<0,"−","+")&IF(ABS(E89)<0,"−","")&"$"&TEXT(ABS(ABS(E89)),"#,##0.000")&"bn"&"；"&"OCI 營收＝在役 MW × 每 MW 年收入（Tokenomics 正向推導），期初可計費 MW 以 Q1 實際 OCI 年化校準；傳統事業四線依近四季年增率；共識未揭露 MW 與單價假設"&"）"),"營收 vs 指引中點 "&IF(E45<0,"−","+")&TEXT(ABS(E45)*100,"#,##0.0")&"%"&"：觀點（"&"OCI 營收＝在役 MW × 每 MW 年收入（Tokenomics 正向推導），期初可計費 MW 以 Q1 實際 OCI 年化校準；傳統事業四線依近四季年增率；共識未揭露 MW 與單價假設"&"）"),""),"") | F92: =IF(ISNUMBER(F45),IF(OR(ABS(F45)>輸入與假設!$C$333,F22>F32,F22<F31),IF(ISNUMBER(F88),IF(ABS(F89)>ABS(F88),"營收 vs 指引中點 "&IF(F45<0,"−","+")&TEXT(ABS(F45)*100,"#,##0.0")&"%"&"：拆法（分配 "&IF(F89<0,"−","+")&IF(ABS(F89)<0,"−","")&"$"&TEXT(ABS(ABS(F89)),"#,##0.000")&"bn"&"（Q1 FY28 占 FY28 "&TEXT((F22/損益!D9)*100,"#,##0.0")&"%"&"，指引隱含 "&TEXT(((((F31+F32)/2))/F87)*100,"#,##0.0")&"%"&"）；水準 "&IF(F88<0,"−","+")&IF(ABS(F88)<0,"−","")&"$"&TEXT(ABS(ABS(F88)),"#,##0.000")&"bn"&"）","營收 vs 指引中點 "&IF(F45<0,"−","+")&TEXT(ABS(F45)*100,"#,##0.0")&"%"&"：觀點（水準 "&IF(F88<0,"−","+")&IF(ABS(F88)<0,"−","")&"$"&TEXT(ABS(ABS(F88)),"#,##0.000")&"bn"&"（FY28 模型 "&IF(損益!D9<0,"−","")&"$"&TEXT(ABS(損益!D9),"#,##0.000")&"bn"&"，指引隱含 "&IF(F87<0,"−","")&"$"&TEXT(ABS(F87),"#,##0.000")&"bn"&"）；分配 "&IF(F89<0,"−","+")&IF(ABS(F89)<0,"−","")&"$"&TEXT(ABS(ABS(F89)),"#,##0.000")&"bn"&"；"&"OCI 營收＝在役 MW × 每 MW 年收入（Tokenomics 正向推導），期初可計費 MW 以 Q1 實際 OCI 年化校準；傳統事業四線依近四季年增率；共識未揭露 MW 與單價假設"&"）"),"營收 vs 指引中點 "&IF(F45<0,"−","+")&TEXT(ABS(F45)*100,"#,##0.0")&"%"&"：觀點（"&"OCI 營收＝在役 MW × 每 MW 年收入（Tokenomics 正向推導），期初可計費 MW 以 Q1 實際 OCI 年化校準；傳統事業四線依近四季年增率；共識未揭露 MW 與單價假設"&"）"),""),"") | G92: =IF(ISNUMBER(G45),IF(OR(ABS(G45)>輸入與假設!$C$333,G22>G32,G22<G31),IF(ISNUMBER(G88),IF(ABS(G89)>ABS(G88),"營收 vs 指引中點 "&IF(G45<0,"−","+")&TEXT(ABS(G45)*100,"#,##0.0")&"%"&"：拆法（分配 "&IF(G89<0,"−","+")&IF(ABS(G89)<0,"−","")&"$"&TEXT(ABS(ABS(G89)),"#,##0.000")&"bn"&"（Q2 FY28 占 FY28 "&TEXT((G22/損益!D9)*100,"#,##0.0")&"%"&"，指引隱含 "&TEXT(((((G31+G32)/2))/G87)*100,"#,##0.0")&"%"&"）；水準 "&IF(G88<0,"−","+")&IF(ABS(G88)<0,"−","")&"$"&TEXT(ABS(ABS(G88)),"#,##0.000")&"bn"&"）","營收 vs 指引中點 "&IF(G45<0,"−","+")&TEXT(ABS(G45)*100,"#,##0.0")&"%"&"：觀點（水準 "&IF(G88<0,"−","+")&IF(ABS(G88)<0,"−","")&"$"&TEXT(ABS(ABS(G88)),"#,##0.000")&"bn"&"（FY28 模型 "&IF(損益!D9<0,"−","")&"$"&TEXT(ABS(損益!D9),"#,##0.000")&"bn"&"，指引隱含 "&IF(G87<0,"−","")&"$"&TEXT(ABS(G87),"#,##0.000")&"bn"&"）；分配 "&IF(G89<0,"−","+")&IF(ABS(G89)<0,"−","")&"$"&TEXT(ABS(ABS(G89)),"#,##0.000")&"bn"&"；"&"OCI 營收＝在役 MW × 每 MW 年收入（Tokenomics 正向推導），期初可計費 MW 以 Q1 實際 OCI 年化校準；傳統事業四線依近四季年增率；共識未揭露 MW 與單價假設"&"）"),"營收 vs 指引中點 "&IF(G45<0,"−","+")&TEXT(ABS(G45)*100,"#,##0.0")&"%"&"：觀點（"&"OCI 營收＝在役 MW × 每 MW 年收入（Tokenomics 正向推導），期初可計費 MW 以 Q1 實際 OCI 年化校準；傳統事業四線依近四季年增率；共識未揭露 MW 與單價假設"&"）"),""),"") | H92: =IF(ISNUMBER(H45),IF(OR(ABS(H45)>輸入與假設!$C$333,H22>H32,H22<H31),IF(ISNUMBER(H88),IF(ABS(H89)>ABS(H88),"營收 vs 指引中點 "&IF(H45<0,"−","+")&TEXT(ABS(H45)*100,"#,##0.0")&"%"&"：拆法（分配 "&IF(H89<0,"−","+")&IF(ABS(H89)<0,"−","")&"$"&TEXT(ABS(ABS(H89)),"#,##0.000")&"bn"&"（Q3 FY28 占 FY28 "&TEXT((H22/損益!D9)*100,"#,##0.0")&"%"&"，指引隱含 "&TEXT(((((H31+H32)/2))/H87)*100,"#,##0.0")&"%"&"）；水準 "&IF(H88<0,"−","+")&IF(ABS(H88)<0,"−","")&"$"&TEXT(ABS(ABS(H88)),"#,##0.000")&"bn"&"）","營收 vs 指引中點 "&IF(H45<0,"−","+")&TEXT(ABS(H45)*100,"#,##0.0")&"%"&"：觀點（水準 "&IF(H88<0,"−","+")&IF(ABS(H88)<0,"−","")&"$"&TEXT(ABS(ABS(H88)),"#,##0.000")&"bn"&"（FY28 模型 "&IF(損益!D9<0,"−","")&"$"&TEXT(ABS(損益!D9),"#,##0.000")&"bn"&"，指引隱含 "&IF(H87<0,"−","")&"$"&TEXT(ABS(H87),"#,##0.000")&"bn"&"）；分配 "&IF(H89<0,"−","+")&IF(ABS(H89)<0,"−","")&"$"&TEXT(ABS(ABS(H89)),"#,##0.000")&"bn"&"；"&"OCI 營收＝在役 MW × 每 MW 年收入（Tokenomics 正向推導），期初可計費 MW 以 Q1 實際 OCI 年化校準；傳統事業四線依近四季年增率；共識未揭露 MW 與單價假設"&"）"),"營收 vs 指引中點 "&IF(H45<0,"−","+")&TEXT(ABS(H45)*100,"#,##0.0")&"%"&"：觀點（"&"OCI 營收＝在役 MW × 每 MW 年收入（Tokenomics 正向推導），期初可計費 MW 以 Q1 實際 OCI 年化校準；傳統事業四線依近四季年增率；共識未揭露 MW 與單價假設"&"）"),""),"")
A93: 原因類型｜營收｜vs 指引中點 | C93: =IF(ISNUMBER(C45),IF(OR(ABS(C45)>輸入與假設!$C$333,C22>C32,C22<C31),IF(ISNUMBER(C88),IF(ABS(C89)>ABS(C88),"拆法","觀點"),"觀點"),""),"") -> 觀點 | D93: =IF(ISNUMBER(D45),IF(OR(ABS(D45)>輸入與假設!$C$333,D22>D32,D22<D31),IF(ISNUMBER(D88),IF(ABS(D89)>ABS(D88),"拆法","觀點"),"觀點"),""),"") | E93: =IF(ISNUMBER(E45),IF(OR(ABS(E45)>輸入與假設!$C$333,E22>E32,E22<E31),IF(ISNUMBER(E88),IF(ABS(E89)>ABS(E88),"拆法","觀點"),"觀點"),""),"") | F93: =IF(ISNUMBER(F45),IF(OR(ABS(F45)>輸入與假設!$C$333,F22>F32,F22<F31),IF(ISNUMBER(F88),IF(ABS(F89)>ABS(F88),"拆法","觀點"),"觀點"),""),"") | G93: =IF(ISNUMBER(G45),IF(OR(ABS(G45)>輸入與假設!$C$333,G22>G32,G22<G31),IF(ISNUMBER(G88),IF(ABS(G89)>ABS(G88),"拆法","觀點"),"觀點"),""),"") | H93: =IF(ISNUMBER(H45),IF(OR(ABS(H45)>輸入與假設!$C$333,H22>H32,H22<H31),IF(ISNUMBER(H88),IF(ABS(H89)>ABS(H88),"拆法","觀點"),"觀點"),""),"")
A94: 原因｜營收｜實際 vs 模型 | C94: =IF(ISNUMBER(C46),IF(ABS(C46)>輸入與假設!$C$333,"營收 實際 vs 模型 "&IF(C46<0,"−","+")&TEXT(ABS(C46)*100,"#,##0.0")&"%"&"：觀點（"&"OCI 營收＝在役 MW × 每 MW 年收入（Tokenomics 正向推導），期初可計費 MW 以 Q1 實際 OCI 年化校準；傳統事業四線依近四季年增率；共識未揭露 MW 與單價假設"&"）",""),"") | D94: =IF(ISNUMBER(D46),IF(ABS(D46)>輸入與假設!$C$333,"營收 實際 vs 模型 "&IF(D46<0,"−","+")&TEXT(ABS(D46)*100,"#,##0.0")&"%"&"：觀點（"&"OCI 營收＝在役 MW × 每 MW 年收入（Tokenomics 正向推導），期初可計費 MW 以 Q1 實際 OCI 年化校準；傳統事業四線依近四季年增率；共識未揭露 MW 與單價假設"&"）",""),"") | E94: =IF(ISNUMBER(E46),IF(ABS(E46)>輸入與假設!$C$333,"營收 實際 vs 模型 "&IF(E46<0,"−","+")&TEXT(ABS(E46)*100,"#,##0.0")&"%"&"：觀點（"&"OCI 營收＝在役 MW × 每 MW 年收入（Tokenomics 正向推導），期初可計費 MW 以 Q1 實際 OCI 年化校準；傳統事業四線依近四季年增率；共識未揭露 MW 與單價假設"&"）",""),"") | F94: =IF(ISNUMBER(F46),IF(ABS(F46)>輸入與假設!$C$333,"營收 實際 vs 模型 "&IF(F46<0,"−","+")&TEXT(ABS(F46)*100,"#,##0.0")&"%"&"：觀點（"&"OCI 營收＝在役 MW × 每 MW 年收入（Tokenomics 正向推導），期初可計費 MW 以 Q1 實際 OCI 年化校準；傳統事業四線依近四季年增率；共識未揭露 MW 與單價假設"&"）",""),"") | G94: =IF(ISNUMBER(G46),IF(ABS(G46)>輸入與假設!$C$333,"營收 實際 vs 模型 "&IF(G46<0,"−","+")&TEXT(ABS(G46)*100,"#,##0.0")&"%"&"：觀點（"&"OCI 營收＝在役 MW × 每 MW 年收入（Tokenomics 正向推導），期初可計費 MW 以 Q1 實際 OCI 年化校準；傳統事業四線依近四季年增率；共識未揭露 MW 與單價假設"&"）",""),"") | H94: =IF(ISNUMBER(H46),IF(ABS(H46)>輸入與假設!$C$333,"營收 實際 vs 模型 "&IF(H46<0,"−","+")&TEXT(ABS(H46)*100,"#,##0.0")&"%"&"：觀點（"&"OCI 營收＝在役 MW × 每 MW 年收入（Tokenomics 正向推導），期初可計費 MW 以 Q1 實際 OCI 年化校準；傳統事業四線依近四季年增率；共識未揭露 MW 與單價假設"&"）",""),"")
A95: 原因類型｜營收｜實際 vs 模型 | C95: =IF(ISNUMBER(C46),IF(ABS(C46)>輸入與假設!$C$333,"觀點",""),"") | D95: =IF(ISNUMBER(D46),IF(ABS(D46)>輸入與假設!$C$333,"觀點",""),"") | E95: =IF(ISNUMBER(E46),IF(ABS(E46)>輸入與假設!$C$333,"觀點",""),"") | F95: =IF(ISNUMBER(F46),IF(ABS(F46)>輸入與假設!$C$333,"觀點",""),"") | G95: =IF(ISNUMBER(G46),IF(ABS(G46)>輸入與假設!$C$333,"觀點",""),"") | H95: =IF(ISNUMBER(H46),IF(ABS(H46)>輸入與假設!$C$333,"觀點",""),"")
A96: 合計基準｜調整後 EBITDA｜vs 共識 | B96: US$bn | C96: =IF(COUNT(C35,D35,E35)=3,C35+D35+E35,"不適用") -> 不適用 | D96: =IF(COUNT(C35,D35,E35)=3,C35+D35+E35,"不適用") -> 不適用 | E96: =IF(COUNT(C35,D35,E35)=3,C35+D35+E35,"不適用") -> 不適用 | F96: =IF(COUNT(F35,G35,H35)=3,F35+G35+H35,"不適用") -> 不適用 | G96: =IF(COUNT(F35,G35,H35)=3,F35+G35+H35,"不適用") -> 不適用 | H96: =IF(COUNT(F35,G35,H35)=3,F35+G35+H35,"不適用") -> 不適用 | J96: 所屬期間的季度共識合計
A97: 拆解｜調整後 EBITDA｜vs 共識｜水準 | B97: US$bn | C97: =IF(AND(ISNUMBER(C96),C96<>0,ISNUMBER(C35),ISNUMBER(C28)),(損益!C21-C96)*(C35)/C96,"不適用") -> 不適用 | D97: =IF(AND(ISNUMBER(D96),D96<>0,ISNUMBER(D35),ISNUMBER(D28)),(損益!C21-D96)*(D35)/D96,"不適用") -> 不適用 | E97: =IF(AND(ISNUMBER(E96),E96<>0,ISNUMBER(E35),ISNUMBER(E28)),(損益!C21-E96)*(E35)/E96,"不適用") -> 不適用 | F97: =IF(AND(ISNUMBER(F96),F96<>0,ISNUMBER(F35),ISNUMBER(F28)),(損益!D21-F96)*(F35)/F96,"不適用") -> 不適用 | G97: =IF(AND(ISNUMBER(G96),G96<>0,ISNUMBER(G35),ISNUMBER(G28)),(損益!D21-G96)*(G35)/G96,"不適用") -> 不適用 | H97: =IF(AND(ISNUMBER(H96),H96<>0,ISNUMBER(H35),ISNUMBER(H28)),(損益!D21-H96)*(H35)/H96,"不適用") -> 不適用 | J97: (模型期間 − 比較期間) × 比較的季占比
A98: 拆解｜調整後 EBITDA｜vs 共識｜分配 | B98: US$bn | C98: =IF(AND(ISNUMBER(C96),C96<>0,ISNUMBER(C35),ISNUMBER(C28)),(C28/損益!C21-(C35)/C96)*損益!C21,"不適用") -> 不適用 | D98: =IF(AND(ISNUMBER(D96),D96<>0,ISNUMBER(D35),ISNUMBER(D28)),(D28/損益!C21-(D35)/D96)*損益!C21,"不適用") -> 不適用 | E98: =IF(AND(ISNUMBER(E96),E96<>0,ISNUMBER(E35),ISNUMBER(E28)),(E28/損益!C21-(E35)/E96)*損益!C21,"不適用") -> 不適用 | F98: =IF(AND(ISNUMBER(F96),F96<>0,ISNUMBER(F35),ISNUMBER(F28)),(F28/損益!D21-(F35)/F96)*損益!D21,"不適用") -> 不適用 | G98: =IF(AND(ISNUMBER(G96),G96<>0,ISNUMBER(G35),ISNUMBER(G28)),(G28/損益!D21-(G35)/G96)*損益!D21,"不適用") -> 不適用 | H98: =IF(AND(ISNUMBER(H96),H96<>0,ISNUMBER(H35),ISNUMBER(H28)),(H28/損益!D21-(H35)/H96)*損益!D21,"不適用") -> 不適用 | J98: (模型季占比 − 比較季占比) × 模型期間；水準＋分配＝季度差距
A99: 原因｜調整後 EBITDA｜vs 共識 | C99: =IF(ISNUMBER(C49),IF(IF(ISNUMBER(C54),ABS(C54)>輸入與假設!$C$334,OR(AND(C35<>0,ABS(C49)>輸入與假設!$C$333*ABS(C35)),AND(C35=0,C49<>0))),IF(ISNUMBER(C97),IF(ABS(C98)>ABS(C97),"調整後 EBITDA vs 共識 "&IF(C49<0,"−","+")&IF(ABS(C49)<0,"−","")&"$"&TEXT(ABS(ABS(C49)),"#,##0.00")&"bn"&IF(ISNUMBER(C54),"／"&IF(C54<0,"−","+")&TEXT(ABS(C54)*100,"#,##0.0")&"pt","")&"：拆法（分配 "&IF(C98<0,"−","+")&IF(ABS(C98)<0,"−","")&"$"&TEXT(ABS(ABS(C98)),"#,##0.000")&"bn"&"（Q2 FY27 占 2Q–4Q27 "&TEXT((C28/損益!C21)*100,"#,##0.0")&"%"&"，共識合計 "&TEXT(((C35)/C96)*100,"#,##0.0")&"%"&"）；水準 "&IF(C97<0,"−","+")&IF(ABS(C97)<0,"−","")&"$"&TEXT(ABS(ABS(C97)),"#,##0.000")&"bn"&"）","調整後 EBITDA vs 共識 "&IF(C49<0,"−","+")&IF(ABS(C49)<0,"−","")&"$"&TEXT(ABS(ABS(C49)),"#,##0.00")&"bn"&IF(ISNUMBER(C54),"／"&IF(C54<0,"−","+")&TEXT(ABS(C54)*100,"#,##0.0")&"pt","")&"：觀點（水準 "&IF(C97<0,"−","+")&IF(ABS(C97)<0,"−","")&"$"&TEXT(ABS(ABS(C97)),"#,##0.000")&"bn"&"（2Q–4Q27 模型 "&IF(損益!C21<0,"−","")&"$"&TEXT(ABS(損益!C21),"#,##0.000")&"bn"&"，共識合計 "&IF(C96<0,"−","")&"$"&TEXT(ABS(C96),"#,##0.000")&"bn"&"）；分配 "&IF(C98<0,"−","+")&IF(ABS(C98)<0,"−","")&"$"&TEXT(ABS(ABS(C98)),"#,##0.000")&"bn"&"；"&"模型 EBITDA 率 "&IF((C27)<0,"−","")&TEXT(ABS((C27))*100,"#,##0.0")&"%"&"；季度共識 EBITDA "&IF((輸入與假設!$C$306)<0,"−","")&TEXT(ABS((輸入與假設!$C$306)),"#,##0.00")&"、營收 "&IF((輸入與假設!$C$305)<0,"−","")&TEXT(ABS((輸入與假設!$C$305)),"#,##0.00")&"（共識 EBITDA＝非 GAAP 營業利益＋折舊）"&"）"),"調整後 EBITDA vs 共識 "&IF(C49<0,"−","+")&IF(ABS(C49)<0,"−","")&"$"&TEXT(ABS(ABS(C49)),"#,##0.00")&"bn"&IF(ISNUMBER(C54),"／"&IF(C54<0,"−","+")&TEXT(ABS(C54)*100,"#,##0.0")&"pt","")&"：觀點（"&"模型 EBITDA 率 "&IF((C27)<0,"−","")&TEXT(ABS((C27))*100,"#,##0.0")&"%"&"；季度共識 EBITDA "&IF((輸入與假設!$C$306)<0,"−","")&TEXT(ABS((輸入與假設!$C$306)),"#,##0.00")&"、營收 "&IF((輸入與假設!$C$305)<0,"−","")&TEXT(ABS((輸入與假設!$C$305)),"#,##0.00")&"（共識 EBITDA＝非 GAAP 營業利益＋折舊）"&"）"),""),"") | D99: =IF(ISNUMBER(D49),IF(IF(ISNUMBER(D54),ABS(D54)>輸入與假設!$C$334,OR(AND(D35<>0,ABS(D49)>輸入與假設!$C$333*ABS(D35)),AND(D35=0,D49<>0))),IF(ISNUMBER(D97),IF(ABS(D98)>ABS(D97),"調整後 EBITDA vs 共識 "&IF(D49<0,"−","+")&IF(ABS(D49)<0,"−","")&"$"&TEXT(ABS(ABS(D49)),"#,##0.00")&"bn"&IF(ISNUMBER(D54),"／"&IF(D54<0,"−","+")&TEXT(ABS(D54)*100,"#,##0.0")&"pt","")&"：拆法（分配 "&IF(D98<0,"−","+")&IF(ABS(D98)<0,"−","")&"$"&TEXT(ABS(ABS(D98)),"#,##0.000")&"bn"&"（Q3 FY27 占 2Q–4Q27 "&TEXT((D28/損益!C21)*100,"#,##0.0")&"%"&"，共識合計 "&TEXT(((D35)/D96)*100,"#,##0.0")&"%"&"）；水準 "&IF(D97<0,"−","+")&IF(ABS(D97)<0,"−","")&"$"&TEXT(ABS(ABS(D97)),"#,##0.000")&"bn"&"）","調整後 EBITDA vs 共識 "&IF(D49<0,"−","+")&IF(ABS(D49)<0,"−","")&"$"&TEXT(ABS(ABS(D49)),"#,##0.00")&"bn"&IF(ISNUMBER(D54),"／"&IF(D54<0,"−","+")&TEXT(ABS(D54)*100,"#,##0.0")&"pt","")&"：觀點（水準 "&IF(D97<0,"−","+")&IF(ABS(D97)<0,"−","")&"$"&TEXT(ABS(ABS(D97)),"#,##0.000")&"bn"&"（2Q–4Q27 模型 "&IF(損益!C21<0,"−","")&"$"&TEXT(ABS(損益!C21),"#,##0.000")&"bn"&"，共識合計 "&IF(D96<0,"−","")&"$"&TEXT(ABS(D96),"#,##0.000")&"bn"&"）；分配 "&IF(D98<0,"−","+")&IF(ABS(D98)<0,"−","")&"$"&TEXT(ABS(ABS(D98)),"#,##0.000")&"bn"&"；"&"模型 EBITDA 率 "&IF((D27)<0,"−","")&TEXT(ABS((D27))*100,"#,##0.0")&"%"&"；季度共識 EBITDA "&IF((輸入與假設!$D$306)<0,"−","")&TEXT(ABS((輸入與假設!$D$306)),"#,##0.00")&"、營收 "&IF((輸入與假設!$D$305)<0,"−","")&TEXT(ABS((輸入與假設!$D$305)),"#,##0.00")&"（共識 EBITDA＝非 GAAP 營業利益＋折舊）"&"）"),"調整後 EBITDA vs 共識 "&IF(D49<0,"−","+")&IF(ABS(D49)<0,"−","")&"$"&TEXT(ABS(ABS(D49)),"#,##0.00")&"bn"&IF(ISNUMBER(D54),"／"&IF(D54<0,"−","+")&TEXT(ABS(D54)*100,"#,##0.0")&"pt","")&"：觀點（"&"模型 EBITDA 率 "&IF((D27)<0,"−","")&TEXT(ABS((D27))*100,"#,##0.0")&"%"&"；季度共識 EBITDA "&IF((輸入與假設!$D$306)<0,"−","")&TEXT(ABS((輸入與假設!$D$306)),"#,##0.00")&"、營收 "&IF((輸入與假設!$D$305)<0,"−","")&TEXT(ABS((輸入與假設!$D$305)),"#,##0.00")&"（共識 EBITDA＝非 GAAP 營業利益＋折舊）"&"）"),""),"") | E99: =IF(ISNUMBER(E49),IF(IF(ISNUMBER(E54),ABS(E54)>輸入與假設!$C$334,OR(AND(E35<>0,ABS(E49)>輸入與假設!$C$333*ABS(E35)),AND(E35=0,E49<>0))),IF(ISNUMBER(E97),IF(ABS(E98)>ABS(E97),"調整後 EBITDA vs 共識 "&IF(E49<0,"−","+")&IF(ABS(E49)<0,"−","")&"$"&TEXT(ABS(ABS(E49)),"#,##0.00")&"bn"&IF(ISNUMBER(E54),"／"&IF(E54<0,"−","+")&TEXT(ABS(E54)*100,"#,##0.0")&"pt","")&"：拆法（分配 "&IF(E98<0,"−","+")&IF(ABS(E98)<0,"−","")&"$"&TEXT(ABS(ABS(E98)),"#,##0.000")&"bn"&"（Q4 FY27 占 2Q–4Q27 "&TEXT((E28/損益!C21)*100,"#,##0.0")&"%"&"，共識合計 "&TEXT(((E35)/E96)*100,"#,##0.0")&"%"&"）；水準 "&IF(E97<0,"−","+")&IF(ABS(E97)<0,"−","")&"$"&TEXT(ABS(ABS(E97)),"#,##0.000")&"bn"&"）","調整後 EBITDA vs 共識 "&IF(E49<0,"−","+")&IF(ABS(E49)<0,"−","")&"$"&TEXT(ABS(ABS(E49)),"#,##0.00")&"bn"&IF(ISNUMBER(E54),"／"&IF(E54<0,"−","+")&TEXT(ABS(E54)*100,"#,##0.0")&"pt","")&"：觀點（水準 "&IF(E97<0,"−","+")&IF(ABS(E97)<0,"−","")&"$"&TEXT(ABS(ABS(E97)),"#,##0.000")&"bn"&"（2Q–4Q27 模型 "&IF(損益!C21<0,"−","")&"$"&TEXT(ABS(損益!C21),"#,##0.000")&"bn"&"，共識合計 "&IF(E96<0,"−","")&"$"&TEXT(ABS(E96),"#,##0.000")&"bn"&"）；分配 "&IF(E98<0,"−","+")&IF(ABS(E98)<0,"−","")&"$"&TEXT(ABS(ABS(E98)),"#,##0.000")&"bn"&"；"&"模型 EBITDA 率 "&IF((E27)<0,"−","")&TEXT(ABS((E27))*100,"#,##0.0")&"%"&"；季度共識 EBITDA "&"不適用"&"、營收 "&"不適用"&"（共識 EBITDA＝非 GAAP 營業利益＋折舊）"&"）"),"調整後 EBITDA vs 共識 "&IF(E49<0,"−","+")&IF(ABS(E49)<0,"−","")&"$"&TEXT(ABS(ABS(E49)),"#,##0.00")&"bn"&IF(ISNUMBER(E54),"／"&IF(E54<0,"−","+")&TEXT(ABS(E54)*100,"#,##0.0")&"pt","")&"：觀點（"&"模型 EBITDA 率 "&IF((E27)<0,"−","")&TEXT(ABS((E27))*100,"#,##0.0")&"%"&"；季度共識 EBITDA "&"不適用"&"、營收 "&"不適用"&"（共識 EBITDA＝非 GAAP 營業利益＋折舊）"&"）"),""),"") | F99: =IF(ISNUMBER(F49),IF(IF(ISNUMBER(F54),ABS(F54)>輸入與假設!$C$334,OR(AND(F35<>0,ABS(F49)>輸入與假設!$C$333*ABS(F35)),AND(F35=0,F49<>0))),IF(ISNUMBER(F97),IF(ABS(F98)>ABS(F97),"調整後 EBITDA vs 共識 "&IF(F49<0,"−","+")&IF(ABS(F49)<0,"−","")&"$"&TEXT(ABS(ABS(F49)),"#,##0.00")&"bn"&IF(ISNUMBER(F54),"／"&IF(F54<0,"−","+")&TEXT(ABS(F54)*100,"#,##0.0")&"pt","")&"：拆法（分配 "&IF(F98<0,"−","+")&IF(ABS(F98)<0,"−","")&"$"&TEXT(ABS(ABS(F98)),"#,##0.000")&"bn"&"（Q1 FY28 占 FY28 "&TEXT((F28/損益!D21)*100,"#,##0.0")&"%"&"，共識合計 "&TEXT(((F35)/F96)*100,"#,##0.0")&"%"&"）；水準 "&IF(F97<0,"−","+")&IF(ABS(F97)<0,"−","")&"$"&TEXT(ABS(ABS(F97)),"#,##0.000")&"bn"&"）","調整後 EBITDA vs 共識 "&IF(F49<0,"−","+")&IF(ABS(F49)<0,"−","")&"$"&TEXT(ABS(ABS(F49)),"#,##0.00")&"bn"&IF(ISNUMBER(F54),"／"&IF(F54<0,"−","+")&TEXT(ABS(F54)*100,"#,##0.0")&"pt","")&"：觀點（水準 "&IF(F97<0,"−","+")&IF(ABS(F97)<0,"−","")&"$"&TEXT(ABS(ABS(F97)),"#,##0.000")&"bn"&"（FY28 模型 "&IF(損益!D21<0,"−","")&"$"&TEXT(ABS(損益!D21),"#,##0.000")&"bn"&"，共識合計 "&IF(F96<0,"−","")&"$"&TEXT(ABS(F96),"#,##0.000")&"bn"&"）；分配 "&IF(F98<0,"−","+")&IF(ABS(F98)<0,"−","")&"$"&TEXT(ABS(ABS(F98)),"#,##0.000")&"bn"&"；"&"模型 EBITDA 率 "&IF((F27)<0,"−","")&TEXT(ABS((F27))*100,"#,##0.0")&"%"&"；季度共識 EBITDA "&"不適用"&"、營收 "&"不適用"&"（共識 EBITDA＝非 GAAP 營業利益＋折舊）"&"）"),"調整後 EBITDA vs 共識 "&IF(F49<0,"−","+")&IF(ABS(F49)<0,"−","")&"$"&TEXT(ABS(ABS(F49)),"#,##0.00")&"bn"&IF(ISNUMBER(F54),"／"&IF(F54<0,"−","+")&TEXT(ABS(F54)*100,"#,##0.0")&"pt","")&"：觀點（"&"模型 EBITDA 率 "&IF((F27)<0,"−","")&TEXT(ABS((F27))*100,"#,##0.0")&"%"&"；季度共識 EBITDA "&"不適用"&"、營收 "&"不適用"&"（共識 EBITDA＝非 GAAP 營業利益＋折舊）"&"）"),""),"") | G99: =IF(ISNUMBER(G49),IF(IF(ISNUMBER(G54),ABS(G54)>輸入與假設!$C$334,OR(AND(G35<>0,ABS(G49)>輸入與假設!$C$333*ABS(G35)),AND(G35=0,G49<>0))),IF(ISNUMBER(G97),IF(ABS(G98)>ABS(G97),"調整後 EBITDA vs 共識 "&IF(G49<0,"−","+")&IF(ABS(G49)<0,"−","")&"$"&TEXT(ABS(ABS(G49)),"#,##0.00")&"bn"&IF(ISNUMBER(G54),"／"&IF(G54<0,"−","+")&TEXT(ABS(G54)*100,"#,##0.0")&"pt","")&"：拆法（分配 "&IF(G98<0,"−","+")&IF(ABS(G98)<0,"−","")&"$"&TEXT(ABS(ABS(G98)),"#,##0.000")&"bn"&"（Q2 FY28 占 FY28 "&TEXT((G28/損益!D21)*100,"#,##0.0")&"%"&"，共識合計 "&TEXT(((G35)/G96)*100,"#,##0.0")&"%"&"）；水準 "&IF(G97<0,"−","+")&IF(ABS(G97)<0,"−","")&"$"&TEXT(ABS(ABS(G97)),"#,##0.000")&"bn"&"）","調整後 EBITDA vs 共識 "&IF(G49<0,"−","+")&IF(ABS(G49)<0,"−","")&"$"&TEXT(ABS(ABS(G49)),"#,##0.00")&"bn"&IF(ISNUMBER(G54),"／"&IF(G54<0,"−","+")&TEXT(ABS(G54)*100,"#,##0.0")&"pt","")&"：觀點（水準 "&IF(G97<0,"−","+")&IF(ABS(G97)<0,"−","")&"$"&TEXT(ABS(ABS(G97)),"#,##0.000")&"bn"&"（FY28 模型 "&IF(損益!D21<0,"−","")&"$"&TEXT(ABS(損益!D21),"#,##0.000")&"bn"&"，共識合計 "&IF(G96<0,"−","")&"$"&TEXT(ABS(G96),"#,##0.000")&"bn"&"）；分配 "&IF(G98<0,"−","+")&IF(ABS(G98)<0,"−","")&"$"&TEXT(ABS(ABS(G98)),"#,##0.000")&"bn"&"；"&"模型 EBITDA 率 "&IF((G27)<0,"−","")&TEXT(ABS((G27))*100,"#,##0.0")&"%"&"；季度共識 EBITDA "&"不適用"&"、營收 "&"不適用"&"（共識 EBITDA＝非 GAAP 營業利益＋折舊）"&"）"),"調整後 EBITDA vs 共識 "&IF(G49<0,"−","+")&IF(ABS(G49)<0,"−","")&"$"&TEXT(ABS(ABS(G49)),"#,##0.00")&"bn"&IF(ISNUMBER(G54),"／"&IF(G54<0,"−","+")&TEXT(ABS(G54)*100,"#,##0.0")&"pt","")&"：觀點（"&"模型 EBITDA 率 "&IF((G27)<0,"−","")&TEXT(ABS((G27))*100,"#,##0.0")&"%"&"；季度共識 EBITDA "&"不適用"&"、營收 "&"不適用"&"（共識 EBITDA＝非 GAAP 營業利益＋折舊）"&"）"),""),"") | H99: =IF(ISNUMBER(H49),IF(IF(ISNUMBER(H54),ABS(H54)>輸入與假設!$C$334,OR(AND(H35<>0,ABS(H49)>輸入與假設!$C$333*ABS(H35)),AND(H35=0,H49<>0))),IF(ISNUMBER(H97),IF(ABS(H98)>ABS(H97),"調整後 EBITDA vs 共識 "&IF(H49<0,"−","+")&IF(ABS(H49)<0,"−","")&"$"&TEXT(ABS(ABS(H49)),"#,##0.00")&"bn"&IF(ISNUMBER(H54),"／"&IF(H54<0,"−","+")&TEXT(ABS(H54)*100,"#,##0.0")&"pt","")&"：拆法（分配 "&IF(H98<0,"−","+")&IF(ABS(H98)<0,"−","")&"$"&TEXT(ABS(ABS(H98)),"#,##0.000")&"bn"&"（Q3 FY28 占 FY28 "&TEXT((H28/損益!D21)*100,"#,##0.0")&"%"&"，共識合計 "&TEXT(((H35)/H96)*100,"#,##0.0")&"%"&"）；水準 "&IF(H97<0,"−","+")&IF(ABS(H97)<0,"−","")&"$"&TEXT(ABS(ABS(H97)),"#,##0.000")&"bn"&"）","調整後 EBITDA vs 共識 "&IF(H49<0,"−","+")&IF(ABS(H49)<0,"−","")&"$"&TEXT(ABS(ABS(H49)),"#,##0.00")&"bn"&IF(ISNUMBER(H54),"／"&IF(H54<0,"−","+")&TEXT(ABS(H54)*100,"#,##0.0")&"pt","")&"：觀點（水準 "&IF(H97<0,"−","+")&IF(ABS(H97)<0,"−","")&"$"&TEXT(ABS(ABS(H97)),"#,##0.000")&"bn"&"（FY28 模型 "&IF(損益!D21<0,"−","")&"$"&TEXT(ABS(損益!D21),"#,##0.000")&"bn"&"，共識合計 "&IF(H96<0,"−","")&"$"&TEXT(ABS(H96),"#,##0.000")&"bn"&"）；分配 "&IF(H98<0,"−","+")&IF(ABS(H98)<0,"−","")&"$"&TEXT(ABS(ABS(H98)),"#,##0.000")&"bn"&"；"&"模型 EBITDA 率 "&IF((H27)<0,"−","")&TEXT(ABS((H27))*100,"#,##0.0")&"%"&"；季度共識 EBITDA "&"不適用"&"、營收 "&"不適用"&"（共識 EBITDA＝非 GAAP 營業利益＋折舊）"&"）"),"調整後 EBITDA vs 共識 "&IF(H49<0,"−","+")&IF(ABS(H49)<0,"−","")&"$"&TEXT(ABS(ABS(H49)),"#,##0.00")&"bn"&IF(ISNUMBER(H54),"／"&IF(H54<0,"−","+")&TEXT(ABS(H54)*100,"#,##0.0")&"pt","")&"：觀點（"&"模型 EBITDA 率 "&IF((H27)<0,"−","")&TEXT(ABS((H27))*100,"#,##0.0")&"%"&"；季度共識 EBITDA "&"不適用"&"、營收 "&"不適用"&"（共識 EBITDA＝非 GAAP 營業利益＋折舊）"&"）"),""),"")
A100: 原因類型｜調整後 EBITDA｜vs 共識 | C100: =IF(ISNUMBER(C49),IF(IF(ISNUMBER(C54),ABS(C54)>輸入與假設!$C$334,OR(AND(C35<>0,ABS(C49)>輸入與假設!$C$333*ABS(C35)),AND(C35=0,C49<>0))),IF(ISNUMBER(C97),IF(ABS(C98)>ABS(C97),"拆法","觀點"),"觀點"),""),"") | D100: =IF(ISNUMBER(D49),IF(IF(ISNUMBER(D54),ABS(D54)>輸入與假設!$C$334,OR(AND(D35<>0,ABS(D49)>輸入與假設!$C$333*ABS(D35)),AND(D35=0,D49<>0))),IF(ISNUMBER(D97),IF(ABS(D98)>ABS(D97),"拆法","觀點"),"觀點"),""),"") | E100: =IF(ISNUMBER(E49),IF(IF(ISNUMBER(E54),ABS(E54)>輸入與假設!$C$334,OR(AND(E35<>0,ABS(E49)>輸入與假設!$C$333*ABS(E35)),AND(E35=0,E49<>0))),IF(ISNUMBER(E97),IF(ABS(E98)>ABS(E97),"拆法","觀點"),"觀點"),""),"") | F100: =IF(ISNUMBER(F49),IF(IF(ISNUMBER(F54),ABS(F54)>輸入與假設!$C$334,OR(AND(F35<>0,ABS(F49)>輸入與假設!$C$333*ABS(F35)),AND(F35=0,F49<>0))),IF(ISNUMBER(F97),IF(ABS(F98)>ABS(F97),"拆法","觀點"),"觀點"),""),"") | G100: =IF(ISNUMBER(G49),IF(IF(ISNUMBER(G54),ABS(G54)>輸入與假設!$C$334,OR(AND(G35<>0,ABS(G49)>輸入與假設!$C$333*ABS(G35)),AND(G35=0,G49<>0))),IF(ISNUMBER(G97),IF(ABS(G98)>ABS(G97),"拆法","觀點"),"觀點"),""),"") | H100: =IF(ISNUMBER(H49),IF(IF(ISNUMBER(H54),ABS(H54)>輸入與假設!$C$334,OR(AND(H35<>0,ABS(H49)>輸入與假設!$C$333*ABS(H35)),AND(H35=0,H49<>0))),IF(ISNUMBER(H97),IF(ABS(H98)>ABS(H97),"拆法","觀點"),"觀點"),""),"")
A101: 原因｜調整後 EBITDA｜vs 指引中點
A102: 原因類型｜調整後 EBITDA｜vs 指引中點
...

Sheet 運營_產能與收入
A1: 產能與收入 — 合約排程 vs 機房產能
A2: 兩條線獨立產生後相減：排程>容量→瓶頸（收不到）；容量>排程→剩餘產能（要靠新簽約賣掉）
A3: FY27 欄口徑：MW 為年底存量；標示「（模型期）」的收入列只含 2027 第 2–4 季——RPO 桶自 2026-08-31 起算，1Q 收入已實現、不再受產能約束。1Q 實際單列，兩者相加即 FY27 全年（見本頁「FY26 全年」列）。
A5: 項目 | B5: 單位 | C5: FY27 | D5: FY28 | E5: FY29 | F5: FY30 | G5: FY31 | I5: 公式／來源說明
A6: 模型期間 | C6: ="2026-09-01~05-31" -> 2026-09-01~05-31 | D6: ="2028 全年" -> 2028 全年 | E6: ="2029 全年" -> 2029 全年 | F6: ="2030 全年" -> 2030 全年 | G6: ="2031 全年" -> 2031 全年 | I6: FY27 的模型期只有第 2–4 季；1Q 已實現的營收單列於下方
A7: 模型期長度（年） | C7: =輸入與假設!C$41 -> 0.75 | D7: =輸入與假設!D$41 -> 1 | E7: =輸入與假設!E$41 -> 1 | F7: =輸入與假設!F$41 -> 1 | G7: =輸入與假設!G$41 -> 1 | I7: 只用於下方三處：容量上限、電力、維護——把年率換算成該期金額
A8: （A）機房：容量上限
A9: Accepted MW（已驗收，單調不減） | B9: MW | C9: =MAX(0,輸入與假設!C$43) -> 4668 | D9: =MAX(輸入與假設!D$43,C9) -> 7501 | E9: =MAX(輸入與假設!E$43,D9) -> 8778 | F9: =MAX(輸入與假設!F$43,E9) -> 8778 | G9: =MAX(輸入與假設!G$43,F9) -> 8778 | I9: 引擎規則：不得低於前期（產能不會消失）
A10: Billable MW（上限為 Accepted） | B10: MW | C10: =MIN(MAX(0,輸入與假設!C$44),C9) -> 3183 | D10: =MIN(MAX(0,輸入與假設!D$44),D9) -> 6340 | E10: =MIN(MAX(0,輸入與假設!E$44),E9) -> 7716 | F10: =MIN(MAX(0,輸入與假設!F$44),F9) -> 8070 | G10: =MIN(MAX(0,輸入與假設!G$44),G9) -> 8070 | I10: 引擎規則：可計費不得超過已驗收
A11: 期初在役 MW | B11: MW | C11: =輸入與假設!$C$36 -> 1698 | D11: =C10 -> 3183 | E11: =D10 -> 6340 | F11: =E10 -> 7716 | G11: =F10 -> 8070 | I11: 前期期末＝本期期初
A12: 平均在役 MW（FY27 欄為第 2–4 季平均） | B12: MW | C12: =IF(輸入與假設!$C$37=1,(C11+C10)/2,C10) -> 2440.5 | D12: =IF(輸入與假設!$C$37=1,(D11+D10)/2,D10) -> 4761.5 | E12: =IF(輸入與假設!$C$37=1,(E11+E10)/2,E10) -> 7028 | F12: =IF(輸入與假設!$C$37=1,(F11+F10)/2,F10) -> 7893 | G12: =IF(輸入與假設!$C$37=1,(G11+G10)/2,G10) -> 8070 | I12: 開關在輸入頁：1＝(期初+期末)/2，0＝期末全期化
A13: 利用率 | B13: % | C13: =輸入與假設!C$45 -> 1 | D13: =輸入與假設!D$45 -> 1 | E13: =輸入與假設!E$45 -> 1 | F13: =輸入與假設!F$45 -> 1 | G13: =輸入與假設!G$45 -> 1
A14: 每 MW 年收入 | B14: US$bn/MW | C14: =輸入與假設!C$46 -> 0.0174 | D14: =輸入與假設!D$46 -> 0.0174 | E14: =輸入與假設!E$46 -> 0.0174 | F14: =輸入與假設!F$46 -> 0.0174 | G14: =輸入與假設!G$46 -> 0.0174
A15: 容量上限（模型期最多能交付的收入） | B15: US$bn | C15: =C12*輸入與假設!C$46*輸入與假設!$C$39*輸入與假設!C$45*C7 -> 31.848525 | D15: =D12*輸入與假設!D$46*輸入與假設!$C$39*輸入與假設!D$45*D7 -> 82.8501 | E15: =E12*輸入與假設!E$46*輸入與假設!$C$39*輸入與假設!E$45*E7 -> 122.2872 | F15: =F12*輸入與假設!F$46*輸入與假設!$C$39*輸入與假設!F$45*F7 -> 137.3382 | G15: =G12*輸入與假設!G$46*輸入與假設!$C$39*輸入與假設!G$45*G7 -> 140.418 | I15: ＝平均在役 MW × 每 MW 年收入 × 利用率 × 期間係數。只看機房，不看合約
A16: （B）合約：排程 RPO
A17: 排程 RPO（模型期，依季報桶分攤） | B17: US$bn | C17: =(輸入與假設!$C$31+輸入與假設!$C$32)*(輸入與假設!C$42/輸入與假設!$C$34)*輸入與假設!$C$33 -> 64.74 | D17: =(輸入與假設!$C$31+輸入與假設!$C$32)*(輸入與假設!D$42/輸入與假設!$C$34)*輸入與假設!$C$33 -> 113.71 | E17: =(輸入與假設!$C$31+輸入與假設!$C$32)*(輸入與假設!E$42/輸入與假設!$C$34)*輸入與假設!$C$33 -> 122.84 | F17: =(輸入與假設!$C$31+輸入與假設!$C$32)*(輸入與假設!F$42/輸入與假設!$C$34)*輸入與假設!$C$33 -> 115.37 | G17: =(輸入與假設!$C$31+輸入與假設!$C$32)*(輸入與假設!G$42/輸入與假設!$C$34)*輸入與假設!$C$33 -> 112.88 | I17: ＝(8/31 RPO＋評價日後新增)×本期權重÷權重合計×五期認列比例。只看合約，不看機房
A18: （C）兩條線相減
A19: 產能瓶頸（模型期：排程 − 容量） | B19: US$bn | C19: =MAX(0,C17-C15) -> 32.891475 | D19: =MAX(0,D17-D15) -> 30.8599 | E19: =MAX(0,E17-E15) -> 0.5528 | F19: =MAX(0,F17-F15) -> 0 | G19: =MAX(0,G17-G15) -> 0 | I19: 合約有、機房沒有 → 本期收不到，且不遞延到下期（保守處理）
A20: 期初 RPO 轉換收入（模型期） | B20: US$bn | C20: =C17-C19 -> 31.848525 | D20: =D17-D19 -> 82.8501 | E20: =E17-E19 -> 122.2872 | F20: =F17-F19 -> 115.37 | G20: =G17-G19 -> 112.88 | I20: ＝排程 − 瓶頸。當瓶頸>0 時，此值恆等於容量上限
A21: 未被期初 RPO 占用的產能 | B21: US$bn | C21: =MAX(0,C15-C17) -> 0 | D21: =MAX(0,D15-D17) -> 0 | E21: =MAX(0,E15-E17) -> 0 | F21: =MAX(0,F15-F17) -> 21.9682 | G21: =MAX(0,G15-G17) -> 27.538 | I21: 容量 − 排程。機房有、期初合約沒占滿 → 要靠新簽約
A22: 新產能簽約率 | B22: % | C22: =IF(輸入與假設!$C$38="mw",1,輸入與假設!C$47) -> 1 | D22: =IF(輸入與假設!$C$38="mw",1,輸入與假設!D$47) -> 1 | E22: =IF(輸入與假設!$C$38="mw",1,輸入與假設!E$47) -> 1 | F22: =IF(輸入與假設!$C$38="mw",1,輸入與假設!F$47) -> 1 | G22: =IF(輸入與假設!$C$38="mw",1,輸入與假設!G$47) -> 1 | I22: MW 驅動時固定 100%
A23: 新簽約收入 | B23: US$bn | C23: =C21*C22 -> 0 | D23: =D21*D22 -> 0 | E23: =E21*E22 -> 0 | F23: =F21*F22 -> 21.9682 | G23: =G21*G22 -> 27.538 | I23: 超出期初 RPO 的產能收入（MW 驅動，簽約率 100%）
A24: 未售產能（浪費） | B24: US$bn | C24: =MAX(0,C15-C20-C23) -> 0 | D24: =MAX(0,D15-D20-D23) -> 0 | E24: =MAX(0,E15-E20-E23) -> 0 | F24: =MAX(0,F15-F20-F23) -> 0 | G24: =MAX(0,G15-G20-G23) -> 0 | I24: 蓋好但賣不掉（MW 驅動時為 0）
A25: 損益用算力收入（模型期＝RPO 轉換＋新簽約） | B25: US$bn | C25: =C20+C23 -> 31.848525 | D25: =D20+D23 -> 82.8501 | E25: =E20+E23 -> 122.2872 | F25: =F20+F23 -> 137.3382 | G25: =G20+G23 -> 140.418 | I25: 損益與評價頁的算力收入由此連結，確保現金與損益同一組數字
A26: 核對：算力收入 − 平均在役 MW × 每 MW × 利用率 × 期間 | B26: US$bn | C26: =C25-C12*輸入與假設!C$46*輸入與假設!$C$39*輸入與假設!C$45*C7 -> 0 | D26: =D25-D12*輸入與假設!D$46*輸入與假設!$C$39*輸入與假設!D$45*D7 -> 0 | E26: =E25-E12*輸入與假設!E$46*輸入與假設!$C$39*輸入與假設!E$45*E7 -> 0 | F26: =F25-F12*輸入與假設!F$46*輸入與假設!$C$39*輸入與假設!F$45*F7 -> 0 | G26: =G25-G12*輸入與假設!G$46*輸入與假設!$C$39*輸入與假設!G$45*G7 -> 0 | I26: MW 驅動時應為 0：營收可追溯為 MW × 每 MW 年收入 × 利用率（v0.1b）
A27: 對照：評價日起 36 個月營收權重 | B27: % | C27: 1 | D27: 1 | E27: 1 | F27: 0.25 | G27: 0 | I27: RPO 36 個月內轉換的對照用（只作對照，不驅動營收）
A28: 對照：評價日起 36 個月 MW 驅動營收 | B28: US$bn | C28: =C25*C27 -> 31.848525 | D28: =D25*D27 -> 82.8501 | E28: =E25*E27 -> 122.2872 | F28: =F25*F27 -> 34.33455 | G28: =G25*G27 -> 0 | I28: 合計對照季報 RPO 664 × 36 個月內 50%（含傳統事業 RPO）；差額不回推每 MW 單價
A29: 1Q27 實際營收（季報，已實現） | B29: US$bn | C29: =輸入與假設!$C$251 -> 19.345 | D29: =0 -> 0 | E29: =0 -> 0 | F29: =0 -> 0 | G29: =0 -> 0 | I29: 2026-06-01 至 08-31 已認列營收。已實現，不受第 2–4 季產能約束，故不進入上方的瓶頸計算
A30: FY27 全年總營收（1Q 實際＋模型期算力＋服務＋傳統事業） | B30: US$bn | C30: =C29+C25+輸入與假設!C$50+輸入與假設!C$81 -> 90.727495 | D30: =D29+D25+輸入與假設!D$50+輸入與假設!D$81 -> 136.55822 | E30: =E29+E25+輸入與假設!E$50+輸入與假設!E$81 -> 178.14101 | F30: =F29+F25+輸入與假設!F$50+輸入與假設!F$81 -> 195.21332 | G30: =G29+G25+輸入與假設!G$50+輸入與假設!G$81 -> 200.14048 | I30: FY27 欄對照公司全年指引 ≥90；FY28 以後即為該年度總營收
A31: （D）收入 → 現金：三道折扣
A32: 客戶違約率 | B32: % | C32: =輸入與假設!C$48 -> 0.005 | D32: =輸入與假設!D$48 -> 0.01 | E32: =輸入與假設!E$48 -> 0.015 | F32: =輸入與假設!F$48 -> 0.02 | G32: =輸入與假設!G$48 -> 0.025
A33: 回收率 | B33: % | C33: =輸入與假設!C$49 -> 0.5 | D33: =輸入與假設!D$49 -> 0.5 | E33: =輸入與假設!E$49 -> 0.5 | F33: =輸入與假設!F$49 -> 0.5 | G33: =輸入與假設!G$49 -> 0.5
A34: 信用損失（期初 RPO 部分） | B34: US$bn | C34: =C20*輸入與假設!C$48*(1-輸入與假設!C$49) -> 0.079621312 | D34: =D20*輸入與假設!D$48*(1-輸入與假設!D$49) -> 0.4142505 | E34: =E20*輸入與假設!E$48*(1-輸入與假設!E$49) -> 0.917154 | F34: =F20*輸入與假設!F$48*(1-輸入與假設!F$49) -> 1.1537 | G34: =G20*輸入與假設!G$48*(1-輸入與假設!G$49) -> 1.411 | I34: ＝收入 × 違約率 × (1−回收率)
A35: 收現（期初 RPO 部分） | B35: US$bn | C35: =C20-C34 -> 31.768904 | D35: =D20-D34 -> 82.43585 | E35: =E20-E34 -> 121.37005 | F35: =F20-F34 -> 114.2163 | G35: =G20-G34 -> 111.469
A36: EBITDA 率（損益與資金共用） | B36: % | C36: =輸入與假設!C$93 -> 0.6519998 | D36: =輸入與假設!D$93 -> 0.62804402 | E36: =輸入與假設!E$93 -> 0.57518339 | F36: =輸入與假設!F$93 -> 0.52111306 | G36: =輸入與假設!G$93 -> 0.46999955 | I36: 起始→穩態線性爬升
A37: 模型期總營收（算力＋服務） | B37: US$bn | C37: =C25+輸入與假設!C$50 -> 31.848525 | D37: =D25+輸入與假設!D$50 -> 82.8501 | E37: =E25+輸入與假設!E$50 -> 122.2872 | F37: =F25+輸入與假設!F$50 -> 137.3382 | G37: =G25+輸入與假設!G$50 -> 140.418
A38: EBITDAR 率（EBITDA 率＋租金÷營收） | B38: % | C38: =輸入與假設!C$93+各期收支!C16/MAX(0.01,C37) -> 0.845075 | D38: =輸入與假設!D$93+各期收支!D16/MAX(0.01,D37) -> 0.790477 | E38: =輸入與假設!E$93+各期收支!E16/MAX(0.01,E37) -> 0.735879 | F38: =輸入與假設!F$93+各期收支!F16/MAX(0.01,F37) -> 0.681281 | G38: =輸入與假設!G$93+各期收支!G16/MAX(0.01,G37) -> 0.626683 | I38: 租金前的 EBITDA 率。EBITDA 已扣租金，而資金模型把租金列在支出端，所以要加回，避免重複扣除
A39: RPO 現金（可支應資本用途） | B39: US$bn | C39: =C35*C38 -> 26.847106 | D39: =D35*D38 -> 65.163643 | E39: =E35*E38 -> 89.313668 | F39: =F35*F38 -> 77.813395 | G39: =G35*G38 -> 69.855727 | I39: ×EBITDAR 率。租金與利息在支出頁單獨列示
A40: 新簽約現金 | B40: US$bn | C40: =C23*(1-輸入與假設!C$48*(1-輸入與假設!C$49))*C38 -> 0 | D40: =D23*(1-輸入與假設!D$48*(1-輸入與假設!D$49))*D38 -> 0 | E40: =E23*(1-輸入與假設!E$48*(1-輸入與假設!E$49))*E38 -> 0 | F40: =F23*(1-輸入與假設!F$48*(1-輸入與假設!F$49))*F38 -> 14.816852 | G40: =G23*(1-輸入與假設!G$48*(1-輸入與假設!G$49))*G38 -> 17.041876 | I40: 同樣扣信用損失、乘 EBITDAR 率
A42: 讀法：FY27（2Q–4Q）與 FY28 瓶頸>0，合約多於機房；FY28 起反轉，收入愈來愈靠『新簽約收入』這一列。
A43: 把『新產能簽約率』調到 0，就能看到只靠期初 RPO 的資金缺口有多大——這是最重要的一個壓力測試。

Sheet 運營_站點
A1: 站點租賃 — 公司揭露 vs 季報總額（檢驗租金路徑用）
A2: 季報不揭露逐站租金；下表為具名站點（company.json → defaults.sites），有租約金額者用來檢驗『每 MW 年租金』與模型租金路徑是否一致
A4: 站點 | B4: 營運方 | C4: 契約 MW | D4: 已驗收 MW | E4: 合約總值 $bn | F4: 年期 | G4: 年租金 $bn | H4: 每 MW 年租金 $m | I4: 時程 | J4: 季報對應 | K4: 說明
A5: Abilene, TX（Stargate 一期） | B5: Crusoe／Blue Owl 開發、Oracle 承租（OpenAI） | C5: 1000 | D5: 515 | E5: 未揭露 | F5: 未揭露 | I5: 2026–2027 | J5: — | K5: 法說：已交付 618 MW＝75%（口徑不明，÷1.2 換 IT 約 515）；Epoch 估設施 1.2 GW [Interested-party／Derived]
A6: Shackelford County, TX（Frontier） | B6: Vantage 開發、Oracle 承租 | C6: 1667 | D6: 0 | E6: 未揭露 | F6: 未揭露 | I6: 2027 起 | J6: — | K6: Epoch 估設施 2.0 GW（÷1.2 約 1,667 MW-IT）；開發商融資 38B（含 Port Washington）[Derived]
A7: Doña Ana County, NM（Project Jupiter） | B7: BorderPlex／STACK 開發、Oracle 承租 | C7: 1833 | D7: 0 | E7: 未揭露 | F7: 未揭露 | I7: 延後 | J7: — | K7: Epoch 估設施 2.2 GW；2026-09-24 Oracle 發不可抗力通知（能源延誤）[Interested-party]
A8: Port Washington, WI | B8: Vantage 開發、Oracle 承租 | C8: 1083 | D8: 0 | E8: 未揭露 | F8: 未揭露 | I8: 2027 起 | J8: — | K8: Epoch 估設施 1.3 GW [Derived]
A9: Saline Township, MI（The Barn） | B9: Related Digital 開發、Oracle 承租 | C9: 1167 | D9: 0 | E9: 未揭露 | F9: 未揭露 | I9: 2027 起 | J9: — | K9: Epoch 估設施 1.4 GW；開發商融資 16B [Derived]
A10: 具名站點合計 | C10: =SUM(C5:C9) -> 6750 | D10: =SUM(D5:D9) -> 515 | E10: =SUM(E5:E9) -> 0 | G10: =SUM(G5:G9) -> 0 | H10: =IF(I10>0,G10/I10*1000,0) -> 0 | I10: =SUMPRODUCT(ISNUMBER(G5:G9)*C5:C9) -> 0 | K10: 加權每 MW 年租金＝具名站點的市場基準（I 欄＝有租約金額站點的契約 MW；沒有時為 0，不適用）
A12: 對帳：具名站點 vs 季報租賃承諾總額
A13: 季報在帳租賃（未折現，已起租） | E13: 63.245 | K13: company.json → leases.facts.onBal
A14: 季報未起租租賃（未折現） | E14: 288 | K14: company.json → leases.facts.notCommenced
A15: 季報單站按造價計租上限 | E15: 0 | K15: company.json → leases.facts.singleCap（無則 0）
A16: 季報已揭露租賃承諾合計 | E16: =SUM(E13:E15) -> 351.245 | K16: 未折現金額
A17: 減：具名站點合約總值 | E17: =-E10 -> 0
A18: ＝ 未具名站點（殘差） | E18: =E16+E17 -> 351.245 | K18: 未具名站點；公司不揭露逐站租金，殘差大是必然
A19: 殘差占季報總額 | E19: =IF(E16<>0,E18/E16,0) -> 1
A21: 檢驗：模型租金路徑 ÷ 在役 MW vs 市場基準
A22: 項目 | B22: 單位 | C22: FY27 | D22: FY28 | E22: FY29 | F22: FY30 | G22: FY31
A23: 模型租金（在帳＋表外） | B23: US$bn | C23: =各期收支!C16 -> 6.1491604 | D23: =各期收支!D16 -> 13.457588 | E23: =各期收支!E16 -> 19.651016 | F23: =各期收支!F16 -> 21.997176 | G23: =各期收支!G16 -> 22.001176
A24: 平均在役 MW（已連網） | B24: MW | C24: =(輸入與假設!C$124+輸入與假設!C$43)/2 -> 3251.5 | D24: =(輸入與假設!D$124+輸入與假設!D$43)/2 -> 6084.5 | E24: =(輸入與假設!E$124+輸入與假設!E$43)/2 -> 8139.5 | F24: =(輸入與假設!F$124+輸入與假設!F$43)/2 -> 8778 | G24: =(輸入與假設!G$124+輸入與假設!G$43)/2 -> 8778
A25: 模型期長度（年） | B25: 年 | C25: =輸入與假設!C$41 -> 0.75 | D25: =輸入與假設!D$41 -> 1 | E25: =輸入與假設!E$41 -> 1 | F25: =輸入與假設!F$41 -> 1 | G25: =輸入與假設!G$41 -> 1
A26: 模型每 MW 年租金 | B26: US$m/MW | C26: =C23/C25/C24*1000 -> 2.5215687 | D26: =D23/D25/D24*1000 -> 2.2117821 | E26: =E23/E25/E24*1000 -> 2.414278 | F26: =F23/F25/F24*1000 -> 2.505944 | G26: =G23/G25/G24*1000 -> 2.5063997 | K26: FY27 欄只含第 2–4 季租金、MW 取全期平均，略有低估
A27: 第三方租賃占比 | C27: 1 | K27: 其餘為自建，成本走 CapEx（company.json → leases.facts.share）[Assumed]
A28: 基準租金（MW×市場基準×占比） | B28: US$bn | C28: =C24*運營_站點!$H$10/1000*$C$27*C25 -> 0 | D28: =D24*運營_站點!$H$10/1000*$C$27*D25 -> 0 | E28: =E24*運營_站點!$H$10/1000*$C$27*E25 -> 0 | F28: =F24*運營_站點!$H$10/1000*$C$27*F25 -> 0 | G28: =G24*運營_站點!$H$10/1000*$C$27*G25 -> 0 | K28: 具名站點有租約金額時才有意義；否則為 0
A29: 差額（基準 − 模型） | B29: US$bn | C29: =C28-C23 -> -6.1491604 | D29: =D28-D23 -> -13.457588 | E29: =E28-E23 -> -19.651016 | F29: =F28-F23 -> -21.997176 | G29: =G28-G23 -> -22.001176 | K29: 正值＝模型租金可能低估的金額
A30: 五期差額合計 | C30: =SUM(C29:G29) -> -83.256118

Sheet 資產負債_既有債務
A1: 債務明細 — 季報（2026-08-31）逐筆＋存量利息推導
A2: 有效利率為現金票息口徑（可轉債＝票息 ÷ 到期累積倍數，本金以到期累積本金計）。本頁算出的存量利息連回『輸入』頁，再進入支出與資金頁
A4: 工具 | B4: 類別 | C4: 到期 | D4: 有效利率 | E4: 8/31 本金 | F4: 年化利息 | I4: 備註
A5: 2.80% 優先票據 2027-04 | B5: 無擔保 | C5: 2027-04 | D5: 0.028 | E5: 2.25 | F5: =D5*E5 -> 0.063 | I5: 10-K 附註 6（發行 April 2020）[Verified]
A6: 3.25% 優先票據 2027-11 | B6: 無擔保 | C6: 2027-11 | D6: 0.0325 | E6: 2.75 | F6: =D6*E6 -> 0.089375 | I6: 10-K 附註 6（發行 November 2017）[Verified]
A7: 2.30% 優先票據 2028-03 | B7: 無擔保 | C7: 2028-03 | D7: 0.023 | E7: 2 | F7: =D7*E7 -> 0.046 | I7: 10-K 附註 6（發行 March 2021）[Verified]
A8: 4.50% 優先票據 2028-05 | B8: 無擔保 | C8: 2028-05 | D8: 0.045 | E8: 0.75 | F8: =D8*E8 -> 0.03375 | I8: 10-K 附註 6（發行 February 2023）[Verified]
A9: 4.80% 優先票據 2028-08 | B9: 無擔保 | C9: 2028-08 | D9: 0.048 | E9: 1.5 | F9: =D9*E9 -> 0.072 | I9: 10-K 附註 6（發行 February 2025）[Verified]
A10: 4.55% 優先票據 2029-02 | B10: 無擔保 | C10: 2029-02 | D10: 0.0455 | E10: 3 | F10: =D10*E10 -> 0.1365 | I10: 10-K 附註 6（發行 February 2026）[Verified]
A11: 4.20% 優先票據 2029-09 | B11: 無擔保 | C11: 2029-09 | D11: 0.042 | E11: 1.5 | F11: =D11*E11 -> 0.063 | I11: 10-K 附註 6（發行 September 2024）[Verified]
A12: 6.15% 優先票據 2029-11 | B12: 無擔保 | C12: 2029-11 | D12: 0.0615 | E12: 1.25 | F12: =D12*E12 -> 0.076875 | I12: 10-K 附註 6（發行 November 2022）[Verified]
A13: 2.95% 優先票據 2030-04 | B13: 無擔保 | C13: 2030-04 | D13: 0.0295 | E13: 3.25 | F13: =D13*E13 -> 0.095875 | I13: 10-K 附註 6（發行 April 2020）[Verified]
A14: 4.65% 優先票據 2030-05 | B14: 無擔保 | C14: 2030-05 | D14: 0.0465 | E14: 0.75 | F14: =D14*E14 -> 0.034875 | I14: 10-K 附註 6（發行 February 2023）[Verified]
A15: 3.25% 優先票據 2030-05 | B15: 無擔保 | C15: 2030-05 | D15: 0.0325 | E15: 0.5 | F15: =D15*E15 -> 0.01625 | I15: 10-K 附註 6（發行 May 2015）[Verified]
A16: 4.45% 優先票據 2030-09 | B16: 無擔保 | C16: 2030-09 | D16: 0.0445 | E16: 3 | F16: =D16*E16 -> 0.1335 | I16: 10-K 附註 6（發行 September 2025）[Verified]
... A61: 商業本票 | B61: 無擔保 | C61: 2026-11 | D61: 0.0435 | E61: 0.337 | F61: =D61*E61 -> 0.0146595 | I61: 帳面總借款 − 附註 2 不含商本借款推得 [Derived]
A62: 合計（8/31） | E62: =SUM(E5:E61) -> 125.904 | F62: =SUM(F5:F61) -> 6.0449478 | I62: 應等於最新季報本金合計 125.904（company.json → latestQuarter.debtPrincipal）
A63: 加權有效利率 | D63: =F62/E62 -> 0.048012357 | I63: ＝年化利息 ÷ 本金（company.json → debt.instruments 的有效利率）
A65: 評價日後新發可轉債 | D65: 0 | E65: 0 | F65: =D65*E65 -> 0 | I65: company.json → debt.convertible（期後新發；不在五期還本表內，只計利息）
A67: 可轉債逐檔（若轉換法：有效轉換價 < 判斷價 → 視為轉股，不計利息與還本）
A68: 可轉債 | B68: 到期 | C68: 票息 | D68: 原始本金 | E68: 到期累積倍數 | F68: 轉換價 | G68: 到期所屬模型期 | H68: 強制轉換（1＝是） | I68: 備註
A69: 6.50% Series D 強制轉換特別股（2026-02） | B69: 2029-01 | C69: 0.065 | D69: 5 | E69: 1 | F69: 160.06 | G69: 2 | H69: 1 | I69: 清算價 $5B（5,000 萬股 × $100）；2029-01-15 強制轉換為普通股，每股特別股轉 499.8126–624.7657 股（2,499–3,124 萬股）；一律轉股，取稀釋最大 31.238m 股（轉換價下限 $160.06）[Interested-party 8-K 2026-02]；6.50% 股利列於 defaults.dividend.preferred；權益，不列債務本金
I70: 到期所屬模型期：0＝首期 … 4＝末期、5＝模型期後（建置時依期末日推算）
A72: 可轉債（推導） | C72: 到期本金 | D72: 若轉換股數 | E72: 有效轉換價 | F72: 融資分類 | G72: 評價第一輪 | H72: 評價第二輪 | I72: 說明
A73: =A69 -> 6.50% Series D 強制轉換特別股（2026-02） | C73: =D69*E69 -> 5 | D73: =D69/F69 -> 0.031238286 | E73: =F69*E69 -> 160.06 | F73: =IF(OR(H69=1,E73<輸入與假設!$C$152),1,0) -> 1 | G73: =IF(OR(H69=1,E73<輸入與假設!$C$175),1,0) -> 1 | H73: =IF(OR(H69=1,E73<評價_DCF與目標價!$C$66),1,0) -> 1
A74: 合計 | C74: =SUM(C73:C73) -> 5 | D74: =SUM(D73:D73) -> 0.031238286 | I74: 分類 1＝轉股（若轉換法）、0＝債務。強制轉換者一律為 1。融資分類判斷價＝股權發行價；評價第一輪＝現價；第二輪＝MIN(現價, 第一輪加權目標價)
A76: 存量利息推導（本金依季報到期表遞減）
A77: 項目 | B77: 單位 | C77: FY27 | D77: FY28 | E77: FY29 | F77: FY30 | G77: FY31 | I77: 公式／來源說明
A78: 期初本金 | B78: US$bn | C78: =E62 -> 125.904 | D78: =C80 -> 122.897 | E78: =D80 -> 112.75 | F78: =E80 -> 107.25 | G78: =F80 -> 100 | I78: FY27 期初為 8/31 本金（模型期起點）
A79: 排程還本 | B79: US$bn | C79: =輸入與假設!C$170 -> 3.007 | D79: =輸入與假設!D$170 -> 10.147 | E79: =輸入與假設!E$170 -> 5.5 | F79: =輸入與假設!F$170 -> 7.25 | G79: =輸入與假設!G$170 -> 9.75 | I79: 季報到期表
A80: 期末本金 | B80: US$bn | C80: =C78-C79 -> 122.897 | D80: =D78-D79 -> 112.75 | E80: =E78-E79 -> 107.25 | F80: =F78-F79 -> 100 | G80: =G78-G79 -> 90.25
A81: 平均本金 | B81: US$bn | C81: =(C78+C80)/2 -> 124.4005 | D81: =(D78+D80)/2 -> 117.8235 | E81: =(E78+E80)/2 -> 110 | F81: =(F78+F80)/2 -> 103.625 | G81: =(G78+G80)/2 -> 95.125
A82: 存量債務利息 | B82: US$bn | C82: =C81*資產負債_既有債務!$D$63*輸入與假設!C$41 -> 4.4795709 | D82: =D81*資產負債_既有債務!$D$63*輸入與假設!D$41 -> 5.6569839 | E82: =E81*資產負債_既有債務!$D$63*輸入與假設!E$41 -> 5.2813593 | F82: =F81*資產負債_既有債務!$D$63*輸入與假設!F$41 -> 4.9752805 | G82: =G81*資產負債_既有債務!$D$63*輸入與假設!G$41 -> 4.5671755 | I82: ＝平均本金×加權有效利率×期間長度。限制：假設利率組合不變；可轉債折價攤銷（非現金）不計
A83: 期後新發可轉債利息 | B83: US$bn | C83: =資產負債_既有債務!$F$65*輸入與假設!C$41 -> 0 | D83: =資產負債_既有債務!$F$65*輸入與假設!D$41 -> 0 | E83: =資產負債_既有債務!$F$65*輸入與假設!E$41 -> 0 | F83: =資產負債_既有債務!$F$65*輸入與假設!F$41 -> 0 | G83: =資產負債_既有債務!$F$65*輸入與假設!G$41 -> 0
A84: 可轉債到期還本（債務處理） | B84: US$bn | C84: =IF(輸入與假設!$C$144=1,SUMPRODUCT((1-資產負債_既有債務!$F$73:$F$73)*資產負債_既有債務!$C$73:$C$73*(資產負債_既有債務!$G$69:$G$69=0)),0) -> 0 | D84: =IF(輸入與假設!$C$144=1,SUMPRODUCT((1-資產負債_既有債務!$F$73:$F$73)*資產負債_既有債務!$C$73:$C$73*(資產負債_既有債務!$G$69:$G$69=1)),0) -> 0 | E84: =IF(輸入與假設!$C$144=1,SUMPRODUCT((1-資產負債_既有債務!$F$73:$F$73)*資產負債_既有債務!$C$73:$C$73*(資產負債_既有債務!$G$69:$G$69=2)),0) -> 0 | F84: =IF(輸入與假設!$C$144=1,SUMPRODUCT((1-資產負債_既有債務!$F$73:$F$73)*資產負債_既有債務!$C$73:$C$73*(資產負債_既有債務!$G$69:$G$69=3)),0) -> 0 | G84: =IF(輸入與假設!$C$144=1,SUMPRODUCT((1-資產負債_既有債務!$F$73:$F$73)*資產負債_既有債務!$C$73:$C$73*(資產負債_既有債務!$G$69:$G$69=4)),0) -> 0 | I84: 融資分類為債務的可轉債，到期當期以到期累積本金現金還本
A85: 可轉債期末餘額（債務處理） | B85: US$bn | C85: =IF(輸入與假設!$C$144=1,SUMPRODUCT((1-資產負債_既有債務!$F$73:$F$73)*資產負債_既有債務!$C$73:$C$73*(資產負債_既有債務!$G$69:$G$69>0)),SUMPRODUCT((1-資產負債_既有債務!$F$73:$F$73)*資產負債_既有債務!$C$73:$C$73)) -> 0 | D85: =IF(輸入與假設!$C$144=1,SUMPRODUCT((1-資產負債_既有債務!$F$73:$F$73)*資產負債_既有債務!$C$73:$C$73*(資產負債_既有債務!$G$69:$G$69>1)),SUMPRODUCT((1-資產負債_既有債務!$F$73:$F$73)*資產負債_既有債務!$C$73:$C$73)) -> 0 | E85: =IF(輸入與假設!$C$144=1,SUMPRODUCT((1-資產負債_既有債務!$F$73:$F$73)*資產負債_既有債務!$C$73:$C$73*(資產負債_既有債務!$G$69:$G$69>2)),SUMPRODUCT((1-資產負債_既有債務!$F$73:$F$73)*資產負債_既有債務!$C$73:$C$73)) -> 0 | F85: =IF(輸入與假設!$C$144=1,SUMPRODUCT((1-資產負債_既有債務!$F$73:$F$73)*資產負債_既有債務!$C$73:$C$73*(資產負債_既有債務!$G$69:$G$69>3)),SUMPRODUCT((1-資產負債_既有債務!$F$73:$F$73)*資產負債_既有債務!$C$73:$C$73)) -> 0 | G85: =IF(輸入與假設!$C$144=1,SUMPRODUCT((1-資產負債_既有債務!$F$73:$F$73)*資產負債_既有債務!$C$73:$C$73*(資產負債_既有債務!$G$69:$G$69>4)),SUMPRODUCT((1-資產負債_既有債務!$F$73:$F$73)*資產負債_既有債務!$C$73:$C$73)) -> 0 | I85: 到期累積本金；關閉攤還時維持全額
A86: 可轉債票息（債務處理） | B86: US$bn | C86: =IF(輸入與假設!$C$144=1,SUMPRODUCT((1-資產負債_既有債務!$F$73:$F$73)*資產負債_既有債務!$D$69:$D$69*資產負債_既有債務!$C$69:$C$69*((資產負債_既有債務!$G$69:$G$69>0)+0.5*(資產負債_既有債務!$G$69:$G$69=0))),SUMPRODUCT((1-資產負債_既有債務!$F$73:$F$73)*資產負債_既有債務!$D$69:$D$69*資產負債_既有債務!$C$69:$C$69))*輸入與假設!C$41 -> 0 | D86: =IF(輸入與假設!$C$144=1,SUMPRODUCT((1-資產負債_既有債務!$F$73:$F$73)*資產負債_既有債務!$D$69:$D$69*資產負債_既有債務!$C$69:$C$69*((資產負債_既有債務!$G$69:$G$69>1)+0.5*(資產負債_既有債務!$G$69:$G$69=1))),SUMPRODUCT((1-資產負債_既有債務!$F$73:$F$73)*資產負債_既有債務!$D$69:$D$69*資產負債_既有債務!$C$69:$C$69))*輸入與假設!D$41 -> 0 | E86: =IF(輸入與假設!$C$144=1,SUMPRODUCT((1-資產負債_既有債務!$F$73:$F$73)*資產負債_既有債務!$D$69:$D$69*資產負債_既有債務!$C$69:$C$69*((資產負債_既有債務!$G$69:$G$69>2)+0.5*(資產負債_既有債務!$G$69:$G$69=2))),SUMPRODUCT((1-資產負債_既有債務!$F$73:$F$73)*資產負債_既有債務!$D$69:$D$69*資產負債_既有債務!$C$69:$C$69))*輸入與假設!E$41 -> 0 | F86: =IF(輸入與假設!$C$144=1,SUMPRODUCT((1-資產負債_既有債務!$F$73:$F$73)*資產負債_既有債務!$D$69:$D$69*資產負債_既有債務!$C$69:$C$69*((資產負債_既有債務!$G$69:$G$69>3)+0.5*(資產負債_既有債務!$G$69:$G$69=3))),SUMPRODUCT((1-資產負債_既有債務!$F$73:$F$73)*資產負債_既有債務!$D$69:$D$69*資產負債_既有債務!$C$69:$C$69))*輸入與假設!F$41 -> 0 | G86: =IF(輸入與假設!$C$144=1,SUMPRODUCT((1-資產負債_既有債務!$F$73:$F$73)*資產負債_既有債務!$D$69:$D$69*資產負債_既有債務!$C$69:$C$69*((資產負債_既有債務!$G$69:$G$69>4)+0.5*(資產負債_既有債務!$G$69:$G$69=4))),SUMPRODUCT((1-資產負債_既有債務!$F$73:$F$73)*資產負債_既有債務!$D$69:$D$69*資產負債_既有債務!$C$69:$C$69))*輸入與假設!G$41 -> 0 | I86: ＝原始本金 × 票息 × 期間長度；到期當期計半期
A87: FY26 新增借款利息校準 | B87: US$bn | C87: =0 -> 0 | D87: =0 -> 0 | E87: =0 -> 0 | F87: =0 -> 0 | G87: =0 -> 0 | I87: 讓首期模型利息對上公司季度利息指引的校準值（company.json → defaults.intCal）；無指引時為 0
A88: 存量利息合計（連回輸入頁） | B88: US$bn | C88: =C82+C83+C86+C87 -> 4.4795709 | D88: =D82+D83+D86+D87 -> 5.6569839 | E88: =E82+E83+E86+E87 -> 5.2813593 | F88: =F82+F83+F86+F87 -> 4.9752805 | G88: =G82+G83+G86+G87 -> 4.5671755 | I88: ＝存量債務利息＋期後新發可轉債利息＋可轉債票息＋首期校準

Sheet 資產負債_新債與新股
A1: 新債與新股（類資產負債表：現金、債務、股本、槓桿）
A2: 全部為連結公式。FY27 欄的現金自 2026-08-31 起算（模型期），與 HTML『資產與負債 → 新債與新股』同口徑
A4: 項目 | B4: 單位 | C4: FY27 | D4: FY28 | E4: FY29 | F4: FY30 | G4: FY31 | I4: 公式／來源說明
A5: 現金
A6: 期初現金 | B6: US$bn | C6: =輸入與假設!$C$139 -> 36.369 | D6: =各期收支!C51 -> 10 | E6: =各期收支!D51 -> 10 | F6: =各期收支!E51 -> 48.446703 | G6: =各期收支!F51 -> 69.42544 | I6: FY27＝8/31 現金（模型期起點）
A7: 營運收支淨額（含期後股權／可轉債，不含瀑布） | B7: US$bn | C7: =各期收支!C87-輸入與假設!$C$139 -> -35.019094 | D7: =各期收支!D87-各期收支!C87 -> -20.370782 | E7: =各期收支!E87-各期收支!D87 -> 40.257772 | F7: =各期收支!F87-各期收支!E87 -> 22.789806 | G7: =各期收支!G87-各期收支!F87 -> 15.120019 | I7: ＝融資前累積現金的當期變動；負值即當期外部資金需求
A8: ＋ 瀑布：新債（額度＋資產層） | B8: US$bn | C8: =各期收支!C70 -> 9.0434854 | D8: =各期收支!D70 -> 22.181851 | E8: =各期收支!E70 -> 0 | F8: =各期收支!F70 -> 0 | G8: =各期收支!G70 -> 0
A9: ＋ 瀑布：可轉債 | B9: US$bn | C9: =各期收支!C73 -> 0 | D9: =各期收支!D73 -> 0 | E9: =各期收支!E73 -> 0 | F9: =各期收支!F73 -> 0 | G9: =各期收支!G73 -> 0
A10: ＋ 瀑布：高息債 | B10: US$bn | C10: =各期收支!C77 -> 0 | D10: =各期收支!D77 -> 0 | E10: =各期收支!E77 -> 0 | F10: =各期收支!F77 -> 0 | G10: =各期收支!G77 -> 0
A11: ＋ 瀑布：股權募資 | B11: US$bn | C11: =各期收支!C76 -> 0 | D11: =各期收支!D76 -> 0 | E11: =各期收支!E76 -> 0 | F11: =各期收支!F76 -> 0 | G11: =各期收支!G76 -> 0
A12: − 新融資利息（新債＋可轉債＋高息債） | B12: US$bn | C12: =-各期收支!C78 -> -0.39339161 | D12: =-各期收支!D78 -> -1.8110695 | E12: =-各期收支!E78 -> -1.8110695 | F12: =-各期收支!F78 -> -1.8110695 | G12: =-各期收支!G78 -> -1.8110695
A13: 期末現金 | B13: US$bn | C13: =SUM(C6:C12) -> 10 | D13: =SUM(D6:D12) -> 10 | E13: =SUM(E6:E12) -> 48.446703 | F13: =SUM(F6:F12) -> 69.42544 | G13: =SUM(G6:G12) -> 82.734389 | I13: 應等於『各期收支』期末累積現金（見下列驗算）
A14: 驗算：與各期收支期末現金差異 | B14: US$bn | C14: =C13-各期收支!C51 -> 0 | D14: =D13-各期收支!D51 -> 0 | E14: =E13-各期收支!E51 -> 0 | F14: =F13-各期收支!F51 -> 0 | G14: =G13-各期收支!G51 -> 0 | I14: 應為 0
A15: 債務
A16: 既有債務期初（季報本金） | B16: US$bn | C16: =資產負債_既有債務!$E$62+SUMPRODUCT((1-資產負債_既有債務!$F$73:$F$73)*資產負債_既有債務!$C$73:$C$73) -> 125.904 | D16: =C18 -> 122.897 | E16: =D18 -> 112.75 | F16: =E18 -> 107.25 | G16: =F18 -> 100 | I16: FY27＝其他借款＋債務處理可轉債到期本金（轉股處理者不列）
A17: − 排程還本（模型期） | B17: US$bn | C17: =-IF(輸入與假設!$C$144=1,輸入與假設!C$170,0)-資產負債_既有債務!C84 -> -3.007 | D17: =-IF(輸入與假設!$C$144=1,輸入與假設!D$170,0)-資產負債_既有債務!D84 -> -10.147 | E17: =-IF(輸入與假設!$C$144=1,輸入與假設!E$170,0)-資產負債_既有債務!E84 -> -5.5 | F17: =-IF(輸入與假設!$C$144=1,輸入與假設!F$170,0)-資產負債_既有債務!F84 -> -7.25 | G17: =-IF(輸入與假設!$C$144=1,輸入與假設!G$170,0)-資產負債_既有債務!G84 -> -9.75
A18: 既有債務期末 | B18: US$bn | C18: =各期收支!C66-0 -> 122.897 | D18: =各期收支!D66-0 -> 112.75 | E18: =各期收支!E66-0 -> 107.25 | F18: =各期收支!F66-0 -> 100 | G18: =各期收支!G66-0 -> 90.25 | I18: ＝依到期表遞減（關閉攤還時維持期初）
A19: ＋ 期後新發可轉債 | B19: US$bn | C19: =0 -> 0 | D19: =0 -> 0 | E19: =0 -> 0 | F19: =0 -> 0 | G19: =0 -> 0
A20: ＋ 瀑布新債餘額 | B20: US$bn | C20: =各期收支!C82 -> 9.0434854 | D20: =各期收支!D82 -> 31.225337 | E20: =各期收支!E82 -> 31.225337 | F20: =各期收支!F82 -> 31.225337 | G20: =各期收支!G82 -> 31.225337
A21: ＋ 瀑布可轉債餘額 | B21: US$bn | C21: =各期收支!C85 -> 0 | D21: =各期收支!D85 -> 0 | E21: =各期收支!E85 -> 0 | F21: =各期收支!F85 -> 0 | G21: =各期收支!G85 -> 0
A22: ＋ 高息債餘額 | B22: US$bn | C22: =各期收支!C84 -> 0 | D22: =各期收支!D84 -> 0 | E22: =各期收支!E84 -> 0 | F22: =各期收支!F84 -> 0 | G22: =各期收支!G84 -> 0
A23: 總債務 | B23: US$bn | C23: =SUM(C18:C22) -> 131.94049 | D23: =SUM(D18:D22) -> 143.97534 | E23: =SUM(E18:E22) -> 138.47534 | F23: =SUM(F18:F22) -> 131.22534 | G23: =SUM(G18:G22) -> 121.47534 | I23: 應等於『各期收支』期末總債務
A24: 淨負債（總債務 − 期末現金） | B24: US$bn | C24: =C23-C13 -> 121.94049 | D24: =D23-D13 -> 133.97534 | E24: =E23-E13 -> 90.028634 | F24: =F23-F13 -> 61.799897 | G24: =G23-G13 -> 38.740948
A25: 股本
A26: 基礎股數（含 ATM 上限、SBC 稀釋） | B26: bn | C26: =損益!C22 -> 3.0889743 | D26: =損益!D22 -> 3.119864 | E26: =損益!E22 -> 3.1510627 | F26: =損益!F22 -> 3.1825733 | G26: =損益!G22 -> 3.214399
A27: ＋ 本期新股 | B27: bn | C27: =各期收支!C80 -> 0 | D27: =各期收支!D80 -> 0 | E27: =各期收支!E80 -> 0 | F27: =各期收支!F80 -> 0 | G27: =各期收支!G80 -> 0
A28: 總股數（期末） | B28: bn | C28: =損益!C23 -> 3.0889743 | D28: =損益!D23 -> 3.119864 | E28: =損益!E23 -> 3.1510627 | F28: =損益!F23 -> 3.1825733 | G28: =損益!G23 -> 3.214399 | I28: ＝基礎股數＋累計新股
A29: 槓桿
A30: 期末 backlog | B30: US$bn | C30: =各期收支!C65 -> 599.26 | D30: =各期收支!D65 -> 485.55 | E30: =各期收支!E65 -> 362.71 | F30: =各期收支!F65 -> 291.2764 | G30: =各期收支!G65 -> 167.5678
A31: 債務上限（債務／backlog × 期末 backlog） | B31: US$bn | C31: =各期收支!C67 -> 225.15394 | D31: =各期收支!D67 -> 324.70215 | E31: =各期收支!E67 -> 402.57538 | F31: =各期收支!F67 -> 411.88709 | G31: =各期收支!G67 -> 393.60726
A32: 總債務 ÷ 期末 backlog | B32: x | C32: =C23/MAX(0.01,C30) -> 0.22017235 | D32: =D23/MAX(0.01,D30) -> 0.2965201 | E32: =E23/MAX(0.01,E30) -> 0.38177976 | F32: =F23/MAX(0.01,F30) -> 0.45051826 | G32: =G23/MAX(0.01,G30) -> 0.72493246 | I32: 高息債不受 backlog 上限約束
A33: 總債務 ÷ EBITDA（年化） | B33: x | C33: =C23/MAX(0.01,損益!C21/輸入與假設!C$41) -> 2.3440049 | D33: =D23/MAX(0.01,損益!D21/輸入與假設!D$41) -> 1.7736296 | E33: =E23/MAX(0.01,損益!E21/輸入與假設!E$41) -> 1.3758947 | F33: =F23/MAX(0.01,損益!F21/輸入與假設!F$41) -> 1.2743817 | G33: =G23/MAX(0.01,損益!G21/輸入與假設!G$41) -> 1.2344827 | I33: FY26 模型期 EBITDA 以半年×2 年化

Sheet 資產負債_租賃承諾
A1: 租賃與承諾 — 季報（2026-08-31）原始揭露
A2: 本頁為硬編碼的申報數字（藍字），支出與資金頁的租金與還本列由此而來
A4: 在帳租賃到期表（未折現）
A5: 項目 | B5: 單位 | C5: 2026 下半 | D5: 2027 | E5: 2028 | F5: 2029 | G5: 2030 | H5: 其後
A6: 營業租賃付款 | B6: US$bn | C6: 3.219 | D6: 4.135 | E6: 4.097 | F6: 4.109 | G6: 4.089 | H6: 28.401
A7: 融資租賃付款 | B7: US$bn | C7: 0.62 | D7: 0.852 | E7: 0.923 | F7: 0.947 | G7: 0.971 | H7: 10.882
A8: 合計（＝支出頁「在帳現金租金」） | C8: =SUM(C6:C7) -> 3.839 | D8: =SUM(D6:D7) -> 4.987 | E8: =SUM(E6:E7) -> 5.02 | F8: =SUM(F6:F7) -> 5.056 | G8: =SUM(G6:G7) -> 5.06 | H8: =SUM(H6:H7) -> 39.283 | I8: 營業租賃負債現值 34.621、融資租賃 9.185；年報加權剩餘租期 12／14 年、折現率 5.7% [Verified]
A10: 債務本金到期表
A11: 項目 | B11: 單位 | C11: 2026 下半 | D11: 2027 | E11: 2028 | F11: 2029 | G11: 2030 | H11: 其後
A12: 本金（＝支出頁「排程還本」） | B12: US$bn | C12: 3.007 | D12: 10.147 | E12: 5.5 | F12: 7.25 | G12: 9.75 | H12: 90.25 | I12: 其他借款到期表（company.json → debt.amortization）；可轉債到期還本依融資分類另計，見『資產負債_既有債務』逐檔表
A13: 合計 | C13: =SUM(C12:H12) -> 125.904
A15: 表外與契約性承諾（未入表）
A16: 項目 | B16: 單位 | C16: 金額 | D16: 時程 | E16: 入表？ | F16: 模型位置
A17: 未起租租賃（未折現） | B17: US$bn | C17: 288 | D17: 季報揭露之已簽約未起租租賃 | E17: 否 | F17: 表外現金租金
A18: 單站按造價計租，上限 | B18: US$bn | C18: 0 | D18: 無此類揭露時為 0 | E18: 否 | F18: 表外現金租金
A19: 未動用信用額度 | B19: US$bn | C19: 10 | D19: company.json → defaults.facility（循環信用額度，未動用） | E19: 否（來源） | F19: 瀑布：未動用額度
A20: 已揭露金額之承諾合計（未起租＋單站上限） | C20: =C17+C18 -> 288
A21: 模型表外租金五期合計 | C21: =SUM(各期收支!C15:G15) -> 59.294118
A22: 模型表外租金尾端（模型期後未付＝總額 − 五期） | C22: =MAX(0,輸入與假設!$C$26-C21) -> 228.70588
A23: 模型路徑合計 ÷ 已承諾（≥0.8 為合理） | C23: =(C21+C22)/C20 -> 1 | I23: 起租排程依季報附註（起租期間與期限）平均分攤；五期＋尾端＝未起租總額

Sheet 損益
A1: 損益（類損益表）— 與資金模型同一組收入
A2: 算力收入、Cash CapEx、利息皆由前面分頁連結而來；改資金假設，此頁會跟著動
A4: 項目 | B4: 單位 | C4: FY27 | D4: FY28 | E4: FY29 | F4: FY30 | G4: FY31 | I4: 公式／來源說明
A5: 損益表
A6: 算力收入 | B6: US$bn | C6: =運營_產能與收入!C25 -> 31.848525 | D6: =運營_產能與收入!D25 -> 82.8501 | E6: =運營_產能與收入!E25 -> 122.2872 | F6: =運營_產能與收入!F25 -> 137.3382 | G6: =運營_產能與收入!G25 -> 140.418 | I6: ＝RPO 轉換＋新簽約
A7: 非算力服務 | B7: US$bn | C7: =輸入與假設!C$50 -> 0 | D7: =輸入與假設!D$50 -> 0 | E7: =輸入與假設!E$50 -> 0 | F7: =輸入與假設!F$50 -> 0 | G7: =輸入與假設!G$50 -> 0
A8: 傳統事業 | B8: US$bn | C8: =輸入與假設!C$81 -> 39.53397 | D8: =輸入與假設!D$81 -> 53.708122 | E8: =輸入與假設!E$81 -> 55.853812 | F8: =輸入與假設!F$81 -> 57.875123 | G8: =輸入與假設!G$81 -> 59.722479 | I8: SaaS、軟體、硬體、服務（v0.1b）
A9: 總營收 | B9: US$bn | C9: =C6+C7+C8 -> 71.382495 | D9: =D6+D7+D8 -> 136.55822 | E9: =E6+E7+E8 -> 178.14101 | F9: =F6+F7+F8 -> 195.21332 | G9: =G6+G7+G8 -> 200.14048
A10: EBITDA 率 | B10: % | C10: =輸入與假設!C$93 -> 0.6519998 | D10: =輸入與假設!D$93 -> 0.62804402 | E10: =輸入與假設!E$93 -> 0.57518339 | F10: =輸入與假設!F$93 -> 0.52111306 | G10: =輸入與假設!G$93 -> 0.46999955
A11: 營業利益（EBIT） | B11: US$bn | C11: =(C6+C7)*輸入與假設!C$93+輸入與假設!C$51+輸入與假設!C$83-輸入與假設!C$136 -> 27.899061 | D11: =(D6+D7)*輸入與假設!D$93+輸入與假設!D$51+輸入與假設!D$83-輸入與假設!D$136 -> 48.450983 | E11: =(E6+E7)*輸入與假設!E$93+輸入與假設!E$51+輸入與假設!E$83-輸入與假設!E$136 -> 58.150745 | F11: =(F6+F7)*輸入與假設!F$93+輸入與假設!F$51+輸入與假設!F$83-輸入與假設!F$136 -> 57.87854 | G11: =(G6+G7)*輸入與假設!G$93+輸入與假設!G$51+輸入與假設!G$83-輸入與假設!G$136 -> 53.308583 | I11: ＝(算力＋服務營收)×EBITDA 率＋其他事業 EBITDA＋傳統事業 EBITDA − 車隊 D&A
A12: 利息（含瀑布新債） | B12: US$bn | C12: =各期收支!C21 -> 4.8729625 | D12: =各期收支!D21 -> 7.4680535 | E12: =各期收支!E21 -> 7.0924288 | F12: =各期收支!F21 -> 6.78635 | G12: =各期收支!G21 -> 6.378245
A13: 預付財務組成利息（非現金） | B13: US$bn | C13: =各期收支!C10 -> 1.543922 | D13: =各期收支!D10 -> 3.583133 | E13: =各期收支!E10 -> 4.423574 | F13: =各期收支!F10 -> 4.7366933 | G13: =各期收支!G10 -> 5.2888366 | I13: 客戶預付的重大財務組成：合約負債以隱含利率累積的利息（v0.1b）
A14: 稅前損益 | B14: US$bn | C14: =C11-C12-C13 -> 21.482176 | D14: =D11-D12-D13 -> 37.399796 | E14: =E11-E12-E13 -> 46.634742 | F14: =F11-F12-F13 -> 46.355497 | G14: =G11-G12-G13 -> 41.641502
A15: NOL 期初餘額 | B15: US$bn | C15: =輸入與假設!$C$193 -> 0 | D15: =C17 -> 0 | E15: =D17 -> 0 | F15: =E17 -> 0 | G15: =F17 -> 0 | I15: 8/31 累積虧損約 0.0
A16: 本期動用 NOL | B16: US$bn | C16: =MIN(C15,MAX(0,C14)*輸入與假設!$C$194) -> 0 | D16: =MIN(D15,MAX(0,D14)*輸入與假設!$C$194) -> 0 | E16: =MIN(E15,MAX(0,E14)*輸入與假設!$C$194) -> 0 | F16: =MIN(F15,MAX(0,F14)*輸入與假設!$C$194) -> 0 | G16: =MIN(G15,MAX(0,G14)*輸入與假設!$C$194) -> 0 | I16: 美國規定：抵扣上限為應稅所得 80%
A17: NOL 期末餘額 | B17: US$bn | C17: =C15-C16+MAX(0,-C14) -> 0 | D17: =D15-D16+MAX(0,-D14) -> 0 | E17: =E15-E16+MAX(0,-E14) -> 0 | F17: =F15-F16+MAX(0,-F14) -> 0 | G17: =G15-G16+MAX(0,-G14) -> 0
A18: 所得稅 | B18: US$bn | C18: =MAX(0,C14-C16)*輸入與假設!$C$180 -> 3.2438086 | D18: =MAX(0,D14-D16)*輸入與假設!$C$180 -> 5.6473692 | E18: =MAX(0,E14-E16)*輸入與假設!$C$180 -> 7.0418461 | F18: =MAX(0,F14-F16)*輸入與假設!$C$180 -> 6.9996801 | G18: =MAX(0,G14-G16)*輸入與假設!$C$180 -> 6.2878668 | I18: 虧損年不認列稅盾（與公司評價備抵一致）
A19: 淨利 | B19: US$bn | C19: =C14-C18 -> 18.238368 | D19: =D14-D18 -> 31.752427 | E19: =E14-E18 -> 39.592896 | F19: =F14-F18 -> 39.355817 | G19: =G14-G18 -> 35.353635
A20: D&A | B20: US$bn | C20: =輸入與假設!C$136 -> 14.317303 | D20: =輸入與假設!D$136 -> 32.724555 | E20: =輸入與假設!E$136 -> 42.493099 | F20: =輸入與假設!F$136 -> 45.093231 | G20: =輸入與假設!G$136 -> 45.093231 | I20: 車隊折舊，見輸入頁
A21: EBITDA | B21: US$bn | C21: =C11+C20 -> 42.216364 | D21: =D11+D20 -> 81.175537 | E21: =E11+E20 -> 100.64384 | F21: =F11+F20 -> 102.97177 | G21: =G11+G20 -> 98.401814
A22: 基礎股數（每年 +SBC 稀釋） | B22: bn | C22: =評價_DCF與目標價!$C$69 -> 3.0889743 | D22: =C22*(1+輸入與假設!$C$210) -> 3.119864 | E22: =D22*(1+輸入與假設!$C$210) -> 3.1510627 | F22: =E22*(1+輸入與假設!$C$210) -> 3.1825733 | G22: =F22*(1+輸入與假設!$C$210) -> 3.214399 | I22: FY27＝評價股數（含價內可轉債轉股，見『評價_DCF與目標價』可轉債區）；之後每年 ×(1＋股數年增)
A23: 股數（含瀑布新股） | B23: bn | C23: =C22+各期收支!C81 -> 3.0889743 | D23: =D22+各期收支!D81 -> 3.119864 | E23: =E22+各期收支!E81 -> 3.1510627 | F23: =F22+各期收支!F81 -> 3.1825733 | G23: =G22+各期收支!G81 -> 3.214399 | I23: ＝基礎股數＋累計瀑布新股
A24: 每股盈餘（EPS，模型期） | B24: US$ | C24: =C19/C23 -> 5.9043443 | D24: =D19/D23 -> 10.177503 | E24: =E19/E23 -> 12.564935 | F24: =F19/F23 -> 12.366036 | G24: =G19/G23 -> 10.998521 | I24: FY27 欄只含第 2–4 季；全年口徑見下方
A26: 損益表（全年口徑；FY27＝1Q 實際＋第 2–4 季模型；與 HTML 損益簡表一致）
A27: 1Q27 實際營收（已實現） | B27: US$bn | C27: =輸入與假設!$C$251 -> 19.345 | D27: =0 -> 0 | E27: =0 -> 0 | F27: =0 -> 0 | G27: =0 -> 0
A28: 全年總營收 | B28: US$bn | C28: =C27+C9 -> 90.727495 | D28: =D27+D9 -> 136.55822 | E28: =E27+E9 -> 178.14101 | F28: =F27+F9 -> 195.21332 | G28: =G27+G9 -> 200.14048 | I28: FY27 可對照指引 ≥90
A29: 營收 YoY | B29: % | C29: =C28/67.357-1 -> 0.3469646 | D29: =D28/C28-1 -> 0.50514706 | E29: =E28/D28-1 -> 0.30450594 | F29: =F28/E28-1 -> 0.09583594 | G29: =G28/F28-1 -> 0.025239858 | I29: FY26 實際 67.357
A30: 全年 GAAP 營業利益 | B30: US$bn | C30: =輸入與假設!$C$252+C11 -> 34.627061 | D30: =D11 -> 48.450983 | E30: =E11 -> 58.150745 | F30: =F11 -> 57.87854 | G30: =G11 -> 53.308583
A31: 營利率 | B31: % | C31: =C30/C28 -> 0.38166006 | D31: =D30/D28 -> 0.35480092 | E31: =E30/E28 -> 0.32643098 | F31: =F30/F28 -> 0.29648868 | G31: =G30/G28 -> 0.26635583
A32: 全年 D&A | B32: US$bn | C32: =輸入與假設!$C$255+C20 -> 17.675303 | D32: =D20 -> 32.724555 | E32: =E20 -> 42.493099 | F32: =F20 -> 45.093231 | G32: =G20 -> 45.093231 | I32: 1Q 實際 3.358
A33: 全年 EBITDA | B33: US$bn | C33: =C30+C32 -> 52.302364 | D33: =D30+D32 -> 81.175537 | E33: =E30+E32 -> 100.64384 | F33: =F30+F32 -> 102.97177 | G33: =G30+G32 -> 98.401814
A34: 全年利息（含瀑布新債） | B34: US$bn | C34: =輸入與假設!$C$249+C12 -> 6.3009625 | D34: =D12 -> 7.4680535 | E34: =E12 -> 7.0924288 | F34: =F12 -> 6.78635 | G34: =G12 -> 6.378245 | I34: FY27 起瀑布新債利息（9%）與新股同時影響 EPS
A35: 全年淨利 | B35: US$bn | C35: =輸入與假設!$C$253+C19 -> 22.998368 | D35: =D19 -> 31.752427 | E35: =E19 -> 39.592896 | F35: =F19 -> 39.355817 | G35: =G19 -> 35.353635
A36: 淨利率 | B36: % | C36: =C35/C28 -> 0.2534884 | D36: =D35/D28 -> 0.23251933 | E36: =E35/E28 -> 0.22225593 | F36: =F35/F28 -> 0.20160416 | G36: =G35/G28 -> 0.1766441
A37: 全年 GAAP EPS | B37: US$ | C37: =輸入與假設!$C$257+C19/C23 -> 7.4643443 | D37: =D19/D23 -> 10.177503 | E37: =E19/E23 -> 12.564935 | F37: =F19/F23 -> 12.366036 | G37: =G19/G23 -> 10.998521 | I37: FY27＝1Q 實際 EPS 1.56＋第 2–4 季淨利÷股數
A38: 全年 EPS（加回 SBC） | B38: US$ | C38: =輸入與假設!$C$258+(C19+輸入與假設!$C$211*輸入與假設!C$41)/C23 -> 8.9588823 | D38: =(D19+輸入與假設!$C$211*輸入與假設!D$41)/D23 -> 11.622438 | E38: =(E19+輸入與假設!$C$211*輸入與假設!E$41)/E23 -> 13.995563 | F38: =(F19+輸入與假設!$C$211*輸入與假設!F$41)/F23 -> 13.7825 | G38: =(G19+輸入與假設!$C$211*輸入與假設!G$41)/G23 -> 12.40096 | I38: ＝(淨利＋SBC)÷股數；NOL 狀態無現金稅，SBC 全額加回

Sheet 評價_DCF與目標價
A1: 評價 — DCF、EV/EBITDA、加權目標價
A2: 營收、營業利益、D&A、EBITDA、股數引用『損益』頁；Cash CapEx 與融資引用『各期收支』頁
A4: 項目 | B4: 單位 | C4: FY27 | D4: FY28 | E4: FY29 | F4: FY30 | G4: FY31 | I4: 公式／來源說明
A5: DCF（無槓桿自由現金流；起點為 2026-08-31）
A6: 現金 CapEx（2026-08-31 之後） | B6: US$bn | C6: =輸入與假設!C$135-各期收支!C8 -> 58.740815 | D6: =輸入與假設!D$135-各期收支!D8 -> 65.117864 | E6: =輸入與假設!E$135-各期收支!E8 -> 23.619596 | F6: =輸入與假設!F$135-各期收支!F8 -> 41.630587 | G6: =輸入與假設!G$135-各期收支!G8 -> 41.630587 | I6: DCF 起點為 8/31，故 FY27 欄只含 2Q–4Q 的建置支出，不含 1Q 已發生的 28.499
A7: 比較基期營收 | B7: US$bn | C7: =67.357 -> 67.357 | D7: =19.345+損益!C9 -> 90.727495 | E7: =損益!D9 -> 136.55822 | F7: =損益!E9 -> 178.14101 | G7: =損益!F9 -> 195.21332 | I7: FY26 實際 67.357；FY28 基期＝1Q 實際 19.345＋FY27 模型期營收
A8: 預付認列（非現金營收，扣除） | B8: US$bn | C8: =各期收支!C11 -> 2.6248383 | D8: =各期收支!D11 -> 7.4626503 | E8: =各期收支!E11 -> 11.035453 | F8: =各期收支!F11 -> 11.292098 | G8: =各期收支!G11 -> 12.764163 | I8: 營收中由合約負債轉入的部分已在預付時收現（預付流入已自現金 CapEx 抵減），UFCF 扣除以免重複（v0.1b）
A9: 營運資金變動 | B9: US$bn | C9: =輸入與假設!$C$195*MAX(0,損益!C9-C7) -> 0.080509896 | D9: =輸入與假設!$C$195*MAX(0,損益!D9-D7) -> 0.91661455 | E9: =輸入與假設!$C$195*MAX(0,損益!E9-E7) -> 0.83165579 | F9: =輸入與假設!$C$195*MAX(0,損益!F9-F7) -> 0.34144622 | G9: =輸入與假設!$C$195*MAX(0,損益!G9-G7) -> 0.098543133 | I9: 營收增量的 2%
A10: 無槓桿 NOL 期初 | B10: US$bn | C10: =輸入與假設!$C$193 -> 0 | D10: =C12 -> 0 | E10: =D12 -> 0 | F10: =E12 -> 0 | G10: =F12 -> 0 | I10: DCF 用無槓桿稅（利息不可抵稅，否則稅盾被計兩次：一次在 UFCF、一次在 WACC）
A11: 本期動用（無槓桿） | B11: US$bn | C11: =MIN(C10,MAX(0,損益!C11)*輸入與假設!$C$194) -> 0 | D11: =MIN(D10,MAX(0,損益!D11)*輸入與假設!$C$194) -> 0 | E11: =MIN(E10,MAX(0,損益!E11)*輸入與假設!$C$194) -> 0 | F11: =MIN(F10,MAX(0,損益!F11)*輸入與假設!$C$194) -> 0 | G11: =MIN(G10,MAX(0,損益!G11)*輸入與假設!$C$194) -> 0
A12: 無槓桿 NOL 期末 | B12: US$bn | C12: =C10-C11+MAX(0,-損益!C11) -> 0 | D12: =D10-D11+MAX(0,-損益!D11) -> 0 | E12: =E10-E11+MAX(0,-損益!E11) -> 0 | F12: =F10-F11+MAX(0,-損益!F11) -> 0 | G12: =G10-G11+MAX(0,-損益!G11) -> 0
A13: 無槓桿所得稅（DCF 用） | B13: US$bn | C13: =MAX(0,損益!C11-C11)*輸入與假設!$C$180 -> 4.2127582 | D13: =MAX(0,損益!D11-D11)*輸入與假設!$C$180 -> 7.3160984 | E13: =MAX(0,損益!E11-E11)*輸入與假設!$C$180 -> 8.7807625 | F13: =MAX(0,損益!F11-F11)*輸入與假設!$C$180 -> 8.7396596 | G13: =MAX(0,損益!G11-G11)*輸入與假設!$C$180 -> 8.0495961 | I13: 與損益表的所得稅不同：此處不扣利息，數字較高，這是 DCF 的正確口徑
A14: UFCF | B14: US$bn | C14: =損益!C11-C13+損益!C20-C6-C9-C8 -> -23.442558 | D14: =損益!D11-D13+損益!D20-D6-D9-D8 -> 0.36231042 | E14: =損益!E11-E13+損益!E20-E6-E9-E8 -> 56.376377 | F14: =損益!F11-F13+損益!F20-F6-F9-F8 -> 40.967981 | G14: =損益!G11-G13+損益!G20-G6-G9-G8 -> 35.858926 | I14: ＝EBIT−無槓桿稅＋D&A−現金 CapEx（已扣客戶預付）−營運資金−預付認列。建置期全為負是正常的
A15: 折現期數 | B15: 年 | C15: =輸入與假設!$C$228 -> 0.75 | D15: =輸入與假設!$D$228 -> 1.75 | E15: =輸入與假設!$E$228 -> 2.75 | F15: =輸入與假設!$F$228 -> 3.75 | G15: =輸入與假設!$G$228 -> 4.75 | I15: 自 2026-08-31 起算；FY27 模型期（第 2–4 季）的現金流平均落在 0.75 年
A16: 折現因子 | C16: =1/(1+輸入與假設!$C$190)^C15 -> 0.91542773 | D16: =1/(1+輸入與假設!$C$190)^D15 -> 0.81368471 | E16: =1/(1+輸入與假設!$C$190)^E15 -> 0.72324967 | F16: =1/(1+輸入與假設!$C$190)^F15 -> 0.64286581 | G16: =1/(1+輸入與假設!$C$190)^G15 -> 0.57141603
A17: UFCF 現值 | B17: US$bn | C17: =C14*C16 -> -21.459968 | D17: =D14*D16 -> 0.29480645 | E17: =E14*E16 -> 40.774196 | F17: =F14*F16 -> 26.336914 | G17: =G14*G16 -> 20.490365
A19: 五期 UFCF 現值合計 | C19: =SUM(C17:G17) -> 66.436314 | I19: 建置期現金流現值
A20: 終值基準 FCF（FY31 UFCF，含汰換 CapEx） | C20: =G14+輸入與假設!G128*(1-各期收支!G7) -> 35.858926 | I20: v0.1c：終值基準＝末期 UFCF（含穩態汰換 CapEx，已扣客戶預付覆蓋）＋加回末期成長型 CapEx（扣預付後；成長由 g 表達，預設情境為 0）；GPU 不是永續資產，終值年須持續再投資
A21: 終值（Gordon） | C21: =IF(C30=1,0,C20*(1+輸入與假設!$C$191)/(輸入與假設!$C$190-輸入與假設!$C$191)) -> 388.62316 | I21: ＝常態化 FCF×(1+g)÷(WACC−g)
A22: 終值現值 | C22: =C21*G16 -> 222.0655
A23: 企業價值 EV | C23: =C19+C22 -> 288.50182
A24: 減：淨負債 | C24: =-評價_DCF與目標價!$C$70 -> -88.827 | I24: ＝評價淨負債（不含可轉債的淨負債＋債務處理可轉債到期本金＋調整項；見下方可轉債區）
A25: 股權價值 | C25: =C23+C24 -> 199.67482
A26: DCF 每股 | C26: =IF(C30=1,0,IF(輸入與假設!$C$213=2,C32,C31)) -> 64.641139 | I26: 採用值：失效時為 0 且權重歸零；否則依「DCF 下限方式」取 0 截斷或選擇權
A27: 終值占 EV 比重 | C27: =C22/C23 -> 0.7697196 | I27: ="超過 "&IF(ROUND(ABS(輸入與假設!$C$237)*100,4)=INT(ROUND(ABS(輸入與假設!$C$237)*100,4)),TEXT(ROUND(ABS(輸入與假設!$C$237)*100,4),"0"),TEXT(ROUND(ABS(輸入與假設!$C$237)*100,4),"0.0"))&"%"&" 表示結論由終值假設決定，不由現金流決定" -> 超過 85% 表示結論由終值假設決定，不由現金流決定
A28: 新股募得現金（現值） | C28: =各期收支!C76/(1+輸入與假設!$C$190)^輸入與假設!$C$229+各期收支!D76/(1+輸入與假設!$C$190)^輸入與假設!$D$229+各期收支!E76/(1+輸入與假設!$C$190)^輸入與假設!$E$229+各期收支!F76/(1+輸入與假設!$C$190)^輸入與假設!$F$229+各期收支!G76/(1+輸入與假設!$C$190)^輸入與假設!$G$229 -> 0 | I28: 期初到位，折現期數 0／0.5／1.5／2.5／3.5 年
A29: 融資後股數（含瀑布新股） | C29: =評價_DCF與目標價!$C$69+各期收支!G81 -> 3.0889743
A30: DCF 失效？（WACC ≤ g 或常態化 FCF ≤ 0） | C30: =IF(OR(輸入與假設!$C$190<=輸入與假設!$C$191,C20<=0),1,0) -> 0 | I30: 1＝失效：DCF 權重歸零、EV/EBITDA 100%。股權為負不算失效
A31: DCF 每股：0 截斷 | C31: =MAX(0,(C25+C28)/C29) -> 64.641139
A32: DCF 每股：選擇權（Merton） | C32: =IF((C23+C28)<=0,0,IF(評價_DCF與目標價!$C$70<=0,(C23+C28),(C23+C28)*NORMSDIST(C33)-評價_DCF與目標價!$C$70*EXP(-輸入與假設!$C$181*輸入與假設!$C$215)*NORMSDIST(C34))/C29) -> 73.010746 | I32: Black-Scholes：S＝企業價值＋新股現值、K＝淨負債
A33: d1 | C33: =IF(OR((C23+C28)<=0,評價_DCF與目標價!$C$70<=0),0,(LN((C23+C28)/評價_DCF與目標價!$C$70)+(輸入與假設!$C$181+輸入與假設!$C$214^2/2)*輸入與假設!$C$215)/(輸入與假設!$C$214*SQRT(輸入與假設!$C$215))) -> 1.8555931
A34: d2 | C34: =C33-輸入與假設!$C$214*SQRT(輸入與假設!$C$215) -> 0.76586839
A36: 倍數法（錨定年度，預設 FY29；折回 2027-08-31）
A37: 錨定年度 | C37: =CHOOSE(輸入與假設!$C$205,"FY28","FY29","FY30","FY31") -> FY29 | I37: 輸入與假設 F 區可改
A38: 錨定年度 EBITDA | C38: =INDEX(損益!$D$21:$G$21,1,輸入與假設!$C$205) -> 100.64384
A39: 錨定年度企業價值（倍數 × EBITDA） | C39: =C45*輸入與假設!$C$196+C44*輸入與假設!$C$204 -> 877.2257 | I39: 分部加總：OCI EBITDA × EV/EBITDA 倍數＋傳統事業 EBITDA × 傳統事業倍數（下方兩列）
A40: 錨定年度末淨負債（總債務 − 現金） | C40: =INDEX(各期收支!$D$86:$G$86,1,輸入與假設!$C$205)-INDEX(各期收支!$D$51:$G$51,1,輸入與假設!$C$205)+評價_DCF與目標價!$C$71 -> 90.028634 | I40: 含瀑布新債；加可轉債分類調整與淨負債調整項（見下方可轉債區）
A41: 錨定年度末股數（含瀑布新股） | C41: =INDEX(損益!$D$23:$G$23,1,輸入與假設!$C$205) -> 3.1510627 | I41: 損益股數：SBC 逐年稀釋＋瀑布新股
A42: 折回 2027-08-31 的折現因子 | C42: =1/(1+輸入與假設!$C$190)^(輸入與假設!$C$205-輸入與假設!$C$225) -> 0.81368471 | I42: 以 WACC 折現 [Assumed]
A43: EV/EBITDA 每股（融資後） | C43: =MAX(0,(C39-C40)/C41)*C42 -> 203.27435 | I43: 以 0 為下限
A44: 錨定年度傳統事業 EBITDA | C44: =INDEX(輸入與假設!$D$83:$G$83,1,輸入與假設!$C$205) -> 30.306278 | I44: × 傳統事業 EV/EBITDA 倍數（軟體同業 NTM 中位數）
A45: 錨定年度 OCI EBITDA（算力＋服務＋其他） | C45: =C38-C44 -> 70.337566 | I45: ＝錨定年度 EBITDA − 傳統事業；× EV/EBITDA 倍數
A47: 加權目標價
A48: DCF 每股（推到目標價時點） | C48: =C26*(1+輸入與假設!$C$190)^輸入與假設!$C$221 -> 72.723859 | I48: ＝DCF 每股 ×（1＋WACC）^（評價日至目標價時點的年數）
A49: DCF 每股 × 有效權重 | C49: =C48*IF(C30=1,0,輸入與假設!$C$206) -> 32.725737
A50: EV/EBITDA（融資後）× 有效權重 | C50: =C43*IF(C30=1,1,1-輸入與假設!$C$206) -> 111.80089
A51: 加權目標價 | C51: =SUM(C49:C50) -> 144.52663 | I51: 期前融資瀑布：缺口先由額度與資產層新債支應，殘差以股權募足；估值不再扣缺口本金
A52: 現價 | C52: =輸入與假設!$C$175 -> 144.77
A53: 潛在空間 | C53: =C51/C52-1 -> -0.0016810932
A55: 可轉債稀釋（若轉換法；第一輪判斷價＝現價，第二輪＝MIN(現價, 第一輪目標價)）
A56: 第一輪：轉股股數 | C56: =SUMPRODUCT(資產負債_既有債務!$D$73:$D$73*資產負債_既有債務!$G$73:$G$73) -> 0.031238286 | I56: 有效轉換價 < 現價的可轉債：原始本金 ÷ 轉換價
A57: 第一輪：評價股數 | C57: =輸入與假設!$C$176+C56 -> 3.0889743
A58: 第一輪：評價淨負債 | C58: =輸入與假設!$C$177+SUMPRODUCT(資產負債_既有債務!$C$73:$C$73*(1-資產負債_既有債務!$G$73:$G$73))+輸入與假設!$C$179 -> 88.827 | I58: ＝不含可轉債的淨負債＋債務處理可轉債到期本金＋調整項
A59: 第一輪：DCF 融資後股數 | C59: =C57+各期收支!G81 -> 3.0889743
A60: 第一輪：d1 | C60: =IF(OR((C23+C28)<=0,C58<=0),0,(LN((C23+C28)/C58)+(輸入與假設!$C$181+輸入與假設!$C$214^2/2)*輸入與假設!$C$215)/(輸入與假設!$C$214*SQRT(輸入與假設!$C$215))) -> 1.8555931
A61: 第一輪：DCF 每股（評價日） | C61: =IF(C30=1,0,IF(輸入與假設!$C$213=2,IF((C23+C28)<=0,0,IF(C58<=0,(C23+C28),(C23+C28)*NORMSDIST(C60)-C58*EXP(-輸入與假設!$C$181*輸入與假設!$C$215)*NORMSDIST(C60-輸入與假設!$C$214*SQRT(輸入與假設!$C$215)))/C59),MAX(0,(C23-C58+C28)/C59))) -> 64.641139 | I61: 與上方 DCF 同算法，只換股數與淨負債
A62: 第一輪：錨定年末淨負債 | C62: =INDEX(各期收支!$D$86:$G$86,1,輸入與假設!$C$205)-INDEX(各期收支!$D$51:$G$51,1,輸入與假設!$C$205)+SUMPRODUCT(資產負債_既有債務!$C$73:$C$73*(資產負債_既有債務!$F$73:$F$73-資產負債_既有債務!$G$73:$G$73))+輸入與假設!$C$179 -> 90.028634 | I62: ＝融資表錨定年末淨負債＋（融資分類為轉股、評價分類為債務的到期本金）＋調整項
A63: 第一輪：錨定年末股數 | C63: =C57*(1+輸入與假設!$C$210)^輸入與假設!$C$205+INDEX(各期收支!$D$81:$G$81,1,輸入與假設!$C$205) -> 3.1510627
A64: 第一輪：EV/EBITDA 每股 | C64: =MAX(0,(C39-C62)/C63)*C42 -> 203.27435
A65: 第一輪：加權目標價 | C65: =C61*(1+輸入與假設!$C$190)^輸入與假設!$C$221*IF(C30=1,0,輸入與假設!$C$206)+C64*IF(C30=1,1,1-輸入與假設!$C$206) -> 144.52663
A66: 第二輪判斷價 | C66: =MIN(輸入與假設!$C$175,C65) -> 144.52663 | I66: ＝MIN(現價, 第一輪加權目標價)：以較保守者判斷是否價內
A67: 第二輪：轉股股數 | C67: =SUMPRODUCT(資產負債_既有債務!$D$73:$D$73*資產負債_既有債務!$H$73:$H$73) -> 0.031238286 | I67: 有效轉換價 < 第二輪判斷價的可轉債
A68: 第二輪：債務處理到期本金 | C68: =SUMPRODUCT(資產負債_既有債務!$C$73:$C$73*(1-資產負債_既有債務!$H$73:$H$73)) -> 0
A69: 評價股數（含可轉債轉股） | C69: =輸入與假設!$C$176+C67 -> 3.0889743 | I69: DCF、損益股數與錨定年末股數的起點
A70: 評價淨負債（含可轉債與調整項） | C70: =輸入與假設!$C$177+C68+輸入與假設!$C$179 -> 88.827 | I70: DCF 減項與 Merton 履約價
A71: 錨定年末淨負債調整（可轉債分類差＋調整項） | C71: =SUMPRODUCT(資產負債_既有債務!$C$73:$C$73*(資產負債_既有債務!$F$73:$F$73-資產負債_既有債務!$H$73:$H$73))+輸入與假設!$C$179 -> 0 | I71: 融資現金流依『融資分類』（判斷價＝股權發行價）；評價依第二輪分類，差額在錨定年末淨負債補回
A72: DCF 權重說明 | C72: =IF(C30=1,"DCF 失效，已以 EV/EBITDA 100% 計。",IF(AND(輸入與假設!$C$213<>2,C87<0),"DCF 為 $0 仍計 "&TEXT(輸入與假設!$C$206,"0%")&" 權重的原因：DCF 沒有失效，而是算出的股權價值為負（每股約 −$"&TEXT(ABS(C87),"0.0")&"），代表自由現金流折現後的企業價值不足以償還淨負債。EV/EBITDA 沒有扣除 GPU 汰換與擴張支出，保留 DCF 權重，是為了讓目標價反映「EBITDA 付不起資本成本」。若不計 DCF，目標價為 $"&TEXT(C43,"0.0")&"（"&CHOOSE(D86+2,"賣出","中立","買進")&"）；"&TEXT(輸入與假設!$C$206,"0%")&"／"&TEXT(1-輸入與假設!$C$206,"0%")&" 為判斷值。","")) | I72: 只在 DCF 被 0 截斷時顯示；DCF 失效時改為一句；DCF 為正時空白（與 HTML 同一字串）
A74: 目標價區間（情境區間、方法區間；評等仍依點位）
A75: 目標價區間｜點位（目前輸入的加權目標價） | C75: =C51 -> 144.52663 | I75: ="評等規則不變：空間 ≥"&IF(ROUND(ABS(輸入與假設!$C$231)*100,4)=INT(ROUND(ABS(輸入與假設!$C$231)*100,4)),TEXT(ROUND(ABS(輸入與假設!$C$231)*100,4),"0"),TEXT(ROUND(ABS(輸入與假設!$C$231)*100,4),"0.0"))&"%"&" 且終值占比 <"&IF(ROUND(ABS(輸入與假設!$C$232)*100,4)=INT(ROUND(ABS(輸入與假設!$C$232)*100,4)),TEXT(ROUND(ABS(輸入與假設!$C$232)*100,4),"0"),TEXT(ROUND(ABS(輸入與假設!$C$232)*100,4),"0.0"))&"%"&"、股權募資 ≤"&IF(輸入與假設!$C$234=INT(輸入與假設!$C$234),TEXT(輸入與假設!$C$234,"0"),TEXT(輸入與假設!$C$234,"0.0"))&" 倍現市值 → 買進；空間 ≤−"&IF(ROUND(ABS(輸入與假設!$C$233)*100,4)=INT(ROUND(ABS(輸入與假設!$C$233)*100,4)),TEXT(ROUND(ABS(輸入與假設!$C$233)*100,4),"0"),TEXT(ROUND(ABS(輸入與假設!$C$233)*100,4),"0.0"))&"%"&"，或股權募資 >"&IF(輸入與假設!$C$234=INT(輸入與假設!$C$234),TEXT(輸入與假設!$C$234,"0"),TEXT(輸入與假設!$C$234,"0.0"))&" 倍且空間 ≤−"&IF(ROUND(ABS(輸入與假設!$C$235)*100,4)=INT(ROUND(ABS(輸入與假設!$C$235)*100,4)),TEXT(ROUND(ABS(輸入與假設!$C$235)*100,4),"0"),TEXT(ROUND(ABS(輸入與假設!$C$235)*100,4),"0.0"))&"%"&" → 賣出；其餘中立" -> 評等規則不變：空間 ≥25% 且終值占比 <90%、股權募資 ≤1.5 倍現市值 → 買進；空間 ≤−15%，或股權募資 >1.5 倍且空間 ≤−8% → 賣出；其餘中立
A76: 目標價區間｜終值占 EV（評等用） | C76: =C22/MAX(ABS(C23),1)*IF(C23=0,1,SIGN(C23)) -> 0.7697196
A77: 目標價區間｜股權募資 ÷ 現市值（評等用） | C77: =SUM(各期收支!C76:G76)/(輸入與假設!$C$175*輸入與假設!$C$176) -> 0
A78: 目標價區間｜點位評等代碼（1＝買進、0＝中立、−1＝賣出） | C78: =IF(AND((C51/MAX(輸入與假設!$C$175,0.01)-1)>=輸入與假設!$C$231,$C$76<輸入與假設!$C$232,$C$77<=輸入與假設!$C$234),1,IF(OR((C51/MAX(輸入與假設!$C$175,0.01)-1)<=輸入與假設!$C$233,AND($C$77>輸入與假設!$C$234,(C51/MAX(輸入與假設!$C$175,0.01)-1)<=輸入與假設!$C$235)),-1,0)) -> 0 | D78: =CHOOSE(C78+2,"賣出","中立","買進") -> 中立
A79: 目標價區間｜賣出門檻價（現價 × (1 − 15%)） | C79: =輸入與假設!$C$175*(1+輸入與假設!$C$233) -> 123.0545
A80: 目標價區間｜保守 OpenAI 相關 60%（加權目標價／評等代碼／距賣出門檻） | C80: =輸入與假設!D264 -> 79.79295 | D80: =輸入與假設!E264 -> -1 | E80: =C80-$C$79 -> -43.26155 | I80: 引用『輸入與假設』底部模擬運算表（情境選擇 1／2／3），保留其餘手動輸入
A81: 目標價區間｜基準 已簽約站點依 Q1 速度（加權目標價／評等代碼／距賣出門檻） | C81: =輸入與假設!D265 -> 144.52663 | D81: =輸入與假設!E265 -> 0 | E81: =C81-$C$79 -> 21.472128
A82: 目標價區間｜積極 依公司時程（加權目標價／評等代碼／距賣出門檻） | C82: =輸入與假設!D266 -> 226.60959 | D82: =輸入與假設!E266 -> 1 | E82: =C82-$C$79 -> 103.55509
A83: 目標價區間｜情境區間（下緣／上緣） | C83: =MIN(C80,C82) -> 79.79295 | D83: =MAX(C80,C82) -> 226.60959
A84: 目標價區間｜方法區間倍數（下端／上端） | C84: =MIN(輸入與假設!$C$208,輸入與假設!$C$209) -> 5 | D84: =MAX(輸入與假設!$C$208,輸入與假設!$C$209) -> 6
A85: 目標價區間｜方法區間（下緣／上緣） | C85: =MIN(C48*IF(C30=1,0,輸入與假設!$C$206)+MAX(0,(C45*C84+C44*輸入與假設!$C$204-C40)/C41)*C42*IF(C30=1,1,1-輸入與假設!$C$206),C48*IF(C30=1,0,輸入與假設!$C$206)+MAX(0,(C45*D84+C44*輸入與假設!$C$204-C40)/C41)*C42*IF(C30=1,1,1-輸入與假設!$C$206)) -> 134.537 | D85: =MAX(C48*IF(C30=1,0,輸入與假設!$C$206)+MAX(0,(C45*C84+C44*輸入與假設!$C$204-C40)/C41)*C42*IF(C30=1,1,1-輸入與假設!$C$206),C48*IF(C30=1,0,輸入與假設!$C$206)+MAX(0,(C45*D84+C44*輸入與假設!$C$204-C40)/C41)*C42*IF(C30=1,1,1-輸入與假設!$C$206)) -> 144.52663 | I85: ＝DCF 採用值 × 有效權重 ＋ EV/EBITDA 腿（倍數換成兩端）× 有效權重
A86: 目標價區間｜100% EV/EBITDA 目標價（價位／評等代碼） | C86: =C43 -> 203.27435 | D86: =IF(AND((C43/MAX(輸入與假設!$C$175,0.01)-1)>=輸入與假設!$C$231,$C$76<輸入與假設!$C$232,$C$77<=輸入與假設!$C$234),1,IF(OR((C43/MAX(輸入與假設!$C$175,0.01)-1)<=輸入與假設!$C$233,AND($C$77>輸入與假設!$C$234,(C43/MAX(輸入與假設!$C$175,0.01)-1)<=輸入與假設!$C$235)),-1,0)) -> 1 | E86: =CHOOSE(D86+2,"賣出","中立","買進") -> 買進
A87: 目標價區間｜未截斷 DCF 每股 | C87: =(C25+C28)/C29 -> 64.641139
A88: 目標價區間｜點位摘要 | C88: ="目標價 $"&TEXT(C51,"0.0")&"（情境區間 $"&TEXT(C83,"0.0")&"–$"&TEXT(D83,"0.0")&"）" -> 目標價 $144.5（情境區間 $79.8–$226.6）
A89: 目標價區間｜方法區間標籤 | C89: ="方法區間（目前情境，"&IF(C84=INT(C84),TEXT(C84,"0"),TEXT(C84,"0.0"))&"–"&IF(D84=INT(D84),TEXT(D84,"0"),TEXT(D84,"0.0"))&"x）" -> 方法區間（目前情境，5–6x）
A90: 目標價區間｜點位位置 | C90: =IF(ABS(輸入與假設!$C$196-D84)<0.000000001,"目前點位位於方法區間上緣（"&IF(D84=INT(D84),TEXT(D84,"0"),TEXT(D84,"0.0"))&"x 為穩態倍數上緣）",IF(ABS(輸入與假設!$C$196-C84)<0.000000001,"目前點位位於方法區間下緣（"&IF(C84=INT(C84),TEXT(C84,"0"),TEXT(C84,"0.0"))&"x）","目前點位"&IF(AND(輸入與假設!$C$196>C84,輸入與假設!$C$196<D84),"位於方法區間內",IF(輸入與假設!$C$196>D84,"高於方法區間上緣","低於方法區間下緣"))&"（目前倍數 "&IF(輸入與假設!$C$196=INT(輸入與假設!$C$196),TEXT(輸入與假設!$C$196,"0"),TEXT(輸入與假設!$C$196,"0.0"))&"x）")) -> 目前點位位於方法區間上緣（6x 為穩態倍數上緣）
A91: 目標價區間｜判斷句 | C91: =IF(D83<輸入與假設!$C$175,"情境區間上緣 $"&TEXT(D83,"0.0")&" 低於現價 $"&TEXT(輸入與假設!$C$175,"0.00")&IF((D80<>-1)+(D81<>-1)+(D82<>-1)>0,"，但"&SUBSTITUTE(TRIM(IF(D80<>-1,"保守","")&" "&IF(D81<>-1,"基準","")&" "&IF(D82<>-1,"積極",""))," ","、")&"情境未達賣出門檻 $"&TEXT($C$79,"0.0"),"：賣出在三個擴張情境下都成立"),"情境區間上緣 $"&TEXT(D83,"0.0")&" 不低於現價 $"&TEXT(輸入與假設!$C$175,"0.00")&"：賣出並非在三個擴張情境下都成立")&"。"&IF(ABS(E80)<輸入與假設!$C$236*輸入與假設!$C$175,"保守情境 $"&TEXT(C80,"0.0")&"，"&IF(E80<0,"距賣出門檻","高於賣出門檻")&" $"&TEXT($C$79,"0.0")&" 僅 $"&TEXT(ABS(E80),"0.0")&"。","")&IF(ABS(E81)<輸入與假設!$C$236*輸入與假設!$C$175,"基準情境 $"&TEXT(C81,"0.0")&"，"&IF(E81<0,"距賣出門檻","高於賣出門檻")&" $"&TEXT($C$79,"0.0")&" 僅 $"&TEXT(ABS(E81),"0.0")&"。","")&IF(ABS(E82)<輸入與假設!$C$236*輸入與假設!$C$175,"積極情境 $"&TEXT(C82,"0.0")&"，"&IF(E82<0,"距賣出門檻","高於賣出門檻")&" $"&TEXT($C$79,"0.0")&" 僅 $"&TEXT(ABS(E82),"0.0")&"。","") -> 情境區間上緣 $226.6 不低於現價 $144.77：賣出並非在三個擴張情境下都成立。
A93: 錨定年度 × 倍數矩陣（每股；以 WACC 折回 2027-08-31）
A94: OCI 倍數 ＼ 錨定（EV/EBITDA 腿） | B94: 倍數 | C94: FY28 | D94: FY29 | E94: FY30 | F94: FY31 | I94: EV/EBITDA 腿＝(OCI EBITDA × 倍數＋傳統事業 EBITDA × 傳統事業倍數 − 錨定年末淨負債) ÷ 錨定年末股數 × 折現因子；加權＝DCF 採用值 × 有效權重 ＋ 腿 × 有效權重。綠底＝不低於現價
A95: 錨定×倍數｜EV/EBITDA 腿｜3.4x | B95: 3.4 | C95: =MAX(0,((INDEX(損益!$D$21:$G$21,1,1)-INDEX(輸入與假設!$D$83:$G$83,1,1))*$B95+INDEX(輸入與假設!$D$83:$G$83,1,1)*輸入與假設!$C$204-(INDEX(各期收支!$D$86:$G$86,1,1)-INDEX(各期收支!$D$51:$G$51,1,1)+評價_DCF與目標價!$C$71))/INDEX(損益!$D$23:$G$23,1,1))/(1+輸入與假設!$C$190)^(1-輸入與假設!$C$225) -> 141.03244 | D95: =MAX(0,((INDEX(損益!$D$21:$G$21,1,2)-INDEX(輸入與假設!$D$83:$G$83,1,2))*$B95+INDEX(輸入與假設!$D$83:$G$83,1,2)*輸入與假設!$C$204-(INDEX(各期收支!$D$86:$G$86,1,2)-INDEX(各期收支!$D$51:$G$51,1,2)+評價_DCF與目標價!$C$71))/INDEX(損益!$D$23:$G$23,1,2))/(1+輸入與假設!$C$190)^(2-輸入與假設!$C$225) -> 156.05067 | E95: =MAX(0,((INDEX(損益!$D$21:$G$21,1,3)-INDEX(輸入與假設!$D$83:$G$83,1,3))*$B95+INDEX(輸入與假設!$D$83:$G$83,1,3)*輸入與假設!$C$204-(INDEX(各期收支!$D$86:$G$86,1,3)-INDEX(各期收支!$D$51:$G$51,1,3)+評價_DCF與目標價!$C$71))/INDEX(損益!$D$23:$G$23,1,3))/(1+輸入與假設!$C$190)^(3-輸入與假設!$C$225) -> 148.44343 | F95: =MAX(0,((INDEX(損益!$D$21:$G$21,1,4)-INDEX(輸入與假設!$D$83:$G$83,1,4))*$B95+INDEX(輸入與假設!$D$83:$G$83,1,4)*輸入與假設!$C$204-(INDEX(各期收支!$D$86:$G$86,1,4)-INDEX(各期收支!$D$51:$G$51,1,4)+評價_DCF與目標價!$C$71))/INDEX(損益!$D$23:$G$23,1,4))/(1+輸入與假設!$C$190)^(4-輸入與假設!$C$225) -> 134.47231
A96: 錨定×倍數｜EV/EBITDA 腿｜4.5x | B96: 4.5 | C96: =MAX(0,((INDEX(損益!$D$21:$G$21,1,1)-INDEX(輸入與假設!$D$83:$G$83,1,1))*$B96+INDEX(輸入與假設!$D$83:$G$83,1,1)*輸入與假設!$C$204-(INDEX(各期收支!$D$86:$G$86,1,1)-INDEX(各期收支!$D$51:$G$51,1,1)+評價_DCF與目標價!$C$71))/INDEX(損益!$D$23:$G$23,1,1))/(1+輸入與假設!$C$190)^(1-輸入與假設!$C$225) -> 157.82683 | D96: =MAX(0,((INDEX(損益!$D$21:$G$21,1,2)-INDEX(輸入與假設!$D$83:$G$83,1,2))*$B96+INDEX(輸入與假設!$D$83:$G$83,1,2)*輸入與假設!$C$204-(INDEX(各期收支!$D$86:$G$86,1,2)-INDEX(各期收支!$D$51:$G$51,1,2)+評價_DCF與目標價!$C$71))/INDEX(損益!$D$23:$G$23,1,2))/(1+輸入與假設!$C$190)^(2-輸入與假設!$C$225) -> 176.02992 | E96: =MAX(0,((INDEX(損益!$D$21:$G$21,1,3)-INDEX(輸入與假設!$D$83:$G$83,1,3))*$B96+INDEX(輸入與假設!$D$83:$G$83,1,3)*輸入與假設!$C$204-(INDEX(各期收支!$D$86:$G$86,1,3)-INDEX(各期收支!$D$51:$G$51,1,3)+評價_DCF與目標價!$C$71))/INDEX(損益!$D$23:$G$23,1,3))/(1+輸入與假設!$C$190)^(3-輸入與假設!$C$225) -> 166.33406 | F96: =MAX(0,((INDEX(損益!$D$21:$G$21,1,4)-INDEX(輸入與假設!$D$83:$G$83,1,4))*$B96+INDEX(輸入與假設!$D$83:$G$83,1,4)*輸入與假設!$C$204-(INDEX(各期收支!$D$86:$G$86,1,4)-INDEX(各期收支!$D$51:$G$51,1,4)+評價_DCF與目標價!$C$71))/INDEX(損益!$D$23:$G$23,1,4))/(1+輸入與假設!$C$190)^(4-輸入與假設!$C$225) -> 148.9912
A97: 錨定×倍數｜EV/EBITDA 腿｜5.0x | B97: 5 | C97: =MAX(0,((INDEX(損益!$D$21:$G$21,1,1)-INDEX(輸入與假設!$D$83:$G$83,1,1))*$B97+INDEX(輸入與假設!$D$83:$G$83,1,1)*輸入與假設!$C$204-(INDEX(各期收支!$D$86:$G$86,1,1)-INDEX(各期收支!$D$51:$G$51,1,1)+評價_DCF與目標價!$C$71))/INDEX(損益!$D$23:$G$23,1,1))/(1+輸入與假設!$C$190)^(1-輸入與假設!$C$225) -> 165.46064 | D97: =MAX(0,((INDEX(損益!$D$21:$G$21,1,2)-INDEX(輸入與假設!$D$83:$G$83,1,2))*$B97+INDEX(輸入與假設!$D$83:$G$83,1,2)*輸入與假設!$C$204-(INDEX(各期收支!$D$86:$G$86,1,2)-INDEX(各期收支!$D$51:$G$51,1,2)+評價_DCF與目標價!$C$71))/INDEX(損益!$D$23:$G$23,1,2))/(1+輸入與假設!$C$190)^(2-輸入與假設!$C$225) -> 185.1114 | E97: =MAX(0,((INDEX(損益!$D$21:$G$21,1,3)-INDEX(輸入與假設!$D$83:$G$83,1,3))*$B97+INDEX(輸入與假設!$D$83:$G$83,1,3)*輸入與假設!$C$204-(INDEX(各期收支!$D$86:$G$86,1,3)-INDEX(各期收支!$D$51:$G$51,1,3)+評價_DCF與目標價!$C$71))/INDEX(損益!$D$23:$G$23,1,3))/(1+輸入與假設!$C$190)^(3-輸入與假設!$C$225) -> 174.46617 | F97: =MAX(0,((INDEX(損益!$D$21:$G$21,1,4)-INDEX(輸入與假設!$D$83:$G$83,1,4))*$B97+INDEX(輸入與假設!$D$83:$G$83,1,4)*輸入與假設!$C$204-(INDEX(各期收支!$D$86:$G$86,1,4)-INDEX(各期收支!$D$51:$G$51,1,4)+評價_DCF與目標價!$C$71))/INDEX(損益!$D$23:$G$23,1,4))/(1+輸入與假設!$C$190)^(4-輸入與假設!$C$225) -> 155.59069
A98: 錨定×倍數｜EV/EBITDA 腿｜6.0x | B98: 6 | C98: =MAX(0,((INDEX(損益!$D$21:$G$21,1,1)-INDEX(輸入與假設!$D$83:$G$83,1,1))*$B98+INDEX(輸入與假設!$D$83:$G$83,1,1)*輸入與假設!$C$204-(INDEX(各期收支!$D$86:$G$86,1,1)-INDEX(各期收支!$D$51:$G$51,1,1)+評價_DCF與目標價!$C$71))/INDEX(損益!$D$23:$G$23,1,1))/(1+輸入與假設!$C$190)^(1-輸入與假設!$C$225) -> 180.72827 | D98: =MAX(0,((INDEX(損益!$D$21:$G$21,1,2)-INDEX(輸入與假設!$D$83:$G$83,1,2))*$B98+INDEX(輸入與假設!$D$83:$G$83,1,2)*輸入與假設!$C$204-(INDEX(各期收支!$D$86:$G$86,1,2)-INDEX(各期收支!$D$51:$G$51,1,2)+評價_DCF與目標價!$C$71))/INDEX(損益!$D$23:$G$23,1,2))/(1+輸入與假設!$C$190)^(2-輸入與假設!$C$225) -> 203.27435 | E98: =MAX(0,((INDEX(損益!$D$21:$G$21,1,3)-INDEX(輸入與假設!$D$83:$G$83,1,3))*$B98+INDEX(輸入與假設!$D$83:$G$83,1,3)*輸入與假設!$C$204-(INDEX(各期收支!$D$86:$G$86,1,3)-INDEX(各期收支!$D$51:$G$51,1,3)+評價_DCF與目標價!$C$71))/INDEX(損益!$D$23:$G$23,1,3))/(1+輸入與假設!$C$190)^(3-輸入與假設!$C$225) -> 190.73039 | F98: =MAX(0,((INDEX(損益!$D$21:$G$21,1,4)-INDEX(輸入與假設!$D$83:$G$83,1,4))*$B98+INDEX(輸入與假設!$D$83:$G$83,1,4)*輸入與假設!$C$204-(INDEX(各期收支!$D$86:$G$86,1,4)-INDEX(各期收支!$D$51:$G$51,1,4)+評價_DCF與目標價!$C$71))/INDEX(損益!$D$23:$G$23,1,4))/(1+輸入與假設!$C$190)^(4-輸入與假設!$C$225) -> 168.78969
A99: 錨定×倍數｜EV/EBITDA 腿｜7.0x | B99: 7 | C99: =MAX(0,((INDEX(損益!$D$21:$G$21,1,1)-INDEX(輸入與假設!$D$83:$G$83,1,1))*$B99+INDEX(輸入與假設!$D$83:$G$83,1,1)*輸入與假設!$C$204-(INDEX(各期收支!$D$86:$G$86,1,1)-INDEX(各期收支!$D$51:$G$51,1,1)+評價_DCF與目標價!$C$71))/INDEX(損益!$D$23:$G$23,1,1))/(1+輸入與假設!$C$190)^(1-輸入與假設!$C$225) -> 195.99589 | D99: =MAX(0,((INDEX(損益!$D$21:$G$21,1,2)-INDEX(輸入與假設!$D$83:$G$83,1,2))*$B99+INDEX(輸入與假設!$D$83:$G$83,1,2)*輸入與假設!$C$204-(INDEX(各期收支!$D$86:$G$86,1,2)-INDEX(各期收支!$D$51:$G$51,1,2)+評價_DCF與目標價!$C$71))/INDEX(損益!$D$23:$G$23,1,2))/(1+輸入與假設!$C$190)^(2-輸入與假設!$C$225) -> 221.4373 | E99: =MAX(0,((INDEX(損益!$D$21:$G$21,1,3)-INDEX(輸入與假設!$D$83:$G$83,1,3))*$B99+INDEX(輸入與假設!$D$83:$G$83,1,3)*輸入與假設!$C$204-(INDEX(各期收支!$D$86:$G$86,1,3)-INDEX(各期收支!$D$51:$G$51,1,3)+評價_DCF與目標價!$C$71))/INDEX(損益!$D$23:$G$23,1,3))/(1+輸入與假設!$C$190)^(3-輸入與假設!$C$225) -> 206.9946 | F99: =MAX(0,((INDEX(損益!$D$21:$G$21,1,4)-INDEX(輸入與假設!$D$83:$G$83,1,4))*$B99+INDEX(輸入與假設!$D$83:$G$83,1,4)*輸入與假設!$C$204-(INDEX(各期收支!$D$86:$G$86,1,4)-INDEX(各期收支!$D$51:$G$51,1,4)+評價_DCF與目標價!$C$71))/INDEX(損益!$D$23:$G$23,1,4))/(1+輸入與假設!$C$190)^(4-輸入與假設!$C$225) -> 181.98868
A101: OCI 倍數 ＼ 錨定（加權目標價） | B101: 倍數 | C101: FY28 | D101: FY29 | E101: FY30 | F101: FY31
A102: 錨定×倍數｜加權目標價｜3.4x | B102: 3.4 | C102: =C48*IF(C30=1,0,輸入與假設!$C$206)+C95*IF(C30=1,1,1-輸入與假設!$C$206) -> 110.29358 | D102: =C48*IF(C30=1,0,輸入與假設!$C$206)+D95*IF(C30=1,1,1-輸入與假設!$C$206) -> 118.55361 | E102: =C48*IF(C30=1,0,輸入與假設!$C$206)+E95*IF(C30=1,1,1-輸入與假設!$C$206) -> 114.36962 | F102: =C48*IF(C30=1,0,輸入與假設!$C$206)+F95*IF(C30=1,1,1-輸入與假設!$C$206) -> 106.68551
A103: 錨定×倍數｜加權目標價｜4.5x | B103: 4.5 | C103: =C48*IF(C30=1,0,輸入與假設!$C$206)+C96*IF(C30=1,1,1-輸入與假設!$C$206) -> 119.53049 | D103: =C48*IF(C30=1,0,輸入與假設!$C$206)+D96*IF(C30=1,1,1-輸入與假設!$C$206) -> 129.54219 | E103: =C48*IF(C30=1,0,輸入與假設!$C$206)+E96*IF(C30=1,1,1-輸入與假設!$C$206) -> 124.20947 | F103: =C48*IF(C30=1,0,輸入與假設!$C$206)+F96*IF(C30=1,1,1-輸入與假設!$C$206) -> 114.6709
A104: 錨定×倍數｜加權目標價｜5.0x | B104: 5 | C104: =C48*IF(C30=1,0,輸入與假設!$C$206)+C97*IF(C30=1,1,1-輸入與假設!$C$206) -> 123.72909 | D104: =C48*IF(C30=1,0,輸入與假設!$C$206)+D97*IF(C30=1,1,1-輸入與假設!$C$206) -> 134.537 | E104: =C48*IF(C30=1,0,輸入與假設!$C$206)+E97*IF(C30=1,1,1-輸入與假設!$C$206) -> 128.68213 | F104: =C48*IF(C30=1,0,輸入與假設!$C$206)+F97*IF(C30=1,1,1-輸入與假設!$C$206) -> 118.30062
A105: 錨定×倍數｜加權目標價｜6.0x | B105: 6 | C105: =C48*IF(C30=1,0,輸入與假設!$C$206)+C98*IF(C30=1,1,1-輸入與假設!$C$206) -> 132.12628 | D105: =C48*IF(C30=1,0,輸入與假設!$C$206)+D98*IF(C30=1,1,1-輸入與假設!$C$206) -> 144.52663 | E105: =C48*IF(C30=1,0,輸入與假設!$C$206)+E98*IF(C30=1,1,1-輸入與假設!$C$206) -> 137.62745 | F105: =C48*IF(C30=1,0,輸入與假設!$C$206)+F98*IF(C30=1,1,1-輸入與假設!$C$206) -> 125.56006
A106: 錨定×倍數｜加權目標價｜7.0x | B106: 7 | C106: =C48*IF(C30=1,0,輸入與假設!$C$206)+C99*IF(C30=1,1,1-輸入與假設!$C$206) -> 140.52348 | D106: =C48*IF(C30=1,0,輸入與假設!$C$206)+D99*IF(C30=1,1,1-輸入與假設!$C$206) -> 154.51625 | E106: =C48*IF(C30=1,0,輸入與假設!$C$206)+E99*IF(C30=1,1,1-輸入與假設!$C$206) -> 146.57277 | F106: =C48*IF(C30=1,0,輸入與假設!$C$206)+F99*IF(C30=1,1,1-輸入與假設!$C$206) -> 132.81951

Sheet 評價_反向DCF
A1: 反向 DCF — 現價隱含什麼樣的收入與成本
A2: 不是問「值多少」，而是問「要值現價，營運要長什麼樣」。Excel 以『目標搜尋』反解；下方另附 HTML 即時計算結果的快照（v4.0 預設輸入）
A4: 即時：目前 DCF 與現價的差距
A5: 現價 | B5: =輸入與假設!$C$175 -> 144.77
A6: 目前 DCF 每股（依下限方式） | B6: =評價_DCF與目標價!C26 -> 64.641139
A7: 差距（DCF − 現價）＝目標搜尋的『設定儲存格』 | B7: =B6-B5 -> -80.128861
A8: 目前每 MW 年收入倍數／建置成本倍數 | B8: =輸入與假設!$C$39 -> 1 | C8: =輸入與假設!$C$107 -> 1
A10: 操作：用『目標搜尋』反解（資料 → 模擬分析 → 目標搜尋）
A11: ① 設定儲存格：本頁 B7；目標值：0
A12: ② 變數儲存格（擇一）：輸入與假設 B 區『每 MW 年收入倍數』→ 市價隱含單價；或 D 區『每 MW 建置成本倍數』→ 市價隱含建置成本；或 C 區『穩態 EBITDA 率』
A13: ③ 解完請記下結果，再把倍數改回 100%（或按 Ctrl+Z）。DCF 以 0 截斷時，負值區域斜率為 0，請從 100% 以上開始搜尋
A14: ④ 組合分析：先把 D 區建置成本倍數與 C 區穩態 EBITDA 率設為想測的值，再對『每 MW 年收入倍數』做目標搜尋，即得下方矩陣中的一格
A16: 快照：單一槓桿（HTML v4.0 預設輸入，DCF 0 截斷）
A17: 單一槓桿（其他不變） | B17: 目前 | C17: 市價隱含 | D17: 變動 | G17: 對照
A18: FY31 每 MW 年收入（US$m） | B18: 17.4 | C18: 23.7781 | D18: 0.3666 | G18: Oracle 對照：OCI 年化 ÷ 新增 MW 14.4、OpenAI 合約隱含 13.3（MW 口徑不明）
A19: 每 MW 建置成本（US$m） | B19: 37.59 | C19: 16.3658 | D19: -0.5646 | G19: FY27 指引 90–95 ÷ 估計新增 MW-IT 約 2,800 ≈ $32–34m（含客戶自帶硬體效果）
A20: 穩態 EBITDA 率（FY31） | B20: 0.47 | C20: 0.7407 | D20: 0.2707 | G20: OCI（算力）EBITDA 率；傳統事業 EBITDA 率固定不動。可觀察 neocloud 區間 IREN 約 35%、CRWV 約 59%（變動為百分點）
A21: （對照）加權目標價＝現價所需每 MW 年收入 | B21: 17.4 | C21: 17.4201 | D21: 0.0012 | G21: 含 EV/EBITDA 腿（FY29 錨定）；非純反向 DCF
A23: 快照：收入與成本的綜合影響——要值現價，FY31 每 MW 年收入需要多少（US$m）
A24: 建置成本 ＼ 穩態 EBITDA 率 | B24: 0.35 | C24: 0.47 | D24: 0.59 | E24: 0.7 | I24: 矩陣保留 OCI EBITDA 率維度：傳統事業（約 54% EBITDA 率、軟體同業倍數）不隨此表變動，表內只測算力業務的單位經濟
A25: $26.3m（-30%） | B25: 24.16 | C25: 20.23 | D25: 17.41 | E25: 15.43
A26: $30.1m（-20%） | B26: 25.44 | C26: 21.3 | D26: 18.33 | E26: 16.24
A27: $33.8m（-10%） | B27: 26.85 | C27: 22.49 | D27: 19.34 | E27: 17.15
A28: $37.6m（目前） | B28: 28.39 | C28: 23.78 | D28: 20.45 | E28: 18.13
A29: $41.3m（+10%） | B29: 29.93 | C29: 25.07 | D29: 21.56 | E29: 19.11
A30: 快照為靜態數值（HTML 以同一引擎即時計算）；改變輸入後請以目標搜尋重算，或參考 HTML『評價 → 反向 DCF』

Sheet 評價_可比公司
A1: 可比公司 — 以 EV/Sales 為主（市值：2026-09-21 收盤）
A2: EV＝市值＋（有息負債−非受限現金）；含租賃＝EV＋營業租賃負債。EV/EBITDA 僅供參考（GAAP EBITDA 為負者顯示 n/m）。此表不進入目標價。與 HTML Comps 分頁同一組數字
A4: 公司 | B4: 市值 | C4: 淨負債 | D4: EV | E4: TTM 營收 | F4: EV/Sales（TTM） | G4: 含租賃 EV/Sales | H4: TTM EBITDA | I4: EV/EBITDA | J4: 資料期 | K4: 備註
A5: CRWV CoreWeave | B5: 49.11 | C5: 46.03 | D5: =B5+C5 -> 95.14 | E5: 7.59 | F5: =D5/E5 -> 12.534914 | G5: =(D5+16.54)/E5 -> 14.714097 | H5: =-0.231+3.991 -> 3.76 | I5: =IF(H5>0,D5/H5,"n/m") -> 25.303191 | J5: TTM 至 Q2（6/30，10-Q）；市值與 EV 2026-10-07 | K5: 營業租賃負債 16.54；GAAP 營業損益 -0.231＋D&A 3.991。CRWV 市值與 EV 2026-10-07；TTM 至 Q2；租賃負債 16.54
A6: NBIS Nebius | B6: 68.49 | C6: 2.15 | D6: =B6+C6 -> 70.64 | E6: 1.36 | F6: =D6/E6 -> 51.941176 | G6: =(D6+1.6253)/E6 -> 53.13625 | H6: =-0.612+0.418 -> -0.194 | I6: =IF(H6>0,D6/H6,"n/m") -> n/m | J6: 營收 TTM 至 Q2；營業損益與 D&A 為 FY2025（20-F）；市值與 EV 2026-10-06 | K6: 營業租賃負債 1.6253；GAAP 營業損益 -0.612＋D&A 0.418。NBIS 市值與 EV 2026-10-06；EBITDA 用 FY2025
A7: IREN | B7: 18.61 | C7: 1.7 | D7: =B7+C7 -> 20.31 | E7: 0.707 | F7: =D7/E7 -> 28.727016 | G7: =(D7+0.003)/E7 -> 28.731259 | H7: =-1.047+0.418 -> -0.629 | I7: =IF(H7>0,D7/H7,"n/m") -> n/m | J7: FY26 10-K（6/30）；未更新，日期 2026-09-21 | K7: 營業租賃負債 0.003；GAAP 營業損益 -1.047＋D&A 0.418。自有電廠、營業租賃負債僅 0.003bn；FY26 合約 ARR 4.0bn
A8: APLD Applied Digital | B8: 8.22 | C8: 3.37 | D8: =B8+C8 -> 11.59 | E8: 0.6113 | F8: =D8/E8 -> 18.959594 | G8: =(D8+0.066)/E8 -> 19.067561 | H8: =-0.236+0.067 -> -0.169 | I8: =IF(H8>0,D8/H8,"n/m") -> n/m | J8: FY26 10-K（5/31）；未更新，日期 2026-09-21 | K8: 營業租賃負債 0.066；GAAP 營業損益 -0.236＋D&A 0.067。租約多未起租，營收尚未反映約 36bn 合約
A9: CORZ Core Scientific | B9: 5.9 | C9: 2.53 | D9: =B9+C9 -> 8.43 | E9: 0.4403 | F9: =D9/E9 -> 19.146037 | G9: =(D9+0.109)/E9 -> 19.393595 | H9: =-0.561+0.063 -> -0.498 | I9: =IF(H9>0,D9/H9,"n/m") -> n/m | J9: TTM 至 Q2（6/30）；未更新，日期 2026-09-21 | K9: 營業租賃負債 0.109；GAAP 營業損益 -0.561＋D&A 0.063。託管轉型期
A10: 同業中位數 | F10: =MEDIAN(F5:F9) -> 19.146037 | G10: =MEDIAN(G5:G9) -> 19.393595
A11: ORCL（TTM 至 Q1 2027） | B11: 437.75 | C11: =輸入與假設!$C$177+SUMPRODUCT(資產負債_既有債務!$C$73:$C$73*(1-資產負債_既有債務!$H$69:$H$69))+輸入與假設!$C$179 -> 88.827 | D11: =B11+C11 -> 526.577 | E11: 71.777 | F11: =D11/E11 -> 7.3362916 | G11: =(D11+34.621)/E11 -> 7.8186327 | H11: =23.056+10.881 -> 33.937 | I11: =IF(H11>0,D11/H11,"n/m") -> 15.51631 | J11: TTM 至 Q1 2027 | K11: EV 用 2026-09-21 市值（基本股）與評價日淨負債（可轉債全數以到期本金計入）；含租賃再加營業租賃負債 34.621
A12: ORCL 模型 FY28E | B12: =輸入與假設!$C$175*評價_DCF與目標價!$C$69 -> 447.19081 | C12: =評價_DCF與目標價!$C$70 -> 88.827 | D12: =B12+C12 -> 536.01781 | E12: =損益!D9 -> 136.55822 | F12: =D12/E12 -> 3.9251961 | G12: =(D12+34.621)/E12 -> 4.1787217 | H12: =損益!D21 -> 81.175537 | I12: =D12/H12 -> 6.6031938 | K12: 市值用評價股數（含價內可轉債轉股）、淨負債用評價淨負債；分母為模型 FY28 營收
A14: 讀法：ORCL 為整體公司（傳統軟體＋OCI），倍數不可直接與純 AI 基礎設施同業比較；
A15: CRWV 以租約取得機房，加入營業租賃負債後倍數上升；ORCL 同樣以租賃為主（未起租承諾 288B 尚未入表）。
A16: 前瞻：見下方 ORCL 模型列。此表為市場比較用，不進入目標價。

Sheet 檢查_連動
A1: 連動檢查 — 恆等式與口徑
A3: 檢查項目 | B3: 實際值 | C3: 標準 | D3: 結果 | E3: 說明
A4: RPO 桶權重合計 | B4: =SUM(輸入與假設!C42:G42) -> 0.7975 | C4: =輸入與假設!$C$34 -> 0.7975 | D4: =IF(ABS(B4-C4)<0.0001,"通過","不一致") -> 通過 | E4: 季報桶線性分攤後應為 79.75%
A5: 現金橋差異 | B5: =各期收支!C100 -> 0 | C5: =0 -> 0 | D5: =IF(ABS(B5)<0.01,"通過","不一致") -> 通過 | E5: 期初＋營運缺口＋股權＋額度−還本 ＝ 期末
A6: Billable ≤ Accepted（FY31） | B6: =運營_產能與收入!G9-運營_產能與收入!G10 -> 708 | C6: ≥0 | D6: =IF(B6>=0,"通過","不一致") -> 通過 | E6: 引擎已以 MIN 截斷；此列驗證截斷有效
A7: FY27 CapEx 認列 vs 指引 | B7: =各期收支!C104 -> 106.09585 | C7: 90–95 | D7: =IF(AND(B7>=90,B7<=95),"通過","觀察") -> 觀察 | E7: 1Q 實際認列 28.499＋2Q–4Q 模型；全年指引 90–95（法說會轉述）
A8: FY27 營收 vs 指引 | B8: =各期收支!C103 -> 90.727495 | C8: ≥90 | D8: =IF(B8>=90,"通過","觀察") -> 通過 | E8: 1Q 實際 19.345＋2Q–4Q 模型（算力＋非算力服務）
A9: CapEx 強度（模型期合計） | B9: =SUM(各期收支!C6:G6)/((運營_產能與收入!G9-輸入與假設!$C$36)/1000)/1000*1000 -> 47.077221 | C9: $28–51m/MW | D9: =IF(AND(B9>=28,B9<=51),"通過","觀察") -> 通過 | E9: Tokenomics IF_CapexTotal 低／高成本情境（GB300 38.8–67.1 US$m/MW-IT）
A10: 表外租金路徑 ÷ 已承諾 | B10: =資產負債_租賃承諾!C23 -> 1 | C10: ≥0.8x | D10: =IF(B10>=0.8,"通過","不一致") -> 通過 | E10: 表外租金路徑對已簽約未起租租賃
A11: FY27 利息（1Q 實際＋2Q–4Q） | B11: =各期收支!C105 -> 6.3009625 | C11: ≥1.4 | D11: =IF(B11>=1.4,"通過","觀察") -> 通過 | E11: ="1Q 實際 1.428＋2Q–4Q 模型 "&TEXT(各期收支!C17,"0.0")&"；公司未提供季度利息指引（不適用）" -> 1Q 實際 1.428＋2Q–4Q 模型 4.5；公司未提供季度利息指引（不適用）
A12: FY29 起收入是否依賴未簽約 | B12: =SUM(運營_產能與收入!E23:G23)/SUM(運營_產能與收入!E25:G25) -> 0.12375207 | C12: <50% 較穩健 | D12: =IF(B12<0.5,"通過","觀察") -> 通過 | E12: FY29–FY31 超出期初 RPO 的收入 ÷ 同期總算力收入（MW 驅動下為未簽約產能的比重）
A13: 損益營收＝資金營收 | B13: =損益!D6-運營_產能與收入!D25 -> 0 | C13: =0 -> 0 | D13: =IF(ABS(B13)<0.001,"通過","不一致") -> 通過 | E13: FY28 損益算力收入 − 產能頁 isRev。兩邊必須同一組數字
A14: 終值占 EV 比重 | B14: =評價_DCF與目標價!C27 -> 0.7697196 | C14: ="<"&IF(ROUND(ABS(輸入與假設!$C$237)*100,4)=INT(ROUND(ABS(輸入與假設!$C$237)*100,4)),TEXT(ROUND(ABS(輸入與假設!$C$237)*100,4),"0"),TEXT(ROUND(ABS(輸入與假設!$C$237)*100,4),"0.0"))&"%" -> <85% | D14: =IF(B14<輸入與假設!$C$237,"通過","觀察") -> 通過 | E14: 過高表示結論由終值假設決定
A15: EBITDA 單一來源（FY28 算力＋服務 EBITDA÷營收 − 輸入 EBITDA 率） | B15: =(損益!D21-輸入與假設!D83-輸入與假設!D51)/(損益!D6+損益!D7)-輸入與假設!D93 -> 0 | C15: =0 -> 0 | D15: =IF(ABS(B15)<0.0001,"通過","不一致") -> 通過 | E15: 損益與資金引用同一列 EBITDA 率
A16: 現金 EBITDA ＋ 信用調整 − 損益 EBITDA（FY28） | B16: =(運營_產能與收入!D39+運營_產能與收入!D40+輸入與假設!D94+輸入與假設!D51+輸入與假設!D83-各期收支!D16)+(運營_產能與收入!D34+運營_產能與收入!D23*輸入與假設!D48*(1-輸入與假設!D49))*運營_產能與收入!D38-損益!D21 -> 0 | C16: =0 -> 0 | D16: =IF(ABS(B16)<0.001,"通過","不一致") -> 通過 | E16: 現金 EBITDA＝RPO 現金＋新簽約現金＋服務現金−租金；信用調整＝信用損失×EBITDAR 率
A17: DCF 有效性（1＝失效） | B17: =評價_DCF與目標價!C30 -> 0 | C17: 0 | D17: =IF(B17=0,"通過","觀察") -> 通過 | E17: 失效只定義為 WACC ≤ g 或常態化 FCF ≤ 0；股權為負不算失效
A18: 期末現金 ≥ 最低現金（期前融資） | B18: =MIN(各期收支!C51:G51) -> 10 | C18: ≥10.0 | D18: =IF(B18>=9.999,"通過","不一致") -> 通過 | E18: 瀑布每期補足至最低現金；最小值應等於最低現金
A19: 股權募資 ÷ 現市值 | B19: =SUM(各期收支!C76:G76)/(輸入與假設!$C$175*輸入與假設!$C$176) -> 0 | C19: ="≤"&IF(輸入與假設!$C$234=INT(輸入與假設!$C$234),TEXT(輸入與假設!$C$234,"0"),TEXT(輸入與假設!$C$234,"0.0"))&"x" -> ≤1.5x | D19: =IF(B19<=輸入與假設!$C$234,"通過","觀察") -> 通過 | E19: ="超過 "&IF(輸入與假設!$C$234=INT(輸入與假設!$C$234),TEXT(輸入與假設!$C$234,"0"),TEXT(輸入與假設!$C$234,"0.0"))&" 倍：市場吸收能力存疑，結論不得為買進" -> 超過 1.5 倍：市場吸收能力存疑，結論不得為買進
A20: 債務明細合計 = 季報本金 125.904 − 以股換債 ＋ 期後新發 | B20: =資產負債_既有債務!E62+SUMPRODUCT(資產負債_既有債務!$C$73:$C$73*(1-資產負債_既有債務!$H$69:$H$69)) -> 125.904 | C20: 125.904 | D20: =IF(ABS(B20-125.904)<0.01,"通過","不一致") -> 通過 | E20: 其他借款 57 筆＋可轉債 1 檔到期本金（company.json → debt.convertibleBridge）
A21: FY27 全年 CapEx（MW 公式） | B21: =輸入與假設!C127 -> 106.09585 | C21: 90–95 | D21: =IF(AND(B21>=90,B21<=95),"通過","觀察") -> 觀察 | E21: 由已連網 MW 增量與預建次年推得；指引只作對照
A22: JV 已承諾餘額於 2027 年內履行 | B22: =SUM(輸入與假設!C120:G120) -> 0 | C22: =0 -> 0 | D22: =IF(ABS(B22-0)<0.01,"通過","不一致") -> 通過 | E22: 季報未揭露 JV 出資承諾（不適用）
A23: 模型每 MW 年租金（FY31） | B23: =運營_站點!G26 -> 2.5063997 | C23: ≥ 市場基準×占比 | D23: =IF(B23>=運營_站點!$H$10*運營_站點!$C$27*0.8,"通過","觀察") -> 通過 | E23: 低於基準×占比的八成即標示：模型租金路徑可能低估
A24: 站點租賃：五期租金可能低估 | B24: =運營_站點!$C$30 -> -83.256118 | C24: <10 | D24: =IF(B24<10,"通過","觀察") -> 通過 | E24: ＝Σ(在役 MW×市場基準×第三方占比 − 模型租金)
A25: 對照：RPO 36 個月內轉換 − 模型 36 個月 MW 驅動營收 | B25: =664*0.5-SUM(運營_產能與收入!C28:G28) -> 60.679625 | C25: 只作對照 | D25: ="對照" -> 對照 | E25: RPO 664 × 50%（含傳統事業）− 模型同期 MW 驅動營收；正值＝RPO 排程高於模型產能營收
A26: 傳統事業：FY27 年初至今實際＋模型期 − 全年（四線合計） | B26: =輸入與假設!$C$84 -> 0 | C26: =0 -> 0 | D26: =IF(ABS(B26)<0.000001,"通過","不一致") -> 通過 | E26: 首期年初至今實際與模型期相加須等於首期全年（工作單 v0.1b 步驟 3）
A27: 營收＝在役 MW × 每 MW × 利用率（五期差額） | B27: =SUM(運營_產能與收入!C26:G26) -> 0 | C27: =0 -> 0 | D27: =IF(ABS(B27)<0.000001,"通過","不一致") -> 通過 | E27: MW 驅動：營收＝平均在役 MW × 每 MW 年收入 × 利用率 × 期間長度
A29: 關鍵輸出（快照；「模型期」＝2026-07-01～2030，與 HTML 頂部 KPI 同口徑）
A30: 模型期排程 RPO | B30: =SUM(運營_產能與收入!C17:G17) -> 529.54
A31: 模型期產能瓶頸 | B31: =SUM(運營_產能與收入!C19:G19) -> 64.304175
A32: 模型期新簽約收入 | B32: =SUM(運營_產能與收入!C23:G23) -> 49.5062
A33: 模型期毛 CapEx（8/31 起） | B33: =SUM(輸入與假設!C135:G135) -> 304.80773
A34: 模型期租金（8/31 起） | B34: =SUM(各期收支!C16:G16) -> 83.256118
A35: 模型期利息（8/31 起，含瀑布新債） | B35: =SUM(各期收支!C21:G21) -> 32.59804
A36: 模型期排程還本（8/31 起） | B36: =SUM(輸入與假設!C170:G170)*輸入與假設!$C$144+SUM(資產負債_既有債務!C84:G84) -> 35.654
A37: 模型期營運缺口（8/31 起） | B37: =SUM(各期收支!C49:G49)-(輸入與假設!$C$241-輸入與假設!$C$242-輸入與假設!$C$244-輸入與假設!$C$259) -> 50.794052
A38: FY27 全年口徑營運缺口（含 1Q 實際） | B38: =SUM(各期收支!C49:G49) -> 43.833052
A39: 期末現金 | B39: =各期收支!G51 -> 82.734389
A40: DCF 每股 | B40: =評價_DCF與目標價!C26 -> 64.641139
A41: 加權目標價 | B41: =評價_DCF與目標價!C51 -> 144.52663

Sheet 檢查_版本紀錄
A1: 版本紀錄（基準情境目標價變化與原因）
A2: v2.9 以前檔名日期統一沿用 20260918，此處日期為實際修改日。v1.7 以前基準為 8 GW、v1.7 為 5 GW、v1.8 起為 5.6 GW；情境定義改變的版本不可直接比較。目標價以當版預設輸入計算（DCF 0 截斷）
A4: 版本 | B4: 日期 | C4: 主要變更 | D4: 基準目標價 | E4: 變動原因
A5: v0.1 | B5: 10-08 | C5: 由 CRWV v4.5／Nebius v0.1 模板建立（CRWV v1.0–v4.5、Nebius v0.1–v0.2 的歷史見各自資料夾）；OCI 以 MW × 每 MW 收入、傳統事業、客戶出資、投資級融資瀑布、強制轉換特別股、分部 EV/EBITDA；審查修正：MW 觸頂後與終值年加穩態 GPU 汰換 CapEx、終值以末期 UFCF 為基準、OCI 改為 EBITDAR 率 − 固定租金 | D5: $144.5 | E5: 首版（基準）；保守 $79.8（賣出）、積極 $226.6（買進）

Sheet 來源
A1: 來源與標籤
A3: 標籤 | B3: 內容
A4: Interested-party | B4: FY27Q1 10-Q（2026-09-11，核閱、未查核）：營收 19.345（OCI 7.388、SaaS 4.219、軟體 5.550、硬體 0.774、服務 1.414）；GAAP 營業利益 6.728（非 GAAP 8.151）；D&A 3.358；SBC 1.127；利息費用 1.428；淨利 4.760。
A5: Interested-party | B5: 資產負債（2026-08-31）：現金 36.369、有價證券 0.708、受限 2.6；PP&E 淨額 127.845（在建 48.546）；遞延營收 30.789；借款帳面 125.337；營業租賃負債 34.621、融資租賃 9.185；已簽約未起租租賃 288.0；股東權益 67.196。
A6: Interested-party | B6: 現金流（Q1）：CFO 23.103（客戶預付 11.363）；資本支出 28.499；公司定義淨現金資本支出 17.966；還款 4.202；ATM 淨額 19.909；股利 1.565。
A7: Interested-party | B7: RPO 664.0：12 個月內 13%、13–36 個月 37%、37–60 個月 34%、其餘 16%；OpenAI 約占一半（二手）。FY27 指引：營收 ≥90、非 GAAP EPS 8.10、資本支出 90–95（法說）、淨現金資本支出 ≤70。
A8: Verified | B8: FY2026 10-K（經查核）：營收 67.357、GAAP 營業利益 20.606、淨利 17.087、稀釋 EPS 5.83；FY24／FY25 損益取自 XBRL companyfacts；55 檔優先票據逐檔（附註 6）。
A9: Interested-party | B9: 融資與信評：2026-02 一次性投資級無擔保債 25（八檔，加權票面約 5.8%）＋強制轉換特別股 5（6.50%，2029-01-15）＋FY27Q1 ATM 20；S&P BBB-／穩定（2026-07-09）、Moody's Baa2／負向、Fitch BBB／穩定（二手）。
A10: Interested-party | B10: 產能：FY26 交付 1.2 GW、FY27Q1 850 MW（口徑不明）、>30 萬顆 GPU、Abilene 618 MW＝75%；利用率 97.9%；續約 +20%。期後：2026-09-24 Project Jupiter 不可抗力通知（2.45 GW）。
A11: Derived | B11: 每 MW 年收入（Tokenomics v5.24 正向推導，沿用 Nebius v0.1a）：保守 11.62／基準 17.40／積極 24.20 US$m/MW-IT·年；每 MW IT 建置成本 IF_CapexIT 37.45（GB300）／37.59（VR200）。Oracle 對照值只作對照。
A12: User-provided | B12: 5Y CDS：無可引用報價（不適用）。
A13: Verified | B13: 市值（2026-09-21 收盤，S&P Global via stockanalysis.com）：ORCL 現價 $144.77（2026-10-06 收盤）、市值 437.75bn（2026-09-21）、流通 3,023.74m；CRWV 49.11；NBIS 68.49；IREN 18.61；APLD 8.22；CORZ 5.90。淨負債取各公司最新申報：CRWV 46.03、NBIS 2.15、IREN 1.70、APLD 3.37、CORZ 2.53。
A14: Interested-party | B14: 賣方目標價（S&P Global Market Intelligence（經 StockAnalysis.com），擷取 2026-10-07）：平均 $237.97、中位數 $240.00、區間 $110.00–$400.00（43 家）；共識評等 Buy。對照 MarketBeat（自行彙整，獨立於 S&P）：平均 $251.72（47 家，Moderate Buy）。數字為賣方意見；逐筆來源與日期見『輸入與假設』I 區。
A15: 方法 | B15: 期前融資瀑布：客戶預付（營運來源）→ 現金 → 未動用額度與新債（受債務上限約束）→ 股權 → 高息債；營收由 MW 驅動，RPO 只作對照。
