Workbook

Sheet README
A1: 雙鴻（3324）收支與估值模型 v0.1.2（AI 半導體 Project：電源與散熱次產業；樣板＝奇鋐） 2026-10-25
A2: 版本：v0.1.1（2026-10-25：補上檔空間級距、投資建議、重點觀察；上游奇鋐 v0.2.1 液冷滲透率改依情境字母（奇鋐），雙鴻本已依情境字母讀奇鋐 In 頁同一組數值，數值不變）。v0.1（初版）。液冷市場口徑（每架機架內液冷取自橋接表、分歧管、內容調整、滲透率）與奇鋐模型相同（唯讀奇鋐模型 In 頁）；雙鴻份額以 FY2026 液冷占比校準，份額相對值區間與奇鋐相同。目標價＝DCF 與 Comparable 加權；三情境延伸到 FY2032（FY2030 起為收斂法）。
A3: 模型命題：雙鴻的液冷營收＝部署 GW（AI IT 資本支出 ÷ 每 GW IT 資本支出）× 液冷滲透率 × 每 GW 液冷內容 × 雙鴻有效份額；非 AI（伺服器氣冷、筆電與桌機、電競顯卡與其他）另以成長率推估。液冷已占 2026 年營收約六成，EPS 幾乎由液冷市場成長與份額決定。
A4: 核心問題：液冷市場隨部署 GW 與 Rubin 全液冷擴大時，雙鴻能不能守住相對奇鋐的份額（三個 ASIC 液冷專案、Vera Rubin 分歧管），讓 FY2027–28 EPS 達到券商預期的高成長；現價隱含的倍數合不合理。
A6: 會計年度＝日曆年，FY(t)＝CY(t)，不平移。預測期 FY2027–FY2029 為驅動因子推導，FY2030–FY2032 為收斂法，非驅動因子推導。金額：十億新台幣；市場以美元計、以匯率換算。口徑：歸屬母公司淨利。
A8: 驅動因子 → 推導量（全部唯讀上游，不修改）
A9: 液冷營收：markets/network 的 AI IT 資本支出 × 同字母顆數係數（tsmc；＝markets/memory SCEN_UNITS）÷ 每 GW IT 資本支出（Tokenomics，經橋接表）＝部署 GW；× 液冷滲透率 × 每 GW 液冷內容（橋接表每架機架內液冷＋分歧管 × 每 GW 機架數 × 內容調整；皆讀奇鋐模型）× 匯率 × 雙鴻有效份額（FY2026 以凱基液冷占比校準）× 份額相對值。
A10: 非 AI：伺服器氣冷（含 AI 氣冷）、筆電與桌機、電競筆電顯卡主機板與其他，FY2026 以產品比重拆分 × 成長率（Assumed）。毛利率：液冷比其他營收高 d_lc（Assumed），其他毛利率為 FY2026 殘差（Derived）。營業費用：彈性 phi（Derived）。
A11: 情境：A＝順利（顆數係數 A、FY2027 起液冷滲透率高值、份額相對值高值）；B＝平平（顆數係數 B、基準）；C＝不如預期（顆數係數 C、低值）。液冷滲透率屬行業情境（技術替代），份額屬公司特有變數；方向一致：A 最有利、C 最不利。
A12: 校準：FY2026 ＝ 1H26 實績＋3Q26 營收實績（月營收）＋假設（4Q 季增、毛利率、營業費用率）。不用共識或券商數字校準（只在 Recon 對帳）。
A13: 估值：Val 第 0 節目標價＝0.5 × DCF 目標價（股東現金流＝EPS ×（1 − tp_g ÷ tp_roe），FY2027–FY2032 明確期＋永續，r 10%、g 4%，三情境權重 0.3／0.5／0.2，推到 12 個月後；負值取 0）＋0.5 × Comparable 目標價（奇鋐、健策、Vertiv、台達電前瞻 P/E 中位數 × 12 個月後前瞻 EPS）；另列 Comparable 單獨目標價、市場共識目標價與差距拆解、DCF 價格帶、十年 P/E 分位檢查。第 3、6 節十年 P/E 規則值保留給 AI 投資地圖，不是目標價。本版未做先驗，無 Andy 合理 P/E 對照。
A14: 標記：Verified、Interested-party、Analogy、Assumed、Derived。SemiAnalysis 未使用。公司原文經媒體與資料商轉載；券商多經媒體轉述。
A16: 已知限制：(1) 液冷占比只有凱基說法（2025 年 34%、1H26 55%、2026F 60%），公司只給液冷營收年增；(2) 液冷滲透率、每架內容調整、份額相對值為 Assumed（與奇鋐模型同值），是 FY2028 EPS 最敏感的輸入；(3) 本模型的液冷市場只含機架內液冷與分歧管，雙鴻的 CDU 營收計入有效份額的分子，份額偏高估；(4) 十年 P/E 只有 9 年（2016 年未找到），2017–2022 年為 AI 前的倍數；(5) 未建資本支出與折舊；(6) 3Q26 財報（預計 11 月中）後更新錨點；R4 產業部署路徑未建。
A17: ="投資建議："&Val!B130&"（依上檔空間固定規則）" -> 投資建議：強力買進（依上檔空間固定規則）
A18: ="重點觀察 1：目標價 NT$"&TEXT(Val!$B$39,"#,##0")&"（DCF "&TEXT(Val!$B$24,"#,##0")&"、Comparable（相對倍數調整後）"&TEXT(tp_comp_adj,"#,##0")&"；DCF 權重 "&TEXT(tp_w_dcf,"0%")&"），比現價 "&TEXT(px,"#,##0")&"（2026-10-22）"&IF(Val!$B$42>=0,"高 "&TEXT(Val!$B$42,"0.0%"),"低 "&TEXT(-Val!$B$42,"0.0%"))&"，級距 "&Val!$B$129&"、投資建議 "&Val!$B$130&"。相對倍數調整係數 "&TEXT(rm_factor,"0.00")&"（本公司 10 年前瞻倍數中位數 ÷ 同業的中位數，夾在 0.5–2.0；Val 第 0.5 節），調整前加權上檔空間 "&TEXT((tp_w_dcf*Val!$B$24+(1-tp_w_dcf)*Val!$B$35)/px-1,"+0.0%;−0.0%")&"；Comparable 單獨（市場主流同業法、未調整）為 "&TEXT(Val!$B$43,"+0.0%;−0.0%")&"。"&"以下為 2026-10-29 相對倍數調整前撰寫的說明，其中數字為調整前：主因是 EPS 與倍數兩者：本模型 12 個月後前瞻 EPS 123.7 比共識前瞻 EPS 74.3 高 66.4%（兩者期間差約一年；FY2027 B 101.6 比共識 77.97 高 30.4%），同業（奇鋐、健策、Vertiv、台達電）前瞻 P/E 中位數 28.8 倍也高於現價隱含 18.3 倍與共識目標價 1,"&"523 隱含的 20.5 倍；Comparable 未扣雙鴻相對奇鋐的份額折價（雙鴻自身前瞻 P/E 17.3 倍）。" -> 重點觀察 1：目標價 NT$2,290（DCF 1,979、Comparable（相對倍數調整後）2,602；DCF 權重 50%），比現價 1,360（2026-10-22）高 68.4%，級距 大於 50%、投資建議 強力買進。相對倍數調整係數 0.73（本公司 10 年前瞻倍數中位數 ÷ 同業的中位數，夾在 0.5–2.0；Val 第 0.5 節），調整前加權上檔空間 +103.6%；Comparable 單獨（市場主流同業法、未調整）為 +161.7%。以下為 2026-10-29 相對倍數調整前撰寫的說明，其中數字為調整前：主因是 EPS 與倍數兩者：本模型 12 個月後前瞻 EPS 123.7 比共識前瞻 EPS 74.3 高 66.4%（兩者期間差約一年；FY2027 B 101.6 比共識 77.97 高 30.4%），同業（奇鋐、健策、Vertiv、台達電）前瞻 P/E 中位數 28.8 倍也高於現價隱含 18.3 倍與共識目標價 1,523 隱含的 20.5 倍；Comparable 未扣雙鴻相對奇鋐的份額折價（雙鴻自身前瞻 P/E 17.3 倍）。
A19: 重點觀察 2：每架液冷內容調整是最敏感的變數：調整 1.0 時 FY2027 EPS −20.9%，2027 1.6 時 +20.9%；營業費用率 +2pt 時 −10.0%。液冷滲透率與內容調整讀奇鋐模型 In 頁同一組數值（奇鋐 v0.2.1 改依情境字母後，本模型數值不變）。
A20: 重點觀察 3：情境分歧大：FY2028 EPS A／B／C＝188.5／117.8／61.3（A 約為 C 的三倍），DCF 情境價值 3,223／1,744／700；美系券商 FY2028 EPS 110 接近情境 B。10 月營收（約 11-10）與 3Q26 財報與法說（預計 11 月中）可檢驗 2026 年液冷占比約六成（凱基）。
A21: v0.1.2（2026-10-28）：分部原則重建（數值不變）。Q 頁最後追加核對列「檢查：分部合計 − 合併營收」；官方分部與子列宣告見 segments.json。
A23: 2026-10-29：加權目標價中的 Comparable 改用相對倍數調整後的值（Val 第 0.5 節：同業前瞻倍數中位數 × 本公司 10 年相對同業的倍數比，Bloomberg 前瞻倍數；Andy 2026-10-27「照建議做」、10-29 資料取回）。「Comparable 目標價（市場主流同業法）」維持不調整。重點觀察 1 的第一句已改為公式；重點觀察 2、3 與其他說明中的目標價與上檔空間數字為調整前撰寫，以 Val 頁為準。
A25: v0.1.3（2026-10-30）：依個股模型原則第 8 節調整 In 頁呈現（數值不變）。In 頁 D／F 欄名改「敏感度低」「敏感度高」（只用於 Sens 頁、不進目標價）；In 頁最後新增「情境驅動對照」一節，把上方各情境專屬輸入三情境並排（只引用上方各列，純展示）；HTML 驅動因子一節分「情境驅動」與「單一參數」兩張表。

Sheet In
A1: In — 輸入（藍字；基準欄 E，低 D、高 F）。金額：十億新台幣（NT$B），市場與每架內容為美元；比例：%。每個輸入盡量附兩個來源（找不到者寫「未找到」）；公司原文算一個。【v0.1.3】基準欄 E 進主模型；D／F＝敏感度低／高，只用於 Sens 頁（一次動一個參數）、不進目標價；情境 A／B／C 的驅動見本頁最後一節「情境驅動對照」。
A2: 標記：Verified／Interested-party／Analogy／Assumed／Derived；Analogy、Assumed 給低／高區間。SemiAnalysis 未使用。公司原文＝雙鴻財報與月營收（經 HiStock、玩股網、時報轉載）；公司的產品比重說法為 Interested-party；券商估計皆為 Interested-party
A3: 鍵 | B3: 項目 | C3: 單位 | D3: 敏感度低 | E3: 基準 | F3: 敏感度高 | G3: 標記 | H3: 來源1 | I3: 來源2／說明
A4: A. AI 部署規模（讀 markets/network、markets/chip_bridge、tsmc 成品；情境 A 基準，B／C 依同字母顆數係數縮放；與奇鋐模型相同上游）
A5: itc_26 | B5: AI IT 資本支出 2026 | C5: US$B | E5: 781.87292 | G5: Derived | H5: markets/network/dist/20261026_AI網通市場模型_v0.2.3.xlsx｜Mkt!C27:F27 | I5: 加速器顆數 × 每顆 IT capex（含 ASIC）；本模型以此除以每 GW IT 資本支出得到部署 GW
A6: itc_27 | B6: AI IT 資本支出 2027 | C6: US$B | E6: 1565.35 | G6: Derived | H6: markets/network/dist/20261026_AI網通市場模型_v0.2.3.xlsx｜Mkt!C27:F27 | I6: 同上
A7: itc_28 | B7: AI IT 資本支出 2028 | C7: US$B | E7: 1984.2639 | G7: Derived | H7: markets/network/dist/20261026_AI網通市場模型_v0.2.3.xlsx｜Mkt!C27:F27 | I7: 同上
A8: itc_29 | B8: AI IT 資本支出 2029 | C8: US$B | E8: 2260.3903 | G8: Derived | H8: markets/network/dist/20261026_AI網通市場模型_v0.2.3.xlsx｜Mkt!C27:F27 | I8: 同上
A9: itpg_gb | B9: 每 GW IT 資本支出（GB300） | C9: US$B | E9: 32.237224 | G9: Derived | H9: markets/chip_bridge/dist/20261027_晶片內容橋接表_v0.2.2.xlsx｜In!E10（GB300）、H10（VR200） | I9: Tokenomics v20.1 IF_CapexIT（經橋接表；唯讀）
A10: itpg_vr | B10: 每 GW IT 資本支出（VR200；2027 起） | C10: US$B | E10: 37.586352 | G10: Derived | H10: markets/chip_bridge/dist/20261027_晶片內容橋接表_v0.2.2.xlsx｜In!E10（GB300）、H10（VR200） | I10: 同上；Rubin Ultra 與 ASIC 機架未另訂（Assumed：同 VR200）
A11: vr26 | B11: 2026 年部署中 Rubin 世代占比（混合每 GW 數值用） | C11: % | D11: 0.15 | E11: 0.22 | F11: 0.3 | G11: Interested-party | H11: avc/dist/20261030_奇鋐個股模型_v0.2.3.xlsx｜In!D11:F11 | I11: TrendForce 2026 組合 Rubin 22%（經 markets/memory；與奇鋐、台達電模型相同）
A12: racks_gb | B12: 每 GW 機架數（GB300） | C12: 架 | E12: 6764 | G12: Derived | H12: markets/chip_bridge/dist/20261027_晶片內容橋接表_v0.2.2.xlsx｜In!E6（GB300）、H6（VR200） | I12: Tokenomics（經橋接表）
A13: racks_vr | B13: 每 GW 機架數（VR200） | C13: 架 | E13: 4052 | G13: Derived | H13: markets/chip_bridge/dist/20261027_晶片內容橋接表_v0.2.2.xlsx｜In!E6（GB300）、H6（VR200） | I13: 同上
A14: cool_gb | B14: GB300 每架機架內液冷（運算匣＋交換匣，橋接表） | C14: US$K | E14: 50 | G14: Interested-party | H14: markets/chip_bridge/dist/20261027_晶片內容橋接表_v0.2.2.xlsx｜In!E33（GB300）、H33（VR200） | I14: Morgan Stanley（經 Tom's Hardware 2025-11-05）：GB300 NVL72 冷卻 BOM；不含 CDU、分歧管
A15: cool_vr | B15: VR200 每架機架內液冷（橋接表） | C15: US$K | E15: 56 | G15: Interested-party | H15: markets/chip_bridge/dist/20261027_晶片內容橋接表_v0.2.2.xlsx｜In!E33（GB300）、H33（VR200） | I15: 同上：VR NVL144
A16: um28_A | B16: 情境 A：2028 顆數 ÷ 基準 | C16: x | E16: 1 | G16: Assumed | H16: tsmc/dist/20261030_台積電個股模型_v0.4.1.xlsx｜In!E37 | I16: A＝順利（基準）；B＝平平；C＝不如預期；與台積電、奇鋐模型相同（＝markets/memory SCEN_UNITS，建置時核對）
A17: um29_A | B17: 情境 A：2029 顆數 ÷ 基準 | C17: x | E17: 1 | G17: Assumed | H17: tsmc/dist/20261030_台積電個股模型_v0.4.1.xlsx｜In!E38 | I17: 同上
A18: um28_B | B18: 情境 B：2028 顆數 ÷ 基準 | C18: x | E18: 0.8 | G18: Assumed | H18: tsmc/dist/20261030_台積電個股模型_v0.4.1.xlsx｜In!E39 | I18: A＝順利（基準）；B＝平平；C＝不如預期；與台積電、奇鋐模型相同（＝markets/memory SCEN_UNITS，建置時核對）
A19: um29_B | B19: 情境 B：2029 顆數 ÷ 基準 | C19: x | E19: 0.85 | G19: Assumed | H19: tsmc/dist/20261030_台積電個股模型_v0.4.1.xlsx｜In!E40 | I19: 同上
A20: um28_C | B20: 情境 C：2028 顆數 ÷ 基準 | C20: x | E20: 0.6 | G20: Assumed | H20: tsmc/dist/20261030_台積電個股模型_v0.4.1.xlsx｜In!E41 | I20: A＝順利（基準）；B＝平平；C＝不如預期；與台積電、奇鋐模型相同（＝markets/memory SCEN_UNITS，建置時核對）
A21: um29_C | B21: 情境 C：2029 顆數 ÷ 基準 | C21: x | E21: 0.6 | G21: Assumed | H21: tsmc/dist/20261030_台積電個股模型_v0.4.1.xlsx｜In!E42 | I21: 同上
A22: fx | B22: 匯率（新台幣 ÷ 美元） | C22: NT$/US$ | D22: 30.5 | E22: 32 | F22: 33 | G22: Derived | H22: avc/dist/20261030_奇鋐個股模型_v0.2.3.xlsx｜In!D22:F22 | I22: 與奇鋐、台達電模型相同
A23: B. 液冷內容、滲透率（讀奇鋐模型 In 頁：兩家用同一液冷市場口徑）與雙鴻份額相對值
A24: mani | B24: 每架分歧管與快接頭（橋接表未含） | C24: US$K | D24: 3 | E24: 6 | F24: 10 | G24: Assumed | H24: siliconomics｜SIF_lc_mani | I24: Siliconomics M19（與奇鋐模型同一值）；雙鴻另做機架分歧管（Vera Rubin inner／rack manifold，經濟日報 2026-09-18）
A25: lcadj_27 | B25: 每架液冷內容 ÷ 橋接表 2027（Rubin 全液冷、ASIC 液冷；2026＝1） | C25: x | D25: 1 | E25: 1.3 | F25: 1.6 | G25: Assumed | H25: siliconomics｜SIF_lc_adj_27 | I25: Siliconomics M19（與奇鋐模型同一值）：TrendForce 稱 Vera Rubin 全液冷提高單架散熱價值（Interested-party）；本模型三情境用基準值，區間只在 Sens
A26: lcadj_28 | B26: 每架液冷內容 ÷ 橋接表 2028（Rubin 全液冷、ASIC 液冷；2026＝1） | C26: x | D26: 1 | E26: 1.4 | F26: 1.8 | G26: Assumed | H26: siliconomics｜SIF_lc_adj_28 | I26: 同上
A27: lcadj_29 | B27: 每架液冷內容 ÷ 橋接表 2029（Rubin 全液冷、ASIC 液冷；2026＝1） | C27: x | D27: 1 | E27: 1.4 | F27: 1.8 | G27: Assumed | H27: siliconomics｜SIF_lc_adj_29 | I27: 同上
A28: lpen_26 | B28: 液冷滲透率 2026（部署 GW 中液冷占比） | C28: % | D28: 0.45 | E28: 0.55 | F28: 0.65 | G28: Assumed | H28: siliconomics｜SIF_lc_pen_26 | I28: Siliconomics M19（與奇鋐模型同一值；TrendForce 以顆數計 2026 53%、2027 近 60%）。技術替代屬行業情境：FY2027 起 A 取高值、B 基準、C 低值；FY2026 三情境皆基準
A29: lpen_27 | B29: 液冷滲透率 2027（部署 GW 中液冷占比） | C29: % | D29: 0.6 | E29: 0.75 | F29: 0.85 | G29: Assumed | H29: siliconomics｜SIF_lc_pen_27 | I29: 同上
A30: lpen_28 | B30: 液冷滲透率 2028（部署 GW 中液冷占比） | C30: % | D30: 0.7 | E30: 0.85 | F30: 0.95 | G30: Assumed | H30: siliconomics｜SIF_lc_pen_28 | I30: 同上
A31: lpen_29 | B31: 液冷滲透率 2029（部署 GW 中液冷占比） | C31: % | D31: 0.75 | E31: 0.9 | F31: 0.95 | G31: Assumed | H31: siliconomics｜SIF_lc_pen_29 | I31: 同上
A32: rel_27 | B32: 雙鴻液冷份額 2027 ÷ 2026（相對值） | C32: x | D32: 0.85 | E32: 0.95 | F32: 1.05 | G32: Assumed | H32: siliconomics｜SIF_lc_avrel_27（區間與奇鋐相同） | I32: 公司特有：A 取高值（三個 ASIC 液冷專案 3Q／4Q26 量產、Vera Rubin 分歧管）、B 基準（與奇鋐相同的份額流失斜率：酷碼、台達電、富世達等追趕）、C 低值；凱基 2026-08-07：雙鴻為台灣前三大散熱廠（未給份額，Interested-party）；份額數字：未找到
A33: rel_28 | B33: 雙鴻液冷份額 2028 ÷ 2026（相對值） | C33: x | D33: 0.75 | E33: 0.9 | F33: 1.05 | G33: Assumed | H33: siliconomics｜SIF_lc_avrel_28（區間與奇鋐相同） | I33: 同上
A34: rel_29 | B34: 雙鴻液冷份額 2029 ÷ 2026（相對值） | C34: x | D34: 0.7 | E34: 0.85 | F34: 1.05 | G34: Assumed | H34: siliconomics｜SIF_lc_avrel_29（區間與奇鋐相同） | I34: 同上
A35: C. 營收結構錨點（公司揭露比例 × 營收）
A36: srv_25 | B36: 2025 年伺服器 ÷ 營收 | C36: % | E36: 0.57 | G36: Interested-party | H36: https://wantrich.chinatimes.com/news/20260521900232-420101：2025 年伺服器 57%、PC 27%、VGA 14%、其他 2%（公司，股東會） | I36: https://www.kgi.com.hk/zh-cn/-/media/files/kgishk/research-reports/tw-reports/auras-technology-3324-tt20260807en.pdf：2025 年伺服器 57%、筆電與桌機 27%、電競筆電顯卡主機板 14%、其他 2%
A37: nb_25 | B37: 2025 年筆電與桌機 ÷ 營收 | C37: % | E37: 0.27 | G37: Interested-party | H37: 同上（公司 PC 27%） | I37: 同上（凱基 27%）
A38: lc_25 | B38: 2025 年液冷 ÷ 營收 | C38: % | D38: 0.3 | E38: 0.34 | F38: 0.38 | G38: Interested-party | H38: 凱基 2026-08-07（網址見 Sources）：2025 年液冷占營收 34% | I38: 第二來源：未找到
A39: srv_26 | B39: 2026 年伺服器 ÷ 營收 | C39: % | D39: 0.72 | E39: 0.74 | F39: 0.76 | G39: Interested-party | H39: https://www.kgi.com.hk/zh-cn/-/media/files/kgishk/research-reports/tw-reports/auras-technology-3324-tt20260807en.pdf：2026F 伺服器 74%（2Q26 78%） | I39: 公司：2026 年伺服器營收年增 110–120%（凱基轉述）→ 2025 年 57% × 2.15 ÷ 營收年增約 64% ≈ 75%（Derived）
A40: nb_26 | B40: 2026 年筆電與桌機 ÷ 營收 | C40: % | D40: 0.13 | E40: 0.15 | F40: 0.17 | G40: Interested-party | H40: 凱基 2026-08-07（網址見 Sources）：2026F 筆電與桌機 15%（2Q26 17%） | I40: 第二來源：未找到
A41: lc_26 | B41: 2026 年液冷 ÷ 營收 | C41: % | D41: 0.55 | E41: 0.6 | F41: 0.63 | G41: Interested-party | H41: https://www.kgi.com.hk/zh-cn/-/media/files/kgishk/research-reports/tw-reports/auras-technology-3324-tt20260807en.pdf：1H26 液冷 55%、2026F 60% | I41: 公司：2026 年液冷營收年增 190–200%（凱基轉述）→ 2025 年 34% × 2.95 ÷ 1.64 ≈ 61%（Derived）
A42: g_sair_27 | B42: 伺服器氣冷營收年增 2027（含 AI 氣冷與一般伺服器） | C42: % | D42: -0.2 | E42: -0.05 | F42: 0.05 | G42: Assumed | H42: 氣冷轉液冷；凱基 2027F 伺服器 82%、液冷 72% → 伺服器氣冷約 10%（2026F 14%），隱含約 −7% | I42: 非 AI 另列（工作單）：不隨部署 GW
A43: g_sair_28 | B43: 伺服器氣冷營收年增 2028（含 AI 氣冷與一般伺服器） | C43: % | D43: -0.2 | E43: -0.05 | F43: 0.05 | G43: Assumed | H43: 同上 | I43: —
A44: g_sair_29 | B44: 伺服器氣冷營收年增 2029（含 AI 氣冷與一般伺服器） | C44: % | D44: -0.2 | E44: -0.05 | F44: 0.05 | G44: Assumed | H44: 同上 | I44: —
A45: g_nb_27 | B45: 筆電與桌機營收年增 2027 | C45: % | D45: -0.1 | E45: -0.03 | F45: 0.05 | G45: Assumed | H45: 凱基 2027F 筆電與桌機 11%（2026F 15%），隱含約 −5% | I45: —
A46: g_nb_28 | B46: 筆電與桌機營收年增 2028 | C46: % | D46: -0.08 | E46: 0 | F46: 0.05 | G46: Assumed | H46: 同上 | I46: —
A47: g_nb_29 | B47: 筆電與桌機營收年增 2029 | C47: % | D47: -0.08 | E47: 0 | F47: 0.05 | G47: Assumed | H47: 同上 | I47: —
A48: g_oth_27 | B48: 電競筆電、顯卡、主機板與其他營收年增 2027 | C48: % | D48: -0.15 | E48: 0 | F48: 0.08 | G48: Assumed | H48: 凱基 2027F 電競與顯卡 6%、其他 1%（2026F 8%、3%） | I48: —
A49: g_oth_28 | B49: 電競筆電、顯卡、主機板與其他營收年增 2028 | C49: % | D49: -0.1 | E49: 0 | F49: 0.08 | G49: Assumed | H49: 同上 | I49: —
A50: g_oth_29 | B50: 電競筆電、顯卡、主機板與其他營收年增 2029 | C50: % | D50: -0.1 | E50: 0 | F50: 0.08 | G50: Assumed | H50: 同上 | I50: —
A51: D. 毛利率
A52: d_lc | B52: 液冷毛利率高於其他營收的幅度 | C52: pt | D52: 0.02 | E52: 0.05 | F52: 0.08 | G52: Assumed | H52: 毛利率 FY2025 27.4% → 1H26 29.0%，同期液冷占比 34% → 55%（隱含差距約 7–8pt，含泰國廠試產成本等其他因素） | I52: 產品別毛利率：未找到
A53: E. FY2026 錨點（1H26 實績＋3Q26 營收實績＋假設）
A54: q3_rev | B54: 3Q26 營收（7–9 月月營收合計） | C54: NT$B | E54: =3.765466+3.141249+2.884061 -> 9.790776 | G54: Verified | H54: https://histock.tw/stock/financial.aspx?no=3324：7 月 37.65、8 月 31.41、9 月 28.84 億元 | I54: https://finance.technews.tw/2026/10/08/auras-3324-202609-financial-report/：前 9 月 270.40 億元（− 1H26 172.52 ≈ 97.88）
A55: q4g | B55: 4Q26 營收季增 | C55: % | D55: 0.08 | E55: 0.14 | F55: 0.18 | G55: Interested-party | H55: https://money.udn.com/money/story/5607/9764013：花旗估 3Q 季增 17%、4Q 季增 16%（Vera Rubin 出貨、ASIC 液冷量產） | I55: https://www.kgi.com.hk/zh-cn/-/media/files/kgishk/research-reports/tw-reports/auras-technology-3324-tt20260807en.pdf：4Q26 114.98 億元（以 3Q 102.66 億為基礎，季增 12%；3Q 實際 97.9 億）
A56: q_gm | B56: 3Q、4Q26 毛利率 | C56: % | D56: 0.28 | E56: 0.29 | F56: 0.3 | G56: Interested-party | H56: https://www.kgi.com.hk/zh-cn/-/media/files/kgishk/research-reports/tw-reports/auras-technology-3324-tt20260807en.pdf：3Q26 毛利率 29.0% | I56: 2Q26 28.4%、1Q26 29.7%（公司）；花旗：3Q、4Q 毛利率回升（經濟日報 2026-09-19）
A57: q_opx | B57: 3Q、4Q26 營業費用 ÷ 營收 | C57: % | D57: 0.1 | E57: 0.11 | F57: 0.122 | G57: Interested-party | H57: https://www.kgi.com.hk/zh-cn/-/media/files/kgishk/research-reports/tw-reports/auras-technology-3324-tt20260807en.pdf：3Q26 營益率 18.0%、毛利率 29.0%（營業費用率 11.0%） | I57: 1Q26 11.9%、2Q26 12.4%（公司；毛利 − 營業利益）
A58: q_nop | B58: 3Q、4Q26 業外收益（每季） | C58: NT$B | D58: -0.15 | E58: 0 | F58: 0.15 | G58: Derived | H58: 1Q26 +0.05、2Q26 −0.07（稅前 − 營業利益） | I58: https://www.wantgoo.com/stock/3324/financial-statements/income-statement
A59: q_nir | B59: 3Q、4Q26 歸屬母公司淨利 ÷ 稅前 | C59: % | D59: 0.72 | E59: 0.74 | F59: 0.76 | G59: Derived | H59: 1Q26 11.64 ÷ 15.70＝0.741；2Q26 9.69 ÷ 13.17＝0.736 | I59: 含稅率約 19–21% 與非控制權益
A60: q_sh | B60: 股數（十億股；3Q 起與 FY2026 EPS 換算） | C60: 十億股 | E60: 0.093076837 | G60: Verified | H60: HiStock：已發行普通股 93,076,837 股 | I60: https://stockanalysis.com/quote/tpex/3324/：Shares outstanding 93.08M；1H26 淨利 21.33 億 ÷ EPS 23.02 ＝ 加權 0.0927
A61: F. 營業費用、業外、稅與非控制權益、股數（FY2027 起）
A62: phi | B62: 營業費用成長對營收成長的彈性 | C62: x | D62: 0.5 | E62: 0.65 | F62: 0.85 | G62: Derived | H62: FY2026 錨點實測（Q 頁 B26） | I62: FY2025 營業費用年增 47%、營收年增 48%（彈性約 1.0，泰國廠擴產期）
A63: opx_adj | B63: 營業費用額外占營收比（Sens 用；基準 0） | C63: pt | D63: -0.02 | E63: 0 | F63: 0.02 | G63: Assumed | H63: 無 | I63: Sens 用 ±2 個百分點
A64: nop_f | B64: 業外收益（每年） | C64: NT$B | D64: -0.5 | E64: 0 | F64: 0.5 | G64: Assumed | H64: FY2025 約 0.02（2Q25 匯損 −0.42）、1H26 約 −0.02 | I64: 匯兌損益波動大
A65: nir_f | B65: 歸屬母公司淨利 ÷ 稅前 | C65: % | D65: 0.72 | E65: 0.74 | F65: 0.78 | G65: Derived | H65: 同 q_nir；FY2025 25.72 ÷ 32.77＝0.785（2Q25 稅負低） | I65: 非控制權益比例變動：未建模
A66: sh_g | B66: 股數年變動 | C66: % | D66: 0 | E66: 0 | F66: 0.01 | G66: Assumed | H66: FY2025 加權 0.0910 → 2026 年已發行 0.0931 十億股 | I66: 可轉債、員工認股：未找到
A67: mf | B67: AI 部署係數（Sens 用；FY2027 起） | C67: x | D67: 0.8 | E67: 1 | F67: 1.2 | G67: Assumed | H67: 網通模型 2027 年 AI IT 資本支出約 2 倍 | I67: ±20%
A68: G. 共識、市場資料（只作 Recon 對帳，不作校準）
A69: b_rev26 | B69: 凱基 FY2026 營收（2026-08-07） | C69: NT$B | E69: 39.016 | G69: Interested-party | H69: https://www.kgi.com.hk/zh-cn/-/media/files/kgishk/research-reports/tw-reports/auras-technology-3324-tt20260807en.pdf | I69: —
A70: b_eps26 | B70: 凱基 FY2026 EPS（2026-08-07） | C70: NT$ | E70: 55.69 | G70: Interested-party | H70: https://www.kgi.com.hk/zh-cn/-/media/files/kgishk/research-reports/tw-reports/auras-technology-3324-tt20260807en.pdf | I70: —
A71: b_rev27 | B71: 凱基 FY2027 營收（2026-08-07） | C71: NT$B | E71: 50.486 | G71: Interested-party | H71: https://www.kgi.com.hk/zh-cn/-/media/files/kgishk/research-reports/tw-reports/auras-technology-3324-tt20260807en.pdf | I71: —
A72: b_eps27 | B72: 凱基 FY2027 EPS（2026-08-07） | C72: NT$ | E72: 81.55 | G72: Interested-party | H72: https://www.kgi.com.hk/zh-cn/-/media/files/kgishk/research-reports/tw-reports/auras-technology-3324-tt20260807en.pdf | I72: 目標價 1,410（22 倍 2026–27 平均 EPS）
A73: b_lc27 | B73: 凱基：2027 年液冷 ÷ 營收 | C73: % | E73: 0.72 | G73: Interested-party | H73: https://www.kgi.com.hk/zh-cn/-/media/files/kgishk/research-reports/tw-reports/auras-technology-3324-tt20260807en.pdf | I73: 內文 70–75%
A74: u_eps26 | B74: 美系券商 FY2026 EPS（2026-09-18） | C74: NT$ | E74: 58.8 | G74: Interested-party | H74: https://money.udn.com/money/story/5607/9762508：美系券商 2026 58.8、2027 89、2028 110（20 倍 2027 EPS） | I74: 券商名稱未載明；花旗 09-19 目標價 1,800（經濟日報）
A75: u_eps27 | B75: 美系券商 FY2027 EPS（2026-09-18） | C75: NT$ | E75: 89 | G75: Interested-party | H75: https://money.udn.com/money/story/5607/9762508 | I75: —
A76: u_eps28 | B76: 美系券商 FY2028 EPS（2026-09-18） | C76: NT$ | E76: 110 | G76: Interested-party | H76: https://money.udn.com/money/story/5607/9762508 | I76: —
A77: c_rev26 | B77: 共識 FY2026 營收（stockanalysis／S&P Global，2026-10-19） | C77: NT$B | E77: 38.7 | G77: Interested-party | H77: https://stockanalysis.com/quote/tpex/3324/forecast/ | I77: 區間 37.5–39.9
A78: c_eps26 | B78: 共識 FY2026 EPS（同上） | C78: NT$ | E78: 56.18 | G78: Interested-party | H78: https://stockanalysis.com/quote/tpex/3324/forecast/ | I78: 區間 52.19–58.82
A79: c_rev27 | B79: 共識 FY2027 營收（同上，Revenue Next Year） | C79: NT$B | E79: 49.1 | G79: Interested-party | H79: https://stockanalysis.com/quote/tpex/3324/forecast/ | I79: —
A80: c_eps27 | B80: 共識 FY2027 EPS（同上，EPS Next Year） | C80: NT$ | E80: 77.97 | G80: Interested-party | H80: stockanalysis forecast 頁（網址見 Sources） | I80: FY2028 共識：未找到（付費）
... A84: avsh_29 | B84: 奇鋐有效份額 2029（奇鋐模型 Units，情境不變；Recon 用） | C84: % | E84: 0.42408849 | G84: Derived | H84: avc/dist/20261030_奇鋐個股模型_v0.2.3.xlsx｜Units!C9:F9 | I84: 同上
A85: H. 價格與估值
A86: px | B86: 股價（2026-10-22 收盤） | C86: NT$ | E86: 1360 | G86: Interested-party | H86: Yahoo 股市（網址見 Sources）：2026/10/22 收盤 1,360（−15，−1.09%） | I86: HiStock（2026-10-24 頁面）仍為 1,360；10-23 收盤：未找到
A87: eps_ttm | B87: 近 12 月 EPS（3Q25–2Q26） | C87: NT$ | E87: =10.66+10.19+12.61+10.41 -> 43.87 | G87: Verified | H87: https://histock.tw/stock/3324/每股盈餘：3Q25 10.66、4Q25 10.19、1Q26 12.61、2Q26 10.41 | I87: —
A88: I. 目標價（DCF 與 Comparable 加權）與收斂法參數（黃底＝Assumed，Andy 可改）
A89: tp_wA | B89: 目標價情境權重：情境 A（順利） | C89: 權重 | E89: 0.3 | G89: Assumed | H89: Andy 可改（2026-10-25 目標價規格預設 A／B／C＝0.3／0.5／0.2） | I89: 三個權重合計應為 1；用於 DCF 與 Comparable 的情境加權（Val 第 0 節）
A90: tp_wB | B90: 目標價情境權重：情境 B（平平） | C90: 權重 | E90: 0.5 | G90: Assumed | H90: Andy 可改（2026-10-25 目標價規格預設 A／B／C＝0.3／0.5／0.2） | I90: 三個權重合計應為 1；用於 DCF 與 Comparable 的情境加權（Val 第 0 節）
A91: tp_wC | B91: 目標價情境權重：情境 C（不如預期） | C91: 權重 | E91: 0.2 | G91: Assumed | H91: Andy 可改（2026-10-25 目標價規格預設 A／B／C＝0.3／0.5／0.2） | I91: 三個權重合計應為 1；用於 DCF 與 Comparable 的情境加權（Val 第 0 節）
A92: tp_r | B92: 折現率／要求報酬（DCF） | C92: % | E92: 0.1 | G92: Assumed | H92: Andy 可改（工作單 2026-10-25 預設 10%；美、台、日、韓同一值） | I92: Sens 頁 ±1pt
A93: tp_g | B93: 長期成長率（DCF 永續；情境 B 的 FY2032 營收年增收斂目標） | C93: % | E93: 0.04 | G93: Assumed | H93: Andy 可改（工作單預設 4%） | I93: Sens 頁 ±1pt（只動 DCF，PL 收斂目標不隨之變動）
A94: tp_roe | B94: ROE（近三年平均） | C94: % | E94: =AVERAGE(0.1955,0.2391,0.2596) -> 0.2314 | G94: Derived | H94: https://stockanalysis.com/quote/tpex/3324/financials/ratios/：FY2023 19.55%、FY2024 23.91%、FY2025 25.96% | I94: Goodinfo：19.6%、23.9%、26.0%（兩來源一致）
A95: tp_w_dcf | B95: 目標價中 DCF 的權重；其餘為 Comparable | C95: % | E95: 0.5 | G95: Assumed | H95: Andy 可改（2026-10-25 11:53 定 0.5：DCF／Comparable 各半） | I95: Sens 頁 0.3／0.7
A96: fade_gA | B96: 情境 A（順利）：FY2032 營收年增收斂目標（tp_g＋2pt） | C96: % | E96: =tp_g+0.02 -> 0.06 | G96: Assumed | H96: 工作單 2026-10-25 11:20 收斂法 | I96: FY2030 起由 FY2029 年增線性收斂，FY2032 達到
A97: fade_gB | B97: 情境 B（平平）：FY2032 營收年增收斂目標（＝tp_g） | C97: % | E97: =tp_g -> 0.04 | G97: Assumed | H97: 同上 | I97: —
A98: fade_gC | B98: 情境 C（不如預期）：FY2032 營收年增收斂目標（tp_g−2pt） | C98: % | E98: =tp_g-0.02 -> 0.02 | G98: Assumed | H98: 同上 | I98: —
A99: nim10 | B99: 歷史平均淨利率（2017–2025 九年；2016 年未找到） | C99: % | E99: =AVERAGE(0.0424,0.0302,0.0946,0.0923,0.0809,0.0929,0.0975,0.122,0.116) -> 0.085422222 | G99: Derived | H99: Goodinfo（網址見 Sources）：稅後淨利率 2017 4.24%、2018 3.02%、2019 9.46%、2020 9.23%、2021 8.09%、2022 9.29%、2023 9.75%、2024 12.2%、2025 11.6%（合併淨利口徑） | I99: 2016 年：未找到（以九年平均代替十年平均）；本模型淨利為歸屬母公司，FY2025 歸母淨利率 11.05%，合併口徑略高
A100: cons_tp | B100: 市場共識目標價（賣方平均） | C100: NT$ | E100: 1523 | G100: Interested-party | H100: stockanalysis forecast 頁（網址見 Sources）：17 位分析師平均 1,523（中位數 1,550，區間 1,025–2,000），頁面時間 2026-10-19 | I100: 第二來源：未找到（凱基 1,410、花旗 1,800 為個別券商）
A101: cons_feps | B101: 共識前瞻 12 月 EPS（＝2／12 × FY2026＋10／12 × FY2027 共識） | C101: NT$ | E101: =2/12*c_eps26+10/12*c_eps27 -> 74.338333 | G101: Derived | H101: stockanalysis 共識 FY2026 56.18、FY2027 77.97（2026-10-19；Interested-party） | I101: 期間為 2026-10 起算的 12 個月，本模型前瞻 EPS 為 12 個月後起算，兩者期間不同；個股頁 Forward PE 17.27（價格 1,140，2026-08-28）隱含 66.0
A103: 情境驅動對照（三情境並排，進主模型的加權目標價；本節只引用上方各列，修改請改上方藍字。上方「敏感度低／高」欄只用於 Sens 頁，不進目標價）
A104: 鍵 | B104: 項目 | C104: 單位 | D104: 情境 A（樂觀） | E104: 情境 B（基準） | F104: 情境 C（保守） | G104: 標記 | H104: 說明
...

Sheet Q
A1: Q — 實績與 FY2026 錨點（十億新台幣；EPS 為新台幣；股數為十億股）。藍字＝輸入；黑字＝公式。實績取自雙鴻財報（經玩股網、時報、HiStock 轉載）與月營收
A2: FY2026 錨點＝1H26 實績＋3Q26 營收實績（月營收）＋3Q、4Q 假設（毛利率、營業費用率、業外、淨利 ÷ 稅前；4Q 營收＝3Q × (1＋季增)）。3Q26 財報與法說（2025 年為 11 月中）尚未公布。各季毛利、營業利益、稅前取自玩股網各季損益（合併）；歸屬母公司淨利與 EPS 取自公司公告（經時報、凱基、HiStock）
A3: 項目 | B3: FY2025A | C3: 1H26（實績） | D3: 3Q26（營收實績） | E3: 4Q26（模型） | F3: FY2026 錨點 | G3: 標記 | H3: 來源1（公司） | I3: 來源2／說明
A4: 營收 | B4: 23.276 | C4: =8.551657+8.700121 -> 17.251778 | D4: =q3_rev -> 9.790776 | E4: =D4*(1+q4g) -> 11.161485 | F4: =SUM(C4:E4) -> 38.204039 | G4: Verified／Interested-party（4Q 季增） | H4: FY2025：https://wantrich.chinatimes.com/news/20260304900286-420101；各季：https://www.wantgoo.com/stock/3324/financial-statements/income-statement | I4: FY2025 232.76 億元（時報 2026-03-04）；1Q26 85.52、2Q26 87.00 億元（玩股網；凱基 2Q 87.00）
A5: 毛利 | B5: 6.372 | C5: =2.536523+2.472471 -> 5.008994 | D5: =D4*q_gm -> 2.839325 | E5: =E4*q_gm -> 3.2368305 | F5: =SUM(C5:E5) -> 11.08515 | G5: Verified／Interested-party（3Q、4Q） | H5: FY2025：https://wantrich.chinatimes.com/news/20260304900286-420101；各季：https://www.wantgoo.com/stock/3324/financial-statements/income-statement | I5: FY2025 毛利率 27.38%（時報）；2Q26 28.4%（凱基）
A6: 毛利率 | B6: =B5/B4 -> 0.27375838 | C6: =C5/C4 -> 0.29034654 | D6: =D5/D4 -> 0.29 | E6: =E5/E4 -> 0.29 | F6: =F5/F4 -> 0.29015649 | G6: Derived | H6: — | I6: FY2025 27.4%；1H26 29.0%
A7: 營業費用 | B7: =B5-B8 -> 3.113 | C7: =C5-C8 -> 2.099071 | D7: =D4*q_opx -> 1.0769854 | E7: =E4*q_opx -> 1.2277633 | F7: =SUM(C7:E7) -> 4.4038197 | G7: Derived（毛利 − 營業利益）／Interested-party | H7: FY2025：https://wantrich.chinatimes.com/news/20260304900286-420101；各季：https://www.wantgoo.com/stock/3324/financial-statements/income-statement | I7: 凱基 2026-08-07（https://www.kgi.com.hk/zh-cn/-/media/files/kgishk/research-reports/tw-reports/auras-technology-3324-tt20260807en.pdf）
A8: 營業利益 | B8: 3.259 | C8: =1.519644+1.390279 -> 2.909923 | D8: =D5-D7 -> 1.7623397 | E8: =E5-E7 -> 2.0090672 | F8: =SUM(C8:E8) -> 6.6813299 | G8: Verified／Derived | H8: FY2025：https://wantrich.chinatimes.com/news/20260304900286-420101；各季：https://www.wantgoo.com/stock/3324/financial-statements/income-statement | I8: FY2025 營益率 14.0%（時報）；2Q26 13.90 億元、營益率 16.0%（凱基）
A9: 營業利益率 | B9: =B8/B4 -> 0.14001547 | C9: =C8/C4 -> 0.1686738 | D9: =D8/D4 -> 0.18 | E9: =E8/E4 -> 0.18 | F9: =F8/F4 -> 0.17488543 | G9: Derived | H9: — | I9: —
A10: 業外收益 | B10: =B11-B8 -> 0.018436 | C10: =C11-C8 -> -0.022684 | D10: =q_nop -> 0 | E10: =q_nop -> 0 | F10: =SUM(C10:E10) -> -0.022684 | G10: Derived | H10: FY2025：https://wantrich.chinatimes.com/news/20260304900286-420101；各季：https://www.wantgoo.com/stock/3324/financial-statements/income-statement | I10: 凱基 2026-08-07（https://www.kgi.com.hk/zh-cn/-/media/files/kgishk/research-reports/tw-reports/auras-technology-3324-tt20260807en.pdf）
A11: 稅前利益 | B11: 3.277436 | C11: =1.570048+1.317191 -> 2.887239 | D11: =D8+D10 -> 1.7623397 | E11: =E8+E10 -> 2.0090672 | F11: =SUM(C11:E11) -> 6.6586459 | G11: Verified（資料商轉載）／Derived | H11: https://www.wantgoo.com/stock/3324/financial-statements/income-statement | I11: FY2025 為四季加總
A12: 歸屬母公司淨利 | B12: 2.572 | C12: =1.164+0.969 -> 2.133 | D12: =D11*q_nir -> 1.3041314 | E12: =E11*q_nir -> 1.4867098 | F12: =SUM(C12:E12) -> 4.9238411 | G12: Verified／Derived（3Q、4Q） | H12: FY2025：https://wantrich.chinatimes.com/news/20260304900286-420101；各季：https://www.wantgoo.com/stock/3324/financial-statements/income-statement | I12: FY2025 25.72 億（時報 2026-03-04）；1Q26 11.64 億（時報 2026-05-21）；2Q26 9.69 億（凱基）；合併淨利 FY2025 26.98、1Q26 12.65、2Q26 10.39（玩股網）
A13: 淨利 ÷ 稅前（含稅與非控制權益） | B13: =B12/B11 -> 0.78475979 | C13: =C12/C11 -> 0.73876808 | D13: =D12/D11 -> 0.74 | E13: =E12/E11 -> 0.74 | F13: =F12/F11 -> 0.73946583 | G13: Derived | H13: — | I13: —
A14: 股數（十億股） | B14: =2.572/28.26 -> 0.091012031 | C14: =2.133/23.02 -> 0.092658558 | D14: =q_sh -> 0.093076837 | E14: =q_sh -> 0.093076837 | F14: =q_sh -> 0.093076837 | G14: Derived／Verified | H14: FY2025：https://wantrich.chinatimes.com/news/20260304900286-420101；各季：https://www.wantgoo.com/stock/3324/financial-statements/income-statement | I14: FY2025、1H26＝淨利 ÷ EPS（加權）；3Q 起＝已發行股數
A15: EPS | B15: =B12/B14 -> 28.26 | C15: =C12/C14 -> 23.02 | D15: =D12/D14 -> 14.011342 | E15: =E12/E14 -> 15.972929 | F15: =F12/F14 -> 52.900821 | G15: Derived | H15: 淨利 ÷ 股數 | I15: FY2026 錨點以已發行股數換算（1H26 加權股數較少，差約 0.4%）
A16: 公司揭露 EPS | B16: 28.26 | C16: 23.02 | G16: Verified | H16: https://histock.tw/stock/3324/每股盈餘 | I16: 1Q26 12.61、2Q26 10.41；3Q25 10.66、4Q25 10.19（https://winvest.tw/News/Detail/95436）
A17: 液冷營收（＝營收 × 液冷占比） | B17: =B4*lc_25 -> 7.91384 | F17: =F4*lc_26 -> 22.922423 | G17: Derived／Interested-party | H17: 公司與凱基產品比重（In 頁 C 節） | I17: 液冷、伺服器氣冷的季度金額未揭露：未找到
A18: 伺服器氣冷（＝營收 ×（伺服器 − 液冷）） | B18: =B4*(srv_25-lc_25) -> 5.35348 | F18: =F4*(srv_26-lc_26) -> 5.3485654 | G18: Derived／Interested-party | H18: 公司與凱基產品比重（In 頁 C 節） | I18: —
A19: 筆電與桌機（＝營收 × 筆電與桌機占比） | B19: =B4*nb_25 -> 6.28452 | F19: =F4*nb_26 -> 5.7306058 | G19: Derived／Interested-party | H19: 公司與凱基產品比重（In 頁 C 節） | I19: —
A20: 電競筆電、顯卡、主機板與其他（＝營收 ×（1 − 伺服器 − 筆電與桌機）） | B20: =B4*(1-srv_25-nb_25) -> 3.72416 | F20: =F4*(1-srv_26-nb_26) -> 4.2024443 | G20: Derived／Interested-party | H20: 公司與凱基產品比重（In 頁 C 節） | I20: —
A21: 液冷（Sens：2026 液冷占比 低） | F21: =F4*lc_26_lo -> 21.012221 | G21: Derived | H21: Sens 用 | I21: —
A22: 伺服器氣冷（Sens：液冷占比 低） | F22: =F4*(srv_26-lc_26_lo) -> 7.2587673 | G22: Derived | H22: Sens 用 | I22: —
A23: 液冷（Sens：2026 液冷占比 高） | F23: =F4*lc_26_hi -> 24.068544 | G23: Derived | H23: Sens 用 | I23: —
A24: 伺服器氣冷（Sens：液冷占比 高） | F24: =F4*(srv_26-lc_26_hi) -> 4.2024443 | G24: Derived | H24: Sens 用 | I24: —
A26: 營業費用彈性（FY2026 營業費用年增 ÷ 營收年增；In 頁 phi 的依據） | B26: =(F7/B7-1)/(F4/B4-1) -> 0.64653502
A28: FY2026 錨點的檢查（參考；校準未使用券商數字）
A29: FY2026 營收年增 | B29: =F4/B4-1 -> 0.64134897
A30: FY2026 液冷營收年增（公司：+190–200%） | B30: =F17/B17-1 -> 1.8964982
A31: FY2026 伺服器營收年增（公司：+110–120%） | B31: =(F17+F18)/(B17+B18)-1 -> 1.1308741
A32: FY2026 營收 ÷ 共識（stockanalysis）− 1 | B32: =F4/c_rev26-1 -> -0.012815539
A33: FY2026 EPS ÷ 共識（stockanalysis）− 1 | B33: =F15/c_eps26-1 -> -0.058369148
A35: 檢查：分部合計 − 合併營收 | B35: =ROUND(B17+B18+B19+B20-B4,6) -> 0
A36: 分部原則第 3 條（2026-10-28 追加）；分部宣告見 segments.json

Sheet Units
A1: Units — AI 液冷市場（機架內液冷＋分歧管，與奇鋐模型同口徑）、雙鴻份額與每 GW 營收（情境 B）。部署 GW＝AI IT 資本支出（markets/network）÷ 每 GW IT 資本支出（Tokenomics，經橋接表）；每架液冷取自橋接表
A3: 項目 | B3: 單位 | C3: CY2026 | D3: CY2027 | E3: CY2028 | F3: CY2029 | G3: 說明
A4: 部署 GW（情境 B） | B4: GW | C4: =PL!D103 -> 23.399538 | D4: =PL!E103 -> 41.646766 | E4: =PL!F103 -> 42.233711 | F4: =PL!G103 -> 51.117803 | G4: AI IT 資本支出 × 顆數係數 B ÷ 每 GW IT 資本支出
A5: 液冷滲透率（部署 GW） | B5: % | C5: =PL!D104 -> 0.55 | D5: =PL!E104 -> 0.75 | E5: =PL!F104 -> 0.85 | F5: =PL!G104 -> 0.9 | G5: 奇鋐模型的假設（In 頁 B 節）
A6: 每 GW 液冷內容 | B6: US$M/GW | C6: =PL!D105 -> 350.7208 | D6: =PL!E105 -> 326.5912 | E6: =PL!F105 -> 351.7136 | F6: =PL!G105 -> 351.7136 | G6: 橋接表機架內液冷＋分歧管 × 每 GW 機架數 × 內容調整
A7: AI 液冷市場（機架內液冷＋分歧管） | B7: US$B | C7: =PL!D106 -> 4.5136876 | D7: =PL!E106 -> 10.2011 | E7: =PL!F106 -> 12.626045 | F7: =PL!G106 -> 16.180944 | G7: 不含機架外 CDU、液對氣
A8: 雙鴻有效份額 | B8: % | C8: =PL!D110 -> 0.15870078 | D8: =PL!E110 -> 0.15076574 | E8: =PL!F110 -> 0.1428307 | F8: =PL!G110 -> 0.13489566 | G8: FY2026 以凱基液冷占比校準
A9: 奇鋐有效份額（奇鋐模型） | B9: % | C9: =avsh_26 -> 0.49892764 | D9: =avsh_27 -> 0.47398126 | E9: =avsh_28 -> 0.44903488 | F9: =avsh_29 -> 0.42408849 | G9: 奇鋐模型 Units（唯讀）；奇鋐三情境份額相同
A10: 兩家有效份額合計（奇鋐＋雙鴻） | B10: % | C10: =C8+C9 -> 0.65762842 | D10: =D8+D9 -> 0.624747 | E10: =E8+E9 -> 0.59186558 | F10: =F8+F9 -> 0.55898415 | G10: 兩家分子都含 CDU 與機架外產品，合計偏高估實際冷板份額
A11: 其他廠商（酷碼、台達電、富世達、Boyd、CoolIT 等）＝ 1 − 兩家合計 | B11: % | C11: =1-C10 -> 0.34237158 | D11: =1-D10 -> 0.375253 | E11: =1-E10 -> 0.40813442 | F11: =1-F10 -> 0.44101585
A12: 雙鴻液冷營收 | B12: US$B | C12: =PL!D111/fx -> 0.71632572 | D12: =PL!E111/fx -> 1.5379764 | E12: =PL!F111/fx -> 1.8033868 | F12: =PL!G111/fx -> 2.1827391
A13: 每 GW 雙鴻液冷營收 | B13: US$M/GW | C13: =PL!D119 -> 30.612815 | D13: =PL!E119 -> 36.929072 | E13: =PL!F119 -> 42.700174 | F13: =PL!G119 -> 42.700174
A15: 讀法：液冷市場口徑、滲透率、每架內容調整與奇鋐模型相同；雙鴻份額以 FY2026 液冷占比（凱基）校準。兩家有效份額合計約六成，其餘為酷碼、台達電、富世達、Boyd、CoolIT 等；合計若超過八成即不合理，應回頭檢查份額相對值或市場口徑。

Sheet PL
A1: PL — 雙鴻損益（十億新台幣；EPS 新台幣；歸屬母公司）。FY2025A 實績、FY2026 錨點（1H26 實績＋3Q26 營收實績＋假設），FY2027–FY2029 為驅動因子推導，FY2030–FY2032 為收斂法（本頁延伸表，灰底）。FY(t)＝CY(t)。三情境各一個完整推導區塊（本頁下方），頂端為摘要
A3: 情境／項目 | B3: 單位 | C3: FY2025A | D3: FY2026（錨點） | E3: FY2027 | F3: FY2028 | G3: FY2029 | H3: 說明
A4: 情境 A
A5: 營收 | B5: NT$B | C5: =C78 -> 23.276 | D5: =D78 -> 38.204039 | E5: =E78 -> 76.49084 | F5: =F78 -> 108.64721 | G5: =G78 -> 121.49493
A6: 營收年增 | B6: % | D6: =D79 -> 0.64134897 | E6: =E79 -> 1.0021663 | F6: =F79 -> 0.42039505 | G6: =G79 -> 0.1182517
A7: 液冷營收 | B7: NT$B | C7: =C73 -> 7.91384 | D7: =D73 -> 22.922423 | E7: =E73 -> 61.648571 | F7: =F73 -> 94.058998 | G7: =G73 -> 107.14807
A8: 伺服器氣冷營收 | B8: NT$B | C8: =C75 -> 5.35348 | D8: =D75 -> 5.3485654 | E8: =E75 -> 5.0811371 | F8: =F75 -> 4.8270803 | G8: =G75 -> 4.5857263
A9: 筆電與桌機營收 | B9: NT$B | C9: =C76 -> 6.28452 | D9: =D76 -> 5.7306058 | E9: =E76 -> 5.5586876 | F9: =F76 -> 5.5586876 | G9: =G76 -> 5.5586876
A10: 電競、顯卡與其他營收 | B10: NT$B | C10: =C77 -> 3.72416 | D10: =D77 -> 4.2024443 | E10: =E77 -> 4.2024443 | F10: =F77 -> 4.2024443 | G10: =G77 -> 4.2024443
A11: 液冷 ÷ 營收 | B11: % | C11: =C80 -> 0.34 | D11: =D80 -> 0.6 | E11: =E80 -> 0.80596018 | F11: =F80 -> 0.86572861 | G11: =G80 -> 0.88191393
A12: 毛利率 | B12: % | C12: =C85 -> 0.27375838 | D12: =D85 -> 0.29015649 | E12: =E85 -> 0.30045449 | F12: =F85 -> 0.30344292 | G12: =G85 -> 0.30425218
A13: 營業利益率 | B13: % | C13: =C89 -> 0.14001547 | D13: =D89 -> 0.17488543 | E13: =E89 -> 0.2053777 | F13: =F89 -> 0.2182151 | G13: =G89 -> 0.22217877
A14: 歸屬母公司淨利 | B14: NT$B | C14: =C92 -> 2.572 | D14: =D92 -> 4.9238411 | E14: =E92 -> 11.62504 | F14: =F92 -> 17.544262 | G14: =G92 -> 19.975259
A15: EPS | B15: NT$ | C15: =C94 -> 28.26 | D15: =D94 -> 52.900821 | E15: =E94 -> 124.89724 | F15: =F94 -> 188.49224 | G15: =G94 -> 214.61042
A16: EPS 年增 | B16: % | D16: =D95 -> 0.87193281 | E16: =E95 -> 1.3609697 | F16: =F95 -> 0.50917865 | G16: =G95 -> 0.13856368
A18: 情境 B
A19: 營收 | B19: NT$B | C19: =C116 -> 23.276 | D19: =D116 -> 38.204039 | E19: =E116 -> 64.057515 | F19: =F116 -> 72.29659 | G19: =G116 -> 84.194509
A20: 營收年增 | B20: % | D20: =D117 -> 0.64134897 | E20: =E117 -> 0.67672102 | F20: =F117 -> 0.12861996 | G20: =G117 -> 0.16457096
A21: 液冷營收 | B21: NT$B | C21: =C111 -> 7.91384 | D21: =D111 -> 22.922423 | E21: =E111 -> 49.215246 | F21: =F111 -> 57.708378 | G21: =G111 -> 69.847651
A22: 伺服器氣冷營收 | B22: NT$B | C22: =C113 -> 5.35348 | D22: =D113 -> 5.3485654 | E22: =E113 -> 5.0811371 | F22: =F113 -> 4.8270803 | G22: =G113 -> 4.5857263
A23: 筆電與桌機營收 | B23: NT$B | C23: =C114 -> 6.28452 | D23: =D114 -> 5.7306058 | E23: =E114 -> 5.5586876 | F23: =F114 -> 5.5586876 | G23: =G114 -> 5.5586876
A24: 電競、顯卡與其他營收 | B24: NT$B | C24: =C115 -> 3.72416 | D24: =D115 -> 4.2024443 | E24: =E115 -> 4.2024443 | F24: =F115 -> 4.2024443 | G24: =G115 -> 4.2024443
A25: 液冷 ÷ 營收 | B25: % | C25: =C118 -> 0.34 | D25: =D118 -> 0.6 | E25: =E118 -> 0.76829777 | F25: =F118 -> 0.79821715 | G25: =G118 -> 0.82959865
A26: 毛利率 | B26: % | C26: =C123 -> 0.27375838 | D26: =D123 -> 0.29015649 | E26: =E123 -> 0.29857137 | F26: =F123 -> 0.30006734 | G26: =G123 -> 0.30163642
A27: 營業利益率 | B27: % | C27: =C127 -> 0.14001547 | D27: =D127 -> 0.17488543 | E27: =E127 -> 0.19958343 | F27: =F127 -> 0.2050277 | G27: =G127 -> 0.21129745
A28: 歸屬母公司淨利 | B28: NT$B | C28: =C130 -> 2.572 | D28: =D130 -> 4.9238411 | E28: =E130 -> 9.4607655 | F28: =F130 -> 10.968875 | G28: =G130 -> 13.164663
A29: EPS | B29: NT$ | C29: =C132 -> 28.26 | D29: =D132 -> 52.900821 | E29: =E132 -> 101.64468 | F29: =F132 -> 117.84752 | G29: =G132 -> 141.43866
A30: EPS 年增 | B30: % | D30: =D133 -> 0.87193281 | E30: =E133 -> 0.92141974 | F30: =F133 -> 0.15940669 | G30: =G133 -> 0.20018355
A32: 情境 C
A33: 營收 | B33: NT$B | C33: =C154 -> 23.276 | D33: =D154 -> 38.204039 | E33: =E154 -> 50.070024 | F33: =F154 -> 44.291054 | G33: =G154 -> 48.183091
A34: 營收年增 | B34: % | D34: =D155 -> 0.64134897 | E34: =E155 -> 0.31059505 | F34: =F155 -> -0.11541776 | G34: =G155 -> 0.08787411
A35: 液冷營收 | B35: NT$B | C35: =C149 -> 7.91384 | D35: =D149 -> 22.922423 | E35: =E149 -> 35.227755 | F35: =F149 -> 29.702841 | G35: =G149 -> 33.836232
A36: 伺服器氣冷營收 | B36: NT$B | C36: =C151 -> 5.35348 | D36: =D151 -> 5.3485654 | E36: =E151 -> 5.0811371 | F36: =F151 -> 4.8270803 | G36: =G151 -> 4.5857263
A37: 筆電與桌機營收 | B37: NT$B | C37: =C152 -> 6.28452 | D37: =D152 -> 5.7306058 | E37: =E152 -> 5.5586876 | F37: =F152 -> 5.5586876 | G37: =G152 -> 5.5586876
A38: 電競、顯卡與其他營收 | B38: NT$B | C38: =C153 -> 3.72416 | D38: =D153 -> 4.2024443 | E38: =E153 -> 4.2024443 | F38: =F153 -> 4.2024443 | G38: =G153 -> 4.2024443
A39: 液冷 ÷ 營收 | B39: % | C39: =C156 -> 0.34 | D39: =D156 -> 0.6 | E39: =E156 -> 0.70356976 | F39: =F156 -> 0.67062847 | G39: =G156 -> 0.70224288
A40: 毛利率 | B40: % | C40: =C161 -> 0.27375838 | D40: =D161 -> 0.29015649 | E40: =E161 -> 0.29533497 | F40: =F161 -> 0.29368791 | G40: =G161 -> 0.29526863
A41: 營業利益率 | B41: % | C41: =C165 -> 0.14001547 | D41: =D165 -> 0.17488543 | E41: =E165 -> 0.18962516 | F41: =F165 -> 0.17418539 | G41: =G165 -> 0.17914463
A42: 歸屬母公司淨利 | B42: NT$B | C42: =C168 -> 2.572 | D42: =D168 -> 4.9238411 | E42: =E168 -> 7.025957 | F42: =F168 -> 5.7089922 | G42: =G168 -> 6.3874892
A43: EPS | B43: NT$ | C43: =C170 -> 28.26 | D43: =D170 -> 52.900821 | E43: =E170 -> 75.485559 | F43: =F170 -> 61.336336 | G43: =G170 -> 68.62598
A44: EPS 年增 | B44: % | D44: =D171 -> 0.87193281 | E44: =E171 -> 0.42692603 | F44: =F171 -> -0.18744277 | G44: =G171 -> 0.11884707
A46: 核對（應為 0）：FY2026 模型營收 − 錨點；FY2026 模型液冷 − 錨點；FY2026 毛利 − 錨點
A47: 情境 B：營收差（NT$B） | D47: =D116-a26_rev -> 0
A48: 情境 B：液冷差（NT$B） | D48: =D111-a26_lc -> 0
A49: 情境 B：毛利差（NT$B） | D49: =D121*D116+d_lc*D111-a26_gp -> 0
A60: 情境 A（順利）：顆數係數 A＋液冷滲透率高值＋份額相對值高值
A61: 項目 | B61: 單位 | C61: FY2025A | D61: FY2026（錨點） | E61: FY2027 | F61: FY2028 | G61: FY2029 | H61: 說明
A62: A. AI 部署與液冷市場（D 欄＝FY2026 校準年；E–G＝FY2027–FY2029）
A63: AI IT 資本支出 × 情境顆數係數 | B63: US$B | D63: =itc_26*1 -> 781.87292 | E63: =itc_27*1*1 -> 1565.35 | F63: =itc_28*um28_A*1 -> 1984.2639 | G63: =itc_29*um29_A*1 -> 2260.3903
A64: 每 GW IT 資本支出 | B64: US$B | D64: =itpg_gb*(1-vr26)+itpg_vr*vr26 -> 33.414032 | E64: =itpg_vr -> 37.586352 | F64: =itpg_vr -> 37.586352 | G64: =itpg_vr -> 37.586352
A65: 部署 GW（IT 電力） | B65: GW | D65: =D63/D64 -> 23.399538 | E65: =E63/E64 -> 41.646766 | F65: =F63/F64 -> 52.792138 | G65: =G63/G64 -> 60.138592
A66: 液冷滲透率（部署 GW 中液冷占比） | B66: % | D66: =lpenA_26 -> 0.55 | E66: =lpenA_27 -> 0.85 | F66: =lpenA_28 -> 0.95 | G66: =lpenA_29 -> 0.95
A67: 每 GW 液冷內容（機架內液冷＋分歧管；與奇鋐模型同口徑） | B67: US$M/GW | D67: =((1-vr26)*racks_gb*(cool_gb+mani)+vr26*racks_vr*(cool_vr+mani))/1000 -> 350.7208 | E67: =racks_vr*(cool_vr+mani)*lcadj_27/1000 -> 326.5912 | F67: =racks_vr*(cool_vr+mani)*lcadj_28/1000 -> 351.7136 | G67: =racks_vr*(cool_vr+mani)*lcadj_29/1000 -> 351.7136 | H67: 橋接表每架機架內液冷 × 每 GW 機架數；FY2027 起 × 內容調整（Rubin 全液冷、ASIC 液冷）
A68: AI 液冷市場（美元） | B68: US$B | D68: =D65*D66*D67/1000 -> 4.5136876 | E68: =E65*E66*E67/1000 -> 11.561247 | F68: =F65*F66*F67/1000 -> 17.639327 | G68: =G65*G66*G67/1000 -> 20.093983
A69: AI 液冷市場（新台幣） | B69: NT$B | D69: =D68*fx -> 144.438 | E69: =E68*fx -> 369.95991 | F69: =F68*fx -> 564.45847 | G69: =G68*fx -> 643.00744
A70: 雙鴻有效份額（FY2026 校準）＝ 液冷營收 ÷ 市場 | B70: % | D70: =a26_lc/D69 -> 0.15870078 | H70: Derived：分子為券商液冷占比 × 營收（含 CDU、機架分歧管）；分母為機架內液冷＋分歧管市場（不含機架外 CDU）
A71: 份額相對值（÷ FY2026） | B71: x | D71: =1 -> 1 | E71: =relA_27 -> 1.05 | F71: =relA_28 -> 1.05 | G71: =relA_29 -> 1.05
A72: 雙鴻有效份額 | B72: % | D72: =$D$70*D71 -> 0.15870078 | E72: =$D$70*E71 -> 0.16663582 | F72: =$D$70*F71 -> 0.16663582 | G72: =$D$70*G71 -> 0.16663582
A73: 液冷營收 | B73: NT$B | C73: =a25_lc -> 7.91384 | D73: =D69*D72 -> 22.922423 | E73: =E69*E72 -> 61.648571 | F73: =F69*F72 -> 94.058998 | G73: =G69*G72 -> 107.14807
A74: B. 非 AI（伺服器氣冷、筆電與桌機、電競顯卡與其他）與合計
A75: 伺服器氣冷營收（含 AI 氣冷與一般伺服器） | B75: NT$B | C75: =a25_sair -> 5.35348 | D75: =a26_sair -> 5.3485654 | E75: =D75*(1+g_sair_27) -> 5.0811371 | F75: =E75*(1+g_sair_28) -> 4.8270803 | G75: =F75*(1+g_sair_29) -> 4.5857263
A76: 筆電與桌機營收 | B76: NT$B | C76: =a25_nb -> 6.28452 | D76: =a26_nb -> 5.7306058 | E76: =D76*(1+g_nb_27) -> 5.5586876 | F76: =E76*(1+g_nb_28) -> 5.5586876 | G76: =F76*(1+g_nb_29) -> 5.5586876
A77: 電競筆電、顯卡、主機板與其他營收 | B77: NT$B | C77: =a25_oth -> 3.72416 | D77: =a26_oth -> 4.2024443 | E77: =D77*(1+g_oth_27) -> 4.2024443 | F77: =E77*(1+g_oth_28) -> 4.2024443 | G77: =F77*(1+g_oth_29) -> 4.2024443
A78: 營收 | B78: NT$B | C78: =C73+C75+C76+C77 -> 23.276 | D78: =D73+D75+D76+D77 -> 38.204039 | E78: =E73+E75+E76+E77 -> 76.49084 | F78: =F73+F75+F76+F77 -> 108.64721 | G78: =G73+G75+G76+G77 -> 121.49493
A79: 營收年增 | B79: % | D79: =D78/C78-1 -> 0.64134897 | E79: =E78/D78-1 -> 1.0021663 | F79: =F78/E78-1 -> 0.42039505 | G79: =G78/F78-1 -> 0.1182517
A80: 液冷 ÷ 營收 | B80: % | C80: =C73/C78 -> 0.34 | D80: =D73/D78 -> 0.6 | E80: =E73/E78 -> 0.80596018 | F80: =F73/F78 -> 0.86572861 | G80: =G73/G78 -> 0.88191393
A81: 每 GW 雙鴻液冷營收 | B81: US$M/GW | D81: =D73/fx/D65*1000 -> 30.612815 | E81: =E73/fx/E65*1000 -> 46.258522 | F81: =F73/fx/F65*1000 -> 55.677678 | G81: =G73/fx/G65*1000 -> 55.677678
A82: C. 損益
A83: 其他營收毛利率 ＝ 錨點毛利率 − 差距 × 液冷占比（FY2026 校準） | B83: % | D83: =a26_gp/D78-d_lc*D80 -> 0.26015649 | H83: Derived：讓 FY2026 毛利率等於錨點；液冷毛利率＝其他 + 差距。FY2027 起毛利率隨液冷占比變動
A84: 毛利 | B84: NT$B | C84: =a25_gp -> 6.372 | D84: =a26_gp -> 11.08515 | E84: =$D$83*E78+d_lc*E73 -> 22.982017 | F84: =$D$83*F78+d_lc*F73 -> 32.968226 | G84: =$D$83*G78+d_lc*G73 -> 36.965097
A85: 毛利率 | B85: % | C85: =C84/C78 -> 0.27375838 | D85: =D84/D78 -> 0.29015649 | E85: =E84/E78 -> 0.30045449 | F85: =F84/F78 -> 0.30344292 | G85: =G84/G78 -> 0.30425218
A86: 營業費用（基準路徑） | B86: NT$B | C86: =a25_opx -> 3.113 | D86: =a26_opx -> 4.4038197 | E86: =D86*(1+MAX(0,phi*E79)) -> 7.2725036 | F86: =E86*(1+MAX(0,phi*F79)) -> 9.2597645 | G86: =F86*(1+MAX(0,phi*G79)) -> 9.9715033
A87: 營業費用 | B87: NT$B | C87: =C86 -> 3.113 | D87: =D86 -> 4.4038197 | E87: =E86+0*E78 -> 7.2725036 | F87: =F86+0*F78 -> 9.2597645 | G87: =G86+0*G78 -> 9.9715033
A88: 營業利益 | B88: NT$B | C88: =C84-C87 -> 3.259 | D88: =D84-D87 -> 6.6813299 | E88: =E84-E87 -> 15.709513 | F88: =F84-F87 -> 23.708462 | G88: =G84-G87 -> 26.993593
A89: 營業利益率 | B89: % | C89: =C88/C78 -> 0.14001547 | D89: =D88/D78 -> 0.17488543 | E89: =E88/E78 -> 0.2053777 | F89: =F88/F78 -> 0.2182151 | G89: =G88/G78 -> 0.22217877
A90: 業外收益 | B90: NT$B | C90: =a25_nop -> 0.018436 | D90: =a26_nop -> -0.022684 | E90: =nop_f -> 0 | F90: =nop_f -> 0 | G90: =nop_f -> 0
A91: 歸屬母公司淨利 ÷ 稅前 | B91: % | C91: =a25_ni/(a25_oi+a25_nop) -> 0.78475979 | D91: =a26_ni/(a26_oi+a26_nop) -> 0.73946583 | E91: =nir_f -> 0.74 | F91: =nir_f -> 0.74 | G91: =nir_f -> 0.74
A92: 歸屬母公司淨利 | B92: NT$B | C92: =a25_ni -> 2.572 | D92: =a26_ni -> 4.9238411 | E92: =(E88+E90)*E91 -> 11.62504 | F92: =(F88+F90)*F91 -> 17.544262 | G92: =(G88+G90)*G91 -> 19.975259
A93: 股數 | B93: 十億股 | C93: =a25_sh -> 0.091012031 | D93: =a26_sh -> 0.093076837 | E93: =D93*(1+sh_g) -> 0.093076837 | F93: =E93*(1+sh_g) -> 0.093076837 | G93: =F93*(1+sh_g) -> 0.093076837
A94: EPS | B94: NT$ | C94: =C92/C93 -> 28.26 | D94: =D92/D93 -> 52.900821 | E94: =E92/E93 -> 124.89724 | F94: =F92/F93 -> 188.49224 | G94: =G92/G93 -> 214.61042
A95: EPS 年增 | B95: % | D95: =D94/C94-1 -> 0.87193281 | E95: =E94/D94-1 -> 1.3609697 | F95: =F94/E94-1 -> 0.50917865 | G95: =G94/F94-1 -> 0.13856368
A98: 情境 B（平平）：顆數係數 B（CY2028 ×0.8、CY2029 ×0.85）＋基準輸入
A99: 項目 | B99: 單位 | C99: FY2025A | D99: FY2026（錨點） | E99: FY2027 | F99: FY2028 | G99: FY2029 | H99: 說明
A100: A. AI 部署與液冷市場（D 欄＝FY2026 校準年；E–G＝FY2027–FY2029）
A101: AI IT 資本支出 × 情境顆數係數 | B101: US$B | D101: =itc_26*1 -> 781.87292 | E101: =itc_27*1*1 -> 1565.35 | F101: =itc_28*um28_B*1 -> 1587.4111 | G101: =itc_29*um29_B*1 -> 1921.3317
A102: 每 GW IT 資本支出 | B102: US$B | D102: =itpg_gb*(1-vr26)+itpg_vr*vr26 -> 33.414032 | E102: =itpg_vr -> 37.586352 | F102: =itpg_vr -> 37.586352 | G102: =itpg_vr -> 37.586352
A103: 部署 GW（IT 電力） | B103: GW | D103: =D101/D102 -> 23.399538 | E103: =E101/E102 -> 41.646766 | F103: =F101/F102 -> 42.233711 | G103: =G101/G102 -> 51.117803
A104: 液冷滲透率（部署 GW 中液冷占比） | B104: % | D104: =lpenB_26 -> 0.55 | E104: =lpenB_27 -> 0.75 | F104: =lpenB_28 -> 0.85 | G104: =lpenB_29 -> 0.9
A105: 每 GW 液冷內容（機架內液冷＋分歧管；與奇鋐模型同口徑） | B105: US$M/GW | D105: =((1-vr26)*racks_gb*(cool_gb+mani)+vr26*racks_vr*(cool_vr+mani))/1000 -> 350.7208 | E105: =racks_vr*(cool_vr+mani)*lcadj_27/1000 -> 326.5912 | F105: =racks_vr*(cool_vr+mani)*lcadj_28/1000 -> 351.7136 | G105: =racks_vr*(cool_vr+mani)*lcadj_29/1000 -> 351.7136 | H105: 橋接表每架機架內液冷 × 每 GW 機架數；FY2027 起 × 內容調整（Rubin 全液冷、ASIC 液冷）
A106: AI 液冷市場（美元） | B106: US$B | D106: =D103*D104*D105/1000 -> 4.5136876 | E106: =E103*E104*E105/1000 -> 10.2011 | F106: =F103*F104*F105/1000 -> 12.626045 | G106: =G103*G104*G105/1000 -> 16.180944
A107: AI 液冷市場（新台幣） | B107: NT$B | D107: =D106*fx -> 144.438 | E107: =E106*fx -> 326.43521 | F107: =F106*fx -> 404.03343 | G107: =G106*fx -> 517.7902
A108: 雙鴻有效份額（FY2026 校準）＝ 液冷營收 ÷ 市場 | B108: % | D108: =a26_lc/D107 -> 0.15870078 | H108: Derived：分子為券商液冷占比 × 營收（含 CDU、機架分歧管）；分母為機架內液冷＋分歧管市場（不含機架外 CDU）
A109: 份額相對值（÷ FY2026） | B109: x | D109: =1 -> 1 | E109: =relB_27 -> 0.95 | F109: =relB_28 -> 0.9 | G109: =relB_29 -> 0.85
A110: 雙鴻有效份額 | B110: % | D110: =$D$108*D109 -> 0.15870078 | E110: =$D$108*E109 -> 0.15076574 | F110: =$D$108*F109 -> 0.1428307 | G110: =$D$108*G109 -> 0.13489566
A111: 液冷營收 | B111: NT$B | C111: =a25_lc -> 7.91384 | D111: =D107*D110 -> 22.922423 | E111: =E107*E110 -> 49.215246 | F111: =F107*F110 -> 57.708378 | G111: =G107*G110 -> 69.847651
A112: B. 非 AI（伺服器氣冷、筆電與桌機、電競顯卡與其他）與合計
A113: 伺服器氣冷營收（含 AI 氣冷與一般伺服器） | B113: NT$B | C113: =a25_sair -> 5.35348 | D113: =a26_sair -> 5.3485654 | E113: =D113*(1+g_sair_27) -> 5.0811371 | F113: =E113*(1+g_sair_28) -> 4.8270803 | G113: =F113*(1+g_sair_29) -> 4.5857263
A114: 筆電與桌機營收 | B114: NT$B | C114: =a25_nb -> 6.28452 | D114: =a26_nb -> 5.7306058 | E114: =D114*(1+g_nb_27) -> 5.5586876 | F114: =E114*(1+g_nb_28) -> 5.5586876 | G114: =F114*(1+g_nb_29) -> 5.5586876
A115: 電競筆電、顯卡、主機板與其他營收 | B115: NT$B | C115: =a25_oth -> 3.72416 | D115: =a26_oth -> 4.2024443 | E115: =D115*(1+g_oth_27) -> 4.2024443 | F115: =E115*(1+g_oth_28) -> 4.2024443 | G115: =F115*(1+g_oth_29) -> 4.2024443
A116: 營收 | B116: NT$B | C116: =C111+C113+C114+C115 -> 23.276 | D116: =D111+D113+D114+D115 -> 38.204039 | E116: =E111+E113+E114+E115 -> 64.057515 | F116: =F111+F113+F114+F115 -> 72.29659 | G116: =G111+G113+G114+G115 -> 84.194509
...

Sheet Val
A1: Val — P/E 估值（新台幣）。目標價＝DCF 與 Comparable 加權（第 0 節）；另列「現價 ÷ FY2027、FY2028 EPS（模型）」與十年 P/E 規則值（年底落後 P/E，基準為 FY2027 EPS；參考，不是目標價）
A2: 循環位置：雙鴻不是設備股，不套設備市場見頂年；以本模型營收最高的會計年度為見頂年（比照奇鋐、台達電；FY(t)＝CY(t)）。營收到 FY2029 仍在增加時，見頂年未知，判為中段
A3: 目標價：見第 0 節（本頁第 4 列起）。第 3 節與第 6 節「規則值」保留給 AI 投資地圖抽數，不是目標價
A4: 0. 目標價
A5: 0.1 DCF（股東權益現金流，FY2027–FY2032 明確期＋FY2032 後永續）
A6: 項目 | B6: A（順利） | C6: B（平平） | D6: C（不如預期） | E6: 說明
A7: 情境 EPS（FY2027–FY2032） | E7: PL 頁延伸表；FY2030 起為收斂法
A8: FY2027 | B8: =PL!E182 -> 124.89724 | C8: =PL!E194 -> 101.64468 | D8: =PL!E206 -> 75.485559
A9: FY2028 | B9: =PL!F182 -> 188.49224 | C9: =PL!F194 -> 117.84752 | D9: =PL!F206 -> 61.336336
A10: FY2029 | B10: =PL!G182 -> 214.61042 | C10: =PL!G194 -> 141.43866 | D10: =PL!G206 -> 68.62598
A11: FY2030 | B11: =PL!H182 -> 235.82133 | C11: =PL!H194 -> 146.83164 | D11: =PL!H206 -> 64.437819
A12: FY2031 | B12: =PL!I182 -> 254.5496 | C12: =PL!I194 -> 145.81206 | D12: =PL!I206 -> 58.149113
A13: FY2032 | B13: =PL!J182 -> 269.82258 | C13: =PL!J194 -> 138.13513 | D13: =PL!J206 -> 50.096039
A14: 股東現金流＝EPS ×（1 − tp_g ÷ tp_roe）
A15: 再投資率（tp_g ÷ tp_roe，上限 0.8） | B15: =MIN(tp_g/tp_roe,0.8) -> 0.17286085 | E15: ROE 為近三年平均（In 頁 tp_roe）；本模型未建資本支出與折舊，用 g／ROE
A16: FY2027 | B16: =B8*(1-$B$15) -> 103.30739 | C16: =C8*(1-$B$15) -> 84.074296 | D16: =D8*(1-$B$15) -> 62.437061
A17: FY2028 | B17: =B9*(1-$B$15) -> 155.90931 | C17: =C9*(1-$B$15) -> 97.476301 | D17: =D9*(1-$B$15) -> 50.733685
A18: FY2029 | B18: =B10*(1-$B$15) -> 177.51268 | C18: =C10*(1-$B$15) -> 116.98945 | D18: =D10*(1-$B$15) -> 56.763235
A19: FY2030 | B19: =B11*(1-$B$15) -> 195.05705 | C19: =C11*(1-$B$15) -> 121.4502 | D19: =D11*(1-$B$15) -> 53.299043
A20: FY2031 | B20: =B12*(1-$B$15) -> 210.54794 | C20: =C12*(1-$B$15) -> 120.60687 | D20: =D12*(1-$B$15) -> 48.097408
A21: FY2032 | B21: =B13*(1-$B$15) -> 223.18082 | C21: =C13*(1-$B$15) -> 114.25697 | D21: =D13*(1-$B$15) -> 41.436395
A22: DCF 情境每股價值（折現率 tp_r） | B22: =MAX(0,SUMPRODUCT(B16:B21,1/(1+tp_r)^{1;2;3;4;5;6})+B21*(1+tp_g)/(tp_r-tp_g)/(1+tp_r)^6) -> 2929.7235 | C22: =MAX(0,SUMPRODUCT(C16:C21,1/(1+tp_r)^{1;2;3;4;5;6})+C21*(1+tp_g)/(tp_r-tp_g)/(1+tp_r)^6) -> 1585.1354 | D22: =MAX(0,SUMPRODUCT(D16:D21,1/(1+tp_r)^{1;2;3;4;5;6})+D21*(1+tp_g)/(tp_r-tp_g)/(1+tp_r)^6) -> 636.41771 | E22: Σ 明確期現金流 ÷ (1＋r)^t ＋ 永續價值 ÷ (1＋r)^6；永續價值＝FY2032 現金流 ×(1＋g)÷(r−g)；基準日 2026 年底；負值取 0（Andy 12:22）
A23: DCF 情境價值推到 12 個月後（×(1＋tp_r)） | B23: =B22*(1+tp_r) -> 3222.6959 | C23: =C22*(1+tp_r) -> 1743.6489 | D23: =D22*(1+tp_r) -> 700.05948
A24: DCF 目標價（情境加權） | B24: =tp_wA*B23+tp_wB*C23+tp_wC*D23 -> 1978.6451 | E24: Σ 權重 × 情境價值 ×(1＋r)；權重見 In 頁
A26: 0.2 Comparable（市場主流同業前瞻 P/E；非 A 股公司，同業不放 A 股）
A27: 同業與前瞻 P/E | B27: 代號 | C27: 前瞻 12 月 P/E | D27: 日期 | E27: 來源 | F27: 標記
A28: 奇鋐（AVC） | B28: 3017.TW | C28: 27.04 | D28: 2026-10-05 | E28: stockanalysis.com 個股頁 Forward PE（分析師共識；價格日期如左，臺股頁面為快取日期） | F28: Interested-party（賣方共識）
A29: 健策（Jentech） | B29: 3653.TW | C29: 59.27 | D29: 2026-08-27 | E29: stockanalysis.com 個股頁 Forward PE（分析師共識；價格日期如左，臺股頁面為快取日期） | F29: Interested-party（賣方共識）
A30: Vertiv | B30: VRT | C30: 24.53 | D30: 2026-10-23 | E30: stockanalysis.com 個股頁 Forward PE（分析師共識；價格日期如左，臺股頁面為快取日期） | F30: Interested-party（賣方共識）
A31: 台達電（Delta） | B31: 2308.TW | C31: 30.51 | D31: 2026-10-22 | E31: stockanalysis.com 個股頁 Forward PE（分析師共識；價格日期如左，臺股頁面為快取日期） | F31: Interested-party（賣方共識）
A32: 並列參考（不進目標價）：無。英維克（002837.SZ）為 A 股，依規則不列；酷碼（Cooler Master）、Boyd、CoolIT 未上市
A33: 同業前瞻 P/E 中位數 | B33: =MEDIAN(C28:C31) -> 28.775 | E33: 散熱與液冷同業：奇鋐、健策、Vertiv、台達電（與奇鋐模型同一比較組，雙鴻換成奇鋐）；非 A 股公司的同業名單不放中國 A 股（Andy 2026-10-25 11:53）
A34: 12 個月後的前瞻 EPS（情境加權） | B34: =tp_wA*(2/12*B8+10/12*B9)+tp_wB*(2/12*C8+10/12*C9)+tp_wC*(2/12*D8+10/12*D9) -> 123.68036 | E34: 約 2027-10 時的未來 12 月 EPS ≈ 2／12 × FY2027＋10／12 × FY2028（會計年度＝日曆年）
A35: Comparable 目標價 | B35: =B33*B34 -> 3558.9022 | E35: 同業中位數 × 上列 EPS
A37: 0.3 結論
A38: 項目 | B38: 數值 | E38: 說明
A39: 目標價（DCF 與 Comparable 加權） | B39: =tp_w_dcf*B24+(1-tp_w_dcf)*tp_comp_adj -> 2290.2186 | E39: tp_w_dcf × DCF＋（1 − tp_w_dcf）× Comparable；tp_w_dcf 見 In 頁
A40: Comparable 目標價（市場主流同業法） | B40: =B35 -> 3558.9022 | E40: 引用 0.2
A41: 市場共識目標價 | B41: =cons_tp -> 1523 | E41: stockanalysis（S&P Global）：17 位分析師平均 1,523、中位數 1,550（頁面時間 2026-10-19）
A42: 上檔空間：加權目標價 | B42: =B39/px-1 -> 0.68398427 | E42: 現價＝In 頁 px（2026-10-22 收盤 1,360）
A43: 上檔空間：Comparable 目標價 | B43: =B40/px-1 -> 1.6168399
A44: 與市場共識目標價的差距：EPS 因素 | B44: =B34/cons_feps-1 -> 0.66374937 | E44: 本模型前瞻 EPS ÷ 共識前瞻 EPS − 1；共識前瞻 EPS＝2／12 × FY2026＋10／12 × FY2027 共識（In 頁 cons_feps；期間為現在起算 12 個月，與本模型不同）
A45: 與市場共識目標價的差距：倍數因素 | B45: =(cons_tp/cons_feps)/B33-1 -> -0.28801351 | E45: ="共識目標價 ÷ 共識前瞻 EPS 隱含 "&TEXT(cons_tp/cons_feps,"0.0")&"x，同業中位數 "&TEXT(B33,"0.0")&"x" -> 共識目標價 ÷ 共識前瞻 EPS 隱含 20.5x，同業中位數 28.8x
A46: 價格帶（DCF 不如預期～順利） | B46: =TEXT(D23,"#,##0")&"～"&TEXT(B23,"#,##0") -> 700～3,223 | E46: C 情境價值～A 情境價值（推到 12 個月後）
A47: 歷史倍數檢查：現價隱含 P/E 的十年分位（A／B／C） | B47: =IF(px/B9<MIN($B$99:$B$108),0,IF(px/B9>MAX($B$99:$B$108),1,PERCENTRANK($B$99:$B$108,px/B9))) -> 0 | C47: =IF(px/C9<MIN($B$99:$B$108),0,IF(px/C9>MAX($B$99:$B$108),1,PERCENTRANK($B$99:$B$108,px/C9))) -> 0.0343 | D47: =IF(px/D9<MIN($B$99:$B$108),0,IF(px/D9>MAX($B$99:$B$108),1,PERCENTRANK($B$99:$B$108,px/D9))) -> 0.559 | E47: 現價 ÷ 各情境 FY2028 EPS 在 2017–2025 年底 P/E（第 6 節 Goodinfo；2016 年未找到）的分位；低於最小值記 0%、高於最大值記 100%；只作檢查，不進目標價
A48: 目標價方法 | B48: DCF：股東現金流＝歸母 EPS ×（1 − g／ROE），r＝10%、g＝4%、ROE 為近三年平均約 23%（再投資率約 17%），FY2027–29 驅動因子、FY2030–32 收斂法＋永續；本模型未建資本支出與折舊（泰國、越南擴產期），未改用淨利＋折舊－資本支出，現金流可能偏高估。Comparable：奇鋐、健策、Vertiv、台達電前瞻 P/E 中位數（臺美同業，不放 A 股）；健策倍數高（約 59x）、雙鴻自身前瞻 P/E 約 17x，同業倍數分散，中位數可能高估雙鴻的市場倍數。情境對應：A＝順利（顆數基準、滲透率與份額高值）、B＝平平（顆數 ×0.8／0.85、基準）、C＝不如預期（顆數 ×0.6、低值）
A60: 1. 價格與市場隱含倍數
A61: 項目 | B61: A | C61: B | D61: C | E61: 說明
A62: 現價（2026-10-22 收盤） | B62: =px -> 1360
A63: 現價 ÷ FY2026 EPS（錨點） | B63: =px/PL!D15 -> 25.708486 | C63: =px/PL!D29 -> 25.708486 | D63: =px/PL!D43 -> 25.708486
A64: 現價 ÷ FY2027 EPS（模型） | B64: =px/PL!E15 -> 10.888952 | C64: =px/PL!E29 -> 13.379942 | D64: =px/PL!E43 -> 18.016691
A65: 現價 ÷ FY2028 EPS（模型） | B65: =px/PL!F15 -> 7.215151 | C65: =px/PL!F29 -> 11.540336 | D65: =px/PL!F43 -> 22.172827
A66: 現價 ÷ FY2029 EPS（模型） | B66: =px/PL!G15 -> 6.3370641 | C66: =px/PL!G29 -> 9.6154757 | D66: =px/PL!G43 -> 19.817568
A67: 未來 12 月 EPS（模型 B）≈ 2／12 × FY2026＋10／12 × FY2027 | B67: =2/12*PL!D29+10/12*PL!E29 -> 93.520705
A68: 現價 ÷ 未來 12 月 EPS（模型 B） | B68: =px/B67 -> 14.542234
A69: 近 12 月 P/E（3Q25–2Q26 EPS，10-22） | B69: =px/eps_ttm -> 31.000684
A70: 前瞻 P/E（stockanalysis，2026-08-28；價格 1,140） | B70: 17.27 | E70: Interested-party（賣方共識）；10 月價格下的前瞻 P/E：未找到
A72: 2. 循環位置（本模型營收最高年；FY(t)＝CY(t)）
A73: 情境 | B73: 營收最高年（FY2026–FY2029） | C73: FY2027 判定 | D73: 規則倍數（P/E） | E73: 見頂年是否未知 | F73: 說明
A74: A | B74: =INDEX({2026,2027,2028,2029},MATCH(MAX(PL!D78:G78),PL!D78:G78,0)) -> 2029 | C74: =IF(B74=2029,"中段",IF(2027<B74,"中段",IF(2027=B74,"見頂","谷底"))) -> 中段 | D74: =IF(C74="見頂",pe_peak,IF(C74="谷底",pe_trough,pe_mid)) -> 19.95 | E74: =IF(B74=2029,"是：營收到觀測期末仍在增加","否") -> 是：營收到觀測期末仍在增加 | F74: tools/cycle_position.py excel_rule；營收最高年取代設備市場見頂年
A75: B | B75: =INDEX({2026,2027,2028,2029},MATCH(MAX(PL!D116:G116),PL!D116:G116,0)) -> 2029 | C75: =IF(B75=2029,"中段",IF(2027<B75,"中段",IF(2027=B75,"見頂","谷底"))) -> 中段 | D75: =IF(C75="見頂",pe_peak,IF(C75="谷底",pe_trough,pe_mid)) -> 19.95 | E75: =IF(B75=2029,"是：營收到觀測期末仍在增加","否") -> 是：營收到觀測期末仍在增加 | F75: 同上
A76: C | B76: =INDEX({2026,2027,2028,2029},MATCH(MAX(PL!D154:G154),PL!D154:G154,0)) -> 2027 | C76: =IF(B76=2029,"中段",IF(2027<B76,"中段",IF(2027=B76,"見頂","谷底"))) -> 見頂 | D76: =IF(C76="見頂",pe_peak,IF(C76="谷底",pe_trough,pe_mid)) -> 16.61 | E76: =IF(B76=2029,"是：營收到觀測期末仍在增加","否") -> 否 | F76: 同上
A78: 3. 規則值隱含股價（新台幣；約 FY2027 年底，未折現）＝ FY2027 EPS × 規則倍數（參考，不是目標價）
A79: 情境 | B79: FY2027 EPS | C79: （同左） | D79: 規則倍數 | E79: 隱含股價 | F79: 相對現價 | G79: 現價 ÷ FY2027 EPS
A80: A | B80: =PL!E15 -> 124.89724 | C80: =B80 -> 124.89724 | D80: =D74 -> 19.95 | E80: =C80*D80 -> 2491.6999 | F80: =E80/px-1 -> 0.83213225 | G80: =px/C80 -> 10.888952
A81: B | B81: =PL!E29 -> 101.64468 | C81: =B81 -> 101.64468 | D81: =D75 -> 19.95 | E81: =C81*D81 -> 2027.8114 | F81: =E81/px-1 -> 0.4910378 | G81: =px/C81 -> 13.379942
A82: C | B82: =PL!E43 -> 75.485559 | C82: =B82 -> 75.485559 | D82: =D76 -> 16.61 | E82: =C82*D82 -> 1253.8151 | F82: =E82/px-1 -> -0.078077112 | G82: =px/C82 -> 18.016691
A84: 4. What must be true：FY2027 年底價 ＝ 現價 ×（1＋報酬）所需的倍數（FY2028 EPS；約 2027 年底的價格看下一年 EPS）
A85: FY2027 年底價 ÷ 現價 | B85: 所需倍數（÷ FY2028 EPS，A） | C85: 所需倍數（÷ FY2028 EPS，C） | D85: 對照：十年中位數 | E85: 對照：十年 75 分位
A86: 1 | B86: =px*A86/PL!F15 -> 7.215151 | C86: =px*A86/PL!F43 -> 22.172827 | D86: =pe_mid -> 19.95 | E86: =pe_trough -> 31.65
A87: 1.1 | B87: =px*A87/PL!F15 -> 7.9366661 | C87: =px*A87/PL!F43 -> 24.39011 | D87: =pe_mid -> 19.95 | E87: =pe_trough -> 31.65
A88: 1.21 | B88: =px*A88/PL!F15 -> 8.7303328 | C88: =px*A88/PL!F43 -> 26.829121 | D88: =pe_mid -> 19.95 | E88: =pe_trough -> 31.65
A89: 1.5 | B89: =px*A89/PL!F15 -> 10.822727 | C89: =px*A89/PL!F43 -> 33.259241 | D89: =pe_mid -> 19.95 | E89: =pe_trough -> 31.65
A90: 2 | B90: =px*A90/PL!F15 -> 14.430302 | C90: =px*A90/PL!F43 -> 44.345655 | D90: =pe_mid -> 19.95 | E90: =pe_trough -> 31.65
A91: 讀法：1.00＝價格不變、1.21＝一年約 21%。所需倍數低於歷史中位數時，現價相對便宜；倍數是否合理，另看前瞻 P/E 歷史（Bloomberg）。本版未做先驗，無 Andy 合理 P/E 對照。
A94: 6. 十年倍數與規則值（2016–2025 年底；見頂年 25 分位、中段中位數、谷底 75 分位）
A95: 規則（Andy 2026-10-13）：合理倍數＝2016–2025 年底 P/E 依循環位置取分位。採用 Goodinfo 年底收盤 ÷ 當年 EPS（9 年；2016 年未找到）；stockanalysis 只有 2021–2025，只作核對。2017–2022 年雙鴻為筆電、顯卡與伺服器氣冷散熱廠（約 10–34x，2018 年 EPS 低使倍數偏高），AI 前後的倍數口徑不同。
A97: P/E：十年歷史倍數
A98: 年底 | B98: Goodinfo（年底收盤 ÷ 當年 EPS） | C98: stockanalysis（年底 P/E） | D98: 標記／說明
A99: 2016 | D99: Goodinfo（年底收盤 ÷ 當年 EPS）：Derived（資料商年底收盤與 EPS；2017–2025 共 9 年，2016 年未找到）；stockanalysis（年底 P/E）：Interested-party（資料商；只有 2021–2025，只作核對、不採用）
A100: 2017 | B100: =73/3.66 -> 19.945355 | D100: stockanalysis 2021–2025 與 Goodinfo 推導差距在 0.4x 內；HiStock 12 月 P/E（近 4 季 EPS）2021–2025：17.2、9.1、25.7、37.2、44.0
A101: 2018 | B101: =97.9/2.9 -> 33.758621
A102: 2019 | B102: =220/11.71 -> 18.787361
A103: 2020 | B103: =214/12.88 -> 16.614907
A104: 2021 | B104: =202/13.12 -> 15.396341 | C104: 15.35
A105: 2022 | B105: =148/14.68 -> 10.081744 | C105: 10.08
A106: 2023 | B106: =352.5/14.28 -> 24.684874 | C106: 24.65
A107: 2024 | B107: =672/21.23 -> 31.653321 | C107: 31.96
A108: 2025 | B108: =1010/28.26 -> 35.739561 | C108: 35.83
A109: 25 分位（各來源） | B109: =PERCENTILE(B99:B108,0.25) -> 16.614907 | C109: =PERCENTILE(C99:C108,0.25) -> 15.35
A110: 中位數（各來源） | B110: =MEDIAN(B99:B108) -> 19.945355 | C110: =MEDIAN(C99:C108) -> 24.65
A111: 75 分位（各來源） | B111: =PERCENTILE(B99:B108,0.75) -> 31.653321 | C111: =PERCENTILE(C99:C108,0.75) -> 31.96
A112: 最小（各來源） | B112: =MIN(B99:B108) -> 10.081744 | C112: =MIN(C99:C108) -> 10.08
A113: 最大（各來源） | B113: =MAX(B99:B108) -> 35.739561 | C113: =MAX(C99:C108) -> 35.83
A114: 採用 25 分位（P/E） | B114: =ROUND(AVERAGE(B109),2) -> 16.61
A115: 採用 中位數（P/E） | B115: =ROUND(AVERAGE(B110),2) -> 19.95
A116: 採用 75 分位（P/E） | B116: =ROUND(AVERAGE(B111),2) -> 31.65
A117: 採用 最小（P/E） | B117: =ROUND(MIN(B112),2) -> 10.08
A118: 採用 最大（P/E） | B118: =ROUND(MAX(B113),2) -> 35.74
A120: P/E：規則值
...

Sheet Recon
A1: Recon — 本模型 vs 共識、券商估計與奇鋐模型的份額（兩家份額合計檢查）。只作事後對照，不為對上數字而調參數。共識取自 stockanalysis（S&P Global）；券商多經媒體轉述
A3: 項目 | B3: 對照值 | C3: 模型 A | D3: 差距 A | E3: 模型 B | F3: 差距 B | G3: 模型 C | H3: 差距 C | I3: 對照來源 | J3: 說明
A4: A. 共識與券商估計（校準未使用）
A5: FY2026 營收 vs 共識（stockanalysis） | B5: =c_rev26 -> 38.7 | C5: =PL!D78 -> 38.204039 | D5: =C5/B5-1 -> -0.012815539 | E5: =PL!D116 -> 38.204039 | F5: =E5/B5-1 -> -0.012815539 | G5: =PL!D154 -> 38.204039 | H5: =G5/B5-1 -> -0.012815539 | I5: stockanalysis（2026-10-19） | J5: 區間 375–399 億
A6: FY2026 營收 vs 凱基（08-07，3Q 前） | B6: =b_rev26 -> 39.016 | C6: =PL!D78 -> 38.204039 | D6: =C6/B6-1 -> -0.020810984 | E6: =PL!D116 -> 38.204039 | F6: =E6/B6-1 -> -0.020810984 | G6: =PL!D154 -> 38.204039 | H6: =G6/B6-1 -> -0.020810984 | I6: 凱基 2026-08-07 | J6: 凱基 3Q 估 102.7 億，實際 97.9 億
A7: FY2026 EPS vs 共識（stockanalysis） | B7: =c_eps26 -> 56.18 | C7: =PL!D94 -> 52.900821 | D7: =C7/B7-1 -> -0.058369148 | E7: =PL!D132 -> 52.900821 | F7: =E7/B7-1 -> -0.058369148 | G7: =PL!D170 -> 52.900821 | H7: =G7/B7-1 -> -0.058369148 | I7: stockanalysis（2026-10-19） | J7: 3Q26 財報前
A8: FY2026 EPS vs 凱基（08-07） | B8: =b_eps26 -> 55.69 | C8: =PL!D94 -> 52.900821 | D8: =C8/B8-1 -> -0.050084014 | E8: =PL!D132 -> 52.900821 | F8: =E8/B8-1 -> -0.050084014 | G8: =PL!D170 -> 52.900821 | H8: =G8/B8-1 -> -0.050084014 | I8: 凱基 2026-08-07
A9: FY2026 EPS vs 美系券商（09-18） | B9: =u_eps26 -> 58.8 | C9: =PL!D94 -> 52.900821 | D9: =C9/B9-1 -> -0.10032617 | E9: =PL!D132 -> 52.900821 | F9: =E9/B9-1 -> -0.10032617 | G9: =PL!D170 -> 52.900821 | H9: =G9/B9-1 -> -0.10032617 | I9: 經濟日報 2026-09-18
A10: FY2027 營收 vs 共識（stockanalysis） | B10: =c_rev27 -> 49.1 | C10: =PL!E78 -> 76.49084 | D10: =C10/B10-1 -> 0.55785825 | E10: =PL!E116 -> 64.057515 | F10: =E10/B10-1 -> 0.3046337 | G10: =PL!E154 -> 50.070024 | H10: =G10/B10-1 -> 0.019756087 | I10: stockanalysis（2026-10-19）
A11: FY2027 營收 vs 凱基（08-07） | B11: =b_rev27 -> 50.486 | C11: =PL!E78 -> 76.49084 | D11: =C11/B11-1 -> 0.51509012 | E11: =PL!E116 -> 64.057515 | F11: =E11/B11-1 -> 0.26881739 | G11: =PL!E154 -> 50.070024 | H11: =G11/B11-1 -> -0.0082394355 | I11: 凱基 2026-08-07
A12: FY2027 EPS vs 共識（stockanalysis） | B12: =c_eps27 -> 77.97 | C12: =PL!E94 -> 124.89724 | D12: =C12/B12-1 -> 0.60186272 | E12: =PL!E132 -> 101.64468 | F12: =E12/B12-1 -> 0.30363835 | G12: =PL!E170 -> 75.485559 | H12: =G12/B12-1 -> -0.031864068 | I12: stockanalysis（2026-10-19）
A13: FY2027 EPS vs 凱基（08-07） | B13: =b_eps27 -> 81.55 | C13: =PL!E94 -> 124.89724 | D13: =C13/B13-1 -> 0.53154183 | E13: =PL!E132 -> 101.64468 | F13: =E13/B13-1 -> 0.24640934 | G13: =PL!E170 -> 75.485559 | H13: =G13/B13-1 -> -0.074364701 | I13: 凱基 2026-08-07
A14: FY2027 EPS vs 美系券商（09-18） | B14: =u_eps27 -> 89 | C14: =PL!E94 -> 124.89724 | D14: =C14/B14-1 -> 0.40333973 | E14: =PL!E132 -> 101.64468 | F14: =E14/B14-1 -> 0.14207508 | G14: =PL!E170 -> 75.485559 | H14: =G14/B14-1 -> -0.15184766 | I14: 經濟日報 2026-09-18
A15: FY2028 EPS vs 美系券商（09-18） | B15: =u_eps28 -> 110 | C15: =PL!F94 -> 188.49224 | D15: =C15/B15-1 -> 0.71356584 | E15: =PL!F132 -> 117.84752 | F15: =E15/B15-1 -> 0.071341126 | G15: =PL!F170 -> 61.336336 | H15: =G15/B15-1 -> -0.44239694 | I15: 經濟日報 2026-09-18 | J15: FY2028 共識：未找到
A16: B. 液冷結構與兩家份額合計（機制檢查）
A17: FY2027 液冷 ÷ 營收 vs 凱基（72%） | B17: =b_lc27 -> 0.72 | C17: =PL!E80 -> 0.80596018 | D17: =C17-B17 -> 0.085960178 | E17: =PL!E118 -> 0.76829777 | F17: =E17-B17 -> 0.04829777 | G17: =PL!E156 -> 0.70356976 | H17: =G17-B17 -> -0.016430236 | I17: 凱基 2026-08-07
A18: FY2026 雙鴻有效份額（本模型市場口徑） | C18: =PL!D70 -> 0.15870078 | E18: =PL!D108 -> 0.15870078 | G18: =PL!D146 -> 0.15870078 | I18: — | J18: 份額第二來源：未找到
A19: CY2026 兩家有效份額合計（奇鋐＋雙鴻） | C19: =avsh_26+PL!D72 -> 0.65762842 | E19: =avsh_26+PL!D110 -> 0.65762842 | G19: =avsh_26+PL!D148 -> 0.65762842 | I19: 奇鋐模型 Units（唯讀）＋本模型 | J19: 奇鋐三情境份額相同（只讀其值）；兩家分子都含 CDU 等機架外產品，合計偏高估冷板份額。超過八成應視為不合理
A20: CY2027 兩家有效份額合計（奇鋐＋雙鴻） | C20: =avsh_27+PL!E72 -> 0.64061707 | E20: =avsh_27+PL!E110 -> 0.624747 | G20: =avsh_27+PL!E148 -> 0.60887692 | I20: 奇鋐模型 Units（唯讀）＋本模型 | J20: —
A21: CY2028 兩家有效份額合計（奇鋐＋雙鴻） | C21: =avsh_28+PL!F72 -> 0.61567069 | E21: =avsh_28+PL!F110 -> 0.59186558 | G21: =avsh_28+PL!F148 -> 0.56806046 | I21: 奇鋐模型 Units（唯讀）＋本模型 | J21: —
A22: CY2029 兩家有效份額合計（奇鋐＋雙鴻） | C22: =avsh_29+PL!G72 -> 0.59072431 | E22: =avsh_29+PL!G110 -> 0.55898415 | G22: =avsh_29+PL!G148 -> 0.53517904 | I22: 奇鋐模型 Units（唯讀）＋本模型 | J22: —
A23: FY2027 每 GW 雙鴻液冷營收（US$M） | C23: =PL!E81 -> 46.258522 | E23: =PL!E119 -> 36.929072 | G23: =PL!E157 -> 26.433441 | I23: —
A24: C. 校準
A25: 其他營收毛利率（Derived） | C25: =PL!D83 -> 0.26015649 | E25: =PL!D121 -> 0.26015649 | G25: =PL!D159 -> 0.26015649 | I25: FY2026 錨點 | J25: 液冷毛利率＝此值＋d_lc
A26: FY2027 毛利率 vs FY2026（百分點） | B26: =a26_gp/a26_rev -> 0.29015649 | C26: =PL!E85 -> 0.30045449 | D26: =C26-B26 -> 0.010298009 | E26: =PL!E123 -> 0.29857137 | F26: =E26-B26 -> 0.0084148885 | G26: =PL!E161 -> 0.29533497 | H26: =G26-B26 -> 0.0051784882 | I26: 錨點 | J26: 液冷占比上升使毛利率上升
A27: 4Q26 EPS（模型） | C27: =Q!E15 -> 15.972929 | E27: =Q!E15 -> 15.972929 | G27: =Q!E15 -> 15.972929 | I27: — | J27: 凱基 08-07 估 17.83（以 4Q 營收 115.0 億為基礎）
A28: D. 目標價對帳（模型欄為情境加權值，非情境 A）
A29: 12 個月後的前瞻 EPS（情境加權）vs 共識前瞻 EPS | B29: =cons_feps -> 74.338333 | C29: =Val!B34 -> 123.68036 | D29: =C29/B29-1 -> 0.66374937 | I29: stockanalysis 共識（期間不同） | J29: 共識只作對帳，不作校準
A30: 目標價（DCF 與 Comparable 加權）vs 市場共識目標價 | B30: =cons_tp -> 1523 | C30: =Val!B39 -> 2290.2186 | D30: =C30/B30-1 -> 0.50375483 | I30: stockanalysis（2026-10-19） | J30: 共識只作對帳，不作校準
A31: Comparable 目標價 vs 市場共識目標價 | B31: =cons_tp -> 1523 | C31: =Val!B35 -> 3558.9022 | D31: =C31/B31-1 -> 1.336771 | I31: 同上 | J31: 共識只作對帳，不作校準
A32: E. 預留
A33: R4 產業部署路徑（markets/deploy_path/，尚未建立）：上線後以部署路徑取代「AI IT 資本支出 ÷ 每 GW IT 資本支出」 | J33: 預留列：本版無數值

Sheet Sens
A1: Sens — 一次動一個輸入（情境 B＝基準輸入；有效份額、其他營收毛利率在每個案例內依 FY2026 錨點重算，FY2026 恆等於錨點）：對 FY2027、FY2028 的營收、液冷營收、毛利率與 EPS 的影響。每個案例是一個完整推導區塊（本頁下方）
A3: 案例 | B3: 設定 | C3: FY2027 營收 | D3: FY2027 液冷營收 | E3: FY2027 毛利率 | F3: FY2027 EPS | G3: FY2027 EPS 相對基準 | H3: FY2028 營收 | I3: FY2028 液冷營收 | J3: FY2028 毛利率 | K3: FY2028 EPS | L3: FY2028 EPS 相對基準
A4: 基準（情境 B） | B4: PL 區塊 B | C4: =PL!E116 -> 64.057515 | D4: =PL!E111 -> 49.215246 | E4: =PL!E123 -> 0.29857137 | F4: =PL!E132 -> 101.64468 | G4: =F4/F$4-1 -> 0 | H4: =PL!F116 -> 72.29659 | I4: =PL!F111 -> 57.708378 | J4: =PL!F123 -> 0.30006734 | K4: =PL!F132 -> 117.84752 | L4: =K4/K$4-1 -> 0
A5: 份額流失（低） | B5: 份額相對值 2027 0.85、2028 0.75、2029 0.70（＝情境 C 的份額） | C5: =E68 -> 58.876963 | D5: =E63 -> 44.034694 | E5: =E75 -> 0.29755201 | F5: =E84 -> 91.956118 | G5: =F5/F$4-1 -> -0.095317965 | H5: =F68 -> 62.678527 | I5: =F63 -> 48.090315 | J5: =F75 -> 0.29851916 | K5: =F84 -> 99.445018 | L5: =K5/K$4-1 -> -0.15615522
A6: 份額上升（高） | B6: 份額相對值 1.05（＝情境 A 的份額） | C6: =E106 -> 69.238067 | D6: =E101 -> 54.395798 | E6: =E113 -> 0.2994382 | F6: =E122 -> 111.33325 | G6: =F6/F$4-1 -> 0.095317965 | H6: =F106 -> 81.914653 | I6: =F101 -> 67.326441 | J6: =F113 -> 0.30125197 | K6: =F122 -> 136.32638 | L6: =K6/K$4-1 -> 0.15680307
A7: 每架液冷內容 低 | B7: 內容調整 1.0（只有橋接表的機架內液冷） | C7: =E144 -> 52.70015 | D7: =E139 -> 37.857881 | E7: =E151 -> 0.29607468 | F7: =E160 -> 80.404368 | G7: =F7/F$4-1 -> -0.20896631 | H7: =F144 -> 55.808482 | I7: =F139 -> 41.22027 | J7: =F151 -> 0.2970866 | K7: =F160 -> 86.496762 | L7: =K7/K$4-1 -> -0.26602817
A8: 每架液冷內容 高 | B8: 內容調整 2027 1.6、2028–29 1.8 | C8: =E182 -> 75.414879 | D8: =E177 -> 60.57261 | E8: =E189 -> 0.30031607 | F8: =E198 -> 122.885 | G8: =F8/F$4-1 -> 0.20896631 | H8: =F182 -> 88.784698 | I8: =F177 -> 74.196486 | J8: =F189 -> 0.30194099 | K8: =F198 -> 149.36536 | L8: =K8/K$4-1 -> 0.26744586
A9: 液冷滲透率 低 | B9: 2026 45%、2027 60%、2028 70%、2029 75%（FY2026 份額反向調整） | C9: =E220 -> 62.963843 | D9: =E215 -> 48.121574 | E9: =E227 -> 0.29837014 | F9: =E236 -> 99.599318 | G9: =F9/F$4-1 -> -0.020122681 | H9: =F220 -> 72.673769 | I9: =F215 -> 58.085557 | J9: =F227 -> 0.30011971 | K9: =F236 -> 118.65571 | L9: =K9/K$4-1 -> 0.0068579173
A10: 液冷滲透率 高 | B10: 2026 65%、2027 85%、2028–29 95% | C10: =E258 -> 62.038428 | D10: =E253 -> 47.196159 | E10: =E265 -> 0.29819433 | F10: =E274 -> 97.868626 | G10: =F10/F$4-1 -> -0.037149566 | H10: =F258 -> 69.163103 | I10: =F253 -> 54.574891 | J10: =F265 -> 0.29961025 | K10: =F274 -> 111.86473 | L10: =K10/K$4-1 -> -0.050767212
A11: AI 部署 ×0.8 | B11: FY2027 起 AI IT 資本支出 ×0.8 | C11: =E296 -> 54.214466 | D11: =E291 -> 39.372197 | E11: =E303 -> 0.29646801 | F11: =E312 -> 83.23641 | G11: =F11/F$4-1 -> -0.18110413 | H11: =F296 -> 60.754914 | I11: =F291 -> 46.166702 | J11: =F303 -> 0.2981507 | K11: =F312 -> 95.971923 | L11: =K11/K$4-1 -> -0.18562631
A12: AI 部署 ×1.2 | B12: ×1.2 | C12: =E334 -> 73.900564 | D12: =E329 -> 59.058295 | E12: =E341 -> 0.30011443 | F12: =E350 -> 120.05295 | G12: =F12/F$4-1 -> 0.18110413 | H12: =F334 -> 83.838265 | I12: =F329 -> 69.250053 | J12: =F341 -> 0.30145627 | K12: =F350 -> 139.74006 | L12: =K12/K$4-1 -> 0.18576998
A13: 伺服器氣冷 低 | B13: 2027–29 每年 −20% | C13: =E372 -> 63.25523 | D13: =E367 -> 49.215246 | E13: =E379 -> 0.2990586 | F13: =E388 -> 100.46319 | G13: =F13/F$4-1 -> -0.011623744 | H13: =F372 -> 70.892591 | I13: =F367 -> 57.708378 | J13: =F379 -> 0.30085776 | K13: =F388 -> 115.71724 | L13: =K13/K$4-1 -> -0.018076648
A14: 伺服器氣冷 高 | B14: 2027–29 每年 +5% | C14: =E410 -> 64.592371 | D14: =E405 -> 49.215246 | E14: =E417 -> 0.29825328 | F14: =E426 -> 102.43234 | G14: =F14/F$4-1 -> 0.0077491629 | H14: =F410 -> 73.366303 | I14: =F405 -> 57.708378 | J14: =F417 -> 0.29948542 | K14: =F426 -> 119.47689 | L14: =K14/K$4-1 -> 0.013826028
A15: 筆電與其他 低 | B15: 筆電與桌機 −10／−8／−8%、電競顯卡與其他 −15／−10／−10% | C15: =E448 -> 63.026006 | D15: =E443 -> 49.215246 | E15: =E455 -> 0.29920009 | F15: =E464 -> 100.12562 | G15: =F15/F$4-1 -> -0.014944814 | H15: =F448 -> 70.495269 | I15: =F443 -> 57.708378 | J15: =F455 -> 0.30108716 | K15: =F464 -> 115.11482 | L15: =K15/K$4-1 -> -0.023188511
A16: 筆電與其他 高 | B16: 筆電與桌機 +5%、電競顯卡與其他 +8% | C16: =E486 -> 64.852159 | D16: =E481 -> 49.215246 | E16: =E493 -> 0.29810067 | F16: =E502 -> 102.81492 | G16: =F16/F$4-1 -> 0.011513042 | H16: =F486 -> 73.755182 | I16: =F481 -> 57.708378 | J16: =F493 -> 0.29927806 | K16: =F502 -> 120.06497 | L16: =K16/K$4-1 -> 0.018816201
A17: 液冷毛利率差距 2pt | B17: 液冷毛利率只高 2 個百分點 | C17: =E524 -> 64.057515 | D17: =E519 -> 49.215246 | E17: =E531 -> 0.29352244 | F17: =E540 -> 99.07334 | G17: =F17/F$4-1 -> -0.025297357 | H17: =F524 -> 72.29659 | I17: =F519 -> 57.708378 | J17: =F531 -> 0.29412083 | K17: =F540 -> 114.42954 | L17: =K17/K$4-1 -> -0.029003468
A18: 液冷毛利率差距 8pt | B18: 高 8 個百分點 | C18: =E562 -> 64.057515 | D18: =E557 -> 49.215246 | E18: =E569 -> 0.30362031 | F18: =E578 -> 104.21602 | G18: =F18/F$4-1 -> 0.025297357 | H18: =F562 -> 72.29659 | I18: =F557 -> 57.708378 | J18: =F569 -> 0.30601386 | K18: =F578 -> 121.26551 | L18: =K18/K$4-1 -> 0.029003468
A19: 營業費用率 +2pt | B19: 營業費用額外 +2% × 營收 | C19: =E600 -> 64.057515 | D19: =E595 -> 49.215246 | E19: =E607 -> 0.29857137 | F19: =E616 -> 91.458998 | G19: =F19/F$4-1 -> -0.10020872 | H19: =F600 -> 72.29659 | I19: =F595 -> 57.708378 | J19: =F607 -> 0.30006734 | K19: =F616 -> 106.35176 | L19: =K19/K$4-1 -> -0.097547793
A20: 淨利 ÷ 稅前 0.72 | B20: 基準 0.74 | C20: =E638 -> 64.057515 | D20: =E633 -> 49.215246 | E20: =E645 -> 0.29857137 | F20: =E654 -> 98.897528 | G20: =F20/F$4-1 -> -0.027027027 | H20: =F638 -> 72.29659 | I20: =F633 -> 57.708378 | J20: =F645 -> 0.30006734 | K20: =F654 -> 114.66246 | L20: =K20/K$4-1 -> -0.027027027
A21: 淨利 ÷ 稅前 0.78 | C21: =E676 -> 64.057515 | D21: =E671 -> 49.215246 | E21: =E683 -> 0.29857137 | F21: =E692 -> 107.13899 | G21: =F21/F$4-1 -> 0.054054054 | H21: =F676 -> 72.29659 | I21: =F671 -> 57.708378 | J21: =F683 -> 0.30006734 | K21: =F692 -> 124.21766 | L21: =K21/K$4-1 -> 0.054054054
A22: 2026 液冷占比 55%（讀法） | B22: FY2026 液冷＝營收 × 55%（1H26 實績比例）；份額分子變小、氣冷變大 | C22: =E714 -> 61.770936 | D22: =E709 -> 45.113975 | E22: =E721 -> 0.29917364 | F22: =E730 -> 97.874753 | G22: =F22/F$4-1 -> -0.03708929 | H22: =F714 -> 69.211516 | I22: =F709 -> 52.899346 | J22: =F721 -> 0.3008722 | K22: =F730 -> 112.66678 | L22: =K22/K$4-1 -> -0.04396139
A23: 2026 液冷占比 63%（讀法） | B23: FY2026 液冷＝營收 × 63% | C23: =E752 -> 65.429462 | D23: =E747 -> 51.676008 | E23: =E759 -> 0.29814635 | F23: =E768 -> 103.86301 | G23: =F23/F$4-1 -> 0.021824332 | H23: =F752 -> 74.147634 | I23: =F747 -> 60.593797 | J23: =F759 -> 0.29951672 | K23: =F768 -> 120.89928 | L23: =K23/K$4-1 -> 0.025895837
A24: 情境 A（全部） | B24: 顆數係數 A＋液冷滲透率、份額相對值高值 | C24: =PL!E78 -> 76.49084 | D24: =PL!E73 -> 61.648571 | E24: =PL!E85 -> 0.30045449 | F24: =PL!E94 -> 124.89724 | G24: =F24/F$4-1 -> 0.22876312 | H24: =PL!F78 -> 108.64721 | I24: =PL!F73 -> 94.058998 | J24: =PL!F85 -> 0.30344292 | K24: =PL!F94 -> 188.49224 | L24: =K24/K$4-1 -> 0.59945866
A25: 情境 C（全部） | B25: 顆數係數 C＋液冷滲透率、份額相對值低值 | C25: =PL!E154 -> 50.070024 | D25: =PL!E149 -> 35.227755 | E25: =PL!E161 -> 0.29533497 | F25: =PL!E170 -> 75.485559 | G25: =F25/F$4-1 -> -0.25735851 | H25: =PL!F154 -> 44.291054 | I25: =PL!F149 -> 29.702841 | J25: =PL!F161 -> 0.29368791 | K25: =PL!F170 -> 61.336336 | L25: =K25/K$4-1 -> -0.479528
A27: 讀法：基準為情境 B。每個案例的 FY2026 有效份額與其他營收毛利率依該案例重算，所以 FY2026 恆等於錨點。「液冷滲透率」案例的 FY2026 份額會反向調整（滲透率低 → 份額高），只影響 FY2027 起的成長路徑；情境 A／C 的滲透率只在 FY2027 起取高／低值，所以影響較大。
A29: 目標價參數（只改 DCF 參數；PL 收斂法的 fade_g 不隨 tp_g 變動）
A30: 案例 | B30: 設定 | C30: DCF 目標價 | D30: Comparable 目標價（相對倍數調整後） | E30: 加權目標價 | F30: 相對基準
A31: 基準 | B31: r 10%、g 4%、DCF 權重 0.5 | C31: =(tp_wA*MAX(0,Val!B8*(1-MIN(tp_g/tp_roe,0.8))/(1+tp_r)^1+Val!B9*(1-MIN(tp_g/tp_roe,0.8))/(1+tp_r)^2+Val!B10*(1-MIN(tp_g/tp_roe,0.8))/(1+tp_r)^3+Val!B11*(1-MIN(tp_g/tp_roe,0.8))/(1+tp_r)^4+Val!B12*(1-MIN(tp_g/tp_roe,0.8))/(1+tp_r)^5+Val!B13*(1-MIN(tp_g/tp_roe,0.8))/(1+tp_r)^6+Val!B13*(1-MIN(tp_g/tp_roe,0.8))*(1+tp_g)/(tp_r-tp_g)/(1+tp_r)^6)+tp_wB*MAX(0,Val!C8*(1-MIN(tp_g/tp_roe,0.8))/(1+tp_r)^1+Val!C9*(1-MIN(tp_g/tp_roe,0.8))/(1+tp_r)^2+Val!C10*(1-MIN(tp_g/tp_roe,0.8))/(1+tp_r)^3+Val!C11*(1-MIN(tp_g/tp_roe,0.8))/(1+tp_r)^4+Val!C12*(1-MIN(tp_g/tp_roe,0.8))/(1+tp_r)^5+Val!C13*(1-MIN(tp_g/tp_roe,0.8))/(1+tp_r)^6+Val!C13*(1-MIN(tp_g/tp_roe,0.8))*(1+tp_g)/(tp_r-tp_g)/(1+tp_r)^6)+tp_wC*MAX(0,Val!D8*(1-MIN(tp_g/tp_roe,0.8))/(1+tp_r)^1+Val!D9*(1-MIN(tp_g/tp_roe,0.8))/(1+tp_r)^2+Val!D10*(1-MIN(tp_g/tp_roe,0.8))/(1+tp_r)^3+Val!D11*(1-MIN(tp_g/tp_roe,0.8))/(1+tp_r)^4+Val!D12*(1-MIN(tp_g/tp_roe,0.8))/(1+tp_r)^5+Val!D13*(1-MIN(tp_g/tp_roe,0.8))/(1+tp_r)^6+Val!D13*(1-MIN(tp_g/tp_roe,0.8))*(1+tp_g)/(tp_r-tp_g)/(1+tp_r)^6))*(1+tp_r) -> 1978.6451 | D31: =tp_comp_adj -> 2601.7921 | E31: =tp_w_dcf*C31+(1-tp_w_dcf)*D31 -> 2290.2186 | F31: =E31/E$31-1 -> 0
A32: 折現率 +1pt | B32: r 11% | C32: =(tp_wA*MAX(0,Val!B8*(1-MIN(tp_g/tp_roe,0.8))/(1+(tp_r+0.01))^1+Val!B9*(1-MIN(tp_g/tp_roe,0.8))/(1+(tp_r+0.01))^2+Val!B10*(1-MIN(tp_g/tp_roe,0.8))/(1+(tp_r+0.01))^3+Val!B11*(1-MIN(tp_g/tp_roe,0.8))/(1+(tp_r+0.01))^4+Val!B12*(1-MIN(tp_g/tp_roe,0.8))/(1+(tp_r+0.01))^5+Val!B13*(1-MIN(tp_g/tp_roe,0.8))/(1+(tp_r+0.01))^6+Val!B13*(1-MIN(tp_g/tp_roe,0.8))*(1+tp_g)/((tp_r+0.01)-tp_g)/(1+(tp_r+0.01))^6)+tp_wB*MAX(0,Val!C8*(1-MIN(tp_g/tp_roe,0.8))/(1+(tp_r+0.01))^1+Val!C9*(1-MIN(tp_g/tp_roe,0.8))/(1+(tp_r+0.01))^2+Val!C10*(1-MIN(tp_g/tp_roe,0.8))/(1+(tp_r+0.01))^3+Val!C11*(1-MIN(tp_g/tp_roe,0.8))/(1+(tp_r+0.01))^4+Val!C12*(1-MIN(tp_g/tp_roe,0.8))/(1+(tp_r+0.01))^5+Val!C13*(1-MIN(tp_g/tp_roe,0.8))/(1+(tp_r+0.01))^6+Val!C13*(1-MIN(tp_g/tp_roe,0.8))*(1+tp_g)/((tp_r+0.01)-tp_g)/(1+(tp_r+0.01))^6)+tp_wC*MAX(0,Val!D8*(1-MIN(tp_g/tp_roe,0.8))/(1+(tp_r+0.01))^1+Val!D9*(1-MIN(tp_g/tp_roe,0.8))/(1+(tp_r+0.01))^2+Val!D10*(1-MIN(tp_g/tp_roe,0.8))/(1+(tp_r+0.01))^3+Val!D11*(1-MIN(tp_g/tp_roe,0.8))/(1+(tp_r+0.01))^4+Val!D12*(1-MIN(tp_g/tp_roe,0.8))/(1+(tp_r+0.01))^5+Val!D13*(1-MIN(tp_g/tp_roe,0.8))/(1+(tp_r+0.01))^6+Val!D13*(1-MIN(tp_g/tp_roe,0.8))*(1+tp_g)/((tp_r+0.01)-tp_g)/(1+(tp_r+0.01))^6))*(1+(tp_r+0.01)) -> 1708.9279 | D32: =tp_comp_adj -> 2601.7921 | E32: =tp_w_dcf*C32+(1-tp_w_dcf)*D32 -> 2155.36 | F32: =E32/E$31-1 -> -0.058884598
A33: 折現率 −1pt | B33: r 9% | C33: =(tp_wA*MAX(0,Val!B8*(1-MIN(tp_g/tp_roe,0.8))/(1+(tp_r-0.01))^1+Val!B9*(1-MIN(tp_g/tp_roe,0.8))/(1+(tp_r-0.01))^2+Val!B10*(1-MIN(tp_g/tp_roe,0.8))/(1+(tp_r-0.01))^3+Val!B11*(1-MIN(tp_g/tp_roe,0.8))/(1+(tp_r-0.01))^4+Val!B12*(1-MIN(tp_g/tp_roe,0.8))/(1+(tp_r-0.01))^5+Val!B13*(1-MIN(tp_g/tp_roe,0.8))/(1+(tp_r-0.01))^6+Val!B13*(1-MIN(tp_g/tp_roe,0.8))*(1+tp_g)/((tp_r-0.01)-tp_g)/(1+(tp_r-0.01))^6)+tp_wB*MAX(0,Val!C8*(1-MIN(tp_g/tp_roe,0.8))/(1+(tp_r-0.01))^1+Val!C9*(1-MIN(tp_g/tp_roe,0.8))/(1+(tp_r-0.01))^2+Val!C10*(1-MIN(tp_g/tp_roe,0.8))/(1+(tp_r-0.01))^3+Val!C11*(1-MIN(tp_g/tp_roe,0.8))/(1+(tp_r-0.01))^4+Val!C12*(1-MIN(tp_g/tp_roe,0.8))/(1+(tp_r-0.01))^5+Val!C13*(1-MIN(tp_g/tp_roe,0.8))/(1+(tp_r-0.01))^6+Val!C13*(1-MIN(tp_g/tp_roe,0.8))*(1+tp_g)/((tp_r-0.01)-tp_g)/(1+(tp_r-0.01))^6)+tp_wC*MAX(0,Val!D8*(1-MIN(tp_g/tp_roe,0.8))/(1+(tp_r-0.01))^1+Val!D9*(1-MIN(tp_g/tp_roe,0.8))/(1+(tp_r-0.01))^2+Val!D10*(1-MIN(tp_g/tp_roe,0.8))/(1+(tp_r-0.01))^3+Val!D11*(1-MIN(tp_g/tp_roe,0.8))/(1+(tp_r-0.01))^4+Val!D12*(1-MIN(tp_g/tp_roe,0.8))/(1+(tp_r-0.01))^5+Val!D13*(1-MIN(tp_g/tp_roe,0.8))/(1+(tp_r-0.01))^6+Val!D13*(1-MIN(tp_g/tp_roe,0.8))*(1+tp_g)/((tp_r-0.01)-tp_g)/(1+(tp_r-0.01))^6))*(1+(tp_r-0.01)) -> 2356.1379 | D33: =tp_comp_adj -> 2601.7921 | E33: =tp_w_dcf*C33+(1-tp_w_dcf)*D33 -> 2478.965 | F33: =E33/E$31-1 -> 0.082414139
A34: 長期成長 +1pt | B34: g 5% | C34: =(tp_wA*MAX(0,Val!B8*(1-MIN((tp_g+0.01)/tp_roe,0.8))/(1+tp_r)^1+Val!B9*(1-MIN((tp_g+0.01)/tp_roe,0.8))/(1+tp_r)^2+Val!B10*(1-MIN((tp_g+0.01)/tp_roe,0.8))/(1+tp_r)^3+Val!B11*(1-MIN((tp_g+0.01)/tp_roe,0.8))/(1+tp_r)^4+Val!B12*(1-MIN((tp_g+0.01)/tp_roe,0.8))/(1+tp_r)^5+Val!B13*(1-MIN((tp_g+0.01)/tp_roe,0.8))/(1+tp_r)^6+Val!B13*(1-MIN((tp_g+0.01)/tp_roe,0.8))*(1+(tp_g+0.01))/(tp_r-(tp_g+0.01))/(1+tp_r)^6)+tp_wB*MAX(0,Val!C8*(1-MIN((tp_g+0.01)/tp_roe,0.8))/(1+tp_r)^1+Val!C9*(1-MIN((tp_g+0.01)/tp_roe,0.8))/(1+tp_r)^2+Val!C10*(1-MIN((tp_g+0.01)/tp_roe,0.8))/(1+tp_r)^3+Val!C11*(1-MIN((tp_g+0.01)/tp_roe,0.8))/(1+tp_r)^4+Val!C12*(1-MIN((tp_g+0.01)/tp_roe,0.8))/(1+tp_r)^5+Val!C13*(1-MIN((tp_g+0.01)/tp_roe,0.8))/(1+tp_r)^6+Val!C13*(1-MIN((tp_g+0.01)/tp_roe,0.8))*(1+(tp_g+0.01))/(tp_r-(tp_g+0.01))/(1+tp_r)^6)+tp_wC*MAX(0,Val!D8*(1-MIN((tp_g+0.01)/tp_roe,0.8))/(1+tp_r)^1+Val!D9*(1-MIN((tp_g+0.01)/tp_roe,0.8))/(1+tp_r)^2+Val!D10*(1-MIN((tp_g+0.01)/tp_roe,0.8))/(1+tp_r)^3+Val!D11*(1-MIN((tp_g+0.01)/tp_roe,0.8))/(1+tp_r)^4+Val!D12*(1-MIN((tp_g+0.01)/tp_roe,0.8))/(1+tp_r)^5+Val!D13*(1-MIN((tp_g+0.01)/tp_roe,0.8))/(1+tp_r)^6+Val!D13*(1-MIN((tp_g+0.01)/tp_roe,0.8))*(1+(tp_g+0.01))/(tp_r-(tp_g+0.01))/(1+tp_r)^6))*(1+tp_r) -> 2160.8905 | D34: =tp_comp_adj -> 2601.7921 | E34: =tp_w_dcf*C34+(1-tp_w_dcf)*D34 -> 2381.3413 | F34: =E34/E$31-1 -> 0.039787768
A35: 長期成長 −1pt | B35: g 3% | C35: =(tp_wA*MAX(0,Val!B8*(1-MIN((tp_g-0.01)/tp_roe,0.8))/(1+tp_r)^1+Val!B9*(1-MIN((tp_g-0.01)/tp_roe,0.8))/(1+tp_r)^2+Val!B10*(1-MIN((tp_g-0.01)/tp_roe,0.8))/(1+tp_r)^3+Val!B11*(1-MIN((tp_g-0.01)/tp_roe,0.8))/(1+tp_r)^4+Val!B12*(1-MIN((tp_g-0.01)/tp_roe,0.8))/(1+tp_r)^5+Val!B13*(1-MIN((tp_g-0.01)/tp_roe,0.8))/(1+tp_r)^6+Val!B13*(1-MIN((tp_g-0.01)/tp_roe,0.8))*(1+(tp_g-0.01))/(tp_r-(tp_g-0.01))/(1+tp_r)^6)+tp_wB*MAX(0,Val!C8*(1-MIN((tp_g-0.01)/tp_roe,0.8))/(1+tp_r)^1+Val!C9*(1-MIN((tp_g-0.01)/tp_roe,0.8))/(1+tp_r)^2+Val!C10*(1-MIN((tp_g-0.01)/tp_roe,0.8))/(1+tp_r)^3+Val!C11*(1-MIN((tp_g-0.01)/tp_roe,0.8))/(1+tp_r)^4+Val!C12*(1-MIN((tp_g-0.01)/tp_roe,0.8))/(1+tp_r)^5+Val!C13*(1-MIN((tp_g-0.01)/tp_roe,0.8))/(1+tp_r)^6+Val!C13*(1-MIN((tp_g-0.01)/tp_roe,0.8))*(1+(tp_g-0.01))/(tp_r-(tp_g-0.01))/(1+tp_r)^6)+tp_wC*MAX(0,Val!D8*(1-MIN((tp_g-0.01)/tp_roe,0.8))/(1+tp_r)^1+Val!D9*(1-MIN((tp_g-0.01)/tp_roe,0.8))/(1+tp_r)^2+Val!D10*(1-MIN((tp_g-0.01)/tp_roe,0.8))/(1+tp_r)^3+Val!D11*(1-MIN((tp_g-0.01)/tp_roe,0.8))/(1+tp_r)^4+Val!D12*(1-MIN((tp_g-0.01)/tp_roe,0.8))/(1+tp_r)^5+Val!D13*(1-MIN((tp_g-0.01)/tp_roe,0.8))/(1+tp_r)^6+Val!D13*(1-MIN((tp_g-0.01)/tp_roe,0.8))*(1+(tp_g-0.01))/(tp_r-(tp_g-0.01))/(1+tp_r)^6))*(1+tp_r) -> 1855.5127 | D35: =tp_comp_adj -> 2601.7921 | E35: =tp_w_dcf*C35+(1-tp_w_dcf)*D35 -> 2228.6524 | F35: =E35/E$31-1 -> -0.026882231
A36: DCF 權重 0.3 | C36: =(tp_wA*MAX(0,Val!B8*(1-MIN(tp_g/tp_roe,0.8))/(1+tp_r)^1+Val!B9*(1-MIN(tp_g/tp_roe,0.8))/(1+tp_r)^2+Val!B10*(1-MIN(tp_g/tp_roe,0.8))/(1+tp_r)^3+Val!B11*(1-MIN(tp_g/tp_roe,0.8))/(1+tp_r)^4+Val!B12*(1-MIN(tp_g/tp_roe,0.8))/(1+tp_r)^5+Val!B13*(1-MIN(tp_g/tp_roe,0.8))/(1+tp_r)^6+Val!B13*(1-MIN(tp_g/tp_roe,0.8))*(1+tp_g)/(tp_r-tp_g)/(1+tp_r)^6)+tp_wB*MAX(0,Val!C8*(1-MIN(tp_g/tp_roe,0.8))/(1+tp_r)^1+Val!C9*(1-MIN(tp_g/tp_roe,0.8))/(1+tp_r)^2+Val!C10*(1-MIN(tp_g/tp_roe,0.8))/(1+tp_r)^3+Val!C11*(1-MIN(tp_g/tp_roe,0.8))/(1+tp_r)^4+Val!C12*(1-MIN(tp_g/tp_roe,0.8))/(1+tp_r)^5+Val!C13*(1-MIN(tp_g/tp_roe,0.8))/(1+tp_r)^6+Val!C13*(1-MIN(tp_g/tp_roe,0.8))*(1+tp_g)/(tp_r-tp_g)/(1+tp_r)^6)+tp_wC*MAX(0,Val!D8*(1-MIN(tp_g/tp_roe,0.8))/(1+tp_r)^1+Val!D9*(1-MIN(tp_g/tp_roe,0.8))/(1+tp_r)^2+Val!D10*(1-MIN(tp_g/tp_roe,0.8))/(1+tp_r)^3+Val!D11*(1-MIN(tp_g/tp_roe,0.8))/(1+tp_r)^4+Val!D12*(1-MIN(tp_g/tp_roe,0.8))/(1+tp_r)^5+Val!D13*(1-MIN(tp_g/tp_roe,0.8))/(1+tp_r)^6+Val!D13*(1-MIN(tp_g/tp_roe,0.8))*(1+tp_g)/(tp_r-tp_g)/(1+tp_r)^6))*(1+tp_r) -> 1978.6451 | D36: =tp_comp_adj -> 2601.7921 | E36: =0.3*C36+(1-0.3)*D36 -> 2414.848 | F36: =E36/E$31-1 -> 0.054418122
A37: DCF 權重 0.7 | C37: =(tp_wA*MAX(0,Val!B8*(1-MIN(tp_g/tp_roe,0.8))/(1+tp_r)^1+Val!B9*(1-MIN(tp_g/tp_roe,0.8))/(1+tp_r)^2+Val!B10*(1-MIN(tp_g/tp_roe,0.8))/(1+tp_r)^3+Val!B11*(1-MIN(tp_g/tp_roe,0.8))/(1+tp_r)^4+Val!B12*(1-MIN(tp_g/tp_roe,0.8))/(1+tp_r)^5+Val!B13*(1-MIN(tp_g/tp_roe,0.8))/(1+tp_r)^6+Val!B13*(1-MIN(tp_g/tp_roe,0.8))*(1+tp_g)/(tp_r-tp_g)/(1+tp_r)^6)+tp_wB*MAX(0,Val!C8*(1-MIN(tp_g/tp_roe,0.8))/(1+tp_r)^1+Val!C9*(1-MIN(tp_g/tp_roe,0.8))/(1+tp_r)^2+Val!C10*(1-MIN(tp_g/tp_roe,0.8))/(1+tp_r)^3+Val!C11*(1-MIN(tp_g/tp_roe,0.8))/(1+tp_r)^4+Val!C12*(1-MIN(tp_g/tp_roe,0.8))/(1+tp_r)^5+Val!C13*(1-MIN(tp_g/tp_roe,0.8))/(1+tp_r)^6+Val!C13*(1-MIN(tp_g/tp_roe,0.8))*(1+tp_g)/(tp_r-tp_g)/(1+tp_r)^6)+tp_wC*MAX(0,Val!D8*(1-MIN(tp_g/tp_roe,0.8))/(1+tp_r)^1+Val!D9*(1-MIN(tp_g/tp_roe,0.8))/(1+tp_r)^2+Val!D10*(1-MIN(tp_g/tp_roe,0.8))/(1+tp_r)^3+Val!D11*(1-MIN(tp_g/tp_roe,0.8))/(1+tp_r)^4+Val!D12*(1-MIN(tp_g/tp_roe,0.8))/(1+tp_r)^5+Val!D13*(1-MIN(tp_g/tp_roe,0.8))/(1+tp_r)^6+Val!D13*(1-MIN(tp_g/tp_roe,0.8))*(1+tp_g)/(tp_r-tp_g)/(1+tp_r)^6))*(1+tp_r) -> 1978.6451 | D37: =tp_comp_adj -> 2601.7921 | E37: =0.7*C37+(1-0.7)*D37 -> 2165.5892 | F37: =E37/E$31-1 -> -0.054418122
A50: 案例區塊：份額流失（低）（情境 B）
A51: 項目 | B51: 單位 | C51: FY2025A | D51: FY2026（錨點） | E51: FY2027 | F51: FY2028 | G51: FY2029 | H51: 說明
A52: A. AI 部署與液冷市場（D 欄＝FY2026 校準年；E–G＝FY2027–FY2029）
A53: AI IT 資本支出 × 情境顆數係數 | B53: US$B | D53: =itc_26*1 -> 781.87292 | E53: =itc_27*1*1 -> 1565.35 | F53: =itc_28*um28_B*1 -> 1587.4111 | G53: =itc_29*um29_B*1 -> 1921.3317
A54: 每 GW IT 資本支出 | B54: US$B | D54: =itpg_gb*(1-vr26)+itpg_vr*vr26 -> 33.414032 | E54: =itpg_vr -> 37.586352 | F54: =itpg_vr -> 37.586352 | G54: =itpg_vr -> 37.586352
A55: 部署 GW（IT 電力） | B55: GW | D55: =D53/D54 -> 23.399538 | E55: =E53/E54 -> 41.646766 | F55: =F53/F54 -> 42.233711 | G55: =G53/G54 -> 51.117803
A56: 液冷滲透率（部署 GW 中液冷占比） | B56: % | D56: =lpenB_26 -> 0.55 | E56: =lpenB_27 -> 0.75 | F56: =lpenB_28 -> 0.85 | G56: =lpenB_29 -> 0.9
A57: 每 GW 液冷內容（機架內液冷＋分歧管；與奇鋐模型同口徑） | B57: US$M/GW | D57: =((1-vr26)*racks_gb*(cool_gb+mani)+vr26*racks_vr*(cool_vr+mani))/1000 -> 350.7208 | E57: =racks_vr*(cool_vr+mani)*lcadj_27/1000 -> 326.5912 | F57: =racks_vr*(cool_vr+mani)*lcadj_28/1000 -> 351.7136 | G57: =racks_vr*(cool_vr+mani)*lcadj_29/1000 -> 351.7136 | H57: 橋接表每架機架內液冷 × 每 GW 機架數；FY2027 起 × 內容調整（Rubin 全液冷、ASIC 液冷）
A58: AI 液冷市場（美元） | B58: US$B | D58: =D55*D56*D57/1000 -> 4.5136876 | E58: =E55*E56*E57/1000 -> 10.2011 | F58: =F55*F56*F57/1000 -> 12.626045 | G58: =G55*G56*G57/1000 -> 16.180944
A59: AI 液冷市場（新台幣） | B59: NT$B | D59: =D58*fx -> 144.438 | E59: =E58*fx -> 326.43521 | F59: =F58*fx -> 404.03343 | G59: =G58*fx -> 517.7902
A60: 雙鴻有效份額（FY2026 校準）＝ 液冷營收 ÷ 市場 | B60: % | D60: =a26_lc/D59 -> 0.15870078 | H60: Derived：分子為券商液冷占比 × 營收（含 CDU、機架分歧管）；分母為機架內液冷＋分歧管市場（不含機架外 CDU）
A61: 份額相對值（÷ FY2026） | B61: x | D61: =1 -> 1 | E61: =RLO_27 -> 0.85 | F61: =RLO_28 -> 0.75 | G61: =RLO_29 -> 0.7
A62: 雙鴻有效份額 | B62: % | D62: =$D$60*D61 -> 0.15870078 | E62: =$D$60*E61 -> 0.13489566 | F62: =$D$60*F61 -> 0.11902558 | G62: =$D$60*G61 -> 0.11109054
A63: 液冷營收 | B63: NT$B | C63: =a25_lc -> 7.91384 | D63: =D59*D62 -> 22.922423 | E63: =E59*E62 -> 44.034694 | F63: =F59*F62 -> 48.090315 | G63: =G59*G62 -> 57.521595
A64: B. 非 AI（伺服器氣冷、筆電與桌機、電競顯卡與其他）與合計
A65: 伺服器氣冷營收（含 AI 氣冷與一般伺服器） | B65: NT$B | C65: =a25_sair -> 5.35348 | D65: =a26_sair -> 5.3485654 | E65: =D65*(1+g_sair_27) -> 5.0811371 | F65: =E65*(1+g_sair_28) -> 4.8270803 | G65: =F65*(1+g_sair_29) -> 4.5857263
A66: 筆電與桌機營收 | B66: NT$B | C66: =a25_nb -> 6.28452 | D66: =a26_nb -> 5.7306058 | E66: =D66*(1+g_nb_27) -> 5.5586876 | F66: =E66*(1+g_nb_28) -> 5.5586876 | G66: =F66*(1+g_nb_29) -> 5.5586876
A67: 電競筆電、顯卡、主機板與其他營收 | B67: NT$B | C67: =a25_oth -> 3.72416 | D67: =a26_oth -> 4.2024443 | E67: =D67*(1+g_oth_27) -> 4.2024443 | F67: =E67*(1+g_oth_28) -> 4.2024443 | G67: =F67*(1+g_oth_29) -> 4.2024443
A68: 營收 | B68: NT$B | C68: =C63+C65+C66+C67 -> 23.276 | D68: =D63+D65+D66+D67 -> 38.204039 | E68: =E63+E65+E66+E67 -> 58.876963 | F68: =F63+F65+F66+F67 -> 62.678527 | G68: =G63+G65+G66+G67 -> 71.868453
A69: 營收年增 | B69: % | D69: =D68/C68-1 -> 0.64134897 | E69: =E68/D68-1 -> 0.54111881 | F69: =F68/E68-1 -> 0.064567943 | G69: =G68/F68-1 -> 0.14662001
A70: 液冷 ÷ 營收 | B70: % | C70: =C63/C68 -> 0.34 | D70: =D63/D68 -> 0.6 | E70: =E63/E68 -> 0.74791042 | F70: =F63/F68 -> 0.76725343 | G70: =G63/G68 -> 0.80037336
A71: 每 GW 雙鴻液冷營收 | B71: US$M/GW | D71: =D63/fx/D55*1000 -> 30.612815 | E71: =E63/fx/E55*1000 -> 33.041802 | F71: =F63/fx/F55*1000 -> 35.583479 | G71: =G63/fx/G55*1000 -> 35.164849
A72: C. 損益
A73: 其他營收毛利率 ＝ 錨點毛利率 − 差距 × 液冷占比（FY2026 校準） | B73: % | D73: =a26_gp/D68-d_lc*D70 -> 0.26015649 | H73: Derived：讓 FY2026 毛利率等於錨點；液冷毛利率＝其他 + 差距。FY2027 起毛利率隨液冷占比變動
A74: 毛利 | B74: NT$B | C74: =a25_gp -> 6.372 | D74: =a26_gp -> 11.08515 | E74: =$D$73*E68+d_lc*E63 -> 17.518958 | F74: =$D$73*F68+d_lc*F63 -> 18.710741 | G74: =$D$73*G68+d_lc*G63 -> 21.573124
A75: 毛利率 | B75: % | C75: =C74/C68 -> 0.27375838 | D75: =D74/D68 -> 0.29015649 | E75: =E74/E68 -> 0.29755201 | F75: =F74/F68 -> 0.29851916 | G75: =G74/G68 -> 0.30017515
A76: 營業費用（基準路徑） | B76: NT$B | C76: =a25_opx -> 3.113 | D76: =a26_opx -> 4.4038197 | E76: =D76*(1+MAX(0,phi*E69)) -> 5.9527629 | F76: =E76*(1+MAX(0,phi*F69)) -> 6.2025954 | G76: =F76*(1+MAX(0,phi*G69)) -> 6.7937214
A77: 營業費用 | B77: NT$B | C77: =C76 -> 3.113 | D77: =D76 -> 4.4038197 | E77: =E76+0*E68 -> 5.9527629 | F77: =F76+0*F68 -> 6.2025954 | G77: =G76+0*G68 -> 6.7937214
A78: 營業利益 | B78: NT$B | C78: =C74-C77 -> 3.259 | D78: =D74-D77 -> 6.6813299 | E78: =E74-E77 -> 11.566195 | F78: =F74-F77 -> 12.508146 | G78: =G74-G77 -> 14.779403
A79: 營業利益率 | B79: % | C79: =C78/C68 -> 0.14001547 | D79: =D78/D68 -> 0.17488543 | E79: =E78/E68 -> 0.19644688 | F79: =F78/F68 -> 0.1995603 | G79: =G78/G68 -> 0.2056452
A80: 業外收益 | B80: NT$B | C80: =a25_nop -> 0.018436 | D80: =a26_nop -> -0.022684 | E80: =nop_f -> 0 | F80: =nop_f -> 0 | G80: =nop_f -> 0
A81: 歸屬母公司淨利 ÷ 稅前 | B81: % | C81: =a25_ni/(a25_oi+a25_nop) -> 0.78475979 | D81: =a26_ni/(a26_oi+a26_nop) -> 0.73946583 | E81: =nir_f -> 0.74 | F81: =nir_f -> 0.74 | G81: =nir_f -> 0.74
A82: 歸屬母公司淨利 | B82: NT$B | C82: =a25_ni -> 2.572 | D82: =a26_ni -> 4.9238411 | E82: =(E78+E80)*E81 -> 8.5589846 | F82: =(F78+F80)*F81 -> 9.2560277 | G82: =(G78+G80)*G81 -> 10.936758
A83: 股數 | B83: 十億股 | C83: =a25_sh -> 0.091012031 | D83: =a26_sh -> 0.093076837 | E83: =D83*(1+sh_g) -> 0.093076837 | F83: =E83*(1+sh_g) -> 0.093076837 | G83: =F83*(1+sh_g) -> 0.093076837
A84: EPS | B84: NT$ | C84: =C82/C83 -> 28.26 | D84: =D82/D83 -> 52.900821 | E84: =E82/E83 -> 91.956118 | F84: =F82/F83 -> 99.445018 | G84: =G82/G83 -> 117.50247
A85: EPS 年增 | B85: % | D85: =D84/C84-1 -> 0.87193281 | E85: =E84/D84-1 -> 0.73827392 | F85: =F84/E84-1 -> 0.081439936 | G85: =G84/F84-1 -> 0.18158223
A88: 案例區塊：份額上升（高）（情境 B）
A89: 項目 | B89: 單位 | C89: FY2025A | D89: FY2026（錨點） | E89: FY2027 | F89: FY2028 | G89: FY2029 | H89: 說明
A90: A. AI 部署與液冷市場（D 欄＝FY2026 校準年；E–G＝FY2027–FY2029）
A91: AI IT 資本支出 × 情境顆數係數 | B91: US$B | D91: =itc_26*1 -> 781.87292 | E91: =itc_27*1*1 -> 1565.35 | F91: =itc_28*um28_B*1 -> 1587.4111 | G91: =itc_29*um29_B*1 -> 1921.3317
A92: 每 GW IT 資本支出 | B92: US$B | D92: =itpg_gb*(1-vr26)+itpg_vr*vr26 -> 33.414032 | E92: =itpg_vr -> 37.586352 | F92: =itpg_vr -> 37.586352 | G92: =itpg_vr -> 37.586352
A93: 部署 GW（IT 電力） | B93: GW | D93: =D91/D92 -> 23.399538 | E93: =E91/E92 -> 41.646766 | F93: =F91/F92 -> 42.233711 | G93: =G91/G92 -> 51.117803
A94: 液冷滲透率（部署 GW 中液冷占比） | B94: % | D94: =lpenB_26 -> 0.55 | E94: =lpenB_27 -> 0.75 | F94: =lpenB_28 -> 0.85 | G94: =lpenB_29 -> 0.9
A95: 每 GW 液冷內容（機架內液冷＋分歧管；與奇鋐模型同口徑） | B95: US$M/GW | D95: =((1-vr26)*racks_gb*(cool_gb+mani)+vr26*racks_vr*(cool_vr+mani))/1000 -> 350.7208 | E95: =racks_vr*(cool_vr+mani)*lcadj_27/1000 -> 326.5912 | F95: =racks_vr*(cool_vr+mani)*lcadj_28/1000 -> 351.7136 | G95: =racks_vr*(cool_vr+mani)*lcadj_29/1000 -> 351.7136 | H95: 橋接表每架機架內液冷 × 每 GW 機架數；FY2027 起 × 內容調整（Rubin 全液冷、ASIC 液冷）
A96: AI 液冷市場（美元） | B96: US$B | D96: =D93*D94*D95/1000 -> 4.5136876 | E96: =E93*E94*E95/1000 -> 10.2011 | F96: =F93*F94*F95/1000 -> 12.626045 | G96: =G93*G94*G95/1000 -> 16.180944
A97: AI 液冷市場（新台幣） | B97: NT$B | D97: =D96*fx -> 144.438 | E97: =E96*fx -> 326.43521 | F97: =F96*fx -> 404.03343 | G97: =G96*fx -> 517.7902
A98: 雙鴻有效份額（FY2026 校準）＝ 液冷營收 ÷ 市場 | B98: % | D98: =a26_lc/D97 -> 0.15870078 | H98: Derived：分子為券商液冷占比 × 營收（含 CDU、機架分歧管）；分母為機架內液冷＋分歧管市場（不含機架外 CDU）
A99: 份額相對值（÷ FY2026） | B99: x | D99: =1 -> 1 | E99: =RHI_27 -> 1.05 | F99: =RHI_28 -> 1.05 | G99: =RHI_29 -> 1.05
A100: 雙鴻有效份額 | B100: % | D100: =$D$98*D99 -> 0.15870078 | E100: =$D$98*E99 -> 0.16663582 | F100: =$D$98*F99 -> 0.16663582 | G100: =$D$98*G99 -> 0.16663582
A101: 液冷營收 | B101: NT$B | C101: =a25_lc -> 7.91384 | D101: =D97*D100 -> 22.922423 | E101: =E97*E100 -> 54.395798 | F101: =F97*F100 -> 67.326441 | G101: =G97*G100 -> 86.282393
A102: B. 非 AI（伺服器氣冷、筆電與桌機、電競顯卡與其他）與合計
A103: 伺服器氣冷營收（含 AI 氣冷與一般伺服器） | B103: NT$B | C103: =a25_sair -> 5.35348 | D103: =a26_sair -> 5.3485654 | E103: =D103*(1+g_sair_27) -> 5.0811371 | F103: =E103*(1+g_sair_28) -> 4.8270803 | G103: =F103*(1+g_sair_29) -> 4.5857263
A104: 筆電與桌機營收 | B104: NT$B | C104: =a25_nb -> 6.28452 | D104: =a26_nb -> 5.7306058 | E104: =D104*(1+g_nb_27) -> 5.5586876 | F104: =E104*(1+g_nb_28) -> 5.5586876 | G104: =F104*(1+g_nb_29) -> 5.5586876
A105: 電競筆電、顯卡、主機板與其他營收 | B105: NT$B | C105: =a25_oth -> 3.72416 | D105: =a26_oth -> 4.2024443 | E105: =D105*(1+g_oth_27) -> 4.2024443 | F105: =E105*(1+g_oth_28) -> 4.2024443 | G105: =F105*(1+g_oth_29) -> 4.2024443
A106: 營收 | B106: NT$B | C106: =C101+C103+C104+C105 -> 23.276 | D106: =D101+D103+D104+D105 -> 38.204039 | E106: =E101+E103+E104+E105 -> 69.238067 | F106: =F101+F103+F104+F105 -> 81.914653 | G106: =G101+G103+G104+G105 -> 100.62925
A107: 營收年增 | B107: % | D107: =D106/C106-1 -> 0.64134897 | E107: =E106/D106-1 -> 0.81232324 | F107: =F106/E106-1 -> 0.18308694 | G107: =G106/F106-1 -> 0.22846459
A108: 液冷 ÷ 營收 | B108: % | C108: =C101/C106 -> 0.34 | D108: =D101/D106 -> 0.6 | E108: =E101/E106 -> 0.78563427 | F108: =F101/F106 -> 0.82190961 | G108: =G101/G106 -> 0.85742855
A109: 每 GW 雙鴻液冷營收 | B109: US$M/GW | D109: =D101/fx/D93*1000 -> 30.612815 | E109: =E101/fx/E93*1000 -> 40.816343 | F109: =F101/fx/F93*1000 -> 49.81687 | G109: =G101/fx/G93*1000 -> 52.747274
A110: C. 損益
A111: 其他營收毛利率 ＝ 錨點毛利率 − 差距 × 液冷占比（FY2026 校準） | B111: % | D111: =a26_gp/D106-d_lc*D108 -> 0.26015649 | H111: Derived：讓 FY2026 毛利率等於錨點；液冷毛利率＝其他 + 差距。FY2027 起毛利率隨液冷占比變動
A112: 毛利 | B112: NT$B | C112: =a25_gp -> 6.372 | D112: =a26_gp -> 11.08515 | E112: =$D$111*E106+d_lc*E101 -> 20.732522 | F112: =$D$111*F106+d_lc*F101 -> 24.67695 | G112: =$D$111*G106+d_lc*G101 -> 30.493472
A113: 毛利率 | B113: % | C113: =C112/C106 -> 0.27375838 | D113: =D112/D106 -> 0.29015649 | E113: =E112/E106 -> 0.2994382 | F113: =F112/F106 -> 0.30125197 | G113: =G112/G106 -> 0.30302791
A114: 營業費用（基準路徑） | B114: NT$B | C114: =a25_opx -> 3.113 | D114: =a26_opx -> 4.4038197 | E114: =D114*(1+MAX(0,phi*E107)) -> 6.7290809 | F114: =E114*(1+MAX(0,phi*F107)) -> 7.5298854 | G114: =F114*(1+MAX(0,phi*G107)) -> 8.6480883
A115: 營業費用 | B115: NT$B | C115: =C114 -> 3.113 | D115: =D114 -> 4.4038197 | E115: =E114+0*E106 -> 6.7290809 | F115: =F114+0*F106 -> 7.5298854 | G115: =G114+0*G106 -> 8.6480883
A116: 營業利益 | B116: NT$B | C116: =C112-C115 -> 3.259 | D116: =D112-D115 -> 6.6813299 | E116: =E112-E115 -> 14.003441 | F116: =F112-F115 -> 17.147065 | G116: =G112-G115 -> 21.845384
A117: 營業利益率 | B117: % | C117: =C116/C106 -> 0.14001547 | D117: =D116/D106 -> 0.17488543 | E117: =E116/E106 -> 0.20225061 | F117: =F116/F106 -> 0.20932842 | G117: =G116/G106 -> 0.21708781
...

Sheet Sources
A1: 來源（公司原文經媒體與資料商轉載：法說簡報原檔未逐份抓取；券商與研調皆為 Interested-party）
A2: 公司（經時報）：FY2025 財報 2026-03-04（營收、毛利率、營業利益、淨利、EPS） | B2: https://wantrich.chinatimes.com/news/20260304900286-420101
A3: 公司（經時報）：股東會 2026-05-21（1Q26 淨利、EPS；2025 產品比重） | B3: https://wantrich.chinatimes.com/news/20260521900232-420101
A4: 資料商：玩股網各季損益（1Q25–2Q26 營收、毛利、營業利益、稅前、合併淨利） | B4: https://www.wantgoo.com/stock/3324/financial-statements/income-statement
A5: 資料商：HiStock 月營收（2025-01–2026-09）、各季 EPS、已發行股數、股價 | B5: https://histock.tw/stock/financial.aspx?no=3324
A6: 公司（經 TechNews）：9 月營收與前 9 月累計 2026-10-08 | B6: https://finance.technews.tw/2026/10/08/auras-3324-202609-financial-report/
A7: 公司（經 Win 投資）：2Q26 EPS、1H26 累計 EPS 2026-10-08 | B7: https://winvest.tw/News/Detail/95436
A8: 券商：凱基 2026-08-07（2Q26 實績、產品比重、液冷占比、3Q／4Q 與 2026–27 估計、目標價） | B8: https://www.kgi.com.hk/zh-cn/-/media/files/kgishk/research-reports/tw-reports/auras-technology-3324-tt20260807en.pdf
A9: 券商：美系券商（經濟日報 2026-09-18；EPS 2026–28） | B9: https://money.udn.com/money/story/5607/9762508
A10: 券商：花旗（經濟日報 2026-09-19；目標價 1,800、3Q／4Q 季增） | B10: https://money.udn.com/money/story/5607/9764013
A11: 資料商：stockanalysis forecast 頁（共識目標價、2026–27 營收與 EPS，2026-10-19） | B11: https://stockanalysis.com/quote/tpex/3324/forecast/
A12: 資料商：stockanalysis 個股頁（股數、Forward PE）與比率頁（年底 P/E、ROE） | B12: https://stockanalysis.com/quote/tpex/3324/financials/ratios/
A13: 資料商：Goodinfo 歷年年底收盤、EPS、淨利率、ROE（2017–2025；2016 年未取得） | B13: https://goodinfo.tw/tw/StockBzPerformance.asp?STOCK_ID=3324
... A15: 同業前瞻 P/E：stockanalysis 個股頁（3017、3653、VRT、2308） | B15: https://stockanalysis.com/quote/tpe/3017/
A16: 市場層：markets/network、markets/chip_bridge、tsmc 成品；奇鋐模型 In 頁（液冷內容、滲透率、份額相對值）與 Units 頁（份額）（本 repo，唯讀）
A17: 待補（人工）：3Q26 財報與法說（預計 11 月中）；法說簡報原檔；液冷、CDU、分歧管的金額拆分；雙鴻液冷份額；2016 年 EPS 與年底股價；前瞻 P/E 十年歷史（Bloomberg）；FY2028 共識（付費） | B17: 未找到
A18: SemiAnalysis | B18: 未使用
