Workbook

Sheet README
A1: 新易盛（300502.SZ）收支與估值模型 v0.2.3（AI 半導體 Project：網通次產業內複製——光模組） 2026-10-26
A2: 版本：v0.2.1（2026-10-25：補上檔空間級距、投資建議、重點觀察，數值不變）；v0.2（2026-10-25：三情境延伸到 FY2032、目標價＝DCF 與 Comparable 加權；v0.1 初版）。新易盛在 AI 光模組的份額在本模型 Units 頁建立，為本專案權威資料（規則第 13 條）；中際旭創份額讀 innolight 成品，兩家合計在 Units 頁檢查。
A3: 模型命題：新易盛的 AI 營收＝AI 可插拔光模組市場（本專案網通模型）× 新易盛份額 × 單價係數＋CPO 光學 × 新易盛 CPO 份額；其他營收另依成長率推。股價 261 元（10-23）自 9 月底下跌約三成、只約 10 倍模型 FY2027 EPS：市場定價像是 2027 年就是獲利高點，或份額與美國限制風險遠大於模型。
A4: 核心問題：以 15 倍看 FY2028，現價隱含的 EPS 約等於模型情境 C、比情境 A 低四成——要成立，份額（主要客戶轉單、1.6T 落後）、美國限制、單價三條路徑各要不利到什麼程度？
A6: 會計年度＝日曆年，FY(t)＝CY(t)，不平移。預測期 FY2027–FY2029 由驅動因子推導；FY2030–FY2032 為收斂法。口徑：中國會計準則；淨利＝歸母淨利；股數與 EPS 全部以 10 轉 4 後表示（FY2025 EPS 9.61 ÷ 1.4 重述）。
A8: 驅動因子 → 推導量（全部唯讀上游，不修改）
A9: AI 營收：markets/network 的 AI 可插拔光模組市場 × 情境顆數係數 × 新易盛有效份額（FY2026 以 1H26 實績＋2H26 假設校準）× 份額相對值（Assumed）× 單價係數（基準 1）＋ CPO 光學市場 × CPO 份額（Assumed）；乘匯率換成人民幣。
A10: 其他營收：FY2026 營收 × 5%（Assumed）× 成長率。毛利率：FY2027 起為輸入路徑（Assumed）。營業費用、減值與其他：彈性 phi 0.6（Analogy：中際旭創）。稅率 12%（Assumed）、歸母比例 0.998（Derived）。
A11: 校準：FY2026 ＝ 1H26 實績（營收 20.91、綜合毛利率 48.44%、歸母淨利 7.53）＋ 2H26（季增 20%、毛利率 48%、營業費用率 5%，Assumed）。公司不給指引；不用共識（只在 Recon 對帳）。3Q26 季報預計 10-30 公布，本版未納入。
A12: 估值：目標價（Val 第 0 節）＝0.5 × DCF（股東現金流＝EPS ×（1 − g／ROE），FY2027–32 明確期＋永續，r 10%、g 4%，情境權重 0.3／0.5／0.2）＋0.5 × Comparable（A 股光通訊同業前瞻 P/E 中位數 × 12 個月後前瞻 EPS）。舊法規則值情境加權保留參考；現價 ÷ FY2027、FY2028 EPS；市場隱含 FY2028 EPS（Val 第 4 節）；十年 P/E 規則值（2016–2025，兩個資料商）× FY2027 EPS；循環位置以本模型營收最高年判定。本版未做先驗，無 Andy 合理 P/E 對照。
A13: 標記：Verified、Interested-party、Analogy、Assumed、Derived。SemiAnalysis 未使用。公司原文經財經媒體轉載；客戶名稱、客戶集中度與 800G／1.6T 份額未找到第一手來源。
A15: 已知限制：(1) 份額相對值、CPO 份額、毛利率路徑皆為 Assumed，是 FY2028 EPS 最敏感的輸入（Sens）；(2) FY2026 錨點的 2H26 為假設，3Q26 季報 10-30 公布；(3) 網通模型 2027 年可插拔光模組 +84%，未設雷射、DSP 供給上限（Sens 用市場 ×0.8）；(4) 十年 P/E 兩個來源差距大，且含低基期與高成長期溢價，規則值偏高；(5) 稅率與泰國子公司獲利占比未找到；(6) 主要客戶與美國限制風險只有次級來源；(7) R4 產業部署路徑未建（Recon 預留列）。
... A17: v0.2.1（2026-10-25）：補上檔空間級距、投資建議、重點觀察（Val 頁 0.3 結論加「上檔空間級距」「投資建議」兩列、README 頁加重點觀察三點；數值不變，既有儲存格位置不變）。
A18: ="投資建議："&Val!B50&"（依上檔空間固定規則）" -> 投資建議：強力買進（依上檔空間固定規則）
A19: ="重點觀察 1：目標價 ¥"&TEXT(Val!$B$39,"#,##0.00")&"（DCF "&TEXT(Val!$B$24,"#,##0.00")&"、Comparable（相對倍數調整後）"&TEXT(tp_comp_adj,"#,##0.00")&"；DCF 權重 "&TEXT(tp_w_dcf,"0%")&"），比現價 "&TEXT(px,"#,##0.00")&"（2026-10-23）"&IF(Val!$B$42>=0,"高 "&TEXT(Val!$B$42,"0.0%"),"低 "&TEXT(-Val!$B$42,"0.0%"))&"，級距 "&Val!$B$49&"、投資建議 "&Val!$B$50&"。相對倍數調整係數 "&TEXT(rm_factor,"0.00")&"（本公司 10 年前瞻倍數中位數 ÷ 同業的中位數，夾在 0.5–2.0；Val 第 0.5 節），調整前加權上檔空間 "&TEXT((tp_w_dcf*Val!$B$24+(1-tp_w_dcf)*Val!$B$35)/px-1,"+0.0%;−0.0%")&"；Comparable 單獨（市場主流同業法、未調整）為 "&TEXT(Val!$B$43,"+0.0%;−0.0%")&"。"&"以下為 2026-10-29 相對倍數調整前撰寫的說明，其中數字為調整前：主因是倍數不是 EPS：本模型 12 個月後前瞻 EPS 23.74 比共識前瞻 EPS 37.82 低 37.2%，但 A 股光通訊同業前瞻 P/E 中位數 45.1 倍，現價只隱含 10.3 倍（共識未來 12 月 EPS）、共識目標價 460.89 隱含 12.2 倍；Comparable 未扣同業溢價與客戶集中、美國"&"限制風險。DCF 單獨也有 +96.4%（ROE 42.3%，現價只有 FY2027 EPS 的 10.0–10.2 倍）。" -> 重點觀察 1：目標價 ¥705.63（DCF 510.23、Comparable（相對倍數調整後）901.04；DCF 權重 50%），比現價 261.00（2026-10-23）高 170.4%，級距 大於 50%、投資建議 強力買進。相對倍數調整係數 0.84（本公司 10 年前瞻倍數中位數 ÷ 同業的中位數，夾在 0.5–2.0；Val 第 0.5 節），調整前加權上檔空間 +202.5%；Comparable 單獨（市場主流同業法、未調整）為 +309.6%。以下為 2026-10-29 相對倍數調整前撰寫的說明，其中數字為調整前：主因是倍數不是 EPS：本模型 12 個月後前瞻 EPS 23.74 比共識前瞻 EPS 37.82 低 37.2%，但 A 股光通訊同業前瞻 P/E 中位數 45.1 倍，現價只隱含 10.3 倍（共識未來 12 月 EPS）、共識目標價 460.89 隱含 12.2 倍；Comparable 未扣同業溢價與客戶集中、美國限制風險。DCF 單獨也有 +96.4%（ROE 42.3%，現價只有 FY2027 EPS 的 10.0–10.2 倍）。
A20: 重點觀察 2：最敏感的是美國限制與份額：美國限制案例 FY2028 EPS −45.0%、份額流失 −33.9%、降價快於模型 −19.2%；情境 C FY2028 EPS 16.93，比情境 A 的 28.11 低 39.8%。股價自 52 週高點下跌 68.1%、自 9 月底下跌 32.9%，現價 ÷ 情境 C 的 FY2028 EPS 為 15.4 倍，市場定價接近情境 C。
A21: 重點觀察 3：追蹤 3Q26 季報（2026-10-30）：本版 2H26 季增 20%、毛利率 48% 為假設；客戶名稱與集中度未找到第一手來源。網通 CPO 已改三情境（v0.2.2；A＝替代快、C＝慢）：CPO 快對新易盛是減分，情境 A FY2028 EPS 由 28.99 降到 28.11（−3.0%）、C 由 16.72 升到 16.93（+1.3%）、B 不變；CPO 份額 0 時 FY2028 EPS −4.4%。
A22: v0.2.3（2026-10-28）：分部原則重建（數值不變）。Q 頁第 30 列起追加 FY2025 年報產品別：光互聯產品（約 99.7%）、其他（差額）與核對列「分部合計 − 合併營收」；AI 營收屬光互聯產品，推估年仍以 AI／其他拆分。
A23: v0.2.2（2026-10-26）：網通模型 v0.2.3 的 CPO 滲透改三情境（A＝替代快、B＝平平、C＝慢），本模型 A／B／C 改讀同字母的可插拔與 CPO 市場（In 頁末新增 B、C 兩組；情境 A 沿用 A 節 mpl_／mcp_，數值改為網通情境 A）；FY2027 起三情境不再相同。其他輸入不變。
A25: 2026-10-29：加權目標價中的 Comparable 改用相對倍數調整後的值（Val 第 0.5 節：同業前瞻倍數中位數 × 本公司 10 年相對同業的倍數比，Bloomberg 前瞻倍數；Andy 2026-10-27「照建議做」、10-29 資料取回）。「Comparable 目標價（市場主流同業法）」維持不調整。重點觀察 1 的第一句已改為公式；重點觀察 2、3 與其他說明中的目標價與上檔空間數字為調整前撰寫，以 Val 頁為準。

Sheet In
A1: In — 輸入（藍字；基準欄 E，低 D、高 F）。公司金額：十億人民幣（RMB B）；市場：十億美元（US$B）；比例：%。每個輸入附兩個來源（找不到者寫「未找到」）；公司原文算一個
A2: 標記：Verified／Interested-party／Analogy／Assumed／Derived；Analogy、Assumed 給低／高區間。SemiAnalysis 未使用。公司原文＝深交所定期報告與公告（經財經媒體轉載）；公司不給營收指引；客戶名稱、客戶集中度、800G／1.6T 份額：未找到第一手來源
A3: 鍵 | B3: 項目 | C3: 單位 | D3: 低 | E3: 基準 | F3: 高 | G3: 標記 | H3: 來源1 | I3: 來源2／說明
A4: A. AI 光模組市場（讀 markets/network 成品；情境 A 基準，B／C 依顆數係數縮放）與中際旭創份額（讀 innolight 成品）
A5: mpl_26 | B5: AI 可插拔光模組市場 2026 | C5: US$B | E5: 29.753262 | G5: Derived | H5: markets/network/dist/20261026_AI網通市場模型_v0.2.3.xlsx｜Mkt!C45:F45 | I5: 加速器顆數 × 每顆光學內容（scale-out 為主；2029 含 scale-up 光學）− CPO
A6: mpl_27 | B6: AI 可插拔光模組市場 2027 | C6: US$B | E6: 53.560715 | G6: Derived | H6: markets/network/dist/20261026_AI網通市場模型_v0.2.3.xlsx｜Mkt!C45:F45 | I6: 同上
A7: mpl_28 | B7: AI 可插拔光模組市場 2028 | C7: US$B | E7: 57.9915 | G7: Derived | H7: markets/network/dist/20261026_AI網通市場模型_v0.2.3.xlsx｜Mkt!C45:F45 | I7: 同上
A8: mpl_29 | B8: AI 可插拔光模組市場 2029 | C8: US$B | E8: 72.9348 | G8: Derived | H8: markets/network/dist/20261026_AI網通市場模型_v0.2.3.xlsx｜Mkt!C45:F45 | I8: 同上
A9: mcp_26 | B9: AI CPO 光學市場 2026 | C9: US$B | E9: 0.300538 | G9: Derived | H9: markets/network/dist/20261026_AI網通市場模型_v0.2.3.xlsx｜Mkt!C44:F44 | I9: 共同封裝光學；網通模型的 CPO 滲透路徑
A10: mcp_27 | B10: AI CPO 光學市場 2027 | C10: US$B | E10: 2.818985 | G10: Derived | H10: markets/network/dist/20261026_AI網通市場模型_v0.2.3.xlsx｜Mkt!C44:F44 | I10: 同上
A11: mcp_28 | B11: AI CPO 光學市場 2028 | C11: US$B | E11: 6.4435 | G11: Derived | H11: markets/network/dist/20261026_AI網通市場模型_v0.2.3.xlsx｜Mkt!C44:F44 | I11: 同上
A12: mcp_29 | B12: AI CPO 光學市場 2029 | C12: US$B | E12: 11.74736 | G12: Derived | H12: markets/network/dist/20261026_AI網通市場模型_v0.2.3.xlsx｜Mkt!C44:F44 | I12: 同上
A13: itc_26 | B13: AI IT 資本支出 2026 | C13: US$B | E13: 781.87292 | G13: Derived | H13: markets/network/dist/20261026_AI網通市場模型_v0.2.3.xlsx｜Mkt!C27:F27 | I13: Recon 用：新易盛 AI 營收 ÷ AI IT 資本支出
A14: itc_27 | B14: AI IT 資本支出 2027 | C14: US$B | E14: 1565.35 | G14: Derived | H14: markets/network/dist/20261026_AI網通市場模型_v0.2.3.xlsx｜Mkt!C27:F27 | I14: 同上
A15: itc_28 | B15: AI IT 資本支出 2028 | C15: US$B | E15: 1984.2639 | G15: Derived | H15: markets/network/dist/20261026_AI網通市場模型_v0.2.3.xlsx｜Mkt!C27:F27 | I15: 同上
A16: itc_29 | B16: AI IT 資本支出 2029 | C16: US$B | E16: 2260.3903 | G16: Derived | H16: markets/network/dist/20261026_AI網通市場模型_v0.2.3.xlsx｜Mkt!C27:F27 | I16: 同上
... A27: um29_C | B27: 情境 C：2029 顆數 ÷ 基準 | C27: x | E27: 0.6 | G27: Assumed | H27: tsmc/dist/20261028_台積電個股模型_v0.4.xlsx｜In!E42 | I27: 同上
A28: B. 新易盛份額與單價（本專案為權威：新易盛在 AI 光模組的份額，規則第 13 條）
A29: rel_27 | B29: 可插拔份額 2027 ÷ 2026（相對值） | C29: x | D29: 0.8 | E29: 1 | F29: 1.15 | G29: Assumed | H29: https://lightcounting.com/newsletter/en/may-2026-optical-vendor-landscape-376：LightCounting 2025 排名新易盛第二（US$3.5B，+189%，首次超過 Coherent）（Interested-party） | I29: 中際旭創模型同年相對值 0.95（讓出份額給新易盛、Coherent）；新易盛持平時兩家合計仍在 65% 左右（Units 頁）
A30: rel_28 | B30: 可插拔份額 2028 ÷ 2026 | C30: x | D30: 0.65 | E30: 1 | F30: 1.2 | G30: Assumed | H30: 同上；1.6T 份額仍在爬坡（西南證券 9-15，Interested-party） | I30: 主要客戶轉單或 1.6T 落後為低值；美國限制另列
A31: rel_29 | B31: 可插拔份額 2029 ÷ 2026 | C31: x | D31: 0.55 | E31: 0.95 | F31: 1.2 | G31: Assumed | H31: 同上；2029 起 scale-up 光學與 CPO 比重上升 | I31: —
A32: us_27 | B32: 美國限制情境：份額相對值 2027（Sens 用） | C32: x | E32: 0.9 | G32: Assumed | H32: https://hao.cnyes.com/post/262773：花旗認為短期嚴格執行機率低；中國廠供美國大型雲端高速光模組約 60–70%（Interested-party） | I32: 新易盛境外營收占 97.92%（1H26，西南證券轉引公司）；泰國產能不必然豁免（美國價值含量門檻）
A33: us_28 | B33: 美國限制情境：份額相對值 2028（Sens 用） | C33: x | E33: 0.55 | G33: Assumed | H33: 同上；與中際旭創模型相同 | I33: —
A34: us_29 | B34: 美國限制情境：份額相對值 2029（Sens 用） | C34: x | E34: 0.5 | G34: Assumed | H34: 同上 | I34: —
A35: cpo_27 | B35: 新易盛占 CPO 光學金額 2027 | C35: % | D35: 0 | E35: 0.05 | F35: 0.2 | G35: Assumed | H35: https://stock.10jqka.com.cn/20260928/c680329640.shtml：NPO 預計 2027 年批量交付、2028 年規模化供應（公司說法經媒體轉載，Interested-party） | I35: 中際旭創模型 2027–29 為 10%／15%／20%；兩家合計 15–35%
A36: cpo_28 | B36: 新易盛占 CPO 光學金額 2028 | C36: % | D36: 0 | E36: 0.1 | F36: 0.25 | G36: Assumed | H36: 同上 | I36: —
A37: cpo_29 | B37: 新易盛占 CPO 光學金額 2029 | C37: % | D37: 0 | E37: 0.15 | F37: 0.3 | G37: Assumed | H37: 同上 | I37: —
A38: pxr_27 | B38: 單價係數 2027（相對網通模型每顆內容；基準 1） | C38: x | D38: 0.9 | E38: 1 | F38: 1.05 | G38: Assumed | H38: 網通模型每顆光學內容已含世代單價；本係數只在 Sens 動（降價快於模型） | I38: 與中際旭創模型相同
A39: pxr_28 | B39: 單價係數 2028 | C39: x | D39: 0.8 | E39: 1 | F39: 1.05 | G39: Assumed | H39: 同上 | I39: —
A40: pxr_29 | B40: 單價係數 2029 | C40: x | D40: 0.72 | E40: 1 | F40: 1.05 | G40: Assumed | H40: 同上 | I40: —
A41: fx | B41: 人民幣兌美元（RMB／USD） | C41: RMB | D41: 6.5 | E41: 6.72 | F41: 7 | G41: Verified | H41: Siliconomics SIF_fx_rmb（中國經濟網 2026-10-16 中間價 6.7220；v0.8.2 前 7.1） | I41: 1Q26 財務費用 5.22 億元，主因匯兌損失（每日經濟新聞轉載公司一季報）
A42: C. 其他營收（國內、電信、非 AI 數通；網通模型未涵蓋）
A43: oth_s | B43: 其他營收 ÷ 總營收（FY2025、FY2026） | C43: % | D43: 0.03 | E43: 0.05 | F43: 0.1 | G43: Assumed | H43: 西南證券 9-15（網址見 Sources）：境外收入占比約 97.92%（1H26） | I43: 光互聯產品占營收 99.9%（1H26 208.83 ÷ 209.10）；非 AI 部分比重：未找到
A44: g_oth | B44: 其他營收年增（FY2027 起） | C44: % | D44: 0 | E44: 0.1 | F44: 0.2 | G44: Assumed | H44: 與中際旭創模型相同 | I44: —
A45: D. 毛利率
A46: gm_h2 | B46: 2H26 毛利率 | C46: % | D46: 0.45 | E46: 0.48 | F46: 0.5 | G46: Assumed | H46: https://m.gelonghui.com/news/5306856：2Q26 綜合毛利率 47.96%（季減 1.20pt）→ 1Q26 49.16%（推導） | I46: https://stock.10jqka.com.cn/20260915/c679905127.shtml：1H26 綜合毛利率 48.44%
A47: gm_27 | B47: 毛利率 2027 | C47: % | D47: 0.43 | E47: 0.47 | F47: 0.49 | G47: Assumed | H47: 1.6T 占比上升（上推）vs 降價（下壓）；FY2024 光互聯 44.85%、FY2025 47.81%（公司） | I47: 開源證券 2026E–2028E 47.0%（Interested-party）
A48: gm_28 | B48: 毛利率 2028 | C48: % | D48: 0.4 | E48: 0.46 | F48: 0.48 | G48: Assumed | H48: 同上；與中際旭創模型路徑相同 | I48: —
A49: gm_29 | B49: 毛利率 2029 | C49: % | D49: 0.36 | E49: 0.45 | F49: 0.47 | G49: Assumed | H49: 同上 | I49: —
A50: E. FY2026 錨點（1H26 實績＋2H26 假設）
A51: h1_rev | B51: 1H26 營收 | C51: RMB B | E51: 20.91 | G51: Verified | H51: https://m.c114.com.cn/w123-1316262.html：209.1 億元（+100.34%） | I51: https://finance.eastmoney.com/a/202608243851382445.html：同值
A52: h1_gm | B52: 1H26 綜合毛利率 | C52: % | E52: 0.4844 | G52: Verified | H52: https://stock.10jqka.com.cn/20260915/c679905127.shtml：綜合毛利率 48.44%（西南證券轉引公司半年報） | I52: https://m.c114.com.cn/w123-1316262.html：光互聯產品 48.46%（占營收 99.9%）
A53: h1_ni | B53: 1H26 歸母淨利 | C53: RMB B | E53: 7.529 | G53: Verified | H53: https://m.c114.com.cn/w123-1316262.html：75.29 億元（+90.98%） | I53: https://finance.eastmoney.com/a/202608243851382445.html：同值
A54: h1_eps | B54: 1H26 基本 EPS（轉增後） | C54: RMB | E54: 5.41 | G54: Verified | H54: https://finance.eastmoney.com/a/202608243851382445.html：5.41 元（+90.49%） | I54: https://quartr.com/events/eoptolink-technology-inc-ltd-300502-q2-2026_FgrWDhx6：5.41（去年同期 2.84）
A55: q1_rev | B55: 1Q26 營收 | C55: RMB B | E55: 8.338 | G55: Verified | H55: https://www.nbd.com.cn/articles/2026-04-24/4356482.html：約 83.4 億元（+105.76%） | I55: 1H26 209.10 − 2Q26 125.72 ＝ 83.38（長江證券轉引公司）
A56: q_g | B56: 3Q26、4Q26 營收季增 | C56: % | D56: 0.1 | E56: 0.2 | F56: 0.4 | G56: Assumed | H56: 2Q26 ÷ 1Q26 − 1 ＝ +50.8%（公司）；1.6T 下半年放量節奏加快（公司說法，同花順 9-28） | I56: https://pl.investing.com/equities/eoptolink-tech-earnings：3Q26 共識營收 177.6 億元（隱含季增約 +41%，Interested-party）；季報預計 2026-10-30 公布
A57: opx_h2 | B57: 2H26 營業費用、減值與其他 ÷ 營收 | C57: % | D57: 0.04 | E57: 0.05 | F57: 0.07 | G57: Assumed | H57: 2Q26 殘差約 4.9%（Q 頁推導；1Q26 含匯兌損失 5.22 億元，約 9.8%） | I57: https://pdf.dfcfw.com/pdf/H3_AP202608251828397684_1.pdf：1H26 銷售 0.48%、管理 0.62%、研發 2.1%（開源證券）
A58: tx | B58: 有效稅率 | C58: % | D58: 0.08 | E58: 0.12 | F58: 0.15 | G58: Assumed | H58: 成都母公司高新技術企業 15%；泰國子公司稅率與獲利占比：未找到 | I58: 低於 15% 的依據：FY2025 若用 15%，殘差營業費用（2.6%）低於研發費用率 2.83%，不合理（Q 頁）
A59: attr | B59: 歸母淨利 ÷ 淨利（含少數股權） | C59: x | D59: 0.99 | E59: =9.532/(9.532+0.021) -> 0.99780174 | F59: 1 | G59: Derived | H59: https://pdf.dfcfw.com/pdf/H3_AP202608251828397684_1.pdf：FY2025 少數股東損益 0.21 億元（開源證券財務摘要） | I59: 歸母 95.32 億元（公司）
A60: sh_post | B60: 轉增後總股數 | C60: 十億股 | E60: 1.394 | G60: Verified | H60: https://pdf.dfcfw.com/pdf/H3_AP202608251828397684_1.pdf：總股本 13.94 億股（開源證券 8-25） | I60: https://quote.cfi.cn/300502.html：總股本 13.95 億股；10 轉 4 基數約 9.94 億股（每日經濟新聞）
A61: q_sh_h1 | B61: 1H26 加權股數 | C61: 十億股 | E61: =h1_ni/h1_eps -> 1.3916821 | G61: Derived | H61: 歸母淨利 ÷ 基本 EPS | I61: —
A62: F. FY2025 實績
A63: a25_rev_in | B63: FY2025 營收 | C63: RMB B | E63: 24.842 | G63: Verified | H63: https://finance.eastmoney.com/a/202604243717729349.html：248.42 億元（+187.29%） | I63: https://www.nbd.com.cn/articles/2026-04-24/4356482.html：約 248.4 億元
A64: a25_gm_in | B64: FY2025 毛利率（光互聯產品代用，占營收 99.7%） | C64: % | E64: 0.4781 | G64: Verified | H64: 每日經濟新聞轉載公司年報（網址見 Sources）：光互聯產品毛利率 47.81%（2024 年 44.85%） | I64: 虎嗅（網址見 Sources）：同值；全公司毛利率：未找到
A65: a25_ni_in | B65: FY2025 歸母淨利 | C65: RMB B | E65: 9.532 | G65: Verified | H65: https://finance.eastmoney.com/a/202604243717729349.html：95.32 億元（+235.89%） | I65: https://www.nbd.com.cn/articles/2026-04-24/4356482.html：同值
A66: a25_eps_in | B66: FY2025 基本 EPS（轉增前） | C66: RMB | E66: 9.61 | G66: Verified | H66: https://finance.eastmoney.com/a/202604243717729349.html：9.61 元 | I66: https://www.nbd.com.cn/articles/2026-04-24/4356482.html：同值
A67: a25_sh_in | B67: FY2025 股數（轉增後重述） | C67: 十億股 | E67: =a25_ni_in/(a25_eps_in/1.4) -> 1.3886368 | G67: Derived | H67: 歸母淨利 ÷（EPS ÷ 1.4）；10 轉 4（FY2025 年度分配） | I67: 重述 EPS ＝ 9.61 ÷ 1.4 ＝ 6.86
A68: G. 營業費用、股數（FY2027 起）
A69: phi | B69: 營業費用（含減值與其他）成長對營收成長的彈性 | C69: x | D69: 0.3 | E69: 0.6 | F69: 1 | G69: Analogy | H69: 中際旭創模型 0.61（Derived）；本公司 FY2026 推導值（Q 頁 B26）因 1Q26 匯兌損失失真，不採用 | I69: FY2025 研發 7.02 億元、占營收 2.83%（公司）
A70: opx_adj | B70: 營業費用額外占營收比（Sens 用；基準 0） | C70: pt | D70: -0.01 | E70: 0 | F70: 0.02 | G70: Assumed | H70: 無 | I70: Sens 用 +2 個百分點
A71: sh_g | B71: 股數年變動 | C71: % | D71: -0.005 | E71: 0 | F71: 0.01 | G71: Assumed | H71: https://stock.10jqka.com.cn/20260820/c679144690.shtml：2026 年限制性股票 648.12 萬股（0.46%），授予價 212 元 | I71: 考核：2026 年營收 ≥ 500 億元、2026–27 累計 ≥ 1,400 億、2026–28 累計 ≥ 2,900 億（公司公告，Interested-party）
A72: mf | B72: AI 市場係數（Sens 用；FY2027 起） | C72: x | D72: 0.8 | E72: 1 | F72: 1.2 | G72: Assumed | H72: 網通模型 2027 年可插拔光模組 +84% | I72: ±20%
A73: H. 共識、券商、市場資料（只作 Recon 對帳，不作校準）
A74: cons_rev26 | B74: 共識 FY2026 營收 | C74: RMB B | E74: 55.189 | G74: Interested-party | H74: https://basic.10jqka.com.cn/300502/worth.html（2026-10-23；6 個月內 19 家，明細只列 10 家） | I74: 區間見同頁
A75: cons_ni26 | B75: 共識 FY2026 歸母淨利 | C75: RMB B | E75: 20.135 | G75: Interested-party | H75: https://basic.10jqka.com.cn/300502/worth.html（19 家） | I75: 天風（10-10）、國金（8-25）兩家特別高，拉高均值
A76: cons_eps26 | B76: 共識 FY2026 EPS | C76: RMB | E76: 15.05 | G76: Interested-party | H76: https://basic.10jqka.com.cn/300502/worth.html（19 家） | I76: —
A77: cons_rev27 | B77: 共識 FY2027 營收 | C77: RMB B | E77: 99.385 | G77: Interested-party | H77: https://basic.10jqka.com.cn/300502/worth.html（2026-10-23；6 個月內 19 家，明細只列 10 家） | I77: 區間見同頁
A78: cons_ni27 | B78: 共識 FY2027 歸母淨利 | C78: RMB B | E78: 36.358 | G78: Interested-party | H78: https://basic.10jqka.com.cn/300502/worth.html（19 家） | I78: 天風（10-10）、國金（8-25）兩家特別高，拉高均值
A79: cons_eps27 | B79: 共識 FY2027 EPS | C79: RMB | E79: 27.29 | G79: Interested-party | H79: https://basic.10jqka.com.cn/300502/worth.html（19 家） | I79: —
A80: cons_rev28 | B80: 共識 FY2028 營收 | C80: RMB B | E80: 143.815 | G80: Interested-party | H80: https://basic.10jqka.com.cn/300502/worth.html（2026-10-23；6 個月內 19 家，明細只列 10 家） | I80: 區間見同頁
A81: cons_ni28 | B81: 共識 FY2028 歸母淨利 | C81: RMB B | E81: 53.635 | G81: Interested-party | H81: https://basic.10jqka.com.cn/300502/worth.html（19 家） | I81: 天風（10-10）、國金（8-25）兩家特別高，拉高均值
A82: cons_eps28 | B82: 共識 FY2028 EPS | C82: RMB | E82: 39.93 | G82: Interested-party | H82: https://basic.10jqka.com.cn/300502/worth.html（19 家） | I82: —
A83: gs_ni26 | B83: 高盛 FY2026 歸母淨利（單一券商） | C83: RMB B | E83: 20.683 | G83: Interested-party | H83: https://wallstreetcn.com/articles/3777393：高盛（2026-07）2026–28 年 206.83、300.80、345.76 億元；目標價 633 元（29.3x 2027 年獲利） | I83: 共識均值明顯高於高盛（FY2027 +21%、FY2028 +55%）
A84: gs_ni27 | B84: 高盛 FY2027 歸母淨利（單一券商） | C84: RMB B | E84: 30.08 | G84: Interested-party | H84: https://wallstreetcn.com/articles/3777393：高盛（2026-07）2026–28 年 206.83、300.80、345.76 億元；目標價 633 元（29.3x 2027 年獲利） | I84: 共識均值明顯高於高盛（FY2027 +21%、FY2028 +55%）
A85: gs_ni28 | B85: 高盛 FY2028 歸母淨利（單一券商） | C85: RMB B | E85: 34.576 | G85: Interested-party | H85: https://wallstreetcn.com/articles/3777393：高盛（2026-07）2026–28 年 206.83、300.80、345.76 億元；目標價 633 元（29.3x 2027 年獲利） | I85: 共識均值明顯高於高盛（FY2027 +21%、FY2028 +55%）
... A89: tp_avg90 | B89: 同花順 90 天內機構目標均價 | C89: RMB | E89: 460.89 | G89: Interested-party | H89: https://stock.10jqka.com.cn/20260915/c679905127.shtml：15 家（買入 13、增持 2），目標均價 460.89 元 | I89: 多為 9 月前股價較高時給出
A90: I. 價格與估值
A91: px | B91: 股價（2026-10-23 收盤，A 股） | C91: RMB | E91: 261 | G91: Interested-party | H91: https://quote.cfi.cn/300502.html：261.00（+1.16%；前收 258.01；當日 236.10–263.54） | I91: https://www.etnet.com.hk/www/sc/ashares/quote.php?code=300502：同值
A92: px_hi | B92: 52 週高點 | C92: RMB | E92: 818.38 | G92: Interested-party | H92: https://www.etnet.com.hk/www/sc/ashares/quote.php?code=300502：52 週區間上緣 818.38 | I92: https://www.google.com/finance/quote/300502:SHE?hl=zh：另一資料商顯示 618.87（9-30），兩者不一致：未核實；2026-06-10 收盤 772.50（融中財經）
A93: px_0930 | B93: 股價（2026-09-30 收盤） | C93: RMB | E93: 389 | G93: Interested-party | H93: Google 財經（網址見 Sources）：389.00 | I93: 近一個月跌幅原因：未找到
A94: tp_wA | B94: 目標價情境權重 A | C94: % | E94: 0.3 | G94: Assumed | H94: Andy 可改（工作單 2026-10-25 預設 A 0.3／B 0.5／C 0.2） | I94: 三者合計應為 100%（Val 頁第 0 節列示）
A95: tp_wB | B95: 目標價情境權重 B | C95: % | E95: 0.5 | G95: Assumed | H95: Andy 可改（工作單 2026-10-25 預設 A 0.3／B 0.5／C 0.2） | I95: 三者合計應為 100%（Val 頁第 0 節列示）
A96: tp_wC | B96: 目標價情境權重 C | C96: % | E96: 0.2 | G96: Assumed | H96: Andy 可改（工作單 2026-10-25 預設 A 0.3／B 0.5／C 0.2） | I96: 三者合計應為 100%（Val 頁第 0 節列示）
A97: K. 目標價（DCF＋Comparable）與收斂法參數（v0.2 新增；黃底，Assumed，Andy 可改）
A98: tp_r | B98: 折現率／要求報酬（DCF） | C98: % | E98: 0.1 | G98: Assumed | H98: Andy 可改（工作單 2026-10-25 預設 10%；各市場同一值） | I98: DCF 與 Sens
A99: tp_g | B99: 長期成長率（DCF 永續；收斂法情境 B 的 FY2032 營收年增） | C99: % | E99: 0.04 | G99: Assumed | H99: Andy 可改（工作單預設 4%） | I99: —
A100: tp_roe | B100: ROE（近三年平均；DCF 再投資率＝tp_g ÷ tp_roe） | C100: % | E100: =AVERAGE(0.1337,0.4114,0.7239) -> 0.423 | G100: Derived | H100: stockanalysis 比率頁：FY2023 13.37%、FY2024 41.14%、FY2025 72.39%（GAAP 歸母口徑） | I100: 單一來源；近 12 月 72.08%（同站）
A101: tp_w_dcf | B101: 目標價中 DCF 的權重；其餘為 Comparable | C101: % | E101: 0.5 | G101: Assumed | H101: Andy 可改（工作單 2026-10-25 11:53 定 DCF／Comparable 各半） | I101: —
A102: fade_gA | B102: 收斂法：情境 A 於 FY2032 的營收年增（＝tp_g＋2pt） | C102: % | E102: =tp_g+0.02 -> 0.06 | G102: Assumed | H102: 工作單 2026-10-25 11:20 收斂法；FY2030 起由 FY2029 年增線性收斂 | I102: FY2030 起為收斂法，非驅動因子推導
A103: fade_gB | B103: 收斂法：情境 B 於 FY2032 的營收年增（＝tp_g） | C103: % | E103: =tp_g -> 0.04 | G103: Assumed | H103: 同上 | I103: —
A104: fade_gC | B104: 收斂法：情境 C 於 FY2032 的營收年增（＝tp_g−2pt） | C104: % | E104: =tp_g-0.02 -> 0.02 | G104: Assumed | H104: 同上 | I104: —
A105: fade_mA | B105: 收斂法：情境 A 的中段淨利率（＝情境 A FY2029 淨利率） | C105: % | E105: =PL!$G$86 -> 0.35727289 | G105: Derived | H105: PL 頁情境 A FY2029（公式於建置時連結） | I105: —
A106: fade_mB | B106: 收斂法：情境 B 的中段淨利率（＝FY2029 與十年平均的中點；十年平均以 FY2029 × 0.8 代替） | C106: % | E106: =(PL!$G$118+PL!$G$118*0.8)/2 -> 0.31758446 | G106: Assumed | H106: 十年平均淨利率（2016–2025，與本模型同口徑）：未找到，依工作單以 FY2029 × 0.8 代替；本列＝（FY2029＋FY2029 × 0.8）÷ 2 | I106: Andy 可改
A107: fade_mC | B107: 收斂法：情境 C 的中段淨利率（＝十年平均；以情境 C FY2029 × 0.8 代替） | C107: % | E107: =PL!$G$150*0.8 -> 0.27088876 | G107: Assumed | H107: 十年平均淨利率：未找到，依工作單以情境 C FY2029 淨利率 × 0.8 代替 | I107: Andy 可改
A108: cons_tp | B108: 市場共識目標價（賣方平均） | C108: RMB | E108: =tp_avg90 -> 460.89 | G108: Interested-party | H108: 同花順 90 天內機構目標均價（In 頁 tp_avg90；15 家，10 轉 4 後口徑） | I108: stockanalysis 預測頁平均 652.48（9 位；口徑疑為轉增前，不採）；多數目標價訂於 9 月前股價較高時
A109: cons_feps | B109: 共識 12 個月後前瞻 EPS（2/12 × FY2027＋10/12 × FY2028） | C109: RMB | E109: =2/12*cons_eps27+10/12*cons_eps28 -> 37.823333 | G109: Derived | H109: In 頁同花順共識 FY2027、FY2028 EPS（與本模型前瞻 EPS 同期間） | I109: 共識只放 Recon 與本列，不作校準
A111: 網通 CPO 三情境（v0.2.2；markets/network v0.2.3：A＝替代快、B＝平平、C＝慢；情境 A 為上方 A 節，B、C 為下列，各再乘同字母情境顆數係數）
A112: mplB_26 | B112: 情境 B：AI 可插拔光模組市場 CY2026 | C112: US$B | E112: 29.753262 | G112: Derived | H112: markets/network/dist/20261026_AI網通市場模型_v0.2.3.xlsx｜Mkt!C48:F48 | I112: 網通模型 CPO 情境 B（技術替代屬行業情境，公司讀同字母）
A113: mplB_27 | B113: 情境 B：AI 可插拔光模組市場 CY2027 | C113: US$B | E113: 54.688309 | G113: Derived | H113: markets/network/dist/20261026_AI網通市場模型_v0.2.3.xlsx｜Mkt!C48:F48 | I113: 同上
A114: mplB_28 | B114: 情境 B：AI 可插拔光模組市場 CY2028 | C114: US$B | E114: 61.21325 | G114: Derived | H114: markets/network/dist/20261026_AI網通市場模型_v0.2.3.xlsx｜Mkt!C48:F48 | I114: 同上
...

Sheet Q
A1: Q — 實績與 FY2026 錨點（十億人民幣；EPS 為人民幣；股數為十億股，轉增後）。藍字＝輸入；黑字＝公式。口徑：歸母淨利；FY2025 毛利率以光互聯產品（占營收 99.7%）代用
A2: FY2026 錨點＝1H26 實績＋2H26（3Q、4Q 營收依季增假設；毛利率 gm_h2；營業費用率 opx_h2）。營業費用、減值與其他為殘差：毛利 − 歸母淨利 ÷［（1 − 稅率）× 歸母比例］。3Q26 季報預計 2026-10-30 公布（截至 10-25 尚未公布），公布後以實績取代 3Q
A3: 項目 | B3: FY2025A | C3: 1H26（實績） | D3: 3Q26（假設） | E3: 4Q26（假設） | F3: 2H26 合計 | G3: FY2026 錨點 | H3: 標記 | I3: 說明
A4: 營收 | B4: =a25_rev_in -> 24.842 | C4: =h1_rev -> 20.91 | D4: =(h1_rev-q1_rev)*(1+q_g) -> 15.0864 | E4: =D4*(1+q_g) -> 18.10368 | F4: =D4+E4 -> 33.19008 | G4: =C4+F4 -> 54.10008 | H4: Verified／Assumed（3Q、4Q） | I4: 2Q26＝1H26 − 1Q26（125.72）；3Q＝2Q ×（1＋季增）
A5: 毛利 | B5: =B4*a25_gm_in -> 11.87696 | C5: =C4*h1_gm -> 10.128804 | D5: =D4*gm_h2 -> 7.241472 | E5: =E4*gm_h2 -> 8.6897664 | F5: =D5+E5 -> 15.931238 | G5: =C5+F5 -> 26.060042 | H5: Derived
A6: 毛利率 | B6: =B5/B4 -> 0.4781 | C6: =C5/C4 -> 0.4844 | D6: =D5/D4 -> 0.48 | E6: =E5/E4 -> 0.48 | F6: =F5/F4 -> 0.48 | G6: =G5/G4 -> 0.48170063 | H6: Derived
A7: 稅後歸母係數 ＝（1 − 稅率）× 歸母比例 | B7: =(1-tx)*attr -> 0.87806553 | C7: =(1-tx)*attr -> 0.87806553 | D7: =(1-tx)*attr -> 0.87806553 | E7: =(1-tx)*attr -> 0.87806553 | H7: Assumed／Derived
A8: 營業費用、減值與其他（淨） | B8: =B5-B10/B7 -> 1.0212784 | C8: =C5-C10/C7 -> 1.5542731 | D8: =D4*opx_h2 -> 0.75432 | E8: =E4*opx_h2 -> 0.905184 | F8: =D8+E8 -> 1.659504 | G8: =C8+F8 -> 3.2137771 | H8: Derived（殘差）／Assumed（2H） | I8: 1H26 殘差含 1Q26 匯兌損失（財務費用 5.22 億元）
A9: 營業費用率 | B9: =B8/B4 -> 0.041110957 | C9: =C8/C4 -> 0.074331569 | D9: =D8/D4 -> 0.05 | E9: =E8/E4 -> 0.05 | F9: =F8/F4 -> 0.05 | G9: =G8/G4 -> 0.059404295 | H9: Derived
A10: 歸母淨利 | B10: =a25_ni_in -> 9.532 | C10: =h1_ni -> 7.529 | D10: =(D5-D8)*D7 -> 5.6961446 | E10: =(E5-E8)*E7 -> 6.8353735 | F10: =D10+E10 -> 12.531518 | G10: =C10+F10 -> 20.060518 | H10: Verified／Derived（3Q、4Q）
A11: 淨利率 | B11: =B10/B4 -> 0.38370502 | C11: =C10/C4 -> 0.36006695 | D11: =D10/D4 -> 0.37756818 | E11: =E10/E4 -> 0.37756818 | F11: =F10/F4 -> 0.37756818 | G11: =G10/G4 -> 0.37080385 | H11: Derived
A12: 股數（十億股，轉增後） | B12: =a25_sh_in -> 1.3886368 | C12: =q_sh_h1 -> 1.3916821 | D12: =sh_post -> 1.394 | E12: =sh_post -> 1.394 | G12: =(C12*2+D12+E12)/4 -> 1.392841 | H12: Derived | I12: FY2026＝1H 加權 × ½ ＋ 期末股數 × ½（近似）
A13: EPS | B13: =B10/B12 -> 6.8642857 | C13: =C10/C12 -> 5.41 | D13: =D10/D12 -> 4.0861869 | E13: =E10/E12 -> 4.9034243 | G13: =G10/G12 -> 14.40259 | H13: Derived | I13: FY2025 轉增後重述 ＝ 9.61 ÷ 1.4；1H26 公司揭露 5.41
A14: 其他營收（國內、電信等；＝營收 × oth_s） | B14: =B4*oth_s -> 1.2421 | G14: =G4*oth_s -> 2.705004 | H14: Assumed
A15: AI 營收（＝營收 − 其他） | B15: =B4-B14 -> 23.5999 | G15: =G4-G14 -> 51.395076 | H15: Derived
A16: AI 營收（US$B ＝ ÷ fx） | B16: =B15/fx -> 3.5118899 | G16: =G15/fx -> 7.6480768 | H16: Derived
A18: 季度拆分（推導）
A19: 2Q26 營業費用、減值與其他 ÷ 營收（殘差；2Q26 毛利率 47.96%、歸母淨利 47.49 億元） | B19: =(12.572*0.4796-4.749/((1-tx)*attr))/12.572 -> 0.049399541
A20: 1Q26 營業費用、減值與其他 ÷ 營收（殘差；1Q26 毛利率 49.16%、歸母淨利 27.80 億元） | B20: =(q1_rev*0.4916-(h1_ni-4.749)/((1-tx)*attr))/q1_rev -> 0.11188655
A21: FY2026 錨點與共識的距離（參考；校準未使用共識）
A22: FY2026 營收 ÷ 共識 − 1 | B22: =G4/cons_rev26-1 -> -0.019730743
A23: FY2026 歸母淨利 ÷ 共識 − 1 | B23: =G10/cons_ni26-1 -> -0.00369913
A24: FY2026 營收年增 | B24: =G4/B4-1 -> 1.1777667
A25: FY2026 營業費用年增 | B25: =G8/B8-1 -> 2.1468179
A26: 營業費用彈性（營業費用年增 ÷ 營收年增；受 1Q26 匯兌損失影響，In 頁 phi 不採用） | B26: =B25/B24 -> 1.8227871
A27: 1H26 EPS（模型）vs 公司揭露 5.41 | B27: =C13/h1_eps-1 -> 0
A28: FY2026 營收 vs 股權激勵第一期考核 500 億元（÷ 50 − 1） | B28: =G4/50-1 -> 0.0820016
A30: 官方報告產品別（FY2025 年報；分部原則第 3 條）
A31: 光互聯產品營收（含 AI 與國內、電信） | B31: =B4*0.997 -> 24.767474 | H31: Verified | I31: 每日經濟新聞轉載公司 FY2025 年報：光互聯產品占營收 99.7%（金額為推得）
A32: 其他產品營收（差額） | B32: =B4-B31 -> 0.074526 | H32: Derived | I32: 合併營收 − 光互聯產品
A33: 檢查：分部合計 − 合併營收 | B33: =ROUND(B31+B32-B4,6) -> 0 | H33: Derived | I33: 應為 0；PL 的 AI 營收屬光互聯產品，推估年以 AI／其他拆分

Sheet Units
A1: Units — 新易盛在 AI 光模組的份額（本專案權威，規則第 13 條）。市場取自 markets/network（加速器顆數 × 每顆光學內容；美元）；中際旭創份額取自 innolight 成品（唯讀）
A3: 項目 | B3: 單位 | C3: CY2026 | D3: CY2027 | E3: CY2028 | F3: CY2029 | G3: 說明
A4: AI 可插拔光模組市場（情境 A） | B4: US$B | C4: =PL!D63 -> 29.753262 | D4: =PL!E63 -> 53.560715 | E4: =PL!F63 -> 57.9915 | F4: =PL!G63 -> 72.9348 | G4: markets/network Mkt 頁
A5: AI CPO 光學市場（情境 A） | B5: US$B | C5: =PL!D64 -> 0.300538 | D5: =PL!E64 -> 2.818985 | E5: =PL!F64 -> 6.4435 | F5: =PL!G64 -> 11.74736 | G5: 同上
A6: 新易盛可插拔有效份額 | B6: % | C6: =PL!D68 -> 0.25705003 | D6: =PL!E68 -> 0.25705003 | E6: =PL!F68 -> 0.25705003 | F6: =PL!G68 -> 0.24419753 | G6: FY2026 以 1H26 實績＋2H26 假設校準
A7: 中際旭創可插拔有效份額（innolight 成品，情境 A） | B7: % | C7: =inl_26 -> 0.44568706 | D7: =inl_27 -> 0.42340271 | E7: =inl_28 -> 0.40111835 | F7: =inl_29 -> 0.378834 | G7: 唯讀；中際旭創份額的權威在 innolight/
A8: 兩家合計可插拔份額 | B8: % | C8: =C6+C7 -> 0.70273709 | D8: =D6+D7 -> 0.68045273 | E8: =E6+E7 -> 0.65816838 | F8: =F6+F7 -> 0.62303153 | G8: 其餘為 Coherent、光迅、Lumentum、華工等
A9: 新易盛 AI 營收（情境 A；美元） | B9: US$B | C9: =PL!D71 -> 7.6480768 | D9: =PL!E71 -> 13.908732 | E9: =PL!F71 -> 15.551067 | F9: =PL!G71 -> 19.572602
A10: 其他廠商（Coherent 等）＝ 可插拔 ×（1 − 兩家合計份額） | B10: US$B | C10: =C4*(1-C8) -> 8.8445414 | D10: =D4*(1-D8) -> 17.11518 | E10: =E4*(1-E8) -> 19.823328 | F10: =F4*(1-F8) -> 27.49412 | G10: 不含 CPO
A11: 新易盛 AI 營收 ÷ AI IT 資本支出 | B11: % | C11: =PL!D71/itc_26 -> 0.009781739 | D11: =PL!E71/itc_27 -> 0.0088853818 | E11: =PL!F71/itc_28 -> 0.0078371968 | F11: =PL!G71/itc_29 -> 0.0086589479 | G11: markets/network 的 AI IT 資本支出（加速器 × 每顆 IT capex）
A13: 讀法：FY2026 有效份額由 1H26 實績＋2H26 假設校準；與中際旭創合計約三分之二，其餘由 Coherent 等分食。份額相對值與 CPO 份額是 Assumed，是最需要每季檢查的輸入。

Sheet PL
A1: PL — 新易盛損益（RMB B）。FY2025A 實績、FY2026 錨點（1H26 實績＋2H26 假設），FY2027 起為模型。FY(t)＝CY(t)。三情境各一個完整推導區塊（本頁下方），頂端為摘要。FY2026 三情境相同；FY2027 起三情境讀不同的網通 CPO 情境（A 替代快、C 慢），顆數係數從 CY2028 開始
A2: 灰底＝FY2030–FY2032 收斂法，非驅動因子推導（上游市場層只到 2029）：營收年增由 FY2029 線性收斂到 fade_g（A＝tp_g＋2pt、B＝tp_g、C＝tp_g−2pt），淨利率由 FY2029 線性收斂到 fade_m（In 頁 K 節），FY2032 達到；股數依 sh_g
A3: 情境／項目 | B3: 單位 | C3: FY2025A | D3: FY2026（錨點） | E3: FY2027 | F3: FY2028 | G3: FY2029 | H3: FY2030（收斂） | I3: FY2031（收斂） | J3: FY2032（收斂） | K3: 說明
A4: 情境 A
A5: 營收 | B5: RMB B | C5: =C75 -> 24.842 | D5: =D75 -> 54.10008 | E5: =E75 -> 96.442187 | F5: =F75 -> 107.77622 | G5: =G75 -> 135.12824 | H5: =H75 -> 160.69318 | I5: =I75 -> 180.71477 | J5: =J75 -> 191.55765
A6: 營收年增 | B6: % | D6: =D76 -> 1.1777667 | E6: =E76 -> 0.78266255 | F6: =F76 -> 0.11752156 | G6: =G76 -> 0.2537853 | H6: =H76 -> 0.1891902 | I6: =I76 -> 0.1245951 | J6: =J76 -> 0.06
A7: AI 營收 | B7: RMB B | C7: =C72 -> 23.5999 | D7: =D72 -> 51.395076 | E7: =E72 -> 93.466682 | F7: =F72 -> 104.50317 | G7: =G72 -> 131.52788
A8: 其他營收 | B8: RMB B | C8: =C74 -> 1.2421 | D8: =D74 -> 2.705004 | E8: =E74 -> 2.9755044 | F8: =F74 -> 3.2730548 | G8: =G74 -> 3.6003603
A9: AI ÷ 營收 | B9: % | C9: =C77 -> 0.95 | D9: =D77 -> 0.95 | E9: =E77 -> 0.96914727 | F9: =F77 -> 0.96963101 | G9: =G77 -> 0.97335597
A10: 毛利率 | B10: % | C10: =C79 -> 0.4781 | D10: =D79 -> 0.48170063 | E10: =E79 -> 0.47 | F10: =F79 -> 0.46 | G10: =G79 -> 0.45
A11: 淨利率 | B11: % | C11: =C86 -> 0.38370502 | D11: =D86 -> 0.37080385 | E11: =E86 -> 0.36969025 | F11: =F86 -> 0.36271841 | G11: =G86 -> 0.35727289 | H11: =H86 -> 0.35727289 | I11: =I86 -> 0.35727289 | J11: =J86 -> 0.35727289
A12: 歸母淨利 | B12: RMB B | C12: =C85 -> 9.532 | D12: =D85 -> 20.060518 | E12: =E85 -> 35.653736 | F12: =F85 -> 39.09242 | G12: =G85 -> 48.277658 | H12: =H85 -> 57.411318 | I12: =I85 -> 64.564487 | J12: =J85 -> 68.438356
A13: EPS | B13: RMB | C13: =C88 -> 6.8642857 | D13: =D88 -> 14.40259 | E13: =E88 -> 25.576568 | F13: =F88 -> 28.043343 | G13: =G88 -> 34.632466 | H13: =H88 -> 41.18459 | I13: =I88 -> 46.315988 | J13: =J88 -> 49.094947
A14: EPS 年增 | B14: % | D14: =D89 -> 1.0981921 | E14: =E89 -> 0.77583117 | F14: =F89 -> 0.096446685 | G14: =G89 -> 0.23496212 | H14: =H89 -> 0.1891902 | I14: =I89 -> 0.1245951 | J14: =J89 -> 0.06
A16: 情境 B
A17: 營收 | B17: RMB B | C17: =C107 -> 24.842 | D17: =D107 -> 54.10008 | E17: =E107 -> 98.011094 | F17: =F107 -> 89.595716 | G17: =G107 -> 118.55943 | H17: =H107 -> 145.69146 | I17: =I107 -> 165.27585 | J17: =J107 -> 171.88688
A18: 營收年增 | B18: % | D18: =D108 -> 1.1777667 | E18: =E108 -> 0.81166264 | F18: =F108 -> -0.085861489 | G18: =G108 -> 0.32327121 | H18: =H108 -> 0.22884748 | I18: =I108 -> 0.13442374 | J18: =J108 -> 0.04
A19: AI 營收 | B19: RMB B | C19: =C104 -> 23.5999 | D19: =D104 -> 51.395076 | E19: =E104 -> 95.03559 | F19: =F104 -> 86.322661 | G19: =G104 -> 114.95907
A20: 其他營收 | B20: RMB B | C20: =C106 -> 1.2421 | D20: =D106 -> 2.705004 | E20: =E106 -> 2.9755044 | F20: =F106 -> 3.2730548 | G20: =G106 -> 3.6003603
A21: AI ÷ 營收 | B21: % | C21: =C109 -> 0.95 | D21: =D109 -> 0.95 | E21: =E109 -> 0.96964115 | F21: =F109 -> 0.96346862 | G21: =G109 -> 0.96963244
A22: 毛利率 | B22: % | C22: =C111 -> 0.4781 | D22: =D111 -> 0.48170063 | E22: =E111 -> 0.47 | F22: =F111 -> 0.46 | G22: =G111 -> 0.45
A23: 淨利率 | B23: % | C23: =C118 -> 0.38370502 | D23: =D118 -> 0.37080385 | E23: =E118 -> 0.3698776 | F23: =F118 -> 0.35707566 | G23: =G118 -> 0.35287162 | H23: =H118 -> 0.34110923 | I23: =I118 -> 0.32934684 | J23: =J118 -> 0.31758446
A24: 歸母淨利 | B24: RMB B | C24: =C117 -> 9.532 | D24: =D117 -> 20.060518 | E24: =E117 -> 36.252108 | F24: =F117 -> 31.99245 | G24: =G117 -> 41.836258 | H24: =H117 -> 49.696701 | I24: =I117 -> 54.433079 | J24: =J117 -> 54.588602
A25: EPS | B25: RMB | C25: =C120 -> 6.8642857 | D25: =D120 -> 14.40259 | E25: =E120 -> 26.005816 | F25: =F120 -> 22.950107 | G25: =G120 -> 30.011663 | H25: =H120 -> 35.650431 | I25: =I120 -> 39.04812 | J25: =J120 -> 39.159686
A26: EPS 年增 | B26: % | D26: =D121 -> 1.0981921 | E26: =E121 -> 0.80563473 | F26: =F121 -> -0.11750098 | G26: =G121 -> 0.30769162 | H26: =H121 -> 0.18788589 | I26: =I121 -> 0.095305678 | J26: =J121 -> 0.0028571429
A28: 情境 C
A29: 營收 | B29: RMB B | C29: =C139 -> 24.842 | D29: =D139 -> 54.10008 | E29: =E139 -> 98.795548 | F29: =F139 -> 68.831088 | G29: =G139 -> 85.584508 | H29: =H139 -> 100.04253 | I29: =I139 -> 109.49318 | J29: =J139 -> 111.68305
A30: 營收年增 | B30: % | D30: =D140 -> 1.1777667 | E30: =E140 -> 0.82616269 | F30: =F140 -> -0.30329767 | G30: =G140 -> 0.24339903 | H30: =H140 -> 0.16893269 | I30: =I140 -> 0.094466343 | J30: =J140 -> 0.02
A31: AI 營收 | B31: RMB B | C31: =C136 -> 23.5999 | D31: =D136 -> 51.395076 | E31: =E136 -> 95.820043 | F31: =F136 -> 65.558033 | G31: =G136 -> 81.984148
A32: 其他營收 | B32: RMB B | C32: =C138 -> 1.2421 | D32: =D138 -> 2.705004 | E32: =E138 -> 2.9755044 | F32: =F138 -> 3.2730548 | G32: =G138 -> 3.6003603
A33: AI ÷ 營收 | B33: % | C33: =C141 -> 0.95 | D33: =D141 -> 0.95 | E33: =E141 -> 0.9698822 | F33: =F141 -> 0.95244802 | G33: =G141 -> 0.9579321
A34: 毛利率 | B34: % | C34: =C143 -> 0.4781 | D34: =D143 -> 0.48170063 | E34: =E143 -> 0.47 | F34: =F143 -> 0.46 | G34: =G143 -> 0.45
A35: 淨利率 | B35: % | C35: =C150 -> 0.38370502 | D35: =D150 -> 0.37080385 | E35: =E150 -> 0.36996904 | F35: =F150 -> 0.34259019 | G35: =G150 -> 0.33861096 | H35: =H150 -> 0.31603689 | I35: =I150 -> 0.29346283 | J35: =J150 -> 0.27088876
A36: 歸母淨利 | B36: RMB B | C36: =C149 -> 9.532 | D36: =D149 -> 20.060518 | E36: =E149 -> 36.551294 | F36: =F149 -> 23.580855 | G36: =G149 -> 28.979852 | H36: =H149 -> 31.61713 | I36: =I149 -> 32.132179 | J36: =J149 -> 30.253682
A37: EPS | B37: RMB | C37: =C152 -> 6.8642857 | D37: =D152 -> 14.40259 | E37: =E152 -> 26.220441 | F37: =F152 -> 16.915965 | G37: =G152 -> 20.78899 | H37: =H152 -> 22.680868 | I37: =I152 -> 23.050343 | J37: =J152 -> 21.702785
A38: EPS 年增 | B38: % | D38: =D153 -> 1.0981921 | E38: =E153 -> 0.82053651 | F38: =F153 -> -0.3548558 | G38: =G153 -> 0.22895679 | H38: =H153 -> 0.091003841 | I38: =I153 -> 0.016290176 | J38: =J153 -> -0.058461538
A40: 核對（應為 0）：FY2026 模型營收、AI 營收、歸母淨利 − 錨點（校準恆等式）
A41: 情境 A：營收差（RMB B） | D41: =D75-a26_rev -> 0
A42: 情境 A：AI 營收差（RMB B） | D42: =D72-a26_ai -> 0
A43: 情境 A：稅前利益 ×（1 − 稅率）× 歸母比例 − 歸母淨利錨點 | D43: =D83*(1-tx)*attr-a26_ni -> 0
A60: 情境 A：基準（顆數係數 1.0）；網通 CPO 情境 A（替代快）
A61: 項目 | B61: 單位 | C61: FY2025A | D61: FY2026（錨點） | E61: FY2027 | F61: FY2028 | G61: FY2029 | H61: FY2030（收斂） | I61: FY2031（收斂） | J61: FY2032（收斂） | K61: 說明
A62: A. AI 營收（D 欄＝FY2026 校準年；E–G＝FY2027–FY2029）
A63: AI 可插拔光模組市場 × 情境顆數係數 | B63: US$B | D63: =mpl_26*1 -> 29.753262 | E63: =mpl_27*1*1 -> 53.560715 | F63: =mpl_28*um28_A*1 -> 57.9915 | G63: =mpl_29*um29_A*1 -> 72.9348
A64: AI CPO 光學市場 × 情境顆數係數 | B64: US$B | D64: =mcp_26*1 -> 0.300538 | E64: =mcp_27*1 -> 2.818985 | F64: =mcp_28*um28_A -> 6.4435 | G64: =mcp_29*um29_A -> 11.74736
A65: 人民幣兌美元 | B65: RMB | D65: =fx -> 6.72 | E65: =fx -> 6.72 | F65: =fx -> 6.72 | G65: =fx -> 6.72 | K65: FY2026 校準用基準匯率；Sens 只動 FY2027 起
A66: 新易盛可插拔有效份額（FY2026 校準）＝ AI 營收（美元）÷ 可插拔市場 | B66: % | D66: =a26_aiu/D63 -> 0.25705003 | K66: Derived：FY2026 CPO 營收視為 0；FY2027 起乘相對值
A67: 份額相對值（÷ FY2026） | B67: x | D67: =1 -> 1 | E67: =rel_27 -> 1 | F67: =rel_28 -> 1 | G67: =rel_29 -> 0.95
A68: 可插拔有效份額 | B68: % | D68: =$D$66*D67 -> 0.25705003 | E68: =$D$66*E67 -> 0.25705003 | F68: =$D$66*F67 -> 0.25705003 | G68: =$D$66*G67 -> 0.24419753
A69: 單價係數（相對網通模型） | B69: x | D69: =1 -> 1 | E69: =pxr_27 -> 1 | F69: =pxr_28 -> 1 | G69: =pxr_29 -> 1
A70: 新易盛占 CPO 光學金額 | B70: % | D70: =0 -> 0 | E70: =cpo_27 -> 0.05 | F70: =cpo_28 -> 0.1 | G70: =cpo_29 -> 0.15
A71: AI 營收（美元） | B71: US$B | D71: =a26_aiu -> 7.6480768 | E71: =E63*E68*E69+E64*E70 -> 13.908732 | F71: =F63*F68*F69+F64*F70 -> 15.551067 | G71: =G63*G68*G69+G64*G70 -> 19.572602
A72: AI 營收 | B72: RMB B | C72: =a25_ai -> 23.5999 | D72: =D71*D65 -> 51.395076 | E72: =E71*E65 -> 93.466682 | F72: =F71*F65 -> 104.50317 | G72: =G71*G65 -> 131.52788
A73: B. 其他營收與合計
A74: 其他營收（國內、電信等） | B74: RMB B | C74: =a25_oth -> 1.2421 | D74: =a26_oth -> 2.705004 | E74: =D74*(1+g_oth) -> 2.9755044 | F74: =E74*(1+g_oth) -> 3.2730548 | G74: =F74*(1+g_oth) -> 3.6003603
A75: 營收 | B75: RMB B | C75: =a25_rev -> 24.842 | D75: =D72+D74 -> 54.10008 | E75: =E72+E74 -> 96.442187 | F75: =F72+F74 -> 107.77622 | G75: =G72+G74 -> 135.12824 | H75: =G75*(1+H76) -> 160.69318 | I75: =H75*(1+I76) -> 180.71477 | J75: =I75*(1+J76) -> 191.55765
A76: 營收年增 | B76: % | D76: =D75/C75-1 -> 1.1777667 | E76: =E75/D75-1 -> 0.78266255 | F76: =F75/E75-1 -> 0.11752156 | G76: =G75/F75-1 -> 0.2537853 | H76: =$G76+(fade_gA-$G76)*1/3 -> 0.1891902 | I76: =$G76+(fade_gA-$G76)*2/3 -> 0.1245951 | J76: =$G76+(fade_gA-$G76)*3/3 -> 0.06
A77: AI ÷ 營收 | B77: % | C77: =C72/C75 -> 0.95 | D77: =D72/D75 -> 0.95 | E77: =E72/E75 -> 0.96914727 | F77: =F72/F75 -> 0.96963101 | G77: =G72/G75 -> 0.97335597
A78: C. 損益
A79: 毛利率 | B79: % | C79: =a25_gp/a25_rev -> 0.4781 | D79: =a26_gp/a26_rev -> 0.48170063 | E79: =gm_27 -> 0.47 | F79: =gm_28 -> 0.46 | G79: =gm_29 -> 0.45 | K79: FY2027 起為輸入路徑（1.6T 占比上推 vs 降價下壓）
A80: 毛利 | B80: RMB B | C80: =C75*C79 -> 11.87696 | D80: =D75*D79 -> 26.060042 | E80: =E75*E79 -> 45.327828 | F80: =F75*F79 -> 49.577062 | G80: =G75*G79 -> 60.80771
A81: 營業費用、減值與其他（基準路徑） | B81: RMB B | C81: =a25_opx -> 1.0212784 | D81: =a26_opx -> 3.2137771 | E81: =D81*(1+MAX(0,phi*E76)) -> 4.7229589 | F81: =E81*(1+MAX(0,phi*F76)) -> 5.0559886 | G81: =F81*(1+MAX(0,phi*G76)) -> 5.8258699
A82: 營業費用、減值與其他 | B82: RMB B | C82: =C81 -> 1.0212784 | D82: =D81 -> 3.2137771 | E82: =E81+0*E75 -> 4.7229589 | F82: =F81+0*F75 -> 5.0559886 | G82: =G81+0*G75 -> 5.8258699
A83: 稅前利益（＝毛利 − 營業費用等） | B83: RMB B | C83: =C80-C82 -> 10.855682 | D83: =D80-D82 -> 22.846265 | E83: =E80-E82 -> 40.604869 | F83: =F80-F82 -> 44.521074 | G83: =G80-G82 -> 54.98184
A84: 稅前利益率 | B84: % | C84: =C83/C75 -> 0.43698904 | D84: =D83/D75 -> 0.42229633 | E84: =E83/E75 -> 0.42102808 | F84: =F83/F75 -> 0.41308809 | G84: =G83/G75 -> 0.40688636
A85: 歸母淨利 | B85: RMB B | C85: =a25_ni -> 9.532 | D85: =a26_ni -> 20.060518 | E85: =E83*(1-tx)*attr -> 35.653736 | F85: =F83*(1-tx)*attr -> 39.09242 | G85: =G83*(1-tx)*attr -> 48.277658 | H85: =H75*H86 -> 57.411318 | I85: =I75*I86 -> 64.564487 | J85: =J75*J86 -> 68.438356
A86: 淨利率 | B86: % | C86: =C85/C75 -> 0.38370502 | D86: =D85/D75 -> 0.37080385 | E86: =E85/E75 -> 0.36969025 | F86: =F85/F75 -> 0.36271841 | G86: =G85/G75 -> 0.35727289 | H86: =$G86+(fade_mA-$G86)*1/3 -> 0.35727289 | I86: =$G86+(fade_mA-$G86)*2/3 -> 0.35727289 | J86: =$G86+(fade_mA-$G86)*3/3 -> 0.35727289
A87: 股數（轉增後） | B87: 十億股 | C87: =a25_sh -> 1.3886368 | D87: =a26_sh -> 1.392841 | E87: =sh_post*(1+sh_g) -> 1.394 | F87: =E87*(1+sh_g) -> 1.394 | G87: =F87*(1+sh_g) -> 1.394 | H87: =G87*(1+sh_g) -> 1.394 | I87: =H87*(1+sh_g) -> 1.394 | J87: =I87*(1+sh_g) -> 1.394
A88: EPS | B88: RMB | C88: =C85/C87 -> 6.8642857 | D88: =D85/D87 -> 14.40259 | E88: =E85/E87 -> 25.576568 | F88: =F85/F87 -> 28.043343 | G88: =G85/G87 -> 34.632466 | H88: =H85/H87 -> 41.18459 | I88: =I85/I87 -> 46.315988 | J88: =J85/J87 -> 49.094947
A89: EPS 年增 | B89: % | D89: =D88/C88-1 -> 1.0981921 | E89: =E88/D88-1 -> 0.77583117 | F89: =F88/E88-1 -> 0.096446685 | G89: =G88/F88-1 -> 0.23496212 | H89: =H88/G88-1 -> 0.1891902 | I89: =I88/H88-1 -> 0.1245951 | J89: =J88/I88-1 -> 0.06
A92: 情境 B：CY2028 顆數 ×0.8、CY2029 ×0.85；網通 CPO 情境 B
A93: 項目 | B93: 單位 | C93: FY2025A | D93: FY2026（錨點） | E93: FY2027 | F93: FY2028 | G93: FY2029 | H93: FY2030（收斂） | I93: FY2031（收斂） | J93: FY2032（收斂） | K93: 說明
A94: A. AI 營收（D 欄＝FY2026 校準年；E–G＝FY2027–FY2029）
A95: AI 可插拔光模組市場 × 情境顆數係數 | B95: US$B | D95: =mplB_26*1 -> 29.753262 | E95: =mplB_27*1*1 -> 54.688309 | F95: =mplB_28*um28_B*1 -> 48.9706 | G95: =mplB_29*um29_B*1 -> 66.987208
A96: AI CPO 光學市場 × 情境顆數係數 | B96: US$B | D96: =mcpB_26*1 -> 0.300538 | E96: =mcpB_27*1 -> 1.691391 | F96: =mcpB_28*um28_B -> 2.5774 | G96: =mcpB_29*um29_B -> 4.992628
A97: 人民幣兌美元 | B97: RMB | D97: =fx -> 6.72 | E97: =fx -> 6.72 | F97: =fx -> 6.72 | G97: =fx -> 6.72 | K97: FY2026 校準用基準匯率；Sens 只動 FY2027 起
A98: 新易盛可插拔有效份額（FY2026 校準）＝ AI 營收（美元）÷ 可插拔市場 | B98: % | D98: =a26_aiu/D95 -> 0.25705003 | K98: Derived：FY2026 CPO 營收視為 0；FY2027 起乘相對值
A99: 份額相對值（÷ FY2026） | B99: x | D99: =1 -> 1 | E99: =rel_27 -> 1 | F99: =rel_28 -> 1 | G99: =rel_29 -> 0.95
A100: 可插拔有效份額 | B100: % | D100: =$D$98*D99 -> 0.25705003 | E100: =$D$98*E99 -> 0.25705003 | F100: =$D$98*F99 -> 0.25705003 | G100: =$D$98*G99 -> 0.24419753
A101: 單價係數（相對網通模型） | B101: x | D101: =1 -> 1 | E101: =pxr_27 -> 1 | F101: =pxr_28 -> 1 | G101: =pxr_29 -> 1
A102: 新易盛占 CPO 光學金額 | B102: % | D102: =0 -> 0 | E102: =cpo_27 -> 0.05 | F102: =cpo_28 -> 0.1 | G102: =cpo_29 -> 0.15
A103: AI 營收（美元） | B103: US$B | D103: =a26_aiu -> 7.6480768 | E103: =E95*E100*E101+E96*E102 -> 14.142201 | F103: =F95*F100*F101+F96*F102 -> 12.845634 | G103: =G95*G100*G101+G96*G102 -> 17.107005
A104: AI 營收 | B104: RMB B | C104: =a25_ai -> 23.5999 | D104: =D103*D97 -> 51.395076 | E104: =E103*E97 -> 95.03559 | F104: =F103*F97 -> 86.322661 | G104: =G103*G97 -> 114.95907
A105: B. 其他營收與合計
A106: 其他營收（國內、電信等） | B106: RMB B | C106: =a25_oth -> 1.2421 | D106: =a26_oth -> 2.705004 | E106: =D106*(1+g_oth) -> 2.9755044 | F106: =E106*(1+g_oth) -> 3.2730548 | G106: =F106*(1+g_oth) -> 3.6003603
A107: 營收 | B107: RMB B | C107: =a25_rev -> 24.842 | D107: =D104+D106 -> 54.10008 | E107: =E104+E106 -> 98.011094 | F107: =F104+F106 -> 89.595716 | G107: =G104+G106 -> 118.55943 | H107: =G107*(1+H108) -> 145.69146 | I107: =H107*(1+I108) -> 165.27585 | J107: =I107*(1+J108) -> 171.88688
A108: 營收年增 | B108: % | D108: =D107/C107-1 -> 1.1777667 | E108: =E107/D107-1 -> 0.81166264 | F108: =F107/E107-1 -> -0.085861489 | G108: =G107/F107-1 -> 0.32327121 | H108: =$G108+(fade_gB-$G108)*1/3 -> 0.22884748 | I108: =$G108+(fade_gB-$G108)*2/3 -> 0.13442374 | J108: =$G108+(fade_gB-$G108)*3/3 -> 0.04
A109: AI ÷ 營收 | B109: % | C109: =C104/C107 -> 0.95 | D109: =D104/D107 -> 0.95 | E109: =E104/E107 -> 0.96964115 | F109: =F104/F107 -> 0.96346862 | G109: =G104/G107 -> 0.96963244
A110: C. 損益
A111: 毛利率 | B111: % | C111: =a25_gp/a25_rev -> 0.4781 | D111: =a26_gp/a26_rev -> 0.48170063 | E111: =gm_27 -> 0.47 | F111: =gm_28 -> 0.46 | G111: =gm_29 -> 0.45 | K111: FY2027 起為輸入路徑（1.6T 占比上推 vs 降價下壓）
A112: 毛利 | B112: RMB B | C112: =C107*C111 -> 11.87696 | D112: =D107*D111 -> 26.060042 | E112: =E107*E111 -> 46.065214 | F112: =F107*F111 -> 41.214029 | G112: =G107*G111 -> 53.351744
A113: 營業費用、減值與其他（基準路徑） | B113: RMB B | C113: =a25_opx -> 1.0212784 | D113: =a26_opx -> 3.2137771 | E113: =D113*(1+MAX(0,phi*E108)) -> 4.7788788 | F113: =E113*(1+MAX(0,phi*F108)) -> 4.7788788 | G113: =F113*(1+MAX(0,phi*G108)) -> 5.7058032
A114: 營業費用、減值與其他 | B114: RMB B | C114: =C113 -> 1.0212784 | D114: =D113 -> 3.2137771 | E114: =E113+0*E107 -> 4.7788788 | F114: =F113+0*F107 -> 4.7788788 | G114: =G113+0*G107 -> 5.7058032
A115: 稅前利益（＝毛利 − 營業費用等） | B115: RMB B | C115: =C112-C114 -> 10.855682 | D115: =D112-D114 -> 22.846265 | E115: =E112-E114 -> 41.286335 | F115: =F112-F114 -> 36.43515 | G115: =G112-G114 -> 47.645941
A116: 稅前利益率 | B116: % | C116: =C115/C107 -> 0.43698904 | D116: =D115/D107 -> 0.42229633 | E116: =E115/E107 -> 0.42124145 | F116: =F115/F107 -> 0.40666175 | G116: =G115/G107 -> 0.4018739
A117: 歸母淨利 | B117: RMB B | C117: =a25_ni -> 9.532 | D117: =a26_ni -> 20.060518 | E117: =E115*(1-tx)*attr -> 36.252108 | F117: =F115*(1-tx)*attr -> 31.99245 | G117: =G115*(1-tx)*attr -> 41.836258 | H117: =H107*H118 -> 49.696701 | I117: =I107*I118 -> 54.433079 | J117: =J107*J118 -> 54.588602
A118: 淨利率 | B118: % | C118: =C117/C107 -> 0.38370502 | D118: =D117/D107 -> 0.37080385 | E118: =E117/E107 -> 0.3698776 | F118: =F117/F107 -> 0.35707566 | G118: =G117/G107 -> 0.35287162 | H118: =$G118+(fade_mB-$G118)*1/3 -> 0.34110923 | I118: =$G118+(fade_mB-$G118)*2/3 -> 0.32934684 | J118: =$G118+(fade_mB-$G118)*3/3 -> 0.31758446
A119: 股數（轉增後） | B119: 十億股 | C119: =a25_sh -> 1.3886368 | D119: =a26_sh -> 1.392841 | E119: =sh_post*(1+sh_g) -> 1.394 | F119: =E119*(1+sh_g) -> 1.394 | G119: =F119*(1+sh_g) -> 1.394 | H119: =G119*(1+sh_g) -> 1.394 | I119: =H119*(1+sh_g) -> 1.394 | J119: =I119*(1+sh_g) -> 1.394
A120: EPS | B120: RMB | C120: =C117/C119 -> 6.8642857 | D120: =D117/D119 -> 14.40259 | E120: =E117/E119 -> 26.005816 | F120: =F117/F119 -> 22.950107 | G120: =G117/G119 -> 30.011663 | H120: =H117/H119 -> 35.650431 | I120: =I117/I119 -> 39.04812 | J120: =J117/J119 -> 39.159686
A121: EPS 年增 | B121: % | D121: =D120/C120-1 -> 1.0981921 | E121: =E120/D120-1 -> 0.80563473 | F121: =F120/E120-1 -> -0.11750098 | G121: =G120/F120-1 -> 0.30769162 | H121: =H120/G120-1 -> 0.18788589 | I121: =I120/H120-1 -> 0.095305678 | J121: =J120/I120-1 -> 0.0028571429
...

Sheet Val
A1: Val — P/E 估值（人民幣；A 股）。目標價＝DCF 與 Comparable 加權（第 0 節）；舊法規則值情境加權保留參考；另列「現價 ÷ FY2027、FY2028 EPS（模型）」、市場隱含 EPS。十年 P/E 用 2016–2025（兩個資料商來源）
A2: 循環位置：新易盛不是設備股，不套設備市場見頂年；以本模型營收最高的會計年度為見頂年（比照中際旭創、Arista；FY(t)＝CY(t)，不平移）。營收到 FY2029 仍在增加時，見頂年未知，判為中段
A4: 0. 目標價
A5: 0.1 DCF（股東權益現金流，FY2027–FY2032 明確期＋FY2032 後永續）
A6: 項目 | B6: A（順利） | C6: B（平平） | D6: C（不如預期） | E6: 說明
A7: 情境 EPS（FY2027–FY2032） | E7: PL 頁各情境；FY2030 起為收斂法（PL 頁灰底）
A8: FY2027 | B8: =PL!E13 -> 25.576568 | C8: =PL!E25 -> 26.005816 | D8: =PL!E37 -> 26.220441
A9: FY2028 | B9: =PL!F13 -> 28.043343 | C9: =PL!F25 -> 22.950107 | D9: =PL!F37 -> 16.915965
A10: FY2029 | B10: =PL!G13 -> 34.632466 | C10: =PL!G25 -> 30.011663 | D10: =PL!G37 -> 20.78899
A11: FY2030 | B11: =PL!H13 -> 41.18459 | C11: =PL!H25 -> 35.650431 | D11: =PL!H37 -> 22.680868
A12: FY2031 | B12: =PL!I13 -> 46.315988 | C12: =PL!I25 -> 39.04812 | D12: =PL!I37 -> 23.050343
A13: FY2032 | B13: =PL!J13 -> 49.094947 | C13: =PL!J25 -> 39.159686 | D13: =PL!J37 -> 21.702785
A14: 股東現金流＝EPS ×（1 − tp_g ÷ tp_roe）
A15: 再投資率（tp_g ÷ tp_roe，上限 0.8） | B15: =IF(tp_roe<=tp_g,0.8,MIN(tp_g/tp_roe,0.8)) -> 0.094562648 | E15: ROE＝In 頁 tp_roe；tp_roe ≤ tp_g 時取上限 0.8
A16: FY2027 | B16: =B8*(1-$B$15) -> 23.15798 | C16: =C8*(1-$B$15) -> 23.546637 | D16: =D8*(1-$B$15) -> 23.740966
A17: FY2028 | B17: =B9*(1-$B$15) -> 25.39149 | C17: =C9*(1-$B$15) -> 20.779884 | D17: =D9*(1-$B$15) -> 15.316347
A18: FY2029 | B18: =B10*(1-$B$15) -> 31.357529 | C18: =C10*(1-$B$15) -> 27.173681 | D18: =D10*(1-$B$15) -> 18.823128
A19: FY2030 | B19: =B11*(1-$B$15) -> 37.290066 | C19: =C11*(1-$B$15) -> 32.279232 | D19: =D11*(1-$B$15) -> 20.536105
A20: FY2031 | B20: =B12*(1-$B$15) -> 41.936225 | C20: =C12*(1-$B$15) -> 35.355626 | D20: =D12*(1-$B$15) -> 20.870642
A21: FY2032 | B21: =B13*(1-$B$15) -> 44.452399 | C21: =C13*(1-$B$15) -> 35.456642 | D21: =D13*(1-$B$15) -> 19.650512
A22: DCF 情境每股價值（折現率 tp_r） | B22: =SUMPRODUCT(B16:B21,1/(1+tp_r)^{1;2;3;4;5;6})+B21*(1+tp_g)/(tp_r-tp_g)/(1+tp_r)^6 -> 577.12954 | C22: =SUMPRODUCT(C16:C21,1/(1+tp_r)^{1;2;3;4;5;6})+C21*(1+tp_g)/(tp_r-tp_g)/(1+tp_r)^6 -> 469.92545 | D22: =SUMPRODUCT(D16:D21,1/(1+tp_r)^{1;2;3;4;5;6})+D21*(1+tp_g)/(tp_r-tp_g)/(1+tp_r)^6 -> 278.72542 | E22: Σ 明確期現金流 ÷ (1＋r)^t ＋ 永續價值 ÷ (1＋r)^6；永續價值＝FY2032 現金流 ×(1＋g)÷(r−g)；基準日 2026 年底，t＝1 對 FY2027
A23: DCF 情境價值推到 12 個月後（×(1＋tp_r)） | B23: =B22*(1+tp_r) -> 634.84249 | C23: =C22*(1+tp_r) -> 516.91799 | D23: =D22*(1+tp_r) -> 306.59797
A24: DCF 目標價（情境加權） | B24: =tp_wA*B23+tp_wB*C23+tp_wC*D23 -> 510.23134 | E24: Σ 權重 × 情境價值 ×(1＋r)；權重見 In 頁
A26: 0.2 Comparable（市場主流同業前瞻 P/E）
A27: 同業與前瞻 P/E | B27: 代號 | C27: 前瞻 12 月 P/E | D27: 日期 | E27: 來源 | F27: 標記
A28: 中際旭創（Innolight） | B28: 300308.SZ | C28: 14.11 | D28: 2026-10-12 | E28: stockanalysis forward PE（S&P Global 共識；價格日期如左） | F28: Interested-party
A29: 天孚通信（TFC） | B29: 300394.SZ | C29: 46.53 | D29: 2026-09-30 | E29: 同上（頁面價格日期較舊） | F29: Interested-party
A30: 光迅科技（Accelink） | B30: 002281.SZ | C30: 77.09 | D30: 2026-08-18 | E30: 同上（頁面價格日期較舊） | F30: Interested-party
A31: 華工科技（HGTECH） | B31: 000988.SZ | C31: 45.08 | D31: 2026-08-07 | E31: 同上（頁面價格日期較舊） | F31: Interested-party
A32: 劍橋科技（CIG） | B32: 603083.SS | C32: 31.74 | D32: 2026-10-23 | E32: 同上 | F32: Interested-party
A33: 同業前瞻 P/E 中位數 | B33: =MEDIAN(C28:C32) -> 45.08 | E33: A 股光通訊同業（新易盛是 A 股公司，同業只用 A 股；工作單 Andy 11:53）
A34: 12 個月後的前瞻 EPS（情境加權） | B34: =tp_wA*(2/12*B8+10/12*B9)+tp_wB*(2/12*C8+10/12*C9)+tp_wC*(2/12*D8+10/12*D9) -> 23.712702 | E34: 約 2027-10 時的未來 12 月 EPS ≈ 2／12 × FY2027＋10／12 × FY2028（會計年度＝日曆年）
A35: Comparable 目標價 | B35: =B33*B34 -> 1068.9686 | E35: 同業中位數 × 前瞻 EPS
A37: 0.3 結論
A38: 項目 | B38: 數值 | E38: 說明
A39: 目標價（DCF 與 Comparable 加權） | B39: =tp_w_dcf*B24+(1-tp_w_dcf)*tp_comp_adj -> 705.6347 | E39: tp_w_dcf × DCF＋（1 − tp_w_dcf）× Comparable；tp_w_dcf 見 In 頁
A40: Comparable 目標價（市場主流同業法） | B40: =B35 -> 1068.9686
A41: 市場共識目標價 | B41: =cons_tp -> 460.89 | E41: 同花順 90 天機構目標均價 460.89（15 家；In 頁 tp_avg90）；多數訂於 9 月前股價較高時
A42: 上檔空間：加權目標價 | B42: =B39/px-1 -> 1.7035812 | E42: 現價＝In 頁 px
A43: 上檔空間：Comparable 目標價 | B43: =B40/px-1 -> 3.0956652
A44: 與市場共識目標價的差距：EPS 因素 | B44: =B34/cons_feps-1 -> -0.37306683 | E44: 本模型前瞻 EPS ÷ 共識前瞻 EPS − 1；共識前瞻 EPS＝In 頁 cons_feps（同花順 FY2027、FY2028 共識，與本模型同期間加權）
A45: 與市場共識目標價的差距：倍數因素 | B45: =(cons_tp/cons_feps)/B33-1 -> -0.72969531 | E45: ="共識目標價隱含 "&TEXT(cons_tp/cons_feps,"0.0")&"x，同業中位數 "&TEXT(B33,"0.0")&"x" -> 共識目標價隱含 12.2x，同業中位數 45.1x
A46: 價格帶（DCF 不如預期～順利） | B46: =TEXT(D23,"#,##0.00")&"～"&TEXT(B23,"#,##0.00") -> 306.60～634.84 | E46: C 情境價值～A 情境價值（推到 12 個月後）
A47: 歷史倍數檢查：現價隱含 P/E 的十年分位（A／B／C） | B47: =IF(px/B9>MAX($B$102:$C$111),1,IF(px/B9<MIN($B$102:$C$111),0,PERCENTRANK($B$102:$C$111,px/B9))) -> 0 | C47: =IF(px/C9>MAX($B$102:$C$111),1,IF(px/C9<MIN($B$102:$C$111),0,PERCENTRANK($B$102:$C$111,px/C9))) -> 0 | D47: =IF(px/D9>MAX($B$102:$C$111),1,IF(px/D9<MIN($B$102:$C$111),0,PERCENTRANK($B$102:$C$111,px/D9))) -> 0.0288 | E47: 現價 ÷ 各情境 FY2028 EPS 在 2016–2025 年底 P/E（第 6 節採用來源）的分位；高於十年最大值＝100%；只作檢查，不進目標價
A48: 目標價方法 | B48: DCF：股東現金流＝EPS ×（1 − g／ROE），r＝10%、g＝4%、ROE 為近三年平均約 42%（再投資率約 9%），FY2027–32 明確期＋永續，FY2030 起為收斂法。Comparable：A 股光通訊同業（中際旭創、天孚通信、光迅科技、華工科技、劍橋科技）前瞻 P/E 中位數；同業規模較小、部分價格日期為 8–9 月，而中際旭創只有約 14 倍，中位數偏高估。情境對應：顆數情境 A＝順利、B＝平平、C＝不如預期；FY2027 三情境 EPS 只差在網通 CPO 情境（A＝CPO 替代快），顆數差異從 CY2028 起。
A49: 上檔空間級距 | B49: =IF(B42>0.5,"大於 50%",IF(B42>0.25,"25%–50%",IF(B42>=0,"0%–25%",IF(B42>=-0.25,"0%～−25%",IF(B42>=-0.5,"−25%～−50%","小於 −50%"))))) -> 大於 50% | E49: 以「上檔空間：加權目標價」分六級（Andy 2026-10-25 14:00）
A50: 投資建議 | B50: =IF(B42>0.5,"強力買進",IF(B42>0.25,"買進",IF(B42>=-0.25,"中立",IF(B42>=-0.5,"放空","強力放空")))) -> 強力買進 | E50: 依上檔空間固定規則（Andy 2026-10-25 14:17）：大於 +50% 強力買進、+25%～+50% 買進、−25%～+25% 中立、−50%～−25% 放空、小於 −50% 強力放空
A51: 舊法：規則值情境加權（參考）
A52: 項目 | B52: 數值 | E52: 說明
A53: 規則值情境加權價（參考，非目標價） | B53: =tp_wA*D81+tp_wB*D82+tp_wC*D83 -> 1145.9457 | E53: 權重 × 各情境隱含價（第 3 節規則值）
A54: 規則值情境加權價 ÷ 現價 − 1（參考） | B54: =B53/px-1 -> 3.3905966 | E54: 現價＝In 頁 px（2026-10-23 收盤）
A55: 情境 A 隱含價（樂觀） | B55: =D81 -> 1177.8009 | E55: ="FY2027 EPS × "&TEXT(C81,"0.0")&"x（"&C75&"，第 3 節）" -> FY2027 EPS × 46.1x（中段，第 3 節）
A56: 情境 B 隱含價（基準） | B56: =D82 -> 1197.5678 | E56: ="FY2027 EPS × "&TEXT(C82,"0.0")&"x（"&C76&"，第 3 節）" -> FY2027 EPS × 46.1x（中段，第 3 節）
A57: 情境 C 隱含價（下檔） | B57: =D83 -> 969.10748 | E57: ="FY2027 EPS × "&TEXT(C83,"0.0")&"x（"&C77&"，第 3 節）" -> FY2027 EPS × 37.0x（見頂，第 3 節）
A58: 情境權重 A／B／C | B58: =tp_wA -> 0.3 | C58: =tp_wB -> 0.5 | D58: =tp_wC -> 0.2 | E58: ="合計 "&TEXT(B58+C58+D58,"0%")&"；In 頁 tp_wA／tp_wB／tp_wC（Assumed，Andy 可改）" -> 合計 100%；In 頁 tp_wA／tp_wB／tp_wC（Assumed，Andy 可改）
A59: 舊法說明 | B59: P/E：各情境 FY2027 EPS × 十年（2016–2025 年底）P/E 依循環位置取分位（本模型營收最高年判定：營收到 FY2029 仍增加者為中段＝中位數，見頂＝25 分位）。十年倍數含 2016–2020 年小型股低獲利基期與 2023、2025 年高成長期的落後高倍數，偏誤方向為高估；隱含價約為 FY2027 年底的價格、未折現，當作 12 個月目標價時偏高。對照：高盛以 29.3x 前瞻 P/E 給目標價 633 元（In 頁 gs_tp）
A61: 1. 價格與市場隱含倍數
A62: 項目 | B62: A | C62: B | D62: C | E62: 說明
A63: 現價（2026-10-23 收盤） | B63: =px -> 261
A64: 現價 ÷ FY2026 EPS（錨點） | B64: =px/PL!D13 -> 18.121741 | C64: =px/PL!D25 -> 18.121741 | D64: =px/PL!D37 -> 18.121741
A65: 現價 ÷ FY2027 EPS（模型） | B65: =px/PL!E13 -> 10.204653 | C65: =px/PL!E25 -> 10.036216 | D65: =px/PL!E37 -> 9.9540662 | E65: FY2027 三情境只差在網通 CPO 情境（顆數係數從 CY2028 開始）
A66: 現價 ÷ FY2028 EPS（模型） | B66: =px/PL!F13 -> 9.3070216 | C66: =px/PL!F25 -> 11.372496 | D66: =px/PL!F37 -> 15.429211
A67: 現價 ÷ FY2029 EPS（模型） | B67: =px/PL!G13 -> 7.5362811 | C67: =px/PL!G25 -> 8.696619 | D67: =px/PL!G37 -> 12.554722
A68: 現價 ÷ 共識未來 12 月 EPS（2/12 × FY2026＋10/12 × FY2027） | B68: =px/(cons_eps26*2/12+cons_eps27*10/12) -> 10.336634
A69: 現價 ÷ 52 週高點 − 1 | B69: =px/px_hi-1 -> -0.68107725 | E69: 52 週高點兩個資料商不一致（In 頁 px_hi）
A70: 現價 ÷ 近 12 月 EPS（2H25＋1H26；推導） | B70: =px/((a25_ni-h1_ni/1.9098+h1_ni)/sh_post) -> 27.733993 | E70: 1H25 歸母淨利＝1H26 ÷（1＋90.98%）
A71: 現價 ÷ 2026-09-30 收盤 − 1 | B71: =px/px_0930-1 -> -0.32904884
A73: 2. 循環位置（本模型營收最高年；FY(t)＝CY(t)）
A74: 情境 | B74: 營收最高年（FY2026–FY2029） | C74: FY2027 判定 | D74: 規則倍數（P/E） | E74: 見頂年是否未知 | F74: 說明
A75: A | B75: =INDEX({2026,2027,2028,2029},MATCH(MAX(PL!D75:G75),PL!D75:G75,0)) -> 2029 | C75: =IF(B75=2029,"中段",IF(2027<B75,"中段",IF(2027=B75,"見頂","谷底"))) -> 中段 | D75: =IF(C75="見頂",pe_peak,IF(C75="谷底",pe_trough,pe_mid)) -> 46.05 | E75: =IF(B75=2029,"是：營收到觀測期末仍在增加","否") -> 是：營收到觀測期末仍在增加 | F75: tools/cycle_position.py excel_rule；營收最高年取代設備市場見頂年
A76: B | B76: =INDEX({2026,2027,2028,2029},MATCH(MAX(PL!D107:G107),PL!D107:G107,0)) -> 2029 | C76: =IF(B76=2029,"中段",IF(2027<B76,"中段",IF(2027=B76,"見頂","谷底"))) -> 中段 | D76: =IF(C76="見頂",pe_peak,IF(C76="谷底",pe_trough,pe_mid)) -> 46.05 | E76: =IF(B76=2029,"是：營收到觀測期末仍在增加","否") -> 是：營收到觀測期末仍在增加 | F76: 同上
A77: C | B77: =INDEX({2026,2027,2028,2029},MATCH(MAX(PL!D139:G139),PL!D139:G139,0)) -> 2027 | C77: =IF(B77=2029,"中段",IF(2027<B77,"中段",IF(2027=B77,"見頂","谷底"))) -> 見頂 | D77: =IF(C77="見頂",pe_peak,IF(C77="谷底",pe_trough,pe_mid)) -> 36.96 | E77: =IF(B77=2029,"是：營收到觀測期末仍在增加","否") -> 否 | F77: 同上
A79: 3. 規則值隱含股價（人民幣；約 FY2027 年底，未折現）＝ FY2027 EPS × 規則倍數
A80: 情境 | B80: FY2027 EPS | C80: 規則倍數 | D80: 隱含股價 | E80: 相對現價 | F80: 現價 ÷ FY2027 EPS
A81: A | B81: =PL!E13 -> 25.576568 | C81: =D75 -> 46.05 | D81: =B81*C81 -> 1177.8009 | E81: =D81/px-1 -> 3.5126473 | F81: =px/B81 -> 10.204653
A82: B | B82: =PL!E25 -> 26.005816 | C82: =D76 -> 46.05 | D82: =B82*C82 -> 1197.5678 | E82: =D82/px-1 -> 3.5883825 | F82: =px/B82 -> 10.036216
A83: C | B83: =PL!E37 -> 26.220441 | C83: =D77 -> 36.96 | D83: =B83*C83 -> 969.10748 | E83: =D83/px-1 -> 2.7130555 | F83: =px/B83 -> 9.9540662
A85: 4. 核心問題：市場隱含的 FY2028 EPS（＝現價 ÷ 假設倍數；約 2027 年底的價格看下一年 EPS）與模型的距離
A86: 假設倍數（÷ FY2028 EPS） | B86: 市場隱含 FY2028 EPS | C86: 模型 FY2028 EPS（A） | D86: 隱含 ÷ 模型 A − 1 | E86: 模型 FY2028 EPS（C） | F86: 隱含 ÷ 模型 C − 1
A87: 8 | B87: =px/A87 -> 32.625 | C87: =PL!F13 -> 28.043343 | D87: =B87/C87-1 -> 0.1633777 | E87: =PL!F37 -> 16.915965 | F87: =B87/E87-1 -> 0.92865142
A88: 10 | B88: =px/A88 -> 26.1 | C88: =PL!F13 -> 28.043343 | D88: =B88/C88-1 -> -0.069297837 | E88: =PL!F37 -> 16.915965 | F88: =B88/E88-1 -> 0.54292113
A89: 15 | B89: =px/A89 -> 17.4 | C89: =PL!F13 -> 28.043343 | D89: =B89/C89-1 -> -0.37953189 | E89: =PL!F37 -> 16.915965 | F89: =B89/E89-1 -> 0.028614088
A90: 20 | B90: =px/A90 -> 13.05 | C90: =PL!F13 -> 28.043343 | D90: =B90/C90-1 -> -0.53464892 | E90: =PL!F37 -> 16.915965 | F90: =B90/E90-1 -> -0.22853943
A91: =pe_peak -> 36.96 | B91: =px/A91 -> 7.0616883 | C91: =PL!F13 -> 28.043343 | D91: =B91/C91-1 -> -0.74818664 | E91: =PL!F37 -> 16.915965 | F91: =B91/E91-1 -> -0.58254298
A92: 讀法：第五列＝十年 P/E 25 分位（見頂倍數）。現價以 10 倍看 FY2028，隱含 EPS 約比模型 A 低一成；以 15 倍看則約等於情境 C（顆數 ×0.6）——要成立，需要份額、單價、美國限制其中至少一項大幅不利（見 Sens），或 CY2028 光模組需求明顯下修。
A94: 本版未做先驗：無 Andy 合理 P/E 對照。
A97: 6. 十年倍數與規則值（2016–2025 年底；見頂年 25 分位、中段中位數、谷底 75 分位）
A98: 規則（Andy 2026-10-13）：合理倍數＝年底 P/E 依循環位置取分位，兩個來源各取分位再平均。兩來源差距大（2021–2025 年 companiesmarketcap 系統性較高；stockanalysis 無 2016–2020），且 2016–2020 年為小型股、獲利低基期的高倍數，2023、2025 年為高成長期落後 P/E；規則值很可能高估成長放緩後的倍數（高盛稱 2018 年以來平均前瞻 P/E 約 29x，In 頁 gs_tp）。
A100: P/E：十年歷史倍數
A101: 年底 | B101: companiesmarketcap（年底 P/E） | C101: stockanalysis（會計年底 P/E） | D101: 標記／說明
A102: 2016 | B102: 110 | D102: companiesmarketcap（年底 P/E）：Interested-party（資料商；2016–2025 共 10 年）；stockanalysis（會計年底 P/E）：Interested-party（資料商；只有 2021–2025 共 5 年）
A103: 2017 | B103: 82.4
A104: 2018 | B104: 194
A105: 2019 | B105: 59.2
A106: 2020 | B106: 54.5
A107: 2021 | B107: 40.8 | C107: 30
A108: 2022 | B108: 18.6 | C108: 13.29
A109: 2023 | B109: 70.8 | C109: 50.86
A110: 2024 | B110: 41.9 | C110: 28.87
A111: 2025 | B111: 65 | C111: 44.93
...

Sheet Recon
A1: Recon — 本模型 vs 共識、券商、研調。只作事後對照，不為對上數字而調參數。共識（同花順 19 家，明細只列 10 家）區間很寬（FY2027 EPS 16.29–54.49），均值明顯高於高盛（FY2027 歸母淨利 +21%）：天風、國金兩家特別高
A3: 項目 | B3: 對照值 | C3: 模型 A | D3: 差距 A | E3: 模型 B | F3: 差距 B | G3: 模型 C | H3: 差距 C | I3: 對照來源 | J3: 說明
A4: A. 共識與券商（校準未使用）
A5: FY2026 營收 vs 共識 | B5: =cons_rev26 -> 55.189 | C5: =PL!D75 -> 54.10008 | D5: =C5/B5-1 -> -0.019730743 | E5: =PL!D107 -> 54.10008 | F5: =E5/B5-1 -> -0.019730743 | G5: =PL!D139 -> 54.10008 | H5: =G5/B5-1 -> -0.019730743 | I5: 同花順（19 家；440.5–684.8） | J5: 錨點＝1H26 實績＋2H26 季增假設
A6: FY2026 歸母淨利 vs 共識 | B6: =cons_ni26 -> 20.135 | C6: =PL!D85 -> 20.060518 | D6: =C6/B6-1 -> -0.00369913 | E6: =PL!D117 -> 20.060518 | F6: =E6/B6-1 -> -0.00369913 | G6: =PL!D149 -> 20.060518 | H6: =G6/B6-1 -> -0.00369913 | I6: 同花順（19 家；126.9–272.9）
A7: FY2026 歸母淨利 vs 高盛 | B7: =gs_ni26 -> 20.683 | C7: =PL!D85 -> 20.060518 | D7: =C7/B7-1 -> -0.03009631 | E7: =PL!D117 -> 20.060518 | F7: =E7/B7-1 -> -0.03009631 | G7: =PL!D149 -> 20.060518 | H7: =G7/B7-1 -> -0.03009631 | I7: 華爾街見聞轉引高盛（2026-07）
A8: FY2027 營收 vs 共識 | B8: =cons_rev27 -> 99.385 | C8: =PL!E75 -> 96.442187 | D8: =C8/B8-1 -> -0.029610238 | E8: =PL!E107 -> 98.011094 | F8: =E8/B8-1 -> -0.013824078 | G8: =PL!E139 -> 98.795548 | H8: =G8/B8-1 -> -0.0059309989 | I8: 同花順（570.5–1,566.6）
A9: FY2027 歸母淨利 vs 共識 | B9: =cons_ni27 -> 36.358 | C9: =PL!E85 -> 35.653736 | D9: =C9/B9-1 -> -0.019370274 | E9: =PL!E117 -> 36.252108 | F9: =E9/B9-1 -> -0.0029124842 | G9: =PL!E149 -> 36.551294 | H9: =G9/B9-1 -> 0.0053164106 | I9: 同花順（227.1–541.6）
A10: FY2027 歸母淨利 vs 高盛 | B10: =gs_ni27 -> 30.08 | C10: =PL!E85 -> 35.653736 | D10: =C10/B10-1 -> 0.18529706 | E10: =PL!E117 -> 36.252108 | F10: =E10/B10-1 -> 0.20518976 | G10: =PL!E149 -> 36.551294 | H10: =G10/B10-1 -> 0.21513611 | I10: 華爾街見聞轉引高盛（2026-07） | J10: 高盛低於共識均值約兩成
A11: FY2027 EPS vs 共識 | B11: =cons_eps27 -> 27.29 | C11: =PL!E88 -> 25.576568 | D11: =C11/B11-1 -> -0.062786081 | E11: =PL!E120 -> 26.005816 | F11: =E11/B11-1 -> -0.047056934 | G11: =PL!E152 -> 26.220441 | H11: =G11/B11-1 -> -0.03919236 | I11: 同花順（16.29–54.49）
A12: FY2028 營收 vs 共識 | B12: =cons_rev28 -> 143.815 | C12: =PL!F75 -> 107.77622 | D12: =C12/B12-1 -> -0.25059123 | E12: =PL!F107 -> 89.595716 | F12: =E12/B12-1 -> -0.37700716 | G12: =PL!F139 -> 68.831088 | H12: =G12/B12-1 -> -0.52139145 | I12: 同花順（711.4–2,371.1）
A13: FY2028 歸母淨利 vs 高盛 | B13: =gs_ni28 -> 34.576 | C13: =PL!F85 -> 39.09242 | D13: =C13/B13-1 -> 0.13062298 | E13: =PL!F117 -> 31.99245 | F13: =E13/B13-1 -> -0.074720918 | G13: =PL!F149 -> 23.580855 | H13: =G13/B13-1 -> -0.31799933 | I13: 華爾街見聞轉引高盛（2026-07）
A14: FY2028 EPS vs 共識 | B14: =cons_eps28 -> 39.93 | C14: =PL!F88 -> 28.043343 | D14: =C14/B14-1 -> -0.29768738 | E14: =PL!F120 -> 22.950107 | F14: =E14/B14-1 -> -0.42524149 | G14: =PL!F152 -> 16.915965 | H14: =G14/B14-1 -> -0.5763595 | I14: 同花順（21.94–65.32）
A15: 3Q26 營收（模型假設）vs 共識 | B15: =q3_cons_rev -> 17.76 | C15: =Q!D4 -> 15.0864 | D15: =C15/B15-1 -> -0.15054054 | E15: =Q!D4 -> 15.0864 | F15: =E15/B15-1 -> -0.15054054 | G15: =Q!D4 -> 15.0864 | H15: =G15/B15-1 -> -0.15054054 | I15: investing.com | J15: 季報 2026-10-30 公布後取代
A16: B. 份額與市場（機制檢查）
A17: FY2025 AI 營收（美元）vs LightCounting 2025 新易盛光模組營收 | B17: =lc_eo25 -> 3.5 | C17: =a25_aiu -> 3.5118899 | D17: =C17/B17-1 -> 0.0033971088 | E17: =a25_aiu -> 3.5118899 | F17: =E17/B17-1 -> 0.0033971088 | G17: =a25_aiu -> 3.5118899 | H17: =G17/B17-1 -> 0.0033971088 | I17: LightCounting | J17: 口徑不同：LightCounting 含全部光模組
A18: FY2026 可插拔有效份額＋中際旭創份額（兩家合計） | C18: =PL!D66+inl_26 -> 0.70273709 | E18: =PL!D98+inl_26 -> 0.70273709 | G18: =PL!D130+inl_26 -> 0.70273709 | I18: innolight 成品 | J18: 合計應明顯低於 100%（另有 Coherent 等）
A19: FY2028 兩家合計可插拔份額 | C19: =PL!F68+inl_28 -> 0.65816838 | E19: =PL!F100+inl_28 -> 0.65816838 | G19: =PL!F132+inl_28 -> 0.65816838 | I19: innolight 成品（情境 A）
A20: FY2026 新易盛 AI 營收 ÷ 中際旭創 AI 營收（美元） | C20: =PL!D71/inl_aiu26 -> 0.57675003 | E20: =PL!D103/inl_aiu26 -> 0.57675003 | G20: =PL!D135/inl_aiu26 -> 0.57675003 | I20: innolight 成品 Units 頁 | J20: 西南證券：1H26 營收約為中際旭創的 50.1%
A21: FY2027 新易盛 AI 營收 ÷ AI IT 資本支出 | C21: =PL!E71/itc_27 -> 0.0088853818 | E21: =PL!E103/itc_27 -> 0.0090345295 | G21: =PL!E135/itc_27 -> 0.0091091034 | I21: markets/network | J21: 每 1 美元 AI IT 資本支出分到的光模組營收
A22: C. 校準與價格
A23: 1H26 EPS（模型）vs 公司揭露 5.41 | B23: =h1_eps -> 5.41 | C23: =Q!C13 -> 5.41 | D23: =C23/B23-1 -> 0 | E23: =Q!C13 -> 5.41 | F23: =E23/B23-1 -> 0 | G23: =Q!C13 -> 5.41 | H23: =G23/B23-1 -> 0 | I23: 公司 | J23: 股數以淨利 ÷ EPS 推導，恆等
A24: FY2026 營業費用率（Derived） | C24: =Q!G9 -> 0.059404295 | E24: =Q!G9 -> 0.059404295 | G24: =Q!G9 -> 0.059404295 | I24: Q 頁殘差
A25: 規則值情境加權價（舊法，參考）vs 高盛目標價 | B25: =gs_tp -> 633 | C25: =Val!B53 -> 1145.9457 | D25: =C25/B25-1 -> 0.81034076 | E25: =Val!B53 -> 1145.9457 | F25: =E25/B25-1 -> 0.81034076 | G25: =Val!B53 -> 1145.9457 | H25: =G25/B25-1 -> 0.81034076 | I25: 高盛（2026-07） | J25: 本模型用十年落後 P/E，高盛用前瞻 29.3x
A26: 規則值情境加權價（舊法，參考）vs 同花順 90 天機構目標均價 | B26: =tp_avg90 -> 460.89 | C26: =Val!B53 -> 1145.9457 | D26: =C26/B26-1 -> 1.4863757 | E26: =Val!B53 -> 1145.9457 | F26: =E26/B26-1 -> 1.4863757 | G26: =Val!B53 -> 1145.9457 | H26: =G26/B26-1 -> 1.4863757 | I26: 同花順（15 家）
A27: D. 預留
A28: R4 產業部署路徑（markets/deploy_path/，尚未建立）：上線後以新易盛 AI 營收 ÷ 部署 GW 計算每 GW 營收 | J28: 預留列：本版無數值
A29: 3Q26 季報（預計 2026-10-30）：公布後以實績取代 Q 頁 3Q 假設 | J29: 預留列：本版無數值

Sheet Sens
A1: Sens — 一次動一個輸入（情境 A；有效份額在每個案例內依 FY2026 錨點重算，FY2026 恆等於錨點）：對 FY2027、FY2028 的營收、AI 營收、毛利率與 EPS 的影響。每個案例是一個完整推導區塊（本頁下方）
A3: 案例 | B3: 設定 | C3: FY2027 營收 | D3: FY2027 AI 營收 | E3: FY2027 毛利率 | F3: FY2027 EPS | G3: FY2027 EPS 相對基準 | H3: FY2028 營收 | I3: FY2028 AI 營收 | J3: FY2028 毛利率 | K3: FY2028 EPS | L3: FY2028 EPS 相對基準
A4: 基準（情境 A） | B4: PL 區塊 A | C4: =PL!E75 -> 96.442187 | D4: =PL!E72 -> 93.466682 | E4: =PL!E79 -> 0.47 | F4: =PL!E88 -> 25.576568 | G4: =F4/F$4-1 -> 0 | H4: =PL!F75 -> 107.77622 | I4: =PL!F72 -> 104.50317 | J4: =PL!F79 -> 0.46 | K4: =PL!F88 -> 28.043343 | L4: =K4/K$4-1 -> 0
A5: 份額流失（低） | B5: 份額相對值 2027 0.80、2028 0.65、2029 0.55（主要客戶轉單、1.6T 落後） | C5: =E55 -> 77.938286 | D5: =E52 -> 74.962781 | E5: =E59 -> 0.47 | F5: =E68 -> 20.513955 | G5: =F5/F$4-1 -> -0.19793948 | H5: =F55 -> 72.715625 | I5: =F52 -> 69.44257 | J5: =F59 -> 0.46 | K5: =F68 -> 18.50977 | L5: =K5/K$4-1 -> -0.33995852
A6: 份額上升（高） | B6: 份額相對值 2027 1.15、2028–29 1.20（搶中際旭創、Coherent 份額） | C6: =E87 -> 110.32011 | D6: =E84 -> 107.34461 | E6: =E91 -> 0.47 | F6: =E100 -> 29.373527 | G6: =F6/F$4-1 -> 0.14845461 | H6: =F87 -> 127.81085 | I6: =F84 -> 124.53779 | J6: =F91 -> 0.46 | K6: =F100 -> 33.43392 | L6: =K6/K$4-1 -> 0.19222306
A7: 美國限制 | B7: 份額相對值 2027 0.90、2028 0.55、2029 0.50（Covered List 擴及光模組） | C7: =E119 -> 87.190236 | D7: =E116 -> 84.214732 | E7: =E123 -> 0.47 | F7: =E132 -> 23.045262 | G7: =F7/F$4-1 -> -0.09896974 | H7: =F119 -> 62.698311 | I7: =F116 -> 59.425257 | J7: =F123 -> 0.46 | K7: =F132 -> 15.399548 | L7: =K7/K$4-1 -> -0.45086617
A8: 降價快於模型 | B8: 單價係數 2027 0.90、2028 0.80、2029 0.72 | C8: =E151 -> 87.190236 | D8: =E148 -> 84.214732 | E8: =E155 -> 0.47 | F8: =E164 -> 23.045262 | G8: =F8/F$4-1 -> -0.09896974 | H8: =F151 -> 87.741595 | I8: =F148 -> 84.468541 | J8: =F155 -> 0.46 | K8: =F164 -> 22.645316 | L8: =K8/K$4-1 -> -0.19248871
A9: 毛利率 低（價格戰） | B9: 毛利率 2027 43%、2028 40%、2029 36% | C9: =E183 -> 96.442187 | D9: =E180 -> 93.466682 | E9: =E187 -> 0.43 | F9: =E196 -> 23.146652 | G9: =F9/F$4-1 -> -0.095005539 | H9: =F183 -> 107.77622 | I9: =F180 -> 104.50317 | J9: =F187 -> 0.4 | K9: =F196 -> 23.970118 | L9: =K9/K$4-1 -> -0.14524747
A10: 毛利率 高 | B10: 毛利率 2027 49%、2028 48%、2029 47% | C10: =E215 -> 96.442187 | D10: =E212 -> 93.466682 | E10: =E219 -> 0.49 | F10: =E228 -> 26.791526 | G10: =F10/F$4-1 -> 0.04750277 | H10: =F215 -> 107.77622 | I10: =F212 -> 104.50317 | J10: =F219 -> 0.48 | K10: =F228 -> 29.401085 | L10: =K10/K$4-1 -> 0.048415824
A11: CPO 份額 0 | B11: 新易盛不參與 CPO 光學 | C11: =E247 -> 95.495008 | D11: =E244 -> 92.519503 | E11: =E251 -> 0.47 | F11: =E260 -> 25.317422 | G11: =F11/F$4-1 -> -0.01013214 | H11: =F247 -> 103.44619 | I11: =F244 -> 100.17314 | J11: =F251 -> 0.46 | K11: =F260 -> 26.872198 | L11: =K11/K$4-1 -> -0.041761946
A12: CPO 份額 高 | B12: 2027 20%、2028 25%、2029 30% | C12: =E279 -> 99.283723 | D12: =E276 -> 96.308219 | E12: =E283 -> 0.47 | F12: =E292 -> 26.354004 | G12: =F12/F$4-1 -> 0.03039642 | H12: =F279 -> 114.27127 | I12: =F276 -> 110.99822 | J12: =F283 -> 0.46 | K12: =F292 -> 29.796023 | L12: =K12/K$4-1 -> 0.062498971
A13: AI 市場 ×0.8 | B13: FY2027 起可插拔光模組市場 ×0.8 | C13: =E311 -> 77.938286 | D13: =E308 -> 74.962781 | E13: =E315 -> 0.47 | F13: =E324 -> 20.513955 | G13: =F13/F$4-1 -> -0.19793948 | H13: =F311 -> 87.741595 | I13: =F308 -> 84.468541 | J13: =F315 -> 0.46 | K13: =F324 -> 22.670364 | L13: =K13/K$4-1 -> -0.19159552
A14: AI 市場 ×1.2 | B14: ×1.2 | C14: =E343 -> 114.94609 | D14: =E340 -> 111.97058 | E14: =E347 -> 0.47 | F14: =E356 -> 30.63918 | G14: =F14/F$4-1 -> 0.19793948 | H14: =F343 -> 127.81085 | I14: =F340 -> 124.53779 | J14: =F347 -> 0.46 | K14: =F356 -> 33.41503 | L14: =K14/K$4-1 -> 0.19154944
A15: 人民幣升值（6.9） | B15: FY2027 起 RMB／USD 6.9 | C15: =E375 -> 93.382265 | D15: =E372 -> 90.406761 | E15: =E379 -> 0.47 | F15: =E388 -> 24.739382 | G15: =F15/F$4-1 -> -0.032732515 | H15: =F375 -> 104.35499 | I15: =F372 -> 101.08193 | J15: =F379 -> 0.46 | K15: =F388 -> 27.125617 | L15: =K15/K$4-1 -> -0.032725255
A16: 人民幣貶值（7.3） | B16: FY2027 起 7.3 | C16: =E407 -> 100.33663 | D16: =E404 -> 97.361127 | E16: =E411 -> 0.47 | F16: =E420 -> 26.642077 | G16: =F16/F$4-1 -> 0.041659564 | H16: =F407 -> 112.13052 | I16: =F404 -> 108.85747 | J16: =F411 -> 0.46 | K16: =F420 -> 29.211358 | L16: =K16/K$4-1 -> 0.041650352
A17: 營業費用率 +2pt | B17: 營業費用額外 +2% × 營收 | C17: =E439 -> 96.442187 | D17: =E436 -> 93.466682 | E17: =E443 -> 0.47 | F17: =E452 -> 24.36161 | G17: =F17/F$4-1 -> -0.04750277 | H17: =F439 -> 107.77622 | I17: =F436 -> 104.50317 | J17: =F443 -> 0.46 | K17: =F452 -> 26.685601 | L17: =K17/K$4-1 -> -0.048415824
A18: 營業費用彈性 1.0 | B18: phi＝1.0（費用與營收同步成長） | C18: =E471 -> 96.442187 | D18: =E468 -> 93.466682 | E18: =E475 -> 0.47 | F18: =E484 -> 24.942823 | G18: =F18/F$4-1 -> -0.024778339 | H18: =F471 -> 107.77622 | I18: =F468 -> 104.50317 | J18: =F475 -> 0.46 | K18: =F484 -> 27.195272 | L18: =K18/K$4-1 -> -0.030241452
A19: 顆數情境 B | B19: CY2028 ×0.8、CY2029 ×0.85；CPO 情境 B | C19: =PL!E107 -> 98.011094 | D19: =PL!E104 -> 95.03559 | E19: =PL!E111 -> 0.47 | F19: =PL!E120 -> 26.005816 | G19: =F19/F$4-1 -> 0.016782879 | H19: =PL!F107 -> 89.595716 | I19: =PL!F104 -> 86.322661 | J19: =PL!F111 -> 0.46 | K19: =PL!F120 -> 22.950107 | L19: =K19/K$4-1 -> -0.18162013
A20: 顆數情境 C | B20: CY2028–29 ×0.6；CPO 情境 C | C20: =PL!E139 -> 98.795548 | D20: =PL!E136 -> 95.820043 | E20: =PL!E143 -> 0.47 | F20: =PL!E152 -> 26.220441 | G20: =F20/F$4-1 -> 0.025174318 | H20: =PL!F139 -> 68.831088 | I20: =PL!F136 -> 65.558033 | J20: =PL!F143 -> 0.46 | K20: =PL!F152 -> 16.915965 | L20: =K20/K$4-1 -> -0.39679213
A22: 讀法：FY2027 三情境只差在網通 CPO 情境（A 替代快、C 慢）；顆數差異從 FY2028 起。「美國限制」「份額流失」「降價」「毛利率」四案例對應市場隱含衰退的路徑；新易盛境外營收占九成七以上，美國限制與主要客戶轉單是最大的單一風險。
A24: 目標價參數（只改 DCF 參數與權重；PL 收斂法的 fade_g 不隨 tp_g 變動）
A25: 案例 | B25: 設定 | C25: DCF 目標價 | D25: Comparable 目標價（相對倍數調整後） | E25: 加權目標價 | F25: 相對基準
A26: 基準 | B26: r 10%、g 4%、DCF 權重 0.5 | C26: =(tp_wA*(Val!B8*(1-IF(tp_roe<=tp_g,0.8,MIN(tp_g/tp_roe,0.8)))/(1+tp_r)^1+Val!B9*(1-IF(tp_roe<=tp_g,0.8,MIN(tp_g/tp_roe,0.8)))/(1+tp_r)^2+Val!B10*(1-IF(tp_roe<=tp_g,0.8,MIN(tp_g/tp_roe,0.8)))/(1+tp_r)^3+Val!B11*(1-IF(tp_roe<=tp_g,0.8,MIN(tp_g/tp_roe,0.8)))/(1+tp_r)^4+Val!B12*(1-IF(tp_roe<=tp_g,0.8,MIN(tp_g/tp_roe,0.8)))/(1+tp_r)^5+Val!B13*(1-IF(tp_roe<=tp_g,0.8,MIN(tp_g/tp_roe,0.8)))/(1+tp_r)^6+Val!B13*(1-IF(tp_roe<=tp_g,0.8,MIN(tp_g/tp_roe,0.8)))*(1+tp_g)/(tp_r-tp_g)/(1+tp_r)^6)+tp_wB*(Val!C8*(1-IF(tp_roe<=tp_g,0.8,MIN(tp_g/tp_roe,0.8)))/(1+tp_r)^1+Val!C9*(1-IF(tp_roe<=tp_g,0.8,MIN(tp_g/tp_roe,0.8)))/(1+tp_r)^2+Val!C10*(1-IF(tp_roe<=tp_g,0.8,MIN(tp_g/tp_roe,0.8)))/(1+tp_r)^3+Val!C11*(1-IF(tp_roe<=tp_g,0.8,MIN(tp_g/tp_roe,0.8)))/(1+tp_r)^4+Val!C12*(1-IF(tp_roe<=tp_g,0.8,MIN(tp_g/tp_roe,0.8)))/(1+tp_r)^5+Val!C13*(1-IF(tp_roe<=tp_g,0.8,MIN(tp_g/tp_roe,0.8)))/(1+tp_r)^6+Val!C13*(1-IF(tp_roe<=tp_g,0.8,MIN(tp_g/tp_roe,0.8)))*(1+tp_g)/(tp_r-tp_g)/(1+tp_r)^6)+tp_wC*(Val!D8*(1-IF(tp_roe<=tp_g,0.8,MIN(tp_g/tp_roe,0.8)))/(1+tp_r)^1+Val!D9*(1-IF(tp_roe<=tp_g,0.8,MIN(tp_g/tp_roe,0.8)))/(1+tp_r)^2+Val!D10*(1-IF(tp_roe<=tp_g,0.8,MIN(tp_g/tp_roe,0.8)))/(1+tp_r)^3+Val!D11*(1-IF(tp_roe<=tp_g,0.8,MIN(tp_g/tp_roe,0.8)))/(1+tp_r)^4+Val!D12*(1-IF(tp_roe<=tp_g,0.8,MIN(tp_g/tp_roe,0.8)))/(1+tp_r)^5+Val!D13*(1-IF(tp_roe<=tp_g,0.8,MIN(tp_g/tp_roe,0.8)))/(1+tp_r)^6+Val!D13*(1-IF(tp_roe<=tp_g,0.8,MIN(tp_g/tp_roe,0.8)))*(1+tp_g)/(tp_r-tp_g)/(1+tp_r)^6))*(1+tp_r) -> 510.23134 | D26: =tp_comp_adj -> 901.03807 | E26: =tp_w_dcf*C26+(1-tp_w_dcf)*D26 -> 705.6347 | F26: =E26/E$26-1 -> 0
A27: 折現率 +1pt | B27: r 11% | C27: =(tp_wA*(Val!B8*(1-IF(tp_roe<=tp_g,0.8,MIN(tp_g/tp_roe,0.8)))/(1+(tp_r+0.01))^1+Val!B9*(1-IF(tp_roe<=tp_g,0.8,MIN(tp_g/tp_roe,0.8)))/(1+(tp_r+0.01))^2+Val!B10*(1-IF(tp_roe<=tp_g,0.8,MIN(tp_g/tp_roe,0.8)))/(1+(tp_r+0.01))^3+Val!B11*(1-IF(tp_roe<=tp_g,0.8,MIN(tp_g/tp_roe,0.8)))/(1+(tp_r+0.01))^4+Val!B12*(1-IF(tp_roe<=tp_g,0.8,MIN(tp_g/tp_roe,0.8)))/(1+(tp_r+0.01))^5+Val!B13*(1-IF(tp_roe<=tp_g,0.8,MIN(tp_g/tp_roe,0.8)))/(1+(tp_r+0.01))^6+Val!B13*(1-IF(tp_roe<=tp_g,0.8,MIN(tp_g/tp_roe,0.8)))*(1+tp_g)/((tp_r+0.01)-tp_g)/(1+(tp_r+0.01))^6)+tp_wB*(Val!C8*(1-IF(tp_roe<=tp_g,0.8,MIN(tp_g/tp_roe,0.8)))/(1+(tp_r+0.01))^1+Val!C9*(1-IF(tp_roe<=tp_g,0.8,MIN(tp_g/tp_roe,0.8)))/(1+(tp_r+0.01))^2+Val!C10*(1-IF(tp_roe<=tp_g,0.8,MIN(tp_g/tp_roe,0.8)))/(1+(tp_r+0.01))^3+Val!C11*(1-IF(tp_roe<=tp_g,0.8,MIN(tp_g/tp_roe,0.8)))/(1+(tp_r+0.01))^4+Val!C12*(1-IF(tp_roe<=tp_g,0.8,MIN(tp_g/tp_roe,0.8)))/(1+(tp_r+0.01))^5+Val!C13*(1-IF(tp_roe<=tp_g,0.8,MIN(tp_g/tp_roe,0.8)))/(1+(tp_r+0.01))^6+Val!C13*(1-IF(tp_roe<=tp_g,0.8,MIN(tp_g/tp_roe,0.8)))*(1+tp_g)/((tp_r+0.01)-tp_g)/(1+(tp_r+0.01))^6)+tp_wC*(Val!D8*(1-IF(tp_roe<=tp_g,0.8,MIN(tp_g/tp_roe,0.8)))/(1+(tp_r+0.01))^1+Val!D9*(1-IF(tp_roe<=tp_g,0.8,MIN(tp_g/tp_roe,0.8)))/(1+(tp_r+0.01))^2+Val!D10*(1-IF(tp_roe<=tp_g,0.8,MIN(tp_g/tp_roe,0.8)))/(1+(tp_r+0.01))^3+Val!D11*(1-IF(tp_roe<=tp_g,0.8,MIN(tp_g/tp_roe,0.8)))/(1+(tp_r+0.01))^4+Val!D12*(1-IF(tp_roe<=tp_g,0.8,MIN(tp_g/tp_roe,0.8)))/(1+(tp_r+0.01))^5+Val!D13*(1-IF(tp_roe<=tp_g,0.8,MIN(tp_g/tp_roe,0.8)))/(1+(tp_r+0.01))^6+Val!D13*(1-IF(tp_roe<=tp_g,0.8,MIN(tp_g/tp_roe,0.8)))*(1+tp_g)/((tp_r+0.01)-tp_g)/(1+(tp_r+0.01))^6))*(1+(tp_r+0.01)) -> 439.14596 | D27: =tp_comp_adj -> 901.03807 | E27: =tp_w_dcf*C27+(1-tp_w_dcf)*D27 -> 670.09201 | F27: =E27/E$26-1 -> -0.050369815
A28: 折現率 −1pt | B28: r 9% | C28: =(tp_wA*(Val!B8*(1-IF(tp_roe<=tp_g,0.8,MIN(tp_g/tp_roe,0.8)))/(1+(tp_r-0.01))^1+Val!B9*(1-IF(tp_roe<=tp_g,0.8,MIN(tp_g/tp_roe,0.8)))/(1+(tp_r-0.01))^2+Val!B10*(1-IF(tp_roe<=tp_g,0.8,MIN(tp_g/tp_roe,0.8)))/(1+(tp_r-0.01))^3+Val!B11*(1-IF(tp_roe<=tp_g,0.8,MIN(tp_g/tp_roe,0.8)))/(1+(tp_r-0.01))^4+Val!B12*(1-IF(tp_roe<=tp_g,0.8,MIN(tp_g/tp_roe,0.8)))/(1+(tp_r-0.01))^5+Val!B13*(1-IF(tp_roe<=tp_g,0.8,MIN(tp_g/tp_roe,0.8)))/(1+(tp_r-0.01))^6+Val!B13*(1-IF(tp_roe<=tp_g,0.8,MIN(tp_g/tp_roe,0.8)))*(1+tp_g)/((tp_r-0.01)-tp_g)/(1+(tp_r-0.01))^6)+tp_wB*(Val!C8*(1-IF(tp_roe<=tp_g,0.8,MIN(tp_g/tp_roe,0.8)))/(1+(tp_r-0.01))^1+Val!C9*(1-IF(tp_roe<=tp_g,0.8,MIN(tp_g/tp_roe,0.8)))/(1+(tp_r-0.01))^2+Val!C10*(1-IF(tp_roe<=tp_g,0.8,MIN(tp_g/tp_roe,0.8)))/(1+(tp_r-0.01))^3+Val!C11*(1-IF(tp_roe<=tp_g,0.8,MIN(tp_g/tp_roe,0.8)))/(1+(tp_r-0.01))^4+Val!C12*(1-IF(tp_roe<=tp_g,0.8,MIN(tp_g/tp_roe,0.8)))/(1+(tp_r-0.01))^5+Val!C13*(1-IF(tp_roe<=tp_g,0.8,MIN(tp_g/tp_roe,0.8)))/(1+(tp_r-0.01))^6+Val!C13*(1-IF(tp_roe<=tp_g,0.8,MIN(tp_g/tp_roe,0.8)))*(1+tp_g)/((tp_r-0.01)-tp_g)/(1+(tp_r-0.01))^6)+tp_wC*(Val!D8*(1-IF(tp_roe<=tp_g,0.8,MIN(tp_g/tp_roe,0.8)))/(1+(tp_r-0.01))^1+Val!D9*(1-IF(tp_roe<=tp_g,0.8,MIN(tp_g/tp_roe,0.8)))/(1+(tp_r-0.01))^2+Val!D10*(1-IF(tp_roe<=tp_g,0.8,MIN(tp_g/tp_roe,0.8)))/(1+(tp_r-0.01))^3+Val!D11*(1-IF(tp_roe<=tp_g,0.8,MIN(tp_g/tp_roe,0.8)))/(1+(tp_r-0.01))^4+Val!D12*(1-IF(tp_roe<=tp_g,0.8,MIN(tp_g/tp_roe,0.8)))/(1+(tp_r-0.01))^5+Val!D13*(1-IF(tp_roe<=tp_g,0.8,MIN(tp_g/tp_roe,0.8)))/(1+(tp_r-0.01))^6+Val!D13*(1-IF(tp_roe<=tp_g,0.8,MIN(tp_g/tp_roe,0.8)))*(1+tp_g)/((tp_r-0.01)-tp_g)/(1+(tp_r-0.01))^6))*(1+(tp_r-0.01)) -> 609.80251 | D28: =tp_comp_adj -> 901.03807 | E28: =tp_w_dcf*C28+(1-tp_w_dcf)*D28 -> 755.42029 | F28: =E28/E$26-1 -> 0.070554333
A29: 長期成長 +1pt | B29: g 5% | C29: =(tp_wA*(Val!B8*(1-IF(tp_roe<=(tp_g+0.01),0.8,MIN((tp_g+0.01)/tp_roe,0.8)))/(1+tp_r)^1+Val!B9*(1-IF(tp_roe<=(tp_g+0.01),0.8,MIN((tp_g+0.01)/tp_roe,0.8)))/(1+tp_r)^2+Val!B10*(1-IF(tp_roe<=(tp_g+0.01),0.8,MIN((tp_g+0.01)/tp_roe,0.8)))/(1+tp_r)^3+Val!B11*(1-IF(tp_roe<=(tp_g+0.01),0.8,MIN((tp_g+0.01)/tp_roe,0.8)))/(1+tp_r)^4+Val!B12*(1-IF(tp_roe<=(tp_g+0.01),0.8,MIN((tp_g+0.01)/tp_roe,0.8)))/(1+tp_r)^5+Val!B13*(1-IF(tp_roe<=(tp_g+0.01),0.8,MIN((tp_g+0.01)/tp_roe,0.8)))/(1+tp_r)^6+Val!B13*(1-IF(tp_roe<=(tp_g+0.01),0.8,MIN((tp_g+0.01)/tp_roe,0.8)))*(1+(tp_g+0.01))/(tp_r-(tp_g+0.01))/(1+tp_r)^6)+tp_wB*(Val!C8*(1-IF(tp_roe<=(tp_g+0.01),0.8,MIN((tp_g+0.01)/tp_roe,0.8)))/(1+tp_r)^1+Val!C9*(1-IF(tp_roe<=(tp_g+0.01),0.8,MIN((tp_g+0.01)/tp_roe,0.8)))/(1+tp_r)^2+Val!C10*(1-IF(tp_roe<=(tp_g+0.01),0.8,MIN((tp_g+0.01)/tp_roe,0.8)))/(1+tp_r)^3+Val!C11*(1-IF(tp_roe<=(tp_g+0.01),0.8,MIN((tp_g+0.01)/tp_roe,0.8)))/(1+tp_r)^4+Val!C12*(1-IF(tp_roe<=(tp_g+0.01),0.8,MIN((tp_g+0.01)/tp_roe,0.8)))/(1+tp_r)^5+Val!C13*(1-IF(tp_roe<=(tp_g+0.01),0.8,MIN((tp_g+0.01)/tp_roe,0.8)))/(1+tp_r)^6+Val!C13*(1-IF(tp_roe<=(tp_g+0.01),0.8,MIN((tp_g+0.01)/tp_roe,0.8)))*(1+(tp_g+0.01))/(tp_r-(tp_g+0.01))/(1+tp_r)^6)+tp_wC*(Val!D8*(1-IF(tp_roe<=(tp_g+0.01),0.8,MIN((tp_g+0.01)/tp_roe,0.8)))/(1+tp_r)^1+Val!D9*(1-IF(tp_roe<=(tp_g+0.01),0.8,MIN((tp_g+0.01)/tp_roe,0.8)))/(1+tp_r)^2+Val!D10*(1-IF(tp_roe<=(tp_g+0.01),0.8,MIN((tp_g+0.01)/tp_roe,0.8)))/(1+tp_r)^3+Val!D11*(1-IF(tp_roe<=(tp_g+0.01),0.8,MIN((tp_g+0.01)/tp_roe,0.8)))/(1+tp_r)^4+Val!D12*(1-IF(tp_roe<=(tp_g+0.01),0.8,MIN((tp_g+0.01)/tp_roe,0.8)))/(1+tp_r)^5+Val!D13*(1-IF(tp_roe<=(tp_g+0.01),0.8,MIN((tp_g+0.01)/tp_roe,0.8)))/(1+tp_r)^6+Val!D13*(1-IF(tp_roe<=(tp_g+0.01),0.8,MIN((tp_g+0.01)/tp_roe,0.8)))*(1+(tp_g+0.01))/(tp_r-(tp_g+0.01))/(1+tp_r)^6))*(1+tp_r) -> 574.50074 | D29: =tp_comp_adj -> 901.03807 | E29: =tp_w_dcf*C29+(1-tp_w_dcf)*D29 -> 737.76941 | F29: =E29/E$26-1 -> 0.045540138
A30: 長期成長 −1pt | B30: g 3% | C30: =(tp_wA*(Val!B8*(1-IF(tp_roe<=(tp_g-0.01),0.8,MIN((tp_g-0.01)/tp_roe,0.8)))/(1+tp_r)^1+Val!B9*(1-IF(tp_roe<=(tp_g-0.01),0.8,MIN((tp_g-0.01)/tp_roe,0.8)))/(1+tp_r)^2+Val!B10*(1-IF(tp_roe<=(tp_g-0.01),0.8,MIN((tp_g-0.01)/tp_roe,0.8)))/(1+tp_r)^3+Val!B11*(1-IF(tp_roe<=(tp_g-0.01),0.8,MIN((tp_g-0.01)/tp_roe,0.8)))/(1+tp_r)^4+Val!B12*(1-IF(tp_roe<=(tp_g-0.01),0.8,MIN((tp_g-0.01)/tp_roe,0.8)))/(1+tp_r)^5+Val!B13*(1-IF(tp_roe<=(tp_g-0.01),0.8,MIN((tp_g-0.01)/tp_roe,0.8)))/(1+tp_r)^6+Val!B13*(1-IF(tp_roe<=(tp_g-0.01),0.8,MIN((tp_g-0.01)/tp_roe,0.8)))*(1+(tp_g-0.01))/(tp_r-(tp_g-0.01))/(1+tp_r)^6)+tp_wB*(Val!C8*(1-IF(tp_roe<=(tp_g-0.01),0.8,MIN((tp_g-0.01)/tp_roe,0.8)))/(1+tp_r)^1+Val!C9*(1-IF(tp_roe<=(tp_g-0.01),0.8,MIN((tp_g-0.01)/tp_roe,0.8)))/(1+tp_r)^2+Val!C10*(1-IF(tp_roe<=(tp_g-0.01),0.8,MIN((tp_g-0.01)/tp_roe,0.8)))/(1+tp_r)^3+Val!C11*(1-IF(tp_roe<=(tp_g-0.01),0.8,MIN((tp_g-0.01)/tp_roe,0.8)))/(1+tp_r)^4+Val!C12*(1-IF(tp_roe<=(tp_g-0.01),0.8,MIN((tp_g-0.01)/tp_roe,0.8)))/(1+tp_r)^5+Val!C13*(1-IF(tp_roe<=(tp_g-0.01),0.8,MIN((tp_g-0.01)/tp_roe,0.8)))/(1+tp_r)^6+Val!C13*(1-IF(tp_roe<=(tp_g-0.01),0.8,MIN((tp_g-0.01)/tp_roe,0.8)))*(1+(tp_g-0.01))/(tp_r-(tp_g-0.01))/(1+tp_r)^6)+tp_wC*(Val!D8*(1-IF(tp_roe<=(tp_g-0.01),0.8,MIN((tp_g-0.01)/tp_roe,0.8)))/(1+tp_r)^1+Val!D9*(1-IF(tp_roe<=(tp_g-0.01),0.8,MIN((tp_g-0.01)/tp_roe,0.8)))/(1+tp_r)^2+Val!D10*(1-IF(tp_roe<=(tp_g-0.01),0.8,MIN((tp_g-0.01)/tp_roe,0.8)))/(1+tp_r)^3+Val!D11*(1-IF(tp_roe<=(tp_g-0.01),0.8,MIN((tp_g-0.01)/tp_roe,0.8)))/(1+tp_r)^4+Val!D12*(1-IF(tp_roe<=(tp_g-0.01),0.8,MIN((tp_g-0.01)/tp_roe,0.8)))/(1+tp_r)^5+Val!D13*(1-IF(tp_roe<=(tp_g-0.01),0.8,MIN((tp_g-0.01)/tp_roe,0.8)))/(1+tp_r)^6+Val!D13*(1-IF(tp_roe<=(tp_g-0.01),0.8,MIN((tp_g-0.01)/tp_roe,0.8)))*(1+(tp_g-0.01))/(tp_r-(tp_g-0.01))/(1+tp_r)^6))*(1+tp_r) -> 465.15918 | D30: =tp_comp_adj -> 901.03807 | E30: =tp_w_dcf*C30+(1-tp_w_dcf)*D30 -> 683.09863 | F30: =E30/E$26-1 -> -0.031937312
A31: DCF 權重 0.3 | B31: Comparable 0.7 | C31: =(tp_wA*(Val!B8*(1-IF(tp_roe<=tp_g,0.8,MIN(tp_g/tp_roe,0.8)))/(1+tp_r)^1+Val!B9*(1-IF(tp_roe<=tp_g,0.8,MIN(tp_g/tp_roe,0.8)))/(1+tp_r)^2+Val!B10*(1-IF(tp_roe<=tp_g,0.8,MIN(tp_g/tp_roe,0.8)))/(1+tp_r)^3+Val!B11*(1-IF(tp_roe<=tp_g,0.8,MIN(tp_g/tp_roe,0.8)))/(1+tp_r)^4+Val!B12*(1-IF(tp_roe<=tp_g,0.8,MIN(tp_g/tp_roe,0.8)))/(1+tp_r)^5+Val!B13*(1-IF(tp_roe<=tp_g,0.8,MIN(tp_g/tp_roe,0.8)))/(1+tp_r)^6+Val!B13*(1-IF(tp_roe<=tp_g,0.8,MIN(tp_g/tp_roe,0.8)))*(1+tp_g)/(tp_r-tp_g)/(1+tp_r)^6)+tp_wB*(Val!C8*(1-IF(tp_roe<=tp_g,0.8,MIN(tp_g/tp_roe,0.8)))/(1+tp_r)^1+Val!C9*(1-IF(tp_roe<=tp_g,0.8,MIN(tp_g/tp_roe,0.8)))/(1+tp_r)^2+Val!C10*(1-IF(tp_roe<=tp_g,0.8,MIN(tp_g/tp_roe,0.8)))/(1+tp_r)^3+Val!C11*(1-IF(tp_roe<=tp_g,0.8,MIN(tp_g/tp_roe,0.8)))/(1+tp_r)^4+Val!C12*(1-IF(tp_roe<=tp_g,0.8,MIN(tp_g/tp_roe,0.8)))/(1+tp_r)^5+Val!C13*(1-IF(tp_roe<=tp_g,0.8,MIN(tp_g/tp_roe,0.8)))/(1+tp_r)^6+Val!C13*(1-IF(tp_roe<=tp_g,0.8,MIN(tp_g/tp_roe,0.8)))*(1+tp_g)/(tp_r-tp_g)/(1+tp_r)^6)+tp_wC*(Val!D8*(1-IF(tp_roe<=tp_g,0.8,MIN(tp_g/tp_roe,0.8)))/(1+tp_r)^1+Val!D9*(1-IF(tp_roe<=tp_g,0.8,MIN(tp_g/tp_roe,0.8)))/(1+tp_r)^2+Val!D10*(1-IF(tp_roe<=tp_g,0.8,MIN(tp_g/tp_roe,0.8)))/(1+tp_r)^3+Val!D11*(1-IF(tp_roe<=tp_g,0.8,MIN(tp_g/tp_roe,0.8)))/(1+tp_r)^4+Val!D12*(1-IF(tp_roe<=tp_g,0.8,MIN(tp_g/tp_roe,0.8)))/(1+tp_r)^5+Val!D13*(1-IF(tp_roe<=tp_g,0.8,MIN(tp_g/tp_roe,0.8)))/(1+tp_r)^6+Val!D13*(1-IF(tp_roe<=tp_g,0.8,MIN(tp_g/tp_roe,0.8)))*(1+tp_g)/(tp_r-tp_g)/(1+tp_r)^6))*(1+tp_r) -> 510.23134 | D31: =tp_comp_adj -> 901.03807 | E31: =0.3*C31+(1-0.3)*D31 -> 783.79605 | F31: =E31/E$26-1 -> 0.11076744
A32: DCF 權重 0.7 | B32: Comparable 0.3 | C32: =(tp_wA*(Val!B8*(1-IF(tp_roe<=tp_g,0.8,MIN(tp_g/tp_roe,0.8)))/(1+tp_r)^1+Val!B9*(1-IF(tp_roe<=tp_g,0.8,MIN(tp_g/tp_roe,0.8)))/(1+tp_r)^2+Val!B10*(1-IF(tp_roe<=tp_g,0.8,MIN(tp_g/tp_roe,0.8)))/(1+tp_r)^3+Val!B11*(1-IF(tp_roe<=tp_g,0.8,MIN(tp_g/tp_roe,0.8)))/(1+tp_r)^4+Val!B12*(1-IF(tp_roe<=tp_g,0.8,MIN(tp_g/tp_roe,0.8)))/(1+tp_r)^5+Val!B13*(1-IF(tp_roe<=tp_g,0.8,MIN(tp_g/tp_roe,0.8)))/(1+tp_r)^6+Val!B13*(1-IF(tp_roe<=tp_g,0.8,MIN(tp_g/tp_roe,0.8)))*(1+tp_g)/(tp_r-tp_g)/(1+tp_r)^6)+tp_wB*(Val!C8*(1-IF(tp_roe<=tp_g,0.8,MIN(tp_g/tp_roe,0.8)))/(1+tp_r)^1+Val!C9*(1-IF(tp_roe<=tp_g,0.8,MIN(tp_g/tp_roe,0.8)))/(1+tp_r)^2+Val!C10*(1-IF(tp_roe<=tp_g,0.8,MIN(tp_g/tp_roe,0.8)))/(1+tp_r)^3+Val!C11*(1-IF(tp_roe<=tp_g,0.8,MIN(tp_g/tp_roe,0.8)))/(1+tp_r)^4+Val!C12*(1-IF(tp_roe<=tp_g,0.8,MIN(tp_g/tp_roe,0.8)))/(1+tp_r)^5+Val!C13*(1-IF(tp_roe<=tp_g,0.8,MIN(tp_g/tp_roe,0.8)))/(1+tp_r)^6+Val!C13*(1-IF(tp_roe<=tp_g,0.8,MIN(tp_g/tp_roe,0.8)))*(1+tp_g)/(tp_r-tp_g)/(1+tp_r)^6)+tp_wC*(Val!D8*(1-IF(tp_roe<=tp_g,0.8,MIN(tp_g/tp_roe,0.8)))/(1+tp_r)^1+Val!D9*(1-IF(tp_roe<=tp_g,0.8,MIN(tp_g/tp_roe,0.8)))/(1+tp_r)^2+Val!D10*(1-IF(tp_roe<=tp_g,0.8,MIN(tp_g/tp_roe,0.8)))/(1+tp_r)^3+Val!D11*(1-IF(tp_roe<=tp_g,0.8,MIN(tp_g/tp_roe,0.8)))/(1+tp_r)^4+Val!D12*(1-IF(tp_roe<=tp_g,0.8,MIN(tp_g/tp_roe,0.8)))/(1+tp_r)^5+Val!D13*(1-IF(tp_roe<=tp_g,0.8,MIN(tp_g/tp_roe,0.8)))/(1+tp_r)^6+Val!D13*(1-IF(tp_roe<=tp_g,0.8,MIN(tp_g/tp_roe,0.8)))*(1+tp_g)/(tp_r-tp_g)/(1+tp_r)^6))*(1+tp_r) -> 510.23134 | D32: =tp_comp_adj -> 901.03807 | E32: =0.7*C32+(1-0.7)*D32 -> 627.47336 | F32: =E32/E$26-1 -> -0.11076744
A40: 案例區塊：份額流失（低）（情境 A）
A41: 項目 | B41: 單位 | C41: FY2025A | D41: FY2026（錨點） | E41: FY2027 | F41: FY2028 | G41: FY2029 | H41: 說明
A42: A. AI 營收（D 欄＝FY2026 校準年；E–G＝FY2027–FY2029）
A43: AI 可插拔光模組市場 × 情境顆數係數 | B43: US$B | D43: =mpl_26*1 -> 29.753262 | E43: =mpl_27*1*1 -> 53.560715 | F43: =mpl_28*um28_A*1 -> 57.9915 | G43: =mpl_29*um29_A*1 -> 72.9348
A44: AI CPO 光學市場 × 情境顆數係數 | B44: US$B | D44: =mcp_26*1 -> 0.300538 | E44: =mcp_27*1 -> 2.818985 | F44: =mcp_28*um28_A -> 6.4435 | G44: =mcp_29*um29_A -> 11.74736
A45: 人民幣兌美元 | B45: RMB | D45: =fx -> 6.72 | E45: =fx -> 6.72 | F45: =fx -> 6.72 | G45: =fx -> 6.72 | H45: FY2026 校準用基準匯率；Sens 只動 FY2027 起
A46: 新易盛可插拔有效份額（FY2026 校準）＝ AI 營收（美元）÷ 可插拔市場 | B46: % | D46: =a26_aiu/D43 -> 0.25705003 | H46: Derived：FY2026 CPO 營收視為 0；FY2027 起乘相對值
A47: 份額相對值（÷ FY2026） | B47: x | D47: =1 -> 1 | E47: =RLO_27 -> 0.8 | F47: =RLO_28 -> 0.65 | G47: =RLO_29 -> 0.55
A48: 可插拔有效份額 | B48: % | D48: =$D$46*D47 -> 0.25705003 | E48: =$D$46*E47 -> 0.20564002 | F48: =$D$46*F47 -> 0.16708252 | G48: =$D$46*G47 -> 0.14137751
A49: 單價係數（相對網通模型） | B49: x | D49: =1 -> 1 | E49: =pxr_27 -> 1 | F49: =pxr_28 -> 1 | G49: =pxr_29 -> 1
A50: 新易盛占 CPO 光學金額 | B50: % | D50: =0 -> 0 | E50: =cpo_27 -> 0.05 | F50: =cpo_28 -> 0.1 | G50: =cpo_29 -> 0.15
A51: AI 營收（美元） | B51: US$B | D51: =a26_aiu -> 7.6480768 | E51: =E43*E48*E49+E44*E50 -> 11.155176 | F51: =F43*F48*F49+F44*F50 -> 10.333716 | G51: =G43*G48*G49+G44*G50 -> 12.073445
A52: AI 營收 | B52: RMB B | C52: =a25_ai -> 23.5999 | D52: =D51*D45 -> 51.395076 | E52: =E51*E45 -> 74.962781 | F52: =F51*F45 -> 69.44257 | G52: =G51*G45 -> 81.133549
A53: B. 其他營收與合計
A54: 其他營收（國內、電信等） | B54: RMB B | C54: =a25_oth -> 1.2421 | D54: =a26_oth -> 2.705004 | E54: =D54*(1+g_oth) -> 2.9755044 | F54: =E54*(1+g_oth) -> 3.2730548 | G54: =F54*(1+g_oth) -> 3.6003603
A55: 營收 | B55: RMB B | C55: =a25_rev -> 24.842 | D55: =D52+D54 -> 54.10008 | E55: =E52+E54 -> 77.938286 | F55: =F52+F54 -> 72.715625 | G55: =G52+G54 -> 84.733909
A56: 營收年增 | B56: % | D56: =D55/C55-1 -> 1.1777667 | E56: =E55/D55-1 -> 0.44063162 | F56: =F55/E55-1 -> -0.06701021 | G56: =G55/F55-1 -> 0.16527788
A57: AI ÷ 營收 | B57: % | C57: =C52/C55 -> 0.95 | D57: =D52/D55 -> 0.95 | E57: =E52/E55 -> 0.9618223 | F57: =F52/F55 -> 0.95498829 | G57: =G52/G55 -> 0.9575098
A58: C. 損益
A59: 毛利率 | B59: % | C59: =a25_gp/a25_rev -> 0.4781 | D59: =a26_gp/a26_rev -> 0.48170063 | E59: =gm_27 -> 0.47 | F59: =gm_28 -> 0.46 | G59: =gm_29 -> 0.45 | H59: FY2027 起為輸入路徑（1.6T 占比上推 vs 降價下壓）
A60: 毛利 | B60: RMB B | C60: =C55*C59 -> 11.87696 | D60: =D55*D59 -> 26.060042 | E60: =E55*E59 -> 36.630994 | F60: =F55*F59 -> 33.449188 | G60: =G55*G59 -> 38.130259
A61: 營業費用、減值與其他（基準路徑） | B61: RMB B | C61: =a25_opx -> 1.0212784 | D61: =a26_opx -> 3.2137771 | E61: =D61*(1+MAX(0,phi*E56)) -> 4.0634322 | F61: =E61*(1+MAX(0,phi*F56)) -> 4.0634322 | G61: =F61*(1+MAX(0,phi*G56)) -> 4.4663895
A62: 營業費用、減值與其他 | B62: RMB B | C62: =C61 -> 1.0212784 | D62: =D61 -> 3.2137771 | E62: =E61+0*E55 -> 4.0634322 | F62: =F61+0*F55 -> 4.0634322 | G62: =G61+0*G55 -> 4.4663895
A63: 稅前利益（＝毛利 − 營業費用等） | B63: RMB B | C63: =C60-C62 -> 10.855682 | D63: =D60-D62 -> 22.846265 | E63: =E60-E62 -> 32.567562 | F63: =F60-F62 -> 29.385755 | G63: =G60-G62 -> 33.66387
A64: 稅前利益率 | B64: % | C64: =C63/C55 -> 0.43698904 | D64: =D63/D55 -> 0.42229633 | E64: =E63/E55 -> 0.41786346 | F64: =F63/F55 -> 0.40411886 | G64: =G63/G55 -> 0.39728923
A65: 歸母淨利 | B65: RMB B | C65: =a25_ni -> 9.532 | D65: =a26_ni -> 20.060518 | E65: =E63*(1-tx)*attr -> 28.596454 | F65: =F63*(1-tx)*attr -> 25.802619 | G65: =G63*(1-tx)*attr -> 29.559083
A66: 淨利率 | B66: % | C66: =C65/C55 -> 0.38370502 | D66: =D65/D55 -> 0.37080385 | E66: =E65/E55 -> 0.3669115 | F66: =F65/F55 -> 0.35484284 | G66: =G65/G55 -> 0.34884598
A67: 股數（轉增後） | B67: 十億股 | C67: =a25_sh -> 1.3886368 | D67: =a26_sh -> 1.392841 | E67: =sh_post*(1+sh_g) -> 1.394 | F67: =E67*(1+sh_g) -> 1.394 | G67: =F67*(1+sh_g) -> 1.394
A68: EPS | B68: RMB | C68: =C65/C67 -> 6.8642857 | D68: =D65/D67 -> 14.40259 | E68: =E65/E67 -> 20.513955 | F68: =F65/F67 -> 18.50977 | G68: =G65/G67 -> 21.204508
A69: EPS 年增 | B69: % | D69: =D68/C68-1 -> 1.0981921 | E69: =E68/D68-1 -> 0.42432407 | F69: =F68/E68-1 -> -0.09769865 | G69: =G68/F68-1 -> 0.14558463
A72: 案例區塊：份額上升（高）（情境 A）
A73: 項目 | B73: 單位 | C73: FY2025A | D73: FY2026（錨點） | E73: FY2027 | F73: FY2028 | G73: FY2029 | H73: 說明
A74: A. AI 營收（D 欄＝FY2026 校準年；E–G＝FY2027–FY2029）
A75: AI 可插拔光模組市場 × 情境顆數係數 | B75: US$B | D75: =mpl_26*1 -> 29.753262 | E75: =mpl_27*1*1 -> 53.560715 | F75: =mpl_28*um28_A*1 -> 57.9915 | G75: =mpl_29*um29_A*1 -> 72.9348
A76: AI CPO 光學市場 × 情境顆數係數 | B76: US$B | D76: =mcp_26*1 -> 0.300538 | E76: =mcp_27*1 -> 2.818985 | F76: =mcp_28*um28_A -> 6.4435 | G76: =mcp_29*um29_A -> 11.74736
A77: 人民幣兌美元 | B77: RMB | D77: =fx -> 6.72 | E77: =fx -> 6.72 | F77: =fx -> 6.72 | G77: =fx -> 6.72 | H77: FY2026 校準用基準匯率；Sens 只動 FY2027 起
A78: 新易盛可插拔有效份額（FY2026 校準）＝ AI 營收（美元）÷ 可插拔市場 | B78: % | D78: =a26_aiu/D75 -> 0.25705003 | H78: Derived：FY2026 CPO 營收視為 0；FY2027 起乘相對值
A79: 份額相對值（÷ FY2026） | B79: x | D79: =1 -> 1 | E79: =RHI_27 -> 1.15 | F79: =RHI_28 -> 1.2 | G79: =RHI_29 -> 1.2
A80: 可插拔有效份額 | B80: % | D80: =$D$78*D79 -> 0.25705003 | E80: =$D$78*E79 -> 0.29560753 | F80: =$D$78*F79 -> 0.30846003 | G80: =$D$78*G79 -> 0.30846003
A81: 單價係數（相對網通模型） | B81: x | D81: =1 -> 1 | E81: =pxr_27 -> 1 | F81: =pxr_28 -> 1 | G81: =pxr_29 -> 1
A82: 新易盛占 CPO 光學金額 | B82: % | D82: =0 -> 0 | E82: =cpo_27 -> 0.05 | F82: =cpo_28 -> 0.1 | G82: =cpo_29 -> 0.15
A83: AI 營收（美元） | B83: US$B | D83: =a26_aiu -> 7.6480768 | E83: =E75*E80*E81+E76*E82 -> 15.9739 | F83: =F75*F80*F81+F76*F82 -> 18.53241 | G83: =G75*G80*G81+G76*G82 -> 24.259575
A84: AI 營收 | B84: RMB B | C84: =a25_ai -> 23.5999 | D84: =D83*D77 -> 51.395076 | E84: =E83*E77 -> 107.34461 | F84: =F83*F77 -> 124.53779 | G84: =G83*G77 -> 163.02434
A85: B. 其他營收與合計
A86: 其他營收（國內、電信等） | B86: RMB B | C86: =a25_oth -> 1.2421 | D86: =a26_oth -> 2.705004 | E86: =D86*(1+g_oth) -> 2.9755044 | F86: =E86*(1+g_oth) -> 3.2730548 | G86: =F86*(1+g_oth) -> 3.6003603
A87: 營收 | B87: RMB B | C87: =a25_rev -> 24.842 | D87: =D84+D86 -> 54.10008 | E87: =E84+E86 -> 110.32011 | F87: =F84+F86 -> 127.81085 | G87: =G84+G86 -> 166.6247
A88: 營收年增 | B88: % | D88: =D87/C87-1 -> 1.1777667 | E88: =E87/D87-1 -> 1.0391857 | F88: =F87/E87-1 -> 0.15854532 | G88: =G87/F87-1 -> 0.30368199
A89: AI ÷ 營收 | B89: % | C89: =C84/C87 -> 0.95 | D89: =D84/D87 -> 0.95 | E89: =E84/E87 -> 0.97302845 | F89: =F84/F87 -> 0.97439142 | G89: =G84/G87 -> 0.9783924
A90: C. 損益
A91: 毛利率 | B91: % | C91: =a25_gp/a25_rev -> 0.4781 | D91: =a26_gp/a26_rev -> 0.48170063 | E91: =gm_27 -> 0.47 | F91: =gm_28 -> 0.46 | G91: =gm_29 -> 0.45 | H91: FY2027 起為輸入路徑（1.6T 占比上推 vs 降價下壓）
A92: 毛利 | B92: RMB B | C92: =C87*C91 -> 11.87696 | D92: =D87*D91 -> 26.060042 | E92: =E87*E91 -> 51.850453 | F92: =F87*F91 -> 58.792991 | G92: =G87*G91 -> 74.981116
A93: 營業費用、減值與其他（基準路徑） | B93: RMB B | C93: =a25_opx -> 1.0212784 | D93: =a26_opx -> 3.2137771 | E93: =D93*(1+MAX(0,phi*E88)) -> 5.2176039 | F93: =E93*(1+MAX(0,phi*F88)) -> 5.7139399 | G93: =F93*(1+MAX(0,phi*G88)) -> 6.7550723
A94: 營業費用、減值與其他 | B94: RMB B | C94: =C93 -> 1.0212784 | D94: =D93 -> 3.2137771 | E94: =E93+0*E87 -> 5.2176039 | F94: =F93+0*F87 -> 5.7139399 | G94: =G93+0*G87 -> 6.7550723
A95: 稅前利益（＝毛利 − 營業費用等） | B95: RMB B | C95: =C92-C94 -> 10.855682 | D95: =D92-D94 -> 22.846265 | E95: =E92-E94 -> 46.632849 | F95: =F92-F94 -> 53.079051 | G95: =G92-G94 -> 68.226044
A96: 稅前利益率 | B96: % | C96: =C95/C87 -> 0.43698904 | D96: =D95/D87 -> 0.42229633 | E96: =E95/E87 -> 0.42270487 | F96: =F95/F87 -> 0.41529378 | G96: =G95/G87 -> 0.40945936
A97: 歸母淨利 | B97: RMB B | C97: =a25_ni -> 9.532 | D97: =a26_ni -> 20.060518 | E97: =E95*(1-tx)*attr -> 40.946697 | F97: =F95*(1-tx)*attr -> 46.606885 | G97: =G95*(1-tx)*attr -> 59.906937
A98: 淨利率 | B98: % | C98: =C97/C87 -> 0.38370502 | D98: =D97/D87 -> 0.37080385 | E98: =E97/E87 -> 0.37116258 | F98: =F97/F87 -> 0.36465515 | G98: =G97/G87 -> 0.35953215
A99: 股數（轉增後） | B99: 十億股 | C99: =a25_sh -> 1.3886368 | D99: =a26_sh -> 1.392841 | E99: =sh_post*(1+sh_g) -> 1.394 | F99: =E99*(1+sh_g) -> 1.394 | G99: =F99*(1+sh_g) -> 1.394
A100: EPS | B100: RMB | C100: =C97/C99 -> 6.8642857 | D100: =D97/D99 -> 14.40259 | E100: =E97/E99 -> 29.373527 | F100: =F97/F99 -> 33.43392 | G100: =G97/G99 -> 42.974847
A101: EPS 年增 | B101: % | D101: =D100/C100-1 -> 1.0981921 | E101: =E100/D100-1 -> 1.0394615 | F101: =F100/E100-1 -> 0.13823308 | G101: =G100/F100-1 -> 0.28536669
A104: 案例區塊：美國限制（情境 A）
A105: 項目 | B105: 單位 | C105: FY2025A | D105: FY2026（錨點） | E105: FY2027 | F105: FY2028 | G105: FY2029 | H105: 說明
A106: A. AI 營收（D 欄＝FY2026 校準年；E–G＝FY2027–FY2029）
A107: AI 可插拔光模組市場 × 情境顆數係數 | B107: US$B | D107: =mpl_26*1 -> 29.753262 | E107: =mpl_27*1*1 -> 53.560715 | F107: =mpl_28*um28_A*1 -> 57.9915 | G107: =mpl_29*um29_A*1 -> 72.9348
A108: AI CPO 光學市場 × 情境顆數係數 | B108: US$B | D108: =mcp_26*1 -> 0.300538 | E108: =mcp_27*1 -> 2.818985 | F108: =mcp_28*um28_A -> 6.4435 | G108: =mcp_29*um29_A -> 11.74736
A109: 人民幣兌美元 | B109: RMB | D109: =fx -> 6.72 | E109: =fx -> 6.72 | F109: =fx -> 6.72 | G109: =fx -> 6.72 | H109: FY2026 校準用基準匯率；Sens 只動 FY2027 起
A110: 新易盛可插拔有效份額（FY2026 校準）＝ AI 營收（美元）÷ 可插拔市場 | B110: % | D110: =a26_aiu/D107 -> 0.25705003 | H110: Derived：FY2026 CPO 營收視為 0；FY2027 起乘相對值
A111: 份額相對值（÷ FY2026） | B111: x | D111: =1 -> 1 | E111: =us_27 -> 0.9 | F111: =us_28 -> 0.55 | G111: =us_29 -> 0.5
A112: 可插拔有效份額 | B112: % | D112: =$D$110*D111 -> 0.25705003 | E112: =$D$110*E111 -> 0.23134502 | F112: =$D$110*F111 -> 0.14137751 | G112: =$D$110*G111 -> 0.12852501
A113: 單價係數（相對網通模型） | B113: x | D113: =1 -> 1 | E113: =pxr_27 -> 1 | F113: =pxr_28 -> 1 | G113: =pxr_29 -> 1
A114: 新易盛占 CPO 光學金額 | B114: % | D114: =0 -> 0 | E114: =cpo_27 -> 0.05 | F114: =cpo_28 -> 0.1 | G114: =cpo_29 -> 0.15
...

Sheet Sources
A1: 來源（公司原文＝深交所定期報告與公告，經財經媒體轉載；原文 PDF 待人工複核）
A2: 公司（轉載）：FY2025 營收、歸母淨利、EPS、10 轉 4 派 10（東方財富／中證網） | B2: https://finance.eastmoney.com/a/202604243717729349.html
A3: 公司（轉載）：FY2025 光互聯毛利率、4Q25、1Q26 實績與匯兌損失（每日經濟新聞） | B3: https://www.nbd.com.cn/articles/2026-04-24/4356482.html
A4: 公司（轉載）：FY2025 存貨、減值、1Q26 季減（虎嗅） | B4: https://www.huxiu.com/article/4853326.html
A5: 公司（轉載）：1H26 實績、光互聯毛利率 48.46%、境外收入、研發（C114） | B5: https://m.c114.com.cn/w123-1316262.html
A6: 公司（轉載）：1H26 基本 EPS 5.41（東方財富） | B6: https://finance.eastmoney.com/a/202608243851382445.html
A7: 券商：西南證券 9-15（1H26 綜合毛利率 48.44%、境外 97.92%、與中際旭創比較） | B7: https://stock.10jqka.com.cn/20260915/c679905127.shtml
A8: 券商：長江證券（2Q26 毛利率 47.96%、淨利率 37.77%） | B8: https://m.gelonghui.com/news/5306856
A9: 券商：開源證券 8-25（總股本 13.94 億、少數股東損益、費用率） | B9: https://pdf.dfcfw.com/pdf/H3_AP202608251828397684_1.pdf
A10: 券商：天風證券 10-10（2Q26、產能、盈利預測） | B10: https://stock.10jqka.com.cn/20261010/c680549851.shtml
A11: 公司（轉載）：2026 年限制性股票激勵（同花順） | B11: https://stock.10jqka.com.cn/20260820/c679144690.shtml
A12: 公司說法（轉載）：NPO 2027 批量、1.6T 下半年放量（同花順 9-28） | B12: https://stock.10jqka.com.cn/20260928/c680329640.shtml
A13: 共識：同花順 F10 盈利預測（2026-10-23） | B13: https://basic.10jqka.com.cn/300502/worth.html
... A21: 資料商：stockanalysis 會計年底 P/E | B21: https://stockanalysis.com/quote/she/300502/financials/ratios/
A22: 市場層：markets/network、tsmc、innolight 成品（本 repo，唯讀）
A23: 待補（人工）：3Q26 季報（10-30）；全公司 FY2025 毛利率；客戶名稱與集中度；800G／1.6T 份額第一手來源；泰國子公司稅率；52 週高點（資料商不一致）；近一個月跌幅原因；前瞻 P/E 歷史（Bloomberg） | B23: 未找到
A24: SemiAnalysis | B24: 未使用
