Workbook

Sheet README
A1: Coherent（COHR，NYSE）收支與估值模型 v0.2（AI 半導體 Project：網通次產業內複製——光模組，樣板中際旭創） 2026-10-25
A2: 版本：v0.2（2026-10-25：三情境延伸到 FY2032、目標價＝DCF 與 Comparable 加權；v0.1 初版）。Coherent 的有效份額口徑與中際旭創模型一致（資料中心營收 ÷ 可插拔市場），Units 頁檢查兩者相加低於 100%。
A3: 模型命題：Coherent 的資料中心營收＝AI 可插拔光模組市場（本專案網通模型）× Coherent 有效份額（光模組＋自製 EML／VCSEL／CW 雷射）× 單價係數＋CPO 光學 × CPO 份額；通訊、工業另依成長率推。股價自 52 週高點 440 跌到約 209（−52%），約 21 倍共識未來 12 月 EPS：市場在問磷化銦產能倍增換來的成長能否撐到 FY2028。
A4: 核心問題：FY2027 訂單已近滿載，股價卻腰斬——市場隱含的 FY2028 EPS 要多低，份額（新易盛、中際旭創）、單價、AI 市場三條路徑各要不利到什麼程度？
A6: 會計年度：FY(t)＝t−1 年 7 月～t 年 6 月（6 月底結束）；FY2026＝2025-07～2026-06（實績）、FY2027＝2026-07～2027-06。日曆年市場以「上半年比重 hw」換算：FY(t)＝（1 − hw）× CY(t−1)＋hw × CY(t)，FY2027 的 CY2026 下半年用 Q1 指引＋Q2 假設。口徑：non-GAAP；淨利＝歸屬 Coherent。
A8: 驅動因子 → 推導量（全部唯讀上游，不修改）
A9: 資料中心：markets/network 的 AI 可插拔光模組市場 × 情境顆數係數 × Coherent 有效份額（CY2026 校準）× 份額相對值（Assumed）× 單價係數（基準 1）＋ CPO 光學市場 × CPO 份額（Assumed）。
A10: 通訊（電信、DCI、ZR、泵浦雷射）：FY2026 推導值 × 年增（Assumed）。工業（雷射、工程材料、SiC）：FY2026 Q4 × 4（已排除出售的 A&D 與慕尼黑工具）× 成長（Assumed）。毛利率：FY2027 起為輸入路徑。營業費用：彈性 phi（Derived）。稅率 19%（公司指引）。
A11: 校準：FY2026 全年實績；資料中心與通訊的金額公司未揭露，由 Q3、Q4 合計與兩者季增率聯立推導（Q 頁）。不用共識（只在 Recon 對帳）。
A12: 估值：目標價（Val 第 0 節）＝0.5 × DCF（股東現金流＝EPS ×（1 − g／ROE），FY2027–32 明確期＋永續，r 10%、g 4%，情境權重 0.3／0.5／0.2）＋0.5 × Comparable（美股光通訊同業前瞻 P/E 中位數 × 12 個月後前瞻 EPS）。舊法規則值情境加權保留參考（不是目標價）；現價 ÷ FY2027、FY2028 EPS；市場隱含 FY2028 EPS（Val 第 4 節）；十年 GAAP P/E 規則值（兩個資料商，虧損年不列入）× FY2027 EPS。本版未做先驗，無 Andy 合理 P/E 對照。
A13: 標記：Verified、Interested-party、Analogy、Assumed、Derived。SemiAnalysis 未使用。
A15: 已知限制：(1) 份額相對值、CPO 份額、毛利率路徑皆為 Assumed，是 FY2028 EPS 最敏感的輸入（Sens）；(2) 資料中心金額為推導值，FY2027 Q1 季報（2026-11-04）後更新；(3) 有效份額含賣給其他模組廠的雷射元件，與中際旭創份額有部分重疊；(4) 十年 P/E 為 GAAP 倍數、有效年數少，套在 non-GAAP EPS 偏高估；(5) SiC 單獨營收未揭露，包含在工業；(6) R4 產業部署路徑未建（Recon 預留列）。
A16: v0.2（2026-10-25）：Val 頁最前面新增「0. 目標價」（0.1 DCF、0.2 Comparable、0.3 結論），既有內容整體下移；原「0. 目標價與上檔空間」改名「舊法：規則值情境加權（參考）」保留。PL 三情境延伸到 FY2032（FY2030 起為收斂法，非驅動因子推導；灰底），說明欄移到 K 欄。In 頁新增 K 節（tp_r、tp_g、tp_roe、tp_w_dcf、收斂法參數、共識目標價）。Sens 加目標價參數列。FY2026–FY2029 既有數字不變。

Sheet In
A1: In — 輸入（藍字；基準欄 E，低 D、高 F）。金額：十億美元（US$B）；比例：%。每個輸入附兩個來源（找不到者寫「未找到」）；公司原文算一個
A2: 標記：Verified／Interested-party／Analogy／Assumed／Derived；Analogy、Assumed 給低／高區間。SemiAnalysis 未使用。公司原文＝SEC 8-K 新聞稿與 10-K；資料中心與通訊的金額拆分公司未揭露，以法說會季增、年增率推導
A3: 鍵 | B3: 項目 | C3: 單位 | D3: 低 | E3: 基準 | F3: 高 | G3: 標記 | H3: 來源1 | I3: 來源2／說明
A4: A. AI 光模組市場（讀 markets/network 成品；日曆年；情境 A 基準，B／C 依顆數係數縮放）
A5: mpl_26 | B5: AI 可插拔光模組市場 CY2026 | C5: US$B | E5: 29.753262 | G5: Derived | H5: markets/network/dist/20261023_AI網通市場模型_v0.2.2.xlsx｜Mkt!C20:F20 | I5: 加速器顆數 × 每顆光學內容（scale-out 為主；2029 含 scale-up 光學）− CPO
A6: mpl_27 | B6: AI 可插拔光模組市場 CY2027 | C6: US$B | E6: 54.688309 | G6: Derived | H6: markets/network/dist/20261023_AI網通市場模型_v0.2.2.xlsx｜Mkt!C20:F20 | I6: 同上
A7: mpl_28 | B7: AI 可插拔光模組市場 CY2028 | C7: US$B | E7: 61.21325 | G7: Derived | H7: markets/network/dist/20261023_AI網通市場模型_v0.2.2.xlsx｜Mkt!C20:F20 | I7: 同上
A8: mpl_29 | B8: AI 可插拔光模組市場 CY2029 | C8: US$B | E8: 78.80848 | G8: Derived | H8: markets/network/dist/20261023_AI網通市場模型_v0.2.2.xlsx｜Mkt!C20:F20 | I8: 同上
A9: mcp_26 | B9: AI CPO 光學市場 CY2026 | C9: US$B | E9: 0.300538 | G9: Derived | H9: markets/network/dist/20261023_AI網通市場模型_v0.2.2.xlsx｜Mkt!C19:F19 | I9: 共同封裝光學；網通模型的 CPO 滲透路徑
A10: mcp_27 | B10: AI CPO 光學市場 CY2027 | C10: US$B | E10: 1.691391 | G10: Derived | H10: markets/network/dist/20261023_AI網通市場模型_v0.2.2.xlsx｜Mkt!C19:F19 | I10: 同上
A11: mcp_28 | B11: AI CPO 光學市場 CY2028 | C11: US$B | E11: 3.22175 | G11: Derived | H11: markets/network/dist/20261023_AI網通市場模型_v0.2.2.xlsx｜Mkt!C19:F19 | I11: 同上
A12: mcp_29 | B12: AI CPO 光學市場 CY2029 | C12: US$B | E12: 5.87368 | G12: Derived | H12: markets/network/dist/20261023_AI網通市場模型_v0.2.2.xlsx｜Mkt!C19:F19 | I12: 同上
A13: itc_26 | B13: AI IT 資本支出 CY2026 | C13: US$B | E13: 781.87292 | G13: Derived | H13: markets/network/dist/20261023_AI網通市場模型_v0.2.2.xlsx｜Mkt!C27:F27 | I13: Recon 用：Coherent 資料中心營收 ÷ AI IT 資本支出
A14: itc_27 | B14: AI IT 資本支出 CY2027 | C14: US$B | E14: 1565.35 | G14: Derived | H14: markets/network/dist/20261023_AI網通市場模型_v0.2.2.xlsx｜Mkt!C27:F27 | I14: 同上
A15: itc_28 | B15: AI IT 資本支出 CY2028 | C15: US$B | E15: 1984.2639 | G15: Derived | H15: markets/network/dist/20261023_AI網通市場模型_v0.2.2.xlsx｜Mkt!C27:F27 | I15: 同上
A16: itc_29 | B16: AI IT 資本支出 CY2029 | C16: US$B | E16: 2260.3903 | G16: Derived | H16: markets/network/dist/20261023_AI網通市場模型_v0.2.2.xlsx｜Mkt!C27:F27 | I16: 同上
... A26: um29_C | B26: 情境 C：2029 顆數 ÷ 基準 | C26: x | E26: 0.6 | G26: Assumed | H26: tsmc/dist/20261025_台積電模型_v0.2.2.xlsx｜In!E42 | I26: 同上
A27: B. Coherent 份額與單價（資料中心＝光模組＋自製 EML／VCSEL／CW 雷射＋矽光元件；有效份額＝資料中心營收 ÷ 可插拔市場）
A28: rel_27 | B28: 可插拔有效份額 CY2027 ÷ CY2026（相對值） | C28: x | D28: 0.9 | E28: 1.1 | F28: 1.25 | G28: Assumed | H28: https://futurumgroup.com/insights/coherent-q4-fy-2026-earnings-1-6t-transceivers-ramp-cpo-revenue-approaches/：磷化銦雷射內部產能 CY2026 底較前一年倍增、CY2027 底再倍增以上；FY2027 訂單近乎滿載、訂單延伸到 CY2028（公司，Interested-party） | I28: https://lightcounting.com/newsletter/en/may-2026-optical-vendor-landscape-376：LightCounting 2025 光模組排名新易盛首次超過 Coherent 升到第二（Interested-party）
A29: rel_28 | B29: 可插拔有效份額 CY2028 ÷ CY2026 | C29: x | D29: 0.85 | E29: 1.15 | F29: 1.35 | G29: Assumed | H29: 同上；1.6T 放量較三個月前預期提前（公司） | I29: 中際旭創模型同期份額相對值 0.90（新易盛、Coherent 搶 1.6T）
A30: rel_29 | B30: 可插拔有效份額 CY2029 ÷ CY2026 | C30: x | D30: 0.8 | E30: 1.15 | F30: 1.4 | G30: Assumed | H30: 同上 | I30: —
A31: cpo_27 | B31: Coherent 占 CPO 光學金額 CY2027 | C31: % | D31: 0 | E31: 0.1 | F31: 0.25 | G31: Assumed | H31: https://futurumgroup.com/insights/coherent-q4-fy-2026-earnings-1-6t-transceivers-ramp-cpo-revenue-approaches/：CPO 營收自 2026 年 12 月季開始、scale-up CPO 自 CY2027 下半年；與 NVIDIA 合作超高功率 CW 雷射（公司） | I31: CPO、NPO 等整合光學增量市場逾 150 億美元（公司說法，Interested-party）
A32: cpo_28 | B32: Coherent 占 CPO 光學金額 CY2028 | C32: % | D32: 0 | E32: 0.15 | F32: 0.3 | G32: Assumed | H32: 同上 | I32: —
A33: cpo_29 | B33: Coherent 占 CPO 光學金額 CY2029 | C33: % | D33: 0 | E33: 0.2 | F33: 0.35 | G33: Assumed | H33: 同上 | I33: —
A34: pxr_27 | B34: 單價係數 CY2027（相對網通模型每顆內容；基準 1） | C34: x | D34: 0.9 | E34: 1 | F34: 1.05 | G34: Assumed | H34: 網通模型每顆光學內容已含世代單價；本係數只在 Sens 動（降價快於模型） | I34: https://futurumgroup.com/insights/coherent-q4-fy-2026-earnings-1-6t-transceivers-ramp-cpo-revenue-approaches/：長約含固定價格與最低採購承諾（公司）
A35: pxr_28 | B35: 單價係數 CY2028 | C35: x | D35: 0.8 | E35: 1 | F35: 1.05 | G35: Assumed | H35: 同上（與中際旭創模型相同） | I35: —
A36: pxr_29 | B36: 單價係數 CY2029 | C36: x | D36: 0.72 | E36: 1 | F36: 1.05 | G36: Assumed | H36: 同上 | I36: —
A37: hw | B37: 日曆年上半年占全年比重（資料中心；會計年度換算用） | C37: % | D37: 0.42 | E37: 0.46 | F37: 0.5 | G37: Assumed | H37: CY2026 推導：上半年（FY2026 Q3＋Q4）÷ 全年約 41%（高成長年下半年較重） | I37: CY2027 起成長放緩，比重向 50% 靠近；Sens 動 42%／50%
A38: q2_dg | B38: FY2027 Q2（2026-12 季）資料中心季增 | C38: % | D38: 0.05 | E38: 0.12 | F38: 0.2 | G38: Assumed | H38: https://www.benzinga.com/quote/COHR/earnings-forecasts：共識 Q2 營收 25.4 億美元（約 +10%，Interested-party） | I38: CPO 與 PhotonLink 初期營收自 12 月季開始（公司）
A39: C. FY2026 Q3／Q4 實績與資料中心、通訊拆分（公司只揭露 Datacenter & Communications 合計）
A40: q3_rev | B40: FY2026 Q3（2026-03 季）營收 | C40: US$B | E40: 1.8056 | G40: Verified | H40: https://www.sec.gov/Archives/edgar/data/0000820318/000119312526346860/d128030dex991.htm：1,805.6 百萬美元 | I40: https://futurumgroup.com/insights/coherent-q3-fy-2026-ai-data-center-demand-accelerates-optical-growth/：18.1 億美元
A41: q4_rev | B41: FY2026 Q4（2026-06 季）營收 | C41: US$B | E41: 2.0455 | G41: Verified | H41: https://www.sec.gov/Archives/edgar/data/0000820318/000119312526346860/d128030dex991.htm：2,045.5 百萬美元（年增 34%） | I41: https://futurumgroup.com/insights/coherent-q4-fy-2026-earnings-1-6t-transceivers-ramp-cpo-revenue-approaches/：20.5 億美元
A42: q3_dcc | B42: FY2026 Q3 資料中心與通訊（DCC）營收 | C42: US$B | E42: 1.3616 | G42: Verified | H42: https://www.sec.gov/Archives/edgar/data/0000820318/000119312526346860/d128030dex991.htm：1,361.6 百萬美元 | I42: https://futurumgroup.com/insights/coherent-q3-fy-2026-ai-data-center-demand-accelerates-optical-growth/：14 億美元（+37%）
A43: q4_dcc | B43: FY2026 Q4 DCC 營收 | C43: US$B | E43: 1.615 | G43: Verified | H43: https://www.sec.gov/Archives/edgar/data/0000820318/000119312526346860/d128030dex991.htm：1,615.0 百萬美元 | I43: https://futurumgroup.com/insights/coherent-q4-fy-2026-earnings-1-6t-transceivers-ramp-cpo-revenue-approaches/：16.2 億美元（+58.6%，占 79%）
A44: q4_dcc25 | B44: FY2025 Q4 DCC 營收（年增核對用） | C44: US$B | E44: 1.0183 | G44: Verified | H44: https://www.sec.gov/Archives/edgar/data/0000820318/000119312526346860/d128030dex991.htm：1,018.3 百萬美元 | I44: —
A45: q3_ind | B45: FY2026 Q3 工業營收 | C45: US$B | E45: 0.444 | G45: Verified | H45: https://www.sec.gov/Archives/edgar/data/0000820318/000119312526346860/d128030dex991.htm：444.0 百萬美元 | I45: https://futurumgroup.com/insights/coherent-q3-fy-2026-ai-data-center-demand-accelerates-optical-growth/：4.44 億美元
A46: q4_ind | B46: FY2026 Q4 工業營收 | C46: US$B | E46: 0.4305 | G46: Verified | H46: https://www.sec.gov/Archives/edgar/data/0000820318/000119312526346860/d128030dex991.htm：430.5 百萬美元（年減 15.8%；剔除出售事業約持平） | I46: https://futurumgroup.com/insights/coherent-q4-fy-2026-earnings-1-6t-transceivers-ramp-cpo-revenue-approaches/：同值
A47: q4_dg | B47: FY2026 Q4 資料中心季增 | C47: % | E47: 0.24 | G47: Interested-party | H47: https://futurumgroup.com/insights/coherent-q4-fy-2026-earnings-1-6t-transceivers-ramp-cpo-revenue-approaches/：資料中心季增 24%、年增 66%（法說會，公司） | I47: https://www.webull.com/news/15393555909010432：同值（逐字稿轉述）
A48: q4_cg | B48: FY2026 Q4 通訊季增 | C48: % | E48: 0.11 | G48: Interested-party | H48: https://futurumgroup.com/insights/coherent-q4-fy-2026-earnings-1-6t-transceivers-ramp-cpo-revenue-approaches/：通訊（DCI、ZR／ZR+、泵浦雷射）季增 11%、年增 56%（公司） | I48: https://www.webull.com/news/15393555909010432：同值
A49: q4_dy | B49: FY2026 Q4 資料中心年增（核對用） | C49: % | E49: 0.66 | G49: Interested-party | H49: https://futurumgroup.com/insights/coherent-q4-fy-2026-earnings-1-6t-transceivers-ramp-cpo-revenue-approaches/ | I49: https://www.webull.com/news/15393555909010432
A50: q4_cy | B50: FY2026 Q4 通訊年增（核對用） | C50: % | E50: 0.56 | G50: Interested-party | H50: https://futurumgroup.com/insights/coherent-q4-fy-2026-earnings-1-6t-transceivers-ramp-cpo-revenue-approaches/ | I50: https://www.webull.com/news/15393555909010432
A51: h1r26 | B51: FY2026 上半年資料中心 ÷ 下半年資料中心 | C51: x | D51: 0.72 | E51: 0.79 | F51: 0.86 | G51: Assumed | H51: Futurum FY2026 Q1（網址見 Sources）：FY2026 Q1 資料中心年增 23%；Q2 指引約季增 10%（公司） | I51: FY2027 Q1 資料中心年增逾 80%（公司指引）回推 Q1 約 0.67、Q2 約 0.74，對下半年 1.79 約 0.79（推導；資料中心金額公司未揭露：未找到）
A52: D. FY2027 Q1 指引與 Q2 假設（＝CY2026 下半年）
A53: q1_rev | B53: FY2027 Q1（2026-09 季）營收指引中點 | C53: US$B | D53: 2.2 | E53: 2.3 | F53: 2.4 | G53: Interested-party | H53: https://www.sec.gov/Archives/edgar/data/0000820318/000119312526346860/d128030dex991.htm：22–24 億美元（公司指引） | I53: https://www.investing.com/news/stock-market-news/coherent-posts-a-blowout-q4-and-aggressive-guidance-yet-shares-take-a-5-haircut-4856014：高於共識 21.3 億美元
A54: q1_gm | B54: FY2027 Q1 non-GAAP 毛利率指引中點 | C54: % | D54: 0.395 | E54: 0.405 | F54: 0.415 | G54: Interested-party | H54: https://www.sec.gov/Archives/edgar/data/0000820318/000119312526346860/d128030dex991.htm：39.5%–41.5%（公司指引） | I54: —
A55: q1_opx | B55: FY2027 Q1 non-GAAP 營業費用指引中點 | C55: US$B | D55: 0.4 | E55: 0.41 | F55: 0.42 | G55: Interested-party | H55: https://www.sec.gov/Archives/edgar/data/0000820318/000119312526346860/d128030dex991.htm：4.0–4.2 億美元（公司指引） | I55: —
A56: q1_eps | B56: FY2027 Q1 non-GAAP EPS 指引中點 | C56: US$ | D56: 1.85 | E56: 1.95 | F56: 2.05 | G56: Interested-party | H56: https://www.sec.gov/Archives/edgar/data/0000820318/000119312526346860/d128030dex991.htm：1.85–2.05 美元（公司指引） | I56: https://www.benzinga.com/quote/COHR/earnings-forecasts：共識 1.93
A57: q_cg | B57: 通訊季增（FY2027 Q1、Q2） | C57: % | D57: 0 | E57: 0.05 | F57: 0.1 | G57: Assumed | H57: FY2026 Q4 通訊季增 11%（公司） | I57: —
A58: q_ig | B58: 工業季增（FY2027 Q1、Q2） | C58: % | D58: -0.03 | E58: 0 | F58: 0.03 | G58: Assumed | H58: https://futurumgroup.com/insights/coherent-q4-fy-2026-earnings-1-6t-transceivers-ramp-cpo-revenue-approaches/：工業剔除出售事業約持平；半導體與顯示器設備季增（公司） | I58: —
A59: E. 通訊與工業（年增；FY2028 起）——已出售事業排除
A60: g_com_27 | B60: 通訊營收年增 FY2027 | C60: % | D60: 0.1 | E60: 0.2 | F60: 0.3 | G60: Assumed | H60: https://futurumgroup.com/insights/coherent-q4-fy-2026-earnings-1-6t-transceivers-ramp-cpo-revenue-approaches/：通訊 FY2026 Q4 年增 56%（DCI、scale-across、ZR／ZR+） | I60: OCS 光路交換潛在市場逾 40 億美元（約 2030，公司說法）
A61: g_com_28 | B61: 通訊營收年增 FY2028 | C61: % | D61: 0 | E61: 0.12 | F61: 0.2 | G61: Assumed | H61: 同上 | I61: —
A62: g_com_29 | B62: 通訊營收年增 FY2029 | C62: % | D62: -0.05 | E62: 0.08 | F62: 0.15 | G62: Assumed | H62: 同上 | I62: —
A63: ind_run | B63: 工業營收基期（FY2026 Q4 × 4；已排除出售事業） | C63: US$B | E63: =q4_ind*4 -> 1.722 | G63: Derived | H63: https://futurumgroup.com/insights/coherent-q2-fy-2026-ai-datacenter-demand-lifts-revenue-and-margins：慕尼黑工具事業 2026-01 出售（每季約 2,500 萬美元）；A&D 於 FY2026 出售（約 4 億美元，10-K） | I63: https://www.autobound.ai/companies/coherent/10-k：A&D 出售約 4 億美元（10-K 摘要）
A64: g_ind_27 | B64: 工業營收 FY2027 ÷ 基期 − 1 | C64: % | D64: -0.05 | E64: 0.02 | F64: 0.08 | G64: Assumed | H64: 半導體設備回升；Thermadite（XPU 散熱材料）CY2027 下半年起量（公司） | I64: 工業含雷射、工程材料與 SiC 基板（10-K）；SiC 單獨營收：未找到
A65: g_ind_28 | B65: 工業營收年增 FY2028 | C65: % | D65: -0.05 | E65: 0.05 | F65: 0.1 | G65: Assumed | H65: 同上 | I65: SiC 子公司 25% 由 DENSO、三菱電機持有（2023 年投資 10 億美元）
A66: g_ind_29 | B66: 工業營收年增 FY2029 | C66: % | D66: -0.05 | E66: 0.05 | F66: 0.1 | G66: Assumed | H66: 同上 | I66: —
A67: F. 毛利率、費用、稅率、股數（non-GAAP）
A68: gm_27 | B68: non-GAAP 毛利率 FY2027 | C68: % | D68: 0.385 | E68: 0.41 | F68: 0.425 | G68: Assumed | H68: https://www.sec.gov/Archives/edgar/data/0000820318/000119312526346860/d128030dex991.htm：FY2026 39.4%、Q4 40.2%；Q1 指引 39.5%–41.5% | I68: https://www.investing.com/news/stock-market-news/coherent-posts-a-blowout-q4-and-aggressive-guidance-yet-shares-take-a-5-haircut-4856014：Barclays 指出低毛利光模組占比上升壓毛利（Interested-party）
A69: gm_28 | B69: non-GAAP 毛利率 FY2028 | C69: % | D69: 0.375 | E69: 0.42 | F69: 0.44 | G69: Assumed | H69: https://futurumgroup.com/insights/coherent-q4-fy-2026-earnings-1-6t-transceivers-ramp-cpo-revenue-approaches/：長期目標 42% 以上；六吋磷化銦產出 4 倍、成本約一半（公司） | I69: https://futurumgroup.com/insights/coherent-q2-fy-2026-ai-datacenter-demand-lifts-revenue-and-margins：1.6T 毛利率高於 800G（公司）
A70: gm_29 | B70: non-GAAP 毛利率 FY2029 | C70: % | D70: 0.365 | E70: 0.42 | F70: 0.45 | G70: Assumed | H70: 同上 | I70: —
A71: phi | B71: 營業費用成長對營收成長的彈性 | C71: x | D71: 0.4 | E71: =Q!B24 -> 0.70247399 | F71: 0.9 | G71: Derived | H71: FY2026 non-GAAP 營業費用年增 ÷ 營收年增（Q 頁） | I71: https://www.webull.com/news/15393555909010432：目標營業費用率 18%；FY2026 19.0%、Q4 18.4%（公司）
A72: opx_adj | B72: 營業費用額外占營收比（Sens 用；基準 0） | C72: pt | D72: -0.01 | E72: 0 | F72: 0.02 | G72: Assumed | H72: 無 | I72: Sens 用 +2 個百分點
A73: int_f | B73: non-GAAP 利息與其他淨支出（FY2027 起，每年） | C73: US$B | D73: 0.04 | E73: 0.08 | F73: 0.12 | G73: Assumed | H73: https://www.sec.gov/Archives/edgar/data/0000820318/000119312526346860/d128030dex991.htm：FY2026 1.181 億美元；長期借款 32.1 億、現金與短期投資 19.9 億美元（2026-06） | I73: https://www.webull.com/news/15393555909010432：FY2026 還債 5.13 億美元、槓桿 0.7x
A74: tx | B74: non-GAAP 稅率 | C74: % | D74: 0.18 | E74: 0.19 | F74: 0.2 | G74: Interested-party | H74: https://www.sec.gov/Archives/edgar/data/0000820318/000119312526346860/d128030dex991.htm：FY2027 Q1 指引 18%–20%；FY2026 19%（公司） | I74: —
A75: nci | B75: 少數股權調整（加回；每年） | C75: US$B | E75: =Q!C15 -> 0.0122 | G75: Derived | H75: FY2026 non-GAAP 歸屬淨利 − 稅後稅前利益（Q 頁）；SiC 子公司少數股權分攤虧損 | I75: —
A76: sh_q4 | B76: FY2026 Q4 non-GAAP 稀釋股數 | C76: 十億股 | E76: 0.2022 | G76: Verified | H76: https://www.sec.gov/Archives/edgar/data/0000820318/000119312526346860/d128030dex991.htm：202.2 百萬股 | I76: https://www.sec.gov/Archives/edgar/data/820318/000082031826000020/iivi-20260630.htm：普通股 195,832,246 股（2026-08-10）
A77: sh_g | B77: 股數年變動 | C77: % | D77: 0 | E77: 0.01 | F77: 0.03 | G77: Assumed | H77: 10-K 摘要（autobound，網址見 Sources）：NVIDIA 投資 20 億美元；FY2026 發行新股 19.99 億美元（8-K） | I77: 股票薪酬稀釋；回購：未找到
A78: mf | B78: AI 市場係數（Sens 用；CY2027 起） | C78: x | D78: 0.8 | E78: 1 | F78: 1.2 | G78: Assumed | H78: 網通模型 CY2027 可插拔光模組 +84% | I78: ±20%
A79: G. FY2025、FY2026 實績（non-GAAP；US$B）
A80: a25_rev_in | B80: FY2025 營收 | C80: US$B | E80: 5.8101 | G80: Verified | H80: https://www.sec.gov/Archives/edgar/data/0000820318/000119312526346860/d128030dex991.htm：5,810.1 | I80: —
A81: a26_rev_in | B81: FY2026 營收 | C81: US$B | E81: 7.1182 | G81: Verified | H81: https://www.sec.gov/Archives/edgar/data/0000820318/000119312526346860/d128030dex991.htm：7,118.2 百萬美元 | I81: https://www.webull.com/news/15393555909010432：同值（法說會轉述）
A82: a25_dcc_in | B82: FY2025 資料中心與通訊（DCC）營收 | C82: US$B | E82: 3.7552 | G82: Verified | H82: https://www.sec.gov/Archives/edgar/data/0000820318/000119312526346860/d128030dex991.htm：3,755.2 | I82: —
A83: a26_dcc_in | B83: FY2026 資料中心與通訊（DCC）營收 | C83: US$B | E83: 5.2746 | G83: Verified | H83: https://www.sec.gov/Archives/edgar/data/0000820318/000119312526346860/d128030dex991.htm：5,274.6（FY2026 起新分部，FY2025 重編） | I83: https://www.webull.com/news/15393555909010432：同值（法說會轉述）
A84: a25_ind_in | B84: FY2025 工業營收（含已出售事業） | C84: US$B | E84: 2.0549 | G84: Verified | H84: https://www.sec.gov/Archives/edgar/data/0000820318/000119312526346860/d128030dex991.htm：2,054.9 | I84: —
A85: a26_ind_in | B85: FY2026 工業營收（含已出售事業） | C85: US$B | E85: 1.8436 | G85: Verified | H85: https://www.sec.gov/Archives/edgar/data/0000820318/000119312526346860/d128030dex991.htm：1,843.6 | I85: —
A86: a25_gp_in | B86: FY2025 non-GAAP 毛利 | C86: US$B | E86: 2.2023 | G86: Verified | H86: https://www.sec.gov/Archives/edgar/data/0000820318/000119312526346860/d128030dex991.htm：2,202.3 | I86: —
A87: a26_gp_in | B87: FY2026 non-GAAP 毛利 | C87: US$B | E87: 2.8065 | G87: Verified | H87: https://www.sec.gov/Archives/edgar/data/0000820318/000119312526346860/d128030dex991.htm：2,806.5 | I87: —
A88: a25_opx_in | B88: FY2025 non-GAAP 營業費用（研發＋銷管） | C88: US$B | E88: =0.5543+0.611 -> 1.1653 | G88: Verified | H88: https://www.sec.gov/Archives/edgar/data/0000820318/000119312526346860/d128030dex991.htm：研發 554.3＋銷管 611.0 | I88: —
A89: a26_opx_in | B89: FY2026 non-GAAP 營業費用（研發＋銷管） | C89: US$B | E89: =0.6933+0.6563 -> 1.3496 | G89: Verified | H89: https://www.sec.gov/Archives/edgar/data/0000820318/000119312526346860/d128030dex991.htm：研發 693.3＋銷管 656.3 | I89: —
A90: a25_int_in | B90: FY2025 non-GAAP 利息與其他淨支出 | C90: US$B | E90: 0.1673 | G90: Verified | H90: https://www.sec.gov/Archives/edgar/data/0000820318/000119312526346860/d128030dex991.htm：167.3 | I90: —
A91: a26_int_in | B91: FY2026 non-GAAP 利息與其他淨支出 | C91: US$B | E91: 0.1181 | G91: Verified | H91: https://www.sec.gov/Archives/edgar/data/0000820318/000119312526346860/d128030dex991.htm：118.1 | I91: —
A92: a25_tax_in | B92: FY2025 non-GAAP 所得稅 | C92: US$B | E92: 0.184 | G92: Verified | H92: https://www.sec.gov/Archives/edgar/data/0000820318/000119312526346860/d128030dex991.htm：184.0 | I92: —
A93: a26_tax_in | B93: FY2026 non-GAAP 所得稅 | C93: US$B | E93: 0.2544 | G93: Verified | H93: https://www.sec.gov/Archives/edgar/data/0000820318/000119312526346860/d128030dex991.htm：254.4 | I93: —
A94: a25_ni_in | B94: FY2025 non-GAAP 歸屬 Coherent 淨利 | C94: US$B | E94: 0.6926 | G94: Verified | H94: https://www.sec.gov/Archives/edgar/data/0000820318/000119312526346860/d128030dex991.htm：692.6 | I94: —
A95: a26_ni_in | B95: FY2026 non-GAAP 歸屬 Coherent 淨利 | C95: US$B | E95: 1.0966 | G95: Verified | H95: https://www.sec.gov/Archives/edgar/data/0000820318/000119312526346860/d128030dex991.htm：1,096.6 | I95: —
A96: a25_eps_in | B96: FY2025 non-GAAP 稀釋 EPS | C96: US$ | E96: 3.53 | G96: Verified | H96: https://www.sec.gov/Archives/edgar/data/0000820318/000119312526346860/d128030dex991.htm：3.53 | I96: FY2025 EPS 已扣優先股股利（Q 頁推導）
A97: a26_eps_in | B97: FY2026 non-GAAP 稀釋 EPS | C97: US$ | E97: 5.61 | G97: Verified | H97: https://www.sec.gov/Archives/edgar/data/0000820318/000119312526346860/d128030dex991.htm：5.61 美元 | I97: https://www.webull.com/news/15393555909010432：同值（法說會轉述）
A98: a25_sh_in | B98: FY2025 non-GAAP 稀釋股數 | C98: 十億股 | E98: 0.1592 | G98: Verified | H98: https://www.sec.gov/Archives/edgar/data/0000820318/000119312526346860/d128030dex991.htm：159.2 | I98: —
A99: a26_sh_in | B99: FY2026 non-GAAP 稀釋股數 | C99: 十億股 | E99: 0.1954 | G99: Verified | H99: https://www.sec.gov/Archives/edgar/data/0000820318/000119312526346860/d128030dex991.htm：195.4 百萬股 | I99: —
A100: H. 共識、市場資料（只作 Recon 對帳，不作校準）
A101: cons_rev27 | B101: 共識 FY2027 營收 | C101: US$B | E101: 10.63 | G101: Interested-party | H101: https://www.tikr.com/blog/coherent-stock-fell-nearly-10-in-a-day-as-rising-yields-hit-optics-stocks-heres-where-the-stock-could-go-by-2031：106.3 億美元（2026-09-30，TIKR 彙整） | I101: 06-30 時為 95.7
A102: cons_rev28 | B102: 共識 FY2028 營收 | C102: US$B | E102: 14.76 | G102: Interested-party | H102: https://www.tikr.com/blog/coherent-stock-fell-nearly-10-in-a-day-as-rising-yields-hit-optics-stocks-heres-where-the-stock-could-go-by-2031：147.6 億美元（2026-09-30） | I102: 06-30 時為 129.2
A103: cons_eps27 | B103: 共識 FY2027 EPS | C103: US$ | E103: 8.67 | G103: Interested-party | H103: https://www.marketbeat.com/stocks/NYSE/COHR：8.67（2026-10-23，MarketBeat 未標年度，以下一年度判讀） | I103: https://www.benzinga.com/quote/COHR/earnings-forecasts：四季加總 1.93＋2.16＋2.26＋2.50＝8.85
A104: cons_eps27b | B104: 共識 FY2027 EPS（四季加總） | C104: US$ | E104: =1.93+2.16+2.26+2.5 -> 8.85 | G104: Interested-party | H104: https://www.benzinga.com/quote/COHR/earnings-forecasts：各季共識（2026-10-23） | I104: —
A105: cons_eps28 | B105: 共識 FY2028 EPS | C105: US$ | E105: 13.07 | G105: Interested-party | H105: MarketBeat（網址見 Sources）：13.07（2026-10-23） | I105: 第二來源：未找到
A106: cons_q1eps | B106: 共識 FY2027 Q1 EPS | C106: US$ | E106: 1.93 | G106: Interested-party | H106: https://www.benzinga.com/quote/COHR/earnings-forecasts | I106: —
A107: lc_eo25 | B107: 新易盛 2025 光模組營收（LightCounting；Coherent 低於此值） | C107: US$B | E107: 3.5 | G107: Interested-party | H107: LightCounting（網址見 Sources）：新易盛 35 億美元，2025 年首次超過 Coherent | I107: Coherent 光模組營收金額：未找到
A108: I. 價格與估值
A109: px | B109: 股價（2026-10-23 收盤） | C109: US$ | E109: 209.17 | G109: Interested-party | H109: https://www.marketbeat.com/stocks/NYSE/COHR：209.17（+0.65%） | I109: https://www.benzinga.com/quote/COHR/earnings-forecasts：209.29（10-23）
...

Sheet Q
A1: Q — 實績與季度拆分（十億美元；EPS 為美元；股數為十億股；non-GAAP）。藍字＝輸入（In 頁）；黑字＝公式。FY(t)＝t−1 年 7 月～t 年 6 月
A2: 資料中心與通訊的金額公司未揭露：FY2026 Q4 資料中心＝由 Q3、Q4 的 DCC 合計與兩者季增率聯立解出；Q3＝Q4 ÷（1＋季增）。FY2027 Q1 資料中心＝營收指引中點 − 通訊 − 工業；Q2 依季增假設。FY2027 Q1 季報（2026-11-04）公布後以實績取代
A3: 項目 | B3: FY2025A | C3: FY2026A | D3: FY2026 Q3 | E3: FY2026 Q4 | F3: FY2027 Q1（指引） | G3: FY2027 Q2（假設） | H3: 標記 | I3: 說明
A4: 營收 | B4: =a25_rev_in -> 5.8101 | C4: =a26_rev_in -> 7.1182 | D4: =q3_rev -> 1.8056 | E4: =q4_rev -> 2.0455 | F4: =q1_rev -> 2.3 | G4: =G5+G8 -> 2.4782859 | H4: Verified／Interested-party（指引）
A5: 資料中心與通訊（DCC） | B5: =a25_dcc_in -> 3.7552 | C5: =a26_dcc_in -> 5.2746 | D5: =q3_dcc -> 1.3616 | E5: =q4_dcc -> 1.615 | F5: =F6+F7 -> 1.8695 | G5: =G6+G7 -> 2.0477859 | H5: Verified
A6: 資料中心（AI 光模組、雷射與光元件、OCS） | B6: =B5*C6/C5 -> 2.2754201 | C6: =(D6+E6)*(1+h1r26) -> 3.196083 | D6: =E6/(1+q4_dg) -> 0.79710769 | E6: =(D5-E5/(1+q4_cg))/(1/(1+q4_dg)-1/(1+q4_cg)) -> 0.98841354 | F6: =F4-F7-F8 -> 1.2115842 | G6: =F6*(1+q2_dg) -> 1.3569743 | H6: Derived／Assumed | I6: Q4：聯立 Q3 DCC＝Q4 資料中心 ÷（1＋24%）＋Q4 通訊 ÷（1＋11%）；FY2026 全年＝下半年 ×（1＋上半年 ÷ 下半年比）；FY2025 假設與 FY2026 相同結構
A7: 通訊（電信、DCI、ZR、泵浦雷射） | B7: =B5-B6 -> 1.4797799 | C7: =C5-C6 -> 2.078517 | D7: =D5-D6 -> 0.56449231 | E7: =E5-E6 -> 0.62658646 | F7: =E7*(1+q_cg) -> 0.65791578 | G7: =F7*(1+q_cg) -> 0.69081157 | H7: Derived
A8: 工業（雷射、工程材料、SiC） | B8: =a25_ind_in -> 2.0549 | C8: =a26_ind_in -> 1.8436 | D8: =q3_ind -> 0.444 | E8: =q4_ind -> 0.4305 | F8: =E8*(1+q_ig) -> 0.4305 | G8: =F8*(1+q_ig) -> 0.4305 | H8: Verified／Assumed | I8: FY2025、FY2026 含已出售的 A&D 與慕尼黑工具事業；Q4 起不含
A9: non-GAAP 毛利 | B9: =a25_gp_in -> 2.2023 | C9: =a26_gp_in -> 2.8065 | F9: =F4*q1_gm -> 0.9315 | H9: Verified
A10: non-GAAP 毛利率 | B10: =B9/B4 -> 0.37904683 | C10: =C9/C4 -> 0.39427102 | F10: =F9/F4 -> 0.405 | H10: Derived
A11: non-GAAP 營業費用 | B11: =a25_opx_in -> 1.1653 | C11: =a26_opx_in -> 1.3496 | F11: =q1_opx -> 0.41 | H11: Verified
A12: non-GAAP 營業利益 | B12: =B9-B11 -> 1.037 | C12: =C9-C11 -> 1.4569 | F12: =F9-F11 -> 0.5215 | H12: Derived | I12: FY2026 公司揭露 1,456.9 百萬美元
A13: non-GAAP 利息與其他淨支出 | B13: =a25_int_in -> 0.1673 | C13: =a26_int_in -> 0.1181 | F13: =int_f/4 -> 0.02 | H13: Verified
A14: non-GAAP 稅率 | B14: =a25_tax_in/(B12-B13) -> 0.21156721 | C14: =a26_tax_in/(C12-C13) -> 0.19002091 | F14: =tx -> 0.19 | H14: Derived
A15: 少數股權調整（歸屬淨利 −（營業利益 − 利息）×（1 − 稅率）） | B15: =a25_ni_in-(B12-B13)*(1-B14) -> 0.0069 | C15: =a26_ni_in-(C12-C13)*(1-C14) -> 0.0122 | F15: =nci/4 -> 0.00305 | H15: Derived
A16: non-GAAP 歸屬 Coherent 淨利 | B16: =a25_ni_in -> 0.6926 | C16: =a26_ni_in -> 1.0966 | F16: =(F12-F13)*(1-F14)+F15 -> 0.409265 | H16: Verified／Derived
A17: 優先股股利（EPS 計算扣除） | B17: =a25_ni_in-a25_eps_in*a25_sh_in -> 0.130624 | C17: =0 -> 0 | F17: =0 -> 0 | H17: Derived | I17: FY2025 由淨利 − EPS × 股數推得；FY2026 起優先股已轉換，無扣除
A18: non-GAAP 稀釋股數 | B18: =a25_sh_in -> 0.1592 | C18: =a26_sh_in -> 0.1954 | E18: =sh_q4 -> 0.2022 | F18: =sh_q4 -> 0.2022 | H18: Verified
A19: non-GAAP 稀釋 EPS | B19: =(B16-B17)/B18 -> 3.53 | C19: =(C16-C17)/C18 -> 5.6120778 | F19: =(F16-F17)/F18 -> 2.0240603 | H19: Derived | I19: FY2027 Q1 指引中點 1.95
A21: 推導量
A22: FY2026 營收年增 | B22: =C4/B4-1 -> 0.22514242
A23: FY2026 營業費用年增 | B23: =C11/B11-1 -> 0.1581567
A24: 營業費用彈性（營業費用年增 ÷ 營收年增；In 頁 phi 的依據） | B24: =B23/B22 -> 0.70247399
A25: CY2026 資料中心（FY2026 Q3＋Q4＋FY2027 Q1＋Q2；份額校準基礎） | B25: =D6+E6+F6+G6 -> 4.3540798
A26: CY2026 下半年資料中心（＝FY2027 上半年） | B26: =F6+G6 -> 2.5685585
A27: CY2026 上半年資料中心 ÷ 全年（hw 的依據） | B27: =(D6+E6)/B25 -> 0.41008005
A28: 核對：FY2025 Q4 DCC 由年增率回推 ÷ 實績 − 1 | B28: =(E6/(1+q4_dy)+E7/(1+q4_cy))/q4_dcc25-1 -> -0.020830963
A29: FY2027 Q1 EPS（模型，指引中點）÷ 公司 EPS 指引中點 − 1 | B29: =F19/q1_eps-1 -> 0.03797966
A30: FY2026 資料中心 ÷ DCC | B30: =C6/C5 -> 0.60593846

Sheet Units
A1: Units — Coherent 在 AI 光模組的有效份額（日曆年）。市場取自 markets/network（加速器顆數 × 每顆光學內容；美元）；份額口徑與中際旭創模型一致（資料中心營收 ÷ 可插拔市場），兩者相加須低於 100%
A3: 項目 | B3: 單位 | C3: CY2026 | D3: CY2027 | E3: CY2028 | F3: CY2029 | G3: 說明
A4: AI 可插拔光模組市場（情境 A） | B4: US$B | C4: =PL!D63 -> 29.753262 | D4: =PL!E63 -> 54.688309 | E4: =PL!F63 -> 61.21325 | F4: =PL!G63 -> 78.80848 | G4: markets/network Mkt 頁
A5: AI CPO 光學市場（情境 A） | B5: US$B | C5: =PL!D64 -> 0.300538 | D5: =PL!E64 -> 1.691391 | E5: =PL!F64 -> 3.22175 | F5: =PL!G64 -> 5.87368 | G5: 同上
A6: Coherent 可插拔有效份額 | B6: % | C6: =PL!D67 -> 0.14633958 | D6: =PL!E67 -> 0.16097353 | E6: =PL!F67 -> 0.16829051 | F6: =PL!G67 -> 0.16829051 | G6: CY2026 以 FY2026 下半年實績（推導）＋FY2027 Q1 指引＋Q2 假設校準
A7: 中際旭創可插拔有效份額（innolight/dist） | B7: % | C7: =inl_26 -> 0.42183339 | D7: =inl_27 -> 0.40074172 | E7: =inl_28 -> 0.37965005 | F7: =inl_29 -> 0.35855838 | G7: 唯讀上游
A8: 兩者合計 | B8: % | C8: =C6+C7 -> 0.56817296 | D8: =D6+D7 -> 0.56171525 | E8: =E6+E7 -> 0.54794056 | F8: =F6+F7 -> 0.52684889 | G8: 須低於 100%；其餘由新易盛、Lumentum、Fabrinet 代工客戶等分配
A9: Coherent 資料中心營收（情境 A；日曆年） | B9: US$B | C9: =PL!D70 -> 4.3540798 | D9: =PL!E70 -> 8.9725095 | E9: =PL!F70 -> 10.784872 | F9: =PL!G70 -> 14.437456
A10: 其他廠商＝ 可插拔＋CPO − 中際旭創 − Coherent | B10: US$B | C10: =C4+C5-C7*C4-C9 -> 13.148801 | D10: =D4+D5-D7*D4-D9 -> 25.491304 | E10: =E4+E5-E7*E4-E9 -> 30.410515 | F10: =F4+F5-F7*F4-F9 -> 41.987264 | G10: 中際旭創以可插拔份額近似（其 CPO 份額不扣）
A11: Coherent 資料中心營收 ÷ AI IT 資本支出 | B11: % | C11: =PL!D70/itc_26 -> 0.0055687819 | D11: =PL!E70/itc_27 -> 0.005731951 | E11: =PL!F70/itc_28 -> 0.0054352003 | F11: =PL!G70/itc_29 -> 0.0063871517 | G11: markets/network 的 AI IT 資本支出
A12: 核對：兩者合計最大值 < 100%（1＝通過） | C12: =IF(MAX(C8:F8)<1,1,0) -> 1
A14: 讀法：Coherent 有效份額含賣給其他模組廠的雷射與光元件（與中際旭創的採購成本部分重疊），所以是「有效」份額而非出貨份額；份額相對值與 CPO 份額是 Assumed，是最需要每季檢查的輸入。

Sheet PL
A1: PL — Coherent 損益（US$B；non-GAAP）。FY2025A、FY2026A（錨點）為實績，FY2027 起為模型。FY(t)＝t−1 年 7 月～t 年 6 月。三情境各一個完整推導區塊（本頁下方），頂端為摘要。FY2027 三情境相同（顆數係數從 CY2028 開始）
A2: 灰底＝FY2030–FY2032 收斂法，非驅動因子推導（上游市場層只到 2029）：營收年增由 FY2029 線性收斂到 fade_g（A＝tp_g＋2pt、B＝tp_g、C＝tp_g−2pt），淨利率由 FY2029 線性收斂到 fade_m（In 頁 K 節），FY2032 達到；股數依 sh_g
A3: 情境／項目 | B3: 單位 | C3: FY2025A | D3: FY2026A（錨點） | E3: FY2027 | F3: FY2028 | G3: FY2029 | H3: FY2030（收斂） | I3: FY2031（收斂） | J3: FY2032（收斂） | K3: 說明
A4: 情境 A
A5: 營收 | B5: US$B | C5: =C75 -> 5.8101 | D5: =D75 -> 7.1182 | E5: =E75 -> 10.946573 | F5: =F75 -> 14.443985 | G5: =G75 -> 17.418544 | H5: =H75 -> 20.158337 | I5: =I75 -> 22.348457 | J5: =J75 -> 23.689365
A6: 營收年增 | B6: % | D6: =D76 -> 0.22514242 | E6: =E76 -> 0.53782885 | F6: =F76 -> 0.31949831 | G6: =G76 -> 0.20593759 | H6: =H76 -> 0.15729172 | I6: =I76 -> 0.10864586 | J6: =J76 -> 0.06
A7: 資料中心 | B7: US$B | C7: =C72 -> 2.2754201 | D7: =D72 -> 3.196083 | E7: =E72 -> 6.6959129 | F7: =F72 -> 9.8061961 | G7: =G72 -> 12.46506
A8: 通訊 | B8: US$B | C8: =C73 -> 1.4797799 | D8: =D73 -> 2.078517 | E8: =E73 -> 2.4942204 | F8: =F73 -> 2.7935268 | G8: =G73 -> 3.017009
A9: 工業 | B9: US$B | C9: =C74 -> 2.0549 | D9: =D74 -> 1.8436 | E9: =E74 -> 1.75644 | F9: =F74 -> 1.844262 | G9: =G74 -> 1.9364751
A10: 資料中心 ÷ 營收 | B10: % | C10: =C77 -> 0.39163183 | D10: =D77 -> 0.44900157 | E10: =E77 -> 0.61169032 | F10: =F77 -> 0.6789121 | G10: =G77 -> 0.71562009
A11: 毛利率 | B11: % | C11: =C79 -> 0.37904683 | D11: =D79 -> 0.39427102 | E11: =E79 -> 0.41 | F11: =F79 -> 0.42 | G11: =G79 -> 0.42
A12: 營業利益率 | B12: % | C12: =C84 -> 0.1784823 | D12: =D84 -> 0.20467253 | E12: =E84 -> 0.24013009 | F12: =F84 -> 0.26236783 | G12: =G84 -> 0.27037687
A13: 歸屬淨利 | B13: US$B | C13: =C87 -> 0.6926 | D13: =D87 -> 1.0966 | E13: =E87 -> 2.0765673 | F13: =F87 -> 3.0170059 | G13: =G87 -> 3.7621529 | H13: =H87 -> 4.3539084 | I13: =I87 -> 4.8269426 | J13: =J87 -> 5.1165591
A14: EPS | B14: US$ | C14: =C91 -> 3.53 | D14: =D91 -> 5.6120778 | E14: =E91 -> 10.168186 | F14: =F91 -> 14.626899 | G14: =G91 -> 18.058895 | H14: =H91 -> 20.692485 | I14: =I91 -> 22.713503 | J14: =J91 -> 23.837933
A15: EPS 年增 | B15: % | D15: =D92 -> 0.58982374 | E15: =E92 -> 0.81183985 | F15: =F92 -> 0.43849639 | G15: =G92 -> 0.23463591 | H15: =H92 -> 0.14583339 | I15: =I92 -> 0.097669171 | J15: =J92 -> 0.04950495
A17: 情境 B
A18: 營收 | B18: US$B | C18: =C110 -> 5.8101 | D18: =D110 -> 7.1182 | E18: =E110 -> 10.946573 | F18: =F110 -> 13.451777 | G18: =G110 -> 15.257594 | H18: =H110 -> 16.82652 | I18: =I110 -> 18.028178 | J18: =J110 -> 18.749306
A19: 營收年增 | B19: % | D19: =D111 -> 0.22514242 | E19: =E111 -> 0.53782885 | F19: =F111 -> 0.22885732 | G19: =G111 -> 0.13424376 | H19: =H111 -> 0.10282917 | I19: =I111 -> 0.071414585 | J19: =J111 -> 0.04
A20: 資料中心 | B20: US$B | C20: =C107 -> 2.2754201 | D20: =D107 -> 3.196083 | E20: =E107 -> 6.6959129 | F20: =F107 -> 8.8139879 | G20: =G107 -> 10.30411
A21: 通訊 | B21: US$B | C21: =C108 -> 1.4797799 | D21: =D108 -> 2.078517 | E21: =E108 -> 2.4942204 | F21: =F108 -> 2.7935268 | G21: =G108 -> 3.017009
A22: 工業 | B22: US$B | C22: =C109 -> 2.0549 | D22: =D109 -> 1.8436 | E22: =E109 -> 1.75644 | F22: =F109 -> 1.844262 | G22: =G109 -> 1.9364751
A23: 資料中心 ÷ 營收 | B23: % | C23: =C112 -> 0.39163183 | D23: =D112 -> 0.44900157 | E23: =E112 -> 0.61169032 | F23: =F112 -> 0.65522853 | G23: =G112 -> 0.67534304
A24: 毛利率 | B24: % | C24: =C114 -> 0.37904683 | D24: =D114 -> 0.39427102 | E24: =E114 -> 0.41 | F24: =F114 -> 0.42 | G24: =G114 -> 0.42
A25: 營業利益率 | B25: % | C25: =C119 -> 0.1784823 | D25: =D119 -> 0.20467253 | E25: =E119 -> 0.24013009 | F25: =F119 -> 0.25954258 | G25: =G119 -> 0.2651929
A26: 歸屬淨利 | B26: US$B | C26: =C122 -> 0.6926 | D26: =D122 -> 1.0966 | E26: =E122 -> 2.0765673 | F26: =F122 -> 2.7753602 | G26: =G122 -> 3.2248264 | H26: =H122 -> 3.4378849 | I26: =I122 -> 3.5563863 | J26: =J122 -> 3.5665474
A27: EPS | B27: US$ | C27: =C126 -> 3.53 | D27: =D126 -> 5.6120778 | E27: =E126 -> 10.168186 | F27: =F126 -> 13.455364 | G27: =G126 -> 15.479648 | H27: =H126 -> 16.338971 | I27: =I126 -> 16.734814 | J27: =J126 -> 16.616464
A28: EPS 年增 | B28: % | D28: =D127 -> 0.58982374 | E28: =E127 -> 0.81183985 | F28: =F127 -> 0.32328067 | G28: =G127 -> 0.15044435 | H28: =H127 -> 0.055513067 | I28: =I127 -> 0.024226985 | J28: =J127 -> -0.0070721358
A30: 情境 C
A31: 營收 | B31: US$B | C31: =C145 -> 5.8101 | D31: =D145 -> 7.1182 | E31: =E145 -> 10.946573 | F31: =F145 -> 12.459569 | G31: =G145 -> 12.43252 | H31: =H145 -> 12.497411 | I31: =I145 -> 12.654999 | J31: =J145 -> 12.908099
A32: 營收年增 | B32: % | D32: =D146 -> 0.22514242 | E32: =E146 -> 0.53782885 | F32: =F146 -> 0.13821634 | G32: =G146 -> -0.0021708859 | H32: =H146 -> 0.0052194094 | I32: =I146 -> 0.012609705 | J32: =J146 -> 0.02
A33: 資料中心 | B33: US$B | C33: =C142 -> 2.2754201 | D33: =D142 -> 3.196083 | E33: =E142 -> 6.6959129 | F33: =F142 -> 7.8217797 | G33: =G142 -> 7.4790362
A34: 通訊 | B34: US$B | C34: =C143 -> 1.4797799 | D34: =D143 -> 2.078517 | E34: =E143 -> 2.4942204 | F34: =F143 -> 2.7935268 | G34: =G143 -> 3.017009
A35: 工業 | B35: US$B | C35: =C144 -> 2.0549 | D35: =D144 -> 1.8436 | E35: =E144 -> 1.75644 | F35: =F144 -> 1.844262 | G35: =G144 -> 1.9364751
A36: 資料中心 ÷ 營收 | B36: % | C36: =C147 -> 0.39163183 | D36: =D147 -> 0.44900157 | E36: =E147 -> 0.61169032 | F36: =F147 -> 0.62777292 | G36: =G147 -> 0.6015704
A37: 毛利率 | B37: % | C37: =C149 -> 0.37904683 | D37: =D149 -> 0.39427102 | E37: =E149 -> 0.41 | F37: =F149 -> 0.42 | G37: =G149 -> 0.42
A38: 營業利益率 | B38: % | C38: =C154 -> 0.1784823 | D38: =D154 -> 0.20467253 | E38: =E154 -> 0.24013009 | F38: =F154 -> 0.25626737 | G38: =G154 -> 0.25591115
A39: 歸屬淨利 | B39: US$B | C39: =C157 -> 0.6926 | D39: =D157 -> 1.0966 | E39: =E157 -> 2.0765673 | F39: =F157 -> 2.5337145 | G39: =G157 -> 2.5245127 | H39: =H157 -> 2.3685099 | I39: =I157 -> 2.2270635 | J39: =J157 -> 2.0968659
A40: EPS | B40: US$ | C40: =C161 -> 3.53 | D40: =D161 -> 5.6120778 | E40: =E161 -> 10.168186 | F40: =F161 -> 12.283829 | G40: =G161 -> 12.118037 | H40: =H161 -> 11.256634 | I40: =I161 -> 10.479597 | J40: =J161 -> 9.7692511
A41: EPS 年增 | B41: % | D41: =D162 -> 0.58982374 | E41: =E162 -> 0.81183985 | F41: =F162 -> 0.20806496 | G41: =G162 -> -0.013496788 | H41: =H162 -> -0.071084374 | I41: =I162 -> -0.069029267 | J41: =J162 -> -0.067783701
A43: 核對（應為 0）：FY2026 模型與實績（校準恆等式）
A44: 情境 A：營收差（US$B） | D44: =D75-a26_rev_in -> 0
A45: 情境 A：營業利益差（US$B；公司揭露 1.4569） | D45: =D83-1.4569 -> 0
A46: 情境 A：EPS 差（公司揭露 5.61） | D46: =D91-a26_eps_in -> 0.0020777892
A47: 情境 A：CY2026 資料中心 − 可插拔市場 × 有效份額 | D47: =D70-D63*D67 -> 0
A60: 情境 A：基準（顆數係數 1.0）
A61: 項目 | B61: 單位 | C61: FY2025A | D61: FY2026A（錨點） | E61: FY2027 | F61: FY2028 | G61: FY2029 | H61: FY2030（收斂） | I61: FY2031（收斂） | J61: FY2032（收斂） | K61: 說明
A62: A. 日曆年 AI 光學（本節 D–G 欄＝CY2026–CY2029；D 欄＝CY2026 校準年）
A63: AI 可插拔光模組市場 × 情境顆數係數（日曆年） | B63: US$B | D63: =mpl_26*1 -> 29.753262 | E63: =mpl_27*1*1 -> 54.688309 | F63: =mpl_28*um28_A*1 -> 61.21325 | G63: =mpl_29*um29_A*1 -> 78.80848 | K63: 本節欄位為日曆年
A64: AI CPO 光學市場 × 情境顆數係數（日曆年） | B64: US$B | D64: =mcp_26*1 -> 0.300538 | E64: =mcp_27*1 -> 1.691391 | F64: =mcp_28*um28_A -> 3.22175 | G64: =mcp_29*um29_A -> 5.87368
A65: Coherent 可插拔有效份額（CY2026 校準）＝ CY2026 資料中心 ÷ 可插拔市場 | B65: % | D65: =dc_cy26/D63 -> 0.14633958 | K65: Derived：CY2026 CPO 營收視為 0；含賣給其他模組廠的雷射元件，屬「有效」份額
A66: 份額相對值（÷ CY2026） | B66: x | D66: =1 -> 1 | E66: =rel_27 -> 1.1 | F66: =rel_28 -> 1.15 | G66: =rel_29 -> 1.15
A67: 可插拔有效份額（日曆年） | B67: % | D67: =$D$65*D66 -> 0.14633958 | E67: =$D$65*E66 -> 0.16097353 | F67: =$D$65*F66 -> 0.16829051 | G67: =$D$65*G66 -> 0.16829051
A68: 單價係數（相對網通模型） | B68: x | D68: =1 -> 1 | E68: =pxr_27 -> 1 | F68: =pxr_28 -> 1 | G68: =pxr_29 -> 1
A69: Coherent 占 CPO 光學金額 | B69: % | D69: =0 -> 0 | E69: =cpo_27 -> 0.1 | F69: =cpo_28 -> 0.15 | G69: =cpo_29 -> 0.2
A70: 資料中心營收（日曆年） | B70: US$B | D70: =dc_cy26 -> 4.3540798 | E70: =E63*E67*E68+E64*E69 -> 8.9725095 | F70: =F63*F67*F68+F64*F69 -> 10.784872 | G70: =G63*G67*G68+G64*G69 -> 14.437456
A71: B. 會計年度營收（本節起 C–G 欄＝FY2025–FY2029）
A72: 資料中心 | B72: US$B | C72: =a25_dc -> 2.2754201 | D72: =a26_dc -> 3.196083 | E72: =h1_27+hw*E70 -> 6.6959129 | F72: =(1-hw)*E70+hw*F70 -> 9.8061961 | G72: =(1-hw)*F70+hw*G70 -> 12.46506 | K72: FY2027＝CY2026 下半年（Q 頁）＋ hw × CY2027；FY2028＝（1 − hw）× CY2027 ＋ hw × CY2028
A73: 通訊 | B73: US$B | C73: =a25_com -> 1.4797799 | D73: =a26_com -> 2.078517 | E73: =D73*(1+g_com_27) -> 2.4942204 | F73: =E73*(1+g_com_28) -> 2.7935268 | G73: =F73*(1+g_com_29) -> 3.017009
A74: 工業（FY2027 起排除已出售事業） | B74: US$B | C74: =a25_ind -> 2.0549 | D74: =a26_ind -> 1.8436 | E74: =ind_run*(1+g_ind_27) -> 1.75644 | F74: =E74*(1+g_ind_28) -> 1.844262 | G74: =F74*(1+g_ind_29) -> 1.9364751
A75: 營收 | B75: US$B | C75: =C72+C73+C74 -> 5.8101 | D75: =D72+D73+D74 -> 7.1182 | E75: =E72+E73+E74 -> 10.946573 | F75: =F72+F73+F74 -> 14.443985 | G75: =G72+G73+G74 -> 17.418544 | H75: =G75*(1+H76) -> 20.158337 | I75: =H75*(1+I76) -> 22.348457 | J75: =I75*(1+J76) -> 23.689365
A76: 營收年增 | B76: % | D76: =D75/C75-1 -> 0.22514242 | E76: =E75/D75-1 -> 0.53782885 | F76: =F75/E75-1 -> 0.31949831 | G76: =G75/F75-1 -> 0.20593759 | H76: =$G76+(fade_gA-$G76)*1/3 -> 0.15729172 | I76: =$G76+(fade_gA-$G76)*2/3 -> 0.10864586 | J76: =$G76+(fade_gA-$G76)*3/3 -> 0.06
A77: 資料中心 ÷ 營收 | B77: % | C77: =C72/C75 -> 0.39163183 | D77: =D72/D75 -> 0.44900157 | E77: =E72/E75 -> 0.61169032 | F77: =F72/F75 -> 0.6789121 | G77: =G72/G75 -> 0.71562009
A78: C. 損益（non-GAAP）
A79: 毛利率 | B79: % | C79: =a25_gp/a25_rev -> 0.37904683 | D79: =a26_gp/a26_rev -> 0.39427102 | E79: =gm_27 -> 0.41 | F79: =gm_28 -> 0.42 | G79: =gm_29 -> 0.42 | K79: FY2027 起為輸入路徑（六吋磷化銦降本、1.6T 上推 vs 光模組占比上升下壓）
A80: 毛利 | B80: US$B | C80: =C75*C79 -> 2.2023 | D80: =D75*D79 -> 2.8065 | E80: =E75*E79 -> 4.4880951 | F80: =F75*F79 -> 6.0664737 | G80: =G75*G79 -> 7.3157886
A81: 營業費用（基準路徑） | B81: US$B | C81: =a25_opx -> 1.1653 | D81: =a26_opx -> 1.3496 | E81: =D81*(1+MAX(0,phi*E76)) -> 1.8594934 | F81: =E81*(1+MAX(0,phi*F76)) -> 2.2768367 | G81: =F81*(1+MAX(0,phi*G76)) -> 2.6062172
A82: 營業費用 | B82: US$B | C82: =C81 -> 1.1653 | D82: =D81 -> 1.3496 | E82: =E81+0*E75 -> 1.8594934 | F82: =F81+0*F75 -> 2.2768367 | G82: =G81+0*G75 -> 2.6062172
A83: 營業利益 | B83: US$B | C83: =C80-C82 -> 1.037 | D83: =D80-D82 -> 1.4569 | E83: =E80-E82 -> 2.6286016 | F83: =F80-F82 -> 3.7896369 | G83: =G80-G82 -> 4.7095715
A84: 營業利益率 | B84: % | C84: =C83/C75 -> 0.1784823 | D84: =D83/D75 -> 0.20467253 | E84: =E83/E75 -> 0.24013009 | F84: =F83/F75 -> 0.26236783 | G84: =G83/G75 -> 0.27037687
A85: 利息與其他淨支出 | B85: US$B | C85: =a25_int -> 0.1673 | D85: =a26_int -> 0.1181 | E85: =int_f -> 0.08 | F85: =int_f -> 0.08 | G85: =int_f -> 0.08
A86: 稅前利益 | B86: US$B | C86: =C83-C85 -> 0.8697 | D86: =D83-D85 -> 1.3388 | E86: =E83-E85 -> 2.5486016 | F86: =F83-F85 -> 3.7096369 | G86: =G83-G85 -> 4.6295715
A87: 歸屬 Coherent 淨利 | B87: US$B | C87: =a25_ni -> 0.6926 | D87: =a26_ni -> 1.0966 | E87: =E86*(1-tx)+nci -> 2.0765673 | F87: =F86*(1-tx)+nci -> 3.0170059 | G87: =G86*(1-tx)+nci -> 3.7621529 | H87: =H75*H88 -> 4.3539084 | I87: =I75*I88 -> 4.8269426 | J87: =J75*J88 -> 5.1165591
A88: 淨利率 | B88: % | C88: =C87/C75 -> 0.11920621 | D88: =D87/D75 -> 0.1540558 | E88: =E87/E75 -> 0.18970022 | F88: =F87/F75 -> 0.20887629 | G88: =G87/G75 -> 0.21598549 | H88: =$G88+(fade_mA-$G88)*1/3 -> 0.21598549 | I88: =$G88+(fade_mA-$G88)*2/3 -> 0.21598549 | J88: =$G88+(fade_mA-$G88)*3/3 -> 0.21598549
A89: 優先股股利 | B89: US$B | C89: =a25_pref -> 0.130624 | D89: =0 -> 0 | E89: =0 -> 0 | F89: =0 -> 0 | G89: =0 -> 0
A90: 稀釋股數 | B90: 十億股 | C90: =a25_sh -> 0.1592 | D90: =a26_sh -> 0.1954 | E90: =sh_q4*(1+sh_g) -> 0.204222 | F90: =E90*(1+sh_g) -> 0.20626422 | G90: =F90*(1+sh_g) -> 0.20832686 | H90: =G90*(1+sh_g) -> 0.21041013 | I90: =H90*(1+sh_g) -> 0.21251423 | J90: =I90*(1+sh_g) -> 0.21463937
A91: EPS | B91: US$ | C91: =(C87-C89)/C90 -> 3.53 | D91: =(D87-D89)/D90 -> 5.6120778 | E91: =(E87-E89)/E90 -> 10.168186 | F91: =(F87-F89)/F90 -> 14.626899 | G91: =(G87-G89)/G90 -> 18.058895 | H91: =(H87-H89)/H90 -> 20.692485 | I91: =(I87-I89)/I90 -> 22.713503 | J91: =(J87-J89)/J90 -> 23.837933
A92: EPS 年增 | B92: % | D92: =D91/C91-1 -> 0.58982374 | E92: =E91/D91-1 -> 0.81183985 | F92: =F91/E91-1 -> 0.43849639 | G92: =G91/F91-1 -> 0.23463591 | H92: =H91/G91-1 -> 0.14583339 | I92: =I91/H91-1 -> 0.097669171 | J92: =J91/I91-1 -> 0.04950495
A95: 情境 B：CY2028 顆數 ×0.8、CY2029 ×0.85
A96: 項目 | B96: 單位 | C96: FY2025A | D96: FY2026A（錨點） | E96: FY2027 | F96: FY2028 | G96: FY2029 | H96: FY2030（收斂） | I96: FY2031（收斂） | J96: FY2032（收斂） | K96: 說明
A97: A. 日曆年 AI 光學（本節 D–G 欄＝CY2026–CY2029；D 欄＝CY2026 校準年）
A98: AI 可插拔光模組市場 × 情境顆數係數（日曆年） | B98: US$B | D98: =mpl_26*1 -> 29.753262 | E98: =mpl_27*1*1 -> 54.688309 | F98: =mpl_28*um28_B*1 -> 48.9706 | G98: =mpl_29*um29_B*1 -> 66.987208 | K98: 本節欄位為日曆年
A99: AI CPO 光學市場 × 情境顆數係數（日曆年） | B99: US$B | D99: =mcp_26*1 -> 0.300538 | E99: =mcp_27*1 -> 1.691391 | F99: =mcp_28*um28_B -> 2.5774 | G99: =mcp_29*um29_B -> 4.992628
A100: Coherent 可插拔有效份額（CY2026 校準）＝ CY2026 資料中心 ÷ 可插拔市場 | B100: % | D100: =dc_cy26/D98 -> 0.14633958 | K100: Derived：CY2026 CPO 營收視為 0；含賣給其他模組廠的雷射元件，屬「有效」份額
A101: 份額相對值（÷ CY2026） | B101: x | D101: =1 -> 1 | E101: =rel_27 -> 1.1 | F101: =rel_28 -> 1.15 | G101: =rel_29 -> 1.15
A102: 可插拔有效份額（日曆年） | B102: % | D102: =$D$100*D101 -> 0.14633958 | E102: =$D$100*E101 -> 0.16097353 | F102: =$D$100*F101 -> 0.16829051 | G102: =$D$100*G101 -> 0.16829051
A103: 單價係數（相對網通模型） | B103: x | D103: =1 -> 1 | E103: =pxr_27 -> 1 | F103: =pxr_28 -> 1 | G103: =pxr_29 -> 1
A104: Coherent 占 CPO 光學金額 | B104: % | D104: =0 -> 0 | E104: =cpo_27 -> 0.1 | F104: =cpo_28 -> 0.15 | G104: =cpo_29 -> 0.2
A105: 資料中心營收（日曆年） | B105: US$B | D105: =dc_cy26 -> 4.3540798 | E105: =E98*E102*E103+E99*E104 -> 8.9725095 | F105: =F98*F102*F103+F99*F104 -> 8.6278974 | G105: =G98*G102*G103+G99*G104 -> 12.271837
A106: B. 會計年度營收（本節起 C–G 欄＝FY2025–FY2029）
A107: 資料中心 | B107: US$B | C107: =a25_dc -> 2.2754201 | D107: =a26_dc -> 3.196083 | E107: =h1_27+hw*E105 -> 6.6959129 | F107: =(1-hw)*E105+hw*F105 -> 8.8139879 | G107: =(1-hw)*F105+hw*G105 -> 10.30411 | K107: FY2027＝CY2026 下半年（Q 頁）＋ hw × CY2027；FY2028＝（1 − hw）× CY2027 ＋ hw × CY2028
A108: 通訊 | B108: US$B | C108: =a25_com -> 1.4797799 | D108: =a26_com -> 2.078517 | E108: =D108*(1+g_com_27) -> 2.4942204 | F108: =E108*(1+g_com_28) -> 2.7935268 | G108: =F108*(1+g_com_29) -> 3.017009
A109: 工業（FY2027 起排除已出售事業） | B109: US$B | C109: =a25_ind -> 2.0549 | D109: =a26_ind -> 1.8436 | E109: =ind_run*(1+g_ind_27) -> 1.75644 | F109: =E109*(1+g_ind_28) -> 1.844262 | G109: =F109*(1+g_ind_29) -> 1.9364751
A110: 營收 | B110: US$B | C110: =C107+C108+C109 -> 5.8101 | D110: =D107+D108+D109 -> 7.1182 | E110: =E107+E108+E109 -> 10.946573 | F110: =F107+F108+F109 -> 13.451777 | G110: =G107+G108+G109 -> 15.257594 | H110: =G110*(1+H111) -> 16.82652 | I110: =H110*(1+I111) -> 18.028178 | J110: =I110*(1+J111) -> 18.749306
A111: 營收年增 | B111: % | D111: =D110/C110-1 -> 0.22514242 | E111: =E110/D110-1 -> 0.53782885 | F111: =F110/E110-1 -> 0.22885732 | G111: =G110/F110-1 -> 0.13424376 | H111: =$G111+(fade_gB-$G111)*1/3 -> 0.10282917 | I111: =$G111+(fade_gB-$G111)*2/3 -> 0.071414585 | J111: =$G111+(fade_gB-$G111)*3/3 -> 0.04
A112: 資料中心 ÷ 營收 | B112: % | C112: =C107/C110 -> 0.39163183 | D112: =D107/D110 -> 0.44900157 | E112: =E107/E110 -> 0.61169032 | F112: =F107/F110 -> 0.65522853 | G112: =G107/G110 -> 0.67534304
A113: C. 損益（non-GAAP）
A114: 毛利率 | B114: % | C114: =a25_gp/a25_rev -> 0.37904683 | D114: =a26_gp/a26_rev -> 0.39427102 | E114: =gm_27 -> 0.41 | F114: =gm_28 -> 0.42 | G114: =gm_29 -> 0.42 | K114: FY2027 起為輸入路徑（六吋磷化銦降本、1.6T 上推 vs 光模組占比上升下壓）
A115: 毛利 | B115: US$B | C115: =C110*C114 -> 2.2023 | D115: =D110*D114 -> 2.8065 | E115: =E110*E114 -> 4.4880951 | F115: =F110*F114 -> 5.6497462 | G115: =G110*G114 -> 6.4081894
A116: 營業費用（基準路徑） | B116: US$B | C116: =a25_opx -> 1.1653 | D116: =a26_opx -> 1.3496 | E116: =D116*(1+MAX(0,phi*E111)) -> 1.8594934 | F116: =E116*(1+MAX(0,phi*F111)) -> 2.1584373 | G116: =F116*(1+MAX(0,phi*G111)) -> 2.3619839
A117: 營業費用 | B117: US$B | C117: =C116 -> 1.1653 | D117: =D116 -> 1.3496 | E117: =E116+0*E110 -> 1.8594934 | F117: =F116+0*F110 -> 2.1584373 | G117: =G116+0*G110 -> 2.3619839
...

Sheet Val
A1: Val — P/E 估值（美元；non-GAAP EPS）。目標價＝DCF 與 Comparable 加權（第 0 節）；舊法規則值情境加權保留參考；另列「現價 ÷ FY2027、FY2028 EPS（模型）」、市場隱含 EPS 與十年 P/E 規則值。十年 P/E 為 GAAP 年底 P/E（II-VI 2022 年改名 Coherent，同一法人）；GAAP 虧損年度不列入
A2: 循環位置：Coherent 不是設備股，不套設備市場見頂年；以本模型營收最高的會計年度為見頂年（比照中際旭創、Arista）。營收到 FY2029 仍在增加時，見頂年未知，判為中段
A4: 0. 目標價
A5: 0.1 DCF（股東權益現金流，FY2027–FY2032 明確期＋FY2032 後永續）
A6: 項目 | B6: A（順利） | C6: B（平平） | D6: C（不如預期） | E6: 說明
A7: 情境 EPS（FY2027–FY2032） | E7: PL 頁各情境；FY2030 起為收斂法（PL 頁灰底）
A8: FY2027 | B8: =PL!E14 -> 10.168186 | C8: =PL!E27 -> 10.168186 | D8: =PL!E40 -> 10.168186
A9: FY2028 | B9: =PL!F14 -> 14.626899 | C9: =PL!F27 -> 13.455364 | D9: =PL!F40 -> 12.283829
A10: FY2029 | B10: =PL!G14 -> 18.058895 | C10: =PL!G27 -> 15.479648 | D10: =PL!G40 -> 12.118037
A11: FY2030 | B11: =PL!H14 -> 20.692485 | C11: =PL!H27 -> 16.338971 | D11: =PL!H40 -> 11.256634
A12: FY2031 | B12: =PL!I14 -> 22.713503 | C12: =PL!I27 -> 16.734814 | D12: =PL!I40 -> 10.479597
A13: FY2032 | B13: =PL!J14 -> 23.837933 | C13: =PL!J27 -> 16.616464 | D13: =PL!J40 -> 9.7692511
A14: 股東現金流＝EPS ×（1 − tp_g ÷ tp_roe）
A15: 再投資率（tp_g ÷ tp_roe，上限 0.8） | B15: =IF(tp_roe<=tp_g,0.8,MIN(tp_g/tp_roe,0.8)) -> 0.2 | E15: ROE＝In 頁 tp_roe；tp_roe ≤ tp_g 時取上限 0.8
A16: FY2027 | B16: =B8*(1-$B$15) -> 8.1345489 | C16: =C8*(1-$B$15) -> 8.1345489 | D16: =D8*(1-$B$15) -> 8.1345489
A17: FY2028 | B17: =B9*(1-$B$15) -> 11.701519 | C17: =C9*(1-$B$15) -> 10.764291 | D17: =D9*(1-$B$15) -> 9.8270636
A18: FY2029 | B18: =B10*(1-$B$15) -> 14.447116 | C18: =C10*(1-$B$15) -> 12.383718 | D18: =D10*(1-$B$15) -> 9.6944298
A19: FY2030 | B19: =B11*(1-$B$15) -> 16.553988 | C19: =C11*(1-$B$15) -> 13.071176 | D19: =D11*(1-$B$15) -> 9.0053073
A20: FY2031 | B20: =B12*(1-$B$15) -> 18.170802 | C20: =C12*(1-$B$15) -> 13.387852 | D20: =D12*(1-$B$15) -> 8.3836775
A21: FY2032 | B21: =B13*(1-$B$15) -> 19.070347 | C21: =C13*(1-$B$15) -> 13.293171 | D21: =D13*(1-$B$15) -> 7.8154008
A22: DCF 情境每股價值（折現率 tp_r） | B22: =SUMPRODUCT(B16:B21,1/(1+tp_r)^{1;2;3;4;5;6})+B21*(1+tp_g)/(tp_r-tp_g)/(1+tp_r)^6 -> 247.86237 | C22: =SUMPRODUCT(C16:C21,1/(1+tp_r)^{1;2;3;4;5;6})+C21*(1+tp_g)/(tp_r-tp_g)/(1+tp_r)^6 -> 180.4027 | D22: =SUMPRODUCT(D16:D21,1/(1+tp_r)^{1;2;3;4;5;6})+D21*(1+tp_g)/(tp_r-tp_g)/(1+tp_r)^6 -> 115.03565 | E22: Σ 明確期現金流 ÷ (1＋r)^t ＋ 永續價值 ÷ (1＋r)^6；永續價值＝FY2032 現金流 ×(1＋g)÷(r−g)；基準日 2026 年底，t＝1 對 FY2027
A23: DCF 情境價值推到 12 個月後（×(1＋tp_r)） | B23: =B22*(1+tp_r) -> 272.64861 | C23: =C22*(1+tp_r) -> 198.44297 | D23: =D22*(1+tp_r) -> 126.53922
A24: DCF 目標價（情境加權） | B24: =tp_wA*B23+tp_wB*C23+tp_wC*D23 -> 206.32391 | E24: Σ 權重 × 情境價值 ×(1＋r)；權重見 In 頁
A26: 0.2 Comparable（市場主流同業前瞻 P/E）
A27: 同業與前瞻 P/E | B27: 代號 | C27: 前瞻 12 月 P/E | D27: 日期 | E27: 來源 | F27: 標記
A28: Lumentum | B28: LITE | C28: 34.71 | D28: 2026-10-23 | E28: stockanalysis forward PE（分析師共識；價格日期如左） | F28: Interested-party
A29: Fabrinet | B29: FN | C29: 17.27 | D29: 2026-10-23 | E29: stockanalysis forward PE（分析師共識；價格日期如左） | F29: Interested-party
A30: Applied Optoelectronics | B30: AAOI | C30: 29.34 | D30: 2026-10-23 | E30: stockanalysis forward PE（分析師共識；價格日期如左） | F30: Interested-party
A31: Ciena | B31: CIEN | C31: 30.77 | D31: 2026-10-23 | E31: stockanalysis forward PE（分析師共識；價格日期如左） | F31: Interested-party
A32: Corning | B32: GLW | C32: 32.89 | D32: 2026-10-23 | E32: stockanalysis forward PE（分析師共識；價格日期如左） | F32: Interested-party
A33: 同業前瞻 P/E 中位數 | B33: =MEDIAN(C28:C32) -> 30.77 | E33: 美股光通訊同業（不放 A 股；中際旭創、新易盛另見各自模型）
A34: 12 個月後的前瞻 EPS（情境加權） | B34: =tp_wA*(8/12*B9+4/12*B10)+tp_wB*(8/12*C9+4/12*C10)+tp_wC*(8/12*D9+4/12*D10) -> 14.242045 | E34: 約 2027-10 時的未來 12 月（2027-11～2028-10）≈ 8／12 × FY2028＋4／12 × FY2029（會計年度 6 月底結束）
A35: Comparable 目標價 | B35: =B33*B34 -> 438.22773 | E35: 同業中位數 × 前瞻 EPS
A37: 0.3 結論
A38: 項目 | B38: 數值 | E38: 說明
A39: 目標價（DCF 與 Comparable 加權） | B39: =tp_w_dcf*B24+(1-tp_w_dcf)*B35 -> 322.27582 | E39: tp_w_dcf × DCF＋（1 − tp_w_dcf）× Comparable；tp_w_dcf 見 In 頁
A40: Comparable 目標價（市場主流同業法） | B40: =B35 -> 438.22773
A41: 市場共識目標價 | B41: =cons_tp -> 394.79 | E41: stockanalysis：25 位分析師平均 394.79（2026-10-24 擷取）
A42: 上檔空間：加權目標價 | B42: =B39/px-1 -> 0.54073634 | E42: 現價＝In 頁 px
A43: 上檔空間：Comparable 目標價 | B43: =B40/px-1 -> 1.0950793
A44: 與市場共識目標價的差距：EPS 因素 | B44: =B34/cons_feps-1 -> 0.089674453 | E44: 本模型前瞻 EPS ÷ 共識前瞻 EPS − 1；共識前瞻 EPS＝In 頁 cons_feps
A45: 與市場共識目標價的差距：倍數因素 | B45: =(cons_tp/cons_feps)/B33-1 -> -0.018335559 | E45: ="共識目標價隱含 "&TEXT(cons_tp/cons_feps,"0.0")&"x，同業中位數 "&TEXT(B33,"0.0")&"x" -> 共識目標價隱含 30.2x，同業中位數 30.8x
A46: 價格帶（DCF 不如預期～順利） | B46: =TEXT(D23,"#,##0.00")&"～"&TEXT(B23,"#,##0.00") -> 126.54～272.65 | E46: C 情境價值～A 情境價值（推到 12 個月後）
A47: 歷史倍數檢查：現價隱含 P/E 的十年分位（A／B／C） | B47: =IF(px/B9>MAX($B$102:$C$111),1,IF(px/B9<MIN($B$102:$C$111),0,PERCENTRANK($B$102:$C$111,px/B9))) -> 0 | C47: =IF(px/C9>MAX($B$102:$C$111),1,IF(px/C9<MIN($B$102:$C$111),0,PERCENTRANK($B$102:$C$111,px/C9))) -> 0 | D47: =IF(px/D9>MAX($B$102:$C$111),1,IF(px/D9<MIN($B$102:$C$111),0,PERCENTRANK($B$102:$C$111,px/D9))) -> 0 | E47: 現價 ÷ 各情境 FY2028 EPS 在 2016–2025 年底 P/E（第 6 節採用來源）的分位；高於十年最大值＝100%；只作檢查，不進目標價
A48: 目標價方法 | B48: DCF：股東現金流＝EPS ×（1 − g／ROE），r＝10%、g＝4%；ROE 需與 non-GAAP EPS 同口徑，本模型無股東權益、算不出，取 0.20（Assumed；再投資率 20%），FY2027–32 明確期＋永續，FY2030 起為收斂法。Comparable：美股光通訊同業（Lumentum、Fabrinet、AAOI、Ciena、Corning）前瞻 P/E 中位數 × 12 個月後前瞻 EPS（non-GAAP）。會計年度 6 月底結束：DCF 的 t＝1 對 FY2027（2026-07～2027-06），比基準日 2026 年底早半年，偏高估。情境對應：顆數情境 A＝順利、B＝平平、C＝不如預期。
A51: 舊法：規則值情境加權（參考）
A52: 項目 | B52: 數值 | E52: 說明
A53: 規則值情境加權價（參考，非目標價） | B53: =tp_wA*D81+tp_wB*D82+tp_wC*D83 -> 319.78946 | E53: 權重 × 各情境隱含價（第 3 節規則值）
A54: 規則值情境加權價 ÷ 現價 − 1（參考） | B54: =B53/px-1 -> 0.52884953 | E54: 現價＝In 頁 px（2026-10-23 收盤）
A55: 情境 A 隱含價（樂觀） | B55: =D81 -> 319.78946 | E55: ="FY2027 EPS "&TEXT(B81,"0.00")&" × "&C75&" 判定倍數 "&TEXT(C81,"0.0")&"x" -> FY2027 EPS 10.17 × 中段 判定倍數 31.5x
A56: 情境 B 隱含價（基準） | B56: =D82 -> 319.78946 | E56: ="FY2027 EPS "&TEXT(B82,"0.00")&" × "&C76&" 判定倍數 "&TEXT(C82,"0.0")&"x" -> FY2027 EPS 10.17 × 中段 判定倍數 31.5x
A57: 情境 C 隱含價（下檔） | B57: =D83 -> 319.78946 | E57: ="FY2027 EPS "&TEXT(B83,"0.00")&" × "&C77&" 判定倍數 "&TEXT(C83,"0.0")&"x" -> FY2027 EPS 10.17 × 中段 判定倍數 31.5x
A58: 情境權重 A／B／C | B58: =tp_wA -> 0.3 | C58: =tp_wB -> 0.5 | D58: =tp_wC -> 0.2 | E58: ="合計 "&TEXT(B58+C58+D58,"0%")&"；In 頁 tp_wA／tp_wB／tp_wC（Assumed，Andy 可改）" -> 合計 100%；In 頁 tp_wA／tp_wB／tp_wC（Assumed，Andy 可改）
A59: 舊法說明 | B59: P/E：各情境 FY2027（2027-06 結束）non-GAAP EPS × 十年（2016–2025 年底）GAAP P/E 依循環位置取分位（營收最高年規則：仍成長＝中段＝中位數；見頂＝25 分位）。偏誤方向為高估：GAAP 倍數套在較高的 non-GAAP EPS 上，且 2025 年 158x 為 GAAP 盈餘壓低的離群值；隱含價約為 2027 年中的價格、未折現。FY2027 EPS 三情境相同（顆數係數從 CY2028 起），且三情境營收最高年都在 FY2027 之後（皆判中段），所以三個隱含價相同；情境差異見第 1、4 節的 FY2028。
A62: 1. 價格與市場隱含倍數
A63: 項目 | B63: A | C63: B | D63: C | E63: 說明
A64: 現價（2026-10-23 收盤） | B64: =px -> 209.17
A65: 現價 ÷ FY2026 EPS（實績） | B65: =px/PL!D14 -> 37.271401 | C65: =px/PL!D27 -> 37.271401 | D65: =px/PL!D40 -> 37.271401
A66: 現價 ÷ FY2027 EPS（模型） | B66: =px/PL!E14 -> 20.571024 | C66: =px/PL!E27 -> 20.571024 | D66: =px/PL!E40 -> 20.571024 | E66: FY2027 三情境相同（顆數係數從 CY2028 開始）
A67: 現價 ÷ FY2028 EPS（模型） | B67: =px/PL!F14 -> 14.300365 | C67: =px/PL!F27 -> 15.545473 | D67: =px/PL!F40 -> 17.028077
A68: 現價 ÷ FY2029 EPS（模型） | B68: =px/PL!G14 -> 11.582658 | C68: =px/PL!G27 -> 13.512581 | D68: =px/PL!G40 -> 17.261046
A69: 現價 ÷ 共識未來 12 月 EPS（9/12 × FY2027＋3/12 × FY2028） | B69: =px/(cons_eps27*9/12+cons_eps28*3/12) -> 21.409417
A70: 現價 ÷ 52 週高點 − 1 | B70: =px/px_hi-1 -> -0.52461364
A71: 現價 ÷ FY2027 Q1 EPS 指引中點年化 | B71: =px/(q1_eps*4) -> 26.816667 | E71: 1.95 × 4
A73: 2. 循環位置（本模型營收最高的會計年度）
A74: 情境 | B74: 營收最高年（FY2026–FY2029） | C74: FY2027 判定 | D74: 規則倍數（P/E） | E74: 見頂年是否未知 | F74: 說明
A75: A | B75: =INDEX({2026,2027,2028,2029},MATCH(MAX(PL!D75:G75),PL!D75:G75,0)) -> 2029 | C75: =IF(B75=2029,"中段",IF(2027<B75,"中段",IF(2027=B75,"見頂","谷底"))) -> 中段 | D75: =IF(C75="見頂",pe_peak,IF(C75="谷底",pe_trough,pe_mid)) -> 31.45 | E75: =IF(B75=2029,"是：營收到觀測期末仍在增加","否") -> 是：營收到觀測期末仍在增加 | F75: tools/cycle_position.py excel_rule；營收最高年取代設備市場見頂年
A76: B | B76: =INDEX({2026,2027,2028,2029},MATCH(MAX(PL!D110:G110),PL!D110:G110,0)) -> 2029 | C76: =IF(B76=2029,"中段",IF(2027<B76,"中段",IF(2027=B76,"見頂","谷底"))) -> 中段 | D76: =IF(C76="見頂",pe_peak,IF(C76="谷底",pe_trough,pe_mid)) -> 31.45 | E76: =IF(B76=2029,"是：營收到觀測期末仍在增加","否") -> 是：營收到觀測期末仍在增加 | F76: 同上
A77: C | B77: =INDEX({2026,2027,2028,2029},MATCH(MAX(PL!D145:G145),PL!D145:G145,0)) -> 2028 | C77: =IF(B77=2029,"中段",IF(2027<B77,"中段",IF(2027=B77,"見頂","谷底"))) -> 中段 | D77: =IF(C77="見頂",pe_peak,IF(C77="谷底",pe_trough,pe_mid)) -> 31.45 | E77: =IF(B77=2029,"是：營收到觀測期末仍在增加","否") -> 否 | F77: 同上
A79: 3. 規則值隱含股價（美元；約 FY2027 年底＝2027-06，未折現）＝ FY2027 EPS × 規則倍數
A80: 情境 | B80: FY2027 EPS | C80: 規則倍數 | D80: 隱含股價 | E80: 相對現價 | F80: 現價 ÷ FY2027 EPS
A81: A | B81: =PL!E14 -> 10.168186 | C81: =D75 -> 31.45 | D81: =B81*C81 -> 319.78946 | E81: =D81/px-1 -> 0.52884953 | F81: =px/B81 -> 20.571024
A82: B | B82: =PL!E27 -> 10.168186 | C82: =D76 -> 31.45 | D82: =B82*C82 -> 319.78946 | E82: =D82/px-1 -> 0.52884953 | F82: =px/B82 -> 20.571024
A83: C | B83: =PL!E40 -> 10.168186 | C83: =D77 -> 31.45 | D83: =B83*C83 -> 319.78946 | E83: =D83/px-1 -> 0.52884953 | F83: =px/B83 -> 20.571024
A85: 4. 核心問題：市場隱含的 FY2028 EPS（＝現價 ÷ 假設倍數）與模型的距離
A86: 假設倍數（÷ FY2028 EPS） | B86: 市場隱含 FY2028 EPS | C86: 模型 FY2028 EPS（A） | D86: 隱含 ÷ 模型 A − 1 | E86: 模型 FY2028 EPS（C） | F86: 隱含 ÷ 模型 C − 1
A87: 10 | B87: =px/A87 -> 20.917 | C87: =PL!F14 -> 14.626899 | D87: =B87/C87-1 -> 0.43003653 | E87: =PL!F40 -> 12.283829 | F87: =B87/E87-1 -> 0.70280775
A88: 15 | B88: =px/A88 -> 13.944667 | C88: =PL!F14 -> 14.626899 | D88: =B88/C88-1 -> -0.046642313 | E88: =PL!F40 -> 12.283829 | F88: =B88/E88-1 -> 0.13520517
A89: 20 | B89: =px/A89 -> 10.4585 | C89: =PL!F14 -> 14.626899 | D89: =B89/C89-1 -> -0.28498173 | E89: =PL!F40 -> 12.283829 | F89: =B89/E89-1 -> -0.14859613
A90: =pe_peak -> 27.13 | B90: =px/A90 -> 7.7099152 | C90: =PL!F14 -> 14.626899 | D90: =B90/C90-1 -> -0.47289475 | E90: =PL!F40 -> 12.283829 | F90: =B90/E90-1 -> -0.37235247
A91: 讀法：第四列＝十年 P/E 25 分位（見頂倍數）。現價約等於 15 倍模型 FY2028 EPS（A）；若市場對 FY2028 給見頂倍數，隱含 FY2028 EPS 比模型 A 低四成以上——比 Sens 任何單一不利案例都低，要成立需要份額、單價、毛利率與 AI 市場同時不利。
A93: 本版未做先驗：無 Andy 合理 P/E 對照。
A97: 6. 十年倍數與規則值（2016–2025 年底；見頂年 25 分位、中段中位數、谷底 75 分位）
A98: 規則（Andy 2026-10-13）：合理倍數＝年底 P/E 依循環位置取分位。兩個資料商來源（GAAP 落後 P/E）；GAAP 虧損年度（2019、2022–2024）不列入，有效 5–6 年。GAAP 倍數套在 non-GAAP EPS 上（non-GAAP EPS 高於 GAAP），且 2025 年 158x 為 GAAP 盈餘壓低所致，偏誤方向為高估；前瞻 P/E 歷史待 Bloomberg。
A100: P/E：十年歷史倍數
A101: 年底 | B101: companiesmarketcap（年底 P/E） | C101: macrotrends（12 月底 P/E） | D101: 標記／說明
A102: 2016 | B102: 26.7 | C102: 26.95 | D102: companiesmarketcap（年底 P/E）：Interested-party（資料商；GAAP TTM；2019、2022–2024 為負值不列入）；macrotrends（12 月底 P/E）：Interested-party（資料商；GAAP TTM；2025 年底未列，未找到）
A103: 2017 | B103: 34.3 | C103: 35.57
A104: 2018 | B104: 18.3 | C104: 18.98
A105: 2019
A106: 2020 | B106: 42.2 | C106: 44.68
A107: 2021 | B107: 29.1 | C107: 31.2
A108: 2022
A109: 2023
A110: 2024
A111: 2025 | B111: 158
A112: 25 分位（各來源） | B112: =PERCENTILE(B102:B111,0.25) -> 27.3 | C112: =PERCENTILE(C102:C111,0.25) -> 26.95
A113: 中位數（各來源） | B113: =MEDIAN(B102:B111) -> 31.7 | C113: =MEDIAN(C102:C111) -> 31.2
A114: 75 分位（各來源） | B114: =PERCENTILE(B102:B111,0.75) -> 40.225 | C114: =PERCENTILE(C102:C111,0.75) -> 35.57
A115: 最小（各來源） | B115: =MIN(B102:B111) -> 18.3 | C115: =MIN(C102:C111) -> 18.98
...

Sheet Recon
A1: Recon — 本模型 vs 共識、研調與公司指引。只作事後對照，不為對上數字而調參數。共識來自彙整網站（MarketBeat、Benzinga、TIKR），家數與區間未找到
A3: 項目 | B3: 對照值 | C3: 模型 A | D3: 差距 A | E3: 模型 B | F3: 差距 B | G3: 模型 C | H3: 差距 C | I3: 對照來源 | J3: 說明
A4: A. 共識（校準未使用）
A5: FY2027 營收 vs 共識 | B5: =cons_rev27 -> 10.63 | C5: =PL!E75 -> 10.946573 | D5: =C5/B5-1 -> 0.029781119 | E5: =PL!E110 -> 10.946573 | F5: =E5/B5-1 -> 0.029781119 | G5: =PL!E145 -> 10.946573 | H5: =G5/B5-1 -> 0.029781119 | I5: TIKR（2026-09-30）
A6: FY2027 EPS vs 共識 | B6: =cons_eps27 -> 8.67 | C6: =PL!E91 -> 10.168186 | D6: =C6/B6-1 -> 0.17280117 | E6: =PL!E126 -> 10.168186 | F6: =E6/B6-1 -> 0.17280117 | G6: =PL!E161 -> 10.168186 | H6: =G6/B6-1 -> 0.17280117 | I6: MarketBeat（2026-10-23）
A7: FY2027 EPS vs 共識（四季加總） | B7: =cons_eps27b -> 8.85 | C7: =PL!E91 -> 10.168186 | D7: =C7/B7-1 -> 0.14894759 | E7: =PL!E126 -> 10.168186 | F7: =E7/B7-1 -> 0.14894759 | G7: =PL!E161 -> 10.168186 | H7: =G7/B7-1 -> 0.14894759 | I7: Benzinga 各季共識
A8: FY2028 營收 vs 共識 | B8: =cons_rev28 -> 14.76 | C8: =PL!F75 -> 14.443985 | D8: =C8/B8-1 -> -0.021410232 | E8: =PL!F110 -> 13.451777 | F8: =E8/B8-1 -> -0.08863301 | G8: =PL!F145 -> 12.459569 | H8: =G8/B8-1 -> -0.15585579 | I8: TIKR（2026-09-30）
A9: FY2028 EPS vs 共識 | B9: =cons_eps28 -> 13.07 | C9: =PL!F91 -> 14.626899 | D9: =C9/B9-1 -> 0.11912005 | E9: =PL!F126 -> 13.455364 | F9: =E9/B9-1 -> 0.029484642 | G9: =PL!F161 -> 12.283829 | H9: =G9/B9-1 -> -0.060150768 | I9: MarketBeat（2026-10-23）
A10: B. 公司指引與校準
A11: FY2027 Q1 EPS（模型，指引中點的營收、毛利率、費用）vs 公司 EPS 指引中點 | B11: =q1_eps -> 1.95 | C11: =Q!F19 -> 2.0240603 | D11: =C11/B11-1 -> 0.03797966 | E11: =Q!F19 -> 2.0240603 | F11: =E11/B11-1 -> 0.03797966 | G11: =Q!F19 -> 2.0240603 | H11: =G11/B11-1 -> 0.03797966 | I11: 公司指引（2026-08-12） | J11: 費用與稅率皆取指引；股數用 Q4 稀釋股數
A12: FY2027 Q1 EPS（模型）vs 共識 | B12: =cons_q1eps -> 1.93 | C12: =Q!F19 -> 2.0240603 | D12: =C12/B12-1 -> 0.048735926 | E12: =Q!F19 -> 2.0240603 | F12: =E12/B12-1 -> 0.048735926 | G12: =Q!F19 -> 2.0240603 | H12: =G12/B12-1 -> 0.048735926 | I12: Benzinga
A13: FY2025 Q4 DCC 由年增率回推 vs 實績（季增拆分的一致性） | B13: =q4_dcc25 -> 1.0183 | C13: =Q!E6/(1+q4_dy)+Q!E7/(1+q4_cy) -> 0.99708783 | D13: =C13/B13-1 -> -0.020830963 | E13: =Q!E6/(1+q4_dy)+Q!E7/(1+q4_cy) -> 0.99708783 | F13: =E13/B13-1 -> -0.020830963 | G13: =Q!E6/(1+q4_dy)+Q!E7/(1+q4_cy) -> 0.99708783 | H13: =G13/B13-1 -> -0.020830963 | I13: 公司 | J13: 差距小＝資料中心、通訊拆分與兩組成長率一致
A14: C. 份額與市場
A15: CY2026 Coherent＋中際旭創可插拔有效份額 | C15: =Units!C8 -> 0.56817296 | E15: =Units!C8 -> 0.56817296 | G15: =Units!C8 -> 0.56817296 | I15: Units 頁 | J15: 須低於 100%
A16: CY2028 Coherent＋中際旭創可插拔有效份額 | C16: =Units!E8 -> 0.54794056 | E16: =Units!E8 -> 0.54794056 | G16: =Units!E8 -> 0.54794056 | I16: Units 頁（情境 A）
A17: FY2026 資料中心（含元件）vs 新易盛 2025 光模組營收 | B17: =lc_eo25 -> 3.5 | C17: =PL!D72 -> 3.196083 | D17: =C17/B17-1 -> -0.086833428 | E17: =PL!D107 -> 3.196083 | F17: =E17/B17-1 -> -0.086833428 | G17: =PL!D142 -> 3.196083 | H17: =G17/B17-1 -> -0.086833428 | I17: LightCounting | J17: LightCounting 只計光模組；Coherent 2025 光模組低於新易盛，資料中心含雷射元件與 OCS
A18: FY2027 資料中心 ÷ CY2027 AI IT 資本支出 | C18: =PL!E72/itc_27 -> 0.0042775819 | E18: =PL!E107/itc_27 -> 0.0042775819 | G18: =PL!E142/itc_27 -> 0.0042775819 | I18: markets/network | J18: 每 1 美元 AI IT 資本支出分到的 Coherent 資料中心營收
A19: D. 預留
A20: R4 產業部署路徑（markets/deploy_path/，尚未建立）：上線後以資料中心營收 ÷ 部署 GW 計算每 GW 營收 | J20: 預留列：本版無數值
A21: FY2027 Q1 季報（2026-11-04 盤後）：公布後以實績取代 Q 頁 Q1 指引，並更新資料中心拆分 | J21: 預留列：本版無數值

Sheet Sens
A1: Sens — 一次動一個輸入（情境 A；有效份額在每個案例內依 CY2026 重算，FY2026 恆等於實績）：對 FY2027、FY2028 的營收、資料中心營收、毛利率與 EPS 的影響。每個案例是一個完整推導區塊（本頁下方）
A3: 案例 | B3: 設定 | C3: FY2027 營收 | D3: FY2027 資料中心 | E3: FY2027 毛利率 | F3: FY2027 EPS | G3: FY2027 EPS 相對基準 | H3: FY2028 營收 | I3: FY2028 資料中心 | J3: FY2028 毛利率 | K3: FY2028 EPS | L3: FY2028 EPS 相對基準
A4: 基準（情境 A） | B4: PL 區塊 A | C4: =PL!E75 -> 10.946573 | D4: =PL!E72 -> 6.6959129 | E4: =PL!E79 -> 0.41 | F4: =PL!E91 -> 10.168186 | G4: =F4/F$4-1 -> 0 | H4: =PL!F75 -> 14.443985 | I4: =PL!F72 -> 9.8061961 | J4: =PL!F79 -> 0.42 | K4: =PL!F91 -> 14.626899 | L4: =K4/K$4-1 -> 0
A5: 份額流失（低） | B5: 份額相對值 CY2027 0.90、CY2028 0.85、CY2029 0.80（新易盛、中際旭創搶 1.6T） | C5: =E55 -> 10.210291 | D5: =E52 -> 5.959631 | E5: =E59 -> 0.41 | F5: =E71 -> 9.3598137 | G5: =F5/F$4-1 -> -0.079500163 | H5: =F55 -> 12.343461 | I5: =F52 -> 7.7056721 | J5: =F59 -> 0.42 | K5: =F71 -> 12.171242 | L5: =K5/K$4-1 -> -0.16788635
A6: 份額大增（高） | B6: 份額相對值 1.25／1.35／1.40（磷化銦產能倍增） | C6: =E90 -> 11.498785 | D6: =E87 -> 7.2481243 | E6: =E94 -> 0.41 | F6: =E106 -> 10.774466 | G6: =F6/F$4-1 -> 0.059625122 | H6: =F90 -> 15.916362 | I6: =F87 -> 11.278573 | J6: =F94 -> 0.42 | K6: =F106 -> 16.3568 | L6: =K6/K$4-1 -> 0.11826846
A7: 降價快於模型 | B7: 單價係數 CY2027 0.90、CY2028 0.80、CY2029 0.72 | C7: =E125 -> 10.541618 | D7: =E122 -> 6.2909579 | E7: =E129 -> 0.41 | F7: =E141 -> 9.7235813 | G7: =F7/F$4-1 -> -0.043725089 | H7: =F125 -> 13.020855 | I7: =F122 -> 8.3830661 | J7: =F129 -> 0.42 | K7: =F141 -> 12.958962 | L7: =K7/K$4-1 -> -0.11403221
A8: 毛利率 低（光模組占比上升） | B8: 毛利率 FY2027 38.5%、FY2028 37.5%、FY2029 36.5% | C8: =E160 -> 10.946573 | D8: =E157 -> 6.6959129 | E8: =E164 -> 0.385 | F8: =E176 -> 9.082759 | G8: =F8/F$4-1 -> -0.10674737 | H8: =F160 -> 14.443985 | I8: =F157 -> 9.8061961 | J8: =F164 -> 0.375 | K8: =F176 -> 12.074429 | L8: =K8/K$4-1 -> -0.17450521
A9: 毛利率 高（六吋磷化銦） | B9: 毛利率 42.5%／44%／45% | C9: =E195 -> 10.946573 | D9: =E192 -> 6.6959129 | E9: =E199 -> 0.425 | F9: =E211 -> 10.819442 | G9: =F9/F$4-1 -> 0.064048425 | H9: =F195 -> 14.443985 | I9: =F192 -> 9.8061961 | J9: =F199 -> 0.44 | K9: =F211 -> 15.76133 | L9: =K9/K$4-1 -> 0.077557871
A10: CPO 份額 0 | B10: Coherent 不參與 CPO 光學 | C10: =E230 -> 10.868769 | D10: =E227 -> 6.6181089 | E10: =E234 -> 0.41 | F10: =E246 -> 10.082764 | G10: =F10/F$4-1 -> -0.0084008987 | H10: =F230 -> 14.130349 | I10: =F227 -> 9.4925603 | J10: =F234 -> 0.42 | K10: =F246 -> 14.25845 | L10: =K10/K$4-1 -> -0.025189825
A11: CPO 份額 高 | B11: CY2027 25%、CY2028 30%、CY2029 35% | C11: =E265 -> 11.063279 | D11: =E262 -> 6.8126189 | E11: =E269 -> 0.41 | F11: =E281 -> 10.296319 | G11: =F11/F$4-1 -> 0.012601348 | H11: =F265 -> 14.803288 | I11: =F262 -> 10.1655 | J11: =F269 -> 0.42 | K11: =F281 -> 15.048782 | L11: =K11/K$4-1 -> 0.028842944
A12: AI 市場 ×0.8 | B12: CY2027 起可插拔光模組市場 ×0.8 | C12: =E300 -> 10.136663 | D12: =E297 -> 5.8860028 | E12: =E304 -> 0.41 | F12: =E316 -> 9.2789765 | G12: =F12/F$4-1 -> -0.087450179 | H12: =F300 -> 12.545473 | I12: =F297 -> 7.9076841 | J12: =F304 -> 0.42 | K12: =F316 -> 12.409863 | L12: =K12/K$4-1 -> -0.15157256
A13: AI 市場 ×1.2 | B13: ×1.2 | C13: =E335 -> 11.756483 | D13: =E332 -> 7.505823 | E13: =E339 -> 0.41 | F13: =E351 -> 11.057396 | G13: =F13/F$4-1 -> 0.087450179 | H13: =F335 -> 16.342497 | I13: =F332 -> 11.704708 | J13: =F339 -> 0.42 | K13: =F351 -> 16.85643 | L13: =K13/K$4-1 -> 0.15242676
A14: 上半年比重 42% | B14: 日曆年上半年占 42%（FY 認列較晚） | C14: =E370 -> 10.587673 | D14: =E367 -> 6.3370125 | E14: =E374 -> 0.41 | F14: =E386 -> 9.7741453 | G14: =F14/F$4-1 -> -0.03875233 | H14: =F370 -> 14.37149 | I14: =F367 -> 9.7337016 | J14: =F374 -> 0.42 | K14: =F386 -> 14.547856 | L14: =K14/K$4-1 -> -0.0054039674
A15: 上半年比重 50% | B15: 50% | C15: =E405 -> 11.305474 | D15: =E402 -> 7.0548133 | E15: =E409 -> 0.41 | F15: =E421 -> 10.562227 | G15: =F15/F$4-1 -> 0.03875233 | H15: =F405 -> 14.516479 | I15: =F402 -> 9.8786906 | J15: =F409 -> 0.42 | K15: =F421 -> 14.703278 | L15: =K15/K$4-1 -> 0.0052218262
A16: 通訊成長 低 | B16: 通訊年增 10%／0%／−5% | C16: =E440 -> 10.738722 | D16: =E437 -> 6.6959129 | E16: =E444 -> 0.41 | F16: =E456 -> 9.9399834 | G16: =F16/F$4-1 -> -0.022442823 | H16: =F440 -> 13.936827 | I16: =F437 -> 9.8061961 | J16: =F444 -> 0.42 | K16: =F456 -> 14.033128 | L16: =K16/K$4-1 -> -0.040594458
A17: 營業費用率 +2pt | B17: 營業費用額外 +2% × 營收 | C17: =E475 -> 10.946573 | D17: =E472 -> 6.6959129 | E17: =E479 -> 0.41 | F17: =E491 -> 9.2998444 | G17: =F17/F$4-1 -> -0.0853979 | H17: =F475 -> 14.443985 | I17: =F472 -> 9.8061961 | J17: =F479 -> 0.42 | K17: =F491 -> 13.492468 | L17: =K17/K$4-1 -> -0.077557871
A18: 顆數情境 B | B18: CY2028 ×0.8、CY2029 ×0.85 | C18: =PL!E110 -> 10.946573 | D18: =PL!E107 -> 6.6959129 | E18: =PL!E114 -> 0.41 | F18: =PL!E126 -> 10.168186 | G18: =F18/F$4-1 -> 0 | H18: =PL!F110 -> 13.451777 | I18: =PL!F107 -> 8.8139879 | J18: =PL!F114 -> 0.42 | K18: =PL!F126 -> 13.455364 | L18: =K18/K$4-1 -> -0.080094543
A19: 顆數情境 C | B19: CY2028–29 ×0.6 | C19: =PL!E145 -> 10.946573 | D19: =PL!E142 -> 6.6959129 | E19: =PL!E149 -> 0.41 | F19: =PL!E161 -> 10.168186 | G19: =F19/F$4-1 -> 0 | H19: =PL!F145 -> 12.459569 | I19: =PL!F142 -> 7.8217797 | J19: =PL!F149 -> 0.42 | K19: =PL!F161 -> 12.283829 | L19: =K19/K$4-1 -> -0.16018909
A21: 讀法：FY2027 三顆數情境相同；B、C 的差異從 FY2028 起（FY2028 只含半年 CY2028）。FY2027 上半年＝指引＋假設，所以份額、市場等案例對 FY2027 只影響下半年；「上半年比重」案例顯示日曆年換算會計年度的口徑影響。
A23: 目標價參數（只改 DCF 參數與權重；PL 收斂法的 fade_g 不隨 tp_g 變動）
A24: 案例 | B24: 設定 | C24: DCF 目標價 | D24: Comparable 目標價 | E24: 加權目標價 | F24: 相對基準
A25: 基準 | B25: r 10%、g 4%、DCF 權重 0.5 | C25: =(tp_wA*(Val!B8*(1-IF(tp_roe<=tp_g,0.8,MIN(tp_g/tp_roe,0.8)))/(1+tp_r)^1+Val!B9*(1-IF(tp_roe<=tp_g,0.8,MIN(tp_g/tp_roe,0.8)))/(1+tp_r)^2+Val!B10*(1-IF(tp_roe<=tp_g,0.8,MIN(tp_g/tp_roe,0.8)))/(1+tp_r)^3+Val!B11*(1-IF(tp_roe<=tp_g,0.8,MIN(tp_g/tp_roe,0.8)))/(1+tp_r)^4+Val!B12*(1-IF(tp_roe<=tp_g,0.8,MIN(tp_g/tp_roe,0.8)))/(1+tp_r)^5+Val!B13*(1-IF(tp_roe<=tp_g,0.8,MIN(tp_g/tp_roe,0.8)))/(1+tp_r)^6+Val!B13*(1-IF(tp_roe<=tp_g,0.8,MIN(tp_g/tp_roe,0.8)))*(1+tp_g)/(tp_r-tp_g)/(1+tp_r)^6)+tp_wB*(Val!C8*(1-IF(tp_roe<=tp_g,0.8,MIN(tp_g/tp_roe,0.8)))/(1+tp_r)^1+Val!C9*(1-IF(tp_roe<=tp_g,0.8,MIN(tp_g/tp_roe,0.8)))/(1+tp_r)^2+Val!C10*(1-IF(tp_roe<=tp_g,0.8,MIN(tp_g/tp_roe,0.8)))/(1+tp_r)^3+Val!C11*(1-IF(tp_roe<=tp_g,0.8,MIN(tp_g/tp_roe,0.8)))/(1+tp_r)^4+Val!C12*(1-IF(tp_roe<=tp_g,0.8,MIN(tp_g/tp_roe,0.8)))/(1+tp_r)^5+Val!C13*(1-IF(tp_roe<=tp_g,0.8,MIN(tp_g/tp_roe,0.8)))/(1+tp_r)^6+Val!C13*(1-IF(tp_roe<=tp_g,0.8,MIN(tp_g/tp_roe,0.8)))*(1+tp_g)/(tp_r-tp_g)/(1+tp_r)^6)+tp_wC*(Val!D8*(1-IF(tp_roe<=tp_g,0.8,MIN(tp_g/tp_roe,0.8)))/(1+tp_r)^1+Val!D9*(1-IF(tp_roe<=tp_g,0.8,MIN(tp_g/tp_roe,0.8)))/(1+tp_r)^2+Val!D10*(1-IF(tp_roe<=tp_g,0.8,MIN(tp_g/tp_roe,0.8)))/(1+tp_r)^3+Val!D11*(1-IF(tp_roe<=tp_g,0.8,MIN(tp_g/tp_roe,0.8)))/(1+tp_r)^4+Val!D12*(1-IF(tp_roe<=tp_g,0.8,MIN(tp_g/tp_roe,0.8)))/(1+tp_r)^5+Val!D13*(1-IF(tp_roe<=tp_g,0.8,MIN(tp_g/tp_roe,0.8)))/(1+tp_r)^6+Val!D13*(1-IF(tp_roe<=tp_g,0.8,MIN(tp_g/tp_roe,0.8)))*(1+tp_g)/(tp_r-tp_g)/(1+tp_r)^6))*(1+tp_r) -> 206.32391 | D25: =Val!B35 -> 438.22773 | E25: =tp_w_dcf*C25+(1-tp_w_dcf)*D25 -> 322.27582 | F25: =E25/E$25-1 -> 0
A26: 折現率 +1pt | B26: r 11% | C26: =(tp_wA*(Val!B8*(1-IF(tp_roe<=tp_g,0.8,MIN(tp_g/tp_roe,0.8)))/(1+(tp_r+0.01))^1+Val!B9*(1-IF(tp_roe<=tp_g,0.8,MIN(tp_g/tp_roe,0.8)))/(1+(tp_r+0.01))^2+Val!B10*(1-IF(tp_roe<=tp_g,0.8,MIN(tp_g/tp_roe,0.8)))/(1+(tp_r+0.01))^3+Val!B11*(1-IF(tp_roe<=tp_g,0.8,MIN(tp_g/tp_roe,0.8)))/(1+(tp_r+0.01))^4+Val!B12*(1-IF(tp_roe<=tp_g,0.8,MIN(tp_g/tp_roe,0.8)))/(1+(tp_r+0.01))^5+Val!B13*(1-IF(tp_roe<=tp_g,0.8,MIN(tp_g/tp_roe,0.8)))/(1+(tp_r+0.01))^6+Val!B13*(1-IF(tp_roe<=tp_g,0.8,MIN(tp_g/tp_roe,0.8)))*(1+tp_g)/((tp_r+0.01)-tp_g)/(1+(tp_r+0.01))^6)+tp_wB*(Val!C8*(1-IF(tp_roe<=tp_g,0.8,MIN(tp_g/tp_roe,0.8)))/(1+(tp_r+0.01))^1+Val!C9*(1-IF(tp_roe<=tp_g,0.8,MIN(tp_g/tp_roe,0.8)))/(1+(tp_r+0.01))^2+Val!C10*(1-IF(tp_roe<=tp_g,0.8,MIN(tp_g/tp_roe,0.8)))/(1+(tp_r+0.01))^3+Val!C11*(1-IF(tp_roe<=tp_g,0.8,MIN(tp_g/tp_roe,0.8)))/(1+(tp_r+0.01))^4+Val!C12*(1-IF(tp_roe<=tp_g,0.8,MIN(tp_g/tp_roe,0.8)))/(1+(tp_r+0.01))^5+Val!C13*(1-IF(tp_roe<=tp_g,0.8,MIN(tp_g/tp_roe,0.8)))/(1+(tp_r+0.01))^6+Val!C13*(1-IF(tp_roe<=tp_g,0.8,MIN(tp_g/tp_roe,0.8)))*(1+tp_g)/((tp_r+0.01)-tp_g)/(1+(tp_r+0.01))^6)+tp_wC*(Val!D8*(1-IF(tp_roe<=tp_g,0.8,MIN(tp_g/tp_roe,0.8)))/(1+(tp_r+0.01))^1+Val!D9*(1-IF(tp_roe<=tp_g,0.8,MIN(tp_g/tp_roe,0.8)))/(1+(tp_r+0.01))^2+Val!D10*(1-IF(tp_roe<=tp_g,0.8,MIN(tp_g/tp_roe,0.8)))/(1+(tp_r+0.01))^3+Val!D11*(1-IF(tp_roe<=tp_g,0.8,MIN(tp_g/tp_roe,0.8)))/(1+(tp_r+0.01))^4+Val!D12*(1-IF(tp_roe<=tp_g,0.8,MIN(tp_g/tp_roe,0.8)))/(1+(tp_r+0.01))^5+Val!D13*(1-IF(tp_roe<=tp_g,0.8,MIN(tp_g/tp_roe,0.8)))/(1+(tp_r+0.01))^6+Val!D13*(1-IF(tp_roe<=tp_g,0.8,MIN(tp_g/tp_roe,0.8)))*(1+tp_g)/((tp_r+0.01)-tp_g)/(1+(tp_r+0.01))^6))*(1+(tp_r+0.01)) -> 177.95987 | D26: =Val!B35 -> 438.22773 | E26: =tp_w_dcf*C26+(1-tp_w_dcf)*D26 -> 308.0938 | F26: =E26/E$25-1 -> -0.044005854
A27: 折現率 −1pt | B27: r 9% | C27: =(tp_wA*(Val!B8*(1-IF(tp_roe<=tp_g,0.8,MIN(tp_g/tp_roe,0.8)))/(1+(tp_r-0.01))^1+Val!B9*(1-IF(tp_roe<=tp_g,0.8,MIN(tp_g/tp_roe,0.8)))/(1+(tp_r-0.01))^2+Val!B10*(1-IF(tp_roe<=tp_g,0.8,MIN(tp_g/tp_roe,0.8)))/(1+(tp_r-0.01))^3+Val!B11*(1-IF(tp_roe<=tp_g,0.8,MIN(tp_g/tp_roe,0.8)))/(1+(tp_r-0.01))^4+Val!B12*(1-IF(tp_roe<=tp_g,0.8,MIN(tp_g/tp_roe,0.8)))/(1+(tp_r-0.01))^5+Val!B13*(1-IF(tp_roe<=tp_g,0.8,MIN(tp_g/tp_roe,0.8)))/(1+(tp_r-0.01))^6+Val!B13*(1-IF(tp_roe<=tp_g,0.8,MIN(tp_g/tp_roe,0.8)))*(1+tp_g)/((tp_r-0.01)-tp_g)/(1+(tp_r-0.01))^6)+tp_wB*(Val!C8*(1-IF(tp_roe<=tp_g,0.8,MIN(tp_g/tp_roe,0.8)))/(1+(tp_r-0.01))^1+Val!C9*(1-IF(tp_roe<=tp_g,0.8,MIN(tp_g/tp_roe,0.8)))/(1+(tp_r-0.01))^2+Val!C10*(1-IF(tp_roe<=tp_g,0.8,MIN(tp_g/tp_roe,0.8)))/(1+(tp_r-0.01))^3+Val!C11*(1-IF(tp_roe<=tp_g,0.8,MIN(tp_g/tp_roe,0.8)))/(1+(tp_r-0.01))^4+Val!C12*(1-IF(tp_roe<=tp_g,0.8,MIN(tp_g/tp_roe,0.8)))/(1+(tp_r-0.01))^5+Val!C13*(1-IF(tp_roe<=tp_g,0.8,MIN(tp_g/tp_roe,0.8)))/(1+(tp_r-0.01))^6+Val!C13*(1-IF(tp_roe<=tp_g,0.8,MIN(tp_g/tp_roe,0.8)))*(1+tp_g)/((tp_r-0.01)-tp_g)/(1+(tp_r-0.01))^6)+tp_wC*(Val!D8*(1-IF(tp_roe<=tp_g,0.8,MIN(tp_g/tp_roe,0.8)))/(1+(tp_r-0.01))^1+Val!D9*(1-IF(tp_roe<=tp_g,0.8,MIN(tp_g/tp_roe,0.8)))/(1+(tp_r-0.01))^2+Val!D10*(1-IF(tp_roe<=tp_g,0.8,MIN(tp_g/tp_roe,0.8)))/(1+(tp_r-0.01))^3+Val!D11*(1-IF(tp_roe<=tp_g,0.8,MIN(tp_g/tp_roe,0.8)))/(1+(tp_r-0.01))^4+Val!D12*(1-IF(tp_roe<=tp_g,0.8,MIN(tp_g/tp_roe,0.8)))/(1+(tp_r-0.01))^5+Val!D13*(1-IF(tp_roe<=tp_g,0.8,MIN(tp_g/tp_roe,0.8)))/(1+(tp_r-0.01))^6+Val!D13*(1-IF(tp_roe<=tp_g,0.8,MIN(tp_g/tp_roe,0.8)))*(1+tp_g)/((tp_r-0.01)-tp_g)/(1+(tp_r-0.01))^6))*(1+(tp_r-0.01)) -> 246.02966 | D27: =Val!B35 -> 438.22773 | E27: =tp_w_dcf*C27+(1-tp_w_dcf)*D27 -> 342.12869 | F27: =E27/E$25-1 -> 0.061602119
A28: 長期成長 +1pt | B28: g 5% | C28: =(tp_wA*(Val!B8*(1-IF(tp_roe<=(tp_g+0.01),0.8,MIN((tp_g+0.01)/tp_roe,0.8)))/(1+tp_r)^1+Val!B9*(1-IF(tp_roe<=(tp_g+0.01),0.8,MIN((tp_g+0.01)/tp_roe,0.8)))/(1+tp_r)^2+Val!B10*(1-IF(tp_roe<=(tp_g+0.01),0.8,MIN((tp_g+0.01)/tp_roe,0.8)))/(1+tp_r)^3+Val!B11*(1-IF(tp_roe<=(tp_g+0.01),0.8,MIN((tp_g+0.01)/tp_roe,0.8)))/(1+tp_r)^4+Val!B12*(1-IF(tp_roe<=(tp_g+0.01),0.8,MIN((tp_g+0.01)/tp_roe,0.8)))/(1+tp_r)^5+Val!B13*(1-IF(tp_roe<=(tp_g+0.01),0.8,MIN((tp_g+0.01)/tp_roe,0.8)))/(1+tp_r)^6+Val!B13*(1-IF(tp_roe<=(tp_g+0.01),0.8,MIN((tp_g+0.01)/tp_roe,0.8)))*(1+(tp_g+0.01))/(tp_r-(tp_g+0.01))/(1+tp_r)^6)+tp_wB*(Val!C8*(1-IF(tp_roe<=(tp_g+0.01),0.8,MIN((tp_g+0.01)/tp_roe,0.8)))/(1+tp_r)^1+Val!C9*(1-IF(tp_roe<=(tp_g+0.01),0.8,MIN((tp_g+0.01)/tp_roe,0.8)))/(1+tp_r)^2+Val!C10*(1-IF(tp_roe<=(tp_g+0.01),0.8,MIN((tp_g+0.01)/tp_roe,0.8)))/(1+tp_r)^3+Val!C11*(1-IF(tp_roe<=(tp_g+0.01),0.8,MIN((tp_g+0.01)/tp_roe,0.8)))/(1+tp_r)^4+Val!C12*(1-IF(tp_roe<=(tp_g+0.01),0.8,MIN((tp_g+0.01)/tp_roe,0.8)))/(1+tp_r)^5+Val!C13*(1-IF(tp_roe<=(tp_g+0.01),0.8,MIN((tp_g+0.01)/tp_roe,0.8)))/(1+tp_r)^6+Val!C13*(1-IF(tp_roe<=(tp_g+0.01),0.8,MIN((tp_g+0.01)/tp_roe,0.8)))*(1+(tp_g+0.01))/(tp_r-(tp_g+0.01))/(1+tp_r)^6)+tp_wC*(Val!D8*(1-IF(tp_roe<=(tp_g+0.01),0.8,MIN((tp_g+0.01)/tp_roe,0.8)))/(1+tp_r)^1+Val!D9*(1-IF(tp_roe<=(tp_g+0.01),0.8,MIN((tp_g+0.01)/tp_roe,0.8)))/(1+tp_r)^2+Val!D10*(1-IF(tp_roe<=(tp_g+0.01),0.8,MIN((tp_g+0.01)/tp_roe,0.8)))/(1+tp_r)^3+Val!D11*(1-IF(tp_roe<=(tp_g+0.01),0.8,MIN((tp_g+0.01)/tp_roe,0.8)))/(1+tp_r)^4+Val!D12*(1-IF(tp_roe<=(tp_g+0.01),0.8,MIN((tp_g+0.01)/tp_roe,0.8)))/(1+tp_r)^5+Val!D13*(1-IF(tp_roe<=(tp_g+0.01),0.8,MIN((tp_g+0.01)/tp_roe,0.8)))/(1+tp_r)^6+Val!D13*(1-IF(tp_roe<=(tp_g+0.01),0.8,MIN((tp_g+0.01)/tp_roe,0.8)))*(1+(tp_g+0.01))/(tp_r-(tp_g+0.01))/(1+tp_r)^6))*(1+tp_r) -> 223.16274 | D28: =Val!B35 -> 438.22773 | E28: =tp_w_dcf*C28+(1-tp_w_dcf)*D28 -> 330.69523 | F28: =E28/E$25-1 -> 0.02612487
A29: 長期成長 −1pt | B29: g 3% | C29: =(tp_wA*(Val!B8*(1-IF(tp_roe<=(tp_g-0.01),0.8,MIN((tp_g-0.01)/tp_roe,0.8)))/(1+tp_r)^1+Val!B9*(1-IF(tp_roe<=(tp_g-0.01),0.8,MIN((tp_g-0.01)/tp_roe,0.8)))/(1+tp_r)^2+Val!B10*(1-IF(tp_roe<=(tp_g-0.01),0.8,MIN((tp_g-0.01)/tp_roe,0.8)))/(1+tp_r)^3+Val!B11*(1-IF(tp_roe<=(tp_g-0.01),0.8,MIN((tp_g-0.01)/tp_roe,0.8)))/(1+tp_r)^4+Val!B12*(1-IF(tp_roe<=(tp_g-0.01),0.8,MIN((tp_g-0.01)/tp_roe,0.8)))/(1+tp_r)^5+Val!B13*(1-IF(tp_roe<=(tp_g-0.01),0.8,MIN((tp_g-0.01)/tp_roe,0.8)))/(1+tp_r)^6+Val!B13*(1-IF(tp_roe<=(tp_g-0.01),0.8,MIN((tp_g-0.01)/tp_roe,0.8)))*(1+(tp_g-0.01))/(tp_r-(tp_g-0.01))/(1+tp_r)^6)+tp_wB*(Val!C8*(1-IF(tp_roe<=(tp_g-0.01),0.8,MIN((tp_g-0.01)/tp_roe,0.8)))/(1+tp_r)^1+Val!C9*(1-IF(tp_roe<=(tp_g-0.01),0.8,MIN((tp_g-0.01)/tp_roe,0.8)))/(1+tp_r)^2+Val!C10*(1-IF(tp_roe<=(tp_g-0.01),0.8,MIN((tp_g-0.01)/tp_roe,0.8)))/(1+tp_r)^3+Val!C11*(1-IF(tp_roe<=(tp_g-0.01),0.8,MIN((tp_g-0.01)/tp_roe,0.8)))/(1+tp_r)^4+Val!C12*(1-IF(tp_roe<=(tp_g-0.01),0.8,MIN((tp_g-0.01)/tp_roe,0.8)))/(1+tp_r)^5+Val!C13*(1-IF(tp_roe<=(tp_g-0.01),0.8,MIN((tp_g-0.01)/tp_roe,0.8)))/(1+tp_r)^6+Val!C13*(1-IF(tp_roe<=(tp_g-0.01),0.8,MIN((tp_g-0.01)/tp_roe,0.8)))*(1+(tp_g-0.01))/(tp_r-(tp_g-0.01))/(1+tp_r)^6)+tp_wC*(Val!D8*(1-IF(tp_roe<=(tp_g-0.01),0.8,MIN((tp_g-0.01)/tp_roe,0.8)))/(1+tp_r)^1+Val!D9*(1-IF(tp_roe<=(tp_g-0.01),0.8,MIN((tp_g-0.01)/tp_roe,0.8)))/(1+tp_r)^2+Val!D10*(1-IF(tp_roe<=(tp_g-0.01),0.8,MIN((tp_g-0.01)/tp_roe,0.8)))/(1+tp_r)^3+Val!D11*(1-IF(tp_roe<=(tp_g-0.01),0.8,MIN((tp_g-0.01)/tp_roe,0.8)))/(1+tp_r)^4+Val!D12*(1-IF(tp_roe<=(tp_g-0.01),0.8,MIN((tp_g-0.01)/tp_roe,0.8)))/(1+tp_r)^5+Val!D13*(1-IF(tp_roe<=(tp_g-0.01),0.8,MIN((tp_g-0.01)/tp_roe,0.8)))/(1+tp_r)^6+Val!D13*(1-IF(tp_roe<=(tp_g-0.01),0.8,MIN((tp_g-0.01)/tp_roe,0.8)))*(1+(tp_g-0.01))/(tp_r-(tp_g-0.01))/(1+tp_r)^6))*(1+tp_r) -> 195.14872 | D29: =Val!B35 -> 438.22773 | E29: =tp_w_dcf*C29+(1-tp_w_dcf)*D29 -> 316.68822 | F29: =E29/E$25-1 -> -0.017337936
A30: DCF 權重 0.3 | B30: Comparable 0.7 | C30: =(tp_wA*(Val!B8*(1-IF(tp_roe<=tp_g,0.8,MIN(tp_g/tp_roe,0.8)))/(1+tp_r)^1+Val!B9*(1-IF(tp_roe<=tp_g,0.8,MIN(tp_g/tp_roe,0.8)))/(1+tp_r)^2+Val!B10*(1-IF(tp_roe<=tp_g,0.8,MIN(tp_g/tp_roe,0.8)))/(1+tp_r)^3+Val!B11*(1-IF(tp_roe<=tp_g,0.8,MIN(tp_g/tp_roe,0.8)))/(1+tp_r)^4+Val!B12*(1-IF(tp_roe<=tp_g,0.8,MIN(tp_g/tp_roe,0.8)))/(1+tp_r)^5+Val!B13*(1-IF(tp_roe<=tp_g,0.8,MIN(tp_g/tp_roe,0.8)))/(1+tp_r)^6+Val!B13*(1-IF(tp_roe<=tp_g,0.8,MIN(tp_g/tp_roe,0.8)))*(1+tp_g)/(tp_r-tp_g)/(1+tp_r)^6)+tp_wB*(Val!C8*(1-IF(tp_roe<=tp_g,0.8,MIN(tp_g/tp_roe,0.8)))/(1+tp_r)^1+Val!C9*(1-IF(tp_roe<=tp_g,0.8,MIN(tp_g/tp_roe,0.8)))/(1+tp_r)^2+Val!C10*(1-IF(tp_roe<=tp_g,0.8,MIN(tp_g/tp_roe,0.8)))/(1+tp_r)^3+Val!C11*(1-IF(tp_roe<=tp_g,0.8,MIN(tp_g/tp_roe,0.8)))/(1+tp_r)^4+Val!C12*(1-IF(tp_roe<=tp_g,0.8,MIN(tp_g/tp_roe,0.8)))/(1+tp_r)^5+Val!C13*(1-IF(tp_roe<=tp_g,0.8,MIN(tp_g/tp_roe,0.8)))/(1+tp_r)^6+Val!C13*(1-IF(tp_roe<=tp_g,0.8,MIN(tp_g/tp_roe,0.8)))*(1+tp_g)/(tp_r-tp_g)/(1+tp_r)^6)+tp_wC*(Val!D8*(1-IF(tp_roe<=tp_g,0.8,MIN(tp_g/tp_roe,0.8)))/(1+tp_r)^1+Val!D9*(1-IF(tp_roe<=tp_g,0.8,MIN(tp_g/tp_roe,0.8)))/(1+tp_r)^2+Val!D10*(1-IF(tp_roe<=tp_g,0.8,MIN(tp_g/tp_roe,0.8)))/(1+tp_r)^3+Val!D11*(1-IF(tp_roe<=tp_g,0.8,MIN(tp_g/tp_roe,0.8)))/(1+tp_r)^4+Val!D12*(1-IF(tp_roe<=tp_g,0.8,MIN(tp_g/tp_roe,0.8)))/(1+tp_r)^5+Val!D13*(1-IF(tp_roe<=tp_g,0.8,MIN(tp_g/tp_roe,0.8)))/(1+tp_r)^6+Val!D13*(1-IF(tp_roe<=tp_g,0.8,MIN(tp_g/tp_roe,0.8)))*(1+tp_g)/(tp_r-tp_g)/(1+tp_r)^6))*(1+tp_r) -> 206.32391 | D30: =Val!B35 -> 438.22773 | E30: =0.3*C30+(1-0.3)*D30 -> 368.65658 | F30: =E30/E$25-1 -> 0.14391636
A31: DCF 權重 0.7 | B31: Comparable 0.3 | C31: =(tp_wA*(Val!B8*(1-IF(tp_roe<=tp_g,0.8,MIN(tp_g/tp_roe,0.8)))/(1+tp_r)^1+Val!B9*(1-IF(tp_roe<=tp_g,0.8,MIN(tp_g/tp_roe,0.8)))/(1+tp_r)^2+Val!B10*(1-IF(tp_roe<=tp_g,0.8,MIN(tp_g/tp_roe,0.8)))/(1+tp_r)^3+Val!B11*(1-IF(tp_roe<=tp_g,0.8,MIN(tp_g/tp_roe,0.8)))/(1+tp_r)^4+Val!B12*(1-IF(tp_roe<=tp_g,0.8,MIN(tp_g/tp_roe,0.8)))/(1+tp_r)^5+Val!B13*(1-IF(tp_roe<=tp_g,0.8,MIN(tp_g/tp_roe,0.8)))/(1+tp_r)^6+Val!B13*(1-IF(tp_roe<=tp_g,0.8,MIN(tp_g/tp_roe,0.8)))*(1+tp_g)/(tp_r-tp_g)/(1+tp_r)^6)+tp_wB*(Val!C8*(1-IF(tp_roe<=tp_g,0.8,MIN(tp_g/tp_roe,0.8)))/(1+tp_r)^1+Val!C9*(1-IF(tp_roe<=tp_g,0.8,MIN(tp_g/tp_roe,0.8)))/(1+tp_r)^2+Val!C10*(1-IF(tp_roe<=tp_g,0.8,MIN(tp_g/tp_roe,0.8)))/(1+tp_r)^3+Val!C11*(1-IF(tp_roe<=tp_g,0.8,MIN(tp_g/tp_roe,0.8)))/(1+tp_r)^4+Val!C12*(1-IF(tp_roe<=tp_g,0.8,MIN(tp_g/tp_roe,0.8)))/(1+tp_r)^5+Val!C13*(1-IF(tp_roe<=tp_g,0.8,MIN(tp_g/tp_roe,0.8)))/(1+tp_r)^6+Val!C13*(1-IF(tp_roe<=tp_g,0.8,MIN(tp_g/tp_roe,0.8)))*(1+tp_g)/(tp_r-tp_g)/(1+tp_r)^6)+tp_wC*(Val!D8*(1-IF(tp_roe<=tp_g,0.8,MIN(tp_g/tp_roe,0.8)))/(1+tp_r)^1+Val!D9*(1-IF(tp_roe<=tp_g,0.8,MIN(tp_g/tp_roe,0.8)))/(1+tp_r)^2+Val!D10*(1-IF(tp_roe<=tp_g,0.8,MIN(tp_g/tp_roe,0.8)))/(1+tp_r)^3+Val!D11*(1-IF(tp_roe<=tp_g,0.8,MIN(tp_g/tp_roe,0.8)))/(1+tp_r)^4+Val!D12*(1-IF(tp_roe<=tp_g,0.8,MIN(tp_g/tp_roe,0.8)))/(1+tp_r)^5+Val!D13*(1-IF(tp_roe<=tp_g,0.8,MIN(tp_g/tp_roe,0.8)))/(1+tp_r)^6+Val!D13*(1-IF(tp_roe<=tp_g,0.8,MIN(tp_g/tp_roe,0.8)))*(1+tp_g)/(tp_r-tp_g)/(1+tp_r)^6))*(1+tp_r) -> 206.32391 | D31: =Val!B35 -> 438.22773 | E31: =0.7*C31+(1-0.7)*D31 -> 275.89506 | F31: =E31/E$25-1 -> -0.14391636
A40: 案例區塊：份額流失（低）（情境 A）
A41: 項目 | B41: 單位 | C41: FY2025A | D41: FY2026A（錨點） | E41: FY2027 | F41: FY2028 | G41: FY2029 | H41: 說明
A42: A. 日曆年 AI 光學（本節 D–G 欄＝CY2026–CY2029；D 欄＝CY2026 校準年）
A43: AI 可插拔光模組市場 × 情境顆數係數（日曆年） | B43: US$B | D43: =mpl_26*1 -> 29.753262 | E43: =mpl_27*1*1 -> 54.688309 | F43: =mpl_28*um28_A*1 -> 61.21325 | G43: =mpl_29*um29_A*1 -> 78.80848 | H43: 本節欄位為日曆年
A44: AI CPO 光學市場 × 情境顆數係數（日曆年） | B44: US$B | D44: =mcp_26*1 -> 0.300538 | E44: =mcp_27*1 -> 1.691391 | F44: =mcp_28*um28_A -> 3.22175 | G44: =mcp_29*um29_A -> 5.87368
A45: Coherent 可插拔有效份額（CY2026 校準）＝ CY2026 資料中心 ÷ 可插拔市場 | B45: % | D45: =dc_cy26/D43 -> 0.14633958 | H45: Derived：CY2026 CPO 營收視為 0；含賣給其他模組廠的雷射元件，屬「有效」份額
A46: 份額相對值（÷ CY2026） | B46: x | D46: =1 -> 1 | E46: =RLO_27 -> 0.9 | F46: =RLO_28 -> 0.85 | G46: =RLO_29 -> 0.8
A47: 可插拔有效份額（日曆年） | B47: % | D47: =$D$45*D46 -> 0.14633958 | E47: =$D$45*E46 -> 0.13170562 | F47: =$D$45*F46 -> 0.12438864 | G47: =$D$45*G46 -> 0.11707166
A48: 單價係數（相對網通模型） | B48: x | D48: =1 -> 1 | E48: =pxr_27 -> 1 | F48: =pxr_28 -> 1 | G48: =pxr_29 -> 1
A49: Coherent 占 CPO 光學金額 | B49: % | D49: =0 -> 0 | E49: =cpo_27 -> 0.1 | F49: =cpo_28 -> 0.15 | G49: =cpo_29 -> 0.2
A50: 資料中心營收（日曆年） | B50: US$B | D50: =dc_cy26 -> 4.3540798 | E50: =E43*E47*E48+E44*E49 -> 7.3718967 | F50: =F43*F47*F48+F44*F49 -> 8.0974954 | G50: =G43*G47*G48+G44*G49 -> 10.400976
A51: B. 會計年度營收（本節起 C–G 欄＝FY2025–FY2029）
A52: 資料中心 | B52: US$B | C52: =a25_dc -> 2.2754201 | D52: =a26_dc -> 3.196083 | E52: =h1_27+hw*E50 -> 5.959631 | F52: =(1-hw)*E50+hw*F50 -> 7.7056721 | G52: =(1-hw)*F50+hw*G50 -> 9.1570963 | H52: FY2027＝CY2026 下半年（Q 頁）＋ hw × CY2027；FY2028＝（1 − hw）× CY2027 ＋ hw × CY2028
A53: 通訊 | B53: US$B | C53: =a25_com -> 1.4797799 | D53: =a26_com -> 2.078517 | E53: =D53*(1+g_com_27) -> 2.4942204 | F53: =E53*(1+g_com_28) -> 2.7935268 | G53: =F53*(1+g_com_29) -> 3.017009
A54: 工業（FY2027 起排除已出售事業） | B54: US$B | C54: =a25_ind -> 2.0549 | D54: =a26_ind -> 1.8436 | E54: =ind_run*(1+g_ind_27) -> 1.75644 | F54: =E54*(1+g_ind_28) -> 1.844262 | G54: =F54*(1+g_ind_29) -> 1.9364751
A55: 營收 | B55: US$B | C55: =C52+C53+C54 -> 5.8101 | D55: =D52+D53+D54 -> 7.1182 | E55: =E52+E53+E54 -> 10.210291 | F55: =F52+F53+F54 -> 12.343461 | G55: =G52+G53+G54 -> 14.11058
A56: 營收年增 | B56: % | D56: =D55/C55-1 -> 0.22514242 | E56: =E55/D55-1 -> 0.43439232 | F56: =F55/E55-1 -> 0.20892347 | G56: =G55/F55-1 -> 0.1431624
A57: 資料中心 ÷ 營收 | B57: % | C57: =C52/C55 -> 0.39163183 | D57: =D52/D55 -> 0.44900157 | E57: =E52/E55 -> 0.58368863 | F57: =F52/F55 -> 0.6242716 | G57: =G52/G55 -> 0.64895249
A58: C. 損益（non-GAAP）
A59: 毛利率 | B59: % | C59: =a25_gp/a25_rev -> 0.37904683 | D59: =a26_gp/a26_rev -> 0.39427102 | E59: =gm_27 -> 0.41 | F59: =gm_28 -> 0.42 | G59: =gm_29 -> 0.42 | H59: FY2027 起為輸入路徑（六吋磷化銦降本、1.6T 上推 vs 光模組占比上升下壓）
A60: 毛利 | B60: US$B | C60: =C55*C59 -> 2.2023 | D60: =D55*D59 -> 2.8065 | E60: =E55*E59 -> 4.1862195 | F60: =F55*F59 -> 5.1842536 | G60: =G55*G59 -> 5.9264438
A61: 營業費用（基準路徑） | B61: US$B | C61: =a25_opx -> 1.1653 | D61: =a26_opx -> 1.3496 | E61: =D61*(1+MAX(0,phi*E56)) -> 1.7614295 | F61: =E61*(1+MAX(0,phi*F56)) -> 2.0199427 | G61: =F61*(1+MAX(0,phi*G56)) -> 2.223084
A62: 營業費用 | B62: US$B | C62: =C61 -> 1.1653 | D62: =D61 -> 1.3496 | E62: =E61+0*E55 -> 1.7614295 | F62: =F61+0*F55 -> 2.0199427 | G62: =G61+0*G55 -> 2.223084
A63: 營業利益 | B63: US$B | C63: =C60-C62 -> 1.037 | D63: =D60-D62 -> 1.4569 | E63: =E60-E62 -> 2.42479 | F63: =F60-F62 -> 3.1643109 | G63: =G60-G62 -> 3.7033597
A64: 營業利益率 | B64: % | C64: =C63/C55 -> 0.1784823 | D64: =D63/D55 -> 0.20467253 | E64: =E63/E55 -> 0.23748489 | F64: =F63/F55 -> 0.25635524 | G64: =G63/G55 -> 0.26245269
A65: 利息與其他淨支出 | B65: US$B | C65: =a25_int -> 0.1673 | D65: =a26_int -> 0.1181 | E65: =int_f -> 0.08 | F65: =int_f -> 0.08 | G65: =int_f -> 0.08
A66: 稅前利益 | B66: US$B | C66: =C63-C65 -> 0.8697 | D66: =D63-D65 -> 1.3388 | E66: =E63-E65 -> 2.34479 | F66: =F63-F65 -> 3.0843109 | G66: =G63-G65 -> 3.6233597
A67: 歸屬 Coherent 淨利 | B67: US$B | C67: =a25_ni -> 0.6926 | D67: =a26_ni -> 1.0966 | E67: =E66*(1-tx)+nci -> 1.9114799 | F67: =F66*(1-tx)+nci -> 2.5104918 | G67: =G66*(1-tx)+nci -> 2.9471214
A68: 淨利率 | B68: % | C68: =C67/C55 -> 0.11920621 | D68: =D67/D55 -> 0.1540558 | E68: =E67/E55 -> 0.1872111 | F68: =F67/F55 -> 0.20338638 | G68: =G67/G55 -> 0.20885898
A69: 優先股股利 | B69: US$B | C69: =a25_pref -> 0.130624 | D69: =0 -> 0 | E69: =0 -> 0 | F69: =0 -> 0 | G69: =0 -> 0
A70: 稀釋股數 | B70: 十億股 | C70: =a25_sh -> 0.1592 | D70: =a26_sh -> 0.1954 | E70: =sh_q4*(1+sh_g) -> 0.204222 | F70: =E70*(1+sh_g) -> 0.20626422 | G70: =F70*(1+sh_g) -> 0.20832686
A71: EPS | B71: US$ | C71: =(C67-C69)/C70 -> 3.53 | D71: =(D67-D69)/D70 -> 5.6120778 | E71: =(E67-E69)/E70 -> 9.3598137 | F71: =(F67-F69)/F70 -> 12.171242 | G71: =(G67-G69)/G70 -> 14.146622
A72: EPS 年增 | B72: % | D72: =D71/C71-1 -> 0.58982374 | E72: =E71/D71-1 -> 0.66779829 | F72: =F71/E71-1 -> 0.30037228 | G72: =G71/F71-1 -> 0.16229894
A75: 案例區塊：份額大增（高）（情境 A）
A76: 項目 | B76: 單位 | C76: FY2025A | D76: FY2026A（錨點） | E76: FY2027 | F76: FY2028 | G76: FY2029 | H76: 說明
A77: A. 日曆年 AI 光學（本節 D–G 欄＝CY2026–CY2029；D 欄＝CY2026 校準年）
A78: AI 可插拔光模組市場 × 情境顆數係數（日曆年） | B78: US$B | D78: =mpl_26*1 -> 29.753262 | E78: =mpl_27*1*1 -> 54.688309 | F78: =mpl_28*um28_A*1 -> 61.21325 | G78: =mpl_29*um29_A*1 -> 78.80848 | H78: 本節欄位為日曆年
A79: AI CPO 光學市場 × 情境顆數係數（日曆年） | B79: US$B | D79: =mcp_26*1 -> 0.300538 | E79: =mcp_27*1 -> 1.691391 | F79: =mcp_28*um28_A -> 3.22175 | G79: =mcp_29*um29_A -> 5.87368
A80: Coherent 可插拔有效份額（CY2026 校準）＝ CY2026 資料中心 ÷ 可插拔市場 | B80: % | D80: =dc_cy26/D78 -> 0.14633958 | H80: Derived：CY2026 CPO 營收視為 0；含賣給其他模組廠的雷射元件，屬「有效」份額
A81: 份額相對值（÷ CY2026） | B81: x | D81: =1 -> 1 | E81: =RHI_27 -> 1.25 | F81: =RHI_28 -> 1.35 | G81: =RHI_29 -> 1.4
A82: 可插拔有效份額（日曆年） | B82: % | D82: =$D$80*D81 -> 0.14633958 | E82: =$D$80*E81 -> 0.18292447 | F82: =$D$80*F81 -> 0.19755843 | G82: =$D$80*G81 -> 0.20487541
A83: 單價係數（相對網通模型） | B83: x | D83: =1 -> 1 | E83: =pxr_27 -> 1 | F83: =pxr_28 -> 1 | G83: =pxr_29 -> 1
A84: Coherent 占 CPO 光學金額 | B84: % | D84: =0 -> 0 | E84: =cpo_27 -> 0.1 | F84: =cpo_28 -> 0.15 | G84: =cpo_29 -> 0.2
A85: 資料中心營收（日曆年） | B85: US$B | D85: =dc_cy26 -> 4.3540798 | E85: =E78*E82*E83+E79*E84 -> 10.172969 | F85: =F78*F82*F83+F79*F84 -> 12.576456 | G85: =G78*G82*G83+G79*G84 -> 17.320655
A86: B. 會計年度營收（本節起 C–G 欄＝FY2025–FY2029）
A87: 資料中心 | B87: US$B | C87: =a25_dc -> 2.2754201 | D87: =a26_dc -> 3.196083 | E87: =h1_27+hw*E85 -> 7.2481243 | F87: =(1-hw)*E85+hw*F85 -> 11.278573 | G87: =(1-hw)*F85+hw*G85 -> 14.758788 | H87: FY2027＝CY2026 下半年（Q 頁）＋ hw × CY2027；FY2028＝（1 − hw）× CY2027 ＋ hw × CY2028
A88: 通訊 | B88: US$B | C88: =a25_com -> 1.4797799 | D88: =a26_com -> 2.078517 | E88: =D88*(1+g_com_27) -> 2.4942204 | F88: =E88*(1+g_com_28) -> 2.7935268 | G88: =F88*(1+g_com_29) -> 3.017009
A89: 工業（FY2027 起排除已出售事業） | B89: US$B | C89: =a25_ind -> 2.0549 | D89: =a26_ind -> 1.8436 | E89: =ind_run*(1+g_ind_27) -> 1.75644 | F89: =E89*(1+g_ind_28) -> 1.844262 | G89: =F89*(1+g_ind_29) -> 1.9364751
A90: 營收 | B90: US$B | C90: =C87+C88+C89 -> 5.8101 | D90: =D87+D88+D89 -> 7.1182 | E90: =E87+E88+E89 -> 11.498785 | F90: =F87+F88+F89 -> 15.916362 | G90: =G87+G88+G89 -> 19.712272
A91: 營收年增 | B91: % | D91: =D90/C90-1 -> 0.22514242 | E91: =E90/D90-1 -> 0.61540624 | F91: =F90/E90-1 -> 0.38417775 | G91: =G90/F90-1 -> 0.23849105
A92: 資料中心 ÷ 營收 | B92: % | C92: =C87/C90 -> 0.39163183 | D92: =D87/D90 -> 0.44900157 | E92: =E87/E90 -> 0.63033829 | F92: =F87/F90 -> 0.70861502 | G92: =G87/G90 -> 0.74871064
A93: C. 損益（non-GAAP）
A94: 毛利率 | B94: % | C94: =a25_gp/a25_rev -> 0.37904683 | D94: =a26_gp/a26_rev -> 0.39427102 | E94: =gm_27 -> 0.41 | F94: =gm_28 -> 0.42 | G94: =gm_29 -> 0.42 | H94: FY2027 起為輸入路徑（六吋磷化銦降本、1.6T 上推 vs 光模組占比上升下壓）
A95: 毛利 | B95: US$B | C95: =C90*C94 -> 2.2023 | D95: =D90*D94 -> 2.8065 | E95: =E90*E94 -> 4.7145017 | F95: =F90*F94 -> 6.684872 | G95: =G90*G94 -> 8.2791542
A96: 營業費用（基準路徑） | B96: US$B | C96: =a25_opx -> 1.1653 | D96: =a26_opx -> 1.3496 | E96: =D96*(1+MAX(0,phi*E91)) -> 1.9330414 | F96: =E96*(1+MAX(0,phi*F91)) -> 2.4547207 | G96: =F96*(1+MAX(0,phi*G91)) -> 2.8659693
A97: 營業費用 | B97: US$B | C97: =C96 -> 1.1653 | D97: =D96 -> 1.3496 | E97: =E96+0*E90 -> 1.9330414 | F97: =F96+0*F90 -> 2.4547207 | G97: =G96+0*G90 -> 2.8659693
A98: 營業利益 | B98: US$B | C98: =C95-C97 -> 1.037 | D98: =D95-D97 -> 1.4569 | E98: =E95-E97 -> 2.7814604 | F98: =F95-F97 -> 4.2301513 | G98: =G95-G97 -> 5.4131849
A99: 營業利益率 | B99: % | C99: =C98/C90 -> 0.1784823 | D99: =D98/D90 -> 0.20467253 | E99: =E98/E90 -> 0.24189168 | F99: =F98/F90 -> 0.26577376 | G99: =G98/G90 -> 0.2746099
A100: 利息與其他淨支出 | B100: US$B | C100: =a25_int -> 0.1673 | D100: =a26_int -> 0.1181 | E100: =int_f -> 0.08 | F100: =int_f -> 0.08 | G100: =int_f -> 0.08
A101: 稅前利益 | B101: US$B | C101: =C98-C100 -> 0.8697 | D101: =D98-D100 -> 1.3388 | E101: =E98-E100 -> 2.7014604 | F101: =F98-F100 -> 4.1501513 | G101: =G98-G100 -> 5.3331849
A102: 歸屬 Coherent 淨利 | B102: US$B | C102: =a25_ni -> 0.6926 | D102: =a26_ni -> 1.0966 | E102: =E101*(1-tx)+nci -> 2.2003829 | F102: =F101*(1-tx)+nci -> 3.3738226 | G102: =G101*(1-tx)+nci -> 4.3320798
A103: 淨利率 | B103: % | C103: =C102/C90 -> 0.11920621 | D103: =D102/D90 -> 0.1540558 | E103: =E102/E90 -> 0.19135787 | F103: =F102/F90 -> 0.21197197 | G103: =G102/G90 -> 0.21976563
A104: 優先股股利 | B104: US$B | C104: =a25_pref -> 0.130624 | D104: =0 -> 0 | E104: =0 -> 0 | F104: =0 -> 0 | G104: =0 -> 0
A105: 稀釋股數 | B105: 十億股 | C105: =a25_sh -> 0.1592 | D105: =a26_sh -> 0.1954 | E105: =sh_q4*(1+sh_g) -> 0.204222 | F105: =E105*(1+sh_g) -> 0.20626422 | G105: =F105*(1+sh_g) -> 0.20832686
A106: EPS | B106: US$ | C106: =(C102-C104)/C105 -> 3.53 | D106: =(D102-D104)/D105 -> 5.6120778 | E106: =(E102-E104)/E105 -> 10.774466 | F106: =(F102-F104)/F105 -> 16.3568 | G106: =(G102-G104)/G105 -> 20.794629
A107: EPS 年增 | B107: % | D107: =D106/C106-1 -> 0.58982374 | E107: =E106/D106-1 -> 0.91987102 | F107: =F106/E106-1 -> 0.51810778 | G107: =G106/F106-1 -> 0.27131401
A110: 案例區塊：降價快於模型（情境 A）
A111: 項目 | B111: 單位 | C111: FY2025A | D111: FY2026A（錨點） | E111: FY2027 | F111: FY2028 | G111: FY2029 | H111: 說明
A112: A. 日曆年 AI 光學（本節 D–G 欄＝CY2026–CY2029；D 欄＝CY2026 校準年）
A113: AI 可插拔光模組市場 × 情境顆數係數（日曆年） | B113: US$B | D113: =mpl_26*1 -> 29.753262 | E113: =mpl_27*1*1 -> 54.688309 | F113: =mpl_28*um28_A*1 -> 61.21325 | G113: =mpl_29*um29_A*1 -> 78.80848 | H113: 本節欄位為日曆年
A114: AI CPO 光學市場 × 情境顆數係數（日曆年） | B114: US$B | D114: =mcp_26*1 -> 0.300538 | E114: =mcp_27*1 -> 1.691391 | F114: =mcp_28*um28_A -> 3.22175 | G114: =mcp_29*um29_A -> 5.87368
A115: Coherent 可插拔有效份額（CY2026 校準）＝ CY2026 資料中心 ÷ 可插拔市場 | B115: % | D115: =dc_cy26/D113 -> 0.14633958 | H115: Derived：CY2026 CPO 營收視為 0；含賣給其他模組廠的雷射元件，屬「有效」份額
...

Sheet Sources
A1: 來源（公司原文＝SEC 8-K 新聞稿與 10-K；法說會內容經第三方轉述，待人工複核）
A2: 公司：FY2026 第四季與全年財報新聞稿（8-K Exhibit 99.1；分部營收、non-GAAP 調節、Q1 指引、股數） | B2: https://www.sec.gov/Archives/edgar/data/0000820318/000119312526346860/d128030dex991.htm
A3: 公司：FY2026 10-K（分部定義：工業含 SiC；普通股股數） | B3: https://www.sec.gov/Archives/edgar/data/820318/000082031826000020/iivi-20260630.htm
A4: 二手：10-K 摘要（NVIDIA 投資 20 億美元、A&D 出售約 4 億美元、兩大客戶各逾 10%） | B4: https://www.autobound.ai/companies/coherent/10-k
A5: 二手：Futurum FY2026 Q4（資料中心、通訊季增與年增；磷化銦產能；CPO 時程；FY2027 展望） | B5: https://futurumgroup.com/insights/coherent-q4-fy-2026-earnings-1-6t-transceivers-ramp-cpo-revenue-approaches/
A6: 二手：Webull 法說會摘要（同上；營業費用率；FY2027 訂單） | B6: https://www.webull.com/news/15393555909010432
A7: 二手：Futurum FY2026 Q1、Q2、Q3（資料中心年增、慕尼黑工具出售） | B7: https://futurumgroup.com/insights/coherent-q1-fy-2026-shows-strong-datacenter-comms-momentum；https://futurumgroup.com/insights/coherent-q2-fy-2026-ai-datacenter-demand-lifts-revenue-and-margins；https://futurumgroup.com/insights/coherent-q3-fy-2026-ai-data-center-demand-accelerates-optical-growth/
A8: 媒體：Investing.com（Q1 指引 vs 共識；Barclays 毛利率評論） | B8: https://www.investing.com/news/stock-market-news/coherent-posts-a-blowout-q4-and-aggressive-guidance-yet-shares-take-a-5-haircut-4856014
A9: 共識：MarketBeat（FY2027／FY2028 EPS、股價 10-23、52 週區間） | B9: https://www.marketbeat.com/stocks/NYSE/COHR
A10: 共識：Benzinga（各季 EPS 共識、股價） | B10: https://www.benzinga.com/quote/COHR/earnings-forecasts
A11: 共識：TIKR（FY2027／FY2028 營收共識，2026-09-30） | B11: https://www.tikr.com/blog/coherent-stock-fell-nearly-10-in-a-day-as-rising-yields-hit-optics-stocks-heres-where-the-stock-could-go-by-2031
A12: 研調：LightCounting 2025 光模組廠商排名 | B12: https://lightcounting.com/newsletter/en/may-2026-optical-vendor-landscape-376
A13: 資料商：companiesmarketcap 年底 P/E | B13: https://companiesmarketcap.com/coherent/pe-ratio/
... A16: 公司：FY2027 Q1 財報日期（2026-11-04 盤後） | B16: https://finviz.com/news/402637/coherent-corp-announces-timing-of-fy2027-first-quarter-earnings-release
A17: 市場層：markets/network、tsmc、innolight 成品（本 repo，唯讀）
A18: 待補（人工）：資料中心與通訊金額拆分；光模組營收；SiC 營收與少數股權明細；共識家數與區間；前瞻 P/E 歷史（Bloomberg）；回購 | B18: 未找到
A19: SemiAnalysis | B19: 未使用
